{
  "id": 2163020,
  "type": "Feature",
  "properties": {
    "tgn:hierarchy":[
        "tgn:2163020",
        "tgn:1000001",
        "tgn:7012149",
        "tgn:7029392"
    ],
    "tgn:id":2163020,
    "tgn:name":"Bennett Brook",
    "tgn:placetype":[
        "aat:300008699"
    ]
},
  "bbox": [],
  "geometry": {"coordinates":[-71.05,44.9167],"type":"Point"}
}