{
  "id": 1108307,
  "type": "Feature",
  "properties": {
    "tgn:hierarchy":[
        "tgn:1108307",
        "tgn:7001242",
        "tgn:7016833",
        "tgn:1001418",
        "tgn:7029392"
    ],
    "tgn:id":1108307,
    "tgn:name:en":"Zurq, Al Q\u0101r\u0101t az",
    "tgn:placetype":[
        "aat:300008777"
    ]
},
  "bbox": [],
  "geometry": {"coordinates":[29.934191,28.991142],"type":"Point"}
}