{
  "id": 7582474,
  "type": "Feature",
  "properties": {
    "tgn:hierarchy":[
        "tgn:7582474",
        "tgn:1000004",
        "tgn:7000198",
        "tgn:7016788",
        "tgn:7029392"
    ],
    "tgn:id":7582474,
    "tgn:name:en":"Haripur B\u0101s",
    "tgn:placetype":[
        "aat:300008347"
    ]
},
  "bbox": [],
  "geometry": {"coordinates":[75.523574,28.255022],"type":"Point"}
}