{
  "id": 1012183,
  "type": "Feature",
  "properties": {
    "tgn:hierarchy":[
        "tgn:1012183",
        "tgn:1009227",
        "tgn:1000226",
        "tgn:7018437",
        "tgn:1000006",
        "tgn:7029392"
    ],
    "tgn:id":1012183,
    "tgn:name:en":"Moeraki Point",
    "tgn:placetype":[
        "aat:300386846"
    ]
},
  "bbox": [],
  "geometry": {"coordinates":[170.866667,-45.366667],"type":"Point"}
}