{
  "id": 2735118,
  "type": "Feature",
  "properties": {
    "tgn:hierarchy":[
        "tgn:2735118",
        "tgn:1000001",
        "tgn:7012149",
        "tgn:2001543",
        "tgn:7007709",
        "tgn:7029392"
    ],
    "tgn:id":2735118,
    "tgn:name":"Twentymile Ridge",
    "tgn:placetype":[
        "aat:300266640"
    ]
},
  "bbox": [],
  "geometry": {"coordinates":[-83.8167,35.4667],"type":"Point"}
}