<<<<<<< HEAD
{
  "id": 7484253,
  "type": "Feature",
  "properties": {
    "tgn:hierarchy":[
        "tgn:7484253",
        "tgn:7001004",
        "tgn:1000004",
        "tgn:1000141",
        "tgn:7029392"
    ],
    "tgn:id":7484253,
    "tgn:name":"Jiaobayuan",
    "tgn:placetype":[
        "aat:300008347"
    ]
},
  "bbox": [],
  "geometry": {"coordinates":[120.555,23.0275],"type":"Point"}
}
=======
{"geometry":{"type":"Point","coordinates":[120.555000,23.027500]},"type":"Feature","properties":{"hierarchy":["tgn:7484253","tgn:7001004","tgn:1000004","tgn:1000141","tgn:7029392"],"placetype":["aat:300008347"],"id":7484253,"name:xx":"Jiaobayuan"}}
>>>>>>> 03f74aca74312dbeaf24d7e61306dd6a786dc3d0
