{
  "id": 2347700,
  "type": "Feature",
  "properties": {
    "tgn:hierarchy":[
        "tgn:2347700",
        "tgn:1000001",
        "tgn:7012149",
        "tgn:1003017",
        "tgn:7007710",
        "tgn:7029392"
    ],
    "tgn:id":2347700,
    "tgn:name":"Georges Station",
    "tgn:placetype":[
        "aat:300008347"
    ]
},
  "bbox": [],
  "geometry": {"coordinates":[-79.4833,40.3167],"type":"Point"}
}