<<<<<<< HEAD
{
  "id": 7478689,
  "type": "Feature",
  "properties": {
    "tgn:hierarchy":[
        "tgn:7478689",
        "tgn:1000004",
        "tgn:7489179",
        "tgn:1000141",
        "tgn:7029392"
    ],
    "tgn:id":7478689,
    "tgn:name":"Jiuhao Qiao",
    "tgn:placetype":[
        "aat:300007836"
    ]
},
  "bbox": [],
  "geometry": {"coordinates":[121.8093,24.6699],"type":"Point"}
}
=======
{"geometry":{"type":"Point","coordinates":[121.809300,24.669900]},"type":"Feature","properties":{"hierarchy":["tgn:7478689","tgn:1000004","tgn:7489179","tgn:1000141","tgn:7029392"],"placetype":["aat:300007836"],"id":7478689,"name:xx":"Jiuhao Qiao"}}
>>>>>>> 03f74aca74312dbeaf24d7e61306dd6a786dc3d0
