{
  "id": 2369635,
  "type": "Feature",
  "properties": {
    "tgn:hierarchy":[
        "tgn:2369635",
        "tgn:1000001",
        "tgn:2001410",
        "tgn:7012149",
        "tgn:2562899",
        "tgn:7007526",
        "tgn:7029392"
    ],
    "tgn:id":2369635,
    "tgn:name":"Gunsight",
    "tgn:placetype":[
        "aat:300386851",
        "aat:300008791"
    ]
},
  "bbox": [],
  "geometry": {"coordinates":[-114.3833,36.25],"type":"Point"}
}