{
  "id": 2371397,
  "type": "Feature",
  "properties": {
    "tgn:hierarchy":[
        "tgn:2371397",
        "tgn:1000001",
        "tgn:7012149",
        "tgn:2001297",
        "tgn:7007524",
        "tgn:7029392"
    ],
    "tgn:id":2371397,
    "tgn:name":"Hailstone Spring",
    "tgn:placetype":[
        "aat:300008697"
    ]
},
  "bbox": [],
  "geometry": {"coordinates":[-105.8833,45.2167],"type":"Point"}
}