{
  "id": 2687505,
  "type": "Feature",
  "properties": {
    "tgn:hierarchy":[
        "tgn:2687505",
        "tgn:1000001",
        "tgn:7012149",
        "tgn:1002386",
        "tgn:7007706",
        "tgn:7029392"
    ],
    "tgn:id":2687505,
    "tgn:name":"Spring Lakes",
    "tgn:placetype":[
        "aat:300006191"
    ]
},
  "bbox": [],
  "geometry": {"coordinates":[-82.9333,39.9333],"type":"Point"}
}