{
  "id": 7576964,
  "type": "Feature",
  "properties": {
    "tgn:hierarchy":[
        "tgn:7576964",
        "tgn:1000004",
        "tgn:7000198",
        "tgn:1001894",
        "tgn:7029392"
    ],
    "tgn:id":7576964,
    "tgn:name:en":"Karhaia Khoh",
    "tgn:placetype":[
        "aat:300008347"
    ]
},
  "bbox": [],
  "geometry": {"coordinates":[77.286769,23.632861],"type":"Point"}
}