{
  "id": 7034073,
  "type": "Feature",
  "properties": {
    "tgn:hierarchy":[
        "tgn:7034073",
        "tgn:1003468",
        "tgn:1000003",
        "tgn:7010380",
        "tgn:1000080",
        "tgn:7029392"
    ],
    "tgn:id":7034073,
    "tgn:name":"I Savi",
    "tgn:placetype":[
        "aat:300005433"
    ]
},
  "bbox": [],
  "geometry": {"coordinates":[18.022778,40.496944],"type":"Point"}
}