{
  "id": 7102951,
  "type": "Feature",
  "properties": {
    "tgn:hierarchy":[
        "tgn:7102951",
        "tgn:7003669",
        "tgn:1000003",
        "tgn:7000084",
        "tgn:7029392"
    ],
    "tgn:id":7102951,
    "tgn:name":"Sankt Johann",
    "tgn:placetype":[
        "aat:300008347"
    ]
},
  "bbox": [],
  "geometry": {"coordinates":[10.366667,48.066667],"type":"Point"}
}