{
  "id": 7246020,
  "type": "Feature",
  "properties": {
    "tgn:hierarchy":[
        "tgn:7246020",
        "tgn:7007877",
        "tgn:1000003",
        "tgn:1000063",
        "tgn:4012014",
        "tgn:7029392"
    ],
    "tgn:id":7246020,
    "tgn:name":"Bucquoi",
    "tgn:placetype":[
        "aat:300008347"
    ]
},
  "bbox": [],
  "geometry": {"coordinates":[3.233333,50.666667],"type":"Point"}
}