{
  "id": 2157155,
  "type": "Feature",
  "properties": {
    "tgn:hierarchy":[
        "tgn:2157155",
        "tgn:7002659",
        "tgn:1000001",
        "tgn:7012149",
        "tgn:2000051",
        "tgn:7029392"
    ],
    "tgn:id":2157155,
    "tgn:name":"Beaver Cave",
    "tgn:placetype":[
        "aat:300008746"
    ]
},
  "bbox": [],
  "geometry": {"coordinates":[-86.5833,34.3667],"type":"Point"}
}