<<<<<<< HEAD
{
  "id": 2157155,
  "type": "Feature",
  "properties": {
    "tgn:hierarchy":[
        "tgn:2157155",
        "tgn:7002659",
        "tgn:1000001",
        "tgn:7012149",
        "tgn:2000051",
        "tgn:7029392"
    ],
    "tgn:id":2157155,
    "tgn:name":"Beaver Cave",
    "tgn:placetype":[
        "aat:300008746"
    ]
},
  "bbox": [],
  "geometry": {"coordinates":[-86.5833,34.3667],"type":"Point"}
}
=======
{"geometry":{"type":"Point","coordinates":[-86.583300,34.366700]},"type":"Feature","properties":{"hierarchy":["tgn:2157155","tgn:7002659","tgn:1000001","tgn:7012149","tgn:2000051","tgn:7029392"],"placetype":["aat:300008746"],"id":2157155,"name:xx":"Beaver Cave"}}
>>>>>>> 03f74aca74312dbeaf24d7e61306dd6a786dc3d0
