{
  "id": 7479911,
  "type": "Feature",
  "properties": {
    "tgn:hierarchy":[
        "tgn:7479911",
        "tgn:1000004",
        "tgn:7490934",
        "tgn:1000141",
        "tgn:7029392"
    ],
    "tgn:id":7479911,
    "tgn:name":"Zhenhu Gong",
    "tgn:placetype":[
        "aat:300007595"
    ]
},
  "bbox": [],
  "geometry": {"coordinates":[120.251111,23.125556],"type":"Point"}
}