{
  "id": 7405179,
  "type": "Feature",
  "properties": {
    "tgn:hierarchy":[
        "tgn:7405179",
        "tgn:7005578",
        "tgn:1000001",
        "tgn:7005560",
        "tgn:7029392"
    ],
    "tgn:id":7405179,
    "tgn:name":"Yaxch\u00e9 Akal",
    "tgn:placetype":[
        "aat:300008347"
    ]
},
  "bbox": [],
  "geometry": {"coordinates":[-89.658333,19.825],"type":"Point"}
}