{
  "id": 7398231,
  "type": "Feature",
  "properties": {
    "tgn:hierarchy":[
        "tgn:7398231",
        "tgn:1000001",
        "tgn:1001960",
        "tgn:7005560",
        "tgn:7029392"
    ],
    "tgn:id":7398231,
    "tgn:name":"Malpa\u00eds",
    "tgn:placetype":[
        "aat:300006191"
    ]
},
  "bbox": [],
  "geometry": {"coordinates":[-111.109444,30.838611],"type":"Point"}
}