{
  "id": 7585500,
  "type": "Feature",
  "properties": {
    "tgn:hierarchy":[
        "tgn:7585500",
        "tgn:1000004",
        "tgn:7000198",
        "tgn:7000799",
        "tgn:7029392"
    ],
    "tgn:id":7585500,
    "tgn:name:en":"Adipur",
    "tgn:placetype":[
        "aat:300008347"
    ]
},
  "bbox": [],
  "geometry": {"coordinates":[74.488395,34.303258],"type":"Point"}
}