{
  "id": 7496300,
  "type": "Feature",
  "properties": {
    "tgn:hierarchy":[
        "tgn:7496300",
        "tgn:7001004",
        "tgn:1000004",
        "tgn:1000141",
        "tgn:7029392"
    ],
    "tgn:id":7496300,
    "tgn:name":"Xinkaizhuangwei Qiao",
    "tgn:placetype":[
        "aat:300007836"
    ]
},
  "bbox": [],
  "geometry": {"coordinates":[120.532163,22.943892],"type":"Point"}
}