<<<<<<< HEAD
{
  "id": 7051346,
  "type": "Feature",
  "properties": {
    "tgn:hierarchy":[
        "tgn:7051346",
        "tgn:7009084",
        "tgn:7003001",
        "tgn:1000003",
        "tgn:1000080",
        "tgn:7029392"
    ],
    "tgn:id":7051346,
    "tgn:name":"Laghetta, Monte della",
    "tgn:placetype":[
        "aat:300008795"
    ]
},
  "bbox": [],
  "geometry": {"coordinates":[13.383333,42.6],"type":"Point"}
}
=======
{"geometry":{"type":"Point","coordinates":[13.383333,42.600000]},"type":"Feature","properties":{"hierarchy":["tgn:7051346","tgn:7009084","tgn:7003001","tgn:1000003","tgn:1000080","tgn:7029392"],"placetype":["aat:300008795"],"id":7051346,"name:xx":"Laghetta, Monte della"}}
>>>>>>> 03f74aca74312dbeaf24d7e61306dd6a786dc3d0
