{
  "id": 2127597,
  "type": "Feature",
  "properties": {
    "tgn:hierarchy":[
        "tgn:2127597",
        "tgn:2000256",
        "tgn:1000001",
        "tgn:7012149",
        "tgn:7007240",
        "tgn:7029392"
    ],
    "tgn:id":2127597,
    "tgn:name":"Alachua",
    "tgn:placetype":[
        "aat:300008347"
    ]
},
  "bbox": [],
  "geometry": {"coordinates":[-82.4167,29.75],"type":"Point"}
}