{
  "id": 2299468,
  "type": "Feature",
  "properties": {
    "tgn:hierarchy":[
        "tgn:2299468",
        "tgn:1000001",
        "tgn:7012149",
        "tgn:2000442",
        "tgn:7007248",
        "tgn:7029392"
    ],
    "tgn:id":2299468,
    "tgn:name":"Duck Pond",
    "tgn:placetype":[
        "aat:300008905"
    ]
},
  "bbox": [],
  "geometry": {"coordinates":[-81.9667,31.3833],"type":"Point"}
}