{
  "id": 7526354,
  "type": "Feature",
  "properties": {
    "tgn:hierarchy":[
        "tgn:7526354",
        "tgn:7001242",
        "tgn:7016833",
        "tgn:1001091",
        "tgn:7029392"
    ],
    "tgn:id":7526354,
    "tgn:name":"N\u0101d\u012b as Sikkat al \u1e28ad\u012bd",
    "tgn:placetype":[
        "aat:300004792"
    ]
},
  "bbox": [],
  "geometry": {"coordinates":[31.303622,30.056187],"type":"Point"}
}