<<<<<<< HEAD
{
  "id": 7366152,
  "type": "Feature",
  "properties": {
    "tgn:hierarchy":[
        "tgn:7366152",
        "tgn:1001853",
        "tgn:1000001",
        "tgn:7005560",
        "tgn:7029392"
    ],
    "tgn:id":7366152,
    "tgn:name":"Rancho El Refugio",
    "tgn:placetype":[
        "aat:300000241"
    ]
},
  "bbox": [],
  "geometry": {"coordinates":[-100.716667,28.85],"type":"Point"}
}
=======
{"geometry":{"type":"Point","coordinates":[-100.716667,28.850000]},"type":"Feature","properties":{"hierarchy":["tgn:7366152","tgn:1001853","tgn:1000001","tgn:7005560","tgn:7029392"],"placetype":["aat:300000241"],"id":7366152,"name:xx":"Rancho El Refugio"}}
>>>>>>> 03f74aca74312dbeaf24d7e61306dd6a786dc3d0
