{
  "id": 2053069,
  "type": "Feature",
  "properties": {
    "tgn:hierarchy":[
        "tgn:2053069",
        "tgn:1000001",
        "tgn:7012149",
        "tgn:2000978",
        "tgn:7007520",
        "tgn:7029392"
    ],
    "tgn:id":2053069,
    "tgn:name":"Powers",
    "tgn:placetype":[
        "aat:300008347"
    ]
},
  "bbox": [],
  "geometry": {"coordinates":[-87.5167,45.6833],"type":"Point"}
}