{
  "id": 1071669,
  "type": "Feature",
  "properties": {
    "tgn:hierarchy":[
        "tgn:1071669",
        "tgn:1000004",
        "tgn:7002078",
        "tgn:1000111",
        "tgn:7029392"
    ],
    "tgn:id":1071669,
    "tgn:name":"Shihuajie",
    "tgn:placetype":[
        "aat:300008347"
    ]
},
  "bbox": [],
  "geometry": {"coordinates":[111.3667,32.2833],"type":"Point"}
}