{
  "id": 2037171,
  "type": "Feature",
  "properties": {
    "tgn:hierarchy":[
        "tgn:2037171",
        "tgn:1000001",
        "tgn:2000693",
        "tgn:7012149",
        "tgn:7007254",
        "tgn:7029392"
    ],
    "tgn:id":2037171,
    "tgn:name":"Stano",
    "tgn:placetype":[
        "aat:300387016"
    ]
},
  "bbox": [],
  "geometry": {"coordinates":[-101.4833,37.5167],"type":"Point"}
}