{
  "id": 2339677,
  "type": "Feature",
  "properties": {
    "tgn:hierarchy":[
        "tgn:2339677",
        "tgn:1000001",
        "tgn:7012149",
        "tgn:2001281",
        "tgn:7007524",
        "tgn:7029392"
    ],
    "tgn:id":2339677,
    "tgn:name":"Free Enterprise Mine",
    "tgn:placetype":[
        "aat:300000390"
    ]
},
  "bbox": [],
  "geometry": {"coordinates":[-112.1333,46.25],"type":"Point"}
}