{
  "id": 1085352,
  "type": "Feature",
  "properties": {
    "tgn:hierarchy":[
        "tgn:1085352",
        "tgn:1000004",
        "tgn:7490934",
        "tgn:1000141",
        "tgn:7029392"
    ],
    "tgn:id":1085352,
    "tgn:name":"Nan-hsi",
    "tgn:placetype":[
        "aat:300008347"
    ]
},
  "bbox": [],
  "geometry": {"coordinates":[120.486343,23.177536],"type":"Point"}
}