{
  "id": 2198752,
  "type": "Feature",
  "properties": {
    "tgn:hierarchy":[
        "tgn:2198752",
        "tgn:7006450",
        "tgn:1000001",
        "tgn:7012149",
        "tgn:2000088",
        "tgn:7029392"
    ],
    "tgn:id":2198752,
    "tgn:name":"Brownson Peak",
    "tgn:placetype":[
        "aat:300008798"
    ]
},
  "bbox": [],
  "geometry": {"coordinates":[-132.1667,55.95],"type":"Point"}
}