{
  "id": 7308689,
  "type": "Feature",
  "properties": {
    "tgn:hierarchy":[
        "tgn:7308689",
        "tgn:1001623",
        "tgn:1000049",
        "tgn:1000002",
        "tgn:7029392"
    ],
    "tgn:id":7308689,
    "tgn:name":"Lotten, Isla",
    "tgn:placetype":[
        "aat:300008791"
    ]
},
  "bbox": [],
  "geometry": {"coordinates":[-74.866667,-48.633333],"type":"Point"}
}