{
  "id": 7131983,
  "type": "Feature",
  "properties": {
    "tgn:hierarchy":[
        "tgn:7131983",
        "tgn:7003669",
        "tgn:1000003",
        "tgn:7000084",
        "tgn:7029392"
    ],
    "tgn:id":7131983,
    "tgn:name":"Marienbrunn",
    "tgn:placetype":[
        "aat:300008347"
    ]
},
  "bbox": [],
  "geometry": {"coordinates":[9.578056,49.8625],"type":"Point"}
}