{
  "id": 7133373,
  "type": "Feature",
  "properties": {
    "tgn:hierarchy":[
        "tgn:7133373",
        "tgn:1000003",
        "tgn:7003677",
        "tgn:7000084",
        "tgn:7029392"
    ],
    "tgn:id":7133373,
    "tgn:name":"M\u00fcnster-Aa",
    "tgn:placetype":[
        "aat:300008699"
    ]
},
  "bbox": [],
  "geometry": {"coordinates":[7.483333,51.983333],"type":"Point"}
}