{
  "id": 2606637,
  "type": "Feature",
  "properties": {
    "tgn:hierarchy":[
        "tgn:2606637",
        "tgn:1000001",
        "tgn:7012149",
        "tgn:7007825",
        "tgn:7029392"
    ],
    "tgn:id":2606637,
    "tgn:name":"Ramp Hollow",
    "tgn:placetype":[
        "aat:300008761"
    ]
},
  "bbox": [],
  "geometry": {"coordinates":[-86.1667,35.6667],"type":"Point"}
}