{
  "id": 7411819,
  "type": "Feature",
  "properties": {
    "tgn:hierarchy":[
        "tgn:7411819",
        "tgn:7005587",
        "tgn:1000001",
        "tgn:7005560",
        "tgn:7029392"
    ],
    "tgn:id":7411819,
    "tgn:name:es":"Mesa de Santa Luc\u00eda",
    "tgn:placetype":[
        "aat:300008347"
    ]
},
  "bbox": [],
  "geometry": {"coordinates":[-98.430556,20.940278],"type":"Point"}
}