{
  "id": 2509409,
  "type": "Feature",
  "properties": {
    "tgn:hierarchy":[
        "tgn:2509409",
        "tgn:1000001",
        "tgn:7012149",
        "tgn:7007158",
        "tgn:2000243",
        "tgn:7029392"
    ],
    "tgn:id":2509409,
    "tgn:name":"Middle Fork Soldier Creek",
    "tgn:placetype":[
        "aat:300008706"
    ]
},
  "bbox": [],
  "geometry": {"coordinates":[-108.5833,39.6667],"type":"Point"}
}