{
  "id": 2728009,
  "type": "Feature",
  "properties": {
    "tgn:hierarchy":[
        "tgn:2728009",
        "tgn:1000001",
        "tgn:2000469",
        "tgn:7012149",
        "tgn:7007250",
        "tgn:7029392"
    ],
    "tgn:id":2728009,
    "tgn:name":"Trap Point",
    "tgn:placetype":[
        "aat:300008798"
    ]
},
  "bbox": [],
  "geometry": {"coordinates":[-115.0667,46.8833],"type":"Point"}
}