{
  "id": 2170581,
  "type": "Feature",
  "properties": {
    "tgn:hierarchy":[
        "tgn:2170581",
        "tgn:1000001",
        "tgn:2002256",
        "tgn:7012149",
        "tgn:7013961",
        "tgn:7029392"
    ],
    "tgn:id":2170581,
    "tgn:name":"Big Run",
    "tgn:placetype":[
        "aat:300008699"
    ]
},
  "bbox": [],
  "geometry": {"coordinates":[-80.8333,38.55],"type":"Point"}
}