{
  "id": 7527960,
  "type": "Feature",
  "properties": {
    "tgn:hierarchy":[
        "tgn:7527960",
        "tgn:7001242",
        "tgn:1001075",
        "tgn:7016833",
        "tgn:7029392"
    ],
    "tgn:id":7527960,
    "tgn:name:en":"Zumr\u0101n an Nakhl",
    "tgn:placetype":[
        "aat:300008347"
    ]
},
  "bbox": [],
  "geometry": {"coordinates":[30.559167,30.824722],"type":"Point"}
}