{
  "id": 2311001,
  "type": "Feature",
  "properties": {
    "tgn:hierarchy":[
        "tgn:2311001",
        "tgn:1000001",
        "tgn:7012149",
        "tgn:7007157",
        "tgn:1002956",
        "tgn:7029392"
    ],
    "tgn:id":2311001,
    "tgn:name":"Eden Creek",
    "tgn:placetype":[
        "aat:300008706"
    ]
},
  "bbox": [],
  "geometry": {"coordinates":[-118.7333,36.3833],"type":"Point"}
}