{
  "id": 2671206,
  "type": "Feature",
  "properties": {
    "tgn:hierarchy":[
        "tgn:2671206",
        "tgn:1000001",
        "tgn:7012149",
        "tgn:1002487",
        "tgn:7007252",
        "tgn:7029392"
    ],
    "tgn:id":2671206,
    "tgn:name":"Smith Ditch",
    "tgn:placetype":[
        "aat:300006075"
    ]
},
  "bbox": [],
  "geometry": {"coordinates":[-85.9833,40.4667],"type":"Point"}
}