{
  "id": 7296937,
  "type": "Feature",
  "properties": {
    "tgn:hierarchy":[
        "tgn:7296937",
        "tgn:7002829",
        "tgn:1000003",
        "tgn:7002786",
        "tgn:1000095",
        "tgn:7029392"
    ],
    "tgn:id":7296937,
    "tgn:name":"Trimaz, R\u00edo",
    "tgn:placetype":[
        "aat:300008699"
    ]
},
  "bbox": [],
  "geometry": {"coordinates":[-7.683333,43.283333],"type":"Point"}
}