{
  "id": 7166991,
  "type": "Feature",
  "properties": {
    "tgn:hierarchy":[
        "tgn:7166991",
        "tgn:1000003",
        "tgn:7003682",
        "tgn:7000084",
        "tgn:7029392"
    ],
    "tgn:id":7166991,
    "tgn:name":"Harzofen-Berg",
    "tgn:placetype":[
        "aat:300008795"
    ]
},
  "bbox": [],
  "geometry": {"coordinates":[7.983333,49.266667],"type":"Point"}
}