{
  "id": 2780792,
  "type": "Feature",
  "properties": {
    "tgn:hierarchy":[
        "tgn:2780792",
        "tgn:1000001",
        "tgn:7012149",
        "tgn:7007248",
        "tgn:7029392"
    ],
    "tgn:id":2780792,
    "tgn:name":"Wood Station Valley",
    "tgn:placetype":[
        "aat:300008761"
    ]
},
  "bbox": [],
  "geometry": {"coordinates":[-85.1833,34.75],"type":"Point"}
}