{
  "id": 2542004,
  "type": "Feature",
  "properties": {
    "tgn:hierarchy":[
        "tgn:2542004",
        "tgn:1000001",
        "tgn:2000470",
        "tgn:7012149",
        "tgn:7007250",
        "tgn:7029392"
    ],
    "tgn:id":2542004,
    "tgn:name":"Nip And Tuck Creek",
    "tgn:placetype":[
        "aat:300008706"
    ]
},
  "bbox": [],
  "geometry": {"coordinates":[-114.95,44.2333],"type":"Point"}
}