{
  "id": 2772295,
  "type": "Feature",
  "properties": {
    "tgn:hierarchy":[
        "tgn:2772295",
        "tgn:1000001",
        "tgn:7012149",
        "tgn:2000995",
        "tgn:7007520",
        "tgn:7029392"
    ],
    "tgn:id":2772295,
    "tgn:name":"Willey Drain",
    "tgn:placetype":[
        "aat:300006075"
    ]
},
  "bbox": [],
  "geometry": {"coordinates":[-82.6667,43.1833],"type":"Point"}
}