{
  "id": 2451865,
  "type": "Feature",
  "properties": {
    "tgn:hierarchy":[
        "tgn:2451865",
        "tgn:1000001",
        "tgn:7012149",
        "tgn:2001875",
        "tgn:7007825",
        "tgn:7029392"
    ],
    "tgn:id":2451865,
    "tgn:name":"Little Beaver Creek",
    "tgn:placetype":[
        "aat:300008706"
    ]
},
  "bbox": [],
  "geometry": {"coordinates":[-88.4167,35.7833],"type":"Point"}
}