{
  "id": 2555055,
  "type": "Feature",
  "properties": {
    "tgn:hierarchy":[
        "tgn:2555055",
        "tgn:1000001",
        "tgn:1002271",
        "tgn:7012149",
        "tgn:7007920",
        "tgn:7029392"
    ],
    "tgn:id":2555055,
    "tgn:name":"Observatory Point",
    "tgn:placetype":[
        "aat:300008850"
    ]
},
  "bbox": [],
  "geometry": {"coordinates":[-123.6333,48.15],"type":"Point"}
}