{
  "id": 2461640,
  "type": "Feature",
  "properties": {
    "tgn:hierarchy":[
        "tgn:2461640",
        "tgn:1000001",
        "tgn:7012149",
        "tgn:1002392",
        "tgn:7007157",
        "tgn:7029392"
    ],
    "tgn:id":2461640,
    "tgn:name":"Little Tehipte Valley",
    "tgn:placetype":[
        "aat:300386845"
    ]
},
  "bbox": [],
  "geometry": {"coordinates":[-118.7833,36.8833],"type":"Point"}
}