{
  "id": 7353001,
  "type": "Feature",
  "properties": {
    "tgn:hierarchy":[
        "tgn:7353001",
        "tgn:7005583",
        "tgn:1000001",
        "tgn:7005560",
        "tgn:7029392"
    ],
    "tgn:id":7353001,
    "tgn:name":"Buenavista",
    "tgn:placetype":[
        "aat:300008347"
    ]
},
  "bbox": [],
  "geometry": {"coordinates":[-104.483333,25.133333],"type":"Point"}
}