{
  "id": 2188577,
  "type": "Feature",
  "properties": {
    "tgn:hierarchy":[
        "tgn:2188577",
        "tgn:1000001",
        "tgn:7012149",
        "tgn:7007157",
        "tgn:2000187",
        "tgn:7029392"
    ],
    "tgn:id":2188577,
    "tgn:name":"Bottle Springs",
    "tgn:placetype":[
        "aat:300008697"
    ]
},
  "bbox": [],
  "geometry": {"coordinates":[-120.9833,39.85],"type":"Point"}
}