{
  "id": 7290179,
  "type": "Feature",
  "properties": {
    "tgn:hierarchy":[
        "tgn:7290179",
        "tgn:1001702",
        "tgn:1000049",
        "tgn:1000002",
        "tgn:7029392"
    ],
    "tgn:id":7290179,
    "tgn:name":"Seno Duntze",
    "tgn:placetype":[
        "aat:300006495"
    ]
},
  "bbox": [],
  "geometry": {"coordinates":[-71.766667,-54.316667],"type":"Point"}
}