{
  "id": 2362873,
  "type": "Feature",
  "properties": {
    "tgn:hierarchy":[
        "tgn:2362873",
        "tgn:1000001",
        "tgn:2000922",
        "tgn:7012149",
        "tgn:7007515",
        "tgn:7029392"
    ],
    "tgn:id":2362873,
    "tgn:name":"Great Pond",
    "tgn:placetype":[
        "aat:300006191"
    ]
},
  "bbox": [],
  "geometry": {"coordinates":[-68.2833,44.9333],"type":"Point"}
}