{
  "id": 2065453,
  "type": "Feature",
  "properties": {
    "tgn:hierarchy":[
        "tgn:2065453",
        "tgn:1002157",
        "tgn:1000001",
        "tgn:7012149",
        "tgn:7007565",
        "tgn:7029392"
    ],
    "tgn:id":2065453,
    "tgn:name":"Milmay",
    "tgn:placetype":[
        "aat:300008347"
    ]
},
  "bbox": [],
  "geometry": {"coordinates":[-74.85,39.4333],"type":"Point"}
}