{
  "id": 2452499,
  "type": "Feature",
  "properties": {
    "tgn:hierarchy":[
        "tgn:2452499",
        "tgn:1000001",
        "tgn:7012149",
        "tgn:2000412",
        "tgn:7007248",
        "tgn:7029392"
    ],
    "tgn:id":2452499,
    "tgn:name":"Little Brierpatch Lake",
    "tgn:placetype":[
        "aat:300008680"
    ]
},
  "bbox": [],
  "geometry": {"coordinates":[-81.8667,33.2833],"type":"Point"}
}