{
  "id": 7443083,
  "type": "Feature",
  "properties": {
    "tgn:hierarchy":[
        "tgn:7443083",
        "tgn:7002445",
        "tgn:7008116",
        "tgn:1000003",
        "tgn:7008591",
        "tgn:7029392"
    ],
    "tgn:id":7443083,
    "tgn:name:en":"South Stone",
    "tgn:placetype":[
        "aat:300011692"
    ]
},
  "bbox": [],
  "geometry": {"coordinates":[-6.116667,50.048611],"type":"Point"}
}