{
  "id": 7586349,
  "type": "Feature",
  "properties": {
    "tgn:hierarchy":[
        "tgn:7586349",
        "tgn:1000004",
        "tgn:7000198",
        "tgn:7000799",
        "tgn:7029392"
    ],
    "tgn:id":7586349,
    "tgn:name:en":"Kanzdor",
    "tgn:placetype":[
        "aat:300008347"
    ]
},
  "bbox": [],
  "geometry": {"coordinates":[74.767763,34.355895],"type":"Point"}
}