{
  "id": 2436302,
  "type": "Feature",
  "properties": {
    "tgn:hierarchy":[
        "tgn:2436302",
        "tgn:1000001",
        "tgn:7012149",
        "tgn:2001713",
        "tgn:7007708",
        "tgn:7029392"
    ],
    "tgn:id":2436302,
    "tgn:name":"Khoeery Creek",
    "tgn:placetype":[
        "aat:300008706"
    ]
},
  "bbox": [],
  "geometry": {"coordinates":[-123.5833,42.0333],"type":"Point"}
}