{
  "id": 7591904,
  "type": "Feature",
  "properties": {
    "tgn:hierarchy":[
        "tgn:7591904",
        "tgn:1000004",
        "tgn:7000198",
        "tgn:7000799",
        "tgn:7029392"
    ],
    "tgn:id":7591904,
    "tgn:name:en":"Par\u0101ti",
    "tgn:placetype":[
        "aat:300008347"
    ]
},
  "bbox": [],
  "geometry": {"coordinates":[74.236824,33.163426],"type":"Point"}
}