<<<<<<< HEAD
{
  "id": 7173488,
  "type": "Feature",
  "properties": {
    "tgn:hierarchy":[
        "tgn:7173488",
        "tgn:1000003",
        "tgn:7003676",
        "tgn:7000084",
        "tgn:7029392"
    ],
    "tgn:id":7173488,
    "tgn:name":"Gro\u00dfer Schmalen-Berg",
    "tgn:placetype":[
        "aat:300008777"
    ]
},
  "bbox": [],
  "geometry": {"coordinates":[10.183333,51.816667],"type":"Point"}
}
=======
{"geometry":{"type":"Point","coordinates":[10.183333,51.816667]},"type":"Feature","properties":{"hierarchy":["tgn:7173488","tgn:1000003","tgn:7003676","tgn:7000084","tgn:7029392"],"placetype":["aat:300008777"],"id":7173488,"name:xx":"Gro\u00dfer Schmalen-Berg"}}
>>>>>>> 03f74aca74312dbeaf24d7e61306dd6a786dc3d0
