{
  "id": 7508124,
  "type": "Feature",
  "properties": {
    "tgn:hierarchy":[
        "tgn:7508124",
        "tgn:7000508",
        "tgn:1008380",
        "tgn:1000226",
        "tgn:1000006",
        "tgn:7029392"
    ],
    "tgn:id":7508124,
    "tgn:name:en":"Parau",
    "tgn:placetype":[
        "aat:300008347"
    ]
},
  "bbox": [],
  "geometry": {"coordinates":[174.616667,-36.966667],"type":"Point"}
}