{
  "id": 1029996,
  "type": "Feature",
  "properties": {
    "tgn:hierarchy":[
        "tgn:1029996",
        "tgn:7002445",
        "tgn:1000003",
        "tgn:7012032",
        "tgn:7008591",
        "tgn:7029392"
    ],
    "tgn:id":1029996,
    "tgn:name:en":"Martock",
    "tgn:placetype":[
        "aat:300008347"
    ]
},
  "bbox": [],
  "geometry": {"coordinates":[-2.75,50.966667],"type":"Point"}
}