{
  "id": 7435249,
  "type": "Feature",
  "properties": {
    "tgn:hierarchy":[
        "tgn:7435249",
        "tgn:7005581",
        "tgn:1000001",
        "tgn:7005560",
        "tgn:7029392"
    ],
    "tgn:id":7435249,
    "tgn:name":"Tortugas",
    "tgn:placetype":[
        "aat:300008347"
    ]
},
  "bbox": [],
  "geometry": {"coordinates":[-107.166667,28.366667],"type":"Point"}
}