{
  "id": 7342993,
  "type": "Feature",
  "properties": {
    "tgn:hierarchy":[
        "tgn:7342993",
        "tgn:1001439",
        "tgn:1000003",
        "tgn:7002797",
        "tgn:1000095",
        "tgn:7029392"
    ],
    "tgn:id":7342993,
    "tgn:name":"Caser\u00edo Los Fuentes de los Solanos",
    "tgn:placetype":[
        "aat:300008347"
    ]
},
  "bbox": [],
  "geometry": {"coordinates":[-1.166667,37.616667],"type":"Point"}
}