{
  "id": 2139647,
  "type": "Feature",
  "properties": {
    "tgn:hierarchy":[
        "tgn:2139647",
        "tgn:1000001",
        "tgn:7012149",
        "tgn:2000903",
        "tgn:7007256",
        "tgn:7029392"
    ],
    "tgn:id":2139647,
    "tgn:name":"Atchafalaya",
    "tgn:placetype":[
        "aat:300008347"
    ]
},
  "bbox": [],
  "geometry": {"coordinates":[-91.7167,30.3333],"type":"Point"}
}