{
  "id": 7115924,
  "type": "Feature",
  "properties": {
    "tgn:hierarchy":[
        "tgn:7115924",
        "tgn:1000003",
        "tgn:7003676",
        "tgn:7000084",
        "tgn:7029392"
    ],
    "tgn:id":7115924,
    "tgn:name":"Ovelg\u00f6nnermoor",
    "tgn:placetype":[
        "aat:300000206"
    ]
},
  "bbox": [],
  "geometry": {"coordinates":[9.75,53.483333],"type":"Point"}
}