{
  "id": 2576398,
  "type": "Feature",
  "properties": {
    "tgn:hierarchy":[
        "tgn:2576398",
        "tgn:1000001",
        "tgn:7012149",
        "tgn:2000839",
        "tgn:7007255",
        "tgn:7029392"
    ],
    "tgn:id":2576398,
    "tgn:name":"Perry Knob",
    "tgn:placetype":[
        "aat:300008798"
    ]
},
  "bbox": [],
  "geometry": {"coordinates":[-84.5667,37.05],"type":"Point"}
}