{
  "id": 7493824,
  "type": "Feature",
  "properties": {
    "tgn:hierarchy":[
        "tgn:7493824",
        "tgn:1000004",
        "tgn:1000454",
        "tgn:1000141",
        "tgn:7029392"
    ],
    "tgn:id":7493824,
    "tgn:name":"Zongchuan Jian",
    "tgn:placetype":[
        "aat:300008798"
    ]
},
  "bbox": [],
  "geometry": {"coordinates":[121.48843,24.911744],"type":"Point"}
}