<<<<<<< HEAD
{
  "id": 7023448,
  "type": "Feature",
  "properties": {
    "tgn:hierarchy":[
        "tgn:7023448",
        "tgn:1000001",
        "tgn:7012149",
        "tgn:7007255",
        "tgn:7029392"
    ],
    "tgn:id":7023448,
    "tgn:name":"Spears Creek",
    "tgn:placetype":[
        "aat:300008706"
    ]
},
  "bbox": [],
  "geometry": {"coordinates":[-84.8,37.65],"type":"Point"}
}
=======
{"geometry":{"type":"Point","coordinates":[-84.800000,37.650000]},"type":"Feature","properties":{"hierarchy":["tgn:7023448","tgn:1000001","tgn:7012149","tgn:7007255","tgn:7029392"],"placetype":["aat:300008706"],"id":7023448,"name:xx":"Spears Creek"}}
>>>>>>> 03f74aca74312dbeaf24d7e61306dd6a786dc3d0
