{
  "id": 7434259,
  "type": "Feature",
  "properties": {
    "tgn:hierarchy":[
        "tgn:7434259",
        "tgn:1000001",
        "tgn:1001893",
        "tgn:7005560",
        "tgn:7029392"
    ],
    "tgn:id":7434259,
    "tgn:name":"Xochitenco",
    "tgn:placetype":[
        "aat:300008347"
    ]
},
  "bbox": [],
  "geometry": {"coordinates":[-98.95,19.416667],"type":"Point"}
}