{
  "id": 7383629,
  "type": "Feature",
  "properties": {
    "tgn:hierarchy":[
        "tgn:7383629",
        "tgn:7005583",
        "tgn:1000001",
        "tgn:7005560",
        "tgn:7029392"
    ],
    "tgn:id":7383629,
    "tgn:name":"Otatitl\u00e1n",
    "tgn:placetype":[
        "aat:300008347"
    ]
},
  "bbox": [],
  "geometry": {"coordinates":[-106.638611,24.6725],"type":"Point"}
}