{
  "id": 2578565,
  "type": "Feature",
  "properties": {
    "tgn:hierarchy":[
        "tgn:2578565",
        "tgn:1000001",
        "tgn:1002724",
        "tgn:7012149",
        "tgn:7007517",
        "tgn:7029392"
    ],
    "tgn:id":2578565,
    "tgn:name":"Philip Head",
    "tgn:placetype":[
        "aat:300008850"
    ]
},
  "bbox": [],
  "geometry": {"coordinates":[-70.9667,42.25],"type":"Point"}
}