{
  "id": 1027179,
  "type": "Feature",
  "properties": {
    "tgn:hierarchy":[
        "tgn:1027179",
        "tgn:7593920",
        "tgn:1000003",
        "tgn:1001780",
        "tgn:7029392"
    ],
    "tgn:id":1027179,
    "tgn:name":"H\u0159ensko",
    "tgn:placetype":[
        "aat:300008347"
    ]
},
  "bbox": [],
  "geometry": {"coordinates":[14.2333,50.8667],"type":"Point"}
}