{
  "id": 7316153,
  "type": "Feature",
  "properties": {
    "tgn:hierarchy":[
        "tgn:7316153",
        "tgn:1001699",
        "tgn:1000049",
        "tgn:1000002",
        "tgn:7029392"
    ],
    "tgn:id":7316153,
    "tgn:name":"Caucahu\u00e9, Canal",
    "tgn:placetype":[
        "aat:300387026"
    ]
},
  "bbox": [],
  "geometry": {"coordinates":[-73.446667,-42.126944],"type":"Point"}
}