{
  "id": 7412534,
  "type": "Feature",
  "properties": {
    "tgn:hierarchy":[
        "tgn:7412534",
        "tgn:7005587",
        "tgn:1000001",
        "tgn:7005560",
        "tgn:7029392"
    ],
    "tgn:id":7412534,
    "tgn:name:es":"El Capul\u00edn",
    "tgn:placetype":[
        "aat:300008347"
    ]
},
  "bbox": [],
  "geometry": {"coordinates":[-98.980556,21.001389],"type":"Point"}
}