{
  "id": 7149951,
  "type": "Feature",
  "properties": {
    "tgn:hierarchy":[
        "tgn:7149951",
        "tgn:7003692",
        "tgn:1000003",
        "tgn:7000084",
        "tgn:7029392"
    ],
    "tgn:id":7149951,
    "tgn:name":"Laimbach",
    "tgn:placetype":[
        "aat:300008347"
    ]
},
  "bbox": [],
  "geometry": {"coordinates":[9.683333,47.983333],"type":"Point"}
}