{
  "id": 7252133,
  "type": "Feature",
  "properties": {
    "tgn:hierarchy":[
        "tgn:7252133",
        "tgn:7003457",
        "tgn:1000003",
        "tgn:1000063",
        "tgn:7018236",
        "tgn:7029392"
    ],
    "tgn:id":7252133,
    "tgn:name":"Mere",
    "tgn:placetype":[
        "aat:300008347"
    ]
},
  "bbox": [],
  "geometry": {"coordinates":[3.986627,50.924172],"type":"Point"}
}