<<<<<<< HEAD
{
  "id": 2335596,
  "type": "Feature",
  "properties": {
    "tgn:hierarchy":[
        "tgn:2335596",
        "tgn:1000001",
        "tgn:7012149",
        "tgn:2000435",
        "tgn:7007248",
        "tgn:7029392"
    ],
    "tgn:id":2335596,
    "tgn:name":"Fortenberry Creek",
    "tgn:placetype":[
        "aat:300008706"
    ]
},
  "bbox": [],
  "geometry": {"coordinates":[-83.95,34.7833],"type":"Point"}
}
=======
{"geometry":{"type":"Point","coordinates":[-83.950000,34.783300]},"type":"Feature","properties":{"hierarchy":["tgn:2335596","tgn:1000001","tgn:7012149","tgn:2000435","tgn:7007248","tgn:7029392"],"placetype":["aat:300008706"],"id":2335596,"name:xx":"Fortenberry Creek"}}
>>>>>>> 03f74aca74312dbeaf24d7e61306dd6a786dc3d0
