{
  "id": 7191627,
  "type": "Feature",
  "properties": {
    "tgn:hierarchy":[
        "tgn:7191627",
        "tgn:1000003",
        "tgn:7003676",
        "tgn:7000084",
        "tgn:7029392"
    ],
    "tgn:id":7191627,
    "tgn:name":"Filsumer Moor",
    "tgn:placetype":[
        "aat:300008903"
    ]
},
  "bbox": [],
  "geometry": {"coordinates":[7.666667,53.266667],"type":"Point"}
}