{
  "id": 7435419,
  "type": "Feature",
  "properties": {
    "tgn:hierarchy":[
        "tgn:7435419",
        "tgn:1000001",
        "tgn:7005591",
        "tgn:7005560",
        "tgn:7029392"
    ],
    "tgn:id":7435419,
    "tgn:name":"Valerio Mart\u00ednez",
    "tgn:placetype":[
        "aat:300008347"
    ]
},
  "bbox": [],
  "geometry": {"coordinates":[-96.033333,15.783333],"type":"Point"}
}