{
  "id": 2224986,
  "type": "Feature",
  "properties": {
    "tgn:hierarchy":[
        "tgn:2224986",
        "tgn:1002338",
        "tgn:1000001",
        "tgn:7012149",
        "tgn:7007516",
        "tgn:7029392"
    ],
    "tgn:id":2224986,
    "tgn:name":"Casson Point",
    "tgn:placetype":[
        "aat:300008850"
    ]
},
  "bbox": [],
  "geometry": {"coordinates":[-76.2333,38.5333],"type":"Point"}
}