<<<<<<< HEAD
{
  "id": 7179045,
  "type": "Feature",
  "properties": {
    "tgn:hierarchy":[
        "tgn:7179045",
        "tgn:1000003",
        "tgn:7003676",
        "tgn:7000084",
        "tgn:7029392"
    ],
    "tgn:id":7179045,
    "tgn:name":"Gudehausen",
    "tgn:placetype":[
        "aat:300008347"
    ]
},
  "bbox": [],
  "geometry": {"coordinates":[9.883333,52.75],"type":"Point"}
}
=======
{"geometry":{"type":"Point","coordinates":[9.883333,52.750000]},"type":"Feature","properties":{"hierarchy":["tgn:7179045","tgn:1000003","tgn:7003676","tgn:7000084","tgn:7029392"],"placetype":["aat:300008347"],"id":7179045,"name:xx":"Gudehausen"}}
>>>>>>> 03f74aca74312dbeaf24d7e61306dd6a786dc3d0
