{
  "id": 2262480,
  "type": "Feature",
  "properties": {
    "tgn:hierarchy":[
        "tgn:2262480",
        "tgn:1000001",
        "tgn:7012149",
        "tgn:2000386",
        "tgn:7007248",
        "tgn:7029392"
    ],
    "tgn:id":2262480,
    "tgn:name":"Cow Island",
    "tgn:placetype":[
        "aat:300008791"
    ]
},
  "bbox": [],
  "geometry": {"coordinates":[-81.3833,31.35],"type":"Point"}
}