{
  "id": 7250491,
  "type": "Feature",
  "properties": {
    "tgn:hierarchy":[
        "tgn:7250491",
        "tgn:7003456",
        "tgn:1000003",
        "tgn:1000063",
        "tgn:7018236",
        "tgn:7029392"
    ],
    "tgn:id":7250491,
    "tgn:name":"Pullaar",
    "tgn:placetype":[
        "aat:300008347"
    ]
},
  "bbox": [],
  "geometry": {"coordinates":[4.516667,51.116667],"type":"Point"}
}