{
  "id": 7515424,
  "type": "Feature",
  "properties": {
    "tgn:hierarchy":[
        "tgn:7515424",
        "tgn:1009227",
        "tgn:7001866",
        "tgn:1000226",
        "tgn:1000006",
        "tgn:7029392"
    ],
    "tgn:id":7515424,
    "tgn:name:en":"Cass River",
    "tgn:placetype":[
        "aat:300008699"
    ]
},
  "bbox": [],
  "geometry": {"coordinates":[170.466667,-43.866667],"type":"Point"}
}