{
  "id": 2263140,
  "type": "Feature",
  "properties": {
    "tgn:hierarchy":[
        "tgn:2263140",
        "tgn:1000001",
        "tgn:7012149",
        "tgn:2001506",
        "tgn:7007709",
        "tgn:7029392"
    ],
    "tgn:id":2263140,
    "tgn:name":"Cowpen Point",
    "tgn:placetype":[
        "aat:300008850"
    ]
},
  "bbox": [],
  "geometry": {"coordinates":[-76.3333,35.3833],"type":"Point"}
}