{
  "id": 2700768,
  "type": "Feature",
  "properties": {
    "tgn:hierarchy":[
        "tgn:2700768",
        "tgn:1000001",
        "tgn:7012149",
        "tgn:2000846",
        "tgn:7007255",
        "tgn:7029392"
    ],
    "tgn:id":2700768,
    "tgn:name":"Sugar Bay",
    "tgn:placetype":[
        "aat:300132316"
    ]
},
  "bbox": [],
  "geometry": {"coordinates":[-88.1333,36.85],"type":"Point"}
}