{
  "id": 2523236,
  "type": "Feature",
  "properties": {
    "tgn:hierarchy":[
        "tgn:2523236",
        "tgn:7002659",
        "tgn:1000001",
        "tgn:7012149",
        "tgn:2000049",
        "tgn:7029392"
    ],
    "tgn:id":2523236,
    "tgn:name":"Moores Pond",
    "tgn:placetype":[
        "aat:300008680"
    ]
},
  "bbox": [],
  "geometry": {"coordinates":[-87.4833,31.45],"type":"Point"}
}