{
  "id": 2252855,
  "type": "Feature",
  "properties": {
    "tgn:hierarchy":[
        "tgn:2252855",
        "tgn:1000001",
        "tgn:7012149",
        "tgn:7007709",
        "tgn:7029392"
    ],
    "tgn:id":2252855,
    "tgn:name":"Conoho Creek",
    "tgn:placetype":[
        "aat:300008706"
    ]
},
  "bbox": [],
  "geometry": {"coordinates":[-77.3333,36.0667],"type":"Point"}
}