<<<<<<< HEAD
{
  "id": 2252855,
  "type": "Feature",
  "properties": {
    "tgn:hierarchy":[
        "tgn:2252855",
        "tgn:1000001",
        "tgn:7012149",
        "tgn:7007709",
        "tgn:7029392"
    ],
    "tgn:id":2252855,
    "tgn:name":"Conoho Creek",
    "tgn:placetype":[
        "aat:300008706"
    ]
},
  "bbox": [],
  "geometry": {"coordinates":[-77.3333,36.0667],"type":"Point"}
}
=======
{"geometry":{"type":"Point","coordinates":[-77.333300,36.066700]},"type":"Feature","properties":{"hierarchy":["tgn:2252855","tgn:1000001","tgn:7012149","tgn:7007709","tgn:7029392"],"placetype":["aat:300008706"],"id":2252855,"name:xx":"Conoho Creek"}}
>>>>>>> 03f74aca74312dbeaf24d7e61306dd6a786dc3d0
