{
  "id": 2692737,
  "type": "Feature",
  "properties": {
    "tgn:hierarchy":[
        "tgn:2692737",
        "tgn:1000001",
        "tgn:7012149",
        "tgn:2002018",
        "tgn:7007826",
        "tgn:7029392"
    ],
    "tgn:id":2692737,
    "tgn:name":"Steel Creek",
    "tgn:placetype":[
        "aat:300008706"
    ]
},
  "bbox": [],
  "geometry": {"coordinates":[-99.0167,29.9833],"type":"Point"}
}