{
  "id": 7561230,
  "type": "Feature",
  "properties": {
    "tgn:hierarchy":[
        "tgn:7561230",
        "tgn:1000004",
        "tgn:7000198",
        "tgn:7016722",
        "tgn:7029392"
    ],
    "tgn:id":7561230,
    "tgn:name:en":"Jasa Purwa",
    "tgn:placetype":[
        "aat:300008347"
    ]
},
  "bbox": [],
  "geometry": {"coordinates":[79.7564,27.239],"type":"Point"}
}