{
  "id": 1108861,
  "type": "Feature",
  "properties": {
    "tgn:hierarchy":[
        "tgn:1108861",
        "tgn:1000002",
        "tgn:1000056",
        "tgn:7029392"
    ],
    "tgn:id":1108861,
    "tgn:name":"Carabaya, Cordillera de",
    "tgn:placetype":[
        "aat:300386831"
    ]
},
  "bbox": [],
  "geometry": {"coordinates":[-70.75,-13.8333],"type":"Point"}
}