<<<<<<< HEAD
{
  "id": 2254249,
  "type": "Feature",
  "properties": {
    "tgn:hierarchy":[
        "tgn:2254249",
        "tgn:1000001",
        "tgn:7012149",
        "tgn:2002047",
        "tgn:7007826",
        "tgn:7029392"
    ],
    "tgn:id":2254249,
    "tgn:name":"Coon Branch",
    "tgn:placetype":[
        "aat:300008699"
    ]
},
  "bbox": [],
  "geometry": {"coordinates":[-93.65,30.7],"type":"Point"}
}
=======
{"geometry":{"type":"Point","coordinates":[-93.650000,30.700000]},"type":"Feature","properties":{"hierarchy":["tgn:2254249","tgn:1000001","tgn:7012149","tgn:2002047","tgn:7007826","tgn:7029392"],"placetype":["aat:300008699"],"id":2254249,"name:xx":"Coon Branch"}}
>>>>>>> 03f74aca74312dbeaf24d7e61306dd6a786dc3d0
