{
  "id": 2772659,
  "type": "Feature",
  "properties": {
    "tgn:hierarchy":[
        "tgn:2772659",
        "tgn:1002175",
        "tgn:1000001",
        "tgn:7012149",
        "tgn:7007706",
        "tgn:7029392"
    ],
    "tgn:id":2772659,
    "tgn:name":"Williams Creek",
    "tgn:placetype":[
        "aat:300008706"
    ]
},
  "bbox": [],
  "geometry": {"coordinates":[-80.9833,39.9833],"type":"Point"}
}