{
  "id": 2466841,
  "type": "Feature",
  "properties": {
    "tgn:hierarchy":[
        "tgn:2466841",
        "tgn:1000001",
        "tgn:7012149",
        "tgn:2001622",
        "tgn:7007706",
        "tgn:7029392"
    ],
    "tgn:id":2466841,
    "tgn:name":"Long Brook",
    "tgn:placetype":[
        "aat:300008699"
    ]
},
  "bbox": [],
  "geometry": {"coordinates":[-81.6667,39.3167],"type":"Point"}
}