{
  "id": 1062786,
  "type": "Feature",
  "properties": {
    "tgn:hierarchy":[
        "tgn:1062786",
        "tgn:1000003",
        "tgn:7003781",
        "tgn:1000097",
        "tgn:7029392"
    ],
    "tgn:id":1062786,
    "tgn:name":"Asp\u00f6",
    "tgn:placetype":[
        "aat:300008347"
    ]
},
  "bbox": [],
  "geometry": {"coordinates":[17.0333,59.4833],"type":"Point"}
}