{
  "id": 7318277,
  "type": "Feature",
  "properties": {
    "tgn:hierarchy":[
        "tgn:7318277",
        "tgn:1001699",
        "tgn:1000049",
        "tgn:1000002",
        "tgn:7029392"
    ],
    "tgn:id":7318277,
    "tgn:name":"Isla Chaull\u00edn",
    "tgn:placetype":[
        "aat:300008791"
    ]
},
  "bbox": [],
  "geometry": {"coordinates":[-73.446667,-43.066667],"type":"Point"}
}