{
  "id": 7567205,
  "type": "Feature",
  "properties": {
    "tgn:hierarchy":[
        "tgn:7567205",
        "tgn:1000004",
        "tgn:7000198",
        "tgn:7031786",
        "tgn:7029392"
    ],
    "tgn:id":7567205,
    "tgn:name:en":"Bebdi",
    "tgn:placetype":[
        "aat:300008347"
    ]
},
  "bbox": [],
  "geometry": {"coordinates":[78.724901,29.834638],"type":"Point"}
}