{
  "id": 2147681,
  "type": "Feature",
  "properties": {
    "tgn:hierarchy":[
        "tgn:2147681",
        "tgn:1000001",
        "tgn:7012149",
        "tgn:1002214",
        "tgn:7007826",
        "tgn:7029392"
    ],
    "tgn:id":2147681,
    "tgn:name":"Bare Branch",
    "tgn:placetype":[
        "aat:300008699"
    ]
},
  "bbox": [],
  "geometry": {"coordinates":[-96.4667,30.4167],"type":"Point"}
}