<<<<<<< HEAD
{
  "id": 7115938,
  "type": "Feature",
  "properties": {
    "tgn:hierarchy":[
        "tgn:7115938",
        "tgn:1000003",
        "tgn:7003676",
        "tgn:7000084",
        "tgn:7029392"
    ],
    "tgn:id":7115938,
    "tgn:name":"Ostenholzer Moor",
    "tgn:placetype":[
        "aat:300386886"
    ]
},
  "bbox": [],
  "geometry": {"coordinates":[9.75,52.733333],"type":"Point"}
}
=======
{"geometry":{"type":"Point","coordinates":[9.750000,52.733333]},"type":"Feature","properties":{"hierarchy":["tgn:7115938","tgn:1000003","tgn:7003676","tgn:7000084","tgn:7029392"],"placetype":["aat:300386886"],"id":7115938,"name:xx":"Ostenholzer Moor"}}
>>>>>>> 03f74aca74312dbeaf24d7e61306dd6a786dc3d0
