{
  "id": 1025875,
  "type": "Feature",
  "properties": {
    "tgn:hierarchy":[
        "tgn:1025875",
        "tgn:7003029",
        "tgn:1000003",
        "tgn:1000062",
        "tgn:7029392"
    ],
    "tgn:id":1025875,
    "tgn:name":"Nesselw\u00e4ngle",
    "tgn:placetype":[
        "aat:300008347"
    ]
},
  "bbox": [],
  "geometry": {"coordinates":[10.6167,47.4833],"type":"Point"}
}