{
  "id": 1069316,
  "type": "Feature",
  "properties": {
    "tgn:hierarchy":[
        "tgn:1069316",
        "tgn:1000004",
        "tgn:7001796",
        "tgn:1000111",
        "tgn:7029392"
    ],
    "tgn:id":1069316,
    "tgn:name":"Jingning",
    "tgn:placetype":[
        "aat:300008347"
    ]
},
  "bbox": [],
  "geometry": {"coordinates":[119.6333,27.9833],"type":"Point"}
}