{
  "id": 2717083,
  "type": "Feature",
  "properties": {
    "tgn:hierarchy":[
        "tgn:2717083",
        "tgn:1000001",
        "tgn:7012149",
        "tgn:7014600",
        "tgn:7007568",
        "tgn:7029392"
    ],
    "tgn:id":2717083,
    "tgn:name":"Third Creek",
    "tgn:placetype":[
        "aat:300008706"
    ]
},
  "bbox": [],
  "geometry": {"coordinates":[-76.95,43.1667],"type":"Point"}
}