{
  "id": 7541865,
  "type": "Feature",
  "properties": {
    "tgn:hierarchy":[
        "tgn:7541865",
        "tgn:7001242",
        "tgn:7016833",
        "tgn:7000123",
        "tgn:7029392"
    ],
    "tgn:id":7541865,
    "tgn:name:en":"Naj' ash Sha'\u012bn\u012byah",
    "tgn:placetype":[
        "aat:300008347"
    ]
},
  "bbox": [],
  "geometry": {"coordinates":[32.328304,26.087021],"type":"Point"}
}