<<<<<<< HEAD
{
  "id": 2709884,
  "type": "Feature",
  "properties": {
    "tgn:hierarchy":[
        "tgn:2709884",
        "tgn:1000001",
        "tgn:2002319",
        "tgn:7012149",
        "tgn:7007922",
        "tgn:7029392"
    ],
    "tgn:id":2709884,
    "tgn:name":"Tainter Lake",
    "tgn:placetype":[
        "aat:300006191"
    ]
},
  "bbox": [],
  "geometry": {"coordinates":[-91.8833,44.9333],"type":"Point"}
}
=======
{"geometry":{"type":"Point","coordinates":[-91.883300,44.933300]},"type":"Feature","properties":{"hierarchy":["tgn:2709884","tgn:1000001","tgn:2002319","tgn:7012149","tgn:7007922","tgn:7029392"],"placetype":["aat:300006191"],"id":2709884,"name:xx":"Tainter Lake"}}
>>>>>>> 03f74aca74312dbeaf24d7e61306dd6a786dc3d0
