{
  "id": 7325336,
  "type": "Feature",
  "properties": {
    "tgn:hierarchy":[
        "tgn:7325336",
        "tgn:7002808",
        "tgn:7030216",
        "tgn:1000003",
        "tgn:1000095",
        "tgn:7029392"
    ],
    "tgn:id":7325336,
    "tgn:name":"Sant Sadurn\u00ed d'Anoia",
    "tgn:placetype":[
        "aat:300008347"
    ]
},
  "bbox": [],
  "geometry": {"coordinates":[1.783333,41.416667],"type":"Point"}
}