{
  "id": 2207813,
  "type": "Feature",
  "properties": {
    "tgn:hierarchy":[
        "tgn:2207813",
        "tgn:1000001",
        "tgn:7012149",
        "tgn:2002179",
        "tgn:7007919",
        "tgn:7029392"
    ],
    "tgn:id":2207813,
    "tgn:name":"Burges Branch",
    "tgn:placetype":[
        "aat:300008699"
    ]
},
  "bbox": [],
  "geometry": {"coordinates":[-80.3833,36.6167],"type":"Point"}
}