{
  "id": 7542898,
  "type": "Feature",
  "properties": {
    "tgn:hierarchy":[
        "tgn:7542898",
        "tgn:7001242",
        "tgn:7016833",
        "tgn:1001113",
        "tgn:7029392"
    ],
    "tgn:id":7542898,
    "tgn:name":"\u015eaf\u0163 al \u1e28innah",
    "tgn:placetype":[
        "aat:300008347"
    ]
},
  "bbox": [],
  "geometry": {"coordinates":[31.610226,30.554881],"type":"Point"}
}