{
  "id": 2686752,
  "type": "Feature",
  "properties": {
    "tgn:hierarchy":[
        "tgn:2686752",
        "tgn:1000001",
        "tgn:7012149",
        "tgn:1002982",
        "tgn:7007922",
        "tgn:7029392"
    ],
    "tgn:id":2686752,
    "tgn:name":"Spring Creek",
    "tgn:placetype":[
        "aat:300008706"
    ]
},
  "bbox": [],
  "geometry": {"coordinates":[-88.3667,42.75],"type":"Point"}
}