{
  "id": 7102502,
  "type": "Feature",
  "properties": {
    "tgn:hierarchy":[
        "tgn:7102502",
        "tgn:7003669",
        "tgn:1000003",
        "tgn:7000084",
        "tgn:7029392"
    ],
    "tgn:id":7102502,
    "tgn:name":"Sankt Stephan",
    "tgn:placetype":[
        "aat:300008347"
    ]
},
  "bbox": [],
  "geometry": {"coordinates":[10.883333,48.483333],"type":"Point"}
}