{
  "id": 7214924,
  "type": "Feature",
  "properties": {
    "tgn:hierarchy":[
        "tgn:7214924",
        "tgn:1000003",
        "tgn:7003677",
        "tgn:7000084",
        "tgn:7029392"
    ],
    "tgn:id":7214924,
    "tgn:name":"Bettrup",
    "tgn:placetype":[
        "aat:300000206"
    ]
},
  "bbox": [],
  "geometry": {"coordinates":[7.433333,52.05],"type":"Point"}
}