{
  "id": 2436318,
  "type": "Feature",
  "properties": {
    "tgn:hierarchy":[
        "tgn:2436318",
        "tgn:1000001",
        "tgn:2000922",
        "tgn:7012149",
        "tgn:7007515",
        "tgn:7029392"
    ],
    "tgn:id":2436318,
    "tgn:name":"Kiahs Island",
    "tgn:placetype":[
        "aat:300008791"
    ]
},
  "bbox": [],
  "geometry": {"coordinates":[-68.6333,44.1667],"type":"Point"}
}