{
  "id": 7253276,
  "type": "Feature",
  "properties": {
    "tgn:hierarchy":[
        "tgn:7253276",
        "tgn:7003460",
        "tgn:1000003",
        "tgn:1000063",
        "tgn:4012014",
        "tgn:7029392"
    ],
    "tgn:id":7253276,
    "tgn:name":"Sart Tilman",
    "tgn:placetype":[
        "aat:300008347"
    ]
},
  "bbox": [],
  "geometry": {"coordinates":[5.571037,50.590584],"type":"Point"}
}