<<<<<<< HEAD
{
  "id": 2407058,
  "type": "Feature",
  "properties": {
    "tgn:hierarchy":[
        "tgn:2407058",
        "tgn:1000001",
        "tgn:7012149",
        "tgn:2001721",
        "tgn:7007708",
        "tgn:7029392"
    ],
    "tgn:id":2407058,
    "tgn:name":"Hunter Spring",
    "tgn:placetype":[
        "aat:300008697"
    ]
},
  "bbox": [],
  "geometry": {"coordinates":[-118.3167,45.1833],"type":"Point"}
}
=======
{"geometry":{"type":"Point","coordinates":[-118.316700,45.183300]},"type":"Feature","properties":{"hierarchy":["tgn:2407058","tgn:1000001","tgn:7012149","tgn:2001721","tgn:7007708","tgn:7029392"],"placetype":["aat:300008697"],"id":2407058,"name:xx":"Hunter Spring"}}
>>>>>>> 03f74aca74312dbeaf24d7e61306dd6a786dc3d0
