{
  "id": 7208247,
  "type": "Feature",
  "properties": {
    "tgn:hierarchy":[
        "tgn:7208247",
        "tgn:1000003",
        "tgn:7003682",
        "tgn:7000084",
        "tgn:7029392"
    ],
    "tgn:id":7208247,
    "tgn:name":"B\u00fclz",
    "tgn:placetype":[
        "aat:300008777"
    ]
},
  "bbox": [],
  "geometry": {"coordinates":[6.366667,50.116667],"type":"Point"}
}