<<<<<<< HEAD
{
  "id": 2331308,
  "type": "Feature",
  "properties": {
    "tgn:hierarchy":[
        "tgn:2331308",
        "tgn:1000001",
        "tgn:7012149",
        "tgn:2001453",
        "tgn:7007566",
        "tgn:7029392"
    ],
    "tgn:id":2331308,
    "tgn:name":"Flatiron",
    "tgn:placetype":[
        "aat:300008798"
    ]
},
  "bbox": [],
  "geometry": {"coordinates":[-104.15,35.75],"type":"Point"}
}
=======
{"geometry":{"type":"Point","coordinates":[-104.150000,35.750000]},"type":"Feature","properties":{"hierarchy":["tgn:2331308","tgn:1000001","tgn:7012149","tgn:2001453","tgn:7007566","tgn:7029392"],"placetype":["aat:300008798"],"id":2331308,"name:xx":"Flatiron"}}
>>>>>>> 03f74aca74312dbeaf24d7e61306dd6a786dc3d0
