<<<<<<< HEAD
{
  "id": 7477545,
  "type": "Feature",
  "properties": {
    "tgn:hierarchy":[
        "tgn:7477545",
        "tgn:7001010",
        "tgn:1000004",
        "tgn:1000141",
        "tgn:7029392"
    ],
    "tgn:id":7477545,
    "tgn:name":"Anlai Shan",
    "tgn:placetype":[
        "aat:300008798"
    ]
},
  "bbox": [],
  "geometry": {"coordinates":[121.394718,23.85295],"type":"Point"}
}
=======
{"geometry":{"type":"Point","coordinates":[121.394718,23.852950]},"type":"Feature","properties":{"hierarchy":["tgn:7477545","tgn:7001010","tgn:1000004","tgn:1000141","tgn:7029392"],"placetype":["aat:300008798"],"id":7477545,"name:xx":"Anlai Shan"}}
>>>>>>> 03f74aca74312dbeaf24d7e61306dd6a786dc3d0
