{
  "id": 7477545,
  "type": "Feature",
  "properties": {
    "tgn:hierarchy":[
        "tgn:7477545",
        "tgn:7001010",
        "tgn:1000004",
        "tgn:1000141",
        "tgn:7029392"
    ],
    "tgn:id":7477545,
    "tgn:name":"Anlai Shan",
    "tgn:placetype":[
        "aat:300008798"
    ]
},
  "bbox": [],
  "geometry": {"coordinates":[121.394718,23.85295],"type":"Point"}
}