<<<<<<< HEAD
{
  "id": 2402779,
  "type": "Feature",
  "properties": {
    "tgn:hierarchy":[
        "tgn:2402779",
        "tgn:1002145",
        "tgn:1000001",
        "tgn:7012149",
        "tgn:7007157",
        "tgn:7029392"
    ],
    "tgn:id":2402779,
    "tgn:name":"Hot Springs Creek",
    "tgn:placetype":[
        "aat:300008706"
    ]
},
  "bbox": [],
  "geometry": {"coordinates":[-119.9,38.7167],"type":"Point"}
}
=======
{"geometry":{"type":"Point","coordinates":[-119.900000,38.716700]},"type":"Feature","properties":{"hierarchy":["tgn:2402779","tgn:1002145","tgn:1000001","tgn:7012149","tgn:7007157","tgn:7029392"],"placetype":["aat:300008706"],"id":2402779,"name:xx":"Hot Springs Creek"}}
>>>>>>> 03f74aca74312dbeaf24d7e61306dd6a786dc3d0
