{
  "id": 2530804,
  "type": "Feature",
  "properties": {
    "tgn:hierarchy":[
        "tgn:2530804",
        "tgn:1000001",
        "tgn:7012149",
        "tgn:2001709",
        "tgn:7007708",
        "tgn:7029392"
    ],
    "tgn:id":2530804,
    "tgn:name":"Muddy Spring",
    "tgn:placetype":[
        "aat:300008697"
    ]
},
  "bbox": [],
  "geometry": {"coordinates":[-119.3667,43.9333],"type":"Point"}
}