{
  "id": 1133701,
  "type": "Feature",
  "properties": {
    "tgn:hierarchy":[
        "tgn:1133701",
        "tgn:7003669",
        "tgn:1000003",
        "tgn:7000084",
        "tgn:7029392"
    ],
    "tgn:id":1133701,
    "tgn:name":"Loisach",
    "tgn:placetype":[
        "aat:300008706",
        "aat:300008699"
    ]
},
  "bbox": [],
  "geometry": {"coordinates":[11.45,47.933333],"type":"Point"}
}