{
  "id": 2707319,
  "type": "Feature",
  "properties": {
    "tgn:hierarchy":[
        "tgn:2707319",
        "tgn:1000001",
        "tgn:7012149",
        "tgn:2002119",
        "tgn:7007827",
        "tgn:7029392"
    ],
    "tgn:id":2707319,
    "tgn:name":"Sweet Alice Spring",
    "tgn:placetype":[
        "aat:300008697"
    ]
},
  "bbox": [],
  "geometry": {"coordinates":[-109.9167,37.8667],"type":"Point"}
}