{
  "id": 7341066,
  "type": "Feature",
  "properties": {
    "tgn:hierarchy":[
        "tgn:7341066",
        "tgn:7002834",
        "tgn:1000003",
        "tgn:7002786",
        "tgn:1000095",
        "tgn:7029392"
    ],
    "tgn:id":7341066,
    "tgn:name":"Bueu, Ensenada de",
    "tgn:placetype":[
        "aat:300132316"
    ]
},
  "bbox": [],
  "geometry": {"coordinates":[-8.783333,42.333333],"type":"Point"}
}