<<<<<<< HEAD
{
  "id": 2335054,
  "type": "Feature",
  "properties": {
    "tgn:hierarchy":[
        "tgn:2335054",
        "tgn:1000001",
        "tgn:7012149",
        "tgn:2001437",
        "tgn:7007566",
        "tgn:7029392"
    ],
    "tgn:id":2335054,
    "tgn:name":"Forrest Tank",
    "tgn:placetype":[
        "aat:300006191"
    ]
},
  "bbox": [],
  "geometry": {"coordinates":[-108.9167,32.9667],"type":"Point"}
}
=======
{"geometry":{"type":"Point","coordinates":[-108.916700,32.966700]},"type":"Feature","properties":{"hierarchy":["tgn:2335054","tgn:1000001","tgn:7012149","tgn:2001437","tgn:7007566","tgn:7029392"],"placetype":["aat:300006191"],"id":2335054,"name:xx":"Forrest Tank"}}
>>>>>>> 03f74aca74312dbeaf24d7e61306dd6a786dc3d0
