{
  "id": 2449535,
  "type": "Feature",
  "properties": {
    "tgn:hierarchy":[
        "tgn:2449535",
        "tgn:1000001",
        "tgn:7012149",
        "tgn:7014589",
        "tgn:7007515",
        "tgn:7029392"
    ],
    "tgn:id":2449535,
    "tgn:name":"Lincoln Cove",
    "tgn:placetype":[
        "aat:300132316"
    ]
},
  "bbox": [],
  "geometry": {"coordinates":[-67.0667,44.9167],"type":"Point"}
}