{
  "id": 7308038,
  "type": "Feature",
  "properties": {
    "tgn:hierarchy":[
        "tgn:7308038",
        "tgn:1001623",
        "tgn:1000049",
        "tgn:1000002",
        "tgn:7029392"
    ],
    "tgn:id":7308038,
    "tgn:name":"Melita, Islote",
    "tgn:placetype":[
        "aat:300008791"
    ]
},
  "bbox": [],
  "geometry": {"coordinates":[-73.65,-45.233333],"type":"Point"}
}