{
  "id": 2288236,
  "type": "Feature",
  "properties": {
    "tgn:hierarchy":[
        "tgn:2288236",
        "tgn:1000001",
        "tgn:7012149",
        "tgn:2001709",
        "tgn:7007708",
        "tgn:7029392"
    ],
    "tgn:id":2288236,
    "tgn:name":"Dipping Vat Creek",
    "tgn:placetype":[
        "aat:300008706"
    ]
},
  "bbox": [],
  "geometry": {"coordinates":[-117.9167,43.8333],"type":"Point"}
}