{
  "id": 7140212,
  "type": "Feature",
  "properties": {
    "tgn:hierarchy":[
        "tgn:7140212",
        "tgn:1000003",
        "tgn:7003687",
        "tgn:7000084",
        "tgn:7029392"
    ],
    "tgn:id":7140212,
    "tgn:name":"L\u00fcttgenziatz",
    "tgn:placetype":[
        "aat:300008347"
    ]
},
  "bbox": [],
  "geometry": {"coordinates":[12.016667,52.183333],"type":"Point"}
}