{
  "id": 1017453,
  "type": "Feature",
  "properties": {
    "tgn:hierarchy":[
        "tgn:1017453",
        "tgn:7005586",
        "tgn:1000001",
        "tgn:7005560",
        "tgn:7029392"
    ],
    "tgn:id":1017453,
    "tgn:name":"Encarnaci\u00f3n de D\u00edaz",
    "tgn:placetype":[
        "aat:300008347"
    ]
},
  "bbox": [],
  "geometry": {"coordinates":[-102.233333,21.516667],"type":"Point"}
}