{
  "id": 7349616,
  "type": "Feature",
  "properties": {
    "tgn:hierarchy":[
        "tgn:7349616",
        "tgn:1000001",
        "tgn:7005590",
        "tgn:7005560",
        "tgn:7029392"
    ],
    "tgn:id":7349616,
    "tgn:name":"Agua Nueva",
    "tgn:placetype":[
        "aat:300008347"
    ]
},
  "bbox": [],
  "geometry": {"coordinates":[-102.233333,19.35],"type":"Point"}
}