{
  "id": 2786952,
  "type": "Feature",
  "properties": {
    "tgn:hierarchy":[
        "tgn:2786952",
        "tgn:1000001",
        "tgn:7012149",
        "tgn:1002926",
        "tgn:7007568",
        "tgn:7029392"
    ],
    "tgn:id":2786952,
    "tgn:name":"Zieglers Pond",
    "tgn:placetype":[
        "aat:300006191"
    ]
},
  "bbox": [],
  "geometry": {"coordinates":[-74.7833,41.6833],"type":"Point"}
}