{
  "id": 2182836,
  "type": "Feature",
  "properties": {
    "tgn:hierarchy":[
        "tgn:2182836",
        "tgn:1000001",
        "tgn:7016172",
        "tgn:7012149",
        "tgn:2000173",
        "tgn:7029392"
    ],
    "tgn:id":2182836,
    "tgn:name":"Blue Steer Branch",
    "tgn:placetype":[
        "aat:300008699"
    ]
},
  "bbox": [],
  "geometry": {"coordinates":[-92.1667,36.05],"type":"Point"}
}