<<<<<<< HEAD
{
  "id": 2258407,
  "type": "Feature",
  "properties": {
    "tgn:hierarchy":[
        "tgn:2258407",
        "tgn:1000001",
        "tgn:1002270",
        "tgn:7012149",
        "tgn:7007708",
        "tgn:7029392"
    ],
    "tgn:id":2258407,
    "tgn:name":"Cotton Creek",
    "tgn:placetype":[
        "aat:300008706"
    ]
},
  "bbox": [],
  "geometry": {"coordinates":[-122.55,45.05],"type":"Point"}
}
=======
{"geometry":{"type":"Point","coordinates":[-122.550000,45.050000]},"type":"Feature","properties":{"hierarchy":["tgn:2258407","tgn:1000001","tgn:1002270","tgn:7012149","tgn:7007708","tgn:7029392"],"placetype":["aat:300008706"],"id":2258407,"name:xx":"Cotton Creek"}}
>>>>>>> 03f74aca74312dbeaf24d7e61306dd6a786dc3d0
