{
  "id": 2258407,
  "type": "Feature",
  "properties": {
    "tgn:hierarchy":[
        "tgn:2258407",
        "tgn:1000001",
        "tgn:1002270",
        "tgn:7012149",
        "tgn:7007708",
        "tgn:7029392"
    ],
    "tgn:id":2258407,
    "tgn:name":"Cotton Creek",
    "tgn:placetype":[
        "aat:300008706"
    ]
},
  "bbox": [],
  "geometry": {"coordinates":[-122.55,45.05],"type":"Point"}
}