{
  "id": 2587502,
  "type": "Feature",
  "properties": {
    "tgn:hierarchy":[
        "tgn:2587502",
        "tgn:1000001",
        "tgn:7012149",
        "tgn:2001274",
        "tgn:7007524",
        "tgn:7029392"
    ],
    "tgn:id":2587502,
    "tgn:name":"Pleasant Island",
    "tgn:placetype":[
        "aat:300008791"
    ]
},
  "bbox": [],
  "geometry": {"coordinates":[-114.35,48.15],"type":"Point"}
}