<<<<<<< HEAD
{
  "id": 7374026,
  "type": "Feature",
  "properties": {
    "tgn:hierarchy":[
        "tgn:7374026",
        "tgn:7005581",
        "tgn:1000001",
        "tgn:7005560",
        "tgn:7029392"
    ],
    "tgn:id":7374026,
    "tgn:name":"La Guitarra",
    "tgn:placetype":[
        "aat:300387007"
    ]
},
  "bbox": [],
  "geometry": {"coordinates":[-107.016667,26.083333],"type":"Point"}
}
=======
{"geometry":{"type":"Point","coordinates":[-107.016667,26.083333]},"type":"Feature","properties":{"hierarchy":["tgn:7374026","tgn:7005581","tgn:1000001","tgn:7005560","tgn:7029392"],"placetype":["aat:300387007"],"id":7374026,"name:xx":"La Guitarra"}}
>>>>>>> 03f74aca74312dbeaf24d7e61306dd6a786dc3d0
