{
  "id": 2354475,
  "type": "Feature",
  "properties": {
    "tgn:hierarchy":[
        "tgn:2354475",
        "tgn:1000001",
        "tgn:7012149",
        "tgn:7007157",
        "tgn:1002867",
        "tgn:7029392"
    ],
    "tgn:id":2354475,
    "tgn:name":"Goleta Slough",
    "tgn:placetype":[
        "aat:300008905"
    ]
},
  "bbox": [],
  "geometry": {"coordinates":[-119.8333,34.4167],"type":"Point"}
}