<<<<<<< HEAD
{
  "id": 7364727,
  "type": "Feature",
  "properties": {
    "tgn:hierarchy":[
        "tgn:7364727",
        "tgn:1001853",
        "tgn:1000001",
        "tgn:7005560",
        "tgn:7029392"
    ],
    "tgn:id":7364727,
    "tgn:name":"Flores, Potrero de",
    "tgn:placetype":[
        "aat:300008761"
    ]
},
  "bbox": [],
  "geometry": {"coordinates":[-102.65,27.466667],"type":"Point"}
}
=======
{"geometry":{"type":"Point","coordinates":[-102.650000,27.466667]},"type":"Feature","properties":{"hierarchy":["tgn:7364727","tgn:1001853","tgn:1000001","tgn:7005560","tgn:7029392"],"placetype":["aat:300008761"],"id":7364727,"name:xx":"Flores, Potrero de"}}
>>>>>>> 03f74aca74312dbeaf24d7e61306dd6a786dc3d0
