{
  "id": 1120779,
  "type": "Feature",
  "properties": {
    "tgn:hierarchy":[
        "tgn:1120779",
        "tgn:1001052",
        "tgn:1000004",
        "tgn:7018450",
        "tgn:1000144",
        "tgn:7029392"
    ],
    "tgn:id":1120779,
    "tgn:name":"\u00c7avu\u015fba\u015f\u0131",
    "tgn:placetype":[
        "aat:300008707"
    ]
},
  "bbox": [],
  "geometry": {"coordinates":[28.85,40.9667],"type":"Point"}
}