{
  "id": 7513139,
  "type": "Feature",
  "properties": {
    "tgn:hierarchy":[
        "tgn:7513139",
        "tgn:7016670",
        "tgn:1008380",
        "tgn:1000226",
        "tgn:1000006",
        "tgn:7029392"
    ],
    "tgn:id":7513139,
    "tgn:name:en":"Gwavas",
    "tgn:placetype":[
        "aat:300000206"
    ]
},
  "bbox": [],
  "geometry": {"coordinates":[176.483333,-39.783333],"type":"Point"}
}