{
  "id": 2511648,
  "type": "Feature",
  "properties": {
    "tgn:hierarchy":[
        "tgn:2511648",
        "tgn:7006450",
        "tgn:1000001",
        "tgn:7012149",
        "tgn:2000086",
        "tgn:7029392"
    ],
    "tgn:id":2511648,
    "tgn:name":"Miles Glacier",
    "tgn:placetype":[
        "aat:300008835"
    ]
},
  "bbox": [],
  "geometry": {"coordinates":[-144.1167,60.6167],"type":"Point"}
}