<<<<<<< HEAD
{
  "id": 7359165,
  "type": "Feature",
  "properties": {
    "tgn:hierarchy":[
        "tgn:7359165",
        "tgn:7005584",
        "tgn:1000001",
        "tgn:7005560",
        "tgn:7029392"
    ],
    "tgn:id":7359165,
    "tgn:name":"Cruz de la Palma",
    "tgn:placetype":[
        "aat:300008347"
    ]
},
  "bbox": [],
  "geometry": {"coordinates":[-100.6,21.216667],"type":"Point"}
}
=======
{"geometry":{"type":"Point","coordinates":[-100.600000,21.216667]},"type":"Feature","properties":{"hierarchy":["tgn:7359165","tgn:7005584","tgn:1000001","tgn:7005560","tgn:7029392"],"placetype":["aat:300008347"],"id":7359165,"name:xx":"Cruz de la Palma"}}
>>>>>>> 03f74aca74312dbeaf24d7e61306dd6a786dc3d0
