{
  "id": 7328224,
  "type": "Feature",
  "properties": {
    "tgn:hierarchy":[
        "tgn:7328224",
        "tgn:1001439",
        "tgn:1000003",
        "tgn:7002797",
        "tgn:1000095",
        "tgn:7029392"
    ],
    "tgn:id":7328224,
    "tgn:name":"Reona, Cala",
    "tgn:placetype":[
        "aat:300132317"
    ]
},
  "bbox": [],
  "geometry": {"coordinates":[-1.633333,37.383333],"type":"Point"}
}