<<<<<<< HEAD
{
  "id": 2339091,
  "type": "Feature",
  "properties": {
    "tgn:hierarchy":[
        "tgn:2339091",
        "tgn:1002996",
        "tgn:1000001",
        "tgn:7012149",
        "tgn:7007711",
        "tgn:7029392"
    ],
    "tgn:id":2339091,
    "tgn:name":"Franklin Swamp",
    "tgn:placetype":[
        "aat:300008905"
    ]
},
  "bbox": [],
  "geometry": {"coordinates":[-71.6,41.1667],"type":"Point"}
}
=======
{"geometry":{"type":"Point","coordinates":[-71.600000,41.166700]},"type":"Feature","properties":{"hierarchy":["tgn:2339091","tgn:1002996","tgn:1000001","tgn:7012149","tgn:7007711","tgn:7029392"],"placetype":["aat:300008905"],"id":2339091,"name:xx":"Franklin Swamp"}}
>>>>>>> 03f74aca74312dbeaf24d7e61306dd6a786dc3d0
