{
  "id": 2304145,
  "type": "Feature",
  "properties": {
    "tgn:hierarchy":[
        "tgn:2304145",
        "tgn:1000001",
        "tgn:7012149",
        "tgn:2001067",
        "tgn:7007521",
        "tgn:7029392"
    ],
    "tgn:id":2304145,
    "tgn:name":"Eagles Nest",
    "tgn:placetype":[
        "aat:300008347"
    ]
},
  "bbox": [],
  "geometry": {"coordinates":[-92.0833,47.8333],"type":"Point"}
}