{
  "id": 7061297,
  "type": "Feature",
  "properties": {
    "tgn:hierarchy":[
        "tgn:7061297",
        "tgn:7003669",
        "tgn:1000003",
        "tgn:7000084",
        "tgn:7029392"
    ],
    "tgn:id":7061297,
    "tgn:name":"Auf der H\u00f6he",
    "tgn:placetype":[
        "aat:300008777"
    ]
},
  "bbox": [],
  "geometry": {"coordinates":[12.183333,49.533333],"type":"Point"}
}