{
  "id": 2469430,
  "type": "Feature",
  "properties": {
    "tgn:hierarchy":[
        "tgn:2469430",
        "tgn:1000001",
        "tgn:7016172",
        "tgn:7012149",
        "tgn:2000160",
        "tgn:7029392"
    ],
    "tgn:id":2469430,
    "tgn:name":"Lonnie Jaynes Lake",
    "tgn:placetype":[
        "aat:300006191"
    ]
},
  "bbox": [],
  "geometry": {"coordinates":[-90.65,35.6333],"type":"Point"}
}