{
  "id": 7307089,
  "type": "Feature",
  "properties": {
    "tgn:hierarchy":[
        "tgn:7307089",
        "tgn:7002829",
        "tgn:1000003",
        "tgn:7002786",
        "tgn:1000095",
        "tgn:7029392"
    ],
    "tgn:id":7307089,
    "tgn:name":"Marz\u00e1",
    "tgn:placetype":[
        "aat:300008347"
    ]
},
  "bbox": [],
  "geometry": {"coordinates":[-7.85,42.866667],"type":"Point"}
}