<<<<<<< HEAD
{
  "id": 2257677,
  "type": "Feature",
  "properties": {
    "tgn:hierarchy":[
        "tgn:2257677",
        "tgn:1000001",
        "tgn:2002242",
        "tgn:7012149",
        "tgn:7007920",
        "tgn:7029392"
    ],
    "tgn:id":2257677,
    "tgn:name":"Corral Creek",
    "tgn:placetype":[
        "aat:300008706"
    ]
},
  "bbox": [],
  "geometry": {"coordinates":[-119.8667,47.85],"type":"Point"}
}
=======
{"geometry":{"type":"Point","coordinates":[-119.866700,47.850000]},"type":"Feature","properties":{"hierarchy":["tgn:2257677","tgn:1000001","tgn:2002242","tgn:7012149","tgn:7007920","tgn:7029392"],"placetype":["aat:300008706"],"id":2257677,"name:xx":"Corral Creek"}}
>>>>>>> 03f74aca74312dbeaf24d7e61306dd6a786dc3d0
