{
  "id": 2257677,
  "type": "Feature",
  "properties": {
    "tgn:hierarchy":[
        "tgn:2257677",
        "tgn:1000001",
        "tgn:2002242",
        "tgn:7012149",
        "tgn:7007920",
        "tgn:7029392"
    ],
    "tgn:id":2257677,
    "tgn:name":"Corral Creek",
    "tgn:placetype":[
        "aat:300008706"
    ]
},
  "bbox": [],
  "geometry": {"coordinates":[-119.8667,47.85],"type":"Point"}
}