{
  "id": 2657774,
  "type": "Feature",
  "properties": {
    "tgn:hierarchy":[
        "tgn:2657774",
        "tgn:1000001",
        "tgn:2000317",
        "tgn:7012149",
        "tgn:7007248",
        "tgn:7029392"
    ],
    "tgn:id":2657774,
    "tgn:name":"Shell Creek",
    "tgn:placetype":[
        "aat:300008706"
    ]
},
  "bbox": [],
  "geometry": {"coordinates":[-84.8333,32.2833],"type":"Point"}
}