{
  "id": 7303729,
  "type": "Feature",
  "properties": {
    "tgn:hierarchy":[
        "tgn:7303729",
        "tgn:7002803",
        "tgn:1001647",
        "tgn:1000003",
        "tgn:1000095",
        "tgn:7029392"
    ],
    "tgn:id":7303729,
    "tgn:name":"Morote",
    "tgn:placetype":[
        "aat:300008347"
    ]
},
  "bbox": [],
  "geometry": {"coordinates":[-2.25,38.416667],"type":"Point"}
}