{
  "id": 1086473,
  "type": "Feature",
  "properties": {
    "tgn:hierarchy":[
        "tgn:1086473",
        "tgn:7002513",
        "tgn:1000004",
        "tgn:7018451",
        "tgn:1000144",
        "tgn:7029392"
    ],
    "tgn:id":1086473,
    "tgn:name":"Kilandiras",
    "tgn:placetype":[
        "aat:300008347"
    ]
},
  "bbox": [],
  "geometry": {"coordinates":[30.1833,38.5667],"type":"Point"}
}