{
  "id": 2372076,
  "type": "Feature",
  "properties": {
    "tgn:hierarchy":[
        "tgn:2372076",
        "tgn:1000001",
        "tgn:7012149",
        "tgn:2000226",
        "tgn:7007158",
        "tgn:7029392"
    ],
    "tgn:id":2372076,
    "tgn:name":"Half Way Creek",
    "tgn:placetype":[
        "aat:300008706"
    ]
},
  "bbox": [],
  "geometry": {"coordinates":[-105.9167,40.7167],"type":"Point"}
}