{
  "id": 7286459,
  "type": "Feature",
  "properties": {
    "tgn:hierarchy":[
        "tgn:7286459",
        "tgn:1001702",
        "tgn:1000049",
        "tgn:1000002",
        "tgn:7029392"
    ],
    "tgn:id":7286459,
    "tgn:name":"Hermanos, Islotes",
    "tgn:placetype":[
        "aat:300008791"
    ]
},
  "bbox": [],
  "geometry": {"coordinates":[-67.083333,-54.966667],"type":"Point"}
}