{
  "id": 2053022,
  "type": "Feature",
  "properties": {
    "tgn:hierarchy":[
        "tgn:2053022",
        "tgn:1000001",
        "tgn:7012149",
        "tgn:1003005",
        "tgn:7007520",
        "tgn:7029392"
    ],
    "tgn:id":2053022,
    "tgn:name":"Plymouth",
    "tgn:placetype":[
        "aat:300008347"
    ]
},
  "bbox": [],
  "geometry": {"coordinates":[-83.4667,42.3667],"type":"Point"}
}