{
  "id": 7073949,
  "type": "Feature",
  "properties": {
    "tgn:hierarchy":[
        "tgn:7073949",
        "tgn:7003669",
        "tgn:1000003",
        "tgn:7000084",
        "tgn:7029392"
    ],
    "tgn:id":7073949,
    "tgn:name":"Stra\u00dfh\u00e4user",
    "tgn:placetype":[
        "aat:300008347"
    ]
},
  "bbox": [],
  "geometry": {"coordinates":[12.783333,48.35],"type":"Point"}
}