{
  "id": 7236587,
  "type": "Feature",
  "properties": {
    "tgn:hierarchy":[
        "tgn:7236587",
        "tgn:7002681",
        "tgn:7001395",
        "tgn:1000003",
        "tgn:1000074",
        "tgn:7029392"
    ],
    "tgn:id":7236587,
    "tgn:name":"\u00c1no Fan\u00e1rion",
    "tgn:placetype":[
        "aat:300008347"
    ]
},
  "bbox": [],
  "geometry": {"coordinates":[23.233333,37.583333],"type":"Point"}
}