{
  "id": 7557013,
  "type": "Feature",
  "properties": {
    "tgn:hierarchy":[
        "tgn:7557013",
        "tgn:1000004",
        "tgn:7000198",
        "tgn:1001998",
        "tgn:7029392"
    ],
    "tgn:id":7557013,
    "tgn:name:en":"R\u0101mlaitui",
    "tgn:placetype":[
        "aat:300008347"
    ]
},
  "bbox": [],
  "geometry": {"coordinates":[92.738259,23.182833],"type":"Point"}
}