{
  "id": 7589403,
  "type": "Feature",
  "properties": {
    "tgn:hierarchy":[
        "tgn:7589403",
        "tgn:1000004",
        "tgn:7000198",
        "tgn:7000799",
        "tgn:7029392"
    ],
    "tgn:id":7589403,
    "tgn:name:en":"R\u0101ipur",
    "tgn:placetype":[
        "aat:300008347"
    ]
},
  "bbox": [],
  "geometry": {"coordinates":[74.830443,32.806013],"type":"Point"}
}