{
  "id": 1089831,
  "type": "Feature",
  "properties": {
    "tgn:hierarchy":[
        "tgn:1089831",
        "tgn:7001242",
        "tgn:1001266",
        "tgn:7000489",
        "tgn:7029392"
    ],
    "tgn:id":1089831,
    "tgn:name":"Guba",
    "tgn:placetype":[
        "aat:300008347"
    ]
},
  "bbox": [],
  "geometry": {"coordinates":[35.2833,10.2667],"type":"Point"}
}