{
  "id": 7161560,
  "type": "Feature",
  "properties": {
    "tgn:hierarchy":[
        "tgn:7161560",
        "tgn:7003669",
        "tgn:1000003",
        "tgn:7000084",
        "tgn:7029392"
    ],
    "tgn:id":7161560,
    "tgn:name":"Hochriedriegel",
    "tgn:placetype":[
        "aat:300266640"
    ]
},
  "bbox": [],
  "geometry": {"coordinates":[12.95,48.95],"type":"Point"}
}