{
  "id": 7035255,
  "type": "Feature",
  "properties": {
    "tgn:hierarchy":[
        "tgn:7035255",
        "tgn:1003506",
        "tgn:1000003",
        "tgn:7002993",
        "tgn:1000080",
        "tgn:7029392"
    ],
    "tgn:id":7035255,
    "tgn:name":"Sammordenchia",
    "tgn:placetype":[
        "aat:300008347"
    ]
},
  "bbox": [],
  "geometry": {"coordinates":[13.203611,46.239167],"type":"Point"}
}