{
  "id": 7034831,
  "type": "Feature",
  "properties": {
    "tgn:hierarchy":[
        "tgn:7034831",
        "tgn:1000003",
        "tgn:7003236",
        "tgn:1000080",
        "tgn:7029392"
    ],
    "tgn:id":7034831,
    "tgn:name":"Pino, Capo",
    "tgn:placetype":[
        "aat:300008850"
    ]
},
  "bbox": [],
  "geometry": {"coordinates":[9.101667,44.368889],"type":"Point"}
}