{
  "id": 7534258,
  "type": "Feature",
  "properties": {
    "tgn:hierarchy":[
        "tgn:7534258",
        "tgn:7001242",
        "tgn:7016833",
        "tgn:1001418",
        "tgn:7029392"
    ],
    "tgn:id":7534258,
    "tgn:name:en":"Qabr Hawwa",
    "tgn:placetype":[
        "aat:300005926"
    ]
},
  "bbox": [],
  "geometry": {"coordinates":[27.583333,30.916667],"type":"Point"}
}