{
  "id": 2442475,
  "type": "Feature",
  "properties": {
    "tgn:hierarchy":[
        "tgn:2442475",
        "tgn:7006450",
        "tgn:1000001",
        "tgn:2124053",
        "tgn:7012149",
        "tgn:7029392"
    ],
    "tgn:id":2442475,
    "tgn:name":"Kroto Lake",
    "tgn:placetype":[
        "aat:300008680"
    ]
},
  "bbox": [],
  "geometry": {"coordinates":[-150.65,62.4333],"type":"Point"}
}