{
  "id": 2416591,
  "type": "Feature",
  "properties": {
    "tgn:hierarchy":[
        "tgn:2416591",
        "tgn:7006450",
        "tgn:1000001",
        "tgn:7012149",
        "tgn:2000079",
        "tgn:7029392"
    ],
    "tgn:id":2416591,
    "tgn:name":"Jack Gulch",
    "tgn:placetype":[
        "aat:300008761"
    ]
},
  "bbox": [],
  "geometry": {"coordinates":[-165.35,64.7833],"type":"Point"}
}