{
  "id": 4001539,
  "type": "Feature",
  "properties": {
    "tgn:hierarchy":[
        "tgn:4001539",
        "tgn:1000003",
        "tgn:7002889",
        "tgn:1000070",
        "tgn:7029392"
    ],
    "tgn:id":4001539,
    "tgn:name":"Bioule",
    "tgn:placetype":[
        "aat:300008347"
    ]
},
  "bbox": [],
  "geometry": {"coordinates":[1.55,44.0833],"type":"Point"}
}