{
  "id": 2264443,
  "type": "Feature",
  "properties": {
    "tgn:hierarchy":[
        "tgn:2264443",
        "tgn:1000001",
        "tgn:7012149",
        "tgn:2002275",
        "tgn:7013961",
        "tgn:7029392"
    ],
    "tgn:id":2264443,
    "tgn:name":"Crabapple Run",
    "tgn:placetype":[
        "aat:300008699"
    ]
},
  "bbox": [],
  "geometry": {"coordinates":[-80.3833,39.4667],"type":"Point"}
}