{
  "id": 7312403,
  "type": "Feature",
  "properties": {
    "tgn:hierarchy":[
        "tgn:7312403",
        "tgn:1001705",
        "tgn:1000049",
        "tgn:1000002",
        "tgn:7029392"
    ],
    "tgn:id":7312403,
    "tgn:name":"Largo, Caj\u00f3n",
    "tgn:placetype":[
        "aat:300008699"
    ]
},
  "bbox": [],
  "geometry": {"coordinates":[-70.933333,-36.166667],"type":"Point"}
}