{
  "id": 7364423,
  "type": "Feature",
  "properties": {
    "tgn:hierarchy":[
        "tgn:7364423",
        "tgn:1000001",
        "tgn:7005594",
        "tgn:7005560",
        "tgn:7029392"
    ],
    "tgn:id":7364423,
    "tgn:name":"El Sasub",
    "tgn:placetype":[
        "aat:300008347"
    ]
},
  "bbox": [],
  "geometry": {"coordinates":[-98.516667,21.75],"type":"Point"}
}