{
  "id": 7419589,
  "type": "Feature",
  "properties": {
    "tgn:hierarchy":[
        "tgn:7419589",
        "tgn:1000001",
        "tgn:7005589",
        "tgn:7005560",
        "tgn:7029392"
    ],
    "tgn:id":7419589,
    "tgn:name:es":"La Minita",
    "tgn:placetype":[
        "aat:300008347"
    ]
},
  "bbox": [],
  "geometry": {"coordinates":[-99.998611,26.827778],"type":"Point"}
}