{
  "id": 7495365,
  "type": "Feature",
  "properties": {
    "tgn:hierarchy":[
        "tgn:7495365",
        "tgn:1000004",
        "tgn:7001013",
        "tgn:1000141",
        "tgn:7029392"
    ],
    "tgn:id":7495365,
    "tgn:name":"Dacheng Guozhong",
    "tgn:placetype":[
        "aat:300006495"
    ]
},
  "bbox": [],
  "geometry": {"coordinates":[121.306012,24.959294],"type":"Point"}
}