{
  "id": 2730759,
  "type": "Feature",
  "properties": {
    "tgn:hierarchy":[
        "tgn:2730759",
        "tgn:1000001",
        "tgn:7012149",
        "tgn:2002250",
        "tgn:7007920",
        "tgn:7029392"
    ],
    "tgn:id":2730759,
    "tgn:name":"Tshimakain Creek",
    "tgn:placetype":[
        "aat:300008706"
    ]
},
  "bbox": [],
  "geometry": {"coordinates":[-117.75,47.8833],"type":"Point"}
}