{
  "id": 7594004,
  "type": "Feature",
  "properties": {
    "tgn:hierarchy":[
        "tgn:7594004",
        "tgn:1001053",
        "tgn:1000004",
        "tgn:7018451",
        "tgn:1000144",
        "tgn:7029392"
    ],
    "tgn:id":7594004,
    "tgn:name":"Buruncuk",
    "tgn:placetype":[
        "aat:300008347",
        "aat:300008372"
    ]
},
  "bbox": [],
  "geometry": {"coordinates":[27.031,38.667],"type":"Point"}
}