{
  "id": 2326809,
  "type": "Feature",
  "properties": {
    "tgn:hierarchy":[
        "tgn:2326809",
        "tgn:1000001",
        "tgn:7012149",
        "tgn:7007157",
        "tgn:2000188",
        "tgn:7029392"
    ],
    "tgn:id":2326809,
    "tgn:name":"Fir Gulch",
    "tgn:placetype":[
        "aat:300008761"
    ]
},
  "bbox": [],
  "geometry": {"coordinates":[-122.95,40.3167],"type":"Point"}
}