{
  "id": 7493613,
  "type": "Feature",
  "properties": {
    "tgn:hierarchy":[
        "tgn:7493613",
        "tgn:7468018",
        "tgn:1000004",
        "tgn:1000141",
        "tgn:7029392"
    ],
    "tgn:id":7493613,
    "tgn:name":"Xianzu Miao",
    "tgn:placetype":[
        "aat:300007595"
    ]
},
  "bbox": [],
  "geometry": {"coordinates":[120.512217,23.32427],"type":"Point"}
}