{
  "id": 1011448,
  "type": "Feature",
  "properties": {
    "tgn:hierarchy":[
        "tgn:1011448",
        "tgn:7002444",
        "tgn:7008074",
        "tgn:1000003",
        "tgn:7008591",
        "tgn:7029392"
    ],
    "tgn:id":1011448,
    "tgn:name":"Galloway",
    "tgn:placetype":[
        "aat:300387499"
    ]
},
  "bbox": [],
  "geometry": {"coordinates":[-4.8833,54.6333],"type":"Point"}
}