{
  "id": 1103800,
  "type": "Feature",
  "properties": {
    "tgn:hierarchy":[
        "tgn:1103800",
        "tgn:1000584",
        "tgn:1000002",
        "tgn:1000056",
        "tgn:7029392"
    ],
    "tgn:id":1103800,
    "tgn:name":"Auzangate, Nevado",
    "tgn:placetype":[
        "aat:300008795"
    ]
},
  "bbox": [],
  "geometry": {"coordinates":[-71.2167,-13.7833],"type":"Point"}
}