{
  "id": 7426752,
  "type": "Feature",
  "properties": {
    "tgn:hierarchy":[
        "tgn:7426752",
        "tgn:1000001",
        "tgn:7005594",
        "tgn:7005560",
        "tgn:7029392"
    ],
    "tgn:id":7426752,
    "tgn:name":"La Esperanza",
    "tgn:placetype":[
        "aat:300008347"
    ]
},
  "bbox": [],
  "geometry": {"coordinates":[-99.433333,21.983333],"type":"Point"}
}