{
  "id": 7487405,
  "type": "Feature",
  "properties": {
    "tgn:hierarchy":[
        "tgn:7487405",
        "tgn:1000004",
        "tgn:7491221",
        "tgn:1000141",
        "tgn:7029392"
    ],
    "tgn:id":7487405,
    "tgn:name":"Lidong Feng",
    "tgn:placetype":[
        "aat:300008798"
    ]
},
  "bbox": [],
  "geometry": {"coordinates":[121.235556,23.041944],"type":"Point"}
}