<<<<<<< HEAD
{
  "id": 7487405,
  "type": "Feature",
  "properties": {
    "tgn:hierarchy":[
        "tgn:7487405",
        "tgn:1000004",
        "tgn:7491221",
        "tgn:1000141",
        "tgn:7029392"
    ],
    "tgn:id":7487405,
    "tgn:name":"Lidong Feng",
    "tgn:placetype":[
        "aat:300008798"
    ]
},
  "bbox": [],
  "geometry": {"coordinates":[121.235556,23.041944],"type":"Point"}
}
=======
{"geometry":{"type":"Point","coordinates":[121.235556,23.041944]},"type":"Feature","properties":{"hierarchy":["tgn:7487405","tgn:1000004","tgn:7491221","tgn:1000141","tgn:7029392"],"placetype":["aat:300008798"],"id":7487405,"name:xx":"Lidong Feng"}}
>>>>>>> 03f74aca74312dbeaf24d7e61306dd6a786dc3d0
