{
  "id": 1107306,
  "type": "Feature",
  "properties": {
    "tgn:hierarchy":[
        "tgn:1107306",
        "tgn:7003024",
        "tgn:1000003",
        "tgn:1000062",
        "tgn:7029392"
    ],
    "tgn:id":1107306,
    "tgn:name":"Hochalm  Spitze",
    "tgn:placetype":[
        "aat:300008798"
    ]
},
  "bbox": [],
  "geometry": {"coordinates":[13.3333,47.0333],"type":"Point"}
}