{
  "id": 7559778,
  "type": "Feature",
  "properties": {
    "tgn:hierarchy":[
        "tgn:7559778",
        "tgn:1000004",
        "tgn:7000198",
        "tgn:7016722",
        "tgn:7029392"
    ],
    "tgn:id":7559778,
    "tgn:name:en":"Nandpur",
    "tgn:placetype":[
        "aat:300008347"
    ]
},
  "bbox": [],
  "geometry": {"coordinates":[79.087596,26.974663],"type":"Point"}
}