{
  "id": 7581999,
  "type": "Feature",
  "properties": {
    "tgn:hierarchy":[
        "tgn:7581999",
        "tgn:1000004",
        "tgn:7000198",
        "tgn:7016883",
        "tgn:7029392"
    ],
    "tgn:id":7581999,
    "tgn:name:en":"R\u0101mpur Kal\u0101n",
    "tgn:placetype":[
        "aat:300008347"
    ]
},
  "bbox": [],
  "geometry": {"coordinates":[76.776262,30.603355],"type":"Point"}
}