{
  "id": 1139733,
  "type": "Feature",
  "properties": {
    "tgn:hierarchy":[
        "tgn:1139733",
        "tgn:1000004",
        "tgn:7002081",
        "tgn:1000111",
        "tgn:7029392"
    ],
    "tgn:id":1139733,
    "tgn:name":"Tuqiao",
    "tgn:placetype":[
        "aat:300008347"
    ]
},
  "bbox": [],
  "geometry": {"coordinates":[119.05,31.95],"type":"Point"}
}