{
  "id": 7436854,
  "type": "Feature",
  "properties": {
    "tgn:hierarchy":[
        "tgn:7436854",
        "tgn:1000001",
        "tgn:1001960",
        "tgn:7005560",
        "tgn:7029392"
    ],
    "tgn:id":7436854,
    "tgn:name":"Tepoca, Cabo",
    "tgn:placetype":[
        "aat:300008850"
    ]
},
  "bbox": [],
  "geometry": {"coordinates":[-112.883333,30.266667],"type":"Point"}
}