{
  "id": 7316529,
  "type": "Feature",
  "properties": {
    "tgn:hierarchy":[
        "tgn:7316529",
        "tgn:1001623",
        "tgn:1000049",
        "tgn:1000002",
        "tgn:7029392"
    ],
    "tgn:id":7316529,
    "tgn:name":"Casma, Bajo",
    "tgn:placetype":[
        "aat:300008808"
    ]
},
  "bbox": [],
  "geometry": {"coordinates":[-73.583333,-45.416667],"type":"Point"}
}