{
  "id": 7110084,
  "type": "Feature",
  "properties": {
    "tgn:hierarchy":[
        "tgn:7110084",
        "tgn:1000003",
        "tgn:7003682",
        "tgn:7000084",
        "tgn:7029392"
    ],
    "tgn:id":7110084,
    "tgn:name":"Ravengiersburg",
    "tgn:placetype":[
        "aat:300008347"
    ]
},
  "bbox": [],
  "geometry": {"coordinates":[7.483333,49.933333],"type":"Point"}
}