{
  "id": 2045385,
  "type": "Feature",
  "properties": {
    "tgn:hierarchy":[
        "tgn:2045385",
        "tgn:1000001",
        "tgn:7012149",
        "tgn:2000933",
        "tgn:7007515",
        "tgn:7029392"
    ],
    "tgn:id":2045385,
    "tgn:name":"Pine Hill",
    "tgn:placetype":[
        "aat:300008347"
    ]
},
  "bbox": [],
  "geometry": {"coordinates":[-70.5833,43.2167],"type":"Point"}
}