{
  "id": 7504829,
  "type": "Feature",
  "properties": {
    "tgn:hierarchy":[
        "tgn:7504829",
        "tgn:1009227",
        "tgn:1000226",
        "tgn:7016729",
        "tgn:1000006",
        "tgn:7029392"
    ],
    "tgn:id":7504829,
    "tgn:name:en":"Magazine Point",
    "tgn:placetype":[
        "aat:300386846"
    ]
},
  "bbox": [],
  "geometry": {"coordinates":[173.255,-41.276667],"type":"Point"}
}