{
  "id": 7540089,
  "type": "Feature",
  "properties": {
    "tgn:hierarchy":[
        "tgn:7540089",
        "tgn:7001242",
        "tgn:7016833",
        "tgn:1001418",
        "tgn:7029392"
    ],
    "tgn:id":7540089,
    "tgn:name:en":"S\u0101niyat al Qa\u0163\u012bfah",
    "tgn:placetype":[
        "aat:300006207"
    ]
},
  "bbox": [],
  "geometry": {"coordinates":[26.076131,31.476512],"type":"Point"}
}