{
  "id": 1012603,
  "type": "Feature",
  "properties": {
    "tgn:hierarchy":[
        "tgn:1012603",
        "tgn:7006218",
        "tgn:7006211",
        "tgn:1000216",
        "tgn:1000006",
        "tgn:7029392"
    ],
    "tgn:id":1012603,
    "tgn:name":"V\u00e9nus, Pointe",
    "tgn:placetype":[
        "aat:300386846"
    ]
},
  "bbox": [],
  "geometry": {"coordinates":[-149.4833,-17.4667],"type":"Point"}
}