{
  "id": 2660557,
  "type": "Feature",
  "properties": {
    "tgn:hierarchy":[
        "tgn:2660557",
        "tgn:1000001",
        "tgn:7006451",
        "tgn:7012149",
        "tgn:2000099",
        "tgn:7029392"
    ],
    "tgn:id":2660557,
    "tgn:name":"Shonto Butte",
    "tgn:placetype":[
        "aat:300008798"
    ]
},
  "bbox": [],
  "geometry": {"coordinates":[-110.3833,35.4167],"type":"Point"}
}