{
  "id": 7391640,
  "type": "Feature",
  "properties": {
    "tgn:hierarchy":[
        "tgn:7391640",
        "tgn:7005581",
        "tgn:1000001",
        "tgn:7005560",
        "tgn:7029392"
    ],
    "tgn:id":7391640,
    "tgn:name":"Roma, Arroyo",
    "tgn:placetype":[
        "aat:300266554",
        "aat:300008699"
    ]
},
  "bbox": [],
  "geometry": {"coordinates":[-106.433333,30.95],"type":"Point"}
}