{
  "id": 1069979,
  "type": "Feature",
  "properties": {
    "tgn:hierarchy":[
        "tgn:1069979",
        "tgn:1000004",
        "tgn:7002085",
        "tgn:1000111",
        "tgn:7029392"
    ],
    "tgn:id":1069979,
    "tgn:name":"Liujiagou",
    "tgn:placetype":[
        "aat:300008347"
    ]
},
  "bbox": [],
  "geometry": {"coordinates":[120.8667,37.7667],"type":"Point"}
}