{
  "id": 2589641,
  "type": "Feature",
  "properties": {
    "tgn:hierarchy":[
        "tgn:2589641",
        "tgn:1000001",
        "tgn:2002368",
        "tgn:7012149",
        "tgn:7007923",
        "tgn:7029392"
    ],
    "tgn:id":2589641,
    "tgn:name":"Point Of Rocks",
    "tgn:placetype":[
        "aat:300008347"
    ]
},
  "bbox": [],
  "geometry": {"coordinates":[-106.3833,42.2167],"type":"Point"}
}