{
  "id": 2223599,
  "type": "Feature",
  "properties": {
    "tgn:hierarchy":[
        "tgn:2223599",
        "tgn:1000001",
        "tgn:7012149",
        "tgn:2001164",
        "tgn:7007522",
        "tgn:7029392"
    ],
    "tgn:id":2223599,
    "tgn:name":"Carter Creek",
    "tgn:placetype":[
        "aat:300008706"
    ]
},
  "bbox": [],
  "geometry": {"coordinates":[-91.2667,31.0667],"type":"Point"}
}