{
  "id": 2137311,
  "type": "Feature",
  "properties": {
    "tgn:hierarchy":[
        "tgn:2137311",
        "tgn:1000001",
        "tgn:1002934",
        "tgn:7012149",
        "tgn:7007565",
        "tgn:7029392"
    ],
    "tgn:id":2137311,
    "tgn:name":"Armstrong",
    "tgn:placetype":[
        "aat:300008347"
    ]
},
  "bbox": [],
  "geometry": {"coordinates":[-74.6833,41.1333],"type":"Point"}
}