{
  "id": 2666434,
  "type": "Feature",
  "properties": {
    "tgn:hierarchy":[
        "tgn:2666434",
        "tgn:1000001",
        "tgn:7012149",
        "tgn:1002358",
        "tgn:7007710",
        "tgn:7029392"
    ],
    "tgn:id":2666434,
    "tgn:name":"Sixmile Creek",
    "tgn:placetype":[
        "aat:300008706"
    ]
},
  "bbox": [],
  "geometry": {"coordinates":[-79.8833,42.0667],"type":"Point"}
}