<<<<<<< HEAD
{
  "id": 2769420,
  "type": "Feature",
  "properties": {
    "tgn:hierarchy":[
        "tgn:2769420",
        "tgn:1000001",
        "tgn:7012149",
        "tgn:2002122",
        "tgn:7007827",
        "tgn:7029392"
    ],
    "tgn:id":2769420,
    "tgn:name":"Widdop Mountain",
    "tgn:placetype":[
        "aat:300008798"
    ]
},
  "bbox": [],
  "geometry": {"coordinates":[-110.0667,40.95],"type":"Point"}
}
=======
{"geometry":{"type":"Point","coordinates":[-110.066700,40.950000]},"type":"Feature","properties":{"hierarchy":["tgn:2769420","tgn:1000001","tgn:7012149","tgn:2002122","tgn:7007827","tgn:7029392"],"placetype":["aat:300008798"],"id":2769420,"name:xx":"Widdop Mountain"}}
>>>>>>> 03f74aca74312dbeaf24d7e61306dd6a786dc3d0
