<<<<<<< HEAD
{
  "id": 7020727,
  "type": "Feature",
  "properties": {
    "tgn:hierarchy":[
        "tgn:7020727",
        "tgn:1000001",
        "tgn:7016172",
        "tgn:7012149",
        "tgn:2000162",
        "tgn:7029392"
    ],
    "tgn:id":7020727,
    "tgn:name":"Rock House Hollow",
    "tgn:placetype":[
        "aat:300008761"
    ]
},
  "bbox": [],
  "geometry": {"coordinates":[-93.0833,35.5167],"type":"Point"}
}
=======
{"geometry":{"type":"Point","coordinates":[-93.083300,35.516700]},"type":"Feature","properties":{"hierarchy":["tgn:7020727","tgn:1000001","tgn:7016172","tgn:7012149","tgn:2000162","tgn:7029392"],"placetype":["aat:300008761"],"id":7020727,"name:xx":"Rock House Hollow"}}
>>>>>>> 03f74aca74312dbeaf24d7e61306dd6a786dc3d0
