{
  "id": 7536030,
  "type": "Feature",
  "properties": {
    "tgn:hierarchy":[
        "tgn:7536030",
        "tgn:7001242",
        "tgn:1001059",
        "tgn:7016833",
        "tgn:7029392"
    ],
    "tgn:id":7536030,
    "tgn:name:en":"Kafr al Qa\u015f\u0101l\u012b",
    "tgn:placetype":[
        "aat:300008347"
    ]
},
  "bbox": [],
  "geometry": {"coordinates":[31.343105,31.101395],"type":"Point"}
}