{
  "id": 2781745,
  "type": "Feature",
  "properties": {
    "tgn:hierarchy":[
        "tgn:2781745",
        "tgn:1000001",
        "tgn:7012149",
        "tgn:2001508",
        "tgn:7007709",
        "tgn:7029392"
    ],
    "tgn:id":2781745,
    "tgn:name":"Woods Branch",
    "tgn:placetype":[
        "aat:300008699"
    ]
},
  "bbox": [],
  "geometry": {"coordinates":[-83.0833,35.2667],"type":"Point"}
}