{
  "id": 1037840,
  "type": "Feature",
  "properties": {
    "tgn:hierarchy":[
        "tgn:1037840",
        "tgn:1000003",
        "tgn:7003685",
        "tgn:7000084",
        "tgn:7029392"
    ],
    "tgn:id":1037840,
    "tgn:name":"Thallwitz",
    "tgn:placetype":[
        "aat:300008347"
    ]
},
  "bbox": [],
  "geometry": {"coordinates":[12.683333,51.433333],"type":"Point"}
}