{
  "id": 2645547,
  "type": "Feature",
  "properties": {
    "tgn:hierarchy":[
        "tgn:2645547",
        "tgn:2002131",
        "tgn:1000001",
        "tgn:7012149",
        "tgn:7007828",
        "tgn:7029392"
    ],
    "tgn:id":2645547,
    "tgn:name":"Sawdust Pond",
    "tgn:placetype":[
        "aat:300008680"
    ]
},
  "bbox": [],
  "geometry": {"coordinates":[-71.9667,44.7167],"type":"Point"}
}