<<<<<<< HEAD
{
  "id": 7358396,
  "type": "Feature",
  "properties": {
    "tgn:hierarchy":[
        "tgn:7358396",
        "tgn:7005581",
        "tgn:1000001",
        "tgn:7005560",
        "tgn:7029392"
    ],
    "tgn:id":7358396,
    "tgn:name":"Colonia Santa Rosa",
    "tgn:placetype":[
        "aat:300008347"
    ]
},
  "bbox": [],
  "geometry": {"coordinates":[-108.033333,30.116667],"type":"Point"}
}
=======
{"geometry":{"type":"Point","coordinates":[-108.033333,30.116667]},"type":"Feature","properties":{"hierarchy":["tgn:7358396","tgn:7005581","tgn:1000001","tgn:7005560","tgn:7029392"],"placetype":["aat:300008347"],"id":7358396,"name:xx":"Colonia Santa Rosa"}}
>>>>>>> 03f74aca74312dbeaf24d7e61306dd6a786dc3d0
