{
  "id": 2320381,
  "type": "Feature",
  "properties": {
    "tgn:hierarchy":[
        "tgn:2320381",
        "tgn:1000001",
        "tgn:7012149",
        "tgn:7007157",
        "tgn:7014475",
        "tgn:7029392"
    ],
    "tgn:id":2320381,
    "tgn:name":"Evergreen Canal",
    "tgn:placetype":[
        "aat:300006075"
    ]
},
  "bbox": [],
  "geometry": {"coordinates":[-121.7833,37.2833],"type":"Point"}
}