{
  "id": 2597075,
  "type": "Feature",
  "properties": {
    "tgn:hierarchy":[
        "tgn:2597075",
        "tgn:1000001",
        "tgn:7012149",
        "tgn:2000852",
        "tgn:7007255",
        "tgn:7029392"
    ],
    "tgn:id":2597075,
    "tgn:name":"Powers Hollow",
    "tgn:placetype":[
        "aat:300008761"
    ]
},
  "bbox": [],
  "geometry": {"coordinates":[-84.05,36.6667],"type":"Point"}
}