{
  "id": 1112585,
  "type": "Feature",
  "properties": {
    "tgn:hierarchy":[
        "tgn:1112585",
        "tgn:7019034",
        "tgn:1000004",
        "tgn:1003406",
        "tgn:7018214",
        "tgn:7002435",
        "tgn:7029392"
    ],
    "tgn:id":1112585,
    "tgn:name":"Aniva, Zaliv",
    "tgn:placetype":[
        "aat:300132316"
    ]
},
  "bbox": [],
  "geometry": {"coordinates":[142.75,46.25],"type":"Point"}
}