{
  "id": 7291011,
  "type": "Feature",
  "properties": {
    "tgn:hierarchy":[
        "tgn:7291011",
        "tgn:7002464",
        "tgn:1000049",
        "tgn:1000002",
        "tgn:7029392"
    ],
    "tgn:id":7291011,
    "tgn:name":"Culco, Quebrada",
    "tgn:placetype":[
        "aat:300008699"
    ]
},
  "bbox": [],
  "geometry": {"coordinates":[-69.05,-18.583333],"type":"Point"}
}