{
  "id": 2476302,
  "type": "Feature",
  "properties": {
    "tgn:hierarchy":[
        "tgn:2476302",
        "tgn:1000001",
        "tgn:7012149",
        "tgn:2000476",
        "tgn:7007250",
        "tgn:7029392"
    ],
    "tgn:id":2476302,
    "tgn:name":"Lunch Creek",
    "tgn:placetype":[
        "aat:300008706"
    ]
},
  "bbox": [],
  "geometry": {"coordinates":[-114.6667,45.65],"type":"Point"}
}