{
  "id": 2218565,
  "type": "Feature",
  "properties": {
    "tgn:hierarchy":[
        "tgn:2218565",
        "tgn:1000001",
        "tgn:7016172",
        "tgn:7012149",
        "tgn:2000139",
        "tgn:7029392"
    ],
    "tgn:id":2218565,
    "tgn:name":"Cane Creek",
    "tgn:placetype":[
        "aat:300008706"
    ]
},
  "bbox": [],
  "geometry": {"coordinates":[-92.0667,34.0833],"type":"Point"}
}