{
  "id": 2771021,
  "type": "Feature",
  "properties": {
    "tgn:hierarchy":[
        "tgn:2771021",
        "tgn:1000001",
        "tgn:7012149",
        "tgn:2001872",
        "tgn:7007825",
        "tgn:7029392"
    ],
    "tgn:id":2771021,
    "tgn:name":"Wildcat Hollow",
    "tgn:placetype":[
        "aat:300008761"
    ]
},
  "bbox": [],
  "geometry": {"coordinates":[-88.1333,35.05],"type":"Point"}
}