{
  "id": 2203549,
  "type": "Feature",
  "properties": {
    "tgn:hierarchy":[
        "tgn:2203549",
        "tgn:1000001",
        "tgn:7012149",
        "tgn:2000539",
        "tgn:7007251",
        "tgn:7029392"
    ],
    "tgn:id":2203549,
    "tgn:name":"Buckley Creek",
    "tgn:placetype":[
        "aat:300008706"
    ]
},
  "bbox": [],
  "geometry": {"coordinates":[-88.8833,37.7667],"type":"Point"}
}