<<<<<<< HEAD
{
  "id": 2158750,
  "type": "Feature",
  "properties": {
    "tgn:hierarchy":[
        "tgn:2158750",
        "tgn:1000001",
        "tgn:7012149",
        "tgn:1002545",
        "tgn:7007157",
        "tgn:7029392"
    ],
    "tgn:id":2158750,
    "tgn:name":"Beck Canyon",
    "tgn:placetype":[
        "aat:300008761"
    ]
},
  "bbox": [],
  "geometry": {"coordinates":[-118.5667,35.35],"type":"Point"}
}
=======
{"geometry":{"type":"Point","coordinates":[-118.566700,35.350000]},"type":"Feature","properties":{"hierarchy":["tgn:2158750","tgn:1000001","tgn:7012149","tgn:1002545","tgn:7007157","tgn:7029392"],"placetype":["aat:300008761"],"id":2158750,"name:xx":"Beck Canyon"}}
>>>>>>> 03f74aca74312dbeaf24d7e61306dd6a786dc3d0
