{
  "id": 1008442,
  "type": "Feature",
  "properties": {
    "tgn:hierarchy":[
        "tgn:1008442",
        "tgn:1000004",
        "tgn:1001178",
        "tgn:1000135",
        "tgn:7029392"
    ],
    "tgn:id":1008442,
    "tgn:name":"Olutaya Island",
    "tgn:placetype":[
        "aat:300008791"
    ]
},
  "bbox": [],
  "geometry": {"coordinates":[122.8333,11.65],"type":"Point"}
}