{
  "id": 2711303,
  "type": "Feature",
  "properties": {
    "tgn:hierarchy":[
        "tgn:2711303",
        "tgn:1000001",
        "tgn:7012149",
        "tgn:2001854",
        "tgn:7007825",
        "tgn:7029392"
    ],
    "tgn:id":2711303,
    "tgn:name":"Tansi, Lake",
    "tgn:placetype":[
        "aat:300006191"
    ]
},
  "bbox": [],
  "geometry": {"coordinates":[-85.05,35.85],"type":"Point"}
}