{
  "id": 2639434,
  "type": "Feature",
  "properties": {
    "tgn:hierarchy":[
        "tgn:2639434",
        "tgn:1000001",
        "tgn:7012149",
        "tgn:2001769",
        "tgn:7007712",
        "tgn:7029392"
    ],
    "tgn:id":2639434,
    "tgn:name":"Salters Depot",
    "tgn:placetype":[
        "aat:300008347"
    ]
},
  "bbox": [],
  "geometry": {"coordinates":[-79.85,33.5833],"type":"Point"}
}