{
  "id": 7276423,
  "type": "Feature",
  "properties": {
    "tgn:hierarchy":[
        "tgn:7276423",
        "tgn:1001699",
        "tgn:1000049",
        "tgn:1000002",
        "tgn:7029392"
    ],
    "tgn:id":7276423,
    "tgn:name":"Taucol\u00f3n, Paso",
    "tgn:placetype":[
        "aat:300387026"
    ]
},
  "bbox": [],
  "geometry": {"coordinates":[-73.233333,-42.316667],"type":"Point"}
}