{
  "id": 2731715,
  "type": "Feature",
  "properties": {
    "tgn:hierarchy":[
        "tgn:2731715",
        "tgn:1000001",
        "tgn:7012149",
        "tgn:1002312",
        "tgn:7007709",
        "tgn:7029392"
    ],
    "tgn:id":2731715,
    "tgn:name":"Tulls",
    "tgn:placetype":[
        "aat:300008347"
    ]
},
  "bbox": [],
  "geometry": {"coordinates":[-76.0667,36.4833],"type":"Point"}
}