{
  "id": 7258531,
  "type": "Feature",
  "properties": {
    "tgn:hierarchy":[
        "tgn:7258531",
        "tgn:1000003",
        "tgn:7003624",
        "tgn:7016845",
        "tgn:7029392"
    ],
    "tgn:id":7258531,
    "tgn:name:nl":"Aldendriel",
    "tgn:placetype":[
        "aat:300006891"
    ]
},
  "bbox": [],
  "geometry": {"coordinates":[5.783333,51.683333],"type":"Point"}
}