{
  "id": 7256265,
  "type": "Feature",
  "properties": {
    "tgn:hierarchy":[
        "tgn:7256265",
        "tgn:7003456",
        "tgn:1000003",
        "tgn:1000063",
        "tgn:7018236",
        "tgn:7029392"
    ],
    "tgn:id":7256265,
    "tgn:name":"Wespelarenhoek",
    "tgn:placetype":[
        "aat:300008347"
    ]
},
  "bbox": [],
  "geometry": {"coordinates":[4.616667,50.95],"type":"Point"}
}