{
  "id": 7392605,
  "type": "Feature",
  "properties": {
    "tgn:hierarchy":[
        "tgn:7392605",
        "tgn:1001853",
        "tgn:1000001",
        "tgn:7005560",
        "tgn:7029392"
    ],
    "tgn:id":7392605,
    "tgn:name":"Sacramento",
    "tgn:placetype":[
        "aat:300008347"
    ]
},
  "bbox": [],
  "geometry": {"coordinates":[-100.833333,29.033333],"type":"Point"}
}