{
  "id": 2011740,
  "type": "Feature",
  "properties": {
    "tgn:hierarchy":[
        "tgn:2011740",
        "tgn:1000001",
        "tgn:7012149",
        "tgn:7007157",
        "tgn:2000190",
        "tgn:7029392"
    ],
    "tgn:id":2011740,
    "tgn:name":"Henleyville",
    "tgn:placetype":[
        "aat:300008347",
        "aat:300387210"
    ]
},
  "bbox": [],
  "geometry": {"coordinates":[-122.3167,39.95],"type":"Point"}
}