{
  "id": 7490563,
  "type": "Feature",
  "properties": {
    "tgn:hierarchy":[
        "tgn:7490563",
        "tgn:1000004",
        "tgn:7492971",
        "tgn:1000141",
        "tgn:7029392"
    ],
    "tgn:id":7490563,
    "tgn:name":"Dehe",
    "tgn:placetype":[
        "aat:300008347"
    ]
},
  "bbox": [],
  "geometry": {"coordinates":[120.728611,21.998889],"type":"Point"}
}