{
  "id": 2735552,
  "type": "Feature",
  "properties": {
    "tgn:hierarchy":[
        "tgn:2735552",
        "tgn:1000001",
        "tgn:7012149",
        "tgn:2002337",
        "tgn:7007922",
        "tgn:7029392"
    ],
    "tgn:id":2735552,
    "tgn:name":"Twin Creek",
    "tgn:placetype":[
        "aat:300008706"
    ]
},
  "bbox": [],
  "geometry": {"coordinates":[-87.8333,45.2167],"type":"Point"}
}