{
  "id": 7261024,
  "type": "Feature",
  "properties": {
    "tgn:hierarchy":[
        "tgn:7261024",
        "tgn:1000003",
        "tgn:7003624",
        "tgn:7016845",
        "tgn:7029392"
    ],
    "tgn:id":7261024,
    "tgn:name:nl":"Groote Ketel",
    "tgn:placetype":[
        "aat:300387200"
    ]
},
  "bbox": [],
  "geometry": {"coordinates":[4.566667,51.65],"type":"Point"}
}