{
  "id": 7334319,
  "type": "Feature",
  "properties": {
    "tgn:hierarchy":[
        "tgn:7334319",
        "tgn:7002758",
        "tgn:7002821",
        "tgn:1000003",
        "tgn:1000095",
        "tgn:7029392"
    ],
    "tgn:id":7334319,
    "tgn:name":"El Patronato",
    "tgn:placetype":[
        "aat:300008347"
    ]
},
  "bbox": [],
  "geometry": {"coordinates":[-2.65,38.033333],"type":"Point"}
}