{
  "id": 2528866,
  "type": "Feature",
  "properties": {
    "tgn:hierarchy":[
        "tgn:2528866",
        "tgn:1000001",
        "tgn:2000680",
        "tgn:7012149",
        "tgn:7007254",
        "tgn:7029392"
    ],
    "tgn:id":2528866,
    "tgn:name":"Mud Creek",
    "tgn:placetype":[
        "aat:300008706"
    ]
},
  "bbox": [],
  "geometry": {"coordinates":[-97.3167,39.1167],"type":"Point"}
}