{
  "id": 2589611,
  "type": "Feature",
  "properties": {
    "tgn:hierarchy":[
        "tgn:2589611",
        "tgn:1000001",
        "tgn:7012149",
        "tgn:2000960",
        "tgn:7007520",
        "tgn:7029392"
    ],
    "tgn:id":2589611,
    "tgn:name":"Point Mountain",
    "tgn:placetype":[
        "aat:300008798"
    ]
},
  "bbox": [],
  "geometry": {"coordinates":[-90.2833,46.5667],"type":"Point"}
}