{
  "id": 2399444,
  "type": "Feature",
  "properties": {
    "tgn:hierarchy":[
        "tgn:2399444",
        "tgn:1000001",
        "tgn:2000460",
        "tgn:7012149",
        "tgn:7007250",
        "tgn:7029392"
    ],
    "tgn:id":2399444,
    "tgn:name":"Horn, Cape",
    "tgn:placetype":[
        "aat:300008850"
    ]
},
  "bbox": [],
  "geometry": {"coordinates":[-116.4833,47.9833],"type":"Point"}
}