{
  "id": 2482515,
  "type": "Feature",
  "properties": {
    "tgn:hierarchy":[
        "tgn:2482515",
        "tgn:1000001",
        "tgn:2001416",
        "tgn:7012149",
        "tgn:7007526",
        "tgn:7029392"
    ],
    "tgn:id":2482515,
    "tgn:name":"Lanter Canyon",
    "tgn:placetype":[
        "aat:300008761"
    ]
},
  "bbox": [],
  "geometry": {"coordinates":[-114.7333,38.65],"type":"Point"}
}