{
  "id": 7212355,
  "type": "Feature",
  "properties": {
    "tgn:hierarchy":[
        "tgn:7212355",
        "tgn:1000003",
        "tgn:7003678",
        "tgn:7000084",
        "tgn:7029392"
    ],
    "tgn:id":7212355,
    "tgn:name":"B\u00f6dde-Berg",
    "tgn:placetype":[
        "aat:300008777"
    ]
},
  "bbox": [],
  "geometry": {"coordinates":[8.866667,51.016667],"type":"Point"}
}