<<<<<<< HEAD
{
  "id": 2158722,
  "type": "Feature",
  "properties": {
    "tgn:hierarchy":[
        "tgn:2158722",
        "tgn:1000001",
        "tgn:7012149",
        "tgn:2002384",
        "tgn:7007923",
        "tgn:7029392"
    ],
    "tgn:id":2158722,
    "tgn:name":"Bechler Canyon",
    "tgn:placetype":[
        "aat:300008761"
    ]
},
  "bbox": [],
  "geometry": {"coordinates":[-110.8833,44.2833],"type":"Point"}
}
=======
{"geometry":{"type":"Point","coordinates":[-110.883300,44.283300]},"type":"Feature","properties":{"hierarchy":["tgn:2158722","tgn:1000001","tgn:7012149","tgn:2002384","tgn:7007923","tgn:7029392"],"placetype":["aat:300008761"],"id":2158722,"name:xx":"Bechler Canyon"}}
>>>>>>> 03f74aca74312dbeaf24d7e61306dd6a786dc3d0
