<<<<<<< HEAD
{
  "id": 7489413,
  "type": "Feature",
  "properties": {
    "tgn:hierarchy":[
        "tgn:7489413",
        "tgn:1000004",
        "tgn:7001014",
        "tgn:1000141",
        "tgn:7029392"
    ],
    "tgn:id":7489413,
    "tgn:name":"Guogang",
    "tgn:placetype":[
        "aat:300008347"
    ]
},
  "bbox": [],
  "geometry": {"coordinates":[120.191389,23.576389],"type":"Point"}
}
=======
{"geometry":{"type":"Point","coordinates":[120.191389,23.576389]},"type":"Feature","properties":{"hierarchy":["tgn:7489413","tgn:1000004","tgn:7001014","tgn:1000141","tgn:7029392"],"placetype":["aat:300008347"],"id":7489413,"name:xx":"Guogang"}}
>>>>>>> 03f74aca74312dbeaf24d7e61306dd6a786dc3d0
