<<<<<<< HEAD
{
  "id": 7179557,
  "type": "Feature",
  "properties": {
    "tgn:hierarchy":[
        "tgn:7179557",
        "tgn:1000003",
        "tgn:7003676",
        "tgn:7000084",
        "tgn:7029392"
    ],
    "tgn:id":7179557,
    "tgn:name":"Hameln, Stadtforst",
    "tgn:placetype":[
        "aat:300008863"
    ]
},
  "bbox": [],
  "geometry": {"coordinates":[9.316667,52.083333],"type":"Point"}
}
=======
{"geometry":{"type":"Point","coordinates":[9.316667,52.083333]},"type":"Feature","properties":{"hierarchy":["tgn:7179557","tgn:1000003","tgn:7003676","tgn:7000084","tgn:7029392"],"placetype":["aat:300008863"],"id":7179557,"name:xx":"Hameln, Stadtforst"}}
>>>>>>> 03f74aca74312dbeaf24d7e61306dd6a786dc3d0
