{
  "id": 7319644,
  "type": "Feature",
  "properties": {
    "tgn:hierarchy":[
        "tgn:7319644",
        "tgn:1001708",
        "tgn:1000049",
        "tgn:1000002",
        "tgn:7029392"
    ],
    "tgn:id":7319644,
    "tgn:name":"Agua de Los Barrera",
    "tgn:placetype":[
        "aat:300387200"
    ]
},
  "bbox": [],
  "geometry": {"coordinates":[-70.75,-32.933333],"type":"Point"}
}