<<<<<<< HEAD
{
  "id": 2334928,
  "type": "Feature",
  "properties": {
    "tgn:hierarchy":[
        "tgn:2334928",
        "tgn:1000001",
        "tgn:7006451",
        "tgn:2000093",
        "tgn:7012149",
        "tgn:7029392"
    ],
    "tgn:id":2334928,
    "tgn:name":"Forks Butte",
    "tgn:placetype":[
        "aat:300008798"
    ]
},
  "bbox": [],
  "geometry": {"coordinates":[-110.2,33.7167],"type":"Point"}
}
=======
{"geometry":{"type":"Point","coordinates":[-110.200000,33.716700]},"type":"Feature","properties":{"hierarchy":["tgn:2334928","tgn:1000001","tgn:7006451","tgn:2000093","tgn:7012149","tgn:7029392"],"placetype":["aat:300008798"],"id":2334928,"name:xx":"Forks Butte"}}
>>>>>>> 03f74aca74312dbeaf24d7e61306dd6a786dc3d0
