{
  "id": 2783842,
  "type": "Feature",
  "properties": {
    "tgn:hierarchy":[
        "tgn:2783842",
        "tgn:1000001",
        "tgn:7012149",
        "tgn:2002125",
        "tgn:7007827",
        "tgn:7029392"
    ],
    "tgn:id":2783842,
    "tgn:name":"Wyoming Tunnel",
    "tgn:placetype":[
        "aat:300000390"
    ]
},
  "bbox": [],
  "geometry": {"coordinates":[-111.6167,40.5333],"type":"Point"}
}