{
  "id": 7152670,
  "type": "Feature",
  "properties": {
    "tgn:hierarchy":[
        "tgn:7152670",
        "tgn:1000003",
        "tgn:7003688",
        "tgn:7000084",
        "tgn:7029392"
    ],
    "tgn:id":7152670,
    "tgn:name":"J\u00e4gerslust",
    "tgn:placetype":[
        "aat:300000206"
    ]
},
  "bbox": [],
  "geometry": {"coordinates":[9.383333,54.766667],"type":"Point"}
}