{
  "id": 7522286,
  "type": "Feature",
  "properties": {
    "tgn:hierarchy":[
        "tgn:7522286",
        "tgn:7001242",
        "tgn:7016833",
        "tgn:7001335",
        "tgn:7029392"
    ],
    "tgn:id":7522286,
    "tgn:name:en":"Mersa Abu Samra",
    "tgn:placetype":[
        "aat:300386968"
    ]
},
  "bbox": [],
  "geometry": {"coordinates":[28.195033,31.083442],"type":"Point"}
}