{
  "id": 2168702,
  "type": "Feature",
  "properties": {
    "tgn:hierarchy":[
        "tgn:2168702",
        "tgn:1000001",
        "tgn:7012149",
        "tgn:7007568",
        "tgn:7029392"
    ],
    "tgn:id":2168702,
    "tgn:name":"Big Hollow",
    "tgn:placetype":[
        "aat:300008761"
    ]
},
  "bbox": [],
  "geometry": {"coordinates":[-75.4333,42.1167],"type":"Point"}
}