{
  "id": 2188539,
  "type": "Feature",
  "properties": {
    "tgn:hierarchy":[
        "tgn:2188539",
        "tgn:1000001",
        "tgn:7012149",
        "tgn:2002124",
        "tgn:7007827",
        "tgn:7029392"
    ],
    "tgn:id":2188539,
    "tgn:name":"Bottle Hollow Reservoir",
    "tgn:placetype":[
        "aat:300006191"
    ]
},
  "bbox": [],
  "geometry": {"coordinates":[-109.85,40.2833],"type":"Point"}
}