<<<<<<< HEAD
{
  "id": 7058235,
  "type": "Feature",
  "properties": {
    "tgn:hierarchy":[
        "tgn:7058235",
        "tgn:1003483",
        "tgn:1000003",
        "tgn:7003240",
        "tgn:1000080",
        "tgn:7029392"
    ],
    "tgn:id":7058235,
    "tgn:name":"Antico",
    "tgn:placetype":[
        "aat:300008347"
    ]
},
  "bbox": [],
  "geometry": {"coordinates":[12.3,43.85],"type":"Point"}
}
=======
{"geometry":{"type":"Point","coordinates":[12.300000,43.850000]},"type":"Feature","properties":{"hierarchy":["tgn:7058235","tgn:1003483","tgn:1000003","tgn:7003240","tgn:1000080","tgn:7029392"],"placetype":["aat:300008347"],"id":7058235,"name:xx":"Antico"}}
>>>>>>> 03f74aca74312dbeaf24d7e61306dd6a786dc3d0
