{
  "id": 1069658,
  "type": "Feature",
  "properties": {
    "tgn:hierarchy":[
        "tgn:1069658",
        "tgn:1000004",
        "tgn:7018118",
        "tgn:1000111",
        "tgn:7029392"
    ],
    "tgn:id":1069658,
    "tgn:name":"Lanping",
    "tgn:placetype":[
        "aat:300008347"
    ]
},
  "bbox": [],
  "geometry": {"coordinates":[99.4167,26.4167],"type":"Point"}
}