{
  "id": 2701273,
  "type": "Feature",
  "properties": {
    "tgn:hierarchy":[
        "tgn:2701273",
        "tgn:2000919",
        "tgn:1000001",
        "tgn:7012149",
        "tgn:7007515",
        "tgn:7029392"
    ],
    "tgn:id":2701273,
    "tgn:name":"Sugar Loaf",
    "tgn:placetype":[
        "aat:300008798"
    ]
},
  "bbox": [],
  "geometry": {"coordinates":[-67.8833,46.35],"type":"Point"}
}