<<<<<<< HEAD
{
  "id": 2339799,
  "type": "Feature",
  "properties": {
    "tgn:hierarchy":[
        "tgn:2339799",
        "tgn:1000001",
        "tgn:7016172",
        "tgn:2000112",
        "tgn:7012149",
        "tgn:7029392"
    ],
    "tgn:id":2339799,
    "tgn:name":"Freeman Branch",
    "tgn:placetype":[
        "aat:300008699"
    ]
},
  "bbox": [],
  "geometry": {"coordinates":[-93.55,36.3833],"type":"Point"}
}
=======
{"geometry":{"type":"Point","coordinates":[-93.550000,36.383300]},"type":"Feature","properties":{"hierarchy":["tgn:2339799","tgn:1000001","tgn:7016172","tgn:2000112","tgn:7012149","tgn:7029392"],"placetype":["aat:300008699"],"id":2339799,"name:xx":"Freeman Branch"}}
>>>>>>> 03f74aca74312dbeaf24d7e61306dd6a786dc3d0
