<<<<<<< HEAD
{
  "id": 7482098,
  "type": "Feature",
  "properties": {
    "tgn:hierarchy":[
        "tgn:7482098",
        "tgn:1000004",
        "tgn:7001013",
        "tgn:1000141",
        "tgn:7029392"
    ],
    "tgn:id":7482098,
    "tgn:name":"Liangwu",
    "tgn:placetype":[
        "aat:300008347"
    ]
},
  "bbox": [],
  "geometry": {"coordinates":[121.2,24.99],"type":"Point"}
}
=======
{"geometry":{"type":"Point","coordinates":[121.200000,24.990000]},"type":"Feature","properties":{"hierarchy":["tgn:7482098","tgn:1000004","tgn:7001013","tgn:1000141","tgn:7029392"],"placetype":["aat:300008347"],"id":7482098,"name:xx":"Liangwu"}}
>>>>>>> 03f74aca74312dbeaf24d7e61306dd6a786dc3d0
