{
  "id": 7572189,
  "type": "Feature",
  "properties": {
    "tgn:hierarchy":[
        "tgn:7572189",
        "tgn:1000004",
        "tgn:7000198",
        "tgn:7016722",
        "tgn:7029392"
    ],
    "tgn:id":7572189,
    "tgn:name:en":"Jharahi Nad\u012b",
    "tgn:placetype":[
        "aat:300008699"
    ]
},
  "bbox": [],
  "geometry": {"coordinates":[84.158061,26.072001],"type":"Point"}
}