{
  "id": 7590598,
  "type": "Feature",
  "properties": {
    "tgn:hierarchy":[
        "tgn:7590598",
        "tgn:1000004",
        "tgn:7000198",
        "tgn:7000799",
        "tgn:7029392"
    ],
    "tgn:id":7590598,
    "tgn:name:en":"Nainsukh",
    "tgn:placetype":[
        "aat:300008347"
    ]
},
  "bbox": [],
  "geometry": {"coordinates":[74.37373,33.782169],"type":"Point"}
}