{
  "id": 2438996,
  "type": "Feature",
  "properties": {
    "tgn:hierarchy":[
        "tgn:2438996",
        "tgn:1000001",
        "tgn:7012149",
        "tgn:1003041",
        "tgn:7007710",
        "tgn:7029392"
    ],
    "tgn:id":2438996,
    "tgn:name":"Kintner Hill",
    "tgn:placetype":[
        "aat:300008798"
    ]
},
  "bbox": [],
  "geometry": {"coordinates":[-75.95,41.5833],"type":"Point"}
}