<<<<<<< HEAD
{
  "id": 7363395,
  "type": "Feature",
  "properties": {
    "tgn:hierarchy":[
        "tgn:7363395",
        "tgn:1000001",
        "tgn:1001960",
        "tgn:7005560",
        "tgn:7029392"
    ],
    "tgn:id":7363395,
    "tgn:name":"Rancho El Alamo",
    "tgn:placetype":[
        "aat:300000241"
    ]
},
  "bbox": [],
  "geometry": {"coordinates":[-110.666667,30.3],"type":"Point"}
}
=======
{"geometry":{"type":"Point","coordinates":[-110.666667,30.300000]},"type":"Feature","properties":{"hierarchy":["tgn:7363395","tgn:1000001","tgn:1001960","tgn:7005560","tgn:7029392"],"placetype":["aat:300000241"],"id":7363395,"name:xx":"Rancho El Alamo"}}
>>>>>>> 03f74aca74312dbeaf24d7e61306dd6a786dc3d0
