{
  "id": 7581681,
  "type": "Feature",
  "properties": {
    "tgn:hierarchy":[
        "tgn:7581681",
        "tgn:1000004",
        "tgn:7031781",
        "tgn:7000198",
        "tgn:7029392"
    ],
    "tgn:id":7581681,
    "tgn:name:en":"Tomia",
    "tgn:placetype":[
        "aat:300008347"
    ]
},
  "bbox": [],
  "geometry": {"coordinates":[83.884086,22.946897],"type":"Point"}
}