{
  "id": 1064211,
  "type": "Feature",
  "properties": {
    "tgn:hierarchy":[
        "tgn:1064211",
        "tgn:7003739",
        "tgn:1000003",
        "tgn:7011731",
        "tgn:7029392"
    ],
    "tgn:id":1064211,
    "tgn:name":"M\u00f6hlin",
    "tgn:placetype":[
        "aat:300008347"
    ]
},
  "bbox": [],
  "geometry": {"coordinates":[7.85,47.5667],"type":"Point"}
}