{
  "id": 2621489,
  "type": "Feature",
  "properties": {
    "tgn:hierarchy":[
        "tgn:2621489",
        "tgn:1000001",
        "tgn:7012149",
        "tgn:2001304",
        "tgn:7007524",
        "tgn:7029392"
    ],
    "tgn:id":2621489,
    "tgn:name":"Roaring Fork Seepay Creek",
    "tgn:placetype":[
        "aat:300008706"
    ]
},
  "bbox": [],
  "geometry": {"coordinates":[-114.55,47.2667],"type":"Point"}
}