{
  "id": 7322551,
  "type": "Feature",
  "properties": {
    "tgn:hierarchy":[
        "tgn:7322551",
        "tgn:7002816",
        "tgn:1001647",
        "tgn:1000003",
        "tgn:1000095",
        "tgn:7029392"
    ],
    "tgn:id":7322551,
    "tgn:name":"San Juan, Puerto de",
    "tgn:placetype":[
        "aat:300259572"
    ]
},
  "bbox": [],
  "geometry": {"coordinates":[-4.55,38.583333],"type":"Point"}
}