{
  "id": 2211429,
  "type": "Feature",
  "properties": {
    "tgn:hierarchy":[
        "tgn:2211429",
        "tgn:1000001",
        "tgn:7012149",
        "tgn:2002276",
        "tgn:7013961",
        "tgn:7029392"
    ],
    "tgn:id":2211429,
    "tgn:name":"Butter Run",
    "tgn:placetype":[
        "aat:300008699"
    ]
},
  "bbox": [],
  "geometry": {"coordinates":[-80.7667,39.8833],"type":"Point"}
}