{
  "id": 2708213,
  "type": "Feature",
  "properties": {
    "tgn:hierarchy":[
        "tgn:2708213",
        "tgn:1000001",
        "tgn:7012149",
        "tgn:2002291",
        "tgn:7013961",
        "tgn:7029392"
    ],
    "tgn:id":2708213,
    "tgn:name":"Switchback Hollow",
    "tgn:placetype":[
        "aat:300008761"
    ]
},
  "bbox": [],
  "geometry": {"coordinates":[-79.5833,38.7167],"type":"Point"}
}