<<<<<<< HEAD
{
  "id": 7056812,
  "type": "Feature",
  "properties": {
    "tgn:hierarchy":[
        "tgn:7056812",
        "tgn:7003135",
        "tgn:1000003",
        "tgn:7003080",
        "tgn:1000080",
        "tgn:7029392"
    ],
    "tgn:id":7056812,
    "tgn:name":"Belmonte Castello",
    "tgn:placetype":[
        "aat:300008347"
    ]
},
  "bbox": [],
  "geometry": {"coordinates":[13.8,41.583333],"type":"Point"}
}
=======
{"geometry":{"type":"Point","coordinates":[13.800000,41.583333]},"type":"Feature","properties":{"hierarchy":["tgn:7056812","tgn:7003135","tgn:1000003","tgn:7003080","tgn:1000080","tgn:7029392"],"placetype":["aat:300008347"],"id":7056812,"name:xx":"Belmonte Castello"}}
>>>>>>> 03f74aca74312dbeaf24d7e61306dd6a786dc3d0
