{
  "id": 2723267,
  "type": "Feature",
  "properties": {
    "tgn:hierarchy":[
        "tgn:2723267",
        "tgn:1000001",
        "tgn:7006451",
        "tgn:7012149",
        "tgn:2000103",
        "tgn:7029392"
    ],
    "tgn:id":2723267,
    "tgn:name":"Toad Tank",
    "tgn:placetype":[
        "aat:300006191"
    ]
},
  "bbox": [],
  "geometry": {"coordinates":[-112.9167,35.1167],"type":"Point"}
}