{
  "id": 1045297,
  "type": "Feature",
  "properties": {
    "tgn:hierarchy":[
        "tgn:1045297",
        "tgn:7002996",
        "tgn:1000003",
        "tgn:7002997",
        "tgn:1000080",
        "tgn:7029392"
    ],
    "tgn:id":1045297,
    "tgn:name":"Maserada sul Piave",
    "tgn:placetype":[
        "aat:300008347"
    ]
},
  "bbox": [],
  "geometry": {"coordinates":[12.313611,45.756389],"type":"Point"}
}