{
  "id": 1045496,
  "type": "Feature",
  "properties": {
    "tgn:hierarchy":[
        "tgn:1045496",
        "tgn:1003483",
        "tgn:1000003",
        "tgn:7003240",
        "tgn:1000080",
        "tgn:7029392"
    ],
    "tgn:id":1045496,
    "tgn:name":"Montecchio",
    "tgn:placetype":[
        "aat:300008347"
    ]
},
  "bbox": [],
  "geometry": {"coordinates":[12.766667,43.85],"type":"Point"}
}