{
  "id": 2262826,
  "type": "Feature",
  "properties": {
    "tgn:hierarchy":[
        "tgn:2262826",
        "tgn:1000001",
        "tgn:1002665",
        "tgn:7012149",
        "tgn:7007517",
        "tgn:7029392"
    ],
    "tgn:id":2262826,
    "tgn:name":"Cowassock Brook",
    "tgn:placetype":[
        "aat:300008699"
    ]
},
  "bbox": [],
  "geometry": {"coordinates":[-71.4667,42.2667],"type":"Point"}
}