{
  "id": 2690939,
  "type": "Feature",
  "properties": {
    "tgn:hierarchy":[
        "tgn:2690939",
        "tgn:1000001",
        "tgn:7012149",
        "tgn:2002381",
        "tgn:7007923",
        "tgn:7029392"
    ],
    "tgn:id":2690939,
    "tgn:name":"Stanko Draw",
    "tgn:placetype":[
        "aat:300008761"
    ]
},
  "bbox": [],
  "geometry": {"coordinates":[-106.9167,44.65],"type":"Point"}
}