{
  "id": 7219876,
  "type": "Feature",
  "properties": {
    "tgn:hierarchy":[
        "tgn:7219876",
        "tgn:7011330",
        "tgn:7002674",
        "tgn:1000003",
        "tgn:1000074",
        "tgn:7029392"
    ],
    "tgn:id":7219876,
    "tgn:name":"Tsagk\u00e1ri",
    "tgn:placetype":[
        "aat:300266640"
    ]
},
  "bbox": [],
  "geometry": {"coordinates":[27.129444,36.795556],"type":"Point"}
}