{
  "id": 2435330,
  "type": "Feature",
  "properties": {
    "tgn:hierarchy":[
        "tgn:2435330",
        "tgn:7023902",
        "tgn:1000001",
        "tgn:7012149",
        "tgn:7007249",
        "tgn:7029392"
    ],
    "tgn:id":2435330,
    "tgn:name":"Kepuhi O Kahio Point",
    "tgn:placetype":[
        "aat:300008850"
    ]
},
  "bbox": [],
  "geometry": {"coordinates":[-155.6667,18.9667],"type":"Point"}
}