{
  "id": 2399450,
  "type": "Feature",
  "properties": {
    "tgn:hierarchy":[
        "tgn:2399450",
        "tgn:1000001",
        "tgn:7012149",
        "tgn:1002994",
        "tgn:7007708",
        "tgn:7029392"
    ],
    "tgn:id":2399450,
    "tgn:name":"Horn, Cape",
    "tgn:placetype":[
        "aat:300008798"
    ]
},
  "bbox": [],
  "geometry": {"coordinates":[-123.2333,45.7333],"type":"Point"}
}