<<<<<<< HEAD
{
  "id": 2331286,
  "type": "Feature",
  "properties": {
    "tgn:hierarchy":[
        "tgn:2331286",
        "tgn:1000001",
        "tgn:7012149",
        "tgn:2002277",
        "tgn:7013961",
        "tgn:7029392"
    ],
    "tgn:id":2331286,
    "tgn:name":"Flatfoot Creek",
    "tgn:placetype":[
        "aat:300008706"
    ]
},
  "bbox": [],
  "geometry": {"coordinates":[-82.1167,38.7167],"type":"Point"}
}
=======
{"geometry":{"type":"Point","coordinates":[-82.116700,38.716700]},"type":"Feature","properties":{"hierarchy":["tgn:2331286","tgn:1000001","tgn:7012149","tgn:2002277","tgn:7013961","tgn:7029392"],"placetype":["aat:300008706"],"id":2331286,"name:xx":"Flatfoot Creek"}}
>>>>>>> 03f74aca74312dbeaf24d7e61306dd6a786dc3d0
