{
  "id": 1067205,
  "type": "Feature",
  "properties": {
    "tgn:hierarchy":[
        "tgn:1067205",
        "tgn:1000004",
        "tgn:7016672",
        "tgn:1000111",
        "tgn:7029392"
    ],
    "tgn:id":1067205,
    "tgn:name":"Chenqiao",
    "tgn:placetype":[
        "aat:300008347"
    ]
},
  "bbox": [],
  "geometry": {"coordinates":[114.4833,34.9333],"type":"Point"}
}