{
  "id": 2602540,
  "type": "Feature",
  "properties": {
    "tgn:hierarchy":[
        "tgn:2602540",
        "tgn:1000001",
        "tgn:7012149",
        "tgn:2000476",
        "tgn:7007250",
        "tgn:7029392"
    ],
    "tgn:id":2602540,
    "tgn:name":"Quad Lake",
    "tgn:placetype":[
        "aat:300008680"
    ]
},
  "bbox": [],
  "geometry": {"coordinates":[-116.5667,45.3167],"type":"Point"}
}