<<<<<<< HEAD
{
  "id": 7487664,
  "type": "Feature",
  "properties": {
    "tgn:hierarchy":[
        "tgn:7487664",
        "tgn:7488858",
        "tgn:1000004",
        "tgn:1000141",
        "tgn:7029392"
    ],
    "tgn:id":7487664,
    "tgn:name":"Haomajiaban Xi",
    "tgn:placetype":[
        "aat:300008699"
    ]
},
  "bbox": [],
  "geometry": {"coordinates":[120.855833,23.529167],"type":"Point"}
}
=======
{"geometry":{"type":"Point","coordinates":[120.855833,23.529167]},"type":"Feature","properties":{"hierarchy":["tgn:7487664","tgn:7488858","tgn:1000004","tgn:1000141","tgn:7029392"],"placetype":["aat:300008699"],"id":7487664,"name:xx":"Haomajiaban Xi"}}
>>>>>>> 03f74aca74312dbeaf24d7e61306dd6a786dc3d0
