{
  "id": 2028798,
  "type": "Feature",
  "properties": {
    "tgn:hierarchy":[
        "tgn:2028798",
        "tgn:1000001",
        "tgn:7012149",
        "tgn:2000513",
        "tgn:7007251",
        "tgn:7029392"
    ],
    "tgn:id":2028798,
    "tgn:name":"Lis",
    "tgn:placetype":[
        "aat:300008347"
    ]
},
  "bbox": [],
  "geometry": {"coordinates":[-88.25,39.0167],"type":"Point"}
}