{
  "id": 7129595,
  "type": "Feature",
  "properties": {
    "tgn:hierarchy":[
        "tgn:7129595",
        "tgn:1000003",
        "tgn:7003676",
        "tgn:7000084",
        "tgn:7029392"
    ],
    "tgn:id":7129595,
    "tgn:name":"Melkschap",
    "tgn:placetype":[
        "aat:300000206"
    ]
},
  "bbox": [],
  "geometry": {"coordinates":[8.333333,53.533333],"type":"Point"}
}