{
  "id": 7360680,
  "type": "Feature",
  "properties": {
    "tgn:hierarchy":[
        "tgn:7360680",
        "tgn:1000001",
        "tgn:7005590",
        "tgn:7005560",
        "tgn:7029392"
    ],
    "tgn:id":7360680,
    "tgn:name":"C\u00f3poro",
    "tgn:placetype":[
        "aat:300008347"
    ]
},
  "bbox": [],
  "geometry": {"coordinates":[-103.166667,18.85],"type":"Point"}
}