<<<<<<< HEAD
{
  "id": 2762402,
  "type": "Feature",
  "properties": {
    "tgn:hierarchy":[
        "tgn:2762402",
        "tgn:1000001",
        "tgn:2000601",
        "tgn:7012149",
        "tgn:7007253",
        "tgn:7029392"
    ],
    "tgn:id":2762402,
    "tgn:name":"West Twin Lake",
    "tgn:placetype":[
        "aat:300008680"
    ]
},
  "bbox": [],
  "geometry": {"coordinates":[-93.7167,42.9333],"type":"Point"}
}
=======
{"geometry":{"type":"Point","coordinates":[-93.716700,42.933300]},"type":"Feature","properties":{"hierarchy":["tgn:2762402","tgn:1000001","tgn:2000601","tgn:7012149","tgn:7007253","tgn:7029392"],"placetype":["aat:300008680"],"id":2762402,"name:xx":"West Twin Lake"}}
>>>>>>> 03f74aca74312dbeaf24d7e61306dd6a786dc3d0
