{
  "id": 7191114,
  "type": "Feature",
  "properties": {
    "tgn:hierarchy":[
        "tgn:7191114",
        "tgn:7003669",
        "tgn:1000003",
        "tgn:7000084",
        "tgn:7029392"
    ],
    "tgn:id":7191114,
    "tgn:name":"Forstberg",
    "tgn:placetype":[
        "aat:300008777"
    ]
},
  "bbox": [],
  "geometry": {"coordinates":[11.016667,50.216667],"type":"Point"}
}