{
  "id": 7376765,
  "type": "Feature",
  "properties": {
    "tgn:hierarchy":[
        "tgn:7376765",
        "tgn:1000001",
        "tgn:7005589",
        "tgn:7005560",
        "tgn:7029392"
    ],
    "tgn:id":7376765,
    "tgn:name":"La Tinta",
    "tgn:placetype":[
        "aat:300008347"
    ]
},
  "bbox": [],
  "geometry": {"coordinates":[-100.133333,25.55],"type":"Point"}
}