{
  "id": 7453440,
  "type": "Feature",
  "properties": {
    "tgn:hierarchy":[
        "tgn:7453440",
        "tgn:7019094",
        "tgn:7002444",
        "tgn:1000003",
        "tgn:7008591",
        "tgn:7029392"
    ],
    "tgn:id":7453440,
    "tgn:name:en":"Craignish, Loch",
    "tgn:placetype":[
        "aat:300132316"
    ]
},
  "bbox": [],
  "geometry": {"coordinates":[-5.566667,56.15],"type":"Point"}
}