{
  "id": 7239551,
  "type": "Feature",
  "properties": {
    "tgn:hierarchy":[
        "tgn:7239551",
        "tgn:7003458",
        "tgn:1000003",
        "tgn:1000063",
        "tgn:7018236",
        "tgn:7029392"
    ],
    "tgn:id":7239551,
    "tgn:name":"Hollevoorde",
    "tgn:placetype":[
        "aat:300008347"
    ]
},
  "bbox": [],
  "geometry": {"coordinates":[3.13935,51.112561],"type":"Point"}
}