{
  "id": 2167276,
  "type": "Feature",
  "properties": {
    "tgn:hierarchy":[
        "tgn:2167276",
        "tgn:1000001",
        "tgn:7012149",
        "tgn:7007256",
        "tgn:7029392"
    ],
    "tgn:id":2167276,
    "tgn:name":"Big Constance Lake",
    "tgn:placetype":[
        "aat:300008680"
    ]
},
  "bbox": [],
  "geometry": {"coordinates":[-92.6333,29.5833],"type":"Point"}
}