{
  "id": 2674172,
  "type": "Feature",
  "properties": {
    "tgn:hierarchy":[
        "tgn:2674172",
        "tgn:1000001",
        "tgn:2336314",
        "tgn:7012149",
        "tgn:7014510",
        "tgn:7007920",
        "tgn:7029392"
    ],
    "tgn:id":2674172,
    "tgn:name":"Snowking Lake",
    "tgn:placetype":[
        "aat:300008680"
    ]
},
  "bbox": [],
  "geometry": {"coordinates":[-121.25,48.4167],"type":"Point"}
}