<<<<<<< HEAD
{
  "id": 2152184,
  "type": "Feature",
  "properties": {
    "tgn:hierarchy":[
        "tgn:2152184",
        "tgn:1000001",
        "tgn:7012149",
        "tgn:2002113",
        "tgn:7007827",
        "tgn:7029392"
    ],
    "tgn:id":2152184,
    "tgn:name":"Bay Bill Point",
    "tgn:placetype":[
        "aat:300008850"
    ]
},
  "bbox": [],
  "geometry": {"coordinates":[-112.7333,37.1667],"type":"Point"}
}
=======
{"geometry":{"type":"Point","coordinates":[-112.733300,37.166700]},"type":"Feature","properties":{"hierarchy":["tgn:2152184","tgn:1000001","tgn:7012149","tgn:2002113","tgn:7007827","tgn:7029392"],"placetype":["aat:300008850"],"id":2152184,"name:xx":"Bay Bill Point"}}
>>>>>>> 03f74aca74312dbeaf24d7e61306dd6a786dc3d0
