{
  "id": 7138884,
  "type": "Feature",
  "properties": {
    "tgn:hierarchy":[
        "tgn:7138884",
        "tgn:7003669",
        "tgn:1000003",
        "tgn:7000084",
        "tgn:7029392"
    ],
    "tgn:id":7138884,
    "tgn:name":"Libori",
    "tgn:placetype":[
        "aat:300000206"
    ]
},
  "bbox": [],
  "geometry": {"coordinates":[10.466667,47.783333],"type":"Point"}
}