{
  "id": 2705376,
  "type": "Feature",
  "properties": {
    "tgn:hierarchy":[
        "tgn:2705376",
        "tgn:7006450",
        "tgn:1000001",
        "tgn:7012149",
        "tgn:2000086",
        "tgn:7029392"
    ],
    "tgn:id":2705376,
    "tgn:name":"Surprise Creek",
    "tgn:placetype":[
        "aat:300008706"
    ]
},
  "bbox": [],
  "geometry": {"coordinates":[-144.2167,61.3833],"type":"Point"}
}