{
  "id": 2005592,
  "type": "Feature",
  "properties": {
    "tgn:hierarchy":[
        "tgn:2005592",
        "tgn:7002659",
        "tgn:1000001",
        "tgn:7012149",
        "tgn:2000058",
        "tgn:7029392"
    ],
    "tgn:id":2005592,
    "tgn:name":"Underwood",
    "tgn:placetype":[
        "aat:300008347"
    ]
},
  "bbox": [],
  "geometry": {"coordinates":[-86.85,33.15],"type":"Point"}
}