{
  "id": 2686101,
  "type": "Feature",
  "properties": {
    "tgn:hierarchy":[
        "tgn:2686101",
        "tgn:1000001",
        "tgn:7012149",
        "tgn:2001449",
        "tgn:7007566",
        "tgn:7029392"
    ],
    "tgn:id":2686101,
    "tgn:name":"Spring Canyon",
    "tgn:placetype":[
        "aat:300008761"
    ]
},
  "bbox": [],
  "geometry": {"coordinates":[-106.8667,36.4667],"type":"Point"}
}