{
  "id": 2652151,
  "type": "Feature",
  "properties": {
    "tgn:hierarchy":[
        "tgn:2652151",
        "tgn:1000001",
        "tgn:7012149",
        "tgn:1002597",
        "tgn:7007826",
        "tgn:7029392"
    ],
    "tgn:id":2652151,
    "tgn:name":"Sellers Lake",
    "tgn:placetype":[
        "aat:300008680"
    ]
},
  "bbox": [],
  "geometry": {"coordinates":[-96.3167,31.5167],"type":"Point"}
}