{
  "id": 7443343,
  "type": "Feature",
  "properties": {
    "tgn:hierarchy":[
        "tgn:7443343",
        "tgn:7002445",
        "tgn:7008116",
        "tgn:1000003",
        "tgn:7008591",
        "tgn:7029392"
    ],
    "tgn:id":7443343,
    "tgn:name:en":"Pol Bank, The",
    "tgn:placetype":[
        "aat:300387036"
    ]
},
  "bbox": [],
  "geometry": {"coordinates":[-6.466667,49.833333],"type":"Point"}
}