{
  "id": 7267608,
  "type": "Feature",
  "properties": {
    "tgn:hierarchy":[
        "tgn:7267608",
        "tgn:1000003",
        "tgn:7006951",
        "tgn:7016845",
        "tgn:7029392"
    ],
    "tgn:id":7267608,
    "tgn:name:nl":"Overwhere",
    "tgn:placetype":[
        "aat:300000745"
    ]
},
  "bbox": [],
  "geometry": {"coordinates":[4.966667,52.516667],"type":"Point"}
}