{
  "id": 2069517,
  "type": "Feature",
  "properties": {
    "tgn:hierarchy":[
        "tgn:2069517",
        "tgn:1000001",
        "tgn:1002206",
        "tgn:7012149",
        "tgn:7007568",
        "tgn:7029392"
    ],
    "tgn:id":2069517,
    "tgn:name":"Gulf Summit",
    "tgn:placetype":[
        "aat:300008347",
        "aat:300387210"
    ]
},
  "bbox": [],
  "geometry": {"coordinates":[-75.5167,42.0167],"type":"Point"}
}