{
  "id": 2679688,
  "type": "Feature",
  "properties": {
    "tgn:hierarchy":[
        "tgn:2679688",
        "tgn:1000001",
        "tgn:7012149",
        "tgn:7007923",
        "tgn:7029392"
    ],
    "tgn:id":2679688,
    "tgn:name":"South Fork Powder River",
    "tgn:placetype":[
        "aat:300008707"
    ]
},
  "bbox": [],
  "geometry": {"coordinates":[-107.4667,42.8833],"type":"Point"}
}