{
  "id": 7022418,
  "type": "Feature",
  "properties": {
    "tgn:hierarchy":[
        "tgn:7022418",
        "tgn:1000001",
        "tgn:7012149",
        "tgn:7029392"
    ],
    "tgn:id":7022418,
    "tgn:name":"Boggs Hollow",
    "tgn:placetype":[
        "aat:300008761"
    ]
},
  "bbox": [],
  "geometry": {"coordinates":[-82.9333,36.8333],"type":"Point"}
}