{
  "id": 2312284,
  "type": "Feature",
  "properties": {
    "tgn:hierarchy":[
        "tgn:2312284",
        "tgn:1000001",
        "tgn:7012149",
        "tgn:2000180",
        "tgn:7007157",
        "tgn:7029392"
    ],
    "tgn:id":2312284,
    "tgn:name":"Eighteenmile Creek",
    "tgn:placetype":[
        "aat:300008706"
    ]
},
  "bbox": [],
  "geometry": {"coordinates":[-123.8833,41.8833],"type":"Point"}
}