{
  "id": 7098481,
  "type": "Feature",
  "properties": {
    "tgn:hierarchy":[
        "tgn:7098481",
        "tgn:1000003",
        "tgn:7003676",
        "tgn:7000084",
        "tgn:7029392"
    ],
    "tgn:id":7098481,
    "tgn:name":"Silber-See",
    "tgn:placetype":[
        "aat:300008688"
    ]
},
  "bbox": [],
  "geometry": {"coordinates":[8.816667,53.483333],"type":"Point"}
}