{
  "id": 7045482,
  "type": "Feature",
  "properties": {
    "tgn:hierarchy":[
        "tgn:7045482",
        "tgn:7003170",
        "tgn:1000003",
        "tgn:7003125",
        "tgn:1000080",
        "tgn:7029392"
    ],
    "tgn:id":7045482,
    "tgn:name":"Cormelano, Monte",
    "tgn:placetype":[
        "aat:300008795"
    ]
},
  "bbox": [],
  "geometry": {"coordinates":[12.683333,42.683333],"type":"Point"}
}