{
  "id": 2140904,
  "type": "Feature",
  "properties": {
    "tgn:hierarchy":[
        "tgn:2140904",
        "tgn:1000001",
        "tgn:7012149",
        "tgn:2000982",
        "tgn:7007520",
        "tgn:7029392"
    ],
    "tgn:id":2140904,
    "tgn:name":"Avery",
    "tgn:placetype":[
        "aat:300008347"
    ]
},
  "bbox": [],
  "geometry": {"coordinates":[-84.0167,44.95],"type":"Point"}
}