{
  "id": 1022377,
  "type": "Feature",
  "properties": {
    "tgn:hierarchy":[
        "tgn:1022377",
        "tgn:7006237",
        "tgn:1000047",
        "tgn:7002457",
        "tgn:1000002",
        "tgn:7029392"
    ],
    "tgn:id":1022377,
    "tgn:name":"Patos de Minas",
    "tgn:placetype":[
        "aat:300008347"
    ]
},
  "bbox": [],
  "geometry": {"coordinates":[-46.5333,-18.5833],"type":"Point"}
}