{
  "id": 7586569,
  "type": "Feature",
  "properties": {
    "tgn:hierarchy":[
        "tgn:7586569",
        "tgn:1000004",
        "tgn:7000198",
        "tgn:7000799",
        "tgn:7029392"
    ],
    "tgn:id":7586569,
    "tgn:name:en":"Dayin",
    "tgn:placetype":[
        "aat:300008347"
    ]
},
  "bbox": [],
  "geometry": {"coordinates":[74.417482,34.450244],"type":"Point"}
}