{
  "id": 7581290,
  "type": "Feature",
  "properties": {
    "tgn:hierarchy":[
        "tgn:7581290",
        "tgn:1000004",
        "tgn:1001869",
        "tgn:7000198",
        "tgn:7029392"
    ],
    "tgn:id":7581290,
    "tgn:name:en":"Shil",
    "tgn:placetype":[
        "aat:300008347"
    ]
},
  "bbox": [],
  "geometry": {"coordinates":[70.050556,21.187778],"type":"Point"}
}