{
  "id": 2547972,
  "type": "Feature",
  "properties": {
    "tgn:hierarchy":[
        "tgn:2547972",
        "tgn:1000001",
        "tgn:7012149",
        "tgn:7007826",
        "tgn:7029392"
    ],
    "tgn:id":2547972,
    "tgn:name":"North Groesbeck Creek",
    "tgn:placetype":[
        "aat:300008706"
    ]
},
  "bbox": [],
  "geometry": {"coordinates":[-100.1667,34.4167],"type":"Point"}
}