{
  "id": 7459525,
  "type": "Feature",
  "properties": {
    "tgn:hierarchy":[
        "tgn:7459525",
        "tgn:7002444",
        "tgn:1000003",
        "tgn:7008082",
        "tgn:7008591",
        "tgn:7029392"
    ],
    "tgn:id":7459525,
    "tgn:name:en":"Mh\u00e0im-ard, Sgeir a'",
    "tgn:placetype":[
        "aat:300011692"
    ]
},
  "bbox": [],
  "geometry": {"coordinates":[-6.25,56.966667],"type":"Point"}
}