{
  "id": 7295890,
  "type": "Feature",
  "properties": {
    "tgn:hierarchy":[
        "tgn:7295890",
        "tgn:7002832",
        "tgn:7001158",
        "tgn:1000003",
        "tgn:1000095",
        "tgn:7029392"
    ],
    "tgn:id":7295890,
    "tgn:name":"Villasila de Valdavia",
    "tgn:placetype":[
        "aat:300008347"
    ]
},
  "bbox": [],
  "geometry": {"coordinates":[-4.55,42.533333],"type":"Point"}
}