{
  "id": 7529819,
  "type": "Feature",
  "properties": {
    "tgn:hierarchy":[
        "tgn:7529819",
        "tgn:7001242",
        "tgn:7016833",
        "tgn:1001091",
        "tgn:7029392"
    ],
    "tgn:id":7529819,
    "tgn:name":"Masjid Ab\u016b as Su'\u016bd al J\u0101r\u1e29\u012b",
    "tgn:placetype":[
        "aat:300007544"
    ]
},
  "bbox": [],
  "geometry": {"coordinates":[31.238395,30.01514],"type":"Point"}
}