{
  "id": 2687237,
  "type": "Feature",
  "properties": {
    "tgn:hierarchy":[
        "tgn:2687237",
        "tgn:7002659",
        "tgn:1000001",
        "tgn:7012149",
        "tgn:2000048",
        "tgn:7029392"
    ],
    "tgn:id":2687237,
    "tgn:name":"Spring Lake",
    "tgn:placetype":[
        "aat:300006191"
    ]
},
  "bbox": [],
  "geometry": {"coordinates":[-88.2167,31.0333],"type":"Point"}
}