{
  "id": 7289524,
  "type": "Feature",
  "properties": {
    "tgn:hierarchy":[
        "tgn:7289524",
        "tgn:1001657",
        "tgn:1000049",
        "tgn:1000002",
        "tgn:7029392"
    ],
    "tgn:id":7289524,
    "tgn:name":"Infiernillo",
    "tgn:placetype":[
        "aat:300008795"
    ]
},
  "bbox": [],
  "geometry": {"coordinates":[-70.383333,-29.933333],"type":"Point"}
}