{
  "id": 7495573,
  "type": "Feature",
  "properties": {
    "tgn:hierarchy":[
        "tgn:7495573",
        "tgn:1000004",
        "tgn:7001013",
        "tgn:1000141",
        "tgn:7029392"
    ],
    "tgn:id":7495573,
    "tgn:name":"Xu Qiao",
    "tgn:placetype":[
        "aat:300007836"
    ]
},
  "bbox": [],
  "geometry": {"coordinates":[121.30246,24.895852],"type":"Point"}
}