{
  "id": 7032234,
  "type": "Feature",
  "properties": {
    "tgn:hierarchy":[
        "tgn:7032234",
        "tgn:7001680",
        "tgn:7001242",
        "tgn:1000184",
        "tgn:7029392"
    ],
    "tgn:id":7032234,
    "tgn:name:fr":"Bois-Blanc",
    "tgn:placetype":[
        "aat:300008347"
    ]
},
  "bbox": [],
  "geometry": {"coordinates":[55.8166,-21.1833],"type":"Point"}
}