{
  "id": 7383485,
  "type": "Feature",
  "properties": {
    "tgn:hierarchy":[
        "tgn:7383485",
        "tgn:1000001",
        "tgn:7005589",
        "tgn:7005560",
        "tgn:7029392"
    ],
    "tgn:id":7383485,
    "tgn:name":"Oso, Cerro del",
    "tgn:placetype":[
        "aat:300008795"
    ]
},
  "bbox": [],
  "geometry": {"coordinates":[-100.066667,24.683333],"type":"Point"}
}