{
  "id": 7577159,
  "type": "Feature",
  "properties": {
    "tgn:hierarchy":[
        "tgn:7577159",
        "tgn:1000004",
        "tgn:1001869",
        "tgn:7000198",
        "tgn:7029392"
    ],
    "tgn:id":7577159,
    "tgn:name:en":"Limdi",
    "tgn:placetype":[
        "aat:300008347"
    ]
},
  "bbox": [],
  "geometry": {"coordinates":[74.154801,23.008799],"type":"Point"}
}