<<<<<<< HEAD
{
  "id": 7177389,
  "type": "Feature",
  "properties": {
    "tgn:hierarchy":[
        "tgn:7177389",
        "tgn:7003692",
        "tgn:1000003",
        "tgn:7000084",
        "tgn:7029392"
    ],
    "tgn:id":7177389,
    "tgn:name":"Hagenbuchen",
    "tgn:placetype":[
        "aat:300008347"
    ]
},
  "bbox": [],
  "geometry": {"coordinates":[9.583333,47.65],"type":"Point"}
}
=======
{"geometry":{"type":"Point","coordinates":[9.583333,47.650000]},"type":"Feature","properties":{"hierarchy":["tgn:7177389","tgn:7003692","tgn:1000003","tgn:7000084","tgn:7029392"],"placetype":["aat:300008347"],"id":7177389,"name:xx":"Hagenbuchen"}}
>>>>>>> 03f74aca74312dbeaf24d7e61306dd6a786dc3d0
