{
  "id": 7105693,
  "type": "Feature",
  "properties": {
    "tgn:hierarchy":[
        "tgn:7105693",
        "tgn:1000003",
        "tgn:7003688",
        "tgn:7000084",
        "tgn:7029392"
    ],
    "tgn:id":7105693,
    "tgn:name":"Schlichting",
    "tgn:placetype":[
        "aat:300008347"
    ]
},
  "bbox": [],
  "geometry": {"coordinates":[9.083333,54.316667],"type":"Point"}
}