{
  "id": 7493713,
  "type": "Feature",
  "properties": {
    "tgn:hierarchy":[
        "tgn:7493713",
        "tgn:7468018",
        "tgn:1000004",
        "tgn:1000141",
        "tgn:7029392"
    ],
    "tgn:id":7493713,
    "tgn:name":"Shilong Shan",
    "tgn:placetype":[
        "aat:300387002"
    ]
},
  "bbox": [],
  "geometry": {"coordinates":[120.572768,23.381483],"type":"Point"}
}