{
  "id": 7278494,
  "type": "Feature",
  "properties": {
    "tgn:hierarchy":[
        "tgn:7278494",
        "tgn:7016598",
        "tgn:1000049",
        "tgn:1000002",
        "tgn:7029392"
    ],
    "tgn:id":7278494,
    "tgn:name":"Zorritas, Morro",
    "tgn:placetype":[
        "aat:300008795"
    ]
},
  "bbox": [],
  "geometry": {"coordinates":[-68.683333,-24.633333],"type":"Point"}
}