{
  "id": 7561379,
  "type": "Feature",
  "properties": {
    "tgn:hierarchy":[
        "tgn:7561379",
        "tgn:1000004",
        "tgn:7000198",
        "tgn:7016722",
        "tgn:7029392"
    ],
    "tgn:id":7561379,
    "tgn:name:en":"Nagla Bhagat",
    "tgn:placetype":[
        "aat:300008347"
    ]
},
  "bbox": [],
  "geometry": {"coordinates":[79.194561,26.895838],"type":"Point"}
}