{
  "id": 7236109,
  "type": "Feature",
  "properties": {
    "tgn:hierarchy":[
        "tgn:7236109",
        "tgn:7011167",
        "tgn:7001338",
        "tgn:1000003",
        "tgn:1000074",
        "tgn:7029392"
    ],
    "tgn:id":7236109,
    "tgn:name":"Evret\u00ed",
    "tgn:placetype":[
        "aat:300008347"
    ]
},
  "bbox": [],
  "geometry": {"coordinates":[20.583333,38.433333],"type":"Point"}
}