{
  "id": 7544971,
  "type": "Feature",
  "properties": {
    "tgn:hierarchy":[
        "tgn:7544971",
        "tgn:1000004",
        "tgn:7000198",
        "tgn:7016722",
        "tgn:7029392"
    ],
    "tgn:id":7544971,
    "tgn:name:en":"Babr\u0101la",
    "tgn:placetype":[
        "aat:300008347"
    ]
},
  "bbox": [],
  "geometry": {"coordinates":[78.404709,28.2639],"type":"Point"}
}