{
  "id": 2617279,
  "type": "Feature",
  "properties": {
    "tgn:hierarchy":[
        "tgn:2617279",
        "tgn:1000001",
        "tgn:7012149",
        "tgn:2000907",
        "tgn:7007256",
        "tgn:7029392"
    ],
    "tgn:id":2617279,
    "tgn:name":"Richland",
    "tgn:placetype":[
        "aat:300008347"
    ]
},
  "bbox": [],
  "geometry": {"coordinates":[-91.45,31.8333],"type":"Point"}
}