{
  "id": 2010887,
  "type": "Feature",
  "properties": {
    "tgn:hierarchy":[
        "tgn:2010887",
        "tgn:1000001",
        "tgn:7012149",
        "tgn:7007157",
        "tgn:1002656",
        "tgn:7029392"
    ],
    "tgn:id":2010887,
    "tgn:name":"Creegan",
    "tgn:placetype":[
        "aat:300387016"
    ]
},
  "bbox": [],
  "geometry": {"coordinates":[-120.45,37.2833],"type":"Point"}
}