{
  "id": 7586187,
  "type": "Feature",
  "properties": {
    "tgn:hierarchy":[
        "tgn:7586187",
        "tgn:1000004",
        "tgn:7000198",
        "tgn:7000799",
        "tgn:7029392"
    ],
    "tgn:id":7586187,
    "tgn:name:en":"Gul\u0101bpathar",
    "tgn:placetype":[
        "aat:300008347"
    ]
},
  "bbox": [],
  "geometry": {"coordinates":[74.963889,34.325],"type":"Point"}
}