{
  "id": 2403115,
  "type": "Feature",
  "properties": {
    "tgn:hierarchy":[
        "tgn:2403115",
        "tgn:7002659",
        "tgn:1000001",
        "tgn:7012149",
        "tgn:2000042",
        "tgn:7029392"
    ],
    "tgn:id":2403115,
    "tgn:name":"House Creek",
    "tgn:placetype":[
        "aat:300008706"
    ]
},
  "bbox": [],
  "geometry": {"coordinates":[-86.7167,32.3167],"type":"Point"}
}