<<<<<<< HEAD
{
  "id": 7364645,
  "type": "Feature",
  "properties": {
    "tgn:hierarchy":[
        "tgn:7364645",
        "tgn:7005581",
        "tgn:1000001",
        "tgn:7005560",
        "tgn:7029392"
    ],
    "tgn:id":7364645,
    "tgn:name":"Rancho El Progreso",
    "tgn:placetype":[
        "aat:300000241"
    ]
},
  "bbox": [],
  "geometry": {"coordinates":[-103.816667,28.283333],"type":"Point"}
}
=======
{"geometry":{"type":"Point","coordinates":[-103.816667,28.283333]},"type":"Feature","properties":{"hierarchy":["tgn:7364645","tgn:7005581","tgn:1000001","tgn:7005560","tgn:7029392"],"placetype":["aat:300000241"],"id":7364645,"name:xx":"Rancho El Progreso"}}
>>>>>>> 03f74aca74312dbeaf24d7e61306dd6a786dc3d0
