{
  "id": 7592962,
  "type": "Feature",
  "properties": {
    "tgn:hierarchy":[
        "tgn:7592962",
        "tgn:1000004",
        "tgn:7000198",
        "tgn:7000799",
        "tgn:7029392"
    ],
    "tgn:id":7592962,
    "tgn:name:en":"Pandorian",
    "tgn:placetype":[
        "aat:300008347"
    ]
},
  "bbox": [],
  "geometry": {"coordinates":[74.773611,32.806944],"type":"Point"}
}