{
  "id": 7130758,
  "type": "Feature",
  "properties": {
    "tgn:hierarchy":[
        "tgn:7130758",
        "tgn:1000003",
        "tgn:7003676",
        "tgn:7000084",
        "tgn:7029392"
    ],
    "tgn:id":7130758,
    "tgn:name":"Mehrenkamp",
    "tgn:placetype":[
        "aat:300008347"
    ]
},
  "bbox": [],
  "geometry": {"coordinates":[7.85,53.05],"type":"Point"}
}