{
  "id": 2388224,
  "type": "Feature",
  "properties": {
    "tgn:hierarchy":[
        "tgn:2388224",
        "tgn:1000001",
        "tgn:2002146",
        "tgn:7012149",
        "tgn:7007919",
        "tgn:7029392"
    ],
    "tgn:id":2388224,
    "tgn:name":"Hickory Hollow Branch",
    "tgn:placetype":[
        "aat:300008699"
    ]
},
  "bbox": [],
  "geometry": {"coordinates":[-79.6833,37.65],"type":"Point"}
}