{
  "id": 7419406,
  "type": "Feature",
  "properties": {
    "tgn:hierarchy":[
        "tgn:7419406",
        "tgn:1000001",
        "tgn:7005589",
        "tgn:7005560",
        "tgn:7029392"
    ],
    "tgn:id":7419406,
    "tgn:name:es":"Rancho Nuevo",
    "tgn:placetype":[
        "aat:300008347"
    ]
},
  "bbox": [],
  "geometry": {"coordinates":[-100.313611,23.459167],"type":"Point"}
}