{
  "id": 2180984,
  "type": "Feature",
  "properties": {
    "tgn:hierarchy":[
        "tgn:2180984",
        "tgn:1000001",
        "tgn:7012149",
        "tgn:1002785",
        "tgn:7007920",
        "tgn:7029392"
    ],
    "tgn:id":2180984,
    "tgn:name":"Bloyd Woods",
    "tgn:placetype":[
        "aat:300132451"
    ]
},
  "bbox": [],
  "geometry": {"coordinates":[-122.5333,47.0667],"type":"Point"}
}