{
  "id": 2308447,
  "type": "Feature",
  "properties": {
    "tgn:hierarchy":[
        "tgn:2308447",
        "tgn:1000001",
        "tgn:7006451",
        "tgn:2000092",
        "tgn:7012149",
        "tgn:7029392"
    ],
    "tgn:id":2308447,
    "tgn:name":"East Mesa",
    "tgn:placetype":[
        "aat:300008798"
    ]
},
  "bbox": [],
  "geometry": {"coordinates":[-111.45,35.5667],"type":"Point"}
}