<<<<<<< HEAD
{
  "id": 2335734,
  "type": "Feature",
  "properties": {
    "tgn:hierarchy":[
        "tgn:2335734",
        "tgn:2001422",
        "tgn:1000001",
        "tgn:7012149",
        "tgn:7007564",
        "tgn:7029392"
    ],
    "tgn:id":2335734,
    "tgn:name":"Forty Islands",
    "tgn:placetype":[
        "aat:300386853"
    ]
},
  "bbox": [],
  "geometry": {"coordinates":[-71.3667,43.6],"type":"Point"}
}
=======
{"geometry":{"type":"Point","coordinates":[-71.366700,43.600000]},"type":"Feature","properties":{"hierarchy":["tgn:2335734","tgn:2001422","tgn:1000001","tgn:7012149","tgn:7007564","tgn:7029392"],"placetype":["aat:300386853"],"id":2335734,"name:xx":"Forty Islands"}}
>>>>>>> 03f74aca74312dbeaf24d7e61306dd6a786dc3d0
