{
  "id": 1007003,
  "type": "Feature",
  "properties": {
    "tgn:hierarchy":[
        "tgn:1007003",
        "tgn:1000001",
        "tgn:7012149",
        "tgn:7007157",
        "tgn:7014005",
        "tgn:7029392"
    ],
    "tgn:id":1007003,
    "tgn:name":"East Marin Island",
    "tgn:placetype":[
        "aat:300008791"
    ]
},
  "bbox": [],
  "geometry": {"coordinates":[-122.4667,37.95],"type":"Point"}
}