{
  "id": 7253607,
  "type": "Feature",
  "properties": {
    "tgn:hierarchy":[
        "tgn:7253607",
        "tgn:7003456",
        "tgn:1000003",
        "tgn:1000063",
        "tgn:7018236",
        "tgn:7029392"
    ],
    "tgn:id":7253607,
    "tgn:name":"Sneppelaar",
    "tgn:placetype":[
        "aat:300008347"
    ]
},
  "bbox": [],
  "geometry": {"coordinates":[4.277529,51.02199],"type":"Point"}
}