{
  "id": 2593471,
  "type": "Feature",
  "properties": {
    "tgn:hierarchy":[
        "tgn:2593471",
        "tgn:7006450",
        "tgn:1000001",
        "tgn:7012149",
        "tgn:2000085",
        "tgn:7029392"
    ],
    "tgn:id":2593471,
    "tgn:name":"Porcupine Creek",
    "tgn:placetype":[
        "aat:300008706"
    ]
},
  "bbox": [],
  "geometry": {"coordinates":[-142.4667,63.3667],"type":"Point"}
}