{
  "id": 2098508,
  "type": "Feature",
  "properties": {
    "tgn:hierarchy":[
        "tgn:2098508",
        "tgn:1000001",
        "tgn:7012149",
        "tgn:2001912",
        "tgn:7007825",
        "tgn:7029392"
    ],
    "tgn:id":2098508,
    "tgn:name":"Clay Hill",
    "tgn:placetype":[
        "aat:300008347",
        "aat:300387210"
    ]
},
  "bbox": [],
  "geometry": {"coordinates":[-84.4167,36.55],"type":"Point"}
}