<<<<<<< HEAD
{
  "id": 7485787,
  "type": "Feature",
  "properties": {
    "tgn:hierarchy":[
        "tgn:7485787",
        "tgn:1000004",
        "tgn:7001014",
        "tgn:1000141",
        "tgn:7029392"
    ],
    "tgn:id":7485787,
    "tgn:name":"Dimu Qiao",
    "tgn:placetype":[
        "aat:300007836"
    ]
},
  "bbox": [],
  "geometry": {"coordinates":[120.604722,23.655556],"type":"Point"}
}
=======
{"geometry":{"type":"Point","coordinates":[120.604722,23.655556]},"type":"Feature","properties":{"hierarchy":["tgn:7485787","tgn:1000004","tgn:7001014","tgn:1000141","tgn:7029392"],"placetype":["aat:300007836"],"id":7485787,"name:xx":"Dimu Qiao"}}
>>>>>>> 03f74aca74312dbeaf24d7e61306dd6a786dc3d0
