{
  "id": 1019101,
  "type": "Feature",
  "properties": {
    "tgn:hierarchy":[
        "tgn:1019101",
        "tgn:1009905",
        "tgn:1008375",
        "tgn:1000001",
        "tgn:7004630",
        "tgn:7029392"
    ],
    "tgn:id":1019101,
    "tgn:name":"Kew",
    "tgn:placetype":[
        "aat:300008347"
    ]
},
  "bbox": [],
  "geometry": {"coordinates":[-72.0667,21.9167],"type":"Point"}
}