{
  "id": 2192157,
  "type": "Feature",
  "properties": {
    "tgn:hierarchy":[
        "tgn:2192157",
        "tgn:1000001",
        "tgn:7012149",
        "tgn:7007158",
        "tgn:7029392"
    ],
    "tgn:id":2192157,
    "tgn:name":"Bramiers Draw",
    "tgn:placetype":[
        "aat:300008761"
    ]
},
  "bbox": [],
  "geometry": {"coordinates":[-108.55,38.1333],"type":"Point"}
}