{
  "id": 2771064,
  "type": "Feature",
  "properties": {
    "tgn:hierarchy":[
        "tgn:2771064",
        "tgn:1000001",
        "tgn:2001473",
        "tgn:7012149",
        "tgn:7007709",
        "tgn:7029392"
    ],
    "tgn:id":2771064,
    "tgn:name":"Wildcat Knob",
    "tgn:placetype":[
        "aat:300008798"
    ]
},
  "bbox": [],
  "geometry": {"coordinates":[-82.4333,35.75],"type":"Point"}
}