{
  "id": 2286604,
  "type": "Feature",
  "properties": {
    "tgn:hierarchy":[
        "tgn:2286604",
        "tgn:1000001",
        "tgn:7012149",
        "tgn:2000987",
        "tgn:7007520",
        "tgn:7029392"
    ],
    "tgn:id":2286604,
    "tgn:name":"Diamond Lake",
    "tgn:placetype":[
        "aat:300008680"
    ]
},
  "bbox": [],
  "geometry": {"coordinates":[-85.4833,44.0833],"type":"Point"}
}