{
  "id": 7235365,
  "type": "Feature",
  "properties": {
    "tgn:hierarchy":[
        "tgn:7235365",
        "tgn:7002711",
        "tgn:7001338",
        "tgn:1000003",
        "tgn:1000074",
        "tgn:7029392"
    ],
    "tgn:id":7235365,
    "tgn:name":"Ps\u00fdllos, Vr\u00e1chos",
    "tgn:placetype":[
        "aat:300011692"
    ]
},
  "bbox": [],
  "geometry": {"coordinates":[19.983333,39.783333],"type":"Point"}
}