{
  "id": 1004294,
  "type": "Feature",
  "properties": {
    "tgn:hierarchy":[
        "tgn:1004294",
        "tgn:7010420",
        "tgn:1000003",
        "tgn:7002795",
        "tgn:1000095",
        "tgn:7010413",
        "tgn:7029392"
    ],
    "tgn:id":1004294,
    "tgn:name":"Ciudad Universitaria",
    "tgn:placetype":[
        "aat:300000745"
    ]
},
  "bbox": [],
  "geometry": {"coordinates":[-3.7333,40.45],"type":"Point"}
}