{
  "id": 7214259,
  "type": "Feature",
  "properties": {
    "tgn:hierarchy":[
        "tgn:7214259",
        "tgn:1000003",
        "tgn:7003688",
        "tgn:7000084",
        "tgn:7029392"
    ],
    "tgn:id":7214259,
    "tgn:name":"Boizkamp",
    "tgn:placetype":[
        "aat:300000206"
    ]
},
  "bbox": [],
  "geometry": {"coordinates":[10.583333,54.166667],"type":"Point"}
}