{
  "id": 7589348,
  "type": "Feature",
  "properties": {
    "tgn:hierarchy":[
        "tgn:7589348",
        "tgn:1000004",
        "tgn:7000198",
        "tgn:7000799",
        "tgn:7029392"
    ],
    "tgn:id":7589348,
    "tgn:name:en":"Dhora Kh\u0101nke",
    "tgn:placetype":[
        "aat:300008347"
    ]
},
  "bbox": [],
  "geometry": {"coordinates":[74.219444,33.325],"type":"Point"}
}