<<<<<<< HEAD
{
  "id": 7171950,
  "type": "Feature",
  "properties": {
    "tgn:hierarchy":[
        "tgn:7171950",
        "tgn:7003692",
        "tgn:1000003",
        "tgn:7000084",
        "tgn:7029392"
    ],
    "tgn:id":7171950,
    "tgn:name":"Hirnb\u00fchl",
    "tgn:placetype":[
        "aat:300008795"
    ]
},
  "bbox": [],
  "geometry": {"coordinates":[8.783333,48.083333],"type":"Point"}
}
=======
{"geometry":{"type":"Point","coordinates":[8.783333,48.083333]},"type":"Feature","properties":{"hierarchy":["tgn:7171950","tgn:7003692","tgn:1000003","tgn:7000084","tgn:7029392"],"placetype":["aat:300008795"],"id":7171950,"name:xx":"Hirnb\u00fchl"}}
>>>>>>> 03f74aca74312dbeaf24d7e61306dd6a786dc3d0
