{
  "id": 7293675,
  "type": "Feature",
  "properties": {
    "tgn:hierarchy":[
        "tgn:7293675",
        "tgn:7007088",
        "tgn:1000003",
        "tgn:7009604",
        "tgn:1000095",
        "tgn:7029392"
    ],
    "tgn:id":7293675,
    "tgn:name":"Villabuena de \u00c1lava",
    "tgn:placetype":[
        "aat:300008347"
    ]
},
  "bbox": [],
  "geometry": {"coordinates":[-2.665516,42.547875],"type":"Point"}
}