{
  "id": 1102414,
  "type": "Feature",
  "properties": {
    "tgn:hierarchy":[
        "tgn:1102414",
        "tgn:1000001",
        "tgn:7012149",
        "tgn:1002971",
        "tgn:7007710",
        "tgn:7029392"
    ],
    "tgn:id":1102414,
    "tgn:name":"Oil Creek State Park",
    "tgn:placetype":[
        "aat:300008192"
    ]
},
  "bbox": [],
  "geometry": {"coordinates":[-79.65,41.5333],"type":"Point"}
}