{
  "id": 7498922,
  "type": "Feature",
  "properties": {
    "tgn:hierarchy":[
        "tgn:7498922",
        "tgn:1000004",
        "tgn:1000959",
        "tgn:1000141",
        "tgn:7029392"
    ],
    "tgn:id":7498922,
    "tgn:name":"Jiangcuo",
    "tgn:placetype":[
        "aat:300008347"
    ]
},
  "bbox": [],
  "geometry": {"coordinates":[121.6008,25.066762],"type":"Point"}
}