{
  "id": 7418968,
  "type": "Feature",
  "properties": {
    "tgn:hierarchy":[
        "tgn:7418968",
        "tgn:1000001",
        "tgn:7005589",
        "tgn:7005560",
        "tgn:7029392"
    ],
    "tgn:id":7418968,
    "tgn:name:es":"El Porvenir",
    "tgn:placetype":[
        "aat:300008347"
    ]
},
  "bbox": [],
  "geometry": {"coordinates":[-99.7525,24.178333],"type":"Point"}
}