{
  "id": 2503236,
  "type": "Feature",
  "properties": {
    "tgn:hierarchy":[
        "tgn:2503236",
        "tgn:1000001",
        "tgn:2001801",
        "tgn:7012149",
        "tgn:7007713",
        "tgn:7029392"
    ],
    "tgn:id":2503236,
    "tgn:name":"McPherson Creek",
    "tgn:placetype":[
        "aat:300008706"
    ]
},
  "bbox": [],
  "geometry": {"coordinates":[-103.15,45.5833],"type":"Point"}
}