{
  "id": 2483818,
  "type": "Feature",
  "properties": {
    "tgn:hierarchy":[
        "tgn:2483818",
        "tgn:1000001",
        "tgn:7012149",
        "tgn:2002371",
        "tgn:7007923",
        "tgn:7029392"
    ],
    "tgn:id":2483818,
    "tgn:name":"Lateral P-27.0- A",
    "tgn:placetype":[
        "aat:300006075"
    ]
},
  "bbox": [],
  "geometry": {"coordinates":[-108.35,43.15],"type":"Point"}
}