{
  "id": 2419571,
  "type": "Feature",
  "properties": {
    "tgn:hierarchy":[
        "tgn:2419571",
        "tgn:1000001",
        "tgn:7016172",
        "tgn:7012149",
        "tgn:2000177",
        "tgn:7029392"
    ],
    "tgn:id":2419571,
    "tgn:name":"Jarvers Lake",
    "tgn:placetype":[
        "aat:300008680"
    ]
},
  "bbox": [],
  "geometry": {"coordinates":[-91.55,35.1167],"type":"Point"}
}