{
  "id": 2449804,
  "type": "Feature",
  "properties": {
    "tgn:hierarchy":[
        "tgn:2449804",
        "tgn:1000001",
        "tgn:7012149",
        "tgn:7007157",
        "tgn:2000186",
        "tgn:7029392"
    ],
    "tgn:id":2449804,
    "tgn:name":"Lindemenn Lake",
    "tgn:placetype":[
        "aat:300008680"
    ]
},
  "bbox": [],
  "geometry": {"coordinates":[-120.1833,41.3667],"type":"Point"}
}