<<<<<<< HEAD
{
  "id": 7177747,
  "type": "Feature",
  "properties": {
    "tgn:hierarchy":[
        "tgn:7177747",
        "tgn:1000003",
        "tgn:7003688",
        "tgn:7000084",
        "tgn:7029392"
    ],
    "tgn:id":7177747,
    "tgn:name":"Hanredder",
    "tgn:placetype":[
        "aat:300000745"
    ]
},
  "bbox": [],
  "geometry": {"coordinates":[9.733333,53.8],"type":"Point"}
}
=======
{"geometry":{"type":"Point","coordinates":[9.733333,53.800000]},"type":"Feature","properties":{"hierarchy":["tgn:7177747","tgn:1000003","tgn:7003688","tgn:7000084","tgn:7029392"],"placetype":["aat:300000745"],"id":7177747,"name:xx":"Hanredder"}}
>>>>>>> 03f74aca74312dbeaf24d7e61306dd6a786dc3d0
