<<<<<<< HEAD
{
  "id": 7369113,
  "type": "Feature",
  "properties": {
    "tgn:hierarchy":[
        "tgn:7369113",
        "tgn:7016644",
        "tgn:1000001",
        "tgn:7005560",
        "tgn:7029392"
    ],
    "tgn:id":7369113,
    "tgn:name":"Jumpiche, Cerro",
    "tgn:placetype":[
        "aat:300008795"
    ]
},
  "bbox": [],
  "geometry": {"coordinates":[-103.866667,19.333333],"type":"Point"}
}
=======
{"geometry":{"type":"Point","coordinates":[-103.866667,19.333333]},"type":"Feature","properties":{"hierarchy":["tgn:7369113","tgn:7016644","tgn:1000001","tgn:7005560","tgn:7029392"],"placetype":["aat:300008795"],"id":7369113,"name:xx":"Jumpiche, Cerro"}}
>>>>>>> 03f74aca74312dbeaf24d7e61306dd6a786dc3d0
