{
  "id": 2493990,
  "type": "Feature",
  "properties": {
    "tgn:hierarchy":[
        "tgn:2493990",
        "tgn:7002659",
        "tgn:1000001",
        "tgn:2000012",
        "tgn:7012149",
        "tgn:7029392"
    ],
    "tgn:id":2493990,
    "tgn:name":"Marshall Upper Landing",
    "tgn:placetype":[
        "aat:300008347"
    ]
},
  "bbox": [],
  "geometry": {"coordinates":[-87.5667,31.65],"type":"Point"}
}