{
  "id": 7274450,
  "type": "Feature",
  "properties": {
    "tgn:hierarchy":[
        "tgn:7274450",
        "tgn:1000003",
        "tgn:7003624",
        "tgn:7016845",
        "tgn:7029392"
    ],
    "tgn:id":7274450,
    "tgn:name:nl":"Zwijnsbergen",
    "tgn:placetype":[
        "aat:300387502"
    ]
},
  "bbox": [],
  "geometry": {"coordinates":[5.216667,51.65],"type":"Point"}
}