{
  "id": 2381596,
  "type": "Feature",
  "properties": {
    "tgn:hierarchy":[
        "tgn:2381596",
        "tgn:1000001",
        "tgn:7012149",
        "tgn:2001247",
        "tgn:7007523",
        "tgn:7029392"
    ],
    "tgn:id":2381596,
    "tgn:name":"Hay Hollow",
    "tgn:placetype":[
        "aat:300008761"
    ]
},
  "bbox": [],
  "geometry": {"coordinates":[-91.2667,37.0833],"type":"Point"}
}