{
  "id": 7033921,
  "type": "Feature",
  "properties": {
    "tgn:hierarchy":[
        "tgn:7033921",
        "tgn:7003164",
        "tgn:1000003",
        "tgn:7009760",
        "tgn:1000080",
        "tgn:7029392"
    ],
    "tgn:id":7033921,
    "tgn:name":"Pontile Elba",
    "tgn:placetype":[
        "aat:300120786"
    ]
},
  "bbox": [],
  "geometry": {"coordinates":[10.547222,42.929167],"type":"Point"}
}