<<<<<<< HEAD
{
  "id": 2158428,
  "type": "Feature",
  "properties": {
    "tgn:hierarchy":[
        "tgn:2158428",
        "tgn:1000001",
        "tgn:7012149",
        "tgn:2000357",
        "tgn:7007248",
        "tgn:7029392"
    ],
    "tgn:id":2158428,
    "tgn:name":"Beaverdam Creek",
    "tgn:placetype":[
        "aat:300008706"
    ]
},
  "bbox": [],
  "geometry": {"coordinates":[-83.1,33.5833],"type":"Point"}
}
=======
{"geometry":{"type":"Point","coordinates":[-83.100000,33.583300]},"type":"Feature","properties":{"hierarchy":["tgn:2158428","tgn:1000001","tgn:7012149","tgn:2000357","tgn:7007248","tgn:7029392"],"placetype":["aat:300008706"],"id":2158428,"name:xx":"Beaverdam Creek"}}
>>>>>>> 03f74aca74312dbeaf24d7e61306dd6a786dc3d0
