{
  "id": 2707141,
  "type": "Feature",
  "properties": {
    "tgn:hierarchy":[
        "tgn:2707141",
        "tgn:1000001",
        "tgn:2001012",
        "tgn:7012149",
        "tgn:7007521",
        "tgn:7029392"
    ],
    "tgn:id":2707141,
    "tgn:name":"Swede Grove Lake",
    "tgn:placetype":[
        "aat:300008680"
    ]
},
  "bbox": [],
  "geometry": {"coordinates":[-96.2167,46.95],"type":"Point"}
}