{
  "id": 2182819,
  "type": "Feature",
  "properties": {
    "tgn:hierarchy":[
        "tgn:2182819",
        "tgn:1000001",
        "tgn:7012149",
        "tgn:2000218",
        "tgn:7007158",
        "tgn:7029392"
    ],
    "tgn:id":2182819,
    "tgn:name":"Blue Spruce Canyon",
    "tgn:placetype":[
        "aat:300008761"
    ]
},
  "bbox": [],
  "geometry": {"coordinates":[-107.3833,37.4833],"type":"Point"}
}