<<<<<<< HEAD
{
  "id": 2252990,
  "type": "Feature",
  "properties": {
    "tgn:hierarchy":[
        "tgn:2252990",
        "tgn:1000001",
        "tgn:7006451",
        "tgn:7012149",
        "tgn:2000097",
        "tgn:7029392"
    ],
    "tgn:id":2252990,
    "tgn:name":"Consolidated Canal",
    "tgn:placetype":[
        "aat:300006075"
    ]
},
  "bbox": [],
  "geometry": {"coordinates":[-111.8,33.45],"type":"Point"}
}
=======
{"geometry":{"type":"Point","coordinates":[-111.800000,33.450000]},"type":"Feature","properties":{"hierarchy":["tgn:2252990","tgn:1000001","tgn:7006451","tgn:7012149","tgn:2000097","tgn:7029392"],"placetype":["aat:300006075"],"id":2252990,"name:xx":"Consolidated Canal"}}
>>>>>>> 03f74aca74312dbeaf24d7e61306dd6a786dc3d0
