{
  "id": 7502843,
  "type": "Feature",
  "properties": {
    "tgn:hierarchy":[
        "tgn:7502843",
        "tgn:1000004",
        "tgn:7001002",
        "tgn:1000141",
        "tgn:7029392"
    ],
    "tgn:id":7502843,
    "tgn:name":"Dazhuang",
    "tgn:placetype":[
        "aat:300008347"
    ]
},
  "bbox": [],
  "geometry": {"coordinates":[120.925278,24.792222],"type":"Point"}
}