{
  "id": 7511866,
  "type": "Feature",
  "properties": {
    "tgn:hierarchy":[
        "tgn:7511866",
        "tgn:1009227",
        "tgn:7001866",
        "tgn:1000226",
        "tgn:1000006",
        "tgn:7029392"
    ],
    "tgn:id":7511866,
    "tgn:name:en":"Kakahu Bush",
    "tgn:placetype":[
        "aat:300008347"
    ]
},
  "bbox": [],
  "geometry": {"coordinates":[171.116667,-44.15],"type":"Point"}
}