{
  "id": 2166768,
  "type": "Feature",
  "properties": {
    "tgn:hierarchy":[
        "tgn:2166768",
        "tgn:1000001",
        "tgn:7012149",
        "tgn:2002154",
        "tgn:7007919",
        "tgn:7029392"
    ],
    "tgn:id":2166768,
    "tgn:name":"Big Branch",
    "tgn:placetype":[
        "aat:300008699"
    ]
},
  "bbox": [],
  "geometry": {"coordinates":[-80.1333,37.5333],"type":"Point"}
}