<<<<<<< HEAD
{
  "id": 2405220,
  "type": "Feature",
  "properties": {
    "tgn:hierarchy":[
        "tgn:2405220",
        "tgn:1000001",
        "tgn:2001747",
        "tgn:7012149",
        "tgn:7007712",
        "tgn:7029392"
    ],
    "tgn:id":2405220,
    "tgn:name":"Huff Creek",
    "tgn:placetype":[
        "aat:300008706"
    ]
},
  "bbox": [],
  "geometry": {"coordinates":[-82.3667,34.7333],"type":"Point"}
}
=======
{"geometry":{"type":"Point","coordinates":[-82.366700,34.733300]},"type":"Feature","properties":{"hierarchy":["tgn:2405220","tgn:1000001","tgn:2001747","tgn:7012149","tgn:7007712","tgn:7029392"],"placetype":["aat:300008706"],"id":2405220,"name:xx":"Huff Creek"}}
>>>>>>> 03f74aca74312dbeaf24d7e61306dd6a786dc3d0
