{
  "id": 7460863,
  "type": "Feature",
  "properties": {
    "tgn:hierarchy":[
        "tgn:7460863",
        "tgn:7002445",
        "tgn:1000003",
        "tgn:7008131",
        "tgn:7008591",
        "tgn:7029392"
    ],
    "tgn:id":7460863,
    "tgn:name:en":"Holliwell Point",
    "tgn:placetype":[
        "aat:300386846"
    ]
},
  "bbox": [],
  "geometry": {"coordinates":[0.933333,51.633333],"type":"Point"}
}