{
  "id": 2061375,
  "type": "Feature",
  "properties": {
    "tgn:hierarchy":[
        "tgn:2061375",
        "tgn:1000001",
        "tgn:7012149",
        "tgn:2001277",
        "tgn:7007524",
        "tgn:7029392"
    ],
    "tgn:id":2061375,
    "tgn:name":"Gunsight",
    "tgn:placetype":[
        "aat:300387016"
    ]
},
  "bbox": [],
  "geometry": {"coordinates":[-112.45,48.6333],"type":"Point"}
}