{
  "id": 2500791,
  "type": "Feature",
  "properties": {
    "tgn:hierarchy":[
        "tgn:2500791",
        "tgn:1000001",
        "tgn:7012149",
        "tgn:2001504",
        "tgn:7007709",
        "tgn:7029392"
    ],
    "tgn:id":2500791,
    "tgn:name":"McElrath Lake",
    "tgn:placetype":[
        "aat:300006191"
    ]
},
  "bbox": [],
  "geometry": {"coordinates":[-82.6333,35.4167],"type":"Point"}
}