{
  "id": 7460902,
  "type": "Feature",
  "properties": {
    "tgn:hierarchy":[
        "tgn:7460902",
        "tgn:7002443",
        "tgn:1000003",
        "tgn:7018993",
        "tgn:7008591",
        "tgn:7029392"
    ],
    "tgn:id":7460902,
    "tgn:name:en":"Llanstadwell",
    "tgn:placetype":[
        "aat:300008347"
    ]
},
  "bbox": [],
  "geometry": {"coordinates":[-4.969722,51.705833],"type":"Point"}
}