{
  "id": 2040006,
  "type": "Feature",
  "properties": {
    "tgn:hierarchy":[
        "tgn:2040006",
        "tgn:1000001",
        "tgn:2000775",
        "tgn:7012149",
        "tgn:7007255",
        "tgn:7029392"
    ],
    "tgn:id":2040006,
    "tgn:name":"Logansport",
    "tgn:placetype":[
        "aat:300008347"
    ]
},
  "bbox": [],
  "geometry": {"coordinates":[-86.7667,37.2833],"type":"Point"}
}