{
  "id": 2349041,
  "type": "Feature",
  "properties": {
    "tgn:hierarchy":[
        "tgn:2349041",
        "tgn:1000001",
        "tgn:2001009",
        "tgn:7012149",
        "tgn:7007521",
        "tgn:7029392"
    ],
    "tgn:id":2349041,
    "tgn:name":"Gijik Lake",
    "tgn:placetype":[
        "aat:300008680"
    ]
},
  "bbox": [],
  "geometry": {"coordinates":[-94.1667,46.9833],"type":"Point"}
}