<<<<<<< HEAD
{
  "id": 7116619,
  "type": "Feature",
  "properties": {
    "tgn:hierarchy":[
        "tgn:7116619",
        "tgn:7003669",
        "tgn:1000003",
        "tgn:7000084",
        "tgn:7029392"
    ],
    "tgn:id":7116619,
    "tgn:name":"Oesdorf",
    "tgn:placetype":[
        "aat:300008347"
    ]
},
  "bbox": [],
  "geometry": {"coordinates":[10.983333,49.7],"type":"Point"}
}
=======
{"geometry":{"type":"Point","coordinates":[10.983333,49.700000]},"type":"Feature","properties":{"hierarchy":["tgn:7116619","tgn:7003669","tgn:1000003","tgn:7000084","tgn:7029392"],"placetype":["aat:300008347"],"id":7116619,"name:xx":"Oesdorf"}}
>>>>>>> 03f74aca74312dbeaf24d7e61306dd6a786dc3d0
