{
  "id": 7189050,
  "type": "Feature",
  "properties": {
    "tgn:hierarchy":[
        "tgn:7189050",
        "tgn:1000003",
        "tgn:7003676",
        "tgn:7000084",
        "tgn:7029392"
    ],
    "tgn:id":7189050,
    "tgn:name":"Eltern",
    "tgn:placetype":[
        "aat:300008347"
    ]
},
  "bbox": [],
  "geometry": {"coordinates":[7.516667,52.683333],"type":"Point"}
}