<<<<<<< HEAD
{
  "id": 2767937,
  "type": "Feature",
  "properties": {
    "tgn:hierarchy":[
        "tgn:2767937",
        "tgn:1000001",
        "tgn:7012149",
        "tgn:7007568",
        "tgn:7029392"
    ],
    "tgn:id":2767937,
    "tgn:name":"Whiteman Gully",
    "tgn:placetype":[
        "aat:300008761"
    ]
},
  "bbox": [],
  "geometry": {"coordinates":[-77.6333,42.5667],"type":"Point"}
}
=======
{"geometry":{"type":"Point","coordinates":[-77.633300,42.566700]},"type":"Feature","properties":{"hierarchy":["tgn:2767937","tgn:1000001","tgn:7012149","tgn:7007568","tgn:7029392"],"placetype":["aat:300008761"],"id":2767937,"name:xx":"Whiteman Gully"}}
>>>>>>> 03f74aca74312dbeaf24d7e61306dd6a786dc3d0
