{
  "id": 2496260,
  "type": "Feature",
  "properties": {
    "tgn:hierarchy":[
        "tgn:2496260",
        "tgn:1000001",
        "tgn:7012149",
        "tgn:2001965",
        "tgn:7007826",
        "tgn:7029392"
    ],
    "tgn:id":2496260,
    "tgn:name":"Matador Tank",
    "tgn:placetype":[
        "aat:300006191"
    ]
},
  "bbox": [],
  "geometry": {"coordinates":[-100.05,34.0667],"type":"Point"}
}