{
  "id": 7213649,
  "type": "Feature",
  "properties": {
    "tgn:hierarchy":[
        "tgn:7213649",
        "tgn:1000003",
        "tgn:7003676",
        "tgn:7000084",
        "tgn:7029392"
    ],
    "tgn:id":7213649,
    "tgn:name":"Boller Moor",
    "tgn:placetype":[
        "aat:300386886"
    ]
},
  "bbox": [],
  "geometry": {"coordinates":[8.333333,52.683333],"type":"Point"}
}