{
  "id": 7227345,
  "type": "Feature",
  "properties": {
    "tgn:hierarchy":[
        "tgn:7227345",
        "tgn:7002711",
        "tgn:7001338",
        "tgn:1000003",
        "tgn:1000074",
        "tgn:7029392"
    ],
    "tgn:id":7227345,
    "tgn:name":"K\u00e1to Garo\u00fana",
    "tgn:placetype":[
        "aat:300008347"
    ]
},
  "bbox": [],
  "geometry": {"coordinates":[19.858056,39.541111],"type":"Point"}
}