{
  "id": 7202019,
  "type": "Feature",
  "properties": {
    "tgn:hierarchy":[
        "tgn:7202019",
        "tgn:1000003",
        "tgn:7003677",
        "tgn:7000084",
        "tgn:7029392"
    ],
    "tgn:id":7202019,
    "tgn:name":"Bronsfeld",
    "tgn:placetype":[
        "aat:300008347"
    ]
},
  "bbox": [],
  "geometry": {"coordinates":[6.45,50.516667],"type":"Point"}
}