{
  "id": 2518641,
  "type": "Feature",
  "properties": {
    "tgn:hierarchy":[
        "tgn:2518641",
        "tgn:1000001",
        "tgn:2001841",
        "tgn:7012149",
        "tgn:7007825",
        "tgn:7029392"
    ],
    "tgn:id":2518641,
    "tgn:name":"Mitchell Hollow Well",
    "tgn:placetype":[
        "aat:300008746"
    ]
},
  "bbox": [],
  "geometry": {"coordinates":[-83.75,35.65],"type":"Point"}
}