<<<<<<< HEAD
{
  "id": 7365013,
  "type": "Feature",
  "properties": {
    "tgn:hierarchy":[
        "tgn:7365013",
        "tgn:7005583",
        "tgn:1000001",
        "tgn:7005560",
        "tgn:7029392"
    ],
    "tgn:id":7365013,
    "tgn:name":"Fraile",
    "tgn:placetype":[
        "aat:300008347"
    ]
},
  "bbox": [],
  "geometry": {"coordinates":[-106.5,25.25],"type":"Point"}
}
=======
{"geometry":{"type":"Point","coordinates":[-106.500000,25.250000]},"type":"Feature","properties":{"hierarchy":["tgn:7365013","tgn:7005583","tgn:1000001","tgn:7005560","tgn:7029392"],"placetype":["aat:300008347"],"id":7365013,"name:xx":"Fraile"}}
>>>>>>> 03f74aca74312dbeaf24d7e61306dd6a786dc3d0
