{
  "id": 7414790,
  "type": "Feature",
  "properties": {
    "tgn:hierarchy":[
        "tgn:7414790",
        "tgn:1000001",
        "tgn:7005591",
        "tgn:7005560",
        "tgn:7029392"
    ],
    "tgn:id":7414790,
    "tgn:name:es":"Ostuta",
    "tgn:placetype":[
        "aat:300008347"
    ]
},
  "bbox": [],
  "geometry": {"coordinates":[-94.380833,16.496111],"type":"Point"}
}