<<<<<<< HEAD
{
  "id": 2151663,
  "type": "Feature",
  "properties": {
    "tgn:hierarchy":[
        "tgn:2151663",
        "tgn:1000001",
        "tgn:2001411",
        "tgn:7012149",
        "tgn:7007526",
        "tgn:7029392"
    ],
    "tgn:id":2151663,
    "tgn:name":"Battle Creek",
    "tgn:placetype":[
        "aat:300008706"
    ]
},
  "bbox": [],
  "geometry": {"coordinates":[-115.4,40.5167],"type":"Point"}
}
=======
{"geometry":{"type":"Point","coordinates":[-115.400000,40.516700]},"type":"Feature","properties":{"hierarchy":["tgn:2151663","tgn:1000001","tgn:2001411","tgn:7012149","tgn:7007526","tgn:7029392"],"placetype":["aat:300008706"],"id":2151663,"name:xx":"Battle Creek"}}
>>>>>>> 03f74aca74312dbeaf24d7e61306dd6a786dc3d0
