{
  "id": 7398144,
  "type": "Feature",
  "properties": {
    "tgn:hierarchy":[
        "tgn:7398144",
        "tgn:1000001",
        "tgn:1001960",
        "tgn:7005560",
        "tgn:7029392"
    ],
    "tgn:id":7398144,
    "tgn:name":"San Imuris, Cerro",
    "tgn:placetype":[
        "aat:300008795"
    ]
},
  "bbox": [],
  "geometry": {"coordinates":[-110.734167,30.874444],"type":"Point"}
}