{
  "id": 2484447,
  "type": "Feature",
  "properties": {
    "tgn:hierarchy":[
        "tgn:2484447",
        "tgn:1000001",
        "tgn:7012149",
        "tgn:2001908",
        "tgn:7007825",
        "tgn:7029392"
    ],
    "tgn:id":2484447,
    "tgn:name":"Laurel Ford Branch",
    "tgn:placetype":[
        "aat:300008699"
    ]
},
  "bbox": [],
  "geometry": {"coordinates":[-84.8833,35.6667],"type":"Point"}
}