{
  "id": 7280668,
  "type": "Feature",
  "properties": {
    "tgn:hierarchy":[
        "tgn:7280668",
        "tgn:1001695",
        "tgn:1000049",
        "tgn:1000002",
        "tgn:7029392"
    ],
    "tgn:id":7280668,
    "tgn:name":"San Jos\u00e9 de Los Lingues",
    "tgn:placetype":[
        "aat:300000206"
    ]
},
  "bbox": [],
  "geometry": {"coordinates":[-70.916667,-34.566667],"type":"Point"}
}