{
  "id": 2750909,
  "type": "Feature",
  "properties": {
    "tgn:hierarchy":[
        "tgn:2750909",
        "tgn:1000001",
        "tgn:7012149",
        "tgn:1002392",
        "tgn:7007157",
        "tgn:7029392"
    ],
    "tgn:id":2750909,
    "tgn:name":"Ward Mountain Lake",
    "tgn:placetype":[
        "aat:300008680"
    ]
},
  "bbox": [],
  "geometry": {"coordinates":[-118.8833,37.2167],"type":"Point"}
}