{
  "id": 2599919,
  "type": "Feature",
  "properties": {
    "tgn:hierarchy":[
        "tgn:2599919",
        "tgn:1000001",
        "tgn:7012149",
        "tgn:7014589",
        "tgn:7007515",
        "tgn:7029392"
    ],
    "tgn:id":2599919,
    "tgn:name":"Provost Island",
    "tgn:placetype":[
        "aat:300008791"
    ]
},
  "bbox": [],
  "geometry": {"coordinates":[-67.4167,44.9333],"type":"Point"}
}