{
  "id": 7279353,
  "type": "Feature",
  "properties": {
    "tgn:hierarchy":[
        "tgn:7279353",
        "tgn:1001702",
        "tgn:1000049",
        "tgn:1000002",
        "tgn:7029392"
    ],
    "tgn:id":7279353,
    "tgn:name":"Robertson, Isla",
    "tgn:placetype":[
        "aat:300008791"
    ]
},
  "bbox": [],
  "geometry": {"coordinates":[-69.166667,-55.533333],"type":"Point"}
}