<<<<<<< HEAD
{
  "id": 7179534,
  "type": "Feature",
  "properties": {
    "tgn:hierarchy":[
        "tgn:7179534",
        "tgn:1000003",
        "tgn:7003676",
        "tgn:7000084",
        "tgn:7029392"
    ],
    "tgn:id":7179534,
    "tgn:name":"Grupenhagener Bruch",
    "tgn:placetype":[
        "aat:300000206"
    ]
},
  "bbox": [],
  "geometry": {"coordinates":[9.216667,52.066667],"type":"Point"}
}
=======
{"geometry":{"type":"Point","coordinates":[9.216667,52.066667]},"type":"Feature","properties":{"hierarchy":["tgn:7179534","tgn:1000003","tgn:7003676","tgn:7000084","tgn:7029392"],"placetype":["aat:300000206"],"id":7179534,"name:xx":"Grupenhagener Bruch"}}
>>>>>>> 03f74aca74312dbeaf24d7e61306dd6a786dc3d0
