{
  "id": 2566480,
  "type": "Feature",
  "properties": {
    "tgn:hierarchy":[
        "tgn:2566480",
        "tgn:1002165",
        "tgn:1000001",
        "tgn:7012149",
        "tgn:7007517",
        "tgn:7029392"
    ],
    "tgn:id":2566480,
    "tgn:name":"Pamet River",
    "tgn:placetype":[
        "aat:300008707"
    ]
},
  "bbox": [],
  "geometry": {"coordinates":[-70.0167,41.9833],"type":"Point"}
}