<<<<<<< HEAD
{
  "id": 2761264,
  "type": "Feature",
  "properties": {
    "tgn:hierarchy":[
        "tgn:2761264",
        "tgn:1000001",
        "tgn:2000922",
        "tgn:7012149",
        "tgn:7007515",
        "tgn:7029392"
    ],
    "tgn:id":2761264,
    "tgn:name":"West Mark Island Ledge",
    "tgn:placetype":[
        "aat:300132348"
    ]
},
  "bbox": [],
  "geometry": {"coordinates":[-68.7167,44.15],"type":"Point"}
}
=======
{"geometry":{"type":"Point","coordinates":[-68.716700,44.150000]},"type":"Feature","properties":{"hierarchy":["tgn:2761264","tgn:1000001","tgn:2000922","tgn:7012149","tgn:7007515","tgn:7029392"],"placetype":["aat:300132348"],"id":2761264,"name:xx":"West Mark Island Ledge"}}
>>>>>>> 03f74aca74312dbeaf24d7e61306dd6a786dc3d0
