{
  "id": 2504932,
  "type": "Feature",
  "properties": {
    "tgn:hierarchy":[
        "tgn:2504932",
        "tgn:7006450",
        "tgn:1000001",
        "tgn:7012149",
        "tgn:2124002",
        "tgn:7029392"
    ],
    "tgn:id":2504932,
    "tgn:name":"Medvejie Lake",
    "tgn:placetype":[
        "aat:300008680"
    ]
},
  "bbox": [],
  "geometry": {"coordinates":[-135.1167,57.0167],"type":"Point"}
}