{
  "id": 2348403,
  "type": "Feature",
  "properties": {
    "tgn:hierarchy":[
        "tgn:2348403",
        "tgn:2000090",
        "tgn:1000001",
        "tgn:7006451",
        "tgn:7012149",
        "tgn:7029392"
    ],
    "tgn:id":2348403,
    "tgn:name":"Giant Canyon",
    "tgn:placetype":[
        "aat:300008761"
    ]
},
  "bbox": [],
  "geometry": {"coordinates":[-109.3333,36.1833],"type":"Point"}
}