{
  "id": 7343154,
  "type": "Feature",
  "properties": {
    "tgn:hierarchy":[
        "tgn:7343154",
        "tgn:7002803",
        "tgn:1001647",
        "tgn:1000003",
        "tgn:1000095",
        "tgn:7029392"
    ],
    "tgn:id":7343154,
    "tgn:name":"Calar del Cobo, Loma del",
    "tgn:placetype":[
        "aat:300266640"
    ]
},
  "bbox": [],
  "geometry": {"coordinates":[-2.533333,38.233333],"type":"Point"}
}