{
  "id": 7291347,
  "type": "Feature",
  "properties": {
    "tgn:hierarchy":[
        "tgn:7291347",
        "tgn:1001623",
        "tgn:1000049",
        "tgn:1000002",
        "tgn:7029392"
    ],
    "tgn:id":7291347,
    "tgn:name":"Front\u00f3n, Isla",
    "tgn:placetype":[
        "aat:300008791"
    ]
},
  "bbox": [],
  "geometry": {"coordinates":[-75.283333,-46.716667],"type":"Point"}
}