{
  "id": 7125988,
  "type": "Feature",
  "properties": {
    "tgn:hierarchy":[
        "tgn:7125988",
        "tgn:1000003",
        "tgn:7003676",
        "tgn:7000084",
        "tgn:7029392"
    ],
    "tgn:id":7125988,
    "tgn:name":"Nordergroden",
    "tgn:placetype":[
        "aat:300000206"
    ]
},
  "bbox": [],
  "geometry": {"coordinates":[7.983333,53.716667],"type":"Point"}
}