{
  "id": 2100026,
  "type": "Feature",
  "properties": {
    "tgn:hierarchy":[
        "tgn:2100026",
        "tgn:1000001",
        "tgn:2001841",
        "tgn:7012149",
        "tgn:7007825",
        "tgn:7029392"
    ],
    "tgn:id":2100026,
    "tgn:name":"Lawson Crossroad",
    "tgn:placetype":[
        "aat:300008347",
        "aat:300387210"
    ]
},
  "bbox": [],
  "geometry": {"coordinates":[-83.7833,35.65],"type":"Point"}
}