<<<<<<< HEAD
{
  "id": 2257692,
  "type": "Feature",
  "properties": {
    "tgn:hierarchy":[
        "tgn:2257692",
        "tgn:1000001",
        "tgn:7012149",
        "tgn:2002376",
        "tgn:7007923",
        "tgn:7029392"
    ],
    "tgn:id":2257692,
    "tgn:name":"Corral Creek Lake",
    "tgn:placetype":[
        "aat:300008680"
    ]
},
  "bbox": [],
  "geometry": {"coordinates":[-110.7833,42.6833],"type":"Point"}
}
=======
{"geometry":{"type":"Point","coordinates":[-110.783300,42.683300]},"type":"Feature","properties":{"hierarchy":["tgn:2257692","tgn:1000001","tgn:7012149","tgn:2002376","tgn:7007923","tgn:7029392"],"placetype":["aat:300008680"],"id":2257692,"name:xx":"Corral Creek Lake"}}
>>>>>>> 03f74aca74312dbeaf24d7e61306dd6a786dc3d0
