{
  "id": 1045099,
  "type": "Feature",
  "properties": {
    "tgn:hierarchy":[
        "tgn:1045099",
        "tgn:1000003",
        "tgn:1001651",
        "tgn:7003122",
        "tgn:1000080",
        "tgn:7029392"
    ],
    "tgn:id":1045099,
    "tgn:name":"Linguaglossa",
    "tgn:placetype":[
        "aat:300008347"
    ]
},
  "bbox": [],
  "geometry": {"coordinates":[15.133333,37.833333],"type":"Point"}
}