{
  "id": 2418812,
  "type": "Feature",
  "properties": {
    "tgn:hierarchy":[
        "tgn:2418812",
        "tgn:1000001",
        "tgn:7012149",
        "tgn:7029392"
    ],
    "tgn:id":2418812,
    "tgn:name":"James Bayou",
    "tgn:placetype":[
        "aat:300008699"
    ]
},
  "bbox": [],
  "geometry": {"coordinates":[-94.1167,32.8667],"type":"Point"}
}