<<<<<<< HEAD
{
  "id": 7474243,
  "type": "Feature",
  "properties": {
    "tgn:hierarchy":[
        "tgn:7474243",
        "tgn:1000004",
        "tgn:7001014",
        "tgn:1000141",
        "tgn:7029392"
    ],
    "tgn:id":7474243,
    "tgn:name":"Dingtianwei",
    "tgn:placetype":[
        "aat:300008347"
    ]
},
  "bbox": [],
  "geometry": {"coordinates":[120.404041,23.655179],"type":"Point"}
}
=======
{"geometry":{"type":"Point","coordinates":[120.404041,23.655179]},"type":"Feature","properties":{"hierarchy":["tgn:7474243","tgn:1000004","tgn:7001014","tgn:1000141","tgn:7029392"],"placetype":["aat:300008347"],"id":7474243,"name:xx":"Dingtianwei"}}
>>>>>>> 03f74aca74312dbeaf24d7e61306dd6a786dc3d0
