{
  "id": 1139557,
  "type": "Feature",
  "properties": {
    "tgn:hierarchy":[
        "tgn:1139557",
        "tgn:1000004",
        "tgn:7002081",
        "tgn:1000111",
        "tgn:7029392"
    ],
    "tgn:id":1139557,
    "tgn:name":"Shaxi",
    "tgn:placetype":[
        "aat:300008347"
    ]
},
  "bbox": [],
  "geometry": {"coordinates":[121.0667,31.5667],"type":"Point"}
}