{
  "id": 2031017,
  "type": "Feature",
  "properties": {
    "tgn:hierarchy":[
        "tgn:2031017",
        "tgn:1000001",
        "tgn:7012149",
        "tgn:2000545",
        "tgn:7007252",
        "tgn:7029392"
    ],
    "tgn:id":2031017,
    "tgn:name":"Beal",
    "tgn:placetype":[
        "aat:300008347"
    ]
},
  "bbox": [],
  "geometry": {"coordinates":[-87.6167,38.5667],"type":"Point"}
}