{
  "id": 7574197,
  "type": "Feature",
  "properties": {
    "tgn:hierarchy":[
        "tgn:7574197",
        "tgn:7001819",
        "tgn:1000004",
        "tgn:7000198",
        "tgn:7029392"
    ],
    "tgn:id":7574197,
    "tgn:name:en":"Geling",
    "tgn:placetype":[
        "aat:300008347"
    ]
},
  "bbox": [],
  "geometry": {"coordinates":[94.980517,29.145561],"type":"Point"}
}