{
  "id": 2432803,
  "type": "Feature",
  "properties": {
    "tgn:hierarchy":[
        "tgn:2432803",
        "tgn:1000001",
        "tgn:7012149",
        "tgn:2002294",
        "tgn:7013961",
        "tgn:7029392"
    ],
    "tgn:id":2432803,
    "tgn:name":"Keeney Mountain",
    "tgn:placetype":[
        "aat:300266640"
    ]
},
  "bbox": [],
  "geometry": {"coordinates":[-80.7833,37.7167],"type":"Point"}
}