{
  "id": 1052409,
  "type": "Feature",
  "properties": {
    "tgn:hierarchy":[
        "tgn:1052409",
        "tgn:1000004",
        "tgn:7011497",
        "tgn:7002435",
        "tgn:7029392"
    ],
    "tgn:id":1052409,
    "tgn:name":"Baga-Burul",
    "tgn:placetype":[
        "aat:300008347"
    ]
},
  "bbox": [],
  "geometry": {"coordinates":[44.5833,45.9833],"type":"Point"}
}