{
  "id": 7302478,
  "type": "Feature",
  "properties": {
    "tgn:hierarchy":[
        "tgn:7302478",
        "tgn:7002824",
        "tgn:1000003",
        "tgn:7002786",
        "tgn:1000095",
        "tgn:7029392"
    ],
    "tgn:id":7302478,
    "tgn:name":"Noa, R\u00edo",
    "tgn:placetype":[
        "aat:300008699"
    ]
},
  "bbox": [],
  "geometry": {"coordinates":[-8.316667,42.966667],"type":"Point"}
}