{
  "id": 7307918,
  "type": "Feature",
  "properties": {
    "tgn:hierarchy":[
        "tgn:7307918",
        "tgn:1001623",
        "tgn:1000049",
        "tgn:1000002",
        "tgn:7029392"
    ],
    "tgn:id":7307918,
    "tgn:name":"Nef, Estero",
    "tgn:placetype":[
        "aat:300008676"
    ]
},
  "bbox": [],
  "geometry": {"coordinates":[-74.25,-48.116667],"type":"Point"}
}