{
  "id": 2068555,
  "type": "Feature",
  "properties": {
    "tgn:hierarchy":[
        "tgn:2068555",
        "tgn:1000001",
        "tgn:7012149",
        "tgn:1002423",
        "tgn:7007568",
        "tgn:7029392"
    ],
    "tgn:id":2068555,
    "tgn:name":"Climax",
    "tgn:placetype":[
        "aat:300008347"
    ]
},
  "bbox": [],
  "geometry": {"coordinates":[-73.85,42.35],"type":"Point"}
}