{
  "id": 2369956,
  "type": "Feature",
  "properties": {
    "tgn:hierarchy":[
        "tgn:2369956",
        "tgn:7006450",
        "tgn:1000001",
        "tgn:7012149",
        "tgn:2000082",
        "tgn:7029392"
    ],
    "tgn:id":2369956,
    "tgn:name":"Gutchi Creek",
    "tgn:placetype":[
        "aat:300008706"
    ]
},
  "bbox": [],
  "geometry": {"coordinates":[-133.0667,55.85],"type":"Point"}
}