{
  "id": 2295509,
  "type": "Feature",
  "properties": {
    "tgn:hierarchy":[
        "tgn:2295509",
        "tgn:1000001",
        "tgn:7012149",
        "tgn:2001919",
        "tgn:7007825",
        "tgn:7029392"
    ],
    "tgn:id":2295509,
    "tgn:name":"Dripping Spring",
    "tgn:placetype":[
        "aat:300008697"
    ]
},
  "bbox": [],
  "geometry": {"coordinates":[-86.5333,36.4667],"type":"Point"}
}