{
  "id": 1094331,
  "type": "Feature",
  "properties": {
    "tgn:hierarchy":[
        "tgn:1094331",
        "tgn:7001242",
        "tgn:7441555",
        "tgn:7441551",
        "tgn:7029392"
    ],
    "tgn:id":1094331,
    "tgn:name":"Lol",
    "tgn:placetype":[
        "aat:300008347"
    ]
},
  "bbox": [],
  "geometry": {"coordinates":[29.5833,6.4167],"type":"Point"}
}