{
  "id": 2020796,
  "type": "Feature",
  "properties": {
    "tgn:hierarchy":[
        "tgn:2020796",
        "tgn:1000001",
        "tgn:1002269",
        "tgn:7012149",
        "tgn:7007240",
        "tgn:7029392"
    ],
    "tgn:id":2020796,
    "tgn:name":"Paradise Point",
    "tgn:placetype":[
        "aat:300008347"
    ]
},
  "bbox": [],
  "geometry": {"coordinates":[-82.5833,28.8833],"type":"Point"}
}