{
  "id": 2612308,
  "type": "Feature",
  "properties": {
    "tgn:hierarchy":[
        "tgn:2612308",
        "tgn:1000001",
        "tgn:7012149",
        "tgn:2002287",
        "tgn:7013961",
        "tgn:7029392"
    ],
    "tgn:id":2612308,
    "tgn:name":"Red Spruce Knob",
    "tgn:placetype":[
        "aat:300008798"
    ]
},
  "bbox": [],
  "geometry": {"coordinates":[-80.15,38.3167],"type":"Point"}
}