{
  "id": 7413103,
  "type": "Feature",
  "properties": {
    "tgn:hierarchy":[
        "tgn:7413103",
        "tgn:1000001",
        "tgn:7005598",
        "tgn:7005560",
        "tgn:7029392"
    ],
    "tgn:id":7413103,
    "tgn:name":"San Diego Baguedano",
    "tgn:placetype":[
        "aat:300008347"
    ]
},
  "bbox": [],
  "geometry": {"coordinates":[-97.969444,19.413889],"type":"Point"}
}