{
  "id": 1033130,
  "type": "Feature",
  "properties": {
    "tgn:hierarchy":[
        "tgn:1033130",
        "tgn:1000003",
        "tgn:7002881",
        "tgn:1000070",
        "tgn:7029392"
    ],
    "tgn:id":1033130,
    "tgn:name":"Foncine-le-Bas",
    "tgn:placetype":[
        "aat:300008347"
    ]
},
  "bbox": [],
  "geometry": {"coordinates":[6.0333,46.6333],"type":"Point"}
}