{
  "id": 7119665,
  "type": "Feature",
  "properties": {
    "tgn:hierarchy":[
        "tgn:7119665",
        "tgn:7003669",
        "tgn:1000003",
        "tgn:7000084",
        "tgn:7029392"
    ],
    "tgn:id":7119665,
    "tgn:name":"Pellndorf",
    "tgn:placetype":[
        "aat:300008347"
    ]
},
  "bbox": [],
  "geometry": {"coordinates":[11.716667,49.05],"type":"Point"}
}