{
  "id": 1110033,
  "type": "Feature",
  "properties": {
    "tgn:hierarchy":[
        "tgn:1110033",
        "tgn:1000001",
        "tgn:2001418",
        "tgn:7012149",
        "tgn:7007526",
        "tgn:7029392"
    ],
    "tgn:id":1110033,
    "tgn:name":"Kawich Range",
    "tgn:placetype":[
        "aat:300386831"
    ]
},
  "bbox": [],
  "geometry": {"coordinates":[-116.4167,37.9167],"type":"Point"}
}