{
  "id": 1052083,
  "type": "Feature",
  "properties": {
    "tgn:hierarchy":[
        "tgn:1052083",
        "tgn:1000003",
        "tgn:7011662",
        "tgn:7006660",
        "tgn:7029392"
    ],
    "tgn:id":1052083,
    "tgn:name":"Aleksandrija",
    "tgn:placetype":[
        "aat:300008347"
    ]
},
  "bbox": [],
  "geometry": {"coordinates":[33.1167,48.6667],"type":"Point"}
}