{
  "id": 1075166,
  "type": "Feature",
  "properties": {
    "tgn:hierarchy":[
        "tgn:1075166",
        "tgn:1000004",
        "tgn:1001869",
        "tgn:7000198",
        "tgn:7029392"
    ],
    "tgn:id":1075166,
    "tgn:name:en":"Dharampur",
    "tgn:placetype":[
        "aat:300008347"
    ]
},
  "bbox": [],
  "geometry": {"coordinates":[73.173,20.536],"type":"Point"}
}