<<<<<<< HEAD
{
  "id": 7023735,
  "type": "Feature",
  "properties": {
    "tgn:hierarchy":[
        "tgn:7023735",
        "tgn:1000001",
        "tgn:7012149",
        "tgn:7029392"
    ],
    "tgn:id":7023735,
    "tgn:name":"Taylors Millpond",
    "tgn:placetype":[
        "aat:300006191"
    ]
},
  "bbox": [],
  "geometry": {"coordinates":[-77.4333,36.5667],"type":"Point"}
}
=======
{"geometry":{"type":"Point","coordinates":[-77.433300,36.566700]},"type":"Feature","properties":{"hierarchy":["tgn:7023735","tgn:1000001","tgn:7012149","tgn:7029392"],"placetype":["aat:300006191"],"id":7023735,"name:xx":"Taylors Millpond"}}
>>>>>>> 03f74aca74312dbeaf24d7e61306dd6a786dc3d0
