{
  "id": 1131357,
  "type": "Feature",
  "properties": {
    "tgn:hierarchy":[
        "tgn:1131357",
        "tgn:1000003",
        "tgn:7006540",
        "tgn:7029392"
    ],
    "tgn:id":1131357,
    "tgn:name:en":"Valgej\u00f5gi",
    "tgn:placetype":[
        "aat:300008707"
    ]
},
  "bbox": [],
  "geometry": {"coordinates":[25.711,59.579],"type":"Point"}
}