{
  "id": 1069275,
  "type": "Feature",
  "properties": {
    "tgn:hierarchy":[
        "tgn:1069275",
        "tgn:1000004",
        "tgn:7001745",
        "tgn:1000111",
        "tgn:7029392"
    ],
    "tgn:id":1069275,
    "tgn:name":"Jimsar",
    "tgn:placetype":[
        "aat:300008347"
    ]
},
  "bbox": [],
  "geometry": {"coordinates":[89.1667,44.0167],"type":"Point"}
}