<<<<<<< HEAD
{
  "id": 7478476,
  "type": "Feature",
  "properties": {
    "tgn:hierarchy":[
        "tgn:7478476",
        "tgn:1000004",
        "tgn:7492971",
        "tgn:1000141",
        "tgn:7029392"
    ],
    "tgn:id":7478476,
    "tgn:name":"Xingou Qiao",
    "tgn:placetype":[
        "aat:300007836"
    ]
},
  "bbox": [],
  "geometry": {"coordinates":[120.466785,22.468927],"type":"Point"}
}
=======
{"geometry":{"type":"Point","coordinates":[120.466785,22.468927]},"type":"Feature","properties":{"hierarchy":["tgn:7478476","tgn:1000004","tgn:7492971","tgn:1000141","tgn:7029392"],"placetype":["aat:300007836"],"id":7478476,"name:xx":"Xingou Qiao"}}
>>>>>>> 03f74aca74312dbeaf24d7e61306dd6a786dc3d0
