{
  "id": 7461329,
  "type": "Feature",
  "properties": {
    "tgn:hierarchy":[
        "tgn:7461329",
        "tgn:7002445",
        "tgn:1000003",
        "tgn:7008118",
        "tgn:7008591",
        "tgn:7029392"
    ],
    "tgn:id":7461329,
    "tgn:name:en":"Hindlow Station",
    "tgn:placetype":[
        "aat:300007783"
    ]
},
  "bbox": [],
  "geometry": {"coordinates":[-1.866667,53.216667],"type":"Point"}
}