{
  "id": 2467979,
  "type": "Feature",
  "properties": {
    "tgn:hierarchy":[
        "tgn:2467979",
        "tgn:1000001",
        "tgn:2001007",
        "tgn:7012149",
        "tgn:7007521",
        "tgn:7029392"
    ],
    "tgn:id":2467979,
    "tgn:name":"Long Lake",
    "tgn:placetype":[
        "aat:300008680"
    ]
},
  "bbox": [],
  "geometry": {"coordinates":[-92.9333,46.6667],"type":"Point"}
}