{
  "id": 7468342,
  "type": "Feature",
  "properties": {
    "tgn:hierarchy":[
        "tgn:7468342",
        "tgn:7487020",
        "tgn:1000004",
        "tgn:1000141",
        "tgn:7029392"
    ],
    "tgn:id":7468342,
    "tgn:name":"Jiankeng",
    "tgn:placetype":[
        "aat:300008347"
    ]
},
  "bbox": [],
  "geometry": {"coordinates":[120.811583,24.407241],"type":"Point"}
}