{
  "id": 7180771,
  "type": "Feature",
  "properties": {
    "tgn:hierarchy":[
        "tgn:7180771",
        "tgn:7003669",
        "tgn:1000003",
        "tgn:7000084",
        "tgn:7029392"
    ],
    "tgn:id":7180771,
    "tgn:name":"Gasteig",
    "tgn:placetype":[
        "aat:300000206"
    ]
},
  "bbox": [],
  "geometry": {"coordinates":[12.716667,48.233333],"type":"Point"}
}