{
  "id": 2321640,
  "type": "Feature",
  "properties": {
    "tgn:hierarchy":[
        "tgn:2321640",
        "tgn:1000001",
        "tgn:2001409",
        "tgn:7012149",
        "tgn:7007526",
        "tgn:7029392"
    ],
    "tgn:id":2321640,
    "tgn:name":"Fairview Golden Boulder Mine",
    "tgn:placetype":[
        "aat:300000390"
    ]
},
  "bbox": [],
  "geometry": {"coordinates":[-118.1833,39.25],"type":"Point"}
}