{
  "id": 7430302,
  "type": "Feature",
  "properties": {
    "tgn:hierarchy":[
        "tgn:7430302",
        "tgn:7005583",
        "tgn:1000001",
        "tgn:7005560",
        "tgn:7029392"
    ],
    "tgn:id":7430302,
    "tgn:name":"Las Hacienditas",
    "tgn:placetype":[
        "aat:300008347"
    ]
},
  "bbox": [],
  "geometry": {"coordinates":[-106.066667,24.783333],"type":"Point"}
}