{
  "id": 2124624,
  "type": "Feature",
  "properties": {
    "tgn:hierarchy":[
        "tgn:2124624",
        "tgn:1000001",
        "tgn:7012149",
        "tgn:2001459",
        "tgn:7007566",
        "tgn:7029392"
    ],
    "tgn:id":2124624,
    "tgn:name":"Abbott Creek",
    "tgn:placetype":[
        "aat:300008706"
    ]
},
  "bbox": [],
  "geometry": {"coordinates":[-103.6167,36.2333],"type":"Point"}
}