{
  "id": 2753242,
  "type": "Feature",
  "properties": {
    "tgn:hierarchy":[
        "tgn:2753242",
        "tgn:1000001",
        "tgn:7012149",
        "tgn:2001225",
        "tgn:7007523",
        "tgn:7029392"
    ],
    "tgn:id":2753242,
    "tgn:name":"Watered Fork",
    "tgn:placetype":[
        "aat:300008699"
    ]
},
  "bbox": [],
  "geometry": {"coordinates":[-91.6333,36.75],"type":"Point"}
}