{
  "id": 2372059,
  "type": "Feature",
  "properties": {
    "tgn:hierarchy":[
        "tgn:2372059",
        "tgn:1000001",
        "tgn:7012149",
        "tgn:2001878",
        "tgn:7007825",
        "tgn:7029392"
    ],
    "tgn:id":2372059,
    "tgn:name":"Half Pone Branch",
    "tgn:placetype":[
        "aat:300008699"
    ]
},
  "bbox": [],
  "geometry": {"coordinates":[-87.6167,36.2333],"type":"Point"}
}