{
  "id": 7371115,
  "type": "Feature",
  "properties": {
    "tgn:hierarchy":[
        "tgn:7371115",
        "tgn:1000001",
        "tgn:7005592",
        "tgn:7005560",
        "tgn:7029392"
    ],
    "tgn:id":7371115,
    "tgn:name":"Huixtla",
    "tgn:placetype":[
        "aat:300008347"
    ]
},
  "bbox": [],
  "geometry": {"coordinates":[-97.95,20.183333],"type":"Point"}
}