{
  "id": 2070025,
  "type": "Feature",
  "properties": {
    "tgn:hierarchy":[
        "tgn:2070025",
        "tgn:1000001",
        "tgn:7012149",
        "tgn:1002961",
        "tgn:7007568",
        "tgn:7029392"
    ],
    "tgn:id":2070025,
    "tgn:name":"Kingston",
    "tgn:placetype":[
        "aat:300008347"
    ]
},
  "bbox": [],
  "geometry": {"coordinates":[-73.9833,41.9167],"type":"Point"}
}