{
  "id": 2439884,
  "type": "Feature",
  "properties": {
    "tgn:hierarchy":[
        "tgn:2439884",
        "tgn:1000001",
        "tgn:7012149",
        "tgn:2002298",
        "tgn:7013961",
        "tgn:7029392"
    ],
    "tgn:id":2439884,
    "tgn:name":"Kittle Run",
    "tgn:placetype":[
        "aat:300008699"
    ]
},
  "bbox": [],
  "geometry": {"coordinates":[-80.2667,38.85],"type":"Point"}
}