{
  "id": 7227865,
  "type": "Feature",
  "properties": {
    "tgn:hierarchy":[
        "tgn:7227865",
        "tgn:7002751",
        "tgn:7001399",
        "tgn:1000003",
        "tgn:1000074",
        "tgn:7029392"
    ],
    "tgn:id":7227865,
    "tgn:name":"Lith\u00e1dha, \u00c1kra",
    "tgn:placetype":[
        "aat:300008850"
    ]
},
  "bbox": [],
  "geometry": {"coordinates":[22.833333,38.816667],"type":"Point"}
}