{
  "id": 2604958,
  "type": "Feature",
  "properties": {
    "tgn:hierarchy":[
        "tgn:2604958",
        "tgn:1000001",
        "tgn:7012149",
        "tgn:2002154",
        "tgn:7007919",
        "tgn:7029392"
    ],
    "tgn:id":2604958,
    "tgn:name":"Rack Hollow",
    "tgn:placetype":[
        "aat:300008761"
    ]
},
  "bbox": [],
  "geometry": {"coordinates":[-80.2667,37.45],"type":"Point"}
}