{
  "id": 1089501,
  "type": "Feature",
  "properties": {
    "tgn:hierarchy":[
        "tgn:1089501",
        "tgn:7001242",
        "tgn:7016706",
        "tgn:1000159",
        "tgn:7029392"
    ],
    "tgn:id":1089501,
    "tgn:name":"Shangalume",
    "tgn:placetype":[
        "aat:300008347"
    ]
},
  "bbox": [],
  "geometry": {"coordinates":[26.5667,-10.8167],"type":"Point"}
}