{
  "id": 2546248,
  "type": "Feature",
  "properties": {
    "tgn:hierarchy":[
        "tgn:2546248",
        "tgn:1000001",
        "tgn:7012149",
        "tgn:2001420",
        "tgn:7007526",
        "tgn:7029392"
    ],
    "tgn:id":2546248,
    "tgn:name":"North Fork Garden Creek",
    "tgn:placetype":[
        "aat:300008706"
    ]
},
  "bbox": [],
  "geometry": {"coordinates":[-114.5667,39.45],"type":"Point"}
}