{
  "id": 2753213,
  "type": "Feature",
  "properties": {
    "tgn:hierarchy":[
        "tgn:2753213",
        "tgn:1000001",
        "tgn:7012149",
        "tgn:2001708",
        "tgn:7007708",
        "tgn:7029392"
    ],
    "tgn:id":2753213,
    "tgn:name":"Waterbury Mill",
    "tgn:placetype":[
        "aat:300008347"
    ]
},
  "bbox": [],
  "geometry": {"coordinates":[-119.1167,44.65],"type":"Point"}
}