{
  "id": 7265843,
  "type": "Feature",
  "properties": {
    "tgn:hierarchy":[
        "tgn:7265843",
        "tgn:7003619",
        "tgn:1000003",
        "tgn:7016845",
        "tgn:7029392"
    ],
    "tgn:id":7265843,
    "tgn:name:nl":"Indoorniksche Leigraaf",
    "tgn:placetype":[
        "aat:300006075"
    ]
},
  "bbox": [],
  "geometry": {"coordinates":[5.683333,51.933333],"type":"Point"}
}