{
  "id": 1018801,
  "type": "Feature",
  "properties": {
    "tgn:hierarchy":[
        "tgn:1018801",
        "tgn:7593358",
        "tgn:1000001",
        "tgn:7005562",
        "tgn:7029392"
    ],
    "tgn:id":1018801,
    "tgn:name":"Wounta",
    "tgn:placetype":[
        "aat:300008347"
    ]
},
  "bbox": [],
  "geometry": {"coordinates":[-83.5333,13.55],"type":"Point"}
}