{
  "id": 7569224,
  "type": "Feature",
  "properties": {
    "tgn:hierarchy":[
        "tgn:7569224",
        "tgn:1000004",
        "tgn:7000198",
        "tgn:7016788",
        "tgn:7029392"
    ],
    "tgn:id":7569224,
    "tgn:name:en":"Kumarla",
    "tgn:placetype":[
        "aat:300008347"
    ]
},
  "bbox": [],
  "geometry": {"coordinates":[75.702659,25.688891],"type":"Point"}
}