{
  "id": 2043345,
  "type": "Feature",
  "properties": {
    "tgn:hierarchy":[
        "tgn:2043345",
        "tgn:1000001",
        "tgn:7012149",
        "tgn:2000876",
        "tgn:7007256",
        "tgn:7029392"
    ],
    "tgn:id":2043345,
    "tgn:name":"Lozes",
    "tgn:placetype":[
        "aat:300008347",
        "aat:300387210"
    ]
},
  "bbox": [],
  "geometry": {"coordinates":[-91.95,30.0333],"type":"Point"}
}