{
  "id": 7007852,
  "type": "Feature",
  "properties": {
    "tgn:hierarchy":[
        "tgn:7007852",
        "tgn:7003466",
        "tgn:1000003",
        "tgn:1000063",
        "tgn:4012014",
        "tgn:7029392"
    ],
    "tgn:id":7007852,
    "tgn:name":"Ach\u00eane",
    "tgn:placetype":[
        "aat:300008347"
    ]
},
  "bbox": [],
  "geometry": {"coordinates":[5.044535,50.268119],"type":"Point"}
}