{
  "id": 7280500,
  "type": "Feature",
  "properties": {
    "tgn:hierarchy":[
        "tgn:7280500",
        "tgn:7016598",
        "tgn:1000049",
        "tgn:1000002",
        "tgn:7029392"
    ],
    "tgn:id":7280500,
    "tgn:name":"Tambillo",
    "tgn:placetype":[
        "aat:300008347"
    ]
},
  "bbox": [],
  "geometry": {"coordinates":[-68.066667,-23.083333],"type":"Point"}
}