{
  "id": 2745060,
  "type": "Feature",
  "properties": {
    "tgn:hierarchy":[
        "tgn:2745060",
        "tgn:1000001",
        "tgn:7012149",
        "tgn:1002818",
        "tgn:7007252",
        "tgn:7029392"
    ],
    "tgn:id":2745060,
    "tgn:name":"Villa Run",
    "tgn:placetype":[
        "aat:300008699"
    ]
},
  "bbox": [],
  "geometry": {"coordinates":[-85.0167,40.05],"type":"Point"}
}