{
  "id": 2626810,
  "type": "Feature",
  "properties": {
    "tgn:hierarchy":[
        "tgn:2626810",
        "tgn:1000001",
        "tgn:7012149",
        "tgn:1002990",
        "tgn:7007708",
        "tgn:7029392"
    ],
    "tgn:id":2626810,
    "tgn:name":"Rocky Point",
    "tgn:placetype":[
        "aat:300008850"
    ]
},
  "bbox": [],
  "geometry": {"coordinates":[-121.5833,45.0333],"type":"Point"}
}