{
  "id": 7494792,
  "type": "Feature",
  "properties": {
    "tgn:hierarchy":[
        "tgn:7494792",
        "tgn:7468018",
        "tgn:1000004",
        "tgn:1000141",
        "tgn:7029392"
    ],
    "tgn:id":7494792,
    "tgn:name":"Daowanlong",
    "tgn:placetype":[
        "aat:300008347"
    ]
},
  "bbox": [],
  "geometry": {"coordinates":[120.569262,23.260454],"type":"Point"}
}