{
  "id": 2626463,
  "type": "Feature",
  "properties": {
    "tgn:hierarchy":[
        "tgn:2626463",
        "tgn:1000001",
        "tgn:7012149",
        "tgn:2001990",
        "tgn:7007826",
        "tgn:7029392"
    ],
    "tgn:id":2626463,
    "tgn:name":"Rocky Hill",
    "tgn:placetype":[
        "aat:300008347"
    ]
},
  "bbox": [],
  "geometry": {"coordinates":[-98.7833,30.2167],"type":"Point"}
}