{
  "id": 7453277,
  "type": "Feature",
  "properties": {
    "tgn:hierarchy":[
        "tgn:7453277",
        "tgn:7002443",
        "tgn:1000003",
        "tgn:7029493",
        "tgn:7008591",
        "tgn:7029392"
    ],
    "tgn:id":7453277,
    "tgn:name:en":"Cil, Pen y",
    "tgn:placetype":[
        "aat:300008850"
    ]
},
  "bbox": [],
  "geometry": {"coordinates":[-4.733333,52.783333],"type":"Point"}
}