{
  "id": 2010280,
  "type": "Feature",
  "properties": {
    "tgn:hierarchy":[
        "tgn:2010280",
        "tgn:1000001",
        "tgn:7012149",
        "tgn:7007157",
        "tgn:1002857",
        "tgn:7029392"
    ],
    "tgn:id":2010280,
    "tgn:name":"Black Meadow Landing",
    "tgn:placetype":[
        "aat:300008347"
    ]
},
  "bbox": [],
  "geometry": {"coordinates":[-114.1833,34.35],"type":"Point"}
}