{
  "id": 7247947,
  "type": "Feature",
  "properties": {
    "tgn:hierarchy":[
        "tgn:7247947",
        "tgn:7003456",
        "tgn:1000003",
        "tgn:1000063",
        "tgn:7018236",
        "tgn:7029392"
    ],
    "tgn:id":7247947,
    "tgn:name":"Edegemse Beek",
    "tgn:placetype":[
        "aat:300008699"
    ]
},
  "bbox": [],
  "geometry": {"coordinates":[4.386354,51.148705],"type":"Point"}
}