{
  "id": 7507719,
  "type": "Feature",
  "properties": {
    "tgn:hierarchy":[
        "tgn:7507719",
        "tgn:1009227",
        "tgn:1000226",
        "tgn:7018437",
        "tgn:1000006",
        "tgn:7029392"
    ],
    "tgn:id":7507719,
    "tgn:name:en":"Pluto Peak",
    "tgn:placetype":[
        "aat:300008798"
    ]
},
  "bbox": [],
  "geometry": {"coordinates":[168.383333,-44.616667],"type":"Point"}
}