{
  "id": 2655237,
  "type": "Feature",
  "properties": {
    "tgn:hierarchy":[
        "tgn:2655237",
        "tgn:1000001",
        "tgn:2001184",
        "tgn:7012149",
        "tgn:7007523",
        "tgn:7029392"
    ],
    "tgn:id":2655237,
    "tgn:name":"Shannondale Branch",
    "tgn:placetype":[
        "aat:300008699"
    ]
},
  "bbox": [],
  "geometry": {"coordinates":[-92.8333,39.3833],"type":"Point"}
}