{
  "id": 2462032,
  "type": "Feature",
  "properties": {
    "tgn:hierarchy":[
        "tgn:2462032",
        "tgn:1000001",
        "tgn:2001009",
        "tgn:7012149",
        "tgn:7007521",
        "tgn:7029392"
    ],
    "tgn:id":2462032,
    "tgn:name":"Little Twin Lake",
    "tgn:placetype":[
        "aat:300008680"
    ]
},
  "bbox": [],
  "geometry": {"coordinates":[-94.55,47.2833],"type":"Point"}
}