{
  "id": 1066068,
  "type": "Feature",
  "properties": {
    "tgn:hierarchy":[
        "tgn:1066068",
        "tgn:1000004",
        "tgn:7002188",
        "tgn:1000108",
        "tgn:7029392"
    ],
    "tgn:id":1066068,
    "tgn:name":"Kawkareik",
    "tgn:placetype":[
        "aat:300008347"
    ]
},
  "bbox": [],
  "geometry": {"coordinates":[98.2333,16.55],"type":"Point"}
}