{
  "id": 7289889,
  "type": "Feature",
  "properties": {
    "tgn:hierarchy":[
        "tgn:7289889",
        "tgn:1001657",
        "tgn:1000049",
        "tgn:1000002",
        "tgn:7029392"
    ],
    "tgn:id":7289889,
    "tgn:name":"El Bosque",
    "tgn:placetype":[
        "aat:300008347"
    ]
},
  "bbox": [],
  "geometry": {"coordinates":[-70.633333,-30.316667],"type":"Point"}
}