{
  "id": 7038501,
  "type": "Feature",
  "properties": {
    "tgn:hierarchy":[
        "tgn:7038501",
        "tgn:7009084",
        "tgn:7004154",
        "tgn:1000003",
        "tgn:1000080",
        "tgn:7029392"
    ],
    "tgn:id":7038501,
    "tgn:name":"Tirino, Fiume",
    "tgn:placetype":[
        "aat:300008699"
    ]
},
  "bbox": [],
  "geometry": {"coordinates":[13.833333,42.183333],"type":"Point"}
}