{
  "id": 7316283,
  "type": "Feature",
  "properties": {
    "tgn:hierarchy":[
        "tgn:7316283",
        "tgn:1001705",
        "tgn:1000049",
        "tgn:1000002",
        "tgn:7029392"
    ],
    "tgn:id":7316283,
    "tgn:name":"Cardonal, Puntilla",
    "tgn:placetype":[
        "aat:300387002"
    ]
},
  "bbox": [],
  "geometry": {"coordinates":[-72.15,-34.833333],"type":"Point"}
}