{
  "id": 7131680,
  "type": "Feature",
  "properties": {
    "tgn:hierarchy":[
        "tgn:7131680",
        "tgn:1000003",
        "tgn:7000094",
        "tgn:7000084",
        "tgn:7029392"
    ],
    "tgn:id":7131680,
    "tgn:name":"Mechelsdorf",
    "tgn:placetype":[
        "aat:300008347"
    ]
},
  "bbox": [],
  "geometry": {"coordinates":[11.683333,54.116667],"type":"Point"}
}