{
  "id": 2349958,
  "type": "Feature",
  "properties": {
    "tgn:hierarchy":[
        "tgn:2349958",
        "tgn:1000001",
        "tgn:7012149",
        "tgn:2001865",
        "tgn:7007825",
        "tgn:7029392"
    ],
    "tgn:id":2349958,
    "tgn:name":"Gilmore Island",
    "tgn:placetype":[
        "aat:300008791"
    ]
},
  "bbox": [],
  "geometry": {"coordinates":[-83.55,36.1667],"type":"Point"}
}