{
  "id": 7227139,
  "type": "Feature",
  "properties": {
    "tgn:hierarchy":[
        "tgn:7227139",
        "tgn:7002692",
        "tgn:7012056",
        "tgn:1000003",
        "tgn:1000074",
        "tgn:7029392"
    ],
    "tgn:id":7227139,
    "tgn:name":"Mironik\u00edtas",
    "tgn:placetype":[
        "aat:300008347"
    ]
},
  "bbox": [],
  "geometry": {"coordinates":[25.733333,35.333333],"type":"Point"}
}