{
  "id": 2723489,
  "type": "Feature",
  "properties": {
    "tgn:hierarchy":[
        "tgn:2723489",
        "tgn:1000001",
        "tgn:7012149",
        "tgn:2001452",
        "tgn:7007566",
        "tgn:7029392"
    ],
    "tgn:id":2723489,
    "tgn:name":"Tocito Wash",
    "tgn:placetype":[
        "aat:300008699"
    ]
},
  "bbox": [],
  "geometry": {"coordinates":[-108.95,36.35],"type":"Point"}
}