{
  "id": 2736591,
  "type": "Feature",
  "properties": {
    "tgn:hierarchy":[
        "tgn:2736591",
        "tgn:1000001",
        "tgn:7012149",
        "tgn:7007157",
        "tgn:1002857",
        "tgn:7029392"
    ],
    "tgn:id":2736591,
    "tgn:name":"Twin Springs",
    "tgn:placetype":[
        "aat:300008697"
    ]
},
  "bbox": [],
  "geometry": {"coordinates":[-115.65,34.8333],"type":"Point"}
}