{
  "id": 7230545,
  "type": "Feature",
  "properties": {
    "tgn:hierarchy":[
        "tgn:7230545",
        "tgn:7002751",
        "tgn:7001399",
        "tgn:1000003",
        "tgn:1000074",
        "tgn:7029392"
    ],
    "tgn:id":7230545,
    "tgn:name":"Khiliom\u00edli, \u00c1kra",
    "tgn:placetype":[
        "aat:300008850"
    ]
},
  "bbox": [],
  "geometry": {"coordinates":[22.683333,38.85],"type":"Point"}
}