{
  "id": 2620359,
  "type": "Feature",
  "properties": {
    "tgn:hierarchy":[
        "tgn:2620359",
        "tgn:1000001",
        "tgn:7012149",
        "tgn:2001870",
        "tgn:7007825",
        "tgn:7029392"
    ],
    "tgn:id":2620359,
    "tgn:name":"River Knobs",
    "tgn:placetype":[
        "aat:300266640"
    ]
},
  "bbox": [],
  "geometry": {"coordinates":[-83.2667,36.4833],"type":"Point"}
}