{
  "id": 2412433,
  "type": "Feature",
  "properties": {
    "tgn:hierarchy":[
        "tgn:2412433",
        "tgn:7002659",
        "tgn:1000001",
        "tgn:7012149",
        "tgn:2000041",
        "tgn:7029392"
    ],
    "tgn:id":2412433,
    "tgn:name":"Indian Trace",
    "tgn:placetype":[
        "aat:300008347"
    ]
},
  "bbox": [],
  "geometry": {"coordinates":[-86.9167,34.7667],"type":"Point"}
}