{
  "id": 7415455,
  "type": "Feature",
  "properties": {
    "tgn:hierarchy":[
        "tgn:7415455",
        "tgn:1000001",
        "tgn:7005591",
        "tgn:7005560",
        "tgn:7029392"
    ],
    "tgn:id":7415455,
    "tgn:name:es":"Cerro del Oro",
    "tgn:placetype":[
        "aat:300008347"
    ]
},
  "bbox": [],
  "geometry": {"coordinates":[-96.063333,16.014167],"type":"Point"}
}