{
  "id": 7544510,
  "type": "Feature",
  "properties": {
    "tgn:hierarchy":[
        "tgn:7544510",
        "tgn:1000003",
        "tgn:7012216",
        "tgn:1000070",
        "tgn:7029392"
    ],
    "tgn:id":7544510,
    "tgn:name":"Saint-Th\u00e9gonnec",
    "tgn:placetype":[
        "aat:300008347"
    ]
},
  "bbox": [],
  "geometry": {"coordinates":[-3.95,48.516],"type":"Point"}
}