{
  "id": 1044512,
  "type": "Feature",
  "properties": {
    "tgn:hierarchy":[
        "tgn:1044512",
        "tgn:7003158",
        "tgn:1000003",
        "tgn:7003124",
        "tgn:1000080",
        "tgn:7029392"
    ],
    "tgn:id":1044512,
    "tgn:name":"Drena",
    "tgn:placetype":[
        "aat:300008347"
    ]
},
  "bbox": [],
  "geometry": {"coordinates":[10.933333,45.966667],"type":"Point"}
}