{
  "id": 2081421,
  "type": "Feature",
  "properties": {
    "tgn:hierarchy":[
        "tgn:2081421",
        "tgn:1000001",
        "tgn:7012149",
        "tgn:1002386",
        "tgn:7007706",
        "tgn:7029392"
    ],
    "tgn:id":2081421,
    "tgn:name":"Pleasant Corners",
    "tgn:placetype":[
        "aat:300008347"
    ]
},
  "bbox": [],
  "geometry": {"coordinates":[-83.1167,39.8333],"type":"Point"}
}