{
  "id": 2161833,
  "type": "Feature",
  "properties": {
    "tgn:hierarchy":[
        "tgn:2161833",
        "tgn:1000001",
        "tgn:7012149",
        "tgn:1002862",
        "tgn:7007920",
        "tgn:7029392"
    ],
    "tgn:id":2161833,
    "tgn:name":"Bellevue Point",
    "tgn:placetype":[
        "aat:300008850"
    ]
},
  "bbox": [],
  "geometry": {"coordinates":[-123.15,48.5167],"type":"Point"}
}