<<<<<<< HEAD
{
  "id": 2405364,
  "type": "Feature",
  "properties": {
    "tgn:hierarchy":[
        "tgn:2405364",
        "tgn:1000001",
        "tgn:2001632",
        "tgn:7012149",
        "tgn:7007707",
        "tgn:7029392"
    ],
    "tgn:id":2405364,
    "tgn:name":"Hug-me-tight Branch",
    "tgn:placetype":[
        "aat:300008699"
    ]
},
  "bbox": [],
  "geometry": {"coordinates":[-97.3833,34.2667],"type":"Point"}
}
=======
{"geometry":{"type":"Point","coordinates":[-97.383300,34.266700]},"type":"Feature","properties":{"hierarchy":["tgn:2405364","tgn:1000001","tgn:2001632","tgn:7012149","tgn:7007707","tgn:7029392"],"placetype":["aat:300008699"],"id":2405364,"name:xx":"Hug-me-tight Branch"}}
>>>>>>> 03f74aca74312dbeaf24d7e61306dd6a786dc3d0
