{
  "id": 2405364,
  "type": "Feature",
  "properties": {
    "tgn:hierarchy":[
        "tgn:2405364",
        "tgn:1000001",
        "tgn:2001632",
        "tgn:7012149",
        "tgn:7007707",
        "tgn:7029392"
    ],
    "tgn:id":2405364,
    "tgn:name":"Hug-me-tight Branch",
    "tgn:placetype":[
        "aat:300008699"
    ]
},
  "bbox": [],
  "geometry": {"coordinates":[-97.3833,34.2667],"type":"Point"}
}