{
  "id": 2640913,
  "type": "Feature",
  "properties": {
    "tgn:hierarchy":[
        "tgn:2640913",
        "tgn:1000001",
        "tgn:7012149",
        "tgn:2000206",
        "tgn:7007158",
        "tgn:7029392"
    ],
    "tgn:id":2640913,
    "tgn:name":"Sanburg Ditch",
    "tgn:placetype":[
        "aat:300006075"
    ]
},
  "bbox": [],
  "geometry": {"coordinates":[-108.0167,38.8833],"type":"Point"}
}