{
  "id": 7337682,
  "type": "Feature",
  "properties": {
    "tgn:hierarchy":[
        "tgn:7337682",
        "tgn:7002839",
        "tgn:7001158",
        "tgn:1000003",
        "tgn:1000095",
        "tgn:7029392"
    ],
    "tgn:id":7337682,
    "tgn:name":"Cha\u00f1e",
    "tgn:placetype":[
        "aat:300008347"
    ]
},
  "bbox": [],
  "geometry": {"coordinates":[-4.416667,41.333333],"type":"Point"}
}