<<<<<<< HEAD
{
  "id": 2339016,
  "type": "Feature",
  "properties": {
    "tgn:hierarchy":[
        "tgn:2339016",
        "tgn:1000001",
        "tgn:2002323",
        "tgn:7012149",
        "tgn:7007922",
        "tgn:7029392"
    ],
    "tgn:id":2339016,
    "tgn:name":"Franklin Lake",
    "tgn:placetype":[
        "aat:300008680"
    ]
},
  "bbox": [],
  "geometry": {"coordinates":[-88.9833,45.9333],"type":"Point"}
}
=======
{"geometry":{"type":"Point","coordinates":[-88.983300,45.933300]},"type":"Feature","properties":{"hierarchy":["tgn:2339016","tgn:1000001","tgn:2002323","tgn:7012149","tgn:7007922","tgn:7029392"],"placetype":["aat:300008680"],"id":2339016,"name:xx":"Franklin Lake"}}
>>>>>>> 03f74aca74312dbeaf24d7e61306dd6a786dc3d0
