{
  "id": 2339016,
  "type": "Feature",
  "properties": {
    "tgn:hierarchy":[
        "tgn:2339016",
        "tgn:1000001",
        "tgn:2002323",
        "tgn:7012149",
        "tgn:7007922",
        "tgn:7029392"
    ],
    "tgn:id":2339016,
    "tgn:name":"Franklin Lake",
    "tgn:placetype":[
        "aat:300008680"
    ]
},
  "bbox": [],
  "geometry": {"coordinates":[-88.9833,45.9333],"type":"Point"}
}