{
  "id": 1011687,
  "type": "Feature",
  "properties": {
    "tgn:hierarchy":[
        "tgn:1011687",
        "tgn:7001199",
        "tgn:7003494",
        "tgn:1000003",
        "tgn:1000078",
        "tgn:7029392"
    ],
    "tgn:id":1011687,
    "tgn:name":"Cahore Point",
    "tgn:placetype":[
        "aat:300386846"
    ]
},
  "bbox": [],
  "geometry": {"coordinates":[-6.1833,52.5667],"type":"Point"}
}