{
  "id": 7389277,
  "type": "Feature",
  "properties": {
    "tgn:hierarchy":[
        "tgn:7389277",
        "tgn:1000001",
        "tgn:7005589",
        "tgn:7005560",
        "tgn:7029392"
    ],
    "tgn:id":7389277,
    "tgn:name":"Rancho El Pozo",
    "tgn:placetype":[
        "aat:300008347"
    ]
},
  "bbox": [],
  "geometry": {"coordinates":[-100.366667,27.083333],"type":"Point"}
}