{
  "id": 7397007,
  "type": "Feature",
  "properties": {
    "tgn:hierarchy":[
        "tgn:7397007",
        "tgn:7005583",
        "tgn:1000001",
        "tgn:7005560",
        "tgn:7029392"
    ],
    "tgn:id":7397007,
    "tgn:name":"San Miguel del Cantil",
    "tgn:placetype":[
        "aat:300008347"
    ]
},
  "bbox": [],
  "geometry": {"coordinates":[-106.26,24.945833],"type":"Point"}
}