{
  "id": 2616006,
  "type": "Feature",
  "properties": {
    "tgn:hierarchy":[
        "tgn:2616006",
        "tgn:1000001",
        "tgn:7012149",
        "tgn:2001908",
        "tgn:7007825",
        "tgn:7029392"
    ],
    "tgn:id":2616006,
    "tgn:name":"Rhea Springs",
    "tgn:placetype":[
        "aat:300008347",
        "aat:300167671",
        "aat:300387272"
    ]
},
  "bbox": [],
  "geometry": {"coordinates":[-84.8167,35.6667],"type":"Point"}
}