{
  "id": 2322870,
  "type": "Feature",
  "properties": {
    "tgn:hierarchy":[
        "tgn:2322870",
        "tgn:2000948",
        "tgn:1000001",
        "tgn:7012149",
        "tgn:7007520",
        "tgn:7029392"
    ],
    "tgn:id":2322870,
    "tgn:name":"Fanger Drain",
    "tgn:placetype":[
        "aat:300008699"
    ]
},
  "bbox": [],
  "geometry": {"coordinates":[-84.0167,43.85],"type":"Point"}
}