{
  "id": 2672663,
  "type": "Feature",
  "properties": {
    "tgn:hierarchy":[
        "tgn:2672663",
        "tgn:1000001",
        "tgn:7012149",
        "tgn:7007825",
        "tgn:7029392"
    ],
    "tgn:id":2672663,
    "tgn:name":"Smuthers Creek",
    "tgn:placetype":[
        "aat:300008706"
    ]
},
  "bbox": [],
  "geometry": {"coordinates":[-88.1833,36.0667],"type":"Point"}
}