{
  "id": 1002241,
  "type": "Feature",
  "properties": {
    "tgn:hierarchy":[
        "tgn:1002241",
        "tgn:1000001",
        "tgn:7012149",
        "tgn:7007251",
        "tgn:7029392"
    ],
    "tgn:id":1002241,
    "tgn:name":"Cass",
    "tgn:placetype":[
        "aat:300387145",
        "aat:300000771"
    ]
},
  "bbox": [],
  "geometry": {"coordinates":[-90.2333,39.95],"type":"Point"}
}