{
  "id": 2112179,
  "type": "Feature",
  "properties": {
    "tgn:hierarchy":[
        "tgn:2112179",
        "tgn:1000001",
        "tgn:7012149",
        "tgn:2002170",
        "tgn:7007919",
        "tgn:7029392"
    ],
    "tgn:id":2112179,
    "tgn:name":"Harts Shop",
    "tgn:placetype":[
        "aat:300008347",
        "aat:300387210"
    ]
},
  "bbox": [],
  "geometry": {"coordinates":[-77.8167,37.9833],"type":"Point"}
}