{
  "id": 1025358,
  "type": "Feature",
  "properties": {
    "tgn:hierarchy":[
        "tgn:1025358",
        "tgn:7006427",
        "tgn:1000003",
        "tgn:7006417",
        "tgn:7029392"
    ],
    "tgn:id":1025358,
    "tgn:name":"P\u00ebrrenjas",
    "tgn:placetype":[
        "aat:300008347"
    ]
},
  "bbox": [],
  "geometry": {"coordinates":[20.5333,41.0667],"type":"Point"}
}