{
  "id": 2137899,
  "type": "Feature",
  "properties": {
    "tgn:hierarchy":[
        "tgn:2137899",
        "tgn:1000001",
        "tgn:7012149",
        "tgn:2000488",
        "tgn:7007250",
        "tgn:7029392"
    ],
    "tgn:id":2137899,
    "tgn:name":"Arrow Spring",
    "tgn:placetype":[
        "aat:300008697"
    ]
},
  "bbox": [],
  "geometry": {"coordinates":[-116.9167,43.1667],"type":"Point"}
}