{
  "id": 7257351,
  "type": "Feature",
  "properties": {
    "tgn:hierarchy":[
        "tgn:7257351",
        "tgn:7003456",
        "tgn:1000003",
        "tgn:1000063",
        "tgn:7018236",
        "tgn:7029392"
    ],
    "tgn:id":7257351,
    "tgn:name":"Witgoor",
    "tgn:placetype":[
        "aat:300008347"
    ]
},
  "bbox": [],
  "geometry": {"coordinates":[4.521175,51.389642],"type":"Point"}
}