<<<<<<< HEAD
{
  "id": 2703917,
  "type": "Feature",
  "properties": {
    "tgn:hierarchy":[
        "tgn:2703917",
        "tgn:1000001",
        "tgn:7012149",
        "tgn:2001286",
        "tgn:7007524",
        "tgn:7029392"
    ],
    "tgn:id":2703917,
    "tgn:name":"Sunday Creek",
    "tgn:placetype":[
        "aat:300008706"
    ]
},
  "bbox": [],
  "geometry": {"coordinates":[-115.9333,48.85],"type":"Point"}
}
=======
{"geometry":{"type":"Point","coordinates":[-115.933300,48.850000]},"type":"Feature","properties":{"hierarchy":["tgn:2703917","tgn:1000001","tgn:7012149","tgn:2001286","tgn:7007524","tgn:7029392"],"placetype":["aat:300008706"],"id":2703917,"name:xx":"Sunday Creek"}}
>>>>>>> 03f74aca74312dbeaf24d7e61306dd6a786dc3d0
