{
  "id": 7235303,
  "type": "Feature",
  "properties": {
    "tgn:hierarchy":[
        "tgn:7235303",
        "tgn:7002707",
        "tgn:7002705",
        "tgn:1000003",
        "tgn:1000074",
        "tgn:7029392"
    ],
    "tgn:id":7235303,
    "tgn:name":"Fl\u00e1mpouro",
    "tgn:placetype":[
        "aat:300266640"
    ]
},
  "bbox": [],
  "geometry": {"coordinates":[21.063056,39.799167],"type":"Point"}
}