{
  "id": 7553971,
  "type": "Feature",
  "properties": {
    "tgn:hierarchy":[
        "tgn:7553971",
        "tgn:1000004",
        "tgn:7000198",
        "tgn:7031783",
        "tgn:7029392"
    ],
    "tgn:id":7553971,
    "tgn:name:en":"Nimg\u0101chi",
    "tgn:placetype":[
        "aat:300008347"
    ]
},
  "bbox": [],
  "geometry": {"coordinates":[87.75,24.966667],"type":"Point"}
}