{
  "id": 7573435,
  "type": "Feature",
  "properties": {
    "tgn:hierarchy":[
        "tgn:7573435",
        "tgn:1000004",
        "tgn:7000198",
        "tgn:1001895",
        "tgn:7029392"
    ],
    "tgn:id":7573435,
    "tgn:name:en":"Kada",
    "tgn:placetype":[
        "aat:300008347"
    ]
},
  "bbox": [],
  "geometry": {"coordinates":[75.078506,18.896247],"type":"Point"}
}