{
  "id": 7559430,
  "type": "Feature",
  "properties": {
    "tgn:hierarchy":[
        "tgn:7559430",
        "tgn:1000004",
        "tgn:7000198",
        "tgn:7000799",
        "tgn:7029392"
    ],
    "tgn:id":7559430,
    "tgn:name:en":"Saser Kangri",
    "tgn:placetype":[
        "aat:300008795"
    ]
},
  "bbox": [],
  "geometry": {"coordinates":[77.751185,34.867095],"type":"Point"}
}