{
  "id": 7504900,
  "type": "Feature",
  "properties": {
    "tgn:hierarchy":[
        "tgn:7504900",
        "tgn:1009227",
        "tgn:1000226",
        "tgn:7016822",
        "tgn:1000006",
        "tgn:7029392"
    ],
    "tgn:id":7504900,
    "tgn:name:en":"Taringatura Hills",
    "tgn:placetype":[
        "aat:300008795"
    ]
},
  "bbox": [],
  "geometry": {"coordinates":[168.25,-45.916667],"type":"Point"}
}