{
  "id": 7030717,
  "type": "Feature",
  "properties": {
    "tgn:hierarchy":[
        "tgn:7030717",
        "tgn:7001242",
        "tgn:7016833",
        "tgn:1001083",
        "tgn:7029392"
    ],
    "tgn:id":7030717,
    "tgn:name":"Dahsh\u016br",
    "tgn:placetype":[
        "aat:300008347",
        "aat:300000810",
        "aat:300167671",
        "aat:300387004",
        "aat:300008057",
        "aat:300004838",
        "aat:300005926"
    ]
},
  "bbox": [],
  "geometry": {"coordinates":[31.212299,29.802408],"type":"Point"}
}