{
  "id": 1095212,
  "type": "Feature",
  "properties": {
    "tgn:hierarchy":[
        "tgn:1095212",
        "tgn:7001242",
        "tgn:7016833",
        "tgn:7000123",
        "tgn:7029392"
    ],
    "tgn:id":1095212,
    "tgn:name":"Al \u02bbUdays\u0101t",
    "tgn:placetype":[
        "aat:300008347"
    ]
},
  "bbox": [],
  "geometry": {"coordinates":[32.495529,25.581683],"type":"Point"}
}