{
  "id": 7381049,
  "type": "Feature",
  "properties": {
    "tgn:hierarchy":[
        "tgn:7381049",
        "tgn:7005583",
        "tgn:1000001",
        "tgn:7005560",
        "tgn:7029392"
    ],
    "tgn:id":7381049,
    "tgn:name":"Magueyes, Arroyo de",
    "tgn:placetype":[
        "aat:300266554",
        "aat:300008699"
    ]
},
  "bbox": [],
  "geometry": {"coordinates":[-105.616667,26.233333],"type":"Point"}
}