{
  "id": 7457589,
  "type": "Feature",
  "properties": {
    "tgn:hierarchy":[
        "tgn:7457589",
        "tgn:7002445",
        "tgn:7008116",
        "tgn:1000003",
        "tgn:7008591",
        "tgn:7029392"
    ],
    "tgn:id":7457589,
    "tgn:name:en":"Pennance Point",
    "tgn:placetype":[
        "aat:300386846"
    ]
},
  "bbox": [],
  "geometry": {"coordinates":[-5.066667,50.133333],"type":"Point"}
}