{
  "id": 2210128,
  "type": "Feature",
  "properties": {
    "tgn:hierarchy":[
        "tgn:2210128",
        "tgn:1000001",
        "tgn:7012149",
        "tgn:2001719",
        "tgn:7007708",
        "tgn:7029392"
    ],
    "tgn:id":2210128,
    "tgn:name":"Burton Valley",
    "tgn:placetype":[
        "aat:300008761"
    ]
},
  "bbox": [],
  "geometry": {"coordinates":[-119.6667,45.0833],"type":"Point"}
}