{
  "id": 2692644,
  "type": "Feature",
  "properties": {
    "tgn:hierarchy":[
        "tgn:2692644",
        "tgn:1000001",
        "tgn:7012149",
        "tgn:2001303",
        "tgn:7007524",
        "tgn:7029392"
    ],
    "tgn:id":2692644,
    "tgn:name":"Stebbins Creek",
    "tgn:placetype":[
        "aat:300008706"
    ]
},
  "bbox": [],
  "geometry": {"coordinates":[-106.4833,45.6333],"type":"Point"}
}