{
  "id": 2062865,
  "type": "Feature",
  "properties": {
    "tgn:hierarchy":[
        "tgn:2062865",
        "tgn:1000001",
        "tgn:2001411",
        "tgn:7012149",
        "tgn:7007526",
        "tgn:7029392"
    ],
    "tgn:id":2062865,
    "tgn:name":"Dolly Varden",
    "tgn:placetype":[
        "aat:300387016"
    ]
},
  "bbox": [],
  "geometry": {"coordinates":[-114.5333,40.5333],"type":"Point"}
}