{
  "id": 7275201,
  "type": "Feature",
  "properties": {
    "tgn:hierarchy":[
        "tgn:7275201",
        "tgn:7002464",
        "tgn:1000049",
        "tgn:1000002",
        "tgn:7029392"
    ],
    "tgn:id":7275201,
    "tgn:name":"Urizar",
    "tgn:placetype":[
        "aat:300387033"
    ]
},
  "bbox": [],
  "geometry": {"coordinates":[-69.833333,-20.133333],"type":"Point"}
}