{
  "id": 2508237,
  "type": "Feature",
  "properties": {
    "tgn:hierarchy":[
        "tgn:2508237",
        "tgn:1000001",
        "tgn:2002152",
        "tgn:7012149",
        "tgn:7007919",
        "tgn:7029392"
    ],
    "tgn:id":2508237,
    "tgn:name":"Middle Branch Wards Fork Creek",
    "tgn:placetype":[
        "aat:300008706"
    ]
},
  "bbox": [],
  "geometry": {"coordinates":[-78.6333,37.1833],"type":"Point"}
}