{
  "id": 2069566,
  "type": "Feature",
  "properties": {
    "tgn:hierarchy":[
        "tgn:2069566",
        "tgn:1000001",
        "tgn:7012149",
        "tgn:1002924",
        "tgn:7007568",
        "tgn:7029392"
    ],
    "tgn:id":2069566,
    "tgn:name":"Hampton Bays",
    "tgn:placetype":[
        "aat:300008347"
    ]
},
  "bbox": [],
  "geometry": {"coordinates":[-72.5167,40.8667],"type":"Point"}
}