{
  "id": 2139541,
  "type": "Feature",
  "properties": {
    "tgn:hierarchy":[
        "tgn:2139541",
        "tgn:1000001",
        "tgn:7012149",
        "tgn:2001286",
        "tgn:7007524",
        "tgn:7029392"
    ],
    "tgn:id":2139541,
    "tgn:name":"Aster Creek",
    "tgn:placetype":[
        "aat:300008706"
    ]
},
  "bbox": [],
  "geometry": {"coordinates":[-115.9667,48.95],"type":"Point"}
}