{
  "id": 2577598,
  "type": "Feature",
  "properties": {
    "tgn:hierarchy":[
        "tgn:2577598",
        "tgn:1000001",
        "tgn:7012149",
        "tgn:2001145",
        "tgn:7007522",
        "tgn:7029392"
    ],
    "tgn:id":2577598,
    "tgn:name":"Peterson Lake",
    "tgn:placetype":[
        "aat:300008680"
    ]
},
  "bbox": [],
  "geometry": {"coordinates":[-90.25,34.2167],"type":"Point"}
}