<<<<<<< HEAD
{
  "id": 7488032,
  "type": "Feature",
  "properties": {
    "tgn:hierarchy":[
        "tgn:7488032",
        "tgn:1000004",
        "tgn:7467799",
        "tgn:1000141",
        "tgn:7029392"
    ],
    "tgn:id":7488032,
    "tgn:name":"Xiziding",
    "tgn:placetype":[
        "aat:300008347"
    ]
},
  "bbox": [],
  "geometry": {"coordinates":[120.5,23.9],"type":"Point"}
}
=======
{"geometry":{"type":"Point","coordinates":[120.500000,23.900000]},"type":"Feature","properties":{"hierarchy":["tgn:7488032","tgn:1000004","tgn:7467799","tgn:1000141","tgn:7029392"],"placetype":["aat:300008347"],"id":7488032,"name:xx":"Xiziding"}}
>>>>>>> 03f74aca74312dbeaf24d7e61306dd6a786dc3d0
