{
  "id": 1051831,
  "type": "Feature",
  "properties": {
    "tgn:hierarchy":[
        "tgn:1051831",
        "tgn:1000004",
        "tgn:1003407",
        "tgn:7018214",
        "tgn:7002435",
        "tgn:7029392"
    ],
    "tgn:id":1051831,
    "tgn:name":"\u017diguli",
    "tgn:placetype":[
        "aat:300008347"
    ]
},
  "bbox": [],
  "geometry": {"coordinates":[49.3167,53.3667],"type":"Point"}
}