{
  "id": 7452077,
  "type": "Feature",
  "properties": {
    "tgn:hierarchy":[
        "tgn:7452077",
        "tgn:7002445",
        "tgn:1000003",
        "tgn:7012032",
        "tgn:7008591",
        "tgn:7029392"
    ],
    "tgn:id":7452077,
    "tgn:name:en":"Hawkridge",
    "tgn:placetype":[
        "aat:300008347"
    ]
},
  "bbox": [],
  "geometry": {"coordinates":[-3.629167,51.063889],"type":"Point"}
}