<<<<<<< HEAD
{
  "id": 2400992,
  "type": "Feature",
  "properties": {
    "tgn:hierarchy":[
        "tgn:2400992",
        "tgn:1000001",
        "tgn:7012149",
        "tgn:1002506",
        "tgn:7007919",
        "tgn:7029392"
    ],
    "tgn:id":2400992,
    "tgn:name":"Horse Swamp",
    "tgn:placetype":[
        "aat:300008905"
    ]
},
  "bbox": [],
  "geometry": {"coordinates":[-76.85,36.8167],"type":"Point"}
}
=======
{"geometry":{"type":"Point","coordinates":[-76.850000,36.816700]},"type":"Feature","properties":{"hierarchy":["tgn:2400992","tgn:1000001","tgn:7012149","tgn:1002506","tgn:7007919","tgn:7029392"],"placetype":["aat:300008905"],"id":2400992,"name:xx":"Horse Swamp"}}
>>>>>>> 03f74aca74312dbeaf24d7e61306dd6a786dc3d0
