{
  "id": 7274061,
  "type": "Feature",
  "properties": {
    "tgn:hierarchy":[
        "tgn:7274061",
        "tgn:7003616",
        "tgn:1000003",
        "tgn:7016845",
        "tgn:7029392"
    ],
    "tgn:id":7274061,
    "tgn:name:nl":"Zilverkanaal",
    "tgn:placetype":[
        "aat:300006075"
    ]
},
  "bbox": [],
  "geometry": {"coordinates":[5.95,53.066667],"type":"Point"}
}