{
  "id": 2516540,
  "type": "Feature",
  "properties": {
    "tgn:hierarchy":[
        "tgn:2516540",
        "tgn:1000001",
        "tgn:1002219",
        "tgn:7012149",
        "tgn:7007157",
        "tgn:7029392"
    ],
    "tgn:id":2516540,
    "tgn:name":"Mineral Mountain",
    "tgn:placetype":[
        "aat:300008798"
    ]
},
  "bbox": [],
  "geometry": {"coordinates":[-120.4333,38.1833],"type":"Point"}
}