{
  "id": 7412180,
  "type": "Feature",
  "properties": {
    "tgn:hierarchy":[
        "tgn:7412180",
        "tgn:7005580",
        "tgn:1000001",
        "tgn:7005560",
        "tgn:7029392"
    ],
    "tgn:id":7412180,
    "tgn:name":"El Caracol, Lago",
    "tgn:placetype":[
        "aat:300008680"
    ]
},
  "bbox": [],
  "geometry": {"coordinates":[-93.341667,17.833333],"type":"Point"}
}