{
  "id": 7516225,
  "type": "Feature",
  "properties": {
    "tgn:hierarchy":[
        "tgn:7516225",
        "tgn:1008380",
        "tgn:7000507",
        "tgn:1000226",
        "tgn:1000006",
        "tgn:7029392"
    ],
    "tgn:id":7516225,
    "tgn:name:en":"Mangaroa Pa",
    "tgn:placetype":[
        "aat:300008777"
    ]
},
  "bbox": [],
  "geometry": {"coordinates":[174.266667,-35.266667],"type":"Point"}
}