{
  "id": 7240544,
  "type": "Feature",
  "properties": {
    "tgn:hierarchy":[
        "tgn:7240544",
        "tgn:7003456",
        "tgn:1000003",
        "tgn:1000063",
        "tgn:7018236",
        "tgn:7029392"
    ],
    "tgn:id":7240544,
    "tgn:name":"Everveld",
    "tgn:placetype":[
        "aat:300008347"
    ]
},
  "bbox": [],
  "geometry": {"coordinates":[4.783333,50.966667],"type":"Point"}
}