{
  "id": 7425978,
  "type": "Feature",
  "properties": {
    "tgn:hierarchy":[
        "tgn:7425978",
        "tgn:7005581",
        "tgn:1000001",
        "tgn:7005560",
        "tgn:7029392"
    ],
    "tgn:id":7425978,
    "tgn:name":"Pe\u00f1a Dorada",
    "tgn:placetype":[
        "aat:300008347"
    ]
},
  "bbox": [],
  "geometry": {"coordinates":[-107.933333,30.25],"type":"Point"}
}