{
  "id": 2490941,
  "type": "Feature",
  "properties": {
    "tgn:hierarchy":[
        "tgn:2490941",
        "tgn:1000001",
        "tgn:7012149",
        "tgn:2001861",
        "tgn:7007825",
        "tgn:7029392"
    ],
    "tgn:id":2490941,
    "tgn:name":"Manson Saltpeter Cave",
    "tgn:placetype":[
        "aat:300008746"
    ]
},
  "bbox": [],
  "geometry": {"coordinates":[-85.0667,36.3833],"type":"Point"}
}