{
  "id": 7503489,
  "type": "Feature",
  "properties": {
    "tgn:hierarchy":[
        "tgn:7503489",
        "tgn:1000004",
        "tgn:7001009",
        "tgn:1000141",
        "tgn:7029392"
    ],
    "tgn:id":7503489,
    "tgn:name":"Beibu",
    "tgn:placetype":[
        "aat:300008347"
    ]
},
  "bbox": [],
  "geometry": {"coordinates":[120.760556,24.265],"type":"Point"}
}