<<<<<<< HEAD
{
  "id": 2402639,
  "type": "Feature",
  "properties": {
    "tgn:hierarchy":[
        "tgn:2402639",
        "tgn:1000001",
        "tgn:2001418",
        "tgn:7012149",
        "tgn:7007526",
        "tgn:7029392"
    ],
    "tgn:id":2402639,
    "tgn:name":"Hot Creek Valley",
    "tgn:placetype":[
        "aat:300008761"
    ]
},
  "bbox": [],
  "geometry": {"coordinates":[-116.2167,38.7833],"type":"Point"}
}
=======
{"geometry":{"type":"Point","coordinates":[-116.216700,38.783300]},"type":"Feature","properties":{"hierarchy":["tgn:2402639","tgn:1000001","tgn:2001418","tgn:7012149","tgn:7007526","tgn:7029392"],"placetype":["aat:300008761"],"id":2402639,"name:xx":"Hot Creek Valley"}}
>>>>>>> 03f74aca74312dbeaf24d7e61306dd6a786dc3d0
