{
  "id": 7582261,
  "type": "Feature",
  "properties": {
    "tgn:hierarchy":[
        "tgn:7582261",
        "tgn:1000004",
        "tgn:1001871",
        "tgn:7000198",
        "tgn:7029392"
    ],
    "tgn:id":7582261,
    "tgn:name:en":"Sati",
    "tgn:placetype":[
        "aat:300008347"
    ]
},
  "bbox": [],
  "geometry": {"coordinates":[76.973853,30.53063],"type":"Point"}
}