<<<<<<< HEAD
{
  "id": 7365753,
  "type": "Feature",
  "properties": {
    "tgn:hierarchy":[
        "tgn:7365753",
        "tgn:1000001",
        "tgn:7005595",
        "tgn:7005560",
        "tgn:7029392"
    ],
    "tgn:id":7365753,
    "tgn:name":"El T\u00e1scate",
    "tgn:placetype":[
        "aat:300008347"
    ]
},
  "bbox": [],
  "geometry": {"coordinates":[-107.333333,25.633333],"type":"Point"}
}
=======
{"geometry":{"type":"Point","coordinates":[-107.333333,25.633333]},"type":"Feature","properties":{"hierarchy":["tgn:7365753","tgn:1000001","tgn:7005595","tgn:7005560","tgn:7029392"],"placetype":["aat:300008347"],"id":7365753,"name:xx":"El T\u00e1scate"}}
>>>>>>> 03f74aca74312dbeaf24d7e61306dd6a786dc3d0
