{
  "id": 7051529,
  "type": "Feature",
  "properties": {
    "tgn:hierarchy":[
        "tgn:7051529",
        "tgn:7003137",
        "tgn:1000003",
        "tgn:7003080",
        "tgn:1000080",
        "tgn:7029392"
    ],
    "tgn:id":7051529,
    "tgn:name":"Petrana",
    "tgn:placetype":[
        "aat:300008347"
    ]
},
  "bbox": [],
  "geometry": {"coordinates":[13.283333,42.633333],"type":"Point"}
}