{
  "id": 2680096,
  "type": "Feature",
  "properties": {
    "tgn:hierarchy":[
        "tgn:2680096",
        "tgn:1000001",
        "tgn:7012149",
        "tgn:7029392"
    ],
    "tgn:id":2680096,
    "tgn:name":"South Fork Spring River",
    "tgn:placetype":[
        "aat:300008707"
    ]
},
  "bbox": [],
  "geometry": {"coordinates":[-91.4833,36.3167],"type":"Point"}
}