{
  "id": 2743428,
  "type": "Feature",
  "properties": {
    "tgn:hierarchy":[
        "tgn:2743428",
        "tgn:7002659",
        "tgn:1000001",
        "tgn:2000010",
        "tgn:7012149",
        "tgn:7029392"
    ],
    "tgn:id":2743428,
    "tgn:name":"Varden Branch",
    "tgn:placetype":[
        "aat:300008699"
    ]
},
  "bbox": [],
  "geometry": {"coordinates":[-86.6333,32.9833],"type":"Point"}
}