{
  "id": 7171411,
  "type": "Feature",
  "properties": {
    "tgn:hierarchy":[
        "tgn:7171411",
        "tgn:1000003",
        "tgn:7000094",
        "tgn:7000084",
        "tgn:7029392"
    ],
    "tgn:id":7171411,
    "tgn:name":"Hertha",
    "tgn:placetype":[
        "aat:300008347"
    ]
},
  "bbox": [],
  "geometry": {"coordinates":[13.583333,54.55],"type":"Point"}
}