{
  "id": 1090484,
  "type": "Feature",
  "properties": {
    "tgn:hierarchy":[
        "tgn:1090484",
        "tgn:7001242",
        "tgn:7593765",
        "tgn:1000169",
        "tgn:7029392"
    ],
    "tgn:id":1090484,
    "tgn:name":"Lare",
    "tgn:placetype":[
        "aat:300008347"
    ]
},
  "bbox": [],
  "geometry": {"coordinates":[37.9333,0.3333],"type":"Point"}
}