{
  "id": 7517234,
  "type": "Feature",
  "properties": {
    "tgn:hierarchy":[
        "tgn:7517234",
        "tgn:1008380",
        "tgn:1000226",
        "tgn:7018426",
        "tgn:1000006",
        "tgn:7029392"
    ],
    "tgn:id":7517234,
    "tgn:name:en":"Kopia",
    "tgn:placetype":[
        "aat:300008795"
    ]
},
  "bbox": [],
  "geometry": {"coordinates":[174.716667,-38.283333],"type":"Point"}
}