{
  "id": 7293921,
  "type": "Feature",
  "properties": {
    "tgn:hierarchy":[
        "tgn:7293921",
        "tgn:7002824",
        "tgn:1000003",
        "tgn:7002786",
        "tgn:1000095",
        "tgn:7029392"
    ],
    "tgn:id":7293921,
    "tgn:name":"Vij\u00e1n",
    "tgn:placetype":[
        "aat:300008347"
    ]
},
  "bbox": [],
  "geometry": {"coordinates":[-9.016667,42.55],"type":"Point"}
}