{
  "id": 7364036,
  "type": "Feature",
  "properties": {
    "tgn:hierarchy":[
        "tgn:7364036",
        "tgn:1000001",
        "tgn:7005589",
        "tgn:7005560",
        "tgn:7029392"
    ],
    "tgn:id":7364036,
    "tgn:name":"El Barreal",
    "tgn:placetype":[
        "aat:300008347"
    ]
},
  "bbox": [],
  "geometry": {"coordinates":[-100.183333,25.466667],"type":"Point"}
}