{
  "id": 2264357,
  "type": "Feature",
  "properties": {
    "tgn:hierarchy":[
        "tgn:2264357",
        "tgn:1000001",
        "tgn:7012149",
        "tgn:1002646",
        "tgn:7007826",
        "tgn:7029392"
    ],
    "tgn:id":2264357,
    "tgn:name":"Crab Lake",
    "tgn:placetype":[
        "aat:300008680"
    ]
},
  "bbox": [],
  "geometry": {"coordinates":[-96.05,28.6667],"type":"Point"}
}