{
  "id": 2730982,
  "type": "Feature",
  "properties": {
    "tgn:hierarchy":[
        "tgn:2730982",
        "tgn:7006450",
        "tgn:1000001",
        "tgn:7012149",
        "tgn:2000079",
        "tgn:7029392"
    ],
    "tgn:id":2730982,
    "tgn:name":"Tubutulik River",
    "tgn:placetype":[
        "aat:300008707"
    ]
},
  "bbox": [],
  "geometry": {"coordinates":[-162.5667,65.25],"type":"Point"}
}