{
  "id": 7547617,
  "type": "Feature",
  "properties": {
    "tgn:hierarchy":[
        "tgn:7547617",
        "tgn:1000004",
        "tgn:7000198",
        "tgn:7016788",
        "tgn:7029392"
    ],
    "tgn:id":7547617,
    "tgn:name:en":"Ahor",
    "tgn:placetype":[
        "aat:300008347"
    ]
},
  "bbox": [],
  "geometry": {"coordinates":[72.780383,25.368697],"type":"Point"}
}