{
  "id": 2244516,
  "type": "Feature",
  "properties": {
    "tgn:hierarchy":[
        "tgn:2244516",
        "tgn:2001468",
        "tgn:1000001",
        "tgn:7012149",
        "tgn:7007709",
        "tgn:7029392"
    ],
    "tgn:id":2244516,
    "tgn:name":"Clingman Mine Branch",
    "tgn:placetype":[
        "aat:300008699"
    ]
},
  "bbox": [],
  "geometry": {"coordinates":[-81.9167,36.2333],"type":"Point"}
}