{
  "id": 1000639,
  "type": "Feature",
  "properties": {
    "tgn:hierarchy":[
        "tgn:1000639",
        "tgn:1000001",
        "tgn:7005493",
        "tgn:7029392"
    ],
    "tgn:id":1000639,
    "tgn:name":"Huehuetenango",
    "tgn:placetype":[
        "aat:300008631",
        "aat:300387064",
        "aat:300000772"
    ]
},
  "bbox": [],
  "geometry": {"coordinates":[-91.5833,15.6667],"type":"Point"}
}