{
  "id": 2482982,
  "type": "Feature",
  "properties": {
    "tgn:hierarchy":[
        "tgn:2482982",
        "tgn:1000001",
        "tgn:1002276",
        "tgn:7012149",
        "tgn:7007708",
        "tgn:7029392"
    ],
    "tgn:id":2482982,
    "tgn:name":"Larsen Creek",
    "tgn:placetype":[
        "aat:300008706"
    ]
},
  "bbox": [],
  "geometry": {"coordinates":[-123.5833,45.8667],"type":"Point"}
}