{
  "id": 7384292,
  "type": "Feature",
  "properties": {
    "tgn:hierarchy":[
        "tgn:7384292",
        "tgn:7005586",
        "tgn:1000001",
        "tgn:7005560",
        "tgn:7029392"
    ],
    "tgn:id":7384292,
    "tgn:name":"Naranjos de Abajo",
    "tgn:placetype":[
        "aat:300008347"
    ]
},
  "bbox": [],
  "geometry": {"coordinates":[-104.083333,19.916667],"type":"Point"}
}