{
  "id": 2503746,
  "type": "Feature",
  "properties": {
    "tgn:hierarchy":[
        "tgn:2503746",
        "tgn:2000919",
        "tgn:1000001",
        "tgn:7012149",
        "tgn:7007515",
        "tgn:7029392"
    ],
    "tgn:id":2503746,
    "tgn:name":"Meadow Brook",
    "tgn:placetype":[
        "aat:300008699"
    ]
},
  "bbox": [],
  "geometry": {"coordinates":[-67.8667,45.9167],"type":"Point"}
}