{
  "id": 7404845,
  "type": "Feature",
  "properties": {
    "tgn:hierarchy":[
        "tgn:7404845",
        "tgn:7005585",
        "tgn:1000001",
        "tgn:7005560",
        "tgn:7029392"
    ],
    "tgn:id":7404845,
    "tgn:name":"La Lobera",
    "tgn:placetype":[
        "aat:300008347"
    ]
},
  "bbox": [],
  "geometry": {"coordinates":[-99.866667,17.125],"type":"Point"}
}