{
  "id": 7490926,
  "type": "Feature",
  "properties": {
    "tgn:hierarchy":[
        "tgn:7490926",
        "tgn:7468018",
        "tgn:1000004",
        "tgn:1000141",
        "tgn:7029392"
    ],
    "tgn:id":7490926,
    "tgn:name":"Taitang Taibao Nongchang",
    "tgn:placetype":[
        "aat:300000206"
    ]
},
  "bbox": [],
  "geometry": {"coordinates":[120.313333,23.477222],"type":"Point"}
}