{
  "id": 2780639,
  "type": "Feature",
  "properties": {
    "tgn:hierarchy":[
        "tgn:2780639",
        "tgn:1000001",
        "tgn:7012149",
        "tgn:1002676",
        "tgn:7007240",
        "tgn:7029392"
    ],
    "tgn:id":2780639,
    "tgn:name":"Wood Key Cove",
    "tgn:placetype":[
        "aat:300132316"
    ]
},
  "bbox": [],
  "geometry": {"coordinates":[-81.2167,25.5667],"type":"Point"}
}