{
  "id": 7590829,
  "type": "Feature",
  "properties": {
    "tgn:hierarchy":[
        "tgn:7590829",
        "tgn:1000004",
        "tgn:7000198",
        "tgn:7000799",
        "tgn:7029392"
    ],
    "tgn:id":7590829,
    "tgn:name:en":"Char Gali",
    "tgn:placetype":[
        "aat:300259572"
    ]
},
  "bbox": [],
  "geometry": {"coordinates":[74.447222,33.754167],"type":"Point"}
}