{
  "id": 7378261,
  "type": "Feature",
  "properties": {
    "tgn:hierarchy":[
        "tgn:7378261",
        "tgn:7005586",
        "tgn:1000001",
        "tgn:7005560",
        "tgn:7029392"
    ],
    "tgn:id":7378261,
    "tgn:name":"Las Conocas",
    "tgn:placetype":[
        "aat:300008347"
    ]
},
  "bbox": [],
  "geometry": {"coordinates":[-104.083333,21.05],"type":"Point"}
}