{
  "id": 2772010,
  "type": "Feature",
  "properties": {
    "tgn:hierarchy":[
        "tgn:2772010",
        "tgn:1000001",
        "tgn:7012149",
        "tgn:7007523",
        "tgn:7029392"
    ],
    "tgn:id":2772010,
    "tgn:name":"Wilkinson Branch",
    "tgn:placetype":[
        "aat:300008699"
    ]
},
  "bbox": [],
  "geometry": {"coordinates":[-93.1667,37.75],"type":"Point"}
}