{
  "id": 2271883,
  "type": "Feature",
  "properties": {
    "tgn:hierarchy":[
        "tgn:2271883",
        "tgn:7016099",
        "tgn:1000001",
        "tgn:7012149",
        "tgn:7007516",
        "tgn:7029392"
    ],
    "tgn:id":2271883,
    "tgn:name":"Cunninghill Cove",
    "tgn:placetype":[
        "aat:300008347"
    ]
},
  "bbox": [],
  "geometry": {"coordinates":[-76.35,39.35],"type":"Point"}
}