{
  "id": 2483514,
  "type": "Feature",
  "properties": {
    "tgn:hierarchy":[
        "tgn:2483514",
        "tgn:1000001",
        "tgn:7012149",
        "tgn:7007157",
        "tgn:2000191",
        "tgn:7029392"
    ],
    "tgn:id":2483514,
    "tgn:name":"Last Chance Spring",
    "tgn:placetype":[
        "aat:300008697"
    ]
},
  "bbox": [],
  "geometry": {"coordinates":[-123.1833,41.05],"type":"Point"}
}