{
  "id": 1115002,
  "type": "Feature",
  "properties": {
    "tgn:hierarchy":[
        "tgn:1115002",
        "tgn:1009227",
        "tgn:1000226",
        "tgn:7016822",
        "tgn:1000006",
        "tgn:7029392"
    ],
    "tgn:id":1115002,
    "tgn:name:en":"Milford Sound",
    "tgn:placetype":[
        "aat:300266558"
    ]
},
  "bbox": [],
  "geometry": {"coordinates":[167.783333,-44.583333],"type":"Point"}
}