{
  "id": 1002221,
  "type": "Feature",
  "properties": {
    "tgn:hierarchy":[
        "tgn:1002221",
        "tgn:1000001",
        "tgn:7012149",
        "tgn:7007251",
        "tgn:7029392"
    ],
    "tgn:id":1002221,
    "tgn:name":"Calhoun",
    "tgn:placetype":[
        "aat:300387145",
        "aat:300000771"
    ]
},
  "bbox": [],
  "geometry": {"coordinates":[-90.65,39.1667],"type":"Point"}
}