<<<<<<< HEAD
{
  "id": 2335144,
  "type": "Feature",
  "properties": {
    "tgn:hierarchy":[
        "tgn:2335144",
        "tgn:1000001",
        "tgn:7012149",
        "tgn:2001115",
        "tgn:7007522",
        "tgn:7029392"
    ],
    "tgn:id":2335144,
    "tgn:name":"Fort Bayou",
    "tgn:placetype":[
        "aat:300008347"
    ]
},
  "bbox": [],
  "geometry": {"coordinates":[-88.7167,30.4333],"type":"Point"}
}
=======
{"geometry":{"type":"Point","coordinates":[-88.716700,30.433300]},"type":"Feature","properties":{"hierarchy":["tgn:2335144","tgn:1000001","tgn:7012149","tgn:2001115","tgn:7007522","tgn:7029392"],"placetype":["aat:300008347"],"id":2335144,"name:xx":"Fort Bayou"}}
>>>>>>> 03f74aca74312dbeaf24d7e61306dd6a786dc3d0
