{
  "id": 4000627,
  "type": "Feature",
  "properties": {
    "tgn:hierarchy":[
        "tgn:4000627",
        "tgn:7001300",
        "tgn:1000004",
        "tgn:7018456",
        "tgn:1000144",
        "tgn:7029392"
    ],
    "tgn:id":4000627,
    "tgn:name":"Ambar",
    "tgn:placetype":[
        "aat:300008347",
        "aat:300008375"
    ]
},
  "bbox": [],
  "geometry": {"coordinates":[40.9667,37.15],"type":"Point"}
}