{
  "id": 2187803,
  "type": "Feature",
  "properties": {
    "tgn:hierarchy":[
        "tgn:2187803",
        "tgn:7002659",
        "tgn:1000001",
        "tgn:7012149",
        "tgn:2000036",
        "tgn:7029392"
    ],
    "tgn:id":2187803,
    "tgn:name":"Bootleggers Cave",
    "tgn:placetype":[
        "aat:300008746"
    ]
},
  "bbox": [],
  "geometry": {"coordinates":[-86.75,33.5833],"type":"Point"}
}