{
  "id": 2279348,
  "type": "Feature",
  "properties": {
    "tgn:hierarchy":[
        "tgn:2279348",
        "tgn:1000001",
        "tgn:7012149",
        "tgn:2001289",
        "tgn:7007524",
        "tgn:7029392"
    ],
    "tgn:id":2279348,
    "tgn:name":"Deadman Creek",
    "tgn:placetype":[
        "aat:300008706"
    ]
},
  "bbox": [],
  "geometry": {"coordinates":[-110.6667,46.8167],"type":"Point"}
}