{
  "id": 2533836,
  "type": "Feature",
  "properties": {
    "tgn:hierarchy":[
        "tgn:2533836",
        "tgn:1000001",
        "tgn:7012149",
        "tgn:2001904",
        "tgn:7007825",
        "tgn:7029392"
    ],
    "tgn:id":2533836,
    "tgn:name":"Myat Hollow",
    "tgn:placetype":[
        "aat:300008761"
    ]
},
  "bbox": [],
  "geometry": {"coordinates":[-87.9167,35.6667],"type":"Point"}
}