<<<<<<< HEAD
{
  "id": 7487500,
  "type": "Feature",
  "properties": {
    "tgn:hierarchy":[
        "tgn:7487500",
        "tgn:7487020",
        "tgn:1000004",
        "tgn:1000141",
        "tgn:7029392"
    ],
    "tgn:id":7487500,
    "tgn:name":"Moyan Shan",
    "tgn:placetype":[
        "aat:300008777"
    ]
},
  "bbox": [],
  "geometry": {"coordinates":[120.833333,24.566667],"type":"Point"}
}
=======
{"geometry":{"type":"Point","coordinates":[120.833333,24.566667]},"type":"Feature","properties":{"hierarchy":["tgn:7487500","tgn:7487020","tgn:1000004","tgn:1000141","tgn:7029392"],"placetype":["aat:300008777"],"id":7487500,"name:xx":"Moyan Shan"}}
>>>>>>> 03f74aca74312dbeaf24d7e61306dd6a786dc3d0
