<<<<<<< HEAD
{
  "id": 7057204,
  "type": "Feature",
  "properties": {
    "tgn:hierarchy":[
        "tgn:7057204",
        "tgn:7015163",
        "tgn:1000003",
        "tgn:7003121",
        "tgn:1000080",
        "tgn:7029392"
    ],
    "tgn:id":7057204,
    "tgn:name":"Bagnu, Riu lu",
    "tgn:placetype":[
        "aat:300008699"
    ]
},
  "bbox": [],
  "geometry": {"coordinates":[8.683333,40.9],"type":"Point"}
}
=======
{"geometry":{"type":"Point","coordinates":[8.683333,40.900000]},"type":"Feature","properties":{"hierarchy":["tgn:7057204","tgn:7015163","tgn:1000003","tgn:7003121","tgn:1000080","tgn:7029392"],"placetype":["aat:300008699"],"id":7057204,"name:xx":"Bagnu, Riu lu"}}
>>>>>>> 03f74aca74312dbeaf24d7e61306dd6a786dc3d0
