{
  "id": 2205089,
  "type": "Feature",
  "properties": {
    "tgn:hierarchy":[
        "tgn:2205089",
        "tgn:1000001",
        "tgn:7012149",
        "tgn:2000893",
        "tgn:7007256",
        "tgn:7029392"
    ],
    "tgn:id":2205089,
    "tgn:name":"Buhlow, Lake",
    "tgn:placetype":[
        "aat:300008680"
    ]
},
  "bbox": [],
  "geometry": {"coordinates":[-92.4333,31.3333],"type":"Point"}
}