{
  "id": 7447340,
  "type": "Feature",
  "properties": {
    "tgn:hierarchy":[
        "tgn:7447340",
        "tgn:7002445",
        "tgn:7008116",
        "tgn:1000003",
        "tgn:7008591",
        "tgn:7029392"
    ],
    "tgn:id":7447340,
    "tgn:name:en":"Saint Michaels Mount",
    "tgn:placetype":[
        "aat:300008791"
    ]
},
  "bbox": [],
  "geometry": {"coordinates":[-5.483333,50.116667],"type":"Point"}
}