<<<<<<< HEAD
{
  "id": 7174159,
  "type": "Feature",
  "properties": {
    "tgn:hierarchy":[
        "tgn:7174159",
        "tgn:1000003",
        "tgn:7003685",
        "tgn:7000084",
        "tgn:7029392"
    ],
    "tgn:id":7174159,
    "tgn:name":"Gro\u00dfer Litschener Teich",
    "tgn:placetype":[
        "aat:300008688"
    ]
},
  "bbox": [],
  "geometry": {"coordinates":[14.433333,51.366667],"type":"Point"}
}
=======
{"geometry":{"type":"Point","coordinates":[14.433333,51.366667]},"type":"Feature","properties":{"hierarchy":["tgn:7174159","tgn:1000003","tgn:7003685","tgn:7000084","tgn:7029392"],"placetype":["aat:300008688"],"id":7174159,"name:xx":"Gro\u00dfer Litschener Teich"}}
>>>>>>> 03f74aca74312dbeaf24d7e61306dd6a786dc3d0
