{
  "id": 7174159,
  "type": "Feature",
  "properties": {
    "tgn:hierarchy":[
        "tgn:7174159",
        "tgn:1000003",
        "tgn:7003685",
        "tgn:7000084",
        "tgn:7029392"
    ],
    "tgn:id":7174159,
    "tgn:name":"Gro\u00dfer Litschener Teich",
    "tgn:placetype":[
        "aat:300008688"
    ]
},
  "bbox": [],
  "geometry": {"coordinates":[14.433333,51.366667],"type":"Point"}
}