{
  "id": 7341053,
  "type": "Feature",
  "properties": {
    "tgn:hierarchy":[
        "tgn:7341053",
        "tgn:7002824",
        "tgn:1000003",
        "tgn:7002786",
        "tgn:1000095",
        "tgn:7029392"
    ],
    "tgn:id":7341053,
    "tgn:name":"Bugallido",
    "tgn:placetype":[
        "aat:300008347"
    ]
},
  "bbox": [],
  "geometry": {"coordinates":[-8.85,42.95],"type":"Point"}
}