{
  "id": 1131725,
  "type": "Feature",
  "properties": {
    "tgn:hierarchy":[
        "tgn:1131725",
        "tgn:1000001",
        "tgn:7012149",
        "tgn:7007517",
        "tgn:7029392"
    ],
    "tgn:id":1131725,
    "tgn:name":"Westfield",
    "tgn:placetype":[
        "aat:300008707"
    ]
},
  "bbox": [],
  "geometry": {"coordinates":[-73.0167,42.5667],"type":"Point"}
}