{
  "id": 7309951,
  "type": "Feature",
  "properties": {
    "tgn:hierarchy":[
        "tgn:7309951",
        "tgn:1001630",
        "tgn:1000049",
        "tgn:1000002",
        "tgn:7029392"
    ],
    "tgn:id":7309951,
    "tgn:name":"Noriega, Quebrada",
    "tgn:placetype":[
        "aat:300008699"
    ]
},
  "bbox": [],
  "geometry": {"coordinates":[-69.95,-28.35],"type":"Point"}
}