{
  "id": 7530290,
  "type": "Feature",
  "properties": {
    "tgn:hierarchy":[
        "tgn:7530290",
        "tgn:7001242",
        "tgn:7016833",
        "tgn:1001113",
        "tgn:7029392"
    ],
    "tgn:id":7530290,
    "tgn:name":"Kafr ash Shuraf\u0101",
    "tgn:placetype":[
        "aat:300008347"
    ]
},
  "bbox": [],
  "geometry": {"coordinates":[31.699767,30.672279],"type":"Point"}
}