<<<<<<< HEAD
{
  "id": 2768315,
  "type": "Feature",
  "properties": {
    "tgn:hierarchy":[
        "tgn:2768315",
        "tgn:1000001",
        "tgn:2001629",
        "tgn:7012149",
        "tgn:7007707",
        "tgn:7029392"
    ],
    "tgn:id":2768315,
    "tgn:name":"Whitesand Creek",
    "tgn:placetype":[
        "aat:300008706"
    ]
},
  "bbox": [],
  "geometry": {"coordinates":[-95.9833,34.05],"type":"Point"}
}
=======
{"geometry":{"type":"Point","coordinates":[-95.983300,34.050000]},"type":"Feature","properties":{"hierarchy":["tgn:2768315","tgn:1000001","tgn:2001629","tgn:7012149","tgn:7007707","tgn:7029392"],"placetype":["aat:300008706"],"id":2768315,"name:xx":"Whitesand Creek"}}
>>>>>>> 03f74aca74312dbeaf24d7e61306dd6a786dc3d0
