{
  "id": 2768315,
  "type": "Feature",
  "properties": {
    "tgn:hierarchy":[
        "tgn:2768315",
        "tgn:1000001",
        "tgn:2001629",
        "tgn:7012149",
        "tgn:7007707",
        "tgn:7029392"
    ],
    "tgn:id":2768315,
    "tgn:name":"Whitesand Creek",
    "tgn:placetype":[
        "aat:300008706"
    ]
},
  "bbox": [],
  "geometry": {"coordinates":[-95.9833,34.05],"type":"Point"}
}