{
  "id": 2068501,
  "type": "Feature",
  "properties": {
    "tgn:hierarchy":[
        "tgn:2068501",
        "tgn:1000001",
        "tgn:7012149",
        "tgn:7016021",
        "tgn:7007568",
        "tgn:7029392"
    ],
    "tgn:id":2068501,
    "tgn:name":"Childwold",
    "tgn:placetype":[
        "aat:300008347"
    ]
},
  "bbox": [],
  "geometry": {"coordinates":[-74.65,44.2833],"type":"Point"}
}