{
  "id": 2549255,
  "type": "Feature",
  "properties": {
    "tgn:hierarchy":[
        "tgn:2549255",
        "tgn:1000001",
        "tgn:7012149",
        "tgn:1002521",
        "tgn:7007920",
        "tgn:7029392"
    ],
    "tgn:id":2549255,
    "tgn:name":"North Rock",
    "tgn:placetype":[
        "aat:300132348"
    ]
},
  "bbox": [],
  "geometry": {"coordinates":[-124.4667,47.7333],"type":"Point"}
}