{
  "id": 2148691,
  "type": "Feature",
  "properties": {
    "tgn:hierarchy":[
        "tgn:2148691",
        "tgn:1000001",
        "tgn:1002714",
        "tgn:7012149",
        "tgn:7007159",
        "tgn:7029392"
    ],
    "tgn:id":2148691,
    "tgn:name":"Barnes Reservoir",
    "tgn:placetype":[
        "aat:300006191"
    ]
},
  "bbox": [],
  "geometry": {"coordinates":[-72.2167,41.45],"type":"Point"}
}