{
  "id": 2319991,
  "type": "Feature",
  "properties": {
    "tgn:hierarchy":[
        "tgn:2319991",
        "tgn:1000001",
        "tgn:7012149",
        "tgn:2001515",
        "tgn:7007709",
        "tgn:7029392"
    ],
    "tgn:id":2319991,
    "tgn:name":"Evans Creek",
    "tgn:placetype":[
        "aat:300008706"
    ]
},
  "bbox": [],
  "geometry": {"coordinates":[-83.3167,35.0333],"type":"Point"}
}