{
  "id": 2434469,
  "type": "Feature",
  "properties": {
    "tgn:hierarchy":[
        "tgn:2434469",
        "tgn:7030515",
        "tgn:7006450",
        "tgn:1000001",
        "tgn:7012149",
        "tgn:7029392"
    ],
    "tgn:id":2434469,
    "tgn:name":"Kenmore Head",
    "tgn:placetype":[
        "aat:300008798"
    ]
},
  "bbox": [],
  "geometry": {"coordinates":[-163.0333,54.9333],"type":"Point"}
}