{
  "id": 7429368,
  "type": "Feature",
  "properties": {
    "tgn:hierarchy":[
        "tgn:7429368",
        "tgn:1001853",
        "tgn:1000001",
        "tgn:7005560",
        "tgn:7029392"
    ],
    "tgn:id":7429368,
    "tgn:name":"Palos Altos",
    "tgn:placetype":[
        "aat:300008347"
    ]
},
  "bbox": [],
  "geometry": {"coordinates":[-102.716667,25.033333],"type":"Point"}
}