<<<<<<< HEAD
{
  "id": 2335601,
  "type": "Feature",
  "properties": {
    "tgn:hierarchy":[
        "tgn:2335601",
        "tgn:1000001",
        "tgn:1002289",
        "tgn:7012149",
        "tgn:7007240",
        "tgn:7029392"
    ],
    "tgn:id":2335601,
    "tgn:name":"Forth Island",
    "tgn:placetype":[
        "aat:300008791"
    ]
},
  "bbox": [],
  "geometry": {"coordinates":[-81.6,26.2667],"type":"Point"}
}
=======
{"geometry":{"type":"Point","coordinates":[-81.600000,26.266700]},"type":"Feature","properties":{"hierarchy":["tgn:2335601","tgn:1000001","tgn:1002289","tgn:7012149","tgn:7007240","tgn:7029392"],"placetype":["aat:300008791"],"id":2335601,"name:xx":"Forth Island"}}
>>>>>>> 03f74aca74312dbeaf24d7e61306dd6a786dc3d0
