{
  "id": 2274577,
  "type": "Feature",
  "properties": {
    "tgn:hierarchy":[
        "tgn:2274577",
        "tgn:1000001",
        "tgn:2002104",
        "tgn:7012149",
        "tgn:7007827",
        "tgn:7029392"
    ],
    "tgn:id":2274577,
    "tgn:name":"Dalton Canyon",
    "tgn:placetype":[
        "aat:300008761"
    ]
},
  "bbox": [],
  "geometry": {"coordinates":[-110.2667,39.5833],"type":"Point"}
}