{
  "id": 2704921,
  "type": "Feature",
  "properties": {
    "tgn:hierarchy":[
        "tgn:2704921",
        "tgn:1000001",
        "tgn:2000463",
        "tgn:7012149",
        "tgn:7007250",
        "tgn:7029392"
    ],
    "tgn:id":2704921,
    "tgn:name":"Sunset Peak",
    "tgn:placetype":[
        "aat:300008798"
    ]
},
  "bbox": [],
  "geometry": {"coordinates":[-113.3667,43.9667],"type":"Point"}
}