<<<<<<< HEAD
{
  "id": 2408969,
  "type": "Feature",
  "properties": {
    "tgn:hierarchy":[
        "tgn:2408969",
        "tgn:1000001",
        "tgn:7006451",
        "tgn:2000093",
        "tgn:7012149",
        "tgn:7029392"
    ],
    "tgn:id":2408969,
    "tgn:name":"I-nineteen Springs",
    "tgn:placetype":[
        "aat:300008697"
    ]
},
  "bbox": [],
  "geometry": {"coordinates":[-110.0833,33.9333],"type":"Point"}
}
=======
{"geometry":{"type":"Point","coordinates":[-110.083300,33.933300]},"type":"Feature","properties":{"hierarchy":["tgn:2408969","tgn:1000001","tgn:7006451","tgn:2000093","tgn:7012149","tgn:7029392"],"placetype":["aat:300008697"],"id":2408969,"name:xx":"I-nineteen Springs"}}
>>>>>>> 03f74aca74312dbeaf24d7e61306dd6a786dc3d0
