{
  "id": 2403368,
  "type": "Feature",
  "properties": {
    "tgn:hierarchy":[
        "tgn:2403368",
        "tgn:1000001",
        "tgn:7012149",
        "tgn:2000930",
        "tgn:7007515",
        "tgn:7029392"
    ],
    "tgn:id":2403368,
    "tgn:name":"Houston Corner",
    "tgn:placetype":[
        "aat:300008347"
    ]
},
  "bbox": [],
  "geometry": {"coordinates":[-69.3333,44.7833],"type":"Point"}
}