<<<<<<< HEAD
{
  "id": 2403368,
  "type": "Feature",
  "properties": {
    "tgn:hierarchy":[
        "tgn:2403368",
        "tgn:1000001",
        "tgn:7012149",
        "tgn:2000930",
        "tgn:7007515",
        "tgn:7029392"
    ],
    "tgn:id":2403368,
    "tgn:name":"Houston Corner",
    "tgn:placetype":[
        "aat:300008347"
    ]
},
  "bbox": [],
  "geometry": {"coordinates":[-69.3333,44.7833],"type":"Point"}
}
=======
{"geometry":{"type":"Point","coordinates":[-69.333300,44.783300]},"type":"Feature","properties":{"hierarchy":["tgn:2403368","tgn:1000001","tgn:7012149","tgn:2000930","tgn:7007515","tgn:7029392"],"placetype":["aat:300008347"],"id":2403368,"name:xx":"Houston Corner"}}
>>>>>>> 03f74aca74312dbeaf24d7e61306dd6a786dc3d0
