{
  "id": 7592030,
  "type": "Feature",
  "properties": {
    "tgn:hierarchy":[
        "tgn:7592030",
        "tgn:1000004",
        "tgn:7000198",
        "tgn:7000799",
        "tgn:7029392"
    ],
    "tgn:id":7592030,
    "tgn:name:en":"Satw\u0101ri",
    "tgn:placetype":[
        "aat:300008347"
    ]
},
  "bbox": [],
  "geometry": {"coordinates":[74.841235,32.69481],"type":"Point"}
}