{
  "id": 7203300,
  "type": "Feature",
  "properties": {
    "tgn:hierarchy":[
        "tgn:7203300",
        "tgn:1000003",
        "tgn:7003685",
        "tgn:7000084",
        "tgn:7029392"
    ],
    "tgn:id":7203300,
    "tgn:name":"Brunnd\u00f6bra-Bach",
    "tgn:placetype":[
        "aat:300008699"
    ]
},
  "bbox": [],
  "geometry": {"coordinates":[12.466667,50.35],"type":"Point"}
}