{
  "id": 2638637,
  "type": "Feature",
  "properties": {
    "tgn:hierarchy":[
        "tgn:2638637",
        "tgn:1000001",
        "tgn:2002317",
        "tgn:7012149",
        "tgn:7007922",
        "tgn:7029392"
    ],
    "tgn:id":2638637,
    "tgn:name":"Salona",
    "tgn:placetype":[
        "aat:300008347"
    ]
},
  "bbox": [],
  "geometry": {"coordinates":[-87.35,44.7333],"type":"Point"}
}