{
  "id": 1022875,
  "type": "Feature",
  "properties": {
    "tgn:hierarchy":[
        "tgn:1022875",
        "tgn:7006247",
        "tgn:1000047",
        "tgn:7002456",
        "tgn:1000002",
        "tgn:7029392"
    ],
    "tgn:id":1022875,
    "tgn:name":"S\u00e3o Miguel dos Macacos",
    "tgn:placetype":[
        "aat:300008347"
    ]
},
  "bbox": [],
  "geometry": {"coordinates":[-50.4667,-1.1167],"type":"Point"}
}