{
  "id": 2190750,
  "type": "Feature",
  "properties": {
    "tgn:hierarchy":[
        "tgn:2190750",
        "tgn:1000001",
        "tgn:2000463",
        "tgn:7012149",
        "tgn:7007250",
        "tgn:7029392"
    ],
    "tgn:id":2190750,
    "tgn:name":"Boy Scout Cave",
    "tgn:placetype":[
        "aat:300008746"
    ]
},
  "bbox": [],
  "geometry": {"coordinates":[-113.5167,43.4333],"type":"Point"}
}