{
  "id": 7239531,
  "type": "Feature",
  "properties": {
    "tgn:hierarchy":[
        "tgn:7239531",
        "tgn:7003461",
        "tgn:1000003",
        "tgn:1000063",
        "tgn:7018236",
        "tgn:7029392"
    ],
    "tgn:id":7239531,
    "tgn:name":"Grote Leidgracht",
    "tgn:placetype":[
        "aat:300008699"
    ]
},
  "bbox": [],
  "geometry": {"coordinates":[5.066667,50.983333],"type":"Point"}
}