{
  "id": 1125815,
  "type": "Feature",
  "properties": {
    "tgn:hierarchy":[
        "tgn:1125815",
        "tgn:1000004",
        "tgn:7029392"
    ],
    "tgn:id":1125815,
    "tgn:name":"Kurram",
    "tgn:placetype":[
        "aat:300008707"
    ]
},
  "bbox": [],
  "geometry": {"coordinates":[71.4167,32.5833],"type":"Point"}
}