{
  "id": 7012083,
  "type": "Feature",
  "properties": {
    "tgn:hierarchy":[
        "tgn:7012083",
        "tgn:7002751",
        "tgn:7001399",
        "tgn:1000003",
        "tgn:1000074",
        "tgn:7029392"
    ],
    "tgn:id":7012083,
    "tgn:name":"Dimini",
    "tgn:placetype":[
        "aat:300008347",
        "aat:300000810"
    ]
},
  "bbox": [],
  "geometry": {"coordinates":[22.883,39.35],"type":"Point"}
}