{
  "id": 2429101,
  "type": "Feature",
  "properties": {
    "tgn:hierarchy":[
        "tgn:2429101",
        "tgn:1000001",
        "tgn:1002218",
        "tgn:7012149",
        "tgn:7007157",
        "tgn:7029392"
    ],
    "tgn:id":2429101,
    "tgn:name":"Junction House",
    "tgn:placetype":[
        "aat:300008347"
    ]
},
  "bbox": [],
  "geometry": {"coordinates":[-121.2833,39.7333],"type":"Point"}
}