{
  "id": 2235475,
  "type": "Feature",
  "properties": {
    "tgn:hierarchy":[
        "tgn:2235475",
        "tgn:7016099",
        "tgn:1000001",
        "tgn:7012149",
        "tgn:7007516",
        "tgn:7029392"
    ],
    "tgn:id":2235475,
    "tgn:name":"Chesterfield",
    "tgn:placetype":[
        "aat:300008347"
    ]
},
  "bbox": [],
  "geometry": {"coordinates":[-76.65,39.5667],"type":"Point"}
}