<<<<<<< HEAD
{
  "id": 2153336,
  "type": "Feature",
  "properties": {
    "tgn:hierarchy":[
        "tgn:2153336",
        "tgn:1002158",
        "tgn:1000001",
        "tgn:7012149",
        "tgn:7007523",
        "tgn:7029392"
    ],
    "tgn:id":2153336,
    "tgn:name":"Bean Creek",
    "tgn:placetype":[
        "aat:300008706"
    ]
},
  "bbox": [],
  "geometry": {"coordinates":[-91.8333,39.2167],"type":"Point"}
}
=======
{"geometry":{"type":"Point","coordinates":[-91.833300,39.216700]},"type":"Feature","properties":{"hierarchy":["tgn:2153336","tgn:1002158","tgn:1000001","tgn:7012149","tgn:7007523","tgn:7029392"],"placetype":["aat:300008706"],"id":2153336,"name:xx":"Bean Creek"}}
>>>>>>> 03f74aca74312dbeaf24d7e61306dd6a786dc3d0
