{
  "id": 7265622,
  "type": "Feature",
  "properties": {
    "tgn:hierarchy":[
        "tgn:7265622",
        "tgn:7003616",
        "tgn:1000003",
        "tgn:7016845",
        "tgn:7029392"
    ],
    "tgn:id":7265622,
    "tgn:name:nl":"Kleinhorn",
    "tgn:placetype":[
        "aat:300387200"
    ]
},
  "bbox": [],
  "geometry": {"coordinates":[6.183333,53.266667],"type":"Point"}
}