{
  "id": 1058859,
  "type": "Feature",
  "properties": {
    "tgn:hierarchy":[
        "tgn:1058859",
        "tgn:7012251",
        "tgn:1000004",
        "tgn:7006661",
        "tgn:7029392"
    ],
    "tgn:id":1058859,
    "tgn:name":"Rapkan",
    "tgn:placetype":[
        "aat:300008347"
    ]
},
  "bbox": [],
  "geometry": {"coordinates":[70.6667,40.3333],"type":"Point"}
}