{
  "id": 7020019,
  "type": "Feature",
  "properties": {
    "tgn:hierarchy":[
        "tgn:7020019",
        "tgn:1000001",
        "tgn:7012149",
        "tgn:2002384",
        "tgn:7007923",
        "tgn:7029392"
    ],
    "tgn:id":7020019,
    "tgn:name":"Indian Lake",
    "tgn:placetype":[
        "aat:300006191"
    ]
},
  "bbox": [],
  "geometry": {"coordinates":[-110.8833,43.6167],"type":"Point"}
}