{
  "id": 2325792,
  "type": "Feature",
  "properties": {
    "tgn:hierarchy":[
        "tgn:2325792",
        "tgn:1000001",
        "tgn:7012149",
        "tgn:2001858",
        "tgn:7007825",
        "tgn:7029392"
    ],
    "tgn:id":2325792,
    "tgn:name":"Fielder Spring",
    "tgn:placetype":[
        "aat:300008697"
    ]
},
  "bbox": [],
  "geometry": {"coordinates":[-87.45,36.0333],"type":"Point"}
}