{
  "id": 7363731,
  "type": "Feature",
  "properties": {
    "tgn:hierarchy":[
        "tgn:7363731",
        "tgn:1000001",
        "tgn:1001960",
        "tgn:7005560",
        "tgn:7029392"
    ],
    "tgn:id":7363731,
    "tgn:name":"El Gato",
    "tgn:placetype":[
        "aat:300008347"
    ]
},
  "bbox": [],
  "geometry": {"coordinates":[-111.630278,30.806389],"type":"Point"}
}