<<<<<<< HEAD
{
  "id": 7363731,
  "type": "Feature",
  "properties": {
    "tgn:hierarchy":[
        "tgn:7363731",
        "tgn:1000001",
        "tgn:1001960",
        "tgn:7005560",
        "tgn:7029392"
    ],
    "tgn:id":7363731,
    "tgn:name":"El Gato",
    "tgn:placetype":[
        "aat:300008347"
    ]
},
  "bbox": [],
  "geometry": {"coordinates":[-111.630278,30.806389],"type":"Point"}
}
=======
{"geometry":{"type":"Point","coordinates":[-111.630278,30.806389]},"type":"Feature","properties":{"hierarchy":["tgn:7363731","tgn:1000001","tgn:1001960","tgn:7005560","tgn:7029392"],"placetype":["aat:300008347"],"id":7363731,"name:xx":"El Gato"}}
>>>>>>> 03f74aca74312dbeaf24d7e61306dd6a786dc3d0
