{
  "id": 7256575,
  "type": "Feature",
  "properties": {
    "tgn:hierarchy":[
        "tgn:7256575",
        "tgn:7593113",
        "tgn:7016620",
        "tgn:7593112",
        "tgn:1000001",
        "tgn:7029392"
    ],
    "tgn:id":7256575,
    "tgn:name:nl":"Ambuana",
    "tgn:placetype":[
        "aat:300387502"
    ]
},
  "bbox": [],
  "geometry": {"coordinates":[-68.266667,12.15],"type":"Point"}
}