<<<<<<< HEAD
{
  "id": 7028090,
  "type": "Feature",
  "properties": {
    "tgn:hierarchy":[
        "tgn:7028090",
        "tgn:7002445",
        "tgn:1000003",
        "tgn:7008157",
        "tgn:7008591",
        "tgn:7029392"
    ],
    "tgn:id":7028090,
    "tgn:name:en":"Snelland",
    "tgn:placetype":[
        "aat:300008631",
        "aat:300008347",
        "aat:300008372"
    ]
},
  "bbox": [],
  "geometry": {"coordinates":[-0.383333,53.3],"type":"Point"}
}
=======
{"geometry":{"type":"Point","coordinates":[-0.383333,53.300000]},"type":"Feature","properties":{"hierarchy":["tgn:7028090","tgn:7002445","tgn:1000003","tgn:7008157","tgn:7008591","tgn:7029392"],"placetype":["aat:300008631","aat:300008347","aat:300008372"],"name:en":"Snelland","id":7028090}}
>>>>>>> 03f74aca74312dbeaf24d7e61306dd6a786dc3d0
