{
  "id": 7582763,
  "type": "Feature",
  "properties": {
    "tgn:hierarchy":[
        "tgn:7582763",
        "tgn:1000004",
        "tgn:7000198",
        "tgn:1001894",
        "tgn:7029392"
    ],
    "tgn:id":7582763,
    "tgn:name:en":"S\u016bkha Nadi",
    "tgn:placetype":[
        "aat:300008699"
    ]
},
  "bbox": [],
  "geometry": {"coordinates":[78.410755,24.136351],"type":"Point"}
}