{
  "id": 2745219,
  "type": "Feature",
  "properties": {
    "tgn:hierarchy":[
        "tgn:2745219",
        "tgn:1000001",
        "tgn:7012149",
        "tgn:2001750",
        "tgn:7007712",
        "tgn:7029392"
    ],
    "tgn:id":2745219,
    "tgn:name":"Vina",
    "tgn:placetype":[
        "aat:300008347"
    ]
},
  "bbox": [],
  "geometry": {"coordinates":[-78.9333,33.85],"type":"Point"}
}