{
  "id": 7148016,
  "type": "Feature",
  "properties": {
    "tgn:hierarchy":[
        "tgn:7148016",
        "tgn:7003669",
        "tgn:1000003",
        "tgn:7000084",
        "tgn:7029392"
    ],
    "tgn:id":7148016,
    "tgn:name":"Kreuzberg K\u00f6pfl",
    "tgn:placetype":[
        "aat:300008795"
    ]
},
  "bbox": [],
  "geometry": {"coordinates":[11.816667,47.716667],"type":"Point"}
}