{
  "id": 2072726,
  "type": "Feature",
  "properties": {
    "tgn:hierarchy":[
        "tgn:2072726",
        "tgn:1000001",
        "tgn:7012149",
        "tgn:7014612",
        "tgn:7007568",
        "tgn:7029392"
    ],
    "tgn:id":2072726,
    "tgn:name":"Toddville",
    "tgn:placetype":[
        "aat:300008347"
    ]
},
  "bbox": [],
  "geometry": {"coordinates":[-73.8833,41.2833],"type":"Point"}
}