{
  "id": 7407456,
  "type": "Feature",
  "properties": {
    "tgn:hierarchy":[
        "tgn:7407456",
        "tgn:1000001",
        "tgn:1001893",
        "tgn:7005560",
        "tgn:7029392"
    ],
    "tgn:id":7407456,
    "tgn:name":"San Jos\u00e9 del Arenal",
    "tgn:placetype":[
        "aat:300008347"
    ]
},
  "bbox": [],
  "geometry": {"coordinates":[-99.716667,18.858333],"type":"Point"}
}