{
  "id": 7356732,
  "type": "Feature",
  "properties": {
    "tgn:hierarchy":[
        "tgn:7356732",
        "tgn:7005583",
        "tgn:1000001",
        "tgn:7005560",
        "tgn:7029392"
    ],
    "tgn:id":7356732,
    "tgn:name":"Campana, Sierra de la",
    "tgn:placetype":[
        "aat:300008795"
    ]
},
  "bbox": [],
  "geometry": {"coordinates":[-103.55,26.383333],"type":"Point"}
}