{
  "id": 1069709,
  "type": "Feature",
  "properties": {
    "tgn:hierarchy":[
        "tgn:1069709",
        "tgn:1000004",
        "tgn:7001800",
        "tgn:1000111",
        "tgn:7029392"
    ],
    "tgn:id":1069709,
    "tgn:name":"Ledong",
    "tgn:placetype":[
        "aat:300008347"
    ]
},
  "bbox": [],
  "geometry": {"coordinates":[109.15,18.7167],"type":"Point"}
}