{
  "id": 7565799,
  "type": "Feature",
  "properties": {
    "tgn:hierarchy":[
        "tgn:7565799",
        "tgn:1000004",
        "tgn:7000198",
        "tgn:1001894",
        "tgn:7029392"
    ],
    "tgn:id":7565799,
    "tgn:name:en":"Gendal T\u0101l",
    "tgn:placetype":[
        "aat:300008680"
    ]
},
  "bbox": [],
  "geometry": {"coordinates":[79.197424,24.671849],"type":"Point"}
}