{
  "id": 2610123,
  "type": "Feature",
  "properties": {
    "tgn:hierarchy":[
        "tgn:2610123",
        "tgn:1000001",
        "tgn:7012149",
        "tgn:1002676",
        "tgn:7007240",
        "tgn:7029392"
    ],
    "tgn:id":2610123,
    "tgn:name":"Red Bay Bank",
    "tgn:placetype":[
        "aat:300132348"
    ]
},
  "bbox": [],
  "geometry": {"coordinates":[-81.15,24.75],"type":"Point"}
}