{
  "id": 1113144,
  "type": "Feature",
  "properties": {
    "tgn:hierarchy":[
        "tgn:1113144",
        "tgn:1000004",
        "tgn:7005232",
        "tgn:1000111",
        "tgn:7029392"
    ],
    "tgn:id":1113144,
    "tgn:name":"Honghai Wan",
    "tgn:placetype":[
        "aat:300132316"
    ]
},
  "bbox": [],
  "geometry": {"coordinates":[115.1667,22.6667],"type":"Point"}
}