{
  "id": 1031349,
  "type": "Feature",
  "properties": {
    "tgn:hierarchy":[
        "tgn:1031349",
        "tgn:1000003",
        "tgn:7594395",
        "tgn:1000069",
        "tgn:7029392"
    ],
    "tgn:id":1031349,
    "tgn:name":"Karkkila",
    "tgn:placetype":[
        "aat:300008347"
    ]
},
  "bbox": [],
  "geometry": {"coordinates":[24.1667,60.5333],"type":"Point"}
}