<<<<<<< HEAD
{
  "id": 2153164,
  "type": "Feature",
  "properties": {
    "tgn:hierarchy":[
        "tgn:2153164",
        "tgn:1000001",
        "tgn:7012149",
        "tgn:1002785",
        "tgn:7007920",
        "tgn:7029392"
    ],
    "tgn:id":2153164,
    "tgn:name":"Beal Hill",
    "tgn:placetype":[
        "aat:300008798"
    ]
},
  "bbox": [],
  "geometry": {"coordinates":[-122.6167,47.0667],"type":"Point"}
}
=======
{"geometry":{"type":"Point","coordinates":[-122.616700,47.066700]},"type":"Feature","properties":{"hierarchy":["tgn:2153164","tgn:1000001","tgn:7012149","tgn:1002785","tgn:7007920","tgn:7029392"],"placetype":["aat:300008798"],"id":2153164,"name:xx":"Beal Hill"}}
>>>>>>> 03f74aca74312dbeaf24d7e61306dd6a786dc3d0
