{
  "id": 7420617,
  "type": "Feature",
  "properties": {
    "tgn:hierarchy":[
        "tgn:7420617",
        "tgn:1001836",
        "tgn:1000001",
        "tgn:7005560",
        "tgn:7029392"
    ],
    "tgn:id":7420617,
    "tgn:name":"San Lucas, R\u00edo",
    "tgn:placetype":[
        "aat:300008699"
    ]
},
  "bbox": [],
  "geometry": {"coordinates":[-111.609167,25.5625],"type":"Point"}
}