{
  "id": 7544235,
  "type": "Feature",
  "properties": {
    "tgn:hierarchy":[
        "tgn:7544235",
        "tgn:7001242",
        "tgn:7016833",
        "tgn:1001110",
        "tgn:7029392"
    ],
    "tgn:id":7544235,
    "tgn:name":"Ab\u016b Diy\u0101bah, W\u0101d\u012b",
    "tgn:placetype":[
        "aat:300379998"
    ]
},
  "bbox": [],
  "geometry": {"coordinates":[32.100015,29.60972],"type":"Point"}
}