{
  "id": 2164924,
  "type": "Feature",
  "properties": {
    "tgn:hierarchy":[
        "tgn:2164924",
        "tgn:1000001",
        "tgn:7006451",
        "tgn:7012149",
        "tgn:2000103",
        "tgn:7029392"
    ],
    "tgn:id":2164924,
    "tgn:name":"Best Tank",
    "tgn:placetype":[
        "aat:300006191"
    ]
},
  "bbox": [],
  "geometry": {"coordinates":[-111.7667,34.15],"type":"Point"}
}