{
  "id": 7179719,
  "type": "Feature",
  "properties": {
    "tgn:hierarchy":[
        "tgn:7179719",
        "tgn:1000003",
        "tgn:7003689",
        "tgn:7000084",
        "tgn:7029392"
    ],
    "tgn:id":7179719,
    "tgn:name":"Haarburg",
    "tgn:placetype":[
        "aat:300008777"
    ]
},
  "bbox": [],
  "geometry": {"coordinates":[10.45,51.433333],"type":"Point"}
}