{
  "id": 2305305,
  "type": "Feature",
  "properties": {
    "tgn:hierarchy":[
        "tgn:2305305",
        "tgn:1002300",
        "tgn:1000001",
        "tgn:7012149",
        "tgn:7007564",
        "tgn:7029392"
    ],
    "tgn:id":2305305,
    "tgn:name":"East Branch Swift Diamond River",
    "tgn:placetype":[
        "aat:300008707"
    ]
},
  "bbox": [],
  "geometry": {"coordinates":[-71.15,44.9333],"type":"Point"}
}