<<<<<<< HEAD
{
  "id": 2337565,
  "type": "Feature",
  "properties": {
    "tgn:hierarchy":[
        "tgn:2337565",
        "tgn:1000001",
        "tgn:7012149",
        "tgn:2000226",
        "tgn:7007158",
        "tgn:7029392"
    ],
    "tgn:id":2337565,
    "tgn:name":"Fox Acres Reservoir",
    "tgn:placetype":[
        "aat:300006191"
    ]
},
  "bbox": [],
  "geometry": {"coordinates":[-105.5667,40.8],"type":"Point"}
}
=======
{"geometry":{"type":"Point","coordinates":[-105.566700,40.800000]},"type":"Feature","properties":{"hierarchy":["tgn:2337565","tgn:1000001","tgn:7012149","tgn:2000226","tgn:7007158","tgn:7029392"],"placetype":["aat:300006191"],"id":2337565,"name:xx":"Fox Acres Reservoir"}}
>>>>>>> 03f74aca74312dbeaf24d7e61306dd6a786dc3d0
