{
  "id": 7466905,
  "type": "Feature",
  "properties": {
    "tgn:hierarchy":[
        "tgn:7466905",
        "tgn:7002444",
        "tgn:1000003",
        "tgn:7008082",
        "tgn:7008591",
        "tgn:7029392"
    ],
    "tgn:id":7466905,
    "tgn:name:en":"Bulgach, Eilean",
    "tgn:placetype":[
        "aat:300008791"
    ]
},
  "bbox": [],
  "geometry": {"coordinates":[-5.133333,58.55],"type":"Point"}
}