<<<<<<< HEAD
{
  "id": 2252361,
  "type": "Feature",
  "properties": {
    "tgn:hierarchy":[
        "tgn:2252361",
        "tgn:1000001",
        "tgn:7012149",
        "tgn:2002114",
        "tgn:7007827",
        "tgn:7029392"
    ],
    "tgn:id":2252361,
    "tgn:name":"Conger Mountain",
    "tgn:placetype":[
        "aat:300008798"
    ]
},
  "bbox": [],
  "geometry": {"coordinates":[-113.7,39.2333],"type":"Point"}
}
=======
{"geometry":{"type":"Point","coordinates":[-113.700000,39.233300]},"type":"Feature","properties":{"hierarchy":["tgn:2252361","tgn:1000001","tgn:7012149","tgn:2002114","tgn:7007827","tgn:7029392"],"placetype":["aat:300008798"],"id":2252361,"name:xx":"Conger Mountain"}}
>>>>>>> 03f74aca74312dbeaf24d7e61306dd6a786dc3d0
