{
  "id": 2501194,
  "type": "Feature",
  "properties": {
    "tgn:hierarchy":[
        "tgn:2501194",
        "tgn:7002659",
        "tgn:1000001",
        "tgn:2000005",
        "tgn:7012149",
        "tgn:7029392"
    ],
    "tgn:id":2501194,
    "tgn:name":"McGhee Lake Number Two",
    "tgn:placetype":[
        "aat:300006191"
    ]
},
  "bbox": [],
  "geometry": {"coordinates":[-85.95,32.1167],"type":"Point"}
}