{
  "id": 7592488,
  "type": "Feature",
  "properties": {
    "tgn:hierarchy":[
        "tgn:7592488",
        "tgn:1000004",
        "tgn:7000198",
        "tgn:7000799",
        "tgn:7029392"
    ],
    "tgn:id":7592488,
    "tgn:name:en":"Sar\u0101h",
    "tgn:placetype":[
        "aat:300008347"
    ]
},
  "bbox": [],
  "geometry": {"coordinates":[74.947674,32.746962],"type":"Point"}
}