{
  "id": 2462260,
  "type": "Feature",
  "properties": {
    "tgn:hierarchy":[
        "tgn:2462260",
        "tgn:1000001",
        "tgn:7012149",
        "tgn:7007566",
        "tgn:7029392"
    ],
    "tgn:id":2462260,
    "tgn:name":"Little Walt Canyon",
    "tgn:placetype":[
        "aat:300000390"
    ]
},
  "bbox": [],
  "geometry": {"coordinates":[-104.4667,32.4167],"type":"Point"}
}