{
  "id": 1108073,
  "type": "Feature",
  "properties": {
    "tgn:hierarchy":[
        "tgn:1108073",
        "tgn:1000004",
        "tgn:7012911",
        "tgn:7014786",
        "tgn:7029392"
    ],
    "tgn:id":1108073,
    "tgn:name":"Kil'baj, gora",
    "tgn:placetype":[
        "aat:300008777"
    ]
},
  "bbox": [],
  "geometry": {"coordinates":[53.95,43.7167],"type":"Point"}
}