{
  "id": 1054308,
  "type": "Feature",
  "properties": {
    "tgn:hierarchy":[
        "tgn:1054308",
        "tgn:1000004",
        "tgn:7011528",
        "tgn:7002435",
        "tgn:7029392"
    ],
    "tgn:id":1054308,
    "tgn:name":"Ilbenge",
    "tgn:placetype":[
        "aat:300008347"
    ]
},
  "bbox": [],
  "geometry": {"coordinates":[124.9167,62.9667],"type":"Point"}
}