{
  "id": 7218902,
  "type": "Feature",
  "properties": {
    "tgn:hierarchy":[
        "tgn:7218902",
        "tgn:7011270",
        "tgn:7002674",
        "tgn:1000003",
        "tgn:1000074",
        "tgn:7029392"
    ],
    "tgn:id":7218902,
    "tgn:name":"Prason\u00edsi, Vrachonis\u00edda",
    "tgn:placetype":[
        "aat:300008791"
    ]
},
  "bbox": [],
  "geometry": {"coordinates":[25.261667,37.013333],"type":"Point"}
}