{
  "id": 7018899,
  "type": "Feature",
  "properties": {
    "tgn:hierarchy":[
        "tgn:7018899",
        "tgn:7002445",
        "tgn:1000003",
        "tgn:7008136",
        "tgn:7008591",
        "tgn:7029392"
    ],
    "tgn:id":7018899,
    "tgn:name:en":"Barking and Dagenham",
    "tgn:placetype":[
        "aat:300387064",
        "aat:300387145",
        "aat:300000778"
    ]
},
  "bbox": [],
  "geometry": {"coordinates":[0.1167,51.55],"type":"Point"}
}