{
  "id": 2192593,
  "type": "Feature",
  "properties": {
    "tgn:hierarchy":[
        "tgn:2192593",
        "tgn:1002338",
        "tgn:1000001",
        "tgn:7012149",
        "tgn:7007516",
        "tgn:7029392"
    ],
    "tgn:id":2192593,
    "tgn:name":"Brannock Bay",
    "tgn:placetype":[
        "aat:300132316"
    ]
},
  "bbox": [],
  "geometry": {"coordinates":[-76.2667,38.5833],"type":"Point"}
}