{
  "id": 7315624,
  "type": "Feature",
  "properties": {
    "tgn:hierarchy":[
        "tgn:7315624",
        "tgn:1001695",
        "tgn:1000049",
        "tgn:1000002",
        "tgn:7029392"
    ],
    "tgn:id":7315624,
    "tgn:name":"Chacarillas",
    "tgn:placetype":[
        "aat:300008347"
    ]
},
  "bbox": [],
  "geometry": {"coordinates":[-71.166667,-34.633333],"type":"Point"}
}