{
  "id": 1000831,
  "type": "Feature",
  "properties": {
    "tgn:hierarchy":[
        "tgn:1000831",
        "tgn:1000002",
        "tgn:7015386",
        "tgn:7029392"
    ],
    "tgn:id":1000831,
    "tgn:name":"Coronie",
    "tgn:placetype":[
        "aat:300387064",
        "aat:300387081"
    ]
},
  "bbox": [],
  "geometry": {"coordinates":[-56.25,5.583],"type":"Point"}
}