{
  "id": 7407830,
  "type": "Feature",
  "properties": {
    "tgn:hierarchy":[
        "tgn:7407830",
        "tgn:1000001",
        "tgn:1001893",
        "tgn:7005560",
        "tgn:7029392"
    ],
    "tgn:id":7407830,
    "tgn:name":"San Jer\u00f3nimo de los Dolores",
    "tgn:placetype":[
        "aat:300008347"
    ]
},
  "bbox": [],
  "geometry": {"coordinates":[-100.066667,19.65],"type":"Point"}
}