{
  "id": 2298584,
  "type": "Feature",
  "properties": {
    "tgn:hierarchy":[
        "tgn:2298584",
        "tgn:1000001",
        "tgn:7012149",
        "tgn:2001437",
        "tgn:7007566",
        "tgn:7029392"
    ],
    "tgn:id":2298584,
    "tgn:name":"Dry Section Tank",
    "tgn:placetype":[
        "aat:300006191"
    ]
},
  "bbox": [],
  "geometry": {"coordinates":[-108.8667,32.9667],"type":"Point"}
}