{
  "id": 1089976,
  "type": "Feature",
  "properties": {
    "tgn:hierarchy":[
        "tgn:1089976",
        "tgn:7001242",
        "tgn:1001535",
        "tgn:7000489",
        "tgn:7029392"
    ],
    "tgn:id":1089976,
    "tgn:name":"Weber\u012b Bekera",
    "tgn:placetype":[
        "aat:300008347"
    ]
},
  "bbox": [],
  "geometry": {"coordinates":[39.05,9.65],"type":"Point"}
}