{
  "id": 1074312,
  "type": "Feature",
  "properties": {
    "tgn:hierarchy":[
        "tgn:1074312",
        "tgn:7004732",
        "tgn:1000004",
        "tgn:7004542",
        "tgn:1000111",
        "tgn:7029392"
    ],
    "tgn:id":1074312,
    "tgn:name":"Tin Sam",
    "tgn:placetype":[
        "aat:300008347"
    ]
},
  "bbox": [],
  "geometry": {"coordinates":[114.1833,22.3667],"type":"Point"}
}