{
  "id": 2028444,
  "type": "Feature",
  "properties": {
    "tgn:hierarchy":[
        "tgn:2028444",
        "tgn:1000001",
        "tgn:7012149",
        "tgn:1002532",
        "tgn:7007251",
        "tgn:7029392"
    ],
    "tgn:id":2028444,
    "tgn:name":"Indian Oaks",
    "tgn:placetype":[
        "aat:300008347"
    ]
},
  "bbox": [],
  "geometry": {"coordinates":[-87.85,41.1833],"type":"Point"}
}