{
  "id": 7432254,
  "type": "Feature",
  "properties": {
    "tgn:hierarchy":[
        "tgn:7432254",
        "tgn:7005586",
        "tgn:1000001",
        "tgn:7005560",
        "tgn:7029392"
    ],
    "tgn:id":7432254,
    "tgn:name":"Dolores",
    "tgn:placetype":[
        "aat:300008347"
    ]
},
  "bbox": [],
  "geometry": {"coordinates":[-103.333333,22.016667],"type":"Point"}
}