{
  "id": 7164079,
  "type": "Feature",
  "properties": {
    "tgn:hierarchy":[
        "tgn:7164079",
        "tgn:7000096",
        "tgn:1000003",
        "tgn:7000084",
        "tgn:7029392"
    ],
    "tgn:id":7164079,
    "tgn:name":"H\u00fcntenfeld Berge",
    "tgn:placetype":[
        "aat:300008777"
    ]
},
  "bbox": [],
  "geometry": {"coordinates":[12.583333,52.85],"type":"Point"}
}