{
  "id": 7157855,
  "type": "Feature",
  "properties": {
    "tgn:hierarchy":[
        "tgn:7157855",
        "tgn:7003669",
        "tgn:1000003",
        "tgn:7000084",
        "tgn:7029392"
    ],
    "tgn:id":7157855,
    "tgn:name":"Katzentr\u00f6gel",
    "tgn:placetype":[
        "aat:300011692"
    ]
},
  "bbox": [],
  "geometry": {"coordinates":[12.05,49.916667],"type":"Point"}
}