{
  "id": 2649848,
  "type": "Feature",
  "properties": {
    "tgn:hierarchy":[
        "tgn:2649848",
        "tgn:7002659",
        "tgn:1000001",
        "tgn:7012149",
        "tgn:2000039",
        "tgn:7029392"
    ],
    "tgn:id":2649848,
    "tgn:name":"Scrounge Springs Cave",
    "tgn:placetype":[
        "aat:300008746"
    ]
},
  "bbox": [],
  "geometry": {"coordinates":[-87.3667,34.3667],"type":"Point"}
}