{
  "id": 2641026,
  "type": "Feature",
  "properties": {
    "tgn:hierarchy":[
        "tgn:2641026",
        "tgn:7002659",
        "tgn:1000001",
        "tgn:7012149",
        "tgn:2000059",
        "tgn:7029392"
    ],
    "tgn:id":2641026,
    "tgn:name":"Sand Branch",
    "tgn:placetype":[
        "aat:300008699"
    ]
},
  "bbox": [],
  "geometry": {"coordinates":[-88.0167,32.5333],"type":"Point"}
}