{
  "id": 2740609,
  "type": "Feature",
  "properties": {
    "tgn:hierarchy":[
        "tgn:2740609",
        "tgn:1000001",
        "tgn:7012149",
        "tgn:2002374",
        "tgn:7007923",
        "tgn:7029392"
    ],
    "tgn:id":2740609,
    "tgn:name":"Upper Phil Kearny Ditch",
    "tgn:placetype":[
        "aat:300006075"
    ]
},
  "bbox": [],
  "geometry": {"coordinates":[-106.85,44.5167],"type":"Point"}
}