{
  "id": 1105508,
  "type": "Feature",
  "properties": {
    "tgn:hierarchy":[
        "tgn:1105508",
        "tgn:7017300",
        "tgn:1000003",
        "tgn:7006663",
        "tgn:7029392"
    ],
    "tgn:id":1105508,
    "tgn:name":"Mali Rajinac",
    "tgn:placetype":[
        "aat:300008795"
    ]
},
  "bbox": [],
  "geometry": {"coordinates":[14.9833,44.8167],"type":"Point"}
}