{
  "id": 7201420,
  "type": "Feature",
  "properties": {
    "tgn:hierarchy":[
        "tgn:7201420",
        "tgn:1000003",
        "tgn:7003677",
        "tgn:7000084",
        "tgn:7029392"
    ],
    "tgn:id":7201420,
    "tgn:name":"Brand Holz",
    "tgn:placetype":[
        "aat:300008863"
    ]
},
  "bbox": [],
  "geometry": {"coordinates":[8.466667,51.566667],"type":"Point"}
}