{
  "id": 2515633,
  "type": "Feature",
  "properties": {
    "tgn:hierarchy":[
        "tgn:2515633",
        "tgn:1000001",
        "tgn:7012149",
        "tgn:2002009",
        "tgn:7007826",
        "tgn:7029392"
    ],
    "tgn:id":2515633,
    "tgn:name":"Millstead Branch",
    "tgn:placetype":[
        "aat:300008699"
    ]
},
  "bbox": [],
  "geometry": {"coordinates":[-94.2833,31.05],"type":"Point"}
}