{
  "id": 2077489,
  "type": "Feature",
  "properties": {
    "tgn:hierarchy":[
        "tgn:2077489",
        "tgn:1000001",
        "tgn:2001583",
        "tgn:7012149",
        "tgn:7007705",
        "tgn:7029392"
    ],
    "tgn:id":2077489,
    "tgn:name":"Charbonneau",
    "tgn:placetype":[
        "aat:300008347",
        "aat:300387210"
    ]
},
  "bbox": [],
  "geometry": {"coordinates":[-103.75,47.85],"type":"Point"}
}