{
  "id": 2622226,
  "type": "Feature",
  "properties": {
    "tgn:hierarchy":[
        "tgn:2622226",
        "tgn:1000001",
        "tgn:7012149",
        "tgn:2000227",
        "tgn:7007158",
        "tgn:7029392"
    ],
    "tgn:id":2622226,
    "tgn:name":"Roberts Spring Number 2",
    "tgn:placetype":[
        "aat:300008697"
    ]
},
  "bbox": [],
  "geometry": {"coordinates":[-104.2667,37.0167],"type":"Point"}
}