{
  "id": 7373623,
  "type": "Feature",
  "properties": {
    "tgn:hierarchy":[
        "tgn:7373623",
        "tgn:1001853",
        "tgn:1000001",
        "tgn:7005560",
        "tgn:7029392"
    ],
    "tgn:id":7373623,
    "tgn:name":"La Arena",
    "tgn:placetype":[
        "aat:300008347"
    ]
},
  "bbox": [],
  "geometry": {"coordinates":[-101.416667,28.783333],"type":"Point"}
}