{
  "id": 7182338,
  "type": "Feature",
  "properties": {
    "tgn:hierarchy":[
        "tgn:7182338",
        "tgn:1000003",
        "tgn:7003678",
        "tgn:7000084",
        "tgn:7029392"
    ],
    "tgn:id":7182338,
    "tgn:name":"Gammelsbach",
    "tgn:placetype":[
        "aat:300008347"
    ]
},
  "bbox": [],
  "geometry": {"coordinates":[8.965,49.526944],"type":"Point"}
}