{
  "id": 7318179,
  "type": "Feature",
  "properties": {
    "tgn:hierarchy":[
        "tgn:7318179",
        "tgn:7002464",
        "tgn:1000049",
        "tgn:1000002",
        "tgn:7029392"
    ],
    "tgn:id":7318179,
    "tgn:name":"Churicagua, Cerro",
    "tgn:placetype":[
        "aat:300008795"
    ]
},
  "bbox": [],
  "geometry": {"coordinates":[-69.506111,-17.869167],"type":"Point"}
}