{
  "id": 7140800,
  "type": "Feature",
  "properties": {
    "tgn:hierarchy":[
        "tgn:7140800",
        "tgn:1000003",
        "tgn:7003676",
        "tgn:7000084",
        "tgn:7029392"
    ],
    "tgn:id":7140800,
    "tgn:name":"Mammoor",
    "tgn:placetype":[
        "aat:300386886"
    ]
},
  "bbox": [],
  "geometry": {"coordinates":[7.65,52.966667],"type":"Point"}
}