{
  "id": 2179979,
  "type": "Feature",
  "properties": {
    "tgn:hierarchy":[
        "tgn:2179979",
        "tgn:1000001",
        "tgn:7012149",
        "tgn:2000225",
        "tgn:7007158",
        "tgn:7029392"
    ],
    "tgn:id":2179979,
    "tgn:name":"Blind Canyon",
    "tgn:placetype":[
        "aat:300008761"
    ]
},
  "bbox": [],
  "geometry": {"coordinates":[-107.5333,37.3667],"type":"Point"}
}