{
  "id": 7396799,
  "type": "Feature",
  "properties": {
    "tgn:hierarchy":[
        "tgn:7396799",
        "tgn:7005586",
        "tgn:1000001",
        "tgn:7005560",
        "tgn:7029392"
    ],
    "tgn:id":7396799,
    "tgn:name":"Santa Rita de los Altos",
    "tgn:placetype":[
        "aat:300000241"
    ]
},
  "bbox": [],
  "geometry": {"coordinates":[-102.616667,20.583333],"type":"Point"}
}