{
  "id": 2076719,
  "type": "Feature",
  "properties": {
    "tgn:hierarchy":[
        "tgn:2076719",
        "tgn:1000001",
        "tgn:2001473",
        "tgn:7012149",
        "tgn:7007709",
        "tgn:7029392"
    ],
    "tgn:id":2076719,
    "tgn:name":"South Hominy",
    "tgn:placetype":[
        "aat:300008347",
        "aat:300387210"
    ]
},
  "bbox": [],
  "geometry": {"coordinates":[-82.7333,35.4833],"type":"Point"}
}