{
  "id": 2594910,
  "type": "Feature",
  "properties": {
    "tgn:hierarchy":[
        "tgn:2594910",
        "tgn:1000001",
        "tgn:7012149",
        "tgn:2001852",
        "tgn:7007825",
        "tgn:7029392"
    ],
    "tgn:id":2594910,
    "tgn:name":"Possumpaw Branch",
    "tgn:placetype":[
        "aat:300008699"
    ]
},
  "bbox": [],
  "geometry": {"coordinates":[-86.2333,35.6833],"type":"Point"}
}