{
  "id": 7169485,
  "type": "Feature",
  "properties": {
    "tgn:hierarchy":[
        "tgn:7169485",
        "tgn:7003669",
        "tgn:1000003",
        "tgn:7000084",
        "tgn:7029392"
    ],
    "tgn:id":7169485,
    "tgn:name":"Hinterherberg",
    "tgn:placetype":[
        "aat:300008347"
    ]
},
  "bbox": [],
  "geometry": {"coordinates":[13.133333,48.833333],"type":"Point"}
}