{
  "id": 2381344,
  "type": "Feature",
  "properties": {
    "tgn:hierarchy":[
        "tgn:2381344",
        "tgn:1000001",
        "tgn:2001353",
        "tgn:7012149",
        "tgn:7007525",
        "tgn:7029392"
    ],
    "tgn:id":2381344,
    "tgn:name":"Hawthorne Lake",
    "tgn:placetype":[
        "aat:300008680"
    ]
},
  "bbox": [],
  "geometry": {"coordinates":[-101.9333,41.85],"type":"Point"}
}