<<<<<<< HEAD
{
  "id": 2764011,
  "type": "Feature",
  "properties": {
    "tgn:hierarchy":[
        "tgn:2764011",
        "tgn:1000001",
        "tgn:7012149",
        "tgn:2000490",
        "tgn:7007250",
        "tgn:7029392"
    ],
    "tgn:id":2764011,
    "tgn:name":"Wheeler Canyon",
    "tgn:placetype":[
        "aat:300008761"
    ]
},
  "bbox": [],
  "geometry": {"coordinates":[-112.6833,42.4833],"type":"Point"}
}
=======
{"geometry":{"type":"Point","coordinates":[-112.683300,42.483300]},"type":"Feature","properties":{"hierarchy":["tgn:2764011","tgn:1000001","tgn:7012149","tgn:2000490","tgn:7007250","tgn:7029392"],"placetype":["aat:300008761"],"id":2764011,"name:xx":"Wheeler Canyon"}}
>>>>>>> 03f74aca74312dbeaf24d7e61306dd6a786dc3d0
