{
  "id": 2764011,
  "type": "Feature",
  "properties": {
    "tgn:hierarchy":[
        "tgn:2764011",
        "tgn:1000001",
        "tgn:7012149",
        "tgn:2000490",
        "tgn:7007250",
        "tgn:7029392"
    ],
    "tgn:id":2764011,
    "tgn:name":"Wheeler Canyon",
    "tgn:placetype":[
        "aat:300008761"
    ]
},
  "bbox": [],
  "geometry": {"coordinates":[-112.6833,42.4833],"type":"Point"}
}