{
  "id": 1090954,
  "type": "Feature",
  "properties": {
    "tgn:hierarchy":[
        "tgn:1090954",
        "tgn:7001242",
        "tgn:1001575",
        "tgn:1000173",
        "tgn:7029392"
    ],
    "tgn:id":1090954,
    "tgn:name":"Mandronarivo",
    "tgn:placetype":[
        "aat:300008347"
    ]
},
  "bbox": [],
  "geometry": {"coordinates":[45.6333,-21.1167],"type":"Point"}
}