{
  "id": 7312954,
  "type": "Feature",
  "properties": {
    "tgn:hierarchy":[
        "tgn:7312954",
        "tgn:7016598",
        "tgn:1000049",
        "tgn:1000002",
        "tgn:7029392"
    ],
    "tgn:id":7312954,
    "tgn:name":"La Polvorera",
    "tgn:placetype":[
        "aat:300387033"
    ]
},
  "bbox": [],
  "geometry": {"coordinates":[-69.633333,-22.333333],"type":"Point"}
}