{
  "id": 7530846,
  "type": "Feature",
  "properties": {
    "tgn:hierarchy":[
        "tgn:7530846",
        "tgn:7001242",
        "tgn:7016833",
        "tgn:1001087",
        "tgn:7029392"
    ],
    "tgn:id":7530846,
    "tgn:name":"Tur'at al '\u0100mir\u012byah",
    "tgn:placetype":[
        "aat:300006075"
    ]
},
  "bbox": [],
  "geometry": {"coordinates":[31.061451,30.282197],"type":"Point"}
}