{
  "id": 2484321,
  "type": "Feature",
  "properties": {
    "tgn:hierarchy":[
        "tgn:2484321",
        "tgn:1000001",
        "tgn:7012149",
        "tgn:1003038",
        "tgn:7007517",
        "tgn:7029392"
    ],
    "tgn:id":2484321,
    "tgn:name":"Laurel Brook",
    "tgn:placetype":[
        "aat:300008699"
    ]
},
  "bbox": [],
  "geometry": {"coordinates":[-71.6833,42.0333],"type":"Point"}
}