{
  "id": 7255521,
  "type": "Feature",
  "properties": {
    "tgn:hierarchy":[
        "tgn:7255521",
        "tgn:7003466",
        "tgn:1000003",
        "tgn:1000063",
        "tgn:4012014",
        "tgn:7029392"
    ],
    "tgn:id":7255521,
    "tgn:name":"Ronqui\u00e8re, Bois de",
    "tgn:placetype":[
        "aat:300008863"
    ]
},
  "bbox": [],
  "geometry": {"coordinates":[4.798801,50.312653],"type":"Point"}
}