{
  "id": 2137919,
  "type": "Feature",
  "properties": {
    "tgn:hierarchy":[
        "tgn:2137919",
        "tgn:1002141",
        "tgn:1000001",
        "tgn:7012149",
        "tgn:7007568",
        "tgn:7029392"
    ],
    "tgn:id":2137919,
    "tgn:name":"Arrowhead Bay",
    "tgn:placetype":[
        "aat:300132316"
    ]
},
  "bbox": [],
  "geometry": {"coordinates":[-78.1833,42.3667],"type":"Point"}
}