{
  "id": 2784149,
  "type": "Feature",
  "properties": {
    "tgn:hierarchy":[
        "tgn:2784149",
        "tgn:1000001",
        "tgn:7006451",
        "tgn:7012149",
        "tgn:2000103",
        "tgn:7029392"
    ],
    "tgn:id":2784149,
    "tgn:name":"Yampai Tank",
    "tgn:placetype":[
        "aat:300006191"
    ]
},
  "bbox": [],
  "geometry": {"coordinates":[-113.25,35.3833],"type":"Point"}
}