<<<<<<< HEAD
{
  "id": 2258098,
  "type": "Feature",
  "properties": {
    "tgn:hierarchy":[
        "tgn:2258098",
        "tgn:7006450",
        "tgn:1000001",
        "tgn:7012149",
        "tgn:2124014",
        "tgn:7029392"
    ],
    "tgn:id":2258098,
    "tgn:name":"Cosmos Mountain",
    "tgn:placetype":[
        "aat:300008798"
    ]
},
  "bbox": [],
  "geometry": {"coordinates":[-157.05,67.0],"type":"Point"}
}
=======
{"geometry":{"type":"Point","coordinates":[-157.050000,67.000000]},"type":"Feature","properties":{"hierarchy":["tgn:2258098","tgn:7006450","tgn:1000001","tgn:7012149","tgn:2124014","tgn:7029392"],"placetype":["aat:300008798"],"id":2258098,"name:xx":"Cosmos Mountain"}}
>>>>>>> 03f74aca74312dbeaf24d7e61306dd6a786dc3d0
