{
  "id": 7490412,
  "type": "Feature",
  "properties": {
    "tgn:hierarchy":[
        "tgn:7490412",
        "tgn:1000004",
        "tgn:7492971",
        "tgn:1000141",
        "tgn:7029392"
    ],
    "tgn:id":7490412,
    "tgn:name":"Shiniuzi",
    "tgn:placetype":[
        "aat:300008791"
    ]
},
  "bbox": [],
  "geometry": {"coordinates":[120.780833,21.943056],"type":"Point"}
}