{
  "id": 2612141,
  "type": "Feature",
  "properties": {
    "tgn:hierarchy":[
        "tgn:2612141",
        "tgn:1000001",
        "tgn:7012149",
        "tgn:2002005",
        "tgn:7007826",
        "tgn:7029392"
    ],
    "tgn:id":2612141,
    "tgn:name":"Red Rock Tank",
    "tgn:placetype":[
        "aat:300006191"
    ]
},
  "bbox": [],
  "geometry": {"coordinates":[-105.4167,30.9833],"type":"Point"}
}