{
  "id": 2119917,
  "type": "Feature",
  "properties": {
    "tgn:hierarchy":[
        "tgn:2119917",
        "tgn:1000001",
        "tgn:7012149",
        "tgn:2002289",
        "tgn:7013961",
        "tgn:7029392"
    ],
    "tgn:id":2119917,
    "tgn:name":"Scary",
    "tgn:placetype":[
        "aat:300008347",
        "aat:300387210"
    ]
},
  "bbox": [],
  "geometry": {"coordinates":[-81.85,38.4333],"type":"Point"}
}