{
  "id": 2762668,
  "type": "Feature",
  "properties": {
    "tgn:hierarchy":[
        "tgn:2762668",
        "tgn:1000001",
        "tgn:7012149",
        "tgn:7029392"
    ],
    "tgn:id":2762668,
    "tgn:name":"Wester Creek",
    "tgn:placetype":[
        "aat:300008706"
    ]
},
  "bbox": [],
  "geometry": {"coordinates":[-90.0667,46.3167],"type":"Point"}
}