<<<<<<< HEAD
{
  "id": 2762668,
  "type": "Feature",
  "properties": {
    "tgn:hierarchy":[
        "tgn:2762668",
        "tgn:1000001",
        "tgn:7012149",
        "tgn:7029392"
    ],
    "tgn:id":2762668,
    "tgn:name":"Wester Creek",
    "tgn:placetype":[
        "aat:300008706"
    ]
},
  "bbox": [],
  "geometry": {"coordinates":[-90.0667,46.3167],"type":"Point"}
}
=======
{"geometry":{"type":"Point","coordinates":[-90.066700,46.316700]},"type":"Feature","properties":{"hierarchy":["tgn:2762668","tgn:1000001","tgn:7012149","tgn:7029392"],"placetype":["aat:300008706"],"id":2762668,"name:xx":"Wester Creek"}}
>>>>>>> 03f74aca74312dbeaf24d7e61306dd6a786dc3d0
