{
  "id": 1021029,
  "type": "Feature",
  "properties": {
    "tgn:hierarchy":[
        "tgn:1021029",
        "tgn:7012827",
        "tgn:7002454",
        "tgn:1000047",
        "tgn:1000002",
        "tgn:7029392"
    ],
    "tgn:id":1021029,
    "tgn:name":"Campos Belos",
    "tgn:placetype":[
        "aat:300008347"
    ]
},
  "bbox": [],
  "geometry": {"coordinates":[-46.8833,-13.05],"type":"Point"}
}