{
  "id": 2240348,
  "type": "Feature",
  "properties": {
    "tgn:hierarchy":[
        "tgn:2240348",
        "tgn:1000001",
        "tgn:2000696",
        "tgn:7012149",
        "tgn:7007254",
        "tgn:7029392"
    ],
    "tgn:id":2240348,
    "tgn:name":"Cities Service Lake",
    "tgn:placetype":[
        "aat:300006191"
    ]
},
  "bbox": [],
  "geometry": {"coordinates":[-96.3833,38.05],"type":"Point"}
}