{
  "id": 2474143,
  "type": "Feature",
  "properties": {
    "tgn:hierarchy":[
        "tgn:2474143",
        "tgn:2001464",
        "tgn:1000001",
        "tgn:7012149",
        "tgn:7007709",
        "tgn:7029392"
    ],
    "tgn:id":2474143,
    "tgn:name":"Lower Little River",
    "tgn:placetype":[
        "aat:300008707"
    ]
},
  "bbox": [],
  "geometry": {"coordinates":[-81.2667,36.0167],"type":"Point"}
}