{
  "id": 2148844,
  "type": "Feature",
  "properties": {
    "tgn:hierarchy":[
        "tgn:2148844",
        "tgn:1000001",
        "tgn:7012149",
        "tgn:2002060",
        "tgn:7007826",
        "tgn:7029392"
    ],
    "tgn:id":2148844,
    "tgn:name":"Barnett Spring Draw",
    "tgn:placetype":[
        "aat:300008761"
    ]
},
  "bbox": [],
  "geometry": {"coordinates":[-99.8833,29.9667],"type":"Point"}
}