{
  "id": 7590414,
  "type": "Feature",
  "properties": {
    "tgn:hierarchy":[
        "tgn:7590414",
        "tgn:1000004",
        "tgn:7000198",
        "tgn:7000799",
        "tgn:7029392"
    ],
    "tgn:id":7590414,
    "tgn:name:en":"Jabbi Forest",
    "tgn:placetype":[
        "aat:300008863"
    ]
},
  "bbox": [],
  "geometry": {"coordinates":[74.291667,33.755556],"type":"Point"}
}