{
  "id": 7494369,
  "type": "Feature",
  "properties": {
    "tgn:hierarchy":[
        "tgn:7494369",
        "tgn:7468018",
        "tgn:1000004",
        "tgn:1000141",
        "tgn:7029392"
    ],
    "tgn:id":7494369,
    "tgn:name":"Wayao",
    "tgn:placetype":[
        "aat:300008347"
    ]
},
  "bbox": [],
  "geometry": {"coordinates":[120.544589,23.4959],"type":"Point"}
}