{
  "id": 2627024,
  "type": "Feature",
  "properties": {
    "tgn:hierarchy":[
        "tgn:2627024",
        "tgn:1000001",
        "tgn:7012149",
        "tgn:1002771",
        "tgn:7007826",
        "tgn:7029392"
    ],
    "tgn:id":2627024,
    "tgn:name":"Rocky Run",
    "tgn:placetype":[
        "aat:300008699"
    ]
},
  "bbox": [],
  "geometry": {"coordinates":[-97.95,32.5833],"type":"Point"}
}