{
  "id": 7316059,
  "type": "Feature",
  "properties": {
    "tgn:hierarchy":[
        "tgn:7316059",
        "tgn:1001702",
        "tgn:1000049",
        "tgn:1000002",
        "tgn:7029392"
    ],
    "tgn:id":7316059,
    "tgn:name":"Casas Viejas, R\u00edo de las",
    "tgn:placetype":[
        "aat:300008699"
    ]
},
  "bbox": [],
  "geometry": {"coordinates":[-72.15,-51.85],"type":"Point"}
}