{
  "id": 7463351,
  "type": "Feature",
  "properties": {
    "tgn:hierarchy":[
        "tgn:7463351",
        "tgn:7002444",
        "tgn:1000003",
        "tgn:7008072",
        "tgn:7008591",
        "tgn:7029392"
    ],
    "tgn:id":7463351,
    "tgn:name:en":"Hunthill",
    "tgn:placetype":[
        "aat:300387502"
    ]
},
  "bbox": [],
  "geometry": {"coordinates":[-2.533333,55.466667],"type":"Point"}
}