{
  "id": 7191197,
  "type": "Feature",
  "properties": {
    "tgn:hierarchy":[
        "tgn:7191197",
        "tgn:7000096",
        "tgn:1000003",
        "tgn:7000084",
        "tgn:7029392"
    ],
    "tgn:id":7191197,
    "tgn:name":"Fauler See",
    "tgn:placetype":[
        "aat:300008680"
    ]
},
  "bbox": [],
  "geometry": {"coordinates":[13.933333,52.65],"type":"Point"}
}