{
  "id": 2426985,
  "type": "Feature",
  "properties": {
    "tgn:hierarchy":[
        "tgn:2426985",
        "tgn:1000001",
        "tgn:7012149",
        "tgn:2002341",
        "tgn:7007922",
        "tgn:7029392"
    ],
    "tgn:id":2426985,
    "tgn:name":"Jones Spring",
    "tgn:placetype":[
        "aat:300008697"
    ]
},
  "bbox": [],
  "geometry": {"coordinates":[-88.6667,45.2667],"type":"Point"}
}