{
  "id": 7201133,
  "type": "Feature",
  "properties": {
    "tgn:hierarchy":[
        "tgn:7201133",
        "tgn:7003669",
        "tgn:1000003",
        "tgn:7000084",
        "tgn:7029392"
    ],
    "tgn:id":7201133,
    "tgn:name":"Eckartsbrunnen-Bach",
    "tgn:placetype":[
        "aat:300008699"
    ]
},
  "bbox": [],
  "geometry": {"coordinates":[10.066667,50.166667],"type":"Point"}
}