{
  "id": 2083640,
  "type": "Feature",
  "properties": {
    "tgn:hierarchy":[
        "tgn:2083640",
        "tgn:1000001",
        "tgn:7012149",
        "tgn:2001686",
        "tgn:7007707",
        "tgn:7029392"
    ],
    "tgn:id":2083640,
    "tgn:name":"Moyers",
    "tgn:placetype":[
        "aat:300008347"
    ]
},
  "bbox": [],
  "geometry": {"coordinates":[-95.65,34.3167],"type":"Point"}
}