{
  "id": 2684804,
  "type": "Feature",
  "properties": {
    "tgn:hierarchy":[
        "tgn:2684804",
        "tgn:1000001",
        "tgn:7012149",
        "tgn:2001892",
        "tgn:7007825",
        "tgn:7029392"
    ],
    "tgn:id":2684804,
    "tgn:name":"Spivey",
    "tgn:placetype":[
        "aat:300008347"
    ]
},
  "bbox": [],
  "geometry": {"coordinates":[-85.8167,36.5833],"type":"Point"}
}