{
  "id": 2223101,
  "type": "Feature",
  "properties": {
    "tgn:hierarchy":[
        "tgn:2223101",
        "tgn:1000001",
        "tgn:1002188",
        "tgn:7012149",
        "tgn:7007252",
        "tgn:7029392"
    ],
    "tgn:id":2223101,
    "tgn:name":"Carroll Ditch",
    "tgn:placetype":[
        "aat:300006075"
    ]
},
  "bbox": [],
  "geometry": {"coordinates":[-86.35,40.1333],"type":"Point"}
}