{
  "id": 7125949,
  "type": "Feature",
  "properties": {
    "tgn:hierarchy":[
        "tgn:7125949",
        "tgn:7003669",
        "tgn:1000003",
        "tgn:7000084",
        "tgn:7029392"
    ],
    "tgn:id":7125949,
    "tgn:name":"Forsthaus Oberdill",
    "tgn:placetype":[
        "aat:300004792"
    ]
},
  "bbox": [],
  "geometry": {"coordinates":[11.516667,48.016667],"type":"Point"}
}