{
  "id": 7088872,
  "type": "Feature",
  "properties": {
    "tgn:hierarchy":[
        "tgn:7088872",
        "tgn:7003669",
        "tgn:1000003",
        "tgn:7000084",
        "tgn:7029392"
    ],
    "tgn:id":7088872,
    "tgn:name":"Weihergehau",
    "tgn:placetype":[
        "aat:300008863"
    ]
},
  "bbox": [],
  "geometry": {"coordinates":[10.35,48.316667],"type":"Point"}
}