{
  "id": 7387194,
  "type": "Feature",
  "properties": {
    "tgn:hierarchy":[
        "tgn:7387194",
        "tgn:1000001",
        "tgn:7005599",
        "tgn:7005560",
        "tgn:7029392"
    ],
    "tgn:id":7387194,
    "tgn:name":"Perseverancia",
    "tgn:placetype":[
        "aat:300008347"
    ]
},
  "bbox": [],
  "geometry": {"coordinates":[-97.983333,22.216667],"type":"Point"}
}