{
  "id": 2302261,
  "type": "Feature",
  "properties": {
    "tgn:hierarchy":[
        "tgn:2302261",
        "tgn:1000001",
        "tgn:2002368",
        "tgn:7012149",
        "tgn:7007923",
        "tgn:7029392"
    ],
    "tgn:id":2302261,
    "tgn:name":"Dutch Joe Creek",
    "tgn:placetype":[
        "aat:300008706"
    ]
},
  "bbox": [],
  "geometry": {"coordinates":[-107.45,41.1167],"type":"Point"}
}