{
  "id": 2306908,
  "type": "Feature",
  "properties": {
    "tgn:hierarchy":[
        "tgn:2306908",
        "tgn:1002648",
        "tgn:1000001",
        "tgn:1008191",
        "tgn:7012149",
        "tgn:7007249",
        "tgn:7029392"
    ],
    "tgn:id":2306908,
    "tgn:name":"East Fork Kawela Gulch",
    "tgn:placetype":[
        "aat:300008761"
    ]
},
  "bbox": [],
  "geometry": {"coordinates":[-156.8833,21.1167],"type":"Point"}
}