<<<<<<< HEAD
{
  "id": 7367109,
  "type": "Feature",
  "properties": {
    "tgn:hierarchy":[
        "tgn:7367109",
        "tgn:1001853",
        "tgn:1000001",
        "tgn:7005560",
        "tgn:7029392"
    ],
    "tgn:id":7367109,
    "tgn:name":"Rancho El Tres",
    "tgn:placetype":[
        "aat:300000241"
    ]
},
  "bbox": [],
  "geometry": {"coordinates":[-101.066667,26.95],"type":"Point"}
}
=======
{"geometry":{"type":"Point","coordinates":[-101.066667,26.950000]},"type":"Feature","properties":{"hierarchy":["tgn:7367109","tgn:1001853","tgn:1000001","tgn:7005560","tgn:7029392"],"placetype":["aat:300000241"],"id":7367109,"name:xx":"Rancho El Tres"}}
>>>>>>> 03f74aca74312dbeaf24d7e61306dd6a786dc3d0
