{
  "id": 7356175,
  "type": "Feature",
  "properties": {
    "tgn:hierarchy":[
        "tgn:7356175",
        "tgn:1000001",
        "tgn:1001937",
        "tgn:7005560",
        "tgn:7029392"
    ],
    "tgn:id":7356175,
    "tgn:name":"Carmelita",
    "tgn:placetype":[
        "aat:300008347"
    ]
},
  "bbox": [],
  "geometry": {"coordinates":[-88.583333,18.333333],"type":"Point"}
}