{
  "id": 2741243,
  "type": "Feature",
  "properties": {
    "tgn:hierarchy":[
        "tgn:2741243",
        "tgn:1000001",
        "tgn:2000922",
        "tgn:7012149",
        "tgn:7007515",
        "tgn:7029392"
    ],
    "tgn:id":2741243,
    "tgn:name":"Upper Unknown Lake",
    "tgn:placetype":[
        "aat:300008680"
    ]
},
  "bbox": [],
  "geometry": {"coordinates":[-68.0667,45.1667],"type":"Point"}
}