{
  "id": 7252446,
  "type": "Feature",
  "properties": {
    "tgn:hierarchy":[
        "tgn:7252446",
        "tgn:7003456",
        "tgn:1000003",
        "tgn:1000063",
        "tgn:7018236",
        "tgn:7029392"
    ],
    "tgn:id":7252446,
    "tgn:name":"Molenheide",
    "tgn:placetype":[
        "aat:300008347"
    ]
},
  "bbox": [],
  "geometry": {"coordinates":[5.05,51.466667],"type":"Point"}
}