{
  "id": 7399896,
  "type": "Feature",
  "properties": {
    "tgn:hierarchy":[
        "tgn:7399896",
        "tgn:1000001",
        "tgn:7005593",
        "tgn:7005560",
        "tgn:7029392"
    ],
    "tgn:id":7399896,
    "tgn:name":"Pe\u00f1a Blanca",
    "tgn:placetype":[
        "aat:300008347"
    ]
},
  "bbox": [],
  "geometry": {"coordinates":[-99.748611,21.026389],"type":"Point"}
}