{
  "id": 1138523,
  "type": "Feature",
  "properties": {
    "tgn:hierarchy":[
        "tgn:1138523",
        "tgn:1000004",
        "tgn:7014474",
        "tgn:7018214",
        "tgn:7002435",
        "tgn:7029392"
    ],
    "tgn:id":1138523,
    "tgn:name":"Troitskoye",
    "tgn:placetype":[
        "aat:300008347"
    ]
},
  "bbox": [],
  "geometry": {"coordinates":[136.5333,49.4167],"type":"Point"}
}