{
  "id": 2366697,
  "type": "Feature",
  "properties": {
    "tgn:hierarchy":[
        "tgn:2366697",
        "tgn:1000001",
        "tgn:7012149",
        "tgn:7007919",
        "tgn:7029392"
    ],
    "tgn:id":2366697,
    "tgn:name":"Grindstone Hollow",
    "tgn:placetype":[
        "aat:300008761"
    ]
},
  "bbox": [],
  "geometry": {"coordinates":[-82.2833,36.6167],"type":"Point"}
}