<<<<<<< HEAD
{
  "id": 2336337,
  "type": "Feature",
  "properties": {
    "tgn:hierarchy":[
        "tgn:2336337",
        "tgn:1000001",
        "tgn:7012149",
        "tgn:1002810",
        "tgn:7007568",
        "tgn:7029392"
    ],
    "tgn:id":2336337,
    "tgn:name":"Foundry Cove",
    "tgn:placetype":[
        "aat:300132316"
    ]
},
  "bbox": [],
  "geometry": {"coordinates":[-73.95,41.4],"type":"Point"}
}
=======
{"geometry":{"type":"Point","coordinates":[-73.950000,41.400000]},"type":"Feature","properties":{"hierarchy":["tgn:2336337","tgn:1000001","tgn:7012149","tgn:1002810","tgn:7007568","tgn:7029392"],"placetype":["aat:300132316"],"id":2336337,"name:xx":"Foundry Cove"}}
>>>>>>> 03f74aca74312dbeaf24d7e61306dd6a786dc3d0
