{
  "id": 7157017,
  "type": "Feature",
  "properties": {
    "tgn:hierarchy":[
        "tgn:7157017",
        "tgn:7003692",
        "tgn:1000003",
        "tgn:7000084",
        "tgn:7029392"
    ],
    "tgn:id":7157017,
    "tgn:name":"Klausbach",
    "tgn:placetype":[
        "aat:300000206"
    ]
},
  "bbox": [],
  "geometry": {"coordinates":[8.166667,48.55],"type":"Point"}
}