<<<<<<< HEAD
{
  "id": 2330088,
  "type": "Feature",
  "properties": {
    "tgn:hierarchy":[
        "tgn:2330088",
        "tgn:1000001",
        "tgn:7012149",
        "tgn:1002350",
        "tgn:7007157",
        "tgn:7029392"
    ],
    "tgn:id":2330088,
    "tgn:name":"Flagpole Peak",
    "tgn:placetype":[
        "aat:300008798"
    ]
},
  "bbox": [],
  "geometry": {"coordinates":[-120.05,38.8333],"type":"Point"}
}
=======
{"geometry":{"type":"Point","coordinates":[-120.050000,38.833300]},"type":"Feature","properties":{"hierarchy":["tgn:2330088","tgn:1000001","tgn:7012149","tgn:1002350","tgn:7007157","tgn:7029392"],"placetype":["aat:300008798"],"id":2330088,"name:xx":"Flagpole Peak"}}
>>>>>>> 03f74aca74312dbeaf24d7e61306dd6a786dc3d0
