{
  "id": 1077422,
  "type": "Feature",
  "properties": {
    "tgn:hierarchy":[
        "tgn:1077422",
        "tgn:1000004",
        "tgn:1001323",
        "tgn:1000116",
        "tgn:7029392"
    ],
    "tgn:id":1077422,
    "tgn:name":"Bangil",
    "tgn:placetype":[
        "aat:300008347"
    ]
},
  "bbox": [],
  "geometry": {"coordinates":[112.7833,-7.5667],"type":"Point"}
}