{
  "id": 2593869,
  "type": "Feature",
  "properties": {
    "tgn:hierarchy":[
        "tgn:2593869",
        "tgn:1000001",
        "tgn:2000870",
        "tgn:7012149",
        "tgn:7007256",
        "tgn:7029392"
    ],
    "tgn:id":2593869,
    "tgn:name":"Port Hickey Landing",
    "tgn:placetype":[
        "aat:300008347"
    ]
},
  "bbox": [],
  "geometry": {"coordinates":[-91.2833,30.65],"type":"Point"}
}