{
  "id": 7057344,
  "type": "Feature",
  "properties": {
    "tgn:hierarchy":[
        "tgn:7057344",
        "tgn:7003170",
        "tgn:1000003",
        "tgn:7003125",
        "tgn:1000080",
        "tgn:7029392"
    ],
    "tgn:id":7057344,
    "tgn:name":"Baccano",
    "tgn:placetype":[
        "aat:300008347"
    ]
},
  "bbox": [],
  "geometry": {"coordinates":[12.233333,42.916667],"type":"Point"}
}