{
  "id": 7005414,
  "type": "Feature",
  "properties": {
    "tgn:hierarchy":[
        "tgn:7005414",
        "tgn:1000001",
        "tgn:7005388",
        "tgn:7029392"
    ],
    "tgn:id":7005414,
    "tgn:name":"Puerto Plata",
    "tgn:placetype":[
        "aat:300387064",
        "aat:300000774"
    ]
},
  "bbox": [],
  "geometry": {"coordinates":[-70.75,19.75],"type":"Point"}
}