<<<<<<< HEAD
{
  "id": 7476358,
  "type": "Feature",
  "properties": {
    "tgn:hierarchy":[
        "tgn:7476358",
        "tgn:7488858",
        "tgn:1000004",
        "tgn:1000141",
        "tgn:7029392"
    ],
    "tgn:id":7476358,
    "tgn:name":"Shuiguo Qiao",
    "tgn:placetype":[
        "aat:300007836"
    ]
},
  "bbox": [],
  "geometry": {"coordinates":[120.7063,23.9192],"type":"Point"}
}
=======
{"geometry":{"type":"Point","coordinates":[120.706300,23.919200]},"type":"Feature","properties":{"hierarchy":["tgn:7476358","tgn:7488858","tgn:1000004","tgn:1000141","tgn:7029392"],"placetype":["aat:300007836"],"id":7476358,"name:xx":"Shuiguo Qiao"}}
>>>>>>> 03f74aca74312dbeaf24d7e61306dd6a786dc3d0
