{
  "id": 2279762,
  "type": "Feature",
  "properties": {
    "tgn:hierarchy":[
        "tgn:2279762",
        "tgn:1000001",
        "tgn:7012149",
        "tgn:7007157",
        "tgn:1002894",
        "tgn:7029392"
    ],
    "tgn:id":2279762,
    "tgn:name":"Deadwood Diggings",
    "tgn:placetype":[
        "aat:300000390"
    ]
},
  "bbox": [],
  "geometry": {"coordinates":[-120.85,39.6667],"type":"Point"}
}