{
  "id": 1056225,
  "type": "Feature",
  "properties": {
    "tgn:hierarchy":[
        "tgn:1056225",
        "tgn:1000004",
        "tgn:1003363",
        "tgn:7014786",
        "tgn:7029392"
    ],
    "tgn:id":1056225,
    "tgn:name":"Kyzylespe",
    "tgn:placetype":[
        "aat:300008347"
    ]
},
  "bbox": [],
  "geometry": {"coordinates":[73.8833,47.45],"type":"Point"}
}