{
  "id": 2003048,
  "type": "Feature",
  "properties": {
    "tgn:hierarchy":[
        "tgn:2003048",
        "tgn:7002659",
        "tgn:1000001",
        "tgn:7012149",
        "tgn:2000023",
        "tgn:7029392"
    ],
    "tgn:id":2003048,
    "tgn:name":"Central Mills",
    "tgn:placetype":[
        "aat:300008347",
        "aat:300387210"
    ]
},
  "bbox": [],
  "geometry": {"coordinates":[-87.4333,32.2833],"type":"Point"}
}