{
  "id": 7413804,
  "type": "Feature",
  "properties": {
    "tgn:hierarchy":[
        "tgn:7413804",
        "tgn:7005587",
        "tgn:1000001",
        "tgn:7005560",
        "tgn:7029392"
    ],
    "tgn:id":7413804,
    "tgn:name:es":"Pantepec, R\u00edo",
    "tgn:placetype":[
        "aat:300008699"
    ]
},
  "bbox": [],
  "geometry": {"coordinates":[-98.179167,20.409722],"type":"Point"}
}