{
  "id": 7284959,
  "type": "Feature",
  "properties": {
    "tgn:hierarchy":[
        "tgn:7284959",
        "tgn:1001623",
        "tgn:1000049",
        "tgn:1000002",
        "tgn:7029392"
    ],
    "tgn:id":7284959,
    "tgn:name":"Piedras, Estero",
    "tgn:placetype":[
        "aat:300008699"
    ]
},
  "bbox": [],
  "geometry": {"coordinates":[-72.433333,-44.566667],"type":"Point"}
}