{
  "id": 7589342,
  "type": "Feature",
  "properties": {
    "tgn:hierarchy":[
        "tgn:7589342",
        "tgn:1000004",
        "tgn:7000198",
        "tgn:7000799",
        "tgn:7029392"
    ],
    "tgn:id":7589342,
    "tgn:name:en":"Khola",
    "tgn:placetype":[
        "aat:300008347"
    ]
},
  "bbox": [],
  "geometry": {"coordinates":[74.14125,33.315109],"type":"Point"}
}