{
  "id": 7585131,
  "type": "Feature",
  "properties": {
    "tgn:hierarchy":[
        "tgn:7585131",
        "tgn:1000004",
        "tgn:7000200",
        "tgn:7000198",
        "tgn:7029392"
    ],
    "tgn:id":7585131,
    "tgn:name:en":"R\u0101j Bhavan Punjab",
    "tgn:placetype":[
        "aat:300008347"
    ]
},
  "bbox": [],
  "geometry": {"coordinates":[76.810758,30.739242],"type":"Point"}
}