{
  "id": 2684332,
  "type": "Feature",
  "properties": {
    "tgn:hierarchy":[
        "tgn:2684332",
        "tgn:1000001",
        "tgn:7012149",
        "tgn:2001524",
        "tgn:7007709",
        "tgn:7029392"
    ],
    "tgn:id":2684332,
    "tgn:name":"Spicer Bay",
    "tgn:placetype":[
        "aat:300132316"
    ]
},
  "bbox": [],
  "geometry": {"coordinates":[-77.4833,34.4667],"type":"Point"}
}