<<<<<<< HEAD
{
  "id": 2155934,
  "type": "Feature",
  "properties": {
    "tgn:hierarchy":[
        "tgn:2155934",
        "tgn:1000001",
        "tgn:7012149",
        "tgn:2002121",
        "tgn:7007827",
        "tgn:7029392"
    ],
    "tgn:id":2155934,
    "tgn:name":"Bear Valley Reservoir",
    "tgn:placetype":[
        "aat:300006191"
    ]
},
  "bbox": [],
  "geometry": {"coordinates":[-111.8833,38.65],"type":"Point"}
}
=======
{"geometry":{"type":"Point","coordinates":[-111.883300,38.650000]},"type":"Feature","properties":{"hierarchy":["tgn:2155934","tgn:1000001","tgn:7012149","tgn:2002121","tgn:7007827","tgn:7029392"],"placetype":["aat:300006191"],"id":2155934,"name:xx":"Bear Valley Reservoir"}}
>>>>>>> 03f74aca74312dbeaf24d7e61306dd6a786dc3d0
