{
  "id": 7360872,
  "type": "Feature",
  "properties": {
    "tgn:hierarchy":[
        "tgn:7360872",
        "tgn:7005586",
        "tgn:1000001",
        "tgn:7005560",
        "tgn:7029392"
    ],
    "tgn:id":7360872,
    "tgn:name":"Cofrad\u00eda de Preciado",
    "tgn:placetype":[
        "aat:300008347"
    ]
},
  "bbox": [],
  "geometry": {"coordinates":[-103.583333,20.033333],"type":"Point"}
}