<<<<<<< HEAD
{
  "id": 7354851,
  "type": "Feature",
  "properties": {
    "tgn:hierarchy":[
        "tgn:7354851",
        "tgn:1000001",
        "tgn:7005591",
        "tgn:7005560",
        "tgn:7029392"
    ],
    "tgn:id":7354851,
    "tgn:name":"Catarino",
    "tgn:placetype":[
        "aat:300008347"
    ]
},
  "bbox": [],
  "geometry": {"coordinates":[-95.083333,16.366667],"type":"Point"}
}
=======
{"geometry":{"type":"Point","coordinates":[-95.083333,16.366667]},"type":"Feature","properties":{"hierarchy":["tgn:7354851","tgn:1000001","tgn:7005591","tgn:7005560","tgn:7029392"],"placetype":["aat:300008347"],"id":7354851,"name:xx":"Catarino"}}
>>>>>>> 03f74aca74312dbeaf24d7e61306dd6a786dc3d0
