<<<<<<< HEAD
{
  "id": 7362747,
  "type": "Feature",
  "properties": {
    "tgn:hierarchy":[
        "tgn:7362747",
        "tgn:1001835",
        "tgn:1000001",
        "tgn:7005560",
        "tgn:7029392"
    ],
    "tgn:id":7362747,
    "tgn:name":"El Carrizo, Arroyo",
    "tgn:placetype":[
        "aat:300266554",
        "aat:300008699"
    ]
},
  "bbox": [],
  "geometry": {"coordinates":[-115.9,31.116667],"type":"Point"}
}
=======
{"geometry":{"type":"Point","coordinates":[-115.900000,31.116667]},"type":"Feature","properties":{"hierarchy":["tgn:7362747","tgn:1001835","tgn:1000001","tgn:7005560","tgn:7029392"],"placetype":["aat:300266554","aat:300008699"],"id":7362747,"name:xx":"El Carrizo, Arroyo"}}
>>>>>>> 03f74aca74312dbeaf24d7e61306dd6a786dc3d0
