{
  "id": 2307683,
  "type": "Feature",
  "properties": {
    "tgn:hierarchy":[
        "tgn:2307683",
        "tgn:1000001",
        "tgn:7012149",
        "tgn:7007157",
        "tgn:2000191",
        "tgn:7029392"
    ],
    "tgn:id":2307683,
    "tgn:name":"East Fork Trinity River",
    "tgn:placetype":[
        "aat:300008707"
    ]
},
  "bbox": [],
  "geometry": {"coordinates":[-122.45,41.15],"type":"Point"}
}