{
  "id": 7537934,
  "type": "Feature",
  "properties": {
    "tgn:hierarchy":[
        "tgn:7537934",
        "tgn:7001242",
        "tgn:7016833",
        "tgn:1001087",
        "tgn:7029392"
    ],
    "tgn:id":7537934,
    "tgn:name:en":"M\u012bt Shih\u0101lah",
    "tgn:placetype":[
        "aat:300008347"
    ]
},
  "bbox": [],
  "geometry": {"coordinates":[30.890347,30.601626],"type":"Point"}
}