{
  "id": 7420344,
  "type": "Feature",
  "properties": {
    "tgn:hierarchy":[
        "tgn:7420344",
        "tgn:1001836",
        "tgn:1000001",
        "tgn:7005560",
        "tgn:7029392"
    ],
    "tgn:id":7420344,
    "tgn:name":"Cantarrana",
    "tgn:placetype":[
        "aat:300008347"
    ]
},
  "bbox": [],
  "geometry": {"coordinates":[-111.078056,24.861944],"type":"Point"}
}