{
  "id": 1032069,
  "type": "Feature",
  "properties": {
    "tgn:hierarchy":[
        "tgn:1032069",
        "tgn:1000003",
        "tgn:1000070",
        "tgn:7002897",
        "tgn:7029392"
    ],
    "tgn:id":1032069,
    "tgn:name":"Beaurepaire-d'Is\u00e8re",
    "tgn:placetype":[
        "aat:300008347"
    ]
},
  "bbox": [],
  "geometry": {"coordinates":[5.05,45.3333],"type":"Point"}
}