{
  "id": 1059834,
  "type": "Feature",
  "properties": {
    "tgn:hierarchy":[
        "tgn:1059834",
        "tgn:7012152",
        "tgn:1000003",
        "tgn:7006541",
        "tgn:7029392"
    ],
    "tgn:id":1059834,
    "tgn:name":"Stiene",
    "tgn:placetype":[
        "aat:300008347"
    ]
},
  "bbox": [],
  "geometry": {"coordinates":[24.5333,57.4333],"type":"Point"}
}