<<<<<<< HEAD
{
  "id": 2762005,
  "type": "Feature",
  "properties": {
    "tgn:hierarchy":[
        "tgn:2762005",
        "tgn:1002176",
        "tgn:1000001",
        "tgn:7012149",
        "tgn:7007828",
        "tgn:7029392"
    ],
    "tgn:id":2762005,
    "tgn:name":"West Sandgate",
    "tgn:placetype":[
        "aat:300008347"
    ]
},
  "bbox": [],
  "geometry": {"coordinates":[-73.2333,43.15],"type":"Point"}
}
=======
{"geometry":{"type":"Point","coordinates":[-73.233300,43.150000]},"type":"Feature","properties":{"hierarchy":["tgn:2762005","tgn:1002176","tgn:1000001","tgn:7012149","tgn:7007828","tgn:7029392"],"placetype":["aat:300008347"],"id":2762005,"name:xx":"West Sandgate"}}
>>>>>>> 03f74aca74312dbeaf24d7e61306dd6a786dc3d0
