{
  "id": 2619069,
  "type": "Feature",
  "properties": {
    "tgn:hierarchy":[
        "tgn:2619069",
        "tgn:1000001",
        "tgn:7012149",
        "tgn:2001456",
        "tgn:7007566",
        "tgn:7029392"
    ],
    "tgn:id":2619069,
    "tgn:name":"Riley",
    "tgn:placetype":[
        "aat:300008347"
    ]
},
  "bbox": [],
  "geometry": {"coordinates":[-107.2167,34.3667],"type":"Point"}
}