{
  "id": 7526489,
  "type": "Feature",
  "properties": {
    "tgn:hierarchy":[
        "tgn:7526489",
        "tgn:7001242",
        "tgn:1001059",
        "tgn:7016833",
        "tgn:7029392"
    ],
    "tgn:id":7526489,
    "tgn:name:en":"\u0162ayy\u0101r\u012bn, Naq'at a\u0163",
    "tgn:placetype":[
        "aat:300008903"
    ]
},
  "bbox": [],
  "geometry": {"coordinates":[31.333333,31.483333],"type":"Point"}
}