{
  "id": 2370037,
  "type": "Feature",
  "properties": {
    "tgn:hierarchy":[
        "tgn:2370037",
        "tgn:1000001",
        "tgn:7012149",
        "tgn:2000835",
        "tgn:7007255",
        "tgn:7029392"
    ],
    "tgn:id":2370037,
    "tgn:name":"Guy Camp Branch",
    "tgn:placetype":[
        "aat:300008699"
    ]
},
  "bbox": [],
  "geometry": {"coordinates":[-83.5833,37.3667],"type":"Point"}
}