{
  "id": 7551021,
  "type": "Feature",
  "properties": {
    "tgn:hierarchy":[
        "tgn:7551021",
        "tgn:1000004",
        "tgn:7000198",
        "tgn:1001977",
        "tgn:7029392"
    ],
    "tgn:id":7551021,
    "tgn:name:en":"D\u0101nkuni Drainage Channel",
    "tgn:placetype":[
        "aat:300008713"
    ]
},
  "bbox": [],
  "geometry": {"coordinates":[88.349601,22.655103],"type":"Point"}
}