{
  "id": 2261320,
  "type": "Feature",
  "properties": {
    "tgn:hierarchy":[
        "tgn:2261320",
        "tgn:1000001",
        "tgn:7012149",
        "tgn:2002087",
        "tgn:7007826",
        "tgn:7029392"
    ],
    "tgn:id":2261320,
    "tgn:name":"County Line Tank",
    "tgn:placetype":[
        "aat:300006191"
    ]
},
  "bbox": [],
  "geometry": {"coordinates":[-99.7333,29.0833],"type":"Point"}
}