{
  "id": 2735055,
  "type": "Feature",
  "properties": {
    "tgn:hierarchy":[
        "tgn:2735055",
        "tgn:1000001",
        "tgn:7012149",
        "tgn:2001274",
        "tgn:7007524",
        "tgn:7029392"
    ],
    "tgn:id":2735055,
    "tgn:name":"Twentyfive Mile Creek",
    "tgn:placetype":[
        "aat:300008706"
    ]
},
  "bbox": [],
  "geometry": {"coordinates":[-113.3667,48.2167],"type":"Point"}
}