{
  "id": 7044035,
  "type": "Feature",
  "properties": {
    "tgn:hierarchy":[
        "tgn:7044035",
        "tgn:1003455",
        "tgn:1000003",
        "tgn:7010380",
        "tgn:1000080",
        "tgn:7029392"
    ],
    "tgn:id":7044035,
    "tgn:name":"Capoiale, Foce di",
    "tgn:placetype":[
        "aat:300185707"
    ]
},
  "bbox": [],
  "geometry": {"coordinates":[15.666667,41.916667],"type":"Point"}
}