{
  "id": 2653095,
  "type": "Feature",
  "properties": {
    "tgn:hierarchy":[
        "tgn:2653095",
        "tgn:1000001",
        "tgn:7012149",
        "tgn:2002382",
        "tgn:7007923",
        "tgn:7029392"
    ],
    "tgn:id":2653095,
    "tgn:name":"Seven Lakes",
    "tgn:placetype":[
        "aat:300008680"
    ]
},
  "bbox": [],
  "geometry": {"coordinates":[-109.8167,43.4167],"type":"Point"}
}