{
  "id": 7536328,
  "type": "Feature",
  "properties": {
    "tgn:hierarchy":[
        "tgn:7536328",
        "tgn:7001242",
        "tgn:7016833",
        "tgn:7001336",
        "tgn:7029392"
    ],
    "tgn:id":7536328,
    "tgn:name:en":"Ghur\u0101b\u012b, W\u0101d\u012b",
    "tgn:placetype":[
        "aat:300379998"
    ]
},
  "bbox": [],
  "geometry": {"coordinates":[34.409361,28.301888],"type":"Point"}
}