{
  "id": 7466755,
  "type": "Feature",
  "properties": {
    "tgn:hierarchy":[
        "tgn:7466755",
        "tgn:7002445",
        "tgn:7029548",
        "tgn:1000003",
        "tgn:7008591",
        "tgn:7029392"
    ],
    "tgn:id":7466755,
    "tgn:name:en":"Bispham",
    "tgn:placetype":[
        "aat:300008347"
    ]
},
  "bbox": [],
  "geometry": {"coordinates":[-3.05,53.85],"type":"Point"}
}