{
  "id": 2321864,
  "type": "Feature",
  "properties": {
    "tgn:hierarchy":[
        "tgn:2321864",
        "tgn:1000001",
        "tgn:7012149",
        "tgn:2002246",
        "tgn:7007920",
        "tgn:7029392"
    ],
    "tgn:id":2321864,
    "tgn:name":"Falcon Lake",
    "tgn:placetype":[
        "aat:300008680"
    ]
},
  "bbox": [],
  "geometry": {"coordinates":[-119.2833,46.9667],"type":"Point"}
}