{
  "id": 2052750,
  "type": "Feature",
  "properties": {
    "tgn:hierarchy":[
        "tgn:2052750",
        "tgn:1000001",
        "tgn:2000955",
        "tgn:7012149",
        "tgn:7007520",
        "tgn:7029392"
    ],
    "tgn:id":2052750,
    "tgn:name":"Narenta",
    "tgn:placetype":[
        "aat:300387016"
    ]
},
  "bbox": [],
  "geometry": {"coordinates":[-87.2333,45.7167],"type":"Point"}
}