{
  "id": 7293559,
  "type": "Feature",
  "properties": {
    "tgn:hierarchy":[
        "tgn:7293559",
        "tgn:7002829",
        "tgn:1000003",
        "tgn:7002786",
        "tgn:1000095",
        "tgn:7029392"
    ],
    "tgn:id":7293559,
    "tgn:name":"Villafiz",
    "tgn:placetype":[
        "aat:300008347"
    ]
},
  "bbox": [],
  "geometry": {"coordinates":[-7.716667,42.983333],"type":"Point"}
}