{
  "id": 2682528,
  "type": "Feature",
  "properties": {
    "tgn:hierarchy":[
        "tgn:2682528",
        "tgn:1000001",
        "tgn:7012149",
        "tgn:2002100",
        "tgn:7007826",
        "tgn:7029392"
    ],
    "tgn:id":2682528,
    "tgn:name":"Southeast Tank",
    "tgn:placetype":[
        "aat:300006191"
    ]
},
  "bbox": [],
  "geometry": {"coordinates":[-99.8833,28.8667],"type":"Point"}
}