{
  "id": 7055805,
  "type": "Feature",
  "properties": {
    "tgn:hierarchy":[
        "tgn:7055805",
        "tgn:1003506",
        "tgn:1000003",
        "tgn:7002993",
        "tgn:1000080",
        "tgn:7029392"
    ],
    "tgn:id":7055805,
    "tgn:name":"Plezzut di Tarvisio",
    "tgn:placetype":[
        "aat:300008347"
    ]
},
  "bbox": [],
  "geometry": {"coordinates":[13.589167,46.488611],"type":"Point"}
}