{
  "id": 2299128,
  "type": "Feature",
  "properties": {
    "tgn:hierarchy":[
        "tgn:2299128",
        "tgn:1000001",
        "tgn:7013368",
        "tgn:7012149",
        "tgn:7007709",
        "tgn:7029392"
    ],
    "tgn:id":2299128,
    "tgn:name":"Duck Creek",
    "tgn:placetype":[
        "aat:300008706"
    ]
},
  "bbox": [],
  "geometry": {"coordinates":[-76.85,35.4833],"type":"Point"}
}