{
  "id": 2139343,
  "type": "Feature",
  "properties": {
    "tgn:hierarchy":[
        "tgn:2139343",
        "tgn:1000001",
        "tgn:7012149",
        "tgn:7007157",
        "tgn:1002857",
        "tgn:7029392"
    ],
    "tgn:id":2139343,
    "tgn:name":"Aspen Grove",
    "tgn:placetype":[
        "aat:300132451"
    ]
},
  "bbox": [],
  "geometry": {"coordinates":[-116.7833,34.1333],"type":"Point"}
}