{
  "id": 7317216,
  "type": "Feature",
  "properties": {
    "tgn:hierarchy":[
        "tgn:7317216",
        "tgn:1001768",
        "tgn:1000049",
        "tgn:1000002",
        "tgn:7029392"
    ],
    "tgn:id":7317216,
    "tgn:name":"Conc\u00f3n, Rocas",
    "tgn:placetype":[
        "aat:300011692"
    ]
},
  "bbox": [],
  "geometry": {"coordinates":[-71.558611,-32.868333],"type":"Point"}
}