{
  "id": 7528087,
  "type": "Feature",
  "properties": {
    "tgn:hierarchy":[
        "tgn:7528087",
        "tgn:7001242",
        "tgn:7016833",
        "tgn:7001334",
        "tgn:7029392"
    ],
    "tgn:id":7528087,
    "tgn:name:en":"Sinn al Kadhdh\u0101b",
    "tgn:placetype":[
        "aat:300132353"
    ]
},
  "bbox": [],
  "geometry": {"coordinates":[32.109623,23.578431],"type":"Point"}
}