{
  "id": 1108761,
  "type": "Feature",
  "properties": {
    "tgn:hierarchy":[
        "tgn:1108761",
        "tgn:1001256",
        "tgn:1000004",
        "tgn:7018454",
        "tgn:1000144",
        "tgn:7029392"
    ],
    "tgn:id":1108761,
    "tgn:name":"Balabandaglari",
    "tgn:placetype":[
        "aat:300008795"
    ]
},
  "bbox": [],
  "geometry": {"coordinates":[39.25,40.4667],"type":"Point"}
}