{
  "id": 2613819,
  "type": "Feature",
  "properties": {
    "tgn:hierarchy":[
        "tgn:2613819",
        "tgn:1000001",
        "tgn:7012149",
        "tgn:2001489",
        "tgn:7007709",
        "tgn:7029392"
    ],
    "tgn:id":2613819,
    "tgn:name":"Reedy Creek",
    "tgn:placetype":[
        "aat:300008706"
    ]
},
  "bbox": [],
  "geometry": {"coordinates":[-80.2333,35.9167],"type":"Point"}
}