{
  "id": 2559200,
  "type": "Feature",
  "properties": {
    "tgn:hierarchy":[
        "tgn:2559200",
        "tgn:1000001",
        "tgn:7012149",
        "tgn:2000433",
        "tgn:7007248",
        "tgn:7029392"
    ],
    "tgn:id":2559200,
    "tgn:name":"Oneal Wynn Lake Dam",
    "tgn:placetype":[
        "aat:300006191"
    ]
},
  "bbox": [],
  "geometry": {"coordinates":[-83.4833,31.6833],"type":"Point"}
}