{
  "id": 2635103,
  "type": "Feature",
  "properties": {
    "tgn:hierarchy":[
        "tgn:2635103",
        "tgn:1000001",
        "tgn:7012149",
        "tgn:2000837",
        "tgn:7007255",
        "tgn:7029392"
    ],
    "tgn:id":2635103,
    "tgn:name":"Rye Straw Branch",
    "tgn:placetype":[
        "aat:300008699"
    ]
},
  "bbox": [],
  "geometry": {"coordinates":[-82.4167,37.6167],"type":"Point"}
}