{
  "id": 2701690,
  "type": "Feature",
  "properties": {
    "tgn:hierarchy":[
        "tgn:2701690",
        "tgn:1000001",
        "tgn:7012149",
        "tgn:7007157",
        "tgn:1003050",
        "tgn:7029392"
    ],
    "tgn:id":2701690,
    "tgn:name":"Sugarloaf",
    "tgn:placetype":[
        "aat:300008798"
    ]
},
  "bbox": [],
  "geometry": {"coordinates":[-121.35,39.3667],"type":"Point"}
}