{
  "id": 7111224,
  "type": "Feature",
  "properties": {
    "tgn:hierarchy":[
        "tgn:7111224",
        "tgn:7003669",
        "tgn:1000003",
        "tgn:7000084",
        "tgn:7029392"
    ],
    "tgn:id":7111224,
    "tgn:name":"Ried",
    "tgn:placetype":[
        "aat:300000206"
    ]
},
  "bbox": [],
  "geometry": {"coordinates":[12.75,48.95],"type":"Point"}
}