{
  "id": 1018337,
  "type": "Feature",
  "properties": {
    "tgn:hierarchy":[
        "tgn:1018337",
        "tgn:1000001",
        "tgn:7005591",
        "tgn:7005560",
        "tgn:7029392"
    ],
    "tgn:id":1018337,
    "tgn:name":"Santo Tom\u00e1s Ocotepec",
    "tgn:placetype":[
        "aat:300008347"
    ]
},
  "bbox": [],
  "geometry": {"coordinates":[-97.7667,17.1333],"type":"Point"}
}