{
  "id": 2341247,
  "type": "Feature",
  "properties": {
    "tgn:hierarchy":[
        "tgn:2341247",
        "tgn:1000001",
        "tgn:7006451",
        "tgn:7012149",
        "tgn:2000103",
        "tgn:7029392"
    ],
    "tgn:id":2341247,
    "tgn:name":"Fritche Tank",
    "tgn:placetype":[
        "aat:300006191"
    ]
},
  "bbox": [],
  "geometry": {"coordinates":[-112.7833,34.9667],"type":"Point"}
}