{
  "id": 7437720,
  "type": "Feature",
  "properties": {
    "tgn:hierarchy":[
        "tgn:7437720",
        "tgn:1000001",
        "tgn:1001960",
        "tgn:7005560",
        "tgn:7029392"
    ],
    "tgn:id":7437720,
    "tgn:name":"Teopare",
    "tgn:placetype":[
        "aat:300008347"
    ]
},
  "bbox": [],
  "geometry": {"coordinates":[-110.066667,29.233333],"type":"Point"}
}