{
  "id": 2467276,
  "type": "Feature",
  "properties": {
    "tgn:hierarchy":[
        "tgn:2467276",
        "tgn:1000001",
        "tgn:2001945",
        "tgn:7012149",
        "tgn:7007826",
        "tgn:7029392"
    ],
    "tgn:id":2467276,
    "tgn:name":"Long Draw, The",
    "tgn:placetype":[
        "aat:300008761"
    ]
},
  "bbox": [],
  "geometry": {"coordinates":[-103.7167,29.3667],"type":"Point"}
}