{
  "id": 7294084,
  "type": "Feature",
  "properties": {
    "tgn:hierarchy":[
        "tgn:7294084",
        "tgn:7002758",
        "tgn:7002817",
        "tgn:1000003",
        "tgn:1000095",
        "tgn:7029392"
    ],
    "tgn:id":7294084,
    "tgn:name":"Vaquera, Loma de la",
    "tgn:placetype":[
        "aat:300266640"
    ]
},
  "bbox": [],
  "geometry": {"coordinates":[-5.283333,38.066667],"type":"Point"}
}