{
  "id": 7224204,
  "type": "Feature",
  "properties": {
    "tgn:hierarchy":[
        "tgn:7224204",
        "tgn:7002690",
        "tgn:7012056",
        "tgn:1000003",
        "tgn:1000074",
        "tgn:7029392"
    ],
    "tgn:id":7224204,
    "tgn:name":"Nis\u00ed",
    "tgn:placetype":[
        "aat:300008850"
    ]
},
  "bbox": [],
  "geometry": {"coordinates":[24.066667,35.55],"type":"Point"}
}