{
  "id": 7127222,
  "type": "Feature",
  "properties": {
    "tgn:hierarchy":[
        "tgn:7127222",
        "tgn:7003669",
        "tgn:1000003",
        "tgn:7000084",
        "tgn:7029392"
    ],
    "tgn:id":7127222,
    "tgn:name":"Oberhasling",
    "tgn:placetype":[
        "aat:300008347"
    ]
},
  "bbox": [],
  "geometry": {"coordinates":[11.883333,47.833333],"type":"Point"}
}