{
  "id": 7083139,
  "type": "Feature",
  "properties": {
    "tgn:hierarchy":[
        "tgn:7083139",
        "tgn:1000003",
        "tgn:7003677",
        "tgn:7000084",
        "tgn:7029392"
    ],
    "tgn:id":7083139,
    "tgn:name":"Willigenpass",
    "tgn:placetype":[
        "aat:300000206"
    ]
},
  "bbox": [],
  "geometry": {"coordinates":[6.116667,51.833333],"type":"Point"}
}