{
  "id": 7589434,
  "type": "Feature",
  "properties": {
    "tgn:hierarchy":[
        "tgn:7589434",
        "tgn:1000004",
        "tgn:7000198",
        "tgn:7000799",
        "tgn:7029392"
    ],
    "tgn:id":7589434,
    "tgn:name:en":"Bhanera Forest",
    "tgn:placetype":[
        "aat:300008863"
    ]
},
  "bbox": [],
  "geometry": {"coordinates":[74.372222,33.183333],"type":"Point"}
}