{
  "id": 2213094,
  "type": "Feature",
  "properties": {
    "tgn:hierarchy":[
        "tgn:2213094",
        "tgn:1000001",
        "tgn:7012149",
        "tgn:2000277",
        "tgn:7007240",
        "tgn:7029392"
    ],
    "tgn:id":2213094,
    "tgn:name":"Cabbage Slough",
    "tgn:placetype":[
        "aat:300008699"
    ]
},
  "bbox": [],
  "geometry": {"coordinates":[-82.7833,29.25],"type":"Point"}
}