{
  "id": 2493750,
  "type": "Feature",
  "properties": {
    "tgn:hierarchy":[
        "tgn:2493750",
        "tgn:1000001",
        "tgn:2001472",
        "tgn:7012149",
        "tgn:7007709",
        "tgn:7029392"
    ],
    "tgn:id":2493750,
    "tgn:name":"Marsh, Lake",
    "tgn:placetype":[
        "aat:300008680"
    ]
},
  "bbox": [],
  "geometry": {"coordinates":[-78.0167,34.0333],"type":"Point"}
}