{
  "id": 7289288,
  "type": "Feature",
  "properties": {
    "tgn:hierarchy":[
        "tgn:7289288",
        "tgn:1001702",
        "tgn:1000049",
        "tgn:1000002",
        "tgn:7029392"
    ],
    "tgn:id":7289288,
    "tgn:name":"Intricate, Bah\u00eda",
    "tgn:placetype":[
        "aat:300132316"
    ]
},
  "bbox": [],
  "geometry": {"coordinates":[-73.533333,-52.05],"type":"Point"}
}