<<<<<<< HEAD
{
  "id": 7356325,
  "type": "Feature",
  "properties": {
    "tgn:hierarchy":[
        "tgn:7356325",
        "tgn:1000001",
        "tgn:7005595",
        "tgn:7005560",
        "tgn:7029392"
    ],
    "tgn:id":7356325,
    "tgn:name":"Chilicote",
    "tgn:placetype":[
        "aat:300008347"
    ]
},
  "bbox": [],
  "geometry": {"coordinates":[-108.4,26.883333],"type":"Point"}
}
=======
{"geometry":{"type":"Point","coordinates":[-108.400000,26.883333]},"type":"Feature","properties":{"hierarchy":["tgn:7356325","tgn:1000001","tgn:7005595","tgn:7005560","tgn:7029392"],"placetype":["aat:300008347"],"id":7356325,"name:xx":"Chilicote"}}
>>>>>>> 03f74aca74312dbeaf24d7e61306dd6a786dc3d0
