{
  "id": 2514811,
  "type": "Feature",
  "properties": {
    "tgn:hierarchy":[
        "tgn:2514811",
        "tgn:1000001",
        "tgn:7012149",
        "tgn:2001283",
        "tgn:7007524",
        "tgn:7029392"
    ],
    "tgn:id":2514811,
    "tgn:name":"Miller Point",
    "tgn:placetype":[
        "aat:300008850"
    ]
},
  "bbox": [],
  "geometry": {"coordinates":[-114.1667,47.9167],"type":"Point"}
}