<<<<<<< HEAD
{
  "id": 2765895,
  "type": "Feature",
  "properties": {
    "tgn:hierarchy":[
        "tgn:2765895",
        "tgn:7002659",
        "tgn:1000001",
        "tgn:7012149",
        "tgn:2000059",
        "tgn:7029392"
    ],
    "tgn:id":2765895,
    "tgn:name":"White Hall Creek",
    "tgn:placetype":[
        "aat:300008706"
    ]
},
  "bbox": [],
  "geometry": {"coordinates":[-88.3167,32.5333],"type":"Point"}
}
=======
{"geometry":{"type":"Point","coordinates":[-88.316700,32.533300]},"type":"Feature","properties":{"hierarchy":["tgn:2765895","tgn:7002659","tgn:1000001","tgn:7012149","tgn:2000059","tgn:7029392"],"placetype":["aat:300008706"],"id":2765895,"name:xx":"White Hall Creek"}}
>>>>>>> 03f74aca74312dbeaf24d7e61306dd6a786dc3d0
