<<<<<<< HEAD
{
  "id": 2255445,
  "type": "Feature",
  "properties": {
    "tgn:hierarchy":[
        "tgn:2255445",
        "tgn:1000001",
        "tgn:7012149",
        "tgn:2000442",
        "tgn:7007248",
        "tgn:7029392"
    ],
    "tgn:id":2255445,
    "tgn:name":"Cooter Ridge",
    "tgn:placetype":[
        "aat:300266640"
    ]
},
  "bbox": [],
  "geometry": {"coordinates":[-81.6833,31.5667],"type":"Point"}
}
=======
{"geometry":{"type":"Point","coordinates":[-81.683300,31.566700]},"type":"Feature","properties":{"hierarchy":["tgn:2255445","tgn:1000001","tgn:7012149","tgn:2000442","tgn:7007248","tgn:7029392"],"placetype":["aat:300266640"],"id":2255445,"name:xx":"Cooter Ridge"}}
>>>>>>> 03f74aca74312dbeaf24d7e61306dd6a786dc3d0
