<<<<<<< HEAD
{
  "id": 7241493,
  "type": "Feature",
  "properties": {
    "tgn:hierarchy":[
        "tgn:7241493",
        "tgn:7003466",
        "tgn:1000003",
        "tgn:1000063",
        "tgn:4012014",
        "tgn:7029392"
    ],
    "tgn:id":7241493,
    "tgn:name":"Li\u00e9neux",
    "tgn:placetype":[
        "aat:300008347"
    ]
},
  "bbox": [],
  "geometry": {"coordinates":[5.283333,50.3],"type":"Point"}
}
=======
{"geometry":{"type":"Point","coordinates":[5.283333,50.300000]},"type":"Feature","properties":{"hierarchy":["tgn:7241493","tgn:7003466","tgn:1000003","tgn:1000063","tgn:4012014","tgn:7029392"],"placetype":["aat:300008347"],"id":7241493,"name:xx":"Li\u00e9neux"}}
>>>>>>> 03f74aca74312dbeaf24d7e61306dd6a786dc3d0
