{
  "id": 2479777,
  "type": "Feature",
  "properties": {
    "tgn:hierarchy":[
        "tgn:2479777",
        "tgn:1000001",
        "tgn:7012149",
        "tgn:2001712",
        "tgn:7007708",
        "tgn:7029392"
    ],
    "tgn:id":2479777,
    "tgn:name":"Lake Creek",
    "tgn:placetype":[
        "aat:300008706"
    ]
},
  "bbox": [],
  "geometry": {"coordinates":[-121.7167,44.4167],"type":"Point"}
}