{
  "id": 7326592,
  "type": "Feature",
  "properties": {
    "tgn:hierarchy":[
        "tgn:7326592",
        "tgn:7002829",
        "tgn:1000003",
        "tgn:7002786",
        "tgn:1000095",
        "tgn:7029392"
    ],
    "tgn:id":7326592,
    "tgn:name":"Peque\u00f1o, R\u00edo",
    "tgn:placetype":[
        "aat:300008699"
    ]
},
  "bbox": [],
  "geometry": {"coordinates":[-7.45,43.216667],"type":"Point"}
}