{
  "id": 2709441,
  "type": "Feature",
  "properties": {
    "tgn:hierarchy":[
        "tgn:2709441",
        "tgn:1000001",
        "tgn:2001429",
        "tgn:7012149",
        "tgn:7007566",
        "tgn:7029392"
    ],
    "tgn:id":2709441,
    "tgn:name":"Table Top Spring",
    "tgn:placetype":[
        "aat:300008697"
    ]
},
  "bbox": [],
  "geometry": {"coordinates":[-108.95,33.2167],"type":"Point"}
}