{
  "id": 2377563,
  "type": "Feature",
  "properties": {
    "tgn:hierarchy":[
        "tgn:2377563",
        "tgn:1000001",
        "tgn:7012149",
        "tgn:1002723",
        "tgn:7007252",
        "tgn:7029392"
    ],
    "tgn:id":2377563,
    "tgn:name":"Harper Lake",
    "tgn:placetype":[
        "aat:300008680"
    ]
},
  "bbox": [],
  "geometry": {"coordinates":[-85.5833,41.3333],"type":"Point"}
}