{
  "id": 7584481,
  "type": "Feature",
  "properties": {
    "tgn:hierarchy":[
        "tgn:7584481",
        "tgn:1000004",
        "tgn:7000198",
        "tgn:1001894",
        "tgn:7029392"
    ],
    "tgn:id":7584481,
    "tgn:name:en":"L\u0101ira",
    "tgn:placetype":[
        "aat:300008347"
    ]
},
  "bbox": [],
  "geometry": {"coordinates":[78.088562,24.174739],"type":"Point"}
}