{
  "id": 2632528,
  "type": "Feature",
  "properties": {
    "tgn:hierarchy":[
        "tgn:2632528",
        "tgn:1000001",
        "tgn:2001418",
        "tgn:7012149",
        "tgn:7007526",
        "tgn:7029392"
    ],
    "tgn:id":2632528,
    "tgn:name":"Royston Hills",
    "tgn:placetype":[
        "aat:300386831"
    ]
},
  "bbox": [],
  "geometry": {"coordinates":[-117.5667,38.4167],"type":"Point"}
}