{
  "id": 1063132,
  "type": "Feature",
  "properties": {
    "tgn:hierarchy":[
        "tgn:1063132",
        "tgn:1000003",
        "tgn:1000405",
        "tgn:1000097",
        "tgn:7029392"
    ],
    "tgn:id":1063132,
    "tgn:name":"Hohultsl\u00e4tt",
    "tgn:placetype":[
        "aat:300008347"
    ]
},
  "bbox": [],
  "geometry": {"coordinates":[15.65,56.9667],"type":"Point"}
}