{
  "id": 2246913,
  "type": "Feature",
  "properties": {
    "tgn:hierarchy":[
        "tgn:2246913",
        "tgn:1000001",
        "tgn:7012149",
        "tgn:2000441",
        "tgn:7007248",
        "tgn:7029392"
    ],
    "tgn:id":2246913,
    "tgn:name":"Cochran Pond",
    "tgn:placetype":[
        "aat:300006191"
    ]
},
  "bbox": [],
  "geometry": {"coordinates":[-82.9667,32.8833],"type":"Point"}
}