{
  "id": 7075684,
  "type": "Feature",
  "properties": {
    "tgn:hierarchy":[
        "tgn:7075684",
        "tgn:1000003",
        "tgn:7000094",
        "tgn:7000084",
        "tgn:7029392"
    ],
    "tgn:id":7075684,
    "tgn:name":"Zitterpenningshagen",
    "tgn:placetype":[
        "aat:300008347"
    ]
},
  "bbox": [],
  "geometry": {"coordinates":[13.083333,54.25],"type":"Point"}
}