{
  "id": 7413591,
  "type": "Feature",
  "properties": {
    "tgn:hierarchy":[
        "tgn:7413591",
        "tgn:7005587",
        "tgn:1000001",
        "tgn:7005560",
        "tgn:7029392"
    ],
    "tgn:id":7413591,
    "tgn:name:es":"El Chilar",
    "tgn:placetype":[
        "aat:300008347"
    ]
},
  "bbox": [],
  "geometry": {"coordinates":[-98.456944,20.326389],"type":"Point"}
}