{
  "id": 7544305,
  "type": "Feature",
  "properties": {
    "tgn:hierarchy":[
        "tgn:7544305",
        "tgn:7001242",
        "tgn:1001075",
        "tgn:7016833",
        "tgn:7029392"
    ],
    "tgn:id":7544305,
    "tgn:name:en":"Naj' ar Ruzz",
    "tgn:placetype":[
        "aat:300008347"
    ]
},
  "bbox": [],
  "geometry": {"coordinates":[30.097689,30.867576],"type":"Point"}
}