{
  "id": 7513717,
  "type": "Feature",
  "properties": {
    "tgn:hierarchy":[
        "tgn:7513717",
        "tgn:1009227",
        "tgn:1000226",
        "tgn:7018437",
        "tgn:1000006",
        "tgn:7029392"
    ],
    "tgn:id":7513717,
    "tgn:name:en":"Four Mile Creek",
    "tgn:placetype":[
        "aat:300008699"
    ]
},
  "bbox": [],
  "geometry": {"coordinates":[169.216667,-45.016667],"type":"Point"}
}