{
  "id": 7258553,
  "type": "Feature",
  "properties": {
    "tgn:concordances":{
        "gn:id":"2759933"
    },
    "tgn:hierarchy":[
        "tgn:7258553",
        "tgn:1000003",
        "tgn:7003613",
        "tgn:7016845",
        "tgn:7029392"
    ],
    "tgn:id":7258553,
    "tgn:name:nl":"Agodorp",
    "tgn:placetype":[
        "aat:300008347"
    ]
},
  "bbox": [],
  "geometry": {"coordinates":[7.083333,52.866667],"type":"Point"}
}