{
  "id": 7541558,
  "type": "Feature",
  "properties": {
    "tgn:hierarchy":[
        "tgn:7541558",
        "tgn:7001242",
        "tgn:7016833",
        "tgn:7000123",
        "tgn:7029392"
    ],
    "tgn:id":7541558,
    "tgn:name:en":"Ash Sharq\u012b Samh\u016bd",
    "tgn:placetype":[
        "aat:300008347"
    ]
},
  "bbox": [],
  "geometry": {"coordinates":[32.106843,26.183068],"type":"Point"}
}