{
  "id": 2504736,
  "type": "Feature",
  "properties": {
    "tgn:hierarchy":[
        "tgn:2504736",
        "tgn:1000001",
        "tgn:7012149",
        "tgn:2000741",
        "tgn:7007254",
        "tgn:7029392"
    ],
    "tgn:id":2504736,
    "tgn:name":"Medicine Creek",
    "tgn:placetype":[
        "aat:300008706"
    ]
},
  "bbox": [],
  "geometry": {"coordinates":[-99.1333,39.25],"type":"Point"}
}