{
  "id": 2584125,
  "type": "Feature",
  "properties": {
    "tgn:hierarchy":[
        "tgn:2584125",
        "tgn:1000001",
        "tgn:7012149",
        "tgn:2001420",
        "tgn:7007526",
        "tgn:7029392"
    ],
    "tgn:id":2584125,
    "tgn:name":"Pinenut Canyon",
    "tgn:placetype":[
        "aat:300008761"
    ]
},
  "bbox": [],
  "geometry": {"coordinates":[-114.9167,39.9167],"type":"Point"}
}