<<<<<<< HEAD
{
  "id": 2401699,
  "type": "Feature",
  "properties": {
    "tgn:hierarchy":[
        "tgn:2401699",
        "tgn:1000001",
        "tgn:7012149",
        "tgn:2000752",
        "tgn:7007254",
        "tgn:7029392"
    ],
    "tgn:id":2401699,
    "tgn:name":"Horseshoe Lake",
    "tgn:placetype":[
        "aat:300008680"
    ]
},
  "bbox": [],
  "geometry": {"coordinates":[-98.4667,38.1],"type":"Point"}
}
=======
{"geometry":{"type":"Point","coordinates":[-98.466700,38.100000]},"type":"Feature","properties":{"hierarchy":["tgn:2401699","tgn:1000001","tgn:7012149","tgn:2000752","tgn:7007254","tgn:7029392"],"placetype":["aat:300008680"],"id":2401699,"name:xx":"Horseshoe Lake"}}
>>>>>>> 03f74aca74312dbeaf24d7e61306dd6a786dc3d0
