{
  "id": 2446297,
  "type": "Feature",
  "properties": {
    "tgn:hierarchy":[
        "tgn:2446297",
        "tgn:1000001",
        "tgn:7012149",
        "tgn:7007157",
        "tgn:2000189",
        "tgn:7029392"
    ],
    "tgn:id":2446297,
    "tgn:name":"Lewis Creek",
    "tgn:placetype":[
        "aat:300008706"
    ]
},
  "bbox": [],
  "geometry": {"coordinates":[-123.4333,41.2833],"type":"Point"}
}