{
  "id": 7587682,
  "type": "Feature",
  "properties": {
    "tgn:hierarchy":[
        "tgn:7587682",
        "tgn:1000004",
        "tgn:7000198",
        "tgn:7000799",
        "tgn:7029392"
    ],
    "tgn:id":7587682,
    "tgn:name:en":"Nih\u0101lpur",
    "tgn:placetype":[
        "aat:300008347"
    ]
},
  "bbox": [],
  "geometry": {"coordinates":[74.524824,34.149924],"type":"Point"}
}