{
  "id": 2247783,
  "type": "Feature",
  "properties": {
    "tgn:hierarchy":[
        "tgn:2247783",
        "tgn:1000001",
        "tgn:7006451",
        "tgn:7012149",
        "tgn:2000098",
        "tgn:7029392"
    ],
    "tgn:id":2247783,
    "tgn:name":"Cohenour Mine",
    "tgn:placetype":[
        "aat:300000390"
    ]
},
  "bbox": [],
  "geometry": {"coordinates":[-114.5667,36.0667],"type":"Point"}
}