{
  "id": 2720412,
  "type": "Feature",
  "properties": {
    "tgn:hierarchy":[
        "tgn:2720412",
        "tgn:1000001",
        "tgn:2000468",
        "tgn:7012149",
        "tgn:7007250",
        "tgn:7029392"
    ],
    "tgn:id":2720412,
    "tgn:name":"Thunder Gulch",
    "tgn:placetype":[
        "aat:300008761"
    ]
},
  "bbox": [],
  "geometry": {"coordinates":[-112.35,44.3667],"type":"Point"}
}