<<<<<<< HEAD
{
  "id": 7057537,
  "type": "Feature",
  "properties": {
    "tgn:hierarchy":[
        "tgn:7057537",
        "tgn:1003483",
        "tgn:1000003",
        "tgn:7003240",
        "tgn:1000080",
        "tgn:7029392"
    ],
    "tgn:id":7057537,
    "tgn:name":"Ca Boano",
    "tgn:placetype":[
        "aat:300008347"
    ]
},
  "bbox": [],
  "geometry": {"coordinates":[12.266667,43.816667],"type":"Point"}
}
=======
{"geometry":{"type":"Point","coordinates":[12.266667,43.816667]},"type":"Feature","properties":{"hierarchy":["tgn:7057537","tgn:1003483","tgn:1000003","tgn:7003240","tgn:1000080","tgn:7029392"],"placetype":["aat:300008347"],"id":7057537,"name:xx":"Ca Boano"}}
>>>>>>> 03f74aca74312dbeaf24d7e61306dd6a786dc3d0
