{
  "id": 7009678,
  "type": "Feature",
  "properties": {
    "tgn:hierarchy":[
        "tgn:7009678",
        "tgn:1000003",
        "tgn:7002877",
        "tgn:1000070",
        "tgn:7029392"
    ],
    "tgn:id":7009678,
    "tgn:name":"Senonches",
    "tgn:placetype":[
        "aat:300008347"
    ]
},
  "bbox": [],
  "geometry": {"coordinates":[-1.05,48.5667],"type":"Point"}
}