{
  "id": 2712643,
  "type": "Feature",
  "properties": {
    "tgn:hierarchy":[
        "tgn:2712643",
        "tgn:1000001",
        "tgn:7012149",
        "tgn:2001442",
        "tgn:7007566",
        "tgn:7029392"
    ],
    "tgn:id":2712643,
    "tgn:name":"Taylor Canyon",
    "tgn:placetype":[
        "aat:300008701"
    ]
},
  "bbox": [],
  "geometry": {"coordinates":[-105.3833,34.1667],"type":"Point"}
}