{
  "id": 2582089,
  "type": "Feature",
  "properties": {
    "tgn:hierarchy":[
        "tgn:2582089",
        "tgn:1000001",
        "tgn:7016172",
        "tgn:7012149",
        "tgn:2000177",
        "tgn:7029392"
    ],
    "tgn:id":2582089,
    "tgn:name":"Pine Creek",
    "tgn:placetype":[
        "aat:300008706"
    ]
},
  "bbox": [],
  "geometry": {"coordinates":[-91.5667,35.4167],"type":"Point"}
}