{
  "id": 2628516,
  "type": "Feature",
  "properties": {
    "tgn:hierarchy":[
        "tgn:2628516",
        "tgn:1000001",
        "tgn:7012149",
        "tgn:2002248",
        "tgn:7007920",
        "tgn:7029392"
    ],
    "tgn:id":2628516,
    "tgn:name":"Roosevelt Grove Of Ancient Cedars",
    "tgn:placetype":[
        "aat:300132451"
    ]
},
  "bbox": [],
  "geometry": {"coordinates":[-117.05,48.7667],"type":"Point"}
}