{
  "id": 7309325,
  "type": "Feature",
  "properties": {
    "tgn:hierarchy":[
        "tgn:7309325",
        "tgn:1001623",
        "tgn:1000049",
        "tgn:1000002",
        "tgn:7029392"
    ],
    "tgn:id":7309325,
    "tgn:name":"Luc\u00eda, Ventisquero",
    "tgn:placetype":[
        "aat:300008835"
    ]
},
  "bbox": [],
  "geometry": {"coordinates":[-73.35,-48.366667],"type":"Point"}
}