{
  "id": 7165040,
  "type": "Feature",
  "properties": {
    "tgn:hierarchy":[
        "tgn:7165040",
        "tgn:1000003",
        "tgn:7003682",
        "tgn:7000084",
        "tgn:7029392"
    ],
    "tgn:id":7165040,
    "tgn:name":"Hottenbach",
    "tgn:placetype":[
        "aat:300008699"
    ]
},
  "bbox": [],
  "geometry": {"coordinates":[7.633333,49.783333],"type":"Point"}
}