{
  "id": 7101145,
  "type": "Feature",
  "properties": {
    "tgn:hierarchy":[
        "tgn:7101145",
        "tgn:1000003",
        "tgn:7003678",
        "tgn:7000084",
        "tgn:7029392"
    ],
    "tgn:id":7101145,
    "tgn:name":"Sau-Graben",
    "tgn:placetype":[
        "aat:300008699"
    ]
},
  "bbox": [],
  "geometry": {"coordinates":[9.416667,51.216667],"type":"Point"}
}