{
  "id": 2290967,
  "type": "Feature",
  "properties": {
    "tgn:hierarchy":[
        "tgn:2290967",
        "tgn:1000001",
        "tgn:2000924",
        "tgn:7012149",
        "tgn:7007515",
        "tgn:7029392"
    ],
    "tgn:id":2290967,
    "tgn:name":"Dog Point",
    "tgn:placetype":[
        "aat:300008850"
    ]
},
  "bbox": [],
  "geometry": {"coordinates":[-68.8667,44.05],"type":"Point"}
}