{
  "id": 2208653,
  "type": "Feature",
  "properties": {
    "tgn:hierarchy":[
        "tgn:2208653",
        "tgn:1000001",
        "tgn:7012149",
        "tgn:1002899",
        "tgn:7007920",
        "tgn:7029392"
    ],
    "tgn:id":2208653,
    "tgn:name":"Burns Creek",
    "tgn:placetype":[
        "aat:300008706"
    ]
},
  "bbox": [],
  "geometry": {"coordinates":[-121.5333,48.1833],"type":"Point"}
}