{
  "id": 2380165,
  "type": "Feature",
  "properties": {
    "tgn:hierarchy":[
        "tgn:2380165",
        "tgn:1000001",
        "tgn:7012149",
        "tgn:2001507",
        "tgn:7007709",
        "tgn:7029392"
    ],
    "tgn:id":2380165,
    "tgn:name":"Hatfield Association Lake",
    "tgn:placetype":[
        "aat:300006191"
    ]
},
  "bbox": [],
  "geometry": {"coordinates":[-80.8333,35.8167],"type":"Point"}
}