{
  "id": 2626163,
  "type": "Feature",
  "properties": {
    "tgn:hierarchy":[
        "tgn:2626163",
        "tgn:1000001",
        "tgn:7012149",
        "tgn:2001667",
        "tgn:7007707",
        "tgn:7029392"
    ],
    "tgn:id":2626163,
    "tgn:name":"Rocky Creek",
    "tgn:placetype":[
        "aat:300008706"
    ]
},
  "bbox": [],
  "geometry": {"coordinates":[-94.9833,34.35],"type":"Point"}
}