{
  "id": 7519421,
  "type": "Feature",
  "properties": {
    "tgn:hierarchy":[
        "tgn:7519421",
        "tgn:1009227",
        "tgn:1000226",
        "tgn:7018437",
        "tgn:1000006",
        "tgn:7029392"
    ],
    "tgn:id":7519421,
    "tgn:name:en":"Boyds Creek",
    "tgn:placetype":[
        "aat:300008699"
    ]
},
  "bbox": [],
  "geometry": {"coordinates":[170.233333,-45.716667],"type":"Point"}
}