{
  "id": 2668843,
  "type": "Feature",
  "properties": {
    "tgn:hierarchy":[
        "tgn:2668843",
        "tgn:1000001",
        "tgn:7012149",
        "tgn:2002127",
        "tgn:7007827",
        "tgn:7029392"
    ],
    "tgn:id":2668843,
    "tgn:name":"Slaughter Creek",
    "tgn:placetype":[
        "aat:300008706"
    ]
},
  "bbox": [],
  "geometry": {"coordinates":[-113.9333,37.4833],"type":"Point"}
}