{
  "id": 1052463,
  "type": "Feature",
  "properties": {
    "tgn:hierarchy":[
        "tgn:1052463",
        "tgn:1000004",
        "tgn:7011531",
        "tgn:7018214",
        "tgn:7002435",
        "tgn:7029392"
    ],
    "tgn:id":1052463,
    "tgn:name":"Bakinskaya",
    "tgn:placetype":[
        "aat:300008347"
    ]
},
  "bbox": [],
  "geometry": {"coordinates":[39.2833,44.75],"type":"Point"}
}