{
  "id": 7561077,
  "type": "Feature",
  "properties": {
    "tgn:hierarchy":[
        "tgn:7561077",
        "tgn:1000004",
        "tgn:7000198",
        "tgn:7016722",
        "tgn:7029392"
    ],
    "tgn:id":7561077,
    "tgn:name:en":"Randh\u012brpur",
    "tgn:placetype":[
        "aat:300008347"
    ]
},
  "bbox": [],
  "geometry": {"coordinates":[79.489486,27.11845],"type":"Point"}
}