{
  "id": 2269596,
  "type": "Feature",
  "properties": {
    "tgn:hierarchy":[
        "tgn:2269596",
        "tgn:1000001",
        "tgn:7012149",
        "tgn:2001711",
        "tgn:7007708",
        "tgn:7029392"
    ],
    "tgn:id":2269596,
    "tgn:name":"Crowfoot Creek",
    "tgn:placetype":[
        "aat:300008706"
    ]
},
  "bbox": [],
  "geometry": {"coordinates":[-122.7167,42.6167],"type":"Point"}
}