{
  "id": 7322597,
  "type": "Feature",
  "properties": {
    "tgn:hierarchy":[
        "tgn:7322597",
        "tgn:7001155",
        "tgn:1000003",
        "tgn:7002790",
        "tgn:1000095",
        "tgn:7029392"
    ],
    "tgn:id":7322597,
    "tgn:name":"San Adri\u00e1n",
    "tgn:placetype":[
        "aat:300008347"
    ]
},
  "bbox": [],
  "geometry": {"coordinates":[-1.933333,42.333333],"type":"Point"}
}