{
  "id": 7505680,
  "type": "Feature",
  "properties": {
    "tgn:hierarchy":[
        "tgn:7505680",
        "tgn:1008380",
        "tgn:1000226",
        "tgn:7000512",
        "tgn:1000006",
        "tgn:7029392"
    ],
    "tgn:id":7505680,
    "tgn:name:en":"Whakarua",
    "tgn:placetype":[
        "aat:300008699"
    ]
},
  "bbox": [],
  "geometry": {"coordinates":[175.583333,-41.216667],"type":"Point"}
}