{
  "id": 7254744,
  "type": "Feature",
  "properties": {
    "tgn:hierarchy":[
        "tgn:7254744",
        "tgn:7003460",
        "tgn:1000003",
        "tgn:1000063",
        "tgn:4012014",
        "tgn:7029392"
    ],
    "tgn:id":7254744,
    "tgn:name":"Ferme de Tibi\u00e9mont",
    "tgn:placetype":[
        "aat:300000206"
    ]
},
  "bbox": [],
  "geometry": {"coordinates":[5.297982,50.423094],"type":"Point"}
}