{
  "id": 1017257,
  "type": "Feature",
  "properties": {
    "tgn:hierarchy":[
        "tgn:1017257",
        "tgn:1000001",
        "tgn:7005590",
        "tgn:7005560",
        "tgn:7029392"
    ],
    "tgn:id":1017257,
    "tgn:name":"Cojumatl\u00e1n de R\u00e9gules",
    "tgn:placetype":[
        "aat:300008347"
    ]
},
  "bbox": [],
  "geometry": {"coordinates":[-102.833333,20.116667],"type":"Point"}
}