{
  "id": 7512412,
  "type": "Feature",
  "properties": {
    "tgn:hierarchy":[
        "tgn:7512412",
        "tgn:1008380",
        "tgn:1000226",
        "tgn:7016827",
        "tgn:1000006",
        "tgn:7029392"
    ],
    "tgn:id":7512412,
    "tgn:name:en":"Huiroa",
    "tgn:placetype":[
        "aat:300008777"
    ]
},
  "bbox": [],
  "geometry": {"coordinates":[174.416667,-39.216667],"type":"Point"}
}