{
  "id": 1074566,
  "type": "Feature",
  "properties": {
    "tgn:hierarchy":[
        "tgn:1074566",
        "tgn:1000004",
        "tgn:1001842",
        "tgn:7000198",
        "tgn:7029392"
    ],
    "tgn:id":1074566,
    "tgn:name:en":"Bih\u0101r Shar\u012bf",
    "tgn:placetype":[
        "aat:300008347"
    ]
},
  "bbox": [],
  "geometry": {"coordinates":[85.523736,25.197294],"type":"Point"}
}