{
  "id": 7400262,
  "type": "Feature",
  "properties": {
    "tgn:hierarchy":[
        "tgn:7400262",
        "tgn:1000001",
        "tgn:7005599",
        "tgn:7005560",
        "tgn:7029392"
    ],
    "tgn:id":7400262,
    "tgn:name":"Tecuanapa",
    "tgn:placetype":[
        "aat:300008347"
    ]
},
  "bbox": [],
  "geometry": {"coordinates":[-94.233333,17.740278],"type":"Point"}
}