{
  "id": 7357957,
  "type": "Feature",
  "properties": {
    "tgn:hierarchy":[
        "tgn:7357957",
        "tgn:7005581",
        "tgn:1000001",
        "tgn:7005560",
        "tgn:7029392"
    ],
    "tgn:id":7357957,
    "tgn:name":"Colonia Fern\u00e1ndez",
    "tgn:placetype":[
        "aat:300008347"
    ]
},
  "bbox": [],
  "geometry": {"coordinates":[-108.316667,30.033333],"type":"Point"}
}