<<<<<<< HEAD
{
  "id": 7357957,
  "type": "Feature",
  "properties": {
    "tgn:hierarchy":[
        "tgn:7357957",
        "tgn:7005581",
        "tgn:1000001",
        "tgn:7005560",
        "tgn:7029392"
    ],
    "tgn:id":7357957,
    "tgn:name":"Colonia Fern\u00e1ndez",
    "tgn:placetype":[
        "aat:300008347"
    ]
},
  "bbox": [],
  "geometry": {"coordinates":[-108.316667,30.033333],"type":"Point"}
}
=======
{"geometry":{"type":"Point","coordinates":[-108.316667,30.033333]},"type":"Feature","properties":{"hierarchy":["tgn:7357957","tgn:7005581","tgn:1000001","tgn:7005560","tgn:7029392"],"placetype":["aat:300008347"],"id":7357957,"name:xx":"Colonia Fern\u00e1ndez"}}
>>>>>>> 03f74aca74312dbeaf24d7e61306dd6a786dc3d0
