<<<<<<< HEAD
{
  "id": 7027319,
  "type": "Feature",
  "properties": {
    "tgn:hierarchy":[
        "tgn:7027319",
        "tgn:7002445",
        "tgn:7011980",
        "tgn:1000003",
        "tgn:7008591",
        "tgn:7029392"
    ],
    "tgn:id":7027319,
    "tgn:name:en":"Winwick",
    "tgn:placetype":[
        "aat:300008347",
        "aat:300008372"
    ]
},
  "bbox": [],
  "geometry": {"coordinates":[-0.366667,52.4],"type":"Point"}
}
=======
{"geometry":{"type":"Point","coordinates":[-0.366667,52.400000]},"type":"Feature","properties":{"hierarchy":["tgn:7027319","tgn:7002445","tgn:7011980","tgn:1000003","tgn:7008591","tgn:7029392"],"placetype":["aat:300008347","aat:300008372"],"name:en":"Winwick","id":7027319}}
>>>>>>> 03f74aca74312dbeaf24d7e61306dd6a786dc3d0
