{
  "id": 2729873,
  "type": "Feature",
  "properties": {
    "tgn:hierarchy":[
        "tgn:2729873",
        "tgn:1000001",
        "tgn:7012149",
        "tgn:1002747",
        "tgn:7007568",
        "tgn:7029392"
    ],
    "tgn:id":2729873,
    "tgn:name":"Trout Brook",
    "tgn:placetype":[
        "aat:300008699"
    ]
},
  "bbox": [],
  "geometry": {"coordinates":[-77.4667,42.9167],"type":"Point"}
}