{
  "id": 7489469,
  "type": "Feature",
  "properties": {
    "tgn:hierarchy":[
        "tgn:7489469",
        "tgn:7468018",
        "tgn:1000004",
        "tgn:1000141",
        "tgn:7029392"
    ],
    "tgn:id":7489469,
    "tgn:name":"Neitian",
    "tgn:placetype":[
        "aat:300008347"
    ]
},
  "bbox": [],
  "geometry": {"coordinates":[120.17779,23.380965],"type":"Point"}
}