<<<<<<< HEAD
{
  "id": 7489469,
  "type": "Feature",
  "properties": {
    "tgn:hierarchy":[
        "tgn:7489469",
        "tgn:7468018",
        "tgn:1000004",
        "tgn:1000141",
        "tgn:7029392"
    ],
    "tgn:id":7489469,
    "tgn:name":"Neitian",
    "tgn:placetype":[
        "aat:300008347"
    ]
},
  "bbox": [],
  "geometry": {"coordinates":[120.17779,23.380965],"type":"Point"}
}
=======
{"geometry":{"type":"Point","coordinates":[120.177790,23.380965]},"type":"Feature","properties":{"hierarchy":["tgn:7489469","tgn:7468018","tgn:1000004","tgn:1000141","tgn:7029392"],"placetype":["aat:300008347"],"id":7489469,"name:xx":"Neitian"}}
>>>>>>> 03f74aca74312dbeaf24d7e61306dd6a786dc3d0
