{
  "id": 7173433,
  "type": "Feature",
  "properties": {
    "tgn:hierarchy":[
        "tgn:7173433",
        "tgn:7000096",
        "tgn:1000003",
        "tgn:7000084",
        "tgn:7029392"
    ],
    "tgn:id":7173433,
    "tgn:name":"Gro\u00df Pankow",
    "tgn:placetype":[
        "aat:300008347"
    ]
},
  "bbox": [],
  "geometry": {"coordinates":[12.05,53.116667],"type":"Point"}
}