{
  "id": 7410021,
  "type": "Feature",
  "properties": {
    "tgn:hierarchy":[
        "tgn:7410021",
        "tgn:7005580",
        "tgn:1000001",
        "tgn:7005560",
        "tgn:7029392"
    ],
    "tgn:id":7410021,
    "tgn:name":"Aguacatales",
    "tgn:placetype":[
        "aat:300008347"
    ]
},
  "bbox": [],
  "geometry": {"coordinates":[-92.175,15.483333],"type":"Point"}
}