{
  "id": 4011030,
  "type": "Feature",
  "properties": {
    "tgn:hierarchy":[
        "tgn:4011030",
        "tgn:7002444",
        "tgn:1000003",
        "tgn:7008082",
        "tgn:7008591",
        "tgn:7029392"
    ],
    "tgn:id":4011030,
    "tgn:name:en":"Tarbet",
    "tgn:placetype":[
        "aat:300008347"
    ]
},
  "bbox": [],
  "geometry": {"coordinates":[-5.633333,56.966667],"type":"Point"}
}