<<<<<<< HEAD
{
  "id": 7021488,
  "type": "Feature",
  "properties": {
    "tgn:hierarchy":[
        "tgn:7021488",
        "tgn:1000001",
        "tgn:7012149",
        "tgn:2002301",
        "tgn:7013961",
        "tgn:7029392"
    ],
    "tgn:id":7021488,
    "tgn:name":"Long Run",
    "tgn:placetype":[
        "aat:300008699"
    ]
},
  "bbox": [],
  "geometry": {"coordinates":[-80.7667,39.6333],"type":"Point"}
}
=======
{"geometry":{"type":"Point","coordinates":[-80.766700,39.633300]},"type":"Feature","properties":{"hierarchy":["tgn:7021488","tgn:1000001","tgn:7012149","tgn:2002301","tgn:7013961","tgn:7029392"],"placetype":["aat:300008699"],"id":7021488,"name:xx":"Long Run"}}
>>>>>>> 03f74aca74312dbeaf24d7e61306dd6a786dc3d0
