{
  "id": 1028600,
  "type": "Feature",
  "properties": {
    "tgn:hierarchy":[
        "tgn:1028600",
        "tgn:7002445",
        "tgn:1000003",
        "tgn:7008175",
        "tgn:7008591",
        "tgn:7029392"
    ],
    "tgn:id":1028600,
    "tgn:name:en":"Bramley",
    "tgn:placetype":[
        "aat:300008347"
    ]
},
  "bbox": [],
  "geometry": {"coordinates":[-0.55,51.183333],"type":"Point"}
}