{
  "id": 2624652,
  "type": "Feature",
  "properties": {
    "tgn:hierarchy":[
        "tgn:2624652",
        "tgn:1000001",
        "tgn:7012149",
        "tgn:1002613",
        "tgn:7007710",
        "tgn:7029392"
    ],
    "tgn:id":2624652,
    "tgn:name":"Rock Run",
    "tgn:placetype":[
        "aat:300008699"
    ]
},
  "bbox": [],
  "geometry": {"coordinates":[-77.2333,41.5333],"type":"Point"}
}