{
  "id": 2581847,
  "type": "Feature",
  "properties": {
    "tgn:hierarchy":[
        "tgn:2581847",
        "tgn:1000001",
        "tgn:7012149",
        "tgn:7007158",
        "tgn:7029392"
    ],
    "tgn:id":2581847,
    "tgn:name":"Pine Arroyo",
    "tgn:placetype":[
        "aat:300008761"
    ]
},
  "bbox": [],
  "geometry": {"coordinates":[-108.7167,37.8667],"type":"Point"}
}