{
  "id": 2293609,
  "type": "Feature",
  "properties": {
    "tgn:hierarchy":[
        "tgn:2293609",
        "tgn:1000001",
        "tgn:2002135",
        "tgn:7012149",
        "tgn:7007828",
        "tgn:7029392"
    ],
    "tgn:id":2293609,
    "tgn:name":"Double Top Mountain",
    "tgn:placetype":[
        "aat:300008798"
    ]
},
  "bbox": [],
  "geometry": {"coordinates":[-72.8667,44.1167],"type":"Point"}
}