{
  "id": 7405944,
  "type": "Feature",
  "properties": {
    "tgn:hierarchy":[
        "tgn:7405944",
        "tgn:7005585",
        "tgn:1000001",
        "tgn:7005560",
        "tgn:7029392"
    ],
    "tgn:id":7405944,
    "tgn:name":"Las \u00c1nimas",
    "tgn:placetype":[
        "aat:300008347"
    ]
},
  "bbox": [],
  "geometry": {"coordinates":[-99.216667,18.35],"type":"Point"}
}