<<<<<<< HEAD
{
  "id": 2156507,
  "type": "Feature",
  "properties": {
    "tgn:hierarchy":[
        "tgn:2156507",
        "tgn:1000001",
        "tgn:7012149",
        "tgn:7007524",
        "tgn:7029392"
    ],
    "tgn:id":2156507,
    "tgn:name":"Beartrap Draw",
    "tgn:placetype":[
        "aat:300008761"
    ]
},
  "bbox": [],
  "geometry": {"coordinates":[-109.8167,45.55],"type":"Point"}
}
=======
{"geometry":{"type":"Point","coordinates":[-109.816700,45.550000]},"type":"Feature","properties":{"hierarchy":["tgn:2156507","tgn:1000001","tgn:7012149","tgn:7007524","tgn:7029392"],"placetype":["aat:300008761"],"id":2156507,"name:xx":"Beartrap Draw"}}
>>>>>>> 03f74aca74312dbeaf24d7e61306dd6a786dc3d0
