{
  "id": 2257917,
  "type": "Feature",
  "properties": {
    "tgn:hierarchy":[
        "tgn:2257917",
        "tgn:1000001",
        "tgn:2001816",
        "tgn:7012149",
        "tgn:7007713",
        "tgn:7029392"
    ],
    "tgn:id":2257917,
    "tgn:name":"Corsaurt Draw",
    "tgn:placetype":[
        "aat:300008761"
    ]
},
  "bbox": [],
  "geometry": {"coordinates":[-102.7333,44.8333],"type":"Point"}
}