{
  "id": 2513883,
  "type": "Feature",
  "properties": {
    "tgn:hierarchy":[
        "tgn:2513883",
        "tgn:1000001",
        "tgn:7012149",
        "tgn:2001225",
        "tgn:7007523",
        "tgn:7029392"
    ],
    "tgn:id":2513883,
    "tgn:name":"Mill Stone Branch",
    "tgn:placetype":[
        "aat:300008699"
    ]
},
  "bbox": [],
  "geometry": {"coordinates":[-91.5833,36.6167],"type":"Point"}
}