{
  "id": 2271078,
  "type": "Feature",
  "properties": {
    "tgn:hierarchy":[
        "tgn:2271078",
        "tgn:1000001",
        "tgn:7012149",
        "tgn:2000719",
        "tgn:7007254",
        "tgn:7029392"
    ],
    "tgn:id":2271078,
    "tgn:name":"Cudahay Mine",
    "tgn:placetype":[
        "aat:300000390"
    ]
},
  "bbox": [],
  "geometry": {"coordinates":[-100.3333,37.3667],"type":"Point"}
}