{
  "id": 2118785,
  "type": "Feature",
  "properties": {
    "tgn:hierarchy":[
        "tgn:2118785",
        "tgn:1000001",
        "tgn:7012149",
        "tgn:2002303",
        "tgn:7013961",
        "tgn:7029392"
    ],
    "tgn:id":2118785,
    "tgn:name":"Kanawha Station",
    "tgn:placetype":[
        "aat:300008347"
    ]
},
  "bbox": [],
  "geometry": {"coordinates":[-81.4333,39.1833],"type":"Point"}
}