{
  "id": 7016240,
  "type": "Feature",
  "properties": {
    "tgn:hierarchy":[
        "tgn:7016240",
        "tgn:1000001",
        "tgn:7012149",
        "tgn:2000210",
        "tgn:7007158",
        "tgn:7029392"
    ],
    "tgn:id":7016240,
    "tgn:name":"Dotsero",
    "tgn:placetype":[
        "aat:300008347",
        "aat:300387210",
        "aat:300387016"
    ]
},
  "bbox": [],
  "geometry": {"coordinates":[-107.05,39.6333],"type":"Point"}
}