{
  "id": 2107540,
  "type": "Feature",
  "properties": {
    "tgn:hierarchy":[
        "tgn:2107540",
        "tgn:1000001",
        "tgn:7012149",
        "tgn:1002456",
        "tgn:7007826",
        "tgn:7029392"
    ],
    "tgn:id":2107540,
    "tgn:name":"Seabrook",
    "tgn:placetype":[
        "aat:300008347"
    ]
},
  "bbox": [],
  "geometry": {"coordinates":[-95.0167,29.55],"type":"Point"}
}