{
  "id": 7433558,
  "type": "Feature",
  "properties": {
    "tgn:hierarchy":[
        "tgn:7433558",
        "tgn:7005581",
        "tgn:1000001",
        "tgn:7005560",
        "tgn:7029392"
    ],
    "tgn:id":7433558,
    "tgn:name":"Yayepuchic",
    "tgn:placetype":[
        "aat:300008347"
    ]
},
  "bbox": [],
  "geometry": {"coordinates":[-107.983333,27.833333],"type":"Point"}
}