{
  "id": 7550297,
  "type": "Feature",
  "properties": {
    "tgn:hierarchy":[
        "tgn:7550297",
        "tgn:1000004",
        "tgn:7000198",
        "tgn:7016722",
        "tgn:7029392"
    ],
    "tgn:id":7550297,
    "tgn:name:en":"Bisheshwarganj",
    "tgn:placetype":[
        "aat:300007783"
    ]
},
  "bbox": [],
  "geometry": {"coordinates":[81.81945,27.36129],"type":"Point"}
}