{
  "id": 2413132,
  "type": "Feature",
  "properties": {
    "tgn:hierarchy":[
        "tgn:2413132",
        "tgn:1000001",
        "tgn:2000925",
        "tgn:7012149",
        "tgn:7007515",
        "tgn:7029392"
    ],
    "tgn:id":2413132,
    "tgn:name":"Inner Heron Island",
    "tgn:placetype":[
        "aat:300008791"
    ]
},
  "bbox": [],
  "geometry": {"coordinates":[-69.5667,43.8167],"type":"Point"}
}