{
  "id": 1118733,
  "type": "Feature",
  "properties": {
    "tgn:hierarchy":[
        "tgn:1118733",
        "tgn:1000001",
        "tgn:1002200",
        "tgn:7012149",
        "tgn:7007240",
        "tgn:7029392"
    ],
    "tgn:id":1118733,
    "tgn:name":"Winder, Lake",
    "tgn:placetype":[
        "aat:300008680"
    ]
},
  "bbox": [],
  "geometry": {"coordinates":[-80.8333,28.25],"type":"Point"}
}