{
  "id": 2184938,
  "type": "Feature",
  "properties": {
    "tgn:hierarchy":[
        "tgn:2184938",
        "tgn:1000001",
        "tgn:7006451",
        "tgn:7012149",
        "tgn:2000101",
        "tgn:7029392"
    ],
    "tgn:id":2184938,
    "tgn:name":"Bogart Wash",
    "tgn:placetype":[
        "aat:300008699"
    ]
},
  "bbox": [],
  "geometry": {"coordinates":[-111.4167,32.9667],"type":"Point"}
}