{
  "id": 7507400,
  "type": "Feature",
  "properties": {
    "tgn:hierarchy":[
        "tgn:7507400",
        "tgn:7016670",
        "tgn:1008380",
        "tgn:1000226",
        "tgn:1000006",
        "tgn:7029392"
    ],
    "tgn:id":7507400,
    "tgn:name:en":"Pukehuruhuru",
    "tgn:placetype":[
        "aat:300008795"
    ]
},
  "bbox": [],
  "geometry": {"coordinates":[177.25,-38.65],"type":"Point"}
}