{
  "id": 2673612,
  "type": "Feature",
  "properties": {
    "tgn:hierarchy":[
        "tgn:2673612",
        "tgn:1000001",
        "tgn:2002366",
        "tgn:7012149",
        "tgn:7007923",
        "tgn:7029392"
    ],
    "tgn:id":2673612,
    "tgn:name":"Snoopy Reservoir",
    "tgn:placetype":[
        "aat:300006191"
    ]
},
  "bbox": [],
  "geometry": {"coordinates":[-108.2167,44.2833],"type":"Point"}
}