{
  "id": 7457518,
  "type": "Feature",
  "properties": {
    "tgn:hierarchy":[
        "tgn:7457518",
        "tgn:7002445",
        "tgn:1000003",
        "tgn:7025691",
        "tgn:7008591",
        "tgn:7029392"
    ],
    "tgn:id":7457518,
    "tgn:name:en":"Mannamead",
    "tgn:placetype":[
        "aat:300008347"
    ]
},
  "bbox": [],
  "geometry": {"coordinates":[-4.133333,50.383333],"type":"Point"}
}