{
  "id": 1009980,
  "type": "Feature",
  "properties": {
    "tgn:hierarchy":[
        "tgn:1009980",
        "tgn:7002445",
        "tgn:7008116",
        "tgn:1000003",
        "tgn:7011368",
        "tgn:7008591",
        "tgn:7029392"
    ],
    "tgn:id":1009980,
    "tgn:name:en":"Eastern Isles",
    "tgn:placetype":[
        "aat:300008791"
    ]
},
  "bbox": [],
  "geometry": {"coordinates":[-6.262572,49.949113],"type":"Point"}
}