{
  "id": 7473627,
  "type": "Feature",
  "properties": {
    "tgn:hierarchy":[
        "tgn:7473627",
        "tgn:1000004",
        "tgn:7489179",
        "tgn:1000141",
        "tgn:7029392"
    ],
    "tgn:id":7473627,
    "tgn:name":"Dingnanxing",
    "tgn:placetype":[
        "aat:300008347"
    ]
},
  "bbox": [],
  "geometry": {"coordinates":[121.778207,24.721904],"type":"Point"}
}