{
  "id": 2101983,
  "type": "Feature",
  "properties": {
    "tgn:hierarchy":[
        "tgn:2101983",
        "tgn:1000001",
        "tgn:7012149",
        "tgn:2001864",
        "tgn:7007825",
        "tgn:7029392"
    ],
    "tgn:id":2101983,
    "tgn:name":"Wales",
    "tgn:placetype":[
        "aat:300008347",
        "aat:300387210"
    ]
},
  "bbox": [],
  "geometry": {"coordinates":[-87.0667,35.2333],"type":"Point"}
}