{
  "id": 7391874,
  "type": "Feature",
  "properties": {
    "tgn:hierarchy":[
        "tgn:7391874",
        "tgn:7005581",
        "tgn:1000001",
        "tgn:7005560",
        "tgn:7029392"
    ],
    "tgn:id":7391874,
    "tgn:name":"Rosas",
    "tgn:placetype":[
        "aat:300008347"
    ]
},
  "bbox": [],
  "geometry": {"coordinates":[-106.383333,28.366667],"type":"Point"}
}