{
  "id": 2069015,
  "type": "Feature",
  "properties": {
    "tgn:hierarchy":[
        "tgn:2069015",
        "tgn:1000001",
        "tgn:7012149",
        "tgn:1002688",
        "tgn:7007568",
        "tgn:7029392"
    ],
    "tgn:id":2069015,
    "tgn:name":"East Stone Arabia",
    "tgn:placetype":[
        "aat:300008347",
        "aat:300387210"
    ]
},
  "bbox": [],
  "geometry": {"coordinates":[-74.5167,42.95],"type":"Point"}
}