{
  "id": 2308345,
  "type": "Feature",
  "properties": {
    "tgn:hierarchy":[
        "tgn:2308345",
        "tgn:7006450",
        "tgn:2000069",
        "tgn:1000001",
        "tgn:7012149",
        "tgn:7029392"
    ],
    "tgn:id":2308345,
    "tgn:name":"East Lime Lake",
    "tgn:placetype":[
        "aat:300008680"
    ]
},
  "bbox": [],
  "geometry": {"coordinates":[-155.25,61.4167],"type":"Point"}
}