{
  "id": 2433481,
  "type": "Feature",
  "properties": {
    "tgn:hierarchy":[
        "tgn:2433481",
        "tgn:1000001",
        "tgn:2001182",
        "tgn:7012149",
        "tgn:7007523",
        "tgn:7029392"
    ],
    "tgn:id":2433481,
    "tgn:name":"Kellogg Lake",
    "tgn:placetype":[
        "aat:300006191"
    ]
},
  "bbox": [],
  "geometry": {"coordinates":[-94.2667,38.7833],"type":"Point"}
}