{
  "id": 2560826,
  "type": "Feature",
  "properties": {
    "tgn:hierarchy":[
        "tgn:2560826",
        "tgn:1000001",
        "tgn:7012149",
        "tgn:2000219",
        "tgn:7007158",
        "tgn:7029392"
    ],
    "tgn:id":2560826,
    "tgn:name":"Orlando Ditch",
    "tgn:placetype":[
        "aat:300006075"
    ]
},
  "bbox": [],
  "geometry": {"coordinates":[-107.8167,37.7667],"type":"Point"}
}