{
  "id": 2753441,
  "type": "Feature",
  "properties": {
    "tgn:hierarchy":[
        "tgn:2753441",
        "tgn:1000001",
        "tgn:7012149",
        "tgn:2001706",
        "tgn:7007708",
        "tgn:7029392"
    ],
    "tgn:id":2753441,
    "tgn:name":"Watering Trough Creek",
    "tgn:placetype":[
        "aat:300008706"
    ]
},
  "bbox": [],
  "geometry": {"coordinates":[-123.3167,43.7667],"type":"Point"}
}