{
  "id": 7035454,
  "type": "Feature",
  "properties": {
    "tgn:hierarchy":[
        "tgn:7035454",
        "tgn:7002994",
        "tgn:1000003",
        "tgn:7002997",
        "tgn:1000080",
        "tgn:7029392"
    ],
    "tgn:id":7035454,
    "tgn:name":"Campagnolo",
    "tgn:placetype":[
        "aat:300008347"
    ]
},
  "bbox": [],
  "geometry": {"coordinates":[12.027778,45.278889],"type":"Point"}
}