{
  "id": 2612986,
  "type": "Feature",
  "properties": {
    "tgn:hierarchy":[
        "tgn:2612986",
        "tgn:1000001",
        "tgn:2001424",
        "tgn:7012149",
        "tgn:7007564",
        "tgn:7029392"
    ],
    "tgn:id":2612986,
    "tgn:name":"Redrock Brook",
    "tgn:placetype":[
        "aat:300008699"
    ]
},
  "bbox": [],
  "geometry": {"coordinates":[-71.55,44.1667],"type":"Point"}
}