{
  "id": 2289972,
  "type": "Feature",
  "properties": {
    "tgn:hierarchy":[
        "tgn:2289972",
        "tgn:1000001",
        "tgn:2002102",
        "tgn:7012149",
        "tgn:7007827",
        "tgn:7029392"
    ],
    "tgn:id":2289972,
    "tgn:name":"Docken Corral Spring",
    "tgn:placetype":[
        "aat:300008697"
    ]
},
  "bbox": [],
  "geometry": {"coordinates":[-113.4833,41.8333],"type":"Point"}
}