{
  "id": 2779056,
  "type": "Feature",
  "properties": {
    "tgn:hierarchy":[
        "tgn:2779056",
        "tgn:1000001",
        "tgn:7012149",
        "tgn:7007568",
        "tgn:7029392"
    ],
    "tgn:id":2779056,
    "tgn:name":"Wolf Creek",
    "tgn:placetype":[
        "aat:300008706"
    ]
},
  "bbox": [],
  "geometry": {"coordinates":[-78.0667,42.6667],"type":"Point"}
}