{
  "id": 7291734,
  "type": "Feature",
  "properties": {
    "tgn:hierarchy":[
        "tgn:7291734",
        "tgn:1001695",
        "tgn:1000049",
        "tgn:1000002",
        "tgn:7029392"
    ],
    "tgn:id":7291734,
    "tgn:name":"El Piral, Estero",
    "tgn:placetype":[
        "aat:300008699"
    ]
},
  "bbox": [],
  "geometry": {"coordinates":[-71.433333,-34.833333],"type":"Point"}
}