{
  "id": 7318857,
  "type": "Feature",
  "properties": {
    "tgn:hierarchy":[
        "tgn:7318857",
        "tgn:1001702",
        "tgn:1000049",
        "tgn:1000002",
        "tgn:7029392"
    ],
    "tgn:id":7318857,
    "tgn:name":"Barranco, Punta",
    "tgn:placetype":[
        "aat:300386846"
    ]
},
  "bbox": [],
  "geometry": {"coordinates":[-72.85,-52.616667],"type":"Point"}
}