<<<<<<< HEAD
{
  "id": 7376206,
  "type": "Feature",
  "properties": {
    "tgn:hierarchy":[
        "tgn:7376206",
        "tgn:7005586",
        "tgn:1000001",
        "tgn:7005560",
        "tgn:7029392"
    ],
    "tgn:id":7376206,
    "tgn:name":"Lobo",
    "tgn:placetype":[
        "aat:300008347"
    ]
},
  "bbox": [],
  "geometry": {"coordinates":[-102.816667,19.783333],"type":"Point"}
}
=======
{"geometry":{"type":"Point","coordinates":[-102.816667,19.783333]},"type":"Feature","properties":{"hierarchy":["tgn:7376206","tgn:7005586","tgn:1000001","tgn:7005560","tgn:7029392"],"placetype":["aat:300008347"],"id":7376206,"name:xx":"Lobo"}}
>>>>>>> 03f74aca74312dbeaf24d7e61306dd6a786dc3d0
