{
  "id": 7254474,
  "type": "Feature",
  "properties": {
    "tgn:hierarchy":[
        "tgn:7254474",
        "tgn:7007877",
        "tgn:1000003",
        "tgn:1000063",
        "tgn:4012014",
        "tgn:7029392"
    ],
    "tgn:id":7254474,
    "tgn:name":"Thim\u00e9on",
    "tgn:placetype":[
        "aat:300008347"
    ]
},
  "bbox": [],
  "geometry": {"coordinates":[4.416667,50.483333],"type":"Point"}
}