{
  "id": 1084510,
  "type": "Feature",
  "properties": {
    "tgn:hierarchy":[
        "tgn:1084510",
        "tgn:1000004",
        "tgn:1001218",
        "tgn:1000135",
        "tgn:7029392"
    ],
    "tgn:id":1084510,
    "tgn:name":"Padada",
    "tgn:placetype":[
        "aat:300008347"
    ]
},
  "bbox": [],
  "geometry": {"coordinates":[125.4167,6.6333],"type":"Point"}
}