{
  "id": 7303350,
  "type": "Feature",
  "properties": {
    "tgn:hierarchy":[
        "tgn:7303350",
        "tgn:7002808",
        "tgn:7030216",
        "tgn:1000003",
        "tgn:1000095",
        "tgn:7029392"
    ],
    "tgn:id":7303350,
    "tgn:name":"Ol\u00e9rdola",
    "tgn:placetype":[
        "aat:300387173"
    ]
},
  "bbox": [],
  "geometry": {"coordinates":[1.716667,41.316667],"type":"Point"}
}