{
  "id": 7216860,
  "type": "Feature",
  "properties": {
    "tgn:hierarchy":[
        "tgn:7216860",
        "tgn:1000003",
        "tgn:7000094",
        "tgn:7000084",
        "tgn:7029392"
    ],
    "tgn:id":7216860,
    "tgn:name":"Aal Beck",
    "tgn:placetype":[
        "aat:300008699"
    ]
},
  "bbox": [],
  "geometry": {"coordinates":[13.116667,53.533333],"type":"Point"}
}