{
  "id": 7202265,
  "type": "Feature",
  "properties": {
    "tgn:hierarchy":[
        "tgn:7202265",
        "tgn:7003692",
        "tgn:1000003",
        "tgn:7000084",
        "tgn:7029392"
    ],
    "tgn:id":7202265,
    "tgn:name":"Breitenerlen",
    "tgn:placetype":[
        "aat:300000206"
    ]
},
  "bbox": [],
  "geometry": {"coordinates":[9.133333,47.866667],"type":"Point"}
}