{
  "id": 2566126,
  "type": "Feature",
  "properties": {
    "tgn:hierarchy":[
        "tgn:2566126",
        "tgn:1000001",
        "tgn:7012149",
        "tgn:2001867",
        "tgn:7007825",
        "tgn:7029392"
    ],
    "tgn:id":2566126,
    "tgn:name":"Palmer Mine",
    "tgn:placetype":[
        "aat:300000390"
    ]
},
  "bbox": [],
  "geometry": {"coordinates":[-85.5667,35.3333],"type":"Point"}
}