{
  "id": 7525004,
  "type": "Feature",
  "properties": {
    "tgn:hierarchy":[
        "tgn:7525004",
        "tgn:7001242",
        "tgn:7016833",
        "tgn:1001113",
        "tgn:7029392"
    ],
    "tgn:id":7525004,
    "tgn:name:en":"Az Zankal\u016bn",
    "tgn:placetype":[
        "aat:300007783"
    ]
},
  "bbox": [],
  "geometry": {"coordinates":[31.45,30.55],"type":"Point"}
}