{
  "id": 2362657,
  "type": "Feature",
  "properties": {
    "tgn:hierarchy":[
        "tgn:2362657",
        "tgn:1000001",
        "tgn:7006451",
        "tgn:2000092",
        "tgn:7012149",
        "tgn:7029392"
    ],
    "tgn:id":2362657,
    "tgn:name":"Great Dane Tank",
    "tgn:placetype":[
        "aat:300006191"
    ]
},
  "bbox": [],
  "geometry": {"coordinates":[-111.9333,35.2333],"type":"Point"}
}