{
  "id": 1119403,
  "type": "Feature",
  "properties": {
    "tgn:hierarchy":[
        "tgn:1119403",
        "tgn:1000001",
        "tgn:7012149",
        "tgn:7007157",
        "tgn:1002857",
        "tgn:7029392"
    ],
    "tgn:id":1119403,
    "tgn:name":"Arrowhead, Lake",
    "tgn:placetype":[
        "aat:300006191"
    ]
},
  "bbox": [],
  "geometry": {"coordinates":[-117.1833,34.25],"type":"Point"}
}