{
  "id": 2443868,
  "type": "Feature",
  "properties": {
    "tgn:hierarchy":[
        "tgn:2443868",
        "tgn:1000001",
        "tgn:2001269",
        "tgn:7012149",
        "tgn:7007524",
        "tgn:7029392"
    ],
    "tgn:id":2443868,
    "tgn:name":"La Pierre Coulee",
    "tgn:placetype":[
        "aat:300008761"
    ]
},
  "bbox": [],
  "geometry": {"coordinates":[-105.5833,48.85],"type":"Point"}
}