{
  "id": 7319266,
  "type": "Feature",
  "properties": {
    "tgn:hierarchy":[
        "tgn:7319266",
        "tgn:7002464",
        "tgn:1000049",
        "tgn:1000002",
        "tgn:7029392"
    ],
    "tgn:id":7319266,
    "tgn:name":"Ancovilque",
    "tgn:placetype":[
        "aat:300008347"
    ]
},
  "bbox": [],
  "geometry": {"coordinates":[-69.216667,-18.016667],"type":"Point"}
}