{
  "id": 2636087,
  "type": "Feature",
  "properties": {
    "tgn:hierarchy":[
        "tgn:2636087",
        "tgn:1000001",
        "tgn:1002473",
        "tgn:7012149",
        "tgn:7007240",
        "tgn:7029392"
    ],
    "tgn:id":2636087,
    "tgn:name":"Saddle Key",
    "tgn:placetype":[
        "aat:300008791"
    ]
},
  "bbox": [],
  "geometry": {"coordinates":[-82.6667,28.6333],"type":"Point"}
}