{
  "id": 2313153,
  "type": "Feature",
  "properties": {
    "tgn:hierarchy":[
        "tgn:2313153",
        "tgn:1000001",
        "tgn:7012149",
        "tgn:1002942",
        "tgn:7007920",
        "tgn:7029392"
    ],
    "tgn:id":2313153,
    "tgn:name":"Elbow Lake",
    "tgn:placetype":[
        "aat:300008680"
    ]
},
  "bbox": [],
  "geometry": {"coordinates":[-122.45,46.8333],"type":"Point"}
}