{
  "id": 7464896,
  "type": "Feature",
  "properties": {
    "tgn:hierarchy":[
        "tgn:7464896",
        "tgn:7002448",
        "tgn:1000003",
        "tgn:7019206",
        "tgn:7008591",
        "tgn:7029392"
    ],
    "tgn:id":7464896,
    "tgn:name:en":"Beltrim Castle",
    "tgn:placetype":[
        "aat:300387502"
    ]
},
  "bbox": [],
  "geometry": {"coordinates":[-7.233333,54.716667],"type":"Point"}
}