{
  "id": 2403437,
  "type": "Feature",
  "properties": {
    "tgn:hierarchy":[
        "tgn:2403437",
        "tgn:1000001",
        "tgn:2001796",
        "tgn:7012149",
        "tgn:7007713",
        "tgn:7029392"
    ],
    "tgn:id":2403437,
    "tgn:name":"Houston Springs",
    "tgn:placetype":[
        "aat:300008697"
    ]
},
  "bbox": [],
  "geometry": {"coordinates":[-98.9167,43.0667],"type":"Point"}
}