{
  "id": 7411940,
  "type": "Feature",
  "properties": {
    "tgn:hierarchy":[
        "tgn:7411940",
        "tgn:7005580",
        "tgn:1000001",
        "tgn:7005560",
        "tgn:7029392"
    ],
    "tgn:id":7411940,
    "tgn:name":"El Cambio",
    "tgn:placetype":[
        "aat:300008347"
    ]
},
  "bbox": [],
  "geometry": {"coordinates":[-91.866667,17.733333],"type":"Point"}
}