{
  "id": 7385183,
  "type": "Feature",
  "properties": {
    "tgn:hierarchy":[
        "tgn:7385183",
        "tgn:7005583",
        "tgn:1000001",
        "tgn:7005560",
        "tgn:7029392"
    ],
    "tgn:id":7385183,
    "tgn:name":"Nicol\u00e1s",
    "tgn:placetype":[
        "aat:300008347"
    ]
},
  "bbox": [],
  "geometry": {"coordinates":[-104.833333,23.983333],"type":"Point"}
}