{
  "id": 7434274,
  "type": "Feature",
  "properties": {
    "tgn:hierarchy":[
        "tgn:7434274",
        "tgn:7005585",
        "tgn:1000001",
        "tgn:7005560",
        "tgn:7029392"
    ],
    "tgn:id":7434274,
    "tgn:name":"Xochihuehuetl\u00e1n",
    "tgn:placetype":[
        "aat:300008347"
    ]
},
  "bbox": [],
  "geometry": {"coordinates":[-98.433333,17.916667],"type":"Point"}
}