{
  "id": 2053762,
  "type": "Feature",
  "properties": {
    "tgn:hierarchy":[
        "tgn:2053762",
        "tgn:1002166",
        "tgn:1000001",
        "tgn:7012149",
        "tgn:7007520",
        "tgn:7029392"
    ],
    "tgn:id":2053762,
    "tgn:name":"Woodbury",
    "tgn:placetype":[
        "aat:300008347"
    ]
},
  "bbox": [],
  "geometry": {"coordinates":[-85.0667,42.75],"type":"Point"}
}