{
  "id": 7279215,
  "type": "Feature",
  "properties": {
    "tgn:hierarchy":[
        "tgn:7279215",
        "tgn:1001623",
        "tgn:1000049",
        "tgn:1000002",
        "tgn:7029392"
    ],
    "tgn:id":7279215,
    "tgn:name":"Romero",
    "tgn:placetype":[
        "aat:300004792"
    ]
},
  "bbox": [],
  "geometry": {"coordinates":[-72.866667,-47.35],"type":"Point"}
}