{
  "id": 2427688,
  "type": "Feature",
  "properties": {
    "tgn:hierarchy":[
        "tgn:2427688",
        "tgn:1000001",
        "tgn:7012149",
        "tgn:2001713",
        "tgn:7007708",
        "tgn:7029392"
    ],
    "tgn:id":2427688,
    "tgn:name":"Josephine Mountain",
    "tgn:placetype":[
        "aat:300008798"
    ]
},
  "bbox": [],
  "geometry": {"coordinates":[-123.7667,42.15],"type":"Point"}
}