{
  "id": 2629610,
  "type": "Feature",
  "properties": {
    "tgn:hierarchy":[
        "tgn:2629610",
        "tgn:1000001",
        "tgn:7012149",
        "tgn:2002066",
        "tgn:7007826",
        "tgn:7029392"
    ],
    "tgn:id":2629610,
    "tgn:name":"Rosin Ridge",
    "tgn:placetype":[
        "aat:300266640"
    ]
},
  "bbox": [],
  "geometry": {"coordinates":[-93.9167,31.3667],"type":"Point"}
}