{
  "id": 7576395,
  "type": "Feature",
  "properties": {
    "tgn:hierarchy":[
        "tgn:7576395",
        "tgn:1000004",
        "tgn:7000198",
        "tgn:7000799",
        "tgn:7029392"
    ],
    "tgn:id":7576395,
    "tgn:name:en":"Kot",
    "tgn:placetype":[
        "aat:300008347"
    ]
},
  "bbox": [],
  "geometry": {"coordinates":[74.695007,32.87393],"type":"Point"}
}