{
  "id": 1050654,
  "type": "Feature",
  "properties": {
    "tgn:hierarchy":[
        "tgn:1050654",
        "tgn:5000432",
        "tgn:7002444",
        "tgn:1000003",
        "tgn:7008591",
        "tgn:7029392"
    ],
    "tgn:id":1050654,
    "tgn:name:en":"Ellon",
    "tgn:placetype":[
        "aat:300008347"
    ]
},
  "bbox": [],
  "geometry": {"coordinates":[-2.083333,57.35],"type":"Point"}
}