{
  "id": 7203194,
  "type": "Feature",
  "properties": {
    "tgn:hierarchy":[
        "tgn:7203194",
        "tgn:1000003",
        "tgn:7003688",
        "tgn:7000084",
        "tgn:7029392"
    ],
    "tgn:id":7203194,
    "tgn:name":"Breedenmoor",
    "tgn:placetype":[
        "aat:300386886"
    ]
},
  "bbox": [],
  "geometry": {"coordinates":[9.95,53.733333],"type":"Point"}
}