<<<<<<< HEAD
{
  "id": 7357644,
  "type": "Feature",
  "properties": {
    "tgn:hierarchy":[
        "tgn:7357644",
        "tgn:1000001",
        "tgn:1001960",
        "tgn:7005560",
        "tgn:7029392"
    ],
    "tgn:id":7357644,
    "tgn:name":"Rancho Cumaro",
    "tgn:placetype":[
        "aat:300000241"
    ]
},
  "bbox": [],
  "geometry": {"coordinates":[-112.183333,31.4],"type":"Point"}
}
=======
{"geometry":{"type":"Point","coordinates":[-112.183333,31.400000]},"type":"Feature","properties":{"hierarchy":["tgn:7357644","tgn:1000001","tgn:1001960","tgn:7005560","tgn:7029392"],"placetype":["aat:300000241"],"id":7357644,"name:xx":"Rancho Cumaro"}}
>>>>>>> 03f74aca74312dbeaf24d7e61306dd6a786dc3d0
