{
  "id": 2259585,
  "type": "Feature",
  "properties": {
    "tgn:hierarchy":[
        "tgn:2259585",
        "tgn:1000001",
        "tgn:7012149",
        "tgn:7029392"
    ],
    "tgn:id":2259585,
    "tgn:name":"Cotts Creek",
    "tgn:placetype":[
        "aat:300008706"
    ]
},
  "bbox": [],
  "geometry": {"coordinates":[-87.3167,35.05],"type":"Point"}
}