<<<<<<< HEAD
{
  "id": 2259585,
  "type": "Feature",
  "properties": {
    "tgn:hierarchy":[
        "tgn:2259585",
        "tgn:1000001",
        "tgn:7012149",
        "tgn:7029392"
    ],
    "tgn:id":2259585,
    "tgn:name":"Cotts Creek",
    "tgn:placetype":[
        "aat:300008706"
    ]
},
  "bbox": [],
  "geometry": {"coordinates":[-87.3167,35.05],"type":"Point"}
}
=======
{"geometry":{"type":"Point","coordinates":[-87.316700,35.050000]},"type":"Feature","properties":{"hierarchy":["tgn:2259585","tgn:1000001","tgn:7012149","tgn:7029392"],"placetype":["aat:300008706"],"id":2259585,"name:xx":"Cotts Creek"}}
>>>>>>> 03f74aca74312dbeaf24d7e61306dd6a786dc3d0
