{
  "id": 1105575,
  "type": "Feature",
  "properties": {
    "tgn:hierarchy":[
        "tgn:1105575",
        "tgn:7005694",
        "tgn:7005685",
        "tgn:1000001",
        "tgn:7029392"
    ],
    "tgn:id":1105575,
    "tgn:name":"May, Mount",
    "tgn:placetype":[
        "aat:300008795"
    ]
},
  "bbox": [],
  "geometry": {"coordinates":[-119.9667,54.0333],"type":"Point"}
}