{
  "id": 2443635,
  "type": "Feature",
  "properties": {
    "tgn:hierarchy":[
        "tgn:2443635",
        "tgn:1000001",
        "tgn:7012149",
        "tgn:7007158",
        "tgn:2000246",
        "tgn:7029392"
    ],
    "tgn:id":2443635,
    "tgn:name":"La Garita Creek",
    "tgn:placetype":[
        "aat:300008706"
    ]
},
  "bbox": [],
  "geometry": {"coordinates":[-106.5667,37.9167],"type":"Point"}
}