<<<<<<< HEAD
{
  "id": 7022941,
  "type": "Feature",
  "properties": {
    "tgn:hierarchy":[
        "tgn:7022941",
        "tgn:1000001",
        "tgn:7012149",
        "tgn:7029392"
    ],
    "tgn:id":7022941,
    "tgn:name":"Farringtons Pond",
    "tgn:placetype":[
        "aat:300008680"
    ]
},
  "bbox": [],
  "geometry": {"coordinates":[-73.5333,41.4],"type":"Point"}
}
=======
{"geometry":{"type":"Point","coordinates":[-73.533300,41.400000]},"type":"Feature","properties":{"hierarchy":["tgn:7022941","tgn:1000001","tgn:7012149","tgn:7029392"],"placetype":["aat:300008680"],"id":7022941,"name:xx":"Farringtons Pond"}}
>>>>>>> 03f74aca74312dbeaf24d7e61306dd6a786dc3d0
