<<<<<<< HEAD
{
  "id": 2708610,
  "type": "Feature",
  "properties": {
    "tgn:hierarchy":[
        "tgn:2708610",
        "tgn:1000001",
        "tgn:7012149",
        "tgn:7015770",
        "tgn:7007919",
        "tgn:7029392"
    ],
    "tgn:id":2708610,
    "tgn:name":"Sycolin Creek",
    "tgn:placetype":[
        "aat:300008706"
    ]
},
  "bbox": [],
  "geometry": {"coordinates":[-77.65,39.0833],"type":"Point"}
}
=======
{"geometry":{"type":"Point","coordinates":[-77.650000,39.083300]},"type":"Feature","properties":{"hierarchy":["tgn:2708610","tgn:1000001","tgn:7012149","tgn:7015770","tgn:7007919","tgn:7029392"],"placetype":["aat:300008706"],"id":2708610,"name:xx":"Sycolin Creek"}}
>>>>>>> 03f74aca74312dbeaf24d7e61306dd6a786dc3d0
