{
  "id": 7444664,
  "type": "Feature",
  "properties": {
    "tgn:hierarchy":[
        "tgn:7444664",
        "tgn:7002444",
        "tgn:1000003",
        "tgn:7008082",
        "tgn:7008591",
        "tgn:7029392"
    ],
    "tgn:id":7444664,
    "tgn:name:en":"Turret, River",
    "tgn:placetype":[
        "aat:300008699"
    ]
},
  "bbox": [],
  "geometry": {"coordinates":[-4.733333,56.983333],"type":"Point"}
}