{
  "id": 2522838,
  "type": "Feature",
  "properties": {
    "tgn:hierarchy":[
        "tgn:2522838",
        "tgn:1000001",
        "tgn:7012149",
        "tgn:1002640",
        "tgn:7007252",
        "tgn:7029392"
    ],
    "tgn:id":2522838,
    "tgn:name":"Moore Ditch",
    "tgn:placetype":[
        "aat:300006075"
    ]
},
  "bbox": [],
  "geometry": {"coordinates":[-86.0667,41.2333],"type":"Point"}
}