{
  "id": 2628753,
  "type": "Feature",
  "properties": {
    "tgn:hierarchy":[
        "tgn:2628753",
        "tgn:1000001",
        "tgn:2000870",
        "tgn:7012149",
        "tgn:7007256",
        "tgn:7029392"
    ],
    "tgn:id":2628753,
    "tgn:name":"Roppolo Villa",
    "tgn:placetype":[
        "aat:300008347"
    ]
},
  "bbox": [],
  "geometry": {"coordinates":[-91.15,30.4833],"type":"Point"}
}