<<<<<<< HEAD
{
  "id": 7027711,
  "type": "Feature",
  "properties": {
    "tgn:hierarchy":[
        "tgn:7027711",
        "tgn:7002445",
        "tgn:1000003",
        "tgn:7008155",
        "tgn:7008591",
        "tgn:7029392"
    ],
    "tgn:id":7027711,
    "tgn:name:en":"Worthington",
    "tgn:placetype":[
        "aat:300008347",
        "aat:300008372"
    ]
},
  "bbox": [],
  "geometry": {"coordinates":[-1.4,52.766667],"type":"Point"}
}
=======
{"geometry":{"type":"Point","coordinates":[-1.400000,52.766667]},"type":"Feature","properties":{"hierarchy":["tgn:7027711","tgn:7002445","tgn:1000003","tgn:7008155","tgn:7008591","tgn:7029392"],"placetype":["aat:300008347","aat:300008372"],"name:en":"Worthington","id":7027711}}
>>>>>>> 03f74aca74312dbeaf24d7e61306dd6a786dc3d0
