{
  "id": 7252641,
  "type": "Feature",
  "properties": {
    "tgn:hierarchy":[
        "tgn:7252641",
        "tgn:7003460",
        "tgn:1000003",
        "tgn:1000063",
        "tgn:4012014",
        "tgn:7029392"
    ],
    "tgn:id":7252641,
    "tgn:name":"Pixhos",
    "tgn:placetype":[
        "aat:300000206"
    ]
},
  "bbox": [],
  "geometry": {"coordinates":[5.683333,50.65],"type":"Point"}
}