{
  "id": 7552068,
  "type": "Feature",
  "properties": {
    "tgn:hierarchy":[
        "tgn:7552068",
        "tgn:1000004",
        "tgn:7000198",
        "tgn:7016722",
        "tgn:7029392"
    ],
    "tgn:id":7552068,
    "tgn:name:en":"Deogaon",
    "tgn:placetype":[
        "aat:300008347"
    ]
},
  "bbox": [],
  "geometry": {"coordinates":[82.986147,25.74737],"type":"Point"}
}