{
  "id": 2584084,
  "type": "Feature",
  "properties": {
    "tgn:hierarchy":[
        "tgn:2584084",
        "tgn:1000001",
        "tgn:7012149",
        "tgn:7019676",
        "tgn:7007566",
        "tgn:7029392"
    ],
    "tgn:id":2584084,
    "tgn:name":"Pinehaven",
    "tgn:placetype":[
        "aat:300008347"
    ]
},
  "bbox": [],
  "geometry": {"coordinates":[-108.6667,35.3167],"type":"Point"}
}