{
  "id": 7505530,
  "type": "Feature",
  "properties": {
    "tgn:hierarchy":[
        "tgn:7505530",
        "tgn:1009227",
        "tgn:1000226",
        "tgn:7018437",
        "tgn:1000006",
        "tgn:7029392"
    ],
    "tgn:id":7505530,
    "tgn:name:en":"Wharekuri Creek",
    "tgn:placetype":[
        "aat:300008699"
    ]
},
  "bbox": [],
  "geometry": {"coordinates":[170.366667,-44.666667],"type":"Point"}
}