<<<<<<< HEAD
{
  "id": 2335379,
  "type": "Feature",
  "properties": {
    "tgn:hierarchy":[
        "tgn:2335379",
        "tgn:1000001",
        "tgn:2000197",
        "tgn:7012149",
        "tgn:7007158",
        "tgn:7029392"
    ],
    "tgn:id":2335379,
    "tgn:name":"Fort Lyon",
    "tgn:placetype":[
        "aat:300008347"
    ]
},
  "bbox": [],
  "geometry": {"coordinates":[-103.15,39.1],"type":"Point"}
}
=======
{"geometry":{"type":"Point","coordinates":[-103.150000,39.100000]},"type":"Feature","properties":{"hierarchy":["tgn:2335379","tgn:1000001","tgn:2000197","tgn:7012149","tgn:7007158","tgn:7029392"],"placetype":["aat:300008347"],"id":2335379,"name:xx":"Fort Lyon"}}
>>>>>>> 03f74aca74312dbeaf24d7e61306dd6a786dc3d0
