{
  "id": 2509914,
  "type": "Feature",
  "properties": {
    "tgn:hierarchy":[
        "tgn:2509914",
        "tgn:1000001",
        "tgn:7012149",
        "tgn:2001293",
        "tgn:7007524",
        "tgn:7029392"
    ],
    "tgn:id":2509914,
    "tgn:name":"Middle Mountain",
    "tgn:placetype":[
        "aat:300008798"
    ]
},
  "bbox": [],
  "geometry": {"coordinates":[-109.85,45.0667],"type":"Point"}
}