{
  "id": 2485336,
  "type": "Feature",
  "properties": {
    "tgn:hierarchy":[
        "tgn:2485336",
        "tgn:1000001",
        "tgn:7012149",
        "tgn:2001868",
        "tgn:7007825",
        "tgn:7029392"
    ],
    "tgn:id":2485336,
    "tgn:name":"Lawrence Spring",
    "tgn:placetype":[
        "aat:300008697"
    ]
},
  "bbox": [],
  "geometry": {"coordinates":[-83.4167,36.1833],"type":"Point"}
}