{
  "id": 2109671,
  "type": "Feature",
  "properties": {
    "tgn:hierarchy":[
        "tgn:2109671",
        "tgn:1000001",
        "tgn:1002415",
        "tgn:7012149",
        "tgn:7007828",
        "tgn:7029392"
    ],
    "tgn:id":2109671,
    "tgn:name":"Grand Isle",
    "tgn:placetype":[
        "aat:300008347"
    ]
},
  "bbox": [],
  "geometry": {"coordinates":[-73.2833,44.7167],"type":"Point"}
}