<<<<<<< HEAD
{
  "id": 7359724,
  "type": "Feature",
  "properties": {
    "tgn:hierarchy":[
        "tgn:7359724",
        "tgn:1000001",
        "tgn:7005592",
        "tgn:7005560",
        "tgn:7029392"
    ],
    "tgn:id":7359724,
    "tgn:name":"Coapan",
    "tgn:placetype":[
        "aat:300008347"
    ]
},
  "bbox": [],
  "geometry": {"coordinates":[-97.4,18.433333],"type":"Point"}
}
=======
{"geometry":{"type":"Point","coordinates":[-97.400000,18.433333]},"type":"Feature","properties":{"hierarchy":["tgn:7359724","tgn:1000001","tgn:7005592","tgn:7005560","tgn:7029392"],"placetype":["aat:300008347"],"id":7359724,"name:xx":"Coapan"}}
>>>>>>> 03f74aca74312dbeaf24d7e61306dd6a786dc3d0
