{
  "id": 7040199,
  "type": "Feature",
  "properties": {
    "tgn:hierarchy":[
        "tgn:7040199",
        "tgn:7003170",
        "tgn:1000003",
        "tgn:7003125",
        "tgn:1000080",
        "tgn:7029392"
    ],
    "tgn:id":7040199,
    "tgn:name":"Abbazia di Sassovivo",
    "tgn:placetype":[
        "aat:300000641"
    ]
},
  "bbox": [],
  "geometry": {"coordinates":[12.766667,42.95],"type":"Point"}
}