{
  "id": 7136829,
  "type": "Feature",
  "properties": {
    "tgn:hierarchy":[
        "tgn:7136829",
        "tgn:7003692",
        "tgn:1000003",
        "tgn:7000084",
        "tgn:7029392"
    ],
    "tgn:id":7136829,
    "tgn:name":"Lerchenfeld",
    "tgn:placetype":[
        "aat:300386887"
    ]
},
  "bbox": [],
  "geometry": {"coordinates":[9.95,48.45],"type":"Point"}
}