{
  "id": 7458146,
  "type": "Feature",
  "properties": {
    "tgn:hierarchy":[
        "tgn:7458146",
        "tgn:7019140",
        "tgn:7002444",
        "tgn:1000003",
        "tgn:7008591",
        "tgn:7029392"
    ],
    "tgn:id":7458146,
    "tgn:name:en":"Monifieth Sands",
    "tgn:placetype":[
        "aat:300386970"
    ]
},
  "bbox": [],
  "geometry": {"coordinates":[-2.833333,56.466667],"type":"Point"}
}