{
  "id": 1077791,
  "type": "Feature",
  "properties": {
    "tgn:hierarchy":[
        "tgn:1077791",
        "tgn:1009295",
        "tgn:1000004",
        "tgn:1001466",
        "tgn:1000116",
        "tgn:7029392"
    ],
    "tgn:id":1077791,
    "tgn:name":"Kambu",
    "tgn:placetype":[
        "aat:300008347"
    ]
},
  "bbox": [],
  "geometry": {"coordinates":[118.3333,-8.3833],"type":"Point"}
}