{
  "id": 2148595,
  "type": "Feature",
  "properties": {
    "tgn:hierarchy":[
        "tgn:2148595",
        "tgn:1000001",
        "tgn:7012149",
        "tgn:7007159",
        "tgn:7029392"
    ],
    "tgn:id":2148595,
    "tgn:name":"Barnes Hill",
    "tgn:placetype":[
        "aat:300008798"
    ]
},
  "bbox": [],
  "geometry": {"coordinates":[-73.4667,41.5833],"type":"Point"}
}