{
  "id": 7545851,
  "type": "Feature",
  "properties": {
    "tgn:hierarchy":[
        "tgn:7545851",
        "tgn:1000004",
        "tgn:7000198",
        "tgn:7031783",
        "tgn:7029392"
    ],
    "tgn:id":7545851,
    "tgn:name:en":"Bagru",
    "tgn:placetype":[
        "aat:300008777"
    ]
},
  "bbox": [],
  "geometry": {"coordinates":[84.597249,23.488789],"type":"Point"}
}