<<<<<<< HEAD
{
  "id": 7352471,
  "type": "Feature",
  "properties": {
    "tgn:hierarchy":[
        "tgn:7352471",
        "tgn:7005586",
        "tgn:1000001",
        "tgn:7005560",
        "tgn:7029392"
    ],
    "tgn:id":7352471,
    "tgn:name":"Atarjea",
    "tgn:placetype":[
        "aat:300008347"
    ]
},
  "bbox": [],
  "geometry": {"coordinates":[-102.133333,20.583333],"type":"Point"}
}
=======
{"geometry":{"type":"Point","coordinates":[-102.133333,20.583333]},"type":"Feature","properties":{"hierarchy":["tgn:7352471","tgn:7005586","tgn:1000001","tgn:7005560","tgn:7029392"],"placetype":["aat:300008347"],"id":7352471,"name:xx":"Atarjea"}}
>>>>>>> 03f74aca74312dbeaf24d7e61306dd6a786dc3d0
