{
  "id": 2607568,
  "type": "Feature",
  "properties": {
    "tgn:hierarchy":[
        "tgn:2607568",
        "tgn:1000001",
        "tgn:7012149",
        "tgn:2001036",
        "tgn:7007521",
        "tgn:7029392"
    ],
    "tgn:id":2607568,
    "tgn:name":"Rap Lake",
    "tgn:placetype":[
        "aat:300006191"
    ]
},
  "bbox": [],
  "geometry": {"coordinates":[-91.25,47.8167],"type":"Point"}
}