<<<<<<< HEAD
{
  "id": 7054877,
  "type": "Feature",
  "properties": {
    "tgn:hierarchy":[
        "tgn:7054877",
        "tgn:1003432",
        "tgn:1000003",
        "tgn:7003240",
        "tgn:1000080",
        "tgn:7029392"
    ],
    "tgn:id":7054877,
    "tgn:name":"Molino di Monte Urano",
    "tgn:placetype":[
        "aat:300008347"
    ]
},
  "bbox": [],
  "geometry": {"coordinates":[13.683333,43.183333],"type":"Point"}
}
=======
{"geometry":{"type":"Point","coordinates":[13.683333,43.183333]},"type":"Feature","properties":{"hierarchy":["tgn:7054877","tgn:1003432","tgn:1000003","tgn:7003240","tgn:1000080","tgn:7029392"],"placetype":["aat:300008347"],"id":7054877,"name:xx":"Molino di Monte Urano"}}
>>>>>>> 03f74aca74312dbeaf24d7e61306dd6a786dc3d0
