{
  "id": 2612285,
  "type": "Feature",
  "properties": {
    "tgn:hierarchy":[
        "tgn:2612285",
        "tgn:1000001",
        "tgn:2002368",
        "tgn:7012149",
        "tgn:7007923",
        "tgn:7029392"
    ],
    "tgn:id":2612285,
    "tgn:name":"Red Spring Draw",
    "tgn:placetype":[
        "aat:300008761"
    ]
},
  "bbox": [],
  "geometry": {"coordinates":[-106.85,42.1333],"type":"Point"}
}