{
  "id": 7565329,
  "type": "Feature",
  "properties": {
    "tgn:hierarchy":[
        "tgn:7565329",
        "tgn:1000004",
        "tgn:7000198",
        "tgn:7016722",
        "tgn:7029392"
    ],
    "tgn:id":7565329,
    "tgn:name:en":"Goh\u0101n\u0101n",
    "tgn:placetype":[
        "aat:300008347"
    ]
},
  "bbox": [],
  "geometry": {"coordinates":[79.466402,26.466403],"type":"Point"}
}