{
  "id": 7281896,
  "type": "Feature",
  "properties": {
    "tgn:hierarchy":[
        "tgn:7281896",
        "tgn:1001702",
        "tgn:1000049",
        "tgn:1000002",
        "tgn:7029392"
    ],
    "tgn:id":7281896,
    "tgn:name":"Spur, Punta",
    "tgn:placetype":[
        "aat:300386846"
    ]
},
  "bbox": [],
  "geometry": {"coordinates":[-74.95,-50.433333],"type":"Point"}
}