{
  "id": 7226989,
  "type": "Feature",
  "properties": {
    "tgn:hierarchy":[
        "tgn:7226989",
        "tgn:7011170",
        "tgn:7002715",
        "tgn:1000003",
        "tgn:1000074",
        "tgn:7029392"
    ],
    "tgn:id":7226989,
    "tgn:name":"Par\u00e1meron",
    "tgn:placetype":[
        "aat:300008347"
    ]
},
  "bbox": [],
  "geometry": {"coordinates":[24.45,41.35],"type":"Point"}
}