<<<<<<< HEAD
{
  "id": 2764039,
  "type": "Feature",
  "properties": {
    "tgn:hierarchy":[
        "tgn:2764039",
        "tgn:1000001",
        "tgn:7012149",
        "tgn:1002751",
        "tgn:7007568",
        "tgn:7029392"
    ],
    "tgn:id":2764039,
    "tgn:name":"Wheeler Creek",
    "tgn:placetype":[
        "aat:300008706"
    ]
},
  "bbox": [],
  "geometry": {"coordinates":[-74.3833,41.2667],"type":"Point"}
}
=======
{"geometry":{"type":"Point","coordinates":[-74.383300,41.266700]},"type":"Feature","properties":{"hierarchy":["tgn:2764039","tgn:1000001","tgn:7012149","tgn:1002751","tgn:7007568","tgn:7029392"],"placetype":["aat:300008706"],"id":2764039,"name:xx":"Wheeler Creek"}}
>>>>>>> 03f74aca74312dbeaf24d7e61306dd6a786dc3d0
