{
  "id": 2108724,
  "type": "Feature",
  "properties": {
    "tgn:hierarchy":[
        "tgn:2108724",
        "tgn:1000001",
        "tgn:7012149",
        "tgn:2002124",
        "tgn:7007827",
        "tgn:7029392"
    ],
    "tgn:id":2108724,
    "tgn:name":"Bonanza",
    "tgn:placetype":[
        "aat:300008347"
    ]
},
  "bbox": [],
  "geometry": {"coordinates":[-109.1667,40.0167],"type":"Point"}
}