{
  "id": 2119295,
  "type": "Feature",
  "properties": {
    "tgn:hierarchy":[
        "tgn:2119295",
        "tgn:1000001",
        "tgn:2002261",
        "tgn:7012149",
        "tgn:7013961",
        "tgn:7029392"
    ],
    "tgn:id":2119295,
    "tgn:name":"Mount Carbon",
    "tgn:placetype":[
        "aat:300008347"
    ]
},
  "bbox": [],
  "geometry": {"coordinates":[-81.2833,38.1333],"type":"Point"}
}