{
  "id": 1042176,
  "type": "Feature",
  "properties": {
    "tgn:hierarchy":[
        "tgn:1042176",
        "tgn:7002748",
        "tgn:7001399",
        "tgn:1000003",
        "tgn:1000074",
        "tgn:7029392"
    ],
    "tgn:id":1042176,
    "tgn:name":"Palam\u00e1s",
    "tgn:placetype":[
        "aat:300008347"
    ]
},
  "bbox": [],
  "geometry": {"coordinates":[22.083333,39.466667],"type":"Point"}
}