<<<<<<< HEAD
{
  "id": 2763754,
  "type": "Feature",
  "properties": {
    "tgn:hierarchy":[
        "tgn:2763754",
        "tgn:1000001",
        "tgn:7012149",
        "tgn:1002669",
        "tgn:7007710",
        "tgn:7029392"
    ],
    "tgn:id":2763754,
    "tgn:name":"Wharton Run",
    "tgn:placetype":[
        "aat:300008699"
    ]
},
  "bbox": [],
  "geometry": {"coordinates":[-77.7667,40.3833],"type":"Point"}
}
=======
{"geometry":{"type":"Point","coordinates":[-77.766700,40.383300]},"type":"Feature","properties":{"hierarchy":["tgn:2763754","tgn:1000001","tgn:7012149","tgn:1002669","tgn:7007710","tgn:7029392"],"placetype":["aat:300008699"],"id":2763754,"name:xx":"Wharton Run"}}
>>>>>>> 03f74aca74312dbeaf24d7e61306dd6a786dc3d0
