{
  "id": 1090059,
  "type": "Feature",
  "properties": {
    "tgn:hierarchy":[
        "tgn:1090059",
        "tgn:7001242",
        "tgn:1001725",
        "tgn:1000164",
        "tgn:7029392"
    ],
    "tgn:id":1090059,
    "tgn:name":"Tandou Bougou",
    "tgn:placetype":[
        "aat:300008347"
    ]
},
  "bbox": [],
  "geometry": {"coordinates":[10.8833,-3.5333],"type":"Point"}
}