{
  "id": 2360385,
  "type": "Feature",
  "properties": {
    "tgn:hierarchy":[
        "tgn:2360385",
        "tgn:1000001",
        "tgn:7006451",
        "tgn:7012149",
        "tgn:2000099",
        "tgn:7029392"
    ],
    "tgn:id":2360385,
    "tgn:name":"Grasshopper Tank Number Two",
    "tgn:placetype":[
        "aat:300006191"
    ]
},
  "bbox": [],
  "geometry": {"coordinates":[-110.6333,34.0667],"type":"Point"}
}