{
  "id": 7591311,
  "type": "Feature",
  "properties": {
    "tgn:hierarchy":[
        "tgn:7591311",
        "tgn:1000004",
        "tgn:7000198",
        "tgn:7000799",
        "tgn:7029392"
    ],
    "tgn:id":7591311,
    "tgn:name:en":"Par\u0101r",
    "tgn:placetype":[
        "aat:300008347"
    ]
},
  "bbox": [],
  "geometry": {"coordinates":[74.497222,32.966667],"type":"Point"}
}