{
  "id": 7097950,
  "type": "Feature",
  "properties": {
    "tgn:hierarchy":[
        "tgn:7097950",
        "tgn:1000003",
        "tgn:7003676",
        "tgn:7000084",
        "tgn:7029392"
    ],
    "tgn:id":7097950,
    "tgn:name":"Sophienhof",
    "tgn:placetype":[
        "aat:300000206"
    ]
},
  "bbox": [],
  "geometry": {"coordinates":[7.916667,53.683333],"type":"Point"}
}