{
  "id": 7312133,
  "type": "Feature",
  "properties": {
    "tgn:hierarchy":[
        "tgn:7312133",
        "tgn:1001705",
        "tgn:1000049",
        "tgn:1000002",
        "tgn:7029392"
    ],
    "tgn:id":7312133,
    "tgn:name":"Las Catalinas, Alto de",
    "tgn:placetype":[
        "aat:300008795"
    ]
},
  "bbox": [],
  "geometry": {"coordinates":[-72.116667,-35.216667],"type":"Point"}
}