{
  "id": 7456922,
  "type": "Feature",
  "properties": {
    "tgn:hierarchy":[
        "tgn:7456922",
        "tgn:7002444",
        "tgn:1000003",
        "tgn:7029508",
        "tgn:7008591",
        "tgn:7029392"
    ],
    "tgn:id":7456922,
    "tgn:name:en":"Noss Sound",
    "tgn:placetype":[
        "aat:300266558"
    ]
},
  "bbox": [],
  "geometry": {"coordinates":[-1.033333,60.166667],"type":"Point"}
}