{
  "id": 2431442,
  "type": "Feature",
  "properties": {
    "tgn:hierarchy":[
        "tgn:2431442",
        "tgn:7002659",
        "tgn:1000001",
        "tgn:7012149",
        "tgn:2000057",
        "tgn:7029392"
    ],
    "tgn:id":2431442,
    "tgn:name":"Karr Branch",
    "tgn:placetype":[
        "aat:300008699"
    ]
},
  "bbox": [],
  "geometry": {"coordinates":[-86.3167,33.65],"type":"Point"}
}