{
  "id": 7163068,
  "type": "Feature",
  "properties": {
    "tgn:hierarchy":[
        "tgn:7163068",
        "tgn:1000003",
        "tgn:7003677",
        "tgn:7000084",
        "tgn:7029392"
    ],
    "tgn:id":7163068,
    "tgn:name":"In den Sennen",
    "tgn:placetype":[
        "aat:300000206"
    ]
},
  "bbox": [],
  "geometry": {"coordinates":[8.683333,52.466667],"type":"Point"}
}