{
  "id": 2379094,
  "type": "Feature",
  "properties": {
    "tgn:hierarchy":[
        "tgn:2379094",
        "tgn:1000001",
        "tgn:7012149",
        "tgn:1002487",
        "tgn:7007252",
        "tgn:7029392"
    ],
    "tgn:id":2379094,
    "tgn:name":"Hartman Ditch",
    "tgn:placetype":[
        "aat:300006075"
    ]
},
  "bbox": [],
  "geometry": {"coordinates":[-86.25,40.55],"type":"Point"}
}