{
  "id": 7488164,
  "type": "Feature",
  "properties": {
    "tgn:hierarchy":[
        "tgn:7488164",
        "tgn:7001010",
        "tgn:1000004",
        "tgn:1000141",
        "tgn:7029392"
    ],
    "tgn:id":7488164,
    "tgn:name":"Luomawang Shan",
    "tgn:placetype":[
        "aat:300008798"
    ]
},
  "bbox": [],
  "geometry": {"coordinates":[121.643623,24.294317],"type":"Point"}
}