{
  "id": 2743322,
  "type": "Feature",
  "properties": {
    "tgn:hierarchy":[
        "tgn:2743322",
        "tgn:1000001",
        "tgn:7016172",
        "tgn:7012149",
        "tgn:2000156",
        "tgn:7029392"
    ],
    "tgn:id":2743322,
    "tgn:name":"Vanduzer",
    "tgn:placetype":[
        "aat:300008347"
    ]
},
  "bbox": [],
  "geometry": {"coordinates":[-93.7667,33.65],"type":"Point"}
}