{
  "id": 2357331,
  "type": "Feature",
  "properties": {
    "tgn:hierarchy":[
        "tgn:2357331",
        "tgn:1000001",
        "tgn:2001331",
        "tgn:7012149",
        "tgn:7007525",
        "tgn:7029392"
    ],
    "tgn:id":2357331,
    "tgn:name":"Government Canyon",
    "tgn:placetype":[
        "aat:300008761"
    ]
},
  "bbox": [],
  "geometry": {"coordinates":[-100.5667,42.95],"type":"Point"}
}