{
  "id": 7404973,
  "type": "Feature",
  "properties": {
    "tgn:hierarchy":[
        "tgn:7404973",
        "tgn:7016644",
        "tgn:1000001",
        "tgn:7005560",
        "tgn:7029392"
    ],
    "tgn:id":7404973,
    "tgn:name":"Las Gu\u00e1simas",
    "tgn:placetype":[
        "aat:300008347"
    ]
},
  "bbox": [],
  "geometry": {"coordinates":[-104.0625,19.091667],"type":"Point"}
}