{
  "id": 7177379,
  "type": "Feature",
  "properties": {
    "tgn:hierarchy":[
        "tgn:7177379",
        "tgn:7003669",
        "tgn:1000003",
        "tgn:7000084",
        "tgn:7029392"
    ],
    "tgn:id":7177379,
    "tgn:name":"Halbertshofen",
    "tgn:placetype":[
        "aat:300008347"
    ]
},
  "bbox": [],
  "geometry": {"coordinates":[10.216667,48.233333],"type":"Point"}
}