{
  "id": 2031621,
  "type": "Feature",
  "properties": {
    "tgn:hierarchy":[
        "tgn:2031621",
        "tgn:1000001",
        "tgn:7012149",
        "tgn:2000543",
        "tgn:7007252",
        "tgn:7029392"
    ],
    "tgn:id":2031621,
    "tgn:name":"Dongola",
    "tgn:placetype":[
        "aat:300008347",
        "aat:300387210"
    ]
},
  "bbox": [],
  "geometry": {"coordinates":[-87.3333,38.3667],"type":"Point"}
}