{
  "id": 1021041,
  "type": "Feature",
  "properties": {
    "tgn:hierarchy":[
        "tgn:1021041",
        "tgn:1001941",
        "tgn:1000047",
        "tgn:7002458",
        "tgn:1000002",
        "tgn:7029392"
    ],
    "tgn:id":1021041,
    "tgn:name":"Canela",
    "tgn:placetype":[
        "aat:300008347"
    ]
},
  "bbox": [],
  "geometry": {"coordinates":[-50.75,-29.4667],"type":"Point"}
}