{
  "id": 2553936,
  "type": "Feature",
  "properties": {
    "tgn:hierarchy":[
        "tgn:2553936",
        "tgn:1000001",
        "tgn:7012149",
        "tgn:2000615",
        "tgn:7007253",
        "tgn:7029392"
    ],
    "tgn:id":2553936,
    "tgn:name":"Oak Lake",
    "tgn:placetype":[
        "aat:300008680"
    ]
},
  "bbox": [],
  "geometry": {"coordinates":[-94.1667,43.1167],"type":"Point"}
}