<<<<<<< HEAD
{
  "id": 7119502,
  "type": "Feature",
  "properties": {
    "tgn:hierarchy":[
        "tgn:7119502",
        "tgn:1000003",
        "tgn:7003676",
        "tgn:7000084",
        "tgn:7029392"
    ],
    "tgn:id":7119502,
    "tgn:name":"Poggem\u00fchlen",
    "tgn:placetype":[
        "aat:300008347"
    ]
},
  "bbox": [],
  "geometry": {"coordinates":[9.033333,53.45],"type":"Point"}
}
=======
{"geometry":{"type":"Point","coordinates":[9.033333,53.450000]},"type":"Feature","properties":{"hierarchy":["tgn:7119502","tgn:1000003","tgn:7003676","tgn:7000084","tgn:7029392"],"placetype":["aat:300008347"],"id":7119502,"name:xx":"Poggem\u00fchlen"}}
>>>>>>> 03f74aca74312dbeaf24d7e61306dd6a786dc3d0
