{
  "id": 2286829,
  "type": "Feature",
  "properties": {
    "tgn:hierarchy":[
        "tgn:2286829",
        "tgn:1000001",
        "tgn:7012149",
        "tgn:7007158",
        "tgn:2000245",
        "tgn:7029392"
    ],
    "tgn:id":2286829,
    "tgn:name":"Diana, Lake",
    "tgn:placetype":[
        "aat:300008680"
    ]
},
  "bbox": [],
  "geometry": {"coordinates":[-106.7167,40.85],"type":"Point"}
}