{
  "id": 2139017,
  "type": "Feature",
  "properties": {
    "tgn:hierarchy":[
        "tgn:2139017",
        "tgn:7006450",
        "tgn:1000001",
        "tgn:7012149",
        "tgn:2000079",
        "tgn:7029392"
    ],
    "tgn:id":2139017,
    "tgn:name":"Ashland Creek",
    "tgn:placetype":[
        "aat:300008706"
    ]
},
  "bbox": [],
  "geometry": {"coordinates":[-165.75,64.7167],"type":"Point"}
}