{
  "id": 7412043,
  "type": "Feature",
  "properties": {
    "tgn:hierarchy":[
        "tgn:7412043",
        "tgn:7005587",
        "tgn:1000001",
        "tgn:7005560",
        "tgn:7029392"
    ],
    "tgn:id":7412043,
    "tgn:name:es":"Tecolucocalpan",
    "tgn:placetype":[
        "aat:300008347"
    ]
},
  "bbox": [],
  "geometry": {"coordinates":[-98.244444,21.129167],"type":"Point"}
}