<<<<<<< HEAD
{
  "id": 7118976,
  "type": "Feature",
  "properties": {
    "tgn:hierarchy":[
        "tgn:7118976",
        "tgn:7003669",
        "tgn:1000003",
        "tgn:7000084",
        "tgn:7029392"
    ],
    "tgn:id":7118976,
    "tgn:name":"Permering",
    "tgn:placetype":[
        "aat:300008347"
    ]
},
  "bbox": [],
  "geometry": {"coordinates":[12.1,48.316667],"type":"Point"}
}
=======
{"geometry":{"type":"Point","coordinates":[12.100000,48.316667]},"type":"Feature","properties":{"hierarchy":["tgn:7118976","tgn:7003669","tgn:1000003","tgn:7000084","tgn:7029392"],"placetype":["aat:300008347"],"id":7118976,"name:xx":"Permering"}}
>>>>>>> 03f74aca74312dbeaf24d7e61306dd6a786dc3d0
