{
  "id": 7184381,
  "type": "Feature",
  "properties": {
    "tgn:hierarchy":[
        "tgn:7184381",
        "tgn:1000003",
        "tgn:7003676",
        "tgn:7000084",
        "tgn:7029392"
    ],
    "tgn:id":7184381,
    "tgn:name":"Giengets-Berg",
    "tgn:placetype":[
        "aat:300008795"
    ]
},
  "bbox": [],
  "geometry": {"coordinates":[10.45,51.883333],"type":"Point"}
}