{
  "id": 2748458,
  "type": "Feature",
  "properties": {
    "tgn:hierarchy":[
        "tgn:2748458",
        "tgn:1000001",
        "tgn:2001181",
        "tgn:7012149",
        "tgn:7007523",
        "tgn:7029392"
    ],
    "tgn:id":2748458,
    "tgn:name":"Walker Hollow",
    "tgn:placetype":[
        "aat:300008761"
    ]
},
  "bbox": [],
  "geometry": {"coordinates":[-90.9833,37.0333],"type":"Point"}
}