{
  "id": 7512234,
  "type": "Feature",
  "properties": {
    "tgn:hierarchy":[
        "tgn:7512234",
        "tgn:1009227",
        "tgn:7001866",
        "tgn:1000226",
        "tgn:1000006",
        "tgn:7029392"
    ],
    "tgn:id":7512234,
    "tgn:name:en":"Island, The",
    "tgn:placetype":[
        "aat:300008791"
    ]
},
  "bbox": [],
  "geometry": {"coordinates":[170.566667,-43.75],"type":"Point"}
}