{
  "id": 2575246,
  "type": "Feature",
  "properties": {
    "tgn:hierarchy":[
        "tgn:2575246",
        "tgn:1000001",
        "tgn:7012149",
        "tgn:1002932",
        "tgn:7007710",
        "tgn:7029392"
    ],
    "tgn:id":2575246,
    "tgn:name":"Penny Hill",
    "tgn:placetype":[
        "aat:300008798"
    ]
},
  "bbox": [],
  "geometry": {"coordinates":[-75.7167,41.9667],"type":"Point"}
}