{
  "id": 1052668,
  "type": "Feature",
  "properties": {
    "tgn:hierarchy":[
        "tgn:1052668",
        "tgn:1000004",
        "tgn:7011600",
        "tgn:7018214",
        "tgn:7002435",
        "tgn:7029392"
    ],
    "tgn:id":1052668,
    "tgn:name":"Beloyarskiy",
    "tgn:placetype":[
        "aat:300008347"
    ]
},
  "bbox": [],
  "geometry": {"coordinates":[61.4667,56.7833],"type":"Point"}
}