<<<<<<< HEAD
{
  "id": 2253735,
  "type": "Feature",
  "properties": {
    "tgn:hierarchy":[
        "tgn:2253735",
        "tgn:1000001",
        "tgn:7012149",
        "tgn:2000494",
        "tgn:7007250",
        "tgn:7029392"
    ],
    "tgn:id":2253735,
    "tgn:name":"Cookhouse Gulch",
    "tgn:placetype":[
        "aat:300008761"
    ]
},
  "bbox": [],
  "geometry": {"coordinates":[-116.3,44.6833],"type":"Point"}
}
=======
{"geometry":{"type":"Point","coordinates":[-116.300000,44.683300]},"type":"Feature","properties":{"hierarchy":["tgn:2253735","tgn:1000001","tgn:7012149","tgn:2000494","tgn:7007250","tgn:7029392"],"placetype":["aat:300008761"],"id":2253735,"name:xx":"Cookhouse Gulch"}}
>>>>>>> 03f74aca74312dbeaf24d7e61306dd6a786dc3d0
