{
  "id": 2546397,
  "type": "Feature",
  "properties": {
    "tgn:hierarchy":[
        "tgn:2546397",
        "tgn:1000001",
        "tgn:7012149",
        "tgn:2001293",
        "tgn:7007524",
        "tgn:7029392"
    ],
    "tgn:id":2546397,
    "tgn:name":"North Fork Horse Creek",
    "tgn:placetype":[
        "aat:300008706"
    ]
},
  "bbox": [],
  "geometry": {"coordinates":[-110.4333,46.05],"type":"Point"}
}