{
  "id": 2495829,
  "type": "Feature",
  "properties": {
    "tgn:hierarchy":[
        "tgn:2495829",
        "tgn:1000001",
        "tgn:7006451",
        "tgn:2000091",
        "tgn:7012149",
        "tgn:7029392"
    ],
    "tgn:id":2495829,
    "tgn:name":"Mason Hill",
    "tgn:placetype":[
        "aat:300266640"
    ]
},
  "bbox": [],
  "geometry": {"coordinates":[-109.9167,31.4333],"type":"Point"}
}