{
  "id": 2713205,
  "type": "Feature",
  "properties": {
    "tgn:hierarchy":[
        "tgn:2713205",
        "tgn:1002153",
        "tgn:1000001",
        "tgn:7012149",
        "tgn:7007710",
        "tgn:7029392"
    ],
    "tgn:id":2713205,
    "tgn:name":"Taylor Run",
    "tgn:placetype":[
        "aat:300008699"
    ]
},
  "bbox": [],
  "geometry": {"coordinates":[-79.5167,40.6667],"type":"Point"}
}