{
  "id": 2345288,
  "type": "Feature",
  "properties": {
    "tgn:hierarchy":[
        "tgn:2345288",
        "tgn:1000001",
        "tgn:2000589",
        "tgn:7012149",
        "tgn:7007253",
        "tgn:7029392"
    ],
    "tgn:id":2345288,
    "tgn:name":"Garland",
    "tgn:placetype":[
        "aat:300008347"
    ]
},
  "bbox": [],
  "geometry": {"coordinates":[-91.2167,41.05],"type":"Point"}
}