{
  "id": 2173162,
  "type": "Feature",
  "properties": {
    "tgn:hierarchy":[
        "tgn:2173162",
        "tgn:7002659",
        "tgn:1000001",
        "tgn:7012149",
        "tgn:2000035",
        "tgn:7029392"
    ],
    "tgn:id":2173162,
    "tgn:name":"Bingham Mountain",
    "tgn:placetype":[
        "aat:300008798"
    ]
},
  "bbox": [],
  "geometry": {"coordinates":[-86.2833,34.7833],"type":"Point"}
}