{
  "id": 7360370,
  "type": "Feature",
  "properties": {
    "tgn:hierarchy":[
        "tgn:7360370",
        "tgn:7005578",
        "tgn:1000001",
        "tgn:7005560",
        "tgn:7029392"
    ],
    "tgn:id":7360370,
    "tgn:name":"Dzitnup",
    "tgn:placetype":[
        "aat:300008347"
    ]
},
  "bbox": [],
  "geometry": {"coordinates":[-90.033333,20.133333],"type":"Point"}
}