{
  "id": 2253093,
  "type": "Feature",
  "properties": {
    "tgn:hierarchy":[
        "tgn:2253093",
        "tgn:1000001",
        "tgn:2002104",
        "tgn:7012149",
        "tgn:7007827",
        "tgn:7029392"
    ],
    "tgn:id":2253093,
    "tgn:name":"Consumers Wash",
    "tgn:placetype":[
        "aat:300008761"
    ]
},
  "bbox": [],
  "geometry": {"coordinates":[-110.9333,39.6833],"type":"Point"}
}