<<<<<<< HEAD
{
  "id": 2253093,
  "type": "Feature",
  "properties": {
    "tgn:hierarchy":[
        "tgn:2253093",
        "tgn:1000001",
        "tgn:2002104",
        "tgn:7012149",
        "tgn:7007827",
        "tgn:7029392"
    ],
    "tgn:id":2253093,
    "tgn:name":"Consumers Wash",
    "tgn:placetype":[
        "aat:300008761"
    ]
},
  "bbox": [],
  "geometry": {"coordinates":[-110.9333,39.6833],"type":"Point"}
}
=======
{"geometry":{"type":"Point","coordinates":[-110.933300,39.683300]},"type":"Feature","properties":{"hierarchy":["tgn:2253093","tgn:1000001","tgn:2002104","tgn:7012149","tgn:7007827","tgn:7029392"],"placetype":["aat:300008761"],"id":2253093,"name:xx":"Consumers Wash"}}
>>>>>>> 03f74aca74312dbeaf24d7e61306dd6a786dc3d0
