{
  "id": 2109349,
  "type": "Feature",
  "properties": {
    "tgn:hierarchy":[
        "tgn:2109349",
        "tgn:1000001",
        "tgn:7012149",
        "tgn:2002118",
        "tgn:7007827",
        "tgn:7029392"
    ],
    "tgn:id":2109349,
    "tgn:name":"Valley Fair Mall",
    "tgn:placetype":[
        "aat:300247594"
    ]
},
  "bbox": [],
  "geometry": {"coordinates":[-111.95,40.6833],"type":"Point"}
}