{
  "id": 2213977,
  "type": "Feature",
  "properties": {
    "tgn:hierarchy":[
        "tgn:2213977",
        "tgn:1002140",
        "tgn:1000001",
        "tgn:7012149",
        "tgn:7007520",
        "tgn:7029392"
    ],
    "tgn:id":2213977,
    "tgn:name":"Cady Lake",
    "tgn:placetype":[
        "aat:300008680"
    ]
},
  "bbox": [],
  "geometry": {"coordinates":[-85.7833,42.6667],"type":"Point"}
}