{
  "id": 7113872,
  "type": "Feature",
  "properties": {
    "tgn:hierarchy":[
        "tgn:7113872",
        "tgn:1000003",
        "tgn:7003677",
        "tgn:7000084",
        "tgn:7029392"
    ],
    "tgn:id":7113872,
    "tgn:name":"Bahnhof Rodde",
    "tgn:placetype":[
        "aat:300007783"
    ]
},
  "bbox": [],
  "geometry": {"coordinates":[7.52,52.279444],"type":"Point"}
}