{
  "id": 2375655,
  "type": "Feature",
  "properties": {
    "tgn:hierarchy":[
        "tgn:2375655",
        "tgn:1000001",
        "tgn:7012149",
        "tgn:7007157",
        "tgn:2000191",
        "tgn:7029392"
    ],
    "tgn:id":2375655,
    "tgn:name":"Happy Camp Mountain",
    "tgn:placetype":[
        "aat:300008798"
    ]
},
  "bbox": [],
  "geometry": {"coordinates":[-123.4667,40.8833],"type":"Point"}
}