{
  "id": 2465528,
  "type": "Feature",
  "properties": {
    "tgn:hierarchy":[
        "tgn:2465528",
        "tgn:1000001",
        "tgn:7012149",
        "tgn:1002961",
        "tgn:7007568",
        "tgn:7029392"
    ],
    "tgn:id":2465528,
    "tgn:name":"Lone Mountain",
    "tgn:placetype":[
        "aat:300008798"
    ]
},
  "bbox": [],
  "geometry": {"coordinates":[-74.3833,41.9667],"type":"Point"}
}