{
  "id": 7507230,
  "type": "Feature",
  "properties": {
    "tgn:hierarchy":[
        "tgn:7507230",
        "tgn:1008380",
        "tgn:1000226",
        "tgn:7018426",
        "tgn:1000006",
        "tgn:7029392"
    ],
    "tgn:id":7507230,
    "tgn:name:en":"Pukorokoro Creek",
    "tgn:placetype":[
        "aat:300008699"
    ]
},
  "bbox": [],
  "geometry": {"coordinates":[175.316667,-37.183333],"type":"Point"}
}