{
  "id": 7344396,
  "type": "Feature",
  "properties": {
    "tgn:hierarchy":[
        "tgn:7344396",
        "tgn:7001165",
        "tgn:1000003",
        "tgn:7002793",
        "tgn:1000095",
        "tgn:7029392"
    ],
    "tgn:id":7344396,
    "tgn:name":"Aras de Alpuente",
    "tgn:placetype":[
        "aat:300008347"
    ]
},
  "bbox": [],
  "geometry": {"coordinates":[-1.133333,39.916667],"type":"Point"}
}