{
  "id": 7275644,
  "type": "Feature",
  "properties": {
    "tgn:hierarchy":[
        "tgn:7275644",
        "tgn:1001708",
        "tgn:1000049",
        "tgn:1000002",
        "tgn:7029392"
    ],
    "tgn:id":7275644,
    "tgn:name":"Tres Cercas, Cerro",
    "tgn:placetype":[
        "aat:300008777"
    ]
},
  "bbox": [],
  "geometry": {"coordinates":[-71.333333,-33.716667],"type":"Point"}
}