{
  "id": 2151929,
  "type": "Feature",
  "properties": {
    "tgn:hierarchy":[
        "tgn:2151929",
        "tgn:1000001",
        "tgn:7012149",
        "tgn:2002111",
        "tgn:7007827",
        "tgn:7029392"
    ],
    "tgn:id":2151929,
    "tgn:name":"Bauer Point",
    "tgn:placetype":[
        "aat:300008850"
    ]
},
  "bbox": [],
  "geometry": {"coordinates":[-112.9833,37.5167],"type":"Point"}
}