{
  "id": 2222152,
  "type": "Feature",
  "properties": {
    "tgn:hierarchy":[
        "tgn:2222152",
        "tgn:1000001",
        "tgn:7012149",
        "tgn:2001720",
        "tgn:7007708",
        "tgn:7029392"
    ],
    "tgn:id":2222152,
    "tgn:name":"Carney Butte",
    "tgn:placetype":[
        "aat:300008798"
    ]
},
  "bbox": [],
  "geometry": {"coordinates":[-118.9333,45.2667],"type":"Point"}
}