{
  "id": 1086158,
  "type": "Feature",
  "properties": {
    "tgn:hierarchy":[
        "tgn:1086158",
        "tgn:1001236",
        "tgn:1000004",
        "tgn:7018455",
        "tgn:1000144",
        "tgn:7029392"
    ],
    "tgn:id":1086158,
    "tgn:name":"Hidirbaba",
    "tgn:placetype":[
        "aat:300008347"
    ]
},
  "bbox": [],
  "geometry": {"coordinates":[38.9667,38.7667],"type":"Point"}
}