{
  "id": 2466102,
  "type": "Feature",
  "properties": {
    "tgn:hierarchy":[
        "tgn:2466102",
        "tgn:1000001",
        "tgn:2001430",
        "tgn:7012149",
        "tgn:7007566",
        "tgn:7029392"
    ],
    "tgn:id":2466102,
    "tgn:name":"Lone Wolf",
    "tgn:placetype":[
        "aat:300008347"
    ]
},
  "bbox": [],
  "geometry": {"coordinates":[-103.8333,33.6833],"type":"Point"}
}