{
  "id": 2784246,
  "type": "Feature",
  "properties": {
    "tgn:hierarchy":[
        "tgn:2784246",
        "tgn:1000001",
        "tgn:7012149",
        "tgn:2001711",
        "tgn:7007708",
        "tgn:7029392"
    ],
    "tgn:id":2784246,
    "tgn:name":"Yankee Creek",
    "tgn:placetype":[
        "aat:300008706"
    ]
},
  "bbox": [],
  "geometry": {"coordinates":[-122.6667,42.3667],"type":"Point"}
}