{
  "id": 2086281,
  "type": "Feature",
  "properties": {
    "tgn:hierarchy":[
        "tgn:2086281",
        "tgn:1000001",
        "tgn:1002272",
        "tgn:7012149",
        "tgn:7007710",
        "tgn:7029392"
    ],
    "tgn:id":2086281,
    "tgn:name":"Bela",
    "tgn:placetype":[
        "aat:300008347"
    ]
},
  "bbox": [],
  "geometry": {"coordinates":[-79.5667,41.05],"type":"Point"}
}