{
  "id": 7294785,
  "type": "Feature",
  "properties": {
    "tgn:hierarchy":[
        "tgn:7294785",
        "tgn:7002807",
        "tgn:1000003",
        "tgn:7003837",
        "tgn:1000095",
        "tgn:7029392"
    ],
    "tgn:id":7294785,
    "tgn:name":"Valle-Hondo",
    "tgn:placetype":[
        "aat:300386990"
    ]
},
  "bbox": [],
  "geometry": {"coordinates":[-5.466667,38.716667],"type":"Point"}
}