<<<<<<< HEAD
{
  "id": 7058290,
  "type": "Feature",
  "properties": {
    "tgn:hierarchy":[
        "tgn:7058290",
        "tgn:1003505",
        "tgn:1000003",
        "tgn:7002993",
        "tgn:1000080",
        "tgn:7029392"
    ],
    "tgn:id":7058290,
    "tgn:name":"Bovedo",
    "tgn:placetype":[
        "aat:300008347"
    ]
},
  "bbox": [],
  "geometry": {"coordinates":[13.766667,45.683333],"type":"Point"}
}
=======
{"geometry":{"type":"Point","coordinates":[13.766667,45.683333]},"type":"Feature","properties":{"hierarchy":["tgn:7058290","tgn:1003505","tgn:1000003","tgn:7002993","tgn:1000080","tgn:7029392"],"placetype":["aat:300008347"],"id":7058290,"name:xx":"Bovedo"}}
>>>>>>> 03f74aca74312dbeaf24d7e61306dd6a786dc3d0
