{
  "id": 7058290,
  "type": "Feature",
  "properties": {
    "tgn:hierarchy":[
        "tgn:7058290",
        "tgn:1003505",
        "tgn:1000003",
        "tgn:7002993",
        "tgn:1000080",
        "tgn:7029392"
    ],
    "tgn:id":7058290,
    "tgn:name":"Bovedo",
    "tgn:placetype":[
        "aat:300008347"
    ]
},
  "bbox": [],
  "geometry": {"coordinates":[13.766667,45.683333],"type":"Point"}
}