<<<<<<< HEAD
{
  "id": 7246061,
  "type": "Feature",
  "properties": {
    "tgn:hierarchy":[
        "tgn:7246061",
        "tgn:7003456",
        "tgn:1000003",
        "tgn:1000063",
        "tgn:7018236",
        "tgn:7029392"
    ],
    "tgn:id":7246061,
    "tgn:name":"Boonmerkt",
    "tgn:placetype":[
        "aat:300008347"
    ]
},
  "bbox": [],
  "geometry": {"coordinates":[4.71602,51.086282],"type":"Point"}
}
=======
{"geometry":{"type":"Point","coordinates":[4.716020,51.086282]},"type":"Feature","properties":{"hierarchy":["tgn:7246061","tgn:7003456","tgn:1000003","tgn:1000063","tgn:7018236","tgn:7029392"],"placetype":["aat:300008347"],"id":7246061,"name:xx":"Boonmerkt"}}
>>>>>>> 03f74aca74312dbeaf24d7e61306dd6a786dc3d0
