<<<<<<< HEAD
{
  "id": 2766564,
  "type": "Feature",
  "properties": {
    "tgn:hierarchy":[
        "tgn:2766564",
        "tgn:1000001",
        "tgn:7012149",
        "tgn:2000917",
        "tgn:7007256",
        "tgn:7029392"
    ],
    "tgn:id":2766564,
    "tgn:name":"White Oak Creek",
    "tgn:placetype":[
        "aat:300008706"
    ]
},
  "bbox": [],
  "geometry": {"coordinates":[-92.6833,31.7167],"type":"Point"}
}
=======
{"geometry":{"type":"Point","coordinates":[-92.683300,31.716700]},"type":"Feature","properties":{"hierarchy":["tgn:2766564","tgn:1000001","tgn:7012149","tgn:2000917","tgn:7007256","tgn:7029392"],"placetype":["aat:300008706"],"id":2766564,"name:xx":"White Oak Creek"}}
>>>>>>> 03f74aca74312dbeaf24d7e61306dd6a786dc3d0
