{
  "id": 7200570,
  "type": "Feature",
  "properties": {
    "tgn:hierarchy":[
        "tgn:7200570",
        "tgn:1000003",
        "tgn:7003678",
        "tgn:7000084",
        "tgn:7029392"
    ],
    "tgn:id":7200570,
    "tgn:name":"Hof Dotzelrod",
    "tgn:placetype":[
        "aat:300000206"
    ]
},
  "bbox": [],
  "geometry": {"coordinates":[9.283333,50.766667],"type":"Point"}
}