{
  "id": 2757451,
  "type": "Feature",
  "properties": {
    "tgn:hierarchy":[
        "tgn:2757451",
        "tgn:1000001",
        "tgn:7006451",
        "tgn:2000095",
        "tgn:7012149",
        "tgn:7029392"
    ],
    "tgn:id":2757451,
    "tgn:name":"West Becker Seep",
    "tgn:placetype":[
        "aat:300008697"
    ]
},
  "bbox": [],
  "geometry": {"coordinates":[-109.3333,33.7167],"type":"Point"}
}