{
  "id": 7553133,
  "type": "Feature",
  "properties": {
    "tgn:hierarchy":[
        "tgn:7553133",
        "tgn:1001828",
        "tgn:1000004",
        "tgn:7000198",
        "tgn:7029392"
    ],
    "tgn:id":7553133,
    "tgn:name:en":"Marikal",
    "tgn:placetype":[
        "aat:300008347"
    ]
},
  "bbox": [],
  "geometry": {"coordinates":[77.983333,16.916667],"type":"Point"}
}