{
  "id": 7150294,
  "type": "Feature",
  "properties": {
    "tgn:hierarchy":[
        "tgn:7150294",
        "tgn:7003669",
        "tgn:1000003",
        "tgn:7000084",
        "tgn:7029392"
    ],
    "tgn:id":7150294,
    "tgn:name":"Kronawitten",
    "tgn:placetype":[
        "aat:300008347"
    ]
},
  "bbox": [],
  "geometry": {"coordinates":[13.483333,48.616667],"type":"Point"}
}