{
  "id": 2088637,
  "type": "Feature",
  "properties": {
    "tgn:hierarchy":[
        "tgn:2088637",
        "tgn:1000001",
        "tgn:7012149",
        "tgn:1003047",
        "tgn:7007710",
        "tgn:7029392"
    ],
    "tgn:id":2088637,
    "tgn:name":"Frogtown",
    "tgn:placetype":[
        "aat:300008347"
    ]
},
  "bbox": [],
  "geometry": {"coordinates":[-76.85,40.1667],"type":"Point"}
}