{
  "id": 7073141,
  "type": "Feature",
  "properties": {
    "tgn:hierarchy":[
        "tgn:7073141",
        "tgn:7003669",
        "tgn:1000003",
        "tgn:7000084",
        "tgn:7029392"
    ],
    "tgn:id":7073141,
    "tgn:name":"Tannen Bichel",
    "tgn:placetype":[
        "aat:300008777"
    ]
},
  "bbox": [],
  "geometry": {"coordinates":[10.55,47.683333],"type":"Point"}
}