{
  "id": 2671620,
  "type": "Feature",
  "properties": {
    "tgn:hierarchy":[
        "tgn:2671620",
        "tgn:1000001",
        "tgn:2001944",
        "tgn:7012149",
        "tgn:7007826",
        "tgn:7029392"
    ],
    "tgn:id":2671620,
    "tgn:name":"Smith Lake",
    "tgn:placetype":[
        "aat:300008680"
    ]
},
  "bbox": [],
  "geometry": {"coordinates":[-94.2667,33.55],"type":"Point"}
}