{
  "id": 2078520,
  "type": "Feature",
  "properties": {
    "tgn:hierarchy":[
        "tgn:2078520",
        "tgn:1000001",
        "tgn:7012149",
        "tgn:1002627",
        "tgn:7007706",
        "tgn:7029392"
    ],
    "tgn:id":2078520,
    "tgn:name":"Boardman",
    "tgn:placetype":[
        "aat:300008347"
    ]
},
  "bbox": [],
  "geometry": {"coordinates":[-80.65,41.0167],"type":"Point"}
}