{
  "id": 7197636,
  "type": "Feature",
  "properties": {
    "tgn:hierarchy":[
        "tgn:7197636",
        "tgn:1000003",
        "tgn:7003676",
        "tgn:7000084",
        "tgn:7029392"
    ],
    "tgn:id":7197636,
    "tgn:name":"D\u00fclloh",
    "tgn:placetype":[
        "aat:300008863"
    ]
},
  "bbox": [],
  "geometry": {"coordinates":[10.466667,52.833333],"type":"Point"}
}