{
  "id": 2150576,
  "type": "Feature",
  "properties": {
    "tgn:hierarchy":[
        "tgn:2150576",
        "tgn:1000001",
        "tgn:7012149",
        "tgn:2000895",
        "tgn:7007256",
        "tgn:7029392"
    ],
    "tgn:id":2150576,
    "tgn:name":"Basin, The",
    "tgn:placetype":[
        "aat:300008905"
    ]
},
  "bbox": [],
  "geometry": {"coordinates":[-91.8833,32.35],"type":"Point"}
}