{
  "id": 7344282,
  "type": "Feature",
  "properties": {
    "tgn:hierarchy":[
        "tgn:7344282",
        "tgn:7002820",
        "tgn:7030216",
        "tgn:1000003",
        "tgn:1000095",
        "tgn:7029392"
    ],
    "tgn:id":7344282,
    "tgn:name":"Bague de Bordeillat, Serre de la",
    "tgn:placetype":[
        "aat:300008795"
    ]
},
  "bbox": [],
  "geometry": {"coordinates":[2.520198,42.335474],"type":"Point"}
}