<<<<<<< HEAD
{
  "id": 7373371,
  "type": "Feature",
  "properties": {
    "tgn:hierarchy":[
        "tgn:7373371",
        "tgn:1000001",
        "tgn:7005589",
        "tgn:7005560",
        "tgn:7029392"
    ],
    "tgn:id":7373371,
    "tgn:name":"La Leona, Sierra de",
    "tgn:placetype":[
        "aat:300266640"
    ]
},
  "bbox": [],
  "geometry": {"coordinates":[-100.3,24.566667],"type":"Point"}
}
=======
{"geometry":{"type":"Point","coordinates":[-100.300000,24.566667]},"type":"Feature","properties":{"hierarchy":["tgn:7373371","tgn:1000001","tgn:7005589","tgn:7005560","tgn:7029392"],"placetype":["aat:300266640"],"id":7373371,"name:xx":"La Leona, Sierra de"}}
>>>>>>> 03f74aca74312dbeaf24d7e61306dd6a786dc3d0
