{
  "id": 7304923,
  "type": "Feature",
  "properties": {
    "tgn:hierarchy":[
        "tgn:7304923",
        "tgn:7002759",
        "tgn:7008909",
        "tgn:1000003",
        "tgn:1000095",
        "tgn:7029392"
    ],
    "tgn:id":7304923,
    "tgn:name":"Latorre",
    "tgn:placetype":[
        "aat:300008347"
    ]
},
  "bbox": [],
  "geometry": {"coordinates":[0.333611,42.346522],"type":"Point"}
}