<<<<<<< HEAD
{
  "id": 2762422,
  "type": "Feature",
  "properties": {
    "tgn:hierarchy":[
        "tgn:2762422",
        "tgn:1000001",
        "tgn:7012149",
        "tgn:2000646",
        "tgn:7007253",
        "tgn:7029392"
    ],
    "tgn:id":2762422,
    "tgn:name":"West Union",
    "tgn:placetype":[
        "aat:300008347"
    ]
},
  "bbox": [],
  "geometry": {"coordinates":[-92.4333,42.1833],"type":"Point"}
}
=======
{"geometry":{"type":"Point","coordinates":[-92.433300,42.183300]},"type":"Feature","properties":{"hierarchy":["tgn:2762422","tgn:1000001","tgn:7012149","tgn:2000646","tgn:7007253","tgn:7029392"],"placetype":["aat:300008347"],"id":2762422,"name:xx":"West Union"}}
>>>>>>> 03f74aca74312dbeaf24d7e61306dd6a786dc3d0
