{
  "id": 2009596,
  "type": "Feature",
  "properties": {
    "tgn:hierarchy":[
        "tgn:2009596",
        "tgn:1000001",
        "tgn:7016172",
        "tgn:2000110",
        "tgn:7012149",
        "tgn:7029392"
    ],
    "tgn:id":2009596,
    "tgn:name":"Sumpter",
    "tgn:placetype":[
        "aat:300008347",
        "aat:300387210"
    ]
},
  "bbox": [],
  "geometry": {"coordinates":[-92.0333,33.4833],"type":"Point"}
}