{
  "id": 2676807,
  "type": "Feature",
  "properties": {
    "tgn:hierarchy":[
        "tgn:2676807",
        "tgn:1000001",
        "tgn:7012149",
        "tgn:1002913",
        "tgn:7007919",
        "tgn:7029392"
    ],
    "tgn:id":2676807,
    "tgn:name":"South Branch Chopawamsic Creek",
    "tgn:placetype":[
        "aat:300008706"
    ]
},
  "bbox": [],
  "geometry": {"coordinates":[-77.4667,38.55],"type":"Point"}
}