{
  "id": 7002255,
  "type": "Feature",
  "properties": {
    "tgn:hierarchy":[
        "tgn:7002255",
        "tgn:1000004",
        "tgn:1002053",
        "tgn:1000140",
        "tgn:7029392"
    ],
    "tgn:id":7002255,
    "tgn:name":"Af\u0101miy\u0101",
    "tgn:placetype":[
        "aat:300008347",
        "aat:300167671",
        "aat:300387238",
        "aat:300019947",
        "aat:300008057"
    ]
},
  "bbox": [],
  "geometry": {"coordinates":[36.392363,35.413626],"type":"Point"}
}