{
  "id": 2174719,
  "type": "Feature",
  "properties": {
    "tgn:hierarchy":[
        "tgn:2174719",
        "tgn:1000001",
        "tgn:7012149",
        "tgn:2001289",
        "tgn:7007524",
        "tgn:7029392"
    ],
    "tgn:id":2174719,
    "tgn:name":"Bitter Creek",
    "tgn:placetype":[
        "aat:300008706"
    ]
},
  "bbox": [],
  "geometry": {"coordinates":[-110.4667,46.2167],"type":"Point"}
}