<<<<<<< HEAD
{
  "id": 2150863,
  "type": "Feature",
  "properties": {
    "tgn:hierarchy":[
        "tgn:2150863",
        "tgn:1000001",
        "tgn:7012149",
        "tgn:1002897",
        "tgn:7007920",
        "tgn:7029392"
    ],
    "tgn:id":2150863,
    "tgn:name":"Bass Lake",
    "tgn:placetype":[
        "aat:300008680"
    ]
},
  "bbox": [],
  "geometry": {"coordinates":[-121.9333,45.65],"type":"Point"}
}
=======
{"geometry":{"type":"Point","coordinates":[-121.933300,45.650000]},"type":"Feature","properties":{"hierarchy":["tgn:2150863","tgn:1000001","tgn:7012149","tgn:1002897","tgn:7007920","tgn:7029392"],"placetype":["aat:300008680"],"id":2150863,"name:xx":"Bass Lake"}}
>>>>>>> 03f74aca74312dbeaf24d7e61306dd6a786dc3d0
