{
  "id": 7265332,
  "type": "Feature",
  "properties": {
    "tgn:concordances":{
        "gn:id":"2751389"
    },
    "tgn:hierarchy":[
        "tgn:7265332",
        "tgn:7003619",
        "tgn:1000003",
        "tgn:7016845",
        "tgn:7029392"
    ],
    "tgn:id":7265332,
    "tgn:name:nl":"Lunen",
    "tgn:placetype":[
        "aat:300008347"
    ]
},
  "bbox": [],
  "geometry": {"coordinates":[5.75,51.783333],"type":"Point"}
}