{
  "id": 2534469,
  "type": "Feature",
  "properties": {
    "tgn:hierarchy":[
        "tgn:2534469",
        "tgn:1000001",
        "tgn:7012149",
        "tgn:2001281",
        "tgn:7007524",
        "tgn:7029392"
    ],
    "tgn:id":2534469,
    "tgn:name":"NE SW Section 9 Mine",
    "tgn:placetype":[
        "aat:300000390"
    ]
},
  "bbox": [],
  "geometry": {"coordinates":[-112.35,45.9333],"type":"Point"}
}