{
  "id": 2358980,
  "type": "Feature",
  "properties": {
    "tgn:hierarchy":[
        "tgn:2358980",
        "tgn:1002137",
        "tgn:1000001",
        "tgn:7012149",
        "tgn:7007710",
        "tgn:7029392"
    ],
    "tgn:id":2358980,
    "tgn:name":"Granite Hill",
    "tgn:placetype":[
        "aat:300008798"
    ]
},
  "bbox": [],
  "geometry": {"coordinates":[-77.15,39.85],"type":"Point"}
}