{
  "id": 7094335,
  "type": "Feature",
  "properties": {
    "tgn:hierarchy":[
        "tgn:7094335",
        "tgn:1000003",
        "tgn:7003687",
        "tgn:7000084",
        "tgn:7029392"
    ],
    "tgn:id":7094335,
    "tgn:name":"Seedorf",
    "tgn:placetype":[
        "aat:300008347"
    ]
},
  "bbox": [],
  "geometry": {"coordinates":[12.066667,52.416667],"type":"Point"}
}