{
  "id": 2687903,
  "type": "Feature",
  "properties": {
    "tgn:hierarchy":[
        "tgn:2687903",
        "tgn:1000001",
        "tgn:7012149",
        "tgn:2001893",
        "tgn:7007825",
        "tgn:7029392"
    ],
    "tgn:id":2687903,
    "tgn:name":"Springbrook Lake",
    "tgn:placetype":[
        "aat:300006191"
    ]
},
  "bbox": [],
  "geometry": {"coordinates":[-88.65,35.7333],"type":"Point"}
}