{
  "id": 2702603,
  "type": "Feature",
  "properties": {
    "tgn:hierarchy":[
        "tgn:2702603",
        "tgn:1000001",
        "tgn:7012149",
        "tgn:2002071",
        "tgn:7007826",
        "tgn:7029392"
    ],
    "tgn:id":2702603,
    "tgn:name":"Sulphur Creek",
    "tgn:placetype":[
        "aat:300008706"
    ]
},
  "bbox": [],
  "geometry": {"coordinates":[-100.7667,32.6167],"type":"Point"}
}