{
  "id": 2667544,
  "type": "Feature",
  "properties": {
    "tgn:hierarchy":[
        "tgn:2667544",
        "tgn:7006450",
        "tgn:1000001",
        "tgn:7012149",
        "tgn:2000079",
        "tgn:7029392"
    ],
    "tgn:id":2667544,
    "tgn:name":"Skookum River",
    "tgn:placetype":[
        "aat:300008707"
    ]
},
  "bbox": [],
  "geometry": {"coordinates":[-164.0333,64.7167],"type":"Point"}
}