<<<<<<< HEAD
{
  "id": 2768847,
  "type": "Feature",
  "properties": {
    "tgn:hierarchy":[
        "tgn:2768847",
        "tgn:1000001",
        "tgn:7012149",
        "tgn:7007157",
        "tgn:1002608",
        "tgn:7029392"
    ],
    "tgn:id":2768847,
    "tgn:name":"Whitney Canyon",
    "tgn:placetype":[
        "aat:300008761"
    ]
},
  "bbox": [],
  "geometry": {"coordinates":[-118.45,34.35],"type":"Point"}
}
=======
{"geometry":{"type":"Point","coordinates":[-118.450000,34.350000]},"type":"Feature","properties":{"hierarchy":["tgn:2768847","tgn:1000001","tgn:7012149","tgn:7007157","tgn:1002608","tgn:7029392"],"placetype":["aat:300008761"],"id":2768847,"name:xx":"Whitney Canyon"}}
>>>>>>> 03f74aca74312dbeaf24d7e61306dd6a786dc3d0
