{
  "id": 1042618,
  "type": "Feature",
  "properties": {
    "tgn:hierarchy":[
        "tgn:1042618",
        "tgn:7003498",
        "tgn:7001201",
        "tgn:1000003",
        "tgn:1000078",
        "tgn:7029392"
    ],
    "tgn:id":1042618,
    "tgn:name":"Ballyferriter",
    "tgn:placetype":[
        "aat:300008347"
    ]
},
  "bbox": [],
  "geometry": {"coordinates":[-10.4333,52.15],"type":"Point"}
}