{
  "id": 2239217,
  "type": "Feature",
  "properties": {
    "tgn:hierarchy":[
        "tgn:2239217",
        "tgn:7030516",
        "tgn:7006450",
        "tgn:1000001",
        "tgn:7012149",
        "tgn:7029392"
    ],
    "tgn:id":2239217,
    "tgn:name":"Chugul Point",
    "tgn:placetype":[
        "aat:300008850"
    ]
},
  "bbox": [],
  "geometry": {"coordinates":[178.0833,51.9833],"type":"Point"}
}