{
  "id": 7131949,
  "type": "Feature",
  "properties": {
    "tgn:hierarchy":[
        "tgn:7131949",
        "tgn:7003692",
        "tgn:1000003",
        "tgn:7000084",
        "tgn:7029392"
    ],
    "tgn:id":7131949,
    "tgn:name":"Maushalde",
    "tgn:placetype":[
        "aat:300000206"
    ]
},
  "bbox": [],
  "geometry": {"coordinates":[9.05,47.85],"type":"Point"}
}