{
  "id": 7121299,
  "type": "Feature",
  "properties": {
    "tgn:hierarchy":[
        "tgn:7121299",
        "tgn:1000003",
        "tgn:7003689",
        "tgn:7000084",
        "tgn:7029392"
    ],
    "tgn:id":7121299,
    "tgn:name":"Porsts Hof",
    "tgn:placetype":[
        "aat:300000206"
    ]
},
  "bbox": [],
  "geometry": {"coordinates":[11.833333,50.583333],"type":"Point"}
}