{
  "id": 1066516,
  "type": "Feature",
  "properties": {
    "tgn:hierarchy":[
        "tgn:1066516",
        "tgn:1000004",
        "tgn:7002084",
        "tgn:1000111",
        "tgn:7029392"
    ],
    "tgn:id":1066516,
    "tgn:name":"Anbianbu",
    "tgn:placetype":[
        "aat:300008347"
    ]
},
  "bbox": [],
  "geometry": {"coordinates":[108.0667,37.5167],"type":"Point"}
}