{
  "id": 7111678,
  "type": "Feature",
  "properties": {
    "tgn:hierarchy":[
        "tgn:7111678",
        "tgn:1000003",
        "tgn:7003685",
        "tgn:7000084",
        "tgn:7029392"
    ],
    "tgn:id":7111678,
    "tgn:name":"Richters-H\u00fcgel",
    "tgn:placetype":[
        "aat:300008777"
    ]
},
  "bbox": [],
  "geometry": {"coordinates":[14.016667,50.916667],"type":"Point"}
}