{
  "id": 2664169,
  "type": "Feature",
  "properties": {
    "tgn:hierarchy":[
        "tgn:2664169",
        "tgn:1000001",
        "tgn:7012149",
        "tgn:2000183",
        "tgn:7007157",
        "tgn:7029392"
    ],
    "tgn:id":2664169,
    "tgn:name":"Silver Spear Mine",
    "tgn:placetype":[
        "aat:300000390"
    ]
},
  "bbox": [],
  "geometry": {"coordinates":[-117.7833,36.5333],"type":"Point"}
}