{
  "id": 2161447,
  "type": "Feature",
  "properties": {
    "tgn:hierarchy":[
        "tgn:2161447",
        "tgn:1000001",
        "tgn:7012149",
        "tgn:7007710",
        "tgn:7029392"
    ],
    "tgn:id":2161447,
    "tgn:name":"Bell Run",
    "tgn:placetype":[
        "aat:300008699"
    ]
},
  "bbox": [],
  "geometry": {"coordinates":[-78.1833,41.8833],"type":"Point"}
}