{
  "id": 2488104,
  "type": "Feature",
  "properties": {
    "tgn:hierarchy":[
        "tgn:2488104",
        "tgn:1000001",
        "tgn:7012149",
        "tgn:2001109",
        "tgn:7007522",
        "tgn:7029392"
    ],
    "tgn:id":2488104,
    "tgn:name":"Magnolia Bend",
    "tgn:placetype":[
        "aat:300132316"
    ]
},
  "bbox": [],
  "geometry": {"coordinates":[-88.9167,30.4167],"type":"Point"}
}