{
  "id": 2059032,
  "type": "Feature",
  "properties": {
    "tgn:hierarchy":[
        "tgn:2059032",
        "tgn:1000001",
        "tgn:2001176",
        "tgn:7012149",
        "tgn:7007523",
        "tgn:7029392"
    ],
    "tgn:id":2059032,
    "tgn:name":"Harviell",
    "tgn:placetype":[
        "aat:300008347"
    ]
},
  "bbox": [],
  "geometry": {"coordinates":[-90.4667,36.65],"type":"Point"}
}