{
  "id": 2183390,
  "type": "Feature",
  "properties": {
    "tgn:hierarchy":[
        "tgn:2183390",
        "tgn:2002140",
        "tgn:1000001",
        "tgn:7012149",
        "tgn:7007919",
        "tgn:7029392"
    ],
    "tgn:id":2183390,
    "tgn:name":"Bluff Creek",
    "tgn:placetype":[
        "aat:300008706"
    ]
},
  "bbox": [],
  "geometry": {"coordinates":[-79.3333,37.65],"type":"Point"}
}