{
  "id": 7268569,
  "type": "Feature",
  "properties": {
    "tgn:concordances":{
        "gn:id":"2747897"
    },
    "tgn:hierarchy":[
        "tgn:7268569",
        "tgn:7003616",
        "tgn:1000003",
        "tgn:7016845",
        "tgn:7029392"
    ],
    "tgn:id":7268569,
    "tgn:name:nl":"Rotsterhaule",
    "tgn:placetype":[
        "aat:300008347"
    ]
},
  "bbox": [],
  "geometry": {"coordinates":[5.85,52.933333],"type":"Point"}
}