{
  "id": 2199219,
  "type": "Feature",
  "properties": {
    "tgn:hierarchy":[
        "tgn:2199219",
        "tgn:1000001",
        "tgn:7012149",
        "tgn:2002350",
        "tgn:7007922",
        "tgn:7029392"
    ],
    "tgn:id":2199219,
    "tgn:name":"Bruno Lake",
    "tgn:placetype":[
        "aat:300008680"
    ]
},
  "bbox": [],
  "geometry": {"coordinates":[-91.0833,45.4833],"type":"Point"}
}