{
  "id": 2531064,
  "type": "Feature",
  "properties": {
    "tgn:hierarchy":[
        "tgn:2531064",
        "tgn:1000001",
        "tgn:2000540",
        "tgn:7012149",
        "tgn:7007252",
        "tgn:7029392"
    ],
    "tgn:id":2531064,
    "tgn:name":"Muir Lake",
    "tgn:placetype":[
        "aat:300008680"
    ]
},
  "bbox": [],
  "geometry": {"coordinates":[-87.1167,39.1667],"type":"Point"}
}