{
  "id": 7290903,
  "type": "Feature",
  "properties": {
    "tgn:hierarchy":[
        "tgn:7290903",
        "tgn:1001657",
        "tgn:1000049",
        "tgn:1000002",
        "tgn:7029392"
    ],
    "tgn:id":7290903,
    "tgn:name":"Deseada, Punta",
    "tgn:placetype":[
        "aat:300386846"
    ]
},
  "bbox": [],
  "geometry": {"coordinates":[-71.65,-30.266667],"type":"Point"}
}