{
  "id": 2397232,
  "type": "Feature",
  "properties": {
    "tgn:hierarchy":[
        "tgn:2397232",
        "tgn:1000001",
        "tgn:7012149",
        "tgn:2001453",
        "tgn:7007566",
        "tgn:7029392"
    ],
    "tgn:id":2397232,
    "tgn:name":"Hondo Tank",
    "tgn:placetype":[
        "aat:300006191"
    ]
},
  "bbox": [],
  "geometry": {"coordinates":[-103.9167,35.2333],"type":"Point"}
}