{
  "id": 7515065,
  "type": "Feature",
  "properties": {
    "tgn:hierarchy":[
        "tgn:7515065",
        "tgn:1009227",
        "tgn:1000226",
        "tgn:7018437",
        "tgn:1000006",
        "tgn:7029392"
    ],
    "tgn:id":7515065,
    "tgn:name:en":"Camp Hill",
    "tgn:placetype":[
        "aat:300008795"
    ]
},
  "bbox": [],
  "geometry": {"coordinates":[168.416667,-44.75],"type":"Point"}
}