{
  "id": 7285926,
  "type": "Feature",
  "properties": {
    "tgn:hierarchy":[
        "tgn:7285926",
        "tgn:1001708",
        "tgn:1000049",
        "tgn:1000002",
        "tgn:7029392"
    ],
    "tgn:id":7285926,
    "tgn:name":"Quebrada de Las Higueras",
    "tgn:placetype":[
        "aat:300387200"
    ]
},
  "bbox": [],
  "geometry": {"coordinates":[-71.116667,-33.566667],"type":"Point"}
}