{
  "id": 1076019,
  "type": "Feature",
  "properties": {
    "tgn:hierarchy":[
        "tgn:1076019",
        "tgn:1000004",
        "tgn:7000198",
        "tgn:1001977",
        "tgn:7029392"
    ],
    "tgn:id":1076019,
    "tgn:name:en":"Lakshmis\u0101gar",
    "tgn:placetype":[
        "aat:300008347"
    ]
},
  "bbox": [],
  "geometry": {"coordinates":[87.013747,22.927437],"type":"Point"}
}