{
  "id": 7229768,
  "type": "Feature",
  "properties": {
    "tgn:hierarchy":[
        "tgn:7229768",
        "tgn:7011170",
        "tgn:7002715",
        "tgn:1000003",
        "tgn:1000074",
        "tgn:7029392"
    ],
    "tgn:id":7229768,
    "tgn:name":"K\u00edknos",
    "tgn:placetype":[
        "aat:300008347"
    ]
},
  "bbox": [],
  "geometry": {"coordinates":[24.866667,41.266667],"type":"Point"}
}