{
  "id": 2708491,
  "type": "Feature",
  "properties": {
    "tgn:hierarchy":[
        "tgn:2708491",
        "tgn:1000001",
        "tgn:7006451",
        "tgn:2000095",
        "tgn:7012149",
        "tgn:7029392"
    ],
    "tgn:id":2708491,
    "tgn:name":"Sycamore Gulch",
    "tgn:placetype":[
        "aat:300008761"
    ]
},
  "bbox": [],
  "geometry": {"coordinates":[-109.3167,33.15],"type":"Point"}
}