{
  "id": 1099034,
  "type": "Feature",
  "properties": {
    "tgn:hierarchy":[
        "tgn:1099034",
        "tgn:1009227",
        "tgn:1000226",
        "tgn:7018437",
        "tgn:1000006",
        "tgn:7029392"
    ],
    "tgn:id":1099034,
    "tgn:name:en":"Maheno",
    "tgn:placetype":[
        "aat:300008347"
    ]
},
  "bbox": [],
  "geometry": {"coordinates":[170.833333,-45.166667],"type":"Point"}
}