{
  "id": 2336806,
  "type": "Feature",
  "properties": {
    "tgn:hierarchy":[
        "tgn:2336806",
        "tgn:1000001",
        "tgn:7012149",
        "tgn:2000487",
        "tgn:7007250",
        "tgn:7029392"
    ],
    "tgn:id":2336806,
    "tgn:name":"Fourmile Canyon",
    "tgn:placetype":[
        "aat:300008761"
    ]
},
  "bbox": [],
  "geometry": {"coordinates":[-112.1667,42.1333],"type":"Point"}
}