<<<<<<< HEAD
{
  "id": 2708325,
  "type": "Feature",
  "properties": {
    "tgn:hierarchy":[
        "tgn:2708325",
        "tgn:1000001",
        "tgn:2002106",
        "tgn:7012149",
        "tgn:7007827",
        "tgn:7029392"
    ],
    "tgn:id":2708325,
    "tgn:name":"Sycamore",
    "tgn:placetype":[
        "aat:300008347"
    ]
},
  "bbox": [],
  "geometry": {"coordinates":[-111.9,40.8333],"type":"Point"}
}
=======
{"geometry":{"type":"Point","coordinates":[-111.900000,40.833300]},"type":"Feature","properties":{"hierarchy":["tgn:2708325","tgn:1000001","tgn:2002106","tgn:7012149","tgn:7007827","tgn:7029392"],"placetype":["aat:300008347"],"id":2708325,"name:xx":"Sycamore"}}
>>>>>>> 03f74aca74312dbeaf24d7e61306dd6a786dc3d0
