{
  "id": 7567692,
  "type": "Feature",
  "properties": {
    "tgn:hierarchy":[
        "tgn:7567692",
        "tgn:1000004",
        "tgn:7000198",
        "tgn:1001996",
        "tgn:7029392"
    ],
    "tgn:id":7567692,
    "tgn:name:en":"Sainjri",
    "tgn:placetype":[
        "aat:300008347"
    ]
},
  "bbox": [],
  "geometry": {"coordinates":[77.049444,31.239722],"type":"Point"}
}