{
  "id": 7532676,
  "type": "Feature",
  "properties": {
    "tgn:hierarchy":[
        "tgn:7532676",
        "tgn:7001242",
        "tgn:7016833",
        "tgn:1001123",
        "tgn:7029392"
    ],
    "tgn:id":7532676,
    "tgn:name":"Daww\u0101sah, Jaz\u012brat",
    "tgn:placetype":[
        "aat:300008791"
    ]
},
  "bbox": [],
  "geometry": {"coordinates":[32.132767,31.280451],"type":"Point"}
}