{
  "id": 7141860,
  "type": "Feature",
  "properties": {
    "tgn:hierarchy":[
        "tgn:7141860",
        "tgn:1000003",
        "tgn:7003685",
        "tgn:7000084",
        "tgn:7029392"
    ],
    "tgn:id":7141860,
    "tgn:name":"Speicherbecken Lohsa",
    "tgn:placetype":[
        "aat:300006191"
    ]
},
  "bbox": [],
  "geometry": {"coordinates":[14.383333,51.383333],"type":"Point"}
}