{
  "id": 2753661,
  "type": "Feature",
  "properties": {
    "tgn:hierarchy":[
        "tgn:2753661",
        "tgn:1000001",
        "tgn:7012149",
        "tgn:2001851",
        "tgn:7007825",
        "tgn:7029392"
    ],
    "tgn:id":2753661,
    "tgn:name":"Watertank Hollow",
    "tgn:placetype":[
        "aat:300008761"
    ]
},
  "bbox": [],
  "geometry": {"coordinates":[-82.9167,35.9167],"type":"Point"}
}