{
  "id": 7463095,
  "type": "Feature",
  "properties": {
    "tgn:hierarchy":[
        "tgn:7463095",
        "tgn:7002445",
        "tgn:1000003",
        "tgn:7008134",
        "tgn:7008591",
        "tgn:7029392"
    ],
    "tgn:id":7463095,
    "tgn:name:en":"Kingston",
    "tgn:placetype":[
        "aat:300008347"
    ]
},
  "bbox": [],
  "geometry": {"coordinates":[-0.45,50.783333],"type":"Point"}
}