{
  "id": 2470995,
  "type": "Feature",
  "properties": {
    "tgn:hierarchy":[
        "tgn:2470995",
        "tgn:1000001",
        "tgn:7012149",
        "tgn:1002440",
        "tgn:7007568",
        "tgn:7029392"
    ],
    "tgn:id":2470995,
    "tgn:name":"Lost Creek",
    "tgn:placetype":[
        "aat:300008706"
    ]
},
  "bbox": [],
  "geometry": {"coordinates":[-74.2167,43.5333],"type":"Point"}
}