<<<<<<< HEAD
{
  "id": 7487587,
  "type": "Feature",
  "properties": {
    "tgn:hierarchy":[
        "tgn:7487587",
        "tgn:1000004",
        "tgn:7001013",
        "tgn:1000141",
        "tgn:7029392"
    ],
    "tgn:id":7487587,
    "tgn:name":"Xucuo Gang",
    "tgn:placetype":[
        "aat:300008678"
    ]
},
  "bbox": [],
  "geometry": {"coordinates":[121.15,25.083333],"type":"Point"}
}
=======
{"geometry":{"type":"Point","coordinates":[121.150000,25.083333]},"type":"Feature","properties":{"hierarchy":["tgn:7487587","tgn:1000004","tgn:7001013","tgn:1000141","tgn:7029392"],"placetype":["aat:300008678"],"id":7487587,"name:xx":"Xucuo Gang"}}
>>>>>>> 03f74aca74312dbeaf24d7e61306dd6a786dc3d0
