{
  "id": 2411687,
  "type": "Feature",
  "properties": {
    "tgn:hierarchy":[
        "tgn:2411687",
        "tgn:1000001",
        "tgn:2001431",
        "tgn:7012149",
        "tgn:7007566",
        "tgn:7029392"
    ],
    "tgn:id":2411687,
    "tgn:name":"Indian Lake",
    "tgn:placetype":[
        "aat:300008680"
    ]
},
  "bbox": [],
  "geometry": {"coordinates":[-107.75,34.7833],"type":"Point"}
}