{
  "id": 2097496,
  "type": "Feature",
  "properties": {
    "tgn:hierarchy":[
        "tgn:2097496",
        "tgn:1000001",
        "tgn:2001795",
        "tgn:7012149",
        "tgn:7007713",
        "tgn:7029392"
    ],
    "tgn:id":2097496,
    "tgn:name":"Revillo",
    "tgn:placetype":[
        "aat:300008347"
    ]
},
  "bbox": [],
  "geometry": {"coordinates":[-96.5667,45.0167],"type":"Point"}
}