{
  "id": 2752351,
  "type": "Feature",
  "properties": {
    "tgn:hierarchy":[
        "tgn:2752351",
        "tgn:1000001",
        "tgn:7013375",
        "tgn:7012149",
        "tgn:1003020",
        "tgn:7007920",
        "tgn:7029392"
    ],
    "tgn:id":2752351,
    "tgn:name":"Washington Colony",
    "tgn:placetype":[
        "aat:300387241",
        "aat:300008347"
    ]
},
  "bbox": [],
  "geometry": {"coordinates":[-122.4667,48.75],"type":"Point"}
}