<<<<<<< HEAD
{
  "id": 7029906,
  "type": "Feature",
  "properties": {
    "tgn:hierarchy":[
        "tgn:7029906",
        "tgn:7002445",
        "tgn:1000003",
        "tgn:7008166",
        "tgn:7008591",
        "tgn:7029392"
    ],
    "tgn:id":7029906,
    "tgn:name:ang":"Carlentone",
    "tgn:placetype":[
        "aat:300008347",
        "aat:300008372"
    ]
},
  "bbox": [],
  "geometry": {"coordinates":[-2.05,53.933333],"type":"Point"}
}
=======
{"geometry":{"type":"Point","coordinates":[-2.050000,53.933333]},"type":"Feature","properties":{"hierarchy":["tgn:7029906","tgn:7002445","tgn:1000003","tgn:7008166","tgn:7008591","tgn:7029392"],"placetype":["aat:300008347","aat:300008372"],"id":7029906,"name:ang":"Carlentone"}}
>>>>>>> 03f74aca74312dbeaf24d7e61306dd6a786dc3d0
