{
  "id": 2431942,
  "type": "Feature",
  "properties": {
    "tgn:hierarchy":[
        "tgn:2431942",
        "tgn:7023902",
        "tgn:1000001",
        "tgn:7012149",
        "tgn:7007249",
        "tgn:7029392"
    ],
    "tgn:id":2431942,
    "tgn:name":"Kaumoali Gulch",
    "tgn:placetype":[
        "aat:300008761"
    ]
},
  "bbox": [],
  "geometry": {"coordinates":[-155.4333,19.9833],"type":"Point"}
}