<<<<<<< HEAD
{
  "id": 7245393,
  "type": "Feature",
  "properties": {
    "tgn:hierarchy":[
        "tgn:7245393",
        "tgn:7018238",
        "tgn:1000003",
        "tgn:1000063",
        "tgn:4012014",
        "tgn:7029392"
    ],
    "tgn:id":7245393,
    "tgn:name":"Ferme de l' Alf\u00e8re",
    "tgn:placetype":[
        "aat:300000206"
    ]
},
  "bbox": [],
  "geometry": {"coordinates":[4.5,50.633333],"type":"Point"}
}
=======
{"geometry":{"type":"Point","coordinates":[4.500000,50.633333]},"type":"Feature","properties":{"hierarchy":["tgn:7245393","tgn:7018238","tgn:1000003","tgn:1000063","tgn:4012014","tgn:7029392"],"placetype":["aat:300000206"],"id":7245393,"name:xx":"Ferme de l' Alf\u00e8re"}}
>>>>>>> 03f74aca74312dbeaf24d7e61306dd6a786dc3d0
