{
  "id": 2368957,
  "type": "Feature",
  "properties": {
    "tgn:hierarchy":[
        "tgn:2368957",
        "tgn:1000001",
        "tgn:7016172",
        "tgn:7012149",
        "tgn:2000155",
        "tgn:7029392"
    ],
    "tgn:id":2368957,
    "tgn:name":"Gum Branch",
    "tgn:placetype":[
        "aat:300008699"
    ]
},
  "bbox": [],
  "geometry": {"coordinates":[-93.3167,35.8667],"type":"Point"}
}