{
  "id": 7563003,
  "type": "Feature",
  "properties": {
    "tgn:hierarchy":[
        "tgn:7563003",
        "tgn:1000004",
        "tgn:7000198",
        "tgn:7016722",
        "tgn:7029392"
    ],
    "tgn:id":7563003,
    "tgn:name:en":"Harr\u0101chauki Purwa",
    "tgn:placetype":[
        "aat:300008347"
    ]
},
  "bbox": [],
  "geometry": {"coordinates":[79.8386,27.0739],"type":"Point"}
}