{
  "id": 2448514,
  "type": "Feature",
  "properties": {
    "tgn:hierarchy":[
        "tgn:2448514",
        "tgn:1000001",
        "tgn:7012149",
        "tgn:2000963",
        "tgn:7007520",
        "tgn:7029392"
    ],
    "tgn:id":2448514,
    "tgn:name":"Lily Creek",
    "tgn:placetype":[
        "aat:300008706"
    ]
},
  "bbox": [],
  "geometry": {"coordinates":[-88.5167,47.1833],"type":"Point"}
}