{
  "id": 7470363,
  "type": "Feature",
  "properties": {
    "tgn:hierarchy":[
        "tgn:7470363",
        "tgn:7001004",
        "tgn:1000004",
        "tgn:1000141",
        "tgn:7029392"
    ],
    "tgn:id":7470363,
    "tgn:name":"Hexing",
    "tgn:placetype":[
        "aat:300008347"
    ]
},
  "bbox": [],
  "geometry": {"coordinates":[120.520926,22.856962],"type":"Point"}
}