{
  "id": 1070441,
  "type": "Feature",
  "properties": {
    "tgn:hierarchy":[
        "tgn:1070441",
        "tgn:1000004",
        "tgn:7002087",
        "tgn:1000111",
        "tgn:7029392"
    ],
    "tgn:id":1070441,
    "tgn:name":"Mengtong",
    "tgn:placetype":[
        "aat:300008347"
    ]
},
  "bbox": [],
  "geometry": {"coordinates":[105.8833,30.7333],"type":"Point"}
}