{
  "id": 2342700,
  "type": "Feature",
  "properties": {
    "tgn:hierarchy":[
        "tgn:2342700",
        "tgn:7002659",
        "tgn:1000001",
        "tgn:7012149",
        "tgn:7021514",
        "tgn:7029392"
    ],
    "tgn:id":2342700,
    "tgn:name":"Funnel, The",
    "tgn:placetype":[
        "aat:300386845"
    ]
},
  "bbox": [],
  "geometry": {"coordinates":[-85.8333,34.35],"type":"Point"}
}