{
  "id": 1122684,
  "type": "Feature",
  "properties": {
    "tgn:hierarchy":[
        "tgn:1122684",
        "tgn:1000004",
        "tgn:7002076",
        "tgn:1000111",
        "tgn:7029392"
    ],
    "tgn:id":1122684,
    "tgn:name":"Changshan Gang",
    "tgn:placetype":[
        "aat:300008707"
    ]
},
  "bbox": [],
  "geometry": {"coordinates":[118.85,28.95],"type":"Point"}
}