{
  "id": 7556697,
  "type": "Feature",
  "properties": {
    "tgn:hierarchy":[
        "tgn:7556697",
        "tgn:1001828",
        "tgn:1000004",
        "tgn:7000198",
        "tgn:7029392"
    ],
    "tgn:id":7556697,
    "tgn:name:en":"P\u012bleru",
    "tgn:placetype":[
        "aat:300008347"
    ]
},
  "bbox": [],
  "geometry": {"coordinates":[78.933333,13.65],"type":"Point"}
}