{
  "id": 2211775,
  "type": "Feature",
  "properties": {
    "tgn:hierarchy":[
        "tgn:2211775",
        "tgn:1000001",
        "tgn:7012149",
        "tgn:7007568",
        "tgn:7029392"
    ],
    "tgn:id":2211775,
    "tgn:name":"Button Creek",
    "tgn:placetype":[
        "aat:300008706"
    ]
},
  "bbox": [],
  "geometry": {"coordinates":[-75.2833,42.8167],"type":"Point"}
}