{
  "id": 2041553,
  "type": "Feature",
  "properties": {
    "tgn:hierarchy":[
        "tgn:2041553",
        "tgn:1000001",
        "tgn:7012149",
        "tgn:2000844",
        "tgn:7007255",
        "tgn:7029392"
    ],
    "tgn:id":2041553,
    "tgn:name":"Sweeneyville",
    "tgn:placetype":[
        "aat:300008347",
        "aat:300387210"
    ]
},
  "bbox": [],
  "geometry": {"coordinates":[-85.3833,37.35],"type":"Point"}
}