{
  "id": 1046031,
  "type": "Feature",
  "properties": {
    "tgn:hierarchy":[
        "tgn:1046031",
        "tgn:7003167",
        "tgn:1000003",
        "tgn:7009760",
        "tgn:1000080",
        "tgn:7029392"
    ],
    "tgn:id":1046031,
    "tgn:name":"Piteglio",
    "tgn:placetype":[
        "aat:300008347"
    ]
},
  "bbox": [],
  "geometry": {"coordinates":[10.766667,44.016667],"type":"Point"}
}