{
  "id": 2243570,
  "type": "Feature",
  "properties": {
    "tgn:hierarchy":[
        "tgn:2243570",
        "tgn:1000001",
        "tgn:7012149",
        "tgn:2000437",
        "tgn:7007248",
        "tgn:7029392"
    ],
    "tgn:id":2243570,
    "tgn:name":"Cleghorn Spring",
    "tgn:placetype":[
        "aat:300008697"
    ]
},
  "bbox": [],
  "geometry": {"coordinates":[-85.1333,34.6833],"type":"Point"}
}