{
  "id": 1127375,
  "type": "Feature",
  "properties": {
    "tgn:hierarchy":[
        "tgn:1127375",
        "tgn:7001242",
        "tgn:7029392"
    ],
    "tgn:id":1127375,
    "tgn:name":"Moshaweng",
    "tgn:placetype":[
        "aat:300008707"
    ]
},
  "bbox": [],
  "geometry": {"coordinates":[22.8333,-26.5833],"type":"Point"}
}