{
  "id": 2605796,
  "type": "Feature",
  "properties": {
    "tgn:hierarchy":[
        "tgn:2605796",
        "tgn:1000001",
        "tgn:7012149",
        "tgn:2002353",
        "tgn:7007922",
        "tgn:7029392"
    ],
    "tgn:id":2605796,
    "tgn:name":"Rainbow Creek",
    "tgn:placetype":[
        "aat:300008706"
    ]
},
  "bbox": [],
  "geometry": {"coordinates":[-91.5167,45.95],"type":"Point"}
}