<<<<<<< HEAD
{
  "id": 2151796,
  "type": "Feature",
  "properties": {
    "tgn:hierarchy":[
        "tgn:2151796",
        "tgn:1000001",
        "tgn:7012149",
        "tgn:2001723",
        "tgn:7007708",
        "tgn:7029392"
    ],
    "tgn:id":2151796,
    "tgn:name":"Battle Ridge",
    "tgn:placetype":[
        "aat:300266640"
    ]
},
  "bbox": [],
  "geometry": {"coordinates":[-119.7,44.3],"type":"Point"}
}
=======
{"geometry":{"type":"Point","coordinates":[-119.700000,44.300000]},"type":"Feature","properties":{"hierarchy":["tgn:2151796","tgn:1000001","tgn:7012149","tgn:2001723","tgn:7007708","tgn:7029392"],"placetype":["aat:300266640"],"id":2151796,"name:xx":"Battle Ridge"}}
>>>>>>> 03f74aca74312dbeaf24d7e61306dd6a786dc3d0
