{
  "id": 7104020,
  "type": "Feature",
  "properties": {
    "tgn:hierarchy":[
        "tgn:7104020",
        "tgn:1000003",
        "tgn:7003678",
        "tgn:7000084",
        "tgn:7029392"
    ],
    "tgn:id":7104020,
    "tgn:name":"Schachen",
    "tgn:placetype":[
        "aat:300008347"
    ]
},
  "bbox": [],
  "geometry": {"coordinates":[9.916667,50.466667],"type":"Point"}
}