{
  "id": 7246880,
  "type": "Feature",
  "properties": {
    "tgn:hierarchy":[
        "tgn:7246880",
        "tgn:7003456",
        "tgn:1000003",
        "tgn:1000063",
        "tgn:7018236",
        "tgn:7029392"
    ],
    "tgn:id":7246880,
    "tgn:name":"Boterstraat",
    "tgn:placetype":[
        "aat:300008347"
    ]
},
  "bbox": [],
  "geometry": {"coordinates":[4.683333,50.983333],"type":"Point"}
}