<<<<<<< HEAD
{
  "id": 2704593,
  "type": "Feature",
  "properties": {
    "tgn:hierarchy":[
        "tgn:2704593",
        "tgn:1000001",
        "tgn:7006451",
        "tgn:7012149",
        "tgn:2000103",
        "tgn:7029392"
    ],
    "tgn:id":2704593,
    "tgn:name":"Sunrise Peak",
    "tgn:placetype":[
        "aat:300008798"
    ]
},
  "bbox": [],
  "geometry": {"coordinates":[-113.2333,34.9333],"type":"Point"}
}
=======
{"geometry":{"type":"Point","coordinates":[-113.233300,34.933300]},"type":"Feature","properties":{"hierarchy":["tgn:2704593","tgn:1000001","tgn:7006451","tgn:7012149","tgn:2000103","tgn:7029392"],"placetype":["aat:300008798"],"id":2704593,"name:xx":"Sunrise Peak"}}
>>>>>>> 03f74aca74312dbeaf24d7e61306dd6a786dc3d0
