{
  "id": 2739250,
  "type": "Feature",
  "properties": {
    "tgn:hierarchy":[
        "tgn:2739250",
        "tgn:1000001",
        "tgn:7012149",
        "tgn:2001148",
        "tgn:7007522",
        "tgn:7029392"
    ],
    "tgn:id":2739250,
    "tgn:name":"Updike",
    "tgn:placetype":[
        "aat:300008347"
    ]
},
  "bbox": [],
  "geometry": {"coordinates":[-90.7667,33.05],"type":"Point"}
}