{
  "id": 2388514,
  "type": "Feature",
  "properties": {
    "tgn:hierarchy":[
        "tgn:2388514",
        "tgn:7002659",
        "tgn:1000001",
        "tgn:7012149",
        "tgn:7021514",
        "tgn:7029392"
    ],
    "tgn:id":2388514,
    "tgn:name":"Hicks Creek",
    "tgn:placetype":[
        "aat:300008706"
    ]
},
  "bbox": [],
  "geometry": {"coordinates":[-85.7333,34.3833],"type":"Point"}
}