<<<<<<< HEAD
{
  "id": 7355713,
  "type": "Feature",
  "properties": {
    "tgn:hierarchy":[
        "tgn:7355713",
        "tgn:7005581",
        "tgn:1000001",
        "tgn:7005560",
        "tgn:7029392"
    ],
    "tgn:id":7355713,
    "tgn:name":"Cerocahui, Arroyo",
    "tgn:placetype":[
        "aat:300008699"
    ]
},
  "bbox": [],
  "geometry": {"coordinates":[-108.233333,27.283333],"type":"Point"}
}
=======
{"geometry":{"type":"Point","coordinates":[-108.233333,27.283333]},"type":"Feature","properties":{"hierarchy":["tgn:7355713","tgn:7005581","tgn:1000001","tgn:7005560","tgn:7029392"],"placetype":["aat:300008699"],"id":7355713,"name:xx":"Cerocahui, Arroyo"}}
>>>>>>> 03f74aca74312dbeaf24d7e61306dd6a786dc3d0
