{
  "id": 2103746,
  "type": "Feature",
  "properties": {
    "tgn:hierarchy":[
        "tgn:2103746",
        "tgn:1000001",
        "tgn:7012149",
        "tgn:2001949",
        "tgn:7007826",
        "tgn:7029392"
    ],
    "tgn:id":2103746,
    "tgn:name":"Demarco",
    "tgn:placetype":[
        "aat:300387016"
    ]
},
  "bbox": [],
  "geometry": {"coordinates":[-98.25,30.6833],"type":"Point"}
}