{
  "id": 2077476,
  "type": "Feature",
  "properties": {
    "tgn:hierarchy":[
        "tgn:2077476",
        "tgn:1000001",
        "tgn:2001599",
        "tgn:7012149",
        "tgn:7007705",
        "tgn:7029392"
    ],
    "tgn:id":2077476,
    "tgn:name":"Cannon Ball",
    "tgn:placetype":[
        "aat:300008347"
    ]
},
  "bbox": [],
  "geometry": {"coordinates":[-100.5833,46.3833],"type":"Point"}
}