{
  "id": 7280229,
  "type": "Feature",
  "properties": {
    "tgn:hierarchy":[
        "tgn:7280229",
        "tgn:1001768",
        "tgn:1000049",
        "tgn:1000002",
        "tgn:7029392"
    ],
    "tgn:id":7280229,
    "tgn:name":"Quisco, Caleta",
    "tgn:placetype":[
        "aat:300132317"
    ]
},
  "bbox": [],
  "geometry": {"coordinates":[-71.716667,-33.383333],"type":"Point"}
}