{
  "id": 2134693,
  "type": "Feature",
  "properties": {
    "tgn:hierarchy":[
        "tgn:2134693",
        "tgn:1000001",
        "tgn:7012149",
        "tgn:7020792",
        "tgn:7007524",
        "tgn:7029392"
    ],
    "tgn:id":2134693,
    "tgn:name":"Antelope Creek",
    "tgn:placetype":[
        "aat:300008706"
    ]
},
  "bbox": [],
  "geometry": {"coordinates":[-112.95,46.2167],"type":"Point"}
}