{
  "id": 2269688,
  "type": "Feature",
  "properties": {
    "tgn:hierarchy":[
        "tgn:2269688",
        "tgn:1000001",
        "tgn:7012149",
        "tgn:7007158",
        "tgn:2000248",
        "tgn:7029392"
    ],
    "tgn:id":2269688,
    "tgn:name":"Crown Jewel Mine",
    "tgn:placetype":[
        "aat:300000390"
    ]
},
  "bbox": [],
  "geometry": {"coordinates":[-107.8333,37.8667],"type":"Point"}
}