{
  "id": 7560539,
  "type": "Feature",
  "properties": {
    "tgn:hierarchy":[
        "tgn:7560539",
        "tgn:1000004",
        "tgn:7000198",
        "tgn:7016788",
        "tgn:7029392"
    ],
    "tgn:id":7560539,
    "tgn:name:en":"Ajr\u0101jpura",
    "tgn:placetype":[
        "aat:300008347"
    ]
},
  "bbox": [],
  "geometry": {"coordinates":[75.601886,26.763583],"type":"Point"}
}