{
  "id": 7086475,
  "type": "Feature",
  "properties": {
    "tgn:hierarchy":[
        "tgn:7086475",
        "tgn:7003692",
        "tgn:1000003",
        "tgn:7000084",
        "tgn:7029392"
    ],
    "tgn:id":7086475,
    "tgn:name":"Wartenberg",
    "tgn:placetype":[
        "aat:300006891"
    ]
},
  "bbox": [],
  "geometry": {"coordinates":[8.616667,47.933333],"type":"Point"}
}