{
  "id": 7343007,
  "type": "Feature",
  "properties": {
    "tgn:hierarchy":[
        "tgn:7343007",
        "tgn:7001165",
        "tgn:1000003",
        "tgn:7002793",
        "tgn:1000095",
        "tgn:7029392"
    ],
    "tgn:id":7343007,
    "tgn:name":"Caser\u00edo Franchs",
    "tgn:placetype":[
        "aat:300008347"
    ]
},
  "bbox": [],
  "geometry": {"coordinates":[-0.466667,39.033333],"type":"Point"}
}