{
  "id": 7244591,
  "type": "Feature",
  "properties": {
    "tgn:hierarchy":[
        "tgn:7244591",
        "tgn:7003460",
        "tgn:1000003",
        "tgn:1000063",
        "tgn:4012014",
        "tgn:7029392"
    ],
    "tgn:id":7244591,
    "tgn:name":"La Vaux",
    "tgn:placetype":[
        "aat:300008347"
    ]
},
  "bbox": [],
  "geometry": {"coordinates":[5.633333,50.716667],"type":"Point"}
}