<<<<<<< HEAD
{
  "id": 7357639,
  "type": "Feature",
  "properties": {
    "tgn:hierarchy":[
        "tgn:7357639",
        "tgn:7005580",
        "tgn:1000001",
        "tgn:7005560",
        "tgn:7029392"
    ],
    "tgn:id":7357639,
    "tgn:name":"Cumbre, Cerra la",
    "tgn:placetype":[
        "aat:300008795"
    ]
},
  "bbox": [],
  "geometry": {"coordinates":[-92.966667,15.65],"type":"Point"}
}
=======
{"geometry":{"type":"Point","coordinates":[-92.966667,15.650000]},"type":"Feature","properties":{"hierarchy":["tgn:7357639","tgn:7005580","tgn:1000001","tgn:7005560","tgn:7029392"],"placetype":["aat:300008795"],"id":7357639,"name:xx":"Cumbre, Cerra la"}}
>>>>>>> 03f74aca74312dbeaf24d7e61306dd6a786dc3d0
