<<<<<<< HEAD
{
  "id": 7055881,
  "type": "Feature",
  "properties": {
    "tgn:hierarchy":[
        "tgn:7055881",
        "tgn:7003170",
        "tgn:1000003",
        "tgn:7003125",
        "tgn:1000080",
        "tgn:7029392"
    ],
    "tgn:id":7055881,
    "tgn:name":"Pistrino",
    "tgn:placetype":[
        "aat:300008347"
    ]
},
  "bbox": [],
  "geometry": {"coordinates":[12.15,43.516667],"type":"Point"}
}
=======
{"geometry":{"type":"Point","coordinates":[12.150000,43.516667]},"type":"Feature","properties":{"hierarchy":["tgn:7055881","tgn:7003170","tgn:1000003","tgn:7003125","tgn:1000080","tgn:7029392"],"placetype":["aat:300008347"],"id":7055881,"name:xx":"Pistrino"}}
>>>>>>> 03f74aca74312dbeaf24d7e61306dd6a786dc3d0
