{
  "id": 7405918,
  "type": "Feature",
  "properties": {
    "tgn:hierarchy":[
        "tgn:7405918",
        "tgn:7016644",
        "tgn:1000001",
        "tgn:7005560",
        "tgn:7029392"
    ],
    "tgn:id":7405918,
    "tgn:name":"Coyonque",
    "tgn:placetype":[
        "aat:300008347"
    ]
},
  "bbox": [],
  "geometry": {"coordinates":[-103.666667,19.380556],"type":"Point"}
}