{
  "id": 2590114,
  "type": "Feature",
  "properties": {
    "tgn:hierarchy":[
        "tgn:2590114",
        "tgn:1000001",
        "tgn:2000921",
        "tgn:7012149",
        "tgn:7007515",
        "tgn:7029392"
    ],
    "tgn:id":2590114,
    "tgn:name":"Poison Pond",
    "tgn:placetype":[
        "aat:300008680"
    ]
},
  "bbox": [],
  "geometry": {"coordinates":[-70.55,45.25],"type":"Point"}
}