<<<<<<< HEAD
{
  "id": 7177235,
  "type": "Feature",
  "properties": {
    "tgn:hierarchy":[
        "tgn:7177235",
        "tgn:1000003",
        "tgn:7000094",
        "tgn:7000084",
        "tgn:7029392"
    ],
    "tgn:id":7177235,
    "tgn:name":"Gustavshof",
    "tgn:placetype":[
        "aat:300000206"
    ]
},
  "bbox": [],
  "geometry": {"coordinates":[13.033333,53.933333],"type":"Point"}
}
=======
{"geometry":{"type":"Point","coordinates":[13.033333,53.933333]},"type":"Feature","properties":{"hierarchy":["tgn:7177235","tgn:1000003","tgn:7000094","tgn:7000084","tgn:7029392"],"placetype":["aat:300000206"],"id":7177235,"name:xx":"Gustavshof"}}
>>>>>>> 03f74aca74312dbeaf24d7e61306dd6a786dc3d0
