{
  "id": 2606070,
  "type": "Feature",
  "properties": {
    "tgn:hierarchy":[
        "tgn:2606070",
        "tgn:7002659",
        "tgn:1000001",
        "tgn:7012149",
        "tgn:2000035",
        "tgn:7029392"
    ],
    "tgn:id":2606070,
    "tgn:name":"Rainey Cave",
    "tgn:placetype":[
        "aat:300008746"
    ]
},
  "bbox": [],
  "geometry": {"coordinates":[-86.2667,34.6833],"type":"Point"}
}