{
  "id": 6002315,
  "type": "Feature",
  "properties": {
    "tgn:hierarchy":[
        "tgn:6002315",
        "tgn:1000003",
        "tgn:7003688",
        "tgn:7000084",
        "tgn:7029392"
    ],
    "tgn:id":6002315,
    "tgn:name":"Gottorp",
    "tgn:placetype":[
        "aat:300008347",
        "aat:300343603",
        "aat:300008375"
    ]
},
  "bbox": [],
  "geometry": {"coordinates":[9.55,54.5167],"type":"Point"}
}