<<<<<<< HEAD
{
  "id": 7059034,
  "type": "Feature",
  "properties": {
    "tgn:hierarchy":[
        "tgn:7059034",
        "tgn:7003158",
        "tgn:1000003",
        "tgn:7003124",
        "tgn:1000080",
        "tgn:7029392"
    ],
    "tgn:id":7059034,
    "tgn:name":"Albaredo",
    "tgn:placetype":[
        "aat:300008347"
    ]
},
  "bbox": [],
  "geometry": {"coordinates":[11.05,45.85],"type":"Point"}
}
=======
{"geometry":{"type":"Point","coordinates":[11.050000,45.850000]},"type":"Feature","properties":{"hierarchy":["tgn:7059034","tgn:7003158","tgn:1000003","tgn:7003124","tgn:1000080","tgn:7029392"],"placetype":["aat:300008347"],"id":7059034,"name:xx":"Albaredo"}}
>>>>>>> 03f74aca74312dbeaf24d7e61306dd6a786dc3d0
