{
  "id": 7592867,
  "type": "Feature",
  "properties": {
    "tgn:hierarchy":[
        "tgn:7592867",
        "tgn:1000004",
        "tgn:7000198",
        "tgn:7000799",
        "tgn:7029392"
    ],
    "tgn:id":7592867,
    "tgn:name:en":"Mang\u0101ni",
    "tgn:placetype":[
        "aat:300008347"
    ]
},
  "bbox": [],
  "geometry": {"coordinates":[74.395614,33.076759],"type":"Point"}
}