{
  "id": 2436829,
  "type": "Feature",
  "properties": {
    "tgn:hierarchy":[
        "tgn:2436829",
        "tgn:1000001",
        "tgn:7012149",
        "tgn:2002184",
        "tgn:7007919",
        "tgn:7029392"
    ],
    "tgn:id":2436829,
    "tgn:name":"Kilbys Creek",
    "tgn:placetype":[
        "aat:300008706"
    ]
},
  "bbox": [],
  "geometry": {"coordinates":[-78.25,38.5667],"type":"Point"}
}