{
  "id": 2476793,
  "type": "Feature",
  "properties": {
    "tgn:hierarchy":[
        "tgn:2476793",
        "tgn:1000001",
        "tgn:7006451",
        "tgn:2000092",
        "tgn:7012149",
        "tgn:7029392"
    ],
    "tgn:id":2476793,
    "tgn:name":"Lyell Butte",
    "tgn:placetype":[
        "aat:300008798"
    ]
},
  "bbox": [],
  "geometry": {"coordinates":[-112.0167,36.0333],"type":"Point"}
}