<<<<<<< HEAD
{
  "id": 7171015,
  "type": "Feature",
  "properties": {
    "tgn:hierarchy":[
        "tgn:7171015",
        "tgn:1000003",
        "tgn:7003685",
        "tgn:7000084",
        "tgn:7029392"
    ],
    "tgn:id":7171015,
    "tgn:name":"Hengst-Berg",
    "tgn:placetype":[
        "aat:300008777"
    ]
},
  "bbox": [],
  "geometry": {"coordinates":[14.766667,51.116667],"type":"Point"}
}
=======
{"geometry":{"type":"Point","coordinates":[14.766667,51.116667]},"type":"Feature","properties":{"hierarchy":["tgn:7171015","tgn:1000003","tgn:7003685","tgn:7000084","tgn:7029392"],"placetype":["aat:300008777"],"id":7171015,"name:xx":"Hengst-Berg"}}
>>>>>>> 03f74aca74312dbeaf24d7e61306dd6a786dc3d0
