{
  "id": 2351550,
  "type": "Feature",
  "properties": {
    "tgn:hierarchy":[
        "tgn:2351550",
        "tgn:1000001",
        "tgn:7012149",
        "tgn:1002467",
        "tgn:7007919",
        "tgn:7029392"
    ],
    "tgn:id":2351550,
    "tgn:name":"Glenbrook Hills",
    "tgn:placetype":[
        "aat:300008347"
    ]
},
  "bbox": [],
  "geometry": {"coordinates":[-77.55,37.5667],"type":"Point"}
}