{
  "id": 2160230,
  "type": "Feature",
  "properties": {
    "tgn:hierarchy":[
        "tgn:2160230",
        "tgn:1002143",
        "tgn:1000001",
        "tgn:7012149",
        "tgn:7007252",
        "tgn:7029392"
    ],
    "tgn:id":2160230,
    "tgn:name":"Beedy Lake",
    "tgn:placetype":[
        "aat:300006191"
    ]
},
  "bbox": [],
  "geometry": {"coordinates":[-85.05,41.25],"type":"Point"}
}