{
  "id": 2270414,
  "type": "Feature",
  "properties": {
    "tgn:hierarchy":[
        "tgn:2270414",
        "tgn:1000001",
        "tgn:7012149",
        "tgn:2001279",
        "tgn:7007524",
        "tgn:7029392"
    ],
    "tgn:id":2270414,
    "tgn:name":"Crystal Lake",
    "tgn:placetype":[
        "aat:300008680"
    ]
},
  "bbox": [],
  "geometry": {"coordinates":[-113.15,46.3333],"type":"Point"}
}