{
  "id": 2317006,
  "type": "Feature",
  "properties": {
    "tgn:hierarchy":[
        "tgn:2317006",
        "tgn:1000001",
        "tgn:7012149",
        "tgn:2000226",
        "tgn:7007158",
        "tgn:7029392"
    ],
    "tgn:id":2317006,
    "tgn:name":"Emhaw Gulch",
    "tgn:placetype":[
        "aat:300008761"
    ]
},
  "bbox": [],
  "geometry": {"coordinates":[-105.35,40.3667],"type":"Point"}
}