<<<<<<< HEAD
{
  "id": 7375240,
  "type": "Feature",
  "properties": {
    "tgn:hierarchy":[
        "tgn:7375240",
        "tgn:7005583",
        "tgn:1000001",
        "tgn:7005560",
        "tgn:7029392"
    ],
    "tgn:id":7375240,
    "tgn:name":"Leona Vicario",
    "tgn:placetype":[
        "aat:300008347"
    ]
},
  "bbox": [],
  "geometry": {"coordinates":[-104.483333,24.7],"type":"Point"}
}
=======
{"geometry":{"type":"Point","coordinates":[-104.483333,24.700000]},"type":"Feature","properties":{"hierarchy":["tgn:7375240","tgn:7005583","tgn:1000001","tgn:7005560","tgn:7029392"],"placetype":["aat:300008347"],"id":7375240,"name:xx":"Leona Vicario"}}
>>>>>>> 03f74aca74312dbeaf24d7e61306dd6a786dc3d0
