{
  "id": 7319080,
  "type": "Feature",
  "properties": {
    "tgn:hierarchy":[
        "tgn:7319080",
        "tgn:1001708",
        "tgn:1000049",
        "tgn:1000002",
        "tgn:7029392"
    ],
    "tgn:id":7319080,
    "tgn:name":"Aparato, Loma del",
    "tgn:placetype":[
        "aat:300008777"
    ]
},
  "bbox": [],
  "geometry": {"coordinates":[-70.733333,-33.483333],"type":"Point"}
}