{
  "id": 2270520,
  "type": "Feature",
  "properties": {
    "tgn:hierarchy":[
        "tgn:2270520",
        "tgn:1000001",
        "tgn:7012149",
        "tgn:2002375",
        "tgn:7007923",
        "tgn:7029392"
    ],
    "tgn:id":2270520,
    "tgn:name":"Crystal Lake Reservoir",
    "tgn:placetype":[
        "aat:300006191"
    ]
},
  "bbox": [],
  "geometry": {"coordinates":[-105.1833,41.15],"type":"Point"}
}