<<<<<<< HEAD
{
  "id": 2335259,
  "type": "Feature",
  "properties": {
    "tgn:hierarchy":[
        "tgn:2335259",
        "tgn:1000001",
        "tgn:7012149",
        "tgn:1002441",
        "tgn:7007706",
        "tgn:7029392"
    ],
    "tgn:id":2335259,
    "tgn:name":"Fort Gass",
    "tgn:placetype":[
        "aat:300008347"
    ]
},
  "bbox": [],
  "geometry": {"coordinates":[-84.7833,39.2167],"type":"Point"}
}
=======
{"geometry":{"type":"Point","coordinates":[-84.783300,39.216700]},"type":"Feature","properties":{"hierarchy":["tgn:2335259","tgn:1000001","tgn:7012149","tgn:1002441","tgn:7007706","tgn:7029392"],"placetype":["aat:300008347"],"id":2335259,"name:xx":"Fort Gass"}}
>>>>>>> 03f74aca74312dbeaf24d7e61306dd6a786dc3d0
