{
  "id": 7081679,
  "type": "Feature",
  "properties": {
    "tgn:hierarchy":[
        "tgn:7081679",
        "tgn:1000003",
        "tgn:7000094",
        "tgn:7000084",
        "tgn:7029392"
    ],
    "tgn:id":7081679,
    "tgn:name":"Wollkuhl",
    "tgn:placetype":[
        "aat:300132317"
    ]
},
  "bbox": [],
  "geometry": {"coordinates":[12.15,54.183333],"type":"Point"}
}