{
  "id": 7245979,
  "type": "Feature",
  "properties": {
    "tgn:hierarchy":[
        "tgn:7245979",
        "tgn:7003466",
        "tgn:1000003",
        "tgn:1000063",
        "tgn:4012014",
        "tgn:7029392"
    ],
    "tgn:id":7245979,
    "tgn:name":"Boninne",
    "tgn:placetype":[
        "aat:300008347"
    ]
},
  "bbox": [],
  "geometry": {"coordinates":[4.933579,50.496491],"type":"Point"}
}