<<<<<<< HEAD
{
  "id": 7059112,
  "type": "Feature",
  "properties": {
    "tgn:hierarchy":[
        "tgn:7059112",
        "tgn:1000003",
        "tgn:7003151",
        "tgn:7003237",
        "tgn:1000080",
        "tgn:7029392"
    ],
    "tgn:id":7059112,
    "tgn:name":"Agogna, Torrente",
    "tgn:placetype":[
        "aat:300008699"
    ]
},
  "bbox": [],
  "geometry": {"coordinates":[8.9,45.066667],"type":"Point"}
}
=======
{"geometry":{"type":"Point","coordinates":[8.900000,45.066667]},"type":"Feature","properties":{"hierarchy":["tgn:7059112","tgn:1000003","tgn:7003151","tgn:7003237","tgn:1000080","tgn:7029392"],"placetype":["aat:300008699"],"id":7059112,"name:xx":"Agogna, Torrente"}}
>>>>>>> 03f74aca74312dbeaf24d7e61306dd6a786dc3d0
