{
  "id": 1035011,
  "type": "Feature",
  "properties": {
    "tgn:hierarchy":[
        "tgn:1035011",
        "tgn:1000003",
        "tgn:1000070",
        "tgn:7002897",
        "tgn:7029392"
    ],
    "tgn:id":1035011,
    "tgn:name":"Queige",
    "tgn:placetype":[
        "aat:300008347"
    ]
},
  "bbox": [],
  "geometry": {"coordinates":[6.4667,45.7167],"type":"Point"}
}