{
  "id": 2607239,
  "type": "Feature",
  "properties": {
    "tgn:hierarchy":[
        "tgn:2607239",
        "tgn:1000001",
        "tgn:7012149",
        "tgn:1002797",
        "tgn:7007706",
        "tgn:7029392"
    ],
    "tgn:id":2607239,
    "tgn:name":"Randolph Ditch",
    "tgn:placetype":[
        "aat:300006075"
    ]
},
  "bbox": [],
  "geometry": {"coordinates":[-81.2333,41.0167],"type":"Point"}
}