<<<<<<< HEAD
{
  "id": 2766639,
  "type": "Feature",
  "properties": {
    "tgn:hierarchy":[
        "tgn:2766639",
        "tgn:2000918",
        "tgn:1000001",
        "tgn:7012149",
        "tgn:7007515",
        "tgn:7029392"
    ],
    "tgn:id":2766639,
    "tgn:name":"White Oak Hill",
    "tgn:placetype":[
        "aat:300008798"
    ]
},
  "bbox": [],
  "geometry": {"coordinates":[-70.4,44.0333],"type":"Point"}
}
=======
{"geometry":{"type":"Point","coordinates":[-70.400000,44.033300]},"type":"Feature","properties":{"hierarchy":["tgn:2766639","tgn:2000918","tgn:1000001","tgn:7012149","tgn:7007515","tgn:7029392"],"placetype":["aat:300008798"],"id":2766639,"name:xx":"White Oak Hill"}}
>>>>>>> 03f74aca74312dbeaf24d7e61306dd6a786dc3d0
