{
  "id": 2160369,
  "type": "Feature",
  "properties": {
    "tgn:hierarchy":[
        "tgn:2160369",
        "tgn:1000001",
        "tgn:7012149",
        "tgn:7007157",
        "tgn:1002791",
        "tgn:7029392"
    ],
    "tgn:id":2160369,
    "tgn:name":"Beeks Bight",
    "tgn:placetype":[
        "aat:300132316"
    ]
},
  "bbox": [],
  "geometry": {"coordinates":[-121.1167,38.7667],"type":"Point"}
}