{
  "id": 6004859,
  "type": "Feature",
  "properties": {
    "tgn:hierarchy":[
        "tgn:6004859",
        "tgn:1000004",
        "tgn:1001130",
        "tgn:1000118",
        "tgn:7029392"
    ],
    "tgn:id":6004859,
    "tgn:name":"Pumbedita",
    "tgn:placetype":[
        "aat:300008347",
        "aat:300167671",
        "aat:300264742"
    ]
},
  "bbox": [],
  "geometry": {"coordinates":[43.786111,33.351111],"type":"Point"}
}