{
  "id": 7460252,
  "type": "Feature",
  "properties": {
    "tgn:hierarchy":[
        "tgn:7460252",
        "tgn:7002444",
        "tgn:1000003",
        "tgn:7008082",
        "tgn:7008591",
        "tgn:7029392"
    ],
    "tgn:id":7460252,
    "tgn:name:en":"Lochluichart Lodge",
    "tgn:placetype":[
        "aat:300004792"
    ]
},
  "bbox": [],
  "geometry": {"coordinates":[-4.766667,57.633333],"type":"Point"}
}