<<<<<<< HEAD
{
  "id": 2406308,
  "type": "Feature",
  "properties": {
    "tgn:hierarchy":[
        "tgn:2406308",
        "tgn:7023902",
        "tgn:1000001",
        "tgn:7012149",
        "tgn:7007249",
        "tgn:7029392"
    ],
    "tgn:id":2406308,
    "tgn:name":"Humuhumu Point",
    "tgn:placetype":[
        "aat:300008850"
    ]
},
  "bbox": [],
  "geometry": {"coordinates":[-155.8333,19.0167],"type":"Point"}
}
=======
{"geometry":{"type":"Point","coordinates":[-155.833300,19.016700]},"type":"Feature","properties":{"hierarchy":["tgn:2406308","tgn:7023902","tgn:1000001","tgn:7012149","tgn:7007249","tgn:7029392"],"placetype":["aat:300008850"],"id":2406308,"name:xx":"Humuhumu Point"}}
>>>>>>> 03f74aca74312dbeaf24d7e61306dd6a786dc3d0
