{
  "id": 7374309,
  "type": "Feature",
  "properties": {
    "tgn:hierarchy":[
        "tgn:7374309",
        "tgn:1001835",
        "tgn:1000001",
        "tgn:7005560",
        "tgn:7029392"
    ],
    "tgn:id":7374309,
    "tgn:name":"Rancho La Bisnaga",
    "tgn:placetype":[
        "aat:300000241"
    ]
},
  "bbox": [],
  "geometry": {"coordinates":[-116.083333,31.616667],"type":"Point"}
}