{
  "id": 2482189,
  "type": "Feature",
  "properties": {
    "tgn:hierarchy":[
        "tgn:2482189",
        "tgn:1000001",
        "tgn:1002261",
        "tgn:7012149",
        "tgn:7007568",
        "tgn:7029392"
    ],
    "tgn:id":2482189,
    "tgn:name":"Langdon Hill",
    "tgn:placetype":[
        "aat:300008798"
    ]
},
  "bbox": [],
  "geometry": {"coordinates":[-76.6833,42.15],"type":"Point"}
}