{
  "id": 1046913,
  "type": "Feature",
  "properties": {
    "tgn:hierarchy":[
        "tgn:1046913",
        "tgn:1003428",
        "tgn:1000003",
        "tgn:7003120",
        "tgn:1000080",
        "tgn:7029392"
    ],
    "tgn:id":1046913,
    "tgn:name":"Silvano d'Orba",
    "tgn:placetype":[
        "aat:300008347"
    ]
},
  "bbox": [],
  "geometry": {"coordinates":[8.666667,44.683333],"type":"Point"}
}