{
  "id": 2030468,
  "type": "Feature",
  "properties": {
    "tgn:hierarchy":[
        "tgn:2030468",
        "tgn:1000001",
        "tgn:7012149",
        "tgn:7013855",
        "tgn:7007251",
        "tgn:7029392"
    ],
    "tgn:id":2030468,
    "tgn:name":"Upton",
    "tgn:placetype":[
        "aat:300387016"
    ]
},
  "bbox": [],
  "geometry": {"coordinates":[-87.8167,42.3667],"type":"Point"}
}