{
  "id": 7229949,
  "type": "Feature",
  "properties": {
    "tgn:hierarchy":[
        "tgn:7229949",
        "tgn:7002690",
        "tgn:7012056",
        "tgn:1000003",
        "tgn:1000074",
        "tgn:7029392"
    ],
    "tgn:id":7229949,
    "tgn:name":"Meg\u00e1li Kerat\u00e9",
    "tgn:placetype":[
        "aat:300008777"
    ]
},
  "bbox": [],
  "geometry": {"coordinates":[24.183333,35.533333],"type":"Point"}
}