{
  "id": 2144266,
  "type": "Feature",
  "properties": {
    "tgn:hierarchy":[
        "tgn:2144266",
        "tgn:1000001",
        "tgn:2000920",
        "tgn:7012149",
        "tgn:7007515",
        "tgn:7029392"
    ],
    "tgn:id":2144266,
    "tgn:name":"Baker Mountain",
    "tgn:placetype":[
        "aat:300008798"
    ]
},
  "bbox": [],
  "geometry": {"coordinates":[-70.3667,43.8167],"type":"Point"}
}