{
  "id": 7408382,
  "type": "Feature",
  "properties": {
    "tgn:hierarchy":[
        "tgn:7408382",
        "tgn:1000001",
        "tgn:7005590",
        "tgn:7005560",
        "tgn:7029392"
    ],
    "tgn:id":7408382,
    "tgn:name":"Apatzing\u00e1n, R\u00edo",
    "tgn:placetype":[
        "aat:300008699"
    ]
},
  "bbox": [],
  "geometry": {"coordinates":[-102.3625,19.079167],"type":"Point"}
}