{
  "id": 2428757,
  "type": "Feature",
  "properties": {
    "tgn:hierarchy":[
        "tgn:2428757",
        "tgn:1000001",
        "tgn:7012149",
        "tgn:1002742",
        "tgn:7007920",
        "tgn:7029392"
    ],
    "tgn:id":2428757,
    "tgn:name":"July Creek",
    "tgn:placetype":[
        "aat:300008706"
    ]
},
  "bbox": [],
  "geometry": {"coordinates":[-120.0667,48.7333],"type":"Point"}
}