{
  "id": 7056413,
  "type": "Feature",
  "properties": {
    "tgn:hierarchy":[
        "tgn:7056413",
        "tgn:1003440",
        "tgn:1000003",
        "tgn:7003124",
        "tgn:1000080",
        "tgn:7029392"
    ],
    "tgn:id":7056413,
    "tgn:name":"Grosser M\u00f6sele",
    "tgn:placetype":[
        "aat:300008795"
    ]
},
  "bbox": [],
  "geometry": {"coordinates":[11.783333,46.983333],"type":"Point"}
}