<<<<<<< HEAD
{
  "id": 2254553,
  "type": "Feature",
  "properties": {
    "tgn:hierarchy":[
        "tgn:2254553",
        "tgn:7002659",
        "tgn:1000001",
        "tgn:7012149",
        "tgn:2000036",
        "tgn:7029392"
    ],
    "tgn:id":2254553,
    "tgn:name":"Coon Hollow",
    "tgn:placetype":[
        "aat:300008761"
    ]
},
  "bbox": [],
  "geometry": {"coordinates":[-87.2333,33.4667],"type":"Point"}
}
=======
{"geometry":{"type":"Point","coordinates":[-87.233300,33.466700]},"type":"Feature","properties":{"hierarchy":["tgn:2254553","tgn:7002659","tgn:1000001","tgn:7012149","tgn:2000036","tgn:7029392"],"placetype":["aat:300008761"],"id":2254553,"name:xx":"Coon Hollow"}}
>>>>>>> 03f74aca74312dbeaf24d7e61306dd6a786dc3d0
