{
  "id": 7324675,
  "type": "Feature",
  "properties": {
    "tgn:hierarchy":[
        "tgn:7324675",
        "tgn:7002829",
        "tgn:1000003",
        "tgn:7002786",
        "tgn:1000095",
        "tgn:7029392"
    ],
    "tgn:id":7324675,
    "tgn:name":"Sarria, R\u00edo",
    "tgn:placetype":[
        "aat:300008699"
    ]
},
  "bbox": [],
  "geometry": {"coordinates":[-7.45,42.866667],"type":"Point"}
}