{
  "id": 2650830,
  "type": "Feature",
  "properties": {
    "tgn:hierarchy":[
        "tgn:2650830",
        "tgn:1000001",
        "tgn:2001785",
        "tgn:7012149",
        "tgn:7007713",
        "tgn:7029392"
    ],
    "tgn:id":2650830,
    "tgn:name":"Second Creek",
    "tgn:placetype":[
        "aat:300008706"
    ]
},
  "bbox": [],
  "geometry": {"coordinates":[-101.9167,45.6167],"type":"Point"}
}