{
  "id": 2318293,
  "type": "Feature",
  "properties": {
    "tgn:hierarchy":[
        "tgn:2318293",
        "tgn:7002659",
        "tgn:1000001",
        "tgn:7012149",
        "tgn:2000031",
        "tgn:7029392"
    ],
    "tgn:id":2318293,
    "tgn:name":"Epes Bar",
    "tgn:placetype":[
        "aat:300132348"
    ]
},
  "bbox": [],
  "geometry": {"coordinates":[-88.0667,32.7167],"type":"Point"}
}