{
  "id": 2150664,
  "type": "Feature",
  "properties": {
    "tgn:hierarchy":[
        "tgn:2150664",
        "tgn:1000001",
        "tgn:2000569",
        "tgn:7012149",
        "tgn:7007253",
        "tgn:7029392"
    ],
    "tgn:id":2150664,
    "tgn:name":"Baskins Run",
    "tgn:placetype":[
        "aat:300008699"
    ]
},
  "bbox": [],
  "geometry": {"coordinates":[-92.4167,42.85],"type":"Point"}
}