<<<<<<< HEAD
{
  "id": 2150664,
  "type": "Feature",
  "properties": {
    "tgn:hierarchy":[
        "tgn:2150664",
        "tgn:1000001",
        "tgn:2000569",
        "tgn:7012149",
        "tgn:7007253",
        "tgn:7029392"
    ],
    "tgn:id":2150664,
    "tgn:name":"Baskins Run",
    "tgn:placetype":[
        "aat:300008699"
    ]
},
  "bbox": [],
  "geometry": {"coordinates":[-92.4167,42.85],"type":"Point"}
}
=======
{"geometry":{"type":"Point","coordinates":[-92.416700,42.850000]},"type":"Feature","properties":{"hierarchy":["tgn:2150664","tgn:1000001","tgn:2000569","tgn:7012149","tgn:7007253","tgn:7029392"],"placetype":["aat:300008699"],"id":2150664,"name:xx":"Baskins Run"}}
>>>>>>> 03f74aca74312dbeaf24d7e61306dd6a786dc3d0
