{
  "id": 7419700,
  "type": "Feature",
  "properties": {
    "tgn:hierarchy":[
        "tgn:7419700",
        "tgn:7005579",
        "tgn:1000001",
        "tgn:7005560",
        "tgn:7029392"
    ],
    "tgn:id":7419700,
    "tgn:name":"El Salitre",
    "tgn:placetype":[
        "aat:300008347"
    ]
},
  "bbox": [],
  "geometry": {"coordinates":[-101.866667,22.041667],"type":"Point"}
}