{
  "id": 2173411,
  "type": "Feature",
  "properties": {
    "tgn:hierarchy":[
        "tgn:2173411",
        "tgn:1000001",
        "tgn:7012149",
        "tgn:2001535",
        "tgn:7007709",
        "tgn:7029392"
    ],
    "tgn:id":2173411,
    "tgn:name":"Birch Fork",
    "tgn:placetype":[
        "aat:300008699"
    ]
},
  "bbox": [],
  "geometry": {"coordinates":[-79.6333,36.45],"type":"Point"}
}