{
  "id": 7388797,
  "type": "Feature",
  "properties": {
    "tgn:hierarchy":[
        "tgn:7388797",
        "tgn:1000001",
        "tgn:7005590",
        "tgn:7005560",
        "tgn:7029392"
    ],
    "tgn:id":7388797,
    "tgn:name":"Piedra Verde",
    "tgn:placetype":[
        "aat:300008347"
    ]
},
  "bbox": [],
  "geometry": {"coordinates":[-102.566667,18.216667],"type":"Point"}
}