<<<<<<< HEAD
{
  "id": 7024640,
  "type": "Feature",
  "properties": {
    "tgn:hierarchy":[
        "tgn:7024640",
        "tgn:7001155",
        "tgn:1000003",
        "tgn:7002790",
        "tgn:1000095",
        "tgn:7029392"
    ],
    "tgn:id":7024640,
    "tgn:name":"Huarte Araquil",
    "tgn:placetype":[
        "aat:300008347"
    ]
},
  "bbox": [],
  "geometry": {"coordinates":[-1.966667,42.916667],"type":"Point"}
}
=======
{"geometry":{"type":"Point","coordinates":[-1.966667,42.916667]},"type":"Feature","properties":{"hierarchy":["tgn:7024640","tgn:7001155","tgn:1000003","tgn:7002790","tgn:1000095","tgn:7029392"],"placetype":["aat:300008347"],"id":7024640,"name:xx":"Huarte Araquil"}}
>>>>>>> 03f74aca74312dbeaf24d7e61306dd6a786dc3d0
