{
  "id": 7484642,
  "type": "Feature",
  "properties": {
    "tgn:hierarchy":[
        "tgn:7484642",
        "tgn:7468018",
        "tgn:1000004",
        "tgn:1000141",
        "tgn:7029392"
    ],
    "tgn:id":7484642,
    "tgn:name":"Disanshiyihao Suidao",
    "tgn:placetype":[
        "aat:300007899"
    ]
},
  "bbox": [],
  "geometry": {"coordinates":[120.7025,23.500833],"type":"Point"}
}