{
  "id": 2246101,
  "type": "Feature",
  "properties": {
    "tgn:hierarchy":[
        "tgn:2246101",
        "tgn:1000001",
        "tgn:7012149",
        "tgn:2002192",
        "tgn:7007919",
        "tgn:7029392"
    ],
    "tgn:id":2246101,
    "tgn:name":"Coal Run",
    "tgn:placetype":[
        "aat:300008699"
    ]
},
  "bbox": [],
  "geometry": {"coordinates":[-81.35,37.3333],"type":"Point"}
}