{
  "id": 7000593,
  "type": "Feature",
  "properties": {
    "tgn:hierarchy":[
        "tgn:7000593",
        "tgn:7001242",
        "tgn:7016654",
        "tgn:1000159",
        "tgn:7029392"
    ],
    "tgn:id":7000593,
    "tgn:name":"Lisala",
    "tgn:placetype":[
        "aat:300008347"
    ]
},
  "bbox": [],
  "geometry": {"coordinates":[21.6167,2.1333],"type":"Point"}
}