<<<<<<< HEAD
{
  "id": 7054028,
  "type": "Feature",
  "properties": {
    "tgn:hierarchy":[
        "tgn:7054028",
        "tgn:1003483",
        "tgn:1000003",
        "tgn:7003240",
        "tgn:1000080",
        "tgn:7029392"
    ],
    "tgn:id":7054028,
    "tgn:name":"Monte Altavelio",
    "tgn:placetype":[
        "aat:300008347"
    ]
},
  "bbox": [],
  "geometry": {"coordinates":[12.5,43.85],"type":"Point"}
}
=======
{"geometry":{"type":"Point","coordinates":[12.500000,43.850000]},"type":"Feature","properties":{"hierarchy":["tgn:7054028","tgn:1003483","tgn:1000003","tgn:7003240","tgn:1000080","tgn:7029392"],"placetype":["aat:300008347"],"id":7054028,"name:xx":"Monte Altavelio"}}
>>>>>>> 03f74aca74312dbeaf24d7e61306dd6a786dc3d0
