{
  "id": 2528243,
  "type": "Feature",
  "properties": {
    "tgn:hierarchy":[
        "tgn:2528243",
        "tgn:1000001",
        "tgn:7012149",
        "tgn:2000363",
        "tgn:7007248",
        "tgn:7029392"
    ],
    "tgn:id":2528243,
    "tgn:name":"Mountain, The",
    "tgn:placetype":[
        "aat:300008798"
    ]
},
  "bbox": [],
  "geometry": {"coordinates":[-85.1333,32.85],"type":"Point"}
}