{
  "id": 7315766,
  "type": "Feature",
  "properties": {
    "tgn:hierarchy":[
        "tgn:7315766",
        "tgn:1001708",
        "tgn:1000049",
        "tgn:1000002",
        "tgn:7029392"
    ],
    "tgn:id":7315766,
    "tgn:name":"Cepo, R\u00edo del",
    "tgn:placetype":[
        "aat:300008699"
    ]
},
  "bbox": [],
  "geometry": {"coordinates":[-70.266667,-33.383333],"type":"Point"}
}