{
  "id": 2040221,
  "type": "Feature",
  "properties": {
    "tgn:hierarchy":[
        "tgn:2040221",
        "tgn:1000001",
        "tgn:7012149",
        "tgn:2000827",
        "tgn:7007255",
        "tgn:7029392"
    ],
    "tgn:id":2040221,
    "tgn:name":"Mayo",
    "tgn:placetype":[
        "aat:300008347"
    ]
},
  "bbox": [],
  "geometry": {"coordinates":[-84.9167,37.8667],"type":"Point"}
}