{
  "id": 2687250,
  "type": "Feature",
  "properties": {
    "tgn:hierarchy":[
        "tgn:2687250",
        "tgn:1000001",
        "tgn:7012149",
        "tgn:7007157",
        "tgn:1002956",
        "tgn:7029392"
    ],
    "tgn:id":2687250,
    "tgn:name":"Spring Lake",
    "tgn:placetype":[
        "aat:300008680"
    ]
},
  "bbox": [],
  "geometry": {"coordinates":[-118.55,36.4667],"type":"Point"}
}