{
  "id": 2051848,
  "type": "Feature",
  "properties": {
    "tgn:hierarchy":[
        "tgn:2051848",
        "tgn:1000001",
        "tgn:7012149",
        "tgn:2000981",
        "tgn:7007520",
        "tgn:7029392"
    ],
    "tgn:id":2051848,
    "tgn:name":"Entrican",
    "tgn:placetype":[
        "aat:300008347"
    ]
},
  "bbox": [],
  "geometry": {"coordinates":[-85.15,43.35],"type":"Point"}
}