{
  "id": 2314258,
  "type": "Feature",
  "properties": {
    "tgn:hierarchy":[
        "tgn:2314258",
        "tgn:1000001",
        "tgn:7012149",
        "tgn:7007919",
        "tgn:7029392"
    ],
    "tgn:id":2314258,
    "tgn:name":"Elk Creek",
    "tgn:placetype":[
        "aat:300008706"
    ]
},
  "bbox": [],
  "geometry": {"coordinates":[-79.5167,37.5333],"type":"Point"}
}