{
  "id": 2606896,
  "type": "Feature",
  "properties": {
    "tgn:hierarchy":[
        "tgn:2606896",
        "tgn:1000001",
        "tgn:7012149",
        "tgn:1003038",
        "tgn:7007517",
        "tgn:7029392"
    ],
    "tgn:id":2606896,
    "tgn:name":"Ramshorn Brook",
    "tgn:placetype":[
        "aat:300008699"
    ]
},
  "bbox": [],
  "geometry": {"coordinates":[-71.8167,42.1333],"type":"Point"}
}