{
  "id": 7281037,
  "type": "Feature",
  "properties": {
    "tgn:hierarchy":[
        "tgn:7281037",
        "tgn:1001702",
        "tgn:1000049",
        "tgn:1000002",
        "tgn:7029392"
    ],
    "tgn:id":7281037,
    "tgn:name":"Sherbakoff, Cerro",
    "tgn:placetype":[
        "aat:300008795"
    ]
},
  "bbox": [],
  "geometry": {"coordinates":[-73.733333,-52.283333],"type":"Point"}
}