<<<<<<< HEAD
{
  "id": 7240756,
  "type": "Feature",
  "properties": {
    "tgn:hierarchy":[
        "tgn:7240756",
        "tgn:7003456",
        "tgn:1000003",
        "tgn:1000063",
        "tgn:7018236",
        "tgn:7029392"
    ],
    "tgn:id":7240756,
    "tgn:name":"Fermerijhoeve",
    "tgn:placetype":[
        "aat:300000206"
    ]
},
  "bbox": [],
  "geometry": {"coordinates":[4.833333,51.2],"type":"Point"}
}
=======
{"geometry":{"type":"Point","coordinates":[4.833333,51.200000]},"type":"Feature","properties":{"hierarchy":["tgn:7240756","tgn:7003456","tgn:1000003","tgn:1000063","tgn:7018236","tgn:7029392"],"placetype":["aat:300000206"],"id":7240756,"name:xx":"Fermerijhoeve"}}
>>>>>>> 03f74aca74312dbeaf24d7e61306dd6a786dc3d0
