{
  "id": 2450339,
  "type": "Feature",
  "properties": {
    "tgn:hierarchy":[
        "tgn:2450339",
        "tgn:1000001",
        "tgn:7012149",
        "tgn:2002359",
        "tgn:7007922",
        "tgn:7029392"
    ],
    "tgn:id":2450339,
    "tgn:name":"Link Creek",
    "tgn:placetype":[
        "aat:300008706"
    ]
},
  "bbox": [],
  "geometry": {"coordinates":[-89.65,45.9167],"type":"Point"}
}