{
  "id": 7563507,
  "type": "Feature",
  "properties": {
    "tgn:hierarchy":[
        "tgn:7563507",
        "tgn:1000004",
        "tgn:7000198",
        "tgn:7016722",
        "tgn:7029392"
    ],
    "tgn:id":7563507,
    "tgn:name:en":"Kanaura",
    "tgn:placetype":[
        "aat:300008347"
    ]
},
  "bbox": [],
  "geometry": {"coordinates":[79.459501,25.295931],"type":"Point"}
}