{
  "id": 7393335,
  "type": "Feature",
  "properties": {
    "tgn:hierarchy":[
        "tgn:7393335",
        "tgn:1000001",
        "tgn:1001893",
        "tgn:7005560",
        "tgn:7029392"
    ],
    "tgn:id":7393335,
    "tgn:name":"San Antonio Ometusco",
    "tgn:placetype":[
        "aat:300008347"
    ]
},
  "bbox": [],
  "geometry": {"coordinates":[-98.616667,19.783333],"type":"Point"}
}