{
  "id": 7271453,
  "type": "Feature",
  "properties": {
    "tgn:hierarchy":[
        "tgn:7271453",
        "tgn:7003616",
        "tgn:1000003",
        "tgn:7016845",
        "tgn:7029392"
    ],
    "tgn:id":7271453,
    "tgn:name:nl":"Tachtigbunder",
    "tgn:placetype":[
        "aat:300387200"
    ]
},
  "bbox": [],
  "geometry": {"coordinates":[6.366667,52.983333],"type":"Point"}
}