{
  "id": 2326067,
  "type": "Feature",
  "properties": {
    "tgn:hierarchy":[
        "tgn:2326067",
        "tgn:1000001",
        "tgn:7012149",
        "tgn:2000182",
        "tgn:7007157",
        "tgn:7029392"
    ],
    "tgn:id":2326067,
    "tgn:name":"Fig Drain",
    "tgn:placetype":[
        "aat:300006075"
    ]
},
  "bbox": [],
  "geometry": {"coordinates":[-115.6833,32.7333],"type":"Point"}
}