<<<<<<< HEAD
{
  "id": 7351946,
  "type": "Feature",
  "properties": {
    "tgn:hierarchy":[
        "tgn:7351946",
        "tgn:1001835",
        "tgn:1000001",
        "tgn:7005560",
        "tgn:7029392"
    ],
    "tgn:id":7351946,
    "tgn:name":"Calamaju\u00e9, Arroyo",
    "tgn:placetype":[
        "aat:300008699"
    ]
},
  "bbox": [],
  "geometry": {"coordinates":[-114.4,29.7],"type":"Point"}
}
=======
{"geometry":{"type":"Point","coordinates":[-114.400000,29.700000]},"type":"Feature","properties":{"hierarchy":["tgn:7351946","tgn:1001835","tgn:1000001","tgn:7005560","tgn:7029392"],"placetype":["aat:300008699"],"id":7351946,"name:xx":"Calamaju\u00e9, Arroyo"}}
>>>>>>> 03f74aca74312dbeaf24d7e61306dd6a786dc3d0
