{
  "id": 2298373,
  "type": "Feature",
  "properties": {
    "tgn:hierarchy":[
        "tgn:2298373",
        "tgn:1000001",
        "tgn:7012149",
        "tgn:2002383",
        "tgn:7007923",
        "tgn:7029392"
    ],
    "tgn:id":2298373,
    "tgn:name":"Dry Reservoir",
    "tgn:placetype":[
        "aat:300006191"
    ]
},
  "bbox": [],
  "geometry": {"coordinates":[-107.9333,41.0167],"type":"Point"}
}