{
  "id": 7286511,
  "type": "Feature",
  "properties": {
    "tgn:hierarchy":[
        "tgn:7286511",
        "tgn:1001702",
        "tgn:1000049",
        "tgn:1000002",
        "tgn:7029392"
    ],
    "tgn:id":7286511,
    "tgn:name":"Harwood, Isla",
    "tgn:placetype":[
        "aat:300008791"
    ]
},
  "bbox": [],
  "geometry": {"coordinates":[-74.416667,-49.116667],"type":"Point"}
}