{
  "id": 2177443,
  "type": "Feature",
  "properties": {
    "tgn:hierarchy":[
        "tgn:2177443",
        "tgn:1000001",
        "tgn:7012149",
        "tgn:7007923",
        "tgn:7029392"
    ],
    "tgn:id":2177443,
    "tgn:name":"Black Rock Draw",
    "tgn:placetype":[
        "aat:300008761"
    ]
},
  "bbox": [],
  "geometry": {"coordinates":[-107.1167,42.6833],"type":"Point"}
}