<<<<<<< HEAD
{
  "id": 2766819,
  "type": "Feature",
  "properties": {
    "tgn:hierarchy":[
        "tgn:2766819",
        "tgn:1000001",
        "tgn:7012149",
        "tgn:2000352",
        "tgn:7007248",
        "tgn:7029392"
    ],
    "tgn:id":2766819,
    "tgn:name":"White Path",
    "tgn:placetype":[
        "aat:300008347"
    ]
},
  "bbox": [],
  "geometry": {"coordinates":[-84.4,34.75],"type":"Point"}
}
=======
{"geometry":{"type":"Point","coordinates":[-84.400000,34.750000]},"type":"Feature","properties":{"hierarchy":["tgn:2766819","tgn:1000001","tgn:7012149","tgn:2000352","tgn:7007248","tgn:7029392"],"placetype":["aat:300008347"],"id":2766819,"name:xx":"White Path"}}
>>>>>>> 03f74aca74312dbeaf24d7e61306dd6a786dc3d0
