{
  "id": 2238015,
  "type": "Feature",
  "properties": {
    "tgn:hierarchy":[
        "tgn:2238015",
        "tgn:1000001",
        "tgn:7012149",
        "tgn:7007566",
        "tgn:7029392"
    ],
    "tgn:id":2238015,
    "tgn:name":"Chiquito, Rio",
    "tgn:placetype":[
        "aat:300008699"
    ]
},
  "bbox": [],
  "geometry": {"coordinates":[-105.6333,36.0333],"type":"Point"}
}