{
  "id": 7540403,
  "type": "Feature",
  "properties": {
    "tgn:hierarchy":[
        "tgn:7540403",
        "tgn:7001242",
        "tgn:7016833",
        "tgn:1001087",
        "tgn:7029392"
    ],
    "tgn:id":7540403,
    "tgn:name:en":"Minsh\u0101t ash Shar\u012bkayn",
    "tgn:placetype":[
        "aat:300008347"
    ]
},
  "bbox": [],
  "geometry": {"coordinates":[30.960185,30.556139],"type":"Point"}
}