<<<<<<< HEAD
{
  "id": 7241416,
  "type": "Feature",
  "properties": {
    "tgn:hierarchy":[
        "tgn:7241416",
        "tgn:7018238",
        "tgn:1000003",
        "tgn:1000063",
        "tgn:4012014",
        "tgn:7029392"
    ],
    "tgn:id":7241416,
    "tgn:name":"Le Culot",
    "tgn:placetype":[
        "aat:300008347"
    ]
},
  "bbox": [],
  "geometry": {"coordinates":[4.616667,50.733333],"type":"Point"}
}
=======
{"geometry":{"type":"Point","coordinates":[4.616667,50.733333]},"type":"Feature","properties":{"hierarchy":["tgn:7241416","tgn:7018238","tgn:1000003","tgn:1000063","tgn:4012014","tgn:7029392"],"placetype":["aat:300008347"],"id":7241416,"name:xx":"Le Culot"}}
>>>>>>> 03f74aca74312dbeaf24d7e61306dd6a786dc3d0
