{
  "id": 7492917,
  "type": "Feature",
  "properties": {
    "tgn:hierarchy":[
        "tgn:7492917",
        "tgn:7001010",
        "tgn:1000004",
        "tgn:1000141",
        "tgn:7029392"
    ],
    "tgn:id":7492917,
    "tgn:name":"Songshan Suidao",
    "tgn:placetype":[
        "aat:300007899"
    ]
},
  "bbox": [],
  "geometry": {"coordinates":[121.448056,24.201389],"type":"Point"}
}