<<<<<<< HEAD
{
  "id": 7474705,
  "type": "Feature",
  "properties": {
    "tgn:hierarchy":[
        "tgn:7474705",
        "tgn:1000004",
        "tgn:7492971",
        "tgn:1000141",
        "tgn:7029392"
    ],
    "tgn:id":7474705,
    "tgn:name":"Dahou Xi",
    "tgn:placetype":[
        "aat:300008699"
    ]
},
  "bbox": [],
  "geometry": {"coordinates":[120.680918,22.56203],"type":"Point"}
}
=======
{"geometry":{"type":"Point","coordinates":[120.680918,22.562030]},"type":"Feature","properties":{"hierarchy":["tgn:7474705","tgn:1000004","tgn:7492971","tgn:1000141","tgn:7029392"],"placetype":["aat:300008699"],"id":7474705,"name:xx":"Dahou Xi"}}
>>>>>>> 03f74aca74312dbeaf24d7e61306dd6a786dc3d0
