{
  "id": 7407139,
  "type": "Feature",
  "properties": {
    "tgn:hierarchy":[
        "tgn:7407139",
        "tgn:7005578",
        "tgn:1000001",
        "tgn:7005560",
        "tgn:7029392"
    ],
    "tgn:id":7407139,
    "tgn:name":"El Vapor",
    "tgn:placetype":[
        "aat:300008347",
        "aat:300387200"
    ]
},
  "bbox": [],
  "geometry": {"coordinates":[-91.866667,18.508333],"type":"Point"}
}