{
  "id": 2623222,
  "type": "Feature",
  "properties": {
    "tgn:hierarchy":[
        "tgn:2623222",
        "tgn:1000001",
        "tgn:7012149",
        "tgn:2000522",
        "tgn:7007251",
        "tgn:7029392"
    ],
    "tgn:id":2623222,
    "tgn:name":"Rock Branch",
    "tgn:placetype":[
        "aat:300008699"
    ]
},
  "bbox": [],
  "geometry": {"coordinates":[-89.2833,38.15],"type":"Point"}
}