<<<<<<< HEAD
{
  "id": 2769345,
  "type": "Feature",
  "properties": {
    "tgn:hierarchy":[
        "tgn:2769345",
        "tgn:1000001",
        "tgn:7012149",
        "tgn:2001306",
        "tgn:7007524",
        "tgn:7029392"
    ],
    "tgn:id":2769345,
    "tgn:name":"Wickiup Creek",
    "tgn:placetype":[
        "aat:300008706"
    ]
},
  "bbox": [],
  "geometry": {"coordinates":[-112.5667,45.7333],"type":"Point"}
}
=======
{"geometry":{"type":"Point","coordinates":[-112.566700,45.733300]},"type":"Feature","properties":{"hierarchy":["tgn:2769345","tgn:1000001","tgn:7012149","tgn:2001306","tgn:7007524","tgn:7029392"],"placetype":["aat:300008706"],"id":2769345,"name:xx":"Wickiup Creek"}}
>>>>>>> 03f74aca74312dbeaf24d7e61306dd6a786dc3d0
