{
  "id": 2769345,
  "type": "Feature",
  "properties": {
    "tgn:hierarchy":[
        "tgn:2769345",
        "tgn:1000001",
        "tgn:7012149",
        "tgn:2001306",
        "tgn:7007524",
        "tgn:7029392"
    ],
    "tgn:id":2769345,
    "tgn:name":"Wickiup Creek",
    "tgn:placetype":[
        "aat:300008706"
    ]
},
  "bbox": [],
  "geometry": {"coordinates":[-112.5667,45.7333],"type":"Point"}
}