{
  "id": 7559910,
  "type": "Feature",
  "properties": {
    "tgn:hierarchy":[
        "tgn:7559910",
        "tgn:1000004",
        "tgn:7000198",
        "tgn:7016722",
        "tgn:7029392"
    ],
    "tgn:id":7559910,
    "tgn:name:en":"Nagla T\u0101nk",
    "tgn:placetype":[
        "aat:300008347"
    ]
},
  "bbox": [],
  "geometry": {"coordinates":[79.280078,27.242968],"type":"Point"}
}