{
  "id": 2547669,
  "type": "Feature",
  "properties": {
    "tgn:hierarchy":[
        "tgn:2547669",
        "tgn:1000001",
        "tgn:7012149",
        "tgn:2001302",
        "tgn:7007524",
        "tgn:7029392"
    ],
    "tgn:id":2547669,
    "tgn:name":"North Fork Tule Creek",
    "tgn:placetype":[
        "aat:300008706"
    ]
},
  "bbox": [],
  "geometry": {"coordinates":[-105.6333,48.4167],"type":"Point"}
}