{
  "id": 7550419,
  "type": "Feature",
  "properties": {
    "tgn:hierarchy":[
        "tgn:7550419",
        "tgn:1000004",
        "tgn:7000198",
        "tgn:7016788",
        "tgn:7029392"
    ],
    "tgn:id":7550419,
    "tgn:name:en":"Daipha",
    "tgn:placetype":[
        "aat:300008347"
    ]
},
  "bbox": [],
  "geometry": {"coordinates":[72.233333,25.166667],"type":"Point"}
}