<<<<<<< HEAD
{
  "id": 2250517,
  "type": "Feature",
  "properties": {
    "tgn:hierarchy":[
        "tgn:2250517",
        "tgn:1000001",
        "tgn:7012149",
        "tgn:7007157",
        "tgn:1002656",
        "tgn:7029392"
    ],
    "tgn:id":2250517,
    "tgn:name":"Colony Branch Number Three Canal",
    "tgn:placetype":[
        "aat:300006075"
    ]
},
  "bbox": [],
  "geometry": {"coordinates":[-120.65,36.9833],"type":"Point"}
}
=======
{"geometry":{"type":"Point","coordinates":[-120.650000,36.983300]},"type":"Feature","properties":{"hierarchy":["tgn:2250517","tgn:1000001","tgn:7012149","tgn:7007157","tgn:1002656","tgn:7029392"],"placetype":["aat:300006075"],"id":2250517,"name:xx":"Colony Branch Number Three Canal"}}
>>>>>>> 03f74aca74312dbeaf24d7e61306dd6a786dc3d0
