{
  "id": 7499568,
  "type": "Feature",
  "properties": {
    "tgn:hierarchy":[
        "tgn:7499568",
        "tgn:7001010",
        "tgn:1000004",
        "tgn:1000141",
        "tgn:7029392"
    ],
    "tgn:id":7499568,
    "tgn:name":"Taiping Xi Dongyuan",
    "tgn:placetype":[
        "aat:300008699"
    ]
},
  "bbox": [],
  "geometry": {"coordinates":[121.229326,23.581944],"type":"Point"}
}