{
  "id": 2607231,
  "type": "Feature",
  "properties": {
    "tgn:hierarchy":[
        "tgn:2607231",
        "tgn:1000001",
        "tgn:7006451",
        "tgn:7012149",
        "tgn:2000101",
        "tgn:7029392"
    ],
    "tgn:id":2607231,
    "tgn:name":"Randolph Canyon",
    "tgn:placetype":[
        "aat:300008761"
    ]
},
  "bbox": [],
  "geometry": {"coordinates":[-111.1667,33.4167],"type":"Point"}
}