{
  "id": 2215058,
  "type": "Feature",
  "properties": {
    "tgn:hierarchy":[
        "tgn:2215058",
        "tgn:1000001",
        "tgn:7006451",
        "tgn:7012149",
        "tgn:2000102",
        "tgn:7029392"
    ],
    "tgn:id":2215058,
    "tgn:name":"California Gulch",
    "tgn:placetype":[
        "aat:300008761"
    ]
},
  "bbox": [],
  "geometry": {"coordinates":[-111.2167,31.45],"type":"Point"}
}