{
  "id": 2130868,
  "type": "Feature",
  "properties": {
    "tgn:hierarchy":[
        "tgn:2130868",
        "tgn:1000001",
        "tgn:7006451",
        "tgn:7012149",
        "tgn:2000103",
        "tgn:7029392"
    ],
    "tgn:id":2130868,
    "tgn:name":"Ally Wash",
    "tgn:placetype":[
        "aat:300008699"
    ]
},
  "bbox": [],
  "geometry": {"coordinates":[-112.9167,34.45],"type":"Point"}
}