{
  "id": 7517239,
  "type": "Feature",
  "properties": {
    "tgn:hierarchy":[
        "tgn:7517239",
        "tgn:1008380",
        "tgn:7520093",
        "tgn:1000226",
        "tgn:1000006",
        "tgn:7029392"
    ],
    "tgn:id":7517239,
    "tgn:name:en":"Kopae",
    "tgn:placetype":[
        "aat:300008795"
    ]
},
  "bbox": [],
  "geometry": {"coordinates":[175.083333,-38.916667],"type":"Point"}
}