<<<<<<< HEAD
{
  "id": 7368416,
  "type": "Feature",
  "properties": {
    "tgn:hierarchy":[
        "tgn:7368416",
        "tgn:1000001",
        "tgn:7005594",
        "tgn:7005560",
        "tgn:7029392"
    ],
    "tgn:id":7368416,
    "tgn:name":"Joyas Finas",
    "tgn:placetype":[
        "aat:300008347"
    ]
},
  "bbox": [],
  "geometry": {"coordinates":[-99.883333,21.5],"type":"Point"}
}
=======
{"geometry":{"type":"Point","coordinates":[-99.883333,21.500000]},"type":"Feature","properties":{"hierarchy":["tgn:7368416","tgn:1000001","tgn:7005594","tgn:7005560","tgn:7029392"],"placetype":["aat:300008347"],"id":7368416,"name:xx":"Joyas Finas"}}
>>>>>>> 03f74aca74312dbeaf24d7e61306dd6a786dc3d0
