{
  "id": 1110185,
  "type": "Feature",
  "properties": {
    "tgn:hierarchy":[
        "tgn:1110185",
        "tgn:1000004",
        "tgn:7012215",
        "tgn:7006653",
        "tgn:7029392"
    ],
    "tgn:id":1110185,
    "tgn:name":"Svanetskiy Khrebet",
    "tgn:placetype":[
        "aat:300386831"
    ]
},
  "bbox": [],
  "geometry": {"coordinates":[42.6667,42.9167],"type":"Point"}
}