{
  "id": 7281716,
  "type": "Feature",
  "properties": {
    "tgn:hierarchy":[
        "tgn:7281716",
        "tgn:7016598",
        "tgn:1000049",
        "tgn:1000002",
        "tgn:7029392"
    ],
    "tgn:id":7281716,
    "tgn:name":"Seca, Laguna",
    "tgn:placetype":[
        "aat:300008680"
    ]
},
  "bbox": [],
  "geometry": {"coordinates":[-68.933333,-23.233333],"type":"Point"}
}