<<<<<<< HEAD
{
  "id": 7172201,
  "type": "Feature",
  "properties": {
    "tgn:hierarchy":[
        "tgn:7172201",
        "tgn:7003692",
        "tgn:1000003",
        "tgn:7000084",
        "tgn:7029392"
    ],
    "tgn:id":7172201,
    "tgn:name":"Hinterweiherhaus",
    "tgn:placetype":[
        "aat:300000206"
    ]
},
  "bbox": [],
  "geometry": {"coordinates":[9.716667,47.966667],"type":"Point"}
}
=======
{"geometry":{"type":"Point","coordinates":[9.716667,47.966667]},"type":"Feature","properties":{"hierarchy":["tgn:7172201","tgn:7003692","tgn:1000003","tgn:7000084","tgn:7029392"],"placetype":["aat:300000206"],"id":7172201,"name:xx":"Hinterweiherhaus"}}
>>>>>>> 03f74aca74312dbeaf24d7e61306dd6a786dc3d0
