{
  "id": 7512075,
  "type": "Feature",
  "properties": {
    "tgn:hierarchy":[
        "tgn:7512075",
        "tgn:7000508",
        "tgn:1008380",
        "tgn:1000226",
        "tgn:1000006",
        "tgn:7029392"
    ],
    "tgn:id":7512075,
    "tgn:name:en":"Junction Islands",
    "tgn:placetype":[
        "aat:300008791"
    ]
},
  "bbox": [],
  "geometry": {"coordinates":[175.316667,-36.233333],"type":"Point"}
}