{
  "id": 2493142,
  "type": "Feature",
  "properties": {
    "tgn:hierarchy":[
        "tgn:2493142",
        "tgn:1000001",
        "tgn:7012149",
        "tgn:2000917",
        "tgn:7007256",
        "tgn:7029392"
    ],
    "tgn:id":2493142,
    "tgn:name":"Marlin Branch",
    "tgn:placetype":[
        "aat:300008699"
    ]
},
  "bbox": [],
  "geometry": {"coordinates":[-92.6833,31.8167],"type":"Point"}
}