{
  "id": 2602531,
  "type": "Feature",
  "properties": {
    "tgn:hierarchy":[
        "tgn:2602531",
        "tgn:1000001",
        "tgn:7012149",
        "tgn:2001461",
        "tgn:7007568",
        "tgn:7029392"
    ],
    "tgn:id":2602531,
    "tgn:name":"Quackenbush Hill",
    "tgn:placetype":[
        "aat:300008798"
    ]
},
  "bbox": [],
  "geometry": {"coordinates":[-73.75,43.7833],"type":"Point"}
}