<<<<<<< HEAD
{
  "id": 2407121,
  "type": "Feature",
  "properties": {
    "tgn:hierarchy":[
        "tgn:2407121",
        "tgn:1000001",
        "tgn:7012149",
        "tgn:1002528",
        "tgn:7007710",
        "tgn:7029392"
    ],
    "tgn:id":2407121,
    "tgn:name":"Hunters Creek",
    "tgn:placetype":[
        "aat:300008706"
    ]
},
  "bbox": [],
  "geometry": {"coordinates":[-77.4,40.4667],"type":"Point"}
}
=======
{"geometry":{"type":"Point","coordinates":[-77.400000,40.466700]},"type":"Feature","properties":{"hierarchy":["tgn:2407121","tgn:1000001","tgn:7012149","tgn:1002528","tgn:7007710","tgn:7029392"],"placetype":["aat:300008706"],"id":2407121,"name:xx":"Hunters Creek"}}
>>>>>>> 03f74aca74312dbeaf24d7e61306dd6a786dc3d0
