{
  "id": 2674027,
  "type": "Feature",
  "properties": {
    "tgn:hierarchy":[
        "tgn:2674027",
        "tgn:1000001",
        "tgn:7012149",
        "tgn:7007526",
        "tgn:7029392"
    ],
    "tgn:id":2674027,
    "tgn:name":"Snow Valley",
    "tgn:placetype":[
        "aat:300008761"
    ]
},
  "bbox": [],
  "geometry": {"coordinates":[-119.8667,39.15],"type":"Point"}
}