<<<<<<< HEAD
{
  "id": 2255991,
  "type": "Feature",
  "properties": {
    "tgn:hierarchy":[
        "tgn:2255991",
        "tgn:1000001",
        "tgn:7012149",
        "tgn:1002392",
        "tgn:7007157",
        "tgn:7029392"
    ],
    "tgn:id":2255991,
    "tgn:name":"Copper King Mine",
    "tgn:placetype":[
        "aat:300000390"
    ]
},
  "bbox": [],
  "geometry": {"coordinates":[-119.4333,36.9],"type":"Point"}
}
=======
{"geometry":{"type":"Point","coordinates":[-119.433300,36.900000]},"type":"Feature","properties":{"hierarchy":["tgn:2255991","tgn:1000001","tgn:7012149","tgn:1002392","tgn:7007157","tgn:7029392"],"placetype":["aat:300000390"],"id":2255991,"name:xx":"Copper King Mine"}}
>>>>>>> 03f74aca74312dbeaf24d7e61306dd6a786dc3d0
