{
  "id": 2479241,
  "type": "Feature",
  "properties": {
    "tgn:hierarchy":[
        "tgn:2479241",
        "tgn:1000001",
        "tgn:7012149",
        "tgn:7007256",
        "tgn:7029392"
    ],
    "tgn:id":2479241,
    "tgn:name":"Lafourche, Lake",
    "tgn:placetype":[
        "aat:300008680"
    ]
},
  "bbox": [],
  "geometry": {"coordinates":[-91.7167,32.5833],"type":"Point"}
}