<<<<<<< HEAD
{
  "id": 2331104,
  "type": "Feature",
  "properties": {
    "tgn:hierarchy":[
        "tgn:2331104",
        "tgn:1000001",
        "tgn:2001943",
        "tgn:7012149",
        "tgn:7007826",
        "tgn:7029392"
    ],
    "tgn:id":2331104,
    "tgn:name":"Flat Tank",
    "tgn:placetype":[
        "aat:300006191"
    ]
},
  "bbox": [],
  "geometry": {"coordinates":[-101.2833,32.5667],"type":"Point"}
}
=======
{"geometry":{"type":"Point","coordinates":[-101.283300,32.566700]},"type":"Feature","properties":{"hierarchy":["tgn:2331104","tgn:1000001","tgn:2001943","tgn:7012149","tgn:7007826","tgn:7029392"],"placetype":["aat:300006191"],"id":2331104,"name:xx":"Flat Tank"}}
>>>>>>> 03f74aca74312dbeaf24d7e61306dd6a786dc3d0
