{
  "id": 7585280,
  "type": "Feature",
  "properties": {
    "tgn:hierarchy":[
        "tgn:7585280",
        "tgn:1000004",
        "tgn:7000198",
        "tgn:7016722",
        "tgn:7029392"
    ],
    "tgn:id":7585280,
    "tgn:name:en":"Kakr\u0101ri",
    "tgn:placetype":[
        "aat:300008347"
    ]
},
  "bbox": [],
  "geometry": {"coordinates":[78.454952,24.97657],"type":"Point"}
}