{
  "id": 7365374,
  "type": "Feature",
  "properties": {
    "tgn:hierarchy":[
        "tgn:7365374",
        "tgn:1001853",
        "tgn:1000001",
        "tgn:7005560",
        "tgn:7029392"
    ],
    "tgn:id":7365374,
    "tgn:name":"Encinas Nuevas",
    "tgn:placetype":[
        "aat:300008347"
    ]
},
  "bbox": [],
  "geometry": {"coordinates":[-101.066667,27.316667],"type":"Point"}
}