{
  "id": 7545529,
  "type": "Feature",
  "properties": {
    "tgn:hierarchy":[
        "tgn:7545529",
        "tgn:1000004",
        "tgn:7000198",
        "tgn:7016694",
        "tgn:7029392"
    ],
    "tgn:id":7545529,
    "tgn:name:en":"Bh\u012bmkhoj",
    "tgn:placetype":[
        "aat:300008347"
    ]
},
  "bbox": [],
  "geometry": {"coordinates":[84.122378,21.305865],"type":"Point"}
}