{
  "id": 7399736,
  "type": "Feature",
  "properties": {
    "tgn:hierarchy":[
        "tgn:7399736",
        "tgn:1000001",
        "tgn:7005593",
        "tgn:7005560",
        "tgn:7029392"
    ],
    "tgn:id":7399736,
    "tgn:name":"Grande, Arroyo",
    "tgn:placetype":[
        "aat:300008699"
    ]
},
  "bbox": [],
  "geometry": {"coordinates":[-99.705556,20.865278],"type":"Point"}
}