{
  "id": 2434310,
  "type": "Feature",
  "properties": {
    "tgn:hierarchy":[
        "tgn:2434310",
        "tgn:1000001",
        "tgn:2000696",
        "tgn:7012149",
        "tgn:7007254",
        "tgn:7029392"
    ],
    "tgn:id":2434310,
    "tgn:name":"Kenbro",
    "tgn:placetype":[
        "aat:300008347"
    ]
},
  "bbox": [],
  "geometry": {"coordinates":[-96.3333,38.1167],"type":"Point"}
}