{
  "id": 2023802,
  "type": "Feature",
  "properties": {
    "tgn:hierarchy":[
        "tgn:2023802",
        "tgn:1000001",
        "tgn:7012149",
        "tgn:2000444",
        "tgn:7007248",
        "tgn:7029392"
    ],
    "tgn:id":2023802,
    "tgn:name":"Ochwalkee",
    "tgn:placetype":[
        "aat:300008347",
        "aat:300387210"
    ]
},
  "bbox": [],
  "geometry": {"coordinates":[-82.6333,32.1833],"type":"Point"}
}