<<<<<<< HEAD
{
  "id": 7364265,
  "type": "Feature",
  "properties": {
    "tgn:hierarchy":[
        "tgn:7364265",
        "tgn:1000001",
        "tgn:1001906",
        "tgn:7005560",
        "tgn:7029392"
    ],
    "tgn:id":7364265,
    "tgn:name":"El Hijito",
    "tgn:placetype":[
        "aat:300008680"
    ]
},
  "bbox": [],
  "geometry": {"coordinates":[-104.8,21.516667],"type":"Point"}
}
=======
{"geometry":{"type":"Point","coordinates":[-104.800000,21.516667]},"type":"Feature","properties":{"hierarchy":["tgn:7364265","tgn:1000001","tgn:1001906","tgn:7005560","tgn:7029392"],"placetype":["aat:300008680"],"id":7364265,"name:xx":"El Hijito"}}
>>>>>>> 03f74aca74312dbeaf24d7e61306dd6a786dc3d0
