{
  "id": 7493132,
  "type": "Feature",
  "properties": {
    "tgn:hierarchy":[
        "tgn:7493132",
        "tgn:1000004",
        "tgn:7467799",
        "tgn:1000141",
        "tgn:7029392"
    ],
    "tgn:id":7493132,
    "tgn:name":"Shengang Xiang",
    "tgn:placetype":[
        "aat:300387173"
    ]
},
  "bbox": [],
  "geometry": {"coordinates":[120.49,24.171944],"type":"Point"}
}