{
  "id": 2765858,
  "type": "Feature",
  "properties": {
    "tgn:hierarchy":[
        "tgn:2765858",
        "tgn:1000001",
        "tgn:7012149",
        "tgn:2001554",
        "tgn:7007709",
        "tgn:7029392"
    ],
    "tgn:id":2765858,
    "tgn:name":"White Fox",
    "tgn:placetype":[
        "aat:300008347"
    ]
},
  "bbox": [],
  "geometry": {"coordinates":[-77.9167,35.75],"type":"Point"}
}