<<<<<<< HEAD
{
  "id": 2765858,
  "type": "Feature",
  "properties": {
    "tgn:hierarchy":[
        "tgn:2765858",
        "tgn:1000001",
        "tgn:7012149",
        "tgn:2001554",
        "tgn:7007709",
        "tgn:7029392"
    ],
    "tgn:id":2765858,
    "tgn:name":"White Fox",
    "tgn:placetype":[
        "aat:300008347"
    ]
},
  "bbox": [],
  "geometry": {"coordinates":[-77.9167,35.75],"type":"Point"}
}
=======
{"geometry":{"type":"Point","coordinates":[-77.916700,35.750000]},"type":"Feature","properties":{"hierarchy":["tgn:2765858","tgn:1000001","tgn:7012149","tgn:2001554","tgn:7007709","tgn:7029392"],"placetype":["aat:300008347"],"id":2765858,"name:xx":"White Fox"}}
>>>>>>> 03f74aca74312dbeaf24d7e61306dd6a786dc3d0
