{
  "id": 7491501,
  "type": "Feature",
  "properties": {
    "tgn:hierarchy":[
        "tgn:7491501",
        "tgn:1000004",
        "tgn:7491221",
        "tgn:1000141",
        "tgn:7029392"
    ],
    "tgn:id":7491501,
    "tgn:name":"Saobie Qiao",
    "tgn:placetype":[
        "aat:300007836"
    ]
},
  "bbox": [],
  "geometry": {"coordinates":[121.432796,23.288907],"type":"Point"}
}