{
  "id": 7317142,
  "type": "Feature",
  "properties": {
    "tgn:hierarchy":[
        "tgn:7317142",
        "tgn:1001702",
        "tgn:1000049",
        "tgn:1000002",
        "tgn:7029392"
    ],
    "tgn:id":7317142,
    "tgn:name":"Cruz, Punta",
    "tgn:placetype":[
        "aat:300386846"
    ]
},
  "bbox": [],
  "geometry": {"coordinates":[-72.966667,-52.933333],"type":"Point"}
}