<<<<<<< HEAD
{
  "id": 7470556,
  "type": "Feature",
  "properties": {
    "tgn:hierarchy":[
        "tgn:7470556",
        "tgn:1000004",
        "tgn:7001014",
        "tgn:1000141",
        "tgn:7029392"
    ],
    "tgn:id":7470556,
    "tgn:name":"Hebao Shan",
    "tgn:placetype":[
        "aat:300008777"
    ]
},
  "bbox": [],
  "geometry": {"coordinates":[120.584444,23.659722],"type":"Point"}
}
=======
{"geometry":{"type":"Point","coordinates":[120.584444,23.659722]},"type":"Feature","properties":{"hierarchy":["tgn:7470556","tgn:1000004","tgn:7001014","tgn:1000141","tgn:7029392"],"placetype":["aat:300008777"],"id":7470556,"name:xx":"Hebao Shan"}}
>>>>>>> 03f74aca74312dbeaf24d7e61306dd6a786dc3d0
