{
  "id": 2174912,
  "type": "Feature",
  "properties": {
    "tgn:hierarchy":[
        "tgn:2174912",
        "tgn:1000001",
        "tgn:1002695",
        "tgn:7012149",
        "tgn:7007565",
        "tgn:7029392"
    ],
    "tgn:id":2174912,
    "tgn:name":"Blachleys Hill",
    "tgn:placetype":[
        "aat:300008798"
    ]
},
  "bbox": [],
  "geometry": {"coordinates":[-74.5333,40.75],"type":"Point"}
}