{
  "id": 7535813,
  "type": "Feature",
  "properties": {
    "tgn:hierarchy":[
        "tgn:7535813",
        "tgn:7001242",
        "tgn:7001311",
        "tgn:7016833",
        "tgn:7029392"
    ],
    "tgn:id":7535813,
    "tgn:name:en":"Khashab, Jabal",
    "tgn:placetype":[
        "aat:300008795"
    ]
},
  "bbox": [],
  "geometry": {"coordinates":[35.226569,23.071142],"type":"Point"}
}