<<<<<<< HEAD
{
  "id": 7365435,
  "type": "Feature",
  "properties": {
    "tgn:hierarchy":[
        "tgn:7365435",
        "tgn:7005583",
        "tgn:1000001",
        "tgn:7005560",
        "tgn:7029392"
    ],
    "tgn:id":7365435,
    "tgn:name":"El Rayo",
    "tgn:placetype":[
        "aat:300008347"
    ]
},
  "bbox": [],
  "geometry": {"coordinates":[-103.6,25.516667],"type":"Point"}
}
=======
{"geometry":{"type":"Point","coordinates":[-103.600000,25.516667]},"type":"Feature","properties":{"hierarchy":["tgn:7365435","tgn:7005583","tgn:1000001","tgn:7005560","tgn:7029392"],"placetype":["aat:300008347"],"id":7365435,"name:xx":"El Rayo"}}
>>>>>>> 03f74aca74312dbeaf24d7e61306dd6a786dc3d0
