{
  "id": 2466631,
  "type": "Feature",
  "properties": {
    "tgn:hierarchy":[
        "tgn:2466631",
        "tgn:1000001",
        "tgn:2001480",
        "tgn:7012149",
        "tgn:7007709",
        "tgn:7029392"
    ],
    "tgn:id":2466631,
    "tgn:name":"Long Branch",
    "tgn:placetype":[
        "aat:300008699"
    ]
},
  "bbox": [],
  "geometry": {"coordinates":[-79.2667,35.7167],"type":"Point"}
}