{
  "id": 2176436,
  "type": "Feature",
  "properties": {
    "tgn:hierarchy":[
        "tgn:2176436",
        "tgn:2001625",
        "tgn:1000001",
        "tgn:7012149",
        "tgn:7007707",
        "tgn:7029392"
    ],
    "tgn:id":2176436,
    "tgn:name":"Black Knob Ridge",
    "tgn:placetype":[
        "aat:300266640"
    ]
},
  "bbox": [],
  "geometry": {"coordinates":[-96.0667,34.4167],"type":"Point"}
}