{
  "id": 2758194,
  "type": "Feature",
  "properties": {
    "tgn:hierarchy":[
        "tgn:2758194",
        "tgn:1000001",
        "tgn:7012149",
        "tgn:2000216",
        "tgn:7007158",
        "tgn:7029392"
    ],
    "tgn:id":2758194,
    "tgn:name":"West Branch Ute Creek",
    "tgn:placetype":[
        "aat:300008706"
    ]
},
  "bbox": [],
  "geometry": {"coordinates":[-106.1333,39.8333],"type":"Point"}
}