{
  "id": 2516519,
  "type": "Feature",
  "properties": {
    "tgn:hierarchy":[
        "tgn:2516519",
        "tgn:1000001",
        "tgn:7013686",
        "tgn:7012149",
        "tgn:7007517",
        "tgn:7029392"
    ],
    "tgn:id":2516519,
    "tgn:name":"Mineral Hills",
    "tgn:placetype":[
        "aat:300008798"
    ]
},
  "bbox": [],
  "geometry": {"coordinates":[-72.7333,42.3167],"type":"Point"}
}