{
  "id": 2671341,
  "type": "Feature",
  "properties": {
    "tgn:hierarchy":[
        "tgn:2671341",
        "tgn:1000001",
        "tgn:7012149",
        "tgn:2001461",
        "tgn:7007568",
        "tgn:7029392"
    ],
    "tgn:id":2671341,
    "tgn:name":"Smith Hill",
    "tgn:placetype":[
        "aat:300008798"
    ]
},
  "bbox": [],
  "geometry": {"coordinates":[-73.7667,43.8833],"type":"Point"}
}