<<<<<<< HEAD
{
  "id": 2337278,
  "type": "Feature",
  "properties": {
    "tgn:hierarchy":[
        "tgn:2337278",
        "tgn:1000001",
        "tgn:7012149",
        "tgn:2000528",
        "tgn:7007251",
        "tgn:7029392"
    ],
    "tgn:id":2337278,
    "tgn:name":"Fourth Slough",
    "tgn:placetype":[
        "aat:300008699"
    ]
},
  "bbox": [],
  "geometry": {"coordinates":[-90.9833,41.4167],"type":"Point"}
}
=======
{"geometry":{"type":"Point","coordinates":[-90.983300,41.416700]},"type":"Feature","properties":{"hierarchy":["tgn:2337278","tgn:1000001","tgn:7012149","tgn:2000528","tgn:7007251","tgn:7029392"],"placetype":["aat:300008699"],"id":2337278,"name:xx":"Fourth Slough"}}
>>>>>>> 03f74aca74312dbeaf24d7e61306dd6a786dc3d0
