{
  "id": 1122999,
  "type": "Feature",
  "properties": {
    "tgn:hierarchy":[
        "tgn:1122999",
        "tgn:1000001",
        "tgn:7005591",
        "tgn:7005560",
        "tgn:7029392"
    ],
    "tgn:id":1122999,
    "tgn:name":"Colotepec, R\u00edo",
    "tgn:placetype":[
        "aat:300008707",
        "aat:300008699"
    ]
},
  "bbox": [],
  "geometry": {"coordinates":[-97.05,15.783333],"type":"Point"}
}