{
  "id": 7529382,
  "type": "Feature",
  "properties": {
    "tgn:hierarchy":[
        "tgn:7529382",
        "tgn:7001242",
        "tgn:1001059",
        "tgn:7016833",
        "tgn:7029392"
    ],
    "tgn:id":7529382,
    "tgn:name":"Tur'at ash Sh\u016bn",
    "tgn:placetype":[
        "aat:300006075"
    ]
},
  "bbox": [],
  "geometry": {"coordinates":[31.508046,30.916206],"type":"Point"}
}