{
  "id": 2785434,
  "type": "Feature",
  "properties": {
    "tgn:hierarchy":[
        "tgn:2785434",
        "tgn:1000001",
        "tgn:2001261",
        "tgn:7012149",
        "tgn:7007524",
        "tgn:7029392"
    ],
    "tgn:id":2785434,
    "tgn:name":"Yellowtail Afterbay Reservoir",
    "tgn:placetype":[
        "aat:300006191"
    ]
},
  "bbox": [],
  "geometry": {"coordinates":[-107.9167,45.3167],"type":"Point"}
}