<<<<<<< HEAD
{
  "id": 7054679,
  "type": "Feature",
  "properties": {
    "tgn:hierarchy":[
        "tgn:7054679",
        "tgn:7004595",
        "tgn:7003005",
        "tgn:1000003",
        "tgn:1000080",
        "tgn:7029392"
    ],
    "tgn:id":7054679,
    "tgn:name":"Ponte",
    "tgn:placetype":[
        "aat:300008347"
    ]
},
  "bbox": [],
  "geometry": {"coordinates":[14.683333,41.216667],"type":"Point"}
}
=======
{"geometry":{"type":"Point","coordinates":[14.683333,41.216667]},"type":"Feature","properties":{"hierarchy":["tgn:7054679","tgn:7004595","tgn:7003005","tgn:1000003","tgn:1000080","tgn:7029392"],"placetype":["aat:300008347"],"id":7054679,"name:xx":"Ponte"}}
>>>>>>> 03f74aca74312dbeaf24d7e61306dd6a786dc3d0
