{
  "id": 7580050,
  "type": "Feature",
  "properties": {
    "tgn:hierarchy":[
        "tgn:7580050",
        "tgn:1000004",
        "tgn:7000198",
        "tgn:1001895",
        "tgn:7029392"
    ],
    "tgn:id":7580050,
    "tgn:name:en":"Th\u0101lner",
    "tgn:placetype":[
        "aat:300008347"
    ]
},
  "bbox": [],
  "geometry": {"coordinates":[74.95481,21.257079],"type":"Point"}
}