{
  "id": 1114070,
  "type": "Feature",
  "properties": {
    "tgn:hierarchy":[
        "tgn:1114070",
        "tgn:1000004",
        "tgn:1001430",
        "tgn:1000135",
        "tgn:7029392"
    ],
    "tgn:id":1114070,
    "tgn:name":"Apo East Pass",
    "tgn:placetype":[
        "aat:300008713"
    ]
},
  "bbox": [],
  "geometry": {"coordinates":[120.6667,12.6667],"type":"Point"}
}