{
  "id": 2211882,
  "type": "Feature",
  "properties": {
    "tgn:hierarchy":[
        "tgn:2211882",
        "tgn:1000001",
        "tgn:1002328",
        "tgn:7012149",
        "tgn:7007568",
        "tgn:7029392"
    ],
    "tgn:id":2211882,
    "tgn:name":"Butts Corner",
    "tgn:placetype":[
        "aat:300008347"
    ]
},
  "bbox": [],
  "geometry": {"coordinates":[-74.8167,42.4667],"type":"Point"}
}