{
  "id": 7371389,
  "type": "Feature",
  "properties": {
    "tgn:hierarchy":[
        "tgn:7371389",
        "tgn:7005581",
        "tgn:1000001",
        "tgn:7005560",
        "tgn:7029392"
    ],
    "tgn:id":7371389,
    "tgn:name":"Grande, Cerro",
    "tgn:placetype":[
        "aat:300008795"
    ]
},
  "bbox": [],
  "geometry": {"coordinates":[-107.35,29.95],"type":"Point"}
}