{
  "id": 1074186,
  "type": "Feature",
  "properties": {
    "tgn:hierarchy":[
        "tgn:1074186",
        "tgn:1000004",
        "tgn:7002079",
        "tgn:1000111",
        "tgn:7029392"
    ],
    "tgn:id":1074186,
    "tgn:name":"Zhuzikou",
    "tgn:placetype":[
        "aat:300008347"
    ]
},
  "bbox": [],
  "geometry": {"coordinates":[112.7167,29.3167],"type":"Point"}
}