{
  "id": 2786382,
  "type": "Feature",
  "properties": {
    "tgn:hierarchy":[
        "tgn:2786382",
        "tgn:1000001",
        "tgn:2001410",
        "tgn:7012149",
        "tgn:7007526",
        "tgn:7029392"
    ],
    "tgn:id":2786382,
    "tgn:name":"Younts Spring",
    "tgn:placetype":[
        "aat:300008697"
    ]
},
  "bbox": [],
  "geometry": {"coordinates":[-115.6833,36.0833],"type":"Point"}
}