{
  "id": 2720642,
  "type": "Feature",
  "properties": {
    "tgn:hierarchy":[
        "tgn:2720642",
        "tgn:1000001",
        "tgn:7012149",
        "tgn:1002518",
        "tgn:7007568",
        "tgn:7029392"
    ],
    "tgn:id":2720642,
    "tgn:name":"Thurso Bay",
    "tgn:placetype":[
        "aat:300132316"
    ]
},
  "bbox": [],
  "geometry": {"coordinates":[-76.1333,44.2833],"type":"Point"}
}