{
  "id": 7036828,
  "type": "Feature",
  "properties": {
    "tgn:hierarchy":[
        "tgn:7036828",
        "tgn:1001641",
        "tgn:1000003",
        "tgn:7003121",
        "tgn:1000080",
        "tgn:7029392"
    ],
    "tgn:id":7036828,
    "tgn:name":"Villasalto",
    "tgn:placetype":[
        "aat:300008347"
    ]
},
  "bbox": [],
  "geometry": {"coordinates":[9.394167,39.492222],"type":"Point"}
}