{
  "id": 7541411,
  "type": "Feature",
  "properties": {
    "tgn:hierarchy":[
        "tgn:7541411",
        "tgn:7001242",
        "tgn:7016833",
        "tgn:1001142",
        "tgn:7029392"
    ],
    "tgn:id":7541411,
    "tgn:name:en":"Al Mu\u1e29m\u016bd\u012byah",
    "tgn:placetype":[
        "aat:300008347"
    ]
},
  "bbox": [],
  "geometry": {"coordinates":[30.835962,28.900491],"type":"Point"}
}