<<<<<<< HEAD
{
  "id": 2339582,
  "type": "Feature",
  "properties": {
    "tgn:hierarchy":[
        "tgn:2339582",
        "tgn:1000001",
        "tgn:7012149",
        "tgn:1002578",
        "tgn:7007826",
        "tgn:7029392"
    ],
    "tgn:id":2339582,
    "tgn:name":"Frederick Mound",
    "tgn:placetype":[
        "aat:300008798"
    ]
},
  "bbox": [],
  "geometry": {"coordinates":[-97.15,29.5833],"type":"Point"}
}
=======
{"geometry":{"type":"Point","coordinates":[-97.150000,29.583300]},"type":"Feature","properties":{"hierarchy":["tgn:2339582","tgn:1000001","tgn:7012149","tgn:1002578","tgn:7007826","tgn:7029392"],"placetype":["aat:300008798"],"id":2339582,"name:xx":"Frederick Mound"}}
>>>>>>> 03f74aca74312dbeaf24d7e61306dd6a786dc3d0
