{
  "id": 2266358,
  "type": "Feature",
  "properties": {
    "tgn:hierarchy":[
        "tgn:2266358",
        "tgn:1000001",
        "tgn:7012149",
        "tgn:2002127",
        "tgn:7007827",
        "tgn:7029392"
    ],
    "tgn:id":2266358,
    "tgn:name":"Crazy Spring",
    "tgn:placetype":[
        "aat:300008697"
    ]
},
  "bbox": [],
  "geometry": {"coordinates":[-113.9167,37.1333],"type":"Point"}
}