{
  "id": 2307144,
  "type": "Feature",
  "properties": {
    "tgn:hierarchy":[
        "tgn:2307144",
        "tgn:1000001",
        "tgn:7012149",
        "tgn:7007826",
        "tgn:7029392"
    ],
    "tgn:id":2307144,
    "tgn:name":"East Fork Mukewater Creek",
    "tgn:placetype":[
        "aat:300008706"
    ]
},
  "bbox": [],
  "geometry": {"coordinates":[-99.1833,31.75],"type":"Point"}
}