{
  "id": 7260804,
  "type": "Feature",
  "properties": {
    "tgn:hierarchy":[
        "tgn:7260804",
        "tgn:1000003",
        "tgn:7006951",
        "tgn:7016845",
        "tgn:7029392"
    ],
    "tgn:id":7260804,
    "tgn:name:nl":"Falga, Strandslag",
    "tgn:placetype":[
        "aat:300008816"
    ]
},
  "bbox": [],
  "geometry": {"coordinates":[4.716667,52.916667],"type":"Point"}
}