<<<<<<< HEAD
{
  "id": 7170759,
  "type": "Feature",
  "properties": {
    "tgn:hierarchy":[
        "tgn:7170759",
        "tgn:1000003",
        "tgn:7003685",
        "tgn:7000084",
        "tgn:7029392"
    ],
    "tgn:id":7170759,
    "tgn:name":"Hennersdorf",
    "tgn:placetype":[
        "aat:300008347"
    ]
},
  "bbox": [],
  "geometry": {"coordinates":[13.616667,50.833333],"type":"Point"}
}
=======
{"geometry":{"type":"Point","coordinates":[13.616667,50.833333]},"type":"Feature","properties":{"hierarchy":["tgn:7170759","tgn:1000003","tgn:7003685","tgn:7000084","tgn:7029392"],"placetype":["aat:300008347"],"id":7170759,"name:xx":"Hennersdorf"}}
>>>>>>> 03f74aca74312dbeaf24d7e61306dd6a786dc3d0
