{
  "id": 2601273,
  "type": "Feature",
  "properties": {
    "tgn:hierarchy":[
        "tgn:2601273",
        "tgn:7006450",
        "tgn:1000001",
        "tgn:2124076",
        "tgn:7012149",
        "tgn:7029392"
    ],
    "tgn:id":2601273,
    "tgn:name":"Pup Island",
    "tgn:placetype":[
        "aat:300008791"
    ]
},
  "bbox": [],
  "geometry": {"coordinates":[-131.8167,55.4667],"type":"Point"}
}