{
  "id": 1057192,
  "type": "Feature",
  "properties": {
    "tgn:hierarchy":[
        "tgn:1057192",
        "tgn:1000004",
        "tgn:7011500",
        "tgn:7002435",
        "tgn:7029392"
    ],
    "tgn:id":1057192,
    "tgn:name":"Mukhor-Shibir",
    "tgn:placetype":[
        "aat:300008347"
    ]
},
  "bbox": [],
  "geometry": {"coordinates":[107.8333,51.05],"type":"Point"}
}