{
  "id": 7327221,
  "type": "Feature",
  "properties": {
    "tgn:hierarchy":[
        "tgn:7327221",
        "tgn:7002835",
        "tgn:7001158",
        "tgn:1000003",
        "tgn:1000095",
        "tgn:7029392"
    ],
    "tgn:id":7327221,
    "tgn:name":"Parral, Arroyo del",
    "tgn:placetype":[
        "aat:300266554",
        "aat:300008699"
    ]
},
  "bbox": [],
  "geometry": {"coordinates":[-6.233333,40.85],"type":"Point"}
}