<<<<<<< HEAD
{
  "id": 7479919,
  "type": "Feature",
  "properties": {
    "tgn:hierarchy":[
        "tgn:7479919",
        "tgn:1000004",
        "tgn:7490934",
        "tgn:1000141",
        "tgn:7029392"
    ],
    "tgn:id":7479919,
    "tgn:name":"Chaolong Gong",
    "tgn:placetype":[
        "aat:300007595"
    ]
},
  "bbox": [],
  "geometry": {"coordinates":[120.274167,23.271667],"type":"Point"}
}
=======
{"geometry":{"type":"Point","coordinates":[120.274167,23.271667]},"type":"Feature","properties":{"hierarchy":["tgn:7479919","tgn:1000004","tgn:7490934","tgn:1000141","tgn:7029392"],"placetype":["aat:300007595"],"id":7479919,"name:xx":"Chaolong Gong"}}
>>>>>>> 03f74aca74312dbeaf24d7e61306dd6a786dc3d0
