{
  "id": 7479919,
  "type": "Feature",
  "properties": {
    "tgn:hierarchy":[
        "tgn:7479919",
        "tgn:1000004",
        "tgn:7490934",
        "tgn:1000141",
        "tgn:7029392"
    ],
    "tgn:id":7479919,
    "tgn:name":"Chaolong Gong",
    "tgn:placetype":[
        "aat:300007595"
    ]
},
  "bbox": [],
  "geometry": {"coordinates":[120.274167,23.271667],"type":"Point"}
}