{
  "id": 7385229,
  "type": "Feature",
  "properties": {
    "tgn:hierarchy":[
        "tgn:7385229",
        "tgn:1000001",
        "tgn:1001960",
        "tgn:7005560",
        "tgn:7029392"
    ],
    "tgn:id":7385229,
    "tgn:name":"Ojo de Agua",
    "tgn:placetype":[
        "aat:300008347"
    ]
},
  "bbox": [],
  "geometry": {"coordinates":[-111.883333,30.666667],"type":"Point"}
}