<<<<<<< HEAD
{
  "id": 2760092,
  "type": "Feature",
  "properties": {
    "tgn:hierarchy":[
        "tgn:2760092",
        "tgn:2000196",
        "tgn:1000001",
        "tgn:7012149",
        "tgn:7007158",
        "tgn:7029392"
    ],
    "tgn:id":2760092,
    "tgn:name":"West Fork Pat Canyon",
    "tgn:placetype":[
        "aat:300008761"
    ]
},
  "bbox": [],
  "geometry": {"coordinates":[-102.9333,37.0333],"type":"Point"}
}
=======
{"geometry":{"type":"Point","coordinates":[-102.933300,37.033300]},"type":"Feature","properties":{"hierarchy":["tgn:2760092","tgn:2000196","tgn:1000001","tgn:7012149","tgn:7007158","tgn:7029392"],"placetype":["aat:300008761"],"id":2760092,"name:xx":"West Fork Pat Canyon"}}
>>>>>>> 03f74aca74312dbeaf24d7e61306dd6a786dc3d0
