<<<<<<< HEAD
{
  "id": 7375759,
  "type": "Feature",
  "properties": {
    "tgn:hierarchy":[
        "tgn:7375759",
        "tgn:7005581",
        "tgn:1000001",
        "tgn:7005560",
        "tgn:7029392"
    ],
    "tgn:id":7375759,
    "tgn:name":"Llano Blanco, Arroyo",
    "tgn:placetype":[
        "aat:300266554",
        "aat:300008699"
    ]
},
  "bbox": [],
  "geometry": {"coordinates":[-104.483333,27.233333],"type":"Point"}
}
=======
{"geometry":{"type":"Point","coordinates":[-104.483333,27.233333]},"type":"Feature","properties":{"hierarchy":["tgn:7375759","tgn:7005581","tgn:1000001","tgn:7005560","tgn:7029392"],"placetype":["aat:300266554","aat:300008699"],"id":7375759,"name:xx":"Llano Blanco, Arroyo"}}
>>>>>>> 03f74aca74312dbeaf24d7e61306dd6a786dc3d0
