{
  "id": 2264995,
  "type": "Feature",
  "properties": {
    "tgn:hierarchy":[
        "tgn:2264995",
        "tgn:1002201",
        "tgn:1000001",
        "tgn:7012149",
        "tgn:7007517",
        "tgn:7029392"
    ],
    "tgn:id":2264995,
    "tgn:name":"Cranberry Bog Corner",
    "tgn:placetype":[
        "aat:300008347"
    ]
},
  "bbox": [],
  "geometry": {"coordinates":[-70.9833,41.55],"type":"Point"}
}