{
  "id": 2078064,
  "type": "Feature",
  "properties": {
    "tgn:hierarchy":[
        "tgn:2078064",
        "tgn:1000001",
        "tgn:7012149",
        "tgn:2001609",
        "tgn:7007705",
        "tgn:7029392"
    ],
    "tgn:id":2078064,
    "tgn:name":"Trenton",
    "tgn:placetype":[
        "aat:300008347"
    ]
},
  "bbox": [],
  "geometry": {"coordinates":[-103.8333,48.0667],"type":"Point"}
}