{
  "id": 2206788,
  "type": "Feature",
  "properties": {
    "tgn:hierarchy":[
        "tgn:2206788",
        "tgn:1000001",
        "tgn:2000782",
        "tgn:7012149",
        "tgn:7007255",
        "tgn:7029392"
    ],
    "tgn:id":2206788,
    "tgn:name":"Bullskin Creek",
    "tgn:placetype":[
        "aat:300008706"
    ]
},
  "bbox": [],
  "geometry": {"coordinates":[-83.4833,37.1833],"type":"Point"}
}