{
  "id": 2541186,
  "type": "Feature",
  "properties": {
    "tgn:hierarchy":[
        "tgn:2541186",
        "tgn:1000001",
        "tgn:7012149",
        "tgn:2000816",
        "tgn:7007255",
        "tgn:7029392"
    ],
    "tgn:id":2541186,
    "tgn:name":"Nickell Cove",
    "tgn:placetype":[
        "aat:300008761"
    ]
},
  "bbox": [],
  "geometry": {"coordinates":[-88.1833,36.9667],"type":"Point"}
}