{
  "id": 2512526,
  "type": "Feature",
  "properties": {
    "tgn:hierarchy":[
        "tgn:2512526",
        "tgn:1000001",
        "tgn:7012149",
        "tgn:2000377",
        "tgn:7007248",
        "tgn:7029392"
    ],
    "tgn:id":2512526,
    "tgn:name":"Mill Creek",
    "tgn:placetype":[
        "aat:300008706"
    ]
},
  "bbox": [],
  "geometry": {"coordinates":[-83.0833,31.0333],"type":"Point"}
}