<<<<<<< HEAD
{
  "id": 2332696,
  "type": "Feature",
  "properties": {
    "tgn:hierarchy":[
        "tgn:2332696",
        "tgn:1000001",
        "tgn:7013942",
        "tgn:7012149",
        "tgn:7007517",
        "tgn:7029392"
    ],
    "tgn:id":2332696,
    "tgn:name":"Flower Hill",
    "tgn:placetype":[
        "aat:300008798"
    ]
},
  "bbox": [],
  "geometry": {"coordinates":[-72.3667,42.7],"type":"Point"}
}
=======
{"geometry":{"type":"Point","coordinates":[-72.366700,42.700000]},"type":"Feature","properties":{"hierarchy":["tgn:2332696","tgn:1000001","tgn:7013942","tgn:7012149","tgn:7007517","tgn:7029392"],"placetype":["aat:300008798"],"id":2332696,"name:xx":"Flower Hill"}}
>>>>>>> 03f74aca74312dbeaf24d7e61306dd6a786dc3d0
