{
  "id": 7577459,
  "type": "Feature",
  "properties": {
    "tgn:hierarchy":[
        "tgn:7577459",
        "tgn:1000004",
        "tgn:7000198",
        "tgn:7016788",
        "tgn:7029392"
    ],
    "tgn:id":7577459,
    "tgn:name:en":"Kheroda",
    "tgn:placetype":[
        "aat:300008347"
    ]
},
  "bbox": [],
  "geometry": {"coordinates":[74.066591,24.580146],"type":"Point"}
}