<<<<<<< HEAD
{
  "id": 2768795,
  "type": "Feature",
  "properties": {
    "tgn:hierarchy":[
        "tgn:2768795",
        "tgn:1000001",
        "tgn:7012149",
        "tgn:1002696",
        "tgn:7007826",
        "tgn:7029392"
    ],
    "tgn:id":2768795,
    "tgn:name":"Whitmore Branch",
    "tgn:placetype":[
        "aat:300008699"
    ]
},
  "bbox": [],
  "geometry": {"coordinates":[-94.7,33.0833],"type":"Point"}
}
=======
{"geometry":{"type":"Point","coordinates":[-94.700000,33.083300]},"type":"Feature","properties":{"hierarchy":["tgn:2768795","tgn:1000001","tgn:7012149","tgn:1002696","tgn:7007826","tgn:7029392"],"placetype":["aat:300008699"],"id":2768795,"name:xx":"Whitmore Branch"}}
>>>>>>> 03f74aca74312dbeaf24d7e61306dd6a786dc3d0
