{
  "id": 7189661,
  "type": "Feature",
  "properties": {
    "tgn:hierarchy":[
        "tgn:7189661",
        "tgn:7003669",
        "tgn:1000003",
        "tgn:7000084",
        "tgn:7029392"
    ],
    "tgn:id":7189661,
    "tgn:name":"Entengraben",
    "tgn:placetype":[
        "aat:300008863"
    ]
},
  "bbox": [],
  "geometry": {"coordinates":[11.05,49.383333],"type":"Point"}
}