{
  "id": 1105285,
  "type": "Feature",
  "properties": {
    "tgn:hierarchy":[
        "tgn:1105285",
        "tgn:1000003",
        "tgn:7015085",
        "tgn:7006670",
        "tgn:7029392"
    ],
    "tgn:id":1105285,
    "tgn:name":"Krn",
    "tgn:placetype":[
        "aat:300008795"
    ]
},
  "bbox": [],
  "geometry": {"coordinates":[13.6667,46.2667],"type":"Point"}
}