{
  "id": 2274639,
  "type": "Feature",
  "properties": {
    "tgn:hierarchy":[
        "tgn:2274639",
        "tgn:1000001",
        "tgn:7012149",
        "tgn:7007157",
        "tgn:1002858",
        "tgn:7029392"
    ],
    "tgn:id":2274639,
    "tgn:name":"Daly Creek",
    "tgn:placetype":[
        "aat:300008706"
    ]
},
  "bbox": [],
  "geometry": {"coordinates":[-116.85,32.9667],"type":"Point"}
}