<<<<<<< HEAD
{
  "id": 7356003,
  "type": "Feature",
  "properties": {
    "tgn:hierarchy":[
        "tgn:7356003",
        "tgn:1001835",
        "tgn:1000001",
        "tgn:7005560",
        "tgn:7029392"
    ],
    "tgn:id":7356003,
    "tgn:name":"Cerrito El Chivo",
    "tgn:placetype":[
        "aat:300008347"
    ]
},
  "bbox": [],
  "geometry": {"coordinates":[-116.05,32.183333],"type":"Point"}
}
=======
{"geometry":{"type":"Point","coordinates":[-116.050000,32.183333]},"type":"Feature","properties":{"hierarchy":["tgn:7356003","tgn:1001835","tgn:1000001","tgn:7005560","tgn:7029392"],"placetype":["aat:300008347"],"id":7356003,"name:xx":"Cerrito El Chivo"}}
>>>>>>> 03f74aca74312dbeaf24d7e61306dd6a786dc3d0
