{
  "id": 2163310,
  "type": "Feature",
  "properties": {
    "tgn:hierarchy":[
        "tgn:2163310",
        "tgn:1000001",
        "tgn:7012149",
        "tgn:2002125",
        "tgn:7007827",
        "tgn:7029392"
    ],
    "tgn:id":2163310,
    "tgn:name":"Bennie Creek Ridge",
    "tgn:placetype":[
        "aat:300266640"
    ]
},
  "bbox": [],
  "geometry": {"coordinates":[-111.6167,39.9333],"type":"Point"}
}