{
  "id": 7502121,
  "type": "Feature",
  "properties": {
    "tgn:hierarchy":[
        "tgn:7502121",
        "tgn:7001004",
        "tgn:1000004",
        "tgn:1000141",
        "tgn:7029392"
    ],
    "tgn:id":7502121,
    "tgn:name":"Xiliangmulan Shan",
    "tgn:placetype":[
        "aat:300387002"
    ]
},
  "bbox": [],
  "geometry": {"coordinates":[120.790833,23.235278],"type":"Point"}
}