{
  "id": 2746388,
  "type": "Feature",
  "properties": {
    "tgn:hierarchy":[
        "tgn:2746388",
        "tgn:1000001",
        "tgn:7012149",
        "tgn:2000214",
        "tgn:7007158",
        "tgn:7029392"
    ],
    "tgn:id":2746388,
    "tgn:name":"W Mountain",
    "tgn:placetype":[
        "aat:300008798"
    ]
},
  "bbox": [],
  "geometry": {"coordinates":[-107.1333,39.8667],"type":"Point"}
}