{
  "id": 7409934,
  "type": "Feature",
  "properties": {
    "tgn:hierarchy":[
        "tgn:7409934",
        "tgn:1000001",
        "tgn:7005590",
        "tgn:7005560",
        "tgn:7029392"
    ],
    "tgn:id":7409934,
    "tgn:name":"El Jabal\u00ed, Cerro",
    "tgn:placetype":[
        "aat:300008795"
    ]
},
  "bbox": [],
  "geometry": {"coordinates":[-102.533333,18.641667],"type":"Point"}
}