{
  "id": 1076787,
  "type": "Feature",
  "properties": {
    "tgn:hierarchy":[
        "tgn:1076787",
        "tgn:1000004",
        "tgn:1001871",
        "tgn:7000198",
        "tgn:7029392"
    ],
    "tgn:id":1076787,
    "tgn:name":"Sadhaura",
    "tgn:placetype":[
        "aat:300008347"
    ]
},
  "bbox": [],
  "geometry": {"coordinates":[77.220928,30.38576],"type":"Point"}
}