{
  "id": 7214404,
  "type": "Feature",
  "properties": {
    "tgn:hierarchy":[
        "tgn:7214404",
        "tgn:7000096",
        "tgn:1000003",
        "tgn:7000084",
        "tgn:7029392"
    ],
    "tgn:id":7214404,
    "tgn:name":"Borkenhainkan",
    "tgn:placetype":[
        "aat:300008347"
    ]
},
  "bbox": [],
  "geometry": {"coordinates":[14.05,52.016667],"type":"Point"}
}