{
  "id": 2493399,
  "type": "Feature",
  "properties": {
    "tgn:hierarchy":[
        "tgn:2493399",
        "tgn:1000001",
        "tgn:7012149",
        "tgn:2000885",
        "tgn:7007256",
        "tgn:7029392"
    ],
    "tgn:id":2493399,
    "tgn:name":"Mars Branch",
    "tgn:placetype":[
        "aat:300008699"
    ]
},
  "bbox": [],
  "geometry": {"coordinates":[-90.6833,30.55],"type":"Point"}
}