{
  "id": 2497086,
  "type": "Feature",
  "properties": {
    "tgn:hierarchy":[
        "tgn:2497086",
        "tgn:1000001",
        "tgn:7012149",
        "tgn:1002561",
        "tgn:7007252",
        "tgn:7029392"
    ],
    "tgn:id":2497086,
    "tgn:name":"Maurey Ditch",
    "tgn:placetype":[
        "aat:300006075"
    ]
},
  "bbox": [],
  "geometry": {"coordinates":[-86.6833,41.4333],"type":"Point"}
}