<<<<<<< HEAD
{
  "id": 2155728,
  "type": "Feature",
  "properties": {
    "tgn:hierarchy":[
        "tgn:2155728",
        "tgn:7013388",
        "tgn:1000001",
        "tgn:7012149",
        "tgn:7007517",
        "tgn:7029392"
    ],
    "tgn:id":2155728,
    "tgn:name":"Bear Swamp",
    "tgn:placetype":[
        "aat:300008905"
    ]
},
  "bbox": [],
  "geometry": {"coordinates":[-73.25,42.2333],"type":"Point"}
}
=======
{"geometry":{"type":"Point","coordinates":[-73.250000,42.233300]},"type":"Feature","properties":{"hierarchy":["tgn:2155728","tgn:7013388","tgn:1000001","tgn:7012149","tgn:7007517","tgn:7029392"],"placetype":["aat:300008905"],"id":2155728,"name:xx":"Bear Swamp"}}
>>>>>>> 03f74aca74312dbeaf24d7e61306dd6a786dc3d0
