{
  "id": 7299592,
  "type": "Feature",
  "properties": {
    "tgn:hierarchy":[
        "tgn:7299592",
        "tgn:7002847",
        "tgn:1001647",
        "tgn:1000003",
        "tgn:1000095",
        "tgn:7029392"
    ],
    "tgn:id":7299592,
    "tgn:name":"Val de Santo Domingo",
    "tgn:placetype":[
        "aat:300008347"
    ]
},
  "bbox": [],
  "geometry": {"coordinates":[-4.316667,40.016667],"type":"Point"}
}