{
  "id": 1098346,
  "type": "Feature",
  "properties": {
    "tgn:hierarchy":[
        "tgn:1098346",
        "tgn:7000490",
        "tgn:1000006",
        "tgn:7001830",
        "tgn:7029392"
    ],
    "tgn:id":1098346,
    "tgn:name":"Toogoolawah",
    "tgn:placetype":[
        "aat:300008347"
    ]
},
  "bbox": [],
  "geometry": {"coordinates":[152.3167,-27.0833],"type":"Point"}
}