{
  "id": 2694963,
  "type": "Feature",
  "properties": {
    "tgn:hierarchy":[
        "tgn:2694963",
        "tgn:1000001",
        "tgn:7012149",
        "tgn:1002545",
        "tgn:7007157",
        "tgn:7029392"
    ],
    "tgn:id":2694963,
    "tgn:name":"Still Canyon",
    "tgn:placetype":[
        "aat:300008761"
    ]
},
  "bbox": [],
  "geometry": {"coordinates":[-120.1667,35.6167],"type":"Point"}
}