{
  "id": 2032710,
  "type": "Feature",
  "properties": {
    "tgn:hierarchy":[
        "tgn:2032710",
        "tgn:1000001",
        "tgn:7012149",
        "tgn:2000543",
        "tgn:7007252",
        "tgn:7029392"
    ],
    "tgn:id":2032710,
    "tgn:name":"Mackey",
    "tgn:placetype":[
        "aat:300008347"
    ]
},
  "bbox": [],
  "geometry": {"coordinates":[-87.3833,38.25],"type":"Point"}
}