{
  "id": 2583944,
  "type": "Feature",
  "properties": {
    "tgn:hierarchy":[
        "tgn:2583944",
        "tgn:1000001",
        "tgn:7012149",
        "tgn:2001708",
        "tgn:7007708",
        "tgn:7029392"
    ],
    "tgn:id":2583944,
    "tgn:name":"Pine Tree Spring",
    "tgn:placetype":[
        "aat:300008697"
    ]
},
  "bbox": [],
  "geometry": {"coordinates":[-118.3667,44.1167],"type":"Point"}
}