<<<<<<< HEAD
{
  "id": 7055117,
  "type": "Feature",
  "properties": {
    "tgn:hierarchy":[
        "tgn:7055117",
        "tgn:1003483",
        "tgn:1000003",
        "tgn:7003240",
        "tgn:1000080",
        "tgn:7029392"
    ],
    "tgn:id":7055117,
    "tgn:name":"Poggio San Giovanni",
    "tgn:placetype":[
        "aat:300008347"
    ]
},
  "bbox": [],
  "geometry": {"coordinates":[12.55,43.833333],"type":"Point"}
}
=======
{"geometry":{"type":"Point","coordinates":[12.550000,43.833333]},"type":"Feature","properties":{"hierarchy":["tgn:7055117","tgn:1003483","tgn:1000003","tgn:7003240","tgn:1000080","tgn:7029392"],"placetype":["aat:300008347"],"id":7055117,"name:xx":"Poggio San Giovanni"}}
>>>>>>> 03f74aca74312dbeaf24d7e61306dd6a786dc3d0
