{
  "id": 7285799,
  "type": "Feature",
  "properties": {
    "tgn:hierarchy":[
        "tgn:7285799",
        "tgn:1001695",
        "tgn:1000049",
        "tgn:1000002",
        "tgn:7029392"
    ],
    "tgn:id":7285799,
    "tgn:name":"Placetas, Loma de las",
    "tgn:placetype":[
        "aat:300387002"
    ]
},
  "bbox": [],
  "geometry": {"coordinates":[-71.083333,-34.566667],"type":"Point"}
}