{
  "id": 6001737,
  "type": "Feature",
  "properties": {
    "tgn:hierarchy":[
        "tgn:6001737",
        "tgn:7001242",
        "tgn:1001771",
        "tgn:1000166",
        "tgn:7029392"
    ],
    "tgn:id":6001737,
    "tgn:name":"Dixcove",
    "tgn:placetype":[
        "aat:300008347"
    ]
},
  "bbox": [],
  "geometry": {"coordinates":[-1.9833,4.8167],"type":"Point"}
}