{
  "id": 2718786,
  "type": "Feature",
  "properties": {
    "tgn:hierarchy":[
        "tgn:2718786",
        "tgn:1000001",
        "tgn:7012149",
        "tgn:2002266",
        "tgn:7013961",
        "tgn:7029392"
    ],
    "tgn:id":2718786,
    "tgn:name":"Thorn Bottom Pond",
    "tgn:placetype":[
        "aat:300006191"
    ]
},
  "bbox": [],
  "geometry": {"coordinates":[-78.7333,38.9667],"type":"Point"}
}