{
  "id": 2372053,
  "type": "Feature",
  "properties": {
    "tgn:hierarchy":[
        "tgn:2372053",
        "tgn:1000001",
        "tgn:7012149",
        "tgn:2002161",
        "tgn:7007919",
        "tgn:7029392"
    ],
    "tgn:id":2372053,
    "tgn:name":"Half Moon, The",
    "tgn:placetype":[
        "aat:300266640"
    ]
},
  "bbox": [],
  "geometry": {"coordinates":[-78.4833,39.05],"type":"Point"}
}