{
  "id": 2652141,
  "type": "Feature",
  "properties": {
    "tgn:hierarchy":[
        "tgn:2652141",
        "tgn:1000001",
        "tgn:7012149",
        "tgn:2002084",
        "tgn:7007826",
        "tgn:7029392"
    ],
    "tgn:id":2652141,
    "tgn:name":"Sellers Hill",
    "tgn:placetype":[
        "aat:300008798"
    ]
},
  "bbox": [],
  "geometry": {"coordinates":[-99.2667,33.1667],"type":"Point"}
}