{
  "id": 2414883,
  "type": "Feature",
  "properties": {
    "tgn:hierarchy":[
        "tgn:2414883",
        "tgn:1000001",
        "tgn:7012149",
        "tgn:2001896",
        "tgn:7007825",
        "tgn:7029392"
    ],
    "tgn:id":2414883,
    "tgn:name":"Isbell",
    "tgn:placetype":[
        "aat:300008347"
    ]
},
  "bbox": [],
  "geometry": {"coordinates":[-87.1333,35.5333],"type":"Point"}
}