{
  "id": 2456523,
  "type": "Feature",
  "properties": {
    "tgn:hierarchy":[
        "tgn:2456523",
        "tgn:1000001",
        "tgn:7012149",
        "tgn:2002087",
        "tgn:7007826",
        "tgn:7029392"
    ],
    "tgn:id":2456523,
    "tgn:name":"Little Indian Creek",
    "tgn:placetype":[
        "aat:300008706"
    ]
},
  "bbox": [],
  "geometry": {"coordinates":[-99.8833,29.35],"type":"Point"}
}