{
  "id": 2423615,
  "type": "Feature",
  "properties": {
    "tgn:hierarchy":[
        "tgn:2423615",
        "tgn:1000001",
        "tgn:7012149",
        "tgn:2000523",
        "tgn:7007251",
        "tgn:7029392"
    ],
    "tgn:id":2423615,
    "tgn:name":"John Mack Hollow",
    "tgn:placetype":[
        "aat:300008761"
    ]
},
  "bbox": [],
  "geometry": {"coordinates":[-88.65,37.5833],"type":"Point"}
}