{
  "id": 2455824,
  "type": "Feature",
  "properties": {
    "tgn:hierarchy":[
        "tgn:2455824",
        "tgn:1002300",
        "tgn:1000001",
        "tgn:7012149",
        "tgn:7007564",
        "tgn:7029392"
    ],
    "tgn:id":2455824,
    "tgn:name":"Little Greenough Pond",
    "tgn:placetype":[
        "aat:300008680"
    ]
},
  "bbox": [],
  "geometry": {"coordinates":[-71.1167,44.8333],"type":"Point"}
}