{
  "id": 1080461,
  "type": "Feature",
  "properties": {
    "tgn:hierarchy":[
        "tgn:1080461",
        "tgn:7000895",
        "tgn:1000004",
        "tgn:1000977",
        "tgn:1000120",
        "tgn:7029392"
    ],
    "tgn:id":1080461,
    "tgn:name":"Kasamatsu",
    "tgn:placetype":[
        "aat:300008347"
    ]
},
  "bbox": [],
  "geometry": {"coordinates":[136.7667,35.3667],"type":"Point"}
}