{
  "id": 2281342,
  "type": "Feature",
  "properties": {
    "tgn:hierarchy":[
        "tgn:2281342",
        "tgn:1000001",
        "tgn:2001943",
        "tgn:7012149",
        "tgn:7007826",
        "tgn:7029392"
    ],
    "tgn:id":2281342,
    "tgn:name":"Deep Tank",
    "tgn:placetype":[
        "aat:300006191"
    ]
},
  "bbox": [],
  "geometry": {"coordinates":[-101.4833,32.6167],"type":"Point"}
}