<<<<<<< HEAD
{
  "id": 2765550,
  "type": "Feature",
  "properties": {
    "tgn:hierarchy":[
        "tgn:2765550",
        "tgn:1000001",
        "tgn:2001801",
        "tgn:7012149",
        "tgn:7007713",
        "tgn:7029392"
    ],
    "tgn:id":2765550,
    "tgn:name":"White Cap",
    "tgn:placetype":[
        "aat:300008798"
    ]
},
  "bbox": [],
  "geometry": {"coordinates":[-103.9,45.4],"type":"Point"}
}
=======
{"geometry":{"type":"Point","coordinates":[-103.900000,45.400000]},"type":"Feature","properties":{"hierarchy":["tgn:2765550","tgn:1000001","tgn:2001801","tgn:7012149","tgn:7007713","tgn:7029392"],"placetype":["aat:300008798"],"id":2765550,"name:xx":"White Cap"}}
>>>>>>> 03f74aca74312dbeaf24d7e61306dd6a786dc3d0
