{
  "id": 7034979,
  "type": "Feature",
  "properties": {
    "tgn:hierarchy":[
        "tgn:7034979",
        "tgn:7002996",
        "tgn:1000003",
        "tgn:7002997",
        "tgn:1000080",
        "tgn:7029392"
    ],
    "tgn:id":7034979,
    "tgn:name":"Fontanellette",
    "tgn:placetype":[
        "aat:300008347"
    ]
},
  "bbox": [],
  "geometry": {"coordinates":[12.430556,45.828333],"type":"Point"}
}