{
  "id": 7291240,
  "type": "Feature",
  "properties": {
    "tgn:hierarchy":[
        "tgn:7291240",
        "tgn:1001699",
        "tgn:1000049",
        "tgn:1000002",
        "tgn:7029392"
    ],
    "tgn:id":7291240,
    "tgn:name":"El Roble",
    "tgn:placetype":[
        "aat:300000206"
    ]
},
  "bbox": [],
  "geometry": {"coordinates":[-72.883333,-40.483333],"type":"Point"}
}