{
  "id": 7276769,
  "type": "Feature",
  "properties": {
    "tgn:hierarchy":[
        "tgn:7276769",
        "tgn:1001699",
        "tgn:1000049",
        "tgn:1000002",
        "tgn:7029392"
    ],
    "tgn:id":7276769,
    "tgn:name":"San Antonio de Chadmo",
    "tgn:placetype":[
        "aat:300008347"
    ]
},
  "bbox": [],
  "geometry": {"coordinates":[-73.651111,-42.907778],"type":"Point"}
}