{
  "id": 1106841,
  "type": "Feature",
  "properties": {
    "tgn:hierarchy":[
        "tgn:1106841",
        "tgn:1001284",
        "tgn:1000004",
        "tgn:1000122",
        "tgn:7029392"
    ],
    "tgn:id":1106841,
    "tgn:name":"Turyu-san",
    "tgn:placetype":[
        "aat:300008795"
    ]
},
  "bbox": [],
  "geometry": {"coordinates":[128.7667,41.15],"type":"Point"}
}