{
  "id": 7220861,
  "type": "Feature",
  "properties": {
    "tgn:hierarchy":[
        "tgn:7220861",
        "tgn:7011369",
        "tgn:7017076",
        "tgn:1000003",
        "tgn:1000074",
        "tgn:7029392"
    ],
    "tgn:id":7220861,
    "tgn:name":"Var\u00e9la, \u00c1kra",
    "tgn:placetype":[
        "aat:300386846"
    ]
},
  "bbox": [],
  "geometry": {"coordinates":[21.666667,36.883333],"type":"Point"}
}