{
  "id": 7091215,
  "type": "Feature",
  "properties": {
    "tgn:hierarchy":[
        "tgn:7091215",
        "tgn:1000003",
        "tgn:7003678",
        "tgn:7000084",
        "tgn:7029392"
    ],
    "tgn:id":7091215,
    "tgn:name":"Vaitshainer H\u00f6he",
    "tgn:placetype":[
        "aat:300008777"
    ]
},
  "bbox": [],
  "geometry": {"coordinates":[9.35,50.516667],"type":"Point"}
}