{
  "id": 7532996,
  "type": "Feature",
  "properties": {
    "tgn:hierarchy":[
        "tgn:7532996",
        "tgn:7001242",
        "tgn:7016833",
        "tgn:1001335",
        "tgn:7029392"
    ],
    "tgn:id":7532996,
    "tgn:name:en":"Tur'at ash Shuqqah",
    "tgn:placetype":[
        "aat:300006075"
    ]
},
  "bbox": [],
  "geometry": {"coordinates":[30.799968,31.138737],"type":"Point"}
}