<<<<<<< HEAD
{
  "id": 2406451,
  "type": "Feature",
  "properties": {
    "tgn:hierarchy":[
        "tgn:2406451",
        "tgn:1002541",
        "tgn:1000001",
        "tgn:7012149",
        "tgn:7007711",
        "tgn:7029392"
    ],
    "tgn:id":2406451,
    "tgn:name":"Hungry Hill",
    "tgn:placetype":[
        "aat:300008798"
    ]
},
  "bbox": [],
  "geometry": {"coordinates":[-71.6,41.65],"type":"Point"}
}
=======
{"geometry":{"type":"Point","coordinates":[-71.600000,41.650000]},"type":"Feature","properties":{"hierarchy":["tgn:2406451","tgn:1002541","tgn:1000001","tgn:7012149","tgn:7007711","tgn:7029392"],"placetype":["aat:300008798"],"id":2406451,"name:xx":"Hungry Hill"}}
>>>>>>> 03f74aca74312dbeaf24d7e61306dd6a786dc3d0
