{
  "id": 1043166,
  "type": "Feature",
  "properties": {
    "tgn:hierarchy":[
        "tgn:1043166",
        "tgn:1003440",
        "tgn:1000003",
        "tgn:7003124",
        "tgn:1000080",
        "tgn:7029392"
    ],
    "tgn:id":1043166,
    "tgn:name":"Aldino",
    "tgn:placetype":[
        "aat:300008347"
    ]
},
  "bbox": [],
  "geometry": {"coordinates":[11.3333,46.3833],"type":"Point"}
}