{
  "id": 2491033,
  "type": "Feature",
  "properties": {
    "tgn:hierarchy":[
        "tgn:2491033",
        "tgn:2000001",
        "tgn:7002659",
        "tgn:1000001",
        "tgn:7012149",
        "tgn:7029392"
    ],
    "tgn:id":2491033,
    "tgn:name":"Manuel Point",
    "tgn:placetype":[
        "aat:300008850"
    ]
},
  "bbox": [],
  "geometry": {"coordinates":[-87.45,30.35],"type":"Point"}
}