{
  "id": 2079268,
  "type": "Feature",
  "properties": {
    "tgn:hierarchy":[
        "tgn:2079268",
        "tgn:1000001",
        "tgn:7012149",
        "tgn:1002835",
        "tgn:7007706",
        "tgn:7029392"
    ],
    "tgn:id":2079268,
    "tgn:name":"Denver",
    "tgn:placetype":[
        "aat:300008347"
    ]
},
  "bbox": [],
  "geometry": {"coordinates":[-83.05,39.1833],"type":"Point"}
}