{
  "id": 1018907,
  "type": "Feature",
  "properties": {
    "tgn:hierarchy":[
        "tgn:1018907",
        "tgn:7017438",
        "tgn:1000001",
        "tgn:7004643",
        "tgn:7029392"
    ],
    "tgn:id":1018907,
    "tgn:name":"Aguadilla",
    "tgn:placetype":[
        "aat:300008347"
    ]
},
  "bbox": [],
  "geometry": {"coordinates":[-67.1333,18.45],"type":"Point"}
}