<<<<<<< HEAD
{
  "id": 2153214,
  "type": "Feature",
  "properties": {
    "tgn:hierarchy":[
        "tgn:2153214",
        "tgn:1000001",
        "tgn:7016104",
        "tgn:7012149",
        "tgn:7007516",
        "tgn:7029392"
    ],
    "tgn:id":2153214,
    "tgn:name":"Bealls Island",
    "tgn:placetype":[
        "aat:300008791"
    ]
},
  "bbox": [],
  "geometry": {"coordinates":[-77.2333,39.0167],"type":"Point"}
}
=======
{"geometry":{"type":"Point","coordinates":[-77.233300,39.016700]},"type":"Feature","properties":{"hierarchy":["tgn:2153214","tgn:1000001","tgn:7016104","tgn:7012149","tgn:7007516","tgn:7029392"],"placetype":["aat:300008791"],"id":2153214,"name:xx":"Bealls Island"}}
>>>>>>> 03f74aca74312dbeaf24d7e61306dd6a786dc3d0
