{
  "id": 2047633,
  "type": "Feature",
  "properties": {
    "tgn:hierarchy":[
        "tgn:2047633",
        "tgn:1000001",
        "tgn:7016101",
        "tgn:7012149",
        "tgn:7007516",
        "tgn:7029392"
    ],
    "tgn:id":2047633,
    "tgn:name":"Knoxville",
    "tgn:placetype":[
        "aat:300008347"
    ]
},
  "bbox": [],
  "geometry": {"coordinates":[-77.65,39.3167],"type":"Point"}
}