{
  "id": 2408741,
  "type": "Feature",
  "properties": {
    "tgn:hierarchy":[
        "tgn:2408741",
        "tgn:1000001",
        "tgn:7012149",
        "tgn:1002518",
        "tgn:7007568",
        "tgn:7029392"
    ],
    "tgn:id":2408741,
    "tgn:name":"Hyde Creek",
    "tgn:placetype":[
        "aat:300008706"
    ]
},
  "bbox": [],
  "geometry": {"coordinates":[-75.8333,44.2333],"type":"Point"}
}