{
  "id": 7570986,
  "type": "Feature",
  "properties": {
    "tgn:hierarchy":[
        "tgn:7570986",
        "tgn:1000004",
        "tgn:7000198",
        "tgn:1001894",
        "tgn:7029392"
    ],
    "tgn:id":7570986,
    "tgn:name:en":"J\u0101mli",
    "tgn:placetype":[
        "aat:300008347"
    ]
},
  "bbox": [],
  "geometry": {"coordinates":[74.878993,22.970332],"type":"Point"}
}