{
  "id": 7546069,
  "type": "Feature",
  "properties": {
    "tgn:hierarchy":[
        "tgn:7546069",
        "tgn:1000004",
        "tgn:7000198",
        "tgn:1001895",
        "tgn:7029392"
    ],
    "tgn:id":7546069,
    "tgn:name:en":"Bhugaon",
    "tgn:placetype":[
        "aat:300008347"
    ]
},
  "bbox": [],
  "geometry": {"coordinates":[79.340339,21.089948],"type":"Point"}
}