{
  "id": 2428905,
  "type": "Feature",
  "properties": {
    "tgn:hierarchy":[
        "tgn:2428905",
        "tgn:1000001",
        "tgn:7012149",
        "tgn:2001538",
        "tgn:7007709",
        "tgn:7029392"
    ],
    "tgn:id":2428905,
    "tgn:name":"Jump-And Run Branch",
    "tgn:placetype":[
        "aat:300008699"
    ]
},
  "bbox": [],
  "geometry": {"coordinates":[-78.2333,34.9167],"type":"Point"}
}