{
  "id": 2743356,
  "type": "Feature",
  "properties": {
    "tgn:hierarchy":[
        "tgn:2743356",
        "tgn:7002659",
        "tgn:1000001",
        "tgn:7012149",
        "tgn:2000044",
        "tgn:7029392"
    ],
    "tgn:id":2743356,
    "tgn:name":"Vann Cave",
    "tgn:placetype":[
        "aat:300008746"
    ]
},
  "bbox": [],
  "geometry": {"coordinates":[-86.3833,34.5333],"type":"Point"}
}