{
  "id": 2485059,
  "type": "Feature",
  "properties": {
    "tgn:hierarchy":[
        "tgn:2485059",
        "tgn:1000001",
        "tgn:7012149",
        "tgn:2000348",
        "tgn:7007248",
        "tgn:7029392"
    ],
    "tgn:id":2485059,
    "tgn:name":"Lavender Mountain",
    "tgn:placetype":[
        "aat:300008798"
    ]
},
  "bbox": [],
  "geometry": {"coordinates":[-85.2333,34.3333],"type":"Point"}
}