{
  "id": 1022906,
  "type": "Feature",
  "properties": {
    "tgn:hierarchy":[
        "tgn:1022906",
        "tgn:7012827",
        "tgn:7002454",
        "tgn:1000047",
        "tgn:1000002",
        "tgn:7029392"
    ],
    "tgn:id":1022906,
    "tgn:name":"S\u00e3o Sim\u00e3o",
    "tgn:placetype":[
        "aat:300008347"
    ]
},
  "bbox": [],
  "geometry": {"coordinates":[-50.5333,-18.9667],"type":"Point"}
}