{
  "id": 7385888,
  "type": "Feature",
  "properties": {
    "tgn:hierarchy":[
        "tgn:7385888",
        "tgn:7005581",
        "tgn:1000001",
        "tgn:7005560",
        "tgn:7029392"
    ],
    "tgn:id":7385888,
    "tgn:name":"Pres\u00f3n de \u00c1lamo",
    "tgn:placetype":[
        "aat:300008347"
    ]
},
  "bbox": [],
  "geometry": {"coordinates":[-104.866667,28.233333],"type":"Point"}
}