{
  "id": 7505288,
  "type": "Feature",
  "properties": {
    "tgn:hierarchy":[
        "tgn:7505288",
        "tgn:1008380",
        "tgn:7520093",
        "tgn:1000226",
        "tgn:1000006",
        "tgn:7029392"
    ],
    "tgn:id":7505288,
    "tgn:name:en":"Wiritoa Lake",
    "tgn:placetype":[
        "aat:300008680"
    ]
},
  "bbox": [],
  "geometry": {"coordinates":[175.083333,-39.966667],"type":"Point"}
}