{
  "id": 7053659,
  "type": "Feature",
  "properties": {
    "tgn:hierarchy":[
        "tgn:7053659",
        "tgn:1003440",
        "tgn:1000003",
        "tgn:7003124",
        "tgn:1000080",
        "tgn:7029392"
    ],
    "tgn:id":7053659,
    "tgn:name":"Montechiaro",
    "tgn:placetype":[
        "aat:300008347"
    ]
},
  "bbox": [],
  "geometry": {"coordinates":[10.566667,46.633333],"type":"Point"}
}