{
  "id": 1086386,
  "type": "Feature",
  "properties": {
    "tgn:hierarchy":[
        "tgn:1086386",
        "tgn:1001236",
        "tgn:1000004",
        "tgn:7018455",
        "tgn:1000144",
        "tgn:7029392"
    ],
    "tgn:id":1086386,
    "tgn:name":"Hankendi",
    "tgn:placetype":[
        "aat:300008347"
    ]
},
  "bbox": [],
  "geometry": {"coordinates":[39.0667,38.5833],"type":"Point"}
}