{
  "id": 7483562,
  "type": "Feature",
  "properties": {
    "tgn:hierarchy":[
        "tgn:7483562",
        "tgn:1000004",
        "tgn:7471332",
        "tgn:1000141",
        "tgn:7029392"
    ],
    "tgn:id":7483562,
    "tgn:name":"Chongyi Qiao",
    "tgn:placetype":[
        "aat:300007836"
    ]
},
  "bbox": [],
  "geometry": {"coordinates":[120.961944,24.856389],"type":"Point"}
}