<<<<<<< HEAD
{
  "id": 7483562,
  "type": "Feature",
  "properties": {
    "tgn:hierarchy":[
        "tgn:7483562",
        "tgn:1000004",
        "tgn:7471332",
        "tgn:1000141",
        "tgn:7029392"
    ],
    "tgn:id":7483562,
    "tgn:name":"Chongyi Qiao",
    "tgn:placetype":[
        "aat:300007836"
    ]
},
  "bbox": [],
  "geometry": {"coordinates":[120.961944,24.856389],"type":"Point"}
}
=======
{"geometry":{"type":"Point","coordinates":[120.961944,24.856389]},"type":"Feature","properties":{"hierarchy":["tgn:7483562","tgn:1000004","tgn:7471332","tgn:1000141","tgn:7029392"],"placetype":["aat:300007836"],"id":7483562,"name:xx":"Chongyi Qiao"}}
>>>>>>> 03f74aca74312dbeaf24d7e61306dd6a786dc3d0
