{
  "id": 7083798,
  "type": "Feature",
  "properties": {
    "tgn:hierarchy":[
        "tgn:7083798",
        "tgn:7003692",
        "tgn:1000003",
        "tgn:7000084",
        "tgn:7029392"
    ],
    "tgn:id":7083798,
    "tgn:name":"Wilhelmsh\u00f6he",
    "tgn:placetype":[
        "aat:300000206"
    ]
},
  "bbox": [],
  "geometry": {"coordinates":[8.816667,48.45],"type":"Point"}
}