{
  "id": 7141470,
  "type": "Feature",
  "properties": {
    "tgn:hierarchy":[
        "tgn:7141470",
        "tgn:7003692",
        "tgn:1000003",
        "tgn:7000084",
        "tgn:7029392"
    ],
    "tgn:id":7141470,
    "tgn:name":"Linsenhof",
    "tgn:placetype":[
        "aat:300008347"
    ]
},
  "bbox": [],
  "geometry": {"coordinates":[9.466667,48.883333],"type":"Point"}
}