{
  "id": 2764524,
  "type": "Feature",
  "properties": {
    "tgn:hierarchy":[
        "tgn:2764524",
        "tgn:1000001",
        "tgn:7012149",
        "tgn:2000552",
        "tgn:7007252",
        "tgn:7029392"
    ],
    "tgn:id":2764524,
    "tgn:name":"Whipple Ditch",
    "tgn:placetype":[
        "aat:300006075"
    ]
},
  "bbox": [],
  "geometry": {"coordinates":[-87.9667,37.95],"type":"Point"}
}