{
  "id": 7570778,
  "type": "Feature",
  "properties": {
    "tgn:hierarchy":[
        "tgn:7570778",
        "tgn:1000004",
        "tgn:7031781",
        "tgn:7000198",
        "tgn:7029392"
    ],
    "tgn:id":7570778,
    "tgn:name:en":"H\u0101np River",
    "tgn:placetype":[
        "aat:300008699"
    ]
},
  "bbox": [],
  "geometry": {"coordinates":[81.75,21.766667],"type":"Point"}
}