{
  "id": 2482772,
  "type": "Feature",
  "properties": {
    "tgn:hierarchy":[
        "tgn:2482772",
        "tgn:1000001",
        "tgn:7006451",
        "tgn:7012149",
        "tgn:2000099",
        "tgn:7029392"
    ],
    "tgn:id":2482772,
    "tgn:name":"Largo Tank Number Two",
    "tgn:placetype":[
        "aat:300006191"
    ]
},
  "bbox": [],
  "geometry": {"coordinates":[-109.8667,34.0833],"type":"Point"}
}