{
  "id": 7513292,
  "type": "Feature",
  "properties": {
    "tgn:hierarchy":[
        "tgn:7513292",
        "tgn:7000508",
        "tgn:1008380",
        "tgn:1000226",
        "tgn:1000006",
        "tgn:7029392"
    ],
    "tgn:id":7513292,
    "tgn:name:en":"Grahams Beach",
    "tgn:placetype":[
        "aat:300008347"
    ]
},
  "bbox": [],
  "geometry": {"coordinates":[174.633333,-37.066667],"type":"Point"}
}