{
  "id": 7101765,
  "type": "Feature",
  "properties": {
    "tgn:hierarchy":[
        "tgn:7101765",
        "tgn:7003669",
        "tgn:1000003",
        "tgn:7000084",
        "tgn:7029392"
    ],
    "tgn:id":7101765,
    "tgn:name":"Rothensand",
    "tgn:placetype":[
        "aat:300008347"
    ]
},
  "bbox": [],
  "geometry": {"coordinates":[10.966667,49.783333],"type":"Point"}
}