{
  "id": 2271451,
  "type": "Feature",
  "properties": {
    "tgn:hierarchy":[
        "tgn:2271451",
        "tgn:1000001",
        "tgn:7012149",
        "tgn:1002926",
        "tgn:7007568",
        "tgn:7029392"
    ],
    "tgn:id":2271451,
    "tgn:name":"Culvertown",
    "tgn:placetype":[
        "aat:300008347"
    ]
},
  "bbox": [],
  "geometry": {"coordinates":[-74.55,41.55],"type":"Point"}
}