<<<<<<< HEAD
{
  "id": 7371925,
  "type": "Feature",
  "properties": {
    "tgn:hierarchy":[
        "tgn:7371925",
        "tgn:7005581",
        "tgn:1000001",
        "tgn:7005560",
        "tgn:7029392"
    ],
    "tgn:id":7371925,
    "tgn:name":"La Calera",
    "tgn:placetype":[
        "aat:300008347"
    ]
},
  "bbox": [],
  "geometry": {"coordinates":[-108.483333,28.25],"type":"Point"}
}
=======
{"geometry":{"type":"Point","coordinates":[-108.483333,28.250000]},"type":"Feature","properties":{"hierarchy":["tgn:7371925","tgn:7005581","tgn:1000001","tgn:7005560","tgn:7029392"],"placetype":["aat:300008347"],"id":7371925,"name:xx":"La Calera"}}
>>>>>>> 03f74aca74312dbeaf24d7e61306dd6a786dc3d0
