{
  "id": 1007400,
  "type": "Feature",
  "properties": {
    "tgn:hierarchy":[
        "tgn:1007400",
        "tgn:1000004",
        "tgn:1001231",
        "tgn:1000135",
        "tgn:7029392"
    ],
    "tgn:id":1007400,
    "tgn:name":"Hilaban Island",
    "tgn:placetype":[
        "aat:300008791"
    ]
},
  "bbox": [],
  "geometry": {"coordinates":[125.5667,12.05],"type":"Point"}
}