{
  "id": 2055791,
  "type": "Feature",
  "properties": {
    "tgn:hierarchy":[
        "tgn:2055791",
        "tgn:1000001",
        "tgn:7012149",
        "tgn:2001070",
        "tgn:7007521",
        "tgn:7029392"
    ],
    "tgn:id":2055791,
    "tgn:name":"Winthrop",
    "tgn:placetype":[
        "aat:300008347"
    ]
},
  "bbox": [],
  "geometry": {"coordinates":[-94.35,44.5333],"type":"Point"}
}