{
  "id": 1114061,
  "type": "Feature",
  "properties": {
    "tgn:hierarchy":[
        "tgn:1114061",
        "tgn:7005685",
        "tgn:1000001",
        "tgn:7013154",
        "tgn:7029392"
    ],
    "tgn:id":1114061,
    "tgn:name":"Adolphus Reach",
    "tgn:placetype":[
        "aat:300008713"
    ]
},
  "bbox": [],
  "geometry": {"coordinates":[-76.9167,44.0833],"type":"Point"}
}