{
  "id": 1013361,
  "type": "Feature",
  "properties": {
    "tgn:hierarchy":[
        "tgn:1013361",
        "tgn:7005735",
        "tgn:7005685",
        "tgn:1000001",
        "tgn:1007111",
        "tgn:7029392"
    ],
    "tgn:id":1013361,
    "tgn:name":"Ahousat",
    "tgn:placetype":[
        "aat:300008347"
    ]
},
  "bbox": [],
  "geometry": {"coordinates":[-126.05,49.2833],"type":"Point"}
}