{
  "id": 7592707,
  "type": "Feature",
  "properties": {
    "tgn:hierarchy":[
        "tgn:7592707",
        "tgn:1000004",
        "tgn:7000198",
        "tgn:7000799",
        "tgn:7029392"
    ],
    "tgn:id":7592707,
    "tgn:name:en":"Any\u0101na",
    "tgn:placetype":[
        "aat:300008347"
    ]
},
  "bbox": [],
  "geometry": {"coordinates":[74.255466,33.140233],"type":"Point"}
}