{
  "id": 2117640,
  "type": "Feature",
  "properties": {
    "tgn:hierarchy":[
        "tgn:2117640",
        "tgn:1000001",
        "tgn:7012149",
        "tgn:2002270",
        "tgn:7013961",
        "tgn:7029392"
    ],
    "tgn:id":2117640,
    "tgn:name":"Cabin Creek",
    "tgn:placetype":[
        "aat:300008347"
    ]
},
  "bbox": [],
  "geometry": {"coordinates":[-81.4667,38.1833],"type":"Point"}
}