{
  "id": 7417863,
  "type": "Feature",
  "properties": {
    "tgn:hierarchy":[
        "tgn:7417863",
        "tgn:7005584",
        "tgn:1000001",
        "tgn:7005560",
        "tgn:7029392"
    ],
    "tgn:id":7417863,
    "tgn:name":"Ojo de Agua de Espejo",
    "tgn:placetype":[
        "aat:300008347"
    ]
},
  "bbox": [],
  "geometry": {"coordinates":[-100.538889,20.457778],"type":"Point"}
}