{
  "id": 7529264,
  "type": "Feature",
  "properties": {
    "tgn:hierarchy":[
        "tgn:7529264",
        "tgn:7001242",
        "tgn:7001311",
        "tgn:7016833",
        "tgn:7029392"
    ],
    "tgn:id":7529264,
    "tgn:name:en":"Umm T\u0101ghir at Ta\u1e29t\u0101n\u012b, Jabal",
    "tgn:placetype":[
        "aat:300008795"
    ]
},
  "bbox": [],
  "geometry": {"coordinates":[33.781671,26.677486],"type":"Point"}
}