{
  "id": 2570095,
  "type": "Feature",
  "properties": {
    "tgn:hierarchy":[
        "tgn:2570095",
        "tgn:7006450",
        "tgn:2000069",
        "tgn:1000001",
        "tgn:7012149",
        "tgn:7029392"
    ],
    "tgn:id":2570095,
    "tgn:name":"Pass Fork",
    "tgn:placetype":[
        "aat:300008699"
    ]
},
  "bbox": [],
  "geometry": {"coordinates":[-153.0667,62.2167],"type":"Point"}
}