{
  "id": 2752340,
  "type": "Feature",
  "properties": {
    "tgn:hierarchy":[
        "tgn:2752340",
        "tgn:1002169",
        "tgn:1000001",
        "tgn:7012149",
        "tgn:7007255",
        "tgn:7029392"
    ],
    "tgn:id":2752340,
    "tgn:name":"Washington Branch",
    "tgn:placetype":[
        "aat:300008699"
    ]
},
  "bbox": [],
  "geometry": {"coordinates":[-83.7667,38.1833],"type":"Point"}
}