{
  "id": 2157056,
  "type": "Feature",
  "properties": {
    "tgn:hierarchy":[
        "tgn:2157056",
        "tgn:1000001",
        "tgn:7012149",
        "tgn:2001117",
        "tgn:7007522",
        "tgn:7029392"
    ],
    "tgn:id":2157056,
    "tgn:name":"Beaver Branch",
    "tgn:placetype":[
        "aat:300008699"
    ]
},
  "bbox": [],
  "geometry": {"coordinates":[-90.9833,31.65],"type":"Point"}
}