{
  "id": 2087214,
  "type": "Feature",
  "properties": {
    "tgn:hierarchy":[
        "tgn:2087214",
        "tgn:1000001",
        "tgn:7012149",
        "tgn:1002501",
        "tgn:7007710",
        "tgn:7029392"
    ],
    "tgn:id":2087214,
    "tgn:name":"Chevy Chase Heights",
    "tgn:placetype":[
        "aat:300008347"
    ]
},
  "bbox": [],
  "geometry": {"coordinates":[-79.1333,40.6333],"type":"Point"}
}