<<<<<<< HEAD
{
  "id": 2406717,
  "type": "Feature",
  "properties": {
    "tgn:hierarchy":[
        "tgn:2406717",
        "tgn:1000001",
        "tgn:7012149",
        "tgn:2001064",
        "tgn:7007521",
        "tgn:7029392"
    ],
    "tgn:id":2406717,
    "tgn:name":"Hunt Lake",
    "tgn:placetype":[
        "aat:300008680"
    ]
},
  "bbox": [],
  "geometry": {"coordinates":[-93.4333,44.3167],"type":"Point"}
}
=======
{"geometry":{"type":"Point","coordinates":[-93.433300,44.316700]},"type":"Feature","properties":{"hierarchy":["tgn:2406717","tgn:1000001","tgn:7012149","tgn:2001064","tgn:7007521","tgn:7029392"],"placetype":["aat:300008680"],"id":2406717,"name:xx":"Hunt Lake"}}
>>>>>>> 03f74aca74312dbeaf24d7e61306dd6a786dc3d0
