{
  "id": 7129863,
  "type": "Feature",
  "properties": {
    "tgn:hierarchy":[
        "tgn:7129863",
        "tgn:1000003",
        "tgn:7003677",
        "tgn:7000084",
        "tgn:7029392"
    ],
    "tgn:id":7129863,
    "tgn:name":"Meisen-Berg",
    "tgn:placetype":[
        "aat:300008777"
    ]
},
  "bbox": [],
  "geometry": {"coordinates":[6.95,50.583333],"type":"Point"}
}