{
  "id": 2752636,
  "type": "Feature",
  "properties": {
    "tgn:hierarchy":[
        "tgn:2752636",
        "tgn:7006450",
        "tgn:1000001",
        "tgn:2124076",
        "tgn:7012149",
        "tgn:7029392"
    ],
    "tgn:id":2752636,
    "tgn:name":"Wasp Cove",
    "tgn:placetype":[
        "aat:300132316"
    ]
},
  "bbox": [],
  "geometry": {"coordinates":[-130.9833,55.4167],"type":"Point"}
}