{
  "id": 7296584,
  "type": "Feature",
  "properties": {
    "tgn:hierarchy":[
        "tgn:7296584",
        "tgn:7002758",
        "tgn:7002841",
        "tgn:1000003",
        "tgn:1000095",
        "tgn:7029392"
    ],
    "tgn:id":7296584,
    "tgn:name":"Villar Gordo",
    "tgn:placetype":[
        "aat:300008347"
    ]
},
  "bbox": [],
  "geometry": {"coordinates":[-6.433333,37.65],"type":"Point"}
}