{
  "id": 7487069,
  "type": "Feature",
  "properties": {
    "tgn:hierarchy":[
        "tgn:7487069",
        "tgn:1000004",
        "tgn:7467799",
        "tgn:1000141",
        "tgn:7029392"
    ],
    "tgn:id":7487069,
    "tgn:name":"Shanliao",
    "tgn:placetype":[
        "aat:300008347"
    ]
},
  "bbox": [],
  "geometry": {"coordinates":[120.498611,24.092222],"type":"Point"}
}