{
  "id": 2304162,
  "type": "Feature",
  "properties": {
    "tgn:hierarchy":[
        "tgn:2304162",
        "tgn:1000001",
        "tgn:7012149",
        "tgn:2002383",
        "tgn:7007923",
        "tgn:7029392"
    ],
    "tgn:id":2304162,
    "tgn:name":"Eagles Nest Draw Reservoir Number 1",
    "tgn:placetype":[
        "aat:300006191"
    ]
},
  "bbox": [],
  "geometry": {"coordinates":[-107.9667,42.1167],"type":"Point"}
}