<<<<<<< HEAD
{
  "id": 7023617,
  "type": "Feature",
  "properties": {
    "tgn:hierarchy":[
        "tgn:7023617",
        "tgn:1000001",
        "tgn:7012149",
        "tgn:7007255",
        "tgn:7029392"
    ],
    "tgn:id":7023617,
    "tgn:name":"Orchard Branch",
    "tgn:placetype":[
        "aat:300008699"
    ]
},
  "bbox": [],
  "geometry": {"coordinates":[-83.0,37.15],"type":"Point"}
}
=======
{"geometry":{"type":"Point","coordinates":[-83.000000,37.150000]},"type":"Feature","properties":{"hierarchy":["tgn:7023617","tgn:1000001","tgn:7012149","tgn:7007255","tgn:7029392"],"placetype":["aat:300008699"],"id":7023617,"name:xx":"Orchard Branch"}}
>>>>>>> 03f74aca74312dbeaf24d7e61306dd6a786dc3d0
