{
  "id": 7277704,
  "type": "Feature",
  "properties": {
    "tgn:hierarchy":[
        "tgn:7277704",
        "tgn:1001623",
        "tgn:1000049",
        "tgn:1000002",
        "tgn:7029392"
    ],
    "tgn:id":7277704,
    "tgn:name":"Canal Moraleda",
    "tgn:placetype":[
        "aat:300387026"
    ]
},
  "bbox": [],
  "geometry": {"coordinates":[-73.429444,-43.920278],"type":"Point"}
}