{
  "id": 7482737,
  "type": "Feature",
  "properties": {
    "tgn:hierarchy":[
        "tgn:7482737",
        "tgn:7468018",
        "tgn:1000004",
        "tgn:1000141",
        "tgn:7029392"
    ],
    "tgn:id":7482737,
    "tgn:name":"Shiwu Gongmu",
    "tgn:placetype":[
        "aat:300266755"
    ]
},
  "bbox": [],
  "geometry": {"coordinates":[120.252778,23.516667],"type":"Point"}
}