<<<<<<< HEAD
{
  "id": 7482737,
  "type": "Feature",
  "properties": {
    "tgn:hierarchy":[
        "tgn:7482737",
        "tgn:7468018",
        "tgn:1000004",
        "tgn:1000141",
        "tgn:7029392"
    ],
    "tgn:id":7482737,
    "tgn:name":"Shiwu Gongmu",
    "tgn:placetype":[
        "aat:300266755"
    ]
},
  "bbox": [],
  "geometry": {"coordinates":[120.252778,23.516667],"type":"Point"}
}
=======
{"geometry":{"type":"Point","coordinates":[120.252778,23.516667]},"type":"Feature","properties":{"hierarchy":["tgn:7482737","tgn:7468018","tgn:1000004","tgn:1000141","tgn:7029392"],"placetype":["aat:300266755"],"id":7482737,"name:xx":"Shiwu Gongmu"}}
>>>>>>> 03f74aca74312dbeaf24d7e61306dd6a786dc3d0
