{
  "id": 7074416,
  "type": "Feature",
  "properties": {
    "tgn:hierarchy":[
        "tgn:7074416",
        "tgn:7003669",
        "tgn:1000003",
        "tgn:7000084",
        "tgn:7029392"
    ],
    "tgn:id":7074416,
    "tgn:name":"Stra\u00df",
    "tgn:placetype":[
        "aat:300000206"
    ]
},
  "bbox": [],
  "geometry": {"coordinates":[10.333333,47.783333],"type":"Point"}
}