{
  "id": 2115393,
  "type": "Feature",
  "properties": {
    "tgn:hierarchy":[
        "tgn:2115393",
        "tgn:1000001",
        "tgn:7012149",
        "tgn:1002553",
        "tgn:7007920",
        "tgn:7029392"
    ],
    "tgn:id":2115393,
    "tgn:name":"Bristol",
    "tgn:placetype":[
        "aat:300387016"
    ]
},
  "bbox": [],
  "geometry": {"coordinates":[-120.7833,47.1333],"type":"Point"}
}