{
  "id": 2398218,
  "type": "Feature",
  "properties": {
    "tgn:hierarchy":[
        "tgn:2398218",
        "tgn:1000001",
        "tgn:7012149",
        "tgn:7007826",
        "tgn:7029392"
    ],
    "tgn:id":2398218,
    "tgn:name":"Hoolia Creek",
    "tgn:placetype":[
        "aat:300008706"
    ]
},
  "bbox": [],
  "geometry": {"coordinates":[-97.25,31.2833],"type":"Point"}
}