{
  "id": 2729066,
  "type": "Feature",
  "properties": {
    "tgn:hierarchy":[
        "tgn:2729066",
        "tgn:1000001",
        "tgn:7012149",
        "tgn:2001251",
        "tgn:7007523",
        "tgn:7029392"
    ],
    "tgn:id":2729066,
    "tgn:name":"Trigger Creek",
    "tgn:placetype":[
        "aat:300008706"
    ]
},
  "bbox": [],
  "geometry": {"coordinates":[-93.15,36.5667],"type":"Point"}
}