{
  "id": 2005278,
  "type": "Feature",
  "properties": {
    "tgn:hierarchy":[
        "tgn:2005278",
        "tgn:7002659",
        "tgn:1000001",
        "tgn:7012149",
        "tgn:2000054",
        "tgn:7029392"
    ],
    "tgn:id":2005278,
    "tgn:name":"Shiloh",
    "tgn:placetype":[
        "aat:300008347",
        "aat:300387210"
    ]
},
  "bbox": [],
  "geometry": {"coordinates":[-85.7333,31.7667],"type":"Point"}
}