{
  "id": 7085483,
  "type": "Feature",
  "properties": {
    "tgn:hierarchy":[
        "tgn:7085483",
        "tgn:1000003",
        "tgn:7003677",
        "tgn:7000084",
        "tgn:7029392"
    ],
    "tgn:id":7085483,
    "tgn:name":"Westrup",
    "tgn:placetype":[
        "aat:300008347"
    ]
},
  "bbox": [],
  "geometry": {"coordinates":[8.45,52.433333],"type":"Point"}
}