{
  "id": 2218376,
  "type": "Feature",
  "properties": {
    "tgn:hierarchy":[
        "tgn:2218376",
        "tgn:1000001",
        "tgn:2001417",
        "tgn:7012149",
        "tgn:7007526",
        "tgn:7029392"
    ],
    "tgn:id":2218376,
    "tgn:name":"Candelaria Junction",
    "tgn:placetype":[
        "aat:300008347"
    ]
},
  "bbox": [],
  "geometry": {"coordinates":[-118.1667,38.1667],"type":"Point"}
}