{
  "id": 1038840,
  "type": "Feature",
  "properties": {
    "tgn:hierarchy":[
        "tgn:1038840",
        "tgn:7003669",
        "tgn:1000003",
        "tgn:7000084",
        "tgn:7029392"
    ],
    "tgn:id":1038840,
    "tgn:name":"Dollnstein",
    "tgn:placetype":[
        "aat:300008347"
    ]
},
  "bbox": [],
  "geometry": {"coordinates":[11.066667,48.866667],"type":"Point"}
}