{
  "id": 7528221,
  "type": "Feature",
  "properties": {
    "tgn:hierarchy":[
        "tgn:7528221",
        "tgn:7001242",
        "tgn:7016833",
        "tgn:1001335",
        "tgn:7029392"
    ],
    "tgn:id":7528221,
    "tgn:name":"Qaryah Raqm Tham\u0101niyah wa Khams\u016bn",
    "tgn:placetype":[
        "aat:300008347"
    ]
},
  "bbox": [],
  "geometry": {"coordinates":[31.221087,31.467318],"type":"Point"}
}