{
  "id": 7533005,
  "type": "Feature",
  "properties": {
    "tgn:hierarchy":[
        "tgn:7533005",
        "tgn:7001242",
        "tgn:7016833",
        "tgn:1001335",
        "tgn:7029392"
    ],
    "tgn:id":7533005,
    "tgn:name:en":"Mu\u1e29ay\u0163 Sh\u0101bah al Gharb\u012b",
    "tgn:placetype":[
        "aat:300006075"
    ]
},
  "bbox": [],
  "geometry": {"coordinates":[30.81617,31.155919],"type":"Point"}
}