{
  "id": 7550527,
  "type": "Feature",
  "properties": {
    "tgn:hierarchy":[
        "tgn:7550527",
        "tgn:1000004",
        "tgn:7000198",
        "tgn:1001895",
        "tgn:7029392"
    ],
    "tgn:id":7550527,
    "tgn:name:en":"Chapadgaon",
    "tgn:placetype":[
        "aat:300008347"
    ]
},
  "bbox": [],
  "geometry": {"coordinates":[75.161377,18.546219],"type":"Point"}
}