{
  "id": 7124464,
  "type": "Feature",
  "properties": {
    "tgn:hierarchy":[
        "tgn:7124464",
        "tgn:1000003",
        "tgn:7003682",
        "tgn:7000084",
        "tgn:7029392"
    ],
    "tgn:id":7124464,
    "tgn:name":"Ruine Neu Blankenheim",
    "tgn:placetype":[
        "aat:300008057"
    ]
},
  "bbox": [],
  "geometry": {"coordinates":[6.766667,50.35],"type":"Point"}
}