{
  "id": 7511082,
  "type": "Feature",
  "properties": {
    "tgn:hierarchy":[
        "tgn:7511082",
        "tgn:1008380",
        "tgn:1000226",
        "tgn:7018426",
        "tgn:1000006",
        "tgn:7029392"
    ],
    "tgn:id":7511082,
    "tgn:name:en":"Tataweka Island",
    "tgn:placetype":[
        "aat:300008791"
    ]
},
  "bbox": [],
  "geometry": {"coordinates":[175.433333,-36.833333],"type":"Point"}
}