{
  "id": 2438023,
  "type": "Feature",
  "properties": {
    "tgn:hierarchy":[
        "tgn:2438023",
        "tgn:1000001",
        "tgn:7012149",
        "tgn:2000230",
        "tgn:7007158",
        "tgn:7029392"
    ],
    "tgn:id":2438023,
    "tgn:name":"King Reservoir",
    "tgn:placetype":[
        "aat:300006191"
    ]
},
  "bbox": [],
  "geometry": {"coordinates":[-108.6667,38.8833],"type":"Point"}
}