{
  "id": 1020340,
  "type": "Feature",
  "properties": {
    "tgn:hierarchy":[
        "tgn:1020340",
        "tgn:1000525",
        "tgn:1000046",
        "tgn:1000002",
        "tgn:7029392"
    ],
    "tgn:id":1020340,
    "tgn:name":"Magdalena",
    "tgn:placetype":[
        "aat:300008347"
    ]
},
  "bbox": [],
  "geometry": {"coordinates":[-64.1167,-13.3667],"type":"Point"}
}