{
  "id": 2656073,
  "type": "Feature",
  "properties": {
    "tgn:hierarchy":[
        "tgn:2656073",
        "tgn:1000001",
        "tgn:7012149",
        "tgn:7007710",
        "tgn:7029392"
    ],
    "tgn:id":2656073,
    "tgn:name":"Shaw Run",
    "tgn:placetype":[
        "aat:300008699"
    ]
},
  "bbox": [],
  "geometry": {"coordinates":[-78.3667,40.6833],"type":"Point"}
}