<<<<<<< HEAD
{
  "id": 7112589,
  "type": "Feature",
  "properties": {
    "tgn:hierarchy":[
        "tgn:7112589",
        "tgn:1000003",
        "tgn:7003677",
        "tgn:7000084",
        "tgn:7029392"
    ],
    "tgn:id":7112589,
    "tgn:name":"Rheda",
    "tgn:placetype":[
        "aat:300387200"
    ]
},
  "bbox": [],
  "geometry": {"coordinates":[8.2,51.983333],"type":"Point"}
}
=======
{"geometry":{"type":"Point","coordinates":[8.200000,51.983333]},"type":"Feature","properties":{"hierarchy":["tgn:7112589","tgn:1000003","tgn:7003677","tgn:7000084","tgn:7029392"],"placetype":["aat:300387200"],"id":7112589,"name:xx":"Rheda"}}
>>>>>>> 03f74aca74312dbeaf24d7e61306dd6a786dc3d0
