{
  "id": 1125513,
  "type": "Feature",
  "properties": {
    "tgn:hierarchy":[
        "tgn:1125513",
        "tgn:7002445",
        "tgn:1000003",
        "tgn:7008591",
        "tgn:7029392"
    ],
    "tgn:id":1125513,
    "tgn:name:en":"Kennet",
    "tgn:placetype":[
        "aat:300008707",
        "aat:300008699"
    ]
},
  "bbox": [],
  "geometry": {"coordinates":[-0.966667,51.466667],"type":"Point"}
}