<<<<<<< HEAD
{
  "id": 7359699,
  "type": "Feature",
  "properties": {
    "tgn:hierarchy":[
        "tgn:7359699",
        "tgn:1000001",
        "tgn:1001937",
        "tgn:7005560",
        "tgn:7029392"
    ],
    "tgn:id":7359699,
    "tgn:name":"Concepci\u00f3n, Aguada",
    "tgn:placetype":[
        "aat:300387086"
    ]
},
  "bbox": [],
  "geometry": {"coordinates":[-88.933333,18.75],"type":"Point"}
}
=======
{"geometry":{"type":"Point","coordinates":[-88.933333,18.750000]},"type":"Feature","properties":{"hierarchy":["tgn:7359699","tgn:1000001","tgn:1001937","tgn:7005560","tgn:7029392"],"placetype":["aat:300387086"],"id":7359699,"name:xx":"Concepci\u00f3n, Aguada"}}
>>>>>>> 03f74aca74312dbeaf24d7e61306dd6a786dc3d0
