{
  "id": 2626044,
  "type": "Feature",
  "properties": {
    "tgn:hierarchy":[
        "tgn:2626044",
        "tgn:1000001",
        "tgn:2001411",
        "tgn:7012149",
        "tgn:7007526",
        "tgn:7029392"
    ],
    "tgn:id":2626044,
    "tgn:name":"Rocky Canyon Spring",
    "tgn:placetype":[
        "aat:300008697"
    ]
},
  "bbox": [],
  "geometry": {"coordinates":[-116.85,41.0833],"type":"Point"}
}