<<<<<<< HEAD
{
  "id": 7111060,
  "type": "Feature",
  "properties": {
    "tgn:hierarchy":[
        "tgn:7111060",
        "tgn:1000003",
        "tgn:7003688",
        "tgn:7000084",
        "tgn:7029392"
    ],
    "tgn:id":7111060,
    "tgn:name":"Rendsburg, Forst",
    "tgn:placetype":[
        "aat:300008863"
    ]
},
  "bbox": [],
  "geometry": {"coordinates":[9.55,54.35],"type":"Point"}
}
=======
{"geometry":{"type":"Point","coordinates":[9.550000,54.350000]},"type":"Feature","properties":{"hierarchy":["tgn:7111060","tgn:1000003","tgn:7003688","tgn:7000084","tgn:7029392"],"placetype":["aat:300008863"],"id":7111060,"name:xx":"Rendsburg, Forst"}}
>>>>>>> 03f74aca74312dbeaf24d7e61306dd6a786dc3d0
