{
  "id": 2442369,
  "type": "Feature",
  "properties": {
    "tgn:hierarchy":[
        "tgn:2442369",
        "tgn:1000001",
        "tgn:7012149",
        "tgn:1002472",
        "tgn:7007568",
        "tgn:7029392"
    ],
    "tgn:id":2442369,
    "tgn:name":"Kreskern Brook",
    "tgn:placetype":[
        "aat:300008699"
    ]
},
  "bbox": [],
  "geometry": {"coordinates":[-75.0333,43.3667],"type":"Point"}
}