{
  "id": 2718193,
  "type": "Feature",
  "properties": {
    "tgn:hierarchy":[
        "tgn:2718193",
        "tgn:1000001",
        "tgn:7012149",
        "tgn:2001293",
        "tgn:7007524",
        "tgn:7029392"
    ],
    "tgn:id":2718193,
    "tgn:name":"Thompson Creek",
    "tgn:placetype":[
        "aat:300008706"
    ]
},
  "bbox": [],
  "geometry": {"coordinates":[-110.5333,45.1333],"type":"Point"}
}