{
  "id": 7434740,
  "type": "Feature",
  "properties": {
    "tgn:hierarchy":[
        "tgn:7434740",
        "tgn:1000001",
        "tgn:7005595",
        "tgn:7005560",
        "tgn:7029392"
    ],
    "tgn:id":7434740,
    "tgn:name":"Vega",
    "tgn:placetype":[
        "aat:300007783"
    ]
},
  "bbox": [],
  "geometry": {"coordinates":[-108.75,26.166667],"type":"Point"}
}