{
  "id": 2704358,
  "type": "Feature",
  "properties": {
    "tgn:hierarchy":[
        "tgn:2704358",
        "tgn:1000001",
        "tgn:7012149",
        "tgn:2001918",
        "tgn:7007825",
        "tgn:7029392"
    ],
    "tgn:id":2704358,
    "tgn:name":"Sunnybrook Number Two",
    "tgn:placetype":[
        "aat:300008347"
    ]
},
  "bbox": [],
  "geometry": {"coordinates":[-82.2167,36.55],"type":"Point"}
}