{
  "id": 2138456,
  "type": "Feature",
  "properties": {
    "tgn:hierarchy":[
        "tgn:2138456",
        "tgn:7016099",
        "tgn:1000001",
        "tgn:7012149",
        "tgn:7007516",
        "tgn:7029392"
    ],
    "tgn:id":2138456,
    "tgn:name":"Ascot Estates",
    "tgn:placetype":[
        "aat:300008347"
    ]
},
  "bbox": [],
  "geometry": {"coordinates":[-76.55,39.5167],"type":"Point"}
}