{
  "id": 7033254,
  "type": "Feature",
  "properties": {
    "tgn:hierarchy":[
        "tgn:7033254",
        "tgn:7002995",
        "tgn:1000003",
        "tgn:7002997",
        "tgn:1000080",
        "tgn:7029392"
    ],
    "tgn:id":7033254,
    "tgn:name":"Villaregia",
    "tgn:placetype":[
        "aat:300008347"
    ]
},
  "bbox": [],
  "geometry": {"coordinates":[12.301667,44.958611],"type":"Point"}
}