{
  "id": 2244798,
  "type": "Feature",
  "properties": {
    "tgn:hierarchy":[
        "tgn:2244798",
        "tgn:1000001",
        "tgn:7012149",
        "tgn:2001873",
        "tgn:7007825",
        "tgn:7029392"
    ],
    "tgn:id":2244798,
    "tgn:name":"Cloud Shoals",
    "tgn:placetype":[
        "aat:300132348"
    ]
},
  "bbox": [],
  "geometry": {"coordinates":[-83.0833,36.3667],"type":"Point"}
}