{
  "id": 7468061,
  "type": "Feature",
  "properties": {
    "tgn:hierarchy":[
        "tgn:7468061",
        "tgn:7488858",
        "tgn:1000004",
        "tgn:1000141",
        "tgn:7029392"
    ],
    "tgn:id":7468061,
    "tgn:name":"Chepinglun",
    "tgn:placetype":[
        "aat:300008347"
    ]
},
  "bbox": [],
  "geometry": {"coordinates":[120.874934,23.885946],"type":"Point"}
}