{
  "id": 2085763,
  "type": "Feature",
  "properties": {
    "tgn:hierarchy":[
        "tgn:2085763",
        "tgn:1000001",
        "tgn:7012149",
        "tgn:1002994",
        "tgn:7007708",
        "tgn:7029392"
    ],
    "tgn:id":2085763,
    "tgn:name":"West Union",
    "tgn:placetype":[
        "aat:300008347",
        "aat:300387210"
    ]
},
  "bbox": [],
  "geometry": {"coordinates":[-122.8833,45.5667],"type":"Point"}
}