{
  "id": 2363966,
  "type": "Feature",
  "properties": {
    "tgn:hierarchy":[
        "tgn:2363966",
        "tgn:1000001",
        "tgn:7012149",
        "tgn:2000213",
        "tgn:7007158",
        "tgn:7029392"
    ],
    "tgn:id":2363966,
    "tgn:name":"Green Mountain",
    "tgn:placetype":[
        "aat:300008798"
    ]
},
  "bbox": [],
  "geometry": {"coordinates":[-105.65,38.5333],"type":"Point"}
}