{
  "id": 7189930,
  "type": "Feature",
  "properties": {
    "tgn:hierarchy":[
        "tgn:7189930",
        "tgn:7003669",
        "tgn:1000003",
        "tgn:7000084",
        "tgn:7029392"
    ],
    "tgn:id":7189930,
    "tgn:name":"Elmau-Berg",
    "tgn:placetype":[
        "aat:300008795"
    ]
},
  "bbox": [],
  "geometry": {"coordinates":[11.066667,47.65],"type":"Point"}
}