{
  "id": 2324284,
  "type": "Feature",
  "properties": {
    "tgn:hierarchy":[
        "tgn:2324284",
        "tgn:1000001",
        "tgn:7012149",
        "tgn:7019676",
        "tgn:7007566",
        "tgn:7029392"
    ],
    "tgn:id":2324284,
    "tgn:name":"Federal Mine",
    "tgn:placetype":[
        "aat:300000390"
    ]
},
  "bbox": [],
  "geometry": {"coordinates":[-107.9333,35.35],"type":"Point"}
}