{
  "id": 7467351,
  "type": "Feature",
  "properties": {
    "tgn:hierarchy":[
        "tgn:7467351",
        "tgn:7001004",
        "tgn:1000004",
        "tgn:1000141",
        "tgn:7029392"
    ],
    "tgn:id":7467351,
    "tgn:name":"Dafenjian Shan",
    "tgn:placetype":[
        "aat:300008798"
    ]
},
  "bbox": [],
  "geometry": {"coordinates":[121.046944,23.396389],"type":"Point"}
}