{
  "id": 7440924,
  "type": "Feature",
  "properties": {
    "tgn:hierarchy":[
        "tgn:7440924",
        "tgn:1000001",
        "tgn:7005597",
        "tgn:7005560",
        "tgn:7029392"
    ],
    "tgn:id":7440924,
    "tgn:name":"M\u00e1rtires del Agrarismo",
    "tgn:placetype":[
        "aat:300008347"
    ]
},
  "bbox": [],
  "geometry": {"coordinates":[-99.25,24.75],"type":"Point"}
}