{
  "id": 1053957,
  "type": "Feature",
  "properties": {
    "tgn:hierarchy":[
        "tgn:1053957",
        "tgn:1000003",
        "tgn:1003381",
        "tgn:7006660",
        "tgn:7029392"
    ],
    "tgn:id":1053957,
    "tgn:name":"Gaspra",
    "tgn:placetype":[
        "aat:300008347"
    ]
},
  "bbox": [],
  "geometry": {"coordinates":[34.1167,44.45],"type":"Point"}
}