<<<<<<< HEAD
{
  "id": 2401433,
  "type": "Feature",
  "properties": {
    "tgn:hierarchy":[
        "tgn:2401433",
        "tgn:2000258",
        "tgn:1000001",
        "tgn:7012149",
        "tgn:7007240",
        "tgn:7029392"
    ],
    "tgn:id":2401433,
    "tgn:name":"Horseshoe Bayou",
    "tgn:placetype":[
        "aat:300132316"
    ]
},
  "bbox": [],
  "geometry": {"coordinates":[-85.3833,30.0333],"type":"Point"}
}
=======
{"geometry":{"type":"Point","coordinates":[-85.383300,30.033300]},"type":"Feature","properties":{"hierarchy":["tgn:2401433","tgn:2000258","tgn:1000001","tgn:7012149","tgn:7007240","tgn:7029392"],"placetype":["aat:300132316"],"id":2401433,"name:xx":"Horseshoe Bayou"}}
>>>>>>> 03f74aca74312dbeaf24d7e61306dd6a786dc3d0
