<<<<<<< HEAD
{
  "id": 7355989,
  "type": "Feature",
  "properties": {
    "tgn:hierarchy":[
        "tgn:7355989",
        "tgn:1000001",
        "tgn:7005597",
        "tgn:7005560",
        "tgn:7029392"
    ],
    "tgn:id":7355989,
    "tgn:name":"Cerritos, Arroyo",
    "tgn:placetype":[
        "aat:300008699"
    ]
},
  "bbox": [],
  "geometry": {"coordinates":[-98.8,23.55],"type":"Point"}
}
=======
{"geometry":{"type":"Point","coordinates":[-98.800000,23.550000]},"type":"Feature","properties":{"hierarchy":["tgn:7355989","tgn:1000001","tgn:7005597","tgn:7005560","tgn:7029392"],"placetype":["aat:300008699"],"id":7355989,"name:xx":"Cerritos, Arroyo"}}
>>>>>>> 03f74aca74312dbeaf24d7e61306dd6a786dc3d0
