{
  "id": 2377356,
  "type": "Feature",
  "properties": {
    "tgn:hierarchy":[
        "tgn:2377356",
        "tgn:1000001",
        "tgn:7013619",
        "tgn:7012149",
        "tgn:7007252",
        "tgn:7029392"
    ],
    "tgn:id":2377356,
    "tgn:name":"Harner Hollow",
    "tgn:placetype":[
        "aat:300008761"
    ]
},
  "bbox": [],
  "geometry": {"coordinates":[-86.7667,38.6167],"type":"Point"}
}