{
  "id": 2221627,
  "type": "Feature",
  "properties": {
    "tgn:hierarchy":[
        "tgn:2221627",
        "tgn:1000001",
        "tgn:7012149",
        "tgn:1002518",
        "tgn:7007568",
        "tgn:7029392"
    ],
    "tgn:id":2221627,
    "tgn:name":"Carleton Island",
    "tgn:placetype":[
        "aat:300008791"
    ]
},
  "bbox": [],
  "geometry": {"coordinates":[-76.2833,44.1833],"type":"Point"}
}