{
  "id": 2588956,
  "type": "Feature",
  "properties": {
    "tgn:hierarchy":[
        "tgn:2588956",
        "tgn:1000001",
        "tgn:7006451",
        "tgn:2000092",
        "tgn:7012149",
        "tgn:7029392"
    ],
    "tgn:id":2588956,
    "tgn:name":"Pocomate Springs",
    "tgn:placetype":[
        "aat:300008697"
    ]
},
  "bbox": [],
  "geometry": {"coordinates":[-113.15,35.8167],"type":"Point"}
}