{
  "id": 7189874,
  "type": "Feature",
  "properties": {
    "tgn:hierarchy":[
        "tgn:7189874",
        "tgn:7003669",
        "tgn:1000003",
        "tgn:7000084",
        "tgn:7029392"
    ],
    "tgn:id":7189874,
    "tgn:name":"Ensbach",
    "tgn:placetype":[
        "aat:300008347"
    ]
},
  "bbox": [],
  "geometry": {"coordinates":[13.083333,48.85],"type":"Point"}
}