{
  "id": 7594367,
  "type": "Feature",
  "properties": {
    "tgn:hierarchy":[
        "tgn:7594367",
        "tgn:1001052",
        "tgn:1000004",
        "tgn:7018450",
        "tgn:1000144",
        "tgn:7029392"
    ],
    "tgn:id":7594367,
    "tgn:name":"Yoros Castle",
    "tgn:placetype":[
        "aat:300006891",
        "aat:300008057"
    ]
},
  "bbox": [],
  "geometry": {"coordinates":[29.097007,41.178766],"type":"Point"}
}