{
  "id": 2232605,
  "type": "Feature",
  "properties": {
    "tgn:hierarchy":[
        "tgn:2232605",
        "tgn:1000001",
        "tgn:7012149",
        "tgn:2001620",
        "tgn:7007706",
        "tgn:7029392"
    ],
    "tgn:id":2232605,
    "tgn:name":"Chapel Hill",
    "tgn:placetype":[
        "aat:300008347"
    ]
},
  "bbox": [],
  "geometry": {"coordinates":[-82.05,39.6167],"type":"Point"}
}