{
  "id": 7570121,
  "type": "Feature",
  "properties": {
    "tgn:hierarchy":[
        "tgn:7570121",
        "tgn:1000004",
        "tgn:7000198",
        "tgn:1001895",
        "tgn:7029392"
    ],
    "tgn:id":7570121,
    "tgn:name:en":"Navkh\u0101r",
    "tgn:placetype":[
        "aat:300008347"
    ]
},
  "bbox": [],
  "geometry": {"coordinates":[72.995556,18.518333],"type":"Point"}
}