{
  "id": 7516839,
  "type": "Feature",
  "properties": {
    "tgn:hierarchy":[
        "tgn:7516839",
        "tgn:1008380",
        "tgn:7520093",
        "tgn:1000226",
        "tgn:1000006",
        "tgn:7029392"
    ],
    "tgn:id":7516839,
    "tgn:name:en":"Ohangaia Stream",
    "tgn:placetype":[
        "aat:300008699"
    ]
},
  "bbox": [],
  "geometry": {"coordinates":[175.116667,-39.366667],"type":"Point"}
}