{
  "id": 2005478,
  "type": "Feature",
  "properties": {
    "tgn:hierarchy":[
        "tgn:2005478",
        "tgn:7002659",
        "tgn:1000001",
        "tgn:2000009",
        "tgn:7012149",
        "tgn:7029392"
    ],
    "tgn:id":2005478,
    "tgn:name":"Tecumseh",
    "tgn:placetype":[
        "aat:300008347"
    ]
},
  "bbox": [],
  "geometry": {"coordinates":[-85.4167,33.9833],"type":"Point"}
}