{
  "id": 1113696,
  "type": "Feature",
  "properties": {
    "tgn:hierarchy":[
        "tgn:1113696",
        "tgn:7006450",
        "tgn:1000001",
        "tgn:7012149",
        "tgn:2000082",
        "tgn:7029392"
    ],
    "tgn:id":1113696,
    "tgn:name":"Rudyerd Bay",
    "tgn:placetype":[
        "aat:300132316"
    ]
},
  "bbox": [],
  "geometry": {"coordinates":[-130.7333,55.5833],"type":"Point"}
}