{
  "id": 2131350,
  "type": "Feature",
  "properties": {
    "tgn:hierarchy":[
        "tgn:2131350",
        "tgn:1000001",
        "tgn:7012149",
        "tgn:1002468",
        "tgn:7007252",
        "tgn:7029392"
    ],
    "tgn:id":2131350,
    "tgn:name":"Alten Ditch",
    "tgn:placetype":[
        "aat:300006075"
    ]
},
  "bbox": [],
  "geometry": {"coordinates":[-85.2833,39.95],"type":"Point"}
}