<<<<<<< HEAD
{
  "id": 2333739,
  "type": "Feature",
  "properties": {
    "tgn:hierarchy":[
        "tgn:2333739",
        "tgn:1000001",
        "tgn:7006451",
        "tgn:2000095",
        "tgn:7012149",
        "tgn:7029392"
    ],
    "tgn:id":2333739,
    "tgn:name":"Foote Creek Mesa",
    "tgn:placetype":[
        "aat:300008798"
    ]
},
  "bbox": [],
  "geometry": {"coordinates":[-109.1333,33.6167],"type":"Point"}
}
=======
{"geometry":{"type":"Point","coordinates":[-109.133300,33.616700]},"type":"Feature","properties":{"hierarchy":["tgn:2333739","tgn:1000001","tgn:7006451","tgn:2000095","tgn:7012149","tgn:7029392"],"placetype":["aat:300008798"],"id":2333739,"name:xx":"Foote Creek Mesa"}}
>>>>>>> 03f74aca74312dbeaf24d7e61306dd6a786dc3d0
