<<<<<<< HEAD
{
  "id": 7360457,
  "type": "Feature",
  "properties": {
    "tgn:hierarchy":[
        "tgn:7360457",
        "tgn:7005581",
        "tgn:1000001",
        "tgn:7005560",
        "tgn:7029392"
    ],
    "tgn:id":7360457,
    "tgn:name":"Cuesta Prieta",
    "tgn:placetype":[
        "aat:300007783"
    ]
},
  "bbox": [],
  "geometry": {"coordinates":[-107.6,27.933333],"type":"Point"}
}
=======
{"geometry":{"type":"Point","coordinates":[-107.600000,27.933333]},"type":"Feature","properties":{"hierarchy":["tgn:7360457","tgn:7005581","tgn:1000001","tgn:7005560","tgn:7029392"],"placetype":["aat:300007783"],"id":7360457,"name:xx":"Cuesta Prieta"}}
>>>>>>> 03f74aca74312dbeaf24d7e61306dd6a786dc3d0
