<<<<<<< HEAD
{
  "id": 2405451,
  "type": "Feature",
  "properties": {
    "tgn:hierarchy":[
        "tgn:2405451",
        "tgn:1000001",
        "tgn:7012149",
        "tgn:2001274",
        "tgn:7007524",
        "tgn:7029392"
    ],
    "tgn:id":2405451,
    "tgn:name":"Hughes Bay",
    "tgn:placetype":[
        "aat:300132316"
    ]
},
  "bbox": [],
  "geometry": {"coordinates":[-114.1833,47.9667],"type":"Point"}
}
=======
{"geometry":{"type":"Point","coordinates":[-114.183300,47.966700]},"type":"Feature","properties":{"hierarchy":["tgn:2405451","tgn:1000001","tgn:7012149","tgn:2001274","tgn:7007524","tgn:7029392"],"placetype":["aat:300132316"],"id":2405451,"name:xx":"Hughes Bay"}}
>>>>>>> 03f74aca74312dbeaf24d7e61306dd6a786dc3d0
