{
  "id": 2105887,
  "type": "Feature",
  "properties": {
    "tgn:hierarchy":[
        "tgn:2105887",
        "tgn:1000001",
        "tgn:7012149",
        "tgn:1002485",
        "tgn:7007826",
        "tgn:7029392"
    ],
    "tgn:id":2105887,
    "tgn:name":"Mahoney",
    "tgn:placetype":[
        "aat:300008347"
    ]
},
  "bbox": [],
  "geometry": {"coordinates":[-95.4833,33.1833],"type":"Point"}
}