{
  "id": 2002808,
  "type": "Feature",
  "properties": {
    "tgn:hierarchy":[
        "tgn:2002808",
        "tgn:7002659",
        "tgn:1000001",
        "tgn:7012149",
        "tgn:2000040",
        "tgn:7029392"
    ],
    "tgn:id":2002808,
    "tgn:name":"Blanton",
    "tgn:placetype":[
        "aat:300008347",
        "aat:300387210"
    ]
},
  "bbox": [],
  "geometry": {"coordinates":[-85.1333,32.7333],"type":"Point"}
}