{
  "id": 7592982,
  "type": "Feature",
  "properties": {
    "tgn:hierarchy":[
        "tgn:7592982",
        "tgn:1000004",
        "tgn:7000198",
        "tgn:7000799",
        "tgn:7029392"
    ],
    "tgn:id":7592982,
    "tgn:name:en":"Lamber",
    "tgn:placetype":[
        "aat:300008347"
    ]
},
  "bbox": [],
  "geometry": {"coordinates":[74.355555,33.114078],"type":"Point"}
}