{
  "id": 2136374,
  "type": "Feature",
  "properties": {
    "tgn:hierarchy":[
        "tgn:2136374",
        "tgn:7014201",
        "tgn:1000001",
        "tgn:7012149",
        "tgn:7007239",
        "tgn:7029392"
    ],
    "tgn:id":2136374,
    "tgn:name":"Arc Corner",
    "tgn:placetype":[
        "aat:300008347"
    ]
},
  "bbox": [],
  "geometry": {"coordinates":[-75.7667,39.7167],"type":"Point"}
}