{
  "id": 7246323,
  "type": "Feature",
  "properties": {
    "tgn:hierarchy":[
        "tgn:7246323",
        "tgn:7007877",
        "tgn:1000003",
        "tgn:1000063",
        "tgn:4012014",
        "tgn:7029392"
    ],
    "tgn:id":7246323,
    "tgn:name":"Ferme de Bulingue",
    "tgn:placetype":[
        "aat:300000206"
    ]
},
  "bbox": [],
  "geometry": {"coordinates":[4.016667,50.65],"type":"Point"}
}