{
  "id": 7546843,
  "type": "Feature",
  "properties": {
    "tgn:hierarchy":[
        "tgn:7546843",
        "tgn:1000004",
        "tgn:7000198",
        "tgn:1001996",
        "tgn:7029392"
    ],
    "tgn:id":7546843,
    "tgn:name:en":"Balta",
    "tgn:placetype":[
        "aat:300008347"
    ]
},
  "bbox": [],
  "geometry": {"coordinates":[76.15,31.966667],"type":"Point"}
}