{
  "id": 7509392,
  "type": "Feature",
  "properties": {
    "tgn:hierarchy":[
        "tgn:7509392",
        "tgn:1009227",
        "tgn:1000226",
        "tgn:7016822",
        "tgn:1000006",
        "tgn:7029392"
    ],
    "tgn:id":7509392,
    "tgn:name:en":"Table Ridge",
    "tgn:placetype":[
        "aat:300266640"
    ]
},
  "bbox": [],
  "geometry": {"coordinates":[169.166667,-46.45],"type":"Point"}
}