<<<<<<< HEAD
{
  "id": 2764819,
  "type": "Feature",
  "properties": {
    "tgn:hierarchy":[
        "tgn:2764819",
        "tgn:1000001",
        "tgn:7012149",
        "tgn:2002380",
        "tgn:7007923",
        "tgn:7029392"
    ],
    "tgn:id":2764819,
    "tgn:name":"Whiskey Gulch",
    "tgn:placetype":[
        "aat:300008761"
    ]
},
  "bbox": [],
  "geometry": {"coordinates":[-105.1833,42.4833],"type":"Point"}
}
=======
{"geometry":{"type":"Point","coordinates":[-105.183300,42.483300]},"type":"Feature","properties":{"hierarchy":["tgn:2764819","tgn:1000001","tgn:7012149","tgn:2002380","tgn:7007923","tgn:7029392"],"placetype":["aat:300008761"],"id":2764819,"name:xx":"Whiskey Gulch"}}
>>>>>>> 03f74aca74312dbeaf24d7e61306dd6a786dc3d0
