{
  "id": 7033932,
  "type": "Feature",
  "properties": {
    "tgn:hierarchy":[
        "tgn:7033932",
        "tgn:7003136",
        "tgn:1000003",
        "tgn:7003080",
        "tgn:1000080",
        "tgn:7029392"
    ],
    "tgn:id":7033932,
    "tgn:name":"Orlando, Monte",
    "tgn:placetype":[
        "aat:300008777"
    ]
},
  "bbox": [],
  "geometry": {"coordinates":[13.577222,41.206667],"type":"Point"}
}