<<<<<<< HEAD
{
  "id": 7021493,
  "type": "Feature",
  "properties": {
    "tgn:hierarchy":[
        "tgn:7021493",
        "tgn:1000001",
        "tgn:7012149",
        "tgn:2002302",
        "tgn:7013961",
        "tgn:7029392"
    ],
    "tgn:id":7021493,
    "tgn:name":"Brush Run",
    "tgn:placetype":[
        "aat:300008699"
    ]
},
  "bbox": [],
  "geometry": {"coordinates":[-81.4667,39.0667],"type":"Point"}
}
=======
{"geometry":{"type":"Point","coordinates":[-81.466700,39.066700]},"type":"Feature","properties":{"hierarchy":["tgn:7021493","tgn:1000001","tgn:7012149","tgn:2002302","tgn:7013961","tgn:7029392"],"placetype":["aat:300008699"],"id":7021493,"name:xx":"Brush Run"}}
>>>>>>> 03f74aca74312dbeaf24d7e61306dd6a786dc3d0
