{
  "id": 1070132,
  "type": "Feature",
  "properties": {
    "tgn:hierarchy":[
        "tgn:1070132",
        "tgn:1000004",
        "tgn:7002077",
        "tgn:1000111",
        "tgn:7029392"
    ],
    "tgn:id":1070132,
    "tgn:name":"Luanhe",
    "tgn:placetype":[
        "aat:300008347"
    ]
},
  "bbox": [],
  "geometry": {"coordinates":[117.7333,40.95],"type":"Point"}
}