{
  "id": 2613695,
  "type": "Feature",
  "properties": {
    "tgn:hierarchy":[
        "tgn:2613695",
        "tgn:1000001",
        "tgn:7012149",
        "tgn:2000291",
        "tgn:7007240",
        "tgn:7029392"
    ],
    "tgn:id":2613695,
    "tgn:name":"Reedy Bay",
    "tgn:placetype":[
        "aat:300008905"
    ]
},
  "bbox": [],
  "geometry": {"coordinates":[-85.6667,30.6833],"type":"Point"}
}