{
  "id": 2512279,
  "type": "Feature",
  "properties": {
    "tgn:hierarchy":[
        "tgn:2512279",
        "tgn:1000001",
        "tgn:7012149",
        "tgn:1002746",
        "tgn:7007568",
        "tgn:7029392"
    ],
    "tgn:id":2512279,
    "tgn:name":"Mill Brook",
    "tgn:placetype":[
        "aat:300008699"
    ]
},
  "bbox": [],
  "geometry": {"coordinates":[-76.15,43.1167],"type":"Point"}
}