{
  "id": 2626668,
  "type": "Feature",
  "properties": {
    "tgn:hierarchy":[
        "tgn:2626668",
        "tgn:1000001",
        "tgn:7012149",
        "tgn:2001255",
        "tgn:7007523",
        "tgn:7029392"
    ],
    "tgn:id":2626668,
    "tgn:name":"Rocky Mountain",
    "tgn:placetype":[
        "aat:300008798"
    ]
},
  "bbox": [],
  "geometry": {"coordinates":[-90.5667,37.2667],"type":"Point"}
}