{
  "id": 7483902,
  "type": "Feature",
  "properties": {
    "tgn:hierarchy":[
        "tgn:7483902",
        "tgn:1000004",
        "tgn:7001014",
        "tgn:1000141",
        "tgn:7029392"
    ],
    "tgn:id":7483902,
    "tgn:name":"Fengnian Qiao",
    "tgn:placetype":[
        "aat:300007836"
    ]
},
  "bbox": [],
  "geometry": {"coordinates":[120.521111,23.699167],"type":"Point"}
}