{
  "id": 7405310,
  "type": "Feature",
  "properties": {
    "tgn:hierarchy":[
        "tgn:7405310",
        "tgn:7005585",
        "tgn:1000001",
        "tgn:7005560",
        "tgn:7029392"
    ],
    "tgn:id":7405310,
    "tgn:name":"La Parota",
    "tgn:placetype":[
        "aat:300008347"
    ]
},
  "bbox": [],
  "geometry": {"coordinates":[-101.033333,18.366667],"type":"Point"}
}