{
  "id": 7050314,
  "type": "Feature",
  "properties": {
    "tgn:hierarchy":[
        "tgn:7050314",
        "tgn:7003006",
        "tgn:1000003",
        "tgn:7002997",
        "tgn:1000080",
        "tgn:7029392"
    ],
    "tgn:id":7050314,
    "tgn:name":"Taglio Nuovissimo di Brenta",
    "tgn:placetype":[
        "aat:300006075"
    ]
},
  "bbox": [],
  "geometry": {"coordinates":[12.116667,45.433333],"type":"Point"}
}