{
  "id": 2173248,
  "type": "Feature",
  "properties": {
    "tgn:hierarchy":[
        "tgn:2173248",
        "tgn:1000001",
        "tgn:7012149",
        "tgn:2000364",
        "tgn:7007248",
        "tgn:7029392"
    ],
    "tgn:id":2173248,
    "tgn:name":"Bio",
    "tgn:placetype":[
        "aat:300008347"
    ]
},
  "bbox": [],
  "geometry": {"coordinates":[-82.9333,34.2667],"type":"Point"}
}