{
  "id": 2581314,
  "type": "Feature",
  "properties": {
    "tgn:hierarchy":[
        "tgn:2581314",
        "tgn:1000001",
        "tgn:7012149",
        "tgn:2001859",
        "tgn:7007825",
        "tgn:7029392"
    ],
    "tgn:id":2581314,
    "tgn:name":"Pillow Lake",
    "tgn:placetype":[
        "aat:300006191"
    ]
},
  "bbox": [],
  "geometry": {"coordinates":[-89.2833,36.0167],"type":"Point"}
}