{
  "id": 2414064,
  "type": "Feature",
  "properties": {
    "tgn:hierarchy":[
        "tgn:2414064",
        "tgn:1000001",
        "tgn:7012149",
        "tgn:2001456",
        "tgn:7007566",
        "tgn:7029392"
    ],
    "tgn:id":2414064,
    "tgn:name":"Iron Horse",
    "tgn:placetype":[
        "aat:300000390"
    ]
},
  "bbox": [],
  "geometry": {"coordinates":[-106.9333,33.9833],"type":"Point"}
}