{
  "id": 2661073,
  "type": "Feature",
  "properties": {
    "tgn:hierarchy":[
        "tgn:2661073",
        "tgn:1000001",
        "tgn:2000199",
        "tgn:7012149",
        "tgn:7007158",
        "tgn:7029392"
    ],
    "tgn:id":2661073,
    "tgn:name":"Short Gulch",
    "tgn:placetype":[
        "aat:300008761"
    ]
},
  "bbox": [],
  "geometry": {"coordinates":[-106.2333,38.8167],"type":"Point"}
}