{
  "id": 2258435,
  "type": "Feature",
  "properties": {
    "tgn:hierarchy":[
        "tgn:2258435",
        "tgn:1000001",
        "tgn:7012149",
        "tgn:2002299",
        "tgn:7013961",
        "tgn:7029392"
    ],
    "tgn:id":2258435,
    "tgn:name":"Cotton Hill",
    "tgn:placetype":[
        "aat:300008798"
    ]
},
  "bbox": [],
  "geometry": {"coordinates":[-82.3833,37.9333],"type":"Point"}
}