<<<<<<< HEAD
{
  "id": 2258435,
  "type": "Feature",
  "properties": {
    "tgn:hierarchy":[
        "tgn:2258435",
        "tgn:1000001",
        "tgn:7012149",
        "tgn:2002299",
        "tgn:7013961",
        "tgn:7029392"
    ],
    "tgn:id":2258435,
    "tgn:name":"Cotton Hill",
    "tgn:placetype":[
        "aat:300008798"
    ]
},
  "bbox": [],
  "geometry": {"coordinates":[-82.3833,37.9333],"type":"Point"}
}
=======
{"geometry":{"type":"Point","coordinates":[-82.383300,37.933300]},"type":"Feature","properties":{"hierarchy":["tgn:2258435","tgn:1000001","tgn:7012149","tgn:2002299","tgn:7013961","tgn:7029392"],"placetype":["aat:300008798"],"id":2258435,"name:xx":"Cotton Hill"}}
>>>>>>> 03f74aca74312dbeaf24d7e61306dd6a786dc3d0
