{
  "id": 2768725,
  "type": "Feature",
  "properties": {
    "tgn:hierarchy":[
        "tgn:2768725",
        "tgn:1000001",
        "tgn:7012149",
        "tgn:2000852",
        "tgn:7007255",
        "tgn:7029392"
    ],
    "tgn:id":2768725,
    "tgn:name":"Whitman Branch",
    "tgn:placetype":[
        "aat:300008699"
    ]
},
  "bbox": [],
  "geometry": {"coordinates":[-84.25,36.9167],"type":"Point"}
}