{
  "id": 1091813,
  "type": "Feature",
  "properties": {
    "tgn:hierarchy":[
        "tgn:1091813",
        "tgn:7001242",
        "tgn:7032820",
        "tgn:1000181",
        "tgn:7029392"
    ],
    "tgn:id":1091813,
    "tgn:name":"Tillab\u00e9ri",
    "tgn:placetype":[
        "aat:300008347"
    ]
},
  "bbox": [],
  "geometry": {"coordinates":[1.45,14.2167],"type":"Point"}
}