{
  "id": 2674630,
  "type": "Feature",
  "properties": {
    "tgn:hierarchy":[
        "tgn:2674630",
        "tgn:7006450",
        "tgn:1000001",
        "tgn:7012149",
        "tgn:2124005",
        "tgn:7029392"
    ],
    "tgn:id":2674630,
    "tgn:name":"Soakpak Mountain",
    "tgn:placetype":[
        "aat:300008798"
    ]
},
  "bbox": [],
  "geometry": {"coordinates":[-151.85,68.1833],"type":"Point"}
}