<<<<<<< HEAD
{
  "id": 7054872,
  "type": "Feature",
  "properties": {
    "tgn:hierarchy":[
        "tgn:7054872",
        "tgn:7024841",
        "tgn:7007850",
        "tgn:1000003",
        "tgn:1000080",
        "tgn:7029392"
    ],
    "tgn:id":7054872,
    "tgn:name":"Molino di Serrarossa",
    "tgn:placetype":[
        "aat:300008347"
    ]
},
  "bbox": [],
  "geometry": {"coordinates":[16.883333,39.066667],"type":"Point"}
}
=======
{"geometry":{"type":"Point","coordinates":[16.883333,39.066667]},"type":"Feature","properties":{"hierarchy":["tgn:7054872","tgn:7024841","tgn:7007850","tgn:1000003","tgn:1000080","tgn:7029392"],"placetype":["aat:300008347"],"id":7054872,"name:xx":"Molino di Serrarossa"}}
>>>>>>> 03f74aca74312dbeaf24d7e61306dd6a786dc3d0
