{
  "id": 2474956,
  "type": "Feature",
  "properties": {
    "tgn:hierarchy":[
        "tgn:2474956",
        "tgn:1000001",
        "tgn:7012149",
        "tgn:2002125",
        "tgn:7007827",
        "tgn:7029392"
    ],
    "tgn:id":2474956,
    "tgn:name":"Lower Water Hollow",
    "tgn:placetype":[
        "aat:300008761"
    ]
},
  "bbox": [],
  "geometry": {"coordinates":[-111.75,39.8667],"type":"Point"}
}