{
  "id": 2587320,
  "type": "Feature",
  "properties": {
    "tgn:hierarchy":[
        "tgn:2587320",
        "tgn:1000001",
        "tgn:7012149",
        "tgn:1003038",
        "tgn:7007517",
        "tgn:7029392"
    ],
    "tgn:id":2587320,
    "tgn:name":"Pleasant Brook",
    "tgn:placetype":[
        "aat:300008699"
    ]
},
  "bbox": [],
  "geometry": {"coordinates":[-72.0833,42.45],"type":"Point"}
}