{
  "id": 2109920,
  "type": "Feature",
  "properties": {
    "tgn:hierarchy":[
        "tgn:2109920",
        "tgn:1000001",
        "tgn:2002134",
        "tgn:7012149",
        "tgn:7007828",
        "tgn:7029392"
    ],
    "tgn:id":2109920,
    "tgn:name":"Peth",
    "tgn:placetype":[
        "aat:300008347",
        "aat:300387210"
    ]
},
  "bbox": [],
  "geometry": {"coordinates":[-72.6667,43.9667],"type":"Point"}
}