{
  "id": 2166263,
  "type": "Feature",
  "properties": {
    "tgn:hierarchy":[
        "tgn:2166263",
        "tgn:1000001",
        "tgn:7012149",
        "tgn:1002552",
        "tgn:7007920",
        "tgn:7029392"
    ],
    "tgn:id":2166263,
    "tgn:name":"Big Beef Creek",
    "tgn:placetype":[
        "aat:300008706"
    ]
},
  "bbox": [],
  "geometry": {"coordinates":[-122.85,47.55],"type":"Point"}
}