{
  "id": 7111906,
  "type": "Feature",
  "properties": {
    "tgn:hierarchy":[
        "tgn:7111906",
        "tgn:1000003",
        "tgn:7003677",
        "tgn:7000084",
        "tgn:7029392"
    ],
    "tgn:id":7111906,
    "tgn:name":"Ribbentrup",
    "tgn:placetype":[
        "aat:300000206"
    ]
},
  "bbox": [],
  "geometry": {"coordinates":[8.783333,52.083333],"type":"Point"}
}