{
  "id": 2692957,
  "type": "Feature",
  "properties": {
    "tgn:hierarchy":[
        "tgn:2692957",
        "tgn:1000001",
        "tgn:1002480",
        "tgn:7012149",
        "tgn:7007564",
        "tgn:7029392"
    ],
    "tgn:id":2692957,
    "tgn:name":"Steels Pond",
    "tgn:placetype":[
        "aat:300008680"
    ]
},
  "bbox": [],
  "geometry": {"coordinates":[-71.9667,43.0667],"type":"Point"}
}