{
  "id": 7503291,
  "type": "Feature",
  "properties": {
    "tgn:hierarchy":[
        "tgn:7503291",
        "tgn:1000004",
        "tgn:7490934",
        "tgn:1000141",
        "tgn:7029392"
    ],
    "tgn:id":7503291,
    "tgn:name":"Goujinglun",
    "tgn:placetype":[
        "aat:300008347"
    ]
},
  "bbox": [],
  "geometry": {"coordinates":[120.38,22.945833],"type":"Point"}
}