{
  "id": 2563497,
  "type": "Feature",
  "properties": {
    "tgn:hierarchy":[
        "tgn:2563497",
        "tgn:1000001",
        "tgn:7012149",
        "tgn:2001824",
        "tgn:7007713",
        "tgn:7029392"
    ],
    "tgn:id":2563497,
    "tgn:name":"Owl Lake",
    "tgn:placetype":[
        "aat:300008680"
    ]
},
  "bbox": [],
  "geometry": {"coordinates":[-97.1333,45.4167],"type":"Point"}
}