{
  "id": 7414971,
  "type": "Feature",
  "properties": {
    "tgn:hierarchy":[
        "tgn:7414971",
        "tgn:7005584",
        "tgn:1000001",
        "tgn:7005560",
        "tgn:7029392"
    ],
    "tgn:id":7414971,
    "tgn:name":"Las \u00c1nimas",
    "tgn:placetype":[
        "aat:300008347"
    ]
},
  "bbox": [],
  "geometry": {"coordinates":[-101.796667,20.407778],"type":"Point"}
}