{
  "id": 2377178,
  "type": "Feature",
  "properties": {
    "tgn:hierarchy":[
        "tgn:2377178",
        "tgn:1000001",
        "tgn:7016172",
        "tgn:7012149",
        "tgn:2000136",
        "tgn:7029392"
    ],
    "tgn:id":2377178,
    "tgn:name":"Harmon Creek",
    "tgn:placetype":[
        "aat:300008706"
    ]
},
  "bbox": [],
  "geometry": {"coordinates":[-91.7833,35.7667],"type":"Point"}
}