{
  "id": 7166272,
  "type": "Feature",
  "properties": {
    "tgn:hierarchy":[
        "tgn:7166272",
        "tgn:7003669",
        "tgn:1000003",
        "tgn:7000084",
        "tgn:7029392"
    ],
    "tgn:id":7166272,
    "tgn:name":"Hasen-Berg",
    "tgn:placetype":[
        "aat:300008777"
    ]
},
  "bbox": [],
  "geometry": {"coordinates":[9.05,49.866667],"type":"Point"}
}