{
  "id": 2501863,
  "type": "Feature",
  "properties": {
    "tgn:hierarchy":[
        "tgn:2501863",
        "tgn:1000001",
        "tgn:7012149",
        "tgn:2000279",
        "tgn:7007240",
        "tgn:7029392"
    ],
    "tgn:id":2501863,
    "tgn:name":"McKay Lake",
    "tgn:placetype":[
        "aat:300008680"
    ]
},
  "bbox": [],
  "geometry": {"coordinates":[-83.3333,30.3167],"type":"Point"}
}