{
  "id": 2342415,
  "type": "Feature",
  "properties": {
    "tgn:hierarchy":[
        "tgn:2342415",
        "tgn:1000001",
        "tgn:7013686",
        "tgn:7012149",
        "tgn:7007517",
        "tgn:7029392"
    ],
    "tgn:id":2342415,
    "tgn:name":"Fuller Pond",
    "tgn:placetype":[
        "aat:300008680"
    ]
},
  "bbox": [],
  "geometry": {"coordinates":[-72.6667,42.3833],"type":"Point"}
}