{
  "id": 2646660,
  "type": "Feature",
  "properties": {
    "tgn:hierarchy":[
        "tgn:2646660",
        "tgn:1000001",
        "tgn:7012149",
        "tgn:2000963",
        "tgn:7007520",
        "tgn:7029392"
    ],
    "tgn:id":2646660,
    "tgn:name":"Scales Creek",
    "tgn:placetype":[
        "aat:300008706"
    ]
},
  "bbox": [],
  "geometry": {"coordinates":[-88.4167,47.25],"type":"Point"}
}