<<<<<<< HEAD
{
  "id": 7050813,
  "type": "Feature",
  "properties": {
    "tgn:hierarchy":[
        "tgn:7050813",
        "tgn:7003170",
        "tgn:1000003",
        "tgn:7003125",
        "tgn:1000080",
        "tgn:7029392"
    ],
    "tgn:id":7050813,
    "tgn:name":"Massa, Monte",
    "tgn:placetype":[
        "aat:300008795"
    ]
},
  "bbox": [],
  "geometry": {"coordinates":[12.966667,42.616667],"type":"Point"}
}
=======
{"geometry":{"type":"Point","coordinates":[12.966667,42.616667]},"type":"Feature","properties":{"hierarchy":["tgn:7050813","tgn:7003170","tgn:1000003","tgn:7003125","tgn:1000080","tgn:7029392"],"placetype":["aat:300008795"],"id":7050813,"name:xx":"Massa, Monte"}}
>>>>>>> 03f74aca74312dbeaf24d7e61306dd6a786dc3d0
