{
  "id": 2152273,
  "type": "Feature",
  "properties": {
    "tgn:hierarchy":[
        "tgn:2152273",
        "tgn:1000001",
        "tgn:7012149",
        "tgn:2001139",
        "tgn:7007522",
        "tgn:7029392"
    ],
    "tgn:id":2152273,
    "tgn:name":"Bay Creek",
    "tgn:placetype":[
        "aat:300008706"
    ]
},
  "bbox": [],
  "geometry": {"coordinates":[-90.15,34.4833],"type":"Point"}
}