{
  "id": 2002965,
  "type": "Feature",
  "properties": {
    "tgn:hierarchy":[
        "tgn:2002965",
        "tgn:7002659",
        "tgn:1000001",
        "tgn:7012149",
        "tgn:2000065",
        "tgn:7029392"
    ],
    "tgn:id":2002965,
    "tgn:name":"Camden",
    "tgn:placetype":[
        "aat:300008347",
        "aat:300008416"
    ]
},
  "bbox": [],
  "geometry": {"coordinates":[-87.2833,31.9833],"type":"Point"}
}