<<<<<<< HEAD
{
  "id": 2257462,
  "type": "Feature",
  "properties": {
    "tgn:hierarchy":[
        "tgn:2257462",
        "tgn:1000001",
        "tgn:7006451",
        "tgn:7012149",
        "tgn:2000100",
        "tgn:7029392"
    ],
    "tgn:id":2257462,
    "tgn:name":"Corona Wash",
    "tgn:placetype":[
        "aat:300008699"
    ]
},
  "bbox": [],
  "geometry": {"coordinates":[-111.4,31.5167],"type":"Point"}
}
=======
{"geometry":{"type":"Point","coordinates":[-111.400000,31.516700]},"type":"Feature","properties":{"hierarchy":["tgn:2257462","tgn:1000001","tgn:7006451","tgn:7012149","tgn:2000100","tgn:7029392"],"placetype":["aat:300008699"],"id":2257462,"name:xx":"Corona Wash"}}
>>>>>>> 03f74aca74312dbeaf24d7e61306dd6a786dc3d0
