{
  "id": 2422053,
  "type": "Feature",
  "properties": {
    "tgn:hierarchy":[
        "tgn:2422053",
        "tgn:1000001",
        "tgn:7012149",
        "tgn:7007157",
        "tgn:1002566",
        "tgn:7029392"
    ],
    "tgn:id":2422053,
    "tgn:name":"Jim Dollar Mountain",
    "tgn:placetype":[
        "aat:300008798"
    ]
},
  "bbox": [],
  "geometry": {"coordinates":[-122.4667,38.8333],"type":"Point"}
}