{
  "id": 7108640,
  "type": "Feature",
  "properties": {
    "tgn:hierarchy":[
        "tgn:7108640",
        "tgn:1000003",
        "tgn:7003676",
        "tgn:7000084",
        "tgn:7029392"
    ],
    "tgn:id":7108640,
    "tgn:name":"Reislingen",
    "tgn:placetype":[
        "aat:300008347"
    ]
},
  "bbox": [],
  "geometry": {"coordinates":[10.833333,52.416667],"type":"Point"}
}