{
  "id": 2501817,
  "type": "Feature",
  "properties": {
    "tgn:hierarchy":[
        "tgn:2501817",
        "tgn:1000001",
        "tgn:7012149",
        "tgn:7007919",
        "tgn:7029392"
    ],
    "tgn:id":2501817,
    "tgn:name":"McKans Bay",
    "tgn:placetype":[
        "aat:300132316"
    ]
},
  "bbox": [],
  "geometry": {"coordinates":[-76.6667,37.7667],"type":"Point"}
}