{
  "id": 2539544,
  "type": "Feature",
  "properties": {
    "tgn:hierarchy":[
        "tgn:2539544",
        "tgn:1000001",
        "tgn:7012149",
        "tgn:1002440",
        "tgn:7007568",
        "tgn:7029392"
    ],
    "tgn:id":2539544,
    "tgn:name":"New Pond",
    "tgn:placetype":[
        "aat:300008680"
    ]
},
  "bbox": [],
  "geometry": {"coordinates":[-74.6167,43.9333],"type":"Point"}
}