{
  "id": 2135665,
  "type": "Feature",
  "properties": {
    "tgn:hierarchy":[
        "tgn:2135665",
        "tgn:1000001",
        "tgn:7012149",
        "tgn:2001440",
        "tgn:7007566",
        "tgn:7029392"
    ],
    "tgn:id":2135665,
    "tgn:name":"Apache Tank",
    "tgn:placetype":[
        "aat:300006191"
    ]
},
  "bbox": [],
  "geometry": {"coordinates":[-108.55,32.4333],"type":"Point"}
}