{
  "id": 7552040,
  "type": "Feature",
  "properties": {
    "tgn:hierarchy":[
        "tgn:7552040",
        "tgn:1000004",
        "tgn:7000198",
        "tgn:1001977",
        "tgn:7029392"
    ],
    "tgn:id":7552040,
    "tgn:name:en":"N\u0101r\u0101yanpur",
    "tgn:placetype":[
        "aat:300008347"
    ]
},
  "bbox": [],
  "geometry": {"coordinates":[87.693101,24.240987],"type":"Point"}
}