{
  "id": 7351879,
  "type": "Feature",
  "properties": {
    "tgn:hierarchy":[
        "tgn:7351879",
        "tgn:1000001",
        "tgn:7005589",
        "tgn:7005560",
        "tgn:7029392"
    ],
    "tgn:id":7351879,
    "tgn:name":"Borrego",
    "tgn:placetype":[
        "aat:300008347"
    ]
},
  "bbox": [],
  "geometry": {"coordinates":[-99.983333,23.833333],"type":"Point"}
}