{
  "id": 7384933,
  "type": "Feature",
  "properties": {
    "tgn:hierarchy":[
        "tgn:7384933",
        "tgn:7005581",
        "tgn:1000001",
        "tgn:7005560",
        "tgn:7029392"
    ],
    "tgn:id":7384933,
    "tgn:name":"Molinar",
    "tgn:placetype":[
        "aat:300007783"
    ]
},
  "bbox": [],
  "geometry": {"coordinates":[-106.216667,28.883333],"type":"Point"}
}