{
  "id": 7007970,
  "type": "Feature",
  "properties": {
    "tgn:hierarchy":[
        "tgn:7007970",
        "tgn:7018239",
        "tgn:1000003",
        "tgn:1000063",
        "tgn:7018236",
        "tgn:7029392"
    ],
    "tgn:id":7007970,
    "tgn:name":"Opwijk",
    "tgn:placetype":[
        "aat:300008347"
    ]
},
  "bbox": [],
  "geometry": {"coordinates":[4.184777,50.970174],"type":"Point"}
}