{
  "id": 7441188,
  "type": "Feature",
  "properties": {
    "tgn:hierarchy":[
        "tgn:7441188",
        "tgn:1001853",
        "tgn:1000001",
        "tgn:7005560",
        "tgn:7029392"
    ],
    "tgn:id":7441188,
    "tgn:name":"Santa Ana",
    "tgn:placetype":[
        "aat:300008347"
    ]
},
  "bbox": [],
  "geometry": {"coordinates":[-100.716667,28.15],"type":"Point"}
}