{
  "id": 2683816,
  "type": "Feature",
  "properties": {
    "tgn:hierarchy":[
        "tgn:2683816",
        "tgn:1000001",
        "tgn:7012149",
        "tgn:2002290",
        "tgn:7013961",
        "tgn:7029392"
    ],
    "tgn:id":2683816,
    "tgn:name":"Speed Branch",
    "tgn:placetype":[
        "aat:300008699"
    ]
},
  "bbox": [],
  "geometry": {"coordinates":[-81.4333,37.9167],"type":"Point"}
}