<<<<<<< HEAD
{
  "id": 2151889,
  "type": "Feature",
  "properties": {
    "tgn:hierarchy":[
        "tgn:2151889",
        "tgn:1000001",
        "tgn:7013368",
        "tgn:7012149",
        "tgn:7007709",
        "tgn:7029392"
    ],
    "tgn:id":2151889,
    "tgn:name":"Batts Crossroads",
    "tgn:placetype":[
        "aat:300008347"
    ]
},
  "bbox": [],
  "geometry": {"coordinates":[-77.0667,35.6833],"type":"Point"}
}
=======
{"geometry":{"type":"Point","coordinates":[-77.066700,35.683300]},"type":"Feature","properties":{"hierarchy":["tgn:2151889","tgn:1000001","tgn:7013368","tgn:7012149","tgn:7007709","tgn:7029392"],"placetype":["aat:300008347"],"id":2151889,"name:xx":"Batts Crossroads"}}
>>>>>>> 03f74aca74312dbeaf24d7e61306dd6a786dc3d0
