{
  "id": 2050386,
  "type": "Feature",
  "properties": {
    "tgn:hierarchy":[
        "tgn:2050386",
        "tgn:7013388",
        "tgn:1000001",
        "tgn:7012149",
        "tgn:7007517",
        "tgn:7029392"
    ],
    "tgn:id":2050386,
    "tgn:name":"Peru",
    "tgn:placetype":[
        "aat:300008347"
    ]
},
  "bbox": [],
  "geometry": {"coordinates":[-73.0333,42.4333],"type":"Point"}
}