{
  "id": 2161414,
  "type": "Feature",
  "properties": {
    "tgn:hierarchy":[
        "tgn:2161414",
        "tgn:1000001",
        "tgn:7012149",
        "tgn:2001868",
        "tgn:7007825",
        "tgn:7029392"
    ],
    "tgn:id":2161414,
    "tgn:name":"Bell Quarry",
    "tgn:placetype":[
        "aat:300000390"
    ]
},
  "bbox": [],
  "geometry": {"coordinates":[-83.35,36.1833],"type":"Point"}
}