{
  "id": 2776903,
  "type": "Feature",
  "properties": {
    "tgn:hierarchy":[
        "tgn:2776903",
        "tgn:7014201",
        "tgn:1000001",
        "tgn:7012149",
        "tgn:7007239",
        "tgn:7029392"
    ],
    "tgn:id":2776903,
    "tgn:name":"Windward",
    "tgn:placetype":[
        "aat:300008347"
    ]
},
  "bbox": [],
  "geometry": {"coordinates":[-75.6333,39.7667],"type":"Point"}
}