{
  "id": 1040020,
  "type": "Feature",
  "properties": {
    "tgn:hierarchy":[
        "tgn:1040020",
        "tgn:1000003",
        "tgn:7003677",
        "tgn:7000084",
        "tgn:7029392"
    ],
    "tgn:id":1040020,
    "tgn:name":"Langenbochum",
    "tgn:placetype":[
        "aat:300008347"
    ]
},
  "bbox": [],
  "geometry": {"coordinates":[7.116667,51.616667],"type":"Point"}
}