{
  "id": 7250768,
  "type": "Feature",
  "properties": {
    "tgn:hierarchy":[
        "tgn:7250768",
        "tgn:7003458",
        "tgn:1000003",
        "tgn:1000063",
        "tgn:7018236",
        "tgn:7029392"
    ],
    "tgn:id":7250768,
    "tgn:name":"Ooigem",
    "tgn:placetype":[
        "aat:300008347"
    ]
},
  "bbox": [],
  "geometry": {"coordinates":[3.336304,50.893336],"type":"Point"}
}