{
  "id": 7285542,
  "type": "Feature",
  "properties": {
    "tgn:hierarchy":[
        "tgn:7285542",
        "tgn:1001692",
        "tgn:1000049",
        "tgn:1000002",
        "tgn:7029392"
    ],
    "tgn:id":7285542,
    "tgn:name":"Puc\u00f3n",
    "tgn:placetype":[
        "aat:300000206"
    ]
},
  "bbox": [],
  "geometry": {"coordinates":[-71.916667,-39.266667],"type":"Point"}
}