{
  "id": 2169603,
  "type": "Feature",
  "properties": {
    "tgn:hierarchy":[
        "tgn:2169603",
        "tgn:1000001",
        "tgn:7012149",
        "tgn:7007157",
        "tgn:2000184",
        "tgn:7029392"
    ],
    "tgn:id":2169603,
    "tgn:name":"Big Meadows Reservoir",
    "tgn:placetype":[
        "aat:300006191"
    ]
},
  "bbox": [],
  "geometry": {"coordinates":[-120.3167,41.0167],"type":"Point"}
}