{
  "id": 2661929,
  "type": "Feature",
  "properties": {
    "tgn:hierarchy":[
        "tgn:2661929",
        "tgn:1000001",
        "tgn:7012149",
        "tgn:7007523",
        "tgn:7029392"
    ],
    "tgn:id":2661929,
    "tgn:name":"Shut-in Creek",
    "tgn:placetype":[
        "aat:300008706"
    ]
},
  "bbox": [],
  "geometry": {"coordinates":[-90.8333,37.6667],"type":"Point"}
}