{
  "id": 2343470,
  "type": "Feature",
  "properties": {
    "tgn:hierarchy":[
        "tgn:2343470",
        "tgn:1000001",
        "tgn:7012149",
        "tgn:1002416",
        "tgn:7007252",
        "tgn:7029392"
    ],
    "tgn:id":2343470,
    "tgn:name":"Galatia Ditch",
    "tgn:placetype":[
        "aat:300006075"
    ]
},
  "bbox": [],
  "geometry": {"coordinates":[-85.5833,40.4167],"type":"Point"}
}