{
  "id": 7094002,
  "type": "Feature",
  "properties": {
    "tgn:hierarchy":[
        "tgn:7094002",
        "tgn:7003669",
        "tgn:1000003",
        "tgn:7000084",
        "tgn:7029392"
    ],
    "tgn:id":7094002,
    "tgn:name":"Sch\u00f6nreit",
    "tgn:placetype":[
        "aat:300008347"
    ]
},
  "bbox": [],
  "geometry": {"coordinates":[12.533333,48.066667],"type":"Point"}
}