{
  "id": 2215942,
  "type": "Feature",
  "properties": {
    "tgn:hierarchy":[
        "tgn:2215942",
        "tgn:7006450",
        "tgn:1000001",
        "tgn:7012149",
        "tgn:2000086",
        "tgn:7029392"
    ],
    "tgn:id":2215942,
    "tgn:name":"Cameron Creek",
    "tgn:placetype":[
        "aat:300008706"
    ]
},
  "bbox": [],
  "geometry": {"coordinates":[-146.05,61.0833],"type":"Point"}
}