{
  "id": 2432887,
  "type": "Feature",
  "properties": {
    "tgn:hierarchy":[
        "tgn:2432887",
        "tgn:1000001",
        "tgn:1003029",
        "tgn:7012149",
        "tgn:7007828",
        "tgn:7029392"
    ],
    "tgn:id":2432887,
    "tgn:name":"Keets Brook",
    "tgn:placetype":[
        "aat:300008699"
    ]
},
  "bbox": [],
  "geometry": {"coordinates":[-72.6333,42.75],"type":"Point"}
}