{
  "id": 2520710,
  "type": "Feature",
  "properties": {
    "tgn:hierarchy":[
        "tgn:2520710",
        "tgn:1000001",
        "tgn:7012149",
        "tgn:2000234",
        "tgn:7007158",
        "tgn:7029392"
    ],
    "tgn:id":2520710,
    "tgn:name":"Monogram Mesa",
    "tgn:placetype":[
        "aat:300008798"
    ]
},
  "bbox": [],
  "geometry": {"coordinates":[-108.75,38.2167],"type":"Point"}
}