{
  "id": 7096991,
  "type": "Feature",
  "properties": {
    "tgn:hierarchy":[
        "tgn:7096991",
        "tgn:7003669",
        "tgn:1000003",
        "tgn:7000084",
        "tgn:7029392"
    ],
    "tgn:id":7096991,
    "tgn:name":"Stackendorf",
    "tgn:placetype":[
        "aat:300008347"
    ]
},
  "bbox": [],
  "geometry": {"coordinates":[11.083333,49.816667],"type":"Point"}
}