{
  "id": 7363562,
  "type": "Feature",
  "properties": {
    "tgn:hierarchy":[
        "tgn:7363562",
        "tgn:7005581",
        "tgn:1000001",
        "tgn:7005560",
        "tgn:7029392"
    ],
    "tgn:id":7363562,
    "tgn:name":"Rancho El Fundador",
    "tgn:placetype":[
        "aat:300000241"
    ]
},
  "bbox": [],
  "geometry": {"coordinates":[-105.883333,28.933333],"type":"Point"}
}