{
  "id": 2780683,
  "type": "Feature",
  "properties": {
    "tgn:hierarchy":[
        "tgn:2780683",
        "tgn:1000001",
        "tgn:7012149",
        "tgn:1002860",
        "tgn:7007826",
        "tgn:7029392"
    ],
    "tgn:id":2780683,
    "tgn:name":"Wood Lake",
    "tgn:placetype":[
        "aat:300008680"
    ]
},
  "bbox": [],
  "geometry": {"coordinates":[-95.1167,30.5833],"type":"Point"}
}