{
  "id": 2318141,
  "type": "Feature",
  "properties": {
    "tgn:hierarchy":[
        "tgn:2318141",
        "tgn:1000001",
        "tgn:2000582",
        "tgn:7012149",
        "tgn:7007253",
        "tgn:7029392"
    ],
    "tgn:id":2318141,
    "tgn:name":"Ensign Creek",
    "tgn:placetype":[
        "aat:300008706"
    ]
},
  "bbox": [],
  "geometry": {"coordinates":[-91.5833,42.75],"type":"Point"}
}