{
  "id": 7103791,
  "type": "Feature",
  "properties": {
    "tgn:hierarchy":[
        "tgn:7103791",
        "tgn:1000003",
        "tgn:7003678",
        "tgn:7000084",
        "tgn:7029392"
    ],
    "tgn:id":7103791,
    "tgn:name":"Schackau",
    "tgn:placetype":[
        "aat:300008347"
    ]
},
  "bbox": [],
  "geometry": {"coordinates":[9.866667,50.566667],"type":"Point"}
}