{
  "id": 1006741,
  "type": "Feature",
  "properties": {
    "tgn:hierarchy":[
        "tgn:1006741",
        "tgn:1000004",
        "tgn:1001231",
        "tgn:1000135",
        "tgn:7029392"
    ],
    "tgn:id":1006741,
    "tgn:name":"Catalaban Island",
    "tgn:placetype":[
        "aat:300008791"
    ]
},
  "bbox": [],
  "geometry": {"coordinates":[125.4667,11.85],"type":"Point"}
}