{
  "id": 7568033,
  "type": "Feature",
  "properties": {
    "tgn:hierarchy":[
        "tgn:7568033",
        "tgn:1000004",
        "tgn:7000198",
        "tgn:1001996",
        "tgn:7029392"
    ],
    "tgn:id":7568033,
    "tgn:name:en":"Madray\u0101n Protected Forest",
    "tgn:placetype":[
        "aat:300008863"
    ]
},
  "bbox": [],
  "geometry": {"coordinates":[77.015278,31.214167],"type":"Point"}
}