{
  "id": 7311133,
  "type": "Feature",
  "properties": {
    "tgn:hierarchy":[
        "tgn:7311133",
        "tgn:1001702",
        "tgn:1000049",
        "tgn:1000002",
        "tgn:7029392"
    ],
    "tgn:id":7311133,
    "tgn:name":"Montt, Caleta",
    "tgn:placetype":[
        "aat:300132317"
    ]
},
  "bbox": [],
  "geometry": {"coordinates":[-72.95,-51.916667],"type":"Point"}
}