{
  "id": 7446097,
  "type": "Feature",
  "properties": {
    "tgn:hierarchy":[
        "tgn:7446097",
        "tgn:7002444",
        "tgn:7008074",
        "tgn:1000003",
        "tgn:7008591",
        "tgn:7029392"
    ],
    "tgn:id":7446097,
    "tgn:name:en":"Stroquhan",
    "tgn:placetype":[
        "aat:300004792"
    ]
},
  "bbox": [],
  "geometry": {"coordinates":[-3.816667,55.133333],"type":"Point"}
}