<<<<<<< HEAD
{
  "id": 2154566,
  "type": "Feature",
  "properties": {
    "tgn:hierarchy":[
        "tgn:2154566",
        "tgn:1000001",
        "tgn:7012149",
        "tgn:2000445",
        "tgn:7007248",
        "tgn:7029392"
    ],
    "tgn:id":2154566,
    "tgn:name":"Bear Den Creek",
    "tgn:placetype":[
        "aat:300008706"
    ]
},
  "bbox": [],
  "geometry": {"coordinates":[-83.8167,34.7333],"type":"Point"}
}
=======
{"geometry":{"type":"Point","coordinates":[-83.816700,34.733300]},"type":"Feature","properties":{"hierarchy":["tgn:2154566","tgn:1000001","tgn:7012149","tgn:2000445","tgn:7007248","tgn:7029392"],"placetype":["aat:300008706"],"id":2154566,"name:xx":"Bear Den Creek"}}
>>>>>>> 03f74aca74312dbeaf24d7e61306dd6a786dc3d0
