{
  "id": 2192175,
  "type": "Feature",
  "properties": {
    "tgn:hierarchy":[
        "tgn:2192175",
        "tgn:1000001",
        "tgn:7012149",
        "tgn:2000850",
        "tgn:7007255",
        "tgn:7029392"
    ],
    "tgn:id":2192175,
    "tgn:name":"Brammer Hill",
    "tgn:placetype":[
        "aat:300008798"
    ]
},
  "bbox": [],
  "geometry": {"coordinates":[-84.65,36.8333],"type":"Point"}
}