{
  "id": 2741382,
  "type": "Feature",
  "properties": {
    "tgn:hierarchy":[
        "tgn:2741382",
        "tgn:1000001",
        "tgn:7012149",
        "tgn:7007524",
        "tgn:7029392"
    ],
    "tgn:id":2741382,
    "tgn:name":"Upsidedown Creek",
    "tgn:placetype":[
        "aat:300008706"
    ]
},
  "bbox": [],
  "geometry": {"coordinates":[-110.15,45.2667],"type":"Point"}
}