{
  "id": 7484979,
  "type": "Feature",
  "properties": {
    "tgn:hierarchy":[
        "tgn:7484979",
        "tgn:7488858",
        "tgn:1000004",
        "tgn:1000141",
        "tgn:7029392"
    ],
    "tgn:id":7484979,
    "tgn:name":"Xiachunyang",
    "tgn:placetype":[
        "aat:300008347"
    ]
},
  "bbox": [],
  "geometry": {"coordinates":[121.147778,24.025833],"type":"Point"}
}