<<<<<<< HEAD
{
  "id": 2157901,
  "type": "Feature",
  "properties": {
    "tgn:hierarchy":[
        "tgn:2157901",
        "tgn:1000001",
        "tgn:1002267",
        "tgn:7012149",
        "tgn:7007919",
        "tgn:7029392"
    ],
    "tgn:id":2157901,
    "tgn:name":"Beaver Lake",
    "tgn:placetype":[
        "aat:300006191"
    ]
},
  "bbox": [],
  "geometry": {"coordinates":[-77.5833,37.3833],"type":"Point"}
}
=======
{"geometry":{"type":"Point","coordinates":[-77.583300,37.383300]},"type":"Feature","properties":{"hierarchy":["tgn:2157901","tgn:1000001","tgn:1002267","tgn:7012149","tgn:7007919","tgn:7029392"],"placetype":["aat:300006191"],"id":2157901,"name:xx":"Beaver Lake"}}
>>>>>>> 03f74aca74312dbeaf24d7e61306dd6a786dc3d0
