{
  "id": 2330907,
  "type": "Feature",
  "properties": {
    "tgn:hierarchy":[
        "tgn:2330907",
        "tgn:1000001",
        "tgn:7012149",
        "tgn:2001547",
        "tgn:7007709",
        "tgn:7029392"
    ],
    "tgn:id":2330907,
    "tgn:name":"Flat Rock",
    "tgn:placetype":[
        "aat:300008347"
    ]
},
  "bbox": [],
  "geometry": {"coordinates":[-78.3667,36.3833],"type":"Point"}
}