{
  "id": 2685707,
  "type": "Feature",
  "properties": {
    "tgn:hierarchy":[
        "tgn:2685707",
        "tgn:1000001",
        "tgn:2000666",
        "tgn:7012149",
        "tgn:7007254",
        "tgn:7029392"
    ],
    "tgn:id":2685707,
    "tgn:name":"Spring Branch",
    "tgn:placetype":[
        "aat:300008699"
    ]
},
  "bbox": [],
  "geometry": {"coordinates":[-95.5167,39.8833],"type":"Point"}
}