{
  "id": 7431117,
  "type": "Feature",
  "properties": {
    "tgn:hierarchy":[
        "tgn:7431117",
        "tgn:1000001",
        "tgn:7005595",
        "tgn:7005560",
        "tgn:7029392"
    ],
    "tgn:id":7431117,
    "tgn:name":"Venecia",
    "tgn:placetype":[
        "aat:300008347"
    ]
},
  "bbox": [],
  "geometry": {"coordinates":[-108.366667,26.583333],"type":"Point"}
}