{
  "id": 7156869,
  "type": "Feature",
  "properties": {
    "tgn:hierarchy":[
        "tgn:7156869",
        "tgn:7003692",
        "tgn:1000003",
        "tgn:7000084",
        "tgn:7029392"
    ],
    "tgn:id":7156869,
    "tgn:name":"Killingen",
    "tgn:placetype":[
        "aat:300008347"
    ]
},
  "bbox": [],
  "geometry": {"coordinates":[10.216667,48.916667],"type":"Point"}
}