{
  "id": 2786304,
  "type": "Feature",
  "properties": {
    "tgn:hierarchy":[
        "tgn:2786304",
        "tgn:1000001",
        "tgn:7012149",
        "tgn:7021748",
        "tgn:7007826",
        "tgn:7029392"
    ],
    "tgn:id":2786304,
    "tgn:name":"Youngs Lake",
    "tgn:placetype":[
        "aat:300006191"
    ]
},
  "bbox": [],
  "geometry": {"coordinates":[-97.15,31.7333],"type":"Point"}
}