<<<<<<< HEAD
{
  "id": 2159393,
  "type": "Feature",
  "properties": {
    "tgn:hierarchy":[
        "tgn:2159393",
        "tgn:1000001",
        "tgn:7012149",
        "tgn:7007251",
        "tgn:7029392"
    ],
    "tgn:id":2159393,
    "tgn:name":"Bee Creek",
    "tgn:placetype":[
        "aat:300008706"
    ]
},
  "bbox": [],
  "geometry": {"coordinates":[-90.7,39.3833],"type":"Point"}
}
=======
{"geometry":{"type":"Point","coordinates":[-90.700000,39.383300]},"type":"Feature","properties":{"hierarchy":["tgn:2159393","tgn:1000001","tgn:7012149","tgn:7007251","tgn:7029392"],"placetype":["aat:300008706"],"id":2159393,"name:xx":"Bee Creek"}}
>>>>>>> 03f74aca74312dbeaf24d7e61306dd6a786dc3d0
