{
  "id": 2687742,
  "type": "Feature",
  "properties": {
    "tgn:hierarchy":[
        "tgn:2687742",
        "tgn:1000001",
        "tgn:7012149",
        "tgn:2000484",
        "tgn:7007250",
        "tgn:7029392"
    ],
    "tgn:id":2687742,
    "tgn:name":"Spring Slough",
    "tgn:placetype":[
        "aat:300008699"
    ]
},
  "bbox": [],
  "geometry": {"coordinates":[-111.85,43.7333],"type":"Point"}
}