{
  "id": 2712181,
  "type": "Feature",
  "properties": {
    "tgn:hierarchy":[
        "tgn:2712181",
        "tgn:1000001",
        "tgn:7012149",
        "tgn:2001255",
        "tgn:7007523",
        "tgn:7029392"
    ],
    "tgn:id":2712181,
    "tgn:name":"Tater Hill",
    "tgn:placetype":[
        "aat:300008798"
    ]
},
  "bbox": [],
  "geometry": {"coordinates":[-90.4833,37.25],"type":"Point"}
}