{
  "id": 2307818,
  "type": "Feature",
  "properties": {
    "tgn:hierarchy":[
        "tgn:2307818",
        "tgn:1000001",
        "tgn:2000458",
        "tgn:7012149",
        "tgn:7007250",
        "tgn:7029392"
    ],
    "tgn:id":2307818,
    "tgn:name":"East Fork Wood River",
    "tgn:placetype":[
        "aat:300008707"
    ]
},
  "bbox": [],
  "geometry": {"coordinates":[-114.0833,43.7167],"type":"Point"}
}