{
  "id": 2111666,
  "type": "Feature",
  "properties": {
    "tgn:hierarchy":[
        "tgn:2111666",
        "tgn:1000001",
        "tgn:7012149",
        "tgn:2002184",
        "tgn:7007919",
        "tgn:7029392"
    ],
    "tgn:id":2111666,
    "tgn:name":"Estes",
    "tgn:placetype":[
        "aat:300008347",
        "aat:300387210"
    ]
},
  "bbox": [],
  "geometry": {"coordinates":[-78.05,38.6167],"type":"Point"}
}