{
  "id": 7267190,
  "type": "Feature",
  "properties": {
    "tgn:hierarchy":[
        "tgn:7267190",
        "tgn:7003616",
        "tgn:1000003",
        "tgn:7016845",
        "tgn:7029392"
    ],
    "tgn:id":7267190,
    "tgn:name:nl":"Oudhof",
    "tgn:placetype":[
        "aat:300008680"
    ]
},
  "bbox": [],
  "geometry": {"coordinates":[5.683333,52.983333],"type":"Point"}
}