{
  "id": 7363952,
  "type": "Feature",
  "properties": {
    "tgn:hierarchy":[
        "tgn:7363952",
        "tgn:1000001",
        "tgn:1001937",
        "tgn:7005560",
        "tgn:7029392"
    ],
    "tgn:id":7363952,
    "tgn:name":"El Muerto",
    "tgn:placetype":[
        "aat:300387007"
    ]
},
  "bbox": [],
  "geometry": {"coordinates":[-88.433333,18.983333],"type":"Point"}
}