{
  "id": 7387695,
  "type": "Feature",
  "properties": {
    "tgn:hierarchy":[
        "tgn:7387695",
        "tgn:1000001",
        "tgn:7005589",
        "tgn:7005560",
        "tgn:7029392"
    ],
    "tgn:id":7387695,
    "tgn:name":"Potos\u00ed, Arroyo",
    "tgn:placetype":[
        "aat:300008699"
    ]
},
  "bbox": [],
  "geometry": {"coordinates":[-99.216667,24.966667],"type":"Point"}
}