{
  "id": 7592514,
  "type": "Feature",
  "properties": {
    "tgn:hierarchy":[
        "tgn:7592514",
        "tgn:1000004",
        "tgn:7000198",
        "tgn:7000799",
        "tgn:7029392"
    ],
    "tgn:id":7592514,
    "tgn:name:en":"Nambala N\u0101la",
    "tgn:placetype":[
        "aat:300008699"
    ]
},
  "bbox": [],
  "geometry": {"coordinates":[74.916667,32.855556],"type":"Point"}
}