{
  "id": 1015247,
  "type": "Feature",
  "properties": {
    "tgn:hierarchy":[
        "tgn:1015247",
        "tgn:7005685",
        "tgn:1000001",
        "tgn:7005803",
        "tgn:7029392"
    ],
    "tgn:id":1015247,
    "tgn:name":"Hunter River",
    "tgn:placetype":[
        "aat:300008347"
    ]
},
  "bbox": [],
  "geometry": {"coordinates":[-63.3667,46.35],"type":"Point"}
}