{
  "id": 7537335,
  "type": "Feature",
  "properties": {
    "tgn:hierarchy":[
        "tgn:7537335",
        "tgn:7001242",
        "tgn:7016833",
        "tgn:1001083",
        "tgn:7029392"
    ],
    "tgn:id":7537335,
    "tgn:name:en":"Quzzeih, 'Ilw el-",
    "tgn:placetype":[
        "aat:300008777"
    ]
},
  "bbox": [],
  "geometry": {"coordinates":[28.716667,28.55],"type":"Point"}
}