<<<<<<< HEAD
{
  "id": 2407531,
  "type": "Feature",
  "properties": {
    "tgn:hierarchy":[
        "tgn:2407531",
        "tgn:1000001",
        "tgn:7012149",
        "tgn:2000217",
        "tgn:7007158",
        "tgn:7029392"
    ],
    "tgn:id":2407531,
    "tgn:name":"Huntsman Gulch",
    "tgn:placetype":[
        "aat:300008761"
    ]
},
  "bbox": [],
  "geometry": {"coordinates":[-107.0167,38.2667],"type":"Point"}
}
=======
{"geometry":{"type":"Point","coordinates":[-107.016700,38.266700]},"type":"Feature","properties":{"hierarchy":["tgn:2407531","tgn:1000001","tgn:7012149","tgn:2000217","tgn:7007158","tgn:7029392"],"placetype":["aat:300008761"],"id":2407531,"name:xx":"Huntsman Gulch"}}
>>>>>>> 03f74aca74312dbeaf24d7e61306dd6a786dc3d0
