{
  "id": 2186337,
  "type": "Feature",
  "properties": {
    "tgn:hierarchy":[
        "tgn:2186337",
        "tgn:1000001",
        "tgn:7012149",
        "tgn:1002677",
        "tgn:7007251",
        "tgn:7029392"
    ],
    "tgn:id":2186337,
    "tgn:name":"Bond Creek",
    "tgn:placetype":[
        "aat:300008706"
    ]
},
  "bbox": [],
  "geometry": {"coordinates":[-90.25,38.2667],"type":"Point"}
}