<<<<<<< HEAD
{
  "id": 7246367,
  "type": "Feature",
  "properties": {
    "tgn:hierarchy":[
        "tgn:7246367",
        "tgn:7003465",
        "tgn:1000003",
        "tgn:1000063",
        "tgn:4012014",
        "tgn:7029392"
    ],
    "tgn:id":7246367,
    "tgn:name":"C\u00f4te Lambot",
    "tgn:placetype":[
        "aat:300008347"
    ]
},
  "bbox": [],
  "geometry": {"coordinates":[5.2,49.8],"type":"Point"}
}
=======
{"geometry":{"type":"Point","coordinates":[5.200000,49.800000]},"type":"Feature","properties":{"hierarchy":["tgn:7246367","tgn:7003465","tgn:1000003","tgn:1000063","tgn:4012014","tgn:7029392"],"placetype":["aat:300008347"],"id":7246367,"name:xx":"C\u00f4te Lambot"}}
>>>>>>> 03f74aca74312dbeaf24d7e61306dd6a786dc3d0
