{
  "id": 7416206,
  "type": "Feature",
  "properties": {
    "tgn:hierarchy":[
        "tgn:7416206",
        "tgn:1000001",
        "tgn:7005591",
        "tgn:7005560",
        "tgn:7029392"
    ],
    "tgn:id":7416206,
    "tgn:name:es":"San Juan La Laguna",
    "tgn:placetype":[
        "aat:300008347"
    ]
},
  "bbox": [],
  "geometry": {"coordinates":[-97.945833,17.000278],"type":"Point"}
}