<<<<<<< HEAD
{
  "id": 7111372,
  "type": "Feature",
  "properties": {
    "tgn:hierarchy":[
        "tgn:7111372",
        "tgn:1000003",
        "tgn:7003689",
        "tgn:7000084",
        "tgn:7029392"
    ],
    "tgn:id":7111372,
    "tgn:name":"Rittergasser-Berg",
    "tgn:placetype":[
        "aat:300008777"
    ]
},
  "bbox": [],
  "geometry": {"coordinates":[10.483333,51.033333],"type":"Point"}
}
=======
{"geometry":{"type":"Point","coordinates":[10.483333,51.033333]},"type":"Feature","properties":{"hierarchy":["tgn:7111372","tgn:1000003","tgn:7003689","tgn:7000084","tgn:7029392"],"placetype":["aat:300008777"],"id":7111372,"name:xx":"Rittergasser-Berg"}}
>>>>>>> 03f74aca74312dbeaf24d7e61306dd6a786dc3d0
