{
  "id": 1135769,
  "type": "Feature",
  "properties": {
    "tgn:hierarchy":[
        "tgn:1135769",
        "tgn:1000004",
        "tgn:1000105",
        "tgn:7029392"
    ],
    "tgn:id":1135769,
    "tgn:name":"Garai",
    "tgn:placetype":[
        "aat:300387055"
    ]
},
  "bbox": [],
  "geometry": {"coordinates":[89.5167,23.5333],"type":"Point"}
}