{
  "id": 7592901,
  "type": "Feature",
  "properties": {
    "tgn:hierarchy":[
        "tgn:7592901",
        "tgn:1000004",
        "tgn:7000198",
        "tgn:7000799",
        "tgn:7029392"
    ],
    "tgn:id":7592901,
    "tgn:name:en":"Seri",
    "tgn:placetype":[
        "aat:300008347"
    ]
},
  "bbox": [],
  "geometry": {"coordinates":[74.28639,33.085335],"type":"Point"}
}