{
  "id": 7539939,
  "type": "Feature",
  "properties": {
    "tgn:hierarchy":[
        "tgn:7539939",
        "tgn:7001242",
        "tgn:7001311",
        "tgn:7016833",
        "tgn:7029392"
    ],
    "tgn:id":7539939,
    "tgn:name:en":"Qashsh, W\u0101d\u012b al",
    "tgn:placetype":[
        "aat:300379998"
    ]
},
  "bbox": [],
  "geometry": {"coordinates":[33.147067,25.839214],"type":"Point"}
}