{
  "id": 2666713,
  "type": "Feature",
  "properties": {
    "tgn:hierarchy":[
        "tgn:2666713",
        "tgn:1000001",
        "tgn:7012149",
        "tgn:2001115",
        "tgn:7007522",
        "tgn:7029392"
    ],
    "tgn:id":2666713,
    "tgn:name":"Sixth Bayou",
    "tgn:placetype":[
        "aat:300008699"
    ]
},
  "bbox": [],
  "geometry": {"coordinates":[-88.5833,30.4167],"type":"Point"}
}