{
  "id": 2337798,
  "type": "Feature",
  "properties": {
    "tgn:hierarchy":[
        "tgn:2337798",
        "tgn:1000001",
        "tgn:7012149",
        "tgn:1002785",
        "tgn:7007920",
        "tgn:7029392"
    ],
    "tgn:id":2337798,
    "tgn:name":"Fox Creek",
    "tgn:placetype":[
        "aat:300008706"
    ]
},
  "bbox": [],
  "geometry": {"coordinates":[-122.1167,47.0167],"type":"Point"}
}