<<<<<<< HEAD
{
  "id": 2337798,
  "type": "Feature",
  "properties": {
    "tgn:hierarchy":[
        "tgn:2337798",
        "tgn:1000001",
        "tgn:7012149",
        "tgn:1002785",
        "tgn:7007920",
        "tgn:7029392"
    ],
    "tgn:id":2337798,
    "tgn:name":"Fox Creek",
    "tgn:placetype":[
        "aat:300008706"
    ]
},
  "bbox": [],
  "geometry": {"coordinates":[-122.1167,47.0167],"type":"Point"}
}
=======
{"geometry":{"type":"Point","coordinates":[-122.116700,47.016700]},"type":"Feature","properties":{"hierarchy":["tgn:2337798","tgn:1000001","tgn:7012149","tgn:1002785","tgn:7007920","tgn:7029392"],"placetype":["aat:300008706"],"id":2337798,"name:xx":"Fox Creek"}}
>>>>>>> 03f74aca74312dbeaf24d7e61306dd6a786dc3d0
