{
  "id": 2407044,
  "type": "Feature",
  "properties": {
    "tgn:hierarchy":[
        "tgn:2407044",
        "tgn:1000001",
        "tgn:7012149",
        "tgn:7007157",
        "tgn:1002867",
        "tgn:7029392"
    ],
    "tgn:id":2407044,
    "tgn:name":"Hunter Spring",
    "tgn:placetype":[
        "aat:300008697"
    ]
},
  "bbox": [],
  "geometry": {"coordinates":[-120.05,34.8667],"type":"Point"}
}