<<<<<<< HEAD
{
  "id": 2407044,
  "type": "Feature",
  "properties": {
    "tgn:hierarchy":[
        "tgn:2407044",
        "tgn:1000001",
        "tgn:7012149",
        "tgn:7007157",
        "tgn:1002867",
        "tgn:7029392"
    ],
    "tgn:id":2407044,
    "tgn:name":"Hunter Spring",
    "tgn:placetype":[
        "aat:300008697"
    ]
},
  "bbox": [],
  "geometry": {"coordinates":[-120.05,34.8667],"type":"Point"}
}
=======
{"geometry":{"type":"Point","coordinates":[-120.050000,34.866700]},"type":"Feature","properties":{"hierarchy":["tgn:2407044","tgn:1000001","tgn:7012149","tgn:7007157","tgn:1002867","tgn:7029392"],"placetype":["aat:300008697"],"id":2407044,"name:xx":"Hunter Spring"}}
>>>>>>> 03f74aca74312dbeaf24d7e61306dd6a786dc3d0
