{
  "id": 7018122,
  "type": "Feature",
  "properties": {
    "tgn:hierarchy":[
        "tgn:7018122",
        "tgn:1000004",
        "tgn:7002078",
        "tgn:1000111",
        "tgn:7029392"
    ],
    "tgn:id":7018122,
    "tgn:name":"She",
    "tgn:placetype":[
        "aat:300008707"
    ]
},
  "bbox": [],
  "geometry": {"coordinates":[114.5333,30.6833],"type":"Point"}
}