{
  "id": 2532060,
  "type": "Feature",
  "properties": {
    "tgn:hierarchy":[
        "tgn:2532060",
        "tgn:1000001",
        "tgn:7012149",
        "tgn:7007710",
        "tgn:7029392"
    ],
    "tgn:id":2532060,
    "tgn:name":"Muncy Hills",
    "tgn:placetype":[
        "aat:300386831"
    ]
},
  "bbox": [],
  "geometry": {"coordinates":[-76.6667,41.15],"type":"Point"}
}