{
  "id": 7454178,
  "type": "Feature",
  "properties": {
    "tgn:hierarchy":[
        "tgn:7454178",
        "tgn:7002445",
        "tgn:1000003",
        "tgn:7011961",
        "tgn:7008591",
        "tgn:7029392"
    ],
    "tgn:id":7454178,
    "tgn:name:en":"Chetnole",
    "tgn:placetype":[
        "aat:300008347"
    ]
},
  "bbox": [],
  "geometry": {"coordinates":[-2.566667,50.866667],"type":"Point"}
}