{
  "id": 7267687,
  "type": "Feature",
  "properties": {
    "tgn:hierarchy":[
        "tgn:7267687",
        "tgn:1000003",
        "tgn:7003626",
        "tgn:7016845",
        "tgn:7029392"
    ],
    "tgn:id":7267687,
    "tgn:name:nl":"Riggelenbos",
    "tgn:placetype":[
        "aat:300008863"
    ]
},
  "bbox": [],
  "geometry": {"coordinates":[6.633333,52.483333],"type":"Point"}
}