{
  "id": 7563060,
  "type": "Feature",
  "properties": {
    "tgn:hierarchy":[
        "tgn:7563060",
        "tgn:1000004",
        "tgn:7000198",
        "tgn:7016722",
        "tgn:7029392"
    ],
    "tgn:id":7563060,
    "tgn:name:en":"Delpura",
    "tgn:placetype":[
        "aat:300008347"
    ]
},
  "bbox": [],
  "geometry": {"coordinates":[79.2437,26.32294],"type":"Point"}
}