{
  "id": 7032188,
  "type": "Feature",
  "properties": {
    "tgn:hierarchy":[
        "tgn:7032188",
        "tgn:1000003",
        "tgn:1000070",
        "tgn:7002895",
        "tgn:7029392"
    ],
    "tgn:id":7032188,
    "tgn:name":"Maubois, Calanque de",
    "tgn:placetype":[
        "aat:300132317"
    ]
},
  "bbox": [],
  "geometry": {"coordinates":[6.931,43.466],"type":"Point"}
}