{
  "id": 2549776,
  "type": "Feature",
  "properties": {
    "tgn:hierarchy":[
        "tgn:2549776",
        "tgn:1000001",
        "tgn:7012149",
        "tgn:2002377",
        "tgn:7007923",
        "tgn:7029392"
    ],
    "tgn:id":2549776,
    "tgn:name":"North Thirtythree Mile Reservoir",
    "tgn:placetype":[
        "aat:300006191"
    ]
},
  "bbox": [],
  "geometry": {"coordinates":[-106.5833,43.2167],"type":"Point"}
}