<<<<<<< HEAD
{
  "id": 2764029,
  "type": "Feature",
  "properties": {
    "tgn:hierarchy":[
        "tgn:2764029",
        "tgn:1000001",
        "tgn:7012149",
        "tgn:2000551",
        "tgn:7007252",
        "tgn:7029392"
    ],
    "tgn:id":2764029,
    "tgn:name":"Wheeler Creek",
    "tgn:placetype":[
        "aat:300008706"
    ]
},
  "bbox": [],
  "geometry": {"coordinates":[-87.3,38.2667],"type":"Point"}
}
=======
{"geometry":{"type":"Point","coordinates":[-87.300000,38.266700]},"type":"Feature","properties":{"hierarchy":["tgn:2764029","tgn:1000001","tgn:7012149","tgn:2000551","tgn:7007252","tgn:7029392"],"placetype":["aat:300008706"],"id":2764029,"name:xx":"Wheeler Creek"}}
>>>>>>> 03f74aca74312dbeaf24d7e61306dd6a786dc3d0
