{
  "id": 2241144,
  "type": "Feature",
  "properties": {
    "tgn:hierarchy":[
        "tgn:2241144",
        "tgn:1000001",
        "tgn:7012149",
        "tgn:2002382",
        "tgn:7007923",
        "tgn:7029392"
    ],
    "tgn:id":2241144,
    "tgn:name":"Clark Draw",
    "tgn:placetype":[
        "aat:300008761"
    ]
},
  "bbox": [],
  "geometry": {"coordinates":[-110.45,43.15],"type":"Point"}
}