{
  "id": 2378864,
  "type": "Feature",
  "properties": {
    "tgn:hierarchy":[
        "tgn:2378864",
        "tgn:1000001",
        "tgn:7012149",
        "tgn:2000282",
        "tgn:7007240",
        "tgn:7029392"
    ],
    "tgn:id":2378864,
    "tgn:name":"Hart Lake",
    "tgn:placetype":[
        "aat:300008680"
    ]
},
  "bbox": [],
  "geometry": {"coordinates":[-81.8833,29.65],"type":"Point"}
}