{
  "id": 2232642,
  "type": "Feature",
  "properties": {
    "tgn:hierarchy":[
        "tgn:2232642",
        "tgn:1000001",
        "tgn:7012149",
        "tgn:2001719",
        "tgn:7007708",
        "tgn:7029392"
    ],
    "tgn:id":2232642,
    "tgn:name":"Chapel Spring",
    "tgn:placetype":[
        "aat:300008697"
    ]
},
  "bbox": [],
  "geometry": {"coordinates":[-119.6167,45.1167],"type":"Point"}
}