{
  "id": 7586761,
  "type": "Feature",
  "properties": {
    "tgn:hierarchy":[
        "tgn:7586761",
        "tgn:1000004",
        "tgn:7000198",
        "tgn:7000799",
        "tgn:7029392"
    ],
    "tgn:id":7586761,
    "tgn:name:en":"Tekipur",
    "tgn:placetype":[
        "aat:300008347"
    ]
},
  "bbox": [],
  "geometry": {"coordinates":[74.42967,34.466972],"type":"Point"}
}