{
  "id": 2469381,
  "type": "Feature",
  "properties": {
    "tgn:hierarchy":[
        "tgn:2469381",
        "tgn:1000001",
        "tgn:7012149",
        "tgn:2000740",
        "tgn:7007254",
        "tgn:7029392"
    ],
    "tgn:id":2469381,
    "tgn:name":"Longview Hill",
    "tgn:placetype":[
        "aat:300008798"
    ]
},
  "bbox": [],
  "geometry": {"coordinates":[-96.5833,39.1667],"type":"Point"}
}