{
  "id": 2515473,
  "type": "Feature",
  "properties": {
    "tgn:hierarchy":[
        "tgn:2515473",
        "tgn:1000001",
        "tgn:7012149",
        "tgn:2000548",
        "tgn:7007252",
        "tgn:7029392"
    ],
    "tgn:id":2515473,
    "tgn:name":"Mills Creek",
    "tgn:placetype":[
        "aat:300008706"
    ]
},
  "bbox": [],
  "geometry": {"coordinates":[-86.75,39.2167],"type":"Point"}
}