{
  "id": 2232897,
  "type": "Feature",
  "properties": {
    "tgn:hierarchy":[
        "tgn:2232897",
        "tgn:1000001",
        "tgn:7012149",
        "tgn:2001526",
        "tgn:7007709",
        "tgn:7029392"
    ],
    "tgn:id":2232897,
    "tgn:name":"Chappel Creek",
    "tgn:placetype":[
        "aat:300008706"
    ]
},
  "bbox": [],
  "geometry": {"coordinates":[-76.65,35.15],"type":"Point"}
}