{
  "id": 2313120,
  "type": "Feature",
  "properties": {
    "tgn:hierarchy":[
        "tgn:2313120",
        "tgn:1000001",
        "tgn:7012149",
        "tgn:2000927",
        "tgn:7007515",
        "tgn:7029392"
    ],
    "tgn:id":2313120,
    "tgn:name":"Elbow Lake",
    "tgn:placetype":[
        "aat:300008680"
    ]
},
  "bbox": [],
  "geometry": {"coordinates":[-68.7833,45.6333],"type":"Point"}
}