{
  "id": 2533249,
  "type": "Feature",
  "properties": {
    "tgn:hierarchy":[
        "tgn:2533249",
        "tgn:1000001",
        "tgn:7012149",
        "tgn:2002010",
        "tgn:7007826",
        "tgn:7029392"
    ],
    "tgn:id":2533249,
    "tgn:name":"Music Mountain",
    "tgn:placetype":[
        "aat:300008798"
    ]
},
  "bbox": [],
  "geometry": {"coordinates":[-104.3167,30.9667],"type":"Point"}
}