{
  "id": 2214577,
  "type": "Feature",
  "properties": {
    "tgn:hierarchy":[
        "tgn:2214577",
        "tgn:1000001",
        "tgn:7012149",
        "tgn:1002862",
        "tgn:7007920",
        "tgn:7029392"
    ],
    "tgn:id":2214577,
    "tgn:name":"Caldwell Point",
    "tgn:placetype":[
        "aat:300008850"
    ]
},
  "bbox": [],
  "geometry": {"coordinates":[-122.9667,48.5833],"type":"Point"}
}