{
  "id": 2456563,
  "type": "Feature",
  "properties": {
    "tgn:hierarchy":[
        "tgn:2456563",
        "tgn:1000001",
        "tgn:7012149",
        "tgn:7007157",
        "tgn:2000190",
        "tgn:7029392"
    ],
    "tgn:id":2456563,
    "tgn:name":"Little Inskip Hill",
    "tgn:placetype":[
        "aat:300008798"
    ]
},
  "bbox": [],
  "geometry": {"coordinates":[-121.95,40.35],"type":"Point"}
}