<<<<<<< HEAD
{
  "id": 7474255,
  "type": "Feature",
  "properties": {
    "tgn:hierarchy":[
        "tgn:7474255",
        "tgn:7488858",
        "tgn:1000004",
        "tgn:1000141",
        "tgn:7029392"
    ],
    "tgn:id":7474255,
    "tgn:name":"Dingshuiku",
    "tgn:placetype":[
        "aat:300008347"
    ]
},
  "bbox": [],
  "geometry": {"coordinates":[120.816419,23.959379],"type":"Point"}
}
=======
{"geometry":{"type":"Point","coordinates":[120.816419,23.959379]},"type":"Feature","properties":{"hierarchy":["tgn:7474255","tgn:7488858","tgn:1000004","tgn:1000141","tgn:7029392"],"placetype":["aat:300008347"],"id":7474255,"name:xx":"Dingshuiku"}}
>>>>>>> 03f74aca74312dbeaf24d7e61306dd6a786dc3d0
