{
  "id": 1053212,
  "type": "Feature",
  "properties": {
    "tgn:hierarchy":[
        "tgn:1053212",
        "tgn:1000004",
        "tgn:7013207",
        "tgn:7018214",
        "tgn:7002435",
        "tgn:7029392"
    ],
    "tgn:id":1053212,
    "tgn:name":"Bykovo",
    "tgn:placetype":[
        "aat:300008347"
    ]
},
  "bbox": [],
  "geometry": {"coordinates":[45.3167,49.6667],"type":"Point"}
}