<<<<<<< HEAD
{
  "id": 2250385,
  "type": "Feature",
  "properties": {
    "tgn:hierarchy":[
        "tgn:2250385",
        "tgn:1000001",
        "tgn:7012149",
        "tgn:2000964",
        "tgn:7007520",
        "tgn:7029392"
    ],
    "tgn:id":2250385,
    "tgn:name":"Colona Drain",
    "tgn:placetype":[
        "aat:300006075"
    ]
},
  "bbox": [],
  "geometry": {"coordinates":[-83.0167,43.7667],"type":"Point"}
}
=======
{"geometry":{"type":"Point","coordinates":[-83.016700,43.766700]},"type":"Feature","properties":{"hierarchy":["tgn:2250385","tgn:1000001","tgn:7012149","tgn:2000964","tgn:7007520","tgn:7029392"],"placetype":["aat:300006075"],"id":2250385,"name:xx":"Colona Drain"}}
>>>>>>> 03f74aca74312dbeaf24d7e61306dd6a786dc3d0
