{
  "id": 1091096,
  "type": "Feature",
  "properties": {
    "tgn:hierarchy":[
        "tgn:1091096",
        "tgn:7001242",
        "tgn:7016551",
        "tgn:1000175",
        "tgn:7029392"
    ],
    "tgn:id":1091096,
    "tgn:name":"And\u00e9ranboukane",
    "tgn:placetype":[
        "aat:300008347"
    ]
},
  "bbox": [],
  "geometry": {"coordinates":[3.0333,15.4333],"type":"Point"}
}