{
  "id": 2634160,
  "type": "Feature",
  "properties": {
    "tgn:hierarchy":[
        "tgn:2634160",
        "tgn:2000919",
        "tgn:1000001",
        "tgn:7012149",
        "tgn:7007515",
        "tgn:7029392"
    ],
    "tgn:id":2634160,
    "tgn:name":"Russell Crossing",
    "tgn:placetype":[
        "aat:300008347"
    ]
},
  "bbox": [],
  "geometry": {"coordinates":[-68.7333,46.65],"type":"Point"}
}