{
  "id": 2248558,
  "type": "Feature",
  "properties": {
    "tgn:hierarchy":[
        "tgn:2248558",
        "tgn:1000001",
        "tgn:7012149",
        "tgn:2001720",
        "tgn:7007708",
        "tgn:7029392"
    ],
    "tgn:id":2248558,
    "tgn:name":"Cold Spring Canyon",
    "tgn:placetype":[
        "aat:300008761"
    ]
},
  "bbox": [],
  "geometry": {"coordinates":[-118.7833,45.3167],"type":"Point"}
}