{
  "id": 7165200,
  "type": "Feature",
  "properties": {
    "tgn:hierarchy":[
        "tgn:7165200",
        "tgn:7003669",
        "tgn:1000003",
        "tgn:7000084",
        "tgn:7029392"
    ],
    "tgn:id":7165200,
    "tgn:name":"Huttstetten",
    "tgn:placetype":[
        "aat:300008347"
    ]
},
  "bbox": [],
  "geometry": {"coordinates":[13.133333,48.716667],"type":"Point"}
}