{
  "id": 2767405,
  "type": "Feature",
  "properties": {
    "tgn:hierarchy":[
        "tgn:2767405",
        "tgn:1000001",
        "tgn:1002218",
        "tgn:7012149",
        "tgn:7007157",
        "tgn:7029392"
    ],
    "tgn:id":2767405,
    "tgn:name":"White Spring Ridge",
    "tgn:placetype":[
        "aat:300266640"
    ]
},
  "bbox": [],
  "geometry": {"coordinates":[-121.6167,39.7167],"type":"Point"}
}