{
  "id": 7223945,
  "type": "Feature",
  "properties": {
    "tgn:hierarchy":[
        "tgn:7223945",
        "tgn:7002728",
        "tgn:7002715",
        "tgn:1000003",
        "tgn:1000074",
        "tgn:7029392"
    ],
    "tgn:id":7223945,
    "tgn:name":"Theodor\u00e1keion",
    "tgn:placetype":[
        "aat:300008347"
    ]
},
  "bbox": [],
  "geometry": {"coordinates":[22.188611,40.949722],"type":"Point"}
}