{
  "id": 2050455,
  "type": "Feature",
  "properties": {
    "tgn:hierarchy":[
        "tgn:2050455",
        "tgn:1000001",
        "tgn:1002724",
        "tgn:7012149",
        "tgn:7014307",
        "tgn:7007517",
        "tgn:7029392"
    ],
    "tgn:id":2050455,
    "tgn:name":"North Quincy",
    "tgn:placetype":[
        "aat:300000745"
    ]
},
  "bbox": [],
  "geometry": {"coordinates":[-71.0167,42.2667],"type":"Point"}
}