{
  "id": 2218421,
  "type": "Feature",
  "properties": {
    "tgn:hierarchy":[
        "tgn:2218421",
        "tgn:1000001",
        "tgn:7016172",
        "tgn:7012149",
        "tgn:2000137",
        "tgn:7029392"
    ],
    "tgn:id":2218421,
    "tgn:name":"Candlestick Knob",
    "tgn:placetype":[
        "aat:300008798"
    ]
},
  "bbox": [],
  "geometry": {"coordinates":[-92.05,35.9833],"type":"Point"}
}