<<<<<<< HEAD
{
  "id": 2767400,
  "type": "Feature",
  "properties": {
    "tgn:hierarchy":[
        "tgn:2767400",
        "tgn:1000001",
        "tgn:7012149",
        "tgn:7007568",
        "tgn:7029392"
    ],
    "tgn:id":2767400,
    "tgn:name":"White Spring Brook",
    "tgn:placetype":[
        "aat:300008699"
    ]
},
  "bbox": [],
  "geometry": {"coordinates":[-76.9833,42.8333],"type":"Point"}
}
=======
{"geometry":{"type":"Point","coordinates":[-76.983300,42.833300]},"type":"Feature","properties":{"hierarchy":["tgn:2767400","tgn:1000001","tgn:7012149","tgn:7007568","tgn:7029392"],"placetype":["aat:300008699"],"id":2767400,"name:xx":"White Spring Brook"}}
>>>>>>> 03f74aca74312dbeaf24d7e61306dd6a786dc3d0
