{
  "id": 2767400,
  "type": "Feature",
  "properties": {
    "tgn:hierarchy":[
        "tgn:2767400",
        "tgn:1000001",
        "tgn:7012149",
        "tgn:7007568",
        "tgn:7029392"
    ],
    "tgn:id":2767400,
    "tgn:name":"White Spring Brook",
    "tgn:placetype":[
        "aat:300008699"
    ]
},
  "bbox": [],
  "geometry": {"coordinates":[-76.9833,42.8333],"type":"Point"}
}