{
  "id": 7263225,
  "type": "Feature",
  "properties": {
    "tgn:concordances":{
        "gn:id":"2757609"
    },
    "tgn:hierarchy":[
        "tgn:7263225",
        "tgn:7003614",
        "tgn:1000003",
        "tgn:7016845",
        "tgn:7029392"
    ],
    "tgn:id":7263225,
    "tgn:name:nl":"De Groeve",
    "tgn:placetype":[
        "aat:300008347"
    ]
},
  "bbox": [],
  "geometry": {"coordinates":[6.716667,53.116667],"type":"Point"}
}