{
  "id": 7286066,
  "type": "Feature",
  "properties": {
    "tgn:hierarchy":[
        "tgn:7286066",
        "tgn:1001630",
        "tgn:1000049",
        "tgn:1000002",
        "tgn:7029392"
    ],
    "tgn:id":7286066,
    "tgn:name":"Juntas de Montosa",
    "tgn:placetype":[
        "aat:300008347"
    ]
},
  "bbox": [],
  "geometry": {"coordinates":[-69.866667,-28.183333],"type":"Point"}
}