{
  "id": 7370665,
  "type": "Feature",
  "properties": {
    "tgn:hierarchy":[
        "tgn:7370665",
        "tgn:1000001",
        "tgn:7005595",
        "tgn:7005560",
        "tgn:7029392"
    ],
    "tgn:id":7370665,
    "tgn:name":"Huinditos",
    "tgn:placetype":[
        "aat:300008347"
    ]
},
  "bbox": [],
  "geometry": {"coordinates":[-107.75,25.016667],"type":"Point"}
}