{
  "id": 7441479,
  "type": "Feature",
  "properties": {
    "tgn:hierarchy":[
        "tgn:7441479",
        "tgn:7005581",
        "tgn:1000001",
        "tgn:7005560",
        "tgn:7029392"
    ],
    "tgn:id":7441479,
    "tgn:name":"Santa Sof\u00eda",
    "tgn:placetype":[
        "aat:300007783"
    ]
},
  "bbox": [],
  "geometry": {"coordinates":[-107.516667,30.783333],"type":"Point"}
}