{
  "id": 7195625,
  "type": "Feature",
  "properties": {
    "tgn:hierarchy":[
        "tgn:7195625",
        "tgn:7003669",
        "tgn:1000003",
        "tgn:7000084",
        "tgn:7029392"
    ],
    "tgn:id":7195625,
    "tgn:name":"Dirnaich",
    "tgn:placetype":[
        "aat:300000206"
    ]
},
  "bbox": [],
  "geometry": {"coordinates":[12.833333,48.333333],"type":"Point"}
}