{
  "id": 7586043,
  "type": "Feature",
  "properties": {
    "tgn:hierarchy":[
        "tgn:7586043",
        "tgn:1000004",
        "tgn:7000198",
        "tgn:7000799",
        "tgn:7029392"
    ],
    "tgn:id":7586043,
    "tgn:name:en":"M\u0101rotgain",
    "tgn:placetype":[
        "aat:300008347"
    ]
},
  "bbox": [],
  "geometry": {"coordinates":[74.28622,34.380142],"type":"Point"}
}