{
  "id": 2283200,
  "type": "Feature",
  "properties": {
    "tgn:hierarchy":[
        "tgn:2283200",
        "tgn:1000001",
        "tgn:2001948",
        "tgn:7012149",
        "tgn:7007826",
        "tgn:7029392"
    ],
    "tgn:id":2283200,
    "tgn:name":"Delaware Junction",
    "tgn:placetype":[
        "aat:300008347"
    ]
},
  "bbox": [],
  "geometry": {"coordinates":[-98.8667,31.7833],"type":"Point"}
}