{
  "id": 7578849,
  "type": "Feature",
  "properties": {
    "tgn:hierarchy":[
        "tgn:7578849",
        "tgn:1000004",
        "tgn:7000198",
        "tgn:1001882",
        "tgn:7029392"
    ],
    "tgn:id":7578849,
    "tgn:name:en":"Wandalli",
    "tgn:placetype":[
        "aat:300008347"
    ]
},
  "bbox": [],
  "geometry": {"coordinates":[76.75,16.25],"type":"Point"}
}