{
  "id": 2069212,
  "type": "Feature",
  "properties": {
    "tgn:hierarchy":[
        "tgn:2069212",
        "tgn:1000001",
        "tgn:1002328",
        "tgn:7012149",
        "tgn:7007568",
        "tgn:7029392"
    ],
    "tgn:id":2069212,
    "tgn:name":"Fleischmanns",
    "tgn:placetype":[
        "aat:300008347"
    ]
},
  "bbox": [],
  "geometry": {"coordinates":[-74.5167,42.15],"type":"Point"}
}