{
  "id": 7240396,
  "type": "Feature",
  "properties": {
    "tgn:hierarchy":[
        "tgn:7240396",
        "tgn:7003457",
        "tgn:1000003",
        "tgn:1000063",
        "tgn:7018236",
        "tgn:7029392"
    ],
    "tgn:id":7240396,
    "tgn:name":"Ertbuurhoek",
    "tgn:placetype":[
        "aat:300008347"
    ]
},
  "bbox": [],
  "geometry": {"coordinates":[3.866667,51.066667],"type":"Point"}
}