{
  "id": 2784240,
  "type": "Feature",
  "properties": {
    "tgn:hierarchy":[
        "tgn:2784240",
        "tgn:1000001",
        "tgn:7012149",
        "tgn:7007158",
        "tgn:2000246",
        "tgn:7029392"
    ],
    "tgn:id":2784240,
    "tgn:name":"Yankee Creek",
    "tgn:placetype":[
        "aat:300008706"
    ]
},
  "bbox": [],
  "geometry": {"coordinates":[-105.9667,38.45],"type":"Point"}
}