{
  "id": 2776395,
  "type": "Feature",
  "properties": {
    "tgn:hierarchy":[
        "tgn:2776395",
        "tgn:1000001",
        "tgn:7012149",
        "tgn:2000232",
        "tgn:7007158",
        "tgn:7029392"
    ],
    "tgn:id":2776395,
    "tgn:name":"Wind Cow Draw",
    "tgn:placetype":[
        "aat:300008761"
    ]
},
  "bbox": [],
  "geometry": {"coordinates":[-108.4833,40.5333],"type":"Point"}
}