<<<<<<< HEAD
{
  "id": 2768374,
  "type": "Feature",
  "properties": {
    "tgn:hierarchy":[
        "tgn:2768374",
        "tgn:1000001",
        "tgn:7012149",
        "tgn:1002742",
        "tgn:7007920",
        "tgn:7029392"
    ],
    "tgn:id":2768374,
    "tgn:name":"Whitestone Creek",
    "tgn:placetype":[
        "aat:300008706"
    ]
},
  "bbox": [],
  "geometry": {"coordinates":[-119.8333,48.25],"type":"Point"}
}
=======
{"geometry":{"type":"Point","coordinates":[-119.833300,48.250000]},"type":"Feature","properties":{"hierarchy":["tgn:2768374","tgn:1000001","tgn:7012149","tgn:1002742","tgn:7007920","tgn:7029392"],"placetype":["aat:300008706"],"id":2768374,"name:xx":"Whitestone Creek"}}
>>>>>>> 03f74aca74312dbeaf24d7e61306dd6a786dc3d0
