{
  "id": 2768374,
  "type": "Feature",
  "properties": {
    "tgn:hierarchy":[
        "tgn:2768374",
        "tgn:1000001",
        "tgn:7012149",
        "tgn:1002742",
        "tgn:7007920",
        "tgn:7029392"
    ],
    "tgn:id":2768374,
    "tgn:name":"Whitestone Creek",
    "tgn:placetype":[
        "aat:300008706"
    ]
},
  "bbox": [],
  "geometry": {"coordinates":[-119.8333,48.25],"type":"Point"}
}