{
  "id": 1094203,
  "type": "Feature",
  "properties": {
    "tgn:hierarchy":[
        "tgn:1094203",
        "tgn:7001242",
        "tgn:1001112",
        "tgn:1000201",
        "tgn:7029392"
    ],
    "tgn:id":1094203,
    "tgn:name":"Delgo",
    "tgn:placetype":[
        "aat:300008347"
    ]
},
  "bbox": [],
  "geometry": {"coordinates":[30.6667,20.1333],"type":"Point"}
}