<<<<<<< HEAD
{
  "id": 7179017,
  "type": "Feature",
  "properties": {
    "tgn:hierarchy":[
        "tgn:7179017",
        "tgn:1000003",
        "tgn:7003677",
        "tgn:7000084",
        "tgn:7029392"
    ],
    "tgn:id":7179017,
    "tgn:name":"Habighorst",
    "tgn:placetype":[
        "aat:300387200"
    ]
},
  "bbox": [],
  "geometry": {"coordinates":[8.55,52.233333],"type":"Point"}
}
=======
{"geometry":{"type":"Point","coordinates":[8.550000,52.233333]},"type":"Feature","properties":{"hierarchy":["tgn:7179017","tgn:1000003","tgn:7003677","tgn:7000084","tgn:7029392"],"placetype":["aat:300387200"],"id":7179017,"name:xx":"Habighorst"}}
>>>>>>> 03f74aca74312dbeaf24d7e61306dd6a786dc3d0
