<<<<<<< HEAD
{
  "id": 7364774,
  "type": "Feature",
  "properties": {
    "tgn:hierarchy":[
        "tgn:7364774",
        "tgn:1000001",
        "tgn:7005593",
        "tgn:7005560",
        "tgn:7029392"
    ],
    "tgn:id":7364774,
    "tgn:name":"El Zapote",
    "tgn:placetype":[
        "aat:300008347"
    ]
},
  "bbox": [],
  "geometry": {"coordinates":[-99.8,20.85],"type":"Point"}
}
=======
{"geometry":{"type":"Point","coordinates":[-99.800000,20.850000]},"type":"Feature","properties":{"hierarchy":["tgn:7364774","tgn:1000001","tgn:7005593","tgn:7005560","tgn:7029392"],"placetype":["aat:300008347"],"id":7364774,"name:xx":"El Zapote"}}
>>>>>>> 03f74aca74312dbeaf24d7e61306dd6a786dc3d0
