{
  "id": 7121370,
  "type": "Feature",
  "properties": {
    "tgn:hierarchy":[
        "tgn:7121370",
        "tgn:7003669",
        "tgn:1000003",
        "tgn:7000084",
        "tgn:7029392"
    ],
    "tgn:id":7121370,
    "tgn:name":"Pittersdorf",
    "tgn:placetype":[
        "aat:300008347"
    ]
},
  "bbox": [],
  "geometry": {"coordinates":[11.766667,48.583333],"type":"Point"}
}