<<<<<<< HEAD
{
  "id": 2151748,
  "type": "Feature",
  "properties": {
    "tgn:hierarchy":[
        "tgn:2151748",
        "tgn:1000001",
        "tgn:2002368",
        "tgn:7012149",
        "tgn:7007923",
        "tgn:7029392"
    ],
    "tgn:id":2151748,
    "tgn:name":"Battle Lake",
    "tgn:placetype":[
        "aat:300008680"
    ]
},
  "bbox": [],
  "geometry": {"coordinates":[-107.0,41.15],"type":"Point"}
}
=======
{"geometry":{"type":"Point","coordinates":[-107.000000,41.150000]},"type":"Feature","properties":{"hierarchy":["tgn:2151748","tgn:1000001","tgn:2002368","tgn:7012149","tgn:7007923","tgn:7029392"],"placetype":["aat:300008680"],"id":2151748,"name:xx":"Battle Lake"}}
>>>>>>> 03f74aca74312dbeaf24d7e61306dd6a786dc3d0
