{
  "id": 2445051,
  "type": "Feature",
  "properties": {
    "tgn:hierarchy":[
        "tgn:2445051",
        "tgn:1000001",
        "tgn:7012149",
        "tgn:2002352",
        "tgn:7007922",
        "tgn:7029392"
    ],
    "tgn:id":2445051,
    "tgn:name":"Leland Millpond",
    "tgn:placetype":[
        "aat:300006191"
    ]
},
  "bbox": [],
  "geometry": {"coordinates":[-89.95,43.3333],"type":"Point"}
}