{
  "id": 7395899,
  "type": "Feature",
  "properties": {
    "tgn:hierarchy":[
        "tgn:7395899",
        "tgn:1001836",
        "tgn:1000001",
        "tgn:7005560",
        "tgn:7029392"
    ],
    "tgn:id":7395899,
    "tgn:name":"San Javier",
    "tgn:placetype":[
        "aat:300008347"
    ]
},
  "bbox": [],
  "geometry": {"coordinates":[-111.544444,25.858056],"type":"Point"}
}