{
  "id": 2454082,
  "type": "Feature",
  "properties": {
    "tgn:hierarchy":[
        "tgn:2454082",
        "tgn:1000001",
        "tgn:7012149",
        "tgn:2001163",
        "tgn:7007522",
        "tgn:7029392"
    ],
    "tgn:id":2454082,
    "tgn:name":"Little Creek",
    "tgn:placetype":[
        "aat:300008706"
    ]
},
  "bbox": [],
  "geometry": {"coordinates":[-89.3333,33.6167],"type":"Point"}
}