{
  "id": 7550435,
  "type": "Feature",
  "properties": {
    "tgn:hierarchy":[
        "tgn:7550435",
        "tgn:1001828",
        "tgn:1000004",
        "tgn:7000198",
        "tgn:7029392"
    ],
    "tgn:id":7550435,
    "tgn:name:en":"B\u012bb\u012bnagar",
    "tgn:placetype":[
        "aat:300008347"
    ]
},
  "bbox": [],
  "geometry": {"coordinates":[78.798333,17.473611],"type":"Point"}
}