{
  "id": 1001153,
  "type": "Feature",
  "properties": {
    "tgn:hierarchy":[
        "tgn:1001153",
        "tgn:1000001",
        "tgn:7005565",
        "tgn:7029392"
    ],
    "tgn:id":1001153,
    "tgn:name":"Bocas del Toro",
    "tgn:placetype":[
        "aat:300008631",
        "aat:300387064",
        "aat:300000774"
    ]
},
  "bbox": [],
  "geometry": {"coordinates":[-82.65,9.25],"type":"Point"}
}