{
  "id": 2306066,
  "type": "Feature",
  "properties": {
    "tgn:hierarchy":[
        "tgn:2306066",
        "tgn:1000001",
        "tgn:7012149",
        "tgn:2000791",
        "tgn:7007255",
        "tgn:7029392"
    ],
    "tgn:id":2306066,
    "tgn:name":"East Fork Back Creek",
    "tgn:placetype":[
        "aat:300008706"
    ]
},
  "bbox": [],
  "geometry": {"coordinates":[-84.4833,37.5667],"type":"Point"}
}