{
  "id": 2584950,
  "type": "Feature",
  "properties": {
    "tgn:hierarchy":[
        "tgn:2584950",
        "tgn:1000001",
        "tgn:7012149",
        "tgn:2000476",
        "tgn:7007250",
        "tgn:7029392"
    ],
    "tgn:id":2584950,
    "tgn:name":"Pinnacle Creek",
    "tgn:placetype":[
        "aat:300008706"
    ]
},
  "bbox": [],
  "geometry": {"coordinates":[-116.0667,45.7667],"type":"Point"}
}