<<<<<<< HEAD
{
  "id": 2339586,
  "type": "Feature",
  "properties": {
    "tgn:hierarchy":[
        "tgn:2339586",
        "tgn:1000001",
        "tgn:7012149",
        "tgn:7007158",
        "tgn:2000253",
        "tgn:7029392"
    ],
    "tgn:id":2339586,
    "tgn:name":"Frederick Reservoir",
    "tgn:placetype":[
        "aat:300006191"
    ]
},
  "bbox": [],
  "geometry": {"coordinates":[-104.9333,40.1167],"type":"Point"}
}
=======
{"geometry":{"type":"Point","coordinates":[-104.933300,40.116700]},"type":"Feature","properties":{"hierarchy":["tgn:2339586","tgn:1000001","tgn:7012149","tgn:7007158","tgn:2000253","tgn:7029392"],"placetype":["aat:300006191"],"id":2339586,"name:xx":"Frederick Reservoir"}}
>>>>>>> 03f74aca74312dbeaf24d7e61306dd6a786dc3d0
