{
  "id": 2339586,
  "type": "Feature",
  "properties": {
    "tgn:hierarchy":[
        "tgn:2339586",
        "tgn:1000001",
        "tgn:7012149",
        "tgn:7007158",
        "tgn:2000253",
        "tgn:7029392"
    ],
    "tgn:id":2339586,
    "tgn:name":"Frederick Reservoir",
    "tgn:placetype":[
        "aat:300006191"
    ]
},
  "bbox": [],
  "geometry": {"coordinates":[-104.9333,40.1167],"type":"Point"}
}