{
  "id": 2108786,
  "type": "Feature",
  "properties": {
    "tgn:hierarchy":[
        "tgn:2108786",
        "tgn:1000001",
        "tgn:2002102",
        "tgn:7012149",
        "tgn:7007827",
        "tgn:7029392"
    ],
    "tgn:id":2108786,
    "tgn:name":"Collinston",
    "tgn:placetype":[
        "aat:300008347"
    ]
},
  "bbox": [],
  "geometry": {"coordinates":[-112.0833,41.7667],"type":"Point"}
}