{
  "id": 7496472,
  "type": "Feature",
  "properties": {
    "tgn:hierarchy":[
        "tgn:7496472",
        "tgn:7487020",
        "tgn:1000004",
        "tgn:1000141",
        "tgn:7029392"
    ],
    "tgn:id":7496472,
    "tgn:name":"Xiabangwei",
    "tgn:placetype":[
        "aat:300008347"
    ]
},
  "bbox": [],
  "geometry": {"coordinates":[120.900687,24.382509],"type":"Point"}
}