{
  "id": 2036683,
  "type": "Feature",
  "properties": {
    "tgn:hierarchy":[
        "tgn:2036683",
        "tgn:1000001",
        "tgn:2000675",
        "tgn:7012149",
        "tgn:7007254",
        "tgn:7029392"
    ],
    "tgn:id":2036683,
    "tgn:name":"Lebo",
    "tgn:placetype":[
        "aat:300008347"
    ]
},
  "bbox": [],
  "geometry": {"coordinates":[-95.85,38.4167],"type":"Point"}
}