{
  "id": 7126562,
  "type": "Feature",
  "properties": {
    "tgn:hierarchy":[
        "tgn:7126562",
        "tgn:7003669",
        "tgn:1000003",
        "tgn:7000084",
        "tgn:7029392"
    ],
    "tgn:id":7126562,
    "tgn:name":"Ober Hof",
    "tgn:placetype":[
        "aat:300000206"
    ]
},
  "bbox": [],
  "geometry": {"coordinates":[12.65,48.166667],"type":"Point"}
}