{
  "id": 2279977,
  "type": "Feature",
  "properties": {
    "tgn:hierarchy":[
        "tgn:2279977",
        "tgn:1000001",
        "tgn:7012149",
        "tgn:2000435",
        "tgn:7007248",
        "tgn:7029392"
    ],
    "tgn:id":2279977,
    "tgn:name":"Dean Pond",
    "tgn:placetype":[
        "aat:300008680"
    ]
},
  "bbox": [],
  "geometry": {"coordinates":[-84.0833,34.8833],"type":"Point"}
}