{
  "id": 2687589,
  "type": "Feature",
  "properties": {
    "tgn:hierarchy":[
        "tgn:2687589",
        "tgn:1000001",
        "tgn:7006451",
        "tgn:7012149",
        "tgn:2000103",
        "tgn:7029392"
    ],
    "tgn:id":2687589,
    "tgn:name":"Spring Peak",
    "tgn:placetype":[
        "aat:300008798"
    ]
},
  "bbox": [],
  "geometry": {"coordinates":[-113.2167,34.55],"type":"Point"}
}