{
  "id": 7381936,
  "type": "Feature",
  "properties": {
    "tgn:hierarchy":[
        "tgn:7381936",
        "tgn:1001835",
        "tgn:1000001",
        "tgn:7005560",
        "tgn:7029392"
    ],
    "tgn:id":7381936,
    "tgn:name":"Maneadero",
    "tgn:placetype":[
        "aat:300008347"
    ]
},
  "bbox": [],
  "geometry": {"coordinates":[-116.566667,31.716667],"type":"Point"}
}