{
  "id": 2451346,
  "type": "Feature",
  "properties": {
    "tgn:hierarchy":[
        "tgn:2451346",
        "tgn:1000001",
        "tgn:2000859",
        "tgn:7012149",
        "tgn:7007256",
        "tgn:7029392"
    ],
    "tgn:id":2451346,
    "tgn:name":"Little Barnes Creek",
    "tgn:placetype":[
        "aat:300008706"
    ]
},
  "bbox": [],
  "geometry": {"coordinates":[-93.1833,30.7333],"type":"Point"}
}