{
  "id": 2587973,
  "type": "Feature",
  "properties": {
    "tgn:hierarchy":[
        "tgn:2587973",
        "tgn:1000001",
        "tgn:7012149",
        "tgn:1003038",
        "tgn:7007517",
        "tgn:7029392"
    ],
    "tgn:id":2587973,
    "tgn:name":"Pleasant, Mount",
    "tgn:placetype":[
        "aat:300008798"
    ]
},
  "bbox": [],
  "geometry": {"coordinates":[-72.0833,42.4667],"type":"Point"}
}