{
  "id": 7325972,
  "type": "Feature",
  "properties": {
    "tgn:hierarchy":[
        "tgn:7325972",
        "tgn:7002758",
        "tgn:1001316",
        "tgn:1000003",
        "tgn:1000095",
        "tgn:7029392"
    ],
    "tgn:id":7325972,
    "tgn:name":"Rancero, R\u00edo de",
    "tgn:placetype":[
        "aat:300008699"
    ]
},
  "bbox": [],
  "geometry": {"coordinates":[-3.816667,37.583333],"type":"Point"}
}