{
  "id": 2147624,
  "type": "Feature",
  "properties": {
    "tgn:hierarchy":[
        "tgn:2147624",
        "tgn:1000001",
        "tgn:7012149",
        "tgn:7007157",
        "tgn:1002675",
        "tgn:7029392"
    ],
    "tgn:id":2147624,
    "tgn:name":"Barcroft, Mount",
    "tgn:placetype":[
        "aat:300008798"
    ]
},
  "bbox": [],
  "geometry": {"coordinates":[-118.2333,37.5667],"type":"Point"}
}