{
  "id": 2520820,
  "type": "Feature",
  "properties": {
    "tgn:hierarchy":[
        "tgn:2520820",
        "tgn:1000001",
        "tgn:7012149",
        "tgn:1003018",
        "tgn:7007919",
        "tgn:7029392"
    ],
    "tgn:id":2520820,
    "tgn:name":"Monroe Creek",
    "tgn:placetype":[
        "aat:300008706"
    ]
},
  "bbox": [],
  "geometry": {"coordinates":[-77.0167,38.2167],"type":"Point"}
}