{
  "id": 2536316,
  "type": "Feature",
  "properties": {
    "tgn:hierarchy":[
        "tgn:2536316",
        "tgn:1000001",
        "tgn:7012149",
        "tgn:1002518",
        "tgn:7007568",
        "tgn:7029392"
    ],
    "tgn:id":2536316,
    "tgn:name":"Navy Point",
    "tgn:placetype":[
        "aat:300008850"
    ]
},
  "bbox": [],
  "geometry": {"coordinates":[-76.1167,43.95],"type":"Point"}
}