{
  "id": 7240414,
  "type": "Feature",
  "properties": {
    "tgn:hierarchy":[
        "tgn:7240414",
        "tgn:7003465",
        "tgn:1000003",
        "tgn:1000063",
        "tgn:4012014",
        "tgn:7029392"
    ],
    "tgn:id":7240414,
    "tgn:name":"Erpigny",
    "tgn:placetype":[
        "aat:300008347"
    ]
},
  "bbox": [],
  "geometry": {"coordinates":[5.568737,50.282665],"type":"Point"}
}