{
  "id": 7282939,
  "type": "Feature",
  "properties": {
    "tgn:hierarchy":[
        "tgn:7282939",
        "tgn:7016598",
        "tgn:1000049",
        "tgn:1000002",
        "tgn:7029392"
    ],
    "tgn:id":7282939,
    "tgn:name":"Peieta, Portezuelo",
    "tgn:placetype":[
        "aat:300259572"
    ]
},
  "bbox": [],
  "geometry": {"coordinates":[-68.183333,-21.383333],"type":"Point"}
}