{
  "id": 7179683,
  "type": "Feature",
  "properties": {
    "tgn:hierarchy":[
        "tgn:7179683",
        "tgn:1000003",
        "tgn:7003676",
        "tgn:7000084",
        "tgn:7029392"
    ],
    "tgn:id":7179683,
    "tgn:name":"Haarenstroth",
    "tgn:placetype":[
        "aat:300008347"
    ]
},
  "bbox": [],
  "geometry": {"coordinates":[8.083333,53.183333],"type":"Point"}
}