{
  "id": 2490780,
  "type": "Feature",
  "properties": {
    "tgn:hierarchy":[
        "tgn:2490780",
        "tgn:1002483",
        "tgn:7019080",
        "tgn:1000001",
        "tgn:7012149",
        "tgn:7007249",
        "tgn:7029392"
    ],
    "tgn:id":2490780,
    "tgn:name":"Manoa Valley",
    "tgn:placetype":[
        "aat:300008761"
    ]
},
  "bbox": [],
  "geometry": {"coordinates":[-157.7833,21.35],"type":"Point"}
}