{
  "id": 7232732,
  "type": "Feature",
  "properties": {
    "tgn:hierarchy":[
        "tgn:7232732",
        "tgn:7002680",
        "tgn:7001395",
        "tgn:1000003",
        "tgn:1000074",
        "tgn:7029392"
    ],
    "tgn:id":7232732,
    "tgn:name":"Koromb\u00edla",
    "tgn:placetype":[
        "aat:300008798"
    ]
},
  "bbox": [],
  "geometry": {"coordinates":[20.95,38.766667],"type":"Point"}
}