{
  "id": 7286568,
  "type": "Feature",
  "properties": {
    "tgn:hierarchy":[
        "tgn:7286568",
        "tgn:7002464",
        "tgn:1000049",
        "tgn:1000002",
        "tgn:7029392"
    ],
    "tgn:id":7286568,
    "tgn:name":"Hacienda, Pampa",
    "tgn:placetype":[
        "aat:300008805"
    ]
},
  "bbox": [],
  "geometry": {"coordinates":[-68.65,-19.416667],"type":"Point"}
}