{
  "id": 7299860,
  "type": "Feature",
  "properties": {
    "tgn:hierarchy":[
        "tgn:7299860",
        "tgn:7002818",
        "tgn:1001647",
        "tgn:1000003",
        "tgn:1000095",
        "tgn:7029392"
    ],
    "tgn:id":7299860,
    "tgn:name":"Valdemoro del Rey, R\u00edo de",
    "tgn:placetype":[
        "aat:300266554",
        "aat:300008699"
    ]
},
  "bbox": [],
  "geometry": {"coordinates":[-2.683333,40.283333],"type":"Point"}
}