{
  "id": 7527142,
  "type": "Feature",
  "properties": {
    "tgn:hierarchy":[
        "tgn:7527142",
        "tgn:7001242",
        "tgn:7016833",
        "tgn:1001091",
        "tgn:7029392"
    ],
    "tgn:id":7527142,
    "tgn:name":"Ad Darb al A\u1e29mar",
    "tgn:placetype":[
        "aat:300000745"
    ]
},
  "bbox": [],
  "geometry": {"coordinates":[31.264446,30.040578],"type":"Point"}
}