{
  "id": 2777580,
  "type": "Feature",
  "properties": {
    "tgn:hierarchy":[
        "tgn:2777580",
        "tgn:1000001",
        "tgn:7012149",
        "tgn:2002374",
        "tgn:7007923",
        "tgn:7029392"
    ],
    "tgn:id":2777580,
    "tgn:name":"Winnie, Lake",
    "tgn:placetype":[
        "aat:300008680"
    ]
},
  "bbox": [],
  "geometry": {"coordinates":[-107.1167,44.45],"type":"Point"}
}