{
  "id": 1050975,
  "type": "Feature",
  "properties": {
    "tgn:hierarchy":[
        "tgn:1050975",
        "tgn:7002444",
        "tgn:1000003",
        "tgn:7008082",
        "tgn:7008591",
        "tgn:7029392"
    ],
    "tgn:id":1050975,
    "tgn:name":"Opinan",
    "tgn:placetype":[
        "aat:300008347"
    ]
},
  "bbox": [],
  "geometry": {"coordinates":[-5.7833,57.7167],"type":"Point"}
}