{
  "id": 2623907,
  "type": "Feature",
  "properties": {
    "tgn:hierarchy":[
        "tgn:2623907",
        "tgn:1000001",
        "tgn:7006451",
        "tgn:7012149",
        "tgn:2000098",
        "tgn:7029392"
    ],
    "tgn:id":2623907,
    "tgn:name":"Rock Crossing Reservoir",
    "tgn:placetype":[
        "aat:300006191"
    ]
},
  "bbox": [],
  "geometry": {"coordinates":[-113.3333,36.7167],"type":"Point"}
}