{
  "id": 2641048,
  "type": "Feature",
  "properties": {
    "tgn:hierarchy":[
        "tgn:2641048",
        "tgn:1000001",
        "tgn:7012149",
        "tgn:2001119",
        "tgn:7007522",
        "tgn:7029392"
    ],
    "tgn:id":2641048,
    "tgn:name":"Sand Branch",
    "tgn:placetype":[
        "aat:300008699"
    ]
},
  "bbox": [],
  "geometry": {"coordinates":[-89.15,31.55],"type":"Point"}
}