{
  "id": 7459035,
  "type": "Feature",
  "properties": {
    "tgn:hierarchy":[
        "tgn:7459035",
        "tgn:7002445",
        "tgn:7018920",
        "tgn:1000003",
        "tgn:7008136",
        "tgn:7008591",
        "tgn:7029392"
    ],
    "tgn:id":7459035,
    "tgn:name:en":"New Bedfont",
    "tgn:placetype":[
        "aat:300008347",
        "aat:300000745"
    ]
},
  "bbox": [],
  "geometry": {"coordinates":[-0.433333,51.466667],"type":"Point"}
}