{
  "id": 2420913,
  "type": "Feature",
  "properties": {
    "tgn:hierarchy":[
        "tgn:2420913",
        "tgn:1000001",
        "tgn:2000783",
        "tgn:7012149",
        "tgn:7007255",
        "tgn:7029392"
    ],
    "tgn:id":2420913,
    "tgn:name":"Jennys Knob",
    "tgn:placetype":[
        "aat:300008798"
    ]
},
  "bbox": [],
  "geometry": {"coordinates":[-85.05,36.6333],"type":"Point"}
}