{
  "id": 7409100,
  "type": "Feature",
  "properties": {
    "tgn:hierarchy":[
        "tgn:7409100",
        "tgn:1000001",
        "tgn:7005590",
        "tgn:7005560",
        "tgn:7029392"
    ],
    "tgn:id":7409100,
    "tgn:name":"San Antonio Villalongla",
    "tgn:placetype":[
        "aat:300008347"
    ]
},
  "bbox": [],
  "geometry": {"coordinates":[-100.75,19.533333],"type":"Point"}
}