{
  "id": 1050166,
  "type": "Feature",
  "properties": {
    "tgn:hierarchy":[
        "tgn:1050166",
        "tgn:1000003",
        "tgn:7002701",
        "tgn:1000091",
        "tgn:7029392"
    ],
    "tgn:id":1050166,
    "tgn:name":"Jimbolia",
    "tgn:placetype":[
        "aat:300008347"
    ]
},
  "bbox": [],
  "geometry": {"coordinates":[20.7167,45.7833],"type":"Point"}
}