{
  "id": 7177274,
  "type": "Feature",
  "properties": {
    "tgn:hierarchy":[
        "tgn:7177274",
        "tgn:7003669",
        "tgn:1000003",
        "tgn:7000084",
        "tgn:7029392"
    ],
    "tgn:id":7177274,
    "tgn:name":"Harburger Karab",
    "tgn:placetype":[
        "aat:300008863"
    ]
},
  "bbox": [],
  "geometry": {"coordinates":[10.75,48.783333],"type":"Point"}
}