{
  "id": 7355761,
  "type": "Feature",
  "properties": {
    "tgn:hierarchy":[
        "tgn:7355761",
        "tgn:1000001",
        "tgn:7005593",
        "tgn:7005560",
        "tgn:7029392"
    ],
    "tgn:id":7355761,
    "tgn:name":"Capulines",
    "tgn:placetype":[
        "aat:300008347"
    ]
},
  "bbox": [],
  "geometry": {"coordinates":[-99.433333,21.183333],"type":"Point"}
}