{
  "id": 2366863,
  "type": "Feature",
  "properties": {
    "tgn:hierarchy":[
        "tgn:2366863",
        "tgn:1000001",
        "tgn:7012149",
        "tgn:2000933",
        "tgn:7007515",
        "tgn:7029392"
    ],
    "tgn:id":2366863,
    "tgn:name":"Grist Mill Pond",
    "tgn:placetype":[
        "aat:300006191"
    ]
},
  "bbox": [],
  "geometry": {"coordinates":[-70.4667,43.35],"type":"Point"}
}