{
  "id": 7310092,
  "type": "Feature",
  "properties": {
    "tgn:hierarchy":[
        "tgn:7310092",
        "tgn:1001695",
        "tgn:1000049",
        "tgn:1000002",
        "tgn:7029392"
    ],
    "tgn:id":7310092,
    "tgn:name":"Ortigas, Cerro",
    "tgn:placetype":[
        "aat:300008795"
    ]
},
  "bbox": [],
  "geometry": {"coordinates":[-71.133333,-34.566667],"type":"Point"}
}