{
  "id": 7284642,
  "type": "Feature",
  "properties": {
    "tgn:hierarchy":[
        "tgn:7284642",
        "tgn:1001695",
        "tgn:1000049",
        "tgn:1000002",
        "tgn:7029392"
    ],
    "tgn:id":7284642,
    "tgn:name":"Portezuelo, Cerro",
    "tgn:placetype":[
        "aat:300008795"
    ]
},
  "bbox": [],
  "geometry": {"coordinates":[-71.316667,-34.583333],"type":"Point"}
}