<<<<<<< HEAD
{
  "id": 2760729,
  "type": "Feature",
  "properties": {
    "tgn:hierarchy":[
        "tgn:2760729",
        "tgn:1002808",
        "tgn:1000001",
        "tgn:7012149",
        "tgn:7007711",
        "tgn:7029392"
    ],
    "tgn:id":2760729,
    "tgn:name":"West Gloucester",
    "tgn:placetype":[
        "aat:300008347"
    ]
},
  "bbox": [],
  "geometry": {"coordinates":[-71.7833,41.9167],"type":"Point"}
}
=======
{"geometry":{"type":"Point","coordinates":[-71.783300,41.916700]},"type":"Feature","properties":{"hierarchy":["tgn:2760729","tgn:1002808","tgn:1000001","tgn:7012149","tgn:7007711","tgn:7029392"],"placetype":["aat:300008347"],"id":2760729,"name:xx":"West Gloucester"}}
>>>>>>> 03f74aca74312dbeaf24d7e61306dd6a786dc3d0
