{
  "id": 2760729,
  "type": "Feature",
  "properties": {
    "tgn:hierarchy":[
        "tgn:2760729",
        "tgn:1002808",
        "tgn:1000001",
        "tgn:7012149",
        "tgn:7007711",
        "tgn:7029392"
    ],
    "tgn:id":2760729,
    "tgn:name":"West Gloucester",
    "tgn:placetype":[
        "aat:300008347"
    ]
},
  "bbox": [],
  "geometry": {"coordinates":[-71.7833,41.9167],"type":"Point"}
}