{
  "id": 2213523,
  "type": "Feature",
  "properties": {
    "tgn:hierarchy":[
        "tgn:2213523",
        "tgn:1000001",
        "tgn:7012149",
        "tgn:2001709",
        "tgn:7007708",
        "tgn:7029392"
    ],
    "tgn:id":2213523,
    "tgn:name":"Cabin Waterhole",
    "tgn:placetype":[
        "aat:300006191"
    ]
},
  "bbox": [],
  "geometry": {"coordinates":[-119.85,43.1333],"type":"Point"}
}