<<<<<<< HEAD
{
  "id": 2254542,
  "type": "Feature",
  "properties": {
    "tgn:hierarchy":[
        "tgn:2254542",
        "tgn:1000001",
        "tgn:1002328",
        "tgn:7012149",
        "tgn:7007568",
        "tgn:7029392"
    ],
    "tgn:id":2254542,
    "tgn:name":"Coon Hill",
    "tgn:placetype":[
        "aat:300008798"
    ]
},
  "bbox": [],
  "geometry": {"coordinates":[-75.2667,41.9833],"type":"Point"}
}
=======
{"geometry":{"type":"Point","coordinates":[-75.266700,41.983300]},"type":"Feature","properties":{"hierarchy":["tgn:2254542","tgn:1000001","tgn:1002328","tgn:7012149","tgn:7007568","tgn:7029392"],"placetype":["aat:300008798"],"id":2254542,"name:xx":"Coon Hill"}}
>>>>>>> 03f74aca74312dbeaf24d7e61306dd6a786dc3d0
