{
  "id": 7418868,
  "type": "Feature",
  "properties": {
    "tgn:hierarchy":[
        "tgn:7418868",
        "tgn:1001835",
        "tgn:1000001",
        "tgn:7005560",
        "tgn:7029392"
    ],
    "tgn:id":7418868,
    "tgn:name":"Casita de la Minas",
    "tgn:placetype":[
        "aat:300008347"
    ]
},
  "bbox": [],
  "geometry": {"coordinates":[-116.87,32.233889],"type":"Point"}
}