{
  "id": 7480527,
  "type": "Feature",
  "properties": {
    "tgn:hierarchy":[
        "tgn:7480527",
        "tgn:7001010",
        "tgn:1000004",
        "tgn:1000141",
        "tgn:7029392"
    ],
    "tgn:id":7480527,
    "tgn:name":"Guanghuayicun",
    "tgn:placetype":[
        "aat:300008347"
    ]
},
  "bbox": [],
  "geometry": {"coordinates":[121.5675,23.933333],"type":"Point"}
}