<<<<<<< HEAD
{
  "id": 7172308,
  "type": "Feature",
  "properties": {
    "tgn:hierarchy":[
        "tgn:7172308",
        "tgn:7003669",
        "tgn:1000003",
        "tgn:7000084",
        "tgn:7029392"
    ],
    "tgn:id":7172308,
    "tgn:name":"Herrensee",
    "tgn:placetype":[
        "aat:300008680"
    ]
},
  "bbox": [],
  "geometry": {"coordinates":[10.4,49.966667],"type":"Point"}
}
=======
{"geometry":{"type":"Point","coordinates":[10.400000,49.966667]},"type":"Feature","properties":{"hierarchy":["tgn:7172308","tgn:7003669","tgn:1000003","tgn:7000084","tgn:7029392"],"placetype":["aat:300008680"],"id":7172308,"name:xx":"Herrensee"}}
>>>>>>> 03f74aca74312dbeaf24d7e61306dd6a786dc3d0
