{
  "id": 7583364,
  "type": "Feature",
  "properties": {
    "tgn:hierarchy":[
        "tgn:7583364",
        "tgn:1000004",
        "tgn:7000198",
        "tgn:7016883",
        "tgn:7029392"
    ],
    "tgn:id":7583364,
    "tgn:name:en":"Chakohi",
    "tgn:placetype":[
        "aat:300008347"
    ]
},
  "bbox": [],
  "geometry": {"coordinates":[76.137658,30.700243],"type":"Point"}
}