<<<<<<< HEAD
{
  "id": 2255986,
  "type": "Feature",
  "properties": {
    "tgn:hierarchy":[
        "tgn:2255986",
        "tgn:1000001",
        "tgn:7006451",
        "tgn:2000091",
        "tgn:7012149",
        "tgn:7029392"
    ],
    "tgn:id":2255986,
    "tgn:name":"Copper King Canyon",
    "tgn:placetype":[
        "aat:300008761"
    ]
},
  "bbox": [],
  "geometry": {"coordinates":[-109.8833,31.45],"type":"Point"}
}
=======
{"geometry":{"type":"Point","coordinates":[-109.883300,31.450000]},"type":"Feature","properties":{"hierarchy":["tgn:2255986","tgn:1000001","tgn:7006451","tgn:2000091","tgn:7012149","tgn:7029392"],"placetype":["aat:300008761"],"id":2255986,"name:xx":"Copper King Canyon"}}
>>>>>>> 03f74aca74312dbeaf24d7e61306dd6a786dc3d0
