{
  "id": 2504049,
  "type": "Feature",
  "properties": {
    "tgn:hierarchy":[
        "tgn:2504049",
        "tgn:1000001",
        "tgn:7016101",
        "tgn:7012149",
        "tgn:7007516",
        "tgn:7029392"
    ],
    "tgn:id":2504049,
    "tgn:name":"Meadow Island",
    "tgn:placetype":[
        "aat:300008791"
    ]
},
  "bbox": [],
  "geometry": {"coordinates":[-77.4667,39.2333],"type":"Point"}
}