{
  "id": 2624626,
  "type": "Feature",
  "properties": {
    "tgn:hierarchy":[
        "tgn:2624626",
        "tgn:1000001",
        "tgn:7012149",
        "tgn:7007706",
        "tgn:7029392"
    ],
    "tgn:id":2624626,
    "tgn:name":"Rock Run",
    "tgn:placetype":[
        "aat:300008699"
    ]
},
  "bbox": [],
  "geometry": {"coordinates":[-83.15,38.9333],"type":"Point"}
}