{
  "id": 7436284,
  "type": "Feature",
  "properties": {
    "tgn:hierarchy":[
        "tgn:7436284",
        "tgn:1000001",
        "tgn:7005589",
        "tgn:7005560",
        "tgn:7029392"
    ],
    "tgn:id":7436284,
    "tgn:name":"Soledad, R\u00edo de",
    "tgn:placetype":[
        "aat:300266554",
        "aat:300008699"
    ]
},
  "bbox": [],
  "geometry": {"coordinates":[-100.65,25.933333],"type":"Point"}
}