{
  "id": 2181058,
  "type": "Feature",
  "properties": {
    "tgn:hierarchy":[
        "tgn:2181058",
        "tgn:1000001",
        "tgn:7012149",
        "tgn:2001455",
        "tgn:7007566",
        "tgn:7029392"
    ],
    "tgn:id":2181058,
    "tgn:name":"Blue Bell Number Two",
    "tgn:placetype":[
        "aat:300000390"
    ]
},
  "bbox": [],
  "geometry": {"coordinates":[-107.6333,32.75],"type":"Point"}
}