{
  "id": 2692388,
  "type": "Feature",
  "properties": {
    "tgn:hierarchy":[
        "tgn:2692388",
        "tgn:1000001",
        "tgn:2002370",
        "tgn:7012149",
        "tgn:7007923",
        "tgn:7029392"
    ],
    "tgn:id":2692388,
    "tgn:name":"Steam Engine Canyon",
    "tgn:placetype":[
        "aat:300008761"
    ]
},
  "bbox": [],
  "geometry": {"coordinates":[-104.5333,44.7833],"type":"Point"}
}