{
  "id": 7167360,
  "type": "Feature",
  "properties": {
    "tgn:hierarchy":[
        "tgn:7167360",
        "tgn:7003669",
        "tgn:1000003",
        "tgn:7000084",
        "tgn:7029392"
    ],
    "tgn:id":7167360,
    "tgn:name":"Haundorf",
    "tgn:placetype":[
        "aat:300008347"
    ]
},
  "bbox": [],
  "geometry": {"coordinates":[10.766667,49.183333],"type":"Point"}
}