{
  "id": 7233882,
  "type": "Feature",
  "properties": {
    "tgn:hierarchy":[
        "tgn:7233882",
        "tgn:7011170",
        "tgn:7002715",
        "tgn:1000003",
        "tgn:1000074",
        "tgn:7029392"
    ],
    "tgn:id":7233882,
    "tgn:name":"Dhiap\u00f3rti, \u00c1kra",
    "tgn:placetype":[
        "aat:300008850"
    ]
},
  "bbox": [],
  "geometry": {"coordinates":[24.283333,40.133333],"type":"Point"}
}