<<<<<<< HEAD
{
  "id": 7117754,
  "type": "Feature",
  "properties": {
    "tgn:hierarchy":[
        "tgn:7117754",
        "tgn:1000003",
        "tgn:7003688",
        "tgn:7000084",
        "tgn:7029392"
    ],
    "tgn:id":7117754,
    "tgn:name":"Osterwinnertfeld",
    "tgn:placetype":[
        "aat:300000206"
    ]
},
  "bbox": [],
  "geometry": {"coordinates":[9.266667,54.433333],"type":"Point"}
}
=======
{"geometry":{"type":"Point","coordinates":[9.266667,54.433333]},"type":"Feature","properties":{"hierarchy":["tgn:7117754","tgn:1000003","tgn:7003688","tgn:7000084","tgn:7029392"],"placetype":["aat:300000206"],"id":7117754,"name:xx":"Osterwinnertfeld"}}
>>>>>>> 03f74aca74312dbeaf24d7e61306dd6a786dc3d0
