{
  "id": 7568319,
  "type": "Feature",
  "properties": {
    "tgn:hierarchy":[
        "tgn:7568319",
        "tgn:1000004",
        "tgn:7000198",
        "tgn:1001996",
        "tgn:7029392"
    ],
    "tgn:id":7568319,
    "tgn:name:en":"H\u012bri ki Beshak Protected Forest",
    "tgn:placetype":[
        "aat:300008863"
    ]
},
  "bbox": [],
  "geometry": {"coordinates":[77.038889,31.169444],"type":"Point"}
}