{
  "id": 7505105,
  "type": "Feature",
  "properties": {
    "tgn:hierarchy":[
        "tgn:7505105",
        "tgn:1009892",
        "tgn:1000226",
        "tgn:1000006",
        "tgn:7029392"
    ],
    "tgn:id":7505105,
    "tgn:name:en":"Molly Cap",
    "tgn:placetype":[
        "aat:300008791"
    ]
},
  "bbox": [],
  "geometry": {"coordinates":[179.061111,-47.767222],"type":"Point"}
}