<<<<<<< HEAD
{
  "id": 2150715,
  "type": "Feature",
  "properties": {
    "tgn:hierarchy":[
        "tgn:2150715",
        "tgn:1000001",
        "tgn:7012149",
        "tgn:2000973",
        "tgn:7007520",
        "tgn:7029392"
    ],
    "tgn:id":2150715,
    "tgn:name":"Bass Cove Lake",
    "tgn:placetype":[
        "aat:300008680"
    ]
},
  "bbox": [],
  "geometry": {"coordinates":[-84.3167,45.95],"type":"Point"}
}
=======
{"geometry":{"type":"Point","coordinates":[-84.316700,45.950000]},"type":"Feature","properties":{"hierarchy":["tgn:2150715","tgn:1000001","tgn:7012149","tgn:2000973","tgn:7007520","tgn:7029392"],"placetype":["aat:300008680"],"id":2150715,"name:xx":"Bass Cove Lake"}}
>>>>>>> 03f74aca74312dbeaf24d7e61306dd6a786dc3d0
