<<<<<<< HEAD
{
  "id": 7021291,
  "type": "Feature",
  "properties": {
    "tgn:hierarchy":[
        "tgn:7021291",
        "tgn:1000001",
        "tgn:7012149",
        "tgn:7029392"
    ],
    "tgn:id":7021291,
    "tgn:name":"Susquehanna River",
    "tgn:placetype":[
        "aat:300008707"
    ]
},
  "bbox": [],
  "geometry": {"coordinates":[-74.9167,42.7],"type":"Point"}
}
=======
{"geometry":{"type":"Point","coordinates":[-74.916700,42.700000]},"type":"Feature","properties":{"hierarchy":["tgn:7021291","tgn:1000001","tgn:7012149","tgn:7029392"],"placetype":["aat:300008707"],"id":7021291,"name:xx":"Susquehanna River"}}
>>>>>>> 03f74aca74312dbeaf24d7e61306dd6a786dc3d0
