{
  "id": 2053073,
  "type": "Feature",
  "properties": {
    "tgn:hierarchy":[
        "tgn:2053073",
        "tgn:1000001",
        "tgn:7012149",
        "tgn:2000985",
        "tgn:7007520",
        "tgn:7029392"
    ],
    "tgn:id":2053073,
    "tgn:name":"Prescott",
    "tgn:placetype":[
        "aat:300008347"
    ]
},
  "bbox": [],
  "geometry": {"coordinates":[-83.9167,44.1833],"type":"Point"}
}