{
  "id": 2671758,
  "type": "Feature",
  "properties": {
    "tgn:hierarchy":[
        "tgn:2671758",
        "tgn:1000001",
        "tgn:7006451",
        "tgn:7012149",
        "tgn:2000104",
        "tgn:7029392"
    ],
    "tgn:id":2671758,
    "tgn:name":"Smith Peak",
    "tgn:placetype":[
        "aat:300008798"
    ]
},
  "bbox": [],
  "geometry": {"coordinates":[-113.35,34.05],"type":"Point"}
}