{
  "id": 7569785,
  "type": "Feature",
  "properties": {
    "tgn:hierarchy":[
        "tgn:7569785",
        "tgn:1001828",
        "tgn:1000004",
        "tgn:7000198",
        "tgn:7029392"
    ],
    "tgn:id":7569785,
    "tgn:name:en":"Timm\u0101pur",
    "tgn:placetype":[
        "aat:300008347"
    ]
},
  "bbox": [],
  "geometry": {"coordinates":[78.557778,17.13],"type":"Point"}
}