{
  "id": 2394218,
  "type": "Feature",
  "properties": {
    "tgn:hierarchy":[
        "tgn:2394218",
        "tgn:1000001",
        "tgn:7012149",
        "tgn:1002432",
        "tgn:7007706",
        "tgn:7029392"
    ],
    "tgn:id":2394218,
    "tgn:name":"Hogback",
    "tgn:placetype":[
        "aat:300266640"
    ]
},
  "bbox": [],
  "geometry": {"coordinates":[-81.35,40.0833],"type":"Point"}
}