{
  "id": 2410435,
  "type": "Feature",
  "properties": {
    "tgn:hierarchy":[
        "tgn:2410435",
        "tgn:1000001",
        "tgn:7012149",
        "tgn:2002067",
        "tgn:7007826",
        "tgn:7029392"
    ],
    "tgn:id":2410435,
    "tgn:name":"Indian Camp Branch",
    "tgn:placetype":[
        "aat:300008699"
    ]
},
  "bbox": [],
  "geometry": {"coordinates":[-94.0333,31.1833],"type":"Point"}
}