{
  "id": 1078323,
  "type": "Feature",
  "properties": {
    "tgn:hierarchy":[
        "tgn:1078323",
        "tgn:1006656",
        "tgn:1000004",
        "tgn:1001549",
        "tgn:1000116",
        "tgn:7029392"
    ],
    "tgn:id":1078323,
    "tgn:name":"Pasarwajo",
    "tgn:placetype":[
        "aat:300008347"
    ]
},
  "bbox": [],
  "geometry": {"coordinates":[122.85,-5.5167],"type":"Point"}
}