<<<<<<< HEAD
{
  "id": 2702159,
  "type": "Feature",
  "properties": {
    "tgn:hierarchy":[
        "tgn:2702159",
        "tgn:1000001",
        "tgn:1002361",
        "tgn:7012149",
        "tgn:7007828",
        "tgn:7029392"
    ],
    "tgn:id":2702159,
    "tgn:name":"Sukes Pond",
    "tgn:placetype":[
        "aat:300008680"
    ]
},
  "bbox": [],
  "geometry": {"coordinates":[-71.8833,44.75],"type":"Point"}
}
=======
{"geometry":{"type":"Point","coordinates":[-71.883300,44.750000]},"type":"Feature","properties":{"hierarchy":["tgn:2702159","tgn:1000001","tgn:1002361","tgn:7012149","tgn:7007828","tgn:7029392"],"placetype":["aat:300008680"],"id":2702159,"name:xx":"Sukes Pond"}}
>>>>>>> 03f74aca74312dbeaf24d7e61306dd6a786dc3d0
