<<<<<<< HEAD
{
  "id": 7480944,
  "type": "Feature",
  "properties": {
    "tgn:hierarchy":[
        "tgn:7480944",
        "tgn:1000004",
        "tgn:7001014",
        "tgn:1000141",
        "tgn:7029392"
    ],
    "tgn:id":7480944,
    "tgn:name":"Nan Fangchaoti",
    "tgn:placetype":[
        "aat:300006137"
    ]
},
  "bbox": [],
  "geometry": {"coordinates":[120.178889,23.760833],"type":"Point"}
}
=======
{"geometry":{"type":"Point","coordinates":[120.178889,23.760833]},"type":"Feature","properties":{"hierarchy":["tgn:7480944","tgn:1000004","tgn:7001014","tgn:1000141","tgn:7029392"],"placetype":["aat:300006137"],"id":7480944,"name:xx":"Nan Fangchaoti"}}
>>>>>>> 03f74aca74312dbeaf24d7e61306dd6a786dc3d0
