{
  "id": 7480944,
  "type": "Feature",
  "properties": {
    "tgn:hierarchy":[
        "tgn:7480944",
        "tgn:1000004",
        "tgn:7001014",
        "tgn:1000141",
        "tgn:7029392"
    ],
    "tgn:id":7480944,
    "tgn:name":"Nan Fangchaoti",
    "tgn:placetype":[
        "aat:300006137"
    ]
},
  "bbox": [],
  "geometry": {"coordinates":[120.178889,23.760833],"type":"Point"}
}