{
  "id": 7587121,
  "type": "Feature",
  "properties": {
    "tgn:hierarchy":[
        "tgn:7587121",
        "tgn:1000004",
        "tgn:7000198",
        "tgn:7000799",
        "tgn:7029392"
    ],
    "tgn:id":7587121,
    "tgn:name:en":"Nu Chid",
    "tgn:placetype":[
        "aat:300008347"
    ]
},
  "bbox": [],
  "geometry": {"coordinates":[74.908333,34.169444],"type":"Point"}
}