<<<<<<< HEAD
{
  "id": 2257883,
  "type": "Feature",
  "properties": {
    "tgn:hierarchy":[
        "tgn:2257883",
        "tgn:1000001",
        "tgn:7012149",
        "tgn:2001446",
        "tgn:7007566",
        "tgn:7029392"
    ],
    "tgn:id":2257883,
    "tgn:name":"Correo Spring",
    "tgn:placetype":[
        "aat:300008697"
    ]
},
  "bbox": [],
  "geometry": {"coordinates":[-104.7333,36.1],"type":"Point"}
}
=======
{"geometry":{"type":"Point","coordinates":[-104.733300,36.100000]},"type":"Feature","properties":{"hierarchy":["tgn:2257883","tgn:1000001","tgn:7012149","tgn:2001446","tgn:7007566","tgn:7029392"],"placetype":["aat:300008697"],"id":2257883,"name:xx":"Correo Spring"}}
>>>>>>> 03f74aca74312dbeaf24d7e61306dd6a786dc3d0
