{
  "id": 7230556,
  "type": "Feature",
  "properties": {
    "tgn:hierarchy":[
        "tgn:7230556",
        "tgn:7002681",
        "tgn:7001395",
        "tgn:1000003",
        "tgn:1000074",
        "tgn:7029392"
    ],
    "tgn:id":7230556,
    "tgn:name":"Xeronisi, N\u00edsos",
    "tgn:placetype":[
        "aat:300008791"
    ]
},
  "bbox": [],
  "geometry": {"coordinates":[24.283333,38.016667],"type":"Point"}
}