{
  "id": 2650735,
  "type": "Feature",
  "properties": {
    "tgn:hierarchy":[
        "tgn:2650735",
        "tgn:1000001",
        "tgn:7012149",
        "tgn:7016021",
        "tgn:7007568",
        "tgn:7029392"
    ],
    "tgn:id":2650735,
    "tgn:name":"Second Brook",
    "tgn:placetype":[
        "aat:300008699"
    ]
},
  "bbox": [],
  "geometry": {"coordinates":[-74.9667,44.3167],"type":"Point"}
}