{
  "id": 2187256,
  "type": "Feature",
  "properties": {
    "tgn:hierarchy":[
        "tgn:2187256",
        "tgn:1000001",
        "tgn:7012149",
        "tgn:1002881",
        "tgn:7007240",
        "tgn:7029392"
    ],
    "tgn:id":2187256,
    "tgn:name":"Bookertown",
    "tgn:placetype":[
        "aat:300008347"
    ]
},
  "bbox": [],
  "geometry": {"coordinates":[-81.3167,28.8167],"type":"Point"}
}