{
  "id": 7015957,
  "type": "Feature",
  "properties": {
    "tgn:hierarchy":[
        "tgn:7015957",
        "tgn:1000004",
        "tgn:1001339",
        "tgn:1000116",
        "tgn:7029392"
    ],
    "tgn:id":7015957,
    "tgn:name":"Balikpapan",
    "tgn:placetype":[
        "aat:300008347"
    ]
},
  "bbox": [],
  "geometry": {"coordinates":[116.8333,-1.25],"type":"Point"}
}