{
  "id": 2463322,
  "type": "Feature",
  "properties": {
    "tgn:hierarchy":[
        "tgn:2463322",
        "tgn:1000001",
        "tgn:7012149",
        "tgn:1003042",
        "tgn:7007920",
        "tgn:7029392"
    ],
    "tgn:id":2463322,
    "tgn:name":"Lizzy Canyon",
    "tgn:placetype":[
        "aat:300008761"
    ]
},
  "bbox": [],
  "geometry": {"coordinates":[-120.5667,46.1167],"type":"Point"}
}