{
  "id": 1140324,
  "type": "Feature",
  "properties": {
    "tgn:hierarchy":[
        "tgn:1140324",
        "tgn:1000971",
        "tgn:1000004",
        "tgn:7000894",
        "tgn:1000120",
        "tgn:7029392"
    ],
    "tgn:id":1140324,
    "tgn:name":"Asahi",
    "tgn:placetype":[
        "aat:300008347"
    ]
},
  "bbox": [],
  "geometry": {"coordinates":[140.6333,35.7167],"type":"Point"}
}