{
  "id": 2100953,
  "type": "Feature",
  "properties": {
    "tgn:hierarchy":[
        "tgn:2100953",
        "tgn:1000001",
        "tgn:7012149",
        "tgn:2001929",
        "tgn:7007825",
        "tgn:7029392"
    ],
    "tgn:id":2100953,
    "tgn:name":"Peeled Chestnut",
    "tgn:placetype":[
        "aat:300008347"
    ]
},
  "bbox": [],
  "geometry": {"coordinates":[-85.65,35.95],"type":"Point"}
}