{
  "id": 7417987,
  "type": "Feature",
  "properties": {
    "tgn:hierarchy":[
        "tgn:7417987",
        "tgn:1000001",
        "tgn:7005591",
        "tgn:7005560",
        "tgn:7029392"
    ],
    "tgn:id":7417987,
    "tgn:name:es":"San Luis Morelia",
    "tgn:placetype":[
        "aat:300008347"
    ]
},
  "bbox": [],
  "geometry": {"coordinates":[-98.218611,17.715833],"type":"Point"}
}