<<<<<<< HEAD
{
  "id": 2331056,
  "type": "Feature",
  "properties": {
    "tgn:hierarchy":[
        "tgn:2331056",
        "tgn:1000001",
        "tgn:7012149",
        "tgn:2000364",
        "tgn:7007248",
        "tgn:7029392"
    ],
    "tgn:id":2331056,
    "tgn:name":"Flat Shoals Creek",
    "tgn:placetype":[
        "aat:300008706"
    ]
},
  "bbox": [],
  "geometry": {"coordinates":[-83.0167,34.3667],"type":"Point"}
}
=======
{"geometry":{"type":"Point","coordinates":[-83.016700,34.366700]},"type":"Feature","properties":{"hierarchy":["tgn:2331056","tgn:1000001","tgn:7012149","tgn:2000364","tgn:7007248","tgn:7029392"],"placetype":["aat:300008706"],"id":2331056,"name:xx":"Flat Shoals Creek"}}
>>>>>>> 03f74aca74312dbeaf24d7e61306dd6a786dc3d0
