{
  "id": 2110104,
  "type": "Feature",
  "properties": {
    "tgn:hierarchy":[
        "tgn:2110104",
        "tgn:1000001",
        "tgn:2002134",
        "tgn:7012149",
        "tgn:7007828",
        "tgn:7029392"
    ],
    "tgn:id":2110104,
    "tgn:name":"Tunbridge",
    "tgn:placetype":[
        "aat:300008347"
    ]
},
  "bbox": [],
  "geometry": {"coordinates":[-72.4833,43.8833],"type":"Point"}
}