{
  "id": 7219168,
  "type": "Feature",
  "properties": {
    "tgn:hierarchy":[
        "tgn:7219168",
        "tgn:7011167",
        "tgn:7001338",
        "tgn:1000003",
        "tgn:1000074",
        "tgn:7029392"
    ],
    "tgn:id":7219168,
    "tgn:name":"Vourli\u00e1, \u00d3rmos",
    "tgn:placetype":[
        "aat:300132316"
    ]
},
  "bbox": [],
  "geometry": {"coordinates":[21.083333,38.483333],"type":"Point"}
}