{
  "id": 2357198,
  "type": "Feature",
  "properties": {
    "tgn:hierarchy":[
        "tgn:2357198",
        "tgn:1000001",
        "tgn:7012149",
        "tgn:2000927",
        "tgn:7007515",
        "tgn:7029392"
    ],
    "tgn:id":2357198,
    "tgn:name":"Gould Pond",
    "tgn:placetype":[
        "aat:300008680"
    ]
},
  "bbox": [],
  "geometry": {"coordinates":[-69.3167,44.9833],"type":"Point"}
}