{
  "id": 2591704,
  "type": "Feature",
  "properties": {
    "tgn:hierarchy":[
        "tgn:2591704",
        "tgn:1000001",
        "tgn:7012149",
        "tgn:7007525",
        "tgn:7029392"
    ],
    "tgn:id":2591704,
    "tgn:name":"Pond Creek",
    "tgn:placetype":[
        "aat:300008706"
    ]
},
  "bbox": [],
  "geometry": {"coordinates":[-97.0667,41.5167],"type":"Point"}
}