{
  "id": 7363604,
  "type": "Feature",
  "properties": {
    "tgn:hierarchy":[
        "tgn:7363604",
        "tgn:1000001",
        "tgn:1001906",
        "tgn:7005560",
        "tgn:7029392"
    ],
    "tgn:id":7363604,
    "tgn:name":"El Molino",
    "tgn:placetype":[
        "aat:300008347"
    ]
},
  "bbox": [],
  "geometry": {"coordinates":[-104.45,21.016667],"type":"Point"}
}