{
  "id": 7138802,
  "type": "Feature",
  "properties": {
    "tgn:hierarchy":[
        "tgn:7138802",
        "tgn:1000003",
        "tgn:7003677",
        "tgn:7000084",
        "tgn:7029392"
    ],
    "tgn:id":7138802,
    "tgn:name":"Langer Berg",
    "tgn:placetype":[
        "aat:300008777"
    ]
},
  "bbox": [],
  "geometry": {"coordinates":[8.483333,51.366667],"type":"Point"}
}