{
  "id": 2410516,
  "type": "Feature",
  "properties": {
    "tgn:hierarchy":[
        "tgn:2410516",
        "tgn:1000001",
        "tgn:7012149",
        "tgn:2001718",
        "tgn:7007708",
        "tgn:7029392"
    ],
    "tgn:id":2410516,
    "tgn:name":"Indian Canyon",
    "tgn:placetype":[
        "aat:300008761"
    ]
},
  "bbox": [],
  "geometry": {"coordinates":[-117.1333,42.6333],"type":"Point"}
}