{
  "id": 7273732,
  "type": "Feature",
  "properties": {
    "tgn:concordances":{
        "gn:id":"2744312"
    },
    "tgn:hierarchy":[
        "tgn:7273732",
        "tgn:7003619",
        "tgn:1000003",
        "tgn:7016845",
        "tgn:7029392"
    ],
    "tgn:id":7273732,
    "tgn:name:nl":"Wissinkhoek",
    "tgn:placetype":[
        "aat:300008347"
    ]
},
  "bbox": [],
  "geometry": {"coordinates":[6.466667,52.066667],"type":"Point"}
}