{
  "id": 2129540,
  "type": "Feature",
  "properties": {
    "tgn:hierarchy":[
        "tgn:2129540",
        "tgn:1000001",
        "tgn:7012149",
        "tgn:2002382",
        "tgn:7007923",
        "tgn:7029392"
    ],
    "tgn:id":2129540,
    "tgn:name":"Alkali Draw Pit Number 1",
    "tgn:placetype":[
        "aat:300006191"
    ]
},
  "bbox": [],
  "geometry": {"coordinates":[-109.9167,42.45],"type":"Point"}
}