<<<<<<< HEAD
{
  "id": 2151054,
  "type": "Feature",
  "properties": {
    "tgn:hierarchy":[
        "tgn:2151054",
        "tgn:2002308",
        "tgn:1000001",
        "tgn:7012149",
        "tgn:7007922",
        "tgn:7029392"
    ],
    "tgn:id":2151054,
    "tgn:name":"Basswood Lake",
    "tgn:placetype":[
        "aat:300008680"
    ]
},
  "bbox": [],
  "geometry": {"coordinates":[-91.3167,46.4667],"type":"Point"}
}
=======
{"geometry":{"type":"Point","coordinates":[-91.316700,46.466700]},"type":"Feature","properties":{"hierarchy":["tgn:2151054","tgn:2002308","tgn:1000001","tgn:7012149","tgn:7007922","tgn:7029392"],"placetype":["aat:300008680"],"id":2151054,"name:xx":"Basswood Lake"}}
>>>>>>> 03f74aca74312dbeaf24d7e61306dd6a786dc3d0
