{
  "id": 7416346,
  "type": "Feature",
  "properties": {
    "tgn:hierarchy":[
        "tgn:7416346",
        "tgn:1000001",
        "tgn:7005596",
        "tgn:7005560",
        "tgn:7029392"
    ],
    "tgn:id":7416346,
    "tgn:name:es":"Jim\u00e9nez",
    "tgn:placetype":[
        "aat:300008347"
    ]
},
  "bbox": [],
  "geometry": {"coordinates":[-92.929167,18.183333],"type":"Point"}
}