{
  "id": 2618010,
  "type": "Feature",
  "properties": {
    "tgn:hierarchy":[
        "tgn:2618010",
        "tgn:1000001",
        "tgn:7012149",
        "tgn:2000233",
        "tgn:7007158",
        "tgn:7029392"
    ],
    "tgn:id":2618010,
    "tgn:name":"Ridgetop Reservoir",
    "tgn:placetype":[
        "aat:300006191"
    ]
},
  "bbox": [],
  "geometry": {"coordinates":[-108.05,37.5667],"type":"Point"}
}