{
  "id": 7368188,
  "type": "Feature",
  "properties": {
    "tgn:hierarchy":[
        "tgn:7368188",
        "tgn:1000001",
        "tgn:7005592",
        "tgn:7005560",
        "tgn:7029392"
    ],
    "tgn:id":7368188,
    "tgn:name":"Ignacio Ram\u00edrez",
    "tgn:placetype":[
        "aat:300008347"
    ]
},
  "bbox": [],
  "geometry": {"coordinates":[-97.75,20.116667],"type":"Point"}
}