{
  "id": 7501996,
  "type": "Feature",
  "properties": {
    "tgn:hierarchy":[
        "tgn:7501996",
        "tgn:1000004",
        "tgn:7492971",
        "tgn:1000141",
        "tgn:7029392"
    ],
    "tgn:id":7501996,
    "tgn:name":"Bala Xi",
    "tgn:placetype":[
        "aat:300008699"
    ]
},
  "bbox": [],
  "geometry": {"coordinates":[120.831111,22.101944],"type":"Point"}
}