{
  "id": 1021404,
  "type": "Feature",
  "properties": {
    "tgn:hierarchy":[
        "tgn:1021404",
        "tgn:7006237",
        "tgn:1000047",
        "tgn:7002457",
        "tgn:1000002",
        "tgn:7029392"
    ],
    "tgn:id":1021404,
    "tgn:name":"Estr\u00eala do Sul",
    "tgn:placetype":[
        "aat:300008347"
    ]
},
  "bbox": [],
  "geometry": {"coordinates":[-47.7167,-18.75],"type":"Point"}
}