{
  "id": 2399619,
  "type": "Feature",
  "properties": {
    "tgn:hierarchy":[
        "tgn:2399619",
        "tgn:1000001",
        "tgn:1002260",
        "tgn:7012149",
        "tgn:7007920",
        "tgn:7029392"
    ],
    "tgn:id":2399619,
    "tgn:name":"Hornet Ridge",
    "tgn:placetype":[
        "aat:300266640"
    ]
},
  "bbox": [],
  "geometry": {"coordinates":[-120.4833,47.7833],"type":"Point"}
}