{
  "id": 1080868,
  "type": "Feature",
  "properties": {
    "tgn:hierarchy":[
        "tgn:1080868",
        "tgn:7000895",
        "tgn:1000004",
        "tgn:1000977",
        "tgn:1000120",
        "tgn:7029392"
    ],
    "tgn:id":1080868,
    "tgn:name":"Motosu",
    "tgn:placetype":[
        "aat:300008347"
    ]
},
  "bbox": [],
  "geometry": {"coordinates":[136.6667,35.4833],"type":"Point"}
}