{
  "id": 7590733,
  "type": "Feature",
  "properties": {
    "tgn:hierarchy":[
        "tgn:7590733",
        "tgn:1000004",
        "tgn:7000198",
        "tgn:7000799",
        "tgn:7029392"
    ],
    "tgn:id":7590733,
    "tgn:name:en":"Mohar N\u0101r",
    "tgn:placetype":[
        "aat:300008699"
    ]
},
  "bbox": [],
  "geometry": {"coordinates":[73.951723,34.439379],"type":"Point"}
}