{
  "id": 2641530,
  "type": "Feature",
  "properties": {
    "tgn:hierarchy":[
        "tgn:2641530",
        "tgn:1000001",
        "tgn:7012149",
        "tgn:2000745",
        "tgn:7007254",
        "tgn:7029392"
    ],
    "tgn:id":2641530,
    "tgn:name":"Sand Draw",
    "tgn:placetype":[
        "aat:300008761"
    ]
},
  "bbox": [],
  "geometry": {"coordinates":[-100.8833,38.6333],"type":"Point"}
}