{
  "id": 7270401,
  "type": "Feature",
  "properties": {
    "tgn:concordances":{
        "gn:id":"2750345"
    },
    "tgn:hierarchy":[
        "tgn:7270401",
        "tgn:1000003",
        "tgn:7006951",
        "tgn:7016845",
        "tgn:7029392"
    ],
    "tgn:id":7270401,
    "tgn:name:nl":"Nieuwe Brug",
    "tgn:placetype":[
        "aat:300008347"
    ]
},
  "bbox": [],
  "geometry": {"coordinates":[4.666667,52.366667],"type":"Point"}
}