{
  "id": 2315406,
  "type": "Feature",
  "properties": {
    "tgn:hierarchy":[
        "tgn:2315406",
        "tgn:7006450",
        "tgn:1000001",
        "tgn:7012149",
        "tgn:7019760",
        "tgn:7029392"
    ],
    "tgn:id":2315406,
    "tgn:name":"Elliott Island",
    "tgn:placetype":[
        "aat:300008791"
    ]
},
  "bbox": [],
  "geometry": {"coordinates":[-134.05,57.25],"type":"Point"}
}