{
  "id": 2008719,
  "type": "Feature",
  "properties": {
    "tgn:hierarchy":[
        "tgn:2008719",
        "tgn:1000001",
        "tgn:7016172",
        "tgn:7012149",
        "tgn:2000141",
        "tgn:7029392"
    ],
    "tgn:id":2008719,
    "tgn:name":"Lewisville",
    "tgn:placetype":[
        "aat:300008347"
    ]
},
  "bbox": [],
  "geometry": {"coordinates":[-93.5667,33.35],"type":"Point"}
}