{
  "id": 2001942,
  "type": "Feature",
  "properties": {
    "tgn:hierarchy":[
        "tgn:2001942",
        "tgn:1000001",
        "tgn:7012149",
        "tgn:7007826",
        "tgn:7029392"
    ],
    "tgn:id":2001942,
    "tgn:name":"Blanco",
    "tgn:placetype":[
        "aat:300387145",
        "aat:300000771"
    ]
},
  "bbox": [],
  "geometry": {"coordinates":[-98.4167,30.25],"type":"Point"}
}