{
  "id": 7503090,
  "type": "Feature",
  "properties": {
    "tgn:hierarchy":[
        "tgn:7503090",
        "tgn:7001010",
        "tgn:1000004",
        "tgn:1000141",
        "tgn:7029392"
    ],
    "tgn:id":7503090,
    "tgn:name":"Shipai Tifang",
    "tgn:placetype":[
        "aat:300006156"
    ]
},
  "bbox": [],
  "geometry": {"coordinates":[121.257222,23.191111],"type":"Point"}
}