{
  "id": 1061214,
  "type": "Feature",
  "properties": {
    "tgn:hierarchy":[
        "tgn:1061214",
        "tgn:7011701",
        "tgn:1000003",
        "tgn:7006657",
        "tgn:7029392"
    ],
    "tgn:id":1061214,
    "tgn:name":"Vidzy",
    "tgn:placetype":[
        "aat:300008347"
    ]
},
  "bbox": [],
  "geometry": {"coordinates":[26.5333,55.3833],"type":"Point"}
}