{
  "id": 2747902,
  "type": "Feature",
  "properties": {
    "tgn:hierarchy":[
        "tgn:2747902",
        "tgn:1000001",
        "tgn:7012149",
        "tgn:2000488",
        "tgn:7007250",
        "tgn:7029392"
    ],
    "tgn:id":2747902,
    "tgn:name":"Walcot Basin",
    "tgn:placetype":[
        "aat:300386845"
    ]
},
  "bbox": [],
  "geometry": {"coordinates":[-116.8667,42.05],"type":"Point"}
}