{
  "id": 7415855,
  "type": "Feature",
  "properties": {
    "tgn:hierarchy":[
        "tgn:7415855",
        "tgn:7005584",
        "tgn:1000001",
        "tgn:7005560",
        "tgn:7029392"
    ],
    "tgn:id":7415855,
    "tgn:name":"Purianizicuaro",
    "tgn:placetype":[
        "aat:300008347"
    ]
},
  "bbox": [],
  "geometry": {"coordinates":[-100.566389,20.078056],"type":"Point"}
}