{
  "id": 2693500,
  "type": "Feature",
  "properties": {
    "tgn:hierarchy":[
        "tgn:2693500",
        "tgn:7002659",
        "tgn:1000001",
        "tgn:7012149",
        "tgn:2000057",
        "tgn:7029392"
    ],
    "tgn:id":2693500,
    "tgn:name":"Stemley Cove",
    "tgn:placetype":[
        "aat:300008347"
    ]
},
  "bbox": [],
  "geometry": {"coordinates":[-86.2167,33.5167],"type":"Point"}
}