{
  "id": 7131940,
  "type": "Feature",
  "properties": {
    "tgn:hierarchy":[
        "tgn:7131940",
        "tgn:1000003",
        "tgn:7003677",
        "tgn:7000084",
        "tgn:7029392"
    ],
    "tgn:id":7131940,
    "tgn:name":"Mausthal",
    "tgn:placetype":[
        "aat:300000206"
    ]
},
  "bbox": [],
  "geometry": {"coordinates":[8.083333,50.966667],"type":"Point"}
}