{
  "id": 2415979,
  "type": "Feature",
  "properties": {
    "tgn:hierarchy":[
        "tgn:2415979",
        "tgn:1000001",
        "tgn:2002367",
        "tgn:7012149",
        "tgn:7007923",
        "tgn:7029392"
    ],
    "tgn:id":2415979,
    "tgn:name":"Ivy Draw",
    "tgn:placetype":[
        "aat:300008761"
    ]
},
  "bbox": [],
  "geometry": {"coordinates":[-105.9833,44.7167],"type":"Point"}
}