{
  "id": 7188290,
  "type": "Feature",
  "properties": {
    "tgn:hierarchy":[
        "tgn:7188290",
        "tgn:7003692",
        "tgn:1000003",
        "tgn:7000084",
        "tgn:7029392"
    ],
    "tgn:id":7188290,
    "tgn:name":"Erkenbrechtsweiler",
    "tgn:placetype":[
        "aat:300008347"
    ]
},
  "bbox": [],
  "geometry": {"coordinates":[9.433333,48.55],"type":"Point"}
}