{
  "id": 7466808,
  "type": "Feature",
  "properties": {
    "tgn:hierarchy":[
        "tgn:7466808",
        "tgn:7002448",
        "tgn:7008698",
        "tgn:1000003",
        "tgn:7008591",
        "tgn:7029392"
    ],
    "tgn:id":7466808,
    "tgn:name:en":"Ballywillwill House",
    "tgn:placetype":[
        "aat:300387502"
    ]
},
  "bbox": [],
  "geometry": {"coordinates":[-5.916667,54.283333],"type":"Point"}
}