{
  "id": 2749621,
  "type": "Feature",
  "properties": {
    "tgn:hierarchy":[
        "tgn:2749621",
        "tgn:1000001",
        "tgn:7012149",
        "tgn:2001548",
        "tgn:7007709",
        "tgn:7029392"
    ],
    "tgn:id":2749621,
    "tgn:name":"Walnut Creek",
    "tgn:placetype":[
        "aat:300008706"
    ]
},
  "bbox": [],
  "geometry": {"coordinates":[-78.75,35.7833],"type":"Point"}
}