{
  "id": 2469826,
  "type": "Feature",
  "properties": {
    "tgn:hierarchy":[
        "tgn:2469826",
        "tgn:1002159",
        "tgn:1000001",
        "tgn:7012149",
        "tgn:7007706",
        "tgn:7029392"
    ],
    "tgn:id":2469826,
    "tgn:name":"Lookout, Mount",
    "tgn:placetype":[
        "aat:300008798"
    ]
},
  "bbox": [],
  "geometry": {"coordinates":[-84.0167,40.5833],"type":"Point"}
}