{
  "id": 7197065,
  "type": "Feature",
  "properties": {
    "tgn:hierarchy":[
        "tgn:7197065",
        "tgn:1000003",
        "tgn:7000094",
        "tgn:7000084",
        "tgn:7029392"
    ],
    "tgn:id":7197065,
    "tgn:name":"Dar\u00df, Forst",
    "tgn:placetype":[
        "aat:300008863"
    ]
},
  "bbox": [],
  "geometry": {"coordinates":[12.516667,54.433333],"type":"Point"}
}