{
  "id": 2486359,
  "type": "Feature",
  "properties": {
    "tgn:hierarchy":[
        "tgn:2486359",
        "tgn:1000001",
        "tgn:7012149",
        "tgn:1002823",
        "tgn:7007706",
        "tgn:7029392"
    ],
    "tgn:id":2486359,
    "tgn:name":"Leatherwood Creek",
    "tgn:placetype":[
        "aat:300008706"
    ]
},
  "bbox": [],
  "geometry": {"coordinates":[-82.5833,40.85],"type":"Point"}
}