<<<<<<< HEAD
{
  "id": 7352168,
  "type": "Feature",
  "properties": {
    "tgn:hierarchy":[
        "tgn:7352168",
        "tgn:7005583",
        "tgn:1000001",
        "tgn:7005560",
        "tgn:7029392"
    ],
    "tgn:id":7352168,
    "tgn:name":"Bozos",
    "tgn:placetype":[
        "aat:300008347"
    ]
},
  "bbox": [],
  "geometry": {"coordinates":[-106.05,24.65],"type":"Point"}
}
=======
{"geometry":{"type":"Point","coordinates":[-106.050000,24.650000]},"type":"Feature","properties":{"hierarchy":["tgn:7352168","tgn:7005583","tgn:1000001","tgn:7005560","tgn:7029392"],"placetype":["aat:300008347"],"id":7352168,"name:xx":"Bozos"}}
>>>>>>> 03f74aca74312dbeaf24d7e61306dd6a786dc3d0
