{
  "id": 7352168,
  "type": "Feature",
  "properties": {
    "tgn:hierarchy":[
        "tgn:7352168",
        "tgn:7005583",
        "tgn:1000001",
        "tgn:7005560",
        "tgn:7029392"
    ],
    "tgn:id":7352168,
    "tgn:name":"Bozos",
    "tgn:placetype":[
        "aat:300008347"
    ]
},
  "bbox": [],
  "geometry": {"coordinates":[-106.05,24.65],"type":"Point"}
}