{
  "id": 7400942,
  "type": "Feature",
  "properties": {
    "tgn:hierarchy":[
        "tgn:7400942",
        "tgn:1000001",
        "tgn:7005599",
        "tgn:7005560",
        "tgn:7029392"
    ],
    "tgn:id":7400942,
    "tgn:name":"La Luz del Portugu\u00e9s",
    "tgn:placetype":[
        "aat:300008347"
    ]
},
  "bbox": [],
  "geometry": {"coordinates":[-97.066667,20.416667],"type":"Point"}
}