<<<<<<< HEAD
{
  "id": 2332940,
  "type": "Feature",
  "properties": {
    "tgn:hierarchy":[
        "tgn:2332940",
        "tgn:1000001",
        "tgn:7012149",
        "tgn:2001307",
        "tgn:7007524",
        "tgn:7029392"
    ],
    "tgn:id":2332940,
    "tgn:name":"Flume Creek",
    "tgn:placetype":[
        "aat:300008706"
    ]
},
  "bbox": [],
  "geometry": {"coordinates":[-109.8167,45.35],"type":"Point"}
}
=======
{"geometry":{"type":"Point","coordinates":[-109.816700,45.350000]},"type":"Feature","properties":{"hierarchy":["tgn:2332940","tgn:1000001","tgn:7012149","tgn:2001307","tgn:7007524","tgn:7029392"],"placetype":["aat:300008706"],"id":2332940,"name:xx":"Flume Creek"}}
>>>>>>> 03f74aca74312dbeaf24d7e61306dd6a786dc3d0
