{
  "id": 7410975,
  "type": "Feature",
  "properties": {
    "tgn:hierarchy":[
        "tgn:7410975",
        "tgn:1000001",
        "tgn:7005596",
        "tgn:7005560",
        "tgn:7029392"
    ],
    "tgn:id":7410975,
    "tgn:name:es":"Playa Larga",
    "tgn:placetype":[
        "aat:300008347"
    ]
},
  "bbox": [],
  "geometry": {"coordinates":[-91.808333,17.9375],"type":"Point"}
}