<<<<<<< HEAD
{
  "id": 2766730,
  "type": "Feature",
  "properties": {
    "tgn:hierarchy":[
        "tgn:2766730",
        "tgn:1000001",
        "tgn:1002360",
        "tgn:7012149",
        "tgn:7007565",
        "tgn:7029392"
    ],
    "tgn:id":2766730,
    "tgn:name":"White Oak Ridge",
    "tgn:placetype":[
        "aat:300008347"
    ]
},
  "bbox": [],
  "geometry": {"coordinates":[-74.3333,40.7333],"type":"Point"}
}
=======
{"geometry":{"type":"Point","coordinates":[-74.333300,40.733300]},"type":"Feature","properties":{"hierarchy":["tgn:2766730","tgn:1000001","tgn:1002360","tgn:7012149","tgn:7007565","tgn:7029392"],"placetype":["aat:300008347"],"id":2766730,"name:xx":"White Oak Ridge"}}
>>>>>>> 03f74aca74312dbeaf24d7e61306dd6a786dc3d0
