{
  "id": 7224276,
  "type": "Feature",
  "properties": {
    "tgn:hierarchy":[
        "tgn:7224276",
        "tgn:7011330",
        "tgn:7002674",
        "tgn:1000003",
        "tgn:1000074",
        "tgn:7029392"
    ],
    "tgn:id":7224276,
    "tgn:name":"T\u00e9los, \u00c1kra",
    "tgn:placetype":[
        "aat:300008850"
    ]
},
  "bbox": [],
  "geometry": {"coordinates":[26.883333,37.083333],"type":"Point"}
}