{
  "id": 7533032,
  "type": "Feature",
  "properties": {
    "tgn:hierarchy":[
        "tgn:7533032",
        "tgn:7001242",
        "tgn:1001075",
        "tgn:7016833",
        "tgn:7029392"
    ],
    "tgn:id":7533032,
    "tgn:name:en":"Ab\u016b Khar\u0101sh",
    "tgn:placetype":[
        "aat:300008347"
    ]
},
  "bbox": [],
  "geometry": {"coordinates":[30.592005,31.059478],"type":"Point"}
}