{
  "id": 7035883,
  "type": "Feature",
  "properties": {
    "tgn:hierarchy":[
        "tgn:7035883",
        "tgn:7003006",
        "tgn:1000003",
        "tgn:7002997",
        "tgn:1000080",
        "tgn:7029392"
    ],
    "tgn:id":7035883,
    "tgn:name":"Ca Matte",
    "tgn:placetype":[
        "aat:300008347"
    ]
},
  "bbox": [],
  "geometry": {"coordinates":[12.115556,45.123611],"type":"Point"}
}