{
  "id": 2176100,
  "type": "Feature",
  "properties": {
    "tgn:hierarchy":[
        "tgn:2176100",
        "tgn:1000001",
        "tgn:7012149",
        "tgn:2000439",
        "tgn:7007248",
        "tgn:7029392"
    ],
    "tgn:id":2176100,
    "tgn:name":"Black Hammock",
    "tgn:placetype":[
        "aat:300008791"
    ]
},
  "bbox": [],
  "geometry": {"coordinates":[-82.3333,31.05],"type":"Point"}
}