{
  "id": 2237712,
  "type": "Feature",
  "properties": {
    "tgn:hierarchy":[
        "tgn:2237712",
        "tgn:1000001",
        "tgn:7012149",
        "tgn:2000897",
        "tgn:7007256",
        "tgn:7029392"
    ],
    "tgn:id":2237712,
    "tgn:name":"Chino Bay",
    "tgn:placetype":[
        "aat:300132316"
    ]
},
  "bbox": [],
  "geometry": {"coordinates":[-89.2167,30.0167],"type":"Point"}
}