{
  "id": 2427197,
  "type": "Feature",
  "properties": {
    "tgn:hierarchy":[
        "tgn:2427197",
        "tgn:1000001",
        "tgn:7012149",
        "tgn:2002047",
        "tgn:7007826",
        "tgn:7029392"
    ],
    "tgn:id":2427197,
    "tgn:name":"Jordan Branch",
    "tgn:placetype":[
        "aat:300008699"
    ]
},
  "bbox": [],
  "geometry": {"coordinates":[-93.8167,31.0333],"type":"Point"}
}