{
  "id": 2343580,
  "type": "Feature",
  "properties": {
    "tgn:hierarchy":[
        "tgn:2343580",
        "tgn:1000001",
        "tgn:7012149",
        "tgn:1002999",
        "tgn:7007526",
        "tgn:7029392"
    ],
    "tgn:id":2343580,
    "tgn:name":"Galena Hill Mine",
    "tgn:placetype":[
        "aat:300000390"
    ]
},
  "bbox": [],
  "geometry": {"coordinates":[-119.7667,39.3667],"type":"Point"}
}