{
  "id": 7558821,
  "type": "Feature",
  "properties": {
    "tgn:hierarchy":[
        "tgn:7558821",
        "tgn:1000004",
        "tgn:7000198",
        "tgn:7000799",
        "tgn:7029392"
    ],
    "tgn:id":7558821,
    "tgn:name:en":"Rezan",
    "tgn:placetype":[
        "aat:300008347"
    ]
},
  "bbox": [],
  "geometry": {"coordinates":[75.185364,34.274249],"type":"Point"}
}