<<<<<<< HEAD
{
  "id": 7353692,
  "type": "Feature",
  "properties": {
    "tgn:hierarchy":[
        "tgn:7353692",
        "tgn:1000001",
        "tgn:7005597",
        "tgn:7005560",
        "tgn:7029392"
    ],
    "tgn:id":7353692,
    "tgn:name":"\u00c1nimas, Arroyo de las",
    "tgn:placetype":[
        "aat:300008699"
    ]
},
  "bbox": [],
  "geometry": {"coordinates":[-98.533333,22.583333],"type":"Point"}
}
=======
{"geometry":{"type":"Point","coordinates":[-98.533333,22.583333]},"type":"Feature","properties":{"hierarchy":["tgn:7353692","tgn:1000001","tgn:7005597","tgn:7005560","tgn:7029392"],"placetype":["aat:300008699"],"id":7353692,"name:xx":"\u00c1nimas, Arroyo de las"}}
>>>>>>> 03f74aca74312dbeaf24d7e61306dd6a786dc3d0
