{
  "id": 1091821,
  "type": "Feature",
  "properties": {
    "tgn:hierarchy":[
        "tgn:1091821",
        "tgn:7001242",
        "tgn:7032820",
        "tgn:1000181",
        "tgn:7029392"
    ],
    "tgn:id":1091821,
    "tgn:name":"Yatakala",
    "tgn:placetype":[
        "aat:300008347"
    ]
},
  "bbox": [],
  "geometry": {"coordinates":[0.3667,14.8667],"type":"Point"}
}