{
  "id": 7287122,
  "type": "Feature",
  "properties": {
    "tgn:hierarchy":[
        "tgn:7287122",
        "tgn:1001702",
        "tgn:1000049",
        "tgn:1000002",
        "tgn:7029392"
    ],
    "tgn:id":7287122,
    "tgn:name":"Gemelos, Islotes",
    "tgn:placetype":[
        "aat:300008791"
    ]
},
  "bbox": [],
  "geometry": {"coordinates":[-75.483889,-50.460278],"type":"Point"}
}