{
  "id": 7575537,
  "type": "Feature",
  "properties": {
    "tgn:hierarchy":[
        "tgn:7575537",
        "tgn:1000004",
        "tgn:7000198",
        "tgn:7016694",
        "tgn:7029392"
    ],
    "tgn:id":7575537,
    "tgn:name:en":"Kesaib\u0101h\u0101l",
    "tgn:placetype":[
        "aat:300008347"
    ]
},
  "bbox": [],
  "geometry": {"coordinates":[84.388296,21.914038],"type":"Point"}
}