<<<<<<< HEAD
{
  "id": 2401970,
  "type": "Feature",
  "properties": {
    "tgn:hierarchy":[
        "tgn:2401970",
        "tgn:1000001",
        "tgn:2001737",
        "tgn:7012149",
        "tgn:7007712",
        "tgn:7029392"
    ],
    "tgn:id":2401970,
    "tgn:name":"Horseshoe Mountain",
    "tgn:placetype":[
        "aat:300008798"
    ]
},
  "bbox": [],
  "geometry": {"coordinates":[-80.1167,34.5833],"type":"Point"}
}
=======
{"geometry":{"type":"Point","coordinates":[-80.116700,34.583300]},"type":"Feature","properties":{"hierarchy":["tgn:2401970","tgn:1000001","tgn:2001737","tgn:7012149","tgn:7007712","tgn:7029392"],"placetype":["aat:300008798"],"id":2401970,"name:xx":"Horseshoe Mountain"}}
>>>>>>> 03f74aca74312dbeaf24d7e61306dd6a786dc3d0
