{
  "id": 2390476,
  "type": "Feature",
  "properties": {
    "tgn:hierarchy":[
        "tgn:2390476",
        "tgn:1000001",
        "tgn:7012149",
        "tgn:1002669",
        "tgn:7007710",
        "tgn:7029392"
    ],
    "tgn:id":2390476,
    "tgn:name":"Highland Park Cave",
    "tgn:placetype":[
        "aat:300008746"
    ]
},
  "bbox": [],
  "geometry": {"coordinates":[-77.5667,40.6167],"type":"Point"}
}