{
  "id": 2575741,
  "type": "Feature",
  "properties": {
    "tgn:hierarchy":[
        "tgn:2575741",
        "tgn:1000001",
        "tgn:7012149",
        "tgn:2001042",
        "tgn:7007521",
        "tgn:7029392"
    ],
    "tgn:id":2575741,
    "tgn:name":"Perch Lake",
    "tgn:placetype":[
        "aat:300008680"
    ]
},
  "bbox": [],
  "geometry": {"coordinates":[-95.7667,47.3167],"type":"Point"}
}