{
  "id": 7564962,
  "type": "Feature",
  "properties": {
    "tgn:hierarchy":[
        "tgn:7564962",
        "tgn:1000004",
        "tgn:7000198",
        "tgn:7000799",
        "tgn:7029392"
    ],
    "tgn:id":7564962,
    "tgn:name:en":"Kadw\u0101l",
    "tgn:placetype":[
        "aat:300008347"
    ]
},
  "bbox": [],
  "geometry": {"coordinates":[74.801964,32.4964],"type":"Point"}
}