{
  "id": 7234492,
  "type": "Feature",
  "properties": {
    "tgn:hierarchy":[
        "tgn:7234492",
        "tgn:7011170",
        "tgn:7002715",
        "tgn:1000003",
        "tgn:1000074",
        "tgn:7029392"
    ],
    "tgn:id":7234492,
    "tgn:name":"Dad\u00eda",
    "tgn:placetype":[
        "aat:300008347"
    ]
},
  "bbox": [],
  "geometry": {"coordinates":[26.226667,41.130278],"type":"Point"}
}