{
  "id": 2567582,
  "type": "Feature",
  "properties": {
    "tgn:hierarchy":[
        "tgn:2567582",
        "tgn:1002215",
        "tgn:1000001",
        "tgn:7012149",
        "tgn:7007565",
        "tgn:7029392"
    ],
    "tgn:id":2567582,
    "tgn:name":"Papoose Lake",
    "tgn:placetype":[
        "aat:300006191"
    ]
},
  "bbox": [],
  "geometry": {"coordinates":[-74.7833,39.85],"type":"Point"}
}