{
  "id": 2369172,
  "type": "Feature",
  "properties": {
    "tgn:hierarchy":[
        "tgn:2369172",
        "tgn:1000001",
        "tgn:7016172",
        "tgn:7012149",
        "tgn:2000150",
        "tgn:7029392"
    ],
    "tgn:id":2369172,
    "tgn:name":"Gum Ridge",
    "tgn:placetype":[
        "aat:300266640"
    ]
},
  "bbox": [],
  "geometry": {"coordinates":[-94.0333,33.2667],"type":"Point"}
}