{
  "id": 7360567,
  "type": "Feature",
  "properties": {
    "tgn:hierarchy":[
        "tgn:7360567",
        "tgn:7005581",
        "tgn:1000001",
        "tgn:7005560",
        "tgn:7029392"
    ],
    "tgn:id":7360567,
    "tgn:name":"Cueva, Picacho de la",
    "tgn:placetype":[
        "aat:300008795"
    ]
},
  "bbox": [],
  "geometry": {"coordinates":[-106.583333,29.766667],"type":"Point"}
}