{
  "id": 2470036,
  "type": "Feature",
  "properties": {
    "tgn:hierarchy":[
        "tgn:2470036",
        "tgn:7006450",
        "tgn:1000001",
        "tgn:7012149",
        "tgn:2000086",
        "tgn:7029392"
    ],
    "tgn:id":2470036,
    "tgn:name":"Loon Rock",
    "tgn:placetype":[
        "aat:300132348"
    ]
},
  "bbox": [],
  "geometry": {"coordinates":[-146.3333,60.4833],"type":"Point"}
}