{
  "id": 1044584,
  "type": "Feature",
  "properties": {
    "tgn:hierarchy":[
        "tgn:1044584",
        "tgn:1003474",
        "tgn:7004610",
        "tgn:1000003",
        "tgn:1000080",
        "tgn:7029392"
    ],
    "tgn:id":1044584,
    "tgn:name":"Ferrandina",
    "tgn:placetype":[
        "aat:300008347"
    ]
},
  "bbox": [],
  "geometry": {"coordinates":[16.45,40.483333],"type":"Point"}
}