{
  "id": 7522454,
  "type": "Feature",
  "properties": {
    "tgn:hierarchy":[
        "tgn:7522454",
        "tgn:7001242",
        "tgn:7016833",
        "tgn:7000122",
        "tgn:7029392"
    ],
    "tgn:id":7522454,
    "tgn:name:en":"Ar Ragh\u0101mah",
    "tgn:placetype":[
        "aat:300008347"
    ]
},
  "bbox": [],
  "geometry": {"coordinates":[32.913928,24.549987],"type":"Point"}
}