{
  "id": 2557033,
  "type": "Feature",
  "properties": {
    "tgn:hierarchy":[
        "tgn:2557033",
        "tgn:1000001",
        "tgn:2002261",
        "tgn:7012149",
        "tgn:7013961",
        "tgn:7029392"
    ],
    "tgn:id":2557033,
    "tgn:name":"Old Gauley",
    "tgn:placetype":[
        "aat:300008347"
    ]
},
  "bbox": [],
  "geometry": {"coordinates":[-81.1833,38.15],"type":"Point"}
}