{
  "id": 1013114,
  "type": "Feature",
  "properties": {
    "tgn:hierarchy":[
        "tgn:1013114",
        "tgn:7005694",
        "tgn:7005685",
        "tgn:1000001",
        "tgn:7029392"
    ],
    "tgn:id":1013114,
    "tgn:name":"Clyde",
    "tgn:placetype":[
        "aat:300008347"
    ]
},
  "bbox": [],
  "geometry": {"coordinates":[-113.65,54.1667],"type":"Point"}
}