{
  "id": 1043057,
  "type": "Feature",
  "properties": {
    "tgn:hierarchy":[
        "tgn:1043057",
        "tgn:7001199",
        "tgn:7003495",
        "tgn:1000003",
        "tgn:1000078",
        "tgn:7029392"
    ],
    "tgn:id":1043057,
    "tgn:name":"Wicklow",
    "tgn:placetype":[
        "aat:300008347"
    ]
},
  "bbox": [],
  "geometry": {"coordinates":[-6.05,52.9833],"type":"Point"}
}