{
  "id": 7412828,
  "type": "Feature",
  "properties": {
    "tgn:hierarchy":[
        "tgn:7412828",
        "tgn:7005580",
        "tgn:1000001",
        "tgn:7005560",
        "tgn:7029392"
    ],
    "tgn:id":7412828,
    "tgn:name":"San Vicente La Piedra",
    "tgn:placetype":[
        "aat:300008347"
    ]
},
  "bbox": [],
  "geometry": {"coordinates":[-92.383333,16.55],"type":"Point"}
}