{
  "id": 7083614,
  "type": "Feature",
  "properties": {
    "tgn:hierarchy":[
        "tgn:7083614",
        "tgn:1000003",
        "tgn:7003676",
        "tgn:7000084",
        "tgn:7029392"
    ],
    "tgn:id":7083614,
    "tgn:name":"Wiedigshof",
    "tgn:placetype":[
        "aat:300008347"
    ]
},
  "bbox": [],
  "geometry": {"coordinates":[10.633333,51.566667],"type":"Point"}
}