{
  "id": 7156906,
  "type": "Feature",
  "properties": {
    "tgn:hierarchy":[
        "tgn:7156906",
        "tgn:7003669",
        "tgn:1000003",
        "tgn:7000084",
        "tgn:7029392"
    ],
    "tgn:id":7156906,
    "tgn:name":"Keilender Stein",
    "tgn:placetype":[
        "aat:300011692"
    ]
},
  "bbox": [],
  "geometry": {"coordinates":[11.766667,50.366667],"type":"Point"}
}