{
  "id": 1046690,
  "type": "Feature",
  "properties": {
    "tgn:hierarchy":[
        "tgn:1046690",
        "tgn:7007850",
        "tgn:1003491",
        "tgn:1000003",
        "tgn:1000080",
        "tgn:7029392"
    ],
    "tgn:id":1046690,
    "tgn:name":"Sant'Eufemia d'Aspromonte",
    "tgn:placetype":[
        "aat:300008347"
    ]
},
  "bbox": [],
  "geometry": {"coordinates":[15.866667,38.266667],"type":"Point"}
}