{
  "id": 7438997,
  "type": "Feature",
  "properties": {
    "tgn:hierarchy":[
        "tgn:7438997",
        "tgn:1000001",
        "tgn:1001960",
        "tgn:7005560",
        "tgn:7029392"
    ],
    "tgn:id":7438997,
    "tgn:name":"Sapomora",
    "tgn:placetype":[
        "aat:300008347"
    ]
},
  "bbox": [],
  "geometry": {"coordinates":[-109.483333,27.033333],"type":"Point"}
}