{
  "id": 2138272,
  "type": "Feature",
  "properties": {
    "tgn:hierarchy":[
        "tgn:2138272",
        "tgn:1000001",
        "tgn:1002359",
        "tgn:7012149",
        "tgn:7007517",
        "tgn:7029392"
    ],
    "tgn:id":2138272,
    "tgn:name":"Artichoke River",
    "tgn:placetype":[
        "aat:300008707"
    ]
},
  "bbox": [],
  "geometry": {"coordinates":[-70.95,42.7833],"type":"Point"}
}