{
  "id": 1019046,
  "type": "Feature",
  "properties": {
    "tgn:hierarchy":[
        "tgn:1019046",
        "tgn:7017440",
        "tgn:1000001",
        "tgn:7004643",
        "tgn:7029392"
    ],
    "tgn:id":1019046,
    "tgn:name":"Vertedero",
    "tgn:placetype":[
        "aat:300008347"
    ]
},
  "bbox": [],
  "geometry": {"coordinates":[-66.25,18.0833],"type":"Point"}
}