{
  "id": 1082244,
  "type": "Feature",
  "properties": {
    "tgn:hierarchy":[
        "tgn:1082244",
        "tgn:1000004",
        "tgn:1001370",
        "tgn:7000299",
        "tgn:7029392"
    ],
    "tgn:id":1082244,
    "tgn:name":"Ilsan-ni",
    "tgn:placetype":[
        "aat:300008347"
    ]
},
  "bbox": [],
  "geometry": {"coordinates":[126.75,37.6833],"type":"Point"}
}