{
  "id": 1070136,
  "type": "Feature",
  "properties": {
    "tgn:hierarchy":[
        "tgn:1070136",
        "tgn:1000004",
        "tgn:7002077",
        "tgn:1000111",
        "tgn:7029392"
    ],
    "tgn:id":1070136,
    "tgn:name":"Luanxian",
    "tgn:placetype":[
        "aat:300008347"
    ]
},
  "bbox": [],
  "geometry": {"coordinates":[118.7667,39.7667],"type":"Point"}
}