{
  "id": 6005221,
  "type": "Feature",
  "properties": {
    "tgn:hierarchy":[
        "tgn:6005221",
        "tgn:1000001",
        "tgn:7005591",
        "tgn:7005560",
        "tgn:7029392"
    ],
    "tgn:id":6005221,
    "tgn:name":"San Jos\u00e9 Mogote",
    "tgn:placetype":[
        "aat:300008347",
        "aat:300000810",
        "aat:300167671",
        "aat:300008389",
        "aat:300000833"
    ]
},
  "bbox": [],
  "geometry": {"coordinates":[-96.803,17.167],"type":"Point"}
}