{
  "id": 7001472,
  "type": "Feature",
  "properties": {
    "tgn:hierarchy":[
        "tgn:7001472",
        "tgn:1000004",
        "tgn:7002372",
        "tgn:1000111",
        "tgn:7029392"
    ],
    "tgn:id":7001472,
    "tgn:name":"Changchun",
    "tgn:placetype":[
        "aat:300008347",
        "aat:300387218",
        "aat:300008389",
        "aat:300264742",
        "aat:300387223",
        "aat:300265612",
        "aat:300008372"
    ]
},
  "bbox": [],
  "geometry": {"coordinates":[125.3333,43.8333],"type":"Point"}
}