{
  "id": 7514100,
  "type": "Feature",
  "properties": {
    "tgn:hierarchy":[
        "tgn:7514100",
        "tgn:1009227",
        "tgn:1000226",
        "tgn:7016822",
        "tgn:1000006",
        "tgn:7029392"
    ],
    "tgn:id":7514100,
    "tgn:name:en":"Emelius Arm",
    "tgn:placetype":[
        "aat:300132316"
    ]
},
  "bbox": [],
  "geometry": {"coordinates":[167.133333,-45.083333],"type":"Point"}
}