<<<<<<< HEAD
{
  "id": 2157770,
  "type": "Feature",
  "properties": {
    "tgn:hierarchy":[
        "tgn:2157770",
        "tgn:1000001",
        "tgn:2000583",
        "tgn:7012149",
        "tgn:7007253",
        "tgn:7029392"
    ],
    "tgn:id":2157770,
    "tgn:name":"Beaver Island",
    "tgn:placetype":[
        "aat:300008791"
    ]
},
  "bbox": [],
  "geometry": {"coordinates":[-90.2,41.8],"type":"Point"}
}
=======
{"geometry":{"type":"Point","coordinates":[-90.200000,41.800000]},"type":"Feature","properties":{"hierarchy":["tgn:2157770","tgn:1000001","tgn:2000583","tgn:7012149","tgn:7007253","tgn:7029392"],"placetype":["aat:300008791"],"id":2157770,"name:xx":"Beaver Island"}}
>>>>>>> 03f74aca74312dbeaf24d7e61306dd6a786dc3d0
