{
  "id": 2236858,
  "type": "Feature",
  "properties": {
    "tgn:hierarchy":[
        "tgn:2236858",
        "tgn:1000001",
        "tgn:1002340",
        "tgn:7012149",
        "tgn:7007526",
        "tgn:7029392"
    ],
    "tgn:id":2236858,
    "tgn:name":"Childs Canyon",
    "tgn:placetype":[
        "aat:300008761"
    ]
},
  "bbox": [],
  "geometry": {"coordinates":[-119.85,39.0333],"type":"Point"}
}