{
  "id": 2459304,
  "type": "Feature",
  "properties": {
    "tgn:hierarchy":[
        "tgn:2459304",
        "tgn:1002366",
        "tgn:1000001",
        "tgn:7012149",
        "tgn:7007159",
        "tgn:7029392"
    ],
    "tgn:id":2459304,
    "tgn:name":"Little Pond",
    "tgn:placetype":[
        "aat:300008680"
    ]
},
  "bbox": [],
  "geometry": {"coordinates":[-73.4667,41.3167],"type":"Point"}
}