<<<<<<< HEAD
{
  "id": 7475348,
  "type": "Feature",
  "properties": {
    "tgn:hierarchy":[
        "tgn:7475348",
        "tgn:1000004",
        "tgn:7001014",
        "tgn:1000141",
        "tgn:7029392"
    ],
    "tgn:id":7475348,
    "tgn:name":"Dongnan Guozhong",
    "tgn:placetype":[
        "aat:300006495"
    ]
},
  "bbox": [],
  "geometry": {"coordinates":[120.451676,23.804198],"type":"Point"}
}
=======
{"geometry":{"type":"Point","coordinates":[120.451676,23.804198]},"type":"Feature","properties":{"hierarchy":["tgn:7475348","tgn:1000004","tgn:7001014","tgn:1000141","tgn:7029392"],"placetype":["aat:300006495"],"id":7475348,"name:xx":"Dongnan Guozhong"}}
>>>>>>> 03f74aca74312dbeaf24d7e61306dd6a786dc3d0
