{
  "id": 7475348,
  "type": "Feature",
  "properties": {
    "tgn:hierarchy":[
        "tgn:7475348",
        "tgn:1000004",
        "tgn:7001014",
        "tgn:1000141",
        "tgn:7029392"
    ],
    "tgn:id":7475348,
    "tgn:name":"Dongnan Guozhong",
    "tgn:placetype":[
        "aat:300006495"
    ]
},
  "bbox": [],
  "geometry": {"coordinates":[120.451676,23.804198],"type":"Point"}
}