<<<<<<< HEAD
{
  "id": 2768394,
  "type": "Feature",
  "properties": {
    "tgn:hierarchy":[
        "tgn:2768394",
        "tgn:1000001",
        "tgn:7012149",
        "tgn:2002166",
        "tgn:7007919",
        "tgn:7029392"
    ],
    "tgn:id":2768394,
    "tgn:name":"Whitesville",
    "tgn:placetype":[
        "aat:300008347"
    ]
},
  "bbox": [],
  "geometry": {"coordinates":[-78.8833,36.9],"type":"Point"}
}
=======
{"geometry":{"type":"Point","coordinates":[-78.883300,36.900000]},"type":"Feature","properties":{"hierarchy":["tgn:2768394","tgn:1000001","tgn:7012149","tgn:2002166","tgn:7007919","tgn:7029392"],"placetype":["aat:300008347"],"id":2768394,"name:xx":"Whitesville"}}
>>>>>>> 03f74aca74312dbeaf24d7e61306dd6a786dc3d0
