{
  "id": 7511584,
  "type": "Feature",
  "properties": {
    "tgn:hierarchy":[
        "tgn:7511584",
        "tgn:1009227",
        "tgn:1000226",
        "tgn:7520095",
        "tgn:1000006",
        "tgn:7029392"
    ],
    "tgn:id":7511584,
    "tgn:name:en":"Louis",
    "tgn:placetype":[
        "aat:300008795"
    ]
},
  "bbox": [],
  "geometry": {"coordinates":[172.65,-41.816667],"type":"Point"}
}