{
  "id": 7418103,
  "type": "Feature",
  "properties": {
    "tgn:hierarchy":[
        "tgn:7418103",
        "tgn:1001836",
        "tgn:1000001",
        "tgn:7005560",
        "tgn:7029392"
    ],
    "tgn:id":7418103,
    "tgn:name":"Los Becerros",
    "tgn:placetype":[
        "aat:300008347"
    ]
},
  "bbox": [],
  "geometry": {"coordinates":[-111.968611,26.234167],"type":"Point"}
}