{
  "id": 7407921,
  "type": "Feature",
  "properties": {
    "tgn:hierarchy":[
        "tgn:7407921",
        "tgn:1000001",
        "tgn:1001893",
        "tgn:7005560",
        "tgn:7029392"
    ],
    "tgn:id":7407921,
    "tgn:name":"El Rinc\u00f3n de Cristo",
    "tgn:placetype":[
        "aat:300008347"
    ]
},
  "bbox": [],
  "geometry": {"coordinates":[-100.091667,18.758333],"type":"Point"}
}