{
  "id": 7231966,
  "type": "Feature",
  "properties": {
    "tgn:hierarchy":[
        "tgn:7231966",
        "tgn:7011164",
        "tgn:7002674",
        "tgn:1000003",
        "tgn:1000074",
        "tgn:7029392"
    ],
    "tgn:id":7231966,
    "tgn:name":"Kouma\u00ed\u00efka",
    "tgn:placetype":[
        "aat:300008347"
    ]
},
  "bbox": [],
  "geometry": {"coordinates":[26.749722,37.709722],"type":"Point"}
}