{
  "id": 2020242,
  "type": "Feature",
  "properties": {
    "tgn:hierarchy":[
        "tgn:2020242",
        "tgn:1000001",
        "tgn:7012149",
        "tgn:1002631",
        "tgn:7007240",
        "tgn:7029392"
    ],
    "tgn:id":2020242,
    "tgn:name":"McIntosh",
    "tgn:placetype":[
        "aat:300008347"
    ]
},
  "bbox": [],
  "geometry": {"coordinates":[-82.2167,29.4333],"type":"Point"}
}