{
  "id": 7429876,
  "type": "Feature",
  "properties": {
    "tgn:hierarchy":[
        "tgn:7429876",
        "tgn:7005583",
        "tgn:1000001",
        "tgn:7005560",
        "tgn:7029392"
    ],
    "tgn:id":7429876,
    "tgn:name":"Colonia El Refugio",
    "tgn:placetype":[
        "aat:300008347"
    ]
},
  "bbox": [],
  "geometry": {"coordinates":[-104.05,24.783333],"type":"Point"}
}