{
  "id": 2710565,
  "type": "Feature",
  "properties": {
    "tgn:hierarchy":[
        "tgn:2710565",
        "tgn:1000001",
        "tgn:7012149",
        "tgn:7007708",
        "tgn:7029392"
    ],
    "tgn:id":2710565,
    "tgn:name":"Tamarack Spring",
    "tgn:placetype":[
        "aat:300008697"
    ]
},
  "bbox": [],
  "geometry": {"coordinates":[-118.3833,44.0333],"type":"Point"}
}