{
  "id": 7547503,
  "type": "Feature",
  "properties": {
    "tgn:hierarchy":[
        "tgn:7547503",
        "tgn:1000004",
        "tgn:7000198",
        "tgn:1001894",
        "tgn:7029392"
    ],
    "tgn:id":7547503,
    "tgn:name:en":"Asirgarh",
    "tgn:placetype":[
        "aat:300008347"
    ]
},
  "bbox": [],
  "geometry": {"coordinates":[76.293723,21.470875],"type":"Point"}
}