<<<<<<< HEAD
{
  "id": 7370909,
  "type": "Feature",
  "properties": {
    "tgn:hierarchy":[
        "tgn:7370909",
        "tgn:7005578",
        "tgn:1000001",
        "tgn:7005560",
        "tgn:7029392"
    ],
    "tgn:id":7370909,
    "tgn:name":"Jes\u00fas Mar\u00eda",
    "tgn:placetype":[
        "aat:300008347"
    ]
},
  "bbox": [],
  "geometry": {"coordinates":[-90.516667,19.783333],"type":"Point"}
}
=======
{"geometry":{"type":"Point","coordinates":[-90.516667,19.783333]},"type":"Feature","properties":{"hierarchy":["tgn:7370909","tgn:7005578","tgn:1000001","tgn:7005560","tgn:7029392"],"placetype":["aat:300008347"],"id":7370909,"name:xx":"Jes\u00fas Mar\u00eda"}}
>>>>>>> 03f74aca74312dbeaf24d7e61306dd6a786dc3d0
