{
  "id": 7153395,
  "type": "Feature",
  "properties": {
    "tgn:hierarchy":[
        "tgn:7153395",
        "tgn:1000003",
        "tgn:7003678",
        "tgn:7000084",
        "tgn:7029392"
    ],
    "tgn:id":7153395,
    "tgn:name":"Karlsh\u00f6he",
    "tgn:placetype":[
        "aat:300008777"
    ]
},
  "bbox": [],
  "geometry": {"coordinates":[8.666667,49.766667],"type":"Point"}
}