{
  "id": 1043086,
  "type": "Feature",
  "properties": {
    "tgn:hierarchy":[
        "tgn:1043086",
        "tgn:7009084",
        "tgn:7004154",
        "tgn:1000003",
        "tgn:1000080",
        "tgn:7029392"
    ],
    "tgn:id":1043086,
    "tgn:name":"Acciano",
    "tgn:placetype":[
        "aat:300008347"
    ]
},
  "bbox": [],
  "geometry": {"coordinates":[13.716667,42.166667],"type":"Point"}
}