{
  "id": 2690654,
  "type": "Feature",
  "properties": {
    "tgn:hierarchy":[
        "tgn:2690654",
        "tgn:1000001",
        "tgn:7012149",
        "tgn:1002750",
        "tgn:7007252",
        "tgn:7029392"
    ],
    "tgn:id":2690654,
    "tgn:name":"Stampers Creek Sinks",
    "tgn:placetype":[
        "aat:300386845"
    ]
},
  "bbox": [],
  "geometry": {"coordinates":[-86.3833,38.5833],"type":"Point"}
}