{
  "id": 2642116,
  "type": "Feature",
  "properties": {
    "tgn:hierarchy":[
        "tgn:2642116",
        "tgn:1000001",
        "tgn:2000262",
        "tgn:7012149",
        "tgn:7007240",
        "tgn:7029392"
    ],
    "tgn:id":2642116,
    "tgn:name":"Sand Pond",
    "tgn:placetype":[
        "aat:300006191"
    ]
},
  "bbox": [],
  "geometry": {"coordinates":[-82.7667,30.1833],"type":"Point"}
}