{
  "id": 7547802,
  "type": "Feature",
  "properties": {
    "tgn:hierarchy":[
        "tgn:7547802",
        "tgn:1000004",
        "tgn:7000198",
        "tgn:1001882",
        "tgn:7029392"
    ],
    "tgn:id":7547802,
    "tgn:name:en":"Bhair\u0101pur",
    "tgn:placetype":[
        "aat:300008347"
    ]
},
  "bbox": [],
  "geometry": {"coordinates":[76.583333,16.416667],"type":"Point"}
}