{
  "id": 2622305,
  "type": "Feature",
  "properties": {
    "tgn:hierarchy":[
        "tgn:2622305",
        "tgn:1000001",
        "tgn:2000265",
        "tgn:7012149",
        "tgn:7007240",
        "tgn:7029392"
    ],
    "tgn:id":2622305,
    "tgn:name":"Robertson Island",
    "tgn:placetype":[
        "aat:300008791"
    ]
},
  "bbox": [],
  "geometry": {"coordinates":[-87.3167,30.3167],"type":"Point"}
}