{
  "id": 2733738,
  "type": "Feature",
  "properties": {
    "tgn:hierarchy":[
        "tgn:2733738",
        "tgn:1000001",
        "tgn:7012149",
        "tgn:7019014",
        "tgn:7007251",
        "tgn:7029392"
    ],
    "tgn:id":2733738,
    "tgn:name":"Turner Camp",
    "tgn:placetype":[
        "aat:300008347"
    ]
},
  "bbox": [],
  "geometry": {"coordinates":[-88.25,42.1833],"type":"Point"}
}