{
  "id": 1006646,
  "type": "Feature",
  "properties": {
    "tgn:hierarchy":[
        "tgn:1006646",
        "tgn:7002445",
        "tgn:1000003",
        "tgn:7008153",
        "tgn:7008591",
        "tgn:7029392"
    ],
    "tgn:id":1006646,
    "tgn:name":"Burntwick Island",
    "tgn:placetype":[
        "aat:300008791"
    ]
},
  "bbox": [],
  "geometry": {"coordinates":[0.6833,51.4167],"type":"Point"}
}