<<<<<<< HEAD
{
  "id": 2154131,
  "type": "Feature",
  "properties": {
    "tgn:hierarchy":[
        "tgn:2154131",
        "tgn:1000001",
        "tgn:7012149",
        "tgn:2000650",
        "tgn:7007253",
        "tgn:7029392"
    ],
    "tgn:id":2154131,
    "tgn:name":"Bear Creek",
    "tgn:placetype":[
        "aat:300008706"
    ]
},
  "bbox": [],
  "geometry": {"coordinates":[-92.6333,40.9667],"type":"Point"}
}
=======
{"geometry":{"type":"Point","coordinates":[-92.633300,40.966700]},"type":"Feature","properties":{"hierarchy":["tgn:2154131","tgn:1000001","tgn:7012149","tgn:2000650","tgn:7007253","tgn:7029392"],"placetype":["aat:300008706"],"id":2154131,"name:xx":"Bear Creek"}}
>>>>>>> 03f74aca74312dbeaf24d7e61306dd6a786dc3d0
