{
  "id": 1019354,
  "type": "Feature",
  "properties": {
    "tgn:hierarchy":[
        "tgn:1019354",
        "tgn:1001160",
        "tgn:7006477",
        "tgn:1000002",
        "tgn:7029392"
    ],
    "tgn:id":1019354,
    "tgn:name":"Coronel Dorrego",
    "tgn:placetype":[
        "aat:300008347"
    ]
},
  "bbox": [],
  "geometry": {"coordinates":[-61.2667,-38.7333],"type":"Point"}
}