{
  "id": 7334948,
  "type": "Feature",
  "properties": {
    "tgn:hierarchy":[
        "tgn:7334948",
        "tgn:7002759",
        "tgn:7008909",
        "tgn:1000003",
        "tgn:1000095",
        "tgn:7029392"
    ],
    "tgn:id":7334948,
    "tgn:name":"Fuendecampo",
    "tgn:placetype":[
        "aat:300008347"
    ]
},
  "bbox": [],
  "geometry": {"coordinates":[0.26573,42.412522],"type":"Point"}
}