{
  "id": 7318310,
  "type": "Feature",
  "properties": {
    "tgn:hierarchy":[
        "tgn:7318310",
        "tgn:1001708",
        "tgn:1000049",
        "tgn:1000002",
        "tgn:7029392"
    ],
    "tgn:id":7318310,
    "tgn:name":"Corneche, Cerrillo",
    "tgn:placetype":[
        "aat:300008777"
    ]
},
  "bbox": [],
  "geometry": {"coordinates":[-71.716667,-33.95],"type":"Point"}
}