{
  "id": 1074546,
  "type": "Feature",
  "properties": {
    "tgn:hierarchy":[
        "tgn:1074546",
        "tgn:1000004",
        "tgn:7000198",
        "tgn:1001895",
        "tgn:7029392"
    ],
    "tgn:id":1074546,
    "tgn:name":"Baramati",
    "tgn:placetype":[
        "aat:300008347"
    ]
},
  "bbox": [],
  "geometry": {"coordinates":[74.583333,18.15],"type":"Point"}
}