{
  "id": 7441860,
  "type": "Feature",
  "properties": {
    "tgn:hierarchy":[
        "tgn:7441860",
        "tgn:7002444",
        "tgn:7008074",
        "tgn:1000003",
        "tgn:7008591",
        "tgn:7029392"
    ],
    "tgn:id":7441860,
    "tgn:name:en":"Waterbeck",
    "tgn:placetype":[
        "aat:300008347"
    ]
},
  "bbox": [],
  "geometry": {"coordinates":[-3.183333,55.083333],"type":"Point"}
}