<<<<<<< HEAD
{
  "id": 7351137,
  "type": "Feature",
  "properties": {
    "tgn:hierarchy":[
        "tgn:7351137",
        "tgn:1000001",
        "tgn:7005599",
        "tgn:7005560",
        "tgn:7029392"
    ],
    "tgn:id":7351137,
    "tgn:name":"Bajo Grande",
    "tgn:placetype":[
        "aat:300008347"
    ]
},
  "bbox": [],
  "geometry": {"coordinates":[-95.266667,17.733333],"type":"Point"}
}
=======
{"geometry":{"type":"Point","coordinates":[-95.266667,17.733333]},"type":"Feature","properties":{"hierarchy":["tgn:7351137","tgn:1000001","tgn:7005599","tgn:7005560","tgn:7029392"],"placetype":["aat:300008347"],"id":7351137,"name:xx":"Bajo Grande"}}
>>>>>>> 03f74aca74312dbeaf24d7e61306dd6a786dc3d0
