{
  "id": 2773577,
  "type": "Feature",
  "properties": {
    "tgn:hierarchy":[
        "tgn:2773577",
        "tgn:1002234",
        "tgn:1000001",
        "tgn:7012149",
        "tgn:7007516",
        "tgn:7029392"
    ],
    "tgn:id":2773577,
    "tgn:name":"Williston Lake",
    "tgn:placetype":[
        "aat:300008680"
    ]
},
  "bbox": [],
  "geometry": {"coordinates":[-75.8333,38.8167],"type":"Point"}
}