{
  "id": 2704926,
  "type": "Feature",
  "properties": {
    "tgn:hierarchy":[
        "tgn:2704926",
        "tgn:1000001",
        "tgn:7012149",
        "tgn:2001304",
        "tgn:7007524",
        "tgn:7029392"
    ],
    "tgn:id":2704926,
    "tgn:name":"Sunset Peak",
    "tgn:placetype":[
        "aat:300008798"
    ]
},
  "bbox": [],
  "geometry": {"coordinates":[-115.0667,47.4833],"type":"Point"}
}