{
  "id": 7489712,
  "type": "Feature",
  "properties": {
    "tgn:hierarchy":[
        "tgn:7489712",
        "tgn:1000004",
        "tgn:7471332",
        "tgn:1000141",
        "tgn:7029392"
    ],
    "tgn:id":7489712,
    "tgn:name":"Boluowen",
    "tgn:placetype":[
        "aat:300008347"
    ]
},
  "bbox": [],
  "geometry": {"coordinates":[121.02,24.891667],"type":"Point"}
}