<<<<<<< HEAD
{
  "id": 7489712,
  "type": "Feature",
  "properties": {
    "tgn:hierarchy":[
        "tgn:7489712",
        "tgn:1000004",
        "tgn:7471332",
        "tgn:1000141",
        "tgn:7029392"
    ],
    "tgn:id":7489712,
    "tgn:name":"Boluowen",
    "tgn:placetype":[
        "aat:300008347"
    ]
},
  "bbox": [],
  "geometry": {"coordinates":[121.02,24.891667],"type":"Point"}
}
=======
{"geometry":{"type":"Point","coordinates":[121.020000,24.891667]},"type":"Feature","properties":{"hierarchy":["tgn:7489712","tgn:1000004","tgn:7471332","tgn:1000141","tgn:7029392"],"placetype":["aat:300008347"],"id":7489712,"name:xx":"Boluowen"}}
>>>>>>> 03f74aca74312dbeaf24d7e61306dd6a786dc3d0
