{
  "id": 7582738,
  "type": "Feature",
  "properties": {
    "tgn:hierarchy":[
        "tgn:7582738",
        "tgn:1000004",
        "tgn:1001871",
        "tgn:7000198",
        "tgn:7029392"
    ],
    "tgn:id":7582738,
    "tgn:name:en":"Landhi",
    "tgn:placetype":[
        "aat:300008347"
    ]
},
  "bbox": [],
  "geometry": {"coordinates":[76.873032,30.213737],"type":"Point"}
}