{
  "id": 2507560,
  "type": "Feature",
  "properties": {
    "tgn:hierarchy":[
        "tgn:2507560",
        "tgn:1000001",
        "tgn:7012149",
        "tgn:1002943",
        "tgn:7007708",
        "tgn:7029392"
    ],
    "tgn:id":2507560,
    "tgn:name":"Miami Cove",
    "tgn:placetype":[
        "aat:300132316"
    ]
},
  "bbox": [],
  "geometry": {"coordinates":[-123.8833,45.55],"type":"Point"}
}