{
  "id": 2117215,
  "type": "Feature",
  "properties": {
    "tgn:hierarchy":[
        "tgn:2117215",
        "tgn:1000001",
        "tgn:2002254",
        "tgn:7012149",
        "tgn:7013961",
        "tgn:7029392"
    ],
    "tgn:id":2117215,
    "tgn:name":"Allensville",
    "tgn:placetype":[
        "aat:300008347",
        "aat:300387210"
    ]
},
  "bbox": [],
  "geometry": {"coordinates":[-77.9833,39.5667],"type":"Point"}
}