{
  "id": 2430871,
  "type": "Feature",
  "properties": {
    "tgn:hierarchy":[
        "tgn:2430871",
        "tgn:1000001",
        "tgn:7006451",
        "tgn:2000092",
        "tgn:7012149",
        "tgn:7029392"
    ],
    "tgn:id":2430871,
    "tgn:name":"Kanaa Wash",
    "tgn:placetype":[
        "aat:300008701"
    ]
},
  "bbox": [],
  "geometry": {"coordinates":[-111.4833,35.35],"type":"Point"}
}