{
  "id": 7312882,
  "type": "Feature",
  "properties": {
    "tgn:hierarchy":[
        "tgn:7312882",
        "tgn:1001702",
        "tgn:1000049",
        "tgn:1000002",
        "tgn:7029392"
    ],
    "tgn:id":7312882,
    "tgn:name":"Lambarry, Punta",
    "tgn:placetype":[
        "aat:300386846"
    ]
},
  "bbox": [],
  "geometry": {"coordinates":[-69.183333,-54.366667],"type":"Point"}
}