{
  "id": 2780533,
  "type": "Feature",
  "properties": {
    "tgn:hierarchy":[
        "tgn:2780533",
        "tgn:1000001",
        "tgn:7006451",
        "tgn:7012149",
        "tgn:2000101",
        "tgn:7029392"
    ],
    "tgn:id":2780533,
    "tgn:name":"Wood Creek Spring",
    "tgn:placetype":[
        "aat:300008697"
    ]
},
  "bbox": [],
  "geometry": {"coordinates":[-111.0167,33.3833],"type":"Point"}
}