{
  "id": 1004364,
  "type": "Feature",
  "properties": {
    "tgn:hierarchy":[
        "tgn:1004364",
        "tgn:1000004",
        "tgn:7000201",
        "tgn:7000198",
        "tgn:7029392"
    ],
    "tgn:id":1004364,
    "tgn:name:en":"Dich\u0101on Kal\u0101n",
    "tgn:placetype":[
        "aat:300008347",
        "aat:300000745"
    ]
},
  "bbox": [],
  "geometry": {"coordinates":[76.9833,28.65],"type":"Point"}
}