{
  "id": 2369443,
  "type": "Feature",
  "properties": {
    "tgn:hierarchy":[
        "tgn:2369443",
        "tgn:1000001",
        "tgn:1002473",
        "tgn:7012149",
        "tgn:7007240",
        "tgn:7029392"
    ],
    "tgn:id":2369443,
    "tgn:name":"Gun Point",
    "tgn:placetype":[
        "aat:300008850"
    ]
},
  "bbox": [],
  "geometry": {"coordinates":[-82.6667,28.4333],"type":"Point"}
}