{
  "id": 2244242,
  "type": "Feature",
  "properties": {
    "tgn:hierarchy":[
        "tgn:2244242",
        "tgn:1000001",
        "tgn:7016172",
        "tgn:7012149",
        "tgn:2000167",
        "tgn:7029392"
    ],
    "tgn:id":2244242,
    "tgn:name":"Clift Creek",
    "tgn:placetype":[
        "aat:300008706"
    ]
},
  "bbox": [],
  "geometry": {"coordinates":[-92.6833,34.5167],"type":"Point"}
}