{
  "id": 2151351,
  "type": "Feature",
  "properties": {
    "tgn:hierarchy":[
        "tgn:2151351",
        "tgn:1000001",
        "tgn:7012149",
        "tgn:2000227",
        "tgn:7007158",
        "tgn:7029392"
    ],
    "tgn:id":2151351,
    "tgn:name":"Bates Lake",
    "tgn:placetype":[
        "aat:300008680"
    ]
},
  "bbox": [],
  "geometry": {"coordinates":[-104.1833,37.55],"type":"Point"}
}