<<<<<<< HEAD
{
  "id": 2337609,
  "type": "Feature",
  "properties": {
    "tgn:hierarchy":[
        "tgn:2337609",
        "tgn:1000001",
        "tgn:7012149",
        "tgn:2001895",
        "tgn:7007825",
        "tgn:7029392"
    ],
    "tgn:id":2337609,
    "tgn:name":"Fox Branch",
    "tgn:placetype":[
        "aat:300008699"
    ]
},
  "bbox": [],
  "geometry": {"coordinates":[-86.9333,35.4333],"type":"Point"}
}
=======
{"geometry":{"type":"Point","coordinates":[-86.933300,35.433300]},"type":"Feature","properties":{"hierarchy":["tgn:2337609","tgn:1000001","tgn:7012149","tgn:2001895","tgn:7007825","tgn:7029392"],"placetype":["aat:300008699"],"id":2337609,"name:xx":"Fox Branch"}}
>>>>>>> 03f74aca74312dbeaf24d7e61306dd6a786dc3d0
