<<<<<<< HEAD
{
  "id": 2766545,
  "type": "Feature",
  "properties": {
    "tgn:hierarchy":[
        "tgn:2766545",
        "tgn:1000001",
        "tgn:7012149",
        "tgn:2000637",
        "tgn:7007253",
        "tgn:7029392"
    ],
    "tgn:id":2766545,
    "tgn:name":"White Oak Creek",
    "tgn:placetype":[
        "aat:300008706"
    ]
},
  "bbox": [],
  "geometry": {"coordinates":[-93.5833,41.7667],"type":"Point"}
}
=======
{"geometry":{"type":"Point","coordinates":[-93.583300,41.766700]},"type":"Feature","properties":{"hierarchy":["tgn:2766545","tgn:1000001","tgn:7012149","tgn:2000637","tgn:7007253","tgn:7029392"],"placetype":["aat:300008706"],"id":2766545,"name:xx":"White Oak Creek"}}
>>>>>>> 03f74aca74312dbeaf24d7e61306dd6a786dc3d0
