{
  "id": 7569282,
  "type": "Feature",
  "properties": {
    "tgn:hierarchy":[
        "tgn:7569282",
        "tgn:1000004",
        "tgn:7000198",
        "tgn:7031786",
        "tgn:7029392"
    ],
    "tgn:id":7569282,
    "tgn:name:en":"Sarora",
    "tgn:placetype":[
        "aat:300008347"
    ]
},
  "bbox": [],
  "geometry": {"coordinates":[78.642778,29.990278],"type":"Point"}
}