{
  "id": 7313763,
  "type": "Feature",
  "properties": {
    "tgn:hierarchy":[
        "tgn:7313763",
        "tgn:1001768",
        "tgn:1000049",
        "tgn:1000002",
        "tgn:7029392"
    ],
    "tgn:id":7313763,
    "tgn:name":"Los Azules",
    "tgn:placetype":[
        "aat:300008347"
    ]
},
  "bbox": [],
  "geometry": {"coordinates":[-70.366667,-32.916667],"type":"Point"}
}