{
  "id": 7357394,
  "type": "Feature",
  "properties": {
    "tgn:hierarchy":[
        "tgn:7357394",
        "tgn:1000001",
        "tgn:1001960",
        "tgn:7005560",
        "tgn:7029392"
    ],
    "tgn:id":7357394,
    "tgn:name":"Corral de Piedra",
    "tgn:placetype":[
        "aat:300008347"
    ]
},
  "bbox": [],
  "geometry": {"coordinates":[-110.366667,31.25],"type":"Point"}
}