{
  "id": 1019864,
  "type": "Feature",
  "properties": {
    "tgn:hierarchy":[
        "tgn:1019864",
        "tgn:1001160",
        "tgn:7006477",
        "tgn:1000002",
        "tgn:7029392"
    ],
    "tgn:id":1019864,
    "tgn:name":"Pl\u00e1tanos",
    "tgn:placetype":[
        "aat:300008347"
    ]
},
  "bbox": [],
  "geometry": {"coordinates":[-58.1833,-34.7833],"type":"Point"}
}