{
  "id": 7430792,
  "type": "Feature",
  "properties": {
    "tgn:hierarchy":[
        "tgn:7430792",
        "tgn:7005583",
        "tgn:1000001",
        "tgn:7005560",
        "tgn:7029392"
    ],
    "tgn:id":7430792,
    "tgn:name":"Independencia",
    "tgn:placetype":[
        "aat:300008347"
    ]
},
  "bbox": [],
  "geometry": {"coordinates":[-103.416667,25.85],"type":"Point"}
}