{
  "id": 7034850,
  "type": "Feature",
  "properties": {
    "tgn:hierarchy":[
        "tgn:7034850",
        "tgn:7003013",
        "tgn:7003005",
        "tgn:1000003",
        "tgn:1000080",
        "tgn:7029392"
    ],
    "tgn:id":7034850,
    "tgn:name":"Molo San Vincenzo",
    "tgn:placetype":[
        "aat:300120779"
    ]
},
  "bbox": [],
  "geometry": {"coordinates":[14.263333,40.833333],"type":"Point"}
}