{
  "id": 7311797,
  "type": "Feature",
  "properties": {
    "tgn:hierarchy":[
        "tgn:7311797",
        "tgn:1001657",
        "tgn:1000049",
        "tgn:1000002",
        "tgn:7029392"
    ],
    "tgn:id":7311797,
    "tgn:name":"Las Mollacas",
    "tgn:placetype":[
        "aat:300008347"
    ]
},
  "bbox": [],
  "geometry": {"coordinates":[-70.683333,-30.75],"type":"Point"}
}