{
  "id": 7322715,
  "type": "Feature",
  "properties": {
    "tgn:hierarchy":[
        "tgn:7322715",
        "tgn:7002818",
        "tgn:1001647",
        "tgn:1000003",
        "tgn:1000095",
        "tgn:7029392"
    ],
    "tgn:id":7322715,
    "tgn:name":"Salmeroncillos de Arriba",
    "tgn:placetype":[
        "aat:300008347"
    ]
},
  "bbox": [],
  "geometry": {"coordinates":[-2.533333,40.516667],"type":"Point"}
}