{
  "id": 2207354,
  "type": "Feature",
  "properties": {
    "tgn:hierarchy":[
        "tgn:2207354",
        "tgn:1000001",
        "tgn:7006451",
        "tgn:2000092",
        "tgn:7012149",
        "tgn:7029392"
    ],
    "tgn:id":2207354,
    "tgn:name":"Bunker Hill Spring",
    "tgn:placetype":[
        "aat:300008697"
    ]
},
  "bbox": [],
  "geometry": {"coordinates":[-111.9167,34.9833],"type":"Point"}
}