{
  "id": 7244756,
  "type": "Feature",
  "properties": {
    "tgn:hierarchy":[
        "tgn:7244756",
        "tgn:7003457",
        "tgn:1000003",
        "tgn:1000063",
        "tgn:7018236",
        "tgn:7029392"
    ],
    "tgn:id":7244756,
    "tgn:name":"Asper",
    "tgn:placetype":[
        "aat:300008347"
    ]
},
  "bbox": [],
  "geometry": {"coordinates":[3.651263,50.913696],"type":"Point"}
}