{
  "id": 2174821,
  "type": "Feature",
  "properties": {
    "tgn:hierarchy":[
        "tgn:2174821",
        "tgn:1000001",
        "tgn:1002328",
        "tgn:7012149",
        "tgn:7007568",
        "tgn:7029392"
    ],
    "tgn:id":2174821,
    "tgn:name":"Bittersweet Hill",
    "tgn:placetype":[
        "aat:300008798"
    ]
},
  "bbox": [],
  "geometry": {"coordinates":[-75.15,41.9333],"type":"Point"}
}