{
  "id": 2711629,
  "type": "Feature",
  "properties": {
    "tgn:hierarchy":[
        "tgn:2711629",
        "tgn:1000001",
        "tgn:7012149",
        "tgn:1002422",
        "tgn:7007251",
        "tgn:7029392"
    ],
    "tgn:id":2711629,
    "tgn:name":"Tar Hollow",
    "tgn:placetype":[
        "aat:300008761"
    ]
},
  "bbox": [],
  "geometry": {"coordinates":[-90.4833,39.2333],"type":"Point"}
}