{
  "id": 2164728,
  "type": "Feature",
  "properties": {
    "tgn:hierarchy":[
        "tgn:2164728",
        "tgn:1000001",
        "tgn:7012149",
        "tgn:7007157",
        "tgn:1002857",
        "tgn:7029392"
    ],
    "tgn:id":2164728,
    "tgn:name":"Bertha Peak",
    "tgn:placetype":[
        "aat:300008798"
    ]
},
  "bbox": [],
  "geometry": {"coordinates":[-116.8833,34.2667],"type":"Point"}
}