{
  "id": 2487572,
  "type": "Feature",
  "properties": {
    "tgn:hierarchy":[
        "tgn:2487572",
        "tgn:1000001",
        "tgn:7012149",
        "tgn:2002291",
        "tgn:7013961",
        "tgn:7029392"
    ],
    "tgn:id":2487572,
    "tgn:name":"Left Fork Flatrock Creek",
    "tgn:placetype":[
        "aat:300008706"
    ]
},
  "bbox": [],
  "geometry": {"coordinates":[-79.4167,38.9333],"type":"Point"}
}