{
  "id": 7166965,
  "type": "Feature",
  "properties": {
    "tgn:hierarchy":[
        "tgn:7166965",
        "tgn:1000003",
        "tgn:7000094",
        "tgn:7000084",
        "tgn:7029392"
    ],
    "tgn:id":7166965,
    "tgn:name":"Haschen Berg",
    "tgn:placetype":[
        "aat:300008777"
    ]
},
  "bbox": [],
  "geometry": {"coordinates":[12.416667,54.233333],"type":"Point"}
}