{
  "id": 7561227,
  "type": "Feature",
  "properties": {
    "tgn:hierarchy":[
        "tgn:7561227",
        "tgn:1000004",
        "tgn:7000198",
        "tgn:7016722",
        "tgn:7029392"
    ],
    "tgn:id":7561227,
    "tgn:name:en":"Nagla Bari",
    "tgn:placetype":[
        "aat:300008347"
    ]
},
  "bbox": [],
  "geometry": {"coordinates":[79.125186,26.931405],"type":"Point"}
}