{
  "id": 2058671,
  "type": "Feature",
  "properties": {
    "tgn:hierarchy":[
        "tgn:2058671",
        "tgn:1000001",
        "tgn:7012149",
        "tgn:2001243",
        "tgn:7007523",
        "tgn:7029392"
    ],
    "tgn:id":2058671,
    "tgn:name":"Elmwood",
    "tgn:placetype":[
        "aat:300008347"
    ]
},
  "bbox": [],
  "geometry": {"coordinates":[-93.4167,39.0667],"type":"Point"}
}