<<<<<<< HEAD
{
  "id": 7365323,
  "type": "Feature",
  "properties": {
    "tgn:hierarchy":[
        "tgn:7365323",
        "tgn:1000001",
        "tgn:1001960",
        "tgn:7005560",
        "tgn:7029392"
    ],
    "tgn:id":7365323,
    "tgn:name":"El Sorteo, Cerro",
    "tgn:placetype":[
        "aat:300008795"
    ]
},
  "bbox": [],
  "geometry": {"coordinates":[-108.766667,27.333333],"type":"Point"}
}
=======
{"geometry":{"type":"Point","coordinates":[-108.766667,27.333333]},"type":"Feature","properties":{"hierarchy":["tgn:7365323","tgn:1000001","tgn:1001960","tgn:7005560","tgn:7029392"],"placetype":["aat:300008795"],"id":7365323,"name:xx":"El Sorteo, Cerro"}}
>>>>>>> 03f74aca74312dbeaf24d7e61306dd6a786dc3d0
