{
  "id": 2538981,
  "type": "Feature",
  "properties": {
    "tgn:hierarchy":[
        "tgn:2538981",
        "tgn:1000001",
        "tgn:2000466",
        "tgn:7012149",
        "tgn:7007250",
        "tgn:7029392"
    ],
    "tgn:id":2538981,
    "tgn:name":"New Canyon",
    "tgn:placetype":[
        "aat:300008761"
    ]
},
  "bbox": [],
  "geometry": {"coordinates":[-112.1167,42.8167],"type":"Point"}
}