<<<<<<< HEAD
{
  "id": 7355172,
  "type": "Feature",
  "properties": {
    "tgn:hierarchy":[
        "tgn:7355172",
        "tgn:1000001",
        "tgn:7005600",
        "tgn:7005560",
        "tgn:7029392"
    ],
    "tgn:id":7355172,
    "tgn:name":"Chen Castilla",
    "tgn:placetype":[
        "aat:300387007"
    ]
},
  "bbox": [],
  "geometry": {"coordinates":[-90.066667,20.933333],"type":"Point"}
}
=======
{"geometry":{"type":"Point","coordinates":[-90.066667,20.933333]},"type":"Feature","properties":{"hierarchy":["tgn:7355172","tgn:1000001","tgn:7005600","tgn:7005560","tgn:7029392"],"placetype":["aat:300387007"],"id":7355172,"name:xx":"Chen Castilla"}}
>>>>>>> 03f74aca74312dbeaf24d7e61306dd6a786dc3d0
