{
  "id": 2740045,
  "type": "Feature",
  "properties": {
    "tgn:hierarchy":[
        "tgn:2740045",
        "tgn:1000001",
        "tgn:7012149",
        "tgn:2001276",
        "tgn:7007524",
        "tgn:7029392"
    ],
    "tgn:id":2740045,
    "tgn:name":"Upper Hanson Spring",
    "tgn:placetype":[
        "aat:300008697"
    ]
},
  "bbox": [],
  "geometry": {"coordinates":[-106.85,47.0833],"type":"Point"}
}