{
  "id": 7571652,
  "type": "Feature",
  "properties": {
    "tgn:hierarchy":[
        "tgn:7571652",
        "tgn:1001828",
        "tgn:1000004",
        "tgn:7000198",
        "tgn:7029392"
    ],
    "tgn:id":7571652,
    "tgn:name:en":"God\u0101vari",
    "tgn:placetype":[
        "aat:300007783"
    ]
},
  "bbox": [],
  "geometry": {"coordinates":[81.783333,17.016667],"type":"Point"}
}