{
  "id": 1122479,
  "type": "Feature",
  "properties": {
    "tgn:hierarchy":[
        "tgn:1122479",
        "tgn:7002444",
        "tgn:1000003",
        "tgn:7008082",
        "tgn:7008591",
        "tgn:7029392"
    ],
    "tgn:id":1122479,
    "tgn:name:en":"Cannich",
    "tgn:placetype":[
        "aat:300008707",
        "aat:300008699"
    ]
},
  "bbox": [],
  "geometry": {"coordinates":[-4.733333,57.35],"type":"Point"}
}