{
  "id": 7255913,
  "type": "Feature",
  "properties": {
    "tgn:hierarchy":[
        "tgn:7255913",
        "tgn:7003460",
        "tgn:1000003",
        "tgn:1000063",
        "tgn:4012014",
        "tgn:7029392"
    ],
    "tgn:id":7255913,
    "tgn:name":"Saint-Jacques",
    "tgn:placetype":[
        "aat:300008347"
    ]
},
  "bbox": [],
  "geometry": {"coordinates":[5.85,50.35],"type":"Point"}
}