{
  "id": 7505451,
  "type": "Feature",
  "properties": {
    "tgn:hierarchy":[
        "tgn:7505451",
        "tgn:1008380",
        "tgn:7000507",
        "tgn:1000226",
        "tgn:1000006",
        "tgn:7029392"
    ],
    "tgn:id":7505451,
    "tgn:name:en":"Whirinaki",
    "tgn:placetype":[
        "aat:300008347"
    ]
},
  "bbox": [],
  "geometry": {"coordinates":[173.466667,-35.483333],"type":"Point"}
}