{
  "id": 2548779,
  "type": "Feature",
  "properties": {
    "tgn:hierarchy":[
        "tgn:2548779",
        "tgn:1000001",
        "tgn:7012149",
        "tgn:2002162",
        "tgn:7007919",
        "tgn:7029392"
    ],
    "tgn:id":2548779,
    "tgn:name":"North Pearisburg",
    "tgn:placetype":[
        "aat:300008347"
    ]
},
  "bbox": [],
  "geometry": {"coordinates":[-80.7667,37.3333],"type":"Point"}
}