{
  "id": 7335038,
  "type": "Feature",
  "properties": {
    "tgn:hierarchy":[
        "tgn:7335038",
        "tgn:7002849",
        "tgn:1000003",
        "tgn:7009604",
        "tgn:1000095",
        "tgn:7029392"
    ],
    "tgn:id":7335038,
    "tgn:name":"Goyerria",
    "tgn:placetype":[
        "aat:300008347"
    ]
},
  "bbox": [],
  "geometry": {"coordinates":[-2.682334,43.355638],"type":"Point"}
}