{
  "id": 2357579,
  "type": "Feature",
  "properties": {
    "tgn:hierarchy":[
        "tgn:2357579",
        "tgn:1000001",
        "tgn:7006451",
        "tgn:2000093",
        "tgn:7012149",
        "tgn:7029392"
    ],
    "tgn:id":2357579,
    "tgn:name":"Gowan Mine",
    "tgn:placetype":[
        "aat:300000390"
    ]
},
  "bbox": [],
  "geometry": {"coordinates":[-111.4167,34.25],"type":"Point"}
}