{
  "id": 2577263,
  "type": "Feature",
  "properties": {
    "tgn:hierarchy":[
        "tgn:2577263",
        "tgn:1000001",
        "tgn:7012149",
        "tgn:2002303",
        "tgn:7013961",
        "tgn:7029392"
    ],
    "tgn:id":2577263,
    "tgn:name":"Peters Fork",
    "tgn:placetype":[
        "aat:300008699"
    ]
},
  "bbox": [],
  "geometry": {"coordinates":[-81.4667,39.2667],"type":"Point"}
}