{
  "id": 7279370,
  "type": "Feature",
  "properties": {
    "tgn:hierarchy":[
        "tgn:7279370",
        "tgn:1001702",
        "tgn:1000049",
        "tgn:1000002",
        "tgn:7029392"
    ],
    "tgn:id":7279370,
    "tgn:name":"Riveros, Seno",
    "tgn:placetype":[
        "aat:300008676"
    ]
},
  "bbox": [],
  "geometry": {"coordinates":[-73.816667,-52.35],"type":"Point"}
}