{
  "id": 2359486,
  "type": "Feature",
  "properties": {
    "tgn:hierarchy":[
        "tgn:2359486",
        "tgn:1000001",
        "tgn:7012149",
        "tgn:1002794",
        "tgn:7007708",
        "tgn:7029392"
    ],
    "tgn:id":2359486,
    "tgn:name":"Grant Hill",
    "tgn:placetype":[
        "aat:300008798"
    ]
},
  "bbox": [],
  "geometry": {"coordinates":[-123.4167,44.7333],"type":"Point"}
}