{
  "id": 2372624,
  "type": "Feature",
  "properties": {
    "tgn:hierarchy":[
        "tgn:2372624",
        "tgn:1000001",
        "tgn:2001411",
        "tgn:7012149",
        "tgn:7007526",
        "tgn:7029392"
    ],
    "tgn:id":2372624,
    "tgn:name":"Hall Creek",
    "tgn:placetype":[
        "aat:300008706"
    ]
},
  "bbox": [],
  "geometry": {"coordinates":[-115.1333,41.0333],"type":"Point"}
}