{
  "id": 7232095,
  "type": "Feature",
  "properties": {
    "tgn:hierarchy":[
        "tgn:7232095",
        "tgn:7011168",
        "tgn:7001338",
        "tgn:1000003",
        "tgn:1000074",
        "tgn:7029392"
    ],
    "tgn:id":7232095,
    "tgn:name":"K\u00e1lamos",
    "tgn:placetype":[
        "aat:300008347"
    ]
},
  "bbox": [],
  "geometry": {"coordinates":[20.933333,38.616667],"type":"Point"}
}