{
  "id": 7508265,
  "type": "Feature",
  "properties": {
    "tgn:hierarchy":[
        "tgn:7508265",
        "tgn:7016670",
        "tgn:1008380",
        "tgn:1000226",
        "tgn:1000006",
        "tgn:7029392"
    ],
    "tgn:id":7508265,
    "tgn:name:en":"Pakowhai",
    "tgn:placetype":[
        "aat:300008347"
    ]
},
  "bbox": [],
  "geometry": {"coordinates":[176.866667,-39.583333],"type":"Point"}
}