<<<<<<< HEAD
{
  "id": 2769669,
  "type": "Feature",
  "properties": {
    "tgn:hierarchy":[
        "tgn:2769669",
        "tgn:1000001",
        "tgn:1002461",
        "tgn:7012149",
        "tgn:7007159",
        "tgn:7029392"
    ],
    "tgn:id":2769669,
    "tgn:name":"Wiggin Brook",
    "tgn:placetype":[
        "aat:300008699"
    ]
},
  "bbox": [],
  "geometry": {"coordinates":[-72.8667,41.8],"type":"Point"}
}
=======
{"geometry":{"type":"Point","coordinates":[-72.866700,41.800000]},"type":"Feature","properties":{"hierarchy":["tgn:2769669","tgn:1000001","tgn:1002461","tgn:7012149","tgn:7007159","tgn:7029392"],"placetype":["aat:300008699"],"id":2769669,"name:xx":"Wiggin Brook"}}
>>>>>>> 03f74aca74312dbeaf24d7e61306dd6a786dc3d0
