{
  "id": 7291645,
  "type": "Feature",
  "properties": {
    "tgn:hierarchy":[
        "tgn:7291645",
        "tgn:1001702",
        "tgn:1000049",
        "tgn:1000002",
        "tgn:7029392"
    ],
    "tgn:id":7291645,
    "tgn:name":"Entrada, Punta",
    "tgn:placetype":[
        "aat:300386846"
    ]
},
  "bbox": [],
  "geometry": {"coordinates":[-73.533333,-53.15],"type":"Point"}
}