{
  "id": 7327213,
  "type": "Feature",
  "properties": {
    "tgn:hierarchy":[
        "tgn:7327213",
        "tgn:7002758",
        "tgn:7002823",
        "tgn:1000003",
        "tgn:1000095",
        "tgn:7029392"
    ],
    "tgn:id":7327213,
    "tgn:name":"Parrilla, Arroyo de la",
    "tgn:placetype":[
        "aat:300008699"
    ]
},
  "bbox": [],
  "geometry": {"coordinates":[-6.766667,37.45],"type":"Point"}
}