{
  "id": 7335080,
  "type": "Feature",
  "properties": {
    "tgn:hierarchy":[
        "tgn:7335080",
        "tgn:7002758",
        "tgn:7002841",
        "tgn:1000003",
        "tgn:1000095",
        "tgn:7029392"
    ],
    "tgn:id":7335080,
    "tgn:name":"Gandul",
    "tgn:placetype":[
        "aat:300008347"
    ]
},
  "bbox": [],
  "geometry": {"coordinates":[-5.783333,37.333333],"type":"Point"}
}