{
  "id": 7521530,
  "type": "Feature",
  "properties": {
    "tgn:hierarchy":[
        "tgn:7521530",
        "tgn:7001242",
        "tgn:7016833",
        "tgn:7000123",
        "tgn:7029392"
    ],
    "tgn:id":7521530,
    "tgn:name:en":"Ma\u1e29a\u0163\u0163at al Ashr\u0101f",
    "tgn:placetype":[
        "aat:300007783"
    ]
},
  "bbox": [],
  "geometry": {"coordinates":[32.783333,26.083333],"type":"Point"}
}