{
  "id": 2600794,
  "type": "Feature",
  "properties": {
    "tgn:hierarchy":[
        "tgn:2600794",
        "tgn:1000001",
        "tgn:7012149",
        "tgn:1002387",
        "tgn:7007710",
        "tgn:7029392"
    ],
    "tgn:id":2600794,
    "tgn:name":"Pump Run",
    "tgn:placetype":[
        "aat:300008699"
    ]
},
  "bbox": [],
  "geometry": {"coordinates":[-77.9167,39.95],"type":"Point"}
}