{
  "id": 1093580,
  "type": "Feature",
  "properties": {
    "tgn:hierarchy":[
        "tgn:1093580",
        "tgn:7001242",
        "tgn:7017584",
        "tgn:1000193",
        "tgn:7029392"
    ],
    "tgn:id":1093580,
    "tgn:name":"Rosedene",
    "tgn:placetype":[
        "aat:300008347"
    ]
},
  "bbox": [],
  "geometry": {"coordinates":[22.4167,-32.0333],"type":"Point"}
}