{
  "id": 7206940,
  "type": "Feature",
  "properties": {
    "tgn:hierarchy":[
        "tgn:7206940",
        "tgn:7003692",
        "tgn:1000003",
        "tgn:7000084",
        "tgn:7029392"
    ],
    "tgn:id":7206940,
    "tgn:name":"Buchhorn",
    "tgn:placetype":[
        "aat:300008347"
    ]
},
  "bbox": [],
  "geometry": {"coordinates":[9.494444,49.154722],"type":"Point"}
}