{
  "id": 2156306,
  "type": "Feature",
  "properties": {
    "tgn:hierarchy":[
        "tgn:2156306",
        "tgn:1000001",
        "tgn:7012149",
        "tgn:2001497",
        "tgn:7007709",
        "tgn:7029392"
    ],
    "tgn:id":2156306,
    "tgn:name":"Bearpen Branch",
    "tgn:placetype":[
        "aat:300008699"
    ]
},
  "bbox": [],
  "geometry": {"coordinates":[-83.9833,35.2833],"type":"Point"}
}