{
  "id": 7438039,
  "type": "Feature",
  "properties": {
    "tgn:hierarchy":[
        "tgn:7438039",
        "tgn:1000001",
        "tgn:7005597",
        "tgn:7005560",
        "tgn:7029392"
    ],
    "tgn:id":7438039,
    "tgn:name":"Tamat\u00e1n",
    "tgn:placetype":[
        "aat:300008347"
    ]
},
  "bbox": [],
  "geometry": {"coordinates":[-99.166667,23.716667],"type":"Point"}
}