{
  "id": 7402660,
  "type": "Feature",
  "properties": {
    "tgn:hierarchy":[
        "tgn:7402660",
        "tgn:1000001",
        "tgn:1001937",
        "tgn:7005560",
        "tgn:7029392"
    ],
    "tgn:id":7402660,
    "tgn:name":"Bulucax",
    "tgn:placetype":[
        "aat:300008347"
    ]
},
  "bbox": [],
  "geometry": {"coordinates":[-88.766667,19.9625],"type":"Point"}
}