{
  "id": 7362300,
  "type": "Feature",
  "properties": {
    "tgn:hierarchy":[
        "tgn:7362300",
        "tgn:1000001",
        "tgn:1001960",
        "tgn:7005560",
        "tgn:7029392"
    ],
    "tgn:id":7362300,
    "tgn:name":"El Carmen",
    "tgn:placetype":[
        "aat:300008347"
    ]
},
  "bbox": [],
  "geometry": {"coordinates":[-111.383333,28.583333],"type":"Point"}
}