{
  "id": 2001872,
  "type": "Feature",
  "properties": {
    "tgn:hierarchy":[
        "tgn:2001872",
        "tgn:1000001",
        "tgn:7012149",
        "tgn:7007825",
        "tgn:7029392"
    ],
    "tgn:id":2001872,
    "tgn:name":"Hardin",
    "tgn:placetype":[
        "aat:300387145",
        "aat:300000771"
    ]
},
  "bbox": [],
  "geometry": {"coordinates":[-88.1667,35.1833],"type":"Point"}
}