<<<<<<< HEAD
{
  "id": 7377937,
  "type": "Feature",
  "properties": {
    "tgn:hierarchy":[
        "tgn:7377937",
        "tgn:1001853",
        "tgn:1000001",
        "tgn:7005560",
        "tgn:7029392"
    ],
    "tgn:id":7377937,
    "tgn:name":"Rancho La Victoria",
    "tgn:placetype":[
        "aat:300000241"
    ]
},
  "bbox": [],
  "geometry": {"coordinates":[-103.633333,27.766667],"type":"Point"}
}
=======
{"geometry":{"type":"Point","coordinates":[-103.633333,27.766667]},"type":"Feature","properties":{"hierarchy":["tgn:7377937","tgn:1001853","tgn:1000001","tgn:7005560","tgn:7029392"],"placetype":["aat:300000241"],"id":7377937,"name:xx":"Rancho La Victoria"}}
>>>>>>> 03f74aca74312dbeaf24d7e61306dd6a786dc3d0
