{
  "id": 2367361,
  "type": "Feature",
  "properties": {
    "tgn:hierarchy":[
        "tgn:2367361",
        "tgn:1000001",
        "tgn:7013686",
        "tgn:7012149",
        "tgn:7007517",
        "tgn:7029392"
    ],
    "tgn:id":2367361,
    "tgn:name":"Grotto Pond",
    "tgn:placetype":[
        "aat:300008680"
    ]
},
  "bbox": [],
  "geometry": {"coordinates":[-72.8167,42.3167],"type":"Point"}
}