{
  "id": 1115820,
  "type": "Feature",
  "properties": {
    "tgn:hierarchy":[
        "tgn:1115820",
        "tgn:7005685",
        "tgn:1000001",
        "tgn:7013154",
        "tgn:7029392"
    ],
    "tgn:id":1115820,
    "tgn:name":"Carson Lake",
    "tgn:placetype":[
        "aat:300008680"
    ]
},
  "bbox": [],
  "geometry": {"coordinates":[-77.7667,45.5167],"type":"Point"}
}