{
  "id": 7423658,
  "type": "Feature",
  "properties": {
    "tgn:hierarchy":[
        "tgn:7423658",
        "tgn:1000001",
        "tgn:7005597",
        "tgn:7005560",
        "tgn:7029392"
    ],
    "tgn:id":7423658,
    "tgn:name":"Las \u00c1guilas del Bernal",
    "tgn:placetype":[
        "aat:300008347"
    ]
},
  "bbox": [],
  "geometry": {"coordinates":[-98.516667,22.65],"type":"Point"}
}