{
  "id": 7163887,
  "type": "Feature",
  "properties": {
    "tgn:hierarchy":[
        "tgn:7163887",
        "tgn:1000003",
        "tgn:7003688",
        "tgn:7000084",
        "tgn:7029392"
    ],
    "tgn:id":7163887,
    "tgn:name":"Hubsand",
    "tgn:placetype":[
        "aat:300386970"
    ]
},
  "bbox": [],
  "geometry": {"coordinates":[8.383333,54.633333],"type":"Point"}
}