<<<<<<< HEAD
{
  "id": 7377193,
  "type": "Feature",
  "properties": {
    "tgn:hierarchy":[
        "tgn:7377193",
        "tgn:1000001",
        "tgn:7005597",
        "tgn:7005560",
        "tgn:7029392"
    ],
    "tgn:id":7377193,
    "tgn:name":"Las Animas",
    "tgn:placetype":[
        "aat:300266554",
        "aat:300008699"
    ]
},
  "bbox": [],
  "geometry": {"coordinates":[-99.4,23.35],"type":"Point"}
}
=======
{"geometry":{"type":"Point","coordinates":[-99.400000,23.350000]},"type":"Feature","properties":{"hierarchy":["tgn:7377193","tgn:1000001","tgn:7005597","tgn:7005560","tgn:7029392"],"placetype":["aat:300266554","aat:300008699"],"id":7377193,"name:xx":"Las Animas"}}
>>>>>>> 03f74aca74312dbeaf24d7e61306dd6a786dc3d0
