{
  "id": 2624192,
  "type": "Feature",
  "properties": {
    "tgn:hierarchy":[
        "tgn:2624192",
        "tgn:1000001",
        "tgn:2000952",
        "tgn:7012149",
        "tgn:7007520",
        "tgn:7029392"
    ],
    "tgn:id":2624192,
    "tgn:name":"Rock Island",
    "tgn:placetype":[
        "aat:300008791"
    ]
},
  "bbox": [],
  "geometry": {"coordinates":[-84.1333,46.3833],"type":"Point"}
}