{
  "id": 7168530,
  "type": "Feature",
  "properties": {
    "tgn:hierarchy":[
        "tgn:7168530",
        "tgn:1000003",
        "tgn:7003687",
        "tgn:7000084",
        "tgn:7029392"
    ],
    "tgn:id":7168530,
    "tgn:name":"Hasselbusch",
    "tgn:placetype":[
        "aat:300008863"
    ]
},
  "bbox": [],
  "geometry": {"coordinates":[11.866667,51.916667],"type":"Point"}
}