{
  "id": 2050484,
  "type": "Feature",
  "properties": {
    "tgn:hierarchy":[
        "tgn:2050484",
        "tgn:1000001",
        "tgn:2050476",
        "tgn:1002923",
        "tgn:7012149",
        "tgn:7007517",
        "tgn:7029392"
    ],
    "tgn:id":2050484,
    "tgn:name":"Point of Pines",
    "tgn:placetype":[
        "aat:300000745"
    ]
},
  "bbox": [],
  "geometry": {"coordinates":[-70.9667,42.4333],"type":"Point"}
}