<<<<<<< HEAD
{
  "id": 2259539,
  "type": "Feature",
  "properties": {
    "tgn:hierarchy":[
        "tgn:2259539",
        "tgn:1000001",
        "tgn:7006451",
        "tgn:2000094",
        "tgn:7012149",
        "tgn:7029392"
    ],
    "tgn:id":2259539,
    "tgn:name":"Cottonwood Wash",
    "tgn:placetype":[
        "aat:300008699"
    ]
},
  "bbox": [],
  "geometry": {"coordinates":[-109.65,32.9667],"type":"Point"}
}
=======
{"geometry":{"type":"Point","coordinates":[-109.650000,32.966700]},"type":"Feature","properties":{"hierarchy":["tgn:2259539","tgn:1000001","tgn:7006451","tgn:2000094","tgn:7012149","tgn:7029392"],"placetype":["aat:300008699"],"id":2259539,"name:xx":"Cottonwood Wash"}}
>>>>>>> 03f74aca74312dbeaf24d7e61306dd6a786dc3d0
