{
  "id": 1067551,
  "type": "Feature",
  "properties": {
    "tgn:hierarchy":[
        "tgn:1067551",
        "tgn:1000004",
        "tgn:7002078",
        "tgn:1000111",
        "tgn:7029392"
    ],
    "tgn:id":1067551,
    "tgn:name":"Dashaping",
    "tgn:placetype":[
        "aat:300008347"
    ]
},
  "bbox": [],
  "geometry": {"coordinates":[113.8667,29.3833],"type":"Point"}
}