{
  "id": 7117145,
  "type": "Feature",
  "properties": {
    "tgn:hierarchy":[
        "tgn:7117145",
        "tgn:1000003",
        "tgn:7003676",
        "tgn:7000084",
        "tgn:7029392"
    ],
    "tgn:id":7117145,
    "tgn:name":"Oelstorf",
    "tgn:placetype":[
        "aat:300008347"
    ]
},
  "bbox": [],
  "geometry": {"coordinates":[10.133333,53.233333],"type":"Point"}
}