{
  "id": 7008188,
  "type": "Feature",
  "properties": {
    "tgn:hierarchy":[
        "tgn:7008188",
        "tgn:7001155",
        "tgn:1000003",
        "tgn:7002790",
        "tgn:1000095",
        "tgn:7029392"
    ],
    "tgn:id":7008188,
    "tgn:name":"Olite",
    "tgn:placetype":[
        "aat:300008347"
    ]
},
  "bbox": [],
  "geometry": {"coordinates":[-1.65,42.483333],"type":"Point"}
}