{
  "id": 1024121,
  "type": "Feature",
  "properties": {
    "tgn:hierarchy":[
        "tgn:1024121",
        "tgn:1001395",
        "tgn:7002561",
        "tgn:1000051",
        "tgn:1000002",
        "tgn:7029392"
    ],
    "tgn:id":1024121,
    "tgn:name":"Macar\u00e1",
    "tgn:placetype":[
        "aat:300008347"
    ]
},
  "bbox": [],
  "geometry": {"coordinates":[-79.943,-4.381],"type":"Point"}
}