{
  "id": 2278586,
  "type": "Feature",
  "properties": {
    "tgn:hierarchy":[
        "tgn:2278586",
        "tgn:1000001",
        "tgn:7012149",
        "tgn:2002062",
        "tgn:7007826",
        "tgn:7029392"
    ],
    "tgn:id":2278586,
    "tgn:name":"Dead Cow Tank",
    "tgn:placetype":[
        "aat:300006191"
    ]
},
  "bbox": [],
  "geometry": {"coordinates":[-104.0833,31.2333],"type":"Point"}
}