{
  "id": 1085356,
  "type": "Feature",
  "properties": {
    "tgn:hierarchy":[
        "tgn:1085356",
        "tgn:1000957",
        "tgn:1000004",
        "tgn:1000141",
        "tgn:7029392"
    ],
    "tgn:id":1085356,
    "tgn:name":"Nuan-nuan",
    "tgn:placetype":[
        "aat:300008347"
    ]
},
  "bbox": [],
  "geometry": {"coordinates":[121.737439,25.100602],"type":"Point"}
}