{
  "id": 2284923,
  "type": "Feature",
  "properties": {
    "tgn:hierarchy":[
        "tgn:2284923",
        "tgn:1000001",
        "tgn:7012149",
        "tgn:2000822",
        "tgn:7007255",
        "tgn:7029392"
    ],
    "tgn:id":2284923,
    "tgn:name":"Devers Branch",
    "tgn:placetype":[
        "aat:300008699"
    ]
},
  "bbox": [],
  "geometry": {"coordinates":[-85.0667,37.5167],"type":"Point"}
}