{
  "id": 7448263,
  "type": "Feature",
  "properties": {
    "tgn:hierarchy":[
        "tgn:7448263",
        "tgn:7002445",
        "tgn:1000003",
        "tgn:7008153",
        "tgn:7008591",
        "tgn:7029392"
    ],
    "tgn:id":7448263,
    "tgn:name:en":"Sheerness Harbour",
    "tgn:placetype":[
        "aat:300008678"
    ]
},
  "bbox": [],
  "geometry": {"coordinates":[0.733333,51.433333],"type":"Point"}
}