{
  "id": 2521727,
  "type": "Feature",
  "properties": {
    "tgn:hierarchy":[
        "tgn:2521727",
        "tgn:1000001",
        "tgn:7012149",
        "tgn:7029392"
    ],
    "tgn:id":2521727,
    "tgn:name":"Monument Creek",
    "tgn:placetype":[
        "aat:300008706"
    ]
},
  "bbox": [],
  "geometry": {"coordinates":[-109.0833,37.6667],"type":"Point"}
}