{
  "id": 7196783,
  "type": "Feature",
  "properties": {
    "tgn:hierarchy":[
        "tgn:7196783",
        "tgn:7003692",
        "tgn:1000003",
        "tgn:7000084",
        "tgn:7029392"
    ],
    "tgn:id":7196783,
    "tgn:name":"Dettenbach",
    "tgn:placetype":[
        "aat:300000206"
    ]
},
  "bbox": [],
  "geometry": {"coordinates":[7.983333,48.083333],"type":"Point"}
}