<<<<<<< HEAD
{
  "id": 2152750,
  "type": "Feature",
  "properties": {
    "tgn:hierarchy":[
        "tgn:2152750",
        "tgn:1000001",
        "tgn:2001096",
        "tgn:7012149",
        "tgn:7007522",
        "tgn:7029392"
    ],
    "tgn:id":2152750,
    "tgn:name":"Bayou Pierre Mounds",
    "tgn:placetype":[
        "aat:300008798"
    ]
},
  "bbox": [],
  "geometry": {"coordinates":[-91.0,31.9667],"type":"Point"}
}
=======
{"geometry":{"type":"Point","coordinates":[-91.000000,31.966700]},"type":"Feature","properties":{"hierarchy":["tgn:2152750","tgn:1000001","tgn:2001096","tgn:7012149","tgn:7007522","tgn:7029392"],"placetype":["aat:300008798"],"id":2152750,"name:xx":"Bayou Pierre Mounds"}}
>>>>>>> 03f74aca74312dbeaf24d7e61306dd6a786dc3d0
