{
  "id": 7273998,
  "type": "Feature",
  "properties": {
    "tgn:hierarchy":[
        "tgn:7273998",
        "tgn:1000003",
        "tgn:7003632",
        "tgn:7016845",
        "tgn:7029392"
    ],
    "tgn:id":7273998,
    "tgn:name:nl":"Zevenhoven, Polder",
    "tgn:placetype":[
        "aat:300006163"
    ]
},
  "bbox": [],
  "geometry": {"coordinates":[4.783333,51.883333],"type":"Point"}
}