{
  "id": 7525446,
  "type": "Feature",
  "properties": {
    "tgn:hierarchy":[
        "tgn:7525446",
        "tgn:7001242",
        "tgn:7001311",
        "tgn:7016833",
        "tgn:7029392"
    ],
    "tgn:id":7525446,
    "tgn:name:en":"An Nuz\u0101zah",
    "tgn:placetype":[
        "aat:300006207"
    ]
},
  "bbox": [],
  "geometry": {"coordinates":[31.233333,29.25],"type":"Point"}
}