{
  "id": 2504280,
  "type": "Feature",
  "properties": {
    "tgn:hierarchy":[
        "tgn:2504280",
        "tgn:1000001",
        "tgn:7012149",
        "tgn:1002793",
        "tgn:7007240",
        "tgn:7029392"
    ],
    "tgn:id":2504280,
    "tgn:name":"Meadow View Lake",
    "tgn:placetype":[
        "aat:300008680"
    ]
},
  "bbox": [],
  "geometry": {"coordinates":[-81.9833,28.0833],"type":"Point"}
}