{
  "id": 2254405,
  "type": "Feature",
  "properties": {
    "tgn:hierarchy":[
        "tgn:2254405",
        "tgn:1000001",
        "tgn:7012149",
        "tgn:2001395",
        "tgn:7007525",
        "tgn:7029392"
    ],
    "tgn:id":2254405,
    "tgn:name":"Coon Creek",
    "tgn:placetype":[
        "aat:300008706"
    ]
},
  "bbox": [],
  "geometry": {"coordinates":[-96.9833,40.95],"type":"Point"}
}