{
  "id": 7552486,
  "type": "Feature",
  "properties": {
    "tgn:hierarchy":[
        "tgn:7552486",
        "tgn:1000004",
        "tgn:7000198",
        "tgn:7016722",
        "tgn:7029392"
    ],
    "tgn:id":7552486,
    "tgn:name:en":"Motipur",
    "tgn:placetype":[
        "aat:300008347"
    ]
},
  "bbox": [],
  "geometry": {"coordinates":[80.921137,28.355458],"type":"Point"}
}