{
  "id": 7560182,
  "type": "Feature",
  "properties": {
    "tgn:hierarchy":[
        "tgn:7560182",
        "tgn:1000004",
        "tgn:7000198",
        "tgn:7016722",
        "tgn:7029392"
    ],
    "tgn:id":7560182,
    "tgn:name:en":"Durjanpur",
    "tgn:placetype":[
        "aat:300008347"
    ]
},
  "bbox": [],
  "geometry": {"coordinates":[79.329314,27.187924],"type":"Point"}
}