{
  "id": 2039362,
  "type": "Feature",
  "properties": {
    "tgn:hierarchy":[
        "tgn:2039362",
        "tgn:1000001",
        "tgn:7012149",
        "tgn:2000853",
        "tgn:7007255",
        "tgn:7029392"
    ],
    "tgn:id":2039362,
    "tgn:name":"High Falls",
    "tgn:placetype":[
        "aat:300008347",
        "aat:300387210"
    ]
},
  "bbox": [],
  "geometry": {"coordinates":[-83.5833,37.7167],"type":"Point"}
}