{
  "id": 2328105,
  "type": "Feature",
  "properties": {
    "tgn:hierarchy":[
        "tgn:2328105",
        "tgn:1000001",
        "tgn:7012149",
        "tgn:1003038",
        "tgn:7007517",
        "tgn:7029392"
    ],
    "tgn:id":2328105,
    "tgn:name":"Fish Pond",
    "tgn:placetype":[
        "aat:300006191"
    ]
},
  "bbox": [],
  "geometry": {"coordinates":[-71.6833,42.1167],"type":"Point"}
}