{
  "id": 7498166,
  "type": "Feature",
  "properties": {
    "tgn:hierarchy":[
        "tgn:7498166",
        "tgn:1000004",
        "tgn:1000454",
        "tgn:1000141",
        "tgn:7029392"
    ],
    "tgn:id":7498166,
    "tgn:name":"Jingtong Guoxiao",
    "tgn:placetype":[
        "aat:300006495"
    ]
},
  "bbox": [],
  "geometry": {"coordinates":[121.726912,25.022822],"type":"Point"}
}