{
  "id": 2660675,
  "type": "Feature",
  "properties": {
    "tgn:hierarchy":[
        "tgn:2660675",
        "tgn:1000001",
        "tgn:7012149",
        "tgn:2001486",
        "tgn:7007709",
        "tgn:7029392"
    ],
    "tgn:id":2660675,
    "tgn:name":"Shop Branch",
    "tgn:placetype":[
        "aat:300008699"
    ]
},
  "bbox": [],
  "geometry": {"coordinates":[-76.8667,34.8667],"type":"Point"}
}