<<<<<<< HEAD
{
  "id": 7481871,
  "type": "Feature",
  "properties": {
    "tgn:hierarchy":[
        "tgn:7481871",
        "tgn:1000004",
        "tgn:7492971",
        "tgn:1000141",
        "tgn:7029392"
    ],
    "tgn:id":7481871,
    "tgn:name":"Yongxing Qiao",
    "tgn:placetype":[
        "aat:300007836"
    ]
},
  "bbox": [],
  "geometry": {"coordinates":[120.510672,22.673746],"type":"Point"}
}
=======
{"geometry":{"type":"Point","coordinates":[120.510672,22.673746]},"type":"Feature","properties":{"hierarchy":["tgn:7481871","tgn:1000004","tgn:7492971","tgn:1000141","tgn:7029392"],"placetype":["aat:300007836"],"id":7481871,"name:xx":"Yongxing Qiao"}}
>>>>>>> 03f74aca74312dbeaf24d7e61306dd6a786dc3d0
