{
  "id": 2301083,
  "type": "Feature",
  "properties": {
    "tgn:hierarchy":[
        "tgn:2301083",
        "tgn:1000001",
        "tgn:7012149",
        "tgn:1002531",
        "tgn:7007251",
        "tgn:7029392"
    ],
    "tgn:id":2301083,
    "tgn:name":"Dunham Castle",
    "tgn:placetype":[
        "aat:300008347"
    ]
},
  "bbox": [],
  "geometry": {"coordinates":[-88.2667,41.95],"type":"Point"}
}