{
  "id": 7377609,
  "type": "Feature",
  "properties": {
    "tgn:hierarchy":[
        "tgn:7377609",
        "tgn:1000001",
        "tgn:7005589",
        "tgn:7005560",
        "tgn:7029392"
    ],
    "tgn:id":7377609,
    "tgn:name":"Las Ca\u00f1adas",
    "tgn:placetype":[
        "aat:300008347"
    ]
},
  "bbox": [],
  "geometry": {"coordinates":[-99.85,23.95],"type":"Point"}
}