<<<<<<< HEAD
{
  "id": 7116958,
  "type": "Feature",
  "properties": {
    "tgn:hierarchy":[
        "tgn:7116958",
        "tgn:1000003",
        "tgn:7003677",
        "tgn:7000084",
        "tgn:7029392"
    ],
    "tgn:id":7116958,
    "tgn:name":"Oerkhaus",
    "tgn:placetype":[
        "aat:300008347"
    ]
},
  "bbox": [],
  "geometry": {"coordinates":[6.916667,51.15],"type":"Point"}
}
=======
{"geometry":{"type":"Point","coordinates":[6.916667,51.150000]},"type":"Feature","properties":{"hierarchy":["tgn:7116958","tgn:1000003","tgn:7003677","tgn:7000084","tgn:7029392"],"placetype":["aat:300008347"],"id":7116958,"name:xx":"Oerkhaus"}}
>>>>>>> 03f74aca74312dbeaf24d7e61306dd6a786dc3d0
