{
  "id": 7492330,
  "type": "Feature",
  "properties": {
    "tgn:hierarchy":[
        "tgn:7492330",
        "tgn:1000004",
        "tgn:7471332",
        "tgn:1000141",
        "tgn:7029392"
    ],
    "tgn:id":7492330,
    "tgn:name":"Shulinzi",
    "tgn:placetype":[
        "aat:300008347"
    ]
},
  "bbox": [],
  "geometry": {"coordinates":[120.985556,24.931111],"type":"Point"}
}