{
  "id": 2625972,
  "type": "Feature",
  "properties": {
    "tgn:hierarchy":[
        "tgn:2625972",
        "tgn:1000001",
        "tgn:7012149",
        "tgn:1002821",
        "tgn:7007568",
        "tgn:7029392"
    ],
    "tgn:id":2625972,
    "tgn:name":"Rocky Brook",
    "tgn:placetype":[
        "aat:300008699"
    ]
},
  "bbox": [],
  "geometry": {"coordinates":[-73.3667,42.6333],"type":"Point"}
}