{
  "id": 1048373,
  "type": "Feature",
  "properties": {
    "tgn:hierarchy":[
        "tgn:1048373",
        "tgn:7002448",
        "tgn:1000003",
        "tgn:7019199",
        "tgn:7008591",
        "tgn:7029392"
    ],
    "tgn:id":1048373,
    "tgn:name:en":"Kilkeel",
    "tgn:placetype":[
        "aat:300008347"
    ]
},
  "bbox": [],
  "geometry": {"coordinates":[-6.016667,54.066667],"type":"Point"}
}