<<<<<<< HEAD
{
  "id": 7356159,
  "type": "Feature",
  "properties": {
    "tgn:hierarchy":[
        "tgn:7356159",
        "tgn:7005581",
        "tgn:1000001",
        "tgn:7005560",
        "tgn:7029392"
    ],
    "tgn:id":7356159,
    "tgn:name":"Rancho Cerro Colorado",
    "tgn:placetype":[
        "aat:300000241"
    ]
},
  "bbox": [],
  "geometry": {"coordinates":[-107.283333,29.4],"type":"Point"}
}
=======
{"geometry":{"type":"Point","coordinates":[-107.283333,29.400000]},"type":"Feature","properties":{"hierarchy":["tgn:7356159","tgn:7005581","tgn:1000001","tgn:7005560","tgn:7029392"],"placetype":["aat:300000241"],"id":7356159,"name:xx":"Rancho Cerro Colorado"}}
>>>>>>> 03f74aca74312dbeaf24d7e61306dd6a786dc3d0
