{
  "id": 1101718,
  "type": "Feature",
  "properties": {
    "tgn:hierarchy":[
        "tgn:1101718",
        "tgn:7000490",
        "tgn:1000006",
        "tgn:7001828",
        "tgn:7029392"
    ],
    "tgn:id":1101718,
    "tgn:name":"Morton National Park",
    "tgn:placetype":[
        "aat:300008189"
    ]
},
  "bbox": [],
  "geometry": {"coordinates":[150.25,-34.9167],"type":"Point"}
}