{
  "id": 2445490,
  "type": "Feature",
  "properties": {
    "tgn:hierarchy":[
        "tgn:2445490",
        "tgn:1000001",
        "tgn:7012149",
        "tgn:2000480",
        "tgn:7007250",
        "tgn:7029392"
    ],
    "tgn:id":2445490,
    "tgn:name":"Lenville",
    "tgn:placetype":[
        "aat:300008347"
    ]
},
  "bbox": [],
  "geometry": {"coordinates":[-116.8333,46.6333],"type":"Point"}
}