{
  "id": 2427954,
  "type": "Feature",
  "properties": {
    "tgn:hierarchy":[
        "tgn:2427954",
        "tgn:1000001",
        "tgn:7012149",
        "tgn:2000375",
        "tgn:7007248",
        "tgn:7029392"
    ],
    "tgn:id":2427954,
    "tgn:name":"Joycliff Estates",
    "tgn:placetype":[
        "aat:300008347"
    ]
},
  "bbox": [],
  "geometry": {"coordinates":[-83.5667,32.8667],"type":"Point"}
}