{
  "id": 2501074,
  "type": "Feature",
  "properties": {
    "tgn:hierarchy":[
        "tgn:2501074",
        "tgn:1000001",
        "tgn:7012149",
        "tgn:1002877",
        "tgn:7007706",
        "tgn:7029392"
    ],
    "tgn:id":2501074,
    "tgn:name":"McGaw",
    "tgn:placetype":[
        "aat:300008347"
    ]
},
  "bbox": [],
  "geometry": {"coordinates":[-83.2167,38.6333],"type":"Point"}
}