{
  "id": 7120321,
  "type": "Feature",
  "properties": {
    "tgn:hierarchy":[
        "tgn:7120321",
        "tgn:1000003",
        "tgn:7003685",
        "tgn:7000084",
        "tgn:7029392"
    ],
    "tgn:id":7120321,
    "tgn:name":"F\u00f6rsterei Pechh\u00fctte",
    "tgn:placetype":[
        "aat:300004792"
    ]
},
  "bbox": [],
  "geometry": {"coordinates":[12.75,51.616667],"type":"Point"}
}