{
  "id": 2755843,
  "type": "Feature",
  "properties": {
    "tgn:hierarchy":[
        "tgn:2755843",
        "tgn:1000001",
        "tgn:7012149",
        "tgn:2000372",
        "tgn:7007248",
        "tgn:7029392"
    ],
    "tgn:id":2755843,
    "tgn:name":"Weeks Lake",
    "tgn:placetype":[
        "aat:300006191"
    ]
},
  "bbox": [],
  "geometry": {"coordinates":[-82.3833,32.8833],"type":"Point"}
}