{
  "id": 2262613,
  "type": "Feature",
  "properties": {
    "tgn:hierarchy":[
        "tgn:2262613",
        "tgn:1000001",
        "tgn:2000921",
        "tgn:7012149",
        "tgn:7007515",
        "tgn:7029392"
    ],
    "tgn:id":2262613,
    "tgn:name":"Cow Pond",
    "tgn:placetype":[
        "aat:300008680"
    ]
},
  "bbox": [],
  "geometry": {"coordinates":[-70.6333,45.0333],"type":"Point"}
}