{
  "id": 2477466,
  "type": "Feature",
  "properties": {
    "tgn:hierarchy":[
        "tgn:2477466",
        "tgn:1000001",
        "tgn:7012149",
        "tgn:2001901",
        "tgn:7007825",
        "tgn:7029392"
    ],
    "tgn:id":2477466,
    "tgn:name":"Lyons Knob",
    "tgn:placetype":[
        "aat:300008798"
    ]
},
  "bbox": [],
  "geometry": {"coordinates":[-84.7833,36.2833],"type":"Point"}
}