{
  "id": 7070532,
  "type": "Feature",
  "properties": {
    "tgn:hierarchy":[
        "tgn:7070532",
        "tgn:7003692",
        "tgn:1000003",
        "tgn:7000084",
        "tgn:7029392"
    ],
    "tgn:id":7070532,
    "tgn:name":"Steinach",
    "tgn:placetype":[
        "aat:300008699"
    ]
},
  "bbox": [],
  "geometry": {"coordinates":[9.333333,48.633333],"type":"Point"}
}