{
  "id": 2100217,
  "type": "Feature",
  "properties": {
    "tgn:hierarchy":[
        "tgn:2100217",
        "tgn:1000001",
        "tgn:7012149",
        "tgn:2001860",
        "tgn:7007825",
        "tgn:7029392"
    ],
    "tgn:id":2100217,
    "tgn:name":"Macon",
    "tgn:placetype":[
        "aat:300008347"
    ]
},
  "bbox": [],
  "geometry": {"coordinates":[-89.4833,35.15],"type":"Point"}
}