{
  "id": 7268999,
  "type": "Feature",
  "properties": {
    "tgn:hierarchy":[
        "tgn:7268999",
        "tgn:1000003",
        "tgn:7003613",
        "tgn:7016845",
        "tgn:7029392"
    ],
    "tgn:id":7268999,
    "tgn:name:nl":"Oude Diepje",
    "tgn:placetype":[
        "aat:300006075"
    ]
},
  "bbox": [],
  "geometry": {"coordinates":[6.25,53.15],"type":"Point"}
}