{
  "id": 2719083,
  "type": "Feature",
  "properties": {
    "tgn:hierarchy":[
        "tgn:2719083",
        "tgn:1000001",
        "tgn:7012149",
        "tgn:2002284",
        "tgn:7013961",
        "tgn:7029392"
    ],
    "tgn:id":2719083,
    "tgn:name":"Thorny Knob",
    "tgn:placetype":[
        "aat:300008798"
    ]
},
  "bbox": [],
  "geometry": {"coordinates":[-80.6333,38.2167],"type":"Point"}
}