{
  "id": 2560149,
  "type": "Feature",
  "properties": {
    "tgn:hierarchy":[
        "tgn:2560149",
        "tgn:1000001",
        "tgn:2000776",
        "tgn:7012149",
        "tgn:7007255",
        "tgn:7029392"
    ],
    "tgn:id":2560149,
    "tgn:name":"Orange Hill",
    "tgn:placetype":[
        "aat:300008798"
    ]
},
  "bbox": [],
  "geometry": {"coordinates":[-87.7167,37.15],"type":"Point"}
}