{
  "id": 7016574,
  "type": "Feature",
  "properties": {
    "tgn:hierarchy":[
        "tgn:7016574",
        "tgn:7001242",
        "tgn:1001689",
        "tgn:1000203",
        "tgn:7029392"
    ],
    "tgn:id":7016574,
    "tgn:name":"Ujiji",
    "tgn:placetype":[
        "aat:300008347",
        "aat:300008375"
    ]
},
  "bbox": [],
  "geometry": {"coordinates":[29.65,-4.9167],"type":"Point"}
}