{
  "id": 7312782,
  "type": "Feature",
  "properties": {
    "tgn:hierarchy":[
        "tgn:7312782",
        "tgn:1001695",
        "tgn:1000049",
        "tgn:1000002",
        "tgn:7029392"
    ],
    "tgn:id":7312782,
    "tgn:name":"La Punta",
    "tgn:placetype":[
        "aat:300008347"
    ]
},
  "bbox": [],
  "geometry": {"coordinates":[-70.916667,-34.416667],"type":"Point"}
}