{
  "id": 7404262,
  "type": "Feature",
  "properties": {
    "tgn:hierarchy":[
        "tgn:7404262",
        "tgn:7005578",
        "tgn:1000001",
        "tgn:7005560",
        "tgn:7029392"
    ],
    "tgn:id":7404262,
    "tgn:name":"San Francisco",
    "tgn:placetype":[
        "aat:300008347"
    ]
},
  "bbox": [],
  "geometry": {"coordinates":[-90.95,18.75],"type":"Point"}
}