<<<<<<< HEAD
{
  "id": 2150722,
  "type": "Feature",
  "properties": {
    "tgn:hierarchy":[
        "tgn:2150722",
        "tgn:1002165",
        "tgn:1000001",
        "tgn:7012149",
        "tgn:7007517",
        "tgn:7029392"
    ],
    "tgn:id":2150722,
    "tgn:name":"Bass Creek",
    "tgn:placetype":[
        "aat:300008706"
    ]
},
  "bbox": [],
  "geometry": {"coordinates":[-70.2333,41.7167],"type":"Point"}
}
=======
{"geometry":{"type":"Point","coordinates":[-70.233300,41.716700]},"type":"Feature","properties":{"hierarchy":["tgn:2150722","tgn:1002165","tgn:1000001","tgn:7012149","tgn:7007517","tgn:7029392"],"placetype":["aat:300008706"],"id":2150722,"name:xx":"Bass Creek"}}
>>>>>>> 03f74aca74312dbeaf24d7e61306dd6a786dc3d0
