{
  "id": 7407474,
  "type": "Feature",
  "properties": {
    "tgn:hierarchy":[
        "tgn:7407474",
        "tgn:1000001",
        "tgn:7005590",
        "tgn:7005560",
        "tgn:7029392"
    ],
    "tgn:id":7407474,
    "tgn:name":"Cerro Colorado",
    "tgn:placetype":[
        "aat:300008347"
    ]
},
  "bbox": [],
  "geometry": {"coordinates":[-100.472222,19.316667],"type":"Point"}
}