{
  "id": 7291424,
  "type": "Feature",
  "properties": {
    "tgn:hierarchy":[
        "tgn:7291424",
        "tgn:7002464",
        "tgn:1000049",
        "tgn:1000002",
        "tgn:7029392"
    ],
    "tgn:id":7291424,
    "tgn:name":"E. S\u00e1nchez",
    "tgn:placetype":[
        "aat:300008347"
    ]
},
  "bbox": [],
  "geometry": {"coordinates":[-68.633333,-19.883333],"type":"Point"}
}