{
  "id": 7566165,
  "type": "Feature",
  "properties": {
    "tgn:hierarchy":[
        "tgn:7566165",
        "tgn:1000004",
        "tgn:1001832",
        "tgn:7000198",
        "tgn:7029392"
    ],
    "tgn:id":7566165,
    "tgn:name:en":"Bhomrab\u012bl",
    "tgn:placetype":[
        "aat:300008347"
    ]
},
  "bbox": [],
  "geometry": {"coordinates":[89.904058,26.465159],"type":"Point"}
}