{
  "id": 2169243,
  "type": "Feature",
  "properties": {
    "tgn:hierarchy":[
        "tgn:2169243",
        "tgn:1000001",
        "tgn:7012149",
        "tgn:7007157",
        "tgn:1002858",
        "tgn:7029392"
    ],
    "tgn:id":2169243,
    "tgn:name":"Big Lake",
    "tgn:placetype":[
        "aat:300008680"
    ]
},
  "bbox": [],
  "geometry": {"coordinates":[-116.6833,33.2667],"type":"Point"}
}