{
  "id": 1135264,
  "type": "Feature",
  "properties": {
    "tgn:hierarchy":[
        "tgn:1135264",
        "tgn:1000001",
        "tgn:1002903",
        "tgn:7012149",
        "tgn:7007565",
        "tgn:7029392"
    ],
    "tgn:id":1135264,
    "tgn:name":"Hoopstick Brook",
    "tgn:placetype":[
        "aat:300008703"
    ]
},
  "bbox": [],
  "geometry": {"coordinates":[-74.6833,40.6833],"type":"Point"}
}