{
  "id": 2445768,
  "type": "Feature",
  "properties": {
    "tgn:hierarchy":[
        "tgn:2445768",
        "tgn:1000001",
        "tgn:2001411",
        "tgn:7012149",
        "tgn:7007526",
        "tgn:7029392"
    ],
    "tgn:id":2445768,
    "tgn:name":"Leppy Peak",
    "tgn:placetype":[
        "aat:300008798"
    ]
},
  "bbox": [],
  "geometry": {"coordinates":[-114.0667,40.7667],"type":"Point"}
}