{
  "id": 7441043,
  "type": "Feature",
  "properties": {
    "tgn:hierarchy":[
        "tgn:7441043",
        "tgn:1000001",
        "tgn:1001960",
        "tgn:7005560",
        "tgn:7029392"
    ],
    "tgn:id":7441043,
    "tgn:name":"San Lucas",
    "tgn:placetype":[
        "aat:300008347"
    ]
},
  "bbox": [],
  "geometry": {"coordinates":[-109.483333,29.133333],"type":"Point"}
}