{
  "id": 2655267,
  "type": "Feature",
  "properties": {
    "tgn:hierarchy":[
        "tgn:2655267",
        "tgn:1000001",
        "tgn:7012149",
        "tgn:2001909",
        "tgn:7007825",
        "tgn:7029392"
    ],
    "tgn:id":2655267,
    "tgn:name":"Shanty Branch",
    "tgn:placetype":[
        "aat:300008699"
    ]
},
  "bbox": [],
  "geometry": {"coordinates":[-84.5667,35.8833],"type":"Point"}
}