{
  "id": 7565982,
  "type": "Feature",
  "properties": {
    "tgn:hierarchy":[
        "tgn:7565982",
        "tgn:1000004",
        "tgn:7000198",
        "tgn:7016722",
        "tgn:7029392"
    ],
    "tgn:id":7565982,
    "tgn:name:en":"Purwa R\u0101wat",
    "tgn:placetype":[
        "aat:300008347"
    ]
},
  "bbox": [],
  "geometry": {"coordinates":[79.712549,26.760158],"type":"Point"}
}