{
  "id": 7451270,
  "type": "Feature",
  "properties": {
    "tgn:hierarchy":[
        "tgn:7451270",
        "tgn:7002444",
        "tgn:1000003",
        "tgn:7008082",
        "tgn:7008591",
        "tgn:7029392"
    ],
    "tgn:id":7451270,
    "tgn:name:en":"Galmisdale",
    "tgn:placetype":[
        "aat:300008347"
    ]
},
  "bbox": [],
  "geometry": {"coordinates":[-6.15,56.866667],"type":"Point"}
}