{
  "id": 7277234,
  "type": "Feature",
  "properties": {
    "tgn:hierarchy":[
        "tgn:7277234",
        "tgn:1001623",
        "tgn:1000049",
        "tgn:1000002",
        "tgn:7029392"
    ],
    "tgn:id":7277234,
    "tgn:name":"Cerro Tolva",
    "tgn:placetype":[
        "aat:300008795"
    ]
},
  "bbox": [],
  "geometry": {"coordinates":[-72.356667,-43.811111],"type":"Point"}
}