{
  "id": 7498091,
  "type": "Feature",
  "properties": {
    "tgn:hierarchy":[
        "tgn:7498091",
        "tgn:7469009",
        "tgn:1000004",
        "tgn:1000141",
        "tgn:7029392"
    ],
    "tgn:id":7498091,
    "tgn:name":"Ma Shan",
    "tgn:placetype":[
        "aat:300008795"
    ]
},
  "bbox": [],
  "geometry": {"coordinates":[118.408993,24.528659],"type":"Point"}
}