{
  "id": 2526829,
  "type": "Feature",
  "properties": {
    "tgn:hierarchy":[
        "tgn:2526829",
        "tgn:1000001",
        "tgn:7012149",
        "tgn:2000926",
        "tgn:7007515",
        "tgn:7029392"
    ],
    "tgn:id":2526829,
    "tgn:name":"Moulton Ridge",
    "tgn:placetype":[
        "aat:300266640"
    ]
},
  "bbox": [],
  "geometry": {"coordinates":[-70.9333,43.8333],"type":"Point"}
}