{
  "id": 7563637,
  "type": "Feature",
  "properties": {
    "tgn:hierarchy":[
        "tgn:7563637",
        "tgn:1000004",
        "tgn:7000198",
        "tgn:7016788",
        "tgn:7029392"
    ],
    "tgn:id":7563637,
    "tgn:name":"Chhota Jh\u0101rsar",
    "tgn:placetype":[
        "aat:300008347"
    ]
},
  "bbox": [],
  "geometry": {"coordinates":[74.949333,28.828144],"type":"Point"}
}