<<<<<<< HEAD
{
  "id": 2251476,
  "type": "Feature",
  "properties": {
    "tgn:hierarchy":[
        "tgn:2251476",
        "tgn:1002157",
        "tgn:1000001",
        "tgn:7012149",
        "tgn:7007565",
        "tgn:7029392"
    ],
    "tgn:id":2251476,
    "tgn:name":"Commando Creek",
    "tgn:placetype":[
        "aat:300008706"
    ]
},
  "bbox": [],
  "geometry": {"coordinates":[-74.6667,39.3],"type":"Point"}
}
=======
{"geometry":{"type":"Point","coordinates":[-74.666700,39.300000]},"type":"Feature","properties":{"hierarchy":["tgn:2251476","tgn:1002157","tgn:1000001","tgn:7012149","tgn:7007565","tgn:7029392"],"placetype":["aat:300008706"],"id":2251476,"name:xx":"Commando Creek"}}
>>>>>>> 03f74aca74312dbeaf24d7e61306dd6a786dc3d0
