{
  "id": 2235618,
  "type": "Feature",
  "properties": {
    "tgn:hierarchy":[
        "tgn:2235618",
        "tgn:1000001",
        "tgn:1002724",
        "tgn:7012149",
        "tgn:7007517",
        "tgn:7029392"
    ],
    "tgn:id":2235618,
    "tgn:name":"Chestnut Hill",
    "tgn:placetype":[
        "aat:300008798"
    ]
},
  "bbox": [],
  "geometry": {"coordinates":[-71.1667,42.1333],"type":"Point"}
}