{
  "id": 2718930,
  "type": "Feature",
  "properties": {
    "tgn:hierarchy":[
        "tgn:2718930",
        "tgn:1000001",
        "tgn:7012149",
        "tgn:2000183",
        "tgn:7007157",
        "tgn:7029392"
    ],
    "tgn:id":2718930,
    "tgn:name":"Thorndyke Mine",
    "tgn:placetype":[
        "aat:300000390"
    ]
},
  "bbox": [],
  "geometry": {"coordinates":[-117.8167,36.1667],"type":"Point"}
}