<<<<<<< HEAD
{
  "id": 2404003,
  "type": "Feature",
  "properties": {
    "tgn:hierarchy":[
        "tgn:2404003",
        "tgn:1000001",
        "tgn:7012149",
        "tgn:7007826",
        "tgn:7029392"
    ],
    "tgn:id":2404003,
    "tgn:name":"Howell Hollow",
    "tgn:placetype":[
        "aat:300008761"
    ]
},
  "bbox": [],
  "geometry": {"coordinates":[-97.4,29.25],"type":"Point"}
}
=======
{"geometry":{"type":"Point","coordinates":[-97.400000,29.250000]},"type":"Feature","properties":{"hierarchy":["tgn:2404003","tgn:1000001","tgn:7012149","tgn:7007826","tgn:7029392"],"placetype":["aat:300008761"],"id":2404003,"name:xx":"Howell Hollow"}}
>>>>>>> 03f74aca74312dbeaf24d7e61306dd6a786dc3d0
