{
  "id": 1009318,
  "type": "Feature",
  "properties": {
    "tgn:hierarchy":[
        "tgn:1009318",
        "tgn:1000003",
        "tgn:1000431",
        "tgn:7006278",
        "tgn:7029392"
    ],
    "tgn:id":1009318,
    "tgn:name":"Szentendrei-sziget",
    "tgn:placetype":[
        "aat:300008791"
    ]
},
  "bbox": [],
  "geometry": {"coordinates":[19.1167,47.7167],"type":"Point"}
}