{
  "id": 7533503,
  "type": "Feature",
  "properties": {
    "tgn:hierarchy":[
        "tgn:7533503",
        "tgn:7001242",
        "tgn:7016833",
        "tgn:7001334",
        "tgn:7029392"
    ],
    "tgn:id":7533503,
    "tgn:name:en":"Listikhr\u012bb, 'Ayn",
    "tgn:placetype":[
        "aat:300008697"
    ]
},
  "bbox": [],
  "geometry": {"coordinates":[30.533333,25.333333],"type":"Point"}
}