{
  "id": 7496935,
  "type": "Feature",
  "properties": {
    "tgn:hierarchy":[
        "tgn:7496935",
        "tgn:1000004",
        "tgn:1000959",
        "tgn:1000141",
        "tgn:7029392"
    ],
    "tgn:id":7496935,
    "tgn:name":"Wuyin Si",
    "tgn:placetype":[
        "aat:300007595"
    ]
},
  "bbox": [],
  "geometry": {"coordinates":[121.57842,25.02698],"type":"Point"}
}