<<<<<<< HEAD
{
  "id": 7248502,
  "type": "Feature",
  "properties": {
    "tgn:hierarchy":[
        "tgn:7248502",
        "tgn:7003457",
        "tgn:1000003",
        "tgn:1000063",
        "tgn:7018236",
        "tgn:7029392"
    ],
    "tgn:id":7248502,
    "tgn:name":"Beverbeek",
    "tgn:placetype":[
        "aat:300008699"
    ]
},
  "bbox": [],
  "geometry": {"coordinates":[3.95,50.75],"type":"Point"}
}
=======
{"geometry":{"type":"Point","coordinates":[3.950000,50.750000]},"type":"Feature","properties":{"hierarchy":["tgn:7248502","tgn:7003457","tgn:1000003","tgn:1000063","tgn:7018236","tgn:7029392"],"placetype":["aat:300008699"],"id":7248502,"name:xx":"Beverbeek"}}
>>>>>>> 03f74aca74312dbeaf24d7e61306dd6a786dc3d0
