{
  "id": 7060836,
  "type": "Feature",
  "properties": {
    "tgn:hierarchy":[
        "tgn:7060836",
        "tgn:1000003",
        "tgn:7003688",
        "tgn:7000084",
        "tgn:7029392"
    ],
    "tgn:id":7060836,
    "tgn:name":"Alt M\u00f6lln",
    "tgn:placetype":[
        "aat:300008347"
    ]
},
  "bbox": [],
  "geometry": {"coordinates":[10.65,53.616667],"type":"Point"}
}