{
  "id": 7025918,
  "type": "Feature",
  "properties": {
    "tgn:hierarchy":[
        "tgn:7025918",
        "tgn:7002445",
        "tgn:1000003",
        "tgn:7011961",
        "tgn:7008591",
        "tgn:7029392"
    ],
    "tgn:id":7025918,
    "tgn:name:ang":"Circel",
    "tgn:placetype":[
        "aat:300008347",
        "aat:300008372"
    ]
},
  "bbox": [],
  "geometry": {"coordinates":[-2.033333,50.883333],"type":"Point"}
}