{
  "id": 7428045,
  "type": "Feature",
  "properties": {
    "tgn:hierarchy":[
        "tgn:7428045",
        "tgn:1000001",
        "tgn:7005601",
        "tgn:7005560",
        "tgn:7029392"
    ],
    "tgn:id":7428045,
    "tgn:name":"L\u00e1zaro C\u00e1rdenas",
    "tgn:placetype":[
        "aat:300008347"
    ]
},
  "bbox": [],
  "geometry": {"coordinates":[-103.791667,23.533333],"type":"Point"}
}