{
  "id": 7259629,
  "type": "Feature",
  "properties": {
    "tgn:hierarchy":[
        "tgn:7259629",
        "tgn:7003456",
        "tgn:1000003",
        "tgn:1000063",
        "tgn:7018236",
        "tgn:7029392"
    ],
    "tgn:id":7259629,
    "tgn:name":"Waterbroekloop",
    "tgn:placetype":[
        "aat:300008699"
    ]
},
  "bbox": [],
  "geometry": {"coordinates":[5.033333,51.183333],"type":"Point"}
}