{
  "id": 7393260,
  "type": "Feature",
  "properties": {
    "tgn:hierarchy":[
        "tgn:7393260",
        "tgn:1000001",
        "tgn:7005590",
        "tgn:7005560",
        "tgn:7029392"
    ],
    "tgn:id":7393260,
    "tgn:name":"San Juan del Fuerte",
    "tgn:placetype":[
        "aat:300008347"
    ]
},
  "bbox": [],
  "geometry": {"coordinates":[-102.05,20.366667],"type":"Point"}
}