{
  "id": 7184259,
  "type": "Feature",
  "properties": {
    "tgn:hierarchy":[
        "tgn:7184259",
        "tgn:1000003",
        "tgn:7003688",
        "tgn:7000084",
        "tgn:7029392"
    ],
    "tgn:id":7184259,
    "tgn:name":"G\u00f6theby-Holm",
    "tgn:placetype":[
        "aat:300387173"
    ]
},
  "bbox": [],
  "geometry": {"coordinates":[9.716667,54.483333],"type":"Point"}
}