{
  "id": 2643695,
  "type": "Feature",
  "properties": {
    "tgn:hierarchy":[
        "tgn:2643695",
        "tgn:1000001",
        "tgn:1002225",
        "tgn:7012149",
        "tgn:7007710",
        "tgn:7029392"
    ],
    "tgn:id":2643695,
    "tgn:name":"Sandy Run Reservoir",
    "tgn:placetype":[
        "aat:300006191"
    ]
},
  "bbox": [],
  "geometry": {"coordinates":[-78.4667,40.65],"type":"Point"}
}