{
  "id": 1103609,
  "type": "Feature",
  "properties": {
    "tgn:hierarchy":[
        "tgn:1103609",
        "tgn:1002058",
        "tgn:1000004",
        "tgn:1000121",
        "tgn:7029392"
    ],
    "tgn:id":1103609,
    "tgn:name":"\u1e0cab\u0101b, Jabal a\u1e0d-",
    "tgn:placetype":[
        "aat:300008795"
    ]
},
  "bbox": [],
  "geometry": {"coordinates":[35.6333,31.0333],"type":"Point"}
}