{
  "id": 7096472,
  "type": "Feature",
  "properties": {
    "tgn:hierarchy":[
        "tgn:7096472",
        "tgn:1000003",
        "tgn:7000094",
        "tgn:7000084",
        "tgn:7029392"
    ],
    "tgn:id":7096472,
    "tgn:name":"Siedenb\u00fcssow",
    "tgn:placetype":[
        "aat:300008347"
    ]
},
  "bbox": [],
  "geometry": {"coordinates":[13.266667,53.85],"type":"Point"}
}