<<<<<<< HEAD
{
  "id": 2404601,
  "type": "Feature",
  "properties": {
    "tgn:hierarchy":[
        "tgn:2404601",
        "tgn:1000001",
        "tgn:2001411",
        "tgn:7012149",
        "tgn:7007526",
        "tgn:7029392"
    ],
    "tgn:id":2404601,
    "tgn:name":"Huber Hills",
    "tgn:placetype":[
        "aat:300008798"
    ]
},
  "bbox": [],
  "geometry": {"coordinates":[-115.9,41.8333],"type":"Point"}
}
=======
{"geometry":{"type":"Point","coordinates":[-115.900000,41.833300]},"type":"Feature","properties":{"hierarchy":["tgn:2404601","tgn:1000001","tgn:2001411","tgn:7012149","tgn:7007526","tgn:7029392"],"placetype":["aat:300008798"],"id":2404601,"name:xx":"Huber Hills"}}
>>>>>>> 03f74aca74312dbeaf24d7e61306dd6a786dc3d0
