<<<<<<< HEAD
{
  "id": 7489802,
  "type": "Feature",
  "properties": {
    "tgn:hierarchy":[
        "tgn:7489802",
        "tgn:7001004",
        "tgn:1000004",
        "tgn:1000141",
        "tgn:7029392"
    ],
    "tgn:id":7489802,
    "tgn:name":"Shezhixing",
    "tgn:placetype":[
        "aat:300008347"
    ]
},
  "bbox": [],
  "geometry": {"coordinates":[120.367593,22.690198],"type":"Point"}
}
=======
{"geometry":{"type":"Point","coordinates":[120.367593,22.690198]},"type":"Feature","properties":{"hierarchy":["tgn:7489802","tgn:7001004","tgn:1000004","tgn:1000141","tgn:7029392"],"placetype":["aat:300008347"],"id":7489802,"name:xx":"Shezhixing"}}
>>>>>>> 03f74aca74312dbeaf24d7e61306dd6a786dc3d0
