<<<<<<< HEAD
{
  "id": 7176857,
  "type": "Feature",
  "properties": {
    "tgn:hierarchy":[
        "tgn:7176857",
        "tgn:7003692",
        "tgn:1000003",
        "tgn:7000084",
        "tgn:7029392"
    ],
    "tgn:id":7176857,
    "tgn:name":"Hardt",
    "tgn:placetype":[
        "aat:300008863"
    ]
},
  "bbox": [],
  "geometry": {"coordinates":[9.033333,49.45],"type":"Point"}
}
=======
{"geometry":{"type":"Point","coordinates":[9.033333,49.450000]},"type":"Feature","properties":{"hierarchy":["tgn:7176857","tgn:7003692","tgn:1000003","tgn:7000084","tgn:7029392"],"placetype":["aat:300008863"],"id":7176857,"name:xx":"Hardt"}}
>>>>>>> 03f74aca74312dbeaf24d7e61306dd6a786dc3d0
