{
  "id": 2352461,
  "type": "Feature",
  "properties": {
    "tgn:hierarchy":[
        "tgn:2352461",
        "tgn:1000001",
        "tgn:7012149",
        "tgn:2001657",
        "tgn:7007707",
        "tgn:7029392"
    ],
    "tgn:id":2352461,
    "tgn:name":"Goat Island",
    "tgn:placetype":[
        "aat:300008791"
    ]
},
  "bbox": [],
  "geometry": {"coordinates":[-96.5667,34.1167],"type":"Point"}
}