{
  "id": 2288902,
  "type": "Feature",
  "properties": {
    "tgn:hierarchy":[
        "tgn:2288902",
        "tgn:1000001",
        "tgn:7012149",
        "tgn:2001227",
        "tgn:7007523",
        "tgn:7029392"
    ],
    "tgn:id":2288902,
    "tgn:name":"Ditch Number 84",
    "tgn:placetype":[
        "aat:300006075"
    ]
},
  "bbox": [],
  "geometry": {"coordinates":[-89.9333,36.3333],"type":"Point"}
}