{
  "id": 2554528,
  "type": "Feature",
  "properties": {
    "tgn:hierarchy":[
        "tgn:2554528",
        "tgn:1000001",
        "tgn:7014090",
        "tgn:7012149",
        "tgn:7007565",
        "tgn:7029392"
    ],
    "tgn:id":2554528,
    "tgn:name":"Oakland Mills",
    "tgn:placetype":[
        "aat:300008347"
    ]
},
  "bbox": [],
  "geometry": {"coordinates":[-74.3333,40.2167],"type":"Point"}
}