{
  "id": 2241404,
  "type": "Feature",
  "properties": {
    "tgn:hierarchy":[
        "tgn:2241404",
        "tgn:1002808",
        "tgn:1000001",
        "tgn:7012149",
        "tgn:7007711",
        "tgn:7029392"
    ],
    "tgn:id":2241404,
    "tgn:name":"Clark Pond",
    "tgn:placetype":[
        "aat:300006191"
    ]
},
  "bbox": [],
  "geometry": {"coordinates":[-71.7667,41.7667],"type":"Point"}
}