{
  "id": 1033234,
  "type": "Feature",
  "properties": {
    "tgn:hierarchy":[
        "tgn:1033234",
        "tgn:1000003",
        "tgn:7002885",
        "tgn:1000070",
        "tgn:7029392"
    ],
    "tgn:id":1033234,
    "tgn:name":"Ganges",
    "tgn:placetype":[
        "aat:300008347"
    ]
},
  "bbox": [],
  "geometry": {"coordinates":[3.7167,43.9333],"type":"Point"}
}