{
  "id": 2314855,
  "type": "Feature",
  "properties": {
    "tgn:hierarchy":[
        "tgn:2314855",
        "tgn:1000001",
        "tgn:7012149",
        "tgn:2002382",
        "tgn:7007923",
        "tgn:7029392"
    ],
    "tgn:id":2314855,
    "tgn:name":"Elkhorn Ditch",
    "tgn:placetype":[
        "aat:300006075"
    ]
},
  "bbox": [],
  "geometry": {"coordinates":[-109.25,42.4667],"type":"Point"}
}