{
  "id": 1123609,
  "type": "Feature",
  "properties": {
    "tgn:hierarchy":[
        "tgn:1123609",
        "tgn:7002445",
        "tgn:1000003",
        "tgn:7008117",
        "tgn:7008591",
        "tgn:7029392"
    ],
    "tgn:id":1123609,
    "tgn:name:en":"Eamont",
    "tgn:placetype":[
        "aat:300008707",
        "aat:300008699"
    ]
},
  "bbox": [],
  "geometry": {"coordinates":[-2.616667,54.666667],"type":"Point"}
}