{
  "id": 2312916,
  "type": "Feature",
  "properties": {
    "tgn:hierarchy":[
        "tgn:2312916",
        "tgn:1000001",
        "tgn:7012149",
        "tgn:2001449",
        "tgn:7007566",
        "tgn:7029392"
    ],
    "tgn:id":2312916,
    "tgn:name":"El Vado Reservoir",
    "tgn:placetype":[
        "aat:300006191"
    ]
},
  "bbox": [],
  "geometry": {"coordinates":[-106.7167,36.5833],"type":"Point"}
}