{
  "id": 2495382,
  "type": "Feature",
  "properties": {
    "tgn:hierarchy":[
        "tgn:2495382",
        "tgn:2001001",
        "tgn:1000001",
        "tgn:7012149",
        "tgn:7007521",
        "tgn:7029392"
    ],
    "tgn:id":2495382,
    "tgn:name":"Mary Yellowhead Lake",
    "tgn:placetype":[
        "aat:300008680"
    ]
},
  "bbox": [],
  "geometry": {"coordinates":[-95.6667,47.0167],"type":"Point"}
}