{
  "id": 7226769,
  "type": "Feature",
  "properties": {
    "tgn:hierarchy":[
        "tgn:7226769",
        "tgn:7002728",
        "tgn:7002715",
        "tgn:1000003",
        "tgn:1000074",
        "tgn:7029392"
    ],
    "tgn:id":7226769,
    "tgn:name":"Moglen\u00edtsas Potam\u00f3s",
    "tgn:placetype":[
        "aat:300008699"
    ]
},
  "bbox": [],
  "geometry": {"coordinates":[22.185278,40.785278],"type":"Point"}
}