{
  "id": 7257762,
  "type": "Feature",
  "properties": {
    "tgn:hierarchy":[
        "tgn:7257762",
        "tgn:7003456",
        "tgn:1000003",
        "tgn:1000063",
        "tgn:7018236",
        "tgn:7029392"
    ],
    "tgn:id":7257762,
    "tgn:name":"Wolvenbos",
    "tgn:placetype":[
        "aat:300008863"
    ]
},
  "bbox": [],
  "geometry": {"coordinates":[4.461488,51.335131],"type":"Point"}
}