<<<<<<< HEAD
{
  "id": 7376352,
  "type": "Feature",
  "properties": {
    "tgn:hierarchy":[
        "tgn:7376352",
        "tgn:1000001",
        "tgn:7005595",
        "tgn:7005560",
        "tgn:7029392"
    ],
    "tgn:id":7376352,
    "tgn:name":"Las Juntas, Arroyo",
    "tgn:placetype":[
        "aat:300008699"
    ]
},
  "bbox": [],
  "geometry": {"coordinates":[-108.34,26.952778],"type":"Point"}
}
=======
{"geometry":{"type":"Point","coordinates":[-108.340000,26.952778]},"type":"Feature","properties":{"hierarchy":["tgn:7376352","tgn:1000001","tgn:7005595","tgn:7005560","tgn:7029392"],"placetype":["aat:300008699"],"id":7376352,"name:xx":"Las Juntas, Arroyo"}}
>>>>>>> 03f74aca74312dbeaf24d7e61306dd6a786dc3d0
