{
  "id": 7139119,
  "type": "Feature",
  "properties": {
    "tgn:hierarchy":[
        "tgn:7139119",
        "tgn:1000003",
        "tgn:7003684",
        "tgn:7000084",
        "tgn:7029392"
    ],
    "tgn:id":7139119,
    "tgn:name":"Leist-Berg",
    "tgn:placetype":[
        "aat:300008777"
    ]
},
  "bbox": [],
  "geometry": {"coordinates":[7.083333,49.533333],"type":"Point"}
}