{
  "id": 2118741,
  "type": "Feature",
  "properties": {
    "tgn:hierarchy":[
        "tgn:2118741",
        "tgn:1000001",
        "tgn:7012149",
        "tgn:2002296",
        "tgn:7013961",
        "tgn:7029392"
    ],
    "tgn:id":2118741,
    "tgn:name":"Jenningston",
    "tgn:placetype":[
        "aat:300008347",
        "aat:300387210"
    ]
},
  "bbox": [],
  "geometry": {"coordinates":[-79.5167,38.9833],"type":"Point"}
}