{
  "id": 1044190,
  "type": "Feature",
  "properties": {
    "tgn:hierarchy":[
        "tgn:1044190",
        "tgn:7002991",
        "tgn:1000003",
        "tgn:7002997",
        "tgn:1000080",
        "tgn:7029392"
    ],
    "tgn:id":1044190,
    "tgn:name":"Cesiomaggiore",
    "tgn:placetype":[
        "aat:300008347"
    ]
},
  "bbox": [],
  "geometry": {"coordinates":[11.983333,46.083333],"type":"Point"}
}