{
  "id": 2472050,
  "type": "Feature",
  "properties": {
    "tgn:hierarchy":[
        "tgn:2472050",
        "tgn:1000001",
        "tgn:7012149",
        "tgn:2000912",
        "tgn:7007256",
        "tgn:7029392"
    ],
    "tgn:id":2472050,
    "tgn:name":"Lott Lake",
    "tgn:placetype":[
        "aat:300008680"
    ]
},
  "bbox": [],
  "geometry": {"coordinates":[-89.75,30.9167],"type":"Point"}
}