{
  "id": 2084735,
  "type": "Feature",
  "properties": {
    "tgn:hierarchy":[
        "tgn:2084735",
        "tgn:1000001",
        "tgn:1002270",
        "tgn:7012149",
        "tgn:7007708",
        "tgn:7029392"
    ],
    "tgn:id":2084735,
    "tgn:name":"Faubion",
    "tgn:placetype":[
        "aat:300008347"
    ]
},
  "bbox": [],
  "geometry": {"coordinates":[-121.9333,45.3333],"type":"Point"}
}