{
  "id": 2774286,
  "type": "Feature",
  "properties": {
    "tgn:hierarchy":[
        "tgn:2774286",
        "tgn:1000001",
        "tgn:7012149",
        "tgn:2001719",
        "tgn:7007708",
        "tgn:7029392"
    ],
    "tgn:id":2774286,
    "tgn:name":"Willow Forks",
    "tgn:placetype":[
        "aat:300008347"
    ]
},
  "bbox": [],
  "geometry": {"coordinates":[-119.7667,45.4833],"type":"Point"}
}