{
  "id": 7588667,
  "type": "Feature",
  "properties": {
    "tgn:hierarchy":[
        "tgn:7588667",
        "tgn:1000004",
        "tgn:7000198",
        "tgn:7000799",
        "tgn:7029392"
    ],
    "tgn:id":7588667,
    "tgn:name:en":"N\u016brpur",
    "tgn:placetype":[
        "aat:300008347"
    ]
},
  "bbox": [],
  "geometry": {"coordinates":[74.215462,33.812421],"type":"Point"}
}