{
  "id": 2231575,
  "type": "Feature",
  "properties": {
    "tgn:hierarchy":[
        "tgn:2231575",
        "tgn:1000001",
        "tgn:7012149",
        "tgn:7007515",
        "tgn:7029392"
    ],
    "tgn:id":2231575,
    "tgn:name":"Chalk Pond",
    "tgn:placetype":[
        "aat:300008680"
    ]
},
  "bbox": [],
  "geometry": {"coordinates":[-68.0667,44.8167],"type":"Point"}
}