<<<<<<< HEAD
{
  "id": 2404180,
  "type": "Feature",
  "properties": {
    "tgn:hierarchy":[
        "tgn:2404180",
        "tgn:1000001",
        "tgn:7012149",
        "tgn:1002981",
        "tgn:7007826",
        "tgn:7029392"
    ],
    "tgn:id":2404180,
    "tgn:name":"Howth",
    "tgn:placetype":[
        "aat:300008347"
    ]
},
  "bbox": [],
  "geometry": {"coordinates":[-96.05,30.1667],"type":"Point"}
}
=======
{"geometry":{"type":"Point","coordinates":[-96.050000,30.166700]},"type":"Feature","properties":{"hierarchy":["tgn:2404180","tgn:1000001","tgn:7012149","tgn:1002981","tgn:7007826","tgn:7029392"],"placetype":["aat:300008347"],"id":2404180,"name:xx":"Howth"}}
>>>>>>> 03f74aca74312dbeaf24d7e61306dd6a786dc3d0
