{
  "id": 2019269,
  "type": "Feature",
  "properties": {
    "tgn:hierarchy":[
        "tgn:2019269",
        "tgn:1000001",
        "tgn:2000269",
        "tgn:7012149",
        "tgn:7007240",
        "tgn:7029392"
    ],
    "tgn:id":2019269,
    "tgn:name":"Fanning Springs",
    "tgn:placetype":[
        "aat:300008347"
    ]
},
  "bbox": [],
  "geometry": {"coordinates":[-82.9167,29.5833],"type":"Point"}
}