<<<<<<< HEAD
{
  "id": 7171197,
  "type": "Feature",
  "properties": {
    "tgn:hierarchy":[
        "tgn:7171197",
        "tgn:1000003",
        "tgn:7003682",
        "tgn:7000084",
        "tgn:7029392"
    ],
    "tgn:id":7171197,
    "tgn:name":"Herz-Berg",
    "tgn:placetype":[
        "aat:300008777"
    ]
},
  "bbox": [],
  "geometry": {"coordinates":[7.7,50.683333],"type":"Point"}
}
=======
{"geometry":{"type":"Point","coordinates":[7.700000,50.683333]},"type":"Feature","properties":{"hierarchy":["tgn:7171197","tgn:1000003","tgn:7003682","tgn:7000084","tgn:7029392"],"placetype":["aat:300008777"],"id":7171197,"name:xx":"Herz-Berg"}}
>>>>>>> 03f74aca74312dbeaf24d7e61306dd6a786dc3d0
