<<<<<<< HEAD
{
  "id": 7172028,
  "type": "Feature",
  "properties": {
    "tgn:hierarchy":[
        "tgn:7172028",
        "tgn:1000003",
        "tgn:7003678",
        "tgn:7000084",
        "tgn:7029392"
    ],
    "tgn:id":7172028,
    "tgn:name":"Hilders, Forst",
    "tgn:placetype":[
        "aat:300008863"
    ]
},
  "bbox": [],
  "geometry": {"coordinates":[10.05,50.55],"type":"Point"}
}
=======
{"geometry":{"type":"Point","coordinates":[10.050000,50.550000]},"type":"Feature","properties":{"hierarchy":["tgn:7172028","tgn:1000003","tgn:7003678","tgn:7000084","tgn:7029392"],"placetype":["aat:300008863"],"id":7172028,"name:xx":"Hilders, Forst"}}
>>>>>>> 03f74aca74312dbeaf24d7e61306dd6a786dc3d0
