{
  "id": 7009590,
  "type": "Feature",
  "properties": {
    "tgn:hierarchy":[
        "tgn:7009590",
        "tgn:7003646",
        "tgn:1000003",
        "tgn:1000088",
        "tgn:7029392"
    ],
    "tgn:id":7009590,
    "tgn:name":"Rosendal",
    "tgn:placetype":[
        "aat:300008347"
    ]
},
  "bbox": [],
  "geometry": {"coordinates":[6.0167,59.9833],"type":"Point"}
}