{
  "id": 7347096,
  "type": "Feature",
  "properties": {
    "tgn:hierarchy":[
        "tgn:7347096",
        "tgn:7002836",
        "tgn:7016622",
        "tgn:1000003",
        "tgn:1000095",
        "tgn:7029392"
    ],
    "tgn:id":7347096,
    "tgn:name":"Arena, Punta de la",
    "tgn:placetype":[
        "aat:300386846"
    ]
},
  "bbox": [],
  "geometry": {"coordinates":[-18.15,27.766667],"type":"Point"}
}