{
  "id": 7382621,
  "type": "Feature",
  "properties": {
    "tgn:hierarchy":[
        "tgn:7382621",
        "tgn:1001836",
        "tgn:1000001",
        "tgn:7005560",
        "tgn:7029392"
    ],
    "tgn:id":7382621,
    "tgn:name":"Moreno",
    "tgn:placetype":[
        "aat:300008347"
    ]
},
  "bbox": [],
  "geometry": {"coordinates":[-110.766667,24.233333],"type":"Point"}
}