{
  "id": 7251093,
  "type": "Feature",
  "properties": {
    "tgn:hierarchy":[
        "tgn:7251093",
        "tgn:7003458",
        "tgn:1000003",
        "tgn:1000063",
        "tgn:7018236",
        "tgn:7029392"
    ],
    "tgn:id":7251093,
    "tgn:name":"Ramskapelle",
    "tgn:placetype":[
        "aat:300008347"
    ]
},
  "bbox": [],
  "geometry": {"coordinates":[3.250566,51.31511],"type":"Point"}
}