{
  "id": 7496483,
  "type": "Feature",
  "properties": {
    "tgn:hierarchy":[
        "tgn:7496483",
        "tgn:7487020",
        "tgn:1000004",
        "tgn:1000141",
        "tgn:7029392"
    ],
    "tgn:id":7496483,
    "tgn:name":"Guanniuwo",
    "tgn:placetype":[
        "aat:300008347"
    ]
},
  "bbox": [],
  "geometry": {"coordinates":[120.817995,24.358255],"type":"Point"}
}