{
  "id": 2234526,
  "type": "Feature",
  "properties": {
    "tgn:hierarchy":[
        "tgn:2234526",
        "tgn:1000001",
        "tgn:7012149",
        "tgn:2001866",
        "tgn:7007825",
        "tgn:7029392"
    ],
    "tgn:id":2234526,
    "tgn:name":"Cherokee Estates",
    "tgn:placetype":[
        "aat:300008347"
    ]
},
  "bbox": [],
  "geometry": {"coordinates":[-82.8833,36.1667],"type":"Point"}
}