{
  "id": 7019470,
  "type": "Feature",
  "properties": {
    "tgn:hierarchy":[
        "tgn:7019470",
        "tgn:1000001",
        "tgn:7012149",
        "tgn:2001440",
        "tgn:7007566",
        "tgn:7029392"
    ],
    "tgn:id":7019470,
    "tgn:name":"Anita Mine",
    "tgn:placetype":[
        "aat:300000390"
    ]
},
  "bbox": [],
  "geometry": {"coordinates":[-108.75,32.3167],"type":"Point"}
}