{
  "id": 7265947,
  "type": "Feature",
  "properties": {
    "tgn:concordances":{
        "gn:id":"2751230"
    },
    "tgn:hierarchy":[
        "tgn:7265947",
        "tgn:7003619",
        "tgn:1000003",
        "tgn:7016845",
        "tgn:7029392"
    ],
    "tgn:id":7265947,
    "tgn:name:nl":"Mallem",
    "tgn:placetype":[
        "aat:300008347"
    ]
},
  "bbox": [],
  "geometry": {"coordinates":[6.666667,52.116667],"type":"Point"}
}