{
  "id": 1030391,
  "type": "Feature",
  "properties": {
    "tgn:hierarchy":[
        "tgn:1030391",
        "tgn:7002445",
        "tgn:7019021",
        "tgn:1000003",
        "tgn:7008591",
        "tgn:7029392"
    ],
    "tgn:id":1030391,
    "tgn:name:en":"Radstock",
    "tgn:placetype":[
        "aat:300008347"
    ]
},
  "bbox": [],
  "geometry": {"coordinates":[-2.443611,51.293056],"type":"Point"}
}