{
  "id": 7009666,
  "type": "Feature",
  "properties": {
    "tgn:hierarchy":[
        "tgn:7009666",
        "tgn:1000003",
        "tgn:1000070",
        "tgn:7002895",
        "tgn:7029392"
    ],
    "tgn:id":7009666,
    "tgn:name":"Saorge",
    "tgn:placetype":[
        "aat:300008347"
    ]
},
  "bbox": [],
  "geometry": {"coordinates":[7.5667,43.9833],"type":"Point"}
}