{
  "id": 2196458,
  "type": "Feature",
  "properties": {
    "tgn:hierarchy":[
        "tgn:2196458",
        "tgn:1000001",
        "tgn:2002319",
        "tgn:7012149",
        "tgn:7007922",
        "tgn:7029392"
    ],
    "tgn:id":2196458,
    "tgn:name":"Bronken Creek",
    "tgn:placetype":[
        "aat:300008706"
    ]
},
  "bbox": [],
  "geometry": {"coordinates":[-91.7667,45.0833],"type":"Point"}
}