{
  "id": 2316028,
  "type": "Feature",
  "properties": {
    "tgn:hierarchy":[
        "tgn:2316028",
        "tgn:1000001",
        "tgn:7012149",
        "tgn:2001229",
        "tgn:7007523",
        "tgn:7029392"
    ],
    "tgn:id":2316028,
    "tgn:name":"Elm Fork",
    "tgn:placetype":[
        "aat:300008699"
    ]
},
  "bbox": [],
  "geometry": {"coordinates":[-93.4167,38.6667],"type":"Point"}
}