{
  "id": 2693326,
  "type": "Feature",
  "properties": {
    "tgn:hierarchy":[
        "tgn:2693326",
        "tgn:1000001",
        "tgn:1002218",
        "tgn:7012149",
        "tgn:7007157",
        "tgn:7029392"
    ],
    "tgn:id":2693326,
    "tgn:name":"Steifer Mine",
    "tgn:placetype":[
        "aat:300000390"
    ]
},
  "bbox": [],
  "geometry": {"coordinates":[-121.5833,39.85],"type":"Point"}
}