{
  "id": 7376209,
  "type": "Feature",
  "properties": {
    "tgn:hierarchy":[
        "tgn:7376209",
        "tgn:1000001",
        "tgn:7005595",
        "tgn:7005560",
        "tgn:7029392"
    ],
    "tgn:id":7376209,
    "tgn:name":"Lobitos",
    "tgn:placetype":[
        "aat:300008347"
    ]
},
  "bbox": [],
  "geometry": {"coordinates":[-107.283333,25.133333],"type":"Point"}
}