{
  "id": 1042101,
  "type": "Feature",
  "properties": {
    "tgn:hierarchy":[
        "tgn:1042101",
        "tgn:7002715",
        "tgn:7002731",
        "tgn:1000003",
        "tgn:1000074",
        "tgn:7029392"
    ],
    "tgn:id":1042101,
    "tgn:name":"Langadh\u00e1s",
    "tgn:placetype":[
        "aat:300008347"
    ]
},
  "bbox": [],
  "geometry": {"coordinates":[23.066667,40.75],"type":"Point"}
}