{
  "id": 7516983,
  "type": "Feature",
  "properties": {
    "tgn:hierarchy":[
        "tgn:7516983",
        "tgn:1009227",
        "tgn:7001866",
        "tgn:1000226",
        "tgn:1000006",
        "tgn:7029392"
    ],
    "tgn:id":7516983,
    "tgn:name:en":"Mingha River",
    "tgn:placetype":[
        "aat:300008699"
    ]
},
  "bbox": [],
  "geometry": {"coordinates":[171.583333,-42.983333],"type":"Point"}
}