{
  "id": 7302751,
  "type": "Feature",
  "properties": {
    "tgn:hierarchy":[
        "tgn:7302751",
        "tgn:7008911",
        "tgn:1000003",
        "tgn:7002763",
        "tgn:1000095",
        "tgn:7029392"
    ],
    "tgn:id":7302751,
    "tgn:name":"Negro, Cabo",
    "tgn:placetype":[
        "aat:300008850"
    ]
},
  "bbox": [],
  "geometry": {"coordinates":[-5.912778,43.620278],"type":"Point"}
}