{
  "id": 7143388,
  "type": "Feature",
  "properties": {
    "tgn:hierarchy":[
        "tgn:7143388",
        "tgn:1000003",
        "tgn:7003688",
        "tgn:7000084",
        "tgn:7029392"
    ],
    "tgn:id":7143388,
    "tgn:name":"L\u00fcbsches Geh\u00f6lz",
    "tgn:placetype":[
        "aat:300008863"
    ]
},
  "bbox": [],
  "geometry": {"coordinates":[9.55,53.933333],"type":"Point"}
}