{
  "id": 2348023,
  "type": "Feature",
  "properties": {
    "tgn:hierarchy":[
        "tgn:2348023",
        "tgn:1000001",
        "tgn:7012149",
        "tgn:2001244",
        "tgn:7007523",
        "tgn:7029392"
    ],
    "tgn:id":2348023,
    "tgn:name":"Germania",
    "tgn:placetype":[
        "aat:300008347"
    ]
},
  "bbox": [],
  "geometry": {"coordinates":[-92.4667,40.4167],"type":"Point"}
}