{
  "id": 2211213,
  "type": "Feature",
  "properties": {
    "tgn:hierarchy":[
        "tgn:2211213",
        "tgn:1000001",
        "tgn:7012149",
        "tgn:7029392"
    ],
    "tgn:id":2211213,
    "tgn:name":"Buttahatchee River",
    "tgn:placetype":[
        "aat:300008707"
    ]
},
  "bbox": [],
  "geometry": {"coordinates":[-87.6167,34.1833],"type":"Point"}
}