{
  "id": 1090804,
  "type": "Feature",
  "properties": {
    "tgn:hierarchy":[
        "tgn:1090804",
        "tgn:1001105",
        "tgn:7001242",
        "tgn:1000173",
        "tgn:7029392"
    ],
    "tgn:id":1090804,
    "tgn:name":"Anivorano Nord",
    "tgn:placetype":[
        "aat:300008347"
    ]
},
  "bbox": [],
  "geometry": {"coordinates":[49.2333,-12.7333],"type":"Point"}
}