{
  "id": 7463570,
  "type": "Feature",
  "properties": {
    "tgn:hierarchy":[
        "tgn:7463570",
        "tgn:7002445",
        "tgn:1000003",
        "tgn:7008165",
        "tgn:7008591",
        "tgn:7029392"
    ],
    "tgn:id":7463570,
    "tgn:name:en":"Hulne Park",
    "tgn:placetype":[
        "aat:300387502"
    ]
},
  "bbox": [],
  "geometry": {"coordinates":[-1.75,55.416667],"type":"Point"}
}