{
  "id": 6004324,
  "type": "Feature",
  "properties": {
    "tgn:hierarchy":[
        "tgn:6004324",
        "tgn:7002445",
        "tgn:1000003",
        "tgn:7008132",
        "tgn:7008591",
        "tgn:7029392"
    ],
    "tgn:id":6004324,
    "tgn:name:en":"Notgrove",
    "tgn:placetype":[
        "aat:300008347",
        "aat:300008372",
        "aat:300387005"
    ]
},
  "bbox": [],
  "geometry": {"coordinates":[-1.833333,51.866667],"type":"Point"}
}