{
  "id": 2379338,
  "type": "Feature",
  "properties": {
    "tgn:hierarchy":[
        "tgn:2379338",
        "tgn:1000001",
        "tgn:7012149",
        "tgn:2002371",
        "tgn:7007923",
        "tgn:7029392"
    ],
    "tgn:id":2379338,
    "tgn:name":"Harvey Basin",
    "tgn:placetype":[
        "aat:300386845"
    ]
},
  "bbox": [],
  "geometry": {"coordinates":[-108.7333,42.7167],"type":"Point"}
}