{
  "id": 1070057,
  "type": "Feature",
  "properties": {
    "tgn:hierarchy":[
        "tgn:1070057",
        "tgn:1000004",
        "tgn:7002081",
        "tgn:1000111",
        "tgn:7029392"
    ],
    "tgn:id":1070057,
    "tgn:name":"Longdu",
    "tgn:placetype":[
        "aat:300008347"
    ]
},
  "bbox": [],
  "geometry": {"coordinates":[118.9167,31.8333],"type":"Point"}
}