<<<<<<< HEAD
{
  "id": 7483982,
  "type": "Feature",
  "properties": {
    "tgn:hierarchy":[
        "tgn:7483982",
        "tgn:1000004",
        "tgn:7490934",
        "tgn:1000141",
        "tgn:7029392"
    ],
    "tgn:id":7483982,
    "tgn:name":"Chaibengkou",
    "tgn:placetype":[
        "aat:300008347"
    ]
},
  "bbox": [],
  "geometry": {"coordinates":[120.566667,23.134167],"type":"Point"}
}
=======
{"geometry":{"type":"Point","coordinates":[120.566667,23.134167]},"type":"Feature","properties":{"hierarchy":["tgn:7483982","tgn:1000004","tgn:7490934","tgn:1000141","tgn:7029392"],"placetype":["aat:300008347"],"id":7483982,"name:xx":"Chaibengkou"}}
>>>>>>> 03f74aca74312dbeaf24d7e61306dd6a786dc3d0
