<<<<<<< HEAD
{
  "id": 2761873,
  "type": "Feature",
  "properties": {
    "tgn:hierarchy":[
        "tgn:2761873",
        "tgn:1000001",
        "tgn:7012149",
        "tgn:7007524",
        "tgn:7029392"
    ],
    "tgn:id":2761873,
    "tgn:name":"West Razor Creek",
    "tgn:placetype":[
        "aat:300008706"
    ]
},
  "bbox": [],
  "geometry": {"coordinates":[-108.5667,46.2],"type":"Point"}
}
=======
{"geometry":{"type":"Point","coordinates":[-108.566700,46.200000]},"type":"Feature","properties":{"hierarchy":["tgn:2761873","tgn:1000001","tgn:7012149","tgn:7007524","tgn:7029392"],"placetype":["aat:300008706"],"id":2761873,"name:xx":"West Razor Creek"}}
>>>>>>> 03f74aca74312dbeaf24d7e61306dd6a786dc3d0
