{
  "id": 2433679,
  "type": "Feature",
  "properties": {
    "tgn:hierarchy":[
        "tgn:2433679",
        "tgn:1000001",
        "tgn:7012149",
        "tgn:2000786",
        "tgn:7007255",
        "tgn:7029392"
    ],
    "tgn:id":2433679,
    "tgn:name":"Kelly Creek",
    "tgn:placetype":[
        "aat:300008706"
    ]
},
  "bbox": [],
  "geometry": {"coordinates":[-86.95,37.85],"type":"Point"}
}