{
  "id": 2586491,
  "type": "Feature",
  "properties": {
    "tgn:hierarchy":[
        "tgn:2586491",
        "tgn:1000001",
        "tgn:7012149",
        "tgn:2001162",
        "tgn:7007522",
        "tgn:7029392"
    ],
    "tgn:id":2586491,
    "tgn:name":"Pittman Branch",
    "tgn:placetype":[
        "aat:300008699"
    ]
},
  "bbox": [],
  "geometry": {"coordinates":[-88.7167,31.4667],"type":"Point"}
}