<<<<<<< HEAD
{
  "id": 7243904,
  "type": "Feature",
  "properties": {
    "tgn:hierarchy":[
        "tgn:7243904",
        "tgn:7003466",
        "tgn:1000003",
        "tgn:1000063",
        "tgn:4012014",
        "tgn:7029392"
    ],
    "tgn:id":7243904,
    "tgn:name":"Jamblinne",
    "tgn:placetype":[
        "aat:300008347"
    ]
},
  "bbox": [],
  "geometry": {"coordinates":[5.133333,50.166667],"type":"Point"}
}
=======
{"geometry":{"type":"Point","coordinates":[5.133333,50.166667]},"type":"Feature","properties":{"hierarchy":["tgn:7243904","tgn:7003466","tgn:1000003","tgn:1000063","tgn:4012014","tgn:7029392"],"placetype":["aat:300008347"],"id":7243904,"name:xx":"Jamblinne"}}
>>>>>>> 03f74aca74312dbeaf24d7e61306dd6a786dc3d0
