{
  "id": 2550419,
  "type": "Feature",
  "properties": {
    "tgn:hierarchy":[
        "tgn:2550419",
        "tgn:1000001",
        "tgn:2001350",
        "tgn:7012149",
        "tgn:7007525",
        "tgn:7029392"
    ],
    "tgn:id":2550419,
    "tgn:name":"Northwest Meadow Lake",
    "tgn:placetype":[
        "aat:300008680"
    ]
},
  "bbox": [],
  "geometry": {"coordinates":[-102.3667,41.85],"type":"Point"}
}