{
  "id": 7524374,
  "type": "Feature",
  "properties": {
    "tgn:hierarchy":[
        "tgn:7524374",
        "tgn:7001242",
        "tgn:7016833",
        "tgn:7000122",
        "tgn:7029392"
    ],
    "tgn:id":7524374,
    "tgn:name:en":"Bis\u0101w\u012b, Jaz\u012brat",
    "tgn:placetype":[
        "aat:300008791"
    ]
},
  "bbox": [],
  "geometry": {"coordinates":[32.933333,24.716667],"type":"Point"}
}