{
  "id": 2276318,
  "type": "Feature",
  "properties": {
    "tgn:hierarchy":[
        "tgn:2276318",
        "tgn:1000001",
        "tgn:2000312",
        "tgn:7012149",
        "tgn:7007248",
        "tgn:7029392"
    ],
    "tgn:id":2276318,
    "tgn:name":"Daughtry Lake South",
    "tgn:placetype":[
        "aat:300006191"
    ]
},
  "bbox": [],
  "geometry": {"coordinates":[-82.0667,32.4167],"type":"Point"}
}