{
  "id": 1072069,
  "type": "Feature",
  "properties": {
    "tgn:hierarchy":[
        "tgn:1072069",
        "tgn:1000004",
        "tgn:7018118",
        "tgn:1000111",
        "tgn:7029392"
    ],
    "tgn:id":1072069,
    "tgn:name":"Taipingchang",
    "tgn:placetype":[
        "aat:300008347"
    ]
},
  "bbox": [],
  "geometry": {"coordinates":[103.0667,27.4167],"type":"Point"}
}