{
  "id": 7467113,
  "type": "Feature",
  "properties": {
    "tgn:hierarchy":[
        "tgn:7467113",
        "tgn:7002444",
        "tgn:1000003",
        "tgn:7008082",
        "tgn:7008591",
        "tgn:7029392"
    ],
    "tgn:id":7467113,
    "tgn:name:en":"Alturlie Bay",
    "tgn:placetype":[
        "aat:300132316"
    ]
},
  "bbox": [],
  "geometry": {"coordinates":[-4.116667,57.516667],"type":"Point"}
}