{
  "id": 7229794,
  "type": "Feature",
  "properties": {
    "tgn:hierarchy":[
        "tgn:7229794",
        "tgn:7011330",
        "tgn:7002674",
        "tgn:1000003",
        "tgn:1000074",
        "tgn:7029392"
    ],
    "tgn:id":7229794,
    "tgn:name":"Chteni\u00e9s, Vrachonis\u00edda",
    "tgn:placetype":[
        "aat:300008791"
    ]
},
  "bbox": [],
  "geometry": {"coordinates":[27.706389,35.989722],"type":"Point"}
}