{
  "id": 2084271,
  "type": "Feature",
  "properties": {
    "tgn:hierarchy":[
        "tgn:2084271",
        "tgn:1000001",
        "tgn:2001632",
        "tgn:7012149",
        "tgn:7007707",
        "tgn:7029392"
    ],
    "tgn:id":2084271,
    "tgn:name":"Wilson",
    "tgn:placetype":[
        "aat:300008347"
    ]
},
  "bbox": [],
  "geometry": {"coordinates":[-97.4167,34.15],"type":"Point"}
}