{
  "id": 7131982,
  "type": "Feature",
  "properties": {
    "tgn:hierarchy":[
        "tgn:7131982",
        "tgn:7003669",
        "tgn:1000003",
        "tgn:7000084",
        "tgn:7029392"
    ],
    "tgn:id":7131982,
    "tgn:name":"Marienburg",
    "tgn:placetype":[
        "aat:300008347"
    ]
},
  "bbox": [],
  "geometry": {"coordinates":[10.966667,49.233333],"type":"Point"}
}