{
  "id": 2138206,
  "type": "Feature",
  "properties": {
    "tgn:hierarchy":[
        "tgn:2138206",
        "tgn:1000001",
        "tgn:2001411",
        "tgn:7012149",
        "tgn:7007526",
        "tgn:7029392"
    ],
    "tgn:id":2138206,
    "tgn:name":"Arthur Canyon",
    "tgn:placetype":[
        "aat:300008761"
    ]
},
  "bbox": [],
  "geometry": {"coordinates":[-116.25,41.3667],"type":"Point"}
}