{
  "id": 7107219,
  "type": "Feature",
  "properties": {
    "tgn:hierarchy":[
        "tgn:7107219",
        "tgn:1000003",
        "tgn:7003676",
        "tgn:7000084",
        "tgn:7029392"
    ],
    "tgn:id":7107219,
    "tgn:name":"Schmarrie",
    "tgn:placetype":[
        "aat:300008347"
    ]
},
  "bbox": [],
  "geometry": {"coordinates":[9.383333,52.25],"type":"Point"}
}