{
  "id": 7294540,
  "type": "Feature",
  "properties": {
    "tgn:hierarchy":[
        "tgn:7294540",
        "tgn:7002832",
        "tgn:7001158",
        "tgn:1000003",
        "tgn:1000095",
        "tgn:7029392"
    ],
    "tgn:id":7294540,
    "tgn:name":"Vega de Riacos",
    "tgn:placetype":[
        "aat:300008347"
    ]
},
  "bbox": [],
  "geometry": {"coordinates":[-4.666667,42.75],"type":"Point"}
}