{
  "id": 1042054,
  "type": "Feature",
  "properties": {
    "tgn:hierarchy":[
        "tgn:1042054",
        "tgn:7011330",
        "tgn:7002674",
        "tgn:1000003",
        "tgn:1000074",
        "tgn:7011266",
        "tgn:7029392"
    ],
    "tgn:id":1042054,
    "tgn:name":"Kalav\u00e1rdha",
    "tgn:placetype":[
        "aat:300008347"
    ]
},
  "bbox": [],
  "geometry": {"coordinates":[27.95,36.333333],"type":"Point"}
}