{
  "id": 2700135,
  "type": "Feature",
  "properties": {
    "tgn:hierarchy":[
        "tgn:2700135",
        "tgn:1000001",
        "tgn:2000870",
        "tgn:7012149",
        "tgn:7007256",
        "tgn:7029392"
    ],
    "tgn:id":2700135,
    "tgn:name":"Stumpy Lake",
    "tgn:placetype":[
        "aat:300008680"
    ]
},
  "bbox": [],
  "geometry": {"coordinates":[-91.2667,30.6167],"type":"Point"}
}