{
  "id": 2290609,
  "type": "Feature",
  "properties": {
    "tgn:hierarchy":[
        "tgn:2290609",
        "tgn:1000001",
        "tgn:7006451",
        "tgn:7012149",
        "tgn:2000103",
        "tgn:7029392"
    ],
    "tgn:id":2290609,
    "tgn:name":"Doe Tank",
    "tgn:placetype":[
        "aat:300006191"
    ]
},
  "bbox": [],
  "geometry": {"coordinates":[-111.7333,34.45],"type":"Point"}
}