{
  "id": 7528419,
  "type": "Feature",
  "properties": {
    "tgn:hierarchy":[
        "tgn:7528419",
        "tgn:7001242",
        "tgn:7001311",
        "tgn:7016833",
        "tgn:7029392"
    ],
    "tgn:id":7528419,
    "tgn:name:en":"Umm \u1e28arbah, Jabal",
    "tgn:placetype":[
        "aat:300008795"
    ]
},
  "bbox": [],
  "geometry": {"coordinates":[34.815323,24.646678],"type":"Point"}
}