{
  "id": 7435594,
  "type": "Feature",
  "properties": {
    "tgn:hierarchy":[
        "tgn:7435594",
        "tgn:1000001",
        "tgn:7005599",
        "tgn:7005560",
        "tgn:7029392"
    ],
    "tgn:id":7435594,
    "tgn:name":"Viloria",
    "tgn:placetype":[
        "aat:300008347"
    ]
},
  "bbox": [],
  "geometry": {"coordinates":[-95.566667,18.233333],"type":"Point"}
}