{
  "id": 1050729,
  "type": "Feature",
  "properties": {
    "tgn:hierarchy":[
        "tgn:1050729",
        "tgn:7002444",
        "tgn:1000003",
        "tgn:7008082",
        "tgn:7008591",
        "tgn:1008769",
        "tgn:7029392"
    ],
    "tgn:id":1050729,
    "tgn:name":"Harris",
    "tgn:placetype":[
        "aat:300008347"
    ]
},
  "bbox": [],
  "geometry": {"coordinates":[-6.3333,56.9833],"type":"Point"}
}