{
  "id": 7121479,
  "type": "Feature",
  "properties": {
    "tgn:hierarchy":[
        "tgn:7121479",
        "tgn:7000096",
        "tgn:1000003",
        "tgn:7000084",
        "tgn:7029392"
    ],
    "tgn:id":7121479,
    "tgn:name":"Parforceheide",
    "tgn:placetype":[
        "aat:300008863"
    ]
},
  "bbox": [],
  "geometry": {"coordinates":[13.15,52.383333],"type":"Point"}
}