{
  "id": 2200674,
  "type": "Feature",
  "properties": {
    "tgn:hierarchy":[
        "tgn:2200674",
        "tgn:1000001",
        "tgn:7012149",
        "tgn:2001437",
        "tgn:7007566",
        "tgn:7029392"
    ],
    "tgn:id":2200674,
    "tgn:name":"Brushy Tank",
    "tgn:placetype":[
        "aat:300006191"
    ]
},
  "bbox": [],
  "geometry": {"coordinates":[-108.2333,31.95],"type":"Point"}
}