{
  "id": 1100483,
  "type": "Feature",
  "properties": {
    "tgn:hierarchy":[
        "tgn:1100483",
        "tgn:1000001",
        "tgn:7012149",
        "tgn:7014160",
        "tgn:7007919",
        "tgn:7029392"
    ],
    "tgn:id":1100483,
    "tgn:name":"Central Intelligence Agency",
    "tgn:placetype":[
        "aat:300005993"
    ]
},
  "bbox": [],
  "geometry": {"coordinates":[-77.1333,38.95],"type":"Point"}
}