{
  "id": 7072658,
  "type": "Feature",
  "properties": {
    "tgn:hierarchy":[
        "tgn:7072658",
        "tgn:7003669",
        "tgn:1000003",
        "tgn:7000084",
        "tgn:7029392"
    ],
    "tgn:id":7072658,
    "tgn:name":"Tanzplatz",
    "tgn:placetype":[
        "aat:300008777"
    ]
},
  "bbox": [],
  "geometry": {"coordinates":[9.383333,49.933333],"type":"Point"}
}