{
  "id": 2677007,
  "type": "Feature",
  "properties": {
    "tgn:hierarchy":[
        "tgn:2677007",
        "tgn:1000001",
        "tgn:7012149",
        "tgn:2001403",
        "tgn:7007525",
        "tgn:7029392"
    ],
    "tgn:id":2677007,
    "tgn:name":"South Branch Mira Creek",
    "tgn:placetype":[
        "aat:300008706"
    ]
},
  "bbox": [],
  "geometry": {"coordinates":[-98.9167,41.45],"type":"Point"}
}