{
  "id": 2100951,
  "type": "Feature",
  "properties": {
    "tgn:hierarchy":[
        "tgn:2100951",
        "tgn:1000001",
        "tgn:7012149",
        "tgn:7022544",
        "tgn:7007825",
        "tgn:7029392"
    ],
    "tgn:id":2100951,
    "tgn:name":"Pebble Hill",
    "tgn:placetype":[
        "aat:300008347",
        "aat:300387210"
    ]
},
  "bbox": [],
  "geometry": {"coordinates":[-88.4167,35.0833],"type":"Point"}
}