{
  "id": 7355558,
  "type": "Feature",
  "properties": {
    "tgn:hierarchy":[
        "tgn:7355558",
        "tgn:1000001",
        "tgn:1001960",
        "tgn:7005560",
        "tgn:7029392"
    ],
    "tgn:id":7355558,
    "tgn:name":"Cendraditas",
    "tgn:placetype":[
        "aat:300008347"
    ]
},
  "bbox": [],
  "geometry": {"coordinates":[-110.016667,28.483333],"type":"Point"}
}