{
  "id": 7312728,
  "type": "Feature",
  "properties": {
    "tgn:hierarchy":[
        "tgn:7312728",
        "tgn:1001695",
        "tgn:1000049",
        "tgn:1000002",
        "tgn:7029392"
    ],
    "tgn:id":7312728,
    "tgn:name":"La Mina, Quebrada",
    "tgn:placetype":[
        "aat:300266554",
        "aat:300008699"
    ]
},
  "bbox": [],
  "geometry": {"coordinates":[-71.233333,-34.316667],"type":"Point"}
}