{
  "id": 2380804,
  "type": "Feature",
  "properties": {
    "tgn:hierarchy":[
        "tgn:2380804",
        "tgn:1000001",
        "tgn:7012149",
        "tgn:2002291",
        "tgn:7013961",
        "tgn:7029392"
    ],
    "tgn:id":2380804,
    "tgn:name":"Hawflat Knob",
    "tgn:placetype":[
        "aat:300008798"
    ]
},
  "bbox": [],
  "geometry": {"coordinates":[-79.75,38.85],"type":"Point"}
}