{
  "id": 2625381,
  "type": "Feature",
  "properties": {
    "tgn:hierarchy":[
        "tgn:2625381",
        "tgn:1000001",
        "tgn:7012149",
        "tgn:2001440",
        "tgn:7007566",
        "tgn:7029392"
    ],
    "tgn:id":2625381,
    "tgn:name":"Rockhouse Spring",
    "tgn:placetype":[
        "aat:300008697"
    ]
},
  "bbox": [],
  "geometry": {"coordinates":[-109.0167,32.3833],"type":"Point"}
}