{
  "id": 7039699,
  "type": "Feature",
  "properties": {
    "tgn:hierarchy":[
        "tgn:7039699",
        "tgn:7003005",
        "tgn:7003014",
        "tgn:1000003",
        "tgn:1000080",
        "tgn:7029392"
    ],
    "tgn:id":7039699,
    "tgn:name":"Serretella, Monte",
    "tgn:placetype":[
        "aat:300008795"
    ]
},
  "bbox": [],
  "geometry": {"coordinates":[15.633333,40.116667],"type":"Point"}
}