{
  "id": 1068827,
  "type": "Feature",
  "properties": {
    "tgn:hierarchy":[
        "tgn:1068827",
        "tgn:1000004",
        "tgn:1001390",
        "tgn:1000111",
        "tgn:7029392"
    ],
    "tgn:id":1068827,
    "tgn:name":"Houqianjiayu",
    "tgn:placetype":[
        "aat:300008347"
    ]
},
  "bbox": [],
  "geometry": {"coordinates":[120.6833,40.8333],"type":"Point"}
}