{
  "id": 2510249,
  "type": "Feature",
  "properties": {
    "tgn:hierarchy":[
        "tgn:2510249",
        "tgn:1000001",
        "tgn:7012149",
        "tgn:2001543",
        "tgn:7007709",
        "tgn:7029392"
    ],
    "tgn:id":2510249,
    "tgn:name":"Middle Ridge",
    "tgn:placetype":[
        "aat:300266640"
    ]
},
  "bbox": [],
  "geometry": {"coordinates":[-83.3667,35.3833],"type":"Point"}
}