{
  "id": 2234608,
  "type": "Feature",
  "properties": {
    "tgn:hierarchy":[
        "tgn:2234608",
        "tgn:1000001",
        "tgn:7006451",
        "tgn:7012149",
        "tgn:2000098",
        "tgn:7029392"
    ],
    "tgn:id":2234608,
    "tgn:name":"Cherokee Wash",
    "tgn:placetype":[
        "aat:300008701"
    ]
},
  "bbox": [],
  "geometry": {"coordinates":[-113.4667,35.4667],"type":"Point"}
}