{
  "id": 7458673,
  "type": "Feature",
  "properties": {
    "tgn:hierarchy":[
        "tgn:7458673",
        "tgn:7002445",
        "tgn:1000003",
        "tgn:7012077",
        "tgn:7008591",
        "tgn:7029392"
    ],
    "tgn:id":7458673,
    "tgn:name:en":"Luton",
    "tgn:placetype":[
        "aat:300008347"
    ]
},
  "bbox": [],
  "geometry": {"coordinates":[-3.55,50.583333],"type":"Point"}
}