{
  "id": 2107725,
  "type": "Feature",
  "properties": {
    "tgn:hierarchy":[
        "tgn:2107725",
        "tgn:1000001",
        "tgn:7012149",
        "tgn:1002244",
        "tgn:7007826",
        "tgn:7029392"
    ],
    "tgn:id":2107725,
    "tgn:name":"Smyrna",
    "tgn:placetype":[
        "aat:300008347",
        "aat:300387210"
    ]
},
  "bbox": [],
  "geometry": {"coordinates":[-94.0833,33.0667],"type":"Point"}
}