{
  "id": 2557132,
  "type": "Feature",
  "properties": {
    "tgn:hierarchy":[
        "tgn:2557132",
        "tgn:1000001",
        "tgn:7012149",
        "tgn:7007157",
        "tgn:1002684",
        "tgn:7029392"
    ],
    "tgn:id":2557132,
    "tgn:name":"Old Hilltown",
    "tgn:placetype":[
        "aat:300008347"
    ]
},
  "bbox": [],
  "geometry": {"coordinates":[-121.6667,36.6167],"type":"Point"}
}