{
  "id": 7146890,
  "type": "Feature",
  "properties": {
    "tgn:hierarchy":[
        "tgn:7146890",
        "tgn:7003669",
        "tgn:1000003",
        "tgn:7000084",
        "tgn:7029392"
    ],
    "tgn:id":7146890,
    "tgn:name":"Kohlgraben",
    "tgn:placetype":[
        "aat:300008699"
    ]
},
  "bbox": [],
  "geometry": {"coordinates":[11.05,48.65],"type":"Point"}
}