{
  "id": 2119848,
  "type": "Feature",
  "properties": {
    "tgn:hierarchy":[
        "tgn:2119848",
        "tgn:1000001",
        "tgn:7012149",
        "tgn:2002293",
        "tgn:7013961",
        "tgn:7029392"
    ],
    "tgn:id":2119848,
    "tgn:name":"Roxalana",
    "tgn:placetype":[
        "aat:300008347",
        "aat:300387210"
    ]
},
  "bbox": [],
  "geometry": {"coordinates":[-81.25,38.6833],"type":"Point"}
}