{
  "id": 2052732,
  "type": "Feature",
  "properties": {
    "tgn:hierarchy":[
        "tgn:2052732",
        "tgn:2000948",
        "tgn:1000001",
        "tgn:7012149",
        "tgn:7007520",
        "tgn:7029392"
    ],
    "tgn:id":2052732,
    "tgn:name":"Munger",
    "tgn:placetype":[
        "aat:300008347"
    ]
},
  "bbox": [],
  "geometry": {"coordinates":[-83.7667,43.5167],"type":"Point"}
}