{
  "id": 1005422,
  "type": "Feature",
  "properties": {
    "tgn:hierarchy":[
        "tgn:1005422",
        "tgn:7003712",
        "tgn:7003670",
        "tgn:1000003",
        "tgn:7000084",
        "tgn:7029392"
    ],
    "tgn:id":1005422,
    "tgn:name":"Reinickendorf",
    "tgn:placetype":[
        "aat:300387145",
        "aat:300387333"
    ]
},
  "bbox": [],
  "geometry": {"coordinates":[13.3333,52.5833],"type":"Point"}
}