{
  "id": 7297247,
  "type": "Feature",
  "properties": {
    "tgn:hierarchy":[
        "tgn:7297247",
        "tgn:7002758",
        "tgn:7002817",
        "tgn:1000003",
        "tgn:1000095",
        "tgn:7029392"
    ],
    "tgn:id":7297247,
    "tgn:name":"Tamujoso, Arroyo",
    "tgn:placetype":[
        "aat:300008699"
    ]
},
  "bbox": [],
  "geometry": {"coordinates":[-5.233333,38.05],"type":"Point"}
}