{
  "id": 1137817,
  "type": "Feature",
  "properties": {
    "tgn:hierarchy":[
        "tgn:1137817",
        "tgn:1000004",
        "tgn:7011584",
        "tgn:7018214",
        "tgn:7002435",
        "tgn:7029392"
    ],
    "tgn:id":1137817,
    "tgn:name":"Kuzomen",
    "tgn:placetype":[
        "aat:300008347"
    ]
},
  "bbox": [],
  "geometry": {"coordinates":[36.85,66.25],"type":"Point"}
}