{
  "id": 7358241,
  "type": "Feature",
  "properties": {
    "tgn:hierarchy":[
        "tgn:7358241",
        "tgn:7005581",
        "tgn:1000001",
        "tgn:7005560",
        "tgn:7029392"
    ],
    "tgn:id":7358241,
    "tgn:name":"Colonia M\u00e9xico",
    "tgn:placetype":[
        "aat:300008347"
    ]
},
  "bbox": [],
  "geometry": {"coordinates":[-108.15,30.983333],"type":"Point"}
}