{
  "id": 1088805,
  "type": "Feature",
  "properties": {
    "tgn:hierarchy":[
        "tgn:1088805",
        "tgn:7001242",
        "tgn:7016654",
        "tgn:1000159",
        "tgn:7029392"
    ],
    "tgn:id":1088805,
    "tgn:name":"Belondo",
    "tgn:placetype":[
        "aat:300008347"
    ]
},
  "bbox": [],
  "geometry": {"coordinates":[19.5167,-0.3167],"type":"Point"}
}