{
  "id": 2425239,
  "type": "Feature",
  "properties": {
    "tgn:hierarchy":[
        "tgn:2425239",
        "tgn:1000001",
        "tgn:7012149",
        "tgn:2002127",
        "tgn:7007827",
        "tgn:7029392"
    ],
    "tgn:id":2425239,
    "tgn:name":"Johnson Mountain",
    "tgn:placetype":[
        "aat:300008798"
    ]
},
  "bbox": [],
  "geometry": {"coordinates":[-112.9833,37.1667],"type":"Point"}
}