{
  "id": 2605573,
  "type": "Feature",
  "properties": {
    "tgn:hierarchy":[
        "tgn:2605573",
        "tgn:1000001",
        "tgn:7006451",
        "tgn:7012149",
        "tgn:2000103",
        "tgn:7029392"
    ],
    "tgn:id":2605573,
    "tgn:name":"Railroad Embankment Reservoir",
    "tgn:placetype":[
        "aat:300006191"
    ]
},
  "bbox": [],
  "geometry": {"coordinates":[-112.8833,35.3167],"type":"Point"}
}