{
  "id": 2613040,
  "type": "Feature",
  "properties": {
    "tgn:hierarchy":[
        "tgn:2613040",
        "tgn:1000001",
        "tgn:7012149",
        "tgn:2000410",
        "tgn:7007248",
        "tgn:7029392"
    ],
    "tgn:id":2613040,
    "tgn:name":"Redside Mountain",
    "tgn:placetype":[
        "aat:300008798"
    ]
},
  "bbox": [],
  "geometry": {"coordinates":[-83.1167,34.9833],"type":"Point"}
}