<<<<<<< HEAD
{
  "id": 7247711,
  "type": "Feature",
  "properties": {
    "tgn:hierarchy":[
        "tgn:7247711",
        "tgn:7003458",
        "tgn:1000003",
        "tgn:1000063",
        "tgn:7018236",
        "tgn:7029392"
    ],
    "tgn:id":7247711,
    "tgn:name":"De Kat",
    "tgn:placetype":[
        "aat:300008347"
    ]
},
  "bbox": [],
  "geometry": {"coordinates":[3.27352,50.862421],"type":"Point"}
}
=======
{"geometry":{"type":"Point","coordinates":[3.273520,50.862421]},"type":"Feature","properties":{"hierarchy":["tgn:7247711","tgn:7003458","tgn:1000003","tgn:1000063","tgn:7018236","tgn:7029392"],"placetype":["aat:300008347"],"id":7247711,"name:xx":"De Kat"}}
>>>>>>> 03f74aca74312dbeaf24d7e61306dd6a786dc3d0
