{
  "id": 7127018,
  "type": "Feature",
  "properties": {
    "tgn:hierarchy":[
        "tgn:7127018",
        "tgn:7003669",
        "tgn:1000003",
        "tgn:7000084",
        "tgn:7029392"
    ],
    "tgn:id":7127018,
    "tgn:name":"Oberhausen",
    "tgn:placetype":[
        "aat:300008347"
    ]
},
  "bbox": [],
  "geometry": {"coordinates":[12.133333,48.783333],"type":"Point"}
}