{
  "id": 7229734,
  "type": "Feature",
  "properties": {
    "tgn:hierarchy":[
        "tgn:7229734",
        "tgn:7002743",
        "tgn:7017076",
        "tgn:1000003",
        "tgn:1000074",
        "tgn:7029392"
    ],
    "tgn:id":7229734,
    "tgn:name":"Lali\u00f3ti",
    "tgn:placetype":[
        "aat:300008347"
    ]
},
  "bbox": [],
  "geometry": {"coordinates":[21.766667,38.083333],"type":"Point"}
}