<<<<<<< HEAD
{
  "id": 2157979,
  "type": "Feature",
  "properties": {
    "tgn:hierarchy":[
        "tgn:2157979",
        "tgn:1000001",
        "tgn:7012149",
        "tgn:2001461",
        "tgn:7007568",
        "tgn:7029392"
    ],
    "tgn:id":2157979,
    "tgn:name":"Beaver Meadow Hill",
    "tgn:placetype":[
        "aat:300008798"
    ]
},
  "bbox": [],
  "geometry": {"coordinates":[-73.7167,43.8167],"type":"Point"}
}
=======
{"geometry":{"type":"Point","coordinates":[-73.716700,43.816700]},"type":"Feature","properties":{"hierarchy":["tgn:2157979","tgn:1000001","tgn:7012149","tgn:2001461","tgn:7007568","tgn:7029392"],"placetype":["aat:300008798"],"id":2157979,"name:xx":"Beaver Meadow Hill"}}
>>>>>>> 03f74aca74312dbeaf24d7e61306dd6a786dc3d0
