{
  "id": 7541355,
  "type": "Feature",
  "properties": {
    "tgn:hierarchy":[
        "tgn:7541355",
        "tgn:7001242",
        "tgn:7016833",
        "tgn:1001092",
        "tgn:7029392"
    ],
    "tgn:id":7541355,
    "tgn:name":"Nazlat Kafr 'Ulaym",
    "tgn:placetype":[
        "aat:300008347"
    ]
},
  "bbox": [],
  "geometry": {"coordinates":[31.124037,30.25397],"type":"Point"}
}