{
  "id": 2404346,
  "type": "Feature",
  "properties": {
    "tgn:hierarchy":[
        "tgn:2404346",
        "tgn:1000001",
        "tgn:7012149",
        "tgn:2001454",
        "tgn:7007566",
        "tgn:7029392"
    ],
    "tgn:id":2404346,
    "tgn:name":"Hub Canyon",
    "tgn:placetype":[
        "aat:300008761"
    ]
},
  "bbox": [],
  "geometry": {"coordinates":[-105.8667,35.3167],"type":"Point"}
}