{
  "id": 1054669,
  "type": "Feature",
  "properties": {
    "tgn:hierarchy":[
        "tgn:1054669",
        "tgn:1000004",
        "tgn:6003149",
        "tgn:7002435",
        "tgn:7029392"
    ],
    "tgn:id":1054669,
    "tgn:name":"Jeleckij",
    "tgn:placetype":[
        "aat:300008347"
    ]
},
  "bbox": [],
  "geometry": {"coordinates":[64.1667,67.05],"type":"Point"}
}