<<<<<<< HEAD
{
  "id": 7362160,
  "type": "Feature",
  "properties": {
    "tgn:hierarchy":[
        "tgn:7362160",
        "tgn:1000001",
        "tgn:7005597",
        "tgn:7005560",
        "tgn:7029392"
    ],
    "tgn:id":7362160,
    "tgn:name":"El Caracol",
    "tgn:placetype":[
        "aat:300008347"
    ]
},
  "bbox": [],
  "geometry": {"coordinates":[-97.85,24.116667],"type":"Point"}
}
=======
{"geometry":{"type":"Point","coordinates":[-97.850000,24.116667]},"type":"Feature","properties":{"hierarchy":["tgn:7362160","tgn:1000001","tgn:7005597","tgn:7005560","tgn:7029392"],"placetype":["aat:300008347"],"id":7362160,"name:xx":"El Caracol"}}
>>>>>>> 03f74aca74312dbeaf24d7e61306dd6a786dc3d0
