{
  "id": 2534526,
  "type": "Feature",
  "properties": {
    "tgn:hierarchy":[
        "tgn:2534526",
        "tgn:1000001",
        "tgn:7012149",
        "tgn:2001282",
        "tgn:7007524",
        "tgn:7029392"
    ],
    "tgn:id":2534526,
    "tgn:name":"NW NW Section 14 Mine",
    "tgn:placetype":[
        "aat:300000390"
    ]
},
  "bbox": [],
  "geometry": {"coordinates":[-110.4167,46.9667],"type":"Point"}
}