{
  "id": 2629084,
  "type": "Feature",
  "properties": {
    "tgn:hierarchy":[
        "tgn:2629084",
        "tgn:7030515",
        "tgn:7006450",
        "tgn:1000001",
        "tgn:7012149",
        "tgn:7029392"
    ],
    "tgn:id":2629084,
    "tgn:name":"Rose Island",
    "tgn:placetype":[
        "aat:300008791"
    ]
},
  "bbox": [],
  "geometry": {"coordinates":[-161.85,54.8833],"type":"Point"}
}