{
  "id": 2552122,
  "type": "Feature",
  "properties": {
    "tgn:hierarchy":[
        "tgn:2552122",
        "tgn:1000001",
        "tgn:7012149",
        "tgn:1002995",
        "tgn:7007710",
        "tgn:7029392"
    ],
    "tgn:id":2552122,
    "tgn:name":"Number One Reservoir",
    "tgn:placetype":[
        "aat:300006191"
    ]
},
  "bbox": [],
  "geometry": {"coordinates":[-80.2667,40.15],"type":"Point"}
}