{
  "id": 2166561,
  "type": "Feature",
  "properties": {
    "tgn:hierarchy":[
        "tgn:2166561",
        "tgn:1000001",
        "tgn:7012149",
        "tgn:2000354",
        "tgn:7007248",
        "tgn:7029392"
    ],
    "tgn:id":2166561,
    "tgn:name":"Big Branch",
    "tgn:placetype":[
        "aat:300008905"
    ]
},
  "bbox": [],
  "geometry": {"coordinates":[-81.6333,31.1333],"type":"Point"}
}