{
  "id": 2343852,
  "type": "Feature",
  "properties": {
    "tgn:hierarchy":[
        "tgn:2343852",
        "tgn:1000001",
        "tgn:1002200",
        "tgn:7012149",
        "tgn:7007240",
        "tgn:7029392"
    ],
    "tgn:id":2343852,
    "tgn:name":"Gallinipper Point",
    "tgn:placetype":[
        "aat:300008850"
    ]
},
  "bbox": [],
  "geometry": {"coordinates":[-80.65,28.6667],"type":"Point"}
}