{
  "id": 2705385,
  "type": "Feature",
  "properties": {
    "tgn:hierarchy":[
        "tgn:2705385",
        "tgn:1000001",
        "tgn:7012149",
        "tgn:7007250",
        "tgn:7029392"
    ],
    "tgn:id":2705385,
    "tgn:name":"Surprise Creek",
    "tgn:placetype":[
        "aat:300008706"
    ]
},
  "bbox": [],
  "geometry": {"coordinates":[-116.3333,47.9333],"type":"Point"}
}