{
  "id": 2350219,
  "type": "Feature",
  "properties": {
    "tgn:hierarchy":[
        "tgn:2350219",
        "tgn:1000001",
        "tgn:7012149",
        "tgn:2001304",
        "tgn:7007524",
        "tgn:7029392"
    ],
    "tgn:id":2350219,
    "tgn:name":"Gin Gulch",
    "tgn:placetype":[
        "aat:300008761"
    ]
},
  "bbox": [],
  "geometry": {"coordinates":[-115.8167,48.0833],"type":"Point"}
}