{
  "id": 2224324,
  "type": "Feature",
  "properties": {
    "tgn:hierarchy":[
        "tgn:2224324",
        "tgn:1000001",
        "tgn:7012149",
        "tgn:2001124",
        "tgn:7007522",
        "tgn:7029392"
    ],
    "tgn:id":2224324,
    "tgn:name":"Cascade Creek",
    "tgn:placetype":[
        "aat:300008706"
    ]
},
  "bbox": [],
  "geometry": {"coordinates":[-90.0667,31.7333],"type":"Point"}
}