{
  "id": 7209169,
  "type": "Feature",
  "properties": {
    "tgn:hierarchy":[
        "tgn:7209169",
        "tgn:1000003",
        "tgn:7003688",
        "tgn:7000084",
        "tgn:7029392"
    ],
    "tgn:id":7209169,
    "tgn:name":"Barkhorn",
    "tgn:placetype":[
        "aat:300008347"
    ]
},
  "bbox": [],
  "geometry": {"coordinates":[9.666667,54.216667],"type":"Point"}
}