{
  "id": 4010554,
  "type": "Feature",
  "properties": {
    "tgn:hierarchy":[
        "tgn:4010554",
        "tgn:7002824",
        "tgn:1000003",
        "tgn:7002786",
        "tgn:1000095",
        "tgn:7029392"
    ],
    "tgn:id":4010554,
    "tgn:name":"Sobrado",
    "tgn:placetype":[
        "aat:300008347"
    ]
},
  "bbox": [],
  "geometry": {"coordinates":[-6.533333,43.316667],"type":"Point"}
}