{
  "id": 2603771,
  "type": "Feature",
  "properties": {
    "tgn:hierarchy":[
        "tgn:2603771",
        "tgn:1002201",
        "tgn:1000001",
        "tgn:7012149",
        "tgn:7007517",
        "tgn:7029392"
    ],
    "tgn:id":2603771,
    "tgn:name":"Quicksand Point",
    "tgn:placetype":[
        "aat:300008850"
    ]
},
  "bbox": [],
  "geometry": {"coordinates":[-71.1167,41.4833],"type":"Point"}
}