<<<<<<< HEAD
{
  "id": 7249524,
  "type": "Feature",
  "properties": {
    "tgn:hierarchy":[
        "tgn:7249524",
        "tgn:7003457",
        "tgn:1000003",
        "tgn:1000063",
        "tgn:7018236",
        "tgn:7029392"
    ],
    "tgn:id":7249524,
    "tgn:name":"Oudeveldstraat",
    "tgn:placetype":[
        "aat:300008347"
    ]
},
  "bbox": [],
  "geometry": {"coordinates":[3.883333,51.116667],"type":"Point"}
}
=======
{"geometry":{"type":"Point","coordinates":[3.883333,51.116667]},"type":"Feature","properties":{"hierarchy":["tgn:7249524","tgn:7003457","tgn:1000003","tgn:1000063","tgn:7018236","tgn:7029392"],"placetype":["aat:300008347"],"id":7249524,"name:xx":"Oudeveldstraat"}}
>>>>>>> 03f74aca74312dbeaf24d7e61306dd6a786dc3d0
