{
  "id": 2259913,
  "type": "Feature",
  "properties": {
    "tgn:hierarchy":[
        "tgn:2259913",
        "tgn:1000001",
        "tgn:7012149",
        "tgn:7007158",
        "tgn:2000251",
        "tgn:7029392"
    ],
    "tgn:id":2259913,
    "tgn:name":"Coulson Lake",
    "tgn:placetype":[
        "aat:300006191"
    ]
},
  "bbox": [],
  "geometry": {"coordinates":[-105.1333,38.9333],"type":"Point"}
}