<<<<<<< HEAD
{
  "id": 2259913,
  "type": "Feature",
  "properties": {
    "tgn:hierarchy":[
        "tgn:2259913",
        "tgn:1000001",
        "tgn:7012149",
        "tgn:7007158",
        "tgn:2000251",
        "tgn:7029392"
    ],
    "tgn:id":2259913,
    "tgn:name":"Coulson Lake",
    "tgn:placetype":[
        "aat:300006191"
    ]
},
  "bbox": [],
  "geometry": {"coordinates":[-105.1333,38.9333],"type":"Point"}
}
=======
{"geometry":{"type":"Point","coordinates":[-105.133300,38.933300]},"type":"Feature","properties":{"hierarchy":["tgn:2259913","tgn:1000001","tgn:7012149","tgn:7007158","tgn:2000251","tgn:7029392"],"placetype":["aat:300006191"],"id":2259913,"name:xx":"Coulson Lake"}}
>>>>>>> 03f74aca74312dbeaf24d7e61306dd6a786dc3d0
