{
  "id": 7380985,
  "type": "Feature",
  "properties": {
    "tgn:hierarchy":[
        "tgn:7380985",
        "tgn:1000001",
        "tgn:7005590",
        "tgn:7005560",
        "tgn:7029392"
    ],
    "tgn:id":7380985,
    "tgn:name":"Los Llanos",
    "tgn:placetype":[
        "aat:300008347"
    ]
},
  "bbox": [],
  "geometry": {"coordinates":[-101.966667,19.816667],"type":"Point"}
}