{
  "id": 7394115,
  "type": "Feature",
  "properties": {
    "tgn:hierarchy":[
        "tgn:7394115",
        "tgn:1000001",
        "tgn:7005591",
        "tgn:7005560",
        "tgn:7029392"
    ],
    "tgn:id":7394115,
    "tgn:name":"San Francisco Tutepetongo",
    "tgn:placetype":[
        "aat:300008347"
    ]
},
  "bbox": [],
  "geometry": {"coordinates":[-96.883333,17.766667],"type":"Point"}
}