{
  "id": 7359885,
  "type": "Feature",
  "properties": {
    "tgn:hierarchy":[
        "tgn:7359885",
        "tgn:1000001",
        "tgn:7005599",
        "tgn:7005560",
        "tgn:7029392"
    ],
    "tgn:id":7359885,
    "tgn:name":"Ciruelo",
    "tgn:placetype":[
        "aat:300008347"
    ]
},
  "bbox": [],
  "geometry": {"coordinates":[-95.616667,18.033333],"type":"Point"}
}