<<<<<<< HEAD
{
  "id": 7027477,
  "type": "Feature",
  "properties": {
    "tgn:hierarchy":[
        "tgn:7027477",
        "tgn:7002445",
        "tgn:1000003",
        "tgn:7026570",
        "tgn:7008591",
        "tgn:7029392"
    ],
    "tgn:id":7027477,
    "tgn:name":"Manchester",
    "tgn:placetype":[
        "aat:300387337"
    ]
},
  "bbox": [],
  "geometry": {"coordinates":[-2.25,53.4833],"type":"Point"}
}
=======
{"geometry":{"type":"Point","coordinates":[-2.250000,53.483300]},"type":"Feature","properties":{"hierarchy":["tgn:7027477","tgn:7002445","tgn:1000003","tgn:7026570","tgn:7008591","tgn:7029392"],"placetype":["aat:300387337"],"id":7027477,"name:xx":"Manchester"}}
>>>>>>> 03f74aca74312dbeaf24d7e61306dd6a786dc3d0
