{
  "id": 2660124,
  "type": "Feature",
  "properties": {
    "tgn:hierarchy":[
        "tgn:2660124",
        "tgn:2002239",
        "tgn:1000001",
        "tgn:7012149",
        "tgn:7007920",
        "tgn:7029392"
    ],
    "tgn:id":2660124,
    "tgn:name":"Shittim Gulch",
    "tgn:placetype":[
        "aat:300008761"
    ]
},
  "bbox": [],
  "geometry": {"coordinates":[-117.35,46.0167],"type":"Point"}
}