{
  "id": 7331559,
  "type": "Feature",
  "properties": {
    "tgn:hierarchy":[
        "tgn:7331559",
        "tgn:7002829",
        "tgn:1000003",
        "tgn:7002786",
        "tgn:1000095",
        "tgn:7029392"
    ],
    "tgn:id":7331559,
    "tgn:name":"Lajo",
    "tgn:placetype":[
        "aat:300008347"
    ]
},
  "bbox": [],
  "geometry": {"coordinates":[-6.866667,42.966667],"type":"Point"}
}