{
  "id": 2646368,
  "type": "Feature",
  "properties": {
    "tgn:hierarchy":[
        "tgn:2646368",
        "tgn:1000001",
        "tgn:1002415",
        "tgn:7012149",
        "tgn:7007828",
        "tgn:7029392"
    ],
    "tgn:id":2646368,
    "tgn:name":"Sawyer Island",
    "tgn:placetype":[
        "aat:300008791"
    ]
},
  "bbox": [],
  "geometry": {"coordinates":[-73.35,44.65],"type":"Point"}
}