{
  "id": 2109709,
  "type": "Feature",
  "properties": {
    "tgn:hierarchy":[
        "tgn:2109709",
        "tgn:1000001",
        "tgn:1002389",
        "tgn:7012149",
        "tgn:7007828",
        "tgn:7029392"
    ],
    "tgn:id":2109709,
    "tgn:name":"Highgate Falls",
    "tgn:placetype":[
        "aat:300008347"
    ]
},
  "bbox": [],
  "geometry": {"coordinates":[-73.05,44.9167],"type":"Point"}
}