{
  "id": 7130767,
  "type": "Feature",
  "properties": {
    "tgn:hierarchy":[
        "tgn:7130767",
        "tgn:1000003",
        "tgn:7003678",
        "tgn:7000084",
        "tgn:7029392"
    ],
    "tgn:id":7130767,
    "tgn:name":"Mehr-Bach",
    "tgn:placetype":[
        "aat:300008699"
    ]
},
  "bbox": [],
  "geometry": {"coordinates":[7.933333,50.116667],"type":"Point"}
}