{
  "id": 2618388,
  "type": "Feature",
  "properties": {
    "tgn:hierarchy":[
        "tgn:2618388",
        "tgn:1000001",
        "tgn:2001473",
        "tgn:7012149",
        "tgn:7007709",
        "tgn:7029392"
    ],
    "tgn:id":2618388,
    "tgn:name":"Right Fork Beetree Creek",
    "tgn:placetype":[
        "aat:300008706"
    ]
},
  "bbox": [],
  "geometry": {"coordinates":[-82.3667,35.6833],"type":"Point"}
}