{
  "id": 2173151,
  "type": "Feature",
  "properties": {
    "tgn:hierarchy":[
        "tgn:2173151",
        "tgn:1000001",
        "tgn:7016172",
        "tgn:7012149",
        "tgn:2000128",
        "tgn:7029392"
    ],
    "tgn:id":2173151,
    "tgn:name":"Bingham Hollow",
    "tgn:placetype":[
        "aat:300008761"
    ]
},
  "bbox": [],
  "geometry": {"coordinates":[-93.7333,35.65],"type":"Point"}
}