{
  "id": 2552311,
  "type": "Feature",
  "properties": {
    "tgn:hierarchy":[
        "tgn:2552311",
        "tgn:1000001",
        "tgn:7012149",
        "tgn:1002995",
        "tgn:7007710",
        "tgn:7029392"
    ],
    "tgn:id":2552311,
    "tgn:name":"Number Three Reservoir",
    "tgn:placetype":[
        "aat:300006191"
    ]
},
  "bbox": [],
  "geometry": {"coordinates":[-80.25,40.1333],"type":"Point"}
}