{
  "id": 7055865,
  "type": "Feature",
  "properties": {
    "tgn:hierarchy":[
        "tgn:7055865",
        "tgn:7004597",
        "tgn:1000003",
        "tgn:7008516",
        "tgn:1000080",
        "tgn:7029392"
    ],
    "tgn:id":7055865,
    "tgn:name":"Piumazzo",
    "tgn:placetype":[
        "aat:300008347"
    ]
},
  "bbox": [],
  "geometry": {"coordinates":[11.066667,44.55],"type":"Point"}
}