<<<<<<< HEAD
{
  "id": 2150482,
  "type": "Feature",
  "properties": {
    "tgn:hierarchy":[
        "tgn:2150482",
        "tgn:1000001",
        "tgn:7012149",
        "tgn:2000183",
        "tgn:7007157",
        "tgn:7029392"
    ],
    "tgn:id":2150482,
    "tgn:name":"Basin Mountain",
    "tgn:placetype":[
        "aat:300008798"
    ]
},
  "bbox": [],
  "geometry": {"coordinates":[-118.65,37.2833],"type":"Point"}
}
=======
{"geometry":{"type":"Point","coordinates":[-118.650000,37.283300]},"type":"Feature","properties":{"hierarchy":["tgn:2150482","tgn:1000001","tgn:7012149","tgn:2000183","tgn:7007157","tgn:7029392"],"placetype":["aat:300008798"],"id":2150482,"name:xx":"Basin Mountain"}}
>>>>>>> 03f74aca74312dbeaf24d7e61306dd6a786dc3d0
