<<<<<<< HEAD
{
  "id": 2409508,
  "type": "Feature",
  "properties": {
    "tgn:hierarchy":[
        "tgn:2409508",
        "tgn:1000001",
        "tgn:7012149",
        "tgn:1002518",
        "tgn:7007568",
        "tgn:7029392"
    ],
    "tgn:id":2409508,
    "tgn:name":"Idlewild Island",
    "tgn:placetype":[
        "aat:300008791"
    ]
},
  "bbox": [],
  "geometry": {"coordinates":[-75.9,44.3667],"type":"Point"}
}
=======
{"geometry":{"type":"Point","coordinates":[-75.900000,44.366700]},"type":"Feature","properties":{"hierarchy":["tgn:2409508","tgn:1000001","tgn:7012149","tgn:1002518","tgn:7007568","tgn:7029392"],"placetype":["aat:300008791"],"id":2409508,"name:xx":"Idlewild Island"}}
>>>>>>> 03f74aca74312dbeaf24d7e61306dd6a786dc3d0
