{
  "id": 1077434,
  "type": "Feature",
  "properties": {
    "tgn:hierarchy":[
        "tgn:1077434",
        "tgn:1000004",
        "tgn:1001502",
        "tgn:1000116",
        "tgn:7029392"
    ],
    "tgn:id":1077434,
    "tgn:name":"Bantaian",
    "tgn:placetype":[
        "aat:300008347"
    ]
},
  "bbox": [],
  "geometry": {"coordinates":[100.95,1.9167],"type":"Point"}
}