<<<<<<< HEAD
{
  "id": 2333705,
  "type": "Feature",
  "properties": {
    "tgn:hierarchy":[
        "tgn:2333705",
        "tgn:1000001",
        "tgn:7012149",
        "tgn:2001897",
        "tgn:7007825",
        "tgn:7029392"
    ],
    "tgn:id":2333705,
    "tgn:name":"Fooshee Island",
    "tgn:placetype":[
        "aat:300008791"
    ]
},
  "bbox": [],
  "geometry": {"coordinates":[-84.7667,35.6667],"type":"Point"}
}
=======
{"geometry":{"type":"Point","coordinates":[-84.766700,35.666700]},"type":"Feature","properties":{"hierarchy":["tgn:2333705","tgn:1000001","tgn:7012149","tgn:2001897","tgn:7007825","tgn:7029392"],"placetype":["aat:300008791"],"id":2333705,"name:xx":"Fooshee Island"}}
>>>>>>> 03f74aca74312dbeaf24d7e61306dd6a786dc3d0
