{
  "id": 7334020,
  "type": "Feature",
  "properties": {
    "tgn:hierarchy":[
        "tgn:7334020",
        "tgn:7002818",
        "tgn:1001647",
        "tgn:1000003",
        "tgn:1000095",
        "tgn:7029392"
    ],
    "tgn:id":7334020,
    "tgn:name":"Embuena, Ca\u00f1ada de la",
    "tgn:placetype":[
        "aat:300266554",
        "aat:300008699"
    ]
},
  "bbox": [],
  "geometry": {"coordinates":[-1.933333,39.816667],"type":"Point"}
}