{
  "id": 2155944,
  "type": "Feature",
  "properties": {
    "tgn:hierarchy":[
        "tgn:2155944",
        "tgn:1000001",
        "tgn:7012149",
        "tgn:7007157",
        "tgn:2000188",
        "tgn:7029392"
    ],
    "tgn:id":2155944,
    "tgn:name":"Bear Wallow",
    "tgn:placetype":[
        "aat:300386845"
    ]
},
  "bbox": [],
  "geometry": {"coordinates":[-121.9833,41.1667],"type":"Point"}
}