<<<<<<< HEAD
{
  "id": 2155944,
  "type": "Feature",
  "properties": {
    "tgn:hierarchy":[
        "tgn:2155944",
        "tgn:1000001",
        "tgn:7012149",
        "tgn:7007157",
        "tgn:2000188",
        "tgn:7029392"
    ],
    "tgn:id":2155944,
    "tgn:name":"Bear Wallow",
    "tgn:placetype":[
        "aat:300386845"
    ]
},
  "bbox": [],
  "geometry": {"coordinates":[-121.9833,41.1667],"type":"Point"}
}
=======
{"geometry":{"type":"Point","coordinates":[-121.983300,41.166700]},"type":"Feature","properties":{"hierarchy":["tgn:2155944","tgn:1000001","tgn:7012149","tgn:7007157","tgn:2000188","tgn:7029392"],"placetype":["aat:300386845"],"id":2155944,"name:xx":"Bear Wallow"}}
>>>>>>> 03f74aca74312dbeaf24d7e61306dd6a786dc3d0
