{
  "id": 7342445,
  "type": "Feature",
  "properties": {
    "tgn:hierarchy":[
        "tgn:7342445",
        "tgn:7002806",
        "tgn:7001158",
        "tgn:1000003",
        "tgn:1000095",
        "tgn:7029392"
    ],
    "tgn:id":7342445,
    "tgn:name":"Candeleda, Puerto de",
    "tgn:placetype":[
        "aat:300259572"
    ]
},
  "bbox": [],
  "geometry": {"coordinates":[-5.25,40.25],"type":"Point"}
}