{
  "id": 7313662,
  "type": "Feature",
  "properties": {
    "tgn:hierarchy":[
        "tgn:7313662",
        "tgn:1001699",
        "tgn:1000049",
        "tgn:1000002",
        "tgn:7029392"
    ],
    "tgn:id":7313662,
    "tgn:name":"La Viguer\u00eda",
    "tgn:placetype":[
        "aat:300387200"
    ]
},
  "bbox": [],
  "geometry": {"coordinates":[-72.333333,-41.383333],"type":"Point"}
}