{
  "id": 2556635,
  "type": "Feature",
  "properties": {
    "tgn:hierarchy":[
        "tgn:2556635",
        "tgn:1000001",
        "tgn:2000260",
        "tgn:7012149",
        "tgn:7007240",
        "tgn:7029392"
    ],
    "tgn:id":2556635,
    "tgn:name":"Old Camp Four Swamp",
    "tgn:placetype":[
        "aat:300008905"
    ]
},
  "bbox": [],
  "geometry": {"coordinates":[-85.35,30.35],"type":"Point"}
}