{
  "id": 1057228,
  "type": "Feature",
  "properties": {
    "tgn:hierarchy":[
        "tgn:1057228",
        "tgn:1000004",
        "tgn:7002435",
        "tgn:7011524",
        "tgn:7029392"
    ],
    "tgn:id":1057228,
    "tgn:name":"Muslyumovo",
    "tgn:placetype":[
        "aat:300008347"
    ]
},
  "bbox": [],
  "geometry": {"coordinates":[53.1667,55.3333],"type":"Point"}
}