{
  "id": 2349794,
  "type": "Feature",
  "properties": {
    "tgn:hierarchy":[
        "tgn:2349794",
        "tgn:1000001",
        "tgn:1002283",
        "tgn:7012149",
        "tgn:7007520",
        "tgn:7029392"
    ],
    "tgn:id":2349794,
    "tgn:name":"Gillison Drain",
    "tgn:placetype":[
        "aat:300006075"
    ]
},
  "bbox": [],
  "geometry": {"coordinates":[-84.5167,42.9833],"type":"Point"}
}