<<<<<<< HEAD
{
  "id": 7241017,
  "type": "Feature",
  "properties": {
    "tgn:hierarchy":[
        "tgn:7241017",
        "tgn:7007877",
        "tgn:1000003",
        "tgn:1000063",
        "tgn:4012014",
        "tgn:7029392"
    ],
    "tgn:id":7241017,
    "tgn:name":"Forges, Bois de",
    "tgn:placetype":[
        "aat:300008863"
    ]
},
  "bbox": [],
  "geometry": {"coordinates":[4.333333,50.0],"type":"Point"}
}
=======
{"geometry":{"type":"Point","coordinates":[4.333333,50.000000]},"type":"Feature","properties":{"hierarchy":["tgn:7241017","tgn:7007877","tgn:1000003","tgn:1000063","tgn:4012014","tgn:7029392"],"placetype":["aat:300008863"],"id":7241017,"name:xx":"Forges, Bois de"}}
>>>>>>> 03f74aca74312dbeaf24d7e61306dd6a786dc3d0
