{
  "id": 2125341,
  "type": "Feature",
  "properties": {
    "tgn:hierarchy":[
        "tgn:2125341",
        "tgn:1000001",
        "tgn:1002194",
        "tgn:7012149",
        "tgn:7007710",
        "tgn:7029392"
    ],
    "tgn:id":2125341,
    "tgn:name":"Ackleys Pond",
    "tgn:placetype":[
        "aat:300006191"
    ]
},
  "bbox": [],
  "geometry": {"coordinates":[-76.3667,41.6667],"type":"Point"}
}