{
  "id": 2097597,
  "type": "Feature",
  "properties": {
    "tgn:hierarchy":[
        "tgn:2097597",
        "tgn:1000001",
        "tgn:2001816",
        "tgn:7012149",
        "tgn:7007713",
        "tgn:7029392"
    ],
    "tgn:id":2097597,
    "tgn:name":"Union Center",
    "tgn:placetype":[
        "aat:300008347"
    ]
},
  "bbox": [],
  "geometry": {"coordinates":[-102.6667,44.55],"type":"Point"}
}