{
  "id": 2159691,
  "type": "Feature",
  "properties": {
    "tgn:hierarchy":[
        "tgn:2159691",
        "tgn:1000001",
        "tgn:7012149",
        "tgn:7007157",
        "tgn:2000185",
        "tgn:7029392"
    ],
    "tgn:id":2159691,
    "tgn:name":"Beebe Creek",
    "tgn:placetype":[
        "aat:300008706"
    ]
},
  "bbox": [],
  "geometry": {"coordinates":[-123.2167,38.9333],"type":"Point"}
}