<<<<<<< HEAD
{
  "id": 2766714,
  "type": "Feature",
  "properties": {
    "tgn:hierarchy":[
        "tgn:2766714",
        "tgn:1000001",
        "tgn:7016172",
        "tgn:2000120",
        "tgn:7012149",
        "tgn:7029392"
    ],
    "tgn:id":2766714,
    "tgn:name":"White Oak Point",
    "tgn:placetype":[
        "aat:300008850"
    ]
},
  "bbox": [],
  "geometry": {"coordinates":[-90.3667,35.9667],"type":"Point"}
}
=======
{"geometry":{"type":"Point","coordinates":[-90.366700,35.966700]},"type":"Feature","properties":{"hierarchy":["tgn:2766714","tgn:1000001","tgn:7016172","tgn:2000120","tgn:7012149","tgn:7029392"],"placetype":["aat:300008850"],"id":2766714,"name:xx":"White Oak Point"}}
>>>>>>> 03f74aca74312dbeaf24d7e61306dd6a786dc3d0
