{
  "id": 2524029,
  "type": "Feature",
  "properties": {
    "tgn:hierarchy":[
        "tgn:2524029",
        "tgn:1000001",
        "tgn:7012149",
        "tgn:2000362",
        "tgn:7007248",
        "tgn:7029392"
    ],
    "tgn:id":2524029,
    "tgn:name":"Morgan",
    "tgn:placetype":[
        "aat:300008347"
    ]
},
  "bbox": [],
  "geometry": {"coordinates":[-85.0667,33.7333],"type":"Point"}
}