{
  "id": 7445148,
  "type": "Feature",
  "properties": {
    "tgn:hierarchy":[
        "tgn:7445148",
        "tgn:7002443",
        "tgn:7017242",
        "tgn:1000003",
        "tgn:7008591",
        "tgn:7029392"
    ],
    "tgn:id":7445148,
    "tgn:name:en":"Troedyraur",
    "tgn:placetype":[
        "aat:300008347"
    ]
},
  "bbox": [],
  "geometry": {"coordinates":[-4.45,52.083333],"type":"Point"}
}