{
  "id": 7132025,
  "type": "Feature",
  "properties": {
    "tgn:hierarchy":[
        "tgn:7132025",
        "tgn:7003669",
        "tgn:1000003",
        "tgn:7000084",
        "tgn:7029392"
    ],
    "tgn:id":7132025,
    "tgn:name":"Mistendorf",
    "tgn:placetype":[
        "aat:300008347"
    ]
},
  "bbox": [],
  "geometry": {"coordinates":[11.016667,49.866667],"type":"Point"}
}