{
  "id": 7501938,
  "type": "Feature",
  "properties": {
    "tgn:hierarchy":[
        "tgn:7501938",
        "tgn:7001004",
        "tgn:1000004",
        "tgn:1000141",
        "tgn:7029392"
    ],
    "tgn:id":7501938,
    "tgn:name":"Wai'an Qiao",
    "tgn:placetype":[
        "aat:300007836"
    ]
},
  "bbox": [],
  "geometry": {"coordinates":[120.388889,22.857778],"type":"Point"}
}