{
  "id": 7243058,
  "type": "Feature",
  "properties": {
    "tgn:hierarchy":[
        "tgn:7243058",
        "tgn:7007877",
        "tgn:1000003",
        "tgn:1000063",
        "tgn:4012014",
        "tgn:7029392"
    ],
    "tgn:id":7243058,
    "tgn:name":"Les Culots",
    "tgn:placetype":[
        "aat:300008347"
    ]
},
  "bbox": [],
  "geometry": {"coordinates":[4.333333,50.65],"type":"Point"}
}