{
  "id": 2231516,
  "type": "Feature",
  "properties": {
    "tgn:hierarchy":[
        "tgn:2231516",
        "tgn:1000001",
        "tgn:2002367",
        "tgn:7012149",
        "tgn:7007923",
        "tgn:7029392"
    ],
    "tgn:id":2231516,
    "tgn:name":"Chalk Hills",
    "tgn:placetype":[
        "aat:300008798"
    ]
},
  "bbox": [],
  "geometry": {"coordinates":[-105.1833,44.1667],"type":"Point"}
}