<<<<<<< HEAD
{
  "id": 2407014,
  "type": "Feature",
  "properties": {
    "tgn:hierarchy":[
        "tgn:2407014",
        "tgn:1000001",
        "tgn:7012149",
        "tgn:2001969",
        "tgn:7007826",
        "tgn:7029392"
    ],
    "tgn:id":2407014,
    "tgn:name":"Hunter Peak",
    "tgn:placetype":[
        "aat:300008798"
    ]
},
  "bbox": [],
  "geometry": {"coordinates":[-104.8167,31.9],"type":"Point"}
}
=======
{"geometry":{"type":"Point","coordinates":[-104.816700,31.900000]},"type":"Feature","properties":{"hierarchy":["tgn:2407014","tgn:1000001","tgn:7012149","tgn:2001969","tgn:7007826","tgn:7029392"],"placetype":["aat:300008798"],"id":2407014,"name:xx":"Hunter Peak"}}
>>>>>>> 03f74aca74312dbeaf24d7e61306dd6a786dc3d0
