{
  "id": 7592582,
  "type": "Feature",
  "properties": {
    "tgn:hierarchy":[
        "tgn:7592582",
        "tgn:1000004",
        "tgn:7000198",
        "tgn:7016788",
        "tgn:7029392"
    ],
    "tgn:id":7592582,
    "tgn:name:en":"Chhilra Johra",
    "tgn:placetype":[
        "aat:300008688"
    ]
},
  "bbox": [],
  "geometry": {"coordinates":[74.534339,28.018158],"type":"Point"}
}