{
  "id": 1129601,
  "type": "Feature",
  "properties": {
    "tgn:hierarchy":[
        "tgn:1129601",
        "tgn:1000525",
        "tgn:1000046",
        "tgn:1000002",
        "tgn:7029392"
    ],
    "tgn:id":1129601,
    "tgn:name":"San Sim\u00f3n, R\u00edo",
    "tgn:placetype":[
        "aat:300008707"
    ]
},
  "bbox": [],
  "geometry": {"coordinates":[-63.516,-13.216],"type":"Point"}
}