{
  "id": 2394098,
  "type": "Feature",
  "properties": {
    "tgn:hierarchy":[
        "tgn:2394098",
        "tgn:7002659",
        "tgn:1000001",
        "tgn:7012149",
        "tgn:2000041",
        "tgn:7029392"
    ],
    "tgn:id":2394098,
    "tgn:name":"Hogan Cave",
    "tgn:placetype":[
        "aat:300008746"
    ]
},
  "bbox": [],
  "geometry": {"coordinates":[-86.85,34.95],"type":"Point"}
}