<<<<<<< HEAD
{
  "id": 2156024,
  "type": "Feature",
  "properties": {
    "tgn:hierarchy":[
        "tgn:2156024",
        "tgn:1000001",
        "tgn:7012149",
        "tgn:7007157",
        "tgn:1002828",
        "tgn:7029392"
    ],
    "tgn:id":2156024,
    "tgn:name":"Bear Wallow Spring",
    "tgn:placetype":[
        "aat:300008697"
    ]
},
  "bbox": [],
  "geometry": {"coordinates":[-116.75,34.0],"type":"Point"}
}
=======
{"geometry":{"type":"Point","coordinates":[-116.750000,34.000000]},"type":"Feature","properties":{"hierarchy":["tgn:2156024","tgn:1000001","tgn:7012149","tgn:7007157","tgn:1002828","tgn:7029392"],"placetype":["aat:300008697"],"id":2156024,"name:xx":"Bear Wallow Spring"}}
>>>>>>> 03f74aca74312dbeaf24d7e61306dd6a786dc3d0
