{
  "id": 2053873,
  "type": "Feature",
  "properties": {
    "tgn:hierarchy":[
        "tgn:2053873",
        "tgn:1000001",
        "tgn:7012149",
        "tgn:2001056",
        "tgn:7007521",
        "tgn:7029392"
    ],
    "tgn:id":2053873,
    "tgn:name":"Askov",
    "tgn:placetype":[
        "aat:300008347"
    ]
},
  "bbox": [],
  "geometry": {"coordinates":[-92.7667,46.1833],"type":"Point"}
}