{
  "id": 7530369,
  "type": "Feature",
  "properties": {
    "tgn:hierarchy":[
        "tgn:7530369",
        "tgn:7001242",
        "tgn:7016833",
        "tgn:7029392"
    ],
    "tgn:id":7530369,
    "tgn:name:en":"Tur'at al Was\u0163\u0101n\u012b",
    "tgn:placetype":[
        "aat:300006075"
    ]
},
  "bbox": [],
  "geometry": {"coordinates":[30.0609,31.192636],"type":"Point"}
}