{
  "id": 7397485,
  "type": "Feature",
  "properties": {
    "tgn:hierarchy":[
        "tgn:7397485",
        "tgn:7005581",
        "tgn:1000001",
        "tgn:7005560",
        "tgn:7029392"
    ],
    "tgn:id":7397485,
    "tgn:name":"Rancho Santa Rosa",
    "tgn:placetype":[
        "aat:300000241"
    ]
},
  "bbox": [],
  "geometry": {"coordinates":[-106.516667,28.85],"type":"Point"}
}