{
  "id": 2361737,
  "type": "Feature",
  "properties": {
    "tgn:hierarchy":[
        "tgn:2361737",
        "tgn:1000001",
        "tgn:7012149",
        "tgn:2001924",
        "tgn:7007825",
        "tgn:7029392"
    ],
    "tgn:id":2361737,
    "tgn:name":"Graveyard Ridge",
    "tgn:placetype":[
        "aat:300266640"
    ]
},
  "bbox": [],
  "geometry": {"coordinates":[-85.3167,35.7833],"type":"Point"}
}