<<<<<<< HEAD
{
  "id": 7111024,
  "type": "Feature",
  "properties": {
    "tgn:hierarchy":[
        "tgn:7111024",
        "tgn:7003669",
        "tgn:1000003",
        "tgn:7000084",
        "tgn:7029392"
    ],
    "tgn:id":7111024,
    "tgn:name":"Renkbach",
    "tgn:placetype":[
        "aat:300008699"
    ]
},
  "bbox": [],
  "geometry": {"coordinates":[9.85,49.65],"type":"Point"}
}
=======
{"geometry":{"type":"Point","coordinates":[9.850000,49.650000]},"type":"Feature","properties":{"hierarchy":["tgn:7111024","tgn:7003669","tgn:1000003","tgn:7000084","tgn:7029392"],"placetype":["aat:300008699"],"id":7111024,"name:xx":"Renkbach"}}
>>>>>>> 03f74aca74312dbeaf24d7e61306dd6a786dc3d0
