{
  "id": 2104675,
  "type": "Feature",
  "properties": {
    "tgn:hierarchy":[
        "tgn:2104675",
        "tgn:1000001",
        "tgn:7012149",
        "tgn:2001982",
        "tgn:7007826",
        "tgn:7029392"
    ],
    "tgn:id":2104675,
    "tgn:name":"Hannibal",
    "tgn:placetype":[
        "aat:300008347",
        "aat:300387210"
    ]
},
  "bbox": [],
  "geometry": {"coordinates":[-98.3333,32.3667],"type":"Point"}
}