{
  "id": 2525813,
  "type": "Feature",
  "properties": {
    "tgn:hierarchy":[
        "tgn:2525813",
        "tgn:1000001",
        "tgn:7012149",
        "tgn:2001556",
        "tgn:7007709",
        "tgn:7029392"
    ],
    "tgn:id":2525813,
    "tgn:name":"Moses Branch",
    "tgn:placetype":[
        "aat:300008699"
    ]
},
  "bbox": [],
  "geometry": {"coordinates":[-82.3167,35.9667],"type":"Point"}
}