{
  "id": 7164598,
  "type": "Feature",
  "properties": {
    "tgn:hierarchy":[
        "tgn:7164598",
        "tgn:1000003",
        "tgn:7003673",
        "tgn:7000084",
        "tgn:7029392"
    ],
    "tgn:id":7164598,
    "tgn:name":"Howe",
    "tgn:placetype":[
        "aat:300008347"
    ]
},
  "bbox": [],
  "geometry": {"coordinates":[10.15,53.416667],"type":"Point"}
}