{
  "id": 7509519,
  "type": "Feature",
  "properties": {
    "tgn:hierarchy":[
        "tgn:7509519",
        "tgn:1008380",
        "tgn:1000226",
        "tgn:7016827",
        "tgn:1000006",
        "tgn:7029392"
    ],
    "tgn:id":7509519,
    "tgn:name:en":"Waikauau, River",
    "tgn:placetype":[
        "aat:300008699"
    ]
},
  "bbox": [],
  "geometry": {"coordinates":[174.633333,-38.483333],"type":"Point"}
}