{
  "id": 2575656,
  "type": "Feature",
  "properties": {
    "tgn:hierarchy":[
        "tgn:2575656",
        "tgn:7002659",
        "tgn:1000001",
        "tgn:7012149",
        "tgn:2000030",
        "tgn:7029392"
    ],
    "tgn:id":2575656,
    "tgn:name":"Pera",
    "tgn:placetype":[
        "aat:300008347"
    ]
},
  "bbox": [],
  "geometry": {"coordinates":[-86.0833,31.1333],"type":"Point"}
}