{
  "id": 7541075,
  "type": "Feature",
  "properties": {
    "tgn:hierarchy":[
        "tgn:7541075",
        "tgn:7001242",
        "tgn:7016833",
        "tgn:7029392"
    ],
    "tgn:id":7541075,
    "tgn:name":"Tur'at 'Abd al '\u0100l A\u015fl\u012b",
    "tgn:placetype":[
        "aat:300006075"
    ]
},
  "bbox": [],
  "geometry": {"coordinates":[31.120518,30.037036],"type":"Point"}
}