{
  "id": 2349050,
  "type": "Feature",
  "properties": {
    "tgn:hierarchy":[
        "tgn:2349050",
        "tgn:1000001",
        "tgn:7006451",
        "tgn:2000094",
        "tgn:7012149",
        "tgn:7029392"
    ],
    "tgn:id":2349050,
    "tgn:name":"Gila Box",
    "tgn:placetype":[
        "aat:300008761"
    ]
},
  "bbox": [],
  "geometry": {"coordinates":[-109.3667,32.9667],"type":"Point"}
}