{
  "id": 7507334,
  "type": "Feature",
  "properties": {
    "tgn:hierarchy":[
        "tgn:7507334",
        "tgn:1008380",
        "tgn:7000507",
        "tgn:1000226",
        "tgn:1000006",
        "tgn:7029392"
    ],
    "tgn:id":7507334,
    "tgn:name:en":"Pukenuiorongo",
    "tgn:placetype":[
        "aat:300008777"
    ]
},
  "bbox": [],
  "geometry": {"coordinates":[173.45,-35.633333],"type":"Point"}
}