{
  "id": 7552749,
  "type": "Feature",
  "properties": {
    "tgn:hierarchy":[
        "tgn:7552749",
        "tgn:1001828",
        "tgn:1000004",
        "tgn:7000198",
        "tgn:7029392"
    ],
    "tgn:id":7552749,
    "tgn:name:en":"Mughalgidda",
    "tgn:placetype":[
        "aat:300008347"
    ]
},
  "bbox": [],
  "geometry": {"coordinates":[78.121111,17.088889],"type":"Point"}
}