{
  "id": 7283456,
  "type": "Feature",
  "properties": {
    "tgn:hierarchy":[
        "tgn:7283456",
        "tgn:1001768",
        "tgn:1000049",
        "tgn:1000002",
        "tgn:7029392"
    ],
    "tgn:id":7283456,
    "tgn:name":"Parada Portillo",
    "tgn:placetype":[
        "aat:300008347"
    ]
},
  "bbox": [],
  "geometry": {"coordinates":[-70.15,-32.833333],"type":"Point"}
}