{
  "id": 7122488,
  "type": "Feature",
  "properties": {
    "tgn:hierarchy":[
        "tgn:7122488",
        "tgn:1000003",
        "tgn:7003677",
        "tgn:7000084",
        "tgn:7029392"
    ],
    "tgn:id":7122488,
    "tgn:name":"Niederoesterweg",
    "tgn:placetype":[
        "aat:300387200"
    ]
},
  "bbox": [],
  "geometry": {"coordinates":[8.183333,52.033333],"type":"Point"}
}