{
  "id": 2478401,
  "type": "Feature",
  "properties": {
    "tgn:hierarchy":[
        "tgn:2478401",
        "tgn:1000001",
        "tgn:2001785",
        "tgn:7012149",
        "tgn:7007713",
        "tgn:7029392"
    ],
    "tgn:id":2478401,
    "tgn:name":"Mad Bear Creek",
    "tgn:placetype":[
        "aat:300008706"
    ]
},
  "bbox": [],
  "geometry": {"coordinates":[-100.3833,45.75],"type":"Point"}
}