{
  "id": 7594191,
  "type": "Feature",
  "properties": {
    "tgn:hierarchy":[
        "tgn:7594191",
        "tgn:1000003",
        "tgn:7005729",
        "tgn:7029392"
    ],
    "tgn:id":7594191,
    "tgn:name":"Imtarfa",
    "tgn:placetype":[
        "aat:300387064",
        "aat:300387205"
    ]
},
  "bbox": [],
  "geometry": {"coordinates":[14.397222,35.890556],"type":"Point"}
}