{
  "id": 2776423,
  "type": "Feature",
  "properties": {
    "tgn:hierarchy":[
        "tgn:2776423",
        "tgn:1000001",
        "tgn:7012149",
        "tgn:1002815",
        "tgn:7007922",
        "tgn:7029392"
    ],
    "tgn:id":2776423,
    "tgn:name":"Wind Lake Drainage Canal",
    "tgn:placetype":[
        "aat:300006075"
    ]
},
  "bbox": [],
  "geometry": {"coordinates":[-88.15,42.7667],"type":"Point"}
}