{
  "id": 2158361,
  "type": "Feature",
  "properties": {
    "tgn:hierarchy":[
        "tgn:2158361",
        "tgn:1000001",
        "tgn:7012149",
        "tgn:2001510",
        "tgn:7007709",
        "tgn:7029392"
    ],
    "tgn:id":2158361,
    "tgn:name":"Beaverdam Branch",
    "tgn:placetype":[
        "aat:300008699"
    ]
},
  "bbox": [],
  "geometry": {"coordinates":[-77.2833,34.9667],"type":"Point"}
}