{
  "id": 1051473,
  "type": "Feature",
  "properties": {
    "tgn:hierarchy":[
        "tgn:1051473",
        "tgn:1000004",
        "tgn:7011457",
        "tgn:7014786",
        "tgn:7029392"
    ],
    "tgn:id":1051473,
    "tgn:name":"Shchapov",
    "tgn:placetype":[
        "aat:300008347"
    ]
},
  "bbox": [],
  "geometry": {"coordinates":[51.1833,51.0167],"type":"Point"}
}