<<<<<<< HEAD
{
  "id": 7114992,
  "type": "Feature",
  "properties": {
    "tgn:hierarchy":[
        "tgn:7114992",
        "tgn:7003669",
        "tgn:1000003",
        "tgn:7000084",
        "tgn:7029392"
    ],
    "tgn:id":7114992,
    "tgn:name":"Oberroth",
    "tgn:placetype":[
        "aat:300008347"
    ]
},
  "bbox": [],
  "geometry": {"coordinates":[11.333333,48.3],"type":"Point"}
}
=======
{"geometry":{"type":"Point","coordinates":[11.333333,48.300000]},"type":"Feature","properties":{"hierarchy":["tgn:7114992","tgn:7003669","tgn:1000003","tgn:7000084","tgn:7029392"],"placetype":["aat:300008347"],"id":7114992,"name:xx":"Oberroth"}}
>>>>>>> 03f74aca74312dbeaf24d7e61306dd6a786dc3d0
