{
  "id": 7269567,
  "type": "Feature",
  "properties": {
    "tgn:concordances":{
        "gn:id":"2751176"
    },
    "tgn:hierarchy":[
        "tgn:7269567",
        "tgn:7003619",
        "tgn:1000003",
        "tgn:7016845",
        "tgn:7029392"
    ],
    "tgn:id":7269567,
    "tgn:name:nl":"Mari\u00ebnboom",
    "tgn:placetype":[
        "aat:300008347"
    ]
},
  "bbox": [],
  "geometry": {"coordinates":[5.883333,51.833333],"type":"Point"}
}