{
  "id": 7166240,
  "type": "Feature",
  "properties": {
    "tgn:hierarchy":[
        "tgn:7166240",
        "tgn:7003692",
        "tgn:1000003",
        "tgn:7000084",
        "tgn:7029392"
    ],
    "tgn:id":7166240,
    "tgn:name":"H\u00e4userhof",
    "tgn:placetype":[
        "aat:300000206"
    ]
},
  "bbox": [],
  "geometry": {"coordinates":[8.466667,47.633333],"type":"Point"}
}