{
  "id": 2471403,
  "type": "Feature",
  "properties": {
    "tgn:hierarchy":[
        "tgn:2471403",
        "tgn:1000001",
        "tgn:2000949",
        "tgn:7012149",
        "tgn:7007520",
        "tgn:7029392"
    ],
    "tgn:id":2471403,
    "tgn:name":"Lost Lake",
    "tgn:placetype":[
        "aat:300008680"
    ]
},
  "bbox": [],
  "geometry": {"coordinates":[-85.8667,44.5833],"type":"Point"}
}