{
  "id": 7314320,
  "type": "Feature",
  "properties": {
    "tgn:hierarchy":[
        "tgn:7314320",
        "tgn:1001695",
        "tgn:1000049",
        "tgn:1000002",
        "tgn:7029392"
    ],
    "tgn:id":7314320,
    "tgn:name":"La Torcaza, Quebrada",
    "tgn:placetype":[
        "aat:300008699"
    ]
},
  "bbox": [],
  "geometry": {"coordinates":[-70.883333,-34.783333],"type":"Point"}
}