<<<<<<< HEAD
{
  "id": 2257772,
  "type": "Feature",
  "properties": {
    "tgn:hierarchy":[
        "tgn:2257772",
        "tgn:1000001",
        "tgn:7012149",
        "tgn:2002110",
        "tgn:7007827",
        "tgn:7029392"
    ],
    "tgn:id":2257772,
    "tgn:name":"Corral Point",
    "tgn:placetype":[
        "aat:300008850"
    ]
},
  "bbox": [],
  "geometry": {"coordinates":[-109.4333,39.0833],"type":"Point"}
}
=======
{"geometry":{"type":"Point","coordinates":[-109.433300,39.083300]},"type":"Feature","properties":{"hierarchy":["tgn:2257772","tgn:1000001","tgn:7012149","tgn:2002110","tgn:7007827","tgn:7029392"],"placetype":["aat:300008850"],"id":2257772,"name:xx":"Corral Point"}}
>>>>>>> 03f74aca74312dbeaf24d7e61306dd6a786dc3d0
