{
  "id": 2268298,
  "type": "Feature",
  "properties": {
    "tgn:hierarchy":[
        "tgn:2268298",
        "tgn:1000001",
        "tgn:7012149",
        "tgn:2001058",
        "tgn:7007521",
        "tgn:7029392"
    ],
    "tgn:id":2268298,
    "tgn:name":"Crooked Lake",
    "tgn:placetype":[
        "aat:300008680"
    ]
},
  "bbox": [],
  "geometry": {"coordinates":[-96.0833,47.5667],"type":"Point"}
}