{
  "id": 1138144,
  "type": "Feature",
  "properties": {
    "tgn:hierarchy":[
        "tgn:1138144",
        "tgn:7013670",
        "tgn:1000004",
        "tgn:7018214",
        "tgn:7002435",
        "tgn:7029392"
    ],
    "tgn:id":1138144,
    "tgn:name":"Ozerki",
    "tgn:placetype":[
        "aat:300008347"
    ]
},
  "bbox": [],
  "geometry": {"coordinates":[83.7333,53.6833],"type":"Point"}
}