{
  "id": 2511766,
  "type": "Feature",
  "properties": {
    "tgn:hierarchy":[
        "tgn:2511766",
        "tgn:1000001",
        "tgn:7012149",
        "tgn:2001208",
        "tgn:7007523",
        "tgn:7029392"
    ],
    "tgn:id":2511766,
    "tgn:name":"Military Lake",
    "tgn:placetype":[
        "aat:300006191"
    ]
},
  "bbox": [],
  "geometry": {"coordinates":[-94.45,38.95],"type":"Point"}
}