{
  "id": 7040288,
  "type": "Feature",
  "properties": {
    "tgn:hierarchy":[
        "tgn:7040288",
        "tgn:1003489",
        "tgn:7004610",
        "tgn:1000003",
        "tgn:1000080",
        "tgn:7029392"
    ],
    "tgn:id":7040288,
    "tgn:name":"Sarconi",
    "tgn:placetype":[
        "aat:300008347"
    ]
},
  "bbox": [],
  "geometry": {"coordinates":[15.883333,40.25],"type":"Point"}
}