{
  "id": 2141032,
  "type": "Feature",
  "properties": {
    "tgn:hierarchy":[
        "tgn:2141032",
        "tgn:1000001",
        "tgn:7012149",
        "tgn:2002112",
        "tgn:7007827",
        "tgn:7029392"
    ],
    "tgn:id":2141032,
    "tgn:name":"Avocet Pool",
    "tgn:placetype":[
        "aat:300006191"
    ]
},
  "bbox": [],
  "geometry": {"coordinates":[-113.35,39.8333],"type":"Point"}
}