{
  "id": 2297442,
  "type": "Feature",
  "properties": {
    "tgn:hierarchy":[
        "tgn:2297442",
        "tgn:1000001",
        "tgn:7012149",
        "tgn:1002877",
        "tgn:7007706",
        "tgn:7029392"
    ],
    "tgn:id":2297442,
    "tgn:name":"Dry Fork",
    "tgn:placetype":[
        "aat:300008699"
    ]
},
  "bbox": [],
  "geometry": {"coordinates":[-83.2167,38.9833],"type":"Point"}
}