{
  "id": 7584444,
  "type": "Feature",
  "properties": {
    "tgn:hierarchy":[
        "tgn:7584444",
        "tgn:1000004",
        "tgn:7000198",
        "tgn:7016788",
        "tgn:7029392"
    ],
    "tgn:id":7584444,
    "tgn:name:en":"Churela",
    "tgn:placetype":[
        "aat:300008347"
    ]
},
  "bbox": [],
  "geometry": {"coordinates":[75.258191,28.170883],"type":"Point"}
}