{
  "id": 2072259,
  "type": "Feature",
  "properties": {
    "tgn:hierarchy":[
        "tgn:2072259",
        "tgn:1000001",
        "tgn:7012149",
        "tgn:7014612",
        "tgn:7007568",
        "tgn:7029392"
    ],
    "tgn:id":2072259,
    "tgn:name":"Shenorock",
    "tgn:placetype":[
        "aat:300008347"
    ]
},
  "bbox": [],
  "geometry": {"coordinates":[-73.7333,41.3167],"type":"Point"}
}