{
  "id": 7488839,
  "type": "Feature",
  "properties": {
    "tgn:hierarchy":[
        "tgn:7488839",
        "tgn:1000004",
        "tgn:7492971",
        "tgn:1000141",
        "tgn:7029392"
    ],
    "tgn:id":7488839,
    "tgn:name":"Nanwan Li",
    "tgn:placetype":[
        "aat:300387173"
    ]
},
  "bbox": [],
  "geometry": {"coordinates":[120.769167,21.963611],"type":"Point"}
}