{
  "id": 7111641,
  "type": "Feature",
  "properties": {
    "tgn:hierarchy":[
        "tgn:7111641",
        "tgn:1000003",
        "tgn:7003677",
        "tgn:7000084",
        "tgn:7029392"
    ],
    "tgn:id":7111641,
    "tgn:name":"Rippelbaum",
    "tgn:placetype":[
        "aat:300387200"
    ]
},
  "bbox": [],
  "geometry": {"coordinates":[8.066667,52.033333],"type":"Point"}
}