{
  "id": 7162628,
  "type": "Feature",
  "properties": {
    "tgn:hierarchy":[
        "tgn:7162628",
        "tgn:1000003",
        "tgn:7003682",
        "tgn:7000084",
        "tgn:7029392"
    ],
    "tgn:id":7162628,
    "tgn:name":"Ingenheim",
    "tgn:placetype":[
        "aat:300000745"
    ]
},
  "bbox": [],
  "geometry": {"coordinates":[8.081389,49.135],"type":"Point"}
}