{
  "id": 7392242,
  "type": "Feature",
  "properties": {
    "tgn:hierarchy":[
        "tgn:7392242",
        "tgn:1001853",
        "tgn:1000001",
        "tgn:7005560",
        "tgn:7029392"
    ],
    "tgn:id":7392242,
    "tgn:name":"Rancho El Gavillero",
    "tgn:placetype":[
        "aat:300008347"
    ]
},
  "bbox": [],
  "geometry": {"coordinates":[-100.466667,25.233333],"type":"Point"}
}