<<<<<<< HEAD
{
  "id": 7351327,
  "type": "Feature",
  "properties": {
    "tgn:hierarchy":[
        "tgn:7351327",
        "tgn:7005581",
        "tgn:1000001",
        "tgn:7005560",
        "tgn:7029392"
    ],
    "tgn:id":7351327,
    "tgn:name":"Areponapuchic",
    "tgn:placetype":[
        "aat:300008347"
    ]
},
  "bbox": [],
  "geometry": {"coordinates":[-107.833333,27.516667],"type":"Point"}
}
=======
{"geometry":{"type":"Point","coordinates":[-107.833333,27.516667]},"type":"Feature","properties":{"hierarchy":["tgn:7351327","tgn:7005581","tgn:1000001","tgn:7005560","tgn:7029392"],"placetype":["aat:300008347"],"id":7351327,"name:xx":"Areponapuchic"}}
>>>>>>> 03f74aca74312dbeaf24d7e61306dd6a786dc3d0
