{
  "id": 2749746,
  "type": "Feature",
  "properties": {
    "tgn:hierarchy":[
        "tgn:2749746",
        "tgn:1000001",
        "tgn:7012149",
        "tgn:2001461",
        "tgn:7007568",
        "tgn:7029392"
    ],
    "tgn:id":2749746,
    "tgn:name":"Walnut Hill",
    "tgn:placetype":[
        "aat:300008798"
    ]
},
  "bbox": [],
  "geometry": {"coordinates":[-73.5167,43.9667],"type":"Point"}
}