{
  "id": 2144514,
  "type": "Feature",
  "properties": {
    "tgn:hierarchy":[
        "tgn:2144514",
        "tgn:7006450",
        "tgn:1000001",
        "tgn:7012149",
        "tgn:2000082",
        "tgn:7029392"
    ],
    "tgn:id":2144514,
    "tgn:name":"Bakewell Lake",
    "tgn:placetype":[
        "aat:300008680"
    ]
},
  "bbox": [],
  "geometry": {"coordinates":[-130.6667,55.25],"type":"Point"}
}