<<<<<<< HEAD
{
  "id": 7362668,
  "type": "Feature",
  "properties": {
    "tgn:hierarchy":[
        "tgn:7362668",
        "tgn:1000001",
        "tgn:1001960",
        "tgn:7005560",
        "tgn:7029392"
    ],
    "tgn:id":7362668,
    "tgn:name":"Rancho El Durazno",
    "tgn:placetype":[
        "aat:300000241"
    ]
},
  "bbox": [],
  "geometry": {"coordinates":[-110.233333,30.516667],"type":"Point"}
}
=======
{"geometry":{"type":"Point","coordinates":[-110.233333,30.516667]},"type":"Feature","properties":{"hierarchy":["tgn:7362668","tgn:1000001","tgn:1001960","tgn:7005560","tgn:7029392"],"placetype":["aat:300000241"],"id":7362668,"name:xx":"Rancho El Durazno"}}
>>>>>>> 03f74aca74312dbeaf24d7e61306dd6a786dc3d0
