{
  "id": 7228658,
  "type": "Feature",
  "properties": {
    "tgn:hierarchy":[
        "tgn:7228658",
        "tgn:7002681",
        "tgn:7001395",
        "tgn:1000003",
        "tgn:1000074",
        "tgn:7029392"
    ],
    "tgn:id":7228658,
    "tgn:name":"Kokk\u00e1loi",
    "tgn:placetype":[
        "aat:300008347"
    ]
},
  "bbox": [],
  "geometry": {"coordinates":[24.416667,38.033333],"type":"Point"}
}