{
  "id": 2627517,
  "type": "Feature",
  "properties": {
    "tgn:hierarchy":[
        "tgn:2627517",
        "tgn:1000001",
        "tgn:2001640",
        "tgn:7012149",
        "tgn:7007707",
        "tgn:7029392"
    ],
    "tgn:id":2627517,
    "tgn:name":"Rogers",
    "tgn:placetype":[
        "aat:300008347"
    ]
},
  "bbox": [],
  "geometry": {"coordinates":[-95.1833,36.9167],"type":"Point"}
}