<<<<<<< HEAD
{
  "id": 7481586,
  "type": "Feature",
  "properties": {
    "tgn:hierarchy":[
        "tgn:7481586",
        "tgn:1000004",
        "tgn:7492971",
        "tgn:1000141",
        "tgn:7029392"
    ],
    "tgn:id":7481586,
    "tgn:name":"Zhenfengshi",
    "tgn:placetype":[
        "aat:300008798"
    ]
},
  "bbox": [],
  "geometry": {"coordinates":[120.687776,22.688135],"type":"Point"}
}
=======
{"geometry":{"type":"Point","coordinates":[120.687776,22.688135]},"type":"Feature","properties":{"hierarchy":["tgn:7481586","tgn:1000004","tgn:7492971","tgn:1000141","tgn:7029392"],"placetype":["aat:300008798"],"id":7481586,"name:xx":"Zhenfengshi"}}
>>>>>>> 03f74aca74312dbeaf24d7e61306dd6a786dc3d0
