{
  "id": 2396889,
  "type": "Feature",
  "properties": {
    "tgn:hierarchy":[
        "tgn:2396889",
        "tgn:1000001",
        "tgn:7012149",
        "tgn:2000237",
        "tgn:7007158",
        "tgn:7029392"
    ],
    "tgn:id":2396889,
    "tgn:name":"Homer Brown Spring",
    "tgn:placetype":[
        "aat:300008697"
    ]
},
  "bbox": [],
  "geometry": {"coordinates":[-107.8167,38.0667],"type":"Point"}
}