{
  "id": 7371465,
  "type": "Feature",
  "properties": {
    "tgn:hierarchy":[
        "tgn:7371465",
        "tgn:1000001",
        "tgn:7005589",
        "tgn:7005560",
        "tgn:7029392"
    ],
    "tgn:id":7371465,
    "tgn:name":"Hacienda Santa Magadalena",
    "tgn:placetype":[
        "aat:300008347"
    ]
},
  "bbox": [],
  "geometry": {"coordinates":[-99.733333,26.166667],"type":"Point"}
}