{
  "id": 7502316,
  "type": "Feature",
  "properties": {
    "tgn:hierarchy":[
        "tgn:7502316",
        "tgn:7001010",
        "tgn:1000004",
        "tgn:1000141",
        "tgn:7029392"
    ],
    "tgn:id":7502316,
    "tgn:name":"Xinji Qiao",
    "tgn:placetype":[
        "aat:300007836"
    ]
},
  "bbox": [],
  "geometry": {"coordinates":[121.551111,23.696389],"type":"Point"}
}