{
  "id": 2502393,
  "type": "Feature",
  "properties": {
    "tgn:hierarchy":[
        "tgn:2502393",
        "tgn:1000001",
        "tgn:7012149",
        "tgn:7007157",
        "tgn:1002791",
        "tgn:7029392"
    ],
    "tgn:id":2502393,
    "tgn:name":"McKinstry Peak",
    "tgn:placetype":[
        "aat:300008798"
    ]
},
  "bbox": [],
  "geometry": {"coordinates":[-120.3333,39.05],"type":"Point"}
}