{
  "id": 7516516,
  "type": "Feature",
  "properties": {
    "tgn:hierarchy":[
        "tgn:7516516",
        "tgn:1008380",
        "tgn:1000226",
        "tgn:7018426",
        "tgn:1000006",
        "tgn:7029392"
    ],
    "tgn:id":7516516,
    "tgn:name:en":"Mokauiti",
    "tgn:placetype":[
        "aat:300008347"
    ]
},
  "bbox": [],
  "geometry": {"coordinates":[175.166667,-38.583333],"type":"Point"}
}