{
  "id": 2335884,
  "type": "Feature",
  "properties": {
    "tgn:hierarchy":[
        "tgn:2335884",
        "tgn:1000001",
        "tgn:2001642",
        "tgn:7012149",
        "tgn:7007707",
        "tgn:7029392"
    ],
    "tgn:id":2335884,
    "tgn:name":"Foss Reservoir",
    "tgn:placetype":[
        "aat:300006191"
    ]
},
  "bbox": [],
  "geometry": {"coordinates":[-99.25,35.6167],"type":"Point"}
}