{
  "id": 7396178,
  "type": "Feature",
  "properties": {
    "tgn:hierarchy":[
        "tgn:7396178",
        "tgn:7005586",
        "tgn:1000001",
        "tgn:7005560",
        "tgn:7029392"
    ],
    "tgn:id":7396178,
    "tgn:name":"San Jer\u00f3nimo",
    "tgn:placetype":[
        "aat:300008347"
    ]
},
  "bbox": [],
  "geometry": {"coordinates":[-103.983333,22.683333],"type":"Point"}
}