{
  "id": 2595078,
  "type": "Feature",
  "properties": {
    "tgn:hierarchy":[
        "tgn:2595078",
        "tgn:1000001",
        "tgn:7012149",
        "tgn:7007826",
        "tgn:7029392"
    ],
    "tgn:id":2595078,
    "tgn:name":"Post Oak Draw",
    "tgn:placetype":[
        "aat:300008761"
    ]
},
  "bbox": [],
  "geometry": {"coordinates":[-99.75,30.0833],"type":"Point"}
}