{
  "id": 7561790,
  "type": "Feature",
  "properties": {
    "tgn:hierarchy":[
        "tgn:7561790",
        "tgn:1000004",
        "tgn:7000198",
        "tgn:7016722",
        "tgn:7029392"
    ],
    "tgn:id":7561790,
    "tgn:name:en":"Dharmangadpur",
    "tgn:placetype":[
        "aat:300008347"
    ]
},
  "bbox": [],
  "geometry": {"coordinates":[79.281061,27.124638],"type":"Point"}
}