{
  "id": 2360147,
  "type": "Feature",
  "properties": {
    "tgn:hierarchy":[
        "tgn:2360147",
        "tgn:1000001",
        "tgn:2001819",
        "tgn:7012149",
        "tgn:7007713",
        "tgn:7029392"
    ],
    "tgn:id":2360147,
    "tgn:name":"Grass Lake",
    "tgn:placetype":[
        "aat:300008680"
    ]
},
  "bbox": [],
  "geometry": {"coordinates":[-97.0333,43.5833],"type":"Point"}
}