{
  "id": 7546245,
  "type": "Feature",
  "properties": {
    "tgn:hierarchy":[
        "tgn:7546245",
        "tgn:1001828",
        "tgn:1000004",
        "tgn:7000198",
        "tgn:7029392"
    ],
    "tgn:id":7546245,
    "tgn:name:en":"Anantas\u0101garam",
    "tgn:placetype":[
        "aat:300008347"
    ]
},
  "bbox": [],
  "geometry": {"coordinates":[79.416667,14.583333],"type":"Point"}
}