<<<<<<< HEAD
{
  "id": 7369635,
  "type": "Feature",
  "properties": {
    "tgn:hierarchy":[
        "tgn:7369635",
        "tgn:1001836",
        "tgn:1000001",
        "tgn:7005560",
        "tgn:7029392"
    ],
    "tgn:id":7369635,
    "tgn:name":"Guaiparin",
    "tgn:placetype":[
        "aat:300008347"
    ]
},
  "bbox": [],
  "geometry": {"coordinates":[-110.2,24.033333],"type":"Point"}
}
=======
{"geometry":{"type":"Point","coordinates":[-110.200000,24.033333]},"type":"Feature","properties":{"hierarchy":["tgn:7369635","tgn:1001836","tgn:1000001","tgn:7005560","tgn:7029392"],"placetype":["aat:300008347"],"id":7369635,"name:xx":"Guaiparin"}}
>>>>>>> 03f74aca74312dbeaf24d7e61306dd6a786dc3d0
