{
  "id": 7226912,
  "type": "Feature",
  "properties": {
    "tgn:hierarchy":[
        "tgn:7226912",
        "tgn:7002690",
        "tgn:7012056",
        "tgn:1000003",
        "tgn:1000074",
        "tgn:7029392"
    ],
    "tgn:id":7226912,
    "tgn:name":"Prasson\u00edsi, Nis\u00eds",
    "tgn:placetype":[
        "aat:300008791"
    ]
},
  "bbox": [],
  "geometry": {"coordinates":[23.533333,35.266667],"type":"Point"}
}