{
  "id": 7088217,
  "type": "Feature",
  "properties": {
    "tgn:hierarchy":[
        "tgn:7088217",
        "tgn:7003692",
        "tgn:1000003",
        "tgn:7000084",
        "tgn:7029392"
    ],
    "tgn:id":7088217,
    "tgn:name":"Weilenberg",
    "tgn:placetype":[
        "aat:300266640"
    ]
},
  "bbox": [],
  "geometry": {"coordinates":[8.716667,48.166667],"type":"Point"}
}