{
  "id": 1077393,
  "type": "Feature",
  "properties": {
    "tgn:hierarchy":[
        "tgn:1077393",
        "tgn:1000004",
        "tgn:1009293",
        "tgn:1001467",
        "tgn:1000116",
        "tgn:7029392"
    ],
    "tgn:id":1077393,
    "tgn:name":"Baing",
    "tgn:placetype":[
        "aat:300008347"
    ]
},
  "bbox": [],
  "geometry": {"coordinates":[120.5667,-10.2333],"type":"Point"}
}