{
  "id": 7468311,
  "type": "Feature",
  "properties": {
    "tgn:hierarchy":[
        "tgn:7468311",
        "tgn:1000004",
        "tgn:7492971",
        "tgn:1000141",
        "tgn:7029392"
    ],
    "tgn:id":7468311,
    "tgn:name":"Qijia Xi",
    "tgn:placetype":[
        "aat:300008699"
    ]
},
  "bbox": [],
  "geometry": {"coordinates":[120.686111,22.446667],"type":"Point"}
}