{
  "id": 1018152,
  "type": "Feature",
  "properties": {
    "tgn:hierarchy":[
        "tgn:1018152",
        "tgn:1000001",
        "tgn:7005597",
        "tgn:7005560",
        "tgn:7029392"
    ],
    "tgn:id":1018152,
    "tgn:name":"San Antonio Nogalar",
    "tgn:placetype":[
        "aat:300008347"
    ]
},
  "bbox": [],
  "geometry": {"coordinates":[-98.416667,23.066667],"type":"Point"}
}