{
  "id": 2710520,
  "type": "Feature",
  "properties": {
    "tgn:hierarchy":[
        "tgn:2710520",
        "tgn:1000001",
        "tgn:7012149",
        "tgn:2002122",
        "tgn:7007827",
        "tgn:7029392"
    ],
    "tgn:id":2710520,
    "tgn:name":"Tamarack Lake",
    "tgn:placetype":[
        "aat:300008680"
    ]
},
  "bbox": [],
  "geometry": {"coordinates":[-110.0167,40.8333],"type":"Point"}
}