{
  "id": 1130142,
  "type": "Feature",
  "properties": {
    "tgn:hierarchy":[
        "tgn:1130142",
        "tgn:1000001",
        "tgn:7005388",
        "tgn:7029392"
    ],
    "tgn:id":1130142,
    "tgn:name":"Soco, R\u00edo",
    "tgn:placetype":[
        "aat:300008707"
    ]
},
  "bbox": [],
  "geometry": {"coordinates":[-69.205,18.452],"type":"Point"}
}