{
  "id": 2090540,
  "type": "Feature",
  "properties": {
    "tgn:hierarchy":[
        "tgn:2090540",
        "tgn:1000001",
        "tgn:1002266",
        "tgn:7012149",
        "tgn:7007710",
        "tgn:7029392"
    ],
    "tgn:id":2090540,
    "tgn:name":"Maple Grove",
    "tgn:placetype":[
        "aat:300008347",
        "aat:300387210"
    ]
},
  "bbox": [],
  "geometry": {"coordinates":[-75.9333,39.7667],"type":"Point"}
}