{
  "id": 1077299,
  "type": "Feature",
  "properties": {
    "tgn:hierarchy":[
        "tgn:1077299",
        "tgn:1001828",
        "tgn:1000004",
        "tgn:7000198",
        "tgn:7029392"
    ],
    "tgn:id":1077299,
    "tgn:name":"Vuyyuru",
    "tgn:placetype":[
        "aat:300008347"
    ]
},
  "bbox": [],
  "geometry": {"coordinates":[80.85,16.366667],"type":"Point"}
}