<<<<<<< HEAD
{
  "id": 7119321,
  "type": "Feature",
  "properties": {
    "tgn:hierarchy":[
        "tgn:7119321",
        "tgn:1000003",
        "tgn:7003676",
        "tgn:7000084",
        "tgn:7029392"
    ],
    "tgn:id":7119321,
    "tgn:name":"Poggenburger Leide",
    "tgn:placetype":[
        "aat:300008699"
    ]
},
  "bbox": [],
  "geometry": {"coordinates":[7.966667,53.65],"type":"Point"}
}
=======
{"geometry":{"type":"Point","coordinates":[7.966667,53.650000]},"type":"Feature","properties":{"hierarchy":["tgn:7119321","tgn:1000003","tgn:7003676","tgn:7000084","tgn:7029392"],"placetype":["aat:300008699"],"id":7119321,"name:xx":"Poggenburger Leide"}}
>>>>>>> 03f74aca74312dbeaf24d7e61306dd6a786dc3d0
