{
  "id": 7119321,
  "type": "Feature",
  "properties": {
    "tgn:hierarchy":[
        "tgn:7119321",
        "tgn:1000003",
        "tgn:7003676",
        "tgn:7000084",
        "tgn:7029392"
    ],
    "tgn:id":7119321,
    "tgn:name":"Poggenburger Leide",
    "tgn:placetype":[
        "aat:300008699"
    ]
},
  "bbox": [],
  "geometry": {"coordinates":[7.966667,53.65],"type":"Point"}
}