{
  "id": 7215499,
  "type": "Feature",
  "properties": {
    "tgn:hierarchy":[
        "tgn:7215499",
        "tgn:7000096",
        "tgn:1000003",
        "tgn:7000084",
        "tgn:7029392"
    ],
    "tgn:id":7215499,
    "tgn:name":"Albertinenhof",
    "tgn:placetype":[
        "aat:300008347"
    ]
},
  "bbox": [],
  "geometry": {"coordinates":[12.833333,52.85],"type":"Point"}
}