<<<<<<< HEAD
{
  "id": 2334287,
  "type": "Feature",
  "properties": {
    "tgn:hierarchy":[
        "tgn:2334287",
        "tgn:1000001",
        "tgn:7012149",
        "tgn:2001524",
        "tgn:7007709",
        "tgn:7029392"
    ],
    "tgn:id":2334287,
    "tgn:name":"Forest Grove",
    "tgn:placetype":[
        "aat:300008347"
    ]
},
  "bbox": [],
  "geometry": {"coordinates":[-77.4,34.7667],"type":"Point"}
}
=======
{"geometry":{"type":"Point","coordinates":[-77.400000,34.766700]},"type":"Feature","properties":{"hierarchy":["tgn:2334287","tgn:1000001","tgn:7012149","tgn:2001524","tgn:7007709","tgn:7029392"],"placetype":["aat:300008347"],"id":2334287,"name:xx":"Forest Grove"}}
>>>>>>> 03f74aca74312dbeaf24d7e61306dd6a786dc3d0
