<<<<<<< HEAD
{
  "id": 7246346,
  "type": "Feature",
  "properties": {
    "tgn:hierarchy":[
        "tgn:7246346",
        "tgn:7003457",
        "tgn:1000003",
        "tgn:1000063",
        "tgn:7018236",
        "tgn:7029392"
    ],
    "tgn:id":7246346,
    "tgn:name":"De Wijngaardhoeve",
    "tgn:placetype":[
        "aat:300000206"
    ]
},
  "bbox": [],
  "geometry": {"coordinates":[4.1,50.8],"type":"Point"}
}
=======
{"geometry":{"type":"Point","coordinates":[4.100000,50.800000]},"type":"Feature","properties":{"hierarchy":["tgn:7246346","tgn:7003457","tgn:1000003","tgn:1000063","tgn:7018236","tgn:7029392"],"placetype":["aat:300000206"],"id":7246346,"name:xx":"De Wijngaardhoeve"}}
>>>>>>> 03f74aca74312dbeaf24d7e61306dd6a786dc3d0
