{
  "id": 1028885,
  "type": "Feature",
  "properties": {
    "tgn:hierarchy":[
        "tgn:1028885",
        "tgn:1003639",
        "tgn:7002445",
        "tgn:1000003",
        "tgn:7029504",
        "tgn:7008591",
        "tgn:7029392"
    ],
    "tgn:id":1028885,
    "tgn:name:en":"Clock Face",
    "tgn:placetype":[
        "aat:300008347"
    ]
},
  "bbox": [],
  "geometry": {"coordinates":[-2.716667,53.416667],"type":"Point"}
}