{
  "id": 7049164,
  "type": "Feature",
  "properties": {
    "tgn:hierarchy":[
        "tgn:7049164",
        "tgn:1003450",
        "tgn:7007850",
        "tgn:1000003",
        "tgn:1000080",
        "tgn:7029392"
    ],
    "tgn:id":7049164,
    "tgn:name":"Dino, Isola di",
    "tgn:placetype":[
        "aat:300008791"
    ]
},
  "bbox": [],
  "geometry": {"coordinates":[15.766667,39.866667],"type":"Point"}
}