{
  "id": 7452852,
  "type": "Feature",
  "properties": {
    "tgn:hierarchy":[
        "tgn:7452852",
        "tgn:7002445",
        "tgn:1000003",
        "tgn:7008175",
        "tgn:7008591",
        "tgn:7029392"
    ],
    "tgn:id":7452852,
    "tgn:name:en":"Capel",
    "tgn:placetype":[
        "aat:300008347"
    ]
},
  "bbox": [],
  "geometry": {"coordinates":[-0.316667,51.133333],"type":"Point"}
}