{
  "id": 2440953,
  "type": "Feature",
  "properties": {
    "tgn:hierarchy":[
        "tgn:2440953",
        "tgn:1000001",
        "tgn:7012149",
        "tgn:2001241",
        "tgn:7007523",
        "tgn:7029392"
    ],
    "tgn:id":2440953,
    "tgn:name":"Knob Lick Mountain",
    "tgn:placetype":[
        "aat:300008798"
    ]
},
  "bbox": [],
  "geometry": {"coordinates":[-90.3833,37.65],"type":"Point"}
}