{
  "id": 7453091,
  "type": "Feature",
  "properties": {
    "tgn:hierarchy":[
        "tgn:7453091",
        "tgn:7002445",
        "tgn:1000003",
        "tgn:7008166",
        "tgn:7008591",
        "tgn:7029392"
    ],
    "tgn:id":7453091,
    "tgn:name:en":"Cam Houses",
    "tgn:placetype":[
        "aat:300008347"
    ]
},
  "bbox": [],
  "geometry": {"coordinates":[-2.266667,54.233333],"type":"Point"}
}