<<<<<<< HEAD
{
  "id": 7020974,
  "type": "Feature",
  "properties": {
    "tgn:hierarchy":[
        "tgn:7020974",
        "tgn:1000001",
        "tgn:7012149",
        "tgn:2000488",
        "tgn:7007250",
        "tgn:7029392"
    ],
    "tgn:id":7020974,
    "tgn:name":"Twin Buttes",
    "tgn:placetype":[
        "aat:300008798"
    ]
},
  "bbox": [],
  "geometry": {"coordinates":[-115.1833,42.7167],"type":"Point"}
}
=======
{"geometry":{"type":"Point","coordinates":[-115.183300,42.716700]},"type":"Feature","properties":{"hierarchy":["tgn:7020974","tgn:1000001","tgn:7012149","tgn:2000488","tgn:7007250","tgn:7029392"],"placetype":["aat:300008798"],"id":7020974,"name:xx":"Twin Buttes"}}
>>>>>>> 03f74aca74312dbeaf24d7e61306dd6a786dc3d0
