{
  "id": 2304550,
  "type": "Feature",
  "properties": {
    "tgn:hierarchy":[
        "tgn:2304550",
        "tgn:1000001",
        "tgn:7006451",
        "tgn:7012149",
        "tgn:2000103",
        "tgn:7029392"
    ],
    "tgn:id":2304550,
    "tgn:name":"East Ash Spring",
    "tgn:placetype":[
        "aat:300008697"
    ]
},
  "bbox": [],
  "geometry": {"coordinates":[-112.1333,34.65],"type":"Point"}
}