{
  "id": 7520931,
  "type": "Feature",
  "properties": {
    "tgn:hierarchy":[
        "tgn:7520931",
        "tgn:7001242",
        "tgn:7016833",
        "tgn:1001113",
        "tgn:7029392"
    ],
    "tgn:id":7520931,
    "tgn:name:en":"Al Kha\u0163\u0163\u0101rah a\u015f \u015eughr\u00e1",
    "tgn:placetype":[
        "aat:300008347"
    ]
},
  "bbox": [],
  "geometry": {"coordinates":[31.786111,30.66],"type":"Point"}
}