{
  "id": 2274042,
  "type": "Feature",
  "properties": {
    "tgn:hierarchy":[
        "tgn:2274042",
        "tgn:1000001",
        "tgn:2001702",
        "tgn:7012149",
        "tgn:7007708",
        "tgn:7029392"
    ],
    "tgn:id":2274042,
    "tgn:name":"Dahl Log Pond",
    "tgn:placetype":[
        "aat:300006191"
    ]
},
  "bbox": [],
  "geometry": {"coordinates":[-124.4167,43.0667],"type":"Point"}
}