{
  "id": 2598433,
  "type": "Feature",
  "properties": {
    "tgn:hierarchy":[
        "tgn:2598433",
        "tgn:1000001",
        "tgn:7016172",
        "tgn:7012149",
        "tgn:7029392"
    ],
    "tgn:id":2598433,
    "tgn:name":"Price Creek",
    "tgn:placetype":[
        "aat:300008706"
    ]
},
  "bbox": [],
  "geometry": {"coordinates":[-94.3333,34.1833],"type":"Point"}
}