{
  "id": 2620610,
  "type": "Feature",
  "properties": {
    "tgn:hierarchy":[
        "tgn:2620610",
        "tgn:1000001",
        "tgn:2000199",
        "tgn:7012149",
        "tgn:7007158",
        "tgn:7029392"
    ],
    "tgn:id":2620610,
    "tgn:name":"Riverside",
    "tgn:placetype":[
        "aat:300008347"
    ]
},
  "bbox": [],
  "geometry": {"coordinates":[-106.1833,38.9333],"type":"Point"}
}