{
  "id": 2675924,
  "type": "Feature",
  "properties": {
    "tgn:hierarchy":[
        "tgn:2675924",
        "tgn:7006450",
        "tgn:1000001",
        "tgn:7012149",
        "tgn:7019760",
        "tgn:7029392"
    ],
    "tgn:id":2675924,
    "tgn:name":"Sonyakay Ridge",
    "tgn:placetype":[
        "aat:300266640"
    ]
},
  "bbox": [],
  "geometry": {"coordinates":[-134.9833,57.95],"type":"Point"}
}