<<<<<<< HEAD
{
  "id": 2335699,
  "type": "Feature",
  "properties": {
    "tgn:hierarchy":[
        "tgn:2335699",
        "tgn:1000001",
        "tgn:7012149",
        "tgn:2001297",
        "tgn:7007524",
        "tgn:7029392"
    ],
    "tgn:id":2335699,
    "tgn:name":"Fortune Spring",
    "tgn:placetype":[
        "aat:300008697"
    ]
},
  "bbox": [],
  "geometry": {"coordinates":[-106.1,45.4667],"type":"Point"}
}
=======
{"geometry":{"type":"Point","coordinates":[-106.100000,45.466700]},"type":"Feature","properties":{"hierarchy":["tgn:2335699","tgn:1000001","tgn:7012149","tgn:2001297","tgn:7007524","tgn:7029392"],"placetype":["aat:300008697"],"id":2335699,"name:xx":"Fortune Spring"}}
>>>>>>> 03f74aca74312dbeaf24d7e61306dd6a786dc3d0
