{
  "id": 7591028,
  "type": "Feature",
  "properties": {
    "tgn:hierarchy":[
        "tgn:7591028",
        "tgn:1000004",
        "tgn:7000198",
        "tgn:7000799",
        "tgn:7029392"
    ],
    "tgn:id":7591028,
    "tgn:name:en":"M\u0101h\u0101der",
    "tgn:placetype":[
        "aat:300008347"
    ]
},
  "bbox": [],
  "geometry": {"coordinates":[74.32656,32.998107],"type":"Point"}
}