{
  "id": 1017233,
  "type": "Feature",
  "properties": {
    "tgn:hierarchy":[
        "tgn:1017233",
        "tgn:1000001",
        "tgn:7005597",
        "tgn:7005560",
        "tgn:7029392"
    ],
    "tgn:id":1017233,
    "tgn:name":"Ciudad Victoria",
    "tgn:placetype":[
        "aat:300008347",
        "aat:300008389",
        "aat:300387305",
        "aat:300387221",
        "aat:300387249",
        "aat:300387270",
        "aat:300387291"
    ]
},
  "bbox": [],
  "geometry": {"coordinates":[-99.133333,23.733333],"type":"Point"}
}