{
  "id": 7528255,
  "type": "Feature",
  "properties": {
    "tgn:hierarchy":[
        "tgn:7528255",
        "tgn:7001242",
        "tgn:7016833",
        "tgn:7001334",
        "tgn:7029392"
    ],
    "tgn:id":7528255,
    "tgn:name:en":"Sirr\u012b, Jabal",
    "tgn:placetype":[
        "aat:300008795"
    ]
},
  "bbox": [],
  "geometry": {"coordinates":[31.108132,22.145368],"type":"Point"}
}