<<<<<<< HEAD
{
  "id": 7354512,
  "type": "Feature",
  "properties": {
    "tgn:hierarchy":[
        "tgn:7354512",
        "tgn:1000001",
        "tgn:7005600",
        "tgn:7005560",
        "tgn:7029392"
    ],
    "tgn:id":7354512,
    "tgn:name":"Chuny\u00e1",
    "tgn:placetype":[
        "aat:300008347"
    ]
},
  "bbox": [],
  "geometry": {"coordinates":[-89.883333,20.95],"type":"Point"}
}
=======
{"geometry":{"type":"Point","coordinates":[-89.883333,20.950000]},"type":"Feature","properties":{"hierarchy":["tgn:7354512","tgn:1000001","tgn:7005600","tgn:7005560","tgn:7029392"],"placetype":["aat:300008347"],"id":7354512,"name:xx":"Chuny\u00e1"}}
>>>>>>> 03f74aca74312dbeaf24d7e61306dd6a786dc3d0
