{
  "id": 2138961,
  "type": "Feature",
  "properties": {
    "tgn:hierarchy":[
        "tgn:2138961",
        "tgn:1000001",
        "tgn:1003023",
        "tgn:7012149",
        "tgn:7007516",
        "tgn:7029392"
    ],
    "tgn:id":2138961,
    "tgn:name":"Asherwood Branch",
    "tgn:placetype":[
        "aat:300008699"
    ]
},
  "bbox": [],
  "geometry": {"coordinates":[-75.3333,38.3667],"type":"Point"}
}