{
  "id": 2664075,
  "type": "Feature",
  "properties": {
    "tgn:hierarchy":[
        "tgn:2664075",
        "tgn:1000001",
        "tgn:7012149",
        "tgn:2001454",
        "tgn:7007566",
        "tgn:7029392"
    ],
    "tgn:id":2664075,
    "tgn:name":"Silver Queen",
    "tgn:placetype":[
        "aat:300000390"
    ]
},
  "bbox": [],
  "geometry": {"coordinates":[-106.1667,35.2333],"type":"Point"}
}