{
  "id": 7220122,
  "type": "Feature",
  "properties": {
    "tgn:hierarchy":[
        "tgn:7220122",
        "tgn:7002707",
        "tgn:7002705",
        "tgn:1000003",
        "tgn:1000074",
        "tgn:7029392"
    ],
    "tgn:id":7220122,
    "tgn:name":"Mystr\u00e1s",
    "tgn:placetype":[
        "aat:300008347"
    ]
},
  "bbox": [],
  "geometry": {"coordinates":[21.111944,39.565],"type":"Point"}
}