{
  "id": 7299632,
  "type": "Feature",
  "properties": {
    "tgn:hierarchy":[
        "tgn:7299632",
        "tgn:7002826",
        "tgn:7001158",
        "tgn:1000003",
        "tgn:1000095",
        "tgn:7029392"
    ],
    "tgn:id":7299632,
    "tgn:name":"Valdepresente, Arroyo de",
    "tgn:placetype":[
        "aat:300266554",
        "aat:300008699"
    ]
},
  "bbox": [],
  "geometry": {"coordinates":[-5.133333,42.433333],"type":"Point"}
}