{
  "id": 1036257,
  "type": "Feature",
  "properties": {
    "tgn:hierarchy":[
        "tgn:1036257",
        "tgn:1000003",
        "tgn:7002877",
        "tgn:1000070",
        "tgn:7029392"
    ],
    "tgn:id":1036257,
    "tgn:name":"Voves",
    "tgn:placetype":[
        "aat:300008347"
    ]
},
  "bbox": [],
  "geometry": {"coordinates":[1.6167,48.2667],"type":"Point"}
}