<<<<<<< HEAD
{
  "id": 7352042,
  "type": "Feature",
  "properties": {
    "tgn:hierarchy":[
        "tgn:7352042",
        "tgn:1000001",
        "tgn:7005597",
        "tgn:7005560",
        "tgn:7029392"
    ],
    "tgn:id":7352042,
    "tgn:name":"Arroyo Seco",
    "tgn:placetype":[
        "aat:300008347"
    ]
},
  "bbox": [],
  "geometry": {"coordinates":[-97.283333,25.916667],"type":"Point"}
}
=======
{"geometry":{"type":"Point","coordinates":[-97.283333,25.916667]},"type":"Feature","properties":{"hierarchy":["tgn:7352042","tgn:1000001","tgn:7005597","tgn:7005560","tgn:7029392"],"placetype":["aat:300008347"],"id":7352042,"name:xx":"Arroyo Seco"}}
>>>>>>> 03f74aca74312dbeaf24d7e61306dd6a786dc3d0
