{
  "id": 7088846,
  "type": "Feature",
  "properties": {
    "tgn:hierarchy":[
        "tgn:7088846",
        "tgn:7003692",
        "tgn:1000003",
        "tgn:7000084",
        "tgn:7029392"
    ],
    "tgn:id":7088846,
    "tgn:name":"Wagshurst",
    "tgn:placetype":[
        "aat:300008347"
    ]
},
  "bbox": [],
  "geometry": {"coordinates":[7.983333,48.616667],"type":"Point"}
}