{
  "id": 7411711,
  "type": "Feature",
  "properties": {
    "tgn:hierarchy":[
        "tgn:7411711",
        "tgn:7005580",
        "tgn:1000001",
        "tgn:7005560",
        "tgn:7029392"
    ],
    "tgn:id":7411711,
    "tgn:name":"Nuevo San Pedro",
    "tgn:placetype":[
        "aat:300008347"
    ]
},
  "bbox": [],
  "geometry": {"coordinates":[-91.558333,17.35],"type":"Point"}
}