{
  "id": 2484925,
  "type": "Feature",
  "properties": {
    "tgn:hierarchy":[
        "tgn:2484925",
        "tgn:1000001",
        "tgn:7012149",
        "tgn:2002057",
        "tgn:7007826",
        "tgn:7029392"
    ],
    "tgn:id":2484925,
    "tgn:name":"Lava Canyon",
    "tgn:placetype":[
        "aat:300008761"
    ]
},
  "bbox": [],
  "geometry": {"coordinates":[-103.8833,29.4833],"type":"Point"}
}