{
  "id": 7585759,
  "type": "Feature",
  "properties": {
    "tgn:hierarchy":[
        "tgn:7585759",
        "tgn:1000004",
        "tgn:7000198",
        "tgn:7000799",
        "tgn:7029392"
    ],
    "tgn:id":7585759,
    "tgn:name:en":"Malguinpur",
    "tgn:placetype":[
        "aat:300008347"
    ]
},
  "bbox": [],
  "geometry": {"coordinates":[74.400728,34.339823],"type":"Point"}
}