{
  "id": 7481692,
  "type": "Feature",
  "properties": {
    "tgn:hierarchy":[
        "tgn:7481692",
        "tgn:1000004",
        "tgn:7001013",
        "tgn:1000141",
        "tgn:7029392"
    ],
    "tgn:id":7481692,
    "tgn:name":"Taiyao Qiao",
    "tgn:placetype":[
        "aat:300007836"
    ]
},
  "bbox": [],
  "geometry": {"coordinates":[121.353611,24.648333],"type":"Point"}
}