{
  "id": 7470097,
  "type": "Feature",
  "properties": {
    "tgn:hierarchy":[
        "tgn:7470097",
        "tgn:7468018",
        "tgn:1000004",
        "tgn:1000141",
        "tgn:7029392"
    ],
    "tgn:id":7470097,
    "tgn:name":"Haoshou",
    "tgn:placetype":[
        "aat:300008347"
    ]
},
  "bbox": [],
  "geometry": {"coordinates":[120.45023,23.562262],"type":"Point"}
}