{
  "id": 2515392,
  "type": "Feature",
  "properties": {
    "tgn:hierarchy":[
        "tgn:2515392",
        "tgn:1000001",
        "tgn:2001749",
        "tgn:7012149",
        "tgn:7007712",
        "tgn:7029392"
    ],
    "tgn:id":2515392,
    "tgn:name":"Millpond Branch",
    "tgn:placetype":[
        "aat:300008699"
    ]
},
  "bbox": [],
  "geometry": {"coordinates":[-81.25,32.7333],"type":"Point"}
}