<<<<<<< HEAD
{
  "id": 7482710,
  "type": "Feature",
  "properties": {
    "tgn:hierarchy":[
        "tgn:7482710",
        "tgn:7001010",
        "tgn:1000004",
        "tgn:1000141",
        "tgn:7029392"
    ],
    "tgn:id":7482710,
    "tgn:name":"Baiye Shan",
    "tgn:placetype":[
        "aat:300008798"
    ]
},
  "bbox": [],
  "geometry": {"coordinates":[121.497778,23.998611],"type":"Point"}
}
=======
{"geometry":{"type":"Point","coordinates":[121.497778,23.998611]},"type":"Feature","properties":{"hierarchy":["tgn:7482710","tgn:7001010","tgn:1000004","tgn:1000141","tgn:7029392"],"placetype":["aat:300008798"],"id":7482710,"name:xx":"Baiye Shan"}}
>>>>>>> 03f74aca74312dbeaf24d7e61306dd6a786dc3d0
