{
  "id": 7296581,
  "type": "Feature",
  "properties": {
    "tgn:hierarchy":[
        "tgn:7296581",
        "tgn:7001165",
        "tgn:1000003",
        "tgn:7002793",
        "tgn:1000095",
        "tgn:7029392"
    ],
    "tgn:id":7296581,
    "tgn:name":"Villargordo del Cabriel",
    "tgn:placetype":[
        "aat:300008347"
    ]
},
  "bbox": [],
  "geometry": {"coordinates":[-1.433333,39.533333],"type":"Point"}
}