{
  "id": 2528286,
  "type": "Feature",
  "properties": {
    "tgn:hierarchy":[
        "tgn:2528286",
        "tgn:1000001",
        "tgn:1002666",
        "tgn:7012149",
        "tgn:7007565",
        "tgn:7029392"
    ],
    "tgn:id":2528286,
    "tgn:name":"Mounts Mills",
    "tgn:placetype":[
        "aat:300008347"
    ]
},
  "bbox": [],
  "geometry": {"coordinates":[-74.35,40.3167],"type":"Point"}
}