{
  "id": 2118807,
  "type": "Feature",
  "properties": {
    "tgn:hierarchy":[
        "tgn:2118807",
        "tgn:1000001",
        "tgn:7012149",
        "tgn:2002268",
        "tgn:7013961",
        "tgn:7029392"
    ],
    "tgn:id":2118807,
    "tgn:name":"Kentuck",
    "tgn:placetype":[
        "aat:300008347"
    ]
},
  "bbox": [],
  "geometry": {"coordinates":[-81.5833,38.65],"type":"Point"}
}