{
  "id": 2133327,
  "type": "Feature",
  "properties": {
    "tgn:hierarchy":[
        "tgn:2133327",
        "tgn:1000001",
        "tgn:2002368",
        "tgn:7012149",
        "tgn:7007923",
        "tgn:7029392"
    ],
    "tgn:id":2133327,
    "tgn:name":"Anderson Reservoir",
    "tgn:placetype":[
        "aat:300006191"
    ]
},
  "bbox": [],
  "geometry": {"coordinates":[-106.8333,41.25],"type":"Point"}
}