{
  "id": 7404531,
  "type": "Feature",
  "properties": {
    "tgn:hierarchy":[
        "tgn:7404531",
        "tgn:7016644",
        "tgn:1000001",
        "tgn:7005560",
        "tgn:7029392"
    ],
    "tgn:id":7404531,
    "tgn:name":"Tecom\u00e1n, Cerro",
    "tgn:placetype":[
        "aat:300008795"
    ]
},
  "bbox": [],
  "geometry": {"coordinates":[-103.815278,18.948611],"type":"Point"}
}