{
  "id": 7356533,
  "type": "Feature",
  "properties": {
    "tgn:hierarchy":[
        "tgn:7356533",
        "tgn:7005585",
        "tgn:1000001",
        "tgn:7005560",
        "tgn:7029392"
    ],
    "tgn:id":7356533,
    "tgn:name":"Campana",
    "tgn:placetype":[
        "aat:300008347"
    ]
},
  "bbox": [],
  "geometry": {"coordinates":[-101.85,18.433333],"type":"Point"}
}