{
  "id": 7522339,
  "type": "Feature",
  "properties": {
    "tgn:hierarchy":[
        "tgn:7522339",
        "tgn:7001242",
        "tgn:7016833",
        "tgn:1001113",
        "tgn:7029392"
    ],
    "tgn:id":7522339,
    "tgn:name:en":"Daww\u0101r Awl\u0101d Sal\u0101mah",
    "tgn:placetype":[
        "aat:300008347"
    ]
},
  "bbox": [],
  "geometry": {"coordinates":[31.733611,30.995278],"type":"Point"}
}