{
  "id": 2198293,
  "type": "Feature",
  "properties": {
    "tgn:hierarchy":[
        "tgn:2198293",
        "tgn:2002137",
        "tgn:1000001",
        "tgn:7012149",
        "tgn:7007919",
        "tgn:7029392"
    ],
    "tgn:id":2198293,
    "tgn:name":"Browns Cove",
    "tgn:placetype":[
        "aat:300008761"
    ]
},
  "bbox": [],
  "geometry": {"coordinates":[-78.6833,38.2333],"type":"Point"}
}