{
  "id": 2315717,
  "type": "Feature",
  "properties": {
    "tgn:hierarchy":[
        "tgn:2315717",
        "tgn:1000001",
        "tgn:7016172",
        "tgn:7012149",
        "tgn:2000143",
        "tgn:7029392"
    ],
    "tgn:id":2315717,
    "tgn:name":"Ellison Lake",
    "tgn:placetype":[
        "aat:300008680"
    ]
},
  "bbox": [],
  "geometry": {"coordinates":[-90.65,34.75],"type":"Point"}
}