{
  "id": 7226514,
  "type": "Feature",
  "properties": {
    "tgn:hierarchy":[
        "tgn:7226514",
        "tgn:7002743",
        "tgn:7017076",
        "tgn:1000003",
        "tgn:1000074",
        "tgn:7029392"
    ],
    "tgn:id":7226514,
    "tgn:name":"Sm\u00e9rna",
    "tgn:placetype":[
        "aat:300008347"
    ]
},
  "bbox": [],
  "geometry": {"coordinates":[21.683333,37.55],"type":"Point"}
}