{
  "id": 2484434,
  "type": "Feature",
  "properties": {
    "tgn:hierarchy":[
        "tgn:2484434",
        "tgn:1000001",
        "tgn:7012149",
        "tgn:2000818",
        "tgn:7007255",
        "tgn:7029392"
    ],
    "tgn:id":2484434,
    "tgn:name":"Laurel Creek Reservoir",
    "tgn:placetype":[
        "aat:300006191"
    ]
},
  "bbox": [],
  "geometry": {"coordinates":[-84.4333,36.6833],"type":"Point"}
}