<<<<<<< HEAD
{
  "id": 7366198,
  "type": "Feature",
  "properties": {
    "tgn:hierarchy":[
        "tgn:7366198",
        "tgn:1000001",
        "tgn:7005592",
        "tgn:7005560",
        "tgn:7029392"
    ],
    "tgn:id":7366198,
    "tgn:name":"El Terrero",
    "tgn:placetype":[
        "aat:300008347"
    ]
},
  "bbox": [],
  "geometry": {"coordinates":[-97.9,20.55],"type":"Point"}
}
=======
{"geometry":{"type":"Point","coordinates":[-97.900000,20.550000]},"type":"Feature","properties":{"hierarchy":["tgn:7366198","tgn:1000001","tgn:7005592","tgn:7005560","tgn:7029392"],"placetype":["aat:300008347"],"id":7366198,"name:xx":"El Terrero"}}
>>>>>>> 03f74aca74312dbeaf24d7e61306dd6a786dc3d0
