{
  "id": 2466454,
  "type": "Feature",
  "properties": {
    "tgn:hierarchy":[
        "tgn:2466454",
        "tgn:1000001",
        "tgn:7012149",
        "tgn:2000346",
        "tgn:7007248",
        "tgn:7029392"
    ],
    "tgn:id":2466454,
    "tgn:name":"Long Branch",
    "tgn:placetype":[
        "aat:300008699"
    ]
},
  "bbox": [],
  "geometry": {"coordinates":[-84.2833,34.8167],"type":"Point"}
}