{
  "id": 2160803,
  "type": "Feature",
  "properties": {
    "tgn:hierarchy":[
        "tgn:2160803",
        "tgn:1000001",
        "tgn:7012149",
        "tgn:2001460",
        "tgn:7007566",
        "tgn:7029392"
    ],
    "tgn:id":2160803,
    "tgn:name":"Belen Waste Ditch",
    "tgn:placetype":[
        "aat:300006075"
    ]
},
  "bbox": [],
  "geometry": {"coordinates":[-106.7667,34.6333],"type":"Point"}
}