{
  "id": 2212195,
  "type": "Feature",
  "properties": {
    "tgn:hierarchy":[
        "tgn:2212195",
        "tgn:1000001",
        "tgn:7012149",
        "tgn:7007919",
        "tgn:7029392"
    ],
    "tgn:id":2212195,
    "tgn:name":"Buzzard Rock",
    "tgn:placetype":[
        "aat:300008798"
    ]
},
  "bbox": [],
  "geometry": {"coordinates":[-81.6167,36.6333],"type":"Point"}
}