<<<<<<< HEAD
{
  "id": 2766433,
  "type": "Feature",
  "properties": {
    "tgn:hierarchy":[
        "tgn:2766433",
        "tgn:1000001",
        "tgn:7012149",
        "tgn:2000887",
        "tgn:7007256",
        "tgn:7029392"
    ],
    "tgn:id":2766433,
    "tgn:name":"White Oak Bayou",
    "tgn:placetype":[
        "aat:300008699"
    ]
},
  "bbox": [],
  "geometry": {"coordinates":[-91.75,32.7167],"type":"Point"}
}
=======
{"geometry":{"type":"Point","coordinates":[-91.750000,32.716700]},"type":"Feature","properties":{"hierarchy":["tgn:2766433","tgn:1000001","tgn:7012149","tgn:2000887","tgn:7007256","tgn:7029392"],"placetype":["aat:300008699"],"id":2766433,"name:xx":"White Oak Bayou"}}
>>>>>>> 03f74aca74312dbeaf24d7e61306dd6a786dc3d0
