{
  "id": 2148086,
  "type": "Feature",
  "properties": {
    "tgn:hierarchy":[
        "tgn:2148086",
        "tgn:2000919",
        "tgn:1000001",
        "tgn:7012149",
        "tgn:7007515",
        "tgn:7029392"
    ],
    "tgn:id":2148086,
    "tgn:name":"Barker Ridge",
    "tgn:placetype":[
        "aat:300266640"
    ]
},
  "bbox": [],
  "geometry": {"coordinates":[-68.2667,45.9667],"type":"Point"}
}