{
  "id": 2589371,
  "type": "Feature",
  "properties": {
    "tgn:hierarchy":[
        "tgn:2589371",
        "tgn:1000001",
        "tgn:2001025",
        "tgn:7012149",
        "tgn:7007521",
        "tgn:7029392"
    ],
    "tgn:id":2589371,
    "tgn:name":"Point Charming",
    "tgn:placetype":[
        "aat:300008850"
    ]
},
  "bbox": [],
  "geometry": {"coordinates":[-93.55,44.9167],"type":"Point"}
}