{
  "id": 7323471,
  "type": "Feature",
  "properties": {
    "tgn:hierarchy":[
        "tgn:7323471",
        "tgn:7008911",
        "tgn:1000003",
        "tgn:7002763",
        "tgn:1000095",
        "tgn:7029392"
    ],
    "tgn:id":7323471,
    "tgn:name":"Rondiella",
    "tgn:placetype":[
        "aat:300008347"
    ]
},
  "bbox": [],
  "geometry": {"coordinates":[-5.85,43.433333],"type":"Point"}
}