{
  "id": 1004236,
  "type": "Feature",
  "properties": {
    "tgn:hierarchy":[
        "tgn:1004236",
        "tgn:1001942",
        "tgn:1000047",
        "tgn:7002457",
        "tgn:1000002",
        "tgn:7017095",
        "tgn:7029392"
    ],
    "tgn:id":1004236,
    "tgn:name":"Cascadura",
    "tgn:placetype":[
        "aat:300000745"
    ]
},
  "bbox": [],
  "geometry": {"coordinates":[-43.3333,-22.8833],"type":"Point"}
}