{
  "id": 1048545,
  "type": "Feature",
  "properties": {
    "tgn:hierarchy":[
        "tgn:1048545",
        "tgn:7003647",
        "tgn:1000003",
        "tgn:1000088",
        "tgn:7029392"
    ],
    "tgn:id":1048545,
    "tgn:name":"Fosnav\u00e5g",
    "tgn:placetype":[
        "aat:300008347"
    ]
},
  "bbox": [],
  "geometry": {"coordinates":[5.65,62.3667],"type":"Point"}
}