{
  "id": 2057262,
  "type": "Feature",
  "properties": {
    "tgn:hierarchy":[
        "tgn:2057262",
        "tgn:1000001",
        "tgn:7012149",
        "tgn:2001154",
        "tgn:7007522",
        "tgn:7029392"
    ],
    "tgn:id":2057262,
    "tgn:name":"Poagville",
    "tgn:placetype":[
        "aat:300008347",
        "aat:300387210"
    ]
},
  "bbox": [],
  "geometry": {"coordinates":[-89.85,34.6667],"type":"Point"}
}