{
  "id": 2472578,
  "type": "Feature",
  "properties": {
    "tgn:hierarchy":[
        "tgn:2472578",
        "tgn:1000001",
        "tgn:7012149",
        "tgn:7014589",
        "tgn:7007515",
        "tgn:7029392"
    ],
    "tgn:id":2472578,
    "tgn:name":"Love Lake",
    "tgn:placetype":[
        "aat:300008680"
    ]
},
  "bbox": [],
  "geometry": {"coordinates":[-67.5167,44.9833],"type":"Point"}
}