{
  "id": 7559840,
  "type": "Feature",
  "properties": {
    "tgn:hierarchy":[
        "tgn:7559840",
        "tgn:1000004",
        "tgn:7000198",
        "tgn:7016788",
        "tgn:7029392"
    ],
    "tgn:id":7559840,
    "tgn:name:en":"S\u0101ran ki Dh\u0101ni",
    "tgn:placetype":[
        "aat:300008347"
    ]
},
  "bbox": [],
  "geometry": {"coordinates":[75.619591,26.990197],"type":"Point"}
}