{
  "id": 2132026,
  "type": "Feature",
  "properties": {
    "tgn:hierarchy":[
        "tgn:2132026",
        "tgn:1000001",
        "tgn:2001432",
        "tgn:7012149",
        "tgn:7007566",
        "tgn:7029392"
    ],
    "tgn:id":2132026,
    "tgn:name":"American Creek",
    "tgn:placetype":[
        "aat:300008706"
    ]
},
  "bbox": [],
  "geometry": {"coordinates":[-105.1833,36.4667],"type":"Point"}
}