{
  "id": 7228413,
  "type": "Feature",
  "properties": {
    "tgn:hierarchy":[
        "tgn:7228413",
        "tgn:7011369",
        "tgn:7017076",
        "tgn:1000003",
        "tgn:1000074",
        "tgn:7029392"
    ],
    "tgn:id":7228413,
    "tgn:name":"Kast\u00e1nia",
    "tgn:placetype":[
        "aat:300008347"
    ]
},
  "bbox": [],
  "geometry": {"coordinates":[21.883333,36.95],"type":"Point"}
}