<<<<<<< HEAD
{
  "id": 2158052,
  "type": "Feature",
  "properties": {
    "tgn:hierarchy":[
        "tgn:2158052",
        "tgn:7002659",
        "tgn:1000001",
        "tgn:2000003",
        "tgn:7012149",
        "tgn:7029392"
    ],
    "tgn:id":2158052,
    "tgn:name":"Beaver Pond",
    "tgn:placetype":[
        "aat:300008680"
    ]
},
  "bbox": [],
  "geometry": {"coordinates":[-87.1333,33.2167],"type":"Point"}
}
=======
{"geometry":{"type":"Point","coordinates":[-87.133300,33.216700]},"type":"Feature","properties":{"hierarchy":["tgn:2158052","tgn:7002659","tgn:1000001","tgn:2000003","tgn:7012149","tgn:7029392"],"placetype":["aat:300008680"],"id":2158052,"name:xx":"Beaver Pond"}}
>>>>>>> 03f74aca74312dbeaf24d7e61306dd6a786dc3d0
