{
  "id": 2158052,
  "type": "Feature",
  "properties": {
    "tgn:hierarchy":[
        "tgn:2158052",
        "tgn:7002659",
        "tgn:1000001",
        "tgn:2000003",
        "tgn:7012149",
        "tgn:7029392"
    ],
    "tgn:id":2158052,
    "tgn:name":"Beaver Pond",
    "tgn:placetype":[
        "aat:300008680"
    ]
},
  "bbox": [],
  "geometry": {"coordinates":[-87.1333,33.2167],"type":"Point"}
}