{
  "id": 7034810,
  "type": "Feature",
  "properties": {
    "tgn:hierarchy":[
        "tgn:7034810",
        "tgn:1000003",
        "tgn:7003142",
        "tgn:7003236",
        "tgn:1000080",
        "tgn:7029392"
    ],
    "tgn:id":7034810,
    "tgn:name":"San Martino di Noceto",
    "tgn:placetype":[
        "aat:300008347"
    ]
},
  "bbox": [],
  "geometry": {"coordinates":[9.178611,44.360556],"type":"Point"}
}