{
  "id": 1046387,
  "type": "Feature",
  "properties": {
    "tgn:hierarchy":[
        "tgn:1046387",
        "tgn:1000003",
        "tgn:7003122",
        "tgn:1001753",
        "tgn:1000080",
        "tgn:7029392"
    ],
    "tgn:id":1046387,
    "tgn:name":"Rosolini",
    "tgn:placetype":[
        "aat:300008347"
    ]
},
  "bbox": [],
  "geometry": {"coordinates":[14.95,36.816667],"type":"Point"}
}