{
  "id": 2528865,
  "type": "Feature",
  "properties": {
    "tgn:hierarchy":[
        "tgn:2528865",
        "tgn:1000001",
        "tgn:2000686",
        "tgn:7012149",
        "tgn:7007254",
        "tgn:7029392"
    ],
    "tgn:id":2528865,
    "tgn:name":"Mud Creek",
    "tgn:placetype":[
        "aat:300008706"
    ]
},
  "bbox": [],
  "geometry": {"coordinates":[-98.2167,38.6333],"type":"Point"}
}