{
  "id": 2543014,
  "type": "Feature",
  "properties": {
    "tgn:hierarchy":[
        "tgn:2543014",
        "tgn:1000001",
        "tgn:7012149",
        "tgn:2001553",
        "tgn:7007709",
        "tgn:7029392"
    ],
    "tgn:id":2543014,
    "tgn:name":"Noname",
    "tgn:placetype":[
        "aat:300006191"
    ]
},
  "bbox": [],
  "geometry": {"coordinates":[-81.1833,36.0333],"type":"Point"}
}