{
  "id": 7186703,
  "type": "Feature",
  "properties": {
    "tgn:hierarchy":[
        "tgn:7186703",
        "tgn:1000003",
        "tgn:7594165",
        "tgn:7000084",
        "tgn:7029392"
    ],
    "tgn:id":7186703,
    "tgn:name":"Goldene Aue",
    "tgn:placetype":[
        "aat:300387346"
    ]
},
  "bbox": [],
  "geometry": {"coordinates":[10.95,51.45],"type":"Point"}
}