{
  "id": 7303101,
  "type": "Feature",
  "properties": {
    "tgn:hierarchy":[
        "tgn:7303101",
        "tgn:7008911",
        "tgn:1000003",
        "tgn:7002763",
        "tgn:1000095",
        "tgn:7029392"
    ],
    "tgn:id":7303101,
    "tgn:name":"Ozanes",
    "tgn:placetype":[
        "aat:300008347"
    ]
},
  "bbox": [],
  "geometry": {"coordinates":[-5.183333,43.366667],"type":"Point"}
}