{
  "id": 7218594,
  "type": "Feature",
  "properties": {
    "tgn:hierarchy":[
        "tgn:7218594",
        "tgn:7011270",
        "tgn:7002674",
        "tgn:1000003",
        "tgn:1000074",
        "tgn:7029392"
    ],
    "tgn:id":7218594,
    "tgn:name":"Christian\u00ed, Nis\u00eds",
    "tgn:placetype":[
        "aat:300008791"
    ]
},
  "bbox": [],
  "geometry": {"coordinates":[25.200314,36.244859],"type":"Point"}
}