{
  "id": 2226064,
  "type": "Feature",
  "properties": {
    "tgn:hierarchy":[
        "tgn:2226064",
        "tgn:1000001",
        "tgn:7012149",
        "tgn:7007158",
        "tgn:2000240",
        "tgn:7029392"
    ],
    "tgn:id":2226064,
    "tgn:name":"Cataract Creek",
    "tgn:placetype":[
        "aat:300008706"
    ]
},
  "bbox": [],
  "geometry": {"coordinates":[-106.85,39.0333],"type":"Point"}
}