<<<<<<< HEAD
{
  "id": 2768883,
  "type": "Feature",
  "properties": {
    "tgn:hierarchy":[
        "tgn:2768883",
        "tgn:1000001",
        "tgn:7012149",
        "tgn:7007923",
        "tgn:7029392"
    ],
    "tgn:id":2768883,
    "tgn:name":"Whitney Draw",
    "tgn:placetype":[
        "aat:300008761"
    ]
},
  "bbox": [],
  "geometry": {"coordinates":[-104.4,43.4667],"type":"Point"}
}
=======
{"geometry":{"type":"Point","coordinates":[-104.400000,43.466700]},"type":"Feature","properties":{"hierarchy":["tgn:2768883","tgn:1000001","tgn:7012149","tgn:7007923","tgn:7029392"],"placetype":["aat:300008761"],"id":2768883,"name:xx":"Whitney Draw"}}
>>>>>>> 03f74aca74312dbeaf24d7e61306dd6a786dc3d0
