{
  "id": 2656053,
  "type": "Feature",
  "properties": {
    "tgn:hierarchy":[
        "tgn:2656053",
        "tgn:1000001",
        "tgn:7012149",
        "tgn:1002758",
        "tgn:7007568",
        "tgn:7029392"
    ],
    "tgn:id":2656053,
    "tgn:name":"Shaw Point",
    "tgn:placetype":[
        "aat:300008850"
    ]
},
  "bbox": [],
  "geometry": {"coordinates":[-76.0833,43.2333],"type":"Point"}
}