{
  "id": 7307523,
  "type": "Feature",
  "properties": {
    "tgn:hierarchy":[
        "tgn:7307523",
        "tgn:7002844",
        "tgn:7030216",
        "tgn:1000003",
        "tgn:1000095",
        "tgn:7029392"
    ],
    "tgn:id":7307523,
    "tgn:name":"Lled\u00f3, Arroyo de",
    "tgn:placetype":[
        "aat:300266554",
        "aat:300008699"
    ]
},
  "bbox": [],
  "geometry": {"coordinates":[0.533333,40.733333],"type":"Point"}
}