{
  "id": 7501309,
  "type": "Feature",
  "properties": {
    "tgn:hierarchy":[
        "tgn:7501309",
        "tgn:7001004",
        "tgn:1000004",
        "tgn:1000141",
        "tgn:7029392"
    ],
    "tgn:id":7501309,
    "tgn:name":"Sanpi Guoxiao",
    "tgn:placetype":[
        "aat:300006495"
    ]
},
  "bbox": [],
  "geometry": {"coordinates":[120.280278,22.836667],"type":"Point"}
}