{
  "id": 2386108,
  "type": "Feature",
  "properties": {
    "tgn:hierarchy":[
        "tgn:2386108",
        "tgn:1000001",
        "tgn:7016172",
        "tgn:7012149",
        "tgn:2000168",
        "tgn:7029392"
    ],
    "tgn:id":2386108,
    "tgn:name":"Henry Mountain",
    "tgn:placetype":[
        "aat:300266640"
    ]
},
  "bbox": [],
  "geometry": {"coordinates":[-94.2167,34.8167],"type":"Point"}
}