{
  "id": 7039357,
  "type": "Feature",
  "properties": {
    "tgn:hierarchy":[
        "tgn:7039357",
        "tgn:7005852",
        "tgn:1000003",
        "tgn:7003237",
        "tgn:1000080",
        "tgn:7029392"
    ],
    "tgn:id":7039357,
    "tgn:name":"Sueglio",
    "tgn:placetype":[
        "aat:300008347"
    ]
},
  "bbox": [],
  "geometry": {"coordinates":[9.333333,46.083333],"type":"Point"}
}