<<<<<<< HEAD
{
  "id": 2153305,
  "type": "Feature",
  "properties": {
    "tgn:hierarchy":[
        "tgn:2153305",
        "tgn:1000001",
        "tgn:7012149",
        "tgn:7007922",
        "tgn:7029392"
    ],
    "tgn:id":2153305,
    "tgn:name":"Bean Brook",
    "tgn:placetype":[
        "aat:300008699"
    ]
},
  "bbox": [],
  "geometry": {"coordinates":[-91.5167,45.9167],"type":"Point"}
}
=======
{"geometry":{"type":"Point","coordinates":[-91.516700,45.916700]},"type":"Feature","properties":{"hierarchy":["tgn:2153305","tgn:1000001","tgn:7012149","tgn:7007922","tgn:7029392"],"placetype":["aat:300008699"],"id":2153305,"name:xx":"Bean Brook"}}
>>>>>>> 03f74aca74312dbeaf24d7e61306dd6a786dc3d0
