{
  "id": 2533643,
  "type": "Feature",
  "properties": {
    "tgn:hierarchy":[
        "tgn:2533643",
        "tgn:1000001",
        "tgn:7012149",
        "tgn:7007157",
        "tgn:7014475",
        "tgn:7029392"
    ],
    "tgn:id":2533643,
    "tgn:name":"Mustang Ridge",
    "tgn:placetype":[
        "aat:300266640"
    ]
},
  "bbox": [],
  "geometry": {"coordinates":[-121.2667,37.1167],"type":"Point"}
}