{
  "id": 2140820,
  "type": "Feature",
  "properties": {
    "tgn:hierarchy":[
        "tgn:2140820",
        "tgn:1002232",
        "tgn:1000001",
        "tgn:7012149",
        "tgn:7007565",
        "tgn:7029392"
    ],
    "tgn:id":2140820,
    "tgn:name":"Avalon Shoal",
    "tgn:placetype":[
        "aat:300132348"
    ]
},
  "bbox": [],
  "geometry": {"coordinates":[-74.5833,39.0833],"type":"Point"}
}