{
  "id": 7566980,
  "type": "Feature",
  "properties": {
    "tgn:hierarchy":[
        "tgn:7566980",
        "tgn:1000004",
        "tgn:1001871",
        "tgn:7000198",
        "tgn:7029392"
    ],
    "tgn:id":7566980,
    "tgn:name:en":"B\u0101s Khurd",
    "tgn:placetype":[
        "aat:300008347"
    ]
},
  "bbox": [],
  "geometry": {"coordinates":[76.070556,28.423333],"type":"Point"}
}