{
  "id": 7489798,
  "type": "Feature",
  "properties": {
    "tgn:hierarchy":[
        "tgn:7489798",
        "tgn:1000004",
        "tgn:7490934",
        "tgn:1000141",
        "tgn:7029392"
    ],
    "tgn:id":7489798,
    "tgn:name":"Shezilin",
    "tgn:placetype":[
        "aat:300008347"
    ]
},
  "bbox": [],
  "geometry": {"coordinates":[120.443056,23.337222],"type":"Point"}
}