<<<<<<< HEAD
{
  "id": 7170340,
  "type": "Feature",
  "properties": {
    "tgn:hierarchy":[
        "tgn:7170340",
        "tgn:1000003",
        "tgn:7003678",
        "tgn:7000084",
        "tgn:7029392"
    ],
    "tgn:id":7170340,
    "tgn:name":"Hobe",
    "tgn:placetype":[
        "aat:300000206"
    ]
},
  "bbox": [],
  "geometry": {"coordinates":[8.566667,51.016667],"type":"Point"}
}
=======
{"geometry":{"type":"Point","coordinates":[8.566667,51.016667]},"type":"Feature","properties":{"hierarchy":["tgn:7170340","tgn:1000003","tgn:7003678","tgn:7000084","tgn:7029392"],"placetype":["aat:300000206"],"id":7170340,"name:xx":"Hobe"}}
>>>>>>> 03f74aca74312dbeaf24d7e61306dd6a786dc3d0
