{
  "id": 7170340,
  "type": "Feature",
  "properties": {
    "tgn:hierarchy":[
        "tgn:7170340",
        "tgn:1000003",
        "tgn:7003678",
        "tgn:7000084",
        "tgn:7029392"
    ],
    "tgn:id":7170340,
    "tgn:name":"Hobe",
    "tgn:placetype":[
        "aat:300000206"
    ]
},
  "bbox": [],
  "geometry": {"coordinates":[8.566667,51.016667],"type":"Point"}
}