{
  "id": 1092758,
  "type": "Feature",
  "properties": {
    "tgn:hierarchy":[
        "tgn:1092758",
        "tgn:7001242",
        "tgn:1001774",
        "tgn:1000192",
        "tgn:7029392"
    ],
    "tgn:id":1092758,
    "tgn:name":"Saba Wanak",
    "tgn:placetype":[
        "aat:300008347"
    ]
},
  "bbox": [],
  "geometry": {"coordinates":[44.1333,10.55],"type":"Point"}
}