<<<<<<< HEAD
{
  "id": 7488767,
  "type": "Feature",
  "properties": {
    "tgn:hierarchy":[
        "tgn:7488767",
        "tgn:1000004",
        "tgn:1000454",
        "tgn:1000141",
        "tgn:7029392"
    ],
    "tgn:id":7488767,
    "tgn:name":"Longgoukeng",
    "tgn:placetype":[
        "aat:300008347"
    ]
},
  "bbox": [],
  "geometry": {"coordinates":[121.413362,25.084897],"type":"Point"}
}
=======
{"geometry":{"type":"Point","coordinates":[121.413362,25.084897]},"type":"Feature","properties":{"hierarchy":["tgn:7488767","tgn:1000004","tgn:1000454","tgn:1000141","tgn:7029392"],"placetype":["aat:300008347"],"id":7488767,"name:xx":"Longgoukeng"}}
>>>>>>> 03f74aca74312dbeaf24d7e61306dd6a786dc3d0
