{
  "id": 2212873,
  "type": "Feature",
  "properties": {
    "tgn:hierarchy":[
        "tgn:2212873",
        "tgn:1000001",
        "tgn:7022500",
        "tgn:7012149",
        "tgn:7007157",
        "tgn:1002828",
        "tgn:7029392"
    ],
    "tgn:id":2212873,
    "tgn:name":"C-17-1 Canal",
    "tgn:placetype":[
        "aat:300006075"
    ]
},
  "bbox": [],
  "geometry": {"coordinates":[-114.6333,33.4833],"type":"Point"}
}