{
  "id": 2694933,
  "type": "Feature",
  "properties": {
    "tgn:hierarchy":[
        "tgn:2694933",
        "tgn:1000001",
        "tgn:7016172",
        "tgn:7012149",
        "tgn:2000179",
        "tgn:7029392"
    ],
    "tgn:id":2694933,
    "tgn:name":"Still Branch",
    "tgn:placetype":[
        "aat:300008699"
    ]
},
  "bbox": [],
  "geometry": {"coordinates":[-93.5333,34.75],"type":"Point"}
}