{
  "id": 2316205,
  "type": "Feature",
  "properties": {
    "tgn:hierarchy":[
        "tgn:2316205",
        "tgn:1000001",
        "tgn:7012149",
        "tgn:2000995",
        "tgn:7007520",
        "tgn:7029392"
    ],
    "tgn:id":2316205,
    "tgn:name":"Elmer",
    "tgn:placetype":[
        "aat:300008347"
    ]
},
  "bbox": [],
  "geometry": {"coordinates":[-82.9167,43.4167],"type":"Point"}
}