{
  "id": 2352327,
  "type": "Feature",
  "properties": {
    "tgn:hierarchy":[
        "tgn:2352327",
        "tgn:7006450",
        "tgn:1000001",
        "tgn:7012149",
        "tgn:2000088",
        "tgn:7029392"
    ],
    "tgn:id":2352327,
    "tgn:name":"Goat Creek",
    "tgn:placetype":[
        "aat:300008706"
    ]
},
  "bbox": [],
  "geometry": {"coordinates":[-131.9833,56.5667],"type":"Point"}
}