{
  "id": 7489050,
  "type": "Feature",
  "properties": {
    "tgn:hierarchy":[
        "tgn:7489050",
        "tgn:7488858",
        "tgn:1000004",
        "tgn:1000141",
        "tgn:7029392"
    ],
    "tgn:id":7489050,
    "tgn:name":"Longyancun",
    "tgn:placetype":[
        "aat:300008347"
    ]
},
  "bbox": [],
  "geometry": {"coordinates":[120.75781,23.936792],"type":"Point"}
}