{
  "id": 7587420,
  "type": "Feature",
  "properties": {
    "tgn:hierarchy":[
        "tgn:7587420",
        "tgn:1000004",
        "tgn:7000198",
        "tgn:7000799",
        "tgn:7029392"
    ],
    "tgn:id":7587420,
    "tgn:name:en":"Sozyeth Gur\u012bpura",
    "tgn:placetype":[
        "aat:300008347"
    ]
},
  "bbox": [],
  "geometry": {"coordinates":[74.680506,34.114467],"type":"Point"}
}