{
  "id": 2704741,
  "type": "Feature",
  "properties": {
    "tgn:hierarchy":[
        "tgn:2704741",
        "tgn:1000001",
        "tgn:1002218",
        "tgn:7012149",
        "tgn:7007157",
        "tgn:7029392"
    ],
    "tgn:id":2704741,
    "tgn:name":"Sunset Hill",
    "tgn:placetype":[
        "aat:300008798"
    ]
},
  "bbox": [],
  "geometry": {"coordinates":[-121.2833,39.5167],"type":"Point"}
}