{
  "id": 2706483,
  "type": "Feature",
  "properties": {
    "tgn:hierarchy":[
        "tgn:2706483",
        "tgn:1000001",
        "tgn:7012149",
        "tgn:2001706",
        "tgn:7007708",
        "tgn:7029392"
    ],
    "tgn:id":2706483,
    "tgn:name":"Swan Hill",
    "tgn:placetype":[
        "aat:300008798"
    ]
},
  "bbox": [],
  "geometry": {"coordinates":[-123.4833,43.1167],"type":"Point"}
}