{
  "id": 2591890,
  "type": "Feature",
  "properties": {
    "tgn:hierarchy":[
        "tgn:2591890",
        "tgn:1000001",
        "tgn:7012149",
        "tgn:1002594",
        "tgn:7007920",
        "tgn:7029392"
    ],
    "tgn:id":2591890,
    "tgn:name":"Pond Number Two",
    "tgn:placetype":[
        "aat:300006191"
    ]
},
  "bbox": [],
  "geometry": {"coordinates":[-122.8333,46.7333],"type":"Point"}
}