{
  "id": 7201753,
  "type": "Feature",
  "properties": {
    "tgn:hierarchy":[
        "tgn:7201753",
        "tgn:7003669",
        "tgn:1000003",
        "tgn:7000084",
        "tgn:7029392"
    ],
    "tgn:id":7201753,
    "tgn:name":"Buchau",
    "tgn:placetype":[
        "aat:300008791"
    ]
},
  "bbox": [],
  "geometry": {"coordinates":[11.166667,47.683333],"type":"Point"}
}