<<<<<<< HEAD
{
  "id": 7175983,
  "type": "Feature",
  "properties": {
    "tgn:hierarchy":[
        "tgn:7175983",
        "tgn:1000003",
        "tgn:7003688",
        "tgn:7000084",
        "tgn:7029392"
    ],
    "tgn:id":7175983,
    "tgn:name":"Grevensberg",
    "tgn:placetype":[
        "aat:300000206"
    ]
},
  "bbox": [],
  "geometry": {"coordinates":[9.65,54.15],"type":"Point"}
}
=======
{"geometry":{"type":"Point","coordinates":[9.650000,54.150000]},"type":"Feature","properties":{"hierarchy":["tgn:7175983","tgn:1000003","tgn:7003688","tgn:7000084","tgn:7029392"],"placetype":["aat:300000206"],"id":7175983,"name:xx":"Grevensberg"}}
>>>>>>> 03f74aca74312dbeaf24d7e61306dd6a786dc3d0
