{
  "id": 2480213,
  "type": "Feature",
  "properties": {
    "tgn:hierarchy":[
        "tgn:2480213",
        "tgn:2002308",
        "tgn:1000001",
        "tgn:7012149",
        "tgn:7007922",
        "tgn:7029392"
    ],
    "tgn:id":2480213,
    "tgn:name":"Lake Owen",
    "tgn:placetype":[
        "aat:300008347"
    ]
},
  "bbox": [],
  "geometry": {"coordinates":[-91.25,46.2667],"type":"Point"}
}