{
  "id": 2650879,
  "type": "Feature",
  "properties": {
    "tgn:hierarchy":[
        "tgn:2650879",
        "tgn:1000001",
        "tgn:7012149",
        "tgn:2002290",
        "tgn:7013961",
        "tgn:7029392"
    ],
    "tgn:id":2650879,
    "tgn:name":"Second Fork",
    "tgn:placetype":[
        "aat:300008699"
    ]
},
  "bbox": [],
  "geometry": {"coordinates":[-80.9833,37.7833],"type":"Point"}
}