{
  "id": 7068677,
  "type": "Feature",
  "properties": {
    "tgn:hierarchy":[
        "tgn:7068677",
        "tgn:7000096",
        "tgn:1000003",
        "tgn:7000084",
        "tgn:7029392"
    ],
    "tgn:id":7068677,
    "tgn:name":"Staffelde",
    "tgn:placetype":[
        "aat:300008347"
    ]
},
  "bbox": [],
  "geometry": {"coordinates":[14.433333,53.266667],"type":"Point"}
}