{
  "id": 2580587,
  "type": "Feature",
  "properties": {
    "tgn:hierarchy":[
        "tgn:2580587",
        "tgn:1000001",
        "tgn:7012149",
        "tgn:2002361",
        "tgn:7007922",
        "tgn:7029392"
    ],
    "tgn:id":2580587,
    "tgn:name":"Pigeon Lake",
    "tgn:placetype":[
        "aat:300006191"
    ]
},
  "bbox": [],
  "geometry": {"coordinates":[-88.75,44.6167],"type":"Point"}
}