{
  "id": 7582467,
  "type": "Feature",
  "properties": {
    "tgn:hierarchy":[
        "tgn:7582467",
        "tgn:1000004",
        "tgn:7000198",
        "tgn:7016788",
        "tgn:7029392"
    ],
    "tgn:id":7582467,
    "tgn:name:en":"Khudiy\u0101n B\u0101s",
    "tgn:placetype":[
        "aat:300008347"
    ]
},
  "bbox": [],
  "geometry": {"coordinates":[75.550619,28.275572],"type":"Point"}
}