{
  "id": 7205051,
  "type": "Feature",
  "properties": {
    "tgn:hierarchy":[
        "tgn:7205051",
        "tgn:1000003",
        "tgn:7003677",
        "tgn:7000084",
        "tgn:7029392"
    ],
    "tgn:id":7205051,
    "tgn:name":"Claas",
    "tgn:placetype":[
        "aat:300000206"
    ]
},
  "bbox": [],
  "geometry": {"coordinates":[8.216667,51.983333],"type":"Point"}
}