<<<<<<< HEAD
{
  "id": 2404519,
  "type": "Feature",
  "properties": {
    "tgn:hierarchy":[
        "tgn:2404519",
        "tgn:1000001",
        "tgn:7012149",
        "tgn:2001925",
        "tgn:7007825",
        "tgn:7029392"
    ],
    "tgn:id":2404519,
    "tgn:name":"Hubbards Cave",
    "tgn:placetype":[
        "aat:300008746"
    ]
},
  "bbox": [],
  "geometry": {"coordinates":[-85.6667,35.5333],"type":"Point"}
}
=======
{"geometry":{"type":"Point","coordinates":[-85.666700,35.533300]},"type":"Feature","properties":{"hierarchy":["tgn:2404519","tgn:1000001","tgn:7012149","tgn:2001925","tgn:7007825","tgn:7029392"],"placetype":["aat:300008746"],"id":2404519,"name:xx":"Hubbards Cave"}}
>>>>>>> 03f74aca74312dbeaf24d7e61306dd6a786dc3d0
