{
  "id": 7177592,
  "type": "Feature",
  "properties": {
    "tgn:hierarchy":[
        "tgn:7177592",
        "tgn:1000003",
        "tgn:7003688",
        "tgn:7000084",
        "tgn:7029392"
    ],
    "tgn:id":7177592,
    "tgn:name":"Hakenhof",
    "tgn:placetype":[
        "aat:300000206"
    ]
},
  "bbox": [],
  "geometry": {"coordinates":[9.066667,54.416667],"type":"Point"}
}