{
  "id": 7003275,
  "type": "Feature",
  "properties": {
    "tgn:hierarchy":[
        "tgn:7003275",
        "tgn:7003026",
        "tgn:1000003",
        "tgn:1000062",
        "tgn:7029392"
    ],
    "tgn:id":7003275,
    "tgn:name":"Gr\u00fcnau",
    "tgn:placetype":[
        "aat:300008347"
    ]
},
  "bbox": [],
  "geometry": {"coordinates":[13.9667,47.85],"type":"Point"}
}