<<<<<<< HEAD
{
  "id": 2760382,
  "type": "Feature",
  "properties": {
    "tgn:hierarchy":[
        "tgn:2760382",
        "tgn:1000001",
        "tgn:7012149",
        "tgn:2001882",
        "tgn:7007825",
        "tgn:7029392"
    ],
    "tgn:id":2760382,
    "tgn:name":"West Fork Slabtown Branch",
    "tgn:placetype":[
        "aat:300008699"
    ]
},
  "bbox": [],
  "geometry": {"coordinates":[-81.9,36.4667],"type":"Point"}
}
=======
{"geometry":{"type":"Point","coordinates":[-81.900000,36.466700]},"type":"Feature","properties":{"hierarchy":["tgn:2760382","tgn:1000001","tgn:7012149","tgn:2001882","tgn:7007825","tgn:7029392"],"placetype":["aat:300008699"],"id":2760382,"name:xx":"West Fork Slabtown Branch"}}
>>>>>>> 03f74aca74312dbeaf24d7e61306dd6a786dc3d0
