{
  "id": 7331882,
  "type": "Feature",
  "properties": {
    "tgn:hierarchy":[
        "tgn:7331882",
        "tgn:7002824",
        "tgn:1000003",
        "tgn:7002786",
        "tgn:1000095",
        "tgn:7029392"
    ],
    "tgn:id":7331882,
    "tgn:name":"Jallas de Abajo",
    "tgn:placetype":[
        "aat:300008347"
    ]
},
  "bbox": [],
  "geometry": {"coordinates":[-8.866667,42.883333],"type":"Point"}
}