{
  "id": 7059298,
  "type": "Feature",
  "properties": {
    "tgn:hierarchy":[
        "tgn:7059298",
        "tgn:7003692",
        "tgn:1000003",
        "tgn:7000084",
        "tgn:7029392"
    ],
    "tgn:id":7059298,
    "tgn:name":"Alter Gemeindewald",
    "tgn:placetype":[
        "aat:300008863"
    ]
},
  "bbox": [],
  "geometry": {"coordinates":[9.133333,49.333333],"type":"Point"}
}