{
  "id": 7321123,
  "type": "Feature",
  "properties": {
    "tgn:hierarchy":[
        "tgn:7321123",
        "tgn:7016598",
        "tgn:1000049",
        "tgn:1000002",
        "tgn:7029392"
    ],
    "tgn:id":7321123,
    "tgn:name":"Blanca, Caleta",
    "tgn:placetype":[
        "aat:300132317"
    ]
},
  "bbox": [],
  "geometry": {"coordinates":[-70.233333,-22.166667],"type":"Point"}
}