{
  "id": 7472426,
  "type": "Feature",
  "properties": {
    "tgn:hierarchy":[
        "tgn:7472426",
        "tgn:7001010",
        "tgn:1000004",
        "tgn:1000141",
        "tgn:7029392"
    ],
    "tgn:id":7472426,
    "tgn:name":"Jinwen Qiao",
    "tgn:placetype":[
        "aat:300007836"
    ]
},
  "bbox": [],
  "geometry": {"coordinates":[121.621816,24.156384],"type":"Point"}
}