<<<<<<< HEAD
{
  "id": 7472426,
  "type": "Feature",
  "properties": {
    "tgn:hierarchy":[
        "tgn:7472426",
        "tgn:7001010",
        "tgn:1000004",
        "tgn:1000141",
        "tgn:7029392"
    ],
    "tgn:id":7472426,
    "tgn:name":"Jinwen Qiao",
    "tgn:placetype":[
        "aat:300007836"
    ]
},
  "bbox": [],
  "geometry": {"coordinates":[121.621816,24.156384],"type":"Point"}
}
=======
{"geometry":{"type":"Point","coordinates":[121.621816,24.156384]},"type":"Feature","properties":{"hierarchy":["tgn:7472426","tgn:7001010","tgn:1000004","tgn:1000141","tgn:7029392"],"placetype":["aat:300007836"],"id":7472426,"name:xx":"Jinwen Qiao"}}
>>>>>>> 03f74aca74312dbeaf24d7e61306dd6a786dc3d0
