<<<<<<< HEAD
{
  "id": 7471135,
  "type": "Feature",
  "properties": {
    "tgn:hierarchy":[
        "tgn:7471135",
        "tgn:7469009",
        "tgn:1000004",
        "tgn:1000141",
        "tgn:7029392"
    ],
    "tgn:id":7471135,
    "tgn:name":"Qionglin",
    "tgn:placetype":[
        "aat:300008347"
    ]
},
  "bbox": [],
  "geometry": {"coordinates":[118.375,24.452778],"type":"Point"}
}
=======
{"geometry":{"type":"Point","coordinates":[118.375000,24.452778]},"type":"Feature","properties":{"hierarchy":["tgn:7471135","tgn:7469009","tgn:1000004","tgn:1000141","tgn:7029392"],"placetype":["aat:300008347"],"id":7471135,"name:xx":"Qionglin"}}
>>>>>>> 03f74aca74312dbeaf24d7e61306dd6a786dc3d0
