{
  "id": 2507528,
  "type": "Feature",
  "properties": {
    "tgn:hierarchy":[
        "tgn:2507528",
        "tgn:1000001",
        "tgn:7012149",
        "tgn:1002629",
        "tgn:7007523",
        "tgn:7029392"
    ],
    "tgn:id":2507528,
    "tgn:name":"Meyerstown",
    "tgn:placetype":[
        "aat:300008347"
    ]
},
  "bbox": [],
  "geometry": {"coordinates":[-92.15,38.15],"type":"Point"}
}