{
  "id": 2481331,
  "type": "Feature",
  "properties": {
    "tgn:hierarchy":[
        "tgn:2481331",
        "tgn:1000001",
        "tgn:2001418",
        "tgn:7012149",
        "tgn:7007526",
        "tgn:7029392"
    ],
    "tgn:id":2481331,
    "tgn:name":"Lambs Canyon",
    "tgn:placetype":[
        "aat:300008761"
    ]
},
  "bbox": [],
  "geometry": {"coordinates":[-116.2667,37.25],"type":"Point"}
}