{
  "id": 2679757,
  "type": "Feature",
  "properties": {
    "tgn:hierarchy":[
        "tgn:2679757",
        "tgn:1000001",
        "tgn:7012149",
        "tgn:2001553",
        "tgn:7007709",
        "tgn:7029392"
    ],
    "tgn:id":2679757,
    "tgn:name":"South Fork Reddies River",
    "tgn:placetype":[
        "aat:300008707"
    ]
},
  "bbox": [],
  "geometry": {"coordinates":[-81.35,36.2833],"type":"Point"}
}