{
  "id": 7045182,
  "type": "Feature",
  "properties": {
    "tgn:hierarchy":[
        "tgn:7045182",
        "tgn:1000003",
        "tgn:7003142",
        "tgn:7003236",
        "tgn:1000080",
        "tgn:7029392"
    ],
    "tgn:id":7045182,
    "tgn:name":"Castellaccia",
    "tgn:placetype":[
        "aat:300000745"
    ]
},
  "bbox": [],
  "geometry": {"coordinates":[8.816667,44.433333],"type":"Point"}
}