<<<<<<< HEAD
{
  "id": 2401399,
  "type": "Feature",
  "properties": {
    "tgn:hierarchy":[
        "tgn:2401399",
        "tgn:1000001",
        "tgn:1002228",
        "tgn:7012149",
        "tgn:7007709",
        "tgn:7029392"
    ],
    "tgn:id":2401399,
    "tgn:name":"Horseshoe",
    "tgn:placetype":[
        "aat:300008347"
    ]
},
  "bbox": [],
  "geometry": {"coordinates":[-76.3833,36.45],"type":"Point"}
}
=======
{"geometry":{"type":"Point","coordinates":[-76.383300,36.450000]},"type":"Feature","properties":{"hierarchy":["tgn:2401399","tgn:1000001","tgn:1002228","tgn:7012149","tgn:7007709","tgn:7029392"],"placetype":["aat:300008347"],"id":2401399,"name:xx":"Horseshoe"}}
>>>>>>> 03f74aca74312dbeaf24d7e61306dd6a786dc3d0
