{
  "id": 2735885,
  "type": "Feature",
  "properties": {
    "tgn:hierarchy":[
        "tgn:2735885",
        "tgn:1000001",
        "tgn:7012149",
        "tgn:2000493",
        "tgn:7007250",
        "tgn:7029392"
    ],
    "tgn:id":2735885,
    "tgn:name":"Twin Lakes",
    "tgn:placetype":[
        "aat:300008680"
    ]
},
  "bbox": [],
  "geometry": {"coordinates":[-114.95,42.0333],"type":"Point"}
}