{
  "id": 7472309,
  "type": "Feature",
  "properties": {
    "tgn:hierarchy":[
        "tgn:7472309",
        "tgn:1000004",
        "tgn:7489179",
        "tgn:1000141",
        "tgn:7029392"
    ],
    "tgn:id":7472309,
    "tgn:name":"Wulai Xi",
    "tgn:placetype":[
        "aat:300008699"
    ]
},
  "bbox": [],
  "geometry": {"coordinates":[121.54925,24.3608],"type":"Point"}
}