{
  "id": 2146080,
  "type": "Feature",
  "properties": {
    "tgn:hierarchy":[
        "tgn:2146080",
        "tgn:1000001",
        "tgn:7006451",
        "tgn:7012149",
        "tgn:2000097",
        "tgn:7029392"
    ],
    "tgn:id":2146080,
    "tgn:name":"Ballantine Canyon",
    "tgn:placetype":[
        "aat:300008761"
    ]
},
  "bbox": [],
  "geometry": {"coordinates":[-111.3833,33.75],"type":"Point"}
}