{
  "id": 7573545,
  "type": "Feature",
  "properties": {
    "tgn:hierarchy":[
        "tgn:7573545",
        "tgn:1000004",
        "tgn:7000198",
        "tgn:7016722",
        "tgn:7029392"
    ],
    "tgn:id":7573545,
    "tgn:name:en":"Ir\u0101datnagar",
    "tgn:placetype":[
        "aat:300008347"
    ]
},
  "bbox": [],
  "geometry": {"coordinates":[78.043615,26.969551],"type":"Point"}
}