{
  "id": 2509539,
  "type": "Feature",
  "properties": {
    "tgn:hierarchy":[
        "tgn:2509539",
        "tgn:1000001",
        "tgn:7012149",
        "tgn:7013961",
        "tgn:7029392"
    ],
    "tgn:id":2509539,
    "tgn:name":"Middle Fork Williams River",
    "tgn:placetype":[
        "aat:300008707"
    ]
},
  "bbox": [],
  "geometry": {"coordinates":[-80.25,38.2667],"type":"Point"}
}