{
  "id": 7429869,
  "type": "Feature",
  "properties": {
    "tgn:hierarchy":[
        "tgn:7429869",
        "tgn:7005583",
        "tgn:1000001",
        "tgn:7005560",
        "tgn:7029392"
    ],
    "tgn:id":7429869,
    "tgn:name":"Los Alamos, R\u00edo",
    "tgn:placetype":[
        "aat:300008699"
    ]
},
  "bbox": [],
  "geometry": {"coordinates":[-103.833333,24.816667],"type":"Point"}
}