{
  "id": 2240450,
  "type": "Feature",
  "properties": {
    "tgn:hierarchy":[
        "tgn:2240450",
        "tgn:1002148",
        "tgn:1000001",
        "tgn:7012149",
        "tgn:7007826",
        "tgn:7029392"
    ],
    "tgn:id":2240450,
    "tgn:name":"City Lake",
    "tgn:placetype":[
        "aat:300006191"
    ]
},
  "bbox": [],
  "geometry": {"coordinates":[-95.65,31.75],"type":"Point"}
}