{
  "id": 2157875,
  "type": "Feature",
  "properties": {
    "tgn:hierarchy":[
        "tgn:2157875",
        "tgn:1000001",
        "tgn:7012149",
        "tgn:1002593",
        "tgn:7007568",
        "tgn:7029392"
    ],
    "tgn:id":2157875,
    "tgn:name":"Beaver Lake",
    "tgn:placetype":[
        "aat:300008680"
    ]
},
  "bbox": [],
  "geometry": {"coordinates":[-75.15,43.8667],"type":"Point"}
}