{
  "id": 7236625,
  "type": "Feature",
  "properties": {
    "tgn:hierarchy":[
        "tgn:7236625",
        "tgn:7002681",
        "tgn:7001395",
        "tgn:1000003",
        "tgn:1000074",
        "tgn:7029392"
    ],
    "tgn:id":7236625,
    "tgn:name":"\u00c1no A\u00ebt\u00f3s",
    "tgn:placetype":[
        "aat:300000745"
    ]
},
  "bbox": [],
  "geometry": {"coordinates":[24.45,38.016667],"type":"Point"}
}