{
  "id": 7478282,
  "type": "Feature",
  "properties": {
    "tgn:hierarchy":[
        "tgn:7478282",
        "tgn:1000004",
        "tgn:7492971",
        "tgn:1000141",
        "tgn:7029392"
    ],
    "tgn:id":7478282,
    "tgn:name":"Xingshan Si",
    "tgn:placetype":[
        "aat:300007595"
    ]
},
  "bbox": [],
  "geometry": {"coordinates":[120.380224,22.353291],"type":"Point"}
}