{
  "id": 2747054,
  "type": "Feature",
  "properties": {
    "tgn:hierarchy":[
        "tgn:2747054",
        "tgn:1000001",
        "tgn:7012149",
        "tgn:2001846",
        "tgn:7007825",
        "tgn:7029392"
    ],
    "tgn:id":2747054,
    "tgn:name":"Wagners Island",
    "tgn:placetype":[
        "aat:300008791"
    ]
},
  "bbox": [],
  "geometry": {"coordinates":[-82.15,36.35],"type":"Point"}
}