{
  "id": 7262966,
  "type": "Feature",
  "properties": {
    "tgn:concordances":{
        "gn:id":"2757875"
    },
    "tgn:hierarchy":[
        "tgn:7262966",
        "tgn:1000003",
        "tgn:7006951",
        "tgn:7016845",
        "tgn:7029392"
    ],
    "tgn:id":7262966,
    "tgn:name:nl":"Cruquius",
    "tgn:placetype":[
        "aat:300008347"
    ]
},
  "bbox": [],
  "geometry": {"coordinates":[4.633333,52.333333],"type":"Point"}
}