{
  "id": 2265454,
  "type": "Feature",
  "properties": {
    "tgn:hierarchy":[
        "tgn:2265454",
        "tgn:1000001",
        "tgn:7012149",
        "tgn:2000893",
        "tgn:7007256",
        "tgn:7029392"
    ],
    "tgn:id":2265454,
    "tgn:name":"Crane Lake",
    "tgn:placetype":[
        "aat:300008905"
    ]
},
  "bbox": [],
  "geometry": {"coordinates":[-92.7167,31.35],"type":"Point"}
}