{
  "id": 7530206,
  "type": "Feature",
  "properties": {
    "tgn:hierarchy":[
        "tgn:7530206",
        "tgn:7001242",
        "tgn:7016833",
        "tgn:7001335",
        "tgn:7029392"
    ],
    "tgn:id":7530206,
    "tgn:name":"Munbatah, Sahl el-",
    "tgn:placetype":[
        "aat:300008805"
    ]
},
  "bbox": [],
  "geometry": {"coordinates":[34.188056,30.618333],"type":"Point"}
}