{
  "id": 2702904,
  "type": "Feature",
  "properties": {
    "tgn:hierarchy":[
        "tgn:2702904",
        "tgn:1000001",
        "tgn:7012149",
        "tgn:2002186",
        "tgn:7007919",
        "tgn:7029392"
    ],
    "tgn:id":2702904,
    "tgn:name":"Sulphur Spring Hollow",
    "tgn:placetype":[
        "aat:300008761"
    ]
},
  "bbox": [],
  "geometry": {"coordinates":[-79.45,37.5833],"type":"Point"}
}