{
  "id": 2715929,
  "type": "Feature",
  "properties": {
    "tgn:hierarchy":[
        "tgn:2715929",
        "tgn:7006450",
        "tgn:1000001",
        "tgn:7012149",
        "tgn:2000086",
        "tgn:7029392"
    ],
    "tgn:id":2715929,
    "tgn:name":"Texas Creek",
    "tgn:placetype":[
        "aat:300008706"
    ]
},
  "bbox": [],
  "geometry": {"coordinates":[-142.35,61.35],"type":"Point"}
}