{
  "id": 2490819,
  "type": "Feature",
  "properties": {
    "tgn:hierarchy":[
        "tgn:2490819",
        "tgn:1000001",
        "tgn:1002198",
        "tgn:7012149",
        "tgn:7007826",
        "tgn:7029392"
    ],
    "tgn:id":2490819,
    "tgn:name":"Manor Lake",
    "tgn:placetype":[
        "aat:300008680"
    ]
},
  "bbox": [],
  "geometry": {"coordinates":[-95.5667,29.2167],"type":"Point"}
}