<<<<<<< HEAD
{
  "id": 7369048,
  "type": "Feature",
  "properties": {
    "tgn:hierarchy":[
        "tgn:7369048",
        "tgn:1000001",
        "tgn:1001906",
        "tgn:7005560",
        "tgn:7029392"
    ],
    "tgn:id":7369048,
    "tgn:name":"Ixtapa",
    "tgn:placetype":[
        "aat:300008347"
    ]
},
  "bbox": [],
  "geometry": {"coordinates":[-104.5,21.433333],"type":"Point"}
}
=======
{"geometry":{"type":"Point","coordinates":[-104.500000,21.433333]},"type":"Feature","properties":{"hierarchy":["tgn:7369048","tgn:1000001","tgn:1001906","tgn:7005560","tgn:7029392"],"placetype":["aat:300008347"],"id":7369048,"name:xx":"Ixtapa"}}
>>>>>>> 03f74aca74312dbeaf24d7e61306dd6a786dc3d0
