{
  "id": 7139349,
  "type": "Feature",
  "properties": {
    "tgn:hierarchy":[
        "tgn:7139349",
        "tgn:7000096",
        "tgn:1000003",
        "tgn:7000084",
        "tgn:7029392"
    ],
    "tgn:id":7139349,
    "tgn:name":"Leipsche Grobla",
    "tgn:placetype":[
        "aat:300008699"
    ]
},
  "bbox": [],
  "geometry": {"coordinates":[14.033333,51.866667],"type":"Point"}
}