{
  "id": 7186062,
  "type": "Feature",
  "properties": {
    "tgn:hierarchy":[
        "tgn:7186062",
        "tgn:7003669",
        "tgn:1000003",
        "tgn:7000084",
        "tgn:7029392"
    ],
    "tgn:id":7186062,
    "tgn:name":"Gollwitzerhof",
    "tgn:placetype":[
        "aat:300000206"
    ]
},
  "bbox": [],
  "geometry": {"coordinates":[12.233333,49.716667],"type":"Point"}
}