{
  "id": 2752071,
  "type": "Feature",
  "properties": {
    "tgn:hierarchy":[
        "tgn:2752071",
        "tgn:1000001",
        "tgn:2000952",
        "tgn:7012149",
        "tgn:7007520",
        "tgn:7029392"
    ],
    "tgn:id":2752071,
    "tgn:name":"Wasai, Baie de",
    "tgn:placetype":[
        "aat:300132316"
    ]
},
  "bbox": [],
  "geometry": {"coordinates":[-84.25,46.45],"type":"Point"}
}