{
  "id": 7534038,
  "type": "Feature",
  "properties": {
    "tgn:hierarchy":[
        "tgn:7534038",
        "tgn:7001242",
        "tgn:7016833",
        "tgn:7001312",
        "tgn:7029392"
    ],
    "tgn:id":7534038,
    "tgn:name:en":"Ma\u1e29allat al Burj",
    "tgn:placetype":[
        "aat:300008347"
    ]
},
  "bbox": [],
  "geometry": {"coordinates":[31.166667,30.983333],"type":"Point"}
}