{
  "id": 2568852,
  "type": "Feature",
  "properties": {
    "tgn:hierarchy":[
        "tgn:2568852",
        "tgn:1000001",
        "tgn:7012149",
        "tgn:2001878",
        "tgn:7007825",
        "tgn:7029392"
    ],
    "tgn:id":2568852,
    "tgn:name":"Parker Hill",
    "tgn:placetype":[
        "aat:300008798"
    ]
},
  "bbox": [],
  "geometry": {"coordinates":[-87.85,36.25],"type":"Point"}
}