{
  "id": 7165188,
  "type": "Feature",
  "properties": {
    "tgn:hierarchy":[
        "tgn:7165188",
        "tgn:7003692",
        "tgn:1000003",
        "tgn:7000084",
        "tgn:7029392"
    ],
    "tgn:id":7165188,
    "tgn:name":"Ihingerhof",
    "tgn:placetype":[
        "aat:300000206"
    ]
},
  "bbox": [],
  "geometry": {"coordinates":[8.933333,48.733333],"type":"Point"}
}