{
  "id": 2518757,
  "type": "Feature",
  "properties": {
    "tgn:hierarchy":[
        "tgn:2518757",
        "tgn:1000001",
        "tgn:7012149",
        "tgn:2000747",
        "tgn:7007254",
        "tgn:7029392"
    ],
    "tgn:id":2518757,
    "tgn:name":"Mitchell Pond",
    "tgn:placetype":[
        "aat:300006191"
    ]
},
  "bbox": [],
  "geometry": {"coordinates":[-100.95,37.35],"type":"Point"}
}