{
  "id": 1018967,
  "type": "Feature",
  "properties": {
    "tgn:hierarchy":[
        "tgn:1018967",
        "tgn:7017440",
        "tgn:1000001",
        "tgn:7004643",
        "tgn:7029392"
    ],
    "tgn:id":1018967,
    "tgn:name":"Juana D\u00edaz",
    "tgn:placetype":[
        "aat:300008347"
    ]
},
  "bbox": [],
  "geometry": {"coordinates":[-66.5167,18.05],"type":"Point"}
}