{
  "id": 2145633,
  "type": "Feature",
  "properties": {
    "tgn:hierarchy":[
        "tgn:2145633",
        "tgn:1000001",
        "tgn:1002712",
        "tgn:7012149",
        "tgn:7007159",
        "tgn:7029392"
    ],
    "tgn:id":2145633,
    "tgn:name":"Baldwin Swamp",
    "tgn:placetype":[
        "aat:300008905"
    ]
},
  "bbox": [],
  "geometry": {"coordinates":[-73.0667,41.2333],"type":"Point"}
}