{
  "id": 2181426,
  "type": "Feature",
  "properties": {
    "tgn:hierarchy":[
        "tgn:2181426",
        "tgn:1000001",
        "tgn:7012149",
        "tgn:7020792",
        "tgn:7007524",
        "tgn:7029392"
    ],
    "tgn:id":2181426,
    "tgn:name":"Blue Eyed Nellie Gulch",
    "tgn:placetype":[
        "aat:300008761"
    ]
},
  "bbox": [],
  "geometry": {"coordinates":[-113.05,46.1833],"type":"Point"}
}