{
  "id": 2554910,
  "type": "Feature",
  "properties": {
    "tgn:hierarchy":[
        "tgn:2554910",
        "tgn:1000001",
        "tgn:7012149",
        "tgn:7021746",
        "tgn:7007826",
        "tgn:7029392"
    ],
    "tgn:id":2554910,
    "tgn:name":"Oaxley Branch",
    "tgn:placetype":[
        "aat:300008699"
    ]
},
  "bbox": [],
  "geometry": {"coordinates":[-97.25,29.1167],"type":"Point"}
}