{
  "id": 7078070,
  "type": "Feature",
  "properties": {
    "tgn:hierarchy":[
        "tgn:7078070",
        "tgn:1000003",
        "tgn:7003676",
        "tgn:7000084",
        "tgn:7029392"
    ],
    "tgn:id":7078070,
    "tgn:name":"F\u00f6rsterei Ziegelei",
    "tgn:placetype":[
        "aat:300004792"
    ]
},
  "bbox": [],
  "geometry": {"coordinates":[9.35,51.883333],"type":"Point"}
}