{
  "id": 1140935,
  "type": "Feature",
  "properties": {
    "tgn:hierarchy":[
        "tgn:1140935",
        "tgn:7001242",
        "tgn:1001706",
        "tgn:1000203",
        "tgn:7029392"
    ],
    "tgn:id":1140935,
    "tgn:name":"Mwaya",
    "tgn:placetype":[
        "aat:300008347"
    ]
},
  "bbox": [],
  "geometry": {"coordinates":[33.9333,-9.55],"type":"Point"}
}