{
  "id": 1111036,
  "type": "Feature",
  "properties": {
    "tgn:hierarchy":[
        "tgn:1111036",
        "tgn:7001242",
        "tgn:1000905",
        "tgn:1000150",
        "tgn:7029392"
    ],
    "tgn:id":1111036,
    "tgn:name":"Okavango Delta",
    "tgn:placetype":[
        "aat:300008760"
    ]
},
  "bbox": [],
  "geometry": {"coordinates":[22.75,-18.75],"type":"Point"}
}