{
  "id": 2576191,
  "type": "Feature",
  "properties": {
    "tgn:hierarchy":[
        "tgn:2576191",
        "tgn:7030516",
        "tgn:7006450",
        "tgn:1000001",
        "tgn:7012149",
        "tgn:7029392"
    ],
    "tgn:id":2576191,
    "tgn:name":"Perret Ridge",
    "tgn:placetype":[
        "aat:300266640"
    ]
},
  "bbox": [],
  "geometry": {"coordinates":[179.6667,51.9667],"type":"Point"}
}