{
  "id": 2635159,
  "type": "Feature",
  "properties": {
    "tgn:hierarchy":[
        "tgn:2635159",
        "tgn:1000001",
        "tgn:1002235",
        "tgn:7012149",
        "tgn:7007919",
        "tgn:7029392"
    ],
    "tgn:id":2635159,
    "tgn:name":"Ryland Corner",
    "tgn:placetype":[
        "aat:300008347"
    ]
},
  "bbox": [],
  "geometry": {"coordinates":[-77.5167,38.0333],"type":"Point"}
}