{
  "id": 7468440,
  "type": "Feature",
  "properties": {
    "tgn:hierarchy":[
        "tgn:7468440",
        "tgn:7487020",
        "tgn:1000004",
        "tgn:1000141",
        "tgn:7029392"
    ],
    "tgn:id":7468440,
    "tgn:name":"Xingongguan",
    "tgn:placetype":[
        "aat:300008347"
    ]
},
  "bbox": [],
  "geometry": {"coordinates":[120.864399,24.51446],"type":"Point"}
}