{
  "id": 2370521,
  "type": "Feature",
  "properties": {
    "tgn:hierarchy":[
        "tgn:2370521",
        "tgn:1000001",
        "tgn:7012149",
        "tgn:1002550",
        "tgn:7007157",
        "tgn:7029392"
    ],
    "tgn:id":2370521,
    "tgn:name":"Hacienda Spillway",
    "tgn:placetype":[
        "aat:300006075"
    ]
},
  "bbox": [],
  "geometry": {"coordinates":[-119.65,35.8333],"type":"Point"}
}