{
  "id": 2517748,
  "type": "Feature",
  "properties": {
    "tgn:hierarchy":[
        "tgn:2517748",
        "tgn:1000001",
        "tgn:7012149",
        "tgn:2000216",
        "tgn:7007158",
        "tgn:7029392"
    ],
    "tgn:id":2517748,
    "tgn:name":"Mirror Lake",
    "tgn:placetype":[
        "aat:300008680"
    ]
},
  "bbox": [],
  "geometry": {"coordinates":[-105.65,40.0667],"type":"Point"}
}