<<<<<<< HEAD
{
  "id": 2337057,
  "type": "Feature",
  "properties": {
    "tgn:hierarchy":[
        "tgn:2337057",
        "tgn:1000001",
        "tgn:7012149",
        "tgn:2000277",
        "tgn:7007240",
        "tgn:7029392"
    ],
    "tgn:id":2337057,
    "tgn:name":"Fourmile Pond",
    "tgn:placetype":[
        "aat:300008680"
    ]
},
  "bbox": [],
  "geometry": {"coordinates":[-82.5,29.25],"type":"Point"}
}
=======
{"geometry":{"type":"Point","coordinates":[-82.500000,29.250000]},"type":"Feature","properties":{"hierarchy":["tgn:2337057","tgn:1000001","tgn:7012149","tgn:2000277","tgn:7007240","tgn:7029392"],"placetype":["aat:300008680"],"id":2337057,"name:xx":"Fourmile Pond"}}
>>>>>>> 03f74aca74312dbeaf24d7e61306dd6a786dc3d0
