{
  "id": 2258771,
  "type": "Feature",
  "properties": {
    "tgn:hierarchy":[
        "tgn:2258771",
        "tgn:7006450",
        "tgn:1000001",
        "tgn:2124053",
        "tgn:7012149",
        "tgn:7029392"
    ],
    "tgn:id":2258771,
    "tgn:name":"Cottonwood Creek",
    "tgn:placetype":[
        "aat:300008706"
    ]
},
  "bbox": [],
  "geometry": {"coordinates":[-148.45,61.55],"type":"Point"}
}