<<<<<<< HEAD
{
  "id": 2258771,
  "type": "Feature",
  "properties": {
    "tgn:hierarchy":[
        "tgn:2258771",
        "tgn:7006450",
        "tgn:1000001",
        "tgn:2124053",
        "tgn:7012149",
        "tgn:7029392"
    ],
    "tgn:id":2258771,
    "tgn:name":"Cottonwood Creek",
    "tgn:placetype":[
        "aat:300008706"
    ]
},
  "bbox": [],
  "geometry": {"coordinates":[-148.45,61.55],"type":"Point"}
}
=======
{"geometry":{"type":"Point","coordinates":[-148.450000,61.550000]},"type":"Feature","properties":{"hierarchy":["tgn:2258771","tgn:7006450","tgn:1000001","tgn:2124053","tgn:7012149","tgn:7029392"],"placetype":["aat:300008706"],"id":2258771,"name:xx":"Cottonwood Creek"}}
>>>>>>> 03f74aca74312dbeaf24d7e61306dd6a786dc3d0
