{
  "id": 2509399,
  "type": "Feature",
  "properties": {
    "tgn:hierarchy":[
        "tgn:2509399",
        "tgn:1000001",
        "tgn:2001704",
        "tgn:7012149",
        "tgn:7007708",
        "tgn:7029392"
    ],
    "tgn:id":2509399,
    "tgn:name":"Middle Fork Sixes River",
    "tgn:placetype":[
        "aat:300008707"
    ]
},
  "bbox": [],
  "geometry": {"coordinates":[-124.1667,42.75],"type":"Point"}
}