{
  "id": 7548509,
  "type": "Feature",
  "properties": {
    "tgn:hierarchy":[
        "tgn:7548509",
        "tgn:1000004",
        "tgn:7018318",
        "tgn:7000198",
        "tgn:7029392"
    ],
    "tgn:id":7548509,
    "tgn:name:en":"Buimpal",
    "tgn:placetype":[
        "aat:300008347"
    ]
},
  "bbox": [],
  "geometry": {"coordinates":[74.066667,15.533333],"type":"Point"}
}