{
  "id": 7291672,
  "type": "Feature",
  "properties": {
    "tgn:hierarchy":[
        "tgn:7291672",
        "tgn:1001768",
        "tgn:1000049",
        "tgn:1000002",
        "tgn:7029392"
    ],
    "tgn:id":7291672,
    "tgn:name":"Enrique Meiggs",
    "tgn:placetype":[
        "aat:300008347"
    ]
},
  "bbox": [],
  "geometry": {"coordinates":[-70.866667,-32.85],"type":"Point"}
}