{
  "id": 7383593,
  "type": "Feature",
  "properties": {
    "tgn:hierarchy":[
        "tgn:7383593",
        "tgn:1000001",
        "tgn:1001893",
        "tgn:7005560",
        "tgn:7029392"
    ],
    "tgn:id":7383593,
    "tgn:name":"Puente Murillo",
    "tgn:placetype":[
        "aat:300007836"
    ]
},
  "bbox": [],
  "geometry": {"coordinates":[-97.883333,22.216667],"type":"Point"}
}