{
  "id": 2613260,
  "type": "Feature",
  "properties": {
    "tgn:hierarchy":[
        "tgn:2613260",
        "tgn:1000001",
        "tgn:2000921",
        "tgn:7012149",
        "tgn:7007515",
        "tgn:7029392"
    ],
    "tgn:id":2613260,
    "tgn:name":"Reed Brook",
    "tgn:placetype":[
        "aat:300008699"
    ]
},
  "bbox": [],
  "geometry": {"coordinates":[-70.5333,45.1833],"type":"Point"}
}