{
  "id": 7568039,
  "type": "Feature",
  "properties": {
    "tgn:hierarchy":[
        "tgn:7568039",
        "tgn:1000004",
        "tgn:7000198",
        "tgn:1001996",
        "tgn:7029392"
    ],
    "tgn:id":7568039,
    "tgn:name:en":"B\u0101g Protected Forest",
    "tgn:placetype":[
        "aat:300008863"
    ]
},
  "bbox": [],
  "geometry": {"coordinates":[77.122222,31.218333],"type":"Point"}
}