{
  "id": 2381049,
  "type": "Feature",
  "properties": {
    "tgn:hierarchy":[
        "tgn:2381049",
        "tgn:1000001",
        "tgn:7012149",
        "tgn:2000997",
        "tgn:7007520",
        "tgn:7029392"
    ],
    "tgn:id":2381049,
    "tgn:name":"Hawkins Drain",
    "tgn:placetype":[
        "aat:300006075"
    ]
},
  "bbox": [],
  "geometry": {"coordinates":[-83.6833,43.4833],"type":"Point"}
}