{
  "id": 7399336,
  "type": "Feature",
  "properties": {
    "tgn:hierarchy":[
        "tgn:7399336",
        "tgn:1000001",
        "tgn:7005593",
        "tgn:7005560",
        "tgn:7029392"
    ],
    "tgn:id":7399336,
    "tgn:name":"Bordos Cuates",
    "tgn:placetype":[
        "aat:300008347"
    ]
},
  "bbox": [],
  "geometry": {"coordinates":[-100.329167,20.433333],"type":"Point"}
}