{
  "id": 2471386,
  "type": "Feature",
  "properties": {
    "tgn:hierarchy":[
        "tgn:2471386",
        "tgn:1000001",
        "tgn:7012149",
        "tgn:2000886",
        "tgn:7007256",
        "tgn:7029392"
    ],
    "tgn:id":2471386,
    "tgn:name":"Lost Lake",
    "tgn:placetype":[
        "aat:300008680"
    ]
},
  "bbox": [],
  "geometry": {"coordinates":[-91.4167,32.35],"type":"Point"}
}