{
  "id": 7502005,
  "type": "Feature",
  "properties": {
    "tgn:hierarchy":[
        "tgn:7502005",
        "tgn:1000004",
        "tgn:7492971",
        "tgn:1000141",
        "tgn:7029392"
    ],
    "tgn:id":7502005,
    "tgn:name":"Ailiao Xikou",
    "tgn:placetype":[
        "aat:300387057"
    ]
},
  "bbox": [],
  "geometry": {"coordinates":[120.895,22.046667],"type":"Point"}
}