{
  "id": 7136658,
  "type": "Feature",
  "properties": {
    "tgn:hierarchy":[
        "tgn:7136658",
        "tgn:1000003",
        "tgn:7000094",
        "tgn:7000084",
        "tgn:7029392"
    ],
    "tgn:id":7136658,
    "tgn:name":"Lehsten",
    "tgn:placetype":[
        "aat:300008347"
    ]
},
  "bbox": [],
  "geometry": {"coordinates":[13.216667,54.533333],"type":"Point"}
}