{
  "id": 1120230,
  "type": "Feature",
  "properties": {
    "tgn:hierarchy":[
        "tgn:1120230",
        "tgn:1000004",
        "tgn:1001503",
        "tgn:1000135",
        "tgn:7029392"
    ],
    "tgn:id":1120230,
    "tgn:name":"Novaliches Watershed",
    "tgn:placetype":[
        "aat:300006191"
    ]
},
  "bbox": [],
  "geometry": {"coordinates":[121.0833,14.7167],"type":"Point"}
}