{
  "id": 7158983,
  "type": "Feature",
  "properties": {
    "tgn:hierarchy":[
        "tgn:7158983",
        "tgn:7003669",
        "tgn:1000003",
        "tgn:7000084",
        "tgn:7029392"
    ],
    "tgn:id":7158983,
    "tgn:name":"Hofstett",
    "tgn:placetype":[
        "aat:300000206"
    ]
},
  "bbox": [],
  "geometry": {"coordinates":[13.333333,48.633333],"type":"Point"}
}