{
  "id": 2503931,
  "type": "Feature",
  "properties": {
    "tgn:hierarchy":[
        "tgn:2503931",
        "tgn:1000001",
        "tgn:2002241",
        "tgn:7012149",
        "tgn:7007920",
        "tgn:7029392"
    ],
    "tgn:id":2503931,
    "tgn:name":"Meadow Creek",
    "tgn:placetype":[
        "aat:300008706"
    ]
},
  "bbox": [],
  "geometry": {"coordinates":[-117.7667,46.0833],"type":"Point"}
}