{
  "id": 1073246,
  "type": "Feature",
  "properties": {
    "tgn:hierarchy":[
        "tgn:1073246",
        "tgn:1000004",
        "tgn:7002081",
        "tgn:1000111",
        "tgn:7029392"
    ],
    "tgn:id":1073246,
    "tgn:name":"Xuguichenxiaodian",
    "tgn:placetype":[
        "aat:300008347"
    ]
},
  "bbox": [],
  "geometry": {"coordinates":[121.3333,32.1167],"type":"Point"}
}