{
  "id": 2383730,
  "type": "Feature",
  "properties": {
    "tgn:hierarchy":[
        "tgn:2383730",
        "tgn:1000001",
        "tgn:7012149",
        "tgn:2000917",
        "tgn:7007256",
        "tgn:7029392"
    ],
    "tgn:id":2383730,
    "tgn:name":"Hebron Branch",
    "tgn:placetype":[
        "aat:300008699"
    ]
},
  "bbox": [],
  "geometry": {"coordinates":[-92.35,32.0833],"type":"Point"}
}