{
  "id": 2520167,
  "type": "Feature",
  "properties": {
    "tgn:hierarchy":[
        "tgn:2520167",
        "tgn:1000001",
        "tgn:7012149",
        "tgn:2001718",
        "tgn:7007708",
        "tgn:7029392"
    ],
    "tgn:id":2520167,
    "tgn:name":"Moltham Reservoir Two",
    "tgn:placetype":[
        "aat:300006191"
    ]
},
  "bbox": [],
  "geometry": {"coordinates":[-117.95,44.25],"type":"Point"}
}