{
  "id": 1102171,
  "type": "Feature",
  "properties": {
    "tgn:hierarchy":[
        "tgn:1102171",
        "tgn:1000001",
        "tgn:2001418",
        "tgn:7012149",
        "tgn:7007526",
        "tgn:7029392"
    ],
    "tgn:id":1102171,
    "tgn:name":"Berlin-Ichthyosaur State Park",
    "tgn:placetype":[
        "aat:300008192"
    ]
},
  "bbox": [],
  "geometry": {"coordinates":[-117.5833,38.8667],"type":"Point"}
}