{
  "id": 2482192,
  "type": "Feature",
  "properties": {
    "tgn:hierarchy":[
        "tgn:2482192",
        "tgn:1000001",
        "tgn:2001025",
        "tgn:7012149",
        "tgn:7007521",
        "tgn:7029392"
    ],
    "tgn:id":2482192,
    "tgn:name":"Langdon Lake",
    "tgn:placetype":[
        "aat:300008680"
    ]
},
  "bbox": [],
  "geometry": {"coordinates":[-93.6667,44.9333],"type":"Point"}
}