{
  "id": 7348268,
  "type": "Feature",
  "properties": {
    "tgn:hierarchy":[
        "tgn:7348268",
        "tgn:7002758",
        "tgn:7002841",
        "tgn:1000003",
        "tgn:1000095",
        "tgn:7029392"
    ],
    "tgn:id":7348268,
    "tgn:name":"\u00c1guila, Llanos del",
    "tgn:placetype":[
        "aat:300008805"
    ]
},
  "bbox": [],
  "geometry": {"coordinates":[-5.166667,37.383333],"type":"Point"}
}