<<<<<<< HEAD
{
  "id": 7369056,
  "type": "Feature",
  "properties": {
    "tgn:hierarchy":[
        "tgn:7369056",
        "tgn:7005587",
        "tgn:1000001",
        "tgn:7005560",
        "tgn:7029392"
    ],
    "tgn:id":7369056,
    "tgn:name":"Ixtamichapa",
    "tgn:placetype":[
        "aat:300008347"
    ]
},
  "bbox": [],
  "geometry": {"coordinates":[-98.966667,20.8],"type":"Point"}
}
=======
{"geometry":{"type":"Point","coordinates":[-98.966667,20.800000]},"type":"Feature","properties":{"hierarchy":["tgn:7369056","tgn:7005587","tgn:1000001","tgn:7005560","tgn:7029392"],"placetype":["aat:300008347"],"id":7369056,"name:xx":"Ixtamichapa"}}
>>>>>>> 03f74aca74312dbeaf24d7e61306dd6a786dc3d0
