{
  "id": 2638440,
  "type": "Feature",
  "properties": {
    "tgn:hierarchy":[
        "tgn:2638440",
        "tgn:1000001",
        "tgn:1002270",
        "tgn:7012149",
        "tgn:7007708",
        "tgn:7029392"
    ],
    "tgn:id":2638440,
    "tgn:name":"Salmon",
    "tgn:placetype":[
        "aat:300008347"
    ]
},
  "bbox": [],
  "geometry": {"coordinates":[-122.0167,45.3667],"type":"Point"}
}