{
  "id": 2746072,
  "type": "Feature",
  "properties": {
    "tgn:hierarchy":[
        "tgn:2746072",
        "tgn:1000001",
        "tgn:7012149",
        "tgn:7014097",
        "tgn:7007158",
        "tgn:7029392"
    ],
    "tgn:id":2746072,
    "tgn:name":"Vollmer Hill",
    "tgn:placetype":[
        "aat:300008798"
    ]
},
  "bbox": [],
  "geometry": {"coordinates":[-104.65,39.0167],"type":"Point"}
}