{
  "id": 7076466,
  "type": "Feature",
  "properties": {
    "tgn:hierarchy":[
        "tgn:7076466",
        "tgn:1000003",
        "tgn:7000094",
        "tgn:7000084",
        "tgn:7029392"
    ],
    "tgn:id":7076466,
    "tgn:name":"Landkreis Uecker-Randow",
    "tgn:placetype":[
        "aat:300387198"
    ]
},
  "bbox": [],
  "geometry": {"coordinates":[14.088889,53.598333],"type":"Point"}
}