{
  "id": 7425002,
  "type": "Feature",
  "properties": {
    "tgn:hierarchy":[
        "tgn:7425002",
        "tgn:1000001",
        "tgn:7005597",
        "tgn:7005560",
        "tgn:7029392"
    ],
    "tgn:id":7425002,
    "tgn:name":"La Salada, Laguna",
    "tgn:placetype":[
        "aat:300008680"
    ]
},
  "bbox": [],
  "geometry": {"coordinates":[-97.866667,25.216667],"type":"Point"}
}