<<<<<<< HEAD
{
  "id": 2159377,
  "type": "Feature",
  "properties": {
    "tgn:hierarchy":[
        "tgn:2159377",
        "tgn:1000001",
        "tgn:7012149",
        "tgn:2001497",
        "tgn:7007709",
        "tgn:7029392"
    ],
    "tgn:id":2159377,
    "tgn:name":"Bee Cove",
    "tgn:placetype":[
        "aat:300008761"
    ]
},
  "bbox": [],
  "geometry": {"coordinates":[-83.7833,35.4167],"type":"Point"}
}
=======
{"geometry":{"type":"Point","coordinates":[-83.783300,35.416700]},"type":"Feature","properties":{"hierarchy":["tgn:2159377","tgn:1000001","tgn:7012149","tgn:2001497","tgn:7007709","tgn:7029392"],"placetype":["aat:300008761"],"id":2159377,"name:xx":"Bee Cove"}}
>>>>>>> 03f74aca74312dbeaf24d7e61306dd6a786dc3d0
