{
  "id": 2453844,
  "type": "Feature",
  "properties": {
    "tgn:hierarchy":[
        "tgn:2453844",
        "tgn:1000001",
        "tgn:7012149",
        "tgn:7007157",
        "tgn:1002864",
        "tgn:7029392"
    ],
    "tgn:id":2453844,
    "tgn:name":"Little Coyote Point",
    "tgn:placetype":[
        "aat:300008850"
    ]
},
  "bbox": [],
  "geometry": {"coordinates":[-122.25,37.5667],"type":"Point"}
}