{
  "id": 7299539,
  "type": "Feature",
  "properties": {
    "tgn:hierarchy":[
        "tgn:7299539",
        "tgn:7008911",
        "tgn:1000003",
        "tgn:7002763",
        "tgn:1000095",
        "tgn:7029392"
    ],
    "tgn:id":7299539,
    "tgn:name":"Tiroco de Arriba",
    "tgn:placetype":[
        "aat:300008347"
    ]
},
  "bbox": [],
  "geometry": {"coordinates":[-5.65,43.366667],"type":"Point"}
}