<<<<<<< HEAD
{
  "id": 2331574,
  "type": "Feature",
  "properties": {
    "tgn:hierarchy":[
        "tgn:2331574",
        "tgn:1000001",
        "tgn:7012149",
        "tgn:2002093",
        "tgn:7007826",
        "tgn:7029392"
    ],
    "tgn:id":2331574,
    "tgn:name":"Flax Tank",
    "tgn:placetype":[
        "aat:300006191"
    ]
},
  "bbox": [],
  "geometry": {"coordinates":[-99.2,33.9833],"type":"Point"}
}
=======
{"geometry":{"type":"Point","coordinates":[-99.200000,33.983300]},"type":"Feature","properties":{"hierarchy":["tgn:2331574","tgn:1000001","tgn:7012149","tgn:2002093","tgn:7007826","tgn:7029392"],"placetype":["aat:300006191"],"id":2331574,"name:xx":"Flax Tank"}}
>>>>>>> 03f74aca74312dbeaf24d7e61306dd6a786dc3d0
