{
  "id": 7116920,
  "type": "Feature",
  "properties": {
    "tgn:hierarchy":[
        "tgn:7116920",
        "tgn:1000003",
        "tgn:7003677",
        "tgn:7000084",
        "tgn:7029392"
    ],
    "tgn:id":7116920,
    "tgn:name":"Oesterndorf",
    "tgn:placetype":[
        "aat:300008347"
    ]
},
  "bbox": [],
  "geometry": {"coordinates":[8.116667,51.65],"type":"Point"}
}