{
  "id": 7235392,
  "type": "Feature",
  "properties": {
    "tgn:hierarchy":[
        "tgn:7235392",
        "tgn:7011170",
        "tgn:7002715",
        "tgn:1000003",
        "tgn:1000074",
        "tgn:7029392"
    ],
    "tgn:id":7235392,
    "tgn:name":"Balo\u00fastra, \u00c1kra",
    "tgn:placetype":[
        "aat:300008850"
    ]
},
  "bbox": [],
  "geometry": {"coordinates":[24.983333,40.933333],"type":"Point"}
}