{
  "id": 2246220,
  "type": "Feature",
  "properties": {
    "tgn:hierarchy":[
        "tgn:2246220",
        "tgn:1000001",
        "tgn:7012149",
        "tgn:2002297",
        "tgn:7013961",
        "tgn:7029392"
    ],
    "tgn:id":2246220,
    "tgn:name":"Coallick Run",
    "tgn:placetype":[
        "aat:300008699"
    ]
},
  "bbox": [],
  "geometry": {"coordinates":[-80.85,39.5333],"type":"Point"}
}