{
  "id": 2718418,
  "type": "Feature",
  "properties": {
    "tgn:hierarchy":[
        "tgn:2718418",
        "tgn:7002659",
        "tgn:1000001",
        "tgn:2000008",
        "tgn:7012149",
        "tgn:7029392"
    ],
    "tgn:id":2718418,
    "tgn:name":"Thompson Lake",
    "tgn:placetype":[
        "aat:300006191"
    ]
},
  "bbox": [],
  "geometry": {"coordinates":[-85.25,32.9833],"type":"Point"}
}