{
  "id": 2766993,
  "type": "Feature",
  "properties": {
    "tgn:hierarchy":[
        "tgn:2766993",
        "tgn:1000001",
        "tgn:7013686",
        "tgn:7012149",
        "tgn:7007517",
        "tgn:7029392"
    ],
    "tgn:id":2766993,
    "tgn:name":"White Reservoir",
    "tgn:placetype":[
        "aat:300006191"
    ]
},
  "bbox": [],
  "geometry": {"coordinates":[-72.7833,42.25],"type":"Point"}
}