<<<<<<< HEAD
{
  "id": 2766993,
  "type": "Feature",
  "properties": {
    "tgn:hierarchy":[
        "tgn:2766993",
        "tgn:1000001",
        "tgn:7013686",
        "tgn:7012149",
        "tgn:7007517",
        "tgn:7029392"
    ],
    "tgn:id":2766993,
    "tgn:name":"White Reservoir",
    "tgn:placetype":[
        "aat:300006191"
    ]
},
  "bbox": [],
  "geometry": {"coordinates":[-72.7833,42.25],"type":"Point"}
}
=======
{"geometry":{"type":"Point","coordinates":[-72.783300,42.250000]},"type":"Feature","properties":{"hierarchy":["tgn:2766993","tgn:1000001","tgn:7013686","tgn:7012149","tgn:7007517","tgn:7029392"],"placetype":["aat:300006191"],"id":2766993,"name:xx":"White Reservoir"}}
>>>>>>> 03f74aca74312dbeaf24d7e61306dd6a786dc3d0
