{
  "id": 2480425,
  "type": "Feature",
  "properties": {
    "tgn:hierarchy":[
        "tgn:2480425",
        "tgn:1000001",
        "tgn:7012149",
        "tgn:7007568",
        "tgn:7029392"
    ],
    "tgn:id":2480425,
    "tgn:name":"Lake Tiorati Brook",
    "tgn:placetype":[
        "aat:300008699"
    ]
},
  "bbox": [],
  "geometry": {"coordinates":[-74.0833,41.25],"type":"Point"}
}