{
  "id": 7352464,
  "type": "Feature",
  "properties": {
    "tgn:hierarchy":[
        "tgn:7352464",
        "tgn:7005581",
        "tgn:1000001",
        "tgn:7005560",
        "tgn:7029392"
    ],
    "tgn:id":7352464,
    "tgn:name":"Ataros",
    "tgn:placetype":[
        "aat:300007783"
    ]
},
  "bbox": [],
  "geometry": {"coordinates":[-107.466667,28.05],"type":"Point"}
}