{
  "id": 7133615,
  "type": "Feature",
  "properties": {
    "tgn:hierarchy":[
        "tgn:7133615",
        "tgn:1000003",
        "tgn:7003676",
        "tgn:7000084",
        "tgn:7029392"
    ],
    "tgn:id":7133615,
    "tgn:name":"Munderloh",
    "tgn:placetype":[
        "aat:300008347"
    ]
},
  "bbox": [],
  "geometry": {"coordinates":[8.366667,53.05],"type":"Point"}
}