{
  "id": 7458206,
  "type": "Feature",
  "properties": {
    "tgn:hierarchy":[
        "tgn:7458206",
        "tgn:7002445",
        "tgn:1000003",
        "tgn:7008166",
        "tgn:7008591",
        "tgn:7029392"
    ],
    "tgn:id":7458206,
    "tgn:name:en":"Malham Tarn",
    "tgn:placetype":[
        "aat:300008680"
    ]
},
  "bbox": [],
  "geometry": {"coordinates":[-2.166667,54.083333],"type":"Point"}
}