{
  "id": 7053946,
  "type": "Feature",
  "properties": {
    "tgn:hierarchy":[
        "tgn:7053946",
        "tgn:7003008",
        "tgn:1000003",
        "tgn:7002997",
        "tgn:1000080",
        "tgn:7029392"
    ],
    "tgn:id":7053946,
    "tgn:name":"Palla, Monte",
    "tgn:placetype":[
        "aat:300008795"
    ]
},
  "bbox": [],
  "geometry": {"coordinates":[11.783333,45.85],"type":"Point"}
}