{
  "id": 7458376,
  "type": "Feature",
  "properties": {
    "tgn:hierarchy":[
        "tgn:7458376",
        "tgn:7002444",
        "tgn:7008074",
        "tgn:1000003",
        "tgn:7008591",
        "tgn:7029392"
    ],
    "tgn:id":7458376,
    "tgn:name:en":"Mochrum Loch",
    "tgn:placetype":[
        "aat:300008680"
    ]
},
  "bbox": [],
  "geometry": {"coordinates":[-4.65,54.833333],"type":"Point"}
}