{
  "id": 1059067,
  "type": "Feature",
  "properties": {
    "tgn:hierarchy":[
        "tgn:1059067",
        "tgn:1000004",
        "tgn:1003314",
        "tgn:7018214",
        "tgn:7002435",
        "tgn:7029392"
    ],
    "tgn:id":1059067,
    "tgn:name":"Rybnoye",
    "tgn:placetype":[
        "aat:300008347"
    ]
},
  "bbox": [],
  "geometry": {"coordinates":[94.7667,55.7667],"type":"Point"}
}