{
  "id": 2398888,
  "type": "Feature",
  "properties": {
    "tgn:hierarchy":[
        "tgn:2398888",
        "tgn:1000001",
        "tgn:7012149",
        "tgn:1002368",
        "tgn:7007919",
        "tgn:7029392"
    ],
    "tgn:id":2398888,
    "tgn:name":"Hopewell",
    "tgn:placetype":[
        "aat:300008347"
    ]
},
  "bbox": [],
  "geometry": {"coordinates":[-77.7167,38.8667],"type":"Point"}
}