{
  "id": 2134375,
  "type": "Feature",
  "properties": {
    "tgn:hierarchy":[
        "tgn:2134375",
        "tgn:1000001",
        "tgn:7012149",
        "tgn:2001050",
        "tgn:7007521",
        "tgn:7029392"
    ],
    "tgn:id":2134375,
    "tgn:name":"Annexstad Lake",
    "tgn:placetype":[
        "aat:300008680"
    ]
},
  "bbox": [],
  "geometry": {"coordinates":[-94.0833,44.3833],"type":"Point"}
}