{
  "id": 2061306,
  "type": "Feature",
  "properties": {
    "tgn:hierarchy":[
        "tgn:2061306",
        "tgn:1000001",
        "tgn:7012149",
        "tgn:2001286",
        "tgn:7007524",
        "tgn:7029392"
    ],
    "tgn:id":2061306,
    "tgn:name":"Fisher River",
    "tgn:placetype":[
        "aat:300387016"
    ]
},
  "bbox": [],
  "geometry": {"coordinates":[-115.35,48.0167],"type":"Point"}
}