{
  "id": 1070307,
  "type": "Feature",
  "properties": {
    "tgn:hierarchy":[
        "tgn:1070307",
        "tgn:1000956",
        "tgn:1000004",
        "tgn:1000111",
        "tgn:7029392"
    ],
    "tgn:id":1070307,
    "tgn:name":"Majuqiao",
    "tgn:placetype":[
        "aat:300008347"
    ]
},
  "bbox": [],
  "geometry": {"coordinates":[116.5333,39.75],"type":"Point"}
}