{
  "id": 7043437,
  "type": "Feature",
  "properties": {
    "tgn:hierarchy":[
        "tgn:7043437",
        "tgn:7005023",
        "tgn:1000003",
        "tgn:7003237",
        "tgn:1000080",
        "tgn:7029392"
    ],
    "tgn:id":7043437,
    "tgn:name":"Presolana, Pizzo della",
    "tgn:placetype":[
        "aat:300008798"
    ]
},
  "bbox": [],
  "geometry": {"coordinates":[10.05,45.95],"type":"Point"}
}