{
  "id": 7590854,
  "type": "Feature",
  "properties": {
    "tgn:hierarchy":[
        "tgn:7590854",
        "tgn:1000004",
        "tgn:7000198",
        "tgn:7000799",
        "tgn:7029392"
    ],
    "tgn:id":7590854,
    "tgn:name:en":"Wardar N\u0101la",
    "tgn:placetype":[
        "aat:300008699"
    ]
},
  "bbox": [],
  "geometry": {"coordinates":[74.489651,33.900302],"type":"Point"}
}