{
  "id": 7128661,
  "type": "Feature",
  "properties": {
    "tgn:hierarchy":[
        "tgn:7128661",
        "tgn:7003669",
        "tgn:1000003",
        "tgn:7000084",
        "tgn:7029392"
    ],
    "tgn:id":7128661,
    "tgn:name":"Oberer Inselsee",
    "tgn:placetype":[
        "aat:300008680"
    ]
},
  "bbox": [],
  "geometry": {"coordinates":[10.283333,47.633333],"type":"Point"}
}