{
  "id": 2044424,
  "type": "Feature",
  "properties": {
    "tgn:hierarchy":[
        "tgn:2044424",
        "tgn:1000001",
        "tgn:2000923",
        "tgn:7012149",
        "tgn:7007515",
        "tgn:7029392"
    ],
    "tgn:id":2044424,
    "tgn:name":"Batchelders Crossing",
    "tgn:placetype":[
        "aat:300008347",
        "aat:300387210"
    ]
},
  "bbox": [],
  "geometry": {"coordinates":[-69.9333,44.1833],"type":"Point"}
}