{
  "id": 2474538,
  "type": "Feature",
  "properties": {
    "tgn:hierarchy":[
        "tgn:2474538",
        "tgn:1000001",
        "tgn:7012149",
        "tgn:2001454",
        "tgn:7007566",
        "tgn:7029392"
    ],
    "tgn:id":2474538,
    "tgn:name":"Lower Rock Tank",
    "tgn:placetype":[
        "aat:300006191"
    ]
},
  "bbox": [],
  "geometry": {"coordinates":[-105.9667,35.35],"type":"Point"}
}