<<<<<<< HEAD
{
  "id": 7056054,
  "type": "Feature",
  "properties": {
    "tgn:hierarchy":[
        "tgn:7056054",
        "tgn:7003166",
        "tgn:1000003",
        "tgn:7009760",
        "tgn:1000080",
        "tgn:7029392"
    ],
    "tgn:id":7056054,
    "tgn:name":"Micciano",
    "tgn:placetype":[
        "aat:300008347"
    ]
},
  "bbox": [],
  "geometry": {"coordinates":[10.783333,43.283333],"type":"Point"}
}
=======
{"geometry":{"type":"Point","coordinates":[10.783333,43.283333]},"type":"Feature","properties":{"hierarchy":["tgn:7056054","tgn:7003166","tgn:1000003","tgn:7009760","tgn:1000080","tgn:7029392"],"placetype":["aat:300008347"],"id":7056054,"name:xx":"Micciano"}}
>>>>>>> 03f74aca74312dbeaf24d7e61306dd6a786dc3d0
