{
  "id": 7056054,
  "type": "Feature",
  "properties": {
    "tgn:hierarchy":[
        "tgn:7056054",
        "tgn:7003166",
        "tgn:1000003",
        "tgn:7009760",
        "tgn:1000080",
        "tgn:7029392"
    ],
    "tgn:id":7056054,
    "tgn:name":"Micciano",
    "tgn:placetype":[
        "aat:300008347"
    ]
},
  "bbox": [],
  "geometry": {"coordinates":[10.783333,43.283333],"type":"Point"}
}