{
  "id": 7002275,
  "type": "Feature",
  "properties": {
    "tgn:hierarchy":[
        "tgn:7002275",
        "tgn:1000004",
        "tgn:7029392"
    ],
    "tgn:id":7002275,
    "tgn:name":"Nahang",
    "tgn:placetype":[
        "aat:300008707"
    ]
},
  "bbox": [],
  "geometry": {"coordinates":[62.75,25.9167],"type":"Point"}
}