{
  "id": 2566354,
  "type": "Feature",
  "properties": {
    "tgn:hierarchy":[
        "tgn:2566354",
        "tgn:1000001",
        "tgn:7012149",
        "tgn:2001453",
        "tgn:7007566",
        "tgn:7029392"
    ],
    "tgn:id":2566354,
    "tgn:name":"Palo Duroso",
    "tgn:placetype":[
        "aat:300008761"
    ]
},
  "bbox": [],
  "geometry": {"coordinates":[-105.3167,35.25],"type":"Point"}
}