<<<<<<< HEAD
{
  "id": 2253483,
  "type": "Feature",
  "properties": {
    "tgn:hierarchy":[
        "tgn:2253483",
        "tgn:1000001",
        "tgn:7012149",
        "tgn:7007255",
        "tgn:7029392"
    ],
    "tgn:id":2253483,
    "tgn:name":"Cook Creek",
    "tgn:placetype":[
        "aat:300008706"
    ]
},
  "bbox": [],
  "geometry": {"coordinates":[-88.1667,37.05],"type":"Point"}
}
=======
{"geometry":{"type":"Point","coordinates":[-88.166700,37.050000]},"type":"Feature","properties":{"hierarchy":["tgn:2253483","tgn:1000001","tgn:7012149","tgn:7007255","tgn:7029392"],"placetype":["aat:300008706"],"id":2253483,"name:xx":"Cook Creek"}}
>>>>>>> 03f74aca74312dbeaf24d7e61306dd6a786dc3d0
