{
  "id": 2253483,
  "type": "Feature",
  "properties": {
    "tgn:hierarchy":[
        "tgn:2253483",
        "tgn:1000001",
        "tgn:7012149",
        "tgn:7007255",
        "tgn:7029392"
    ],
    "tgn:id":2253483,
    "tgn:name":"Cook Creek",
    "tgn:placetype":[
        "aat:300008706"
    ]
},
  "bbox": [],
  "geometry": {"coordinates":[-88.1667,37.05],"type":"Point"}
}