{
  "id": 2677229,
  "type": "Feature",
  "properties": {
    "tgn:hierarchy":[
        "tgn:2677229",
        "tgn:7006450",
        "tgn:2000069",
        "tgn:1000001",
        "tgn:7012149",
        "tgn:7029392"
    ],
    "tgn:id":2677229,
    "tgn:name":"South Branch Warehouse Creek",
    "tgn:placetype":[
        "aat:300008706"
    ]
},
  "bbox": [],
  "geometry": {"coordinates":[-161.7167,59.8333],"type":"Point"}
}