<<<<<<< HEAD
{
  "id": 7055866,
  "type": "Feature",
  "properties": {
    "tgn:hierarchy":[
        "tgn:7055866",
        "tgn:7003135",
        "tgn:1000003",
        "tgn:7003080",
        "tgn:1000080",
        "tgn:7029392"
    ],
    "tgn:id":7055866,
    "tgn:name":"Piumarola",
    "tgn:placetype":[
        "aat:300008347"
    ]
},
  "bbox": [],
  "geometry": {"coordinates":[13.766667,41.466667],"type":"Point"}
}
=======
{"geometry":{"type":"Point","coordinates":[13.766667,41.466667]},"type":"Feature","properties":{"hierarchy":["tgn:7055866","tgn:7003135","tgn:1000003","tgn:7003080","tgn:1000080","tgn:7029392"],"placetype":["aat:300008347"],"id":7055866,"name:xx":"Piumarola"}}
>>>>>>> 03f74aca74312dbeaf24d7e61306dd6a786dc3d0
