{
  "id": 7309293,
  "type": "Feature",
  "properties": {
    "tgn:hierarchy":[
        "tgn:7309293",
        "tgn:1001699",
        "tgn:1000049",
        "tgn:1000002",
        "tgn:7029392"
    ],
    "tgn:id":7309293,
    "tgn:name":"Lumaco, Estero",
    "tgn:placetype":[
        "aat:300008699"
    ]
},
  "bbox": [],
  "geometry": {"coordinates":[-73.283333,-39.966667],"type":"Point"}
}