{
  "id": 2677713,
  "type": "Feature",
  "properties": {
    "tgn:hierarchy":[
        "tgn:2677713",
        "tgn:1000001",
        "tgn:7012149",
        "tgn:2001283",
        "tgn:7007524",
        "tgn:7029392"
    ],
    "tgn:id":2677713,
    "tgn:name":"South Crow Creek",
    "tgn:placetype":[
        "aat:300008706"
    ]
},
  "bbox": [],
  "geometry": {"coordinates":[-113.9167,47.5333],"type":"Point"}
}