{
  "id": 7473323,
  "type": "Feature",
  "properties": {
    "tgn:hierarchy":[
        "tgn:7473323",
        "tgn:1000004",
        "tgn:7004300",
        "tgn:1000141",
        "tgn:7029392"
    ],
    "tgn:id":7473323,
    "tgn:name":"Tongpan Yu",
    "tgn:placetype":[
        "aat:300008791"
    ]
},
  "bbox": [],
  "geometry": {"coordinates":[119.518635,23.510595],"type":"Point"}
}