<<<<<<< HEAD
{
  "id": 7473323,
  "type": "Feature",
  "properties": {
    "tgn:hierarchy":[
        "tgn:7473323",
        "tgn:1000004",
        "tgn:7004300",
        "tgn:1000141",
        "tgn:7029392"
    ],
    "tgn:id":7473323,
    "tgn:name":"Tongpan Yu",
    "tgn:placetype":[
        "aat:300008791"
    ]
},
  "bbox": [],
  "geometry": {"coordinates":[119.518635,23.510595],"type":"Point"}
}
=======
{"geometry":{"type":"Point","coordinates":[119.518635,23.510595]},"type":"Feature","properties":{"hierarchy":["tgn:7473323","tgn:1000004","tgn:7004300","tgn:1000141","tgn:7029392"],"placetype":["aat:300008791"],"id":7473323,"name:xx":"Tongpan Yu"}}
>>>>>>> 03f74aca74312dbeaf24d7e61306dd6a786dc3d0
