{
  "id": 2706160,
  "type": "Feature",
  "properties": {
    "tgn:hierarchy":[
        "tgn:2706160",
        "tgn:1000001",
        "tgn:7012149",
        "tgn:2001917",
        "tgn:7007825",
        "tgn:7029392"
    ],
    "tgn:id":2706160,
    "tgn:name":"Swamp Bank Mines",
    "tgn:placetype":[
        "aat:300000390"
    ]
},
  "bbox": [],
  "geometry": {"coordinates":[-87.9833,36.3667],"type":"Point"}
}