{
  "id": 2675198,
  "type": "Feature",
  "properties": {
    "tgn:hierarchy":[
        "tgn:2675198",
        "tgn:7006450",
        "tgn:1000001",
        "tgn:2124089",
        "tgn:7012149",
        "tgn:7029392"
    ],
    "tgn:id":2675198,
    "tgn:name":"Sol Thumb",
    "tgn:placetype":[
        "aat:300266640"
    ]
},
  "bbox": [],
  "geometry": {"coordinates":[-134.2667,58.3833],"type":"Point"}
}