<<<<<<< HEAD
{
  "id": 7248455,
  "type": "Feature",
  "properties": {
    "tgn:hierarchy":[
        "tgn:7248455",
        "tgn:7018239",
        "tgn:1000003",
        "tgn:1000063",
        "tgn:7018236",
        "tgn:7029392"
    ],
    "tgn:id":7248455,
    "tgn:name":"Bierbeek",
    "tgn:placetype":[
        "aat:300008347"
    ]
},
  "bbox": [],
  "geometry": {"coordinates":[4.759493,50.828755],"type":"Point"}
}
=======
{"geometry":{"type":"Point","coordinates":[4.759493,50.828755]},"type":"Feature","properties":{"hierarchy":["tgn:7248455","tgn:7018239","tgn:1000003","tgn:1000063","tgn:7018236","tgn:7029392"],"placetype":["aat:300008347"],"id":7248455,"name:xx":"Bierbeek"}}
>>>>>>> 03f74aca74312dbeaf24d7e61306dd6a786dc3d0
