{
  "id": 2577610,
  "type": "Feature",
  "properties": {
    "tgn:hierarchy":[
        "tgn:2577610",
        "tgn:7020393",
        "tgn:1000001",
        "tgn:7012149",
        "tgn:7007705",
        "tgn:7029392"
    ],
    "tgn:id":2577610,
    "tgn:name":"Peterson Lake",
    "tgn:placetype":[
        "aat:300008680"
    ]
},
  "bbox": [],
  "geometry": {"coordinates":[-100.1833,48.95],"type":"Point"}
}