{
  "id": 7422862,
  "type": "Feature",
  "properties": {
    "tgn:hierarchy":[
        "tgn:7422862",
        "tgn:1000001",
        "tgn:7005601",
        "tgn:7005560",
        "tgn:7029392"
    ],
    "tgn:id":7422862,
    "tgn:name":"San Antonio de las Huertas",
    "tgn:placetype":[
        "aat:300008347"
    ]
},
  "bbox": [],
  "geometry": {"coordinates":[-103.416667,23.166667],"type":"Point"}
}