{
  "id": 2717301,
  "type": "Feature",
  "properties": {
    "tgn:hierarchy":[
        "tgn:2717301",
        "tgn:1000001",
        "tgn:1002479",
        "tgn:7012149",
        "tgn:7007240",
        "tgn:7029392"
    ],
    "tgn:id":2717301,
    "tgn:name":"Thirteenmile Run",
    "tgn:placetype":[
        "aat:300008699"
    ]
},
  "bbox": [],
  "geometry": {"coordinates":[-82.4333,28.1167],"type":"Point"}
}