{
  "id": 1104525,
  "type": "Feature",
  "properties": {
    "tgn:hierarchy":[
        "tgn:1104525",
        "tgn:7006450",
        "tgn:1000001",
        "tgn:7012149",
        "tgn:2000085",
        "tgn:7029392"
    ],
    "tgn:id":1104525,
    "tgn:name":"Eldridge, Mount",
    "tgn:placetype":[
        "aat:300008795"
    ]
},
  "bbox": [],
  "geometry": {"coordinates":[-141.7833,64.75],"type":"Point"}
}