{
  "id": 2591990,
  "type": "Feature",
  "properties": {
    "tgn:hierarchy":[
        "tgn:2591990",
        "tgn:1000001",
        "tgn:7012149",
        "tgn:2001516",
        "tgn:7007709",
        "tgn:7029392"
    ],
    "tgn:id":2591990,
    "tgn:name":"Ponder Creek",
    "tgn:placetype":[
        "aat:300008706"
    ]
},
  "bbox": [],
  "geometry": {"coordinates":[-82.4333,35.8833],"type":"Point"}
}