{
  "id": 2548865,
  "type": "Feature",
  "properties": {
    "tgn:hierarchy":[
        "tgn:2548865",
        "tgn:1000001",
        "tgn:7012149",
        "tgn:1002440",
        "tgn:7007568",
        "tgn:7029392"
    ],
    "tgn:id":2548865,
    "tgn:name":"North Point",
    "tgn:placetype":[
        "aat:300008850"
    ]
},
  "bbox": [],
  "geometry": {"coordinates":[-74.6333,43.8667],"type":"Point"}
}