{
  "id": 7324074,
  "type": "Feature",
  "properties": {
    "tgn:hierarchy":[
        "tgn:7324074",
        "tgn:7002829",
        "tgn:1000003",
        "tgn:7002786",
        "tgn:1000095",
        "tgn:7029392"
    ],
    "tgn:id":7324074,
    "tgn:name":"San Robred\u00edn",
    "tgn:placetype":[
        "aat:300008347"
    ]
},
  "bbox": [],
  "geometry": {"coordinates":[-6.933333,42.783333],"type":"Point"}
}