{
  "id": 7281388,
  "type": "Feature",
  "properties": {
    "tgn:hierarchy":[
        "tgn:7281388",
        "tgn:1001768",
        "tgn:1000049",
        "tgn:1000002",
        "tgn:7029392"
    ],
    "tgn:id":7281388,
    "tgn:name":"S\u00e1ndalo, Quebrada",
    "tgn:placetype":[
        "aat:300008699"
    ]
},
  "bbox": [],
  "geometry": {"coordinates":[-80.733333,-33.733333],"type":"Point"}
}