{
  "id": 7584120,
  "type": "Feature",
  "properties": {
    "tgn:hierarchy":[
        "tgn:7584120",
        "tgn:1000004",
        "tgn:7000198",
        "tgn:1001894",
        "tgn:7029392"
    ],
    "tgn:id":7584120,
    "tgn:name:en":"Baidpur",
    "tgn:placetype":[
        "aat:300008347"
    ]
},
  "bbox": [],
  "geometry": {"coordinates":[78.946505,24.924428],"type":"Point"}
}