{
  "id": 7528088,
  "type": "Feature",
  "properties": {
    "tgn:hierarchy":[
        "tgn:7528088",
        "tgn:7001242",
        "tgn:7016833",
        "tgn:7001334",
        "tgn:7029392"
    ],
    "tgn:id":7528088,
    "tgn:name:en":"Sinn al J\u012br, Jabal",
    "tgn:placetype":[
        "aat:300008795"
    ]
},
  "bbox": [],
  "geometry": {"coordinates":[32.526551,26.019988],"type":"Point"}
}