{
  "id": 2312660,
  "type": "Feature",
  "properties": {
    "tgn:hierarchy":[
        "tgn:2312660",
        "tgn:7006450",
        "tgn:1000001",
        "tgn:7012149",
        "tgn:2000082",
        "tgn:7029392"
    ],
    "tgn:id":2312660,
    "tgn:name":"El Capitan Lake",
    "tgn:placetype":[
        "aat:300008680"
    ]
},
  "bbox": [],
  "geometry": {"coordinates":[-133.3667,56.1667],"type":"Point"}
}