{
  "id": 2215721,
  "type": "Feature",
  "properties": {
    "tgn:hierarchy":[
        "tgn:2215721",
        "tgn:1000001",
        "tgn:2001839",
        "tgn:7012149",
        "tgn:7007825",
        "tgn:7029392"
    ],
    "tgn:id":2215721,
    "tgn:name":"Camden Bay Subdivision",
    "tgn:placetype":[
        "aat:300008347"
    ]
},
  "bbox": [],
  "geometry": {"coordinates":[-88.0333,35.9667],"type":"Point"}
}