{
  "id": 2600285,
  "type": "Feature",
  "properties": {
    "tgn:hierarchy":[
        "tgn:2600285",
        "tgn:1000001",
        "tgn:7014423",
        "tgn:7012149",
        "tgn:7007517",
        "tgn:7029392"
    ],
    "tgn:id":2600285,
    "tgn:name":"Pudding Hill",
    "tgn:placetype":[
        "aat:300008798"
    ]
},
  "bbox": [],
  "geometry": {"coordinates":[-70.7167,42.0833],"type":"Point"}
}