{
  "id": 2292654,
  "type": "Feature",
  "properties": {
    "tgn:hierarchy":[
        "tgn:2292654",
        "tgn:1000001",
        "tgn:7012149",
        "tgn:2124023",
        "tgn:7007248",
        "tgn:7029392"
    ],
    "tgn:id":2292654,
    "tgn:name":"Doreen Lake",
    "tgn:placetype":[
        "aat:300006191"
    ]
},
  "bbox": [],
  "geometry": {"coordinates":[-84.2667,33.85],"type":"Point"}
}