{
  "id": 7432462,
  "type": "Feature",
  "properties": {
    "tgn:hierarchy":[
        "tgn:7432462",
        "tgn:1000001",
        "tgn:7005595",
        "tgn:7005560",
        "tgn:7029392"
    ],
    "tgn:id":7432462,
    "tgn:name":"Zacatosa",
    "tgn:placetype":[
        "aat:300387007"
    ]
},
  "bbox": [],
  "geometry": {"coordinates":[-106.35,23.25],"type":"Point"}
}