{
  "id": 7184448,
  "type": "Feature",
  "properties": {
    "tgn:hierarchy":[
        "tgn:7184448",
        "tgn:7003669",
        "tgn:1000003",
        "tgn:7000084",
        "tgn:7029392"
    ],
    "tgn:id":7184448,
    "tgn:name":"G\u00f6\u00dfweinstein",
    "tgn:placetype":[
        "aat:300008347"
    ]
},
  "bbox": [],
  "geometry": {"coordinates":[11.333333,49.766667],"type":"Point"}
}