{
  "id": 2594092,
  "type": "Feature",
  "properties": {
    "tgn:hierarchy":[
        "tgn:2594092",
        "tgn:1000001",
        "tgn:2001260",
        "tgn:7012149",
        "tgn:7007524",
        "tgn:7029392"
    ],
    "tgn:id":2594092,
    "tgn:name":"Portal Gulch",
    "tgn:placetype":[
        "aat:300008761"
    ]
},
  "bbox": [],
  "geometry": {"coordinates":[-113.7333,45.55],"type":"Point"}
}