{
  "id": 7255875,
  "type": "Feature",
  "properties": {
    "tgn:hierarchy":[
        "tgn:7255875",
        "tgn:7003465",
        "tgn:1000003",
        "tgn:1000063",
        "tgn:4012014",
        "tgn:7029392"
    ],
    "tgn:id":7255875,
    "tgn:name":"Saint-Martin, L'Eau",
    "tgn:placetype":[
        "aat:300008699"
    ]
},
  "bbox": [],
  "geometry": {"coordinates":[5.916667,50.25],"type":"Point"}
}