{
  "id": 7067587,
  "type": "Feature",
  "properties": {
    "tgn:hierarchy":[
        "tgn:7067587",
        "tgn:7003669",
        "tgn:1000003",
        "tgn:7000084",
        "tgn:7029392"
    ],
    "tgn:id":7067587,
    "tgn:name":"Traunstorf",
    "tgn:placetype":[
        "aat:300008347"
    ]
},
  "bbox": [],
  "geometry": {"coordinates":[12.616667,47.866667],"type":"Point"}
}