{
  "id": 7267053,
  "type": "Feature",
  "properties": {
    "tgn:hierarchy":[
        "tgn:7267053",
        "tgn:1000003",
        "tgn:7006951",
        "tgn:7016845",
        "tgn:7029392"
    ],
    "tgn:id":7267053,
    "tgn:name:nl":"Lange Sloot",
    "tgn:placetype":[
        "aat:300006075"
    ]
},
  "bbox": [],
  "geometry": {"coordinates":[4.816667,52.566667],"type":"Point"}
}