{
  "id": 7146990,
  "type": "Feature",
  "properties": {
    "tgn:hierarchy":[
        "tgn:7146990",
        "tgn:1000003",
        "tgn:7003676",
        "tgn:7000084",
        "tgn:7029392"
    ],
    "tgn:id":7146990,
    "tgn:name":"Klein Otze",
    "tgn:placetype":[
        "aat:300008347"
    ]
},
  "bbox": [],
  "geometry": {"coordinates":[10.016667,52.483333],"type":"Point"}
}