{
  "id": 1115637,
  "type": "Feature",
  "properties": {
    "tgn:hierarchy":[
        "tgn:1115637",
        "tgn:1000001",
        "tgn:7012149",
        "tgn:1002942",
        "tgn:7007920",
        "tgn:7029392"
    ],
    "tgn:id":1115637,
    "tgn:name":"Black Lake",
    "tgn:placetype":[
        "aat:300008680"
    ]
},
  "bbox": [],
  "geometry": {"coordinates":[-122.9667,46.9833],"type":"Point"}
}