{
  "id": 7005285,
  "type": "Feature",
  "properties": {
    "tgn:hierarchy":[
        "tgn:7005285",
        "tgn:1000003",
        "tgn:7003676",
        "tgn:7000084",
        "tgn:7029392"
    ],
    "tgn:id":7005285,
    "tgn:name":"Hatte",
    "tgn:placetype":[
        "aat:300008347",
        "aat:300008375",
        "aat:300387006"
    ]
},
  "bbox": [],
  "geometry": {"coordinates":[8.3667,53.0333],"type":"Point"}
}