{
  "id": 7092370,
  "type": "Feature",
  "properties": {
    "tgn:hierarchy":[
        "tgn:7092370",
        "tgn:7003669",
        "tgn:1000003",
        "tgn:7000084",
        "tgn:7029392"
    ],
    "tgn:id":7092370,
    "tgn:name":"Urfahrn",
    "tgn:placetype":[
        "aat:300000206"
    ]
},
  "bbox": [],
  "geometry": {"coordinates":[12.35,48.166667],"type":"Point"}
}