<<<<<<< HEAD
{
  "id": 7118751,
  "type": "Feature",
  "properties": {
    "tgn:hierarchy":[
        "tgn:7118751",
        "tgn:7003669",
        "tgn:1000003",
        "tgn:7000084",
        "tgn:7029392"
    ],
    "tgn:id":7118751,
    "tgn:name":"Probstried",
    "tgn:placetype":[
        "aat:300008347"
    ]
},
  "bbox": [],
  "geometry": {"coordinates":[10.333333,47.816667],"type":"Point"}
}
=======
{"geometry":{"type":"Point","coordinates":[10.333333,47.816667]},"type":"Feature","properties":{"hierarchy":["tgn:7118751","tgn:7003669","tgn:1000003","tgn:7000084","tgn:7029392"],"placetype":["aat:300008347"],"id":7118751,"name:xx":"Probstried"}}
>>>>>>> 03f74aca74312dbeaf24d7e61306dd6a786dc3d0
