{
  "id": 7385738,
  "type": "Feature",
  "properties": {
    "tgn:hierarchy":[
        "tgn:7385738",
        "tgn:1000001",
        "tgn:7005594",
        "tgn:7005560",
        "tgn:7029392"
    ],
    "tgn:id":7385738,
    "tgn:name":"Presa de Guadalupe",
    "tgn:placetype":[
        "aat:300008347"
    ]
},
  "bbox": [],
  "geometry": {"coordinates":[-100.15,22.85],"type":"Point"}
}