{
  "id": 2266762,
  "type": "Feature",
  "properties": {
    "tgn:hierarchy":[
        "tgn:2266762",
        "tgn:1000001",
        "tgn:7012149",
        "tgn:2002110",
        "tgn:7007827",
        "tgn:7029392"
    ],
    "tgn:id":2266762,
    "tgn:name":"Crescent Junction",
    "tgn:placetype":[
        "aat:300008347"
    ]
},
  "bbox": [],
  "geometry": {"coordinates":[-109.8167,38.9333],"type":"Point"}
}