{
  "id": 7561724,
  "type": "Feature",
  "properties": {
    "tgn:hierarchy":[
        "tgn:7561724",
        "tgn:1000004",
        "tgn:7000198",
        "tgn:7016722",
        "tgn:7029392"
    ],
    "tgn:id":7561724,
    "tgn:name:en":"Al\u0101pur",
    "tgn:placetype":[
        "aat:300008347"
    ]
},
  "bbox": [],
  "geometry": {"coordinates":[79.246446,27.913562],"type":"Point"}
}