{
  "id": 7425321,
  "type": "Feature",
  "properties": {
    "tgn:hierarchy":[
        "tgn:7425321",
        "tgn:7005581",
        "tgn:1000001",
        "tgn:7005560",
        "tgn:7029392"
    ],
    "tgn:id":7425321,
    "tgn:name":"Estaci\u00f3n Adela",
    "tgn:placetype":[
        "aat:300007783"
    ]
},
  "bbox": [],
  "geometry": {"coordinates":[-105.383333,27.033333],"type":"Point"}
}