{
  "id": 7181624,
  "type": "Feature",
  "properties": {
    "tgn:hierarchy":[
        "tgn:7181624",
        "tgn:7003669",
        "tgn:1000003",
        "tgn:7000084",
        "tgn:7029392"
    ],
    "tgn:id":7181624,
    "tgn:name":"Geisfelder Bach",
    "tgn:placetype":[
        "aat:300008699"
    ]
},
  "bbox": [],
  "geometry": {"coordinates":[10.966667,49.85],"type":"Point"}
}