{
  "id": 7053314,
  "type": "Feature",
  "properties": {
    "tgn:hierarchy":[
        "tgn:7053314",
        "tgn:7003170",
        "tgn:1000003",
        "tgn:7003125",
        "tgn:1000080",
        "tgn:7029392"
    ],
    "tgn:id":7053314,
    "tgn:name":"Menestrello",
    "tgn:placetype":[
        "aat:300008347"
    ]
},
  "bbox": [],
  "geometry": {"coordinates":[12.316667,43.183333],"type":"Point"}
}