{
  "id": 7586614,
  "type": "Feature",
  "properties": {
    "tgn:hierarchy":[
        "tgn:7586614",
        "tgn:1000004",
        "tgn:7000198",
        "tgn:7000799",
        "tgn:7029392"
    ],
    "tgn:id":7586614,
    "tgn:name:en":"Mukarpathri",
    "tgn:placetype":[
        "aat:300387200"
    ]
},
  "bbox": [],
  "geometry": {"coordinates":[74.841667,34.441667],"type":"Point"}
}