{
  "id": 7567600,
  "type": "Feature",
  "properties": {
    "tgn:hierarchy":[
        "tgn:7567600",
        "tgn:1000004",
        "tgn:7000198",
        "tgn:1001996",
        "tgn:7029392"
    ],
    "tgn:id":7567600,
    "tgn:name:en":"Nehra",
    "tgn:placetype":[
        "aat:300008347"
    ]
},
  "bbox": [],
  "geometry": {"coordinates":[77.020833,31.2425],"type":"Point"}
}