<<<<<<< HEAD
{
  "id": 7483217,
  "type": "Feature",
  "properties": {
    "tgn:hierarchy":[
        "tgn:7483217",
        "tgn:1000004",
        "tgn:1000454",
        "tgn:1000141",
        "tgn:7029392"
    ],
    "tgn:id":7483217,
    "tgn:name":"Nanshikeng",
    "tgn:placetype":[
        "aat:300008347"
    ]
},
  "bbox": [],
  "geometry": {"coordinates":[121.801389,24.921389],"type":"Point"}
}
=======
{"geometry":{"type":"Point","coordinates":[121.801389,24.921389]},"type":"Feature","properties":{"hierarchy":["tgn:7483217","tgn:1000004","tgn:1000454","tgn:1000141","tgn:7029392"],"placetype":["aat:300008347"],"id":7483217,"name:xx":"Nanshikeng"}}
>>>>>>> 03f74aca74312dbeaf24d7e61306dd6a786dc3d0
