{
  "id": 2650249,
  "type": "Feature",
  "properties": {
    "tgn:hierarchy":[
        "tgn:2650249",
        "tgn:1000001",
        "tgn:7012149",
        "tgn:1002924",
        "tgn:7007568",
        "tgn:7029392"
    ],
    "tgn:id":2650249,
    "tgn:name":"Seal Rocks",
    "tgn:placetype":[
        "aat:300132348"
    ]
},
  "bbox": [],
  "geometry": {"coordinates":[-71.9167,41.2833],"type":"Point"}
}