<<<<<<< HEAD
{
  "id": 7487462,
  "type": "Feature",
  "properties": {
    "tgn:hierarchy":[
        "tgn:7487462",
        "tgn:1000004",
        "tgn:1000454",
        "tgn:1000141",
        "tgn:7029392"
    ],
    "tgn:id":7487462,
    "tgn:name":"Keng Shan",
    "tgn:placetype":[
        "aat:300008795"
    ]
},
  "bbox": [],
  "geometry": {"coordinates":[121.833333,25.0],"type":"Point"}
}
=======
{"geometry":{"type":"Point","coordinates":[121.833333,25.000000]},"type":"Feature","properties":{"hierarchy":["tgn:7487462","tgn:1000004","tgn:1000454","tgn:1000141","tgn:7029392"],"placetype":["aat:300008795"],"id":7487462,"name:xx":"Keng Shan"}}
>>>>>>> 03f74aca74312dbeaf24d7e61306dd6a786dc3d0
