{
  "id": 2002243,
  "type": "Feature",
  "properties": {
    "tgn:hierarchy":[
        "tgn:2002243",
        "tgn:1000001",
        "tgn:7012149",
        "tgn:7007920",
        "tgn:7029392"
    ],
    "tgn:id":2002243,
    "tgn:name":"Ferry",
    "tgn:placetype":[
        "aat:300387145",
        "aat:300000771"
    ]
},
  "bbox": [],
  "geometry": {"coordinates":[-118.5333,48.4667],"type":"Point"}
}