{
  "id": 2678947,
  "type": "Feature",
  "properties": {
    "tgn:hierarchy":[
        "tgn:2678947",
        "tgn:1000001",
        "tgn:7012149",
        "tgn:7007827",
        "tgn:7029392"
    ],
    "tgn:id":2678947,
    "tgn:name":"South Fork Happy Canyon",
    "tgn:placetype":[
        "aat:300008761"
    ]
},
  "bbox": [],
  "geometry": {"coordinates":[-110.1333,38.0833],"type":"Point"}
}