<<<<<<< HEAD
{
  "id": 2151328,
  "type": "Feature",
  "properties": {
    "tgn:hierarchy":[
        "tgn:2151328",
        "tgn:7002659",
        "tgn:1000001",
        "tgn:7012149",
        "tgn:2000051",
        "tgn:7029392"
    ],
    "tgn:id":2151328,
    "tgn:name":"Bates Hollow",
    "tgn:placetype":[
        "aat:300008761"
    ]
},
  "bbox": [],
  "geometry": {"coordinates":[-86.7167,34.3167],"type":"Point"}
}
=======
{"geometry":{"type":"Point","coordinates":[-86.716700,34.316700]},"type":"Feature","properties":{"hierarchy":["tgn:2151328","tgn:7002659","tgn:1000001","tgn:7012149","tgn:2000051","tgn:7029392"],"placetype":["aat:300008761"],"id":2151328,"name:xx":"Bates Hollow"}}
>>>>>>> 03f74aca74312dbeaf24d7e61306dd6a786dc3d0
