{
  "id": 1063323,
  "type": "Feature",
  "properties": {
    "tgn:hierarchy":[
        "tgn:1063323",
        "tgn:1000003",
        "tgn:1000405",
        "tgn:1000097",
        "tgn:7029392"
    ],
    "tgn:id":1063323,
    "tgn:name":"Ljungby",
    "tgn:placetype":[
        "aat:300008347"
    ]
},
  "bbox": [],
  "geometry": {"coordinates":[13.9167,56.8167],"type":"Point"}
}