<<<<<<< HEAD
{
  "id": 2337654,
  "type": "Feature",
  "properties": {
    "tgn:hierarchy":[
        "tgn:2337654",
        "tgn:2000454",
        "tgn:1000001",
        "tgn:7012149",
        "tgn:7007250",
        "tgn:7029392"
    ],
    "tgn:id":2337654,
    "tgn:name":"Fox Canyon",
    "tgn:placetype":[
        "aat:300008761"
    ]
},
  "bbox": [],
  "geometry": {"coordinates":[-111.9167,42.5],"type":"Point"}
}
=======
{"geometry":{"type":"Point","coordinates":[-111.916700,42.500000]},"type":"Feature","properties":{"hierarchy":["tgn:2337654","tgn:2000454","tgn:1000001","tgn:7012149","tgn:7007250","tgn:7029392"],"placetype":["aat:300008761"],"id":2337654,"name:xx":"Fox Canyon"}}
>>>>>>> 03f74aca74312dbeaf24d7e61306dd6a786dc3d0
