{
  "id": 2608543,
  "type": "Feature",
  "properties": {
    "tgn:hierarchy":[
        "tgn:2608543",
        "tgn:2002143",
        "tgn:1000001",
        "tgn:7012149",
        "tgn:7007919",
        "tgn:7029392"
    ],
    "tgn:id":2608543,
    "tgn:name":"Rattlesnake Hollow",
    "tgn:placetype":[
        "aat:300008761"
    ]
},
  "bbox": [],
  "geometry": {"coordinates":[-79.9167,38.1333],"type":"Point"}
}