{
  "id": 7203862,
  "type": "Feature",
  "properties": {
    "tgn:hierarchy":[
        "tgn:7203862",
        "tgn:1000003",
        "tgn:7003678",
        "tgn:7000084",
        "tgn:7029392"
    ],
    "tgn:id":7203862,
    "tgn:name":"Brauns-Berg",
    "tgn:placetype":[
        "aat:300008777"
    ]
},
  "bbox": [],
  "geometry": {"coordinates":[9.333333,50.916667],"type":"Point"}
}