{
  "id": 1104512,
  "type": "Feature",
  "properties": {
    "tgn:hierarchy":[
        "tgn:1104512",
        "tgn:7016644",
        "tgn:1000001",
        "tgn:7005560",
        "tgn:7029392"
    ],
    "tgn:id":1104512,
    "tgn:name":"El Centinela, Cerro",
    "tgn:placetype":[
        "aat:300008777",
        "aat:300008795"
    ]
},
  "bbox": [],
  "geometry": {"coordinates":[-104.283333,19.216667],"type":"Point"}
}