{
  "id": 1022494,
  "type": "Feature",
  "properties": {
    "tgn:hierarchy":[
        "tgn:1022494",
        "tgn:7006246",
        "tgn:1000047",
        "tgn:7002455",
        "tgn:1000002",
        "tgn:7029392"
    ],
    "tgn:id":1022494,
    "tgn:name":"Pirapemas",
    "tgn:placetype":[
        "aat:300008347"
    ]
},
  "bbox": [],
  "geometry": {"coordinates":[-44.25,-3.7667],"type":"Point"}
}