{
  "id": 2498571,
  "type": "Feature",
  "properties": {
    "tgn:hierarchy":[
        "tgn:2498571",
        "tgn:7002659",
        "tgn:1000001",
        "tgn:2000004",
        "tgn:7012149",
        "tgn:7029392"
    ],
    "tgn:id":2498571,
    "tgn:name":"McAnnally Cove",
    "tgn:placetype":[
        "aat:300008761"
    ]
},
  "bbox": [],
  "geometry": {"coordinates":[-86.7167,33.95],"type":"Point"}
}