{
  "id": 7169404,
  "type": "Feature",
  "properties": {
    "tgn:hierarchy":[
        "tgn:7169404",
        "tgn:7003692",
        "tgn:1000003",
        "tgn:7000084",
        "tgn:7029392"
    ],
    "tgn:id":7169404,
    "tgn:name":"Hermannsberg",
    "tgn:placetype":[
        "aat:300008777"
    ]
},
  "bbox": [],
  "geometry": {"coordinates":[9.233333,49.416667],"type":"Point"}
}