{
  "id": 7560802,
  "type": "Feature",
  "properties": {
    "tgn:hierarchy":[
        "tgn:7560802",
        "tgn:1000004",
        "tgn:7000198",
        "tgn:7016722",
        "tgn:7029392"
    ],
    "tgn:id":7560802,
    "tgn:name:en":"Karnauli",
    "tgn:placetype":[
        "aat:300008347"
    ]
},
  "bbox": [],
  "geometry": {"coordinates":[79.486851,27.196422],"type":"Point"}
}