{
  "id": 2167872,
  "type": "Feature",
  "properties": {
    "tgn:hierarchy":[
        "tgn:2167872",
        "tgn:1000001",
        "tgn:2002368",
        "tgn:7012149",
        "tgn:7007923",
        "tgn:7029392"
    ],
    "tgn:id":2167872,
    "tgn:name":"Big Ditch",
    "tgn:placetype":[
        "aat:300008699"
    ]
},
  "bbox": [],
  "geometry": {"coordinates":[-106.4667,41.8833],"type":"Point"}
}