{
  "id": 7075382,
  "type": "Feature",
  "properties": {
    "tgn:hierarchy":[
        "tgn:7075382",
        "tgn:1000003",
        "tgn:7003677",
        "tgn:7000084",
        "tgn:7029392"
    ],
    "tgn:id":7075382,
    "tgn:name":"Laar",
    "tgn:placetype":[
        "aat:300008347"
    ]
},
  "bbox": [],
  "geometry": {"coordinates":[8.583333,52.083333],"type":"Point"}
}