{
  "id": 2208164,
  "type": "Feature",
  "properties": {
    "tgn:hierarchy":[
        "tgn:2208164",
        "tgn:1000001",
        "tgn:7012149",
        "tgn:2001117",
        "tgn:7007522",
        "tgn:7029392"
    ],
    "tgn:id":2208164,
    "tgn:name":"Burl Branch",
    "tgn:placetype":[
        "aat:300008699"
    ]
},
  "bbox": [],
  "geometry": {"coordinates":[-90.75,31.6667],"type":"Point"}
}