<<<<<<< HEAD
{
  "id": 2408585,
  "type": "Feature",
  "properties": {
    "tgn:hierarchy":[
        "tgn:2408585",
        "tgn:1000001",
        "tgn:2001841",
        "tgn:7012149",
        "tgn:7007825",
        "tgn:7029392"
    ],
    "tgn:id":2408585,
    "tgn:name":"Hutton Ridge",
    "tgn:placetype":[
        "aat:300266640"
    ]
},
  "bbox": [],
  "geometry": {"coordinates":[-84.0667,35.6333],"type":"Point"}
}
=======
{"geometry":{"type":"Point","coordinates":[-84.066700,35.633300]},"type":"Feature","properties":{"hierarchy":["tgn:2408585","tgn:1000001","tgn:2001841","tgn:7012149","tgn:7007825","tgn:7029392"],"placetype":["aat:300266640"],"id":2408585,"name:xx":"Hutton Ridge"}}
>>>>>>> 03f74aca74312dbeaf24d7e61306dd6a786dc3d0
