{
  "id": 2408585,
  "type": "Feature",
  "properties": {
    "tgn:hierarchy":[
        "tgn:2408585",
        "tgn:1000001",
        "tgn:2001841",
        "tgn:7012149",
        "tgn:7007825",
        "tgn:7029392"
    ],
    "tgn:id":2408585,
    "tgn:name":"Hutton Ridge",
    "tgn:placetype":[
        "aat:300266640"
    ]
},
  "bbox": [],
  "geometry": {"coordinates":[-84.0667,35.6333],"type":"Point"}
}