{
  "id": 7146311,
  "type": "Feature",
  "properties": {
    "tgn:hierarchy":[
        "tgn:7146311",
        "tgn:1000003",
        "tgn:7000094",
        "tgn:7000084",
        "tgn:7029392"
    ],
    "tgn:id":7146311,
    "tgn:name":"Klein Sch\u00f6nwalde",
    "tgn:placetype":[
        "aat:300008347"
    ]
},
  "bbox": [],
  "geometry": {"coordinates":[13.416667,54.066667],"type":"Point"}
}