{
  "id": 7235035,
  "type": "Feature",
  "properties": {
    "tgn:hierarchy":[
        "tgn:7235035",
        "tgn:7002739",
        "tgn:7017076",
        "tgn:1000003",
        "tgn:1000074",
        "tgn:7029392"
    ],
    "tgn:id":7235035,
    "tgn:name":"Fon\u00edskos",
    "tgn:placetype":[
        "aat:300008795"
    ]
},
  "bbox": [],
  "geometry": {"coordinates":[22.966667,37.616667],"type":"Point"}
}