{
  "id": 2493599,
  "type": "Feature",
  "properties": {
    "tgn:hierarchy":[
        "tgn:2493599",
        "tgn:1000001",
        "tgn:7012149",
        "tgn:1002518",
        "tgn:7007568",
        "tgn:7029392"
    ],
    "tgn:id":2493599,
    "tgn:name":"Marsh Island",
    "tgn:placetype":[
        "aat:300008791"
    ]
},
  "bbox": [],
  "geometry": {"coordinates":[-75.8667,44.35],"type":"Point"}
}