{
  "id": 2739565,
  "type": "Feature",
  "properties": {
    "tgn:hierarchy":[
        "tgn:2739565",
        "tgn:1000001",
        "tgn:7012149",
        "tgn:2002371",
        "tgn:7007923",
        "tgn:7029392"
    ],
    "tgn:id":2739565,
    "tgn:name":"Upper Cathedral Lake",
    "tgn:placetype":[
        "aat:300008680"
    ]
},
  "bbox": [],
  "geometry": {"coordinates":[-109.15,42.8167],"type":"Point"}
}