{
  "id": 2270025,
  "type": "Feature",
  "properties": {
    "tgn:hierarchy":[
        "tgn:2270025",
        "tgn:1000001",
        "tgn:7012149",
        "tgn:2002118",
        "tgn:7007827",
        "tgn:7029392"
    ],
    "tgn:id":2270025,
    "tgn:name":"Crus",
    "tgn:placetype":[
        "aat:300008347"
    ]
},
  "bbox": [],
  "geometry": {"coordinates":[-111.85,40.6667],"type":"Point"}
}