<<<<<<< HEAD
{
  "id": 2764811,
  "type": "Feature",
  "properties": {
    "tgn:hierarchy":[
        "tgn:2764811",
        "tgn:1000001",
        "tgn:7012149",
        "tgn:2001275",
        "tgn:7007524",
        "tgn:7029392"
    ],
    "tgn:id":2764811,
    "tgn:name":"Whiskey Gulch",
    "tgn:placetype":[
        "aat:300008761"
    ]
},
  "bbox": [],
  "geometry": {"coordinates":[-111.2667,46.0833],"type":"Point"}
}
=======
{"geometry":{"type":"Point","coordinates":[-111.266700,46.083300]},"type":"Feature","properties":{"hierarchy":["tgn:2764811","tgn:1000001","tgn:7012149","tgn:2001275","tgn:7007524","tgn:7029392"],"placetype":["aat:300008761"],"id":2764811,"name:xx":"Whiskey Gulch"}}
>>>>>>> 03f74aca74312dbeaf24d7e61306dd6a786dc3d0
