{
  "id": 2320942,
  "type": "Feature",
  "properties": {
    "tgn:hierarchy":[
        "tgn:2320942",
        "tgn:7002659",
        "tgn:1000001",
        "tgn:7012149",
        "tgn:2000023",
        "tgn:7029392"
    ],
    "tgn:id":2320942,
    "tgn:name":"F W Pierce Lake Number 2",
    "tgn:placetype":[
        "aat:300006191"
    ]
},
  "bbox": [],
  "geometry": {"coordinates":[-87.35,32.3833],"type":"Point"}
}