{
  "id": 7517522,
  "type": "Feature",
  "properties": {
    "tgn:hierarchy":[
        "tgn:7517522",
        "tgn:1009227",
        "tgn:1000226",
        "tgn:7018437",
        "tgn:1000006",
        "tgn:7029392"
    ],
    "tgn:id":7517522,
    "tgn:name:en":"McKays Creek",
    "tgn:placetype":[
        "aat:300008699"
    ]
},
  "bbox": [],
  "geometry": {"coordinates":[169.183333,-45.616667],"type":"Point"}
}