{
  "id": 7534239,
  "type": "Feature",
  "properties": {
    "tgn:hierarchy":[
        "tgn:7534239",
        "tgn:7001242",
        "tgn:1001059",
        "tgn:7016833",
        "tgn:7029392"
    ],
    "tgn:id":7534239,
    "tgn:name":"Kafr Sinj\u0101b",
    "tgn:placetype":[
        "aat:300008347"
    ]
},
  "bbox": [],
  "geometry": {"coordinates":[31.654509,30.942854],"type":"Point"}
}