{
  "id": 7589953,
  "type": "Feature",
  "properties": {
    "tgn:hierarchy":[
        "tgn:7589953",
        "tgn:1000004",
        "tgn:7000198",
        "tgn:7016883",
        "tgn:7029392"
    ],
    "tgn:id":7589953,
    "tgn:name:en":"Sah\u0101ora",
    "tgn:placetype":[
        "aat:300008347"
    ]
},
  "bbox": [],
  "geometry": {"coordinates":[76.006508,30.656501],"type":"Point"}
}