{
  "id": 7292216,
  "type": "Feature",
  "properties": {
    "tgn:hierarchy":[
        "tgn:7292216",
        "tgn:1001708",
        "tgn:1000049",
        "tgn:1000002",
        "tgn:7029392"
    ],
    "tgn:id":7292216,
    "tgn:name":"El Estribo, Cerro",
    "tgn:placetype":[
        "aat:300008795"
    ]
},
  "bbox": [],
  "geometry": {"coordinates":[-71.383333,-33.516667],"type":"Point"}
}