{
  "id": 7030622,
  "type": "Feature",
  "properties": {
    "tgn:hierarchy":[
        "tgn:7030622",
        "tgn:7002445",
        "tgn:1000003",
        "tgn:7008166",
        "tgn:7008591",
        "tgn:7029392"
    ],
    "tgn:id":7030622,
    "tgn:name:en":"Ulleskelf",
    "tgn:placetype":[
        "aat:300008347",
        "aat:300008372"
    ]
},
  "bbox": [],
  "geometry": {"coordinates":[-1.216667,53.85],"type":"Point"}
}