<<<<<<< HEAD
{
  "id": 2251206,
  "type": "Feature",
  "properties": {
    "tgn:hierarchy":[
        "tgn:2251206",
        "tgn:1000001",
        "tgn:7012149",
        "tgn:2001449",
        "tgn:7007566",
        "tgn:7029392"
    ],
    "tgn:id":2251206,
    "tgn:name":"Comanche Number One Tank",
    "tgn:placetype":[
        "aat:300006191"
    ]
},
  "bbox": [],
  "geometry": {"coordinates":[-105.95,36.5],"type":"Point"}
}
=======
{"geometry":{"type":"Point","coordinates":[-105.950000,36.500000]},"type":"Feature","properties":{"hierarchy":["tgn:2251206","tgn:1000001","tgn:7012149","tgn:2001449","tgn:7007566","tgn:7029392"],"placetype":["aat:300006191"],"id":2251206,"name:xx":"Comanche Number One Tank"}}
>>>>>>> 03f74aca74312dbeaf24d7e61306dd6a786dc3d0
