{
  "id": 2678234,
  "type": "Feature",
  "properties": {
    "tgn:hierarchy":[
        "tgn:2678234",
        "tgn:1000001",
        "tgn:7012149",
        "tgn:2002280",
        "tgn:7013961",
        "tgn:7029392"
    ],
    "tgn:id":2678234,
    "tgn:name":"South Fork Buffalo Creek",
    "tgn:placetype":[
        "aat:300008706"
    ]
},
  "bbox": [],
  "geometry": {"coordinates":[-82.2333,37.6833],"type":"Point"}
}