{
  "id": 7547748,
  "type": "Feature",
  "properties": {
    "tgn:hierarchy":[
        "tgn:7547748",
        "tgn:1000004",
        "tgn:7000198",
        "tgn:1001996",
        "tgn:7029392"
    ],
    "tgn:id":7547748,
    "tgn:name:en":"Banj\u0101r",
    "tgn:placetype":[
        "aat:300008347"
    ]
},
  "bbox": [],
  "geometry": {"coordinates":[77.340547,31.639002],"type":"Point"}
}