{
  "id": 2161100,
  "type": "Feature",
  "properties": {
    "tgn:hierarchy":[
        "tgn:2161100",
        "tgn:1000001",
        "tgn:7012149",
        "tgn:7007248",
        "tgn:7029392"
    ],
    "tgn:id":2161100,
    "tgn:name":"Bell Creek",
    "tgn:placetype":[
        "aat:300008706"
    ]
},
  "bbox": [],
  "geometry": {"coordinates":[-84.6667,32.7667],"type":"Point"}
}