{
  "id": 7210165,
  "type": "Feature",
  "properties": {
    "tgn:hierarchy":[
        "tgn:7210165",
        "tgn:7003669",
        "tgn:1000003",
        "tgn:7000084",
        "tgn:7029392"
    ],
    "tgn:id":7210165,
    "tgn:name":"Bergtheim",
    "tgn:placetype":[
        "aat:300008347"
    ]
},
  "bbox": [],
  "geometry": {"coordinates":[10.65,49.65],"type":"Point"}
}