{
  "id": 2590108,
  "type": "Feature",
  "properties": {
    "tgn:hierarchy":[
        "tgn:2590108",
        "tgn:1000001",
        "tgn:7012149",
        "tgn:7007157",
        "tgn:1002684",
        "tgn:7029392"
    ],
    "tgn:id":2590108,
    "tgn:name":"Poison Oak Hill",
    "tgn:placetype":[
        "aat:300008798"
    ]
},
  "bbox": [],
  "geometry": {"coordinates":[-121.5333,36.35],"type":"Point"}
}