<<<<<<< HEAD
{
  "id": 2335013,
  "type": "Feature",
  "properties": {
    "tgn:hierarchy":[
        "tgn:2335013",
        "tgn:1000001",
        "tgn:7012149",
        "tgn:2001513",
        "tgn:7007709",
        "tgn:7029392"
    ],
    "tgn:id":2335013,
    "tgn:name":"Forney Creek",
    "tgn:placetype":[
        "aat:300008706"
    ]
},
  "bbox": [],
  "geometry": {"coordinates":[-81.0167,35.5167],"type":"Point"}
}
=======
{"geometry":{"type":"Point","coordinates":[-81.016700,35.516700]},"type":"Feature","properties":{"hierarchy":["tgn:2335013","tgn:1000001","tgn:7012149","tgn:2001513","tgn:7007709","tgn:7029392"],"placetype":["aat:300008706"],"id":2335013,"name:xx":"Forney Creek"}}
>>>>>>> 03f74aca74312dbeaf24d7e61306dd6a786dc3d0
