{
  "id": 1096821,
  "type": "Feature",
  "properties": {
    "tgn:hierarchy":[
        "tgn:1096821",
        "tgn:7000490",
        "tgn:1000006",
        "tgn:7001830",
        "tgn:7029392"
    ],
    "tgn:id":1096821,
    "tgn:name":"Edmonton",
    "tgn:placetype":[
        "aat:300008347"
    ]
},
  "bbox": [],
  "geometry": {"coordinates":[145.75,-17.0167],"type":"Point"}
}