<<<<<<< HEAD
{
  "id": 2255773,
  "type": "Feature",
  "properties": {
    "tgn:hierarchy":[
        "tgn:2255773",
        "tgn:1000001",
        "tgn:7012149",
        "tgn:7007157",
        "tgn:1002857",
        "tgn:7029392"
    ],
    "tgn:id":2255773,
    "tgn:name":"Copper Canyon",
    "tgn:placetype":[
        "aat:300008761"
    ]
},
  "bbox": [],
  "geometry": {"coordinates":[-114.3333,34.3833],"type":"Point"}
}
=======
{"geometry":{"type":"Point","coordinates":[-114.333300,34.383300]},"type":"Feature","properties":{"hierarchy":["tgn:2255773","tgn:1000001","tgn:7012149","tgn:7007157","tgn:1002857","tgn:7029392"],"placetype":["aat:300008761"],"id":2255773,"name:xx":"Copper Canyon"}}
>>>>>>> 03f74aca74312dbeaf24d7e61306dd6a786dc3d0
