{
  "id": 1090502,
  "type": "Feature",
  "properties": {
    "tgn:hierarchy":[
        "tgn:1090502",
        "tgn:7001242",
        "tgn:7593780",
        "tgn:1000169",
        "tgn:7029392"
    ],
    "tgn:id":1090502,
    "tgn:name":"Mandera",
    "tgn:placetype":[
        "aat:300008347"
    ]
},
  "bbox": [],
  "geometry": {"coordinates":[41.8833,3.9333],"type":"Point"}
}