{
  "id": 7379919,
  "type": "Feature",
  "properties": {
    "tgn:hierarchy":[
        "tgn:7379919",
        "tgn:1000001",
        "tgn:7005595",
        "tgn:7005560",
        "tgn:7029392"
    ],
    "tgn:id":7379919,
    "tgn:name":"Los Vasitos",
    "tgn:placetype":[
        "aat:300008347"
    ]
},
  "bbox": [],
  "geometry": {"coordinates":[-107.077222,24.631111],"type":"Point"}
}