{
  "id": 2544377,
  "type": "Feature",
  "properties": {
    "tgn:hierarchy":[
        "tgn:2544377",
        "tgn:1000001",
        "tgn:1002194",
        "tgn:7012149",
        "tgn:7007710",
        "tgn:7029392"
    ],
    "tgn:id":2544377,
    "tgn:name":"North Branch Towanda Creek",
    "tgn:placetype":[
        "aat:300008706"
    ]
},
  "bbox": [],
  "geometry": {"coordinates":[-76.8333,41.7167],"type":"Point"}
}