{
  "id": 7221039,
  "type": "Feature",
  "properties": {
    "tgn:hierarchy":[
        "tgn:7221039",
        "tgn:7002681",
        "tgn:7001395",
        "tgn:1000003",
        "tgn:1000074",
        "tgn:7029392"
    ],
    "tgn:id":7221039,
    "tgn:name":"Kapnod\u00f3ki, \u00c1kra",
    "tgn:placetype":[
        "aat:300008850"
    ]
},
  "bbox": [],
  "geometry": {"coordinates":[23.33995,37.711731],"type":"Point"}
}