{
  "id": 1066693,
  "type": "Feature",
  "properties": {
    "tgn:hierarchy":[
        "tgn:1066693",
        "tgn:1000004",
        "tgn:1001678",
        "tgn:1000111",
        "tgn:7029392"
    ],
    "tgn:id":1066693,
    "tgn:name":"Baiwang",
    "tgn:placetype":[
        "aat:300008347"
    ]
},
  "bbox": [],
  "geometry": {"coordinates":[108.5333,24.2333],"type":"Point"}
}