{
  "id": 7143792,
  "type": "Feature",
  "properties": {
    "tgn:hierarchy":[
        "tgn:7143792",
        "tgn:1000003",
        "tgn:7003676",
        "tgn:7000084",
        "tgn:7029392"
    ],
    "tgn:id":7143792,
    "tgn:name":"Klein Mimmelage",
    "tgn:placetype":[
        "aat:300008347"
    ]
},
  "bbox": [],
  "geometry": {"coordinates":[7.85,52.65],"type":"Point"}
}