{
  "id": 2057751,
  "type": "Feature",
  "properties": {
    "tgn:hierarchy":[
        "tgn:2057751",
        "tgn:1000001",
        "tgn:7012149",
        "tgn:2001161",
        "tgn:7007522",
        "tgn:7029392"
    ],
    "tgn:id":2057751,
    "tgn:name":"Wayside",
    "tgn:placetype":[
        "aat:300008347"
    ]
},
  "bbox": [],
  "geometry": {"coordinates":[-91.0333,33.2667],"type":"Point"}
}