{
  "id": 7571223,
  "type": "Feature",
  "properties": {
    "tgn:hierarchy":[
        "tgn:7571223",
        "tgn:1000004",
        "tgn:7000198",
        "tgn:1001894",
        "tgn:7029392"
    ],
    "tgn:id":7571223,
    "tgn:name:en":"Gh\u016bra",
    "tgn:placetype":[
        "aat:300008347"
    ]
},
  "bbox": [],
  "geometry": {"coordinates":[79.852808,24.767941],"type":"Point"}
}