{
  "id": 2532820,
  "type": "Feature",
  "properties": {
    "tgn:hierarchy":[
        "tgn:2532820",
        "tgn:2000258",
        "tgn:1000001",
        "tgn:7012149",
        "tgn:7007240",
        "tgn:7029392"
    ],
    "tgn:id":2532820,
    "tgn:name":"Murray Bayou",
    "tgn:placetype":[
        "aat:300132316"
    ]
},
  "bbox": [],
  "geometry": {"coordinates":[-85.4667,30.0167],"type":"Point"}
}