{
  "id": 2423365,
  "type": "Feature",
  "properties": {
    "tgn:hierarchy":[
        "tgn:2423365",
        "tgn:1000001",
        "tgn:7012149",
        "tgn:1002924",
        "tgn:7007568",
        "tgn:7029392"
    ],
    "tgn:id":2423365,
    "tgn:name":"John Boyle Island",
    "tgn:placetype":[
        "aat:300008791"
    ]
},
  "bbox": [],
  "geometry": {"coordinates":[-72.8833,40.7333],"type":"Point"}
}