{
  "id": 2628612,
  "type": "Feature",
  "properties": {
    "tgn:hierarchy":[
        "tgn:2628612",
        "tgn:1000001",
        "tgn:2001415",
        "tgn:7012149",
        "tgn:7007526",
        "tgn:7029392"
    ],
    "tgn:id":2628612,
    "tgn:name":"Roosters Comb",
    "tgn:placetype":[
        "aat:300008798"
    ]
},
  "bbox": [],
  "geometry": {"coordinates":[-116.8833,40.9667],"type":"Point"}
}