{
  "id": 7092092,
  "type": "Feature",
  "properties": {
    "tgn:hierarchy":[
        "tgn:7092092",
        "tgn:1000003",
        "tgn:7000094",
        "tgn:7000084",
        "tgn:7029392"
    ],
    "tgn:id":7092092,
    "tgn:name":"Usedomer See",
    "tgn:placetype":[
        "aat:300008679"
    ]
},
  "bbox": [],
  "geometry": {"coordinates":[13.933333,53.85],"type":"Point"}
}