{
  "id": 7517247,
  "type": "Feature",
  "properties": {
    "tgn:hierarchy":[
        "tgn:7517247",
        "tgn:1009227",
        "tgn:1000226",
        "tgn:7016822",
        "tgn:1000006",
        "tgn:7029392"
    ],
    "tgn:id":7517247,
    "tgn:name:en":"Koputotora",
    "tgn:placetype":[
        "aat:300008699"
    ]
},
  "bbox": [],
  "geometry": {"coordinates":[-176.633333,-43.816667],"type":"Point"}
}