{
  "id": 2472452,
  "type": "Feature",
  "properties": {
    "tgn:hierarchy":[
        "tgn:2472452",
        "tgn:1000001",
        "tgn:7012149",
        "tgn:7007523",
        "tgn:7029392"
    ],
    "tgn:id":2472452,
    "tgn:name":"Louse Run",
    "tgn:placetype":[
        "aat:300008699"
    ]
},
  "bbox": [],
  "geometry": {"coordinates":[-94.0833,38.75],"type":"Point"}
}