{
  "id": 7161399,
  "type": "Feature",
  "properties": {
    "tgn:hierarchy":[
        "tgn:7161399",
        "tgn:7003692",
        "tgn:1000003",
        "tgn:7000084",
        "tgn:7029392"
    ],
    "tgn:id":7161399,
    "tgn:name":"Hoherkopf",
    "tgn:placetype":[
        "aat:300008795"
    ]
},
  "bbox": [],
  "geometry": {"coordinates":[9.166667,48.283333],"type":"Point"}
}