{
  "id": 7007426,
  "type": "Feature",
  "properties": {
    "tgn:hierarchy":[
        "tgn:7007426",
        "tgn:7002808",
        "tgn:7030216",
        "tgn:1000003",
        "tgn:1000095",
        "tgn:7029392"
    ],
    "tgn:id":7007426,
    "tgn:name":"Barcelona",
    "tgn:placetype":[
        "aat:300262964",
        "aat:300008347",
        "aat:300008389",
        "aat:300387512",
        "aat:300387223",
        "aat:300387320",
        "aat:300387220",
        "aat:300387284",
        "aat:300387270",
        "aat:300387302",
        "aat:300120599",
        "aat:300387291",
        "aat:300387296"
    ]
},
  "bbox": [],
  "geometry": {"coordinates":[2.1741,41.398371],"type":"Point"}
}