{
  "id": 7256246,
  "type": "Feature",
  "properties": {
    "tgn:hierarchy":[
        "tgn:7256246",
        "tgn:7003458",
        "tgn:1000003",
        "tgn:1000063",
        "tgn:7018236",
        "tgn:7029392"
    ],
    "tgn:id":7256246,
    "tgn:name":"Westhoek",
    "tgn:placetype":[
        "aat:300008347"
    ]
},
  "bbox": [],
  "geometry": {"coordinates":[3.375112,51.021223],"type":"Point"}
}