{
  "id": 1059909,
  "type": "Feature",
  "properties": {
    "tgn:hierarchy":[
        "tgn:1059909",
        "tgn:1000004",
        "tgn:1003362",
        "tgn:7014786",
        "tgn:7029392"
    ],
    "tgn:id":1059909,
    "tgn:name":"Sugandy",
    "tgn:placetype":[
        "aat:300008347"
    ]
},
  "bbox": [],
  "geometry": {"coordinates":[74.6333,43.45],"type":"Point"}
}