{
  "id": 2218148,
  "type": "Feature",
  "properties": {
    "tgn:hierarchy":[
        "tgn:2218148",
        "tgn:1000001",
        "tgn:7012149",
        "tgn:2001666",
        "tgn:7007707",
        "tgn:7029392"
    ],
    "tgn:id":2218148,
    "tgn:name":"Canadian Sandy Creek",
    "tgn:placetype":[
        "aat:300008706"
    ]
},
  "bbox": [],
  "geometry": {"coordinates":[-97.15,34.8667],"type":"Point"}
}