<<<<<<< HEAD
{
  "id": 2159008,
  "type": "Feature",
  "properties": {
    "tgn:hierarchy":[
        "tgn:2159008",
        "tgn:1000001",
        "tgn:7012149",
        "tgn:2000355",
        "tgn:7007248",
        "tgn:7029392"
    ],
    "tgn:id":2159008,
    "tgn:name":"Becky Branch",
    "tgn:placetype":[
        "aat:300008699"
    ]
},
  "bbox": [],
  "geometry": {"coordinates":[-84.6833,34.5167],"type":"Point"}
}
=======
{"geometry":{"type":"Point","coordinates":[-84.683300,34.516700]},"type":"Feature","properties":{"hierarchy":["tgn:2159008","tgn:1000001","tgn:7012149","tgn:2000355","tgn:7007248","tgn:7029392"],"placetype":["aat:300008699"],"id":2159008,"name:xx":"Becky Branch"}}
>>>>>>> 03f74aca74312dbeaf24d7e61306dd6a786dc3d0
