{
  "id": 7515661,
  "type": "Feature",
  "properties": {
    "tgn:hierarchy":[
        "tgn:7515661",
        "tgn:7000508",
        "tgn:1008380",
        "tgn:1000226",
        "tgn:1000006",
        "tgn:7029392"
    ],
    "tgn:id":7515661,
    "tgn:name:en":"Motukahaua Island",
    "tgn:placetype":[
        "aat:300008791"
    ]
},
  "bbox": [],
  "geometry": {"coordinates":[175.373889,-36.656944],"type":"Point"}
}