{
  "id": 7184776,
  "type": "Feature",
  "properties": {
    "tgn:hierarchy":[
        "tgn:7184776",
        "tgn:1000003",
        "tgn:7003689",
        "tgn:7000084",
        "tgn:7029392"
    ],
    "tgn:id":7184776,
    "tgn:name":"Haltepunkt Gl\u00fcckauf",
    "tgn:placetype":[
        "aat:300007783"
    ]
},
  "bbox": [],
  "geometry": {"coordinates":[10.826111,51.389722],"type":"Point"}
}