{
  "id": 7236962,
  "type": "Feature",
  "properties": {
    "tgn:hierarchy":[
        "tgn:7236962",
        "tgn:7002745",
        "tgn:7017076",
        "tgn:1000003",
        "tgn:1000074",
        "tgn:7029392"
    ],
    "tgn:id":7236962,
    "tgn:name":"Elaiokh\u00f3rion",
    "tgn:placetype":[
        "aat:300008347"
    ]
},
  "bbox": [],
  "geometry": {"coordinates":[22.366667,36.716667],"type":"Point"}
}