<<<<<<< HEAD
{
  "id": 7378580,
  "type": "Feature",
  "properties": {
    "tgn:hierarchy":[
        "tgn:7378580",
        "tgn:1000001",
        "tgn:7005595",
        "tgn:7005560",
        "tgn:7029392"
    ],
    "tgn:id":7378580,
    "tgn:name":"Los Pochotes",
    "tgn:placetype":[
        "aat:300008347"
    ]
},
  "bbox": [],
  "geometry": {"coordinates":[-107.793333,24.673611],"type":"Point"}
}
=======
{"geometry":{"type":"Point","coordinates":[-107.793333,24.673611]},"type":"Feature","properties":{"hierarchy":["tgn:7378580","tgn:1000001","tgn:7005595","tgn:7005560","tgn:7029392"],"placetype":["aat:300008347"],"id":7378580,"name:xx":"Los Pochotes"}}
>>>>>>> 03f74aca74312dbeaf24d7e61306dd6a786dc3d0
