{
  "id": 1007547,
  "type": "Feature",
  "properties": {
    "tgn:hierarchy":[
        "tgn:1007547",
        "tgn:1009881",
        "tgn:7001242",
        "tgn:7014990",
        "tgn:1000183",
        "tgn:7029392"
    ],
    "tgn:id":1007547,
    "tgn:name":"Jeta, Ilha de",
    "tgn:placetype":[
        "aat:300008791"
    ]
},
  "bbox": [],
  "geometry": {"coordinates":[-16.3333,11.9167],"type":"Point"}
}