{
  "id": 7038711,
  "type": "Feature",
  "properties": {
    "tgn:hierarchy":[
        "tgn:7038711",
        "tgn:1000003",
        "tgn:7003122",
        "tgn:1000080",
        "tgn:7029392"
    ],
    "tgn:id":7038711,
    "tgn:name":"Tenna, Punta",
    "tgn:placetype":[
        "aat:300386846"
    ]
},
  "bbox": [],
  "geometry": {"coordinates":[13.733333,37.133333],"type":"Point"}
}