{
  "id": 7420241,
  "type": "Feature",
  "properties": {
    "tgn:hierarchy":[
        "tgn:7420241",
        "tgn:7005584",
        "tgn:1000001",
        "tgn:7005560",
        "tgn:7029392"
    ],
    "tgn:id":7420241,
    "tgn:name":"El Toro",
    "tgn:placetype":[
        "aat:300008347"
    ]
},
  "bbox": [],
  "geometry": {"coordinates":[-99.78,21.374444],"type":"Point"}
}