{
  "id": 7060631,
  "type": "Feature",
  "properties": {
    "tgn:hierarchy":[
        "tgn:7060631",
        "tgn:1000003",
        "tgn:7003687",
        "tgn:7000084",
        "tgn:7029392"
    ],
    "tgn:id":7060631,
    "tgn:name":"Au-Graben",
    "tgn:placetype":[
        "aat:300008699"
    ]
},
  "bbox": [],
  "geometry": {"coordinates":[11.75,52.916667],"type":"Point"}
}