<<<<<<< HEAD
{
  "id": 7359642,
  "type": "Feature",
  "properties": {
    "tgn:hierarchy":[
        "tgn:7359642",
        "tgn:7005581",
        "tgn:1000001",
        "tgn:7005560",
        "tgn:7029392"
    ],
    "tgn:id":7359642,
    "tgn:name":"Club Delfin",
    "tgn:placetype":[
        "aat:300000517"
    ]
},
  "bbox": [],
  "geometry": {"coordinates":[-105.3,28.183333],"type":"Point"}
}
=======
{"geometry":{"type":"Point","coordinates":[-105.300000,28.183333]},"type":"Feature","properties":{"hierarchy":["tgn:7359642","tgn:7005581","tgn:1000001","tgn:7005560","tgn:7029392"],"placetype":["aat:300000517"],"id":7359642,"name:xx":"Club Delfin"}}
>>>>>>> 03f74aca74312dbeaf24d7e61306dd6a786dc3d0
