{
  "id": 2329398,
  "type": "Feature",
  "properties": {
    "tgn:hierarchy":[
        "tgn:2329398",
        "tgn:1000001",
        "tgn:7012149",
        "tgn:7007158",
        "tgn:2000245",
        "tgn:7029392"
    ],
    "tgn:id":2329398,
    "tgn:name":"Five Pine Mesa Creek",
    "tgn:placetype":[
        "aat:300008706"
    ]
},
  "bbox": [],
  "geometry": {"coordinates":[-106.9167,40.0667],"type":"Point"}
}