<<<<<<< HEAD
{
  "id": 7023482,
  "type": "Feature",
  "properties": {
    "tgn:hierarchy":[
        "tgn:7023482",
        "tgn:1000001",
        "tgn:7012149",
        "tgn:7007157",
        "tgn:1002894",
        "tgn:7029392"
    ],
    "tgn:id":7023482,
    "tgn:name":"Mountain View Mine",
    "tgn:placetype":[
        "aat:300000390"
    ]
},
  "bbox": [],
  "geometry": {"coordinates":[-120.8,39.4833],"type":"Point"}
}
=======
{"geometry":{"type":"Point","coordinates":[-120.800000,39.483300]},"type":"Feature","properties":{"hierarchy":["tgn:7023482","tgn:1000001","tgn:7012149","tgn:7007157","tgn:1002894","tgn:7029392"],"placetype":["aat:300000390"],"id":7023482,"name:xx":"Mountain View Mine"}}
>>>>>>> 03f74aca74312dbeaf24d7e61306dd6a786dc3d0
