{
  "id": 7161985,
  "type": "Feature",
  "properties": {
    "tgn:hierarchy":[
        "tgn:7161985",
        "tgn:1000003",
        "tgn:7003676",
        "tgn:7000084",
        "tgn:7029392"
    ],
    "tgn:id":7161985,
    "tgn:name":"Iddensen",
    "tgn:placetype":[
        "aat:300008347"
    ]
},
  "bbox": [],
  "geometry": {"coordinates":[9.916667,53.383333],"type":"Point"}
}