{
  "id": 7561806,
  "type": "Feature",
  "properties": {
    "tgn:hierarchy":[
        "tgn:7561806",
        "tgn:1000004",
        "tgn:7000198",
        "tgn:7016722",
        "tgn:7029392"
    ],
    "tgn:id":7561806,
    "tgn:name:en":"Harchandpur Kusmara",
    "tgn:placetype":[
        "aat:300008347"
    ]
},
  "bbox": [],
  "geometry": {"coordinates":[79.277786,27.104806],"type":"Point"}
}