{
  "id": 2260087,
  "type": "Feature",
  "properties": {
    "tgn:hierarchy":[
        "tgn:2260087",
        "tgn:1000001",
        "tgn:2001746",
        "tgn:7012149",
        "tgn:7007712",
        "tgn:7029392"
    ],
    "tgn:id":2260087,
    "tgn:name":"Country Club Estates",
    "tgn:placetype":[
        "aat:300008347"
    ]
},
  "bbox": [],
  "geometry": {"coordinates":[-79.2833,33.3667],"type":"Point"}
}