<<<<<<< HEAD
{
  "id": 7115796,
  "type": "Feature",
  "properties": {
    "tgn:hierarchy":[
        "tgn:7115796",
        "tgn:1000003",
        "tgn:7003685",
        "tgn:7000084",
        "tgn:7029392"
    ],
    "tgn:id":7115796,
    "tgn:name":"Ohorner Stein-Berg",
    "tgn:placetype":[
        "aat:300008777"
    ]
},
  "bbox": [],
  "geometry": {"coordinates":[14.1,51.2],"type":"Point"}
}
=======
{"geometry":{"type":"Point","coordinates":[14.100000,51.200000]},"type":"Feature","properties":{"hierarchy":["tgn:7115796","tgn:1000003","tgn:7003685","tgn:7000084","tgn:7029392"],"placetype":["aat:300008777"],"id":7115796,"name:xx":"Ohorner Stein-Berg"}}
>>>>>>> 03f74aca74312dbeaf24d7e61306dd6a786dc3d0
