{
  "id": 7539210,
  "type": "Feature",
  "properties": {
    "tgn:hierarchy":[
        "tgn:7539210",
        "tgn:7001242",
        "tgn:7016833",
        "tgn:1001142",
        "tgn:7029392"
    ],
    "tgn:id":7539210,
    "tgn:name:en":"\u015eaf\u0163 al Khirsah",
    "tgn:placetype":[
        "aat:300008347"
    ]
},
  "bbox": [],
  "geometry": {"coordinates":[30.828512,28.826329],"type":"Point"}
}