{
  "id": 7315393,
  "type": "Feature",
  "properties": {
    "tgn:hierarchy":[
        "tgn:7315393",
        "tgn:1001702",
        "tgn:1000049",
        "tgn:1000002",
        "tgn:7029392"
    ],
    "tgn:id":7315393,
    "tgn:name":"Chance, Islotes",
    "tgn:placetype":[
        "aat:300008791"
    ]
},
  "bbox": [],
  "geometry": {"coordinates":[-74.783333,-50.466667],"type":"Point"}
}