{
  "id": 2351779,
  "type": "Feature",
  "properties": {
    "tgn:hierarchy":[
        "tgn:2351779",
        "tgn:1000001",
        "tgn:7016172",
        "tgn:7012149",
        "tgn:2000149",
        "tgn:7029392"
    ],
    "tgn:id":2351779,
    "tgn:name":"Glenn Spring",
    "tgn:placetype":[
        "aat:300008697"
    ]
},
  "bbox": [],
  "geometry": {"coordinates":[-92.7333,36.1333],"type":"Point"}
}