<<<<<<< HEAD
{
  "id": 2332604,
  "type": "Feature",
  "properties": {
    "tgn:hierarchy":[
        "tgn:2332604",
        "tgn:1000001",
        "tgn:7012149",
        "tgn:2000278",
        "tgn:7007240",
        "tgn:7029392"
    ],
    "tgn:id":2332604,
    "tgn:name":"Florida River",
    "tgn:placetype":[
        "aat:300008707"
    ]
},
  "bbox": [],
  "geometry": {"coordinates":[-85.0833,30.2],"type":"Point"}
}
=======
{"geometry":{"type":"Point","coordinates":[-85.083300,30.200000]},"type":"Feature","properties":{"hierarchy":["tgn:2332604","tgn:1000001","tgn:7012149","tgn:2000278","tgn:7007240","tgn:7029392"],"placetype":["aat:300008707"],"id":2332604,"name:xx":"Florida River"}}
>>>>>>> 03f74aca74312dbeaf24d7e61306dd6a786dc3d0
