{
  "id": 2179815,
  "type": "Feature",
  "properties": {
    "tgn:hierarchy":[
        "tgn:2179815",
        "tgn:1000001",
        "tgn:7012149",
        "tgn:2000476",
        "tgn:7007250",
        "tgn:7029392"
    ],
    "tgn:id":2179815,
    "tgn:name":"Bleak Creek",
    "tgn:placetype":[
        "aat:300008706"
    ]
},
  "bbox": [],
  "geometry": {"coordinates":[-115.0167,45.65],"type":"Point"}
}