{
  "id": 7588205,
  "type": "Feature",
  "properties": {
    "tgn:hierarchy":[
        "tgn:7588205",
        "tgn:1000004",
        "tgn:7000198",
        "tgn:7000799",
        "tgn:7029392"
    ],
    "tgn:id":7588205,
    "tgn:name:en":"P\u0101ras",
    "tgn:placetype":[
        "aat:300008347"
    ]
},
  "bbox": [],
  "geometry": {"coordinates":[74.6625,34.005556],"type":"Point"}
}