{
  "id": 2143353,
  "type": "Feature",
  "properties": {
    "tgn:hierarchy":[
        "tgn:2143353",
        "tgn:1000001",
        "tgn:1002714",
        "tgn:7012149",
        "tgn:7007159",
        "tgn:7029392"
    ],
    "tgn:id":2143353,
    "tgn:name":"Bailey Hill",
    "tgn:placetype":[
        "aat:300008798"
    ]
},
  "bbox": [],
  "geometry": {"coordinates":[-72.0667,41.3667],"type":"Point"}
}