{
  "id": 2394206,
  "type": "Feature",
  "properties": {
    "tgn:hierarchy":[
        "tgn:2394206",
        "tgn:1000001",
        "tgn:7012149",
        "tgn:7007158",
        "tgn:2000253",
        "tgn:7029392"
    ],
    "tgn:id":2394206,
    "tgn:name":"Hogarty Reservoir",
    "tgn:placetype":[
        "aat:300006191"
    ]
},
  "bbox": [],
  "geometry": {"coordinates":[-104.7667,40.4667],"type":"Point"}
}