{
  "id": 2489747,
  "type": "Feature",
  "properties": {
    "tgn:hierarchy":[
        "tgn:2489747",
        "tgn:1000001",
        "tgn:7012149",
        "tgn:2000285",
        "tgn:7007240",
        "tgn:7029392"
    ],
    "tgn:id":2489747,
    "tgn:name":"Malone Hammock Branch",
    "tgn:placetype":[
        "aat:300008699"
    ]
},
  "bbox": [],
  "geometry": {"coordinates":[-87.25,30.8667],"type":"Point"}
}