{
  "id": 7319576,
  "type": "Feature",
  "properties": {
    "tgn:hierarchy":[
        "tgn:7319576",
        "tgn:1001695",
        "tgn:1000049",
        "tgn:1000002",
        "tgn:7029392"
    ],
    "tgn:id":7319576,
    "tgn:name":"Alonso de Morales, Estero",
    "tgn:placetype":[
        "aat:300008699"
    ]
},
  "bbox": [],
  "geometry": {"coordinates":[-71.533333,-34.283333],"type":"Point"}
}