{
  "id": 2054752,
  "type": "Feature",
  "properties": {
    "tgn:hierarchy":[
        "tgn:2054752",
        "tgn:1000001",
        "tgn:7012149",
        "tgn:2001036",
        "tgn:7007521",
        "tgn:7029392"
    ],
    "tgn:id":2054752,
    "tgn:name":"Jordan",
    "tgn:placetype":[
        "aat:300387016"
    ]
},
  "bbox": [],
  "geometry": {"coordinates":[-91.6167,47.3667],"type":"Point"}
}