{
  "id": 2699849,
  "type": "Feature",
  "properties": {
    "tgn:hierarchy":[
        "tgn:2699849",
        "tgn:1000001",
        "tgn:1002305",
        "tgn:7012149",
        "tgn:7007920",
        "tgn:7029392"
    ],
    "tgn:id":2699849,
    "tgn:name":"Studebaker Creek",
    "tgn:placetype":[
        "aat:300008706"
    ]
},
  "bbox": [],
  "geometry": {"coordinates":[-122.6667,46.25],"type":"Point"}
}