{
  "id": 2428789,
  "type": "Feature",
  "properties": {
    "tgn:hierarchy":[
        "tgn:2428789",
        "tgn:1000001",
        "tgn:2001410",
        "tgn:7012149",
        "tgn:7007526",
        "tgn:7029392"
    ],
    "tgn:id":2428789,
    "tgn:name":"Jumbo Basin",
    "tgn:placetype":[
        "aat:300386845"
    ]
},
  "bbox": [],
  "geometry": {"coordinates":[-114.1833,36.1667],"type":"Point"}
}