{
  "id": 2324911,
  "type": "Feature",
  "properties": {
    "tgn:hierarchy":[
        "tgn:2324911",
        "tgn:7006450",
        "tgn:1000001",
        "tgn:7012149",
        "tgn:2000082",
        "tgn:7029392"
    ],
    "tgn:id":2324911,
    "tgn:name":"Ferguson Glacier",
    "tgn:placetype":[
        "aat:300008835"
    ]
},
  "bbox": [],
  "geometry": {"coordinates":[-130.2167,56.0167],"type":"Point"}
}