{
  "id": 7296709,
  "type": "Feature",
  "properties": {
    "tgn:hierarchy":[
        "tgn:7296709",
        "tgn:7002758",
        "tgn:7002841",
        "tgn:1000003",
        "tgn:1000095",
        "tgn:7029392"
    ],
    "tgn:id":7296709,
    "tgn:name":"Cortijo del Pinganillo",
    "tgn:placetype":[
        "aat:300000206"
    ]
},
  "bbox": [],
  "geometry": {"coordinates":[-5.784722,37.125],"type":"Point"}
}