{
  "id": 2179684,
  "type": "Feature",
  "properties": {
    "tgn:hierarchy":[
        "tgn:2179684",
        "tgn:1000001",
        "tgn:7012149",
        "tgn:1002518",
        "tgn:7007568",
        "tgn:7029392"
    ],
    "tgn:id":2179684,
    "tgn:name":"Blanket Shoals",
    "tgn:placetype":[
        "aat:300132348"
    ]
},
  "bbox": [],
  "geometry": {"coordinates":[-76.15,44.2333],"type":"Point"}
}