{
  "id": 7577523,
  "type": "Feature",
  "properties": {
    "tgn:hierarchy":[
        "tgn:7577523",
        "tgn:1000004",
        "tgn:7031781",
        "tgn:7000198",
        "tgn:7029392"
    ],
    "tgn:id":7577523,
    "tgn:name:en":"Kui",
    "tgn:placetype":[
        "aat:300008347"
    ]
},
  "bbox": [],
  "geometry": {"coordinates":[81.351263,22.3512],"type":"Point"}
}