{
  "id": 7515111,
  "type": "Feature",
  "properties": {
    "tgn:hierarchy":[
        "tgn:7515111",
        "tgn:1009227",
        "tgn:1000226",
        "tgn:7018437",
        "tgn:1000006",
        "tgn:7029392"
    ],
    "tgn:id":7515111,
    "tgn:name:en":"Crookston Burn",
    "tgn:placetype":[
        "aat:300008699"
    ]
},
  "bbox": [],
  "geometry": {"coordinates":[169.233333,-45.916667],"type":"Point"}
}