{
  "id": 7125882,
  "type": "Feature",
  "properties": {
    "tgn:hierarchy":[
        "tgn:7125882",
        "tgn:1000003",
        "tgn:7003682",
        "tgn:7000084",
        "tgn:7029392"
    ],
    "tgn:id":7125882,
    "tgn:name":"Oberingelbach",
    "tgn:placetype":[
        "aat:300008347"
    ]
},
  "bbox": [],
  "geometry": {"coordinates":[7.716667,50.683333],"type":"Point"}
}