{
  "id": 7586566,
  "type": "Feature",
  "properties": {
    "tgn:hierarchy":[
        "tgn:7586566",
        "tgn:1000004",
        "tgn:7000198",
        "tgn:7000799",
        "tgn:7029392"
    ],
    "tgn:id":7586566,
    "tgn:name:en":"Maid\u0101npura",
    "tgn:placetype":[
        "aat:300008347"
    ]
},
  "bbox": [],
  "geometry": {"coordinates":[74.423611,34.4625],"type":"Point"}
}