{
  "id": 2437006,
  "type": "Feature",
  "properties": {
    "tgn:hierarchy":[
        "tgn:2437006",
        "tgn:1000001",
        "tgn:7012149",
        "tgn:2001521",
        "tgn:7007709",
        "tgn:7029392"
    ],
    "tgn:id":2437006,
    "tgn:name":"Killets Creek",
    "tgn:placetype":[
        "aat:300008706"
    ]
},
  "bbox": [],
  "geometry": {"coordinates":[-79.4167,35.3167],"type":"Point"}
}