{
  "id": 1135131,
  "type": "Feature",
  "properties": {
    "tgn:hierarchy":[
        "tgn:1135131",
        "tgn:1000001",
        "tgn:7012149",
        "tgn:7007826",
        "tgn:7029392"
    ],
    "tgn:id":1135131,
    "tgn:name":"Yegua Creek",
    "tgn:placetype":[
        "aat:300008706"
    ]
},
  "bbox": [],
  "geometry": {"coordinates":[-96.7333,30.3167],"type":"Point"}
}