{
  "id": 2173192,
  "type": "Feature",
  "properties": {
    "tgn:hierarchy":[
        "tgn:2173192",
        "tgn:1000001",
        "tgn:7012149",
        "tgn:7014589",
        "tgn:7007515",
        "tgn:7029392"
    ],
    "tgn:id":2173192,
    "tgn:name":"Bingo",
    "tgn:placetype":[
        "aat:300008347"
    ]
},
  "bbox": [],
  "geometry": {"coordinates":[-67.6667,45.3333],"type":"Point"}
}