{
  "id": 7240398,
  "type": "Feature",
  "properties": {
    "tgn:hierarchy":[
        "tgn:7240398",
        "tgn:7003465",
        "tgn:1000003",
        "tgn:1000063",
        "tgn:4012014",
        "tgn:7029392"
    ],
    "tgn:id":7240398,
    "tgn:name":"Famenne",
    "tgn:placetype":[
        "aat:300008347"
    ]
},
  "bbox": [],
  "geometry": {"coordinates":[5.344428,50.227726],"type":"Point"}
}