{
  "id": 2692572,
  "type": "Feature",
  "properties": {
    "tgn:hierarchy":[
        "tgn:2692572",
        "tgn:7006450",
        "tgn:2000069",
        "tgn:1000001",
        "tgn:7012149",
        "tgn:7029392"
    ],
    "tgn:id":2692572,
    "tgn:name":"Steamboat Slough",
    "tgn:placetype":[
        "aat:300008699"
    ]
},
  "bbox": [],
  "geometry": {"coordinates":[-161.65,60.7833],"type":"Point"}
}