{
  "id": 7509773,
  "type": "Feature",
  "properties": {
    "tgn:hierarchy":[
        "tgn:7509773",
        "tgn:1009227",
        "tgn:1000226",
        "tgn:7018437",
        "tgn:1000006",
        "tgn:7029392"
    ],
    "tgn:id":7509773,
    "tgn:name:en":"Strachan Creek",
    "tgn:placetype":[
        "aat:300008699"
    ]
},
  "bbox": [],
  "geometry": {"coordinates":[169.333333,-44.033333],"type":"Point"}
}