{
  "id": 2536456,
  "type": "Feature",
  "properties": {
    "tgn:hierarchy":[
        "tgn:2536456",
        "tgn:1000001",
        "tgn:7016172",
        "tgn:7012149",
        "tgn:2000136",
        "tgn:7029392"
    ],
    "tgn:id":2536456,
    "tgn:name":"Neal Mountain",
    "tgn:placetype":[
        "aat:300008798"
    ]
},
  "bbox": [],
  "geometry": {"coordinates":[-91.55,35.65],"type":"Point"}
}