{
  "id": 2187722,
  "type": "Feature",
  "properties": {
    "tgn:hierarchy":[
        "tgn:2187722",
        "tgn:1000001",
        "tgn:2001096",
        "tgn:7012149",
        "tgn:7007522",
        "tgn:7029392"
    ],
    "tgn:id":2187722,
    "tgn:name":"Booths Creek",
    "tgn:placetype":[
        "aat:300008706"
    ]
},
  "bbox": [],
  "geometry": {"coordinates":[-90.8167,31.95],"type":"Point"}
}