{
  "id": 2162800,
  "type": "Feature",
  "properties": {
    "tgn:hierarchy":[
        "tgn:2162800",
        "tgn:1000001",
        "tgn:7006451",
        "tgn:7012149",
        "tgn:2000102",
        "tgn:7029392"
    ],
    "tgn:id":2162800,
    "tgn:name":"Benedict, Mount",
    "tgn:placetype":[
        "aat:300008798"
    ]
},
  "bbox": [],
  "geometry": {"coordinates":[-110.9167,31.3833],"type":"Point"}
}