{
  "id": 2247467,
  "type": "Feature",
  "properties": {
    "tgn:hierarchy":[
        "tgn:2247467",
        "tgn:1000001",
        "tgn:7012149",
        "tgn:2001983",
        "tgn:7007826",
        "tgn:7029392"
    ],
    "tgn:id":2247467,
    "tgn:name":"Coffee Mill Lake",
    "tgn:placetype":[
        "aat:300006191"
    ]
},
  "bbox": [],
  "geometry": {"coordinates":[-95.9667,33.7167],"type":"Point"}
}