{
  "id": 1004145,
  "type": "Feature",
  "properties": {
    "tgn:hierarchy":[
        "tgn:1004145",
        "tgn:7002445",
        "tgn:7018914",
        "tgn:1000003",
        "tgn:7008136",
        "tgn:7008591",
        "tgn:7029392"
    ],
    "tgn:id":1004145,
    "tgn:name":"Botany Bay",
    "tgn:placetype":[
        "aat:300000745"
    ]
},
  "bbox": [],
  "geometry": {"coordinates":[-0.1167,51.6833],"type":"Point"}
}