{
  "id": 7487304,
  "type": "Feature",
  "properties": {
    "tgn:hierarchy":[
        "tgn:7487304",
        "tgn:7001004",
        "tgn:1000004",
        "tgn:1000141",
        "tgn:7029392"
    ],
    "tgn:id":7487304,
    "tgn:name":"Yamuliao",
    "tgn:placetype":[
        "aat:300008347"
    ]
},
  "bbox": [],
  "geometry": {"coordinates":[120.452778,22.938611],"type":"Point"}
}