<<<<<<< HEAD
{
  "id": 2760565,
  "type": "Feature",
  "properties": {
    "tgn:hierarchy":[
        "tgn:2760565",
        "tgn:1000001",
        "tgn:7012149",
        "tgn:7007157",
        "tgn:2000191",
        "tgn:7029392"
    ],
    "tgn:id":2760565,
    "tgn:name":"West Fork Van Duzen River",
    "tgn:placetype":[
        "aat:300008707"
    ]
},
  "bbox": [],
  "geometry": {"coordinates":[-123.5333,40.3],"type":"Point"}
}
=======
{"geometry":{"type":"Point","coordinates":[-123.533300,40.300000]},"type":"Feature","properties":{"hierarchy":["tgn:2760565","tgn:1000001","tgn:7012149","tgn:7007157","tgn:2000191","tgn:7029392"],"placetype":["aat:300008707"],"id":2760565,"name:xx":"West Fork Van Duzen River"}}
>>>>>>> 03f74aca74312dbeaf24d7e61306dd6a786dc3d0
