<<<<<<< HEAD
{
  "id": 7485496,
  "type": "Feature",
  "properties": {
    "tgn:hierarchy":[
        "tgn:7485496",
        "tgn:7488858",
        "tgn:1000004",
        "tgn:1000141",
        "tgn:7029392"
    ],
    "tgn:id":7485496,
    "tgn:name":"Bengshanping",
    "tgn:placetype":[
        "aat:300008347"
    ]
},
  "bbox": [],
  "geometry": {"coordinates":[120.723333,23.708611],"type":"Point"}
}
=======
{"geometry":{"type":"Point","coordinates":[120.723333,23.708611]},"type":"Feature","properties":{"hierarchy":["tgn:7485496","tgn:7488858","tgn:1000004","tgn:1000141","tgn:7029392"],"placetype":["aat:300008347"],"id":7485496,"name:xx":"Bengshanping"}}
>>>>>>> 03f74aca74312dbeaf24d7e61306dd6a786dc3d0
