{
  "id": 7237695,
  "type": "Feature",
  "properties": {
    "tgn:hierarchy":[
        "tgn:7237695",
        "tgn:7003465",
        "tgn:1000003",
        "tgn:1000063",
        "tgn:4012014",
        "tgn:7029392"
    ],
    "tgn:id":7237695,
    "tgn:name":"Halconreux",
    "tgn:placetype":[
        "aat:300008347"
    ]
},
  "bbox": [],
  "geometry": {"coordinates":[5.924444,50.195278],"type":"Point"}
}