{
  "id": 2038363,
  "type": "Feature",
  "properties": {
    "tgn:hierarchy":[
        "tgn:2038363",
        "tgn:1000001",
        "tgn:7012149",
        "tgn:2000789",
        "tgn:7007255",
        "tgn:7029392"
    ],
    "tgn:id":2038363,
    "tgn:name":"Craynor",
    "tgn:placetype":[
        "aat:300008347"
    ]
},
  "bbox": [],
  "geometry": {"coordinates":[-82.6667,37.4333],"type":"Point"}
}