{
  "id": 7310731,
  "type": "Feature",
  "properties": {
    "tgn:hierarchy":[
        "tgn:7310731",
        "tgn:1001695",
        "tgn:1000049",
        "tgn:1000002",
        "tgn:7029392"
    ],
    "tgn:id":7310731,
    "tgn:name":"Millaco",
    "tgn:placetype":[
        "aat:300004792"
    ]
},
  "bbox": [],
  "geometry": {"coordinates":[-71.983333,-34.483333],"type":"Point"}
}