<<<<<<< HEAD
{
  "id": 7053938,
  "type": "Feature",
  "properties": {
    "tgn:hierarchy":[
        "tgn:7053938",
        "tgn:7003138",
        "tgn:1000003",
        "tgn:7003080",
        "tgn:1000080",
        "tgn:7029392"
    ],
    "tgn:id":7053938,
    "tgn:name":"Pallavicina, Fosso",
    "tgn:placetype":[
        "aat:300008699"
    ]
},
  "bbox": [],
  "geometry": {"coordinates":[12.733333,41.9],"type":"Point"}
}
=======
{"geometry":{"type":"Point","coordinates":[12.733333,41.900000]},"type":"Feature","properties":{"hierarchy":["tgn:7053938","tgn:7003138","tgn:1000003","tgn:7003080","tgn:1000080","tgn:7029392"],"placetype":["aat:300008699"],"id":7053938,"name:xx":"Pallavicina, Fosso"}}
>>>>>>> 03f74aca74312dbeaf24d7e61306dd6a786dc3d0
