{
  "id": 2785549,
  "type": "Feature",
  "properties": {
    "tgn:hierarchy":[
        "tgn:2785549",
        "tgn:1000001",
        "tgn:7006451",
        "tgn:7012149",
        "tgn:7029392"
    ],
    "tgn:id":2785549,
    "tgn:name":"Yle Canyon",
    "tgn:placetype":[
        "aat:300008761"
    ]
},
  "bbox": [],
  "geometry": {"coordinates":[-110.3667,32.6167],"type":"Point"}
}