{
  "id": 7065874,
  "type": "Feature",
  "properties": {
    "tgn:hierarchy":[
        "tgn:7065874",
        "tgn:1000003",
        "tgn:7003676",
        "tgn:7000084",
        "tgn:7029392"
    ],
    "tgn:id":7065874,
    "tgn:name":"Twiestel",
    "tgn:placetype":[
        "aat:300000206"
    ]
},
  "bbox": [],
  "geometry": {"coordinates":[7.983333,52.533333],"type":"Point"}
}