{
  "id": 7502104,
  "type": "Feature",
  "properties": {
    "tgn:hierarchy":[
        "tgn:7502104",
        "tgn:7001004",
        "tgn:1000004",
        "tgn:1000141",
        "tgn:7029392"
    ],
    "tgn:id":7502104,
    "tgn:name":"Meixiu Xi",
    "tgn:placetype":[
        "aat:300008699"
    ]
},
  "bbox": [],
  "geometry": {"coordinates":[120.778056,23.187222],"type":"Point"}
}