{
  "id": 7537801,
  "type": "Feature",
  "properties": {
    "tgn:hierarchy":[
        "tgn:7537801",
        "tgn:7001242",
        "tgn:7016833",
        "tgn:1001092",
        "tgn:7029392"
    ],
    "tgn:id":7537801,
    "tgn:name":"Ramlah, Jaz\u012brat ar",
    "tgn:placetype":[
        "aat:300008791"
    ]
},
  "bbox": [],
  "geometry": {"coordinates":[31.151552,30.448696],"type":"Point"}
}