<<<<<<< HEAD
{
  "id": 7477314,
  "type": "Feature",
  "properties": {
    "tgn:hierarchy":[
        "tgn:7477314",
        "tgn:1000004",
        "tgn:7001013",
        "tgn:1000141",
        "tgn:7029392"
    ],
    "tgn:id":7477314,
    "tgn:name":"Shipai Qiao",
    "tgn:placetype":[
        "aat:300007836"
    ]
},
  "bbox": [],
  "geometry": {"coordinates":[121.122864,25.013747],"type":"Point"}
}
=======
{"geometry":{"type":"Point","coordinates":[121.122864,25.013747]},"type":"Feature","properties":{"hierarchy":["tgn:7477314","tgn:1000004","tgn:7001013","tgn:1000141","tgn:7029392"],"placetype":["aat:300007836"],"id":7477314,"name:xx":"Shipai Qiao"}}
>>>>>>> 03f74aca74312dbeaf24d7e61306dd6a786dc3d0
