{
  "id": 7138432,
  "type": "Feature",
  "properties": {
    "tgn:hierarchy":[
        "tgn:7138432",
        "tgn:1000003",
        "tgn:7003688",
        "tgn:7000084",
        "tgn:7029392"
    ],
    "tgn:id":7138432,
    "tgn:name":"Lemkenhafener Wiek",
    "tgn:placetype":[
        "aat:300132316"
    ]
},
  "bbox": [],
  "geometry": {"coordinates":[11.083333,54.45],"type":"Point"}
}