<<<<<<< HEAD
{
  "id": 7359747,
  "type": "Feature",
  "properties": {
    "tgn:hierarchy":[
        "tgn:7359747",
        "tgn:7005585",
        "tgn:1000001",
        "tgn:7005560",
        "tgn:7029392"
    ],
    "tgn:id":7359747,
    "tgn:name":"Coacoyulichan",
    "tgn:placetype":[
        "aat:300008347"
    ]
},
  "bbox": [],
  "geometry": {"coordinates":[-99.016667,16.816667],"type":"Point"}
}
=======
{"geometry":{"type":"Point","coordinates":[-99.016667,16.816667]},"type":"Feature","properties":{"hierarchy":["tgn:7359747","tgn:7005585","tgn:1000001","tgn:7005560","tgn:7029392"],"placetype":["aat:300008347"],"id":7359747,"name:xx":"Coacoyulichan"}}
>>>>>>> 03f74aca74312dbeaf24d7e61306dd6a786dc3d0
