{
  "id": 7289824,
  "type": "Feature",
  "properties": {
    "tgn:hierarchy":[
        "tgn:7289824",
        "tgn:1001708",
        "tgn:1000049",
        "tgn:1000002",
        "tgn:7029392"
    ],
    "tgn:id":7289824,
    "tgn:name":"El Canelo",
    "tgn:placetype":[
        "aat:300387200"
    ]
},
  "bbox": [],
  "geometry": {"coordinates":[-71.716667,-33.916667],"type":"Point"}
}