{
  "id": 7587392,
  "type": "Feature",
  "properties": {
    "tgn:hierarchy":[
        "tgn:7587392",
        "tgn:1000004",
        "tgn:7000198",
        "tgn:1001977",
        "tgn:7029392"
    ],
    "tgn:id":7587392,
    "tgn:name:en":"Bedkundu",
    "tgn:placetype":[
        "aat:300008347"
    ]
},
  "bbox": [],
  "geometry": {"coordinates":[88.049345,22.178291],"type":"Point"}
}