{
  "id": 7352901,
  "type": "Feature",
  "properties": {
    "tgn:hierarchy":[
        "tgn:7352901",
        "tgn:7005585",
        "tgn:1000001",
        "tgn:7005560",
        "tgn:7029392"
    ],
    "tgn:id":7352901,
    "tgn:name":"Atlicintla",
    "tgn:placetype":[
        "aat:300008347"
    ]
},
  "bbox": [],
  "geometry": {"coordinates":[-99.066667,17.85],"type":"Point"}
}