<<<<<<< HEAD
{
  "id": 2334678,
  "type": "Feature",
  "properties": {
    "tgn:hierarchy":[
        "tgn:2334678",
        "tgn:1000001",
        "tgn:7016172",
        "tgn:7012149",
        "tgn:2000135",
        "tgn:7029392"
    ],
    "tgn:id":2334678,
    "tgn:name":"Forgy",
    "tgn:placetype":[
        "aat:300008347"
    ]
},
  "bbox": [],
  "geometry": {"coordinates":[-93.9333,33.9333],"type":"Point"}
}
=======
{"geometry":{"type":"Point","coordinates":[-93.933300,33.933300]},"type":"Feature","properties":{"hierarchy":["tgn:2334678","tgn:1000001","tgn:7016172","tgn:7012149","tgn:2000135","tgn:7029392"],"placetype":["aat:300008347"],"id":2334678,"name:xx":"Forgy"}}
>>>>>>> 03f74aca74312dbeaf24d7e61306dd6a786dc3d0
