{
  "id": 1106488,
  "type": "Feature",
  "properties": {
    "tgn:hierarchy":[
        "tgn:1106488",
        "tgn:7002445",
        "tgn:1000003",
        "tgn:7008117",
        "tgn:7008591",
        "tgn:7029392"
    ],
    "tgn:id":1106488,
    "tgn:name:en":"Skiddaw",
    "tgn:placetype":[
        "aat:300008795"
    ]
},
  "bbox": [],
  "geometry": {"coordinates":[-3.116667,54.65],"type":"Point"}
}