{
  "id": 2708194,
  "type": "Feature",
  "properties": {
    "tgn:hierarchy":[
        "tgn:2708194",
        "tgn:1000001",
        "tgn:7012149",
        "tgn:2002250",
        "tgn:7007920",
        "tgn:7029392"
    ],
    "tgn:id":2708194,
    "tgn:name":"Swiss Valley",
    "tgn:placetype":[
        "aat:300008761"
    ]
},
  "bbox": [],
  "geometry": {"coordinates":[-117.9167,48.3833],"type":"Point"}
}