{
  "id": 7228082,
  "type": "Feature",
  "properties": {
    "tgn:hierarchy":[
        "tgn:7228082",
        "tgn:7011167",
        "tgn:7001338",
        "tgn:1000003",
        "tgn:1000074",
        "tgn:7029392"
    ],
    "tgn:id":7228082,
    "tgn:name":"Kast\u00f3s",
    "tgn:placetype":[
        "aat:300008347"
    ]
},
  "bbox": [],
  "geometry": {"coordinates":[20.916667,38.566667],"type":"Point"}
}