<<<<<<< HEAD
{
  "id": 7370606,
  "type": "Feature",
  "properties": {
    "tgn:hierarchy":[
        "tgn:7370606",
        "tgn:1000001",
        "tgn:1001960",
        "tgn:7005560",
        "tgn:7029392"
    ],
    "tgn:id":7370606,
    "tgn:name":"Guaymas, Cerro",
    "tgn:placetype":[
        "aat:300008795"
    ]
},
  "bbox": [],
  "geometry": {"coordinates":[-111.216667,28.183333],"type":"Point"}
}
=======
{"geometry":{"type":"Point","coordinates":[-111.216667,28.183333]},"type":"Feature","properties":{"hierarchy":["tgn:7370606","tgn:1000001","tgn:1001960","tgn:7005560","tgn:7029392"],"placetype":["aat:300008795"],"id":7370606,"name:xx":"Guaymas, Cerro"}}
>>>>>>> 03f74aca74312dbeaf24d7e61306dd6a786dc3d0
