{
  "id": 7096339,
  "type": "Feature",
  "properties": {
    "tgn:hierarchy":[
        "tgn:7096339",
        "tgn:7003669",
        "tgn:1000003",
        "tgn:7000084",
        "tgn:7029392"
    ],
    "tgn:id":7096339,
    "tgn:name":"Sch\u00f6nach",
    "tgn:placetype":[
        "aat:300000206"
    ]
},
  "bbox": [],
  "geometry": {"coordinates":[11.233333,47.75],"type":"Point"}
}