{
  "id": 7319904,
  "type": "Feature",
  "properties": {
    "tgn:hierarchy":[
        "tgn:7319904",
        "tgn:1001623",
        "tgn:1000049",
        "tgn:1000002",
        "tgn:7029392"
    ],
    "tgn:id":7319904,
    "tgn:name":"Alert, Isla",
    "tgn:placetype":[
        "aat:300008791"
    ]
},
  "bbox": [],
  "geometry": {"coordinates":[-74.683333,-47.95],"type":"Point"}
}