{
  "id": 7366490,
  "type": "Feature",
  "properties": {
    "tgn:hierarchy":[
        "tgn:7366490",
        "tgn:1001836",
        "tgn:1000001",
        "tgn:7005560",
        "tgn:7029392"
    ],
    "tgn:id":7366490,
    "tgn:name":"El Tibur\u00f3n",
    "tgn:placetype":[
        "aat:300266554",
        "aat:300008699"
    ]
},
  "bbox": [],
  "geometry": {"coordinates":[-109.833333,22.916667],"type":"Point"}
}