{
  "id": 1030056,
  "type": "Feature",
  "properties": {
    "tgn:hierarchy":[
        "tgn:1030056",
        "tgn:7002445",
        "tgn:7019021",
        "tgn:1000003",
        "tgn:7008591",
        "tgn:7029392"
    ],
    "tgn:id":1030056,
    "tgn:name:en":"Midsomer Norton",
    "tgn:placetype":[
        "aat:300008347"
    ]
},
  "bbox": [],
  "geometry": {"coordinates":[-2.490556,51.284444],"type":"Point"}
}