{
  "id": 7276020,
  "type": "Feature",
  "properties": {
    "tgn:hierarchy":[
        "tgn:7276020",
        "tgn:1001768",
        "tgn:1000049",
        "tgn:1000002",
        "tgn:7029392"
    ],
    "tgn:id":7276020,
    "tgn:name":"Tocadillo, Estero del",
    "tgn:placetype":[
        "aat:300008699"
    ]
},
  "bbox": [],
  "geometry": {"coordinates":[-70.233333,-32.65],"type":"Point"}
}