{
  "id": 7291122,
  "type": "Feature",
  "properties": {
    "tgn:hierarchy":[
        "tgn:7291122",
        "tgn:1001699",
        "tgn:1000049",
        "tgn:1000002",
        "tgn:7029392"
    ],
    "tgn:id":7291122,
    "tgn:name":"Futronhu\u00e9",
    "tgn:placetype":[
        "aat:300000206"
    ]
},
  "bbox": [],
  "geometry": {"coordinates":[-72.466667,-40.083333],"type":"Point"}
}