{
  "id": 2189845,
  "type": "Feature",
  "properties": {
    "tgn:hierarchy":[
        "tgn:2189845",
        "tgn:1000001",
        "tgn:7012149",
        "tgn:7007157",
        "tgn:1002956",
        "tgn:7029392"
    ],
    "tgn:id":2189845,
    "tgn:name":"Bowhay Ditch",
    "tgn:placetype":[
        "aat:300006075"
    ]
},
  "bbox": [],
  "geometry": {"coordinates":[-119.2667,36.5167],"type":"Point"}
}