{
  "id": 1137217,
  "type": "Feature",
  "properties": {
    "tgn:hierarchy":[
        "tgn:1137217",
        "tgn:1000004",
        "tgn:7011478",
        "tgn:7006655",
        "tgn:7029392"
    ],
    "tgn:id":1137217,
    "tgn:name":"Aral",
    "tgn:placetype":[
        "aat:300008347"
    ]
},
  "bbox": [],
  "geometry": {"coordinates":[72.6667,42.5333],"type":"Point"}
}