{
  "id": 7008211,
  "type": "Feature",
  "properties": {
    "tgn:hierarchy":[
        "tgn:7008211",
        "tgn:7002872",
        "tgn:1000003",
        "tgn:1000070",
        "tgn:7029392"
    ],
    "tgn:id":7008211,
    "tgn:name":"Cherbourg",
    "tgn:placetype":[
        "aat:300008347",
        "aat:300387275",
        "aat:300008375",
        "aat:300387302",
        "aat:300120599"
    ]
},
  "bbox": [],
  "geometry": {"coordinates":[-1.6167,49.6333],"type":"Point"}
}