{
  "id": 1051367,
  "type": "Feature",
  "properties": {
    "tgn:hierarchy":[
        "tgn:1051367",
        "tgn:1000004",
        "tgn:7011589",
        "tgn:7018214",
        "tgn:7002435",
        "tgn:7029392"
    ],
    "tgn:id":1051367,
    "tgn:name":"Chik",
    "tgn:placetype":[
        "aat:300008347"
    ]
},
  "bbox": [],
  "geometry": {"coordinates":[82.4833,55.0167],"type":"Point"}
}