{
  "id": 2523963,
  "type": "Feature",
  "properties": {
    "tgn:hierarchy":[
        "tgn:2523963",
        "tgn:1000001",
        "tgn:2001412",
        "tgn:7012149",
        "tgn:7007526",
        "tgn:7029392"
    ],
    "tgn:id":2523963,
    "tgn:name":"Morena Ridge",
    "tgn:placetype":[
        "aat:300266640"
    ]
},
  "bbox": [],
  "geometry": {"coordinates":[-117.2167,37.7333],"type":"Point"}
}