{
  "id": 7487251,
  "type": "Feature",
  "properties": {
    "tgn:hierarchy":[
        "tgn:7487251",
        "tgn:1000004",
        "tgn:7004300",
        "tgn:1000141",
        "tgn:7029392"
    ],
    "tgn:id":7487251,
    "tgn:name":"Lintou Shi",
    "tgn:placetype":[
        "aat:300011692"
    ]
},
  "bbox": [],
  "geometry": {"coordinates":[119.65,23.533333],"type":"Point"}
}