<<<<<<< HEAD
{
  "id": 7487251,
  "type": "Feature",
  "properties": {
    "tgn:hierarchy":[
        "tgn:7487251",
        "tgn:1000004",
        "tgn:7004300",
        "tgn:1000141",
        "tgn:7029392"
    ],
    "tgn:id":7487251,
    "tgn:name":"Lintou Shi",
    "tgn:placetype":[
        "aat:300011692"
    ]
},
  "bbox": [],
  "geometry": {"coordinates":[119.65,23.533333],"type":"Point"}
}
=======
{"geometry":{"type":"Point","coordinates":[119.650000,23.533333]},"type":"Feature","properties":{"hierarchy":["tgn:7487251","tgn:1000004","tgn:7004300","tgn:1000141","tgn:7029392"],"placetype":["aat:300011692"],"id":7487251,"name:xx":"Lintou Shi"}}
>>>>>>> 03f74aca74312dbeaf24d7e61306dd6a786dc3d0
