{
  "id": 2579491,
  "type": "Feature",
  "properties": {
    "tgn:hierarchy":[
        "tgn:2579491",
        "tgn:1000001",
        "tgn:7012149",
        "tgn:2000474",
        "tgn:7007250",
        "tgn:7029392"
    ],
    "tgn:id":2579491,
    "tgn:name":"Picket Corral Canyon",
    "tgn:placetype":[
        "aat:300008761"
    ]
},
  "bbox": [],
  "geometry": {"coordinates":[-116.4167,43.8667],"type":"Point"}
}