<<<<<<< HEAD
{
  "id": 2333559,
  "type": "Feature",
  "properties": {
    "tgn:hierarchy":[
        "tgn:2333559",
        "tgn:1000001",
        "tgn:7012149",
        "tgn:2001720",
        "tgn:7007708",
        "tgn:7029392"
    ],
    "tgn:id":2333559,
    "tgn:name":"Folsoms Spring",
    "tgn:placetype":[
        "aat:300008697"
    ]
},
  "bbox": [],
  "geometry": {"coordinates":[-118.4667,45.4],"type":"Point"}
}
=======
{"geometry":{"type":"Point","coordinates":[-118.466700,45.400000]},"type":"Feature","properties":{"hierarchy":["tgn:2333559","tgn:1000001","tgn:7012149","tgn:2001720","tgn:7007708","tgn:7029392"],"placetype":["aat:300008697"],"id":2333559,"name:xx":"Folsoms Spring"}}
>>>>>>> 03f74aca74312dbeaf24d7e61306dd6a786dc3d0
