{
  "id": 2204259,
  "type": "Feature",
  "properties": {
    "tgn:hierarchy":[
        "tgn:2204259",
        "tgn:1000001",
        "tgn:2001339",
        "tgn:7012149",
        "tgn:7007525",
        "tgn:7029392"
    ],
    "tgn:id":2204259,
    "tgn:name":"Buffalo",
    "tgn:placetype":[
        "aat:300008347"
    ]
},
  "bbox": [],
  "geometry": {"coordinates":[-99.8333,40.9833],"type":"Point"}
}