{
  "id": 7398640,
  "type": "Feature",
  "properties": {
    "tgn:hierarchy":[
        "tgn:7398640",
        "tgn:1000001",
        "tgn:7005593",
        "tgn:7005560",
        "tgn:7029392"
    ],
    "tgn:id":7398640,
    "tgn:name":"Pedro Vega",
    "tgn:placetype":[
        "aat:300008347"
    ]
},
  "bbox": [],
  "geometry": {"coordinates":[-99.945833,20.690278],"type":"Point"}
}