{
  "id": 2758662,
  "type": "Feature",
  "properties": {
    "tgn:hierarchy":[
        "tgn:2758662",
        "tgn:1000001",
        "tgn:7012149",
        "tgn:1002943",
        "tgn:7007708",
        "tgn:7029392"
    ],
    "tgn:id":2758662,
    "tgn:name":"West Creek",
    "tgn:placetype":[
        "aat:300008706"
    ]
},
  "bbox": [],
  "geometry": {"coordinates":[-123.85,45.2667],"type":"Point"}
}