{
  "id": 7547280,
  "type": "Feature",
  "properties": {
    "tgn:hierarchy":[
        "tgn:7547280",
        "tgn:1000004",
        "tgn:1001869",
        "tgn:7000198",
        "tgn:7029392"
    ],
    "tgn:id":7547280,
    "tgn:name:en":"Arn\u0101la",
    "tgn:placetype":[
        "aat:300008347"
    ]
},
  "bbox": [],
  "geometry": {"coordinates":[73.083333,20.416667],"type":"Point"}
}