{
  "id": 7277544,
  "type": "Feature",
  "properties": {
    "tgn:hierarchy":[
        "tgn:7277544",
        "tgn:1001637",
        "tgn:1000049",
        "tgn:1000002",
        "tgn:7029392"
    ],
    "tgn:id":7277544,
    "tgn:name":"La Bomba, Caleta",
    "tgn:placetype":[
        "aat:300132317"
    ]
},
  "bbox": [],
  "geometry": {"coordinates":[-73.104167,-36.716667],"type":"Point"}
}