<<<<<<< HEAD
{
  "id": 7058041,
  "type": "Feature",
  "properties": {
    "tgn:hierarchy":[
        "tgn:7058041",
        "tgn:1003432",
        "tgn:1000003",
        "tgn:7003240",
        "tgn:1000080",
        "tgn:7029392"
    ],
    "tgn:id":7058041,
    "tgn:name":"Aquaviva Picena",
    "tgn:placetype":[
        "aat:300008347"
    ]
},
  "bbox": [],
  "geometry": {"coordinates":[13.816667,42.95],"type":"Point"}
}
=======
{"geometry":{"type":"Point","coordinates":[13.816667,42.950000]},"type":"Feature","properties":{"hierarchy":["tgn:7058041","tgn:1003432","tgn:1000003","tgn:7003240","tgn:1000080","tgn:7029392"],"placetype":["aat:300008347"],"id":7058041,"name:xx":"Aquaviva Picena"}}
>>>>>>> 03f74aca74312dbeaf24d7e61306dd6a786dc3d0
