{
  "id": 2206092,
  "type": "Feature",
  "properties": {
    "tgn:hierarchy":[
        "tgn:2206092",
        "tgn:1000001",
        "tgn:7012149",
        "tgn:2000490",
        "tgn:7007250",
        "tgn:7029392"
    ],
    "tgn:id":2206092,
    "tgn:name":"Bull Spring",
    "tgn:placetype":[
        "aat:300008697"
    ]
},
  "bbox": [],
  "geometry": {"coordinates":[-112.4333,42.5167],"type":"Point"}
}