{
  "id": 5002469,
  "type": "Feature",
  "properties": {
    "tgn:hierarchy":[
        "tgn:5002469",
        "tgn:7003139",
        "tgn:1000003",
        "tgn:7003080",
        "tgn:1000080",
        "tgn:7029392"
    ],
    "tgn:id":5002469,
    "tgn:name":"Vasanello",
    "tgn:placetype":[
        "aat:300008347"
    ]
},
  "bbox": [],
  "geometry": {"coordinates":[12.35,42.416667],"type":"Point"}
}