{
  "id": 7154850,
  "type": "Feature",
  "properties": {
    "tgn:hierarchy":[
        "tgn:7154850",
        "tgn:7003669",
        "tgn:1000003",
        "tgn:7000084",
        "tgn:7029392"
    ],
    "tgn:id":7154850,
    "tgn:name":"Kesselweiher",
    "tgn:placetype":[
        "aat:300008688"
    ]
},
  "bbox": [],
  "geometry": {"coordinates":[11.316667,49.25],"type":"Point"}
}