{
  "id": 7510030,
  "type": "Feature",
  "properties": {
    "tgn:hierarchy":[
        "tgn:7510030",
        "tgn:1008380",
        "tgn:7520093",
        "tgn:1000226",
        "tgn:1000006",
        "tgn:7029392"
    ],
    "tgn:id":7510030,
    "tgn:name:en":"Te Mara Stream",
    "tgn:placetype":[
        "aat:300008699"
    ]
},
  "bbox": [],
  "geometry": {"coordinates":[175.616667,-40.816667],"type":"Point"}
}