{
  "id": 2427858,
  "type": "Feature",
  "properties": {
    "tgn:hierarchy":[
        "tgn:2427858",
        "tgn:1000001",
        "tgn:7012149",
        "tgn:2001440",
        "tgn:7007566",
        "tgn:7029392"
    ],
    "tgn:id":2427858,
    "tgn:name":"Jowell Workings",
    "tgn:placetype":[
        "aat:300000390"
    ]
},
  "bbox": [],
  "geometry": {"coordinates":[-108.4833,31.8333],"type":"Point"}
}