{
  "id": 2211296,
  "type": "Feature",
  "properties": {
    "tgn:hierarchy":[
        "tgn:2211296",
        "tgn:1000001",
        "tgn:7012149",
        "tgn:2002363",
        "tgn:7007922",
        "tgn:7029392"
    ],
    "tgn:id":2211296,
    "tgn:name":"Butte Des Morts, Lake",
    "tgn:placetype":[
        "aat:300008680"
    ]
},
  "bbox": [],
  "geometry": {"coordinates":[-88.6333,44.0667],"type":"Point"}
}