{
  "id": 7168219,
  "type": "Feature",
  "properties": {
    "tgn:hierarchy":[
        "tgn:7168219",
        "tgn:7003692",
        "tgn:1000003",
        "tgn:7000084",
        "tgn:7029392"
    ],
    "tgn:id":7168219,
    "tgn:name":"Heckfeld",
    "tgn:placetype":[
        "aat:300008347"
    ]
},
  "bbox": [],
  "geometry": {"coordinates":[9.633333,49.55],"type":"Point"}
}