{
  "id": 2781853,
  "type": "Feature",
  "properties": {
    "tgn:hierarchy":[
        "tgn:2781853",
        "tgn:1000001",
        "tgn:7012149",
        "tgn:2000560",
        "tgn:7007252",
        "tgn:7029392"
    ],
    "tgn:id":2781853,
    "tgn:name":"Woods Ditch",
    "tgn:placetype":[
        "aat:300006075"
    ]
},
  "bbox": [],
  "geometry": {"coordinates":[-87.45,38.0667],"type":"Point"}
}