{
  "id": 7082640,
  "type": "Feature",
  "properties": {
    "tgn:hierarchy":[
        "tgn:7082640",
        "tgn:1000003",
        "tgn:7003676",
        "tgn:7000084",
        "tgn:7029392"
    ],
    "tgn:id":7082640,
    "tgn:name":"Wiltshausen",
    "tgn:placetype":[
        "aat:300008347"
    ]
},
  "bbox": [],
  "geometry": {"coordinates":[7.516667,53.216667],"type":"Point"}
}