{
  "id": 2760936,
  "type": "Feature",
  "properties": {
    "tgn:hierarchy":[
        "tgn:2760936",
        "tgn:1000001",
        "tgn:7012149",
        "tgn:7007523",
        "tgn:7029392"
    ],
    "tgn:id":2760936,
    "tgn:name":"West Honey Creek",
    "tgn:placetype":[
        "aat:300008706"
    ]
},
  "bbox": [],
  "geometry": {"coordinates":[-93.4667,40.4333],"type":"Point"}
}