{
  "id": 2492454,
  "type": "Feature",
  "properties": {
    "tgn:hierarchy":[
        "tgn:2492454",
        "tgn:1000001",
        "tgn:7012149",
        "tgn:1002798",
        "tgn:7007252",
        "tgn:7029392"
    ],
    "tgn:id":2492454,
    "tgn:name":"Marian Manor",
    "tgn:placetype":[
        "aat:300008347"
    ]
},
  "bbox": [],
  "geometry": {"coordinates":[-87.0833,41.4667],"type":"Point"}
}