{
  "id": 2411235,
  "type": "Feature",
  "properties": {
    "tgn:hierarchy":[
        "tgn:2411235",
        "tgn:1000001",
        "tgn:7012149",
        "tgn:7007157",
        "tgn:2000189",
        "tgn:7029392"
    ],
    "tgn:id":2411235,
    "tgn:name":"Indian Girl Mine",
    "tgn:placetype":[
        "aat:300000390"
    ]
},
  "bbox": [],
  "geometry": {"coordinates":[-122.6167,41.8333],"type":"Point"}
}