{
  "id": 7351751,
  "type": "Feature",
  "properties": {
    "tgn:hierarchy":[
        "tgn:7351751",
        "tgn:1000001",
        "tgn:7005599",
        "tgn:7005560",
        "tgn:7029392"
    ],
    "tgn:id":7351751,
    "tgn:name":"Arroyo Fr\u00edo",
    "tgn:placetype":[
        "aat:300008347"
    ]
},
  "bbox": [],
  "geometry": {"coordinates":[-96.75,19.95],"type":"Point"}
}