{
  "id": 7407233,
  "type": "Feature",
  "properties": {
    "tgn:hierarchy":[
        "tgn:7407233",
        "tgn:1000001",
        "tgn:1001906",
        "tgn:7005560",
        "tgn:7029392"
    ],
    "tgn:id":7407233,
    "tgn:name":"Ixtitahua",
    "tgn:placetype":[
        "aat:300008347"
    ]
},
  "bbox": [],
  "geometry": {"coordinates":[-105.345833,22.7125],"type":"Point"}
}