{
  "id": 7390645,
  "type": "Feature",
  "properties": {
    "tgn:hierarchy":[
        "tgn:7390645",
        "tgn:1000001",
        "tgn:7005596",
        "tgn:7005560",
        "tgn:7029392"
    ],
    "tgn:id":7390645,
    "tgn:name":"San Agust\u00edn",
    "tgn:placetype":[
        "aat:300008347"
    ]
},
  "bbox": [],
  "geometry": {"coordinates":[-91.65,17.633333],"type":"Point"}
}