{
  "id": 2537856,
  "type": "Feature",
  "properties": {
    "tgn:hierarchy":[
        "tgn:2537856",
        "tgn:1000001",
        "tgn:7012149",
        "tgn:2001307",
        "tgn:7007524",
        "tgn:7029392"
    ],
    "tgn:id":2537856,
    "tgn:name":"Nellies Twin Buttes",
    "tgn:placetype":[
        "aat:300008798"
    ]
},
  "bbox": [],
  "geometry": {"coordinates":[-109.6167,45.3833],"type":"Point"}
}