{
  "id": 2232106,
  "type": "Feature",
  "properties": {
    "tgn:hierarchy":[
        "tgn:2232106",
        "tgn:1000001",
        "tgn:7012149",
        "tgn:1002742",
        "tgn:7007920",
        "tgn:7029392"
    ],
    "tgn:id":2232106,
    "tgn:name":"Champneys Slough Stream",
    "tgn:placetype":[
        "aat:300008699"
    ]
},
  "bbox": [],
  "geometry": {"coordinates":[-119.6833,48.9333],"type":"Point"}
}