{
  "id": 7026568,
  "type": "Feature",
  "properties": {
    "tgn:hierarchy":[
        "tgn:7026568",
        "tgn:7002445",
        "tgn:1000003",
        "tgn:7008132",
        "tgn:7008591",
        "tgn:7029392"
    ],
    "tgn:id":7026568,
    "tgn:name":"Boxwell",
    "tgn:placetype":[
        "aat:300008347",
        "aat:300008372"
    ]
},
  "bbox": [],
  "geometry": {"coordinates":[-2.2667,51.6333],"type":"Point"}
}