{
  "id": 2556717,
  "type": "Feature",
  "properties": {
    "tgn:hierarchy":[
        "tgn:2556717",
        "tgn:1000001",
        "tgn:1002241",
        "tgn:7012149",
        "tgn:7007251",
        "tgn:7029392"
    ],
    "tgn:id":2556717,
    "tgn:name":"Old Channel Mud Creek",
    "tgn:placetype":[
        "aat:300008706"
    ]
},
  "bbox": [],
  "geometry": {"coordinates":[-90.3833,39.8667],"type":"Point"}
}