{
  "id": 2624587,
  "type": "Feature",
  "properties": {
    "tgn:hierarchy":[
        "tgn:2624587",
        "tgn:1000001",
        "tgn:7012149",
        "tgn:2002374",
        "tgn:7007923",
        "tgn:7029392"
    ],
    "tgn:id":2624587,
    "tgn:name":"Rock Ridge",
    "tgn:placetype":[
        "aat:300266640"
    ]
},
  "bbox": [],
  "geometry": {"coordinates":[-106.55,43.6667],"type":"Point"}
}