{
  "id": 1036311,
  "type": "Feature",
  "properties": {
    "tgn:hierarchy":[
        "tgn:1036311",
        "tgn:7002871",
        "tgn:1000003",
        "tgn:1000070",
        "tgn:7029392"
    ],
    "tgn:id":1036311,
    "tgn:name":"Yzeure",
    "tgn:placetype":[
        "aat:300008347"
    ]
},
  "bbox": [],
  "geometry": {"coordinates":[3.35,46.5667],"type":"Point"}
}