{
  "id": 2662282,
  "type": "Feature",
  "properties": {
    "tgn:hierarchy":[
        "tgn:2662282",
        "tgn:1000001",
        "tgn:7012149",
        "tgn:1002636",
        "tgn:7007708",
        "tgn:7029392"
    ],
    "tgn:id":2662282,
    "tgn:name":"Sidney Ditch",
    "tgn:placetype":[
        "aat:300006075"
    ]
},
  "bbox": [],
  "geometry": {"coordinates":[-122.95,44.7333],"type":"Point"}
}