{
  "id": 7583614,
  "type": "Feature",
  "properties": {
    "tgn:hierarchy":[
        "tgn:7583614",
        "tgn:1000004",
        "tgn:7000198",
        "tgn:1001894",
        "tgn:7029392"
    ],
    "tgn:id":7583614,
    "tgn:name:en":"Kheri",
    "tgn:placetype":[
        "aat:300008347"
    ]
},
  "bbox": [],
  "geometry": {"coordinates":[78.967049,25.205483],"type":"Point"}
}