{
  "id": 2516719,
  "type": "Feature",
  "properties": {
    "tgn:hierarchy":[
        "tgn:2516719",
        "tgn:1000001",
        "tgn:7012149",
        "tgn:2002371",
        "tgn:7007923",
        "tgn:7029392"
    ],
    "tgn:id":2516719,
    "tgn:name":"Miners Delight Mine",
    "tgn:placetype":[
        "aat:300000390"
    ]
},
  "bbox": [],
  "geometry": {"coordinates":[-108.6833,42.5167],"type":"Point"}
}