{
  "id": 2116355,
  "type": "Feature",
  "properties": {
    "tgn:hierarchy":[
        "tgn:2116355",
        "tgn:1000001",
        "tgn:7012149",
        "tgn:1002742",
        "tgn:7007920",
        "tgn:7029392"
    ],
    "tgn:id":2116355,
    "tgn:name":"Nespelem",
    "tgn:placetype":[
        "aat:300008347"
    ]
},
  "bbox": [],
  "geometry": {"coordinates":[-118.9667,48.1667],"type":"Point"}
}