{
  "id": 2218902,
  "type": "Feature",
  "properties": {
    "tgn:hierarchy":[
        "tgn:2218902",
        "tgn:7002659",
        "tgn:1000001",
        "tgn:7012149",
        "tgn:2000028",
        "tgn:7029392"
    ],
    "tgn:id":2218902,
    "tgn:name":"Caney Branch",
    "tgn:placetype":[
        "aat:300008699"
    ]
},
  "bbox": [],
  "geometry": {"coordinates":[-87.4333,33.6167],"type":"Point"}
}