{
  "id": 2784783,
  "type": "Feature",
  "properties": {
    "tgn:hierarchy":[
        "tgn:2784783",
        "tgn:1000001",
        "tgn:7012149",
        "tgn:7014510",
        "tgn:7007920",
        "tgn:7029392"
    ],
    "tgn:id":2784783,
    "tgn:name":"Yellow Bluff Reef",
    "tgn:placetype":[
        "aat:300132348"
    ]
},
  "bbox": [],
  "geometry": {"coordinates":[-122.65,48.5167],"type":"Point"}
}