{
  "id": 2198934,
  "type": "Feature",
  "properties": {
    "tgn:hierarchy":[
        "tgn:2198934",
        "tgn:1000001",
        "tgn:2000201",
        "tgn:7012149",
        "tgn:7007158",
        "tgn:7029392"
    ],
    "tgn:id":2198934,
    "tgn:name":"Bruce Mine",
    "tgn:placetype":[
        "aat:300000390"
    ]
},
  "bbox": [],
  "geometry": {"coordinates":[-105.5667,39.7167],"type":"Point"}
}