{
  "id": 2169479,
  "type": "Feature",
  "properties": {
    "tgn:hierarchy":[
        "tgn:2169479",
        "tgn:7002659",
        "tgn:1000001",
        "tgn:7012149",
        "tgn:2000031",
        "tgn:7029392"
    ],
    "tgn:id":2169479,
    "tgn:name":"Big Log Shoals",
    "tgn:placetype":[
        "aat:300387099",
        "aat:300132348"
    ]
},
  "bbox": [],
  "geometry": {"coordinates":[-87.8333,32.8333],"type":"Point"}
}