{
  "id": 2350478,
  "type": "Feature",
  "properties": {
    "tgn:hierarchy":[
        "tgn:2350478",
        "tgn:1000001",
        "tgn:7012149",
        "tgn:7014185",
        "tgn:7007710",
        "tgn:7029392"
    ],
    "tgn:id":2350478,
    "tgn:name":"Gist Run",
    "tgn:placetype":[
        "aat:300008699"
    ]
},
  "bbox": [],
  "geometry": {"coordinates":[-79.6333,39.9167],"type":"Point"}
}