{
  "id": 1136787,
  "type": "Feature",
  "properties": {
    "tgn:hierarchy":[
        "tgn:1136787",
        "tgn:1000003",
        "tgn:1000070",
        "tgn:7002897",
        "tgn:7029392"
    ],
    "tgn:id":1136787,
    "tgn:name":"Craponne",
    "tgn:placetype":[
        "aat:300008347"
    ]
},
  "bbox": [],
  "geometry": {"coordinates":[4.7167,45.7333],"type":"Point"}
}