<<<<<<< HEAD
{
  "id": 2159127,
  "type": "Feature",
  "properties": {
    "tgn:hierarchy":[
        "tgn:2159127",
        "tgn:1000001",
        "tgn:1002665",
        "tgn:7012149",
        "tgn:7007517",
        "tgn:7029392"
    ],
    "tgn:id":2159127,
    "tgn:name":"Bedford Meadow",
    "tgn:placetype":[
        "aat:300008905"
    ]
},
  "bbox": [],
  "geometry": {"coordinates":[-71.3,42.5],"type":"Point"}
}
=======
{"geometry":{"type":"Point","coordinates":[-71.300000,42.500000]},"type":"Feature","properties":{"hierarchy":["tgn:2159127","tgn:1000001","tgn:1002665","tgn:7012149","tgn:7007517","tgn:7029392"],"placetype":["aat:300008905"],"id":2159127,"name:xx":"Bedford Meadow"}}
>>>>>>> 03f74aca74312dbeaf24d7e61306dd6a786dc3d0
