{
  "id": 2302172,
  "type": "Feature",
  "properties": {
    "tgn:hierarchy":[
        "tgn:2302172",
        "tgn:1000001",
        "tgn:7012149",
        "tgn:1002995",
        "tgn:7007710",
        "tgn:7029392"
    ],
    "tgn:id":2302172,
    "tgn:name":"Dutch Fork Lake",
    "tgn:placetype":[
        "aat:300006191"
    ]
},
  "bbox": [],
  "geometry": {"coordinates":[-80.4667,40.1333],"type":"Point"}
}