{
  "id": 2593437,
  "type": "Feature",
  "properties": {
    "tgn:hierarchy":[
        "tgn:2593437",
        "tgn:7006450",
        "tgn:1000001",
        "tgn:7012149",
        "tgn:2124002",
        "tgn:7029392"
    ],
    "tgn:id":2593437,
    "tgn:name":"Porcupine Bay",
    "tgn:placetype":[
        "aat:300132316"
    ]
},
  "bbox": [],
  "geometry": {"coordinates":[-136.35,57.8167],"type":"Point"}
}