{
  "id": 7402409,
  "type": "Feature",
  "properties": {
    "tgn:hierarchy":[
        "tgn:7402409",
        "tgn:1000001",
        "tgn:1001937",
        "tgn:7005560",
        "tgn:7029392"
    ],
    "tgn:id":7402409,
    "tgn:name":"Altos de Sevilla",
    "tgn:placetype":[
        "aat:300008347"
    ]
},
  "bbox": [],
  "geometry": {"coordinates":[-88.666667,18.85],"type":"Point"}
}