{
  "id": 7396617,
  "type": "Feature",
  "properties": {
    "tgn:hierarchy":[
        "tgn:7396617",
        "tgn:7005584",
        "tgn:1000001",
        "tgn:7005560",
        "tgn:7029392"
    ],
    "tgn:id":7396617,
    "tgn:name":"Santa Rita",
    "tgn:placetype":[
        "aat:300007783"
    ]
},
  "bbox": [],
  "geometry": {"coordinates":[-100.783333,20.566667],"type":"Point"}
}