{
  "id": 2530780,
  "type": "Feature",
  "properties": {
    "tgn:hierarchy":[
        "tgn:2530780",
        "tgn:1000001",
        "tgn:7012149",
        "tgn:1002528",
        "tgn:7007710",
        "tgn:7029392"
    ],
    "tgn:id":2530780,
    "tgn:name":"Muddy Run",
    "tgn:placetype":[
        "aat:300008699"
    ]
},
  "bbox": [],
  "geometry": {"coordinates":[-77.4333,40.5833],"type":"Point"}
}