{
  "id": 7491415,
  "type": "Feature",
  "properties": {
    "tgn:hierarchy":[
        "tgn:7491415",
        "tgn:1000004",
        "tgn:1000454",
        "tgn:1000141",
        "tgn:7029392"
    ],
    "tgn:id":7491415,
    "tgn:name":"Shuangxing Cun",
    "tgn:placetype":[
        "aat:300387173"
    ]
},
  "bbox": [],
  "geometry": {"coordinates":[121.64057,25.173614],"type":"Point"}
}