{
  "id": 7535067,
  "type": "Feature",
  "properties": {
    "tgn:hierarchy":[
        "tgn:7535067",
        "tgn:7001242",
        "tgn:7016833",
        "tgn:7001312",
        "tgn:7029392"
    ],
    "tgn:id":7535067,
    "tgn:name:en":"Kafr Ab\u016b Jund\u012b",
    "tgn:placetype":[
        "aat:300008347"
    ]
},
  "bbox": [],
  "geometry": {"coordinates":[30.934098,30.913455],"type":"Point"}
}