{
  "id": 7026855,
  "type": "Feature",
  "properties": {
    "tgn:hierarchy":[
        "tgn:7026855",
        "tgn:7002445",
        "tgn:1000003",
        "tgn:7008139",
        "tgn:7008591",
        "tgn:7029392"
    ],
    "tgn:id":7026855,
    "tgn:name:en":"Goodworth Clatford",
    "tgn:placetype":[
        "aat:300008347",
        "aat:300008372"
    ]
},
  "bbox": [],
  "geometry": {"coordinates":[-1.483333,51.166667],"type":"Point"}
}