{
  "id": 7553497,
  "type": "Feature",
  "properties": {
    "tgn:hierarchy":[
        "tgn:7553497",
        "tgn:1000004",
        "tgn:7000198",
        "tgn:1001882",
        "tgn:7029392"
    ],
    "tgn:id":7553497,
    "tgn:name:en":"M\u0101shal",
    "tgn:placetype":[
        "aat:300008347"
    ]
},
  "bbox": [],
  "geometry": {"coordinates":[76.233333,17.333333],"type":"Point"}
}