{
  "id": 7100461,
  "type": "Feature",
  "properties": {
    "tgn:hierarchy":[
        "tgn:7100461",
        "tgn:1000003",
        "tgn:7003677",
        "tgn:7000084",
        "tgn:7029392"
    ],
    "tgn:id":7100461,
    "tgn:name":"Sandforth",
    "tgn:placetype":[
        "aat:300387200"
    ]
},
  "bbox": [],
  "geometry": {"coordinates":[8.35,52.016667],"type":"Point"}
}