{
  "id": 7270058,
  "type": "Feature",
  "properties": {
    "tgn:hierarchy":[
        "tgn:7270058",
        "tgn:7003614",
        "tgn:1000003",
        "tgn:7016845",
        "tgn:7029392"
    ],
    "tgn:id":7270058,
    "tgn:name:nl":"Moltmakersstuk",
    "tgn:placetype":[
        "aat:300387200"
    ]
},
  "bbox": [],
  "geometry": {"coordinates":[6.433333,53.116667],"type":"Point"}
}