{
  "id": 7019783,
  "type": "Feature",
  "properties": {
    "tgn:hierarchy":[
        "tgn:7019783",
        "tgn:1000001",
        "tgn:2002370",
        "tgn:7012149",
        "tgn:7007923",
        "tgn:7029392"
    ],
    "tgn:id":7019783,
    "tgn:name":"Basin Reservoir Number 2",
    "tgn:placetype":[
        "aat:300006191"
    ]
},
  "bbox": [],
  "geometry": {"coordinates":[-104.8333,44.5667],"type":"Point"}
}