<<<<<<< HEAD
{
  "id": 2405776,
  "type": "Feature",
  "properties": {
    "tgn:hierarchy":[
        "tgn:2405776",
        "tgn:7023902",
        "tgn:1000001",
        "tgn:7012149",
        "tgn:7007249",
        "tgn:7029392"
    ],
    "tgn:id":2405776,
    "tgn:name":"Huliilii Stream",
    "tgn:placetype":[
        "aat:300008699"
    ]
},
  "bbox": [],
  "geometry": {"coordinates":[-155.2,19.9333],"type":"Point"}
}
=======
{"geometry":{"type":"Point","coordinates":[-155.200000,19.933300]},"type":"Feature","properties":{"hierarchy":["tgn:2405776","tgn:7023902","tgn:1000001","tgn:7012149","tgn:7007249","tgn:7029392"],"placetype":["aat:300008699"],"id":2405776,"name:xx":"Huliilii Stream"}}
>>>>>>> 03f74aca74312dbeaf24d7e61306dd6a786dc3d0
