{
  "id": 2220558,
  "type": "Feature",
  "properties": {
    "tgn:hierarchy":[
        "tgn:2220558",
        "tgn:1000001",
        "tgn:7012149",
        "tgn:2000181",
        "tgn:7007157",
        "tgn:7029392"
    ],
    "tgn:id":2220558,
    "tgn:name":"Cape Ridge",
    "tgn:placetype":[
        "aat:300266640"
    ]
},
  "bbox": [],
  "geometry": {"coordinates":[-124.35,40.4333],"type":"Point"}
}