{
  "id": 2133908,
  "type": "Feature",
  "properties": {
    "tgn:hierarchy":[
        "tgn:2133908",
        "tgn:1000001",
        "tgn:7012149",
        "tgn:2001516",
        "tgn:7007709",
        "tgn:7029392"
    ],
    "tgn:id":2133908,
    "tgn:name":"Angelico Knob",
    "tgn:placetype":[
        "aat:300008798"
    ]
},
  "bbox": [],
  "geometry": {"coordinates":[-82.7167,35.9833],"type":"Point"}
}