{
  "id": 2228548,
  "type": "Feature",
  "properties": {
    "tgn:hierarchy":[
        "tgn:2228548",
        "tgn:1000001",
        "tgn:7012149",
        "tgn:2001973",
        "tgn:7007826",
        "tgn:7029392"
    ],
    "tgn:id":2228548,
    "tgn:name":"Cedar Creek",
    "tgn:placetype":[
        "aat:300008706"
    ]
},
  "bbox": [],
  "geometry": {"coordinates":[-95.6667,33.35],"type":"Point"}
}