{
  "id": 7036998,
  "type": "Feature",
  "properties": {
    "tgn:hierarchy":[
        "tgn:7036998",
        "tgn:7005869",
        "tgn:1000003",
        "tgn:7003237",
        "tgn:1000080",
        "tgn:7029392"
    ],
    "tgn:id":7036998,
    "tgn:name":"Villachiara",
    "tgn:placetype":[
        "aat:300008347"
    ]
},
  "bbox": [],
  "geometry": {"coordinates":[9.916667,45.35],"type":"Point"}
}