{
  "id": 7306345,
  "type": "Feature",
  "properties": {
    "tgn:hierarchy":[
        "tgn:7306345",
        "tgn:1001439",
        "tgn:1000003",
        "tgn:7002797",
        "tgn:1000095",
        "tgn:7029392"
    ],
    "tgn:id":7306345,
    "tgn:name":"Los Abejorros",
    "tgn:placetype":[
        "aat:300386846"
    ]
},
  "bbox": [],
  "geometry": {"coordinates":[-1.466667,37.466667],"type":"Point"}
}