{
  "id": 1115871,
  "type": "Feature",
  "properties": {
    "tgn:hierarchy":[
        "tgn:1115871",
        "tgn:1000001",
        "tgn:2000950",
        "tgn:7012149",
        "tgn:7007520",
        "tgn:7029392"
    ],
    "tgn:id":1115871,
    "tgn:name":"Charlevoix, Lake",
    "tgn:placetype":[
        "aat:300008680"
    ]
},
  "bbox": [],
  "geometry": {"coordinates":[-85.1333,45.2667],"type":"Point"}
}