{
  "id": 2411222,
  "type": "Feature",
  "properties": {
    "tgn:hierarchy":[
        "tgn:2411222",
        "tgn:1000001",
        "tgn:2001418",
        "tgn:7012149",
        "tgn:7007526",
        "tgn:7029392"
    ],
    "tgn:id":2411222,
    "tgn:name":"Indian Garden Creek",
    "tgn:placetype":[
        "aat:300008706"
    ]
},
  "bbox": [],
  "geometry": {"coordinates":[-116.5333,38.5833],"type":"Point"}
}