{
  "id": 2686501,
  "type": "Feature",
  "properties": {
    "tgn:hierarchy":[
        "tgn:2686501",
        "tgn:1000001",
        "tgn:7012149",
        "tgn:2001277",
        "tgn:7007524",
        "tgn:7029392"
    ],
    "tgn:id":2686501,
    "tgn:name":"Spring Creek",
    "tgn:placetype":[
        "aat:300008706"
    ]
},
  "bbox": [],
  "geometry": {"coordinates":[-112.9333,48.45],"type":"Point"}
}