{
  "id": 1134353,
  "type": "Feature",
  "properties": {
    "tgn:hierarchy":[
        "tgn:1134353",
        "tgn:1000001",
        "tgn:7012149",
        "tgn:2001719",
        "tgn:7007708",
        "tgn:7029392"
    ],
    "tgn:id":1134353,
    "tgn:name":"Rhea Creek",
    "tgn:placetype":[
        "aat:300008706"
    ]
},
  "bbox": [],
  "geometry": {"coordinates":[-119.3667,45.15],"type":"Point"}
}