{
  "id": 7512135,
  "type": "Feature",
  "properties": {
    "tgn:hierarchy":[
        "tgn:7512135",
        "tgn:1009227",
        "tgn:1000226",
        "tgn:7016822",
        "tgn:1000006",
        "tgn:7029392"
    ],
    "tgn:id":7512135,
    "tgn:name:en":"John o'Groats River",
    "tgn:placetype":[
        "aat:300008699"
    ]
},
  "bbox": [],
  "geometry": {"coordinates":[167.816667,-44.516667],"type":"Point"}
}