{
  "id": 7093122,
  "type": "Feature",
  "properties": {
    "tgn:hierarchy":[
        "tgn:7093122",
        "tgn:1000003",
        "tgn:7003678",
        "tgn:7000084",
        "tgn:7029392"
    ],
    "tgn:id":7093122,
    "tgn:name":"Schorr-Bach",
    "tgn:placetype":[
        "aat:300008699"
    ]
},
  "bbox": [],
  "geometry": {"coordinates":[8.716667,50.433333],"type":"Point"}
}