{
  "id": 7544138,
  "type": "Feature",
  "properties": {
    "tgn:hierarchy":[
        "tgn:7544138",
        "tgn:7001242",
        "tgn:7016833",
        "tgn:7001336",
        "tgn:7029392"
    ],
    "tgn:id":7544138,
    "tgn:name":"Khalb\u016b\u015fah, W\u0101d\u012b al",
    "tgn:placetype":[
        "aat:300379998"
    ]
},
  "bbox": [],
  "geometry": {"coordinates":[33.496111,29.433333],"type":"Point"}
}