{
  "id": 1076727,
  "type": "Feature",
  "properties": {
    "tgn:hierarchy":[
        "tgn:1076727",
        "tgn:1000004",
        "tgn:7000198",
        "tgn:1001977",
        "tgn:7029392"
    ],
    "tgn:id":1076727,
    "tgn:name:en":"R\u0101yna",
    "tgn:placetype":[
        "aat:300008347"
    ]
},
  "bbox": [],
  "geometry": {"coordinates":[87.898201,23.073019],"type":"Point"}
}