{
  "id": 2010782,
  "type": "Feature",
  "properties": {
    "tgn:hierarchy":[
        "tgn:2010782",
        "tgn:1000001",
        "tgn:7012149",
        "tgn:1002409",
        "tgn:7007157",
        "tgn:7029392"
    ],
    "tgn:id":2010782,
    "tgn:name":"Codora",
    "tgn:placetype":[
        "aat:300008347",
        "aat:300387210"
    ]
},
  "bbox": [],
  "geometry": {"coordinates":[-122.0167,39.45],"type":"Point"}
}