{
  "id": 1008936,
  "type": "Feature",
  "properties": {
    "tgn:hierarchy":[
        "tgn:1008936",
        "tgn:1001145",
        "tgn:1010330",
        "tgn:1000004",
        "tgn:1000135",
        "tgn:7029392"
    ],
    "tgn:id":1008936,
    "tgn:name":"Saluping Islandz",
    "tgn:placetype":[
        "aat:300008791"
    ]
},
  "bbox": [],
  "geometry": {"coordinates":[122.0167,6.3333],"type":"Point"}
}