{
  "id": 2341198,
  "type": "Feature",
  "properties": {
    "tgn:hierarchy":[
        "tgn:2341198",
        "tgn:1000001",
        "tgn:7012149",
        "tgn:7029392"
    ],
    "tgn:id":2341198,
    "tgn:name":"Frisco Canyon",
    "tgn:placetype":[
        "aat:300008761"
    ]
},
  "bbox": [],
  "geometry": {"coordinates":[-108.8667,33.25],"type":"Point"}
}