{
  "id": 2476178,
  "type": "Feature",
  "properties": {
    "tgn:hierarchy":[
        "tgn:2476178",
        "tgn:1000001",
        "tgn:7012149",
        "tgn:2001449",
        "tgn:7007566",
        "tgn:7029392"
    ],
    "tgn:id":2476178,
    "tgn:name":"Lumberton Prospect",
    "tgn:placetype":[
        "aat:300000390"
    ]
},
  "bbox": [],
  "geometry": {"coordinates":[-106.95,36.9167],"type":"Point"}
}