<<<<<<< HEAD
{
  "id": 7361318,
  "type": "Feature",
  "properties": {
    "tgn:hierarchy":[
        "tgn:7361318",
        "tgn:7005581",
        "tgn:1000001",
        "tgn:7005560",
        "tgn:7029392"
    ],
    "tgn:id":7361318,
    "tgn:name":"Rancho El Consuelo",
    "tgn:placetype":[
        "aat:300000241"
    ]
},
  "bbox": [],
  "geometry": {"coordinates":[-105.7,30.766667],"type":"Point"}
}
=======
{"geometry":{"type":"Point","coordinates":[-105.700000,30.766667]},"type":"Feature","properties":{"hierarchy":["tgn:7361318","tgn:7005581","tgn:1000001","tgn:7005560","tgn:7029392"],"placetype":["aat:300000241"],"id":7361318,"name:xx":"Rancho El Consuelo"}}
>>>>>>> 03f74aca74312dbeaf24d7e61306dd6a786dc3d0
