{
  "id": 2432144,
  "type": "Feature",
  "properties": {
    "tgn:hierarchy":[
        "tgn:2432144",
        "tgn:7006450",
        "tgn:1000001",
        "tgn:7012149",
        "tgn:2124005",
        "tgn:7029392"
    ],
    "tgn:id":2432144,
    "tgn:name":"Kay Creek",
    "tgn:placetype":[
        "aat:300008706"
    ]
},
  "bbox": [],
  "geometry": {"coordinates":[-154.6333,69.4167],"type":"Point"}
}