{
  "id": 2424697,
  "type": "Feature",
  "properties": {
    "tgn:hierarchy":[
        "tgn:2424697",
        "tgn:2002307",
        "tgn:1000001",
        "tgn:7012149",
        "tgn:7007922",
        "tgn:7029392"
    ],
    "tgn:id":2424697,
    "tgn:name":"Johnson Creek",
    "tgn:placetype":[
        "aat:300008706"
    ]
},
  "bbox": [],
  "geometry": {"coordinates":[-92.05,45.4667],"type":"Point"}
}