{
  "id": 7515340,
  "type": "Feature",
  "properties": {
    "tgn:hierarchy":[
        "tgn:7515340",
        "tgn:1009227",
        "tgn:1000226",
        "tgn:7520095",
        "tgn:1000006",
        "tgn:7029392"
    ],
    "tgn:id":7515340,
    "tgn:name:en":"Cedar Creek",
    "tgn:placetype":[
        "aat:300008699"
    ]
},
  "bbox": [],
  "geometry": {"coordinates":[173.033333,-41.516667],"type":"Point"}
}