{
  "id": 2562036,
  "type": "Feature",
  "properties": {
    "tgn:hierarchy":[
        "tgn:2562036",
        "tgn:1000001",
        "tgn:2000669",
        "tgn:7012149",
        "tgn:7007254",
        "tgn:7029392"
    ],
    "tgn:id":2562036,
    "tgn:name":"Otter Creek",
    "tgn:placetype":[
        "aat:300008706"
    ]
},
  "bbox": [],
  "geometry": {"coordinates":[-96.15,37.0167],"type":"Point"}
}