{
  "id": 7193541,
  "type": "Feature",
  "properties": {
    "tgn:hierarchy":[
        "tgn:7193541",
        "tgn:1000003",
        "tgn:7003678",
        "tgn:7000084",
        "tgn:7029392"
    ],
    "tgn:id":7193541,
    "tgn:name":"Frankershausen",
    "tgn:placetype":[
        "aat:300008347"
    ]
},
  "bbox": [],
  "geometry": {"coordinates":[9.916667,51.233333],"type":"Point"}
}