{
  "id": 2336482,
  "type": "Feature",
  "properties": {
    "tgn:hierarchy":[
        "tgn:2336482",
        "tgn:1000001",
        "tgn:7012149",
        "tgn:2002059",
        "tgn:7007826",
        "tgn:7029392"
    ],
    "tgn:id":2336482,
    "tgn:name":"Four Corner Windmill",
    "tgn:placetype":[
        "aat:300008347"
    ]
},
  "bbox": [],
  "geometry": {"coordinates":[-101.5833,31.2833],"type":"Point"}
}