<<<<<<< HEAD
{
  "id": 2159837,
  "type": "Feature",
  "properties": {
    "tgn:hierarchy":[
        "tgn:2159837",
        "tgn:1000001",
        "tgn:7012149",
        "tgn:7007712",
        "tgn:7029392"
    ],
    "tgn:id":2159837,
    "tgn:name":"Beech Creek",
    "tgn:placetype":[
        "aat:300008706"
    ]
},
  "bbox": [],
  "geometry": {"coordinates":[-81.7333,33.85],"type":"Point"}
}
=======
{"geometry":{"type":"Point","coordinates":[-81.733300,33.850000]},"type":"Feature","properties":{"hierarchy":["tgn:2159837","tgn:1000001","tgn:7012149","tgn:7007712","tgn:7029392"],"placetype":["aat:300008706"],"id":2159837,"name:xx":"Beech Creek"}}
>>>>>>> 03f74aca74312dbeaf24d7e61306dd6a786dc3d0
