{
  "id": 2340185,
  "type": "Feature",
  "properties": {
    "tgn:hierarchy":[
        "tgn:2340185",
        "tgn:1000001",
        "tgn:7012149",
        "tgn:2001510",
        "tgn:7007709",
        "tgn:7029392"
    ],
    "tgn:id":2340185,
    "tgn:name":"French Branch",
    "tgn:placetype":[
        "aat:300008699"
    ]
},
  "bbox": [],
  "geometry": {"coordinates":[-77.3333,35.0167],"type":"Point"}
}