{
  "id": 7519333,
  "type": "Feature",
  "properties": {
    "tgn:hierarchy":[
        "tgn:7519333",
        "tgn:1009227",
        "tgn:1000226",
        "tgn:1000006",
        "tgn:7016850",
        "tgn:7029392"
    ],
    "tgn:id":7519333,
    "tgn:name:en":"Allen River",
    "tgn:placetype":[
        "aat:300008699"
    ]
},
  "bbox": [],
  "geometry": {"coordinates":[172.283333,-41.466667],"type":"Point"}
}