{
  "id": 2106191,
  "type": "Feature",
  "properties": {
    "tgn:hierarchy":[
        "tgn:2106191",
        "tgn:1000001",
        "tgn:7012149",
        "tgn:2001985",
        "tgn:7007826",
        "tgn:7029392"
    ],
    "tgn:id":2106191,
    "tgn:name":"Muncy",
    "tgn:placetype":[
        "aat:300008347",
        "aat:300387210"
    ]
},
  "bbox": [],
  "geometry": {"coordinates":[-101.3833,34.05],"type":"Point"}
}