{
  "id": 2601245,
  "type": "Feature",
  "properties": {
    "tgn:hierarchy":[
        "tgn:2601245",
        "tgn:7006450",
        "tgn:1000001",
        "tgn:7012149",
        "tgn:7029392"
    ],
    "tgn:id":2601245,
    "tgn:name":"Puntilla Creek",
    "tgn:placetype":[
        "aat:300008706"
    ]
},
  "bbox": [],
  "geometry": {"coordinates":[-152.9333,62.0667],"type":"Point"}
}