{
  "id": 2520093,
  "type": "Feature",
  "properties": {
    "tgn:hierarchy":[
        "tgn:2520093",
        "tgn:1000001",
        "tgn:7014423",
        "tgn:7012149",
        "tgn:7007517",
        "tgn:7029392"
    ],
    "tgn:id":2520093,
    "tgn:name":"Molly Cove",
    "tgn:placetype":[
        "aat:300132316"
    ]
},
  "bbox": [],
  "geometry": {"coordinates":[-70.8167,41.6333],"type":"Point"}
}