<<<<<<< HEAD
{
  "id": 2702237,
  "type": "Feature",
  "properties": {
    "tgn:hierarchy":[
        "tgn:2702237",
        "tgn:1000001",
        "tgn:7012149",
        "tgn:7014287",
        "tgn:7007568",
        "tgn:7029392"
    ],
    "tgn:id":2702237,
    "tgn:name":"Sullivan Brook",
    "tgn:placetype":[
        "aat:300008699"
    ]
},
  "bbox": [],
  "geometry": {"coordinates":[-75.6167,43.4333],"type":"Point"}
}
=======
{"geometry":{"type":"Point","coordinates":[-75.616700,43.433300]},"type":"Feature","properties":{"hierarchy":["tgn:2702237","tgn:1000001","tgn:7012149","tgn:7014287","tgn:7007568","tgn:7029392"],"placetype":["aat:300008699"],"id":2702237,"name:xx":"Sullivan Brook"}}
>>>>>>> 03f74aca74312dbeaf24d7e61306dd6a786dc3d0
