{
  "id": 2702237,
  "type": "Feature",
  "properties": {
    "tgn:hierarchy":[
        "tgn:2702237",
        "tgn:1000001",
        "tgn:7012149",
        "tgn:7014287",
        "tgn:7007568",
        "tgn:7029392"
    ],
    "tgn:id":2702237,
    "tgn:name":"Sullivan Brook",
    "tgn:placetype":[
        "aat:300008699"
    ]
},
  "bbox": [],
  "geometry": {"coordinates":[-75.6167,43.4333],"type":"Point"}
}