{
  "id": 2690695,
  "type": "Feature",
  "properties": {
    "tgn:hierarchy":[
        "tgn:2690695",
        "tgn:1000001",
        "tgn:7012149",
        "tgn:2001028",
        "tgn:7007521",
        "tgn:7029392"
    ],
    "tgn:id":2690695,
    "tgn:name":"Stanchfield Creek",
    "tgn:placetype":[
        "aat:300008706"
    ]
},
  "bbox": [],
  "geometry": {"coordinates":[-93.4333,45.65],"type":"Point"}
}