<<<<<<< HEAD
{
  "id": 2259591,
  "type": "Feature",
  "properties": {
    "tgn:hierarchy":[
        "tgn:2259591",
        "tgn:1000001",
        "tgn:7012149",
        "tgn:2000898",
        "tgn:7007256",
        "tgn:7029392"
    ],
    "tgn:id":2259591,
    "tgn:name":"Couba Island",
    "tgn:placetype":[
        "aat:300008791"
    ]
},
  "bbox": [],
  "geometry": {"coordinates":[-90.2,29.8],"type":"Point"}
}
=======
{"geometry":{"type":"Point","coordinates":[-90.200000,29.800000]},"type":"Feature","properties":{"hierarchy":["tgn:2259591","tgn:1000001","tgn:7012149","tgn:2000898","tgn:7007256","tgn:7029392"],"placetype":["aat:300008791"],"id":2259591,"name:xx":"Couba Island"}}
>>>>>>> 03f74aca74312dbeaf24d7e61306dd6a786dc3d0
