{
  "id": 2214282,
  "type": "Feature",
  "properties": {
    "tgn:hierarchy":[
        "tgn:2214282",
        "tgn:1000001",
        "tgn:7006451",
        "tgn:7012149",
        "tgn:2000100",
        "tgn:7029392"
    ],
    "tgn:id":2214282,
    "tgn:name":"Cajon Tank",
    "tgn:placetype":[
        "aat:300006191"
    ]
},
  "bbox": [],
  "geometry": {"coordinates":[-111.1667,31.5167],"type":"Point"}
}