<<<<<<< HEAD
{
  "id": 2406987,
  "type": "Feature",
  "properties": {
    "tgn:hierarchy":[
        "tgn:2406987",
        "tgn:1000001",
        "tgn:7012149",
        "tgn:1002742",
        "tgn:7007920",
        "tgn:7029392"
    ],
    "tgn:id":2406987,
    "tgn:name":"Hunter Lake",
    "tgn:placetype":[
        "aat:300008680"
    ]
},
  "bbox": [],
  "geometry": {"coordinates":[-119.6167,48.7167],"type":"Point"}
}
=======
{"geometry":{"type":"Point","coordinates":[-119.616700,48.716700]},"type":"Feature","properties":{"hierarchy":["tgn:2406987","tgn:1000001","tgn:7012149","tgn:1002742","tgn:7007920","tgn:7029392"],"placetype":["aat:300008680"],"id":2406987,"name:xx":"Hunter Lake"}}
>>>>>>> 03f74aca74312dbeaf24d7e61306dd6a786dc3d0
