{
  "id": 7163826,
  "type": "Feature",
  "properties": {
    "tgn:hierarchy":[
        "tgn:7163826",
        "tgn:1000003",
        "tgn:7003688",
        "tgn:7000084",
        "tgn:7029392"
    ],
    "tgn:id":7163826,
    "tgn:name":"H\u00fcrup",
    "tgn:placetype":[
        "aat:300008347"
    ]
},
  "bbox": [],
  "geometry": {"coordinates":[9.533333,54.75],"type":"Point"}
}