{
  "id": 7501626,
  "type": "Feature",
  "properties": {
    "tgn:hierarchy":[
        "tgn:7501626",
        "tgn:7488858",
        "tgn:1000004",
        "tgn:1000141",
        "tgn:7029392"
    ],
    "tgn:id":7501626,
    "tgn:name":"Fucheng",
    "tgn:placetype":[
        "aat:300008347"
    ]
},
  "bbox": [],
  "geometry": {"coordinates":[120.820081,24.022129],"type":"Point"}
}