{
  "id": 1084158,
  "type": "Feature",
  "properties": {
    "tgn:hierarchy":[
        "tgn:1084158",
        "tgn:1000004",
        "tgn:1007429",
        "tgn:1001231",
        "tgn:1000135",
        "tgn:7029392"
    ],
    "tgn:id":1084158,
    "tgn:name":"Culasi",
    "tgn:placetype":[
        "aat:300008347"
    ]
},
  "bbox": [],
  "geometry": {"coordinates":[125.7167,10.7167],"type":"Point"}
}