{
  "id": 7219933,
  "type": "Feature",
  "properties": {
    "tgn:hierarchy":[
        "tgn:7219933",
        "tgn:7011163",
        "tgn:7002674",
        "tgn:1000003",
        "tgn:1000074",
        "tgn:7029392"
    ],
    "tgn:id":7219933,
    "tgn:name":"Palai\u00f3loutros, Agk\u00e1li",
    "tgn:placetype":[
        "aat:300132317"
    ]
},
  "bbox": [],
  "geometry": {"coordinates":[26.532222,39.0275],"type":"Point"}
}