<<<<<<< HEAD
{
  "id": 7375479,
  "type": "Feature",
  "properties": {
    "tgn:hierarchy":[
        "tgn:7375479",
        "tgn:7005581",
        "tgn:1000001",
        "tgn:7005560",
        "tgn:7029392"
    ],
    "tgn:id":7375479,
    "tgn:name":"Presa Las Estacas",
    "tgn:placetype":[
        "aat:300006191"
    ]
},
  "bbox": [],
  "geometry": {"coordinates":[-106.333333,29.183333],"type":"Point"}
}
=======
{"geometry":{"type":"Point","coordinates":[-106.333333,29.183333]},"type":"Feature","properties":{"hierarchy":["tgn:7375479","tgn:7005581","tgn:1000001","tgn:7005560","tgn:7029392"],"placetype":["aat:300006191"],"id":7375479,"name:xx":"Presa Las Estacas"}}
>>>>>>> 03f74aca74312dbeaf24d7e61306dd6a786dc3d0
