{
  "id": 2670150,
  "type": "Feature",
  "properties": {
    "tgn:hierarchy":[
        "tgn:2670150",
        "tgn:1000001",
        "tgn:2001411",
        "tgn:7012149",
        "tgn:7007526",
        "tgn:7029392"
    ],
    "tgn:id":2670150,
    "tgn:name":"Slough, The",
    "tgn:placetype":[
        "aat:300008699"
    ]
},
  "bbox": [],
  "geometry": {"coordinates":[-114.9333,40.9833],"type":"Point"}
}