<<<<<<< HEAD
{
  "id": 2761105,
  "type": "Feature",
  "properties": {
    "tgn:hierarchy":[
        "tgn:2761105",
        "tgn:1000001",
        "tgn:7012149",
        "tgn:2001084",
        "tgn:7007521",
        "tgn:7029392"
    ],
    "tgn:id":2761105,
    "tgn:name":"West Lake",
    "tgn:placetype":[
        "aat:300008680"
    ]
},
  "bbox": [],
  "geometry": {"coordinates":[-93.9167,45.3167],"type":"Point"}
}
=======
{"geometry":{"type":"Point","coordinates":[-93.916700,45.316700]},"type":"Feature","properties":{"hierarchy":["tgn:2761105","tgn:1000001","tgn:7012149","tgn:2001084","tgn:7007521","tgn:7029392"],"placetype":["aat:300008680"],"id":2761105,"name:xx":"West Lake"}}
>>>>>>> 03f74aca74312dbeaf24d7e61306dd6a786dc3d0
