{
  "id": 7135677,
  "type": "Feature",
  "properties": {
    "tgn:hierarchy":[
        "tgn:7135677",
        "tgn:7000096",
        "tgn:1000003",
        "tgn:7000084",
        "tgn:7029392"
    ],
    "tgn:id":7135677,
    "tgn:name":"M\u00fchlen-See",
    "tgn:placetype":[
        "aat:300008680"
    ]
},
  "bbox": [],
  "geometry": {"coordinates":[14.25,52.316667],"type":"Point"}
}