{
  "id": 2517428,
  "type": "Feature",
  "properties": {
    "tgn:hierarchy":[
        "tgn:2517428",
        "tgn:1000001",
        "tgn:7012149",
        "tgn:1002440",
        "tgn:7007568",
        "tgn:7029392"
    ],
    "tgn:id":2517428,
    "tgn:name":"Minnow Pond",
    "tgn:placetype":[
        "aat:300008680"
    ]
},
  "bbox": [],
  "geometry": {"coordinates":[-74.4333,43.8667],"type":"Point"}
}