<<<<<<< HEAD
{
  "id": 7024963,
  "type": "Feature",
  "properties": {
    "tgn:hierarchy":[
        "tgn:7024963",
        "tgn:7002445",
        "tgn:7008103",
        "tgn:1000003",
        "tgn:7008591",
        "tgn:7029392"
    ],
    "tgn:id":7024963,
    "tgn:name:en":"Milton Bryan",
    "tgn:placetype":[
        "aat:300008347"
    ]
},
  "bbox": [],
  "geometry": {"coordinates":[-0.5667,51.95],"type":"Point"}
}
=======
{"geometry":{"type":"Point","coordinates":[-0.566700,51.950000]},"type":"Feature","properties":{"hierarchy":["tgn:7024963","tgn:7002445","tgn:7008103","tgn:1000003","tgn:7008591","tgn:7029392"],"placetype":["aat:300008347"],"name:en":"Milton Bryan","id":7024963}}
>>>>>>> 03f74aca74312dbeaf24d7e61306dd6a786dc3d0
