{
  "id": 2426512,
  "type": "Feature",
  "properties": {
    "tgn:hierarchy":[
        "tgn:2426512",
        "tgn:1000001",
        "tgn:2000920",
        "tgn:7012149",
        "tgn:7007515",
        "tgn:7029392"
    ],
    "tgn:id":2426512,
    "tgn:name":"Jones Hill",
    "tgn:placetype":[
        "aat:300008798"
    ]
},
  "bbox": [],
  "geometry": {"coordinates":[-70.3667,43.7667],"type":"Point"}
}