{
  "id": 7110955,
  "type": "Feature",
  "properties": {
    "tgn:hierarchy":[
        "tgn:7110955",
        "tgn:7003669",
        "tgn:1000003",
        "tgn:7000084",
        "tgn:7029392"
    ],
    "tgn:id":7110955,
    "tgn:name":"Reichen-Bach",
    "tgn:placetype":[
        "aat:300008699"
    ]
},
  "bbox": [],
  "geometry": {"coordinates":[9.183333,50.066667],"type":"Point"}
}