{
  "id": 2515960,
  "type": "Feature",
  "properties": {
    "tgn:hierarchy":[
        "tgn:2515960",
        "tgn:1002648",
        "tgn:1000001",
        "tgn:1008191",
        "tgn:7012149",
        "tgn:7007249",
        "tgn:7029392"
    ],
    "tgn:id":2515960,
    "tgn:name":"Mimino Gulch",
    "tgn:placetype":[
        "aat:300008761"
    ]
},
  "bbox": [],
  "geometry": {"coordinates":[-157.0167,21.1667],"type":"Point"}
}