{
  "id": 2054691,
  "type": "Feature",
  "properties": {
    "tgn:hierarchy":[
        "tgn:2054691",
        "tgn:1000001",
        "tgn:2001014",
        "tgn:7012149",
        "tgn:7007521",
        "tgn:7029392"
    ],
    "tgn:id":2054691,
    "tgn:name":"Hovland",
    "tgn:placetype":[
        "aat:300008347"
    ]
},
  "bbox": [],
  "geometry": {"coordinates":[-89.9667,47.8333],"type":"Point"}
}