{
  "id": 1140931,
  "type": "Feature",
  "properties": {
    "tgn:hierarchy":[
        "tgn:1140931",
        "tgn:7001242",
        "tgn:1001711",
        "tgn:1000203",
        "tgn:7029392"
    ],
    "tgn:id":1140931,
    "tgn:name":"Kidete",
    "tgn:placetype":[
        "aat:300008347"
    ]
},
  "bbox": [],
  "geometry": {"coordinates":[36.7333,-6.6667],"type":"Point"}
}