{
  "id": 2623223,
  "type": "Feature",
  "properties": {
    "tgn:hierarchy":[
        "tgn:2623223",
        "tgn:1000001",
        "tgn:7012149",
        "tgn:2000527",
        "tgn:7007251",
        "tgn:7029392"
    ],
    "tgn:id":2623223,
    "tgn:name":"Rock Branch",
    "tgn:placetype":[
        "aat:300008699"
    ]
},
  "bbox": [],
  "geometry": {"coordinates":[-88.1667,38.7667],"type":"Point"}
}