<<<<<<< HEAD
{
  "id": 2768949,
  "type": "Feature",
  "properties": {
    "tgn:hierarchy":[
        "tgn:2768949",
        "tgn:1002933",
        "tgn:1000001",
        "tgn:7012149",
        "tgn:7007239",
        "tgn:7029392"
    ],
    "tgn:id":2768949,
    "tgn:name":"Whitney Swamp",
    "tgn:placetype":[
        "aat:300008905"
    ]
},
  "bbox": [],
  "geometry": {"coordinates":[-75.6667,38.7333],"type":"Point"}
}
=======
{"geometry":{"type":"Point","coordinates":[-75.666700,38.733300]},"type":"Feature","properties":{"hierarchy":["tgn:2768949","tgn:1002933","tgn:1000001","tgn:7012149","tgn:7007239","tgn:7029392"],"placetype":["aat:300008905"],"id":2768949,"name:xx":"Whitney Swamp"}}
>>>>>>> 03f74aca74312dbeaf24d7e61306dd6a786dc3d0
