{
  "id": 2580435,
  "type": "Feature",
  "properties": {
    "tgn:hierarchy":[
        "tgn:2580435",
        "tgn:1000001",
        "tgn:2001701",
        "tgn:7012149",
        "tgn:7007708",
        "tgn:7029392"
    ],
    "tgn:id":2580435,
    "tgn:name":"Pigeon Butte",
    "tgn:placetype":[
        "aat:300008798"
    ]
},
  "bbox": [],
  "geometry": {"coordinates":[-123.3167,44.3833],"type":"Point"}
}