{
  "id": 7539458,
  "type": "Feature",
  "properties": {
    "tgn:hierarchy":[
        "tgn:7539458",
        "tgn:7001242",
        "tgn:7016833",
        "tgn:7001335",
        "tgn:7029392"
    ],
    "tgn:id":7539458,
    "tgn:name:en":"Sakriat, W\u00e2di el-",
    "tgn:placetype":[
        "aat:300379998"
    ]
},
  "bbox": [],
  "geometry": {"coordinates":[32.872488,29.955875],"type":"Point"}
}