<<<<<<< HEAD
{
  "id": 2405820,
  "type": "Feature",
  "properties": {
    "tgn:hierarchy":[
        "tgn:2405820",
        "tgn:1000001",
        "tgn:7012149",
        "tgn:2002374",
        "tgn:7007923",
        "tgn:7029392"
    ],
    "tgn:id":2405820,
    "tgn:name":"Hull Draw",
    "tgn:placetype":[
        "aat:300008761"
    ]
},
  "bbox": [],
  "geometry": {"coordinates":[-106.4833,43.5],"type":"Point"}
}
=======
{"geometry":{"type":"Point","coordinates":[-106.483300,43.500000]},"type":"Feature","properties":{"hierarchy":["tgn:2405820","tgn:1000001","tgn:7012149","tgn:2002374","tgn:7007923","tgn:7029392"],"placetype":["aat:300008761"],"id":2405820,"name:xx":"Hull Draw"}}
>>>>>>> 03f74aca74312dbeaf24d7e61306dd6a786dc3d0
