{
  "id": 2534285,
  "type": "Feature",
  "properties": {
    "tgn:hierarchy":[
        "tgn:2534285",
        "tgn:1000001",
        "tgn:7012149",
        "tgn:2000891",
        "tgn:7007256",
        "tgn:7029392"
    ],
    "tgn:id":2534285,
    "tgn:name":"Myth Shoal",
    "tgn:placetype":[
        "aat:300132348"
    ]
},
  "bbox": [],
  "geometry": {"coordinates":[-89.0333,29.5667],"type":"Point"}
}