<<<<<<< HEAD
{
  "id": 2769691,
  "type": "Feature",
  "properties": {
    "tgn:hierarchy":[
        "tgn:2769691",
        "tgn:1000001",
        "tgn:7016172",
        "tgn:7012149",
        "tgn:7029392"
    ],
    "tgn:id":2769691,
    "tgn:name":"Wiggins Creek",
    "tgn:placetype":[
        "aat:300008706"
    ]
},
  "bbox": [],
  "geometry": {"coordinates":[-92.8667,34.5],"type":"Point"}
}
=======
{"geometry":{"type":"Point","coordinates":[-92.866700,34.500000]},"type":"Feature","properties":{"hierarchy":["tgn:2769691","tgn:1000001","tgn:7016172","tgn:7012149","tgn:7029392"],"placetype":["aat:300008706"],"id":2769691,"name:xx":"Wiggins Creek"}}
>>>>>>> 03f74aca74312dbeaf24d7e61306dd6a786dc3d0
