{
  "id": 1121030,
  "type": "Feature",
  "properties": {
    "tgn:hierarchy":[
        "tgn:1121030",
        "tgn:1002001",
        "tgn:1000047",
        "tgn:7002456",
        "tgn:1000002",
        "tgn:7029392"
    ],
    "tgn:id":1121030,
    "tgn:name":"Ajarani",
    "tgn:placetype":[
        "aat:300008707"
    ]
},
  "bbox": [],
  "geometry": {"coordinates":[-61.2667,1.55],"type":"Point"}
}