{
  "id": 2448076,
  "type": "Feature",
  "properties": {
    "tgn:hierarchy":[
        "tgn:2448076",
        "tgn:1000001",
        "tgn:7012149",
        "tgn:2001312",
        "tgn:7007524",
        "tgn:7029392"
    ],
    "tgn:id":2448076,
    "tgn:name":"Lighthouse Hill",
    "tgn:placetype":[
        "aat:300008798"
    ]
},
  "bbox": [],
  "geometry": {"coordinates":[-106.8167,48.8833],"type":"Point"}
}