{
  "id": 2690207,
  "type": "Feature",
  "properties": {
    "tgn:hierarchy":[
        "tgn:2690207",
        "tgn:1000001",
        "tgn:1002473",
        "tgn:7012149",
        "tgn:7007240",
        "tgn:7029392"
    ],
    "tgn:id":2690207,
    "tgn:name":"Stafford Lake",
    "tgn:placetype":[
        "aat:300008680"
    ]
},
  "bbox": [],
  "geometry": {"coordinates":[-82.4333,28.6333],"type":"Point"}
}