{
  "id": 1082553,
  "type": "Feature",
  "properties": {
    "tgn:hierarchy":[
        "tgn:1082553",
        "tgn:1000004",
        "tgn:7000851",
        "tgn:1000125",
        "tgn:7029392"
    ],
    "tgn:id":1082553,
    "tgn:name":"Tourakom",
    "tgn:placetype":[
        "aat:300008347"
    ]
},
  "bbox": [],
  "geometry": {"coordinates":[102.5333,18.4333],"type":"Point"}
}