{
  "id": 2078603,
  "type": "Feature",
  "properties": {
    "tgn:hierarchy":[
        "tgn:2078603",
        "tgn:1000001",
        "tgn:7012149",
        "tgn:1002519",
        "tgn:7007706",
        "tgn:7029392"
    ],
    "tgn:id":2078603,
    "tgn:name":"Broadacre",
    "tgn:placetype":[
        "aat:300008347"
    ]
},
  "bbox": [],
  "geometry": {"coordinates":[-80.7833,40.35],"type":"Point"}
}