{
  "id": 2519251,
  "type": "Feature",
  "properties": {
    "tgn:hierarchy":[
        "tgn:2519251",
        "tgn:1000001",
        "tgn:7012149",
        "tgn:2002333",
        "tgn:7007922",
        "tgn:7029392"
    ],
    "tgn:id":2519251,
    "tgn:name":"Moccasin Lake",
    "tgn:placetype":[
        "aat:300008680"
    ]
},
  "bbox": [],
  "geometry": {"coordinates":[-89.2667,45.4333],"type":"Point"}
}