{
  "id": 2686184,
  "type": "Feature",
  "properties": {
    "tgn:hierarchy":[
        "tgn:2686184",
        "tgn:1000001",
        "tgn:7012149",
        "tgn:2001277",
        "tgn:7007524",
        "tgn:7029392"
    ],
    "tgn:id":2686184,
    "tgn:name":"Spring Coulee",
    "tgn:placetype":[
        "aat:300008761"
    ]
},
  "bbox": [],
  "geometry": {"coordinates":[-113.1333,48.7333],"type":"Point"}
}