{
  "id": 7131750,
  "type": "Feature",
  "properties": {
    "tgn:hierarchy":[
        "tgn:7131750",
        "tgn:7000096",
        "tgn:1000003",
        "tgn:7000084",
        "tgn:7029392"
    ],
    "tgn:id":7131750,
    "tgn:name":"Marienhof",
    "tgn:placetype":[
        "aat:300000206"
    ]
},
  "bbox": [],
  "geometry": {"coordinates":[12.75,52.65],"type":"Point"}
}