{
  "id": 2080688,
  "type": "Feature",
  "properties": {
    "tgn:hierarchy":[
        "tgn:2080688",
        "tgn:1000001",
        "tgn:7012149",
        "tgn:1002570",
        "tgn:7007706",
        "tgn:7029392"
    ],
    "tgn:id":2080688,
    "tgn:name":"Mentor",
    "tgn:placetype":[
        "aat:300008347"
    ]
},
  "bbox": [],
  "geometry": {"coordinates":[-81.3333,41.65],"type":"Point"}
}