<<<<<<< HEAD
{
  "id": 2702404,
  "type": "Feature",
  "properties": {
    "tgn:hierarchy":[
        "tgn:2702404",
        "tgn:1000001",
        "tgn:2000460",
        "tgn:7012149",
        "tgn:7007250",
        "tgn:7029392"
    ],
    "tgn:id":2702404,
    "tgn:name":"Sullivan Spring",
    "tgn:placetype":[
        "aat:300008697"
    ]
},
  "bbox": [],
  "geometry": {"coordinates":[-116.4167,48.0667],"type":"Point"}
}
=======
{"geometry":{"type":"Point","coordinates":[-116.416700,48.066700]},"type":"Feature","properties":{"hierarchy":["tgn:2702404","tgn:1000001","tgn:2000460","tgn:7012149","tgn:7007250","tgn:7029392"],"placetype":["aat:300008697"],"id":2702404,"name:xx":"Sullivan Spring"}}
>>>>>>> 03f74aca74312dbeaf24d7e61306dd6a786dc3d0
