{
  "id": 7560830,
  "type": "Feature",
  "properties": {
    "tgn:hierarchy":[
        "tgn:7560830",
        "tgn:1000004",
        "tgn:7000198",
        "tgn:7016722",
        "tgn:7029392"
    ],
    "tgn:id":7560830,
    "tgn:name:en":"Kunwardepur",
    "tgn:placetype":[
        "aat:300008347"
    ]
},
  "bbox": [],
  "geometry": {"coordinates":[79.343553,26.48363],"type":"Point"}
}