{
  "id": 7554489,
  "type": "Feature",
  "properties": {
    "tgn:hierarchy":[
        "tgn:7554489",
        "tgn:1000004",
        "tgn:7000198",
        "tgn:1001894",
        "tgn:7029392"
    ],
    "tgn:id":7554489,
    "tgn:name:en":"Non Nad\u012b",
    "tgn:placetype":[
        "aat:300008699"
    ]
},
  "bbox": [],
  "geometry": {"coordinates":[78.364561,25.832363],"type":"Point"}
}