{
  "id": 7565265,
  "type": "Feature",
  "properties": {
    "tgn:hierarchy":[
        "tgn:7565265",
        "tgn:1000004",
        "tgn:7000198",
        "tgn:7016788",
        "tgn:7029392"
    ],
    "tgn:id":7565265,
    "tgn:name:en":"Kundal Tibba",
    "tgn:placetype":[
        "aat:300008347"
    ]
},
  "bbox": [],
  "geometry": {"coordinates":[71.155884,27.391118],"type":"Point"}
}