{
  "id": 2399254,
  "type": "Feature",
  "properties": {
    "tgn:hierarchy":[
        "tgn:2399254",
        "tgn:1000001",
        "tgn:7012149",
        "tgn:1002553",
        "tgn:7007920",
        "tgn:7029392"
    ],
    "tgn:id":2399254,
    "tgn:name":"Horlick",
    "tgn:placetype":[
        "aat:300008347"
    ]
},
  "bbox": [],
  "geometry": {"coordinates":[-120.7833,47.1167],"type":"Point"}
}