{
  "id": 2491450,
  "type": "Feature",
  "properties": {
    "tgn:hierarchy":[
        "tgn:2491450",
        "tgn:1000001",
        "tgn:7012149",
        "tgn:1002399",
        "tgn:7007710",
        "tgn:7029392"
    ],
    "tgn:id":2491450,
    "tgn:name":"Maple Hollow",
    "tgn:placetype":[
        "aat:300008761"
    ]
},
  "bbox": [],
  "geometry": {"coordinates":[-78.15,39.95],"type":"Point"}
}