{
  "id": 7092341,
  "type": "Feature",
  "properties": {
    "tgn:hierarchy":[
        "tgn:7092341",
        "tgn:1000003",
        "tgn:7003682",
        "tgn:7000084",
        "tgn:7029392"
    ],
    "tgn:id":7092341,
    "tgn:name":"Urmitzer Werth",
    "tgn:placetype":[
        "aat:300008791"
    ]
},
  "bbox": [],
  "geometry": {"coordinates":[7.516667,50.416667],"type":"Point"}
}