{
  "id": 7319603,
  "type": "Feature",
  "properties": {
    "tgn:hierarchy":[
        "tgn:7319603",
        "tgn:1001657",
        "tgn:1000049",
        "tgn:1000002",
        "tgn:7029392"
    ],
    "tgn:id":7319603,
    "tgn:name":"Almendrillo",
    "tgn:placetype":[
        "aat:300000206"
    ]
},
  "bbox": [],
  "geometry": {"coordinates":[-70.616667,-32.066667],"type":"Point"}
}