{
  "id": 1117039,
  "type": "Feature",
  "properties": {
    "tgn:hierarchy":[
        "tgn:1117039",
        "tgn:1000001",
        "tgn:1002361",
        "tgn:7012149",
        "tgn:7007828",
        "tgn:7029392"
    ],
    "tgn:id":1117039,
    "tgn:name":"Little Averill Lake",
    "tgn:placetype":[
        "aat:300008680"
    ]
},
  "bbox": [],
  "geometry": {"coordinates":[-71.7167,44.95],"type":"Point"}
}