{
  "id": 2500660,
  "type": "Feature",
  "properties": {
    "tgn:hierarchy":[
        "tgn:2500660",
        "tgn:1000001",
        "tgn:7012149",
        "tgn:2002382",
        "tgn:7007923",
        "tgn:7029392"
    ],
    "tgn:id":2500660,
    "tgn:name":"McDougal Creek",
    "tgn:placetype":[
        "aat:300008706"
    ]
},
  "bbox": [],
  "geometry": {"coordinates":[-110.5667,42.8333],"type":"Point"}
}