{
  "id": 1049243,
  "type": "Feature",
  "properties": {
    "tgn:hierarchy":[
        "tgn:1049243",
        "tgn:1000003",
        "tgn:7024120",
        "tgn:7006366",
        "tgn:7029392"
    ],
    "tgn:id":1049243,
    "tgn:name":"Mie\u031cdzyrzecz",
    "tgn:placetype":[
        "aat:300008347"
    ]
},
  "bbox": [],
  "geometry": {"coordinates":[15.5667,52.45],"type":"Point"}
}