{
  "id": 2655087,
  "type": "Feature",
  "properties": {
    "tgn:hierarchy":[
        "tgn:2655087",
        "tgn:1000001",
        "tgn:2000682",
        "tgn:7012149",
        "tgn:7007254",
        "tgn:7029392"
    ],
    "tgn:id":2655087,
    "tgn:name":"Shank Hill",
    "tgn:placetype":[
        "aat:300008798"
    ]
},
  "bbox": [],
  "geometry": {"coordinates":[-95.25,38.8833],"type":"Point"}
}