<<<<<<< HEAD
{
  "id": 7052131,
  "type": "Feature",
  "properties": {
    "tgn:hierarchy":[
        "tgn:7052131",
        "tgn:7003127",
        "tgn:1000003",
        "tgn:7008516",
        "tgn:1000080",
        "tgn:7029392"
    ],
    "tgn:id":7052131,
    "tgn:name":"La Cavanella",
    "tgn:placetype":[
        "aat:300008347"
    ]
},
  "bbox": [],
  "geometry": {"coordinates":[11.1,44.35],"type":"Point"}
}
=======
{"geometry":{"type":"Point","coordinates":[11.100000,44.350000]},"type":"Feature","properties":{"hierarchy":["tgn:7052131","tgn:7003127","tgn:1000003","tgn:7008516","tgn:1000080","tgn:7029392"],"placetype":["aat:300008347"],"id":7052131,"name:xx":"La Cavanella"}}
>>>>>>> 03f74aca74312dbeaf24d7e61306dd6a786dc3d0
