<<<<<<< HEAD
{
  "id": 2255524,
  "type": "Feature",
  "properties": {
    "tgn:hierarchy":[
        "tgn:2255524",
        "tgn:1000001",
        "tgn:7012149",
        "tgn:2001706",
        "tgn:7007708",
        "tgn:7029392"
    ],
    "tgn:id":2255524,
    "tgn:name":"Copeland Butte",
    "tgn:placetype":[
        "aat:300008798"
    ]
},
  "bbox": [],
  "geometry": {"coordinates":[-123.0833,43.3667],"type":"Point"}
}
=======
{"geometry":{"type":"Point","coordinates":[-123.083300,43.366700]},"type":"Feature","properties":{"hierarchy":["tgn:2255524","tgn:1000001","tgn:7012149","tgn:2001706","tgn:7007708","tgn:7029392"],"placetype":["aat:300008798"],"id":2255524,"name:xx":"Copeland Butte"}}
>>>>>>> 03f74aca74312dbeaf24d7e61306dd6a786dc3d0
