{
  "id": 2743500,
  "type": "Feature",
  "properties": {
    "tgn:hierarchy":[
        "tgn:2743500",
        "tgn:1000001",
        "tgn:7012149",
        "tgn:7007520",
        "tgn:7029392"
    ],
    "tgn:id":2743500,
    "tgn:name":"Varney Hill",
    "tgn:placetype":[
        "aat:300008798"
    ]
},
  "bbox": [],
  "geometry": {"coordinates":[-85.8667,44.7667],"type":"Point"}
}