{
  "id": 2237794,
  "type": "Feature",
  "properties": {
    "tgn:hierarchy":[
        "tgn:2237794",
        "tgn:1000001",
        "tgn:7016172",
        "tgn:7012149",
        "tgn:2000155",
        "tgn:7029392"
    ],
    "tgn:id":2237794,
    "tgn:name":"Chinquapin Knob",
    "tgn:placetype":[
        "aat:300008798"
    ]
},
  "bbox": [],
  "geometry": {"coordinates":[-92.9667,35.9167],"type":"Point"}
}