{
  "id": 7563534,
  "type": "Feature",
  "properties": {
    "tgn:hierarchy":[
        "tgn:7563534",
        "tgn:1000004",
        "tgn:7000198",
        "tgn:7016722",
        "tgn:7029392"
    ],
    "tgn:id":7563534,
    "tgn:name:en":"Mus\u0101l T\u0101l",
    "tgn:placetype":[
        "aat:300008680"
    ]
},
  "bbox": [],
  "geometry": {"coordinates":[79.365051,25.344065],"type":"Point"}
}