{
  "id": 7501849,
  "type": "Feature",
  "properties": {
    "tgn:hierarchy":[
        "tgn:7501849",
        "tgn:1000004",
        "tgn:7491221",
        "tgn:1000141",
        "tgn:7029392"
    ],
    "tgn:id":7501849,
    "tgn:name":"Zhongshan Muchang",
    "tgn:placetype":[
        "aat:300000241"
    ]
},
  "bbox": [],
  "geometry": {"coordinates":[120.894722,22.244444],"type":"Point"}
}