{
  "id": 2104489,
  "type": "Feature",
  "properties": {
    "tgn:hierarchy":[
        "tgn:2104489",
        "tgn:1000001",
        "tgn:7012149",
        "tgn:1003034",
        "tgn:7007826",
        "tgn:7029392"
    ],
    "tgn:id":2104489,
    "tgn:name":"Golden",
    "tgn:placetype":[
        "aat:300008347"
    ]
},
  "bbox": [],
  "geometry": {"coordinates":[-95.55,32.7167],"type":"Point"}
}