{
  "id": 1107237,
  "type": "Feature",
  "properties": {
    "tgn:hierarchy":[
        "tgn:1107237",
        "tgn:1000001",
        "tgn:7012149",
        "tgn:7014510",
        "tgn:7007920",
        "tgn:7029392"
    ],
    "tgn:id":1107237,
    "tgn:name":"Eldorado Peak",
    "tgn:placetype":[
        "aat:300008798"
    ]
},
  "bbox": [],
  "geometry": {"coordinates":[-121.1167,48.5333],"type":"Point"}
}