{
  "id": 2461382,
  "type": "Feature",
  "properties": {
    "tgn:hierarchy":[
        "tgn:2461382",
        "tgn:1000001",
        "tgn:7012149",
        "tgn:7007252",
        "tgn:7029392"
    ],
    "tgn:id":2461382,
    "tgn:name":"Little Sugar Creek",
    "tgn:placetype":[
        "aat:300008706"
    ]
},
  "bbox": [],
  "geometry": {"coordinates":[-85.8167,39.7167],"type":"Point"}
}