{
  "id": 7499484,
  "type": "Feature",
  "properties": {
    "tgn:hierarchy":[
        "tgn:7499484",
        "tgn:7001004",
        "tgn:1000004",
        "tgn:1000141",
        "tgn:7029392"
    ],
    "tgn:id":7499484,
    "tgn:name":"Longfeng Gong",
    "tgn:placetype":[
        "aat:300007595"
    ]
},
  "bbox": [],
  "geometry": {"coordinates":[120.404665,22.6297],"type":"Point"}
}