{
  "id": 2239410,
  "type": "Feature",
  "properties": {
    "tgn:hierarchy":[
        "tgn:2239410",
        "tgn:1000001",
        "tgn:7012149",
        "tgn:2002288",
        "tgn:7013961",
        "tgn:7029392"
    ],
    "tgn:id":2239410,
    "tgn:name":"Church Creek",
    "tgn:placetype":[
        "aat:300008706"
    ]
},
  "bbox": [],
  "geometry": {"coordinates":[-79.7333,39.4667],"type":"Point"}
}