{
  "id": 7110777,
  "type": "Feature",
  "properties": {
    "tgn:hierarchy":[
        "tgn:7110777",
        "tgn:1000003",
        "tgn:7003677",
        "tgn:7000084",
        "tgn:7029392"
    ],
    "tgn:id":7110777,
    "tgn:name":"Rauhe Hardt",
    "tgn:placetype":[
        "aat:300266640"
    ]
},
  "bbox": [],
  "geometry": {"coordinates":[7.65,51.383333],"type":"Point"}
}