<<<<<<< HEAD
{
  "id": 7110777,
  "type": "Feature",
  "properties": {
    "tgn:hierarchy":[
        "tgn:7110777",
        "tgn:1000003",
        "tgn:7003677",
        "tgn:7000084",
        "tgn:7029392"
    ],
    "tgn:id":7110777,
    "tgn:name":"Rauhe Hardt",
    "tgn:placetype":[
        "aat:300266640"
    ]
},
  "bbox": [],
  "geometry": {"coordinates":[7.65,51.383333],"type":"Point"}
}
=======
{"geometry":{"type":"Point","coordinates":[7.650000,51.383333]},"type":"Feature","properties":{"hierarchy":["tgn:7110777","tgn:1000003","tgn:7003677","tgn:7000084","tgn:7029392"],"placetype":["aat:300266640"],"id":7110777,"name:xx":"Rauhe Hardt"}}
>>>>>>> 03f74aca74312dbeaf24d7e61306dd6a786dc3d0
