<<<<<<< HEAD
{
  "id": 7350248,
  "type": "Feature",
  "properties": {
    "tgn:hierarchy":[
        "tgn:7350248",
        "tgn:1000001",
        "tgn:1001960",
        "tgn:7005560",
        "tgn:7029392"
    ],
    "tgn:id":7350248,
    "tgn:name":"Bacabachi",
    "tgn:placetype":[
        "aat:300008347"
    ]
},
  "bbox": [],
  "geometry": {"coordinates":[-109.4,26.916667],"type":"Point"}
}
=======
{"geometry":{"type":"Point","coordinates":[-109.400000,26.916667]},"type":"Feature","properties":{"hierarchy":["tgn:7350248","tgn:1000001","tgn:1001960","tgn:7005560","tgn:7029392"],"placetype":["aat:300008347"],"id":7350248,"name:xx":"Bacabachi"}}
>>>>>>> 03f74aca74312dbeaf24d7e61306dd6a786dc3d0
