{
  "id": 7496732,
  "type": "Feature",
  "properties": {
    "tgn:hierarchy":[
        "tgn:7496732",
        "tgn:1000004",
        "tgn:1000454",
        "tgn:1000141",
        "tgn:7029392"
    ],
    "tgn:id":7496732,
    "tgn:name":"Ashikeng",
    "tgn:placetype":[
        "aat:300008347"
    ]
},
  "bbox": [],
  "geometry": {"coordinates":[121.385726,24.919914],"type":"Point"}
}