{
  "id": 2185122,
  "type": "Feature",
  "properties": {
    "tgn:hierarchy":[
        "tgn:2185122",
        "tgn:1000001",
        "tgn:7012149",
        "tgn:2001756",
        "tgn:7007712",
        "tgn:7029392"
    ],
    "tgn:id":2185122,
    "tgn:name":"Boggy Branch",
    "tgn:placetype":[
        "aat:300008699"
    ]
},
  "bbox": [],
  "geometry": {"coordinates":[-81.2667,33.9667],"type":"Point"}
}