{
  "id": 7028212,
  "type": "Feature",
  "properties": {
    "tgn:hierarchy":[
        "tgn:7028212",
        "tgn:7002445",
        "tgn:1000003",
        "tgn:7008157",
        "tgn:7008591",
        "tgn:7029392"
    ],
    "tgn:id":7028212,
    "tgn:name":"Wharton",
    "tgn:placetype":[
        "aat:300008347",
        "aat:300008372"
    ]
},
  "bbox": [],
  "geometry": {"coordinates":[-0.728,53.419],"type":"Point"}
}