{
  "id": 2383664,
  "type": "Feature",
  "properties": {
    "tgn:hierarchy":[
        "tgn:2383664",
        "tgn:7006450",
        "tgn:1000001",
        "tgn:7012149",
        "tgn:2000086",
        "tgn:7029392"
    ],
    "tgn:id":2383664,
    "tgn:name":"Heavenly Ridge",
    "tgn:placetype":[
        "aat:300266640"
    ]
},
  "bbox": [],
  "geometry": {"coordinates":[-146.8667,61.8833],"type":"Point"}
}