{
  "id": 7507466,
  "type": "Feature",
  "properties": {
    "tgn:hierarchy":[
        "tgn:7507466",
        "tgn:1008380",
        "tgn:7000507",
        "tgn:1000226",
        "tgn:1000006",
        "tgn:7029392"
    ],
    "tgn:id":7507466,
    "tgn:name:en":"Puhau Creek",
    "tgn:placetype":[
        "aat:300008699"
    ]
},
  "bbox": [],
  "geometry": {"coordinates":[173.383333,-35.466667],"type":"Point"}
}