{
  "id": 7200734,
  "type": "Feature",
  "properties": {
    "tgn:hierarchy":[
        "tgn:7200734",
        "tgn:1000003",
        "tgn:7003677",
        "tgn:7000084",
        "tgn:7029392"
    ],
    "tgn:id":7200734,
    "tgn:name":"Durbeke",
    "tgn:placetype":[
        "aat:300004792"
    ]
},
  "bbox": [],
  "geometry": {"coordinates":[8.916667,51.766667],"type":"Point"}
}