{
  "id": 2036085,
  "type": "Feature",
  "properties": {
    "tgn:hierarchy":[
        "tgn:2036085",
        "tgn:1000001",
        "tgn:7012149",
        "tgn:2000722",
        "tgn:7007254",
        "tgn:7029392"
    ],
    "tgn:id":2036085,
    "tgn:name":"Blake",
    "tgn:placetype":[
        "aat:300387016"
    ]
},
  "bbox": [],
  "geometry": {"coordinates":[-95.75,37.1667],"type":"Point"}
}