<<<<<<< HEAD
{
  "id": 2152247,
  "type": "Feature",
  "properties": {
    "tgn:hierarchy":[
        "tgn:2152247",
        "tgn:1000001",
        "tgn:7012149",
        "tgn:2000225",
        "tgn:7007158",
        "tgn:7029392"
    ],
    "tgn:id":2152247,
    "tgn:name":"Bay City Gulch",
    "tgn:placetype":[
        "aat:300008761"
    ]
},
  "bbox": [],
  "geometry": {"coordinates":[-108.0833,37.35],"type":"Point"}
}
=======
{"geometry":{"type":"Point","coordinates":[-108.083300,37.350000]},"type":"Feature","properties":{"hierarchy":["tgn:2152247","tgn:1000001","tgn:7012149","tgn:2000225","tgn:7007158","tgn:7029392"],"placetype":["aat:300008761"],"id":2152247,"name:xx":"Bay City Gulch"}}
>>>>>>> 03f74aca74312dbeaf24d7e61306dd6a786dc3d0
