{
  "id": 2760332,
  "type": "Feature",
  "properties": {
    "tgn:hierarchy":[
        "tgn:2760332",
        "tgn:1000001",
        "tgn:2001411",
        "tgn:7012149",
        "tgn:7007526",
        "tgn:7029392"
    ],
    "tgn:id":2760332,
    "tgn:name":"West Fork Seventysix Creek",
    "tgn:placetype":[
        "aat:300008706"
    ]
},
  "bbox": [],
  "geometry": {"coordinates":[-115.4667,41.7333],"type":"Point"}
}