<<<<<<< HEAD
{
  "id": 2769804,
  "type": "Feature",
  "properties": {
    "tgn:hierarchy":[
        "tgn:2769804",
        "tgn:1000001",
        "tgn:7012149",
        "tgn:2002186",
        "tgn:7007919",
        "tgn:7029392"
    ],
    "tgn:id":2769804,
    "tgn:name":"Wigwam Mountain",
    "tgn:placetype":[
        "aat:300008798"
    ]
},
  "bbox": [],
  "geometry": {"coordinates":[-79.1667,37.8],"type":"Point"}
}
=======
{"geometry":{"type":"Point","coordinates":[-79.166700,37.800000]},"type":"Feature","properties":{"hierarchy":["tgn:2769804","tgn:1000001","tgn:7012149","tgn:2002186","tgn:7007919","tgn:7029392"],"placetype":["aat:300008798"],"id":2769804,"name:xx":"Wigwam Mountain"}}
>>>>>>> 03f74aca74312dbeaf24d7e61306dd6a786dc3d0
