{
  "id": 7581364,
  "type": "Feature",
  "properties": {
    "tgn:hierarchy":[
        "tgn:7581364",
        "tgn:1000004",
        "tgn:7000198",
        "tgn:1001996",
        "tgn:7029392"
    ],
    "tgn:id":7581364,
    "tgn:name:en":"Suruj T\u0101l",
    "tgn:placetype":[
        "aat:300008680"
    ]
},
  "bbox": [],
  "geometry": {"coordinates":[77.404888,32.758052],"type":"Point"}
}