{
  "id": 2536564,
  "type": "Feature",
  "properties": {
    "tgn:hierarchy":[
        "tgn:2536564",
        "tgn:1000001",
        "tgn:7012149",
        "tgn:1002785",
        "tgn:7007920",
        "tgn:7029392"
    ],
    "tgn:id":2536564,
    "tgn:name":"Nearns Point",
    "tgn:placetype":[
        "aat:300008850"
    ]
},
  "bbox": [],
  "geometry": {"coordinates":[-122.65,47.2667],"type":"Point"}
}