{
  "id": 1082024,
  "type": "Feature",
  "properties": {
    "tgn:hierarchy":[
        "tgn:1082024",
        "tgn:1000004",
        "tgn:1001477",
        "tgn:1000122",
        "tgn:7029392"
    ],
    "tgn:id":1082024,
    "tgn:name":"Kangdong-\u016dp",
    "tgn:placetype":[
        "aat:300008347"
    ]
},
  "bbox": [],
  "geometry": {"coordinates":[126.0333,39.1333],"type":"Point"}
}