{
  "id": 2178984,
  "type": "Feature",
  "properties": {
    "tgn:hierarchy":[
        "tgn:2178984",
        "tgn:1000001",
        "tgn:7012149",
        "tgn:1002779",
        "tgn:7007710",
        "tgn:7029392"
    ],
    "tgn:id":2178984,
    "tgn:name":"Blain Hollow",
    "tgn:placetype":[
        "aat:300008761"
    ]
},
  "bbox": [],
  "geometry": {"coordinates":[-77.5333,40.35],"type":"Point"}
}