{
  "id": 2202295,
  "type": "Feature",
  "properties": {
    "tgn:hierarchy":[
        "tgn:2202295",
        "tgn:1000001",
        "tgn:7012149",
        "tgn:2001720",
        "tgn:7007708",
        "tgn:7029392"
    ],
    "tgn:id":2202295,
    "tgn:name":"Buck Mountain",
    "tgn:placetype":[
        "aat:300008798"
    ]
},
  "bbox": [],
  "geometry": {"coordinates":[-118.15,45.6833],"type":"Point"}
}