{
  "id": 2487421,
  "type": "Feature",
  "properties": {
    "tgn:hierarchy":[
        "tgn:2487421",
        "tgn:1000001",
        "tgn:7012149",
        "tgn:2000811",
        "tgn:7007255",
        "tgn:7029392"
    ],
    "tgn:id":2487421,
    "tgn:name":"Left Fork Bear Branch",
    "tgn:placetype":[
        "aat:300008699"
    ]
},
  "bbox": [],
  "geometry": {"coordinates":[-83.5167,37.15],"type":"Point"}
}