{
  "id": 2097989,
  "type": "Feature",
  "properties": {
    "tgn:hierarchy":[
        "tgn:2097989",
        "tgn:1000001",
        "tgn:2001839",
        "tgn:7012149",
        "tgn:7007825",
        "tgn:7029392"
    ],
    "tgn:id":2097989,
    "tgn:name":"Black Center",
    "tgn:placetype":[
        "aat:300008347"
    ]
},
  "bbox": [],
  "geometry": {"coordinates":[-88.0833,36.0667],"type":"Point"}
}