{
  "id": 2420936,
  "type": "Feature",
  "properties": {
    "tgn:hierarchy":[
        "tgn:2420936",
        "tgn:1000001",
        "tgn:2000950",
        "tgn:7012149",
        "tgn:7007520",
        "tgn:7029392"
    ],
    "tgn:id":2420936,
    "tgn:name":"Jensen Harbor",
    "tgn:placetype":[
        "aat:300132316"
    ]
},
  "bbox": [],
  "geometry": {"coordinates":[-85.4667,45.7833],"type":"Point"}
}