<<<<<<< HEAD
{
  "id": 7366665,
  "type": "Feature",
  "properties": {
    "tgn:hierarchy":[
        "tgn:7366665",
        "tgn:1000001",
        "tgn:7005597",
        "tgn:7005560",
        "tgn:7029392"
    ],
    "tgn:id":7366665,
    "tgn:name":"El Tinieblo",
    "tgn:placetype":[
        "aat:300008347"
    ]
},
  "bbox": [],
  "geometry": {"coordinates":[-98.5,24.316667],"type":"Point"}
}
=======
{"geometry":{"type":"Point","coordinates":[-98.500000,24.316667]},"type":"Feature","properties":{"hierarchy":["tgn:7366665","tgn:1000001","tgn:7005597","tgn:7005560","tgn:7029392"],"placetype":["aat:300008347"],"id":7366665,"name:xx":"El Tinieblo"}}
>>>>>>> 03f74aca74312dbeaf24d7e61306dd6a786dc3d0
