<<<<<<< HEAD
{
  "id": 7114924,
  "type": "Feature",
  "properties": {
    "tgn:hierarchy":[
        "tgn:7114924",
        "tgn:1000003",
        "tgn:7003676",
        "tgn:7000084",
        "tgn:7029392"
    ],
    "tgn:id":7114924,
    "tgn:name":"Ochsenmoor",
    "tgn:placetype":[
        "aat:300386886"
    ]
},
  "bbox": [],
  "geometry": {"coordinates":[10.616667,52.683333],"type":"Point"}
}
=======
{"geometry":{"type":"Point","coordinates":[10.616667,52.683333]},"type":"Feature","properties":{"hierarchy":["tgn:7114924","tgn:1000003","tgn:7003676","tgn:7000084","tgn:7029392"],"placetype":["aat:300386886"],"id":7114924,"name:xx":"Ochsenmoor"}}
>>>>>>> 03f74aca74312dbeaf24d7e61306dd6a786dc3d0
