<<<<<<< HEAD
{
  "id": 7248557,
  "type": "Feature",
  "properties": {
    "tgn:hierarchy":[
        "tgn:7248557",
        "tgn:7003458",
        "tgn:1000003",
        "tgn:1000063",
        "tgn:7018236",
        "tgn:7029392"
    ],
    "tgn:id":7248557,
    "tgn:name":"Biesgat",
    "tgn:placetype":[
        "aat:300008347"
    ]
},
  "bbox": [],
  "geometry": {"coordinates":[3.350666,51.021223],"type":"Point"}
}
=======
{"geometry":{"type":"Point","coordinates":[3.350666,51.021223]},"type":"Feature","properties":{"hierarchy":["tgn:7248557","tgn:7003458","tgn:1000003","tgn:1000063","tgn:7018236","tgn:7029392"],"placetype":["aat:300008347"],"id":7248557,"name:xx":"Biesgat"}}
>>>>>>> 03f74aca74312dbeaf24d7e61306dd6a786dc3d0
