{
  "id": 7248557,
  "type": "Feature",
  "properties": {
    "tgn:hierarchy":[
        "tgn:7248557",
        "tgn:7003458",
        "tgn:1000003",
        "tgn:1000063",
        "tgn:7018236",
        "tgn:7029392"
    ],
    "tgn:id":7248557,
    "tgn:name":"Biesgat",
    "tgn:placetype":[
        "aat:300008347"
    ]
},
  "bbox": [],
  "geometry": {"coordinates":[3.350666,51.021223],"type":"Point"}
}