{
  "id": 2563982,
  "type": "Feature",
  "properties": {
    "tgn:hierarchy":[
        "tgn:2563982",
        "tgn:1000001",
        "tgn:7012149",
        "tgn:7007920",
        "tgn:7029392"
    ],
    "tgn:id":2563982,
    "tgn:name":"Oyster Creek",
    "tgn:placetype":[
        "aat:300008706"
    ]
},
  "bbox": [],
  "geometry": {"coordinates":[-122.4667,48.6667],"type":"Point"}
}