{
  "id": 2441046,
  "type": "Feature",
  "properties": {
    "tgn:hierarchy":[
        "tgn:2441046",
        "tgn:1000001",
        "tgn:1002274",
        "tgn:7012149",
        "tgn:7007706",
        "tgn:7029392"
    ],
    "tgn:id":2441046,
    "tgn:name":"Knobs, The",
    "tgn:placetype":[
        "aat:300008798"
    ]
},
  "bbox": [],
  "geometry": {"coordinates":[-83.65,39.9667],"type":"Point"}
}