{
  "id": 7314948,
  "type": "Feature",
  "properties": {
    "tgn:hierarchy":[
        "tgn:7314948",
        "tgn:1001637",
        "tgn:1000049",
        "tgn:1000002",
        "tgn:7029392"
    ],
    "tgn:id":7314948,
    "tgn:name":"Licauqu\u00e9n",
    "tgn:placetype":[
        "aat:300000206"
    ]
},
  "bbox": [],
  "geometry": {"coordinates":[-73.433333,-37.733333],"type":"Point"}
}