{
  "id": 1122791,
  "type": "Feature",
  "properties": {
    "tgn:hierarchy":[
        "tgn:1122791",
        "tgn:7005685",
        "tgn:1000001",
        "tgn:7029392"
    ],
    "tgn:id":1122791,
    "tgn:name":"Chinchaga",
    "tgn:placetype":[
        "aat:300008707"
    ]
},
  "bbox": [],
  "geometry": {"coordinates":[-118.3167,58.8667],"type":"Point"}
}