<<<<<<< HEAD
{
  "id": 2404067,
  "type": "Feature",
  "properties": {
    "tgn:hierarchy":[
        "tgn:2404067",
        "tgn:1000001",
        "tgn:7012149",
        "tgn:2001750",
        "tgn:7007712",
        "tgn:7029392"
    ],
    "tgn:id":2404067,
    "tgn:name":"Howells",
    "tgn:placetype":[
        "aat:300008347"
    ]
},
  "bbox": [],
  "geometry": {"coordinates":[-78.9833,33.9667],"type":"Point"}
}
=======
{"geometry":{"type":"Point","coordinates":[-78.983300,33.966700]},"type":"Feature","properties":{"hierarchy":["tgn:2404067","tgn:1000001","tgn:7012149","tgn:2001750","tgn:7007712","tgn:7029392"],"placetype":["aat:300008347"],"id":2404067,"name:xx":"Howells"}}
>>>>>>> 03f74aca74312dbeaf24d7e61306dd6a786dc3d0
