{
  "id": 7281375,
  "type": "Feature",
  "properties": {
    "tgn:hierarchy":[
        "tgn:7281375",
        "tgn:1001702",
        "tgn:1000049",
        "tgn:1000002",
        "tgn:7029392"
    ],
    "tgn:id":7281375,
    "tgn:name":"Sandwich, Cabo",
    "tgn:placetype":[
        "aat:300386846"
    ]
},
  "bbox": [],
  "geometry": {"coordinates":[-75.469444,-50.304167],"type":"Point"}
}