{
  "id": 2402822,
  "type": "Feature",
  "properties": {
    "tgn:hierarchy":[
        "tgn:2402822",
        "tgn:1000001",
        "tgn:7006451",
        "tgn:7012149",
        "tgn:2000101",
        "tgn:7029392"
    ],
    "tgn:id":2402822,
    "tgn:name":"Hot Tamale Wash",
    "tgn:placetype":[
        "aat:300008699"
    ]
},
  "bbox": [],
  "geometry": {"coordinates":[-110.95,33.2167],"type":"Point"}
}