<<<<<<< HEAD
{
  "id": 2402822,
  "type": "Feature",
  "properties": {
    "tgn:hierarchy":[
        "tgn:2402822",
        "tgn:1000001",
        "tgn:7006451",
        "tgn:7012149",
        "tgn:2000101",
        "tgn:7029392"
    ],
    "tgn:id":2402822,
    "tgn:name":"Hot Tamale Wash",
    "tgn:placetype":[
        "aat:300008699"
    ]
},
  "bbox": [],
  "geometry": {"coordinates":[-110.95,33.2167],"type":"Point"}
}
=======
{"geometry":{"type":"Point","coordinates":[-110.950000,33.216700]},"type":"Feature","properties":{"hierarchy":["tgn:2402822","tgn:1000001","tgn:7006451","tgn:7012149","tgn:2000101","tgn:7029392"],"placetype":["aat:300008699"],"id":2402822,"name:xx":"Hot Tamale Wash"}}
>>>>>>> 03f74aca74312dbeaf24d7e61306dd6a786dc3d0
