<<<<<<< HEAD
{
  "id": 7353389,
  "type": "Feature",
  "properties": {
    "tgn:hierarchy":[
        "tgn:7353389",
        "tgn:1000001",
        "tgn:7005590",
        "tgn:7005560",
        "tgn:7029392"
    ],
    "tgn:id":7353389,
    "tgn:name":"Bellas Fuentes",
    "tgn:placetype":[
        "aat:300008347"
    ]
},
  "bbox": [],
  "geometry": {"coordinates":[-101.666667,19.833333],"type":"Point"}
}
=======
{"geometry":{"type":"Point","coordinates":[-101.666667,19.833333]},"type":"Feature","properties":{"hierarchy":["tgn:7353389","tgn:1000001","tgn:7005590","tgn:7005560","tgn:7029392"],"placetype":["aat:300008347"],"id":7353389,"name:xx":"Bellas Fuentes"}}
>>>>>>> 03f74aca74312dbeaf24d7e61306dd6a786dc3d0
