{
  "id": 1128399,
  "type": "Feature",
  "properties": {
    "tgn:hierarchy":[
        "tgn:1128399",
        "tgn:7006247",
        "tgn:1000047",
        "tgn:7002456",
        "tgn:1000002",
        "tgn:7029392"
    ],
    "tgn:id":1128399,
    "tgn:name":"Parauapebas",
    "tgn:placetype":[
        "aat:300008707"
    ]
},
  "bbox": [],
  "geometry": {"coordinates":[-49.6833,-5.5833],"type":"Point"}
}