{
  "id": 2159553,
  "type": "Feature",
  "properties": {
    "tgn:hierarchy":[
        "tgn:2159553",
        "tgn:1000001",
        "tgn:7012149",
        "tgn:1002555",
        "tgn:7007523",
        "tgn:7029392"
    ],
    "tgn:id":2159553,
    "tgn:name":"Bee Ridge",
    "tgn:placetype":[
        "aat:300266640"
    ]
},
  "bbox": [],
  "geometry": {"coordinates":[-92.05,40.0667],"type":"Point"}
}