<<<<<<< HEAD
{
  "id": 2159553,
  "type": "Feature",
  "properties": {
    "tgn:hierarchy":[
        "tgn:2159553",
        "tgn:1000001",
        "tgn:7012149",
        "tgn:1002555",
        "tgn:7007523",
        "tgn:7029392"
    ],
    "tgn:id":2159553,
    "tgn:name":"Bee Ridge",
    "tgn:placetype":[
        "aat:300266640"
    ]
},
  "bbox": [],
  "geometry": {"coordinates":[-92.05,40.0667],"type":"Point"}
}
=======
{"geometry":{"type":"Point","coordinates":[-92.050000,40.066700]},"type":"Feature","properties":{"hierarchy":["tgn:2159553","tgn:1000001","tgn:7012149","tgn:1002555","tgn:7007523","tgn:7029392"],"placetype":["aat:300266640"],"id":2159553,"name:xx":"Bee Ridge"}}
>>>>>>> 03f74aca74312dbeaf24d7e61306dd6a786dc3d0
