{
  "id": 7515605,
  "type": "Feature",
  "properties": {
    "tgn:hierarchy":[
        "tgn:7515605",
        "tgn:1008380",
        "tgn:7000507",
        "tgn:1000226",
        "tgn:1000006",
        "tgn:7029392"
    ],
    "tgn:id":7515605,
    "tgn:name:en":"Moturua",
    "tgn:placetype":[
        "aat:300008791"
    ]
},
  "bbox": [],
  "geometry": {"coordinates":[174.183333,-35.216667],"type":"Point"}
}