{
  "id": 2535444,
  "type": "Feature",
  "properties": {
    "tgn:hierarchy":[
        "tgn:2535444",
        "tgn:7006450",
        "tgn:1000001",
        "tgn:7012149",
        "tgn:2000087",
        "tgn:7029392"
    ],
    "tgn:id":2535444,
    "tgn:name":"Naringolapak Slough",
    "tgn:placetype":[
        "aat:300008699"
    ]
},
  "bbox": [],
  "geometry": {"coordinates":[-164.0333,62.6333],"type":"Point"}
}