{
  "id": 2613893,
  "type": "Feature",
  "properties": {
    "tgn:hierarchy":[
        "tgn:2613893",
        "tgn:1000001",
        "tgn:7012149",
        "tgn:2001502",
        "tgn:7007709",
        "tgn:7029392"
    ],
    "tgn:id":2613893,
    "tgn:name":"Reedys Swamp",
    "tgn:placetype":[
        "aat:300008905"
    ]
},
  "bbox": [],
  "geometry": {"coordinates":[-79.0167,35.2667],"type":"Point"}
}