{
  "id": 2424767,
  "type": "Feature",
  "properties": {
    "tgn:hierarchy":[
        "tgn:2424767",
        "tgn:2000948",
        "tgn:1000001",
        "tgn:7012149",
        "tgn:7007520",
        "tgn:7029392"
    ],
    "tgn:id":2424767,
    "tgn:name":"Johnson Drain",
    "tgn:placetype":[
        "aat:300008699"
    ]
},
  "bbox": [],
  "geometry": {"coordinates":[-83.9833,43.8167],"type":"Point"}
}