{
  "id": 1032912,
  "type": "Feature",
  "properties": {
    "tgn:hierarchy":[
        "tgn:1032912",
        "tgn:1000003",
        "tgn:7002875",
        "tgn:1000070",
        "tgn:7029392"
    ],
    "tgn:id":1032912,
    "tgn:name":"Decize",
    "tgn:placetype":[
        "aat:300008347"
    ]
},
  "bbox": [],
  "geometry": {"coordinates":[3.4667,46.8333],"type":"Point"}
}