{
  "id": 2262296,
  "type": "Feature",
  "properties": {
    "tgn:hierarchy":[
        "tgn:2262296",
        "tgn:2001837",
        "tgn:1000001",
        "tgn:7012149",
        "tgn:7007825",
        "tgn:7029392"
    ],
    "tgn:id":2262296,
    "tgn:name":"Cow Creek",
    "tgn:placetype":[
        "aat:300008706"
    ]
},
  "bbox": [],
  "geometry": {"coordinates":[-84.3167,36.0833],"type":"Point"}
}