{
  "id": 7325696,
  "type": "Feature",
  "properties": {
    "tgn:hierarchy":[
        "tgn:7325696",
        "tgn:7002836",
        "tgn:7016622",
        "tgn:1000003",
        "tgn:1000095",
        "tgn:7029392"
    ],
    "tgn:id":7325696,
    "tgn:name":"San Luis",
    "tgn:placetype":[
        "aat:300008347"
    ]
},
  "bbox": [],
  "geometry": {"coordinates":[-16.333333,28.516667],"type":"Point"}
}