{
  "id": 2130779,
  "type": "Feature",
  "properties": {
    "tgn:hierarchy":[
        "tgn:2130779",
        "tgn:1000001",
        "tgn:7012149",
        "tgn:2002019",
        "tgn:7007826",
        "tgn:7029392"
    ],
    "tgn:id":2130779,
    "tgn:name":"Allison Mountain",
    "tgn:placetype":[
        "aat:300008798"
    ]
},
  "bbox": [],
  "geometry": {"coordinates":[-99.9333,30.45],"type":"Point"}
}