{
  "id": 2620248,
  "type": "Feature",
  "properties": {
    "tgn:hierarchy":[
        "tgn:2620248",
        "tgn:1000001",
        "tgn:7012149",
        "tgn:1002624",
        "tgn:7007568",
        "tgn:7029392"
    ],
    "tgn:id":2620248,
    "tgn:name":"Ritz Hill",
    "tgn:placetype":[
        "aat:300008798"
    ]
},
  "bbox": [],
  "geometry": {"coordinates":[-75.3833,42.8167],"type":"Point"}
}