{
  "id": 2566121,
  "type": "Feature",
  "properties": {
    "tgn:hierarchy":[
        "tgn:2566121",
        "tgn:1000001",
        "tgn:7012149",
        "tgn:2000928",
        "tgn:7007515",
        "tgn:7029392"
    ],
    "tgn:id":2566121,
    "tgn:name":"Palmer Meadow",
    "tgn:placetype":[
        "aat:300008905"
    ]
},
  "bbox": [],
  "geometry": {"coordinates":[-68.8833,45.2833],"type":"Point"}
}