{
  "id": 7533850,
  "type": "Feature",
  "properties": {
    "tgn:hierarchy":[
        "tgn:7533850",
        "tgn:7001242",
        "tgn:7001311",
        "tgn:7016833",
        "tgn:7029392"
    ],
    "tgn:id":7533850,
    "tgn:name:en":"Hamret Mast\u00fbra",
    "tgn:placetype":[
        "aat:300008777"
    ]
},
  "bbox": [],
  "geometry": {"coordinates":[34.316667,24.866667],"type":"Point"}
}