{
  "id": 2121504,
  "type": "Feature",
  "properties": {
    "tgn:hierarchy":[
        "tgn:2121504",
        "tgn:1000001",
        "tgn:7012149",
        "tgn:2002347",
        "tgn:7007922",
        "tgn:7029392"
    ],
    "tgn:id":2121504,
    "tgn:name":"Kellner",
    "tgn:placetype":[
        "aat:300008347"
    ]
},
  "bbox": [],
  "geometry": {"coordinates":[-89.7167,44.35],"type":"Point"}
}