{
  "id": 2748110,
  "type": "Feature",
  "properties": {
    "tgn:hierarchy":[
        "tgn:2748110",
        "tgn:1000001",
        "tgn:7012149",
        "tgn:2001167",
        "tgn:7007522",
        "tgn:7029392"
    ],
    "tgn:id":2748110,
    "tgn:name":"Walesheba Creek",
    "tgn:placetype":[
        "aat:300008706"
    ]
},
  "bbox": [],
  "geometry": {"coordinates":[-90.2667,32.8167],"type":"Point"}
}