<<<<<<< HEAD
{
  "id": 7489312,
  "type": "Feature",
  "properties": {
    "tgn:hierarchy":[
        "tgn:7489312",
        "tgn:1000004",
        "tgn:7490934",
        "tgn:1000141",
        "tgn:7029392"
    ],
    "tgn:id":7489312,
    "tgn:name":"Lutaoyang",
    "tgn:placetype":[
        "aat:300008347"
    ]
},
  "bbox": [],
  "geometry": {"coordinates":[120.49019,23.155629],"type":"Point"}
}
=======
{"geometry":{"type":"Point","coordinates":[120.490190,23.155629]},"type":"Feature","properties":{"hierarchy":["tgn:7489312","tgn:1000004","tgn:7490934","tgn:1000141","tgn:7029392"],"placetype":["aat:300008347"],"id":7489312,"name:xx":"Lutaoyang"}}
>>>>>>> 03f74aca74312dbeaf24d7e61306dd6a786dc3d0
