{
  "id": 2321949,
  "type": "Feature",
  "properties": {
    "tgn:hierarchy":[
        "tgn:2321949",
        "tgn:1000001",
        "tgn:7012149",
        "tgn:2001851",
        "tgn:7007825",
        "tgn:7029392"
    ],
    "tgn:id":2321949,
    "tgn:name":"Fall Branch",
    "tgn:placetype":[
        "aat:300008699"
    ]
},
  "bbox": [],
  "geometry": {"coordinates":[-83.05,35.7833],"type":"Point"}
}