{
  "id": 7195178,
  "type": "Feature",
  "properties": {
    "tgn:hierarchy":[
        "tgn:7195178",
        "tgn:1000003",
        "tgn:7003676",
        "tgn:7000084",
        "tgn:7029392"
    ],
    "tgn:id":7195178,
    "tgn:name":"Dittmars-Berg",
    "tgn:placetype":[
        "aat:300008795"
    ]
},
  "bbox": [],
  "geometry": {"coordinates":[10.366667,51.916667],"type":"Point"}
}