{
  "id": 2463190,
  "type": "Feature",
  "properties": {
    "tgn:hierarchy":[
        "tgn:2463190",
        "tgn:1000001",
        "tgn:7012149",
        "tgn:7007826",
        "tgn:7029392"
    ],
    "tgn:id":2463190,
    "tgn:name":"Livingston, Lake",
    "tgn:placetype":[
        "aat:300006191"
    ]
},
  "bbox": [],
  "geometry": {"coordinates":[-95.0167,30.6167],"type":"Point"}
}