{
  "id": 2579920,
  "type": "Feature",
  "properties": {
    "tgn:hierarchy":[
        "tgn:2579920",
        "tgn:1000001",
        "tgn:7012149",
        "tgn:2001544",
        "tgn:7007709",
        "tgn:7029392"
    ],
    "tgn:id":2579920,
    "tgn:name":"Piedmont Lake",
    "tgn:placetype":[
        "aat:300006191"
    ]
},
  "bbox": [],
  "geometry": {"coordinates":[-82.6667,35.1333],"type":"Point"}
}