{
  "id": 2280044,
  "type": "Feature",
  "properties": {
    "tgn:hierarchy":[
        "tgn:2280044",
        "tgn:1000001",
        "tgn:7012149",
        "tgn:1002871",
        "tgn:7007568",
        "tgn:7029392"
    ],
    "tgn:id":2280044,
    "tgn:name":"Deans Corners",
    "tgn:placetype":[
        "aat:300008347"
    ]
},
  "bbox": [],
  "geometry": {"coordinates":[-73.6667,43.0333],"type":"Point"}
}