{
  "id": 2191657,
  "type": "Feature",
  "properties": {
    "tgn:hierarchy":[
        "tgn:2191657",
        "tgn:1000001",
        "tgn:7012149",
        "tgn:2000995",
        "tgn:7007520",
        "tgn:7029392"
    ],
    "tgn:id":2191657,
    "tgn:name":"Bradley Creek",
    "tgn:placetype":[
        "aat:300008706"
    ]
},
  "bbox": [],
  "geometry": {"coordinates":[-82.7333,43.2167],"type":"Point"}
}