<<<<<<< HEAD
{
  "id": 7365757,
  "type": "Feature",
  "properties": {
    "tgn:hierarchy":[
        "tgn:7365757",
        "tgn:1000001",
        "tgn:1001960",
        "tgn:7005560",
        "tgn:7029392"
    ],
    "tgn:id":7365757,
    "tgn:name":"Rancho El Taraysal",
    "tgn:placetype":[
        "aat:300000241"
    ]
},
  "bbox": [],
  "geometry": {"coordinates":[-109.65,29.916667],"type":"Point"}
}
=======
{"geometry":{"type":"Point","coordinates":[-109.650000,29.916667]},"type":"Feature","properties":{"hierarchy":["tgn:7365757","tgn:1000001","tgn:1001960","tgn:7005560","tgn:7029392"],"placetype":["aat:300000241"],"id":7365757,"name:xx":"Rancho El Taraysal"}}
>>>>>>> 03f74aca74312dbeaf24d7e61306dd6a786dc3d0
