{
  "id": 2529205,
  "type": "Feature",
  "properties": {
    "tgn:hierarchy":[
        "tgn:2529205",
        "tgn:1000001",
        "tgn:7012149",
        "tgn:2001851",
        "tgn:7007825",
        "tgn:7029392"
    ],
    "tgn:id":2529205,
    "tgn:name":"Mud Hollow",
    "tgn:placetype":[
        "aat:300008761"
    ]
},
  "bbox": [],
  "geometry": {"coordinates":[-82.9333,35.8833],"type":"Point"}
}