{
  "id": 7559632,
  "type": "Feature",
  "properties": {
    "tgn:hierarchy":[
        "tgn:7559632",
        "tgn:1000004",
        "tgn:7000198",
        "tgn:7000799",
        "tgn:7029392"
    ],
    "tgn:id":7559632,
    "tgn:name:en":"Rumbak",
    "tgn:placetype":[
        "aat:300008347"
    ]
},
  "bbox": [],
  "geometry": {"coordinates":[77.416203,34.04974],"type":"Point"}
}