{
  "id": 7434567,
  "type": "Feature",
  "properties": {
    "tgn:hierarchy":[
        "tgn:7434567",
        "tgn:7005580",
        "tgn:1000001",
        "tgn:7005560",
        "tgn:7029392"
    ],
    "tgn:id":7434567,
    "tgn:name":"Vega de Guerrero",
    "tgn:placetype":[
        "aat:300008699"
    ]
},
  "bbox": [],
  "geometry": {"coordinates":[-92.35,15.666667],"type":"Point"}
}