{
  "id": 1011392,
  "type": "Feature",
  "properties": {
    "tgn:hierarchy":[
        "tgn:1011392",
        "tgn:1000003",
        "tgn:7003122",
        "tgn:1001732",
        "tgn:1000080",
        "tgn:7029392"
    ],
    "tgn:id":1011392,
    "tgn:name":"Zafferano, Capo",
    "tgn:placetype":[
        "aat:300008850"
    ]
},
  "bbox": [],
  "geometry": {"coordinates":[13.533333,38.116667],"type":"Point"}
}