<<<<<<< HEAD
{
  "id": 2155664,
  "type": "Feature",
  "properties": {
    "tgn:hierarchy":[
        "tgn:2155664",
        "tgn:1000001",
        "tgn:7012149",
        "tgn:1002742",
        "tgn:7007920",
        "tgn:7029392"
    ],
    "tgn:id":2155664,
    "tgn:name":"Bear Spring",
    "tgn:placetype":[
        "aat:300008697"
    ]
},
  "bbox": [],
  "geometry": {"coordinates":[-119.35,48.3167],"type":"Point"}
}
=======
{"geometry":{"type":"Point","coordinates":[-119.350000,48.316700]},"type":"Feature","properties":{"hierarchy":["tgn:2155664","tgn:1000001","tgn:7012149","tgn:1002742","tgn:7007920","tgn:7029392"],"placetype":["aat:300008697"],"id":2155664,"name:xx":"Bear Spring"}}
>>>>>>> 03f74aca74312dbeaf24d7e61306dd6a786dc3d0
