{
  "id": 7466169,
  "type": "Feature",
  "properties": {
    "tgn:hierarchy":[
        "tgn:7466169",
        "tgn:5000432",
        "tgn:7002444",
        "tgn:1000003",
        "tgn:7008591",
        "tgn:7029392"
    ],
    "tgn:id":7466169,
    "tgn:name:en":"Ardmiddle House",
    "tgn:placetype":[
        "aat:300387502"
    ]
},
  "bbox": [],
  "geometry": {"coordinates":[-2.533333,57.533333],"type":"Point"}
}