{
  "id": 2706381,
  "type": "Feature",
  "properties": {
    "tgn:hierarchy":[
        "tgn:2706381",
        "tgn:1000001",
        "tgn:7012149",
        "tgn:1003038",
        "tgn:7007517",
        "tgn:7029392"
    ],
    "tgn:id":2706381,
    "tgn:name":"Swan Avenue",
    "tgn:placetype":[
        "aat:300008347"
    ]
},
  "bbox": [],
  "geometry": {"coordinates":[-71.8333,42.25],"type":"Point"}
}