<<<<<<< HEAD
{
  "id": 7022273,
  "type": "Feature",
  "properties": {
    "tgn:hierarchy":[
        "tgn:7022273",
        "tgn:1000001",
        "tgn:2001409",
        "tgn:7012149",
        "tgn:7007526",
        "tgn:7029392"
    ],
    "tgn:id":7022273,
    "tgn:name":"Upper Soda Lake Drain",
    "tgn:placetype":[
        "aat:300006075"
    ]
},
  "bbox": [],
  "geometry": {"coordinates":[-118.8167,39.4833],"type":"Point"}
}
=======
{"geometry":{"type":"Point","coordinates":[-118.816700,39.483300]},"type":"Feature","properties":{"hierarchy":["tgn:7022273","tgn:1000001","tgn:2001409","tgn:7012149","tgn:7007526","tgn:7029392"],"placetype":["aat:300006075"],"id":7022273,"name:xx":"Upper Soda Lake Drain"}}
>>>>>>> 03f74aca74312dbeaf24d7e61306dd6a786dc3d0
