{
  "id": 7471622,
  "type": "Feature",
  "properties": {
    "tgn:hierarchy":[
        "tgn:7471622",
        "tgn:1000004",
        "tgn:1000454",
        "tgn:1000141",
        "tgn:7029392"
    ],
    "tgn:id":7471622,
    "tgn:name":"Fanzilun",
    "tgn:placetype":[
        "aat:300008347"
    ]
},
  "bbox": [],
  "geometry": {"coordinates":[121.478024,25.241654],"type":"Point"}
}