{
  "id": 2705137,
  "type": "Feature",
  "properties": {
    "tgn:hierarchy":[
        "tgn:2705137",
        "tgn:1000001",
        "tgn:7012149",
        "tgn:2002333",
        "tgn:7007922",
        "tgn:7029392"
    ],
    "tgn:id":2705137,
    "tgn:name":"Sunshine Springs",
    "tgn:placetype":[
        "aat:300008697"
    ]
},
  "bbox": [],
  "geometry": {"coordinates":[-88.8667,45.15],"type":"Point"}
}