{
  "id": 1068359,
  "type": "Feature",
  "properties": {
    "tgn:hierarchy":[
        "tgn:1068359",
        "tgn:1000004",
        "tgn:1001390",
        "tgn:1000111",
        "tgn:7029392"
    ],
    "tgn:id":1068359,
    "tgn:name":"Guaimozi",
    "tgn:placetype":[
        "aat:300008347"
    ]
},
  "bbox": [],
  "geometry": {"coordinates":[125.45,41.4667],"type":"Point"}
}