{
  "id": 2096559,
  "type": "Feature",
  "properties": {
    "tgn:hierarchy":[
        "tgn:2096559",
        "tgn:1000001",
        "tgn:2001744",
        "tgn:7012149",
        "tgn:7007712",
        "tgn:7029392"
    ],
    "tgn:id":2096559,
    "tgn:name":"Richtex",
    "tgn:placetype":[
        "aat:300008347",
        "aat:300387210"
    ]
},
  "bbox": [],
  "geometry": {"coordinates":[-81.1667,34.1833],"type":"Point"}
}