{
  "id": 7185543,
  "type": "Feature",
  "properties": {
    "tgn:hierarchy":[
        "tgn:7185543",
        "tgn:7003669",
        "tgn:1000003",
        "tgn:7000084",
        "tgn:7029392"
    ],
    "tgn:id":7185543,
    "tgn:name":"Gramig",
    "tgn:placetype":[
        "aat:300000206"
    ]
},
  "bbox": [],
  "geometry": {"coordinates":[12.833333,48.25],"type":"Point"}
}