<<<<<<< HEAD
{
  "id": 7475772,
  "type": "Feature",
  "properties": {
    "tgn:hierarchy":[
        "tgn:7475772",
        "tgn:1000004",
        "tgn:7489179",
        "tgn:1000141",
        "tgn:7029392"
    ],
    "tgn:id":7475772,
    "tgn:name":"Xingang Qiao",
    "tgn:placetype":[
        "aat:300007836"
    ]
},
  "bbox": [],
  "geometry": {"coordinates":[121.775924,24.735572],"type":"Point"}
}
=======
{"geometry":{"type":"Point","coordinates":[121.775924,24.735572]},"type":"Feature","properties":{"hierarchy":["tgn:7475772","tgn:1000004","tgn:7489179","tgn:1000141","tgn:7029392"],"placetype":["aat:300007836"],"id":7475772,"name:xx":"Xingang Qiao"}}
>>>>>>> 03f74aca74312dbeaf24d7e61306dd6a786dc3d0
