{
  "id": 7309160,
  "type": "Feature",
  "properties": {
    "tgn:hierarchy":[
        "tgn:7309160",
        "tgn:1001695",
        "tgn:1000049",
        "tgn:1000002",
        "tgn:7029392"
    ],
    "tgn:id":7309160,
    "tgn:name":"Los Rode\u00edllos",
    "tgn:placetype":[
        "aat:300387200"
    ]
},
  "bbox": [],
  "geometry": {"coordinates":[-70.583333,-34.016667],"type":"Point"}
}