{
  "id": 2752497,
  "type": "Feature",
  "properties": {
    "tgn:hierarchy":[
        "tgn:2752497",
        "tgn:1000001",
        "tgn:2000924",
        "tgn:7012149",
        "tgn:7007515",
        "tgn:7029392"
    ],
    "tgn:id":2752497,
    "tgn:name":"Washington Pond",
    "tgn:placetype":[
        "aat:300008680"
    ]
},
  "bbox": [],
  "geometry": {"coordinates":[-69.3667,44.2833],"type":"Point"}
}