{
  "id": 7041940,
  "type": "Feature",
  "properties": {
    "tgn:hierarchy":[
        "tgn:7041940",
        "tgn:1003478",
        "tgn:1000003",
        "tgn:7003120",
        "tgn:1000080",
        "tgn:7029392"
    ],
    "tgn:id":7041940,
    "tgn:name":"Sabbia",
    "tgn:placetype":[
        "aat:300008347"
    ]
},
  "bbox": [],
  "geometry": {"coordinates":[8.233333,45.85],"type":"Point"}
}