{
  "id": 1002198,
  "type": "Feature",
  "properties": {
    "tgn:hierarchy":[
        "tgn:1002198",
        "tgn:1000001",
        "tgn:7012149",
        "tgn:7007826",
        "tgn:7029392"
    ],
    "tgn:id":1002198,
    "tgn:name":"Brazoria",
    "tgn:placetype":[
        "aat:300387145",
        "aat:300000771"
    ]
},
  "bbox": [],
  "geometry": {"coordinates":[-95.45,29.1833],"type":"Point"}
}