{
  "id": 2744755,
  "type": "Feature",
  "properties": {
    "tgn:hierarchy":[
        "tgn:2744755",
        "tgn:1000001",
        "tgn:7006451",
        "tgn:7012149",
        "tgn:2000100",
        "tgn:7029392"
    ],
    "tgn:id":2744755,
    "tgn:name":"Victoria Mine",
    "tgn:placetype":[
        "aat:300000390"
    ]
},
  "bbox": [],
  "geometry": {"coordinates":[-112.8333,31.9167],"type":"Point"}
}