{
  "id": 7281303,
  "type": "Feature",
  "properties": {
    "tgn:hierarchy":[
        "tgn:7281303",
        "tgn:1001695",
        "tgn:1000049",
        "tgn:1000002",
        "tgn:7029392"
    ],
    "tgn:id":7281303,
    "tgn:name":"Estaci\u00f3n Santa Cruz",
    "tgn:placetype":[
        "aat:300007783"
    ]
},
  "bbox": [],
  "geometry": {"coordinates":[-71.35,-34.633333],"type":"Point"}
}