{
  "id": 7537249,
  "type": "Feature",
  "properties": {
    "tgn:hierarchy":[
        "tgn:7537249",
        "tgn:7001242",
        "tgn:1001075",
        "tgn:7016833",
        "tgn:7029392"
    ],
    "tgn:id":7537249,
    "tgn:name:en":"Sh\u0101mikh, Tall\u0101t",
    "tgn:placetype":[
        "aat:300008777"
    ]
},
  "bbox": [],
  "geometry": {"coordinates":[30.25,30.666667],"type":"Point"}
}