{
  "id": 7289885,
  "type": "Feature",
  "properties": {
    "tgn:hierarchy":[
        "tgn:7289885",
        "tgn:7002464",
        "tgn:1000049",
        "tgn:1000002",
        "tgn:7029392"
    ],
    "tgn:id":7289885,
    "tgn:name":"El Bosque",
    "tgn:placetype":[
        "aat:300006207"
    ]
},
  "bbox": [],
  "geometry": {"coordinates":[-69.783333,-20.183333],"type":"Point"}
}