{
  "id": 7227625,
  "type": "Feature",
  "properties": {
    "tgn:hierarchy":[
        "tgn:7227625",
        "tgn:7011167",
        "tgn:7001338",
        "tgn:1000003",
        "tgn:1000074",
        "tgn:7029392"
    ],
    "tgn:id":7227625,
    "tgn:name":"Kontogour\u00e1ta",
    "tgn:placetype":[
        "aat:300008347"
    ]
},
  "bbox": [],
  "geometry": {"coordinates":[20.466667,38.266667],"type":"Point"}
}