{
  "id": 7007683,
  "type": "Feature",
  "properties": {
    "tgn:hierarchy":[
        "tgn:7007683",
        "tgn:1000003",
        "tgn:7024127",
        "tgn:7006366",
        "tgn:7029392"
    ],
    "tgn:id":7007683,
    "tgn:name":"Kalwaria Zebrzydowska",
    "tgn:placetype":[
        "aat:300008347"
    ]
},
  "bbox": [],
  "geometry": {"coordinates":[19.6833,49.8667],"type":"Point"}
}