{
  "id": 2166237,
  "type": "Feature",
  "properties": {
    "tgn:hierarchy":[
        "tgn:2166237",
        "tgn:1000001",
        "tgn:7012149",
        "tgn:2001304",
        "tgn:7007524",
        "tgn:7029392"
    ],
    "tgn:id":2166237,
    "tgn:name":"Big Beaver Creek",
    "tgn:placetype":[
        "aat:300008706"
    ]
},
  "bbox": [],
  "geometry": {"coordinates":[-115.7167,47.65],"type":"Point"}
}