{
  "id": 2191022,
  "type": "Feature",
  "properties": {
    "tgn:hierarchy":[
        "tgn:2191022",
        "tgn:1000001",
        "tgn:7012149",
        "tgn:2001533",
        "tgn:7007709",
        "tgn:7029392"
    ],
    "tgn:id":2191022,
    "tgn:name":"Boyds Lake",
    "tgn:placetype":[
        "aat:300006191"
    ]
},
  "bbox": [],
  "geometry": {"coordinates":[-79.6667,34.8833],"type":"Point"}
}