{
  "id": 2669074,
  "type": "Feature",
  "properties": {
    "tgn:hierarchy":[
        "tgn:2669074",
        "tgn:1000001",
        "tgn:1002271",
        "tgn:7012149",
        "tgn:7007920",
        "tgn:7029392"
    ],
    "tgn:id":2669074,
    "tgn:name":"Sledge Hammer Point",
    "tgn:placetype":[
        "aat:300008850"
    ]
},
  "bbox": [],
  "geometry": {"coordinates":[-123.7667,48.0667],"type":"Point"}
}