{
  "id": 7221519,
  "type": "Feature",
  "properties": {
    "tgn:hierarchy":[
        "tgn:7221519",
        "tgn:7011164",
        "tgn:7002674",
        "tgn:1000003",
        "tgn:1000074",
        "tgn:7029392"
    ],
    "tgn:id":7221519,
    "tgn:name":"Z\u00e1stano",
    "tgn:placetype":[
        "aat:300387200"
    ]
},
  "bbox": [],
  "geometry": {"coordinates":[26.628889,37.735278],"type":"Point"}
}