{
  "id": 7573156,
  "type": "Feature",
  "properties": {
    "tgn:hierarchy":[
        "tgn:7573156",
        "tgn:1000004",
        "tgn:7000198",
        "tgn:1001894",
        "tgn:7029392"
    ],
    "tgn:id":7573156,
    "tgn:name:en":"Jungel",
    "tgn:placetype":[
        "aat:300008347"
    ]
},
  "bbox": [],
  "geometry": {"coordinates":[82.850842,24.515661],"type":"Point"}
}