{
  "id": 2093901,
  "type": "Feature",
  "properties": {
    "tgn:hierarchy":[
        "tgn:2093901",
        "tgn:1000001",
        "tgn:7012149",
        "tgn:1002729",
        "tgn:7007710",
        "tgn:7029392"
    ],
    "tgn:id":2093901,
    "tgn:name":"University Heights",
    "tgn:placetype":[
        "aat:300008347"
    ]
},
  "bbox": [],
  "geometry": {"coordinates":[-75.3833,40.5833],"type":"Point"}
}