{
  "id": 2521425,
  "type": "Feature",
  "properties": {
    "tgn:hierarchy":[
        "tgn:2521425",
        "tgn:2000001",
        "tgn:7002659",
        "tgn:1000001",
        "tgn:7012149",
        "tgn:7029392"
    ],
    "tgn:id":2521425,
    "tgn:name":"Montgomery Hill Landing",
    "tgn:placetype":[
        "aat:300008347"
    ]
},
  "bbox": [],
  "geometry": {"coordinates":[-87.85,31.1667],"type":"Point"}
}