{
  "id": 7240635,
  "type": "Feature",
  "properties": {
    "tgn:hierarchy":[
        "tgn:7240635",
        "tgn:7007877",
        "tgn:1000003",
        "tgn:1000063",
        "tgn:4012014",
        "tgn:7029392"
    ],
    "tgn:id":7240635,
    "tgn:name":"Faintiau",
    "tgn:placetype":[
        "aat:300008347"
    ]
},
  "bbox": [],
  "geometry": {"coordinates":[3.470778,50.625557],"type":"Point"}
}