{
  "id": 2493138,
  "type": "Feature",
  "properties": {
    "tgn:hierarchy":[
        "tgn:2493138",
        "tgn:1000001",
        "tgn:7012149",
        "tgn:2001521",
        "tgn:7007709",
        "tgn:7029392"
    ],
    "tgn:id":2493138,
    "tgn:name":"Marleys Branch",
    "tgn:placetype":[
        "aat:300008699"
    ]
},
  "bbox": [],
  "geometry": {"coordinates":[-79.5833,35.4167],"type":"Point"}
}