{
  "id": 7061993,
  "type": "Feature",
  "properties": {
    "tgn:hierarchy":[
        "tgn:7061993",
        "tgn:7003692",
        "tgn:1000003",
        "tgn:7000084",
        "tgn:7029392"
    ],
    "tgn:id":7061993,
    "tgn:name":"Auertal",
    "tgn:placetype":[
        "aat:300008761"
    ]
},
  "bbox": [],
  "geometry": {"coordinates":[10.333333,48.716667],"type":"Point"}
}