{
  "id": 7233132,
  "type": "Feature",
  "properties": {
    "tgn:hierarchy":[
        "tgn:7233132",
        "tgn:4003773",
        "tgn:7001395",
        "tgn:1000003",
        "tgn:1000074",
        "tgn:7029392"
    ],
    "tgn:id":7233132,
    "tgn:name":"K\u00e1to Potami\u00e1",
    "tgn:placetype":[
        "aat:300008347"
    ]
},
  "bbox": [],
  "geometry": {"coordinates":[21.488333,39.075278],"type":"Point"}
}