{
  "id": 7363730,
  "type": "Feature",
  "properties": {
    "tgn:hierarchy":[
        "tgn:7363730",
        "tgn:7005581",
        "tgn:1000001",
        "tgn:7005560",
        "tgn:7029392"
    ],
    "tgn:id":7363730,
    "tgn:name":"El Gato, Arroyo",
    "tgn:placetype":[
        "aat:300266554",
        "aat:300008699"
    ]
},
  "bbox": [],
  "geometry": {"coordinates":[-104.466667,29.166667],"type":"Point"}
}