{
  "id": 2060702,
  "type": "Feature",
  "properties": {
    "tgn:hierarchy":[
        "tgn:2060702",
        "tgn:1000001",
        "tgn:2001179",
        "tgn:7012149",
        "tgn:7007523",
        "tgn:7029392"
    ],
    "tgn:id":2060702,
    "tgn:name":"Tilsit",
    "tgn:placetype":[
        "aat:300008347"
    ]
},
  "bbox": [],
  "geometry": {"coordinates":[-89.7333,37.3167],"type":"Point"}
}