{
  "id": 7576238,
  "type": "Feature",
  "properties": {
    "tgn:hierarchy":[
        "tgn:7576238",
        "tgn:1009838",
        "tgn:7000204",
        "tgn:1000004",
        "tgn:7000198",
        "tgn:1008372",
        "tgn:7029392"
    ],
    "tgn:id":7576238,
    "tgn:name:en":"Karen",
    "tgn:placetype":[
        "aat:300008347"
    ]
},
  "bbox": [],
  "geometry": {"coordinates":[92.883333,12.85],"type":"Point"}
}