{
  "id": 7481294,
  "type": "Feature",
  "properties": {
    "tgn:hierarchy":[
        "tgn:7481294",
        "tgn:1000004",
        "tgn:7471332",
        "tgn:1000141",
        "tgn:7029392"
    ],
    "tgn:id":7481294,
    "tgn:name":"Qingwo Pi",
    "tgn:placetype":[
        "aat:300008688"
    ]
},
  "bbox": [],
  "geometry": {"coordinates":[121.050833,24.773611],"type":"Point"}
}