{
  "id": 7164983,
  "type": "Feature",
  "properties": {
    "tgn:hierarchy":[
        "tgn:7164983",
        "tgn:1000003",
        "tgn:7003685",
        "tgn:7000084",
        "tgn:7029392"
    ],
    "tgn:id":7164983,
    "tgn:name":"Hundsh\u00fcbel",
    "tgn:placetype":[
        "aat:300008347"
    ]
},
  "bbox": [],
  "geometry": {"coordinates":[12.566667,50.55],"type":"Point"}
}