{
  "id": 2545400,
  "type": "Feature",
  "properties": {
    "tgn:hierarchy":[
        "tgn:2545400",
        "tgn:1000001",
        "tgn:2001415",
        "tgn:7012149",
        "tgn:7007526",
        "tgn:7029392"
    ],
    "tgn:id":2545400,
    "tgn:name":"North Fork Big Creek",
    "tgn:placetype":[
        "aat:300008706"
    ]
},
  "bbox": [],
  "geometry": {"coordinates":[-117.0833,39.35],"type":"Point"}
}