{
  "id": 2417317,
  "type": "Feature",
  "properties": {
    "tgn:hierarchy":[
        "tgn:2417317",
        "tgn:1000001",
        "tgn:7012149",
        "tgn:2000797",
        "tgn:7007255",
        "tgn:7029392"
    ],
    "tgn:id":2417317,
    "tgn:name":"Jacks Fork",
    "tgn:placetype":[
        "aat:300008699"
    ]
},
  "bbox": [],
  "geometry": {"coordinates":[-83.0667,36.8667],"type":"Point"}
}