{
  "id": 2172037,
  "type": "Feature",
  "properties": {
    "tgn:hierarchy":[
        "tgn:2172037",
        "tgn:1000001",
        "tgn:2002133",
        "tgn:7012149",
        "tgn:7007828",
        "tgn:7029392"
    ],
    "tgn:id":2172037,
    "tgn:name":"Bigelow Basin",
    "tgn:placetype":[
        "aat:300386845"
    ]
},
  "bbox": [],
  "geometry": {"coordinates":[-72.45,44.7167],"type":"Point"}
}