{
  "id": 2126812,
  "type": "Feature",
  "properties": {
    "tgn:hierarchy":[
        "tgn:2126812",
        "tgn:7006450",
        "tgn:1000001",
        "tgn:7030517",
        "tgn:7012149",
        "tgn:7029392"
    ],
    "tgn:id":2126812,
    "tgn:name":"Agripina River",
    "tgn:placetype":[
        "aat:300008707"
    ]
},
  "bbox": [],
  "geometry": {"coordinates":[-156.5167,57.1667],"type":"Point"}
}