{
  "id": 2672924,
  "type": "Feature",
  "properties": {
    "tgn:hierarchy":[
        "tgn:2672924",
        "tgn:1000001",
        "tgn:2001262",
        "tgn:7012149",
        "tgn:7007524",
        "tgn:7029392"
    ],
    "tgn:id":2672924,
    "tgn:name":"Snake Creek",
    "tgn:placetype":[
        "aat:300008706"
    ]
},
  "bbox": [],
  "geometry": {"coordinates":[-109.3333,48.2333],"type":"Point"}
}