{
  "id": 2379290,
  "type": "Feature",
  "properties": {
    "tgn:hierarchy":[
        "tgn:2379290",
        "tgn:7006450",
        "tgn:1000001",
        "tgn:7012149",
        "tgn:7029392"
    ],
    "tgn:id":2379290,
    "tgn:name":"Harvard Glacier",
    "tgn:placetype":[
        "aat:300008835"
    ]
},
  "bbox": [],
  "geometry": {"coordinates":[-147.4333,61.3833],"type":"Point"}
}