{
  "id": 7501751,
  "type": "Feature",
  "properties": {
    "tgn:hierarchy":[
        "tgn:7501751",
        "tgn:7001004",
        "tgn:1000004",
        "tgn:1000141",
        "tgn:7029392"
    ],
    "tgn:id":7501751,
    "tgn:name":"Diqihao Qiao",
    "tgn:placetype":[
        "aat:300007836"
    ]
},
  "bbox": [],
  "geometry": {"coordinates":[120.431389,22.926667],"type":"Point"}
}