{
  "id": 2657610,
  "type": "Feature",
  "properties": {
    "tgn:hierarchy":[
        "tgn:2657610",
        "tgn:1000001",
        "tgn:7012149",
        "tgn:7029392"
    ],
    "tgn:id":2657610,
    "tgn:name":"Shelby Creek",
    "tgn:placetype":[
        "aat:300008706"
    ]
},
  "bbox": [],
  "geometry": {"coordinates":[-87.8333,36.6667],"type":"Point"}
}