{
  "id": 7419345,
  "type": "Feature",
  "properties": {
    "tgn:hierarchy":[
        "tgn:7419345",
        "tgn:1000001",
        "tgn:7005589",
        "tgn:7005560",
        "tgn:7029392"
    ],
    "tgn:id":7419345,
    "tgn:name:es":"Mar\u00eda Luisa",
    "tgn:placetype":[
        "aat:300008347"
    ]
},
  "bbox": [],
  "geometry": {"coordinates":[-99.843611,27.381944],"type":"Point"}
}