{
  "id": 7416741,
  "type": "Feature",
  "properties": {
    "tgn:hierarchy":[
        "tgn:7416741",
        "tgn:7005584",
        "tgn:1000001",
        "tgn:7005560",
        "tgn:7029392"
    ],
    "tgn:id":7416741,
    "tgn:name":"Galera de la Grulla",
    "tgn:placetype":[
        "aat:300008347"
    ]
},
  "bbox": [],
  "geometry": {"coordinates":[-101.649444,20.636667],"type":"Point"}
}