{
  "id": 2686380,
  "type": "Feature",
  "properties": {
    "tgn:hierarchy":[
        "tgn:2686380",
        "tgn:1000001",
        "tgn:2000666",
        "tgn:7012149",
        "tgn:7007254",
        "tgn:7029392"
    ],
    "tgn:id":2686380,
    "tgn:name":"Spring Creek",
    "tgn:placetype":[
        "aat:300008706"
    ]
},
  "bbox": [],
  "geometry": {"coordinates":[-95.75,39.8833],"type":"Point"}
}