{
  "id": 7284610,
  "type": "Feature",
  "properties": {
    "tgn:hierarchy":[
        "tgn:7284610",
        "tgn:1001699",
        "tgn:1000049",
        "tgn:1000002",
        "tgn:7029392"
    ],
    "tgn:id":7284610,
    "tgn:name":"Punahue",
    "tgn:placetype":[
        "aat:300000206"
    ]
},
  "bbox": [],
  "geometry": {"coordinates":[-72.566667,-39.866667],"type":"Point"}
}