{
  "id": 2391492,
  "type": "Feature",
  "properties": {
    "tgn:hierarchy":[
        "tgn:2391492",
        "tgn:1000001",
        "tgn:1002210",
        "tgn:7012149",
        "tgn:7007706",
        "tgn:7029392"
    ],
    "tgn:id":2391492,
    "tgn:name":"Hillman Ridge",
    "tgn:placetype":[
        "aat:300266640"
    ]
},
  "bbox": [],
  "geometry": {"coordinates":[-83.85,38.8333],"type":"Point"}
}