<<<<<<< HEAD
{
  "id": 2767710,
  "type": "Feature",
  "properties": {
    "tgn:hierarchy":[
        "tgn:2767710",
        "tgn:1002716",
        "tgn:1000001",
        "tgn:7012149",
        "tgn:7007711",
        "tgn:7029392"
    ],
    "tgn:id":2767710,
    "tgn:name":"Whitehall",
    "tgn:placetype":[
        "aat:300008347"
    ]
},
  "bbox": [],
  "geometry": {"coordinates":[-71.2667,41.5],"type":"Point"}
}
=======
{"geometry":{"type":"Point","coordinates":[-71.266700,41.500000]},"type":"Feature","properties":{"hierarchy":["tgn:2767710","tgn:1002716","tgn:1000001","tgn:7012149","tgn:7007711","tgn:7029392"],"placetype":["aat:300008347"],"id":2767710,"name:xx":"Whitehall"}}
>>>>>>> 03f74aca74312dbeaf24d7e61306dd6a786dc3d0
