{
  "id": 2703555,
  "type": "Feature",
  "properties": {
    "tgn:hierarchy":[
        "tgn:2703555",
        "tgn:1000001",
        "tgn:7012149",
        "tgn:7007157",
        "tgn:1002957",
        "tgn:7029392"
    ],
    "tgn:id":2703555,
    "tgn:name":"Summit Ridge",
    "tgn:placetype":[
        "aat:300266640"
    ]
},
  "bbox": [],
  "geometry": {"coordinates":[-120.15,38.0167],"type":"Point"}
}