{
  "id": 2240828,
  "type": "Feature",
  "properties": {
    "tgn:hierarchy":[
        "tgn:2240828",
        "tgn:1000001",
        "tgn:1003029",
        "tgn:7012149",
        "tgn:7007828",
        "tgn:7029392"
    ],
    "tgn:id":2240828,
    "tgn:name":"Clara Lake",
    "tgn:placetype":[
        "aat:300008680"
    ]
},
  "bbox": [],
  "geometry": {"coordinates":[-72.8667,42.7833],"type":"Point"}
}