<<<<<<< HEAD
{
  "id": 2255992,
  "type": "Feature",
  "properties": {
    "tgn:hierarchy":[
        "tgn:2255992",
        "tgn:1000001",
        "tgn:7012149",
        "tgn:7007157",
        "tgn:1002857",
        "tgn:7029392"
    ],
    "tgn:id":2255992,
    "tgn:name":"Copper King Mine",
    "tgn:placetype":[
        "aat:300000390"
    ]
},
  "bbox": [],
  "geometry": {"coordinates":[-115.1167,34.5833],"type":"Point"}
}
=======
{"geometry":{"type":"Point","coordinates":[-115.116700,34.583300]},"type":"Feature","properties":{"hierarchy":["tgn:2255992","tgn:1000001","tgn:7012149","tgn:7007157","tgn:1002857","tgn:7029392"],"placetype":["aat:300000390"],"id":2255992,"name:xx":"Copper King Mine"}}
>>>>>>> 03f74aca74312dbeaf24d7e61306dd6a786dc3d0
