{
  "id": 1049168,
  "type": "Feature",
  "properties": {
    "tgn:hierarchy":[
        "tgn:1049168",
        "tgn:7024116",
        "tgn:1000003",
        "tgn:7006366",
        "tgn:7029392"
    ],
    "tgn:id":1049168,
    "tgn:name":"Kowal",
    "tgn:placetype":[
        "aat:300008347"
    ]
},
  "bbox": [],
  "geometry": {"coordinates":[19.0833,52.5333],"type":"Point"}
}