{
  "id": 2430645,
  "type": "Feature",
  "properties": {
    "tgn:hierarchy":[
        "tgn:2430645",
        "tgn:1000001",
        "tgn:7012149",
        "tgn:2000968",
        "tgn:7007520",
        "tgn:7029392"
    ],
    "tgn:id":2430645,
    "tgn:name":"Kalkaska State Forest",
    "tgn:placetype":[
        "aat:300008863"
    ]
},
  "bbox": [],
  "geometry": {"coordinates":[-84.9333,44.5333],"type":"Point"}
}