{
  "id": 7398966,
  "type": "Feature",
  "properties": {
    "tgn:hierarchy":[
        "tgn:7398966",
        "tgn:1000001",
        "tgn:1001893",
        "tgn:7005560",
        "tgn:7029392"
    ],
    "tgn:id":7398966,
    "tgn:name":"Zaragoza",
    "tgn:placetype":[
        "aat:300008347"
    ]
},
  "bbox": [],
  "geometry": {"coordinates":[-99.751389,19.894444],"type":"Point"}
}