<<<<<<< HEAD
{
  "id": 7361025,
  "type": "Feature",
  "properties": {
    "tgn:hierarchy":[
        "tgn:7361025",
        "tgn:7005581",
        "tgn:1000001",
        "tgn:7005560",
        "tgn:7029392"
    ],
    "tgn:id":7361025,
    "tgn:name":"El Comedor",
    "tgn:placetype":[
        "aat:300008347"
    ]
},
  "bbox": [],
  "geometry": {"coordinates":[-104.766667,30.266667],"type":"Point"}
}
=======
{"geometry":{"type":"Point","coordinates":[-104.766667,30.266667]},"type":"Feature","properties":{"hierarchy":["tgn:7361025","tgn:7005581","tgn:1000001","tgn:7005560","tgn:7029392"],"placetype":["aat:300008347"],"id":7361025,"name:xx":"El Comedor"}}
>>>>>>> 03f74aca74312dbeaf24d7e61306dd6a786dc3d0
