{
  "id": 2454274,
  "type": "Feature",
  "properties": {
    "tgn:hierarchy":[
        "tgn:2454274",
        "tgn:1000001",
        "tgn:7012149",
        "tgn:2001442",
        "tgn:7007566",
        "tgn:7029392"
    ],
    "tgn:id":2454274,
    "tgn:name":"Little Creek Spring",
    "tgn:placetype":[
        "aat:300008697"
    ]
},
  "bbox": [],
  "geometry": {"coordinates":[-105.7167,33.4167],"type":"Point"}
}