<<<<<<< HEAD
{
  "id": 7377844,
  "type": "Feature",
  "properties": {
    "tgn:hierarchy":[
        "tgn:7377844",
        "tgn:1000001",
        "tgn:7005595",
        "tgn:7005560",
        "tgn:7029392"
    ],
    "tgn:id":7377844,
    "tgn:name":"La Pitahaya",
    "tgn:placetype":[
        "aat:300008347"
    ]
},
  "bbox": [],
  "geometry": {"coordinates":[-108.45,25.833333],"type":"Point"}
}
=======
{"geometry":{"type":"Point","coordinates":[-108.450000,25.833333]},"type":"Feature","properties":{"hierarchy":["tgn:7377844","tgn:1000001","tgn:7005595","tgn:7005560","tgn:7029392"],"placetype":["aat:300008347"],"id":7377844,"name:xx":"La Pitahaya"}}
>>>>>>> 03f74aca74312dbeaf24d7e61306dd6a786dc3d0
