{
  "id": 7132124,
  "type": "Feature",
  "properties": {
    "tgn:hierarchy":[
        "tgn:7132124",
        "tgn:1000003",
        "tgn:7003676",
        "tgn:7000084",
        "tgn:7029392"
    ],
    "tgn:id":7132124,
    "tgn:name":"Mausethal-Bach",
    "tgn:placetype":[
        "aat:300008699"
    ]
},
  "bbox": [],
  "geometry": {"coordinates":[10.633333,53.233333],"type":"Point"}
}