{
  "id": 2156099,
  "type": "Feature",
  "properties": {
    "tgn:hierarchy":[
        "tgn:2156099",
        "tgn:1000001",
        "tgn:7006451",
        "tgn:2000092",
        "tgn:7012149",
        "tgn:7029392"
    ],
    "tgn:id":2156099,
    "tgn:name":"Beard Canyon",
    "tgn:placetype":[
        "aat:300008761"
    ]
},
  "bbox": [],
  "geometry": {"coordinates":[-111.6667,35.3333],"type":"Point"}
}