{
  "id": 2462873,
  "type": "Feature",
  "properties": {
    "tgn:hierarchy":[
        "tgn:2462873",
        "tgn:2001466",
        "tgn:1000001",
        "tgn:7012149",
        "tgn:7007709",
        "tgn:7029392"
    ],
    "tgn:id":2462873,
    "tgn:name":"Littles Quarters",
    "tgn:placetype":[
        "aat:300008347"
    ]
},
  "bbox": [],
  "geometry": {"coordinates":[-80.1833,34.8167],"type":"Point"}
}