{
  "id": 7515020,
  "type": "Feature",
  "properties": {
    "tgn:hierarchy":[
        "tgn:7515020",
        "tgn:1009227",
        "tgn:1000226",
        "tgn:7018437",
        "tgn:1000006",
        "tgn:7029392"
    ],
    "tgn:id":7515020,
    "tgn:name:en":"Caria",
    "tgn:placetype":[
        "aat:300008798"
    ]
},
  "bbox": [],
  "geometry": {"coordinates":[168.533333,-44.366667],"type":"Point"}
}