{
  "id": 7401342,
  "type": "Feature",
  "properties": {
    "tgn:hierarchy":[
        "tgn:7401342",
        "tgn:1000001",
        "tgn:7005599",
        "tgn:7005560",
        "tgn:7029392"
    ],
    "tgn:id":7401342,
    "tgn:name":"Nuevo Horizonte",
    "tgn:placetype":[
        "aat:300008347"
    ]
},
  "bbox": [],
  "geometry": {"coordinates":[-98.322222,21.725],"type":"Point"}
}