<<<<<<< HEAD
{
  "id": 7375643,
  "type": "Feature",
  "properties": {
    "tgn:hierarchy":[
        "tgn:7375643",
        "tgn:7005586",
        "tgn:1000001",
        "tgn:7005560",
        "tgn:7029392"
    ],
    "tgn:id":7375643,
    "tgn:name":"Las Fuentes",
    "tgn:placetype":[
        "aat:300008347"
    ]
},
  "bbox": [],
  "geometry": {"coordinates":[-104.066667,20.766667],"type":"Point"}
}
=======
{"geometry":{"type":"Point","coordinates":[-104.066667,20.766667]},"type":"Feature","properties":{"hierarchy":["tgn:7375643","tgn:7005586","tgn:1000001","tgn:7005560","tgn:7029392"],"placetype":["aat:300008347"],"id":7375643,"name:xx":"Las Fuentes"}}
>>>>>>> 03f74aca74312dbeaf24d7e61306dd6a786dc3d0
