{
  "id": 1005360,
  "type": "Feature",
  "properties": {
    "tgn:hierarchy":[
        "tgn:1005360",
        "tgn:7003138",
        "tgn:1000003",
        "tgn:7003080",
        "tgn:1000080",
        "tgn:7029392"
    ],
    "tgn:id":1005360,
    "tgn:name":"Ponte Galeria",
    "tgn:placetype":[
        "aat:300008347"
    ]
},
  "bbox": [],
  "geometry": {"coordinates":[12.35,41.816667],"type":"Point"}
}