{
  "id": 2426572,
  "type": "Feature",
  "properties": {
    "tgn:hierarchy":[
        "tgn:2426572",
        "tgn:1000001",
        "tgn:7012149",
        "tgn:2001930",
        "tgn:7007825",
        "tgn:7029392"
    ],
    "tgn:id":2426572,
    "tgn:name":"Jones Hollow",
    "tgn:placetype":[
        "aat:300008761"
    ]
},
  "bbox": [],
  "geometry": {"coordinates":[-86.9833,35.95],"type":"Point"}
}