{
  "id": 7373311,
  "type": "Feature",
  "properties": {
    "tgn:hierarchy":[
        "tgn:7373311",
        "tgn:1000001",
        "tgn:7005589",
        "tgn:7005560",
        "tgn:7029392"
    ],
    "tgn:id":7373311,
    "tgn:name":"Rancho La Ganadera",
    "tgn:placetype":[
        "aat:300000241"
    ]
},
  "bbox": [],
  "geometry": {"coordinates":[-100.383333,27.183333],"type":"Point"}
}