{
  "id": 7346837,
  "type": "Feature",
  "properties": {
    "tgn:hierarchy":[
        "tgn:7346837",
        "tgn:7001158",
        "tgn:7002850",
        "tgn:1000003",
        "tgn:1000095",
        "tgn:7029392"
    ],
    "tgn:id":7346837,
    "tgn:name":"Asturianos",
    "tgn:placetype":[
        "aat:300008347"
    ]
},
  "bbox": [],
  "geometry": {"coordinates":[-6.483333,42.05],"type":"Point"}
}