{
  "id": 2368963,
  "type": "Feature",
  "properties": {
    "tgn:hierarchy":[
        "tgn:2368963",
        "tgn:1000001",
        "tgn:2000307",
        "tgn:7012149",
        "tgn:7007248",
        "tgn:7029392"
    ],
    "tgn:id":2368963,
    "tgn:name":"Gum Branch",
    "tgn:placetype":[
        "aat:300008699"
    ]
},
  "bbox": [],
  "geometry": {"coordinates":[-81.7667,32.3333],"type":"Point"}
}