{
  "id": 7290504,
  "type": "Feature",
  "properties": {
    "tgn:hierarchy":[
        "tgn:7290504",
        "tgn:1001692",
        "tgn:1000049",
        "tgn:1000002",
        "tgn:7029392"
    ],
    "tgn:id":7290504,
    "tgn:name":"Curaco, Estero",
    "tgn:placetype":[
        "aat:300008699"
    ]
},
  "bbox": [],
  "geometry": {"coordinates":[-72.116667,-39.033333],"type":"Point"}
}