{
  "id": 1114271,
  "type": "Feature",
  "properties": {
    "tgn:hierarchy":[
        "tgn:1114271",
        "tgn:7016678",
        "tgn:7000204",
        "tgn:1000004",
        "tgn:7000198",
        "tgn:7029392"
    ],
    "tgn:id":1114271,
    "tgn:name:en":"Sombrero Channel",
    "tgn:placetype":[
        "aat:300008713"
    ]
},
  "bbox": [],
  "geometry": {"coordinates":[93.583333,7.683333],"type":"Point"}
}