{
  "id": 2126556,
  "type": "Feature",
  "properties": {
    "tgn:hierarchy":[
        "tgn:2126556",
        "tgn:7006450",
        "tgn:1000001",
        "tgn:2124012",
        "tgn:7012149",
        "tgn:7029392"
    ],
    "tgn:id":2126556,
    "tgn:name":"Afognak Mountain",
    "tgn:placetype":[
        "aat:300008798"
    ]
},
  "bbox": [],
  "geometry": {"coordinates":[-152.8833,58.1167],"type":"Point"}
}