<<<<<<< HEAD
{
  "id": 2769633,
  "type": "Feature",
  "properties": {
    "tgn:hierarchy":[
        "tgn:2769633",
        "tgn:1000001",
        "tgn:7012149",
        "tgn:2002336",
        "tgn:7007922",
        "tgn:7029392"
    ],
    "tgn:id":2769633,
    "tgn:name":"Wien",
    "tgn:placetype":[
        "aat:300008347"
    ]
},
  "bbox": [],
  "geometry": {"coordinates":[-90.0167,44.9],"type":"Point"}
}
=======
{"geometry":{"type":"Point","coordinates":[-90.016700,44.900000]},"type":"Feature","properties":{"hierarchy":["tgn:2769633","tgn:1000001","tgn:7012149","tgn:2002336","tgn:7007922","tgn:7029392"],"placetype":["aat:300008347"],"id":2769633,"name:xx":"Wien"}}
>>>>>>> 03f74aca74312dbeaf24d7e61306dd6a786dc3d0
