{
  "id": 2171903,
  "type": "Feature",
  "properties": {
    "tgn:hierarchy":[
        "tgn:2171903",
        "tgn:1000001",
        "tgn:7012149",
        "tgn:2000208",
        "tgn:7007158",
        "tgn:7029392"
    ],
    "tgn:id":2171903,
    "tgn:name":"Big Water Reservoir Number Five",
    "tgn:placetype":[
        "aat:300006191"
    ]
},
  "bbox": [],
  "geometry": {"coordinates":[-108.7333,37.8167],"type":"Point"}
}