{
  "id": 7388259,
  "type": "Feature",
  "properties": {
    "tgn:hierarchy":[
        "tgn:7388259",
        "tgn:7005583",
        "tgn:1000001",
        "tgn:7005560",
        "tgn:7029392"
    ],
    "tgn:id":7388259,
    "tgn:name":"Piedra Ancha",
    "tgn:placetype":[
        "aat:300008347"
    ]
},
  "bbox": [],
  "geometry": {"coordinates":[-105.366667,23.333333],"type":"Point"}
}