{
  "id": 2564816,
  "type": "Feature",
  "properties": {
    "tgn:hierarchy":[
        "tgn:2564816",
        "tgn:1000001",
        "tgn:7012149",
        "tgn:7014398",
        "tgn:7013961",
        "tgn:7029392"
    ],
    "tgn:id":2564816,
    "tgn:name":"Paddy Run",
    "tgn:placetype":[
        "aat:300008699"
    ]
},
  "bbox": [],
  "geometry": {"coordinates":[-79.2833,38.6167],"type":"Point"}
}