<<<<<<< HEAD
{
  "id": 7171701,
  "type": "Feature",
  "properties": {
    "tgn:hierarchy":[
        "tgn:7171701",
        "tgn:1000003",
        "tgn:7003678",
        "tgn:7000084",
        "tgn:7029392"
    ],
    "tgn:id":7171701,
    "tgn:name":"F\u00f6rsterei Hemelberg",
    "tgn:placetype":[
        "aat:300004792"
    ]
},
  "bbox": [],
  "geometry": {"coordinates":[9.55,51.5],"type":"Point"}
}
=======
{"geometry":{"type":"Point","coordinates":[9.550000,51.500000]},"type":"Feature","properties":{"hierarchy":["tgn:7171701","tgn:1000003","tgn:7003678","tgn:7000084","tgn:7029392"],"placetype":["aat:300004792"],"id":7171701,"name:xx":"F\u00f6rsterei Hemelberg"}}
>>>>>>> 03f74aca74312dbeaf24d7e61306dd6a786dc3d0
