<<<<<<< HEAD
{
  "id": 7353272,
  "type": "Feature",
  "properties": {
    "tgn:hierarchy":[
        "tgn:7353272",
        "tgn:7005580",
        "tgn:1000001",
        "tgn:7005560",
        "tgn:7029392"
    ],
    "tgn:id":7353272,
    "tgn:name":"Finca Buena Vista",
    "tgn:placetype":[
        "aat:300000206"
    ]
},
  "bbox": [],
  "geometry": {"coordinates":[-92.2,14.966667],"type":"Point"}
}
=======
{"geometry":{"type":"Point","coordinates":[-92.200000,14.966667]},"type":"Feature","properties":{"hierarchy":["tgn:7353272","tgn:7005580","tgn:1000001","tgn:7005560","tgn:7029392"],"placetype":["aat:300000206"],"id":7353272,"name:xx":"Finca Buena Vista"}}
>>>>>>> 03f74aca74312dbeaf24d7e61306dd6a786dc3d0
