{
  "id": 2782287,
  "type": "Feature",
  "properties": {
    "tgn:hierarchy":[
        "tgn:2782287",
        "tgn:1000001",
        "tgn:7012149",
        "tgn:2000627",
        "tgn:7007253",
        "tgn:7029392"
    ],
    "tgn:id":2782287,
    "tgn:name":"Woodward Glen",
    "tgn:placetype":[
        "aat:300008761"
    ]
},
  "bbox": [],
  "geometry": {"coordinates":[-95.9833,42.1833],"type":"Point"}
}