{
  "id": 2614331,
  "type": "Feature",
  "properties": {
    "tgn:hierarchy":[
        "tgn:2614331",
        "tgn:1000001",
        "tgn:7012149",
        "tgn:1002755",
        "tgn:7007523",
        "tgn:7029392"
    ],
    "tgn:id":2614331,
    "tgn:name":"Rehard Lake",
    "tgn:placetype":[
        "aat:300006191"
    ]
},
  "bbox": [],
  "geometry": {"coordinates":[-91.75,38.65],"type":"Point"}
}