{
  "id": 2751653,
  "type": "Feature",
  "properties": {
    "tgn:hierarchy":[
        "tgn:2751653",
        "tgn:1002157",
        "tgn:1000001",
        "tgn:7012149",
        "tgn:7007565",
        "tgn:7029392"
    ],
    "tgn:id":2751653,
    "tgn:name":"Warners Mill Stream",
    "tgn:placetype":[
        "aat:300008699"
    ]
},
  "bbox": [],
  "geometry": {"coordinates":[-74.7833,39.3333],"type":"Point"}
}