{
  "id": 2548448,
  "type": "Feature",
  "properties": {
    "tgn:hierarchy":[
        "tgn:2548448",
        "tgn:1000001",
        "tgn:7012149",
        "tgn:2001709",
        "tgn:7007708",
        "tgn:7029392"
    ],
    "tgn:id":2548448,
    "tgn:name":"North Loggerhead Reservoir",
    "tgn:placetype":[
        "aat:300006191"
    ]
},
  "bbox": [],
  "geometry": {"coordinates":[-119.3833,42.9667],"type":"Point"}
}