{
  "id": 7181377,
  "type": "Feature",
  "properties": {
    "tgn:hierarchy":[
        "tgn:7181377",
        "tgn:7003669",
        "tgn:1000003",
        "tgn:7000084",
        "tgn:7029392"
    ],
    "tgn:id":7181377,
    "tgn:name":"Gei\u00df-B\u00fchl",
    "tgn:placetype":[
        "aat:300008777"
    ]
},
  "bbox": [],
  "geometry": {"coordinates":[12.35,49.783333],"type":"Point"}
}