{
  "id": 7320974,
  "type": "Feature",
  "properties": {
    "tgn:hierarchy":[
        "tgn:7320974",
        "tgn:1001768",
        "tgn:1000049",
        "tgn:1000002",
        "tgn:7029392"
    ],
    "tgn:id":7320974,
    "tgn:name":"Campiche",
    "tgn:placetype":[
        "aat:300008347"
    ]
},
  "bbox": [],
  "geometry": {"coordinates":[-71.45,-32.733333],"type":"Point"}
}