{
  "id": 2191246,
  "type": "Feature",
  "properties": {
    "tgn:hierarchy":[
        "tgn:2191246",
        "tgn:1000001",
        "tgn:7006451",
        "tgn:7012149",
        "tgn:2000103",
        "tgn:7029392"
    ],
    "tgn:id":2191246,
    "tgn:name":"Bozarth Point",
    "tgn:placetype":[
        "aat:300008850"
    ]
},
  "bbox": [],
  "geometry": {"coordinates":[-113.2333,34.6667],"type":"Point"}
}