{
  "id": 7134993,
  "type": "Feature",
  "properties": {
    "tgn:hierarchy":[
        "tgn:7134993",
        "tgn:7003692",
        "tgn:1000003",
        "tgn:7000084",
        "tgn:7029392"
    ],
    "tgn:id":7134993,
    "tgn:name":"M\u00fchllehen",
    "tgn:placetype":[
        "aat:300008347"
    ]
},
  "bbox": [],
  "geometry": {"coordinates":[8.416667,48.166667],"type":"Point"}
}