{
  "id": 2495165,
  "type": "Feature",
  "properties": {
    "tgn:hierarchy":[
        "tgn:2495165",
        "tgn:1000001",
        "tgn:7012149",
        "tgn:2001420",
        "tgn:7007526",
        "tgn:7029392"
    ],
    "tgn:id":2495165,
    "tgn:name":"Mary Ann Canyon",
    "tgn:placetype":[
        "aat:300008761"
    ]
},
  "bbox": [],
  "geometry": {"coordinates":[-114.3833,39.05],"type":"Point"}
}