{
  "id": 7576207,
  "type": "Feature",
  "properties": {
    "tgn:hierarchy":[
        "tgn:7576207",
        "tgn:1000004",
        "tgn:7000198",
        "tgn:7001797",
        "tgn:7029392"
    ],
    "tgn:id":7576207,
    "tgn:name:en":"L\u0101lgudi",
    "tgn:placetype":[
        "aat:300008347"
    ]
},
  "bbox": [],
  "geometry": {"coordinates":[78.833333,10.866667],"type":"Point"}
}