{
  "id": 7439176,
  "type": "Feature",
  "properties": {
    "tgn:hierarchy":[
        "tgn:7439176",
        "tgn:7005581",
        "tgn:1000001",
        "tgn:7005560",
        "tgn:7029392"
    ],
    "tgn:id":7439176,
    "tgn:name":"Sub\u00eda",
    "tgn:placetype":[
        "aat:300008347"
    ]
},
  "bbox": [],
  "geometry": {"coordinates":[-108.383333,28.416667],"type":"Point"}
}