{
  "id": 2505397,
  "type": "Feature",
  "properties": {
    "tgn:hierarchy":[
        "tgn:2505397",
        "tgn:1000001",
        "tgn:7012149",
        "tgn:2001036",
        "tgn:7007521",
        "tgn:7029392"
    ],
    "tgn:id":2505397,
    "tgn:name":"Melon Lake",
    "tgn:placetype":[
        "aat:300008680"
    ]
},
  "bbox": [],
  "geometry": {"coordinates":[-91.3167,48.0667],"type":"Point"}
}