{
  "id": 2202652,
  "type": "Feature",
  "properties": {
    "tgn:hierarchy":[
        "tgn:2202652",
        "tgn:1000001",
        "tgn:7012149",
        "tgn:2001493",
        "tgn:7007709",
        "tgn:7029392"
    ],
    "tgn:id":2202652,
    "tgn:name":"Buck Swamp",
    "tgn:placetype":[
        "aat:300008699"
    ]
},
  "bbox": [],
  "geometry": {"coordinates":[-77.7167,35.9167],"type":"Point"}
}