{
  "id": 2552372,
  "type": "Feature",
  "properties": {
    "tgn:hierarchy":[
        "tgn:2552372",
        "tgn:1000001",
        "tgn:7012149",
        "tgn:1002453",
        "tgn:7007706",
        "tgn:7029392"
    ],
    "tgn:id":2552372,
    "tgn:name":"Number Twentyeight Ditch",
    "tgn:placetype":[
        "aat:300006075"
    ]
},
  "bbox": [],
  "geometry": {"coordinates":[-83.75,40.7833],"type":"Point"}
}