{
  "id": 2680913,
  "type": "Feature",
  "properties": {
    "tgn:hierarchy":[
        "tgn:2680913",
        "tgn:1000001",
        "tgn:7012149",
        "tgn:2001283",
        "tgn:7007524",
        "tgn:7029392"
    ],
    "tgn:id":2680913,
    "tgn:name":"South Lamoose Creek",
    "tgn:placetype":[
        "aat:300008706"
    ]
},
  "bbox": [],
  "geometry": {"coordinates":[-114.0167,47.2167],"type":"Point"}
}