{
  "id": 7578842,
  "type": "Feature",
  "properties": {
    "tgn:hierarchy":[
        "tgn:7578842",
        "tgn:1000004",
        "tgn:7000198",
        "tgn:1001886",
        "tgn:7029392"
    ],
    "tgn:id":7578842,
    "tgn:name:en":"Tangasseri Point",
    "tgn:placetype":[
        "aat:300386846"
    ]
},
  "bbox": [],
  "geometry": {"coordinates":[76.583333,8.883333],"type":"Point"}
}