<<<<<<< HEAD
{
  "id": 2339248,
  "type": "Feature",
  "properties": {
    "tgn:hierarchy":[
        "tgn:2339248",
        "tgn:1000001",
        "tgn:7012149",
        "tgn:2001230",
        "tgn:7007523",
        "tgn:7029392"
    ],
    "tgn:id":2339248,
    "tgn:name":"Franz Branch",
    "tgn:placetype":[
        "aat:300008699"
    ]
},
  "bbox": [],
  "geometry": {"coordinates":[-91.7333,37.9667],"type":"Point"}
}
=======
{"geometry":{"type":"Point","coordinates":[-91.733300,37.966700]},"type":"Feature","properties":{"hierarchy":["tgn:2339248","tgn:1000001","tgn:7012149","tgn:2001230","tgn:7007523","tgn:7029392"],"placetype":["aat:300008699"],"id":2339248,"name:xx":"Franz Branch"}}
>>>>>>> 03f74aca74312dbeaf24d7e61306dd6a786dc3d0
