{
  "id": 1134975,
  "type": "Feature",
  "properties": {
    "tgn:hierarchy":[
        "tgn:1134975",
        "tgn:1000001",
        "tgn:7012149",
        "tgn:7007523",
        "tgn:7029392"
    ],
    "tgn:id":1134975,
    "tgn:name":"Wakenda Creek",
    "tgn:placetype":[
        "aat:300008706"
    ]
},
  "bbox": [],
  "geometry": {"coordinates":[-93.8833,39.4333],"type":"Point"}
}