{
  "id": 7101752,
  "type": "Feature",
  "properties": {
    "tgn:hierarchy":[
        "tgn:7101752",
        "tgn:7003669",
        "tgn:1000003",
        "tgn:7000084",
        "tgn:7029392"
    ],
    "tgn:id":7101752,
    "tgn:name":"Rothenstetter",
    "tgn:placetype":[
        "aat:300008863"
    ]
},
  "bbox": [],
  "geometry": {"coordinates":[11.966667,49.566667],"type":"Point"}
}