{
  "id": 2238070,
  "type": "Feature",
  "properties": {
    "tgn:hierarchy":[
        "tgn:2238070",
        "tgn:1000001",
        "tgn:2001416",
        "tgn:7012149",
        "tgn:7007526",
        "tgn:7029392"
    ],
    "tgn:id":2238070,
    "tgn:name":"Chisholm Mine",
    "tgn:placetype":[
        "aat:300000390"
    ]
},
  "bbox": [],
  "geometry": {"coordinates":[-114.4833,37.9333],"type":"Point"}
}