{
  "id": 7386840,
  "type": "Feature",
  "properties": {
    "tgn:hierarchy":[
        "tgn:7386840",
        "tgn:1000001",
        "tgn:1001960",
        "tgn:7005560",
        "tgn:7029392"
    ],
    "tgn:id":7386840,
    "tgn:name":"Rancho Alegre",
    "tgn:placetype":[
        "aat:300008347"
    ]
},
  "bbox": [],
  "geometry": {"coordinates":[-109.066667,27.066667],"type":"Point"}
}