{
  "id": 7481358,
  "type": "Feature",
  "properties": {
    "tgn:hierarchy":[
        "tgn:7481358",
        "tgn:7468018",
        "tgn:1000004",
        "tgn:1000141",
        "tgn:7029392"
    ],
    "tgn:id":7481358,
    "tgn:name":"Shanliao Erhao Qiao",
    "tgn:placetype":[
        "aat:300007836"
    ]
},
  "bbox": [],
  "geometry": {"coordinates":[120.157524,23.476308],"type":"Point"}
}