{
  "id": 7478835,
  "type": "Feature",
  "properties": {
    "tgn:hierarchy":[
        "tgn:7478835",
        "tgn:1000004",
        "tgn:7489179",
        "tgn:1000141",
        "tgn:7029392"
    ],
    "tgn:id":7478835,
    "tgn:name":"Yamupi",
    "tgn:placetype":[
        "aat:300008347"
    ]
},
  "bbox": [],
  "geometry": {"coordinates":[121.797633,24.627805],"type":"Point"}
}