{
  "id": 7374682,
  "type": "Feature",
  "properties": {
    "tgn:hierarchy":[
        "tgn:7374682",
        "tgn:7005581",
        "tgn:1000001",
        "tgn:7005560",
        "tgn:7029392"
    ],
    "tgn:id":7374682,
    "tgn:name":"La Mesa Colorada",
    "tgn:placetype":[
        "aat:300008347"
    ]
},
  "bbox": [],
  "geometry": {"coordinates":[-106.65,25.866667],"type":"Point"}
}