{
  "id": 2051353,
  "type": "Feature",
  "properties": {
    "tgn:hierarchy":[
        "tgn:2051353",
        "tgn:1000001",
        "tgn:7012149",
        "tgn:2000963",
        "tgn:7007520",
        "tgn:7029392"
    ],
    "tgn:id":2051353,
    "tgn:name":"Boston",
    "tgn:placetype":[
        "aat:300008347"
    ]
},
  "bbox": [],
  "geometry": {"coordinates":[-88.5167,47.1667],"type":"Point"}
}