{
  "id": 1069296,
  "type": "Feature",
  "properties": {
    "tgn:hierarchy":[
        "tgn:1069296",
        "tgn:1000004",
        "tgn:7001796",
        "tgn:1000111",
        "tgn:7029392"
    ],
    "tgn:id":1069296,
    "tgn:name":"Jingcheng",
    "tgn:placetype":[
        "aat:300008347"
    ]
},
  "bbox": [],
  "geometry": {"coordinates":[117.5167,24.5667],"type":"Point"}
}