{
  "id": 1060829,
  "type": "Feature",
  "properties": {
    "tgn:hierarchy":[
        "tgn:1060829",
        "tgn:1000004",
        "tgn:1003399",
        "tgn:7018214",
        "tgn:7002435",
        "tgn:7029392"
    ],
    "tgn:id":1060829,
    "tgn:name":"Ust Uza",
    "tgn:placetype":[
        "aat:300008347"
    ]
},
  "bbox": [],
  "geometry": {"coordinates":[45.3333,52.9833],"type":"Point"}
}