{
  "id": 7144843,
  "type": "Feature",
  "properties": {
    "tgn:hierarchy":[
        "tgn:7144843",
        "tgn:7003669",
        "tgn:1000003",
        "tgn:7000084",
        "tgn:7029392"
    ],
    "tgn:id":7144843,
    "tgn:name":"K\u00f6ble Bach",
    "tgn:placetype":[
        "aat:300008699"
    ]
},
  "bbox": [],
  "geometry": {"coordinates":[10.366667,47.566667],"type":"Point"}
}