{
  "id": 7353574,
  "type": "Feature",
  "properties": {
    "tgn:hierarchy":[
        "tgn:7353574",
        "tgn:7005587",
        "tgn:1000001",
        "tgn:7005560",
        "tgn:7029392"
    ],
    "tgn:id":7353574,
    "tgn:name":"Azihua",
    "tgn:placetype":[
        "aat:300008347"
    ]
},
  "bbox": [],
  "geometry": {"coordinates":[-98.516667,21.183333],"type":"Point"}
}