{
  "id": 2605412,
  "type": "Feature",
  "properties": {
    "tgn:hierarchy":[
        "tgn:2605412",
        "tgn:1000001",
        "tgn:7012149",
        "tgn:2000831",
        "tgn:7007255",
        "tgn:7029392"
    ],
    "tgn:id":2605412,
    "tgn:name":"Ragstand Branch",
    "tgn:placetype":[
        "aat:300008699"
    ]
},
  "bbox": [],
  "geometry": {"coordinates":[-83.45,37.9833],"type":"Point"}
}