{
  "id": 7580208,
  "type": "Feature",
  "properties": {
    "tgn:hierarchy":[
        "tgn:7580208",
        "tgn:1000004",
        "tgn:7000198",
        "tgn:7031786",
        "tgn:7029392"
    ],
    "tgn:id":7580208,
    "tgn:name:en":"Thar\u0101li",
    "tgn:placetype":[
        "aat:300008347"
    ]
},
  "bbox": [],
  "geometry": {"coordinates":[79.506013,30.075651],"type":"Point"}
}