{
  "id": 2721654,
  "type": "Feature",
  "properties": {
    "tgn:hierarchy":[
        "tgn:2721654",
        "tgn:1000001",
        "tgn:7012149",
        "tgn:2000930",
        "tgn:7007515",
        "tgn:7029392"
    ],
    "tgn:id":2721654,
    "tgn:name":"Tilton Corner",
    "tgn:placetype":[
        "aat:300008347"
    ]
},
  "bbox": [],
  "geometry": {"coordinates":[-69.4833,44.7833],"type":"Point"}
}