{
  "id": 2763555,
  "type": "Feature",
  "properties": {
    "tgn:hierarchy":[
        "tgn:2763555",
        "tgn:1000001",
        "tgn:7012149",
        "tgn:1002790",
        "tgn:7007240",
        "tgn:7029392"
    ],
    "tgn:id":2763555,
    "tgn:name":"Whale Island",
    "tgn:placetype":[
        "aat:300008791"
    ]
},
  "bbox": [],
  "geometry": {"coordinates":[-82.6833,27.65],"type":"Point"}
}