{
  "id": 7400355,
  "type": "Feature",
  "properties": {
    "tgn:hierarchy":[
        "tgn:7400355",
        "tgn:1000001",
        "tgn:7005599",
        "tgn:7005560",
        "tgn:7029392"
    ],
    "tgn:id":7400355,
    "tgn:name":"Moralillo",
    "tgn:placetype":[
        "aat:300008347"
    ]
},
  "bbox": [],
  "geometry": {"coordinates":[-97.966667,21.498611],"type":"Point"}
}