<<<<<<< HEAD
{
  "id": 7475791,
  "type": "Feature",
  "properties": {
    "tgn:hierarchy":[
        "tgn:7475791",
        "tgn:1000004",
        "tgn:7489179",
        "tgn:1000141",
        "tgn:7029392"
    ],
    "tgn:id":7475791,
    "tgn:name":"Guosheng Miao",
    "tgn:placetype":[
        "aat:300007595"
    ]
},
  "bbox": [],
  "geometry": {"coordinates":[121.848145,24.610627],"type":"Point"}
}
=======
{"geometry":{"type":"Point","coordinates":[121.848145,24.610627]},"type":"Feature","properties":{"hierarchy":["tgn:7475791","tgn:1000004","tgn:7489179","tgn:1000141","tgn:7029392"],"placetype":["aat:300007595"],"id":7475791,"name:xx":"Guosheng Miao"}}
>>>>>>> 03f74aca74312dbeaf24d7e61306dd6a786dc3d0
