{
  "id": 2032026,
  "type": "Feature",
  "properties": {
    "tgn:hierarchy":[
        "tgn:2032026",
        "tgn:1000001",
        "tgn:7012149",
        "tgn:1002523",
        "tgn:7007252",
        "tgn:7029392"
    ],
    "tgn:id":2032026,
    "tgn:name":"Grayford",
    "tgn:placetype":[
        "aat:300008347"
    ]
},
  "bbox": [],
  "geometry": {"coordinates":[-85.5667,38.95],"type":"Point"}
}