{
  "id": 2527967,
  "type": "Feature",
  "properties": {
    "tgn:hierarchy":[
        "tgn:2527967",
        "tgn:1000001",
        "tgn:7012149",
        "tgn:1002545",
        "tgn:7007157",
        "tgn:7029392"
    ],
    "tgn:id":2527967,
    "tgn:name":"Mountain Oak Spring",
    "tgn:placetype":[
        "aat:300008697"
    ]
},
  "bbox": [],
  "geometry": {"coordinates":[-118.5333,35.2667],"type":"Point"}
}