{
  "id": 7318678,
  "type": "Feature",
  "properties": {
    "tgn:hierarchy":[
        "tgn:7318678",
        "tgn:1001657",
        "tgn:1000049",
        "tgn:1000002",
        "tgn:7029392"
    ],
    "tgn:id":7318678,
    "tgn:name":"Choros, Quebrada de los",
    "tgn:placetype":[
        "aat:300008699"
    ]
},
  "bbox": [],
  "geometry": {"coordinates":[-71.35,-29.316667],"type":"Point"}
}