{
  "id": 7554831,
  "type": "Feature",
  "properties": {
    "tgn:hierarchy":[
        "tgn:7554831",
        "tgn:1000004",
        "tgn:7000198",
        "tgn:7016722",
        "tgn:7029392"
    ],
    "tgn:id":7554831,
    "tgn:name:en":"Mainpur",
    "tgn:placetype":[
        "aat:300008347"
    ]
},
  "bbox": [],
  "geometry": {"coordinates":[83.480547,25.517812],"type":"Point"}
}