{
  "id": 7279772,
  "type": "Feature",
  "properties": {
    "tgn:hierarchy":[
        "tgn:7279772",
        "tgn:1001637",
        "tgn:1000049",
        "tgn:1000002",
        "tgn:7029392"
    ],
    "tgn:id":7279772,
    "tgn:name":"Rinconada",
    "tgn:placetype":[
        "aat:300008347"
    ]
},
  "bbox": [],
  "geometry": {"coordinates":[-72.55,-36.816667],"type":"Point"}
}