{
  "id": 7215919,
  "type": "Feature",
  "properties": {
    "tgn:hierarchy":[
        "tgn:7215919",
        "tgn:7003669",
        "tgn:1000003",
        "tgn:7000084",
        "tgn:7029392"
    ],
    "tgn:id":7215919,
    "tgn:name":"Achsenried",
    "tgn:placetype":[
        "aat:300008347"
    ]
},
  "bbox": [],
  "geometry": {"coordinates":[10.383333,48.116667],"type":"Point"}
}