<<<<<<< HEAD
{
  "id": 7020466,
  "type": "Feature",
  "properties": {
    "tgn:hierarchy":[
        "tgn:7020466",
        "tgn:1000001",
        "tgn:7012149",
        "tgn:2001276",
        "tgn:7007524",
        "tgn:7029392"
    ],
    "tgn:id":7020466,
    "tgn:name":"Twin Buttes",
    "tgn:placetype":[
        "aat:300008798"
    ]
},
  "bbox": [],
  "geometry": {"coordinates":[-107.3833,47.1667],"type":"Point"}
}
=======
{"geometry":{"type":"Point","coordinates":[-107.383300,47.166700]},"type":"Feature","properties":{"hierarchy":["tgn:7020466","tgn:1000001","tgn:7012149","tgn:2001276","tgn:7007524","tgn:7029392"],"placetype":["aat:300008798"],"id":7020466,"name:xx":"Twin Buttes"}}
>>>>>>> 03f74aca74312dbeaf24d7e61306dd6a786dc3d0
