{
  "id": 2621094,
  "type": "Feature",
  "properties": {
    "tgn:hierarchy":[
        "tgn:2621094",
        "tgn:7006450",
        "tgn:1000001",
        "tgn:7012149",
        "tgn:2124002",
        "tgn:7029392"
    ],
    "tgn:id":2621094,
    "tgn:name":"Road Island",
    "tgn:placetype":[
        "aat:300008791"
    ]
},
  "bbox": [],
  "geometry": {"coordinates":[-135.35,56.9167],"type":"Point"}
}