{
  "id": 2676058,
  "type": "Feature",
  "properties": {
    "tgn:hierarchy":[
        "tgn:2676058",
        "tgn:7006450",
        "tgn:1000001",
        "tgn:7012149",
        "tgn:2000085",
        "tgn:7029392"
    ],
    "tgn:id":2676058,
    "tgn:name":"Sorenson, Mount",
    "tgn:placetype":[
        "aat:300008798"
    ]
},
  "bbox": [],
  "geometry": {"coordinates":[-142.95,64.9833],"type":"Point"}
}