{
  "id": 7469802,
  "type": "Feature",
  "properties": {
    "tgn:hierarchy":[
        "tgn:7469802",
        "tgn:1000004",
        "tgn:7471332",
        "tgn:1000141",
        "tgn:7029392"
    ],
    "tgn:id":7469802,
    "tgn:name":"Jinshanmian",
    "tgn:placetype":[
        "aat:300008347"
    ]
},
  "bbox": [],
  "geometry": {"coordinates":[121.022778,24.771667],"type":"Point"}
}