{
  "id": 7594187,
  "type": "Feature",
  "properties": {
    "tgn:hierarchy":[
        "tgn:7594187",
        "tgn:1000003",
        "tgn:7005729",
        "tgn:7029392"
    ],
    "tgn:id":7594187,
    "tgn:name":"Imsida",
    "tgn:placetype":[
        "aat:300387064",
        "aat:300387205"
    ]
},
  "bbox": [],
  "geometry": {"coordinates":[14.483889,35.898611],"type":"Point"}
}