{
  "id": 7085695,
  "type": "Feature",
  "properties": {
    "tgn:hierarchy":[
        "tgn:7085695",
        "tgn:1000003",
        "tgn:7003682",
        "tgn:7000084",
        "tgn:7029392"
    ],
    "tgn:id":7085695,
    "tgn:name":"Weierscheid",
    "tgn:placetype":[
        "aat:300008777"
    ]
},
  "bbox": [],
  "geometry": {"coordinates":[6.983333,50.466667],"type":"Point"}
}