{
  "id": 2612819,
  "type": "Feature",
  "properties": {
    "tgn:hierarchy":[
        "tgn:2612819",
        "tgn:7002659",
        "tgn:1000001",
        "tgn:7012149",
        "tgn:2000025",
        "tgn:7029392"
    ],
    "tgn:id":2612819,
    "tgn:name":"Redland Bluffs",
    "tgn:placetype":[
        "aat:300008347"
    ]
},
  "bbox": [],
  "geometry": {"coordinates":[-86.1667,32.45],"type":"Point"}
}