{
  "id": 2320681,
  "type": "Feature",
  "properties": {
    "tgn:hierarchy":[
        "tgn:2320681",
        "tgn:1000001",
        "tgn:7012149",
        "tgn:7007157",
        "tgn:1002857",
        "tgn:7029392"
    ],
    "tgn:id":2320681,
    "tgn:name":"Excelsior Mine",
    "tgn:placetype":[
        "aat:300000390"
    ]
},
  "bbox": [],
  "geometry": {"coordinates":[-115.8333,35.7667],"type":"Point"}
}