{
  "id": 2394242,
  "type": "Feature",
  "properties": {
    "tgn:hierarchy":[
        "tgn:2394242",
        "tgn:1000001",
        "tgn:7012149",
        "tgn:2001279",
        "tgn:7007524",
        "tgn:7029392"
    ],
    "tgn:id":2394242,
    "tgn:name":"Hogback Creek",
    "tgn:placetype":[
        "aat:300008706"
    ]
},
  "bbox": [],
  "geometry": {"coordinates":[-113.6333,46.4333],"type":"Point"}
}