<<<<<<< HEAD
{
  "id": 2402155,
  "type": "Feature",
  "properties": {
    "tgn:hierarchy":[
        "tgn:2402155",
        "tgn:1000001",
        "tgn:7012149",
        "tgn:2002384",
        "tgn:7007923",
        "tgn:7029392"
    ],
    "tgn:id":2402155,
    "tgn:name":"Horsetail Creek",
    "tgn:placetype":[
        "aat:300008706"
    ]
},
  "bbox": [],
  "geometry": {"coordinates":[-110.4333,43.6333],"type":"Point"}
}
=======
{"geometry":{"type":"Point","coordinates":[-110.433300,43.633300]},"type":"Feature","properties":{"hierarchy":["tgn:2402155","tgn:1000001","tgn:7012149","tgn:2002384","tgn:7007923","tgn:7029392"],"placetype":["aat:300008706"],"id":2402155,"name:xx":"Horsetail Creek"}}
>>>>>>> 03f74aca74312dbeaf24d7e61306dd6a786dc3d0
