{
  "id": 2239099,
  "type": "Feature",
  "properties": {
    "tgn:hierarchy":[
        "tgn:2239099",
        "tgn:1000001",
        "tgn:7012149",
        "tgn:2002359",
        "tgn:7007922",
        "tgn:7029392"
    ],
    "tgn:id":2239099,
    "tgn:name":"Chub Lake",
    "tgn:placetype":[
        "aat:300008680"
    ]
},
  "bbox": [],
  "geometry": {"coordinates":[-89.8833,46.1167],"type":"Point"}
}