{
  "id": 2654634,
  "type": "Feature",
  "properties": {
    "tgn:hierarchy":[
        "tgn:2654634",
        "tgn:1000001",
        "tgn:7012149",
        "tgn:2000474",
        "tgn:7007250",
        "tgn:7029392"
    ],
    "tgn:id":2654634,
    "tgn:name":"Shake Gulch",
    "tgn:placetype":[
        "aat:300008761"
    ]
},
  "bbox": [],
  "geometry": {"coordinates":[-116.2167,44.3167],"type":"Point"}
}