{
  "id": 2500287,
  "type": "Feature",
  "properties": {
    "tgn:hierarchy":[
        "tgn:2500287",
        "tgn:1000001",
        "tgn:7012149",
        "tgn:2001709",
        "tgn:7007708",
        "tgn:7029392"
    ],
    "tgn:id":2500287,
    "tgn:name":"McDade Reservoir",
    "tgn:placetype":[
        "aat:300006191"
    ]
},
  "bbox": [],
  "geometry": {"coordinates":[-118.8333,42.2333],"type":"Point"}
}