{
  "id": 7537875,
  "type": "Feature",
  "properties": {
    "tgn:hierarchy":[
        "tgn:7537875",
        "tgn:7001242",
        "tgn:7016833",
        "tgn:7000123",
        "tgn:7029392"
    ],
    "tgn:id":7537875,
    "tgn:name:en":"Shaykh 'Al\u012b, \u1e28ashat ash",
    "tgn:placetype":[
        "aat:300343519"
    ]
},
  "bbox": [],
  "geometry": {"coordinates":[32.366667,26.033333],"type":"Point"}
}