{
  "id": 2444029,
  "type": "Feature",
  "properties": {
    "tgn:hierarchy":[
        "tgn:2444029",
        "tgn:1000001",
        "tgn:7012149",
        "tgn:7029392"
    ],
    "tgn:id":2444029,
    "tgn:name":"LaChapelle Creek",
    "tgn:placetype":[
        "aat:300008706"
    ]
},
  "bbox": [],
  "geometry": {"coordinates":[-110.7167,40.9833],"type":"Point"}
}