{
  "id": 2305126,
  "type": "Feature",
  "properties": {
    "tgn:hierarchy":[
        "tgn:2305126",
        "tgn:1000001",
        "tgn:7012149",
        "tgn:7007520",
        "tgn:7029392"
    ],
    "tgn:id":2305126,
    "tgn:name":"East Branch Net River",
    "tgn:placetype":[
        "aat:300008707"
    ]
},
  "bbox": [],
  "geometry": {"coordinates":[-88.3333,46.4833],"type":"Point"}
}