{
  "id": 2365166,
  "type": "Feature",
  "properties": {
    "tgn:hierarchy":[
        "tgn:2365166",
        "tgn:1000001",
        "tgn:1002168",
        "tgn:7012149",
        "tgn:7007826",
        "tgn:7029392"
    ],
    "tgn:id":2365166,
    "tgn:name":"Greens Creek",
    "tgn:placetype":[
        "aat:300008706"
    ]
},
  "bbox": [],
  "geometry": {"coordinates":[-97.4833,30.1333],"type":"Point"}
}