{
  "id": 2000641,
  "type": "Feature",
  "properties": {
    "tgn:hierarchy":[
        "tgn:2000641",
        "tgn:1000001",
        "tgn:7012149",
        "tgn:7007253",
        "tgn:7029392"
    ],
    "tgn:id":2000641,
    "tgn:name":"Sac",
    "tgn:placetype":[
        "aat:300387145",
        "aat:300000771"
    ]
},
  "bbox": [],
  "geometry": {"coordinates":[-95.1167,42.3833],"type":"Point"}
}