{
  "id": 2527311,
  "type": "Feature",
  "properties": {
    "tgn:hierarchy":[
        "tgn:2527311",
        "tgn:1000001",
        "tgn:7012149",
        "tgn:2002118",
        "tgn:7007827",
        "tgn:7029392"
    ],
    "tgn:id":2527311,
    "tgn:name":"Mount Olympus Spring",
    "tgn:placetype":[
        "aat:300008697"
    ]
},
  "bbox": [],
  "geometry": {"coordinates":[-111.7667,40.6667],"type":"Point"}
}