{
  "id": 7309535,
  "type": "Feature",
  "properties": {
    "tgn:hierarchy":[
        "tgn:7309535",
        "tgn:1001708",
        "tgn:1000049",
        "tgn:1000002",
        "tgn:7029392"
    ],
    "tgn:id":7309535,
    "tgn:name":"Naranjo, Quebrada",
    "tgn:placetype":[
        "aat:300266554",
        "aat:300008699"
    ]
},
  "bbox": [],
  "geometry": {"coordinates":[-70.666667,-32.983333],"type":"Point"}
}