{
  "id": 7427835,
  "type": "Feature",
  "properties": {
    "tgn:hierarchy":[
        "tgn:7427835",
        "tgn:1000001",
        "tgn:7005594",
        "tgn:7005560",
        "tgn:7029392"
    ],
    "tgn:id":7427835,
    "tgn:name":"Veinte de Noviembre",
    "tgn:placetype":[
        "aat:300008347"
    ]
},
  "bbox": [],
  "geometry": {"coordinates":[-98.383333,22.233333],"type":"Point"}
}