<<<<<<< HEAD
{
  "id": 2333414,
  "type": "Feature",
  "properties": {
    "tgn:hierarchy":[
        "tgn:2333414",
        "tgn:1000001",
        "tgn:7012149",
        "tgn:2001715",
        "tgn:7007708",
        "tgn:7029392"
    ],
    "tgn:id":2333414,
    "tgn:name":"Foley Lake",
    "tgn:placetype":[
        "aat:300008680"
    ]
},
  "bbox": [],
  "geometry": {"coordinates":[-120.0167,42.6667],"type":"Point"}
}
=======
{"geometry":{"type":"Point","coordinates":[-120.016700,42.666700]},"type":"Feature","properties":{"hierarchy":["tgn:2333414","tgn:1000001","tgn:7012149","tgn:2001715","tgn:7007708","tgn:7029392"],"placetype":["aat:300008680"],"id":2333414,"name:xx":"Foley Lake"}}
>>>>>>> 03f74aca74312dbeaf24d7e61306dd6a786dc3d0
