{
  "id": 7202304,
  "type": "Feature",
  "properties": {
    "tgn:hierarchy":[
        "tgn:7202304",
        "tgn:1000003",
        "tgn:7003685",
        "tgn:7000084",
        "tgn:7029392"
    ],
    "tgn:id":7202304,
    "tgn:name":"Breitenberg",
    "tgn:placetype":[
        "aat:300008347"
    ]
},
  "bbox": [],
  "geometry": {"coordinates":[13.033333,51.066667],"type":"Point"}
}