{
  "id": 2617933,
  "type": "Feature",
  "properties": {
    "tgn:hierarchy":[
        "tgn:2617933",
        "tgn:1000001",
        "tgn:7012149",
        "tgn:1003020",
        "tgn:7007920",
        "tgn:7029392"
    ],
    "tgn:id":2617933,
    "tgn:name":"Ridge of Gendarmes",
    "tgn:placetype":[
        "aat:300266640"
    ]
},
  "bbox": [],
  "geometry": {"coordinates":[-121.25,48.9333],"type":"Point"}
}