{
  "id": 2652231,
  "type": "Feature",
  "properties": {
    "tgn:hierarchy":[
        "tgn:2652231",
        "tgn:1000001",
        "tgn:2000318",
        "tgn:7012149",
        "tgn:7007248",
        "tgn:7029392"
    ],
    "tgn:id":2652231,
    "tgn:name":"Selmans Lake",
    "tgn:placetype":[
        "aat:300006191"
    ]
},
  "bbox": [],
  "geometry": {"coordinates":[-85.2833,34.5167],"type":"Point"}
}