{
  "id": 2417933,
  "type": "Feature",
  "properties": {
    "tgn:hierarchy":[
        "tgn:2417933",
        "tgn:1000001",
        "tgn:7012149",
        "tgn:7007158",
        "tgn:7029392"
    ],
    "tgn:id":2417933,
    "tgn:name":"Jackson Lake Inlet",
    "tgn:placetype":[
        "aat:300006075"
    ]
},
  "bbox": [],
  "geometry": {"coordinates":[-104.15,40.3167],"type":"Point"}
}