{
  "id": 1107883,
  "type": "Feature",
  "properties": {
    "tgn:hierarchy":[
        "tgn:1107883",
        "tgn:1000001",
        "tgn:7012149",
        "tgn:7007826",
        "tgn:7029392"
    ],
    "tgn:id":1107883,
    "tgn:name":"Black Mountain",
    "tgn:placetype":[
        "aat:300008777"
    ]
},
  "bbox": [],
  "geometry": {"coordinates":[-97.7333,31.15],"type":"Point"}
}