{
  "id": 2152399,
  "type": "Feature",
  "properties": {
    "tgn:hierarchy":[
        "tgn:2152399",
        "tgn:2001731",
        "tgn:1000001",
        "tgn:7012149",
        "tgn:7007712",
        "tgn:7029392"
    ],
    "tgn:id":2152399,
    "tgn:name":"Bay Pines",
    "tgn:placetype":[
        "aat:300008347"
    ]
},
  "bbox": [],
  "geometry": {"coordinates":[-80.7667,32.1667],"type":"Point"}
}