{
  "id": 2694788,
  "type": "Feature",
  "properties": {
    "tgn:hierarchy":[
        "tgn:2694788",
        "tgn:1000001",
        "tgn:2000935",
        "tgn:7012149",
        "tgn:7007516",
        "tgn:7029392"
    ],
    "tgn:id":2694788,
    "tgn:name":"Steyer Run",
    "tgn:placetype":[
        "aat:300008699"
    ]
},
  "bbox": [],
  "geometry": {"coordinates":[-79.2833,39.3167],"type":"Point"}
}