{
  "id": 2483643,
  "type": "Feature",
  "properties": {
    "tgn:hierarchy":[
        "tgn:2483643",
        "tgn:1000001",
        "tgn:7012149",
        "tgn:2000220",
        "tgn:7007158",
        "tgn:7029392"
    ],
    "tgn:id":2483643,
    "tgn:name":"Lateral C",
    "tgn:placetype":[
        "aat:300006075"
    ]
},
  "bbox": [],
  "geometry": {"coordinates":[-106.3333,40.5667],"type":"Point"}
}