{
  "id": 7074760,
  "type": "Feature",
  "properties": {
    "tgn:hierarchy":[
        "tgn:7074760",
        "tgn:1000003",
        "tgn:7003685",
        "tgn:7000084",
        "tgn:7029392"
    ],
    "tgn:id":7074760,
    "tgn:name":"Zschopen-Berg",
    "tgn:placetype":[
        "aat:300008777"
    ]
},
  "bbox": [],
  "geometry": {"coordinates":[13.066667,50.733333],"type":"Point"}
}