{
  "id": 1057629,
  "type": "Feature",
  "properties": {
    "tgn:hierarchy":[
        "tgn:1057629",
        "tgn:1000003",
        "tgn:7011662",
        "tgn:7006660",
        "tgn:7029392"
    ],
    "tgn:id":1057629,
    "tgn:name":"Novoarkhangelsk",
    "tgn:placetype":[
        "aat:300008347"
    ]
},
  "bbox": [],
  "geometry": {"coordinates":[30.8333,48.5833],"type":"Point"}
}