{
  "id": 2716829,
  "type": "Feature",
  "properties": {
    "tgn:hierarchy":[
        "tgn:2716829",
        "tgn:1000001",
        "tgn:7012149",
        "tgn:2001284",
        "tgn:7007524",
        "tgn:7029392"
    ],
    "tgn:id":2716829,
    "tgn:name":"Theodore Creek",
    "tgn:placetype":[
        "aat:300008706"
    ]
},
  "bbox": [],
  "geometry": {"coordinates":[-112.7333,47.05],"type":"Point"}
}