{
  "id": 7277307,
  "type": "Feature",
  "properties": {
    "tgn:hierarchy":[
        "tgn:7277307",
        "tgn:7002464",
        "tgn:1000049",
        "tgn:1000002",
        "tgn:7029392"
    ],
    "tgn:id":7277307,
    "tgn:name":"Cobani, Cerro",
    "tgn:placetype":[
        "aat:300008795"
    ]
},
  "bbox": [],
  "geometry": {"coordinates":[-69.713333,-17.955278],"type":"Point"}
}