{
  "id": 7374260,
  "type": "Feature",
  "properties": {
    "tgn:hierarchy":[
        "tgn:7374260",
        "tgn:7005581",
        "tgn:1000001",
        "tgn:7005560",
        "tgn:7029392"
    ],
    "tgn:id":7374260,
    "tgn:name":"Rancho La Manchita",
    "tgn:placetype":[
        "aat:300000241"
    ]
},
  "bbox": [],
  "geometry": {"coordinates":[-106.116667,26.833333],"type":"Point"}
}