{
  "id": 2515501,
  "type": "Feature",
  "properties": {
    "tgn:hierarchy":[
        "tgn:2515501",
        "tgn:1000001",
        "tgn:2000957",
        "tgn:7012149",
        "tgn:7007520",
        "tgn:7029392"
    ],
    "tgn:id":2515501,
    "tgn:name":"Mills Ditch",
    "tgn:placetype":[
        "aat:300006075"
    ]
},
  "bbox": [],
  "geometry": {"coordinates":[-84.7833,42.4833],"type":"Point"}
}