{
  "id": 2341828,
  "type": "Feature",
  "properties": {
    "tgn:hierarchy":[
        "tgn:2341828",
        "tgn:1000001",
        "tgn:7012149",
        "tgn:2001922",
        "tgn:7007825",
        "tgn:7029392"
    ],
    "tgn:id":2341828,
    "tgn:name":"Frozen Knob",
    "tgn:placetype":[
        "aat:300008798"
    ]
},
  "bbox": [],
  "geometry": {"coordinates":[-82.55,36.0667],"type":"Point"}
}