{
  "id": 2590476,
  "type": "Feature",
  "properties": {
    "tgn:hierarchy":[
        "tgn:2590476",
        "tgn:1000001",
        "tgn:7012149",
        "tgn:7007158",
        "tgn:2000244",
        "tgn:7029392"
    ],
    "tgn:id":2590476,
    "tgn:name":"Pole Canyon",
    "tgn:placetype":[
        "aat:300008761"
    ]
},
  "bbox": [],
  "geometry": {"coordinates":[-106.45,37.55],"type":"Point"}
}