{
  "id": 7519621,
  "type": "Feature",
  "properties": {
    "tgn:hierarchy":[
        "tgn:7519621",
        "tgn:1009227",
        "tgn:1000226",
        "tgn:1000006",
        "tgn:7016850",
        "tgn:7029392"
    ],
    "tgn:id":7519621,
    "tgn:name:en":"Abbey Rocks",
    "tgn:placetype":[
        "aat:300011692"
    ]
},
  "bbox": [],
  "geometry": {"coordinates":[169.333333,-43.666667],"type":"Point"}
}