{
  "id": 7225920,
  "type": "Feature",
  "properties": {
    "tgn:hierarchy":[
        "tgn:7225920",
        "tgn:7011270",
        "tgn:7002674",
        "tgn:1000003",
        "tgn:1000074",
        "tgn:7029392"
    ],
    "tgn:id":7225920,
    "tgn:name":"Perat\u00ed, \u00c1kra",
    "tgn:placetype":[
        "aat:300008850"
    ]
},
  "bbox": [],
  "geometry": {"coordinates":[24.983333,37.683333],"type":"Point"}
}