<<<<<<< HEAD
{
  "id": 2768094,
  "type": "Feature",
  "properties": {
    "tgn:hierarchy":[
        "tgn:2768094",
        "tgn:1000001",
        "tgn:7012149",
        "tgn:2002273",
        "tgn:7013961",
        "tgn:7029392"
    ],
    "tgn:id":2768094,
    "tgn:name":"Whites Additon",
    "tgn:placetype":[
        "aat:300008347"
    ]
},
  "bbox": [],
  "geometry": {"coordinates":[-82.0,37.8333],"type":"Point"}
}
=======
{"geometry":{"type":"Point","coordinates":[-82.000000,37.833300]},"type":"Feature","properties":{"hierarchy":["tgn:2768094","tgn:1000001","tgn:7012149","tgn:2002273","tgn:7013961","tgn:7029392"],"placetype":["aat:300008347"],"id":2768094,"name:xx":"Whites Additon"}}
>>>>>>> 03f74aca74312dbeaf24d7e61306dd6a786dc3d0
