{
  "id": 7282460,
  "type": "Feature",
  "properties": {
    "tgn:hierarchy":[
        "tgn:7282460",
        "tgn:1001708",
        "tgn:1000049",
        "tgn:1000002",
        "tgn:7029392"
    ],
    "tgn:id":7282460,
    "tgn:name":"Peumo, Quebrada del",
    "tgn:placetype":[
        "aat:300266554",
        "aat:300008699"
    ]
},
  "bbox": [],
  "geometry": {"coordinates":[-70.516667,-33.333333],"type":"Point"}
}