{
  "id": 7510671,
  "type": "Feature",
  "properties": {
    "tgn:hierarchy":[
        "tgn:7510671",
        "tgn:7016670",
        "tgn:1008380",
        "tgn:1000226",
        "tgn:1000006",
        "tgn:7029392"
    ],
    "tgn:id":7510671,
    "tgn:name:en":"Te Ana o Kaiwhaka",
    "tgn:placetype":[
        "aat:300008699"
    ]
},
  "bbox": [],
  "geometry": {"coordinates":[176.716667,-39.066667],"type":"Point"}
}