{
  "id": 2176032,
  "type": "Feature",
  "properties": {
    "tgn:hierarchy":[
        "tgn:2176032",
        "tgn:1000001",
        "tgn:2001474",
        "tgn:7012149",
        "tgn:7007709",
        "tgn:7029392"
    ],
    "tgn:id":2176032,
    "tgn:name":"Black Fox Ridge",
    "tgn:placetype":[
        "aat:300266640"
    ]
},
  "bbox": [],
  "geometry": {"coordinates":[-81.6667,35.65],"type":"Point"}
}