{
  "id": 2582126,
  "type": "Feature",
  "properties": {
    "tgn:hierarchy":[
        "tgn:2582126",
        "tgn:1000001",
        "tgn:7012149",
        "tgn:2000351",
        "tgn:7007248",
        "tgn:7029392"
    ],
    "tgn:id":2582126,
    "tgn:name":"Pine Creek",
    "tgn:placetype":[
        "aat:300008706"
    ]
},
  "bbox": [],
  "geometry": {"coordinates":[-84.7833,33.55],"type":"Point"}
}