{
  "id": 1052881,
  "type": "Feature",
  "properties": {
    "tgn:hierarchy":[
        "tgn:1052881",
        "tgn:6000729",
        "tgn:1000004",
        "tgn:7018214",
        "tgn:7002435",
        "tgn:7029392"
    ],
    "tgn:id":1052881,
    "tgn:name":"Bol'shaya Khalan",
    "tgn:placetype":[
        "aat:300008347"
    ]
},
  "bbox": [],
  "geometry": {"coordinates":[37.4833,50.9167],"type":"Point"}
}