{
  "id": 7394615,
  "type": "Feature",
  "properties": {
    "tgn:hierarchy":[
        "tgn:7394615",
        "tgn:7005581",
        "tgn:1000001",
        "tgn:7005560",
        "tgn:7029392"
    ],
    "tgn:id":7394615,
    "tgn:name":"Rancho San Jos\u00e9",
    "tgn:placetype":[
        "aat:300000241"
    ]
},
  "bbox": [],
  "geometry": {"coordinates":[-107.633333,30.15],"type":"Point"}
}