<<<<<<< HEAD
{
  "id": 7350025,
  "type": "Feature",
  "properties": {
    "tgn:hierarchy":[
        "tgn:7350025",
        "tgn:1000001",
        "tgn:7005597",
        "tgn:7005560",
        "tgn:7029392"
    ],
    "tgn:id":7350025,
    "tgn:name":"Aguilar, Cerro",
    "tgn:placetype":[
        "aat:300008795"
    ]
},
  "bbox": [],
  "geometry": {"coordinates":[-98.316667,23.4],"type":"Point"}
}
=======
{"geometry":{"type":"Point","coordinates":[-98.316667,23.400000]},"type":"Feature","properties":{"hierarchy":["tgn:7350025","tgn:1000001","tgn:7005597","tgn:7005560","tgn:7029392"],"placetype":["aat:300008795"],"id":7350025,"name:xx":"Aguilar, Cerro"}}
>>>>>>> 03f74aca74312dbeaf24d7e61306dd6a786dc3d0
