{
  "id": 2597321,
  "type": "Feature",
  "properties": {
    "tgn:hierarchy":[
        "tgn:2597321",
        "tgn:1000001",
        "tgn:7012149",
        "tgn:2000646",
        "tgn:7007253",
        "tgn:7029392"
    ],
    "tgn:id":2597321,
    "tgn:name":"Prairie Creek",
    "tgn:placetype":[
        "aat:300008706"
    ]
},
  "bbox": [],
  "geometry": {"coordinates":[-92.6667,42.0667],"type":"Point"}
}