{
  "id": 2649412,
  "type": "Feature",
  "properties": {
    "tgn:hierarchy":[
        "tgn:2649412",
        "tgn:1000001",
        "tgn:7012149",
        "tgn:7007157",
        "tgn:1002566",
        "tgn:7029392"
    ],
    "tgn:id":2649412,
    "tgn:name":"Scotts Creek",
    "tgn:placetype":[
        "aat:300008706"
    ]
},
  "bbox": [],
  "geometry": {"coordinates":[-123.05,39.1667],"type":"Point"}
}