{
  "id": 2254157,
  "type": "Feature",
  "properties": {
    "tgn:hierarchy":[
        "tgn:2254157",
        "tgn:1000001",
        "tgn:7012149",
        "tgn:1002945",
        "tgn:7007710",
        "tgn:7029392"
    ],
    "tgn:id":2254157,
    "tgn:name":"Coolidge Hollow",
    "tgn:placetype":[
        "aat:300008347"
    ]
},
  "bbox": [],
  "geometry": {"coordinates":[-77.2833,41.6833],"type":"Point"}
}