{
  "id": 7163413,
  "type": "Feature",
  "properties": {
    "tgn:hierarchy":[
        "tgn:7163413",
        "tgn:1000003",
        "tgn:7003676",
        "tgn:7000084",
        "tgn:7029392"
    ],
    "tgn:id":7163413,
    "tgn:name":"Huster",
    "tgn:placetype":[
        "aat:300000206"
    ]
},
  "bbox": [],
  "geometry": {"coordinates":[7.966667,52.083333],"type":"Point"}
}