{
  "id": 2019312,
  "type": "Feature",
  "properties": {
    "tgn:hierarchy":[
        "tgn:2019312",
        "tgn:1000001",
        "tgn:1002200",
        "tgn:7012149",
        "tgn:7007240",
        "tgn:7029392"
    ],
    "tgn:id":2019312,
    "tgn:name":"Floridana Beach",
    "tgn:placetype":[
        "aat:300008347"
    ]
},
  "bbox": [],
  "geometry": {"coordinates":[-80.4833,27.9333],"type":"Point"}
}