<<<<<<< HEAD
{
  "id": 7027911,
  "type": "Feature",
  "properties": {
    "tgn:hierarchy":[
        "tgn:7027911",
        "tgn:7002445",
        "tgn:1000003",
        "tgn:7008157",
        "tgn:7008591",
        "tgn:7029392"
    ],
    "tgn:id":7027911,
    "tgn:name":"Hasthorpe",
    "tgn:placetype":[
        "aat:300008347",
        "aat:300008372"
    ]
},
  "bbox": [],
  "geometry": {"coordinates":[0.2167,53.2],"type":"Point"}
}
=======
{"geometry":{"type":"Point","coordinates":[0.216700,53.200000]},"type":"Feature","properties":{"hierarchy":["tgn:7027911","tgn:7002445","tgn:1000003","tgn:7008157","tgn:7008591","tgn:7029392"],"placetype":["aat:300008347","aat:300008372"],"id":7027911,"name:xx":"Hasthorpe"}}
>>>>>>> 03f74aca74312dbeaf24d7e61306dd6a786dc3d0
