{
  "id": 2220347,
  "type": "Feature",
  "properties": {
    "tgn:hierarchy":[
        "tgn:2220347",
        "tgn:1000001",
        "tgn:2001482",
        "tgn:7012149",
        "tgn:7007709",
        "tgn:7029392"
    ],
    "tgn:id":2220347,
    "tgn:name":"Cape Colony",
    "tgn:placetype":[
        "aat:300008347"
    ]
},
  "bbox": [],
  "geometry": {"coordinates":[-76.5667,36.0167],"type":"Point"}
}