{
  "id": 1044104,
  "type": "Feature",
  "properties": {
    "tgn:hierarchy":[
        "tgn:1044104",
        "tgn:1000003",
        "tgn:7003155",
        "tgn:7003122",
        "tgn:1000080",
        "tgn:7029392"
    ],
    "tgn:id":1044104,
    "tgn:name":"Catenanuova",
    "tgn:placetype":[
        "aat:300008347"
    ]
},
  "bbox": [],
  "geometry": {"coordinates":[14.683333,37.566667],"type":"Point"}
}