{
  "id": 2001377,
  "type": "Feature",
  "properties": {
    "tgn:hierarchy":[
        "tgn:2001377",
        "tgn:1000001",
        "tgn:7012149",
        "tgn:7007525",
        "tgn:7029392"
    ],
    "tgn:id":2001377,
    "tgn:name":"Morrill",
    "tgn:placetype":[
        "aat:300387145",
        "aat:300000771"
    ]
},
  "bbox": [],
  "geometry": {"coordinates":[-103.0167,41.7167],"type":"Point"}
}