{
  "id": 2668424,
  "type": "Feature",
  "properties": {
    "tgn:hierarchy":[
        "tgn:2668424",
        "tgn:1000001",
        "tgn:7012149",
        "tgn:1002886",
        "tgn:7007252",
        "tgn:7029392"
    ],
    "tgn:id":2668424,
    "tgn:name":"Slash Creek",
    "tgn:placetype":[
        "aat:300008706"
    ]
},
  "bbox": [],
  "geometry": {"coordinates":[-85.85,39.4333],"type":"Point"}
}