{
  "id": 7164845,
  "type": "Feature",
  "properties": {
    "tgn:hierarchy":[
        "tgn:7164845",
        "tgn:7003669",
        "tgn:1000003",
        "tgn:7000084",
        "tgn:7029392"
    ],
    "tgn:id":7164845,
    "tgn:name":"H\u00f6tzelsdorf",
    "tgn:placetype":[
        "aat:300000206"
    ]
},
  "bbox": [],
  "geometry": {"coordinates":[11.883333,48.666667],"type":"Point"}
}