{
  "id": 7544247,
  "type": "Feature",
  "properties": {
    "tgn:hierarchy":[
        "tgn:7544247",
        "tgn:7001242",
        "tgn:1001059",
        "tgn:7016833",
        "tgn:7029392"
    ],
    "tgn:id":7544247,
    "tgn:name:en":"Qan\u0101t al 'In\u0101b\u012byah",
    "tgn:placetype":[
        "aat:300006075"
    ]
},
  "bbox": [],
  "geometry": {"coordinates":[31.883333,31.35],"type":"Point"}
}