{
  "id": 1094696,
  "type": "Feature",
  "properties": {
    "tgn:hierarchy":[
        "tgn:1094696",
        "tgn:7001242",
        "tgn:1001711",
        "tgn:1000203",
        "tgn:7029392"
    ],
    "tgn:id":1094696,
    "tgn:name":"Lupiro",
    "tgn:placetype":[
        "aat:300008347"
    ]
},
  "bbox": [],
  "geometry": {"coordinates":[36.65,-8.4167],"type":"Point"}
}