{
  "id": 7283069,
  "type": "Feature",
  "properties": {
    "tgn:hierarchy":[
        "tgn:7283069",
        "tgn:1001702",
        "tgn:1000049",
        "tgn:1000002",
        "tgn:7029392"
    ],
    "tgn:id":7283069,
    "tgn:name":"Patch, Punta",
    "tgn:placetype":[
        "aat:300386846"
    ]
},
  "bbox": [],
  "geometry": {"coordinates":[-74.45,-49.616667],"type":"Point"}
}