{
  "id": 2526576,
  "type": "Feature",
  "properties": {
    "tgn:hierarchy":[
        "tgn:2526576",
        "tgn:1000001",
        "tgn:7012149",
        "tgn:2000367",
        "tgn:7007248",
        "tgn:7029392"
    ],
    "tgn:id":2526576,
    "tgn:name":"Mossy Lake",
    "tgn:placetype":[
        "aat:300006191"
    ]
},
  "bbox": [],
  "geometry": {"coordinates":[-83.6333,32.4667],"type":"Point"}
}