{
  "id": 7262724,
  "type": "Feature",
  "properties": {
    "tgn:hierarchy":[
        "tgn:7262724",
        "tgn:1000003",
        "tgn:7003632",
        "tgn:7016845",
        "tgn:7029392"
    ],
    "tgn:id":7262724,
    "tgn:name:nl":"Bruggehof",
    "tgn:placetype":[
        "aat:300387200"
    ]
},
  "bbox": [],
  "geometry": {"coordinates":[4.633333,51.733333],"type":"Point"}
}