{
  "id": 2361791,
  "type": "Feature",
  "properties": {
    "tgn:hierarchy":[
        "tgn:2361791",
        "tgn:7002659",
        "tgn:1000001",
        "tgn:7012149",
        "tgn:2000038",
        "tgn:7029392"
    ],
    "tgn:id":2361791,
    "tgn:name":"Gray Branch",
    "tgn:placetype":[
        "aat:300008699"
    ]
},
  "bbox": [],
  "geometry": {"coordinates":[-87.6667,34.9833],"type":"Point"}
}