{
  "id": 2530634,
  "type": "Feature",
  "properties": {
    "tgn:hierarchy":[
        "tgn:2530634",
        "tgn:1000001",
        "tgn:7012149",
        "tgn:2000217",
        "tgn:7007158",
        "tgn:7029392"
    ],
    "tgn:id":2530634,
    "tgn:name":"Muddy Fork",
    "tgn:placetype":[
        "aat:300008699"
    ]
},
  "bbox": [],
  "geometry": {"coordinates":[-107.3833,38.8667],"type":"Point"}
}