{
  "id": 7410880,
  "type": "Feature",
  "properties": {
    "tgn:hierarchy":[
        "tgn:7410880",
        "tgn:1000001",
        "tgn:7005590",
        "tgn:7005560",
        "tgn:7029392"
    ],
    "tgn:id":7410880,
    "tgn:name":"Paso de Corupa",
    "tgn:placetype":[
        "aat:300008347"
    ]
},
  "bbox": [],
  "geometry": {"coordinates":[-100.825,18.506944],"type":"Point"}
}