{
  "id": 2104055,
  "type": "Feature",
  "properties": {
    "tgn:hierarchy":[
        "tgn:2104055",
        "tgn:1000001",
        "tgn:7012149",
        "tgn:1002460",
        "tgn:7007826",
        "tgn:7029392"
    ],
    "tgn:id":2104055,
    "tgn:name":"Elysian Fields",
    "tgn:placetype":[
        "aat:300008347"
    ]
},
  "bbox": [],
  "geometry": {"coordinates":[-94.1667,32.3667],"type":"Point"}
}