{
  "id": 7518468,
  "type": "Feature",
  "properties": {
    "tgn:hierarchy":[
        "tgn:7518468",
        "tgn:1008380",
        "tgn:1000226",
        "tgn:7016827",
        "tgn:1000006",
        "tgn:7029392"
    ],
    "tgn:id":7518468,
    "tgn:name:en":"Mata Creek",
    "tgn:placetype":[
        "aat:300008699"
    ]
},
  "bbox": [],
  "geometry": {"coordinates":[174.333333,-38.833333],"type":"Point"}
}