{
  "id": 7545728,
  "type": "Feature",
  "properties": {
    "tgn:hierarchy":[
        "tgn:7545728",
        "tgn:1000004",
        "tgn:7031781",
        "tgn:7000198",
        "tgn:7029392"
    ],
    "tgn:id":7545728,
    "tgn:name:en":"Barthi",
    "tgn:placetype":[
        "aat:300008347"
    ]
},
  "bbox": [],
  "geometry": {"coordinates":[83.225876,23.658668],"type":"Point"}
}