{
  "id": 7589846,
  "type": "Feature",
  "properties": {
    "tgn:hierarchy":[
        "tgn:7589846",
        "tgn:1000004",
        "tgn:7000198",
        "tgn:7000799",
        "tgn:7029392"
    ],
    "tgn:id":7589846,
    "tgn:name:en":"Kunjiw\u0101la Forest",
    "tgn:placetype":[
        "aat:300008863"
    ]
},
  "bbox": [],
  "geometry": {"coordinates":[73.966667,34.619444],"type":"Point"}
}