{
  "id": 1069470,
  "type": "Feature",
  "properties": {
    "tgn:hierarchy":[
        "tgn:1069470",
        "tgn:1000004",
        "tgn:7002077",
        "tgn:1000111",
        "tgn:7029392"
    ],
    "tgn:id":1069470,
    "tgn:name":"Juncheng",
    "tgn:placetype":[
        "aat:300008347"
    ]
},
  "bbox": [],
  "geometry": {"coordinates":[114.6667,38.9333],"type":"Point"}
}