{
  "id": 1129836,
  "type": "Feature",
  "properties": {
    "tgn:hierarchy":[
        "tgn:1129836",
        "tgn:1000003",
        "tgn:7006417",
        "tgn:7029392"
    ],
    "tgn:id":1129836,
    "tgn:name":"Semanit, Lumi i",
    "tgn:placetype":[
        "aat:300008707"
    ]
},
  "bbox": [],
  "geometry": {"coordinates":[19.4075,40.816944],"type":"Point"}
}