{
  "id": 2160287,
  "type": "Feature",
  "properties": {
    "tgn:hierarchy":[
        "tgn:2160287",
        "tgn:1000001",
        "tgn:7012149",
        "tgn:7007523",
        "tgn:7029392"
    ],
    "tgn:id":2160287,
    "tgn:name":"Beefsteak Hollow",
    "tgn:placetype":[
        "aat:300008761"
    ]
},
  "bbox": [],
  "geometry": {"coordinates":[-91.1667,37.6667],"type":"Point"}
}