{
  "id": 7455219,
  "type": "Feature",
  "properties": {
    "tgn:hierarchy":[
        "tgn:7455219",
        "tgn:7002443",
        "tgn:5000552",
        "tgn:1000003",
        "tgn:7008591",
        "tgn:7029392"
    ],
    "tgn:id":7455219,
    "tgn:name:en":"Cwmorgan",
    "tgn:placetype":[
        "aat:300008347"
    ]
},
  "bbox": [],
  "geometry": {"coordinates":[-4.486944,51.986389],"type":"Point"}
}