{
  "id": 7544702,
  "type": "Feature",
  "properties": {
    "tgn:hierarchy":[
        "tgn:7544702",
        "tgn:1000004",
        "tgn:7000198",
        "tgn:7016722",
        "tgn:7029392"
    ],
    "tgn:id":7544702,
    "tgn:name:en":"Bar\u0101gaon",
    "tgn:placetype":[
        "aat:300008347"
    ]
},
  "bbox": [],
  "geometry": {"coordinates":[80.502121,27.748596],"type":"Point"}
}