{
  "id": 2447607,
  "type": "Feature",
  "properties": {
    "tgn:hierarchy":[
        "tgn:2447607",
        "tgn:1000001",
        "tgn:7012149",
        "tgn:2001917",
        "tgn:7007825",
        "tgn:7029392"
    ],
    "tgn:id":2447607,
    "tgn:name":"Lick Hollow",
    "tgn:placetype":[
        "aat:300008761"
    ]
},
  "bbox": [],
  "geometry": {"coordinates":[-87.95,36.4667],"type":"Point"}
}