{
  "id": 1126784,
  "type": "Feature",
  "properties": {
    "tgn:hierarchy":[
        "tgn:1126784",
        "tgn:1000004",
        "tgn:7014831",
        "tgn:7029392"
    ],
    "tgn:id":1126784,
    "tgn:name":"Mangde",
    "tgn:placetype":[
        "aat:300008707"
    ]
},
  "bbox": [],
  "geometry": {"coordinates":[90.95,26.8667],"type":"Point"}
}