{
  "id": 7308764,
  "type": "Feature",
  "properties": {
    "tgn:hierarchy":[
        "tgn:7308764",
        "tgn:1001623",
        "tgn:1000049",
        "tgn:1000002",
        "tgn:7029392"
    ],
    "tgn:id":7308764,
    "tgn:name":"Maipo, Cerro",
    "tgn:placetype":[
        "aat:300008795"
    ]
},
  "bbox": [],
  "geometry": {"coordinates":[-75.616667,-48.55],"type":"Point"}
}