{
  "id": 2363963,
  "type": "Feature",
  "properties": {
    "tgn:hierarchy":[
        "tgn:2363963",
        "tgn:1000001",
        "tgn:7012149",
        "tgn:7007158",
        "tgn:2000247",
        "tgn:7029392"
    ],
    "tgn:id":2363963,
    "tgn:name":"Green Mountain",
    "tgn:placetype":[
        "aat:300008798"
    ]
},
  "bbox": [],
  "geometry": {"coordinates":[-107.55,37.7833],"type":"Point"}
}