<<<<<<< HEAD
{
  "id": 2766836,
  "type": "Feature",
  "properties": {
    "tgn:hierarchy":[
        "tgn:2766836",
        "tgn:1000001",
        "tgn:7012149",
        "tgn:2000538",
        "tgn:7007251",
        "tgn:7029392"
    ],
    "tgn:id":2766836,
    "tgn:name":"White Pigeon",
    "tgn:placetype":[
        "aat:300008347"
    ]
},
  "bbox": [],
  "geometry": {"coordinates":[-89.8833,41.8833],"type":"Point"}
}
=======
{"geometry":{"type":"Point","coordinates":[-89.883300,41.883300]},"type":"Feature","properties":{"hierarchy":["tgn:2766836","tgn:1000001","tgn:7012149","tgn:2000538","tgn:7007251","tgn:7029392"],"placetype":["aat:300008347"],"id":2766836,"name:xx":"White Pigeon"}}
>>>>>>> 03f74aca74312dbeaf24d7e61306dd6a786dc3d0
