{
  "id": 7277232,
  "type": "Feature",
  "properties": {
    "tgn:hierarchy":[
        "tgn:7277232",
        "tgn:1001623",
        "tgn:1000049",
        "tgn:1000002",
        "tgn:7029392"
    ],
    "tgn:id":7277232,
    "tgn:name":"Valle Mirta",
    "tgn:placetype":[
        "aat:300008761"
    ]
},
  "bbox": [],
  "geometry": {"coordinates":[-72.319444,-43.881944],"type":"Point"}
}