{
  "id": 2673709,
  "type": "Feature",
  "properties": {
    "tgn:hierarchy":[
        "tgn:2673709",
        "tgn:1000001",
        "tgn:2000463",
        "tgn:7012149",
        "tgn:7007250",
        "tgn:7029392"
    ],
    "tgn:id":2673709,
    "tgn:name":"Snow Cone",
    "tgn:placetype":[
        "aat:300008798"
    ]
},
  "bbox": [],
  "geometry": {"coordinates":[-113.55,43.4333],"type":"Point"}
}