<<<<<<< HEAD
{
  "id": 2251262,
  "type": "Feature",
  "properties": {
    "tgn:hierarchy":[
        "tgn:2251262",
        "tgn:1000001",
        "tgn:7012149",
        "tgn:2002119",
        "tgn:7007827",
        "tgn:7029392"
    ],
    "tgn:id":2251262,
    "tgn:name":"Comb Wash",
    "tgn:placetype":[
        "aat:300008761"
    ]
},
  "bbox": [],
  "geometry": {"coordinates":[-109.7,37.6167],"type":"Point"}
}
=======
{"geometry":{"type":"Point","coordinates":[-109.700000,37.616700]},"type":"Feature","properties":{"hierarchy":["tgn:2251262","tgn:1000001","tgn:7012149","tgn:2002119","tgn:7007827","tgn:7029392"],"placetype":["aat:300008761"],"id":2251262,"name:xx":"Comb Wash"}}
>>>>>>> 03f74aca74312dbeaf24d7e61306dd6a786dc3d0
