<<<<<<< HEAD
{
  "id": 2251654,
  "type": "Feature",
  "properties": {
    "tgn:hierarchy":[
        "tgn:2251654",
        "tgn:1000001",
        "tgn:7012149",
        "tgn:2002379",
        "tgn:7007923",
        "tgn:7029392"
    ],
    "tgn:id":2251654,
    "tgn:name":"Company Creek",
    "tgn:placetype":[
        "aat:300008706"
    ]
},
  "bbox": [],
  "geometry": {"coordinates":[-109.6333,44.6333],"type":"Point"}
}
=======
{"geometry":{"type":"Point","coordinates":[-109.633300,44.633300]},"type":"Feature","properties":{"hierarchy":["tgn:2251654","tgn:1000001","tgn:7012149","tgn:2002379","tgn:7007923","tgn:7029392"],"placetype":["aat:300008706"],"id":2251654,"name:xx":"Company Creek"}}
>>>>>>> 03f74aca74312dbeaf24d7e61306dd6a786dc3d0
