{
  "id": 7589994,
  "type": "Feature",
  "properties": {
    "tgn:hierarchy":[
        "tgn:7589994",
        "tgn:1000004",
        "tgn:7000198",
        "tgn:7000799",
        "tgn:7029392"
    ],
    "tgn:id":7589994,
    "tgn:name:en":"Ashniji",
    "tgn:placetype":[
        "aat:300008347"
    ]
},
  "bbox": [],
  "geometry": {"coordinates":[73.903631,34.089147],"type":"Point"}
}