{
  "id": 2366579,
  "type": "Feature",
  "properties": {
    "tgn:hierarchy":[
        "tgn:2366579",
        "tgn:1000001",
        "tgn:7012149",
        "tgn:7015666",
        "tgn:7007825",
        "tgn:7029392"
    ],
    "tgn:id":2366579,
    "tgn:name":"Grimmett Hill",
    "tgn:placetype":[
        "aat:300008798"
    ]
},
  "bbox": [],
  "geometry": {"coordinates":[-87.4167,35.7333],"type":"Point"}
}