{
  "id": 7193857,
  "type": "Feature",
  "properties": {
    "tgn:hierarchy":[
        "tgn:7193857",
        "tgn:7000096",
        "tgn:1000003",
        "tgn:7000084",
        "tgn:7029392"
    ],
    "tgn:id":7193857,
    "tgn:name":"Feldgrieben",
    "tgn:placetype":[
        "aat:300008347"
    ]
},
  "bbox": [],
  "geometry": {"coordinates":[12.95,53.133333],"type":"Point"}
}