{
  "id": 7011587,
  "type": "Feature",
  "properties": {
    "tgn:hierarchy":[
        "tgn:7011587",
        "tgn:7002445",
        "tgn:1000003",
        "tgn:7008153",
        "tgn:7008591",
        "tgn:7029392"
    ],
    "tgn:id":7011587,
    "tgn:name:en":"Meopham",
    "tgn:placetype":[
        "aat:300008347",
        "aat:300008372"
    ]
},
  "bbox": [],
  "geometry": {"coordinates":[0.366667,51.366667],"type":"Point"}
}