{
  "id": 7033216,
  "type": "Feature",
  "properties": {
    "tgn:hierarchy":[
        "tgn:7033216",
        "tgn:1003440",
        "tgn:1000003",
        "tgn:7003124",
        "tgn:1000080",
        "tgn:7029392"
    ],
    "tgn:id":7033216,
    "tgn:name":"Dobbiaca, Lago di",
    "tgn:placetype":[
        "aat:300008680"
    ]
},
  "bbox": [],
  "geometry": {"coordinates":[12.218333,46.703889],"type":"Point"}
}