{
  "id": 2558260,
  "type": "Feature",
  "properties": {
    "tgn:hierarchy":[
        "tgn:2558260",
        "tgn:1000001",
        "tgn:7012149",
        "tgn:2002029",
        "tgn:7007826",
        "tgn:7029392"
    ],
    "tgn:id":2558260,
    "tgn:name":"Olds Slough",
    "tgn:placetype":[
        "aat:300008699"
    ]
},
  "bbox": [],
  "geometry": {"coordinates":[-98.1833,28.4667],"type":"Point"}
}