<<<<<<< HEAD
{
  "id": 2330048,
  "type": "Feature",
  "properties": {
    "tgn:hierarchy":[
        "tgn:2330048",
        "tgn:1000001",
        "tgn:2001746",
        "tgn:7012149",
        "tgn:7007712",
        "tgn:7029392"
    ],
    "tgn:id":2330048,
    "tgn:name":"Flagg Pond",
    "tgn:placetype":[
        "aat:300008680"
    ]
},
  "bbox": [],
  "geometry": {"coordinates":[-79.0833,33.4833],"type":"Point"}
}
=======
{"geometry":{"type":"Point","coordinates":[-79.083300,33.483300]},"type":"Feature","properties":{"hierarchy":["tgn:2330048","tgn:1000001","tgn:2001746","tgn:7012149","tgn:7007712","tgn:7029392"],"placetype":["aat:300008680"],"id":2330048,"name:xx":"Flagg Pond"}}
>>>>>>> 03f74aca74312dbeaf24d7e61306dd6a786dc3d0
