{
  "id": 2538161,
  "type": "Feature",
  "properties": {
    "tgn:hierarchy":[
        "tgn:2538161",
        "tgn:1000001",
        "tgn:7012149",
        "tgn:2001300",
        "tgn:7007524",
        "tgn:7029392"
    ],
    "tgn:id":2538161,
    "tgn:name":"Nelson Lake",
    "tgn:placetype":[
        "aat:300008680"
    ]
},
  "bbox": [],
  "geometry": {"coordinates":[-114.35,45.8167],"type":"Point"}
}