{
  "id": 7279178,
  "type": "Feature",
  "properties": {
    "tgn:hierarchy":[
        "tgn:7279178",
        "tgn:1001702",
        "tgn:1000049",
        "tgn:1000002",
        "tgn:7029392"
    ],
    "tgn:id":7279178,
    "tgn:name":"Rosa, Punta",
    "tgn:placetype":[
        "aat:300386846"
    ]
},
  "bbox": [],
  "geometry": {"coordinates":[-70.816667,-52.85],"type":"Point"}
}