{
  "id": 7366810,
  "type": "Feature",
  "properties": {
    "tgn:hierarchy":[
        "tgn:7366810",
        "tgn:7005581",
        "tgn:1000001",
        "tgn:7005560",
        "tgn:7029392"
    ],
    "tgn:id":7366810,
    "tgn:name":"El Pipizque",
    "tgn:placetype":[
        "aat:300008347"
    ]
},
  "bbox": [],
  "geometry": {"coordinates":[-107.816667,26.833333],"type":"Point"}
}