{
  "id": 7554839,
  "type": "Feature",
  "properties": {
    "tgn:hierarchy":[
        "tgn:7554839",
        "tgn:1000004",
        "tgn:7000198",
        "tgn:1001894",
        "tgn:7029392"
    ],
    "tgn:id":7554839,
    "tgn:name:en":"Maina",
    "tgn:placetype":[
        "aat:300008347"
    ]
},
  "bbox": [],
  "geometry": {"coordinates":[76.663055,23.171101],"type":"Point"}
}