{
  "id": 7074853,
  "type": "Feature",
  "properties": {
    "tgn:hierarchy":[
        "tgn:7074853",
        "tgn:1000003",
        "tgn:7003677",
        "tgn:7000084",
        "tgn:7029392"
    ],
    "tgn:id":7074853,
    "tgn:name":"Hamb\u00fcren",
    "tgn:placetype":[
        "aat:300008347"
    ]
},
  "bbox": [],
  "geometry": {"coordinates":[7.85,52.266667],"type":"Point"}
}