{
  "id": 2336129,
  "type": "Feature",
  "properties": {
    "tgn:hierarchy":[
        "tgn:2336129",
        "tgn:1000001",
        "tgn:7012149",
        "tgn:7014589",
        "tgn:7007515",
        "tgn:7029392"
    ],
    "tgn:id":2336129,
    "tgn:name":"Foster Island",
    "tgn:placetype":[
        "aat:300008791"
    ]
},
  "bbox": [],
  "geometry": {"coordinates":[-67.8167,44.5167],"type":"Point"}
}