<<<<<<< HEAD
{
  "id": 2336129,
  "type": "Feature",
  "properties": {
    "tgn:hierarchy":[
        "tgn:2336129",
        "tgn:1000001",
        "tgn:7012149",
        "tgn:7014589",
        "tgn:7007515",
        "tgn:7029392"
    ],
    "tgn:id":2336129,
    "tgn:name":"Foster Island",
    "tgn:placetype":[
        "aat:300008791"
    ]
},
  "bbox": [],
  "geometry": {"coordinates":[-67.8167,44.5167],"type":"Point"}
}
=======
{"geometry":{"type":"Point","coordinates":[-67.816700,44.516700]},"type":"Feature","properties":{"hierarchy":["tgn:2336129","tgn:1000001","tgn:7012149","tgn:7014589","tgn:7007515","tgn:7029392"],"placetype":["aat:300008791"],"id":2336129,"name:xx":"Foster Island"}}
>>>>>>> 03f74aca74312dbeaf24d7e61306dd6a786dc3d0
