{
  "id": 2455675,
  "type": "Feature",
  "properties": {
    "tgn:hierarchy":[
        "tgn:2455675",
        "tgn:1000001",
        "tgn:7012149",
        "tgn:2000882",
        "tgn:7007256",
        "tgn:7029392"
    ],
    "tgn:id":2455675,
    "tgn:name":"Little Grand Bay",
    "tgn:placetype":[
        "aat:300008680"
    ]
},
  "bbox": [],
  "geometry": {"coordinates":[-90.3167,29.3167],"type":"Point"}
}