{
  "id": 7218513,
  "type": "Feature",
  "properties": {
    "tgn:hierarchy":[
        "tgn:7218513",
        "tgn:7011161",
        "tgn:7002674",
        "tgn:1000003",
        "tgn:1000074",
        "tgn:7029392"
    ],
    "tgn:id":7218513,
    "tgn:name":"\u00c1gios The\u00f3doros",
    "tgn:placetype":[
        "aat:300007466"
    ]
},
  "bbox": [],
  "geometry": {"coordinates":[25.989722,38.201944],"type":"Point"}
}