{
  "id": 7257303,
  "type": "Feature",
  "properties": {
    "tgn:hierarchy":[
        "tgn:7257303",
        "tgn:7593113",
        "tgn:7016620",
        "tgn:7593112",
        "tgn:1000001",
        "tgn:7029392"
    ],
    "tgn:id":7257303,
    "tgn:name:nl":"Roi Pagai",
    "tgn:placetype":[
        "aat:300387200"
    ]
},
  "bbox": [],
  "geometry": {"coordinates":[-68.25,12.166667],"type":"Point"}
}