{
  "id": 2555572,
  "type": "Feature",
  "properties": {
    "tgn:hierarchy":[
        "tgn:2555572",
        "tgn:1000001",
        "tgn:7012149",
        "tgn:2001965",
        "tgn:7007826",
        "tgn:7029392"
    ],
    "tgn:id":2555572,
    "tgn:name":"Ogden",
    "tgn:placetype":[
        "aat:300008347"
    ]
},
  "bbox": [],
  "geometry": {"coordinates":[-100.1167,34.0833],"type":"Point"}
}