{
  "id": 7340811,
  "type": "Feature",
  "properties": {
    "tgn:hierarchy":[
        "tgn:7340811",
        "tgn:7002827",
        "tgn:1000003",
        "tgn:7002789",
        "tgn:1000095",
        "tgn:7029392"
    ],
    "tgn:id":7340811,
    "tgn:name":"Buzarra",
    "tgn:placetype":[
        "aat:300008347"
    ]
},
  "bbox": [],
  "geometry": {"coordinates":[-2.316667,42.25],"type":"Point"}
}