{
  "id": 7078915,
  "type": "Feature",
  "properties": {
    "tgn:hierarchy":[
        "tgn:7078915",
        "tgn:7003692",
        "tgn:1000003",
        "tgn:7000084",
        "tgn:7029392"
    ],
    "tgn:id":7078915,
    "tgn:name":"W\u00fcrm",
    "tgn:placetype":[
        "aat:300008347"
    ]
},
  "bbox": [],
  "geometry": {"coordinates":[8.733333,48.866667],"type":"Point"}
}