<<<<<<< HEAD
{
  "id": 2150904,
  "type": "Feature",
  "properties": {
    "tgn:hierarchy":[
        "tgn:2150904",
        "tgn:1000001",
        "tgn:7012149",
        "tgn:2002098",
        "tgn:7007826",
        "tgn:7029392"
    ],
    "tgn:id":2150904,
    "tgn:name":"Bass Mountain",
    "tgn:placetype":[
        "aat:300008798"
    ]
},
  "bbox": [],
  "geometry": {"coordinates":[-98.6333,33.0],"type":"Point"}
}
=======
{"geometry":{"type":"Point","coordinates":[-98.633300,33.000000]},"type":"Feature","properties":{"hierarchy":["tgn:2150904","tgn:1000001","tgn:7012149","tgn:2002098","tgn:7007826","tgn:7029392"],"placetype":["aat:300008798"],"id":2150904,"name:xx":"Bass Mountain"}}
>>>>>>> 03f74aca74312dbeaf24d7e61306dd6a786dc3d0
