{
  "id": 2427655,
  "type": "Feature",
  "properties": {
    "tgn:hierarchy":[
        "tgn:2427655",
        "tgn:1000001",
        "tgn:7012149",
        "tgn:7007157",
        "tgn:1002608",
        "tgn:7029392"
    ],
    "tgn:id":2427655,
    "tgn:name":"Josephine Creek",
    "tgn:placetype":[
        "aat:300008706"
    ]
},
  "bbox": [],
  "geometry": {"coordinates":[-118.15,34.2833],"type":"Point"}
}