<<<<<<< HEAD
{
  "id": 7175646,
  "type": "Feature",
  "properties": {
    "tgn:hierarchy":[
        "tgn:7175646",
        "tgn:1000003",
        "tgn:7000094",
        "tgn:7000084",
        "tgn:7029392"
    ],
    "tgn:id":7175646,
    "tgn:name":"Gro\u00dfes Moor",
    "tgn:placetype":[
        "aat:300008903"
    ]
},
  "bbox": [],
  "geometry": {"coordinates":[11.9,53.483333],"type":"Point"}
}
=======
{"geometry":{"type":"Point","coordinates":[11.900000,53.483333]},"type":"Feature","properties":{"hierarchy":["tgn:7175646","tgn:1000003","tgn:7000094","tgn:7000084","tgn:7029392"],"placetype":["aat:300008903"],"id":7175646,"name:xx":"Gro\u00dfes Moor"}}
>>>>>>> 03f74aca74312dbeaf24d7e61306dd6a786dc3d0
