{
  "id": 2125885,
  "type": "Feature",
  "properties": {
    "tgn:hierarchy":[
        "tgn:2125885",
        "tgn:1000001",
        "tgn:7012149",
        "tgn:1002819",
        "tgn:7007523",
        "tgn:7029392"
    ],
    "tgn:id":2125885,
    "tgn:name":"Adams Lake",
    "tgn:placetype":[
        "aat:300006191"
    ]
},
  "bbox": [],
  "geometry": {"coordinates":[-92.5333,39.55],"type":"Point"}
}