{
  "id": 7439446,
  "type": "Feature",
  "properties": {
    "tgn:hierarchy":[
        "tgn:7439446",
        "tgn:1000001",
        "tgn:1001906",
        "tgn:7005560",
        "tgn:7029392"
    ],
    "tgn:id":7439446,
    "tgn:name":"San Pelayo",
    "tgn:placetype":[
        "aat:300000241"
    ]
},
  "bbox": [],
  "geometry": {"coordinates":[-104.083333,21.383333],"type":"Point"}
}