{
  "id": 7551721,
  "type": "Feature",
  "properties": {
    "tgn:hierarchy":[
        "tgn:7551721",
        "tgn:1000004",
        "tgn:7000198",
        "tgn:7016722",
        "tgn:7029392"
    ],
    "tgn:id":7551721,
    "tgn:name:en":"Daw\u0101mi",
    "tgn:placetype":[
        "aat:300008347"
    ]
},
  "bbox": [],
  "geometry": {"coordinates":[83.566667,25.866667],"type":"Point"}
}