<<<<<<< HEAD
{
  "id": 7119086,
  "type": "Feature",
  "properties": {
    "tgn:hierarchy":[
        "tgn:7119086",
        "tgn:1000003",
        "tgn:7003688",
        "tgn:7000084",
        "tgn:7029392"
    ],
    "tgn:id":7119086,
    "tgn:name":"Pohlsee",
    "tgn:placetype":[
        "aat:300000206"
    ]
},
  "bbox": [],
  "geometry": {"coordinates":[9.933333,54.233333],"type":"Point"}
}
=======
{"geometry":{"type":"Point","coordinates":[9.933333,54.233333]},"type":"Feature","properties":{"hierarchy":["tgn:7119086","tgn:1000003","tgn:7003688","tgn:7000084","tgn:7029392"],"placetype":["aat:300000206"],"id":7119086,"name:xx":"Pohlsee"}}
>>>>>>> 03f74aca74312dbeaf24d7e61306dd6a786dc3d0
