{
  "id": 7493235,
  "type": "Feature",
  "properties": {
    "tgn:hierarchy":[
        "tgn:7493235",
        "tgn:1000004",
        "tgn:7492971",
        "tgn:1000141",
        "tgn:7029392"
    ],
    "tgn:id":7493235,
    "tgn:name":"Xinnanshi",
    "tgn:placetype":[
        "aat:300387033"
    ]
},
  "bbox": [],
  "geometry": {"coordinates":[120.55375,22.784884],"type":"Point"}
}