{
  "id": 2548040,
  "type": "Feature",
  "properties": {
    "tgn:hierarchy":[
        "tgn:2548040",
        "tgn:1000001",
        "tgn:2002368",
        "tgn:7012149",
        "tgn:7007923",
        "tgn:7029392"
    ],
    "tgn:id":2548040,
    "tgn:name":"North Heather Creek",
    "tgn:placetype":[
        "aat:300008706"
    ]
},
  "bbox": [],
  "geometry": {"coordinates":[-106.9833,41.2167],"type":"Point"}
}