{
  "id": 2526838,
  "type": "Feature",
  "properties": {
    "tgn:hierarchy":[
        "tgn:2526838",
        "tgn:1000001",
        "tgn:7012149",
        "tgn:2000283",
        "tgn:7007240",
        "tgn:7029392"
    ],
    "tgn:id":2526838,
    "tgn:name":"Moultrie Creek",
    "tgn:placetype":[
        "aat:300008706"
    ]
},
  "bbox": [],
  "geometry": {"coordinates":[-81.3667,29.85],"type":"Point"}
}