{
  "id": 7291512,
  "type": "Feature",
  "properties": {
    "tgn:hierarchy":[
        "tgn:7291512",
        "tgn:1001657",
        "tgn:1000049",
        "tgn:1000002",
        "tgn:7029392"
    ],
    "tgn:id":7291512,
    "tgn:name":"El Litre, Quebrada",
    "tgn:placetype":[
        "aat:300008699"
    ]
},
  "bbox": [],
  "geometry": {"coordinates":[-71.65,-31.283333],"type":"Point"}
}