{
  "id": 2429354,
  "type": "Feature",
  "properties": {
    "tgn:hierarchy":[
        "tgn:2429354",
        "tgn:1000001",
        "tgn:7012149",
        "tgn:7007157",
        "tgn:1002608",
        "tgn:7029392"
    ],
    "tgn:id":2429354,
    "tgn:name":"Juniper Bowl",
    "tgn:placetype":[
        "aat:300386845"
    ]
},
  "bbox": [],
  "geometry": {"coordinates":[-117.9333,34.45],"type":"Point"}
}