{
  "id": 4008287,
  "type": "Feature",
  "properties": {
    "tgn:hierarchy":[
        "tgn:4008287",
        "tgn:7018767",
        "tgn:1000003",
        "tgn:7006413",
        "tgn:7029392"
    ],
    "tgn:id":4008287,
    "tgn:name":"Osenovo",
    "tgn:placetype":[
        "aat:300008347"
    ]
},
  "bbox": [],
  "geometry": {"coordinates":[28.016,43.316],"type":"Point"}
}