{
  "id": 2595475,
  "type": "Feature",
  "properties": {
    "tgn:hierarchy":[
        "tgn:2595475",
        "tgn:1000001",
        "tgn:7012149",
        "tgn:1002771",
        "tgn:7007826",
        "tgn:7029392"
    ],
    "tgn:id":2595475,
    "tgn:name":"Potato Hill",
    "tgn:placetype":[
        "aat:300008798"
    ]
},
  "bbox": [],
  "geometry": {"coordinates":[-98.0167,32.6167],"type":"Point"}
}