{
  "id": 7589441,
  "type": "Feature",
  "properties": {
    "tgn:hierarchy":[
        "tgn:7589441",
        "tgn:1000004",
        "tgn:7000198",
        "tgn:7000799",
        "tgn:7029392"
    ],
    "tgn:id":7589441,
    "tgn:name:en":"Ph\u0101nra",
    "tgn:placetype":[
        "aat:300008347"
    ]
},
  "bbox": [],
  "geometry": {"coordinates":[74.366667,33.175],"type":"Point"}
}