<<<<<<< HEAD
{
  "id": 7029667,
  "type": "Feature",
  "properties": {
    "tgn:hierarchy":[
        "tgn:7029667",
        "tgn:7001155",
        "tgn:1000003",
        "tgn:7002790",
        "tgn:1000095",
        "tgn:7029392"
    ],
    "tgn:id":7029667,
    "tgn:name:es":"Irache",
    "tgn:placetype":[
        "aat:300008347"
    ]
},
  "bbox": [],
  "geometry": {"coordinates":[-2.033,42.65],"type":"Point"}
}
=======
{"geometry":{"type":"Point","coordinates":[-2.033000,42.650000]},"type":"Feature","properties":{"hierarchy":["tgn:7029667","tgn:7001155","tgn:1000003","tgn:7002790","tgn:1000095","tgn:7029392"],"placetype":["aat:300008347"],"id":7029667,"name:es":"Irache"}}
>>>>>>> 03f74aca74312dbeaf24d7e61306dd6a786dc3d0
