{
  "id": 7060771,
  "type": "Feature",
  "properties": {
    "tgn:hierarchy":[
        "tgn:7060771",
        "tgn:7003669",
        "tgn:1000003",
        "tgn:7000084",
        "tgn:7029392"
    ],
    "tgn:id":7060771,
    "tgn:name":"Angert-Kopf",
    "tgn:placetype":[
        "aat:300008795"
    ]
},
  "bbox": [],
  "geometry": {"coordinates":[11.466667,47.716667],"type":"Point"}
}