{
  "id": 2208461,
  "type": "Feature",
  "properties": {
    "tgn:hierarchy":[
        "tgn:2208461",
        "tgn:1000001",
        "tgn:7012149",
        "tgn:2001503",
        "tgn:7007709",
        "tgn:7029392"
    ],
    "tgn:id":2208461,
    "tgn:name":"Burnett Siding",
    "tgn:placetype":[
        "aat:300008347"
    ]
},
  "bbox": [],
  "geometry": {"coordinates":[-82.9333,35.3833],"type":"Point"}
}