{
  "id": 7467335,
  "type": "Feature",
  "properties": {
    "tgn:hierarchy":[
        "tgn:7467335",
        "tgn:1000004",
        "tgn:7467799",
        "tgn:1000141",
        "tgn:7029392"
    ],
    "tgn:id":7467335,
    "tgn:name":"Ayizhuang",
    "tgn:placetype":[
        "aat:300000745"
    ]
},
  "bbox": [],
  "geometry": {"coordinates":[120.553816,24.096248],"type":"Point"}
}