{
  "id": 2372001,
  "type": "Feature",
  "properties": {
    "tgn:hierarchy":[
        "tgn:2372001",
        "tgn:2000293",
        "tgn:1000001",
        "tgn:7012149",
        "tgn:7007248",
        "tgn:7029392"
    ],
    "tgn:id":2372001,
    "tgn:name":"Half Moon Lake",
    "tgn:placetype":[
        "aat:300008680"
    ]
},
  "bbox": [],
  "geometry": {"coordinates":[-83.0333,31.2167],"type":"Point"}
}