{
  "id": 1107794,
  "type": "Feature",
  "properties": {
    "tgn:hierarchy":[
        "tgn:1107794",
        "tgn:1000001",
        "tgn:7012149",
        "tgn:2001717",
        "tgn:7007708",
        "tgn:7029392"
    ],
    "tgn:id":1107794,
    "tgn:name":"Twin Buttes",
    "tgn:placetype":[
        "aat:300008744"
    ]
},
  "bbox": [],
  "geometry": {"coordinates":[-122.2333,44.3333],"type":"Point"}
}