{
  "id": 7344892,
  "type": "Feature",
  "properties": {
    "tgn:hierarchy":[
        "tgn:7344892",
        "tgn:7002808",
        "tgn:7030216",
        "tgn:1000003",
        "tgn:1000095",
        "tgn:7029392"
    ],
    "tgn:id":7344892,
    "tgn:name":"Ermita Alto de San Mateo",
    "tgn:placetype":[
        "aat:300000640"
    ]
},
  "bbox": [],
  "geometry": {"coordinates":[2.328836,41.51679],"type":"Point"}
}