{
  "id": 2509392,
  "type": "Feature",
  "properties": {
    "tgn:hierarchy":[
        "tgn:2509392",
        "tgn:1000001",
        "tgn:7012149",
        "tgn:2002385",
        "tgn:7007923",
        "tgn:7029392"
    ],
    "tgn:id":2509392,
    "tgn:name":"Middle Fork Sheep Creek",
    "tgn:placetype":[
        "aat:300008706"
    ]
},
  "bbox": [],
  "geometry": {"coordinates":[-110.8833,41.55],"type":"Point"}
}