{
  "id": 2234638,
  "type": "Feature",
  "properties": {
    "tgn:hierarchy":[
        "tgn:2234638",
        "tgn:1000001",
        "tgn:2001183",
        "tgn:7012149",
        "tgn:7007523",
        "tgn:7029392"
    ],
    "tgn:id":2234638,
    "tgn:name":"Cherry Branch",
    "tgn:placetype":[
        "aat:300008699"
    ]
},
  "bbox": [],
  "geometry": {"coordinates":[-93.9833,37.7667],"type":"Point"}
}