{
  "id": 2617761,
  "type": "Feature",
  "properties": {
    "tgn:hierarchy":[
        "tgn:2617761",
        "tgn:1000001",
        "tgn:7012149",
        "tgn:1002897",
        "tgn:7007920",
        "tgn:7029392"
    ],
    "tgn:id":2617761,
    "tgn:name":"Ridell Lake",
    "tgn:placetype":[
        "aat:300008680"
    ]
},
  "bbox": [],
  "geometry": {"coordinates":[-122.0167,45.6167],"type":"Point"}
}