<<<<<<< HEAD
{
  "id": 2407051,
  "type": "Feature",
  "properties": {
    "tgn:hierarchy":[
        "tgn:2407051",
        "tgn:1000001",
        "tgn:7012149",
        "tgn:2001715",
        "tgn:7007708",
        "tgn:7029392"
    ],
    "tgn:id":2407051,
    "tgn:name":"Hunter Spring",
    "tgn:placetype":[
        "aat:300008697"
    ]
},
  "bbox": [],
  "geometry": {"coordinates":[-120.7333,42.0833],"type":"Point"}
}
=======
{"geometry":{"type":"Point","coordinates":[-120.733300,42.083300]},"type":"Feature","properties":{"hierarchy":["tgn:2407051","tgn:1000001","tgn:7012149","tgn:2001715","tgn:7007708","tgn:7029392"],"placetype":["aat:300008697"],"id":2407051,"name:xx":"Hunter Spring"}}
>>>>>>> 03f74aca74312dbeaf24d7e61306dd6a786dc3d0
