{
  "id": 2183415,
  "type": "Feature",
  "properties": {
    "tgn:hierarchy":[
        "tgn:2183415",
        "tgn:1000001",
        "tgn:2000922",
        "tgn:7012149",
        "tgn:7007515",
        "tgn:7029392"
    ],
    "tgn:id":2183415,
    "tgn:name":"Bluff Head",
    "tgn:placetype":[
        "aat:300008798"
    ]
},
  "bbox": [],
  "geometry": {"coordinates":[-68.6667,44.3833],"type":"Point"}
}