{
  "id": 2335518,
  "type": "Feature",
  "properties": {
    "tgn:hierarchy":[
        "tgn:2335518",
        "tgn:1000001",
        "tgn:7012149",
        "tgn:2002266",
        "tgn:7013961",
        "tgn:7029392"
    ],
    "tgn:id":2335518,
    "tgn:name":"Fort Run",
    "tgn:placetype":[
        "aat:300008699"
    ]
},
  "bbox": [],
  "geometry": {"coordinates":[-78.85,39.05],"type":"Point"}
}