<<<<<<< HEAD
{
  "id": 2335518,
  "type": "Feature",
  "properties": {
    "tgn:hierarchy":[
        "tgn:2335518",
        "tgn:1000001",
        "tgn:7012149",
        "tgn:2002266",
        "tgn:7013961",
        "tgn:7029392"
    ],
    "tgn:id":2335518,
    "tgn:name":"Fort Run",
    "tgn:placetype":[
        "aat:300008699"
    ]
},
  "bbox": [],
  "geometry": {"coordinates":[-78.85,39.05],"type":"Point"}
}
=======
{"geometry":{"type":"Point","coordinates":[-78.850000,39.050000]},"type":"Feature","properties":{"hierarchy":["tgn:2335518","tgn:1000001","tgn:7012149","tgn:2002266","tgn:7013961","tgn:7029392"],"placetype":["aat:300008699"],"id":2335518,"name:xx":"Fort Run"}}
>>>>>>> 03f74aca74312dbeaf24d7e61306dd6a786dc3d0
