{
  "id": 7268562,
  "type": "Feature",
  "properties": {
    "tgn:hierarchy":[
        "tgn:7268562",
        "tgn:1000003",
        "tgn:7003632",
        "tgn:7016845",
        "tgn:7029392"
    ],
    "tgn:id":7268562,
    "tgn:name:nl":"Noordergat",
    "tgn:placetype":[
        "aat:300387026"
    ]
},
  "bbox": [],
  "geometry": {"coordinates":[4.233333,51.65],"type":"Point"}
}