{
  "id": 2379604,
  "type": "Feature",
  "properties": {
    "tgn:hierarchy":[
        "tgn:2379604",
        "tgn:1000001",
        "tgn:7012149",
        "tgn:2001199",
        "tgn:7007523",
        "tgn:7029392"
    ],
    "tgn:id":2379604,
    "tgn:name":"Haseltine Branch",
    "tgn:placetype":[
        "aat:300008699"
    ]
},
  "bbox": [],
  "geometry": {"coordinates":[-93.3833,37.2167],"type":"Point"}
}