{
  "id": 2225205,
  "type": "Feature",
  "properties": {
    "tgn:hierarchy":[
        "tgn:2225205",
        "tgn:1002338",
        "tgn:1000001",
        "tgn:7012149",
        "tgn:7007516",
        "tgn:7029392"
    ],
    "tgn:id":2225205,
    "tgn:name":"Castle Haven Point",
    "tgn:placetype":[
        "aat:300008850"
    ]
},
  "bbox": [],
  "geometry": {"coordinates":[-76.1667,38.6167],"type":"Point"}
}