{
  "id": 1037527,
  "type": "Feature",
  "properties": {
    "tgn:hierarchy":[
        "tgn:1037527",
        "tgn:1000003",
        "tgn:7003685",
        "tgn:7000084",
        "tgn:7029392"
    ],
    "tgn:id":1037527,
    "tgn:name":"Pulsnitz",
    "tgn:placetype":[
        "aat:300008347"
    ]
},
  "bbox": [],
  "geometry": {"coordinates":[14.016667,51.183333],"type":"Point"}
}