{
  "id": 7009695,
  "type": "Feature",
  "properties": {
    "tgn:hierarchy":[
        "tgn:7009695",
        "tgn:1003483",
        "tgn:1000003",
        "tgn:7003240",
        "tgn:1000080",
        "tgn:7029392"
    ],
    "tgn:id":7009695,
    "tgn:name":"Fiorenzuola di Focara",
    "tgn:placetype":[
        "aat:300008347",
        "aat:300008375"
    ]
},
  "bbox": [],
  "geometry": {"coordinates":[12.8167,43.95],"type":"Point"}
}