{
  "id": 2109271,
  "type": "Feature",
  "properties": {
    "tgn:hierarchy":[
        "tgn:2109271",
        "tgn:1000001",
        "tgn:2002103",
        "tgn:7012149",
        "tgn:7007827",
        "tgn:7029392"
    ],
    "tgn:id":2109271,
    "tgn:name":"Smithfield",
    "tgn:placetype":[
        "aat:300008347"
    ]
},
  "bbox": [],
  "geometry": {"coordinates":[-111.8167,41.8333],"type":"Point"}
}