{
  "id": 1139257,
  "type": "Feature",
  "properties": {
    "tgn:hierarchy":[
        "tgn:1139257",
        "tgn:1000004",
        "tgn:7016672",
        "tgn:1000111",
        "tgn:7029392"
    ],
    "tgn:id":1139257,
    "tgn:name":"Linqi",
    "tgn:placetype":[
        "aat:300008347"
    ]
},
  "bbox": [],
  "geometry": {"coordinates":[113.8833,35.7667],"type":"Point"}
}