<<<<<<< HEAD
{
  "id": 2760928,
  "type": "Feature",
  "properties": {
    "tgn:hierarchy":[
        "tgn:2760928",
        "tgn:1000001",
        "tgn:7012149",
        "tgn:2002087",
        "tgn:7007826",
        "tgn:7029392"
    ],
    "tgn:id":2760928,
    "tgn:name":"West Hollow",
    "tgn:placetype":[
        "aat:300008761"
    ]
},
  "bbox": [],
  "geometry": {"coordinates":[-99.5833,29.4833],"type":"Point"}
}
=======
{"geometry":{"type":"Point","coordinates":[-99.583300,29.483300]},"type":"Feature","properties":{"hierarchy":["tgn:2760928","tgn:1000001","tgn:7012149","tgn:2002087","tgn:7007826","tgn:7029392"],"placetype":["aat:300008761"],"id":2760928,"name:xx":"West Hollow"}}
>>>>>>> 03f74aca74312dbeaf24d7e61306dd6a786dc3d0
