{
  "id": 2071288,
  "type": "Feature",
  "properties": {
    "tgn:hierarchy":[
        "tgn:2071288",
        "tgn:1000001",
        "tgn:7012149",
        "tgn:1002356",
        "tgn:7007568",
        "tgn:7029392"
    ],
    "tgn:id":2071288,
    "tgn:name":"North Evans",
    "tgn:placetype":[
        "aat:300008347"
    ]
},
  "bbox": [],
  "geometry": {"coordinates":[-78.9333,42.6833],"type":"Point"}
}