{
  "id": 2073588,
  "type": "Feature",
  "properties": {
    "tgn:hierarchy":[
        "tgn:2073588",
        "tgn:1000001",
        "tgn:7012149",
        "tgn:2001519",
        "tgn:7007709",
        "tgn:7029392"
    ],
    "tgn:id":2073588,
    "tgn:name":"Bandana",
    "tgn:placetype":[
        "aat:300008347"
    ]
},
  "bbox": [],
  "geometry": {"coordinates":[-82.1667,35.9667],"type":"Point"}
}