{
  "id": 2574148,
  "type": "Feature",
  "properties": {
    "tgn:hierarchy":[
        "tgn:2574148",
        "tgn:1000001",
        "tgn:7012149",
        "tgn:2000973",
        "tgn:7007520",
        "tgn:7029392"
    ],
    "tgn:id":2574148,
    "tgn:name":"Peggley Lake",
    "tgn:placetype":[
        "aat:300008680"
    ]
},
  "bbox": [],
  "geometry": {"coordinates":[-85.1667,46.1167],"type":"Point"}
}