{
  "id": 2077877,
  "type": "Feature",
  "properties": {
    "tgn:hierarchy":[
        "tgn:2077877",
        "tgn:1000001",
        "tgn:2001577",
        "tgn:7012149",
        "tgn:7007705",
        "tgn:7029392"
    ],
    "tgn:id":2077877,
    "tgn:name":"New England",
    "tgn:placetype":[
        "aat:300008347"
    ]
},
  "bbox": [],
  "geometry": {"coordinates":[-102.8667,46.5333],"type":"Point"}
}