{
  "id": 7297910,
  "type": "Feature",
  "properties": {
    "tgn:hierarchy":[
        "tgn:7297910",
        "tgn:7002758",
        "tgn:7002817",
        "tgn:1000003",
        "tgn:1000095",
        "tgn:7029392"
    ],
    "tgn:id":7297910,
    "tgn:name":"Solecho, Arroyo de",
    "tgn:placetype":[
        "aat:300008699"
    ]
},
  "bbox": [],
  "geometry": {"coordinates":[-4.333333,37.283333],"type":"Point"}
}