{
  "id": 7564857,
  "type": "Feature",
  "properties": {
    "tgn:hierarchy":[
        "tgn:7564857",
        "tgn:1000004",
        "tgn:7000198",
        "tgn:7016722",
        "tgn:7029392"
    ],
    "tgn:id":7564857,
    "tgn:name:en":"Purwa Mansukh",
    "tgn:placetype":[
        "aat:300008347"
    ]
},
  "bbox": [],
  "geometry": {"coordinates":[79.65733,26.912388],"type":"Point"}
}