{
  "id": 2436390,
  "type": "Feature",
  "properties": {
    "tgn:hierarchy":[
        "tgn:2436390",
        "tgn:1000001",
        "tgn:7012149",
        "tgn:2002178",
        "tgn:7007919",
        "tgn:7029392"
    ],
    "tgn:id":2436390,
    "tgn:name":"Kibler Hill",
    "tgn:placetype":[
        "aat:300008798"
    ]
},
  "bbox": [],
  "geometry": {"coordinates":[-78.4333,38.7167],"type":"Point"}
}