<<<<<<< HEAD
{
  "id": 2760785,
  "type": "Feature",
  "properties": {
    "tgn:hierarchy":[
        "tgn:2760785",
        "tgn:1000001",
        "tgn:7012149",
        "tgn:2001452",
        "tgn:7007566",
        "tgn:7029392"
    ],
    "tgn:id":2760785,
    "tgn:name":"West Gum Canyon",
    "tgn:placetype":[
        "aat:300008761"
    ]
},
  "bbox": [],
  "geometry": {"coordinates":[-108.5667,36.95],"type":"Point"}
}
=======
{"geometry":{"type":"Point","coordinates":[-108.566700,36.950000]},"type":"Feature","properties":{"hierarchy":["tgn:2760785","tgn:1000001","tgn:7012149","tgn:2001452","tgn:7007566","tgn:7029392"],"placetype":["aat:300008761"],"id":2760785,"name:xx":"West Gum Canyon"}}
>>>>>>> 03f74aca74312dbeaf24d7e61306dd6a786dc3d0
