{
  "id": 2781583,
  "type": "Feature",
  "properties": {
    "tgn:hierarchy":[
        "tgn:2781583",
        "tgn:1000001",
        "tgn:7012149",
        "tgn:7007524",
        "tgn:7029392"
    ],
    "tgn:id":2781583,
    "tgn:name":"Woodpile Coulee",
    "tgn:placetype":[
        "aat:300008761"
    ]
},
  "bbox": [],
  "geometry": {"coordinates":[-109.45,48.9333],"type":"Point"}
}