{
  "id": 7507060,
  "type": "Feature",
  "properties": {
    "tgn:hierarchy":[
        "tgn:7507060",
        "tgn:1008380",
        "tgn:1000226",
        "tgn:7016827",
        "tgn:1000006",
        "tgn:7029392"
    ],
    "tgn:id":7507060,
    "tgn:name:en":"Rahui",
    "tgn:placetype":[
        "aat:300008795"
    ]
},
  "bbox": [],
  "geometry": {"coordinates":[174.416667,-39.416667],"type":"Point"}
}