{
  "id": 2292304,
  "type": "Feature",
  "properties": {
    "tgn:hierarchy":[
        "tgn:2292304",
        "tgn:1000001",
        "tgn:2002367",
        "tgn:7012149",
        "tgn:7007923",
        "tgn:7029392"
    ],
    "tgn:id":2292304,
    "tgn:name":"Donna Reservoir",
    "tgn:placetype":[
        "aat:300006191"
    ]
},
  "bbox": [],
  "geometry": {"coordinates":[-105.2167,44.95],"type":"Point"}
}