{
  "id": 7370431,
  "type": "Feature",
  "properties": {
    "tgn:hierarchy":[
        "tgn:7370431",
        "tgn:1000001",
        "tgn:1001960",
        "tgn:7005560",
        "tgn:7029392"
    ],
    "tgn:id":7370431,
    "tgn:name":"Rancho Garibaica",
    "tgn:placetype":[
        "aat:300000241"
    ]
},
  "bbox": [],
  "geometry": {"coordinates":[-110.75,29.05],"type":"Point"}
}