{
  "id": 2417193,
  "type": "Feature",
  "properties": {
    "tgn:hierarchy":[
        "tgn:2417193",
        "tgn:1000001",
        "tgn:7012149",
        "tgn:7007240",
        "tgn:7029392"
    ],
    "tgn:id":2417193,
    "tgn:name":"Jacks Branch",
    "tgn:placetype":[
        "aat:300008699"
    ]
},
  "bbox": [],
  "geometry": {"coordinates":[-81.6167,26.9167],"type":"Point"}
}