{
  "id": 1094660,
  "type": "Feature",
  "properties": {
    "tgn:hierarchy":[
        "tgn:1094660",
        "tgn:7001242",
        "tgn:1001778",
        "tgn:1000203",
        "tgn:7029392"
    ],
    "tgn:id":1094660,
    "tgn:name":"Kishanda",
    "tgn:placetype":[
        "aat:300008347"
    ]
},
  "bbox": [],
  "geometry": {"coordinates":[31.5667,-1.6833],"type":"Point"}
}