{
  "id": 2659287,
  "type": "Feature",
  "properties": {
    "tgn:hierarchy":[
        "tgn:2659287",
        "tgn:1000001",
        "tgn:7012149",
        "tgn:1002427",
        "tgn:7007826",
        "tgn:7029392"
    ],
    "tgn:id":2659287,
    "tgn:name":"Shiloh",
    "tgn:placetype":[
        "aat:300008347"
    ]
},
  "bbox": [],
  "geometry": {"coordinates":[-94.85,32.5667],"type":"Point"}
}