{
  "id": 7467416,
  "type": "Feature",
  "properties": {
    "tgn:hierarchy":[
        "tgn:7467416",
        "tgn:1000004",
        "tgn:1000454",
        "tgn:1000141",
        "tgn:7029392"
    ],
    "tgn:id":7467416,
    "tgn:name":"Jianshanzi Bi",
    "tgn:placetype":[
        "aat:300386846"
    ]
},
  "bbox": [],
  "geometry": {"coordinates":[121.80688,25.147567],"type":"Point"}
}