{
  "id": 2452950,
  "type": "Feature",
  "properties": {
    "tgn:hierarchy":[
        "tgn:2452950",
        "tgn:1000001",
        "tgn:7006451",
        "tgn:2000091",
        "tgn:7012149",
        "tgn:7029392"
    ],
    "tgn:id":2452950,
    "tgn:name":"Little California Gulch",
    "tgn:placetype":[
        "aat:300008761"
    ]
},
  "bbox": [],
  "geometry": {"coordinates":[-109.65,32.25],"type":"Point"}
}