{
  "id": 7092287,
  "type": "Feature",
  "properties": {
    "tgn:hierarchy":[
        "tgn:7092287",
        "tgn:1000003",
        "tgn:7000094",
        "tgn:7000084",
        "tgn:7029392"
    ],
    "tgn:id":7092287,
    "tgn:name":"Vietl\u00fcbber Tannen",
    "tgn:placetype":[
        "aat:300008863"
    ]
},
  "bbox": [],
  "geometry": {"coordinates":[12.133333,53.416667],"type":"Point"}
}