{
  "id": 2346739,
  "type": "Feature",
  "properties": {
    "tgn:hierarchy":[
        "tgn:2346739",
        "tgn:1000001",
        "tgn:7012149",
        "tgn:2000476",
        "tgn:7007250",
        "tgn:7029392"
    ],
    "tgn:id":2346739,
    "tgn:name":"Gedney Mountain",
    "tgn:placetype":[
        "aat:300008798"
    ]
},
  "bbox": [],
  "geometry": {"coordinates":[-115.25,46.15],"type":"Point"}
}