{
  "id": 2682052,
  "type": "Feature",
  "properties": {
    "tgn:hierarchy":[
        "tgn:2682052",
        "tgn:1000001",
        "tgn:7013942",
        "tgn:7012149",
        "tgn:7007517",
        "tgn:7029392"
    ],
    "tgn:id":2682052,
    "tgn:name":"South Sugarloaf Mountain",
    "tgn:placetype":[
        "aat:300008798"
    ]
},
  "bbox": [],
  "geometry": {"coordinates":[-72.5833,42.4667],"type":"Point"}
}