{
  "id": 7409975,
  "type": "Feature",
  "properties": {
    "tgn:hierarchy":[
        "tgn:7409975",
        "tgn:1000001",
        "tgn:7005590",
        "tgn:7005560",
        "tgn:7029392"
    ],
    "tgn:id":7409975,
    "tgn:name":"El Sarate",
    "tgn:placetype":[
        "aat:300008347"
    ]
},
  "bbox": [],
  "geometry": {"coordinates":[-102.35,18.866667],"type":"Point"}
}