{
  "id": 2006843,
  "type": "Feature",
  "properties": {
    "tgn:hierarchy":[
        "tgn:2006843",
        "tgn:1000001",
        "tgn:7006451",
        "tgn:7012149",
        "tgn:2000098",
        "tgn:7029392"
    ],
    "tgn:id":2006843,
    "tgn:name":"Grasshopper Junction",
    "tgn:placetype":[
        "aat:300008347",
        "aat:300387210"
    ]
},
  "bbox": [],
  "geometry": {"coordinates":[-114.25,35.3833],"type":"Point"}
}