{
  "id": 7482110,
  "type": "Feature",
  "properties": {
    "tgn:hierarchy":[
        "tgn:7482110",
        "tgn:1000004",
        "tgn:7489179",
        "tgn:1000141",
        "tgn:7029392"
    ],
    "tgn:id":7482110,
    "tgn:name":"Ganzixiang",
    "tgn:placetype":[
        "aat:300008347"
    ]
},
  "bbox": [],
  "geometry": {"coordinates":[121.789722,24.473333],"type":"Point"}
}