<<<<<<< HEAD
{
  "id": 7173012,
  "type": "Feature",
  "properties": {
    "tgn:hierarchy":[
        "tgn:7173012",
        "tgn:1000003",
        "tgn:7003685",
        "tgn:7000084",
        "tgn:7029392"
    ],
    "tgn:id":7173012,
    "tgn:name":"Gro\u00dfer Triemig-Teich",
    "tgn:placetype":[
        "aat:300008680"
    ]
},
  "bbox": [],
  "geometry": {"coordinates":[13.95,51.35],"type":"Point"}
}
=======
{"geometry":{"type":"Point","coordinates":[13.950000,51.350000]},"type":"Feature","properties":{"hierarchy":["tgn:7173012","tgn:1000003","tgn:7003685","tgn:7000084","tgn:7029392"],"placetype":["aat:300008680"],"id":7173012,"name:xx":"Gro\u00dfer Triemig-Teich"}}
>>>>>>> 03f74aca74312dbeaf24d7e61306dd6a786dc3d0
