{
  "id": 7590117,
  "type": "Feature",
  "properties": {
    "tgn:hierarchy":[
        "tgn:7590117",
        "tgn:1000004",
        "tgn:7000198",
        "tgn:7000799",
        "tgn:7029392"
    ],
    "tgn:id":7590117,
    "tgn:name:en":"Chhambar Forest",
    "tgn:placetype":[
        "aat:300008863"
    ]
},
  "bbox": [],
  "geometry": {"coordinates":[74.286111,33.830556],"type":"Point"}
}