{
  "id": 7437448,
  "type": "Feature",
  "properties": {
    "tgn:hierarchy":[
        "tgn:7437448",
        "tgn:7016644",
        "tgn:1000001",
        "tgn:7005560",
        "tgn:7029392"
    ],
    "tgn:id":7437448,
    "tgn:name":"Santiago",
    "tgn:placetype":[
        "aat:300008347"
    ]
},
  "bbox": [],
  "geometry": {"coordinates":[-104.35,19.116667],"type":"Point"}
}