{
  "id": 2365610,
  "type": "Feature",
  "properties": {
    "tgn:hierarchy":[
        "tgn:2365610",
        "tgn:1000001",
        "tgn:7016172",
        "tgn:2000116",
        "tgn:7012149",
        "tgn:7029392"
    ],
    "tgn:id":2365610,
    "tgn:name":"Greers Ferry Nursery Pond",
    "tgn:placetype":[
        "aat:300006191"
    ]
},
  "bbox": [],
  "geometry": {"coordinates":[-92.2167,35.5667],"type":"Point"}
}