{
  "id": 7361925,
  "type": "Feature",
  "properties": {
    "tgn:hierarchy":[
        "tgn:7361925",
        "tgn:7005581",
        "tgn:1000001",
        "tgn:7005560",
        "tgn:7029392"
    ],
    "tgn:id":7361925,
    "tgn:name":"El Cuervo",
    "tgn:placetype":[
        "aat:300008347"
    ]
},
  "bbox": [],
  "geometry": {"coordinates":[-108.266667,30.716667],"type":"Point"}
}