{
  "id": 1095808,
  "type": "Feature",
  "properties": {
    "tgn:hierarchy":[
        "tgn:1095808",
        "tgn:7024179",
        "tgn:7001242",
        "tgn:1000772",
        "tgn:1000208",
        "tgn:7029392"
    ],
    "tgn:id":1095808,
    "tgn:name":"Kampti",
    "tgn:placetype":[
        "aat:300008347"
    ]
},
  "bbox": [],
  "geometry": {"coordinates":[-3.3667,10.1167],"type":"Point"}
}