{
  "id": 2002294,
  "type": "Feature",
  "properties": {
    "tgn:hierarchy":[
        "tgn:2002294",
        "tgn:1000001",
        "tgn:7012149",
        "tgn:7013961",
        "tgn:7029392"
    ],
    "tgn:id":2002294,
    "tgn:name":"Summers",
    "tgn:placetype":[
        "aat:300387145",
        "aat:300000771"
    ]
},
  "bbox": [],
  "geometry": {"coordinates":[-80.8667,37.65],"type":"Point"}
}