{
  "id": 2024311,
  "type": "Feature",
  "properties": {
    "tgn:hierarchy":[
        "tgn:2024311",
        "tgn:1000001",
        "tgn:7012149",
        "tgn:2000348",
        "tgn:7007248",
        "tgn:7029392"
    ],
    "tgn:id":2024311,
    "tgn:name":"Sherwood Forest",
    "tgn:placetype":[
        "aat:300008347"
    ]
},
  "bbox": [],
  "geometry": {"coordinates":[-85.1167,34.25],"type":"Point"}
}