{
  "id": 7570717,
  "type": "Feature",
  "properties": {
    "tgn:hierarchy":[
        "tgn:7570717",
        "tgn:1000004",
        "tgn:7000198",
        "tgn:1001996",
        "tgn:7029392"
    ],
    "tgn:id":7570717,
    "tgn:name:en":"Jalori Galu",
    "tgn:placetype":[
        "aat:300259572"
    ]
},
  "bbox": [],
  "geometry": {"coordinates":[77.367539,31.538309],"type":"Point"}
}