{
  "id": 7013137,
  "type": "Feature",
  "properties": {
    "tgn:hierarchy":[
        "tgn:7013137",
        "tgn:7005685",
        "tgn:1000001",
        "tgn:7013154",
        "tgn:7029392"
    ],
    "tgn:id":7013137,
    "tgn:name":"Waterloo",
    "tgn:placetype":[
        "aat:300008347"
    ]
},
  "bbox": [],
  "geometry": {"coordinates":[-80.5333,43.4667],"type":"Point"}
}