<<<<<<< HEAD
{
  "id": 7350400,
  "type": "Feature",
  "properties": {
    "tgn:hierarchy":[
        "tgn:7350400",
        "tgn:1001853",
        "tgn:1000001",
        "tgn:7005560",
        "tgn:7029392"
    ],
    "tgn:id":7350400,
    "tgn:name":"Bu\u00f1uelos",
    "tgn:placetype":[
        "aat:300008347"
    ]
},
  "bbox": [],
  "geometry": {"coordinates":[-101.183333,25.05],"type":"Point"}
}
=======
{"geometry":{"type":"Point","coordinates":[-101.183333,25.050000]},"type":"Feature","properties":{"hierarchy":["tgn:7350400","tgn:1001853","tgn:1000001","tgn:7005560","tgn:7029392"],"placetype":["aat:300008347"],"id":7350400,"name:xx":"Bu\u00f1uelos"}}
>>>>>>> 03f74aca74312dbeaf24d7e61306dd6a786dc3d0
