<<<<<<< HEAD
{
  "id": 2252043,
  "type": "Feature",
  "properties": {
    "tgn:hierarchy":[
        "tgn:2252043",
        "tgn:1000001",
        "tgn:2001091",
        "tgn:7012149",
        "tgn:7007522",
        "tgn:7029392"
    ],
    "tgn:id":2252043,
    "tgn:name":"Concordia, Lake",
    "tgn:placetype":[
        "aat:300008680"
    ]
},
  "bbox": [],
  "geometry": {"coordinates":[-90.9833,33.9333],"type":"Point"}
}
=======
{"geometry":{"type":"Point","coordinates":[-90.983300,33.933300]},"type":"Feature","properties":{"hierarchy":["tgn:2252043","tgn:1000001","tgn:2001091","tgn:7012149","tgn:7007522","tgn:7029392"],"placetype":["aat:300008680"],"id":2252043,"name:xx":"Concordia, Lake"}}
>>>>>>> 03f74aca74312dbeaf24d7e61306dd6a786dc3d0
