{
  "id": 7176147,
  "type": "Feature",
  "properties": {
    "tgn:hierarchy":[
        "tgn:7176147",
        "tgn:1000003",
        "tgn:7000094",
        "tgn:7000084",
        "tgn:7029392"
    ],
    "tgn:id":7176147,
    "tgn:name":"Gro\u00dfe Moorwiese",
    "tgn:placetype":[
        "aat:300008903"
    ]
},
  "bbox": [],
  "geometry": {"coordinates":[12.183333,54.166667],"type":"Point"}
}