{
  "id": 2475113,
  "type": "Feature",
  "properties": {
    "tgn:hierarchy":[
        "tgn:2475113",
        "tgn:1000001",
        "tgn:7012149",
        "tgn:7018871",
        "tgn:7007920",
        "tgn:7029392"
    ],
    "tgn:id":2475113,
    "tgn:name":"Lowman Beach Park",
    "tgn:placetype":[
        "aat:300008347"
    ]
},
  "bbox": [],
  "geometry": {"coordinates":[-122.3833,47.5333],"type":"Point"}
}