{
  "id": 2445864,
  "type": "Feature",
  "properties": {
    "tgn:hierarchy":[
        "tgn:2445864",
        "tgn:1000001",
        "tgn:1002233",
        "tgn:7012149",
        "tgn:7007710",
        "tgn:7029392"
    ],
    "tgn:id":2445864,
    "tgn:name":"Leslie Run",
    "tgn:placetype":[
        "aat:300008347"
    ]
},
  "bbox": [],
  "geometry": {"coordinates":[-75.7167,40.9833],"type":"Point"}
}