{
  "id": 7468290,
  "type": "Feature",
  "properties": {
    "tgn:hierarchy":[
        "tgn:7468290",
        "tgn:1000004",
        "tgn:7491221",
        "tgn:1000141",
        "tgn:7029392"
    ],
    "tgn:id":7468290,
    "tgn:name":"Jie Qiao",
    "tgn:placetype":[
        "aat:300007836"
    ]
},
  "bbox": [],
  "geometry": {"coordinates":[121.408238,23.214544],"type":"Point"}
}