{
  "id": 7548498,
  "type": "Feature",
  "properties": {
    "tgn:hierarchy":[
        "tgn:7548498",
        "tgn:1000004",
        "tgn:1001869",
        "tgn:7000198",
        "tgn:7029392"
    ],
    "tgn:id":7548498,
    "tgn:name:en":"Deolia",
    "tgn:placetype":[
        "aat:300008347"
    ]
},
  "bbox": [],
  "geometry": {"coordinates":[70.983333,23.016667],"type":"Point"}
}