{
  "id": 7471876,
  "type": "Feature",
  "properties": {
    "tgn:hierarchy":[
        "tgn:7471876",
        "tgn:1000004",
        "tgn:7001009",
        "tgn:1000141",
        "tgn:7029392"
    ],
    "tgn:id":7471876,
    "tgn:name":"Wujiajianan Shan",
    "tgn:placetype":[
        "aat:300008798"
    ]
},
  "bbox": [],
  "geometry": {"coordinates":[121.249722,24.316111],"type":"Point"}
}