<<<<<<< HEAD
{
  "id": 7471876,
  "type": "Feature",
  "properties": {
    "tgn:hierarchy":[
        "tgn:7471876",
        "tgn:1000004",
        "tgn:7001009",
        "tgn:1000141",
        "tgn:7029392"
    ],
    "tgn:id":7471876,
    "tgn:name":"Wujiajianan Shan",
    "tgn:placetype":[
        "aat:300008798"
    ]
},
  "bbox": [],
  "geometry": {"coordinates":[121.249722,24.316111],"type":"Point"}
}
=======
{"geometry":{"type":"Point","coordinates":[121.249722,24.316111]},"type":"Feature","properties":{"hierarchy":["tgn:7471876","tgn:1000004","tgn:7001009","tgn:1000141","tgn:7029392"],"placetype":["aat:300008798"],"id":7471876,"name:xx":"Wujiajianan Shan"}}
>>>>>>> 03f74aca74312dbeaf24d7e61306dd6a786dc3d0
