{
  "id": 2352162,
  "type": "Feature",
  "properties": {
    "tgn:hierarchy":[
        "tgn:2352162",
        "tgn:1000001",
        "tgn:7012149",
        "tgn:2000227",
        "tgn:7007158",
        "tgn:7029392"
    ],
    "tgn:id":2352162,
    "tgn:name":"Glover Spring",
    "tgn:placetype":[
        "aat:300008697"
    ]
},
  "bbox": [],
  "geometry": {"coordinates":[-103.55,37.4833],"type":"Point"}
}