{
  "id": 2449652,
  "type": "Feature",
  "properties": {
    "tgn:hierarchy":[
        "tgn:2449652",
        "tgn:1000001",
        "tgn:7012149",
        "tgn:2001615",
        "tgn:7007706",
        "tgn:7029392"
    ],
    "tgn:id":2449652,
    "tgn:name":"Lincoln Park",
    "tgn:placetype":[
        "aat:300008347"
    ]
},
  "bbox": [],
  "geometry": {"coordinates":[-82.5167,38.4167],"type":"Point"}
}