<<<<<<< HEAD
{
  "id": 7472888,
  "type": "Feature",
  "properties": {
    "tgn:hierarchy":[
        "tgn:7472888",
        "tgn:7488858",
        "tgn:1000004",
        "tgn:1000141",
        "tgn:7029392"
    ],
    "tgn:id":7472888,
    "tgn:name":"Dongfeng Xi",
    "tgn:placetype":[
        "aat:300008699"
    ]
},
  "bbox": [],
  "geometry": {"coordinates":[121.091111,24.09],"type":"Point"}
}
=======
{"geometry":{"type":"Point","coordinates":[121.091111,24.090000]},"type":"Feature","properties":{"hierarchy":["tgn:7472888","tgn:7488858","tgn:1000004","tgn:1000141","tgn:7029392"],"placetype":["aat:300008699"],"id":7472888,"name:xx":"Dongfeng Xi"}}
>>>>>>> 03f74aca74312dbeaf24d7e61306dd6a786dc3d0
