{
  "id": 7436505,
  "type": "Feature",
  "properties": {
    "tgn:hierarchy":[
        "tgn:7436505",
        "tgn:7005578",
        "tgn:1000001",
        "tgn:7005560",
        "tgn:7029392"
    ],
    "tgn:id":7436505,
    "tgn:name":"Soledad",
    "tgn:placetype":[
        "aat:300008347"
    ]
},
  "bbox": [],
  "geometry": {"coordinates":[-91.066667,18.483333],"type":"Point"}
}