{
  "id": 7286604,
  "type": "Feature",
  "properties": {
    "tgn:hierarchy":[
        "tgn:7286604",
        "tgn:1001623",
        "tgn:1000049",
        "tgn:1000002",
        "tgn:7029392"
    ],
    "tgn:id":7286604,
    "tgn:name":"Guitarra, Lago",
    "tgn:placetype":[
        "aat:300008680"
    ]
},
  "bbox": [],
  "geometry": {"coordinates":[-72.433333,-48.066667],"type":"Point"}
}