{
  "id": 2672302,
  "type": "Feature",
  "properties": {
    "tgn:hierarchy":[
        "tgn:2672302",
        "tgn:1000001",
        "tgn:7012149",
        "tgn:7007158",
        "tgn:2000243",
        "tgn:7029392"
    ],
    "tgn:id":2672302,
    "tgn:name":"Smizer Gulch",
    "tgn:placetype":[
        "aat:300008761"
    ]
},
  "bbox": [],
  "geometry": {"coordinates":[-108.15,40.1667],"type":"Point"}
}