{
  "id": 7262931,
  "type": "Feature",
  "properties": {
    "tgn:hierarchy":[
        "tgn:7262931",
        "tgn:1000003",
        "tgn:7006951",
        "tgn:7016845",
        "tgn:7029392"
    ],
    "tgn:id":7262931,
    "tgn:name:nl":"Damlanderpolder",
    "tgn:placetype":[
        "aat:300006163"
    ]
},
  "bbox": [],
  "geometry": {"coordinates":[4.683333,52.666667],"type":"Point"}
}