{
  "id": 2167317,
  "type": "Feature",
  "properties": {
    "tgn:hierarchy":[
        "tgn:2167317",
        "tgn:1000001",
        "tgn:7012149",
        "tgn:2000486",
        "tgn:7007250",
        "tgn:7029392"
    ],
    "tgn:id":2167317,
    "tgn:name":"Big Cougar Creek",
    "tgn:placetype":[
        "aat:300008706"
    ]
},
  "bbox": [],
  "geometry": {"coordinates":[-116.85,45.9833],"type":"Point"}
}