{
  "id": 2199942,
  "type": "Feature",
  "properties": {
    "tgn:hierarchy":[
        "tgn:2199942",
        "tgn:1000001",
        "tgn:7012149",
        "tgn:1002426",
        "tgn:7007255",
        "tgn:7029392"
    ],
    "tgn:id":2199942,
    "tgn:name":"Brushy Branch",
    "tgn:placetype":[
        "aat:300008699"
    ]
},
  "bbox": [],
  "geometry": {"coordinates":[-82.9833,38.55],"type":"Point"}
}