{
  "id": 2492451,
  "type": "Feature",
  "properties": {
    "tgn:hierarchy":[
        "tgn:2492451",
        "tgn:1000001",
        "tgn:7012149",
        "tgn:7007157",
        "tgn:2000187",
        "tgn:7029392"
    ],
    "tgn:id":2492451,
    "tgn:name":"Marian Creek",
    "tgn:placetype":[
        "aat:300008706"
    ]
},
  "bbox": [],
  "geometry": {"coordinates":[-121.35,40.2833],"type":"Point"}
}