{
  "id": 1012391,
  "type": "Feature",
  "properties": {
    "tgn:hierarchy":[
        "tgn:1012391",
        "tgn:7018312",
        "tgn:1006440",
        "tgn:1000001",
        "tgn:7004545",
        "tgn:7029392"
    ],
    "tgn:id":1012391,
    "tgn:name":"Rivi\u00e8re \u00e0 Goyaves, Pointe de la",
    "tgn:placetype":[
        "aat:300386846"
    ]
},
  "bbox": [],
  "geometry": {"coordinates":[-61.5833,16.1833],"type":"Point"}
}