<<<<<<< HEAD
{
  "id": 2403627,
  "type": "Feature",
  "properties": {
    "tgn:hierarchy":[
        "tgn:2403627",
        "tgn:1000001",
        "tgn:2002106",
        "tgn:7012149",
        "tgn:7007827",
        "tgn:7029392"
    ],
    "tgn:id":2403627,
    "tgn:name":"Howard Estates",
    "tgn:placetype":[
        "aat:300008347"
    ]
},
  "bbox": [],
  "geometry": {"coordinates":[-111.85,40.8833],"type":"Point"}
}
=======
{"geometry":{"type":"Point","coordinates":[-111.850000,40.883300]},"type":"Feature","properties":{"hierarchy":["tgn:2403627","tgn:1000001","tgn:2002106","tgn:7012149","tgn:7007827","tgn:7029392"],"placetype":["aat:300008347"],"id":2403627,"name:xx":"Howard Estates"}}
>>>>>>> 03f74aca74312dbeaf24d7e61306dd6a786dc3d0
