{
  "id": 2190964,
  "type": "Feature",
  "properties": {
    "tgn:hierarchy":[
        "tgn:2190964",
        "tgn:7014651",
        "tgn:1000001",
        "tgn:7012149",
        "tgn:7007516",
        "tgn:7029392"
    ],
    "tgn:id":2190964,
    "tgn:name":"Boyd Pond",
    "tgn:placetype":[
        "aat:300008680"
    ]
},
  "bbox": [],
  "geometry": {"coordinates":[-76.45,39.1333],"type":"Point"}
}