<<<<<<< HEAD
{
  "id": 2256552,
  "type": "Feature",
  "properties": {
    "tgn:hierarchy":[
        "tgn:2256552",
        "tgn:1000001",
        "tgn:7012149",
        "tgn:1002688",
        "tgn:7007568",
        "tgn:7029392"
    ],
    "tgn:id":2256552,
    "tgn:name":"Corbin Hill",
    "tgn:placetype":[
        "aat:300008798"
    ]
},
  "bbox": [],
  "geometry": {"coordinates":[-74.4,42.7833],"type":"Point"}
}
=======
{"geometry":{"type":"Point","coordinates":[-74.400000,42.783300]},"type":"Feature","properties":{"hierarchy":["tgn:2256552","tgn:1000001","tgn:7012149","tgn:1002688","tgn:7007568","tgn:7029392"],"placetype":["aat:300008798"],"id":2256552,"name:xx":"Corbin Hill"}}
>>>>>>> 03f74aca74312dbeaf24d7e61306dd6a786dc3d0
