{
  "id": 2643230,
  "type": "Feature",
  "properties": {
    "tgn:hierarchy":[
        "tgn:2643230",
        "tgn:1000001",
        "tgn:7012149",
        "tgn:2000555",
        "tgn:7007252",
        "tgn:7029392"
    ],
    "tgn:id":2643230,
    "tgn:name":"Sandy Creek",
    "tgn:placetype":[
        "aat:300008706"
    ]
},
  "bbox": [],
  "geometry": {"coordinates":[-86.9667,38.0667],"type":"Point"}
}