{
  "id": 2586610,
  "type": "Feature",
  "properties": {
    "tgn:hierarchy":[
        "tgn:2586610",
        "tgn:1000001",
        "tgn:7013686",
        "tgn:7012149",
        "tgn:7007517",
        "tgn:7029392"
    ],
    "tgn:id":2586610,
    "tgn:name":"Pittsinger Brook",
    "tgn:placetype":[
        "aat:300008699"
    ]
},
  "bbox": [],
  "geometry": {"coordinates":[-72.8167,42.3167],"type":"Point"}
}