{
  "id": 7402268,
  "type": "Feature",
  "properties": {
    "tgn:hierarchy":[
        "tgn:7402268",
        "tgn:1000001",
        "tgn:7005599",
        "tgn:7005560",
        "tgn:7029392"
    ],
    "tgn:id":7402268,
    "tgn:name":"Rancho Nuevo",
    "tgn:placetype":[
        "aat:300008347"
    ]
},
  "bbox": [],
  "geometry": {"coordinates":[-96.791667,19.525],"type":"Point"}
}