{
  "id": 2642434,
  "type": "Feature",
  "properties": {
    "tgn:hierarchy":[
        "tgn:2642434",
        "tgn:1000001",
        "tgn:2001336",
        "tgn:7012149",
        "tgn:7007525",
        "tgn:7029392"
    ],
    "tgn:id":2642434,
    "tgn:name":"Sand Valley",
    "tgn:placetype":[
        "aat:300008761"
    ]
},
  "bbox": [],
  "geometry": {"coordinates":[-100.0167,41.2333],"type":"Point"}
}