{
  "id": 2267028,
  "type": "Feature",
  "properties": {
    "tgn:hierarchy":[
        "tgn:2267028",
        "tgn:1000001",
        "tgn:7012149",
        "tgn:7007158",
        "tgn:7029392"
    ],
    "tgn:id":2267028,
    "tgn:name":"Crestone Peaks",
    "tgn:placetype":[
        "aat:300008798"
    ]
},
  "bbox": [],
  "geometry": {"coordinates":[-105.5667,37.95],"type":"Point"}
}