<<<<<<< HEAD
{
  "id": 7366307,
  "type": "Feature",
  "properties": {
    "tgn:hierarchy":[
        "tgn:7366307",
        "tgn:1000001",
        "tgn:7005591",
        "tgn:7005560",
        "tgn:7029392"
    ],
    "tgn:id":7366307,
    "tgn:name":"Escondida",
    "tgn:placetype":[
        "aat:300007783"
    ]
},
  "bbox": [],
  "geometry": {"coordinates":[-96.983333,17.366667],"type":"Point"}
}
=======
{"geometry":{"type":"Point","coordinates":[-96.983333,17.366667]},"type":"Feature","properties":{"hierarchy":["tgn:7366307","tgn:1000001","tgn:7005591","tgn:7005560","tgn:7029392"],"placetype":["aat:300007783"],"id":7366307,"name:xx":"Escondida"}}
>>>>>>> 03f74aca74312dbeaf24d7e61306dd6a786dc3d0
