{
  "id": 2196376,
  "type": "Feature",
  "properties": {
    "tgn:hierarchy":[
        "tgn:2196376",
        "tgn:1000001",
        "tgn:2002109",
        "tgn:7012149",
        "tgn:7007827",
        "tgn:7029392"
    ],
    "tgn:id":2196376,
    "tgn:name":"Bromide Basin",
    "tgn:placetype":[
        "aat:300386845"
    ]
},
  "bbox": [],
  "geometry": {"coordinates":[-110.7833,38.05],"type":"Point"}
}