<<<<<<< HEAD
{
  "id": 2159270,
  "type": "Feature",
  "properties": {
    "tgn:hierarchy":[
        "tgn:2159270",
        "tgn:1000001",
        "tgn:7012149",
        "tgn:2001162",
        "tgn:7007522",
        "tgn:7029392"
    ],
    "tgn:id":2159270,
    "tgn:name":"Bee Branch",
    "tgn:placetype":[
        "aat:300008699"
    ]
},
  "bbox": [],
  "geometry": {"coordinates":[-88.45,31.5167],"type":"Point"}
}
=======
{"geometry":{"type":"Point","coordinates":[-88.450000,31.516700]},"type":"Feature","properties":{"hierarchy":["tgn:2159270","tgn:1000001","tgn:7012149","tgn:2001162","tgn:7007522","tgn:7029392"],"placetype":["aat:300008699"],"id":2159270,"name:xx":"Bee Branch"}}
>>>>>>> 03f74aca74312dbeaf24d7e61306dd6a786dc3d0
