{
  "id": 2634294,
  "type": "Feature",
  "properties": {
    "tgn:hierarchy":[
        "tgn:2634294",
        "tgn:1000001",
        "tgn:2001702",
        "tgn:7012149",
        "tgn:7007708",
        "tgn:7029392"
    ],
    "tgn:id":2634294,
    "tgn:name":"Russell Point",
    "tgn:placetype":[
        "aat:300008850"
    ]
},
  "bbox": [],
  "geometry": {"coordinates":[-124.2167,43.4333],"type":"Point"}
}