{
  "id": 7291826,
  "type": "Feature",
  "properties": {
    "tgn:hierarchy":[
        "tgn:7291826",
        "tgn:7016598",
        "tgn:1000049",
        "tgn:1000002",
        "tgn:7029392"
    ],
    "tgn:id":7291826,
    "tgn:name":"Florida, Quebrada",
    "tgn:placetype":[
        "aat:300266554",
        "aat:300008699"
    ]
},
  "bbox": [],
  "geometry": {"coordinates":[-70.083333,-25.566667],"type":"Point"}
}