{
  "id": 7559003,
  "type": "Feature",
  "properties": {
    "tgn:hierarchy":[
        "tgn:7559003",
        "tgn:1000004",
        "tgn:1001832",
        "tgn:7000198",
        "tgn:7029392"
    ],
    "tgn:id":7559003,
    "tgn:name:en":"Rih\u0101b\u0101ri",
    "tgn:placetype":[
        "aat:300008347"
    ]
},
  "bbox": [],
  "geometry": {"coordinates":[91.16903,26.601945],"type":"Point"}
}