{
  "id": 2548361,
  "type": "Feature",
  "properties": {
    "tgn:hierarchy":[
        "tgn:2548361",
        "tgn:1000001",
        "tgn:7012149",
        "tgn:2000205",
        "tgn:7007158",
        "tgn:7029392"
    ],
    "tgn:id":2548361,
    "tgn:name":"North Lake Creek",
    "tgn:placetype":[
        "aat:300008706"
    ]
},
  "bbox": [],
  "geometry": {"coordinates":[-105.7333,38.2167],"type":"Point"}
}