{
  "id": 2578780,
  "type": "Feature",
  "properties": {
    "tgn:hierarchy":[
        "tgn:2578780",
        "tgn:7006450",
        "tgn:1000001",
        "tgn:7012149",
        "tgn:2000079",
        "tgn:7029392"
    ],
    "tgn:id":2578780,
    "tgn:name":"Phillips Gulch",
    "tgn:placetype":[
        "aat:300008761"
    ]
},
  "bbox": [],
  "geometry": {"coordinates":[-165.2667,64.55],"type":"Point"}
}