{
  "id": 2415471,
  "type": "Feature",
  "properties": {
    "tgn:hierarchy":[
        "tgn:2415471",
        "tgn:1000001",
        "tgn:2001734",
        "tgn:7012149",
        "tgn:7007712",
        "tgn:7029392"
    ],
    "tgn:id":2415471,
    "tgn:name":"Island of Palms",
    "tgn:placetype":[
        "aat:300008347"
    ]
},
  "bbox": [],
  "geometry": {"coordinates":[-79.7833,32.7833],"type":"Point"}
}