{
  "id": 1078838,
  "type": "Feature",
  "properties": {
    "tgn:hierarchy":[
        "tgn:1078838",
        "tgn:1000004",
        "tgn:1001547",
        "tgn:1000116",
        "tgn:7029392"
    ],
    "tgn:id":1078838,
    "tgn:name":"Ujunglamuru",
    "tgn:placetype":[
        "aat:300008347"
    ]
},
  "bbox": [],
  "geometry": {"coordinates":[119.9667,-4.6667],"type":"Point"}
}