{
  "id": 2240786,
  "type": "Feature",
  "properties": {
    "tgn:hierarchy":[
        "tgn:2240786",
        "tgn:7019618",
        "tgn:1000001",
        "tgn:7012149",
        "tgn:7007564",
        "tgn:7029392"
    ],
    "tgn:id":2240786,
    "tgn:name":"Clapp Pond",
    "tgn:placetype":[
        "aat:300008680"
    ]
},
  "bbox": [],
  "geometry": {"coordinates":[-72.1667,42.9167],"type":"Point"}
}