{
  "id": 2607581,
  "type": "Feature",
  "properties": {
    "tgn:hierarchy":[
        "tgn:2607581",
        "tgn:1000001",
        "tgn:7012149",
        "tgn:2001451",
        "tgn:7007566",
        "tgn:7029392"
    ],
    "tgn:id":2607581,
    "tgn:name":"Raphael Gallegos, Ca\u00f1on del",
    "tgn:placetype":[
        "aat:300008761"
    ]
},
  "bbox": [],
  "geometry": {"coordinates":[-106.6667,35.7333],"type":"Point"}
}