{
  "id": 1123343,
  "type": "Feature",
  "properties": {
    "tgn:hierarchy":[
        "tgn:1123343",
        "tgn:7002445",
        "tgn:1000003",
        "tgn:7008185",
        "tgn:7008591",
        "tgn:7029392"
    ],
    "tgn:id":1123343,
    "tgn:name:en":"Deben",
    "tgn:placetype":[
        "aat:300008707",
        "aat:300008699"
    ]
},
  "bbox": [],
  "geometry": {"coordinates":[1.366667,52.016667],"type":"Point"}
}