{
  "id": 1094743,
  "type": "Feature",
  "properties": {
    "tgn:hierarchy":[
        "tgn:1094743",
        "tgn:7001242",
        "tgn:1001756",
        "tgn:1000203",
        "tgn:7029392"
    ],
    "tgn:id":1094743,
    "tgn:name":"Mkata",
    "tgn:placetype":[
        "aat:300008347"
    ]
},
  "bbox": [],
  "geometry": {"coordinates":[38.2833,-5.7833],"type":"Point"}
}