{
  "id": 7513848,
  "type": "Feature",
  "properties": {
    "tgn:hierarchy":[
        "tgn:7513848",
        "tgn:1009227",
        "tgn:7001866",
        "tgn:1000226",
        "tgn:1000006",
        "tgn:7029392"
    ],
    "tgn:id":7513848,
    "tgn:name:en":"Fish Lake",
    "tgn:placetype":[
        "aat:300008680"
    ]
},
  "bbox": [],
  "geometry": {"coordinates":[172.933333,-42.116667],"type":"Point"}
}