{
  "id": 1060530,
  "type": "Feature",
  "properties": {
    "tgn:hierarchy":[
        "tgn:1060530",
        "tgn:7011495",
        "tgn:1000004",
        "tgn:7002435",
        "tgn:7029392"
    ],
    "tgn:id":1060530,
    "tgn:name":"Turochak",
    "tgn:placetype":[
        "aat:300008347"
    ]
},
  "bbox": [],
  "geometry": {"coordinates":[87.1667,52.25],"type":"Point"}
}