{
  "id": 2579094,
  "type": "Feature",
  "properties": {
    "tgn:hierarchy":[
        "tgn:2579094",
        "tgn:1000001",
        "tgn:7006451",
        "tgn:7012149",
        "tgn:2000099",
        "tgn:7029392"
    ],
    "tgn:id":2579094,
    "tgn:name":"Phoenix Park Wash",
    "tgn:placetype":[
        "aat:300008699"
    ]
},
  "bbox": [],
  "geometry": {"coordinates":[-110.5333,34.2833],"type":"Point"}
}