{
  "id": 2651297,
  "type": "Feature",
  "properties": {
    "tgn:hierarchy":[
        "tgn:2651297",
        "tgn:1000001",
        "tgn:7012149",
        "tgn:2001303",
        "tgn:7007524",
        "tgn:7029392"
    ],
    "tgn:id":2651297,
    "tgn:name":"Section Line Spring",
    "tgn:placetype":[
        "aat:300008697"
    ]
},
  "bbox": [],
  "geometry": {"coordinates":[-106.4167,45.3833],"type":"Point"}
}