{
  "id": 2283468,
  "type": "Feature",
  "properties": {
    "tgn:hierarchy":[
        "tgn:2283468",
        "tgn:1000001",
        "tgn:1002270",
        "tgn:7012149",
        "tgn:7007708",
        "tgn:7029392"
    ],
    "tgn:id":2283468,
    "tgn:name":"Delph Creek",
    "tgn:placetype":[
        "aat:300008706"
    ]
},
  "bbox": [],
  "geometry": {"coordinates":[-122.1333,45.2667],"type":"Point"}
}