{
  "id": 2405024,
  "type": "Feature",
  "properties": {
    "tgn:hierarchy":[
        "tgn:2405024",
        "tgn:7013349",
        "tgn:1000001",
        "tgn:7012149",
        "tgn:7007708",
        "tgn:7029392"
    ],
    "tgn:id":2405024,
    "tgn:name":"Hudson Creek",
    "tgn:placetype":[
        "aat:300008706"
    ]
},
  "bbox": [],
  "geometry": {"coordinates":[-117.3333,45.0667],"type":"Point"}
}