{
  "id": 2250866,
  "type": "Feature",
  "properties": {
    "tgn:hierarchy":[
        "tgn:2250866",
        "tgn:1000001",
        "tgn:7012149",
        "tgn:2002371",
        "tgn:7007923",
        "tgn:7029392"
    ],
    "tgn:id":2250866,
    "tgn:name":"Columbia Geneva Mines",
    "tgn:placetype":[
        "aat:300000390"
    ]
},
  "bbox": [],
  "geometry": {"coordinates":[-108.7333,42.5333],"type":"Point"}
}