{
  "id": 1021865,
  "type": "Feature",
  "properties": {
    "tgn:hierarchy":[
        "tgn:1021865",
        "tgn:1001834",
        "tgn:1000047",
        "tgn:7002455",
        "tgn:1000002",
        "tgn:7029392"
    ],
    "tgn:id":1021865,
    "tgn:name":"Jeremoabo",
    "tgn:placetype":[
        "aat:300008347"
    ]
},
  "bbox": [],
  "geometry": {"coordinates":[-38.3833,-10.0667],"type":"Point"}
}