{
  "id": 1070787,
  "type": "Feature",
  "properties": {
    "tgn:hierarchy":[
        "tgn:1070787",
        "tgn:1000004",
        "tgn:7001838",
        "tgn:1000111",
        "tgn:7029392"
    ],
    "tgn:id":1070787,
    "tgn:name":"Ulan Balgas",
    "tgn:placetype":[
        "aat:300008347"
    ]
},
  "bbox": [],
  "geometry": {"coordinates":[107.9833,39.0833],"type":"Point"}
}