{
  "id": 2078692,
  "type": "Feature",
  "properties": {
    "tgn:hierarchy":[
        "tgn:2078692",
        "tgn:1000001",
        "tgn:7012149",
        "tgn:2001612",
        "tgn:7007706",
        "tgn:7029392"
    ],
    "tgn:id":2078692,
    "tgn:name":"Cadmus",
    "tgn:placetype":[
        "aat:300008347"
    ]
},
  "bbox": [],
  "geometry": {"coordinates":[-82.4333,38.7667],"type":"Point"}
}