{
  "id": 2718597,
  "type": "Feature",
  "properties": {
    "tgn:hierarchy":[
        "tgn:2718597",
        "tgn:1000001",
        "tgn:7012149",
        "tgn:7015666",
        "tgn:7007825",
        "tgn:7029392"
    ],
    "tgn:id":2718597,
    "tgn:name":"Thompson Ridge",
    "tgn:placetype":[
        "aat:300266640"
    ]
},
  "bbox": [],
  "geometry": {"coordinates":[-87.2333,35.7333],"type":"Point"}
}