<<<<<<< HEAD
{
  "id": 2154591,
  "type": "Feature",
  "properties": {
    "tgn:hierarchy":[
        "tgn:2154591",
        "tgn:7002659",
        "tgn:1000001",
        "tgn:7012149",
        "tgn:2000035",
        "tgn:7029392"
    ],
    "tgn:id":2154591,
    "tgn:name":"Bear Den Point",
    "tgn:placetype":[
        "aat:300008850"
    ]
},
  "bbox": [],
  "geometry": {"coordinates":[-86.05,34.9667],"type":"Point"}
}
=======
{"geometry":{"type":"Point","coordinates":[-86.050000,34.966700]},"type":"Feature","properties":{"hierarchy":["tgn:2154591","tgn:7002659","tgn:1000001","tgn:7012149","tgn:2000035","tgn:7029392"],"placetype":["aat:300008850"],"id":2154591,"name:xx":"Bear Den Point"}}
>>>>>>> 03f74aca74312dbeaf24d7e61306dd6a786dc3d0
