{
  "id": 1007062,
  "type": "Feature",
  "properties": {
    "tgn:hierarchy":[
        "tgn:1007062",
        "tgn:7000528",
        "tgn:7000529",
        "tgn:1000006",
        "tgn:7029392"
    ],
    "tgn:id":1007062,
    "tgn:name":"Eua Iki",
    "tgn:placetype":[
        "aat:300008791"
    ]
},
  "bbox": [],
  "geometry": {"coordinates":[-174.9833,-21.1167],"type":"Point"}
}