<<<<<<< HEAD
{
  "id": 7027852,
  "type": "Feature",
  "properties": {
    "tgn:hierarchy":[
        "tgn:7027852",
        "tgn:7002445",
        "tgn:1000003",
        "tgn:7008157",
        "tgn:7008591",
        "tgn:7029392"
    ],
    "tgn:id":7027852,
    "tgn:name:en":"North Elkington",
    "tgn:placetype":[
        "aat:300008347",
        "aat:300008369"
    ]
},
  "bbox": [],
  "geometry": {"coordinates":[-0.066667,53.4],"type":"Point"}
}
=======
{"geometry":{"type":"Point","coordinates":[-0.066667,53.400000]},"type":"Feature","properties":{"hierarchy":["tgn:7027852","tgn:7002445","tgn:1000003","tgn:7008157","tgn:7008591","tgn:7029392"],"placetype":["aat:300008347","aat:300008369"],"name:en":"North Elkington","id":7027852}}
>>>>>>> 03f74aca74312dbeaf24d7e61306dd6a786dc3d0
