{
  "id": 7077330,
  "type": "Feature",
  "properties": {
    "tgn:hierarchy":[
        "tgn:7077330",
        "tgn:7003692",
        "tgn:1000003",
        "tgn:7000084",
        "tgn:7029392"
    ],
    "tgn:id":7077330,
    "tgn:name":"Alb-Donau-Kreis",
    "tgn:placetype":[
        "aat:300387198"
    ]
},
  "bbox": [],
  "geometry": {"coordinates":[9.8375,48.417778],"type":"Point"}
}