{
  "id": 7548800,
  "type": "Feature",
  "properties": {
    "tgn:hierarchy":[
        "tgn:7548800",
        "tgn:1000004",
        "tgn:7000198",
        "tgn:1001894",
        "tgn:7029392"
    ],
    "tgn:id":7548800,
    "tgn:name:en":"Dundi",
    "tgn:placetype":[
        "aat:300007783"
    ]
},
  "bbox": [],
  "geometry": {"coordinates":[80.216862,23.557076],"type":"Point"}
}