{
  "id": 1017712,
  "type": "Feature",
  "properties": {
    "tgn:hierarchy":[
        "tgn:1017712",
        "tgn:1000001",
        "tgn:7005594",
        "tgn:7005560",
        "tgn:7029392"
    ],
    "tgn:id":1017712,
    "tgn:name":"La Mutua",
    "tgn:placetype":[
        "aat:300008347"
    ]
},
  "bbox": [],
  "geometry": {"coordinates":[-99.316667,22.466667],"type":"Point"}
}