{
  "id": 7096117,
  "type": "Feature",
  "properties": {
    "tgn:hierarchy":[
        "tgn:7096117",
        "tgn:7000096",
        "tgn:1000003",
        "tgn:7000084",
        "tgn:7029392"
    ],
    "tgn:id":7096117,
    "tgn:name":"Sch\u00f6nau",
    "tgn:placetype":[
        "aat:300008347"
    ]
},
  "bbox": [],
  "geometry": {"coordinates":[13.65,51.416667],"type":"Point"}
}