<<<<<<< HEAD
{
  "id": 2769247,
  "type": "Feature",
  "properties": {
    "tgn:hierarchy":[
        "tgn:2769247",
        "tgn:1000001",
        "tgn:2001638",
        "tgn:7012149",
        "tgn:7007707",
        "tgn:7029392"
    ],
    "tgn:id":2769247,
    "tgn:name":"Wichita Mountains National Wildlife Refuge Headquarters",
    "tgn:placetype":[
        "aat:300055621"
    ]
},
  "bbox": [],
  "geometry": {"coordinates":[-98.7,34.7167],"type":"Point"}
}
=======
{"geometry":{"type":"Point","coordinates":[-98.700000,34.716700]},"type":"Feature","properties":{"hierarchy":["tgn:2769247","tgn:1000001","tgn:2001638","tgn:7012149","tgn:7007707","tgn:7029392"],"placetype":["aat:300055621"],"id":2769247,"name:xx":"Wichita Mountains National Wildlife Refuge Headquarters"}}
>>>>>>> 03f74aca74312dbeaf24d7e61306dd6a786dc3d0
