<<<<<<< HEAD
{
  "id": 7358764,
  "type": "Feature",
  "properties": {
    "tgn:hierarchy":[
        "tgn:7358764",
        "tgn:7005586",
        "tgn:1000001",
        "tgn:7005560",
        "tgn:7029392"
    ],
    "tgn:id":7358764,
    "tgn:name":"El Aguacate",
    "tgn:placetype":[
        "aat:300266554",
        "aat:300008699"
    ]
},
  "bbox": [],
  "geometry": {"coordinates":[-102.7,20.766667],"type":"Point"}
}
=======
{"geometry":{"type":"Point","coordinates":[-102.700000,20.766667]},"type":"Feature","properties":{"hierarchy":["tgn:7358764","tgn:7005586","tgn:1000001","tgn:7005560","tgn:7029392"],"placetype":["aat:300266554","aat:300008699"],"id":7358764,"name:xx":"El Aguacate"}}
>>>>>>> 03f74aca74312dbeaf24d7e61306dd6a786dc3d0
