{
  "id": 7218097,
  "type": "Feature",
  "properties": {
    "tgn:hierarchy":[
        "tgn:7218097",
        "tgn:7002690",
        "tgn:7012056",
        "tgn:1000003",
        "tgn:1000074",
        "tgn:7029392"
    ],
    "tgn:id":7218097,
    "tgn:name":"Tr\u00e9kala, \u00c1kra",
    "tgn:placetype":[
        "aat:300386846"
    ]
},
  "bbox": [],
  "geometry": {"coordinates":[24.966667,34.933333],"type":"Point"}
}