<<<<<<< HEAD
{
  "id": 2401488,
  "type": "Feature",
  "properties": {
    "tgn:hierarchy":[
        "tgn:2401488",
        "tgn:1000001",
        "tgn:7006451",
        "tgn:2000091",
        "tgn:7012149",
        "tgn:7029392"
    ],
    "tgn:id":2401488,
    "tgn:name":"Horseshoe Canyon",
    "tgn:placetype":[
        "aat:300008761"
    ]
},
  "bbox": [],
  "geometry": {"coordinates":[-109.2,31.8167],"type":"Point"}
}
=======
{"geometry":{"type":"Point","coordinates":[-109.200000,31.816700]},"type":"Feature","properties":{"hierarchy":["tgn:2401488","tgn:1000001","tgn:7006451","tgn:2000091","tgn:7012149","tgn:7029392"],"placetype":["aat:300008761"],"id":2401488,"name:xx":"Horseshoe Canyon"}}
>>>>>>> 03f74aca74312dbeaf24d7e61306dd6a786dc3d0
