{
  "id": 7198524,
  "type": "Feature",
  "properties": {
    "tgn:hierarchy":[
        "tgn:7198524",
        "tgn:1000003",
        "tgn:7003682",
        "tgn:7000084",
        "tgn:7029392"
    ],
    "tgn:id":7198524,
    "tgn:name":"Dromigt",
    "tgn:placetype":[
        "aat:300000206"
    ]
},
  "bbox": [],
  "geometry": {"coordinates":[6.25,50.15],"type":"Point"}
}