<<<<<<< HEAD
{
  "id": 7172541,
  "type": "Feature",
  "properties": {
    "tgn:hierarchy":[
        "tgn:7172541",
        "tgn:1000003",
        "tgn:7003689",
        "tgn:7000084",
        "tgn:7029392"
    ],
    "tgn:id":7172541,
    "tgn:name":"Herrenbreitungen",
    "tgn:placetype":[
        "aat:300008347"
    ]
},
  "bbox": [],
  "geometry": {"coordinates":[10.333333,50.75],"type":"Point"}
}
=======
{"geometry":{"type":"Point","coordinates":[10.333333,50.750000]},"type":"Feature","properties":{"hierarchy":["tgn:7172541","tgn:1000003","tgn:7003689","tgn:7000084","tgn:7029392"],"placetype":["aat:300008347"],"id":7172541,"name:xx":"Herrenbreitungen"}}
>>>>>>> 03f74aca74312dbeaf24d7e61306dd6a786dc3d0
