{
  "id": 2586669,
  "type": "Feature",
  "properties": {
    "tgn:hierarchy":[
        "tgn:2586669",
        "tgn:1000001",
        "tgn:7012149",
        "tgn:2002119",
        "tgn:7007827",
        "tgn:7029392"
    ],
    "tgn:id":2586669,
    "tgn:name":"Piute Spring",
    "tgn:placetype":[
        "aat:300008697"
    ]
},
  "bbox": [],
  "geometry": {"coordinates":[-109.05,37.8833],"type":"Point"}
}