{
  "id": 2634255,
  "type": "Feature",
  "properties": {
    "tgn:hierarchy":[
        "tgn:2634255",
        "tgn:7002659",
        "tgn:1000001",
        "tgn:7012149",
        "tgn:2000062",
        "tgn:7029392"
    ],
    "tgn:id":2634255,
    "tgn:name":"Russell Lee Lake",
    "tgn:placetype":[
        "aat:300006191"
    ]
},
  "bbox": [],
  "geometry": {"coordinates":[-87.6333,33.15],"type":"Point"}
}