{
  "id": 2511476,
  "type": "Feature",
  "properties": {
    "tgn:hierarchy":[
        "tgn:2511476",
        "tgn:2001726",
        "tgn:1000001",
        "tgn:7012149",
        "tgn:7007712",
        "tgn:7029392"
    ],
    "tgn:id":2511476,
    "tgn:name":"Mile Branch",
    "tgn:placetype":[
        "aat:300008699"
    ]
},
  "bbox": [],
  "geometry": {"coordinates":[-81.6667,33.7167],"type":"Point"}
}