<<<<<<< HEAD
{
  "id": 2332883,
  "type": "Feature",
  "properties": {
    "tgn:hierarchy":[
        "tgn:2332883",
        "tgn:2002140",
        "tgn:1000001",
        "tgn:7012149",
        "tgn:7007919",
        "tgn:7029392"
    ],
    "tgn:id":2332883,
    "tgn:name":"Floyds Mountain",
    "tgn:placetype":[
        "aat:300008798"
    ]
},
  "bbox": [],
  "geometry": {"coordinates":[-79.1833,37.7333],"type":"Point"}
}
=======
{"geometry":{"type":"Point","coordinates":[-79.183300,37.733300]},"type":"Feature","properties":{"hierarchy":["tgn:2332883","tgn:2002140","tgn:1000001","tgn:7012149","tgn:7007919","tgn:7029392"],"placetype":["aat:300008798"],"id":2332883,"name:xx":"Floyds Mountain"}}
>>>>>>> 03f74aca74312dbeaf24d7e61306dd6a786dc3d0
