{
  "id": 2010604,
  "type": "Feature",
  "properties": {
    "tgn:hierarchy":[
        "tgn:2010604",
        "tgn:1000001",
        "tgn:7012149",
        "tgn:2000183",
        "tgn:7007157",
        "tgn:7029392"
    ],
    "tgn:id":2010604,
    "tgn:name":"Cartago",
    "tgn:placetype":[
        "aat:300008347"
    ]
},
  "bbox": [],
  "geometry": {"coordinates":[-118.0167,36.3167],"type":"Point"}
}