{
  "id": 2126104,
  "type": "Feature",
  "properties": {
    "tgn:hierarchy":[
        "tgn:2126104",
        "tgn:1000001",
        "tgn:2001476",
        "tgn:7012149",
        "tgn:7007709",
        "tgn:7029392"
    ],
    "tgn:id":2126104,
    "tgn:name":"Addies Branch",
    "tgn:placetype":[
        "aat:300008699"
    ]
},
  "bbox": [],
  "geometry": {"coordinates":[-81.5833,36.05],"type":"Point"}
}