<<<<<<< HEAD
{
  "id": 7375499,
  "type": "Feature",
  "properties": {
    "tgn:hierarchy":[
        "tgn:7375499",
        "tgn:7005581",
        "tgn:1000001",
        "tgn:7005560",
        "tgn:7029392"
    ],
    "tgn:id":7375499,
    "tgn:name":"Lim\u00f3n, Arroyo del",
    "tgn:placetype":[
        "aat:300008699"
    ]
},
  "bbox": [],
  "geometry": {"coordinates":[-107.233333,26.683333],"type":"Point"}
}
=======
{"geometry":{"type":"Point","coordinates":[-107.233333,26.683333]},"type":"Feature","properties":{"hierarchy":["tgn:7375499","tgn:7005581","tgn:1000001","tgn:7005560","tgn:7029392"],"placetype":["aat:300008699"],"id":7375499,"name:xx":"Lim\u00f3n, Arroyo del"}}
>>>>>>> 03f74aca74312dbeaf24d7e61306dd6a786dc3d0
