{
  "id": 2035007,
  "type": "Feature",
  "properties": {
    "tgn:hierarchy":[
        "tgn:2035007",
        "tgn:1000001",
        "tgn:2000570",
        "tgn:7012149",
        "tgn:7007253",
        "tgn:7029392"
    ],
    "tgn:id":2035007,
    "tgn:name":"Jesup",
    "tgn:placetype":[
        "aat:300008347"
    ]
},
  "bbox": [],
  "geometry": {"coordinates":[-92.05,42.4667],"type":"Point"}
}