{
  "id": 7293029,
  "type": "Feature",
  "properties": {
    "tgn:hierarchy":[
        "tgn:7293029",
        "tgn:1001657",
        "tgn:1000049",
        "tgn:1000002",
        "tgn:7029392"
    ],
    "tgn:id":7293029,
    "tgn:name":"El Sauce",
    "tgn:placetype":[
        "aat:300000206"
    ]
},
  "bbox": [],
  "geometry": {"coordinates":[-71.383333,-30.55],"type":"Point"}
}