<<<<<<< HEAD
{
  "id": 7367044,
  "type": "Feature",
  "properties": {
    "tgn:hierarchy":[
        "tgn:7367044",
        "tgn:1000001",
        "tgn:7005597",
        "tgn:7005560",
        "tgn:7029392"
    ],
    "tgn:id":7367044,
    "tgn:name":"El Roc\u00edo",
    "tgn:placetype":[
        "aat:300008347"
    ]
},
  "bbox": [],
  "geometry": {"coordinates":[-97.8,25.4],"type":"Point"}
}
=======
{"geometry":{"type":"Point","coordinates":[-97.800000,25.400000]},"type":"Feature","properties":{"hierarchy":["tgn:7367044","tgn:1000001","tgn:7005597","tgn:7005560","tgn:7029392"],"placetype":["aat:300008347"],"id":7367044,"name:xx":"El Roc\u00edo"}}
>>>>>>> 03f74aca74312dbeaf24d7e61306dd6a786dc3d0
