<<<<<<< HEAD
{
  "id": 2404638,
  "type": "Feature",
  "properties": {
    "tgn:hierarchy":[
        "tgn:2404638",
        "tgn:1000001",
        "tgn:2001266",
        "tgn:7012149",
        "tgn:7007524",
        "tgn:7029392"
    ],
    "tgn:id":2404638,
    "tgn:name":"Huchinson Mine",
    "tgn:placetype":[
        "aat:300000390"
    ]
},
  "bbox": [],
  "geometry": {"coordinates":[-110.7,46.95],"type":"Point"}
}
=======
{"geometry":{"type":"Point","coordinates":[-110.700000,46.950000]},"type":"Feature","properties":{"hierarchy":["tgn:2404638","tgn:1000001","tgn:2001266","tgn:7012149","tgn:7007524","tgn:7029392"],"placetype":["aat:300000390"],"id":2404638,"name:xx":"Huchinson Mine"}}
>>>>>>> 03f74aca74312dbeaf24d7e61306dd6a786dc3d0
