<<<<<<< HEAD
{
  "id": 2256357,
  "type": "Feature",
  "properties": {
    "tgn:hierarchy":[
        "tgn:2256357",
        "tgn:1002247",
        "tgn:1000001",
        "tgn:7012149",
        "tgn:7007516",
        "tgn:7029392"
    ],
    "tgn:id":2256357,
    "tgn:name":"Coppin Creek",
    "tgn:placetype":[
        "aat:300008706"
    ]
},
  "bbox": [],
  "geometry": {"coordinates":[-75.85,39.3833],"type":"Point"}
}
=======
{"geometry":{"type":"Point","coordinates":[-75.850000,39.383300]},"type":"Feature","properties":{"hierarchy":["tgn:2256357","tgn:1002247","tgn:1000001","tgn:7012149","tgn:7007516","tgn:7029392"],"placetype":["aat:300008706"],"id":2256357,"name:xx":"Coppin Creek"}}
>>>>>>> 03f74aca74312dbeaf24d7e61306dd6a786dc3d0
