{
  "id": 2449590,
  "type": "Feature",
  "properties": {
    "tgn:hierarchy":[
        "tgn:2449590",
        "tgn:1000001",
        "tgn:7012149",
        "tgn:1002694",
        "tgn:7007252",
        "tgn:7029392"
    ],
    "tgn:id":2449590,
    "tgn:name":"Lincoln Hill",
    "tgn:placetype":[
        "aat:300008798"
    ]
},
  "bbox": [],
  "geometry": {"coordinates":[-86.4167,39.4333],"type":"Point"}
}