{
  "id": 7502164,
  "type": "Feature",
  "properties": {
    "tgn:hierarchy":[
        "tgn:7502164",
        "tgn:1000004",
        "tgn:7471332",
        "tgn:1000141",
        "tgn:7029392"
    ],
    "tgn:id":7502164,
    "tgn:name":"Zhubei Gaozhong",
    "tgn:placetype":[
        "aat:300006495"
    ]
},
  "bbox": [],
  "geometry": {"coordinates":[121.003611,24.835278],"type":"Point"}
}