{
  "id": 2643088,
  "type": "Feature",
  "properties": {
    "tgn:hierarchy":[
        "tgn:2643088",
        "tgn:1000001",
        "tgn:7012149",
        "tgn:1002694",
        "tgn:7007252",
        "tgn:7029392"
    ],
    "tgn:id":2643088,
    "tgn:name":"Sandy Branch",
    "tgn:placetype":[
        "aat:300008699"
    ]
},
  "bbox": [],
  "geometry": {"coordinates":[-86.6167,39.5167],"type":"Point"}
}