{
  "id": 7218901,
  "type": "Feature",
  "properties": {
    "tgn:hierarchy":[
        "tgn:7218901",
        "tgn:7011270",
        "tgn:7002674",
        "tgn:1000003",
        "tgn:1000074",
        "tgn:7029392"
    ],
    "tgn:id":7218901,
    "tgn:name":"Kalyps\u00f3, Vr\u00e1chos",
    "tgn:placetype":[
        "aat:300011692"
    ]
},
  "bbox": [],
  "geometry": {"coordinates":[25.322778,37.0675],"type":"Point"}
}