{
  "id": 2278905,
  "type": "Feature",
  "properties": {
    "tgn:hierarchy":[
        "tgn:2278905",
        "tgn:1000001",
        "tgn:2001435",
        "tgn:7012149",
        "tgn:7007566",
        "tgn:7029392"
    ],
    "tgn:id":2278905,
    "tgn:name":"Dead Man Canyon",
    "tgn:placetype":[
        "aat:300008761"
    ]
},
  "bbox": [],
  "geometry": {"coordinates":[-106.6167,32.8167],"type":"Point"}
}