{
  "id": 7186515,
  "type": "Feature",
  "properties": {
    "tgn:hierarchy":[
        "tgn:7186515",
        "tgn:1000003",
        "tgn:7000094",
        "tgn:7000084",
        "tgn:7029392"
    ],
    "tgn:id":7186515,
    "tgn:name":"Goldenitzer Tannen",
    "tgn:placetype":[
        "aat:300008863"
    ]
},
  "bbox": [],
  "geometry": {"coordinates":[12.133333,53.916667],"type":"Point"}
}