{
  "id": 2754093,
  "type": "Feature",
  "properties": {
    "tgn:hierarchy":[
        "tgn:2754093",
        "tgn:1002153",
        "tgn:1000001",
        "tgn:7012149",
        "tgn:7007710",
        "tgn:7029392"
    ],
    "tgn:id":2754093,
    "tgn:name":"Watson Run",
    "tgn:placetype":[
        "aat:300008699"
    ]
},
  "bbox": [],
  "geometry": {"coordinates":[-79.6167,40.7167],"type":"Point"}
}