{
  "id": 7120433,
  "type": "Feature",
  "properties": {
    "tgn:hierarchy":[
        "tgn:7120433",
        "tgn:7003669",
        "tgn:1000003",
        "tgn:7000084",
        "tgn:7029392"
    ],
    "tgn:id":7120433,
    "tgn:name":"Pleckenstein",
    "tgn:placetype":[
        "aat:300000206"
    ]
},
  "bbox": [],
  "geometry": {"coordinates":[13.75,48.783333],"type":"Point"}
}