{
  "id": 7517451,
  "type": "Feature",
  "properties": {
    "tgn:hierarchy":[
        "tgn:7517451",
        "tgn:1009227",
        "tgn:1000226",
        "tgn:7016822",
        "tgn:1000006",
        "tgn:7029392"
    ],
    "tgn:id":7517451,
    "tgn:name:en":"Meggs Hill",
    "tgn:placetype":[
        "aat:300008777"
    ]
},
  "bbox": [],
  "geometry": {"coordinates":[166.233333,-50.566667],"type":"Point"}
}