{
  "id": 2181670,
  "type": "Feature",
  "properties": {
    "tgn:hierarchy":[
        "tgn:2181670",
        "tgn:1000001",
        "tgn:7012149",
        "tgn:2002037",
        "tgn:7007826",
        "tgn:7029392"
    ],
    "tgn:id":2181670,
    "tgn:name":"Blue Hole",
    "tgn:placetype":[
        "aat:300008680"
    ]
},
  "bbox": [],
  "geometry": {"coordinates":[-99.3833,30.9333],"type":"Point"}
}