{
  "id": 7237874,
  "type": "Feature",
  "properties": {
    "tgn:hierarchy":[
        "tgn:7237874",
        "tgn:7003466",
        "tgn:1000003",
        "tgn:1000063",
        "tgn:4012014",
        "tgn:7029392"
    ],
    "tgn:id":7237874,
    "tgn:name":"Hermeton",
    "tgn:placetype":[
        "aat:300008699"
    ]
},
  "bbox": [],
  "geometry": {"coordinates":[4.817199,50.198903],"type":"Point"}
}