{
  "id": 2135274,
  "type": "Feature",
  "properties": {
    "tgn:hierarchy":[
        "tgn:2135274",
        "tgn:1000001",
        "tgn:7012149",
        "tgn:2001154",
        "tgn:7007522",
        "tgn:7029392"
    ],
    "tgn:id":2135274,
    "tgn:name":"Antioch",
    "tgn:placetype":[
        "aat:300008347"
    ]
},
  "bbox": [],
  "geometry": {"coordinates":[-89.8667,34.6833],"type":"Point"}
}