{
  "id": 2307008,
  "type": "Feature",
  "properties": {
    "tgn:hierarchy":[
        "tgn:2307008",
        "tgn:1000001",
        "tgn:7012149",
        "tgn:2002126",
        "tgn:7007827",
        "tgn:7029392"
    ],
    "tgn:id":2307008,
    "tgn:name":"East Fork Little Sand Creek",
    "tgn:placetype":[
        "aat:300008706"
    ]
},
  "bbox": [],
  "geometry": {"coordinates":[-110.95,40.4167],"type":"Point"}
}