{
  "id": 7496044,
  "type": "Feature",
  "properties": {
    "tgn:hierarchy":[
        "tgn:7496044",
        "tgn:7468018",
        "tgn:1000004",
        "tgn:1000141",
        "tgn:7029392"
    ],
    "tgn:id":7496044,
    "tgn:name":"Xidiliao Qiao",
    "tgn:placetype":[
        "aat:300007836"
    ]
},
  "bbox": [],
  "geometry": {"coordinates":[120.347798,23.577437],"type":"Point"}
}