{
  "id": 7526430,
  "type": "Feature",
  "properties": {
    "tgn:hierarchy":[
        "tgn:7526430",
        "tgn:7001242",
        "tgn:7016833",
        "tgn:1001083",
        "tgn:7029392"
    ],
    "tgn:id":7526430,
    "tgn:name:en":"S\u012bd\u012b Khal\u012bl al Ghan\u0101'im",
    "tgn:placetype":[
        "aat:300005926"
    ]
},
  "bbox": [],
  "geometry": {"coordinates":[31.266667,29.35],"type":"Point"}
}