{
  "id": 7373669,
  "type": "Feature",
  "properties": {
    "tgn:hierarchy":[
        "tgn:7373669",
        "tgn:1000001",
        "tgn:1001960",
        "tgn:7005560",
        "tgn:7029392"
    ],
    "tgn:id":7373669,
    "tgn:name":"La Cieneguita, Arroyo de",
    "tgn:placetype":[
        "aat:300266554",
        "aat:300008699"
    ]
},
  "bbox": [],
  "geometry": {"coordinates":[-109.916667,28.166667],"type":"Point"}
}