{
  "id": 2690426,
  "type": "Feature",
  "properties": {
    "tgn:hierarchy":[
        "tgn:2690426",
        "tgn:1000001",
        "tgn:2000924",
        "tgn:7012149",
        "tgn:7007515",
        "tgn:7029392"
    ],
    "tgn:id":2690426,
    "tgn:name":"Stahls Hill",
    "tgn:placetype":[
        "aat:300008798"
    ]
},
  "bbox": [],
  "geometry": {"coordinates":[-69.2667,44.0667],"type":"Point"}
}