{
  "id": 7559966,
  "type": "Feature",
  "properties": {
    "tgn:hierarchy":[
        "tgn:7559966",
        "tgn:1000004",
        "tgn:7000198",
        "tgn:7016722",
        "tgn:7029392"
    ],
    "tgn:id":7559966,
    "tgn:name:en":"Gurgaon",
    "tgn:placetype":[
        "aat:300008347"
    ]
},
  "bbox": [],
  "geometry": {"coordinates":[79.675439,27.693556],"type":"Point"}
}