<<<<<<< HEAD
{
  "id": 2330216,
  "type": "Feature",
  "properties": {
    "tgn:hierarchy":[
        "tgn:2330216",
        "tgn:1000001",
        "tgn:7012149",
        "tgn:2000928",
        "tgn:7007515",
        "tgn:7029392"
    ],
    "tgn:id":2330216,
    "tgn:name":"Flanders Brook",
    "tgn:placetype":[
        "aat:300008699"
    ]
},
  "bbox": [],
  "geometry": {"coordinates":[-69.2833,45.15],"type":"Point"}
}
=======
{"geometry":{"type":"Point","coordinates":[-69.283300,45.150000]},"type":"Feature","properties":{"hierarchy":["tgn:2330216","tgn:1000001","tgn:7012149","tgn:2000928","tgn:7007515","tgn:7029392"],"placetype":["aat:300008699"],"id":2330216,"name:xx":"Flanders Brook"}}
>>>>>>> 03f74aca74312dbeaf24d7e61306dd6a786dc3d0
