{
  "id": 7373898,
  "type": "Feature",
  "properties": {
    "tgn:hierarchy":[
        "tgn:7373898",
        "tgn:1000001",
        "tgn:7005589",
        "tgn:7005560",
        "tgn:7029392"
    ],
    "tgn:id":7373898,
    "tgn:name":"La Bandera",
    "tgn:placetype":[
        "aat:300008347"
    ]
},
  "bbox": [],
  "geometry": {"coordinates":[-98.966667,25.983333],"type":"Point"}
}