{
  "id": 7034648,
  "type": "Feature",
  "properties": {
    "tgn:hierarchy":[
        "tgn:7034648",
        "tgn:7003006",
        "tgn:1000003",
        "tgn:7002997",
        "tgn:1000080",
        "tgn:7029392"
    ],
    "tgn:id":7034648,
    "tgn:name":"Vignola Grande",
    "tgn:placetype":[
        "aat:300008347"
    ]
},
  "bbox": [],
  "geometry": {"coordinates":[12.379167,45.441667],"type":"Point"}
}