{
  "id": 2674182,
  "type": "Feature",
  "properties": {
    "tgn:hierarchy":[
        "tgn:2674182",
        "tgn:1000001",
        "tgn:7012149",
        "tgn:7007158",
        "tgn:2000240",
        "tgn:7029392"
    ],
    "tgn:id":2674182,
    "tgn:name":"Snowmass Divide Ditch",
    "tgn:placetype":[
        "aat:300006075"
    ]
},
  "bbox": [],
  "geometry": {"coordinates":[-106.9333,39.2833],"type":"Point"}
}