<<<<<<< HEAD
{
  "id": 2250738,
  "type": "Feature",
  "properties": {
    "tgn:hierarchy":[
        "tgn:2250738",
        "tgn:1000001",
        "tgn:7012149",
        "tgn:2000494",
        "tgn:7007250",
        "tgn:7029392"
    ],
    "tgn:id":2250738,
    "tgn:name":"Colt Creek",
    "tgn:placetype":[
        "aat:300008706"
    ]
},
  "bbox": [],
  "geometry": {"coordinates":[-115.2167,44.7667],"type":"Point"}
}
=======
{"geometry":{"type":"Point","coordinates":[-115.216700,44.766700]},"type":"Feature","properties":{"hierarchy":["tgn:2250738","tgn:1000001","tgn:7012149","tgn:2000494","tgn:7007250","tgn:7029392"],"placetype":["aat:300008706"],"id":2250738,"name:xx":"Colt Creek"}}
>>>>>>> 03f74aca74312dbeaf24d7e61306dd6a786dc3d0
