{
  "id": 2343124,
  "type": "Feature",
  "properties": {
    "tgn:hierarchy":[
        "tgn:2343124",
        "tgn:2001468",
        "tgn:1000001",
        "tgn:7012149",
        "tgn:7007709",
        "tgn:7029392"
    ],
    "tgn:id":2343124,
    "tgn:name":"Gabes Mountain",
    "tgn:placetype":[
        "aat:300008798"
    ]
},
  "bbox": [],
  "geometry": {"coordinates":[-81.8167,36.0667],"type":"Point"}
}