{
  "id": 7573540,
  "type": "Feature",
  "properties": {
    "tgn:hierarchy":[
        "tgn:7573540",
        "tgn:1000004",
        "tgn:7000198",
        "tgn:1001886",
        "tgn:7029392"
    ],
    "tgn:id":7573540,
    "tgn:name:en":"Irikk\u016br",
    "tgn:placetype":[
        "aat:300008347"
    ]
},
  "bbox": [],
  "geometry": {"coordinates":[75.566667,11.966667],"type":"Point"}
}