{
  "id": 7077185,
  "type": "Feature",
  "properties": {
    "tgn:hierarchy":[
        "tgn:7077185",
        "tgn:1000003",
        "tgn:7003677",
        "tgn:7000084",
        "tgn:7029392"
    ],
    "tgn:id":7077185,
    "tgn:name":"Kreisfreie Stadt M\u00f6nchengladbach",
    "tgn:placetype":[
        "aat:300387198"
    ]
},
  "bbox": [],
  "geometry": {"coordinates":[6.404444,51.170833],"type":"Point"}
}