{
  "id": 1033067,
  "type": "Feature",
  "properties": {
    "tgn:hierarchy":[
        "tgn:1033067",
        "tgn:1000003",
        "tgn:7002888",
        "tgn:1000070",
        "tgn:7029392"
    ],
    "tgn:id":1033067,
    "tgn:name":"Falck",
    "tgn:placetype":[
        "aat:300008347"
    ]
},
  "bbox": [],
  "geometry": {"coordinates":[6.6333,49.2333],"type":"Point"}
}