{
  "id": 7539092,
  "type": "Feature",
  "properties": {
    "tgn:hierarchy":[
        "tgn:7539092",
        "tgn:7001242",
        "tgn:7016833",
        "tgn:7000122",
        "tgn:7029392"
    ],
    "tgn:id":7539092,
    "tgn:name:en":"M\u0101r\u012byah, W\u0101d\u012b",
    "tgn:placetype":[
        "aat:300379998"
    ]
},
  "bbox": [],
  "geometry": {"coordinates":[33.085663,23.298947],"type":"Point"}
}