{
  "id": 7344777,
  "type": "Feature",
  "properties": {
    "tgn:hierarchy":[
        "tgn:7344777",
        "tgn:7001158",
        "tgn:7002850",
        "tgn:1000003",
        "tgn:1000095",
        "tgn:7029392"
    ],
    "tgn:id":7344777,
    "tgn:name":"Amor",
    "tgn:placetype":[
        "aat:300008347"
    ]
},
  "bbox": [],
  "geometry": {"coordinates":[-5.816667,41.383333],"type":"Point"}
}