{
  "id": 7401363,
  "type": "Feature",
  "properties": {
    "tgn:hierarchy":[
        "tgn:7401363",
        "tgn:1000001",
        "tgn:7005599",
        "tgn:7005560",
        "tgn:7029392"
    ],
    "tgn:id":7401363,
    "tgn:name":"La Reforma",
    "tgn:placetype":[
        "aat:300008347"
    ]
},
  "bbox": [],
  "geometry": {"coordinates":[-98.598611,21.566667],"type":"Point"}
}