{
  "id": 7046122,
  "type": "Feature",
  "properties": {
    "tgn:hierarchy":[
        "tgn:7046122",
        "tgn:7003002",
        "tgn:7003005",
        "tgn:1000003",
        "tgn:1000080",
        "tgn:7029392"
    ],
    "tgn:id":7046122,
    "tgn:name":"Campanarello",
    "tgn:placetype":[
        "aat:300008347"
    ]
},
  "bbox": [],
  "geometry": {"coordinates":[14.916667,41.05],"type":"Point"}
}