{
  "id": 7546887,
  "type": "Feature",
  "properties": {
    "tgn:hierarchy":[
        "tgn:7546887",
        "tgn:1000004",
        "tgn:1001869",
        "tgn:7000198",
        "tgn:7029392"
    ],
    "tgn:id":7546887,
    "tgn:name:en":"Aramda Reefs",
    "tgn:placetype":[
        "aat:300008808"
    ]
},
  "bbox": [],
  "geometry": {"coordinates":[68.99,22.457222],"type":"Point"}
}