<<<<<<< HEAD
{
  "id": 7353917,
  "type": "Feature",
  "properties": {
    "tgn:hierarchy":[
        "tgn:7353917",
        "tgn:1000001",
        "tgn:7005600",
        "tgn:7005560",
        "tgn:7029392"
    ],
    "tgn:id":7353917,
    "tgn:name":"Choltunha, Cenote",
    "tgn:placetype":[
        "aat:300343547"
    ]
},
  "bbox": [],
  "geometry": {"coordinates":[-88.7,21.216667],"type":"Point"}
}
=======
{"geometry":{"type":"Point","coordinates":[-88.700000,21.216667]},"type":"Feature","properties":{"hierarchy":["tgn:7353917","tgn:1000001","tgn:7005600","tgn:7005560","tgn:7029392"],"placetype":["aat:300343547"],"id":7353917,"name:xx":"Choltunha, Cenote"}}
>>>>>>> 03f74aca74312dbeaf24d7e61306dd6a786dc3d0
