<<<<<<< HEAD
{
  "id": 2769207,
  "type": "Feature",
  "properties": {
    "tgn:hierarchy":[
        "tgn:2769207",
        "tgn:1000001",
        "tgn:7012149",
        "tgn:1003038",
        "tgn:7007517",
        "tgn:7029392"
    ],
    "tgn:id":2769207,
    "tgn:name":"Whortleberry Hill",
    "tgn:placetype":[
        "aat:300008798"
    ]
},
  "bbox": [],
  "geometry": {"coordinates":[-72.1333,42.2833],"type":"Point"}
}
=======
{"geometry":{"type":"Point","coordinates":[-72.133300,42.283300]},"type":"Feature","properties":{"hierarchy":["tgn:2769207","tgn:1000001","tgn:7012149","tgn:1003038","tgn:7007517","tgn:7029392"],"placetype":["aat:300008798"],"id":2769207,"name:xx":"Whortleberry Hill"}}
>>>>>>> 03f74aca74312dbeaf24d7e61306dd6a786dc3d0
