<<<<<<< HEAD
{
  "id": 2401638,
  "type": "Feature",
  "properties": {
    "tgn:hierarchy":[
        "tgn:2401638",
        "tgn:1000001",
        "tgn:7016172",
        "tgn:7012149",
        "tgn:2000179",
        "tgn:7029392"
    ],
    "tgn:id":2401638,
    "tgn:name":"Horseshoe Lake",
    "tgn:placetype":[
        "aat:300008680"
    ]
},
  "bbox": [],
  "geometry": {"coordinates":[-93.45,35.05],"type":"Point"}
}
=======
{"geometry":{"type":"Point","coordinates":[-93.450000,35.050000]},"type":"Feature","properties":{"hierarchy":["tgn:2401638","tgn:1000001","tgn:7016172","tgn:7012149","tgn:2000179","tgn:7029392"],"placetype":["aat:300008680"],"id":2401638,"name:xx":"Horseshoe Lake"}}
>>>>>>> 03f74aca74312dbeaf24d7e61306dd6a786dc3d0
