{
  "id": 1103377,
  "type": "Feature",
  "properties": {
    "tgn:hierarchy":[
        "tgn:1103377",
        "tgn:1000004",
        "tgn:7029392"
    ],
    "tgn:id":1103377,
    "tgn:name":"Gobi",
    "tgn:placetype":[
        "aat:300008916"
    ]
},
  "bbox": [],
  "geometry": {"coordinates":[105.0833,43.0833],"type":"Point"}
}