{
  "id": 2400909,
  "type": "Feature",
  "properties": {
    "tgn:hierarchy":[
        "tgn:2400909",
        "tgn:1000001",
        "tgn:7012149",
        "tgn:2002302",
        "tgn:7013961",
        "tgn:7029392"
    ],
    "tgn:id":2400909,
    "tgn:name":"Horse Run",
    "tgn:placetype":[
        "aat:300008699"
    ]
},
  "bbox": [],
  "geometry": {"coordinates":[-81.35,38.9167],"type":"Point"}
}