{
  "id": 2372509,
  "type": "Feature",
  "properties": {
    "tgn:hierarchy":[
        "tgn:2372509",
        "tgn:1000001",
        "tgn:2000302",
        "tgn:7012149",
        "tgn:7007248",
        "tgn:7029392"
    ],
    "tgn:id":2372509,
    "tgn:name":"Hall Branch",
    "tgn:placetype":[
        "aat:300008699"
    ]
},
  "bbox": [],
  "geometry": {"coordinates":[-83.5167,32.8333],"type":"Point"}
}