{
  "id": 2520529,
  "type": "Feature",
  "properties": {
    "tgn:hierarchy":[
        "tgn:2520529",
        "tgn:1000001",
        "tgn:2001418",
        "tgn:7012149",
        "tgn:7007526",
        "tgn:7029392"
    ],
    "tgn:id":2520529,
    "tgn:name":"Monitor Mine",
    "tgn:placetype":[
        "aat:300000390"
    ]
},
  "bbox": [],
  "geometry": {"coordinates":[-116.85,38.95],"type":"Point"}
}