{
  "id": 2096408,
  "type": "Feature",
  "properties": {
    "tgn:hierarchy":[
        "tgn:2096408",
        "tgn:1000001",
        "tgn:2001746",
        "tgn:7012149",
        "tgn:7007712",
        "tgn:7029392"
    ],
    "tgn:id":2096408,
    "tgn:name":"Outland",
    "tgn:placetype":[
        "aat:300008347",
        "aat:300387210"
    ]
},
  "bbox": [],
  "geometry": {"coordinates":[-79.3667,33.7167],"type":"Point"}
}