{
  "id": 7499098,
  "type": "Feature",
  "properties": {
    "tgn:hierarchy":[
        "tgn:7499098",
        "tgn:1000004",
        "tgn:7001009",
        "tgn:1000141",
        "tgn:7029392"
    ],
    "tgn:id":7499098,
    "tgn:name":"Longzhouwo",
    "tgn:placetype":[
        "aat:300008347"
    ]
},
  "bbox": [],
  "geometry": {"coordinates":[120.780828,24.190601],"type":"Point"}
}