{
  "id": 7199846,
  "type": "Feature",
  "properties": {
    "tgn:hierarchy":[
        "tgn:7199846",
        "tgn:1000003",
        "tgn:7003689",
        "tgn:7000084",
        "tgn:7029392"
    ],
    "tgn:id":7199846,
    "tgn:name":"Drei Gleichen",
    "tgn:placetype":[
        "aat:300000206"
    ]
},
  "bbox": [],
  "geometry": {"coordinates":[10.816667,50.95],"type":"Point"}
}