{
  "id": 7270635,
  "type": "Feature",
  "properties": {
    "tgn:hierarchy":[
        "tgn:7270635",
        "tgn:1000003",
        "tgn:7003624",
        "tgn:7016845",
        "tgn:7029392"
    ],
    "tgn:id":7270635,
    "tgn:name:nl":"Sengelbroeksche Heide",
    "tgn:placetype":[
        "aat:300387200"
    ]
},
  "bbox": [],
  "geometry": {"coordinates":[5.333333,51.266667],"type":"Point"}
}