{
  "id": 2304746,
  "type": "Feature",
  "properties": {
    "tgn:hierarchy":[
        "tgn:2304746",
        "tgn:1000001",
        "tgn:2002109",
        "tgn:7012149",
        "tgn:7007827",
        "tgn:7029392"
    ],
    "tgn:id":2304746,
    "tgn:name":"East Boulder Draw",
    "tgn:placetype":[
        "aat:300008761"
    ]
},
  "bbox": [],
  "geometry": {"coordinates":[-111.4833,38.1333],"type":"Point"}
}