<<<<<<< HEAD
{
  "id": 2257544,
  "type": "Feature",
  "properties": {
    "tgn:hierarchy":[
        "tgn:2257544",
        "tgn:1000001",
        "tgn:2001415",
        "tgn:7012149",
        "tgn:7007526",
        "tgn:7029392"
    ],
    "tgn:id":2257544,
    "tgn:name":"Corral Canyon",
    "tgn:placetype":[
        "aat:300008761"
    ]
},
  "bbox": [],
  "geometry": {"coordinates":[-117.0833,39.3167],"type":"Point"}
}
=======
{"geometry":{"type":"Point","coordinates":[-117.083300,39.316700]},"type":"Feature","properties":{"hierarchy":["tgn:2257544","tgn:1000001","tgn:2001415","tgn:7012149","tgn:7007526","tgn:7029392"],"placetype":["aat:300008761"],"id":2257544,"name:xx":"Corral Canyon"}}
>>>>>>> 03f74aca74312dbeaf24d7e61306dd6a786dc3d0
