{
  "id": 2503695,
  "type": "Feature",
  "properties": {
    "tgn:hierarchy":[
        "tgn:2503695",
        "tgn:1000001",
        "tgn:7012149",
        "tgn:2001553",
        "tgn:7007709",
        "tgn:7029392"
    ],
    "tgn:id":2503695,
    "tgn:name":"Meadow Branch",
    "tgn:placetype":[
        "aat:300008699"
    ]
},
  "bbox": [],
  "geometry": {"coordinates":[-81.4167,36.1667],"type":"Point"}
}