{
  "id": 2279743,
  "type": "Feature",
  "properties": {
    "tgn:hierarchy":[
        "tgn:2279743",
        "tgn:1000001",
        "tgn:7012149",
        "tgn:7007157",
        "tgn:1002894",
        "tgn:7029392"
    ],
    "tgn:id":2279743,
    "tgn:name":"Deadwood Creek",
    "tgn:placetype":[
        "aat:300008706"
    ]
},
  "bbox": [],
  "geometry": {"coordinates":[-120.85,39.6667],"type":"Point"}
}