{
  "id": 7034840,
  "type": "Feature",
  "properties": {
    "tgn:hierarchy":[
        "tgn:7034840",
        "tgn:7003013",
        "tgn:7003005",
        "tgn:1000003",
        "tgn:1000080",
        "tgn:7029392"
    ],
    "tgn:id":7034840,
    "tgn:name":"Diga Foranea Emanuele Filiberto Duca D'Aosta",
    "tgn:placetype":[
        "aat:300170882"
    ]
},
  "bbox": [],
  "geometry": {"coordinates":[14.291111,40.833333],"type":"Point"}
}