{
  "id": 2711511,
  "type": "Feature",
  "properties": {
    "tgn:hierarchy":[
        "tgn:2711511",
        "tgn:7006450",
        "tgn:1000001",
        "tgn:7012149",
        "tgn:2000079",
        "tgn:7029392"
    ],
    "tgn:id":2711511,
    "tgn:name":"Taphook Mountain",
    "tgn:placetype":[
        "aat:300008798"
    ]
},
  "bbox": [],
  "geometry": {"coordinates":[-171.2667,63.5667],"type":"Point"}
}