{
  "id": 2037490,
  "type": "Feature",
  "properties": {
    "tgn:hierarchy":[
        "tgn:2037490",
        "tgn:1000001",
        "tgn:7012149",
        "tgn:2000805",
        "tgn:7007255",
        "tgn:7029392"
    ],
    "tgn:id":2037490,
    "tgn:name":"Anco",
    "tgn:placetype":[
        "aat:300008347"
    ]
},
  "bbox": [],
  "geometry": {"coordinates":[-83.05,37.2333],"type":"Point"}
}