{
  "id": 7571462,
  "type": "Feature",
  "properties": {
    "tgn:hierarchy":[
        "tgn:7571462",
        "tgn:1000004",
        "tgn:7000198",
        "tgn:7016722",
        "tgn:7029392"
    ],
    "tgn:id":7571462,
    "tgn:name:en":"Haswa",
    "tgn:placetype":[
        "aat:300008347"
    ]
},
  "bbox": [],
  "geometry": {"coordinates":[80.915999,25.87255],"type":"Point"}
}