{
  "id": 1028156,
  "type": "Feature",
  "properties": {
    "tgn:hierarchy":[
        "tgn:1028156",
        "tgn:1000003",
        "tgn:7594009",
        "tgn:1000066",
        "tgn:7029392"
    ],
    "tgn:id":1028156,
    "tgn:name":"Strib",
    "tgn:placetype":[
        "aat:300008347"
    ]
},
  "bbox": [],
  "geometry": {"coordinates":[9.7833,55.55],"type":"Point"}
}