{
  "id": 2394542,
  "type": "Feature",
  "properties": {
    "tgn:hierarchy":[
        "tgn:2394542",
        "tgn:1000001",
        "tgn:7016172",
        "tgn:7012149",
        "tgn:7029392"
    ],
    "tgn:id":2394542,
    "tgn:name":"Hogpen Mountain",
    "tgn:placetype":[
        "aat:300008798"
    ]
},
  "bbox": [],
  "geometry": {"coordinates":[-93.8167,34.3333],"type":"Point"}
}