{
  "id": 2482161,
  "type": "Feature",
  "properties": {
    "tgn:hierarchy":[
        "tgn:2482161",
        "tgn:1000001",
        "tgn:7006451",
        "tgn:7012149",
        "tgn:2000103",
        "tgn:7029392"
    ],
    "tgn:id":2482161,
    "tgn:name":"Lang Spring",
    "tgn:placetype":[
        "aat:300008697"
    ]
},
  "bbox": [],
  "geometry": {"coordinates":[-112.1667,34.65],"type":"Point"}
}