<<<<<<< HEAD
{
  "id": 7057580,
  "type": "Feature",
  "properties": {
    "tgn:hierarchy":[
        "tgn:7057580",
        "tgn:7003006",
        "tgn:1000003",
        "tgn:7002997",
        "tgn:1000080",
        "tgn:7029392"
    ],
    "tgn:id":7057580,
    "tgn:name":"Asseggiano",
    "tgn:placetype":[
        "aat:300008347"
    ]
},
  "bbox": [],
  "geometry": {"coordinates":[12.183333,45.483333],"type":"Point"}
}
=======
{"geometry":{"type":"Point","coordinates":[12.183333,45.483333]},"type":"Feature","properties":{"hierarchy":["tgn:7057580","tgn:7003006","tgn:1000003","tgn:7002997","tgn:1000080","tgn:7029392"],"placetype":["aat:300008347"],"id":7057580,"name:xx":"Asseggiano"}}
>>>>>>> 03f74aca74312dbeaf24d7e61306dd6a786dc3d0
