{
  "id": 2355382,
  "type": "Feature",
  "properties": {
    "tgn:hierarchy":[
        "tgn:2355382",
        "tgn:1000001",
        "tgn:7012149",
        "tgn:2001247",
        "tgn:7007523",
        "tgn:7029392"
    ],
    "tgn:id":2355382,
    "tgn:name":"Goose Bay Creek",
    "tgn:placetype":[
        "aat:300008706"
    ]
},
  "bbox": [],
  "geometry": {"coordinates":[-91.2167,37.1333],"type":"Point"}
}