{
  "id": 2636076,
  "type": "Feature",
  "properties": {
    "tgn:hierarchy":[
        "tgn:2636076",
        "tgn:1000001",
        "tgn:7012149",
        "tgn:2002371",
        "tgn:7007923",
        "tgn:7029392"
    ],
    "tgn:id":2636076,
    "tgn:name":"Saddle Horse Draw",
    "tgn:placetype":[
        "aat:300008761"
    ]
},
  "bbox": [],
  "geometry": {"coordinates":[-109.7333,43.5333],"type":"Point"}
}