{
  "id": 2089779,
  "type": "Feature",
  "properties": {
    "tgn:hierarchy":[
        "tgn:2089779",
        "tgn:1000001",
        "tgn:7013387",
        "tgn:7012149",
        "tgn:7007710",
        "tgn:7029392"
    ],
    "tgn:id":2089779,
    "tgn:name":"Kindts Corner",
    "tgn:placetype":[
        "aat:300008347",
        "aat:300387210"
    ]
},
  "bbox": [],
  "geometry": {"coordinates":[-75.9167,40.45],"type":"Point"}
}