{
  "id": 2386507,
  "type": "Feature",
  "properties": {
    "tgn:hierarchy":[
        "tgn:2386507",
        "tgn:1000001",
        "tgn:7012149",
        "tgn:2001447",
        "tgn:7007566",
        "tgn:7029392"
    ],
    "tgn:id":2386507,
    "tgn:name":"Herd Pasture Tub",
    "tgn:placetype":[
        "aat:300006191"
    ]
},
  "bbox": [],
  "geometry": {"coordinates":[-105.75,32.3333],"type":"Point"}
}