{
  "id": 2371494,
  "type": "Feature",
  "properties": {
    "tgn:hierarchy":[
        "tgn:2371494",
        "tgn:1000001",
        "tgn:7012149",
        "tgn:2000524",
        "tgn:7007251",
        "tgn:7029392"
    ],
    "tgn:id":2371494,
    "tgn:name":"Hairy Hill",
    "tgn:placetype":[
        "aat:300008798"
    ]
},
  "bbox": [],
  "geometry": {"coordinates":[-88.95,37.3333],"type":"Point"}
}