{
  "id": 1138915,
  "type": "Feature",
  "properties": {
    "tgn:hierarchy":[
        "tgn:1138915",
        "tgn:1000004",
        "tgn:1001390",
        "tgn:1000111",
        "tgn:7029392"
    ],
    "tgn:id":1138915,
    "tgn:name":"Donggou",
    "tgn:placetype":[
        "aat:300008347"
    ]
},
  "bbox": [],
  "geometry": {"coordinates":[124.1333,39.8667],"type":"Point"}
}