{
  "id": 2512917,
  "type": "Feature",
  "properties": {
    "tgn:hierarchy":[
        "tgn:2512917",
        "tgn:1000001",
        "tgn:7012149",
        "tgn:1002682",
        "tgn:7007710",
        "tgn:7029392"
    ],
    "tgn:id":2512917,
    "tgn:name":"Mill Creek",
    "tgn:placetype":[
        "aat:300008706"
    ]
},
  "bbox": [],
  "geometry": {"coordinates":[-75.3167,41.1667],"type":"Point"}
}