{
  "id": 2080255,
  "type": "Feature",
  "properties": {
    "tgn:hierarchy":[
        "tgn:2080255",
        "tgn:1000001",
        "tgn:7012149",
        "tgn:1003025",
        "tgn:7007706",
        "tgn:7029392"
    ],
    "tgn:id":2080255,
    "tgn:name":"Kunkle",
    "tgn:placetype":[
        "aat:300008347"
    ]
},
  "bbox": [],
  "geometry": {"coordinates":[-84.4833,41.6333],"type":"Point"}
}