{
  "id": 2725573,
  "type": "Feature",
  "properties": {
    "tgn:hierarchy":[
        "tgn:2725573",
        "tgn:1000001",
        "tgn:7012149",
        "tgn:2000238",
        "tgn:7007158",
        "tgn:7029392"
    ],
    "tgn:id":2725573,
    "tgn:name":"Topaz Mountain",
    "tgn:placetype":[
        "aat:300008798"
    ]
},
  "bbox": [],
  "geometry": {"coordinates":[-105.5667,39.2833],"type":"Point"}
}