{
  "id": 7577181,
  "type": "Feature",
  "properties": {
    "tgn:hierarchy":[
        "tgn:7577181",
        "tgn:1000004",
        "tgn:1001869",
        "tgn:7000198",
        "tgn:7029392"
    ],
    "tgn:id":7577181,
    "tgn:name:en":"Khed Brahma",
    "tgn:placetype":[
        "aat:300008347"
    ]
},
  "bbox": [],
  "geometry": {"coordinates":[73.046973,24.031651],"type":"Point"}
}