<<<<<<< HEAD
{
  "id": 2256191,
  "type": "Feature",
  "properties": {
    "tgn:hierarchy":[
        "tgn:2256191",
        "tgn:1000001",
        "tgn:7006451",
        "tgn:2000093",
        "tgn:7012149",
        "tgn:7029392"
    ],
    "tgn:id":2256191,
    "tgn:name":"Copper Springs Canyon",
    "tgn:placetype":[
        "aat:300008761"
    ]
},
  "bbox": [],
  "geometry": {"coordinates":[-110.8833,33.3333],"type":"Point"}
}
=======
{"geometry":{"type":"Point","coordinates":[-110.883300,33.333300]},"type":"Feature","properties":{"hierarchy":["tgn:2256191","tgn:1000001","tgn:7006451","tgn:2000093","tgn:7012149","tgn:7029392"],"placetype":["aat:300008761"],"id":2256191,"name:xx":"Copper Springs Canyon"}}
>>>>>>> 03f74aca74312dbeaf24d7e61306dd6a786dc3d0
