{
  "id": 2202733,
  "type": "Feature",
  "properties": {
    "tgn:hierarchy":[
        "tgn:2202733",
        "tgn:1000001",
        "tgn:2001418",
        "tgn:7012149",
        "tgn:7007526",
        "tgn:7029392"
    ],
    "tgn:id":2202733,
    "tgn:name":"Buckboard Mesa",
    "tgn:placetype":[
        "aat:300008798"
    ]
},
  "bbox": [],
  "geometry": {"coordinates":[-116.3667,37.1167],"type":"Point"}
}