{
  "id": 2295805,
  "type": "Feature",
  "properties": {
    "tgn:hierarchy":[
        "tgn:2295805",
        "tgn:1000001",
        "tgn:7012149",
        "tgn:2000891",
        "tgn:7007256",
        "tgn:7029392"
    ],
    "tgn:id":2295805,
    "tgn:name":"Drum Island",
    "tgn:placetype":[
        "aat:300008791"
    ]
},
  "bbox": [],
  "geometry": {"coordinates":[-89.65,29.5333],"type":"Point"}
}