{
  "id": 7043026,
  "type": "Feature",
  "properties": {
    "tgn:hierarchy":[
        "tgn:7043026",
        "tgn:1000003",
        "tgn:7003142",
        "tgn:7003236",
        "tgn:1000080",
        "tgn:7029392"
    ],
    "tgn:id":7043026,
    "tgn:name":"Reppia",
    "tgn:placetype":[
        "aat:300008347"
    ]
},
  "bbox": [],
  "geometry": {"coordinates":[9.45,44.366667],"type":"Point"}
}