{
  "id": 7364537,
  "type": "Feature",
  "properties": {
    "tgn:hierarchy":[
        "tgn:7364537",
        "tgn:7005581",
        "tgn:1000001",
        "tgn:7005560",
        "tgn:7029392"
    ],
    "tgn:id":7364537,
    "tgn:name":"El Presidio",
    "tgn:placetype":[
        "aat:300008347"
    ]
},
  "bbox": [],
  "geometry": {"coordinates":[-105.316667,27.583333],"type":"Point"}
}