{
  "id": 2656697,
  "type": "Feature",
  "properties": {
    "tgn:hierarchy":[
        "tgn:2656697",
        "tgn:1000001",
        "tgn:7012149",
        "tgn:2001310",
        "tgn:7007524",
        "tgn:7029392"
    ],
    "tgn:id":2656697,
    "tgn:name":"Sheep Creek",
    "tgn:placetype":[
        "aat:300008706"
    ]
},
  "bbox": [],
  "geometry": {"coordinates":[-111.35,48.8333],"type":"Point"}
}