{
  "id": 2749616,
  "type": "Feature",
  "properties": {
    "tgn:hierarchy":[
        "tgn:2749616",
        "tgn:1000001",
        "tgn:1002259",
        "tgn:7012149",
        "tgn:7007568",
        "tgn:7029392"
    ],
    "tgn:id":2749616,
    "tgn:name":"Walnut Creek",
    "tgn:placetype":[
        "aat:300008706"
    ]
},
  "bbox": [],
  "geometry": {"coordinates":[-79.2167,42.4167],"type":"Point"}
}