<<<<<<< HEAD
{
  "id": 7487704,
  "type": "Feature",
  "properties": {
    "tgn:hierarchy":[
        "tgn:7487704",
        "tgn:7488858",
        "tgn:1000004",
        "tgn:1000141",
        "tgn:7029392"
    ],
    "tgn:id":7487704,
    "tgn:name":"Liufenliao",
    "tgn:placetype":[
        "aat:300008347"
    ]
},
  "bbox": [],
  "geometry": {"coordinates":[120.636913,23.929246],"type":"Point"}
}
=======
{"geometry":{"type":"Point","coordinates":[120.636913,23.929246]},"type":"Feature","properties":{"hierarchy":["tgn:7487704","tgn:7488858","tgn:1000004","tgn:1000141","tgn:7029392"],"placetype":["aat:300008347"],"id":7487704,"name:xx":"Liufenliao"}}
>>>>>>> 03f74aca74312dbeaf24d7e61306dd6a786dc3d0
