{
  "id": 2646760,
  "type": "Feature",
  "properties": {
    "tgn:hierarchy":[
        "tgn:2646760",
        "tgn:1000001",
        "tgn:7012149",
        "tgn:2000891",
        "tgn:7007256",
        "tgn:7029392"
    ],
    "tgn:id":2646760,
    "tgn:name":"Scarabin Island",
    "tgn:placetype":[
        "aat:300008791"
    ]
},
  "bbox": [],
  "geometry": {"coordinates":[-89.15,29.25],"type":"Point"}
}