{
  "id": 2608432,
  "type": "Feature",
  "properties": {
    "tgn:hierarchy":[
        "tgn:2608432",
        "tgn:1000001",
        "tgn:7012149",
        "tgn:7007157",
        "tgn:1002856",
        "tgn:7029392"
    ],
    "tgn:id":2608432,
    "tgn:name":"Rattlesnake Gulch",
    "tgn:placetype":[
        "aat:300008761"
    ]
},
  "bbox": [],
  "geometry": {"coordinates":[-120.75,36.2833],"type":"Point"}
}