<<<<<<< HEAD
{
  "id": 7248100,
  "type": "Feature",
  "properties": {
    "tgn:hierarchy":[
        "tgn:7248100",
        "tgn:7003458",
        "tgn:1000003",
        "tgn:1000063",
        "tgn:7018236",
        "tgn:7029392"
    ],
    "tgn:id":7248100,
    "tgn:name":"Belhutte",
    "tgn:placetype":[
        "aat:300008347"
    ]
},
  "bbox": [],
  "geometry": {"coordinates":[2.987473,51.074734],"type":"Point"}
}
=======
{"geometry":{"type":"Point","coordinates":[2.987473,51.074734]},"type":"Feature","properties":{"hierarchy":["tgn:7248100","tgn:7003458","tgn:1000003","tgn:1000063","tgn:7018236","tgn:7029392"],"placetype":["aat:300008347"],"id":7248100,"name:xx":"Belhutte"}}
>>>>>>> 03f74aca74312dbeaf24d7e61306dd6a786dc3d0
