{
  "id": 2617160,
  "type": "Feature",
  "properties": {
    "tgn:hierarchy":[
        "tgn:2617160",
        "tgn:2002308",
        "tgn:1000001",
        "tgn:7012149",
        "tgn:7007922",
        "tgn:7029392"
    ],
    "tgn:id":2617160,
    "tgn:name":"Richardson Lake",
    "tgn:placetype":[
        "aat:300008680"
    ]
},
  "bbox": [],
  "geometry": {"coordinates":[-91.45,46.5333],"type":"Point"}
}