{
  "id": 2571521,
  "type": "Feature",
  "properties": {
    "tgn:hierarchy":[
        "tgn:2571521",
        "tgn:1000001",
        "tgn:2002136",
        "tgn:7012149",
        "tgn:7007828",
        "tgn:7029392"
    ],
    "tgn:id":2571521,
    "tgn:name":"Pauls Peak",
    "tgn:placetype":[
        "aat:300008798"
    ]
},
  "bbox": [],
  "geometry": {"coordinates":[-72.7167,43.8333],"type":"Point"}
}