{
  "id": 7233329,
  "type": "Feature",
  "properties": {
    "tgn:hierarchy":[
        "tgn:7233329",
        "tgn:7011170",
        "tgn:7002715",
        "tgn:1000003",
        "tgn:1000074",
        "tgn:7029392"
    ],
    "tgn:id":7233329,
    "tgn:name":"Dhorik\u00f3n",
    "tgn:placetype":[
        "aat:300008347"
    ]
},
  "bbox": [],
  "geometry": {"coordinates":[25.983333,40.916667],"type":"Point"}
}