{
  "id": 2365888,
  "type": "Feature",
  "properties": {
    "tgn:hierarchy":[
        "tgn:2365888",
        "tgn:1000001",
        "tgn:7012149",
        "tgn:1002723",
        "tgn:7007252",
        "tgn:7029392"
    ],
    "tgn:id":2365888,
    "tgn:name":"Gretzinger Ditch",
    "tgn:placetype":[
        "aat:300006075"
    ]
},
  "bbox": [],
  "geometry": {"coordinates":[-85.3333,41.4333],"type":"Point"}
}