<<<<<<< HEAD
{
  "id": 2254218,
  "type": "Feature",
  "properties": {
    "tgn:hierarchy":[
        "tgn:2254218",
        "tgn:1000001",
        "tgn:7006451",
        "tgn:7012149",
        "tgn:2000097",
        "tgn:7029392"
    ],
    "tgn:id":2254218,
    "tgn:name":"Coon Bluff",
    "tgn:placetype":[
        "aat:300008798"
    ]
},
  "bbox": [],
  "geometry": {"coordinates":[-111.6333,33.5333],"type":"Point"}
}
=======
{"geometry":{"type":"Point","coordinates":[-111.633300,33.533300]},"type":"Feature","properties":{"hierarchy":["tgn:2254218","tgn:1000001","tgn:7006451","tgn:7012149","tgn:2000097","tgn:7029392"],"placetype":["aat:300008798"],"id":2254218,"name:xx":"Coon Bluff"}}
>>>>>>> 03f74aca74312dbeaf24d7e61306dd6a786dc3d0
