{
  "id": 2485681,
  "type": "Feature",
  "properties": {
    "tgn:hierarchy":[
        "tgn:2485681",
        "tgn:1000001",
        "tgn:7012149",
        "tgn:2002289",
        "tgn:7013961",
        "tgn:7029392"
    ],
    "tgn:id":2485681,
    "tgn:name":"Laywell Branch",
    "tgn:placetype":[
        "aat:300008699"
    ]
},
  "bbox": [],
  "geometry": {"coordinates":[-82.0333,38.3667],"type":"Point"}
}