{
  "id": 7400268,
  "type": "Feature",
  "properties": {
    "tgn:hierarchy":[
        "tgn:7400268",
        "tgn:1000001",
        "tgn:7005599",
        "tgn:7005560",
        "tgn:7029392"
    ],
    "tgn:id":7400268,
    "tgn:name":"Gustavo D\u00edaz Ordaz",
    "tgn:placetype":[
        "aat:300008347"
    ]
},
  "bbox": [],
  "geometry": {"coordinates":[-94.183333,17.675],"type":"Point"}
}