{
  "id": 1064500,
  "type": "Feature",
  "properties": {
    "tgn:hierarchy":[
        "tgn:1064500",
        "tgn:1000003",
        "tgn:7003762",
        "tgn:7011731",
        "tgn:7029392"
    ],
    "tgn:id":1064500,
    "tgn:name":"Vouvry",
    "tgn:placetype":[
        "aat:300008347"
    ]
},
  "bbox": [],
  "geometry": {"coordinates":[6.8833,46.35],"type":"Point"}
}