{
  "id": 2102164,
  "type": "Feature",
  "properties": {
    "tgn:hierarchy":[
        "tgn:2102164",
        "tgn:1000001",
        "tgn:7012149",
        "tgn:2001861",
        "tgn:7007825",
        "tgn:7029392"
    ],
    "tgn:id":2102164,
    "tgn:name":"Wolf River",
    "tgn:placetype":[
        "aat:300008347",
        "aat:300387210"
    ]
},
  "bbox": [],
  "geometry": {"coordinates":[-84.95,36.5333],"type":"Point"}
}