{
  "id": 7374402,
  "type": "Feature",
  "properties": {
    "tgn:hierarchy":[
        "tgn:7374402",
        "tgn:1000001",
        "tgn:1001906",
        "tgn:7005560",
        "tgn:7029392"
    ],
    "tgn:id":7374402,
    "tgn:name":"La Concha",
    "tgn:placetype":[
        "aat:300008347"
    ]
},
  "bbox": [],
  "geometry": {"coordinates":[-105.483333,21.766667],"type":"Point"}
}