{
  "id": 7211573,
  "type": "Feature",
  "properties": {
    "tgn:hierarchy":[
        "tgn:7211573",
        "tgn:7000096",
        "tgn:1000003",
        "tgn:7000084",
        "tgn:7029392"
    ],
    "tgn:id":7211573,
    "tgn:name":"Behlendorfer Wald",
    "tgn:placetype":[
        "aat:300008863"
    ]
},
  "bbox": [],
  "geometry": {"coordinates":[14.216667,52.483333],"type":"Point"}
}