{
  "id": 7012308,
  "type": "Feature",
  "properties": {
    "tgn:hierarchy":[
        "tgn:7012308",
        "tgn:1000003",
        "tgn:7003687",
        "tgn:7000084",
        "tgn:7029392"
    ],
    "tgn:id":7012308,
    "tgn:name":"Bilzingsleben",
    "tgn:placetype":[
        "aat:300008347"
    ]
},
  "bbox": [],
  "geometry": {"coordinates":[11.066667,51.283333],"type":"Point"}
}