{
  "id": 2536064,
  "type": "Feature",
  "properties": {
    "tgn:hierarchy":[
        "tgn:2536064",
        "tgn:1000001",
        "tgn:7012149",
        "tgn:2002119",
        "tgn:7007827",
        "tgn:7029392"
    ],
    "tgn:id":2536064,
    "tgn:name":"Natural Bridge",
    "tgn:placetype":[
        "aat:300386837"
    ]
},
  "bbox": [],
  "geometry": {"coordinates":[-109.7167,37.9833],"type":"Point"}
}