<<<<<<< HEAD
{
  "id": 7020397,
  "type": "Feature",
  "properties": {
    "tgn:hierarchy":[
        "tgn:7020397",
        "tgn:1000001",
        "tgn:1002714",
        "tgn:7012149",
        "tgn:7007159",
        "tgn:7029392"
    ],
    "tgn:id":7020397,
    "tgn:name":"Avery Corner",
    "tgn:placetype":[
        "aat:300008347"
    ]
},
  "bbox": [],
  "geometry": {"coordinates":[-72.2,41.5833],"type":"Point"}
}
=======
{"geometry":{"type":"Point","coordinates":[-72.200000,41.583300]},"type":"Feature","properties":{"hierarchy":["tgn:7020397","tgn:1000001","tgn:1002714","tgn:7012149","tgn:7007159","tgn:7029392"],"placetype":["aat:300008347"],"id":7020397,"name:xx":"Avery Corner"}}
>>>>>>> 03f74aca74312dbeaf24d7e61306dd6a786dc3d0
