{
  "id": 2544969,
  "type": "Feature",
  "properties": {
    "tgn:hierarchy":[
        "tgn:2544969",
        "tgn:1000001",
        "tgn:7012149",
        "tgn:7007158",
        "tgn:2000246",
        "tgn:7029392"
    ],
    "tgn:id":2544969,
    "tgn:name":"North Crestone Ditch",
    "tgn:placetype":[
        "aat:300006075"
    ]
},
  "bbox": [],
  "geometry": {"coordinates":[-105.7833,37.9667],"type":"Point"}
}