{
  "id": 2332115,
  "type": "Feature",
  "properties": {
    "tgn:hierarchy":[
        "tgn:2332115",
        "tgn:1000001",
        "tgn:7012149",
        "tgn:2000218",
        "tgn:7007158",
        "tgn:7029392"
    ],
    "tgn:id":2332115,
    "tgn:name":"Flint Lakes",
    "tgn:placetype":[
        "aat:300008680"
    ]
},
  "bbox": [],
  "geometry": {"coordinates":[-107.4333,37.6167],"type":"Point"}
}