<<<<<<< HEAD
{
  "id": 2701992,
  "type": "Feature",
  "properties": {
    "tgn:hierarchy":[
        "tgn:2701992",
        "tgn:1000001",
        "tgn:2000459",
        "tgn:7012149",
        "tgn:7007250",
        "tgn:7029392"
    ],
    "tgn:id":2701992,
    "tgn:name":"Sugarloaf Rock",
    "tgn:placetype":[
        "aat:300008798"
    ]
},
  "bbox": [],
  "geometry": {"coordinates":[-116.05,43.8333],"type":"Point"}
}
=======
{"geometry":{"type":"Point","coordinates":[-116.050000,43.833300]},"type":"Feature","properties":{"hierarchy":["tgn:2701992","tgn:1000001","tgn:2000459","tgn:7012149","tgn:7007250","tgn:7029392"],"placetype":["aat:300008798"],"id":2701992,"name:xx":"Sugarloaf Rock"}}
>>>>>>> 03f74aca74312dbeaf24d7e61306dd6a786dc3d0
