{
  "id": 1075529,
  "type": "Feature",
  "properties": {
    "tgn:hierarchy":[
        "tgn:1075529",
        "tgn:1000004",
        "tgn:7000198",
        "tgn:7016722",
        "tgn:7029392"
    ],
    "tgn:id":1075529,
    "tgn:name:en":"Itwa",
    "tgn:placetype":[
        "aat:300008347"
    ]
},
  "bbox": [],
  "geometry": {"coordinates":[82.696216,27.330572],"type":"Point"}
}