{
  "id": 2391711,
  "type": "Feature",
  "properties": {
    "tgn:hierarchy":[
        "tgn:2391711",
        "tgn:1000001",
        "tgn:7012149",
        "tgn:2001283",
        "tgn:7007524",
        "tgn:7029392"
    ],
    "tgn:id":2391711,
    "tgn:name":"Hillside Ditch",
    "tgn:placetype":[
        "aat:300006075"
    ]
},
  "bbox": [],
  "geometry": {"coordinates":[-114.2667,47.3833],"type":"Point"}
}