{
  "id": 2292097,
  "type": "Feature",
  "properties": {
    "tgn:hierarchy":[
        "tgn:2292097",
        "tgn:2002142",
        "tgn:1000001",
        "tgn:7012149",
        "tgn:7007919",
        "tgn:7029392"
    ],
    "tgn:id":2292097,
    "tgn:name":"Donald Fauber Mountain",
    "tgn:placetype":[
        "aat:300008798"
    ]
},
  "bbox": [],
  "geometry": {"coordinates":[-79.0333,37.95],"type":"Point"}
}