{
  "id": 2105993,
  "type": "Feature",
  "properties": {
    "tgn:hierarchy":[
        "tgn:2105993",
        "tgn:1000001",
        "tgn:7012149",
        "tgn:1002291",
        "tgn:7007826",
        "tgn:7029392"
    ],
    "tgn:id":2105993,
    "tgn:name":"Mentz",
    "tgn:placetype":[
        "aat:300008347",
        "aat:300387210"
    ]
},
  "bbox": [],
  "geometry": {"coordinates":[-96.4333,29.75],"type":"Point"}
}