{
  "id": 2390289,
  "type": "Feature",
  "properties": {
    "tgn:hierarchy":[
        "tgn:2390289",
        "tgn:1000001",
        "tgn:7012149",
        "tgn:2000987",
        "tgn:7007520",
        "tgn:7029392"
    ],
    "tgn:id":2390289,
    "tgn:name":"Highland",
    "tgn:placetype":[
        "aat:300008347"
    ]
},
  "bbox": [],
  "geometry": {"coordinates":[-85.25,44.1333],"type":"Point"}
}