{
  "id": 7044967,
  "type": "Feature",
  "properties": {
    "tgn:hierarchy":[
        "tgn:7044967",
        "tgn:7003164",
        "tgn:1000003",
        "tgn:7009760",
        "tgn:1000080",
        "tgn:7029392"
    ],
    "tgn:id":7044967,
    "tgn:name":"Forte di Bibbona",
    "tgn:placetype":[
        "aat:300008347"
    ]
},
  "bbox": [],
  "geometry": {"coordinates":[10.516667,43.233333],"type":"Point"}
}