{
  "id": 7416742,
  "type": "Feature",
  "properties": {
    "tgn:hierarchy":[
        "tgn:7416742",
        "tgn:7005584",
        "tgn:1000001",
        "tgn:7005560",
        "tgn:7029392"
    ],
    "tgn:id":7416742,
    "tgn:name":"Presa El Coyote",
    "tgn:placetype":[
        "aat:300006191"
    ]
},
  "bbox": [],
  "geometry": {"coordinates":[-101.585833,20.63],"type":"Point"}
}