{
  "id": 2542777,
  "type": "Feature",
  "properties": {
    "tgn:hierarchy":[
        "tgn:2542777",
        "tgn:1000001",
        "tgn:7006451",
        "tgn:7012149",
        "tgn:2000098",
        "tgn:7029392"
    ],
    "tgn:id":2542777,
    "tgn:name":"Nogales Spring",
    "tgn:placetype":[
        "aat:300008697"
    ]
},
  "bbox": [],
  "geometry": {"coordinates":[-110.4667,31.8667],"type":"Point"}
}