{
  "id": 2662087,
  "type": "Feature",
  "properties": {
    "tgn:hierarchy":[
        "tgn:2662087",
        "tgn:1000001",
        "tgn:1002377",
        "tgn:7012149",
        "tgn:7007251",
        "tgn:7029392"
    ],
    "tgn:id":2662087,
    "tgn:name":"Sibley, Lake",
    "tgn:placetype":[
        "aat:300008680"
    ]
},
  "bbox": [],
  "geometry": {"coordinates":[-88.3833,40.5833],"type":"Point"}
}