{
  "id": 7531524,
  "type": "Feature",
  "properties": {
    "tgn:hierarchy":[
        "tgn:7531524",
        "tgn:7001242",
        "tgn:7016833",
        "tgn:7001335",
        "tgn:7029392"
    ],
    "tgn:id":7531524,
    "tgn:name":"Qaryat at Til\u016bl",
    "tgn:placetype":[
        "aat:300008347"
    ]
},
  "bbox": [],
  "geometry": {"coordinates":[33.223333,31.052222],"type":"Point"}
}