{
  "id": 7035000,
  "type": "Feature",
  "properties": {
    "tgn:hierarchy":[
        "tgn:7035000",
        "tgn:1003506",
        "tgn:1000003",
        "tgn:7002993",
        "tgn:1000080",
        "tgn:7029392"
    ],
    "tgn:id":7035000,
    "tgn:name":"Priuso",
    "tgn:placetype":[
        "aat:300008347"
    ]
},
  "bbox": [],
  "geometry": {"coordinates":[12.813889,46.400833],"type":"Point"}
}