{
  "id": 2677567,
  "type": "Feature",
  "properties": {
    "tgn:hierarchy":[
        "tgn:2677567",
        "tgn:1000001",
        "tgn:7012149",
        "tgn:1002518",
        "tgn:7007568",
        "tgn:7029392"
    ],
    "tgn:id":2677567,
    "tgn:name":"South Colwell Pond",
    "tgn:placetype":[
        "aat:300008680"
    ]
},
  "bbox": [],
  "geometry": {"coordinates":[-76.1833,43.6833],"type":"Point"}
}