{
  "id": 2280670,
  "type": "Feature",
  "properties": {
    "tgn:hierarchy":[
        "tgn:2280670",
        "tgn:1000001",
        "tgn:7012149",
        "tgn:2001456",
        "tgn:7007566",
        "tgn:7029392"
    ],
    "tgn:id":2280670,
    "tgn:name":"Deep Canyon Tank",
    "tgn:placetype":[
        "aat:300006191"
    ]
},
  "bbox": [],
  "geometry": {"coordinates":[-107.3167,33.7333],"type":"Point"}
}