{
  "id": 2127799,
  "type": "Feature",
  "properties": {
    "tgn:hierarchy":[
        "tgn:2127799",
        "tgn:1000001",
        "tgn:7012149",
        "tgn:7007826",
        "tgn:7029392"
    ],
    "tgn:id":2127799,
    "tgn:name":"Alamo de Cesario Creek",
    "tgn:placetype":[
        "aat:300008706"
    ]
},
  "bbox": [],
  "geometry": {"coordinates":[-103.85,29.5833],"type":"Point"}
}