{
  "id": 7127348,
  "type": "Feature",
  "properties": {
    "tgn:hierarchy":[
        "tgn:7127348",
        "tgn:1000003",
        "tgn:7003676",
        "tgn:7000084",
        "tgn:7029392"
    ],
    "tgn:id":7127348,
    "tgn:name":"Nindorf",
    "tgn:placetype":[
        "aat:300008347"
    ]
},
  "bbox": [],
  "geometry": {"coordinates":[9.65,53.416667],"type":"Point"}
}