<<<<<<< HEAD
{
  "id": 7355386,
  "type": "Feature",
  "properties": {
    "tgn:hierarchy":[
        "tgn:7355386",
        "tgn:1000001",
        "tgn:1001906",
        "tgn:7005560",
        "tgn:7029392"
    ],
    "tgn:id":7355386,
    "tgn:name":"Cegada, Boca el",
    "tgn:placetype":[
        "aat:300387057"
    ]
},
  "bbox": [],
  "geometry": {"coordinates":[-105.4,21.583333],"type":"Point"}
}
=======
{"geometry":{"type":"Point","coordinates":[-105.400000,21.583333]},"type":"Feature","properties":{"hierarchy":["tgn:7355386","tgn:1000001","tgn:1001906","tgn:7005560","tgn:7029392"],"placetype":["aat:300387057"],"id":7355386,"name:xx":"Cegada, Boca el"}}
>>>>>>> 03f74aca74312dbeaf24d7e61306dd6a786dc3d0
