{
  "id": 2674158,
  "type": "Feature",
  "properties": {
    "tgn:hierarchy":[
        "tgn:2674158",
        "tgn:1000001",
        "tgn:7012149",
        "tgn:2001437",
        "tgn:7007566",
        "tgn:7029392"
    ],
    "tgn:id":2674158,
    "tgn:name":"Snowflake Canyon",
    "tgn:placetype":[
        "aat:300008761"
    ]
},
  "bbox": [],
  "geometry": {"coordinates":[-108.05,32.8333],"type":"Point"}
}