{
  "id": 2586161,
  "type": "Feature",
  "properties": {
    "tgn:hierarchy":[
        "tgn:2586161",
        "tgn:7006450",
        "tgn:1000001",
        "tgn:7012149",
        "tgn:2124005",
        "tgn:7029392"
    ],
    "tgn:id":2586161,
    "tgn:name":"Pisiksagiavik Creek",
    "tgn:placetype":[
        "aat:300008706"
    ]
},
  "bbox": [],
  "geometry": {"coordinates":[-157.3667,70.0333],"type":"Point"}
}