<<<<<<< HEAD
{
  "id": 7055819,
  "type": "Feature",
  "properties": {
    "tgn:hierarchy":[
        "tgn:7055819",
        "tgn:1003450",
        "tgn:7007850",
        "tgn:1000003",
        "tgn:1000080",
        "tgn:7029392"
    ],
    "tgn:id":7055819,
    "tgn:name":"Plataci",
    "tgn:placetype":[
        "aat:300008347"
    ]
},
  "bbox": [],
  "geometry": {"coordinates":[16.433333,39.9],"type":"Point"}
}
=======
{"geometry":{"type":"Point","coordinates":[16.433333,39.900000]},"type":"Feature","properties":{"hierarchy":["tgn:7055819","tgn:1003450","tgn:7007850","tgn:1000003","tgn:1000080","tgn:7029392"],"placetype":["aat:300008347"],"id":7055819,"name:xx":"Plataci"}}
>>>>>>> 03f74aca74312dbeaf24d7e61306dd6a786dc3d0
