{
  "id": 2154801,
  "type": "Feature",
  "properties": {
    "tgn:hierarchy":[
        "tgn:2154801",
        "tgn:1000001",
        "tgn:7012149",
        "tgn:2000931",
        "tgn:7007515",
        "tgn:7029392"
    ],
    "tgn:id":2154801,
    "tgn:name":"Bear Hill",
    "tgn:placetype":[
        "aat:300008798"
    ]
},
  "bbox": [],
  "geometry": {"coordinates":[-69.0333,44.55],"type":"Point"}
}