<<<<<<< HEAD
{
  "id": 2154801,
  "type": "Feature",
  "properties": {
    "tgn:hierarchy":[
        "tgn:2154801",
        "tgn:1000001",
        "tgn:7012149",
        "tgn:2000931",
        "tgn:7007515",
        "tgn:7029392"
    ],
    "tgn:id":2154801,
    "tgn:name":"Bear Hill",
    "tgn:placetype":[
        "aat:300008798"
    ]
},
  "bbox": [],
  "geometry": {"coordinates":[-69.0333,44.55],"type":"Point"}
}
=======
{"geometry":{"type":"Point","coordinates":[-69.033300,44.550000]},"type":"Feature","properties":{"hierarchy":["tgn:2154801","tgn:1000001","tgn:7012149","tgn:2000931","tgn:7007515","tgn:7029392"],"placetype":["aat:300008798"],"id":2154801,"name:xx":"Bear Hill"}}
>>>>>>> 03f74aca74312dbeaf24d7e61306dd6a786dc3d0
