{
  "id": 7143410,
  "type": "Feature",
  "properties": {
    "tgn:hierarchy":[
        "tgn:7143410",
        "tgn:1000003",
        "tgn:7000094",
        "tgn:7000084",
        "tgn:7029392"
    ],
    "tgn:id":7143410,
    "tgn:name":"Lubkow",
    "tgn:placetype":[
        "aat:300008347"
    ]
},
  "bbox": [],
  "geometry": {"coordinates":[13.55,54.416667],"type":"Point"}
}