{
  "id": 2145126,
  "type": "Feature",
  "properties": {
    "tgn:hierarchy":[
        "tgn:2145126",
        "tgn:1000001",
        "tgn:7012149",
        "tgn:2000928",
        "tgn:7007515",
        "tgn:7029392"
    ],
    "tgn:id":2145126,
    "tgn:name":"Bald Mountain",
    "tgn:placetype":[
        "aat:300008798"
    ]
},
  "bbox": [],
  "geometry": {"coordinates":[-68.9833,45.9833],"type":"Point"}
}