{
  "id": 2353124,
  "type": "Feature",
  "properties": {
    "tgn:hierarchy":[
        "tgn:2353124",
        "tgn:1000001",
        "tgn:7012149",
        "tgn:2000933",
        "tgn:7007515",
        "tgn:7029392"
    ],
    "tgn:id":2353124,
    "tgn:name":"Goff Mill Brook",
    "tgn:placetype":[
        "aat:300008699"
    ]
},
  "bbox": [],
  "geometry": {"coordinates":[-70.4667,43.45],"type":"Point"}
}