<<<<<<< HEAD
{
  "id": 2336369,
  "type": "Feature",
  "properties": {
    "tgn:hierarchy":[
        "tgn:2336369",
        "tgn:1000001",
        "tgn:7012149",
        "tgn:2001254",
        "tgn:7007523",
        "tgn:7029392"
    ],
    "tgn:id":2336369,
    "tgn:name":"Fountain Farm Branch",
    "tgn:placetype":[
        "aat:300008699"
    ]
},
  "bbox": [],
  "geometry": {"coordinates":[-90.75,37.95],"type":"Point"}
}
=======
{"geometry":{"type":"Point","coordinates":[-90.750000,37.950000]},"type":"Feature","properties":{"hierarchy":["tgn:2336369","tgn:1000001","tgn:7012149","tgn:2001254","tgn:7007523","tgn:7029392"],"placetype":["aat:300008699"],"id":2336369,"name:xx":"Fountain Farm Branch"}}
>>>>>>> 03f74aca74312dbeaf24d7e61306dd6a786dc3d0
