{
  "id": 2376049,
  "type": "Feature",
  "properties": {
    "tgn:hierarchy":[
        "tgn:2376049",
        "tgn:1000001",
        "tgn:7012149",
        "tgn:7018871",
        "tgn:7007920",
        "tgn:7029392"
    ],
    "tgn:id":2376049,
    "tgn:name":"Harbor Heights",
    "tgn:placetype":[
        "aat:300008347"
    ]
},
  "bbox": [],
  "geometry": {"coordinates":[-122.4833,47.3667],"type":"Point"}
}