<<<<<<< HEAD
{
  "id": 2254140,
  "type": "Feature",
  "properties": {
    "tgn:hierarchy":[
        "tgn:2254140",
        "tgn:7014651",
        "tgn:1000001",
        "tgn:7012149",
        "tgn:7007516",
        "tgn:7029392"
    ],
    "tgn:id":2254140,
    "tgn:name":"Cooleys Pond",
    "tgn:placetype":[
        "aat:300008680"
    ]
},
  "bbox": [],
  "geometry": {"coordinates":[-76.4333,39.0667],"type":"Point"}
}
=======
{"geometry":{"type":"Point","coordinates":[-76.433300,39.066700]},"type":"Feature","properties":{"hierarchy":["tgn:2254140","tgn:7014651","tgn:1000001","tgn:7012149","tgn:7007516","tgn:7029392"],"placetype":["aat:300008680"],"id":2254140,"name:xx":"Cooleys Pond"}}
>>>>>>> 03f74aca74312dbeaf24d7e61306dd6a786dc3d0
