{
  "id": 7203939,
  "type": "Feature",
  "properties": {
    "tgn:hierarchy":[
        "tgn:7203939",
        "tgn:1000003",
        "tgn:7003689",
        "tgn:7000084",
        "tgn:7029392"
    ],
    "tgn:id":7203939,
    "tgn:name":"B\u00f6rthen",
    "tgn:placetype":[
        "aat:300008347"
    ]
},
  "bbox": [],
  "geometry": {"coordinates":[11.733333,50.75],"type":"Point"}
}