{
  "id": 7563550,
  "type": "Feature",
  "properties": {
    "tgn:hierarchy":[
        "tgn:7563550",
        "tgn:1000004",
        "tgn:7000198",
        "tgn:1001894",
        "tgn:7029392"
    ],
    "tgn:id":7563550,
    "tgn:name:en":"Prahl\u0101dpura Reserved Forest",
    "tgn:placetype":[
        "aat:300008865"
    ]
},
  "bbox": [],
  "geometry": {"coordinates":[79.042469,24.004411],"type":"Point"}
}