{
  "id": 7462680,
  "type": "Feature",
  "properties": {
    "tgn:hierarchy":[
        "tgn:7462680",
        "tgn:7002444",
        "tgn:1000003",
        "tgn:7008076",
        "tgn:7008591",
        "tgn:7029392"
    ],
    "tgn:id":7462680,
    "tgn:name:en":"Inchkeith",
    "tgn:placetype":[
        "aat:300008791"
    ]
},
  "bbox": [],
  "geometry": {"coordinates":[-3.133333,56.033333],"type":"Point"}
}