{
  "id": 2522313,
  "type": "Feature",
  "properties": {
    "tgn:hierarchy":[
        "tgn:2522313",
        "tgn:1000001",
        "tgn:7012149",
        "tgn:1002463",
        "tgn:7007826",
        "tgn:7029392"
    ],
    "tgn:id":2522313,
    "tgn:name":"Moon Mountain",
    "tgn:placetype":[
        "aat:300008798"
    ]
},
  "bbox": [],
  "geometry": {"coordinates":[-98.15,29.95],"type":"Point"}
}