{
  "id": 2228553,
  "type": "Feature",
  "properties": {
    "tgn:hierarchy":[
        "tgn:2228553",
        "tgn:1002149",
        "tgn:1000001",
        "tgn:7012149",
        "tgn:7007826",
        "tgn:7029392"
    ],
    "tgn:id":2228553,
    "tgn:name":"Cedar Creek",
    "tgn:placetype":[
        "aat:300008706"
    ]
},
  "bbox": [],
  "geometry": {"coordinates":[-94.7333,31.35],"type":"Point"}
}