{
  "id": 7291495,
  "type": "Feature",
  "properties": {
    "tgn:hierarchy":[
        "tgn:7291495",
        "tgn:1001637",
        "tgn:1000049",
        "tgn:1000002",
        "tgn:7029392"
    ],
    "tgn:id":7291495,
    "tgn:name":"El Quillay",
    "tgn:placetype":[
        "aat:300008347"
    ]
},
  "bbox": [],
  "geometry": {"coordinates":[-72.566667,-36.733333],"type":"Point"}
}