{
  "id": 2368648,
  "type": "Feature",
  "properties": {
    "tgn:hierarchy":[
        "tgn:2368648",
        "tgn:1000001",
        "tgn:7012149",
        "tgn:7016021",
        "tgn:7007568",
        "tgn:7029392"
    ],
    "tgn:id":2368648,
    "tgn:name":"Gulf Stream",
    "tgn:placetype":[
        "aat:300008699"
    ]
},
  "bbox": [],
  "geometry": {"coordinates":[-75.1167,44.1667],"type":"Point"}
}