{
  "id": 2555238,
  "type": "Feature",
  "properties": {
    "tgn:hierarchy":[
        "tgn:2555238",
        "tgn:1000001",
        "tgn:7012149",
        "tgn:7007240",
        "tgn:7029392"
    ],
    "tgn:id":2555238,
    "tgn:name":"Ocklawaha Creek",
    "tgn:placetype":[
        "aat:300008706"
    ]
},
  "bbox": [],
  "geometry": {"coordinates":[-84.7833,30.4833],"type":"Point"}
}