{
  "id": 7529799,
  "type": "Feature",
  "properties": {
    "tgn:hierarchy":[
        "tgn:7529799",
        "tgn:7001242",
        "tgn:7016833",
        "tgn:1001091",
        "tgn:7029392"
    ],
    "tgn:id":7529799,
    "tgn:name":"Kan\u012bsat S\u0101n M\u0101rk",
    "tgn:placetype":[
        "aat:300007466"
    ]
},
  "bbox": [],
  "geometry": {"coordinates":[31.231948,30.005061],"type":"Point"}
}