{
  "id": 1024158,
  "type": "Feature",
  "properties": {
    "tgn:hierarchy":[
        "tgn:1024158",
        "tgn:7593311",
        "tgn:1001211",
        "tgn:7002561",
        "tgn:1000051",
        "tgn:1000002",
        "tgn:7029392"
    ],
    "tgn:id":1024158,
    "tgn:name":"San Miguel de Salcedo",
    "tgn:placetype":[
        "aat:300008347"
    ]
},
  "bbox": [],
  "geometry": {"coordinates":[-78.59,-1.045],"type":"Point"}
}