{
  "id": 2647237,
  "type": "Feature",
  "properties": {
    "tgn:hierarchy":[
        "tgn:2647237",
        "tgn:1000001",
        "tgn:7012149",
        "tgn:2002335",
        "tgn:7007922",
        "tgn:7029392"
    ],
    "tgn:id":2647237,
    "tgn:name":"Schisel Lake",
    "tgn:placetype":[
        "aat:300008680"
    ]
},
  "bbox": [],
  "geometry": {"coordinates":[-87.8167,44.1167],"type":"Point"}
}