{
  "id": 7459425,
  "type": "Feature",
  "properties": {
    "tgn:hierarchy":[
        "tgn:7459425",
        "tgn:7002444",
        "tgn:1000003",
        "tgn:5000451",
        "tgn:7008591",
        "tgn:7029392"
    ],
    "tgn:id":7459425,
    "tgn:name:en":"Orton Station",
    "tgn:placetype":[
        "aat:300007783"
    ]
},
  "bbox": [],
  "geometry": {"coordinates":[-3.15,57.55],"type":"Point"}
}