{
  "id": 7408325,
  "type": "Feature",
  "properties": {
    "tgn:hierarchy":[
        "tgn:7408325",
        "tgn:1000001",
        "tgn:1001893",
        "tgn:7005560",
        "tgn:7029392"
    ],
    "tgn:id":7408325,
    "tgn:name":"Salado, R\u00edo",
    "tgn:placetype":[
        "aat:300008699"
    ]
},
  "bbox": [],
  "geometry": {"coordinates":[-99.95,18.666667],"type":"Point"}
}