{
  "id": 2205249,
  "type": "Feature",
  "properties": {
    "tgn:hierarchy":[
        "tgn:2205249",
        "tgn:1000001",
        "tgn:7012149",
        "tgn:2001510",
        "tgn:7007709",
        "tgn:7029392"
    ],
    "tgn:id":2205249,
    "tgn:name":"Bull Branch",
    "tgn:placetype":[
        "aat:300008699"
    ]
},
  "bbox": [],
  "geometry": {"coordinates":[-77.55,35.0667],"type":"Point"}
}