{
  "id": 2302256,
  "type": "Feature",
  "properties": {
    "tgn:hierarchy":[
        "tgn:2302256",
        "tgn:7002659",
        "tgn:1000001",
        "tgn:7012149",
        "tgn:2000042",
        "tgn:7029392"
    ],
    "tgn:id":2302256,
    "tgn:name":"Dutch Island",
    "tgn:placetype":[
        "aat:300008791"
    ]
},
  "bbox": [],
  "geometry": {"coordinates":[-86.65,32.3833],"type":"Point"}
}