{
  "id": 7427146,
  "type": "Feature",
  "properties": {
    "tgn:hierarchy":[
        "tgn:7427146",
        "tgn:1000001",
        "tgn:7005601",
        "tgn:7005560",
        "tgn:7029392"
    ],
    "tgn:id":7427146,
    "tgn:name":"Ci\u00e9nega San Pedro",
    "tgn:placetype":[
        "aat:300008347"
    ]
},
  "bbox": [],
  "geometry": {"coordinates":[-103.75,23.25],"type":"Point"}
}