<<<<<<< HEAD
{
  "id": 7367684,
  "type": "Feature",
  "properties": {
    "tgn:hierarchy":[
        "tgn:7367684",
        "tgn:1000001",
        "tgn:7005597",
        "tgn:7005560",
        "tgn:7029392"
    ],
    "tgn:id":7367684,
    "tgn:name":"El Postazo",
    "tgn:placetype":[
        "aat:300008347"
    ]
},
  "bbox": [],
  "geometry": {"coordinates":[-98.183333,23.5],"type":"Point"}
}
=======
{"geometry":{"type":"Point","coordinates":[-98.183333,23.500000]},"type":"Feature","properties":{"hierarchy":["tgn:7367684","tgn:1000001","tgn:7005597","tgn:7005560","tgn:7029392"],"placetype":["aat:300008347"],"id":7367684,"name:xx":"El Postazo"}}
>>>>>>> 03f74aca74312dbeaf24d7e61306dd6a786dc3d0
