{
  "id": 7414034,
  "type": "Feature",
  "properties": {
    "tgn:hierarchy":[
        "tgn:7414034",
        "tgn:7005587",
        "tgn:1000001",
        "tgn:7005560",
        "tgn:7029392"
    ],
    "tgn:id":7414034,
    "tgn:name:es":"Papaxtla",
    "tgn:placetype":[
        "aat:300008347"
    ]
},
  "bbox": [],
  "geometry": {"coordinates":[-98.666667,20.613889],"type":"Point"}
}