{
  "id": 2168287,
  "type": "Feature",
  "properties": {
    "tgn:hierarchy":[
        "tgn:2168287",
        "tgn:1000001",
        "tgn:7012149",
        "tgn:7007157",
        "tgn:2000191",
        "tgn:7029392"
    ],
    "tgn:id":2168287,
    "tgn:name":"Big French Creek",
    "tgn:placetype":[
        "aat:300008706"
    ]
},
  "bbox": [],
  "geometry": {"coordinates":[-123.2333,40.9167],"type":"Point"}
}