{
  "id": 7563996,
  "type": "Feature",
  "properties": {
    "tgn:hierarchy":[
        "tgn:7563996",
        "tgn:1000004",
        "tgn:7000198",
        "tgn:1001894",
        "tgn:7029392"
    ],
    "tgn:id":7563996,
    "tgn:name:en":"Shy\u0101mra",
    "tgn:placetype":[
        "aat:300266554",
        "aat:300008699"
    ]
},
  "bbox": [],
  "geometry": {"coordinates":[79.367035,24.892644],"type":"Point"}
}