<<<<<<< HEAD
{
  "id": 7371171,
  "type": "Feature",
  "properties": {
    "tgn:hierarchy":[
        "tgn:7371171",
        "tgn:1001853",
        "tgn:1000001",
        "tgn:7005560",
        "tgn:7029392"
    ],
    "tgn:id":7371171,
    "tgn:name":"Jicoteros, Loma de",
    "tgn:placetype":[
        "aat:300008795"
    ]
},
  "bbox": [],
  "geometry": {"coordinates":[-103.266667,28.833333],"type":"Point"}
}
=======
{"geometry":{"type":"Point","coordinates":[-103.266667,28.833333]},"type":"Feature","properties":{"hierarchy":["tgn:7371171","tgn:1001853","tgn:1000001","tgn:7005560","tgn:7029392"],"placetype":["aat:300008795"],"id":7371171,"name:xx":"Jicoteros, Loma de"}}
>>>>>>> 03f74aca74312dbeaf24d7e61306dd6a786dc3d0
