{
  "id": 2431226,
  "type": "Feature",
  "properties": {
    "tgn:hierarchy":[
        "tgn:2431226",
        "tgn:7023902",
        "tgn:1000001",
        "tgn:7012149",
        "tgn:7007249",
        "tgn:7029392"
    ],
    "tgn:id":2431226,
    "tgn:name":"Kapaaiki Point",
    "tgn:placetype":[
        "aat:300008850"
    ]
},
  "bbox": [],
  "geometry": {"coordinates":[-155.75,20.2333],"type":"Point"}
}