{
  "id": 2524356,
  "type": "Feature",
  "properties": {
    "tgn:hierarchy":[
        "tgn:2524356",
        "tgn:1000001",
        "tgn:7012149",
        "tgn:2001452",
        "tgn:7007566",
        "tgn:7029392"
    ],
    "tgn:id":2524356,
    "tgn:name":"Morgan Mines",
    "tgn:placetype":[
        "aat:300000390"
    ]
},
  "bbox": [],
  "geometry": {"coordinates":[-108.1833,36.9667],"type":"Point"}
}