{
  "id": 2167829,
  "type": "Feature",
  "properties": {
    "tgn:hierarchy":[
        "tgn:2167829",
        "tgn:1000001",
        "tgn:7012149",
        "tgn:2001029",
        "tgn:7007521",
        "tgn:7029392"
    ],
    "tgn:id":2167829,
    "tgn:name":"Big Diamond Lake",
    "tgn:placetype":[
        "aat:300008680"
    ]
},
  "bbox": [],
  "geometry": {"coordinates":[-93.3333,47.3167],"type":"Point"}
}