{
  "id": 2157533,
  "type": "Feature",
  "properties": {
    "tgn:hierarchy":[
        "tgn:2157533",
        "tgn:1000001",
        "tgn:7012149",
        "tgn:2002357",
        "tgn:7007922",
        "tgn:7029392"
    ],
    "tgn:id":2157533,
    "tgn:name":"Beaver Creek",
    "tgn:placetype":[
        "aat:300008706"
    ]
},
  "bbox": [],
  "geometry": {"coordinates":[-91.2667,44.15],"type":"Point"}
}