{
  "id": 2659749,
  "type": "Feature",
  "properties": {
    "tgn:hierarchy":[
        "tgn:2659749",
        "tgn:1000001",
        "tgn:7012149",
        "tgn:1002862",
        "tgn:7007920",
        "tgn:7029392"
    ],
    "tgn:id":2659749,
    "tgn:name":"Ship Bay",
    "tgn:placetype":[
        "aat:300132316"
    ]
},
  "bbox": [],
  "geometry": {"coordinates":[-122.8833,48.6833],"type":"Point"}
}