{
  "id": 7240874,
  "type": "Feature",
  "properties": {
    "tgn:hierarchy":[
        "tgn:7240874",
        "tgn:7003460",
        "tgn:1000003",
        "tgn:1000063",
        "tgn:4012014",
        "tgn:7029392"
    ],
    "tgn:id":7240874,
    "tgn:name":"Fond de Harz\u00e9, Ruisseau du",
    "tgn:placetype":[
        "aat:300008699"
    ]
},
  "bbox": [],
  "geometry": {"coordinates":[5.683333,50.483333],"type":"Point"}
}