{
  "id": 2506911,
  "type": "Feature",
  "properties": {
    "tgn:hierarchy":[
        "tgn:2506911",
        "tgn:1000001",
        "tgn:7006451",
        "tgn:7012149",
        "tgn:2000098",
        "tgn:7029392"
    ],
    "tgn:id":2506911,
    "tgn:name":"Mesquite Spring",
    "tgn:placetype":[
        "aat:300008697"
    ]
},
  "bbox": [],
  "geometry": {"coordinates":[-113.4167,35.6667],"type":"Point"}
}