<<<<<<< HEAD
{
  "id": 2408706,
  "type": "Feature",
  "properties": {
    "tgn:hierarchy":[
        "tgn:2408706",
        "tgn:1000001",
        "tgn:7012149",
        "tgn:2001214",
        "tgn:7007523",
        "tgn:7029392"
    ],
    "tgn:id":2408706,
    "tgn:name":"Hybrid",
    "tgn:placetype":[
        "aat:300008347"
    ]
},
  "bbox": [],
  "geometry": {"coordinates":[-92.9667,39.9167],"type":"Point"}
}
=======
{"geometry":{"type":"Point","coordinates":[-92.966700,39.916700]},"type":"Feature","properties":{"hierarchy":["tgn:2408706","tgn:1000001","tgn:7012149","tgn:2001214","tgn:7007523","tgn:7029392"],"placetype":["aat:300008347"],"id":2408706,"name:xx":"Hybrid"}}
>>>>>>> 03f74aca74312dbeaf24d7e61306dd6a786dc3d0
