{
  "id": 7291060,
  "type": "Feature",
  "properties": {
    "tgn:hierarchy":[
        "tgn:7291060",
        "tgn:1001702",
        "tgn:1000049",
        "tgn:1000002",
        "tgn:7029392"
    ],
    "tgn:id":7291060,
    "tgn:name":"Demonio, Puerto",
    "tgn:placetype":[
        "aat:300132317"
    ]
},
  "bbox": [],
  "geometry": {"coordinates":[-69.616667,-54.383333],"type":"Point"}
}