{
  "id": 2667675,
  "type": "Feature",
  "properties": {
    "tgn:hierarchy":[
        "tgn:2667675",
        "tgn:7006450",
        "tgn:1000001",
        "tgn:7012149",
        "tgn:2000086",
        "tgn:7029392"
    ],
    "tgn:id":2667675,
    "tgn:name":"Skull Lake",
    "tgn:placetype":[
        "aat:300008680"
    ]
},
  "bbox": [],
  "geometry": {"coordinates":[-143.6667,61.3667],"type":"Point"}
}