{
  "id": 7555977,
  "type": "Feature",
  "properties": {
    "tgn:hierarchy":[
        "tgn:7555977",
        "tgn:1000004",
        "tgn:7000198",
        "tgn:7031783",
        "tgn:7029392"
    ],
    "tgn:id":7555977,
    "tgn:name:en":"Pet\u0101rb\u0101r",
    "tgn:placetype":[
        "aat:300008347"
    ]
},
  "bbox": [],
  "geometry": {"coordinates":[85.851099,23.612359],"type":"Point"}
}