{
  "id": 1089929,
  "type": "Feature",
  "properties": {
    "tgn:hierarchy":[
        "tgn:1089929",
        "tgn:7001242",
        "tgn:7017572",
        "tgn:7001658",
        "tgn:7029392"
    ],
    "tgn:id":1089929,
    "tgn:name":"Om H\u0101jer",
    "tgn:placetype":[
        "aat:300008347"
    ]
},
  "bbox": [],
  "geometry": {"coordinates":[36.6833,14.3333],"type":"Point"}
}