{
  "id": 7582341,
  "type": "Feature",
  "properties": {
    "tgn:hierarchy":[
        "tgn:7582341",
        "tgn:1000004",
        "tgn:7000198",
        "tgn:7016722",
        "tgn:7029392"
    ],
    "tgn:id":7582341,
    "tgn:name:en":"Banauli",
    "tgn:placetype":[
        "aat:300008347"
    ]
},
  "bbox": [],
  "geometry": {"coordinates":[78.352486,24.833089],"type":"Point"}
}