{
  "id": 1034502,
  "type": "Feature",
  "properties": {
    "tgn:hierarchy":[
        "tgn:1034502",
        "tgn:1000003",
        "tgn:7002877",
        "tgn:1000070",
        "tgn:7029392"
    ],
    "tgn:id":1034502,
    "tgn:name":"Montlouet",
    "tgn:placetype":[
        "aat:300008347"
    ]
},
  "bbox": [],
  "geometry": {"coordinates":[1.7167,48.5167],"type":"Point"}
}