{
  "id": 2398661,
  "type": "Feature",
  "properties": {
    "tgn:hierarchy":[
        "tgn:2398661",
        "tgn:1000001",
        "tgn:7012149",
        "tgn:2001026",
        "tgn:7007521",
        "tgn:7029392"
    ],
    "tgn:id":2398661,
    "tgn:name":"Hop Hollow",
    "tgn:placetype":[
        "aat:300008761"
    ]
},
  "bbox": [],
  "geometry": {"coordinates":[-91.5167,43.75],"type":"Point"}
}