{
  "id": 7346658,
  "type": "Feature",
  "properties": {
    "tgn:hierarchy":[
        "tgn:7346658",
        "tgn:7002842",
        "tgn:7001158",
        "tgn:1000003",
        "tgn:1000095",
        "tgn:7029392"
    ],
    "tgn:id":7346658,
    "tgn:name":"Arganza",
    "tgn:placetype":[
        "aat:300008347"
    ]
},
  "bbox": [],
  "geometry": {"coordinates":[-3.083333,41.816667],"type":"Point"}
}