{
  "id": 2569153,
  "type": "Feature",
  "properties": {
    "tgn:hierarchy":[
        "tgn:2569153",
        "tgn:7013349",
        "tgn:1000001",
        "tgn:7012149",
        "tgn:7007708",
        "tgn:7029392"
    ],
    "tgn:id":2569153,
    "tgn:name":"Parkerville Mine",
    "tgn:placetype":[
        "aat:300000390"
    ]
},
  "bbox": [],
  "geometry": {"coordinates":[-118.4167,44.6833],"type":"Point"}
}