{
  "id": 7395825,
  "type": "Feature",
  "properties": {
    "tgn:hierarchy":[
        "tgn:7395825",
        "tgn:1000001",
        "tgn:7005593",
        "tgn:7005560",
        "tgn:7029392"
    ],
    "tgn:id":7395825,
    "tgn:name":"San Isidro de la Corregidora",
    "tgn:placetype":[
        "aat:300008347"
    ]
},
  "bbox": [],
  "geometry": {"coordinates":[-100.433333,20.383333],"type":"Point"}
}