{
  "id": 2080544,
  "type": "Feature",
  "properties": {
    "tgn:hierarchy":[
        "tgn:2080544",
        "tgn:1000001",
        "tgn:1002239",
        "tgn:7012149",
        "tgn:7007706",
        "tgn:7029392"
    ],
    "tgn:id":2080544,
    "tgn:name":"Malvern",
    "tgn:placetype":[
        "aat:300008347"
    ]
},
  "bbox": [],
  "geometry": {"coordinates":[-81.1667,40.6833],"type":"Point"}
}