{
  "id": 7064912,
  "type": "Feature",
  "properties": {
    "tgn:hierarchy":[
        "tgn:7064912",
        "tgn:1000003",
        "tgn:7003682",
        "tgn:7000084",
        "tgn:7029392"
    ],
    "tgn:id":7064912,
    "tgn:name":"Steinshardt",
    "tgn:placetype":[
        "aat:300008347"
    ]
},
  "bbox": [],
  "geometry": {"coordinates":[7.383333,50.583333],"type":"Point"}
}