{
  "id": 2162528,
  "type": "Feature",
  "properties": {
    "tgn:hierarchy":[
        "tgn:2162528",
        "tgn:1000001",
        "tgn:2001596",
        "tgn:7012149",
        "tgn:7007705",
        "tgn:7029392"
    ],
    "tgn:id":2162528,
    "tgn:name":"Ben Waters Lake",
    "tgn:placetype":[
        "aat:300008680"
    ]
},
  "bbox": [],
  "geometry": {"coordinates":[-99.8833,48.9667],"type":"Point"}
}