{
  "id": 2745667,
  "type": "Feature",
  "properties": {
    "tgn:hierarchy":[
        "tgn:2745667",
        "tgn:1000001",
        "tgn:7012149",
        "tgn:1002742",
        "tgn:7007920",
        "tgn:7029392"
    ],
    "tgn:id":2745667,
    "tgn:name":"Virginia City",
    "tgn:placetype":[
        "aat:300008347"
    ]
},
  "bbox": [],
  "geometry": {"coordinates":[-119.7667,48.0833],"type":"Point"}
}