{
  "id": 7474069,
  "type": "Feature",
  "properties": {
    "tgn:hierarchy":[
        "tgn:7474069",
        "tgn:1000004",
        "tgn:7467799",
        "tgn:1000141",
        "tgn:7029392"
    ],
    "tgn:id":7474069,
    "tgn:name":"Tucuocuo",
    "tgn:placetype":[
        "aat:300008347"
    ]
},
  "bbox": [],
  "geometry": {"coordinates":[120.508611,24.137222],"type":"Point"}
}