{
  "id": 2535053,
  "type": "Feature",
  "properties": {
    "tgn:hierarchy":[
        "tgn:2535053",
        "tgn:1002483",
        "tgn:7019080",
        "tgn:1000001",
        "tgn:7012149",
        "tgn:7007249",
        "tgn:7029392"
    ],
    "tgn:id":2535053,
    "tgn:name":"Nanaikaalaea",
    "tgn:placetype":[
        "aat:300008798"
    ]
},
  "bbox": [],
  "geometry": {"coordinates":[-157.8667,21.45],"type":"Point"}
}