{
  "id": 7168327,
  "type": "Feature",
  "properties": {
    "tgn:hierarchy":[
        "tgn:7168327",
        "tgn:7003669",
        "tgn:1000003",
        "tgn:7000084",
        "tgn:7029392"
    ],
    "tgn:id":7168327,
    "tgn:name":"Hart",
    "tgn:placetype":[
        "aat:300008347"
    ]
},
  "bbox": [],
  "geometry": {"coordinates":[12.916667,48.25],"type":"Point"}
}