<<<<<<< HEAD
{
  "id": 7367794,
  "type": "Feature",
  "properties": {
    "tgn:hierarchy":[
        "tgn:7367794",
        "tgn:7005584",
        "tgn:1000001",
        "tgn:7005560",
        "tgn:7029392"
    ],
    "tgn:id":7367794,
    "tgn:name":"El Vicario",
    "tgn:placetype":[
        "aat:300008347"
    ]
},
  "bbox": [],
  "geometry": {"coordinates":[-100.666667,20.583333],"type":"Point"}
}
=======
{"geometry":{"type":"Point","coordinates":[-100.666667,20.583333]},"type":"Feature","properties":{"hierarchy":["tgn:7367794","tgn:7005584","tgn:1000001","tgn:7005560","tgn:7029392"],"placetype":["aat:300008347"],"id":7367794,"name:xx":"El Vicario"}}
>>>>>>> 03f74aca74312dbeaf24d7e61306dd6a786dc3d0
