{
  "id": 7235790,
  "type": "Feature",
  "properties": {
    "tgn:hierarchy":[
        "tgn:7235790",
        "tgn:7002750",
        "tgn:7001399",
        "tgn:1000003",
        "tgn:1000074",
        "tgn:7029392"
    ],
    "tgn:id":7235790,
    "tgn:name":"Farm\u00e1ki",
    "tgn:placetype":[
        "aat:300008347"
    ]
},
  "bbox": [],
  "geometry": {"coordinates":[22.049722,40.026111],"type":"Point"}
}