{
  "id": 7437177,
  "type": "Feature",
  "properties": {
    "tgn:hierarchy":[
        "tgn:7437177",
        "tgn:7005583",
        "tgn:1000001",
        "tgn:7005560",
        "tgn:7029392"
    ],
    "tgn:id":7437177,
    "tgn:name":"Silla",
    "tgn:placetype":[
        "aat:300008347"
    ]
},
  "bbox": [],
  "geometry": {"coordinates":[-104.533333,24.55],"type":"Point"}
}