{
  "id": 2692871,
  "type": "Feature",
  "properties": {
    "tgn:hierarchy":[
        "tgn:2692871",
        "tgn:1000001",
        "tgn:7012149",
        "tgn:1003031",
        "tgn:7007826",
        "tgn:7029392"
    ],
    "tgn:id":2692871,
    "tgn:name":"Steele Island",
    "tgn:placetype":[
        "aat:300008791"
    ]
},
  "bbox": [],
  "geometry": {"coordinates":[-97.8667,33.2333],"type":"Point"}
}