{
  "id": 1068038,
  "type": "Feature",
  "properties": {
    "tgn:hierarchy":[
        "tgn:1068038",
        "tgn:1000004",
        "tgn:1000958",
        "tgn:1000111",
        "tgn:7029392"
    ],
    "tgn:id":1068038,
    "tgn:name":"Fengjingzhen",
    "tgn:placetype":[
        "aat:300008347"
    ]
},
  "bbox": [],
  "geometry": {"coordinates":[121.0167,30.8833],"type":"Point"}
}