{
  "id": 2266882,
  "type": "Feature",
  "properties": {
    "tgn:hierarchy":[
        "tgn:2266882",
        "tgn:1000001",
        "tgn:7012149",
        "tgn:2002371",
        "tgn:7007923",
        "tgn:7029392"
    ],
    "tgn:id":2266882,
    "tgn:name":"Crescent Top",
    "tgn:placetype":[
        "aat:300008798"
    ]
},
  "bbox": [],
  "geometry": {"coordinates":[-109.5333,43.8667],"type":"Point"}
}