{
  "id": 2762044,
  "type": "Feature",
  "properties": {
    "tgn:hierarchy":[
        "tgn:2762044",
        "tgn:1000001",
        "tgn:7006451",
        "tgn:7012149",
        "tgn:2000099",
        "tgn:7029392"
    ],
    "tgn:id":2762044,
    "tgn:name":"West Sevenmile Tank",
    "tgn:placetype":[
        "aat:300006191"
    ]
},
  "bbox": [],
  "geometry": {"coordinates":[-109.9333,33.7667],"type":"Point"}
}