{
  "id": 2531145,
  "type": "Feature",
  "properties": {
    "tgn:hierarchy":[
        "tgn:2531145",
        "tgn:7002659",
        "tgn:1000001",
        "tgn:2000004",
        "tgn:7012149",
        "tgn:7029392"
    ],
    "tgn:id":2531145,
    "tgn:name":"Mulberry Cave",
    "tgn:placetype":[
        "aat:300008746"
    ]
},
  "bbox": [],
  "geometry": {"coordinates":[-86.8167,33.8833],"type":"Point"}
}