{
  "id": 1119444,
  "type": "Feature",
  "properties": {
    "tgn:hierarchy":[
        "tgn:1119444",
        "tgn:1000001",
        "tgn:7012149",
        "tgn:7007706",
        "tgn:7029392"
    ],
    "tgn:id":1119444,
    "tgn:name":"Beach City Lake",
    "tgn:placetype":[
        "aat:300006191"
    ]
},
  "bbox": [],
  "geometry": {"coordinates":[-81.55,40.6333],"type":"Point"}
}