{
  "id": 2141768,
  "type": "Feature",
  "properties": {
    "tgn:hierarchy":[
        "tgn:2141768",
        "tgn:1000001",
        "tgn:7012149",
        "tgn:1002599",
        "tgn:7007708",
        "tgn:7029392"
    ],
    "tgn:id":2141768,
    "tgn:name":"Baber Butte",
    "tgn:placetype":[
        "aat:300008798"
    ]
},
  "bbox": [],
  "geometry": {"coordinates":[-123.7833,44.6167],"type":"Point"}
}