{
  "id": 7335954,
  "type": "Feature",
  "properties": {
    "tgn:hierarchy":[
        "tgn:7335954",
        "tgn:7002808",
        "tgn:7030216",
        "tgn:1000003",
        "tgn:1000095",
        "tgn:7029392"
    ],
    "tgn:id":7335954,
    "tgn:name":"Gironella",
    "tgn:placetype":[
        "aat:300008347"
    ]
},
  "bbox": [],
  "geometry": {"coordinates":[1.880192,42.034332],"type":"Point"}
}