{
  "id": 2088286,
  "type": "Feature",
  "properties": {
    "tgn:hierarchy":[
        "tgn:2088286",
        "tgn:1000001",
        "tgn:7012149",
        "tgn:7014185",
        "tgn:7007710",
        "tgn:7029392"
    ],
    "tgn:id":2088286,
    "tgn:name":"Everson",
    "tgn:placetype":[
        "aat:300008347"
    ]
},
  "bbox": [],
  "geometry": {"coordinates":[-79.5833,40.0833],"type":"Point"}
}