<<<<<<< HEAD
{
  "id": 2250041,
  "type": "Feature",
  "properties": {
    "tgn:hierarchy":[
        "tgn:2250041",
        "tgn:1000001",
        "tgn:7012149",
        "tgn:7007825",
        "tgn:7029392"
    ],
    "tgn:id":2250041,
    "tgn:name":"Collins Branch",
    "tgn:placetype":[
        "aat:300008699"
    ]
},
  "bbox": [],
  "geometry": {"coordinates":[-86.8,35.7],"type":"Point"}
}
=======
{"geometry":{"type":"Point","coordinates":[-86.800000,35.700000]},"type":"Feature","properties":{"hierarchy":["tgn:2250041","tgn:1000001","tgn:7012149","tgn:7007825","tgn:7029392"],"placetype":["aat:300008699"],"id":2250041,"name:xx":"Collins Branch"}}
>>>>>>> 03f74aca74312dbeaf24d7e61306dd6a786dc3d0
