{
  "id": 4012651,
  "type": "Feature",
  "properties": {
    "tgn:hierarchy":[
        "tgn:4012651",
        "tgn:7594005",
        "tgn:1000003",
        "tgn:1000066",
        "tgn:7029392"
    ],
    "tgn:id":4012651,
    "tgn:name":"Nyhavn",
    "tgn:placetype":[
        "aat:300000874"
    ]
},
  "bbox": [],
  "geometry": {"coordinates":[12.583333,55.683333],"type":"Point"}
}