{
  "id": 2082024,
  "type": "Feature",
  "properties": {
    "tgn:hierarchy":[
        "tgn:2082024",
        "tgn:1000001",
        "tgn:7012149",
        "tgn:1002372",
        "tgn:7007706",
        "tgn:7029392"
    ],
    "tgn:id":2082024,
    "tgn:name":"Staunton",
    "tgn:placetype":[
        "aat:300008347"
    ]
},
  "bbox": [],
  "geometry": {"coordinates":[-83.4833,39.4667],"type":"Point"}
}