{
  "id": 7553572,
  "type": "Feature",
  "properties": {
    "tgn:hierarchy":[
        "tgn:7553572",
        "tgn:1000004",
        "tgn:1001842",
        "tgn:7000198",
        "tgn:7029392"
    ],
    "tgn:id":7553572,
    "tgn:name:en":"Makrandpur",
    "tgn:placetype":[
        "aat:300008347"
    ]
},
  "bbox": [],
  "geometry": {"coordinates":[85.633333,26.133333],"type":"Point"}
}