<<<<<<< HEAD
{
  "id": 2405076,
  "type": "Feature",
  "properties": {
    "tgn:hierarchy":[
        "tgn:2405076",
        "tgn:1000001",
        "tgn:7012149",
        "tgn:2001288",
        "tgn:7007524",
        "tgn:7029392"
    ],
    "tgn:id":2405076,
    "tgn:name":"Hudson Mine",
    "tgn:placetype":[
        "aat:300000390"
    ]
},
  "bbox": [],
  "geometry": {"coordinates":[-112.3,45.6833],"type":"Point"}
}
=======
{"geometry":{"type":"Point","coordinates":[-112.300000,45.683300]},"type":"Feature","properties":{"hierarchy":["tgn:2405076","tgn:1000001","tgn:7012149","tgn:2001288","tgn:7007524","tgn:7029392"],"placetype":["aat:300000390"],"id":2405076,"name:xx":"Hudson Mine"}}
>>>>>>> 03f74aca74312dbeaf24d7e61306dd6a786dc3d0
