{
  "id": 7169342,
  "type": "Feature",
  "properties": {
    "tgn:hierarchy":[
        "tgn:7169342",
        "tgn:7003669",
        "tgn:1000003",
        "tgn:7000084",
        "tgn:7029392"
    ],
    "tgn:id":7169342,
    "tgn:name":"Heuersberg",
    "tgn:placetype":[
        "aat:300008777"
    ]
},
  "bbox": [],
  "geometry": {"coordinates":[10.233333,50.283333],"type":"Point"}
}