{
  "id": 1073934,
  "type": "Feature",
  "properties": {
    "tgn:hierarchy":[
        "tgn:1073934",
        "tgn:1000004",
        "tgn:7018118",
        "tgn:1000111",
        "tgn:7029392"
    ],
    "tgn:id":1073934,
    "tgn:name":"Zhaotong",
    "tgn:placetype":[
        "aat:300008347"
    ]
},
  "bbox": [],
  "geometry": {"coordinates":[103.65,27.3333],"type":"Point"}
}