{
  "id": 2627884,
  "type": "Feature",
  "properties": {
    "tgn:hierarchy":[
        "tgn:2627884",
        "tgn:1000001",
        "tgn:7016172",
        "tgn:7012149",
        "tgn:2000151",
        "tgn:7029392"
    ],
    "tgn:id":2627884,
    "tgn:name":"Rokey",
    "tgn:placetype":[
        "aat:300008347"
    ]
},
  "bbox": [],
  "geometry": {"coordinates":[-90.2667,35.85],"type":"Point"}
}