{
  "id": 1096284,
  "type": "Feature",
  "properties": {
    "tgn:hierarchy":[
        "tgn:1096284",
        "tgn:7000490",
        "tgn:1000006",
        "tgn:7001830",
        "tgn:7029392"
    ],
    "tgn:id":1096284,
    "tgn:name":"Blackall",
    "tgn:placetype":[
        "aat:300008347"
    ]
},
  "bbox": [],
  "geometry": {"coordinates":[145.45,-24.3833],"type":"Point"}
}