{
  "id": 2614927,
  "type": "Feature",
  "properties": {
    "tgn:hierarchy":[
        "tgn:2614927",
        "tgn:1000001",
        "tgn:2001185",
        "tgn:7012149",
        "tgn:7007523",
        "tgn:7029392"
    ],
    "tgn:id":2614927,
    "tgn:name":"Reno Spring",
    "tgn:placetype":[
        "aat:300008697"
    ]
},
  "bbox": [],
  "geometry": {"coordinates":[-93.2833,36.8167],"type":"Point"}
}