{
  "id": 2532802,
  "type": "Feature",
  "properties": {
    "tgn:hierarchy":[
        "tgn:2532802",
        "tgn:1000001",
        "tgn:7012149",
        "tgn:2000512",
        "tgn:7007251",
        "tgn:7029392"
    ],
    "tgn:id":2532802,
    "tgn:name":"Murphysboro, Lake",
    "tgn:placetype":[
        "aat:300006191"
    ]
},
  "bbox": [],
  "geometry": {"coordinates":[-89.3667,37.7667],"type":"Point"}
}