{
  "id": 7358649,
  "type": "Feature",
  "properties": {
    "tgn:hierarchy":[
        "tgn:7358649",
        "tgn:7005581",
        "tgn:1000001",
        "tgn:7005560",
        "tgn:7029392"
    ],
    "tgn:id":7358649,
    "tgn:name":"Colorado, Arroyo",
    "tgn:placetype":[
        "aat:300008699"
    ]
},
  "bbox": [],
  "geometry": {"coordinates":[-105.233333,28.866667],"type":"Point"}
}