{
  "id": 2514677,
  "type": "Feature",
  "properties": {
    "tgn:hierarchy":[
        "tgn:2514677",
        "tgn:1000001",
        "tgn:7012149",
        "tgn:2001054",
        "tgn:7007521",
        "tgn:7029392"
    ],
    "tgn:id":2514677,
    "tgn:name":"Miller Lake",
    "tgn:placetype":[
        "aat:300008680"
    ]
},
  "bbox": [],
  "geometry": {"coordinates":[-95.3667,46.15],"type":"Point"}
}