{
  "id": 7301666,
  "type": "Feature",
  "properties": {
    "tgn:hierarchy":[
        "tgn:7301666",
        "tgn:1001439",
        "tgn:1000003",
        "tgn:7002797",
        "tgn:1000095",
        "tgn:7029392"
    ],
    "tgn:id":7301666,
    "tgn:name":"Mojarra, Cala",
    "tgn:placetype":[
        "aat:300132317"
    ]
},
  "bbox": [],
  "geometry": {"coordinates":[-1.116667,37.55],"type":"Point"}
}