{
  "id": 2669623,
  "type": "Feature",
  "properties": {
    "tgn:hierarchy":[
        "tgn:2669623",
        "tgn:1000001",
        "tgn:7012149",
        "tgn:2001308",
        "tgn:7007524",
        "tgn:7029392"
    ],
    "tgn:id":2669623,
    "tgn:name":"Slide Rock Gulch",
    "tgn:placetype":[
        "aat:300008761"
    ]
},
  "bbox": [],
  "geometry": {"coordinates":[-109.9333,45.6667],"type":"Point"}
}