{
  "id": 7094223,
  "type": "Feature",
  "properties": {
    "tgn:hierarchy":[
        "tgn:7094223",
        "tgn:1000003",
        "tgn:7003687",
        "tgn:7000084",
        "tgn:7029392"
    ],
    "tgn:id":7094223,
    "tgn:name":"Sch\u00f6nitz",
    "tgn:placetype":[
        "aat:300008347"
    ]
},
  "bbox": [],
  "geometry": {"coordinates":[12.466667,51.833333],"type":"Point"}
}