{
  "id": 2340673,
  "type": "Feature",
  "properties": {
    "tgn:hierarchy":[
        "tgn:2340673",
        "tgn:1000001",
        "tgn:7012149",
        "tgn:1002402",
        "tgn:7007523",
        "tgn:7029392"
    ],
    "tgn:id":2340673,
    "tgn:name":"Frene Creek",
    "tgn:placetype":[
        "aat:300008706"
    ]
},
  "bbox": [],
  "geometry": {"coordinates":[-91.45,38.6333],"type":"Point"}
}