{
  "id": 7314018,
  "type": "Feature",
  "properties": {
    "tgn:hierarchy":[
        "tgn:7314018",
        "tgn:1001768",
        "tgn:1000049",
        "tgn:1000002",
        "tgn:7029392"
    ],
    "tgn:id":7314018,
    "tgn:name":"Llampaiquillo",
    "tgn:placetype":[
        "aat:300000206"
    ]
},
  "bbox": [],
  "geometry": {"coordinates":[-71.633333,-33.216667],"type":"Point"}
}