{
  "id": 7311771,
  "type": "Feature",
  "properties": {
    "tgn:hierarchy":[
        "tgn:7311771",
        "tgn:1001699",
        "tgn:1000049",
        "tgn:1000002",
        "tgn:7029392"
    ],
    "tgn:id":7311771,
    "tgn:name":"Las Ortigas",
    "tgn:placetype":[
        "aat:300008699"
    ]
},
  "bbox": [],
  "geometry": {"coordinates":[-73.45,-41.55],"type":"Point"}
}