{
  "id": 7195511,
  "type": "Feature",
  "properties": {
    "tgn:hierarchy":[
        "tgn:7195511",
        "tgn:7003669",
        "tgn:1000003",
        "tgn:7000084",
        "tgn:7029392"
    ],
    "tgn:id":7195511,
    "tgn:name":"Dehnhof",
    "tgn:placetype":[
        "aat:300000206"
    ]
},
  "bbox": [],
  "geometry": {"coordinates":[12.466667,49.283333],"type":"Point"}
}