{
  "id": 7196035,
  "type": "Feature",
  "properties": {
    "tgn:hierarchy":[
        "tgn:7196035",
        "tgn:1000003",
        "tgn:7003682",
        "tgn:7000084",
        "tgn:7029392"
    ],
    "tgn:id":7196035,
    "tgn:name":"Dinkelbach",
    "tgn:placetype":[
        "aat:300008347"
    ]
},
  "bbox": [],
  "geometry": {"coordinates":[7.383333,50.633333],"type":"Point"}
}