{
  "id": 1101677,
  "type": "Feature",
  "properties": {
    "tgn:hierarchy":[
        "tgn:1101677",
        "tgn:7001242",
        "tgn:1001542",
        "tgn:7000726",
        "tgn:7029392"
    ],
    "tgn:id":1101677,
    "tgn:name":"Liwonde National Park",
    "tgn:placetype":[
        "aat:300008189"
    ]
},
  "bbox": [],
  "geometry": {"coordinates":[35.3333,-14.8333],"type":"Point"}
}