{
  "id": 2217035,
  "type": "Feature",
  "properties": {
    "tgn:hierarchy":[
        "tgn:2217035",
        "tgn:1000001",
        "tgn:7012149",
        "tgn:2001527",
        "tgn:7007709",
        "tgn:7029392"
    ],
    "tgn:id":2217035,
    "tgn:name":"Camp Newkirk Pond",
    "tgn:placetype":[
        "aat:300006191"
    ]
},
  "bbox": [],
  "geometry": {"coordinates":[-77.9167,34.6333],"type":"Point"}
}