{
  "id": 2698919,
  "type": "Feature",
  "properties": {
    "tgn:hierarchy":[
        "tgn:2698919",
        "tgn:1000001",
        "tgn:7012149",
        "tgn:7007157",
        "tgn:1002621",
        "tgn:7029392"
    ],
    "tgn:id":2698919,
    "tgn:name":"Strawberry Mines",
    "tgn:placetype":[
        "aat:300000390"
    ]
},
  "bbox": [],
  "geometry": {"coordinates":[-119.2833,37.55],"type":"Point"}
}