{
  "id": 2523538,
  "type": "Feature",
  "properties": {
    "tgn:hierarchy":[
        "tgn:2523538",
        "tgn:1000001",
        "tgn:2000469",
        "tgn:7012149",
        "tgn:7007250",
        "tgn:7029392"
    ],
    "tgn:id":2523538,
    "tgn:name":"Moose Mountain",
    "tgn:placetype":[
        "aat:300008798"
    ]
},
  "bbox": [],
  "geometry": {"coordinates":[-115.1833,46.7667],"type":"Point"}
}