<<<<<<< HEAD
{
  "id": 7179589,
  "type": "Feature",
  "properties": {
    "tgn:hierarchy":[
        "tgn:7179589",
        "tgn:1000003",
        "tgn:7003677",
        "tgn:7000084",
        "tgn:7029392"
    ],
    "tgn:id":7179589,
    "tgn:name":"Hambuchshof",
    "tgn:placetype":[
        "aat:300000206"
    ]
},
  "bbox": [],
  "geometry": {"coordinates":[7.016667,50.65],"type":"Point"}
}
=======
{"geometry":{"type":"Point","coordinates":[7.016667,50.650000]},"type":"Feature","properties":{"hierarchy":["tgn:7179589","tgn:1000003","tgn:7003677","tgn:7000084","tgn:7029392"],"placetype":["aat:300000206"],"id":7179589,"name:xx":"Hambuchshof"}}
>>>>>>> 03f74aca74312dbeaf24d7e61306dd6a786dc3d0
