<<<<<<< HEAD
{
  "id": 2258886,
  "type": "Feature",
  "properties": {
    "tgn:hierarchy":[
        "tgn:2258886",
        "tgn:1000001",
        "tgn:7012149",
        "tgn:2001303",
        "tgn:7007524",
        "tgn:7029392"
    ],
    "tgn:id":2258886,
    "tgn:name":"Cottonwood Creek",
    "tgn:placetype":[
        "aat:300008706"
    ]
},
  "bbox": [],
  "geometry": {"coordinates":[-106.7333,45.6833],"type":"Point"}
}
=======
{"geometry":{"type":"Point","coordinates":[-106.733300,45.683300]},"type":"Feature","properties":{"hierarchy":["tgn:2258886","tgn:1000001","tgn:7012149","tgn:2001303","tgn:7007524","tgn:7029392"],"placetype":["aat:300008706"],"id":2258886,"name:xx":"Cottonwood Creek"}}
>>>>>>> 03f74aca74312dbeaf24d7e61306dd6a786dc3d0
