<<<<<<< HEAD
{
  "id": 7052570,
  "type": "Feature",
  "properties": {
    "tgn:hierarchy":[
        "tgn:7052570",
        "tgn:7015163",
        "tgn:1000003",
        "tgn:7003121",
        "tgn:1000080",
        "tgn:7029392"
    ],
    "tgn:id":7052570,
    "tgn:name":"Iscanneddu, Riu",
    "tgn:placetype":[
        "aat:300008699"
    ]
},
  "bbox": [],
  "geometry": {"coordinates":[8.8,40.816667],"type":"Point"}
}
=======
{"geometry":{"type":"Point","coordinates":[8.800000,40.816667]},"type":"Feature","properties":{"hierarchy":["tgn:7052570","tgn:7015163","tgn:1000003","tgn:7003121","tgn:1000080","tgn:7029392"],"placetype":["aat:300008699"],"id":7052570,"name:xx":"Iscanneddu, Riu"}}
>>>>>>> 03f74aca74312dbeaf24d7e61306dd6a786dc3d0
