{
  "id": 7335947,
  "type": "Feature",
  "properties": {
    "tgn:hierarchy":[
        "tgn:7335947",
        "tgn:7002826",
        "tgn:7001158",
        "tgn:1000003",
        "tgn:1000095",
        "tgn:7029392"
    ],
    "tgn:id":7335947,
    "tgn:name":"Gistreo, Sierra de",
    "tgn:placetype":[
        "aat:300008795"
    ]
},
  "bbox": [],
  "geometry": {"coordinates":[-6.416667,42.75],"type":"Point"}
}