{
  "id": 7419275,
  "type": "Feature",
  "properties": {
    "tgn:hierarchy":[
        "tgn:7419275",
        "tgn:7005579",
        "tgn:1000001",
        "tgn:7005560",
        "tgn:7029392"
    ],
    "tgn:id":7419275,
    "tgn:name":"Cerro Colorado, Arroyo",
    "tgn:placetype":[
        "aat:300266554",
        "aat:300008699"
    ]
},
  "bbox": [],
  "geometry": {"coordinates":[-102.766667,21.883333],"type":"Point"}
}