{
  "id": 2011299,
  "type": "Feature",
  "properties": {
    "tgn:hierarchy":[
        "tgn:2011299",
        "tgn:1000001",
        "tgn:7012149",
        "tgn:2000181",
        "tgn:7007157",
        "tgn:7029392"
    ],
    "tgn:id":2011299,
    "tgn:name":"Falk",
    "tgn:placetype":[
        "aat:300008347",
        "aat:300387210"
    ]
},
  "bbox": [],
  "geometry": {"coordinates":[-124.1167,40.6833],"type":"Point"}
}