<<<<<<< HEAD
{
  "id": 7172290,
  "type": "Feature",
  "properties": {
    "tgn:hierarchy":[
        "tgn:7172290",
        "tgn:1000003",
        "tgn:7003677",
        "tgn:7000084",
        "tgn:7029392"
    ],
    "tgn:id":7172290,
    "tgn:name":"Hiddeser-Berg",
    "tgn:placetype":[
        "aat:300008777"
    ]
},
  "bbox": [],
  "geometry": {"coordinates":[8.85,51.933333],"type":"Point"}
}
=======
{"geometry":{"type":"Point","coordinates":[8.850000,51.933333]},"type":"Feature","properties":{"hierarchy":["tgn:7172290","tgn:1000003","tgn:7003677","tgn:7000084","tgn:7029392"],"placetype":["aat:300008777"],"id":7172290,"name:xx":"Hiddeser-Berg"}}
>>>>>>> 03f74aca74312dbeaf24d7e61306dd6a786dc3d0
