{
  "id": 7209363,
  "type": "Feature",
  "properties": {
    "tgn:hierarchy":[
        "tgn:7209363",
        "tgn:1000003",
        "tgn:7003678",
        "tgn:7000084",
        "tgn:7029392"
    ],
    "tgn:id":7209363,
    "tgn:name":"Bechlingen",
    "tgn:placetype":[
        "aat:300008347"
    ]
},
  "bbox": [],
  "geometry": {"coordinates":[8.45,50.633333],"type":"Point"}
}