{
  "id": 7126259,
  "type": "Feature",
  "properties": {
    "tgn:hierarchy":[
        "tgn:7126259",
        "tgn:7003692",
        "tgn:1000003",
        "tgn:7000084",
        "tgn:7029392"
    ],
    "tgn:id":7126259,
    "tgn:name":"Oberried",
    "tgn:placetype":[
        "aat:300000206"
    ]
},
  "bbox": [],
  "geometry": {"coordinates":[9.916667,47.716667],"type":"Point"}
}