{
  "id": 2175291,
  "type": "Feature",
  "properties": {
    "tgn:hierarchy":[
        "tgn:2175291",
        "tgn:1000001",
        "tgn:7012149",
        "tgn:7007157",
        "tgn:2000188",
        "tgn:7029392"
    ],
    "tgn:id":2175291,
    "tgn:name":"Black Butte",
    "tgn:placetype":[
        "aat:300008798"
    ]
},
  "bbox": [],
  "geometry": {"coordinates":[-121.9833,40.45],"type":"Point"}
}