{
  "id": 7108726,
  "type": "Feature",
  "properties": {
    "tgn:hierarchy":[
        "tgn:7108726",
        "tgn:1000003",
        "tgn:7003677",
        "tgn:7000084",
        "tgn:7029392"
    ],
    "tgn:id":7108726,
    "tgn:name":"Rapslage",
    "tgn:placetype":[
        "aat:300000206"
    ]
},
  "bbox": [],
  "geometry": {"coordinates":[8.616667,52.483333],"type":"Point"}
}