{
  "id": 2620044,
  "type": "Feature",
  "properties": {
    "tgn:hierarchy":[
        "tgn:2620044",
        "tgn:1000001",
        "tgn:2001701",
        "tgn:7012149",
        "tgn:7007708",
        "tgn:7029392"
    ],
    "tgn:id":2620044,
    "tgn:name":"Riser Lake",
    "tgn:placetype":[
        "aat:300008680"
    ]
},
  "bbox": [],
  "geometry": {"coordinates":[-123.2333,44.4333],"type":"Point"}
}