{
  "id": 2756544,
  "type": "Feature",
  "properties": {
    "tgn:hierarchy":[
        "tgn:2756544",
        "tgn:1000001",
        "tgn:7012149",
        "tgn:7007706",
        "tgn:7029392"
    ],
    "tgn:id":2756544,
    "tgn:name":"Wellington Creek",
    "tgn:placetype":[
        "aat:300008706"
    ]
},
  "bbox": [],
  "geometry": {"coordinates":[-82.1833,41.05],"type":"Point"}
}