{
  "id": 2425538,
  "type": "Feature",
  "properties": {
    "tgn:hierarchy":[
        "tgn:2425538",
        "tgn:1000001",
        "tgn:7012149",
        "tgn:2000230",
        "tgn:7007158",
        "tgn:7029392"
    ],
    "tgn:id":2425538,
    "tgn:name":"Johnsons Corner",
    "tgn:placetype":[
        "aat:300008347"
    ]
},
  "bbox": [],
  "geometry": {"coordinates":[-108.4833,39.0833],"type":"Point"}
}