{
  "id": 2189797,
  "type": "Feature",
  "properties": {
    "tgn:hierarchy":[
        "tgn:2189797",
        "tgn:1000001",
        "tgn:7012149",
        "tgn:2000218",
        "tgn:7007158",
        "tgn:7029392"
    ],
    "tgn:id":2189797,
    "tgn:name":"Bowers Lakes",
    "tgn:placetype":[
        "aat:300006191"
    ]
},
  "bbox": [],
  "geometry": {"coordinates":[-107.05,38.1167],"type":"Point"}
}