<<<<<<< HEAD
{
  "id": 7050240,
  "type": "Feature",
  "properties": {
    "tgn:hierarchy":[
        "tgn:7050240",
        "tgn:7003139",
        "tgn:1000003",
        "tgn:7003080",
        "tgn:1000080",
        "tgn:7029392"
    ],
    "tgn:id":7050240,
    "tgn:name":"Pietre, Fosso delle",
    "tgn:placetype":[
        "aat:300008699"
    ]
},
  "bbox": [],
  "geometry": {"coordinates":[12.133333,42.483333],"type":"Point"}
}
=======
{"geometry":{"type":"Point","coordinates":[12.133333,42.483333]},"type":"Feature","properties":{"hierarchy":["tgn:7050240","tgn:7003139","tgn:1000003","tgn:7003080","tgn:1000080","tgn:7029392"],"placetype":["aat:300008699"],"id":7050240,"name:xx":"Pietre, Fosso delle"}}
>>>>>>> 03f74aca74312dbeaf24d7e61306dd6a786dc3d0
