{
  "id": 2097075,
  "type": "Feature",
  "properties": {
    "tgn:hierarchy":[
        "tgn:2097075",
        "tgn:1000001",
        "tgn:2001785",
        "tgn:7012149",
        "tgn:7007713",
        "tgn:7029392"
    ],
    "tgn:id":2097075,
    "tgn:name":"Bullhead",
    "tgn:placetype":[
        "aat:300008347"
    ]
},
  "bbox": [],
  "geometry": {"coordinates":[-101.0667,45.75],"type":"Point"}
}