{
  "id": 7168335,
  "type": "Feature",
  "properties": {
    "tgn:hierarchy":[
        "tgn:7168335",
        "tgn:7003669",
        "tgn:1000003",
        "tgn:7000084",
        "tgn:7029392"
    ],
    "tgn:id":7168335,
    "tgn:name":"Hart",
    "tgn:placetype":[
        "aat:300008347"
    ]
},
  "bbox": [],
  "geometry": {"coordinates":[12.55,47.933333],"type":"Point"}
}