<<<<<<< HEAD
{
  "id": 2409489,
  "type": "Feature",
  "properties": {
    "tgn:hierarchy":[
        "tgn:2409489",
        "tgn:1000001",
        "tgn:7012149",
        "tgn:2001288",
        "tgn:7007524",
        "tgn:7029392"
    ],
    "tgn:id":2409489,
    "tgn:name":"Idler Mine",
    "tgn:placetype":[
        "aat:300000390"
    ]
},
  "bbox": [],
  "geometry": {"coordinates":[-112.4667,45.6],"type":"Point"}
}
=======
{"geometry":{"type":"Point","coordinates":[-112.466700,45.600000]},"type":"Feature","properties":{"hierarchy":["tgn:2409489","tgn:1000001","tgn:7012149","tgn:2001288","tgn:7007524","tgn:7029392"],"placetype":["aat:300000390"],"id":2409489,"name:xx":"Idler Mine"}}
>>>>>>> 03f74aca74312dbeaf24d7e61306dd6a786dc3d0
