{
  "id": 2084444,
  "type": "Feature",
  "properties": {
    "tgn:hierarchy":[
        "tgn:2084444",
        "tgn:1000001",
        "tgn:7012149",
        "tgn:2001717",
        "tgn:7007708",
        "tgn:7029392"
    ],
    "tgn:id":2084444,
    "tgn:name":"Brewster",
    "tgn:placetype":[
        "aat:300387016"
    ]
},
  "bbox": [],
  "geometry": {"coordinates":[-122.8667,44.5667],"type":"Point"}
}