{
  "id": 2163615,
  "type": "Feature",
  "properties": {
    "tgn:hierarchy":[
        "tgn:2163615",
        "tgn:7002659",
        "tgn:1000001",
        "tgn:2000004",
        "tgn:7012149",
        "tgn:7029392"
    ],
    "tgn:id":2163615,
    "tgn:name":"Bent Tree",
    "tgn:placetype":[
        "aat:300008347"
    ]
},
  "bbox": [],
  "geometry": {"coordinates":[-86.7667,33.8667],"type":"Point"}
}