{
  "id": 1085404,
  "type": "Feature",
  "properties": {
    "tgn:hierarchy":[
        "tgn:1085404",
        "tgn:1000004",
        "tgn:7491221",
        "tgn:1000141",
        "tgn:7029392"
    ],
    "tgn:id":1085404,
    "tgn:name":"Tung-ho",
    "tgn:placetype":[
        "aat:300008347"
    ]
},
  "bbox": [],
  "geometry": {"coordinates":[121.303611,22.968056],"type":"Point"}
}