{
  "id": 7286754,
  "type": "Feature",
  "properties": {
    "tgn:hierarchy":[
        "tgn:7286754",
        "tgn:7002464",
        "tgn:1000049",
        "tgn:1000002",
        "tgn:7029392"
    ],
    "tgn:id":7286754,
    "tgn:name":"Apacheta Guantija",
    "tgn:placetype":[
        "aat:300006960"
    ]
},
  "bbox": [],
  "geometry": {"coordinates":[-68.683333,-19.866667],"type":"Point"}
}