{
  "id": 2202015,
  "type": "Feature",
  "properties": {
    "tgn:hierarchy":[
        "tgn:2202015",
        "tgn:1000001",
        "tgn:2000466",
        "tgn:7012149",
        "tgn:7007250",
        "tgn:7029392"
    ],
    "tgn:id":2202015,
    "tgn:name":"Buck Island",
    "tgn:placetype":[
        "aat:300008791"
    ]
},
  "bbox": [],
  "geometry": {"coordinates":[-111.55,42.9167],"type":"Point"}
}