{
  "id": 2508383,
  "type": "Feature",
  "properties": {
    "tgn:hierarchy":[
        "tgn:2508383",
        "tgn:7006450",
        "tgn:1000001",
        "tgn:7012149",
        "tgn:2124014",
        "tgn:7029392"
    ],
    "tgn:id":2508383,
    "tgn:name":"Middle Channel Kiwalk River",
    "tgn:placetype":[
        "aat:300008707"
    ]
},
  "bbox": [],
  "geometry": {"coordinates":[-161.8667,65.95],"type":"Point"}
}