{
  "id": 1127107,
  "type": "Feature",
  "properties": {
    "tgn:hierarchy":[
        "tgn:1127107",
        "tgn:1000003",
        "tgn:7012216",
        "tgn:1000070",
        "tgn:7029392"
    ],
    "tgn:id":1127107,
    "tgn:name":"Meu",
    "tgn:placetype":[
        "aat:300008707"
    ]
},
  "bbox": [],
  "geometry": {"coordinates":[-1.7833,48.05],"type":"Point"}
}