{
  "id": 2735587,
  "type": "Feature",
  "properties": {
    "tgn:hierarchy":[
        "tgn:2735587",
        "tgn:1000001",
        "tgn:7012149",
        "tgn:1002899",
        "tgn:7007920",
        "tgn:7029392"
    ],
    "tgn:id":2735587,
    "tgn:name":"Twin Falls Lake",
    "tgn:placetype":[
        "aat:300008680"
    ]
},
  "bbox": [],
  "geometry": {"coordinates":[-121.7333,48.0167],"type":"Point"}
}