{
  "id": 2149483,
  "type": "Feature",
  "properties": {
    "tgn:hierarchy":[
        "tgn:2149483",
        "tgn:1000001",
        "tgn:2002368",
        "tgn:7012149",
        "tgn:7007923",
        "tgn:7029392"
    ],
    "tgn:id":2149483,
    "tgn:name":"Barrett Creek",
    "tgn:placetype":[
        "aat:300008706"
    ]
},
  "bbox": [],
  "geometry": {"coordinates":[-106.45,41.2833],"type":"Point"}
}