{
  "id": 7309025,
  "type": "Feature",
  "properties": {
    "tgn:hierarchy":[
        "tgn:7309025",
        "tgn:1001705",
        "tgn:1000049",
        "tgn:1000002",
        "tgn:7029392"
    ],
    "tgn:id":7309025,
    "tgn:name":"Los Santos del Mar",
    "tgn:placetype":[
        "aat:300386846"
    ]
},
  "bbox": [],
  "geometry": {"coordinates":[-72.633333,-35.583333],"type":"Point"}
}