{
  "id": 2667004,
  "type": "Feature",
  "properties": {
    "tgn:hierarchy":[
        "tgn:2667004",
        "tgn:1000001",
        "tgn:7012149",
        "tgn:2000232",
        "tgn:7007158",
        "tgn:7029392"
    ],
    "tgn:id":2667004,
    "tgn:name":"Skeltcher Creek",
    "tgn:placetype":[
        "aat:300008706"
    ]
},
  "bbox": [],
  "geometry": {"coordinates":[-109.0333,40.9667],"type":"Point"}
}