{
  "id": 2463996,
  "type": "Feature",
  "properties": {
    "tgn:hierarchy":[
        "tgn:2463996",
        "tgn:2000090",
        "tgn:1000001",
        "tgn:7006451",
        "tgn:7012149",
        "tgn:7029392"
    ],
    "tgn:id":2463996,
    "tgn:name":"Loco Knoll Number Three Tank",
    "tgn:placetype":[
        "aat:300006191"
    ]
},
  "bbox": [],
  "geometry": {"coordinates":[-109.1167,34.0167],"type":"Point"}
}