{
  "id": 7498291,
  "type": "Feature",
  "properties": {
    "tgn:hierarchy":[
        "tgn:7498291",
        "tgn:7001004",
        "tgn:1000004",
        "tgn:1000141",
        "tgn:7029392"
    ],
    "tgn:id":7498291,
    "tgn:name":"Meinong Guozhong",
    "tgn:placetype":[
        "aat:300006495"
    ]
},
  "bbox": [],
  "geometry": {"coordinates":[120.544159,22.893863],"type":"Point"}
}