{
  "id": 7256309,
  "type": "Feature",
  "properties": {
    "tgn:hierarchy":[
        "tgn:7256309",
        "tgn:7003458",
        "tgn:1000003",
        "tgn:1000063",
        "tgn:7018236",
        "tgn:7029392"
    ],
    "tgn:id":7256309,
    "tgn:name":"Zwartpaard",
    "tgn:placetype":[
        "aat:300008347"
    ]
},
  "bbox": [],
  "geometry": {"coordinates":[2.666667,51.016667],"type":"Point"}
}