{
  "id": 2642646,
  "type": "Feature",
  "properties": {
    "tgn:hierarchy":[
        "tgn:2642646",
        "tgn:1000001",
        "tgn:7012149",
        "tgn:7007157",
        "tgn:2000188",
        "tgn:7029392"
    ],
    "tgn:id":2642646,
    "tgn:name":"Sanders Ridge",
    "tgn:placetype":[
        "aat:300266640"
    ]
},
  "bbox": [],
  "geometry": {"coordinates":[-121.85,40.85],"type":"Point"}
}