<<<<<<< HEAD
{
  "id": 7475009,
  "type": "Feature",
  "properties": {
    "tgn:hierarchy":[
        "tgn:7475009",
        "tgn:1000004",
        "tgn:1000454",
        "tgn:1000141",
        "tgn:7029392"
    ],
    "tgn:id":7475009,
    "tgn:name":"Yangguang Bieshu",
    "tgn:placetype":[
        "aat:300005567"
    ]
},
  "bbox": [],
  "geometry": {"coordinates":[121.51865,25.263943],"type":"Point"}
}
=======
{"geometry":{"type":"Point","coordinates":[121.518650,25.263943]},"type":"Feature","properties":{"hierarchy":["tgn:7475009","tgn:1000004","tgn:1000454","tgn:1000141","tgn:7029392"],"placetype":["aat:300005567"],"id":7475009,"name:xx":"Yangguang Bieshu"}}
>>>>>>> 03f74aca74312dbeaf24d7e61306dd6a786dc3d0
