{
  "id": 7237086,
  "type": "Feature",
  "properties": {
    "tgn:hierarchy":[
        "tgn:7237086",
        "tgn:7011330",
        "tgn:7002674",
        "tgn:1000003",
        "tgn:1000074",
        "tgn:7029392"
    ],
    "tgn:id":7237086,
    "tgn:name":"\u00c1gios Andr\u00e9as, Vrachonis\u00edda",
    "tgn:placetype":[
        "aat:300008791"
    ]
},
  "bbox": [],
  "geometry": {"coordinates":[26.936389,36.9325],"type":"Point"}
}