{
  "id": 2547033,
  "type": "Feature",
  "properties": {
    "tgn:hierarchy":[
        "tgn:2547033",
        "tgn:1000001",
        "tgn:7012149",
        "tgn:7007250",
        "tgn:7029392"
    ],
    "tgn:id":2547033,
    "tgn:name":"North Fork Pine Creek",
    "tgn:placetype":[
        "aat:300008706"
    ]
},
  "bbox": [],
  "geometry": {"coordinates":[-111.3333,43.6333],"type":"Point"}
}