{
  "id": 2091289,
  "type": "Feature",
  "properties": {
    "tgn:hierarchy":[
        "tgn:2091289",
        "tgn:1000001",
        "tgn:1002185",
        "tgn:7012149",
        "tgn:7007710",
        "tgn:7029392"
    ],
    "tgn:id":2091289,
    "tgn:name":"Newry",
    "tgn:placetype":[
        "aat:300008347"
    ]
},
  "bbox": [],
  "geometry": {"coordinates":[-78.4333,40.3833],"type":"Point"}
}