{
  "id": 7311901,
  "type": "Feature",
  "properties": {
    "tgn:hierarchy":[
        "tgn:7311901",
        "tgn:1001705",
        "tgn:1000049",
        "tgn:1000002",
        "tgn:7029392"
    ],
    "tgn:id":7311901,
    "tgn:name":"Las Lajas, Puntilla",
    "tgn:placetype":[
        "aat:300008777"
    ]
},
  "bbox": [],
  "geometry": {"coordinates":[-72.05,-34.783333],"type":"Point"}
}