<<<<<<< HEAD
{
  "id": 7373474,
  "type": "Feature",
  "properties": {
    "tgn:hierarchy":[
        "tgn:7373474",
        "tgn:7005586",
        "tgn:1000001",
        "tgn:7005560",
        "tgn:7029392"
    ],
    "tgn:id":7373474,
    "tgn:name":"La Gavilana",
    "tgn:placetype":[
        "aat:300008347"
    ]
},
  "bbox": [],
  "geometry": {"coordinates":[-104.0,20.716667],"type":"Point"}
}
=======
{"geometry":{"type":"Point","coordinates":[-104.000000,20.716667]},"type":"Feature","properties":{"hierarchy":["tgn:7373474","tgn:7005586","tgn:1000001","tgn:7005560","tgn:7029392"],"placetype":["aat:300008347"],"id":7373474,"name:xx":"La Gavilana"}}
>>>>>>> 03f74aca74312dbeaf24d7e61306dd6a786dc3d0
