{
  "id": 2747162,
  "type": "Feature",
  "properties": {
    "tgn:hierarchy":[
        "tgn:2747162",
        "tgn:1000001",
        "tgn:7012149",
        "tgn:1002999",
        "tgn:7007526",
        "tgn:7029392"
    ],
    "tgn:id":2747162,
    "tgn:name":"Wagon Tire Spring",
    "tgn:placetype":[
        "aat:300008697"
    ]
},
  "bbox": [],
  "geometry": {"coordinates":[-119.4667,40.8833],"type":"Point"}
}