{
  "id": 1023141,
  "type": "Feature",
  "properties": {
    "tgn:hierarchy":[
        "tgn:1023141",
        "tgn:1001826",
        "tgn:1000047",
        "tgn:7002456",
        "tgn:1000002",
        "tgn:7029392"
    ],
    "tgn:id":1023141,
    "tgn:name":"Tapau\u00e1",
    "tgn:placetype":[
        "aat:300008347"
    ]
},
  "bbox": [],
  "geometry": {"coordinates":[-63.0667,-5.75],"type":"Point"}
}