{
  "id": 2500819,
  "type": "Feature",
  "properties": {
    "tgn:hierarchy":[
        "tgn:2500819",
        "tgn:1000001",
        "tgn:7012149",
        "tgn:2001123",
        "tgn:7007522",
        "tgn:7029392"
    ],
    "tgn:id":2500819,
    "tgn:name":"McElroys Lake",
    "tgn:placetype":[
        "aat:300008680"
    ]
},
  "bbox": [],
  "geometry": {"coordinates":[-88.5833,32.5333],"type":"Point"}
}