<<<<<<< HEAD
{
  "id": 7489664,
  "type": "Feature",
  "properties": {
    "tgn:hierarchy":[
        "tgn:7489664",
        "tgn:1000004",
        "tgn:7491221",
        "tgn:1000141",
        "tgn:7029392"
    ],
    "tgn:id":7489664,
    "tgn:name":"Dasen Shan",
    "tgn:placetype":[
        "aat:300008795"
    ]
},
  "bbox": [],
  "geometry": {"coordinates":[121.585833,22.010556],"type":"Point"}
}
=======
{"geometry":{"type":"Point","coordinates":[121.585833,22.010556]},"type":"Feature","properties":{"hierarchy":["tgn:7489664","tgn:1000004","tgn:7491221","tgn:1000141","tgn:7029392"],"placetype":["aat:300008795"],"id":7489664,"name:xx":"Dasen Shan"}}
>>>>>>> 03f74aca74312dbeaf24d7e61306dd6a786dc3d0
