{
  "id": 7471230,
  "type": "Feature",
  "properties": {
    "tgn:hierarchy":[
        "tgn:7471230",
        "tgn:7488858",
        "tgn:1000004",
        "tgn:1000141",
        "tgn:7029392"
    ],
    "tgn:id":7471230,
    "tgn:name":"Xinzhuang",
    "tgn:placetype":[
        "aat:300008347"
    ]
},
  "bbox": [],
  "geometry": {"coordinates":[121.166667,24.033333],"type":"Point"}
}