{
  "id": 2070238,
  "type": "Feature",
  "properties": {
    "tgn:hierarchy":[
        "tgn:2070238",
        "tgn:1000001",
        "tgn:7012149",
        "tgn:1002751",
        "tgn:7007568",
        "tgn:7029392"
    ],
    "tgn:id":2070238,
    "tgn:name":"Little Britain",
    "tgn:placetype":[
        "aat:300008347",
        "aat:300387210"
    ]
},
  "bbox": [],
  "geometry": {"coordinates":[-74.1167,41.4667],"type":"Point"}
}