{
  "id": 2782519,
  "type": "Feature",
  "properties": {
    "tgn:hierarchy":[
        "tgn:2782519",
        "tgn:1000001",
        "tgn:7012149",
        "tgn:2002113",
        "tgn:7007827",
        "tgn:7029392"
    ],
    "tgn:id":2782519,
    "tgn:name":"Woolsey Arch",
    "tgn:placetype":[
        "aat:300386837"
    ]
},
  "bbox": [],
  "geometry": {"coordinates":[-111.1833,37.2333],"type":"Point"}
}