{
  "id": 7491841,
  "type": "Feature",
  "properties": {
    "tgn:hierarchy":[
        "tgn:7491841",
        "tgn:7001010",
        "tgn:1000004",
        "tgn:1000141",
        "tgn:7029392"
    ],
    "tgn:id":7491841,
    "tgn:name":"Taluomu Xi",
    "tgn:placetype":[
        "aat:300008699"
    ]
},
  "bbox": [],
  "geometry": {"coordinates":[121.198056,23.36],"type":"Point"}
}