{
  "id": 7132392,
  "type": "Feature",
  "properties": {
    "tgn:hierarchy":[
        "tgn:7132392",
        "tgn:7003669",
        "tgn:1000003",
        "tgn:7000084",
        "tgn:7029392"
    ],
    "tgn:id":7132392,
    "tgn:name":"Mauerhof",
    "tgn:placetype":[
        "aat:300000206"
    ]
},
  "bbox": [],
  "geometry": {"coordinates":[11.95,49.616667],"type":"Point"}
}