{
  "id": 2546713,
  "type": "Feature",
  "properties": {
    "tgn:hierarchy":[
        "tgn:2546713",
        "tgn:1000001",
        "tgn:7012149",
        "tgn:2000181",
        "tgn:7007157",
        "tgn:7029392"
    ],
    "tgn:id":2546713,
    "tgn:name":"North Fork Mad River",
    "tgn:placetype":[
        "aat:300008707"
    ]
},
  "bbox": [],
  "geometry": {"coordinates":[-123.9333,40.9833],"type":"Point"}
}