{
  "id": 2583194,
  "type": "Feature",
  "properties": {
    "tgn:hierarchy":[
        "tgn:2583194",
        "tgn:1000001",
        "tgn:2001485",
        "tgn:7012149",
        "tgn:7007709",
        "tgn:7029392"
    ],
    "tgn:id":2583194,
    "tgn:name":"Pine Log Swamp",
    "tgn:placetype":[
        "aat:300008905"
    ]
},
  "bbox": [],
  "geometry": {"coordinates":[-78.7167,34.3167],"type":"Point"}
}