<<<<<<< HEAD
{
  "id": 2764487,
  "type": "Feature",
  "properties": {
    "tgn:hierarchy":[
        "tgn:2764487",
        "tgn:2001467",
        "tgn:1000001",
        "tgn:7012149",
        "tgn:7007709",
        "tgn:7029392"
    ],
    "tgn:id":2764487,
    "tgn:name":"Whindling Ridge",
    "tgn:placetype":[
        "aat:300266640"
    ]
},
  "bbox": [],
  "geometry": {"coordinates":[-81.6,36.55],"type":"Point"}
}
=======
{"geometry":{"type":"Point","coordinates":[-81.600000,36.550000]},"type":"Feature","properties":{"hierarchy":["tgn:2764487","tgn:2001467","tgn:1000001","tgn:7012149","tgn:7007709","tgn:7029392"],"placetype":["aat:300266640"],"id":2764487,"name:xx":"Whindling Ridge"}}
>>>>>>> 03f74aca74312dbeaf24d7e61306dd6a786dc3d0
