{
  "id": 7319433,
  "type": "Feature",
  "properties": {
    "tgn:hierarchy":[
        "tgn:7319433",
        "tgn:1001708",
        "tgn:1000049",
        "tgn:1000002",
        "tgn:7029392"
    ],
    "tgn:id":7319433,
    "tgn:name":"Alto Santa Cruz",
    "tgn:placetype":[
        "aat:300000206"
    ]
},
  "bbox": [],
  "geometry": {"coordinates":[-70.833333,-33.566667],"type":"Point"}
}