{
  "id": 2184610,
  "type": "Feature",
  "properties": {
    "tgn:hierarchy":[
        "tgn:2184610",
        "tgn:1000001",
        "tgn:7012149",
        "tgn:7007157",
        "tgn:7014516",
        "tgn:7029392"
    ],
    "tgn:id":2184610,
    "tgn:name":"Bodega Rock",
    "tgn:placetype":[
        "aat:300008791"
    ]
},
  "bbox": [],
  "geometry": {"coordinates":[-123.0333,38.2833],"type":"Point"}
}