{
  "id": 2730780,
  "type": "Feature",
  "properties": {
    "tgn:hierarchy":[
        "tgn:2730780",
        "tgn:7006450",
        "tgn:1000001",
        "tgn:7012149",
        "tgn:2000086",
        "tgn:7029392"
    ],
    "tgn:id":2730780,
    "tgn:name":"Tsiu River",
    "tgn:placetype":[
        "aat:300008707"
    ]
},
  "bbox": [],
  "geometry": {"coordinates":[-143.1667,60.15],"type":"Point"}
}