{
  "id": 2773127,
  "type": "Feature",
  "properties": {
    "tgn:hierarchy":[
        "tgn:2773127",
        "tgn:1000001",
        "tgn:7012149",
        "tgn:2001718",
        "tgn:7007708",
        "tgn:7029392"
    ],
    "tgn:id":2773127,
    "tgn:name":"Williams Spring Number Three",
    "tgn:placetype":[
        "aat:300008697"
    ]
},
  "bbox": [],
  "geometry": {"coordinates":[-118.15,43.6333],"type":"Point"}
}