{
  "id": 2319755,
  "type": "Feature",
  "properties": {
    "tgn:hierarchy":[
        "tgn:2319755",
        "tgn:1000001",
        "tgn:2001737",
        "tgn:7012149",
        "tgn:7007712",
        "tgn:7029392"
    ],
    "tgn:id":2319755,
    "tgn:name":"Eureka Lake",
    "tgn:placetype":[
        "aat:300006191"
    ]
},
  "bbox": [],
  "geometry": {"coordinates":[-79.8833,34.6333],"type":"Point"}
}