{
  "id": 7161960,
  "type": "Feature",
  "properties": {
    "tgn:hierarchy":[
        "tgn:7161960",
        "tgn:1000003",
        "tgn:7003688",
        "tgn:7000084",
        "tgn:7029392"
    ],
    "tgn:id":7161960,
    "tgn:name":"Holzsee",
    "tgn:placetype":[
        "aat:300008680"
    ]
},
  "bbox": [],
  "geometry": {"coordinates":[10.183333,54.166667],"type":"Point"}
}