{
  "id": 2052496,
  "type": "Feature",
  "properties": {
    "tgn:hierarchy":[
        "tgn:2052496",
        "tgn:1000001",
        "tgn:7012149",
        "tgn:1002481",
        "tgn:7007520",
        "tgn:7029392"
    ],
    "tgn:id":2052496,
    "tgn:name":"Litchfield",
    "tgn:placetype":[
        "aat:300008347"
    ]
},
  "bbox": [],
  "geometry": {"coordinates":[-84.75,42.0333],"type":"Point"}
}