{
  "id": 2102158,
  "type": "Feature",
  "properties": {
    "tgn:hierarchy":[
        "tgn:2102158",
        "tgn:1000001",
        "tgn:7012149",
        "tgn:2001868",
        "tgn:7007825",
        "tgn:7029392"
    ],
    "tgn:id":2102158,
    "tgn:name":"Witt",
    "tgn:placetype":[
        "aat:300008347"
    ]
},
  "bbox": [],
  "geometry": {"coordinates":[-83.2667,36.15],"type":"Point"}
}