{
  "id": 7544796,
  "type": "Feature",
  "properties": {
    "tgn:hierarchy":[
        "tgn:7544796",
        "tgn:1000004",
        "tgn:7000198",
        "tgn:1001882",
        "tgn:7029392"
    ],
    "tgn:id":7544796,
    "tgn:name:en":"Ald\u016br",
    "tgn:placetype":[
        "aat:300008347"
    ]
},
  "bbox": [],
  "geometry": {"coordinates":[75.666667,13.25],"type":"Point"}
}