{
  "id": 7319649,
  "type": "Feature",
  "properties": {
    "tgn:hierarchy":[
        "tgn:7319649",
        "tgn:1001768",
        "tgn:1000049",
        "tgn:1000002",
        "tgn:7029392"
    ],
    "tgn:id":7319649,
    "tgn:name":"Agua del Litre",
    "tgn:placetype":[
        "aat:300387200"
    ]
},
  "bbox": [],
  "geometry": {"coordinates":[-70.916667,-32.566667],"type":"Point"}
}