{
  "id": 2198551,
  "type": "Feature",
  "properties": {
    "tgn:hierarchy":[
        "tgn:2198551",
        "tgn:1000001",
        "tgn:7012149",
        "tgn:2002288",
        "tgn:7013961",
        "tgn:7029392"
    ],
    "tgn:id":2198551,
    "tgn:name":"Browns Mill",
    "tgn:placetype":[
        "aat:300008347"
    ]
},
  "bbox": [],
  "geometry": {"coordinates":[-79.8167,39.4667],"type":"Point"}
}