{
  "id": 1050643,
  "type": "Feature",
  "properties": {
    "tgn:hierarchy":[
        "tgn:1050643",
        "tgn:7002444",
        "tgn:1000003",
        "tgn:7008076",
        "tgn:7008591",
        "tgn:7029392"
    ],
    "tgn:id":1050643,
    "tgn:name:en":"East Wemyss",
    "tgn:placetype":[
        "aat:300008347"
    ]
},
  "bbox": [],
  "geometry": {"coordinates":[-3.066667,56.15],"type":"Point"}
}