<<<<<<< HEAD
{
  "id": 2251695,
  "type": "Feature",
  "properties": {
    "tgn:hierarchy":[
        "tgn:2251695",
        "tgn:7016099",
        "tgn:1000001",
        "tgn:7012149",
        "tgn:7007516",
        "tgn:7029392"
    ],
    "tgn:id":2251695,
    "tgn:name":"Compass Run",
    "tgn:placetype":[
        "aat:300008699"
    ]
},
  "bbox": [],
  "geometry": {"coordinates":[-76.8,39.6333],"type":"Point"}
}
=======
{"geometry":{"type":"Point","coordinates":[-76.800000,39.633300]},"type":"Feature","properties":{"hierarchy":["tgn:2251695","tgn:7016099","tgn:1000001","tgn:7012149","tgn:7007516","tgn:7029392"],"placetype":["aat:300008699"],"id":2251695,"name:xx":"Compass Run"}}
>>>>>>> 03f74aca74312dbeaf24d7e61306dd6a786dc3d0
