<<<<<<< HEAD
{
  "id": 7481917,
  "type": "Feature",
  "properties": {
    "tgn:hierarchy":[
        "tgn:7481917",
        "tgn:1000004",
        "tgn:7001013",
        "tgn:1000141",
        "tgn:7029392"
    ],
    "tgn:id":7481917,
    "tgn:name":"Houhu Xi",
    "tgn:placetype":[
        "aat:300008699"
    ]
},
  "bbox": [],
  "geometry": {"coordinates":[121.046667,24.992222],"type":"Point"}
}
=======
{"geometry":{"type":"Point","coordinates":[121.046667,24.992222]},"type":"Feature","properties":{"hierarchy":["tgn:7481917","tgn:1000004","tgn:7001013","tgn:1000141","tgn:7029392"],"placetype":["aat:300008699"],"id":7481917,"name:xx":"Houhu Xi"}}
>>>>>>> 03f74aca74312dbeaf24d7e61306dd6a786dc3d0
