{
  "id": 2458171,
  "type": "Feature",
  "properties": {
    "tgn:hierarchy":[
        "tgn:2458171",
        "tgn:1000001",
        "tgn:7012149",
        "tgn:2001926",
        "tgn:7007825",
        "tgn:7029392"
    ],
    "tgn:id":2458171,
    "tgn:name":"Little Mountain",
    "tgn:placetype":[
        "aat:300008798"
    ]
},
  "bbox": [],
  "geometry": {"coordinates":[-82.6667,36.4333],"type":"Point"}
}