<<<<<<< HEAD
{
  "id": 7375767,
  "type": "Feature",
  "properties": {
    "tgn:hierarchy":[
        "tgn:7375767",
        "tgn:1001853",
        "tgn:1000001",
        "tgn:7005560",
        "tgn:7029392"
    ],
    "tgn:id":7375767,
    "tgn:name":"Llano, Mesa del",
    "tgn:placetype":[
        "aat:300008811"
    ]
},
  "bbox": [],
  "geometry": {"coordinates":[-101.783333,25.333333],"type":"Point"}
}
=======
{"geometry":{"type":"Point","coordinates":[-101.783333,25.333333]},"type":"Feature","properties":{"hierarchy":["tgn:7375767","tgn:1001853","tgn:1000001","tgn:7005560","tgn:7029392"],"placetype":["aat:300008811"],"id":7375767,"name:xx":"Llano, Mesa del"}}
>>>>>>> 03f74aca74312dbeaf24d7e61306dd6a786dc3d0
