{
  "id": 7120928,
  "type": "Feature",
  "properties": {
    "tgn:hierarchy":[
        "tgn:7120928",
        "tgn:7003669",
        "tgn:1000003",
        "tgn:7000084",
        "tgn:7029392"
    ],
    "tgn:id":7120928,
    "tgn:name":"Plantage",
    "tgn:placetype":[
        "aat:300008347"
    ]
},
  "bbox": [],
  "geometry": {"coordinates":[13.433333,48.583333],"type":"Point"}
}