{
  "id": 2617914,
  "type": "Feature",
  "properties": {
    "tgn:hierarchy":[
        "tgn:2617914",
        "tgn:1000001",
        "tgn:7006451",
        "tgn:7012149",
        "tgn:2000100",
        "tgn:7029392"
    ],
    "tgn:id":2617914,
    "tgn:name":"Ridge Tank",
    "tgn:placetype":[
        "aat:300006191"
    ]
},
  "bbox": [],
  "geometry": {"coordinates":[-111.15,31.8333],"type":"Point"}
}