{
  "id": 2709024,
  "type": "Feature",
  "properties": {
    "tgn:hierarchy":[
        "tgn:2709024",
        "tgn:7013349",
        "tgn:1000001",
        "tgn:7012149",
        "tgn:7007708",
        "tgn:7029392"
    ],
    "tgn:id":2709024,
    "tgn:name":"T Reservoir",
    "tgn:placetype":[
        "aat:300006191"
    ]
},
  "bbox": [],
  "geometry": {"coordinates":[-117.55,44.6833],"type":"Point"}
}