{
  "id": 7193502,
  "type": "Feature",
  "properties": {
    "tgn:hierarchy":[
        "tgn:7193502",
        "tgn:7003669",
        "tgn:1000003",
        "tgn:7000084",
        "tgn:7029392"
    ],
    "tgn:id":7193502,
    "tgn:name":"Frankldorf",
    "tgn:placetype":[
        "aat:300008347"
    ]
},
  "bbox": [],
  "geometry": {"coordinates":[13.483333,48.633333],"type":"Point"}
}