{
  "id": 1071860,
  "type": "Feature",
  "properties": {
    "tgn:hierarchy":[
        "tgn:1071860",
        "tgn:1000004",
        "tgn:7002079",
        "tgn:1000111",
        "tgn:7029392"
    ],
    "tgn:id":1071860,
    "tgn:name":"Shuikoushan",
    "tgn:placetype":[
        "aat:300008347"
    ]
},
  "bbox": [],
  "geometry": {"coordinates":[112.5833,26.55],"type":"Point"}
}