{
  "id": 7482854,
  "type": "Feature",
  "properties": {
    "tgn:hierarchy":[
        "tgn:7482854",
        "tgn:1000004",
        "tgn:7001014",
        "tgn:1000141",
        "tgn:7029392"
    ],
    "tgn:id":7482854,
    "tgn:name":"Xishi Qiao",
    "tgn:placetype":[
        "aat:300007836"
    ]
},
  "bbox": [],
  "geometry": {"coordinates":[120.248889,23.671944],"type":"Point"}
}