{
  "id": 2174381,
  "type": "Feature",
  "properties": {
    "tgn:hierarchy":[
        "tgn:2174381",
        "tgn:1000001",
        "tgn:7012149",
        "tgn:2002113",
        "tgn:7007827",
        "tgn:7029392"
    ],
    "tgn:id":2174381,
    "tgn:name":"Bishop Canyon",
    "tgn:placetype":[
        "aat:300008761"
    ]
},
  "bbox": [],
  "geometry": {"coordinates":[-112.65,37.3333],"type":"Point"}
}