{
  "id": 7270746,
  "type": "Feature",
  "properties": {
    "tgn:concordances":{
        "gn:id":"2747239"
    },
    "tgn:hierarchy":[
        "tgn:7270746",
        "tgn:1000003",
        "tgn:7006951",
        "tgn:7016845",
        "tgn:7029392"
    ],
    "tgn:id":7270746,
    "tgn:name:nl":"Sint Maartensvlotbrug",
    "tgn:placetype":[
        "aat:300008347"
    ]
},
  "bbox": [],
  "geometry": {"coordinates":[4.716667,52.783333],"type":"Point"}
}