{
  "id": 2100114,
  "type": "Feature",
  "properties": {
    "tgn:hierarchy":[
        "tgn:2100114",
        "tgn:1000001",
        "tgn:2001840",
        "tgn:7012149",
        "tgn:7007825",
        "tgn:7029392"
    ],
    "tgn:id":2100114,
    "tgn:name":"Litton",
    "tgn:placetype":[
        "aat:300008347",
        "aat:300387210"
    ]
},
  "bbox": [],
  "geometry": {"coordinates":[-85.0333,35.7333],"type":"Point"}
}