<<<<<<< HEAD
{
  "id": 7350002,
  "type": "Feature",
  "properties": {
    "tgn:hierarchy":[
        "tgn:7350002",
        "tgn:7005581",
        "tgn:1000001",
        "tgn:7005560",
        "tgn:7029392"
    ],
    "tgn:id":7350002,
    "tgn:name":"Aguja, Cerro de la",
    "tgn:placetype":[
        "aat:300008795"
    ]
},
  "bbox": [],
  "geometry": {"coordinates":[-106.95,30.1],"type":"Point"}
}
=======
{"geometry":{"type":"Point","coordinates":[-106.950000,30.100000]},"type":"Feature","properties":{"hierarchy":["tgn:7350002","tgn:7005581","tgn:1000001","tgn:7005560","tgn:7029392"],"placetype":["aat:300008795"],"id":7350002,"name:xx":"Aguja, Cerro de la"}}
>>>>>>> 03f74aca74312dbeaf24d7e61306dd6a786dc3d0
