{
  "id": 2564823,
  "type": "Feature",
  "properties": {
    "tgn:hierarchy":[
        "tgn:2564823",
        "tgn:1000001",
        "tgn:7012149",
        "tgn:2001918",
        "tgn:7007825",
        "tgn:7029392"
    ],
    "tgn:id":2564823,
    "tgn:name":"Paddys Knob",
    "tgn:placetype":[
        "aat:300008798"
    ]
},
  "bbox": [],
  "geometry": {"coordinates":[-82.2667,36.45],"type":"Point"}
}