{
  "id": 2584521,
  "type": "Feature",
  "properties": {
    "tgn:hierarchy":[
        "tgn:2584521",
        "tgn:1000001",
        "tgn:2001473",
        "tgn:7012149",
        "tgn:7007709",
        "tgn:7029392"
    ],
    "tgn:id":2584521,
    "tgn:name":"Piney Mountain",
    "tgn:placetype":[
        "aat:300008798"
    ]
},
  "bbox": [],
  "geometry": {"coordinates":[-82.7167,35.5167],"type":"Point"}
}