{
  "id": 7260771,
  "type": "Feature",
  "properties": {
    "tgn:hierarchy":[
        "tgn:7260771",
        "tgn:7003619",
        "tgn:1000003",
        "tgn:7016845",
        "tgn:7029392"
    ],
    "tgn:id":7260771,
    "tgn:name:nl":"Boswachterij Groesbeek",
    "tgn:placetype":[
        "aat:300008187"
    ]
},
  "bbox": [],
  "geometry": {"coordinates":[5.916667,51.766667],"type":"Point"}
}