{
  "id": 2270352,
  "type": "Feature",
  "properties": {
    "tgn:hierarchy":[
        "tgn:2270352",
        "tgn:1000001",
        "tgn:2000261",
        "tgn:7012149",
        "tgn:7007240",
        "tgn:7029392"
    ],
    "tgn:id":2270352,
    "tgn:name":"Crystal Lake",
    "tgn:placetype":[
        "aat:300008680"
    ]
},
  "bbox": [],
  "geometry": {"coordinates":[-82.0333,29.8167],"type":"Point"}
}