{
  "id": 1089278,
  "type": "Feature",
  "properties": {
    "tgn:hierarchy":[
        "tgn:1089278",
        "tgn:7001242",
        "tgn:7016755",
        "tgn:1000159",
        "tgn:7029392"
    ],
    "tgn:id":1089278,
    "tgn:name":"Mabenge",
    "tgn:placetype":[
        "aat:300008347"
    ]
},
  "bbox": [],
  "geometry": {"coordinates":[24.15,4.2333],"type":"Point"}
}