{
  "id": 7400423,
  "type": "Feature",
  "properties": {
    "tgn:hierarchy":[
        "tgn:7400423",
        "tgn:1000001",
        "tgn:7005599",
        "tgn:7005560",
        "tgn:7029392"
    ],
    "tgn:id":7400423,
    "tgn:name":"Horconcitos",
    "tgn:placetype":[
        "aat:300008347"
    ]
},
  "bbox": [],
  "geometry": {"coordinates":[-97.75,21.858333],"type":"Point"}
}