{
  "id": 2499186,
  "type": "Feature",
  "properties": {
    "tgn:hierarchy":[
        "tgn:2499186",
        "tgn:1000001",
        "tgn:7012149",
        "tgn:7013961",
        "tgn:7029392"
    ],
    "tgn:id":2499186,
    "tgn:name":"McCausland Run",
    "tgn:placetype":[
        "aat:300008699"
    ]
},
  "bbox": [],
  "geometry": {"coordinates":[-81.9833,38.6667],"type":"Point"}
}