{
  "id": 2541599,
  "type": "Feature",
  "properties": {
    "tgn:hierarchy":[
        "tgn:2541599",
        "tgn:2000090",
        "tgn:1000001",
        "tgn:7006451",
        "tgn:7012149",
        "tgn:7029392"
    ],
    "tgn:id":2541599,
    "tgn:name":"Nine Bar Three Tank",
    "tgn:placetype":[
        "aat:300006191"
    ]
},
  "bbox": [],
  "geometry": {"coordinates":[-109.35,33.8333],"type":"Point"}
}