{
  "id": 7522569,
  "type": "Feature",
  "properties": {
    "tgn:hierarchy":[
        "tgn:7522569",
        "tgn:7001242",
        "tgn:7016833",
        "tgn:7000122",
        "tgn:7029392"
    ],
    "tgn:id":7522569,
    "tgn:name:en":"Dibeira Sharq",
    "tgn:placetype":[
        "aat:300055621"
    ]
},
  "bbox": [],
  "geometry": {"coordinates":[31.466667,22.033333],"type":"Point"}
}