{
  "id": 2491821,
  "type": "Feature",
  "properties": {
    "tgn:hierarchy":[
        "tgn:2491821",
        "tgn:1000001",
        "tgn:7012149",
        "tgn:2000227",
        "tgn:7007158",
        "tgn:7029392"
    ],
    "tgn:id":2491821,
    "tgn:name":"Mararski Lake",
    "tgn:placetype":[
        "aat:300008680"
    ]
},
  "bbox": [],
  "geometry": {"coordinates":[-104.3167,37.0167],"type":"Point"}
}