{
  "id": 7180620,
  "type": "Feature",
  "properties": {
    "tgn:hierarchy":[
        "tgn:7180620",
        "tgn:1000003",
        "tgn:7003682",
        "tgn:7000084",
        "tgn:7029392"
    ],
    "tgn:id":7180620,
    "tgn:name":"Galgen-Berg",
    "tgn:placetype":[
        "aat:300008777"
    ]
},
  "bbox": [],
  "geometry": {"coordinates":[7.516667,49.683333],"type":"Point"}
}