{
  "id": 1111541,
  "type": "Feature",
  "properties": {
    "tgn:hierarchy":[
        "tgn:1111541",
        "tgn:7001242",
        "tgn:7000613",
        "tgn:1000172",
        "tgn:7029392"
    ],
    "tgn:id":1111541,
    "tgn:name":"Nash\u016b\u02bb, W\u0101d\u012b an",
    "tgn:placetype":[
        "aat:300008773"
    ]
},
  "bbox": [],
  "geometry": {"coordinates":[14.1833,26.35],"type":"Point"}
}