<<<<<<< HEAD
{
  "id": 2760828,
  "type": "Feature",
  "properties": {
    "tgn:hierarchy":[
        "tgn:2760828",
        "tgn:1000001",
        "tgn:7012149",
        "tgn:2000230",
        "tgn:7007158",
        "tgn:7029392"
    ],
    "tgn:id":2760828,
    "tgn:name":"West Hawxhurst Creek",
    "tgn:placetype":[
        "aat:300008706"
    ]
},
  "bbox": [],
  "geometry": {"coordinates":[-107.8833,39.35],"type":"Point"}
}
=======
{"geometry":{"type":"Point","coordinates":[-107.883300,39.350000]},"type":"Feature","properties":{"hierarchy":["tgn:2760828","tgn:1000001","tgn:7012149","tgn:2000230","tgn:7007158","tgn:7029392"],"placetype":["aat:300008706"],"id":2760828,"name:xx":"West Hawxhurst Creek"}}
>>>>>>> 03f74aca74312dbeaf24d7e61306dd6a786dc3d0
