{
  "id": 2760828,
  "type": "Feature",
  "properties": {
    "tgn:hierarchy":[
        "tgn:2760828",
        "tgn:1000001",
        "tgn:7012149",
        "tgn:2000230",
        "tgn:7007158",
        "tgn:7029392"
    ],
    "tgn:id":2760828,
    "tgn:name":"West Hawxhurst Creek",
    "tgn:placetype":[
        "aat:300008706"
    ]
},
  "bbox": [],
  "geometry": {"coordinates":[-107.8833,39.35],"type":"Point"}
}