{
  "id": 1047121,
  "type": "Feature",
  "properties": {
    "tgn:hierarchy":[
        "tgn:1047121",
        "tgn:7002994",
        "tgn:1000003",
        "tgn:7002997",
        "tgn:1000080",
        "tgn:7029392"
    ],
    "tgn:id":1047121,
    "tgn:name":"Tombolo",
    "tgn:placetype":[
        "aat:300008347"
    ]
},
  "bbox": [],
  "geometry": {"coordinates":[11.833333,45.633333],"type":"Point"}
}