{
  "id": 7592272,
  "type": "Feature",
  "properties": {
    "tgn:hierarchy":[
        "tgn:7592272",
        "tgn:1000004",
        "tgn:7000198",
        "tgn:7000799",
        "tgn:7029392"
    ],
    "tgn:id":7592272,
    "tgn:name:en":"Parah",
    "tgn:placetype":[
        "aat:300008347"
    ]
},
  "bbox": [],
  "geometry": {"coordinates":[74.948292,32.970501],"type":"Point"}
}