{
  "id": 1092546,
  "type": "Feature",
  "properties": {
    "tgn:hierarchy":[
        "tgn:1092546",
        "tgn:7016459",
        "tgn:7001242",
        "tgn:1000189",
        "tgn:7029392"
    ],
    "tgn:id":1092546,
    "tgn:name":"Sokone",
    "tgn:placetype":[
        "aat:300008347"
    ]
},
  "bbox": [],
  "geometry": {"coordinates":[-16.3667,13.8833],"type":"Point"}
}