{
  "id": 7349703,
  "type": "Feature",
  "properties": {
    "tgn:hierarchy":[
        "tgn:7349703",
        "tgn:1000001",
        "tgn:7005595",
        "tgn:7005560",
        "tgn:7029392"
    ],
    "tgn:id":7349703,
    "tgn:name":"Abuya",
    "tgn:placetype":[
        "aat:300007783"
    ]
},
  "bbox": [],
  "geometry": {"coordinates":[-107.096389,24.183056],"type":"Point"}
}