{
  "id": 2446321,
  "type": "Feature",
  "properties": {
    "tgn:hierarchy":[
        "tgn:2446321",
        "tgn:1000001",
        "tgn:2000872",
        "tgn:7012149",
        "tgn:7007256",
        "tgn:7029392"
    ],
    "tgn:id":2446321,
    "tgn:name":"Lewis Creek",
    "tgn:placetype":[
        "aat:300008706"
    ]
},
  "bbox": [],
  "geometry": {"coordinates":[-90.9833,30.85],"type":"Point"}
}