{
  "id": 2162123,
  "type": "Feature",
  "properties": {
    "tgn:hierarchy":[
        "tgn:2162123",
        "tgn:1000001",
        "tgn:7012149",
        "tgn:2001706",
        "tgn:7007708",
        "tgn:7029392"
    ],
    "tgn:id":2162123,
    "tgn:name":"Belmont",
    "tgn:placetype":[
        "aat:300008347"
    ]
},
  "bbox": [],
  "geometry": {"coordinates":[-123.0833,43.4333],"type":"Point"}
}