{
  "id": 2711549,
  "type": "Feature",
  "properties": {
    "tgn:hierarchy":[
        "tgn:2711549",
        "tgn:1000001",
        "tgn:7012149",
        "tgn:2002090",
        "tgn:7007826",
        "tgn:7029392"
    ],
    "tgn:id":2711549,
    "tgn:name":"Tapon Tank",
    "tgn:placetype":[
        "aat:300006191"
    ]
},
  "bbox": [],
  "geometry": {"coordinates":[-99.6167,27.9167],"type":"Point"}
}