{
  "id": 2240058,
  "type": "Feature",
  "properties": {
    "tgn:hierarchy":[
        "tgn:2240058",
        "tgn:1000001",
        "tgn:7012149",
        "tgn:7007157",
        "tgn:2000189",
        "tgn:7029392"
    ],
    "tgn:id":2240058,
    "tgn:name":"Cinnabar Mine",
    "tgn:placetype":[
        "aat:300000390"
    ]
},
  "bbox": [],
  "geometry": {"coordinates":[-122.8667,41.95],"type":"Point"}
}