{
  "id": 2234887,
  "type": "Feature",
  "properties": {
    "tgn:hierarchy":[
        "tgn:2234887",
        "tgn:1000001",
        "tgn:7012149",
        "tgn:2002289",
        "tgn:7013961",
        "tgn:7029392"
    ],
    "tgn:id":2234887,
    "tgn:name":"Cherry Fork",
    "tgn:placetype":[
        "aat:300008699"
    ]
},
  "bbox": [],
  "geometry": {"coordinates":[-81.7667,38.5833],"type":"Point"}
}