{
  "id": 2287805,
  "type": "Feature",
  "properties": {
    "tgn:hierarchy":[
        "tgn:2287805",
        "tgn:1000001",
        "tgn:2000957",
        "tgn:7012149",
        "tgn:7007520",
        "tgn:7029392"
    ],
    "tgn:id":2287805,
    "tgn:name":"Dillon Relaid Drain",
    "tgn:placetype":[
        "aat:300006075"
    ]
},
  "bbox": [],
  "geometry": {"coordinates":[-84.9167,42.4833],"type":"Point"}
}