{
  "id": 2128341,
  "type": "Feature",
  "properties": {
    "tgn:hierarchy":[
        "tgn:2128341",
        "tgn:1000001",
        "tgn:7012149",
        "tgn:2000926",
        "tgn:7007515",
        "tgn:7029392"
    ],
    "tgn:id":2128341,
    "tgn:name":"Alder Brook",
    "tgn:placetype":[
        "aat:300008699"
    ]
},
  "bbox": [],
  "geometry": {"coordinates":[-70.8833,44.1667],"type":"Point"}
}