{
  "id": 7516608,
  "type": "Feature",
  "properties": {
    "tgn:hierarchy":[
        "tgn:7516608",
        "tgn:7520092",
        "tgn:1008380",
        "tgn:1000226",
        "tgn:1000006",
        "tgn:7029392"
    ],
    "tgn:id":7516608,
    "tgn:name:en":"Mangarakai Stream",
    "tgn:placetype":[
        "aat:300008699"
    ]
},
  "bbox": [],
  "geometry": {"coordinates":[178.25,-38.15],"type":"Point"}
}