{
  "id": 2755115,
  "type": "Feature",
  "properties": {
    "tgn:hierarchy":[
        "tgn:2755115",
        "tgn:2000297",
        "tgn:1000001",
        "tgn:7012149",
        "tgn:7007248",
        "tgn:7029392"
    ],
    "tgn:id":2755115,
    "tgn:name":"Webb Creek",
    "tgn:placetype":[
        "aat:300008706"
    ]
},
  "bbox": [],
  "geometry": {"coordinates":[-83.4667,34.35],"type":"Point"}
}