{
  "id": 2289542,
  "type": "Feature",
  "properties": {
    "tgn:hierarchy":[
        "tgn:2289542",
        "tgn:1000001",
        "tgn:7012149",
        "tgn:1002599",
        "tgn:7007708",
        "tgn:7029392"
    ],
    "tgn:id":2289542,
    "tgn:name":"Dixon Creek",
    "tgn:placetype":[
        "aat:300008706"
    ]
},
  "bbox": [],
  "geometry": {"coordinates":[-123.85,44.5833],"type":"Point"}
}