{
  "id": 1022820,
  "type": "Feature",
  "properties": {
    "tgn:hierarchy":[
        "tgn:1022820",
        "tgn:7006246",
        "tgn:1000047",
        "tgn:7002455",
        "tgn:1000002",
        "tgn:7029392"
    ],
    "tgn:id":1022820,
    "tgn:name":"S\u00e3o Jo\u00e3o dos Patos",
    "tgn:placetype":[
        "aat:300008347"
    ]
},
  "bbox": [],
  "geometry": {"coordinates":[-43.7333,-6.4833],"type":"Point"}
}