{
  "id": 7486803,
  "type": "Feature",
  "properties": {
    "tgn:hierarchy":[
        "tgn:7486803",
        "tgn:1000004",
        "tgn:7001009",
        "tgn:1000141",
        "tgn:7029392"
    ],
    "tgn:id":7486803,
    "tgn:name":"Lifen Li",
    "tgn:placetype":[
        "aat:300387173"
    ]
},
  "bbox": [],
  "geometry": {"coordinates":[120.579722,24.246389],"type":"Point"}
}