{
  "id": 1021157,
  "type": "Feature",
  "properties": {
    "tgn:hierarchy":[
        "tgn:1021157",
        "tgn:7006260",
        "tgn:7002454",
        "tgn:1000047",
        "tgn:1000002",
        "tgn:7029392"
    ],
    "tgn:id":1021157,
    "tgn:name":"Chapada dos Guimar\u00e3es",
    "tgn:placetype":[
        "aat:300008347"
    ]
},
  "bbox": [],
  "geometry": {"coordinates":[-55.7333,-15.3333],"type":"Point"}
}