{
  "id": 2231989,
  "type": "Feature",
  "properties": {
    "tgn:hierarchy":[
        "tgn:2231989",
        "tgn:1000001",
        "tgn:7012149",
        "tgn:2000986",
        "tgn:7007520",
        "tgn:7029392"
    ],
    "tgn:id":2231989,
    "tgn:name":"Champagne Creek",
    "tgn:placetype":[
        "aat:300008706"
    ]
},
  "bbox": [],
  "geometry": {"coordinates":[-89.05,46.55],"type":"Point"}
}