{
  "id": 2605375,
  "type": "Feature",
  "properties": {
    "tgn:hierarchy":[
        "tgn:2605375",
        "tgn:1000001",
        "tgn:2002149",
        "tgn:7012149",
        "tgn:7007919",
        "tgn:7029392"
    ],
    "tgn:id":2605375,
    "tgn:name":"Ragland Lake",
    "tgn:placetype":[
        "aat:300006191"
    ]
},
  "bbox": [],
  "geometry": {"coordinates":[-78.6667,37.5833],"type":"Point"}
}