{
  "id": 2297136,
  "type": "Feature",
  "properties": {
    "tgn:hierarchy":[
        "tgn:2297136",
        "tgn:1000001",
        "tgn:7012149",
        "tgn:2002166",
        "tgn:7007919",
        "tgn:7029392"
    ],
    "tgn:id":2297136,
    "tgn:name":"Dry Creek",
    "tgn:placetype":[
        "aat:300008706"
    ]
},
  "bbox": [],
  "geometry": {"coordinates":[-78.85,36.5667],"type":"Point"}
}