<<<<<<< HEAD
{
  "id": 2157457,
  "type": "Feature",
  "properties": {
    "tgn:hierarchy":[
        "tgn:2157457",
        "tgn:1000001",
        "tgn:2001790",
        "tgn:7012149",
        "tgn:7007713",
        "tgn:7029392"
    ],
    "tgn:id":2157457,
    "tgn:name":"Beaver Creek",
    "tgn:placetype":[
        "aat:300008706"
    ]
},
  "bbox": [],
  "geometry": {"coordinates":[-100.5167,45.25],"type":"Point"}
}
=======
{"geometry":{"type":"Point","coordinates":[-100.516700,45.250000]},"type":"Feature","properties":{"hierarchy":["tgn:2157457","tgn:1000001","tgn:2001790","tgn:7012149","tgn:7007713","tgn:7029392"],"placetype":["aat:300008706"],"id":2157457,"name:xx":"Beaver Creek"}}
>>>>>>> 03f74aca74312dbeaf24d7e61306dd6a786dc3d0
