<<<<<<< HEAD
{
  "id": 7021434,
  "type": "Feature",
  "properties": {
    "tgn:hierarchy":[
        "tgn:7021434",
        "tgn:7002659",
        "tgn:1000001",
        "tgn:7012149",
        "tgn:2000047",
        "tgn:7029392"
    ],
    "tgn:id":7021434,
    "tgn:name":"Devils Spring Cave",
    "tgn:placetype":[
        "aat:300008746"
    ]
},
  "bbox": [],
  "geometry": {"coordinates":[-86.15,34.5333],"type":"Point"}
}
=======
{"geometry":{"type":"Point","coordinates":[-86.150000,34.533300]},"type":"Feature","properties":{"hierarchy":["tgn:7021434","tgn:7002659","tgn:1000001","tgn:7012149","tgn:2000047","tgn:7029392"],"placetype":["aat:300008746"],"id":7021434,"name:xx":"Devils Spring Cave"}}
>>>>>>> 03f74aca74312dbeaf24d7e61306dd6a786dc3d0
