{
  "id": 7009458,
  "type": "Feature",
  "properties": {
    "tgn:hierarchy":[
        "tgn:7009458",
        "tgn:1000003",
        "tgn:7002882",
        "tgn:1000070",
        "tgn:7029392"
    ],
    "tgn:id":7009458,
    "tgn:name":"Quillebeuf",
    "tgn:placetype":[
        "aat:300008347"
    ]
},
  "bbox": [],
  "geometry": {"coordinates":[0.5333,49.4667],"type":"Point"}
}