{
  "id": 1063689,
  "type": "Feature",
  "properties": {
    "tgn:hierarchy":[
        "tgn:1063689",
        "tgn:1000403",
        "tgn:1000003",
        "tgn:1000097",
        "tgn:7029392"
    ],
    "tgn:id":1063689,
    "tgn:name":"Sunnansj\u00f6",
    "tgn:placetype":[
        "aat:300008347"
    ]
},
  "bbox": [],
  "geometry": {"coordinates":[14.95,60.2167],"type":"Point"}
}