{
  "id": 2382134,
  "type": "Feature",
  "properties": {
    "tgn:hierarchy":[
        "tgn:2382134",
        "tgn:1000001",
        "tgn:7012149",
        "tgn:2001461",
        "tgn:7007568",
        "tgn:7029392"
    ],
    "tgn:id":2382134,
    "tgn:name":"Haymeadow Brook",
    "tgn:placetype":[
        "aat:300008699"
    ]
},
  "bbox": [],
  "geometry": {"coordinates":[-73.5167,43.8333],"type":"Point"}
}