{
  "id": 1108365,
  "type": "Feature",
  "properties": {
    "tgn:hierarchy":[
        "tgn:1108365",
        "tgn:7005735",
        "tgn:7005685",
        "tgn:1000001",
        "tgn:7029392"
    ],
    "tgn:id":1108365,
    "tgn:name":"Chilkat Pass",
    "tgn:placetype":[
        "aat:300259572"
    ]
},
  "bbox": [],
  "geometry": {"coordinates":[-136.5833,59.7167],"type":"Point"}
}