{
  "id": 2672199,
  "type": "Feature",
  "properties": {
    "tgn:hierarchy":[
        "tgn:2672199",
        "tgn:1000001",
        "tgn:1002714",
        "tgn:7012149",
        "tgn:7007159",
        "tgn:7029392"
    ],
    "tgn:id":2672199,
    "tgn:name":"Smiths Neck",
    "tgn:placetype":[
        "aat:300008850"
    ]
},
  "bbox": [],
  "geometry": {"coordinates":[-72.3167,41.2833],"type":"Point"}
}