{
  "id": 7399651,
  "type": "Feature",
  "properties": {
    "tgn:hierarchy":[
        "tgn:7399651",
        "tgn:1000001",
        "tgn:7005593",
        "tgn:7005560",
        "tgn:7029392"
    ],
    "tgn:id":7399651,
    "tgn:name":"El Pilar",
    "tgn:placetype":[
        "aat:300008347"
    ]
},
  "bbox": [],
  "geometry": {"coordinates":[-100.283333,20.758333],"type":"Point"}
}