{
  "id": 2630185,
  "type": "Feature",
  "properties": {
    "tgn:hierarchy":[
        "tgn:2630185",
        "tgn:1000001",
        "tgn:7012149",
        "tgn:2001661",
        "tgn:7007707",
        "tgn:7029392"
    ],
    "tgn:id":2630185,
    "tgn:name":"Rough Canyon",
    "tgn:placetype":[
        "aat:300008761"
    ]
},
  "bbox": [],
  "geometry": {"coordinates":[-95.3167,35.0167],"type":"Point"}
}