{
  "id": 2607267,
  "type": "Feature",
  "properties": {
    "tgn:hierarchy":[
        "tgn:2607267",
        "tgn:1000001",
        "tgn:7012149",
        "tgn:2001915",
        "tgn:7007825",
        "tgn:7029392"
    ],
    "tgn:id":2607267,
    "tgn:name":"Randolph Point",
    "tgn:placetype":[
        "aat:300008850"
    ]
},
  "bbox": [],
  "geometry": {"coordinates":[-90.0833,35.3333],"type":"Point"}
}