{
  "id": 2252648,
  "type": "Feature",
  "properties": {
    "tgn:hierarchy":[
        "tgn:2252648",
        "tgn:1000001",
        "tgn:7012149",
        "tgn:7014600",
        "tgn:7007568",
        "tgn:7029392"
    ],
    "tgn:id":2252648,
    "tgn:name":"Connellys Cove",
    "tgn:placetype":[
        "aat:300132316"
    ]
},
  "bbox": [],
  "geometry": {"coordinates":[-76.9333,43.25],"type":"Point"}
}