{
  "id": 2004380,
  "type": "Feature",
  "properties": {
    "tgn:hierarchy":[
        "tgn:2004380",
        "tgn:7002659",
        "tgn:1000001",
        "tgn:2000016",
        "tgn:7012149",
        "tgn:7029392"
    ],
    "tgn:id":2004380,
    "tgn:name":"Margerum",
    "tgn:placetype":[
        "aat:300008347"
    ]
},
  "bbox": [],
  "geometry": {"coordinates":[-88.0667,34.7667],"type":"Point"}
}