{
  "id": 2224910,
  "type": "Feature",
  "properties": {
    "tgn:hierarchy":[
        "tgn:2224910",
        "tgn:1000001",
        "tgn:7012149",
        "tgn:2000363",
        "tgn:7007248",
        "tgn:7029392"
    ],
    "tgn:id":2224910,
    "tgn:name":"Casselberry Lake",
    "tgn:placetype":[
        "aat:300006191"
    ]
},
  "bbox": [],
  "geometry": {"coordinates":[-84.9833,32.65],"type":"Point"}
}