<<<<<<< HEAD
{
  "id": 7352032,
  "type": "Feature",
  "properties": {
    "tgn:hierarchy":[
        "tgn:7352032",
        "tgn:7005583",
        "tgn:1000001",
        "tgn:7005560",
        "tgn:7029392"
    ],
    "tgn:id":7352032,
    "tgn:name":"Arroyo Verde",
    "tgn:placetype":[
        "aat:300008347"
    ]
},
  "bbox": [],
  "geometry": {"coordinates":[-104.166667,23.183333],"type":"Point"}
}
=======
{"geometry":{"type":"Point","coordinates":[-104.166667,23.183333]},"type":"Feature","properties":{"hierarchy":["tgn:7352032","tgn:7005583","tgn:1000001","tgn:7005560","tgn:7029392"],"placetype":["aat:300008347"],"id":7352032,"name:xx":"Arroyo Verde"}}
>>>>>>> 03f74aca74312dbeaf24d7e61306dd6a786dc3d0
