<<<<<<< HEAD
{
  "id": 2253943,
  "type": "Feature",
  "properties": {
    "tgn:hierarchy":[
        "tgn:2253943",
        "tgn:1000001",
        "tgn:2002367",
        "tgn:7012149",
        "tgn:7007923",
        "tgn:7029392"
    ],
    "tgn:id":2253943,
    "tgn:name":"Cookstove Prong Olmstead Creek",
    "tgn:placetype":[
        "aat:300008706"
    ]
},
  "bbox": [],
  "geometry": {"coordinates":[-105.5833,44.9667],"type":"Point"}
}
=======
{"geometry":{"type":"Point","coordinates":[-105.583300,44.966700]},"type":"Feature","properties":{"hierarchy":["tgn:2253943","tgn:1000001","tgn:2002367","tgn:7012149","tgn:7007923","tgn:7029392"],"placetype":["aat:300008706"],"id":2253943,"name:xx":"Cookstove Prong Olmstead Creek"}}
>>>>>>> 03f74aca74312dbeaf24d7e61306dd6a786dc3d0
