{
  "id": 1112712,
  "type": "Feature",
  "properties": {
    "tgn:hierarchy":[
        "tgn:1112712",
        "tgn:1000001",
        "tgn:7012149",
        "tgn:7016056",
        "tgn:7007520",
        "tgn:7029392"
    ],
    "tgn:id":1112712,
    "tgn:name":"Bouvier Bay",
    "tgn:placetype":[
        "aat:300132316"
    ]
},
  "bbox": [],
  "geometry": {"coordinates":[-82.6333,42.65],"type":"Point"}
}