{
  "id": 2448984,
  "type": "Feature",
  "properties": {
    "tgn:hierarchy":[
        "tgn:2448984",
        "tgn:1000001",
        "tgn:7006451",
        "tgn:7012149",
        "tgn:2000099",
        "tgn:7029392"
    ],
    "tgn:id":2448984,
    "tgn:name":"Lime Mountain",
    "tgn:placetype":[
        "aat:300008798"
    ]
},
  "bbox": [],
  "geometry": {"coordinates":[-109.9167,35.1167],"type":"Point"}
}