<<<<<<< HEAD
{
  "id": 2157112,
  "type": "Feature",
  "properties": {
    "tgn:hierarchy":[
        "tgn:2157112",
        "tgn:1000001",
        "tgn:7012149",
        "tgn:7013941",
        "tgn:7007568",
        "tgn:7029392"
    ],
    "tgn:id":2157112,
    "tgn:name":"Beaver Brook",
    "tgn:placetype":[
        "aat:300008699"
    ]
},
  "bbox": [],
  "geometry": {"coordinates":[-74.3667,44.5667],"type":"Point"}
}
=======
{"geometry":{"type":"Point","coordinates":[-74.366700,44.566700]},"type":"Feature","properties":{"hierarchy":["tgn:2157112","tgn:1000001","tgn:7012149","tgn:7013941","tgn:7007568","tgn:7029392"],"placetype":["aat:300008699"],"id":2157112,"name:xx":"Beaver Brook"}}
>>>>>>> 03f74aca74312dbeaf24d7e61306dd6a786dc3d0
