{
  "id": 7227413,
  "type": "Feature",
  "properties": {
    "tgn:hierarchy":[
        "tgn:7227413",
        "tgn:7002725",
        "tgn:7002715",
        "tgn:1000003",
        "tgn:1000074",
        "tgn:7029392"
    ],
    "tgn:id":7227413,
    "tgn:name":"Eidom\u00e9ni",
    "tgn:placetype":[
        "aat:300008347"
    ]
},
  "bbox": [],
  "geometry": {"coordinates":[22.506111,41.119444],"type":"Point"}
}