{
  "id": 2030510,
  "type": "Feature",
  "properties": {
    "tgn:hierarchy":[
        "tgn:2030510",
        "tgn:1000001",
        "tgn:7012149",
        "tgn:7013855",
        "tgn:7007251",
        "tgn:7029392"
    ],
    "tgn:id":2030510,
    "tgn:name":"Vernon Hills",
    "tgn:placetype":[
        "aat:300008347"
    ]
},
  "bbox": [],
  "geometry": {"coordinates":[-87.9667,42.2167],"type":"Point"}
}