{
  "id": 7421365,
  "type": "Feature",
  "properties": {
    "tgn:hierarchy":[
        "tgn:7421365",
        "tgn:7005584",
        "tgn:1000001",
        "tgn:7005560",
        "tgn:7029392"
    ],
    "tgn:id":7421365,
    "tgn:name":"Providencia del Llano",
    "tgn:placetype":[
        "aat:300008347"
    ]
},
  "bbox": [],
  "geometry": {"coordinates":[-101.479167,21.356111],"type":"Point"}
}