{
  "id": 2322531,
  "type": "Feature",
  "properties": {
    "tgn:hierarchy":[
        "tgn:2322531",
        "tgn:1000001",
        "tgn:7012149",
        "tgn:2001279",
        "tgn:7007524",
        "tgn:7029392"
    ],
    "tgn:id":2322531,
    "tgn:name":"Falls Creek",
    "tgn:placetype":[
        "aat:300008706"
    ]
},
  "bbox": [],
  "geometry": {"coordinates":[-113.6667,46.1167],"type":"Point"}
}