{
  "id": 7462668,
  "type": "Feature",
  "properties": {
    "tgn:hierarchy":[
        "tgn:7462668",
        "tgn:7002444",
        "tgn:1000003",
        "tgn:5000451",
        "tgn:7008591",
        "tgn:7029392"
    ],
    "tgn:id":7462668,
    "tgn:name:en":"Inchrory",
    "tgn:placetype":[
        "aat:300008347"
    ]
},
  "bbox": [],
  "geometry": {"coordinates":[-3.35,57.15],"type":"Point"}
}