{
  "id": 7284366,
  "type": "Feature",
  "properties": {
    "tgn:hierarchy":[
        "tgn:7284366",
        "tgn:1001630",
        "tgn:1000049",
        "tgn:1000002",
        "tgn:7029392"
    ],
    "tgn:id":7284366,
    "tgn:name":"Punta de Lobos, Caleta",
    "tgn:placetype":[
        "aat:300132316"
    ]
},
  "bbox": [],
  "geometry": {"coordinates":[-71.183333,-28.283333],"type":"Point"}
}