{
  "id": 2617565,
  "type": "Feature",
  "properties": {
    "tgn:hierarchy":[
        "tgn:2617565",
        "tgn:1000001",
        "tgn:7006451",
        "tgn:7012149",
        "tgn:2000103",
        "tgn:7029392"
    ],
    "tgn:id":2617565,
    "tgn:name":"Rick Tank",
    "tgn:placetype":[
        "aat:300006191"
    ]
},
  "bbox": [],
  "geometry": {"coordinates":[-112.1833,34.7333],"type":"Point"}
}