{
  "id": 7533739,
  "type": "Feature",
  "properties": {
    "tgn:hierarchy":[
        "tgn:7533739",
        "tgn:7001242",
        "tgn:7016833",
        "tgn:7029392"
    ],
    "tgn:id":7533739,
    "tgn:name:en":"Jarr\u0101r\u012byah, W\u0101d\u012b",
    "tgn:placetype":[
        "aat:300379998"
    ]
},
  "bbox": [],
  "geometry": {"coordinates":[31.346317,29.393673],"type":"Point"}
}