<<<<<<< HEAD
{
  "id": 2762495,
  "type": "Feature",
  "properties": {
    "tgn:hierarchy":[
        "tgn:2762495",
        "tgn:1000001",
        "tgn:7006451",
        "tgn:7012149",
        "tgn:2000103",
        "tgn:7029392"
    ],
    "tgn:id":2762495,
    "tgn:name":"West Water",
    "tgn:placetype":[
        "aat:300008697"
    ]
},
  "bbox": [],
  "geometry": {"coordinates":[-111.8667,34.2833],"type":"Point"}
}
=======
{"geometry":{"type":"Point","coordinates":[-111.866700,34.283300]},"type":"Feature","properties":{"hierarchy":["tgn:2762495","tgn:1000001","tgn:7006451","tgn:7012149","tgn:2000103","tgn:7029392"],"placetype":["aat:300008697"],"id":2762495,"name:xx":"West Water"}}
>>>>>>> 03f74aca74312dbeaf24d7e61306dd6a786dc3d0
