{
  "id": 2348143,
  "type": "Feature",
  "properties": {
    "tgn:hierarchy":[
        "tgn:2348143",
        "tgn:1000001",
        "tgn:2001703",
        "tgn:7012149",
        "tgn:7007708",
        "tgn:7029392"
    ],
    "tgn:id":2348143,
    "tgn:name":"Gerry Mountain",
    "tgn:placetype":[
        "aat:300008798"
    ]
},
  "bbox": [],
  "geometry": {"coordinates":[-120.1667,43.8833],"type":"Point"}
}