{
  "id": 1022170,
  "type": "Feature",
  "properties": {
    "tgn:hierarchy":[
        "tgn:1022170",
        "tgn:1001834",
        "tgn:1000047",
        "tgn:7002455",
        "tgn:1000002",
        "tgn:7029392"
    ],
    "tgn:id":1022170,
    "tgn:name":"Mucug\u00ea",
    "tgn:placetype":[
        "aat:300008347"
    ]
},
  "bbox": [],
  "geometry": {"coordinates":[-41.3667,-12.9833],"type":"Point"}
}