{
  "id": 7210932,
  "type": "Feature",
  "properties": {
    "tgn:hierarchy":[
        "tgn:7210932",
        "tgn:1000003",
        "tgn:7003689",
        "tgn:7000084",
        "tgn:7029392"
    ],
    "tgn:id":7210932,
    "tgn:name":"Bauer-Berg",
    "tgn:placetype":[
        "aat:300008777"
    ]
},
  "bbox": [],
  "geometry": {"coordinates":[10.516667,51.483333],"type":"Point"}
}