{
  "id": 2078256,
  "type": "Feature",
  "properties": {
    "tgn:hierarchy":[
        "tgn:2078256",
        "tgn:1000001",
        "tgn:7012149",
        "tgn:1002448",
        "tgn:7007706",
        "tgn:7029392"
    ],
    "tgn:id":2078256,
    "tgn:name":"Arlington",
    "tgn:placetype":[
        "aat:300008347"
    ]
},
  "bbox": [],
  "geometry": {"coordinates":[-83.65,40.8833],"type":"Point"}
}