{
  "id": 7176863,
  "type": "Feature",
  "properties": {
    "tgn:hierarchy":[
        "tgn:7176863",
        "tgn:1000003",
        "tgn:7003677",
        "tgn:7000084",
        "tgn:7029392"
    ],
    "tgn:id":7176863,
    "tgn:name":"Hardt",
    "tgn:placetype":[
        "aat:300000206"
    ]
},
  "bbox": [],
  "geometry": {"coordinates":[7.35,50.85],"type":"Point"}
}