{
  "id": 7528865,
  "type": "Feature",
  "properties": {
    "tgn:hierarchy":[
        "tgn:7528865",
        "tgn:7001242",
        "tgn:7016833",
        "tgn:7001336",
        "tgn:7029392"
    ],
    "tgn:id":7528865,
    "tgn:name:en":"Umm Mafr\u016bd, Jabal",
    "tgn:placetype":[
        "aat:300008795"
    ]
},
  "bbox": [],
  "geometry": {"coordinates":[34.211431,29.157871],"type":"Point"}
}