{
  "id": 2430114,
  "type": "Feature",
  "properties": {
    "tgn:hierarchy":[
        "tgn:2430114",
        "tgn:1002648",
        "tgn:1000001",
        "tgn:7019158",
        "tgn:7012149",
        "tgn:7007249",
        "tgn:7029392"
    ],
    "tgn:id":2430114,
    "tgn:name":"Kahaleaimakani Gulch",
    "tgn:placetype":[
        "aat:300008761"
    ]
},
  "bbox": [],
  "geometry": {"coordinates":[-156.2333,20.65],"type":"Point"}
}