{
  "id": 1020799,
  "type": "Feature",
  "properties": {
    "tgn:hierarchy":[
        "tgn:1020799",
        "tgn:1001945",
        "tgn:1000047",
        "tgn:7002457",
        "tgn:1000002",
        "tgn:7029392"
    ],
    "tgn:id":1020799,
    "tgn:name":"Barretos",
    "tgn:placetype":[
        "aat:300387277",
        "aat:300008347",
        "aat:300008389"
    ]
},
  "bbox": [],
  "geometry": {"coordinates":[-48.5833,-20.6667],"type":"Point"}
}