{
  "id": 7399233,
  "type": "Feature",
  "properties": {
    "tgn:hierarchy":[
        "tgn:7399233",
        "tgn:1001836",
        "tgn:1000001",
        "tgn:7005560",
        "tgn:7029392"
    ],
    "tgn:id":7399233,
    "tgn:name":"La Joya, Cerro",
    "tgn:placetype":[
        "aat:300008777"
    ]
},
  "bbox": [],
  "geometry": {"coordinates":[-109.481389,23.247222],"type":"Point"}
}