{
  "id": 2535262,
  "type": "Feature",
  "properties": {
    "tgn:hierarchy":[
        "tgn:2535262",
        "tgn:1000001",
        "tgn:7012149",
        "tgn:2001679",
        "tgn:7007707",
        "tgn:7029392"
    ],
    "tgn:id":2535262,
    "tgn:name":"Nanos",
    "tgn:placetype":[
        "aat:300008347"
    ]
},
  "bbox": [],
  "geometry": {"coordinates":[-96.2667,36.7833],"type":"Point"}
}