{
  "id": 7364907,
  "type": "Feature",
  "properties": {
    "tgn:hierarchy":[
        "tgn:7364907",
        "tgn:7005586",
        "tgn:1000001",
        "tgn:7005560",
        "tgn:7029392"
    ],
    "tgn:id":7364907,
    "tgn:name":"El Sauz",
    "tgn:placetype":[
        "aat:300008347"
    ]
},
  "bbox": [],
  "geometry": {"coordinates":[-103.366667,20.183333],"type":"Point"}
}