{
  "id": 7472089,
  "type": "Feature",
  "properties": {
    "tgn:hierarchy":[
        "tgn:7472089",
        "tgn:1000004",
        "tgn:7490934",
        "tgn:1000141",
        "tgn:7029392"
    ],
    "tgn:id":7472089,
    "tgn:name":"Zhongxing Shequ",
    "tgn:placetype":[
        "aat:300008347"
    ]
},
  "bbox": [],
  "geometry": {"coordinates":[120.196389,22.913333],"type":"Point"}
}