{
  "id": 7052191,
  "type": "Feature",
  "properties": {
    "tgn:hierarchy":[
        "tgn:7052191",
        "tgn:7004597",
        "tgn:1000003",
        "tgn:7008516",
        "tgn:1000080",
        "tgn:7029392"
    ],
    "tgn:id":7052191,
    "tgn:name":"I Tre Olmi",
    "tgn:placetype":[
        "aat:300008347"
    ]
},
  "bbox": [],
  "geometry": {"coordinates":[10.883333,44.666667],"type":"Point"}
}