{
  "id": 7030577,
  "type": "Feature",
  "properties": {
    "tgn:hierarchy":[
        "tgn:7030577",
        "tgn:7003028",
        "tgn:1000003",
        "tgn:1000062",
        "tgn:7029392"
    ],
    "tgn:id":7030577,
    "tgn:name":"Brunn",
    "tgn:placetype":[
        "aat:300008347"
    ]
},
  "bbox": [],
  "geometry": {"coordinates":[15.316,46.75],"type":"Point"}
}