{
  "id": 7302707,
  "type": "Feature",
  "properties": {
    "tgn:hierarchy":[
        "tgn:7302707",
        "tgn:7002808",
        "tgn:7030216",
        "tgn:1000003",
        "tgn:1000095",
        "tgn:7029392"
    ],
    "tgn:id":7302707,
    "tgn:name":"Olzinellas",
    "tgn:placetype":[
        "aat:300008347"
    ]
},
  "bbox": [],
  "geometry": {"coordinates":[2.510385,41.663169],"type":"Point"}
}