{
  "id": 7300701,
  "type": "Feature",
  "properties": {
    "tgn:hierarchy":[
        "tgn:7300701",
        "tgn:7002825",
        "tgn:7016622",
        "tgn:1000003",
        "tgn:1000095",
        "tgn:7029392"
    ],
    "tgn:id":7300701,
    "tgn:name":"Naos, Puerto de",
    "tgn:placetype":[
        "aat:300132317"
    ]
},
  "bbox": [],
  "geometry": {"coordinates":[-13.533333,28.95],"type":"Point"}
}