{
  "id": 2218539,
  "type": "Feature",
  "properties": {
    "tgn:hierarchy":[
        "tgn:2218539",
        "tgn:1000001",
        "tgn:7012149",
        "tgn:2000787",
        "tgn:7007255",
        "tgn:7029392"
    ],
    "tgn:id":2218539,
    "tgn:name":"Cane Camp Branch",
    "tgn:placetype":[
        "aat:300008699"
    ]
},
  "bbox": [],
  "geometry": {"coordinates":[-86.2333,37.3167],"type":"Point"}
}