{
  "id": 2576029,
  "type": "Feature",
  "properties": {
    "tgn:hierarchy":[
        "tgn:2576029",
        "tgn:1000001",
        "tgn:7012149",
        "tgn:2001249",
        "tgn:7007523",
        "tgn:7029392"
    ],
    "tgn:id":2576029,
    "tgn:name":"Perkins Hollow",
    "tgn:placetype":[
        "aat:300008761"
    ]
},
  "bbox": [],
  "geometry": {"coordinates":[-93.4667,36.5833],"type":"Point"}
}