{
  "id": 2115898,
  "type": "Feature",
  "properties": {
    "tgn:hierarchy":[
        "tgn:2115898",
        "tgn:1000001",
        "tgn:7012149",
        "tgn:7018871",
        "tgn:7007920",
        "tgn:7029392"
    ],
    "tgn:id":2115898,
    "tgn:name":"Greenwater",
    "tgn:placetype":[
        "aat:300008347"
    ]
},
  "bbox": [],
  "geometry": {"coordinates":[-121.6333,47.15],"type":"Point"}
}