{
  "id": 1093990,
  "type": "Feature",
  "properties": {
    "tgn:hierarchy":[
        "tgn:1093990",
        "tgn:7001242",
        "tgn:7030594",
        "tgn:1000198",
        "tgn:7029392"
    ],
    "tgn:id":1093990,
    "tgn:name":"Osire S\u00fcd",
    "tgn:placetype":[
        "aat:300008347",
        "aat:300000206"
    ]
},
  "bbox": [],
  "geometry": {"coordinates":[17.3667,-21.0167],"type":"Point"}
}