{
  "id": 2612859,
  "type": "Feature",
  "properties": {
    "tgn:hierarchy":[
        "tgn:2612859",
        "tgn:1000001",
        "tgn:7012149",
        "tgn:2001541",
        "tgn:7007709",
        "tgn:7029392"
    ],
    "tgn:id":2612859,
    "tgn:name":"Redman Creek",
    "tgn:placetype":[
        "aat:300008706"
    ]
},
  "bbox": [],
  "geometry": {"coordinates":[-80.1667,36.45],"type":"Point"}
}