{
  "id": 7580556,
  "type": "Feature",
  "properties": {
    "tgn:hierarchy":[
        "tgn:7580556",
        "tgn:1000004",
        "tgn:7000198",
        "tgn:7001797",
        "tgn:7029392"
    ],
    "tgn:id":7580556,
    "tgn:name:en":"Vairamangalam",
    "tgn:placetype":[
        "aat:300008347"
    ]
},
  "bbox": [],
  "geometry": {"coordinates":[77.616667,11.45],"type":"Point"}
}