<<<<<<< HEAD
{
  "id": 2255636,
  "type": "Feature",
  "properties": {
    "tgn:hierarchy":[
        "tgn:2255636",
        "tgn:1000001",
        "tgn:7012149",
        "tgn:2000238",
        "tgn:7007158",
        "tgn:7029392"
    ],
    "tgn:id":2255636,
    "tgn:name":"Copenhaver Gulch",
    "tgn:placetype":[
        "aat:300008761"
    ]
},
  "bbox": [],
  "geometry": {"coordinates":[-105.7,39.2333],"type":"Point"}
}
=======
{"geometry":{"type":"Point","coordinates":[-105.700000,39.233300]},"type":"Feature","properties":{"hierarchy":["tgn:2255636","tgn:1000001","tgn:7012149","tgn:2000238","tgn:7007158","tgn:7029392"],"placetype":["aat:300008761"],"id":2255636,"name:xx":"Copenhaver Gulch"}}
>>>>>>> 03f74aca74312dbeaf24d7e61306dd6a786dc3d0
