{
  "id": 7579217,
  "type": "Feature",
  "properties": {
    "tgn:hierarchy":[
        "tgn:7579217",
        "tgn:1000004",
        "tgn:7000198",
        "tgn:7016883",
        "tgn:7029392"
    ],
    "tgn:id":7579217,
    "tgn:name:en":"Sobr\u0101on",
    "tgn:placetype":[
        "aat:300008347"
    ]
},
  "bbox": [],
  "geometry": {"coordinates":[74.852064,31.17935],"type":"Point"}
}