<<<<<<< HEAD
{
  "id": 2152775,
  "type": "Feature",
  "properties": {
    "tgn:hierarchy":[
        "tgn:2152775",
        "tgn:2000858",
        "tgn:1000001",
        "tgn:7012149",
        "tgn:7007256",
        "tgn:7029392"
    ],
    "tgn:id":2152775,
    "tgn:name":"Bayou de L'Isle",
    "tgn:placetype":[
        "aat:300008699"
    ]
},
  "bbox": [],
  "geometry": {"coordinates":[-91.85,31.15],"type":"Point"}
}
=======
{"geometry":{"type":"Point","coordinates":[-91.850000,31.150000]},"type":"Feature","properties":{"hierarchy":["tgn:2152775","tgn:2000858","tgn:1000001","tgn:7012149","tgn:7007256","tgn:7029392"],"placetype":["aat:300008699"],"id":2152775,"name:xx":"Bayou de L'Isle"}}
>>>>>>> 03f74aca74312dbeaf24d7e61306dd6a786dc3d0
