{
  "id": 7538733,
  "type": "Feature",
  "properties": {
    "tgn:hierarchy":[
        "tgn:7538733",
        "tgn:7001242",
        "tgn:1001075",
        "tgn:7016833",
        "tgn:7029392"
    ],
    "tgn:id":7538733,
    "tgn:name:en":"Mun\u015fif, Jabal",
    "tgn:placetype":[
        "aat:300008777"
    ]
},
  "bbox": [],
  "geometry": {"coordinates":[30.566667,30.383333],"type":"Point"}
}