{
  "id": 2477642,
  "type": "Feature",
  "properties": {
    "tgn:hierarchy":[
        "tgn:2477642",
        "tgn:2000090",
        "tgn:1000001",
        "tgn:7006451",
        "tgn:7012149",
        "tgn:7029392"
    ],
    "tgn:id":2477642,
    "tgn:name":"MVC Tank Number One",
    "tgn:placetype":[
        "aat:300006191"
    ]
},
  "bbox": [],
  "geometry": {"coordinates":[-109.2833,34.0167],"type":"Point"}
}