{
  "id": 2134926,
  "type": "Feature",
  "properties": {
    "tgn:hierarchy":[
        "tgn:2134926",
        "tgn:1000001",
        "tgn:7012149",
        "tgn:2001297",
        "tgn:7007524",
        "tgn:7029392"
    ],
    "tgn:id":2134926,
    "tgn:name":"Antelope Reservoir",
    "tgn:placetype":[
        "aat:300006191"
    ]
},
  "bbox": [],
  "geometry": {"coordinates":[-105.9333,45.2167],"type":"Point"}
}