{
  "id": 2104944,
  "type": "Feature",
  "properties": {
    "tgn:hierarchy":[
        "tgn:2104944",
        "tgn:1000001",
        "tgn:7013727",
        "tgn:7012149",
        "tgn:1002456",
        "tgn:7007826",
        "tgn:7029392"
    ],
    "tgn:id":2104944,
    "tgn:name":"Bellaire West",
    "tgn:placetype":[
        "aat:300000745"
    ]
},
  "bbox": [],
  "geometry": {"coordinates":[-95.5667,29.6833],"type":"Point"}
}