<<<<<<< HEAD
{
  "id": 2400906,
  "type": "Feature",
  "properties": {
    "tgn:hierarchy":[
        "tgn:2400906",
        "tgn:1000001",
        "tgn:7012149",
        "tgn:1002945",
        "tgn:7007710",
        "tgn:7029392"
    ],
    "tgn:id":2400906,
    "tgn:name":"Horse Run",
    "tgn:placetype":[
        "aat:300008699"
    ]
},
  "bbox": [],
  "geometry": {"coordinates":[-77.4667,41.6667],"type":"Point"}
}
=======
{"geometry":{"type":"Point","coordinates":[-77.466700,41.666700]},"type":"Feature","properties":{"hierarchy":["tgn:2400906","tgn:1000001","tgn:7012149","tgn:1002945","tgn:7007710","tgn:7029392"],"placetype":["aat:300008699"],"id":2400906,"name:xx":"Horse Run"}}
>>>>>>> 03f74aca74312dbeaf24d7e61306dd6a786dc3d0
