{
  "id": 2314724,
  "type": "Feature",
  "properties": {
    "tgn:hierarchy":[
        "tgn:2314724",
        "tgn:1000001",
        "tgn:7012149",
        "tgn:2000476",
        "tgn:7007250",
        "tgn:7029392"
    ],
    "tgn:id":2314724,
    "tgn:name":"Elk Summit",
    "tgn:placetype":[
        "aat:300008798"
    ]
},
  "bbox": [],
  "geometry": {"coordinates":[-115.5333,45.8667],"type":"Point"}
}