{
  "id": 7550839,
  "type": "Feature",
  "properties": {
    "tgn:hierarchy":[
        "tgn:7550839",
        "tgn:1000004",
        "tgn:7000198",
        "tgn:7016883",
        "tgn:7029392"
    ],
    "tgn:id":7550839,
    "tgn:name:en":"Dangar Khera",
    "tgn:placetype":[
        "aat:300008347"
    ]
},
  "bbox": [],
  "geometry": {"coordinates":[74.166334,30.2102],"type":"Point"}
}