{
  "id": 7548919,
  "type": "Feature",
  "properties": {
    "tgn:hierarchy":[
        "tgn:7548919",
        "tgn:1000004",
        "tgn:7000198",
        "tgn:1001882",
        "tgn:7029392"
    ],
    "tgn:id":7548919,
    "tgn:name:en":"Devargud",
    "tgn:placetype":[
        "aat:300007783"
    ]
},
  "bbox": [],
  "geometry": {"coordinates":[75.566667,14.683333],"type":"Point"}
}