{
  "id": 2517283,
  "type": "Feature",
  "properties": {
    "tgn:hierarchy":[
        "tgn:2517283",
        "tgn:1000001",
        "tgn:7012149",
        "tgn:2000635",
        "tgn:7007253",
        "tgn:7029392"
    ],
    "tgn:id":2517283,
    "tgn:name":"Minnie Brook",
    "tgn:placetype":[
        "aat:300008699"
    ]
},
  "bbox": [],
  "geometry": {"coordinates":[-96.15,42.6833],"type":"Point"}
}