<<<<<<< HEAD
{
  "id": 2401238,
  "type": "Feature",
  "properties": {
    "tgn:hierarchy":[
        "tgn:2401238",
        "tgn:2000455",
        "tgn:1000001",
        "tgn:7012149",
        "tgn:7007250",
        "tgn:7029392"
    ],
    "tgn:id":2401238,
    "tgn:name":"Horsehoe Basin",
    "tgn:placetype":[
        "aat:300386845"
    ]
},
  "bbox": [],
  "geometry": {"coordinates":[-111.6,42.2333],"type":"Point"}
}
=======
{"geometry":{"type":"Point","coordinates":[-111.600000,42.233300]},"type":"Feature","properties":{"hierarchy":["tgn:2401238","tgn:2000455","tgn:1000001","tgn:7012149","tgn:7007250","tgn:7029392"],"placetype":["aat:300386845"],"id":2401238,"name:xx":"Horsehoe Basin"}}
>>>>>>> 03f74aca74312dbeaf24d7e61306dd6a786dc3d0
