<<<<<<< HEAD
{
  "id": 7054993,
  "type": "Feature",
  "properties": {
    "tgn:hierarchy":[
        "tgn:7054993",
        "tgn:1000003",
        "tgn:7003143",
        "tgn:7003236",
        "tgn:1000080",
        "tgn:7029392"
    ],
    "tgn:id":7054993,
    "tgn:name":"Lisorno",
    "tgn:placetype":[
        "aat:300008347"
    ]
},
  "bbox": [],
  "geometry": {"coordinates":[9.65,44.316667],"type":"Point"}
}
=======
{"geometry":{"type":"Point","coordinates":[9.650000,44.316667]},"type":"Feature","properties":{"hierarchy":["tgn:7054993","tgn:1000003","tgn:7003143","tgn:7003236","tgn:1000080","tgn:7029392"],"placetype":["aat:300008347"],"id":7054993,"name:xx":"Lisorno"}}
>>>>>>> 03f74aca74312dbeaf24d7e61306dd6a786dc3d0
