{
  "id": 2495651,
  "type": "Feature",
  "properties": {
    "tgn:hierarchy":[
        "tgn:2495651",
        "tgn:1002808",
        "tgn:1000001",
        "tgn:7012149",
        "tgn:7007711",
        "tgn:7029392"
    ],
    "tgn:id":2495651,
    "tgn:name":"Mashapaug Brook",
    "tgn:placetype":[
        "aat:300008699"
    ]
},
  "bbox": [],
  "geometry": {"coordinates":[-71.4333,41.7833],"type":"Point"}
}