<<<<<<< HEAD
{
  "id": 2257089,
  "type": "Feature",
  "properties": {
    "tgn:hierarchy":[
        "tgn:2257089",
        "tgn:1000001",
        "tgn:7012149",
        "tgn:7007157",
        "tgn:1002608",
        "tgn:7029392"
    ],
    "tgn:id":2257089,
    "tgn:name":"Cornell",
    "tgn:placetype":[
        "aat:300008347"
    ]
},
  "bbox": [],
  "geometry": {"coordinates":[-118.7667,34.1],"type":"Point"}
}
=======
{"geometry":{"type":"Point","coordinates":[-118.766700,34.100000]},"type":"Feature","properties":{"hierarchy":["tgn:2257089","tgn:1000001","tgn:7012149","tgn:7007157","tgn:1002608","tgn:7029392"],"placetype":["aat:300008347"],"id":2257089,"name:xx":"Cornell"}}
>>>>>>> 03f74aca74312dbeaf24d7e61306dd6a786dc3d0
