{
  "id": 2464847,
  "type": "Feature",
  "properties": {
    "tgn:hierarchy":[
        "tgn:2464847",
        "tgn:1000001",
        "tgn:7012149",
        "tgn:7029392"
    ],
    "tgn:id":2464847,
    "tgn:name":"Logan River",
    "tgn:placetype":[
        "aat:300008707"
    ]
},
  "bbox": [],
  "geometry": {"coordinates":[-111.5833,42.0333],"type":"Point"}
}