<<<<<<< HEAD
{
  "id": 2252052,
  "type": "Feature",
  "properties": {
    "tgn:hierarchy":[
        "tgn:2252052",
        "tgn:1000001",
        "tgn:7006451",
        "tgn:7012149",
        "tgn:2000103",
        "tgn:7029392"
    ],
    "tgn:id":2252052,
    "tgn:name":"Concrete Tank",
    "tgn:placetype":[
        "aat:300006191"
    ]
},
  "bbox": [],
  "geometry": {"coordinates":[-111.8833,34.95],"type":"Point"}
}
=======
{"geometry":{"type":"Point","coordinates":[-111.883300,34.950000]},"type":"Feature","properties":{"hierarchy":["tgn:2252052","tgn:1000001","tgn:7006451","tgn:7012149","tgn:2000103","tgn:7029392"],"placetype":["aat:300006191"],"id":2252052,"name:xx":"Concrete Tank"}}
>>>>>>> 03f74aca74312dbeaf24d7e61306dd6a786dc3d0
