{
  "id": 2263306,
  "type": "Feature",
  "properties": {
    "tgn:hierarchy":[
        "tgn:2263306",
        "tgn:1000001",
        "tgn:2000582",
        "tgn:7012149",
        "tgn:7007253",
        "tgn:7029392"
    ],
    "tgn:id":2263306,
    "tgn:name":"Cox Creek",
    "tgn:placetype":[
        "aat:300008706"
    ]
},
  "bbox": [],
  "geometry": {"coordinates":[-91.4667,42.6667],"type":"Point"}
}