{
  "id": 2101546,
  "type": "Feature",
  "properties": {
    "tgn:hierarchy":[
        "tgn:2101546",
        "tgn:1000001",
        "tgn:7012149",
        "tgn:2001866",
        "tgn:7007825",
        "tgn:7029392"
    ],
    "tgn:id":2101546,
    "tgn:name":"Skinner Crossroad",
    "tgn:placetype":[
        "aat:300008347",
        "aat:300387210"
    ]
},
  "bbox": [],
  "geometry": {"coordinates":[-83.0667,36.1667],"type":"Point"}
}