{
  "id": 7002633,
  "type": "Feature",
  "properties": {
    "tgn:hierarchy":[
        "tgn:7002633",
        "tgn:1001102",
        "tgn:7018452",
        "tgn:1000004",
        "tgn:1000144",
        "tgn:7029392"
    ],
    "tgn:id":7002633,
    "tgn:name":"G\u00fcn\u00fck",
    "tgn:placetype":[
        "aat:300008347",
        "aat:300000810"
    ]
},
  "bbox": [],
  "geometry": {"coordinates":[29.3333,36.3667],"type":"Point"}
}