{
  "id": 7576559,
  "type": "Feature",
  "properties": {
    "tgn:hierarchy":[
        "tgn:7576559",
        "tgn:1000004",
        "tgn:7000198",
        "tgn:7016883",
        "tgn:7029392"
    ],
    "tgn:id":7576559,
    "tgn:name:en":"Kot Dharm\u016bn",
    "tgn:placetype":[
        "aat:300008347"
    ]
},
  "bbox": [],
  "geometry": {"coordinates":[75.372591,29.892316],"type":"Point"}
}