<<<<<<< HEAD
{
  "id": 7486883,
  "type": "Feature",
  "properties": {
    "tgn:hierarchy":[
        "tgn:7486883",
        "tgn:1000004",
        "tgn:7490934",
        "tgn:1000141",
        "tgn:7029392"
    ],
    "tgn:id":7486883,
    "tgn:name":"Dingcaodi",
    "tgn:placetype":[
        "aat:300008347"
    ]
},
  "bbox": [],
  "geometry": {"coordinates":[120.200556,23.2225],"type":"Point"}
}
=======
{"geometry":{"type":"Point","coordinates":[120.200556,23.222500]},"type":"Feature","properties":{"hierarchy":["tgn:7486883","tgn:1000004","tgn:7490934","tgn:1000141","tgn:7029392"],"placetype":["aat:300008347"],"id":7486883,"name:xx":"Dingcaodi"}}
>>>>>>> 03f74aca74312dbeaf24d7e61306dd6a786dc3d0
