{
  "id": 7486883,
  "type": "Feature",
  "properties": {
    "tgn:hierarchy":[
        "tgn:7486883",
        "tgn:1000004",
        "tgn:7490934",
        "tgn:1000141",
        "tgn:7029392"
    ],
    "tgn:id":7486883,
    "tgn:name":"Dingcaodi",
    "tgn:placetype":[
        "aat:300008347"
    ]
},
  "bbox": [],
  "geometry": {"coordinates":[120.200556,23.2225],"type":"Point"}
}