{
  "id": 1074405,
  "type": "Feature",
  "properties": {
    "tgn:hierarchy":[
        "tgn:1074405",
        "tgn:1000004",
        "tgn:7000198",
        "tgn:7016722",
        "tgn:7029392"
    ],
    "tgn:id":1074405,
    "tgn:name:en":"Amausi",
    "tgn:placetype":[
        "aat:300007783"
    ]
},
  "bbox": [],
  "geometry": {"coordinates":[80.84271,26.775165],"type":"Point"}
}