{
  "id": 2776813,
  "type": "Feature",
  "properties": {
    "tgn:hierarchy":[
        "tgn:2776813",
        "tgn:1000001",
        "tgn:7012149",
        "tgn:2001767",
        "tgn:7007712",
        "tgn:7029392"
    ],
    "tgn:id":2776813,
    "tgn:name":"Windsor City Mobile Home Park",
    "tgn:placetype":[
        "aat:300008347"
    ]
},
  "bbox": [],
  "geometry": {"coordinates":[-80.3833,33.9667],"type":"Point"}
}