<<<<<<< HEAD
{
  "id": 7248851,
  "type": "Feature",
  "properties": {
    "tgn:hierarchy":[
        "tgn:7248851",
        "tgn:7003460",
        "tgn:1000003",
        "tgn:1000063",
        "tgn:4012014",
        "tgn:7029392"
    ],
    "tgn:id":7248851,
    "tgn:name":"Bois l'\u00c9v\u00eaque",
    "tgn:placetype":[
        "aat:300008347"
    ]
},
  "bbox": [],
  "geometry": {"coordinates":[5.75,50.616667],"type":"Point"}
}
=======
{"geometry":{"type":"Point","coordinates":[5.750000,50.616667]},"type":"Feature","properties":{"hierarchy":["tgn:7248851","tgn:7003460","tgn:1000003","tgn:1000063","tgn:4012014","tgn:7029392"],"placetype":["aat:300008347"],"id":7248851,"name:xx":"Bois l'\u00c9v\u00eaque"}}
>>>>>>> 03f74aca74312dbeaf24d7e61306dd6a786dc3d0
