{
  "id": 7347767,
  "type": "Feature",
  "properties": {
    "tgn:hierarchy":[
        "tgn:7347767",
        "tgn:7002847",
        "tgn:1001647",
        "tgn:1000003",
        "tgn:1000095",
        "tgn:7029392"
    ],
    "tgn:id":7347767,
    "tgn:name":"Aceca",
    "tgn:placetype":[
        "aat:300008347"
    ]
},
  "bbox": [],
  "geometry": {"coordinates":[-3.85,39.95],"type":"Point"}
}