<<<<<<< HEAD
{
  "id": 2331662,
  "type": "Feature",
  "properties": {
    "tgn:hierarchy":[
        "tgn:2331662",
        "tgn:7002659",
        "tgn:1000001",
        "tgn:7012149",
        "tgn:2000062",
        "tgn:7029392"
    ],
    "tgn:id":2331662,
    "tgn:name":"Fleetwood Mine",
    "tgn:placetype":[
        "aat:300000390"
    ]
},
  "bbox": [],
  "geometry": {"coordinates":[-87.3833,33.2333],"type":"Point"}
}
=======
{"geometry":{"type":"Point","coordinates":[-87.383300,33.233300]},"type":"Feature","properties":{"hierarchy":["tgn:2331662","tgn:7002659","tgn:1000001","tgn:7012149","tgn:2000062","tgn:7029392"],"placetype":["aat:300000390"],"id":2331662,"name:xx":"Fleetwood Mine"}}
>>>>>>> 03f74aca74312dbeaf24d7e61306dd6a786dc3d0
