{
  "id": 2355316,
  "type": "Feature",
  "properties": {
    "tgn:hierarchy":[
        "tgn:2355316",
        "tgn:7002659",
        "tgn:1000001",
        "tgn:7012149",
        "tgn:2000043",
        "tgn:7029392"
    ],
    "tgn:id":2355316,
    "tgn:name":"Goodwyn",
    "tgn:placetype":[
        "aat:300008347"
    ]
},
  "bbox": [],
  "geometry": {"coordinates":[-85.9333,32.4333],"type":"Point"}
}