{
  "id": 7278534,
  "type": "Feature",
  "properties": {
    "tgn:hierarchy":[
        "tgn:7278534",
        "tgn:7002464",
        "tgn:1000049",
        "tgn:1000002",
        "tgn:7029392"
    ],
    "tgn:id":7278534,
    "tgn:name":"Vista Faro",
    "tgn:placetype":[
        "aat:300387033"
    ]
},
  "bbox": [],
  "geometry": {"coordinates":[-70.066667,-20.35],"type":"Point"}
}