{
  "id": 7311041,
  "type": "Feature",
  "properties": {
    "tgn:hierarchy":[
        "tgn:7311041",
        "tgn:7002464",
        "tgn:1000049",
        "tgn:1000002",
        "tgn:7029392"
    ],
    "tgn:id":7311041,
    "tgn:name":"Oficina Pirineo",
    "tgn:placetype":[
        "aat:300008057"
    ]
},
  "bbox": [],
  "geometry": {"coordinates":[-69.983333,-20.45],"type":"Point"}
}