<<<<<<< HEAD
{
  "id": 2335995,
  "type": "Feature",
  "properties": {
    "tgn:hierarchy":[
        "tgn:2335995",
        "tgn:1000001",
        "tgn:7012149",
        "tgn:2001883",
        "tgn:7007825",
        "tgn:7029392"
    ],
    "tgn:id":2335995,
    "tgn:name":"Foster Branch",
    "tgn:placetype":[
        "aat:300008699"
    ]
},
  "bbox": [],
  "geometry": {"coordinates":[-84.0333,36.1],"type":"Point"}
}
=======
{"geometry":{"type":"Point","coordinates":[-84.033300,36.100000]},"type":"Feature","properties":{"hierarchy":["tgn:2335995","tgn:1000001","tgn:7012149","tgn:2001883","tgn:7007825","tgn:7029392"],"placetype":["aat:300008699"],"id":2335995,"name:xx":"Foster Branch"}}
>>>>>>> 03f74aca74312dbeaf24d7e61306dd6a786dc3d0
