{
  "id": 1051314,
  "type": "Feature",
  "properties": {
    "tgn:hierarchy":[
        "tgn:1051314",
        "tgn:6001332",
        "tgn:1000003",
        "tgn:7006660",
        "tgn:7029392"
    ],
    "tgn:id":1051314,
    "tgn:name":"Chernobay",
    "tgn:placetype":[
        "aat:300008347"
    ]
},
  "bbox": [],
  "geometry": {"coordinates":[32.3667,49.6667],"type":"Point"}
}