{
  "id": 7257613,
  "type": "Feature",
  "properties": {
    "tgn:hierarchy":[
        "tgn:7257613",
        "tgn:7003616",
        "tgn:1000003",
        "tgn:7016845",
        "tgn:7029392"
    ],
    "tgn:id":7257613,
    "tgn:name:nl":"Bakkeveense Duinen",
    "tgn:placetype":[
        "aat:300008178"
    ]
},
  "bbox": [],
  "geometry": {"coordinates":[6.266667,53.083333],"type":"Point"}
}