{
  "id": 2644633,
  "type": "Feature",
  "properties": {
    "tgn:hierarchy":[
        "tgn:2644633",
        "tgn:1000001",
        "tgn:7012149",
        "tgn:1002403",
        "tgn:7007709",
        "tgn:7029392"
    ],
    "tgn:id":2644633,
    "tgn:name":"Sarem",
    "tgn:placetype":[
        "aat:300008347"
    ]
},
  "bbox": [],
  "geometry": {"coordinates":[-76.7833,36.4833],"type":"Point"}
}