{
  "id": 2711662,
  "type": "Feature",
  "properties": {
    "tgn:hierarchy":[
        "tgn:2711662",
        "tgn:1000001",
        "tgn:7013368",
        "tgn:7012149",
        "tgn:7007709",
        "tgn:7029392"
    ],
    "tgn:id":2711662,
    "tgn:name":"Tar Landing Gut",
    "tgn:placetype":[
        "aat:300008699"
    ]
},
  "bbox": [],
  "geometry": {"coordinates":[-76.6333,35.3167],"type":"Point"}
}