{
  "id": 7589831,
  "type": "Feature",
  "properties": {
    "tgn:hierarchy":[
        "tgn:7589831",
        "tgn:1000004",
        "tgn:7000198",
        "tgn:7000799",
        "tgn:7029392"
    ],
    "tgn:id":7589831,
    "tgn:name:en":"Ch\u016bnk\u0101n Baihk",
    "tgn:placetype":[
        "aat:300008347"
    ]
},
  "bbox": [],
  "geometry": {"coordinates":[73.984768,34.589467],"type":"Point"}
}