{
  "id": 2590961,
  "type": "Feature",
  "properties": {
    "tgn:hierarchy":[
        "tgn:2590961",
        "tgn:7002659",
        "tgn:1000001",
        "tgn:7012149",
        "tgn:2000030",
        "tgn:7029392"
    ],
    "tgn:id":2590961,
    "tgn:name":"Poley Branch",
    "tgn:placetype":[
        "aat:300008699"
    ]
},
  "bbox": [],
  "geometry": {"coordinates":[-85.6333,31.15],"type":"Point"}
}