{
  "id": 2188557,
  "type": "Feature",
  "properties": {
    "tgn:hierarchy":[
        "tgn:2188557",
        "tgn:1000001",
        "tgn:7012149",
        "tgn:7029392"
    ],
    "tgn:id":2188557,
    "tgn:name":"Bottle Point",
    "tgn:placetype":[
        "aat:300008798"
    ]
},
  "bbox": [],
  "geometry": {"coordinates":[-115.9333,47.8667],"type":"Point"}
}