{
  "id": 2166013,
  "type": "Feature",
  "properties": {
    "tgn:hierarchy":[
        "tgn:2166013",
        "tgn:1000001",
        "tgn:2002103",
        "tgn:7012149",
        "tgn:7007827",
        "tgn:7029392"
    ],
    "tgn:id":2166013,
    "tgn:name":"Big Ballard Spring",
    "tgn:placetype":[
        "aat:300008697"
    ]
},
  "bbox": [],
  "geometry": {"coordinates":[-111.8167,41.6833],"type":"Point"}
}