{
  "id": 2303420,
  "type": "Feature",
  "properties": {
    "tgn:hierarchy":[
        "tgn:2303420",
        "tgn:1000001",
        "tgn:1002271",
        "tgn:7012149",
        "tgn:7007920",
        "tgn:7029392"
    ],
    "tgn:id":2303420,
    "tgn:name":"Eagle Creek",
    "tgn:placetype":[
        "aat:300008706"
    ]
},
  "bbox": [],
  "geometry": {"coordinates":[-123.8833,48.05],"type":"Point"}
}