{
  "id": 2389175,
  "type": "Feature",
  "properties": {
    "tgn:hierarchy":[
        "tgn:2389175",
        "tgn:1000001",
        "tgn:7012149",
        "tgn:2000226",
        "tgn:7007158",
        "tgn:7029392"
    ],
    "tgn:id":2389175,
    "tgn:name":"Hidden Valley Creek",
    "tgn:placetype":[
        "aat:300008706"
    ]
},
  "bbox": [],
  "geometry": {"coordinates":[-105.6667,40.3833],"type":"Point"}
}