{
  "id": 7570142,
  "type": "Feature",
  "properties": {
    "tgn:hierarchy":[
        "tgn:7570142",
        "tgn:1000004",
        "tgn:7000198",
        "tgn:7031786",
        "tgn:7029392"
    ],
    "tgn:id":7570142,
    "tgn:name:en":"Naikh\u0101na Chhota",
    "tgn:placetype":[
        "aat:300008347"
    ]
},
  "bbox": [],
  "geometry": {"coordinates":[78.619136,29.902193],"type":"Point"}
}