{
  "id": 7273317,
  "type": "Feature",
  "properties": {
    "tgn:concordances":{
        "gn:id":"2744671"
    },
    "tgn:hierarchy":[
        "tgn:7273317",
        "tgn:1000003",
        "tgn:7003613",
        "tgn:7016845",
        "tgn:7029392"
    ],
    "tgn:id":7273317,
    "tgn:name:nl":"Westerwijtwerd",
    "tgn:placetype":[
        "aat:300008347"
    ]
},
  "bbox": [],
  "geometry": {"coordinates":[6.65,53.333333],"type":"Point"}
}