{
  "id": 2644021,
  "type": "Feature",
  "properties": {
    "tgn:hierarchy":[
        "tgn:2644021",
        "tgn:1000001",
        "tgn:2001945",
        "tgn:7012149",
        "tgn:7007826",
        "tgn:7029392"
    ],
    "tgn:id":2644021,
    "tgn:name":"Santa Elena Canyon",
    "tgn:placetype":[
        "aat:300008761"
    ]
},
  "bbox": [],
  "geometry": {"coordinates":[-103.6833,29.1667],"type":"Point"}
}