{
  "id": 2542551,
  "type": "Feature",
  "properties": {
    "tgn:hierarchy":[
        "tgn:2542551",
        "tgn:1008293",
        "tgn:1000001",
        "tgn:1002705",
        "tgn:7012149",
        "tgn:7007517",
        "tgn:7029392"
    ],
    "tgn:id":2542551,
    "tgn:name":"Nobadeer Valley",
    "tgn:placetype":[
        "aat:300008761"
    ]
},
  "bbox": [],
  "geometry": {"coordinates":[-70.0667,41.2333],"type":"Point"}
}