{
  "id": 7364031,
  "type": "Feature",
  "properties": {
    "tgn:hierarchy":[
        "tgn:7364031",
        "tgn:7005581",
        "tgn:1000001",
        "tgn:7005560",
        "tgn:7029392"
    ],
    "tgn:id":7364031,
    "tgn:name":"El Barre\u00f1o",
    "tgn:placetype":[
        "aat:300008347"
    ]
},
  "bbox": [],
  "geometry": {"coordinates":[-106.083333,27.95],"type":"Point"}
}