{
  "id": 2687231,
  "type": "Feature",
  "properties": {
    "tgn:hierarchy":[
        "tgn:2687231",
        "tgn:1000001",
        "tgn:7012149",
        "tgn:2000824",
        "tgn:7007255",
        "tgn:7029392"
    ],
    "tgn:id":2687231,
    "tgn:name":"Spring Knob",
    "tgn:placetype":[
        "aat:300387099",
        "aat:300008798"
    ]
},
  "bbox": [],
  "geometry": {"coordinates":[-82.5167,37.6833],"type":"Point"}
}