{
  "id": 1016268,
  "type": "Feature",
  "properties": {
    "tgn:hierarchy":[
        "tgn:1016268",
        "tgn:1001491",
        "tgn:1000001",
        "tgn:7005364",
        "tgn:7029392"
    ],
    "tgn:id":1016268,
    "tgn:name":"Quepos",
    "tgn:placetype":[
        "aat:300008347"
    ]
},
  "bbox": [],
  "geometry": {"coordinates":[-84.15,9.45],"type":"Point"}
}