{
  "id": 2263070,
  "type": "Feature",
  "properties": {
    "tgn:hierarchy":[
        "tgn:2263070",
        "tgn:1000001",
        "tgn:7012149",
        "tgn:1002785",
        "tgn:7007920",
        "tgn:7029392"
    ],
    "tgn:id":2263070,
    "tgn:name":"Cowlitz Cleaver",
    "tgn:placetype":[
        "aat:300266640"
    ]
},
  "bbox": [],
  "geometry": {"coordinates":[-121.7333,46.8333],"type":"Point"}
}