{
  "id": 7467473,
  "type": "Feature",
  "properties": {
    "tgn:hierarchy":[
        "tgn:7467473",
        "tgn:1000004",
        "tgn:7490934",
        "tgn:1000141",
        "tgn:7029392"
    ],
    "tgn:id":7467473,
    "tgn:name":"Anjiao",
    "tgn:placetype":[
        "aat:300008347"
    ]
},
  "bbox": [],
  "geometry": {"coordinates":[120.25252,23.339865],"type":"Point"}
}