<<<<<<< HEAD
{
  "id": 7487647,
  "type": "Feature",
  "properties": {
    "tgn:hierarchy":[
        "tgn:7487647",
        "tgn:1000004",
        "tgn:7001013",
        "tgn:1000141",
        "tgn:7029392"
    ],
    "tgn:id":7487647,
    "tgn:name":"Kengwu",
    "tgn:placetype":[
        "aat:300008347"
    ]
},
  "bbox": [],
  "geometry": {"coordinates":[121.105512,25.012173],"type":"Point"}
}
=======
{"geometry":{"type":"Point","coordinates":[121.105512,25.012173]},"type":"Feature","properties":{"hierarchy":["tgn:7487647","tgn:1000004","tgn:7001013","tgn:1000141","tgn:7029392"],"placetype":["aat:300008347"],"id":7487647,"name:xx":"Kengwu"}}
>>>>>>> 03f74aca74312dbeaf24d7e61306dd6a786dc3d0
