{
  "id": 7024823,
  "type": "Feature",
  "properties": {
    "tgn:hierarchy":[
        "tgn:7024823",
        "tgn:7002445",
        "tgn:7011980",
        "tgn:1000003",
        "tgn:7008591",
        "tgn:7029392"
    ],
    "tgn:id":7024823,
    "tgn:name:ang":"Wilbertone",
    "tgn:placetype":[
        "aat:300008347"
    ]
},
  "bbox": [],
  "geometry": {"coordinates":[0.166667,52.35],"type":"Point"}
}