<<<<<<< HEAD
{
  "id": 7024823,
  "type": "Feature",
  "properties": {
    "tgn:hierarchy":[
        "tgn:7024823",
        "tgn:7002445",
        "tgn:7011980",
        "tgn:1000003",
        "tgn:7008591",
        "tgn:7029392"
    ],
    "tgn:id":7024823,
    "tgn:name:ang":"Wilbertone",
    "tgn:placetype":[
        "aat:300008347"
    ]
},
  "bbox": [],
  "geometry": {"coordinates":[0.166667,52.35],"type":"Point"}
}
=======
{"geometry":{"type":"Point","coordinates":[0.166667,52.350000]},"type":"Feature","properties":{"hierarchy":["tgn:7024823","tgn:7002445","tgn:7011980","tgn:1000003","tgn:7008591","tgn:7029392"],"placetype":["aat:300008347"],"id":7024823,"name:ang":"Wilbertone"}}
>>>>>>> 03f74aca74312dbeaf24d7e61306dd6a786dc3d0
