<<<<<<< HEAD
{
  "id": 7179148,
  "type": "Feature",
  "properties": {
    "tgn:hierarchy":[
        "tgn:7179148",
        "tgn:7000096",
        "tgn:1000003",
        "tgn:7000084",
        "tgn:7029392"
    ],
    "tgn:id":7179148,
    "tgn:name":"Hammelspring",
    "tgn:placetype":[
        "aat:300008347"
    ]
},
  "bbox": [],
  "geometry": {"coordinates":[13.45,53.066667],"type":"Point"}
}
=======
{"geometry":{"type":"Point","coordinates":[13.450000,53.066667]},"type":"Feature","properties":{"hierarchy":["tgn:7179148","tgn:7000096","tgn:1000003","tgn:7000084","tgn:7029392"],"placetype":["aat:300008347"],"id":7179148,"name:xx":"Hammelspring"}}
>>>>>>> 03f74aca74312dbeaf24d7e61306dd6a786dc3d0
