{
  "id": 2372869,
  "type": "Feature",
  "properties": {
    "tgn:hierarchy":[
        "tgn:2372869",
        "tgn:1000001",
        "tgn:7012149",
        "tgn:1002472",
        "tgn:7007568",
        "tgn:7029392"
    ],
    "tgn:id":2372869,
    "tgn:name":"Hall Vly",
    "tgn:placetype":[
        "aat:300008905"
    ]
},
  "bbox": [],
  "geometry": {"coordinates":[-74.7667,43.2667],"type":"Point"}
}