{
  "id": 7468367,
  "type": "Feature",
  "properties": {
    "tgn:hierarchy":[
        "tgn:7468367",
        "tgn:1000004",
        "tgn:7492971",
        "tgn:1000141",
        "tgn:7029392"
    ],
    "tgn:id":7468367,
    "tgn:name":"Qianjin Shan",
    "tgn:placetype":[
        "aat:300387002"
    ]
},
  "bbox": [],
  "geometry": {"coordinates":[120.620278,22.49],"type":"Point"}
}