{
  "id": 2183491,
  "type": "Feature",
  "properties": {
    "tgn:hierarchy":[
        "tgn:2183491",
        "tgn:1000001",
        "tgn:2000922",
        "tgn:7012149",
        "tgn:7007515",
        "tgn:7029392"
    ],
    "tgn:id":2183491,
    "tgn:name":"Bluff Point",
    "tgn:placetype":[
        "aat:300008850"
    ]
},
  "bbox": [],
  "geometry": {"coordinates":[-68.4167,44.45],"type":"Point"}
}