{
  "id": 2419780,
  "type": "Feature",
  "properties": {
    "tgn:hierarchy":[
        "tgn:2419780",
        "tgn:1000001",
        "tgn:7012149",
        "tgn:2001449",
        "tgn:7007566",
        "tgn:7029392"
    ],
    "tgn:id":2419780,
    "tgn:name":"Jawbone Mountain",
    "tgn:placetype":[
        "aat:300008798"
    ]
},
  "bbox": [],
  "geometry": {"coordinates":[-106.2333,36.7333],"type":"Point"}
}