{
  "id": 7581749,
  "type": "Feature",
  "properties": {
    "tgn:hierarchy":[
        "tgn:7581749",
        "tgn:1000004",
        "tgn:7000198",
        "tgn:1001895",
        "tgn:7029392"
    ],
    "tgn:id":7581749,
    "tgn:name:en":"Vida",
    "tgn:placetype":[
        "aat:300008347"
    ]
},
  "bbox": [],
  "geometry": {"coordinates":[75.930572,18.814164],"type":"Point"}
}