<<<<<<< HEAD
{
  "id": 2157953,
  "type": "Feature",
  "properties": {
    "tgn:hierarchy":[
        "tgn:2157953",
        "tgn:1000001",
        "tgn:1002664",
        "tgn:7012149",
        "tgn:7007159",
        "tgn:7029392"
    ],
    "tgn:id":2157953,
    "tgn:name":"Beaver Meadow Brook",
    "tgn:placetype":[
        "aat:300008699"
    ]
},
  "bbox": [],
  "geometry": {"coordinates":[-72.55,41.4333],"type":"Point"}
}
=======
{"geometry":{"type":"Point","coordinates":[-72.550000,41.433300]},"type":"Feature","properties":{"hierarchy":["tgn:2157953","tgn:1000001","tgn:1002664","tgn:7012149","tgn:7007159","tgn:7029392"],"placetype":["aat:300008699"],"id":2157953,"name:xx":"Beaver Meadow Brook"}}
>>>>>>> 03f74aca74312dbeaf24d7e61306dd6a786dc3d0
