{
  "id": 7038441,
  "type": "Feature",
  "properties": {
    "tgn:hierarchy":[
        "tgn:7038441",
        "tgn:1003510",
        "tgn:1000003",
        "tgn:7003120",
        "tgn:1000080",
        "tgn:7029392"
    ],
    "tgn:id":7038441,
    "tgn:name":"Tollegno",
    "tgn:placetype":[
        "aat:300008347"
    ]
},
  "bbox": [],
  "geometry": {"coordinates":[8.05,45.583333],"type":"Point"}
}