{
  "id": 2477064,
  "type": "Feature",
  "properties": {
    "tgn:hierarchy":[
        "tgn:2477064",
        "tgn:1000001",
        "tgn:7012149",
        "tgn:2001110",
        "tgn:7007522",
        "tgn:7029392"
    ],
    "tgn:id":2477064,
    "tgn:name":"Lynchburg",
    "tgn:placetype":[
        "aat:300008347"
    ]
},
  "bbox": [],
  "geometry": {"coordinates":[-90.5333,32.4333],"type":"Point"}
}