{
  "id": 7534105,
  "type": "Feature",
  "properties": {
    "tgn:hierarchy":[
        "tgn:7534105",
        "tgn:7001242",
        "tgn:7016833",
        "tgn:7029392"
    ],
    "tgn:id":7534105,
    "tgn:name:en":"\u1e28asan\u012b, W\u0101d\u012b",
    "tgn:placetype":[
        "aat:300379998"
    ]
},
  "bbox": [],
  "geometry": {"coordinates":[31.630501,29.701687],"type":"Point"}
}