{
  "id": 7227099,
  "type": "Feature",
  "properties": {
    "tgn:hierarchy":[
        "tgn:7227099",
        "tgn:7011270",
        "tgn:7002674",
        "tgn:1000003",
        "tgn:1000074",
        "tgn:7029392"
    ],
    "tgn:id":7227099,
    "tgn:name":"Mis\u00f3, \u00d3rmos",
    "tgn:placetype":[
        "aat:300132316"
    ]
},
  "bbox": [],
  "geometry": {"coordinates":[25.216667,37.383333],"type":"Point"}
}