{
  "id": 7458112,
  "type": "Feature",
  "properties": {
    "tgn:hierarchy":[
        "tgn:7458112",
        "tgn:7019141",
        "tgn:7002444",
        "tgn:1000003",
        "tgn:7008591",
        "tgn:7029392"
    ],
    "tgn:id":7458112,
    "tgn:name:en":"Nigg Bay",
    "tgn:placetype":[
        "aat:300132316"
    ]
},
  "bbox": [],
  "geometry": {"coordinates":[-2.05,57.133333],"type":"Point"}
}