{
  "id": 2347973,
  "type": "Feature",
  "properties": {
    "tgn:hierarchy":[
        "tgn:2347973",
        "tgn:1000001",
        "tgn:7012149",
        "tgn:1002789",
        "tgn:7007710",
        "tgn:7029392"
    ],
    "tgn:id":2347973,
    "tgn:name":"German Hill",
    "tgn:placetype":[
        "aat:300008798"
    ]
},
  "bbox": [],
  "geometry": {"coordinates":[-74.9333,41.45],"type":"Point"}
}