{
  "id": 7505127,
  "type": "Feature",
  "properties": {
    "tgn:hierarchy":[
        "tgn:7505127",
        "tgn:1009227",
        "tgn:1000226",
        "tgn:7016822",
        "tgn:1000006",
        "tgn:7029392"
    ],
    "tgn:id":7505127,
    "tgn:name:en":"North Promontory",
    "tgn:placetype":[
        "aat:300387499"
    ]
},
  "bbox": [],
  "geometry": {"coordinates":[166.600278,-48.016667],"type":"Point"}
}