{
  "id": 2436861,
  "type": "Feature",
  "properties": {
    "tgn:hierarchy":[
        "tgn:2436861",
        "tgn:1000001",
        "tgn:7012149",
        "tgn:2001976",
        "tgn:7007826",
        "tgn:7029392"
    ],
    "tgn:id":2436861,
    "tgn:name":"Kilfoil Draw",
    "tgn:placetype":[
        "aat:300008761"
    ]
},
  "bbox": [],
  "geometry": {"coordinates":[-100.7167,34.8167],"type":"Point"}
}