{
  "id": 7040824,
  "type": "Feature",
  "properties": {
    "tgn:hierarchy":[
        "tgn:7040824",
        "tgn:1003473",
        "tgn:1000003",
        "tgn:7009760",
        "tgn:1000080",
        "tgn:7029392"
    ],
    "tgn:id":7040824,
    "tgn:name":"Santa Maria, Punta",
    "tgn:placetype":[
        "aat:300386846"
    ]
},
  "bbox": [],
  "geometry": {"coordinates":[9.85,44.066667],"type":"Point"}
}