<<<<<<< HEAD
{
  "id": 7118005,
  "type": "Feature",
  "properties": {
    "tgn:hierarchy":[
        "tgn:7118005",
        "tgn:7000096",
        "tgn:1000003",
        "tgn:7000084",
        "tgn:7029392"
    ],
    "tgn:id":7118005,
    "tgn:name":"\u00d6lsener See",
    "tgn:placetype":[
        "aat:300008680"
    ]
},
  "bbox": [],
  "geometry": {"coordinates":[14.4,52.133333],"type":"Point"}
}
=======
{"geometry":{"type":"Point","coordinates":[14.400000,52.133333]},"type":"Feature","properties":{"hierarchy":["tgn:7118005","tgn:7000096","tgn:1000003","tgn:7000084","tgn:7029392"],"placetype":["aat:300008680"],"id":7118005,"name:xx":"\u00d6lsener See"}}
>>>>>>> 03f74aca74312dbeaf24d7e61306dd6a786dc3d0
