{
  "id": 2706529,
  "type": "Feature",
  "properties": {
    "tgn:hierarchy":[
        "tgn:2706529",
        "tgn:1000001",
        "tgn:7012149",
        "tgn:2000401",
        "tgn:7007248",
        "tgn:7029392"
    ],
    "tgn:id":2706529,
    "tgn:name":"Swan Lake",
    "tgn:placetype":[
        "aat:300008347"
    ]
},
  "bbox": [],
  "geometry": {"coordinates":[-84.8167,33.8333],"type":"Point"}
}