{
  "id": 7016009,
  "type": "Feature",
  "properties": {
    "tgn:hierarchy":[
        "tgn:7016009",
        "tgn:1000001",
        "tgn:7014406",
        "tgn:7012149",
        "tgn:1002782",
        "tgn:7007710",
        "tgn:7029392"
    ],
    "tgn:id":7016009,
    "tgn:name":"Tacony",
    "tgn:placetype":[
        "aat:300000745"
    ]
},
  "bbox": [],
  "geometry": {"coordinates":[-75.0333,40.0167],"type":"Point"}
}