<<<<<<< HEAD
{
  "id": 2401895,
  "type": "Feature",
  "properties": {
    "tgn:hierarchy":[
        "tgn:2401895",
        "tgn:1000001",
        "tgn:1002305",
        "tgn:7012149",
        "tgn:7007920",
        "tgn:7029392"
    ],
    "tgn:id":2401895,
    "tgn:name":"Horseshoe Lake",
    "tgn:placetype":[
        "aat:300008680"
    ]
},
  "bbox": [],
  "geometry": {"coordinates":[-122.7333,45.8833],"type":"Point"}
}
=======
{"geometry":{"type":"Point","coordinates":[-122.733300,45.883300]},"type":"Feature","properties":{"hierarchy":["tgn:2401895","tgn:1000001","tgn:1002305","tgn:7012149","tgn:7007920","tgn:7029392"],"placetype":["aat:300008680"],"id":2401895,"name:xx":"Horseshoe Lake"}}
>>>>>>> 03f74aca74312dbeaf24d7e61306dd6a786dc3d0
