{
  "id": 2401895,
  "type": "Feature",
  "properties": {
    "tgn:hierarchy":[
        "tgn:2401895",
        "tgn:1000001",
        "tgn:1002305",
        "tgn:7012149",
        "tgn:7007920",
        "tgn:7029392"
    ],
    "tgn:id":2401895,
    "tgn:name":"Horseshoe Lake",
    "tgn:placetype":[
        "aat:300008680"
    ]
},
  "bbox": [],
  "geometry": {"coordinates":[-122.7333,45.8833],"type":"Point"}
}