<<<<<<< HEAD
{
  "id": 7246088,
  "type": "Feature",
  "properties": {
    "tgn:hierarchy":[
        "tgn:7246088",
        "tgn:7003466",
        "tgn:1000003",
        "tgn:1000063",
        "tgn:4012014",
        "tgn:7029392"
    ],
    "tgn:id":7246088,
    "tgn:name":"Corbeau",
    "tgn:placetype":[
        "aat:300008347"
    ]
},
  "bbox": [],
  "geometry": {"coordinates":[4.891002,50.57048],"type":"Point"}
}
=======
{"geometry":{"type":"Point","coordinates":[4.891002,50.570480]},"type":"Feature","properties":{"hierarchy":["tgn:7246088","tgn:7003466","tgn:1000003","tgn:1000063","tgn:4012014","tgn:7029392"],"placetype":["aat:300008347"],"id":7246088,"name:xx":"Corbeau"}}
>>>>>>> 03f74aca74312dbeaf24d7e61306dd6a786dc3d0
