{
  "id": 7061730,
  "type": "Feature",
  "properties": {
    "tgn:hierarchy":[
        "tgn:7061730",
        "tgn:1000003",
        "tgn:7003685",
        "tgn:7000084",
        "tgn:7029392"
    ],
    "tgn:id":7061730,
    "tgn:name":"Bachwiesen",
    "tgn:placetype":[
        "aat:300386990"
    ]
},
  "bbox": [],
  "geometry": {"coordinates":[13.866667,51.35],"type":"Point"}
}