{
  "id": 2335923,
  "type": "Feature",
  "properties": {
    "tgn:hierarchy":[
        "tgn:2335923",
        "tgn:1000001",
        "tgn:7012149",
        "tgn:2001892",
        "tgn:7007825",
        "tgn:7029392"
    ],
    "tgn:id":2335923,
    "tgn:name":"Fossil Creek Cave",
    "tgn:placetype":[
        "aat:300008746"
    ]
},
  "bbox": [],
  "geometry": {"coordinates":[-86.0167,36.45],"type":"Point"}
}