<<<<<<< HEAD
{
  "id": 2335923,
  "type": "Feature",
  "properties": {
    "tgn:hierarchy":[
        "tgn:2335923",
        "tgn:1000001",
        "tgn:7012149",
        "tgn:2001892",
        "tgn:7007825",
        "tgn:7029392"
    ],
    "tgn:id":2335923,
    "tgn:name":"Fossil Creek Cave",
    "tgn:placetype":[
        "aat:300008746"
    ]
},
  "bbox": [],
  "geometry": {"coordinates":[-86.0167,36.45],"type":"Point"}
}
=======
{"geometry":{"type":"Point","coordinates":[-86.016700,36.450000]},"type":"Feature","properties":{"hierarchy":["tgn:2335923","tgn:1000001","tgn:7012149","tgn:2001892","tgn:7007825","tgn:7029392"],"placetype":["aat:300008746"],"id":2335923,"name:xx":"Fossil Creek Cave"}}
>>>>>>> 03f74aca74312dbeaf24d7e61306dd6a786dc3d0
