{
  "id": 7133947,
  "type": "Feature",
  "properties": {
    "tgn:hierarchy":[
        "tgn:7133947",
        "tgn:1000003",
        "tgn:7000094",
        "tgn:7000084",
        "tgn:7029392"
    ],
    "tgn:id":7133947,
    "tgn:name":"Moorteich",
    "tgn:placetype":[
        "aat:300008679"
    ]
},
  "bbox": [],
  "geometry": {"coordinates":[13.066667,54.316667],"type":"Point"}
}