{
  "id": 2604750,
  "type": "Feature",
  "properties": {
    "tgn:hierarchy":[
        "tgn:2604750",
        "tgn:1000001",
        "tgn:2001425",
        "tgn:7012149",
        "tgn:7007564",
        "tgn:7029392"
    ],
    "tgn:id":2604750,
    "tgn:name":"Raccoon Hill",
    "tgn:placetype":[
        "aat:300008798"
    ]
},
  "bbox": [],
  "geometry": {"coordinates":[-71.75,43.4167],"type":"Point"}
}