{
  "id": 2182228,
  "type": "Feature",
  "properties": {
    "tgn:hierarchy":[
        "tgn:2182228",
        "tgn:1000001",
        "tgn:7006451",
        "tgn:7012149",
        "tgn:2000097",
        "tgn:7029392"
    ],
    "tgn:id":2182228,
    "tgn:name":"Blue Mountain Spring",
    "tgn:placetype":[
        "aat:300008697"
    ]
},
  "bbox": [],
  "geometry": {"coordinates":[-111.7667,33.8333],"type":"Point"}
}