<<<<<<< HEAD
{
  "id": 7176826,
  "type": "Feature",
  "properties": {
    "tgn:hierarchy":[
        "tgn:7176826",
        "tgn:1000003",
        "tgn:7003677",
        "tgn:7000084",
        "tgn:7029392"
    ],
    "tgn:id":7176826,
    "tgn:name":"Hardt",
    "tgn:placetype":[
        "aat:300008795"
    ]
},
  "bbox": [],
  "geometry": {"coordinates":[8.366667,51.166667],"type":"Point"}
}
=======
{"geometry":{"type":"Point","coordinates":[8.366667,51.166667]},"type":"Feature","properties":{"hierarchy":["tgn:7176826","tgn:1000003","tgn:7003677","tgn:7000084","tgn:7029392"],"placetype":["aat:300008795"],"id":7176826,"name:xx":"Hardt"}}
>>>>>>> 03f74aca74312dbeaf24d7e61306dd6a786dc3d0
