{
  "id": 7549713,
  "type": "Feature",
  "properties": {
    "tgn:hierarchy":[
        "tgn:7549713",
        "tgn:1000004",
        "tgn:7031781",
        "tgn:7000198",
        "tgn:7029392"
    ],
    "tgn:id":7549713,
    "tgn:name:en":"Dhanpunji",
    "tgn:placetype":[
        "aat:300008347"
    ]
},
  "bbox": [],
  "geometry": {"coordinates":[82.216667,19.083333],"type":"Point"}
}