{
  "id": 7231456,
  "type": "Feature",
  "properties": {
    "tgn:hierarchy":[
        "tgn:7231456",
        "tgn:7011167",
        "tgn:7001338",
        "tgn:1000003",
        "tgn:1000074",
        "tgn:7029392"
    ],
    "tgn:id":7231456,
    "tgn:name":"Marandokh\u00f3rion",
    "tgn:placetype":[
        "aat:300008347"
    ]
},
  "bbox": [],
  "geometry": {"coordinates":[20.65,38.633333],"type":"Point"}
}