{
  "id": 2743924,
  "type": "Feature",
  "properties": {
    "tgn:hierarchy":[
        "tgn:2743924",
        "tgn:1000001",
        "tgn:7012149",
        "tgn:7029392"
    ],
    "tgn:id":2743924,
    "tgn:name":"Venadito Draw",
    "tgn:placetype":[
        "aat:300008761"
    ]
},
  "bbox": [],
  "geometry": {"coordinates":[-108.7667,34.8333],"type":"Point"}
}