{
  "id": 2505646,
  "type": "Feature",
  "properties": {
    "tgn:hierarchy":[
        "tgn:2505646",
        "tgn:1000001",
        "tgn:7006451",
        "tgn:2000092",
        "tgn:7012149",
        "tgn:7029392"
    ],
    "tgn:id":2505646,
    "tgn:name":"Mencius Temple",
    "tgn:placetype":[
        "aat:300008798"
    ]
},
  "bbox": [],
  "geometry": {"coordinates":[-112.2167,36.1667],"type":"Point"}
}