{
  "id": 2104651,
  "type": "Feature",
  "properties": {
    "tgn:hierarchy":[
        "tgn:2104651",
        "tgn:1000001",
        "tgn:7012149",
        "tgn:2001994",
        "tgn:7007826",
        "tgn:7029392"
    ],
    "tgn:id":2104651,
    "tgn:name":"Halfway",
    "tgn:placetype":[
        "aat:300008347"
    ]
},
  "bbox": [],
  "geometry": {"coordinates":[-101.95,34.1833],"type":"Point"}
}