{
  "id": 7222431,
  "type": "Feature",
  "properties": {
    "tgn:hierarchy":[
        "tgn:7222431",
        "tgn:7011330",
        "tgn:7002674",
        "tgn:1000003",
        "tgn:1000074",
        "tgn:7029392"
    ],
    "tgn:id":7222431,
    "tgn:name":"Meg\u00edsti",
    "tgn:placetype":[
        "aat:300008347"
    ]
},
  "bbox": [],
  "geometry": {"coordinates":[29.593611,36.148889],"type":"Point"}
}