{
  "id": 2085436,
  "type": "Feature",
  "properties": {
    "tgn:hierarchy":[
        "tgn:2085436",
        "tgn:1000001",
        "tgn:7012149",
        "tgn:2001718",
        "tgn:7007708",
        "tgn:7029392"
    ],
    "tgn:id":2085436,
    "tgn:name":"Riverside",
    "tgn:placetype":[
        "aat:300008347"
    ]
},
  "bbox": [],
  "geometry": {"coordinates":[-118.15,43.5333],"type":"Point"}
}