{
  "id": 2606114,
  "type": "Feature",
  "properties": {
    "tgn:hierarchy":[
        "tgn:2606114",
        "tgn:1000001",
        "tgn:7012149",
        "tgn:2001723",
        "tgn:7007708",
        "tgn:7029392"
    ],
    "tgn:id":2606114,
    "tgn:name":"Rainier Spring",
    "tgn:placetype":[
        "aat:300008697"
    ]
},
  "bbox": [],
  "geometry": {"coordinates":[-120.0333,44.4667],"type":"Point"}
}