{
  "id": 2191413,
  "type": "Feature",
  "properties": {
    "tgn:hierarchy":[
        "tgn:2191413",
        "tgn:2000919",
        "tgn:1000001",
        "tgn:7012149",
        "tgn:7007515",
        "tgn:7029392"
    ],
    "tgn:id":2191413,
    "tgn:name":"Bradbury",
    "tgn:placetype":[
        "aat:300008347"
    ]
},
  "bbox": [],
  "geometry": {"coordinates":[-68.8333,47.1833],"type":"Point"}
}