{
  "id": 7487151,
  "type": "Feature",
  "properties": {
    "tgn:hierarchy":[
        "tgn:7487151",
        "tgn:1000004",
        "tgn:7001014",
        "tgn:1000141",
        "tgn:7029392"
    ],
    "tgn:id":7487151,
    "tgn:name":"Linnei",
    "tgn:placetype":[
        "aat:300008347"
    ]
},
  "bbox": [],
  "geometry": {"coordinates":[120.618849,23.761499],"type":"Point"}
}