<<<<<<< HEAD
{
  "id": 2155101,
  "type": "Feature",
  "properties": {
    "tgn:hierarchy":[
        "tgn:2155101",
        "tgn:1000001",
        "tgn:7012149",
        "tgn:7007522",
        "tgn:7029392"
    ],
    "tgn:id":2155101,
    "tgn:name":"Bear Lake",
    "tgn:placetype":[
        "aat:300008699"
    ]
},
  "bbox": [],
  "geometry": {"coordinates":[-90.85,33.5833],"type":"Point"}
}
=======
{"geometry":{"type":"Point","coordinates":[-90.850000,33.583300]},"type":"Feature","properties":{"hierarchy":["tgn:2155101","tgn:1000001","tgn:7012149","tgn:7007522","tgn:7029392"],"placetype":["aat:300008699"],"id":2155101,"name:xx":"Bear Lake"}}
>>>>>>> 03f74aca74312dbeaf24d7e61306dd6a786dc3d0
