{
  "id": 2155101,
  "type": "Feature",
  "properties": {
    "tgn:hierarchy":[
        "tgn:2155101",
        "tgn:1000001",
        "tgn:7012149",
        "tgn:7007522",
        "tgn:7029392"
    ],
    "tgn:id":2155101,
    "tgn:name":"Bear Lake",
    "tgn:placetype":[
        "aat:300008699"
    ]
},
  "bbox": [],
  "geometry": {"coordinates":[-90.85,33.5833],"type":"Point"}
}