{
  "id": 2482394,
  "type": "Feature",
  "properties": {
    "tgn:hierarchy":[
        "tgn:2482394",
        "tgn:7002659",
        "tgn:1000001",
        "tgn:2000009",
        "tgn:7012149",
        "tgn:7029392"
    ],
    "tgn:id":2482394,
    "tgn:name":"Lanie Hollow",
    "tgn:placetype":[
        "aat:300008761"
    ]
},
  "bbox": [],
  "geometry": {"coordinates":[-85.4833,33.95],"type":"Point"}
}