{
  "id": 1120415,
  "type": "Feature",
  "properties": {
    "tgn:hierarchy":[
        "tgn:1120415",
        "tgn:1000001",
        "tgn:7012149",
        "tgn:1002758",
        "tgn:7007568",
        "tgn:7029392"
    ],
    "tgn:id":1120415,
    "tgn:name":"Salmon River Reservoir",
    "tgn:placetype":[
        "aat:300006191"
    ]
},
  "bbox": [],
  "geometry": {"coordinates":[-75.9167,43.5333],"type":"Point"}
}