{
  "id": 1036110,
  "type": "Feature",
  "properties": {
    "tgn:hierarchy":[
        "tgn:1036110",
        "tgn:1000003",
        "tgn:1000070",
        "tgn:7002897",
        "tgn:7029392"
    ],
    "tgn:id":1036110,
    "tgn:name":"Vif",
    "tgn:placetype":[
        "aat:300008347"
    ]
},
  "bbox": [],
  "geometry": {"coordinates":[5.6667,45.05],"type":"Point"}
}