{
  "id": 2199320,
  "type": "Feature",
  "properties": {
    "tgn:hierarchy":[
        "tgn:2199320",
        "tgn:1000001",
        "tgn:7012149",
        "tgn:2001299",
        "tgn:7007524",
        "tgn:7029392"
    ],
    "tgn:id":2199320,
    "tgn:name":"Brush Coulee",
    "tgn:placetype":[
        "aat:300008761"
    ]
},
  "bbox": [],
  "geometry": {"coordinates":[-105.4667,47.0667],"type":"Point"}
}