{
  "id": 2221734,
  "type": "Feature",
  "properties": {
    "tgn:hierarchy":[
        "tgn:2221734",
        "tgn:1000001",
        "tgn:7012149",
        "tgn:1002818",
        "tgn:7007252",
        "tgn:7029392"
    ],
    "tgn:id":2221734,
    "tgn:name":"Carlos Drain",
    "tgn:placetype":[
        "aat:300008699"
    ]
},
  "bbox": [],
  "geometry": {"coordinates":[-85.0167,40.0167],"type":"Point"}
}