{
  "id": 7235557,
  "type": "Feature",
  "properties": {
    "tgn:hierarchy":[
        "tgn:7235557",
        "tgn:7002715",
        "tgn:7002731",
        "tgn:1000003",
        "tgn:1000074",
        "tgn:7029392"
    ],
    "tgn:id":7235557,
    "tgn:name":"Filadh\u00e9lfion",
    "tgn:placetype":[
        "aat:300008347"
    ]
},
  "bbox": [],
  "geometry": {"coordinates":[23.466667,40.75],"type":"Point"}
}