{
  "id": 7282462,
  "type": "Feature",
  "properties": {
    "tgn:hierarchy":[
        "tgn:7282462",
        "tgn:1001705",
        "tgn:1000049",
        "tgn:1000002",
        "tgn:7029392"
    ],
    "tgn:id":7282462,
    "tgn:name":"Peumo, Quebrada del",
    "tgn:placetype":[
        "aat:300008699"
    ]
},
  "bbox": [],
  "geometry": {"coordinates":[-72.15,-34.85],"type":"Point"}
}