{
  "id": 7404763,
  "type": "Feature",
  "properties": {
    "tgn:hierarchy":[
        "tgn:7404763",
        "tgn:7016644",
        "tgn:1000001",
        "tgn:7005560",
        "tgn:7029392"
    ],
    "tgn:id":7404763,
    "tgn:name":"Cuyutl\u00e1n",
    "tgn:placetype":[
        "aat:300008347"
    ]
},
  "bbox": [],
  "geometry": {"coordinates":[-104.066667,18.916667],"type":"Point"}
}