{
  "id": 7468727,
  "type": "Feature",
  "properties": {
    "tgn:hierarchy":[
        "tgn:7468727",
        "tgn:1000004",
        "tgn:1000454",
        "tgn:1000141",
        "tgn:7029392"
    ],
    "tgn:id":7468727,
    "tgn:name":"Fengtian Cun",
    "tgn:placetype":[
        "aat:300387173"
    ]
},
  "bbox": [],
  "geometry": {"coordinates":[121.6943,24.9724],"type":"Point"}
}