{
  "id": 2208885,
  "type": "Feature",
  "properties": {
    "tgn:hierarchy":[
        "tgn:2208885",
        "tgn:1000001",
        "tgn:7012149",
        "tgn:7007157",
        "tgn:7029392"
    ],
    "tgn:id":2208885,
    "tgn:name":"Burnt Canyon",
    "tgn:placetype":[
        "aat:300008761"
    ]
},
  "bbox": [],
  "geometry": {"coordinates":[-118.2833,35.7667],"type":"Point"}
}