{
  "id": 1083320,
  "type": "Feature",
  "properties": {
    "tgn:hierarchy":[
        "tgn:1083320",
        "tgn:7001433",
        "tgn:7001420",
        "tgn:1000004",
        "tgn:1000132",
        "tgn:7029392"
    ],
    "tgn:id":1083320,
    "tgn:name":"T\u0101lkot",
    "tgn:placetype":[
        "aat:300008347"
    ]
},
  "bbox": [],
  "geometry": {"coordinates":[81.3167,29.6167],"type":"Point"}
}