{
  "id": 7316233,
  "type": "Feature",
  "properties": {
    "tgn:hierarchy":[
        "tgn:7316233",
        "tgn:1001630",
        "tgn:1000049",
        "tgn:1000002",
        "tgn:7029392"
    ],
    "tgn:id":7316233,
    "tgn:name":"Casa de Piedra, Aguada",
    "tgn:placetype":[
        "aat:300008697"
    ]
},
  "bbox": [],
  "geometry": {"coordinates":[-70.65,-28.816667],"type":"Point"}
}