{
  "id": 5002073,
  "type": "Feature",
  "properties": {
    "tgn:hierarchy":[
        "tgn:5002073",
        "tgn:7009084",
        "tgn:7004154",
        "tgn:1000003",
        "tgn:1000080",
        "tgn:7029392"
    ],
    "tgn:id":5002073,
    "tgn:name":"Preturo",
    "tgn:placetype":[
        "aat:300008347",
        "aat:300008375"
    ]
},
  "bbox": [],
  "geometry": {"coordinates":[13.283333,42.366667],"type":"Point"}
}