{
  "id": 2045216,
  "type": "Feature",
  "properties": {
    "tgn:hierarchy":[
        "tgn:2045216",
        "tgn:1000001",
        "tgn:7012149",
        "tgn:2000927",
        "tgn:7007515",
        "tgn:7029392"
    ],
    "tgn:id":2045216,
    "tgn:name":"Newport",
    "tgn:placetype":[
        "aat:300008347"
    ]
},
  "bbox": [],
  "geometry": {"coordinates":[-69.2667,44.8333],"type":"Point"}
}