{
  "id": 7356152,
  "type": "Feature",
  "properties": {
    "tgn:hierarchy":[
        "tgn:7356152",
        "tgn:7005584",
        "tgn:1000001",
        "tgn:7005560",
        "tgn:7029392"
    ],
    "tgn:id":7356152,
    "tgn:name":"Cerro del Diablo",
    "tgn:placetype":[
        "aat:300008347"
    ]
},
  "bbox": [],
  "geometry": {"coordinates":[-101.716667,20.816667],"type":"Point"}
}