{
  "id": 7531778,
  "type": "Feature",
  "properties": {
    "tgn:hierarchy":[
        "tgn:7531778",
        "tgn:7001242",
        "tgn:7016833",
        "tgn:7001335",
        "tgn:7029392"
    ],
    "tgn:id":7531778,
    "tgn:name":"Abu Nafil, \u1e24\u00f4\u1e0d",
    "tgn:placetype":[
        "aat:300387498"
    ]
},
  "bbox": [],
  "geometry": {"coordinates":[32.979012,31.015843],"type":"Point"}
}