{
  "id": 2620957,
  "type": "Feature",
  "properties": {
    "tgn:hierarchy":[
        "tgn:2620957",
        "tgn:1000001",
        "tgn:7012149",
        "tgn:2001451",
        "tgn:7007566",
        "tgn:7029392"
    ],
    "tgn:id":2620957,
    "tgn:name":"Road Canyon",
    "tgn:placetype":[
        "aat:300008761"
    ]
},
  "bbox": [],
  "geometry": {"coordinates":[-106.6167,35.9667],"type":"Point"}
}