{
  "id": 2533791,
  "type": "Feature",
  "properties": {
    "tgn:hierarchy":[
        "tgn:2533791",
        "tgn:1000001",
        "tgn:7016172",
        "tgn:7012149",
        "tgn:2000155",
        "tgn:7029392"
    ],
    "tgn:id":2533791,
    "tgn:name":"Mutton Point",
    "tgn:placetype":[
        "aat:300008798"
    ]
},
  "bbox": [],
  "geometry": {"coordinates":[-93.2333,36.05],"type":"Point"}
}