{
  "id": 2235366,
  "type": "Feature",
  "properties": {
    "tgn:hierarchy":[
        "tgn:2235366",
        "tgn:1000001",
        "tgn:2001417",
        "tgn:7012149",
        "tgn:7007526",
        "tgn:7029392"
    ],
    "tgn:id":2235366,
    "tgn:name":"Chesco Mine",
    "tgn:placetype":[
        "aat:300000390"
    ]
},
  "bbox": [],
  "geometry": {"coordinates":[-118.8667,38.2833],"type":"Point"}
}