<<<<<<< HEAD
{
  "id": 7249502,
  "type": "Feature",
  "properties": {
    "tgn:hierarchy":[
        "tgn:7249502",
        "tgn:7003460",
        "tgn:1000003",
        "tgn:1000063",
        "tgn:4012014",
        "tgn:7029392"
    ],
    "tgn:id":7249502,
    "tgn:name":"Oufny",
    "tgn:placetype":[
        "aat:300008347"
    ]
},
  "bbox": [],
  "geometry": {"coordinates":[5.7,50.383333],"type":"Point"}
}
=======
{"geometry":{"type":"Point","coordinates":[5.700000,50.383333]},"type":"Feature","properties":{"hierarchy":["tgn:7249502","tgn:7003460","tgn:1000003","tgn:1000063","tgn:4012014","tgn:7029392"],"placetype":["aat:300008347"],"id":7249502,"name:xx":"Oufny"}}
>>>>>>> 03f74aca74312dbeaf24d7e61306dd6a786dc3d0
