{
  "id": 7504981,
  "type": "Feature",
  "properties": {
    "tgn:hierarchy":[
        "tgn:7504981",
        "tgn:1008380",
        "tgn:1000226",
        "tgn:7000512",
        "tgn:1000006",
        "tgn:7029392"
    ],
    "tgn:id":7504981,
    "tgn:name:en":"Kahau Rocks",
    "tgn:placetype":[
        "aat:300011692"
    ]
},
  "bbox": [],
  "geometry": {"coordinates":[175.828889,-41.373056],"type":"Point"}
}