{
  "id": 2304311,
  "type": "Feature",
  "properties": {
    "tgn:hierarchy":[
        "tgn:2304311",
        "tgn:1000001",
        "tgn:7012149",
        "tgn:2000281",
        "tgn:7007240",
        "tgn:7029392"
    ],
    "tgn:id":2304311,
    "tgn:name":"Earl, Lake",
    "tgn:placetype":[
        "aat:300008680"
    ]
},
  "bbox": [],
  "geometry": {"coordinates":[-86.5833,30.4167],"type":"Point"}
}