{
  "id": 7410132,
  "type": "Feature",
  "properties": {
    "tgn:hierarchy":[
        "tgn:7410132",
        "tgn:1000001",
        "tgn:1001893",
        "tgn:7005560",
        "tgn:7029392"
    ],
    "tgn:id":7410132,
    "tgn:name":"El Sauz",
    "tgn:placetype":[
        "aat:300008347"
    ]
},
  "bbox": [],
  "geometry": {"coordinates":[-100.225,18.991667],"type":"Point"}
}