{
  "id": 7108358,
  "type": "Feature",
  "properties": {
    "tgn:hierarchy":[
        "tgn:7108358",
        "tgn:1000003",
        "tgn:7003678",
        "tgn:7000084",
        "tgn:7029392"
    ],
    "tgn:id":7108358,
    "tgn:name":"Rabertshausen",
    "tgn:placetype":[
        "aat:300008347"
    ]
},
  "bbox": [],
  "geometry": {"coordinates":[8.983333,50.466667],"type":"Point"}
}