<<<<<<< HEAD
{
  "id": 2152038,
  "type": "Feature",
  "properties": {
    "tgn:hierarchy":[
        "tgn:2152038",
        "tgn:1000001",
        "tgn:7012149",
        "tgn:2001458",
        "tgn:7007566",
        "tgn:7029392"
    ],
    "tgn:id":2152038,
    "tgn:name":"Baumgartner Tank",
    "tgn:placetype":[
        "aat:300006191"
    ]
},
  "bbox": [],
  "geometry": {"coordinates":[-106.1833,34.4667],"type":"Point"}
}
=======
{"geometry":{"type":"Point","coordinates":[-106.183300,34.466700]},"type":"Feature","properties":{"hierarchy":["tgn:2152038","tgn:1000001","tgn:7012149","tgn:2001458","tgn:7007566","tgn:7029392"],"placetype":["aat:300006191"],"id":2152038,"name:xx":"Baumgartner Tank"}}
>>>>>>> 03f74aca74312dbeaf24d7e61306dd6a786dc3d0
