{
  "id": 2151003,
  "type": "Feature",
  "properties": {
    "tgn:hierarchy":[
        "tgn:2151003",
        "tgn:1000001",
        "tgn:1003037",
        "tgn:7012149",
        "tgn:7007516",
        "tgn:7029392"
    ],
    "tgn:id":2151003,
    "tgn:name":"Bassett Millpond",
    "tgn:placetype":[
        "aat:300008905"
    ]
},
  "bbox": [],
  "geometry": {"coordinates":[-75.2333,38.25],"type":"Point"}
}