{
  "id": 7414824,
  "type": "Feature",
  "properties": {
    "tgn:hierarchy":[
        "tgn:7414824",
        "tgn:1000001",
        "tgn:7005591",
        "tgn:7005560",
        "tgn:7029392"
    ],
    "tgn:id":7414824,
    "tgn:name:es":"Guadalupe del Palmar",
    "tgn:placetype":[
        "aat:300008347"
    ]
},
  "bbox": [],
  "geometry": {"coordinates":[-98.126389,17.606944],"type":"Point"}
}