{
  "id": 7282156,
  "type": "Feature",
  "properties": {
    "tgn:hierarchy":[
        "tgn:7282156",
        "tgn:1001702",
        "tgn:1000049",
        "tgn:1000002",
        "tgn:7029392"
    ],
    "tgn:id":7282156,
    "tgn:name":"Sat\u00e9lites, Islotes",
    "tgn:placetype":[
        "aat:300008791"
    ]
},
  "bbox": [],
  "geometry": {"coordinates":[-72.633333,-52.666667],"type":"Point"}
}