{
  "id": 2387448,
  "type": "Feature",
  "properties": {
    "tgn:hierarchy":[
        "tgn:2387448",
        "tgn:1000001",
        "tgn:7012149",
        "tgn:2001883",
        "tgn:7007825",
        "tgn:7029392"
    ],
    "tgn:id":2387448,
    "tgn:name":"Hewitt Branch",
    "tgn:placetype":[
        "aat:300008699"
    ]
},
  "bbox": [],
  "geometry": {"coordinates":[-84.2167,35.9333],"type":"Point"}
}