{
  "id": 2785575,
  "type": "Feature",
  "properties": {
    "tgn:hierarchy":[
        "tgn:2785575",
        "tgn:1000001",
        "tgn:7012149",
        "tgn:2000984",
        "tgn:7007520",
        "tgn:7029392"
    ],
    "tgn:id":2785575,
    "tgn:name":"Yocks Pond",
    "tgn:placetype":[
        "aat:300008905"
    ]
},
  "bbox": [],
  "geometry": {"coordinates":[-86.1333,43.75],"type":"Point"}
}