{
  "id": 1119631,
  "type": "Feature",
  "properties": {
    "tgn:hierarchy":[
        "tgn:1119631",
        "tgn:1000001",
        "tgn:7019982",
        "tgn:7012149",
        "tgn:7007517",
        "tgn:7029392"
    ],
    "tgn:id":1119631,
    "tgn:name":"Cobble Mountain Reservoir",
    "tgn:placetype":[
        "aat:300006191"
    ]
},
  "bbox": [],
  "geometry": {"coordinates":[-72.8833,42.1167],"type":"Point"}
}