{
  "id": 2213669,
  "type": "Feature",
  "properties": {
    "tgn:hierarchy":[
        "tgn:2213669",
        "tgn:1002145",
        "tgn:1000001",
        "tgn:7012149",
        "tgn:7007157",
        "tgn:7029392"
    ],
    "tgn:id":2213669,
    "tgn:name":"Cache Creek",
    "tgn:placetype":[
        "aat:300008706"
    ]
},
  "bbox": [],
  "geometry": {"coordinates":[-119.9333,38.5833],"type":"Point"}
}