{
  "id": 2316195,
  "type": "Feature",
  "properties": {
    "tgn:hierarchy":[
        "tgn:2316195",
        "tgn:1000001",
        "tgn:7012149",
        "tgn:1002746",
        "tgn:7007568",
        "tgn:7029392"
    ],
    "tgn:id":2316195,
    "tgn:name":"Elmcrest",
    "tgn:placetype":[
        "aat:300008347"
    ]
},
  "bbox": [],
  "geometry": {"coordinates":[-76.2333,43.1167],"type":"Point"}
}