{
  "id": 2466633,
  "type": "Feature",
  "properties": {
    "tgn:hierarchy":[
        "tgn:2466633",
        "tgn:1000001",
        "tgn:7012149",
        "tgn:2001532",
        "tgn:7007709",
        "tgn:7029392"
    ],
    "tgn:id":2466633,
    "tgn:name":"Long Branch",
    "tgn:placetype":[
        "aat:300008699"
    ]
},
  "bbox": [],
  "geometry": {"coordinates":[-79.8167,35.7333],"type":"Point"}
}