<<<<<<< HEAD
{
  "id": 7376677,
  "type": "Feature",
  "properties": {
    "tgn:hierarchy":[
        "tgn:7376677",
        "tgn:7005581",
        "tgn:1000001",
        "tgn:7005560",
        "tgn:7029392"
    ],
    "tgn:id":7376677,
    "tgn:name":"Lo de Ru\u00edz",
    "tgn:placetype":[
        "aat:300008347"
    ]
},
  "bbox": [],
  "geometry": {"coordinates":[-107.3,30.416667],"type":"Point"}
}
=======
{"geometry":{"type":"Point","coordinates":[-107.300000,30.416667]},"type":"Feature","properties":{"hierarchy":["tgn:7376677","tgn:7005581","tgn:1000001","tgn:7005560","tgn:7029392"],"placetype":["aat:300008347"],"id":7376677,"name:xx":"Lo de Ru\u00edz"}}
>>>>>>> 03f74aca74312dbeaf24d7e61306dd6a786dc3d0
