{
  "id": 2033718,
  "type": "Feature",
  "properties": {
    "tgn:hierarchy":[
        "tgn:2033718",
        "tgn:1000001",
        "tgn:7012149",
        "tgn:1002561",
        "tgn:7007252",
        "tgn:7029392"
    ],
    "tgn:id":2033718,
    "tgn:name":"South Center",
    "tgn:placetype":[
        "aat:300008347"
    ]
},
  "bbox": [],
  "geometry": {"coordinates":[-86.6333,41.4667],"type":"Point"}
}