{
  "id": 2734818,
  "type": "Feature",
  "properties": {
    "tgn:hierarchy":[
        "tgn:2734818",
        "tgn:1000001",
        "tgn:7012149",
        "tgn:2001880",
        "tgn:7007825",
        "tgn:7029392"
    ],
    "tgn:id":2734818,
    "tgn:name":"Twelve Corners Hollow",
    "tgn:placetype":[
        "aat:300008761"
    ]
},
  "bbox": [],
  "geometry": {"coordinates":[-85.5167,36.25],"type":"Point"}
}