{
  "id": 2078079,
  "type": "Feature",
  "properties": {
    "tgn:hierarchy":[
        "tgn:2078079",
        "tgn:1000001",
        "tgn:2001581",
        "tgn:7012149",
        "tgn:7007705",
        "tgn:7029392"
    ],
    "tgn:id":2078079,
    "tgn:name":"Velva",
    "tgn:placetype":[
        "aat:300008347"
    ]
},
  "bbox": [],
  "geometry": {"coordinates":[-100.9167,48.05],"type":"Point"}
}