{
  "id": 1023657,
  "type": "Feature",
  "properties": {
    "tgn:hierarchy":[
        "tgn:1023657",
        "tgn:1001705",
        "tgn:1000049",
        "tgn:1000002",
        "tgn:7029392"
    ],
    "tgn:id":1023657,
    "tgn:name":"Talca",
    "tgn:placetype":[
        "aat:300008347",
        "aat:300008389",
        "aat:300387220",
        "aat:300387270"
    ]
},
  "bbox": [],
  "geometry": {"coordinates":[-71.666667,-35.433333],"type":"Point"}
}