{
  "id": 1119324,
  "type": "Feature",
  "properties": {
    "tgn:hierarchy":[
        "tgn:1119324",
        "tgn:1000001",
        "tgn:1002359",
        "tgn:7012149",
        "tgn:7007517",
        "tgn:7029392"
    ],
    "tgn:id":1119324,
    "tgn:name":"Stearns Pond",
    "tgn:placetype":[
        "aat:300008688"
    ]
},
  "bbox": [],
  "geometry": {"coordinates":[-71.0667,42.6167],"type":"Point"}
}