{
  "id": 2187988,
  "type": "Feature",
  "properties": {
    "tgn:hierarchy":[
        "tgn:2187988",
        "tgn:1000001",
        "tgn:7012149",
        "tgn:7014510",
        "tgn:7007920",
        "tgn:7029392"
    ],
    "tgn:id":2187988,
    "tgn:name":"Borealis Glacier",
    "tgn:placetype":[
        "aat:300008835"
    ]
},
  "bbox": [],
  "geometry": {"coordinates":[-121.0667,48.5833],"type":"Point"}
}