{
  "id": 7537568,
  "type": "Feature",
  "properties": {
    "tgn:hierarchy":[
        "tgn:7537568",
        "tgn:7001242",
        "tgn:7016833",
        "tgn:7029392"
    ],
    "tgn:id":7537568,
    "tgn:name:en":"N\u00e2sh\u00e2t el-Kheima, W\u00e2di",
    "tgn:placetype":[
        "aat:300379998"
    ]
},
  "bbox": [],
  "geometry": {"coordinates":[31.824785,29.03597],"type":"Point"}
}