{
  "id": 2610371,
  "type": "Feature",
  "properties": {
    "tgn:hierarchy":[
        "tgn:2610371",
        "tgn:1000001",
        "tgn:7012149",
        "tgn:2002371",
        "tgn:7007923",
        "tgn:7029392"
    ],
    "tgn:id":2610371,
    "tgn:name":"Red Butte",
    "tgn:placetype":[
        "aat:300008798"
    ]
},
  "bbox": [],
  "geometry": {"coordinates":[-108.85,42.8333],"type":"Point"}
}