{
  "id": 2062048,
  "type": "Feature",
  "properties": {
    "tgn:hierarchy":[
        "tgn:2062048",
        "tgn:1000001",
        "tgn:2001332",
        "tgn:7012149",
        "tgn:7007525",
        "tgn:7029392"
    ],
    "tgn:id":2062048,
    "tgn:name":"Colton",
    "tgn:placetype":[
        "aat:300008347",
        "aat:300387210"
    ]
},
  "bbox": [],
  "geometry": {"coordinates":[-102.85,41.15],"type":"Point"}
}