{
  "id": 7288341,
  "type": "Feature",
  "properties": {
    "tgn:hierarchy":[
        "tgn:7288341",
        "tgn:1001702",
        "tgn:1000049",
        "tgn:1000002",
        "tgn:7029392"
    ],
    "tgn:id":7288341,
    "tgn:name":"Jofr\u00e9, Punta",
    "tgn:placetype":[
        "aat:300386846"
    ]
},
  "bbox": [],
  "geometry": {"coordinates":[-72.25,-53.15],"type":"Point"}
}