{
  "id": 7466790,
  "type": "Feature",
  "properties": {
    "tgn:hierarchy":[
        "tgn:7466790",
        "tgn:7002445",
        "tgn:1000003",
        "tgn:7008166",
        "tgn:7008591",
        "tgn:7029392"
    ],
    "tgn:id":7466790,
    "tgn:name:en":"Bishopdale",
    "tgn:placetype":[
        "aat:300008761"
    ]
},
  "bbox": [],
  "geometry": {"coordinates":[-2.016667,54.25],"type":"Point"}
}