{
  "id": 7516798,
  "type": "Feature",
  "properties": {
    "tgn:hierarchy":[
        "tgn:7516798",
        "tgn:1008380",
        "tgn:7000507",
        "tgn:1000226",
        "tgn:1000006",
        "tgn:7029392"
    ],
    "tgn:id":7516798,
    "tgn:name:en":"Kumetewhiwhia",
    "tgn:placetype":[
        "aat:300008795"
    ]
},
  "bbox": [],
  "geometry": {"coordinates":[173.45,-35.216667],"type":"Point"}
}