{
  "id": 2546528,
  "type": "Feature",
  "properties": {
    "tgn:hierarchy":[
        "tgn:2546528",
        "tgn:1000001",
        "tgn:7012149",
        "tgn:2001274",
        "tgn:7007524",
        "tgn:7029392"
    ],
    "tgn:id":2546528,
    "tgn:name":"North Fork Kintla Creek",
    "tgn:placetype":[
        "aat:300008706"
    ]
},
  "bbox": [],
  "geometry": {"coordinates":[-114.1333,48.9833],"type":"Point"}
}