<<<<<<< HEAD
{
  "id": 7021500,
  "type": "Feature",
  "properties": {
    "tgn:hierarchy":[
        "tgn:7021500",
        "tgn:7002659",
        "tgn:1000001",
        "tgn:7012149",
        "tgn:2000059",
        "tgn:7029392"
    ],
    "tgn:id":7021500,
    "tgn:name":"Barns Pond",
    "tgn:placetype":[
        "aat:300006191"
    ]
},
  "bbox": [],
  "geometry": {"coordinates":[-88.2333,32.85],"type":"Point"}
}
=======
{"geometry":{"type":"Point","coordinates":[-88.233300,32.850000]},"type":"Feature","properties":{"hierarchy":["tgn:7021500","tgn:7002659","tgn:1000001","tgn:7012149","tgn:2000059","tgn:7029392"],"placetype":["aat:300006191"],"id":7021500,"name:xx":"Barns Pond"}}
>>>>>>> 03f74aca74312dbeaf24d7e61306dd6a786dc3d0
