{
  "id": 7533618,
  "type": "Feature",
  "properties": {
    "tgn:hierarchy":[
        "tgn:7533618",
        "tgn:7001242",
        "tgn:7016833",
        "tgn:7001334",
        "tgn:7029392"
    ],
    "tgn:id":7533618,
    "tgn:name:en":"Jarmash\u012bn, 'Ayn",
    "tgn:placetype":[
        "aat:300008697"
    ]
},
  "bbox": [],
  "geometry": {"coordinates":[30.553776,25.043131],"type":"Point"}
}