{
  "id": 7197410,
  "type": "Feature",
  "properties": {
    "tgn:hierarchy":[
        "tgn:7197410",
        "tgn:1000003",
        "tgn:7003684",
        "tgn:7000084",
        "tgn:7029392"
    ],
    "tgn:id":7197410,
    "tgn:name":"Diersdorferhof",
    "tgn:placetype":[
        "aat:300000206"
    ]
},
  "bbox": [],
  "geometry": {"coordinates":[6.583333,49.383333],"type":"Point"}
}