{
  "id": 7269010,
  "type": "Feature",
  "properties": {
    "tgn:concordances":{
        "gn:id":"2749828"
    },
    "tgn:hierarchy":[
        "tgn:7269010",
        "tgn:1000003",
        "tgn:7006951",
        "tgn:7016845",
        "tgn:7029392"
    ],
    "tgn:id":7269010,
    "tgn:name:nl":"Noord-Spierdijk",
    "tgn:placetype":[
        "aat:300008347"
    ]
},
  "bbox": [],
  "geometry": {"coordinates":[4.95,52.666667],"type":"Point"}
}