{
  "id": 2722175,
  "type": "Feature",
  "properties": {
    "tgn:hierarchy":[
        "tgn:2722175",
        "tgn:1000001",
        "tgn:7012149",
        "tgn:1002917",
        "tgn:7007706",
        "tgn:7029392"
    ],
    "tgn:id":2722175,
    "tgn:name":"Timken Lake",
    "tgn:placetype":[
        "aat:300006191"
    ]
},
  "bbox": [],
  "geometry": {"coordinates":[-81.4833,40.8333],"type":"Point"}
}