{
  "id": 2600178,
  "type": "Feature",
  "properties": {
    "tgn:hierarchy":[
        "tgn:2600178",
        "tgn:1007657",
        "tgn:1002534",
        "tgn:1000001",
        "tgn:7012149",
        "tgn:7007249",
        "tgn:7029392"
    ],
    "tgn:id":2600178,
    "tgn:name":"Puakukui Stream",
    "tgn:placetype":[
        "aat:300008699"
    ]
},
  "bbox": [],
  "geometry": {"coordinates":[-159.4333,21.95],"type":"Point"}
}