{
  "id": 7495666,
  "type": "Feature",
  "properties": {
    "tgn:hierarchy":[
        "tgn:7495666",
        "tgn:7001010",
        "tgn:1000004",
        "tgn:1000141",
        "tgn:7029392"
    ],
    "tgn:id":7495666,
    "tgn:name":"Dayanshi",
    "tgn:placetype":[
        "aat:300008347"
    ]
},
  "bbox": [],
  "geometry": {"coordinates":[121.491143,23.43392],"type":"Point"}
}