<<<<<<< HEAD
{
  "id": 7355041,
  "type": "Feature",
  "properties": {
    "tgn:hierarchy":[
        "tgn:7355041",
        "tgn:1000001",
        "tgn:1001893",
        "tgn:7005560",
        "tgn:7029392"
    ],
    "tgn:id":7355041,
    "tgn:name":"Canoa Wash",
    "tgn:placetype":[
        "aat:300266554",
        "aat:300008699"
    ]
},
  "bbox": [],
  "geometry": {"coordinates":[-111.5,31.45],"type":"Point"}
}
=======
{"geometry":{"type":"Point","coordinates":[-111.500000,31.450000]},"type":"Feature","properties":{"hierarchy":["tgn:7355041","tgn:1000001","tgn:1001893","tgn:7005560","tgn:7029392"],"placetype":["aat:300266554","aat:300008699"],"id":7355041,"name:xx":"Canoa Wash"}}
>>>>>>> 03f74aca74312dbeaf24d7e61306dd6a786dc3d0
