{
  "id": 7020857,
  "type": "Feature",
  "properties": {
    "tgn:hierarchy":[
        "tgn:7020857",
        "tgn:1000001",
        "tgn:7012149",
        "tgn:7029392"
    ],
    "tgn:id":7020857,
    "tgn:name":"Lawson Gant Lot",
    "tgn:placetype":[
        "aat:300008798",
        "aat:300266640"
    ]
},
  "bbox": [],
  "geometry": {"coordinates":[-83.7833,35.5333],"type":"Point"}
}