{
  "id": 7539624,
  "type": "Feature",
  "properties": {
    "tgn:hierarchy":[
        "tgn:7539624",
        "tgn:7001242",
        "tgn:7016833",
        "tgn:7001336",
        "tgn:7029392"
    ],
    "tgn:id":7539624,
    "tgn:name":"Nafas, W\u0101d\u012b an",
    "tgn:placetype":[
        "aat:300379998"
    ]
},
  "bbox": [],
  "geometry": {"coordinates":[33.992222,29.558611],"type":"Point"}
}