{
  "id": 2304702,
  "type": "Feature",
  "properties": {
    "tgn:hierarchy":[
        "tgn:2304702",
        "tgn:1000001",
        "tgn:7012149",
        "tgn:7007707",
        "tgn:7029392"
    ],
    "tgn:id":2304702,
    "tgn:name":"East Bills Creek",
    "tgn:placetype":[
        "aat:300008706"
    ]
},
  "bbox": [],
  "geometry": {"coordinates":[-98.1167,34.95],"type":"Point"}
}