{
  "id": 7289157,
  "type": "Feature",
  "properties": {
    "tgn:hierarchy":[
        "tgn:7289157",
        "tgn:7016598",
        "tgn:1000049",
        "tgn:1000002",
        "tgn:7029392"
    ],
    "tgn:id":7289157,
    "tgn:name":"La Gorra, Cerro",
    "tgn:placetype":[
        "aat:300008795"
    ]
},
  "bbox": [],
  "geometry": {"coordinates":[-69.816667,-25.083333],"type":"Point"}
}