<<<<<<< HEAD
{
  "id": 7477795,
  "type": "Feature",
  "properties": {
    "tgn:hierarchy":[
        "tgn:7477795",
        "tgn:1000004",
        "tgn:7001013",
        "tgn:1000141",
        "tgn:7029392"
    ],
    "tgn:id":7477795,
    "tgn:name":"Tongluo Pi",
    "tgn:placetype":[
        "aat:300008688"
    ]
},
  "bbox": [],
  "geometry": {"coordinates":[121.170556,24.965],"type":"Point"}
}
=======
{"geometry":{"type":"Point","coordinates":[121.170556,24.965000]},"type":"Feature","properties":{"hierarchy":["tgn:7477795","tgn:1000004","tgn:7001013","tgn:1000141","tgn:7029392"],"placetype":["aat:300008688"],"id":7477795,"name:xx":"Tongluo Pi"}}
>>>>>>> 03f74aca74312dbeaf24d7e61306dd6a786dc3d0
