{
  "id": 1070703,
  "type": "Feature",
  "properties": {
    "tgn:hierarchy":[
        "tgn:1070703",
        "tgn:1000004",
        "tgn:7001838",
        "tgn:1000111",
        "tgn:7029392"
    ],
    "tgn:id":1070703,
    "tgn:name":"Niangniangmiao",
    "tgn:placetype":[
        "aat:300008347"
    ]
},
  "bbox": [],
  "geometry": {"coordinates":[118.0833,42.5667],"type":"Point"}
}