{
  "id": 2480448,
  "type": "Feature",
  "properties": {
    "tgn:hierarchy":[
        "tgn:2480448",
        "tgn:1000001",
        "tgn:2001430",
        "tgn:7012149",
        "tgn:7007566",
        "tgn:7029392"
    ],
    "tgn:id":2480448,
    "tgn:name":"Lake Van",
    "tgn:placetype":[
        "aat:300008347"
    ]
},
  "bbox": [],
  "geometry": {"coordinates":[-104.35,33.1833],"type":"Point"}
}