{
  "id": 7501393,
  "type": "Feature",
  "properties": {
    "tgn:hierarchy":[
        "tgn:7501393",
        "tgn:7488858",
        "tgn:1000004",
        "tgn:1000141",
        "tgn:7029392"
    ],
    "tgn:id":7501393,
    "tgn:name":"Pingfeng Qiao",
    "tgn:placetype":[
        "aat:300007836"
    ]
},
  "bbox": [],
  "geometry": {"coordinates":[120.774167,23.728056],"type":"Point"}
}