<<<<<<< HEAD
{
  "id": 2159603,
  "type": "Feature",
  "properties": {
    "tgn:hierarchy":[
        "tgn:2159603",
        "tgn:7002659",
        "tgn:1000001",
        "tgn:7012149",
        "tgn:2000063",
        "tgn:7029392"
    ],
    "tgn:id":2159603,
    "tgn:name":"Bee Shoals",
    "tgn:placetype":[
        "aat:300132348"
    ]
},
  "bbox": [],
  "geometry": {"coordinates":[-87.1333,33.7],"type":"Point"}
}
=======
{"geometry":{"type":"Point","coordinates":[-87.133300,33.700000]},"type":"Feature","properties":{"hierarchy":["tgn:2159603","tgn:7002659","tgn:1000001","tgn:7012149","tgn:2000063","tgn:7029392"],"placetype":["aat:300132348"],"id":2159603,"name:xx":"Bee Shoals"}}
>>>>>>> 03f74aca74312dbeaf24d7e61306dd6a786dc3d0
