{
  "id": 7184284,
  "type": "Feature",
  "properties": {
    "tgn:hierarchy":[
        "tgn:7184284",
        "tgn:1000003",
        "tgn:7003682",
        "tgn:7000084",
        "tgn:7029392"
    ],
    "tgn:id":7184284,
    "tgn:name":"G\u00f6ckel-Berg",
    "tgn:placetype":[
        "aat:300266640"
    ]
},
  "bbox": [],
  "geometry": {"coordinates":[7.883333,49.216667],"type":"Point"}
}