{
  "id": 7011097,
  "type": "Feature",
  "properties": {
    "tgn:hierarchy":[
        "tgn:7011097",
        "tgn:1000882",
        "tgn:1000003",
        "tgn:1000090",
        "tgn:7029392"
    ],
    "tgn:id":7011097,
    "tgn:name":"Torres Vedras",
    "tgn:placetype":[
        "aat:300008347"
    ]
},
  "bbox": [],
  "geometry": {"coordinates":[-9.258,39.091],"type":"Point"}
}