{
  "id": 1084550,
  "type": "Feature",
  "properties": {
    "tgn:hierarchy":[
        "tgn:1084550",
        "tgn:1000004",
        "tgn:1001503",
        "tgn:1000135",
        "tgn:7029392"
    ],
    "tgn:id":1084550,
    "tgn:name":"Pasig",
    "tgn:placetype":[
        "aat:300008347",
        "aat:300387223",
        "aat:300265612",
        "aat:300008375",
        "aat:300387285"
    ]
},
  "bbox": [],
  "geometry": {"coordinates":[121.0667,14.5667],"type":"Point"}
}