{
  "id": 2363278,
  "type": "Feature",
  "properties": {
    "tgn:hierarchy":[
        "tgn:2363278",
        "tgn:1000001",
        "tgn:7012149",
        "tgn:2000926",
        "tgn:7007515",
        "tgn:7029392"
    ],
    "tgn:id":2363278,
    "tgn:name":"Green Brook",
    "tgn:placetype":[
        "aat:300008699"
    ]
},
  "bbox": [],
  "geometry": {"coordinates":[-70.7667,44.1833],"type":"Point"}
}