{
  "id": 2298008,
  "type": "Feature",
  "properties": {
    "tgn:hierarchy":[
        "tgn:2298008",
        "tgn:1000001",
        "tgn:7012149",
        "tgn:2000214",
        "tgn:7007158",
        "tgn:7029392"
    ],
    "tgn:id":2298008,
    "tgn:name":"Dry Lake",
    "tgn:placetype":[
        "aat:300008680"
    ]
},
  "bbox": [],
  "geometry": {"coordinates":[-107.3333,39.6833],"type":"Point"}
}