{
  "id": 7310354,
  "type": "Feature",
  "properties": {
    "tgn:hierarchy":[
        "tgn:7310354",
        "tgn:1001692",
        "tgn:1000049",
        "tgn:1000002",
        "tgn:7029392"
    ],
    "tgn:id":7310354,
    "tgn:name":"O\u00f1oico, Estero",
    "tgn:placetype":[
        "aat:300008699"
    ]
},
  "bbox": [],
  "geometry": {"coordinates":[-73.116667,-38.716667],"type":"Point"}
}