{
  "id": 2140080,
  "type": "Feature",
  "properties": {
    "tgn:hierarchy":[
        "tgn:2140080",
        "tgn:1000001",
        "tgn:7012149",
        "tgn:2000476",
        "tgn:7007250",
        "tgn:7029392"
    ],
    "tgn:id":2140080,
    "tgn:name":"Aubion Creek",
    "tgn:placetype":[
        "aat:300008706"
    ]
},
  "bbox": [],
  "geometry": {"coordinates":[-115.7833,45.6833],"type":"Point"}
}