{
  "id": 1010045,
  "type": "Feature",
  "properties": {
    "tgn:hierarchy":[
        "tgn:1010045",
        "tgn:1000574",
        "tgn:1000002",
        "tgn:1000058",
        "tgn:7029392"
    ],
    "tgn:id":1010045,
    "tgn:name":"Hornos, Islas de",
    "tgn:placetype":[
        "aat:300386853"
    ]
},
  "bbox": [],
  "geometry": {"coordinates":[-57.9167,-34.4167],"type":"Point"}
}