{
  "id": 7234027,
  "type": "Feature",
  "properties": {
    "tgn:hierarchy":[
        "tgn:7234027",
        "tgn:7002681",
        "tgn:7001395",
        "tgn:1000003",
        "tgn:1000074",
        "tgn:7029392"
    ],
    "tgn:id":7234027,
    "tgn:name":"Avl\u00e1ki, \u00d3rmos",
    "tgn:placetype":[
        "aat:300132316"
    ]
},
  "bbox": [],
  "geometry": {"coordinates":[24.083333,37.783333],"type":"Point"}
}