{
  "id": 7342395,
  "type": "Feature",
  "properties": {
    "tgn:hierarchy":[
        "tgn:7342395",
        "tgn:7002831",
        "tgn:1000003",
        "tgn:7002786",
        "tgn:1000095",
        "tgn:7029392"
    ],
    "tgn:id":7342395,
    "tgn:name":"Carrajo",
    "tgn:placetype":[
        "aat:300008347"
    ]
},
  "bbox": [],
  "geometry": {"coordinates":[-7.533333,42.083333],"type":"Point"}
}