{
  "id": 7572767,
  "type": "Feature",
  "properties": {
    "tgn:hierarchy":[
        "tgn:7572767",
        "tgn:1001828",
        "tgn:1000004",
        "tgn:7000198",
        "tgn:7029392"
    ],
    "tgn:id":7572767,
    "tgn:name:en":"Griddal\u016bru",
    "tgn:placetype":[
        "aat:300008347"
    ]
},
  "bbox": [],
  "geometry": {"coordinates":[79.783333,14.266667],"type":"Point"}
}