{
  "id": 2770489,
  "type": "Feature",
  "properties": {
    "tgn:hierarchy":[
        "tgn:2770489",
        "tgn:1000001",
        "tgn:7012149",
        "tgn:7007157",
        "tgn:1002858",
        "tgn:7029392"
    ],
    "tgn:id":2770489,
    "tgn:name":"Wild Mans Canyon",
    "tgn:placetype":[
        "aat:300008761"
    ]
},
  "bbox": [],
  "geometry": {"coordinates":[-116.9667,32.65],"type":"Point"}
}