<<<<<<< HEAD
{
  "id": 7179171,
  "type": "Feature",
  "properties": {
    "tgn:hierarchy":[
        "tgn:7179171",
        "tgn:7003669",
        "tgn:1000003",
        "tgn:7000084",
        "tgn:7029392"
    ],
    "tgn:id":7179171,
    "tgn:name":"Haidberg",
    "tgn:placetype":[
        "aat:300000206"
    ]
},
  "bbox": [],
  "geometry": {"coordinates":[11.716667,48.433333],"type":"Point"}
}
=======
{"geometry":{"type":"Point","coordinates":[11.716667,48.433333]},"type":"Feature","properties":{"hierarchy":["tgn:7179171","tgn:7003669","tgn:1000003","tgn:7000084","tgn:7029392"],"placetype":["aat:300000206"],"id":7179171,"name:xx":"Haidberg"}}
>>>>>>> 03f74aca74312dbeaf24d7e61306dd6a786dc3d0
