<<<<<<< HEAD
{
  "id": 7474045,
  "type": "Feature",
  "properties": {
    "tgn:hierarchy":[
        "tgn:7474045",
        "tgn:1000004",
        "tgn:7001009",
        "tgn:1000141",
        "tgn:7029392"
    ],
    "tgn:id":7474045,
    "tgn:name":"Mingjian Shan",
    "tgn:placetype":[
        "aat:300008798"
    ]
},
  "bbox": [],
  "geometry": {"coordinates":[121.271944,24.388889],"type":"Point"}
}
=======
{"geometry":{"type":"Point","coordinates":[121.271944,24.388889]},"type":"Feature","properties":{"hierarchy":["tgn:7474045","tgn:1000004","tgn:7001009","tgn:1000141","tgn:7029392"],"placetype":["aat:300008798"],"id":7474045,"name:xx":"Mingjian Shan"}}
>>>>>>> 03f74aca74312dbeaf24d7e61306dd6a786dc3d0
