{
  "id": 2533350,
  "type": "Feature",
  "properties": {
    "tgn:hierarchy":[
        "tgn:2533350",
        "tgn:1000001",
        "tgn:7012149",
        "tgn:2002371",
        "tgn:7007923",
        "tgn:7029392"
    ],
    "tgn:id":2533350,
    "tgn:name":"Muskrat Basin",
    "tgn:placetype":[
        "aat:300386845"
    ]
},
  "bbox": [],
  "geometry": {"coordinates":[-107.7833,42.6667],"type":"Point"}
}