{
  "id": 7299863,
  "type": "Feature",
  "properties": {
    "tgn:hierarchy":[
        "tgn:7299863",
        "tgn:7002835",
        "tgn:7001158",
        "tgn:1000003",
        "tgn:1000095",
        "tgn:7029392"
    ],
    "tgn:id":7299863,
    "tgn:name":"Valdemoro, Arroyo",
    "tgn:placetype":[
        "aat:300266554",
        "aat:300008699"
    ]
},
  "bbox": [],
  "geometry": {"coordinates":[-6.05,40.85],"type":"Point"}
}