{
  "id": 7310894,
  "type": "Feature",
  "properties": {
    "tgn:hierarchy":[
        "tgn:7310894",
        "tgn:1001702",
        "tgn:1000049",
        "tgn:1000002",
        "tgn:7029392"
    ],
    "tgn:id":7310894,
    "tgn:name":"Negro, Islote",
    "tgn:placetype":[
        "aat:300008791"
    ]
},
  "bbox": [],
  "geometry": {"coordinates":[-74.633333,-51.483333],"type":"Point"}
}