{
  "id": 2576170,
  "type": "Feature",
  "properties": {
    "tgn:hierarchy":[
        "tgn:2576170",
        "tgn:1000001",
        "tgn:7012149",
        "tgn:1002576",
        "tgn:7007520",
        "tgn:7029392"
    ],
    "tgn:id":2576170,
    "tgn:name":"Pero Lake",
    "tgn:placetype":[
        "aat:300008680"
    ]
},
  "bbox": [],
  "geometry": {"coordinates":[-83.4167,43.0833],"type":"Point"}
}