{
  "id": 2706049,
  "type": "Feature",
  "properties": {
    "tgn:hierarchy":[
        "tgn:2706049",
        "tgn:1000001",
        "tgn:7012149",
        "tgn:2002377",
        "tgn:7007923",
        "tgn:7029392"
    ],
    "tgn:id":2706049,
    "tgn:name":"Swaim Place",
    "tgn:placetype":[
        "aat:300008347"
    ]
},
  "bbox": [],
  "geometry": {"coordinates":[-107.3667,43.3333],"type":"Point"}
}