<<<<<<< HEAD
{
  "id": 7350914,
  "type": "Feature",
  "properties": {
    "tgn:hierarchy":[
        "tgn:7350914",
        "tgn:7005586",
        "tgn:1000001",
        "tgn:7005560",
        "tgn:7029392"
    ],
    "tgn:id":7350914,
    "tgn:name":"Boca, Punta la",
    "tgn:placetype":[
        "aat:300386846"
    ]
},
  "bbox": [],
  "geometry": {"coordinates":[-105.4,20.5],"type":"Point"}
}
=======
{"geometry":{"type":"Point","coordinates":[-105.400000,20.500000]},"type":"Feature","properties":{"hierarchy":["tgn:7350914","tgn:7005586","tgn:1000001","tgn:7005560","tgn:7029392"],"placetype":["aat:300386846"],"id":7350914,"name:xx":"Boca, Punta la"}}
>>>>>>> 03f74aca74312dbeaf24d7e61306dd6a786dc3d0
