{
  "id": 7410956,
  "type": "Feature",
  "properties": {
    "tgn:hierarchy":[
        "tgn:7410956",
        "tgn:1000001",
        "tgn:7005596",
        "tgn:7005560",
        "tgn:7029392"
    ],
    "tgn:id":7410956,
    "tgn:name:es":"El Avispero Segunda Secci\u00f3n",
    "tgn:placetype":[
        "aat:300008347"
    ]
},
  "bbox": [],
  "geometry": {"coordinates":[-91.775,17.758333],"type":"Point"}
}