{
  "id": 7361935,
  "type": "Feature",
  "properties": {
    "tgn:hierarchy":[
        "tgn:7361935",
        "tgn:1000001",
        "tgn:7005590",
        "tgn:7005560",
        "tgn:7029392"
    ],
    "tgn:id":7361935,
    "tgn:name":"El Cu\u00e9ramo",
    "tgn:placetype":[
        "aat:300008347"
    ]
},
  "bbox": [],
  "geometry": {"coordinates":[-100.766667,18.433333],"type":"Point"}
}