{
  "id": 7525613,
  "type": "Feature",
  "properties": {
    "tgn:hierarchy":[
        "tgn:7525613",
        "tgn:7001242",
        "tgn:7016833",
        "tgn:7029392"
    ],
    "tgn:id":7525613,
    "tgn:name:en":"Dandana",
    "tgn:placetype":[
        "aat:300008697"
    ]
},
  "bbox": [],
  "geometry": {"coordinates":[31.762994,29.371226],"type":"Point"}
}