{
  "id": 2431997,
  "type": "Feature",
  "properties": {
    "tgn:hierarchy":[
        "tgn:2431997",
        "tgn:7006450",
        "tgn:1000001",
        "tgn:7012149",
        "tgn:2124014",
        "tgn:7029392"
    ],
    "tgn:id":2431997,
    "tgn:name":"Kavachurak Creek",
    "tgn:placetype":[
        "aat:300008706"
    ]
},
  "bbox": [],
  "geometry": {"coordinates":[-156.7333,67.6333],"type":"Point"}
}