{
  "id": 2712919,
  "type": "Feature",
  "properties": {
    "tgn:hierarchy":[
        "tgn:2712919",
        "tgn:1000001",
        "tgn:2000273",
        "tgn:7012149",
        "tgn:7007240",
        "tgn:7029392"
    ],
    "tgn:id":2712919,
    "tgn:name":"Taylor Hole",
    "tgn:placetype":[
        "aat:300132316"
    ]
},
  "bbox": [],
  "geometry": {"coordinates":[-85.25,30.7333],"type":"Point"}
}