{
  "id": 2401570,
  "type": "Feature",
  "properties": {
    "tgn:hierarchy":[
        "tgn:2401570",
        "tgn:1000001",
        "tgn:7012149",
        "tgn:2001459",
        "tgn:7007566",
        "tgn:7029392"
    ],
    "tgn:id":2401570,
    "tgn:name":"Horseshoe Draw",
    "tgn:placetype":[
        "aat:300008761"
    ]
},
  "bbox": [],
  "geometry": {"coordinates":[-103.5333,36.9667],"type":"Point"}
}