{
  "id": 2171418,
  "type": "Feature",
  "properties": {
    "tgn:hierarchy":[
        "tgn:2171418",
        "tgn:1000001",
        "tgn:7012149",
        "tgn:7007157",
        "tgn:1002608",
        "tgn:1008999",
        "tgn:7029392"
    ],
    "tgn:id":2171418,
    "tgn:name":"Big Springs Reservoir",
    "tgn:placetype":[
        "aat:300006191"
    ]
},
  "bbox": [],
  "geometry": {"coordinates":[-118.45,33.4333],"type":"Point"}
}