{
  "id": 1059080,
  "type": "Feature",
  "properties": {
    "tgn:hierarchy":[
        "tgn:1059080",
        "tgn:1000004",
        "tgn:7011572",
        "tgn:7018214",
        "tgn:7002435",
        "tgn:7029392"
    ],
    "tgn:id":1059080,
    "tgn:name":"Syas'stroy",
    "tgn:placetype":[
        "aat:300008347"
    ]
},
  "bbox": [],
  "geometry": {"coordinates":[32.5667,60.1333],"type":"Point"}
}