{
  "id": 7339536,
  "type": "Feature",
  "properties": {
    "tgn:hierarchy":[
        "tgn:7339536",
        "tgn:7001158",
        "tgn:7002850",
        "tgn:1000003",
        "tgn:1000095",
        "tgn:7029392"
    ],
    "tgn:id":7339536,
    "tgn:name":"Cozcurrita",
    "tgn:placetype":[
        "aat:300008347"
    ]
},
  "bbox": [],
  "geometry": {"coordinates":[-6.266667,41.433333],"type":"Point"}
}