{
  "id": 7552933,
  "type": "Feature",
  "properties": {
    "tgn:hierarchy":[
        "tgn:7552933",
        "tgn:1000004",
        "tgn:7000198",
        "tgn:7016722",
        "tgn:7029392"
    ],
    "tgn:id":7552933,
    "tgn:name:en":"Muhammadpur",
    "tgn:placetype":[
        "aat:300008347"
    ]
},
  "bbox": [],
  "geometry": {"coordinates":[80.05,27.916667],"type":"Point"}
}