{
  "id": 7074037,
  "type": "Feature",
  "properties": {
    "tgn:hierarchy":[
        "tgn:7074037",
        "tgn:7003692",
        "tgn:1000003",
        "tgn:7000084",
        "tgn:7029392"
    ],
    "tgn:id":7074037,
    "tgn:name":"Talbach",
    "tgn:placetype":[
        "aat:300008699"
    ]
},
  "bbox": [],
  "geometry": {"coordinates":[8.766667,47.833333],"type":"Point"}
}