<<<<<<< HEAD
{
  "id": 7376827,
  "type": "Feature",
  "properties": {
    "tgn:hierarchy":[
        "tgn:7376827",
        "tgn:1000001",
        "tgn:7005597",
        "tgn:7005560",
        "tgn:7029392"
    ],
    "tgn:id":7376827,
    "tgn:name":"La Parida",
    "tgn:placetype":[
        "aat:300266554",
        "aat:300008699"
    ]
},
  "bbox": [],
  "geometry": {"coordinates":[-99.866667,23.333333],"type":"Point"}
}
=======
{"geometry":{"type":"Point","coordinates":[-99.866667,23.333333]},"type":"Feature","properties":{"hierarchy":["tgn:7376827","tgn:1000001","tgn:7005597","tgn:7005560","tgn:7029392"],"placetype":["aat:300266554","aat:300008699"],"id":7376827,"name:xx":"La Parida"}}
>>>>>>> 03f74aca74312dbeaf24d7e61306dd6a786dc3d0
