{
  "id": 7275828,
  "type": "Feature",
  "properties": {
    "tgn:hierarchy":[
        "tgn:7275828",
        "tgn:1001657",
        "tgn:1000049",
        "tgn:1000002",
        "tgn:7029392"
    ],
    "tgn:id":7275828,
    "tgn:name":"Totoralillo, Ensenada",
    "tgn:placetype":[
        "aat:300132317"
    ]
},
  "bbox": [],
  "geometry": {"coordinates":[-71.524167,-32.020833],"type":"Point"}
}