{
  "id": 2257442,
  "type": "Feature",
  "properties": {
    "tgn:hierarchy":[
        "tgn:2257442",
        "tgn:1000001",
        "tgn:7012149",
        "tgn:2001279",
        "tgn:7007524",
        "tgn:7029392"
    ],
    "tgn:id":2257442,
    "tgn:name":"Corona Gulch",
    "tgn:placetype":[
        "aat:300008761"
    ]
},
  "bbox": [],
  "geometry": {"coordinates":[-113.5667,46.6333],"type":"Point"}
}