<<<<<<< HEAD
{
  "id": 2257442,
  "type": "Feature",
  "properties": {
    "tgn:hierarchy":[
        "tgn:2257442",
        "tgn:1000001",
        "tgn:7012149",
        "tgn:2001279",
        "tgn:7007524",
        "tgn:7029392"
    ],
    "tgn:id":2257442,
    "tgn:name":"Corona Gulch",
    "tgn:placetype":[
        "aat:300008761"
    ]
},
  "bbox": [],
  "geometry": {"coordinates":[-113.5667,46.6333],"type":"Point"}
}
=======
{"geometry":{"type":"Point","coordinates":[-113.566700,46.633300]},"type":"Feature","properties":{"hierarchy":["tgn:2257442","tgn:1000001","tgn:7012149","tgn:2001279","tgn:7007524","tgn:7029392"],"placetype":["aat:300008761"],"id":2257442,"name:xx":"Corona Gulch"}}
>>>>>>> 03f74aca74312dbeaf24d7e61306dd6a786dc3d0
