{
  "id": 7448756,
  "type": "Feature",
  "properties": {
    "tgn:hierarchy":[
        "tgn:7448756",
        "tgn:7019049",
        "tgn:7002445",
        "tgn:1000003",
        "tgn:7029505",
        "tgn:7008591",
        "tgn:7029392"
    ],
    "tgn:id":7448756,
    "tgn:name:en":"Rotherham Road",
    "tgn:placetype":[
        "aat:300007783"
    ]
},
  "bbox": [],
  "geometry": {"coordinates":[-1.35,53.433333],"type":"Point"}
}