{
  "id": 2775147,
  "type": "Feature",
  "properties": {
    "tgn:hierarchy":[
        "tgn:2775147",
        "tgn:1000001",
        "tgn:7012149",
        "tgn:1002472",
        "tgn:7007568",
        "tgn:7029392"
    ],
    "tgn:id":2775147,
    "tgn:name":"Willys Lake",
    "tgn:placetype":[
        "aat:300008680"
    ]
},
  "bbox": [],
  "geometry": {"coordinates":[-74.95,43.9667],"type":"Point"}
}