{
  "id": 2516356,
  "type": "Feature",
  "properties": {
    "tgn:hierarchy":[
        "tgn:2516356",
        "tgn:1002140",
        "tgn:1000001",
        "tgn:7012149",
        "tgn:7007520",
        "tgn:7029392"
    ],
    "tgn:id":2516356,
    "tgn:name":"Miner Creek",
    "tgn:placetype":[
        "aat:300008706"
    ]
},
  "bbox": [],
  "geometry": {"coordinates":[-85.7833,42.55],"type":"Point"}
}