{
  "id": 7583452,
  "type": "Feature",
  "properties": {
    "tgn:hierarchy":[
        "tgn:7583452",
        "tgn:1000004",
        "tgn:7000198",
        "tgn:1001894",
        "tgn:7029392"
    ],
    "tgn:id":7583452,
    "tgn:name:en":"Chorasgarh",
    "tgn:placetype":[
        "aat:300008057"
    ]
},
  "bbox": [],
  "geometry": {"coordinates":[75.602941,24.644076],"type":"Point"}
}