<<<<<<< HEAD
{
  "id": 2152126,
  "type": "Feature",
  "properties": {
    "tgn:hierarchy":[
        "tgn:2152126",
        "tgn:1000001",
        "tgn:7012149",
        "tgn:2001872",
        "tgn:7007825",
        "tgn:7029392"
    ],
    "tgn:id":2152126,
    "tgn:name":"Baxter Hollow",
    "tgn:placetype":[
        "aat:300008761"
    ]
},
  "bbox": [],
  "geometry": {"coordinates":[-88.1,35.2667],"type":"Point"}
}
=======
{"geometry":{"type":"Point","coordinates":[-88.100000,35.266700]},"type":"Feature","properties":{"hierarchy":["tgn:2152126","tgn:1000001","tgn:7012149","tgn:2001872","tgn:7007825","tgn:7029392"],"placetype":["aat:300008761"],"id":2152126,"name:xx":"Baxter Hollow"}}
>>>>>>> 03f74aca74312dbeaf24d7e61306dd6a786dc3d0
