{
  "id": 7216302,
  "type": "Feature",
  "properties": {
    "tgn:hierarchy":[
        "tgn:7216302",
        "tgn:7003669",
        "tgn:1000003",
        "tgn:7000084",
        "tgn:7029392"
    ],
    "tgn:id":7216302,
    "tgn:name":"Aign",
    "tgn:placetype":[
        "aat:300008347"
    ]
},
  "bbox": [],
  "geometry": {"coordinates":[12.933333,48.983333],"type":"Point"}
}