{
  "id": 7000479,
  "type": "Feature",
  "properties": {
    "tgn:hierarchy":[
        "tgn:7000479",
        "tgn:7003162",
        "tgn:1000003",
        "tgn:7009760",
        "tgn:1000080",
        "tgn:7029392"
    ],
    "tgn:id":7000479,
    "tgn:name":"Monterchi",
    "tgn:placetype":[
        "aat:300008347"
    ]
},
  "bbox": [],
  "geometry": {"coordinates":[12.116667,43.483333],"type":"Point"}
}