{
  "id": 2549926,
  "type": "Feature",
  "properties": {
    "tgn:hierarchy":[
        "tgn:2549926",
        "tgn:1000001",
        "tgn:7012149",
        "tgn:7007826",
        "tgn:7029392"
    ],
    "tgn:id":2549926,
    "tgn:name":"North Valley Prong",
    "tgn:placetype":[
        "aat:300008699"
    ]
},
  "bbox": [],
  "geometry": {"coordinates":[-100.5833,30.8167],"type":"Point"}
}