{
  "id": 7282986,
  "type": "Feature",
  "properties": {
    "tgn:hierarchy":[
        "tgn:7282986",
        "tgn:1001630",
        "tgn:1000049",
        "tgn:1000002",
        "tgn:7029392"
    ],
    "tgn:id":7282986,
    "tgn:name":"Pedernales, Cerro",
    "tgn:placetype":[
        "aat:300008795"
    ]
},
  "bbox": [],
  "geometry": {"coordinates":[-69.283333,-26.416667],"type":"Point"}
}