<<<<<<< HEAD
{
  "id": 7024562,
  "type": "Feature",
  "properties": {
    "tgn:hierarchy":[
        "tgn:7024562",
        "tgn:7593551",
        "tgn:1000001",
        "tgn:7024573",
        "tgn:7029392"
    ],
    "tgn:id":7024562,
    "tgn:name":"Christian, Kap",
    "tgn:placetype":[
        "aat:300008850"
    ]
},
  "bbox": [],
  "geometry": {"coordinates":[-44.1167,59.8],"type":"Point"}
}
=======
{"geometry":{"type":"Point","coordinates":[-44.116700,59.800000]},"type":"Feature","properties":{"hierarchy":["tgn:7024562","tgn:7593551","tgn:1000001","tgn:7024573","tgn:7029392"],"placetype":["aat:300008850"],"id":7024562,"name:xx":"Christian, Kap"}}
>>>>>>> 03f74aca74312dbeaf24d7e61306dd6a786dc3d0
