{
  "id": 7366633,
  "type": "Feature",
  "properties": {
    "tgn:hierarchy":[
        "tgn:7366633",
        "tgn:7005581",
        "tgn:1000001",
        "tgn:7005560",
        "tgn:7029392"
    ],
    "tgn:id":7366633,
    "tgn:name":"El Tordillo, Arroyo",
    "tgn:placetype":[
        "aat:300266554",
        "aat:300008699"
    ]
},
  "bbox": [],
  "geometry": {"coordinates":[-104.916667,29.316667],"type":"Point"}
}