{
  "id": 7462155,
  "type": "Feature",
  "properties": {
    "tgn:hierarchy":[
        "tgn:7462155",
        "tgn:7019094",
        "tgn:7002444",
        "tgn:1000003",
        "tgn:7008591",
        "tgn:7029392"
    ],
    "tgn:id":7462155,
    "tgn:name:en":"Kirn",
    "tgn:placetype":[
        "aat:300008347"
    ]
},
  "bbox": [],
  "geometry": {"coordinates":[-4.916667,55.95],"type":"Point"}
}