{
  "id": 7588388,
  "type": "Feature",
  "properties": {
    "tgn:hierarchy":[
        "tgn:7588388",
        "tgn:1000004",
        "tgn:7000198",
        "tgn:7000799",
        "tgn:7029392"
    ],
    "tgn:id":7588388,
    "tgn:name:en":"Bandi Koma Kil\u0101",
    "tgn:placetype":[
        "aat:300008347"
    ]
},
  "bbox": [],
  "geometry": {"coordinates":[74.215281,33.780601],"type":"Point"}
}