{
  "id": 2524627,
  "type": "Feature",
  "properties": {
    "tgn:hierarchy":[
        "tgn:2524627",
        "tgn:1000001",
        "tgn:7012149",
        "tgn:2001451",
        "tgn:7007566",
        "tgn:7029392"
    ],
    "tgn:id":2524627,
    "tgn:name":"Mormon Canyon",
    "tgn:placetype":[
        "aat:300008761"
    ]
},
  "bbox": [],
  "geometry": {"coordinates":[-106.5833,35.8833],"type":"Point"}
}