{
  "id": 1097219,
  "type": "Feature",
  "properties": {
    "tgn:hierarchy":[
        "tgn:1097219",
        "tgn:7000490",
        "tgn:1000006",
        "tgn:7006238",
        "tgn:7029392"
    ],
    "tgn:id":1097219,
    "tgn:name":"Kaniva",
    "tgn:placetype":[
        "aat:300008347"
    ]
},
  "bbox": [],
  "geometry": {"coordinates":[141.2833,-36.55],"type":"Point"}
}