{
  "id": 2609500,
  "type": "Feature",
  "properties": {
    "tgn:hierarchy":[
        "tgn:2609500",
        "tgn:1000001",
        "tgn:7012149",
        "tgn:1002646",
        "tgn:7007826",
        "tgn:7029392"
    ],
    "tgn:id":2609500,
    "tgn:name":"Raymond Landing Shoal",
    "tgn:placetype":[
        "aat:300132348"
    ]
},
  "bbox": [],
  "geometry": {"coordinates":[-95.8833,28.6667],"type":"Point"}
}