{
  "id": 7472226,
  "type": "Feature",
  "properties": {
    "tgn:hierarchy":[
        "tgn:7472226",
        "tgn:7001010",
        "tgn:1000004",
        "tgn:1000141",
        "tgn:7029392"
    ],
    "tgn:id":7472226,
    "tgn:name":"Aiyu Youzhiyuan",
    "tgn:placetype":[
        "aat:300006495"
    ]
},
  "bbox": [],
  "geometry": {"coordinates":[121.60249,24.002667],"type":"Point"}
}