{
  "id": 2302938,
  "type": "Feature",
  "properties": {
    "tgn:hierarchy":[
        "tgn:2302938",
        "tgn:1000001",
        "tgn:7012149",
        "tgn:2001196",
        "tgn:7007523",
        "tgn:7029392"
    ],
    "tgn:id":2302938,
    "tgn:name":"Dyestone Mountain",
    "tgn:placetype":[
        "aat:300008798"
    ]
},
  "bbox": [],
  "geometry": {"coordinates":[-92.0833,36.95],"type":"Point"}
}