<<<<<<< HEAD
{
  "id": 2150383,
  "type": "Feature",
  "properties": {
    "tgn:hierarchy":[
        "tgn:2150383",
        "tgn:1000001",
        "tgn:7012149",
        "tgn:2001297",
        "tgn:7007524",
        "tgn:7029392"
    ],
    "tgn:id":2150383,
    "tgn:name":"Basin Creek",
    "tgn:placetype":[
        "aat:300008706"
    ]
},
  "bbox": [],
  "geometry": {"coordinates":[-105.7667,45.4333],"type":"Point"}
}
=======
{"geometry":{"type":"Point","coordinates":[-105.766700,45.433300]},"type":"Feature","properties":{"hierarchy":["tgn:2150383","tgn:1000001","tgn:7012149","tgn:2001297","tgn:7007524","tgn:7029392"],"placetype":["aat:300008706"],"id":2150383,"name:xx":"Basin Creek"}}
>>>>>>> 03f74aca74312dbeaf24d7e61306dd6a786dc3d0
