{
  "id": 7482269,
  "type": "Feature",
  "properties": {
    "tgn:hierarchy":[
        "tgn:7482269",
        "tgn:1000004",
        "tgn:7490934",
        "tgn:1000141",
        "tgn:7029392"
    ],
    "tgn:id":7482269,
    "tgn:name":"Longtan Guoxiao",
    "tgn:placetype":[
        "aat:300006495"
    ]
},
  "bbox": [],
  "geometry": {"coordinates":[120.268848,23.032604],"type":"Point"}
}