{
  "id": 2276215,
  "type": "Feature",
  "properties": {
    "tgn:hierarchy":[
        "tgn:2276215",
        "tgn:7006450",
        "tgn:1000001",
        "tgn:7012149",
        "tgn:2000089",
        "tgn:7029392"
    ],
    "tgn:id":2276215,
    "tgn:name":"Dasha Island",
    "tgn:placetype":[
        "aat:300008791"
    ]
},
  "bbox": [],
  "geometry": {"coordinates":[-154.95,64.8833],"type":"Point"}
}