<<<<<<< HEAD
{
  "id": 2336983,
  "type": "Feature",
  "properties": {
    "tgn:hierarchy":[
        "tgn:2336983",
        "tgn:1000001",
        "tgn:7012149",
        "tgn:2002387",
        "tgn:7007923",
        "tgn:7029392"
    ],
    "tgn:id":2336983,
    "tgn:name":"Fourmile Draw",
    "tgn:placetype":[
        "aat:300008761"
    ]
},
  "bbox": [],
  "geometry": {"coordinates":[-104.25,43.8833],"type":"Point"}
}
=======
{"geometry":{"type":"Point","coordinates":[-104.250000,43.883300]},"type":"Feature","properties":{"hierarchy":["tgn:2336983","tgn:1000001","tgn:7012149","tgn:2002387","tgn:7007923","tgn:7029392"],"placetype":["aat:300008761"],"id":2336983,"name:xx":"Fourmile Draw"}}
>>>>>>> 03f74aca74312dbeaf24d7e61306dd6a786dc3d0
