{
  "id": 2218537,
  "type": "Feature",
  "properties": {
    "tgn:hierarchy":[
        "tgn:2218537",
        "tgn:1000001",
        "tgn:7012149",
        "tgn:7029392"
    ],
    "tgn:id":2218537,
    "tgn:name":"Cane Break Canyon",
    "tgn:placetype":[
        "aat:300008761"
    ]
},
  "bbox": [],
  "geometry": {"coordinates":[-114.5667,33.0333],"type":"Point"}
}