{
  "id": 7284329,
  "type": "Feature",
  "properties": {
    "tgn:hierarchy":[
        "tgn:7284329",
        "tgn:1001699",
        "tgn:1000049",
        "tgn:1000002",
        "tgn:7029392"
    ],
    "tgn:id":7284329,
    "tgn:name":"Punta Quill\u00f3n",
    "tgn:placetype":[
        "aat:300386846"
    ]
},
  "bbox": [],
  "geometry": {"coordinates":[-72.728611,-42.210556],"type":"Point"}
}