{
  "id": 2467074,
  "type": "Feature",
  "properties": {
    "tgn:hierarchy":[
        "tgn:2467074",
        "tgn:1000001",
        "tgn:7012149",
        "tgn:7007250",
        "tgn:7029392"
    ],
    "tgn:id":2467074,
    "tgn:name":"Long Creek",
    "tgn:placetype":[
        "aat:300008706"
    ]
},
  "bbox": [],
  "geometry": {"coordinates":[-115.05,46.95],"type":"Point"}
}