{
  "id": 2147436,
  "type": "Feature",
  "properties": {
    "tgn:hierarchy":[
        "tgn:2147436",
        "tgn:1000001",
        "tgn:7012149",
        "tgn:2000985",
        "tgn:7007520",
        "tgn:7029392"
    ],
    "tgn:id":2147436,
    "tgn:name":"Barber Creek",
    "tgn:placetype":[
        "aat:300008706"
    ]
},
  "bbox": [],
  "geometry": {"coordinates":[-84.1333,44.45],"type":"Point"}
}