{
  "id": 2402152,
  "type": "Feature",
  "properties": {
    "tgn:hierarchy":[
        "tgn:2402152",
        "tgn:1000001",
        "tgn:7012149",
        "tgn:1002699",
        "tgn:7007708",
        "tgn:7029392"
    ],
    "tgn:id":2402152,
    "tgn:name":"Horsetail Creek",
    "tgn:placetype":[
        "aat:300008706"
    ]
},
  "bbox": [],
  "geometry": {"coordinates":[-122.0167,45.55],"type":"Point"}
}