<<<<<<< HEAD
{
  "id": 2402152,
  "type": "Feature",
  "properties": {
    "tgn:hierarchy":[
        "tgn:2402152",
        "tgn:1000001",
        "tgn:7012149",
        "tgn:1002699",
        "tgn:7007708",
        "tgn:7029392"
    ],
    "tgn:id":2402152,
    "tgn:name":"Horsetail Creek",
    "tgn:placetype":[
        "aat:300008706"
    ]
},
  "bbox": [],
  "geometry": {"coordinates":[-122.0167,45.55],"type":"Point"}
}
=======
{"geometry":{"type":"Point","coordinates":[-122.016700,45.550000]},"type":"Feature","properties":{"hierarchy":["tgn:2402152","tgn:1000001","tgn:7012149","tgn:1002699","tgn:7007708","tgn:7029392"],"placetype":["aat:300008706"],"id":2402152,"name:xx":"Horsetail Creek"}}
>>>>>>> 03f74aca74312dbeaf24d7e61306dd6a786dc3d0
