{
  "id": 2308950,
  "type": "Feature",
  "properties": {
    "tgn:hierarchy":[
        "tgn:2308950",
        "tgn:1000001",
        "tgn:7012149",
        "tgn:1002578",
        "tgn:7007826",
        "tgn:7029392"
    ],
    "tgn:id":2308950,
    "tgn:name":"East Ragsdale Creek",
    "tgn:placetype":[
        "aat:300008706"
    ]
},
  "bbox": [],
  "geometry": {"coordinates":[-96.7167,29.4667],"type":"Point"}
}