{
  "id": 7399467,
  "type": "Feature",
  "properties": {
    "tgn:hierarchy":[
        "tgn:7399467",
        "tgn:1000001",
        "tgn:7005599",
        "tgn:7005560",
        "tgn:7029392"
    ],
    "tgn:id":7399467,
    "tgn:name":"Pe\u00f1a Blanca",
    "tgn:placetype":[
        "aat:300008347"
    ]
},
  "bbox": [],
  "geometry": {"coordinates":[-94.75,17.641667],"type":"Point"}
}