{
  "id": 2216184,
  "type": "Feature",
  "properties": {
    "tgn:hierarchy":[
        "tgn:2216184",
        "tgn:1000001",
        "tgn:7012149",
        "tgn:2000372",
        "tgn:7007248",
        "tgn:7029392"
    ],
    "tgn:id":2216184,
    "tgn:name":"Camp Branch",
    "tgn:placetype":[
        "aat:300008699"
    ]
},
  "bbox": [],
  "geometry": {"coordinates":[-82.5667,33.05],"type":"Point"}
}