<<<<<<< HEAD
{
  "id": 2158882,
  "type": "Feature",
  "properties": {
    "tgn:hierarchy":[
        "tgn:2158882",
        "tgn:1000001",
        "tgn:7016172",
        "tgn:7012149",
        "tgn:2000155",
        "tgn:7029392"
    ],
    "tgn:id":2158882,
    "tgn:name":"Beckham Creek",
    "tgn:placetype":[
        "aat:300008706"
    ]
},
  "bbox": [],
  "geometry": {"coordinates":[-93.35,35.9667],"type":"Point"}
}
=======
{"geometry":{"type":"Point","coordinates":[-93.350000,35.966700]},"type":"Feature","properties":{"hierarchy":["tgn:2158882","tgn:1000001","tgn:7016172","tgn:7012149","tgn:2000155","tgn:7029392"],"placetype":["aat:300008706"],"id":2158882,"name:xx":"Beckham Creek"}}
>>>>>>> 03f74aca74312dbeaf24d7e61306dd6a786dc3d0
