{
  "id": 2087445,
  "type": "Feature",
  "properties": {
    "tgn:hierarchy":[
        "tgn:2087445",
        "tgn:1000001",
        "tgn:7012149",
        "tgn:1002690",
        "tgn:7007710",
        "tgn:7029392"
    ],
    "tgn:id":2087445,
    "tgn:name":"Congo",
    "tgn:placetype":[
        "aat:300008347"
    ]
},
  "bbox": [],
  "geometry": {"coordinates":[-75.5833,40.35],"type":"Point"}
}