{
  "id": 2519986,
  "type": "Feature",
  "properties": {
    "tgn:hierarchy":[
        "tgn:2519986",
        "tgn:1000001",
        "tgn:7006451",
        "tgn:7012149",
        "tgn:2000100",
        "tgn:7029392"
    ],
    "tgn:id":2519986,
    "tgn:name":"Molino Basin",
    "tgn:placetype":[
        "aat:300386845"
    ]
},
  "bbox": [],
  "geometry": {"coordinates":[-110.6833,32.3333],"type":"Point"}
}