{
  "id": 7381080,
  "type": "Feature",
  "properties": {
    "tgn:hierarchy":[
        "tgn:7381080",
        "tgn:1000001",
        "tgn:7005597",
        "tgn:7005560",
        "tgn:7029392"
    ],
    "tgn:id":7381080,
    "tgn:name":"Loma Prieta, Mesa",
    "tgn:placetype":[
        "aat:300008811"
    ]
},
  "bbox": [],
  "geometry": {"coordinates":[-98.75,23.75],"type":"Point"}
}