{
  "id": 2521017,
  "type": "Feature",
  "properties": {
    "tgn:hierarchy":[
        "tgn:2521017",
        "tgn:1000001",
        "tgn:2002370",
        "tgn:7012149",
        "tgn:7007923",
        "tgn:7029392"
    ],
    "tgn:id":2521017,
    "tgn:name":"Montana Lake",
    "tgn:placetype":[
        "aat:300008680"
    ]
},
  "bbox": [],
  "geometry": {"coordinates":[-104.05,44.5333],"type":"Point"}
}