{
  "id": 2316431,
  "type": "Feature",
  "properties": {
    "tgn:hierarchy":[
        "tgn:2316431",
        "tgn:1000001",
        "tgn:7012149",
        "tgn:2000491",
        "tgn:7007250",
        "tgn:7029392"
    ],
    "tgn:id":2316431,
    "tgn:name":"Elsie Lake",
    "tgn:placetype":[
        "aat:300008680"
    ]
},
  "bbox": [],
  "geometry": {"coordinates":[-116.0167,47.4167],"type":"Point"}
}