{
  "id": 1084364,
  "type": "Feature",
  "properties": {
    "tgn:hierarchy":[
        "tgn:1084364",
        "tgn:1000004",
        "tgn:1001154",
        "tgn:1000135",
        "tgn:7029392"
    ],
    "tgn:id":1084364,
    "tgn:name":"Loay",
    "tgn:placetype":[
        "aat:300008347"
    ]
},
  "bbox": [],
  "geometry": {"coordinates":[124.0333,9.6167],"type":"Point"}
}