{
  "id": 2726790,
  "type": "Feature",
  "properties": {
    "tgn:hierarchy":[
        "tgn:2726790",
        "tgn:1000001",
        "tgn:7012149",
        "tgn:7007158",
        "tgn:2000253",
        "tgn:7029392"
    ],
    "tgn:id":2726790,
    "tgn:name":"Town of Mead Reservoir",
    "tgn:placetype":[
        "aat:300006191"
    ]
},
  "bbox": [],
  "geometry": {"coordinates":[-105.0167,40.2333],"type":"Point"}
}