{
  "id": 1123385,
  "type": "Feature",
  "properties": {
    "tgn:hierarchy":[
        "tgn:1123385",
        "tgn:7006477",
        "tgn:1000002",
        "tgn:7029392"
    ],
    "tgn:id":1123385,
    "tgn:name":"Desaguadero, R\u00edo",
    "tgn:placetype":[
        "aat:300008707"
    ]
},
  "bbox": [],
  "geometry": {"coordinates":[-66.7833,-34.2167],"type":"Point"}
}