{
  "id": 7009213,
  "type": "Feature",
  "properties": {
    "tgn:hierarchy":[
        "tgn:7009213",
        "tgn:1000003",
        "tgn:7002888",
        "tgn:1000070",
        "tgn:7029392"
    ],
    "tgn:id":7009213,
    "tgn:name":"Gondrecourt-le-Ch\u00e2teau",
    "tgn:placetype":[
        "aat:300008347"
    ]
},
  "bbox": [],
  "geometry": {"coordinates":[5.5167,48.5167],"type":"Point"}
}