<<<<<<< HEAD
{
  "id": 7059604,
  "type": "Feature",
  "properties": {
    "tgn:hierarchy":[
        "tgn:7059604",
        "tgn:1000003",
        "tgn:7003677",
        "tgn:7000084",
        "tgn:7029392"
    ],
    "tgn:id":7059604,
    "tgn:name":"Ahlhausen",
    "tgn:placetype":[
        "aat:300000206"
    ]
},
  "bbox": [],
  "geometry": {"coordinates":[7.383333,51.3],"type":"Point"}
}
=======
{"geometry":{"type":"Point","coordinates":[7.383333,51.300000]},"type":"Feature","properties":{"hierarchy":["tgn:7059604","tgn:1000003","tgn:7003677","tgn:7000084","tgn:7029392"],"placetype":["aat:300000206"],"id":7059604,"name:xx":"Ahlhausen"}}
>>>>>>> 03f74aca74312dbeaf24d7e61306dd6a786dc3d0
