<<<<<<< HEAD
{
  "id": 7022421,
  "type": "Feature",
  "properties": {
    "tgn:hierarchy":[
        "tgn:7022421",
        "tgn:1000001",
        "tgn:7012149",
        "tgn:7007248",
        "tgn:7029392"
    ],
    "tgn:id":7022421,
    "tgn:name":"Boneville Pond",
    "tgn:placetype":[
        "aat:300006191"
    ]
},
  "bbox": [],
  "geometry": {"coordinates":[-82.4333,33.4167],"type":"Point"}
}
=======
{"geometry":{"type":"Point","coordinates":[-82.433300,33.416700]},"type":"Feature","properties":{"hierarchy":["tgn:7022421","tgn:1000001","tgn:7012149","tgn:7007248","tgn:7029392"],"placetype":["aat:300006191"],"id":7022421,"name:xx":"Boneville Pond"}}
>>>>>>> 03f74aca74312dbeaf24d7e61306dd6a786dc3d0
