{
  "id": 2255263,
  "type": "Feature",
  "properties": {
    "tgn:hierarchy":[
        "tgn:2255263",
        "tgn:1000001",
        "tgn:7012149",
        "tgn:2000798",
        "tgn:7007255",
        "tgn:7029392"
    ],
    "tgn:id":2255263,
    "tgn:name":"Cooper Spring",
    "tgn:placetype":[
        "aat:300008697"
    ]
},
  "bbox": [],
  "geometry": {"coordinates":[-86.0333,37.1833],"type":"Point"}
}