{
  "id": 2652815,
  "type": "Feature",
  "properties": {
    "tgn:hierarchy":[
        "tgn:2652815",
        "tgn:1000001",
        "tgn:7012149",
        "tgn:2001503",
        "tgn:7007709",
        "tgn:7029392"
    ],
    "tgn:id":2652815,
    "tgn:name":"Service Ridge",
    "tgn:placetype":[
        "aat:300266640"
    ]
},
  "bbox": [],
  "geometry": {"coordinates":[-83.1167,35.55],"type":"Point"}
}