<<<<<<< HEAD
{
  "id": 7365522,
  "type": "Feature",
  "properties": {
    "tgn:hierarchy":[
        "tgn:7365522",
        "tgn:1000001",
        "tgn:1001960",
        "tgn:7005560",
        "tgn:7029392"
    ],
    "tgn:id":7365522,
    "tgn:name":"Rancho El Realito",
    "tgn:placetype":[
        "aat:300000241"
    ]
},
  "bbox": [],
  "geometry": {"coordinates":[-109.533333,29.35],"type":"Point"}
}
=======
{"geometry":{"type":"Point","coordinates":[-109.533333,29.350000]},"type":"Feature","properties":{"hierarchy":["tgn:7365522","tgn:1000001","tgn:1001960","tgn:7005560","tgn:7029392"],"placetype":["aat:300000241"],"id":7365522,"name:xx":"Rancho El Realito"}}
>>>>>>> 03f74aca74312dbeaf24d7e61306dd6a786dc3d0
