{
  "id": 1052461,
  "type": "Feature",
  "properties": {
    "tgn:hierarchy":[
        "tgn:1052461",
        "tgn:1003353",
        "tgn:1000004",
        "tgn:7014786",
        "tgn:7029392"
    ],
    "tgn:id":1052461,
    "tgn:name":"Bakbakty",
    "tgn:placetype":[
        "aat:300008347"
    ]
},
  "bbox": [],
  "geometry": {"coordinates":[76.6667,44.5833],"type":"Point"}
}