{
  "id": 2031522,
  "type": "Feature",
  "properties": {
    "tgn:hierarchy":[
        "tgn:2031522",
        "tgn:1000001",
        "tgn:7012149",
        "tgn:1002798",
        "tgn:7007252",
        "tgn:7029392"
    ],
    "tgn:id":2031522,
    "tgn:name":"Crocker",
    "tgn:placetype":[
        "aat:300008347"
    ]
},
  "bbox": [],
  "geometry": {"coordinates":[-87.1167,41.5833],"type":"Point"}
}