{
  "id": 1020219,
  "type": "Feature",
  "properties": {
    "tgn:hierarchy":[
        "tgn:1020219",
        "tgn:1001160",
        "tgn:7006477",
        "tgn:1000002",
        "tgn:7029392"
    ],
    "tgn:id":1020219,
    "tgn:name":"Villars",
    "tgn:placetype":[
        "aat:300008347"
    ]
},
  "bbox": [],
  "geometry": {"coordinates":[-58.9333,-34.8333],"type":"Point"}
}