{
  "id": 7034381,
  "type": "Feature",
  "properties": {
    "tgn:hierarchy":[
        "tgn:7034381",
        "tgn:1001641",
        "tgn:1000003",
        "tgn:7003121",
        "tgn:1000080",
        "tgn:7029392"
    ],
    "tgn:id":7034381,
    "tgn:name":"Mosca, Cala",
    "tgn:placetype":[
        "aat:300132317"
    ]
},
  "bbox": [],
  "geometry": {"coordinates":[9.151389,39.183889],"type":"Point"}
}