{
  "id": 7464426,
  "type": "Feature",
  "properties": {
    "tgn:hierarchy":[
        "tgn:7464426",
        "tgn:7002444",
        "tgn:1000003",
        "tgn:7008082",
        "tgn:7008591",
        "tgn:7029392"
    ],
    "tgn:id":7464426,
    "tgn:name:en":"Br\u00e0igh Horrisdale, Loch",
    "tgn:placetype":[
        "aat:300008680"
    ]
},
  "bbox": [],
  "geometry": {"coordinates":[-5.666667,57.666667],"type":"Point"}
}