{
  "id": 2507905,
  "type": "Feature",
  "properties": {
    "tgn:hierarchy":[
        "tgn:2507905",
        "tgn:1000001",
        "tgn:7012149",
        "tgn:7007523",
        "tgn:7029392"
    ],
    "tgn:id":2507905,
    "tgn:name":"Mid-Missouri Planning Region",
    "tgn:placetype":[
        "aat:300055621"
    ]
},
  "bbox": [],
  "geometry": {"coordinates":[-92.75,39.25],"type":"Point"}
}