{
  "id": 7484677,
  "type": "Feature",
  "properties": {
    "tgn:hierarchy":[
        "tgn:7484677",
        "tgn:7001004",
        "tgn:1000004",
        "tgn:1000141",
        "tgn:7029392"
    ],
    "tgn:id":7484677,
    "tgn:name":"Xiaxinkai",
    "tgn:placetype":[
        "aat:300008347"
    ]
},
  "bbox": [],
  "geometry": {"coordinates":[120.682778,23.063333],"type":"Point"}
}