{
  "id": 2441419,
  "type": "Feature",
  "properties": {
    "tgn:hierarchy":[
        "tgn:2441419",
        "tgn:1000001",
        "tgn:7012149",
        "tgn:2000233",
        "tgn:7007158",
        "tgn:7029392"
    ],
    "tgn:id":2441419,
    "tgn:name":"Knuckles Reservoir",
    "tgn:placetype":[
        "aat:300006191"
    ]
},
  "bbox": [],
  "geometry": {"coordinates":[-108.2667,37.5833],"type":"Point"}
}