{
  "id": 2683358,
  "type": "Feature",
  "properties": {
    "tgn:hierarchy":[
        "tgn:2683358",
        "tgn:1000001",
        "tgn:7012149",
        "tgn:2002026",
        "tgn:7007826",
        "tgn:7029392"
    ],
    "tgn:id":2683358,
    "tgn:name":"Sparks Crossing",
    "tgn:placetype":[
        "aat:300008347"
    ]
},
  "bbox": [],
  "geometry": {"coordinates":[-98.1333,31.0667],"type":"Point"}
}