{
  "id": 2050882,
  "type": "Feature",
  "properties": {
    "tgn:hierarchy":[
        "tgn:2050882",
        "tgn:1000001",
        "tgn:7012149",
        "tgn:1003038",
        "tgn:7007517",
        "tgn:7029392"
    ],
    "tgn:id":2050882,
    "tgn:name":"West Brookfield",
    "tgn:placetype":[
        "aat:300008347"
    ]
},
  "bbox": [],
  "geometry": {"coordinates":[-72.1333,42.2333],"type":"Point"}
}