{
  "id": 7221400,
  "type": "Feature",
  "properties": {
    "tgn:hierarchy":[
        "tgn:7221400",
        "tgn:1042193",
        "tgn:7002705",
        "tgn:1000003",
        "tgn:1000074",
        "tgn:7029392"
    ],
    "tgn:id":7221400,
    "tgn:name":"Tsoukal\u00e1dhes",
    "tgn:placetype":[
        "aat:300008347"
    ]
},
  "bbox": [],
  "geometry": {"coordinates":[20.65,38.816667],"type":"Point"}
}