{
  "id": 2585749,
  "type": "Feature",
  "properties": {
    "tgn:hierarchy":[
        "tgn:2585749",
        "tgn:1000001",
        "tgn:2000773",
        "tgn:7012149",
        "tgn:7007255",
        "tgn:7029392"
    ],
    "tgn:id":2585749,
    "tgn:name":"Pipe Run",
    "tgn:placetype":[
        "aat:300008699"
    ]
},
  "bbox": [],
  "geometry": {"coordinates":[-86.6167,37.6333],"type":"Point"}
}