<<<<<<< HEAD
{
  "id": 7485987,
  "type": "Feature",
  "properties": {
    "tgn:hierarchy":[
        "tgn:7485987",
        "tgn:1000004",
        "tgn:7001014",
        "tgn:1000141",
        "tgn:7029392"
    ],
    "tgn:id":7485987,
    "tgn:name":"Bietan",
    "tgn:placetype":[
        "aat:300008347"
    ]
},
  "bbox": [],
  "geometry": {"coordinates":[120.189722,23.609722],"type":"Point"}
}
=======
{"geometry":{"type":"Point","coordinates":[120.189722,23.609722]},"type":"Feature","properties":{"hierarchy":["tgn:7485987","tgn:1000004","tgn:7001014","tgn:1000141","tgn:7029392"],"placetype":["aat:300008347"],"id":7485987,"name:xx":"Bietan"}}
>>>>>>> 03f74aca74312dbeaf24d7e61306dd6a786dc3d0
