{
  "id": 7485987,
  "type": "Feature",
  "properties": {
    "tgn:hierarchy":[
        "tgn:7485987",
        "tgn:1000004",
        "tgn:7001014",
        "tgn:1000141",
        "tgn:7029392"
    ],
    "tgn:id":7485987,
    "tgn:name":"Bietan",
    "tgn:placetype":[
        "aat:300008347"
    ]
},
  "bbox": [],
  "geometry": {"coordinates":[120.189722,23.609722],"type":"Point"}
}