{
  "id": 2393698,
  "type": "Feature",
  "properties": {
    "tgn:hierarchy":[
        "tgn:2393698",
        "tgn:1000001",
        "tgn:7012149",
        "tgn:2000811",
        "tgn:7007255",
        "tgn:7029392"
    ],
    "tgn:id":2393698,
    "tgn:name":"Hog Hollow",
    "tgn:placetype":[
        "aat:300008761"
    ]
},
  "bbox": [],
  "geometry": {"coordinates":[-83.5333,37.0833],"type":"Point"}
}