{
  "id": 2403432,
  "type": "Feature",
  "properties": {
    "tgn:hierarchy":[
        "tgn:2403432",
        "tgn:1000001",
        "tgn:7012149",
        "tgn:7013867",
        "tgn:7007710",
        "tgn:7029392"
    ],
    "tgn:id":2403432,
    "tgn:name":"Houston Run",
    "tgn:placetype":[
        "aat:300008699"
    ]
},
  "bbox": [],
  "geometry": {"coordinates":[-76.05,39.9667],"type":"Point"}
}