<<<<<<< HEAD
{
  "id": 2403432,
  "type": "Feature",
  "properties": {
    "tgn:hierarchy":[
        "tgn:2403432",
        "tgn:1000001",
        "tgn:7012149",
        "tgn:7013867",
        "tgn:7007710",
        "tgn:7029392"
    ],
    "tgn:id":2403432,
    "tgn:name":"Houston Run",
    "tgn:placetype":[
        "aat:300008699"
    ]
},
  "bbox": [],
  "geometry": {"coordinates":[-76.05,39.9667],"type":"Point"}
}
=======
{"geometry":{"type":"Point","coordinates":[-76.050000,39.966700]},"type":"Feature","properties":{"hierarchy":["tgn:2403432","tgn:1000001","tgn:7012149","tgn:7013867","tgn:7007710","tgn:7029392"],"placetype":["aat:300008699"],"id":2403432,"name:xx":"Houston Run"}}
>>>>>>> 03f74aca74312dbeaf24d7e61306dd6a786dc3d0
