{
  "id": 2272371,
  "type": "Feature",
  "properties": {
    "tgn:hierarchy":[
        "tgn:2272371",
        "tgn:1000001",
        "tgn:2000920",
        "tgn:7012149",
        "tgn:7007515",
        "tgn:7029392"
    ],
    "tgn:id":2272371,
    "tgn:name":"Curtis Cove",
    "tgn:placetype":[
        "aat:300132316"
    ]
},
  "bbox": [],
  "geometry": {"coordinates":[-70.0167,43.7667],"type":"Point"}
}