<<<<<<< HEAD
{
  "id": 7476730,
  "type": "Feature",
  "properties": {
    "tgn:hierarchy":[
        "tgn:7476730",
        "tgn:7488858",
        "tgn:1000004",
        "tgn:1000141",
        "tgn:7029392"
    ],
    "tgn:id":7476730,
    "tgn:name":"Jin'an Yihao Qiao",
    "tgn:placetype":[
        "aat:300007836"
    ]
},
  "bbox": [],
  "geometry": {"coordinates":[120.895345,23.981603],"type":"Point"}
}
=======
{"geometry":{"type":"Point","coordinates":[120.895345,23.981603]},"type":"Feature","properties":{"hierarchy":["tgn:7476730","tgn:7488858","tgn:1000004","tgn:1000141","tgn:7029392"],"placetype":["aat:300007836"],"id":7476730,"name:xx":"Jin'an Yihao Qiao"}}
>>>>>>> 03f74aca74312dbeaf24d7e61306dd6a786dc3d0
