{
  "id": 7308427,
  "type": "Feature",
  "properties": {
    "tgn:hierarchy":[
        "tgn:7308427",
        "tgn:1001657",
        "tgn:1000049",
        "tgn:1000002",
        "tgn:7029392"
    ],
    "tgn:id":7308427,
    "tgn:name":"Mar Gruesa, Ensenada",
    "tgn:placetype":[
        "aat:300132316"
    ]
},
  "bbox": [],
  "geometry": {"coordinates":[-71.756111,-30.496944],"type":"Point"}
}