{
  "id": 2311244,
  "type": "Feature",
  "properties": {
    "tgn:hierarchy":[
        "tgn:2311244",
        "tgn:1000001",
        "tgn:7012149",
        "tgn:1002746",
        "tgn:7007568",
        "tgn:7029392"
    ],
    "tgn:id":2311244,
    "tgn:name":"Edgewater Park",
    "tgn:placetype":[
        "aat:300008347"
    ]
},
  "bbox": [],
  "geometry": {"coordinates":[-76.3667,42.8667],"type":"Point"}
}