{
  "id": 1054541,
  "type": "Feature",
  "properties": {
    "tgn:hierarchy":[
        "tgn:1054541",
        "tgn:1003391",
        "tgn:1000003",
        "tgn:7006657",
        "tgn:7029392"
    ],
    "tgn:id":1054541,
    "tgn:name":"Jaminsk",
    "tgn:placetype":[
        "aat:300008347"
    ]
},
  "bbox": [],
  "geometry": {"coordinates":[28.2667,52.7667],"type":"Point"}
}