{
  "id": 7039681,
  "type": "Feature",
  "properties": {
    "tgn:hierarchy":[
        "tgn:7039681",
        "tgn:1003505",
        "tgn:1000003",
        "tgn:7002993",
        "tgn:1000080",
        "tgn:7029392"
    ],
    "tgn:id":7039681,
    "tgn:name":"Servola",
    "tgn:placetype":[
        "aat:300008347"
    ]
},
  "bbox": [],
  "geometry": {"coordinates":[13.778056,45.627222],"type":"Point"}
}