{
  "id": 2770562,
  "type": "Feature",
  "properties": {
    "tgn:hierarchy":[
        "tgn:2770562",
        "tgn:1000001",
        "tgn:2000935",
        "tgn:7012149",
        "tgn:7007516",
        "tgn:7029392"
    ],
    "tgn:id":2770562,
    "tgn:name":"Wild Turkey Rock",
    "tgn:placetype":[
        "aat:300008798"
    ]
},
  "bbox": [],
  "geometry": {"coordinates":[-79.25,39.4167],"type":"Point"}
}