{
  "id": 2520657,
  "type": "Feature",
  "properties": {
    "tgn:hierarchy":[
        "tgn:2520657",
        "tgn:1000001",
        "tgn:7012149",
        "tgn:1002613",
        "tgn:7007710",
        "tgn:7029392"
    ],
    "tgn:id":2520657,
    "tgn:name":"Monks Hollow",
    "tgn:placetype":[
        "aat:300008761"
    ]
},
  "bbox": [],
  "geometry": {"coordinates":[-77.4333,41.4833],"type":"Point"}
}