{
  "id": 7562557,
  "type": "Feature",
  "properties": {
    "tgn:hierarchy":[
        "tgn:7562557",
        "tgn:1000004",
        "tgn:7000198",
        "tgn:7016722",
        "tgn:7029392"
    ],
    "tgn:id":7562557,
    "tgn:name:en":"Pahla",
    "tgn:placetype":[
        "aat:300008347"
    ]
},
  "bbox": [],
  "geometry": {"coordinates":[79.8213,27.0883],"type":"Point"}
}