{
  "id": 2734839,
  "type": "Feature",
  "properties": {
    "tgn:hierarchy":[
        "tgn:2734839",
        "tgn:1000001",
        "tgn:7012149",
        "tgn:7014021",
        "tgn:7007709",
        "tgn:7029392"
    ],
    "tgn:id":2734839,
    "tgn:name":"Twelve Oaks",
    "tgn:placetype":[
        "aat:300008347"
    ]
},
  "bbox": [],
  "geometry": {"coordinates":[-80.95,35.1333],"type":"Point"}
}