{
  "id": 7158012,
  "type": "Feature",
  "properties": {
    "tgn:hierarchy":[
        "tgn:7158012",
        "tgn:7003669",
        "tgn:1000003",
        "tgn:7000084",
        "tgn:7029392"
    ],
    "tgn:id":7158012,
    "tgn:name":"Kieferling",
    "tgn:placetype":[
        "aat:300008347"
    ]
},
  "bbox": [],
  "geometry": {"coordinates":[13.016667,48.45],"type":"Point"}
}