{
  "id": 2771281,
  "type": "Feature",
  "properties": {
    "tgn:hierarchy":[
        "tgn:2771281",
        "tgn:1000001",
        "tgn:7012149",
        "tgn:1002935",
        "tgn:7007919",
        "tgn:7029392"
    ],
    "tgn:id":2771281,
    "tgn:name":"Wildcat Swamp",
    "tgn:placetype":[
        "aat:300008699"
    ]
},
  "bbox": [],
  "geometry": {"coordinates":[-76.9833,36.9833],"type":"Point"}
}