{
  "id": 2680765,
  "type": "Feature",
  "properties": {
    "tgn:hierarchy":[
        "tgn:2680765",
        "tgn:1000001",
        "tgn:7012149",
        "tgn:2000928",
        "tgn:7007515",
        "tgn:7029392"
    ],
    "tgn:id":2680765,
    "tgn:name":"South Inlet Brook",
    "tgn:placetype":[
        "aat:300008699"
    ]
},
  "bbox": [],
  "geometry": {"coordinates":[-69.1167,45.5167],"type":"Point"}
}