{
  "id": 2608408,
  "type": "Feature",
  "properties": {
    "tgn:hierarchy":[
        "tgn:2608408",
        "tgn:1000001",
        "tgn:7012149",
        "tgn:2001458",
        "tgn:7007566",
        "tgn:7029392"
    ],
    "tgn:id":2608408,
    "tgn:name":"Rattlesnake Draw",
    "tgn:placetype":[
        "aat:300008761"
    ]
},
  "bbox": [],
  "geometry": {"coordinates":[-105.7167,34.9667],"type":"Point"}
}