{
  "id": 2539287,
  "type": "Feature",
  "properties": {
    "tgn:hierarchy":[
        "tgn:2539287",
        "tgn:1000001",
        "tgn:7012149",
        "tgn:2000412",
        "tgn:7007248",
        "tgn:7029392"
    ],
    "tgn:id":2539287,
    "tgn:name":"New Hope Branch",
    "tgn:placetype":[
        "aat:300008699"
    ]
},
  "bbox": [],
  "geometry": {"coordinates":[-82.15,33.3167],"type":"Point"}
}