{
  "id": 2510875,
  "type": "Feature",
  "properties": {
    "tgn:hierarchy":[
        "tgn:2510875",
        "tgn:1000001",
        "tgn:7012149",
        "tgn:2001455",
        "tgn:7007566",
        "tgn:7029392"
    ],
    "tgn:id":2510875,
    "tgn:name":"Midnight Mine",
    "tgn:placetype":[
        "aat:300000390"
    ]
},
  "bbox": [],
  "geometry": {"coordinates":[-107.7167,33.2833],"type":"Point"}
}