{
  "id": 2727057,
  "type": "Feature",
  "properties": {
    "tgn:hierarchy":[
        "tgn:2727057",
        "tgn:1000001",
        "tgn:7012149",
        "tgn:2002374",
        "tgn:7007923",
        "tgn:7029392"
    ],
    "tgn:id":2727057,
    "tgn:name":"Trabing Draw",
    "tgn:placetype":[
        "aat:300008761"
    ]
},
  "bbox": [],
  "geometry": {"coordinates":[-106.5667,44.15],"type":"Point"}
}