<<<<<<< HEAD
{
  "id": 7177997,
  "type": "Feature",
  "properties": {
    "tgn:hierarchy":[
        "tgn:7177997",
        "tgn:1000003",
        "tgn:7003682",
        "tgn:7000084",
        "tgn:7029392"
    ],
    "tgn:id":7177997,
    "tgn:name":"Hangen-Weisheim",
    "tgn:placetype":[
        "aat:300008347"
    ]
},
  "bbox": [],
  "geometry": {"coordinates":[8.183611,49.710278],"type":"Point"}
}
=======
{"geometry":{"type":"Point","coordinates":[8.183611,49.710278]},"type":"Feature","properties":{"hierarchy":["tgn:7177997","tgn:1000003","tgn:7003682","tgn:7000084","tgn:7029392"],"placetype":["aat:300008347"],"id":7177997,"name:xx":"Hangen-Weisheim"}}
>>>>>>> 03f74aca74312dbeaf24d7e61306dd6a786dc3d0
