{
  "id": 7365389,
  "type": "Feature",
  "properties": {
    "tgn:hierarchy":[
        "tgn:7365389",
        "tgn:1000001",
        "tgn:7005590",
        "tgn:7005560",
        "tgn:7029392"
    ],
    "tgn:id":7365389,
    "tgn:name":"Encinal",
    "tgn:placetype":[
        "aat:300008795"
    ]
},
  "bbox": [],
  "geometry": {"coordinates":[-102.333333,20.116667],"type":"Point"}
}