{
  "id": 2226286,
  "type": "Feature",
  "properties": {
    "tgn:hierarchy":[
        "tgn:2226286",
        "tgn:1000001",
        "tgn:7012149",
        "tgn:1002645",
        "tgn:7007920",
        "tgn:7029392"
    ],
    "tgn:id":2226286,
    "tgn:name":"Catfish Lake",
    "tgn:placetype":[
        "aat:300008680"
    ]
},
  "bbox": [],
  "geometry": {"coordinates":[-122.8333,47.35],"type":"Point"}
}