{
  "id": 7351479,
  "type": "Feature",
  "properties": {
    "tgn:hierarchy":[
        "tgn:7351479",
        "tgn:7005578",
        "tgn:1000001",
        "tgn:7005560",
        "tgn:7029392"
    ],
    "tgn:id":7351479,
    "tgn:name":"Bolantauch\u00e9",
    "tgn:placetype":[
        "aat:300008347"
    ]
},
  "bbox": [],
  "geometry": {"coordinates":[-90.466667,20.15],"type":"Point"}
}