{
  "id": 7315049,
  "type": "Feature",
  "properties": {
    "tgn:hierarchy":[
        "tgn:7315049",
        "tgn:1001702",
        "tgn:1000049",
        "tgn:1000002",
        "tgn:7029392"
    ],
    "tgn:id":7315049,
    "tgn:name":"Los Jemelos, Cerros",
    "tgn:placetype":[
        "aat:300008777"
    ]
},
  "bbox": [],
  "geometry": {"coordinates":[-72.65,-53.333333],"type":"Point"}
}