{
  "id": 1051419,
  "type": "Feature",
  "properties": {
    "tgn:hierarchy":[
        "tgn:1051419",
        "tgn:1000004",
        "tgn:7011458",
        "tgn:7014786",
        "tgn:7029392"
    ],
    "tgn:id":1051419,
    "tgn:name":"\u010cornoje",
    "tgn:placetype":[
        "aat:300008347"
    ]
},
  "bbox": [],
  "geometry": {"coordinates":[77.5667,51.7333],"type":"Point"}
}