{
  "id": 2575948,
  "type": "Feature",
  "properties": {
    "tgn:hierarchy":[
        "tgn:2575948",
        "tgn:1000001",
        "tgn:2000772",
        "tgn:7012149",
        "tgn:7007255",
        "tgn:7029392"
    ],
    "tgn:id":2575948,
    "tgn:name":"Perkins Branch",
    "tgn:placetype":[
        "aat:300008699"
    ]
},
  "bbox": [],
  "geometry": {"coordinates":[-83.2833,37.3833],"type":"Point"}
}