{
  "id": 7232479,
  "type": "Feature",
  "properties": {
    "tgn:hierarchy":[
        "tgn:7232479",
        "tgn:7002743",
        "tgn:7017076",
        "tgn:1000003",
        "tgn:1000074",
        "tgn:7029392"
    ],
    "tgn:id":7232479,
    "tgn:name":"Kakavoula\u00edika",
    "tgn:placetype":[
        "aat:300008347"
    ]
},
  "bbox": [],
  "geometry": {"coordinates":[21.75,38.05],"type":"Point"}
}