{
  "id": 7166100,
  "type": "Feature",
  "properties": {
    "tgn:hierarchy":[
        "tgn:7166100",
        "tgn:1000003",
        "tgn:7003689",
        "tgn:7000084",
        "tgn:7029392"
    ],
    "tgn:id":7166100,
    "tgn:name":"Helder-Bach",
    "tgn:placetype":[
        "aat:300008713"
    ]
},
  "bbox": [],
  "geometry": {"coordinates":[11.283333,51.366667],"type":"Point"}
}