<<<<<<< HEAD
{
  "id": 7173923,
  "type": "Feature",
  "properties": {
    "tgn:hierarchy":[
        "tgn:7173923",
        "tgn:1000003",
        "tgn:7000094",
        "tgn:7000084",
        "tgn:7029392"
    ],
    "tgn:id":7173923,
    "tgn:name":"Gro\u00dfe Rosinwiesen",
    "tgn:placetype":[
        "aat:300008876"
    ]
},
  "bbox": [],
  "geometry": {"coordinates":[12.85,53.85],"type":"Point"}
}
=======
{"geometry":{"type":"Point","coordinates":[12.850000,53.850000]},"type":"Feature","properties":{"hierarchy":["tgn:7173923","tgn:1000003","tgn:7000094","tgn:7000084","tgn:7029392"],"placetype":["aat:300008876"],"id":7173923,"name:xx":"Gro\u00dfe Rosinwiesen"}}
>>>>>>> 03f74aca74312dbeaf24d7e61306dd6a786dc3d0
