{
  "id": 7230118,
  "type": "Feature",
  "properties": {
    "tgn:hierarchy":[
        "tgn:7230118",
        "tgn:7002725",
        "tgn:7002715",
        "tgn:1000003",
        "tgn:1000074",
        "tgn:7029392"
    ],
    "tgn:id":7230118,
    "tgn:name":"Chrys\u00f3kampos",
    "tgn:placetype":[
        "aat:300008347"
    ]
},
  "bbox": [],
  "geometry": {"coordinates":[22.632222,40.985],"type":"Point"}
}