{
  "id": 2564734,
  "type": "Feature",
  "properties": {
    "tgn:hierarchy":[
        "tgn:2564734",
        "tgn:1000001",
        "tgn:7012149",
        "tgn:2001918",
        "tgn:7007825",
        "tgn:7029392"
    ],
    "tgn:id":2564734,
    "tgn:name":"Paddle Creek",
    "tgn:placetype":[
        "aat:300008706"
    ]
},
  "bbox": [],
  "geometry": {"coordinates":[-82.1667,36.5167],"type":"Point"}
}