<<<<<<< HEAD
{
  "id": 7178970,
  "type": "Feature",
  "properties": {
    "tgn:hierarchy":[
        "tgn:7178970",
        "tgn:7003669",
        "tgn:1000003",
        "tgn:7000084",
        "tgn:7029392"
    ],
    "tgn:id":7178970,
    "tgn:name":"Haideck",
    "tgn:placetype":[
        "aat:300008347"
    ]
},
  "bbox": [],
  "geometry": {"coordinates":[11.95,50.25],"type":"Point"}
}
=======
{"geometry":{"type":"Point","coordinates":[11.950000,50.250000]},"type":"Feature","properties":{"hierarchy":["tgn:7178970","tgn:7003669","tgn:1000003","tgn:7000084","tgn:7029392"],"placetype":["aat:300008347"],"id":7178970,"name:xx":"Haideck"}}
>>>>>>> 03f74aca74312dbeaf24d7e61306dd6a786dc3d0
