{
  "id": 7494470,
  "type": "Feature",
  "properties": {
    "tgn:hierarchy":[
        "tgn:7494470",
        "tgn:7001010",
        "tgn:1000004",
        "tgn:1000141",
        "tgn:7029392"
    ],
    "tgn:id":7494470,
    "tgn:name":"Daxing Erhao Ti",
    "tgn:placetype":[
        "aat:300006156"
    ]
},
  "bbox": [],
  "geometry": {"coordinates":[121.402444,23.630941],"type":"Point"}
}