{
  "id": 7047413,
  "type": "Feature",
  "properties": {
    "tgn:hierarchy":[
        "tgn:7047413",
        "tgn:7003163",
        "tgn:1000003",
        "tgn:7009760",
        "tgn:1000080",
        "tgn:7029392"
    ],
    "tgn:id":7047413,
    "tgn:name":"Gricignano",
    "tgn:placetype":[
        "aat:300008347"
    ]
},
  "bbox": [],
  "geometry": {"coordinates":[11.366667,43.916667],"type":"Point"}
}