{
  "id": 2239882,
  "type": "Feature",
  "properties": {
    "tgn:hierarchy":[
        "tgn:2239882",
        "tgn:1000001",
        "tgn:7006451",
        "tgn:7012149",
        "tgn:2000103",
        "tgn:7029392"
    ],
    "tgn:id":2239882,
    "tgn:name":"Cimarron Creek",
    "tgn:placetype":[
        "aat:300008706"
    ]
},
  "bbox": [],
  "geometry": {"coordinates":[-111.65,34.4167],"type":"Point"}
}