{
  "id": 2425388,
  "type": "Feature",
  "properties": {
    "tgn:hierarchy":[
        "tgn:2425388",
        "tgn:1000001",
        "tgn:7012149",
        "tgn:7007706",
        "tgn:7029392"
    ],
    "tgn:id":2425388,
    "tgn:name":"Johnson Run",
    "tgn:placetype":[
        "aat:300008699"
    ]
},
  "bbox": [],
  "geometry": {"coordinates":[-82.5667,39.1667],"type":"Point"}
}