{
  "id": 2286592,
  "type": "Feature",
  "properties": {
    "tgn:hierarchy":[
        "tgn:2286592",
        "tgn:1000001",
        "tgn:2000198",
        "tgn:7012149",
        "tgn:7007158",
        "tgn:7029392"
    ],
    "tgn:id":2286592,
    "tgn:name":"Diamond Lake",
    "tgn:placetype":[
        "aat:300008680"
    ]
},
  "bbox": [],
  "geometry": {"coordinates":[-105.6333,39.9833],"type":"Point"}
}