{
  "id": 7243099,
  "type": "Feature",
  "properties": {
    "tgn:hierarchy":[
        "tgn:7243099",
        "tgn:7003457",
        "tgn:1000003",
        "tgn:1000063",
        "tgn:7018236",
        "tgn:7029392"
    ],
    "tgn:id":7243099,
    "tgn:name":"Maagd van Gent",
    "tgn:placetype":[
        "aat:300008347"
    ]
},
  "bbox": [],
  "geometry": {"coordinates":[3.69029,51.280807],"type":"Point"}
}