{
  "id": 2532736,
  "type": "Feature",
  "properties": {
    "tgn:hierarchy":[
        "tgn:2532736",
        "tgn:1000001",
        "tgn:7012149",
        "tgn:2002374",
        "tgn:7007923",
        "tgn:7029392"
    ],
    "tgn:id":2532736,
    "tgn:name":"Murphy Reservoir",
    "tgn:placetype":[
        "aat:300006191"
    ]
},
  "bbox": [],
  "geometry": {"coordinates":[-106.4667,44.0333],"type":"Point"}
}