{
  "id": 1007137,
  "type": "Feature",
  "properties": {
    "tgn:hierarchy":[
        "tgn:1007137",
        "tgn:7018487",
        "tgn:1000004",
        "tgn:7004542",
        "tgn:1000111",
        "tgn:7029392"
    ],
    "tgn:id":1007137,
    "tgn:name":"Fu Tau Pun Chau",
    "tgn:placetype":[
        "aat:300008791"
    ]
},
  "bbox": [],
  "geometry": {"coordinates":[114.3667,22.3333],"type":"Point"}
}