{
  "id": 2223529,
  "type": "Feature",
  "properties": {
    "tgn:hierarchy":[
        "tgn:2223529",
        "tgn:1000001",
        "tgn:2002145",
        "tgn:7012149",
        "tgn:7007919",
        "tgn:7029392"
    ],
    "tgn:id":2223529,
    "tgn:name":"Carter Branch",
    "tgn:placetype":[
        "aat:300008699"
    ]
},
  "bbox": [],
  "geometry": {"coordinates":[-81.25,37.1167],"type":"Point"}
}