{
  "id": 2626566,
  "type": "Feature",
  "properties": {
    "tgn:hierarchy":[
        "tgn:2626566",
        "tgn:7006450",
        "tgn:1000001",
        "tgn:2124012",
        "tgn:7012149",
        "tgn:7029392"
    ],
    "tgn:id":2626566,
    "tgn:name":"Rocky Islet",
    "tgn:placetype":[
        "aat:300008791"
    ]
},
  "bbox": [],
  "geometry": {"coordinates":[-152.4167,57.7667],"type":"Point"}
}