{
  "id": 7053279,
  "type": "Feature",
  "properties": {
    "tgn:hierarchy":[
        "tgn:7053279",
        "tgn:1003489",
        "tgn:7004610",
        "tgn:1000003",
        "tgn:1000080",
        "tgn:7029392"
    ],
    "tgn:id":7053279,
    "tgn:name":"Maglia, Fiume",
    "tgn:placetype":[
        "aat:300008699"
    ]
},
  "bbox": [],
  "geometry": {"coordinates":[15.95,40.283333],"type":"Point"}
}