{
  "id": 7415593,
  "type": "Feature",
  "properties": {
    "tgn:hierarchy":[
        "tgn:7415593",
        "tgn:7005584",
        "tgn:1000001",
        "tgn:7005560",
        "tgn:7029392"
    ],
    "tgn:id":7415593,
    "tgn:name":"Los Mart\u00ednez",
    "tgn:placetype":[
        "aat:300008347"
    ]
},
  "bbox": [],
  "geometry": {"coordinates":[-100.843611,20.825556],"type":"Point"}
}