{
  "id": 7282236,
  "type": "Feature",
  "properties": {
    "tgn:hierarchy":[
        "tgn:7282236",
        "tgn:1001637",
        "tgn:1000049",
        "tgn:1000002",
        "tgn:7029392"
    ],
    "tgn:id":7282236,
    "tgn:name":"San Miguel de Bul\u00ed",
    "tgn:placetype":[
        "aat:300008347"
    ]
},
  "bbox": [],
  "geometry": {"coordinates":[-71.766667,-36.366667],"type":"Point"}
}