{
  "id": 2712132,
  "type": "Feature",
  "properties": {
    "tgn:hierarchy":[
        "tgn:2712132",
        "tgn:2001623",
        "tgn:1000001",
        "tgn:7012149",
        "tgn:7007707",
        "tgn:7029392"
    ],
    "tgn:id":2712132,
    "tgn:name":"Tate Parris Branch",
    "tgn:placetype":[
        "aat:300008699"
    ]
},
  "bbox": [],
  "geometry": {"coordinates":[-94.6333,36.0833],"type":"Point"}
}