{
  "id": 1018713,
  "type": "Feature",
  "properties": {
    "tgn:hierarchy":[
        "tgn:1018713",
        "tgn:7593358",
        "tgn:1000001",
        "tgn:7005562",
        "tgn:7029392"
    ],
    "tgn:id":1018713,
    "tgn:name":"Cabo Gracias a Dios",
    "tgn:placetype":[
        "aat:300008347"
    ]
},
  "bbox": [],
  "geometry": {"coordinates":[-83.1667,14.9833],"type":"Point"}
}