{
  "id": 7412222,
  "type": "Feature",
  "properties": {
    "tgn:hierarchy":[
        "tgn:7412222",
        "tgn:7005587",
        "tgn:1000001",
        "tgn:7005560",
        "tgn:7029392"
    ],
    "tgn:id":7412222,
    "tgn:name:es":"Llano Grande",
    "tgn:placetype":[
        "aat:300008347"
    ]
},
  "bbox": [],
  "geometry": {"coordinates":[-98.569444,20.183333],"type":"Point"}
}