<<<<<<< HEAD
{
  "id": 2156648,
  "type": "Feature",
  "properties": {
    "tgn:hierarchy":[
        "tgn:2156648",
        "tgn:1000001",
        "tgn:7012149",
        "tgn:2001864",
        "tgn:7007825",
        "tgn:7029392"
    ],
    "tgn:id":2156648,
    "tgn:name":"Beasley Branch",
    "tgn:placetype":[
        "aat:300008699"
    ]
},
  "bbox": [],
  "geometry": {"coordinates":[-86.9,35.05],"type":"Point"}
}
=======
{"geometry":{"type":"Point","coordinates":[-86.900000,35.050000]},"type":"Feature","properties":{"hierarchy":["tgn:2156648","tgn:1000001","tgn:7012149","tgn:2001864","tgn:7007825","tgn:7029392"],"placetype":["aat:300008699"],"id":2156648,"name:xx":"Beasley Branch"}}
>>>>>>> 03f74aca74312dbeaf24d7e61306dd6a786dc3d0
