<<<<<<< HEAD
{
  "id": 7053486,
  "type": "Feature",
  "properties": {
    "tgn:hierarchy":[
        "tgn:7053486",
        "tgn:1003506",
        "tgn:1000003",
        "tgn:7002993",
        "tgn:1000080",
        "tgn:7029392"
    ],
    "tgn:id":7053486,
    "tgn:name":"Paradiso",
    "tgn:placetype":[
        "aat:300008347"
    ]
},
  "bbox": [],
  "geometry": {"coordinates":[13.145833,45.867778],"type":"Point"}
}
=======
{"geometry":{"type":"Point","coordinates":[13.145833,45.867778]},"type":"Feature","properties":{"hierarchy":["tgn:7053486","tgn:1003506","tgn:1000003","tgn:7002993","tgn:1000080","tgn:7029392"],"placetype":["aat:300008347"],"id":7053486,"name:xx":"Paradiso"}}
>>>>>>> 03f74aca74312dbeaf24d7e61306dd6a786dc3d0
