{
  "id": 2460105,
  "type": "Feature",
  "properties": {
    "tgn:hierarchy":[
        "tgn:2460105",
        "tgn:1000001",
        "tgn:2000952",
        "tgn:7012149",
        "tgn:7007520",
        "tgn:7029392"
    ],
    "tgn:id":2460105,
    "tgn:name":"Little Rogg Island",
    "tgn:placetype":[
        "aat:300008791"
    ]
},
  "bbox": [],
  "geometry": {"coordinates":[-83.7333,46.0333],"type":"Point"}
}