{
  "id": 2516466,
  "type": "Feature",
  "properties": {
    "tgn:hierarchy":[
        "tgn:2516466",
        "tgn:1000001",
        "tgn:7012149",
        "tgn:1003020",
        "tgn:7007920",
        "tgn:7029392"
    ],
    "tgn:id":2516466,
    "tgn:name":"Mineral Creek",
    "tgn:placetype":[
        "aat:300008706"
    ]
},
  "bbox": [],
  "geometry": {"coordinates":[-121.4333,48.85],"type":"Point"}
}