{
  "id": 7408313,
  "type": "Feature",
  "properties": {
    "tgn:hierarchy":[
        "tgn:7408313",
        "tgn:1000001",
        "tgn:1001893",
        "tgn:7005560",
        "tgn:7029392"
    ],
    "tgn:id":7408313,
    "tgn:name":"Vista Hermosa",
    "tgn:placetype":[
        "aat:300008347"
    ]
},
  "bbox": [],
  "geometry": {"coordinates":[-99.475,20.066667],"type":"Point"}
}