{
  "id": 2140123,
  "type": "Feature",
  "properties": {
    "tgn:hierarchy":[
        "tgn:2140123",
        "tgn:2000918",
        "tgn:1000001",
        "tgn:7012149",
        "tgn:7007515",
        "tgn:7029392"
    ],
    "tgn:id":2140123,
    "tgn:name":"Auburn Plains",
    "tgn:placetype":[
        "aat:300008347"
    ]
},
  "bbox": [],
  "geometry": {"coordinates":[-70.2167,44.1667],"type":"Point"}
}