{
  "id": 2045670,
  "type": "Feature",
  "properties": {
    "tgn:hierarchy":[
        "tgn:2045670",
        "tgn:1000001",
        "tgn:7012149",
        "tgn:2000926",
        "tgn:7007515",
        "tgn:7029392"
    ],
    "tgn:id":2045670,
    "tgn:name":"South Waterford",
    "tgn:placetype":[
        "aat:300008347"
    ]
},
  "bbox": [],
  "geometry": {"coordinates":[-70.7167,44.15],"type":"Point"}
}