{
  "id": 7115558,
  "type": "Feature",
  "properties": {
    "tgn:hierarchy":[
        "tgn:7115558",
        "tgn:1000003",
        "tgn:7000094",
        "tgn:7000084",
        "tgn:7029392"
    ],
    "tgn:id":7115558,
    "tgn:name":"Oie",
    "tgn:placetype":[
        "aat:300008791"
    ]
},
  "bbox": [],
  "geometry": {"coordinates":[12.733333,54.416667],"type":"Point"}
}