{
  "id": 7228590,
  "type": "Feature",
  "properties": {
    "tgn:hierarchy":[
        "tgn:7228590",
        "tgn:7011270",
        "tgn:7002674",
        "tgn:1000003",
        "tgn:1000074",
        "tgn:7029392"
    ],
    "tgn:id":7228590,
    "tgn:name":"Liarop\u00e1",
    "tgn:placetype":[
        "aat:300008347"
    ]
},
  "bbox": [],
  "geometry": {"coordinates":[24.916667,37.383333],"type":"Point"}
}