{
  "id": 7568842,
  "type": "Feature",
  "properties": {
    "tgn:hierarchy":[
        "tgn:7568842",
        "tgn:1000004",
        "tgn:7000198",
        "tgn:1001996",
        "tgn:7029392"
    ],
    "tgn:id":7568842,
    "tgn:name:en":"Dharog",
    "tgn:placetype":[
        "aat:300008347"
    ]
},
  "bbox": [],
  "geometry": {"coordinates":[77.074444,31.158611],"type":"Point"}
}