{
  "id": 2280322,
  "type": "Feature",
  "properties": {
    "tgn:hierarchy":[
        "tgn:2280322",
        "tgn:1000001",
        "tgn:7012149",
        "tgn:2001706",
        "tgn:7007708",
        "tgn:7029392"
    ],
    "tgn:id":2280322,
    "tgn:name":"Deception Creek",
    "tgn:placetype":[
        "aat:300008706"
    ]
},
  "bbox": [],
  "geometry": {"coordinates":[-122.5833,43.2333],"type":"Point"}
}