<<<<<<< HEAD
{
  "id": 7350170,
  "type": "Feature",
  "properties": {
    "tgn:hierarchy":[
        "tgn:7350170",
        "tgn:7005585",
        "tgn:1000001",
        "tgn:7005560",
        "tgn:7029392"
    ],
    "tgn:id":7350170,
    "tgn:name":"Ahuelic\u00e1n",
    "tgn:placetype":[
        "aat:300008347"
    ]
},
  "bbox": [],
  "geometry": {"coordinates":[-99.45,18.1],"type":"Point"}
}
=======
{"geometry":{"type":"Point","coordinates":[-99.450000,18.100000]},"type":"Feature","properties":{"hierarchy":["tgn:7350170","tgn:7005585","tgn:1000001","tgn:7005560","tgn:7029392"],"placetype":["aat:300008347"],"id":7350170,"name:xx":"Ahuelic\u00e1n"}}
>>>>>>> 03f74aca74312dbeaf24d7e61306dd6a786dc3d0
