<<<<<<< HEAD
{
  "id": 7484129,
  "type": "Feature",
  "properties": {
    "tgn:hierarchy":[
        "tgn:7484129",
        "tgn:1000004",
        "tgn:7492971",
        "tgn:1000141",
        "tgn:7029392"
    ],
    "tgn:id":7484129,
    "tgn:name":"Xinpi Guoxiao",
    "tgn:placetype":[
        "aat:300006495"
    ]
},
  "bbox": [],
  "geometry": {"coordinates":[120.551111,22.471111],"type":"Point"}
}
=======
{"geometry":{"type":"Point","coordinates":[120.551111,22.471111]},"type":"Feature","properties":{"hierarchy":["tgn:7484129","tgn:1000004","tgn:7492971","tgn:1000141","tgn:7029392"],"placetype":["aat:300006495"],"id":7484129,"name:xx":"Xinpi Guoxiao"}}
>>>>>>> 03f74aca74312dbeaf24d7e61306dd6a786dc3d0
