{
  "id": 2125868,
  "type": "Feature",
  "properties": {
    "tgn:hierarchy":[
        "tgn:2125868",
        "tgn:1000001",
        "tgn:2000263",
        "tgn:7012149",
        "tgn:7007240",
        "tgn:7029392"
    ],
    "tgn:id":2125868,
    "tgn:name":"Adams Lake",
    "tgn:placetype":[
        "aat:300008680"
    ]
},
  "bbox": [],
  "geometry": {"coordinates":[-83.05,29.7167],"type":"Point"}
}