{
  "id": 2613003,
  "type": "Feature",
  "properties": {
    "tgn:hierarchy":[
        "tgn:2613003",
        "tgn:1000001",
        "tgn:7012149",
        "tgn:2002283",
        "tgn:7013961",
        "tgn:7029392"
    ],
    "tgn:id":2613003,
    "tgn:name":"Redrock Crossing",
    "tgn:placetype":[
        "aat:300008347"
    ]
},
  "bbox": [],
  "geometry": {"coordinates":[-78.15,39.6833],"type":"Point"}
}