{
  "id": 7434528,
  "type": "Feature",
  "properties": {
    "tgn:hierarchy":[
        "tgn:7434528",
        "tgn:1000001",
        "tgn:7005595",
        "tgn:7005560",
        "tgn:7029392"
    ],
    "tgn:id":7434528,
    "tgn:name":"Veladero",
    "tgn:placetype":[
        "aat:300008347"
    ]
},
  "bbox": [],
  "geometry": {"coordinates":[-105.916667,23.283333],"type":"Point"}
}