{
  "id": 2643096,
  "type": "Feature",
  "properties": {
    "tgn:hierarchy":[
        "tgn:2643096",
        "tgn:1000001",
        "tgn:7012149",
        "tgn:2000875",
        "tgn:7007256",
        "tgn:7029392"
    ],
    "tgn:id":2643096,
    "tgn:name":"Sandy Branch",
    "tgn:placetype":[
        "aat:300008699"
    ]
},
  "bbox": [],
  "geometry": {"coordinates":[-92.45,31.6167],"type":"Point"}
}