{
  "id": 7368987,
  "type": "Feature",
  "properties": {
    "tgn:hierarchy":[
        "tgn:7368987",
        "tgn:7016644",
        "tgn:1000001",
        "tgn:7005560",
        "tgn:7029392"
    ],
    "tgn:id":7368987,
    "tgn:name":"Horca, Punta",
    "tgn:placetype":[
        "aat:300386846"
    ]
},
  "bbox": [],
  "geometry": {"coordinates":[-110.916667,18.716667],"type":"Point"}
}