{
  "id": 7057845,
  "type": "Feature",
  "properties": {
    "tgn:hierarchy":[
        "tgn:7057845",
        "tgn:7003154",
        "tgn:1000003",
        "tgn:7003120",
        "tgn:1000080",
        "tgn:7029392"
    ],
    "tgn:id":7057845,
    "tgn:name":"Argentiera",
    "tgn:placetype":[
        "aat:300008347"
    ]
},
  "bbox": [],
  "geometry": {"coordinates":[6.933333,44.883333],"type":"Point"}
}