{
  "id": 2495954,
  "type": "Feature",
  "properties": {
    "tgn:hierarchy":[
        "tgn:2495954",
        "tgn:1000001",
        "tgn:7012149",
        "tgn:2001523",
        "tgn:7007709",
        "tgn:7029392"
    ],
    "tgn:id":2495954,
    "tgn:name":"Masonboro Sound",
    "tgn:placetype":[
        "aat:300132316"
    ]
},
  "bbox": [],
  "geometry": {"coordinates":[-77.8333,34.1333],"type":"Point"}
}