{
  "id": 7293973,
  "type": "Feature",
  "properties": {
    "tgn:hierarchy":[
        "tgn:7293973",
        "tgn:7002759",
        "tgn:7008909",
        "tgn:1000003",
        "tgn:1000095",
        "tgn:7029392"
    ],
    "tgn:id":7293973,
    "tgn:name":"Vieja, Sierra",
    "tgn:placetype":[
        "aat:300266640"
    ]
},
  "bbox": [],
  "geometry": {"coordinates":[0.420475,42.551634],"type":"Point"}
}