{
  "id": 2752738,
  "type": "Feature",
  "properties": {
    "tgn:hierarchy":[
        "tgn:2752738",
        "tgn:1000001",
        "tgn:7012149",
        "tgn:2001071",
        "tgn:7007521",
        "tgn:7029392"
    ],
    "tgn:id":2752738,
    "tgn:name":"Watab River",
    "tgn:placetype":[
        "aat:300008707"
    ]
},
  "bbox": [],
  "geometry": {"coordinates":[-94.3167,45.5667],"type":"Point"}
}