{
  "id": 7322034,
  "type": "Feature",
  "properties": {
    "tgn:hierarchy":[
        "tgn:7322034",
        "tgn:1001692",
        "tgn:1000049",
        "tgn:1000002",
        "tgn:7029392"
    ],
    "tgn:id":7322034,
    "tgn:name":"Batuco, Estero",
    "tgn:placetype":[
        "aat:300008699"
    ]
},
  "bbox": [],
  "geometry": {"coordinates":[-72.516667,-38.733333],"type":"Point"}
}