{
  "id": 2474319,
  "type": "Feature",
  "properties": {
    "tgn:hierarchy":[
        "tgn:2474319",
        "tgn:1000001",
        "tgn:7016172",
        "tgn:7012149",
        "tgn:2000156",
        "tgn:7029392"
    ],
    "tgn:id":2474319,
    "tgn:name":"Lower Old River",
    "tgn:placetype":[
        "aat:300008680"
    ]
},
  "bbox": [],
  "geometry": {"coordinates":[-92.8333,33.6333],"type":"Point"}
}