{
  "id": 7396825,
  "type": "Feature",
  "properties": {
    "tgn:hierarchy":[
        "tgn:7396825",
        "tgn:1001853",
        "tgn:1000001",
        "tgn:7005560",
        "tgn:7029392"
    ],
    "tgn:id":7396825,
    "tgn:name":"Rancho San Rafael",
    "tgn:placetype":[
        "aat:300000241"
    ]
},
  "bbox": [],
  "geometry": {"coordinates":[-101.883333,28.316667],"type":"Point"}
}