{
  "id": 2610549,
  "type": "Feature",
  "properties": {
    "tgn:hierarchy":[
        "tgn:2610549",
        "tgn:1000001",
        "tgn:7012149",
        "tgn:1002703",
        "tgn:7007826",
        "tgn:7029392"
    ],
    "tgn:id":2610549,
    "tgn:name":"Red Clifton Branch",
    "tgn:placetype":[
        "aat:300008699"
    ]
},
  "bbox": [],
  "geometry": {"coordinates":[-94.65,31.8167],"type":"Point"}
}