{
  "id": 2603923,
  "type": "Feature",
  "properties": {
    "tgn:hierarchy":[
        "tgn:2603923",
        "tgn:2001732",
        "tgn:1000001",
        "tgn:7012149",
        "tgn:7007712",
        "tgn:7029392"
    ],
    "tgn:id":2603923,
    "tgn:name":"Quimby Creek",
    "tgn:placetype":[
        "aat:300008706"
    ]
},
  "bbox": [],
  "geometry": {"coordinates":[-79.7333,33.0333],"type":"Point"}
}