{
  "id": 2315615,
  "type": "Feature",
  "properties": {
    "tgn:hierarchy":[
        "tgn:2315615",
        "tgn:1000001",
        "tgn:7012149",
        "tgn:7007157",
        "tgn:1002956",
        "tgn:7029392"
    ],
    "tgn:id":2315615,
    "tgn:name":"Ellis Mountain",
    "tgn:placetype":[
        "aat:300008798"
    ]
},
  "bbox": [],
  "geometry": {"coordinates":[-119.0167,36.5333],"type":"Point"}
}