{
  "id": 2296139,
  "type": "Feature",
  "properties": {
    "tgn:hierarchy":[
        "tgn:2296139",
        "tgn:1000001",
        "tgn:7012149",
        "tgn:2000829",
        "tgn:7007255",
        "tgn:7029392"
    ],
    "tgn:id":2296139,
    "tgn:name":"Dry Branch",
    "tgn:placetype":[
        "aat:300008699"
    ]
},
  "bbox": [],
  "geometry": {"coordinates":[-85.7167,36.8333],"type":"Point"}
}