{
  "id": 1026330,
  "type": "Feature",
  "properties": {
    "tgn:hierarchy":[
        "tgn:1026330",
        "tgn:7003457",
        "tgn:1000003",
        "tgn:1000063",
        "tgn:7018236",
        "tgn:7029392"
    ],
    "tgn:id":1026330,
    "tgn:name":"Beveren",
    "tgn:placetype":[
        "aat:300008347"
    ]
},
  "bbox": [],
  "geometry": {"coordinates":[4.25633,51.211872],"type":"Point"}
}