{
  "id": 7097922,
  "type": "Feature",
  "properties": {
    "tgn:hierarchy":[
        "tgn:7097922",
        "tgn:1000003",
        "tgn:7003688",
        "tgn:7000084",
        "tgn:7029392"
    ],
    "tgn:id":7097922,
    "tgn:name":"Sophienkoog",
    "tgn:placetype":[
        "aat:300006163"
    ]
},
  "bbox": [],
  "geometry": {"coordinates":[8.983333,53.966667],"type":"Point"}
}