{
  "id": 2329086,
  "type": "Feature",
  "properties": {
    "tgn:hierarchy":[
        "tgn:2329086",
        "tgn:1000001",
        "tgn:7012149",
        "tgn:2001553",
        "tgn:7007709",
        "tgn:7029392"
    ],
    "tgn:id":2329086,
    "tgn:name":"Fitches Knob",
    "tgn:placetype":[
        "aat:300008798"
    ]
},
  "bbox": [],
  "geometry": {"coordinates":[-80.9833,36.0833],"type":"Point"}
}