{
  "id": 2069575,
  "type": "Feature",
  "properties": {
    "tgn:hierarchy":[
        "tgn:2069575",
        "tgn:1000001",
        "tgn:1002328",
        "tgn:7012149",
        "tgn:7007568",
        "tgn:7029392"
    ],
    "tgn:id":2069575,
    "tgn:name":"Hancock",
    "tgn:placetype":[
        "aat:300008347"
    ]
},
  "bbox": [],
  "geometry": {"coordinates":[-75.2667,41.95],"type":"Point"}
}