{
  "id": 7212226,
  "type": "Feature",
  "properties": {
    "tgn:hierarchy":[
        "tgn:7212226",
        "tgn:7003669",
        "tgn:1000003",
        "tgn:7000084",
        "tgn:7029392"
    ],
    "tgn:id":7212226,
    "tgn:name":"Bihls",
    "tgn:placetype":[
        "aat:300008347"
    ]
},
  "bbox": [],
  "geometry": {"coordinates":[10.166667,47.833333],"type":"Point"}
}