{
  "id": 2216502,
  "type": "Feature",
  "properties": {
    "tgn:hierarchy":[
        "tgn:2216502",
        "tgn:1000001",
        "tgn:2000955",
        "tgn:7012149",
        "tgn:7007520",
        "tgn:7029392"
    ],
    "tgn:id":2216502,
    "tgn:name":"Camp Creek",
    "tgn:placetype":[
        "aat:300008706"
    ]
},
  "bbox": [],
  "geometry": {"coordinates":[-87.2667,45.9333],"type":"Point"}
}