{
  "id": 7590301,
  "type": "Feature",
  "properties": {
    "tgn:hierarchy":[
        "tgn:7590301",
        "tgn:1000004",
        "tgn:7000198",
        "tgn:7000799",
        "tgn:7029392"
    ],
    "tgn:id":7590301,
    "tgn:name:en":"Kuli\u0101n ka Katha",
    "tgn:placetype":[
        "aat:300008699"
    ]
},
  "bbox": [],
  "geometry": {"coordinates":[74.309046,33.813256],"type":"Point"}
}