{
  "id": 2520399,
  "type": "Feature",
  "properties": {
    "tgn:hierarchy":[
        "tgn:2520399",
        "tgn:1002247",
        "tgn:1000001",
        "tgn:7012149",
        "tgn:7007516",
        "tgn:7029392"
    ],
    "tgn:id":2520399,
    "tgn:name":"Money Creek",
    "tgn:placetype":[
        "aat:300008706"
    ]
},
  "bbox": [],
  "geometry": {"coordinates":[-75.9667,39.3833],"type":"Point"}
}