{
  "id": 2383771,
  "type": "Feature",
  "properties": {
    "tgn:hierarchy":[
        "tgn:2383771",
        "tgn:1000001",
        "tgn:7012149",
        "tgn:7029392"
    ],
    "tgn:id":2383771,
    "tgn:name":"Heckel Creek",
    "tgn:placetype":[
        "aat:300008706"
    ]
},
  "bbox": [],
  "geometry": {"coordinates":[-101.7333,42.9833],"type":"Point"}
}