{
  "id": 2777736,
  "type": "Feature",
  "properties": {
    "tgn:hierarchy":[
        "tgn:2777736",
        "tgn:1000001",
        "tgn:7012149",
        "tgn:2001930",
        "tgn:7007825",
        "tgn:7029392"
    ],
    "tgn:id":2777736,
    "tgn:name":"Winstead Hill",
    "tgn:placetype":[
        "aat:300008798"
    ]
},
  "bbox": [],
  "geometry": {"coordinates":[-86.8833,35.8833],"type":"Point"}
}