{
  "id": 7341643,
  "type": "Feature",
  "properties": {
    "tgn:hierarchy":[
        "tgn:7341643",
        "tgn:7002758",
        "tgn:7002823",
        "tgn:1000003",
        "tgn:1000095",
        "tgn:7029392"
    ],
    "tgn:id":7341643,
    "tgn:name":"Bernab\u00e9, Arroyo de",
    "tgn:placetype":[
        "aat:300266554",
        "aat:300008699"
    ]
},
  "bbox": [],
  "geometry": {"coordinates":[-6.516667,37.133333],"type":"Point"}
}