{
  "id": 7420441,
  "type": "Feature",
  "properties": {
    "tgn:hierarchy":[
        "tgn:7420441",
        "tgn:7005579",
        "tgn:1000001",
        "tgn:7005560",
        "tgn:7029392"
    ],
    "tgn:id":7420441,
    "tgn:name":"La M\u00e1quina",
    "tgn:placetype":[
        "aat:300008347"
    ]
},
  "bbox": [],
  "geometry": {"coordinates":[-102.295833,22.0375],"type":"Point"}
}