{
  "id": 2545029,
  "type": "Feature",
  "properties": {
    "tgn:hierarchy":[
        "tgn:2545029",
        "tgn:1000001",
        "tgn:7012149",
        "tgn:1002401",
        "tgn:7007826",
        "tgn:7029392"
    ],
    "tgn:id":2545029,
    "tgn:name":"North Deer Island",
    "tgn:placetype":[
        "aat:300008791"
    ]
},
  "bbox": [],
  "geometry": {"coordinates":[-94.9167,29.2833],"type":"Point"}
}