{
  "id": 2149129,
  "type": "Feature",
  "properties": {
    "tgn:hierarchy":[
        "tgn:2149129",
        "tgn:1000001",
        "tgn:7012149",
        "tgn:2002381",
        "tgn:7007923",
        "tgn:7029392"
    ],
    "tgn:id":2149129,
    "tgn:name":"Barr Draw",
    "tgn:placetype":[
        "aat:300008761"
    ]
},
  "bbox": [],
  "geometry": {"coordinates":[-106.6667,44.5667],"type":"Point"}
}