{
  "id": 7277085,
  "type": "Feature",
  "properties": {
    "tgn:hierarchy":[
        "tgn:7277085",
        "tgn:7002464",
        "tgn:1000049",
        "tgn:1000002",
        "tgn:7029392"
    ],
    "tgn:id":7277085,
    "tgn:name":"Pahuta, Pampa",
    "tgn:placetype":[
        "aat:300008805"
    ]
},
  "bbox": [],
  "geometry": {"coordinates":[-69.579167,-17.881667],"type":"Point"}
}