<<<<<<< HEAD
{
  "id": 2156427,
  "type": "Feature",
  "properties": {
    "tgn:hierarchy":[
        "tgn:2156427",
        "tgn:1000001",
        "tgn:7012149",
        "tgn:2001535",
        "tgn:7007709",
        "tgn:7029392"
    ],
    "tgn:id":2156427,
    "tgn:name":"Bearslide",
    "tgn:placetype":[
        "aat:300008347"
    ]
},
  "bbox": [],
  "geometry": {"coordinates":[-79.7333,36.4833],"type":"Point"}
}
=======
{"geometry":{"type":"Point","coordinates":[-79.733300,36.483300]},"type":"Feature","properties":{"hierarchy":["tgn:2156427","tgn:1000001","tgn:7012149","tgn:2001535","tgn:7007709","tgn:7029392"],"placetype":["aat:300008347"],"id":2156427,"name:xx":"Bearslide"}}
>>>>>>> 03f74aca74312dbeaf24d7e61306dd6a786dc3d0
