{
  "id": 7192484,
  "type": "Feature",
  "properties": {
    "tgn:hierarchy":[
        "tgn:7192484",
        "tgn:1000003",
        "tgn:7003677",
        "tgn:7000084",
        "tgn:7029392"
    ],
    "tgn:id":7192484,
    "tgn:name":"Flinsbach",
    "tgn:placetype":[
        "aat:300008347"
    ]
},
  "bbox": [],
  "geometry": {"coordinates":[7.466667,51.466667],"type":"Point"}
}