{
  "id": 7036158,
  "type": "Feature",
  "properties": {
    "tgn:hierarchy":[
        "tgn:7036158",
        "tgn:1003505",
        "tgn:1000003",
        "tgn:7002993",
        "tgn:1000080",
        "tgn:7029392"
    ],
    "tgn:id":7036158,
    "tgn:name":"Fernetti",
    "tgn:placetype":[
        "aat:300008347"
    ]
},
  "bbox": [],
  "geometry": {"coordinates":[13.829167,45.697222],"type":"Point"}
}