{
  "id": 7034352,
  "type": "Feature",
  "properties": {
    "tgn:hierarchy":[
        "tgn:7034352",
        "tgn:1001641",
        "tgn:1000003",
        "tgn:7003121",
        "tgn:1000080",
        "tgn:7029392"
    ],
    "tgn:id":7034352,
    "tgn:name":"Camisa",
    "tgn:placetype":[
        "aat:300008347"
    ]
},
  "bbox": [],
  "geometry": {"coordinates":[9.5225,39.297778],"type":"Point"}
}