{
  "id": 1078021,
  "type": "Feature",
  "properties": {
    "tgn:hierarchy":[
        "tgn:1078021",
        "tgn:1000004",
        "tgn:1001550",
        "tgn:1000116",
        "tgn:7029392"
    ],
    "tgn:id":1078021,
    "tgn:name":"Lombagin",
    "tgn:placetype":[
        "aat:300008347"
    ]
},
  "bbox": [],
  "geometry": {"coordinates":[124.0667,0.9167],"type":"Point"}
}