{
  "id": 7519053,
  "type": "Feature",
  "properties": {
    "tgn:hierarchy":[
        "tgn:7519053",
        "tgn:1009227",
        "tgn:1000226",
        "tgn:1000006",
        "tgn:7016850",
        "tgn:7029392"
    ],
    "tgn:id":7519053,
    "tgn:name:en":"Browns Creek",
    "tgn:placetype":[
        "aat:300008699"
    ]
},
  "bbox": [],
  "geometry": {"coordinates":[171.766667,-42.333333],"type":"Point"}
}