{
  "id": 7286619,
  "type": "Feature",
  "properties": {
    "tgn:hierarchy":[
        "tgn:7286619",
        "tgn:1001623",
        "tgn:1000049",
        "tgn:1000002",
        "tgn:7029392"
    ],
    "tgn:id":7286619,
    "tgn:name":"Guillermo, Islote",
    "tgn:placetype":[
        "aat:300008791"
    ]
},
  "bbox": [],
  "geometry": {"coordinates":[-74.716667,-45.766667],"type":"Point"}
}