{
  "id": 7045345,
  "type": "Feature",
  "properties": {
    "tgn:hierarchy":[
        "tgn:7045345",
        "tgn:7003162",
        "tgn:1000003",
        "tgn:7009760",
        "tgn:1000080",
        "tgn:7029392"
    ],
    "tgn:id":7045345,
    "tgn:name":"Calla, Passo la",
    "tgn:placetype":[
        "aat:300259572"
    ]
},
  "bbox": [],
  "geometry": {"coordinates":[11.733333,43.833333],"type":"Point"}
}