{
  "id": 1011926,
  "type": "Feature",
  "properties": {
    "tgn:hierarchy":[
        "tgn:1011926",
        "tgn:7593359",
        "tgn:1000001",
        "tgn:7005562",
        "tgn:7029392"
    ],
    "tgn:id":1011926,
    "tgn:name":"Punta Grindston Bay",
    "tgn:placetype":[
        "aat:300386846"
    ]
},
  "bbox": [],
  "geometry": {"coordinates":[-83.799,11.441],"type":"Point"}
}