{
  "id": 2216118,
  "type": "Feature",
  "properties": {
    "tgn:hierarchy":[
        "tgn:2216118",
        "tgn:7016099",
        "tgn:1000001",
        "tgn:7012149",
        "tgn:7007516",
        "tgn:7029392"
    ],
    "tgn:id":2216118,
    "tgn:name":"Camp Alkor Spring",
    "tgn:placetype":[
        "aat:300008697"
    ]
},
  "bbox": [],
  "geometry": {"coordinates":[-76.6333,39.5833],"type":"Point"}
}