{
  "id": 2762592,
  "type": "Feature",
  "properties": {
    "tgn:hierarchy":[
        "tgn:2762592",
        "tgn:1000001",
        "tgn:7012149",
        "tgn:2002129",
        "tgn:7007827",
        "tgn:7029392"
    ],
    "tgn:id":2762592,
    "tgn:name":"Westbrook",
    "tgn:placetype":[
        "aat:300008347"
    ]
},
  "bbox": [],
  "geometry": {"coordinates":[-112.05,41.15],"type":"Point"}
}