{
  "id": 7501066,
  "type": "Feature",
  "properties": {
    "tgn:hierarchy":[
        "tgn:7501066",
        "tgn:7001004",
        "tgn:1000004",
        "tgn:1000141",
        "tgn:7029392"
    ],
    "tgn:id":7501066,
    "tgn:name":"Xinpiziwei",
    "tgn:placetype":[
        "aat:300008347"
    ]
},
  "bbox": [],
  "geometry": {"coordinates":[120.325278,22.86],"type":"Point"}
}