{
  "id": 7435865,
  "type": "Feature",
  "properties": {
    "tgn:hierarchy":[
        "tgn:7435865",
        "tgn:1000001",
        "tgn:7005597",
        "tgn:7005560",
        "tgn:7029392"
    ],
    "tgn:id":7435865,
    "tgn:name":"San Vicente",
    "tgn:placetype":[
        "aat:300008347"
    ]
},
  "bbox": [],
  "geometry": {"coordinates":[-98.666667,23.416667],"type":"Point"}
}