{
  "id": 7533398,
  "type": "Feature",
  "properties": {
    "tgn:hierarchy":[
        "tgn:7533398",
        "tgn:7001242",
        "tgn:7016833",
        "tgn:1001418",
        "tgn:7029392"
    ],
    "tgn:id":7533398,
    "tgn:name:en":"\u1e28\u0101mid, W\u0101d\u012b",
    "tgn:placetype":[
        "aat:300379998"
    ]
},
  "bbox": [],
  "geometry": {"coordinates":[26.526006,29.161045],"type":"Point"}
}