{
  "id": 7505551,
  "type": "Feature",
  "properties": {
    "tgn:hierarchy":[
        "tgn:7505551",
        "tgn:1009227",
        "tgn:1000226",
        "tgn:7016822",
        "tgn:1000006",
        "tgn:7029392"
    ],
    "tgn:id":7505551,
    "tgn:name:en":"Whare Creek",
    "tgn:placetype":[
        "aat:300008699"
    ]
},
  "bbox": [],
  "geometry": {"coordinates":[167.683333,-45.633333],"type":"Point"}
}