{
  "id": 2617010,
  "type": "Feature",
  "properties": {
    "tgn:hierarchy":[
        "tgn:2617010",
        "tgn:1000001",
        "tgn:7012149",
        "tgn:7007256",
        "tgn:7029392"
    ],
    "tgn:id":2617010,
    "tgn:name":"Richards Gully",
    "tgn:placetype":[
        "aat:300008699"
    ]
},
  "bbox": [],
  "geometry": {"coordinates":[-92.4333,30.4833],"type":"Point"}
}