{
  "id": 7275702,
  "type": "Feature",
  "properties": {
    "tgn:hierarchy":[
        "tgn:7275702",
        "tgn:1001699",
        "tgn:1000049",
        "tgn:1000002",
        "tgn:7029392"
    ],
    "tgn:id":7275702,
    "tgn:name":"Trapi",
    "tgn:placetype":[
        "aat:300008347"
    ]
},
  "bbox": [],
  "geometry": {"coordinates":[-72.633333,-40.316667],"type":"Point"}
}