{
  "id": 2161340,
  "type": "Feature",
  "properties": {
    "tgn:hierarchy":[
        "tgn:2161340",
        "tgn:1000001",
        "tgn:2001411",
        "tgn:7012149",
        "tgn:7007526",
        "tgn:7029392"
    ],
    "tgn:id":2161340,
    "tgn:name":"Bell Mine",
    "tgn:placetype":[
        "aat:300000390"
    ]
},
  "bbox": [],
  "geometry": {"coordinates":[-114.5833,41.6333],"type":"Point"}
}