{
  "id": 2423106,
  "type": "Feature",
  "properties": {
    "tgn:hierarchy":[
        "tgn:2423106",
        "tgn:1000001",
        "tgn:7012149",
        "tgn:2000238",
        "tgn:7007158",
        "tgn:7029392"
    ],
    "tgn:id":2423106,
    "tgn:name":"Joe Wilson Recreation Reservoir",
    "tgn:placetype":[
        "aat:300006191"
    ]
},
  "bbox": [],
  "geometry": {"coordinates":[-105.3167,38.9333],"type":"Point"}
}