<<<<<<< HEAD
{
  "id": 7174050,
  "type": "Feature",
  "properties": {
    "tgn:hierarchy":[
        "tgn:7174050",
        "tgn:7003692",
        "tgn:1000003",
        "tgn:7000084",
        "tgn:7029392"
    ],
    "tgn:id":7174050,
    "tgn:name":"Grunbach",
    "tgn:placetype":[
        "aat:300008699"
    ]
},
  "bbox": [],
  "geometry": {"coordinates":[8.733333,48.3],"type":"Point"}
}
=======
{"geometry":{"type":"Point","coordinates":[8.733333,48.300000]},"type":"Feature","properties":{"hierarchy":["tgn:7174050","tgn:7003692","tgn:1000003","tgn:7000084","tgn:7029392"],"placetype":["aat:300008699"],"id":7174050,"name:xx":"Grunbach"}}
>>>>>>> 03f74aca74312dbeaf24d7e61306dd6a786dc3d0
