{
  "id": 7212725,
  "type": "Feature",
  "properties": {
    "tgn:hierarchy":[
        "tgn:7212725",
        "tgn:1000003",
        "tgn:7003688",
        "tgn:7000084",
        "tgn:7029392"
    ],
    "tgn:id":7212725,
    "tgn:name":"Bokni\u00df-Eck",
    "tgn:placetype":[
        "aat:300386846"
    ]
},
  "bbox": [],
  "geometry": {"coordinates":[10.033333,54.55],"type":"Point"}
}