{
  "id": 1085990,
  "type": "Feature",
  "properties": {
    "tgn:hierarchy":[
        "tgn:1085990",
        "tgn:1001287",
        "tgn:7018452",
        "tgn:1000004",
        "tgn:1000144",
        "tgn:7029392"
    ],
    "tgn:id":1085990,
    "tgn:name":"Arsuz",
    "tgn:placetype":[
        "aat:300008347"
    ]
},
  "bbox": [],
  "geometry": {"coordinates":[35.85,36.4333],"type":"Point"}
}