{
  "id": 7463330,
  "type": "Feature",
  "properties": {
    "tgn:hierarchy":[
        "tgn:7463330",
        "tgn:7002445",
        "tgn:1000003",
        "tgn:7012032",
        "tgn:7008591",
        "tgn:7029392"
    ],
    "tgn:id":7463330,
    "tgn:name:en":"Hurcot",
    "tgn:placetype":[
        "aat:300008347"
    ]
},
  "bbox": [],
  "geometry": {"coordinates":[-2.708889,51.064722],"type":"Point"}
}