{
  "id": 2435339,
  "type": "Feature",
  "properties": {
    "tgn:hierarchy":[
        "tgn:2435339",
        "tgn:1000001",
        "tgn:7012149",
        "tgn:7007158",
        "tgn:2000246",
        "tgn:7029392"
    ],
    "tgn:id":2435339,
    "tgn:name":"Kerber Creek",
    "tgn:placetype":[
        "aat:300008706"
    ]
},
  "bbox": [],
  "geometry": {"coordinates":[-106.1833,38.3333],"type":"Point"}
}