{
  "id": 7138379,
  "type": "Feature",
  "properties": {
    "tgn:hierarchy":[
        "tgn:7138379",
        "tgn:1000003",
        "tgn:7003689",
        "tgn:7000084",
        "tgn:7029392"
    ],
    "tgn:id":7138379,
    "tgn:name":"Lichters-Berg",
    "tgn:placetype":[
        "aat:300008777"
    ]
},
  "bbox": [],
  "geometry": {"coordinates":[11.583333,50.866667],"type":"Point"}
}