{
  "id": 7040078,
  "type": "Feature",
  "properties": {
    "tgn:hierarchy":[
        "tgn:7040078",
        "tgn:1003489",
        "tgn:7004610",
        "tgn:1000003",
        "tgn:1000080",
        "tgn:7029392"
    ],
    "tgn:id":7040078,
    "tgn:name":"Scarpaleggia",
    "tgn:placetype":[
        "aat:300008347"
    ]
},
  "bbox": [],
  "geometry": {"coordinates":[16.066667,39.983333],"type":"Point"}
}