{
  "id": 2605501,
  "type": "Feature",
  "properties": {
    "tgn:hierarchy":[
        "tgn:2605501",
        "tgn:1000001",
        "tgn:7012149",
        "tgn:1002376",
        "tgn:7007252",
        "tgn:7029392"
    ],
    "tgn:id":2605501,
    "tgn:name":"Rail Run",
    "tgn:placetype":[
        "aat:300008699"
    ]
},
  "bbox": [],
  "geometry": {"coordinates":[-85.8167,38.3333],"type":"Point"}
}