{
  "id": 2715146,
  "type": "Feature",
  "properties": {
    "tgn:hierarchy":[
        "tgn:2715146",
        "tgn:1000001",
        "tgn:2001093",
        "tgn:7012149",
        "tgn:7007522",
        "tgn:7029392"
    ],
    "tgn:id":2715146,
    "tgn:name":"Teoc Creek",
    "tgn:placetype":[
        "aat:300008706"
    ]
},
  "bbox": [],
  "geometry": {"coordinates":[-89.9333,33.5833],"type":"Point"}
}