{
  "id": 1092644,
  "type": "Feature",
  "properties": {
    "tgn:hierarchy":[
        "tgn:1092644",
        "tgn:7001242",
        "tgn:1001759",
        "tgn:1000192",
        "tgn:7029392"
    ],
    "tgn:id":1092644,
    "tgn:name":"Buuhoodle",
    "tgn:placetype":[
        "aat:300008347"
    ]
},
  "bbox": [],
  "geometry": {"coordinates":[46.3333,8.1833],"type":"Point"}
}