{
  "id": 7457322,
  "type": "Feature",
  "properties": {
    "tgn:hierarchy":[
        "tgn:7457322",
        "tgn:7002445",
        "tgn:1000003",
        "tgn:7008143",
        "tgn:7008591",
        "tgn:7029392"
    ],
    "tgn:id":7457322,
    "tgn:name:en":"Peterchurch",
    "tgn:placetype":[
        "aat:300008347"
    ]
},
  "bbox": [],
  "geometry": {"coordinates":[-2.95,52.033333],"type":"Point"}
}