<<<<<<< HEAD
{
  "id": 7483271,
  "type": "Feature",
  "properties": {
    "tgn:hierarchy":[
        "tgn:7483271",
        "tgn:1000004",
        "tgn:7491221",
        "tgn:1000141",
        "tgn:7029392"
    ],
    "tgn:id":7483271,
    "tgn:name":"Huzhang Shan",
    "tgn:placetype":[
        "aat:300008798"
    ]
},
  "bbox": [],
  "geometry": {"coordinates":[121.0,22.785556],"type":"Point"}
}
=======
{"geometry":{"type":"Point","coordinates":[121.000000,22.785556]},"type":"Feature","properties":{"hierarchy":["tgn:7483271","tgn:1000004","tgn:7491221","tgn:1000141","tgn:7029392"],"placetype":["aat:300008798"],"id":7483271,"name:xx":"Huzhang Shan"}}
>>>>>>> 03f74aca74312dbeaf24d7e61306dd6a786dc3d0
