{
  "id": 7564511,
  "type": "Feature",
  "properties": {
    "tgn:hierarchy":[
        "tgn:7564511",
        "tgn:1000004",
        "tgn:7000198",
        "tgn:7016722",
        "tgn:7029392"
    ],
    "tgn:id":7564511,
    "tgn:name:en":"Shankarpur Gaon Mustaqil",
    "tgn:placetype":[
        "aat:300008347"
    ]
},
  "bbox": [],
  "geometry": {"coordinates":[79.476047,26.42001],"type":"Point"}
}