{
  "id": 2610376,
  "type": "Feature",
  "properties": {
    "tgn:hierarchy":[
        "tgn:2610376",
        "tgn:1000001",
        "tgn:2001585",
        "tgn:7012149",
        "tgn:7007705",
        "tgn:7029392"
    ],
    "tgn:id":2610376,
    "tgn:name":"Red Butte Bay",
    "tgn:placetype":[
        "aat:300132316"
    ]
},
  "bbox": [],
  "geometry": {"coordinates":[-102.0833,47.5333],"type":"Point"}
}