{
  "id": 2219275,
  "type": "Feature",
  "properties": {
    "tgn:hierarchy":[
        "tgn:2219275",
        "tgn:2000919",
        "tgn:1000001",
        "tgn:7012149",
        "tgn:7007515",
        "tgn:7029392"
    ],
    "tgn:id":2219275,
    "tgn:name":"Caniba Brook",
    "tgn:placetype":[
        "aat:300008699"
    ]
},
  "bbox": [],
  "geometry": {"coordinates":[-68.0667,47.1167],"type":"Point"}
}