{
  "id": 2016253,
  "type": "Feature",
  "properties": {
    "tgn:hierarchy":[
        "tgn:2016253",
        "tgn:1000001",
        "tgn:7012149",
        "tgn:2000229",
        "tgn:7007158",
        "tgn:7029392"
    ],
    "tgn:id":2016253,
    "tgn:name":"Saint Petersburg",
    "tgn:placetype":[
        "aat:300008347",
        "aat:300387210"
    ]
},
  "bbox": [],
  "geometry": {"coordinates":[-102.8167,40.55],"type":"Point"}
}