{
  "id": 7415220,
  "type": "Feature",
  "properties": {
    "tgn:hierarchy":[
        "tgn:7415220",
        "tgn:7005584",
        "tgn:1000001",
        "tgn:7005560",
        "tgn:7029392"
    ],
    "tgn:id":7415220,
    "tgn:name":"La Pur\u00edsima",
    "tgn:placetype":[
        "aat:300008347"
    ]
},
  "bbox": [],
  "geometry": {"coordinates":[-101.238056,20.201389],"type":"Point"}
}