<<<<<<< HEAD
{
  "id": 7021935,
  "type": "Feature",
  "properties": {
    "tgn:hierarchy":[
        "tgn:7021935",
        "tgn:1000001",
        "tgn:7012149",
        "tgn:7007919",
        "tgn:7029392"
    ],
    "tgn:id":7021935,
    "tgn:name":"Big Swamp, The",
    "tgn:placetype":[
        "aat:300008699"
    ]
},
  "bbox": [],
  "geometry": {"coordinates":[-76.9167,38.1333],"type":"Point"}
}
=======
{"geometry":{"type":"Point","coordinates":[-76.916700,38.133300]},"type":"Feature","properties":{"hierarchy":["tgn:7021935","tgn:1000001","tgn:7012149","tgn:7007919","tgn:7029392"],"placetype":["aat:300008699"],"id":7021935,"name:xx":"Big Swamp, The"}}
>>>>>>> 03f74aca74312dbeaf24d7e61306dd6a786dc3d0
