{
  "id": 2466816,
  "type": "Feature",
  "properties": {
    "tgn:hierarchy":[
        "tgn:2466816",
        "tgn:1000001",
        "tgn:7012149",
        "tgn:2001710",
        "tgn:7007708",
        "tgn:7029392"
    ],
    "tgn:id":2466816,
    "tgn:name":"Long Branch Creek",
    "tgn:placetype":[
        "aat:300008706"
    ]
},
  "bbox": [],
  "geometry": {"coordinates":[-121.75,45.5667],"type":"Point"}
}