{
  "id": 2345815,
  "type": "Feature",
  "properties": {
    "tgn:hierarchy":[
        "tgn:2345815",
        "tgn:1000001",
        "tgn:7012149",
        "tgn:1002913",
        "tgn:7007919",
        "tgn:7029392"
    ],
    "tgn:id":2345815,
    "tgn:name":"Garrisonville Estates",
    "tgn:placetype":[
        "aat:300008347"
    ]
},
  "bbox": [],
  "geometry": {"coordinates":[-77.4667,38.4667],"type":"Point"}
}