<<<<<<< HEAD
{
  "id": 2253106,
  "type": "Feature",
  "properties": {
    "tgn:hierarchy":[
        "tgn:2253106",
        "tgn:7006450",
        "tgn:1000001",
        "tgn:7030517",
        "tgn:7012149",
        "tgn:7029392"
    ],
    "tgn:id":2253106,
    "tgn:name":"Contact Creek",
    "tgn:placetype":[
        "aat:300008706"
    ]
},
  "bbox": [],
  "geometry": {"coordinates":[-155.6,58.3167],"type":"Point"}
}
=======
{"geometry":{"type":"Point","coordinates":[-155.600000,58.316700]},"type":"Feature","properties":{"hierarchy":["tgn:2253106","tgn:7006450","tgn:1000001","tgn:7030517","tgn:7012149","tgn:7029392"],"placetype":["aat:300008706"],"id":2253106,"name:xx":"Contact Creek"}}
>>>>>>> 03f74aca74312dbeaf24d7e61306dd6a786dc3d0
