{
  "id": 7282174,
  "type": "Feature",
  "properties": {
    "tgn:hierarchy":[
        "tgn:7282174",
        "tgn:1001702",
        "tgn:1000049",
        "tgn:1000002",
        "tgn:7029392"
    ],
    "tgn:id":7282174,
    "tgn:name":"Sarita, Laguna",
    "tgn:placetype":[
        "aat:300008680"
    ]
},
  "bbox": [],
  "geometry": {"coordinates":[-70.066667,-52.983333],"type":"Point"}
}