{
  "id": 2344112,
  "type": "Feature",
  "properties": {
    "tgn:hierarchy":[
        "tgn:2344112",
        "tgn:1000001",
        "tgn:2002368",
        "tgn:7012149",
        "tgn:7007923",
        "tgn:7029392"
    ],
    "tgn:id":2344112,
    "tgn:name":"Gamblers Reservoir",
    "tgn:placetype":[
        "aat:300006191"
    ]
},
  "bbox": [],
  "geometry": {"coordinates":[-107.7667,41.05],"type":"Point"}
}