{
  "id": 2538159,
  "type": "Feature",
  "properties": {
    "tgn:hierarchy":[
        "tgn:2538159",
        "tgn:2000999",
        "tgn:1000001",
        "tgn:7012149",
        "tgn:7007521",
        "tgn:7029392"
    ],
    "tgn:id":2538159,
    "tgn:name":"Nelson Lake",
    "tgn:placetype":[
        "aat:300008680"
    ]
},
  "bbox": [],
  "geometry": {"coordinates":[-93.0833,46.6167],"type":"Point"}
}