{
  "id": 2471373,
  "type": "Feature",
  "properties": {
    "tgn:hierarchy":[
        "tgn:2471373",
        "tgn:1000001",
        "tgn:7012149",
        "tgn:1002396",
        "tgn:7007252",
        "tgn:7029392"
    ],
    "tgn:id":2471373,
    "tgn:name":"Lost Lake",
    "tgn:placetype":[
        "aat:300008680"
    ]
},
  "bbox": [],
  "geometry": {"coordinates":[-85.95,41.0167],"type":"Point"}
}