<<<<<<< HEAD
{
  "id": 7245971,
  "type": "Feature",
  "properties": {
    "tgn:hierarchy":[
        "tgn:7245971",
        "tgn:7007877",
        "tgn:1000003",
        "tgn:1000063",
        "tgn:4012014",
        "tgn:7029392"
    ],
    "tgn:id":7245971,
    "tgn:name":"Bonne Haie",
    "tgn:placetype":[
        "aat:300008347"
    ]
},
  "bbox": [],
  "geometry": {"coordinates":[4.009063,50.635867],"type":"Point"}
}
=======
{"geometry":{"type":"Point","coordinates":[4.009063,50.635867]},"type":"Feature","properties":{"hierarchy":["tgn:7245971","tgn:7007877","tgn:1000003","tgn:1000063","tgn:4012014","tgn:7029392"],"placetype":["aat:300008347"],"id":7245971,"name:xx":"Bonne Haie"}}
>>>>>>> 03f74aca74312dbeaf24d7e61306dd6a786dc3d0
