{
  "id": 2630893,
  "type": "Feature",
  "properties": {
    "tgn:hierarchy":[
        "tgn:2630893",
        "tgn:1000001",
        "tgn:2001360",
        "tgn:7012149",
        "tgn:7007525",
        "tgn:7029392"
    ],
    "tgn:id":2630893,
    "tgn:name":"Round Lake",
    "tgn:placetype":[
        "aat:300008680"
    ]
},
  "bbox": [],
  "geometry": {"coordinates":[-99.0333,42.2333],"type":"Point"}
}