<<<<<<< HEAD
{
  "id": 7020716,
  "type": "Feature",
  "properties": {
    "tgn:hierarchy":[
        "tgn:7020716",
        "tgn:1002234",
        "tgn:1000001",
        "tgn:7012149",
        "tgn:7007516",
        "tgn:7029392"
    ],
    "tgn:id":7020716,
    "tgn:name":"Smithville Lake",
    "tgn:placetype":[
        "aat:300006191"
    ]
},
  "bbox": [],
  "geometry": {"coordinates":[-75.7167,38.7667],"type":"Point"}
}
=======
{"geometry":{"type":"Point","coordinates":[-75.716700,38.766700]},"type":"Feature","properties":{"hierarchy":["tgn:7020716","tgn:1002234","tgn:1000001","tgn:7012149","tgn:7007516","tgn:7029392"],"placetype":["aat:300006191"],"id":7020716,"name:xx":"Smithville Lake"}}
>>>>>>> 03f74aca74312dbeaf24d7e61306dd6a786dc3d0
