{
  "id": 7020716,
  "type": "Feature",
  "properties": {
    "tgn:hierarchy":[
        "tgn:7020716",
        "tgn:1002234",
        "tgn:1000001",
        "tgn:7012149",
        "tgn:7007516",
        "tgn:7029392"
    ],
    "tgn:id":7020716,
    "tgn:name":"Smithville Lake",
    "tgn:placetype":[
        "aat:300006191"
    ]
},
  "bbox": [],
  "geometry": {"coordinates":[-75.7167,38.7667],"type":"Point"}
}