{
  "id": 1023792,
  "type": "Feature",
  "properties": {
    "tgn:hierarchy":[
        "tgn:1023792",
        "tgn:1000529",
        "tgn:1000050",
        "tgn:1000002",
        "tgn:7029392"
    ],
    "tgn:id":1023792,
    "tgn:name":"El Carmen de Bol\u00edvar",
    "tgn:placetype":[
        "aat:300008347"
    ]
},
  "bbox": [],
  "geometry": {"coordinates":[-75.1333,9.7167],"type":"Point"}
}