<<<<<<< HEAD
{
  "id": 7024063,
  "type": "Feature",
  "properties": {
    "tgn:hierarchy":[
        "tgn:7024063",
        "tgn:1000004",
        "tgn:7006651",
        "tgn:7029392"
    ],
    "tgn:id":7024063,
    "tgn:name":"Pemzashen Lerrants'k'",
    "tgn:placetype":[
        "aat:300259572"
    ]
},
  "bbox": [],
  "geometry": {"coordinates":[45.3,40.5667],"type":"Point"}
}
=======
{"geometry":{"type":"Point","coordinates":[45.300000,40.566700]},"type":"Feature","properties":{"hierarchy":["tgn:7024063","tgn:1000004","tgn:7006651","tgn:7029392"],"placetype":["aat:300259572"],"id":7024063,"name:xx":"Pemzashen Lerrants'k'"}}
>>>>>>> 03f74aca74312dbeaf24d7e61306dd6a786dc3d0
