{
  "id": 2588146,
  "type": "Feature",
  "properties": {
    "tgn:hierarchy":[
        "tgn:2588146",
        "tgn:1000001",
        "tgn:7012149",
        "tgn:2001979",
        "tgn:7007826",
        "tgn:7029392"
    ],
    "tgn:id":2588146,
    "tgn:name":"Plover Lake",
    "tgn:placetype":[
        "aat:300008680"
    ]
},
  "bbox": [],
  "geometry": {"coordinates":[-102.5333,31.95],"type":"Point"}
}