{
  "id": 7378221,
  "type": "Feature",
  "properties": {
    "tgn:hierarchy":[
        "tgn:7378221",
        "tgn:1000001",
        "tgn:1001960",
        "tgn:7005560",
        "tgn:7029392"
    ],
    "tgn:id":7378221,
    "tgn:name":"Rancho La Volanta",
    "tgn:placetype":[
        "aat:300000241"
    ]
},
  "bbox": [],
  "geometry": {"coordinates":[-109.666667,29.766667],"type":"Point"}
}