{
  "id": 7498223,
  "type": "Feature",
  "properties": {
    "tgn:hierarchy":[
        "tgn:7498223",
        "tgn:1000004",
        "tgn:7467799",
        "tgn:1000141",
        "tgn:7029392"
    ],
    "tgn:id":7498223,
    "tgn:name":"Fushan Guoxiao",
    "tgn:placetype":[
        "aat:300006495"
    ]
},
  "bbox": [],
  "geometry": {"coordinates":[120.618847,24.027144],"type":"Point"}
}