{
  "id": 2271273,
  "type": "Feature",
  "properties": {
    "tgn:hierarchy":[
        "tgn:2271273",
        "tgn:1000001",
        "tgn:1002276",
        "tgn:7012149",
        "tgn:7007708",
        "tgn:7029392"
    ],
    "tgn:id":2271273,
    "tgn:name":"Cullaby Slough",
    "tgn:placetype":[
        "aat:300008699"
    ]
},
  "bbox": [],
  "geometry": {"coordinates":[-123.8833,46.05],"type":"Point"}
}