{
  "id": 1000349,
  "type": "Feature",
  "properties": {
    "tgn:hierarchy":[
        "tgn:1000349",
        "tgn:1000003",
        "tgn:1000091",
        "tgn:7029392"
    ],
    "tgn:id":1000349,
    "tgn:name":"Boto\u0219ani",
    "tgn:placetype":[
        "aat:300387064",
        "aat:300000771"
    ]
},
  "bbox": [],
  "geometry": {"coordinates":[26.75,47.833],"type":"Point"}
}