{
  "id": 7179389,
  "type": "Feature",
  "properties": {
    "tgn:hierarchy":[
        "tgn:7179389",
        "tgn:7003669",
        "tgn:1000003",
        "tgn:7000084",
        "tgn:7029392"
    ],
    "tgn:id":7179389,
    "tgn:name":"Haid",
    "tgn:placetype":[
        "aat:300000206"
    ]
},
  "bbox": [],
  "geometry": {"coordinates":[12.966667,48.716667],"type":"Point"}
}