{
  "id": 7398132,
  "type": "Feature",
  "properties": {
    "tgn:hierarchy":[
        "tgn:7398132",
        "tgn:1000001",
        "tgn:1001960",
        "tgn:7005560",
        "tgn:7029392"
    ],
    "tgn:id":7398132,
    "tgn:name":"Cieneguita, Cerro",
    "tgn:placetype":[
        "aat:300008795"
    ]
},
  "bbox": [],
  "geometry": {"coordinates":[-110.741111,30.764167],"type":"Point"}
}