{
  "id": 2273847,
  "type": "Feature",
  "properties": {
    "tgn:hierarchy":[
        "tgn:2273847",
        "tgn:1000001",
        "tgn:7012149",
        "tgn:7019676",
        "tgn:7007566",
        "tgn:7029392"
    ],
    "tgn:id":2273847,
    "tgn:name":"Dadasoa Spring",
    "tgn:placetype":[
        "aat:300008697"
    ]
},
  "bbox": [],
  "geometry": {"coordinates":[-108.7833,35.95],"type":"Point"}
}