{
  "id": 2004247,
  "type": "Feature",
  "properties": {
    "tgn:hierarchy":[
        "tgn:2004247",
        "tgn:7002659",
        "tgn:1000001",
        "tgn:2000011",
        "tgn:7012149",
        "tgn:7029392"
    ],
    "tgn:id":2004247,
    "tgn:name":"Lisman",
    "tgn:placetype":[
        "aat:300008347"
    ]
},
  "bbox": [],
  "geometry": {"coordinates":[-88.2667,32.1667],"type":"Point"}
}