{
  "id": 2776091,
  "type": "Feature",
  "properties": {
    "tgn:hierarchy":[
        "tgn:2776091",
        "tgn:1000001",
        "tgn:2002109",
        "tgn:7012149",
        "tgn:7007827",
        "tgn:7029392"
    ],
    "tgn:id":2776091,
    "tgn:name":"Wilson Spring",
    "tgn:placetype":[
        "aat:300008697"
    ]
},
  "bbox": [],
  "geometry": {"coordinates":[-112.5667,37.5833],"type":"Point"}
}