{
  "id": 7001328,
  "type": "Feature",
  "properties": {
    "tgn:hierarchy":[
        "tgn:7001328",
        "tgn:7001242",
        "tgn:1000523",
        "tgn:7016752",
        "tgn:7029392"
    ],
    "tgn:id":7001328,
    "tgn:name":"Timgad",
    "tgn:placetype":[
        "aat:300008347",
        "aat:300000810",
        "aat:300167671",
        "aat:300263063"
    ]
},
  "bbox": [],
  "geometry": {"coordinates":[6.4667,35.4833],"type":"Point"}
}