{
  "id": 7178852,
  "type": "Feature",
  "properties": {
    "tgn:hierarchy":[
        "tgn:7178852",
        "tgn:7003669",
        "tgn:1000003",
        "tgn:7000084",
        "tgn:7029392"
    ],
    "tgn:id":7178852,
    "tgn:name":"Gugelhupf",
    "tgn:placetype":[
        "aat:300008798"
    ]
},
  "bbox": [],
  "geometry": {"coordinates":[13.383333,49.016667],"type":"Point"}
}