{
  "id": 2370246,
  "type": "Feature",
  "properties": {
    "tgn:hierarchy":[
        "tgn:2370246",
        "tgn:1000001",
        "tgn:7012149",
        "tgn:2000960",
        "tgn:7007520",
        "tgn:7029392"
    ],
    "tgn:id":2370246,
    "tgn:name":"Gypo Creek",
    "tgn:placetype":[
        "aat:300008706"
    ]
},
  "bbox": [],
  "geometry": {"coordinates":[-89.5833,46.3167],"type":"Point"}
}