{
  "id": 2260693,
  "type": "Feature",
  "properties": {
    "tgn:hierarchy":[
        "tgn:2260693",
        "tgn:1000001",
        "tgn:7012149",
        "tgn:2001074",
        "tgn:7007521",
        "tgn:7029392"
    ],
    "tgn:id":2260693,
    "tgn:name":"County Ditch Number One",
    "tgn:placetype":[
        "aat:300006075"
    ]
},
  "bbox": [],
  "geometry": {"coordinates":[-95.2833,45.35],"type":"Point"}
}