{
  "id": 7245012,
  "type": "Feature",
  "properties": {
    "tgn:hierarchy":[
        "tgn:7245012",
        "tgn:7003466",
        "tgn:1000003",
        "tgn:1000063",
        "tgn:4012014",
        "tgn:7029392"
    ],
    "tgn:id":7245012,
    "tgn:name":"Baileu",
    "tgn:placetype":[
        "aat:300008347"
    ]
},
  "bbox": [],
  "geometry": {"coordinates":[4.416667,50.216667],"type":"Point"}
}