{
  "id": 7460969,
  "type": "Feature",
  "properties": {
    "tgn:hierarchy":[
        "tgn:7460969",
        "tgn:7019094",
        "tgn:7002444",
        "tgn:1000003",
        "tgn:7008591",
        "tgn:7029392"
    ],
    "tgn:id":7460969,
    "tgn:name:en":"Laoigh, Gleann",
    "tgn:placetype":[
        "aat:300008761"
    ]
},
  "bbox": [],
  "geometry": {"coordinates":[-5.116667,56.033333],"type":"Point"}
}