{
  "id": 2739050,
  "type": "Feature",
  "properties": {
    "tgn:hierarchy":[
        "tgn:2739050",
        "tgn:1000001",
        "tgn:7012149",
        "tgn:2001455",
        "tgn:7007566",
        "tgn:7029392"
    ],
    "tgn:id":2739050,
    "tgn:name":"United States and Illinois",
    "tgn:placetype":[
        "aat:300000390"
    ]
},
  "bbox": [],
  "geometry": {"coordinates":[-107.7167,32.9167],"type":"Point"}
}