{
  "id": 2262390,
  "type": "Feature",
  "properties": {
    "tgn:hierarchy":[
        "tgn:2262390",
        "tgn:1000001",
        "tgn:7012149",
        "tgn:2000217",
        "tgn:7007158",
        "tgn:7029392"
    ],
    "tgn:id":2262390,
    "tgn:name":"Cow Gulch",
    "tgn:placetype":[
        "aat:300008761"
    ]
},
  "bbox": [],
  "geometry": {"coordinates":[-107.2667,38.35],"type":"Point"}
}