<<<<<<< HEAD
{
  "id": 2332957,
  "type": "Feature",
  "properties": {
    "tgn:hierarchy":[
        "tgn:2332957",
        "tgn:1000001",
        "tgn:7012149",
        "tgn:2001306",
        "tgn:7007524",
        "tgn:7029392"
    ],
    "tgn:id":2332957,
    "tgn:name":"Flume Gulch",
    "tgn:placetype":[
        "aat:300008761"
    ]
},
  "bbox": [],
  "geometry": {"coordinates":[-112.6167,46.1667],"type":"Point"}
}
=======
{"geometry":{"type":"Point","coordinates":[-112.616700,46.166700]},"type":"Feature","properties":{"hierarchy":["tgn:2332957","tgn:1000001","tgn:7012149","tgn:2001306","tgn:7007524","tgn:7029392"],"placetype":["aat:300008761"],"id":2332957,"name:xx":"Flume Gulch"}}
>>>>>>> 03f74aca74312dbeaf24d7e61306dd6a786dc3d0
