{
  "id": 7491504,
  "type": "Feature",
  "properties": {
    "tgn:hierarchy":[
        "tgn:7491504",
        "tgn:1000004",
        "tgn:7490934",
        "tgn:1000141",
        "tgn:7029392"
    ],
    "tgn:id":7491504,
    "tgn:name":"Sanye Gong Xi",
    "tgn:placetype":[
        "aat:300008699"
    ]
},
  "bbox": [],
  "geometry": {"coordinates":[120.1925,22.921389],"type":"Point"}
}