{
  "id": 2581587,
  "type": "Feature",
  "properties": {
    "tgn:hierarchy":[
        "tgn:2581587",
        "tgn:1000001",
        "tgn:7016172",
        "tgn:7012149",
        "tgn:7029392"
    ],
    "tgn:id":2581587,
    "tgn:name":"Pilot Rock Mountain",
    "tgn:placetype":[
        "aat:300386831"
    ]
},
  "bbox": [],
  "geometry": {"coordinates":[-93.2333,35.6167],"type":"Point"}
}