{
  "id": 2685528,
  "type": "Feature",
  "properties": {
    "tgn:hierarchy":[
        "tgn:2685528",
        "tgn:1000001",
        "tgn:7012149",
        "tgn:2000476",
        "tgn:7007250",
        "tgn:7029392"
    ],
    "tgn:id":2685528,
    "tgn:name":"Spread Creek",
    "tgn:placetype":[
        "aat:300008706"
    ]
},
  "bbox": [],
  "geometry": {"coordinates":[-115.0333,45.6333],"type":"Point"}
}