{
  "id": 2643923,
  "type": "Feature",
  "properties": {
    "tgn:hierarchy":[
        "tgn:2643923",
        "tgn:1000001",
        "tgn:7012149",
        "tgn:1002924",
        "tgn:7007568",
        "tgn:7029392"
    ],
    "tgn:id":2643923,
    "tgn:name":"Sans Souci Lakes",
    "tgn:placetype":[
        "aat:300008680"
    ]
},
  "bbox": [],
  "geometry": {"coordinates":[-73.05,40.75],"type":"Point"}
}