{
  "id": 1097272,
  "type": "Feature",
  "properties": {
    "tgn:hierarchy":[
        "tgn:1097272",
        "tgn:7000490",
        "tgn:1000006",
        "tgn:7001834",
        "tgn:7029392"
    ],
    "tgn:id":1097272,
    "tgn:name":"Kitchener",
    "tgn:placetype":[
        "aat:300008347"
    ]
},
  "bbox": [],
  "geometry": {"coordinates":[124.1833,-31.0333],"type":"Point"}
}