{
  "id": 2257327,
  "type": "Feature",
  "properties": {
    "tgn:hierarchy":[
        "tgn:2257327",
        "tgn:1000001",
        "tgn:7012149",
        "tgn:2001279",
        "tgn:7007524",
        "tgn:7029392"
    ],
    "tgn:id":2257327,
    "tgn:name":"Cornish Gulch",
    "tgn:placetype":[
        "aat:300008761"
    ]
},
  "bbox": [],
  "geometry": {"coordinates":[-113.5833,46.2667],"type":"Point"}
}