{
  "id": 2786161,
  "type": "Feature",
  "properties": {
    "tgn:hierarchy":[
        "tgn:2786161",
        "tgn:1000001",
        "tgn:7012149",
        "tgn:2001715",
        "tgn:7007708",
        "tgn:7029392"
    ],
    "tgn:id":2786161,
    "tgn:name":"Young Valley",
    "tgn:placetype":[
        "aat:300008761"
    ]
},
  "bbox": [],
  "geometry": {"coordinates":[-120.7167,42.0333],"type":"Point"}
}