{
  "id": 7374816,
  "type": "Feature",
  "properties": {
    "tgn:hierarchy":[
        "tgn:7374816",
        "tgn:1001853",
        "tgn:1000001",
        "tgn:7005560",
        "tgn:7029392"
    ],
    "tgn:id":7374816,
    "tgn:name":"Rancho La Cruz",
    "tgn:placetype":[
        "aat:300000241"
    ]
},
  "bbox": [],
  "geometry": {"coordinates":[-100.75,25.483333],"type":"Point"}
}