{
  "id": 2718354,
  "type": "Feature",
  "properties": {
    "tgn:hierarchy":[
        "tgn:2718354",
        "tgn:1000001",
        "tgn:2001424",
        "tgn:7012149",
        "tgn:7007564",
        "tgn:7029392"
    ],
    "tgn:id":2718354,
    "tgn:name":"Thompson Hill",
    "tgn:placetype":[
        "aat:300008798"
    ]
},
  "bbox": [],
  "geometry": {"coordinates":[-71.9833,43.7333],"type":"Point"}
}