<<<<<<< HEAD
{
  "id": 2402591,
  "type": "Feature",
  "properties": {
    "tgn:hierarchy":[
        "tgn:2402591",
        "tgn:1000001",
        "tgn:1002274",
        "tgn:7012149",
        "tgn:7007706",
        "tgn:7029392"
    ],
    "tgn:id":2402591,
    "tgn:name":"Hosterman Lake",
    "tgn:placetype":[
        "aat:300006191"
    ]
},
  "bbox": [],
  "geometry": {"coordinates":[-83.9,39.9],"type":"Point"}
}
=======
{"geometry":{"type":"Point","coordinates":[-83.900000,39.900000]},"type":"Feature","properties":{"hierarchy":["tgn:2402591","tgn:1000001","tgn:1002274","tgn:7012149","tgn:7007706","tgn:7029392"],"placetype":["aat:300006191"],"id":2402591,"name:xx":"Hosterman Lake"}}
>>>>>>> 03f74aca74312dbeaf24d7e61306dd6a786dc3d0
