{
  "id": 7334115,
  "type": "Feature",
  "properties": {
    "tgn:hierarchy":[
        "tgn:7334115",
        "tgn:7002758",
        "tgn:7002821",
        "tgn:1000003",
        "tgn:1000095",
        "tgn:7029392"
    ],
    "tgn:id":7334115,
    "tgn:name":"El Tesoro",
    "tgn:placetype":[
        "aat:300008347"
    ]
},
  "bbox": [],
  "geometry": {"coordinates":[-2.733333,37.266667],"type":"Point"}
}