{
  "id": 7062541,
  "type": "Feature",
  "properties": {
    "tgn:hierarchy":[
        "tgn:7062541",
        "tgn:1000003",
        "tgn:7000094",
        "tgn:7000084",
        "tgn:7029392"
    ],
    "tgn:id":7062541,
    "tgn:name":"Amholz",
    "tgn:placetype":[
        "aat:300008347"
    ]
},
  "bbox": [],
  "geometry": {"coordinates":[10.816667,53.316667],"type":"Point"}
}