<<<<<<< HEAD
{
  "id": 7470458,
  "type": "Feature",
  "properties": {
    "tgn:hierarchy":[
        "tgn:7470458",
        "tgn:1000004",
        "tgn:7490934",
        "tgn:1000141",
        "tgn:7029392"
    ],
    "tgn:id":7470458,
    "tgn:name":"Zhuzijiao",
    "tgn:placetype":[
        "aat:300008347"
    ]
},
  "bbox": [],
  "geometry": {"coordinates":[120.376111,23.440556],"type":"Point"}
}
=======
{"geometry":{"type":"Point","coordinates":[120.376111,23.440556]},"type":"Feature","properties":{"hierarchy":["tgn:7470458","tgn:1000004","tgn:7490934","tgn:1000141","tgn:7029392"],"placetype":["aat:300008347"],"id":7470458,"name:xx":"Zhuzijiao"}}
>>>>>>> 03f74aca74312dbeaf24d7e61306dd6a786dc3d0
