{
  "id": 7566835,
  "type": "Feature",
  "properties": {
    "tgn:hierarchy":[
        "tgn:7566835",
        "tgn:1000004",
        "tgn:7000198",
        "tgn:7001797",
        "tgn:7029392"
    ],
    "tgn:id":7566835,
    "tgn:name:en":"Elephinstone Bridge",
    "tgn:placetype":[
        "aat:300007836"
    ]
},
  "bbox": [],
  "geometry": {"coordinates":[80.260278,13.011667],"type":"Point"}
}