{
  "id": 2372279,
  "type": "Feature",
  "properties": {
    "tgn:hierarchy":[
        "tgn:2372279",
        "tgn:1000001",
        "tgn:7012149",
        "tgn:7029392"
    ],
    "tgn:id":2372279,
    "tgn:name":"Halfway Canyon",
    "tgn:placetype":[
        "aat:300008761"
    ]
},
  "bbox": [],
  "geometry": {"coordinates":[-107.65,45.0167],"type":"Point"}
}