{
  "id": 2031487,
  "type": "Feature",
  "properties": {
    "tgn:hierarchy":[
        "tgn:2031487",
        "tgn:1000001",
        "tgn:7012149",
        "tgn:1002508",
        "tgn:7007252",
        "tgn:7029392"
    ],
    "tgn:id":2031487,
    "tgn:name":"Cortland",
    "tgn:placetype":[
        "aat:300008347"
    ]
},
  "bbox": [],
  "geometry": {"coordinates":[-85.95,38.9667],"type":"Point"}
}