{
  "id": 7582071,
  "type": "Feature",
  "properties": {
    "tgn:hierarchy":[
        "tgn:7582071",
        "tgn:1000004",
        "tgn:7000198",
        "tgn:7016722",
        "tgn:7029392"
    ],
    "tgn:id":7582071,
    "tgn:name:en":"Jamora",
    "tgn:placetype":[
        "aat:300008347"
    ]
},
  "bbox": [],
  "geometry": {"coordinates":[78.373372,24.867071],"type":"Point"}
}