{
  "id": 1072971,
  "type": "Feature",
  "properties": {
    "tgn:hierarchy":[
        "tgn:1072971",
        "tgn:1000004",
        "tgn:1001390",
        "tgn:1000111",
        "tgn:7029392"
    ],
    "tgn:id":1072971,
    "tgn:name":"Xiexinggou",
    "tgn:placetype":[
        "aat:300008347"
    ]
},
  "bbox": [],
  "geometry": {"coordinates":[121.0833,41.85],"type":"Point"}
}