{
  "id": 2189791,
  "type": "Feature",
  "properties": {
    "tgn:hierarchy":[
        "tgn:2189791",
        "tgn:1000001",
        "tgn:7012149",
        "tgn:1002631",
        "tgn:7007240",
        "tgn:7029392"
    ],
    "tgn:id":2189791,
    "tgn:name":"Bowers Lake",
    "tgn:placetype":[
        "aat:300008680"
    ]
},
  "bbox": [],
  "geometry": {"coordinates":[-81.95,29.0333],"type":"Point"}
}