<<<<<<< HEAD
{
  "id": 7488403,
  "type": "Feature",
  "properties": {
    "tgn:hierarchy":[
        "tgn:7488403",
        "tgn:1000004",
        "tgn:7004300",
        "tgn:1000141",
        "tgn:7029392"
    ],
    "tgn:id":7488403,
    "tgn:name":"Nanmiangua Yu",
    "tgn:placetype":[
        "aat:300386881"
    ]
},
  "bbox": [],
  "geometry": {"coordinates":[119.665186,23.668398],"type":"Point"}
}
=======
{"geometry":{"type":"Point","coordinates":[119.665186,23.668398]},"type":"Feature","properties":{"hierarchy":["tgn:7488403","tgn:1000004","tgn:7004300","tgn:1000141","tgn:7029392"],"placetype":["aat:300386881"],"id":7488403,"name:xx":"Nanmiangua Yu"}}
>>>>>>> 03f74aca74312dbeaf24d7e61306dd6a786dc3d0
