{
  "id": 7488403,
  "type": "Feature",
  "properties": {
    "tgn:hierarchy":[
        "tgn:7488403",
        "tgn:1000004",
        "tgn:7004300",
        "tgn:1000141",
        "tgn:7029392"
    ],
    "tgn:id":7488403,
    "tgn:name":"Nanmiangua Yu",
    "tgn:placetype":[
        "aat:300386881"
    ]
},
  "bbox": [],
  "geometry": {"coordinates":[119.665186,23.668398],"type":"Point"}
}