<<<<<<< HEAD
{
  "id": 2259611,
  "type": "Feature",
  "properties": {
    "tgn:hierarchy":[
        "tgn:2259611",
        "tgn:1000001",
        "tgn:7012149",
        "tgn:2001225",
        "tgn:7007523",
        "tgn:7029392"
    ],
    "tgn:id":2259611,
    "tgn:name":"Couch Hollow",
    "tgn:placetype":[
        "aat:300008761"
    ]
},
  "bbox": [],
  "geometry": {"coordinates":[-91.2333,36.6333],"type":"Point"}
}
=======
{"geometry":{"type":"Point","coordinates":[-91.233300,36.633300]},"type":"Feature","properties":{"hierarchy":["tgn:2259611","tgn:1000001","tgn:7012149","tgn:2001225","tgn:7007523","tgn:7029392"],"placetype":["aat:300008761"],"id":2259611,"name:xx":"Couch Hollow"}}
>>>>>>> 03f74aca74312dbeaf24d7e61306dd6a786dc3d0
