{
  "id": 7314192,
  "type": "Feature",
  "properties": {
    "tgn:hierarchy":[
        "tgn:7314192",
        "tgn:7016598",
        "tgn:1000049",
        "tgn:1000002",
        "tgn:7029392"
    ],
    "tgn:id":7314192,
    "tgn:name":"Loromal",
    "tgn:placetype":[
        "aat:300008697"
    ]
},
  "bbox": [],
  "geometry": {"coordinates":[-67.566667,-23.533333],"type":"Point"}
}