{
  "id": 2347644,
  "type": "Feature",
  "properties": {
    "tgn:hierarchy":[
        "tgn:2347644",
        "tgn:1000001",
        "tgn:7012149",
        "tgn:2002282",
        "tgn:7013961",
        "tgn:7029392"
    ],
    "tgn:id":2347644,
    "tgn:name":"Georges Cut Hollow",
    "tgn:placetype":[
        "aat:300008761"
    ]
},
  "bbox": [],
  "geometry": {"coordinates":[-80.45,37.4333],"type":"Point"}
}