{
  "id": 7286698,
  "type": "Feature",
  "properties": {
    "tgn:hierarchy":[
        "tgn:7286698",
        "tgn:1001699",
        "tgn:1000049",
        "tgn:1000002",
        "tgn:7029392"
    ],
    "tgn:id":7286698,
    "tgn:name":"Guarne, R\u00edo",
    "tgn:placetype":[
        "aat:300008699"
    ]
},
  "bbox": [],
  "geometry": {"coordinates":[-73.433333,-41.516667],"type":"Point"}
}