{
  "id": 7567720,
  "type": "Feature",
  "properties": {
    "tgn:hierarchy":[
        "tgn:7567720",
        "tgn:1001828",
        "tgn:1000004",
        "tgn:7000198",
        "tgn:7029392"
    ],
    "tgn:id":7567720,
    "tgn:name:en":"Sandampet",
    "tgn:placetype":[
        "aat:300008347"
    ]
},
  "bbox": [],
  "geometry": {"coordinates":[78.098611,17.791944],"type":"Point"}
}