{
  "id": 2543002,
  "type": "Feature",
  "properties": {
    "tgn:hierarchy":[
        "tgn:2543002",
        "tgn:1000001",
        "tgn:1002665",
        "tgn:7012149",
        "tgn:7007517",
        "tgn:7029392"
    ],
    "tgn:id":2543002,
    "tgn:name":"Nonaicoicus Hill",
    "tgn:placetype":[
        "aat:300008798"
    ]
},
  "bbox": [],
  "geometry": {"coordinates":[-71.5667,42.55],"type":"Point"}
}