{
  "id": 2737551,
  "type": "Feature",
  "properties": {
    "tgn:hierarchy":[
        "tgn:2737551",
        "tgn:1000001",
        "tgn:7012149",
        "tgn:1002990",
        "tgn:7007708",
        "tgn:7029392"
    ],
    "tgn:id":2737551,
    "tgn:name":"Tygh Valley Storage Pond",
    "tgn:placetype":[
        "aat:300006191"
    ]
},
  "bbox": [],
  "geometry": {"coordinates":[-121.1833,45.2333],"type":"Point"}
}