{
  "id": 2354677,
  "type": "Feature",
  "properties": {
    "tgn:hierarchy":[
        "tgn:2354677",
        "tgn:1000001",
        "tgn:7012149",
        "tgn:2001287",
        "tgn:7007524",
        "tgn:7029392"
    ],
    "tgn:id":2354677,
    "tgn:name":"Good Creek",
    "tgn:placetype":[
        "aat:300008706"
    ]
},
  "bbox": [],
  "geometry": {"coordinates":[-106.2667,47.4167],"type":"Point"}
}