{
  "id": 2454627,
  "type": "Feature",
  "properties": {
    "tgn:hierarchy":[
        "tgn:2454627",
        "tgn:1000001",
        "tgn:7012149",
        "tgn:7007708",
        "tgn:7029392"
    ],
    "tgn:id":2454627,
    "tgn:name":"Little Digger Mountain",
    "tgn:placetype":[
        "aat:300008798"
    ]
},
  "bbox": [],
  "geometry": {"coordinates":[-123.7167,44.3667],"type":"Point"}
}