{
  "id": 7500831,
  "type": "Feature",
  "properties": {
    "tgn:hierarchy":[
        "tgn:7500831",
        "tgn:1000004",
        "tgn:7467799",
        "tgn:1000141",
        "tgn:7029392"
    ],
    "tgn:id":7500831,
    "tgn:name":"Nanxing Qiao",
    "tgn:placetype":[
        "aat:300007836"
    ]
},
  "bbox": [],
  "geometry": {"coordinates":[120.533604,24.055448],"type":"Point"}
}