<<<<<<< HEAD
{
  "id": 2764279,
  "type": "Feature",
  "properties": {
    "tgn:hierarchy":[
        "tgn:2764279",
        "tgn:2000919",
        "tgn:1000001",
        "tgn:7012149",
        "tgn:7007515",
        "tgn:7029392"
    ],
    "tgn:id":2764279,
    "tgn:name":"Wheelock Mill",
    "tgn:placetype":[
        "aat:300008347"
    ]
},
  "bbox": [],
  "geometry": {"coordinates":[-68.8833,46.9833],"type":"Point"}
}
=======
{"geometry":{"type":"Point","coordinates":[-68.883300,46.983300]},"type":"Feature","properties":{"hierarchy":["tgn:2764279","tgn:2000919","tgn:1000001","tgn:7012149","tgn:7007515","tgn:7029392"],"placetype":["aat:300008347"],"id":2764279,"name:xx":"Wheelock Mill"}}
>>>>>>> 03f74aca74312dbeaf24d7e61306dd6a786dc3d0
