{
  "id": 7535473,
  "type": "Feature",
  "properties": {
    "tgn:hierarchy":[
        "tgn:7535473",
        "tgn:7001242",
        "tgn:7016833",
        "tgn:1001113",
        "tgn:7029392"
    ],
    "tgn:id":7535473,
    "tgn:name":"Kafr al Ghaz\u0101l\u012byah",
    "tgn:placetype":[
        "aat:300008347"
    ]
},
  "bbox": [],
  "geometry": {"coordinates":[31.761366,30.654795],"type":"Point"}
}