{
  "id": 7407639,
  "type": "Feature",
  "properties": {
    "tgn:hierarchy":[
        "tgn:7407639",
        "tgn:1000001",
        "tgn:1001893",
        "tgn:7005560",
        "tgn:7029392"
    ],
    "tgn:id":7407639,
    "tgn:name":"Concepci\u00f3 del Monte",
    "tgn:placetype":[
        "aat:300008347"
    ]
},
  "bbox": [],
  "geometry": {"coordinates":[-100.15,19.65],"type":"Point"}
}