<<<<<<< HEAD
{
  "id": 2402780,
  "type": "Feature",
  "properties": {
    "tgn:hierarchy":[
        "tgn:2402780",
        "tgn:1000001",
        "tgn:7012149",
        "tgn:7007157",
        "tgn:7029392"
    ],
    "tgn:id":2402780,
    "tgn:name":"Hot Springs Creek",
    "tgn:placetype":[
        "aat:300008706"
    ]
},
  "bbox": [],
  "geometry": {"coordinates":[-121.45,40.45],"type":"Point"}
}
=======
{"geometry":{"type":"Point","coordinates":[-121.450000,40.450000]},"type":"Feature","properties":{"hierarchy":["tgn:2402780","tgn:1000001","tgn:7012149","tgn:7007157","tgn:7029392"],"placetype":["aat:300008706"],"id":2402780,"name:xx":"Hot Springs Creek"}}
>>>>>>> 03f74aca74312dbeaf24d7e61306dd6a786dc3d0
