{
  "id": 7349472,
  "type": "Feature",
  "properties": {
    "tgn:hierarchy":[
        "tgn:7349472",
        "tgn:7005583",
        "tgn:1000001",
        "tgn:7005560",
        "tgn:7029392"
    ],
    "tgn:id":7349472,
    "tgn:name":"Aguaje, Arroyo del",
    "tgn:placetype":[
        "aat:300266554",
        "aat:300008699"
    ]
},
  "bbox": [],
  "geometry": {"coordinates":[-106.183333,25.266667],"type":"Point"}
}