{
  "id": 2040356,
  "type": "Feature",
  "properties": {
    "tgn:hierarchy":[
        "tgn:2040356",
        "tgn:1000001",
        "tgn:7012149",
        "tgn:1002516",
        "tgn:7007255",
        "tgn:7029392"
    ],
    "tgn:id":2040356,
    "tgn:name":"Moorland",
    "tgn:placetype":[
        "aat:300008347"
    ]
},
  "bbox": [],
  "geometry": {"coordinates":[-85.5833,38.2667],"type":"Point"}
}