{
  "id": 7153415,
  "type": "Feature",
  "properties": {
    "tgn:hierarchy":[
        "tgn:7153415",
        "tgn:7003692",
        "tgn:1000003",
        "tgn:7000084",
        "tgn:7029392"
    ],
    "tgn:id":7153415,
    "tgn:name":"Karlshof",
    "tgn:placetype":[
        "aat:300008347"
    ]
},
  "bbox": [],
  "geometry": {"coordinates":[9.366667,48.983333],"type":"Point"}
}