{
  "id": 7195855,
  "type": "Feature",
  "properties": {
    "tgn:hierarchy":[
        "tgn:7195855",
        "tgn:1000003",
        "tgn:7003678",
        "tgn:7000084",
        "tgn:7029392"
    ],
    "tgn:id":7195855,
    "tgn:name":"Dicker Kopf",
    "tgn:placetype":[
        "aat:300008777"
    ]
},
  "bbox": [],
  "geometry": {"coordinates":[9.55,51.366667],"type":"Point"}
}