<<<<<<< HEAD
{
  "id": 2763400,
  "type": "Feature",
  "properties": {
    "tgn:hierarchy":[
        "tgn:2763400",
        "tgn:1000001",
        "tgn:7012149",
        "tgn:2001459",
        "tgn:7007566",
        "tgn:7029392"
    ],
    "tgn:id":2763400,
    "tgn:name":"Wetherly Lake",
    "tgn:placetype":[
        "aat:300006191"
    ]
},
  "bbox": [],
  "geometry": {"coordinates":[-103.6667,36.7167],"type":"Point"}
}
=======
{"geometry":{"type":"Point","coordinates":[-103.666700,36.716700]},"type":"Feature","properties":{"hierarchy":["tgn:2763400","tgn:1000001","tgn:7012149","tgn:2001459","tgn:7007566","tgn:7029392"],"placetype":["aat:300006191"],"id":2763400,"name:xx":"Wetherly Lake"}}
>>>>>>> 03f74aca74312dbeaf24d7e61306dd6a786dc3d0
