<<<<<<< HEAD
{
  "id": 7485896,
  "type": "Feature",
  "properties": {
    "tgn:hierarchy":[
        "tgn:7485896",
        "tgn:7001004",
        "tgn:1000004",
        "tgn:1000141",
        "tgn:7029392"
    ],
    "tgn:id":7485896,
    "tgn:name":"Xingda Yuanyang Yugang",
    "tgn:placetype":[
        "aat:300008678"
    ]
},
  "bbox": [],
  "geometry": {"coordinates":[120.207222,22.874444],"type":"Point"}
}
=======
{"geometry":{"type":"Point","coordinates":[120.207222,22.874444]},"type":"Feature","properties":{"hierarchy":["tgn:7485896","tgn:7001004","tgn:1000004","tgn:1000141","tgn:7029392"],"placetype":["aat:300008678"],"id":7485896,"name:xx":"Xingda Yuanyang Yugang"}}
>>>>>>> 03f74aca74312dbeaf24d7e61306dd6a786dc3d0
