{
  "id": 2719547,
  "type": "Feature",
  "properties": {
    "tgn:hierarchy":[
        "tgn:2719547",
        "tgn:1000001",
        "tgn:7012149",
        "tgn:2000488",
        "tgn:7007250",
        "tgn:7029392"
    ],
    "tgn:id":2719547,
    "tgn:name":"Three Forks Summit Springs",
    "tgn:placetype":[
        "aat:300008697"
    ]
},
  "bbox": [],
  "geometry": {"coordinates":[-116.05,42.0833],"type":"Point"}
}