{
  "id": 7059118,
  "type": "Feature",
  "properties": {
    "tgn:hierarchy":[
        "tgn:7059118",
        "tgn:7015163",
        "tgn:1000003",
        "tgn:7003121",
        "tgn:1000080",
        "tgn:7029392"
    ],
    "tgn:id":7059118,
    "tgn:name":"Agnese, Monte",
    "tgn:placetype":[
        "aat:300008777"
    ]
},
  "bbox": [],
  "geometry": {"coordinates":[8.337222,40.581111],"type":"Point"}
}