{
  "id": 2742480,
  "type": "Feature",
  "properties": {
    "tgn:hierarchy":[
        "tgn:2742480",
        "tgn:1000001",
        "tgn:7012149",
        "tgn:7007827",
        "tgn:7029392"
    ],
    "tgn:id":2742480,
    "tgn:name":"Valley Mountains",
    "tgn:placetype":[
        "aat:300386831"
    ]
},
  "bbox": [],
  "geometry": {"coordinates":[-111.95,39.2667],"type":"Point"}
}