{
  "id": 2608541,
  "type": "Feature",
  "properties": {
    "tgn:hierarchy":[
        "tgn:2608541",
        "tgn:1000001",
        "tgn:2002108",
        "tgn:7012149",
        "tgn:7007827",
        "tgn:7029392"
    ],
    "tgn:id":2608541,
    "tgn:name":"Rattlesnake Hollow",
    "tgn:placetype":[
        "aat:300008761"
    ]
},
  "bbox": [],
  "geometry": {"coordinates":[-110.8833,39.3833],"type":"Point"}
}