{
  "id": 7215106,
  "type": "Feature",
  "properties": {
    "tgn:hierarchy":[
        "tgn:7215106",
        "tgn:7003692",
        "tgn:1000003",
        "tgn:7000084",
        "tgn:7029392"
    ],
    "tgn:id":7215106,
    "tgn:name":"Binsberg",
    "tgn:placetype":[
        "aat:300008795"
    ]
},
  "bbox": [],
  "geometry": {"coordinates":[8.783333,48.116667],"type":"Point"}
}