<<<<<<< HEAD
{
  "id": 2333640,
  "type": "Feature",
  "properties": {
    "tgn:hierarchy":[
        "tgn:2333640",
        "tgn:1000001",
        "tgn:7012149",
        "tgn:1002742",
        "tgn:7007920",
        "tgn:7029392"
    ],
    "tgn:id":2333640,
    "tgn:name":"Fool Hen Creek",
    "tgn:placetype":[
        "aat:300008706"
    ]
},
  "bbox": [],
  "geometry": {"coordinates":[-120.3167,48.8333],"type":"Point"}
}
=======
{"geometry":{"type":"Point","coordinates":[-120.316700,48.833300]},"type":"Feature","properties":{"hierarchy":["tgn:2333640","tgn:1000001","tgn:7012149","tgn:1002742","tgn:7007920","tgn:7029392"],"placetype":["aat:300008706"],"id":2333640,"name:xx":"Fool Hen Creek"}}
>>>>>>> 03f74aca74312dbeaf24d7e61306dd6a786dc3d0
