{
  "id": 1138032,
  "type": "Feature",
  "properties": {
    "tgn:hierarchy":[
        "tgn:1138032",
        "tgn:7011651",
        "tgn:1000003",
        "tgn:7006660",
        "tgn:7029392"
    ],
    "tgn:id":1138032,
    "tgn:name":"Novooleksiyivka",
    "tgn:placetype":[
        "aat:300008347",
        "aat:300008375"
    ]
},
  "bbox": [],
  "geometry": {"coordinates":[34.65,46.2167],"type":"Point"}
}