<<<<<<< HEAD
{
  "id": 2762201,
  "type": "Feature",
  "properties": {
    "tgn:hierarchy":[
        "tgn:2762201",
        "tgn:1000001",
        "tgn:2001424",
        "tgn:7012149",
        "tgn:7007564",
        "tgn:7029392"
    ],
    "tgn:id":2762201,
    "tgn:name":"West Spur Whiteface",
    "tgn:placetype":[
        "aat:300266640"
    ]
},
  "bbox": [],
  "geometry": {"coordinates":[-71.4167,43.9167],"type":"Point"}
}
=======
{"geometry":{"type":"Point","coordinates":[-71.416700,43.916700]},"type":"Feature","properties":{"hierarchy":["tgn:2762201","tgn:1000001","tgn:2001424","tgn:7012149","tgn:7007564","tgn:7029392"],"placetype":["aat:300266640"],"id":2762201,"name:xx":"West Spur Whiteface"}}
>>>>>>> 03f74aca74312dbeaf24d7e61306dd6a786dc3d0
