<<<<<<< HEAD
{
  "id": 7023981,
  "type": "Feature",
  "properties": {
    "tgn:hierarchy":[
        "tgn:7023981",
        "tgn:1000003",
        "tgn:7029392"
    ],
    "tgn:id":7023981,
    "tgn:name:en":"Italian Peninsula",
    "tgn:placetype":[
        "aat:300008804"
    ]
},
  "bbox": [],
  "geometry": {"coordinates":[13.0,42.0],"type":"Point"}
}
=======
{"geometry":{"type":"Point","coordinates":[13.000000,42.000000]},"type":"Feature","properties":{"hierarchy":["tgn:7023981","tgn:1000003","tgn:7029392"],"placetype":["aat:300008804"],"name:en":"Italian Peninsula","id":7023981}}
>>>>>>> 03f74aca74312dbeaf24d7e61306dd6a786dc3d0
