{
  "id": 2410919,
  "type": "Feature",
  "properties": {
    "tgn:hierarchy":[
        "tgn:2410919",
        "tgn:2001627",
        "tgn:1000001",
        "tgn:7012149",
        "tgn:7007707",
        "tgn:7029392"
    ],
    "tgn:id":2410919,
    "tgn:name":"Indian Creek",
    "tgn:placetype":[
        "aat:300008706"
    ]
},
  "bbox": [],
  "geometry": {"coordinates":[-99.4667,35.3667],"type":"Point"}
}