{
  "id": 1085634,
  "type": "Feature",
  "properties": {
    "tgn:hierarchy":[
        "tgn:1085634",
        "tgn:7005194",
        "tgn:1000004",
        "tgn:7000977",
        "tgn:1000142",
        "tgn:7029392"
    ],
    "tgn:id":1085634,
    "tgn:name":"Phichai",
    "tgn:placetype":[
        "aat:300008347"
    ]
},
  "bbox": [],
  "geometry": {"coordinates":[100.0833,17.2833],"type":"Point"}
}