{
  "id": 2598808,
  "type": "Feature",
  "properties": {
    "tgn:hierarchy":[
        "tgn:2598808",
        "tgn:1000001",
        "tgn:7006451",
        "tgn:7012149",
        "tgn:2000101",
        "tgn:7029392"
    ],
    "tgn:id":2598808,
    "tgn:name":"Prieto, Cerro",
    "tgn:placetype":[
        "aat:300008798"
    ]
},
  "bbox": [],
  "geometry": {"coordinates":[-111.4167,32.5167],"type":"Point"}
}