<<<<<<< HEAD
{
  "id": 7364650,
  "type": "Feature",
  "properties": {
    "tgn:hierarchy":[
        "tgn:7364650",
        "tgn:1000001",
        "tgn:7005596",
        "tgn:7005560",
        "tgn:7029392"
    ],
    "tgn:id":7364650,
    "tgn:name":"El Progreso",
    "tgn:placetype":[
        "aat:300008347"
    ]
},
  "bbox": [],
  "geometry": {"coordinates":[-90.716667,18.016667],"type":"Point"}
}
=======
{"geometry":{"type":"Point","coordinates":[-90.716667,18.016667]},"type":"Feature","properties":{"hierarchy":["tgn:7364650","tgn:1000001","tgn:7005596","tgn:7005560","tgn:7029392"],"placetype":["aat:300008347"],"id":7364650,"name:xx":"El Progreso"}}
>>>>>>> 03f74aca74312dbeaf24d7e61306dd6a786dc3d0
