{
  "id": 2644341,
  "type": "Feature",
  "properties": {
    "tgn:hierarchy":[
        "tgn:2644341",
        "tgn:1000001",
        "tgn:7012149",
        "tgn:2001982",
        "tgn:7007826",
        "tgn:7029392"
    ],
    "tgn:id":2644341,
    "tgn:name":"Sapoak",
    "tgn:placetype":[
        "aat:300008347"
    ]
},
  "bbox": [],
  "geometry": {"coordinates":[-98.2333,32.45],"type":"Point"}
}