{
  "id": 2132250,
  "type": "Feature",
  "properties": {
    "tgn:hierarchy":[
        "tgn:2132250",
        "tgn:1000001",
        "tgn:7012149",
        "tgn:7007157",
        "tgn:1002858",
        "tgn:7029392"
    ],
    "tgn:id":2132250,
    "tgn:name":"Ames Valley",
    "tgn:placetype":[
        "aat:300008761"
    ]
},
  "bbox": [],
  "geometry": {"coordinates":[-116.4333,32.8167],"type":"Point"}
}