{
  "id": 7225609,
  "type": "Feature",
  "properties": {
    "tgn:hierarchy":[
        "tgn:7225609",
        "tgn:7002724",
        "tgn:7002715",
        "tgn:1000003",
        "tgn:1000074",
        "tgn:7029392"
    ],
    "tgn:id":7225609,
    "tgn:name":"Er\u00edpia Perikop\u00eds",
    "tgn:placetype":[
        "aat:300008057"
    ]
},
  "bbox": [],
  "geometry": {"coordinates":[21.416667,40.616667],"type":"Point"}
}