<<<<<<< HEAD
{
  "id": 2253581,
  "type": "Feature",
  "properties": {
    "tgn:hierarchy":[
        "tgn:2253581",
        "tgn:7006450",
        "tgn:1000001",
        "tgn:7019698",
        "tgn:7012149",
        "tgn:7029392"
    ],
    "tgn:id":2253581,
    "tgn:name":"Cook Lake",
    "tgn:placetype":[
        "aat:300008680"
    ]
},
  "bbox": [],
  "geometry": {"coordinates":[-150.3667,61.0],"type":"Point"}
}
=======
{"geometry":{"type":"Point","coordinates":[-150.366700,61.000000]},"type":"Feature","properties":{"hierarchy":["tgn:2253581","tgn:7006450","tgn:1000001","tgn:7019698","tgn:7012149","tgn:7029392"],"placetype":["aat:300008680"],"id":2253581,"name:xx":"Cook Lake"}}
>>>>>>> 03f74aca74312dbeaf24d7e61306dd6a786dc3d0
