{
  "id": 2599147,
  "type": "Feature",
  "properties": {
    "tgn:hierarchy":[
        "tgn:2599147",
        "tgn:1000001",
        "tgn:7012149",
        "tgn:2001855",
        "tgn:7007825",
        "tgn:7029392"
    ],
    "tgn:id":2599147,
    "tgn:name":"Pritchard Branch",
    "tgn:placetype":[
        "aat:300008699"
    ]
},
  "bbox": [],
  "geometry": {"coordinates":[-86.9833,36.0167],"type":"Point"}
}