{
  "id": 2429274,
  "type": "Feature",
  "properties": {
    "tgn:hierarchy":[
        "tgn:2429274",
        "tgn:1000001",
        "tgn:7012149",
        "tgn:1002553",
        "tgn:7007920",
        "tgn:7029392"
    ],
    "tgn:id":2429274,
    "tgn:name":"Jungle Creek",
    "tgn:placetype":[
        "aat:300008706"
    ]
},
  "bbox": [],
  "geometry": {"coordinates":[-120.9167,47.3333],"type":"Point"}
}