<<<<<<< HEAD
{
  "id": 7020167,
  "type": "Feature",
  "properties": {
    "tgn:hierarchy":[
        "tgn:7020167",
        "tgn:1000001",
        "tgn:7012149",
        "tgn:2002376",
        "tgn:7007923",
        "tgn:7029392"
    ],
    "tgn:id":7020167,
    "tgn:name":"Freedom",
    "tgn:placetype":[
        "aat:300008347"
    ]
},
  "bbox": [],
  "geometry": {"coordinates":[-111.0333,42.9667],"type":"Point"}
}
=======
{"geometry":{"type":"Point","coordinates":[-111.033300,42.966700]},"type":"Feature","properties":{"hierarchy":["tgn:7020167","tgn:1000001","tgn:7012149","tgn:2002376","tgn:7007923","tgn:7029392"],"placetype":["aat:300008347"],"id":7020167,"name:xx":"Freedom"}}
>>>>>>> 03f74aca74312dbeaf24d7e61306dd6a786dc3d0
