{
  "id": 2111378,
  "type": "Feature",
  "properties": {
    "tgn:hierarchy":[
        "tgn:2111378",
        "tgn:1000001",
        "tgn:7012149",
        "tgn:2002166",
        "tgn:7007919",
        "tgn:7029392"
    ],
    "tgn:id":2111378,
    "tgn:name":"Crossroads",
    "tgn:placetype":[
        "aat:300008347",
        "aat:300387210"
    ]
},
  "bbox": [],
  "geometry": {"coordinates":[-78.8333,36.9167],"type":"Point"}
}