{
  "id": 7257115,
  "type": "Feature",
  "properties": {
    "tgn:concordances":{
        "gn:id":"2759590"
    },
    "tgn:hierarchy":[
        "tgn:7257115",
        "tgn:1000003",
        "tgn:7006951",
        "tgn:7016845",
        "tgn:7029392"
    ],
    "tgn:id":7257115,
    "tgn:name:nl":"Axwijk",
    "tgn:placetype":[
        "aat:300008347"
    ]
},
  "bbox": [],
  "geometry": {"coordinates":[5.016667,52.533333],"type":"Point"}
}