{
  "id": 2416733,
  "type": "Feature",
  "properties": {
    "tgn:hierarchy":[
        "tgn:2416733",
        "tgn:1000001",
        "tgn:7012149",
        "tgn:7029392"
    ],
    "tgn:id":2416733,
    "tgn:name":"Jack Mountain",
    "tgn:placetype":[
        "aat:300386831"
    ]
},
  "bbox": [],
  "geometry": {"coordinates":[-79.5833,38.3333],"type":"Point"}
}