{
  "id": 1049557,
  "type": "Feature",
  "properties": {
    "tgn:hierarchy":[
        "tgn:1049557",
        "tgn:1000003",
        "tgn:7024128",
        "tgn:7006366",
        "tgn:7029392"
    ],
    "tgn:id":1049557,
    "tgn:name":"Turobin",
    "tgn:placetype":[
        "aat:300008347"
    ]
},
  "bbox": [],
  "geometry": {"coordinates":[22.75,50.8333],"type":"Point"}
}