{
  "id": 7568059,
  "type": "Feature",
  "properties": {
    "tgn:hierarchy":[
        "tgn:7568059",
        "tgn:1000004",
        "tgn:1001869",
        "tgn:7000198",
        "tgn:7029392"
    ],
    "tgn:id":7568059,
    "tgn:name:en":"Shoal Bank",
    "tgn:placetype":[
        "aat:300387036"
    ]
},
  "bbox": [],
  "geometry": {"coordinates":[70.753056,20.691944],"type":"Point"}
}