{
  "id": 1050473,
  "type": "Feature",
  "properties": {
    "tgn:hierarchy":[
        "tgn:1050473",
        "tgn:7019094",
        "tgn:7002444",
        "tgn:1000003",
        "tgn:7009993",
        "tgn:7008591",
        "tgn:7029392"
    ],
    "tgn:id":1050473,
    "tgn:name:en":"Bridgend",
    "tgn:placetype":[
        "aat:300008347"
    ]
},
  "bbox": [],
  "geometry": {"coordinates":[-6.233333,55.766667],"type":"Point"}
}