{
  "id": 7560457,
  "type": "Feature",
  "properties": {
    "tgn:hierarchy":[
        "tgn:7560457",
        "tgn:1000004",
        "tgn:7000198",
        "tgn:7016722",
        "tgn:7029392"
    ],
    "tgn:id":7560457,
    "tgn:name:en":"Nagla Khajvaiya",
    "tgn:placetype":[
        "aat:300008347"
    ]
},
  "bbox": [],
  "geometry": {"coordinates":[79.373733,27.198634],"type":"Point"}
}