{
  "id": 2300272,
  "type": "Feature",
  "properties": {
    "tgn:hierarchy":[
        "tgn:2300272",
        "tgn:1000001",
        "tgn:7006451",
        "tgn:2000092",
        "tgn:7012149",
        "tgn:7029392"
    ],
    "tgn:id":2300272,
    "tgn:name":"Dugway Tank",
    "tgn:placetype":[
        "aat:300006191"
    ]
},
  "bbox": [],
  "geometry": {"coordinates":[-112.25,36.4667],"type":"Point"}
}