{
  "id": 7491269,
  "type": "Feature",
  "properties": {
    "tgn:hierarchy":[
        "tgn:7491269",
        "tgn:1000004",
        "tgn:1000454",
        "tgn:1000141",
        "tgn:7029392"
    ],
    "tgn:id":7491269,
    "tgn:name":"Banping Shan",
    "tgn:placetype":[
        "aat:300008798"
    ]
},
  "bbox": [],
  "geometry": {"coordinates":[121.868829,25.102443],"type":"Point"}
}