{
  "id": 7252211,
  "type": "Feature",
  "properties": {
    "tgn:hierarchy":[
        "tgn:7252211",
        "tgn:7003460",
        "tgn:1000003",
        "tgn:1000063",
        "tgn:4012014",
        "tgn:7029392"
    ],
    "tgn:id":7252211,
    "tgn:name":"Messitert",
    "tgn:placetype":[
        "aat:300008347"
    ]
},
  "bbox": [],
  "geometry": {"coordinates":[5.85,50.683333],"type":"Point"}
}