{
  "id": 2068574,
  "type": "Feature",
  "properties": {
    "tgn:hierarchy":[
        "tgn:2068574",
        "tgn:1000001",
        "tgn:7012149",
        "tgn:7016021",
        "tgn:7007568",
        "tgn:7029392"
    ],
    "tgn:id":2068574,
    "tgn:name":"Coffins Mills",
    "tgn:placetype":[
        "aat:300008347",
        "aat:300387210"
    ]
},
  "bbox": [],
  "geometry": {"coordinates":[-75.0833,44.1667],"type":"Point"}
}