{
  "id": 7502304,
  "type": "Feature",
  "properties": {
    "tgn:hierarchy":[
        "tgn:7502304",
        "tgn:7001004",
        "tgn:1000004",
        "tgn:1000141",
        "tgn:7029392"
    ],
    "tgn:id":7502304,
    "tgn:name":"Tieben Shan",
    "tgn:placetype":[
        "aat:300008798"
    ]
},
  "bbox": [],
  "geometry": {"coordinates":[120.865833,23.229167],"type":"Point"}
}