{
  "id": 2730928,
  "type": "Feature",
  "properties": {
    "tgn:hierarchy":[
        "tgn:2730928",
        "tgn:1000001",
        "tgn:7012149",
        "tgn:2000823",
        "tgn:7007255",
        "tgn:7029392"
    ],
    "tgn:id":2730928,
    "tgn:name":"Tubbs Branch",
    "tgn:placetype":[
        "aat:300008699"
    ]
},
  "bbox": [],
  "geometry": {"coordinates":[-88.2833,36.8667],"type":"Point"}
}