{
  "id": 2657165,
  "type": "Feature",
  "properties": {
    "tgn:hierarchy":[
        "tgn:2657165",
        "tgn:1000001",
        "tgn:7012149",
        "tgn:2001884",
        "tgn:7007825",
        "tgn:7029392"
    ],
    "tgn:id":2657165,
    "tgn:name":"Sheep Ridge",
    "tgn:placetype":[
        "aat:300266640"
    ]
},
  "bbox": [],
  "geometry": {"coordinates":[-89.5667,36.3167],"type":"Point"}
}