{
  "id": 7203950,
  "type": "Feature",
  "properties": {
    "tgn:hierarchy":[
        "tgn:7203950",
        "tgn:7003692",
        "tgn:1000003",
        "tgn:7000084",
        "tgn:7029392"
    ],
    "tgn:id":7203950,
    "tgn:name":"Br\u00fchl",
    "tgn:placetype":[
        "aat:300008347"
    ]
},
  "bbox": [],
  "geometry": {"coordinates":[8.533611,49.397222],"type":"Point"}
}