{
  "id": 2131633,
  "type": "Feature",
  "properties": {
    "tgn:hierarchy":[
        "tgn:2131633",
        "tgn:1000001",
        "tgn:7012149",
        "tgn:2001458",
        "tgn:7007566",
        "tgn:7029392"
    ],
    "tgn:id":2131633,
    "tgn:name":"Alvas Tank",
    "tgn:placetype":[
        "aat:300006191"
    ]
},
  "bbox": [],
  "geometry": {"coordinates":[-105.4333,34.85],"type":"Point"}
}