{
  "id": 2685898,
  "type": "Feature",
  "properties": {
    "tgn:hierarchy":[
        "tgn:2685898",
        "tgn:1000001",
        "tgn:7012149",
        "tgn:2002110",
        "tgn:7007827",
        "tgn:7029392"
    ],
    "tgn:id":2685898,
    "tgn:name":"Spring Branch",
    "tgn:placetype":[
        "aat:300008699"
    ]
},
  "bbox": [],
  "geometry": {"coordinates":[-109.2667,38.5667],"type":"Point"}
}