{
  "id": 2734344,
  "type": "Feature",
  "properties": {
    "tgn:hierarchy":[
        "tgn:2734344",
        "tgn:1000001",
        "tgn:7012149",
        "tgn:2000931",
        "tgn:7007515",
        "tgn:7029392"
    ],
    "tgn:id":2734344,
    "tgn:name":"Turtle Head Cove",
    "tgn:placetype":[
        "aat:300132316"
    ]
},
  "bbox": [],
  "geometry": {"coordinates":[-68.8833,44.3667],"type":"Point"}
}