{
  "id": 2309170,
  "type": "Feature",
  "properties": {
    "tgn:hierarchy":[
        "tgn:2309170",
        "tgn:1000001",
        "tgn:7012149",
        "tgn:2002381",
        "tgn:7007923",
        "tgn:7029392"
    ],
    "tgn:id":2309170,
    "tgn:name":"East Side Ditch",
    "tgn:placetype":[
        "aat:300006075"
    ]
},
  "bbox": [],
  "geometry": {"coordinates":[-106.95,44.6833],"type":"Point"}
}