<<<<<<< HEAD
{
  "id": 2154442,
  "type": "Feature",
  "properties": {
    "tgn:hierarchy":[
        "tgn:2154442",
        "tgn:1000001",
        "tgn:7012149",
        "tgn:2002278",
        "tgn:7013961",
        "tgn:7029392"
    ],
    "tgn:id":2154442,
    "tgn:name":"Bear Creek",
    "tgn:placetype":[
        "aat:300008706"
    ]
},
  "bbox": [],
  "geometry": {"coordinates":[-81.15,37.55],"type":"Point"}
}
=======
{"geometry":{"type":"Point","coordinates":[-81.150000,37.550000]},"type":"Feature","properties":{"hierarchy":["tgn:2154442","tgn:1000001","tgn:7012149","tgn:2002278","tgn:7013961","tgn:7029392"],"placetype":["aat:300008706"],"id":2154442,"name:xx":"Bear Creek"}}
>>>>>>> 03f74aca74312dbeaf24d7e61306dd6a786dc3d0
