{
  "id": 2734458,
  "type": "Feature",
  "properties": {
    "tgn:hierarchy":[
        "tgn:2734458",
        "tgn:1000001",
        "tgn:1002923",
        "tgn:7012149",
        "tgn:7007517",
        "tgn:7029392"
    ],
    "tgn:id":2734458,
    "tgn:name":"Turtle Pond",
    "tgn:placetype":[
        "aat:300008680"
    ]
},
  "bbox": [],
  "geometry": {"coordinates":[-71.1333,42.25],"type":"Point"}
}