{
  "id": 7037280,
  "type": "Feature",
  "properties": {
    "tgn:hierarchy":[
        "tgn:7037280",
        "tgn:1000003",
        "tgn:7003142",
        "tgn:7003236",
        "tgn:1000080",
        "tgn:7029392"
    ],
    "tgn:id":7037280,
    "tgn:name":"Vallebuona",
    "tgn:placetype":[
        "aat:300008347"
    ]
},
  "bbox": [],
  "geometry": {"coordinates":[9.116667,44.45],"type":"Point"}
}