{
  "id": 2535031,
  "type": "Feature",
  "properties": {
    "tgn:hierarchy":[
        "tgn:2535031",
        "tgn:1000001",
        "tgn:7012149",
        "tgn:7007827",
        "tgn:7029392"
    ],
    "tgn:id":2535031,
    "tgn:name":"Nampab Swale",
    "tgn:placetype":[
        "aat:300008761"
    ]
},
  "bbox": [],
  "geometry": {"coordinates":[-111.6833,38.5167],"type":"Point"}
}