{
  "id": 2508161,
  "type": "Feature",
  "properties": {
    "tgn:hierarchy":[
        "tgn:2508161",
        "tgn:1000001",
        "tgn:7012149",
        "tgn:2000933",
        "tgn:7007515",
        "tgn:7029392"
    ],
    "tgn:id":2508161,
    "tgn:name":"Middle Branch Mousam River",
    "tgn:placetype":[
        "aat:300008707"
    ]
},
  "bbox": [],
  "geometry": {"coordinates":[-70.7667,43.55],"type":"Point"}
}