{
  "id": 7503935,
  "type": "Feature",
  "properties": {
    "tgn:hierarchy":[
        "tgn:7503935",
        "tgn:7016670",
        "tgn:1008380",
        "tgn:1000226",
        "tgn:1000006",
        "tgn:7029392"
    ],
    "tgn:id":7503935,
    "tgn:name:en":"Whakamarumaru",
    "tgn:placetype":[
        "aat:300000206"
    ]
},
  "bbox": [],
  "geometry": {"coordinates":[176.533333,-39.566667],"type":"Point"}
}