<<<<<<< HEAD
{
  "id": 7356644,
  "type": "Feature",
  "properties": {
    "tgn:hierarchy":[
        "tgn:7356644",
        "tgn:1001853",
        "tgn:1000001",
        "tgn:7005560",
        "tgn:7029392"
    ],
    "tgn:id":7356644,
    "tgn:name":"Carra, Sierra de la",
    "tgn:placetype":[
        "aat:300008795"
    ]
},
  "bbox": [],
  "geometry": {"coordinates":[-101.716667,24.933333],"type":"Point"}
}
=======
{"geometry":{"type":"Point","coordinates":[-101.716667,24.933333]},"type":"Feature","properties":{"hierarchy":["tgn:7356644","tgn:1001853","tgn:1000001","tgn:7005560","tgn:7029392"],"placetype":["aat:300008795"],"id":7356644,"name:xx":"Carra, Sierra de la"}}
>>>>>>> 03f74aca74312dbeaf24d7e61306dd6a786dc3d0
