{
  "id": 7490930,
  "type": "Feature",
  "properties": {
    "tgn:hierarchy":[
        "tgn:7490930",
        "tgn:1000957",
        "tgn:1000004",
        "tgn:1000141",
        "tgn:7029392"
    ],
    "tgn:id":7490930,
    "tgn:name":"Taibaizhuang",
    "tgn:placetype":[
        "aat:300008347"
    ]
},
  "bbox": [],
  "geometry": {"coordinates":[121.744039,25.152868],"type":"Point"}
}