{
  "id": 7115068,
  "type": "Feature",
  "properties": {
    "tgn:hierarchy":[
        "tgn:7115068",
        "tgn:1000003",
        "tgn:7003688",
        "tgn:7000084",
        "tgn:7029392"
    ],
    "tgn:id":7115068,
    "tgn:name":"Oldgras",
    "tgn:placetype":[
        "aat:300008347"
    ]
},
  "bbox": [],
  "geometry": {"coordinates":[9.033333,54.483333],"type":"Point"}
}