{
  "id": 2553684,
  "type": "Feature",
  "properties": {
    "tgn:hierarchy":[
        "tgn:2553684",
        "tgn:1000001",
        "tgn:7012149",
        "tgn:2002297",
        "tgn:7013961",
        "tgn:7029392"
    ],
    "tgn:id":2553684,
    "tgn:name":"Oak Grove Ridge",
    "tgn:placetype":[
        "aat:300266640"
    ]
},
  "bbox": [],
  "geometry": {"coordinates":[-81.05,39.4667],"type":"Point"}
}