{
  "id": 2758526,
  "type": "Feature",
  "properties": {
    "tgn:hierarchy":[
        "tgn:2758526",
        "tgn:1000001",
        "tgn:7012149",
        "tgn:2001036",
        "tgn:7007521",
        "tgn:7029392"
    ],
    "tgn:id":2758526,
    "tgn:name":"West Chub Lake",
    "tgn:placetype":[
        "aat:300008680"
    ]
},
  "bbox": [],
  "geometry": {"coordinates":[-91.6333,47.6667],"type":"Point"}
}