{
  "id": 2268385,
  "type": "Feature",
  "properties": {
    "tgn:hierarchy":[
        "tgn:2268385",
        "tgn:1000001",
        "tgn:7012149",
        "tgn:7007564",
        "tgn:7029392"
    ],
    "tgn:id":2268385,
    "tgn:name":"Crooked Run",
    "tgn:placetype":[
        "aat:300008699"
    ]
},
  "bbox": [],
  "geometry": {"coordinates":[-71.2333,43.2833],"type":"Point"}
}