{
  "id": 7404204,
  "type": "Feature",
  "properties": {
    "tgn:hierarchy":[
        "tgn:7404204",
        "tgn:7005585",
        "tgn:1000001",
        "tgn:7005560",
        "tgn:7029392"
    ],
    "tgn:id":7404204,
    "tgn:name":"R\u00edo Fr\u00edo",
    "tgn:placetype":[
        "aat:300008347"
    ]
},
  "bbox": [],
  "geometry": {"coordinates":[-101.083333,17.866667],"type":"Point"}
}