{
  "id": 7348439,
  "type": "Feature",
  "properties": {
    "tgn:hierarchy":[
        "tgn:7348439",
        "tgn:7007780",
        "tgn:1000003",
        "tgn:7009604",
        "tgn:1000095",
        "tgn:7029392"
    ],
    "tgn:id":7348439,
    "tgn:name":"Aeta",
    "tgn:placetype":[
        "aat:300008347"
    ]
},
  "bbox": [],
  "geometry": {"coordinates":[-2.298573,43.076087],"type":"Point"}
}