{
  "id": 7306539,
  "type": "Feature",
  "properties": {
    "tgn:hierarchy":[
        "tgn:7306539",
        "tgn:1001439",
        "tgn:1000003",
        "tgn:7002797",
        "tgn:1000095",
        "tgn:7029392"
    ],
    "tgn:id":7306539,
    "tgn:name":"Los Puchos",
    "tgn:placetype":[
        "aat:300008347"
    ]
},
  "bbox": [],
  "geometry": {"coordinates":[-1.116667,37.633333],"type":"Point"}
}