{
  "id": 7296732,
  "type": "Feature",
  "properties": {
    "tgn:hierarchy":[
        "tgn:7296732",
        "tgn:7002758",
        "tgn:7002841",
        "tgn:1000003",
        "tgn:1000095",
        "tgn:7029392"
    ],
    "tgn:id":7296732,
    "tgn:name":"Convento",
    "tgn:placetype":[
        "aat:300387033"
    ]
},
  "bbox": [],
  "geometry": {"coordinates":[-6.038611,37.136944],"type":"Point"}
}