{
  "id": 7389428,
  "type": "Feature",
  "properties": {
    "tgn:hierarchy":[
        "tgn:7389428",
        "tgn:1000001",
        "tgn:7005596",
        "tgn:7005560",
        "tgn:7029392"
    ],
    "tgn:id":7389428,
    "tgn:name":"Reforma Agraria",
    "tgn:placetype":[
        "aat:300008347"
    ]
},
  "bbox": [],
  "geometry": {"coordinates":[-91.25,17.366667],"type":"Point"}
}