{
  "id": 2523255,
  "type": "Feature",
  "properties": {
    "tgn:hierarchy":[
        "tgn:2523255",
        "tgn:1002136",
        "tgn:1000001",
        "tgn:7012149",
        "tgn:7007706",
        "tgn:7029392"
    ],
    "tgn:id":2523255,
    "tgn:name":"Moores Run",
    "tgn:placetype":[
        "aat:300008699"
    ]
},
  "bbox": [],
  "geometry": {"coordinates":[-83.55,38.7333],"type":"Point"}
}