{
  "id": 1014882,
  "type": "Feature",
  "properties": {
    "tgn:hierarchy":[
        "tgn:1014882",
        "tgn:7005685",
        "tgn:1000001",
        "tgn:7013154",
        "tgn:7029392"
    ],
    "tgn:id":1014882,
    "tgn:name":"Listowel",
    "tgn:placetype":[
        "aat:300008347"
    ]
},
  "bbox": [],
  "geometry": {"coordinates":[-80.95,43.7333],"type":"Point"}
}