{
  "id": 1093832,
  "type": "Feature",
  "properties": {
    "tgn:hierarchy":[
        "tgn:1093832",
        "tgn:7001242",
        "tgn:7017584",
        "tgn:1000193",
        "tgn:7029392"
    ],
    "tgn:id":1093832,
    "tgn:name":"Worcester",
    "tgn:placetype":[
        "aat:300008347"
    ]
},
  "bbox": [],
  "geometry": {"coordinates":[19.4333,-33.65],"type":"Point"}
}