<<<<<<< HEAD
{
  "id": 7487694,
  "type": "Feature",
  "properties": {
    "tgn:hierarchy":[
        "tgn:7487694",
        "tgn:1000004",
        "tgn:7001009",
        "tgn:1000141",
        "tgn:7029392"
    ],
    "tgn:id":7487694,
    "tgn:name":"Liugu Cun",
    "tgn:placetype":[
        "aat:300008347",
        "aat:300387200"
    ]
},
  "bbox": [],
  "geometry": {"coordinates":[120.6912,24.0418],"type":"Point"}
}
=======
{"geometry":{"type":"Point","coordinates":[120.691200,24.041800]},"type":"Feature","properties":{"hierarchy":["tgn:7487694","tgn:1000004","tgn:7001009","tgn:1000141","tgn:7029392"],"placetype":["aat:300008347","aat:300387200"],"id":7487694,"name:xx":"Liugu Cun"}}
>>>>>>> 03f74aca74312dbeaf24d7e61306dd6a786dc3d0
