{
  "id": 7350928,
  "type": "Feature",
  "properties": {
    "tgn:hierarchy":[
        "tgn:7350928",
        "tgn:1000001",
        "tgn:7005594",
        "tgn:7005560",
        "tgn:7029392"
    ],
    "tgn:id":7350928,
    "tgn:name":"Bledos",
    "tgn:placetype":[
        "aat:300008347"
    ]
},
  "bbox": [],
  "geometry": {"coordinates":[-101.116667,21.85],"type":"Point"}
}