{
  "id": 2309293,
  "type": "Feature",
  "properties": {
    "tgn:hierarchy":[
        "tgn:2309293",
        "tgn:1000001",
        "tgn:7012149",
        "tgn:2002376",
        "tgn:7007923",
        "tgn:7029392"
    ],
    "tgn:id":2309293,
    "tgn:name":"East Stock Ditch",
    "tgn:placetype":[
        "aat:300006075"
    ]
},
  "bbox": [],
  "geometry": {"coordinates":[-110.65,42.05],"type":"Point"}
}