{
  "id": 7280956,
  "type": "Feature",
  "properties": {
    "tgn:hierarchy":[
        "tgn:7280956",
        "tgn:1001637",
        "tgn:1000049",
        "tgn:1000002",
        "tgn:7029392"
    ],
    "tgn:id":7280956,
    "tgn:name":"Taimo",
    "tgn:placetype":[
        "aat:300008347"
    ]
},
  "bbox": [],
  "geometry": {"coordinates":[-72.616667,-36.216667],"type":"Point"}
}