{
  "id": 7499756,
  "type": "Feature",
  "properties": {
    "tgn:hierarchy":[
        "tgn:7499756",
        "tgn:7488858",
        "tgn:1000004",
        "tgn:1000141",
        "tgn:7029392"
    ],
    "tgn:id":7499756,
    "tgn:name":"Dongluanda Shan Xiyou",
    "tgn:placetype":[
        "aat:300008699"
    ]
},
  "bbox": [],
  "geometry": {"coordinates":[121.015083,23.630136],"type":"Point"}
}