{
  "id": 7494255,
  "type": "Feature",
  "properties": {
    "tgn:hierarchy":[
        "tgn:7494255",
        "tgn:7468018",
        "tgn:1000004",
        "tgn:1000141",
        "tgn:7029392"
    ],
    "tgn:id":7494255,
    "tgn:name":"Zhonglin Guoxiao",
    "tgn:placetype":[
        "aat:300006495"
    ]
},
  "bbox": [],
  "geometry": {"coordinates":[120.477963,23.589363],"type":"Point"}
}