{
  "id": 2426355,
  "type": "Feature",
  "properties": {
    "tgn:hierarchy":[
        "tgn:2426355",
        "tgn:1000001",
        "tgn:7012149",
        "tgn:1002699",
        "tgn:7007708",
        "tgn:7029392"
    ],
    "tgn:id":2426355,
    "tgn:name":"Jones Creek",
    "tgn:placetype":[
        "aat:300008706"
    ]
},
  "bbox": [],
  "geometry": {"coordinates":[-122.8833,45.6833],"type":"Point"}
}