{
  "id": 2559872,
  "type": "Feature",
  "properties": {
    "tgn:hierarchy":[
        "tgn:2559872",
        "tgn:1007657",
        "tgn:1002534",
        "tgn:1000001",
        "tgn:7012149",
        "tgn:7007249",
        "tgn:7029392"
    ],
    "tgn:id":2559872,
    "tgn:name":"Opoi",
    "tgn:placetype":[
        "aat:300055621"
    ]
},
  "bbox": [],
  "geometry": {"coordinates":[-159.3333,21.9667],"type":"Point"}
}