{
  "id": 2612784,
  "type": "Feature",
  "properties": {
    "tgn:hierarchy":[
        "tgn:2612784",
        "tgn:1000001",
        "tgn:2000672",
        "tgn:7012149",
        "tgn:7007254",
        "tgn:7029392"
    ],
    "tgn:id":2612784,
    "tgn:name":"Redhole Creek",
    "tgn:placetype":[
        "aat:300008706"
    ]
},
  "bbox": [],
  "geometry": {"coordinates":[-99.8333,37.2167],"type":"Point"}
}