{
  "id": 1132611,
  "type": "Feature",
  "properties": {
    "tgn:hierarchy":[
        "tgn:1132611",
        "tgn:1000001",
        "tgn:7012149",
        "tgn:7007826",
        "tgn:7029392"
    ],
    "tgn:id":1132611,
    "tgn:name":"Buckners Creek",
    "tgn:placetype":[
        "aat:300008706"
    ]
},
  "bbox": [],
  "geometry": {"coordinates":[-97.2333,29.8833],"type":"Point"}
}