{
  "id": 1075523,
  "type": "Feature",
  "properties": {
    "tgn:hierarchy":[
        "tgn:1075523",
        "tgn:1000004",
        "tgn:7000198",
        "tgn:1001886",
        "tgn:7029392"
    ],
    "tgn:id":1075523,
    "tgn:name":"Irinjalakuda",
    "tgn:placetype":[
        "aat:300008347"
    ]
},
  "bbox": [],
  "geometry": {"coordinates":[76.233333,10.333333],"type":"Point"}
}