{
  "id": 1107248,
  "type": "Feature",
  "properties": {
    "tgn:hierarchy":[
        "tgn:1107248",
        "tgn:1000004",
        "tgn:1000145",
        "tgn:7029392"
    ],
    "tgn:id":1107248,
    "tgn:name":"Fan Si Pan",
    "tgn:placetype":[
        "aat:300008798"
    ]
},
  "bbox": [],
  "geometry": {"coordinates":[103.7667,22.25],"type":"Point"}
}