<<<<<<< HEAD
{
  "id": 2764583,
  "type": "Feature",
  "properties": {
    "tgn:hierarchy":[
        "tgn:2764583",
        "tgn:1000001",
        "tgn:7012149",
        "tgn:2000628",
        "tgn:7007253",
        "tgn:7029392"
    ],
    "tgn:id":2764583,
    "tgn:name":"Whippoorwill Creek",
    "tgn:placetype":[
        "aat:300008706"
    ]
},
  "bbox": [],
  "geometry": {"coordinates":[-93.05,41.0],"type":"Point"}
}
=======
{"geometry":{"type":"Point","coordinates":[-93.050000,41.000000]},"type":"Feature","properties":{"hierarchy":["tgn:2764583","tgn:1000001","tgn:7012149","tgn:2000628","tgn:7007253","tgn:7029392"],"placetype":["aat:300008706"],"id":2764583,"name:xx":"Whippoorwill Creek"}}
>>>>>>> 03f74aca74312dbeaf24d7e61306dd6a786dc3d0
