{
  "id": 7431109,
  "type": "Feature",
  "properties": {
    "tgn:hierarchy":[
        "tgn:7431109",
        "tgn:1000001",
        "tgn:7005595",
        "tgn:7005560",
        "tgn:7029392"
    ],
    "tgn:id":7431109,
    "tgn:name":"El Desenga\u00f1o",
    "tgn:placetype":[
        "aat:300008347"
    ]
},
  "bbox": [],
  "geometry": {"coordinates":[-109.016667,26.35],"type":"Point"}
}