{
  "id": 2031891,
  "type": "Feature",
  "properties": {
    "tgn:hierarchy":[
        "tgn:2031891",
        "tgn:1000001",
        "tgn:1002306",
        "tgn:7012149",
        "tgn:7007252",
        "tgn:7029392"
    ],
    "tgn:id":2031891,
    "tgn:name":"Fredonia",
    "tgn:placetype":[
        "aat:300008347"
    ]
},
  "bbox": [],
  "geometry": {"coordinates":[-86.3667,38.1667],"type":"Point"}
}