{
  "id": 1117299,
  "type": "Feature",
  "properties": {
    "tgn:hierarchy":[
        "tgn:1117299",
        "tgn:7000895",
        "tgn:1000004",
        "tgn:1000974",
        "tgn:1000120",
        "tgn:7029392"
    ],
    "tgn:id":1117299,
    "tgn:name":"Mikata-ko",
    "tgn:placetype":[
        "aat:300008680"
    ]
},
  "bbox": [],
  "geometry": {"coordinates":[135.8833,35.5667],"type":"Point"}
}