{
  "id": 2558470,
  "type": "Feature",
  "properties": {
    "tgn:hierarchy":[
        "tgn:2558470",
        "tgn:1000001",
        "tgn:7012149",
        "tgn:2000182",
        "tgn:7007157",
        "tgn:7029392"
    ],
    "tgn:id":2558470,
    "tgn:name":"Olive Drain",
    "tgn:placetype":[
        "aat:300006075"
    ]
},
  "bbox": [],
  "geometry": {"coordinates":[-115.35,32.9333],"type":"Point"}
}