<<<<<<< HEAD
{
  "id": 7050795,
  "type": "Feature",
  "properties": {
    "tgn:hierarchy":[
        "tgn:7050795",
        "tgn:7003163",
        "tgn:1000003",
        "tgn:7009760",
        "tgn:1000080",
        "tgn:7029392"
    ],
    "tgn:id":7050795,
    "tgn:name":"Massa Nera, Poggio",
    "tgn:placetype":[
        "aat:300008795"
    ]
},
  "bbox": [],
  "geometry": {"coordinates":[11.55,43.7],"type":"Point"}
}
=======
{"geometry":{"type":"Point","coordinates":[11.550000,43.700000]},"type":"Feature","properties":{"hierarchy":["tgn:7050795","tgn:7003163","tgn:1000003","tgn:7009760","tgn:1000080","tgn:7029392"],"placetype":["aat:300008795"],"id":7050795,"name:xx":"Massa Nera, Poggio"}}
>>>>>>> 03f74aca74312dbeaf24d7e61306dd6a786dc3d0
