{
  "id": 7270116,
  "type": "Feature",
  "properties": {
    "tgn:concordances":{
        "gn:id":"2750572"
    },
    "tgn:hierarchy":[
        "tgn:7270116",
        "tgn:1000003",
        "tgn:7003624",
        "tgn:7016845",
        "tgn:7029392"
    ],
    "tgn:id":7270116,
    "tgn:name:nl":"Muggenhoek",
    "tgn:placetype":[
        "aat:300008347"
    ]
},
  "bbox": [],
  "geometry": {"coordinates":[5.483333,51.65],"type":"Point"}
}