{
  "id": 7304710,
  "type": "Feature",
  "properties": {
    "tgn:hierarchy":[
        "tgn:7304710",
        "tgn:7002832",
        "tgn:7001158",
        "tgn:1000003",
        "tgn:1000095",
        "tgn:7029392"
    ],
    "tgn:id":7304710,
    "tgn:name":"Lebanza",
    "tgn:placetype":[
        "aat:300008347"
    ]
},
  "bbox": [],
  "geometry": {"coordinates":[-4.516667,42.966667],"type":"Point"}
}