{
  "id": 7383685,
  "type": "Feature",
  "properties": {
    "tgn:hierarchy":[
        "tgn:7383685",
        "tgn:1000001",
        "tgn:7005594",
        "tgn:7005560",
        "tgn:7029392"
    ],
    "tgn:id":7383685,
    "tgn:name":"Paradita",
    "tgn:placetype":[
        "aat:300008347"
    ]
},
  "bbox": [],
  "geometry": {"coordinates":[-100.533333,22.35],"type":"Point"}
}