<<<<<<< HEAD
{
  "id": 7117906,
  "type": "Feature",
  "properties": {
    "tgn:hierarchy":[
        "tgn:7117906",
        "tgn:1000003",
        "tgn:7003678",
        "tgn:7000084",
        "tgn:7029392"
    ],
    "tgn:id":7117906,
    "tgn:name":"Obersensbach",
    "tgn:placetype":[
        "aat:300008347"
    ]
},
  "bbox": [],
  "geometry": {"coordinates":[9.015278,49.561944],"type":"Point"}
}
=======
{"geometry":{"type":"Point","coordinates":[9.015278,49.561944]},"type":"Feature","properties":{"hierarchy":["tgn:7117906","tgn:1000003","tgn:7003678","tgn:7000084","tgn:7029392"],"placetype":["aat:300008347"],"id":7117906,"name:xx":"Obersensbach"}}
>>>>>>> 03f74aca74312dbeaf24d7e61306dd6a786dc3d0
