{
  "id": 1098722,
  "type": "Feature",
  "properties": {
    "tgn:hierarchy":[
        "tgn:1098722",
        "tgn:7006215",
        "tgn:1009344",
        "tgn:1000216",
        "tgn:1000006",
        "tgn:7029392"
    ],
    "tgn:id":1098722,
    "tgn:name":"Hanatetena",
    "tgn:placetype":[
        "aat:300008347"
    ]
},
  "bbox": [],
  "geometry": {"coordinates":[-139.0667,-9.9667],"type":"Point"}
}