{
  "id": 7209993,
  "type": "Feature",
  "properties": {
    "tgn:hierarchy":[
        "tgn:7209993",
        "tgn:1000003",
        "tgn:7003678",
        "tgn:7000084",
        "tgn:7029392"
    ],
    "tgn:id":7209993,
    "tgn:name":"Bengendorf",
    "tgn:placetype":[
        "aat:300008347"
    ]
},
  "bbox": [],
  "geometry": {"coordinates":[9.966667,50.883333],"type":"Point"}
}