{
  "id": 7339986,
  "type": "Feature",
  "properties": {
    "tgn:hierarchy":[
        "tgn:7339986",
        "tgn:7002810",
        "tgn:7001158",
        "tgn:1000003",
        "tgn:1000095",
        "tgn:7029392"
    ],
    "tgn:id":7339986,
    "tgn:name":"Cotero, Alto",
    "tgn:placetype":[
        "aat:300008795"
    ]
},
  "bbox": [],
  "geometry": {"coordinates":[-3.75,43.083333],"type":"Point"}
}