{
  "id": 7571510,
  "type": "Feature",
  "properties": {
    "tgn:hierarchy":[
        "tgn:7571510",
        "tgn:1000004",
        "tgn:7000198",
        "tgn:7016722",
        "tgn:7029392"
    ],
    "tgn:id":7571510,
    "tgn:name:en":"Jarwal Road",
    "tgn:placetype":[
        "aat:300007783"
    ]
},
  "bbox": [],
  "geometry": {"coordinates":[81.537826,27.120199],"type":"Point"}
}