{
  "id": 7367089,
  "type": "Feature",
  "properties": {
    "tgn:hierarchy":[
        "tgn:7367089",
        "tgn:1000001",
        "tgn:7005589",
        "tgn:7005560",
        "tgn:7029392"
    ],
    "tgn:id":7367089,
    "tgn:name":"El Tronc\u00f3n",
    "tgn:placetype":[
        "aat:300008347"
    ]
},
  "bbox": [],
  "geometry": {"coordinates":[-99.647778,24.776389],"type":"Point"}
}