{
  "id": 2741679,
  "type": "Feature",
  "properties": {
    "tgn:hierarchy":[
        "tgn:2741679",
        "tgn:1000001",
        "tgn:7012149",
        "tgn:2000217",
        "tgn:7007158",
        "tgn:7029392"
    ],
    "tgn:id":2741679,
    "tgn:name":"Ute Gulch",
    "tgn:placetype":[
        "aat:300008761"
    ]
},
  "bbox": [],
  "geometry": {"coordinates":[-106.6667,38.8167],"type":"Point"}
}