{
  "id": 7090708,
  "type": "Feature",
  "properties": {
    "tgn:hierarchy":[
        "tgn:7090708",
        "tgn:1000003",
        "tgn:7003678",
        "tgn:7000084",
        "tgn:7029392"
    ],
    "tgn:id":7090708,
    "tgn:name":"Vogelsberg",
    "tgn:placetype":[
        "aat:300008347"
    ]
},
  "bbox": [],
  "geometry": {"coordinates":[9.716667,50.483333],"type":"Point"}
}