{
  "id": 7362752,
  "type": "Feature",
  "properties": {
    "tgn:hierarchy":[
        "tgn:7362752",
        "tgn:7005586",
        "tgn:1000001",
        "tgn:7005560",
        "tgn:7029392"
    ],
    "tgn:id":7362752,
    "tgn:name":"El Carrizo",
    "tgn:placetype":[
        "aat:300000241"
    ]
},
  "bbox": [],
  "geometry": {"coordinates":[-103.116667,20.733333],"type":"Point"}
}