{
  "id": 7545972,
  "type": "Feature",
  "properties": {
    "tgn:hierarchy":[
        "tgn:7545972",
        "tgn:1000004",
        "tgn:7000198",
        "tgn:1001894",
        "tgn:7029392"
    ],
    "tgn:id":7545972,
    "tgn:name:en":"Bhonria",
    "tgn:placetype":[
        "aat:300008347"
    ]
},
  "bbox": [],
  "geometry": {"coordinates":[77.708784,24.197246],"type":"Point"}
}