{
  "id": 2516190,
  "type": "Feature",
  "properties": {
    "tgn:hierarchy":[
        "tgn:2516190",
        "tgn:1000001",
        "tgn:7012149",
        "tgn:2001846",
        "tgn:7007825",
        "tgn:7029392"
    ],
    "tgn:id":2516190,
    "tgn:name":"Mine Hollow",
    "tgn:placetype":[
        "aat:300008761"
    ]
},
  "bbox": [],
  "geometry": {"coordinates":[-82.0333,36.1667],"type":"Point"}
}