<<<<<<< HEAD
{
  "id": 7022405,
  "type": "Feature",
  "properties": {
    "tgn:hierarchy":[
        "tgn:7022405",
        "tgn:1000001",
        "tgn:7016172",
        "tgn:7012149",
        "tgn:7029392"
    ],
    "tgn:id":7022405,
    "tgn:name":"Blaylock Mountain",
    "tgn:placetype":[
        "aat:300008798"
    ]
},
  "bbox": [],
  "geometry": {"coordinates":[-93.9167,34.35],"type":"Point"}
}
=======
{"geometry":{"type":"Point","coordinates":[-93.916700,34.350000]},"type":"Feature","properties":{"hierarchy":["tgn:7022405","tgn:1000001","tgn:7016172","tgn:7012149","tgn:7029392"],"placetype":["aat:300008798"],"id":7022405,"name:xx":"Blaylock Mountain"}}
>>>>>>> 03f74aca74312dbeaf24d7e61306dd6a786dc3d0
