{
  "id": 7185145,
  "type": "Feature",
  "properties": {
    "tgn:hierarchy":[
        "tgn:7185145",
        "tgn:1000003",
        "tgn:7003685",
        "tgn:7000084",
        "tgn:7029392"
    ],
    "tgn:id":7185145,
    "tgn:name":"G\u00f6rnitz",
    "tgn:placetype":[
        "aat:300008347"
    ]
},
  "bbox": [],
  "geometry": {"coordinates":[12.933333,51.183333],"type":"Point"}
}