{
  "id": 7512030,
  "type": "Feature",
  "properties": {
    "tgn:hierarchy":[
        "tgn:7512030",
        "tgn:1008380",
        "tgn:1000226",
        "tgn:7018426",
        "tgn:1000006",
        "tgn:7029392"
    ],
    "tgn:id":7512030,
    "tgn:name:en":"Kaiaua",
    "tgn:placetype":[
        "aat:300008347"
    ]
},
  "bbox": [],
  "geometry": {"coordinates":[175.283333,-37.133333],"type":"Point"}
}