{
  "id": 7336676,
  "type": "Feature",
  "properties": {
    "tgn:hierarchy":[
        "tgn:7336676",
        "tgn:7002827",
        "tgn:1000003",
        "tgn:7002789",
        "tgn:1000095",
        "tgn:7029392"
    ],
    "tgn:id":7336676,
    "tgn:name":"Gat\u00f3n, R\u00edo",
    "tgn:placetype":[
        "aat:300008699"
    ]
},
  "bbox": [],
  "geometry": {"coordinates":[-2.95,42.15],"type":"Point"}
}