{
  "id": 2786455,
  "type": "Feature",
  "properties": {
    "tgn:hierarchy":[
        "tgn:2786455",
        "tgn:1000001",
        "tgn:7012149",
        "tgn:2001440",
        "tgn:7007566",
        "tgn:7029392"
    ],
    "tgn:id":2786455,
    "tgn:name":"Yucca Claim",
    "tgn:placetype":[
        "aat:300000390"
    ]
},
  "bbox": [],
  "geometry": {"coordinates":[-108.2167,31.75],"type":"Point"}
}