<<<<<<< HEAD
{
  "id": 7481695,
  "type": "Feature",
  "properties": {
    "tgn:hierarchy":[
        "tgn:7481695",
        "tgn:1000004",
        "tgn:7001013",
        "tgn:1000141",
        "tgn:7029392"
    ],
    "tgn:id":7481695,
    "tgn:name":"Fuhua Qiao",
    "tgn:placetype":[
        "aat:300007836"
    ]
},
  "bbox": [],
  "geometry": {"coordinates":[121.37,24.668611],"type":"Point"}
}
=======
{"geometry":{"type":"Point","coordinates":[121.370000,24.668611]},"type":"Feature","properties":{"hierarchy":["tgn:7481695","tgn:1000004","tgn:7001013","tgn:1000141","tgn:7029392"],"placetype":["aat:300007836"],"id":7481695,"name:xx":"Fuhua Qiao"}}
>>>>>>> 03f74aca74312dbeaf24d7e61306dd6a786dc3d0
