{
  "id": 2655298,
  "type": "Feature",
  "properties": {
    "tgn:hierarchy":[
        "tgn:2655298",
        "tgn:1000001",
        "tgn:2000866",
        "tgn:7012149",
        "tgn:7007256",
        "tgn:7029392"
    ],
    "tgn:id":2655298,
    "tgn:name":"Shanty Lake",
    "tgn:placetype":[
        "aat:300008680"
    ]
},
  "bbox": [],
  "geometry": {"coordinates":[-91.6667,31.6833],"type":"Point"}
}