{
  "id": 2650876,
  "type": "Feature",
  "properties": {
    "tgn:hierarchy":[
        "tgn:2650876",
        "tgn:1000001",
        "tgn:7012149",
        "tgn:2000811",
        "tgn:7007255",
        "tgn:7029392"
    ],
    "tgn:id":2650876,
    "tgn:name":"Second Fork",
    "tgn:placetype":[
        "aat:300008699"
    ]
},
  "bbox": [],
  "geometry": {"coordinates":[-83.25,37.1667],"type":"Point"}
}