{
  "id": 2723976,
  "type": "Feature",
  "properties": {
    "tgn:hierarchy":[
        "tgn:2723976",
        "tgn:1000001",
        "tgn:1002328",
        "tgn:7012149",
        "tgn:7007568",
        "tgn:7029392"
    ],
    "tgn:id":2723976,
    "tgn:name":"Toll Gate Brook",
    "tgn:placetype":[
        "aat:300008699"
    ]
},
  "bbox": [],
  "geometry": {"coordinates":[-74.8833,42.2667],"type":"Point"}
}