{
  "id": 2509559,
  "type": "Feature",
  "properties": {
    "tgn:hierarchy":[
        "tgn:2509559",
        "tgn:1000001",
        "tgn:7012149",
        "tgn:7007252",
        "tgn:7029392"
    ],
    "tgn:id":2509559,
    "tgn:name":"Middle Fork Yellow River",
    "tgn:placetype":[
        "aat:300008707"
    ]
},
  "bbox": [],
  "geometry": {"coordinates":[-85.9667,41.4167],"type":"Point"}
}