<<<<<<< HEAD
{
  "id": 2403766,
  "type": "Feature",
  "properties": {
    "tgn:hierarchy":[
        "tgn:2403766",
        "tgn:1000001",
        "tgn:7012149",
        "tgn:1002448",
        "tgn:7007706",
        "tgn:7029392"
    ],
    "tgn:id":2403766,
    "tgn:name":"Howard Run",
    "tgn:placetype":[
        "aat:300008699"
    ]
},
  "bbox": [],
  "geometry": {"coordinates":[-83.6167,41.0833],"type":"Point"}
}
=======
{"geometry":{"type":"Point","coordinates":[-83.616700,41.083300]},"type":"Feature","properties":{"hierarchy":["tgn:2403766","tgn:1000001","tgn:7012149","tgn:1002448","tgn:7007706","tgn:7029392"],"placetype":["aat:300008699"],"id":2403766,"name:xx":"Howard Run"}}
>>>>>>> 03f74aca74312dbeaf24d7e61306dd6a786dc3d0
