{
  "id": 2412277,
  "type": "Feature",
  "properties": {
    "tgn:hierarchy":[
        "tgn:2412277",
        "tgn:1000001",
        "tgn:7012149",
        "tgn:2001288",
        "tgn:7007524",
        "tgn:7029392"
    ],
    "tgn:id":2412277,
    "tgn:name":"Indian Spring Creek",
    "tgn:placetype":[
        "aat:300008706"
    ]
},
  "bbox": [],
  "geometry": {"coordinates":[-111.7167,44.85],"type":"Point"}
}