{
  "id": 7265087,
  "type": "Feature",
  "properties": {
    "tgn:concordances":{
        "gn:id":"2752176"
    },
    "tgn:hierarchy":[
        "tgn:7265087",
        "tgn:7003616",
        "tgn:1000003",
        "tgn:7016845",
        "tgn:7029392"
    ],
    "tgn:id":7265087,
    "tgn:name:nl":"Kuikhorne",
    "tgn:placetype":[
        "aat:300008347"
    ]
},
  "bbox": [],
  "geometry": {"coordinates":[6.016667,53.25],"type":"Point"}
}