{
  "id": 7247831,
  "type": "Feature",
  "properties": {
    "tgn:hierarchy":[
        "tgn:7247831",
        "tgn:7003460",
        "tgn:1000003",
        "tgn:1000063",
        "tgn:4012014",
        "tgn:7029392"
    ],
    "tgn:id":7247831,
    "tgn:name":"Ch\u00ean\u00e9e",
    "tgn:placetype":[
        "aat:300008347"
    ]
},
  "bbox": [],
  "geometry": {"coordinates":[5.616667,50.616667],"type":"Point"}
}