<<<<<<< HEAD
{
  "id": 7247831,
  "type": "Feature",
  "properties": {
    "tgn:hierarchy":[
        "tgn:7247831",
        "tgn:7003460",
        "tgn:1000003",
        "tgn:1000063",
        "tgn:4012014",
        "tgn:7029392"
    ],
    "tgn:id":7247831,
    "tgn:name":"Ch\u00ean\u00e9e",
    "tgn:placetype":[
        "aat:300008347"
    ]
},
  "bbox": [],
  "geometry": {"coordinates":[5.616667,50.616667],"type":"Point"}
}
=======
{"geometry":{"type":"Point","coordinates":[5.616667,50.616667]},"type":"Feature","properties":{"hierarchy":["tgn:7247831","tgn:7003460","tgn:1000003","tgn:1000063","tgn:4012014","tgn:7029392"],"placetype":["aat:300008347"],"id":7247831,"name:xx":"Ch\u00ean\u00e9e"}}
>>>>>>> 03f74aca74312dbeaf24d7e61306dd6a786dc3d0
