{
  "id": 7480785,
  "type": "Feature",
  "properties": {
    "tgn:hierarchy":[
        "tgn:7480785",
        "tgn:7001010",
        "tgn:1000004",
        "tgn:1000141",
        "tgn:7029392"
    ],
    "tgn:id":7480785,
    "tgn:name":"Beifeng Qiao",
    "tgn:placetype":[
        "aat:300007836"
    ]
},
  "bbox": [],
  "geometry": {"coordinates":[121.577778,23.978889],"type":"Point"}
}