{
  "id": 2071803,
  "type": "Feature",
  "properties": {
    "tgn:hierarchy":[
        "tgn:2071803",
        "tgn:1000001",
        "tgn:7012149",
        "tgn:1002758",
        "tgn:7007568",
        "tgn:7029392"
    ],
    "tgn:id":2071803,
    "tgn:name":"Pulaski",
    "tgn:placetype":[
        "aat:300008347"
    ]
},
  "bbox": [],
  "geometry": {"coordinates":[-76.1167,43.5667],"type":"Point"}
}