{
  "id": 7537972,
  "type": "Feature",
  "properties": {
    "tgn:hierarchy":[
        "tgn:7537972",
        "tgn:7001242",
        "tgn:7016833",
        "tgn:1001142",
        "tgn:7029392"
    ],
    "tgn:id":7537972,
    "tgn:name:en":"Nazlat ar Ruhb\u0101n",
    "tgn:placetype":[
        "aat:300008347"
    ]
},
  "bbox": [],
  "geometry": {"coordinates":[31.133333,29.133333],"type":"Point"}
}