{
  "id": 2440523,
  "type": "Feature",
  "properties": {
    "tgn:hierarchy":[
        "tgn:2440523",
        "tgn:1000001",
        "tgn:7013638",
        "tgn:7012149",
        "tgn:7007568",
        "tgn:7029392"
    ],
    "tgn:id":2440523,
    "tgn:name":"Knapp Hollow",
    "tgn:placetype":[
        "aat:300008761"
    ]
},
  "bbox": [],
  "geometry": {"coordinates":[-73.55,42.2167],"type":"Point"}
}