{
  "id": 2457199,
  "type": "Feature",
  "properties": {
    "tgn:hierarchy":[
        "tgn:2457199",
        "tgn:1000001",
        "tgn:7012149",
        "tgn:1002881",
        "tgn:7007240",
        "tgn:7029392"
    ],
    "tgn:id":2457199,
    "tgn:name":"Little Lake Howell",
    "tgn:placetype":[
        "aat:300008680"
    ]
},
  "bbox": [],
  "geometry": {"coordinates":[-81.2667,28.6667],"type":"Point"}
}