{
  "id": 7067390,
  "type": "Feature",
  "properties": {
    "tgn:hierarchy":[
        "tgn:7067390",
        "tgn:7003669",
        "tgn:1000003",
        "tgn:7000084",
        "tgn:7029392"
    ],
    "tgn:id":7067390,
    "tgn:name":"Stockstadt am Main",
    "tgn:placetype":[
        "aat:300008347"
    ]
},
  "bbox": [],
  "geometry": {"coordinates":[9.064167,49.976944],"type":"Point"}
}