{
  "id": 2470139,
  "type": "Feature",
  "properties": {
    "tgn:hierarchy":[
        "tgn:2470139",
        "tgn:1002648",
        "tgn:1000001",
        "tgn:1007799",
        "tgn:7012149",
        "tgn:7007249",
        "tgn:7029392"
    ],
    "tgn:id":2470139,
    "tgn:name":"Lopa Gulch",
    "tgn:placetype":[
        "aat:300008761"
    ]
},
  "bbox": [],
  "geometry": {"coordinates":[-156.85,20.8167],"type":"Point"}
}