{
  "id": 1090337,
  "type": "Feature",
  "properties": {
    "tgn:hierarchy":[
        "tgn:1090337",
        "tgn:7001242",
        "tgn:1000687",
        "tgn:1000168",
        "tgn:7029392"
    ],
    "tgn:id":1090337,
    "tgn:name":"Dianra",
    "tgn:placetype":[
        "aat:300008347"
    ]
},
  "bbox": [],
  "geometry": {"coordinates":[-6.2333,8.75],"type":"Point"}
}