<<<<<<< HEAD
{
  "id": 2761683,
  "type": "Feature",
  "properties": {
    "tgn:hierarchy":[
        "tgn:2761683",
        "tgn:1000001",
        "tgn:1002902",
        "tgn:7012149",
        "tgn:7007516",
        "tgn:7029392"
    ],
    "tgn:id":2761683,
    "tgn:name":"West Point",
    "tgn:placetype":[
        "aat:300008850"
    ]
},
  "bbox": [],
  "geometry": {"coordinates":[-75.8667,38.1333],"type":"Point"}
}
=======
{"geometry":{"type":"Point","coordinates":[-75.866700,38.133300]},"type":"Feature","properties":{"hierarchy":["tgn:2761683","tgn:1000001","tgn:1002902","tgn:7012149","tgn:7007516","tgn:7029392"],"placetype":["aat:300008850"],"id":2761683,"name:xx":"West Point"}}
>>>>>>> 03f74aca74312dbeaf24d7e61306dd6a786dc3d0
