{
  "id": 7587095,
  "type": "Feature",
  "properties": {
    "tgn:hierarchy":[
        "tgn:7587095",
        "tgn:1000004",
        "tgn:1001832",
        "tgn:7000198",
        "tgn:7029392"
    ],
    "tgn:id":7587095,
    "tgn:name:en":"Pathakhuri",
    "tgn:placetype":[
        "aat:300008347"
    ]
},
  "bbox": [],
  "geometry": {"coordinates":[92.400476,24.379259],"type":"Point"}
}