<<<<<<< HEAD
{
  "id": 7363101,
  "type": "Feature",
  "properties": {
    "tgn:hierarchy":[
        "tgn:7363101",
        "tgn:1000001",
        "tgn:7005597",
        "tgn:7005560",
        "tgn:7029392"
    ],
    "tgn:id":7363101,
    "tgn:name":"El Estero",
    "tgn:placetype":[
        "aat:300008347"
    ]
},
  "bbox": [],
  "geometry": {"coordinates":[-98.55,26.2],"type":"Point"}
}
=======
{"geometry":{"type":"Point","coordinates":[-98.550000,26.200000]},"type":"Feature","properties":{"hierarchy":["tgn:7363101","tgn:1000001","tgn:7005597","tgn:7005560","tgn:7029392"],"placetype":["aat:300008347"],"id":7363101,"name:xx":"El Estero"}}
>>>>>>> 03f74aca74312dbeaf24d7e61306dd6a786dc3d0
