{
  "id": 2198254,
  "type": "Feature",
  "properties": {
    "tgn:hierarchy":[
        "tgn:2198254",
        "tgn:1000001",
        "tgn:2001413",
        "tgn:7012149",
        "tgn:7007526",
        "tgn:7029392"
    ],
    "tgn:id":2198254,
    "tgn:name":"Browns Canyon",
    "tgn:placetype":[
        "aat:300008761"
    ]
},
  "bbox": [],
  "geometry": {"coordinates":[-116.1167,39.4167],"type":"Point"}
}