{
  "id": 2314955,
  "type": "Feature",
  "properties": {
    "tgn:hierarchy":[
        "tgn:2314955",
        "tgn:1000001",
        "tgn:7012149",
        "tgn:2001542",
        "tgn:7007709",
        "tgn:7029392"
    ],
    "tgn:id":2314955,
    "tgn:name":"Elkin Valley",
    "tgn:placetype":[
        "aat:300008347"
    ]
},
  "bbox": [],
  "geometry": {"coordinates":[-80.85,36.2667],"type":"Point"}
}