{
  "id": 1040563,
  "type": "Feature",
  "properties": {
    "tgn:hierarchy":[
        "tgn:1040563",
        "tgn:7003669",
        "tgn:1000003",
        "tgn:7000084",
        "tgn:7029392"
    ],
    "tgn:id":1040563,
    "tgn:name":"Oberjoch Pass",
    "tgn:placetype":[
        "aat:300008347"
    ]
},
  "bbox": [],
  "geometry": {"coordinates":[10.45,47.55],"type":"Point"}
}