{
  "id": 7215975,
  "type": "Feature",
  "properties": {
    "tgn:hierarchy":[
        "tgn:7215975",
        "tgn:7003669",
        "tgn:1000003",
        "tgn:7000084",
        "tgn:7029392"
    ],
    "tgn:id":7215975,
    "tgn:name":"Altkreut",
    "tgn:placetype":[
        "aat:300000206"
    ]
},
  "bbox": [],
  "geometry": {"coordinates":[11.033333,47.866667],"type":"Point"}
}