{
  "id": 7564279,
  "type": "Feature",
  "properties": {
    "tgn:hierarchy":[
        "tgn:7564279",
        "tgn:1000004",
        "tgn:7000198",
        "tgn:1001894",
        "tgn:7029392"
    ],
    "tgn:id":7564279,
    "tgn:name:en":"Jetgarh",
    "tgn:placetype":[
        "aat:300008777"
    ]
},
  "bbox": [],
  "geometry": {"coordinates":[79.436432,24.807113],"type":"Point"}
}