{
  "id": 2729085,
  "type": "Feature",
  "properties": {
    "tgn:hierarchy":[
        "tgn:2729085",
        "tgn:2000090",
        "tgn:1000001",
        "tgn:7006451",
        "tgn:7012149",
        "tgn:7029392"
    ],
    "tgn:id":2729085,
    "tgn:name":"Trigo, Cerro",
    "tgn:placetype":[
        "aat:300008798"
    ]
},
  "bbox": [],
  "geometry": {"coordinates":[-109.5667,34.1833],"type":"Point"}
}