{
  "id": 2715509,
  "type": "Feature",
  "properties": {
    "tgn:hierarchy":[
        "tgn:2715509",
        "tgn:1000001",
        "tgn:7012149",
        "tgn:2001896",
        "tgn:7007825",
        "tgn:7029392"
    ],
    "tgn:id":2715509,
    "tgn:name":"Terrell Branch",
    "tgn:placetype":[
        "aat:300008699"
    ]
},
  "bbox": [],
  "geometry": {"coordinates":[-87.0333,35.75],"type":"Point"}
}