{
  "id": 7559655,
  "type": "Feature",
  "properties": {
    "tgn:hierarchy":[
        "tgn:7559655",
        "tgn:1000004",
        "tgn:7000198",
        "tgn:7016722",
        "tgn:7029392"
    ],
    "tgn:id":7559655,
    "tgn:name:en":"Haidalpura",
    "tgn:placetype":[
        "aat:300008347"
    ]
},
  "bbox": [],
  "geometry": {"coordinates":[79.170413,26.26775],"type":"Point"}
}