{
  "id": 2763899,
  "type": "Feature",
  "properties": {
    "tgn:hierarchy":[
        "tgn:2763899",
        "tgn:1000001",
        "tgn:2000924",
        "tgn:7012149",
        "tgn:7007515",
        "tgn:7029392"
    ],
    "tgn:id":2763899,
    "tgn:name":"Wheaton Island",
    "tgn:placetype":[
        "aat:300008791"
    ]
},
  "bbox": [],
  "geometry": {"coordinates":[-68.8667,43.85],"type":"Point"}
}