<<<<<<< HEAD
{
  "id": 2763899,
  "type": "Feature",
  "properties": {
    "tgn:hierarchy":[
        "tgn:2763899",
        "tgn:1000001",
        "tgn:2000924",
        "tgn:7012149",
        "tgn:7007515",
        "tgn:7029392"
    ],
    "tgn:id":2763899,
    "tgn:name":"Wheaton Island",
    "tgn:placetype":[
        "aat:300008791"
    ]
},
  "bbox": [],
  "geometry": {"coordinates":[-68.8667,43.85],"type":"Point"}
}
=======
{"geometry":{"type":"Point","coordinates":[-68.866700,43.850000]},"type":"Feature","properties":{"hierarchy":["tgn:2763899","tgn:1000001","tgn:2000924","tgn:7012149","tgn:7007515","tgn:7029392"],"placetype":["aat:300008791"],"id":2763899,"name:xx":"Wheaton Island"}}
>>>>>>> 03f74aca74312dbeaf24d7e61306dd6a786dc3d0
