{
  "id": 2413574,
  "type": "Feature",
  "properties": {
    "tgn:hierarchy":[
        "tgn:2413574",
        "tgn:1000001",
        "tgn:7012149",
        "tgn:7007158",
        "tgn:2000253",
        "tgn:7029392"
    ],
    "tgn:id":2413574,
    "tgn:name":"Ireland Reservoir Number Five",
    "tgn:placetype":[
        "aat:300006191"
    ]
},
  "bbox": [],
  "geometry": {"coordinates":[-104.5833,40.0833],"type":"Point"}
}