{
  "id": 7492149,
  "type": "Feature",
  "properties": {
    "tgn:hierarchy":[
        "tgn:7492149",
        "tgn:7001004",
        "tgn:1000004",
        "tgn:1000141",
        "tgn:7029392"
    ],
    "tgn:id":7492149,
    "tgn:name":"Dinglaonong",
    "tgn:placetype":[
        "aat:300008347"
    ]
},
  "bbox": [],
  "geometry": {"coordinates":[120.680556,23.086111],"type":"Point"}
}