{
  "id": 1050455,
  "type": "Feature",
  "properties": {
    "tgn:hierarchy":[
        "tgn:1050455",
        "tgn:7002444",
        "tgn:1000003",
        "tgn:7008082",
        "tgn:7008591",
        "tgn:7029392"
    ],
    "tgn:id":1050455,
    "tgn:name:en":"Boath",
    "tgn:placetype":[
        "aat:300008347"
    ]
},
  "bbox": [],
  "geometry": {"coordinates":[-4.383333,57.733333],"type":"Point"}
}