<<<<<<< HEAD
{
  "id": 7369886,
  "type": "Feature",
  "properties": {
    "tgn:hierarchy":[
        "tgn:7369886",
        "tgn:1000001",
        "tgn:7005601",
        "tgn:7005560",
        "tgn:7029392"
    ],
    "tgn:id":7369886,
    "tgn:name":"Guanajuato",
    "tgn:placetype":[
        "aat:300008347"
    ]
},
  "bbox": [],
  "geometry": {"coordinates":[-103.1,23.083333],"type":"Point"}
}
=======
{"geometry":{"type":"Point","coordinates":[-103.100000,23.083333]},"type":"Feature","properties":{"hierarchy":["tgn:7369886","tgn:1000001","tgn:7005601","tgn:7005560","tgn:7029392"],"placetype":["aat:300008347"],"id":7369886,"name:xx":"Guanajuato"}}
>>>>>>> 03f74aca74312dbeaf24d7e61306dd6a786dc3d0
