{
  "id": 2128912,
  "type": "Feature",
  "properties": {
    "tgn:hierarchy":[
        "tgn:2128912",
        "tgn:1000001",
        "tgn:7012149",
        "tgn:2001851",
        "tgn:7007825",
        "tgn:7029392"
    ],
    "tgn:id":2128912,
    "tgn:name":"Alexander Branch",
    "tgn:placetype":[
        "aat:300008699"
    ]
},
  "bbox": [],
  "geometry": {"coordinates":[-83.1167,35.8833],"type":"Point"}
}