{
  "id": 2171580,
  "type": "Feature",
  "properties": {
    "tgn:hierarchy":[
        "tgn:2171580",
        "tgn:1000001",
        "tgn:7012149",
        "tgn:2002373",
        "tgn:7007923",
        "tgn:7029392"
    ],
    "tgn:id":2171580,
    "tgn:name":"Big Table Mountain",
    "tgn:placetype":[
        "aat:300008798"
    ]
},
  "bbox": [],
  "geometry": {"coordinates":[-108.4833,43.5833],"type":"Point"}
}