{
  "id": 2084526,
  "type": "Feature",
  "properties": {
    "tgn:hierarchy":[
        "tgn:2084526",
        "tgn:1000001",
        "tgn:7012149",
        "tgn:2001720",
        "tgn:7007708",
        "tgn:7029392"
    ],
    "tgn:id":2084526,
    "tgn:name":"Charlestown",
    "tgn:placetype":[
        "aat:300008347"
    ]
},
  "bbox": [],
  "geometry": {"coordinates":[-119.2833,45.8833],"type":"Point"}
}