{
  "id": 7328256,
  "type": "Feature",
  "properties": {
    "tgn:hierarchy":[
        "tgn:7328256",
        "tgn:7002822",
        "tgn:1001647",
        "tgn:1000003",
        "tgn:1000095",
        "tgn:7029392"
    ],
    "tgn:id":7328256,
    "tgn:name":"Renales",
    "tgn:placetype":[
        "aat:300008347"
    ]
},
  "bbox": [],
  "geometry": {"coordinates":[-2.516667,40.916667],"type":"Point"}
}