{
  "id": 7577849,
  "type": "Feature",
  "properties": {
    "tgn:hierarchy":[
        "tgn:7577849",
        "tgn:1000004",
        "tgn:1001869",
        "tgn:7000198",
        "tgn:7029392"
    ],
    "tgn:id":7577849,
    "tgn:name:en":"Luh\u0101ra",
    "tgn:placetype":[
        "aat:300008347"
    ]
},
  "bbox": [],
  "geometry": {"coordinates":[72.55,21.666667],"type":"Point"}
}