<<<<<<< HEAD
{
  "id": 2405438,
  "type": "Feature",
  "properties": {
    "tgn:hierarchy":[
        "tgn:2405438",
        "tgn:1000001",
        "tgn:2001653",
        "tgn:7012149",
        "tgn:7007707",
        "tgn:7029392"
    ],
    "tgn:id":2405438,
    "tgn:name":"Hughart",
    "tgn:placetype":[
        "aat:300008347"
    ]
},
  "bbox": [],
  "geometry": {"coordinates":[-95.2833,35.2],"type":"Point"}
}
=======
{"geometry":{"type":"Point","coordinates":[-95.283300,35.200000]},"type":"Feature","properties":{"hierarchy":["tgn:2405438","tgn:1000001","tgn:2001653","tgn:7012149","tgn:7007707","tgn:7029392"],"placetype":["aat:300008347"],"id":2405438,"name:xx":"Hughart"}}
>>>>>>> 03f74aca74312dbeaf24d7e61306dd6a786dc3d0
