{
  "id": 7274961,
  "type": "Feature",
  "properties": {
    "tgn:hierarchy":[
        "tgn:7274961",
        "tgn:1001699",
        "tgn:1000049",
        "tgn:1000002",
        "tgn:7029392"
    ],
    "tgn:id":7274961,
    "tgn:name":"Tique, Raya de",
    "tgn:placetype":[
        "aat:300008736"
    ]
},
  "bbox": [],
  "geometry": {"coordinates":[-73.435,-41.8525],"type":"Point"}
}