{
  "id": 7476711,
  "type": "Feature",
  "properties": {
    "tgn:hierarchy":[
        "tgn:7476711",
        "tgn:7487020",
        "tgn:1000004",
        "tgn:1000141",
        "tgn:7029392"
    ],
    "tgn:id":7476711,
    "tgn:name":"Shizitou",
    "tgn:placetype":[
        "aat:300008347"
    ]
},
  "bbox": [],
  "geometry": {"coordinates":[120.834405,24.601444],"type":"Point"}
}