{
  "id": 7276855,
  "type": "Feature",
  "properties": {
    "tgn:hierarchy":[
        "tgn:7276855",
        "tgn:1001705",
        "tgn:1000049",
        "tgn:1000002",
        "tgn:7029392"
    ],
    "tgn:id":7276855,
    "tgn:name":"Roncurra, Punta",
    "tgn:placetype":[
        "aat:300386846"
    ]
},
  "bbox": [],
  "geometry": {"coordinates":[-72.15,-34.966667],"type":"Point"}
}