{
  "id": 2483491,
  "type": "Feature",
  "properties": {
    "tgn:hierarchy":[
        "tgn:2483491",
        "tgn:1000001",
        "tgn:7012149",
        "tgn:2002248",
        "tgn:7007920",
        "tgn:7029392"
    ],
    "tgn:id":2483491,
    "tgn:name":"Last Chance Mine",
    "tgn:placetype":[
        "aat:300000390"
    ]
},
  "bbox": [],
  "geometry": {"coordinates":[-117.05,48.5167],"type":"Point"}
}