{
  "id": 2532939,
  "type": "Feature",
  "properties": {
    "tgn:hierarchy":[
        "tgn:2532939",
        "tgn:1000001",
        "tgn:7012149",
        "tgn:2000917",
        "tgn:7007256",
        "tgn:7029392"
    ],
    "tgn:id":2532939,
    "tgn:name":"Murray Junction",
    "tgn:placetype":[
        "aat:300008347"
    ]
},
  "bbox": [],
  "geometry": {"coordinates":[-92.4833,31.8833],"type":"Point"}
}