<<<<<<< HEAD
{
  "id": 7359650,
  "type": "Feature",
  "properties": {
    "tgn:hierarchy":[
        "tgn:7359650",
        "tgn:1000001",
        "tgn:7005594",
        "tgn:7005560",
        "tgn:7029392"
    ],
    "tgn:id":7359650,
    "tgn:name":"Clavellinas",
    "tgn:placetype":[
        "aat:300008347"
    ]
},
  "bbox": [],
  "geometry": {"coordinates":[-101.016667,22.7],"type":"Point"}
}
=======
{"geometry":{"type":"Point","coordinates":[-101.016667,22.700000]},"type":"Feature","properties":{"hierarchy":["tgn:7359650","tgn:1000001","tgn:7005594","tgn:7005560","tgn:7029392"],"placetype":["aat:300008347"],"id":7359650,"name:xx":"Clavellinas"}}
>>>>>>> 03f74aca74312dbeaf24d7e61306dd6a786dc3d0
