{
  "id": 2317139,
  "type": "Feature",
  "properties": {
    "tgn:hierarchy":[
        "tgn:2317139",
        "tgn:1000001",
        "tgn:7016172",
        "tgn:2000113",
        "tgn:7012149",
        "tgn:7029392"
    ],
    "tgn:id":2317139,
    "tgn:name":"Eminence Bayou",
    "tgn:placetype":[
        "aat:300008699"
    ]
},
  "bbox": [],
  "geometry": {"coordinates":[-91.1333,33.2333],"type":"Point"}
}