{
  "id": 7065140,
  "type": "Feature",
  "properties": {
    "tgn:hierarchy":[
        "tgn:7065140",
        "tgn:1000003",
        "tgn:7003676",
        "tgn:7000084",
        "tgn:7029392"
    ],
    "tgn:id":7065140,
    "tgn:name":"Steinkamp",
    "tgn:placetype":[
        "aat:300000206"
    ]
},
  "bbox": [],
  "geometry": {"coordinates":[9.016667,53.066667],"type":"Point"}
}