<<<<<<< HEAD
{
  "id": 7057067,
  "type": "Feature",
  "properties": {
    "tgn:hierarchy":[
        "tgn:7057067",
        "tgn:7003163",
        "tgn:1000003",
        "tgn:7009760",
        "tgn:1000080",
        "tgn:7029392"
    ],
    "tgn:id":7057067,
    "tgn:name":"Barco",
    "tgn:placetype":[
        "aat:300008347"
    ]
},
  "bbox": [],
  "geometry": {"coordinates":[11.383333,44.066667],"type":"Point"}
}
=======
{"geometry":{"type":"Point","coordinates":[11.383333,44.066667]},"type":"Feature","properties":{"hierarchy":["tgn:7057067","tgn:7003163","tgn:1000003","tgn:7009760","tgn:1000080","tgn:7029392"],"placetype":["aat:300008347"],"id":7057067,"name:xx":"Barco"}}
>>>>>>> 03f74aca74312dbeaf24d7e61306dd6a786dc3d0
