{
  "id": 7057067,
  "type": "Feature",
  "properties": {
    "tgn:hierarchy":[
        "tgn:7057067",
        "tgn:7003163",
        "tgn:1000003",
        "tgn:7009760",
        "tgn:1000080",
        "tgn:7029392"
    ],
    "tgn:id":7057067,
    "tgn:name":"Barco",
    "tgn:placetype":[
        "aat:300008347"
    ]
},
  "bbox": [],
  "geometry": {"coordinates":[11.383333,44.066667],"type":"Point"}
}