{
  "id": 4001248,
  "type": "Feature",
  "properties": {
    "tgn:hierarchy":[
        "tgn:4001248",
        "tgn:7005852",
        "tgn:1000003",
        "tgn:7003237",
        "tgn:1000080",
        "tgn:7029392"
    ],
    "tgn:id":4001248,
    "tgn:name":"Barzan\u00f2",
    "tgn:placetype":[
        "aat:300008347"
    ]
},
  "bbox": [],
  "geometry": {"coordinates":[9.316667,45.733333],"type":"Point"}
}