{
  "id": 2228689,
  "type": "Feature",
  "properties": {
    "tgn:hierarchy":[
        "tgn:2228689",
        "tgn:1000001",
        "tgn:7012149",
        "tgn:2002383",
        "tgn:7007923",
        "tgn:7029392"
    ],
    "tgn:id":2228689,
    "tgn:name":"Cedar Draw",
    "tgn:placetype":[
        "aat:300008761"
    ]
},
  "bbox": [],
  "geometry": {"coordinates":[-108.7833,41.3333],"type":"Point"}
}