<<<<<<< HEAD
{
  "id": 7379407,
  "type": "Feature",
  "properties": {
    "tgn:hierarchy":[
        "tgn:7379407",
        "tgn:7005583",
        "tgn:1000001",
        "tgn:7005560",
        "tgn:7029392"
    ],
    "tgn:id":7379407,
    "tgn:name":"Micks",
    "tgn:placetype":[
        "aat:300008347"
    ]
},
  "bbox": [],
  "geometry": {"coordinates":[-106.7,25.283333],"type":"Point"}
}
=======
{"geometry":{"type":"Point","coordinates":[-106.700000,25.283333]},"type":"Feature","properties":{"hierarchy":["tgn:7379407","tgn:7005583","tgn:1000001","tgn:7005560","tgn:7029392"],"placetype":["aat:300008347"],"id":7379407,"name:xx":"Micks"}}
>>>>>>> 03f74aca74312dbeaf24d7e61306dd6a786dc3d0
