{
  "id": 2677447,
  "type": "Feature",
  "properties": {
    "tgn:hierarchy":[
        "tgn:2677447",
        "tgn:1000001",
        "tgn:7012149",
        "tgn:7007250",
        "tgn:7029392"
    ],
    "tgn:id":2677447,
    "tgn:name":"South Carson Creek",
    "tgn:placetype":[
        "aat:300008706"
    ]
},
  "bbox": [],
  "geometry": {"coordinates":[-113.7333,42.15],"type":"Point"}
}