<<<<<<< HEAD
{
  "id": 7024401,
  "type": "Feature",
  "properties": {
    "tgn:hierarchy":[
        "tgn:7024401",
        "tgn:7000490",
        "tgn:1000006",
        "tgn:7001829",
        "tgn:7029392"
    ],
    "tgn:id":7024401,
    "tgn:name":"Jiberu Creek",
    "tgn:placetype":[
        "aat:300008706"
    ]
},
  "bbox": [],
  "geometry": {"coordinates":[134.45,16.2667],"type":"Point"}
}
=======
{"geometry":{"type":"Point","coordinates":[134.450000,16.266700]},"type":"Feature","properties":{"hierarchy":["tgn:7024401","tgn:7000490","tgn:1000006","tgn:7001829","tgn:7029392"],"placetype":["aat:300008706"],"id":7024401,"name:xx":"Jiberu Creek"}}
>>>>>>> 03f74aca74312dbeaf24d7e61306dd6a786dc3d0
