{
  "id": 2413114,
  "type": "Feature",
  "properties": {
    "tgn:hierarchy":[
        "tgn:2413114",
        "tgn:1000001",
        "tgn:2000922",
        "tgn:7012149",
        "tgn:7007515",
        "tgn:7029392"
    ],
    "tgn:id":2413114,
    "tgn:name":"Inner Dawes Ledge",
    "tgn:placetype":[
        "aat:300132348"
    ]
},
  "bbox": [],
  "geometry": {"coordinates":[-68.3333,44.1833],"type":"Point"}
}