{
  "id": 7582606,
  "type": "Feature",
  "properties": {
    "tgn:hierarchy":[
        "tgn:7582606",
        "tgn:1000004",
        "tgn:7000198",
        "tgn:1001894",
        "tgn:7029392"
    ],
    "tgn:id":7582606,
    "tgn:name:en":"Garholi",
    "tgn:placetype":[
        "aat:300008347"
    ]
},
  "bbox": [],
  "geometry": {"coordinates":[78.400376,24.217222],"type":"Point"}
}