{
  "id": 7317978,
  "type": "Feature",
  "properties": {
    "tgn:hierarchy":[
        "tgn:7317978",
        "tgn:1001630",
        "tgn:1000049",
        "tgn:1000002",
        "tgn:7029392"
    ],
    "tgn:id":7317978,
    "tgn:name":"Ci\u00e9naga Redonda, Llano",
    "tgn:placetype":[
        "aat:300008805"
    ]
},
  "bbox": [],
  "geometry": {"coordinates":[-69.033333,-26.95],"type":"Point"}
}