{
  "id": 1105426,
  "type": "Feature",
  "properties": {
    "tgn:hierarchy":[
        "tgn:1105426",
        "tgn:1000004",
        "tgn:7593853",
        "tgn:1000111",
        "tgn:7029392"
    ],
    "tgn:id":1105426,
    "tgn:name":"Longjie",
    "tgn:placetype":[
        "aat:300008795"
    ]
},
  "bbox": [],
  "geometry": {"coordinates":[98.4167,25.25],"type":"Point"}
}