{
  "id": 7481167,
  "type": "Feature",
  "properties": {
    "tgn:hierarchy":[
        "tgn:7481167",
        "tgn:1000004",
        "tgn:7492971",
        "tgn:1000141",
        "tgn:7029392"
    ],
    "tgn:id":7481167,
    "tgn:name":"Shuimen",
    "tgn:placetype":[
        "aat:300008347"
    ]
},
  "bbox": [],
  "geometry": {"coordinates":[120.643848,22.708702],"type":"Point"}
}