<<<<<<< HEAD
{
  "id": 7114791,
  "type": "Feature",
  "properties": {
    "tgn:hierarchy":[
        "tgn:7114791",
        "tgn:1000003",
        "tgn:7003688",
        "tgn:7000084",
        "tgn:7029392"
    ],
    "tgn:id":7114791,
    "tgn:name":"Osterkoog",
    "tgn:placetype":[
        "aat:300006163"
    ]
},
  "bbox": [],
  "geometry": {"coordinates":[8.866667,54.35],"type":"Point"}
}
=======
{"geometry":{"type":"Point","coordinates":[8.866667,54.350000]},"type":"Feature","properties":{"hierarchy":["tgn:7114791","tgn:1000003","tgn:7003688","tgn:7000084","tgn:7029392"],"placetype":["aat:300006163"],"id":7114791,"name:xx":"Osterkoog"}}
>>>>>>> 03f74aca74312dbeaf24d7e61306dd6a786dc3d0
