{
  "id": 2426129,
  "type": "Feature",
  "properties": {
    "tgn:hierarchy":[
        "tgn:2426129",
        "tgn:1000001",
        "tgn:1002840",
        "tgn:7012149",
        "tgn:7007828",
        "tgn:7029392"
    ],
    "tgn:id":2426129,
    "tgn:name":"Jones Brook",
    "tgn:placetype":[
        "aat:300008699"
    ]
},
  "bbox": [],
  "geometry": {"coordinates":[-73.05,43.7833],"type":"Point"}
}