{
  "id": 7297001,
  "type": "Feature",
  "properties": {
    "tgn:hierarchy":[
        "tgn:7297001",
        "tgn:7002759",
        "tgn:7002845",
        "tgn:1000003",
        "tgn:1000095",
        "tgn:7029392"
    ],
    "tgn:id":7297001,
    "tgn:name":"Torralba de los Frailes",
    "tgn:placetype":[
        "aat:300008347"
    ]
},
  "bbox": [],
  "geometry": {"coordinates":[-1.666667,41.033333],"type":"Point"}
}