{
  "id": 7468088,
  "type": "Feature",
  "properties": {
    "tgn:hierarchy":[
        "tgn:7468088",
        "tgn:1000004",
        "tgn:7491221",
        "tgn:1000141",
        "tgn:7029392"
    ],
    "tgn:id":7468088,
    "tgn:name":"Jia'naimei Shan",
    "tgn:placetype":[
        "aat:300008798"
    ]
},
  "bbox": [],
  "geometry": {"coordinates":[120.91,22.431944],"type":"Point"}
}