{
  "id": 7209804,
  "type": "Feature",
  "properties": {
    "tgn:hierarchy":[
        "tgn:7209804",
        "tgn:1000003",
        "tgn:7003677",
        "tgn:7000084",
        "tgn:7029392"
    ],
    "tgn:id":7209804,
    "tgn:name":"Bavert",
    "tgn:placetype":[
        "aat:300008347"
    ]
},
  "bbox": [],
  "geometry": {"coordinates":[7.016667,51.183333],"type":"Point"}
}