<<<<<<< HEAD
{
  "id": 7364560,
  "type": "Feature",
  "properties": {
    "tgn:hierarchy":[
        "tgn:7364560",
        "tgn:1000001",
        "tgn:1001937",
        "tgn:7005560",
        "tgn:7029392"
    ],
    "tgn:id":7364560,
    "tgn:name":"Filomeno Mata",
    "tgn:placetype":[
        "aat:300008347"
    ]
},
  "bbox": [],
  "geometry": {"coordinates":[-88.4,19.866667],"type":"Point"}
}
=======
{"geometry":{"type":"Point","coordinates":[-88.400000,19.866667]},"type":"Feature","properties":{"hierarchy":["tgn:7364560","tgn:1000001","tgn:1001937","tgn:7005560","tgn:7029392"],"placetype":["aat:300008347"],"id":7364560,"name:xx":"Filomeno Mata"}}
>>>>>>> 03f74aca74312dbeaf24d7e61306dd6a786dc3d0
