{
  "id": 1103602,
  "type": "Feature",
  "properties": {
    "tgn:hierarchy":[
        "tgn:1103602",
        "tgn:1000861",
        "tgn:1000004",
        "tgn:1000119",
        "tgn:7029392"
    ],
    "tgn:id":1103602,
    "tgn:name":"\u02bbArif, Har",
    "tgn:placetype":[
        "aat:300008795"
    ]
},
  "bbox": [],
  "geometry": {"coordinates":[34.7333,30.4333],"type":"Point"}
}