{
  "id": 2389083,
  "type": "Feature",
  "properties": {
    "tgn:hierarchy":[
        "tgn:2389083",
        "tgn:1000001",
        "tgn:7012149",
        "tgn:7007157",
        "tgn:1002828",
        "tgn:7029392"
    ],
    "tgn:id":2389083,
    "tgn:name":"Hidden Tank",
    "tgn:placetype":[
        "aat:300006191"
    ]
},
  "bbox": [],
  "geometry": {"coordinates":[-116.0167,33.95],"type":"Point"}
}