{
  "id": 7027821,
  "type": "Feature",
  "properties": {
    "tgn:hierarchy":[
        "tgn:7027821",
        "tgn:7002445",
        "tgn:1000003",
        "tgn:7008157",
        "tgn:7008591",
        "tgn:7029392"
    ],
    "tgn:id":7027821,
    "tgn:name:en":"South Cockerington",
    "tgn:placetype":[
        "aat:300008347",
        "aat:300008369"
    ]
},
  "bbox": [],
  "geometry": {"coordinates":[0.066667,53.366667],"type":"Point"}
}