{
  "id": 7371849,
  "type": "Feature",
  "properties": {
    "tgn:hierarchy":[
        "tgn:7371849",
        "tgn:1000001",
        "tgn:7005595",
        "tgn:7005560",
        "tgn:7029392"
    ],
    "tgn:id":7371849,
    "tgn:name":"La Mula",
    "tgn:placetype":[
        "aat:300008347"
    ]
},
  "bbox": [],
  "geometry": {"coordinates":[-107.566667,26.016667],"type":"Point"}
}