{
  "id": 7568236,
  "type": "Feature",
  "properties": {
    "tgn:hierarchy":[
        "tgn:7568236",
        "tgn:1000004",
        "tgn:7000198",
        "tgn:7016788",
        "tgn:7029392"
    ],
    "tgn:id":7568236,
    "tgn:name:en":"Alph\u0101nagar",
    "tgn:placetype":[
        "aat:300008347"
    ]
},
  "bbox": [],
  "geometry": {"coordinates":[75.711615,25.280522],"type":"Point"}
}