{
  "id": 7055039,
  "type": "Feature",
  "properties": {
    "tgn:hierarchy":[
        "tgn:7055039",
        "tgn:7003013",
        "tgn:7003005",
        "tgn:1000003",
        "tgn:1000080",
        "tgn:7029392"
    ],
    "tgn:id":7055039,
    "tgn:name":"Pollena, Lagno di",
    "tgn:placetype":[
        "aat:300008699"
    ]
},
  "bbox": [],
  "geometry": {"coordinates":[14.283333,40.833333],"type":"Point"}
}