{
  "id": 2203659,
  "type": "Feature",
  "properties": {
    "tgn:hierarchy":[
        "tgn:2203659",
        "tgn:1000001",
        "tgn:2001473",
        "tgn:7012149",
        "tgn:7007709",
        "tgn:7029392"
    ],
    "tgn:id":2203659,
    "tgn:name":"Buckner Branch",
    "tgn:placetype":[
        "aat:300008699"
    ]
},
  "bbox": [],
  "geometry": {"coordinates":[-82.4667,35.7667],"type":"Point"}
}