{
  "id": 7483474,
  "type": "Feature",
  "properties": {
    "tgn:hierarchy":[
        "tgn:7483474",
        "tgn:1000004",
        "tgn:7491221",
        "tgn:1000141",
        "tgn:7029392"
    ],
    "tgn:id":7483474,
    "tgn:name":"Gongguan Bi",
    "tgn:placetype":[
        "aat:300386846"
    ]
},
  "bbox": [],
  "geometry": {"coordinates":[121.491667,22.679444],"type":"Point"}
}