<<<<<<< HEAD
{
  "id": 7483474,
  "type": "Feature",
  "properties": {
    "tgn:hierarchy":[
        "tgn:7483474",
        "tgn:1000004",
        "tgn:7491221",
        "tgn:1000141",
        "tgn:7029392"
    ],
    "tgn:id":7483474,
    "tgn:name":"Gongguan Bi",
    "tgn:placetype":[
        "aat:300386846"
    ]
},
  "bbox": [],
  "geometry": {"coordinates":[121.491667,22.679444],"type":"Point"}
}
=======
{"geometry":{"type":"Point","coordinates":[121.491667,22.679444]},"type":"Feature","properties":{"hierarchy":["tgn:7483474","tgn:1000004","tgn:7491221","tgn:1000141","tgn:7029392"],"placetype":["aat:300386846"],"id":7483474,"name:xx":"Gongguan Bi"}}
>>>>>>> 03f74aca74312dbeaf24d7e61306dd6a786dc3d0
