{
  "id": 7134493,
  "type": "Feature",
  "properties": {
    "tgn:hierarchy":[
        "tgn:7134493",
        "tgn:7003669",
        "tgn:1000003",
        "tgn:7000084",
        "tgn:7029392"
    ],
    "tgn:id":7134493,
    "tgn:name":"M\u00fcllerholz",
    "tgn:placetype":[
        "aat:300008863"
    ]
},
  "bbox": [],
  "geometry": {"coordinates":[10.133333,48.283333],"type":"Point"}
}