<<<<<<< HEAD
{
  "id": 2330804,
  "type": "Feature",
  "properties": {
    "tgn:hierarchy":[
        "tgn:2330804",
        "tgn:7006450",
        "tgn:2000069",
        "tgn:1000001",
        "tgn:7012149",
        "tgn:7029392"
    ],
    "tgn:id":2330804,
    "tgn:name":"Flat Mountain",
    "tgn:placetype":[
        "aat:300008798"
    ]
},
  "bbox": [],
  "geometry": {"coordinates":[-161.4667,59.0833],"type":"Point"}
}
=======
{"geometry":{"type":"Point","coordinates":[-161.466700,59.083300]},"type":"Feature","properties":{"hierarchy":["tgn:2330804","tgn:7006450","tgn:2000069","tgn:1000001","tgn:7012149","tgn:7029392"],"placetype":["aat:300008798"],"id":2330804,"name:xx":"Flat Mountain"}}
>>>>>>> 03f74aca74312dbeaf24d7e61306dd6a786dc3d0
