{
  "id": 7143686,
  "type": "Feature",
  "properties": {
    "tgn:hierarchy":[
        "tgn:7143686",
        "tgn:1000003",
        "tgn:7003678",
        "tgn:7000084",
        "tgn:7029392"
    ],
    "tgn:id":7143686,
    "tgn:name":"F\u00f6rsterei Lochseif",
    "tgn:placetype":[
        "aat:300004792"
    ]
},
  "bbox": [],
  "geometry": {"coordinates":[9.033333,50.15],"type":"Point"}
}