{
  "id": 7533175,
  "type": "Feature",
  "properties": {
    "tgn:hierarchy":[
        "tgn:7533175",
        "tgn:7001242",
        "tgn:7016833",
        "tgn:1001335",
        "tgn:7029392"
    ],
    "tgn:id":7533175,
    "tgn:name:en":"Mansh\u012byat J\u0101d All\u0101h",
    "tgn:placetype":[
        "aat:300008347"
    ]
},
  "bbox": [],
  "geometry": {"coordinates":[30.971579,31.222592],"type":"Point"}
}