{
  "id": 1097065,
  "type": "Feature",
  "properties": {
    "tgn:hierarchy":[
        "tgn:1097065",
        "tgn:7000490",
        "tgn:1000006",
        "tgn:7001834",
        "tgn:7029392"
    ],
    "tgn:id":1097065,
    "tgn:name":"Hamelin Pool",
    "tgn:placetype":[
        "aat:300008347"
    ]
},
  "bbox": [],
  "geometry": {"coordinates":[114.2167,-26.4167],"type":"Point"}
}