{
  "id": 7537064,
  "type": "Feature",
  "properties": {
    "tgn:hierarchy":[
        "tgn:7537064",
        "tgn:7001242",
        "tgn:7016833",
        "tgn:1001123",
        "tgn:7029392"
    ],
    "tgn:id":7537064,
    "tgn:name":"Laj\u0101n, Tall",
    "tgn:placetype":[
        "aat:300008777"
    ]
},
  "bbox": [],
  "geometry": {"coordinates":[32.080019,31.24035],"type":"Point"}
}