{
  "id": 7589729,
  "type": "Feature",
  "properties": {
    "tgn:hierarchy":[
        "tgn:7589729",
        "tgn:1000004",
        "tgn:7000198",
        "tgn:7000799",
        "tgn:7029392"
    ],
    "tgn:id":7589729,
    "tgn:name:en":"Gragrio",
    "tgn:placetype":[
        "aat:300008699"
    ]
},
  "bbox": [],
  "geometry": {"coordinates":[76.475902,34.67503],"type":"Point"}
}