{
  "id": 2665993,
  "type": "Feature",
  "properties": {
    "tgn:hierarchy":[
        "tgn:2665993",
        "tgn:1000001",
        "tgn:7012149",
        "tgn:2000180",
        "tgn:7007157",
        "tgn:7029392"
    ],
    "tgn:id":2665993,
    "tgn:name":"Sister Rocks",
    "tgn:placetype":[
        "aat:300008791"
    ]
},
  "bbox": [],
  "geometry": {"coordinates":[-124.1333,41.65],"type":"Point"}
}