{
  "id": 7308170,
  "type": "Feature",
  "properties": {
    "tgn:hierarchy":[
        "tgn:7308170",
        "tgn:7016598",
        "tgn:1000049",
        "tgn:1000002",
        "tgn:7029392"
    ],
    "tgn:id":7308170,
    "tgn:name":"Medano, Cerro",
    "tgn:placetype":[
        "aat:300008795"
    ]
},
  "bbox": [],
  "geometry": {"coordinates":[-67.65,-23.966667],"type":"Point"}
}