{
  "id": 1075846,
  "type": "Feature",
  "properties": {
    "tgn:hierarchy":[
        "tgn:1075846",
        "tgn:1000004",
        "tgn:7000198",
        "tgn:1001977",
        "tgn:7029392"
    ],
    "tgn:id":1075846,
    "tgn:name:en":"Kharar",
    "tgn:placetype":[
        "aat:300008347"
    ]
},
  "bbox": [],
  "geometry": {"coordinates":[87.678235,22.722115],"type":"Point"}
}