{
  "id": 2676536,
  "type": "Feature",
  "properties": {
    "tgn:hierarchy":[
        "tgn:2676536",
        "tgn:1002300",
        "tgn:1000001",
        "tgn:7012149",
        "tgn:7007564",
        "tgn:7029392"
    ],
    "tgn:id":2676536,
    "tgn:name":"South Bay",
    "tgn:placetype":[
        "aat:300132316"
    ]
},
  "bbox": [],
  "geometry": {"coordinates":[-71.25,45.0667],"type":"Point"}
}