{
  "id": 7464325,
  "type": "Feature",
  "properties": {
    "tgn:hierarchy":[
        "tgn:7464325",
        "tgn:7002445",
        "tgn:1000003",
        "tgn:7008185",
        "tgn:7008591",
        "tgn:7029392"
    ],
    "tgn:id":7464325,
    "tgn:name:en":"Aldeburgh Napes",
    "tgn:placetype":[
        "aat:300387036"
    ]
},
  "bbox": [],
  "geometry": {"coordinates":[1.716667,52.15],"type":"Point"}
}