{
  "id": 2476172,
  "type": "Feature",
  "properties": {
    "tgn:hierarchy":[
        "tgn:2476172",
        "tgn:1000001",
        "tgn:7012149",
        "tgn:2001456",
        "tgn:7007566",
        "tgn:7029392"
    ],
    "tgn:id":2476172,
    "tgn:name":"Lumber Tank",
    "tgn:placetype":[
        "aat:300006191"
    ]
},
  "bbox": [],
  "geometry": {"coordinates":[-107.3667,33.4833],"type":"Point"}
}