{
  "id": 2742307,
  "type": "Feature",
  "properties": {
    "tgn:hierarchy":[
        "tgn:2742307",
        "tgn:1000001",
        "tgn:7012149",
        "tgn:1002625",
        "tgn:7007706",
        "tgn:7029392"
    ],
    "tgn:id":2742307,
    "tgn:name":"Vallery Ditch",
    "tgn:placetype":[
        "aat:300006075"
    ]
},
  "bbox": [],
  "geometry": {"coordinates":[-83.4833,39.7333],"type":"Point"}
}