{
  "id": 2039252,
  "type": "Feature",
  "properties": {
    "tgn:hierarchy":[
        "tgn:2039252",
        "tgn:1000001",
        "tgn:7012149",
        "tgn:2000837",
        "tgn:7007255",
        "tgn:7029392"
    ],
    "tgn:id":2039252,
    "tgn:name":"Hardy",
    "tgn:placetype":[
        "aat:300008347"
    ]
},
  "bbox": [],
  "geometry": {"coordinates":[-82.2333,37.6167],"type":"Point"}
}