{
  "id": 2125887,
  "type": "Feature",
  "properties": {
    "tgn:hierarchy":[
        "tgn:2125887",
        "tgn:1000001",
        "tgn:7012149",
        "tgn:2001390",
        "tgn:7007525",
        "tgn:7029392"
    ],
    "tgn:id":2125887,
    "tgn:name":"Adams Lake",
    "tgn:placetype":[
        "aat:300008680"
    ]
},
  "bbox": [],
  "geometry": {"coordinates":[-99.4667,42.5167],"type":"Point"}
}