{
  "id": 2302351,
  "type": "Feature",
  "properties": {
    "tgn:hierarchy":[
        "tgn:2302351",
        "tgn:1000001",
        "tgn:7012149",
        "tgn:2002270",
        "tgn:7013961",
        "tgn:7029392"
    ],
    "tgn:id":2302351,
    "tgn:name":"Dutch Ridge",
    "tgn:placetype":[
        "aat:300266640"
    ]
},
  "bbox": [],
  "geometry": {"coordinates":[-81.3167,38.3833],"type":"Point"}
}