{
  "id": 7179861,
  "type": "Feature",
  "properties": {
    "tgn:hierarchy":[
        "tgn:7179861",
        "tgn:1000003",
        "tgn:7003676",
        "tgn:7000084",
        "tgn:7029392"
    ],
    "tgn:id":7179861,
    "tgn:name":"Hahnen Berg",
    "tgn:placetype":[
        "aat:300008777"
    ]
},
  "bbox": [],
  "geometry": {"coordinates":[8.65,53.383333],"type":"Point"}
}