<<<<<<< HEAD
{
  "id": 2760319,
  "type": "Feature",
  "properties": {
    "tgn:hierarchy":[
        "tgn:2760319",
        "tgn:1000001",
        "tgn:7012149",
        "tgn:2000214",
        "tgn:7007158",
        "tgn:7029392"
    ],
    "tgn:id":2760319,
    "tgn:name":"West Fork Sawmill Gulch",
    "tgn:placetype":[
        "aat:300008761"
    ]
},
  "bbox": [],
  "geometry": {"coordinates":[-108.9833,39.5833],"type":"Point"}
}
=======
{"geometry":{"type":"Point","coordinates":[-108.983300,39.583300]},"type":"Feature","properties":{"hierarchy":["tgn:2760319","tgn:1000001","tgn:7012149","tgn:2000214","tgn:7007158","tgn:7029392"],"placetype":["aat:300008761"],"id":2760319,"name:xx":"West Fork Sawmill Gulch"}}
>>>>>>> 03f74aca74312dbeaf24d7e61306dd6a786dc3d0
