<<<<<<< HEAD
{
  "id": 2402166,
  "type": "Feature",
  "properties": {
    "tgn:hierarchy":[
        "tgn:2402166",
        "tgn:1000001",
        "tgn:7012149",
        "tgn:1002554",
        "tgn:7007920",
        "tgn:7029392"
    ],
    "tgn:id":2402166,
    "tgn:name":"Horsethief Butte",
    "tgn:placetype":[
        "aat:300008798"
    ]
},
  "bbox": [],
  "geometry": {"coordinates":[-121.0833,45.6333],"type":"Point"}
}
=======
{"geometry":{"type":"Point","coordinates":[-121.083300,45.633300]},"type":"Feature","properties":{"hierarchy":["tgn:2402166","tgn:1000001","tgn:7012149","tgn:1002554","tgn:7007920","tgn:7029392"],"placetype":["aat:300008798"],"id":2402166,"name:xx":"Horsethief Butte"}}
>>>>>>> 03f74aca74312dbeaf24d7e61306dd6a786dc3d0
