{
  "id": 7410727,
  "type": "Feature",
  "properties": {
    "tgn:hierarchy":[
        "tgn:7410727",
        "tgn:1000001",
        "tgn:1001893",
        "tgn:7005560",
        "tgn:7029392"
    ],
    "tgn:id":7410727,
    "tgn:name":"Oyame, R\u00edo",
    "tgn:placetype":[
        "aat:300008699"
    ]
},
  "bbox": [],
  "geometry": {"coordinates":[-99.866667,19.266667],"type":"Point"}
}