{
  "id": 7515768,
  "type": "Feature",
  "properties": {
    "tgn:hierarchy":[
        "tgn:7515768",
        "tgn:1008380",
        "tgn:1000226",
        "tgn:7016827",
        "tgn:1000006",
        "tgn:7029392"
    ],
    "tgn:id":7515768,
    "tgn:name:en":"Mangawhio",
    "tgn:placetype":[
        "aat:300008347"
    ]
},
  "bbox": [],
  "geometry": {"coordinates":[174.716667,-39.716667],"type":"Point"}
}