{
  "id": 7334358,
  "type": "Feature",
  "properties": {
    "tgn:hierarchy":[
        "tgn:7334358",
        "tgn:7008911",
        "tgn:1000003",
        "tgn:7002763",
        "tgn:1000095",
        "tgn:7029392"
    ],
    "tgn:id":7334358,
    "tgn:name":"El Invernal",
    "tgn:placetype":[
        "aat:300008347"
    ]
},
  "bbox": [],
  "geometry": {"coordinates":[-5.616667,43.266667],"type":"Point"}
}