{
  "id": 2602011,
  "type": "Feature",
  "properties": {
    "tgn:hierarchy":[
        "tgn:2602011",
        "tgn:7023902",
        "tgn:1000001",
        "tgn:7012149",
        "tgn:7007249",
        "tgn:7029392"
    ],
    "tgn:id":2602011,
    "tgn:name":"Puu Makahalau",
    "tgn:placetype":[
        "aat:300008798"
    ]
},
  "bbox": [],
  "geometry": {"coordinates":[-155.5667,19.9667],"type":"Point"}
}