{
  "id": 2676202,
  "type": "Feature",
  "properties": {
    "tgn:hierarchy":[
        "tgn:2676202",
        "tgn:1000001",
        "tgn:7012149",
        "tgn:2000839",
        "tgn:7007255",
        "tgn:7029392"
    ],
    "tgn:id":2676202,
    "tgn:name":"Soul Chapel Branch",
    "tgn:placetype":[
        "aat:300008699"
    ]
},
  "bbox": [],
  "geometry": {"coordinates":[-84.5333,37.1167],"type":"Point"}
}