{
  "id": 7156782,
  "type": "Feature",
  "properties": {
    "tgn:hierarchy":[
        "tgn:7156782",
        "tgn:7000096",
        "tgn:1000003",
        "tgn:7000084",
        "tgn:7029392"
    ],
    "tgn:id":7156782,
    "tgn:name":"Klausiushof",
    "tgn:placetype":[
        "aat:300008347"
    ]
},
  "bbox": [],
  "geometry": {"coordinates":[12.366667,52.783333],"type":"Point"}
}