{
  "id": 7521837,
  "type": "Feature",
  "properties": {
    "tgn:hierarchy":[
        "tgn:7521837",
        "tgn:7001242",
        "tgn:7016833",
        "tgn:7001336",
        "tgn:7029392"
    ],
    "tgn:id":7521837,
    "tgn:name":"Al Bal\u0101'\u012bm",
    "tgn:placetype":[
        "aat:300008679"
    ]
},
  "bbox": [],
  "geometry": {"coordinates":[33.254633,28.566958],"type":"Point"}
}