{
  "id": 2086755,
  "type": "Feature",
  "properties": {
    "tgn:hierarchy":[
        "tgn:2086755",
        "tgn:1000001",
        "tgn:7012149",
        "tgn:1002876",
        "tgn:7007710",
        "tgn:7029392"
    ],
    "tgn:id":2086755,
    "tgn:name":"Brookside",
    "tgn:placetype":[
        "aat:300008347",
        "aat:300387210"
    ]
},
  "bbox": [],
  "geometry": {"coordinates":[-76.3833,40.5167],"type":"Point"}
}