{
  "id": 7217679,
  "type": "Feature",
  "properties": {
    "tgn:hierarchy":[
        "tgn:7217679",
        "tgn:7002711",
        "tgn:7001338",
        "tgn:1000003",
        "tgn:1000074",
        "tgn:7029392"
    ],
    "tgn:id":7217679,
    "tgn:name":"Giann\u00e1des",
    "tgn:placetype":[
        "aat:300008347"
    ]
},
  "bbox": [],
  "geometry": {"coordinates":[19.759444,39.63],"type":"Point"}
}