{
  "id": 7005233,
  "type": "Feature",
  "properties": {
    "tgn:hierarchy":[
        "tgn:7005233",
        "tgn:1000003",
        "tgn:7029392"
    ],
    "tgn:id":7005233,
    "tgn:name":"Jabal \u1e6c\u0101riq",
    "tgn:name:en":"Gibraltar",
    "tgn:name:it":"Gibilterra",
    "tgn:placetype":[
        "aat:300387054",
        "aat:300235115",
        "aat:300387176",
        "aat:300008804"
    ]
},
  "bbox": [],
  "geometry": {"coordinates":[-5.35,36.1333],"type":"Point"}
}