{
  "id": 2732895,
  "type": "Feature",
  "properties": {
    "tgn:hierarchy":[
        "tgn:2732895",
        "tgn:1000001",
        "tgn:7012149",
        "tgn:2002274",
        "tgn:7013961",
        "tgn:7029392"
    ],
    "tgn:id":2732895,
    "tgn:name":"Turkey Gap Branch",
    "tgn:placetype":[
        "aat:300008699"
    ]
},
  "bbox": [],
  "geometry": {"coordinates":[-81.35,37.3833],"type":"Point"}
}