{
  "id": 7044644,
  "type": "Feature",
  "properties": {
    "tgn:hierarchy":[
        "tgn:7044644",
        "tgn:1003432",
        "tgn:1000003",
        "tgn:7003240",
        "tgn:1000080",
        "tgn:7029392"
    ],
    "tgn:id":7044644,
    "tgn:name":"Cossignano",
    "tgn:placetype":[
        "aat:300008347"
    ]
},
  "bbox": [],
  "geometry": {"coordinates":[13.683333,42.983333],"type":"Point"}
}