{
  "id": 7161277,
  "type": "Feature",
  "properties": {
    "tgn:hierarchy":[
        "tgn:7161277",
        "tgn:7003669",
        "tgn:1000003",
        "tgn:7000084",
        "tgn:7029392"
    ],
    "tgn:id":7161277,
    "tgn:name":"Hochstra\u00df",
    "tgn:placetype":[
        "aat:300000206"
    ]
},
  "bbox": [],
  "geometry": {"coordinates":[12.083333,49.116667],"type":"Point"}
}