<<<<<<< HEAD
{
  "id": 7379227,
  "type": "Feature",
  "properties": {
    "tgn:hierarchy":[
        "tgn:7379227",
        "tgn:7005586",
        "tgn:1000001",
        "tgn:7005560",
        "tgn:7029392"
    ],
    "tgn:id":7379227,
    "tgn:name":"Los Cimientos",
    "tgn:placetype":[
        "aat:300008347"
    ]
},
  "bbox": [],
  "geometry": {"coordinates":[-104.816667,19.7],"type":"Point"}
}
=======
{"geometry":{"type":"Point","coordinates":[-104.816667,19.700000]},"type":"Feature","properties":{"hierarchy":["tgn:7379227","tgn:7005586","tgn:1000001","tgn:7005560","tgn:7029392"],"placetype":["aat:300008347"],"id":7379227,"name:xx":"Los Cimientos"}}
>>>>>>> 03f74aca74312dbeaf24d7e61306dd6a786dc3d0
