{
  "id": 7512073,
  "type": "Feature",
  "properties": {
    "tgn:hierarchy":[
        "tgn:7512073",
        "tgn:1008380",
        "tgn:1000226",
        "tgn:7000512",
        "tgn:1000006",
        "tgn:7029392"
    ],
    "tgn:id":7512073,
    "tgn:name:en":"Jury Hill",
    "tgn:placetype":[
        "aat:300008777"
    ]
},
  "bbox": [],
  "geometry": {"coordinates":[175.516667,-41.133333],"type":"Point"}
}