{
  "id": 2574558,
  "type": "Feature",
  "properties": {
    "tgn:hierarchy":[
        "tgn:2574558",
        "tgn:1000001",
        "tgn:7012149",
        "tgn:2000960",
        "tgn:7007520",
        "tgn:7029392"
    ],
    "tgn:id":2574558,
    "tgn:name":"Pelton River",
    "tgn:placetype":[
        "aat:300008707"
    ]
},
  "bbox": [],
  "geometry": {"coordinates":[-89.6333,46.35],"type":"Point"}
}