{
  "id": 7170689,
  "type": "Feature",
  "properties": {
    "tgn:hierarchy":[
        "tgn:7170689",
        "tgn:7003669",
        "tgn:1000003",
        "tgn:7000084",
        "tgn:7029392"
    ],
    "tgn:id":7170689,
    "tgn:name":"Hessel-Berg",
    "tgn:placetype":[
        "aat:300008777"
    ]
},
  "bbox": [],
  "geometry": {"coordinates":[10.016667,50.15],"type":"Point"}
}