<<<<<<< HEAD
{
  "id": 7059176,
  "type": "Feature",
  "properties": {
    "tgn:hierarchy":[
        "tgn:7059176",
        "tgn:1000004",
        "tgn:7012947",
        "tgn:1060525",
        "tgn:7014786",
        "tgn:7029392"
    ],
    "tgn:id":7059176,
    "tgn:name":"Mausoleum of Khoja Ahmed Yasawi",
    "tgn:placetype":[
        "aat:300005891",
        "aat:300008459",
        "aat:300263063"
    ]
},
  "bbox": [],
  "geometry": {"coordinates":[68.271,43.293],"type":"Point"}
}
=======
{"geometry":{"type":"Point","coordinates":[68.271000,43.293000]},"type":"Feature","properties":{"hierarchy":["tgn:7059176","tgn:1000004","tgn:7012947","tgn:1060525","tgn:7014786","tgn:7029392"],"placetype":["aat:300005891","aat:300008459","aat:300263063"],"id":7059176,"name:xx":"Mausoleum of Khoja Ahmed Yasawi"}}
>>>>>>> 03f74aca74312dbeaf24d7e61306dd6a786dc3d0
