{
  "id": 2272437,
  "type": "Feature",
  "properties": {
    "tgn:hierarchy":[
        "tgn:2272437",
        "tgn:1000001",
        "tgn:2001476",
        "tgn:7012149",
        "tgn:7007709",
        "tgn:7029392"
    ],
    "tgn:id":2272437,
    "tgn:name":"Curtis Knob",
    "tgn:placetype":[
        "aat:300008798"
    ]
},
  "bbox": [],
  "geometry": {"coordinates":[-81.5833,36.0833],"type":"Point"}
}