{
  "id": 7010977,
  "type": "Feature",
  "properties": {
    "tgn:hierarchy":[
        "tgn:7010977",
        "tgn:1000852",
        "tgn:1000003",
        "tgn:1000090",
        "tgn:7029392"
    ],
    "tgn:id":7010977,
    "tgn:name":"Olh\u00e3o",
    "tgn:placetype":[
        "aat:300008347",
        "aat:300387218"
    ]
},
  "bbox": [],
  "geometry": {"coordinates":[-7.841,37.028],"type":"Point"}
}