{
  "id": 7562088,
  "type": "Feature",
  "properties": {
    "tgn:hierarchy":[
        "tgn:7562088",
        "tgn:1000004",
        "tgn:7000198",
        "tgn:7016722",
        "tgn:7029392"
    ],
    "tgn:id":7562088,
    "tgn:name:en":"Mahnepur",
    "tgn:placetype":[
        "aat:300008347"
    ]
},
  "bbox": [],
  "geometry": {"coordinates":[79.103279,26.783193],"type":"Point"}
}