{
  "id": 2134834,
  "type": "Feature",
  "properties": {
    "tgn:hierarchy":[
        "tgn:2134834",
        "tgn:1000001",
        "tgn:7012149",
        "tgn:2001828",
        "tgn:7007713",
        "tgn:7029392"
    ],
    "tgn:id":2134834,
    "tgn:name":"Antelope Island",
    "tgn:placetype":[
        "aat:300008791"
    ]
},
  "bbox": [],
  "geometry": {"coordinates":[-100.1667,44.3167],"type":"Point"}
}