{
  "id": 2183001,
  "type": "Feature",
  "properties": {
    "tgn:hierarchy":[
        "tgn:2183001",
        "tgn:1000001",
        "tgn:2001009",
        "tgn:7012149",
        "tgn:7007521",
        "tgn:7029392"
    ],
    "tgn:id":2183001,
    "tgn:name":"Blueberry Lake",
    "tgn:placetype":[
        "aat:300008680"
    ]
},
  "bbox": [],
  "geometry": {"coordinates":[-94.1167,46.9167],"type":"Point"}
}