{
  "id": 2670473,
  "type": "Feature",
  "properties": {
    "tgn:hierarchy":[
        "tgn:2670473",
        "tgn:1000001",
        "tgn:7012149",
        "tgn:2001860",
        "tgn:7007825",
        "tgn:7029392"
    ],
    "tgn:id":2670473,
    "tgn:name":"Smart Creek",
    "tgn:placetype":[
        "aat:300008706"
    ]
},
  "bbox": [],
  "geometry": {"coordinates":[-89.3167,35.25],"type":"Point"}
}