{
  "id": 7326162,
  "type": "Feature",
  "properties": {
    "tgn:hierarchy":[
        "tgn:7326162",
        "tgn:7001155",
        "tgn:1000003",
        "tgn:7002790",
        "tgn:1000095",
        "tgn:7029392"
    ],
    "tgn:id":7326162,
    "tgn:name":"Pinar de C\u00e1seda",
    "tgn:placetype":[
        "aat:300008798"
    ]
},
  "bbox": [],
  "geometry": {"coordinates":[-1.383333,42.433333],"type":"Point"}
}