{
  "id": 2551743,
  "type": "Feature",
  "properties": {
    "tgn:hierarchy":[
        "tgn:2551743",
        "tgn:1000001",
        "tgn:7016172",
        "tgn:7012149",
        "tgn:2000151",
        "tgn:7029392"
    ],
    "tgn:id":2551743,
    "tgn:name":"Number 53, Ditch",
    "tgn:placetype":[
        "aat:300006075"
    ]
},
  "bbox": [],
  "geometry": {"coordinates":[-90.2167,35.5333],"type":"Point"}
}