{
  "id": 2451564,
  "type": "Feature",
  "properties": {
    "tgn:hierarchy":[
        "tgn:2451564",
        "tgn:7002659",
        "tgn:1000001",
        "tgn:7012149",
        "tgn:2000053",
        "tgn:7029392"
    ],
    "tgn:id":2451564,
    "tgn:name":"Little Bear Creek",
    "tgn:placetype":[
        "aat:300008706"
    ]
},
  "bbox": [],
  "geometry": {"coordinates":[-87.8333,33.35],"type":"Point"}
}