{
  "id": 2096770,
  "type": "Feature",
  "properties": {
    "tgn:hierarchy":[
        "tgn:2096770",
        "tgn:1000001",
        "tgn:2001739",
        "tgn:7012149",
        "tgn:7007712",
        "tgn:7029392"
    ],
    "tgn:id":2096770,
    "tgn:name":"Stokes",
    "tgn:placetype":[
        "aat:300008347"
    ]
},
  "bbox": [],
  "geometry": {"coordinates":[-80.7167,32.95],"type":"Point"}
}