{
  "id": 7489773,
  "type": "Feature",
  "properties": {
    "tgn:hierarchy":[
        "tgn:7489773",
        "tgn:1000004",
        "tgn:7001014",
        "tgn:1000141",
        "tgn:7029392"
    ],
    "tgn:id":7489773,
    "tgn:name":"Songyuan",
    "tgn:placetype":[
        "aat:300008347"
    ]
},
  "bbox": [],
  "geometry": {"coordinates":[120.415445,23.741061],"type":"Point"}
}