{
  "id": 2471773,
  "type": "Feature",
  "properties": {
    "tgn:hierarchy":[
        "tgn:2471773",
        "tgn:1000001",
        "tgn:7012149",
        "tgn:7029392"
    ],
    "tgn:id":2471773,
    "tgn:name":"Lost River",
    "tgn:placetype":[
        "aat:300008707"
    ]
},
  "bbox": [],
  "geometry": {"coordinates":[-121.0667,41.9167],"type":"Point"}
}