{
  "id": 7407597,
  "type": "Feature",
  "properties": {
    "tgn:hierarchy":[
        "tgn:7407597",
        "tgn:1000001",
        "tgn:1001893",
        "tgn:7005560",
        "tgn:7029392"
    ],
    "tgn:id":7407597,
    "tgn:name":"Santa Ana",
    "tgn:placetype":[
        "aat:300008347"
    ]
},
  "bbox": [],
  "geometry": {"coordinates":[-100.058333,19.541667],"type":"Point"}
}