{
  "id": 2356723,
  "type": "Feature",
  "properties": {
    "tgn:hierarchy":[
        "tgn:2356723",
        "tgn:1000001",
        "tgn:7012149",
        "tgn:2000743",
        "tgn:7007254",
        "tgn:7029392"
    ],
    "tgn:id":2356723,
    "tgn:name":"Gorham",
    "tgn:placetype":[
        "aat:300008347"
    ]
},
  "bbox": [],
  "geometry": {"coordinates":[-99.0167,38.8667],"type":"Point"}
}