{
  "id": 7554071,
  "type": "Feature",
  "properties": {
    "tgn:hierarchy":[
        "tgn:7554071",
        "tgn:1000004",
        "tgn:7000198",
        "tgn:7016788",
        "tgn:7029392"
    ],
    "tgn:id":7554071,
    "tgn:name:en":"Nindhar Ben\u0101r Railroad Station",
    "tgn:placetype":[
        "aat:300007783"
    ]
},
  "bbox": [],
  "geometry": {"coordinates":[75.729466,27.004147],"type":"Point"}
}