{
  "id": 7487034,
  "type": "Feature",
  "properties": {
    "tgn:hierarchy":[
        "tgn:7487034",
        "tgn:7469009",
        "tgn:1000004",
        "tgn:1000141",
        "tgn:7029392"
    ],
    "tgn:id":7487034,
    "tgn:name":"Menghu Yu",
    "tgn:placetype":[
        "aat:300008791"
    ]
},
  "bbox": [],
  "geometry": {"coordinates":[118.192911,24.396818],"type":"Point"}
}