{
  "id": 1053791,
  "type": "Feature",
  "properties": {
    "tgn:hierarchy":[
        "tgn:1053791",
        "tgn:7017324",
        "tgn:1000003",
        "tgn:7006656",
        "tgn:7029392"
    ],
    "tgn:id":1053791,
    "tgn:name":"Durle\u0219ti",
    "tgn:placetype":[
        "aat:300008347"
    ]
},
  "bbox": [],
  "geometry": {"coordinates":[28.75,47.0333],"type":"Point"}
}