{
  "id": 2542579,
  "type": "Feature",
  "properties": {
    "tgn:hierarchy":[
        "tgn:2542579",
        "tgn:1002145",
        "tgn:1000001",
        "tgn:7012149",
        "tgn:7007157",
        "tgn:7029392"
    ],
    "tgn:id":2542579,
    "tgn:name":"Noble Canyon",
    "tgn:placetype":[
        "aat:300008761"
    ]
},
  "bbox": [],
  "geometry": {"coordinates":[-119.7667,38.5167],"type":"Point"}
}