{
  "id": 2140357,
  "type": "Feature",
  "properties": {
    "tgn:hierarchy":[
        "tgn:2140357",
        "tgn:1000001",
        "tgn:7012149",
        "tgn:2000450",
        "tgn:7007248",
        "tgn:7029392"
    ],
    "tgn:id":2140357,
    "tgn:name":"Aultmans",
    "tgn:placetype":[
        "aat:300008347"
    ]
},
  "bbox": [],
  "geometry": {"coordinates":[-83.9167,31.6833],"type":"Point"}
}