{
  "id": 2387587,
  "type": "Feature",
  "properties": {
    "tgn:hierarchy":[
        "tgn:2387587",
        "tgn:1000001",
        "tgn:7012149",
        "tgn:1002943",
        "tgn:7007708",
        "tgn:7029392"
    ],
    "tgn:id":2387587,
    "tgn:name":"Hiack Creek",
    "tgn:placetype":[
        "aat:300008706"
    ]
},
  "bbox": [],
  "geometry": {"coordinates":[-123.8167,45.0667],"type":"Point"}
}