{
  "id": 7396757,
  "type": "Feature",
  "properties": {
    "tgn:hierarchy":[
        "tgn:7396757",
        "tgn:7005586",
        "tgn:1000001",
        "tgn:7005560",
        "tgn:7029392"
    ],
    "tgn:id":7396757,
    "tgn:name":"Santa Rosa",
    "tgn:placetype":[
        "aat:300008347"
    ]
},
  "bbox": [],
  "geometry": {"coordinates":[-104.283333,19.916667],"type":"Point"}
}