{
  "id": 7566803,
  "type": "Feature",
  "properties": {
    "tgn:hierarchy":[
        "tgn:7566803",
        "tgn:1000004",
        "tgn:7000198",
        "tgn:1001894",
        "tgn:7029392"
    ],
    "tgn:id":7566803,
    "tgn:name:en":"Jakha",
    "tgn:placetype":[
        "aat:300008347"
    ]
},
  "bbox": [],
  "geometry": {"coordinates":[79.239012,24.244096],"type":"Point"}
}