<<<<<<< HEAD
{
  "id": 2336164,
  "type": "Feature",
  "properties": {
    "tgn:hierarchy":[
        "tgn:2336164",
        "tgn:1000001",
        "tgn:7012149",
        "tgn:2002342",
        "tgn:7007922",
        "tgn:7029392"
    ],
    "tgn:id":2336164,
    "tgn:name":"Foster Lake",
    "tgn:placetype":[
        "aat:300008680"
    ]
},
  "bbox": [],
  "geometry": {"coordinates":[-89.6667,45.8],"type":"Point"}
}
=======
{"geometry":{"type":"Point","coordinates":[-89.666700,45.800000]},"type":"Feature","properties":{"hierarchy":["tgn:2336164","tgn:1000001","tgn:7012149","tgn:2002342","tgn:7007922","tgn:7029392"],"placetype":["aat:300008680"],"id":2336164,"name:xx":"Foster Lake"}}
>>>>>>> 03f74aca74312dbeaf24d7e61306dd6a786dc3d0
