<<<<<<< HEAD
{
  "id": 7021174,
  "type": "Feature",
  "properties": {
    "tgn:hierarchy":[
        "tgn:7021174",
        "tgn:1000001",
        "tgn:7012149",
        "tgn:2002271",
        "tgn:7013961",
        "tgn:7029392"
    ],
    "tgn:id":7021174,
    "tgn:name":"Poplar Lick Run",
    "tgn:placetype":[
        "aat:300008699"
    ]
},
  "bbox": [],
  "geometry": {"coordinates":[-80.45,38.95],"type":"Point"}
}
=======
{"geometry":{"type":"Point","coordinates":[-80.450000,38.950000]},"type":"Feature","properties":{"hierarchy":["tgn:7021174","tgn:1000001","tgn:7012149","tgn:2002271","tgn:7013961","tgn:7029392"],"placetype":["aat:300008699"],"id":7021174,"name:xx":"Poplar Lick Run"}}
>>>>>>> 03f74aca74312dbeaf24d7e61306dd6a786dc3d0
