{
  "id": 7019211,
  "type": "Feature",
  "properties": {
    "tgn:hierarchy":[
        "tgn:7019211",
        "tgn:1000001",
        "tgn:7012149",
        "tgn:2000226",
        "tgn:7007158",
        "tgn:7029392"
    ],
    "tgn:id":7019211,
    "tgn:name":"Bellaire Lake",
    "tgn:placetype":[
        "aat:300008680",
        "aat:300006191"
    ]
},
  "bbox": [],
  "geometry": {"coordinates":[-105.6167,40.7667],"type":"Point"}
}