{
  "id": 7235787,
  "type": "Feature",
  "properties": {
    "tgn:hierarchy":[
        "tgn:7235787",
        "tgn:7002709",
        "tgn:7002705",
        "tgn:1000003",
        "tgn:1000074",
        "tgn:7029392"
    ],
    "tgn:id":7235787,
    "tgn:name":"Farmakovo\u00fani",
    "tgn:placetype":[
        "aat:300008795"
    ]
},
  "bbox": [],
  "geometry": {"coordinates":[20.35,39.65],"type":"Point"}
}