{
  "id": 7278561,
  "type": "Feature",
  "properties": {
    "tgn:hierarchy":[
        "tgn:7278561",
        "tgn:1001657",
        "tgn:1000049",
        "tgn:1000002",
        "tgn:7029392"
    ],
    "tgn:id":7278561,
    "tgn:name":"Virgen, Punta",
    "tgn:placetype":[
        "aat:300386846"
    ]
},
  "bbox": [],
  "geometry": {"coordinates":[-71.621944,-31.388333],"type":"Point"}
}