{
  "id": 2670985,
  "type": "Feature",
  "properties": {
    "tgn:hierarchy":[
        "tgn:2670985",
        "tgn:1000001",
        "tgn:7012149",
        "tgn:2000289",
        "tgn:7007240",
        "tgn:7029392"
    ],
    "tgn:id":2670985,
    "tgn:name":"Smith Creek",
    "tgn:placetype":[
        "aat:300008347"
    ]
},
  "bbox": [],
  "geometry": {"coordinates":[-84.65,30.1667],"type":"Point"}
}