{
  "id": 7569239,
  "type": "Feature",
  "properties": {
    "tgn:hierarchy":[
        "tgn:7569239",
        "tgn:1000004",
        "tgn:7000198",
        "tgn:7016788",
        "tgn:7029392"
    ],
    "tgn:id":7569239,
    "tgn:name:en":"S\u012bt\u0101pura",
    "tgn:placetype":[
        "aat:300008347"
    ]
},
  "bbox": [],
  "geometry": {"coordinates":[75.698078,25.297429],"type":"Point"}
}