{
  "id": 1096863,
  "type": "Feature",
  "properties": {
    "tgn:hierarchy":[
        "tgn:1096863",
        "tgn:7000490",
        "tgn:1000006",
        "tgn:7001830",
        "tgn:7029392"
    ],
    "tgn:id":1096863,
    "tgn:name":"Esk",
    "tgn:placetype":[
        "aat:300008347"
    ]
},
  "bbox": [],
  "geometry": {"coordinates":[152.3833,-27.25],"type":"Point"}
}