{
  "id": 1134563,
  "type": "Feature",
  "properties": {
    "tgn:hierarchy":[
        "tgn:1134563",
        "tgn:1000001",
        "tgn:7012149",
        "tgn:7029392"
    ],
    "tgn:id":1134563,
    "tgn:name":"Seneca Creek",
    "tgn:placetype":[
        "aat:300008706"
    ]
},
  "bbox": [],
  "geometry": {"coordinates":[-103.7667,36.65],"type":"Point"}
}