{
  "id": 2199350,
  "type": "Feature",
  "properties": {
    "tgn:hierarchy":[
        "tgn:2199350",
        "tgn:1000001",
        "tgn:7012149",
        "tgn:7007157",
        "tgn:1002791",
        "tgn:7029392"
    ],
    "tgn:id":2199350,
    "tgn:name":"Brush Creek",
    "tgn:placetype":[
        "aat:300008706"
    ]
},
  "bbox": [],
  "geometry": {"coordinates":[-120.2167,39.2667],"type":"Point"}
}