{
  "id": 2400296,
  "type": "Feature",
  "properties": {
    "tgn:hierarchy":[
        "tgn:2400296",
        "tgn:1000001",
        "tgn:7012149",
        "tgn:2002371",
        "tgn:7007923",
        "tgn:7029392"
    ],
    "tgn:id":2400296,
    "tgn:name":"Horse Draw",
    "tgn:placetype":[
        "aat:300008761"
    ]
},
  "bbox": [],
  "geometry": {"coordinates":[-109.45,43.65],"type":"Point"}
}