<<<<<<< HEAD
{
  "id": 7054265,
  "type": "Feature",
  "properties": {
    "tgn:hierarchy":[
        "tgn:7054265",
        "tgn:7003128",
        "tgn:1000003",
        "tgn:7008516",
        "tgn:1000080",
        "tgn:7029392"
    ],
    "tgn:id":7054265,
    "tgn:name":"Ponte Trevisani",
    "tgn:placetype":[
        "aat:300008347"
    ]
},
  "bbox": [],
  "geometry": {"coordinates":[11.383333,44.833333],"type":"Point"}
}
=======
{"geometry":{"type":"Point","coordinates":[11.383333,44.833333]},"type":"Feature","properties":{"hierarchy":["tgn:7054265","tgn:7003128","tgn:1000003","tgn:7008516","tgn:1000080","tgn:7029392"],"placetype":["aat:300008347"],"id":7054265,"name:xx":"Ponte Trevisani"}}
>>>>>>> 03f74aca74312dbeaf24d7e61306dd6a786dc3d0
