<<<<<<< HEAD
{
  "id": 7022605,
  "type": "Feature",
  "properties": {
    "tgn:hierarchy":[
        "tgn:7022605",
        "tgn:1000001",
        "tgn:7012149",
        "tgn:7007826",
        "tgn:7029392"
    ],
    "tgn:id":7022605,
    "tgn:name":"Coontop Creek",
    "tgn:placetype":[
        "aat:300008706"
    ]
},
  "bbox": [],
  "geometry": {"coordinates":[-94.7167,30.85],"type":"Point"}
}
=======
{"geometry":{"type":"Point","coordinates":[-94.716700,30.850000]},"type":"Feature","properties":{"hierarchy":["tgn:7022605","tgn:1000001","tgn:7012149","tgn:7007826","tgn:7029392"],"placetype":["aat:300008706"],"id":7022605,"name:xx":"Coontop Creek"}}
>>>>>>> 03f74aca74312dbeaf24d7e61306dd6a786dc3d0
