{
  "id": 7022605,
  "type": "Feature",
  "properties": {
    "tgn:hierarchy":[
        "tgn:7022605",
        "tgn:1000001",
        "tgn:7012149",
        "tgn:7007826",
        "tgn:7029392"
    ],
    "tgn:id":7022605,
    "tgn:name":"Coontop Creek",
    "tgn:placetype":[
        "aat:300008706"
    ]
},
  "bbox": [],
  "geometry": {"coordinates":[-94.7167,30.85],"type":"Point"}
}