{
  "id": 2008606,
  "type": "Feature",
  "properties": {
    "tgn:hierarchy":[
        "tgn:2008606",
        "tgn:1000001",
        "tgn:7016172",
        "tgn:7012149",
        "tgn:2000138",
        "tgn:7029392"
    ],
    "tgn:id":2008606,
    "tgn:name":"Johnstown",
    "tgn:placetype":[
        "aat:300008347",
        "aat:300387210"
    ]
},
  "bbox": [],
  "geometry": {"coordinates":[-91.15,35.5667],"type":"Point"}
}