<<<<<<< HEAD
{
  "id": 2333344,
  "type": "Feature",
  "properties": {
    "tgn:hierarchy":[
        "tgn:2333344",
        "tgn:1000001",
        "tgn:7012149",
        "tgn:2000984",
        "tgn:7007520",
        "tgn:7029392"
    ],
    "tgn:id":2333344,
    "tgn:name":"Fogg Lake",
    "tgn:placetype":[
        "aat:300008680"
    ]
},
  "bbox": [],
  "geometry": {"coordinates":[-86.2667,43.4833],"type":"Point"}
}
=======
{"geometry":{"type":"Point","coordinates":[-86.266700,43.483300]},"type":"Feature","properties":{"hierarchy":["tgn:2333344","tgn:1000001","tgn:7012149","tgn:2000984","tgn:7007520","tgn:7029392"],"placetype":["aat:300008680"],"id":2333344,"name:xx":"Fogg Lake"}}
>>>>>>> 03f74aca74312dbeaf24d7e61306dd6a786dc3d0
