{
  "id": 2470838,
  "type": "Feature",
  "properties": {
    "tgn:hierarchy":[
        "tgn:2470838",
        "tgn:1000001",
        "tgn:2001410",
        "tgn:7012149",
        "tgn:7007526",
        "tgn:7029392"
    ],
    "tgn:id":2470838,
    "tgn:name":"Lost City Cove",
    "tgn:placetype":[
        "aat:300132316"
    ]
},
  "bbox": [],
  "geometry": {"coordinates":[-114.35,36.4833],"type":"Point"}
}