<<<<<<< HEAD
{
  "id": 2767785,
  "type": "Feature",
  "properties": {
    "tgn:hierarchy":[
        "tgn:2767785",
        "tgn:1000001",
        "tgn:7012149",
        "tgn:2001896",
        "tgn:7007825",
        "tgn:7029392"
    ],
    "tgn:id":2767785,
    "tgn:name":"Whitehead Spring",
    "tgn:placetype":[
        "aat:300008697"
    ]
},
  "bbox": [],
  "geometry": {"coordinates":[-86.8333,35.5667],"type":"Point"}
}
=======
{"geometry":{"type":"Point","coordinates":[-86.833300,35.566700]},"type":"Feature","properties":{"hierarchy":["tgn:2767785","tgn:1000001","tgn:7012149","tgn:2001896","tgn:7007825","tgn:7029392"],"placetype":["aat:300008697"],"id":2767785,"name:xx":"Whitehead Spring"}}
>>>>>>> 03f74aca74312dbeaf24d7e61306dd6a786dc3d0
