{
  "id": 2683422,
  "type": "Feature",
  "properties": {
    "tgn:hierarchy":[
        "tgn:2683422",
        "tgn:1000001",
        "tgn:2001745",
        "tgn:7012149",
        "tgn:7007712",
        "tgn:7029392"
    ],
    "tgn:id":2683422,
    "tgn:name":"Sparrows Crossroads",
    "tgn:placetype":[
        "aat:300008347"
    ]
},
  "bbox": [],
  "geometry": {"coordinates":[-79.8667,34.05],"type":"Point"}
}