{
  "id": 7243375,
  "type": "Feature",
  "properties": {
    "tgn:hierarchy":[
        "tgn:7243375",
        "tgn:7007877",
        "tgn:1000003",
        "tgn:1000063",
        "tgn:4012014",
        "tgn:7029392"
    ],
    "tgn:id":7243375,
    "tgn:name":"Mai Cornet",
    "tgn:placetype":[
        "aat:300008347"
    ]
},
  "bbox": [],
  "geometry": {"coordinates":[2.977874,50.765419],"type":"Point"}
}