{
  "id": 7209463,
  "type": "Feature",
  "properties": {
    "tgn:hierarchy":[
        "tgn:7209463",
        "tgn:7003692",
        "tgn:1000003",
        "tgn:7000084",
        "tgn:7029392"
    ],
    "tgn:id":7209463,
    "tgn:name":"Berndshausen",
    "tgn:placetype":[
        "aat:300008347"
    ]
},
  "bbox": [],
  "geometry": {"coordinates":[9.770278,49.291667],"type":"Point"}
}