{
  "id": 2279963,
  "type": "Feature",
  "properties": {
    "tgn:hierarchy":[
        "tgn:2279963",
        "tgn:1000001",
        "tgn:7012149",
        "tgn:2001912",
        "tgn:7007825",
        "tgn:7029392"
    ],
    "tgn:id":2279963,
    "tgn:name":"Dean Mine",
    "tgn:placetype":[
        "aat:300000390"
    ]
},
  "bbox": [],
  "geometry": {"coordinates":[-84.3167,36.35],"type":"Point"}
}