<<<<<<< HEAD
{
  "id": 2154680,
  "type": "Feature",
  "properties": {
    "tgn:hierarchy":[
        "tgn:2154680",
        "tgn:1000001",
        "tgn:7012149",
        "tgn:2000221",
        "tgn:7007158",
        "tgn:7029392"
    ],
    "tgn:id":2154680,
    "tgn:name":"Bear Gulch",
    "tgn:placetype":[
        "aat:300008761"
    ]
},
  "bbox": [],
  "geometry": {"coordinates":[-105.2833,39.7],"type":"Point"}
}
=======
{"geometry":{"type":"Point","coordinates":[-105.283300,39.700000]},"type":"Feature","properties":{"hierarchy":["tgn:2154680","tgn:1000001","tgn:7012149","tgn:2000221","tgn:7007158","tgn:7029392"],"placetype":["aat:300008761"],"id":2154680,"name:xx":"Bear Gulch"}}
>>>>>>> 03f74aca74312dbeaf24d7e61306dd6a786dc3d0
