{
  "id": 7457949,
  "type": "Feature",
  "properties": {
    "tgn:hierarchy":[
        "tgn:7457949",
        "tgn:7002445",
        "tgn:1000003",
        "tgn:7008127",
        "tgn:7008591",
        "tgn:7029392"
    ],
    "tgn:id":7457949,
    "tgn:name:en":"Ludworth",
    "tgn:placetype":[
        "aat:300008347"
    ]
},
  "bbox": [],
  "geometry": {"coordinates":[-1.433333,54.766667],"type":"Point"}
}