<<<<<<< HEAD
{
  "id": 2253526,
  "type": "Feature",
  "properties": {
    "tgn:hierarchy":[
        "tgn:2253526",
        "tgn:1000001",
        "tgn:7012149",
        "tgn:2002374",
        "tgn:7007923",
        "tgn:7029392"
    ],
    "tgn:id":2253526,
    "tgn:name":"Cook Ditch Number 9",
    "tgn:placetype":[
        "aat:300006075"
    ]
},
  "bbox": [],
  "geometry": {"coordinates":[-106.75,44.2],"type":"Point"}
}
=======
{"geometry":{"type":"Point","coordinates":[-106.750000,44.200000]},"type":"Feature","properties":{"hierarchy":["tgn:2253526","tgn:1000001","tgn:7012149","tgn:2002374","tgn:7007923","tgn:7029392"],"placetype":["aat:300006075"],"id":2253526,"name:xx":"Cook Ditch Number 9"}}
>>>>>>> 03f74aca74312dbeaf24d7e61306dd6a786dc3d0
