{
  "id": 1099106,
  "type": "Feature",
  "properties": {
    "tgn:hierarchy":[
        "tgn:1099106",
        "tgn:7016670",
        "tgn:1008380",
        "tgn:1000226",
        "tgn:1000006",
        "tgn:7029392"
    ],
    "tgn:id":1099106,
    "tgn:name:en":"Nuhaka",
    "tgn:placetype":[
        "aat:300008347"
    ]
},
  "bbox": [],
  "geometry": {"coordinates":[177.75,-39.05],"type":"Point"}
}