{
  "id": 7527004,
  "type": "Feature",
  "properties": {
    "tgn:hierarchy":[
        "tgn:7527004",
        "tgn:7001242",
        "tgn:7016833",
        "tgn:1001088",
        "tgn:7029392"
    ],
    "tgn:id":7527004,
    "tgn:name:en":"T\u016bnat al Jabal",
    "tgn:placetype":[
        "aat:300387007"
    ]
},
  "bbox": [],
  "geometry": {"coordinates":[30.733333,27.766667],"type":"Point"}
}