{
  "id": 7308942,
  "type": "Feature",
  "properties": {
    "tgn:hierarchy":[
        "tgn:7308942",
        "tgn:1001702",
        "tgn:1000049",
        "tgn:1000002",
        "tgn:7029392"
    ],
    "tgn:id":7308942,
    "tgn:name":"Madre de Dios, Isla",
    "tgn:placetype":[
        "aat:300008791"
    ]
},
  "bbox": [],
  "geometry": {"coordinates":[-75.243889,-50.102778],"type":"Point"}
}