{
  "id": 1128083,
  "type": "Feature",
  "properties": {
    "tgn:hierarchy":[
        "tgn:1128083",
        "tgn:1000004",
        "tgn:1000144",
        "tgn:7029392"
    ],
    "tgn:id":1128083,
    "tgn:name":"Oltu \u00c7ay\u0131",
    "tgn:placetype":[
        "aat:300008707"
    ]
},
  "bbox": [],
  "geometry": {"coordinates":[41.6667,40.8167],"type":"Point"}
}