{
  "id": 1021785,
  "type": "Feature",
  "properties": {
    "tgn:hierarchy":[
        "tgn:1021785",
        "tgn:7006237",
        "tgn:1000047",
        "tgn:7002457",
        "tgn:1000002",
        "tgn:7029392"
    ],
    "tgn:id":1021785,
    "tgn:name":"Itueta",
    "tgn:placetype":[
        "aat:300008347"
    ]
},
  "bbox": [],
  "geometry": {"coordinates":[-41.1833,-19.3833],"type":"Point"}
}