{
  "id": 2460587,
  "type": "Feature",
  "properties": {
    "tgn:hierarchy":[
        "tgn:2460587",
        "tgn:1000001",
        "tgn:7012149",
        "tgn:2000442",
        "tgn:7007248",
        "tgn:7029392"
    ],
    "tgn:id":2460587,
    "tgn:name":"Little Satilla Creek Struc Number Seven L",
    "tgn:placetype":[
        "aat:300006191"
    ]
},
  "bbox": [],
  "geometry": {"coordinates":[-82.0333,31.5667],"type":"Point"}
}