{
  "id": 2164410,
  "type": "Feature",
  "properties": {
    "tgn:hierarchy":[
        "tgn:2164410",
        "tgn:1000001",
        "tgn:7012149",
        "tgn:2001192",
        "tgn:7007523",
        "tgn:7029392"
    ],
    "tgn:id":2164410,
    "tgn:name":"Berry Ford",
    "tgn:placetype":[
        "aat:300008347"
    ]
},
  "bbox": [],
  "geometry": {"coordinates":[-92.8667,37.85],"type":"Point"}
}