{
  "id": 1088671,
  "type": "Feature",
  "properties": {
    "tgn:hierarchy":[
        "tgn:1088671",
        "tgn:7001242",
        "tgn:1001001",
        "tgn:1000158",
        "tgn:7029392"
    ],
    "tgn:id":1088671,
    "tgn:name":"Liranga",
    "tgn:placetype":[
        "aat:300008347"
    ]
},
  "bbox": [],
  "geometry": {"coordinates":[17.5333,-0.7167],"type":"Point"}
}