<<<<<<< HEAD
{
  "id": 7375915,
  "type": "Feature",
  "properties": {
    "tgn:hierarchy":[
        "tgn:7375915",
        "tgn:1000001",
        "tgn:7005595",
        "tgn:7005560",
        "tgn:7029392"
    ],
    "tgn:id":7375915,
    "tgn:name":"Las Higueras",
    "tgn:placetype":[
        "aat:300008347"
    ]
},
  "bbox": [],
  "geometry": {"coordinates":[-106.862222,24.423333],"type":"Point"}
}
=======
{"geometry":{"type":"Point","coordinates":[-106.862222,24.423333]},"type":"Feature","properties":{"hierarchy":["tgn:7375915","tgn:1000001","tgn:7005595","tgn:7005560","tgn:7029392"],"placetype":["aat:300008347"],"id":7375915,"name:xx":"Las Higueras"}}
>>>>>>> 03f74aca74312dbeaf24d7e61306dd6a786dc3d0
