{
  "id": 7495663,
  "type": "Feature",
  "properties": {
    "tgn:hierarchy":[
        "tgn:7495663",
        "tgn:7001010",
        "tgn:1000004",
        "tgn:1000141",
        "tgn:7029392"
    ],
    "tgn:id":7495663,
    "tgn:name":"Beihuiguixian Biaozhi",
    "tgn:placetype":[
        "aat:300006958"
    ]
},
  "bbox": [],
  "geometry": {"coordinates":[121.495927,23.448656],"type":"Point"}
}