{
  "id": 2307569,
  "type": "Feature",
  "properties": {
    "tgn:hierarchy":[
        "tgn:2307569",
        "tgn:1000001",
        "tgn:2001266",
        "tgn:7012149",
        "tgn:7007524",
        "tgn:7029392"
    ],
    "tgn:id":2307569,
    "tgn:name":"East Fork Spring Creek",
    "tgn:placetype":[
        "aat:300008706"
    ]
},
  "bbox": [],
  "geometry": {"coordinates":[-111.4167,47.0833],"type":"Point"}
}