{
  "id": 2524417,
  "type": "Feature",
  "properties": {
    "tgn:hierarchy":[
        "tgn:2524417",
        "tgn:1000001",
        "tgn:7012149",
        "tgn:2002278",
        "tgn:7013961",
        "tgn:7029392"
    ],
    "tgn:id":2524417,
    "tgn:name":"Morgan Ridge",
    "tgn:placetype":[
        "aat:300266640"
    ]
},
  "bbox": [],
  "geometry": {"coordinates":[-81.2333,37.4667],"type":"Point"}
}