{
  "id": 7277978,
  "type": "Feature",
  "properties": {
    "tgn:hierarchy":[
        "tgn:7277978",
        "tgn:1001637",
        "tgn:1000049",
        "tgn:1000002",
        "tgn:7029392"
    ],
    "tgn:id":7277978,
    "tgn:name":"Muelle El Parr\u00f3n",
    "tgn:placetype":[
        "aat:300120779"
    ]
},
  "bbox": [],
  "geometry": {"coordinates":[-73.093056,-36.675],"type":"Point"}
}