<<<<<<< HEAD
{
  "id": 7057292,
  "type": "Feature",
  "properties": {
    "tgn:hierarchy":[
        "tgn:7057292",
        "tgn:7015163",
        "tgn:1000003",
        "tgn:7003121",
        "tgn:1000080",
        "tgn:7029392"
    ],
    "tgn:id":7057292,
    "tgn:name":"Badu Mesina, Riu",
    "tgn:placetype":[
        "aat:300008699"
    ]
},
  "bbox": [],
  "geometry": {"coordinates":[9.0,40.833333],"type":"Point"}
}
=======
{"geometry":{"type":"Point","coordinates":[9.000000,40.833333]},"type":"Feature","properties":{"hierarchy":["tgn:7057292","tgn:7015163","tgn:1000003","tgn:7003121","tgn:1000080","tgn:7029392"],"placetype":["aat:300008699"],"id":7057292,"name:xx":"Badu Mesina, Riu"}}
>>>>>>> 03f74aca74312dbeaf24d7e61306dd6a786dc3d0
