{
  "id": 2117391,
  "type": "Feature",
  "properties": {
    "tgn:hierarchy":[
        "tgn:2117391",
        "tgn:1000001",
        "tgn:7012149",
        "tgn:2002304",
        "tgn:7013961",
        "tgn:7029392"
    ],
    "tgn:id":2117391,
    "tgn:name":"Beechwood",
    "tgn:placetype":[
        "aat:300008347"
    ]
},
  "bbox": [],
  "geometry": {"coordinates":[-81.35,37.5667],"type":"Point"}
}