{
  "id": 7033738,
  "type": "Feature",
  "properties": {
    "tgn:hierarchy":[
        "tgn:7033738",
        "tgn:7003129",
        "tgn:1000003",
        "tgn:7008516",
        "tgn:1000080",
        "tgn:7029392"
    ],
    "tgn:id":7033738,
    "tgn:name":"Piavola",
    "tgn:placetype":[
        "aat:300008347"
    ]
},
  "bbox": [],
  "geometry": {"coordinates":[12.139167,44.026667],"type":"Point"}
}