{
  "id": 7080069,
  "type": "Feature",
  "properties": {
    "tgn:hierarchy":[
        "tgn:7080069",
        "tgn:7000096",
        "tgn:1000003",
        "tgn:7000084",
        "tgn:7029392"
    ],
    "tgn:id":7080069,
    "tgn:name":"Wublitz",
    "tgn:placetype":[
        "aat:300008680"
    ]
},
  "bbox": [],
  "geometry": {"coordinates":[12.366667,52.516667],"type":"Point"}
}