{
  "id": 7510015,
  "type": "Feature",
  "properties": {
    "tgn:hierarchy":[
        "tgn:7510015",
        "tgn:1009227",
        "tgn:1000226",
        "tgn:7016729",
        "tgn:1000006",
        "tgn:7029392"
    ],
    "tgn:id":7510015,
    "tgn:name:en":"Te Matau a Maui Bay",
    "tgn:placetype":[
        "aat:300132316"
    ]
},
  "bbox": [],
  "geometry": {"coordinates":[173.966667,-41.183333],"type":"Point"}
}