<<<<<<< HEAD
{
  "id": 2158676,
  "type": "Feature",
  "properties": {
    "tgn:hierarchy":[
        "tgn:2158676",
        "tgn:1000001",
        "tgn:7012149",
        "tgn:1002862",
        "tgn:7007920",
        "tgn:7029392"
    ],
    "tgn:id":2158676,
    "tgn:name":"Beaverton Valley",
    "tgn:placetype":[
        "aat:300008761"
    ]
},
  "bbox": [],
  "geometry": {"coordinates":[-123.0667,48.55],"type":"Point"}
}
=======
{"geometry":{"type":"Point","coordinates":[-123.066700,48.550000]},"type":"Feature","properties":{"hierarchy":["tgn:2158676","tgn:1000001","tgn:7012149","tgn:1002862","tgn:7007920","tgn:7029392"],"placetype":["aat:300008761"],"id":2158676,"name:xx":"Beaverton Valley"}}
>>>>>>> 03f74aca74312dbeaf24d7e61306dd6a786dc3d0
