{
  "id": 7331743,
  "type": "Feature",
  "properties": {
    "tgn:hierarchy":[
        "tgn:7331743",
        "tgn:7002805",
        "tgn:7002758",
        "tgn:1000003",
        "tgn:1000095",
        "tgn:7029392"
    ],
    "tgn:id":7331743,
    "tgn:name":"La Jauca",
    "tgn:placetype":[
        "aat:300008347"
    ]
},
  "bbox": [],
  "geometry": {"coordinates":[-2.55,37.416667],"type":"Point"}
}