{
  "id": 7261712,
  "type": "Feature",
  "properties": {
    "tgn:hierarchy":[
        "tgn:7261712",
        "tgn:1000003",
        "tgn:7003624",
        "tgn:7016845",
        "tgn:7029392"
    ],
    "tgn:id":7261712,
    "tgn:name:nl":"De Stroom",
    "tgn:placetype":[
        "aat:300008699"
    ]
},
  "bbox": [],
  "geometry": {"coordinates":[5.15,51.416667],"type":"Point"}
}