{
  "id": 2555365,
  "type": "Feature",
  "properties": {
    "tgn:hierarchy":[
        "tgn:2555365",
        "tgn:1000001",
        "tgn:2001480",
        "tgn:7012149",
        "tgn:7007709",
        "tgn:7029392"
    ],
    "tgn:id":2555365,
    "tgn:name":"Odell Pond",
    "tgn:placetype":[
        "aat:300006191"
    ]
},
  "bbox": [],
  "geometry": {"coordinates":[-79.15,35.7667],"type":"Point"}
}