{
  "id": 7288437,
  "type": "Feature",
  "properties": {
    "tgn:hierarchy":[
        "tgn:7288437",
        "tgn:1001637",
        "tgn:1000049",
        "tgn:1000002",
        "tgn:7029392"
    ],
    "tgn:id":7288437,
    "tgn:name":"Huillinco, R\u00edo",
    "tgn:placetype":[
        "aat:300008699"
    ]
},
  "bbox": [],
  "geometry": {"coordinates":[-73.283333,-38.116667],"type":"Point"}
}