{
  "id": 2170747,
  "type": "Feature",
  "properties": {
    "tgn:hierarchy":[
        "tgn:2170747",
        "tgn:1000001",
        "tgn:7012149",
        "tgn:2001487",
        "tgn:7007709",
        "tgn:7029392"
    ],
    "tgn:id":2170747,
    "tgn:name":"Big Sandy Run",
    "tgn:placetype":[
        "aat:300008699"
    ]
},
  "bbox": [],
  "geometry": {"coordinates":[-78.9167,34.9833],"type":"Point"}
}