<<<<<<< HEAD
{
  "id": 7354441,
  "type": "Feature",
  "properties": {
    "tgn:hierarchy":[
        "tgn:7354441",
        "tgn:1000001",
        "tgn:1001960",
        "tgn:7005560",
        "tgn:7029392"
    ],
    "tgn:id":7354441,
    "tgn:name":"Rancho Charababi",
    "tgn:placetype":[
        "aat:300000241"
    ]
},
  "bbox": [],
  "geometry": {"coordinates":[-110.5,30.183333],"type":"Point"}
}
=======
{"geometry":{"type":"Point","coordinates":[-110.500000,30.183333]},"type":"Feature","properties":{"hierarchy":["tgn:7354441","tgn:1000001","tgn:1001960","tgn:7005560","tgn:7029392"],"placetype":["aat:300000241"],"id":7354441,"name:xx":"Rancho Charababi"}}
>>>>>>> 03f74aca74312dbeaf24d7e61306dd6a786dc3d0
