{
  "id": 7552839,
  "type": "Feature",
  "properties": {
    "tgn:hierarchy":[
        "tgn:7552839",
        "tgn:1000004",
        "tgn:7000198",
        "tgn:7016722",
        "tgn:7029392"
    ],
    "tgn:id":7552839,
    "tgn:name:en":"Naw\u0101da",
    "tgn:placetype":[
        "aat:300008347"
    ]
},
  "bbox": [],
  "geometry": {"coordinates":[80.066667,27.016667],"type":"Point"}
}