<<<<<<< HEAD
{
  "id": 2404725,
  "type": "Feature",
  "properties": {
    "tgn:hierarchy":[
        "tgn:2404725",
        "tgn:1000001",
        "tgn:7012149",
        "tgn:2002158",
        "tgn:7007919",
        "tgn:7029392"
    ],
    "tgn:id":2404725,
    "tgn:name":"Huckleberry Creek",
    "tgn:placetype":[
        "aat:300008706"
    ]
},
  "bbox": [],
  "geometry": {"coordinates":[-80.4,36.9167],"type":"Point"}
}
=======
{"geometry":{"type":"Point","coordinates":[-80.400000,36.916700]},"type":"Feature","properties":{"hierarchy":["tgn:2404725","tgn:1000001","tgn:7012149","tgn:2002158","tgn:7007919","tgn:7029392"],"placetype":["aat:300008706"],"id":2404725,"name:xx":"Huckleberry Creek"}}
>>>>>>> 03f74aca74312dbeaf24d7e61306dd6a786dc3d0
