{
  "id": 2162910,
  "type": "Feature",
  "properties": {
    "tgn:hierarchy":[
        "tgn:2162910",
        "tgn:1000001",
        "tgn:7012149",
        "tgn:2002117",
        "tgn:7007827",
        "tgn:7029392"
    ],
    "tgn:id":2162910,
    "tgn:name":"Benjamin Mine",
    "tgn:placetype":[
        "aat:300000390"
    ]
},
  "bbox": [],
  "geometry": {"coordinates":[-111.0667,41.6833],"type":"Point"}
}