<<<<<<< HEAD
{
  "id": 7248471,
  "type": "Feature",
  "properties": {
    "tgn:hierarchy":[
        "tgn:7248471",
        "tgn:7003465",
        "tgn:1000003",
        "tgn:1000063",
        "tgn:4012014",
        "tgn:7029392"
    ],
    "tgn:id":7248471,
    "tgn:name":"Beynert, Bois de",
    "tgn:placetype":[
        "aat:300008863"
    ]
},
  "bbox": [],
  "geometry": {"coordinates":[5.766667,49.716667],"type":"Point"}
}
=======
{"geometry":{"type":"Point","coordinates":[5.766667,49.716667]},"type":"Feature","properties":{"hierarchy":["tgn:7248471","tgn:7003465","tgn:1000003","tgn:1000063","tgn:4012014","tgn:7029392"],"placetype":["aat:300008863"],"id":7248471,"name:xx":"Beynert, Bois de"}}
>>>>>>> 03f74aca74312dbeaf24d7e61306dd6a786dc3d0
