{
  "id": 7073494,
  "type": "Feature",
  "properties": {
    "tgn:hierarchy":[
        "tgn:7073494",
        "tgn:1000003",
        "tgn:7003678",
        "tgn:7000084",
        "tgn:7029392"
    ],
    "tgn:id":7073494,
    "tgn:name":"Streichen-Berg",
    "tgn:placetype":[
        "aat:300008777"
    ]
},
  "bbox": [],
  "geometry": {"coordinates":[8.583333,50.816667],"type":"Point"}
}