{
  "id": 2592730,
  "type": "Feature",
  "properties": {
    "tgn:hierarchy":[
        "tgn:2592730",
        "tgn:1000001",
        "tgn:1002389",
        "tgn:7012149",
        "tgn:7007828",
        "tgn:7029392"
    ],
    "tgn:id":2592730,
    "tgn:name":"Popasquash Island",
    "tgn:placetype":[
        "aat:300008791"
    ]
},
  "bbox": [],
  "geometry": {"coordinates":[-73.1833,44.85],"type":"Point"}
}