{
  "id": 2722779,
  "type": "Feature",
  "properties": {
    "tgn:hierarchy":[
        "tgn:2722779",
        "tgn:1000001",
        "tgn:7012149",
        "tgn:7007157",
        "tgn:1002675",
        "tgn:7029392"
    ],
    "tgn:id":2722779,
    "tgn:name":"Tioga Peak",
    "tgn:placetype":[
        "aat:300008798"
    ]
},
  "bbox": [],
  "geometry": {"coordinates":[-119.2333,37.9333],"type":"Point"}
}