{
  "id": 7494105,
  "type": "Feature",
  "properties": {
    "tgn:hierarchy":[
        "tgn:7494105",
        "tgn:1000004",
        "tgn:7001014",
        "tgn:1000141",
        "tgn:7029392"
    ],
    "tgn:id":7494105,
    "tgn:name":"Kendi Qiao",
    "tgn:placetype":[
        "aat:300007836"
    ]
},
  "bbox": [],
  "geometry": {"coordinates":[120.401544,23.728038],"type":"Point"}
}