{
  "id": 7523758,
  "type": "Feature",
  "properties": {
    "tgn:hierarchy":[
        "tgn:7523758",
        "tgn:7001242",
        "tgn:7016833",
        "tgn:1001418",
        "tgn:7029392"
    ],
    "tgn:id":7523758,
    "tgn:name:en":"Beacon Point",
    "tgn:placetype":[
        "aat:300386846"
    ]
},
  "bbox": [],
  "geometry": {"coordinates":[25.179055,31.569476],"type":"Point"}
}