{
  "id": 1133853,
  "type": "Feature",
  "properties": {
    "tgn:hierarchy":[
        "tgn:1133853",
        "tgn:1000001",
        "tgn:7012149",
        "tgn:7007252",
        "tgn:7029392"
    ],
    "tgn:id":1133853,
    "tgn:name":"Mill Creek",
    "tgn:placetype":[
        "aat:300008706"
    ]
},
  "bbox": [],
  "geometry": {"coordinates":[-85.1667,40.55],"type":"Point"}
}