{
  "id": 7302306,
  "type": "Feature",
  "properties": {
    "tgn:hierarchy":[
        "tgn:7302306",
        "tgn:7001122",
        "tgn:1000003",
        "tgn:7002765",
        "tgn:1000095",
        "tgn:7029392"
    ],
    "tgn:id":7302306,
    "tgn:name":"Nabarxa, Punta",
    "tgn:placetype":[
        "aat:300386846"
    ]
},
  "bbox": [],
  "geometry": {"coordinates":[3.466667,39.683333],"type":"Point"}
}