{
  "id": 7121200,
  "type": "Feature",
  "properties": {
    "tgn:hierarchy":[
        "tgn:7121200",
        "tgn:7003692",
        "tgn:1000003",
        "tgn:7000084",
        "tgn:7029392"
    ],
    "tgn:id":7121200,
    "tgn:name":"Pfaffenhofen",
    "tgn:placetype":[
        "aat:300008347"
    ]
},
  "bbox": [],
  "geometry": {"coordinates":[8.976389,49.064444],"type":"Point"}
}