{
  "id": 2515883,
  "type": "Feature",
  "properties": {
    "tgn:hierarchy":[
        "tgn:2515883",
        "tgn:1000001",
        "tgn:7012149",
        "tgn:7007157",
        "tgn:1002894",
        "tgn:7029392"
    ],
    "tgn:id":2515883,
    "tgn:name":"Milton Creek",
    "tgn:placetype":[
        "aat:300008706"
    ]
},
  "bbox": [],
  "geometry": {"coordinates":[-120.5333,39.5167],"type":"Point"}
}