{
  "id": 1110769,
  "type": "Feature",
  "properties": {
    "tgn:hierarchy":[
        "tgn:1110769",
        "tgn:7005132",
        "tgn:1000001",
        "tgn:7005118",
        "tgn:7029392"
    ],
    "tgn:id":1110769,
    "tgn:name":"Hams Bluff",
    "tgn:placetype":[
        "aat:300008749"
    ]
},
  "bbox": [],
  "geometry": {"coordinates":[-64.8667,17.7667],"type":"Point"}
}