{
  "id": 7126856,
  "type": "Feature",
  "properties": {
    "tgn:hierarchy":[
        "tgn:7126856",
        "tgn:1000003",
        "tgn:7003678",
        "tgn:7000084",
        "tgn:7029392"
    ],
    "tgn:id":7126856,
    "tgn:name":"Ober-Beerbach",
    "tgn:placetype":[
        "aat:300008347"
    ]
},
  "bbox": [],
  "geometry": {"coordinates":[8.684722,49.764722],"type":"Point"}
}