{
  "id": 7048468,
  "type": "Feature",
  "properties": {
    "tgn:hierarchy":[
        "tgn:7048468",
        "tgn:1000003",
        "tgn:7003122",
        "tgn:1001762",
        "tgn:1000080",
        "tgn:7029392"
    ],
    "tgn:id":7048468,
    "tgn:name":"Chiesa Nuova",
    "tgn:placetype":[
        "aat:300008347"
    ]
},
  "bbox": [],
  "geometry": {"coordinates":[12.65,38.016667],"type":"Point"}
}