{
  "id": 1012511,
  "type": "Feature",
  "properties": {
    "tgn:hierarchy":[
        "tgn:1012511",
        "tgn:7002445",
        "tgn:1000003",
        "tgn:7012077",
        "tgn:7008591",
        "tgn:7029392"
    ],
    "tgn:id":1012511,
    "tgn:name:en":"Start Point",
    "tgn:placetype":[
        "aat:300008850",
        "aat:300386846"
    ]
},
  "bbox": [],
  "geometry": {"coordinates":[-3.633333,50.216667],"type":"Point"}
}