{
  "id": 2376615,
  "type": "Feature",
  "properties": {
    "tgn:hierarchy":[
        "tgn:2376615",
        "tgn:1000001",
        "tgn:7012149",
        "tgn:2001706",
        "tgn:7007708",
        "tgn:7029392"
    ],
    "tgn:id":2376615,
    "tgn:name":"Hardscrable Creek",
    "tgn:placetype":[
        "aat:300008706"
    ]
},
  "bbox": [],
  "geometry": {"coordinates":[-123.35,43.7333],"type":"Point"}
}