{
  "id": 2730189,
  "type": "Feature",
  "properties": {
    "tgn:hierarchy":[
        "tgn:2730189",
        "tgn:1000001",
        "tgn:7012149",
        "tgn:2002281",
        "tgn:7013961",
        "tgn:7029392"
    ],
    "tgn:id":2730189,
    "tgn:name":"Trout Pond",
    "tgn:placetype":[
        "aat:300006191"
    ]
},
  "bbox": [],
  "geometry": {"coordinates":[-79.7833,39.65],"type":"Point"}
}