{
  "id": 2076143,
  "type": "Feature",
  "properties": {
    "tgn:hierarchy":[
        "tgn:2076143",
        "tgn:1000001",
        "tgn:7012149",
        "tgn:2001550",
        "tgn:7007709",
        "tgn:7029392"
    ],
    "tgn:id":2076143,
    "tgn:name":"Pleasant Grove",
    "tgn:placetype":[
        "aat:300008347",
        "aat:300387210"
    ]
},
  "bbox": [],
  "geometry": {"coordinates":[-76.5833,35.9167],"type":"Point"}
}