{
  "id": 7418390,
  "type": "Feature",
  "properties": {
    "tgn:hierarchy":[
        "tgn:7418390",
        "tgn:1001835",
        "tgn:1000001",
        "tgn:7005560",
        "tgn:7029392"
    ],
    "tgn:id":7418390,
    "tgn:name":"Cedro",
    "tgn:placetype":[
        "aat:300387033"
    ]
},
  "bbox": [],
  "geometry": {"coordinates":[-115.984722,32.149444],"type":"Point"}
}