{
  "id": 4011311,
  "type": "Feature",
  "properties": {
    "tgn:hierarchy":[
        "tgn:4011311",
        "tgn:7593917",
        "tgn:1000003",
        "tgn:1001780",
        "tgn:7029392"
    ],
    "tgn:id":4011311,
    "tgn:name":"Tova\u010dov",
    "tgn:placetype":[
        "aat:300008347"
    ]
},
  "bbox": [],
  "geometry": {"coordinates":[17.2833,49.4333],"type":"Point"}
}