{
  "id": 2364929,
  "type": "Feature",
  "properties": {
    "tgn:hierarchy":[
        "tgn:2364929",
        "tgn:1000001",
        "tgn:7012149",
        "tgn:2001542",
        "tgn:7007709",
        "tgn:7029392"
    ],
    "tgn:id":2364929,
    "tgn:name":"Greenhill Lake",
    "tgn:placetype":[
        "aat:300006191"
    ]
},
  "bbox": [],
  "geometry": {"coordinates":[-80.6167,36.55],"type":"Point"}
}