{
  "id": 7231489,
  "type": "Feature",
  "properties": {
    "tgn:hierarchy":[
        "tgn:7231489",
        "tgn:7002681",
        "tgn:7001395",
        "tgn:1000003",
        "tgn:1000074",
        "tgn:7029392"
    ],
    "tgn:id":7231489,
    "tgn:name":"Mani\u00e1ti, \u00c1kra",
    "tgn:placetype":[
        "aat:300008850"
    ]
},
  "bbox": [],
  "geometry": {"coordinates":[23.566667,37.366667],"type":"Point"}
}