{
  "id": 2222072,
  "type": "Feature",
  "properties": {
    "tgn:hierarchy":[
        "tgn:2222072",
        "tgn:1000001",
        "tgn:2001009",
        "tgn:7012149",
        "tgn:7007521",
        "tgn:7029392"
    ],
    "tgn:id":2222072,
    "tgn:name":"Carnahan Lake",
    "tgn:placetype":[
        "aat:300008680"
    ]
},
  "bbox": [],
  "geometry": {"coordinates":[-94.25,46.9833],"type":"Point"}
}