{
  "id": 7207034,
  "type": "Feature",
  "properties": {
    "tgn:hierarchy":[
        "tgn:7207034",
        "tgn:7003669",
        "tgn:1000003",
        "tgn:7000084",
        "tgn:7029392"
    ],
    "tgn:id":7207034,
    "tgn:name":"Butzenhof",
    "tgn:placetype":[
        "aat:300000206"
    ]
},
  "bbox": [],
  "geometry": {"coordinates":[10.816667,49.333333],"type":"Point"}
}