{
  "id": 7319631,
  "type": "Feature",
  "properties": {
    "tgn:hierarchy":[
        "tgn:7319631",
        "tgn:1001630",
        "tgn:1000049",
        "tgn:1000002",
        "tgn:7029392"
    ],
    "tgn:id":7319631,
    "tgn:name":"Agua de Ordenes, Cord\u00f3n",
    "tgn:placetype":[
        "aat:300008795"
    ]
},
  "bbox": [],
  "geometry": {"coordinates":[-71.05,-28.383333],"type":"Point"}
}