{
  "id": 7548051,
  "type": "Feature",
  "properties": {
    "tgn:hierarchy":[
        "tgn:7548051",
        "tgn:1000004",
        "tgn:7000198",
        "tgn:1001895",
        "tgn:7029392"
    ],
    "tgn:id":7548051,
    "tgn:name:en":"Aundhi",
    "tgn:placetype":[
        "aat:300008347"
    ]
},
  "bbox": [],
  "geometry": {"coordinates":[80.45,20.233333],"type":"Point"}
}