{
  "id": 2260535,
  "type": "Feature",
  "properties": {
    "tgn:hierarchy":[
        "tgn:2260535",
        "tgn:1000001",
        "tgn:7012149",
        "tgn:2001079",
        "tgn:7007521",
        "tgn:7029392"
    ],
    "tgn:id":2260535,
    "tgn:name":"County Ditch Number Forty",
    "tgn:placetype":[
        "aat:300006075"
    ]
},
  "bbox": [],
  "geometry": {"coordinates":[-93.6833,43.8667],"type":"Point"}
}