{
  "id": 2293525,
  "type": "Feature",
  "properties": {
    "tgn:hierarchy":[
        "tgn:2293525",
        "tgn:1000001",
        "tgn:7012149",
        "tgn:7029392"
    ],
    "tgn:id":2293525,
    "tgn:name":"Double Spring Branch",
    "tgn:placetype":[
        "aat:300008699"
    ]
},
  "bbox": [],
  "geometry": {"coordinates":[-80.5167,36.5333],"type":"Point"}
}