{
  "id": 7136842,
  "type": "Feature",
  "properties": {
    "tgn:hierarchy":[
        "tgn:7136842",
        "tgn:1000003",
        "tgn:7003676",
        "tgn:7000084",
        "tgn:7029392"
    ],
    "tgn:id":7136842,
    "tgn:name":"Lerchen-Berg",
    "tgn:placetype":[
        "aat:300008777"
    ]
},
  "bbox": [],
  "geometry": {"coordinates":[10.133333,53.15],"type":"Point"}
}