{
  "id": 1045770,
  "type": "Feature",
  "properties": {
    "tgn:hierarchy":[
        "tgn:1045770",
        "tgn:7002996",
        "tgn:1000003",
        "tgn:7002997",
        "tgn:1000080",
        "tgn:7029392"
    ],
    "tgn:id":1045770,
    "tgn:name":"Orsago",
    "tgn:placetype":[
        "aat:300008347"
    ]
},
  "bbox": [],
  "geometry": {"coordinates":[12.420833,45.932222],"type":"Point"}
}