{
  "id": 2018656,
  "type": "Feature",
  "properties": {
    "tgn:hierarchy":[
        "tgn:2018656",
        "tgn:1000001",
        "tgn:7012149",
        "tgn:1002641",
        "tgn:7007240",
        "tgn:7029392"
    ],
    "tgn:id":2018656,
    "tgn:name":"Bluefield",
    "tgn:placetype":[
        "aat:300387016"
    ]
},
  "bbox": [],
  "geometry": {"coordinates":[-80.5833,27.1833],"type":"Point"}
}