{
  "id": 2625469,
  "type": "Feature",
  "properties": {
    "tgn:hierarchy":[
        "tgn:2625469",
        "tgn:1000001",
        "tgn:7012149",
        "tgn:2001716",
        "tgn:7007708",
        "tgn:7029392"
    ],
    "tgn:id":2625469,
    "tgn:name":"Rockpile Lake",
    "tgn:placetype":[
        "aat:300008680"
    ]
},
  "bbox": [],
  "geometry": {"coordinates":[-122.1333,43.4833],"type":"Point"}
}