{
  "id": 2090074,
  "type": "Feature",
  "properties": {
    "tgn:hierarchy":[
        "tgn:2090074",
        "tgn:1000001",
        "tgn:1002310",
        "tgn:7012149",
        "tgn:7007710",
        "tgn:7029392"
    ],
    "tgn:id":2090074,
    "tgn:name":"Lemoyne",
    "tgn:placetype":[
        "aat:300008347"
    ]
},
  "bbox": [],
  "geometry": {"coordinates":[-76.8833,40.2333],"type":"Point"}
}