<<<<<<< HEAD
{
  "id": 7245713,
  "type": "Feature",
  "properties": {
    "tgn:hierarchy":[
        "tgn:7245713",
        "tgn:7003458",
        "tgn:1000003",
        "tgn:1000063",
        "tgn:7018236",
        "tgn:7029392"
    ],
    "tgn:id":7245713,
    "tgn:name":"De Paling",
    "tgn:placetype":[
        "aat:300008347"
    ]
},
  "bbox": [],
  "geometry": {"coordinates":[3.433333,50.95],"type":"Point"}
}
=======
{"geometry":{"type":"Point","coordinates":[3.433333,50.950000]},"type":"Feature","properties":{"hierarchy":["tgn:7245713","tgn:7003458","tgn:1000003","tgn:1000063","tgn:7018236","tgn:7029392"],"placetype":["aat:300008347"],"id":7245713,"name:xx":"De Paling"}}
>>>>>>> 03f74aca74312dbeaf24d7e61306dd6a786dc3d0
