{
  "id": 7556147,
  "type": "Feature",
  "properties": {
    "tgn:hierarchy":[
        "tgn:7556147",
        "tgn:1000004",
        "tgn:7000198",
        "tgn:7016788",
        "tgn:7029392"
    ],
    "tgn:id":7556147,
    "tgn:name:en":"Phalsund",
    "tgn:placetype":[
        "aat:300008347"
    ]
},
  "bbox": [],
  "geometry": {"coordinates":[71.92323,26.397497],"type":"Point"}
}