{
  "id": 7245595,
  "type": "Feature",
  "properties": {
    "tgn:hierarchy":[
        "tgn:7245595",
        "tgn:7003456",
        "tgn:1000003",
        "tgn:1000063",
        "tgn:7018236",
        "tgn:7029392"
    ],
    "tgn:id":7245595,
    "tgn:name":"Broekzijde",
    "tgn:placetype":[
        "aat:300008347"
    ]
},
  "bbox": [],
  "geometry": {"coordinates":[4.804925,51.240435],"type":"Point"}
}