{
  "id": 7465950,
  "type": "Feature",
  "properties": {
    "tgn:hierarchy":[
        "tgn:7465950",
        "tgn:7002444",
        "tgn:1000003",
        "tgn:7008082",
        "tgn:7008591",
        "tgn:7029392"
    ],
    "tgn:id":7465950,
    "tgn:name:en":"Ardtornish Bay",
    "tgn:placetype":[
        "aat:300132316"
    ]
},
  "bbox": [],
  "geometry": {"coordinates":[-5.733333,56.516667],"type":"Point"}
}