<<<<<<< HEAD
{
  "id": 2700291,
  "type": "Feature",
  "properties": {
    "tgn:hierarchy":[
        "tgn:2700291",
        "tgn:1000001",
        "tgn:7012149",
        "tgn:1002756",
        "tgn:7007240",
        "tgn:7029392"
    ],
    "tgn:id":2700291,
    "tgn:name":"Sturm Island",
    "tgn:placetype":[
        "aat:300008791"
    ]
},
  "bbox": [],
  "geometry": {"coordinates":[-81.2667,27.95],"type":"Point"}
}
=======
{"geometry":{"type":"Point","coordinates":[-81.266700,27.950000]},"type":"Feature","properties":{"hierarchy":["tgn:2700291","tgn:1000001","tgn:7012149","tgn:1002756","tgn:7007240","tgn:7029392"],"placetype":["aat:300008791"],"id":2700291,"name:xx":"Sturm Island"}}
>>>>>>> 03f74aca74312dbeaf24d7e61306dd6a786dc3d0
