<<<<<<< HEAD
{
  "id": 7352506,
  "type": "Feature",
  "properties": {
    "tgn:hierarchy":[
        "tgn:7352506",
        "tgn:1000001",
        "tgn:7005600",
        "tgn:7005560",
        "tgn:7029392"
    ],
    "tgn:id":7352506,
    "tgn:name":"Buctzotz",
    "tgn:placetype":[
        "aat:300008347"
    ]
},
  "bbox": [],
  "geometry": {"coordinates":[-88.783333,21.2],"type":"Point"}
}
=======
{"geometry":{"type":"Point","coordinates":[-88.783333,21.200000]},"type":"Feature","properties":{"hierarchy":["tgn:7352506","tgn:1000001","tgn:7005600","tgn:7005560","tgn:7029392"],"placetype":["aat:300008347"],"id":7352506,"name:xx":"Buctzotz"}}
>>>>>>> 03f74aca74312dbeaf24d7e61306dd6a786dc3d0
