{
  "id": 2058635,
  "type": "Feature",
  "properties": {
    "tgn:hierarchy":[
        "tgn:2058635",
        "tgn:1000001",
        "tgn:7012149",
        "tgn:2001236",
        "tgn:7007523",
        "tgn:7029392"
    ],
    "tgn:id":2058635,
    "tgn:name":"Edgehill",
    "tgn:placetype":[
        "aat:300008347",
        "aat:300387210"
    ]
},
  "bbox": [],
  "geometry": {"coordinates":[-90.9333,37.5833],"type":"Point"}
}