<<<<<<< HEAD
{
  "id": 2764248,
  "type": "Feature",
  "properties": {
    "tgn:hierarchy":[
        "tgn:2764248",
        "tgn:1000001",
        "tgn:2000577",
        "tgn:7012149",
        "tgn:7007253",
        "tgn:7029392"
    ],
    "tgn:id":2764248,
    "tgn:name":"Wheelerwood",
    "tgn:placetype":[
        "aat:300008347"
    ]
},
  "bbox": [],
  "geometry": {"coordinates":[-93.05,43.2333],"type":"Point"}
}
=======
{"geometry":{"type":"Point","coordinates":[-93.050000,43.233300]},"type":"Feature","properties":{"hierarchy":["tgn:2764248","tgn:1000001","tgn:2000577","tgn:7012149","tgn:7007253","tgn:7029392"],"placetype":["aat:300008347"],"id":2764248,"name:xx":"Wheelerwood"}}
>>>>>>> 03f74aca74312dbeaf24d7e61306dd6a786dc3d0
