{
  "id": 7152373,
  "type": "Feature",
  "properties": {
    "tgn:hierarchy":[
        "tgn:7152373",
        "tgn:1000003",
        "tgn:7003687",
        "tgn:7000084",
        "tgn:7029392"
    ],
    "tgn:id":7152373,
    "tgn:name":"K\u00e4cklitz",
    "tgn:placetype":[
        "aat:300008347"
    ]
},
  "bbox": [],
  "geometry": {"coordinates":[11.116667,52.733333],"type":"Point"}
}