{
  "id": 2321386,
  "type": "Feature",
  "properties": {
    "tgn:hierarchy":[
        "tgn:2321386",
        "tgn:1000001",
        "tgn:7012149",
        "tgn:7007158",
        "tgn:2000243",
        "tgn:7029392"
    ],
    "tgn:id":2321386,
    "tgn:name":"Fairfield Gulch",
    "tgn:placetype":[
        "aat:300008761"
    ]
},
  "bbox": [],
  "geometry": {"coordinates":[-107.9333,40.0333],"type":"Point"}
}