{
  "id": 7575971,
  "type": "Feature",
  "properties": {
    "tgn:hierarchy":[
        "tgn:7575971",
        "tgn:7001819",
        "tgn:1000004",
        "tgn:7000198",
        "tgn:7029392"
    ],
    "tgn:id":7575971,
    "tgn:name:en":"Kapteng",
    "tgn:placetype":[
        "aat:300008347"
    ]
},
  "bbox": [],
  "geometry": {"coordinates":[91.690321,27.534364],"type":"Point"}
}