{
  "id": 2341041,
  "type": "Feature",
  "properties": {
    "tgn:hierarchy":[
        "tgn:2341041",
        "tgn:1000001",
        "tgn:7012149",
        "tgn:2001971",
        "tgn:7007826",
        "tgn:7029392"
    ],
    "tgn:id":2341041,
    "tgn:name":"Friendship",
    "tgn:placetype":[
        "aat:300008347"
    ]
},
  "bbox": [],
  "geometry": {"coordinates":[-102.0167,32.6167],"type":"Point"}
}