<<<<<<< HEAD
{
  "id": 2258620,
  "type": "Feature",
  "properties": {
    "tgn:hierarchy":[
        "tgn:2258620",
        "tgn:1000001",
        "tgn:2001418",
        "tgn:7012149",
        "tgn:7007526",
        "tgn:7029392"
    ],
    "tgn:id":2258620,
    "tgn:name":"Cottonwood Basin Spring",
    "tgn:placetype":[
        "aat:300008697"
    ]
},
  "bbox": [],
  "geometry": {"coordinates":[-117.4167,38.6667],"type":"Point"}
}
=======
{"geometry":{"type":"Point","coordinates":[-117.416700,38.666700]},"type":"Feature","properties":{"hierarchy":["tgn:2258620","tgn:1000001","tgn:2001418","tgn:7012149","tgn:7007526","tgn:7029392"],"placetype":["aat:300008697"],"id":2258620,"name:xx":"Cottonwood Basin Spring"}}
>>>>>>> 03f74aca74312dbeaf24d7e61306dd6a786dc3d0
