{
  "id": 2258620,
  "type": "Feature",
  "properties": {
    "tgn:hierarchy":[
        "tgn:2258620",
        "tgn:1000001",
        "tgn:2001418",
        "tgn:7012149",
        "tgn:7007526",
        "tgn:7029392"
    ],
    "tgn:id":2258620,
    "tgn:name":"Cottonwood Basin Spring",
    "tgn:placetype":[
        "aat:300008697"
    ]
},
  "bbox": [],
  "geometry": {"coordinates":[-117.4167,38.6667],"type":"Point"}
}