{
  "id": 1100290,
  "type": "Feature",
  "properties": {
    "tgn:hierarchy":[
        "tgn:1100290",
        "tgn:1000003",
        "tgn:7003677",
        "tgn:7000084",
        "tgn:7029392"
    ],
    "tgn:id":1100290,
    "tgn:name":"Hohenlimburg, Schloss",
    "tgn:placetype":[
        "aat:300006891"
    ]
},
  "bbox": [],
  "geometry": {"coordinates":[7.5667,51.35],"type":"Point"}
}