{
  "id": 2209697,
  "type": "Feature",
  "properties": {
    "tgn:hierarchy":[
        "tgn:2209697",
        "tgn:1000001",
        "tgn:7012149",
        "tgn:2002113",
        "tgn:7007827",
        "tgn:7029392"
    ],
    "tgn:id":2209697,
    "tgn:name":"Burro Bar",
    "tgn:placetype":[
        "aat:300132348"
    ]
},
  "bbox": [],
  "geometry": {"coordinates":[-110.7333,37.45],"type":"Point"}
}