{
  "id": 1086371,
  "type": "Feature",
  "properties": {
    "tgn:hierarchy":[
        "tgn:1086371",
        "tgn:1001045",
        "tgn:1000004",
        "tgn:7018454",
        "tgn:1000144",
        "tgn:7029392"
    ],
    "tgn:id":1086371,
    "tgn:name":"Hacihamza",
    "tgn:placetype":[
        "aat:300008347"
    ]
},
  "bbox": [],
  "geometry": {"coordinates":[34.4667,41.0833],"type":"Point"}
}