{
  "id": 2482342,
  "type": "Feature",
  "properties": {
    "tgn:hierarchy":[
        "tgn:2482342",
        "tgn:1000001",
        "tgn:7012149",
        "tgn:7007709",
        "tgn:7029392"
    ],
    "tgn:id":2482342,
    "tgn:name":"Langs Mill Run",
    "tgn:placetype":[
        "aat:300008699"
    ]
},
  "bbox": [],
  "geometry": {"coordinates":[-77.6667,35.6833],"type":"Point"}
}