{
  "id": 7512825,
  "type": "Feature",
  "properties": {
    "tgn:hierarchy":[
        "tgn:7512825",
        "tgn:1009227",
        "tgn:1000226",
        "tgn:7016822",
        "tgn:1000006",
        "tgn:7029392"
    ],
    "tgn:id":7512825,
    "tgn:name:en":"Helena Falls",
    "tgn:placetype":[
        "aat:300008736"
    ]
},
  "bbox": [],
  "geometry": {"coordinates":[167.166667,-45.466667],"type":"Point"}
}