{
  "id": 2237539,
  "type": "Feature",
  "properties": {
    "tgn:hierarchy":[
        "tgn:2237539",
        "tgn:1000001",
        "tgn:7012149",
        "tgn:7007157",
        "tgn:1003046",
        "tgn:7029392"
    ],
    "tgn:id":2237539,
    "tgn:name":"China Peak",
    "tgn:placetype":[
        "aat:300008798"
    ]
},
  "bbox": [],
  "geometry": {"coordinates":[-122.1833,38.85],"type":"Point"}
}