{
  "id": 2566448,
  "type": "Feature",
  "properties": {
    "tgn:hierarchy":[
        "tgn:2566448",
        "tgn:1000001",
        "tgn:7012149",
        "tgn:7007157",
        "tgn:1002867",
        "tgn:7029392"
    ],
    "tgn:id":2566448,
    "tgn:name":"Palos Colorados Creek",
    "tgn:placetype":[
        "aat:300008706"
    ]
},
  "bbox": [],
  "geometry": {"coordinates":[-120.3167,34.5667],"type":"Point"}
}