{
  "id": 7359800,
  "type": "Feature",
  "properties": {
    "tgn:hierarchy":[
        "tgn:7359800",
        "tgn:7005581",
        "tgn:1000001",
        "tgn:7005560",
        "tgn:7029392"
    ],
    "tgn:id":7359800,
    "tgn:name":"Concha, Cerro de la",
    "tgn:placetype":[
        "aat:300008795"
    ]
},
  "bbox": [],
  "geometry": {"coordinates":[-107.916667,29.183333],"type":"Point"}
}