{
  "id": 2679210,
  "type": "Feature",
  "properties": {
    "tgn:hierarchy":[
        "tgn:2679210",
        "tgn:1000001",
        "tgn:1002276",
        "tgn:7012149",
        "tgn:7007708",
        "tgn:7029392"
    ],
    "tgn:id":2679210,
    "tgn:name":"South Fork Lewis And Clark River",
    "tgn:placetype":[
        "aat:300008707"
    ]
},
  "bbox": [],
  "geometry": {"coordinates":[-123.7833,45.95],"type":"Point"}
}