<<<<<<< HEAD
{
  "id": 7471545,
  "type": "Feature",
  "properties": {
    "tgn:hierarchy":[
        "tgn:7471545",
        "tgn:1000004",
        "tgn:1000454",
        "tgn:1000141",
        "tgn:7029392"
    ],
    "tgn:id":7471545,
    "tgn:name":"Fansheqian",
    "tgn:placetype":[
        "aat:300008347"
    ]
},
  "bbox": [],
  "geometry": {"coordinates":[121.475939,25.236123],"type":"Point"}
}
=======
{"geometry":{"type":"Point","coordinates":[121.475939,25.236123]},"type":"Feature","properties":{"hierarchy":["tgn:7471545","tgn:1000004","tgn:1000454","tgn:1000141","tgn:7029392"],"placetype":["aat:300008347"],"id":7471545,"name:xx":"Fansheqian"}}
>>>>>>> 03f74aca74312dbeaf24d7e61306dd6a786dc3d0
