{
  "id": 1079773,
  "type": "Feature",
  "properties": {
    "tgn:hierarchy":[
        "tgn:1079773",
        "tgn:1000980",
        "tgn:1000004",
        "tgn:7000894",
        "tgn:1000120",
        "tgn:7029392"
    ],
    "tgn:id":1079773,
    "tgn:name":"Akabori",
    "tgn:placetype":[
        "aat:300008347"
    ]
},
  "bbox": [],
  "geometry": {"coordinates":[139.2333,36.3667],"type":"Point"}
}