{
  "id": 7239906,
  "type": "Feature",
  "properties": {
    "tgn:hierarchy":[
        "tgn:7239906",
        "tgn:7018239",
        "tgn:1000003",
        "tgn:1000063",
        "tgn:7018236",
        "tgn:7029392"
    ],
    "tgn:id":7239906,
    "tgn:name":"Glabbeek-Zuurbemde",
    "tgn:placetype":[
        "aat:300008347"
    ]
},
  "bbox": [],
  "geometry": {"coordinates":[4.944425,50.873481],"type":"Point"}
}