{
  "id": 7503206,
  "type": "Feature",
  "properties": {
    "tgn:hierarchy":[
        "tgn:7503206",
        "tgn:7001010",
        "tgn:1000004",
        "tgn:1000141",
        "tgn:7029392"
    ],
    "tgn:id":7503206,
    "tgn:name":"Funan Qiao",
    "tgn:placetype":[
        "aat:300007836"
    ]
},
  "bbox": [],
  "geometry": {"coordinates":[121.235,23.138611],"type":"Point"}
}