<<<<<<< HEAD
{
  "id": 7360922,
  "type": "Feature",
  "properties": {
    "tgn:hierarchy":[
        "tgn:7360922",
        "tgn:7005581",
        "tgn:1000001",
        "tgn:7005560",
        "tgn:7029392"
    ],
    "tgn:id":7360922,
    "tgn:name":"Rancho El Negro",
    "tgn:placetype":[
        "aat:300000241"
    ]
},
  "bbox": [],
  "geometry": {"coordinates":[-108.433333,29.566667],"type":"Point"}
}
=======
{"geometry":{"type":"Point","coordinates":[-108.433333,29.566667]},"type":"Feature","properties":{"hierarchy":["tgn:7360922","tgn:7005581","tgn:1000001","tgn:7005560","tgn:7029392"],"placetype":["aat:300000241"],"id":7360922,"name:xx":"Rancho El Negro"}}
>>>>>>> 03f74aca74312dbeaf24d7e61306dd6a786dc3d0
