{
  "id": 1046170,
  "type": "Feature",
  "properties": {
    "tgn:hierarchy":[
        "tgn:1046170",
        "tgn:1000003",
        "tgn:7003122",
        "tgn:1001737",
        "tgn:1000080",
        "tgn:7029392"
    ],
    "tgn:id":1046170,
    "tgn:name":"Pozzallo",
    "tgn:placetype":[
        "aat:300008347"
    ]
},
  "bbox": [],
  "geometry": {"coordinates":[14.85,36.716667],"type":"Point"}
}