{
  "id": 2301361,
  "type": "Feature",
  "properties": {
    "tgn:hierarchy":[
        "tgn:2301361",
        "tgn:1000001",
        "tgn:7012149",
        "tgn:2001290",
        "tgn:7007524",
        "tgn:7029392"
    ],
    "tgn:id":2301361,
    "tgn:name":"Dunn Creek",
    "tgn:placetype":[
        "aat:300008706"
    ]
},
  "bbox": [],
  "geometry": {"coordinates":[-114.9833,47.0333],"type":"Point"}
}