{
  "id": 2220144,
  "type": "Feature",
  "properties": {
    "tgn:hierarchy":[
        "tgn:2220144",
        "tgn:1000001",
        "tgn:7012149",
        "tgn:2002326",
        "tgn:7007922",
        "tgn:7029392"
    ],
    "tgn:id":2220144,
    "tgn:name":"Canyon Park Creek",
    "tgn:placetype":[
        "aat:300008706"
    ]
},
  "bbox": [],
  "geometry": {"coordinates":[-90.0333,42.9667],"type":"Point"}
}