{
  "id": 7317677,
  "type": "Feature",
  "properties": {
    "tgn:hierarchy":[
        "tgn:7317677",
        "tgn:7016598",
        "tgn:1000049",
        "tgn:1000002",
        "tgn:7029392"
    ],
    "tgn:id":7317677,
    "tgn:name":"Colupito, Cerro de",
    "tgn:placetype":[
        "aat:300008795"
    ]
},
  "bbox": [],
  "geometry": {"coordinates":[-69.983333,-22.35],"type":"Point"}
}