{
  "id": 7424484,
  "type": "Feature",
  "properties": {
    "tgn:hierarchy":[
        "tgn:7424484",
        "tgn:1000001",
        "tgn:1001960",
        "tgn:7005560",
        "tgn:7029392"
    ],
    "tgn:id":7424484,
    "tgn:name":"Bella Vista",
    "tgn:placetype":[
        "aat:300008347"
    ]
},
  "bbox": [],
  "geometry": {"coordinates":[-111.783333,29.116667],"type":"Point"}
}