{
  "id": 2138555,
  "type": "Feature",
  "properties": {
    "tgn:hierarchy":[
        "tgn:2138555",
        "tgn:1000001",
        "tgn:7012149",
        "tgn:2000741",
        "tgn:7007254",
        "tgn:7029392"
    ],
    "tgn:id":2138555,
    "tgn:name":"Ash Creek",
    "tgn:placetype":[
        "aat:300008706"
    ]
},
  "bbox": [],
  "geometry": {"coordinates":[-99.4333,39.5167],"type":"Point"}
}