{
  "id": 7015729,
  "type": "Feature",
  "properties": {
    "tgn:hierarchy":[
        "tgn:7015729",
        "tgn:1000001",
        "tgn:7012149",
        "tgn:1002441",
        "tgn:7007706",
        "tgn:7029392"
    ],
    "tgn:id":7015729,
    "tgn:name":"Greenhills",
    "tgn:placetype":[
        "aat:300008347"
    ]
},
  "bbox": [],
  "geometry": {"coordinates":[-84.5167,39.2667],"type":"Point"}
}