{
  "id": 2069202,
  "type": "Feature",
  "properties": {
    "tgn:hierarchy":[
        "tgn:2069202",
        "tgn:1000001",
        "tgn:1002206",
        "tgn:7012149",
        "tgn:7007568",
        "tgn:7029392"
    ],
    "tgn:id":2069202,
    "tgn:name":"Fivemile Point",
    "tgn:placetype":[
        "aat:300008347"
    ]
},
  "bbox": [],
  "geometry": {"coordinates":[-75.8167,42.0833],"type":"Point"}
}