{
  "id": 2779546,
  "type": "Feature",
  "properties": {
    "tgn:hierarchy":[
        "tgn:2779546",
        "tgn:1000001",
        "tgn:7012149",
        "tgn:2000960",
        "tgn:7007520",
        "tgn:7029392"
    ],
    "tgn:id":2779546,
    "tgn:name":"Wolf Mountain",
    "tgn:placetype":[
        "aat:300008798"
    ]
},
  "bbox": [],
  "geometry": {"coordinates":[-89.7667,46.4333],"type":"Point"}
}