<<<<<<< HEAD
{
  "id": 7356960,
  "type": "Feature",
  "properties": {
    "tgn:hierarchy":[
        "tgn:7356960",
        "tgn:1000001",
        "tgn:1001960",
        "tgn:7005560",
        "tgn:7029392"
    ],
    "tgn:id":7356960,
    "tgn:name":"Chaerababi, Sierra",
    "tgn:placetype":[
        "aat:300008795"
    ]
},
  "bbox": [],
  "geometry": {"coordinates":[-110.466667,30.0],"type":"Point"}
}
=======
{"geometry":{"type":"Point","coordinates":[-110.466667,30.000000]},"type":"Feature","properties":{"hierarchy":["tgn:7356960","tgn:1000001","tgn:1001960","tgn:7005560","tgn:7029392"],"placetype":["aat:300008795"],"id":7356960,"name:xx":"Chaerababi, Sierra"}}
>>>>>>> 03f74aca74312dbeaf24d7e61306dd6a786dc3d0
