{
  "id": 2297253,
  "type": "Feature",
  "properties": {
    "tgn:hierarchy":[
        "tgn:2297253",
        "tgn:1000001",
        "tgn:7012149",
        "tgn:2000488",
        "tgn:7007250",
        "tgn:7029392"
    ],
    "tgn:id":2297253,
    "tgn:name":"Dry Creek Reservoir Number Seven",
    "tgn:placetype":[
        "aat:300006191"
    ]
},
  "bbox": [],
  "geometry": {"coordinates":[-116.3333,42.4833],"type":"Point"}
}