{
  "id": 7178629,
  "type": "Feature",
  "properties": {
    "tgn:hierarchy":[
        "tgn:7178629",
        "tgn:7000096",
        "tgn:1000003",
        "tgn:7000084",
        "tgn:7029392"
    ],
    "tgn:id":7178629,
    "tgn:name":"Gory",
    "tgn:placetype":[
        "aat:300008347"
    ]
},
  "bbox": [],
  "geometry": {"coordinates":[14.233333,51.816667],"type":"Point"}
}