{
  "id": 7294586,
  "type": "Feature",
  "properties": {
    "tgn:hierarchy":[
        "tgn:7294586",
        "tgn:7002844",
        "tgn:7030216",
        "tgn:1000003",
        "tgn:1000095",
        "tgn:7029392"
    ],
    "tgn:id":7294586,
    "tgn:name":"Vallmoll, Torrent de",
    "tgn:placetype":[
        "aat:300008699"
    ]
},
  "bbox": [],
  "geometry": {"coordinates":[1.23062,41.227337],"type":"Point"}
}