{
  "id": 1085633,
  "type": "Feature",
  "properties": {
    "tgn:hierarchy":[
        "tgn:1085633",
        "tgn:7005193",
        "tgn:1000004",
        "tgn:7000974",
        "tgn:1000142",
        "tgn:7029392"
    ],
    "tgn:id":1085633,
    "tgn:name":"Phibun Mangsahan",
    "tgn:placetype":[
        "aat:300008347"
    ]
},
  "bbox": [],
  "geometry": {"coordinates":[105.2333,15.2333],"type":"Point"}
}