{
  "id": 2570157,
  "type": "Feature",
  "properties": {
    "tgn:hierarchy":[
        "tgn:2570157",
        "tgn:1000001",
        "tgn:7012149",
        "tgn:7007825",
        "tgn:7029392"
    ],
    "tgn:id":2570157,
    "tgn:name":"Passenger Creek",
    "tgn:placetype":[
        "aat:300008706"
    ]
},
  "bbox": [],
  "geometry": {"coordinates":[-87.1333,36.4333],"type":"Point"}
}