<<<<<<< HEAD
{
  "id": 7175084,
  "type": "Feature",
  "properties": {
    "tgn:hierarchy":[
        "tgn:7175084",
        "tgn:7003692",
        "tgn:1000003",
        "tgn:7000084",
        "tgn:7029392"
    ],
    "tgn:id":7175084,
    "tgn:name":"Grimmersbach",
    "tgn:placetype":[
        "aat:300000206"
    ]
},
  "bbox": [],
  "geometry": {"coordinates":[8.1,48.5],"type":"Point"}
}
=======
{"geometry":{"type":"Point","coordinates":[8.100000,48.500000]},"type":"Feature","properties":{"hierarchy":["tgn:7175084","tgn:7003692","tgn:1000003","tgn:7000084","tgn:7029392"],"placetype":["aat:300000206"],"id":7175084,"name:xx":"Grimmersbach"}}
>>>>>>> 03f74aca74312dbeaf24d7e61306dd6a786dc3d0
