{
  "id": 1056170,
  "type": "Feature",
  "properties": {
    "tgn:hierarchy":[
        "tgn:1056170",
        "tgn:1000004",
        "tgn:1003398",
        "tgn:7018214",
        "tgn:7002435",
        "tgn:7029392"
    ],
    "tgn:id":1056170,
    "tgn:name":"Kuvandyk",
    "tgn:placetype":[
        "aat:300008347"
    ]
},
  "bbox": [],
  "geometry": {"coordinates":[57.4167,51.4833],"type":"Point"}
}