{
  "id": 7557044,
  "type": "Feature",
  "properties": {
    "tgn:hierarchy":[
        "tgn:7557044",
        "tgn:1000004",
        "tgn:7000198",
        "tgn:7016788",
        "tgn:7029392"
    ],
    "tgn:id":7557044,
    "tgn:name:en":"Seriska",
    "tgn:placetype":[
        "aat:300008347"
    ]
},
  "bbox": [],
  "geometry": {"coordinates":[76.371017,27.392578],"type":"Point"}
}