<<<<<<< HEAD
{
  "id": 2154749,
  "type": "Feature",
  "properties": {
    "tgn:hierarchy":[
        "tgn:2154749",
        "tgn:1000001",
        "tgn:7012149",
        "tgn:2002379",
        "tgn:7007923",
        "tgn:7029392"
    ],
    "tgn:id":2154749,
    "tgn:name":"Bear Gulch",
    "tgn:placetype":[
        "aat:300008761"
    ]
},
  "bbox": [],
  "geometry": {"coordinates":[-109.7333,44.3667],"type":"Point"}
}
=======
{"geometry":{"type":"Point","coordinates":[-109.733300,44.366700]},"type":"Feature","properties":{"hierarchy":["tgn:2154749","tgn:1000001","tgn:7012149","tgn:2002379","tgn:7007923","tgn:7029392"],"placetype":["aat:300008761"],"id":2154749,"name:xx":"Bear Gulch"}}
>>>>>>> 03f74aca74312dbeaf24d7e61306dd6a786dc3d0
