{
  "id": 2506055,
  "type": "Feature",
  "properties": {
    "tgn:hierarchy":[
        "tgn:2506055",
        "tgn:7006450",
        "tgn:1000001",
        "tgn:7019698",
        "tgn:7012149",
        "tgn:7029392"
    ],
    "tgn:id":2506055,
    "tgn:name":"Meridian Lake",
    "tgn:placetype":[
        "aat:300008680"
    ]
},
  "bbox": [],
  "geometry": {"coordinates":[-149.35,60.2833],"type":"Point"}
}