{
  "id": 2750721,
  "type": "Feature",
  "properties": {
    "tgn:hierarchy":[
        "tgn:2750721",
        "tgn:1000001",
        "tgn:7012149",
        "tgn:1002570",
        "tgn:7007706",
        "tgn:7029392"
    ],
    "tgn:id":2750721,
    "tgn:name":"Ward Brook",
    "tgn:placetype":[
        "aat:300008699"
    ]
},
  "bbox": [],
  "geometry": {"coordinates":[-81.3667,41.6333],"type":"Point"}
}