{
  "id": 2288898,
  "type": "Feature",
  "properties": {
    "tgn:hierarchy":[
        "tgn:2288898",
        "tgn:1000001",
        "tgn:7012149",
        "tgn:2001197",
        "tgn:7007523",
        "tgn:7029392"
    ],
    "tgn:id":2288898,
    "tgn:name":"Ditch Number 80",
    "tgn:placetype":[
        "aat:300006075"
    ]
},
  "bbox": [],
  "geometry": {"coordinates":[-90.0833,36.0333],"type":"Point"}
}