{
  "id": 7205798,
  "type": "Feature",
  "properties": {
    "tgn:hierarchy":[
        "tgn:7205798",
        "tgn:1000003",
        "tgn:7000094",
        "tgn:7000084",
        "tgn:7029392"
    ],
    "tgn:id":7205798,
    "tgn:name":"Buggow",
    "tgn:placetype":[
        "aat:300008347"
    ]
},
  "bbox": [],
  "geometry": {"coordinates":[13.733333,53.95],"type":"Point"}
}