<<<<<<< HEAD
{
  "id": 7175025,
  "type": "Feature",
  "properties": {
    "tgn:hierarchy":[
        "tgn:7175025",
        "tgn:7003669",
        "tgn:1000003",
        "tgn:7000084",
        "tgn:7029392"
    ],
    "tgn:id":7175025,
    "tgn:name":"Gro\u00dfer Forst",
    "tgn:placetype":[
        "aat:300008863"
    ]
},
  "bbox": [],
  "geometry": {"coordinates":[10.466667,49.716667],"type":"Point"}
}
=======
{"geometry":{"type":"Point","coordinates":[10.466667,49.716667]},"type":"Feature","properties":{"hierarchy":["tgn:7175025","tgn:7003669","tgn:1000003","tgn:7000084","tgn:7029392"],"placetype":["aat:300008863"],"id":7175025,"name:xx":"Gro\u00dfer Forst"}}
>>>>>>> 03f74aca74312dbeaf24d7e61306dd6a786dc3d0
