<<<<<<< HEAD
{
  "id": 7477135,
  "type": "Feature",
  "properties": {
    "tgn:hierarchy":[
        "tgn:7477135",
        "tgn:1000004",
        "tgn:7001013",
        "tgn:1000141",
        "tgn:7029392"
    ],
    "tgn:id":7477135,
    "tgn:name":"Chencuo Qiao",
    "tgn:placetype":[
        "aat:300007836"
    ]
},
  "bbox": [],
  "geometry": {"coordinates":[121.185911,25.033871],"type":"Point"}
}
=======
{"geometry":{"type":"Point","coordinates":[121.185911,25.033871]},"type":"Feature","properties":{"hierarchy":["tgn:7477135","tgn:1000004","tgn:7001013","tgn:1000141","tgn:7029392"],"placetype":["aat:300007836"],"id":7477135,"name:xx":"Chencuo Qiao"}}
>>>>>>> 03f74aca74312dbeaf24d7e61306dd6a786dc3d0
