<<<<<<< HEAD
{
  "id": 7354585,
  "type": "Feature",
  "properties": {
    "tgn:hierarchy":[
        "tgn:7354585",
        "tgn:1001835",
        "tgn:1000001",
        "tgn:7005560",
        "tgn:7029392"
    ],
    "tgn:id":7354585,
    "tgn:name":"Rancho Cancio",
    "tgn:placetype":[
        "aat:300000241"
    ]
},
  "bbox": [],
  "geometry": {"coordinates":[-116.583333,32.3],"type":"Point"}
}
=======
{"geometry":{"type":"Point","coordinates":[-116.583333,32.300000]},"type":"Feature","properties":{"hierarchy":["tgn:7354585","tgn:1001835","tgn:1000001","tgn:7005560","tgn:7029392"],"placetype":["aat:300000241"],"id":7354585,"name:xx":"Rancho Cancio"}}
>>>>>>> 03f74aca74312dbeaf24d7e61306dd6a786dc3d0
