{
  "id": 7195326,
  "type": "Feature",
  "properties": {
    "tgn:hierarchy":[
        "tgn:7195326",
        "tgn:1000003",
        "tgn:7003678",
        "tgn:7000084",
        "tgn:7029392"
    ],
    "tgn:id":7195326,
    "tgn:name":"Dorheim",
    "tgn:placetype":[
        "aat:300008347"
    ]
},
  "bbox": [],
  "geometry": {"coordinates":[8.783333,50.35],"type":"Point"}
}