{
  "id": 7316033,
  "type": "Feature",
  "properties": {
    "tgn:hierarchy":[
        "tgn:7316033",
        "tgn:1001702",
        "tgn:1000049",
        "tgn:1000002",
        "tgn:7029392"
    ],
    "tgn:id":7316033,
    "tgn:name":"Cascada, Punta",
    "tgn:placetype":[
        "aat:300386846"
    ]
},
  "bbox": [],
  "geometry": {"coordinates":[-72.383333,-53.066667],"type":"Point"}
}