{
  "id": 2283010,
  "type": "Feature",
  "properties": {
    "tgn:hierarchy":[
        "tgn:2283010",
        "tgn:1000001",
        "tgn:7012149",
        "tgn:2001981",
        "tgn:7007826",
        "tgn:7029392"
    ],
    "tgn:id":2283010,
    "tgn:name":"Del Monte Lateral",
    "tgn:placetype":[
        "aat:300006075"
    ]
},
  "bbox": [],
  "geometry": {"coordinates":[-106.2667,31.5833],"type":"Point"}
}