{
  "id": 2318274,
  "type": "Feature",
  "properties": {
    "tgn:hierarchy":[
        "tgn:2318274",
        "tgn:1000001",
        "tgn:7016172",
        "tgn:7012149",
        "tgn:2000141",
        "tgn:7029392"
    ],
    "tgn:id":2318274,
    "tgn:name":"Enyart Lake",
    "tgn:placetype":[
        "aat:300006191"
    ]
},
  "bbox": [],
  "geometry": {"coordinates":[-93.7167,33.0333],"type":"Point"}
}