<<<<<<< HEAD
{
  "id": 2768928,
  "type": "Feature",
  "properties": {
    "tgn:hierarchy":[
        "tgn:2768928",
        "tgn:1000001",
        "tgn:1002666",
        "tgn:7012149",
        "tgn:7007565",
        "tgn:7029392"
    ],
    "tgn:id":2768928,
    "tgn:name":"Whitney Pond",
    "tgn:placetype":[
        "aat:300008680"
    ]
},
  "bbox": [],
  "geometry": {"coordinates":[-74.4,40.4667],"type":"Point"}
}
=======
{"geometry":{"type":"Point","coordinates":[-74.400000,40.466700]},"type":"Feature","properties":{"hierarchy":["tgn:2768928","tgn:1000001","tgn:1002666","tgn:7012149","tgn:7007565","tgn:7029392"],"placetype":["aat:300008680"],"id":2768928,"name:xx":"Whitney Pond"}}
>>>>>>> 03f74aca74312dbeaf24d7e61306dd6a786dc3d0
