<<<<<<< HEAD
{
  "id": 7352654,
  "type": "Feature",
  "properties": {
    "tgn:hierarchy":[
        "tgn:7352654",
        "tgn:1000001",
        "tgn:7005598",
        "tgn:7005560",
        "tgn:7029392"
    ],
    "tgn:id":7352654,
    "tgn:name":"Amaxac",
    "tgn:placetype":[
        "aat:300008347"
    ]
},
  "bbox": [],
  "geometry": {"coordinates":[-98.516667,19.55],"type":"Point"}
}
=======
{"geometry":{"type":"Point","coordinates":[-98.516667,19.550000]},"type":"Feature","properties":{"hierarchy":["tgn:7352654","tgn:1000001","tgn:7005598","tgn:7005560","tgn:7029392"],"placetype":["aat:300008347"],"id":7352654,"name:xx":"Amaxac"}}
>>>>>>> 03f74aca74312dbeaf24d7e61306dd6a786dc3d0
