{
  "id": 2324293,
  "type": "Feature",
  "properties": {
    "tgn:hierarchy":[
        "tgn:2324293",
        "tgn:1000001",
        "tgn:7012149",
        "tgn:2002286",
        "tgn:7013961",
        "tgn:7029392"
    ],
    "tgn:id":2324293,
    "tgn:name":"Federal Ridge",
    "tgn:placetype":[
        "aat:300266640"
    ]
},
  "bbox": [],
  "geometry": {"coordinates":[-81.0833,39.3833],"type":"Point"}
}