{
  "id": 2180607,
  "type": "Feature",
  "properties": {
    "tgn:hierarchy":[
        "tgn:2180607",
        "tgn:1000001",
        "tgn:7012149",
        "tgn:2001713",
        "tgn:7007708",
        "tgn:7029392"
    ],
    "tgn:id":2180607,
    "tgn:name":"Bloody Run Creek",
    "tgn:placetype":[
        "aat:300008706"
    ]
},
  "bbox": [],
  "geometry": {"coordinates":[-123.2333,42.4333],"type":"Point"}
}