{
  "id": 7490218,
  "type": "Feature",
  "properties": {
    "tgn:hierarchy":[
        "tgn:7490218",
        "tgn:1000004",
        "tgn:7467799",
        "tgn:1000141",
        "tgn:7029392"
    ],
    "tgn:id":7490218,
    "tgn:name":"Zhanghua Datong Nongchang",
    "tgn:placetype":[
        "aat:300000206"
    ]
},
  "bbox": [],
  "geometry": {"coordinates":[120.583599,23.818139],"type":"Point"}
}