{
  "id": 2611179,
  "type": "Feature",
  "properties": {
    "tgn:hierarchy":[
        "tgn:2611179",
        "tgn:2000090",
        "tgn:1000001",
        "tgn:7006451",
        "tgn:7012149",
        "tgn:7029392"
    ],
    "tgn:id":2611179,
    "tgn:name":"Red Hole Draw",
    "tgn:placetype":[
        "aat:300008761"
    ]
},
  "bbox": [],
  "geometry": {"coordinates":[-109.3167,33.9333],"type":"Point"}
}