{
  "id": 2330607,
  "type": "Feature",
  "properties": {
    "tgn:hierarchy":[
        "tgn:2330607",
        "tgn:1000001",
        "tgn:7012149",
        "tgn:2002039",
        "tgn:7007826",
        "tgn:7029392"
    ],
    "tgn:id":2330607,
    "tgn:name":"Flat Creek",
    "tgn:placetype":[
        "aat:300008706"
    ]
},
  "bbox": [],
  "geometry": {"coordinates":[-98.85,29.3833],"type":"Point"}
}