{
  "id": 2730832,
  "type": "Feature",
  "properties": {
    "tgn:hierarchy":[
        "tgn:2730832",
        "tgn:1000001",
        "tgn:7012149",
        "tgn:2002009",
        "tgn:7007826",
        "tgn:7029392"
    ],
    "tgn:id":2730832,
    "tgn:name":"Tub Lake",
    "tgn:placetype":[
        "aat:300008680"
    ]
},
  "bbox": [],
  "geometry": {"coordinates":[-94.2167,30.9333],"type":"Point"}
}