<<<<<<< HEAD
{
  "id": 7366518,
  "type": "Feature",
  "properties": {
    "tgn:hierarchy":[
        "tgn:7366518",
        "tgn:1000001",
        "tgn:1001960",
        "tgn:7005560",
        "tgn:7029392"
    ],
    "tgn:id":7366518,
    "tgn:name":"Rancho El Pimiento",
    "tgn:placetype":[
        "aat:300000241"
    ]
},
  "bbox": [],
  "geometry": {"coordinates":[-110.85,30.116667],"type":"Point"}
}
=======
{"geometry":{"type":"Point","coordinates":[-110.850000,30.116667]},"type":"Feature","properties":{"hierarchy":["tgn:7366518","tgn:1000001","tgn:1001960","tgn:7005560","tgn:7029392"],"placetype":["aat:300000241"],"id":7366518,"name:xx":"Rancho El Pimiento"}}
>>>>>>> 03f74aca74312dbeaf24d7e61306dd6a786dc3d0
