{
  "id": 2008187,
  "type": "Feature",
  "properties": {
    "tgn:hierarchy":[
        "tgn:2008187",
        "tgn:1000001",
        "tgn:7016172",
        "tgn:7012149",
        "tgn:2000154",
        "tgn:7029392"
    ],
    "tgn:id":2008187,
    "tgn:name":"Emmet",
    "tgn:placetype":[
        "aat:300008347"
    ]
},
  "bbox": [],
  "geometry": {"coordinates":[-93.4667,33.7167],"type":"Point"}
}