<<<<<<< HEAD
{
  "id": 7367686,
  "type": "Feature",
  "properties": {
    "tgn:hierarchy":[
        "tgn:7367686",
        "tgn:7005581",
        "tgn:1000001",
        "tgn:7005560",
        "tgn:7029392"
    ],
    "tgn:id":7367686,
    "tgn:name":"El Porvenir del Campesino",
    "tgn:placetype":[
        "aat:300008347"
    ]
},
  "bbox": [],
  "geometry": {"coordinates":[-107.75,29.433333],"type":"Point"}
}
=======
{"geometry":{"type":"Point","coordinates":[-107.750000,29.433333]},"type":"Feature","properties":{"hierarchy":["tgn:7367686","tgn:7005581","tgn:1000001","tgn:7005560","tgn:7029392"],"placetype":["aat:300008347"],"id":7367686,"name:xx":"El Porvenir del Campesino"}}
>>>>>>> 03f74aca74312dbeaf24d7e61306dd6a786dc3d0
