<<<<<<< HEAD
{
  "id": 7177942,
  "type": "Feature",
  "properties": {
    "tgn:hierarchy":[
        "tgn:7177942",
        "tgn:1000003",
        "tgn:7003677",
        "tgn:7000084",
        "tgn:7029392"
    ],
    "tgn:id":7177942,
    "tgn:name":"G\u00fcnhoven",
    "tgn:placetype":[
        "aat:300000745"
    ]
},
  "bbox": [],
  "geometry": {"coordinates":[6.383333,51.15],"type":"Point"}
}
=======
{"geometry":{"type":"Point","coordinates":[6.383333,51.150000]},"type":"Feature","properties":{"hierarchy":["tgn:7177942","tgn:1000003","tgn:7003677","tgn:7000084","tgn:7029392"],"placetype":["aat:300000745"],"id":7177942,"name:xx":"G\u00fcnhoven"}}
>>>>>>> 03f74aca74312dbeaf24d7e61306dd6a786dc3d0
