{
  "id": 2116227,
  "type": "Feature",
  "properties": {
    "tgn:hierarchy":[
        "tgn:2116227",
        "tgn:1000001",
        "tgn:1002275",
        "tgn:7012149",
        "tgn:7007920",
        "tgn:7029392"
    ],
    "tgn:id":2116227,
    "tgn:name":"Manor",
    "tgn:placetype":[
        "aat:300008347",
        "aat:300387210"
    ]
},
  "bbox": [],
  "geometry": {"coordinates":[-122.5833,45.75],"type":"Point"}
}