{
  "id": 2574671,
  "type": "Feature",
  "properties": {
    "tgn:hierarchy":[
        "tgn:2574671",
        "tgn:1000001",
        "tgn:7012149",
        "tgn:7019676",
        "tgn:7007566",
        "tgn:7029392"
    ],
    "tgn:id":2574671,
    "tgn:name":"Pe\u00f1a Springs",
    "tgn:placetype":[
        "aat:300008697"
    ]
},
  "bbox": [],
  "geometry": {"coordinates":[-107.5667,35.5333],"type":"Point"}
}