{
  "id": 7236632,
  "type": "Feature",
  "properties": {
    "tgn:hierarchy":[
        "tgn:7236632",
        "tgn:7002690",
        "tgn:7012056",
        "tgn:1000003",
        "tgn:1000074",
        "tgn:7029392"
    ],
    "tgn:id":7236632,
    "tgn:name":"Anisar\u00e1kion",
    "tgn:placetype":[
        "aat:300008347"
    ]
},
  "bbox": [],
  "geometry": {"coordinates":[23.766667,35.333333],"type":"Point"}
}