{
  "id": 2596124,
  "type": "Feature",
  "properties": {
    "tgn:hierarchy":[
        "tgn:2596124",
        "tgn:1000001",
        "tgn:7012149",
        "tgn:1002545",
        "tgn:7007157",
        "tgn:7029392"
    ],
    "tgn:id":2596124,
    "tgn:name":"Pottinger Canyon",
    "tgn:placetype":[
        "aat:300008761"
    ]
},
  "bbox": [],
  "geometry": {"coordinates":[-119.75,35.2667],"type":"Point"}
}