{
  "id": 2592760,
  "type": "Feature",
  "properties": {
    "tgn:hierarchy":[
        "tgn:2592760",
        "tgn:1000001",
        "tgn:7012149",
        "tgn:2002123",
        "tgn:7007827",
        "tgn:7029392"
    ],
    "tgn:id":2592760,
    "tgn:name":"Pope Canyon Spring",
    "tgn:placetype":[
        "aat:300008697"
    ]
},
  "bbox": [],
  "geometry": {"coordinates":[-112.5833,40.5667],"type":"Point"}
}