{
  "id": 2419234,
  "type": "Feature",
  "properties": {
    "tgn:hierarchy":[
        "tgn:2419234",
        "tgn:1000001",
        "tgn:7012149",
        "tgn:2002128",
        "tgn:7007827",
        "tgn:7029392"
    ],
    "tgn:id":2419234,
    "tgn:name":"Jane Lake",
    "tgn:placetype":[
        "aat:300008680"
    ]
},
  "bbox": [],
  "geometry": {"coordinates":[-111.4833,38.1667],"type":"Point"}
}