{
  "id": 7495372,
  "type": "Feature",
  "properties": {
    "tgn:hierarchy":[
        "tgn:7495372",
        "tgn:1000004",
        "tgn:1000454",
        "tgn:1000141",
        "tgn:7029392"
    ],
    "tgn:id":7495372,
    "tgn:name":"Fengming Guoxiao",
    "tgn:placetype":[
        "aat:300006495"
    ]
},
  "bbox": [],
  "geometry": {"coordinates":[121.335846,24.968835],"type":"Point"}
}