{
  "id": 1036802,
  "type": "Feature",
  "properties": {
    "tgn:hierarchy":[
        "tgn:1036802",
        "tgn:1000003",
        "tgn:7000094",
        "tgn:7000084",
        "tgn:7029392"
    ],
    "tgn:id":1036802,
    "tgn:name":"Gorlosen",
    "tgn:placetype":[
        "aat:300008347"
    ]
},
  "bbox": [],
  "geometry": {"coordinates":[11.466667,53.183333],"type":"Point"}
}