{
  "id": 7223261,
  "type": "Feature",
  "properties": {
    "tgn:hierarchy":[
        "tgn:7223261",
        "tgn:7002735",
        "tgn:7017076",
        "tgn:1000003",
        "tgn:1000074",
        "tgn:7029392"
    ],
    "tgn:id":7223261,
    "tgn:name":"Sevet\u00edla",
    "tgn:placetype":[
        "aat:300008795"
    ]
},
  "bbox": [],
  "geometry": {"coordinates":[22.800316,37.2444],"type":"Point"}
}