{
  "id": 2180508,
  "type": "Feature",
  "properties": {
    "tgn:hierarchy":[
        "tgn:2180508",
        "tgn:1000001",
        "tgn:7006451",
        "tgn:2000094",
        "tgn:7012149",
        "tgn:7029392"
    ],
    "tgn:id":2180508,
    "tgn:name":"Bloody Basin Canyon",
    "tgn:placetype":[
        "aat:300008761"
    ]
},
  "bbox": [],
  "geometry": {"coordinates":[-109.95,33.5167],"type":"Point"}
}