{
  "id": 2498590,
  "type": "Feature",
  "properties": {
    "tgn:hierarchy":[
        "tgn:2498590",
        "tgn:1000001",
        "tgn:7012149",
        "tgn:2001524",
        "tgn:7007709",
        "tgn:7029392"
    ],
    "tgn:id":2498590,
    "tgn:name":"McArthur Estates",
    "tgn:placetype":[
        "aat:300008347"
    ]
},
  "bbox": [],
  "geometry": {"coordinates":[-77.4667,34.8333],"type":"Point"}
}