<<<<<<< HEAD
{
  "id": 2158145,
  "type": "Feature",
  "properties": {
    "tgn:hierarchy":[
        "tgn:2158145",
        "tgn:7002659",
        "tgn:1000001",
        "tgn:7012149",
        "tgn:2000054",
        "tgn:7029392"
    ],
    "tgn:id":2158145,
    "tgn:name":"Beaver Pond Branch",
    "tgn:placetype":[
        "aat:300008699"
    ]
},
  "bbox": [],
  "geometry": {"coordinates":[-85.8667,31.8],"type":"Point"}
}
=======
{"geometry":{"type":"Point","coordinates":[-85.866700,31.800000]},"type":"Feature","properties":{"hierarchy":["tgn:2158145","tgn:7002659","tgn:1000001","tgn:7012149","tgn:2000054","tgn:7029392"],"placetype":["aat:300008699"],"id":2158145,"name:xx":"Beaver Pond Branch"}}
>>>>>>> 03f74aca74312dbeaf24d7e61306dd6a786dc3d0
