<<<<<<< HEAD
{
  "id": 7176442,
  "type": "Feature",
  "properties": {
    "tgn:hierarchy":[
        "tgn:7176442",
        "tgn:1000003",
        "tgn:7003687",
        "tgn:7000084",
        "tgn:7029392"
    ],
    "tgn:id":7176442,
    "tgn:name":"Halt-Berg",
    "tgn:placetype":[
        "aat:300008777"
    ]
},
  "bbox": [],
  "geometry": {"coordinates":[11.95,51.633333],"type":"Point"}
}
=======
{"geometry":{"type":"Point","coordinates":[11.950000,51.633333]},"type":"Feature","properties":{"hierarchy":["tgn:7176442","tgn:1000003","tgn:7003687","tgn:7000084","tgn:7029392"],"placetype":["aat:300008777"],"id":7176442,"name:xx":"Halt-Berg"}}
>>>>>>> 03f74aca74312dbeaf24d7e61306dd6a786dc3d0
