{
  "id": 2279584,
  "type": "Feature",
  "properties": {
    "tgn:hierarchy":[
        "tgn:2279584",
        "tgn:1000001",
        "tgn:2001178",
        "tgn:7012149",
        "tgn:7007523",
        "tgn:7029392"
    ],
    "tgn:id":2279584,
    "tgn:name":"Deadman Ridge",
    "tgn:placetype":[
        "aat:300266640"
    ]
},
  "bbox": [],
  "geometry": {"coordinates":[-92.8667,38.1167],"type":"Point"}
}