{
  "id": 7358950,
  "type": "Feature",
  "properties": {
    "tgn:hierarchy":[
        "tgn:7358950",
        "tgn:1000001",
        "tgn:7005595",
        "tgn:7005560",
        "tgn:7029392"
    ],
    "tgn:id":7358950,
    "tgn:name":"Dimas",
    "tgn:placetype":[
        "aat:300007783"
    ]
},
  "bbox": [],
  "geometry": {"coordinates":[-106.783333,23.716667],"type":"Point"}
}