{
  "id": 2307660,
  "type": "Feature",
  "properties": {
    "tgn:hierarchy":[
        "tgn:2307660",
        "tgn:1000001",
        "tgn:2002368",
        "tgn:7012149",
        "tgn:7007923",
        "tgn:7029392"
    ],
    "tgn:id":2307660,
    "tgn:name":"East Fork Thomas Creek",
    "tgn:placetype":[
        "aat:300008706"
    ]
},
  "bbox": [],
  "geometry": {"coordinates":[-106.6167,42.0833],"type":"Point"}
}