{
  "id": 2681195,
  "type": "Feature",
  "properties": {
    "tgn:hierarchy":[
        "tgn:2681195",
        "tgn:1000001",
        "tgn:7012149",
        "tgn:2000219",
        "tgn:7007158",
        "tgn:7029392"
    ],
    "tgn:id":2681195,
    "tgn:name":"South Muddy Creek",
    "tgn:placetype":[
        "aat:300008706"
    ]
},
  "bbox": [],
  "geometry": {"coordinates":[-105.45,37.8667],"type":"Point"}
}