{
  "id": 7309662,
  "type": "Feature",
  "properties": {
    "tgn:hierarchy":[
        "tgn:7309662",
        "tgn:7002464",
        "tgn:1000049",
        "tgn:1000002",
        "tgn:7029392"
    ],
    "tgn:id":7309662,
    "tgn:name":"Oyarbide, Cerro",
    "tgn:placetype":[
        "aat:300008795"
    ]
},
  "bbox": [],
  "geometry": {"coordinates":[-70.083333,-20.466667],"type":"Point"}
}