{
  "id": 2527177,
  "type": "Feature",
  "properties": {
    "tgn:hierarchy":[
        "tgn:2527177",
        "tgn:1000001",
        "tgn:1002903",
        "tgn:7012149",
        "tgn:7007565",
        "tgn:7029392"
    ],
    "tgn:id":2527177,
    "tgn:name":"Mount Horeb",
    "tgn:placetype":[
        "aat:300008347"
    ]
},
  "bbox": [],
  "geometry": {"coordinates":[-74.55,40.6167],"type":"Point"}
}