{
  "id": 2637827,
  "type": "Feature",
  "properties": {
    "tgn:hierarchy":[
        "tgn:2637827",
        "tgn:7006450",
        "tgn:1000001",
        "tgn:7012149",
        "tgn:2000082",
        "tgn:7029392"
    ],
    "tgn:id":2637827,
    "tgn:name":"Saks Creek",
    "tgn:placetype":[
        "aat:300008706"
    ]
},
  "bbox": [],
  "geometry": {"coordinates":[-130.95,55.95],"type":"Point"}
}