{
  "id": 2604609,
  "type": "Feature",
  "properties": {
    "tgn:hierarchy":[
        "tgn:2604609",
        "tgn:1000001",
        "tgn:7012149",
        "tgn:1002379",
        "tgn:7007826",
        "tgn:7029392"
    ],
    "tgn:id":2604609,
    "tgn:name":"Rabbs Bayou",
    "tgn:placetype":[
        "aat:300008699"
    ]
},
  "bbox": [],
  "geometry": {"coordinates":[-95.7667,29.5667],"type":"Point"}
}