<<<<<<< HEAD
{
  "id": 7359231,
  "type": "Feature",
  "properties": {
    "tgn:hierarchy":[
        "tgn:7359231",
        "tgn:1000001",
        "tgn:7005599",
        "tgn:7005560",
        "tgn:7029392"
    ],
    "tgn:id":7359231,
    "tgn:name":"Dobladero",
    "tgn:placetype":[
        "aat:300007783"
    ]
},
  "bbox": [],
  "geometry": {"coordinates":[-95.766667,18.1],"type":"Point"}
}
=======
{"geometry":{"type":"Point","coordinates":[-95.766667,18.100000]},"type":"Feature","properties":{"hierarchy":["tgn:7359231","tgn:1000001","tgn:7005599","tgn:7005560","tgn:7029392"],"placetype":["aat:300007783"],"id":7359231,"name:xx":"Dobladero"}}
>>>>>>> 03f74aca74312dbeaf24d7e61306dd6a786dc3d0
