{
  "id": 2391742,
  "type": "Feature",
  "properties": {
    "tgn:hierarchy":[
        "tgn:2391742",
        "tgn:1000001",
        "tgn:7012149",
        "tgn:2000928",
        "tgn:7007515",
        "tgn:7029392"
    ],
    "tgn:id":2391742,
    "tgn:name":"Hillside Quarry",
    "tgn:placetype":[
        "aat:300000390"
    ]
},
  "bbox": [],
  "geometry": {"coordinates":[-69.4833,45.2667],"type":"Point"}
}