{
  "id": 7565352,
  "type": "Feature",
  "properties": {
    "tgn:hierarchy":[
        "tgn:7565352",
        "tgn:1000004",
        "tgn:7000198",
        "tgn:1001894",
        "tgn:7029392"
    ],
    "tgn:id":7565352,
    "tgn:name:en":"H\u012br\u0101pur",
    "tgn:placetype":[
        "aat:300008347"
    ]
},
  "bbox": [],
  "geometry": {"coordinates":[79.2495,24.7526],"type":"Point"}
}