{
  "id": 7311343,
  "type": "Feature",
  "properties": {
    "tgn:hierarchy":[
        "tgn:7311343",
        "tgn:1001699",
        "tgn:1000049",
        "tgn:1000002",
        "tgn:7029392"
    ],
    "tgn:id":7311343,
    "tgn:name":"Negra, Roca",
    "tgn:placetype":[
        "aat:300011692"
    ]
},
  "bbox": [],
  "geometry": {"coordinates":[-73.748333,-44.101667],"type":"Point"}
}