{
  "id": 7400687,
  "type": "Feature",
  "properties": {
    "tgn:hierarchy":[
        "tgn:7400687",
        "tgn:1000001",
        "tgn:7005599",
        "tgn:7005560",
        "tgn:7029392"
    ],
    "tgn:id":7400687,
    "tgn:name":"La Camacha",
    "tgn:placetype":[
        "aat:300008347"
    ]
},
  "bbox": [],
  "geometry": {"coordinates":[-96.0625,18.743056],"type":"Point"}
}