{
  "id": 2667906,
  "type": "Feature",
  "properties": {
    "tgn:hierarchy":[
        "tgn:2667906",
        "tgn:1000001",
        "tgn:1002200",
        "tgn:7012149",
        "tgn:7007240",
        "tgn:7029392"
    ],
    "tgn:id":2667906,
    "tgn:name":"Skunk Island",
    "tgn:placetype":[
        "aat:300008791"
    ]
},
  "bbox": [],
  "geometry": {"coordinates":[-80.7167,28.5833],"type":"Point"}
}