{
  "id": 7392311,
  "type": "Feature",
  "properties": {
    "tgn:hierarchy":[
        "tgn:7392311",
        "tgn:1000001",
        "tgn:7005597",
        "tgn:7005560",
        "tgn:7029392"
    ],
    "tgn:id":7392311,
    "tgn:name":"Rancho Los Garc\u00edas",
    "tgn:placetype":[
        "aat:300008347"
    ]
},
  "bbox": [],
  "geometry": {"coordinates":[-99.033333,26.183333],"type":"Point"}
}