{
  "id": 1038679,
  "type": "Feature",
  "properties": {
    "tgn:hierarchy":[
        "tgn:1038679",
        "tgn:1000003",
        "tgn:7003676",
        "tgn:7000084",
        "tgn:7029392"
    ],
    "tgn:id":1038679,
    "tgn:name":"Buchholz in der Nordheide",
    "tgn:placetype":[
        "aat:300008347"
    ]
},
  "bbox": [],
  "geometry": {"coordinates":[9.866667,53.333333],"type":"Point"}
}