{
  "id": 2478850,
  "type": "Feature",
  "properties": {
    "tgn:hierarchy":[
        "tgn:2478850",
        "tgn:1000001",
        "tgn:7012149",
        "tgn:2001457",
        "tgn:7007566",
        "tgn:7029392"
    ],
    "tgn:id":2478850,
    "tgn:name":"Maestas Ridge",
    "tgn:placetype":[
        "aat:300266640"
    ]
},
  "bbox": [],
  "geometry": {"coordinates":[-105.5167,36.2333],"type":"Point"}
}