{
  "id": 2288749,
  "type": "Feature",
  "properties": {
    "tgn:hierarchy":[
        "tgn:2288749",
        "tgn:1000001",
        "tgn:7012149",
        "tgn:2000659",
        "tgn:7007253",
        "tgn:7029392"
    ],
    "tgn:id":2288749,
    "tgn:name":"Ditch Number 187",
    "tgn:placetype":[
        "aat:300006075"
    ]
},
  "bbox": [],
  "geometry": {"coordinates":[-93.5833,42.65],"type":"Point"}
}