{
  "id": 2367220,
  "type": "Feature",
  "properties": {
    "tgn:hierarchy":[
        "tgn:2367220",
        "tgn:1000001",
        "tgn:7012149",
        "tgn:2000910",
        "tgn:7007256",
        "tgn:7029392"
    ],
    "tgn:id":2367220,
    "tgn:name":"Grophes Island",
    "tgn:placetype":[
        "aat:300008791"
    ]
},
  "bbox": [],
  "geometry": {"coordinates":[-92.2167,29.7667],"type":"Point"}
}