<<<<<<< HEAD
{
  "id": 2407281,
  "type": "Feature",
  "properties": {
    "tgn:hierarchy":[
        "tgn:2407281",
        "tgn:1000001",
        "tgn:2001477",
        "tgn:7012149",
        "tgn:7007709",
        "tgn:7029392"
    ],
    "tgn:id":2407281,
    "tgn:name":"Hunting Island",
    "tgn:placetype":[
        "aat:300008791"
    ]
},
  "bbox": [],
  "geometry": {"coordinates":[-77.05,34.6667],"type":"Point"}
}
=======
{"geometry":{"type":"Point","coordinates":[-77.050000,34.666700]},"type":"Feature","properties":{"hierarchy":["tgn:2407281","tgn:1000001","tgn:2001477","tgn:7012149","tgn:7007709","tgn:7029392"],"placetype":["aat:300008791"],"id":2407281,"name:xx":"Hunting Island"}}
>>>>>>> 03f74aca74312dbeaf24d7e61306dd6a786dc3d0
