{
  "id": 2176457,
  "type": "Feature",
  "properties": {
    "tgn:hierarchy":[
        "tgn:2176457",
        "tgn:7006450",
        "tgn:1000001",
        "tgn:7012149",
        "tgn:2000089",
        "tgn:7029392"
    ],
    "tgn:id":2176457,
    "tgn:name":"Black Lake",
    "tgn:placetype":[
        "aat:300008680"
    ]
},
  "bbox": [],
  "geometry": {"coordinates":[-156.7833,65.3167],"type":"Point"}
}