{
  "id": 2460527,
  "type": "Feature",
  "properties": {
    "tgn:hierarchy":[
        "tgn:2460527",
        "tgn:1000001",
        "tgn:7012149",
        "tgn:2002024",
        "tgn:7007826",
        "tgn:7029392"
    ],
    "tgn:id":2460527,
    "tgn:name":"Little Sandy Creek",
    "tgn:placetype":[
        "aat:300008706"
    ]
},
  "bbox": [],
  "geometry": {"coordinates":[-95.45,33.6333],"type":"Point"}
}