{
  "id": 2538564,
  "type": "Feature",
  "properties": {
    "tgn:hierarchy":[
        "tgn:2538564",
        "tgn:1000001",
        "tgn:7012149",
        "tgn:2000891",
        "tgn:7007256",
        "tgn:7029392"
    ],
    "tgn:id":2538564,
    "tgn:name":"Nestor Canal",
    "tgn:placetype":[
        "aat:300006075"
    ]
},
  "bbox": [],
  "geometry": {"coordinates":[-89.6833,29.4833],"type":"Point"}
}