{
  "id": 7454669,
  "type": "Feature",
  "properties": {
    "tgn:hierarchy":[
        "tgn:7454669",
        "tgn:7002445",
        "tgn:1000003",
        "tgn:7012077",
        "tgn:7008591",
        "tgn:7029392"
    ],
    "tgn:id":7454669,
    "tgn:name:en":"Chapman Rock",
    "tgn:placetype":[
        "aat:300011692"
    ]
},
  "bbox": [],
  "geometry": {"coordinates":[-4.466667,51.016667],"type":"Point"}
}