{
  "id": 7259944,
  "type": "Feature",
  "properties": {
    "tgn:concordances":{
        "gn:id":"2759120"
    },
    "tgn:hierarchy":[
        "tgn:7259944",
        "tgn:7003619",
        "tgn:1000003",
        "tgn:7016845",
        "tgn:7029392"
    ],
    "tgn:id":7259944,
    "tgn:name:nl":"Berghuizen",
    "tgn:placetype":[
        "aat:300008347"
    ]
},
  "bbox": [],
  "geometry": {"coordinates":[5.516667,51.816667],"type":"Point"}
}