{
  "id": 2161993,
  "type": "Feature",
  "properties": {
    "tgn:hierarchy":[
        "tgn:2161993",
        "tgn:1000001",
        "tgn:7012149",
        "tgn:7007706",
        "tgn:7029392"
    ],
    "tgn:id":2161993,
    "tgn:name":"Bells Run",
    "tgn:placetype":[
        "aat:300008699"
    ]
},
  "bbox": [],
  "geometry": {"coordinates":[-83.7667,39.0833],"type":"Point"}
}