<<<<<<< HEAD
{
  "id": 2259658,
  "type": "Feature",
  "properties": {
    "tgn:hierarchy":[
        "tgn:2259658",
        "tgn:1000001",
        "tgn:2001416",
        "tgn:7012149",
        "tgn:7007526",
        "tgn:7029392"
    ],
    "tgn:id":2259658,
    "tgn:name":"Cougar Canyon",
    "tgn:placetype":[
        "aat:300008761"
    ]
},
  "bbox": [],
  "geometry": {"coordinates":[-114.3333,37.3333],"type":"Point"}
}
=======
{"geometry":{"type":"Point","coordinates":[-114.333300,37.333300]},"type":"Feature","properties":{"hierarchy":["tgn:2259658","tgn:1000001","tgn:2001416","tgn:7012149","tgn:7007526","tgn:7029392"],"placetype":["aat:300008761"],"id":2259658,"name:xx":"Cougar Canyon"}}
>>>>>>> 03f74aca74312dbeaf24d7e61306dd6a786dc3d0
