{
  "id": 2224655,
  "type": "Feature",
  "properties": {
    "tgn:hierarchy":[
        "tgn:2224655",
        "tgn:1000001",
        "tgn:7012149",
        "tgn:1002391",
        "tgn:7007826",
        "tgn:7029392"
    ],
    "tgn:id":2224655,
    "tgn:name":"Cash Branch",
    "tgn:placetype":[
        "aat:300008699"
    ]
},
  "bbox": [],
  "geometry": {"coordinates":[-96.2333,31.5833],"type":"Point"}
}