{
  "id": 1121729,
  "type": "Feature",
  "properties": {
    "tgn:hierarchy":[
        "tgn:1121729",
        "tgn:7003669",
        "tgn:1000003",
        "tgn:7000084",
        "tgn:7029392"
    ],
    "tgn:id":1121729,
    "tgn:name":"Baunach",
    "tgn:placetype":[
        "aat:300008707",
        "aat:300008699"
    ]
},
  "bbox": [],
  "geometry": {"coordinates":[10.85,49.983333],"type":"Point"}
}