{
  "id": 2739926,
  "type": "Feature",
  "properties": {
    "tgn:hierarchy":[
        "tgn:2739926",
        "tgn:1000001",
        "tgn:7012149",
        "tgn:2000231",
        "tgn:7007158",
        "tgn:7029392"
    ],
    "tgn:id":2739926,
    "tgn:name":"Upper Fourmile Lake",
    "tgn:placetype":[
        "aat:300008680"
    ]
},
  "bbox": [],
  "geometry": {"coordinates":[-107.0333,37.4667],"type":"Point"}
}