{
  "id": 7408640,
  "type": "Feature",
  "properties": {
    "tgn:hierarchy":[
        "tgn:7408640",
        "tgn:1000001",
        "tgn:7005590",
        "tgn:7005560",
        "tgn:7029392"
    ],
    "tgn:id":7408640,
    "tgn:name":"Santa Cruz",
    "tgn:placetype":[
        "aat:300008347"
    ]
},
  "bbox": [],
  "geometry": {"coordinates":[-101.533333,19.608333],"type":"Point"}
}