{
  "id": 2207909,
  "type": "Feature",
  "properties": {
    "tgn:hierarchy":[
        "tgn:2207909",
        "tgn:1000001",
        "tgn:7012149",
        "tgn:7007706",
        "tgn:7029392"
    ],
    "tgn:id":2207909,
    "tgn:name":"Burgett Run",
    "tgn:placetype":[
        "aat:300008699"
    ]
},
  "bbox": [],
  "geometry": {"coordinates":[-80.8833,40.5667],"type":"Point"}
}