{
  "id": 7021619,
  "type": "Feature",
  "properties": {
    "tgn:hierarchy":[
        "tgn:7021619",
        "tgn:1000001",
        "tgn:7012149",
        "tgn:1002627",
        "tgn:7007706",
        "tgn:7029392"
    ],
    "tgn:id":7021619,
    "tgn:name":"Kings Lake",
    "tgn:placetype":[
        "aat:300006191"
    ]
},
  "bbox": [],
  "geometry": {"coordinates":[-80.5167,41.0833],"type":"Point"}
}