{
  "id": 1092628,
  "type": "Feature",
  "properties": {
    "tgn:hierarchy":[
        "tgn:1092628",
        "tgn:1001633",
        "tgn:7001242",
        "tgn:1000192",
        "tgn:7029392"
    ],
    "tgn:id":1092628,
    "tgn:name":"Bohin",
    "tgn:placetype":[
        "aat:300008347"
    ]
},
  "bbox": [],
  "geometry": {"coordinates":[51.25,11.75],"type":"Point"}
}