{
  "id": 2675169,
  "type": "Feature",
  "properties": {
    "tgn:hierarchy":[
        "tgn:2675169",
        "tgn:1000001",
        "tgn:7012149",
        "tgn:2002384",
        "tgn:7007923",
        "tgn:7029392"
    ],
    "tgn:id":2675169,
    "tgn:name":"Sohare Creek",
    "tgn:placetype":[
        "aat:300008706"
    ]
},
  "bbox": [],
  "geometry": {"coordinates":[-110.2667,43.6333],"type":"Point"}
}