{
  "id": 1103471,
  "type": "Feature",
  "properties": {
    "tgn:hierarchy":[
        "tgn:1103471",
        "tgn:7004687",
        "tgn:1000006",
        "tgn:7029392"
    ],
    "tgn:id":1103471,
    "tgn:name":"Huvalu Forest",
    "tgn:placetype":[
        "aat:300132451"
    ]
},
  "bbox": [],
  "geometry": {"coordinates":[-169.85,-19.05],"type":"Point"}
}