{
  "id": 7239440,
  "type": "Feature",
  "properties": {
    "tgn:hierarchy":[
        "tgn:7239440",
        "tgn:7003457",
        "tgn:1000003",
        "tgn:1000063",
        "tgn:7018236",
        "tgn:7029392"
    ],
    "tgn:id":7239440,
    "tgn:name":"Gerstebeek",
    "tgn:placetype":[
        "aat:300008699"
    ]
},
  "bbox": [],
  "geometry": {"coordinates":[4.233333,50.933333],"type":"Point"}
}