{
  "id": 7352603,
  "type": "Feature",
  "properties": {
    "tgn:hierarchy":[
        "tgn:7352603",
        "tgn:1000001",
        "tgn:7005591",
        "tgn:7005560",
        "tgn:7029392"
    ],
    "tgn:id":7352603,
    "tgn:name":"Buenavista",
    "tgn:placetype":[
        "aat:300008347"
    ]
},
  "bbox": [],
  "geometry": {"coordinates":[-96.783333,16.733333],"type":"Point"}
}