{
  "id": 7199893,
  "type": "Feature",
  "properties": {
    "tgn:hierarchy":[
        "tgn:7199893",
        "tgn:7003692",
        "tgn:1000003",
        "tgn:7000084",
        "tgn:7029392"
    ],
    "tgn:id":7199893,
    "tgn:name":"Dreiangel",
    "tgn:placetype":[
        "aat:300008347"
    ]
},
  "bbox": [],
  "geometry": {"coordinates":[8.25,48.116667],"type":"Point"}
}