{
  "id": 7584169,
  "type": "Feature",
  "properties": {
    "tgn:hierarchy":[
        "tgn:7584169",
        "tgn:1000004",
        "tgn:7000198",
        "tgn:7016788",
        "tgn:7029392"
    ],
    "tgn:id":7584169,
    "tgn:name:en":"Lohsana Chhota",
    "tgn:placetype":[
        "aat:300008347"
    ]
},
  "bbox": [],
  "geometry": {"coordinates":[75.193604,28.400995],"type":"Point"}
}