{
  "id": 2583752,
  "type": "Feature",
  "properties": {
    "tgn:hierarchy":[
        "tgn:2583752",
        "tgn:1000001",
        "tgn:2002104",
        "tgn:7012149",
        "tgn:7007827",
        "tgn:7029392"
    ],
    "tgn:id":2583752,
    "tgn:name":"Pine Spring Draw",
    "tgn:placetype":[
        "aat:300008761"
    ]
},
  "bbox": [],
  "geometry": {"coordinates":[-110.1667,39.65],"type":"Point"}
}