{
  "id": 2324321,
  "type": "Feature",
  "properties": {
    "tgn:hierarchy":[
        "tgn:2324321",
        "tgn:1000001",
        "tgn:7016172",
        "tgn:7012149",
        "tgn:2000149",
        "tgn:7029392"
    ],
    "tgn:id":2324321,
    "tgn:name":"Fee Hollow",
    "tgn:placetype":[
        "aat:300008761"
    ]
},
  "bbox": [],
  "geometry": {"coordinates":[-92.75,36.3333],"type":"Point"}
}