{
  "id": 7504700,
  "type": "Feature",
  "properties": {
    "tgn:hierarchy":[
        "tgn:7504700",
        "tgn:7000508",
        "tgn:1008380",
        "tgn:1000226",
        "tgn:1000006",
        "tgn:7029392"
    ],
    "tgn:id":7504700,
    "tgn:name:en":"West Bastion Reef",
    "tgn:placetype":[
        "aat:300008808"
    ]
},
  "bbox": [],
  "geometry": {"coordinates":[174.836389,-36.839444],"type":"Point"}
}