{
  "id": 7514838,
  "type": "Feature",
  "properties": {
    "tgn:hierarchy":[
        "tgn:7514838",
        "tgn:1008380",
        "tgn:7520093",
        "tgn:1000226",
        "tgn:1000006",
        "tgn:7029392"
    ],
    "tgn:id":7514838,
    "tgn:name:en":"Curl, Mount",
    "tgn:placetype":[
        "aat:300008795"
    ]
},
  "bbox": [],
  "geometry": {"coordinates":[175.483333,-39.95],"type":"Point"}
}