{
  "id": 2361205,
  "type": "Feature",
  "properties": {
    "tgn:hierarchy":[
        "tgn:2361205",
        "tgn:1000001",
        "tgn:2001746",
        "tgn:7012149",
        "tgn:7007712",
        "tgn:7029392"
    ],
    "tgn:id":2361205,
    "tgn:name":"Gravel Gully",
    "tgn:placetype":[
        "aat:300008761"
    ]
},
  "bbox": [],
  "geometry": {"coordinates":[-79.2167,33.6667],"type":"Point"}
}