{
  "id": 2107944,
  "type": "Feature",
  "properties": {
    "tgn:hierarchy":[
        "tgn:2107944",
        "tgn:1000001",
        "tgn:7012149",
        "tgn:1002691",
        "tgn:7007826",
        "tgn:7029392"
    ],
    "tgn:id":2107944,
    "tgn:name":"Tamina",
    "tgn:placetype":[
        "aat:300008347"
    ]
},
  "bbox": [],
  "geometry": {"coordinates":[-95.4333,30.1667],"type":"Point"}
}