{
  "id": 7088723,
  "type": "Feature",
  "properties": {
    "tgn:hierarchy":[
        "tgn:7088723",
        "tgn:1000003",
        "tgn:7003678",
        "tgn:7000084",
        "tgn:7029392"
    ],
    "tgn:id":7088723,
    "tgn:name":"Watt-Berg",
    "tgn:placetype":[
        "aat:300008777"
    ]
},
  "bbox": [],
  "geometry": {"coordinates":[9.333333,51.483333],"type":"Point"}
}