{
  "id": 2185077,
  "type": "Feature",
  "properties": {
    "tgn:hierarchy":[
        "tgn:2185077",
        "tgn:7002659",
        "tgn:1000001",
        "tgn:7012149",
        "tgn:2000033",
        "tgn:7029392"
    ],
    "tgn:id":2185077,
    "tgn:name":"Boggy Branch",
    "tgn:placetype":[
        "aat:300008699"
    ]
},
  "bbox": [],
  "geometry": {"coordinates":[-85.25,31.6667],"type":"Point"}
}