{
  "id": 2718485,
  "type": "Feature",
  "properties": {
    "tgn:hierarchy":[
        "tgn:2718485",
        "tgn:1000001",
        "tgn:7012149",
        "tgn:7022217",
        "tgn:7007919",
        "tgn:7029392"
    ],
    "tgn:id":2718485,
    "tgn:name":"Thompson Landing",
    "tgn:placetype":[
        "aat:300008347"
    ]
},
  "bbox": [],
  "geometry": {"coordinates":[-76.55,36.7667],"type":"Point"}
}