{
  "id": 7092719,
  "type": "Feature",
  "properties": {
    "tgn:hierarchy":[
        "tgn:7092719",
        "tgn:1000003",
        "tgn:7003676",
        "tgn:7000084",
        "tgn:7029392"
    ],
    "tgn:id":7092719,
    "tgn:name":"Vorberg",
    "tgn:placetype":[
        "aat:300008347"
    ]
},
  "bbox": [],
  "geometry": {"coordinates":[8.583333,53.25],"type":"Point"}
}