{
  "id": 7446708,
  "type": "Feature",
  "properties": {
    "tgn:hierarchy":[
        "tgn:7446708",
        "tgn:7002445",
        "tgn:1000003",
        "tgn:7008180",
        "tgn:7008591",
        "tgn:7029392"
    ],
    "tgn:id":7446708,
    "tgn:name:en":"Redlynch",
    "tgn:placetype":[
        "aat:300008347"
    ]
},
  "bbox": [],
  "geometry": {"coordinates":[-1.716667,50.983333],"type":"Point"}
}