{
  "id": 7468193,
  "type": "Feature",
  "properties": {
    "tgn:hierarchy":[
        "tgn:7468193",
        "tgn:7488858",
        "tgn:1000004",
        "tgn:1000141",
        "tgn:7029392"
    ],
    "tgn:id":7468193,
    "tgn:name":"Jiangxilin",
    "tgn:placetype":[
        "aat:300008347"
    ]
},
  "bbox": [],
  "geometry": {"coordinates":[120.69748,23.77286],"type":"Point"}
}