{
  "id": 2450190,
  "type": "Feature",
  "properties": {
    "tgn:hierarchy":[
        "tgn:2450190",
        "tgn:1000001",
        "tgn:7012149",
        "tgn:2001067",
        "tgn:7007521",
        "tgn:7029392"
    ],
    "tgn:id":2450190,
    "tgn:name":"Line Lake",
    "tgn:placetype":[
        "aat:300008680"
    ]
},
  "bbox": [],
  "geometry": {"coordinates":[-92.0333,47.1333],"type":"Point"}
}