{
  "id": 7315898,
  "type": "Feature",
  "properties": {
    "tgn:hierarchy":[
        "tgn:7315898",
        "tgn:7016598",
        "tgn:1000049",
        "tgn:1000002",
        "tgn:7029392"
    ],
    "tgn:id":7315898,
    "tgn:name":"Ceballos, Aguada de",
    "tgn:placetype":[
        "aat:300008697"
    ]
},
  "bbox": [],
  "geometry": {"coordinates":[-69.233333,-25.05],"type":"Point"}
}