{
  "id": 1123489,
  "type": "Feature",
  "properties": {
    "tgn:hierarchy":[
        "tgn:1123489",
        "tgn:1000003",
        "tgn:7016845",
        "tgn:7029392"
    ],
    "tgn:id":1123489,
    "tgn:name":"Dordtse Kil",
    "tgn:placetype":[
        "aat:300008707"
    ]
},
  "bbox": [],
  "geometry": {"coordinates":[4.6333,51.7167],"type":"Point"}
}