{
  "id": 7281788,
  "type": "Feature",
  "properties": {
    "tgn:hierarchy":[
        "tgn:7281788",
        "tgn:1001695",
        "tgn:1000049",
        "tgn:1000002",
        "tgn:7029392"
    ],
    "tgn:id":7281788,
    "tgn:name":"San Rafael",
    "tgn:placetype":[
        "aat:300004792"
    ]
},
  "bbox": [],
  "geometry": {"coordinates":[-70.916667,-34.466667],"type":"Point"}
}