{
  "id": 7398586,
  "type": "Feature",
  "properties": {
    "tgn:hierarchy":[
        "tgn:7398586",
        "tgn:1000001",
        "tgn:7005593",
        "tgn:7005560",
        "tgn:7029392"
    ],
    "tgn:id":7398586,
    "tgn:name":"Barajas",
    "tgn:placetype":[
        "aat:300008347"
    ]
},
  "bbox": [],
  "geometry": {"coordinates":[-99.766667,20.577778],"type":"Point"}
}