{
  "id": 2242365,
  "type": "Feature",
  "properties": {
    "tgn:hierarchy":[
        "tgn:2242365",
        "tgn:1000001",
        "tgn:7012149",
        "tgn:2002378",
        "tgn:7007923",
        "tgn:7029392"
    ],
    "tgn:id":2242365,
    "tgn:name":"Clayton Draw",
    "tgn:placetype":[
        "aat:300008761"
    ]
},
  "bbox": [],
  "geometry": {"coordinates":[-104.6167,43.3333],"type":"Point"}
}