{
  "id": 2170707,
  "type": "Feature",
  "properties": {
    "tgn:hierarchy":[
        "tgn:2170707",
        "tgn:1000001",
        "tgn:7012149",
        "tgn:1002535",
        "tgn:7007826",
        "tgn:7029392"
    ],
    "tgn:id":2170707,
    "tgn:name":"Big Sandy Creek",
    "tgn:placetype":[
        "aat:300008706"
    ]
},
  "bbox": [],
  "geometry": {"coordinates":[-96.3833,32.45],"type":"Point"}
}