{
  "id": 1041943,
  "type": "Feature",
  "properties": {
    "tgn:hierarchy":[
        "tgn:1041943",
        "tgn:7002692",
        "tgn:7012056",
        "tgn:1000003",
        "tgn:1000074",
        "tgn:7029392"
    ],
    "tgn:id":1041943,
    "tgn:name":"\u00c1yios Nik\u00f3laos",
    "tgn:placetype":[
        "aat:300008347",
        "aat:300387220"
    ]
},
  "bbox": [],
  "geometry": {"coordinates":[25.713333,35.191389],"type":"Point"}
}