{
  "id": 7475519,
  "type": "Feature",
  "properties": {
    "tgn:hierarchy":[
        "tgn:7475519",
        "tgn:1000004",
        "tgn:7001002",
        "tgn:1000141",
        "tgn:7029392"
    ],
    "tgn:id":7475519,
    "tgn:name":"Nangang",
    "tgn:placetype":[
        "aat:300008347"
    ]
},
  "bbox": [],
  "geometry": {"coordinates":[120.897449,24.740981],"type":"Point"}
}