{
  "id": 7562721,
  "type": "Feature",
  "properties": {
    "tgn:hierarchy":[
        "tgn:7562721",
        "tgn:1000004",
        "tgn:7000198",
        "tgn:7016722",
        "tgn:7029392"
    ],
    "tgn:id":7562721,
    "tgn:name:en":"Mawai Rah\u0101yak",
    "tgn:placetype":[
        "aat:300008347"
    ]
},
  "bbox": [],
  "geometry": {"coordinates":[79.798,27.0479],"type":"Point"}
}