{
  "id": 7358468,
  "type": "Feature",
  "properties": {
    "tgn:hierarchy":[
        "tgn:7358468",
        "tgn:7005581",
        "tgn:1000001",
        "tgn:7005560",
        "tgn:7029392"
    ],
    "tgn:id":7358468,
    "tgn:name":"Coyote, Ojo del",
    "tgn:placetype":[
        "aat:300008697"
    ]
},
  "bbox": [],
  "geometry": {"coordinates":[-106.516667,30.783333],"type":"Point"}
}