{
  "id": 1113428,
  "type": "Feature",
  "properties": {
    "tgn:hierarchy":[
        "tgn:1113428",
        "tgn:7019094",
        "tgn:7002444",
        "tgn:1000003",
        "tgn:7008591",
        "tgn:7029392"
    ],
    "tgn:id":1113428,
    "tgn:name:en":"Melfort, Loch",
    "tgn:placetype":[
        "aat:300132316"
    ]
},
  "bbox": [],
  "geometry": {"coordinates":[-5.516667,56.25],"type":"Point"}
}