{
  "id": 2266353,
  "type": "Feature",
  "properties": {
    "tgn:hierarchy":[
        "tgn:2266353",
        "tgn:1000001",
        "tgn:1002308",
        "tgn:7012149",
        "tgn:7007710",
        "tgn:7029392"
    ],
    "tgn:id":2266353,
    "tgn:name":"Crazy Run",
    "tgn:placetype":[
        "aat:300008699"
    ]
},
  "bbox": [],
  "geometry": {"coordinates":[-80.4167,41.7667],"type":"Point"}
}