{
  "id": 2619616,
  "type": "Feature",
  "properties": {
    "tgn:hierarchy":[
        "tgn:2619616",
        "tgn:1000001",
        "tgn:7006451",
        "tgn:7012149",
        "tgn:2000100",
        "tgn:7029392"
    ],
    "tgn:id":2619616,
    "tgn:name":"Rinconada Spring",
    "tgn:placetype":[
        "aat:300008697"
    ]
},
  "bbox": [],
  "geometry": {"coordinates":[-110.6333,32.2833],"type":"Point"}
}