{
  "id": 7017970,
  "type": "Feature",
  "properties": {
    "tgn:hierarchy":[
        "tgn:7017970",
        "tgn:1000004",
        "tgn:7029392"
    ],
    "tgn:id":7017970,
    "tgn:name":"Kunjirap Daban",
    "tgn:placetype":[
        "aat:300259572"
    ]
},
  "bbox": [],
  "geometry": {"coordinates":[75.2667,36.8333],"type":"Point"}
}