{
  "id": 7358602,
  "type": "Feature",
  "properties": {
    "tgn:hierarchy":[
        "tgn:7358602",
        "tgn:1001853",
        "tgn:1000001",
        "tgn:7005560",
        "tgn:7029392"
    ],
    "tgn:id":7358602,
    "tgn:name":"Rancho El Abanico",
    "tgn:placetype":[
        "aat:300000241"
    ]
},
  "bbox": [],
  "geometry": {"coordinates":[-102.383333,29.683333],"type":"Point"}
}