<<<<<<< HEAD
{
  "id": 7358602,
  "type": "Feature",
  "properties": {
    "tgn:hierarchy":[
        "tgn:7358602",
        "tgn:1001853",
        "tgn:1000001",
        "tgn:7005560",
        "tgn:7029392"
    ],
    "tgn:id":7358602,
    "tgn:name":"Rancho El Abanico",
    "tgn:placetype":[
        "aat:300000241"
    ]
},
  "bbox": [],
  "geometry": {"coordinates":[-102.383333,29.683333],"type":"Point"}
}
=======
{"geometry":{"type":"Point","coordinates":[-102.383333,29.683333]},"type":"Feature","properties":{"hierarchy":["tgn:7358602","tgn:1001853","tgn:1000001","tgn:7005560","tgn:7029392"],"placetype":["aat:300000241"],"id":7358602,"name:xx":"Rancho El Abanico"}}
>>>>>>> 03f74aca74312dbeaf24d7e61306dd6a786dc3d0
