{
  "id": 2193269,
  "type": "Feature",
  "properties": {
    "tgn:hierarchy":[
        "tgn:2193269",
        "tgn:1000001",
        "tgn:7012149",
        "tgn:2001667",
        "tgn:7007707",
        "tgn:7029392"
    ],
    "tgn:id":2193269,
    "tgn:name":"Breedlove Lake",
    "tgn:placetype":[
        "aat:300008680"
    ]
},
  "bbox": [],
  "geometry": {"coordinates":[-94.5167,33.65],"type":"Point"}
}