{
  "id": 1010054,
  "type": "Feature",
  "properties": {
    "tgn:hierarchy":[
        "tgn:1010054",
        "tgn:7000895",
        "tgn:1000004",
        "tgn:1001031",
        "tgn:1000120",
        "tgn:7029392"
    ],
    "tgn:id":1010054,
    "tgn:name":"Izu-shot\u014d",
    "tgn:placetype":[
        "aat:300386853"
    ]
},
  "bbox": [],
  "geometry": {"coordinates":[140.0333,34.0833],"type":"Point"}
}