{
  "id": 2328829,
  "type": "Feature",
  "properties": {
    "tgn:hierarchy":[
        "tgn:2328829",
        "tgn:1000001",
        "tgn:2001734",
        "tgn:7012149",
        "tgn:7007712",
        "tgn:7029392"
    ],
    "tgn:id":2328829,
    "tgn:name":"Fishing Creek",
    "tgn:placetype":[
        "aat:300008706"
    ]
},
  "bbox": [],
  "geometry": {"coordinates":[-80.2833,32.5333],"type":"Point"}
}