{
  "id": 2415720,
  "type": "Feature",
  "properties": {
    "tgn:hierarchy":[
        "tgn:2415720",
        "tgn:7006450",
        "tgn:1000001",
        "tgn:7012149",
        "tgn:2124005",
        "tgn:7029392"
    ],
    "tgn:id":2415720,
    "tgn:name":"Iteriak Creek",
    "tgn:placetype":[
        "aat:300008706"
    ]
},
  "bbox": [],
  "geometry": {"coordinates":[-155.8333,68.2667],"type":"Point"}
}