{
  "id": 7373099,
  "type": "Feature",
  "properties": {
    "tgn:hierarchy":[
        "tgn:7373099",
        "tgn:1000001",
        "tgn:7005593",
        "tgn:7005560",
        "tgn:7029392"
    ],
    "tgn:id":7373099,
    "tgn:name":"La Laja",
    "tgn:placetype":[
        "aat:300008347"
    ]
},
  "bbox": [],
  "geometry": {"coordinates":[-99.966667,20.583333],"type":"Point"}
}