{
  "id": 2614829,
  "type": "Feature",
  "properties": {
    "tgn:hierarchy":[
        "tgn:2614829",
        "tgn:1000001",
        "tgn:2002146",
        "tgn:7012149",
        "tgn:7007919",
        "tgn:7029392"
    ],
    "tgn:id":2614829,
    "tgn:name":"Renick Run",
    "tgn:placetype":[
        "aat:300008699"
    ]
},
  "bbox": [],
  "geometry": {"coordinates":[-79.65,37.6167],"type":"Point"}
}