{
  "id": 2057308,
  "type": "Feature",
  "properties": {
    "tgn:hierarchy":[
        "tgn:2057308",
        "tgn:1000001",
        "tgn:2001097",
        "tgn:7012149",
        "tgn:7007522",
        "tgn:7029392"
    ],
    "tgn:id":2057308,
    "tgn:name":"Quitman",
    "tgn:placetype":[
        "aat:300008347",
        "aat:300008416"
    ]
},
  "bbox": [],
  "geometry": {"coordinates":[-88.7167,32.0333],"type":"Point"}
}