{
  "id": 2680637,
  "type": "Feature",
  "properties": {
    "tgn:hierarchy":[
        "tgn:2680637",
        "tgn:1002140",
        "tgn:1000001",
        "tgn:7012149",
        "tgn:7007520",
        "tgn:7029392"
    ],
    "tgn:id":2680637,
    "tgn:name":"South Haven Highlands",
    "tgn:placetype":[
        "aat:300008347"
    ]
},
  "bbox": [],
  "geometry": {"coordinates":[-86.25,42.45],"type":"Point"}
}