{
  "id": 2402376,
  "type": "Feature",
  "properties": {
    "tgn:hierarchy":[
        "tgn:2402376",
        "tgn:1000001",
        "tgn:2000465",
        "tgn:7012149",
        "tgn:7007250",
        "tgn:7029392"
    ],
    "tgn:id":2402376,
    "tgn:name":"Horton Lateral",
    "tgn:placetype":[
        "aat:300006075"
    ]
},
  "bbox": [],
  "geometry": {"coordinates":[-116.6167,43.65],"type":"Point"}
}