{
  "id": 2190065,
  "type": "Feature",
  "properties": {
    "tgn:hierarchy":[
        "tgn:2190065",
        "tgn:1000001",
        "tgn:7012149",
        "tgn:2001607",
        "tgn:7007705",
        "tgn:7029392"
    ],
    "tgn:id":2190065,
    "tgn:name":"Bowman Coulee",
    "tgn:placetype":[
        "aat:300008761"
    ]
},
  "bbox": [],
  "geometry": {"coordinates":[-101.9667,48.4833],"type":"Point"}
}