{
  "id": 7586984,
  "type": "Feature",
  "properties": {
    "tgn:hierarchy":[
        "tgn:7586984",
        "tgn:1000004",
        "tgn:7000198",
        "tgn:7000799",
        "tgn:7029392"
    ],
    "tgn:id":7586984,
    "tgn:name:en":"Dundhganga Nala",
    "tgn:placetype":[
        "aat:300008347"
    ]
},
  "bbox": [],
  "geometry": {"coordinates":[74.529451,33.744094],"type":"Point"}
}