{
  "id": 1034412,
  "type": "Feature",
  "properties": {
    "tgn:hierarchy":[
        "tgn:1034412",
        "tgn:1000003",
        "tgn:7002881",
        "tgn:1000070",
        "tgn:7029392"
    ],
    "tgn:id":1034412,
    "tgn:name":"Molinges",
    "tgn:placetype":[
        "aat:300008347"
    ]
},
  "bbox": [],
  "geometry": {"coordinates":[5.75,46.35],"type":"Point"}
}