{
  "id": 7356985,
  "type": "Feature",
  "properties": {
    "tgn:hierarchy":[
        "tgn:7356985",
        "tgn:1000001",
        "tgn:7005595",
        "tgn:7005560",
        "tgn:7029392"
    ],
    "tgn:id":7356985,
    "tgn:name":"Campo Mato",
    "tgn:placetype":[
        "aat:300008347"
    ]
},
  "bbox": [],
  "geometry": {"coordinates":[-107.441667,24.532778],"type":"Point"}
}