{
  "id": 1059111,
  "type": "Feature",
  "properties": {
    "tgn:hierarchy":[
        "tgn:1059111",
        "tgn:7012908",
        "tgn:1000004",
        "tgn:7014786",
        "tgn:7029392"
    ],
    "tgn:id":1059111,
    "tgn:name":"Sagiz",
    "tgn:placetype":[
        "aat:300008347",
        "aat:300008375"
    ]
},
  "bbox": [],
  "geometry": {"coordinates":[53.2667,47.5167],"type":"Point"}
}