{
  "id": 2247040,
  "type": "Feature",
  "properties": {
    "tgn:hierarchy":[
        "tgn:2247040",
        "tgn:1000001",
        "tgn:7012149",
        "tgn:7015778",
        "tgn:7007919",
        "tgn:7029392"
    ],
    "tgn:id":2247040,
    "tgn:name":"Cockpit Point",
    "tgn:placetype":[
        "aat:300008850"
    ]
},
  "bbox": [],
  "geometry": {"coordinates":[-77.25,38.55],"type":"Point"}
}