{
  "id": 7276551,
  "type": "Feature",
  "properties": {
    "tgn:hierarchy":[
        "tgn:7276551",
        "tgn:1001699",
        "tgn:1000049",
        "tgn:1000002",
        "tgn:7029392"
    ],
    "tgn:id":7276551,
    "tgn:name":"R\u00edo Pudidi",
    "tgn:placetype":[
        "aat:300008699"
    ]
},
  "bbox": [],
  "geometry": {"coordinates":[-73.794444,-42.252778],"type":"Point"}
}