{
  "id": 7345930,
  "type": "Feature",
  "properties": {
    "tgn:hierarchy":[
        "tgn:7345930",
        "tgn:7002836",
        "tgn:7016622",
        "tgn:1000003",
        "tgn:1000095",
        "tgn:7029392"
    ],
    "tgn:id":7345930,
    "tgn:name":"Arona",
    "tgn:placetype":[
        "aat:300008347"
    ]
},
  "bbox": [],
  "geometry": {"coordinates":[-16.666667,28.083333],"type":"Point"}
}