{
  "id": 2211930,
  "type": "Feature",
  "properties": {
    "tgn:hierarchy":[
        "tgn:2211930",
        "tgn:1000001",
        "tgn:2001733",
        "tgn:7012149",
        "tgn:7007712",
        "tgn:7029392"
    ],
    "tgn:id":2211930,
    "tgn:name":"Buyck Bottom",
    "tgn:placetype":[
        "aat:300008761"
    ]
},
  "bbox": [],
  "geometry": {"coordinates":[-80.8333,33.7333],"type":"Point"}
}