{
  "id": 2785992,
  "type": "Feature",
  "properties": {
    "tgn:hierarchy":[
        "tgn:2785992",
        "tgn:1000001",
        "tgn:7006451",
        "tgn:7012149",
        "tgn:2000097",
        "tgn:7029392"
    ],
    "tgn:id":2785992,
    "tgn:name":"Young America West",
    "tgn:placetype":[
        "aat:300008347"
    ]
},
  "bbox": [],
  "geometry": {"coordinates":[-112.25,33.4833],"type":"Point"}
}