{
  "id": 2092192,
  "type": "Feature",
  "properties": {
    "tgn:hierarchy":[
        "tgn:2092192",
        "tgn:1000001",
        "tgn:1002249",
        "tgn:7012149",
        "tgn:7007710",
        "tgn:7029392"
    ],
    "tgn:id":2092192,
    "tgn:name":"Potters Mills",
    "tgn:placetype":[
        "aat:300008347"
    ]
},
  "bbox": [],
  "geometry": {"coordinates":[-77.6167,40.7833],"type":"Point"}
}