{
  "id": 7517686,
  "type": "Feature",
  "properties": {
    "tgn:hierarchy":[
        "tgn:7517686",
        "tgn:1009227",
        "tgn:1000226",
        "tgn:7016822",
        "tgn:1000006",
        "tgn:7029392"
    ],
    "tgn:id":7517686,
    "tgn:name:en":"Knapdale",
    "tgn:placetype":[
        "aat:300008347"
    ]
},
  "bbox": [],
  "geometry": {"coordinates":[168.916667,-46.016667],"type":"Point"}
}