<<<<<<< HEAD
{
  "id": 2405822,
  "type": "Feature",
  "properties": {
    "tgn:hierarchy":[
        "tgn:2405822",
        "tgn:1000001",
        "tgn:7012149",
        "tgn:1002456",
        "tgn:7007826",
        "tgn:7029392"
    ],
    "tgn:id":2405822,
    "tgn:name":"Hull Gully",
    "tgn:placetype":[
        "aat:300008761"
    ]
},
  "bbox": [],
  "geometry": {"coordinates":[-94.95,29.7333],"type":"Point"}
}
=======
{"geometry":{"type":"Point","coordinates":[-94.950000,29.733300]},"type":"Feature","properties":{"hierarchy":["tgn:2405822","tgn:1000001","tgn:7012149","tgn:1002456","tgn:7007826","tgn:7029392"],"placetype":["aat:300008761"],"id":2405822,"name:xx":"Hull Gully"}}
>>>>>>> 03f74aca74312dbeaf24d7e61306dd6a786dc3d0
