{
  "id": 2405822,
  "type": "Feature",
  "properties": {
    "tgn:hierarchy":[
        "tgn:2405822",
        "tgn:1000001",
        "tgn:7012149",
        "tgn:1002456",
        "tgn:7007826",
        "tgn:7029392"
    ],
    "tgn:id":2405822,
    "tgn:name":"Hull Gully",
    "tgn:placetype":[
        "aat:300008761"
    ]
},
  "bbox": [],
  "geometry": {"coordinates":[-94.95,29.7333],"type":"Point"}
}