{
  "id": 2707537,
  "type": "Feature",
  "properties": {
    "tgn:hierarchy":[
        "tgn:2707537",
        "tgn:1000001",
        "tgn:7012149",
        "tgn:2001442",
        "tgn:7007566",
        "tgn:7029392"
    ],
    "tgn:id":2707537,
    "tgn:name":"Sweethart Windmill",
    "tgn:placetype":[
        "aat:300006191"
    ]
},
  "bbox": [],
  "geometry": {"coordinates":[-105.4833,33.3833],"type":"Point"}
}