{
  "id": 2513040,
  "type": "Feature",
  "properties": {
    "tgn:hierarchy":[
        "tgn:2513040",
        "tgn:1000001",
        "tgn:7012149",
        "tgn:2002162",
        "tgn:7007919",
        "tgn:7029392"
    ],
    "tgn:id":2513040,
    "tgn:name":"Mill Creek",
    "tgn:placetype":[
        "aat:300008706"
    ]
},
  "bbox": [],
  "geometry": {"coordinates":[-80.8333,37.2667],"type":"Point"}
}