{
  "id": 7478542,
  "type": "Feature",
  "properties": {
    "tgn:hierarchy":[
        "tgn:7478542",
        "tgn:1000004",
        "tgn:7467799",
        "tgn:1000141",
        "tgn:7029392"
    ],
    "tgn:id":7478542,
    "tgn:name":"Erchongcun Qiao",
    "tgn:placetype":[
        "aat:300007836"
    ]
},
  "bbox": [],
  "geometry": {"coordinates":[120.523631,23.963569],"type":"Point"}
}