<<<<<<< HEAD
{
  "id": 7478542,
  "type": "Feature",
  "properties": {
    "tgn:hierarchy":[
        "tgn:7478542",
        "tgn:1000004",
        "tgn:7467799",
        "tgn:1000141",
        "tgn:7029392"
    ],
    "tgn:id":7478542,
    "tgn:name":"Erchongcun Qiao",
    "tgn:placetype":[
        "aat:300007836"
    ]
},
  "bbox": [],
  "geometry": {"coordinates":[120.523631,23.963569],"type":"Point"}
}
=======
{"geometry":{"type":"Point","coordinates":[120.523631,23.963569]},"type":"Feature","properties":{"hierarchy":["tgn:7478542","tgn:1000004","tgn:7467799","tgn:1000141","tgn:7029392"],"placetype":["aat:300007836"],"id":7478542,"name:xx":"Erchongcun Qiao"}}
>>>>>>> 03f74aca74312dbeaf24d7e61306dd6a786dc3d0
