{
  "id": 7063679,
  "type": "Feature",
  "properties": {
    "tgn:hierarchy":[
        "tgn:7063679",
        "tgn:7000096",
        "tgn:1000003",
        "tgn:7000084",
        "tgn:7029392"
    ],
    "tgn:id":7063679,
    "tgn:name":"Altthymen",
    "tgn:placetype":[
        "aat:300008347"
    ]
},
  "bbox": [],
  "geometry": {"coordinates":[13.166667,53.233333],"type":"Point"}
}