{
  "id": 7566812,
  "type": "Feature",
  "properties": {
    "tgn:hierarchy":[
        "tgn:7566812",
        "tgn:1000004",
        "tgn:7000198",
        "tgn:7001797",
        "tgn:7029392"
    ],
    "tgn:id":7566812,
    "tgn:name:en":"Karunanidhi Nagar",
    "tgn:placetype":[
        "aat:300000745"
    ]
},
  "bbox": [],
  "geometry": {"coordinates":[80.278611,13.133333],"type":"Point"}
}