{
  "id": 7004738,
  "type": "Feature",
  "properties": {
    "tgn:hierarchy":[
        "tgn:7004738",
        "tgn:1000961",
        "tgn:1000004",
        "tgn:7000901",
        "tgn:1000120",
        "tgn:7029392"
    ],
    "tgn:id":7004738,
    "tgn:name":"Nakatsu",
    "tgn:placetype":[
        "aat:300008347",
        "aat:300008375",
        "aat:300120599"
    ]
},
  "bbox": [],
  "geometry": {"coordinates":[131.1833,33.6167],"type":"Point"}
}