{
  "id": 2538252,
  "type": "Feature",
  "properties": {
    "tgn:hierarchy":[
        "tgn:2538252",
        "tgn:1000001",
        "tgn:7012149",
        "tgn:7007524",
        "tgn:7029392"
    ],
    "tgn:id":2538252,
    "tgn:name":"Nelson South Number 9 Canal",
    "tgn:placetype":[
        "aat:300006075"
    ]
},
  "bbox": [],
  "geometry": {"coordinates":[-107.3667,48.4667],"type":"Point"}
}