{
  "id": 1024213,
  "type": "Feature",
  "properties": {
    "tgn:hierarchy":[
        "tgn:1024213",
        "tgn:7002568",
        "tgn:1000054",
        "tgn:1000002",
        "tgn:7029392"
    ],
    "tgn:id":1024213,
    "tgn:name":"Holmia",
    "tgn:placetype":[
        "aat:300008347"
    ]
},
  "bbox": [],
  "geometry": {"coordinates":[-59.5833,4.9667],"type":"Point"}
}