{
  "id": 7511511,
  "type": "Feature",
  "properties": {
    "tgn:hierarchy":[
        "tgn:7511511",
        "tgn:1008380",
        "tgn:7000507",
        "tgn:1000226",
        "tgn:1000006",
        "tgn:7029392"
    ],
    "tgn:id":7511511,
    "tgn:name:en":"Marohapa",
    "tgn:placetype":[
        "aat:300008777"
    ]
},
  "bbox": [],
  "geometry": {"coordinates":[174.016667,-35.416667],"type":"Point"}
}