{
  "id": 2614707,
  "type": "Feature",
  "properties": {
    "tgn:hierarchy":[
        "tgn:2614707",
        "tgn:1000001",
        "tgn:2001187",
        "tgn:7012149",
        "tgn:7007523",
        "tgn:7029392"
    ],
    "tgn:id":2614707,
    "tgn:name":"Remote, Lake",
    "tgn:placetype":[
        "aat:300008680"
    ]
},
  "bbox": [],
  "geometry": {"coordinates":[-94.55,39.3833],"type":"Point"}
}