{
  "id": 7575574,
  "type": "Feature",
  "properties": {
    "tgn:hierarchy":[
        "tgn:7575574",
        "tgn:1000004",
        "tgn:7000198",
        "tgn:7016883",
        "tgn:7029392"
    ],
    "tgn:id":7575574,
    "tgn:name:en":"Mahatpur",
    "tgn:placetype":[
        "aat:300008347"
    ]
},
  "bbox": [],
  "geometry": {"coordinates":[75.47821,31.049588],"type":"Point"}
}