{
  "id": 7419733,
  "type": "Feature",
  "properties": {
    "tgn:hierarchy":[
        "tgn:7419733",
        "tgn:7005579",
        "tgn:1000001",
        "tgn:7005560",
        "tgn:7029392"
    ],
    "tgn:id":7419733,
    "tgn:name":"El Rosal",
    "tgn:placetype":[
        "aat:300008347"
    ]
},
  "bbox": [],
  "geometry": {"coordinates":[-102.029167,22.116667],"type":"Point"}
}