{
  "id": 2485717,
  "type": "Feature",
  "properties": {
    "tgn:hierarchy":[
        "tgn:2485717",
        "tgn:1000001",
        "tgn:7012149",
        "tgn:2001895",
        "tgn:7007825",
        "tgn:7029392"
    ],
    "tgn:id":2485717,
    "tgn:name":"Lazy Branch",
    "tgn:placetype":[
        "aat:300008699"
    ]
},
  "bbox": [],
  "geometry": {"coordinates":[-86.6667,35.3833],"type":"Point"}
}