{
  "id": 7339106,
  "type": "Feature",
  "properties": {
    "tgn:hierarchy":[
        "tgn:7339106",
        "tgn:7002825",
        "tgn:7016622",
        "tgn:1000003",
        "tgn:1000095",
        "tgn:7029392"
    ],
    "tgn:id":7339106,
    "tgn:name":"Cruz, Punta de la",
    "tgn:placetype":[
        "aat:300386846"
    ]
},
  "bbox": [],
  "geometry": {"coordinates":[-14.066667,28.533333],"type":"Point"}
}