{
  "id": 7411274,
  "type": "Feature",
  "properties": {
    "tgn:hierarchy":[
        "tgn:7411274",
        "tgn:7005580",
        "tgn:1000001",
        "tgn:7005560",
        "tgn:7029392"
    ],
    "tgn:id":7411274,
    "tgn:name":"El Chich",
    "tgn:placetype":[
        "aat:300008347"
    ]
},
  "bbox": [],
  "geometry": {"coordinates":[-92.175,17.091667],"type":"Point"}
}