<<<<<<< HEAD
{
  "id": 7177234,
  "type": "Feature",
  "properties": {
    "tgn:hierarchy":[
        "tgn:7177234",
        "tgn:7000096",
        "tgn:1000003",
        "tgn:7000084",
        "tgn:7029392"
    ],
    "tgn:id":7177234,
    "tgn:name":"Gustavsruh",
    "tgn:placetype":[
        "aat:300000206"
    ]
},
  "bbox": [],
  "geometry": {"coordinates":[13.783333,53.2],"type":"Point"}
}
=======
{"geometry":{"type":"Point","coordinates":[13.783333,53.200000]},"type":"Feature","properties":{"hierarchy":["tgn:7177234","tgn:7000096","tgn:1000003","tgn:7000084","tgn:7029392"],"placetype":["aat:300000206"],"id":7177234,"name:xx":"Gustavsruh"}}
>>>>>>> 03f74aca74312dbeaf24d7e61306dd6a786dc3d0
