{
  "id": 7282076,
  "type": "Feature",
  "properties": {
    "tgn:hierarchy":[
        "tgn:7282076",
        "tgn:1001630",
        "tgn:1000049",
        "tgn:1000002",
        "tgn:7029392"
    ],
    "tgn:id":7282076,
    "tgn:name":"Salto del Pingo",
    "tgn:placetype":[
        "aat:300008697"
    ]
},
  "bbox": [],
  "geometry": {"coordinates":[-69.65,-26.783333],"type":"Point"}
}