{
  "id": 1080473,
  "type": "Feature",
  "properties": {
    "tgn:hierarchy":[
        "tgn:1080473",
        "tgn:1000004",
        "tgn:7000894",
        "tgn:7016797",
        "tgn:1000120",
        "tgn:7029392"
    ],
    "tgn:id":1080473,
    "tgn:name":"Kasukabe",
    "tgn:placetype":[
        "aat:300008347"
    ]
},
  "bbox": [],
  "geometry": {"coordinates":[139.75,35.9667],"type":"Point"}
}