{
  "id": 2289629,
  "type": "Feature",
  "properties": {
    "tgn:hierarchy":[
        "tgn:2289629",
        "tgn:1000001",
        "tgn:7012149",
        "tgn:2000226",
        "tgn:7007158",
        "tgn:7029392"
    ],
    "tgn:id":2289629,
    "tgn:name":"Dixon Reservoir",
    "tgn:placetype":[
        "aat:300006191"
    ]
},
  "bbox": [],
  "geometry": {"coordinates":[-105.0667,40.65],"type":"Point"}
}