{
  "id": 2654053,
  "type": "Feature",
  "properties": {
    "tgn:hierarchy":[
        "tgn:2654053",
        "tgn:1000001",
        "tgn:7012149",
        "tgn:1002441",
        "tgn:7007706",
        "tgn:7029392"
    ],
    "tgn:id":2654053,
    "tgn:name":"Shademoore",
    "tgn:placetype":[
        "aat:300008347"
    ]
},
  "bbox": [],
  "geometry": {"coordinates":[-84.3667,39.1333],"type":"Point"}
}