{
  "id": 2591860,
  "type": "Feature",
  "properties": {
    "tgn:hierarchy":[
        "tgn:2591860",
        "tgn:1000001",
        "tgn:7012149",
        "tgn:1002871",
        "tgn:7007568",
        "tgn:7029392"
    ],
    "tgn:id":2591860,
    "tgn:name":"Pond Mountain",
    "tgn:placetype":[
        "aat:300008798"
    ]
},
  "bbox": [],
  "geometry": {"coordinates":[-73.8833,43.3333],"type":"Point"}
}