{
  "id": 2440846,
  "type": "Feature",
  "properties": {
    "tgn:hierarchy":[
        "tgn:2440846",
        "tgn:7006450",
        "tgn:1000001",
        "tgn:2124053",
        "tgn:7012149",
        "tgn:7029392"
    ],
    "tgn:id":2440846,
    "tgn:name":"Knik",
    "tgn:placetype":[
        "aat:300008347"
    ]
},
  "bbox": [],
  "geometry": {"coordinates":[-149.7167,61.45],"type":"Point"}
}