{
  "id": 7259929,
  "type": "Feature",
  "properties": {
    "tgn:concordances":{
        "gn:id":"2759105"
    },
    "tgn:hierarchy":[
        "tgn:7259929",
        "tgn:1000003",
        "tgn:7003632",
        "tgn:7016845",
        "tgn:7029392"
    ],
    "tgn:id":7259929,
    "tgn:name:nl":"Bergstoep",
    "tgn:placetype":[
        "aat:300008347"
    ]
},
  "bbox": [],
  "geometry": {"coordinates":[4.783333,51.916667],"type":"Point"}
}