{
  "id": 7050498,
  "type": "Feature",
  "properties": {
    "tgn:hierarchy":[
        "tgn:7050498",
        "tgn:7003127",
        "tgn:1000003",
        "tgn:7008516",
        "tgn:1000080",
        "tgn:7029392"
    ],
    "tgn:id":7050498,
    "tgn:name":"La Sirena",
    "tgn:placetype":[
        "aat:300008347"
    ]
},
  "bbox": [],
  "geometry": {"coordinates":[11.083333,44.35],"type":"Point"}
}