{
  "id": 2347121,
  "type": "Feature",
  "properties": {
    "tgn:hierarchy":[
        "tgn:2347121",
        "tgn:1000001",
        "tgn:1002283",
        "tgn:7012149",
        "tgn:7007520",
        "tgn:7029392"
    ],
    "tgn:id":2347121,
    "tgn:name":"Geneva, Lake",
    "tgn:placetype":[
        "aat:300008680"
    ]
},
  "bbox": [],
  "geometry": {"coordinates":[-84.5667,42.8333],"type":"Point"}
}