{
  "id": 7014156,
  "type": "Feature",
  "properties": {
    "tgn:hierarchy":[
        "tgn:7014156",
        "tgn:1002996",
        "tgn:1000001",
        "tgn:7012149",
        "tgn:7007711",
        "tgn:7029392"
    ],
    "tgn:id":7014156,
    "tgn:name":"Exeter",
    "tgn:placetype":[
        "aat:300008347"
    ]
},
  "bbox": [],
  "geometry": {"coordinates":[-71.5333,41.5667],"type":"Point"}
}