<<<<<<< HEAD
{
  "id": 2763532,
  "type": "Feature",
  "properties": {
    "tgn:hierarchy":[
        "tgn:2763532",
        "tgn:1000001",
        "tgn:2001014",
        "tgn:7012149",
        "tgn:7007521",
        "tgn:7029392"
    ],
    "tgn:id":2763532,
    "tgn:name":"Whale Creek",
    "tgn:placetype":[
        "aat:300008706"
    ]
},
  "bbox": [],
  "geometry": {"coordinates":[-90.5333,47.8833],"type":"Point"}
}
=======
{"geometry":{"type":"Point","coordinates":[-90.533300,47.883300]},"type":"Feature","properties":{"hierarchy":["tgn:2763532","tgn:1000001","tgn:2001014","tgn:7012149","tgn:7007521","tgn:7029392"],"placetype":["aat:300008706"],"id":2763532,"name:xx":"Whale Creek"}}
>>>>>>> 03f74aca74312dbeaf24d7e61306dd6a786dc3d0
