{
  "id": 2153762,
  "type": "Feature",
  "properties": {
    "tgn:hierarchy":[
        "tgn:2153762",
        "tgn:1000001",
        "tgn:2000469",
        "tgn:7012149",
        "tgn:7007250",
        "tgn:7029392"
    ],
    "tgn:id":2153762,
    "tgn:name":"Bear Butte",
    "tgn:placetype":[
        "aat:300008798"
    ]
},
  "bbox": [],
  "geometry": {"coordinates":[-115.8833,46.6833],"type":"Point"}
}