{
  "id": 1051471,
  "type": "Feature",
  "properties": {
    "tgn:hierarchy":[
        "tgn:1051471",
        "tgn:1000004",
        "tgn:7002435",
        "tgn:7011526",
        "tgn:7029392"
    ],
    "tgn:id":1051471,
    "tgn:name":"Chutyr'",
    "tgn:placetype":[
        "aat:300008347"
    ]
},
  "bbox": [],
  "geometry": {"coordinates":[53.25,57.3833],"type":"Point"}
}