{
  "id": 2559649,
  "type": "Feature",
  "properties": {
    "tgn:hierarchy":[
        "tgn:2559649",
        "tgn:1000001",
        "tgn:7012149",
        "tgn:1002636",
        "tgn:7007708",
        "tgn:7029392"
    ],
    "tgn:id":2559649,
    "tgn:name":"Opal Lake",
    "tgn:placetype":[
        "aat:300008680"
    ]
},
  "bbox": [],
  "geometry": {"coordinates":[-122.2167,44.7833],"type":"Point"}
}