{
  "id": 7553694,
  "type": "Feature",
  "properties": {
    "tgn:hierarchy":[
        "tgn:7553694",
        "tgn:1000004",
        "tgn:1001871",
        "tgn:7000198",
        "tgn:7029392"
    ],
    "tgn:id":7553694,
    "tgn:name:en":"Nikur\u0101n",
    "tgn:placetype":[
        "aat:300008347"
    ]
},
  "bbox": [],
  "geometry": {"coordinates":[76.372124,29.437226],"type":"Point"}
}