{
  "id": 2761095,
  "type": "Feature",
  "properties": {
    "tgn:hierarchy":[
        "tgn:2761095",
        "tgn:1002166",
        "tgn:1000001",
        "tgn:7012149",
        "tgn:7007520",
        "tgn:7029392"
    ],
    "tgn:id":2761095,
    "tgn:name":"West Lake",
    "tgn:placetype":[
        "aat:300008680"
    ]
},
  "bbox": [],
  "geometry": {"coordinates":[-85.15,42.45],"type":"Point"}
}