<<<<<<< HEAD
{
  "id": 2761095,
  "type": "Feature",
  "properties": {
    "tgn:hierarchy":[
        "tgn:2761095",
        "tgn:1002166",
        "tgn:1000001",
        "tgn:7012149",
        "tgn:7007520",
        "tgn:7029392"
    ],
    "tgn:id":2761095,
    "tgn:name":"West Lake",
    "tgn:placetype":[
        "aat:300008680"
    ]
},
  "bbox": [],
  "geometry": {"coordinates":[-85.15,42.45],"type":"Point"}
}
=======
{"geometry":{"type":"Point","coordinates":[-85.150000,42.450000]},"type":"Feature","properties":{"hierarchy":["tgn:2761095","tgn:1002166","tgn:1000001","tgn:7012149","tgn:7007520","tgn:7029392"],"placetype":["aat:300008680"],"id":2761095,"name:xx":"West Lake"}}
>>>>>>> 03f74aca74312dbeaf24d7e61306dd6a786dc3d0
