<<<<<<< HEAD
{
  "id": 2251152,
  "type": "Feature",
  "properties": {
    "tgn:hierarchy":[
        "tgn:2251152",
        "tgn:1000001",
        "tgn:7012149",
        "tgn:2002066",
        "tgn:7007826",
        "tgn:7029392"
    ],
    "tgn:id":2251152,
    "tgn:name":"Coma Creek",
    "tgn:placetype":[
        "aat:300008706"
    ]
},
  "bbox": [],
  "geometry": {"coordinates":[-93.75,31.3667],"type":"Point"}
}
=======
{"geometry":{"type":"Point","coordinates":[-93.750000,31.366700]},"type":"Feature","properties":{"hierarchy":["tgn:2251152","tgn:1000001","tgn:7012149","tgn:2002066","tgn:7007826","tgn:7029392"],"placetype":["aat:300008706"],"id":2251152,"name:xx":"Coma Creek"}}
>>>>>>> 03f74aca74312dbeaf24d7e61306dd6a786dc3d0
