{
  "id": 1040824,
  "type": "Feature",
  "properties": {
    "tgn:hierarchy":[
        "tgn:1040824",
        "tgn:1000003",
        "tgn:7003688",
        "tgn:7000084",
        "tgn:7029392"
    ],
    "tgn:id":1040824,
    "tgn:name":"Rantzau",
    "tgn:placetype":[
        "aat:300008347"
    ]
},
  "bbox": [],
  "geometry": {"coordinates":[10.516667,54.25],"type":"Point"}
}