{
  "id": 2176420,
  "type": "Feature",
  "properties": {
    "tgn:hierarchy":[
        "tgn:2176420",
        "tgn:1000001",
        "tgn:7012149",
        "tgn:7007157",
        "tgn:7014005",
        "tgn:7029392"
    ],
    "tgn:id":2176420,
    "tgn:name":"Black John Slough",
    "tgn:placetype":[
        "aat:300008699"
    ]
},
  "bbox": [],
  "geometry": {"coordinates":[-122.5333,38.1333],"type":"Point"}
}