<<<<<<< HEAD
{
  "id": 7371579,
  "type": "Feature",
  "properties": {
    "tgn:hierarchy":[
        "tgn:7371579",
        "tgn:1000001",
        "tgn:7005590",
        "tgn:7005560",
        "tgn:7029392"
    ],
    "tgn:id":7371579,
    "tgn:name":"La Mora",
    "tgn:placetype":[
        "aat:300008347"
    ]
},
  "bbox": [],
  "geometry": {"coordinates":[-102.666667,18.7],"type":"Point"}
}
=======
{"geometry":{"type":"Point","coordinates":[-102.666667,18.700000]},"type":"Feature","properties":{"hierarchy":["tgn:7371579","tgn:1000001","tgn:7005590","tgn:7005560","tgn:7029392"],"placetype":["aat:300008347"],"id":7371579,"name:xx":"La Mora"}}
>>>>>>> 03f74aca74312dbeaf24d7e61306dd6a786dc3d0
