{
  "id": 2778431,
  "type": "Feature",
  "properties": {
    "tgn:hierarchy":[
        "tgn:2778431",
        "tgn:1000001",
        "tgn:7012149",
        "tgn:1002749",
        "tgn:7007240",
        "tgn:7029392"
    ],
    "tgn:id":2778431,
    "tgn:name":"Witherington Spring",
    "tgn:placetype":[
        "aat:300008697"
    ]
},
  "bbox": [],
  "geometry": {"coordinates":[-81.4833,28.7167],"type":"Point"}
}