<<<<<<< HEAD
{
  "id": 7355649,
  "type": "Feature",
  "properties": {
    "tgn:hierarchy":[
        "tgn:7355649",
        "tgn:7005581",
        "tgn:1000001",
        "tgn:7005560",
        "tgn:7029392"
    ],
    "tgn:id":7355649,
    "tgn:name":"Capul\u00edn, Cerro",
    "tgn:placetype":[
        "aat:300008795"
    ]
},
  "bbox": [],
  "geometry": {"coordinates":[-108.616667,27.25],"type":"Point"}
}
=======
{"geometry":{"type":"Point","coordinates":[-108.616667,27.250000]},"type":"Feature","properties":{"hierarchy":["tgn:7355649","tgn:7005581","tgn:1000001","tgn:7005560","tgn:7029392"],"placetype":["aat:300008795"],"id":7355649,"name:xx":"Capul\u00edn, Cerro"}}
>>>>>>> 03f74aca74312dbeaf24d7e61306dd6a786dc3d0
