{
  "id": 2038188,
  "type": "Feature",
  "properties": {
    "tgn:hierarchy":[
        "tgn:2038188",
        "tgn:1000001",
        "tgn:7012149",
        "tgn:2000849",
        "tgn:7007255",
        "tgn:7029392"
    ],
    "tgn:id":2038188,
    "tgn:name":"Cisselville",
    "tgn:placetype":[
        "aat:300008347",
        "aat:300387210"
    ]
},
  "bbox": [],
  "geometry": {"coordinates":[-85.2667,37.6833],"type":"Point"}
}