{
  "id": 1132217,
  "type": "Feature",
  "properties": {
    "tgn:hierarchy":[
        "tgn:1132217",
        "tgn:1000001",
        "tgn:7012149",
        "tgn:7007919",
        "tgn:7029392"
    ],
    "tgn:id":1132217,
    "tgn:name":"Accotink Creek",
    "tgn:placetype":[
        "aat:300008706"
    ]
},
  "bbox": [],
  "geometry": {"coordinates":[-77.3167,38.85],"type":"Point"}
}