{
  "id": 1101927,
  "type": "Feature",
  "properties": {
    "tgn:hierarchy":[
        "tgn:1101927",
        "tgn:1000003",
        "tgn:1000097",
        "tgn:7029392"
    ],
    "tgn:id":1101927,
    "tgn:name":"Vadvetj\u00e5kko Nationalpark",
    "tgn:placetype":[
        "aat:300008189"
    ]
},
  "bbox": [],
  "geometry": {"coordinates":[18.3333,68.5833],"type":"Point"}
}