{
  "id": 2355397,
  "type": "Feature",
  "properties": {
    "tgn:hierarchy":[
        "tgn:2355397",
        "tgn:1000001",
        "tgn:7012149",
        "tgn:7015666",
        "tgn:7007825",
        "tgn:7029392"
    ],
    "tgn:id":2355397,
    "tgn:name":"Goose Branch",
    "tgn:placetype":[
        "aat:300008699"
    ]
},
  "bbox": [],
  "geometry": {"coordinates":[-87.3333,35.95],"type":"Point"}
}