{
  "id": 1005547,
  "type": "Feature",
  "properties": {
    "tgn:hierarchy":[
        "tgn:1005547",
        "tgn:1000004",
        "tgn:7001518",
        "tgn:7000198",
        "tgn:1001895",
        "tgn:1008931",
        "tgn:7029392"
    ],
    "tgn:id":1005547,
    "tgn:name:en":"Santa Cruz",
    "tgn:placetype":[
        "aat:300008347",
        "aat:300000745"
    ]
},
  "bbox": [],
  "geometry": {"coordinates":[72.8333,19.0833],"type":"Point"}
}