{
  "id": 7463562,
  "type": "Feature",
  "properties": {
    "tgn:hierarchy":[
        "tgn:7463562",
        "tgn:7002445",
        "tgn:1000003",
        "tgn:7026515",
        "tgn:7008591",
        "tgn:7029392"
    ],
    "tgn:id":7463562,
    "tgn:name:en":"Humberstone",
    "tgn:placetype":[
        "aat:300008347"
    ]
},
  "bbox": [],
  "geometry": {"coordinates":[-1.066667,52.633333],"type":"Point"}
}