{
  "id": 2786608,
  "type": "Feature",
  "properties": {
    "tgn:hierarchy":[
        "tgn:2786608",
        "tgn:1000001",
        "tgn:7012149",
        "tgn:2001883",
        "tgn:7007825",
        "tgn:7029392"
    ],
    "tgn:id":2786608,
    "tgn:name":"Zachary Branch",
    "tgn:placetype":[
        "aat:300008699"
    ]
},
  "bbox": [],
  "geometry": {"coordinates":[-83.7167,36.15],"type":"Point"}
}