{
  "id": 2587506,
  "type": "Feature",
  "properties": {
    "tgn:hierarchy":[
        "tgn:2587506",
        "tgn:1000001",
        "tgn:2001473",
        "tgn:7012149",
        "tgn:7007709",
        "tgn:7029392"
    ],
    "tgn:id":2587506,
    "tgn:name":"Pleasant Knob",
    "tgn:placetype":[
        "aat:300008798"
    ]
},
  "bbox": [],
  "geometry": {"coordinates":[-82.5333,35.6167],"type":"Point"}
}