{
  "id": 2026040,
  "type": "Feature",
  "properties": {
    "tgn:hierarchy":[
        "tgn:2026040",
        "tgn:1000001",
        "tgn:7012149",
        "tgn:2000472",
        "tgn:7007250",
        "tgn:7029392"
    ],
    "tgn:id":2026040,
    "tgn:name":"Preston",
    "tgn:placetype":[
        "aat:300008347"
    ]
},
  "bbox": [],
  "geometry": {"coordinates":[-111.8667,42.0833],"type":"Point"}
}