<<<<<<< HEAD
{
  "id": 7022564,
  "type": "Feature",
  "properties": {
    "tgn:hierarchy":[
        "tgn:7022564",
        "tgn:1000001",
        "tgn:7012149",
        "tgn:2001244",
        "tgn:7007523",
        "tgn:7029392"
    ],
    "tgn:id":7022564,
    "tgn:name":"Coatsville",
    "tgn:placetype":[
        "aat:300008347"
    ]
},
  "bbox": [],
  "geometry": {"coordinates":[-92.6333,40.5833],"type":"Point"}
}
=======
{"geometry":{"type":"Point","coordinates":[-92.633300,40.583300]},"type":"Feature","properties":{"hierarchy":["tgn:7022564","tgn:1000001","tgn:7012149","tgn:2001244","tgn:7007523","tgn:7029392"],"placetype":["aat:300008347"],"id":7022564,"name:xx":"Coatsville"}}
>>>>>>> 03f74aca74312dbeaf24d7e61306dd6a786dc3d0
