{
  "id": 2247451,
  "type": "Feature",
  "properties": {
    "tgn:hierarchy":[
        "tgn:2247451",
        "tgn:1000001",
        "tgn:7012149",
        "tgn:2001054",
        "tgn:7007521",
        "tgn:7029392"
    ],
    "tgn:id":2247451,
    "tgn:name":"Coffee Lake",
    "tgn:placetype":[
        "aat:300008680"
    ]
},
  "bbox": [],
  "geometry": {"coordinates":[-95.8167,46.65],"type":"Point"}
}