{
  "id": 2324979,
  "type": "Feature",
  "properties": {
    "tgn:hierarchy":[
        "tgn:2324979",
        "tgn:1000001",
        "tgn:7012149",
        "tgn:2002387",
        "tgn:7007923",
        "tgn:7029392"
    ],
    "tgn:id":2324979,
    "tgn:name":"Ferguson Spring",
    "tgn:placetype":[
        "aat:300008697"
    ]
},
  "bbox": [],
  "geometry": {"coordinates":[-104.05,43.7333],"type":"Point"}
}