{
  "id": 2457619,
  "type": "Feature",
  "properties": {
    "tgn:hierarchy":[
        "tgn:2457619",
        "tgn:1000001",
        "tgn:7012149",
        "tgn:1002755",
        "tgn:7007523",
        "tgn:7029392"
    ],
    "tgn:id":2457619,
    "tgn:name":"Little Maries Creek",
    "tgn:placetype":[
        "aat:300008706"
    ]
},
  "bbox": [],
  "geometry": {"coordinates":[-92.1333,38.3333],"type":"Point"}
}