<<<<<<< HEAD
{
  "id": 2400834,
  "type": "Feature",
  "properties": {
    "tgn:hierarchy":[
        "tgn:2400834",
        "tgn:1000001",
        "tgn:7012149",
        "tgn:7007157",
        "tgn:2000189",
        "tgn:7029392"
    ],
    "tgn:id":2400834,
    "tgn:name":"Horse Range Lake",
    "tgn:placetype":[
        "aat:300008680"
    ]
},
  "bbox": [],
  "geometry": {"coordinates":[-123.2,41.4167],"type":"Point"}
}
=======
{"geometry":{"type":"Point","coordinates":[-123.200000,41.416700]},"type":"Feature","properties":{"hierarchy":["tgn:2400834","tgn:1000001","tgn:7012149","tgn:7007157","tgn:2000189","tgn:7029392"],"placetype":["aat:300008680"],"id":2400834,"name:xx":"Horse Range Lake"}}
>>>>>>> 03f74aca74312dbeaf24d7e61306dd6a786dc3d0
