{
  "id": 7053319,
  "type": "Feature",
  "properties": {
    "tgn:hierarchy":[
        "tgn:7053319",
        "tgn:1003460",
        "tgn:1000003",
        "tgn:7009760",
        "tgn:1000080",
        "tgn:7029392"
    ],
    "tgn:id":7053319,
    "tgn:name":"Maestra, Cala",
    "tgn:placetype":[
        "aat:300132317"
    ]
},
  "bbox": [],
  "geometry": {"coordinates":[11.083333,42.25],"type":"Point"}
}