{
  "id": 2309035,
  "type": "Feature",
  "properties": {
    "tgn:hierarchy":[
        "tgn:2309035",
        "tgn:1000001",
        "tgn:7012149",
        "tgn:2000230",
        "tgn:7007158",
        "tgn:7029392"
    ],
    "tgn:id":2309035,
    "tgn:name":"East Road Gulch",
    "tgn:placetype":[
        "aat:300008761"
    ]
},
  "bbox": [],
  "geometry": {"coordinates":[-107.6667,39.3167],"type":"Point"}
}