{
  "id": 2060712,
  "type": "Feature",
  "properties": {
    "tgn:hierarchy":[
        "tgn:2060712",
        "tgn:1000001",
        "tgn:7012149",
        "tgn:2001207",
        "tgn:7007523",
        "tgn:7029392"
    ],
    "tgn:id":2060712,
    "tgn:name":"Tip Top",
    "tgn:placetype":[
        "aat:300008347",
        "aat:300387210"
    ]
},
  "bbox": [],
  "geometry": {"coordinates":[-90.65,37.55],"type":"Point"}
}