{
  "id": 2787357,
  "type": "Feature",
  "properties": {
    "tgn:hierarchy":[
        "tgn:2787357",
        "tgn:1000001",
        "tgn:7012149",
        "tgn:2000890",
        "tgn:7007256",
        "tgn:7029392"
    ],
    "tgn:id":2787357,
    "tgn:name":"de Siard, Bayou",
    "tgn:placetype":[
        "aat:300008699"
    ]
},
  "bbox": [],
  "geometry": {"coordinates":[-92.0333,32.6833],"type":"Point"}
}