{
  "id": 1104817,
  "type": "Feature",
  "properties": {
    "tgn:hierarchy":[
        "tgn:1104817",
        "tgn:7001242",
        "tgn:1000201",
        "tgn:1001213",
        "tgn:7029392"
    ],
    "tgn:id":1104817,
    "tgn:name":"Gurgei, Jabal",
    "tgn:placetype":[
        "aat:300008795"
    ]
},
  "bbox": [],
  "geometry": {"coordinates":[24.3333,13.8667],"type":"Point"}
}