{
  "id": 1034256,
  "type": "Feature",
  "properties": {
    "tgn:hierarchy":[
        "tgn:1034256",
        "tgn:1000003",
        "tgn:7002883",
        "tgn:1000070",
        "tgn:7029392"
    ],
    "tgn:id":1034256,
    "tgn:name":"Mareil-le-Guyon",
    "tgn:placetype":[
        "aat:300008347"
    ]
},
  "bbox": [],
  "geometry": {"coordinates":[1.85,48.7833],"type":"Point"}
}