{
  "id": 2160194,
  "type": "Feature",
  "properties": {
    "tgn:hierarchy":[
        "tgn:2160194",
        "tgn:7002659",
        "tgn:1000001",
        "tgn:7012149",
        "tgn:2000041",
        "tgn:7029392"
    ],
    "tgn:id":2160194,
    "tgn:name":"Beechwood Acres",
    "tgn:placetype":[
        "aat:300008347"
    ]
},
  "bbox": [],
  "geometry": {"coordinates":[-87.1667,34.75],"type":"Point"}
}