{
  "id": 2273167,
  "type": "Feature",
  "properties": {
    "tgn:hierarchy":[
        "tgn:2273167",
        "tgn:1000001",
        "tgn:7016172",
        "tgn:7012149",
        "tgn:2000137",
        "tgn:7029392"
    ],
    "tgn:id":2273167,
    "tgn:name":"Cypert Mountain",
    "tgn:placetype":[
        "aat:300008798"
    ]
},
  "bbox": [],
  "geometry": {"coordinates":[-91.9667,35.9667],"type":"Point"}
}