{
  "id": 7587169,
  "type": "Feature",
  "properties": {
    "tgn:hierarchy":[
        "tgn:7587169",
        "tgn:1000004",
        "tgn:7000198",
        "tgn:7000799",
        "tgn:7029392"
    ],
    "tgn:id":7587169,
    "tgn:name:en":"Chhandna Deh Nau\u0101b\u0101d",
    "tgn:placetype":[
        "aat:300008347"
    ]
},
  "bbox": [],
  "geometry": {"coordinates":[74.72486,34.174087],"type":"Point"}
}