{
  "id": 7497268,
  "type": "Feature",
  "properties": {
    "tgn:hierarchy":[
        "tgn:7497268",
        "tgn:1000004",
        "tgn:1000959",
        "tgn:1000141",
        "tgn:7029392"
    ],
    "tgn:id":7497268,
    "tgn:name":"Qingque",
    "tgn:placetype":[
        "aat:300008347"
    ]
},
  "bbox": [],
  "geometry": {"coordinates":[121.565198,25.138836],"type":"Point"}
}