{
  "id": 2652861,
  "type": "Feature",
  "properties": {
    "tgn:hierarchy":[
        "tgn:2652861",
        "tgn:1000001",
        "tgn:7012149",
        "tgn:2001236",
        "tgn:7007523",
        "tgn:7029392"
    ],
    "tgn:id":2652861,
    "tgn:name":"Session Spring",
    "tgn:placetype":[
        "aat:300008697"
    ]
},
  "bbox": [],
  "geometry": {"coordinates":[-90.9833,37.4333],"type":"Point"}
}