{
  "id": 2147652,
  "type": "Feature",
  "properties": {
    "tgn:hierarchy":[
        "tgn:2147652",
        "tgn:1002808",
        "tgn:1000001",
        "tgn:7012149",
        "tgn:7007711",
        "tgn:7029392"
    ],
    "tgn:id":2147652,
    "tgn:name":"Barden Reservoir",
    "tgn:placetype":[
        "aat:300006191"
    ]
},
  "bbox": [],
  "geometry": {"coordinates":[-71.6667,41.7833],"type":"Point"}
}