{
  "id": 7431713,
  "type": "Feature",
  "properties": {
    "tgn:hierarchy":[
        "tgn:7431713",
        "tgn:1000001",
        "tgn:7005595",
        "tgn:7005560",
        "tgn:7029392"
    ],
    "tgn:id":7431713,
    "tgn:name":"La Rastra",
    "tgn:placetype":[
        "aat:300008347"
    ]
},
  "bbox": [],
  "geometry": {"coordinates":[-105.516667,23.066667],"type":"Point"}
}