{
  "id": 2235027,
  "type": "Feature",
  "properties": {
    "tgn:hierarchy":[
        "tgn:2235027",
        "tgn:1000001",
        "tgn:7012149",
        "tgn:1002449",
        "tgn:7013961",
        "tgn:7029392"
    ],
    "tgn:id":2235027,
    "tgn:name":"Cherry Lake",
    "tgn:placetype":[
        "aat:300006191"
    ]
},
  "bbox": [],
  "geometry": {"coordinates":[-80.5833,40.5167],"type":"Point"}
}