<<<<<<< HEAD
{
  "id": 7356274,
  "type": "Feature",
  "properties": {
    "tgn:hierarchy":[
        "tgn:7356274",
        "tgn:1000001",
        "tgn:1001906",
        "tgn:7005560",
        "tgn:7029392"
    ],
    "tgn:id":7356274,
    "tgn:name":"Calera, Cerro la",
    "tgn:placetype":[
        "aat:300008777"
    ]
},
  "bbox": [],
  "geometry": {"coordinates":[-104.2,21.416667],"type":"Point"}
}
=======
{"geometry":{"type":"Point","coordinates":[-104.200000,21.416667]},"type":"Feature","properties":{"hierarchy":["tgn:7356274","tgn:1000001","tgn:1001906","tgn:7005560","tgn:7029392"],"placetype":["aat:300008777"],"id":7356274,"name:xx":"Calera, Cerro la"}}
>>>>>>> 03f74aca74312dbeaf24d7e61306dd6a786dc3d0
