{
  "id": 2200114,
  "type": "Feature",
  "properties": {
    "tgn:hierarchy":[
        "tgn:2200114",
        "tgn:1000001",
        "tgn:7012149",
        "tgn:2001207",
        "tgn:7007523",
        "tgn:7029392"
    ],
    "tgn:id":2200114,
    "tgn:name":"Brushy Creek",
    "tgn:placetype":[
        "aat:300008706"
    ]
},
  "bbox": [],
  "geometry": {"coordinates":[-90.6333,37.35],"type":"Point"}
}