{
  "id": 7551968,
  "type": "Feature",
  "properties": {
    "tgn:hierarchy":[
        "tgn:7551968",
        "tgn:7001819",
        "tgn:1000004",
        "tgn:7000198",
        "tgn:7029392"
    ],
    "tgn:id":7551968,
    "tgn:name:en":"Demw\u0113",
    "tgn:placetype":[
        "aat:300008347"
    ]
},
  "bbox": [],
  "geometry": {"coordinates":[96.295063,27.899164],"type":"Point"}
}