{
  "id": 7277674,
  "type": "Feature",
  "properties": {
    "tgn:hierarchy":[
        "tgn:7277674",
        "tgn:1001692",
        "tgn:1000049",
        "tgn:1000002",
        "tgn:7029392"
    ],
    "tgn:id":7277674,
    "tgn:name":"Ventrenco, Estero",
    "tgn:placetype":[
        "aat:300008699"
    ]
},
  "bbox": [],
  "geometry": {"coordinates":[-72.033333,-38.483333],"type":"Point"}
}