{
  "id": 7178678,
  "type": "Feature",
  "properties": {
    "tgn:hierarchy":[
        "tgn:7178678",
        "tgn:7003669",
        "tgn:1000003",
        "tgn:7000084",
        "tgn:7029392"
    ],
    "tgn:id":7178678,
    "tgn:name":"Hammerstetten",
    "tgn:placetype":[
        "aat:300008347"
    ]
},
  "bbox": [],
  "geometry": {"coordinates":[10.366667,48.416667],"type":"Point"}
}