{
  "id": 7060024,
  "type": "Feature",
  "properties": {
    "tgn:hierarchy":[
        "tgn:7060024",
        "tgn:1000003",
        "tgn:7003678",
        "tgn:7000084",
        "tgn:7029392"
    ],
    "tgn:id":7060024,
    "tgn:name":"Alheim",
    "tgn:placetype":[
        "aat:300008347"
    ]
},
  "bbox": [],
  "geometry": {"coordinates":[9.666667,51.033333],"type":"Point"}
}