{
  "id": 7221971,
  "type": "Feature",
  "properties": {
    "tgn:hierarchy":[
        "tgn:7221971",
        "tgn:1042193",
        "tgn:7002705",
        "tgn:1000003",
        "tgn:1000074",
        "tgn:7029392"
    ],
    "tgn:id":7221971,
    "tgn:name":"Panag\u00eda",
    "tgn:placetype":[
        "aat:300008347"
    ]
},
  "bbox": [],
  "geometry": {"coordinates":[20.683333,39.283333],"type":"Point"}
}