{
  "id": 7578930,
  "type": "Feature",
  "properties": {
    "tgn:hierarchy":[
        "tgn:7578930",
        "tgn:1001828",
        "tgn:1000004",
        "tgn:7000198",
        "tgn:7029392"
    ],
    "tgn:id":7578930,
    "tgn:name:en":"Shivannaguda",
    "tgn:placetype":[
        "aat:300008347"
    ]
},
  "bbox": [],
  "geometry": {"coordinates":[78.889444,17.006111],"type":"Point"}
}