{
  "id": 2466899,
  "type": "Feature",
  "properties": {
    "tgn:hierarchy":[
        "tgn:2466899",
        "tgn:1000001",
        "tgn:7012149",
        "tgn:7007157",
        "tgn:1002828",
        "tgn:7029392"
    ],
    "tgn:id":2466899,
    "tgn:name":"Long Canyon",
    "tgn:placetype":[
        "aat:300008761"
    ]
},
  "bbox": [],
  "geometry": {"coordinates":[-117.05,33.5167],"type":"Point"}
}