{
  "id": 7066531,
  "type": "Feature",
  "properties": {
    "tgn:hierarchy":[
        "tgn:7066531",
        "tgn:1000003",
        "tgn:7003678",
        "tgn:7000084",
        "tgn:7029392"
    ],
    "tgn:id":7066531,
    "tgn:name":"Uengsterode",
    "tgn:placetype":[
        "aat:300008347"
    ]
},
  "bbox": [],
  "geometry": {"coordinates":[9.816667,51.25],"type":"Point"}
}