{
  "id": 1002632,
  "type": "Feature",
  "properties": {
    "tgn:hierarchy":[
        "tgn:1002632",
        "tgn:1000001",
        "tgn:7012149",
        "tgn:7007251",
        "tgn:7029392"
    ],
    "tgn:id":1002632,
    "tgn:name":"Marion",
    "tgn:placetype":[
        "aat:300387145",
        "aat:300000771"
    ]
},
  "bbox": [],
  "geometry": {"coordinates":[-88.9333,38.65],"type":"Point"}
}