{
  "id": 2508964,
  "type": "Feature",
  "properties": {
    "tgn:hierarchy":[
        "tgn:2508964",
        "tgn:1000001",
        "tgn:2002369",
        "tgn:7012149",
        "tgn:7007923",
        "tgn:7029392"
    ],
    "tgn:id":2508964,
    "tgn:name":"Middle Fork Dry Fork Cheyenne River",
    "tgn:placetype":[
        "aat:300008707"
    ]
},
  "bbox": [],
  "geometry": {"coordinates":[-105.95,43.0833],"type":"Point"}
}