{
  "id": 2781955,
  "type": "Feature",
  "properties": {
    "tgn:hierarchy":[
        "tgn:2781955",
        "tgn:1000001",
        "tgn:7012149",
        "tgn:1002472",
        "tgn:7007568",
        "tgn:7029392"
    ],
    "tgn:id":2781955,
    "tgn:name":"Woods Lake",
    "tgn:placetype":[
        "aat:300008680"
    ]
},
  "bbox": [],
  "geometry": {"coordinates":[-74.95,43.8667],"type":"Point"}
}