{
  "id": 2016846,
  "type": "Feature",
  "properties": {
    "tgn:hierarchy":[
        "tgn:2016846",
        "tgn:1000001",
        "tgn:1002601",
        "tgn:7012149",
        "tgn:7007159",
        "tgn:7029392"
    ],
    "tgn:id":2016846,
    "tgn:name":"Ellsworth",
    "tgn:placetype":[
        "aat:300008347",
        "aat:300387210"
    ]
},
  "bbox": [],
  "geometry": {"coordinates":[-73.4167,41.8167],"type":"Point"}
}