{
  "id": 7066437,
  "type": "Feature",
  "properties": {
    "tgn:hierarchy":[
        "tgn:7066437",
        "tgn:7000096",
        "tgn:1000003",
        "tgn:7000084",
        "tgn:7029392"
    ],
    "tgn:id":7066437,
    "tgn:name":"Uhlenhof",
    "tgn:placetype":[
        "aat:300000206"
    ]
},
  "bbox": [],
  "geometry": {"coordinates":[13.766667,53.416667],"type":"Point"}
}