{
  "id": 7014245,
  "type": "Feature",
  "properties": {
    "tgn:hierarchy":[
        "tgn:7014245",
        "tgn:1002201",
        "tgn:1000001",
        "tgn:7012149",
        "tgn:7007517",
        "tgn:7029392"
    ],
    "tgn:id":7014245,
    "tgn:name":"Norton",
    "tgn:placetype":[
        "aat:300008347"
    ]
},
  "bbox": [],
  "geometry": {"coordinates":[-71.1833,41.9667],"type":"Point"}
}