{
  "id": 7368202,
  "type": "Feature",
  "properties": {
    "tgn:hierarchy":[
        "tgn:7368202",
        "tgn:1000001",
        "tgn:7005601",
        "tgn:7005560",
        "tgn:7029392"
    ],
    "tgn:id":7368202,
    "tgn:name":"Iglesias, Sierra de las",
    "tgn:placetype":[
        "aat:300008795"
    ]
},
  "bbox": [],
  "geometry": {"coordinates":[-101.666667,24.316667],"type":"Point"}
}