<<<<<<< HEAD
{
  "id": 2333323,
  "type": "Feature",
  "properties": {
    "tgn:hierarchy":[
        "tgn:2333323",
        "tgn:1000001",
        "tgn:7012149",
        "tgn:2001226",
        "tgn:7007523",
        "tgn:7029392"
    ],
    "tgn:id":2333323,
    "tgn:name":"Fogey Cave Hollow",
    "tgn:placetype":[
        "aat:300008761"
    ]
},
  "bbox": [],
  "geometry": {"coordinates":[-92.15,36.6667],"type":"Point"}
}
=======
{"geometry":{"type":"Point","coordinates":[-92.150000,36.666700]},"type":"Feature","properties":{"hierarchy":["tgn:2333323","tgn:1000001","tgn:7012149","tgn:2001226","tgn:7007523","tgn:7029392"],"placetype":["aat:300008761"],"id":2333323,"name:xx":"Fogey Cave Hollow"}}
>>>>>>> 03f74aca74312dbeaf24d7e61306dd6a786dc3d0
