{
  "id": 7567329,
  "type": "Feature",
  "properties": {
    "tgn:hierarchy":[
        "tgn:7567329",
        "tgn:1000004",
        "tgn:1001871",
        "tgn:7000198",
        "tgn:7029392"
    ],
    "tgn:id":7567329,
    "tgn:name:en":"S\u0101mar Gop\u0101lpur Railroad Station",
    "tgn:placetype":[
        "aat:300007783"
    ]
},
  "bbox": [],
  "geometry": {"coordinates":[76.518375,28.958995],"type":"Point"}
}