{
  "id": 7227379,
  "type": "Feature",
  "properties": {
    "tgn:hierarchy":[
        "tgn:7227379",
        "tgn:7011330",
        "tgn:7002674",
        "tgn:1000003",
        "tgn:1000074",
        "tgn:7029392"
    ],
    "tgn:id":7227379,
    "tgn:name":"Il\u00edas, \u00c1kra",
    "tgn:placetype":[
        "aat:300008850"
    ]
},
  "bbox": [],
  "geometry": {"coordinates":[26.566667,37.266667],"type":"Point"}
}