<<<<<<< HEAD
{
  "id": 2333336,
  "type": "Feature",
  "properties": {
    "tgn:hierarchy":[
        "tgn:2333336",
        "tgn:1000001",
        "tgn:2000461",
        "tgn:7012149",
        "tgn:7007250",
        "tgn:7029392"
    ],
    "tgn:id":2333336,
    "tgn:name":"Fogg Hill",
    "tgn:placetype":[
        "aat:300008798"
    ]
},
  "bbox": [],
  "geometry": {"coordinates":[-111.1167,43.5],"type":"Point"}
}
=======
{"geometry":{"type":"Point","coordinates":[-111.116700,43.500000]},"type":"Feature","properties":{"hierarchy":["tgn:2333336","tgn:1000001","tgn:2000461","tgn:7012149","tgn:7007250","tgn:7029392"],"placetype":["aat:300008798"],"id":2333336,"name:xx":"Fogg Hill"}}
>>>>>>> 03f74aca74312dbeaf24d7e61306dd6a786dc3d0
