{
  "id": 2510480,
  "type": "Feature",
  "properties": {
    "tgn:hierarchy":[
        "tgn:2510480",
        "tgn:1000001",
        "tgn:7012149",
        "tgn:7007826",
        "tgn:7029392"
    ],
    "tgn:id":2510480,
    "tgn:name":"Middle Sulphur River",
    "tgn:placetype":[
        "aat:300008707"
    ]
},
  "bbox": [],
  "geometry": {"coordinates":[-96.05,33.3833],"type":"Point"}
}