{
  "id": 2560603,
  "type": "Feature",
  "properties": {
    "tgn:hierarchy":[
        "tgn:2560603",
        "tgn:7006450",
        "tgn:1000001",
        "tgn:7012149",
        "tgn:2124014",
        "tgn:7029392"
    ],
    "tgn:id":2560603,
    "tgn:name":"Oregon Creek",
    "tgn:placetype":[
        "aat:300008706"
    ]
},
  "bbox": [],
  "geometry": {"coordinates":[-163.3833,65.9667],"type":"Point"}
}