<<<<<<< HEAD
{
  "id": 7023001,
  "type": "Feature",
  "properties": {
    "tgn:hierarchy":[
        "tgn:7023001",
        "tgn:1000001",
        "tgn:7012149",
        "tgn:7007248",
        "tgn:7029392"
    ],
    "tgn:id":7023001,
    "tgn:name":"Georgia Marble Co. Lake",
    "tgn:placetype":[
        "aat:300006191"
    ]
},
  "bbox": [],
  "geometry": {"coordinates":[-84.3667,34.3667],"type":"Point"}
}
=======
{"geometry":{"type":"Point","coordinates":[-84.366700,34.366700]},"type":"Feature","properties":{"hierarchy":["tgn:7023001","tgn:1000001","tgn:7012149","tgn:7007248","tgn:7029392"],"placetype":["aat:300006191"],"id":7023001,"name:xx":"Georgia Marble Co. Lake"}}
>>>>>>> 03f74aca74312dbeaf24d7e61306dd6a786dc3d0
