{
  "id": 7023001,
  "type": "Feature",
  "properties": {
    "tgn:hierarchy":[
        "tgn:7023001",
        "tgn:1000001",
        "tgn:7012149",
        "tgn:7007248",
        "tgn:7029392"
    ],
    "tgn:id":7023001,
    "tgn:name":"Georgia Marble Co. Lake",
    "tgn:placetype":[
        "aat:300006191"
    ]
},
  "bbox": [],
  "geometry": {"coordinates":[-84.3667,34.3667],"type":"Point"}
}