{
  "id": 1065036,
  "type": "Feature",
  "properties": {
    "tgn:hierarchy":[
        "tgn:1065036",
        "tgn:1000003",
        "tgn:7017290",
        "tgn:7006663",
        "tgn:7029392"
    ],
    "tgn:id":1065036,
    "tgn:name":"Jastrebarsko",
    "tgn:placetype":[
        "aat:300008347"
    ]
},
  "bbox": [],
  "geometry": {"coordinates":[15.65,45.6833],"type":"Point"}
}