{
  "id": 7481202,
  "type": "Feature",
  "properties": {
    "tgn:hierarchy":[
        "tgn:7481202",
        "tgn:1000004",
        "tgn:7471332",
        "tgn:1000141",
        "tgn:7029392"
    ],
    "tgn:id":7481202,
    "tgn:name":"Zhiwo",
    "tgn:placetype":[
        "aat:300008347"
    ]
},
  "bbox": [],
  "geometry": {"coordinates":[121.079722,24.717222],"type":"Point"}
}