{
  "id": 7354582,
  "type": "Feature",
  "properties": {
    "tgn:hierarchy":[
        "tgn:7354582",
        "tgn:1000001",
        "tgn:1001937",
        "tgn:7005560",
        "tgn:7029392"
    ],
    "tgn:id":7354582,
    "tgn:name":"Canc\u00fan, Isla",
    "tgn:placetype":[
        "aat:300008791"
    ]
},
  "bbox": [],
  "geometry": {"coordinates":[-86.766667,21.083333],"type":"Point"}
}