{
  "id": 2169126,
  "type": "Feature",
  "properties": {
    "tgn:hierarchy":[
        "tgn:2169126",
        "tgn:7006450",
        "tgn:1000001",
        "tgn:7012149",
        "tgn:2000085",
        "tgn:7029392"
    ],
    "tgn:id":2169126,
    "tgn:name":"Big John Lake",
    "tgn:placetype":[
        "aat:300008680"
    ]
},
  "bbox": [],
  "geometry": {"coordinates":[-142.1667,63.0667],"type":"Point"}
}