<<<<<<< HEAD
{
  "id": 2252805,
  "type": "Feature",
  "properties": {
    "tgn:hierarchy":[
        "tgn:2252805",
        "tgn:1000001",
        "tgn:7012149",
        "tgn:2001516",
        "tgn:7007709",
        "tgn:7029392"
    ],
    "tgn:id":2252805,
    "tgn:name":"Connor Ridge",
    "tgn:placetype":[
        "aat:300266640"
    ]
},
  "bbox": [],
  "geometry": {"coordinates":[-82.5667,35.8333],"type":"Point"}
}
=======
{"geometry":{"type":"Point","coordinates":[-82.566700,35.833300]},"type":"Feature","properties":{"hierarchy":["tgn:2252805","tgn:1000001","tgn:7012149","tgn:2001516","tgn:7007709","tgn:7029392"],"placetype":["aat:300266640"],"id":2252805,"name:xx":"Connor Ridge"}}
>>>>>>> 03f74aca74312dbeaf24d7e61306dd6a786dc3d0
