{
  "id": 7427135,
  "type": "Feature",
  "properties": {
    "tgn:hierarchy":[
        "tgn:7427135",
        "tgn:1000001",
        "tgn:7005601",
        "tgn:7005560",
        "tgn:7029392"
    ],
    "tgn:id":7427135,
    "tgn:name":"El Naranjo",
    "tgn:placetype":[
        "aat:300008347"
    ]
},
  "bbox": [],
  "geometry": {"coordinates":[-103.466667,23.466667],"type":"Point"}
}