{
  "id": 7242311,
  "type": "Feature",
  "properties": {
    "tgn:hierarchy":[
        "tgn:7242311",
        "tgn:7003466",
        "tgn:1000003",
        "tgn:1000063",
        "tgn:4012014",
        "tgn:7029392"
    ],
    "tgn:id":7242311,
    "tgn:name":"Le Pachis",
    "tgn:placetype":[
        "aat:300008347"
    ]
},
  "bbox": [],
  "geometry": {"coordinates":[5.007969,50.44761],"type":"Point"}
}