<<<<<<< HEAD
{
  "id": 7025992,
  "type": "Feature",
  "properties": {
    "tgn:hierarchy":[
        "tgn:7025992",
        "tgn:7002445",
        "tgn:1000003",
        "tgn:7011961",
        "tgn:7008591",
        "tgn:7029392"
    ],
    "tgn:id":7025992,
    "tgn:name:ang":"Tolre",
    "tgn:placetype":[
        "aat:300008347",
        "aat:300008372"
    ]
},
  "bbox": [],
  "geometry": {"coordinates":[-2.6833,50.8],"type":"Point"}
}
=======
{"geometry":{"type":"Point","coordinates":[-2.683300,50.800000]},"type":"Feature","properties":{"hierarchy":["tgn:7025992","tgn:7002445","tgn:1000003","tgn:7011961","tgn:7008591","tgn:7029392"],"placetype":["aat:300008347","aat:300008372"],"id":7025992,"name:ang":"Tolre"}}
>>>>>>> 03f74aca74312dbeaf24d7e61306dd6a786dc3d0
