{
  "id": 7226057,
  "type": "Feature",
  "properties": {
    "tgn:hierarchy":[
        "tgn:7226057",
        "tgn:7002681",
        "tgn:7001395",
        "tgn:1000003",
        "tgn:1000074",
        "tgn:7029392"
    ],
    "tgn:id":7226057,
    "tgn:name":"Mounikh\u00edas, Lim\u00edn",
    "tgn:placetype":[
        "aat:300008678"
    ]
},
  "bbox": [],
  "geometry": {"coordinates":[23.666667,37.933333],"type":"Point"}
}