{
  "id": 2186218,
  "type": "Feature",
  "properties": {
    "tgn:hierarchy":[
        "tgn:2186218",
        "tgn:1000001",
        "tgn:2001411",
        "tgn:7012149",
        "tgn:7007526",
        "tgn:7029392"
    ],
    "tgn:id":2186218,
    "tgn:name":"Bonanza Creek",
    "tgn:placetype":[
        "aat:300008706"
    ]
},
  "bbox": [],
  "geometry": {"coordinates":[-115.3833,41.8333],"type":"Point"}
}