{
  "id": 2417513,
  "type": "Feature",
  "properties": {
    "tgn:hierarchy":[
        "tgn:2417513",
        "tgn:1000001",
        "tgn:7012149",
        "tgn:1002391",
        "tgn:7007826",
        "tgn:7029392"
    ],
    "tgn:id":2417513,
    "tgn:name":"Jackson Branch",
    "tgn:placetype":[
        "aat:300008699"
    ]
},
  "bbox": [],
  "geometry": {"coordinates":[-96.4333,31.7833],"type":"Point"}
}