<<<<<<< HEAD
{
  "id": 2767786,
  "type": "Feature",
  "properties": {
    "tgn:hierarchy":[
        "tgn:2767786",
        "tgn:7002659",
        "tgn:1000001",
        "tgn:7012149",
        "tgn:2000029",
        "tgn:7029392"
    ],
    "tgn:id":2767786,
    "tgn:name":"Whitehead Spring Branch",
    "tgn:placetype":[
        "aat:300008699"
    ]
},
  "bbox": [],
  "geometry": {"coordinates":[-87.8,34.3167],"type":"Point"}
}
=======
{"geometry":{"type":"Point","coordinates":[-87.800000,34.316700]},"type":"Feature","properties":{"hierarchy":["tgn:2767786","tgn:7002659","tgn:1000001","tgn:7012149","tgn:2000029","tgn:7029392"],"placetype":["aat:300008699"],"id":2767786,"name:xx":"Whitehead Spring Branch"}}
>>>>>>> 03f74aca74312dbeaf24d7e61306dd6a786dc3d0
