{
  "id": 2341786,
  "type": "Feature",
  "properties": {
    "tgn:hierarchy":[
        "tgn:2341786",
        "tgn:1000001",
        "tgn:7012149",
        "tgn:2000333",
        "tgn:7007248",
        "tgn:7029392"
    ],
    "tgn:id":2341786,
    "tgn:name":"Frosty Mountain",
    "tgn:placetype":[
        "aat:300008798"
    ]
},
  "bbox": [],
  "geometry": {"coordinates":[-84.2167,34.5833],"type":"Point"}
}