{
  "id": 7072280,
  "type": "Feature",
  "properties": {
    "tgn:hierarchy":[
        "tgn:7072280",
        "tgn:7003669",
        "tgn:1000003",
        "tgn:7000084",
        "tgn:7029392"
    ],
    "tgn:id":7072280,
    "tgn:name":"Sulz-Berg",
    "tgn:placetype":[
        "aat:300008777"
    ]
},
  "bbox": [],
  "geometry": {"coordinates":[9.183333,49.916667],"type":"Point"}
}