{
  "id": 2652606,
  "type": "Feature",
  "properties": {
    "tgn:hierarchy":[
        "tgn:2652606",
        "tgn:1000001",
        "tgn:2000463",
        "tgn:7012149",
        "tgn:7007250",
        "tgn:7029392"
    ],
    "tgn:id":2652606,
    "tgn:name":"Sentinel, The",
    "tgn:placetype":[
        "aat:300008798"
    ]
},
  "bbox": [],
  "geometry": {"coordinates":[-113.4833,43.3667],"type":"Point"}
}