<<<<<<< HEAD
{
  "id": 2252623,
  "type": "Feature",
  "properties": {
    "tgn:hierarchy":[
        "tgn:2252623",
        "tgn:1000001",
        "tgn:1002269",
        "tgn:7012149",
        "tgn:7007240",
        "tgn:7029392"
    ],
    "tgn:id":2252623,
    "tgn:name":"Connell Lake",
    "tgn:placetype":[
        "aat:300008680"
    ]
},
  "bbox": [],
  "geometry": {"coordinates":[-82.3333,28.8667],"type":"Point"}
}
=======
{"geometry":{"type":"Point","coordinates":[-82.333300,28.866700]},"type":"Feature","properties":{"hierarchy":["tgn:2252623","tgn:1000001","tgn:1002269","tgn:7012149","tgn:7007240","tgn:7029392"],"placetype":["aat:300008680"],"id":2252623,"name:xx":"Connell Lake"}}
>>>>>>> 03f74aca74312dbeaf24d7e61306dd6a786dc3d0
