{
  "id": 1096975,
  "type": "Feature",
  "properties": {
    "tgn:hierarchy":[
        "tgn:1096975",
        "tgn:7000490",
        "tgn:1000006",
        "tgn:7001830",
        "tgn:7029392"
    ],
    "tgn:id":1096975,
    "tgn:name":"Gleneagle",
    "tgn:placetype":[
        "aat:300008347"
    ]
},
  "bbox": [],
  "geometry": {"coordinates":[152.9833,-27.95],"type":"Point"}
}