{
  "id": 7388305,
  "type": "Feature",
  "properties": {
    "tgn:hierarchy":[
        "tgn:7388305",
        "tgn:1000001",
        "tgn:7005595",
        "tgn:7005560",
        "tgn:7029392"
    ],
    "tgn:id":7388305,
    "tgn:name":"Potrero de los Vegas",
    "tgn:placetype":[
        "aat:300008347"
    ]
},
  "bbox": [],
  "geometry": {"coordinates":[-107.283333,25.35],"type":"Point"}
}