{
  "id": 2283892,
  "type": "Feature",
  "properties": {
    "tgn:hierarchy":[
        "tgn:2283892",
        "tgn:1000001",
        "tgn:2000460",
        "tgn:7012149",
        "tgn:7007250",
        "tgn:7029392"
    ],
    "tgn:id":2283892,
    "tgn:name":"Dennick Lake",
    "tgn:placetype":[
        "aat:300008680"
    ]
},
  "bbox": [],
  "geometry": {"coordinates":[-116.3833,48.4833],"type":"Point"}
}