<<<<<<< HEAD
{
  "id": 7111455,
  "type": "Feature",
  "properties": {
    "tgn:hierarchy":[
        "tgn:7111455",
        "tgn:1000003",
        "tgn:7003676",
        "tgn:7000084",
        "tgn:7029392"
    ],
    "tgn:id":7111455,
    "tgn:name":"Ricklinger Moor",
    "tgn:placetype":[
        "aat:300008903"
    ]
},
  "bbox": [],
  "geometry": {"coordinates":[9.55,52.433333],"type":"Point"}
}
=======
{"geometry":{"type":"Point","coordinates":[9.550000,52.433333]},"type":"Feature","properties":{"hierarchy":["tgn:7111455","tgn:1000003","tgn:7003676","tgn:7000084","tgn:7029392"],"placetype":["aat:300008903"],"id":7111455,"name:xx":"Ricklinger Moor"}}
>>>>>>> 03f74aca74312dbeaf24d7e61306dd6a786dc3d0
