{
  "id": 2204831,
  "type": "Feature",
  "properties": {
    "tgn:hierarchy":[
        "tgn:2204831",
        "tgn:1000001",
        "tgn:7012149",
        "tgn:2001456",
        "tgn:7007566",
        "tgn:7029392"
    ],
    "tgn:id":2204831,
    "tgn:name":"Buffalo Tank",
    "tgn:placetype":[
        "aat:300006191"
    ]
},
  "bbox": [],
  "geometry": {"coordinates":[-107.2333,33.8167],"type":"Point"}
}