{
  "id": 2196465,
  "type": "Feature",
  "properties": {
    "tgn:hierarchy":[
        "tgn:2196465",
        "tgn:1000001",
        "tgn:7013686",
        "tgn:7012149",
        "tgn:7007517",
        "tgn:7029392"
    ],
    "tgn:id":2196465,
    "tgn:name":"Bronson Brook",
    "tgn:placetype":[
        "aat:300008699"
    ]
},
  "bbox": [],
  "geometry": {"coordinates":[-72.9667,42.45],"type":"Point"}
}