{
  "id": 2579395,
  "type": "Feature",
  "properties": {
    "tgn:hierarchy":[
        "tgn:2579395",
        "tgn:1000001",
        "tgn:7012149",
        "tgn:2001067",
        "tgn:7007521",
        "tgn:7029392"
    ],
    "tgn:id":2579395,
    "tgn:name":"Pickerel Lake",
    "tgn:placetype":[
        "aat:300008680"
    ]
},
  "bbox": [],
  "geometry": {"coordinates":[-93.0167,47.6833],"type":"Point"}
}