{
  "id": 2589298,
  "type": "Feature",
  "properties": {
    "tgn:hierarchy":[
        "tgn:2589298",
        "tgn:1000001",
        "tgn:7014449",
        "tgn:7012149",
        "tgn:7007565",
        "tgn:7029392"
    ],
    "tgn:id":2589298,
    "tgn:name":"Point Airy",
    "tgn:placetype":[
        "aat:300008347"
    ]
},
  "bbox": [],
  "geometry": {"coordinates":[-75.3167,39.6667],"type":"Point"}
}