{
  "id": 7061029,
  "type": "Feature",
  "properties": {
    "tgn:hierarchy":[
        "tgn:7061029",
        "tgn:1000003",
        "tgn:7003676",
        "tgn:7000084",
        "tgn:7029392"
    ],
    "tgn:id":7061029,
    "tgn:name":"Bahnhof Bad Nenndorf",
    "tgn:placetype":[
        "aat:300007783"
    ]
},
  "bbox": [],
  "geometry": {"coordinates":[9.378056,52.345],"type":"Point"}
}