{
  "id": 1135396,
  "type": "Feature",
  "properties": {
    "tgn:hierarchy":[
        "tgn:1135396",
        "tgn:1000001",
        "tgn:7019013",
        "tgn:7012149",
        "tgn:7007251",
        "tgn:7029392"
    ],
    "tgn:id":1135396,
    "tgn:name":"Spring Brook",
    "tgn:placetype":[
        "aat:300008703"
    ]
},
  "bbox": [],
  "geometry": {"coordinates":[-88.0333,41.95],"type":"Point"}
}