{
  "id": 2550314,
  "type": "Feature",
  "properties": {
    "tgn:hierarchy":[
        "tgn:2550314",
        "tgn:1000001",
        "tgn:7012149",
        "tgn:7007158",
        "tgn:2000242",
        "tgn:7029392"
    ],
    "tgn:id":2550314,
    "tgn:name":"Northside Reservoir",
    "tgn:placetype":[
        "aat:300006191"
    ]
},
  "bbox": [],
  "geometry": {"coordinates":[-104.6333,38.2667],"type":"Point"}
}