{
  "id": 7585869,
  "type": "Feature",
  "properties": {
    "tgn:hierarchy":[
        "tgn:7585869",
        "tgn:1000004",
        "tgn:7000198",
        "tgn:7000799",
        "tgn:7029392"
    ],
    "tgn:id":7585869,
    "tgn:name:en":"Bumai",
    "tgn:placetype":[
        "aat:300008347"
    ]
},
  "bbox": [],
  "geometry": {"coordinates":[74.422846,34.360698],"type":"Point"}
}