{
  "id": 2242014,
  "type": "Feature",
  "properties": {
    "tgn:hierarchy":[
        "tgn:2242014",
        "tgn:1000001",
        "tgn:7012149",
        "tgn:2001706",
        "tgn:7007708",
        "tgn:7029392"
    ],
    "tgn:id":2242014,
    "tgn:name":"Clay Creek",
    "tgn:placetype":[
        "aat:300008706"
    ]
},
  "bbox": [],
  "geometry": {"coordinates":[-122.95,43.3167],"type":"Point"}
}