{
  "id": 7578008,
  "type": "Feature",
  "properties": {
    "tgn:hierarchy":[
        "tgn:7578008",
        "tgn:1000004",
        "tgn:7000198",
        "tgn:1001894",
        "tgn:7029392"
    ],
    "tgn:id":7578008,
    "tgn:name:en":"Khujner",
    "tgn:placetype":[
        "aat:300008347"
    ]
},
  "bbox": [],
  "geometry": {"coordinates":[76.617739,23.786114],"type":"Point"}
}