<<<<<<< HEAD
{
  "id": 7111768,
  "type": "Feature",
  "properties": {
    "tgn:hierarchy":[
        "tgn:7111768",
        "tgn:7003669",
        "tgn:1000003",
        "tgn:7000084",
        "tgn:7029392"
    ],
    "tgn:id":7111768,
    "tgn:name":"Ro\u00df-Filz",
    "tgn:placetype":[
        "aat:300008863"
    ]
},
  "bbox": [],
  "geometry": {"coordinates":[11.416667,47.8],"type":"Point"}
}
=======
{"geometry":{"type":"Point","coordinates":[11.416667,47.800000]},"type":"Feature","properties":{"hierarchy":["tgn:7111768","tgn:7003669","tgn:1000003","tgn:7000084","tgn:7029392"],"placetype":["aat:300008863"],"id":7111768,"name:xx":"Ro\u00df-Filz"}}
>>>>>>> 03f74aca74312dbeaf24d7e61306dd6a786dc3d0
