<<<<<<< HEAD
{
  "id": 2333859,
  "type": "Feature",
  "properties": {
    "tgn:hierarchy":[
        "tgn:2333859",
        "tgn:1000001",
        "tgn:7012149",
        "tgn:7007157",
        "tgn:2000191",
        "tgn:7029392"
    ],
    "tgn:id":2333859,
    "tgn:name":"Forbidden Lakes",
    "tgn:placetype":[
        "aat:300008680"
    ]
},
  "bbox": [],
  "geometry": {"coordinates":[-123.0333,40.9333],"type":"Point"}
}
=======
{"geometry":{"type":"Point","coordinates":[-123.033300,40.933300]},"type":"Feature","properties":{"hierarchy":["tgn:2333859","tgn:1000001","tgn:7012149","tgn:7007157","tgn:2000191","tgn:7029392"],"placetype":["aat:300008680"],"id":2333859,"name:xx":"Forbidden Lakes"}}
>>>>>>> 03f74aca74312dbeaf24d7e61306dd6a786dc3d0
