{
  "id": 2323759,
  "type": "Feature",
  "properties": {
    "tgn:hierarchy":[
        "tgn:2323759",
        "tgn:1000001",
        "tgn:7012149",
        "tgn:1003008",
        "tgn:7007710",
        "tgn:7029392"
    ],
    "tgn:id":2323759,
    "tgn:name":"Faulkner Brook",
    "tgn:placetype":[
        "aat:300008699"
    ]
},
  "bbox": [],
  "geometry": {"coordinates":[-75.3667,41.9833],"type":"Point"}
}