{
  "id": 2366555,
  "type": "Feature",
  "properties": {
    "tgn:hierarchy":[
        "tgn:2366555",
        "tgn:1000001",
        "tgn:7012149",
        "tgn:2001312",
        "tgn:7007524",
        "tgn:7029392"
    ],
    "tgn:id":2366555,
    "tgn:name":"Grimes Reservoir",
    "tgn:placetype":[
        "aat:300006191"
    ]
},
  "bbox": [],
  "geometry": {"coordinates":[-107.1333,48.95],"type":"Point"}
}