<<<<<<< HEAD
{
  "id": 2403826,
  "type": "Feature",
  "properties": {
    "tgn:hierarchy":[
        "tgn:2403826",
        "tgn:1000001",
        "tgn:7012149",
        "tgn:2001920",
        "tgn:7007825",
        "tgn:7029392"
    ],
    "tgn:id":2403826,
    "tgn:name":"Howards Landing",
    "tgn:placetype":[
        "aat:300008347"
    ]
},
  "bbox": [],
  "geometry": {"coordinates":[-90.0,35.5],"type":"Point"}
}
=======
{"geometry":{"type":"Point","coordinates":[-90.000000,35.500000]},"type":"Feature","properties":{"hierarchy":["tgn:2403826","tgn:1000001","tgn:7012149","tgn:2001920","tgn:7007825","tgn:7029392"],"placetype":["aat:300008347"],"id":2403826,"name:xx":"Howards Landing"}}
>>>>>>> 03f74aca74312dbeaf24d7e61306dd6a786dc3d0
