<<<<<<< HEAD
{
  "id": 7356766,
  "type": "Feature",
  "properties": {
    "tgn:hierarchy":[
        "tgn:7356766",
        "tgn:7005581",
        "tgn:1000001",
        "tgn:7005560",
        "tgn:7029392"
    ],
    "tgn:id":7356766,
    "tgn:name":"Chino",
    "tgn:placetype":[
        "aat:300008347"
    ]
},
  "bbox": [],
  "geometry": {"coordinates":[-104.15,29.383333],"type":"Point"}
}
=======
{"geometry":{"type":"Point","coordinates":[-104.150000,29.383333]},"type":"Feature","properties":{"hierarchy":["tgn:7356766","tgn:7005581","tgn:1000001","tgn:7005560","tgn:7029392"],"placetype":["aat:300008347"],"id":7356766,"name:xx":"Chino"}}
>>>>>>> 03f74aca74312dbeaf24d7e61306dd6a786dc3d0
