{
  "id": 7088618,
  "type": "Feature",
  "properties": {
    "tgn:hierarchy":[
        "tgn:7088618",
        "tgn:1000003",
        "tgn:7003676",
        "tgn:7000084",
        "tgn:7029392"
    ],
    "tgn:id":7088618,
    "tgn:name":"Wahls-Berg",
    "tgn:placetype":[
        "aat:300008777"
    ]
},
  "bbox": [],
  "geometry": {"coordinates":[10.35,53.283333],"type":"Point"}
}