{
  "id": 2711577,
  "type": "Feature",
  "properties": {
    "tgn:hierarchy":[
        "tgn:2711577",
        "tgn:1000001",
        "tgn:7012149",
        "tgn:1002938",
        "tgn:7007252",
        "tgn:7029392"
    ],
    "tgn:id":2711577,
    "tgn:name":"Tapps Ridge",
    "tgn:placetype":[
        "aat:300266640"
    ]
},
  "bbox": [],
  "geometry": {"coordinates":[-85.0167,38.7833],"type":"Point"}
}