{
  "id": 2222874,
  "type": "Feature",
  "properties": {
    "tgn:hierarchy":[
        "tgn:2222874",
        "tgn:1000001",
        "tgn:7012149",
        "tgn:2001613",
        "tgn:7007706",
        "tgn:7029392"
    ],
    "tgn:id":2222874,
    "tgn:name":"Carrick Hill",
    "tgn:placetype":[
        "aat:300008798"
    ]
},
  "bbox": [],
  "geometry": {"coordinates":[-82.3667,39.45],"type":"Point"}
}