{
  "id": 2415055,
  "type": "Feature",
  "properties": {
    "tgn:hierarchy":[
        "tgn:2415055",
        "tgn:1000001",
        "tgn:7012149",
        "tgn:2001718",
        "tgn:7007708",
        "tgn:7029392"
    ],
    "tgn:id":2415055,
    "tgn:name":"Island Canyon",
    "tgn:placetype":[
        "aat:300008761"
    ]
},
  "bbox": [],
  "geometry": {"coordinates":[-117.8833,42.1167],"type":"Point"}
}