{
  "id": 2607563,
  "type": "Feature",
  "properties": {
    "tgn:hierarchy":[
        "tgn:2607563",
        "tgn:1000001",
        "tgn:7012149",
        "tgn:2001052",
        "tgn:7007521",
        "tgn:7029392"
    ],
    "tgn:id":2607563,
    "tgn:name":"Ranum",
    "tgn:placetype":[
        "aat:300008347"
    ]
},
  "bbox": [],
  "geometry": {"coordinates":[-96.1167,47.45],"type":"Point"}
}