{
  "id": 7412103,
  "type": "Feature",
  "properties": {
    "tgn:hierarchy":[
        "tgn:7412103",
        "tgn:1000001",
        "tgn:7005596",
        "tgn:7005560",
        "tgn:7029392"
    ],
    "tgn:id":7412103,
    "tgn:name:es":"C\u00e1rdenal",
    "tgn:placetype":[
        "aat:300008347"
    ]
},
  "bbox": [],
  "geometry": {"coordinates":[-93.05,17.983333],"type":"Point"}
}