<<<<<<< HEAD
{
  "id": 7355916,
  "type": "Feature",
  "properties": {
    "tgn:hierarchy":[
        "tgn:7355916",
        "tgn:7005585",
        "tgn:1000001",
        "tgn:7005560",
        "tgn:7029392"
    ],
    "tgn:id":7355916,
    "tgn:name":"Carboneras",
    "tgn:placetype":[
        "aat:300008347"
    ]
},
  "bbox": [],
  "geometry": {"coordinates":[-101.283333,18.05],"type":"Point"}
}
=======
{"geometry":{"type":"Point","coordinates":[-101.283333,18.050000]},"type":"Feature","properties":{"hierarchy":["tgn:7355916","tgn:7005585","tgn:1000001","tgn:7005560","tgn:7029392"],"placetype":["aat:300008347"],"id":7355916,"name:xx":"Carboneras"}}
>>>>>>> 03f74aca74312dbeaf24d7e61306dd6a786dc3d0
