{
  "id": 2690658,
  "type": "Feature",
  "properties": {
    "tgn:hierarchy":[
        "tgn:2690658",
        "tgn:1000001",
        "tgn:7012149",
        "tgn:2001922",
        "tgn:7007825",
        "tgn:7029392"
    ],
    "tgn:id":2690658,
    "tgn:name":"Stamping Ground Ridge",
    "tgn:placetype":[
        "aat:300266640"
    ]
},
  "bbox": [],
  "geometry": {"coordinates":[-82.2667,36.1333],"type":"Point"}
}