{
  "id": 2619511,
  "type": "Feature",
  "properties": {
    "tgn:hierarchy":[
        "tgn:2619511",
        "tgn:1000001",
        "tgn:7012149",
        "tgn:2001451",
        "tgn:7007566",
        "tgn:7029392"
    ],
    "tgn:id":2619511,
    "tgn:name":"Rincon Entra\u00f1oso",
    "tgn:placetype":[
        "aat:300055621"
    ]
},
  "bbox": [],
  "geometry": {"coordinates":[-107.0167,35.4667],"type":"Point"}
}