{
  "id": 7048521,
  "type": "Feature",
  "properties": {
    "tgn:hierarchy":[
        "tgn:7048521",
        "tgn:1003464",
        "tgn:1000003",
        "tgn:7003241",
        "tgn:1000080",
        "tgn:7029392"
    ],
    "tgn:id":7048521,
    "tgn:name":"Casalciprano",
    "tgn:placetype":[
        "aat:300008347"
    ]
},
  "bbox": [],
  "geometry": {"coordinates":[14.533333,41.583333],"type":"Point"}
}