{
  "id": 7083979,
  "type": "Feature",
  "properties": {
    "tgn:hierarchy":[
        "tgn:7083979",
        "tgn:7003692",
        "tgn:1000003",
        "tgn:7000084",
        "tgn:7029392"
    ],
    "tgn:id":7083979,
    "tgn:name":"Welland",
    "tgn:placetype":[
        "aat:300055621"
    ]
},
  "bbox": [],
  "geometry": {"coordinates":[10.016667,48.866667],"type":"Point"}
}