{
  "id": 7033369,
  "type": "Feature",
  "properties": {
    "tgn:hierarchy":[
        "tgn:7033369",
        "tgn:7002996",
        "tgn:1000003",
        "tgn:7002997",
        "tgn:1000080",
        "tgn:7029392"
    ],
    "tgn:id":7033369,
    "tgn:name":"Pero",
    "tgn:placetype":[
        "aat:300008347"
    ]
},
  "bbox": [],
  "geometry": {"coordinates":[12.348333,45.707222],"type":"Point"}
}