{
  "id": 2188467,
  "type": "Feature",
  "properties": {
    "tgn:hierarchy":[
        "tgn:2188467",
        "tgn:1000001",
        "tgn:7012149",
        "tgn:2001770",
        "tgn:7007712",
        "tgn:7029392"
    ],
    "tgn:id":2188467,
    "tgn:name":"Botany Woods",
    "tgn:placetype":[
        "aat:300008347"
    ]
},
  "bbox": [],
  "geometry": {"coordinates":[-81.05,34.95],"type":"Point"}
}