{
  "id": 7355741,
  "type": "Feature",
  "properties": {
    "tgn:hierarchy":[
        "tgn:7355741",
        "tgn:1001836",
        "tgn:1000001",
        "tgn:7005560",
        "tgn:7029392"
    ],
    "tgn:id":7355741,
    "tgn:name":"Caracol, Arroyo",
    "tgn:placetype":[
        "aat:300008699"
    ]
},
  "bbox": [],
  "geometry": {"coordinates":[-111.116667,24.566667],"type":"Point"}
}