{
  "id": 2347315,
  "type": "Feature",
  "properties": {
    "tgn:hierarchy":[
        "tgn:2347315",
        "tgn:7006450",
        "tgn:1000001",
        "tgn:2124053",
        "tgn:7012149",
        "tgn:7029392"
    ],
    "tgn:id":2347315,
    "tgn:name":"George Creek",
    "tgn:placetype":[
        "aat:300008706"
    ]
},
  "bbox": [],
  "geometry": {"coordinates":[-147.9333,62.4667],"type":"Point"}
}