{
  "id": 2604930,
  "type": "Feature",
  "properties": {
    "tgn:hierarchy":[
        "tgn:2604930",
        "tgn:1000001",
        "tgn:7012149",
        "tgn:2001763",
        "tgn:7007712",
        "tgn:7029392"
    ],
    "tgn:id":2604930,
    "tgn:name":"Rachael Creek",
    "tgn:placetype":[
        "aat:300008706"
    ]
},
  "bbox": [],
  "geometry": {"coordinates":[-82.7333,35.0167],"type":"Point"}
}