{
  "id": 2073185,
  "type": "Feature",
  "properties": {
    "tgn:hierarchy":[
        "tgn:2073185",
        "tgn:1000001",
        "tgn:7012149",
        "tgn:1002821",
        "tgn:7007568",
        "tgn:7029392"
    ],
    "tgn:id":2073185,
    "tgn:name":"West Stephentown",
    "tgn:placetype":[
        "aat:300008347"
    ]
},
  "bbox": [],
  "geometry": {"coordinates":[-73.4667,42.5667],"type":"Point"}
}