{
  "id": 7151012,
  "type": "Feature",
  "properties": {
    "tgn:hierarchy":[
        "tgn:7151012",
        "tgn:1000003",
        "tgn:7003677",
        "tgn:7000084",
        "tgn:7029392"
    ],
    "tgn:id":7151012,
    "tgn:name":"Jitten-Berg",
    "tgn:placetype":[
        "aat:300008777"
    ]
},
  "bbox": [],
  "geometry": {"coordinates":[8.866667,51.45],"type":"Point"}
}