{
  "id": 2293115,
  "type": "Feature",
  "properties": {
    "tgn:hierarchy":[
        "tgn:2293115",
        "tgn:1000001",
        "tgn:7012149",
        "tgn:2002363",
        "tgn:7007922",
        "tgn:7029392"
    ],
    "tgn:id":2293115,
    "tgn:name":"Doty Island",
    "tgn:placetype":[
        "aat:300008791"
    ]
},
  "bbox": [],
  "geometry": {"coordinates":[-88.4333,44.1833],"type":"Point"}
}