{
  "id": 7227002,
  "type": "Feature",
  "properties": {
    "tgn:hierarchy":[
        "tgn:7227002",
        "tgn:7002739",
        "tgn:7017076",
        "tgn:1000003",
        "tgn:1000074",
        "tgn:7029392"
    ],
    "tgn:id":7227002,
    "tgn:name":"Paral\u00eda Ir\u00edon",
    "tgn:placetype":[
        "aat:300008347"
    ]
},
  "bbox": [],
  "geometry": {"coordinates":[22.991442,37.490861],"type":"Point"}
}