{
  "id": 2706821,
  "type": "Feature",
  "properties": {
    "tgn:hierarchy":[
        "tgn:2706821",
        "tgn:7006450",
        "tgn:1000001",
        "tgn:7012149",
        "tgn:2000086",
        "tgn:7029392"
    ],
    "tgn:id":2706821,
    "tgn:name":"Swanson Bay",
    "tgn:placetype":[
        "aat:300132316"
    ]
},
  "bbox": [],
  "geometry": {"coordinates":[-148.2333,60.0333],"type":"Point"}
}