{
  "id": 7198881,
  "type": "Feature",
  "properties": {
    "tgn:hierarchy":[
        "tgn:7198881",
        "tgn:1000003",
        "tgn:7003677",
        "tgn:7000084",
        "tgn:7029392"
    ],
    "tgn:id":7198881,
    "tgn:name":"Eggeberg",
    "tgn:placetype":[
        "aat:300008347"
    ]
},
  "bbox": [],
  "geometry": {"coordinates":[8.35,52.083333],"type":"Point"}
}