{
  "id": 7443497,
  "type": "Feature",
  "properties": {
    "tgn:hierarchy":[
        "tgn:7443497",
        "tgn:7002445",
        "tgn:1000003",
        "tgn:7008134",
        "tgn:7008591",
        "tgn:7029392"
    ],
    "tgn:id":7443497,
    "tgn:name:en":"Tillington",
    "tgn:placetype":[
        "aat:300008347"
    ]
},
  "bbox": [],
  "geometry": {"coordinates":[-0.616667,50.983333],"type":"Point"}
}