{
  "id": 7314690,
  "type": "Feature",
  "properties": {
    "tgn:hierarchy":[
        "tgn:7314690",
        "tgn:1001623",
        "tgn:1000049",
        "tgn:1000002",
        "tgn:7029392"
    ],
    "tgn:id":7314690,
    "tgn:name":"Loma Baja, Lagos de la",
    "tgn:placetype":[
        "aat:300008680"
    ]
},
  "bbox": [],
  "geometry": {"coordinates":[-71.983333,-44.533333],"type":"Point"}
}