{
  "id": 7257816,
  "type": "Feature",
  "properties": {
    "tgn:concordances":{
        "gn:id":"2760101"
    },
    "tgn:hierarchy":[
        "tgn:7257816",
        "tgn:1000003",
        "tgn:7003632",
        "tgn:7016845",
        "tgn:7029392"
    ],
    "tgn:id":7257816,
    "tgn:name:nl":"Aardam",
    "tgn:placetype":[
        "aat:300008347"
    ]
},
  "bbox": [],
  "geometry": {"coordinates":[4.766667,52.166667],"type":"Point"}
}