{
  "id": 7577772,
  "type": "Feature",
  "properties": {
    "tgn:hierarchy":[
        "tgn:7577772",
        "tgn:1000004",
        "tgn:7000198",
        "tgn:1001882",
        "tgn:7029392"
    ],
    "tgn:id":7577772,
    "tgn:name:en":"Kum\u0101rasw\u0101mi",
    "tgn:placetype":[
        "aat:300008347"
    ]
},
  "bbox": [],
  "geometry": {"coordinates":[76.566667,15.016667],"type":"Point"}
}