<<<<<<< HEAD
{
  "id": 2404666,
  "type": "Feature",
  "properties": {
    "tgn:hierarchy":[
        "tgn:2404666",
        "tgn:1000001",
        "tgn:2000466",
        "tgn:7012149",
        "tgn:7007250",
        "tgn:7029392"
    ],
    "tgn:id":2404666,
    "tgn:name":"Huckleberry Basin",
    "tgn:placetype":[
        "aat:300386845"
    ]
},
  "bbox": [],
  "geometry": {"coordinates":[-111.3667,42.6333],"type":"Point"}
}
=======
{"geometry":{"type":"Point","coordinates":[-111.366700,42.633300]},"type":"Feature","properties":{"hierarchy":["tgn:2404666","tgn:1000001","tgn:2000466","tgn:7012149","tgn:7007250","tgn:7029392"],"placetype":["aat:300386845"],"id":2404666,"name:xx":"Huckleberry Basin"}}
>>>>>>> 03f74aca74312dbeaf24d7e61306dd6a786dc3d0
