{
  "id": 2149314,
  "type": "Feature",
  "properties": {
    "tgn:hierarchy":[
        "tgn:2149314",
        "tgn:1000001",
        "tgn:7012149",
        "tgn:7007923",
        "tgn:7029392"
    ],
    "tgn:id":2149314,
    "tgn:name":"Barrel Springs Draw",
    "tgn:placetype":[
        "aat:300008761"
    ]
},
  "bbox": [],
  "geometry": {"coordinates":[-108.15,41.4167],"type":"Point"}
}