{
  "id": 7299768,
  "type": "Feature",
  "properties": {
    "tgn:hierarchy":[
        "tgn:7299768",
        "tgn:7002825",
        "tgn:7016622",
        "tgn:1000003",
        "tgn:1000095",
        "tgn:7029392"
    ],
    "tgn:id":7299768,
    "tgn:name":"Timagada",
    "tgn:placetype":[
        "aat:300008347"
    ]
},
  "bbox": [],
  "geometry": {"coordinates":[-15.65,27.966667],"type":"Point"}
}