{
  "id": 7326571,
  "type": "Feature",
  "properties": {
    "tgn:hierarchy":[
        "tgn:7326571",
        "tgn:7002759",
        "tgn:7002843",
        "tgn:1000003",
        "tgn:1000095",
        "tgn:7029392"
    ],
    "tgn:id":7326571,
    "tgn:name":"Peralejos",
    "tgn:placetype":[
        "aat:300008347"
    ]
},
  "bbox": [],
  "geometry": {"coordinates":[-1.033333,40.483333],"type":"Point"}
}