{
  "id": 2658927,
  "type": "Feature",
  "properties": {
    "tgn:hierarchy":[
        "tgn:2658927",
        "tgn:1000001",
        "tgn:7012149",
        "tgn:7007523",
        "tgn:7029392"
    ],
    "tgn:id":2658927,
    "tgn:name":"Sherry Branch",
    "tgn:placetype":[
        "aat:300008699"
    ]
},
  "bbox": [],
  "geometry": {"coordinates":[-91.8667,39.75],"type":"Point"}
}