{
  "id": 7548607,
  "type": "Feature",
  "properties": {
    "tgn:hierarchy":[
        "tgn:7548607",
        "tgn:1000004",
        "tgn:7000198",
        "tgn:7016722",
        "tgn:7029392"
    ],
    "tgn:id":7548607,
    "tgn:name:en":"Bundk\u012b",
    "tgn:placetype":[
        "aat:300007783"
    ]
},
  "bbox": [],
  "geometry": {"coordinates":[78.393487,29.522585],"type":"Point"}
}