{
  "id": 7150624,
  "type": "Feature",
  "properties": {
    "tgn:hierarchy":[
        "tgn:7150624",
        "tgn:7003669",
        "tgn:1000003",
        "tgn:7000084",
        "tgn:7029392"
    ],
    "tgn:id":7150624,
    "tgn:name":"Lackenh\u00e4user",
    "tgn:placetype":[
        "aat:300008347"
    ]
},
  "bbox": [],
  "geometry": {"coordinates":[13.816667,48.733333],"type":"Point"}
}