{
  "id": 2275915,
  "type": "Feature",
  "properties": {
    "tgn:hierarchy":[
        "tgn:2275915",
        "tgn:1000001",
        "tgn:7012149",
        "tgn:2001034",
        "tgn:7007521",
        "tgn:7029392"
    ],
    "tgn:id":2275915,
    "tgn:name":"Dark Lake",
    "tgn:placetype":[
        "aat:300008680"
    ]
},
  "bbox": [],
  "geometry": {"coordinates":[-94.0833,47.95],"type":"Point"}
}