{
  "id": 2525578,
  "type": "Feature",
  "properties": {
    "tgn:hierarchy":[
        "tgn:2525578",
        "tgn:1000001",
        "tgn:7012149",
        "tgn:2000375",
        "tgn:7007248",
        "tgn:7029392"
    ],
    "tgn:id":2525578,
    "tgn:name":"Morton",
    "tgn:placetype":[
        "aat:300008347"
    ]
},
  "bbox": [],
  "geometry": {"coordinates":[-83.5167,32.9667],"type":"Point"}
}