<<<<<<< HEAD
{
  "id": 2157033,
  "type": "Feature",
  "properties": {
    "tgn:hierarchy":[
        "tgn:2157033",
        "tgn:1000001",
        "tgn:2000921",
        "tgn:7012149",
        "tgn:7007515",
        "tgn:7029392"
    ],
    "tgn:id":2157033,
    "tgn:name":"Beaver Bog",
    "tgn:placetype":[
        "aat:300008905"
    ]
},
  "bbox": [],
  "geometry": {"coordinates":[-70.65,45.1333],"type":"Point"}
}
=======
{"geometry":{"type":"Point","coordinates":[-70.650000,45.133300]},"type":"Feature","properties":{"hierarchy":["tgn:2157033","tgn:1000001","tgn:2000921","tgn:7012149","tgn:7007515","tgn:7029392"],"placetype":["aat:300008905"],"id":2157033,"name:xx":"Beaver Bog"}}
>>>>>>> 03f74aca74312dbeaf24d7e61306dd6a786dc3d0
