{
  "id": 2522490,
  "type": "Feature",
  "properties": {
    "tgn:hierarchy":[
        "tgn:2522490",
        "tgn:1000001",
        "tgn:1002408",
        "tgn:7012149",
        "tgn:7007240",
        "tgn:7029392"
    ],
    "tgn:id":2522490,
    "tgn:name":"Moonshine Bay",
    "tgn:placetype":[
        "aat:300132316"
    ]
},
  "bbox": [],
  "geometry": {"coordinates":[-81.0167,26.8667],"type":"Point"}
}