{
  "id": 7520673,
  "type": "Feature",
  "properties": {
    "tgn:hierarchy":[
        "tgn:7520673",
        "tgn:7001242",
        "tgn:7001311",
        "tgn:7016833",
        "tgn:7029392"
    ],
    "tgn:id":7520673,
    "tgn:name:en":"Abraq, W\u00e2di",
    "tgn:placetype":[
        "aat:300379998"
    ]
},
  "bbox": [],
  "geometry": {"coordinates":[34.89847,23.377029],"type":"Point"}
}