{
  "id": 2293835,
  "type": "Feature",
  "properties": {
    "tgn:hierarchy":[
        "tgn:2293835",
        "tgn:1002140",
        "tgn:1000001",
        "tgn:7012149",
        "tgn:7007520",
        "tgn:7029392"
    ],
    "tgn:id":2293835,
    "tgn:name":"Douglas Bayou",
    "tgn:placetype":[
        "aat:300132316"
    ]
},
  "bbox": [],
  "geometry": {"coordinates":[-86.1833,42.65],"type":"Point"}
}