{
  "id": 7492232,
  "type": "Feature",
  "properties": {
    "tgn:hierarchy":[
        "tgn:7492232",
        "tgn:7487020",
        "tgn:1000004",
        "tgn:1000141",
        "tgn:7029392"
    ],
    "tgn:id":7492232,
    "tgn:name":"Shangdawo",
    "tgn:placetype":[
        "aat:300008347"
    ]
},
  "bbox": [],
  "geometry": {"coordinates":[120.944919,24.554387],"type":"Point"}
}