{
  "id": 2249854,
  "type": "Feature",
  "properties": {
    "tgn:hierarchy":[
        "tgn:2249854",
        "tgn:1000001",
        "tgn:7012149",
        "tgn:1002931",
        "tgn:7007919",
        "tgn:7029392"
    ],
    "tgn:id":2249854,
    "tgn:name":"College Run",
    "tgn:placetype":[
        "aat:300008699"
    ]
},
  "bbox": [],
  "geometry": {"coordinates":[-76.8167,37.1167],"type":"Point"}
}