{
  "id": 7569420,
  "type": "Feature",
  "properties": {
    "tgn:hierarchy":[
        "tgn:7569420",
        "tgn:1000004",
        "tgn:7000198",
        "tgn:7016694",
        "tgn:7029392"
    ],
    "tgn:id":7569420,
    "tgn:name:en":"Simlipal Massif",
    "tgn:placetype":[
        "aat:300387346"
    ]
},
  "bbox": [],
  "geometry": {"coordinates":[86.374167,21.763333],"type":"Point"}
}