{
  "id": 2082813,
  "type": "Feature",
  "properties": {
    "tgn:hierarchy":[
        "tgn:2082813",
        "tgn:1000001",
        "tgn:7012149",
        "tgn:2001698",
        "tgn:7007707",
        "tgn:7029392"
    ],
    "tgn:id":2082813,
    "tgn:name":"Avard",
    "tgn:placetype":[
        "aat:300008347"
    ]
},
  "bbox": [],
  "geometry": {"coordinates":[-98.7833,36.6833],"type":"Point"}
}