{
  "id": 2645487,
  "type": "Feature",
  "properties": {
    "tgn:hierarchy":[
        "tgn:2645487",
        "tgn:1000001",
        "tgn:2000769",
        "tgn:7012149",
        "tgn:7007255",
        "tgn:7029392"
    ],
    "tgn:id":2645487,
    "tgn:name":"Saw Mill Branch",
    "tgn:placetype":[
        "aat:300008699"
    ]
},
  "bbox": [],
  "geometry": {"coordinates":[-83.7833,36.7167],"type":"Point"}
}