{
  "id": 7396955,
  "type": "Feature",
  "properties": {
    "tgn:hierarchy":[
        "tgn:7396955",
        "tgn:7005586",
        "tgn:1000001",
        "tgn:7005560",
        "tgn:7029392"
    ],
    "tgn:id":7396955,
    "tgn:name":"Santa Rosa",
    "tgn:placetype":[
        "aat:300008347"
    ]
},
  "bbox": [],
  "geometry": {"coordinates":[-102.183333,21.116667],"type":"Point"}
}