{
  "id": 7034199,
  "type": "Feature",
  "properties": {
    "tgn:hierarchy":[
        "tgn:7034199",
        "tgn:1003468",
        "tgn:1000003",
        "tgn:7010380",
        "tgn:1000080",
        "tgn:7029392"
    ],
    "tgn:id":7034199,
    "tgn:name":"Masseria Pisciani",
    "tgn:placetype":[
        "aat:300000206"
    ]
},
  "bbox": [],
  "geometry": {"coordinates":[18.045556,40.501389],"type":"Point"}
}