{
  "id": 7211803,
  "type": "Feature",
  "properties": {
    "tgn:hierarchy":[
        "tgn:7211803",
        "tgn:1000003",
        "tgn:7003684",
        "tgn:7000084",
        "tgn:7029392"
    ],
    "tgn:id":7211803,
    "tgn:name":"Bilsen-Berg",
    "tgn:placetype":[
        "aat:300008777"
    ]
},
  "bbox": [],
  "geometry": {"coordinates":[6.883333,49.366667],"type":"Point"}
}