{
  "id": 1044613,
  "type": "Feature",
  "properties": {
    "tgn:hierarchy":[
        "tgn:1044613",
        "tgn:7003132",
        "tgn:1000003",
        "tgn:7008516",
        "tgn:1000080",
        "tgn:7029392"
    ],
    "tgn:id":1044613,
    "tgn:name":"Fiorenzuola d'Arda",
    "tgn:placetype":[
        "aat:300008347"
    ]
},
  "bbox": [],
  "geometry": {"coordinates":[9.916667,44.933333],"type":"Point"}
}