{
  "id": 2631137,
  "type": "Feature",
  "properties": {
    "tgn:hierarchy":[
        "tgn:2631137",
        "tgn:1000001",
        "tgn:7012149",
        "tgn:2001520",
        "tgn:7007709",
        "tgn:7029392"
    ],
    "tgn:id":2631137,
    "tgn:name":"Round Mountain",
    "tgn:placetype":[
        "aat:300008798"
    ]
},
  "bbox": [],
  "geometry": {"coordinates":[-79.9833,35.4667],"type":"Point"}
}