{
  "id": 2392125,
  "type": "Feature",
  "properties": {
    "tgn:hierarchy":[
        "tgn:2392125",
        "tgn:1000001",
        "tgn:7012149",
        "tgn:7007157",
        "tgn:2000186",
        "tgn:7029392"
    ],
    "tgn:id":2392125,
    "tgn:name":"Hines Reservoir",
    "tgn:placetype":[
        "aat:300006191"
    ]
},
  "bbox": [],
  "geometry": {"coordinates":[-121.1333,41.2667],"type":"Point"}
}