{
  "id": 1125659,
  "type": "Feature",
  "properties": {
    "tgn:hierarchy":[
        "tgn:1125659",
        "tgn:1000004",
        "tgn:7000894",
        "tgn:1000120",
        "tgn:7029392"
    ],
    "tgn:id":1125659,
    "tgn:name":"Kokai-gawa",
    "tgn:placetype":[
        "aat:300008707"
    ]
},
  "bbox": [],
  "geometry": {"coordinates":[140.1333,35.8667],"type":"Point"}
}