{
  "id": 2455016,
  "type": "Feature",
  "properties": {
    "tgn:hierarchy":[
        "tgn:2455016",
        "tgn:1000001",
        "tgn:7012149",
        "tgn:7007713",
        "tgn:7029392"
    ],
    "tgn:id":2455016,
    "tgn:name":"Little Elk Canyon",
    "tgn:placetype":[
        "aat:300008761"
    ]
},
  "bbox": [],
  "geometry": {"coordinates":[-103.5667,44.25],"type":"Point"}
}