{
  "id": 1069339,
  "type": "Feature",
  "properties": {
    "tgn:hierarchy":[
        "tgn:1069339",
        "tgn:1000004",
        "tgn:1001390",
        "tgn:1000111",
        "tgn:7029392"
    ],
    "tgn:id":1069339,
    "tgn:name":"Jinjiawopu",
    "tgn:placetype":[
        "aat:300008347"
    ]
},
  "bbox": [],
  "geometry": {"coordinates":[122.1667,42.5333],"type":"Point"}
}