{
  "id": 7495776,
  "type": "Feature",
  "properties": {
    "tgn:hierarchy":[
        "tgn:7495776",
        "tgn:1000004",
        "tgn:7467799",
        "tgn:1000141",
        "tgn:7029392"
    ],
    "tgn:id":7495776,
    "tgn:name":"Pinghe Er Qiao",
    "tgn:placetype":[
        "aat:300007836"
    ]
},
  "bbox": [],
  "geometry": {"coordinates":[120.576463,23.997963],"type":"Point"}
}