{
  "id": 2052754,
  "type": "Feature",
  "properties": {
    "tgn:hierarchy":[
        "tgn:2052754",
        "tgn:1000001",
        "tgn:7012149",
        "tgn:2000975",
        "tgn:7007520",
        "tgn:7029392"
    ],
    "tgn:id":2052754,
    "tgn:name":"National Mine",
    "tgn:placetype":[
        "aat:300008347"
    ]
},
  "bbox": [],
  "geometry": {"coordinates":[-87.6667,46.45],"type":"Point"}
}