{
  "id": 2039542,
  "type": "Feature",
  "properties": {
    "tgn:hierarchy":[
        "tgn:2039542",
        "tgn:1000001",
        "tgn:7012149",
        "tgn:1002354",
        "tgn:7007255",
        "tgn:7029392"
    ],
    "tgn:id":2039542,
    "tgn:name":"Isonville",
    "tgn:placetype":[
        "aat:300008347"
    ]
},
  "bbox": [],
  "geometry": {"coordinates":[-83.05,38.05],"type":"Point"}
}