{
  "id": 2565640,
  "type": "Feature",
  "properties": {
    "tgn:hierarchy":[
        "tgn:2565640",
        "tgn:1000001",
        "tgn:7012149",
        "tgn:2001452",
        "tgn:7007566",
        "tgn:7029392"
    ],
    "tgn:id":2565640,
    "tgn:name":"Pajarito Creek",
    "tgn:placetype":[
        "aat:300008706"
    ]
},
  "bbox": [],
  "geometry": {"coordinates":[-108.8833,36.45],"type":"Point"}
}