{
  "id": 7237589,
  "type": "Feature",
  "properties": {
    "tgn:hierarchy":[
        "tgn:7237589",
        "tgn:7003461",
        "tgn:1000003",
        "tgn:1000063",
        "tgn:7018236",
        "tgn:7029392"
    ],
    "tgn:id":7237589,
    "tgn:name":"Heren Bossen",
    "tgn:placetype":[
        "aat:300008863"
    ]
},
  "bbox": [],
  "geometry": {"coordinates":[5.583333,51.116667],"type":"Point"}
}