{
  "id": 2459883,
  "type": "Feature",
  "properties": {
    "tgn:hierarchy":[
        "tgn:2459883",
        "tgn:1000001",
        "tgn:7012149",
        "tgn:2001883",
        "tgn:7007825",
        "tgn:7029392"
    ],
    "tgn:id":2459883,
    "tgn:name":"Little River Shoals",
    "tgn:placetype":[
        "aat:300132348"
    ]
},
  "bbox": [],
  "geometry": {"coordinates":[-83.9833,35.8667],"type":"Point"}
}