<<<<<<< HEAD
{
  "id": 2336489,
  "type": "Feature",
  "properties": {
    "tgn:hierarchy":[
        "tgn:2336489",
        "tgn:1000001",
        "tgn:7012149",
        "tgn:1002790",
        "tgn:7007240",
        "tgn:7029392"
    ],
    "tgn:id":2336489,
    "tgn:name":"Four Corners",
    "tgn:placetype":[
        "aat:300008347"
    ]
},
  "bbox": [],
  "geometry": {"coordinates":[-82.7167,27.9],"type":"Point"}
}
=======
{"geometry":{"type":"Point","coordinates":[-82.716700,27.900000]},"type":"Feature","properties":{"hierarchy":["tgn:2336489","tgn:1000001","tgn:7012149","tgn:1002790","tgn:7007240","tgn:7029392"],"placetype":["aat:300008347"],"id":2336489,"name:xx":"Four Corners"}}
>>>>>>> 03f74aca74312dbeaf24d7e61306dd6a786dc3d0
