{
  "id": 2117694,
  "type": "Feature",
  "properties": {
    "tgn:hierarchy":[
        "tgn:2117694",
        "tgn:1000001",
        "tgn:7012149",
        "tgn:2002281",
        "tgn:7013961",
        "tgn:7029392"
    ],
    "tgn:id":2117694,
    "tgn:name":"Cassville",
    "tgn:placetype":[
        "aat:300008347"
    ]
},
  "bbox": [],
  "geometry": {"coordinates":[-80.05,39.65],"type":"Point"}
}