{
  "id": 7245963,
  "type": "Feature",
  "properties": {
    "tgn:hierarchy":[
        "tgn:7245963",
        "tgn:7003466",
        "tgn:1000003",
        "tgn:1000063",
        "tgn:4012014",
        "tgn:7029392"
    ],
    "tgn:id":7245963,
    "tgn:name":"Bonneville",
    "tgn:placetype":[
        "aat:300008347"
    ]
},
  "bbox": [],
  "geometry": {"coordinates":[5.034866,50.471318],"type":"Point"}
}