{
  "id": 7494736,
  "type": "Feature",
  "properties": {
    "tgn:hierarchy":[
        "tgn:7494736",
        "tgn:7468018",
        "tgn:1000004",
        "tgn:1000141",
        "tgn:7029392"
    ],
    "tgn:id":7494736,
    "tgn:name":"Chaitouzi",
    "tgn:placetype":[
        "aat:300008347"
    ]
},
  "bbox": [],
  "geometry": {"coordinates":[120.39728,23.537932],"type":"Point"}
}