{
  "id": 2723139,
  "type": "Feature",
  "properties": {
    "tgn:hierarchy":[
        "tgn:2723139",
        "tgn:1000001",
        "tgn:7012149",
        "tgn:2000652",
        "tgn:7007253",
        "tgn:7029392"
    ],
    "tgn:id":2723139,
    "tgn:name":"Titu",
    "tgn:placetype":[
        "aat:300008347"
    ]
},
  "bbox": [],
  "geometry": {"coordinates":[-91.7833,41.2667],"type":"Point"}
}