{
  "id": 7300053,
  "type": "Feature",
  "properties": {
    "tgn:hierarchy":[
        "tgn:7300053",
        "tgn:7002844",
        "tgn:7030216",
        "tgn:1000003",
        "tgn:1000095",
        "tgn:7029392"
    ],
    "tgn:id":7300053,
    "tgn:name":"Term, Cabo del",
    "tgn:placetype":[
        "aat:300008850"
    ]
},
  "bbox": [],
  "geometry": {"coordinates":[0.866667,40.933333],"type":"Point"}
}