{
  "id": 7476067,
  "type": "Feature",
  "properties": {
    "tgn:hierarchy":[
        "tgn:7476067",
        "tgn:1000004",
        "tgn:7489179",
        "tgn:1000141",
        "tgn:7029392"
    ],
    "tgn:id":7476067,
    "tgn:name":"Bao'an Gong",
    "tgn:placetype":[
        "aat:300007595"
    ]
},
  "bbox": [],
  "geometry": {"coordinates":[121.813767,24.680222],"type":"Point"}
}