{
  "id": 7154429,
  "type": "Feature",
  "properties": {
    "tgn:hierarchy":[
        "tgn:7154429",
        "tgn:1000003",
        "tgn:7000094",
        "tgn:7000084",
        "tgn:7029392"
    ],
    "tgn:id":7154429,
    "tgn:name":"Johannenh\u00f6he",
    "tgn:placetype":[
        "aat:300008347"
    ]
},
  "bbox": [],
  "geometry": {"coordinates":[13.05,53.816667],"type":"Point"}
}