{
  "id": 7195088,
  "type": "Feature",
  "properties": {
    "tgn:hierarchy":[
        "tgn:7195088",
        "tgn:1000003",
        "tgn:7003678",
        "tgn:7000084",
        "tgn:7029392"
    ],
    "tgn:id":7195088,
    "tgn:name":"Dorn-Bach",
    "tgn:placetype":[
        "aat:300008699"
    ]
},
  "bbox": [],
  "geometry": {"coordinates":[7.983333,50.116667],"type":"Point"}
}