<<<<<<< HEAD
{
  "id": 2252336,
  "type": "Feature",
  "properties": {
    "tgn:hierarchy":[
        "tgn:2252336",
        "tgn:1002996",
        "tgn:1000001",
        "tgn:7012149",
        "tgn:7007711",
        "tgn:7029392"
    ],
    "tgn:id":2252336,
    "tgn:name":"Congdon Hill",
    "tgn:placetype":[
        "aat:300008798"
    ]
},
  "bbox": [],
  "geometry": {"coordinates":[-71.4833,41.5167],"type":"Point"}
}
=======
{"geometry":{"type":"Point","coordinates":[-71.483300,41.516700]},"type":"Feature","properties":{"hierarchy":["tgn:2252336","tgn:1002996","tgn:1000001","tgn:7012149","tgn:7007711","tgn:7029392"],"placetype":["aat:300008798"],"id":2252336,"name:xx":"Congdon Hill"}}
>>>>>>> 03f74aca74312dbeaf24d7e61306dd6a786dc3d0
