{
  "id": 2724506,
  "type": "Feature",
  "properties": {
    "tgn:hierarchy":[
        "tgn:2724506",
        "tgn:1000001",
        "tgn:7012149",
        "tgn:2000183",
        "tgn:7007157",
        "tgn:7029392"
    ],
    "tgn:id":2724506,
    "tgn:name":"Tom, Mount",
    "tgn:placetype":[
        "aat:300008798"
    ]
},
  "bbox": [],
  "geometry": {"coordinates":[-118.65,37.3333],"type":"Point"}
}