{
  "id": 7501811,
  "type": "Feature",
  "properties": {
    "tgn:hierarchy":[
        "tgn:7501811",
        "tgn:7488858",
        "tgn:1000004",
        "tgn:1000141",
        "tgn:7029392"
    ],
    "tgn:id":7501811,
    "tgn:name":"Dacaoku",
    "tgn:placetype":[
        "aat:300008347"
    ]
},
  "bbox": [],
  "geometry": {"coordinates":[120.852645,24.054864],"type":"Point"}
}