{
  "id": 2482332,
  "type": "Feature",
  "properties": {
    "tgn:hierarchy":[
        "tgn:2482332",
        "tgn:1000001",
        "tgn:7012149",
        "tgn:7016166",
        "tgn:7007523",
        "tgn:7029392"
    ],
    "tgn:id":2482332,
    "tgn:name":"Langosch Lake",
    "tgn:placetype":[
        "aat:300006191"
    ]
},
  "bbox": [],
  "geometry": {"coordinates":[-90.8833,38.7167],"type":"Point"}
}