{
  "id": 7393562,
  "type": "Feature",
  "properties": {
    "tgn:hierarchy":[
        "tgn:7393562",
        "tgn:1000001",
        "tgn:7005597",
        "tgn:7005560",
        "tgn:7029392"
    ],
    "tgn:id":7393562,
    "tgn:name":"San Juan del R\u00edo",
    "tgn:placetype":[
        "aat:300008347"
    ]
},
  "bbox": [],
  "geometry": {"coordinates":[-99.233333,22.55],"type":"Point"}
}