{
  "id": 1054905,
  "type": "Feature",
  "properties": {
    "tgn:hierarchy":[
        "tgn:1054905",
        "tgn:7011631",
        "tgn:1000004",
        "tgn:7014835",
        "tgn:7029392"
    ],
    "tgn:id":1054905,
    "tgn:name":"Kalininabad",
    "tgn:placetype":[
        "aat:300008347"
    ]
},
  "bbox": [],
  "geometry": {"coordinates":[69.15,39.7667],"type":"Point"}
}