{
  "id": 7403167,
  "type": "Feature",
  "properties": {
    "tgn:hierarchy":[
        "tgn:7403167",
        "tgn:1000001",
        "tgn:7005600",
        "tgn:7005560",
        "tgn:7029392"
    ],
    "tgn:id":7403167,
    "tgn:name":"Mahaycab",
    "tgn:placetype":[
        "aat:300008347"
    ]
},
  "bbox": [],
  "geometry": {"coordinates":[-88.408333,21.004167],"type":"Point"}
}