{
  "id": 2364800,
  "type": "Feature",
  "properties": {
    "tgn:hierarchy":[
        "tgn:2364800",
        "tgn:7006450",
        "tgn:1000001",
        "tgn:7012149",
        "tgn:2000086",
        "tgn:7029392"
    ],
    "tgn:id":2364800,
    "tgn:name":"Greene Lake",
    "tgn:placetype":[
        "aat:300008680"
    ]
},
  "bbox": [],
  "geometry": {"coordinates":[-141.5667,61.7833],"type":"Point"}
}