{
  "id": 2322794,
  "type": "Feature",
  "properties": {
    "tgn:hierarchy":[
        "tgn:2322794",
        "tgn:1000001",
        "tgn:7012149",
        "tgn:2175302",
        "tgn:7007524",
        "tgn:7029392"
    ],
    "tgn:id":2322794,
    "tgn:name":"Fan Creek",
    "tgn:placetype":[
        "aat:300008706"
    ]
},
  "bbox": [],
  "geometry": {"coordinates":[-110.9667,44.9833],"type":"Point"}
}