{
  "id": 1095269,
  "type": "Feature",
  "properties": {
    "tgn:hierarchy":[
        "tgn:1095269",
        "tgn:7001242",
        "tgn:7016833",
        "tgn:7001334",
        "tgn:7029392"
    ],
    "tgn:id":1095269,
    "tgn:name:en":"Al Jad\u012bdah",
    "tgn:placetype":[
        "aat:300008347"
    ]
},
  "bbox": [],
  "geometry": {"coordinates":[28.859167,25.577861],"type":"Point"}
}