{
  "id": 2654286,
  "type": "Feature",
  "properties": {
    "tgn:hierarchy":[
        "tgn:2654286",
        "tgn:2000107",
        "tgn:1000001",
        "tgn:7016172",
        "tgn:7012149",
        "tgn:7029392"
    ],
    "tgn:id":2654286,
    "tgn:name":"Shady Grove",
    "tgn:placetype":[
        "aat:300008347"
    ]
},
  "bbox": [],
  "geometry": {"coordinates":[-92.3667,36.25],"type":"Point"}
}