{
  "id": 2608556,
  "type": "Feature",
  "properties": {
    "tgn:hierarchy":[
        "tgn:2608556",
        "tgn:1000001",
        "tgn:7012149",
        "tgn:1002423",
        "tgn:7007568",
        "tgn:7029392"
    ],
    "tgn:id":2608556,
    "tgn:name":"Rattlesnake Island",
    "tgn:placetype":[
        "aat:300008791"
    ]
},
  "bbox": [],
  "geometry": {"coordinates":[-73.7833,42.3667],"type":"Point"}
}