<<<<<<< HEAD
{
  "id": 2403227,
  "type": "Feature",
  "properties": {
    "tgn:hierarchy":[
        "tgn:2403227",
        "tgn:1000001",
        "tgn:7012149",
        "tgn:1003008",
        "tgn:7007710",
        "tgn:7029392"
    ],
    "tgn:id":2403227,
    "tgn:name":"House Pond",
    "tgn:placetype":[
        "aat:300006191"
    ]
},
  "bbox": [],
  "geometry": {"coordinates":[-75.2,41.45],"type":"Point"}
}
=======
{"geometry":{"type":"Point","coordinates":[-75.200000,41.450000]},"type":"Feature","properties":{"hierarchy":["tgn:2403227","tgn:1000001","tgn:7012149","tgn:1003008","tgn:7007710","tgn:7029392"],"placetype":["aat:300006191"],"id":2403227,"name:xx":"House Pond"}}
>>>>>>> 03f74aca74312dbeaf24d7e61306dd6a786dc3d0
