{
  "id": 2597856,
  "type": "Feature",
  "properties": {
    "tgn:hierarchy":[
        "tgn:2597856",
        "tgn:2000943",
        "tgn:1000001",
        "tgn:7012149",
        "tgn:7007520",
        "tgn:7029392"
    ],
    "tgn:id":2597856,
    "tgn:name":"Preacher Lake",
    "tgn:placetype":[
        "aat:300008680"
    ]
},
  "bbox": [],
  "geometry": {"coordinates":[-86.15,46.5833],"type":"Point"}
}