{
  "id": 2507575,
  "type": "Feature",
  "properties": {
    "tgn:hierarchy":[
        "tgn:2507575",
        "tgn:1000001",
        "tgn:7012149",
        "tgn:2000402",
        "tgn:7007248",
        "tgn:7029392"
    ],
    "tgn:id":2507575,
    "tgn:name":"Miami Valley",
    "tgn:placetype":[
        "aat:300008347"
    ]
},
  "bbox": [],
  "geometry": {"coordinates":[-83.7833,32.55],"type":"Point"}
}