{
  "id": 2043919,
  "type": "Feature",
  "properties": {
    "tgn:hierarchy":[
        "tgn:2043919",
        "tgn:1000001",
        "tgn:7012149",
        "tgn:2000914",
        "tgn:7007256",
        "tgn:7029392"
    ],
    "tgn:id":2043919,
    "tgn:name":"Saint Delphine",
    "tgn:placetype":[
        "aat:300008347",
        "aat:300387210"
    ]
},
  "bbox": [],
  "geometry": {"coordinates":[-91.25,30.3333],"type":"Point"}
}