{
  "id": 2346340,
  "type": "Feature",
  "properties": {
    "tgn:hierarchy":[
        "tgn:2346340",
        "tgn:1000001",
        "tgn:7012149",
        "tgn:2002087",
        "tgn:7007826",
        "tgn:7029392"
    ],
    "tgn:id":2346340,
    "tgn:name":"Gato Quarry",
    "tgn:placetype":[
        "aat:300000390"
    ]
},
  "bbox": [],
  "geometry": {"coordinates":[-100.0333,29.15],"type":"Point"}
}