{
  "id": 2279948,
  "type": "Feature",
  "properties": {
    "tgn:hierarchy":[
        "tgn:2279948",
        "tgn:1000001",
        "tgn:7012149",
        "tgn:2000637",
        "tgn:7007253",
        "tgn:7029392"
    ],
    "tgn:id":2279948,
    "tgn:name":"Dean Lake",
    "tgn:placetype":[
        "aat:300008680"
    ]
},
  "bbox": [],
  "geometry": {"coordinates":[-93.5667,41.5833],"type":"Point"}
}