{
  "id": 7177774,
  "type": "Feature",
  "properties": {
    "tgn:hierarchy":[
        "tgn:7177774",
        "tgn:7000096",
        "tgn:1000003",
        "tgn:7000084",
        "tgn:7029392"
    ],
    "tgn:id":7177774,
    "tgn:name":"Hannemannei",
    "tgn:placetype":[
        "aat:300008347"
    ]
},
  "bbox": [],
  "geometry": {"coordinates":[14.266667,52.166667],"type":"Point"}
}