{
  "id": 7036007,
  "type": "Feature",
  "properties": {
    "tgn:hierarchy":[
        "tgn:7036007",
        "tgn:7002991",
        "tgn:1000003",
        "tgn:7002997",
        "tgn:1000080",
        "tgn:7029392"
    ],
    "tgn:id":7036007,
    "tgn:name":"Alvera",
    "tgn:placetype":[
        "aat:300008347"
    ]
},
  "bbox": [],
  "geometry": {"coordinates":[12.155556,46.548889],"type":"Point"}
}