{
  "id": 1014174,
  "type": "Feature",
  "properties": {
    "tgn:hierarchy":[
        "tgn:1014174",
        "tgn:7005685",
        "tgn:7005807",
        "tgn:1000001",
        "tgn:7005801",
        "tgn:7029392"
    ],
    "tgn:id":1014174,
    "tgn:name":"Change Islands",
    "tgn:placetype":[
        "aat:300008347"
    ]
},
  "bbox": [],
  "geometry": {"coordinates":[-54.3833,49.6333],"type":"Point"}
}