{
  "id": 7265928,
  "type": "Feature",
  "properties": {
    "tgn:concordances":{
        "gn:id":"2752649"
    },
    "tgn:hierarchy":[
        "tgn:7265928",
        "tgn:7003616",
        "tgn:1000003",
        "tgn:7016845",
        "tgn:7029392"
    ],
    "tgn:id":7265928,
    "tgn:name:nl":"Klidse",
    "tgn:placetype":[
        "aat:300008347"
    ]
},
  "bbox": [],
  "geometry": {"coordinates":[6.016667,53.016667],"type":"Point"}
}