{
  "id": 2594918,
  "type": "Feature",
  "properties": {
    "tgn:hierarchy":[
        "tgn:2594918",
        "tgn:1000001",
        "tgn:7012149",
        "tgn:2001886",
        "tgn:7007825",
        "tgn:7029392"
    ],
    "tgn:id":2594918,
    "tgn:name":"Possumtrot Branch",
    "tgn:placetype":[
        "aat:300008699"
    ]
},
  "bbox": [],
  "geometry": {"coordinates":[-87.3167,35.35],"type":"Point"}
}