{
  "id": 2396573,
  "type": "Feature",
  "properties": {
    "tgn:hierarchy":[
        "tgn:2396573",
        "tgn:1000001",
        "tgn:2001436",
        "tgn:7012149",
        "tgn:7007566",
        "tgn:7029392"
    ],
    "tgn:id":2396573,
    "tgn:name":"Holt Tank",
    "tgn:placetype":[
        "aat:300006191"
    ]
},
  "bbox": [],
  "geometry": {"coordinates":[-104.8167,32.65],"type":"Point"}
}