{
  "id": 2355097,
  "type": "Feature",
  "properties": {
    "tgn:hierarchy":[
        "tgn:2355097",
        "tgn:1000001",
        "tgn:7012149",
        "tgn:7007157",
        "tgn:2000184",
        "tgn:7029392"
    ],
    "tgn:id":2355097,
    "tgn:name":"Goodrich Creek",
    "tgn:placetype":[
        "aat:300008706"
    ]
},
  "bbox": [],
  "geometry": {"coordinates":[-120.9667,40.3833],"type":"Point"}
}