{
  "id": 2223467,
  "type": "Feature",
  "properties": {
    "tgn:hierarchy":[
        "tgn:2223467",
        "tgn:1000001",
        "tgn:2000312",
        "tgn:7012149",
        "tgn:7007248",
        "tgn:7029392"
    ],
    "tgn:id":2223467,
    "tgn:name":"Cartee Lake",
    "tgn:placetype":[
        "aat:300006191"
    ]
},
  "bbox": [],
  "geometry": {"coordinates":[-82.0667,32.45],"type":"Point"}
}