{
  "id": 2580984,
  "type": "Feature",
  "properties": {
    "tgn:hierarchy":[
        "tgn:2580984",
        "tgn:1000001",
        "tgn:7012149",
        "tgn:7014398",
        "tgn:7013961",
        "tgn:7029392"
    ],
    "tgn:id":2580984,
    "tgn:name":"Pike Knob",
    "tgn:placetype":[
        "aat:300008798"
    ]
},
  "bbox": [],
  "geometry": {"coordinates":[-79.4333,38.6667],"type":"Point"}
}