<<<<<<< HEAD
{
  "id": 7023639,
  "type": "Feature",
  "properties": {
    "tgn:hierarchy":[
        "tgn:7023639",
        "tgn:1000001",
        "tgn:7012149",
        "tgn:7029392"
    ],
    "tgn:id":7023639,
    "tgn:name":"Patton Creek",
    "tgn:placetype":[
        "aat:300008706"
    ]
},
  "bbox": [],
  "geometry": {"coordinates":[-88.5833,31.7167],"type":"Point"}
}
=======
{"geometry":{"type":"Point","coordinates":[-88.583300,31.716700]},"type":"Feature","properties":{"hierarchy":["tgn:7023639","tgn:1000001","tgn:7012149","tgn:7029392"],"placetype":["aat:300008706"],"id":7023639,"name:xx":"Patton Creek"}}
>>>>>>> 03f74aca74312dbeaf24d7e61306dd6a786dc3d0
