{
  "id": 2271929,
  "type": "Feature",
  "properties": {
    "tgn:hierarchy":[
        "tgn:2271929",
        "tgn:1000001",
        "tgn:7012149",
        "tgn:2001237",
        "tgn:7007523",
        "tgn:7029392"
    ],
    "tgn:id":2271929,
    "tgn:name":"Cupola Pond",
    "tgn:placetype":[
        "aat:300008680"
    ]
},
  "bbox": [],
  "geometry": {"coordinates":[-91.0833,36.7833],"type":"Point"}
}