{
  "id": 2418721,
  "type": "Feature",
  "properties": {
    "tgn:hierarchy":[
        "tgn:2418721",
        "tgn:1002175",
        "tgn:1000001",
        "tgn:7012149",
        "tgn:7007706",
        "tgn:7029392"
    ],
    "tgn:id":2418721,
    "tgn:name":"Jakes Run",
    "tgn:placetype":[
        "aat:300008699"
    ]
},
  "bbox": [],
  "geometry": {"coordinates":[-81.0833,39.9833],"type":"Point"}
}