{
  "id": 7215877,
  "type": "Feature",
  "properties": {
    "tgn:hierarchy":[
        "tgn:7215877",
        "tgn:1000003",
        "tgn:7003676",
        "tgn:7000084",
        "tgn:7029392"
    ],
    "tgn:id":7215877,
    "tgn:name":"Aksmoor",
    "tgn:placetype":[
        "aat:300386886"
    ]
},
  "bbox": [],
  "geometry": {"coordinates":[9.583333,53.066667],"type":"Point"}
}