{
  "id": 7153143,
  "type": "Feature",
  "properties": {
    "tgn:hierarchy":[
        "tgn:7153143",
        "tgn:1000003",
        "tgn:7003676",
        "tgn:7000084",
        "tgn:7029392"
    ],
    "tgn:id":7153143,
    "tgn:name":"Karolinen-H\u00f6he",
    "tgn:placetype":[
        "aat:300008777"
    ]
},
  "bbox": [],
  "geometry": {"coordinates":[8.833333,53.616667],"type":"Point"}
}