{
  "id": 7592775,
  "type": "Feature",
  "properties": {
    "tgn:hierarchy":[
        "tgn:7592775",
        "tgn:1000004",
        "tgn:7000198",
        "tgn:7000799",
        "tgn:7029392"
    ],
    "tgn:id":7592775,
    "tgn:name:en":"Bhulw\u0101l",
    "tgn:placetype":[
        "aat:300008347"
    ]
},
  "bbox": [],
  "geometry": {"coordinates":[74.819319,32.837127],"type":"Point"}
}