{
  "id": 2357136,
  "type": "Feature",
  "properties": {
    "tgn:hierarchy":[
        "tgn:2357136",
        "tgn:2002130",
        "tgn:1000001",
        "tgn:7012149",
        "tgn:7007828",
        "tgn:7029392"
    ],
    "tgn:id":2357136,
    "tgn:name":"Gould Brook",
    "tgn:placetype":[
        "aat:300008699"
    ]
},
  "bbox": [],
  "geometry": {"coordinates":[-72.9833,43.8667],"type":"Point"}
}