{
  "id": 2684886,
  "type": "Feature",
  "properties": {
    "tgn:hierarchy":[
        "tgn:2684886",
        "tgn:1000001",
        "tgn:7012149",
        "tgn:2000805",
        "tgn:7007255",
        "tgn:7029392"
    ],
    "tgn:id":2684886,
    "tgn:name":"Split Log Branch",
    "tgn:placetype":[
        "aat:300008699"
    ]
},
  "bbox": [],
  "geometry": {"coordinates":[-83.05,37.4833],"type":"Point"}
}