{
  "id": 2626796,
  "type": "Feature",
  "properties": {
    "tgn:hierarchy":[
        "tgn:2626796",
        "tgn:1000001",
        "tgn:7012149",
        "tgn:2001295",
        "tgn:7007524",
        "tgn:7029392"
    ],
    "tgn:id":2626796,
    "tgn:name":"Rocky Point",
    "tgn:placetype":[
        "aat:300008850"
    ]
},
  "bbox": [],
  "geometry": {"coordinates":[-108.1833,48.35],"type":"Point"}
}