{
  "id": 2290395,
  "type": "Feature",
  "properties": {
    "tgn:hierarchy":[
        "tgn:2290395",
        "tgn:1000001",
        "tgn:7012149",
        "tgn:1002862",
        "tgn:7007920",
        "tgn:7029392"
    ],
    "tgn:id":2290395,
    "tgn:name":"Doe Bay",
    "tgn:placetype":[
        "aat:300132316"
    ]
},
  "bbox": [],
  "geometry": {"coordinates":[-122.7667,48.6333],"type":"Point"}
}