{
  "id": 7501635,
  "type": "Feature",
  "properties": {
    "tgn:hierarchy":[
        "tgn:7501635",
        "tgn:7488858",
        "tgn:1000004",
        "tgn:1000141",
        "tgn:7029392"
    ],
    "tgn:id":7501635,
    "tgn:name":"Shuangfu Suidao",
    "tgn:placetype":[
        "aat:300007899"
    ]
},
  "bbox": [],
  "geometry": {"coordinates":[120.831013,24.025653],"type":"Point"}
}