<<<<<<< HEAD
{
  "id": 7369782,
  "type": "Feature",
  "properties": {
    "tgn:hierarchy":[
        "tgn:7369782",
        "tgn:1000001",
        "tgn:7005595",
        "tgn:7005560",
        "tgn:7029392"
    ],
    "tgn:id":7369782,
    "tgn:name":"Jacola",
    "tgn:placetype":[
        "aat:300008347"
    ]
},
  "bbox": [],
  "geometry": {"coordinates":[-107.133333,24.166667],"type":"Point"}
}
=======
{"geometry":{"type":"Point","coordinates":[-107.133333,24.166667]},"type":"Feature","properties":{"hierarchy":["tgn:7369782","tgn:1000001","tgn:7005595","tgn:7005560","tgn:7029392"],"placetype":["aat:300008347"],"id":7369782,"name:xx":"Jacola"}}
>>>>>>> 03f74aca74312dbeaf24d7e61306dd6a786dc3d0
