{
  "id": 2249820,
  "type": "Feature",
  "properties": {
    "tgn:hierarchy":[
        "tgn:2249820",
        "tgn:1000001",
        "tgn:7012149",
        "tgn:1002392",
        "tgn:7007157",
        "tgn:7029392"
    ],
    "tgn:id":2249820,
    "tgn:name":"College Lake",
    "tgn:placetype":[
        "aat:300008680"
    ]
},
  "bbox": [],
  "geometry": {"coordinates":[-119.1667,37.2833],"type":"Point"}
}