{
  "id": 7398226,
  "type": "Feature",
  "properties": {
    "tgn:hierarchy":[
        "tgn:7398226",
        "tgn:1000001",
        "tgn:1001960",
        "tgn:7005560",
        "tgn:7029392"
    ],
    "tgn:id":7398226,
    "tgn:name":"La Joya",
    "tgn:placetype":[
        "aat:300006191"
    ]
},
  "bbox": [],
  "geometry": {"coordinates":[-111.080278,30.842778],"type":"Point"}
}