{
  "id": 2022201,
  "type": "Feature",
  "properties": {
    "tgn:hierarchy":[
        "tgn:2022201",
        "tgn:1000001",
        "tgn:2000316",
        "tgn:7012149",
        "tgn:7007248",
        "tgn:7029392"
    ],
    "tgn:id":2022201,
    "tgn:name":"Bloomingdale",
    "tgn:placetype":[
        "aat:300008347"
    ]
},
  "bbox": [],
  "geometry": {"coordinates":[-81.2833,32.1167],"type":"Point"}
}