{
  "id": 2346406,
  "type": "Feature",
  "properties": {
    "tgn:hierarchy":[
        "tgn:2346406",
        "tgn:1000001",
        "tgn:2001594",
        "tgn:7012149",
        "tgn:7007705",
        "tgn:7029392"
    ],
    "tgn:id":2346406,
    "tgn:name":"Gatten Lake",
    "tgn:placetype":[
        "aat:300008680"
    ]
},
  "bbox": [],
  "geometry": {"coordinates":[-100.15,48.9833],"type":"Point"}
}