{
  "id": 1071360,
  "type": "Feature",
  "properties": {
    "tgn:hierarchy":[
        "tgn:1071360",
        "tgn:1000004",
        "tgn:7002081",
        "tgn:1000111",
        "tgn:7029392"
    ],
    "tgn:id":1071360,
    "tgn:name":"Sanxingzhen",
    "tgn:placetype":[
        "aat:300008347"
    ]
},
  "bbox": [],
  "geometry": {"coordinates":[121.5833,31.8333],"type":"Point"}
}