{
  "id": 7120364,
  "type": "Feature",
  "properties": {
    "tgn:hierarchy":[
        "tgn:7120364",
        "tgn:7003669",
        "tgn:1000003",
        "tgn:7000084",
        "tgn:7029392"
    ],
    "tgn:id":7120364,
    "tgn:name":"Paunzhausen",
    "tgn:placetype":[
        "aat:300008347"
    ]
},
  "bbox": [],
  "geometry": {"coordinates":[11.566667,48.483333],"type":"Point"}
}