{
  "id": 7377703,
  "type": "Feature",
  "properties": {
    "tgn:hierarchy":[
        "tgn:7377703",
        "tgn:7005581",
        "tgn:1000001",
        "tgn:7005560",
        "tgn:7029392"
    ],
    "tgn:id":7377703,
    "tgn:name":"La Soledad",
    "tgn:placetype":[
        "aat:300008347"
    ]
},
  "bbox": [],
  "geometry": {"coordinates":[-107.35,28.866667],"type":"Point"}
}