{
  "id": 2527616,
  "type": "Feature",
  "properties": {
    "tgn:hierarchy":[
        "tgn:2527616",
        "tgn:1000001",
        "tgn:7012149",
        "tgn:2002296",
        "tgn:7013961",
        "tgn:7029392"
    ],
    "tgn:id":2527616,
    "tgn:name":"Mount Zion Ridge",
    "tgn:placetype":[
        "aat:300266640"
    ]
},
  "bbox": [],
  "geometry": {"coordinates":[-79.75,39.1333],"type":"Point"}
}