{
  "id": 1027304,
  "type": "Feature",
  "properties": {
    "tgn:hierarchy":[
        "tgn:1027304",
        "tgn:7027133",
        "tgn:1000003",
        "tgn:7011765",
        "tgn:7029392"
    ],
    "tgn:id":1027304,
    "tgn:name":"Krompachy",
    "tgn:placetype":[
        "aat:300008347"
    ]
},
  "bbox": [],
  "geometry": {"coordinates":[20.8667,48.9167],"type":"Point"}
}