{
  "id": 1071816,
  "type": "Feature",
  "properties": {
    "tgn:hierarchy":[
        "tgn:1071816",
        "tgn:1000004",
        "tgn:1001390",
        "tgn:1000111",
        "tgn:7029392"
    ],
    "tgn:id":1071816,
    "tgn:name":"Shuangmiaozi",
    "tgn:placetype":[
        "aat:300008347"
    ]
},
  "bbox": [],
  "geometry": {"coordinates":[121.8667,42.0333],"type":"Point"}
}