{
  "id": 2358962,
  "type": "Feature",
  "properties": {
    "tgn:hierarchy":[
        "tgn:2358962",
        "tgn:1000001",
        "tgn:7012149",
        "tgn:1002899",
        "tgn:7007920",
        "tgn:7029392"
    ],
    "tgn:id":2358962,
    "tgn:name":"Granite Falls Reservoir",
    "tgn:placetype":[
        "aat:300006191"
    ]
},
  "bbox": [],
  "geometry": {"coordinates":[-121.9333,48.0833],"type":"Point"}
}