{
  "id": 7114185,
  "type": "Feature",
  "properties": {
    "tgn:hierarchy":[
        "tgn:7114185",
        "tgn:7003692",
        "tgn:1000003",
        "tgn:7000084",
        "tgn:7029392"
    ],
    "tgn:id":7114185,
    "tgn:name":"Riedhof",
    "tgn:placetype":[
        "aat:300000206"
    ]
},
  "bbox": [],
  "geometry": {"coordinates":[9.416667,47.766667],"type":"Point"}
}