{
  "id": 2025897,
  "type": "Feature",
  "properties": {
    "tgn:hierarchy":[
        "tgn:2025897",
        "tgn:1000001",
        "tgn:7012149",
        "tgn:2000485",
        "tgn:7007250",
        "tgn:7029392"
    ],
    "tgn:id":2025897,
    "tgn:name":"Minidoka",
    "tgn:placetype":[
        "aat:300008347"
    ]
},
  "bbox": [],
  "geometry": {"coordinates":[-113.4833,42.75],"type":"Point"}
}