<<<<<<< HEAD
{
  "id": 2150901,
  "type": "Feature",
  "properties": {
    "tgn:hierarchy":[
        "tgn:2150901",
        "tgn:1000001",
        "tgn:7016172",
        "tgn:7012149",
        "tgn:2000175",
        "tgn:7029392"
    ],
    "tgn:id":2150901,
    "tgn:name":"Bass Mountain",
    "tgn:placetype":[
        "aat:300008798"
    ]
},
  "bbox": [],
  "geometry": {"coordinates":[-92.7,35.4667],"type":"Point"}
}
=======
{"geometry":{"type":"Point","coordinates":[-92.700000,35.466700]},"type":"Feature","properties":{"hierarchy":["tgn:2150901","tgn:1000001","tgn:7016172","tgn:7012149","tgn:2000175","tgn:7029392"],"placetype":["aat:300008798"],"id":2150901,"name:xx":"Bass Mountain"}}
>>>>>>> 03f74aca74312dbeaf24d7e61306dd6a786dc3d0
