{
  "id": 2697450,
  "type": "Feature",
  "properties": {
    "tgn:hierarchy":[
        "tgn:2697450",
        "tgn:1000001",
        "tgn:7012149",
        "tgn:7007157",
        "tgn:1003050",
        "tgn:7029392"
    ],
    "tgn:id":2697450,
    "tgn:name":"Stony Point",
    "tgn:placetype":[
        "aat:300008850"
    ]
},
  "bbox": [],
  "geometry": {"coordinates":[-121.15,39.45],"type":"Point"}
}