<<<<<<< HEAD
{
  "id": 7372430,
  "type": "Feature",
  "properties": {
    "tgn:hierarchy":[
        "tgn:7372430",
        "tgn:1000001",
        "tgn:1001893",
        "tgn:7005560",
        "tgn:7029392"
    ],
    "tgn:id":7372430,
    "tgn:name":"La Estancia",
    "tgn:placetype":[
        "aat:300008347"
    ]
},
  "bbox": [],
  "geometry": {"coordinates":[-99.7,20.083333],"type":"Point"}
}
=======
{"geometry":{"type":"Point","coordinates":[-99.700000,20.083333]},"type":"Feature","properties":{"hierarchy":["tgn:7372430","tgn:1000001","tgn:1001893","tgn:7005560","tgn:7029392"],"placetype":["aat:300008347"],"id":7372430,"name:xx":"La Estancia"}}
>>>>>>> 03f74aca74312dbeaf24d7e61306dd6a786dc3d0
