{
  "id": 2708093,
  "type": "Feature",
  "properties": {
    "tgn:hierarchy":[
        "tgn:2708093",
        "tgn:1000001",
        "tgn:7012149",
        "tgn:2000291",
        "tgn:7007240",
        "tgn:7029392"
    ],
    "tgn:id":2708093,
    "tgn:name":"Swindle Swamp",
    "tgn:placetype":[
        "aat:300008905"
    ]
},
  "bbox": [],
  "geometry": {"coordinates":[-85.5333,30.5167],"type":"Point"}
}