{
  "id": 2786210,
  "type": "Feature",
  "properties": {
    "tgn:hierarchy":[
        "tgn:2786210",
        "tgn:1000001",
        "tgn:7012149",
        "tgn:7021313",
        "tgn:7007521",
        "tgn:7029392"
    ],
    "tgn:id":2786210,
    "tgn:name":"Youngs Bay",
    "tgn:placetype":[
        "aat:300132316"
    ]
},
  "bbox": [],
  "geometry": {"coordinates":[-94.9667,49.3333],"type":"Point"}
}