{
  "id": 2508673,
  "type": "Feature",
  "properties": {
    "tgn:hierarchy":[
        "tgn:2508673",
        "tgn:1000001",
        "tgn:7012149",
        "tgn:7007254",
        "tgn:7029392"
    ],
    "tgn:id":2508673,
    "tgn:name":"Middle Emma Creek",
    "tgn:placetype":[
        "aat:300008706"
    ]
},
  "bbox": [],
  "geometry": {"coordinates":[-97.35,38.2833],"type":"Point"}
}