{
  "id": 7403849,
  "type": "Feature",
  "properties": {
    "tgn:hierarchy":[
        "tgn:7403849",
        "tgn:1000001",
        "tgn:1001906",
        "tgn:7005560",
        "tgn:7029392"
    ],
    "tgn:id":7403849,
    "tgn:name":"El Naranjo",
    "tgn:placetype":[
        "aat:300008347"
    ]
},
  "bbox": [],
  "geometry": {"coordinates":[-105.2375,22.841667],"type":"Point"}
}