{
  "id": 2006745,
  "type": "Feature",
  "properties": {
    "tgn:hierarchy":[
        "tgn:2006745",
        "tgn:1000001",
        "tgn:7006451",
        "tgn:7012149",
        "tgn:2000103",
        "tgn:7029392"
    ],
    "tgn:id":2006745,
    "tgn:name":"Drake",
    "tgn:placetype":[
        "aat:300008347",
        "aat:300387210"
    ]
},
  "bbox": [],
  "geometry": {"coordinates":[-112.3667,34.9667],"type":"Point"}
}