{
  "id": 2226040,
  "type": "Feature",
  "properties": {
    "tgn:hierarchy":[
        "tgn:2226040",
        "tgn:1000001",
        "tgn:7012149",
        "tgn:2000898",
        "tgn:7007256",
        "tgn:7029392"
    ],
    "tgn:id":2226040,
    "tgn:name":"Cataouatche, Lake",
    "tgn:placetype":[
        "aat:300008680"
    ]
},
  "bbox": [],
  "geometry": {"coordinates":[-90.2333,29.8333],"type":"Point"}
}