{
  "id": 7245124,
  "type": "Feature",
  "properties": {
    "tgn:hierarchy":[
        "tgn:7245124",
        "tgn:7007877",
        "tgn:1000003",
        "tgn:1000063",
        "tgn:4012014",
        "tgn:7029392"
    ],
    "tgn:id":7245124,
    "tgn:name":"Barbesioneau",
    "tgn:placetype":[
        "aat:300008699"
    ]
},
  "bbox": [],
  "geometry": {"coordinates":[4.25,50.216667],"type":"Point"}
}