{
  "id": 7469594,
  "type": "Feature",
  "properties": {
    "tgn:hierarchy":[
        "tgn:7469594",
        "tgn:1000004",
        "tgn:7490934",
        "tgn:1000141",
        "tgn:7029392"
    ],
    "tgn:id":7469594,
    "tgn:name":"Zhongliao",
    "tgn:placetype":[
        "aat:300008347"
    ]
},
  "bbox": [],
  "geometry": {"coordinates":[120.317222,23.395556],"type":"Point"}
}