{
  "id": 7562375,
  "type": "Feature",
  "properties": {
    "tgn:hierarchy":[
        "tgn:7562375",
        "tgn:1000004",
        "tgn:7000198",
        "tgn:1001894",
        "tgn:7029392"
    ],
    "tgn:id":7562375,
    "tgn:name:en":"Sagra",
    "tgn:placetype":[
        "aat:300008347"
    ]
},
  "bbox": [],
  "geometry": {"coordinates":[79.000948,26.44513],"type":"Point"}
}