{
  "id": 2382186,
  "type": "Feature",
  "properties": {
    "tgn:hierarchy":[
        "tgn:2382186",
        "tgn:1000001",
        "tgn:7012149",
        "tgn:2001295",
        "tgn:7007524",
        "tgn:7029392"
    ],
    "tgn:id":2382186,
    "tgn:name":"Haynes Coulee",
    "tgn:placetype":[
        "aat:300008761"
    ]
},
  "bbox": [],
  "geometry": {"coordinates":[-107.3167,48.5667],"type":"Point"}
}