<<<<<<< HEAD
{
  "id": 2400150,
  "type": "Feature",
  "properties": {
    "tgn:hierarchy":[
        "tgn:2400150",
        "tgn:1000001",
        "tgn:7012149",
        "tgn:2001713",
        "tgn:7007708",
        "tgn:7029392"
    ],
    "tgn:id":2400150,
    "tgn:name":"Horse Creek",
    "tgn:placetype":[
        "aat:300008706"
    ]
},
  "bbox": [],
  "geometry": {"coordinates":[-123.6667,42.3333],"type":"Point"}
}
=======
{"geometry":{"type":"Point","coordinates":[-123.666700,42.333300]},"type":"Feature","properties":{"hierarchy":["tgn:2400150","tgn:1000001","tgn:7012149","tgn:2001713","tgn:7007708","tgn:7029392"],"placetype":["aat:300008706"],"id":2400150,"name:xx":"Horse Creek"}}
>>>>>>> 03f74aca74312dbeaf24d7e61306dd6a786dc3d0
