{
  "id": 7323312,
  "type": "Feature",
  "properties": {
    "tgn:hierarchy":[
        "tgn:7323312",
        "tgn:7002825",
        "tgn:7016622",
        "tgn:1000003",
        "tgn:1000095",
        "tgn:7029392"
    ],
    "tgn:id":7323312,
    "tgn:name":"Rosario, Puerto del",
    "tgn:placetype":[
        "aat:300132316"
    ]
},
  "bbox": [],
  "geometry": {"coordinates":[-13.85,28.483333],"type":"Point"}
}