{
  "id": 1010446,
  "type": "Feature",
  "properties": {
    "tgn:hierarchy":[
        "tgn:1010446",
        "tgn:1007992",
        "tgn:1001407",
        "tgn:1000233",
        "tgn:1000006",
        "tgn:7029392"
    ],
    "tgn:id":1010446,
    "tgn:name":"Aracides, Cape",
    "tgn:placetype":[
        "aat:300008850"
    ]
},
  "bbox": [],
  "geometry": {"coordinates":[161.0167,-8.6167],"type":"Point"}
}