{
  "id": 7591197,
  "type": "Feature",
  "properties": {
    "tgn:hierarchy":[
        "tgn:7591197",
        "tgn:1000004",
        "tgn:7000198",
        "tgn:7000799",
        "tgn:7029392"
    ],
    "tgn:id":7591197,
    "tgn:name:en":"Gan",
    "tgn:placetype":[
        "aat:300008347"
    ]
},
  "bbox": [],
  "geometry": {"coordinates":[74.143056,33.180556],"type":"Point"}
}