{
  "id": 7332583,
  "type": "Feature",
  "properties": {
    "tgn:hierarchy":[
        "tgn:7332583",
        "tgn:7007780",
        "tgn:1000003",
        "tgn:7009604",
        "tgn:1000095",
        "tgn:7029392"
    ],
    "tgn:id":7332583,
    "tgn:name":"Iraeta",
    "tgn:placetype":[
        "aat:300008347"
    ]
},
  "bbox": [],
  "geometry": {"coordinates":[-2.260491,43.254781],"type":"Point"}
}