{
  "id": 7446639,
  "type": "Feature",
  "properties": {
    "tgn:hierarchy":[
        "tgn:7446639",
        "tgn:7002444",
        "tgn:1000003",
        "tgn:7008082",
        "tgn:7008591",
        "tgn:7029392"
    ],
    "tgn:id":7446639,
    "tgn:name:en":"Slaggan",
    "tgn:placetype":[
        "aat:300008347"
    ]
},
  "bbox": [],
  "geometry": {"coordinates":[-5.633333,57.883333],"type":"Point"}
}