{
  "id": 2706418,
  "type": "Feature",
  "properties": {
    "tgn:hierarchy":[
        "tgn:2706418",
        "tgn:7014651",
        "tgn:1000001",
        "tgn:7012149",
        "tgn:7007516",
        "tgn:7029392"
    ],
    "tgn:id":2706418,
    "tgn:name":"Swan Creek",
    "tgn:placetype":[
        "aat:300008706"
    ]
},
  "bbox": [],
  "geometry": {"coordinates":[-76.5333,39.1833],"type":"Point"}
}