{
  "id": 2141260,
  "type": "Feature",
  "properties": {
    "tgn:hierarchy":[
        "tgn:2141260",
        "tgn:1000001",
        "tgn:7012149",
        "tgn:2001719",
        "tgn:7007708",
        "tgn:7029392"
    ],
    "tgn:id":2141260,
    "tgn:name":"Ayers Canyon",
    "tgn:placetype":[
        "aat:300008761"
    ]
},
  "bbox": [],
  "geometry": {"coordinates":[-119.2667,45.4333],"type":"Point"}
}