{
  "id": 2385870,
  "type": "Feature",
  "properties": {
    "tgn:hierarchy":[
        "tgn:2385870",
        "tgn:1000001",
        "tgn:7012149",
        "tgn:7007157",
        "tgn:1002684",
        "tgn:7029392"
    ],
    "tgn:id":2385870,
    "tgn:name":"Hennicksons Ridge",
    "tgn:placetype":[
        "aat:300266640"
    ]
},
  "bbox": [],
  "geometry": {"coordinates":[-121.6333,36.35],"type":"Point"}
}