{
  "id": 2679694,
  "type": "Feature",
  "properties": {
    "tgn:hierarchy":[
        "tgn:2679694",
        "tgn:1000001",
        "tgn:1002260",
        "tgn:7012149",
        "tgn:7007920",
        "tgn:7029392"
    ],
    "tgn:id":2679694,
    "tgn:name":"South Fork Preston Creek",
    "tgn:placetype":[
        "aat:300008706"
    ]
},
  "bbox": [],
  "geometry": {"coordinates":[-120.35,47.8833],"type":"Point"}
}