{
  "id": 7199365,
  "type": "Feature",
  "properties": {
    "tgn:hierarchy":[
        "tgn:7199365",
        "tgn:1000003",
        "tgn:7000094",
        "tgn:7000084",
        "tgn:7029392"
    ],
    "tgn:id":7199365,
    "tgn:name":"Dweer Berg",
    "tgn:placetype":[
        "aat:300008777"
    ]
},
  "bbox": [],
  "geometry": {"coordinates":[11.716667,53.483333],"type":"Point"}
}