{
  "id": 7544240,
  "type": "Feature",
  "properties": {
    "tgn:hierarchy":[
        "tgn:7544240",
        "tgn:7001242",
        "tgn:1001059",
        "tgn:7016833",
        "tgn:7029392"
    ],
    "tgn:id":7544240,
    "tgn:name:en":"Bitilt\u012bsh, Barr",
    "tgn:placetype":[
        "aat:300386885"
    ]
},
  "bbox": [],
  "geometry": {"coordinates":[31.875,31.316667],"type":"Point"}
}