{
  "id": 2694284,
  "type": "Feature",
  "properties": {
    "tgn:hierarchy":[
        "tgn:2694284",
        "tgn:1000001",
        "tgn:7006451",
        "tgn:7012149",
        "tgn:2000103",
        "tgn:7029392"
    ],
    "tgn:id":2694284,
    "tgn:name":"Stevens Tank",
    "tgn:placetype":[
        "aat:300006191"
    ]
},
  "bbox": [],
  "geometry": {"coordinates":[-112.8333,34.5667],"type":"Point"}
}