{
  "id": 7553413,
  "type": "Feature",
  "properties": {
    "tgn:hierarchy":[
        "tgn:7553413",
        "tgn:1000004",
        "tgn:7000198",
        "tgn:7000799",
        "tgn:7029392"
    ],
    "tgn:id":7553413,
    "tgn:name:en":"M\u0101rtand",
    "tgn:placetype":[
        "aat:300008347"
    ]
},
  "bbox": [],
  "geometry": {"coordinates":[75.216667,33.75],"type":"Point"}
}