{
  "id": 2386324,
  "type": "Feature",
  "properties": {
    "tgn:hierarchy":[
        "tgn:2386324",
        "tgn:1000001",
        "tgn:7012149",
        "tgn:2001876",
        "tgn:7007825",
        "tgn:7029392"
    ],
    "tgn:id":2386324,
    "tgn:name":"Henson Branch",
    "tgn:placetype":[
        "aat:300008699"
    ]
},
  "bbox": [],
  "geometry": {"coordinates":[-88.2833,36.35],"type":"Point"}
}