{
  "id": 7376983,
  "type": "Feature",
  "properties": {
    "tgn:hierarchy":[
        "tgn:7376983",
        "tgn:7005580",
        "tgn:1000001",
        "tgn:7005560",
        "tgn:7029392"
    ],
    "tgn:id":7376983,
    "tgn:name":"Las Mercedes",
    "tgn:placetype":[
        "aat:300008347"
    ]
},
  "bbox": [],
  "geometry": {"coordinates":[-93.45,16.183333],"type":"Point"}
}