{
  "id": 2243928,
  "type": "Feature",
  "properties": {
    "tgn:hierarchy":[
        "tgn:2243928",
        "tgn:1000001",
        "tgn:1002310",
        "tgn:7012149",
        "tgn:7007710",
        "tgn:7029392"
    ],
    "tgn:id":2243928,
    "tgn:name":"Cleversburg Den Cave Two",
    "tgn:placetype":[
        "aat:300008746"
    ]
},
  "bbox": [],
  "geometry": {"coordinates":[-77.4667,40.05],"type":"Point"}
}