{
  "id": 7401177,
  "type": "Feature",
  "properties": {
    "tgn:hierarchy":[
        "tgn:7401177",
        "tgn:1000001",
        "tgn:7005599",
        "tgn:7005560",
        "tgn:7029392"
    ],
    "tgn:id":7401177,
    "tgn:name":"Tetitl\u00e1n",
    "tgn:placetype":[
        "aat:300008347"
    ]
},
  "bbox": [],
  "geometry": {"coordinates":[-97.016667,19.183333],"type":"Point"}
}