{
  "id": 7313460,
  "type": "Feature",
  "properties": {
    "tgn:hierarchy":[
        "tgn:7313460",
        "tgn:1001630",
        "tgn:1000049",
        "tgn:1000002",
        "tgn:7029392"
    ],
    "tgn:id":7313460,
    "tgn:name":"Los Pajaritos, Quebrada",
    "tgn:placetype":[
        "aat:300266554",
        "aat:300008699"
    ]
},
  "bbox": [],
  "geometry": {"coordinates":[-69.966667,-27.416667],"type":"Point"}
}