{
  "id": 2425071,
  "type": "Feature",
  "properties": {
    "tgn:hierarchy":[
        "tgn:2425071",
        "tgn:1000001",
        "tgn:7012149",
        "tgn:2000975",
        "tgn:7007520",
        "tgn:7029392"
    ],
    "tgn:id":2425071,
    "tgn:name":"Johnson Lake",
    "tgn:placetype":[
        "aat:300008680"
    ]
},
  "bbox": [],
  "geometry": {"coordinates":[-87.4167,46.25],"type":"Point"}
}