{
  "id": 2016436,
  "type": "Feature",
  "properties": {
    "tgn:hierarchy":[
        "tgn:2016436",
        "tgn:1000001",
        "tgn:7012149",
        "tgn:2000221",
        "tgn:7007158",
        "tgn:7029392"
    ],
    "tgn:id":2016436,
    "tgn:name":"Twin Spruce",
    "tgn:placetype":[
        "aat:300008347"
    ]
},
  "bbox": [],
  "geometry": {"coordinates":[-105.35,39.8833],"type":"Point"}
}