{
  "id": 7003323,
  "type": "Feature",
  "properties": {
    "tgn:hierarchy":[
        "tgn:7003323",
        "tgn:7003321",
        "tgn:7003030",
        "tgn:1000003",
        "tgn:1000062",
        "tgn:7029392"
    ],
    "tgn:id":7003323,
    "tgn:name":"Kalksburg",
    "tgn:placetype":[
        "aat:300000874"
    ]
},
  "bbox": [],
  "geometry": {"coordinates":[16.25,48.1333],"type":"Point"}
}