{
  "id": 2459427,
  "type": "Feature",
  "properties": {
    "tgn:hierarchy":[
        "tgn:2459427",
        "tgn:1000001",
        "tgn:7012149",
        "tgn:7007157",
        "tgn:1002858",
        "tgn:7029392"
    ],
    "tgn:id":2459427,
    "tgn:name":"Little Potrero Creek",
    "tgn:placetype":[
        "aat:300008706"
    ]
},
  "bbox": [],
  "geometry": {"coordinates":[-116.5667,32.6167],"type":"Point"}
}