{
  "id": 2443485,
  "type": "Feature",
  "properties": {
    "tgn:hierarchy":[
        "tgn:2443485",
        "tgn:1000001",
        "tgn:7012149",
        "tgn:2002099",
        "tgn:7007826",
        "tgn:7029392"
    ],
    "tgn:id":2443485,
    "tgn:name":"La Cabrada Tank",
    "tgn:placetype":[
        "aat:300006191"
    ]
},
  "bbox": [],
  "geometry": {"coordinates":[-99.0333,26.95],"type":"Point"}
}