{
  "id": 2613524,
  "type": "Feature",
  "properties": {
    "tgn:hierarchy":[
        "tgn:2613524",
        "tgn:1000001",
        "tgn:7012149",
        "tgn:2001995",
        "tgn:7007826",
        "tgn:7029392"
    ],
    "tgn:id":2613524,
    "tgn:name":"Reed Tank",
    "tgn:placetype":[
        "aat:300006191"
    ]
},
  "bbox": [],
  "geometry": {"coordinates":[-100.8833,34.55],"type":"Point"}
}