{
  "id": 2722278,
  "type": "Feature",
  "properties": {
    "tgn:hierarchy":[
        "tgn:2722278",
        "tgn:1000001",
        "tgn:7012149",
        "tgn:2002125",
        "tgn:7007827",
        "tgn:7029392"
    ],
    "tgn:id":2722278,
    "tgn:name":"Timpanogos Glacier",
    "tgn:placetype":[
        "aat:300008835"
    ]
},
  "bbox": [],
  "geometry": {"coordinates":[-111.6167,40.35],"type":"Point"}
}