{
  "id": 2419797,
  "type": "Feature",
  "properties": {
    "tgn:hierarchy":[
        "tgn:2419797",
        "tgn:1000001",
        "tgn:7012149",
        "tgn:1002999",
        "tgn:7007526",
        "tgn:7029392"
    ],
    "tgn:id":2419797,
    "tgn:name":"Jay Bird Mine",
    "tgn:placetype":[
        "aat:300000390"
    ]
},
  "bbox": [],
  "geometry": {"coordinates":[-119.2167,39.9833],"type":"Point"}
}