{
  "id": 2069628,
  "type": "Feature",
  "properties": {
    "tgn:hierarchy":[
        "tgn:2069628",
        "tgn:1000001",
        "tgn:1002245",
        "tgn:7012149",
        "tgn:7007568",
        "tgn:7029392"
    ],
    "tgn:id":2069628,
    "tgn:name":"Haskell Flats",
    "tgn:placetype":[
        "aat:300008347"
    ]
},
  "bbox": [],
  "geometry": {"coordinates":[-78.3167,42.15],"type":"Point"}
}