{
  "id": 1074353,
  "type": "Feature",
  "properties": {
    "tgn:hierarchy":[
        "tgn:1074353",
        "tgn:1000004",
        "tgn:7000198",
        "tgn:7000799",
        "tgn:7029392"
    ],
    "tgn:id":1074353,
    "tgn:name:en":"Achh\u012bbal",
    "tgn:placetype":[
        "aat:300008347"
    ]
},
  "bbox": [],
  "geometry": {"coordinates":[75.218351,33.684089],"type":"Point"}
}