{
  "id": 2234889,
  "type": "Feature",
  "properties": {
    "tgn:hierarchy":[
        "tgn:2234889",
        "tgn:1000001",
        "tgn:7012149",
        "tgn:2001508",
        "tgn:7007709",
        "tgn:7029392"
    ],
    "tgn:id":2234889,
    "tgn:name":"Cherry Gap Branch",
    "tgn:placetype":[
        "aat:300008699"
    ]
},
  "bbox": [],
  "geometry": {"coordinates":[-83.15,35.25],"type":"Point"}
}