{
  "id": 2157231,
  "type": "Feature",
  "properties": {
    "tgn:hierarchy":[
        "tgn:2157231",
        "tgn:1000001",
        "tgn:7012149",
        "tgn:7014543",
        "tgn:7007248",
        "tgn:7029392"
    ],
    "tgn:id":2157231,
    "tgn:name":"Beaver Creek",
    "tgn:placetype":[
        "aat:300008706"
    ]
},
  "bbox": [],
  "geometry": {"coordinates":[-84.7667,31.9833],"type":"Point"}
}