{
  "id": 7390336,
  "type": "Feature",
  "properties": {
    "tgn:hierarchy":[
        "tgn:7390336",
        "tgn:1000001",
        "tgn:1001960",
        "tgn:7005560",
        "tgn:7029392"
    ],
    "tgn:id":7390336,
    "tgn:name":"Rancho San Alejandro",
    "tgn:placetype":[
        "aat:300008347"
    ]
},
  "bbox": [],
  "geometry": {"coordinates":[-112.016667,30.716667],"type":"Point"}
}