{
  "id": 2079015,
  "type": "Feature",
  "properties": {
    "tgn:hierarchy":[
        "tgn:2079015",
        "tgn:1000001",
        "tgn:7012149",
        "tgn:1002441",
        "tgn:7007706",
        "tgn:7029392"
    ],
    "tgn:id":2079015,
    "tgn:name":"Colerain Heights",
    "tgn:placetype":[
        "aat:300008347"
    ]
},
  "bbox": [],
  "geometry": {"coordinates":[-84.5833,39.2333],"type":"Point"}
}