{
  "id": 1044134,
  "type": "Feature",
  "properties": {
    "tgn:hierarchy":[
        "tgn:1044134",
        "tgn:1003450",
        "tgn:7007850",
        "tgn:1000003",
        "tgn:1000080",
        "tgn:7029392"
    ],
    "tgn:id":1044134,
    "tgn:name":"Celico",
    "tgn:placetype":[
        "aat:300008347"
    ]
},
  "bbox": [],
  "geometry": {"coordinates":[16.333333,39.316667],"type":"Point"}
}