{
  "id": 2341658,
  "type": "Feature",
  "properties": {
    "tgn:hierarchy":[
        "tgn:2341658",
        "tgn:1000001",
        "tgn:7012149",
        "tgn:2000234",
        "tgn:7007158",
        "tgn:7029392"
    ],
    "tgn:id":2341658,
    "tgn:name":"Frost",
    "tgn:placetype":[
        "aat:300008347"
    ]
},
  "bbox": [],
  "geometry": {"coordinates":[-107.9667,38.5667],"type":"Point"}
}