<<<<<<< HEAD
{
  "id": 7027338,
  "type": "Feature",
  "properties": {
    "tgn:hierarchy":[
        "tgn:7027338",
        "tgn:7002445",
        "tgn:1000003",
        "tgn:7008153",
        "tgn:7008591",
        "tgn:7029392"
    ],
    "tgn:id":7027338,
    "tgn:name":"Bodsham",
    "tgn:placetype":[
        "aat:300008347",
        "aat:300008372"
    ]
},
  "bbox": [],
  "geometry": {"coordinates":[1.0167,51.1667],"type":"Point"}
}
=======
{"geometry":{"type":"Point","coordinates":[1.016700,51.166700]},"type":"Feature","properties":{"hierarchy":["tgn:7027338","tgn:7002445","tgn:1000003","tgn:7008153","tgn:7008591","tgn:7029392"],"placetype":["aat:300008347","aat:300008372"],"id":7027338,"name:xx":"Bodsham"}}
>>>>>>> 03f74aca74312dbeaf24d7e61306dd6a786dc3d0
