{
  "id": 2134148,
  "type": "Feature",
  "properties": {
    "tgn:hierarchy":[
        "tgn:2134148",
        "tgn:7006450",
        "tgn:1000001",
        "tgn:7012149",
        "tgn:2124014",
        "tgn:7029392"
    ],
    "tgn:id":2134148,
    "tgn:name":"Anirak, Lake",
    "tgn:placetype":[
        "aat:300008680"
    ]
},
  "bbox": [],
  "geometry": {"coordinates":[-157.1833,67.1667],"type":"Point"}
}