{
  "id": 1056285,
  "type": "Feature",
  "properties": {
    "tgn:hierarchy":[
        "tgn:1056285",
        "tgn:1000004",
        "tgn:1003379",
        "tgn:7018214",
        "tgn:7002435",
        "tgn:7029392"
    ],
    "tgn:id":1056285,
    "tgn:name":"Shmelikha",
    "tgn:placetype":[
        "aat:300008347"
    ]
},
  "bbox": [],
  "geometry": {"coordinates":[49.9833,58.2667],"type":"Point"}
}