{
  "id": 7253240,
  "type": "Feature",
  "properties": {
    "tgn:hierarchy":[
        "tgn:7253240",
        "tgn:7003466",
        "tgn:1000003",
        "tgn:1000063",
        "tgn:4012014",
        "tgn:7029392"
    ],
    "tgn:id":7253240,
    "tgn:name":"Sur les Sarts",
    "tgn:placetype":[
        "aat:300008347"
    ]
},
  "bbox": [],
  "geometry": {"coordinates":[5.17036,50.457978],"type":"Point"}
}