<<<<<<< HEAD
{
  "id": 2401859,
  "type": "Feature",
  "properties": {
    "tgn:hierarchy":[
        "tgn:2401859",
        "tgn:1000001",
        "tgn:7012149",
        "tgn:2001871",
        "tgn:7007825",
        "tgn:7029392"
    ],
    "tgn:id":2401859,
    "tgn:name":"Horseshoe Lake",
    "tgn:placetype":[
        "aat:300008680"
    ]
},
  "bbox": [],
  "geometry": {"coordinates":[-89.0833,35.4167],"type":"Point"}
}
=======
{"geometry":{"type":"Point","coordinates":[-89.083300,35.416700]},"type":"Feature","properties":{"hierarchy":["tgn:2401859","tgn:1000001","tgn:7012149","tgn:2001871","tgn:7007825","tgn:7029392"],"placetype":["aat:300008680"],"id":2401859,"name:xx":"Horseshoe Lake"}}
>>>>>>> 03f74aca74312dbeaf24d7e61306dd6a786dc3d0
