<<<<<<< HEAD
{
  "id": 7470927,
  "type": "Feature",
  "properties": {
    "tgn:hierarchy":[
        "tgn:7470927",
        "tgn:1000004",
        "tgn:7001013",
        "tgn:1000141",
        "tgn:7029392"
    ],
    "tgn:id":7470927,
    "tgn:name":"Liangzuowu",
    "tgn:placetype":[
        "aat:300008347"
    ]
},
  "bbox": [],
  "geometry": {"coordinates":[121.06796,25.011205],"type":"Point"}
}
=======
{"geometry":{"type":"Point","coordinates":[121.067960,25.011205]},"type":"Feature","properties":{"hierarchy":["tgn:7470927","tgn:1000004","tgn:7001013","tgn:1000141","tgn:7029392"],"placetype":["aat:300008347"],"id":7470927,"name:xx":"Liangzuowu"}}
>>>>>>> 03f74aca74312dbeaf24d7e61306dd6a786dc3d0
