{
  "id": 7573797,
  "type": "Feature",
  "properties": {
    "tgn:hierarchy":[
        "tgn:7573797",
        "tgn:1000004",
        "tgn:7000198",
        "tgn:1001882",
        "tgn:7029392"
    ],
    "tgn:id":7573797,
    "tgn:name:en":"Jade",
    "tgn:placetype":[
        "aat:300008347"
    ]
},
  "bbox": [],
  "geometry": {"coordinates":[75.066667,14.583333],"type":"Point"}
}