{
  "id": 7077993,
  "type": "Feature",
  "properties": {
    "tgn:hierarchy":[
        "tgn:7077993",
        "tgn:1000003",
        "tgn:7003676",
        "tgn:7000084",
        "tgn:7029392"
    ],
    "tgn:id":7077993,
    "tgn:name":"Bernshausen",
    "tgn:placetype":[
        "aat:300008347"
    ]
},
  "bbox": [],
  "geometry": {"coordinates":[10.166667,51.566667],"type":"Point"}
}