{
  "id": 7392360,
  "type": "Feature",
  "properties": {
    "tgn:hierarchy":[
        "tgn:7392360",
        "tgn:1000001",
        "tgn:7005601",
        "tgn:7005560",
        "tgn:7029392"
    ],
    "tgn:id":7392360,
    "tgn:name":"Sabanilla",
    "tgn:placetype":[
        "aat:300008347"
    ]
},
  "bbox": [],
  "geometry": {"coordinates":[-101.366667,24.483333],"type":"Point"}
}