{
  "id": 2412719,
  "type": "Feature",
  "properties": {
    "tgn:hierarchy":[
        "tgn:2412719",
        "tgn:1000001",
        "tgn:2000920",
        "tgn:7012149",
        "tgn:7007515",
        "tgn:7029392"
    ],
    "tgn:id":2412719,
    "tgn:name":"Ingalls",
    "tgn:placetype":[
        "aat:300008347"
    ]
},
  "bbox": [],
  "geometry": {"coordinates":[-70.7167,43.9833],"type":"Point"}
}