{
  "id": 7444608,
  "type": "Feature",
  "properties": {
    "tgn:hierarchy":[
        "tgn:7444608",
        "tgn:7002444",
        "tgn:1000003",
        "tgn:7019121",
        "tgn:7008591",
        "tgn:7029392"
    ],
    "tgn:id":7444608,
    "tgn:name:en":"Westcraigs Station",
    "tgn:placetype":[
        "aat:300007783"
    ]
},
  "bbox": [],
  "geometry": {"coordinates":[-3.75,55.866667],"type":"Point"}
}