<<<<<<< HEAD
{
  "id": 2253606,
  "type": "Feature",
  "properties": {
    "tgn:hierarchy":[
        "tgn:2253606",
        "tgn:1000001",
        "tgn:7012149",
        "tgn:2002128",
        "tgn:7007827",
        "tgn:7029392"
    ],
    "tgn:id":2253606,
    "tgn:name":"Cook Lake",
    "tgn:placetype":[
        "aat:300008680"
    ]
},
  "bbox": [],
  "geometry": {"coordinates":[-111.5333,38.1667],"type":"Point"}
}
=======
{"geometry":{"type":"Point","coordinates":[-111.533300,38.166700]},"type":"Feature","properties":{"hierarchy":["tgn:2253606","tgn:1000001","tgn:7012149","tgn:2002128","tgn:7007827","tgn:7029392"],"placetype":["aat:300008680"],"id":2253606,"name:xx":"Cook Lake"}}
>>>>>>> 03f74aca74312dbeaf24d7e61306dd6a786dc3d0
