{
  "id": 7229326,
  "type": "Feature",
  "properties": {
    "tgn:hierarchy":[
        "tgn:7229326",
        "tgn:7002748",
        "tgn:7001399",
        "tgn:1000003",
        "tgn:1000074",
        "tgn:7029392"
    ],
    "tgn:id":7229326,
    "tgn:name":"Lazar\u00edna",
    "tgn:placetype":[
        "aat:300008347"
    ]
},
  "bbox": [],
  "geometry": {"coordinates":[21.736667,39.4625],"type":"Point"}
}