<<<<<<< HEAD
{
  "id": 7481932,
  "type": "Feature",
  "properties": {
    "tgn:hierarchy":[
        "tgn:7481932",
        "tgn:1000004",
        "tgn:7471332",
        "tgn:1000141",
        "tgn:7029392"
    ],
    "tgn:id":7481932,
    "tgn:name":"Niulanwo Shan",
    "tgn:placetype":[
        "aat:300008798"
    ]
},
  "bbox": [],
  "geometry": {"coordinates":[121.127222,24.765556],"type":"Point"}
}
=======
{"geometry":{"type":"Point","coordinates":[121.127222,24.765556]},"type":"Feature","properties":{"hierarchy":["tgn:7481932","tgn:1000004","tgn:7471332","tgn:1000141","tgn:7029392"],"placetype":["aat:300008798"],"id":7481932,"name:xx":"Niulanwo Shan"}}
>>>>>>> 03f74aca74312dbeaf24d7e61306dd6a786dc3d0
