{
  "id": 1079725,
  "type": "Feature",
  "properties": {
    "tgn:hierarchy":[
        "tgn:1079725",
        "tgn:1000961",
        "tgn:1000004",
        "tgn:7000901",
        "tgn:1000120",
        "tgn:7029392"
    ],
    "tgn:id":1079725,
    "tgn:name":"\u014cta",
    "tgn:placetype":[
        "aat:300008347"
    ]
},
  "bbox": [],
  "geometry": {"coordinates":[131.55,33.5167],"type":"Point"}
}