{
  "id": 7349292,
  "type": "Feature",
  "properties": {
    "tgn:hierarchy":[
        "tgn:7349292",
        "tgn:7005581",
        "tgn:1000001",
        "tgn:7005560",
        "tgn:7029392"
    ],
    "tgn:id":7349292,
    "tgn:name":"Almance\u00f1a",
    "tgn:placetype":[
        "aat:300008347"
    ]
},
  "bbox": [],
  "geometry": {"coordinates":[-105.716667,26.933333],"type":"Point"}
}