{
  "id": 2412341,
  "type": "Feature",
  "properties": {
    "tgn:hierarchy":[
        "tgn:2412341",
        "tgn:1000001",
        "tgn:7012149",
        "tgn:2001524",
        "tgn:7007709",
        "tgn:7029392"
    ],
    "tgn:id":2412341,
    "tgn:name":"Indian Springs",
    "tgn:placetype":[
        "aat:300008347"
    ]
},
  "bbox": [],
  "geometry": {"coordinates":[-77.4167,34.8167],"type":"Point"}
}