{
  "id": 2127661,
  "type": "Feature",
  "properties": {
    "tgn:hierarchy":[
        "tgn:2127661",
        "tgn:1000001",
        "tgn:2001428",
        "tgn:7012149",
        "tgn:7007566",
        "tgn:7029392"
    ],
    "tgn:id":2127661,
    "tgn:name":"Alameda Lateral",
    "tgn:placetype":[
        "aat:300006075"
    ]
},
  "bbox": [],
  "geometry": {"coordinates":[-106.6167,35.1167],"type":"Point"}
}