{
  "id": 2783180,
  "type": "Feature",
  "properties": {
    "tgn:hierarchy":[
        "tgn:2783180",
        "tgn:1000001",
        "tgn:7012149",
        "tgn:7014612",
        "tgn:7007568",
        "tgn:7029392"
    ],
    "tgn:id":2783180,
    "tgn:name":"Wright Island",
    "tgn:placetype":[
        "aat:300008791"
    ]
},
  "bbox": [],
  "geometry": {"coordinates":[-73.7667,40.8833],"type":"Point"}
}