{
  "id": 2757467,
  "type": "Feature",
  "properties": {
    "tgn:hierarchy":[
        "tgn:2757467",
        "tgn:1000001",
        "tgn:2000596",
        "tgn:7012149",
        "tgn:7007253",
        "tgn:7029392"
    ],
    "tgn:id":2757467,
    "tgn:name":"West Benton Ditch",
    "tgn:placetype":[
        "aat:300006075"
    ]
},
  "bbox": [],
  "geometry": {"coordinates":[-95.8333,40.7167],"type":"Point"}
}