{
  "id": 2137617,
  "type": "Feature",
  "properties": {
    "tgn:hierarchy":[
        "tgn:2137617",
        "tgn:1000001",
        "tgn:7012149",
        "tgn:2001927",
        "tgn:7007825",
        "tgn:7029392"
    ],
    "tgn:id":2137617,
    "tgn:name":"Arnold Hollow Spring",
    "tgn:placetype":[
        "aat:300008697"
    ]
},
  "bbox": [],
  "geometry": {"coordinates":[-87.8667,35.25],"type":"Point"}
}