{
  "id": 2721840,
  "type": "Feature",
  "properties": {
    "tgn:hierarchy":[
        "tgn:2721840",
        "tgn:1000001",
        "tgn:7012149",
        "tgn:2002378",
        "tgn:7007923",
        "tgn:7029392"
    ],
    "tgn:id":2721840,
    "tgn:name":"Timber Draw Number 2 Reservoir",
    "tgn:placetype":[
        "aat:300006191"
    ]
},
  "bbox": [],
  "geometry": {"coordinates":[-104.6833,43.3167],"type":"Point"}
}