{
  "id": 2609674,
  "type": "Feature",
  "properties": {
    "tgn:hierarchy":[
        "tgn:2609674",
        "tgn:7030516",
        "tgn:7006450",
        "tgn:1000001",
        "tgn:7012149",
        "tgn:7029392"
    ],
    "tgn:id":2609674,
    "tgn:name":"Reach Point",
    "tgn:placetype":[
        "aat:300008850"
    ]
},
  "bbox": [],
  "geometry": {"coordinates":[-175.95,51.8667],"type":"Point"}
}