{
  "id": 2499921,
  "type": "Feature",
  "properties": {
    "tgn:hierarchy":[
        "tgn:2499921",
        "tgn:1000001",
        "tgn:2001409",
        "tgn:7012149",
        "tgn:7007526",
        "tgn:7029392"
    ],
    "tgn:id":2499921,
    "tgn:name":"McCoy Mine",
    "tgn:placetype":[
        "aat:300000390"
    ]
},
  "bbox": [],
  "geometry": {"coordinates":[-117.4833,39.8667],"type":"Point"}
}