{
  "id": 2102866,
  "type": "Feature",
  "properties": {
    "tgn:hierarchy":[
        "tgn:2102866",
        "tgn:1002148",
        "tgn:1000001",
        "tgn:7012149",
        "tgn:7007826",
        "tgn:7029392"
    ],
    "tgn:id":2102866,
    "tgn:name":"Bradford",
    "tgn:placetype":[
        "aat:300008347",
        "aat:300387210"
    ]
},
  "bbox": [],
  "geometry": {"coordinates":[-95.75,31.9833],"type":"Point"}
}