{
  "id": 7267432,
  "type": "Feature",
  "properties": {
    "tgn:concordances":{
        "gn:id":"2748220"
    },
    "tgn:hierarchy":[
        "tgn:7267432",
        "tgn:1000003",
        "tgn:7003635",
        "tgn:7016845",
        "tgn:7029392"
    ],
    "tgn:id":7267432,
    "tgn:name:nl":"Retranchement",
    "tgn:placetype":[
        "aat:300008347"
    ]
},
  "bbox": [],
  "geometry": {"coordinates":[3.383333,51.35],"type":"Point"}
}