{
  "id": 7224410,
  "type": "Feature",
  "properties": {
    "tgn:hierarchy":[
        "tgn:7224410",
        "tgn:7002690",
        "tgn:7012056",
        "tgn:1000003",
        "tgn:1000074",
        "tgn:7029392"
    ],
    "tgn:id":7224410,
    "tgn:name":"Rodhov\u00e1nion",
    "tgn:placetype":[
        "aat:300008347"
    ]
},
  "bbox": [],
  "geometry": {"coordinates":[23.783333,35.283333],"type":"Point"}
}