{
  "id": 7574736,
  "type": "Feature",
  "properties": {
    "tgn:hierarchy":[
        "tgn:7574736",
        "tgn:1000004",
        "tgn:7000198",
        "tgn:7016883",
        "tgn:7029392"
    ],
    "tgn:id":7574736,
    "tgn:name:en":"Kishanpura",
    "tgn:placetype":[
        "aat:300008347"
    ]
},
  "bbox": [],
  "geometry": {"coordinates":[75.350631,30.931784],"type":"Point"}
}