{
  "id": 7224339,
  "type": "Feature",
  "properties": {
    "tgn:hierarchy":[
        "tgn:7224339",
        "tgn:7002692",
        "tgn:7012056",
        "tgn:1000003",
        "tgn:1000074",
        "tgn:7029392"
    ],
    "tgn:id":7224339,
    "tgn:name":"Ro\u00fassa L\u00edmni",
    "tgn:placetype":[
        "aat:300008347"
    ]
},
  "bbox": [],
  "geometry": {"coordinates":[26.033333,35.216667],"type":"Point"}
}