{
  "id": 7371058,
  "type": "Feature",
  "properties": {
    "tgn:hierarchy":[
        "tgn:7371058",
        "tgn:1000001",
        "tgn:7005601",
        "tgn:7005560",
        "tgn:7029392"
    ],
    "tgn:id":7371058,
    "tgn:name":"Jicacalco",
    "tgn:placetype":[
        "aat:300008347"
    ]
},
  "bbox": [],
  "geometry": {"coordinates":[-103.316667,21.716667],"type":"Point"}
}