{
  "id": 7395412,
  "type": "Feature",
  "properties": {
    "tgn:hierarchy":[
        "tgn:7395412",
        "tgn:7005583",
        "tgn:1000001",
        "tgn:7005560",
        "tgn:7029392"
    ],
    "tgn:id":7395412,
    "tgn:name":"San Diego de Alcal\u00e1",
    "tgn:placetype":[
        "aat:300008347"
    ]
},
  "bbox": [],
  "geometry": {"coordinates":[-105.171111,24.463056],"type":"Point"}
}