{
  "id": 2183285,
  "type": "Feature",
  "properties": {
    "tgn:hierarchy":[
        "tgn:2183285",
        "tgn:1000001",
        "tgn:7012149",
        "tgn:2002125",
        "tgn:7007827",
        "tgn:7029392"
    ],
    "tgn:id":2183285,
    "tgn:name":"Bluff",
    "tgn:placetype":[
        "aat:300000390"
    ]
},
  "bbox": [],
  "geometry": {"coordinates":[-112.0333,39.9667],"type":"Point"}
}