{
  "id": 2693961,
  "type": "Feature",
  "properties": {
    "tgn:hierarchy":[
        "tgn:2693961",
        "tgn:1000001",
        "tgn:7012149",
        "tgn:2001516",
        "tgn:7007709",
        "tgn:7029392"
    ],
    "tgn:id":2693961,
    "tgn:name":"Steve Branch",
    "tgn:placetype":[
        "aat:300008699"
    ]
},
  "bbox": [],
  "geometry": {"coordinates":[-82.85,35.85],"type":"Point"}
}