{
  "id": 2517143,
  "type": "Feature",
  "properties": {
    "tgn:hierarchy":[
        "tgn:2517143",
        "tgn:1002169",
        "tgn:1000001",
        "tgn:7012149",
        "tgn:7007255",
        "tgn:7029392"
    ],
    "tgn:id":2517143,
    "tgn:name":"Minks Run",
    "tgn:placetype":[
        "aat:300008699"
    ]
},
  "bbox": [],
  "geometry": {"coordinates":[-83.7667,38.1667],"type":"Point"}
}