{
  "id": 2778094,
  "type": "Feature",
  "properties": {
    "tgn:hierarchy":[
        "tgn:2778094",
        "tgn:1002141",
        "tgn:1000001",
        "tgn:7012149",
        "tgn:7007568",
        "tgn:7029392"
    ],
    "tgn:id":2778094,
    "tgn:name":"Wirt",
    "tgn:placetype":[
        "aat:300008347"
    ]
},
  "bbox": [],
  "geometry": {"coordinates":[-78.15,42.1333],"type":"Point"}
}