{
  "id": 2705228,
  "type": "Feature",
  "properties": {
    "tgn:hierarchy":[
        "tgn:2705228",
        "tgn:1000001",
        "tgn:7006451",
        "tgn:2000093",
        "tgn:7012149",
        "tgn:7029392"
    ],
    "tgn:id":2705228,
    "tgn:name":"Superior Mine",
    "tgn:placetype":[
        "aat:300000390"
    ]
},
  "bbox": [],
  "geometry": {"coordinates":[-110.75,33.4333],"type":"Point"}
}