{
  "id": 2574887,
  "type": "Feature",
  "properties": {
    "tgn:hierarchy":[
        "tgn:2574887",
        "tgn:1000001",
        "tgn:7012149",
        "tgn:2001531",
        "tgn:7007709",
        "tgn:7029392"
    ],
    "tgn:id":2574887,
    "tgn:name":"Peniel",
    "tgn:placetype":[
        "aat:300008347"
    ]
},
  "bbox": [],
  "geometry": {"coordinates":[-82.1333,35.2333],"type":"Point"}
}