{
  "id": 7519276,
  "type": "Feature",
  "properties": {
    "tgn:hierarchy":[
        "tgn:7519276",
        "tgn:1009227",
        "tgn:1000226",
        "tgn:7016822",
        "tgn:1000006",
        "tgn:7029392"
    ],
    "tgn:id":7519276,
    "tgn:name:en":"Bravo Island",
    "tgn:placetype":[
        "aat:300008791"
    ]
},
  "bbox": [],
  "geometry": {"coordinates":[168.15,-46.966667],"type":"Point"}
}