{
  "id": 2147204,
  "type": "Feature",
  "properties": {
    "tgn:hierarchy":[
        "tgn:2147204",
        "tgn:1000001",
        "tgn:7006451",
        "tgn:7012149",
        "tgn:2000098",
        "tgn:7029392"
    ],
    "tgn:id":2147204,
    "tgn:name":"Bar I-L Wash",
    "tgn:placetype":[
        "aat:300008699"
    ]
},
  "bbox": [],
  "geometry": {"coordinates":[-113.85,34.8333],"type":"Point"}
}