{
  "id": 7239960,
  "type": "Feature",
  "properties": {
    "tgn:hierarchy":[
        "tgn:7239960",
        "tgn:7003460",
        "tgn:1000003",
        "tgn:1000063",
        "tgn:4012014",
        "tgn:7029392"
    ],
    "tgn:id":7239960,
    "tgn:name":"Hac, Ruisseau du",
    "tgn:placetype":[
        "aat:300008699"
    ]
},
  "bbox": [],
  "geometry": {"coordinates":[5.766667,50.616667],"type":"Point"}
}