{
  "id": 2069623,
  "type": "Feature",
  "properties": {
    "tgn:hierarchy":[
        "tgn:2069623",
        "tgn:1000001",
        "tgn:7012149",
        "tgn:7014318",
        "tgn:7007568",
        "tgn:7029392"
    ],
    "tgn:id":2069623,
    "tgn:name":"Hartwick",
    "tgn:placetype":[
        "aat:300008347"
    ]
},
  "bbox": [],
  "geometry": {"coordinates":[-75.0333,42.65],"type":"Point"}
}