{
  "id": 2327478,
  "type": "Feature",
  "properties": {
    "tgn:hierarchy":[
        "tgn:2327478",
        "tgn:1000001",
        "tgn:2000466",
        "tgn:7012149",
        "tgn:7007250",
        "tgn:7029392"
    ],
    "tgn:id":2327478,
    "tgn:name":"First West Lateral",
    "tgn:placetype":[
        "aat:300006075"
    ]
},
  "bbox": [],
  "geometry": {"coordinates":[-111.7667,42.55],"type":"Point"}
}