{
  "id": 2373558,
  "type": "Feature",
  "properties": {
    "tgn:hierarchy":[
        "tgn:2373558",
        "tgn:1000001",
        "tgn:7012149",
        "tgn:1002766",
        "tgn:7007922",
        "tgn:7029392"
    ],
    "tgn:id":2373558,
    "tgn:name":"Hamilton",
    "tgn:placetype":[
        "aat:300008347"
    ]
},
  "bbox": [],
  "geometry": {"coordinates":[-87.9667,43.2833],"type":"Point"}
}