{
  "id": 7200817,
  "type": "Feature",
  "properties": {
    "tgn:hierarchy":[
        "tgn:7200817",
        "tgn:7003669",
        "tgn:1000003",
        "tgn:7000084",
        "tgn:7029392"
    ],
    "tgn:id":7200817,
    "tgn:name":"Eibwang",
    "tgn:placetype":[
        "aat:300000206"
    ]
},
  "bbox": [],
  "geometry": {"coordinates":[11.35,48.983333],"type":"Point"}
}