<<<<<<< HEAD
{
  "id": 7023928,
  "type": "Feature",
  "properties": {
    "tgn:hierarchy":[
        "tgn:7023928",
        "tgn:1000001",
        "tgn:7004786",
        "tgn:7029392"
    ],
    "tgn:id":7023928,
    "tgn:name":"Saint Georges",
    "tgn:placetype":[
        "aat:300387064",
        "aat:300387092"
    ]
},
  "bbox": [],
  "geometry": {"coordinates":[-62.2,16.7],"type":"Point"}
}
=======
{"geometry":{"type":"Point","coordinates":[-62.200000,16.700000]},"type":"Feature","properties":{"hierarchy":["tgn:7023928","tgn:1000001","tgn:7004786","tgn:7029392"],"placetype":["aat:300387064","aat:300387092"],"id":7023928,"name:xx":"Saint Georges"}}
>>>>>>> 03f74aca74312dbeaf24d7e61306dd6a786dc3d0
