{
  "id": 2580279,
  "type": "Feature",
  "properties": {
    "tgn:hierarchy":[
        "tgn:2580279",
        "tgn:1000001",
        "tgn:7012149",
        "tgn:7007253",
        "tgn:7029392"
    ],
    "tgn:id":2580279,
    "tgn:name":"Pierson Creek",
    "tgn:placetype":[
        "aat:300008706"
    ]
},
  "bbox": [],
  "geometry": {"coordinates":[-95.7667,42.65],"type":"Point"}
}