{
  "id": 1075080,
  "type": "Feature",
  "properties": {
    "tgn:hierarchy":[
        "tgn:1075080",
        "tgn:1000004",
        "tgn:7000198",
        "tgn:1001882",
        "tgn:7029392"
    ],
    "tgn:id":1075080,
    "tgn:name:en":"Dandeli",
    "tgn:placetype":[
        "aat:300008347"
    ]
},
  "bbox": [],
  "geometry": {"coordinates":[74.616667,15.266667],"type":"Point"}
}