{
  "id": 7572197,
  "type": "Feature",
  "properties": {
    "tgn:hierarchy":[
        "tgn:7572197",
        "tgn:1000004",
        "tgn:1001869",
        "tgn:7000198",
        "tgn:7029392"
    ],
    "tgn:id":7572197,
    "tgn:name:en":"Jh\u0101nkhar",
    "tgn:placetype":[
        "aat:300008347"
    ]
},
  "bbox": [],
  "geometry": {"coordinates":[69.766667,22.366667],"type":"Point"}
}