{
  "id": 2296940,
  "type": "Feature",
  "properties": {
    "tgn:hierarchy":[
        "tgn:2296940",
        "tgn:1000001",
        "tgn:7012149",
        "tgn:7007709",
        "tgn:7029392"
    ],
    "tgn:id":2296940,
    "tgn:name":"Dry Creek",
    "tgn:placetype":[
        "aat:300008706"
    ]
},
  "bbox": [],
  "geometry": {"coordinates":[-80.0167,35.1333],"type":"Point"}
}