{
  "id": 1105204,
  "type": "Feature",
  "properties": {
    "tgn:hierarchy":[
        "tgn:1105204",
        "tgn:1000004",
        "tgn:7001319",
        "tgn:1000111",
        "tgn:7029392"
    ],
    "tgn:id":1105204,
    "tgn:name":"Keyangkeershan",
    "tgn:placetype":[
        "aat:300008795"
    ]
},
  "bbox": [],
  "geometry": {"coordinates":[87.2167,31.3333],"type":"Point"}
}