{
  "id": 7010314,
  "type": "Feature",
  "properties": {
    "tgn:hierarchy":[
        "tgn:7010314",
        "tgn:1000004",
        "tgn:6003149",
        "tgn:7002435",
        "tgn:7029392"
    ],
    "tgn:id":7010314,
    "tgn:name":"Ust' Vym'",
    "tgn:placetype":[
        "aat:300008347"
    ]
},
  "bbox": [],
  "geometry": {"coordinates":[50.4167,62.25],"type":"Point"}
}