{
  "id": 2053065,
  "type": "Feature",
  "properties": {
    "tgn:hierarchy":[
        "tgn:2053065",
        "tgn:1000001",
        "tgn:7012149",
        "tgn:2000990",
        "tgn:7007520",
        "tgn:7029392"
    ],
    "tgn:id":2053065,
    "tgn:name":"Posen",
    "tgn:placetype":[
        "aat:300008347"
    ]
},
  "bbox": [],
  "geometry": {"coordinates":[-83.6833,45.25],"type":"Point"}
}