{
  "id": 7087097,
  "type": "Feature",
  "properties": {
    "tgn:hierarchy":[
        "tgn:7087097",
        "tgn:1000003",
        "tgn:7003684",
        "tgn:7000084",
        "tgn:7029392"
    ],
    "tgn:id":7087097,
    "tgn:name":"Wehrden",
    "tgn:placetype":[
        "aat:300008347"
    ]
},
  "bbox": [],
  "geometry": {"coordinates":[6.833333,49.25],"type":"Point"}
}