<<<<<<< HEAD
{
  "id": 7368728,
  "type": "Feature",
  "properties": {
    "tgn:hierarchy":[
        "tgn:7368728",
        "tgn:7005586",
        "tgn:1000001",
        "tgn:7005560",
        "tgn:7029392"
    ],
    "tgn:id":7368728,
    "tgn:name":"Higuerillas",
    "tgn:placetype":[
        "aat:300008699"
    ]
},
  "bbox": [],
  "geometry": {"coordinates":[-104.8,19.566667],"type":"Point"}
}
=======
{"geometry":{"type":"Point","coordinates":[-104.800000,19.566667]},"type":"Feature","properties":{"hierarchy":["tgn:7368728","tgn:7005586","tgn:1000001","tgn:7005560","tgn:7029392"],"placetype":["aat:300008699"],"id":7368728,"name:xx":"Higuerillas"}}
>>>>>>> 03f74aca74312dbeaf24d7e61306dd6a786dc3d0
