{
  "id": 2507061,
  "type": "Feature",
  "properties": {
    "tgn:hierarchy":[
        "tgn:2507061",
        "tgn:1000001",
        "tgn:7012149",
        "tgn:1002899",
        "tgn:7007920",
        "tgn:7029392"
    ],
    "tgn:id":2507061,
    "tgn:name":"Metam, Lake",
    "tgn:placetype":[
        "aat:300008680"
    ]
},
  "bbox": [],
  "geometry": {"coordinates":[-121.3833,48.1333],"type":"Point"}
}