{
  "id": 1125149,
  "type": "Feature",
  "properties": {
    "tgn:hierarchy":[
        "tgn:1125149",
        "tgn:1000003",
        "tgn:7003687",
        "tgn:7000084",
        "tgn:7029392"
    ],
    "tgn:id":1125149,
    "tgn:name":"Jeetze",
    "tgn:placetype":[
        "aat:300008707",
        "aat:300008699"
    ]
},
  "bbox": [],
  "geometry": {"coordinates":[11.066667,53.15],"type":"Point"}
}