{
  "id": 2651282,
  "type": "Feature",
  "properties": {
    "tgn:hierarchy":[
        "tgn:2651282",
        "tgn:1000001",
        "tgn:7006451",
        "tgn:2000092",
        "tgn:7012149",
        "tgn:7029392"
    ],
    "tgn:id":2651282,
    "tgn:name":"Section Hill",
    "tgn:placetype":[
        "aat:300008798"
    ]
},
  "bbox": [],
  "geometry": {"coordinates":[-111.9667,35.3667],"type":"Point"}
}