{
  "id": 2565346,
  "type": "Feature",
  "properties": {
    "tgn:hierarchy":[
        "tgn:2565346",
        "tgn:1000001",
        "tgn:7012149",
        "tgn:7007255",
        "tgn:7029392"
    ],
    "tgn:id":2565346,
    "tgn:name":"Paint Lick Creek",
    "tgn:placetype":[
        "aat:300008706"
    ]
},
  "bbox": [],
  "geometry": {"coordinates":[-84.35,37.55],"type":"Point"}
}