{
  "id": 2710252,
  "type": "Feature",
  "properties": {
    "tgn:hierarchy":[
        "tgn:2710252",
        "tgn:1000001",
        "tgn:7012149",
        "tgn:2001487",
        "tgn:7007709",
        "tgn:7029392"
    ],
    "tgn:id":2710252,
    "tgn:name":"Talleywood",
    "tgn:placetype":[
        "aat:300008347"
    ]
},
  "bbox": [],
  "geometry": {"coordinates":[-78.9167,35.05],"type":"Point"}
}