<<<<<<< HEAD
{
  "id": 7246244,
  "type": "Feature",
  "properties": {
    "tgn:hierarchy":[
        "tgn:7246244",
        "tgn:7003461",
        "tgn:1000003",
        "tgn:1000063",
        "tgn:7018236",
        "tgn:7029392"
    ],
    "tgn:id":7246244,
    "tgn:name":"Borloberg",
    "tgn:placetype":[
        "aat:300008347"
    ]
},
  "bbox": [],
  "geometry": {"coordinates":[5.15928,50.731334],"type":"Point"}
}
=======
{"geometry":{"type":"Point","coordinates":[5.159280,50.731334]},"type":"Feature","properties":{"hierarchy":["tgn:7246244","tgn:7003461","tgn:1000003","tgn:1000063","tgn:7018236","tgn:7029392"],"placetype":["aat:300008347"],"id":7246244,"name:xx":"Borloberg"}}
>>>>>>> 03f74aca74312dbeaf24d7e61306dd6a786dc3d0
