{
  "id": 2324051,
  "type": "Feature",
  "properties": {
    "tgn:hierarchy":[
        "tgn:2324051",
        "tgn:1000001",
        "tgn:7012149",
        "tgn:2001555",
        "tgn:7007709",
        "tgn:7029392"
    ],
    "tgn:id":2324051,
    "tgn:name":"Fax Brown Lake",
    "tgn:placetype":[
        "aat:300006191"
    ]
},
  "bbox": [],
  "geometry": {"coordinates":[-80.7333,36.1833],"type":"Point"}
}