{
  "id": 2653065,
  "type": "Feature",
  "properties": {
    "tgn:hierarchy":[
        "tgn:2653065",
        "tgn:1000001",
        "tgn:2000299",
        "tgn:7012149",
        "tgn:7007248",
        "tgn:7029392"
    ],
    "tgn:id":2653065,
    "tgn:name":"Seven Islands",
    "tgn:placetype":[
        "aat:300386851",
        "aat:300386853"
    ]
},
  "bbox": [],
  "geometry": {"coordinates":[-84.6833,34.15],"type":"Point"}
}