{
  "id": 7443266,
  "type": "Feature",
  "properties": {
    "tgn:hierarchy":[
        "tgn:7443266",
        "tgn:7002444",
        "tgn:1000003",
        "tgn:7009907",
        "tgn:7008591",
        "tgn:7029392"
    ],
    "tgn:id":7443266,
    "tgn:name:en":"Teistie Taing",
    "tgn:placetype":[
        "aat:300386846"
    ]
},
  "bbox": [],
  "geometry": {"coordinates":[-2.866667,59.35],"type":"Point"}
}