{
  "id": 2631826,
  "type": "Feature",
  "properties": {
    "tgn:hierarchy":[
        "tgn:2631826",
        "tgn:1000001",
        "tgn:7012149",
        "tgn:2001309",
        "tgn:7007524",
        "tgn:7029392"
    ],
    "tgn:id":2631826,
    "tgn:name":"Roundup Coulee",
    "tgn:placetype":[
        "aat:300008761"
    ]
},
  "bbox": [],
  "geometry": {"coordinates":[-112.2333,47.6667],"type":"Point"}
}