{
  "id": 2582469,
  "type": "Feature",
  "properties": {
    "tgn:hierarchy":[
        "tgn:2582469",
        "tgn:1000001",
        "tgn:7012149",
        "tgn:7007157",
        "tgn:1002894",
        "tgn:7029392"
    ],
    "tgn:id":2582469,
    "tgn:name":"Pine Grove Creek",
    "tgn:placetype":[
        "aat:300008706"
    ]
},
  "bbox": [],
  "geometry": {"coordinates":[-120.8833,39.7167],"type":"Point"}
}