{
  "id": 7392614,
  "type": "Feature",
  "properties": {
    "tgn:hierarchy":[
        "tgn:7392614",
        "tgn:1000001",
        "tgn:7005595",
        "tgn:7005560",
        "tgn:7029392"
    ],
    "tgn:id":7392614,
    "tgn:name":"Sacramento",
    "tgn:placetype":[
        "aat:300008347"
    ]
},
  "bbox": [],
  "geometry": {"coordinates":[-107.721389,24.876111],"type":"Point"}
}