{
  "id": 2028070,
  "type": "Feature",
  "properties": {
    "tgn:hierarchy":[
        "tgn:2028070",
        "tgn:1000001",
        "tgn:7012149",
        "tgn:1003024",
        "tgn:7007251",
        "tgn:7029392"
    ],
    "tgn:id":2028070,
    "tgn:name":"Godley",
    "tgn:placetype":[
        "aat:300008347"
    ]
},
  "bbox": [],
  "geometry": {"coordinates":[-88.2333,41.2333],"type":"Point"}
}