{
  "id": 2130689,
  "type": "Feature",
  "properties": {
    "tgn:hierarchy":[
        "tgn:2130689",
        "tgn:1000001",
        "tgn:2001472",
        "tgn:7012149",
        "tgn:7007709",
        "tgn:7029392"
    ],
    "tgn:id":2130689,
    "tgn:name":"Alligator Swamp",
    "tgn:placetype":[
        "aat:300008699"
    ]
},
  "bbox": [],
  "geometry": {"coordinates":[-78.4667,34.0667],"type":"Point"}
}