{
  "id": 2723765,
  "type": "Feature",
  "properties": {
    "tgn:hierarchy":[
        "tgn:2723765",
        "tgn:2000090",
        "tgn:1000001",
        "tgn:7006451",
        "tgn:7012149",
        "tgn:7029392"
    ],
    "tgn:id":2723765,
    "tgn:name":"Toh Del Toshi Spring",
    "tgn:placetype":[
        "aat:300008697"
    ]
},
  "bbox": [],
  "geometry": {"coordinates":[-109.8667,35.85],"type":"Point"}
}