{
  "id": 1019521,
  "type": "Feature",
  "properties": {
    "tgn:hierarchy":[
        "tgn:1019521",
        "tgn:7006477",
        "tgn:1001203",
        "tgn:1000002",
        "tgn:7029392"
    ],
    "tgn:id":1019521,
    "tgn:name":"Gobernador Costa",
    "tgn:placetype":[
        "aat:300008347"
    ]
},
  "bbox": [],
  "geometry": {"coordinates":[-70.5833,-44.0667],"type":"Point"}
}