<<<<<<< HEAD
{
  "id": 2407020,
  "type": "Feature",
  "properties": {
    "tgn:hierarchy":[
        "tgn:2407020",
        "tgn:1000001",
        "tgn:7012149",
        "tgn:7007157",
        "tgn:1002566",
        "tgn:7029392"
    ],
    "tgn:id":2407020,
    "tgn:name":"Hunter Point",
    "tgn:placetype":[
        "aat:300008798"
    ]
},
  "bbox": [],
  "geometry": {"coordinates":[-122.95,39.2],"type":"Point"}
}
=======
{"geometry":{"type":"Point","coordinates":[-122.950000,39.200000]},"type":"Feature","properties":{"hierarchy":["tgn:2407020","tgn:1000001","tgn:7012149","tgn:7007157","tgn:1002566","tgn:7029392"],"placetype":["aat:300008798"],"id":2407020,"name:xx":"Hunter Point"}}
>>>>>>> 03f74aca74312dbeaf24d7e61306dd6a786dc3d0
