{
  "id": 7277491,
  "type": "Feature",
  "properties": {
    "tgn:hierarchy":[
        "tgn:7277491",
        "tgn:1001623",
        "tgn:1000049",
        "tgn:1000002",
        "tgn:7029392"
    ],
    "tgn:id":7277491,
    "tgn:name":"Laguna Las Cruces",
    "tgn:placetype":[
        "aat:300008680"
    ]
},
  "bbox": [],
  "geometry": {"coordinates":[-72.944722,-43.983056],"type":"Point"}
}