{
  "id": 2399163,
  "type": "Feature",
  "properties": {
    "tgn:hierarchy":[
        "tgn:2399163",
        "tgn:1000001",
        "tgn:7012149",
        "tgn:7007517",
        "tgn:7029392"
    ],
    "tgn:id":2399163,
    "tgn:name":"Hopping Brook",
    "tgn:placetype":[
        "aat:300008699"
    ]
},
  "bbox": [],
  "geometry": {"coordinates":[-71.4667,42.1833],"type":"Point"}
}