{
  "id": 2634735,
  "type": "Feature",
  "properties": {
    "tgn:hierarchy":[
        "tgn:2634735",
        "tgn:7002659",
        "tgn:1000001",
        "tgn:7012149",
        "tgn:2000050",
        "tgn:7029392"
    ],
    "tgn:id":2634735,
    "tgn:name":"Rutland Lake",
    "tgn:placetype":[
        "aat:300006191"
    ]
},
  "bbox": [],
  "geometry": {"coordinates":[-86.4667,32.3333],"type":"Point"}
}