{
  "id": 7118773,
  "type": "Feature",
  "properties": {
    "tgn:hierarchy":[
        "tgn:7118773",
        "tgn:7003669",
        "tgn:1000003",
        "tgn:7000084",
        "tgn:7029392"
    ],
    "tgn:id":7118773,
    "tgn:name":"Probst Berg",
    "tgn:placetype":[
        "aat:300008777"
    ]
},
  "bbox": [],
  "geometry": {"coordinates":[13.216667,48.95],"type":"Point"}
}