{
  "id": 7476824,
  "type": "Feature",
  "properties": {
    "tgn:hierarchy":[
        "tgn:7476824",
        "tgn:1000004",
        "tgn:7004300",
        "tgn:1000141",
        "tgn:7029392"
    ],
    "tgn:id":7476824,
    "tgn:name":"Waidongmen",
    "tgn:placetype":[
        "aat:300008347"
    ]
},
  "bbox": [],
  "geometry": {"coordinates":[119.575417,23.552844],"type":"Point"}
}