{
  "id": 7277054,
  "type": "Feature",
  "properties": {
    "tgn:hierarchy":[
        "tgn:7277054",
        "tgn:7002464",
        "tgn:1000049",
        "tgn:1000002",
        "tgn:7029392"
    ],
    "tgn:id":7277054,
    "tgn:name":"Huaylillas, Sierra de",
    "tgn:placetype":[
        "aat:300008795"
    ]
},
  "bbox": [],
  "geometry": {"coordinates":[-69.787222,-17.962778],"type":"Point"}
}