{
  "id": 7427500,
  "type": "Feature",
  "properties": {
    "tgn:hierarchy":[
        "tgn:7427500",
        "tgn:7005581",
        "tgn:1000001",
        "tgn:7005560",
        "tgn:7029392"
    ],
    "tgn:id":7427500,
    "tgn:name":"La Ternera",
    "tgn:placetype":[
        "aat:300008347"
    ]
},
  "bbox": [],
  "geometry": {"coordinates":[-104.15,27.733333],"type":"Point"}
}