{
  "id": 7016024,
  "type": "Feature",
  "properties": {
    "tgn:hierarchy":[
        "tgn:7016024",
        "tgn:7019599",
        "tgn:7019604",
        "tgn:7030516",
        "tgn:7019773",
        "tgn:7006450",
        "tgn:1000001",
        "tgn:7012149",
        "tgn:7029392"
    ],
    "tgn:id":7016024,
    "tgn:name":"Unalaska",
    "tgn:placetype":[
        "aat:300008347",
        "aat:300008375"
    ]
},
  "bbox": [],
  "geometry": {"coordinates":[-166.5333,53.8667],"type":"Point"}
}