<<<<<<< HEAD
{
  "id": 2159138,
  "type": "Feature",
  "properties": {
    "tgn:hierarchy":[
        "tgn:2159138",
        "tgn:1000001",
        "tgn:7012149",
        "tgn:2001122",
        "tgn:7007522",
        "tgn:7029392"
    ],
    "tgn:id":2159138,
    "tgn:name":"Bedford Woods West",
    "tgn:placetype":[
        "aat:300008347"
    ]
},
  "bbox": [],
  "geometry": {"coordinates":[-89.35,31.3],"type":"Point"}
}
=======
{"geometry":{"type":"Point","coordinates":[-89.350000,31.300000]},"type":"Feature","properties":{"hierarchy":["tgn:2159138","tgn:1000001","tgn:7012149","tgn:2001122","tgn:7007522","tgn:7029392"],"placetype":["aat:300008347"],"id":2159138,"name:xx":"Bedford Woods West"}}
>>>>>>> 03f74aca74312dbeaf24d7e61306dd6a786dc3d0
