<<<<<<< HEAD
{
  "id": 2256954,
  "type": "Feature",
  "properties": {
    "tgn:hierarchy":[
        "tgn:2256954",
        "tgn:1000001",
        "tgn:7012149",
        "tgn:7019676",
        "tgn:7007566",
        "tgn:7029392"
    ],
    "tgn:id":2256954,
    "tgn:name":"Corn Burned Hill",
    "tgn:placetype":[
        "aat:300008798"
    ]
},
  "bbox": [],
  "geometry": {"coordinates":[-108.7667,35.65],"type":"Point"}
}
=======
{"geometry":{"type":"Point","coordinates":[-108.766700,35.650000]},"type":"Feature","properties":{"hierarchy":["tgn:2256954","tgn:1000001","tgn:7012149","tgn:7019676","tgn:7007566","tgn:7029392"],"placetype":["aat:300008798"],"id":2256954,"name:xx":"Corn Burned Hill"}}
>>>>>>> 03f74aca74312dbeaf24d7e61306dd6a786dc3d0
