{
  "id": 2256954,
  "type": "Feature",
  "properties": {
    "tgn:hierarchy":[
        "tgn:2256954",
        "tgn:1000001",
        "tgn:7012149",
        "tgn:7019676",
        "tgn:7007566",
        "tgn:7029392"
    ],
    "tgn:id":2256954,
    "tgn:name":"Corn Burned Hill",
    "tgn:placetype":[
        "aat:300008798"
    ]
},
  "bbox": [],
  "geometry": {"coordinates":[-108.7667,35.65],"type":"Point"}
}