{
  "id": 2245573,
  "type": "Feature",
  "properties": {
    "tgn:hierarchy":[
        "tgn:2245573",
        "tgn:1000001",
        "tgn:2001268",
        "tgn:7012149",
        "tgn:7007524",
        "tgn:7029392"
    ],
    "tgn:id":2245573,
    "tgn:name":"Coal Bank Spring",
    "tgn:placetype":[
        "aat:300008697"
    ]
},
  "bbox": [],
  "geometry": {"coordinates":[-105.75,46.6167],"type":"Point"}
}