{
  "id": 2283031,
  "type": "Feature",
  "properties": {
    "tgn:hierarchy":[
        "tgn:2283031",
        "tgn:1000001",
        "tgn:7012149",
        "tgn:7007157",
        "tgn:1002608",
        "tgn:7029392"
    ],
    "tgn:id":2283031,
    "tgn:name":"Del Rey Lagoon",
    "tgn:placetype":[
        "aat:300008680"
    ]
},
  "bbox": [],
  "geometry": {"coordinates":[-118.45,33.95],"type":"Point"}
}