{
  "id": 2137538,
  "type": "Feature",
  "properties": {
    "tgn:hierarchy":[
        "tgn:2137538",
        "tgn:2002130",
        "tgn:1000001",
        "tgn:7012149",
        "tgn:7007828",
        "tgn:7029392"
    ],
    "tgn:id":2137538,
    "tgn:name":"Arnold Bay",
    "tgn:placetype":[
        "aat:300132316"
    ]
},
  "bbox": [],
  "geometry": {"coordinates":[-73.3667,44.1333],"type":"Point"}
}