{
  "id": 2703340,
  "type": "Feature",
  "properties": {
    "tgn:hierarchy":[
        "tgn:2703340",
        "tgn:1000001",
        "tgn:7012149",
        "tgn:1002640",
        "tgn:7007252",
        "tgn:7029392"
    ],
    "tgn:id":2703340,
    "tgn:name":"Summit Chapel",
    "tgn:placetype":[
        "aat:300008347"
    ]
},
  "bbox": [],
  "geometry": {"coordinates":[-86.0833,41.2333],"type":"Point"}
}