{
  "id": 7586125,
  "type": "Feature",
  "properties": {
    "tgn:hierarchy":[
        "tgn:7586125",
        "tgn:1000004",
        "tgn:7000198",
        "tgn:1001977",
        "tgn:7029392"
    ],
    "tgn:id":7586125,
    "tgn:name:en":"Chhon\u0101pur",
    "tgn:placetype":[
        "aat:300008347"
    ]
},
  "bbox": [],
  "geometry": {"coordinates":[88.015278,22.823333],"type":"Point"}
}