{
  "id": 1101703,
  "type": "Feature",
  "properties": {
    "tgn:hierarchy":[
        "tgn:1101703",
        "tgn:1000003",
        "tgn:1003410",
        "tgn:7006660",
        "tgn:7029392"
    ],
    "tgn:id":1101703,
    "tgn:name":"Michajlovskaja Celina, zapovednik",
    "tgn:placetype":[
        "aat:300008189"
    ]
},
  "bbox": [],
  "geometry": {"coordinates":[34.1667,50.75],"type":"Point"}
}