{
  "id": 7028436,
  "type": "Feature",
  "properties": {
    "tgn:hierarchy":[
        "tgn:7028436",
        "tgn:7002445",
        "tgn:1000003",
        "tgn:7008160",
        "tgn:7008591",
        "tgn:7029392"
    ],
    "tgn:id":7028436,
    "tgn:name":"Hellesdon",
    "tgn:placetype":[
        "aat:300008347"
    ]
},
  "bbox": [],
  "geometry": {"coordinates":[1.25,52.633333],"type":"Point"}
}