{
  "id": 7417841,
  "type": "Feature",
  "properties": {
    "tgn:hierarchy":[
        "tgn:7417841",
        "tgn:1000001",
        "tgn:7005591",
        "tgn:7005560",
        "tgn:7029392"
    ],
    "tgn:id":7417841,
    "tgn:name:es":"San Francisco",
    "tgn:placetype":[
        "aat:300008347"
    ]
},
  "bbox": [],
  "geometry": {"coordinates":[-95.625,16.099167],"type":"Point"}
}