{
  "id": 7035615,
  "type": "Feature",
  "properties": {
    "tgn:hierarchy":[
        "tgn:7035615",
        "tgn:7002991",
        "tgn:1000003",
        "tgn:7002997",
        "tgn:1000080",
        "tgn:7029392"
    ],
    "tgn:id":7035615,
    "tgn:name":"Tambruz",
    "tgn:placetype":[
        "aat:300008347"
    ]
},
  "bbox": [],
  "geometry": {"coordinates":[12.425556,46.131944],"type":"Point"}
}