{
  "id": 7186513,
  "type": "Feature",
  "properties": {
    "tgn:hierarchy":[
        "tgn:7186513",
        "tgn:1000003",
        "tgn:7003676",
        "tgn:7000084",
        "tgn:7029392"
    ],
    "tgn:id":7186513,
    "tgn:name":"Goldenkerklippe",
    "tgn:placetype":[
        "aat:300008749"
    ]
},
  "bbox": [],
  "geometry": {"coordinates":[10.416667,51.733333],"type":"Point"}
}