{
  "id": 7531982,
  "type": "Feature",
  "properties": {
    "tgn:hierarchy":[
        "tgn:7531982",
        "tgn:7001242",
        "tgn:7016833",
        "tgn:1001091",
        "tgn:7029392"
    ],
    "tgn:id":7531982,
    "tgn:name":"Al Hay'ah al '\u0100mmah lil Istithm\u0101r wa al Man\u0101\u0163iq al \u1e28urrah",
    "tgn:placetype":[
        "aat:300000853"
    ]
},
  "bbox": [],
  "geometry": {"coordinates":[31.346224,30.030609],"type":"Point"}
}