{
  "id": 1037409,
  "type": "Feature",
  "properties": {
    "tgn:hierarchy":[
        "tgn:1037409",
        "tgn:1000003",
        "tgn:7003685",
        "tgn:7000084",
        "tgn:7029392"
    ],
    "tgn:id":1037409,
    "tgn:name":"Oberlungwitz",
    "tgn:placetype":[
        "aat:300008347"
    ]
},
  "bbox": [],
  "geometry": {"coordinates":[12.716667,50.783333],"type":"Point"}
}