{
  "id": 2681078,
  "type": "Feature",
  "properties": {
    "tgn:hierarchy":[
        "tgn:2681078",
        "tgn:1000001",
        "tgn:7012149",
        "tgn:2001996",
        "tgn:7007826",
        "tgn:7029392"
    ],
    "tgn:id":2681078,
    "tgn:name":"South Mesquite Creek",
    "tgn:placetype":[
        "aat:300008706"
    ]
},
  "bbox": [],
  "geometry": {"coordinates":[-98.2167,31.6833],"type":"Point"}
}