{
  "id": 2305352,
  "type": "Feature",
  "properties": {
    "tgn:hierarchy":[
        "tgn:2305352",
        "tgn:1000001",
        "tgn:1002480",
        "tgn:7012149",
        "tgn:7007564",
        "tgn:7029392"
    ],
    "tgn:id":2305352,
    "tgn:name":"East Branch Village Brook",
    "tgn:placetype":[
        "aat:300008699"
    ]
},
  "bbox": [],
  "geometry": {"coordinates":[-71.6333,42.7333],"type":"Point"}
}