{
  "id": 1021280,
  "type": "Feature",
  "properties": {
    "tgn:hierarchy":[
        "tgn:1021280",
        "tgn:1001925",
        "tgn:1000047",
        "tgn:7002458",
        "tgn:1000002",
        "tgn:7029392"
    ],
    "tgn:id":1021280,
    "tgn:name":"Cruz Machado",
    "tgn:placetype":[
        "aat:300008347"
    ]
},
  "bbox": [],
  "geometry": {"coordinates":[-51.35,-26.0167],"type":"Point"}
}