{
  "id": 7357581,
  "type": "Feature",
  "properties": {
    "tgn:hierarchy":[
        "tgn:7357581",
        "tgn:7005586",
        "tgn:1000001",
        "tgn:7005560",
        "tgn:7029392"
    ],
    "tgn:id":7357581,
    "tgn:name":"Corrales, Ensenada",
    "tgn:placetype":[
        "aat:300132317"
    ]
},
  "bbox": [],
  "geometry": {"coordinates":[-105.677778,20.414722],"type":"Point"}
}