<<<<<<< HEAD
{
  "id": 7357581,
  "type": "Feature",
  "properties": {
    "tgn:hierarchy":[
        "tgn:7357581",
        "tgn:7005586",
        "tgn:1000001",
        "tgn:7005560",
        "tgn:7029392"
    ],
    "tgn:id":7357581,
    "tgn:name":"Corrales, Ensenada",
    "tgn:placetype":[
        "aat:300132317"
    ]
},
  "bbox": [],
  "geometry": {"coordinates":[-105.677778,20.414722],"type":"Point"}
}
=======
{"geometry":{"type":"Point","coordinates":[-105.677778,20.414722]},"type":"Feature","properties":{"hierarchy":["tgn:7357581","tgn:7005586","tgn:1000001","tgn:7005560","tgn:7029392"],"placetype":["aat:300132317"],"id":7357581,"name:xx":"Corrales, Ensenada"}}
>>>>>>> 03f74aca74312dbeaf24d7e61306dd6a786dc3d0
