{
  "id": 2643262,
  "type": "Feature",
  "properties": {
    "tgn:hierarchy":[
        "tgn:2643262",
        "tgn:1000001",
        "tgn:2001179",
        "tgn:7012149",
        "tgn:7007523",
        "tgn:7029392"
    ],
    "tgn:id":2643262,
    "tgn:name":"Sandy Creek",
    "tgn:placetype":[
        "aat:300008706"
    ]
},
  "bbox": [],
  "geometry": {"coordinates":[-89.8167,37.5667],"type":"Point"}
}