<<<<<<< HEAD
{
  "id": 2251215,
  "type": "Feature",
  "properties": {
    "tgn:hierarchy":[
        "tgn:2251215",
        "tgn:1000001",
        "tgn:7006451",
        "tgn:2000092",
        "tgn:7012149",
        "tgn:7029392"
    ],
    "tgn:id":2251215,
    "tgn:name":"Comanche Point",
    "tgn:placetype":[
        "aat:300008798"
    ]
},
  "bbox": [],
  "geometry": {"coordinates":[-111.8,36.0833],"type":"Point"}
}
=======
{"geometry":{"type":"Point","coordinates":[-111.800000,36.083300]},"type":"Feature","properties":{"hierarchy":["tgn:2251215","tgn:1000001","tgn:7006451","tgn:2000092","tgn:7012149","tgn:7029392"],"placetype":["aat:300008798"],"id":2251215,"name:xx":"Comanche Point"}}
>>>>>>> 03f74aca74312dbeaf24d7e61306dd6a786dc3d0
