{
  "id": 2036812,
  "type": "Feature",
  "properties": {
    "tgn:hierarchy":[
        "tgn:2036812",
        "tgn:1000001",
        "tgn:7012149",
        "tgn:2000739",
        "tgn:7007254",
        "tgn:7029392"
    ],
    "tgn:id":2036812,
    "tgn:name":"Mitchell",
    "tgn:placetype":[
        "aat:300008347",
        "aat:300387210"
    ]
},
  "bbox": [],
  "geometry": {"coordinates":[-98.0833,38.3833],"type":"Point"}
}