<<<<<<< HEAD
{
  "id": 2156316,
  "type": "Feature",
  "properties": {
    "tgn:hierarchy":[
        "tgn:2156316",
        "tgn:1000001",
        "tgn:7012149",
        "tgn:7007157",
        "tgn:7014516",
        "tgn:7029392"
    ],
    "tgn:id":2156316,
    "tgn:name":"Bearpen Creek",
    "tgn:placetype":[
        "aat:300008706"
    ]
},
  "bbox": [],
  "geometry": {"coordinates":[-123.1,38.65],"type":"Point"}
}
=======
{"geometry":{"type":"Point","coordinates":[-123.100000,38.650000]},"type":"Feature","properties":{"hierarchy":["tgn:2156316","tgn:1000001","tgn:7012149","tgn:7007157","tgn:7014516","tgn:7029392"],"placetype":["aat:300008706"],"id":2156316,"name:xx":"Bearpen Creek"}}
>>>>>>> 03f74aca74312dbeaf24d7e61306dd6a786dc3d0
