{
  "id": 2517860,
  "type": "Feature",
  "properties": {
    "tgn:hierarchy":[
        "tgn:2517860",
        "tgn:1000001",
        "tgn:7012149",
        "tgn:2001277",
        "tgn:7007524",
        "tgn:7029392"
    ],
    "tgn:id":2517860,
    "tgn:name":"Mirror Pond",
    "tgn:placetype":[
        "aat:300008680"
    ]
},
  "bbox": [],
  "geometry": {"coordinates":[-113.65,48.65],"type":"Point"}
}