{
  "id": 2035456,
  "type": "Feature",
  "properties": {
    "tgn:hierarchy":[
        "tgn:2035456",
        "tgn:1000001",
        "tgn:2000581",
        "tgn:7012149",
        "tgn:7007253",
        "tgn:7029392"
    ],
    "tgn:id":2035456,
    "tgn:name":"Peterson",
    "tgn:placetype":[
        "aat:300008347"
    ]
},
  "bbox": [],
  "geometry": {"coordinates":[-95.3333,42.9167],"type":"Point"}
}