{
  "id": 2045082,
  "type": "Feature",
  "properties": {
    "tgn:hierarchy":[
        "tgn:2045082",
        "tgn:2000918",
        "tgn:1000001",
        "tgn:7012149",
        "tgn:7007515",
        "tgn:7029392"
    ],
    "tgn:id":2045082,
    "tgn:name":"Lisbon Falls",
    "tgn:placetype":[
        "aat:300008347"
    ]
},
  "bbox": [],
  "geometry": {"coordinates":[-70.05,43.9833],"type":"Point"}
}