{
  "id": 7568886,
  "type": "Feature",
  "properties": {
    "tgn:hierarchy":[
        "tgn:7568886",
        "tgn:1000004",
        "tgn:7000198",
        "tgn:7016788",
        "tgn:7029392"
    ],
    "tgn:id":7568886,
    "tgn:name:en":"Baijupurohit ki Dh\u0101ni",
    "tgn:placetype":[
        "aat:300008347"
    ]
},
  "bbox": [],
  "geometry": {"coordinates":[74.83357,28.059442],"type":"Point"}
}