{
  "id": 2682584,
  "type": "Feature",
  "properties": {
    "tgn:hierarchy":[
        "tgn:2682584",
        "tgn:1000001",
        "tgn:7016172",
        "tgn:7012149",
        "tgn:2000136",
        "tgn:7029392"
    ],
    "tgn:id":2682584,
    "tgn:name":"Southern Hill",
    "tgn:placetype":[
        "aat:300008798"
    ]
},
  "bbox": [],
  "geometry": {"coordinates":[-91.7333,35.8833],"type":"Point"}
}