{
  "id": 1069452,
  "type": "Feature",
  "properties": {
    "tgn:hierarchy":[
        "tgn:1069452",
        "tgn:1000004",
        "tgn:7002076",
        "tgn:1000111",
        "tgn:7029392"
    ],
    "tgn:id":1069452,
    "tgn:name":"Jixiashi",
    "tgn:placetype":[
        "aat:300008347"
    ]
},
  "bbox": [],
  "geometry": {"coordinates":[118.7333,28.3667],"type":"Point"}
}