{
  "id": 1009044,
  "type": "Feature",
  "properties": {
    "tgn:hierarchy":[
        "tgn:1009044",
        "tgn:7005151",
        "tgn:7005152",
        "tgn:1000002",
        "tgn:7029392"
    ],
    "tgn:id":1009044,
    "tgn:name":"Saunders Island",
    "tgn:placetype":[
        "aat:300008791"
    ]
},
  "bbox": [],
  "geometry": {"coordinates":[-60.1667,-51.3333],"type":"Point"}
}