<<<<<<< HEAD
{
  "id": 2400813,
  "type": "Feature",
  "properties": {
    "tgn:hierarchy":[
        "tgn:2400813",
        "tgn:1000001",
        "tgn:2000273",
        "tgn:7012149",
        "tgn:7007240",
        "tgn:7029392"
    ],
    "tgn:id":2400813,
    "tgn:name":"Horse Ponds",
    "tgn:placetype":[
        "aat:300008680"
    ]
},
  "bbox": [],
  "geometry": {"coordinates":[-85.2167,30.8667],"type":"Point"}
}
=======
{"geometry":{"type":"Point","coordinates":[-85.216700,30.866700]},"type":"Feature","properties":{"hierarchy":["tgn:2400813","tgn:1000001","tgn:2000273","tgn:7012149","tgn:7007240","tgn:7029392"],"placetype":["aat:300008680"],"id":2400813,"name:xx":"Horse Ponds"}}
>>>>>>> 03f74aca74312dbeaf24d7e61306dd6a786dc3d0
