<<<<<<< HEAD
{
  "id": 7177972,
  "type": "Feature",
  "properties": {
    "tgn:hierarchy":[
        "tgn:7177972",
        "tgn:1000003",
        "tgn:7003676",
        "tgn:7000084",
        "tgn:7029392"
    ],
    "tgn:id":7177972,
    "tgn:name":"H\u00e4nigser Wiesen",
    "tgn:placetype":[
        "aat:300386990"
    ]
},
  "bbox": [],
  "geometry": {"coordinates":[10.116667,52.5],"type":"Point"}
}
=======
{"geometry":{"type":"Point","coordinates":[10.116667,52.500000]},"type":"Feature","properties":{"hierarchy":["tgn:7177972","tgn:1000003","tgn:7003676","tgn:7000084","tgn:7029392"],"placetype":["aat:300386990"],"id":7177972,"name:xx":"H\u00e4nigser Wiesen"}}
>>>>>>> 03f74aca74312dbeaf24d7e61306dd6a786dc3d0
