{
  "id": 2261521,
  "type": "Feature",
  "properties": {
    "tgn:hierarchy":[
        "tgn:2261521",
        "tgn:1000001",
        "tgn:7012149",
        "tgn:1002794",
        "tgn:7007708",
        "tgn:7029392"
    ],
    "tgn:id":2261521,
    "tgn:name":"Couter Reservoir",
    "tgn:placetype":[
        "aat:300006191"
    ]
},
  "bbox": [],
  "geometry": {"coordinates":[-123.3167,44.9667],"type":"Point"}
}