{
  "id": 2635191,
  "type": "Feature",
  "properties": {
    "tgn:hierarchy":[
        "tgn:2635191",
        "tgn:1000001",
        "tgn:7012149",
        "tgn:1002872",
        "tgn:7007568",
        "tgn:7029392"
    ],
    "tgn:id":2635191,
    "tgn:name":"Rynex Corners",
    "tgn:placetype":[
        "aat:300008347"
    ]
},
  "bbox": [],
  "geometry": {"coordinates":[-74.0667,42.8167],"type":"Point"}
}