{
  "id": 2576957,
  "type": "Feature",
  "properties": {
    "tgn:hierarchy":[
        "tgn:2576957",
        "tgn:1000001",
        "tgn:7006451",
        "tgn:2000092",
        "tgn:7012149",
        "tgn:7029392"
    ],
    "tgn:id":2576957,
    "tgn:name":"Pete Tank",
    "tgn:placetype":[
        "aat:300006191"
    ]
},
  "bbox": [],
  "geometry": {"coordinates":[-111.55,35.4333],"type":"Point"}
}