{
  "id": 2613313,
  "type": "Feature",
  "properties": {
    "tgn:hierarchy":[
        "tgn:2613313",
        "tgn:1000001",
        "tgn:7012149",
        "tgn:2001315",
        "tgn:7007524",
        "tgn:7029392"
    ],
    "tgn:id":2613313,
    "tgn:name":"Reed Creek",
    "tgn:placetype":[
        "aat:300008706"
    ]
},
  "bbox": [],
  "geometry": {"coordinates":[-107.7167,45.95],"type":"Point"}
}