<<<<<<< HEAD
{
  "id": 7117094,
  "type": "Feature",
  "properties": {
    "tgn:hierarchy":[
        "tgn:7117094",
        "tgn:1000003",
        "tgn:7003677",
        "tgn:7000084",
        "tgn:7029392"
    ],
    "tgn:id":7117094,
    "tgn:name":"Orsbach",
    "tgn:placetype":[
        "aat:300008347"
    ]
},
  "bbox": [],
  "geometry": {"coordinates":[6.15,50.683333],"type":"Point"}
}
=======
{"geometry":{"type":"Point","coordinates":[6.150000,50.683333]},"type":"Feature","properties":{"hierarchy":["tgn:7117094","tgn:1000003","tgn:7003677","tgn:7000084","tgn:7029392"],"placetype":["aat:300008347"],"id":7117094,"name:xx":"Orsbach"}}
>>>>>>> 03f74aca74312dbeaf24d7e61306dd6a786dc3d0
