{
  "id": 7538104,
  "type": "Feature",
  "properties": {
    "tgn:hierarchy":[
        "tgn:7538104",
        "tgn:7001242",
        "tgn:7016833",
        "tgn:1001418",
        "tgn:7029392"
    ],
    "tgn:id":7538104,
    "tgn:name:en":"Shifshifa, Qaret el",
    "tgn:placetype":[
        "aat:300008777"
    ]
},
  "bbox": [],
  "geometry": {"coordinates":[27.546496,30.425797],"type":"Point"}
}