{
  "id": 2713527,
  "type": "Feature",
  "properties": {
    "tgn:hierarchy":[
        "tgn:2713527",
        "tgn:1000001",
        "tgn:7012149",
        "tgn:2001195",
        "tgn:7007523",
        "tgn:7029392"
    ],
    "tgn:id":2713527,
    "tgn:name":"Teague Hollow",
    "tgn:placetype":[
        "aat:300008761"
    ]
},
  "bbox": [],
  "geometry": {"coordinates":[-91.3167,37.5667],"type":"Point"}
}