{
  "id": 2629316,
  "type": "Feature",
  "properties": {
    "tgn:hierarchy":[
        "tgn:2629316",
        "tgn:1000001",
        "tgn:2001590",
        "tgn:7012149",
        "tgn:7007705",
        "tgn:7029392"
    ],
    "tgn:id":2629316,
    "tgn:name":"Rosebud Coulee",
    "tgn:placetype":[
        "aat:300008761"
    ]
},
  "bbox": [],
  "geometry": {"coordinates":[-97.5333,48.9167],"type":"Point"}
}