{
  "id": 7343744,
  "type": "Feature",
  "properties": {
    "tgn:hierarchy":[
        "tgn:7343744",
        "tgn:7002825",
        "tgn:7016622",
        "tgn:1000003",
        "tgn:1000095",
        "tgn:7029392"
    ],
    "tgn:id":7343744,
    "tgn:name":"Iglesia de los Capuchinos",
    "tgn:placetype":[
        "aat:300007466"
    ]
},
  "bbox": [],
  "geometry": {"coordinates":[-15.433333,28.133333],"type":"Point"}
}