{
  "id": 7328357,
  "type": "Feature",
  "properties": {
    "tgn:hierarchy":[
        "tgn:7328357",
        "tgn:7002829",
        "tgn:1000003",
        "tgn:7002786",
        "tgn:1000095",
        "tgn:7029392"
    ],
    "tgn:id":7328357,
    "tgn:name":"Praducelo",
    "tgn:placetype":[
        "aat:300008347"
    ]
},
  "bbox": [],
  "geometry": {"coordinates":[-7.216667,42.683333],"type":"Point"}
}