{
  "id": 7535691,
  "type": "Feature",
  "properties": {
    "tgn:hierarchy":[
        "tgn:7535691",
        "tgn:7001242",
        "tgn:1001075",
        "tgn:7016833",
        "tgn:7029392"
    ],
    "tgn:id":7535691,
    "tgn:name:en":"Iby\u0101 al \u1e28amr\u0101'",
    "tgn:placetype":[
        "aat:300008347"
    ]
},
  "bbox": [],
  "geometry": {"coordinates":[30.545739,30.846655],"type":"Point"}
}