{
  "id": 2751467,
  "type": "Feature",
  "properties": {
    "tgn:hierarchy":[
        "tgn:2751467",
        "tgn:1000001",
        "tgn:7012149",
        "tgn:2002125",
        "tgn:7007827",
        "tgn:7029392"
    ],
    "tgn:id":2751467,
    "tgn:name":"Warm Springs Ditch",
    "tgn:placetype":[
        "aat:300006075"
    ]
},
  "bbox": [],
  "geometry": {"coordinates":[-111.8667,39.9333],"type":"Point"}
}