{
  "id": 7373179,
  "type": "Feature",
  "properties": {
    "tgn:hierarchy":[
        "tgn:7373179",
        "tgn:1000001",
        "tgn:7005589",
        "tgn:7005560",
        "tgn:7029392"
    ],
    "tgn:id":7373179,
    "tgn:name":"Rancho La Palma",
    "tgn:placetype":[
        "aat:300000241"
    ]
},
  "bbox": [],
  "geometry": {"coordinates":[-99.333333,26.133333],"type":"Point"}
}