{
  "id": 7254092,
  "type": "Feature",
  "properties": {
    "tgn:hierarchy":[
        "tgn:7254092",
        "tgn:7003461",
        "tgn:1000003",
        "tgn:1000063",
        "tgn:7018236",
        "tgn:7029392"
    ],
    "tgn:id":7254092,
    "tgn:name":"Vechmaal",
    "tgn:placetype":[
        "aat:300008347"
    ]
},
  "bbox": [],
  "geometry": {"coordinates":[5.377801,50.761833],"type":"Point"}
}