{
  "id": 7185135,
  "type": "Feature",
  "properties": {
    "tgn:hierarchy":[
        "tgn:7185135",
        "tgn:1000003",
        "tgn:7003684",
        "tgn:7000084",
        "tgn:7029392"
    ],
    "tgn:id":7185135,
    "tgn:name":"Gorren-Berg",
    "tgn:placetype":[
        "aat:300008777"
    ]
},
  "bbox": [],
  "geometry": {"coordinates":[7.233333,49.383333],"type":"Point"}
}