{
  "id": 2174122,
  "type": "Feature",
  "properties": {
    "tgn:hierarchy":[
        "tgn:2174122",
        "tgn:1000001",
        "tgn:7012149",
        "tgn:2000913",
        "tgn:7007256",
        "tgn:7029392"
    ],
    "tgn:id":2174122,
    "tgn:name":"Birds Island",
    "tgn:placetype":[
        "aat:300008791"
    ]
},
  "bbox": [],
  "geometry": {"coordinates":[-93.35,32.4167],"type":"Point"}
}