{
  "id": 1101529,
  "type": "Feature",
  "properties": {
    "tgn:hierarchy":[
        "tgn:1101529",
        "tgn:1000699",
        "tgn:1000002",
        "tgn:1000058",
        "tgn:7029392"
    ],
    "tgn:id":1101529,
    "tgn:name":"Franklin Delano Roosevelt, Parque Nacional",
    "tgn:placetype":[
        "aat:300008189"
    ]
},
  "bbox": [],
  "geometry": {"coordinates":[-56.05,-34.8667],"type":"Point"}
}