{
  "id": 7507556,
  "type": "Feature",
  "properties": {
    "tgn:hierarchy":[
        "tgn:7507556",
        "tgn:7016670",
        "tgn:1008380",
        "tgn:1000226",
        "tgn:1000006",
        "tgn:7029392"
    ],
    "tgn:id":7507556,
    "tgn:name:en":"Potua Stream",
    "tgn:placetype":[
        "aat:300008699"
    ]
},
  "bbox": [],
  "geometry": {"coordinates":[177.35,-39.083333],"type":"Point"}
}