{
  "id": 2175835,
  "type": "Feature",
  "properties": {
    "tgn:hierarchy":[
        "tgn:2175835",
        "tgn:7002659",
        "tgn:1000001",
        "tgn:7012149",
        "tgn:2000063",
        "tgn:7029392"
    ],
    "tgn:id":2175835,
    "tgn:name":"Black Creek Mine Number Two",
    "tgn:placetype":[
        "aat:300000390"
    ]
},
  "bbox": [],
  "geometry": {"coordinates":[-87.4667,33.9667],"type":"Point"}
}