{
  "id": 1110473,
  "type": "Feature",
  "properties": {
    "tgn:hierarchy":[
        "tgn:1110473",
        "tgn:1000001",
        "tgn:7012149",
        "tgn:7029392"
    ],
    "tgn:id":1110473,
    "tgn:name":"Gogebic Range",
    "tgn:placetype":[
        "aat:300008777"
    ]
},
  "bbox": [],
  "geometry": {"coordinates":[-90.7667,46.2833],"type":"Point"}
}