{
  "id": 2192972,
  "type": "Feature",
  "properties": {
    "tgn:hierarchy":[
        "tgn:2192972",
        "tgn:7002659",
        "tgn:1000001",
        "tgn:7012149",
        "tgn:2000021",
        "tgn:7029392"
    ],
    "tgn:id":2192972,
    "tgn:name":"Brazeal Branch",
    "tgn:placetype":[
        "aat:300008699"
    ]
},
  "bbox": [],
  "geometry": {"coordinates":[-87.0167,33.9667],"type":"Point"}
}