{
  "id": 2590091,
  "type": "Feature",
  "properties": {
    "tgn:hierarchy":[
        "tgn:2590091",
        "tgn:1000001",
        "tgn:7012149",
        "tgn:2000494",
        "tgn:7007250",
        "tgn:7029392"
    ],
    "tgn:id":2590091,
    "tgn:name":"Poison Lake",
    "tgn:placetype":[
        "aat:300008680"
    ]
},
  "bbox": [],
  "geometry": {"coordinates":[-116.1667,44.6333],"type":"Point"}
}