{
  "id": 2210147,
  "type": "Feature",
  "properties": {
    "tgn:hierarchy":[
        "tgn:2210147",
        "tgn:1000001",
        "tgn:7012149",
        "tgn:2002100",
        "tgn:7007826",
        "tgn:7029392"
    ],
    "tgn:id":2210147,
    "tgn:name":"Burtrand Creek",
    "tgn:placetype":[
        "aat:300008706"
    ]
},
  "bbox": [],
  "geometry": {"coordinates":[-99.55,28.7667],"type":"Point"}
}