{
  "id": 7415782,
  "type": "Feature",
  "properties": {
    "tgn:hierarchy":[
        "tgn:7415782",
        "tgn:1000001",
        "tgn:7005591",
        "tgn:7005560",
        "tgn:7029392"
    ],
    "tgn:id":7415782,
    "tgn:name:es":"Atoyaquillo, R\u00edo",
    "tgn:placetype":[
        "aat:300008699"
    ]
},
  "bbox": [],
  "geometry": {"coordinates":[-97.694444,16.6875],"type":"Point"}
}