{
  "id": 7049819,
  "type": "Feature",
  "properties": {
    "tgn:hierarchy":[
        "tgn:7049819",
        "tgn:7004597",
        "tgn:1000003",
        "tgn:7008516",
        "tgn:1000080",
        "tgn:7029392"
    ],
    "tgn:id":7049819,
    "tgn:name":"Cargedolo",
    "tgn:placetype":[
        "aat:300008347"
    ]
},
  "bbox": [],
  "geometry": {"coordinates":[10.566667,44.266667],"type":"Point"}
}