{
  "id": 2224755,
  "type": "Feature",
  "properties": {
    "tgn:hierarchy":[
        "tgn:2224755",
        "tgn:1000001",
        "tgn:7012149",
        "tgn:2001457",
        "tgn:7007566",
        "tgn:7029392"
    ],
    "tgn:id":2224755,
    "tgn:name":"Casias Canyon",
    "tgn:placetype":[
        "aat:300008761"
    ]
},
  "bbox": [],
  "geometry": {"coordinates":[-105.4667,36.3333],"type":"Point"}
}