{
  "id": 1017492,
  "type": "Feature",
  "properties": {
    "tgn:hierarchy":[
        "tgn:1017492",
        "tgn:1000001",
        "tgn:7005590",
        "tgn:7005560",
        "tgn:7029392"
    ],
    "tgn:id":1017492,
    "tgn:name":"G\u00e1mbara",
    "tgn:placetype":[
        "aat:300008347"
    ]
},
  "bbox": [],
  "geometry": {"coordinates":[-102.116667,18.933333],"type":"Point"}
}