{
  "id": 2634290,
  "type": "Feature",
  "properties": {
    "tgn:hierarchy":[
        "tgn:2634290",
        "tgn:1000001",
        "tgn:7012149",
        "tgn:2000927",
        "tgn:7007515",
        "tgn:7029392"
    ],
    "tgn:id":2634290,
    "tgn:name":"Russell Point",
    "tgn:placetype":[
        "aat:300008850"
    ]
},
  "bbox": [],
  "geometry": {"coordinates":[-68.8333,45.6167],"type":"Point"}
}