<<<<<<< HEAD
{
  "id": 2761336,
  "type": "Feature",
  "properties": {
    "tgn:hierarchy":[
        "tgn:2761336",
        "tgn:1000001",
        "tgn:7012149",
        "tgn:1002945",
        "tgn:7007710",
        "tgn:7029392"
    ],
    "tgn:id":2761336,
    "tgn:name":"West Mill Creek",
    "tgn:placetype":[
        "aat:300008706"
    ]
},
  "bbox": [],
  "geometry": {"coordinates":[-76.9667,41.6333],"type":"Point"}
}
=======
{"geometry":{"type":"Point","coordinates":[-76.966700,41.633300]},"type":"Feature","properties":{"hierarchy":["tgn:2761336","tgn:1000001","tgn:7012149","tgn:1002945","tgn:7007710","tgn:7029392"],"placetype":["aat:300008706"],"id":2761336,"name:xx":"West Mill Creek"}}
>>>>>>> 03f74aca74312dbeaf24d7e61306dd6a786dc3d0
