{
  "id": 2761336,
  "type": "Feature",
  "properties": {
    "tgn:hierarchy":[
        "tgn:2761336",
        "tgn:1000001",
        "tgn:7012149",
        "tgn:1002945",
        "tgn:7007710",
        "tgn:7029392"
    ],
    "tgn:id":2761336,
    "tgn:name":"West Mill Creek",
    "tgn:placetype":[
        "aat:300008706"
    ]
},
  "bbox": [],
  "geometry": {"coordinates":[-76.9667,41.6333],"type":"Point"}
}