{
  "id": 7439006,
  "type": "Feature",
  "properties": {
    "tgn:hierarchy":[
        "tgn:7439006",
        "tgn:1001836",
        "tgn:1000001",
        "tgn:7005560",
        "tgn:7029392"
    ],
    "tgn:id":7439006,
    "tgn:name":"San Zacar\u00edas",
    "tgn:placetype":[
        "aat:300008347"
    ]
},
  "bbox": [],
  "geometry": {"coordinates":[-112.906111,27.132778],"type":"Point"}
}