{
  "id": 2534247,
  "type": "Feature",
  "properties": {
    "tgn:hierarchy":[
        "tgn:2534247",
        "tgn:1000001",
        "tgn:7012149",
        "tgn:2000903",
        "tgn:7007256",
        "tgn:7029392"
    ],
    "tgn:id":2534247,
    "tgn:name":"Mystic Crew Bayou",
    "tgn:placetype":[
        "aat:300008699"
    ]
},
  "bbox": [],
  "geometry": {"coordinates":[-91.2833,29.8667],"type":"Point"}
}