{
  "id": 2451766,
  "type": "Feature",
  "properties": {
    "tgn:hierarchy":[
        "tgn:2451766",
        "tgn:1000001",
        "tgn:7012149",
        "tgn:1002789",
        "tgn:7007710",
        "tgn:7029392"
    ],
    "tgn:id":2451766,
    "tgn:name":"Little Bear Swamp",
    "tgn:placetype":[
        "aat:300008905"
    ]
},
  "bbox": [],
  "geometry": {"coordinates":[-74.9833,41.2333],"type":"Point"}
}