{
  "id": 2361594,
  "type": "Feature",
  "properties": {
    "tgn:hierarchy":[
        "tgn:2361594",
        "tgn:1000001",
        "tgn:7012149",
        "tgn:1002755",
        "tgn:7007523",
        "tgn:7029392"
    ],
    "tgn:id":2361594,
    "tgn:name":"Graveyard Branch",
    "tgn:placetype":[
        "aat:300008699"
    ]
},
  "bbox": [],
  "geometry": {"coordinates":[-91.8833,38.4333],"type":"Point"}
}