{
  "id": 2184355,
  "type": "Feature",
  "properties": {
    "tgn:hierarchy":[
        "tgn:2184355",
        "tgn:1000001",
        "tgn:7012149",
        "tgn:2000481",
        "tgn:7007250",
        "tgn:7029392"
    ],
    "tgn:id":2184355,
    "tgn:name":"Bobcat Gulch",
    "tgn:placetype":[
        "aat:300008761"
    ]
},
  "bbox": [],
  "geometry": {"coordinates":[-113.9833,45.3333],"type":"Point"}
}