{
  "id": 2180614,
  "type": "Feature",
  "properties": {
    "tgn:hierarchy":[
        "tgn:2180614",
        "tgn:1000001",
        "tgn:7006451",
        "tgn:2000092",
        "tgn:7012149",
        "tgn:7029392"
    ],
    "tgn:id":2180614,
    "tgn:name":"Bloody Tank",
    "tgn:placetype":[
        "aat:300006191"
    ]
},
  "bbox": [],
  "geometry": {"coordinates":[-111.8833,35.7833],"type":"Point"}
}