{
  "id": 2494907,
  "type": "Feature",
  "properties": {
    "tgn:hierarchy":[
        "tgn:2494907",
        "tgn:1000001",
        "tgn:7012149",
        "tgn:2001449",
        "tgn:7007566",
        "tgn:7029392"
    ],
    "tgn:id":2494907,
    "tgn:name":"Martinez Tanks",
    "tgn:placetype":[
        "aat:300006191"
    ]
},
  "bbox": [],
  "geometry": {"coordinates":[-106.6667,36.0667],"type":"Point"}
}