{
  "id": 7046668,
  "type": "Feature",
  "properties": {
    "tgn:hierarchy":[
        "tgn:7046668",
        "tgn:7005126",
        "tgn:1000003",
        "tgn:7003120",
        "tgn:1000080",
        "tgn:7029392"
    ],
    "tgn:id":7046668,
    "tgn:name":"Ferriere, Rio di",
    "tgn:placetype":[
        "aat:300008699"
    ]
},
  "bbox": [],
  "geometry": {"coordinates":[6.983333,44.366667],"type":"Point"}
}