{
  "id": 2313760,
  "type": "Feature",
  "properties": {
    "tgn:hierarchy":[
        "tgn:2313760",
        "tgn:2001318",
        "tgn:1000001",
        "tgn:7012149",
        "tgn:7007525",
        "tgn:7029392"
    ],
    "tgn:id":2313760,
    "tgn:name":"Eleven Valley",
    "tgn:placetype":[
        "aat:300386845"
    ]
},
  "bbox": [],
  "geometry": {"coordinates":[-101.4167,41.7167],"type":"Point"}
}