<<<<<<< HEAD
{
  "id": 2330452,
  "type": "Feature",
  "properties": {
    "tgn:hierarchy":[
        "tgn:2330452",
        "tgn:1000001",
        "tgn:7012149",
        "tgn:2001277",
        "tgn:7007524",
        "tgn:7029392"
    ],
    "tgn:id":2330452,
    "tgn:name":"Flat Coulee",
    "tgn:placetype":[
        "aat:300008761"
    ]
},
  "bbox": [],
  "geometry": {"coordinates":[-112.6833,48.5167],"type":"Point"}
}
=======
{"geometry":{"type":"Point","coordinates":[-112.683300,48.516700]},"type":"Feature","properties":{"hierarchy":["tgn:2330452","tgn:1000001","tgn:7012149","tgn:2001277","tgn:7007524","tgn:7029392"],"placetype":["aat:300008761"],"id":2330452,"name:xx":"Flat Coulee"}}
>>>>>>> 03f74aca74312dbeaf24d7e61306dd6a786dc3d0
