{
  "id": 1006305,
  "type": "Feature",
  "properties": {
    "tgn:hierarchy":[
        "tgn:1006305",
        "tgn:1000007",
        "tgn:7029392"
    ],
    "tgn:id":1006305,
    "tgn:name":"Anvers Island",
    "tgn:placetype":[
        "aat:300008791"
    ]
},
  "bbox": [],
  "geometry": {"coordinates":[-63.5833,-64.55],"type":"Point"}
}