{
  "id": 2740155,
  "type": "Feature",
  "properties": {
    "tgn:hierarchy":[
        "tgn:2740155",
        "tgn:1000001",
        "tgn:7012149",
        "tgn:2002337",
        "tgn:7007922",
        "tgn:7029392"
    ],
    "tgn:id":2740155,
    "tgn:name":"Upper Inlet",
    "tgn:placetype":[
        "aat:300008699"
    ]
},
  "bbox": [],
  "geometry": {"coordinates":[-87.8167,45.2833],"type":"Point"}
}