{
  "id": 2632272,
  "type": "Feature",
  "properties": {
    "tgn:hierarchy":[
        "tgn:2632272",
        "tgn:1000001",
        "tgn:7012149",
        "tgn:2001894",
        "tgn:7007825",
        "tgn:7029392"
    ],
    "tgn:id":2632272,
    "tgn:name":"Roy Cove Branch",
    "tgn:placetype":[
        "aat:300008699"
    ]
},
  "bbox": [],
  "geometry": {"coordinates":[-85.75,35.1833],"type":"Point"}
}