{
  "id": 2173952,
  "type": "Feature",
  "properties": {
    "tgn:hierarchy":[
        "tgn:2173952",
        "tgn:1000001",
        "tgn:1002200",
        "tgn:7012149",
        "tgn:7007240",
        "tgn:7029392"
    ],
    "tgn:id":2173952,
    "tgn:name":"Bird Lake",
    "tgn:placetype":[
        "aat:300008905"
    ]
},
  "bbox": [],
  "geometry": {"coordinates":[-80.8333,28.5167],"type":"Point"}
}