{
  "id": 7512616,
  "type": "Feature",
  "properties": {
    "tgn:hierarchy":[
        "tgn:7512616",
        "tgn:1009227",
        "tgn:1000226",
        "tgn:7016729",
        "tgn:1000006",
        "tgn:7029392"
    ],
    "tgn:id":7512616,
    "tgn:name:en":"Hog Swamp Creek",
    "tgn:placetype":[
        "aat:300008699"
    ]
},
  "bbox": [],
  "geometry": {"coordinates":[174.116667,-41.683333],"type":"Point"}
}