{
  "id": 7034625,
  "type": "Feature",
  "properties": {
    "tgn:hierarchy":[
        "tgn:7034625",
        "tgn:7003006",
        "tgn:1000003",
        "tgn:7002997",
        "tgn:1000080",
        "tgn:7029392"
    ],
    "tgn:id":7034625,
    "tgn:name":"Canale Vecchio di Fusina",
    "tgn:placetype":[
        "aat:300006075"
    ]
},
  "bbox": [],
  "geometry": {"coordinates":[12.283333,45.425],"type":"Point"}
}