{
  "id": 7555505,
  "type": "Feature",
  "properties": {
    "tgn:hierarchy":[
        "tgn:7555505",
        "tgn:1000004",
        "tgn:7031781",
        "tgn:7000198",
        "tgn:7029392"
    ],
    "tgn:id":7555505,
    "tgn:name:en":"M\u0101ndhar",
    "tgn:placetype":[
        "aat:300008347"
    ]
},
  "bbox": [],
  "geometry": {"coordinates":[81.683333,21.35],"type":"Point"}
}