{
  "id": 7287925,
  "type": "Feature",
  "properties": {
    "tgn:hierarchy":[
        "tgn:7287925",
        "tgn:7016598",
        "tgn:1000049",
        "tgn:1000002",
        "tgn:7029392"
    ],
    "tgn:id":7287925,
    "tgn:name":"Joya",
    "tgn:placetype":[
        "aat:300387033"
    ]
},
  "bbox": [],
  "geometry": {"coordinates":[-69.383333,-21.85],"type":"Point"}
}