{
  "id": 2487290,
  "type": "Feature",
  "properties": {
    "tgn:hierarchy":[
        "tgn:2487290",
        "tgn:2001423",
        "tgn:1000001",
        "tgn:7012149",
        "tgn:7007564",
        "tgn:7029392"
    ],
    "tgn:id":2487290,
    "tgn:name":"Lees Pond",
    "tgn:placetype":[
        "aat:300008680"
    ]
},
  "bbox": [],
  "geometry": {"coordinates":[-71.3833,43.7333],"type":"Point"}
}