{
  "id": 7410649,
  "type": "Feature",
  "properties": {
    "tgn:hierarchy":[
        "tgn:7410649",
        "tgn:1000001",
        "tgn:7005590",
        "tgn:7005560",
        "tgn:7029392"
    ],
    "tgn:id":7410649,
    "tgn:name":"Car\u00e1cuaro, R\u00edo",
    "tgn:placetype":[
        "aat:300008699"
    ]
},
  "bbox": [],
  "geometry": {"coordinates":[-101.2125,18.816667],"type":"Point"}
}