{
  "id": 1016399,
  "type": "Feature",
  "properties": {
    "tgn:hierarchy":[
        "tgn:1016399",
        "tgn:1007571",
        "tgn:7006369",
        "tgn:1000001",
        "tgn:7004624",
        "tgn:7029392"
    ],
    "tgn:id":1016399,
    "tgn:name":"Nueva Gerona",
    "tgn:placetype":[
        "aat:300008347",
        "aat:300008389",
        "aat:300387223",
        "aat:300387302",
        "aat:300120599",
        "aat:300387286"
    ]
},
  "bbox": [],
  "geometry": {"coordinates":[-82.8167,21.8833],"type":"Point"}
}