{
  "id": 2779864,
  "type": "Feature",
  "properties": {
    "tgn:hierarchy":[
        "tgn:2779864",
        "tgn:1000001",
        "tgn:7012149",
        "tgn:2000278",
        "tgn:7007240",
        "tgn:7029392"
    ],
    "tgn:id":2779864,
    "tgn:name":"Wolf Trail Bay",
    "tgn:placetype":[
        "aat:300008905"
    ]
},
  "bbox": [],
  "geometry": {"coordinates":[-84.9167,30.3167],"type":"Point"}
}