{
  "id": 7578193,
  "type": "Feature",
  "properties": {
    "tgn:hierarchy":[
        "tgn:7578193",
        "tgn:1000004",
        "tgn:7000198",
        "tgn:7001797",
        "tgn:7029392"
    ],
    "tgn:id":7578193,
    "tgn:name:en":"Vikrav\u0101ndi",
    "tgn:placetype":[
        "aat:300008347"
    ]
},
  "bbox": [],
  "geometry": {"coordinates":[79.55,12.033333],"type":"Point"}
}