{
  "id": 7166748,
  "type": "Feature",
  "properties": {
    "tgn:hierarchy":[
        "tgn:7166748",
        "tgn:7003669",
        "tgn:1000003",
        "tgn:7000084",
        "tgn:7029392"
    ],
    "tgn:id":7166748,
    "tgn:name":"Haselbach",
    "tgn:placetype":[
        "aat:300008699"
    ]
},
  "bbox": [],
  "geometry": {"coordinates":[10.366667,48.333333],"type":"Point"}
}