{
  "id": 7301219,
  "type": "Feature",
  "properties": {
    "tgn:hierarchy":[
        "tgn:7301219",
        "tgn:7002806",
        "tgn:7001158",
        "tgn:1000003",
        "tgn:1000095",
        "tgn:7029392"
    ],
    "tgn:id":7301219,
    "tgn:name":"Monsalupe",
    "tgn:placetype":[
        "aat:300008347"
    ]
},
  "bbox": [],
  "geometry": {"coordinates":[-4.783333,40.766667],"type":"Point"}
}