{
  "id": 2340549,
  "type": "Feature",
  "properties": {
    "tgn:hierarchy":[
        "tgn:2340549",
        "tgn:1000001",
        "tgn:7012149",
        "tgn:2002371",
        "tgn:7007923",
        "tgn:7029392"
    ],
    "tgn:id":2340549,
    "tgn:name":"Frenchie Reservoir",
    "tgn:placetype":[
        "aat:300006191"
    ]
},
  "bbox": [],
  "geometry": {"coordinates":[-107.65,43.15],"type":"Point"}
}