{
  "id": 2508013,
  "type": "Feature",
  "properties": {
    "tgn:hierarchy":[
        "tgn:2508013",
        "tgn:1000001",
        "tgn:7012149",
        "tgn:7029392"
    ],
    "tgn:id":2508013,
    "tgn:name":"Middle Beaver Creek",
    "tgn:placetype":[
        "aat:300008706"
    ]
},
  "bbox": [],
  "geometry": {"coordinates":[-102.3333,39.1667],"type":"Point"}
}