{
  "id": 2355809,
  "type": "Feature",
  "properties": {
    "tgn:hierarchy":[
        "tgn:2355809",
        "tgn:1000001",
        "tgn:7012149",
        "tgn:2000980",
        "tgn:7007520",
        "tgn:7029392"
    ],
    "tgn:id":2355809,
    "tgn:name":"Goose Lake",
    "tgn:placetype":[
        "aat:300008680"
    ]
},
  "bbox": [],
  "geometry": {"coordinates":[-85.2333,44.35],"type":"Point"}
}