{
  "id": 7532783,
  "type": "Feature",
  "properties": {
    "tgn:hierarchy":[
        "tgn:7532783",
        "tgn:7001242",
        "tgn:7016833",
        "tgn:1001091",
        "tgn:7029392"
    ],
    "tgn:id":7532783,
    "tgn:name":"Masjid 'Alam ad D\u012bn",
    "tgn:placetype":[
        "aat:300007544"
    ]
},
  "bbox": [],
  "geometry": {"coordinates":[31.245285,30.046766],"type":"Point"}
}