<<<<<<< HEAD
{
  "id": 7362953,
  "type": "Feature",
  "properties": {
    "tgn:hierarchy":[
        "tgn:7362953",
        "tgn:1000001",
        "tgn:7005596",
        "tgn:7005560",
        "tgn:7029392"
    ],
    "tgn:id":7362953,
    "tgn:name":"El Amparo",
    "tgn:placetype":[
        "aat:300008347"
    ]
},
  "bbox": [],
  "geometry": {"coordinates":[-93.466667,17.566667],"type":"Point"}
}
=======
{"geometry":{"type":"Point","coordinates":[-93.466667,17.566667]},"type":"Feature","properties":{"hierarchy":["tgn:7362953","tgn:1000001","tgn:7005596","tgn:7005560","tgn:7029392"],"placetype":["aat:300008347"],"id":7362953,"name:xx":"El Amparo"}}
>>>>>>> 03f74aca74312dbeaf24d7e61306dd6a786dc3d0
