{
  "id": 2411852,
  "type": "Feature",
  "properties": {
    "tgn:hierarchy":[
        "tgn:2411852",
        "tgn:1000001",
        "tgn:7012149",
        "tgn:2000491",
        "tgn:7007250",
        "tgn:7029392"
    ],
    "tgn:id":2411852,
    "tgn:name":"Indian Peak",
    "tgn:placetype":[
        "aat:300008798"
    ]
},
  "bbox": [],
  "geometry": {"coordinates":[-115.3167,47.0667],"type":"Point"}
}