{
  "id": 2349470,
  "type": "Feature",
  "properties": {
    "tgn:hierarchy":[
        "tgn:2349470",
        "tgn:1000001",
        "tgn:7012149",
        "tgn:2002118",
        "tgn:7007827",
        "tgn:7029392"
    ],
    "tgn:id":2349470,
    "tgn:name":"Gill",
    "tgn:placetype":[
        "aat:300008347"
    ]
},
  "bbox": [],
  "geometry": {"coordinates":[-111.8333,40.6167],"type":"Point"}
}