{
  "id": 2605468,
  "type": "Feature",
  "properties": {
    "tgn:hierarchy":[
        "tgn:2605468",
        "tgn:1000001",
        "tgn:7012149",
        "tgn:2001708",
        "tgn:7007708",
        "tgn:7029392"
    ],
    "tgn:id":2605468,
    "tgn:name":"Rail Creek",
    "tgn:placetype":[
        "aat:300008706"
    ]
},
  "bbox": [],
  "geometry": {"coordinates":[-119.0833,44.0667],"type":"Point"}
}