{
  "id": 1101830,
  "type": "Feature",
  "properties": {
    "tgn:hierarchy":[
        "tgn:1101830",
        "tgn:1006698",
        "tgn:7005685",
        "tgn:1000001",
        "tgn:7005799",
        "tgn:7029392"
    ],
    "tgn:id":1101830,
    "tgn:name":"Roosevelt Campobello International Park",
    "tgn:placetype":[
        "aat:300008189"
    ]
},
  "bbox": [],
  "geometry": {"coordinates":[-66.9667,44.8667],"type":"Point"}
}