{
  "id": 7054433,
  "type": "Feature",
  "properties": {
    "tgn:hierarchy":[
        "tgn:7054433",
        "tgn:7002994",
        "tgn:1000003",
        "tgn:7002997",
        "tgn:1000080",
        "tgn:7029392"
    ],
    "tgn:id":7054433,
    "tgn:name":"Canale Monselice",
    "tgn:placetype":[
        "aat:300006075"
    ]
},
  "bbox": [],
  "geometry": {"coordinates":[11.766667,45.233333],"type":"Point"}
}