{
  "id": 7346224,
  "type": "Feature",
  "properties": {
    "tgn:hierarchy":[
        "tgn:7346224",
        "tgn:7002759",
        "tgn:7008909",
        "tgn:1000003",
        "tgn:1000095",
        "tgn:7029392"
    ],
    "tgn:id":7346224,
    "tgn:name":"Benasque",
    "tgn:placetype":[
        "aat:300008347"
    ]
},
  "bbox": [],
  "geometry": {"coordinates":[0.522583,42.60488],"type":"Point"}
}