{
  "id": 2610791,
  "type": "Feature",
  "properties": {
    "tgn:hierarchy":[
        "tgn:2610791",
        "tgn:1000001",
        "tgn:2002241",
        "tgn:7012149",
        "tgn:7007920",
        "tgn:7029392"
    ],
    "tgn:id":2610791,
    "tgn:name":"Red Fir Spring",
    "tgn:placetype":[
        "aat:300008697"
    ]
},
  "bbox": [],
  "geometry": {"coordinates":[-117.65,46.1667],"type":"Point"}
}