{
  "id": 7429366,
  "type": "Feature",
  "properties": {
    "tgn:hierarchy":[
        "tgn:7429366",
        "tgn:1001853",
        "tgn:1000001",
        "tgn:7005560",
        "tgn:7029392"
    ],
    "tgn:id":7429366,
    "tgn:name":"Agua de la Mula",
    "tgn:placetype":[
        "aat:300008347"
    ]
},
  "bbox": [],
  "geometry": {"coordinates":[-101.416667,25.466667],"type":"Point"}
}