{
  "id": 7052348,
  "type": "Feature",
  "properties": {
    "tgn:hierarchy":[
        "tgn:7052348",
        "tgn:7009084",
        "tgn:7003000",
        "tgn:1000003",
        "tgn:1000080",
        "tgn:7029392"
    ],
    "tgn:id":7052348,
    "tgn:name":"Moro, Torrente",
    "tgn:placetype":[
        "aat:300008699"
    ]
},
  "bbox": [],
  "geometry": {"coordinates":[14.416667,42.316667],"type":"Point"}
}