{
  "id": 7587563,
  "type": "Feature",
  "properties": {
    "tgn:hierarchy":[
        "tgn:7587563",
        "tgn:1000004",
        "tgn:7000198",
        "tgn:1001977",
        "tgn:7029392"
    ],
    "tgn:id":7587563,
    "tgn:name:en":"Raghun\u0101thpur",
    "tgn:placetype":[
        "aat:300008347"
    ]
},
  "bbox": [],
  "geometry": {"coordinates":[88.347778,22.121944],"type":"Point"}
}