{
  "id": 2489765,
  "type": "Feature",
  "properties": {
    "tgn:hierarchy":[
        "tgn:2489765",
        "tgn:1000001",
        "tgn:7012149",
        "tgn:2002005",
        "tgn:7007826",
        "tgn:7029392"
    ],
    "tgn:id":2489765,
    "tgn:name":"Malone Mountains",
    "tgn:placetype":[
        "aat:300008798"
    ]
},
  "bbox": [],
  "geometry": {"coordinates":[-105.5333,31.2333],"type":"Point"}
}