{
  "id": 7423563,
  "type": "Feature",
  "properties": {
    "tgn:hierarchy":[
        "tgn:7423563",
        "tgn:1000001",
        "tgn:1001960",
        "tgn:7005560",
        "tgn:7029392"
    ],
    "tgn:id":7423563,
    "tgn:name":"La Bolsa",
    "tgn:placetype":[
        "aat:300008347"
    ]
},
  "bbox": [],
  "geometry": {"coordinates":[-110.116667,28.966667],"type":"Point"}
}