{
  "id": 7407934,
  "type": "Feature",
  "properties": {
    "tgn:hierarchy":[
        "tgn:7407934",
        "tgn:1000001",
        "tgn:7005590",
        "tgn:7005560",
        "tgn:7029392"
    ],
    "tgn:id":7407934,
    "tgn:name":"Catanicua",
    "tgn:placetype":[
        "aat:300008347"
    ]
},
  "bbox": [],
  "geometry": {"coordinates":[-101.497222,19.016667],"type":"Point"}
}