{
  "id": 2374436,
  "type": "Feature",
  "properties": {
    "tgn:hierarchy":[
        "tgn:2374436",
        "tgn:1000001",
        "tgn:2001413",
        "tgn:7012149",
        "tgn:7007526",
        "tgn:7029392"
    ],
    "tgn:id":2374436,
    "tgn:name":"Hams Canyon",
    "tgn:placetype":[
        "aat:300008761"
    ]
},
  "bbox": [],
  "geometry": {"coordinates":[-116.05,40.1833],"type":"Point"}
}