{
  "id": 2504952,
  "type": "Feature",
  "properties": {
    "tgn:hierarchy":[
        "tgn:2504952",
        "tgn:1000001",
        "tgn:7012149",
        "tgn:2000441",
        "tgn:7007248",
        "tgn:7029392"
    ],
    "tgn:id":2504952,
    "tgn:name":"Meek Branch",
    "tgn:placetype":[
        "aat:300008699"
    ]
},
  "bbox": [],
  "geometry": {"coordinates":[-82.85,33.1667],"type":"Point"}
}