{
  "id": 2009562,
  "type": "Feature",
  "properties": {
    "tgn:hierarchy":[
        "tgn:2009562",
        "tgn:1000001",
        "tgn:7016172",
        "tgn:7012149",
        "tgn:2000144",
        "tgn:7029392"
    ],
    "tgn:id":2009562,
    "tgn:name":"Star City",
    "tgn:placetype":[
        "aat:300008347"
    ]
},
  "bbox": [],
  "geometry": {"coordinates":[-91.8333,33.9333],"type":"Point"}
}