{
  "id": 7336984,
  "type": "Feature",
  "properties": {
    "tgn:hierarchy":[
        "tgn:7336984",
        "tgn:7002826",
        "tgn:7001158",
        "tgn:1000003",
        "tgn:1000095",
        "tgn:7029392"
    ],
    "tgn:id":7336984,
    "tgn:name":"Cueva, Manantial de la",
    "tgn:placetype":[
        "aat:300008697"
    ]
},
  "bbox": [],
  "geometry": {"coordinates":[-6.733333,42.316667],"type":"Point"}
}