{
  "id": 2628026,
  "type": "Feature",
  "properties": {
    "tgn:hierarchy":[
        "tgn:2628026",
        "tgn:1000001",
        "tgn:7012149",
        "tgn:7007710",
        "tgn:7029392"
    ],
    "tgn:id":2628026,
    "tgn:name":"Rolling Green Run",
    "tgn:placetype":[
        "aat:300008699"
    ]
},
  "bbox": [],
  "geometry": {"coordinates":[-76.85,40.85],"type":"Point"}
}