{
  "id": 7356154,
  "type": "Feature",
  "properties": {
    "tgn:hierarchy":[
        "tgn:7356154",
        "tgn:1000001",
        "tgn:7005594",
        "tgn:7005560",
        "tgn:7029392"
    ],
    "tgn:id":7356154,
    "tgn:name":"Cerro de la Virgen",
    "tgn:placetype":[
        "aat:300008347"
    ]
},
  "bbox": [],
  "geometry": {"coordinates":[-100.583333,21.683333],"type":"Point"}
}