<<<<<<< HEAD
{
  "id": 7356154,
  "type": "Feature",
  "properties": {
    "tgn:hierarchy":[
        "tgn:7356154",
        "tgn:1000001",
        "tgn:7005594",
        "tgn:7005560",
        "tgn:7029392"
    ],
    "tgn:id":7356154,
    "tgn:name":"Cerro de la Virgen",
    "tgn:placetype":[
        "aat:300008347"
    ]
},
  "bbox": [],
  "geometry": {"coordinates":[-100.583333,21.683333],"type":"Point"}
}
=======
{"geometry":{"type":"Point","coordinates":[-100.583333,21.683333]},"type":"Feature","properties":{"hierarchy":["tgn:7356154","tgn:1000001","tgn:7005594","tgn:7005560","tgn:7029392"],"placetype":["aat:300008347"],"id":7356154,"name:xx":"Cerro de la Virgen"}}
>>>>>>> 03f74aca74312dbeaf24d7e61306dd6a786dc3d0
