{
  "id": 1099663,
  "type": "Feature",
  "properties": {
    "tgn:hierarchy":[
        "tgn:1099663",
        "tgn:1009572",
        "tgn:1000239",
        "tgn:1000006",
        "tgn:7029392"
    ],
    "tgn:id":1099663,
    "tgn:name":"Matautu",
    "tgn:placetype":[
        "aat:300008347"
    ]
},
  "bbox": [],
  "geometry": {"coordinates":[-171.9167,-13.95],"type":"Point"}
}