{
  "id": 2207374,
  "type": "Feature",
  "properties": {
    "tgn:hierarchy":[
        "tgn:2207374",
        "tgn:1000001",
        "tgn:1002359",
        "tgn:7012149",
        "tgn:7007517",
        "tgn:7029392"
    ],
    "tgn:id":2207374,
    "tgn:name":"Bunker Meadows",
    "tgn:placetype":[
        "aat:300008905"
    ]
},
  "bbox": [],
  "geometry": {"coordinates":[-70.9167,42.6167],"type":"Point"}
}