{
  "id": 7540795,
  "type": "Feature",
  "properties": {
    "tgn:hierarchy":[
        "tgn:7540795",
        "tgn:7001242",
        "tgn:1001075",
        "tgn:7016833",
        "tgn:7029392"
    ],
    "tgn:id":7540795,
    "tgn:name:en":"Qaryat Kh\u0101lid Ibn al Wal\u012bd",
    "tgn:placetype":[
        "aat:300008347"
    ]
},
  "bbox": [],
  "geometry": {"coordinates":[30.743519,30.635443],"type":"Point"}
}