{
  "id": 2015680,
  "type": "Feature",
  "properties": {
    "tgn:hierarchy":[
        "tgn:2015680",
        "tgn:1000001",
        "tgn:7012149",
        "tgn:2000206",
        "tgn:7007158",
        "tgn:7029392"
    ],
    "tgn:id":2015680,
    "tgn:name":"Grand Mesa",
    "tgn:placetype":[
        "aat:300008347",
        "aat:300387247"
    ]
},
  "bbox": [],
  "geometry": {"coordinates":[-107.9333,39.0333],"type":"Point"}
}