{
  "id": 7504762,
  "type": "Feature",
  "properties": {
    "tgn:hierarchy":[
        "tgn:7504762",
        "tgn:7000508",
        "tgn:1008380",
        "tgn:1000226",
        "tgn:1000006",
        "tgn:7029392"
    ],
    "tgn:id":7504762,
    "tgn:name:en":"Te Kawau Point",
    "tgn:placetype":[
        "aat:300386846"
    ]
},
  "bbox": [],
  "geometry": {"coordinates":[175.420278,-36.598889],"type":"Point"}
}