{
  "id": 7071003,
  "type": "Feature",
  "properties": {
    "tgn:hierarchy":[
        "tgn:7071003",
        "tgn:7003669",
        "tgn:1000003",
        "tgn:7000084",
        "tgn:7029392"
    ],
    "tgn:id":7071003,
    "tgn:name":"Strahlehen",
    "tgn:placetype":[
        "aat:300000206"
    ]
},
  "bbox": [],
  "geometry": {"coordinates":[12.683333,48.166667],"type":"Point"}
}