{
  "id": 2711358,
  "type": "Feature",
  "properties": {
    "tgn:hierarchy":[
        "tgn:2711358",
        "tgn:7002659",
        "tgn:1000001",
        "tgn:7012149",
        "tgn:2000022",
        "tgn:7029392"
    ],
    "tgn:id":2711358,
    "tgn:name":"Tanyard Branch",
    "tgn:placetype":[
        "aat:300008699"
    ]
},
  "bbox": [],
  "geometry": {"coordinates":[-85.75,31.5667],"type":"Point"}
}