{
  "id": 2230796,
  "type": "Feature",
  "properties": {
    "tgn:hierarchy":[
        "tgn:2230796",
        "tgn:1000001",
        "tgn:7012149",
        "tgn:2000182",
        "tgn:7007157",
        "tgn:7029392"
    ],
    "tgn:id":2230796,
    "tgn:name":"Central Drain Three E",
    "tgn:placetype":[
        "aat:300006075"
    ]
},
  "bbox": [],
  "geometry": {"coordinates":[-115.4333,32.6667],"type":"Point"}
}