{
  "id": 2139171,
  "type": "Feature",
  "properties": {
    "tgn:hierarchy":[
        "tgn:2139171",
        "tgn:1000001",
        "tgn:7012149",
        "tgn:2001885",
        "tgn:7007825",
        "tgn:7029392"
    ],
    "tgn:id":2139171,
    "tgn:name":"Ashport Landing",
    "tgn:placetype":[
        "aat:300008347"
    ]
},
  "bbox": [],
  "geometry": {"coordinates":[-89.7833,35.75],"type":"Point"}
}