{
  "id": 2777965,
  "type": "Feature",
  "properties": {
    "tgn:hierarchy":[
        "tgn:2777965",
        "tgn:1000001",
        "tgn:7006451",
        "tgn:7012149",
        "tgn:2000097",
        "tgn:7029392"
    ],
    "tgn:id":2777965,
    "tgn:name":"Wintersburg",
    "tgn:placetype":[
        "aat:300008347"
    ]
},
  "bbox": [],
  "geometry": {"coordinates":[-112.8667,33.4167],"type":"Point"}
}