{
  "id": 2575212,
  "type": "Feature",
  "properties": {
    "tgn:hierarchy":[
        "tgn:2575212",
        "tgn:1000001",
        "tgn:7012149",
        "tgn:2000238",
        "tgn:7007158",
        "tgn:7029392"
    ],
    "tgn:id":2575212,
    "tgn:name":"Pennsylvania Tunnel",
    "tgn:placetype":[
        "aat:300000390"
    ]
},
  "bbox": [],
  "geometry": {"coordinates":[-106.1333,39.25],"type":"Point"}
}