{
  "id": 2489593,
  "type": "Feature",
  "properties": {
    "tgn:hierarchy":[
        "tgn:2489593",
        "tgn:1000001",
        "tgn:7012149",
        "tgn:2000724",
        "tgn:7007254",
        "tgn:7029392"
    ],
    "tgn:id":2489593,
    "tgn:name":"Mallard Ponds",
    "tgn:placetype":[
        "aat:300008680"
    ]
},
  "bbox": [],
  "geometry": {"coordinates":[-101.7833,37.1333],"type":"Point"}
}