<<<<<<< HEAD
{
  "id": 7359457,
  "type": "Feature",
  "properties": {
    "tgn:hierarchy":[
        "tgn:7359457",
        "tgn:1000001",
        "tgn:1001893",
        "tgn:7005560",
        "tgn:7029392"
    ],
    "tgn:id":7359457,
    "tgn:name":"Ciudad Sat\u00e9lite",
    "tgn:placetype":[
        "aat:300008347"
    ]
},
  "bbox": [],
  "geometry": {"coordinates":[-99.25,19.516667],"type":"Point"}
}
=======
{"geometry":{"type":"Point","coordinates":[-99.250000,19.516667]},"type":"Feature","properties":{"hierarchy":["tgn:7359457","tgn:1000001","tgn:1001893","tgn:7005560","tgn:7029392"],"placetype":["aat:300008347"],"id":7359457,"name:xx":"Ciudad Sat\u00e9lite"}}
>>>>>>> 03f74aca74312dbeaf24d7e61306dd6a786dc3d0
