{
  "id": 7359457,
  "type": "Feature",
  "properties": {
    "tgn:hierarchy":[
        "tgn:7359457",
        "tgn:1000001",
        "tgn:1001893",
        "tgn:7005560",
        "tgn:7029392"
    ],
    "tgn:id":7359457,
    "tgn:name":"Ciudad Sat\u00e9lite",
    "tgn:placetype":[
        "aat:300008347"
    ]
},
  "bbox": [],
  "geometry": {"coordinates":[-99.25,19.516667],"type":"Point"}
}