<<<<<<< HEAD
{
  "id": 7482909,
  "type": "Feature",
  "properties": {
    "tgn:hierarchy":[
        "tgn:7482909",
        "tgn:7468018",
        "tgn:1000004",
        "tgn:1000141",
        "tgn:7029392"
    ],
    "tgn:id":7482909,
    "tgn:name":"Sheqianhu",
    "tgn:placetype":[
        "aat:300008347"
    ]
},
  "bbox": [],
  "geometry": {"coordinates":[120.722778,23.556389],"type":"Point"}
}
=======
{"geometry":{"type":"Point","coordinates":[120.722778,23.556389]},"type":"Feature","properties":{"hierarchy":["tgn:7482909","tgn:7468018","tgn:1000004","tgn:1000141","tgn:7029392"],"placetype":["aat:300008347"],"id":7482909,"name:xx":"Sheqianhu"}}
>>>>>>> 03f74aca74312dbeaf24d7e61306dd6a786dc3d0
