{
  "id": 2165955,
  "type": "Feature",
  "properties": {
    "tgn:hierarchy":[
        "tgn:2165955",
        "tgn:1000001",
        "tgn:2001419",
        "tgn:7012149",
        "tgn:7007526",
        "tgn:7029392"
    ],
    "tgn:id":2165955,
    "tgn:name":"Big Antelope Spring",
    "tgn:placetype":[
        "aat:300008697"
    ]
},
  "bbox": [],
  "geometry": {"coordinates":[-118.4833,40.6833],"type":"Point"}
}