<<<<<<< HEAD
{
  "id": 7373312,
  "type": "Feature",
  "properties": {
    "tgn:hierarchy":[
        "tgn:7373312",
        "tgn:1000001",
        "tgn:7005597",
        "tgn:7005560",
        "tgn:7029392"
    ],
    "tgn:id":7373312,
    "tgn:name":"Laga\u00f1a, Isla de la",
    "tgn:placetype":[
        "aat:300008791"
    ]
},
  "bbox": [],
  "geometry": {"coordinates":[-97.433333,25.383333],"type":"Point"}
}
=======
{"geometry":{"type":"Point","coordinates":[-97.433333,25.383333]},"type":"Feature","properties":{"hierarchy":["tgn:7373312","tgn:1000001","tgn:7005597","tgn:7005560","tgn:7029392"],"placetype":["aat:300008791"],"id":7373312,"name:xx":"Laga\u00f1a, Isla de la"}}
>>>>>>> 03f74aca74312dbeaf24d7e61306dd6a786dc3d0
