{
  "id": 2739318,
  "type": "Feature",
  "properties": {
    "tgn:hierarchy":[
        "tgn:2739318",
        "tgn:1000001",
        "tgn:7006451",
        "tgn:7012149",
        "tgn:2000098",
        "tgn:7029392"
    ],
    "tgn:id":2739318,
    "tgn:name":"Upper Antelope",
    "tgn:placetype":[
        "aat:300008798"
    ]
},
  "bbox": [],
  "geometry": {"coordinates":[-113.2333,36.9167],"type":"Point"}
}