{
  "id": 2393460,
  "type": "Feature",
  "properties": {
    "tgn:hierarchy":[
        "tgn:2393460",
        "tgn:1000001",
        "tgn:7012149",
        "tgn:2002067",
        "tgn:7007826",
        "tgn:7029392"
    ],
    "tgn:id":2393460,
    "tgn:name":"Hog Branch",
    "tgn:placetype":[
        "aat:300008699"
    ]
},
  "bbox": [],
  "geometry": {"coordinates":[-94.2833,31.25],"type":"Point"}
}