{
  "id": 7490377,
  "type": "Feature",
  "properties": {
    "tgn:hierarchy":[
        "tgn:7490377",
        "tgn:1000004",
        "tgn:7492971",
        "tgn:1000141",
        "tgn:7029392"
    ],
    "tgn:id":7490377,
    "tgn:name":"Dawu Shan",
    "tgn:placetype":[
        "aat:300008798"
    ]
},
  "bbox": [],
  "geometry": {"coordinates":[120.70407,22.503579],"type":"Point"}
}