{
  "id": 2588342,
  "type": "Feature",
  "properties": {
    "tgn:hierarchy":[
        "tgn:2588342",
        "tgn:1000001",
        "tgn:7012149",
        "tgn:2001883",
        "tgn:7007825",
        "tgn:7029392"
    ],
    "tgn:id":2588342,
    "tgn:name":"Plum Creek",
    "tgn:placetype":[
        "aat:300008347"
    ]
},
  "bbox": [],
  "geometry": {"coordinates":[-84.1333,35.9333],"type":"Point"}
}