{
  "id": 1100008,
  "type": "Feature",
  "properties": {
    "tgn:hierarchy":[
        "tgn:1100008",
        "tgn:7000430",
        "tgn:1000006",
        "tgn:7029392"
    ],
    "tgn:id":1100008,
    "tgn:name":"Saint Barnabas Chapel",
    "tgn:placetype":[
        "aat:300007466"
    ]
},
  "bbox": [],
  "geometry": {"coordinates":[167.9167,-29.0333],"type":"Point"}
}