{
  "id": 7517591,
  "type": "Feature",
  "properties": {
    "tgn:hierarchy":[
        "tgn:7517591",
        "tgn:1008380",
        "tgn:7520093",
        "tgn:1000226",
        "tgn:1000006",
        "tgn:7029392"
    ],
    "tgn:id":7517591,
    "tgn:name:en":"Makorokio Stream",
    "tgn:placetype":[
        "aat:300008699"
    ]
},
  "bbox": [],
  "geometry": {"coordinates":[175.266667,-40.683333],"type":"Point"}
}