{
  "id": 7480547,
  "type": "Feature",
  "properties": {
    "tgn:hierarchy":[
        "tgn:7480547",
        "tgn:1000004",
        "tgn:7490934",
        "tgn:1000141",
        "tgn:7029392"
    ],
    "tgn:id":7480547,
    "tgn:name":"Shanhua",
    "tgn:placetype":[
        "aat:300387033"
    ]
},
  "bbox": [],
  "geometry": {"coordinates":[120.295939,23.120092],"type":"Point"}
}