<<<<<<< HEAD
{
  "id": 7480547,
  "type": "Feature",
  "properties": {
    "tgn:hierarchy":[
        "tgn:7480547",
        "tgn:1000004",
        "tgn:7490934",
        "tgn:1000141",
        "tgn:7029392"
    ],
    "tgn:id":7480547,
    "tgn:name":"Shanhua",
    "tgn:placetype":[
        "aat:300387033"
    ]
},
  "bbox": [],
  "geometry": {"coordinates":[120.295939,23.120092],"type":"Point"}
}
=======
{"geometry":{"type":"Point","coordinates":[120.295939,23.120092]},"type":"Feature","properties":{"hierarchy":["tgn:7480547","tgn:1000004","tgn:7490934","tgn:1000141","tgn:7029392"],"placetype":["aat:300387033"],"id":7480547,"name:xx":"Shanhua"}}
>>>>>>> 03f74aca74312dbeaf24d7e61306dd6a786dc3d0
