{
  "id": 2590211,
  "type": "Feature",
  "properties": {
    "tgn:hierarchy":[
        "tgn:2590211",
        "tgn:1000001",
        "tgn:7012149",
        "tgn:1003017",
        "tgn:7007710",
        "tgn:7029392"
    ],
    "tgn:id":2590211,
    "tgn:name":"Poke Run",
    "tgn:placetype":[
        "aat:300008347"
    ]
},
  "bbox": [],
  "geometry": {"coordinates":[-79.5833,40.4833],"type":"Point"}
}