{
  "id": 7460871,
  "type": "Feature",
  "properties": {
    "tgn:hierarchy":[
        "tgn:7460871",
        "tgn:7002445",
        "tgn:1000003",
        "tgn:7008185",
        "tgn:7008591",
        "tgn:7029392"
    ],
    "tgn:id":7460871,
    "tgn:name:en":"Hollesley Bay",
    "tgn:placetype":[
        "aat:300132316"
    ]
},
  "bbox": [],
  "geometry": {"coordinates":[1.55,52.066667],"type":"Point"}
}