{
  "id": 7208770,
  "type": "Feature",
  "properties": {
    "tgn:hierarchy":[
        "tgn:7208770",
        "tgn:7003669",
        "tgn:1000003",
        "tgn:7000084",
        "tgn:7029392"
    ],
    "tgn:id":7208770,
    "tgn:name":"B\u00e4rndorf",
    "tgn:placetype":[
        "aat:300008347"
    ]
},
  "bbox": [],
  "geometry": {"coordinates":[13.266667,48.816667],"type":"Point"}
}