{
  "id": 2319796,
  "type": "Feature",
  "properties": {
    "tgn:hierarchy":[
        "tgn:2319796",
        "tgn:1000001",
        "tgn:7012149",
        "tgn:2000494",
        "tgn:7007250",
        "tgn:7029392"
    ],
    "tgn:id":2319796,
    "tgn:name":"Eureka Point",
    "tgn:placetype":[
        "aat:300008850"
    ]
},
  "bbox": [],
  "geometry": {"coordinates":[-115.7667,44.4667],"type":"Point"}
}