{
  "id": 2503590,
  "type": "Feature",
  "properties": {
    "tgn:hierarchy":[
        "tgn:2503590",
        "tgn:1000001",
        "tgn:1002284",
        "tgn:7012149",
        "tgn:7007568",
        "tgn:7029392"
    ],
    "tgn:id":2503590,
    "tgn:name":"Mead Reservoir",
    "tgn:placetype":[
        "aat:300006191"
    ]
},
  "bbox": [],
  "geometry": {"coordinates":[-73.5667,44.7167],"type":"Point"}
}