{
  "id": 2547612,
  "type": "Feature",
  "properties": {
    "tgn:hierarchy":[
        "tgn:2547612",
        "tgn:7006450",
        "tgn:1000001",
        "tgn:2124012",
        "tgn:7012149",
        "tgn:7029392"
    ],
    "tgn:id":2547612,
    "tgn:name":"North Fork Thumb River",
    "tgn:placetype":[
        "aat:300008707"
    ]
},
  "bbox": [],
  "geometry": {"coordinates":[-153.9167,57.3833],"type":"Point"}
}