{
  "id": 7157178,
  "type": "Feature",
  "properties": {
    "tgn:hierarchy":[
        "tgn:7157178",
        "tgn:1000003",
        "tgn:7000094",
        "tgn:7000084",
        "tgn:7029392"
    ],
    "tgn:id":7157178,
    "tgn:name":"Keez",
    "tgn:placetype":[
        "aat:300008347"
    ]
},
  "bbox": [],
  "geometry": {"coordinates":[11.633333,53.733333],"type":"Point"}
}