{
  "id": 7419394,
  "type": "Feature",
  "properties": {
    "tgn:hierarchy":[
        "tgn:7419394",
        "tgn:1000001",
        "tgn:7005589",
        "tgn:7005560",
        "tgn:7029392"
    ],
    "tgn:id":7419394,
    "tgn:name:es":"El Campanero",
    "tgn:placetype":[
        "aat:300008347"
    ]
},
  "bbox": [],
  "geometry": {"coordinates":[-100.382778,27.038056],"type":"Point"}
}