{
  "id": 2250895,
  "type": "Feature",
  "properties": {
    "tgn:hierarchy":[
        "tgn:2250895",
        "tgn:1000001",
        "tgn:7012149",
        "tgn:7007157",
        "tgn:1002857",
        "tgn:7029392"
    ],
    "tgn:id":2250895,
    "tgn:name":"Columbia Mine",
    "tgn:placetype":[
        "aat:300000390"
    ]
},
  "bbox": [],
  "geometry": {"coordinates":[-115.4667,35.0667],"type":"Point"}
}