{
  "id": 7346093,
  "type": "Feature",
  "properties": {
    "tgn:hierarchy":[
        "tgn:7346093",
        "tgn:7002807",
        "tgn:1000003",
        "tgn:7003837",
        "tgn:1000095",
        "tgn:7029392"
    ],
    "tgn:id":7346093,
    "tgn:name":"Azorejo, Collado de",
    "tgn:placetype":[
        "aat:300259572"
    ]
},
  "bbox": [],
  "geometry": {"coordinates":[-4.916667,38.916667],"type":"Point"}
}