{
  "id": 1034936,
  "type": "Feature",
  "properties": {
    "tgn:hierarchy":[
        "tgn:1034936",
        "tgn:7002871",
        "tgn:1000003",
        "tgn:1000070",
        "tgn:7029392"
    ],
    "tgn:id":1034936,
    "tgn:name":"Pontaumur",
    "tgn:placetype":[
        "aat:300008347"
    ]
},
  "bbox": [],
  "geometry": {"coordinates":[2.6667,45.8667],"type":"Point"}
}