{
  "id": 1028367,
  "type": "Feature",
  "properties": {
    "tgn:hierarchy":[
        "tgn:1028367",
        "tgn:7002445",
        "tgn:1000003",
        "tgn:1003654",
        "tgn:7008591",
        "tgn:7029392"
    ],
    "tgn:id":1028367,
    "tgn:name:en":"Aveley",
    "tgn:placetype":[
        "aat:300008347",
        "aat:300008372",
        "aat:300020533"
    ]
},
  "bbox": [],
  "geometry": {"coordinates":[0.25,51.483333],"type":"Point"}
}