{
  "id": 7071893,
  "type": "Feature",
  "properties": {
    "tgn:hierarchy":[
        "tgn:7071893",
        "tgn:7003669",
        "tgn:1000003",
        "tgn:7000084",
        "tgn:7029392"
    ],
    "tgn:id":7071893,
    "tgn:name":"Theisenorter Wald",
    "tgn:placetype":[
        "aat:300008863"
    ]
},
  "bbox": [],
  "geometry": {"coordinates":[11.266667,50.233333],"type":"Point"}
}