{
  "id": 2476857,
  "type": "Feature",
  "properties": {
    "tgn:hierarchy":[
        "tgn:2476857",
        "tgn:1000001",
        "tgn:7012149",
        "tgn:2000911",
        "tgn:7007256",
        "tgn:7029392"
    ],
    "tgn:id":2476857,
    "tgn:name":"Lyles Addition",
    "tgn:placetype":[
        "aat:300008347"
    ]
},
  "bbox": [],
  "geometry": {"coordinates":[-93.25,31.1333],"type":"Point"}
}