{
  "id": 7098061,
  "type": "Feature",
  "properties": {
    "tgn:hierarchy":[
        "tgn:7098061",
        "tgn:7000096",
        "tgn:1000003",
        "tgn:7000084",
        "tgn:7029392"
    ],
    "tgn:id":7098061,
    "tgn:name":"Senzke",
    "tgn:placetype":[
        "aat:300008347"
    ]
},
  "bbox": [],
  "geometry": {"coordinates":[12.583333,52.65],"type":"Point"}
}