{
  "id": 2231695,
  "type": "Feature",
  "properties": {
    "tgn:hierarchy":[
        "tgn:2231695",
        "tgn:1000001",
        "tgn:7016172",
        "tgn:7012149",
        "tgn:2000179",
        "tgn:7029392"
    ],
    "tgn:id":2231695,
    "tgn:name":"Chalybeate Springs",
    "tgn:placetype":[
        "aat:300008347"
    ]
},
  "bbox": [],
  "geometry": {"coordinates":[-93.5667,34.9833],"type":"Point"}
}