{
  "id": 7320110,
  "type": "Feature",
  "properties": {
    "tgn:hierarchy":[
        "tgn:7320110",
        "tgn:1001630",
        "tgn:1000049",
        "tgn:1000002",
        "tgn:7029392"
    ],
    "tgn:id":7320110,
    "tgn:name":"Agua Helada, Vega del",
    "tgn:placetype":[
        "aat:300386871"
    ]
},
  "bbox": [],
  "geometry": {"coordinates":[-68.95,-26.333333],"type":"Point"}
}