{
  "id": 7263686,
  "type": "Feature",
  "properties": {
    "tgn:hierarchy":[
        "tgn:7263686",
        "tgn:1000003",
        "tgn:7003626",
        "tgn:7016845",
        "tgn:7029392"
    ],
    "tgn:id":7263686,
    "tgn:name:nl":"Jordaanshoeve",
    "tgn:placetype":[
        "aat:300000206"
    ]
},
  "bbox": [],
  "geometry": {"coordinates":[6.75,52.183333],"type":"Point"}
}