{
  "id": 7480546,
  "type": "Feature",
  "properties": {
    "tgn:hierarchy":[
        "tgn:7480546",
        "tgn:1000004",
        "tgn:7490934",
        "tgn:1000141",
        "tgn:7029392"
    ],
    "tgn:id":7480546,
    "tgn:name":"Wenkai Qizo",
    "tgn:placetype":[
        "aat:300007836"
    ]
},
  "bbox": [],
  "geometry": {"coordinates":[120.293563,23.137185],"type":"Point"}
}