{
  "id": 2454974,
  "type": "Feature",
  "properties": {
    "tgn:hierarchy":[
        "tgn:2454974",
        "tgn:1000001",
        "tgn:2001099",
        "tgn:7012149",
        "tgn:7007522",
        "tgn:7029392"
    ],
    "tgn:id":2454974,
    "tgn:name":"Little Eddy Lake",
    "tgn:placetype":[
        "aat:300008680"
    ]
},
  "bbox": [],
  "geometry": {"coordinates":[-90.7833,34.15],"type":"Point"}
}