<<<<<<< HEAD
{
  "id": 7171846,
  "type": "Feature",
  "properties": {
    "tgn:hierarchy":[
        "tgn:7171846",
        "tgn:7003669",
        "tgn:1000003",
        "tgn:7000084",
        "tgn:7029392"
    ],
    "tgn:id":7171846,
    "tgn:name":"Herrn Holz",
    "tgn:placetype":[
        "aat:300008863"
    ]
},
  "bbox": [],
  "geometry": {"coordinates":[11.783333,47.983333],"type":"Point"}
}
=======
{"geometry":{"type":"Point","coordinates":[11.783333,47.983333]},"type":"Feature","properties":{"hierarchy":["tgn:7171846","tgn:7003669","tgn:1000003","tgn:7000084","tgn:7029392"],"placetype":["aat:300008863"],"id":7171846,"name:xx":"Herrn Holz"}}
>>>>>>> 03f74aca74312dbeaf24d7e61306dd6a786dc3d0
