{
  "id": 7196904,
  "type": "Feature",
  "properties": {
    "tgn:hierarchy":[
        "tgn:7196904",
        "tgn:1000003",
        "tgn:7003677",
        "tgn:7000084",
        "tgn:7029392"
    ],
    "tgn:id":7196904,
    "tgn:name":"Dong",
    "tgn:placetype":[
        "aat:300387200"
    ]
},
  "bbox": [],
  "geometry": {"coordinates":[6.566667,51.466667],"type":"Point"}
}