{
  "id": 7339447,
  "type": "Feature",
  "properties": {
    "tgn:hierarchy":[
        "tgn:7339447",
        "tgn:7002836",
        "tgn:7016622",
        "tgn:1000003",
        "tgn:1000095",
        "tgn:7029392"
    ],
    "tgn:id":7339447,
    "tgn:name":"El Cabrito, Playa de",
    "tgn:placetype":[
        "aat:300008816"
    ]
},
  "bbox": [],
  "geometry": {"coordinates":[-17.133333,28.05],"type":"Point"}
}