{
  "id": 7123856,
  "type": "Feature",
  "properties": {
    "tgn:hierarchy":[
        "tgn:7123856",
        "tgn:1000003",
        "tgn:7003682",
        "tgn:7000084",
        "tgn:7029392"
    ],
    "tgn:id":7123856,
    "tgn:name":"Niederheimbacher Wald",
    "tgn:placetype":[
        "aat:300008863"
    ]
},
  "bbox": [],
  "geometry": {"coordinates":[7.816667,50.016667],"type":"Point"}
}