<<<<<<< HEAD
{
  "id": 7244181,
  "type": "Feature",
  "properties": {
    "tgn:hierarchy":[
        "tgn:7244181",
        "tgn:7003456",
        "tgn:1000003",
        "tgn:1000063",
        "tgn:7018236",
        "tgn:7029392"
    ],
    "tgn:id":7244181,
    "tgn:name":"Kapelhoeve",
    "tgn:placetype":[
        "aat:300000206"
    ]
},
  "bbox": [],
  "geometry": {"coordinates":[5.05,51.433333],"type":"Point"}
}
=======
{"geometry":{"type":"Point","coordinates":[5.050000,51.433333]},"type":"Feature","properties":{"hierarchy":["tgn:7244181","tgn:7003456","tgn:1000003","tgn:1000063","tgn:7018236","tgn:7029392"],"placetype":["aat:300000206"],"id":7244181,"name:xx":"Kapelhoeve"}}
>>>>>>> 03f74aca74312dbeaf24d7e61306dd6a786dc3d0
