{
  "id": 2128737,
  "type": "Feature",
  "properties": {
    "tgn:hierarchy":[
        "tgn:2128737",
        "tgn:1000001",
        "tgn:7012149",
        "tgn:2001293",
        "tgn:7007524",
        "tgn:7029392"
    ],
    "tgn:id":2128737,
    "tgn:name":"Aldridge",
    "tgn:placetype":[
        "aat:300008347"
    ]
},
  "bbox": [],
  "geometry": {"coordinates":[-110.8167,45.0833],"type":"Point"}
}