{
  "id": 1020529,
  "type": "Feature",
  "properties": {
    "tgn:hierarchy":[
        "tgn:1020529",
        "tgn:1001826",
        "tgn:1000047",
        "tgn:7002456",
        "tgn:1000002",
        "tgn:7029392"
    ],
    "tgn:id":1020529,
    "tgn:name":"Aiapu\u00e1",
    "tgn:placetype":[
        "aat:300008347"
    ]
},
  "bbox": [],
  "geometry": {"coordinates":[-62.0333,-4.4833],"type":"Point"}
}