<<<<<<< HEAD
{
  "id": 7470337,
  "type": "Feature",
  "properties": {
    "tgn:hierarchy":[
        "tgn:7470337",
        "tgn:1000004",
        "tgn:1000959",
        "tgn:1000141",
        "tgn:7029392"
    ],
    "tgn:id":7470337,
    "tgn:name":"Xizhoudi",
    "tgn:placetype":[
        "aat:300008347"
    ]
},
  "bbox": [],
  "geometry": {"coordinates":[121.496,25.0964],"type":"Point"}
}
=======
{"geometry":{"type":"Point","coordinates":[121.496000,25.096400]},"type":"Feature","properties":{"hierarchy":["tgn:7470337","tgn:1000004","tgn:1000959","tgn:1000141","tgn:7029392"],"placetype":["aat:300008347"],"id":7470337,"name:xx":"Xizhoudi"}}
>>>>>>> 03f74aca74312dbeaf24d7e61306dd6a786dc3d0
