{
  "id": 7470337,
  "type": "Feature",
  "properties": {
    "tgn:hierarchy":[
        "tgn:7470337",
        "tgn:1000004",
        "tgn:1000959",
        "tgn:1000141",
        "tgn:7029392"
    ],
    "tgn:id":7470337,
    "tgn:name":"Xizhoudi",
    "tgn:placetype":[
        "aat:300008347"
    ]
},
  "bbox": [],
  "geometry": {"coordinates":[121.496,25.0964],"type":"Point"}
}