{
  "id": 7473086,
  "type": "Feature",
  "properties": {
    "tgn:hierarchy":[
        "tgn:7473086",
        "tgn:7001004",
        "tgn:1000004",
        "tgn:1000141",
        "tgn:7029392"
    ],
    "tgn:id":7473086,
    "tgn:name":"Tiebutiekai Xi",
    "tgn:placetype":[
        "aat:300008699"
    ]
},
  "bbox": [],
  "geometry": {"coordinates":[120.729486,23.294288],"type":"Point"}
}