{
  "id": 1110440,
  "type": "Feature",
  "properties": {
    "tgn:hierarchy":[
        "tgn:1110440",
        "tgn:1000574",
        "tgn:1000002",
        "tgn:1000058",
        "tgn:7029392"
    ],
    "tgn:id":1110440,
    "tgn:name":"Cufr\u00e9, Cuchilla",
    "tgn:placetype":[
        "aat:300008777"
    ]
},
  "bbox": [],
  "geometry": {"coordinates":[-57.1667,-34.3333],"type":"Point"}
}