{
  "id": 7405684,
  "type": "Feature",
  "properties": {
    "tgn:hierarchy":[
        "tgn:7405684",
        "tgn:7016644",
        "tgn:1000001",
        "tgn:7005560",
        "tgn:7029392"
    ],
    "tgn:id":7405684,
    "tgn:name":"Cantera",
    "tgn:placetype":[
        "aat:300008347"
    ]
},
  "bbox": [],
  "geometry": {"coordinates":[-104.422222,19.141667],"type":"Point"}
}