{
  "id": 1113920,
  "type": "Feature",
  "properties": {
    "tgn:hierarchy":[
        "tgn:1113920",
        "tgn:7002715",
        "tgn:1000003",
        "tgn:1000074",
        "tgn:7029392"
    ],
    "tgn:id":1113920,
    "tgn:name":"Therma\u00efk\u00f3s K\u00f3lpos",
    "tgn:placetype":[
        "aat:300132316",
        "aat:300132315"
    ]
},
  "bbox": [],
  "geometry": {"coordinates":[22.783333,40.383333],"type":"Point"}
}