{
  "id": 1091806,
  "type": "Feature",
  "properties": {
    "tgn:hierarchy":[
        "tgn:1091806",
        "tgn:7001242",
        "tgn:1000774",
        "tgn:1000181",
        "tgn:7029392"
    ],
    "tgn:id":1091806,
    "tgn:name":"Tamask\u00e9",
    "tgn:placetype":[
        "aat:300008347"
    ]
},
  "bbox": [],
  "geometry": {"coordinates":[5.7167,14.8167],"type":"Point"}
}