{
  "id": 2176447,
  "type": "Feature",
  "properties": {
    "tgn:hierarchy":[
        "tgn:2176447",
        "tgn:1000001",
        "tgn:7006451",
        "tgn:7012149",
        "tgn:2000098",
        "tgn:7029392"
    ],
    "tgn:id":2176447,
    "tgn:name":"Black Knolls",
    "tgn:placetype":[
        "aat:300008798"
    ]
},
  "bbox": [],
  "geometry": {"coordinates":[-113.0667,36.85],"type":"Point"}
}