{
  "id": 7561535,
  "type": "Feature",
  "properties": {
    "tgn:hierarchy":[
        "tgn:7561535",
        "tgn:1000004",
        "tgn:7000198",
        "tgn:7016722",
        "tgn:7029392"
    ],
    "tgn:id":7561535,
    "tgn:name:en":"Munshi Ka Nagla",
    "tgn:placetype":[
        "aat:300008347"
    ]
},
  "bbox": [],
  "geometry": {"coordinates":[79.016484,27.853047],"type":"Point"}
}