{
  "id": 7056658,
  "type": "Feature",
  "properties": {
    "tgn:hierarchy":[
        "tgn:7056658",
        "tgn:1003464",
        "tgn:1000003",
        "tgn:7003241",
        "tgn:1000080",
        "tgn:7029392"
    ],
    "tgn:id":7056658,
    "tgn:name":"Acquevive",
    "tgn:placetype":[
        "aat:300008347"
    ]
},
  "bbox": [],
  "geometry": {"coordinates":[14.433333,41.633333],"type":"Point"}
}