{
  "id": 2014251,
  "type": "Feature",
  "properties": {
    "tgn:hierarchy":[
        "tgn:2014251",
        "tgn:1000001",
        "tgn:7012149",
        "tgn:7007157",
        "tgn:1002867",
        "tgn:7029392"
    ],
    "tgn:id":2014251,
    "tgn:name":"Shuman",
    "tgn:placetype":[
        "aat:300387016"
    ]
},
  "bbox": [],
  "geometry": {"coordinates":[-120.5167,34.8667],"type":"Point"}
}