{
  "id": 2295580,
  "type": "Feature",
  "properties": {
    "tgn:hierarchy":[
        "tgn:2295580",
        "tgn:1000001",
        "tgn:2001636",
        "tgn:7012149",
        "tgn:7007707",
        "tgn:7029392"
    ],
    "tgn:id":2295580,
    "tgn:name":"Dripping Springs Creek",
    "tgn:placetype":[
        "aat:300008706"
    ]
},
  "bbox": [],
  "geometry": {"coordinates":[-97.3333,35.15],"type":"Point"}
}