{
  "id": 7036135,
  "type": "Feature",
  "properties": {
    "tgn:hierarchy":[
        "tgn:7036135",
        "tgn:7002996",
        "tgn:1000003",
        "tgn:7002997",
        "tgn:1000080",
        "tgn:7029392"
    ],
    "tgn:id":7036135,
    "tgn:name":"Santo Stefano",
    "tgn:placetype":[
        "aat:300008347"
    ]
},
  "bbox": [],
  "geometry": {"coordinates":[12.015556,45.906389],"type":"Point"}
}