{
  "id": 2575364,
  "type": "Feature",
  "properties": {
    "tgn:hierarchy":[
        "tgn:2575364",
        "tgn:1000001",
        "tgn:7006451",
        "tgn:7012149",
        "tgn:2000099",
        "tgn:7029392"
    ],
    "tgn:id":2575364,
    "tgn:name":"Penrod Number One Tank",
    "tgn:placetype":[
        "aat:300006191"
    ]
},
  "bbox": [],
  "geometry": {"coordinates":[-109.8333,34.2167],"type":"Point"}
}