{
  "id": 1078064,
  "type": "Feature",
  "properties": {
    "tgn:hierarchy":[
        "tgn:1078064",
        "tgn:1001321",
        "tgn:1000004",
        "tgn:1000116",
        "tgn:7029392"
    ],
    "tgn:id":1078064,
    "tgn:name":"Malingping",
    "tgn:placetype":[
        "aat:300008347"
    ]
},
  "bbox": [],
  "geometry": {"coordinates":[106.0167,-6.7667],"type":"Point"}
}