{
  "id": 1128334,
  "type": "Feature",
  "properties": {
    "tgn:hierarchy":[
        "tgn:1128334",
        "tgn:1000752",
        "tgn:1000046",
        "tgn:1000002",
        "tgn:7029392"
    ],
    "tgn:id":1128334,
    "tgn:name":"Palacios, R\u00edo",
    "tgn:placetype":[
        "aat:300008707"
    ]
},
  "bbox": [],
  "geometry": {"coordinates":[-64.383,-16.25],"type":"Point"}
}