{
  "id": 1115260,
  "type": "Feature",
  "properties": {
    "tgn:hierarchy":[
        "tgn:1115260",
        "tgn:1000003",
        "tgn:1000069",
        "tgn:7029392"
    ],
    "tgn:id":1115260,
    "tgn:name":"Kihti",
    "tgn:placetype":[
        "aat:300266559"
    ]
},
  "bbox": [],
  "geometry": {"coordinates":[21.0833,60.25],"type":"Point"}
}