{
  "id": 2734992,
  "type": "Feature",
  "properties": {
    "tgn:hierarchy":[
        "tgn:2734992",
        "tgn:1000001",
        "tgn:7012149",
        "tgn:2002371",
        "tgn:7007923",
        "tgn:7029392"
    ],
    "tgn:id":2734992,
    "tgn:name":"Twenty Lakes Creek",
    "tgn:placetype":[
        "aat:300008706"
    ]
},
  "bbox": [],
  "geometry": {"coordinates":[-109.2667,42.9167],"type":"Point"}
}