{
  "id": 7128381,
  "type": "Feature",
  "properties": {
    "tgn:hierarchy":[
        "tgn:7128381",
        "tgn:1000003",
        "tgn:7003685",
        "tgn:7000084",
        "tgn:7029392"
    ],
    "tgn:id":7128381,
    "tgn:name":"Oberes Vorwerk",
    "tgn:placetype":[
        "aat:300000206"
    ]
},
  "bbox": [],
  "geometry": {"coordinates":[13.233333,50.666667],"type":"Point"}
}