{
  "id": 7032149,
  "type": "Feature",
  "properties": {
    "tgn:hierarchy":[
        "tgn:7032149",
        "tgn:1000003",
        "tgn:1000070",
        "tgn:7002895",
        "tgn:7029392"
    ],
    "tgn:id":7032149,
    "tgn:name":"Callian",
    "tgn:placetype":[
        "aat:300008347"
    ]
},
  "bbox": [],
  "geometry": {"coordinates":[6.762,43.633],"type":"Point"}
}