{
  "id": 7070849,
  "type": "Feature",
  "properties": {
    "tgn:hierarchy":[
        "tgn:7070849",
        "tgn:7000096",
        "tgn:1000003",
        "tgn:7000084",
        "tgn:7029392"
    ],
    "tgn:id":7070849,
    "tgn:name":"Stein-Berge",
    "tgn:placetype":[
        "aat:300008777"
    ]
},
  "bbox": [],
  "geometry": {"coordinates":[13.866667,52.95],"type":"Point"}
}