<<<<<<< HEAD
{
  "id": 7364922,
  "type": "Feature",
  "properties": {
    "tgn:hierarchy":[
        "tgn:7364922",
        "tgn:1001836",
        "tgn:1000001",
        "tgn:7005560",
        "tgn:7029392"
    ],
    "tgn:id":7364922,
    "tgn:name":"Foca, Arrecife de la",
    "tgn:placetype":[
        "aat:300008808"
    ]
},
  "bbox": [],
  "geometry": {"coordinates":[-109.983333,24.433333],"type":"Point"}
}
=======
{"geometry":{"type":"Point","coordinates":[-109.983333,24.433333]},"type":"Feature","properties":{"hierarchy":["tgn:7364922","tgn:1001836","tgn:1000001","tgn:7005560","tgn:7029392"],"placetype":["aat:300008808"],"id":7364922,"name:xx":"Foca, Arrecife de la"}}
>>>>>>> 03f74aca74312dbeaf24d7e61306dd6a786dc3d0
