{
  "id": 1008327,
  "type": "Feature",
  "properties": {
    "tgn:hierarchy":[
        "tgn:1008327",
        "tgn:1000004",
        "tgn:7000198",
        "tgn:1001977",
        "tgn:7029392"
    ],
    "tgn:id":1008327,
    "tgn:name":"New Island",
    "tgn:placetype":[
        "aat:300008791"
    ]
},
  "bbox": [],
  "geometry": {"coordinates":[88.199367,21.520726],"type":"Point"}
}