{
  "id": 7415739,
  "type": "Feature",
  "properties": {
    "tgn:hierarchy":[
        "tgn:7415739",
        "tgn:1000001",
        "tgn:7005591",
        "tgn:7005560",
        "tgn:7029392"
    ],
    "tgn:id":7415739,
    "tgn:name:es":"Las Cuevas",
    "tgn:placetype":[
        "aat:300008347"
    ]
},
  "bbox": [],
  "geometry": {"coordinates":[-97.565278,16.638889],"type":"Point"}
}