{
  "id": 7010423,
  "type": "Feature",
  "properties": {
    "tgn:hierarchy":[
        "tgn:7010423",
        "tgn:7002445",
        "tgn:1000003",
        "tgn:7008154",
        "tgn:7008591",
        "tgn:7029392"
    ],
    "tgn:id":7010423,
    "tgn:name:en":"Accrington",
    "tgn:placetype":[
        "aat:300008347"
    ]
},
  "bbox": [],
  "geometry": {"coordinates":[-2.35,53.766667],"type":"Point"}
}