{
  "id": 7020406,
  "type": "Feature",
  "properties": {
    "tgn:hierarchy":[
        "tgn:7020406",
        "tgn:1000001",
        "tgn:2001266",
        "tgn:7012149",
        "tgn:7007524",
        "tgn:7029392"
    ],
    "tgn:id":7020406,
    "tgn:name":"Broadwater Mines",
    "tgn:placetype":[
        "aat:300000390"
    ]
},
  "bbox": [],
  "geometry": {"coordinates":[-110.7167,46.9167],"type":"Point"}
}