{
  "id": 7583412,
  "type": "Feature",
  "properties": {
    "tgn:hierarchy":[
        "tgn:7583412",
        "tgn:1000004",
        "tgn:7000198",
        "tgn:1001894",
        "tgn:7029392"
    ],
    "tgn:id":7583412,
    "tgn:name:en":"Chh\u0101par",
    "tgn:placetype":[
        "aat:300008347"
    ]
},
  "bbox": [],
  "geometry": {"coordinates":[78.807439,25.226173],"type":"Point"}
}