{
  "id": 7342566,
  "type": "Feature",
  "properties": {
    "tgn:hierarchy":[
        "tgn:7342566",
        "tgn:7008911",
        "tgn:1000003",
        "tgn:7002763",
        "tgn:1000095",
        "tgn:7029392"
    ],
    "tgn:id":7342566,
    "tgn:name":"Casta\u00f1edo",
    "tgn:placetype":[
        "aat:300008347"
    ]
},
  "bbox": [],
  "geometry": {"coordinates":[-6.233333,43.366667],"type":"Point"}
}