{
  "id": 7551979,
  "type": "Feature",
  "properties": {
    "tgn:hierarchy":[
        "tgn:7551979",
        "tgn:1000004",
        "tgn:7000198",
        "tgn:7016788",
        "tgn:7029392"
    ],
    "tgn:id":7551979,
    "tgn:name:en":"Delm\u0101ra",
    "tgn:placetype":[
        "aat:300008347"
    ]
},
  "bbox": [],
  "geometry": {"coordinates":[72.72306,24.60835],"type":"Point"}
}