<<<<<<< HEAD
{
  "id": 7024514,
  "type": "Feature",
  "properties": {
    "tgn:hierarchy":[
        "tgn:7024514",
        "tgn:7593552",
        "tgn:1000001",
        "tgn:7024573",
        "tgn:7029392"
    ],
    "tgn:id":7024514,
    "tgn:name":"Qeqertaq",
    "tgn:placetype":[
        "aat:300008791"
    ]
},
  "bbox": [],
  "geometry": {"coordinates":[-56.4667,73.3],"type":"Point"}
}
=======
{"geometry":{"type":"Point","coordinates":[-56.466700,73.300000]},"type":"Feature","properties":{"hierarchy":["tgn:7024514","tgn:7593552","tgn:1000001","tgn:7024573","tgn:7029392"],"placetype":["aat:300008791"],"id":7024514,"name:xx":"Qeqertaq"}}
>>>>>>> 03f74aca74312dbeaf24d7e61306dd6a786dc3d0
