{
  "id": 7280862,
  "type": "Feature",
  "properties": {
    "tgn:hierarchy":[
        "tgn:7280862",
        "tgn:1001768",
        "tgn:1000049",
        "tgn:1000002",
        "tgn:7029392"
    ],
    "tgn:id":7280862,
    "tgn:name":"Santa Julia",
    "tgn:placetype":[
        "aat:300387200"
    ]
},
  "bbox": [],
  "geometry": {"coordinates":[-70.933333,-32.816667],"type":"Point"}
}