{
  "id": 7337559,
  "type": "Feature",
  "properties": {
    "tgn:hierarchy":[
        "tgn:7337559",
        "tgn:7002836",
        "tgn:7016622",
        "tgn:1000003",
        "tgn:1000095",
        "tgn:7029392"
    ],
    "tgn:id":7337559,
    "tgn:name":"Chiguel, Roque",
    "tgn:placetype":[
        "aat:300011692"
    ]
},
  "bbox": [],
  "geometry": {"coordinates":[-16.216667,28.533333],"type":"Point"}
}