{
  "id": 7571204,
  "type": "Feature",
  "properties": {
    "tgn:hierarchy":[
        "tgn:7571204",
        "tgn:1000004",
        "tgn:7000198",
        "tgn:7031786",
        "tgn:7029392"
    ],
    "tgn:id":7571204,
    "tgn:name:en":"Harmal",
    "tgn:placetype":[
        "aat:300008347"
    ]
},
  "bbox": [],
  "geometry": {"coordinates":[79.791707,30.056579],"type":"Point"}
}