<<<<<<< HEAD
{
  "id": 7025739,
  "type": "Feature",
  "properties": {
    "tgn:hierarchy":[
        "tgn:7025739",
        "tgn:7002445",
        "tgn:1000003",
        "tgn:7012077",
        "tgn:7008591",
        "tgn:7029392"
    ],
    "tgn:id":7025739,
    "tgn:name:en":"Staverton",
    "tgn:placetype":[
        "aat:300008347"
    ]
},
  "bbox": [],
  "geometry": {"coordinates":[-3.7,50.466667],"type":"Point"}
}
=======
{"geometry":{"type":"Point","coordinates":[-3.700000,50.466667]},"type":"Feature","properties":{"hierarchy":["tgn:7025739","tgn:7002445","tgn:1000003","tgn:7012077","tgn:7008591","tgn:7029392"],"placetype":["aat:300008347"],"name:en":"Staverton","id":7025739}}
>>>>>>> 03f74aca74312dbeaf24d7e61306dd6a786dc3d0
