<<<<<<< HEAD
{
  "id": 7356195,
  "type": "Feature",
  "properties": {
    "tgn:hierarchy":[
        "tgn:7356195",
        "tgn:7005581",
        "tgn:1000001",
        "tgn:7005560",
        "tgn:7029392"
    ],
    "tgn:id":7356195,
    "tgn:name":"Carichic",
    "tgn:placetype":[
        "aat:300008347"
    ]
},
  "bbox": [],
  "geometry": {"coordinates":[-107.0,28.066667],"type":"Point"}
}
=======
{"geometry":{"type":"Point","coordinates":[-107.000000,28.066667]},"type":"Feature","properties":{"hierarchy":["tgn:7356195","tgn:7005581","tgn:1000001","tgn:7005560","tgn:7029392"],"placetype":["aat:300008347"],"id":7356195,"name:xx":"Carichic"}}
>>>>>>> 03f74aca74312dbeaf24d7e61306dd6a786dc3d0
