{
  "id": 7506675,
  "type": "Feature",
  "properties": {
    "tgn:hierarchy":[
        "tgn:7506675",
        "tgn:1009227",
        "tgn:7001866",
        "tgn:1000226",
        "tgn:1000006",
        "tgn:7029392"
    ],
    "tgn:id":7506675,
    "tgn:name:en":"Richmond",
    "tgn:placetype":[
        "aat:300000206"
    ]
},
  "bbox": [],
  "geometry": {"coordinates":[170.55,-43.883333],"type":"Point"}
}