{
  "id": 2342184,
  "type": "Feature",
  "properties": {
    "tgn:hierarchy":[
        "tgn:2342184",
        "tgn:1000001",
        "tgn:7012149",
        "tgn:2002169",
        "tgn:7007919",
        "tgn:7029392"
    ],
    "tgn:id":2342184,
    "tgn:name":"Fugate Cave",
    "tgn:placetype":[
        "aat:300008746"
    ]
},
  "bbox": [],
  "geometry": {"coordinates":[-83.05,36.65],"type":"Point"}
}