{
  "id": 7486663,
  "type": "Feature",
  "properties": {
    "tgn:hierarchy":[
        "tgn:7486663",
        "tgn:1000004",
        "tgn:1000959",
        "tgn:1000141",
        "tgn:7029392"
    ],
    "tgn:id":7486663,
    "tgn:name":"Baxian Li",
    "tgn:placetype":[
        "aat:300387173"
    ]
},
  "bbox": [],
  "geometry": {"coordinates":[121.481768,25.117623],"type":"Point"}
}