<<<<<<< HEAD
{
  "id": 7486663,
  "type": "Feature",
  "properties": {
    "tgn:hierarchy":[
        "tgn:7486663",
        "tgn:1000004",
        "tgn:1000959",
        "tgn:1000141",
        "tgn:7029392"
    ],
    "tgn:id":7486663,
    "tgn:name":"Baxian Li",
    "tgn:placetype":[
        "aat:300387173"
    ]
},
  "bbox": [],
  "geometry": {"coordinates":[121.481768,25.117623],"type":"Point"}
}
=======
{"geometry":{"type":"Point","coordinates":[121.481768,25.117623]},"type":"Feature","properties":{"hierarchy":["tgn:7486663","tgn:1000004","tgn:1000959","tgn:1000141","tgn:7029392"],"placetype":["aat:300387173"],"id":7486663,"name:xx":"Baxian Li"}}
>>>>>>> 03f74aca74312dbeaf24d7e61306dd6a786dc3d0
