{
  "id": 2538566,
  "type": "Feature",
  "properties": {
    "tgn:hierarchy":[
        "tgn:2538566",
        "tgn:1000001",
        "tgn:7012149",
        "tgn:2000959",
        "tgn:7007520",
        "tgn:7029392"
    ],
    "tgn:id":2538566,
    "tgn:name":"Nestor Drain",
    "tgn:placetype":[
        "aat:300006075"
    ]
},
  "bbox": [],
  "geometry": {"coordinates":[-84.4333,43.8167],"type":"Point"}
}