{
  "id": 7226121,
  "type": "Feature",
  "properties": {
    "tgn:hierarchy":[
        "tgn:7226121",
        "tgn:7002724",
        "tgn:7002715",
        "tgn:1000003",
        "tgn:1000074",
        "tgn:7029392"
    ],
    "tgn:id":7226121,
    "tgn:name":"Souvasl\u00e1",
    "tgn:placetype":[
        "aat:300266640"
    ]
},
  "bbox": [],
  "geometry": {"coordinates":[21.216667,40.833333],"type":"Point"}
}