{
  "id": 2280911,
  "type": "Feature",
  "properties": {
    "tgn:hierarchy":[
        "tgn:2280911",
        "tgn:1000001",
        "tgn:7012149",
        "tgn:2002379",
        "tgn:7007923",
        "tgn:7029392"
    ],
    "tgn:id":2280911,
    "tgn:name":"Deep Creek",
    "tgn:placetype":[
        "aat:300008706"
    ]
},
  "bbox": [],
  "geometry": {"coordinates":[-109.3833,44.9167],"type":"Point"}
}