{
  "id": 2129871,
  "type": "Feature",
  "properties": {
    "tgn:hierarchy":[
        "tgn:2129871",
        "tgn:1000001",
        "tgn:7012149",
        "tgn:2001854",
        "tgn:7007825",
        "tgn:7029392"
    ],
    "tgn:id":2129871,
    "tgn:name":"Allen Branch",
    "tgn:placetype":[
        "aat:300008699"
    ]
},
  "bbox": [],
  "geometry": {"coordinates":[-84.9167,36.1167],"type":"Point"}
}