{
  "id": 7583439,
  "type": "Feature",
  "properties": {
    "tgn:hierarchy":[
        "tgn:7583439",
        "tgn:1000004",
        "tgn:7000198",
        "tgn:1001894",
        "tgn:7029392"
    ],
    "tgn:id":7583439,
    "tgn:name:en":"Katera Reserved Forest",
    "tgn:placetype":[
        "aat:300008865"
    ]
},
  "bbox": [],
  "geometry": {"coordinates":[78.952107,25.241251],"type":"Point"}
}