{
  "id": 7584461,
  "type": "Feature",
  "properties": {
    "tgn:hierarchy":[
        "tgn:7584461",
        "tgn:1000004",
        "tgn:7000198",
        "tgn:7016788",
        "tgn:7029392"
    ],
    "tgn:id":7584461,
    "tgn:name:en":"P\u012bpal ka B\u0101s",
    "tgn:placetype":[
        "aat:300008347"
    ]
},
  "bbox": [],
  "geometry": {"coordinates":[75.360459,28.221415],"type":"Point"}
}