{
  "id": 7214289,
  "type": "Feature",
  "properties": {
    "tgn:hierarchy":[
        "tgn:7214289",
        "tgn:1000003",
        "tgn:7003676",
        "tgn:7000084",
        "tgn:7029392"
    ],
    "tgn:id":7214289,
    "tgn:name":"B\u00f6kenfeld",
    "tgn:placetype":[
        "aat:300000206"
    ]
},
  "bbox": [],
  "geometry": {"coordinates":[7.55,52.733333],"type":"Point"}
}