{
  "id": 2633305,
  "type": "Feature",
  "properties": {
    "tgn:hierarchy":[
        "tgn:2633305",
        "tgn:1000001",
        "tgn:7012149",
        "tgn:2000996",
        "tgn:7007520",
        "tgn:7029392"
    ],
    "tgn:id":2633305,
    "tgn:name":"Rumble Lake",
    "tgn:placetype":[
        "aat:300008680"
    ]
},
  "bbox": [],
  "geometry": {"coordinates":[-86.55,46.1833],"type":"Point"}
}