{
  "id": 2293149,
  "type": "Feature",
  "properties": {
    "tgn:hierarchy":[
        "tgn:2293149",
        "tgn:7002659",
        "tgn:1000001",
        "tgn:7012149",
        "tgn:2000029",
        "tgn:7029392"
    ],
    "tgn:id":2293149,
    "tgn:name":"Double Barrell Cave",
    "tgn:placetype":[
        "aat:300008746"
    ]
},
  "bbox": [],
  "geometry": {"coordinates":[-87.7833,34.45],"type":"Point"}
}