{
  "id": 7298111,
  "type": "Feature",
  "properties": {
    "tgn:hierarchy":[
        "tgn:7298111",
        "tgn:7008911",
        "tgn:1000003",
        "tgn:7002763",
        "tgn:1000095",
        "tgn:7029392"
    ],
    "tgn:id":7298111,
    "tgn:name":"Sietes",
    "tgn:placetype":[
        "aat:300008347"
    ]
},
  "bbox": [],
  "geometry": {"coordinates":[-5.366667,43.433333],"type":"Point"}
}