{
  "id": 2558224,
  "type": "Feature",
  "properties": {
    "tgn:hierarchy":[
        "tgn:2558224",
        "tgn:1000001",
        "tgn:2000311",
        "tgn:7012149",
        "tgn:7007248",
        "tgn:7029392"
    ],
    "tgn:id":2558224,
    "tgn:name":"Oldhouse Creek",
    "tgn:placetype":[
        "aat:300008706"
    ]
},
  "bbox": [],
  "geometry": {"coordinates":[-81.4667,30.7833],"type":"Point"}
}