{
  "id": 2435059,
  "type": "Feature",
  "properties": {
    "tgn:hierarchy":[
        "tgn:2435059",
        "tgn:2002101",
        "tgn:1000001",
        "tgn:7012149",
        "tgn:7007827",
        "tgn:7029392"
    ],
    "tgn:id":2435059,
    "tgn:name":"Kents Lake Number One",
    "tgn:placetype":[
        "aat:300006191"
    ]
},
  "bbox": [],
  "geometry": {"coordinates":[-112.45,38.2167],"type":"Point"}
}