<<<<<<< HEAD
{
  "id": 7486107,
  "type": "Feature",
  "properties": {
    "tgn:hierarchy":[
        "tgn:7486107",
        "tgn:7001010",
        "tgn:1000004",
        "tgn:1000141",
        "tgn:7029392"
    ],
    "tgn:id":7486107,
    "tgn:name":"Tianxiang Suidao",
    "tgn:placetype":[
        "aat:300007899"
    ]
},
  "bbox": [],
  "geometry": {"coordinates":[121.498889,24.181111],"type":"Point"}
}
=======
{"geometry":{"type":"Point","coordinates":[121.498889,24.181111]},"type":"Feature","properties":{"hierarchy":["tgn:7486107","tgn:7001010","tgn:1000004","tgn:1000141","tgn:7029392"],"placetype":["aat:300007899"],"id":7486107,"name:xx":"Tianxiang Suidao"}}
>>>>>>> 03f74aca74312dbeaf24d7e61306dd6a786dc3d0
