{
  "id": 2290439,
  "type": "Feature",
  "properties": {
    "tgn:hierarchy":[
        "tgn:2290439",
        "tgn:1000001",
        "tgn:7012149",
        "tgn:7007252",
        "tgn:7029392"
    ],
    "tgn:id":2290439,
    "tgn:name":"Doe Creek",
    "tgn:placetype":[
        "aat:300008706"
    ]
},
  "bbox": [],
  "geometry": {"coordinates":[-85.8833,39.7667],"type":"Point"}
}