<<<<<<< HEAD
{
  "id": 7241219,
  "type": "Feature",
  "properties": {
    "tgn:hierarchy":[
        "tgn:7241219",
        "tgn:7003457",
        "tgn:1000003",
        "tgn:1000063",
        "tgn:7018236",
        "tgn:7029392"
    ],
    "tgn:id":7241219,
    "tgn:name":"Leuvenstraat",
    "tgn:placetype":[
        "aat:300008347"
    ]
},
  "bbox": [],
  "geometry": {"coordinates":[4.066667,50.916667],"type":"Point"}
}
=======
{"geometry":{"type":"Point","coordinates":[4.066667,50.916667]},"type":"Feature","properties":{"hierarchy":["tgn:7241219","tgn:7003457","tgn:1000003","tgn:1000063","tgn:7018236","tgn:7029392"],"placetype":["aat:300008347"],"id":7241219,"name:xx":"Leuvenstraat"}}
>>>>>>> 03f74aca74312dbeaf24d7e61306dd6a786dc3d0
