{
  "id": 2107518,
  "type": "Feature",
  "properties": {
    "tgn:hierarchy":[
        "tgn:2107518",
        "tgn:1000001",
        "tgn:1002168",
        "tgn:7012149",
        "tgn:7007826",
        "tgn:7029392"
    ],
    "tgn:id":2107518,
    "tgn:name":"Sayersville",
    "tgn:placetype":[
        "aat:300008347"
    ]
},
  "bbox": [],
  "geometry": {"coordinates":[-97.3167,30.2167],"type":"Point"}
}