{
  "id": 7590923,
  "type": "Feature",
  "properties": {
    "tgn:hierarchy":[
        "tgn:7590923",
        "tgn:1000004",
        "tgn:7000198",
        "tgn:7000799",
        "tgn:7029392"
    ],
    "tgn:id":7590923,
    "tgn:name:en":"Q\u0101dirpur",
    "tgn:placetype":[
        "aat:300008347"
    ]
},
  "bbox": [],
  "geometry": {"coordinates":[74.77842,32.550141],"type":"Point"}
}