{
  "id": 2615426,
  "type": "Feature",
  "properties": {
    "tgn:hierarchy":[
        "tgn:2615426",
        "tgn:1000001",
        "tgn:7012149",
        "tgn:2001510",
        "tgn:7007709",
        "tgn:7029392"
    ],
    "tgn:id":2615426,
    "tgn:name":"Resolution Branch",
    "tgn:placetype":[
        "aat:300008699"
    ]
},
  "bbox": [],
  "geometry": {"coordinates":[-77.35,35.1167],"type":"Point"}
}