{
  "id": 7175846,
  "type": "Feature",
  "properties": {
    "tgn:hierarchy":[
        "tgn:7175846",
        "tgn:1000003",
        "tgn:7000094",
        "tgn:7000084",
        "tgn:7029392"
    ],
    "tgn:id":7175846,
    "tgn:name":"Gro\u00df Volksitz",
    "tgn:placetype":[
        "aat:300008347"
    ]
},
  "bbox": [],
  "geometry": {"coordinates":[13.583333,54.533333],"type":"Point"}
}