{
  "id": 2779370,
  "type": "Feature",
  "properties": {
    "tgn:hierarchy":[
        "tgn:2779370",
        "tgn:1000001",
        "tgn:7012149",
        "tgn:1002872",
        "tgn:7007568",
        "tgn:7029392"
    ],
    "tgn:id":2779370,
    "tgn:name":"Wolf Hollow",
    "tgn:placetype":[
        "aat:300008761"
    ]
},
  "bbox": [],
  "geometry": {"coordinates":[-74.0667,42.9167],"type":"Point"}
}