{
  "id": 7335203,
  "type": "Feature",
  "properties": {
    "tgn:hierarchy":[
        "tgn:7335203",
        "tgn:7002805",
        "tgn:7002758",
        "tgn:1000003",
        "tgn:1000095",
        "tgn:7029392"
    ],
    "tgn:id":7335203,
    "tgn:name":"Filabres, Sierra de los",
    "tgn:placetype":[
        "aat:300008795"
    ]
},
  "bbox": [],
  "geometry": {"coordinates":[-2.333333,37.216667],"type":"Point"}
}