<<<<<<< HEAD
{
  "id": 2252263,
  "type": "Feature",
  "properties": {
    "tgn:hierarchy":[
        "tgn:2252263",
        "tgn:1000001",
        "tgn:7012149",
        "tgn:7016021",
        "tgn:7007568",
        "tgn:7029392"
    ],
    "tgn:id":2252263,
    "tgn:name":"Coney Island",
    "tgn:placetype":[
        "aat:300008347"
    ]
},
  "bbox": [],
  "geometry": {"coordinates":[-74.9667,44.6],"type":"Point"}
}
=======
{"geometry":{"type":"Point","coordinates":[-74.966700,44.600000]},"type":"Feature","properties":{"hierarchy":["tgn:2252263","tgn:1000001","tgn:7012149","tgn:7016021","tgn:7007568","tgn:7029392"],"placetype":["aat:300008347"],"id":2252263,"name:xx":"Coney Island"}}
>>>>>>> 03f74aca74312dbeaf24d7e61306dd6a786dc3d0
