{
  "id": 2584994,
  "type": "Feature",
  "properties": {
    "tgn:hierarchy":[
        "tgn:2584994",
        "tgn:1000001",
        "tgn:7012149",
        "tgn:2000183",
        "tgn:7007157",
        "tgn:7029392"
    ],
    "tgn:id":2584994,
    "tgn:name":"Pinnacle Mine",
    "tgn:placetype":[
        "aat:300000390"
    ]
},
  "bbox": [],
  "geometry": {"coordinates":[-118.35,36.9333],"type":"Point"}
}