{
  "id": 2392794,
  "type": "Feature",
  "properties": {
    "tgn:hierarchy":[
        "tgn:2392794",
        "tgn:1000001",
        "tgn:2000924",
        "tgn:7012149",
        "tgn:7007515",
        "tgn:7029392"
    ],
    "tgn:id":2392794,
    "tgn:name":"Hobbs Pond",
    "tgn:placetype":[
        "aat:300008680"
    ]
},
  "bbox": [],
  "geometry": {"coordinates":[-69.1667,44.2333],"type":"Point"}
}