<<<<<<< HEAD
{
  "id": 7023302,
  "type": "Feature",
  "properties": {
    "tgn:hierarchy":[
        "tgn:7023302",
        "tgn:1000001",
        "tgn:7012149",
        "tgn:7007158",
        "tgn:7029392"
    ],
    "tgn:id":7023302,
    "tgn:name":"Long Draw Reservoir",
    "tgn:placetype":[
        "aat:300006191"
    ]
},
  "bbox": [],
  "geometry": {"coordinates":[-108.3,37.6167],"type":"Point"}
}
=======
{"geometry":{"type":"Point","coordinates":[-108.300000,37.616700]},"type":"Feature","properties":{"hierarchy":["tgn:7023302","tgn:1000001","tgn:7012149","tgn:7007158","tgn:7029392"],"placetype":["aat:300006191"],"id":7023302,"name:xx":"Long Draw Reservoir"}}
>>>>>>> 03f74aca74312dbeaf24d7e61306dd6a786dc3d0
