{
  "id": 2287163,
  "type": "Feature",
  "properties": {
    "tgn:hierarchy":[
        "tgn:2287163",
        "tgn:1000001",
        "tgn:7012149",
        "tgn:2002387",
        "tgn:7007923",
        "tgn:7029392"
    ],
    "tgn:id":2287163,
    "tgn:name":"Dickey Draw",
    "tgn:placetype":[
        "aat:300008761"
    ]
},
  "bbox": [],
  "geometry": {"coordinates":[-104.8833,44.0167],"type":"Point"}
}