{
  "id": 2750274,
  "type": "Feature",
  "properties": {
    "tgn:hierarchy":[
        "tgn:2750274",
        "tgn:1000001",
        "tgn:2001734",
        "tgn:7012149",
        "tgn:7007712",
        "tgn:7029392"
    ],
    "tgn:id":2750274,
    "tgn:name":"Wambaw Corner",
    "tgn:placetype":[
        "aat:300008347"
    ]
},
  "bbox": [],
  "geometry": {"coordinates":[-79.45,33.1833],"type":"Point"}
}