{
  "id": 7062174,
  "type": "Feature",
  "properties": {
    "tgn:hierarchy":[
        "tgn:7062174",
        "tgn:7003669",
        "tgn:1000003",
        "tgn:7000084",
        "tgn:7029392"
    ],
    "tgn:id":7062174,
    "tgn:name":"Bachappen",
    "tgn:placetype":[
        "aat:300008347"
    ]
},
  "bbox": [],
  "geometry": {"coordinates":[11.516667,48.566667],"type":"Point"}
}