{
  "id": 2543511,
  "type": "Feature",
  "properties": {
    "tgn:hierarchy":[
        "tgn:2543511",
        "tgn:1000001",
        "tgn:7012149",
        "tgn:2001908",
        "tgn:7007825",
        "tgn:7029392"
    ],
    "tgn:id":2543511,
    "tgn:name":"Norris Number One Mine",
    "tgn:placetype":[
        "aat:300000390"
    ]
},
  "bbox": [],
  "geometry": {"coordinates":[-84.9333,35.6667],"type":"Point"}
}