{
  "id": 2001391,
  "type": "Feature",
  "properties": {
    "tgn:hierarchy":[
        "tgn:2001391",
        "tgn:1000001",
        "tgn:7012149",
        "tgn:7007525",
        "tgn:7029392"
    ],
    "tgn:id":2001391,
    "tgn:name":"Saline",
    "tgn:placetype":[
        "aat:300387145",
        "aat:300000771"
    ]
},
  "bbox": [],
  "geometry": {"coordinates":[-97.15,40.5333],"type":"Point"}
}