{
  "id": 7458683,
  "type": "Feature",
  "properties": {
    "tgn:hierarchy":[
        "tgn:7458683",
        "tgn:7019094",
        "tgn:7002444",
        "tgn:1000003",
        "tgn:7008591",
        "tgn:7029392"
    ],
    "tgn:id":7458683,
    "tgn:name:en":"Lussa, Glen",
    "tgn:placetype":[
        "aat:300008761"
    ]
},
  "bbox": [],
  "geometry": {"coordinates":[-5.533333,55.466667],"type":"Point"}
}