{
  "id": 2677298,
  "type": "Feature",
  "properties": {
    "tgn:hierarchy":[
        "tgn:2677298",
        "tgn:1000001",
        "tgn:7012149",
        "tgn:2002123",
        "tgn:7007827",
        "tgn:7029392"
    ],
    "tgn:id":2677298,
    "tgn:name":"South Broons Canyon",
    "tgn:placetype":[
        "aat:300008761"
    ]
},
  "bbox": [],
  "geometry": {"coordinates":[-112.6167,40.5833],"type":"Point"}
}