{
  "id": 7557586,
  "type": "Feature",
  "properties": {
    "tgn:hierarchy":[
        "tgn:7557586",
        "tgn:1000004",
        "tgn:7000198",
        "tgn:1001977",
        "tgn:7029392"
    ],
    "tgn:id":7557586,
    "tgn:name:en":"P\u0101rok\u0101ta",
    "tgn:placetype":[
        "aat:300008347"
    ]
},
  "bbox": [],
  "geometry": {"coordinates":[89.716667,26.45],"type":"Point"}
}