{
  "id": 7409188,
  "type": "Feature",
  "properties": {
    "tgn:hierarchy":[
        "tgn:7409188",
        "tgn:1000001",
        "tgn:1001893",
        "tgn:7005560",
        "tgn:7029392"
    ],
    "tgn:id":7409188,
    "tgn:name":"Guadalupe Amanalco",
    "tgn:placetype":[
        "aat:300008347"
    ]
},
  "bbox": [],
  "geometry": {"coordinates":[-98.716667,19.516667],"type":"Point"}
}