{
  "id": 2507730,
  "type": "Feature",
  "properties": {
    "tgn:hierarchy":[
        "tgn:2507730",
        "tgn:1002137",
        "tgn:1000001",
        "tgn:7012149",
        "tgn:7007710",
        "tgn:7029392"
    ],
    "tgn:id":2507730,
    "tgn:name":"Michaux State Forest",
    "tgn:placetype":[
        "aat:300008863"
    ]
},
  "bbox": [],
  "geometry": {"coordinates":[-77.35,39.9833],"type":"Point"}
}