{
  "id": 2380601,
  "type": "Feature",
  "properties": {
    "tgn:hierarchy":[
        "tgn:2380601",
        "tgn:1000001",
        "tgn:7012149",
        "tgn:2001492",
        "tgn:7007709",
        "tgn:7029392"
    ],
    "tgn:id":2380601,
    "tgn:name":"Havenhill",
    "tgn:placetype":[
        "aat:300008347"
    ]
},
  "bbox": [],
  "geometry": {"coordinates":[-78.95,36.0667],"type":"Point"}
}