<<<<<<< HEAD
{
  "id": 7487476,
  "type": "Feature",
  "properties": {
    "tgn:hierarchy":[
        "tgn:7487476",
        "tgn:7001004",
        "tgn:1000004",
        "tgn:1000141",
        "tgn:7029392"
    ],
    "tgn:id":7487476,
    "tgn:name":"Musheng Xi",
    "tgn:placetype":[
        "aat:300008699"
    ]
},
  "bbox": [],
  "geometry": {"coordinates":[120.673544,22.890859],"type":"Point"}
}
=======
{"geometry":{"type":"Point","coordinates":[120.673544,22.890859]},"type":"Feature","properties":{"hierarchy":["tgn:7487476","tgn:7001004","tgn:1000004","tgn:1000141","tgn:7029392"],"placetype":["aat:300008699"],"id":7487476,"name:xx":"Musheng Xi"}}
>>>>>>> 03f74aca74312dbeaf24d7e61306dd6a786dc3d0
