{
  "id": 2671047,
  "type": "Feature",
  "properties": {
    "tgn:hierarchy":[
        "tgn:2671047",
        "tgn:1000001",
        "tgn:7012149",
        "tgn:2001125",
        "tgn:7007522",
        "tgn:7029392"
    ],
    "tgn:id":2671047,
    "tgn:name":"Smith Creek",
    "tgn:placetype":[
        "aat:300008706"
    ]
},
  "bbox": [],
  "geometry": {"coordinates":[-89.5833,32.8667],"type":"Point"}
}