{
  "id": 7402414,
  "type": "Feature",
  "properties": {
    "tgn:hierarchy":[
        "tgn:7402414",
        "tgn:1000001",
        "tgn:1001937",
        "tgn:7005560",
        "tgn:7029392"
    ],
    "tgn:id":7402414,
    "tgn:name":"Cedralito",
    "tgn:placetype":[
        "aat:300008347"
    ]
},
  "bbox": [],
  "geometry": {"coordinates":[-88.733333,18.941667],"type":"Point"}
}