{
  "id": 2769038,
  "type": "Feature",
  "properties": {
    "tgn:hierarchy":[
        "tgn:2769038",
        "tgn:1000001",
        "tgn:1002480",
        "tgn:7012149",
        "tgn:7007564",
        "tgn:7029392"
    ],
    "tgn:id":2769038,
    "tgn:name":"Whittemore Hill",
    "tgn:placetype":[
        "aat:300008798"
    ]
},
  "bbox": [],
  "geometry": {"coordinates":[-71.8333,42.7167],"type":"Point"}
}