<<<<<<< HEAD
{
  "id": 2405013,
  "type": "Feature",
  "properties": {
    "tgn:hierarchy":[
        "tgn:2405013",
        "tgn:1000001",
        "tgn:7012149",
        "tgn:2000973",
        "tgn:7007520",
        "tgn:7029392"
    ],
    "tgn:id":2405013,
    "tgn:name":"Hudson Creek",
    "tgn:placetype":[
        "aat:300008706"
    ]
},
  "bbox": [],
  "geometry": {"coordinates":[-85.7333,45.9833],"type":"Point"}
}
=======
{"geometry":{"type":"Point","coordinates":[-85.733300,45.983300]},"type":"Feature","properties":{"hierarchy":["tgn:2405013","tgn:1000001","tgn:7012149","tgn:2000973","tgn:7007520","tgn:7029392"],"placetype":["aat:300008706"],"id":2405013,"name:xx":"Hudson Creek"}}
>>>>>>> 03f74aca74312dbeaf24d7e61306dd6a786dc3d0
