{
  "id": 7152827,
  "type": "Feature",
  "properties": {
    "tgn:hierarchy":[
        "tgn:7152827",
        "tgn:1000003",
        "tgn:7003689",
        "tgn:7000084",
        "tgn:7029392"
    ],
    "tgn:id":7152827,
    "tgn:name":"Junker Bach",
    "tgn:placetype":[
        "aat:300008699"
    ]
},
  "bbox": [],
  "geometry": {"coordinates":[11.083333,50.616667],"type":"Point"}
}