{
  "id": 2606794,
  "type": "Feature",
  "properties": {
    "tgn:hierarchy":[
        "tgn:2606794",
        "tgn:1000001",
        "tgn:7012149",
        "tgn:2000229",
        "tgn:7007158",
        "tgn:7029392"
    ],
    "tgn:id":2606794,
    "tgn:name":"Ramsey Draw",
    "tgn:placetype":[
        "aat:300008761"
    ]
},
  "bbox": [],
  "geometry": {"coordinates":[-102.9167,40.8833],"type":"Point"}
}