{
  "id": 7506074,
  "type": "Feature",
  "properties": {
    "tgn:hierarchy":[
        "tgn:7506074",
        "tgn:1009227",
        "tgn:1000226",
        "tgn:7016822",
        "tgn:1000006",
        "tgn:7029392"
    ],
    "tgn:id":7506074,
    "tgn:name:en":"Second Cove",
    "tgn:placetype":[
        "aat:300132317"
    ]
},
  "bbox": [],
  "geometry": {"coordinates":[166.816667,-45.55],"type":"Point"}
}