{
  "id": 2383711,
  "type": "Feature",
  "properties": {
    "tgn:hierarchy":[
        "tgn:2383711",
        "tgn:1000001",
        "tgn:7012149",
        "tgn:2001275",
        "tgn:7007524",
        "tgn:7029392"
    ],
    "tgn:id":2383711,
    "tgn:name":"Hebgen Lake",
    "tgn:placetype":[
        "aat:300006191"
    ]
},
  "bbox": [],
  "geometry": {"coordinates":[-111.3333,44.85],"type":"Point"}
}