{
  "id": 1136676,
  "type": "Feature",
  "properties": {
    "tgn:hierarchy":[
        "tgn:1136676",
        "tgn:7002445",
        "tgn:1000003",
        "tgn:7008166",
        "tgn:7008591",
        "tgn:7029392"
    ],
    "tgn:id":1136676,
    "tgn:name:en":"Buckden",
    "tgn:placetype":[
        "aat:300008347"
    ]
},
  "bbox": [],
  "geometry": {"coordinates":[-2.083333,54.183333],"type":"Point"}
}