{
  "id": 7321493,
  "type": "Feature",
  "properties": {
    "tgn:hierarchy":[
        "tgn:7321493",
        "tgn:1001692",
        "tgn:1000049",
        "tgn:1000002",
        "tgn:7029392"
    ],
    "tgn:id":7321493,
    "tgn:name":"Budi, Estero",
    "tgn:placetype":[
        "aat:300008699"
    ]
},
  "bbox": [],
  "geometry": {"coordinates":[-73.283333,-38.933333],"type":"Point"}
}