{
  "id": 7505913,
  "type": "Feature",
  "properties": {
    "tgn:hierarchy":[
        "tgn:7505913",
        "tgn:1008380",
        "tgn:1000226",
        "tgn:7018426",
        "tgn:1000006",
        "tgn:7029392"
    ],
    "tgn:id":7505913,
    "tgn:name:en":"Tapirimoko Point",
    "tgn:placetype":[
        "aat:300386846"
    ]
},
  "bbox": [],
  "geometry": {"coordinates":[174.666667,-38.366667],"type":"Point"}
}