{
  "id": 2148907,
  "type": "Feature",
  "properties": {
    "tgn:hierarchy":[
        "tgn:2148907",
        "tgn:1000001",
        "tgn:7012149",
        "tgn:7013855",
        "tgn:7007251",
        "tgn:7029392"
    ],
    "tgn:id":2148907,
    "tgn:name":"Barney Island",
    "tgn:placetype":[
        "aat:300008791"
    ]
},
  "bbox": [],
  "geometry": {"coordinates":[-88.15,42.4333],"type":"Point"}
}