{
  "id": 7051300,
  "type": "Feature",
  "properties": {
    "tgn:hierarchy":[
        "tgn:7051300",
        "tgn:1003432",
        "tgn:1000003",
        "tgn:7003240",
        "tgn:1000080",
        "tgn:7029392"
    ],
    "tgn:id":7051300,
    "tgn:name":"Marino",
    "tgn:placetype":[
        "aat:300008347"
    ]
},
  "bbox": [],
  "geometry": {"coordinates":[13.65,42.833333],"type":"Point"}
}