{
  "id": 7251053,
  "type": "Feature",
  "properties": {
    "tgn:hierarchy":[
        "tgn:7251053",
        "tgn:7003457",
        "tgn:1000003",
        "tgn:1000063",
        "tgn:7018236",
        "tgn:7029392"
    ],
    "tgn:id":7251053,
    "tgn:name":"Oosthoek",
    "tgn:placetype":[
        "aat:300008347"
    ]
},
  "bbox": [],
  "geometry": {"coordinates":[3.474753,51.242896],"type":"Point"}
}