{
  "id": 2033586,
  "type": "Feature",
  "properties": {
    "tgn:hierarchy":[
        "tgn:2033586",
        "tgn:1000001",
        "tgn:7012149",
        "tgn:2000558",
        "tgn:7007252",
        "tgn:7029392"
    ],
    "tgn:id":2033586,
    "tgn:name":"Sandytown",
    "tgn:placetype":[
        "aat:300008347"
    ]
},
  "bbox": [],
  "geometry": {"coordinates":[-87.4333,39.6667],"type":"Point"}
}