{
  "id": 2161444,
  "type": "Feature",
  "properties": {
    "tgn:hierarchy":[
        "tgn:2161444",
        "tgn:1000001",
        "tgn:7012149",
        "tgn:2000834",
        "tgn:7007255",
        "tgn:7029392"
    ],
    "tgn:id":2161444,
    "tgn:name":"Bell Run",
    "tgn:placetype":[
        "aat:300008699"
    ]
},
  "bbox": [],
  "geometry": {"coordinates":[-86.9333,37.5833],"type":"Point"}
}