{
  "id": 7285598,
  "type": "Feature",
  "properties": {
    "tgn:hierarchy":[
        "tgn:7285598",
        "tgn:7002464",
        "tgn:1000049",
        "tgn:1000002",
        "tgn:7029392"
    ],
    "tgn:id":7285598,
    "tgn:name":"Planta Azufrera",
    "tgn:placetype":[
        "aat:300004792"
    ]
},
  "bbox": [],
  "geometry": {"coordinates":[-68.483333,-20.633333],"type":"Point"}
}