{
  "id": 2463503,
  "type": "Feature",
  "properties": {
    "tgn:hierarchy":[
        "tgn:2463503",
        "tgn:1000001",
        "tgn:2001436",
        "tgn:7012149",
        "tgn:7007566",
        "tgn:7029392"
    ],
    "tgn:id":2463503,
    "tgn:name":"Loafer Tank",
    "tgn:placetype":[
        "aat:300006191"
    ]
},
  "bbox": [],
  "geometry": {"coordinates":[-104.6833,32.45],"type":"Point"}
}