<<<<<<< HEAD
{
  "id": 7059959,
  "type": "Feature",
  "properties": {
    "tgn:hierarchy":[
        "tgn:7059959",
        "tgn:1000003",
        "tgn:7003677",
        "tgn:7000084",
        "tgn:7029392"
    ],
    "tgn:id":7059959,
    "tgn:name":"Altenilpe",
    "tgn:placetype":[
        "aat:300008347"
    ]
},
  "bbox": [],
  "geometry": {"coordinates":[8.266667,51.216667],"type":"Point"}
}
=======
{"geometry":{"type":"Point","coordinates":[8.266667,51.216667]},"type":"Feature","properties":{"hierarchy":["tgn:7059959","tgn:1000003","tgn:7003677","tgn:7000084","tgn:7029392"],"placetype":["aat:300008347"],"id":7059959,"name:xx":"Altenilpe"}}
>>>>>>> 03f74aca74312dbeaf24d7e61306dd6a786dc3d0
