{
  "id": 2589627,
  "type": "Feature",
  "properties": {
    "tgn:hierarchy":[
        "tgn:2589627",
        "tgn:1002366",
        "tgn:1000001",
        "tgn:7012149",
        "tgn:7007159",
        "tgn:7029392"
    ],
    "tgn:id":2589627,
    "tgn:name":"Point No Point",
    "tgn:placetype":[
        "aat:300008850"
    ]
},
  "bbox": [],
  "geometry": {"coordinates":[-73.1167,41.1333],"type":"Point"}
}