{
  "id": 2135630,
  "type": "Feature",
  "properties": {
    "tgn:hierarchy":[
        "tgn:2135630",
        "tgn:1000001",
        "tgn:7006451",
        "tgn:2000093",
        "tgn:7012149",
        "tgn:7029392"
    ],
    "tgn:id":2135630,
    "tgn:name":"Apache Peaks",
    "tgn:placetype":[
        "aat:300008798"
    ]
},
  "bbox": [],
  "geometry": {"coordinates":[-110.7333,33.5333],"type":"Point"}
}