{
  "id": 2314415,
  "type": "Feature",
  "properties": {
    "tgn:hierarchy":[
        "tgn:2314415",
        "tgn:1000001",
        "tgn:7012149",
        "tgn:1002576",
        "tgn:7007520",
        "tgn:7029392"
    ],
    "tgn:id":2314415,
    "tgn:name":"Elk Lake",
    "tgn:placetype":[
        "aat:300008680"
    ]
},
  "bbox": [],
  "geometry": {"coordinates":[-83.15,43.0333],"type":"Point"}
}