{
  "id": 1079253,
  "type": "Feature",
  "properties": {
    "tgn:hierarchy":[
        "tgn:1079253",
        "tgn:1000004",
        "tgn:7002004",
        "tgn:7000231",
        "tgn:7029392"
    ],
    "tgn:id":1079253,
    "tgn:name":"Qolhak",
    "tgn:placetype":[
        "aat:300008347"
    ]
},
  "bbox": [],
  "geometry": {"coordinates":[51.4333,35.7667],"type":"Point"}
}