{
  "id": 7341286,
  "type": "Feature",
  "properties": {
    "tgn:hierarchy":[
        "tgn:7341286",
        "tgn:7008911",
        "tgn:1000003",
        "tgn:7002763",
        "tgn:1000095",
        "tgn:7029392"
    ],
    "tgn:id":7341286,
    "tgn:name":"Bra\u00f1anoveles",
    "tgn:placetype":[
        "aat:300008347"
    ]
},
  "bbox": [],
  "geometry": {"coordinates":[-5.75,43.25],"type":"Point"}
}