<<<<<<< HEAD
{
  "id": 2330361,
  "type": "Feature",
  "properties": {
    "tgn:hierarchy":[
        "tgn:2330361",
        "tgn:1000001",
        "tgn:7012149",
        "tgn:7007255",
        "tgn:7029392"
    ],
    "tgn:id":2330361,
    "tgn:name":"Flat Branch",
    "tgn:placetype":[
        "aat:300008699"
    ]
},
  "bbox": [],
  "geometry": {"coordinates":[-86.9333,37.5833],"type":"Point"}
}
=======
{"geometry":{"type":"Point","coordinates":[-86.933300,37.583300]},"type":"Feature","properties":{"hierarchy":["tgn:2330361","tgn:1000001","tgn:7012149","tgn:7007255","tgn:7029392"],"placetype":["aat:300008699"],"id":2330361,"name:xx":"Flat Branch"}}
>>>>>>> 03f74aca74312dbeaf24d7e61306dd6a786dc3d0
