<<<<<<< HEAD
{
  "id": 2254710,
  "type": "Feature",
  "properties": {
    "tgn:hierarchy":[
        "tgn:2254710",
        "tgn:1000001",
        "tgn:7012149",
        "tgn:1002631",
        "tgn:7007240",
        "tgn:7029392"
    ],
    "tgn:id":2254710,
    "tgn:name":"Coon Pond",
    "tgn:placetype":[
        "aat:300008680"
    ]
},
  "bbox": [],
  "geometry": {"coordinates":[-82.5,29.0833],"type":"Point"}
}
=======
{"geometry":{"type":"Point","coordinates":[-82.500000,29.083300]},"type":"Feature","properties":{"hierarchy":["tgn:2254710","tgn:1000001","tgn:7012149","tgn:1002631","tgn:7007240","tgn:7029392"],"placetype":["aat:300008680"],"id":2254710,"name:xx":"Coon Pond"}}
>>>>>>> 03f74aca74312dbeaf24d7e61306dd6a786dc3d0
