{
  "id": 2446118,
  "type": "Feature",
  "properties": {
    "tgn:hierarchy":[
        "tgn:2446118",
        "tgn:1000001",
        "tgn:7012149",
        "tgn:2000907",
        "tgn:7007256",
        "tgn:7029392"
    ],
    "tgn:id":2446118,
    "tgn:name":"Levi Lake",
    "tgn:placetype":[
        "aat:300008680"
    ]
},
  "bbox": [],
  "geometry": {"coordinates":[-91.3667,31.95],"type":"Point"}
}