{
  "id": 2371879,
  "type": "Feature",
  "properties": {
    "tgn:hierarchy":[
        "tgn:2371879",
        "tgn:1000001",
        "tgn:7012149",
        "tgn:2002374",
        "tgn:7007923",
        "tgn:7029392"
    ],
    "tgn:id":2371879,
    "tgn:name":"Haley Draw",
    "tgn:placetype":[
        "aat:300008761"
    ]
},
  "bbox": [],
  "geometry": {"coordinates":[-106.6333,44.4167],"type":"Point"}
}