<<<<<<< HEAD
{
  "id": 7369636,
  "type": "Feature",
  "properties": {
    "tgn:hierarchy":[
        "tgn:7369636",
        "tgn:7005581",
        "tgn:1000001",
        "tgn:7005560",
        "tgn:7029392"
    ],
    "tgn:id":7369636,
    "tgn:name":"Guahuachioue",
    "tgn:placetype":[
        "aat:300008347"
    ]
},
  "bbox": [],
  "geometry": {"coordinates":[-107.683333,27.383333],"type":"Point"}
}
=======
{"geometry":{"type":"Point","coordinates":[-107.683333,27.383333]},"type":"Feature","properties":{"hierarchy":["tgn:7369636","tgn:7005581","tgn:1000001","tgn:7005560","tgn:7029392"],"placetype":["aat:300008347"],"id":7369636,"name:xx":"Guahuachioue"}}
>>>>>>> 03f74aca74312dbeaf24d7e61306dd6a786dc3d0
