{
  "id": 2143301,
  "type": "Feature",
  "properties": {
    "tgn:hierarchy":[
        "tgn:2143301",
        "tgn:1000001",
        "tgn:7012149",
        "tgn:2001490",
        "tgn:7007709",
        "tgn:7029392"
    ],
    "tgn:id":2143301,
    "tgn:name":"Bailey Creek",
    "tgn:placetype":[
        "aat:300008706"
    ]
},
  "bbox": [],
  "geometry": {"coordinates":[-80.4667,35.9833],"type":"Point"}
}