<<<<<<< HEAD
{
  "id": 2409941,
  "type": "Feature",
  "properties": {
    "tgn:hierarchy":[
        "tgn:2409941",
        "tgn:1002300",
        "tgn:1000001",
        "tgn:7012149",
        "tgn:7007564",
        "tgn:7029392"
    ],
    "tgn:id":2409941,
    "tgn:name":"Imp Face",
    "tgn:placetype":[
        "aat:300008798"
    ]
},
  "bbox": [],
  "geometry": {"coordinates":[-71.1833,44.3167],"type":"Point"}
}
=======
{"geometry":{"type":"Point","coordinates":[-71.183300,44.316700]},"type":"Feature","properties":{"hierarchy":["tgn:2409941","tgn:1002300","tgn:1000001","tgn:7012149","tgn:7007564","tgn:7029392"],"placetype":["aat:300008798"],"id":2409941,"name:xx":"Imp Face"}}
>>>>>>> 03f74aca74312dbeaf24d7e61306dd6a786dc3d0
