{
  "id": 1047568,
  "type": "Feature",
  "properties": {
    "tgn:hierarchy":[
        "tgn:1047568",
        "tgn:7003534",
        "tgn:1000003",
        "tgn:7003514",
        "tgn:7029392"
    ],
    "tgn:id":1047568,
    "tgn:name":"P\u00e9tange",
    "tgn:placetype":[
        "aat:300008347"
    ]
},
  "bbox": [],
  "geometry": {"coordinates":[5.8833,49.55],"type":"Point"}
}