{
  "id": 1051512,
  "type": "Feature",
  "properties": {
    "tgn:hierarchy":[
        "tgn:1051512",
        "tgn:7012076",
        "tgn:1000003",
        "tgn:7006660",
        "tgn:7029392"
    ],
    "tgn:id":1051512,
    "tgn:name":"Shakhtars'k",
    "tgn:placetype":[
        "aat:300008347"
    ]
},
  "bbox": [],
  "geometry": {"coordinates":[38.4667,48.05],"type":"Point"}
}