<<<<<<< HEAD
{
  "id": 7361109,
  "type": "Feature",
  "properties": {
    "tgn:hierarchy":[
        "tgn:7361109",
        "tgn:1001853",
        "tgn:1000001",
        "tgn:7005560",
        "tgn:7029392"
    ],
    "tgn:id":7361109,
    "tgn:name":"El Huisache",
    "tgn:placetype":[
        "aat:300008347"
    ]
},
  "bbox": [],
  "geometry": {"coordinates":[-101.133333,26.85],"type":"Point"}
}
=======
{"geometry":{"type":"Point","coordinates":[-101.133333,26.850000]},"type":"Feature","properties":{"hierarchy":["tgn:7361109","tgn:1001853","tgn:1000001","tgn:7005560","tgn:7029392"],"placetype":["aat:300008347"],"id":7361109,"name:xx":"El Huisache"}}
>>>>>>> 03f74aca74312dbeaf24d7e61306dd6a786dc3d0
