{
  "id": 1068751,
  "type": "Feature",
  "properties": {
    "tgn:hierarchy":[
        "tgn:1068751",
        "tgn:1000004",
        "tgn:7002082",
        "tgn:1000111",
        "tgn:7029392"
    ],
    "tgn:id":1068751,
    "tgn:name":"Hezixu",
    "tgn:placetype":[
        "aat:300008347"
    ]
},
  "bbox": [],
  "geometry": {"coordinates":[115.2167,24.9167],"type":"Point"}
}