{
  "id": 7278791,
  "type": "Feature",
  "properties": {
    "tgn:hierarchy":[
        "tgn:7278791",
        "tgn:1001630",
        "tgn:1000049",
        "tgn:1000002",
        "tgn:7029392"
    ],
    "tgn:id":7278791,
    "tgn:name":"Santo Domingo, Cerro",
    "tgn:placetype":[
        "aat:300008798"
    ]
},
  "bbox": [],
  "geometry": {"coordinates":[-70.066667,-26.433333],"type":"Point"}
}