{
  "id": 7097277,
  "type": "Feature",
  "properties": {
    "tgn:hierarchy":[
        "tgn:7097277",
        "tgn:1000003",
        "tgn:7003678",
        "tgn:7000084",
        "tgn:7029392"
    ],
    "tgn:id":7097277,
    "tgn:name":"Sossenheim",
    "tgn:placetype":[
        "aat:300008347"
    ]
},
  "bbox": [],
  "geometry": {"coordinates":[8.566667,50.116667],"type":"Point"}
}