{
  "id": 7103034,
  "type": "Feature",
  "properties": {
    "tgn:hierarchy":[
        "tgn:7103034",
        "tgn:1000003",
        "tgn:7003687",
        "tgn:7000084",
        "tgn:7029392"
    ],
    "tgn:id":7103034,
    "tgn:name":"Sachsendorf",
    "tgn:placetype":[
        "aat:300008347"
    ]
},
  "bbox": [],
  "geometry": {"coordinates":[11.883333,51.866667],"type":"Point"}
}