{
  "id": 7086504,
  "type": "Feature",
  "properties": {
    "tgn:hierarchy":[
        "tgn:7086504",
        "tgn:7003692",
        "tgn:1000003",
        "tgn:7000084",
        "tgn:7029392"
    ],
    "tgn:id":7086504,
    "tgn:name":"Waldm\u00fchlbach",
    "tgn:placetype":[
        "aat:300008347"
    ]
},
  "bbox": [],
  "geometry": {"coordinates":[9.282778,49.360556],"type":"Point"}
}