{
  "id": 2545737,
  "type": "Feature",
  "properties": {
    "tgn:hierarchy":[
        "tgn:2545737",
        "tgn:1000001",
        "tgn:7012149",
        "tgn:7007920",
        "tgn:7029392"
    ],
    "tgn:id":2545737,
    "tgn:name":"North Fork Clear Creek",
    "tgn:placetype":[
        "aat:300008706"
    ]
},
  "bbox": [],
  "geometry": {"coordinates":[-121.3833,46.6667],"type":"Point"}
}