{
  "id": 2419111,
  "type": "Feature",
  "properties": {
    "tgn:hierarchy":[
        "tgn:2419111",
        "tgn:1000001",
        "tgn:7012149",
        "tgn:1002511",
        "tgn:7007919",
        "tgn:7029392"
    ],
    "tgn:id":2419111,
    "tgn:name":"Jamestown Farms",
    "tgn:placetype":[
        "aat:300008347"
    ]
},
  "bbox": [],
  "geometry": {"coordinates":[-76.7333,37.25],"type":"Point"}
}