{
  "id": 7298886,
  "type": "Feature",
  "properties": {
    "tgn:hierarchy":[
        "tgn:7298886",
        "tgn:7002760",
        "tgn:1000003",
        "tgn:1000095",
        "tgn:7029392"
    ],
    "tgn:id":7298886,
    "tgn:name":"Topor\u00edas",
    "tgn:placetype":[
        "aat:300008347"
    ]
},
  "bbox": [],
  "geometry": {"coordinates":[-4.216667,43.333333],"type":"Point"}
}