{
  "id": 7051362,
  "type": "Feature",
  "properties": {
    "tgn:hierarchy":[
        "tgn:7051362",
        "tgn:7003137",
        "tgn:1000003",
        "tgn:7003080",
        "tgn:1000080",
        "tgn:7029392"
    ],
    "tgn:id":7051362,
    "tgn:name":"La Forchetta",
    "tgn:placetype":[
        "aat:300259572"
    ]
},
  "bbox": [],
  "geometry": {"coordinates":[13.15,42.633333],"type":"Point"}
}