{
  "id": 2603758,
  "type": "Feature",
  "properties": {
    "tgn:hierarchy":[
        "tgn:2603758",
        "tgn:1000001",
        "tgn:2001409",
        "tgn:7012149",
        "tgn:7007526",
        "tgn:7029392"
    ],
    "tgn:id":2603758,
    "tgn:name":"Quick Tung Quicksilver Mine",
    "tgn:placetype":[
        "aat:300000390"
    ]
},
  "bbox": [],
  "geometry": {"coordinates":[-118.2167,39.7833],"type":"Point"}
}