{
  "id": 7214512,
  "type": "Feature",
  "properties": {
    "tgn:hierarchy":[
        "tgn:7214512",
        "tgn:1000003",
        "tgn:7000094",
        "tgn:7000084",
        "tgn:7029392"
    ],
    "tgn:id":7214512,
    "tgn:name":"Boize",
    "tgn:placetype":[
        "aat:300008347"
    ]
},
  "bbox": [],
  "geometry": {"coordinates":[10.85,53.566667],"type":"Point"}
}