{
  "id": 2695724,
  "type": "Feature",
  "properties": {
    "tgn:hierarchy":[
        "tgn:2695724",
        "tgn:1000001",
        "tgn:7012149",
        "tgn:1002553",
        "tgn:7007920",
        "tgn:7029392"
    ],
    "tgn:id":2695724,
    "tgn:name":"Stirrup Creek",
    "tgn:placetype":[
        "aat:300008706"
    ]
},
  "bbox": [],
  "geometry": {"coordinates":[-121.4167,47.2833],"type":"Point"}
}