{
  "id": 7416601,
  "type": "Feature",
  "properties": {
    "tgn:hierarchy":[
        "tgn:7416601",
        "tgn:1000001",
        "tgn:7005591",
        "tgn:7005560",
        "tgn:7029392"
    ],
    "tgn:id":7416601,
    "tgn:name:es":"Dolores Hidalgo",
    "tgn:placetype":[
        "aat:300008347"
    ]
},
  "bbox": [],
  "geometry": {"coordinates":[-95.493056,17.4925],"type":"Point"}
}