{
  "id": 2585344,
  "type": "Feature",
  "properties": {
    "tgn:hierarchy":[
        "tgn:2585344",
        "tgn:1000001",
        "tgn:7012149",
        "tgn:2000891",
        "tgn:7007256",
        "tgn:7029392"
    ],
    "tgn:id":2585344,
    "tgn:name":"Pintail Flat",
    "tgn:placetype":[
        "aat:300008680"
    ]
},
  "bbox": [],
  "geometry": {"coordinates":[-89.6667,29.6667],"type":"Point"}
}