{
  "id": 7236813,
  "type": "Feature",
  "properties": {
    "tgn:hierarchy":[
        "tgn:7236813",
        "tgn:7002692",
        "tgn:7012056",
        "tgn:1000003",
        "tgn:1000074",
        "tgn:7029392"
    ],
    "tgn:id":7236813,
    "tgn:name":"\u00c1yios Io\u00e1nnis",
    "tgn:placetype":[
        "aat:300008347"
    ]
},
  "bbox": [],
  "geometry": {"coordinates":[25.683333,35.25],"type":"Point"}
}