{
  "id": 2715545,
  "type": "Feature",
  "properties": {
    "tgn:hierarchy":[
        "tgn:2715545",
        "tgn:1000001",
        "tgn:2001480",
        "tgn:7012149",
        "tgn:7007709",
        "tgn:7029392"
    ],
    "tgn:id":2715545,
    "tgn:name":"Terrells Creek",
    "tgn:placetype":[
        "aat:300008706"
    ]
},
  "bbox": [],
  "geometry": {"coordinates":[-79.3667,35.7833],"type":"Point"}
}