{
  "id": 2221478,
  "type": "Feature",
  "properties": {
    "tgn:hierarchy":[
        "tgn:2221478",
        "tgn:1000001",
        "tgn:7012149",
        "tgn:7007157",
        "tgn:2000189",
        "tgn:7029392"
    ],
    "tgn:id":2221478,
    "tgn:name":"Caribou Creek",
    "tgn:placetype":[
        "aat:300008706"
    ]
},
  "bbox": [],
  "geometry": {"coordinates":[-122.9667,41.0333],"type":"Point"}
}