{
  "id": 7288909,
  "type": "Feature",
  "properties": {
    "tgn:hierarchy":[
        "tgn:7288909",
        "tgn:1001692",
        "tgn:1000049",
        "tgn:1000002",
        "tgn:7029392"
    ],
    "tgn:id":7288909,
    "tgn:name":"Hue\u00f1ivales, Cerro",
    "tgn:placetype":[
        "aat:300008795"
    ]
},
  "bbox": [],
  "geometry": {"coordinates":[-71.733333,-38.516667],"type":"Point"}
}