{
  "id": 2033342,
  "type": "Feature",
  "properties": {
    "tgn:hierarchy":[
        "tgn:2033342",
        "tgn:1000001",
        "tgn:7012149",
        "tgn:1002513",
        "tgn:7007252",
        "tgn:7029392"
    ],
    "tgn:id":2033342,
    "tgn:name":"Poling",
    "tgn:placetype":[
        "aat:300008347",
        "aat:300387210"
    ]
},
  "bbox": [],
  "geometry": {"coordinates":[-85.05,40.5167],"type":"Point"}
}