{
  "id": 7434263,
  "type": "Feature",
  "properties": {
    "tgn:hierarchy":[
        "tgn:7434263",
        "tgn:1000001",
        "tgn:7005588",
        "tgn:7005560",
        "tgn:7029392"
    ],
    "tgn:id":7434263,
    "tgn:name":"Xochipala",
    "tgn:placetype":[
        "aat:300008347"
    ]
},
  "bbox": [],
  "geometry": {"coordinates":[-99.066667,18.416667],"type":"Point"}
}