{
  "id": 7309983,
  "type": "Feature",
  "properties": {
    "tgn:hierarchy":[
        "tgn:7309983",
        "tgn:1001702",
        "tgn:1000049",
        "tgn:1000002",
        "tgn:7029392"
    ],
    "tgn:id":7309983,
    "tgn:name":"Nachbaur, Islas",
    "tgn:placetype":[
        "aat:300008791"
    ]
},
  "bbox": [],
  "geometry": {"coordinates":[-69.15,-55.266667],"type":"Point"}
}