{
  "id": 7013848,
  "type": "Feature",
  "properties": {
    "tgn:hierarchy":[
        "tgn:7013848",
        "tgn:1000001",
        "tgn:7012149",
        "tgn:1002946",
        "tgn:7007252",
        "tgn:7029392"
    ],
    "tgn:id":7013848,
    "tgn:name":"Lafayette",
    "tgn:placetype":[
        "aat:300008347",
        "aat:300008416",
        "aat:300008389",
        "aat:300387308",
        "aat:300387285"
    ]
},
  "bbox": [],
  "geometry": {"coordinates":[-86.8667,40.4167],"type":"Point"}
}