{
  "id": 7266840,
  "type": "Feature",
  "properties": {
    "tgn:hierarchy":[
        "tgn:7266840",
        "tgn:7003616",
        "tgn:1000003",
        "tgn:7016845",
        "tgn:7029392"
    ],
    "tgn:id":7266840,
    "tgn:name:nl":"Hofland, Polder het",
    "tgn:placetype":[
        "aat:300006163"
    ]
},
  "bbox": [],
  "geometry": {"coordinates":[5.833333,53.116667],"type":"Point"}
}