{
  "id": 2702290,
  "type": "Feature",
  "properties": {
    "tgn:hierarchy":[
        "tgn:2702290",
        "tgn:1000001",
        "tgn:7012149",
        "tgn:2002327",
        "tgn:7007922",
        "tgn:7029392"
    ],
    "tgn:id":2702290,
    "tgn:name":"Sullivan Creek",
    "tgn:placetype":[
        "aat:300008706"
    ]
},
  "bbox": [],
  "geometry": {"coordinates":[-90.3667,46.4167],"type":"Point"}
}