{
  "id": 1058331,
  "type": "Feature",
  "properties": {
    "tgn:hierarchy":[
        "tgn:1058331",
        "tgn:7011475",
        "tgn:1000004",
        "tgn:7006655",
        "tgn:7029392"
    ],
    "tgn:id":1058331,
    "tgn:name":"Pervomajskij",
    "tgn:placetype":[
        "aat:300008347"
    ]
},
  "bbox": [],
  "geometry": {"coordinates":[74.0667,42.85],"type":"Point"}
}