{
  "id": 2048317,
  "type": "Feature",
  "properties": {
    "tgn:hierarchy":[
        "tgn:2048317",
        "tgn:1000001",
        "tgn:7016106",
        "tgn:7012149",
        "tgn:7007516",
        "tgn:7029392"
    ],
    "tgn:id":2048317,
    "tgn:name":"Pleasant Valley",
    "tgn:placetype":[
        "aat:300008347",
        "aat:300387210"
    ]
},
  "bbox": [],
  "geometry": {"coordinates":[-77.5333,39.6333],"type":"Point"}
}