<<<<<<< HEAD
{
  "id": 7021165,
  "type": "Feature",
  "properties": {
    "tgn:hierarchy":[
        "tgn:7021165",
        "tgn:7002659",
        "tgn:1000001",
        "tgn:2000004",
        "tgn:7012149",
        "tgn:7029392"
    ],
    "tgn:id":7021165,
    "tgn:name":"Inland Junction",
    "tgn:placetype":[
        "aat:300008347"
    ]
},
  "bbox": [],
  "geometry": {"coordinates":[-86.55,33.8333],"type":"Point"}
}
=======
{"geometry":{"type":"Point","coordinates":[-86.550000,33.833300]},"type":"Feature","properties":{"hierarchy":["tgn:7021165","tgn:7002659","tgn:1000001","tgn:2000004","tgn:7012149","tgn:7029392"],"placetype":["aat:300008347"],"id":7021165,"name:xx":"Inland Junction"}}
>>>>>>> 03f74aca74312dbeaf24d7e61306dd6a786dc3d0
