{
  "id": 2391407,
  "type": "Feature",
  "properties": {
    "tgn:hierarchy":[
        "tgn:2391407",
        "tgn:1000001",
        "tgn:7016172",
        "tgn:7012149",
        "tgn:2000178",
        "tgn:7029392"
    ],
    "tgn:id":2391407,
    "tgn:name":"Hillemann",
    "tgn:placetype":[
        "aat:300008347"
    ]
},
  "bbox": [],
  "geometry": {"coordinates":[-91.0833,35.1167],"type":"Point"}
}