{
  "id": 2640826,
  "type": "Feature",
  "properties": {
    "tgn:hierarchy":[
        "tgn:2640826",
        "tgn:1000001",
        "tgn:7012149",
        "tgn:2001449",
        "tgn:7007566",
        "tgn:7029392"
    ],
    "tgn:id":2640826,
    "tgn:name":"San Texas Mine",
    "tgn:placetype":[
        "aat:300000390"
    ]
},
  "bbox": [],
  "geometry": {"coordinates":[-106.05,36.3167],"type":"Point"}
}