{
  "id": 7380968,
  "type": "Feature",
  "properties": {
    "tgn:hierarchy":[
        "tgn:7380968",
        "tgn:7005583",
        "tgn:1000001",
        "tgn:7005560",
        "tgn:7029392"
    ],
    "tgn:id":7380968,
    "tgn:name":"Los Lobos",
    "tgn:placetype":[
        "aat:300008347"
    ]
},
  "bbox": [],
  "geometry": {"coordinates":[-105.95,26.133333],"type":"Point"}
}