{
  "id": 2332761,
  "type": "Feature",
  "properties": {
    "tgn:hierarchy":[
        "tgn:2332761",
        "tgn:1000001",
        "tgn:7012149",
        "tgn:2001134",
        "tgn:7007522",
        "tgn:7029392"
    ],
    "tgn:id":2332761,
    "tgn:name":"Flowers Creek",
    "tgn:placetype":[
        "aat:300008706"
    ]
},
  "bbox": [],
  "geometry": {"coordinates":[-89.5833,33.45],"type":"Point"}
}