{
  "id": 2675806,
  "type": "Feature",
  "properties": {
    "tgn:hierarchy":[
        "tgn:2675806",
        "tgn:1000001",
        "tgn:1002174",
        "tgn:7012149",
        "tgn:7007826",
        "tgn:7029392"
    ],
    "tgn:id":2675806,
    "tgn:name":"Sommers Mill",
    "tgn:placetype":[
        "aat:300008347"
    ]
},
  "bbox": [],
  "geometry": {"coordinates":[-97.4167,30.9667],"type":"Point"}
}