{
  "id": 7445197,
  "type": "Feature",
  "properties": {
    "tgn:hierarchy":[
        "tgn:7445197",
        "tgn:7002443",
        "tgn:5000552",
        "tgn:1000003",
        "tgn:7008591",
        "tgn:7029392"
    ],
    "tgn:id":7445197,
    "tgn:name:en":"Llanmiloe",
    "tgn:placetype":[
        "aat:300008347"
    ]
},
  "bbox": [],
  "geometry": {"coordinates":[-4.5325,51.75],"type":"Point"}
}