<<<<<<< HEAD
{
  "id": 7025728,
  "type": "Feature",
  "properties": {
    "tgn:hierarchy":[
        "tgn:7025728",
        "tgn:7002445",
        "tgn:1000003",
        "tgn:7012077",
        "tgn:7008591",
        "tgn:7029392"
    ],
    "tgn:id":7025728,
    "tgn:name":"Sorley",
    "tgn:placetype":[
        "aat:300008347"
    ]
},
  "bbox": [],
  "geometry": {"coordinates":[-3.7833,50.3],"type":"Point"}
}
=======
{"geometry":{"type":"Point","coordinates":[-3.783300,50.300000]},"type":"Feature","properties":{"hierarchy":["tgn:7025728","tgn:7002445","tgn:1000003","tgn:7012077","tgn:7008591","tgn:7029392"],"placetype":["aat:300008347"],"id":7025728,"name:xx":"Sorley"}}
>>>>>>> 03f74aca74312dbeaf24d7e61306dd6a786dc3d0
