{
  "id": 7350874,
  "type": "Feature",
  "properties": {
    "tgn:hierarchy":[
        "tgn:7350874",
        "tgn:1000001",
        "tgn:1001960",
        "tgn:7005560",
        "tgn:7029392"
    ],
    "tgn:id":7350874,
    "tgn:name":"\u00c1rbol, Cerro",
    "tgn:placetype":[
        "aat:300008795"
    ]
},
  "bbox": [],
  "geometry": {"coordinates":[-108.916667,26.583333],"type":"Point"}
}