{
  "id": 2710319,
  "type": "Feature",
  "properties": {
    "tgn:hierarchy":[
        "tgn:2710319",
        "tgn:7002659",
        "tgn:1000001",
        "tgn:2000007",
        "tgn:7012149",
        "tgn:7029392"
    ],
    "tgn:id":2710319,
    "tgn:name":"Tally Spring",
    "tgn:placetype":[
        "aat:300008697"
    ]
},
  "bbox": [],
  "geometry": {"coordinates":[-85.65,33.6333],"type":"Point"}
}