<<<<<<< HEAD
{
  "id": 7368103,
  "type": "Feature",
  "properties": {
    "tgn:hierarchy":[
        "tgn:7368103",
        "tgn:1001853",
        "tgn:1000001",
        "tgn:7005560",
        "tgn:7029392"
    ],
    "tgn:id":7368103,
    "tgn:name":"Hedionda Chica",
    "tgn:placetype":[
        "aat:300008347"
    ]
},
  "bbox": [],
  "geometry": {"coordinates":[-101.4,25.55],"type":"Point"}
}
=======
{"geometry":{"type":"Point","coordinates":[-101.400000,25.550000]},"type":"Feature","properties":{"hierarchy":["tgn:7368103","tgn:1001853","tgn:1000001","tgn:7005560","tgn:7029392"],"placetype":["aat:300008347"],"id":7368103,"name:xx":"Hedionda Chica"}}
>>>>>>> 03f74aca74312dbeaf24d7e61306dd6a786dc3d0
