{
  "id": 7174800,
  "type": "Feature",
  "properties": {
    "tgn:hierarchy":[
        "tgn:7174800",
        "tgn:1000003",
        "tgn:7003677",
        "tgn:7000084",
        "tgn:7029392"
    ],
    "tgn:id":7174800,
    "tgn:name":"Gro\u00dfer Hein-Berg",
    "tgn:placetype":[
        "aat:300008777"
    ]
},
  "bbox": [],
  "geometry": {"coordinates":[9.166667,51.95],"type":"Point"}
}