{
  "id": 7007392,
  "type": "Feature",
  "properties": {
    "tgn:hierarchy":[
        "tgn:7007392",
        "tgn:1000003",
        "tgn:7003763",
        "tgn:7011731",
        "tgn:7029392"
    ],
    "tgn:id":7007392,
    "tgn:name":"La Sarraz",
    "tgn:placetype":[
        "aat:300008347"
    ]
},
  "bbox": [],
  "geometry": {"coordinates":[6.5167,46.6667],"type":"Point"}
}