{
  "id": 2573495,
  "type": "Feature",
  "properties": {
    "tgn:hierarchy":[
        "tgn:2573495",
        "tgn:1000001",
        "tgn:2001742",
        "tgn:7012149",
        "tgn:7007712",
        "tgn:7029392"
    ],
    "tgn:id":2573495,
    "tgn:name":"Pecan Grove",
    "tgn:placetype":[
        "aat:300008347"
    ]
},
  "bbox": [],
  "geometry": {"coordinates":[-80.2167,33.0167],"type":"Point"}
}