{
  "id": 2034694,
  "type": "Feature",
  "properties": {
    "tgn:hierarchy":[
        "tgn:2034694",
        "tgn:1000001",
        "tgn:7012149",
        "tgn:2000624",
        "tgn:7007253",
        "tgn:7029392"
    ],
    "tgn:id":2034694,
    "tgn:name":"Dunbar",
    "tgn:placetype":[
        "aat:300008347"
    ]
},
  "bbox": [],
  "geometry": {"coordinates":[-92.7833,41.9333],"type":"Point"}
}