{
  "id": 2691912,
  "type": "Feature",
  "properties": {
    "tgn:hierarchy":[
        "tgn:2691912",
        "tgn:1000001",
        "tgn:7012149",
        "tgn:7016056",
        "tgn:7007520",
        "tgn:7029392"
    ],
    "tgn:id":2691912,
    "tgn:name":"Starville",
    "tgn:placetype":[
        "aat:300008347"
    ]
},
  "bbox": [],
  "geometry": {"coordinates":[-82.5833,42.6667],"type":"Point"}
}