{
  "id": 7554441,
  "type": "Feature",
  "properties": {
    "tgn:hierarchy":[
        "tgn:7554441",
        "tgn:1000004",
        "tgn:7000198",
        "tgn:1001895",
        "tgn:7029392"
    ],
    "tgn:id":7554441,
    "tgn:name:en":"N\u0101g\u0101pur",
    "tgn:placetype":[
        "aat:300008347"
    ]
},
  "bbox": [],
  "geometry": {"coordinates":[75.25,20.383333],"type":"Point"}
}