{
  "id": 2274764,
  "type": "Feature",
  "properties": {
    "tgn:hierarchy":[
        "tgn:2274764",
        "tgn:1000001",
        "tgn:2001424",
        "tgn:7012149",
        "tgn:7007564",
        "tgn:7029392"
    ],
    "tgn:id":2274764,
    "tgn:name":"Dame Hill",
    "tgn:placetype":[
        "aat:300008798"
    ]
},
  "bbox": [],
  "geometry": {"coordinates":[-72.0833,43.8833],"type":"Point"}
}