{
  "id": 2717088,
  "type": "Feature",
  "properties": {
    "tgn:hierarchy":[
        "tgn:2717088",
        "tgn:1000001",
        "tgn:7012149",
        "tgn:2001708",
        "tgn:7007708",
        "tgn:7029392"
    ],
    "tgn:id":2717088,
    "tgn:name":"Third Creek",
    "tgn:placetype":[
        "aat:300008706"
    ]
},
  "bbox": [],
  "geometry": {"coordinates":[-119.25,44.35],"type":"Point"}
}