{
  "id": 7590234,
  "type": "Feature",
  "properties": {
    "tgn:hierarchy":[
        "tgn:7590234",
        "tgn:1000004",
        "tgn:1001871",
        "tgn:7000198",
        "tgn:7029392"
    ],
    "tgn:id":7590234,
    "tgn:name:en":"Sarwan M\u0101jra",
    "tgn:placetype":[
        "aat:300008347"
    ]
},
  "bbox": [],
  "geometry": {"coordinates":[76.971863,29.923425],"type":"Point"}
}