{
  "id": 2621334,
  "type": "Feature",
  "properties": {
    "tgn:hierarchy":[
        "tgn:2621334",
        "tgn:1000001",
        "tgn:7012149",
        "tgn:7007710",
        "tgn:7029392"
    ],
    "tgn:id":2621334,
    "tgn:name":"Roaring Branch",
    "tgn:placetype":[
        "aat:300008699"
    ]
},
  "bbox": [],
  "geometry": {"coordinates":[-77.0833,41.5167],"type":"Point"}
}