{
  "id": 2167964,
  "type": "Feature",
  "properties": {
    "tgn:hierarchy":[
        "tgn:2167964",
        "tgn:1000001",
        "tgn:7012149",
        "tgn:7007566",
        "tgn:7029392"
    ],
    "tgn:id":2167964,
    "tgn:name":"Big Dry Creek",
    "tgn:placetype":[
        "aat:300008706"
    ]
},
  "bbox": [],
  "geometry": {"coordinates":[-108.65,33.2833],"type":"Point"}
}