{
  "id": 7043639,
  "type": "Feature",
  "properties": {
    "tgn:hierarchy":[
        "tgn:7043639",
        "tgn:7007850",
        "tgn:1000003",
        "tgn:1000080",
        "tgn:7029392"
    ],
    "tgn:id":7043639,
    "tgn:name":"Carafuno di Cappellieri",
    "tgn:placetype":[
        "aat:300008699"
    ]
},
  "bbox": [],
  "geometry": {"coordinates":[17.066667,39.416667],"type":"Point"}
}