{
  "id": 1028443,
  "type": "Feature",
  "properties": {
    "tgn:hierarchy":[
        "tgn:1028443",
        "tgn:7002445",
        "tgn:1000003",
        "tgn:7012032",
        "tgn:7008591",
        "tgn:7029392"
    ],
    "tgn:id":1028443,
    "tgn:name:en":"Beckington",
    "tgn:placetype":[
        "aat:300008347"
    ]
},
  "bbox": [],
  "geometry": {"coordinates":[-2.287222,51.264444],"type":"Point"}
}