{
  "id": 2766654,
  "type": "Feature",
  "properties": {
    "tgn:hierarchy":[
        "tgn:2766654",
        "tgn:1000001",
        "tgn:7012149",
        "tgn:2001195",
        "tgn:7007523",
        "tgn:7029392"
    ],
    "tgn:id":2766654,
    "tgn:name":"White Oak Hollow",
    "tgn:placetype":[
        "aat:300008761"
    ]
},
  "bbox": [],
  "geometry": {"coordinates":[-91.5667,37.4667],"type":"Point"}
}