<<<<<<< HEAD
{
  "id": 2766654,
  "type": "Feature",
  "properties": {
    "tgn:hierarchy":[
        "tgn:2766654",
        "tgn:1000001",
        "tgn:7012149",
        "tgn:2001195",
        "tgn:7007523",
        "tgn:7029392"
    ],
    "tgn:id":2766654,
    "tgn:name":"White Oak Hollow",
    "tgn:placetype":[
        "aat:300008761"
    ]
},
  "bbox": [],
  "geometry": {"coordinates":[-91.5667,37.4667],"type":"Point"}
}
=======
{"geometry":{"type":"Point","coordinates":[-91.566700,37.466700]},"type":"Feature","properties":{"hierarchy":["tgn:2766654","tgn:1000001","tgn:7012149","tgn:2001195","tgn:7007523","tgn:7029392"],"placetype":["aat:300008761"],"id":2766654,"name:xx":"White Oak Hollow"}}
>>>>>>> 03f74aca74312dbeaf24d7e61306dd6a786dc3d0
