{
  "id": 7124342,
  "type": "Feature",
  "properties": {
    "tgn:hierarchy":[
        "tgn:7124342",
        "tgn:1000003",
        "tgn:7000094",
        "tgn:7000084",
        "tgn:7029392"
    ],
    "tgn:id":7124342,
    "tgn:name":"Neu Quitzenow",
    "tgn:placetype":[
        "aat:300008347"
    ]
},
  "bbox": [],
  "geometry": {"coordinates":[12.733333,54.033333],"type":"Point"}
}