{
  "id": 2178181,
  "type": "Feature",
  "properties": {
    "tgn:hierarchy":[
        "tgn:2178181",
        "tgn:1000001",
        "tgn:7012149",
        "tgn:7007524",
        "tgn:7029392"
    ],
    "tgn:id":2178181,
    "tgn:name":"Blackhawk Coulee",
    "tgn:placetype":[
        "aat:300008761"
    ]
},
  "bbox": [],
  "geometry": {"coordinates":[-106.1167,48.75],"type":"Point"}
}