{
  "id": 7339855,
  "type": "Feature",
  "properties": {
    "tgn:hierarchy":[
        "tgn:7339855",
        "tgn:7008912",
        "tgn:7030216",
        "tgn:1000003",
        "tgn:1000095",
        "tgn:7029392"
    ],
    "tgn:id":7339855,
    "tgn:name":"Coma de Parr\u00f3s, Cabeza de",
    "tgn:placetype":[
        "aat:300008798"
    ]
},
  "bbox": [],
  "geometry": {"coordinates":[0.948198,42.742482],"type":"Point"}
}