{
  "id": 2040933,
  "type": "Feature",
  "properties": {
    "tgn:hierarchy":[
        "tgn:2040933",
        "tgn:1000001",
        "tgn:7012149",
        "tgn:2000849",
        "tgn:7007255",
        "tgn:7029392"
    ],
    "tgn:id":2040933,
    "tgn:name":"Pulliam",
    "tgn:placetype":[
        "aat:300008347",
        "aat:300387210"
    ]
},
  "bbox": [],
  "geometry": {"coordinates":[-85.1333,37.8333],"type":"Point"}
}