{
  "id": 2383378,
  "type": "Feature",
  "properties": {
    "tgn:hierarchy":[
        "tgn:2383378",
        "tgn:2002308",
        "tgn:1000001",
        "tgn:7012149",
        "tgn:7007922",
        "tgn:7029392"
    ],
    "tgn:id":2383378,
    "tgn:name":"Heart Lake",
    "tgn:placetype":[
        "aat:300008680"
    ]
},
  "bbox": [],
  "geometry": {"coordinates":[-91.2833,46.4833],"type":"Point"}
}