{
  "id": 2462359,
  "type": "Feature",
  "properties": {
    "tgn:hierarchy":[
        "tgn:2462359",
        "tgn:1000001",
        "tgn:7012149",
        "tgn:1002378",
        "tgn:7007710",
        "tgn:7029392"
    ],
    "tgn:id":2462359,
    "tgn:name":"Little Weaver Run",
    "tgn:placetype":[
        "aat:300008699"
    ]
},
  "bbox": [],
  "geometry": {"coordinates":[-79.25,41.45],"type":"Point"}
}