{
  "id": 1135878,
  "type": "Feature",
  "properties": {
    "tgn:hierarchy":[
        "tgn:1135878",
        "tgn:1001160",
        "tgn:7006477",
        "tgn:1000002",
        "tgn:7029392"
    ],
    "tgn:id":1135878,
    "tgn:name":"Cinco, Canal Numero",
    "tgn:placetype":[
        "aat:300006075"
    ]
},
  "bbox": [],
  "geometry": {"coordinates":[-57.3333,-37.5833],"type":"Point"}
}