{
  "id": 7074534,
  "type": "Feature",
  "properties": {
    "tgn:hierarchy":[
        "tgn:7074534",
        "tgn:1000003",
        "tgn:7003689",
        "tgn:7000084",
        "tgn:7029392"
    ],
    "tgn:id":7074534,
    "tgn:name":"Zickeshaupt",
    "tgn:placetype":[
        "aat:300055621"
    ]
},
  "bbox": [],
  "geometry": {"coordinates":[10.05,50.733333],"type":"Point"}
}