{
  "id": 2619624,
  "type": "Feature",
  "properties": {
    "tgn:hierarchy":[
        "tgn:2619624",
        "tgn:1000001",
        "tgn:1002219",
        "tgn:7012149",
        "tgn:7007157",
        "tgn:7029392"
    ],
    "tgn:id":2619624,
    "tgn:name":"Rindge Mine Number Three",
    "tgn:placetype":[
        "aat:300000390"
    ]
},
  "bbox": [],
  "geometry": {"coordinates":[-120.5667,38.3333],"type":"Point"}
}