{
  "id": 2281817,
  "type": "Feature",
  "properties": {
    "tgn:hierarchy":[
        "tgn:2281817",
        "tgn:1000001",
        "tgn:7012149",
        "tgn:2001956",
        "tgn:7007826",
        "tgn:7029392"
    ],
    "tgn:id":2281817,
    "tgn:name":"Deer Creek",
    "tgn:placetype":[
        "aat:300008706"
    ]
},
  "bbox": [],
  "geometry": {"coordinates":[-98.25,33.55],"type":"Point"}
}