{
  "id": 2710433,
  "type": "Feature",
  "properties": {
    "tgn:hierarchy":[
        "tgn:2710433",
        "tgn:1000001",
        "tgn:2000469",
        "tgn:7012149",
        "tgn:7007250",
        "tgn:7029392"
    ],
    "tgn:id":2710433,
    "tgn:name":"Tamarack Creek",
    "tgn:placetype":[
        "aat:300008706"
    ]
},
  "bbox": [],
  "geometry": {"coordinates":[-115.55,46.5333],"type":"Point"}
}