{
  "id": 2175313,
  "type": "Feature",
  "properties": {
    "tgn:hierarchy":[
        "tgn:2175313",
        "tgn:1000001",
        "tgn:2001262",
        "tgn:7012149",
        "tgn:7007524",
        "tgn:7029392"
    ],
    "tgn:id":2175313,
    "tgn:name":"Black Butte",
    "tgn:placetype":[
        "aat:300008798"
    ]
},
  "bbox": [],
  "geometry": {"coordinates":[-109.1667,47.8333],"type":"Point"}
}