{
  "id": 7468660,
  "type": "Feature",
  "properties": {
    "tgn:hierarchy":[
        "tgn:7468660",
        "tgn:1000004",
        "tgn:7491221",
        "tgn:1000141",
        "tgn:7029392"
    ],
    "tgn:id":7468660,
    "tgn:name":"Chong'an",
    "tgn:placetype":[
        "aat:300008347"
    ]
},
  "bbox": [],
  "geometry": {"coordinates":[121.395117,23.192718],"type":"Point"}
}