{
  "id": 2692402,
  "type": "Feature",
  "properties": {
    "tgn:hierarchy":[
        "tgn:2692402",
        "tgn:1000001",
        "tgn:2002103",
        "tgn:7012149",
        "tgn:7007827",
        "tgn:7029392"
    ],
    "tgn:id":2692402,
    "tgn:name":"Steam Mill Canyon",
    "tgn:placetype":[
        "aat:300008761"
    ]
},
  "bbox": [],
  "geometry": {"coordinates":[-111.65,41.95],"type":"Point"}
}