{
  "id": 7232651,
  "type": "Feature",
  "properties": {
    "tgn:hierarchy":[
        "tgn:7232651",
        "tgn:7002741",
        "tgn:7017076",
        "tgn:1000003",
        "tgn:1000074",
        "tgn:7029392"
    ],
    "tgn:id":7232651,
    "tgn:name":"Lo\u00fatsa",
    "tgn:placetype":[
        "aat:300008777"
    ]
},
  "bbox": [],
  "geometry": {"coordinates":[22.633333,38.45],"type":"Point"}
}