{
  "id": 2382930,
  "type": "Feature",
  "properties": {
    "tgn:hierarchy":[
        "tgn:2382930",
        "tgn:7002659",
        "tgn:1000001",
        "tgn:7012149",
        "tgn:2000064",
        "tgn:7029392"
    ],
    "tgn:id":2382930,
    "tgn:name":"Hazzards Bar",
    "tgn:placetype":[
        "aat:300132348"
    ]
},
  "bbox": [],
  "geometry": {"coordinates":[-88.0667,31.6667],"type":"Point"}
}