{
  "id": 1086839,
  "type": "Feature",
  "properties": {
    "tgn:hierarchy":[
        "tgn:1086839",
        "tgn:1001052",
        "tgn:1000004",
        "tgn:7018450",
        "tgn:1000144",
        "tgn:7029392"
    ],
    "tgn:id":1086839,
    "tgn:name":"Samand\u0131ra",
    "tgn:placetype":[
        "aat:300008347"
    ]
},
  "bbox": [],
  "geometry": {"coordinates":[29.2167,40.9833],"type":"Point"}
}