{
  "id": 2042787,
  "type": "Feature",
  "properties": {
    "tgn:hierarchy":[
        "tgn:2042787",
        "tgn:1000001",
        "tgn:2000862",
        "tgn:7012149",
        "tgn:7007256",
        "tgn:7029392"
    ],
    "tgn:id":2042787,
    "tgn:name":"Forbing",
    "tgn:placetype":[
        "aat:300008347"
    ]
},
  "bbox": [],
  "geometry": {"coordinates":[-93.7167,32.3833],"type":"Point"}
}