{
  "id": 2167024,
  "type": "Feature",
  "properties": {
    "tgn:hierarchy":[
        "tgn:2167024",
        "tgn:1000001",
        "tgn:7012149",
        "tgn:1002595",
        "tgn:7007826",
        "tgn:7029392"
    ],
    "tgn:id":2167024,
    "tgn:name":"Big Caney Creek",
    "tgn:placetype":[
        "aat:300008706"
    ]
},
  "bbox": [],
  "geometry": {"coordinates":[-94.85,29.95],"type":"Point"}
}