{
  "id": 7565920,
  "type": "Feature",
  "properties": {
    "tgn:hierarchy":[
        "tgn:7565920",
        "tgn:1000004",
        "tgn:7000198",
        "tgn:7016722",
        "tgn:7029392"
    ],
    "tgn:id":7565920,
    "tgn:name:en":"Karmukha Mustaqil Reserved Forest",
    "tgn:placetype":[
        "aat:300008865"
    ]
},
  "bbox": [],
  "geometry": {"coordinates":[79.492442,26.365074],"type":"Point"}
}