{
  "id": 2198364,
  "type": "Feature",
  "properties": {
    "tgn:hierarchy":[
        "tgn:2198364",
        "tgn:1000001",
        "tgn:7012149",
        "tgn:2002287",
        "tgn:7013961",
        "tgn:7029392"
    ],
    "tgn:id":2198364,
    "tgn:name":"Browns Creek",
    "tgn:placetype":[
        "aat:300008706"
    ]
},
  "bbox": [],
  "geometry": {"coordinates":[-79.95,38.25],"type":"Point"}
}