{
  "id": 2272335,
  "type": "Feature",
  "properties": {
    "tgn:hierarchy":[
        "tgn:2272335",
        "tgn:1000001",
        "tgn:2000269",
        "tgn:7012149",
        "tgn:7007240",
        "tgn:7029392"
    ],
    "tgn:id":2272335,
    "tgn:name":"Curtis",
    "tgn:placetype":[
        "aat:300008347"
    ]
},
  "bbox": [],
  "geometry": {"coordinates":[-82.8833,29.7333],"type":"Point"}
}