{
  "id": 2584690,
  "type": "Feature",
  "properties": {
    "tgn:hierarchy":[
        "tgn:2584690",
        "tgn:1000001",
        "tgn:7013368",
        "tgn:7012149",
        "tgn:7007709",
        "tgn:7029392"
    ],
    "tgn:id":2584690,
    "tgn:name":"Pineygrove",
    "tgn:placetype":[
        "aat:300008347"
    ]
},
  "bbox": [],
  "geometry": {"coordinates":[-76.9833,35.55],"type":"Point"}
}