{
  "id": 7245206,
  "type": "Feature",
  "properties": {
    "tgn:hierarchy":[
        "tgn:7245206",
        "tgn:7003456",
        "tgn:1000003",
        "tgn:1000063",
        "tgn:7018236",
        "tgn:7029392"
    ],
    "tgn:id":7245206,
    "tgn:name":"Achterbist",
    "tgn:placetype":[
        "aat:300008347"
    ]
},
  "bbox": [],
  "geometry": {"coordinates":[4.653035,51.166453],"type":"Point"}
}