{
  "id": 7530731,
  "type": "Feature",
  "properties": {
    "tgn:hierarchy":[
        "tgn:7530731",
        "tgn:7001242",
        "tgn:7016833",
        "tgn:1001114",
        "tgn:7029392"
    ],
    "tgn:id":7530731,
    "tgn:name:en":"Minsh\u0101t Hamm\u0101m",
    "tgn:placetype":[
        "aat:300008347"
    ]
},
  "bbox": [],
  "geometry": {"coordinates":[31.376866,27.01736],"type":"Point"}
}