{
  "id": 7507000,
  "type": "Feature",
  "properties": {
    "tgn:hierarchy":[
        "tgn:7507000",
        "tgn:1009227",
        "tgn:1000226",
        "tgn:7016822",
        "tgn:1000006",
        "tgn:7029392"
    ],
    "tgn:id":7507000,
    "tgn:name:en":"Ram Hill",
    "tgn:placetype":[
        "aat:300008795"
    ]
},
  "bbox": [],
  "geometry": {"coordinates":[168.633333,-45.566667],"type":"Point"}
}