{
  "id": 7274409,
  "type": "Feature",
  "properties": {
    "tgn:concordances":{
        "gn:id":"2743577"
    },
    "tgn:hierarchy":[
        "tgn:7274409",
        "tgn:1000003",
        "tgn:7003632",
        "tgn:7016845",
        "tgn:7029392"
    ],
    "tgn:id":7274409,
    "tgn:name:nl":"Zwanegat",
    "tgn:placetype":[
        "aat:300008347"
    ]
},
  "bbox": [],
  "geometry": {"coordinates":[4.516667,51.783333],"type":"Point"}
}