{
  "id": 2656017,
  "type": "Feature",
  "properties": {
    "tgn:hierarchy":[
        "tgn:2656017",
        "tgn:1000001",
        "tgn:2001430",
        "tgn:7012149",
        "tgn:7007566",
        "tgn:7029392"
    ],
    "tgn:id":2656017,
    "tgn:name":"Shaw Lake",
    "tgn:placetype":[
        "aat:300008680"
    ]
},
  "bbox": [],
  "geometry": {"coordinates":[-104.4167,33.5167],"type":"Point"}
}