{
  "id": 7481682,
  "type": "Feature",
  "properties": {
    "tgn:hierarchy":[
        "tgn:7481682",
        "tgn:1000004",
        "tgn:7489179",
        "tgn:1000141",
        "tgn:7029392"
    ],
    "tgn:id":7481682,
    "tgn:name":"Dongqiusi Shan",
    "tgn:placetype":[
        "aat:300008798"
    ]
},
  "bbox": [],
  "geometry": {"coordinates":[121.403056,24.591667],"type":"Point"}
}