{
  "id": 2733301,
  "type": "Feature",
  "properties": {
    "tgn:hierarchy":[
        "tgn:2733301",
        "tgn:1002136",
        "tgn:1000001",
        "tgn:7012149",
        "tgn:7007706",
        "tgn:7029392"
    ],
    "tgn:id":2733301,
    "tgn:name":"Turkey Run",
    "tgn:placetype":[
        "aat:300008699"
    ]
},
  "bbox": [],
  "geometry": {"coordinates":[-83.35,38.8167],"type":"Point"}
}