{
  "id": 7336651,
  "type": "Feature",
  "properties": {
    "tgn:hierarchy":[
        "tgn:7336651",
        "tgn:7002825",
        "tgn:7016622",
        "tgn:1000003",
        "tgn:1000095",
        "tgn:7029392"
    ],
    "tgn:id":7336651,
    "tgn:name":"Gaviota, Punta",
    "tgn:placetype":[
        "aat:300386846"
    ]
},
  "bbox": [],
  "geometry": {"coordinates":[-13.75,29.066667],"type":"Point"}
}