{
  "id": 7016401,
  "type": "Feature",
  "properties": {
    "tgn:hierarchy":[
        "tgn:7016401",
        "tgn:1000001",
        "tgn:2000924",
        "tgn:7012149",
        "tgn:7007515",
        "tgn:7029392"
    ],
    "tgn:id":7016401,
    "tgn:name":"Warren",
    "tgn:placetype":[
        "aat:300008347",
        "aat:300387210"
    ]
},
  "bbox": [],
  "geometry": {"coordinates":[-69.2333,44.1167],"type":"Point"}
}