{
  "id": 1077119,
  "type": "Feature",
  "properties": {
    "tgn:hierarchy":[
        "tgn:1077119",
        "tgn:1000004",
        "tgn:7000198",
        "tgn:1001895",
        "tgn:7029392"
    ],
    "tgn:id":1077119,
    "tgn:name:en":"Taloda",
    "tgn:placetype":[
        "aat:300008347"
    ]
},
  "bbox": [],
  "geometry": {"coordinates":[74.212578,21.560599],"type":"Point"}
}