{
  "id": 7012991,
  "type": "Feature",
  "properties": {
    "tgn:hierarchy":[
        "tgn:7012991",
        "tgn:1000003",
        "tgn:7000084",
        "tgn:7029392"
    ],
    "tgn:id":7012991,
    "tgn:name":"Mittellandkanal",
    "tgn:placetype":[
        "aat:300006075"
    ]
},
  "bbox": [],
  "geometry": {"coordinates":[11.6833,52.2667],"type":"Point"}
}