{
  "id": 1136424,
  "type": "Feature",
  "properties": {
    "tgn:hierarchy":[
        "tgn:1136424",
        "tgn:1001160",
        "tgn:7006477",
        "tgn:1000002",
        "tgn:7029392"
    ],
    "tgn:id":1136424,
    "tgn:name":"Bella Vista",
    "tgn:placetype":[
        "aat:300008347"
    ]
},
  "bbox": [],
  "geometry": {"coordinates":[-58.6833,-34.55],"type":"Point"}
}