{
  "id": 7541067,
  "type": "Feature",
  "properties": {
    "tgn:hierarchy":[
        "tgn:7541067",
        "tgn:7001242",
        "tgn:7016833",
        "tgn:7029392"
    ],
    "tgn:id":7541067,
    "tgn:name":"Tur'at az Zumur",
    "tgn:placetype":[
        "aat:300006075"
    ]
},
  "bbox": [],
  "geometry": {"coordinates":[31.20385,30.000334],"type":"Point"}
}