{
  "id": 1024715,
  "type": "Feature",
  "properties": {
    "tgn:hierarchy":[
        "tgn:1024715",
        "tgn:1000518",
        "tgn:1000002",
        "tgn:1000056",
        "tgn:7029392"
    ],
    "tgn:id":1024715,
    "tgn:name":"Querobamba",
    "tgn:placetype":[
        "aat:300008347"
    ]
},
  "bbox": [],
  "geometry": {"coordinates":[-73.8333,-13.8667],"type":"Point"}
}