{
  "id": 1002367,
  "type": "Feature",
  "properties": {
    "tgn:hierarchy":[
        "tgn:1002367",
        "tgn:1000001",
        "tgn:7012149",
        "tgn:7007826",
        "tgn:7029392"
    ],
    "tgn:id":1002367,
    "tgn:name":"Falls",
    "tgn:placetype":[
        "aat:300387145",
        "aat:300000771"
    ]
},
  "bbox": [],
  "geometry": {"coordinates":[-96.9333,31.2667],"type":"Point"}
}