{
  "id": 7223441,
  "type": "Feature",
  "properties": {
    "tgn:hierarchy":[
        "tgn:7223441",
        "tgn:7011270",
        "tgn:7002674",
        "tgn:1000003",
        "tgn:1000074",
        "tgn:7029392"
    ],
    "tgn:id":7223441,
    "tgn:name":"Ovri\u00f3kastro, Nis\u00edda",
    "tgn:placetype":[
        "aat:300008791"
    ]
},
  "bbox": [],
  "geometry": {"coordinates":[25.296944,37.152222],"type":"Point"}
}