{
  "id": 2742155,
  "type": "Feature",
  "properties": {
    "tgn:hierarchy":[
        "tgn:2742155",
        "tgn:1000001",
        "tgn:7012149",
        "tgn:2001290",
        "tgn:7007524",
        "tgn:7029392"
    ],
    "tgn:id":2742155,
    "tgn:name":"Valentine Mine",
    "tgn:placetype":[
        "aat:300000390"
    ]
},
  "bbox": [],
  "geometry": {"coordinates":[-115.3167,47.4333],"type":"Point"}
}