{
  "id": 7184466,
  "type": "Feature",
  "properties": {
    "tgn:hierarchy":[
        "tgn:7184466",
        "tgn:1000003",
        "tgn:7003689",
        "tgn:7000084",
        "tgn:7029392"
    ],
    "tgn:id":7184466,
    "tgn:name":"G\u00f6ssitzer Wald",
    "tgn:placetype":[
        "aat:300008863"
    ]
},
  "bbox": [],
  "geometry": {"coordinates":[11.616667,50.633333],"type":"Point"}
}