{
  "id": 2491880,
  "type": "Feature",
  "properties": {
    "tgn:hierarchy":[
        "tgn:2491880",
        "tgn:1000001",
        "tgn:7012149",
        "tgn:1002817",
        "tgn:7007523",
        "tgn:7029392"
    ],
    "tgn:id":2491880,
    "tgn:name":"Marble Creek",
    "tgn:placetype":[
        "aat:300008706"
    ]
},
  "bbox": [],
  "geometry": {"coordinates":[-91.3167,39.6167],"type":"Point"}
}