{
  "id": 2604409,
  "type": "Feature",
  "properties": {
    "tgn:hierarchy":[
        "tgn:2604409",
        "tgn:7006450",
        "tgn:1000001",
        "tgn:7019698",
        "tgn:7012149",
        "tgn:7029392"
    ],
    "tgn:id":2604409,
    "tgn:name":"Rabbit Foot Lake",
    "tgn:placetype":[
        "aat:300008680"
    ]
},
  "bbox": [],
  "geometry": {"coordinates":[-150.35,60.7333],"type":"Point"}
}