{
  "id": 2636997,
  "type": "Feature",
  "properties": {
    "tgn:hierarchy":[
        "tgn:2636997",
        "tgn:1000001",
        "tgn:2000778",
        "tgn:7012149",
        "tgn:7007255",
        "tgn:7029392"
    ],
    "tgn:id":2636997,
    "tgn:name":"Saint Arbor Slough",
    "tgn:placetype":[
        "aat:300008905"
    ]
},
  "bbox": [],
  "geometry": {"coordinates":[-88.9167,36.9167],"type":"Point"}
}