{
  "id": 2460848,
  "type": "Feature",
  "properties": {
    "tgn:hierarchy":[
        "tgn:2460848",
        "tgn:1000001",
        "tgn:7012149",
        "tgn:7029392"
    ],
    "tgn:id":2460848,
    "tgn:name":"Little Simpson Creek",
    "tgn:placetype":[
        "aat:300008706"
    ]
},
  "bbox": [],
  "geometry": {"coordinates":[-104.7333,41.0333],"type":"Point"}
}