{
  "id": 7299956,
  "type": "Feature",
  "properties": {
    "tgn:hierarchy":[
        "tgn:7299956",
        "tgn:7002811",
        "tgn:1000003",
        "tgn:7003837",
        "tgn:1000095",
        "tgn:7029392"
    ],
    "tgn:id":7299956,
    "tgn:name":"Torremenga",
    "tgn:placetype":[
        "aat:300008347"
    ]
},
  "bbox": [],
  "geometry": {"coordinates":[-5.766667,40.05],"type":"Point"}
}