{
  "id": 2276234,
  "type": "Feature",
  "properties": {
    "tgn:hierarchy":[
        "tgn:2276234",
        "tgn:1000001",
        "tgn:7012149",
        "tgn:2000182",
        "tgn:7007157",
        "tgn:7029392"
    ],
    "tgn:id":2276234,
    "tgn:name":"Date Drain Three",
    "tgn:placetype":[
        "aat:300006075"
    ]
},
  "bbox": [],
  "geometry": {"coordinates":[-115.5333,32.7333],"type":"Point"}
}