{
  "id": 2245933,
  "type": "Feature",
  "properties": {
    "tgn:hierarchy":[
        "tgn:2245933",
        "tgn:1000001",
        "tgn:2001584",
        "tgn:7012149",
        "tgn:7007705",
        "tgn:7029392"
    ],
    "tgn:id":2245933,
    "tgn:name":"Coal Lake Coulee",
    "tgn:placetype":[
        "aat:300008699"
    ]
},
  "bbox": [],
  "geometry": {"coordinates":[-101.1167,47.35],"type":"Point"}
}