{
  "id": 7032487,
  "type": "Feature",
  "properties": {
    "tgn:hierarchy":[
        "tgn:7032487",
        "tgn:1001287",
        "tgn:7018452",
        "tgn:1000004",
        "tgn:1000144",
        "tgn:7029392"
    ],
    "tgn:id":7032487,
    "tgn:name":"P\u0131narba\u015f\u0131",
    "tgn:placetype":[
        "aat:300008347",
        "aat:300000810",
        "aat:300167671",
        "aat:300008057"
    ]
},
  "bbox": [],
  "geometry": {"coordinates":[36.5275,36.580833],"type":"Point"}
}