{
  "id": 2574119,
  "type": "Feature",
  "properties": {
    "tgn:hierarchy":[
        "tgn:2574119",
        "tgn:1000001",
        "tgn:7012149",
        "tgn:2000824",
        "tgn:7007255",
        "tgn:7029392"
    ],
    "tgn:id":2574119,
    "tgn:name":"Peg Fork",
    "tgn:placetype":[
        "aat:300008699"
    ]
},
  "bbox": [],
  "geometry": {"coordinates":[-82.4833,37.7667],"type":"Point"}
}