{
  "id": 2617087,
  "type": "Feature",
  "properties": {
    "tgn:hierarchy":[
        "tgn:2617087",
        "tgn:1000001",
        "tgn:7012149",
        "tgn:2001442",
        "tgn:7007566",
        "tgn:7029392"
    ],
    "tgn:id":2617087,
    "tgn:name":"Richardson Claims",
    "tgn:placetype":[
        "aat:300000390"
    ]
},
  "bbox": [],
  "geometry": {"coordinates":[-105.7833,33.5167],"type":"Point"}
}