{
  "id": 2549528,
  "type": "Feature",
  "properties": {
    "tgn:hierarchy":[
        "tgn:2549528",
        "tgn:1000001",
        "tgn:7012149",
        "tgn:2001453",
        "tgn:7007566",
        "tgn:7029392"
    ],
    "tgn:id":2549528,
    "tgn:name":"North Spring Canyon",
    "tgn:placetype":[
        "aat:300008761"
    ]
},
  "bbox": [],
  "geometry": {"coordinates":[-104.5167,35.6833],"type":"Point"}
}