{
  "id": 2234251,
  "type": "Feature",
  "properties": {
    "tgn:hierarchy":[
        "tgn:2234251",
        "tgn:1000001",
        "tgn:7012149",
        "tgn:2001302",
        "tgn:7007524",
        "tgn:7029392"
    ],
    "tgn:id":2234251,
    "tgn:name":"Chelsea Creek",
    "tgn:placetype":[
        "aat:300008706"
    ]
},
  "bbox": [],
  "geometry": {"coordinates":[-105.5333,48.35],"type":"Point"}
}