<<<<<<< HEAD
{
  "id": 2333503,
  "type": "Feature",
  "properties": {
    "tgn:hierarchy":[
        "tgn:2333503",
        "tgn:1000001",
        "tgn:2001734",
        "tgn:7012149",
        "tgn:7007712",
        "tgn:7029392"
    ],
    "tgn:id":2333503,
    "tgn:name":"Folly River",
    "tgn:placetype":[
        "aat:300008707"
    ]
},
  "bbox": [],
  "geometry": {"coordinates":[-79.9167,32.6833],"type":"Point"}
}
=======
{"geometry":{"type":"Point","coordinates":[-79.916700,32.683300]},"type":"Feature","properties":{"hierarchy":["tgn:2333503","tgn:1000001","tgn:2001734","tgn:7012149","tgn:7007712","tgn:7029392"],"placetype":["aat:300008707"],"id":2333503,"name:xx":"Folly River"}}
>>>>>>> 03f74aca74312dbeaf24d7e61306dd6a786dc3d0
