{
  "id": 2333503,
  "type": "Feature",
  "properties": {
    "tgn:hierarchy":[
        "tgn:2333503",
        "tgn:1000001",
        "tgn:2001734",
        "tgn:7012149",
        "tgn:7007712",
        "tgn:7029392"
    ],
    "tgn:id":2333503,
    "tgn:name":"Folly River",
    "tgn:placetype":[
        "aat:300008707"
    ]
},
  "bbox": [],
  "geometry": {"coordinates":[-79.9167,32.6833],"type":"Point"}
}