<<<<<<< HEAD
{
  "id": 2150594,
  "type": "Feature",
  "properties": {
    "tgn:hierarchy":[
        "tgn:2150594",
        "tgn:2001423",
        "tgn:1000001",
        "tgn:7012149",
        "tgn:7007564",
        "tgn:7029392"
    ],
    "tgn:id":2150594,
    "tgn:name":"Basin, The",
    "tgn:placetype":[
        "aat:300132316"
    ]
},
  "bbox": [],
  "geometry": {"coordinates":[-71.2667,43.6167],"type":"Point"}
}
=======
{"geometry":{"type":"Point","coordinates":[-71.266700,43.616700]},"type":"Feature","properties":{"hierarchy":["tgn:2150594","tgn:2001423","tgn:1000001","tgn:7012149","tgn:7007564","tgn:7029392"],"placetype":["aat:300132316"],"id":2150594,"name:xx":"Basin, The"}}
>>>>>>> 03f74aca74312dbeaf24d7e61306dd6a786dc3d0
