{
  "id": 7572018,
  "type": "Feature",
  "properties": {
    "tgn:hierarchy":[
        "tgn:7572018",
        "tgn:1009838",
        "tgn:7000204",
        "tgn:1000004",
        "tgn:7000198",
        "tgn:7029392"
    ],
    "tgn:id":7572018,
    "tgn:name:en":"Flat Island",
    "tgn:placetype":[
        "aat:300008791"
    ]
},
  "bbox": [],
  "geometry": {"coordinates":[92.683333,12.533333],"type":"Point"}
}