{
  "id": 1125294,
  "type": "Feature",
  "properties": {
    "tgn:hierarchy":[
        "tgn:1125294",
        "tgn:1000004",
        "tgn:7000198",
        "tgn:1001977",
        "tgn:7029392"
    ],
    "tgn:id":1125294,
    "tgn:name":"K\u0101li\u0101ghaj",
    "tgn:placetype":[
        "aat:300008707"
    ]
},
  "bbox": [],
  "geometry": {"coordinates":[87.8333,22.1667],"type":"Point"}
}