{
  "id": 2138638,
  "type": "Feature",
  "properties": {
    "tgn:hierarchy":[
        "tgn:2138638",
        "tgn:1000001",
        "tgn:7012149",
        "tgn:2001515",
        "tgn:7007709",
        "tgn:7029392"
    ],
    "tgn:id":2138638,
    "tgn:name":"Ash Flat Branch",
    "tgn:placetype":[
        "aat:300008699"
    ]
},
  "bbox": [],
  "geometry": {"coordinates":[-83.4833,35.0667],"type":"Point"}
}