{
  "id": 2606845,
  "type": "Feature",
  "properties": {
    "tgn:hierarchy":[
        "tgn:2606845",
        "tgn:1000001",
        "tgn:7012149",
        "tgn:2002383",
        "tgn:7007923",
        "tgn:7029392"
    ],
    "tgn:id":2606845,
    "tgn:name":"Ramsey Peak",
    "tgn:placetype":[
        "aat:300008798"
    ]
},
  "bbox": [],
  "geometry": {"coordinates":[-109.25,41.1667],"type":"Point"}
}