{
  "id": 2748642,
  "type": "Feature",
  "properties": {
    "tgn:hierarchy":[
        "tgn:2748642",
        "tgn:1000001",
        "tgn:7012149",
        "tgn:2000471",
        "tgn:7007250",
        "tgn:7029392"
    ],
    "tgn:id":2748642,
    "tgn:name":"Walker Reservoir",
    "tgn:placetype":[
        "aat:300006191"
    ]
},
  "bbox": [],
  "geometry": {"coordinates":[-115.1833,43.0167],"type":"Point"}
}