{
  "id": 7289744,
  "type": "Feature",
  "properties": {
    "tgn:hierarchy":[
        "tgn:7289744",
        "tgn:1001708",
        "tgn:1000049",
        "tgn:1000002",
        "tgn:7029392"
    ],
    "tgn:id":7289744,
    "tgn:name":"El Castillo",
    "tgn:placetype":[
        "aat:300000206"
    ]
},
  "bbox": [],
  "geometry": {"coordinates":[-70.633333,-33.583333],"type":"Point"}
}