{
  "id": 2440618,
  "type": "Feature",
  "properties": {
    "tgn:hierarchy":[
        "tgn:2440618",
        "tgn:1000001",
        "tgn:7012149",
        "tgn:1002921",
        "tgn:7007526",
        "tgn:7029392"
    ],
    "tgn:id":2440618,
    "tgn:name":"Knickerbocker Mine",
    "tgn:placetype":[
        "aat:300000390"
    ]
},
  "bbox": [],
  "geometry": {"coordinates":[-119.65,39.2667],"type":"Point"}
}