{
  "id": 7203541,
  "type": "Feature",
  "properties": {
    "tgn:hierarchy":[
        "tgn:7203541",
        "tgn:1000003",
        "tgn:7003677",
        "tgn:7000084",
        "tgn:7029392"
    ],
    "tgn:id":7203541,
    "tgn:name":"Br\u00fcninghausen",
    "tgn:placetype":[
        "aat:300000206"
    ]
},
  "bbox": [],
  "geometry": {"coordinates":[7.533333,51.166667],"type":"Point"}
}