{
  "id": 1063475,
  "type": "Feature",
  "properties": {
    "tgn:hierarchy":[
        "tgn:1063475",
        "tgn:1000003",
        "tgn:7003774",
        "tgn:1000097",
        "tgn:7029392"
    ],
    "tgn:id":1063475,
    "tgn:name":"Polcirkeln",
    "tgn:placetype":[
        "aat:300008347"
    ]
},
  "bbox": [],
  "geometry": {"coordinates":[21.0167,66.5667],"type":"Point"}
}