{
  "id": 7536330,
  "type": "Feature",
  "properties": {
    "tgn:hierarchy":[
        "tgn:7536330",
        "tgn:7001242",
        "tgn:7016833",
        "tgn:7029392"
    ],
    "tgn:id":7536330,
    "tgn:name:en":"Ghur\u0101b\u012b, Jabal",
    "tgn:placetype":[
        "aat:300008777"
    ]
},
  "bbox": [],
  "geometry": {"coordinates":[29.037242,28.486177],"type":"Point"}
}