{
  "id": 2327909,
  "type": "Feature",
  "properties": {
    "tgn:hierarchy":[
        "tgn:2327909",
        "tgn:1000001",
        "tgn:2000470",
        "tgn:7012149",
        "tgn:7007250",
        "tgn:7029392"
    ],
    "tgn:id":2327909,
    "tgn:name":"Fish Lake",
    "tgn:placetype":[
        "aat:300008680"
    ]
},
  "bbox": [],
  "geometry": {"coordinates":[-114.9167,44.4333],"type":"Point"}
}