<<<<<<< HEAD
{
  "id": 7365180,
  "type": "Feature",
  "properties": {
    "tgn:hierarchy":[
        "tgn:7365180",
        "tgn:7005580",
        "tgn:1000001",
        "tgn:7005560",
        "tgn:7029392"
    ],
    "tgn:id":7365180,
    "tgn:name":"Francisco Le\u00f3n",
    "tgn:placetype":[
        "aat:300008347"
    ]
},
  "bbox": [],
  "geometry": {"coordinates":[-93.216667,17.3],"type":"Point"}
}
=======
{"geometry":{"type":"Point","coordinates":[-93.216667,17.300000]},"type":"Feature","properties":{"hierarchy":["tgn:7365180","tgn:7005580","tgn:1000001","tgn:7005560","tgn:7029392"],"placetype":["aat:300008347"],"id":7365180,"name:xx":"Francisco Le\u00f3n"}}
>>>>>>> 03f74aca74312dbeaf24d7e61306dd6a786dc3d0
