<<<<<<< HEAD
{
  "id": 7354989,
  "type": "Feature",
  "properties": {
    "tgn:hierarchy":[
        "tgn:7354989",
        "tgn:1000001",
        "tgn:1001960",
        "tgn:7005560",
        "tgn:7029392"
    ],
    "tgn:id":7354989,
    "tgn:name":"Ciaris, Estero",
    "tgn:placetype":[
        "aat:300008679"
    ]
},
  "bbox": [],
  "geometry": {"coordinates":[-109.983333,27.016667],"type":"Point"}
}
=======
{"geometry":{"type":"Point","coordinates":[-109.983333,27.016667]},"type":"Feature","properties":{"hierarchy":["tgn:7354989","tgn:1000001","tgn:1001960","tgn:7005560","tgn:7029392"],"placetype":["aat:300008679"],"id":7354989,"name:xx":"Ciaris, Estero"}}
>>>>>>> 03f74aca74312dbeaf24d7e61306dd6a786dc3d0
