<<<<<<< HEAD
{
  "id": 7177795,
  "type": "Feature",
  "properties": {
    "tgn:hierarchy":[
        "tgn:7177795",
        "tgn:7003669",
        "tgn:1000003",
        "tgn:7000084",
        "tgn:7029392"
    ],
    "tgn:id":7177795,
    "tgn:name":"Haitzen",
    "tgn:placetype":[
        "aat:300008347"
    ]
},
  "bbox": [],
  "geometry": {"coordinates":[10.2,47.883333],"type":"Point"}
}
=======
{"geometry":{"type":"Point","coordinates":[10.200000,47.883333]},"type":"Feature","properties":{"hierarchy":["tgn:7177795","tgn:7003669","tgn:1000003","tgn:7000084","tgn:7029392"],"placetype":["aat:300008347"],"id":7177795,"name:xx":"Haitzen"}}
>>>>>>> 03f74aca74312dbeaf24d7e61306dd6a786dc3d0
