{
  "id": 2226648,
  "type": "Feature",
  "properties": {
    "tgn:hierarchy":[
        "tgn:2226648",
        "tgn:1000001",
        "tgn:7012149",
        "tgn:7007157",
        "tgn:1002956",
        "tgn:7029392"
    ],
    "tgn:id":2226648,
    "tgn:name":"Catron Ditch",
    "tgn:placetype":[
        "aat:300006075"
    ]
},
  "bbox": [],
  "geometry": {"coordinates":[-119.15,36.3167],"type":"Point"}
}