{
  "id": 7465662,
  "type": "Feature",
  "properties": {
    "tgn:hierarchy":[
        "tgn:7465662",
        "tgn:7002444",
        "tgn:1000003",
        "tgn:7008076",
        "tgn:7008591",
        "tgn:7029392"
    ],
    "tgn:id":7465662,
    "tgn:name:en":"Bogside Station",
    "tgn:placetype":[
        "aat:300007783"
    ]
},
  "bbox": [],
  "geometry": {"coordinates":[-3.65,56.083333],"type":"Point"}
}