{
  "id": 7031871,
  "type": "Feature",
  "properties": {
    "tgn:hierarchy":[
        "tgn:7031871",
        "tgn:7011918",
        "tgn:7002445",
        "tgn:1000003",
        "tgn:7026489",
        "tgn:7008591",
        "tgn:7029392"
    ],
    "tgn:id":7031871,
    "tgn:name":"Southcote",
    "tgn:placetype":[
        "aat:300008347",
        "aat:300000874"
    ]
},
  "bbox": [],
  "geometry": {"coordinates":[-1.15,51.4333],"type":"Point"}
}