{
  "id": 2614942,
  "type": "Feature",
  "properties": {
    "tgn:hierarchy":[
        "tgn:2614942",
        "tgn:1000001",
        "tgn:7012149",
        "tgn:2001619",
        "tgn:7007706",
        "tgn:7029392"
    ],
    "tgn:id":2614942,
    "tgn:name":"Renrock",
    "tgn:placetype":[
        "aat:300008347"
    ]
},
  "bbox": [],
  "geometry": {"coordinates":[-81.6667,39.75],"type":"Point"}
}