<<<<<<< HEAD
{
  "id": 2254522,
  "type": "Feature",
  "properties": {
    "tgn:hierarchy":[
        "tgn:2254522",
        "tgn:1000001",
        "tgn:2002255",
        "tgn:7012149",
        "tgn:7013961",
        "tgn:7029392"
    ],
    "tgn:id":2254522,
    "tgn:name":"Coon Fork",
    "tgn:placetype":[
        "aat:300008699"
    ]
},
  "bbox": [],
  "geometry": {"coordinates":[-81.6333,38.1167],"type":"Point"}
}
=======
{"geometry":{"type":"Point","coordinates":[-81.633300,38.116700]},"type":"Feature","properties":{"hierarchy":["tgn:2254522","tgn:1000001","tgn:2002255","tgn:7012149","tgn:7013961","tgn:7029392"],"placetype":["aat:300008699"],"id":2254522,"name:xx":"Coon Fork"}}
>>>>>>> 03f74aca74312dbeaf24d7e61306dd6a786dc3d0
