{
  "id": 7517003,
  "type": "Feature",
  "properties": {
    "tgn:hierarchy":[
        "tgn:7517003",
        "tgn:1009227",
        "tgn:1000226",
        "tgn:7016729",
        "tgn:1000006",
        "tgn:7029392"
    ],
    "tgn:id":7517003,
    "tgn:name:en":"Mill Stream",
    "tgn:placetype":[
        "aat:300008699"
    ]
},
  "bbox": [],
  "geometry": {"coordinates":[173.866667,-41.516667],"type":"Point"}
}