{
  "id": 2431079,
  "type": "Feature",
  "properties": {
    "tgn:hierarchy":[
        "tgn:2431079",
        "tgn:1000001",
        "tgn:7012149",
        "tgn:2001067",
        "tgn:7007521",
        "tgn:7029392"
    ],
    "tgn:id":2431079,
    "tgn:name":"Kangas Lake",
    "tgn:placetype":[
        "aat:300008680"
    ]
},
  "bbox": [],
  "geometry": {"coordinates":[-91.8333,47.75],"type":"Point"}
}