<<<<<<< HEAD
{
  "id": 2155068,
  "type": "Feature",
  "properties": {
    "tgn:hierarchy":[
        "tgn:2155068",
        "tgn:1000001",
        "tgn:7012149",
        "tgn:2000974",
        "tgn:7007520",
        "tgn:7029392"
    ],
    "tgn:id":2155068,
    "tgn:name":"Bear Lake",
    "tgn:placetype":[
        "aat:300008680"
    ]
},
  "bbox": [],
  "geometry": {"coordinates":[-86.15,44.4333],"type":"Point"}
}
=======
{"geometry":{"type":"Point","coordinates":[-86.150000,44.433300]},"type":"Feature","properties":{"hierarchy":["tgn:2155068","tgn:1000001","tgn:7012149","tgn:2000974","tgn:7007520","tgn:7029392"],"placetype":["aat:300008680"],"id":2155068,"name:xx":"Bear Lake"}}
>>>>>>> 03f74aca74312dbeaf24d7e61306dd6a786dc3d0
