{
  "id": 2730925,
  "type": "Feature",
  "properties": {
    "tgn:hierarchy":[
        "tgn:2730925",
        "tgn:7002659",
        "tgn:1000001",
        "tgn:7012149",
        "tgn:2000063",
        "tgn:7029392"
    ],
    "tgn:id":2730925,
    "tgn:name":"Tubbs Branch",
    "tgn:placetype":[
        "aat:300008699"
    ]
},
  "bbox": [],
  "geometry": {"coordinates":[-87.1667,33.9167],"type":"Point"}
}