{
  "id": 7280215,
  "type": "Feature",
  "properties": {
    "tgn:hierarchy":[
        "tgn:7280215",
        "tgn:7002464",
        "tgn:1000049",
        "tgn:1000002",
        "tgn:7029392"
    ],
    "tgn:id":7280215,
    "tgn:name":"Quisma, Quebrada de",
    "tgn:placetype":[
        "aat:300266554",
        "aat:300008699"
    ]
},
  "bbox": [],
  "geometry": {"coordinates":[-69.416667,-20.516667],"type":"Point"}
}