{
  "id": 2577563,
  "type": "Feature",
  "properties": {
    "tgn:hierarchy":[
        "tgn:2577563",
        "tgn:1000001",
        "tgn:2002107",
        "tgn:7012149",
        "tgn:7007827",
        "tgn:7029392"
    ],
    "tgn:id":2577563,
    "tgn:name":"Peterson Hollow",
    "tgn:placetype":[
        "aat:300008761"
    ]
},
  "bbox": [],
  "geometry": {"coordinates":[-110.6833,39.8833],"type":"Point"}
}