{
  "id": 2300873,
  "type": "Feature",
  "properties": {
    "tgn:hierarchy":[
        "tgn:2300873",
        "tgn:1000001",
        "tgn:7012149",
        "tgn:2002189",
        "tgn:7007919",
        "tgn:7029392"
    ],
    "tgn:id":2300873,
    "tgn:name":"Duncan Mill",
    "tgn:placetype":[
        "aat:300008347"
    ]
},
  "bbox": [],
  "geometry": {"coordinates":[-82.6333,36.75],"type":"Point"}
}