{
  "id": 2302595,
  "type": "Feature",
  "properties": {
    "tgn:hierarchy":[
        "tgn:2302595",
        "tgn:1000001",
        "tgn:2000923",
        "tgn:7012149",
        "tgn:7007515",
        "tgn:7029392"
    ],
    "tgn:id":2302595,
    "tgn:name":"Dutton Pond",
    "tgn:placetype":[
        "aat:300008680"
    ]
},
  "bbox": [],
  "geometry": {"coordinates":[-69.4833,44.4833],"type":"Point"}
}