{
  "id": 2353539,
  "type": "Feature",
  "properties": {
    "tgn:hierarchy":[
        "tgn:2353539",
        "tgn:1000001",
        "tgn:7012149",
        "tgn:2000491",
        "tgn:7007250",
        "tgn:7029392"
    ],
    "tgn:id":2353539,
    "tgn:name":"Gold Hill",
    "tgn:placetype":[
        "aat:300008798"
    ]
},
  "bbox": [],
  "geometry": {"coordinates":[-115.8167,47.4167],"type":"Point"}
}