{
  "id": 7566026,
  "type": "Feature",
  "properties": {
    "tgn:hierarchy":[
        "tgn:7566026",
        "tgn:1000004",
        "tgn:7000198",
        "tgn:7016722",
        "tgn:7029392"
    ],
    "tgn:id":7566026,
    "tgn:name:en":"Purwa Garhi",
    "tgn:placetype":[
        "aat:300008347"
    ]
},
  "bbox": [],
  "geometry": {"coordinates":[79.720205,26.825177],"type":"Point"}
}