<<<<<<< HEAD
{
  "id": 2156683,
  "type": "Feature",
  "properties": {
    "tgn:hierarchy":[
        "tgn:2156683",
        "tgn:1000001",
        "tgn:7006451",
        "tgn:2000092",
        "tgn:7012149",
        "tgn:7029392"
    ],
    "tgn:id":2156683,
    "tgn:name":"Beasley Lake",
    "tgn:placetype":[
        "aat:300008680"
    ]
},
  "bbox": [],
  "geometry": {"coordinates":[-111.7,35.6],"type":"Point"}
}
=======
{"geometry":{"type":"Point","coordinates":[-111.700000,35.600000]},"type":"Feature","properties":{"hierarchy":["tgn:2156683","tgn:1000001","tgn:7006451","tgn:2000092","tgn:7012149","tgn:7029392"],"placetype":["aat:300008680"],"id":2156683,"name:xx":"Beasley Lake"}}
>>>>>>> 03f74aca74312dbeaf24d7e61306dd6a786dc3d0
