{
  "id": 7047085,
  "type": "Feature",
  "properties": {
    "tgn:hierarchy":[
        "tgn:7047085",
        "tgn:7003006",
        "tgn:1000003",
        "tgn:7002997",
        "tgn:1000080",
        "tgn:7029392"
    ],
    "tgn:id":7047085,
    "tgn:name":"Favaro Veneto",
    "tgn:placetype":[
        "aat:300008347"
    ]
},
  "bbox": [],
  "geometry": {"coordinates":[12.283333,45.498889],"type":"Point"}
}