{
  "id": 2222591,
  "type": "Feature",
  "properties": {
    "tgn:hierarchy":[
        "tgn:2222591",
        "tgn:1000001",
        "tgn:7012149",
        "tgn:7007157",
        "tgn:1002710",
        "tgn:7029392"
    ],
    "tgn:id":2222591,
    "tgn:name":"Carpenter Valley",
    "tgn:placetype":[
        "aat:300008761"
    ]
},
  "bbox": [],
  "geometry": {"coordinates":[-120.3167,39.3833],"type":"Point"}
}