<<<<<<< HEAD
{
  "id": 7170073,
  "type": "Feature",
  "properties": {
    "tgn:hierarchy":[
        "tgn:7170073",
        "tgn:7003669",
        "tgn:1000003",
        "tgn:7000084",
        "tgn:7029392"
    ],
    "tgn:id":7170073,
    "tgn:name":"Herbstau",
    "tgn:placetype":[
        "aat:300386990"
    ]
},
  "bbox": [],
  "geometry": {"coordinates":[12.183333,49.7],"type":"Point"}
}
=======
{"geometry":{"type":"Point","coordinates":[12.183333,49.700000]},"type":"Feature","properties":{"hierarchy":["tgn:7170073","tgn:7003669","tgn:1000003","tgn:7000084","tgn:7029392"],"placetype":["aat:300386990"],"id":7170073,"name:xx":"Herbstau"}}
>>>>>>> 03f74aca74312dbeaf24d7e61306dd6a786dc3d0
