<<<<<<< HEAD
{
  "id": 2407838,
  "type": "Feature",
  "properties": {
    "tgn:hierarchy":[
        "tgn:2407838",
        "tgn:1000001",
        "tgn:7012149",
        "tgn:2002304",
        "tgn:7013961",
        "tgn:7029392"
    ],
    "tgn:id":2407838,
    "tgn:name":"Hurricane Branch",
    "tgn:placetype":[
        "aat:300008699"
    ]
},
  "bbox": [],
  "geometry": {"coordinates":[-81.5333,37.5167],"type":"Point"}
}
=======
{"geometry":{"type":"Point","coordinates":[-81.533300,37.516700]},"type":"Feature","properties":{"hierarchy":["tgn:2407838","tgn:1000001","tgn:7012149","tgn:2002304","tgn:7013961","tgn:7029392"],"placetype":["aat:300008699"],"id":2407838,"name:xx":"Hurricane Branch"}}
>>>>>>> 03f74aca74312dbeaf24d7e61306dd6a786dc3d0
