{
  "id": 2340306,
  "type": "Feature",
  "properties": {
    "tgn:hierarchy":[
        "tgn:2340306",
        "tgn:1000001",
        "tgn:7012149",
        "tgn:7007922",
        "tgn:7029392"
    ],
    "tgn:id":2340306,
    "tgn:name":"French Creek",
    "tgn:placetype":[
        "aat:300008706"
    ]
},
  "bbox": [],
  "geometry": {"coordinates":[-89.3167,43.65],"type":"Point"}
}