{
  "id": 2634969,
  "type": "Feature",
  "properties": {
    "tgn:hierarchy":[
        "tgn:2634969",
        "tgn:1000001",
        "tgn:7012149",
        "tgn:2001077",
        "tgn:7007521",
        "tgn:7029392"
    ],
    "tgn:id":2634969,
    "tgn:name":"Ryans Bay",
    "tgn:placetype":[
        "aat:300132316"
    ]
},
  "bbox": [],
  "geometry": {"coordinates":[-92.4667,44.1833],"type":"Point"}
}