{
  "id": 2262041,
  "type": "Feature",
  "properties": {
    "tgn:hierarchy":[
        "tgn:2262041",
        "tgn:1000001",
        "tgn:7012149",
        "tgn:2002180",
        "tgn:7007919",
        "tgn:7029392"
    ],
    "tgn:id":2262041,
    "tgn:name":"Cow Branch",
    "tgn:placetype":[
        "aat:300008699"
    ]
},
  "bbox": [],
  "geometry": {"coordinates":[-79.65,36.5667],"type":"Point"}
}