{
  "id": 7300287,
  "type": "Feature",
  "properties": {
    "tgn:hierarchy":[
        "tgn:7300287",
        "tgn:7002826",
        "tgn:7001158",
        "tgn:1000003",
        "tgn:1000095",
        "tgn:7029392"
    ],
    "tgn:id":7300287,
    "tgn:name":"Valdeladehesa, Arroyo de",
    "tgn:placetype":[
        "aat:300266554",
        "aat:300008699"
    ]
},
  "bbox": [],
  "geometry": {"coordinates":[-5.466667,42.15],"type":"Point"}
}