{
  "id": 7215800,
  "type": "Feature",
  "properties": {
    "tgn:hierarchy":[
        "tgn:7215800",
        "tgn:1000003",
        "tgn:7003688",
        "tgn:7000084",
        "tgn:7029392"
    ],
    "tgn:id":7215800,
    "tgn:name":"Alte Kirche",
    "tgn:placetype":[
        "aat:300008347"
    ]
},
  "bbox": [],
  "geometry": {"coordinates":[8.616667,54.516667],"type":"Point"}
}