{
  "id": 2363214,
  "type": "Feature",
  "properties": {
    "tgn:hierarchy":[
        "tgn:2363214",
        "tgn:7002659",
        "tgn:1000001",
        "tgn:7012149",
        "tgn:2000046",
        "tgn:7029392"
    ],
    "tgn:id":2363214,
    "tgn:name":"Green Branch",
    "tgn:placetype":[
        "aat:300008699"
    ]
},
  "bbox": [],
  "geometry": {"coordinates":[-87.8167,34.25],"type":"Point"}
}