{
  "id": 1006943,
  "type": "Feature",
  "properties": {
    "tgn:hierarchy":[
        "tgn:1006943",
        "tgn:7000406",
        "tgn:1000004",
        "tgn:1000110",
        "tgn:7029392"
    ],
    "tgn:id":1006943,
    "tgn:name":"Delft Island",
    "tgn:placetype":[
        "aat:300008791"
    ]
},
  "bbox": [],
  "geometry": {"coordinates":[79.6667,9.5333],"type":"Point"}
}