{
  "id": 2661498,
  "type": "Feature",
  "properties": {
    "tgn:hierarchy":[
        "tgn:2661498",
        "tgn:7006450",
        "tgn:1000001",
        "tgn:7012149",
        "tgn:2124014",
        "tgn:7029392"
    ],
    "tgn:id":2661498,
    "tgn:name":"Shovel Creek",
    "tgn:placetype":[
        "aat:300008706"
    ]
},
  "bbox": [],
  "geometry": {"coordinates":[-157.7833,66.3667],"type":"Point"}
}