{
  "id": 7004029,
  "type": "Feature",
  "properties": {
    "tgn:hierarchy":[
        "tgn:7004029",
        "tgn:1003432",
        "tgn:1000003",
        "tgn:7003240",
        "tgn:1000080",
        "tgn:7029392"
    ],
    "tgn:id":7004029,
    "tgn:name":"Fermo",
    "tgn:placetype":[
        "aat:300387236",
        "aat:300387277",
        "aat:300008347",
        "aat:300387218",
        "aat:300387315",
        "aat:300387308",
        "aat:300008375",
        "aat:300391516",
        "aat:300020533"
    ]
},
  "bbox": [],
  "geometry": {"coordinates":[13.716667,43.15],"type":"Point"}
}