{
  "id": 2603517,
  "type": "Feature",
  "properties": {
    "tgn:hierarchy":[
        "tgn:2603517",
        "tgn:2001467",
        "tgn:1000001",
        "tgn:7012149",
        "tgn:7007709",
        "tgn:7029392"
    ],
    "tgn:id":2603517,
    "tgn:name":"Queen Ridge",
    "tgn:placetype":[
        "aat:300266640"
    ]
},
  "bbox": [],
  "geometry": {"coordinates":[-81.5167,36.3333],"type":"Point"}
}