{
  "id": 2313439,
  "type": "Feature",
  "properties": {
    "tgn:hierarchy":[
        "tgn:2313439",
        "tgn:7002659",
        "tgn:1000001",
        "tgn:7012149",
        "tgn:2000036",
        "tgn:7029392"
    ],
    "tgn:id":2313439,
    "tgn:name":"Eldorda Number 2 Mine",
    "tgn:placetype":[
        "aat:300000390"
    ]
},
  "bbox": [],
  "geometry": {"coordinates":[-86.8333,33.6333],"type":"Point"}
}