<<<<<<< HEAD
{
  "id": 2406680,
  "type": "Feature",
  "properties": {
    "tgn:hierarchy":[
        "tgn:2406680",
        "tgn:1000001",
        "tgn:7012149",
        "tgn:2002270",
        "tgn:7013961",
        "tgn:7029392"
    ],
    "tgn:id":2406680,
    "tgn:name":"Hunt Fork",
    "tgn:placetype":[
        "aat:300008699"
    ]
},
  "bbox": [],
  "geometry": {"coordinates":[-81.4833,38.5333],"type":"Point"}
}
=======
{"geometry":{"type":"Point","coordinates":[-81.483300,38.533300]},"type":"Feature","properties":{"hierarchy":["tgn:2406680","tgn:1000001","tgn:7012149","tgn:2002270","tgn:7013961","tgn:7029392"],"placetype":["aat:300008699"],"id":2406680,"name:xx":"Hunt Fork"}}
>>>>>>> 03f74aca74312dbeaf24d7e61306dd6a786dc3d0
