{
  "id": 2743719,
  "type": "Feature",
  "properties": {
    "tgn:hierarchy":[
        "tgn:2743719",
        "tgn:1000001",
        "tgn:7016172",
        "tgn:7012149",
        "tgn:2000163",
        "tgn:7029392"
    ],
    "tgn:id":2743719,
    "tgn:name":"Vaughts Reservoir",
    "tgn:placetype":[
        "aat:300006191"
    ]
},
  "bbox": [],
  "geometry": {"coordinates":[-91.6333,34.8333],"type":"Point"}
}