{
  "id": 2312698,
  "type": "Feature",
  "properties": {
    "tgn:hierarchy":[
        "tgn:2312698",
        "tgn:1000001",
        "tgn:2001416",
        "tgn:7012149",
        "tgn:7007526",
        "tgn:7029392"
    ],
    "tgn:id":2312698,
    "tgn:name":"El Cortez Mine",
    "tgn:placetype":[
        "aat:300000390"
    ]
},
  "bbox": [],
  "geometry": {"coordinates":[-115.7333,38.0333],"type":"Point"}
}