{
  "id": 2617882,
  "type": "Feature",
  "properties": {
    "tgn:hierarchy":[
        "tgn:2617882",
        "tgn:1000001",
        "tgn:7012149",
        "tgn:2002248",
        "tgn:7007920",
        "tgn:7029392"
    ],
    "tgn:id":2617882,
    "tgn:name":"Ridge Lake",
    "tgn:placetype":[
        "aat:300008680"
    ]
},
  "bbox": [],
  "geometry": {"coordinates":[-117.2833,48.6167],"type":"Point"}
}