{
  "id": 7555319,
  "type": "Feature",
  "properties": {
    "tgn:hierarchy":[
        "tgn:7555319",
        "tgn:1000004",
        "tgn:7000198",
        "tgn:7016788",
        "tgn:7029392"
    ],
    "tgn:id":7555319,
    "tgn:name:en":"Mithri Nadi",
    "tgn:placetype":[
        "aat:300008699"
    ]
},
  "bbox": [],
  "geometry": {"coordinates":[73.439445,25.764446],"type":"Point"}
}