{
  "id": 6003875,
  "type": "Feature",
  "properties": {
    "tgn:hierarchy":[
        "tgn:6003875",
        "tgn:1000976",
        "tgn:1000004",
        "tgn:7000893",
        "tgn:1000120",
        "tgn:7029392"
    ],
    "tgn:id":6003875,
    "tgn:name":"Miharu",
    "tgn:placetype":[
        "aat:300008347"
    ]
},
  "bbox": [],
  "geometry": {"coordinates":[140.4833,37.4167],"type":"Point"}
}