{
  "id": 2353986,
  "type": "Feature",
  "properties": {
    "tgn:hierarchy":[
        "tgn:2353986",
        "tgn:1000001",
        "tgn:2001417",
        "tgn:7012149",
        "tgn:7007526",
        "tgn:7029392"
    ],
    "tgn:id":2353986,
    "tgn:name":"Golden Bomber Mine",
    "tgn:placetype":[
        "aat:300000390"
    ]
},
  "bbox": [],
  "geometry": {"coordinates":[-118.4333,38.4833],"type":"Point"}
}