{
  "id": 7189813,
  "type": "Feature",
  "properties": {
    "tgn:hierarchy":[
        "tgn:7189813",
        "tgn:7003669",
        "tgn:1000003",
        "tgn:7000084",
        "tgn:7029392"
    ],
    "tgn:id":7189813,
    "tgn:name":"Escheldorf",
    "tgn:placetype":[
        "aat:300008347"
    ]
},
  "bbox": [],
  "geometry": {"coordinates":[12.133333,49.85],"type":"Point"}
}