{
  "id": 7400988,
  "type": "Feature",
  "properties": {
    "tgn:hierarchy":[
        "tgn:7400988",
        "tgn:1000001",
        "tgn:7005599",
        "tgn:7005560",
        "tgn:7029392"
    ],
    "tgn:id":7400988,
    "tgn:name":"El Panal",
    "tgn:placetype":[
        "aat:300008347"
    ]
},
  "bbox": [],
  "geometry": {"coordinates":[-97.233333,20.766667],"type":"Point"}
}