{
  "id": 2357743,
  "type": "Feature",
  "properties": {
    "tgn:hierarchy":[
        "tgn:2357743",
        "tgn:1000001",
        "tgn:7012149",
        "tgn:1002376",
        "tgn:7007252",
        "tgn:7029392"
    ],
    "tgn:id":2357743,
    "tgn:name":"Grace Run",
    "tgn:placetype":[
        "aat:300008699"
    ]
},
  "bbox": [],
  "geometry": {"coordinates":[-85.7833,38.3167],"type":"Point"}
}