<<<<<<< HEAD
{
  "id": 2769294,
  "type": "Feature",
  "properties": {
    "tgn:hierarchy":[
        "tgn:2769294",
        "tgn:7006450",
        "tgn:1000001",
        "tgn:7012149",
        "tgn:7029392"
    ],
    "tgn:id":2769294,
    "tgn:name":"Wickersham Creek",
    "tgn:placetype":[
        "aat:300008706"
    ]
},
  "bbox": [],
  "geometry": {"coordinates":[-148.0333,65.2],"type":"Point"}
}
=======
{"geometry":{"type":"Point","coordinates":[-148.033300,65.200000]},"type":"Feature","properties":{"hierarchy":["tgn:2769294","tgn:7006450","tgn:1000001","tgn:7012149","tgn:7029392"],"placetype":["aat:300008706"],"id":2769294,"name:xx":"Wickersham Creek"}}
>>>>>>> 03f74aca74312dbeaf24d7e61306dd6a786dc3d0
