{
  "id": 2545249,
  "type": "Feature",
  "properties": {
    "tgn:hierarchy":[
        "tgn:2545249",
        "tgn:1000001",
        "tgn:7012149",
        "tgn:2000181",
        "tgn:7007157",
        "tgn:7029392"
    ],
    "tgn:id":2545249,
    "tgn:name":"North Fork Ah Pah Creek",
    "tgn:placetype":[
        "aat:300008706"
    ]
},
  "bbox": [],
  "geometry": {"coordinates":[-124.0167,41.4333],"type":"Point"}
}