<<<<<<< HEAD
{
  "id": 7354374,
  "type": "Feature",
  "properties": {
    "tgn:hierarchy":[
        "tgn:7354374",
        "tgn:7005581",
        "tgn:1000001",
        "tgn:7005560",
        "tgn:7029392"
    ],
    "tgn:id":7354374,
    "tgn:name":"Chuchupate, Sierra del",
    "tgn:placetype":[
        "aat:300008795"
    ]
},
  "bbox": [],
  "geometry": {"coordinates":[-108.8,28.283333],"type":"Point"}
}
=======
{"geometry":{"type":"Point","coordinates":[-108.800000,28.283333]},"type":"Feature","properties":{"hierarchy":["tgn:7354374","tgn:7005581","tgn:1000001","tgn:7005560","tgn:7029392"],"placetype":["aat:300008795"],"id":7354374,"name:xx":"Chuchupate, Sierra del"}}
>>>>>>> 03f74aca74312dbeaf24d7e61306dd6a786dc3d0
