<<<<<<< HEAD
{
  "id": 7475884,
  "type": "Feature",
  "properties": {
    "tgn:hierarchy":[
        "tgn:7475884",
        "tgn:7488858",
        "tgn:1000004",
        "tgn:1000141",
        "tgn:7029392"
    ],
    "tgn:id":7475884,
    "tgn:name":"Xiabu",
    "tgn:placetype":[
        "aat:300008347"
    ]
},
  "bbox": [],
  "geometry": {"coordinates":[120.6664,23.8303],"type":"Point"}
}
=======
{"geometry":{"type":"Point","coordinates":[120.666400,23.830300]},"type":"Feature","properties":{"hierarchy":["tgn:7475884","tgn:7488858","tgn:1000004","tgn:1000141","tgn:7029392"],"placetype":["aat:300008347"],"id":7475884,"name:xx":"Xiabu"}}
>>>>>>> 03f74aca74312dbeaf24d7e61306dd6a786dc3d0
