{
  "id": 2219267,
  "type": "Feature",
  "properties": {
    "tgn:hierarchy":[
        "tgn:2219267",
        "tgn:1000001",
        "tgn:7012149",
        "tgn:2001067",
        "tgn:7007521",
        "tgn:7029392"
    ],
    "tgn:id":2219267,
    "tgn:name":"Canfield Portage Bay",
    "tgn:placetype":[
        "aat:300132316"
    ]
},
  "bbox": [],
  "geometry": {"coordinates":[-92.2833,47.8667],"type":"Point"}
}