{
  "id": 1047354,
  "type": "Feature",
  "properties": {
    "tgn:hierarchy":[
        "tgn:1047354",
        "tgn:7003150",
        "tgn:1000003",
        "tgn:7003237",
        "tgn:1000080",
        "tgn:7029392"
    ],
    "tgn:id":1047354,
    "tgn:name":"Verano Brianza",
    "tgn:placetype":[
        "aat:300008347"
    ]
},
  "bbox": [],
  "geometry": {"coordinates":[9.2333,45.6833],"type":"Point"}
}