{
  "id": 2652266,
  "type": "Feature",
  "properties": {
    "tgn:hierarchy":[
        "tgn:2652266",
        "tgn:1000001",
        "tgn:7012149",
        "tgn:1003020",
        "tgn:7007920",
        "tgn:7029392"
    ],
    "tgn:id":2652266,
    "tgn:name":"Semiahmoo Spit",
    "tgn:placetype":[
        "aat:300008850"
    ]
},
  "bbox": [],
  "geometry": {"coordinates":[-122.7667,48.9833],"type":"Point"}
}