{
  "id": 2206327,
  "type": "Feature",
  "properties": {
    "tgn:hierarchy":[
        "tgn:2206327",
        "tgn:7006450",
        "tgn:1000001",
        "tgn:7012149",
        "tgn:2124005",
        "tgn:7029392"
    ],
    "tgn:id":2206327,
    "tgn:name":"Bullen Point",
    "tgn:placetype":[
        "aat:300008850"
    ]
},
  "bbox": [],
  "geometry": {"coordinates":[-146.8667,70.1833],"type":"Point"}
}