<<<<<<< HEAD
{
  "id": 7481470,
  "type": "Feature",
  "properties": {
    "tgn:hierarchy":[
        "tgn:7481470",
        "tgn:1000004",
        "tgn:7471332",
        "tgn:1000141",
        "tgn:7029392"
    ],
    "tgn:id":7481470,
    "tgn:name":"Shangyuanshan",
    "tgn:placetype":[
        "aat:300008347"
    ]
},
  "bbox": [],
  "geometry": {"coordinates":[121.055,24.779722],"type":"Point"}
}
=======
{"geometry":{"type":"Point","coordinates":[121.055000,24.779722]},"type":"Feature","properties":{"hierarchy":["tgn:7481470","tgn:1000004","tgn:7471332","tgn:1000141","tgn:7029392"],"placetype":["aat:300008347"],"id":7481470,"name:xx":"Shangyuanshan"}}
>>>>>>> 03f74aca74312dbeaf24d7e61306dd6a786dc3d0
