{
  "id": 7481470,
  "type": "Feature",
  "properties": {
    "tgn:hierarchy":[
        "tgn:7481470",
        "tgn:1000004",
        "tgn:7471332",
        "tgn:1000141",
        "tgn:7029392"
    ],
    "tgn:id":7481470,
    "tgn:name":"Shangyuanshan",
    "tgn:placetype":[
        "aat:300008347"
    ]
},
  "bbox": [],
  "geometry": {"coordinates":[121.055,24.779722],"type":"Point"}
}