{
  "id": 2667428,
  "type": "Feature",
  "properties": {
    "tgn:hierarchy":[
        "tgn:2667428",
        "tgn:1000001",
        "tgn:1002305",
        "tgn:7012149",
        "tgn:7007920",
        "tgn:7029392"
    ],
    "tgn:id":2667428,
    "tgn:name":"Skipper Creek",
    "tgn:placetype":[
        "aat:300008706"
    ]
},
  "bbox": [],
  "geometry": {"coordinates":[-122.5667,46.1667],"type":"Point"}
}