{
  "id": 1047535,
  "type": "Feature",
  "properties": {
    "tgn:hierarchy":[
        "tgn:1047535",
        "tgn:7032079",
        "tgn:1000003",
        "tgn:7003515",
        "tgn:7029392"
    ],
    "tgn:id":1047535,
    "tgn:name":"Nendeln",
    "tgn:placetype":[
        "aat:300008347",
        "aat:300387319",
        "aat:300008375"
    ]
},
  "bbox": [],
  "geometry": {"coordinates":[9.55,47.2167],"type":"Point"}
}