{
  "id": 2192499,
  "type": "Feature",
  "properties": {
    "tgn:hierarchy":[
        "tgn:2192499",
        "tgn:1000001",
        "tgn:2000922",
        "tgn:7012149",
        "tgn:7007515",
        "tgn:7029392"
    ],
    "tgn:id":2192499,
    "tgn:name":"Brandy Stream",
    "tgn:placetype":[
        "aat:300008699"
    ]
},
  "bbox": [],
  "geometry": {"coordinates":[-68.2667,45.0167],"type":"Point"}
}