{
  "id": 2659310,
  "type": "Feature",
  "properties": {
    "tgn:hierarchy":[
        "tgn:2659310",
        "tgn:1000001",
        "tgn:7006451",
        "tgn:7012149",
        "tgn:2000097",
        "tgn:7029392"
    ],
    "tgn:id":2659310,
    "tgn:name":"Shiloh Canyon",
    "tgn:placetype":[
        "aat:300008347"
    ]
},
  "bbox": [],
  "geometry": {"coordinates":[-111.8333,33.5833],"type":"Point"}
}