{
  "id": 2705729,
  "type": "Feature",
  "properties": {
    "tgn:hierarchy":[
        "tgn:2705729",
        "tgn:1000001",
        "tgn:7012149",
        "tgn:7007525",
        "tgn:7029392"
    ],
    "tgn:id":2705729,
    "tgn:name":"Sutherland Canal",
    "tgn:placetype":[
        "aat:300006075"
    ]
},
  "bbox": [],
  "geometry": {"coordinates":[-101.4667,41.15],"type":"Point"}
}