{
  "id": 7449392,
  "type": "Feature",
  "properties": {
    "tgn:hierarchy":[
        "tgn:7449392",
        "tgn:7002444",
        "tgn:1000003",
        "tgn:7008072",
        "tgn:7008591",
        "tgn:7029392"
    ],
    "tgn:id":7449392,
    "tgn:name:en":"Glentress",
    "tgn:placetype":[
        "aat:300005433"
    ]
},
  "bbox": [],
  "geometry": {"coordinates":[-3.05,55.666667],"type":"Point"}
}