{
  "id": 2640552,
  "type": "Feature",
  "properties": {
    "tgn:hierarchy":[
        "tgn:2640552",
        "tgn:1000001",
        "tgn:7012149",
        "tgn:2001452",
        "tgn:7007566",
        "tgn:7029392"
    ],
    "tgn:id":2640552,
    "tgn:name":"San Juan Power Generation Reservoir",
    "tgn:placetype":[
        "aat:300006191"
    ]
},
  "bbox": [],
  "geometry": {"coordinates":[-108.4333,36.7833],"type":"Point"}
}