{
  "id": 2444769,
  "type": "Feature",
  "properties": {
    "tgn:hierarchy":[
        "tgn:2444769",
        "tgn:1000001",
        "tgn:7012149",
        "tgn:2002357",
        "tgn:7007922",
        "tgn:7029392"
    ],
    "tgn:id":2444769,
    "tgn:name":"Legue Coulee",
    "tgn:placetype":[
        "aat:300008761"
    ]
},
  "bbox": [],
  "geometry": {"coordinates":[-91.1833,44.2333],"type":"Point"}
}