{
  "id": 7511242,
  "type": "Feature",
  "properties": {
    "tgn:hierarchy":[
        "tgn:7511242",
        "tgn:1009227",
        "tgn:1000226",
        "tgn:7016822",
        "tgn:1000006",
        "tgn:7029392"
    ],
    "tgn:id":7511242,
    "tgn:name:en":"Tucker Cove",
    "tgn:placetype":[
        "aat:300132317"
    ]
},
  "bbox": [],
  "geometry": {"coordinates":[169.116667,-52.55],"type":"Point"}
}