{
  "id": 7546275,
  "type": "Feature",
  "properties": {
    "tgn:hierarchy":[
        "tgn:7546275",
        "tgn:1000004",
        "tgn:7000198",
        "tgn:1003539",
        "tgn:7029392"
    ],
    "tgn:id":7546275,
    "tgn:name:en":"Bataw",
    "tgn:placetype":[
        "aat:300008347"
    ]
},
  "bbox": [],
  "geometry": {"coordinates":[92.243533,25.230198],"type":"Point"}
}