{
  "id": 7238000,
  "type": "Feature",
  "properties": {
    "tgn:hierarchy":[
        "tgn:7238000",
        "tgn:7007877",
        "tgn:1000003",
        "tgn:1000063",
        "tgn:4012014",
        "tgn:7029392"
    ],
    "tgn:id":7238000,
    "tgn:name":"Grand Breucq",
    "tgn:placetype":[
        "aat:300008347"
    ]
},
  "bbox": [],
  "geometry": {"coordinates":[3.440169,50.724264],"type":"Point"}
}