{
  "id": 7180614,
  "type": "Feature",
  "properties": {
    "tgn:hierarchy":[
        "tgn:7180614",
        "tgn:1000003",
        "tgn:7003682",
        "tgn:7000084",
        "tgn:7029392"
    ],
    "tgn:id":7180614,
    "tgn:name":"Galgenberg",
    "tgn:placetype":[
        "aat:300008777"
    ]
},
  "bbox": [],
  "geometry": {"coordinates":[8.133333,49.766667],"type":"Point"}
}