{
  "id": 2218662,
  "type": "Feature",
  "properties": {
    "tgn:hierarchy":[
        "tgn:2218662",
        "tgn:1000001",
        "tgn:7016172",
        "tgn:7012149",
        "tgn:2000144",
        "tgn:7029392"
    ],
    "tgn:id":2218662,
    "tgn:name":"Cane Creek Lake",
    "tgn:placetype":[
        "aat:300008680"
    ]
},
  "bbox": [],
  "geometry": {"coordinates":[-91.75,33.9167],"type":"Point"}
}