<<<<<<< HEAD
{
  "id": 7470854,
  "type": "Feature",
  "properties": {
    "tgn:hierarchy":[
        "tgn:7470854",
        "tgn:1000004",
        "tgn:7489179",
        "tgn:1000141",
        "tgn:7029392"
    ],
    "tgn:id":7470854,
    "tgn:name":"Jiufen Shan",
    "tgn:placetype":[
        "aat:300008798"
    ]
},
  "bbox": [],
  "geometry": {"coordinates":[121.571715,24.607344],"type":"Point"}
}
=======
{"geometry":{"type":"Point","coordinates":[121.571715,24.607344]},"type":"Feature","properties":{"hierarchy":["tgn:7470854","tgn:1000004","tgn:7489179","tgn:1000141","tgn:7029392"],"placetype":["aat:300008798"],"id":7470854,"name:xx":"Jiufen Shan"}}
>>>>>>> 03f74aca74312dbeaf24d7e61306dd6a786dc3d0
