{
  "id": 2504627,
  "type": "Feature",
  "properties": {
    "tgn:hierarchy":[
        "tgn:2504627",
        "tgn:1000001",
        "tgn:1002205",
        "tgn:7012149",
        "tgn:7013961",
        "tgn:7029392"
    ],
    "tgn:id":2504627,
    "tgn:name":"Mechling Run",
    "tgn:placetype":[
        "aat:300008699"
    ]
},
  "bbox": [],
  "geometry": {"coordinates":[-80.5167,40.35],"type":"Point"}
}