{
  "id": 7413159,
  "type": "Feature",
  "properties": {
    "tgn:hierarchy":[
        "tgn:7413159",
        "tgn:7005587",
        "tgn:1000001",
        "tgn:7005560",
        "tgn:7029392"
    ],
    "tgn:id":7413159,
    "tgn:name:es":"Ca\u00f1ada Chica",
    "tgn:placetype":[
        "aat:300008347"
    ]
},
  "bbox": [],
  "geometry": {"coordinates":[-99.151389,20.418056],"type":"Point"}
}