{
  "id": 7391784,
  "type": "Feature",
  "properties": {
    "tgn:hierarchy":[
        "tgn:7391784",
        "tgn:7005581",
        "tgn:1000001",
        "tgn:7005560",
        "tgn:7029392"
    ],
    "tgn:id":7391784,
    "tgn:name":"Rancho Las Jaras",
    "tgn:placetype":[
        "aat:300008347"
    ]
},
  "bbox": [],
  "geometry": {"coordinates":[-105.15,27.416667],"type":"Point"}
}