<<<<<<< HEAD
{
  "id": 2253286,
  "type": "Feature",
  "properties": {
    "tgn:hierarchy":[
        "tgn:2253286",
        "tgn:1000001",
        "tgn:7012149",
        "tgn:2001766",
        "tgn:7007712",
        "tgn:7029392"
    ],
    "tgn:id":2253286,
    "tgn:name":"Converse Heights",
    "tgn:placetype":[
        "aat:300008347"
    ]
},
  "bbox": [],
  "geometry": {"coordinates":[-81.9,34.95],"type":"Point"}
}
=======
{"geometry":{"type":"Point","coordinates":[-81.900000,34.950000]},"type":"Feature","properties":{"hierarchy":["tgn:2253286","tgn:1000001","tgn:7012149","tgn:2001766","tgn:7007712","tgn:7029392"],"placetype":["aat:300008347"],"id":2253286,"name:xx":"Converse Heights"}}
>>>>>>> 03f74aca74312dbeaf24d7e61306dd6a786dc3d0
