<<<<<<< HEAD
{
  "id": 7369695,
  "type": "Feature",
  "properties": {
    "tgn:hierarchy":[
        "tgn:7369695",
        "tgn:7005581",
        "tgn:1000001",
        "tgn:7005560",
        "tgn:7029392"
    ],
    "tgn:id":7369695,
    "tgn:name":"Huarache, Sierra del",
    "tgn:placetype":[
        "aat:300008795"
    ]
},
  "bbox": [],
  "geometry": {"coordinates":[-106.133333,30.066667],"type":"Point"}
}
=======
{"geometry":{"type":"Point","coordinates":[-106.133333,30.066667]},"type":"Feature","properties":{"hierarchy":["tgn:7369695","tgn:7005581","tgn:1000001","tgn:7005560","tgn:7029392"],"placetype":["aat:300008795"],"id":7369695,"name:xx":"Huarache, Sierra del"}}
>>>>>>> 03f74aca74312dbeaf24d7e61306dd6a786dc3d0
