{
  "id": 2116541,
  "type": "Feature",
  "properties": {
    "tgn:hierarchy":[
        "tgn:2116541",
        "tgn:1000001",
        "tgn:7012149",
        "tgn:1002505",
        "tgn:7007920",
        "tgn:7029392"
    ],
    "tgn:id":2116541,
    "tgn:name":"Possession",
    "tgn:placetype":[
        "aat:300008347"
    ]
},
  "bbox": [],
  "geometry": {"coordinates":[-122.3667,47.9167],"type":"Point"}
}