{
  "id": 2393832,
  "type": "Feature",
  "properties": {
    "tgn:hierarchy":[
        "tgn:2393832",
        "tgn:7002659",
        "tgn:1000001",
        "tgn:7012149",
        "tgn:2000047",
        "tgn:7029392"
    ],
    "tgn:id":2393832,
    "tgn:name":"Hog Jaw Creek",
    "tgn:placetype":[
        "aat:300008706"
    ]
},
  "bbox": [],
  "geometry": {"coordinates":[-86.5333,34.3167],"type":"Point"}
}