{
  "id": 7430650,
  "type": "Feature",
  "properties": {
    "tgn:hierarchy":[
        "tgn:7430650",
        "tgn:1000001",
        "tgn:7005595",
        "tgn:7005560",
        "tgn:7029392"
    ],
    "tgn:id":7430650,
    "tgn:name":"La Mesa",
    "tgn:placetype":[
        "aat:300008347"
    ]
},
  "bbox": [],
  "geometry": {"coordinates":[-107.833333,25.816667],"type":"Point"}
}