{
  "id": 2508989,
  "type": "Feature",
  "properties": {
    "tgn:hierarchy":[
        "tgn:2508989",
        "tgn:1000001",
        "tgn:7012149",
        "tgn:2002377",
        "tgn:7007923",
        "tgn:7029392"
    ],
    "tgn:id":2508989,
    "tgn:name":"Middle Fork Elkhorn Creek",
    "tgn:placetype":[
        "aat:300008706"
    ]
},
  "bbox": [],
  "geometry": {"coordinates":[-106.2667,42.7333],"type":"Point"}
}