<<<<<<< HEAD
{
  "id": 7473334,
  "type": "Feature",
  "properties": {
    "tgn:hierarchy":[
        "tgn:7473334",
        "tgn:1000004",
        "tgn:7490934",
        "tgn:1000141",
        "tgn:7029392"
    ],
    "tgn:id":7473334,
    "tgn:name":"Daping Shan",
    "tgn:placetype":[
        "aat:300008777"
    ]
},
  "bbox": [],
  "geometry": {"coordinates":[120.355833,22.981111],"type":"Point"}
}
=======
{"geometry":{"type":"Point","coordinates":[120.355833,22.981111]},"type":"Feature","properties":{"hierarchy":["tgn:7473334","tgn:1000004","tgn:7490934","tgn:1000141","tgn:7029392"],"placetype":["aat:300008777"],"id":7473334,"name:xx":"Daping Shan"}}
>>>>>>> 03f74aca74312dbeaf24d7e61306dd6a786dc3d0
