{
  "id": 7473334,
  "type": "Feature",
  "properties": {
    "tgn:hierarchy":[
        "tgn:7473334",
        "tgn:1000004",
        "tgn:7490934",
        "tgn:1000141",
        "tgn:7029392"
    ],
    "tgn:id":7473334,
    "tgn:name":"Daping Shan",
    "tgn:placetype":[
        "aat:300008777"
    ]
},
  "bbox": [],
  "geometry": {"coordinates":[120.355833,22.981111],"type":"Point"}
}