{
  "id": 2009373,
  "type": "Feature",
  "properties": {
    "tgn:hierarchy":[
        "tgn:2009373",
        "tgn:1000001",
        "tgn:7016172",
        "tgn:7012149",
        "tgn:2000160",
        "tgn:7029392"
    ],
    "tgn:id":2009373,
    "tgn:name":"Rivervale",
    "tgn:placetype":[
        "aat:300008347"
    ]
},
  "bbox": [],
  "geometry": {"coordinates":[-90.3333,35.6667],"type":"Point"}
}