{
  "id": 6004419,
  "type": "Feature",
  "properties": {
    "tgn:hierarchy":[
        "tgn:6004419",
        "tgn:1000004",
        "tgn:1000118",
        "tgn:1001054",
        "tgn:7029392"
    ],
    "tgn:id":6004419,
    "tgn:name":"Opis",
    "tgn:placetype":[
        "aat:300008347",
        "aat:300008389",
        "aat:300008057"
    ]
},
  "bbox": [],
  "geometry": {"coordinates":[44.305,33.95],"type":"Point"}
}