{
  "id": 7582065,
  "type": "Feature",
  "properties": {
    "tgn:hierarchy":[
        "tgn:7582065",
        "tgn:1000004",
        "tgn:7000198",
        "tgn:7016722",
        "tgn:7029392"
    ],
    "tgn:id":7582065,
    "tgn:name:en":"Sirsi East Reserved Forest",
    "tgn:placetype":[
        "aat:300008865"
    ]
},
  "bbox": [],
  "geometry": {"coordinates":[78.362546,24.846788],"type":"Point"}
}