{
  "id": 1121862,
  "type": "Feature",
  "properties": {
    "tgn:hierarchy":[
        "tgn:1121862",
        "tgn:1000003",
        "tgn:7002883",
        "tgn:1000070",
        "tgn:7029392"
    ],
    "tgn:id":1121862,
    "tgn:name":"Bi\u00e8vre",
    "tgn:placetype":[
        "aat:300008707"
    ]
},
  "bbox": [],
  "geometry": {"coordinates":[2.3667,48.8333],"type":"Point"}
}