{
  "id": 7255402,
  "type": "Feature",
  "properties": {
    "tgn:hierarchy":[
        "tgn:7255402",
        "tgn:7003465",
        "tgn:1000003",
        "tgn:1000063",
        "tgn:4012014",
        "tgn:7029392"
    ],
    "tgn:id":7255402,
    "tgn:name":"Rodenhoff",
    "tgn:placetype":[
        "aat:300008347"
    ]
},
  "bbox": [],
  "geometry": {"coordinates":[5.766667,49.783333],"type":"Point"}
}