{
  "id": 7381366,
  "type": "Feature",
  "properties": {
    "tgn:hierarchy":[
        "tgn:7381366",
        "tgn:7005581",
        "tgn:1000001",
        "tgn:7005560",
        "tgn:7029392"
    ],
    "tgn:id":7381366,
    "tgn:name":"Los Alisos",
    "tgn:placetype":[
        "aat:300008347"
    ]
},
  "bbox": [],
  "geometry": {"coordinates":[-108.45,28.166667],"type":"Point"}
}