<<<<<<< HEAD
{
  "id": 7370413,
  "type": "Feature",
  "properties": {
    "tgn:hierarchy":[
        "tgn:7370413",
        "tgn:1001853",
        "tgn:1000001",
        "tgn:7005560",
        "tgn:7029392"
    ],
    "tgn:id":7370413,
    "tgn:name":"Huertas",
    "tgn:placetype":[
        "aat:300008347"
    ]
},
  "bbox": [],
  "geometry": {"coordinates":[-101.05,25.4],"type":"Point"}
}
=======
{"geometry":{"type":"Point","coordinates":[-101.050000,25.400000]},"type":"Feature","properties":{"hierarchy":["tgn:7370413","tgn:1001853","tgn:1000001","tgn:7005560","tgn:7029392"],"placetype":["aat:300008347"],"id":7370413,"name:xx":"Huertas"}}
>>>>>>> 03f74aca74312dbeaf24d7e61306dd6a786dc3d0
