{
  "id": 1102189,
  "type": "Feature",
  "properties": {
    "tgn:hierarchy":[
        "tgn:1102189",
        "tgn:1000001",
        "tgn:1002168",
        "tgn:7012149",
        "tgn:7007826",
        "tgn:7029392"
    ],
    "tgn:id":1102189,
    "tgn:name":"Buescher State Park",
    "tgn:placetype":[
        "aat:300008192"
    ]
},
  "bbox": [],
  "geometry": {"coordinates":[-97.1667,30.05],"type":"Point"}
}