{
  "id": 1124947,
  "type": "Feature",
  "properties": {
    "tgn:hierarchy":[
        "tgn:1124947",
        "tgn:1000004",
        "tgn:7002088",
        "tgn:1000111",
        "tgn:7029392"
    ],
    "tgn:id":1124947,
    "tgn:name":"Iqe He",
    "tgn:placetype":[
        "aat:300008707"
    ]
},
  "bbox": [],
  "geometry": {"coordinates":[94.3333,38.25],"type":"Point"}
}