{
  "id": 2344990,
  "type": "Feature",
  "properties": {
    "tgn:hierarchy":[
        "tgn:2344990",
        "tgn:1000001",
        "tgn:7012149",
        "tgn:2001297",
        "tgn:7007524",
        "tgn:7029392"
    ],
    "tgn:id":2344990,
    "tgn:name":"Gardner Butte",
    "tgn:placetype":[
        "aat:300008798"
    ]
},
  "bbox": [],
  "geometry": {"coordinates":[-105.8667,45.3167],"type":"Point"}
}