{
  "id": 7513206,
  "type": "Feature",
  "properties": {
    "tgn:hierarchy":[
        "tgn:7513206",
        "tgn:1009227",
        "tgn:7001866",
        "tgn:1000226",
        "tgn:1000006",
        "tgn:7029392"
    ],
    "tgn:id":7513206,
    "tgn:name:en":"Greenlaw Creek",
    "tgn:placetype":[
        "aat:300008699"
    ]
},
  "bbox": [],
  "geometry": {"coordinates":[171.466667,-42.983333],"type":"Point"}
}