{
  "id": 2165470,
  "type": "Feature",
  "properties": {
    "tgn:hierarchy":[
        "tgn:2165470",
        "tgn:1000001",
        "tgn:2001585",
        "tgn:7012149",
        "tgn:7007705",
        "tgn:7029392"
    ],
    "tgn:id":2165470,
    "tgn:name":"Beulah Bay",
    "tgn:placetype":[
        "aat:300132316"
    ]
},
  "bbox": [],
  "geometry": {"coordinates":[-101.75,47.4833],"type":"Point"}
}