<<<<<<< HEAD
{
  "id": 7026989,
  "type": "Feature",
  "properties": {
    "tgn:hierarchy":[
        "tgn:7026989",
        "tgn:7002445",
        "tgn:1000003",
        "tgn:7011430",
        "tgn:7008591",
        "tgn:7029392"
    ],
    "tgn:id":7026989,
    "tgn:name":"Yafford",
    "tgn:placetype":[
        "aat:300008347",
        "aat:300008372"
    ]
},
  "bbox": [],
  "geometry": {"coordinates":[-1.3667,50.6333],"type":"Point"}
}
=======
{"geometry":{"type":"Point","coordinates":[-1.366700,50.633300]},"type":"Feature","properties":{"hierarchy":["tgn:7026989","tgn:7002445","tgn:1000003","tgn:7011430","tgn:7008591","tgn:7029392"],"placetype":["aat:300008347","aat:300008372"],"id":7026989,"name:xx":"Yafford"}}
>>>>>>> 03f74aca74312dbeaf24d7e61306dd6a786dc3d0
