{
  "id": 2715923,
  "type": "Feature",
  "properties": {
    "tgn:hierarchy":[
        "tgn:2715923",
        "tgn:1000001",
        "tgn:7012149",
        "tgn:2000225",
        "tgn:7007158",
        "tgn:7029392"
    ],
    "tgn:id":2715923,
    "tgn:name":"Texas Chief Mine",
    "tgn:placetype":[
        "aat:300000390"
    ]
},
  "bbox": [],
  "geometry": {"coordinates":[-108.0167,37.3667],"type":"Point"}
}