{
  "id": 2181822,
  "type": "Feature",
  "properties": {
    "tgn:hierarchy":[
        "tgn:2181822",
        "tgn:1000001",
        "tgn:7012149",
        "tgn:2001916",
        "tgn:7007825",
        "tgn:7029392"
    ],
    "tgn:id":2181822,
    "tgn:name":"Blue Knob",
    "tgn:placetype":[
        "aat:300008798"
    ]
},
  "bbox": [],
  "geometry": {"coordinates":[-86.0667,36.2167],"type":"Point"}
}