{
  "id": 7479319,
  "type": "Feature",
  "properties": {
    "tgn:hierarchy":[
        "tgn:7479319",
        "tgn:1000004",
        "tgn:7490934",
        "tgn:1000141",
        "tgn:7029392"
    ],
    "tgn:id":7479319,
    "tgn:name":"Luliao Qiao",
    "tgn:placetype":[
        "aat:300007836"
    ]
},
  "bbox": [],
  "geometry": {"coordinates":[120.471667,23.385556],"type":"Point"}
}