{
  "id": 2666425,
  "type": "Feature",
  "properties": {
    "tgn:hierarchy":[
        "tgn:2666425",
        "tgn:1002159",
        "tgn:1000001",
        "tgn:7012149",
        "tgn:7007706",
        "tgn:7029392"
    ],
    "tgn:id":2666425,
    "tgn:name":"Sixmile Creek",
    "tgn:placetype":[
        "aat:300008706"
    ]
},
  "bbox": [],
  "geometry": {"coordinates":[-84.2667,40.5667],"type":"Point"}
}