{
  "id": 7034328,
  "type": "Feature",
  "properties": {
    "tgn:hierarchy":[
        "tgn:7034328",
        "tgn:7003138",
        "tgn:1000003",
        "tgn:7003080",
        "tgn:1000080",
        "tgn:7029392"
    ],
    "tgn:id":7034328,
    "tgn:name":"Banchina Apollodoro",
    "tgn:placetype":[
        "aat:300120782"
    ]
},
  "bbox": [],
  "geometry": {"coordinates":[11.783333,42.083333],"type":"Point"}
}