<<<<<<< HEAD
{
  "id": 2409966,
  "type": "Feature",
  "properties": {
    "tgn:hierarchy":[
        "tgn:2409966",
        "tgn:1000001",
        "tgn:7012149",
        "tgn:2000852",
        "tgn:7007255",
        "tgn:7029392"
    ],
    "tgn:id":2409966,
    "tgn:name":"Imperial Hollow",
    "tgn:placetype":[
        "aat:300008761"
    ]
},
  "bbox": [],
  "geometry": {"coordinates":[-84.0667,36.8333],"type":"Point"}
}
=======
{"geometry":{"type":"Point","coordinates":[-84.066700,36.833300]},"type":"Feature","properties":{"hierarchy":["tgn:2409966","tgn:1000001","tgn:7012149","tgn:2000852","tgn:7007255","tgn:7029392"],"placetype":["aat:300008761"],"id":2409966,"name:xx":"Imperial Hollow"}}
>>>>>>> 03f74aca74312dbeaf24d7e61306dd6a786dc3d0
