{
  "id": 2631304,
  "type": "Feature",
  "properties": {
    "tgn:hierarchy":[
        "tgn:2631304",
        "tgn:1000001",
        "tgn:2000925",
        "tgn:7012149",
        "tgn:7007515",
        "tgn:7029392"
    ],
    "tgn:id":2631304,
    "tgn:name":"Round Pond",
    "tgn:placetype":[
        "aat:300132316"
    ]
},
  "bbox": [],
  "geometry": {"coordinates":[-69.45,43.9333],"type":"Point"}
}