{
  "id": 2700231,
  "type": "Feature",
  "properties": {
    "tgn:hierarchy":[
        "tgn:2700231",
        "tgn:1000001",
        "tgn:2001350",
        "tgn:7012149",
        "tgn:7007525",
        "tgn:7029392"
    ],
    "tgn:id":2700231,
    "tgn:name":"Sturgeon Lake",
    "tgn:placetype":[
        "aat:300008680"
    ]
},
  "bbox": [],
  "geometry": {"coordinates":[-102.6667,41.9833],"type":"Point"}
}