{
  "id": 2231007,
  "type": "Feature",
  "properties": {
    "tgn:hierarchy":[
        "tgn:2231007",
        "tgn:1000001",
        "tgn:7012149",
        "tgn:2001451",
        "tgn:7007566",
        "tgn:7029392"
    ],
    "tgn:id":2231007,
    "tgn:name":"Cerro Colorado Tank",
    "tgn:placetype":[
        "aat:300006191"
    ]
},
  "bbox": [],
  "geometry": {"coordinates":[-107.0833,35.7333],"type":"Point"}
}