{
  "id": 7010652,
  "type": "Feature",
  "properties": {
    "tgn:hierarchy":[
        "tgn:7010652",
        "tgn:7002445",
        "tgn:7008114",
        "tgn:1000003",
        "tgn:7008591",
        "tgn:7029392"
    ],
    "tgn:id":7010652,
    "tgn:name:ang":"Nestone",
    "tgn:placetype":[
        "aat:300008347"
    ]
},
  "bbox": [],
  "geometry": {"coordinates":[-3.05,53.283333],"type":"Point"}
}