{
  "id": 2014699,
  "type": "Feature",
  "properties": {
    "tgn:hierarchy":[
        "tgn:2014699",
        "tgn:1000001",
        "tgn:7012149",
        "tgn:7007157",
        "tgn:7014475",
        "tgn:7029392"
    ],
    "tgn:id":2014699,
    "tgn:name":"Twin Creeks",
    "tgn:placetype":[
        "aat:300008347"
    ]
},
  "bbox": [],
  "geometry": {"coordinates":[-121.8333,37.15],"type":"Point"}
}