{
  "id": 2061415,
  "type": "Feature",
  "properties": {
    "tgn:hierarchy":[
        "tgn:2061415",
        "tgn:1000001",
        "tgn:7012149",
        "tgn:2001273",
        "tgn:7007524",
        "tgn:7029392"
    ],
    "tgn:id":2061415,
    "tgn:name":"Hoosac",
    "tgn:placetype":[
        "aat:300387016"
    ]
},
  "bbox": [],
  "geometry": {"coordinates":[-109.8333,47.2667],"type":"Point"}
}