{
  "id": 2463804,
  "type": "Feature",
  "properties": {
    "tgn:hierarchy":[
        "tgn:2463804",
        "tgn:1000001",
        "tgn:7012149",
        "tgn:1002526",
        "tgn:7007826",
        "tgn:7029392"
    ],
    "tgn:id":2463804,
    "tgn:name":"Lockett Branch",
    "tgn:placetype":[
        "aat:300008699"
    ]
},
  "bbox": [],
  "geometry": {"coordinates":[-97.3333,32.3833],"type":"Point"}
}