{
  "id": 2495745,
  "type": "Feature",
  "properties": {
    "tgn:hierarchy":[
        "tgn:2495745",
        "tgn:1000001",
        "tgn:7012149",
        "tgn:2001273",
        "tgn:7007524",
        "tgn:7029392"
    ],
    "tgn:id":2495745,
    "tgn:name":"Mason Canyon",
    "tgn:placetype":[
        "aat:300008761"
    ]
},
  "bbox": [],
  "geometry": {"coordinates":[-109.4833,47.2833],"type":"Point"}
}