<<<<<<< HEAD
{
  "id": 7471537,
  "type": "Feature",
  "properties": {
    "tgn:hierarchy":[
        "tgn:7471537",
        "tgn:1000004",
        "tgn:7489179",
        "tgn:1000141",
        "tgn:7029392"
    ],
    "tgn:id":7471537,
    "tgn:name":"Fanshuliao",
    "tgn:placetype":[
        "aat:300008347"
    ]
},
  "bbox": [],
  "geometry": {"coordinates":[121.906667,24.95],"type":"Point"}
}
=======
{"geometry":{"type":"Point","coordinates":[121.906667,24.950000]},"type":"Feature","properties":{"hierarchy":["tgn:7471537","tgn:1000004","tgn:7489179","tgn:1000141","tgn:7029392"],"placetype":["aat:300008347"],"id":7471537,"name:xx":"Fanshuliao"}}
>>>>>>> 03f74aca74312dbeaf24d7e61306dd6a786dc3d0
