{
  "id": 7471537,
  "type": "Feature",
  "properties": {
    "tgn:hierarchy":[
        "tgn:7471537",
        "tgn:1000004",
        "tgn:7489179",
        "tgn:1000141",
        "tgn:7029392"
    ],
    "tgn:id":7471537,
    "tgn:name":"Fanshuliao",
    "tgn:placetype":[
        "aat:300008347"
    ]
},
  "bbox": [],
  "geometry": {"coordinates":[121.906667,24.95],"type":"Point"}
}