{
  "id": 2250136,
  "type": "Feature",
  "properties": {
    "tgn:hierarchy":[
        "tgn:2250136",
        "tgn:1000001",
        "tgn:7012149",
        "tgn:1002406",
        "tgn:7007520",
        "tgn:7029392"
    ],
    "tgn:id":2250136,
    "tgn:name":"Collins Drain",
    "tgn:placetype":[
        "aat:300006075"
    ]
},
  "bbox": [],
  "geometry": {"coordinates":[-83.7333,43.1833],"type":"Point"}
}