{
  "id": 7534861,
  "type": "Feature",
  "properties": {
    "tgn:hierarchy":[
        "tgn:7534861",
        "tgn:7001242",
        "tgn:7016833",
        "tgn:7001312",
        "tgn:7029392"
    ],
    "tgn:id":7534861,
    "tgn:name:en":"Kafr al Hill\u0101w\u012b",
    "tgn:placetype":[
        "aat:300008347"
    ]
},
  "bbox": [],
  "geometry": {"coordinates":[30.855753,30.856838],"type":"Point"}
}