{
  "id": 2455332,
  "type": "Feature",
  "properties": {
    "tgn:hierarchy":[
        "tgn:2455332",
        "tgn:1000001",
        "tgn:7012149",
        "tgn:2001721",
        "tgn:7007708",
        "tgn:7029392"
    ],
    "tgn:id":2455332,
    "tgn:name":"Little Fly Creek",
    "tgn:placetype":[
        "aat:300008706"
    ]
},
  "bbox": [],
  "geometry": {"coordinates":[-118.5167,45.0167],"type":"Point"}
}