{
  "id": 7525965,
  "type": "Feature",
  "properties": {
    "tgn:hierarchy":[
        "tgn:7525965",
        "tgn:7001242",
        "tgn:7016833",
        "tgn:1001087",
        "tgn:7029392"
    ],
    "tgn:id":7525965,
    "tgn:name:en":"S\u012bd\u012b \u1e28ass\u0101n",
    "tgn:placetype":[
        "aat:300005926"
    ]
},
  "bbox": [],
  "geometry": {"coordinates":[30.931667,30.661111],"type":"Point"}
}