{
  "id": 7461972,
  "type": "Feature",
  "properties": {
    "tgn:hierarchy":[
        "tgn:7461972",
        "tgn:7002444",
        "tgn:1000003",
        "tgn:7009907",
        "tgn:7008591",
        "tgn:7029392"
    ],
    "tgn:id":7461972,
    "tgn:name:en":"Ireland, Bay of",
    "tgn:placetype":[
        "aat:300132316"
    ]
},
  "bbox": [],
  "geometry": {"coordinates":[-3.25,58.966667],"type":"Point"}
}