{
  "id": 1106628,
  "type": "Feature",
  "properties": {
    "tgn:hierarchy":[
        "tgn:1106628",
        "tgn:7017440",
        "tgn:1000001",
        "tgn:7004643",
        "tgn:7029392"
    ],
    "tgn:id":1106628,
    "tgn:name":"Tabla, Cerro de la",
    "tgn:placetype":[
        "aat:300008795"
    ]
},
  "bbox": [],
  "geometry": {"coordinates":[-66.1333,18.05],"type":"Point"}
}