{
  "id": 2674406,
  "type": "Feature",
  "properties": {
    "tgn:hierarchy":[
        "tgn:2674406",
        "tgn:1000001",
        "tgn:7012149",
        "tgn:1002700",
        "tgn:7007520",
        "tgn:7029392"
    ],
    "tgn:id":2674406,
    "tgn:name":"Snug Harbor",
    "tgn:placetype":[
        "aat:300132316"
    ]
},
  "bbox": [],
  "geometry": {"coordinates":[-86.3167,43.2333],"type":"Point"}
}