{
  "id": 7047149,
  "type": "Feature",
  "properties": {
    "tgn:hierarchy":[
        "tgn:7047149",
        "tgn:7009084",
        "tgn:7003001",
        "tgn:1000003",
        "tgn:1000080",
        "tgn:7029392"
    ],
    "tgn:id":7047149,
    "tgn:name":"Cola",
    "tgn:placetype":[
        "aat:300008347"
    ]
},
  "bbox": [],
  "geometry": {"coordinates":[13.666667,42.55],"type":"Point"}
}