{
  "id": 7196118,
  "type": "Feature",
  "properties": {
    "tgn:hierarchy":[
        "tgn:7196118",
        "tgn:7003669",
        "tgn:1000003",
        "tgn:7000084",
        "tgn:7029392"
    ],
    "tgn:id":7196118,
    "tgn:name":"Dexhof",
    "tgn:placetype":[
        "aat:300000206"
    ]
},
  "bbox": [],
  "geometry": {"coordinates":[11.966667,49.233333],"type":"Point"}
}