{
  "id": 2122071,
  "type": "Feature",
  "properties": {
    "tgn:hierarchy":[
        "tgn:2122071",
        "tgn:1000001",
        "tgn:7012149",
        "tgn:2002357",
        "tgn:7007922",
        "tgn:7029392"
    ],
    "tgn:id":2122071,
    "tgn:name":"Osseo",
    "tgn:placetype":[
        "aat:300008347"
    ]
},
  "bbox": [],
  "geometry": {"coordinates":[-91.2167,44.5667],"type":"Point"}
}