{
  "id": 1013355,
  "type": "Feature",
  "properties": {
    "tgn:hierarchy":[
        "tgn:1013355",
        "tgn:7005694",
        "tgn:7005685",
        "tgn:1000001",
        "tgn:7029392"
    ],
    "tgn:id":1013355,
    "tgn:name":"Winfield",
    "tgn:placetype":[
        "aat:300008347"
    ]
},
  "bbox": [],
  "geometry": {"coordinates":[-114.3833,52.9667],"type":"Point"}
}