{
  "id": 7151375,
  "type": "Feature",
  "properties": {
    "tgn:hierarchy":[
        "tgn:7151375",
        "tgn:1000003",
        "tgn:7003677",
        "tgn:7000084",
        "tgn:7029392"
    ],
    "tgn:id":7151375,
    "tgn:name":"Kaninchen-Berge",
    "tgn:placetype":[
        "aat:300008777"
    ]
},
  "bbox": [],
  "geometry": {"coordinates":[6.783333,51.666667],"type":"Point"}
}