{
  "id": 2216708,
  "type": "Feature",
  "properties": {
    "tgn:hierarchy":[
        "tgn:2216708",
        "tgn:1000001",
        "tgn:2001417",
        "tgn:7012149",
        "tgn:7007526",
        "tgn:7029392"
    ],
    "tgn:id":2216708,
    "tgn:name":"Camp Douglas",
    "tgn:placetype":[
        "aat:300008347"
    ]
},
  "bbox": [],
  "geometry": {"coordinates":[-118.1833,38.3333],"type":"Point"}
}