{
  "id": 2572261,
  "type": "Feature",
  "properties": {
    "tgn:hierarchy":[
        "tgn:2572261",
        "tgn:1000001",
        "tgn:7012149",
        "tgn:7007254",
        "tgn:7029392"
    ],
    "tgn:id":2572261,
    "tgn:name":"Peace Creek",
    "tgn:placetype":[
        "aat:300008706"
    ]
},
  "bbox": [],
  "geometry": {"coordinates":[-98.6333,37.95],"type":"Point"}
}