{
  "id": 2191689,
  "type": "Feature",
  "properties": {
    "tgn:hierarchy":[
        "tgn:2191689",
        "tgn:1000001",
        "tgn:7012149",
        "tgn:2002270",
        "tgn:7013961",
        "tgn:7029392"
    ],
    "tgn:id":2191689,
    "tgn:name":"Bradley Fork",
    "tgn:placetype":[
        "aat:300008699"
    ]
},
  "bbox": [],
  "geometry": {"coordinates":[-81.5333,38.15],"type":"Point"}
}