{
  "id": 7129079,
  "type": "Feature",
  "properties": {
    "tgn:hierarchy":[
        "tgn:7129079",
        "tgn:7003669",
        "tgn:1000003",
        "tgn:7000084",
        "tgn:7029392"
    ],
    "tgn:id":7129079,
    "tgn:name":"Oberelsbach",
    "tgn:placetype":[
        "aat:300008347"
    ]
},
  "bbox": [],
  "geometry": {"coordinates":[10.133333,50.433333],"type":"Point"}
}