{
  "id": 7139443,
  "type": "Feature",
  "properties": {
    "tgn:hierarchy":[
        "tgn:7139443",
        "tgn:1000003",
        "tgn:7003685",
        "tgn:7000084",
        "tgn:7029392"
    ],
    "tgn:id":7139443,
    "tgn:name":"Lausa",
    "tgn:placetype":[
        "aat:300008347"
    ]
},
  "bbox": [],
  "geometry": {"coordinates":[13.066667,51.433333],"type":"Point"}
}