{
  "id": 7593390,
  "type": "Feature",
  "properties": {
    "tgn:hierarchy":[
        "tgn:7593390",
        "tgn:7005394",
        "tgn:1000001",
        "tgn:7005388",
        "tgn:7029392"
    ],
    "tgn:id":7593390,
    "tgn:name":"Villa Riva",
    "tgn:placetype":[
        "aat:300008347"
    ]
},
  "bbox": [],
  "geometry": {"coordinates":[-69.913,19.18],"type":"Point"}
}