{
  "id": 7463558,
  "type": "Feature",
  "properties": {
    "tgn:hierarchy":[
        "tgn:7463558",
        "tgn:7002448",
        "tgn:7019165",
        "tgn:1000003",
        "tgn:7008591",
        "tgn:7029392"
    ],
    "tgn:id":7463558,
    "tgn:name:en":"Kilroot",
    "tgn:placetype":[
        "aat:300008347"
    ]
},
  "bbox": [],
  "geometry": {"coordinates":[-5.766667,54.716667],"type":"Point"}
}