{
  "id": 2584326,
  "type": "Feature",
  "properties": {
    "tgn:hierarchy":[
        "tgn:2584326",
        "tgn:1000001",
        "tgn:7012149",
        "tgn:2001519",
        "tgn:7007709",
        "tgn:7029392"
    ],
    "tgn:id":2584326,
    "tgn:name":"Piney Branch",
    "tgn:placetype":[
        "aat:300008699"
    ]
},
  "bbox": [],
  "geometry": {"coordinates":[-82.1667,36.0667],"type":"Point"}
}