{
  "id": 2011912,
  "type": "Feature",
  "properties": {
    "tgn:hierarchy":[
        "tgn:2011912",
        "tgn:1000001",
        "tgn:7012149",
        "tgn:7007157",
        "tgn:1002956",
        "tgn:7029392"
    ],
    "tgn:id":2011912,
    "tgn:name":"Ivanhoe",
    "tgn:placetype":[
        "aat:300008347"
    ]
},
  "bbox": [],
  "geometry": {"coordinates":[-119.2167,36.3833],"type":"Point"}
}