{
  "id": 2115215,
  "type": "Feature",
  "properties": {
    "tgn:hierarchy":[
        "tgn:2115215",
        "tgn:1000001",
        "tgn:7012149",
        "tgn:7014510",
        "tgn:7007920",
        "tgn:7029392"
    ],
    "tgn:id":2115215,
    "tgn:name":"Allen",
    "tgn:placetype":[
        "aat:300008347"
    ]
},
  "bbox": [],
  "geometry": {"coordinates":[-122.3667,48.5167],"type":"Point"}
}