{
  "id": 7030099,
  "type": "Feature",
  "properties": {
    "tgn:hierarchy":[
        "tgn:7030099",
        "tgn:7002445",
        "tgn:7008103",
        "tgn:1000003",
        "tgn:7008591",
        "tgn:7029392"
    ],
    "tgn:id":7030099,
    "tgn:name":"Sandy",
    "tgn:name:ang":"Sandeia",
    "tgn:placetype":[
        "aat:300008347"
    ]
},
  "bbox": [],
  "geometry": {"coordinates":[-0.283333,52.116667],"type":"Point"}
}