{
  "id": 2724638,
  "type": "Feature",
  "properties": {
    "tgn:hierarchy":[
        "tgn:2724638",
        "tgn:1000001",
        "tgn:7012149",
        "tgn:1002742",
        "tgn:7007920",
        "tgn:7029392"
    ],
    "tgn:id":2724638,
    "tgn:name":"Tomasket Creek",
    "tgn:placetype":[
        "aat:300008706"
    ]
},
  "bbox": [],
  "geometry": {"coordinates":[-119.2667,48.85],"type":"Point"}
}