{
  "id": 7508130,
  "type": "Feature",
  "properties": {
    "tgn:hierarchy":[
        "tgn:7508130",
        "tgn:7520092",
        "tgn:1008380",
        "tgn:1000226",
        "tgn:1000006",
        "tgn:7029392"
    ],
    "tgn:id":7508130,
    "tgn:name:en":"Pararika Stream",
    "tgn:placetype":[
        "aat:300008699"
    ]
},
  "bbox": [],
  "geometry": {"coordinates":[177.983333,-38.283333],"type":"Point"}
}