{
  "id": 2745433,
  "type": "Feature",
  "properties": {
    "tgn:hierarchy":[
        "tgn:2745433",
        "tgn:1000001",
        "tgn:7012149",
        "tgn:1002599",
        "tgn:7007708",
        "tgn:7029392"
    ],
    "tgn:id":2745433,
    "tgn:name":"Vingie Creek",
    "tgn:placetype":[
        "aat:300008706"
    ]
},
  "bbox": [],
  "geometry": {"coordinates":[-124.0167,44.3167],"type":"Point"}
}