{
  "id": 2712416,
  "type": "Feature",
  "properties": {
    "tgn:hierarchy":[
        "tgn:2712416",
        "tgn:1000001",
        "tgn:7012149",
        "tgn:7016166",
        "tgn:7007523",
        "tgn:7029392"
    ],
    "tgn:id":2712416,
    "tgn:name":"Tavern Rock Quarry",
    "tgn:placetype":[
        "aat:300000390"
    ]
},
  "bbox": [],
  "geometry": {"coordinates":[-90.8333,38.5667],"type":"Point"}
}