{
  "id": 2523759,
  "type": "Feature",
  "properties": {
    "tgn:hierarchy":[
        "tgn:2523759",
        "tgn:1000001",
        "tgn:7012149",
        "tgn:7029392"
    ],
    "tgn:id":2523759,
    "tgn:name":"Moraine Lake",
    "tgn:placetype":[
        "aat:300008680"
    ]
},
  "bbox": [],
  "geometry": {"coordinates":[-89.7833,46.2667],"type":"Point"}
}