{
  "id": 2346821,
  "type": "Feature",
  "properties": {
    "tgn:hierarchy":[
        "tgn:2346821",
        "tgn:1000001",
        "tgn:7012149",
        "tgn:1002512",
        "tgn:7007252",
        "tgn:7029392"
    ],
    "tgn:id":2346821,
    "tgn:name":"Gehring And Gumz Ditch",
    "tgn:placetype":[
        "aat:300006075"
    ]
},
  "bbox": [],
  "geometry": {"coordinates":[-86.9833,41.05],"type":"Point"}
}