<<<<<<< HEAD
{
  "id": 2409280,
  "type": "Feature",
  "properties": {
    "tgn:hierarchy":[
        "tgn:2409280",
        "tgn:1000001",
        "tgn:1002260",
        "tgn:7012149",
        "tgn:7007920",
        "tgn:7029392"
    ],
    "tgn:id":2409280,
    "tgn:name":"Icicle Ridge",
    "tgn:placetype":[
        "aat:300266640"
    ]
},
  "bbox": [],
  "geometry": {"coordinates":[-120.7667,47.6],"type":"Point"}
}
=======
{"geometry":{"type":"Point","coordinates":[-120.766700,47.600000]},"type":"Feature","properties":{"hierarchy":["tgn:2409280","tgn:1000001","tgn:1002260","tgn:7012149","tgn:7007920","tgn:7029392"],"placetype":["aat:300266640"],"id":2409280,"name:xx":"Icicle Ridge"}}
>>>>>>> 03f74aca74312dbeaf24d7e61306dd6a786dc3d0
