<<<<<<< HEAD
{
  "id": 7179688,
  "type": "Feature",
  "properties": {
    "tgn:hierarchy":[
        "tgn:7179688",
        "tgn:7000096",
        "tgn:1000003",
        "tgn:7000084",
        "tgn:7029392"
    ],
    "tgn:id":7179688,
    "tgn:name":"Haaren",
    "tgn:placetype":[
        "aat:300008347"
    ]
},
  "bbox": [],
  "geometry": {"coordinates":[11.983333,52.966667],"type":"Point"}
}
=======
{"geometry":{"type":"Point","coordinates":[11.983333,52.966667]},"type":"Feature","properties":{"hierarchy":["tgn:7179688","tgn:7000096","tgn:1000003","tgn:7000084","tgn:7029392"],"placetype":["aat:300008347"],"id":7179688,"name:xx":"Haaren"}}
>>>>>>> 03f74aca74312dbeaf24d7e61306dd6a786dc3d0
