{
  "id": 7064028,
  "type": "Feature",
  "properties": {
    "tgn:hierarchy":[
        "tgn:7064028",
        "tgn:1000003",
        "tgn:7003677",
        "tgn:7000084",
        "tgn:7029392"
    ],
    "tgn:id":7064028,
    "tgn:name":"Asperschlag",
    "tgn:placetype":[
        "aat:300000206"
    ]
},
  "bbox": [],
  "geometry": {"coordinates":[6.683333,50.983333],"type":"Point"}
}