{
  "id": 2478964,
  "type": "Feature",
  "properties": {
    "tgn:hierarchy":[
        "tgn:2478964",
        "tgn:2000192",
        "tgn:1000001",
        "tgn:7012149",
        "tgn:7007158",
        "tgn:7029392"
    ],
    "tgn:id":2478964,
    "tgn:name":"Magers Reservoir",
    "tgn:placetype":[
        "aat:300006191"
    ]
},
  "bbox": [],
  "geometry": {"coordinates":[-104.7833,39.95],"type":"Point"}
}