{
  "id": 7395739,
  "type": "Feature",
  "properties": {
    "tgn:hierarchy":[
        "tgn:7395739",
        "tgn:7005578",
        "tgn:1000001",
        "tgn:7005560",
        "tgn:7029392"
    ],
    "tgn:id":7395739,
    "tgn:name":"San Jos\u00e9 Xkix",
    "tgn:placetype":[
        "aat:300008347"
    ]
},
  "bbox": [],
  "geometry": {"coordinates":[-90.133333,19.733333],"type":"Point"}
}