{
  "id": 7271473,
  "type": "Feature",
  "properties": {
    "tgn:concordances":{
        "gn:id":"2746552"
    },
    "tgn:hierarchy":[
        "tgn:7271473",
        "tgn:1000003",
        "tgn:7003613",
        "tgn:7016845",
        "tgn:7029392"
    ],
    "tgn:id":7271473,
    "tgn:name:nl":"Suttum",
    "tgn:placetype":[
        "aat:300008347"
    ]
},
  "bbox": [],
  "geometry": {"coordinates":[6.433333,53.283333],"type":"Point"}
}