{
  "id": 2657340,
  "type": "Feature",
  "properties": {
    "tgn:hierarchy":[
        "tgn:2657340",
        "tgn:1000001",
        "tgn:7012149",
        "tgn:1002924",
        "tgn:7007568",
        "tgn:7029392"
    ],
    "tgn:id":2657340,
    "tgn:name":"Sheepen Creek",
    "tgn:placetype":[
        "aat:300008706"
    ]
},
  "bbox": [],
  "geometry": {"coordinates":[-72.85,40.7333],"type":"Point"}
}