{
  "id": 1049257,
  "type": "Feature",
  "properties": {
    "tgn:hierarchy":[
        "tgn:1049257",
        "tgn:1000003",
        "tgn:7024119",
        "tgn:7006366",
        "tgn:7029392"
    ],
    "tgn:id":1049257,
    "tgn:name":"Mikstat",
    "tgn:placetype":[
        "aat:300008347"
    ]
},
  "bbox": [],
  "geometry": {"coordinates":[17.9833,51.5333],"type":"Point"}
}