{
  "id": 2208691,
  "type": "Feature",
  "properties": {
    "tgn:hierarchy":[
        "tgn:2208691",
        "tgn:1000001",
        "tgn:7012149",
        "tgn:7015666",
        "tgn:7007825",
        "tgn:7029392"
    ],
    "tgn:id":2208691,
    "tgn:name":"Burns Hollow",
    "tgn:placetype":[
        "aat:300008761"
    ]
},
  "bbox": [],
  "geometry": {"coordinates":[-87.4667,35.6833],"type":"Point"}
}