{
  "id": 1002647,
  "type": "Feature",
  "properties": {
    "tgn:hierarchy":[
        "tgn:1002647",
        "tgn:1000001",
        "tgn:7012149",
        "tgn:7007919",
        "tgn:7029392"
    ],
    "tgn:id":1002647,
    "tgn:name":"Mathews",
    "tgn:placetype":[
        "aat:300387145",
        "aat:300000771"
    ]
},
  "bbox": [],
  "geometry": {"coordinates":[-76.3667,37.4333],"type":"Point"}
}