<<<<<<< HEAD
{
  "id": 7478022,
  "type": "Feature",
  "properties": {
    "tgn:hierarchy":[
        "tgn:7478022",
        "tgn:1000004",
        "tgn:1000454",
        "tgn:1000141",
        "tgn:7029392"
    ],
    "tgn:id":7478022,
    "tgn:name":"Neiganjiao",
    "tgn:placetype":[
        "aat:300008347"
    ]
},
  "bbox": [],
  "geometry": {"coordinates":[121.805155,25.014427],"type":"Point"}
}
=======
{"geometry":{"type":"Point","coordinates":[121.805155,25.014427]},"type":"Feature","properties":{"hierarchy":["tgn:7478022","tgn:1000004","tgn:1000454","tgn:1000141","tgn:7029392"],"placetype":["aat:300008347"],"id":7478022,"name:xx":"Neiganjiao"}}
>>>>>>> 03f74aca74312dbeaf24d7e61306dd6a786dc3d0
