<<<<<<< HEAD
{
  "id": 7478719,
  "type": "Feature",
  "properties": {
    "tgn:hierarchy":[
        "tgn:7478719",
        "tgn:7488858",
        "tgn:1000004",
        "tgn:1000141",
        "tgn:7029392"
    ],
    "tgn:id":7478719,
    "tgn:name":"Liulongtou",
    "tgn:placetype":[
        "aat:300008347"
    ]
},
  "bbox": [],
  "geometry": {"coordinates":[120.869831,23.88159],"type":"Point"}
}
=======
{"geometry":{"type":"Point","coordinates":[120.869831,23.881590]},"type":"Feature","properties":{"hierarchy":["tgn:7478719","tgn:7488858","tgn:1000004","tgn:1000141","tgn:7029392"],"placetype":["aat:300008347"],"id":7478719,"name:xx":"Liulongtou"}}
>>>>>>> 03f74aca74312dbeaf24d7e61306dd6a786dc3d0
