{
  "id": 7478719,
  "type": "Feature",
  "properties": {
    "tgn:hierarchy":[
        "tgn:7478719",
        "tgn:7488858",
        "tgn:1000004",
        "tgn:1000141",
        "tgn:7029392"
    ],
    "tgn:id":7478719,
    "tgn:name":"Liulongtou",
    "tgn:placetype":[
        "aat:300008347"
    ]
},
  "bbox": [],
  "geometry": {"coordinates":[120.869831,23.88159],"type":"Point"}
}