<<<<<<< HEAD
{
  "id": 2337510,
  "type": "Feature",
  "properties": {
    "tgn:hierarchy":[
        "tgn:2337510",
        "tgn:1000001",
        "tgn:7012149",
        "tgn:7007157",
        "tgn:1002710",
        "tgn:7029392"
    ],
    "tgn:id":2337510,
    "tgn:name":"Fowler Spring",
    "tgn:placetype":[
        "aat:300008697"
    ]
},
  "bbox": [],
  "geometry": {"coordinates":[-120.8833,39.2833],"type":"Point"}
}
=======
{"geometry":{"type":"Point","coordinates":[-120.883300,39.283300]},"type":"Feature","properties":{"hierarchy":["tgn:2337510","tgn:1000001","tgn:7012149","tgn:7007157","tgn:1002710","tgn:7029392"],"placetype":["aat:300008697"],"id":2337510,"name:xx":"Fowler Spring"}}
>>>>>>> 03f74aca74312dbeaf24d7e61306dd6a786dc3d0
