{
  "id": 2165678,
  "type": "Feature",
  "properties": {
    "tgn:hierarchy":[
        "tgn:2165678",
        "tgn:1002201",
        "tgn:1000001",
        "tgn:7012149",
        "tgn:7007517",
        "tgn:7029392"
    ],
    "tgn:id":2165678,
    "tgn:name":"Bial Point",
    "tgn:placetype":[
        "aat:300008850"
    ]
},
  "bbox": [],
  "geometry": {"coordinates":[-71.0833,41.5167],"type":"Point"}
}