{
  "id": 1024038,
  "type": "Feature",
  "properties": {
    "tgn:hierarchy":[
        "tgn:1024038",
        "tgn:1000554",
        "tgn:1000050",
        "tgn:1000002",
        "tgn:7029392"
    ],
    "tgn:id":1024038,
    "tgn:name":"Timb\u00edo",
    "tgn:placetype":[
        "aat:300008347"
    ]
},
  "bbox": [],
  "geometry": {"coordinates":[-76.6667,2.3333],"type":"Point"}
}