<<<<<<< HEAD
{
  "id": 7175397,
  "type": "Feature",
  "properties": {
    "tgn:hierarchy":[
        "tgn:7175397",
        "tgn:1000003",
        "tgn:7003677",
        "tgn:7000084",
        "tgn:7029392"
    ],
    "tgn:id":7175397,
    "tgn:name":"Grote Bahne",
    "tgn:placetype":[
        "aat:300055621"
    ]
},
  "bbox": [],
  "geometry": {"coordinates":[7.116667,51.816667],"type":"Point"}
}
=======
{"geometry":{"type":"Point","coordinates":[7.116667,51.816667]},"type":"Feature","properties":{"hierarchy":["tgn:7175397","tgn:1000003","tgn:7003677","tgn:7000084","tgn:7029392"],"placetype":["aat:300055621"],"id":7175397,"name:xx":"Grote Bahne"}}
>>>>>>> 03f74aca74312dbeaf24d7e61306dd6a786dc3d0
