{
  "id": 7236362,
  "type": "Feature",
  "properties": {
    "tgn:hierarchy":[
        "tgn:7236362",
        "tgn:7002743",
        "tgn:7017076",
        "tgn:1000003",
        "tgn:1000074",
        "tgn:7029392"
    ],
    "tgn:id":7236362,
    "tgn:name":"Er\u00edmanthos Potam\u00f3s",
    "tgn:placetype":[
        "aat:300008699"
    ]
},
  "bbox": [],
  "geometry": {"coordinates":[21.783333,37.583333],"type":"Point"}
}