{
  "id": 1033133,
  "type": "Feature",
  "properties": {
    "tgn:hierarchy":[
        "tgn:1033133",
        "tgn:1000003",
        "tgn:7002875",
        "tgn:1000070",
        "tgn:7029392"
    ],
    "tgn:id":1033133,
    "tgn:name":"Fontaine Fran\u00e7aise",
    "tgn:placetype":[
        "aat:300008347"
    ]
},
  "bbox": [],
  "geometry": {"coordinates":[5.3667,47.5333],"type":"Point"}
}