{
  "id": 2588753,
  "type": "Feature",
  "properties": {
    "tgn:hierarchy":[
        "tgn:2588753",
        "tgn:1000001",
        "tgn:7012149",
        "tgn:2001846",
        "tgn:7007825",
        "tgn:7029392"
    ],
    "tgn:id":2588753,
    "tgn:name":"Plymouth Park",
    "tgn:placetype":[
        "aat:300008347"
    ]
},
  "bbox": [],
  "geometry": {"coordinates":[-82.3167,36.2833],"type":"Point"}
}