{
  "id": 2605373,
  "type": "Feature",
  "properties": {
    "tgn:hierarchy":[
        "tgn:2605373",
        "tgn:1000001",
        "tgn:7012149",
        "tgn:7022246",
        "tgn:7007825",
        "tgn:7029392"
    ],
    "tgn:id":2605373,
    "tgn:name":"Ragland Hollow",
    "tgn:placetype":[
        "aat:300008761"
    ]
},
  "bbox": [],
  "geometry": {"coordinates":[-85.6833,35.9667],"type":"Point"}
}