{
  "id": 2560657,
  "type": "Feature",
  "properties": {
    "tgn:hierarchy":[
        "tgn:2560657",
        "tgn:1000001",
        "tgn:7012149",
        "tgn:2001718",
        "tgn:7007708",
        "tgn:7029392"
    ],
    "tgn:id":2560657,
    "tgn:name":"Oregon Slope",
    "tgn:placetype":[
        "aat:300055621"
    ]
},
  "bbox": [],
  "geometry": {"coordinates":[-116.9667,44.1333],"type":"Point"}
}