<<<<<<< HEAD
{
  "id": 7470996,
  "type": "Feature",
  "properties": {
    "tgn:hierarchy":[
        "tgn:7470996",
        "tgn:1000004",
        "tgn:7001013",
        "tgn:1000141",
        "tgn:7029392"
    ],
    "tgn:id":7470996,
    "tgn:name":"Houguan",
    "tgn:placetype":[
        "aat:300008347"
    ]
},
  "bbox": [],
  "geometry": {"coordinates":[121.196186,25.080245],"type":"Point"}
}
=======
{"geometry":{"type":"Point","coordinates":[121.196186,25.080245]},"type":"Feature","properties":{"hierarchy":["tgn:7470996","tgn:1000004","tgn:7001013","tgn:1000141","tgn:7029392"],"placetype":["aat:300008347"],"id":7470996,"name:xx":"Houguan"}}
>>>>>>> 03f74aca74312dbeaf24d7e61306dd6a786dc3d0
