{
  "id": 2279383,
  "type": "Feature",
  "properties": {
    "tgn:hierarchy":[
        "tgn:2279383",
        "tgn:1000001",
        "tgn:1002260",
        "tgn:7012149",
        "tgn:7007920",
        "tgn:7029392"
    ],
    "tgn:id":2279383,
    "tgn:name":"Deadman Creek",
    "tgn:placetype":[
        "aat:300008706"
    ]
},
  "bbox": [],
  "geometry": {"coordinates":[-120.8833,48.4667],"type":"Point"}
}