{
  "id": 7354961,
  "type": "Feature",
  "properties": {
    "tgn:hierarchy":[
        "tgn:7354961",
        "tgn:1000001",
        "tgn:7005589",
        "tgn:7005560",
        "tgn:7029392"
    ],
    "tgn:id":7354961,
    "tgn:name":"Cienaguitas",
    "tgn:placetype":[
        "aat:300008347"
    ]
},
  "bbox": [],
  "geometry": {"coordinates":[-99.866667,26.333333],"type":"Point"}
}