{
  "id": 2600014,
  "type": "Feature",
  "properties": {
    "tgn:hierarchy":[
        "tgn:2600014",
        "tgn:1000001",
        "tgn:7012149",
        "tgn:2001254",
        "tgn:7007523",
        "tgn:7029392"
    ],
    "tgn:id":2600014,
    "tgn:name":"Pruitt Mountain",
    "tgn:placetype":[
        "aat:300008798"
    ]
},
  "bbox": [],
  "geometry": {"coordinates":[-90.8333,37.7333],"type":"Point"}
}