{
  "id": 7531657,
  "type": "Feature",
  "properties": {
    "tgn:hierarchy":[
        "tgn:7531657",
        "tgn:7001242",
        "tgn:7016833",
        "tgn:1001092",
        "tgn:7029392"
    ],
    "tgn:id":7531657,
    "tgn:name":"Mustashf\u00e1 \u1e28ummay\u0101t Baht\u012bm",
    "tgn:placetype":[
        "aat:300006676"
    ]
},
  "bbox": [],
  "geometry": {"coordinates":[31.275193,30.136204],"type":"Point"}
}