<<<<<<< HEAD
{
  "id": 7474530,
  "type": "Feature",
  "properties": {
    "tgn:hierarchy":[
        "tgn:7474530",
        "tgn:1000004",
        "tgn:7492971",
        "tgn:1000141",
        "tgn:7029392"
    ],
    "tgn:id":7474530,
    "tgn:name":"Tianzi",
    "tgn:placetype":[
        "aat:300008347"
    ]
},
  "bbox": [],
  "geometry": {"coordinates":[120.5795,22.8025],"type":"Point"}
}
=======
{"geometry":{"type":"Point","coordinates":[120.579500,22.802500]},"type":"Feature","properties":{"hierarchy":["tgn:7474530","tgn:1000004","tgn:7492971","tgn:1000141","tgn:7029392"],"placetype":["aat:300008347"],"id":7474530,"name:xx":"Tianzi"}}
>>>>>>> 03f74aca74312dbeaf24d7e61306dd6a786dc3d0
