{
  "id": 7046510,
  "type": "Feature",
  "properties": {
    "tgn:hierarchy":[
        "tgn:7046510",
        "tgn:1001643",
        "tgn:1000003",
        "tgn:7003122",
        "tgn:1000080",
        "tgn:7029392"
    ],
    "tgn:id":7046510,
    "tgn:name":"Case Martinez",
    "tgn:placetype":[
        "aat:300008347"
    ]
},
  "bbox": [],
  "geometry": {"coordinates":[14.066667,37.433333],"type":"Point"}
}