{
  "id": 1024379,
  "type": "Feature",
  "properties": {
    "tgn:hierarchy":[
        "tgn:1024379",
        "tgn:1000547",
        "tgn:1000002",
        "tgn:1000056",
        "tgn:7029392"
    ],
    "tgn:id":1024379,
    "tgn:name":"Bambamarca",
    "tgn:placetype":[
        "aat:300008347"
    ]
},
  "bbox": [],
  "geometry": {"coordinates":[-78.5333,-6.6833],"type":"Point"}
}