{
  "id": 1084826,
  "type": "Feature",
  "properties": {
    "tgn:hierarchy":[
        "tgn:1084826",
        "tgn:7000679",
        "tgn:7003866",
        "tgn:1000004",
        "tgn:1000137",
        "tgn:7029392"
    ],
    "tgn:id":1084826,
    "tgn:name":"Al-L\u012bth",
    "tgn:placetype":[
        "aat:300008347"
    ]
},
  "bbox": [],
  "geometry": {"coordinates":[40.2667,20.15],"type":"Point"}
}