<<<<<<< HEAD
{
  "id": 7178679,
  "type": "Feature",
  "properties": {
    "tgn:hierarchy":[
        "tgn:7178679",
        "tgn:1000003",
        "tgn:7003676",
        "tgn:7000084",
        "tgn:7029392"
    ],
    "tgn:id":7178679,
    "tgn:name":"Hammersteins H\u00f6he",
    "tgn:placetype":[
        "aat:300008777"
    ]
},
  "bbox": [],
  "geometry": {"coordinates":[10.05,52.05],"type":"Point"}
}
=======
{"geometry":{"type":"Point","coordinates":[10.050000,52.050000]},"type":"Feature","properties":{"hierarchy":["tgn:7178679","tgn:1000003","tgn:7003676","tgn:7000084","tgn:7029392"],"placetype":["aat:300008777"],"id":7178679,"name:xx":"Hammersteins H\u00f6he"}}
>>>>>>> 03f74aca74312dbeaf24d7e61306dd6a786dc3d0
