{
  "id": 7178679,
  "type": "Feature",
  "properties": {
    "tgn:hierarchy":[
        "tgn:7178679",
        "tgn:1000003",
        "tgn:7003676",
        "tgn:7000084",
        "tgn:7029392"
    ],
    "tgn:id":7178679,
    "tgn:name":"Hammersteins H\u00f6he",
    "tgn:placetype":[
        "aat:300008777"
    ]
},
  "bbox": [],
  "geometry": {"coordinates":[10.05,52.05],"type":"Point"}
}