<<<<<<< HEAD
{
  "id": 7056806,
  "type": "Feature",
  "properties": {
    "tgn:hierarchy":[
        "tgn:7056806",
        "tgn:1000003",
        "tgn:7003142",
        "tgn:7003236",
        "tgn:1000080",
        "tgn:7029392"
    ],
    "tgn:id":7056806,
    "tgn:name":"Belnome",
    "tgn:placetype":[
        "aat:300008347"
    ]
},
  "bbox": [],
  "geometry": {"coordinates":[9.25,44.65],"type":"Point"}
}
=======
{"geometry":{"type":"Point","coordinates":[9.250000,44.650000]},"type":"Feature","properties":{"hierarchy":["tgn:7056806","tgn:1000003","tgn:7003142","tgn:7003236","tgn:1000080","tgn:7029392"],"placetype":["aat:300008347"],"id":7056806,"name:xx":"Belnome"}}
>>>>>>> 03f74aca74312dbeaf24d7e61306dd6a786dc3d0
