{
  "id": 6004932,
  "type": "Feature",
  "properties": {
    "tgn:hierarchy":[
        "tgn:6004932",
        "tgn:1000004",
        "tgn:1002053",
        "tgn:1000140",
        "tgn:7029392"
    ],
    "tgn:id":6004932,
    "tgn:name":"Ragh\u0101nah",
    "tgn:placetype":[
        "aat:300008347",
        "aat:300167671",
        "aat:300008057"
    ]
},
  "bbox": [],
  "geometry": {"coordinates":[36.406,34.933],"type":"Point"}
}