{
  "id": 7491942,
  "type": "Feature",
  "properties": {
    "tgn:hierarchy":[
        "tgn:7491942",
        "tgn:1000004",
        "tgn:7467799",
        "tgn:1000141",
        "tgn:7029392"
    ],
    "tgn:id":7491942,
    "tgn:name":"Dalupan",
    "tgn:placetype":[
        "aat:300008347"
    ]
},
  "bbox": [],
  "geometry": {"coordinates":[120.564651,23.994552],"type":"Point"}
}