{
  "id": 2258881,
  "type": "Feature",
  "properties": {
    "tgn:hierarchy":[
        "tgn:2258881",
        "tgn:1000001",
        "tgn:7012149",
        "tgn:2001212",
        "tgn:7007523",
        "tgn:7029392"
    ],
    "tgn:id":2258881,
    "tgn:name":"Cottonwood Creek",
    "tgn:placetype":[
        "aat:300008706"
    ]
},
  "bbox": [],
  "geometry": {"coordinates":[-93.6833,39.0833],"type":"Point"}
}