<<<<<<< HEAD
{
  "id": 2258881,
  "type": "Feature",
  "properties": {
    "tgn:hierarchy":[
        "tgn:2258881",
        "tgn:1000001",
        "tgn:7012149",
        "tgn:2001212",
        "tgn:7007523",
        "tgn:7029392"
    ],
    "tgn:id":2258881,
    "tgn:name":"Cottonwood Creek",
    "tgn:placetype":[
        "aat:300008706"
    ]
},
  "bbox": [],
  "geometry": {"coordinates":[-93.6833,39.0833],"type":"Point"}
}
=======
{"geometry":{"type":"Point","coordinates":[-93.683300,39.083300]},"type":"Feature","properties":{"hierarchy":["tgn:2258881","tgn:1000001","tgn:7012149","tgn:2001212","tgn:7007523","tgn:7029392"],"placetype":["aat:300008706"],"id":2258881,"name:xx":"Cottonwood Creek"}}
>>>>>>> 03f74aca74312dbeaf24d7e61306dd6a786dc3d0
