{
  "id": 2462534,
  "type": "Feature",
  "properties": {
    "tgn:hierarchy":[
        "tgn:2462534",
        "tgn:1000001",
        "tgn:2002108",
        "tgn:7012149",
        "tgn:7007827",
        "tgn:7029392"
    ],
    "tgn:id":2462534,
    "tgn:name":"Little Wild Horse Mesa",
    "tgn:placetype":[
        "aat:300008798"
    ]
},
  "bbox": [],
  "geometry": {"coordinates":[-110.85,38.5333],"type":"Point"}
}