{
  "id": 2380221,
  "type": "Feature",
  "properties": {
    "tgn:hierarchy":[
        "tgn:2380221",
        "tgn:1000001",
        "tgn:7012149",
        "tgn:2000826",
        "tgn:7007255",
        "tgn:7029392"
    ],
    "tgn:id":2380221,
    "tgn:name":"Hathaway Creek",
    "tgn:placetype":[
        "aat:300008706"
    ]
},
  "bbox": [],
  "geometry": {"coordinates":[-83.6667,37.9333],"type":"Point"}
}