{
  "id": 2432203,
  "type": "Feature",
  "properties": {
    "tgn:hierarchy":[
        "tgn:2432203",
        "tgn:1000001",
        "tgn:2002261",
        "tgn:7012149",
        "tgn:7013961",
        "tgn:7029392"
    ],
    "tgn:id":2432203,
    "tgn:name":"Kaymoor Number 1",
    "tgn:placetype":[
        "aat:300008347"
    ]
},
  "bbox": [],
  "geometry": {"coordinates":[-81.0667,38.0333],"type":"Point"}
}