{
  "id": 7253256,
  "type": "Feature",
  "properties": {
    "tgn:hierarchy":[
        "tgn:7253256",
        "tgn:7007877",
        "tgn:1000003",
        "tgn:1000063",
        "tgn:4012014",
        "tgn:7029392"
    ],
    "tgn:id":7253256,
    "tgn:name":"Saussois",
    "tgn:placetype":[
        "aat:300008699"
    ]
},
  "bbox": [],
  "geometry": {"coordinates":[4.077188,50.563365],"type":"Point"}
}