{
  "id": 2656722,
  "type": "Feature",
  "properties": {
    "tgn:hierarchy":[
        "tgn:2656722",
        "tgn:1000001",
        "tgn:2001703",
        "tgn:7012149",
        "tgn:7007708",
        "tgn:7029392"
    ],
    "tgn:id":2656722,
    "tgn:name":"Sheep Creek",
    "tgn:placetype":[
        "aat:300008706"
    ]
},
  "bbox": [],
  "geometry": {"coordinates":[-120.45,44.2667],"type":"Point"}
}