<<<<<<< HEAD
{
  "id": 2764627,
  "type": "Feature",
  "properties": {
    "tgn:hierarchy":[
        "tgn:2764627",
        "tgn:1000001",
        "tgn:7012149",
        "tgn:2002119",
        "tgn:7007827",
        "tgn:7029392"
    ],
    "tgn:id":2764627,
    "tgn:name":"Whipstock Draw",
    "tgn:placetype":[
        "aat:300008761"
    ]
},
  "bbox": [],
  "geometry": {"coordinates":[-109.3667,37.7667],"type":"Point"}
}
=======
{"geometry":{"type":"Point","coordinates":[-109.366700,37.766700]},"type":"Feature","properties":{"hierarchy":["tgn:2764627","tgn:1000001","tgn:7012149","tgn:2002119","tgn:7007827","tgn:7029392"],"placetype":["aat:300008761"],"id":2764627,"name:xx":"Whipstock Draw"}}
>>>>>>> 03f74aca74312dbeaf24d7e61306dd6a786dc3d0
