<<<<<<< HEAD
{
  "id": 7113713,
  "type": "Feature",
  "properties": {
    "tgn:hierarchy":[
        "tgn:7113713",
        "tgn:7003669",
        "tgn:1000003",
        "tgn:7000084",
        "tgn:7029392"
    ],
    "tgn:id":7113713,
    "tgn:name":"Rieglersreuth",
    "tgn:placetype":[
        "aat:300008347"
    ]
},
  "bbox": [],
  "geometry": {"coordinates":[11.766667,50.133333],"type":"Point"}
}
=======
{"geometry":{"type":"Point","coordinates":[11.766667,50.133333]},"type":"Feature","properties":{"hierarchy":["tgn:7113713","tgn:7003669","tgn:1000003","tgn:7000084","tgn:7029392"],"placetype":["aat:300008347"],"id":7113713,"name:xx":"Rieglersreuth"}}
>>>>>>> 03f74aca74312dbeaf24d7e61306dd6a786dc3d0
