{
  "id": 7240937,
  "type": "Feature",
  "properties": {
    "tgn:hierarchy":[
        "tgn:7240937",
        "tgn:7003461",
        "tgn:1000003",
        "tgn:1000063",
        "tgn:7018236",
        "tgn:7029392"
    ],
    "tgn:id":7240937,
    "tgn:name":"Fonteintje",
    "tgn:placetype":[
        "aat:300008347"
    ]
},
  "bbox": [],
  "geometry": {"coordinates":[5.333333,51.083333],"type":"Point"}
}