{
  "id": 2352074,
  "type": "Feature",
  "properties": {
    "tgn:hierarchy":[
        "tgn:2352074",
        "tgn:7006450",
        "tgn:1000001",
        "tgn:2124089",
        "tgn:7012149",
        "tgn:7029392"
    ],
    "tgn:id":2352074,
    "tgn:name":"Glory Lake",
    "tgn:placetype":[
        "aat:300008680"
    ]
},
  "bbox": [],
  "geometry": {"coordinates":[-134.1333,58.3833],"type":"Point"}
}