{
  "id": 7562058,
  "type": "Feature",
  "properties": {
    "tgn:hierarchy":[
        "tgn:7562058",
        "tgn:1000004",
        "tgn:7000198",
        "tgn:7016722",
        "tgn:7029392"
    ],
    "tgn:id":7562058,
    "tgn:name:en":"Sah\u0101ra",
    "tgn:placetype":[
        "aat:300008347"
    ]
},
  "bbox": [],
  "geometry": {"coordinates":[79.290839,27.078243],"type":"Point"}
}