{
  "id": 7397165,
  "type": "Feature",
  "properties": {
    "tgn:hierarchy":[
        "tgn:7397165",
        "tgn:1001853",
        "tgn:1000001",
        "tgn:7005560",
        "tgn:7029392"
    ],
    "tgn:id":7397165,
    "tgn:name":"Santa Eulalia",
    "tgn:placetype":[
        "aat:300008347"
    ]
},
  "bbox": [],
  "geometry": {"coordinates":[-103.616667,27.133333],"type":"Point"}
}