{
  "id": 2760408,
  "type": "Feature",
  "properties": {
    "tgn:hierarchy":[
        "tgn:2760408",
        "tgn:1000001",
        "tgn:2001477",
        "tgn:7012149",
        "tgn:7007709",
        "tgn:7029392"
    ],
    "tgn:id":2760408,
    "tgn:name":"West Fork South River",
    "tgn:placetype":[
        "aat:300008707"
    ]
},
  "bbox": [],
  "geometry": {"coordinates":[-76.5167,34.8667],"type":"Point"}
}