<<<<<<< HEAD
{
  "id": 2760408,
  "type": "Feature",
  "properties": {
    "tgn:hierarchy":[
        "tgn:2760408",
        "tgn:1000001",
        "tgn:2001477",
        "tgn:7012149",
        "tgn:7007709",
        "tgn:7029392"
    ],
    "tgn:id":2760408,
    "tgn:name":"West Fork South River",
    "tgn:placetype":[
        "aat:300008707"
    ]
},
  "bbox": [],
  "geometry": {"coordinates":[-76.5167,34.8667],"type":"Point"}
}
=======
{"geometry":{"type":"Point","coordinates":[-76.516700,34.866700]},"type":"Feature","properties":{"hierarchy":["tgn:2760408","tgn:1000001","tgn:2001477","tgn:7012149","tgn:7007709","tgn:7029392"],"placetype":["aat:300008707"],"id":2760408,"name:xx":"West Fork South River"}}
>>>>>>> 03f74aca74312dbeaf24d7e61306dd6a786dc3d0
