{
  "id": 7533544,
  "type": "Feature",
  "properties": {
    "tgn:hierarchy":[
        "tgn:7533544",
        "tgn:7001242",
        "tgn:7016833",
        "tgn:1001335",
        "tgn:7029392"
    ],
    "tgn:id":7533544,
    "tgn:name:en":"Kafr Ibr\u00e2h\u00eem",
    "tgn:placetype":[
        "aat:300008347"
    ]
},
  "bbox": [],
  "geometry": {"coordinates":[30.662773,31.113477],"type":"Point"}
}