{
  "id": 2007681,
  "type": "Feature",
  "properties": {
    "tgn:hierarchy":[
        "tgn:2007681",
        "tgn:1000001",
        "tgn:7016172",
        "tgn:7012149",
        "tgn:2000136",
        "tgn:7029392"
    ],
    "tgn:id":2007681,
    "tgn:name":"Batesville",
    "tgn:placetype":[
        "aat:300008347"
    ]
},
  "bbox": [],
  "geometry": {"coordinates":[-91.6333,35.7667],"type":"Point"}
}