<<<<<<< HEAD
{
  "id": 7174855,
  "type": "Feature",
  "properties": {
    "tgn:hierarchy":[
        "tgn:7174855",
        "tgn:7003692",
        "tgn:1000003",
        "tgn:7000084",
        "tgn:7029392"
    ],
    "tgn:id":7174855,
    "tgn:name":"Grobekopf",
    "tgn:placetype":[
        "aat:300000206"
    ]
},
  "bbox": [],
  "geometry": {"coordinates":[8.133333,48.633333],"type":"Point"}
}
=======
{"geometry":{"type":"Point","coordinates":[8.133333,48.633333]},"type":"Feature","properties":{"hierarchy":["tgn:7174855","tgn:7003692","tgn:1000003","tgn:7000084","tgn:7029392"],"placetype":["aat:300000206"],"id":7174855,"name:xx":"Grobekopf"}}
>>>>>>> 03f74aca74312dbeaf24d7e61306dd6a786dc3d0
