{
  "id": 7293085,
  "type": "Feature",
  "properties": {
    "tgn:hierarchy":[
        "tgn:7293085",
        "tgn:1001699",
        "tgn:1000049",
        "tgn:1000002",
        "tgn:7029392"
    ],
    "tgn:id":7293085,
    "tgn:name":"El Mocho, Cerro",
    "tgn:placetype":[
        "aat:300008795"
    ]
},
  "bbox": [],
  "geometry": {"coordinates":[-72.033333,-39.933333],"type":"Point"}
}