{
  "id": 7580901,
  "type": "Feature",
  "properties": {
    "tgn:hierarchy":[
        "tgn:7580901",
        "tgn:1000004",
        "tgn:7000198",
        "tgn:1001894",
        "tgn:7029392"
    ],
    "tgn:id":7580901,
    "tgn:name:en":"Tilw\u0101r\u0101gh\u0101t",
    "tgn:placetype":[
        "aat:300008347"
    ]
},
  "bbox": [],
  "geometry": {"coordinates":[80.866667,23.116667],"type":"Point"}
}