{
  "id": 2240070,
  "type": "Feature",
  "properties": {
    "tgn:hierarchy":[
        "tgn:2240070",
        "tgn:1000001",
        "tgn:2001419",
        "tgn:7012149",
        "tgn:7007526",
        "tgn:7029392"
    ],
    "tgn:id":2240070,
    "tgn:name":"Cinnabar Ridge",
    "tgn:placetype":[
        "aat:300266640"
    ]
},
  "bbox": [],
  "geometry": {"coordinates":[-117.8167,40.2667],"type":"Point"}
}