{
  "id": 7500270,
  "type": "Feature",
  "properties": {
    "tgn:hierarchy":[
        "tgn:7500270",
        "tgn:1000004",
        "tgn:7001009",
        "tgn:1000141",
        "tgn:7029392"
    ],
    "tgn:id":7500270,
    "tgn:name":"Xiaxintian",
    "tgn:placetype":[
        "aat:300008347"
    ]
},
  "bbox": [],
  "geometry": {"coordinates":[120.724022,24.202588],"type":"Point"}
}