{
  "id": 2278013,
  "type": "Feature",
  "properties": {
    "tgn:hierarchy":[
        "tgn:2278013",
        "tgn:1000001",
        "tgn:1002714",
        "tgn:7012149",
        "tgn:7007159",
        "tgn:7029392"
    ],
    "tgn:id":2278013,
    "tgn:name":"Day Pond Brook",
    "tgn:placetype":[
        "aat:300008699"
    ]
},
  "bbox": [],
  "geometry": {"coordinates":[-72.4167,41.5333],"type":"Point"}
}