{
  "id": 7209356,
  "type": "Feature",
  "properties": {
    "tgn:hierarchy":[
        "tgn:7209356",
        "tgn:1000003",
        "tgn:7003678",
        "tgn:7000084",
        "tgn:7029392"
    ],
    "tgn:id":7209356,
    "tgn:name":"Bechtels-Berg",
    "tgn:placetype":[
        "aat:300008777"
    ]
},
  "bbox": [],
  "geometry": {"coordinates":[9.366667,50.783333],"type":"Point"}
}