<<<<<<< HEAD
{
  "id": 2158770,
  "type": "Feature",
  "properties": {
    "tgn:hierarchy":[
        "tgn:2158770",
        "tgn:1000001",
        "tgn:7012149",
        "tgn:7007255",
        "tgn:7029392"
    ],
    "tgn:id":2158770,
    "tgn:name":"Beck Hollow",
    "tgn:placetype":[
        "aat:300008761"
    ]
},
  "bbox": [],
  "geometry": {"coordinates":[-85.5333,36.8667],"type":"Point"}
}
=======
{"geometry":{"type":"Point","coordinates":[-85.533300,36.866700]},"type":"Feature","properties":{"hierarchy":["tgn:2158770","tgn:1000001","tgn:7012149","tgn:7007255","tgn:7029392"],"placetype":["aat:300008761"],"id":2158770,"name:xx":"Beck Hollow"}}
>>>>>>> 03f74aca74312dbeaf24d7e61306dd6a786dc3d0
