{
  "id": 2189796,
  "type": "Feature",
  "properties": {
    "tgn:hierarchy":[
        "tgn:2189796",
        "tgn:1000001",
        "tgn:7012149",
        "tgn:7014350",
        "tgn:7007922",
        "tgn:7029392"
    ],
    "tgn:id":2189796,
    "tgn:name":"Bowers Lake",
    "tgn:placetype":[
        "aat:300008905"
    ]
},
  "bbox": [],
  "geometry": {"coordinates":[-88.9167,42.7833],"type":"Point"}
}