<<<<<<< HEAD
{
  "id": 7364103,
  "type": "Feature",
  "properties": {
    "tgn:hierarchy":[
        "tgn:7364103",
        "tgn:1000001",
        "tgn:1001960",
        "tgn:7005560",
        "tgn:7029392"
    ],
    "tgn:id":7364103,
    "tgn:name":"Rancho El Chupadero",
    "tgn:placetype":[
        "aat:300000241"
    ]
},
  "bbox": [],
  "geometry": {"coordinates":[-111.15,30.666667],"type":"Point"}
}
=======
{"geometry":{"type":"Point","coordinates":[-111.150000,30.666667]},"type":"Feature","properties":{"hierarchy":["tgn:7364103","tgn:1000001","tgn:1001960","tgn:7005560","tgn:7029392"],"placetype":["aat:300000241"],"id":7364103,"name:xx":"Rancho El Chupadero"}}
>>>>>>> 03f74aca74312dbeaf24d7e61306dd6a786dc3d0
