{
  "id": 1007746,
  "type": "Feature",
  "properties": {
    "tgn:hierarchy":[
        "tgn:1007746",
        "tgn:1000004",
        "tgn:7000190",
        "tgn:1000105",
        "tgn:7029392"
    ],
    "tgn:id":1007746,
    "tgn:name":"Kukuri Mukuri Char",
    "tgn:placetype":[
        "aat:300008791"
    ]
},
  "bbox": [],
  "geometry": {"coordinates":[90.65,21.9333],"type":"Point"}
}