{
  "id": 7388926,
  "type": "Feature",
  "properties": {
    "tgn:hierarchy":[
        "tgn:7388926",
        "tgn:1000001",
        "tgn:7005599",
        "tgn:7005560",
        "tgn:7029392"
    ],
    "tgn:id":7388926,
    "tgn:name":"Pastor\u00edas",
    "tgn:placetype":[
        "aat:300008347"
    ]
},
  "bbox": [],
  "geometry": {"coordinates":[-96.55,19.533333],"type":"Point"}
}