{
  "id": 2407660,
  "type": "Feature",
  "properties": {
    "tgn:hierarchy":[
        "tgn:2407660",
        "tgn:1000001",
        "tgn:7012149",
        "tgn:2000476",
        "tgn:7007250",
        "tgn:7029392"
    ],
    "tgn:id":2407660,
    "tgn:name":"Hurley Creek",
    "tgn:placetype":[
        "aat:300008706"
    ]
},
  "bbox": [],
  "geometry": {"coordinates":[-116.1667,45.65],"type":"Point"}
}