<<<<<<< HEAD
{
  "id": 2407660,
  "type": "Feature",
  "properties": {
    "tgn:hierarchy":[
        "tgn:2407660",
        "tgn:1000001",
        "tgn:7012149",
        "tgn:2000476",
        "tgn:7007250",
        "tgn:7029392"
    ],
    "tgn:id":2407660,
    "tgn:name":"Hurley Creek",
    "tgn:placetype":[
        "aat:300008706"
    ]
},
  "bbox": [],
  "geometry": {"coordinates":[-116.1667,45.65],"type":"Point"}
}
=======
{"geometry":{"type":"Point","coordinates":[-116.166700,45.650000]},"type":"Feature","properties":{"hierarchy":["tgn:2407660","tgn:1000001","tgn:7012149","tgn:2000476","tgn:7007250","tgn:7029392"],"placetype":["aat:300008706"],"id":2407660,"name:xx":"Hurley Creek"}}
>>>>>>> 03f74aca74312dbeaf24d7e61306dd6a786dc3d0
