{
  "id": 7225159,
  "type": "Feature",
  "properties": {
    "tgn:hierarchy":[
        "tgn:7225159",
        "tgn:7002724",
        "tgn:7002715",
        "tgn:1000003",
        "tgn:1000074",
        "tgn:7029392"
    ],
    "tgn:id":7225159,
    "tgn:name":"R\u00e1mnitsa",
    "tgn:placetype":[
        "aat:300266640"
    ]
},
  "bbox": [],
  "geometry": {"coordinates":[21.05,40.75],"type":"Point"}
}