{
  "id": 2315938,
  "type": "Feature",
  "properties": {
    "tgn:hierarchy":[
        "tgn:2315938",
        "tgn:1000001",
        "tgn:7012149",
        "tgn:2001386",
        "tgn:7007525",
        "tgn:7029392"
    ],
    "tgn:id":2315938,
    "tgn:name":"Elm Creek",
    "tgn:placetype":[
        "aat:300008706"
    ]
},
  "bbox": [],
  "geometry": {"coordinates":[-97.5667,41.65],"type":"Point"}
}