{
  "id": 7166434,
  "type": "Feature",
  "properties": {
    "tgn:hierarchy":[
        "tgn:7166434",
        "tgn:7003692",
        "tgn:1000003",
        "tgn:7000084",
        "tgn:7029392"
    ],
    "tgn:id":7166434,
    "tgn:name":"Hausen ob Rottweil",
    "tgn:placetype":[
        "aat:300008347"
    ]
},
  "bbox": [],
  "geometry": {"coordinates":[8.583333,48.15],"type":"Point"}
}