{
  "id": 2558380,
  "type": "Feature",
  "properties": {
    "tgn:hierarchy":[
        "tgn:2558380",
        "tgn:1000001",
        "tgn:2000307",
        "tgn:7012149",
        "tgn:7007248",
        "tgn:7029392"
    ],
    "tgn:id":2558380,
    "tgn:name":"Oliff Pond",
    "tgn:placetype":[
        "aat:300006191"
    ]
},
  "bbox": [],
  "geometry": {"coordinates":[-81.9333,32.2833],"type":"Point"}
}