{
  "id": 7484528,
  "type": "Feature",
  "properties": {
    "tgn:hierarchy":[
        "tgn:7484528",
        "tgn:1000004",
        "tgn:7492971",
        "tgn:1000141",
        "tgn:7029392"
    ],
    "tgn:id":7484528,
    "tgn:name":"Shinan Xi",
    "tgn:placetype":[
        "aat:300008699"
    ]
},
  "bbox": [],
  "geometry": {"coordinates":[120.629167,22.423056],"type":"Point"}
}