<<<<<<< HEAD
{
  "id": 7025898,
  "type": "Feature",
  "properties": {
    "tgn:hierarchy":[
        "tgn:7025898",
        "tgn:7002445",
        "tgn:1000003",
        "tgn:7011961",
        "tgn:7008591",
        "tgn:7029392"
    ],
    "tgn:id":7025898,
    "tgn:name:ang":"Hame",
    "tgn:placetype":[
        "aat:300008347"
    ]
},
  "bbox": [],
  "geometry": {"coordinates":[-2.266667,50.933333],"type":"Point"}
}
=======
{"geometry":{"type":"Point","coordinates":[-2.266667,50.933333]},"type":"Feature","properties":{"hierarchy":["tgn:7025898","tgn:7002445","tgn:1000003","tgn:7011961","tgn:7008591","tgn:7029392"],"placetype":["aat:300008347"],"id":7025898,"name:ang":"Hame"}}
>>>>>>> 03f74aca74312dbeaf24d7e61306dd6a786dc3d0
