{
  "id": 2690300,
  "type": "Feature",
  "properties": {
    "tgn:hierarchy":[
        "tgn:2690300",
        "tgn:1000001",
        "tgn:7012149",
        "tgn:2001866",
        "tgn:7007825",
        "tgn:7029392"
    ],
    "tgn:id":2690300,
    "tgn:name":"Stage Creek",
    "tgn:placetype":[
        "aat:300008706"
    ]
},
  "bbox": [],
  "geometry": {"coordinates":[-82.7167,36.1333],"type":"Point"}
}