{
  "id": 7262143,
  "type": "Feature",
  "properties": {
    "tgn:hierarchy":[
        "tgn:7262143",
        "tgn:7003619",
        "tgn:1000003",
        "tgn:7016845",
        "tgn:7029392"
    ],
    "tgn:id":7262143,
    "tgn:name:nl":"Gendtsche Polder",
    "tgn:placetype":[
        "aat:300006163"
    ]
},
  "bbox": [],
  "geometry": {"coordinates":[5.966667,51.866667],"type":"Point"}
}