{
  "id": 1066328,
  "type": "Feature",
  "properties": {
    "tgn:hierarchy":[
        "tgn:1066328",
        "tgn:1000004",
        "tgn:7002190",
        "tgn:1000108",
        "tgn:7029392"
    ],
    "tgn:id":1066328,
    "tgn:name":"Ving Ng\u00fcn",
    "tgn:placetype":[
        "aat:300008347"
    ]
},
  "bbox": [],
  "geometry": {"coordinates":[99.2667,22.6167],"type":"Point"}
}