{
  "id": 7535660,
  "type": "Feature",
  "properties": {
    "tgn:hierarchy":[
        "tgn:7535660",
        "tgn:7001242",
        "tgn:1001075",
        "tgn:7016833",
        "tgn:7029392"
    ],
    "tgn:id":7535660,
    "tgn:name:en":"Khamm\u0101rah",
    "tgn:placetype":[
        "aat:300008347"
    ]
},
  "bbox": [],
  "geometry": {"coordinates":[30.610278,30.853333],"type":"Point"}
}