{
  "id": 1065818,
  "type": "Feature",
  "properties": {
    "tgn:hierarchy":[
        "tgn:1065818",
        "tgn:1000004",
        "tgn:7032097",
        "tgn:1000105",
        "tgn:7029392"
    ],
    "tgn:id":1065818,
    "tgn:name":"Maulvi B\u0101z\u0101r",
    "tgn:placetype":[
        "aat:300008347"
    ]
},
  "bbox": [],
  "geometry": {"coordinates":[91.7833,24.4833],"type":"Point"}
}