{
  "id": 2700406,
  "type": "Feature",
  "properties": {
    "tgn:hierarchy":[
        "tgn:2700406",
        "tgn:1000001",
        "tgn:7012149",
        "tgn:2001718",
        "tgn:7007708",
        "tgn:7029392"
    ],
    "tgn:id":2700406,
    "tgn:name":"Subsoiler Reservoir",
    "tgn:placetype":[
        "aat:300006191"
    ]
},
  "bbox": [],
  "geometry": {"coordinates":[-117.1667,42.7167],"type":"Point"}
}