{
  "id": 2122876,
  "type": "Feature",
  "properties": {
    "tgn:hierarchy":[
        "tgn:2122876",
        "tgn:2002365",
        "tgn:1000001",
        "tgn:7012149",
        "tgn:7007923",
        "tgn:7029392"
    ],
    "tgn:id":2122876,
    "tgn:name":"Colores",
    "tgn:placetype":[
        "aat:300387016"
    ]
},
  "bbox": [],
  "geometry": {"coordinates":[-105.5167,41.15],"type":"Point"}
}