<<<<<<< HEAD
{
  "id": 2763246,
  "type": "Feature",
  "properties": {
    "tgn:hierarchy":[
        "tgn:2763246",
        "tgn:2002138",
        "tgn:1000001",
        "tgn:7012149",
        "tgn:7007919",
        "tgn:7029392"
    ],
    "tgn:id":2763246,
    "tgn:name":"Westwood Place",
    "tgn:placetype":[
        "aat:300008347"
    ]
},
  "bbox": [],
  "geometry": {"coordinates":[-80.0167,37.8],"type":"Point"}
}
=======
{"geometry":{"type":"Point","coordinates":[-80.016700,37.800000]},"type":"Feature","properties":{"hierarchy":["tgn:2763246","tgn:2002138","tgn:1000001","tgn:7012149","tgn:7007919","tgn:7029392"],"placetype":["aat:300008347"],"id":2763246,"name:xx":"Westwood Place"}}
>>>>>>> 03f74aca74312dbeaf24d7e61306dd6a786dc3d0
