<<<<<<< HEAD
{
  "id": 2330991,
  "type": "Feature",
  "properties": {
    "tgn:hierarchy":[
        "tgn:2330991",
        "tgn:1000001",
        "tgn:7016172",
        "tgn:7012149",
        "tgn:2000162",
        "tgn:7029392"
    ],
    "tgn:id":2330991,
    "tgn:name":"Flat Rock Hollow",
    "tgn:placetype":[
        "aat:300008761"
    ]
},
  "bbox": [],
  "geometry": {"coordinates":[-93.1333,35.6333],"type":"Point"}
}
=======
{"geometry":{"type":"Point","coordinates":[-93.133300,35.633300]},"type":"Feature","properties":{"hierarchy":["tgn:2330991","tgn:1000001","tgn:7016172","tgn:7012149","tgn:2000162","tgn:7029392"],"placetype":["aat:300008761"],"id":2330991,"name:xx":"Flat Rock Hollow"}}
>>>>>>> 03f74aca74312dbeaf24d7e61306dd6a786dc3d0
