{
  "id": 1084172,
  "type": "Feature",
  "properties": {
    "tgn:hierarchy":[
        "tgn:1084172",
        "tgn:1000004",
        "tgn:1001610",
        "tgn:1000135",
        "tgn:7029392"
    ],
    "tgn:id":1084172,
    "tgn:name":"Dapitan",
    "tgn:placetype":[
        "aat:300008347"
    ]
},
  "bbox": [],
  "geometry": {"coordinates":[123.4333,8.65],"type":"Point"}
}