{
  "id": 2741792,
  "type": "Feature",
  "properties": {
    "tgn:hierarchy":[
        "tgn:2741792",
        "tgn:1000001",
        "tgn:7012149",
        "tgn:2001444",
        "tgn:7007566",
        "tgn:7029392"
    ],
    "tgn:id":2741792,
    "tgn:name":"Uvas Valley",
    "tgn:placetype":[
        "aat:300008761"
    ]
},
  "bbox": [],
  "geometry": {"coordinates":[-107.3333,32.3333],"type":"Point"}
}