{
  "id": 7549221,
  "type": "Feature",
  "properties": {
    "tgn:hierarchy":[
        "tgn:7549221",
        "tgn:1000004",
        "tgn:7000198",
        "tgn:1001882",
        "tgn:7029392"
    ],
    "tgn:id":7549221,
    "tgn:name:en":"Edl\u0101pur",
    "tgn:placetype":[
        "aat:300008347"
    ]
},
  "bbox": [],
  "geometry": {"coordinates":[77.333333,16.366667],"type":"Point"}
}