<<<<<<< HEAD
{
  "id": 7379590,
  "type": "Feature",
  "properties": {
    "tgn:hierarchy":[
        "tgn:7379590",
        "tgn:7005585",
        "tgn:1000001",
        "tgn:7005560",
        "tgn:7029392"
    ],
    "tgn:id":7379590,
    "tgn:name":"Miguelito",
    "tgn:placetype":[
        "aat:300008347"
    ]
},
  "bbox": [],
  "geometry": {"coordinates":[-101.366667,17.65],"type":"Point"}
}
=======
{"geometry":{"type":"Point","coordinates":[-101.366667,17.650000]},"type":"Feature","properties":{"hierarchy":["tgn:7379590","tgn:7005585","tgn:1000001","tgn:7005560","tgn:7029392"],"placetype":["aat:300008347"],"id":7379590,"name:xx":"Miguelito"}}
>>>>>>> 03f74aca74312dbeaf24d7e61306dd6a786dc3d0
