{
  "id": 7099083,
  "type": "Feature",
  "properties": {
    "tgn:hierarchy":[
        "tgn:7099083",
        "tgn:7003692",
        "tgn:1000003",
        "tgn:7000084",
        "tgn:7029392"
    ],
    "tgn:id":7099083,
    "tgn:name":"Sommerwald",
    "tgn:placetype":[
        "aat:300008863"
    ]
},
  "bbox": [],
  "geometry": {"coordinates":[8.35,48.033333],"type":"Point"}
}