{
  "id": 7548241,
  "type": "Feature",
  "properties": {
    "tgn:hierarchy":[
        "tgn:7548241",
        "tgn:1000004",
        "tgn:1001871",
        "tgn:7000198",
        "tgn:7029392"
    ],
    "tgn:id":7548241,
    "tgn:name:en":"Aurang\u0101b\u0101d",
    "tgn:placetype":[
        "aat:300008347"
    ]
},
  "bbox": [],
  "geometry": {"coordinates":[77.328757,28.02798],"type":"Point"}
}