{
  "id": 7277570,
  "type": "Feature",
  "properties": {
    "tgn:hierarchy":[
        "tgn:7277570",
        "tgn:1001768",
        "tgn:1000049",
        "tgn:1000002",
        "tgn:7029392"
    ],
    "tgn:id":7277570,
    "tgn:name":"Llolleo, Playa",
    "tgn:placetype":[
        "aat:300008816"
    ]
},
  "bbox": [],
  "geometry": {"coordinates":[-71.625,-33.602778],"type":"Point"}
}