{
  "id": 2316684,
  "type": "Feature",
  "properties": {
    "tgn:hierarchy":[
        "tgn:2316684",
        "tgn:1000001",
        "tgn:7012149",
        "tgn:7018871",
        "tgn:7007920",
        "tgn:7029392"
    ],
    "tgn:id":2316684,
    "tgn:name":"Embro Lake",
    "tgn:placetype":[
        "aat:300008680"
    ]
},
  "bbox": [],
  "geometry": {"coordinates":[-121.1667,47.7333],"type":"Point"}
}