{
  "id": 1083690,
  "type": "Feature",
  "properties": {
    "tgn:hierarchy":[
        "tgn:1083690",
        "tgn:7000360",
        "tgn:1000004",
        "tgn:1000133",
        "tgn:7029392"
    ],
    "tgn:id":1083690,
    "tgn:name":"Nirw\u0101no",
    "tgn:placetype":[
        "aat:300008347"
    ]
},
  "bbox": [],
  "geometry": {"coordinates":[62.7167,26.3667],"type":"Point"}
}