{
  "id": 2227171,
  "type": "Feature",
  "properties": {
    "tgn:hierarchy":[
        "tgn:2227171",
        "tgn:1000001",
        "tgn:2001183",
        "tgn:7012149",
        "tgn:7007523",
        "tgn:7029392"
    ],
    "tgn:id":2227171,
    "tgn:name":"Cave Hill",
    "tgn:placetype":[
        "aat:300008798"
    ]
},
  "bbox": [],
  "geometry": {"coordinates":[-93.8333,37.8667],"type":"Point"}
}