{
  "id": 2559297,
  "type": "Feature",
  "properties": {
    "tgn:hierarchy":[
        "tgn:2559297",
        "tgn:7006450",
        "tgn:1000001",
        "tgn:2124053",
        "tgn:7012149",
        "tgn:7029392"
    ],
    "tgn:id":2559297,
    "tgn:name":"Onestone Lake",
    "tgn:placetype":[
        "aat:300008680"
    ]
},
  "bbox": [],
  "geometry": {"coordinates":[-151.5167,61.9167],"type":"Point"}
}