{
  "id": 7301361,
  "type": "Feature",
  "properties": {
    "tgn:hierarchy":[
        "tgn:7301361",
        "tgn:7002813",
        "tgn:7002758",
        "tgn:1000003",
        "tgn:1000095",
        "tgn:7029392"
    ],
    "tgn:id":7301361,
    "tgn:name":"Mollina, Sierra de",
    "tgn:placetype":[
        "aat:300008795"
    ]
},
  "bbox": [],
  "geometry": {"coordinates":[-5.133333,36.916667],"type":"Point"}
}