<<<<<<< HEAD
{
  "id": 2334092,
  "type": "Feature",
  "properties": {
    "tgn:hierarchy":[
        "tgn:2334092",
        "tgn:1000001",
        "tgn:7012149",
        "tgn:7007522",
        "tgn:7029392"
    ],
    "tgn:id":2334092,
    "tgn:name":"Fords Creek",
    "tgn:placetype":[
        "aat:300008706"
    ]
},
  "bbox": [],
  "geometry": {"coordinates":[-90.3833,31.6667],"type":"Point"}
}
=======
{"geometry":{"type":"Point","coordinates":[-90.383300,31.666700]},"type":"Feature","properties":{"hierarchy":["tgn:2334092","tgn:1000001","tgn:7012149","tgn:7007522","tgn:7029392"],"placetype":["aat:300008706"],"id":2334092,"name:xx":"Fords Creek"}}
>>>>>>> 03f74aca74312dbeaf24d7e61306dd6a786dc3d0
