{
  "id": 2200116,
  "type": "Feature",
  "properties": {
    "tgn:hierarchy":[
        "tgn:2200116",
        "tgn:1000001",
        "tgn:7012149",
        "tgn:2001232",
        "tgn:7007523",
        "tgn:7029392"
    ],
    "tgn:id":2200116,
    "tgn:name":"Brushy Creek",
    "tgn:placetype":[
        "aat:300008706"
    ]
},
  "bbox": [],
  "geometry": {"coordinates":[-93.2333,37.5833],"type":"Point"}
}