{
  "id": 7077030,
  "type": "Feature",
  "properties": {
    "tgn:hierarchy":[
        "tgn:7077030",
        "tgn:1000003",
        "tgn:7003682",
        "tgn:7000084",
        "tgn:7029392"
    ],
    "tgn:id":7077030,
    "tgn:name":"Steinbachtalsperre",
    "tgn:placetype":[
        "aat:300006191"
    ]
},
  "bbox": [],
  "geometry": {"coordinates":[7.216667,49.766667],"type":"Point"}
}