<<<<<<< HEAD
{
  "id": 7170250,
  "type": "Feature",
  "properties": {
    "tgn:hierarchy":[
        "tgn:7170250",
        "tgn:1000003",
        "tgn:7003676",
        "tgn:7000084",
        "tgn:7029392"
    ],
    "tgn:id":7170250,
    "tgn:name":"Hestern",
    "tgn:placetype":[
        "aat:300000206"
    ]
},
  "bbox": [],
  "geometry": {"coordinates":[8.516667,53.0],"type":"Point"}
}
=======
{"geometry":{"type":"Point","coordinates":[8.516667,53.000000]},"type":"Feature","properties":{"hierarchy":["tgn:7170250","tgn:1000003","tgn:7003676","tgn:7000084","tgn:7029392"],"placetype":["aat:300000206"],"id":7170250,"name:xx":"Hestern"}}
>>>>>>> 03f74aca74312dbeaf24d7e61306dd6a786dc3d0
