{
  "id": 7439896,
  "type": "Feature",
  "properties": {
    "tgn:hierarchy":[
        "tgn:7439896",
        "tgn:1000001",
        "tgn:7005597",
        "tgn:7005560",
        "tgn:7029392"
    ],
    "tgn:id":7439896,
    "tgn:name":"San Pedro de Guti\u00e9rrez",
    "tgn:placetype":[
        "aat:300008347"
    ]
},
  "bbox": [],
  "geometry": {"coordinates":[-98.45,25.083333],"type":"Point"}
}