<<<<<<< HEAD
{
  "id": 7370814,
  "type": "Feature",
  "properties": {
    "tgn:hierarchy":[
        "tgn:7370814",
        "tgn:7005586",
        "tgn:1000001",
        "tgn:7005560",
        "tgn:7029392"
    ],
    "tgn:id":7370814,
    "tgn:name":"Huitzilapa",
    "tgn:placetype":[
        "aat:300000241"
    ]
},
  "bbox": [],
  "geometry": {"coordinates":[-103.9,20.85],"type":"Point"}
}
=======
{"geometry":{"type":"Point","coordinates":[-103.900000,20.850000]},"type":"Feature","properties":{"hierarchy":["tgn:7370814","tgn:7005586","tgn:1000001","tgn:7005560","tgn:7029392"],"placetype":["aat:300000241"],"id":7370814,"name:xx":"Huitzilapa"}}
>>>>>>> 03f74aca74312dbeaf24d7e61306dd6a786dc3d0
