{
  "id": 7045146,
  "type": "Feature",
  "properties": {
    "tgn:hierarchy":[
        "tgn:7045146",
        "tgn:1003464",
        "tgn:1000003",
        "tgn:7003241",
        "tgn:1000080",
        "tgn:7029392"
    ],
    "tgn:id":7045146,
    "tgn:name":"Castelnuovo, Monte",
    "tgn:placetype":[
        "aat:300008795"
    ]
},
  "bbox": [],
  "geometry": {"coordinates":[14.033333,41.633333],"type":"Point"}
}