{
  "id": 7341207,
  "type": "Feature",
  "properties": {
    "tgn:hierarchy":[
        "tgn:7341207",
        "tgn:7002834",
        "tgn:1000003",
        "tgn:7002786",
        "tgn:1000095",
        "tgn:7029392"
    ],
    "tgn:id":7341207,
    "tgn:name":"Briallos",
    "tgn:placetype":[
        "aat:300008347"
    ]
},
  "bbox": [],
  "geometry": {"coordinates":[-8.633333,42.566667],"type":"Point"}
}