{
  "id": 2719279,
  "type": "Feature",
  "properties": {
    "tgn:hierarchy":[
        "tgn:2719279",
        "tgn:1000001",
        "tgn:7012149",
        "tgn:2001544",
        "tgn:7007709",
        "tgn:7029392"
    ],
    "tgn:id":2719279,
    "tgn:name":"Thrash Branch",
    "tgn:placetype":[
        "aat:300008699"
    ]
},
  "bbox": [],
  "geometry": {"coordinates":[-82.6833,35.2667],"type":"Point"}
}