{
  "id": 2390191,
  "type": "Feature",
  "properties": {
    "tgn:hierarchy":[
        "tgn:2390191",
        "tgn:1000001",
        "tgn:7012149",
        "tgn:1003042",
        "tgn:7007920",
        "tgn:7029392"
    ],
    "tgn:id":2390191,
    "tgn:name":"High Top",
    "tgn:placetype":[
        "aat:300008798"
    ]
},
  "bbox": [],
  "geometry": {"coordinates":[-120.0833,46.4667],"type":"Point"}
}