{
  "id": 7071088,
  "type": "Feature",
  "properties": {
    "tgn:hierarchy":[
        "tgn:7071088",
        "tgn:7003669",
        "tgn:1000003",
        "tgn:7000084",
        "tgn:7029392"
    ],
    "tgn:id":7071088,
    "tgn:name":"Sylbach",
    "tgn:placetype":[
        "aat:300008347"
    ]
},
  "bbox": [],
  "geometry": {"coordinates":[10.516667,50.05],"type":"Point"}
}