{
  "id": 7318820,
  "type": "Feature",
  "properties": {
    "tgn:hierarchy":[
        "tgn:7318820",
        "tgn:1001699",
        "tgn:1000049",
        "tgn:1000002",
        "tgn:7029392"
    ],
    "tgn:id":7318820,
    "tgn:name":"Barrientos, Rocas",
    "tgn:placetype":[
        "aat:300011692"
    ]
},
  "bbox": [],
  "geometry": {"coordinates":[-73.05,-42.583333],"type":"Point"}
}