{
  "id": 7523790,
  "type": "Feature",
  "properties": {
    "tgn:hierarchy":[
        "tgn:7523790",
        "tgn:7001242",
        "tgn:7016833",
        "tgn:7001335",
        "tgn:7029392"
    ],
    "tgn:id":7523790,
    "tgn:name:en":"El Ageira",
    "tgn:placetype":[
        "aat:300386860"
    ]
},
  "bbox": [],
  "geometry": {"coordinates":[33.583056,30.883889],"type":"Point"}
}