{
  "id": 2584639,
  "type": "Feature",
  "properties": {
    "tgn:hierarchy":[
        "tgn:2584639",
        "tgn:1000001",
        "tgn:7012149",
        "tgn:7007825",
        "tgn:7029392"
    ],
    "tgn:id":2584639,
    "tgn:name":"Piney River Shoals",
    "tgn:placetype":[
        "aat:300132348"
    ]
},
  "bbox": [],
  "geometry": {"coordinates":[-84.7833,35.6167],"type":"Point"}
}