{
  "id": 2664127,
  "type": "Feature",
  "properties": {
    "tgn:hierarchy":[
        "tgn:2664127",
        "tgn:1000001",
        "tgn:7012149",
        "tgn:1002945",
        "tgn:7007710",
        "tgn:7029392"
    ],
    "tgn:id":2664127,
    "tgn:name":"Silver Run",
    "tgn:placetype":[
        "aat:300008699"
    ]
},
  "bbox": [],
  "geometry": {"coordinates":[-77.1667,41.6333],"type":"Point"}
}