{
  "id": 2481831,
  "type": "Feature",
  "properties": {
    "tgn:hierarchy":[
        "tgn:2481831",
        "tgn:1000001",
        "tgn:7016104",
        "tgn:7012149",
        "tgn:7007516",
        "tgn:7029392"
    ],
    "tgn:id":2481831,
    "tgn:name":"Landon Village",
    "tgn:placetype":[
        "aat:300008347"
    ]
},
  "bbox": [],
  "geometry": {"coordinates":[-77.1167,38.9833],"type":"Point"}
}