{
  "id": 2677357,
  "type": "Feature",
  "properties": {
    "tgn:hierarchy":[
        "tgn:2677357",
        "tgn:1000001",
        "tgn:7012149",
        "tgn:1003042",
        "tgn:7007920",
        "tgn:7029392"
    ],
    "tgn:id":2677357,
    "tgn:name":"South Butte",
    "tgn:placetype":[
        "aat:300008798"
    ]
},
  "bbox": [],
  "geometry": {"coordinates":[-121.4667,46.15],"type":"Point"}
}