{
  "id": 2597738,
  "type": "Feature",
  "properties": {
    "tgn:hierarchy":[
        "tgn:2597738",
        "tgn:1000001",
        "tgn:7012149",
        "tgn:2001274",
        "tgn:7007524",
        "tgn:7029392"
    ],
    "tgn:id":2597738,
    "tgn:name":"Pratt Lake",
    "tgn:placetype":[
        "aat:300008680"
    ]
},
  "bbox": [],
  "geometry": {"coordinates":[-114.0833,48.1667],"type":"Point"}
}