<<<<<<< HEAD
{
  "id": 2766145,
  "type": "Feature",
  "properties": {
    "tgn:hierarchy":[
        "tgn:2766145",
        "tgn:1000001",
        "tgn:2000470",
        "tgn:7012149",
        "tgn:7007250",
        "tgn:7029392"
    ],
    "tgn:id":2766145,
    "tgn:name":"White Knob Mountains",
    "tgn:placetype":[
        "aat:300386831"
    ]
},
  "bbox": [],
  "geometry": {"coordinates":[-113.7,43.8],"type":"Point"}
}
=======
{"geometry":{"type":"Point","coordinates":[-113.700000,43.800000]},"type":"Feature","properties":{"hierarchy":["tgn:2766145","tgn:1000001","tgn:2000470","tgn:7012149","tgn:7007250","tgn:7029392"],"placetype":["aat:300386831"],"id":2766145,"name:xx":"White Knob Mountains"}}
>>>>>>> 03f74aca74312dbeaf24d7e61306dd6a786dc3d0
