{
  "id": 1095731,
  "type": "Feature",
  "properties": {
    "tgn:hierarchy":[
        "tgn:1095731",
        "tgn:7001242",
        "tgn:7016833",
        "tgn:1001335",
        "tgn:7029392"
    ],
    "tgn:id":1095731,
    "tgn:name:en":"T\u012bdah",
    "tgn:placetype":[
        "aat:300008347"
    ]
},
  "bbox": [],
  "geometry": {"coordinates":[30.838153,31.244044],"type":"Point"}
}