{
  "id": 2706365,
  "type": "Feature",
  "properties": {
    "tgn:hierarchy":[
        "tgn:2706365",
        "tgn:1000001",
        "tgn:7012149",
        "tgn:2001910",
        "tgn:7007825",
        "tgn:7029392"
    ],
    "tgn:id":2706365,
    "tgn:name":"Swamps, The",
    "tgn:placetype":[
        "aat:300008905"
    ]
},
  "bbox": [],
  "geometry": {"coordinates":[-86.8333,36.55],"type":"Point"}
}