{
  "id": 2612120,
  "type": "Feature",
  "properties": {
    "tgn:hierarchy":[
        "tgn:2612120",
        "tgn:1000001",
        "tgn:7012149",
        "tgn:2000476",
        "tgn:7007250",
        "tgn:7029392"
    ],
    "tgn:id":2612120,
    "tgn:name":"Red Rock Spring",
    "tgn:placetype":[
        "aat:300008697"
    ]
},
  "bbox": [],
  "geometry": {"coordinates":[-116.4833,45.6667],"type":"Point"}
}