{
  "id": 7418147,
  "type": "Feature",
  "properties": {
    "tgn:hierarchy":[
        "tgn:7418147",
        "tgn:1001835",
        "tgn:1000001",
        "tgn:7005560",
        "tgn:7029392"
    ],
    "tgn:id":7418147,
    "tgn:name":"Comunidad Indigena Cucap\u00e1",
    "tgn:placetype":[
        "aat:300008347"
    ]
},
  "bbox": [],
  "geometry": {"coordinates":[-115.256667,32.119722],"type":"Point"}
}