{
  "id": 1137399,
  "type": "Feature",
  "properties": {
    "tgn:hierarchy":[
        "tgn:1137399",
        "tgn:1003391",
        "tgn:1000003",
        "tgn:7006657",
        "tgn:7029392"
    ],
    "tgn:id":1137399,
    "tgn:name":"Dzerzhinsk",
    "tgn:placetype":[
        "aat:300008347"
    ]
},
  "bbox": [],
  "geometry": {"coordinates":[27.0167,53.6667],"type":"Point"}
}