{
  "id": 2133304,
  "type": "Feature",
  "properties": {
    "tgn:hierarchy":[
        "tgn:2133304",
        "tgn:1000001",
        "tgn:2000923",
        "tgn:7012149",
        "tgn:7007515",
        "tgn:7029392"
    ],
    "tgn:id":2133304,
    "tgn:name":"Anderson Pond",
    "tgn:placetype":[
        "aat:300008680"
    ]
},
  "bbox": [],
  "geometry": {"coordinates":[-69.65,44.35],"type":"Point"}
}