{
  "id": 7565937,
  "type": "Feature",
  "properties": {
    "tgn:hierarchy":[
        "tgn:7565937",
        "tgn:1000004",
        "tgn:7000198",
        "tgn:7016722",
        "tgn:7029392"
    ],
    "tgn:id":7565937,
    "tgn:name:en":"Harshankarpur Mustaqil",
    "tgn:placetype":[
        "aat:300008347"
    ]
},
  "bbox": [],
  "geometry": {"coordinates":[79.471568,26.410249],"type":"Point"}
}