{
  "id": 2446667,
  "type": "Feature",
  "properties": {
    "tgn:hierarchy":[
        "tgn:2446667",
        "tgn:1000001",
        "tgn:2002370",
        "tgn:7012149",
        "tgn:7007923",
        "tgn:7029392"
    ],
    "tgn:id":2446667,
    "tgn:name":"Lewisa, Mount",
    "tgn:placetype":[
        "aat:300008798"
    ]
},
  "bbox": [],
  "geometry": {"coordinates":[-104.35,44.4667],"type":"Point"}
}