{
  "id": 2216079,
  "type": "Feature",
  "properties": {
    "tgn:hierarchy":[
        "tgn:2216079",
        "tgn:1000001",
        "tgn:7006451",
        "tgn:7012149",
        "tgn:2000098",
        "tgn:7029392"
    ],
    "tgn:id":2216079,
    "tgn:name":"Camino Drain, El",
    "tgn:placetype":[
        "aat:300008699"
    ]
},
  "bbox": [],
  "geometry": {"coordinates":[-114.35,34.4833],"type":"Point"}
}