{
  "id": 7592560,
  "type": "Feature",
  "properties": {
    "tgn:hierarchy":[
        "tgn:7592560",
        "tgn:1000004",
        "tgn:7000198",
        "tgn:7016722",
        "tgn:7029392"
    ],
    "tgn:id":7592560,
    "tgn:name:en":"D\u0101modarab\u0101d",
    "tgn:placetype":[
        "aat:300008347"
    ]
},
  "bbox": [],
  "geometry": {"coordinates":[77.814522,30.095962],"type":"Point"}
}