{
  "id": 7540954,
  "type": "Feature",
  "properties": {
    "tgn:hierarchy":[
        "tgn:7540954",
        "tgn:7001242",
        "tgn:7016833",
        "tgn:7001336",
        "tgn:7029392"
    ],
    "tgn:id":7540954,
    "tgn:name:en":"Suweir, Gebel el-",
    "tgn:placetype":[
        "aat:300008795"
    ]
},
  "bbox": [],
  "geometry": {"coordinates":[34.007989,28.638656],"type":"Point"}
}