{
  "id": 7274959,
  "type": "Feature",
  "properties": {
    "tgn:hierarchy":[
        "tgn:7274959",
        "tgn:1001699",
        "tgn:1000049",
        "tgn:1000002",
        "tgn:7029392"
    ],
    "tgn:id":7274959,
    "tgn:name":"Cola, Bajo",
    "tgn:placetype":[
        "aat:300387036"
    ]
},
  "bbox": [],
  "geometry": {"coordinates":[-73.273056,-41.827778],"type":"Point"}
}