{
  "id": 2146669,
  "type": "Feature",
  "properties": {
    "tgn:hierarchy":[
        "tgn:2146669",
        "tgn:1000001",
        "tgn:2001703",
        "tgn:7012149",
        "tgn:7007708",
        "tgn:7029392"
    ],
    "tgn:id":2146669,
    "tgn:name":"Bandit Spring",
    "tgn:placetype":[
        "aat:300008697"
    ]
},
  "bbox": [],
  "geometry": {"coordinates":[-120.3833,44.4833],"type":"Point"}
}