{
  "id": 2618400,
  "type": "Feature",
  "properties": {
    "tgn:hierarchy":[
        "tgn:2618400",
        "tgn:1000001",
        "tgn:7012149",
        "tgn:2002268",
        "tgn:7013961",
        "tgn:7029392"
    ],
    "tgn:id":2618400,
    "tgn:name":"Right Fork Big Run",
    "tgn:placetype":[
        "aat:300008699"
    ]
},
  "bbox": [],
  "geometry": {"coordinates":[-81.55,38.8667],"type":"Point"}
}