{
  "id": 2498506,
  "type": "Feature",
  "properties": {
    "tgn:hierarchy":[
        "tgn:2498506",
        "tgn:7006450",
        "tgn:1000001",
        "tgn:7012149",
        "tgn:2000086",
        "tgn:7029392"
    ],
    "tgn:id":2498506,
    "tgn:name":"McAllister Creek",
    "tgn:placetype":[
        "aat:300008706"
    ]
},
  "bbox": [],
  "geometry": {"coordinates":[-146.65,61.1167],"type":"Point"}
}