{
  "id": 2173208,
  "type": "Feature",
  "properties": {
    "tgn:hierarchy":[
        "tgn:2173208",
        "tgn:1000001",
        "tgn:7012149",
        "tgn:2000895",
        "tgn:7007256",
        "tgn:7029392"
    ],
    "tgn:id":2173208,
    "tgn:name":"Binion Brake",
    "tgn:placetype":[
        "aat:300008905"
    ]
},
  "bbox": [],
  "geometry": {"coordinates":[-91.85,32.4333],"type":"Point"}
}