{
  "id": 7311425,
  "type": "Feature",
  "properties": {
    "tgn:hierarchy":[
        "tgn:7311425",
        "tgn:1001708",
        "tgn:1000049",
        "tgn:1000002",
        "tgn:7029392"
    ],
    "tgn:id":7311425,
    "tgn:name":"Los Cristales, Cerro",
    "tgn:placetype":[
        "aat:300008795"
    ]
},
  "bbox": [],
  "geometry": {"coordinates":[-70.483333,-33.866667],"type":"Point"}
}