{
  "id": 2070508,
  "type": "Feature",
  "properties": {
    "tgn:hierarchy":[
        "tgn:2070508",
        "tgn:1000001",
        "tgn:1002328",
        "tgn:7012149",
        "tgn:7007568",
        "tgn:7029392"
    ],
    "tgn:id":2070508,
    "tgn:name":"Meridale",
    "tgn:placetype":[
        "aat:300008347"
    ]
},
  "bbox": [],
  "geometry": {"coordinates":[-74.95,42.3667],"type":"Point"}
}