{
  "id": 7533744,
  "type": "Feature",
  "properties": {
    "tgn:hierarchy":[
        "tgn:7533744",
        "tgn:7001242",
        "tgn:7001311",
        "tgn:7016833",
        "tgn:7029392"
    ],
    "tgn:id":7533744,
    "tgn:name:en":"Magal 'Atalla",
    "tgn:placetype":[
        "aat:300008697"
    ]
},
  "bbox": [],
  "geometry": {"coordinates":[33.561807,26.183997],"type":"Point"}
}