{
  "id": 2103016,
  "type": "Feature",
  "properties": {
    "tgn:hierarchy":[
        "tgn:2103016",
        "tgn:1000001",
        "tgn:7012149",
        "tgn:2001956",
        "tgn:7007826",
        "tgn:7029392"
    ],
    "tgn:id":2103016,
    "tgn:name":"Byers",
    "tgn:placetype":[
        "aat:300008347"
    ]
},
  "bbox": [],
  "geometry": {"coordinates":[-98.1833,34.0667],"type":"Point"}
}