{
  "id": 1069794,
  "type": "Feature",
  "properties": {
    "tgn:hierarchy":[
        "tgn:1069794",
        "tgn:1000004",
        "tgn:7002079",
        "tgn:1000111",
        "tgn:7029392"
    ],
    "tgn:id":1069794,
    "tgn:name":"Liaojiangshi",
    "tgn:placetype":[
        "aat:300008347"
    ]
},
  "bbox": [],
  "geometry": {"coordinates":[113.2667,26.0833],"type":"Point"}
}