{
  "id": 1064056,
  "type": "Feature",
  "properties": {
    "tgn:hierarchy":[
        "tgn:1064056",
        "tgn:7003748",
        "tgn:1000003",
        "tgn:7011731",
        "tgn:7029392"
    ],
    "tgn:id":1064056,
    "tgn:name":"Flims",
    "tgn:placetype":[
        "aat:300008347"
    ]
},
  "bbox": [],
  "geometry": {"coordinates":[9.2833,46.85],"type":"Point"}
}