<<<<<<< HEAD
{
  "id": 2331099,
  "type": "Feature",
  "properties": {
    "tgn:hierarchy":[
        "tgn:2331099",
        "tgn:1000001",
        "tgn:7012149",
        "tgn:2001455",
        "tgn:7007566",
        "tgn:7029392"
    ],
    "tgn:id":2331099,
    "tgn:name":"Flat Tank",
    "tgn:placetype":[
        "aat:300006191"
    ]
},
  "bbox": [],
  "geometry": {"coordinates":[-107.6333,33.1833],"type":"Point"}
}
=======
{"geometry":{"type":"Point","coordinates":[-107.633300,33.183300]},"type":"Feature","properties":{"hierarchy":["tgn:2331099","tgn:1000001","tgn:7012149","tgn:2001455","tgn:7007566","tgn:7029392"],"placetype":["aat:300006191"],"id":2331099,"name:xx":"Flat Tank"}}
>>>>>>> 03f74aca74312dbeaf24d7e61306dd6a786dc3d0
