<<<<<<< HEAD
{
  "id": 2768104,
  "type": "Feature",
  "properties": {
    "tgn:hierarchy":[
        "tgn:2768104",
        "tgn:1000001",
        "tgn:7012149",
        "tgn:2001108",
        "tgn:7007522",
        "tgn:7029392"
    ],
    "tgn:id":2768104,
    "tgn:name":"Whites Bayou",
    "tgn:placetype":[
        "aat:300008699"
    ]
},
  "bbox": [],
  "geometry": {"coordinates":[-89.5833,30.2667],"type":"Point"}
}
=======
{"geometry":{"type":"Point","coordinates":[-89.583300,30.266700]},"type":"Feature","properties":{"hierarchy":["tgn:2768104","tgn:1000001","tgn:7012149","tgn:2001108","tgn:7007522","tgn:7029392"],"placetype":["aat:300008699"],"id":2768104,"name:xx":"Whites Bayou"}}
>>>>>>> 03f74aca74312dbeaf24d7e61306dd6a786dc3d0
