{
  "id": 7119889,
  "type": "Feature",
  "properties": {
    "tgn:hierarchy":[
        "tgn:7119889",
        "tgn:1000003",
        "tgn:7003688",
        "tgn:7000084",
        "tgn:7029392"
    ],
    "tgn:id":7119889,
    "tgn:name":"Pein",
    "tgn:placetype":[
        "aat:300000206"
    ]
},
  "bbox": [],
  "geometry": {"coordinates":[9.766667,53.666667],"type":"Point"}
}