{
  "id": 7545785,
  "type": "Feature",
  "properties": {
    "tgn:hierarchy":[
        "tgn:7545785",
        "tgn:1000004",
        "tgn:7000198",
        "tgn:1001895",
        "tgn:7029392"
    ],
    "tgn:id":7545785,
    "tgn:name:en":"Bhokar",
    "tgn:placetype":[
        "aat:300008347"
    ]
},
  "bbox": [],
  "geometry": {"coordinates":[77.683333,19.216667],"type":"Point"}
}