{
  "id": 7538253,
  "type": "Feature",
  "properties": {
    "tgn:hierarchy":[
        "tgn:7538253",
        "tgn:7001242",
        "tgn:7016833",
        "tgn:1001114",
        "tgn:7029392"
    ],
    "tgn:id":7538253,
    "tgn:name:en":"Nazlat 'In\u0101n",
    "tgn:placetype":[
        "aat:300008347"
    ]
},
  "bbox": [],
  "geometry": {"coordinates":[31.333333,27.066667],"type":"Point"}
}