{
  "id": 2126474,
  "type": "Feature",
  "properties": {
    "tgn:hierarchy":[
        "tgn:2126474",
        "tgn:7006450",
        "tgn:1000001",
        "tgn:7012149",
        "tgn:2124005",
        "tgn:7029392"
    ],
    "tgn:id":2126474,
    "tgn:name":"Adventure Creek",
    "tgn:placetype":[
        "aat:300008706"
    ]
},
  "bbox": [],
  "geometry": {"coordinates":[-161.2833,68.6333],"type":"Point"}
}