{
  "id": 2557530,
  "type": "Feature",
  "properties": {
    "tgn:hierarchy":[
        "tgn:2557530",
        "tgn:1000001",
        "tgn:7014423",
        "tgn:7012149",
        "tgn:7007517",
        "tgn:7029392"
    ],
    "tgn:id":2557530,
    "tgn:name":"Old Oaken Bucket Homestead",
    "tgn:placetype":[
        "aat:300008347"
    ]
},
  "bbox": [],
  "geometry": {"coordinates":[-70.75,42.1667],"type":"Point"}
}