{
  "id": 2223441,
  "type": "Feature",
  "properties": {
    "tgn:hierarchy":[
        "tgn:2223441",
        "tgn:1002933",
        "tgn:1000001",
        "tgn:7012149",
        "tgn:7007239",
        "tgn:7029392"
    ],
    "tgn:id":2223441,
    "tgn:name":"Carsylian Acres",
    "tgn:placetype":[
        "aat:300008347"
    ]
},
  "bbox": [],
  "geometry": {"coordinates":[-75.2167,38.7333],"type":"Point"}
}