<<<<<<< HEAD
{
  "id": 7175420,
  "type": "Feature",
  "properties": {
    "tgn:hierarchy":[
        "tgn:7175420",
        "tgn:1000003",
        "tgn:7594165",
        "tgn:7000084",
        "tgn:7029392"
    ],
    "tgn:id":7175420,
    "tgn:name":"Gro\u00dfe Wiese",
    "tgn:placetype":[
        "aat:300055621"
    ]
},
  "bbox": [],
  "geometry": {"coordinates":[10.966667,52.05],"type":"Point"}
}
=======
{"geometry":{"type":"Point","coordinates":[10.966667,52.050000]},"type":"Feature","properties":{"hierarchy":["tgn:7175420","tgn:1000003","tgn:7594165","tgn:7000084","tgn:7029392"],"placetype":["aat:300055621"],"id":7175420,"name:xx":"Gro\u00dfe Wiese"}}
>>>>>>> 03f74aca74312dbeaf24d7e61306dd6a786dc3d0
