{
  "id": 2228092,
  "type": "Feature",
  "properties": {
    "tgn:hierarchy":[
        "tgn:2228092",
        "tgn:1000001",
        "tgn:7012149",
        "tgn:1002350",
        "tgn:7007157",
        "tgn:7029392"
    ],
    "tgn:id":2228092,
    "tgn:name":"Cedar Canyon",
    "tgn:placetype":[
        "aat:300008761"
    ]
},
  "bbox": [],
  "geometry": {"coordinates":[-120.5167,38.65],"type":"Point"}
}