{
  "id": 2683558,
  "type": "Feature",
  "properties": {
    "tgn:hierarchy":[
        "tgn:2683558",
        "tgn:1000001",
        "tgn:7012149",
        "tgn:2001882",
        "tgn:7007825",
        "tgn:7029392"
    ],
    "tgn:id":2683558,
    "tgn:name":"Spear Branch Prospect",
    "tgn:placetype":[
        "aat:300000390"
    ]
},
  "bbox": [],
  "geometry": {"coordinates":[-81.9167,36.45],"type":"Point"}
}