<<<<<<< HEAD
{
  "id": 7483048,
  "type": "Feature",
  "properties": {
    "tgn:hierarchy":[
        "tgn:7483048",
        "tgn:1000004",
        "tgn:7489179",
        "tgn:1000141",
        "tgn:7029392"
    ],
    "tgn:id":7483048,
    "tgn:name":"Jietian Gong",
    "tgn:placetype":[
        "aat:300007595"
    ]
},
  "bbox": [],
  "geometry": {"coordinates":[121.840833,24.879722],"type":"Point"}
}
=======
{"geometry":{"type":"Point","coordinates":[121.840833,24.879722]},"type":"Feature","properties":{"hierarchy":["tgn:7483048","tgn:1000004","tgn:7489179","tgn:1000141","tgn:7029392"],"placetype":["aat:300007595"],"id":7483048,"name:xx":"Jietian Gong"}}
>>>>>>> 03f74aca74312dbeaf24d7e61306dd6a786dc3d0
