{
  "id": 7387061,
  "type": "Feature",
  "properties": {
    "tgn:hierarchy":[
        "tgn:7387061",
        "tgn:7005583",
        "tgn:1000001",
        "tgn:7005560",
        "tgn:7029392"
    ],
    "tgn:id":7387061,
    "tgn:name":"Pueblo de la Garro",
    "tgn:placetype":[
        "aat:300008347"
    ]
},
  "bbox": [],
  "geometry": {"coordinates":[-105.563056,24.496667],"type":"Point"}
}