{
  "id": 2569307,
  "type": "Feature",
  "properties": {
    "tgn:hierarchy":[
        "tgn:2569307",
        "tgn:1000001",
        "tgn:2001842",
        "tgn:7012149",
        "tgn:7007825",
        "tgn:7029392"
    ],
    "tgn:id":2569307,
    "tgn:name":"Parks Store",
    "tgn:placetype":[
        "aat:300008347"
    ]
},
  "bbox": [],
  "geometry": {"coordinates":[-84.95,35.05],"type":"Point"}
}