{
  "id": 2549713,
  "type": "Feature",
  "properties": {
    "tgn:hierarchy":[
        "tgn:2549713",
        "tgn:1000001",
        "tgn:1002479",
        "tgn:7012149",
        "tgn:7007240",
        "tgn:7029392"
    ],
    "tgn:id":2549713,
    "tgn:name":"North Tampa Heights",
    "tgn:placetype":[
        "aat:300008347"
    ]
},
  "bbox": [],
  "geometry": {"coordinates":[-82.45,28.05],"type":"Point"}
}