{
  "id": 2444122,
  "type": "Feature",
  "properties": {
    "tgn:hierarchy":[
        "tgn:2444122",
        "tgn:7006450",
        "tgn:1000001",
        "tgn:7012149",
        "tgn:2000079",
        "tgn:7029392"
    ],
    "tgn:id":2444122,
    "tgn:name":"LaSpray Creek",
    "tgn:placetype":[
        "aat:300008706"
    ]
},
  "bbox": [],
  "geometry": {"coordinates":[-165.1667,64.75],"type":"Point"}
}