{
  "id": 7192678,
  "type": "Feature",
  "properties": {
    "tgn:hierarchy":[
        "tgn:7192678",
        "tgn:1000003",
        "tgn:7003688",
        "tgn:7000084",
        "tgn:7029392"
    ],
    "tgn:id":7192678,
    "tgn:name":"Fliegenfelde",
    "tgn:placetype":[
        "aat:300000206"
    ]
},
  "bbox": [],
  "geometry": {"coordinates":[10.55,53.85],"type":"Point"}
}