<<<<<<< HEAD
{
  "id": 2409524,
  "type": "Feature",
  "properties": {
    "tgn:hierarchy":[
        "tgn:2409524",
        "tgn:1000001",
        "tgn:7012149",
        "tgn:2001926",
        "tgn:7007825",
        "tgn:7029392"
    ],
    "tgn:id":2409524,
    "tgn:name":"Idlewilde",
    "tgn:placetype":[
        "aat:300008347"
    ]
},
  "bbox": [],
  "geometry": {"coordinates":[-82.35,36.3333],"type":"Point"}
}
=======
{"geometry":{"type":"Point","coordinates":[-82.350000,36.333300]},"type":"Feature","properties":{"hierarchy":["tgn:2409524","tgn:1000001","tgn:7012149","tgn:2001926","tgn:7007825","tgn:7029392"],"placetype":["aat:300008347"],"id":2409524,"name:xx":"Idlewilde"}}
>>>>>>> 03f74aca74312dbeaf24d7e61306dd6a786dc3d0
