{
  "id": 7217045,
  "type": "Feature",
  "properties": {
    "tgn:hierarchy":[
        "tgn:7217045",
        "tgn:1003447",
        "tgn:7007850",
        "tgn:1000003",
        "tgn:1000080",
        "tgn:7029392"
    ],
    "tgn:id":7217045,
    "tgn:name":"Villaggio Mancuso",
    "tgn:placetype":[
        "aat:300008347"
    ]
},
  "bbox": [],
  "geometry": {"coordinates":[16.566,39.083],"type":"Point"}
}