{
  "id": 7427224,
  "type": "Feature",
  "properties": {
    "tgn:hierarchy":[
        "tgn:7427224",
        "tgn:1000001",
        "tgn:7005594",
        "tgn:7005560",
        "tgn:7029392"
    ],
    "tgn:id":7427224,
    "tgn:name":"San Juan",
    "tgn:placetype":[
        "aat:300008347"
    ]
},
  "bbox": [],
  "geometry": {"coordinates":[-100.766667,23.133333],"type":"Point"}
}