{
  "id": 1020149,
  "type": "Feature",
  "properties": {
    "tgn:hierarchy":[
        "tgn:1020149",
        "tgn:7006477",
        "tgn:1001169",
        "tgn:1000002",
        "tgn:7029392"
    ],
    "tgn:id":1020149,
    "tgn:name":"Viamonte",
    "tgn:placetype":[
        "aat:300008347"
    ]
},
  "bbox": [],
  "geometry": {"coordinates":[-63.05,-33.7667],"type":"Point"}
}