<<<<<<< HEAD
{
  "id": 7472750,
  "type": "Feature",
  "properties": {
    "tgn:hierarchy":[
        "tgn:7472750",
        "tgn:1000004",
        "tgn:7001014",
        "tgn:1000141",
        "tgn:7029392"
    ],
    "tgn:id":7472750,
    "tgn:name":"Xiutan",
    "tgn:placetype":[
        "aat:300008347"
    ]
},
  "bbox": [],
  "geometry": {"coordinates":[120.349388,23.654888],"type":"Point"}
}
=======
{"geometry":{"type":"Point","coordinates":[120.349388,23.654888]},"type":"Feature","properties":{"hierarchy":["tgn:7472750","tgn:1000004","tgn:7001014","tgn:1000141","tgn:7029392"],"placetype":["aat:300008347"],"id":7472750,"name:xx":"Xiutan"}}
>>>>>>> 03f74aca74312dbeaf24d7e61306dd6a786dc3d0
