{
  "id": 7556832,
  "type": "Feature",
  "properties": {
    "tgn:hierarchy":[
        "tgn:7556832",
        "tgn:1000004",
        "tgn:7000198",
        "tgn:1001894",
        "tgn:7029392"
    ],
    "tgn:id":7556832,
    "tgn:name:en":"Pipaljhopa",
    "tgn:placetype":[
        "aat:300008347"
    ]
},
  "bbox": [],
  "geometry": {"coordinates":[75.686982,21.553498],"type":"Point"}
}