<<<<<<< HEAD
{
  "id": 2332126,
  "type": "Feature",
  "properties": {
    "tgn:hierarchy":[
        "tgn:2332126",
        "tgn:1000001",
        "tgn:7012149",
        "tgn:2000282",
        "tgn:7007240",
        "tgn:7029392"
    ],
    "tgn:id":2332126,
    "tgn:name":"Flint Point",
    "tgn:placetype":[
        "aat:300008850"
    ]
},
  "bbox": [],
  "geometry": {"coordinates":[-81.5667,29.7833],"type":"Point"}
}
=======
{"geometry":{"type":"Point","coordinates":[-81.566700,29.783300]},"type":"Feature","properties":{"hierarchy":["tgn:2332126","tgn:1000001","tgn:7012149","tgn:2000282","tgn:7007240","tgn:7029392"],"placetype":["aat:300008850"],"id":2332126,"name:xx":"Flint Point"}}
>>>>>>> 03f74aca74312dbeaf24d7e61306dd6a786dc3d0
