{
  "id": 7520268,
  "type": "Feature",
  "properties": {
    "tgn:hierarchy":[
        "tgn:7520268",
        "tgn:7001242",
        "tgn:7016833",
        "tgn:7001336",
        "tgn:7029392"
    ],
    "tgn:id":7520268,
    "tgn:name":"Jardah, W\u0101d\u012b",
    "tgn:placetype":[
        "aat:300379998"
    ]
},
  "bbox": [],
  "geometry": {"coordinates":[33.971781,29.418877],"type":"Point"}
}