{
  "id": 2717498,
  "type": "Feature",
  "properties": {
    "tgn:hierarchy":[
        "tgn:2717498",
        "tgn:1000001",
        "tgn:7012149",
        "tgn:1003038",
        "tgn:7007517",
        "tgn:7029392"
    ],
    "tgn:id":2717498,
    "tgn:name":"Thomas Basin",
    "tgn:placetype":[
        "aat:300132316"
    ]
},
  "bbox": [],
  "geometry": {"coordinates":[-71.7833,42.3667],"type":"Point"}
}