{
  "id": 2278760,
  "type": "Feature",
  "properties": {
    "tgn:hierarchy":[
        "tgn:2278760",
        "tgn:1000001",
        "tgn:2002107",
        "tgn:7012149",
        "tgn:7007827",
        "tgn:7029392"
    ],
    "tgn:id":2278760,
    "tgn:name":"Dead Horse Lake",
    "tgn:placetype":[
        "aat:300008680"
    ]
},
  "bbox": [],
  "geometry": {"coordinates":[-110.6667,40.7333],"type":"Point"}
}