{
  "id": 2513159,
  "type": "Feature",
  "properties": {
    "tgn:hierarchy":[
        "tgn:2513159",
        "tgn:1000001",
        "tgn:7012149",
        "tgn:7007157",
        "tgn:2000189",
        "tgn:7029392"
    ],
    "tgn:id":2513159,
    "tgn:name":"Mill Creek Lake",
    "tgn:placetype":[
        "aat:300008680"
    ]
},
  "bbox": [],
  "geometry": {"coordinates":[-122.7667,41.2333],"type":"Point"}
}