{
  "id": 7583977,
  "type": "Feature",
  "properties": {
    "tgn:hierarchy":[
        "tgn:7583977",
        "tgn:1000004",
        "tgn:7000198",
        "tgn:7016883",
        "tgn:7029392"
    ],
    "tgn:id":7583977,
    "tgn:name:en":"Sati",
    "tgn:placetype":[
        "aat:300008347"
    ]
},
  "bbox": [],
  "geometry": {"coordinates":[76.002268,30.590248],"type":"Point"}
}