<<<<<<< HEAD
{
  "id": 2334747,
  "type": "Feature",
  "properties": {
    "tgn:hierarchy":[
        "tgn:2334747",
        "tgn:1000001",
        "tgn:7012149",
        "tgn:2001514",
        "tgn:7007709",
        "tgn:7029392"
    ],
    "tgn:id":2334747,
    "tgn:name":"Fork Mountain",
    "tgn:placetype":[
        "aat:300008798"
    ]
},
  "bbox": [],
  "geometry": {"coordinates":[-82.1,35.7333],"type":"Point"}
}
=======
{"geometry":{"type":"Point","coordinates":[-82.100000,35.733300]},"type":"Feature","properties":{"hierarchy":["tgn:2334747","tgn:1000001","tgn:7012149","tgn:2001514","tgn:7007709","tgn:7029392"],"placetype":["aat:300008798"],"id":2334747,"name:xx":"Fork Mountain"}}
>>>>>>> 03f74aca74312dbeaf24d7e61306dd6a786dc3d0
