{
  "id": 2694632,
  "type": "Feature",
  "properties": {
    "tgn:hierarchy":[
        "tgn:2694632",
        "tgn:1000001",
        "tgn:2001600",
        "tgn:7012149",
        "tgn:7007705",
        "tgn:7029392"
    ],
    "tgn:id":2694632,
    "tgn:name":"Stewart Lake",
    "tgn:placetype":[
        "aat:300006191"
    ]
},
  "bbox": [],
  "geometry": {"coordinates":[-103.4333,46.3333],"type":"Point"}
}