{
  "id": 7016633,
  "type": "Feature",
  "properties": {
    "tgn:hierarchy":[
        "tgn:7016633",
        "tgn:1000004",
        "tgn:7001745",
        "tgn:1000111",
        "tgn:7029392"
    ],
    "tgn:id":7016633,
    "tgn:name":"Taxkorgan",
    "tgn:placetype":[
        "aat:300008347"
    ]
},
  "bbox": [],
  "geometry": {"coordinates":[75.2333,37.7833],"type":"Point"}
}