{
  "id": 2561573,
  "type": "Feature",
  "properties": {
    "tgn:hierarchy":[
        "tgn:2561573",
        "tgn:1000001",
        "tgn:7012149",
        "tgn:2001895",
        "tgn:7007825",
        "tgn:7029392"
    ],
    "tgn:id":2561573,
    "tgn:name":"Oslin",
    "tgn:placetype":[
        "aat:300008347"
    ]
},
  "bbox": [],
  "geometry": {"coordinates":[-86.75,35.5167],"type":"Point"}
}