{
  "id": 7230060,
  "type": "Feature",
  "properties": {
    "tgn:hierarchy":[
        "tgn:7230060",
        "tgn:7002743",
        "tgn:7017076",
        "tgn:1000003",
        "tgn:1000074",
        "tgn:7029392"
    ],
    "tgn:id":7230060,
    "tgn:name":"Lagovo\u00fanion",
    "tgn:placetype":[
        "aat:300008347"
    ]
},
  "bbox": [],
  "geometry": {"coordinates":[22.05,37.966667],"type":"Point"}
}