{
  "id": 2648012,
  "type": "Feature",
  "properties": {
    "tgn:hierarchy":[
        "tgn:2648012",
        "tgn:1000001",
        "tgn:7012149",
        "tgn:2001708",
        "tgn:7007708",
        "tgn:7029392"
    ],
    "tgn:id":2648012,
    "tgn:name":"Schoolhouse Hill",
    "tgn:placetype":[
        "aat:300008798"
    ]
},
  "bbox": [],
  "geometry": {"coordinates":[-119.3333,44.75],"type":"Point"}
}