{
  "id": 2214397,
  "type": "Feature",
  "properties": {
    "tgn:hierarchy":[
        "tgn:2214397",
        "tgn:1000001",
        "tgn:7012149",
        "tgn:7007253",
        "tgn:7029392"
    ],
    "tgn:id":2214397,
    "tgn:name":"Calamus Creek",
    "tgn:placetype":[
        "aat:300008706"
    ]
},
  "bbox": [],
  "geometry": {"coordinates":[-93.4833,41.9333],"type":"Point"}
}