{
  "id": 7589749,
  "type": "Feature",
  "properties": {
    "tgn:hierarchy":[
        "tgn:7589749",
        "tgn:1000004",
        "tgn:7000198",
        "tgn:7000799",
        "tgn:7029392"
    ],
    "tgn:id":7589749,
    "tgn:name:en":"Gampa",
    "tgn:placetype":[
        "aat:300008347"
    ]
},
  "bbox": [],
  "geometry": {"coordinates":[76.384722,34.634722],"type":"Point"}
}