{
  "id": 7274133,
  "type": "Feature",
  "properties": {
    "tgn:hierarchy":[
        "tgn:7274133",
        "tgn:1000003",
        "tgn:7003613",
        "tgn:7016845",
        "tgn:7029392"
    ],
    "tgn:id":7274133,
    "tgn:name:nl":"Zoutkamperril",
    "tgn:placetype":[
        "aat:300387026"
    ]
},
  "bbox": [],
  "geometry": {"coordinates":[6.25,53.35],"type":"Point"}
}