{
  "id": 7547152,
  "type": "Feature",
  "properties": {
    "tgn:hierarchy":[
        "tgn:7547152",
        "tgn:1000004",
        "tgn:7000198",
        "tgn:1001882",
        "tgn:7029392"
    ],
    "tgn:id":7547152,
    "tgn:name:en":"Ark\u0101vati River",
    "tgn:placetype":[
        "aat:300008699"
    ]
},
  "bbox": [],
  "geometry": {"coordinates":[77.433333,12.283333],"type":"Point"}
}