{
  "id": 1015336,
  "type": "Feature",
  "properties": {
    "tgn:hierarchy":[
        "tgn:1015336",
        "tgn:7005685",
        "tgn:1000001",
        "tgn:7005804",
        "tgn:7029392"
    ],
    "tgn:id":1015336,
    "tgn:name":"Cap-de-la-Madeleine",
    "tgn:placetype":[
        "aat:300008347"
    ]
},
  "bbox": [],
  "geometry": {"coordinates":[-72.5167,46.3667],"type":"Point"}
}