{
  "id": 7428447,
  "type": "Feature",
  "properties": {
    "tgn:hierarchy":[
        "tgn:7428447",
        "tgn:7005581",
        "tgn:1000001",
        "tgn:7005560",
        "tgn:7029392"
    ],
    "tgn:id":7428447,
    "tgn:name":"Estaci\u00f3n Temores",
    "tgn:placetype":[
        "aat:300007783"
    ]
},
  "bbox": [],
  "geometry": {"coordinates":[-108.233333,27.25],"type":"Point"}
}