{
  "id": 2133937,
  "type": "Feature",
  "properties": {
    "tgn:hierarchy":[
        "tgn:2133937",
        "tgn:1000001",
        "tgn:1002477",
        "tgn:7012149",
        "tgn:7007240",
        "tgn:7029392"
    ],
    "tgn:id":2133937,
    "tgn:name":"Angelo, Lake",
    "tgn:placetype":[
        "aat:300008680"
    ]
},
  "bbox": [],
  "geometry": {"coordinates":[-81.4667,27.5833],"type":"Point"}
}