{
  "id": 2142347,
  "type": "Feature",
  "properties": {
    "tgn:hierarchy":[
        "tgn:2142347",
        "tgn:1000001",
        "tgn:7012149",
        "tgn:2001964",
        "tgn:7007826",
        "tgn:7029392"
    ],
    "tgn:id":2142347,
    "tgn:name":"Backbone, The",
    "tgn:placetype":[
        "aat:300266640"
    ]
},
  "bbox": [],
  "geometry": {"coordinates":[-97.35,33.4333],"type":"Point"}
}