{
  "id": 2231790,
  "type": "Feature",
  "properties": {
    "tgn:hierarchy":[
        "tgn:2231790",
        "tgn:1000001",
        "tgn:7012149",
        "tgn:2001120",
        "tgn:7007522",
        "tgn:7029392"
    ],
    "tgn:id":2231790,
    "tgn:name":"Chamberlin Creek",
    "tgn:placetype":[
        "aat:300008706"
    ]
},
  "bbox": [],
  "geometry": {"coordinates":[-88.7667,32.9167],"type":"Point"}
}