{
  "id": 2611552,
  "type": "Feature",
  "properties": {
    "tgn:hierarchy":[
        "tgn:2611552",
        "tgn:1000001",
        "tgn:7012149",
        "tgn:7007157",
        "tgn:1002710",
        "tgn:7029392"
    ],
    "tgn:id":2611552,
    "tgn:name":"Red Mountain",
    "tgn:placetype":[
        "aat:300008798"
    ]
},
  "bbox": [],
  "geometry": {"coordinates":[-120.5333,39.3333],"type":"Point"}
}