{
  "id": 7065951,
  "type": "Feature",
  "properties": {
    "tgn:hierarchy":[
        "tgn:7065951",
        "tgn:1000003",
        "tgn:7003676",
        "tgn:7000084",
        "tgn:7029392"
    ],
    "tgn:id":7065951,
    "tgn:name":"Turmhof",
    "tgn:placetype":[
        "aat:300000206"
    ]
},
  "bbox": [],
  "geometry": {"coordinates":[10.016667,51.733333],"type":"Point"}
}