<<<<<<< HEAD
{
  "id": 7480514,
  "type": "Feature",
  "properties": {
    "tgn:hierarchy":[
        "tgn:7480514",
        "tgn:7001010",
        "tgn:1000004",
        "tgn:1000141",
        "tgn:7029392"
    ],
    "tgn:id":7480514,
    "tgn:name":"Zhixue Erhao Qiao",
    "tgn:placetype":[
        "aat:300007836"
    ]
},
  "bbox": [],
  "geometry": {"coordinates":[121.526111,23.893889],"type":"Point"}
}
=======
{"geometry":{"type":"Point","coordinates":[121.526111,23.893889]},"type":"Feature","properties":{"hierarchy":["tgn:7480514","tgn:7001010","tgn:1000004","tgn:1000141","tgn:7029392"],"placetype":["aat:300007836"],"id":7480514,"name:xx":"Zhixue Erhao Qiao"}}
>>>>>>> 03f74aca74312dbeaf24d7e61306dd6a786dc3d0
