{
  "id": 2344427,
  "type": "Feature",
  "properties": {
    "tgn:hierarchy":[
        "tgn:2344427",
        "tgn:1000001",
        "tgn:7012149",
        "tgn:7007157",
        "tgn:2000188",
        "tgn:7029392"
    ],
    "tgn:id":2344427,
    "tgn:name":"Gap Creek",
    "tgn:placetype":[
        "aat:300008706"
    ]
},
  "bbox": [],
  "geometry": {"coordinates":[-122.0167,41.05],"type":"Point"}
}