{
  "id": 2653924,
  "type": "Feature",
  "properties": {
    "tgn:hierarchy":[
        "tgn:2653924",
        "tgn:1000001",
        "tgn:7012149",
        "tgn:2000804",
        "tgn:7007255",
        "tgn:7029392"
    ],
    "tgn:id":2653924,
    "tgn:name":"Shack Branch",
    "tgn:placetype":[
        "aat:300008699"
    ]
},
  "bbox": [],
  "geometry": {"coordinates":[-82.9667,37.85],"type":"Point"}
}