{
  "id": 2651986,
  "type": "Feature",
  "properties": {
    "tgn:hierarchy":[
        "tgn:2651986",
        "tgn:1002132",
        "tgn:1000001",
        "tgn:7012149",
        "tgn:7007919",
        "tgn:7029392"
    ],
    "tgn:id":2651986,
    "tgn:name":"Selby Mill Branch",
    "tgn:placetype":[
        "aat:300008699"
    ]
},
  "bbox": [],
  "geometry": {"coordinates":[-75.4667,37.9833],"type":"Point"}
}