{
  "id": 2442997,
  "type": "Feature",
  "properties": {
    "tgn:hierarchy":[
        "tgn:2442997",
        "tgn:7006450",
        "tgn:1000001",
        "tgn:7012149",
        "tgn:2124005",
        "tgn:7029392"
    ],
    "tgn:id":2442997,
    "tgn:name":"Kuropak Creek",
    "tgn:placetype":[
        "aat:300008706"
    ]
},
  "bbox": [],
  "geometry": {"coordinates":[-165.5833,68.1167],"type":"Point"}
}