{
  "id": 7129598,
  "type": "Feature",
  "properties": {
    "tgn:hierarchy":[
        "tgn:7129598",
        "tgn:1000003",
        "tgn:7003677",
        "tgn:7000084",
        "tgn:7029392"
    ],
    "tgn:id":7129598,
    "tgn:name":"Melkmeskopf",
    "tgn:placetype":[
        "aat:300008777"
    ]
},
  "bbox": [],
  "geometry": {"coordinates":[7.533333,51.333333],"type":"Point"}
}