{
  "id": 7098540,
  "type": "Feature",
  "properties": {
    "tgn:hierarchy":[
        "tgn:7098540",
        "tgn:1000003",
        "tgn:7003676",
        "tgn:7000084",
        "tgn:7029392"
    ],
    "tgn:id":7098540,
    "tgn:name":"Semis-Kopf",
    "tgn:placetype":[
        "aat:300008777"
    ]
},
  "bbox": [],
  "geometry": {"coordinates":[10.033333,51.683333],"type":"Point"}
}