{
  "id": 7243539,
  "type": "Feature",
  "properties": {
    "tgn:hierarchy":[
        "tgn:7243539",
        "tgn:7003465",
        "tgn:1000003",
        "tgn:1000063",
        "tgn:4012014",
        "tgn:7029392"
    ],
    "tgn:id":7243539,
    "tgn:name":"Malbout\u00e9",
    "tgn:placetype":[
        "aat:300008347"
    ]
},
  "bbox": [],
  "geometry": {"coordinates":[5.616667,50.383333],"type":"Point"}
}