{
  "id": 2477978,
  "type": "Feature",
  "properties": {
    "tgn:hierarchy":[
        "tgn:2477978",
        "tgn:1000001",
        "tgn:7012149",
        "tgn:7007157",
        "tgn:1002856",
        "tgn:7029392"
    ],
    "tgn:id":2477978,
    "tgn:name":"Machete Ridge",
    "tgn:placetype":[
        "aat:300266640"
    ]
},
  "bbox": [],
  "geometry": {"coordinates":[-121.1833,36.4833],"type":"Point"}
}