{
  "id": 2377701,
  "type": "Feature",
  "properties": {
    "tgn:hierarchy":[
        "tgn:2377701",
        "tgn:1000001",
        "tgn:7012149",
        "tgn:2001918",
        "tgn:7007825",
        "tgn:7029392"
    ],
    "tgn:id":2377701,
    "tgn:name":"Harr Hollow",
    "tgn:placetype":[
        "aat:300008761"
    ]
},
  "bbox": [],
  "geometry": {"coordinates":[-82.2667,36.5833],"type":"Point"}
}