{
  "id": 2331139,
  "type": "Feature",
  "properties": {
    "tgn:hierarchy":[
        "tgn:2331139",
        "tgn:1000001",
        "tgn:7012149",
        "tgn:2001713",
        "tgn:7007708",
        "tgn:7029392"
    ],
    "tgn:id":2331139,
    "tgn:name":"Flat Top",
    "tgn:placetype":[
        "aat:300008798"
    ]
},
  "bbox": [],
  "geometry": {"coordinates":[-123.7833,42.4167],"type":"Point"}
}