<<<<<<< HEAD
{
  "id": 2331139,
  "type": "Feature",
  "properties": {
    "tgn:hierarchy":[
        "tgn:2331139",
        "tgn:1000001",
        "tgn:7012149",
        "tgn:2001713",
        "tgn:7007708",
        "tgn:7029392"
    ],
    "tgn:id":2331139,
    "tgn:name":"Flat Top",
    "tgn:placetype":[
        "aat:300008798"
    ]
},
  "bbox": [],
  "geometry": {"coordinates":[-123.7833,42.4167],"type":"Point"}
}
=======
{"geometry":{"type":"Point","coordinates":[-123.783300,42.416700]},"type":"Feature","properties":{"hierarchy":["tgn:2331139","tgn:1000001","tgn:7012149","tgn:2001713","tgn:7007708","tgn:7029392"],"placetype":["aat:300008798"],"id":2331139,"name:xx":"Flat Top"}}
>>>>>>> 03f74aca74312dbeaf24d7e61306dd6a786dc3d0
