{
  "id": 7076756,
  "type": "Feature",
  "properties": {
    "tgn:hierarchy":[
        "tgn:7076756",
        "tgn:1000003",
        "tgn:7003688",
        "tgn:7000084",
        "tgn:7029392"
    ],
    "tgn:id":7076756,
    "tgn:name":"R\u00fcsterberg",
    "tgn:placetype":[
        "aat:300008777"
    ]
},
  "bbox": [],
  "geometry": {"coordinates":[9.616667,54.233333],"type":"Point"}
}