{
  "id": 1103923,
  "type": "Feature",
  "properties": {
    "tgn:hierarchy":[
        "tgn:1103923",
        "tgn:7001198",
        "tgn:7003481",
        "tgn:1000003",
        "tgn:1000078",
        "tgn:7029392"
    ],
    "tgn:id":1103923,
    "tgn:name":"Benwee",
    "tgn:placetype":[
        "aat:300008795"
    ]
},
  "bbox": [],
  "geometry": {"coordinates":[-9.5667,53.6167],"type":"Point"}
}