{
  "id": 7356266,
  "type": "Feature",
  "properties": {
    "tgn:hierarchy":[
        "tgn:7356266",
        "tgn:7005584",
        "tgn:1000001",
        "tgn:7005560",
        "tgn:7029392"
    ],
    "tgn:id":7356266,
    "tgn:name":"Cerro Gordo",
    "tgn:placetype":[
        "aat:300008347"
    ]
},
  "bbox": [],
  "geometry": {"coordinates":[-101.133333,20.583333],"type":"Point"}
}