{
  "id": 7454520,
  "type": "Feature",
  "properties": {
    "tgn:hierarchy":[
        "tgn:7454520",
        "tgn:7002444",
        "tgn:1000003",
        "tgn:7009907",
        "tgn:7008591",
        "tgn:7029392"
    ],
    "tgn:id":7454520,
    "tgn:name:en":"Burra Sound",
    "tgn:placetype":[
        "aat:300266558"
    ]
},
  "bbox": [],
  "geometry": {"coordinates":[-3.316667,58.933333],"type":"Point"}
}