<<<<<<< HEAD
{
  "id": 2401188,
  "type": "Feature",
  "properties": {
    "tgn:hierarchy":[
        "tgn:2401188",
        "tgn:1000001",
        "tgn:7012149",
        "tgn:2002062",
        "tgn:7007826",
        "tgn:7029392"
    ],
    "tgn:id":2401188,
    "tgn:name":"Horsehead Draw",
    "tgn:placetype":[
        "aat:300008761"
    ]
},
  "bbox": [],
  "geometry": {"coordinates":[-103.8667,31.5833],"type":"Point"}
}
=======
{"geometry":{"type":"Point","coordinates":[-103.866700,31.583300]},"type":"Feature","properties":{"hierarchy":["tgn:2401188","tgn:1000001","tgn:7012149","tgn:2002062","tgn:7007826","tgn:7029392"],"placetype":["aat:300008761"],"id":2401188,"name:xx":"Horsehead Draw"}}
>>>>>>> 03f74aca74312dbeaf24d7e61306dd6a786dc3d0
