{
  "id": 7397527,
  "type": "Feature",
  "properties": {
    "tgn:hierarchy":[
        "tgn:7397527",
        "tgn:1000001",
        "tgn:1001906",
        "tgn:7005560",
        "tgn:7029392"
    ],
    "tgn:id":7397527,
    "tgn:name":"San Nicol\u00e1s",
    "tgn:placetype":[
        "aat:300008347"
    ]
},
  "bbox": [],
  "geometry": {"coordinates":[-105.033333,21.766667],"type":"Point"}
}