{
  "id": 7460153,
  "type": "Feature",
  "properties": {
    "tgn:hierarchy":[
        "tgn:7460153",
        "tgn:7002445",
        "tgn:1000003",
        "tgn:7008165",
        "tgn:7008591",
        "tgn:7029392"
    ],
    "tgn:id":7460153,
    "tgn:name:en":"Horsley",
    "tgn:placetype":[
        "aat:300008347"
    ]
},
  "bbox": [],
  "geometry": {"coordinates":[-1.85,54.983333],"type":"Point"}
}