{
  "id": 7297905,
  "type": "Feature",
  "properties": {
    "tgn:hierarchy":[
        "tgn:7297905",
        "tgn:7002758",
        "tgn:1001316",
        "tgn:1000003",
        "tgn:1000095",
        "tgn:7029392"
    ],
    "tgn:id":7297905,
    "tgn:name":"Solera",
    "tgn:placetype":[
        "aat:300008347"
    ]
},
  "bbox": [],
  "geometry": {"coordinates":[-3.35,37.683333],"type":"Point"}
}