{
  "id": 7339299,
  "type": "Feature",
  "properties": {
    "tgn:hierarchy":[
        "tgn:7339299",
        "tgn:7002811",
        "tgn:1000003",
        "tgn:7003837",
        "tgn:1000095",
        "tgn:7029392"
    ],
    "tgn:id":7339299,
    "tgn:name":"Cruces, Puerto de las",
    "tgn:placetype":[
        "aat:300259572"
    ]
},
  "bbox": [],
  "geometry": {"coordinates":[-6.466667,39.233333],"type":"Point"}
}