{
  "id": 7056077,
  "type": "Feature",
  "properties": {
    "tgn:hierarchy":[
        "tgn:7056077",
        "tgn:1003440",
        "tgn:1000003",
        "tgn:7003124",
        "tgn:1000080",
        "tgn:7029392"
    ],
    "tgn:id":7056077,
    "tgn:name":"Mezzo, Giogo di",
    "tgn:placetype":[
        "aat:300259572"
    ]
},
  "bbox": [],
  "geometry": {"coordinates":[12.033333,47.05],"type":"Point"}
}