{
  "id": 2127851,
  "type": "Feature",
  "properties": {
    "tgn:hierarchy":[
        "tgn:2127851",
        "tgn:1000001",
        "tgn:2001431",
        "tgn:7012149",
        "tgn:7007566",
        "tgn:7029392"
    ],
    "tgn:id":2127851,
    "tgn:name":"Alamosa Spring",
    "tgn:placetype":[
        "aat:300008697"
    ]
},
  "bbox": [],
  "geometry": {"coordinates":[-108.2167,35.1167],"type":"Point"}
}