{
  "id": 7527796,
  "type": "Feature",
  "properties": {
    "tgn:hierarchy":[
        "tgn:7527796",
        "tgn:7001242",
        "tgn:7016833",
        "tgn:1001088",
        "tgn:7029392"
    ],
    "tgn:id":7527796,
    "tgn:name:en":"S\u00eeh el-Ghaz\u00e2l",
    "tgn:placetype":[
        "aat:300008777"
    ]
},
  "bbox": [],
  "geometry": {"coordinates":[30.05,28.483333],"type":"Point"}
}