{
  "id": 7406152,
  "type": "Feature",
  "properties": {
    "tgn:hierarchy":[
        "tgn:7406152",
        "tgn:7005585",
        "tgn:1000001",
        "tgn:7005560",
        "tgn:7029392"
    ],
    "tgn:id":7406152,
    "tgn:name":"La Laguna, Cerro",
    "tgn:placetype":[
        "aat:300008795"
    ]
},
  "bbox": [],
  "geometry": {"coordinates":[-98.45,16.791667],"type":"Point"}
}