<<<<<<< HEAD
{
  "id": 7112741,
  "type": "Feature",
  "properties": {
    "tgn:hierarchy":[
        "tgn:7112741",
        "tgn:1000003",
        "tgn:7003678",
        "tgn:7000084",
        "tgn:7029392"
    ],
    "tgn:id":7112741,
    "tgn:name":"Roggen-Berg",
    "tgn:placetype":[
        "aat:300008777"
    ]
},
  "bbox": [],
  "geometry": {"coordinates":[9.866667,51.283333],"type":"Point"}
}
=======
{"geometry":{"type":"Point","coordinates":[9.866667,51.283333]},"type":"Feature","properties":{"hierarchy":["tgn:7112741","tgn:1000003","tgn:7003678","tgn:7000084","tgn:7029392"],"placetype":["aat:300008777"],"id":7112741,"name:xx":"Roggen-Berg"}}
>>>>>>> 03f74aca74312dbeaf24d7e61306dd6a786dc3d0
