{
  "id": 7452439,
  "type": "Feature",
  "properties": {
    "tgn:hierarchy":[
        "tgn:7452439",
        "tgn:7002445",
        "tgn:1000003",
        "tgn:7008165",
        "tgn:7008591",
        "tgn:7029392"
    ],
    "tgn:id":7452439,
    "tgn:name:en":"Emmanuel Head",
    "tgn:placetype":[
        "aat:300386846"
    ]
},
  "bbox": [],
  "geometry": {"coordinates":[-1.783333,55.683333],"type":"Point"}
}