{
  "id": 2031730,
  "type": "Feature",
  "properties": {
    "tgn:hierarchy":[
        "tgn:2031730",
        "tgn:1000001",
        "tgn:7012149",
        "tgn:1002694",
        "tgn:7007252",
        "tgn:7029392"
    ],
    "tgn:id":2031730,
    "tgn:name":"Eminence",
    "tgn:placetype":[
        "aat:300008347"
    ]
},
  "bbox": [],
  "geometry": {"coordinates":[-86.6333,39.5167],"type":"Point"}
}