{
  "id": 2736917,
  "type": "Feature",
  "properties": {
    "tgn:hierarchy":[
        "tgn:2736917",
        "tgn:1000001",
        "tgn:7012149",
        "tgn:2001708",
        "tgn:7007708",
        "tgn:7029392"
    ],
    "tgn:id":2736917,
    "tgn:name":"Two Cabin Creek",
    "tgn:placetype":[
        "aat:300008706"
    ]
},
  "bbox": [],
  "geometry": {"coordinates":[-119.3667,44.8667],"type":"Point"}
}