{
  "id": 7507037,
  "type": "Feature",
  "properties": {
    "tgn:hierarchy":[
        "tgn:7507037",
        "tgn:1008380",
        "tgn:7520093",
        "tgn:1000226",
        "tgn:1000006",
        "tgn:7029392"
    ],
    "tgn:id":7507037,
    "tgn:name:en":"Rakaiatai",
    "tgn:placetype":[
        "aat:300000206"
    ]
},
  "bbox": [],
  "geometry": {"coordinates":[176.216667,-40.133333],"type":"Point"}
}