{
  "id": 2620694,
  "type": "Feature",
  "properties": {
    "tgn:hierarchy":[
        "tgn:2620694",
        "tgn:1000001",
        "tgn:7012149",
        "tgn:1002717",
        "tgn:7007252",
        "tgn:7029392"
    ],
    "tgn:id":2620694,
    "tgn:name":"Riverside Lake",
    "tgn:placetype":[
        "aat:300008680"
    ]
},
  "bbox": [],
  "geometry": {"coordinates":[-87.35,40.85],"type":"Point"}
}