{
  "id": 7308662,
  "type": "Feature",
  "properties": {
    "tgn:hierarchy":[
        "tgn:7308662",
        "tgn:1001699",
        "tgn:1000049",
        "tgn:1000002",
        "tgn:7029392"
    ],
    "tgn:id":7308662,
    "tgn:name":"Puerto Low",
    "tgn:placetype":[
        "aat:300386968"
    ]
},
  "bbox": [],
  "geometry": {"coordinates":[-74.003056,-43.816944],"type":"Point"}
}