{
  "id": 2642282,
  "type": "Feature",
  "properties": {
    "tgn:hierarchy":[
        "tgn:2642282",
        "tgn:1000001",
        "tgn:7016172",
        "tgn:2000121",
        "tgn:7012149",
        "tgn:7029392"
    ],
    "tgn:id":2642282,
    "tgn:name":"Sand Spring",
    "tgn:placetype":[
        "aat:300008697"
    ]
},
  "bbox": [],
  "geometry": {"coordinates":[-93.9833,35.6667],"type":"Point"}
}