{
  "id": 7371905,
  "type": "Feature",
  "properties": {
    "tgn:hierarchy":[
        "tgn:7371905",
        "tgn:7005586",
        "tgn:1000001",
        "tgn:7005560",
        "tgn:7029392"
    ],
    "tgn:id":7371905,
    "tgn:name":"La Campana",
    "tgn:placetype":[
        "aat:300008347"
    ]
},
  "bbox": [],
  "geometry": {"coordinates":[-104.616667,20.366667],"type":"Point"}
}