{
  "id": 2518315,
  "type": "Feature",
  "properties": {
    "tgn:hierarchy":[
        "tgn:2518315",
        "tgn:1000001",
        "tgn:7012149",
        "tgn:2001312",
        "tgn:7007524",
        "tgn:7029392"
    ],
    "tgn:id":2518315,
    "tgn:name":"Missouri Pump Canal",
    "tgn:placetype":[
        "aat:300006075"
    ]
},
  "bbox": [],
  "geometry": {"coordinates":[-106.1833,48.05],"type":"Point"}
}