{
  "id": 2766546,
  "type": "Feature",
  "properties": {
    "tgn:hierarchy":[
        "tgn:2766546",
        "tgn:1000001",
        "tgn:7012149",
        "tgn:2000613",
        "tgn:7007253",
        "tgn:7029392"
    ],
    "tgn:id":2766546,
    "tgn:name":"White Oak Creek",
    "tgn:placetype":[
        "aat:300008706"
    ]
},
  "bbox": [],
  "geometry": {"coordinates":[-91.3333,41.95],"type":"Point"}
}