<<<<<<< HEAD
{
  "id": 2766546,
  "type": "Feature",
  "properties": {
    "tgn:hierarchy":[
        "tgn:2766546",
        "tgn:1000001",
        "tgn:7012149",
        "tgn:2000613",
        "tgn:7007253",
        "tgn:7029392"
    ],
    "tgn:id":2766546,
    "tgn:name":"White Oak Creek",
    "tgn:placetype":[
        "aat:300008706"
    ]
},
  "bbox": [],
  "geometry": {"coordinates":[-91.3333,41.95],"type":"Point"}
}
=======
{"geometry":{"type":"Point","coordinates":[-91.333300,41.950000]},"type":"Feature","properties":{"hierarchy":["tgn:2766546","tgn:1000001","tgn:7012149","tgn:2000613","tgn:7007253","tgn:7029392"],"placetype":["aat:300008706"],"id":2766546,"name:xx":"White Oak Creek"}}
>>>>>>> 03f74aca74312dbeaf24d7e61306dd6a786dc3d0
