{
  "id": 2564182,
  "type": "Feature",
  "properties": {
    "tgn:hierarchy":[
        "tgn:2564182",
        "tgn:1000001",
        "tgn:7012149",
        "tgn:2001273",
        "tgn:7007524",
        "tgn:7029392"
    ],
    "tgn:id":2564182,
    "tgn:name":"PN Island",
    "tgn:placetype":[
        "aat:300008791"
    ]
},
  "bbox": [],
  "geometry": {"coordinates":[-109.6333,47.7333],"type":"Point"}
}