<<<<<<< HEAD
{
  "id": 2767152,
  "type": "Feature",
  "properties": {
    "tgn:hierarchy":[
        "tgn:2767152",
        "tgn:1000001",
        "tgn:7012149",
        "tgn:2002175",
        "tgn:7007919",
        "tgn:7029392"
    ],
    "tgn:id":2767152,
    "tgn:name":"White Rock Creek",
    "tgn:placetype":[
        "aat:300008706"
    ]
},
  "bbox": [],
  "geometry": {"coordinates":[-79.05,37.9],"type":"Point"}
}
=======
{"geometry":{"type":"Point","coordinates":[-79.050000,37.900000]},"type":"Feature","properties":{"hierarchy":["tgn:2767152","tgn:1000001","tgn:7012149","tgn:2002175","tgn:7007919","tgn:7029392"],"placetype":["aat:300008706"],"id":2767152,"name:xx":"White Rock Creek"}}
>>>>>>> 03f74aca74312dbeaf24d7e61306dd6a786dc3d0
