{
  "id": 7496163,
  "type": "Feature",
  "properties": {
    "tgn:hierarchy":[
        "tgn:7496163",
        "tgn:7487020",
        "tgn:1000004",
        "tgn:1000141",
        "tgn:7029392"
    ],
    "tgn:id":7496163,
    "tgn:name":"Yangliaoqi",
    "tgn:placetype":[
        "aat:300008347"
    ]
},
  "bbox": [],
  "geometry": {"coordinates":[120.754534,24.542632],"type":"Point"}
}