{
  "id": 1014854,
  "type": "Feature",
  "properties": {
    "tgn:hierarchy":[
        "tgn:1014854",
        "tgn:7005685",
        "tgn:1000001",
        "tgn:7013154",
        "tgn:7029392"
    ],
    "tgn:id":1014854,
    "tgn:name":"Killarney",
    "tgn:placetype":[
        "aat:300008347"
    ]
},
  "bbox": [],
  "geometry": {"coordinates":[-81.5167,45.9667],"type":"Point"}
}