{
  "id": 7345572,
  "type": "Feature",
  "properties": {
    "tgn:hierarchy":[
        "tgn:7345572",
        "tgn:7008911",
        "tgn:1000003",
        "tgn:7002763",
        "tgn:1000095",
        "tgn:7029392"
    ],
    "tgn:id":7345572,
    "tgn:name":"Allence",
    "tgn:placetype":[
        "aat:300008347"
    ]
},
  "bbox": [],
  "geometry": {"coordinates":[-6.166667,43.466667],"type":"Point"}
}