{
  "id": 7297918,
  "type": "Feature",
  "properties": {
    "tgn:hierarchy":[
        "tgn:7297918",
        "tgn:7002829",
        "tgn:1000003",
        "tgn:7002786",
        "tgn:1000095",
        "tgn:7029392"
    ],
    "tgn:id":7297918,
    "tgn:name":"Sindr\u00e1n",
    "tgn:placetype":[
        "aat:300008347"
    ]
},
  "bbox": [],
  "geometry": {"coordinates":[-7.416667,42.516667],"type":"Point"}
}