{
  "id": 2223997,
  "type": "Feature",
  "properties": {
    "tgn:hierarchy":[
        "tgn:2223997",
        "tgn:1000001",
        "tgn:2001945",
        "tgn:7012149",
        "tgn:7007826",
        "tgn:7029392"
    ],
    "tgn:id":2223997,
    "tgn:name":"Cartwright Draw",
    "tgn:placetype":[
        "aat:300008701"
    ]
},
  "bbox": [],
  "geometry": {"coordinates":[-103.3167,30.1333],"type":"Point"}
}