{
  "id": 2230989,
  "type": "Feature",
  "properties": {
    "tgn:hierarchy":[
        "tgn:2230989",
        "tgn:1000001",
        "tgn:7012149",
        "tgn:2002090",
        "tgn:7007826",
        "tgn:7029392"
    ],
    "tgn:id":2230989,
    "tgn:name":"Cerritos Blancos",
    "tgn:placetype":[
        "aat:300008798"
    ]
},
  "bbox": [],
  "geometry": {"coordinates":[-99.65,27.7667],"type":"Point"}
}