{
  "id": 1088639,
  "type": "Feature",
  "properties": {
    "tgn:hierarchy":[
        "tgn:1088639",
        "tgn:7001242",
        "tgn:1000996",
        "tgn:1000158",
        "tgn:7029392"
    ],
    "tgn:id":1088639,
    "tgn:name":"Ikalou",
    "tgn:placetype":[
        "aat:300008347"
    ]
},
  "bbox": [],
  "geometry": {"coordinates":[11.7833,-4.0333],"type":"Point"}
}