<<<<<<< HEAD
{
  "id": 7020701,
  "type": "Feature",
  "properties": {
    "tgn:hierarchy":[
        "tgn:7020701",
        "tgn:2000934",
        "tgn:1000001",
        "tgn:7012149",
        "tgn:7007516",
        "tgn:7029392"
    ],
    "tgn:id":7020701,
    "tgn:name":"Dans Mountain",
    "tgn:placetype":[
        "aat:300008798"
    ]
},
  "bbox": [],
  "geometry": {"coordinates":[-78.8833,39.5667],"type":"Point"}
}
=======
{"geometry":{"type":"Point","coordinates":[-78.883300,39.566700]},"type":"Feature","properties":{"hierarchy":["tgn:7020701","tgn:2000934","tgn:1000001","tgn:7012149","tgn:7007516","tgn:7029392"],"placetype":["aat:300008798"],"id":7020701,"name:xx":"Dans Mountain"}}
>>>>>>> 03f74aca74312dbeaf24d7e61306dd6a786dc3d0
