{
  "id": 7020701,
  "type": "Feature",
  "properties": {
    "tgn:hierarchy":[
        "tgn:7020701",
        "tgn:2000934",
        "tgn:1000001",
        "tgn:7012149",
        "tgn:7007516",
        "tgn:7029392"
    ],
    "tgn:id":7020701,
    "tgn:name":"Dans Mountain",
    "tgn:placetype":[
        "aat:300008798"
    ]
},
  "bbox": [],
  "geometry": {"coordinates":[-78.8833,39.5667],"type":"Point"}
}