{
  "id": 7496019,
  "type": "Feature",
  "properties": {
    "tgn:hierarchy":[
        "tgn:7496019",
        "tgn:1000004",
        "tgn:1000454",
        "tgn:1000141",
        "tgn:7029392"
    ],
    "tgn:id":7496019,
    "tgn:name":"Zhongyi Shanzhuang",
    "tgn:placetype":[
        "aat:300005567"
    ]
},
  "bbox": [],
  "geometry": {"coordinates":[121.394122,24.910139],"type":"Point"}
}