{
  "id": 2400544,
  "type": "Feature",
  "properties": {
    "tgn:hierarchy":[
        "tgn:2400544",
        "tgn:1000001",
        "tgn:2001432",
        "tgn:7012149",
        "tgn:7007566",
        "tgn:7029392"
    ],
    "tgn:id":2400544,
    "tgn:name":"Horse Lake",
    "tgn:placetype":[
        "aat:300008680"
    ]
},
  "bbox": [],
  "geometry": {"coordinates":[-105.1167,36.2667],"type":"Point"}
}