{
  "id": 2686954,
  "type": "Feature",
  "properties": {
    "tgn:hierarchy":[
        "tgn:2686954",
        "tgn:1000001",
        "tgn:7012149",
        "tgn:2000209",
        "tgn:7007158",
        "tgn:7029392"
    ],
    "tgn:id":2686954,
    "tgn:name":"Spring Gulch",
    "tgn:placetype":[
        "aat:300008761"
    ]
},
  "bbox": [],
  "geometry": {"coordinates":[-104.9833,39.5167],"type":"Point"}
}