{
  "id": 2495434,
  "type": "Feature",
  "properties": {
    "tgn:hierarchy":[
        "tgn:2495434",
        "tgn:2001610",
        "tgn:1000001",
        "tgn:7012149",
        "tgn:7007706",
        "tgn:7029392"
    ],
    "tgn:id":2495434,
    "tgn:name":"Marydale",
    "tgn:placetype":[
        "aat:300008347"
    ]
},
  "bbox": [],
  "geometry": {"coordinates":[-82.15,39.2833],"type":"Point"}
}