{
  "id": 7183634,
  "type": "Feature",
  "properties": {
    "tgn:hierarchy":[
        "tgn:7183634",
        "tgn:1000003",
        "tgn:7003689",
        "tgn:7000084",
        "tgn:7029392"
    ],
    "tgn:id":7183634,
    "tgn:name":"G\u00f6hren-D\u00f6hlen",
    "tgn:placetype":[
        "aat:300008347"
    ]
},
  "bbox": [],
  "geometry": {"coordinates":[12.016667,50.716667],"type":"Point"}
}