{
  "id": 7089322,
  "type": "Feature",
  "properties": {
    "tgn:hierarchy":[
        "tgn:7089322",
        "tgn:1000003",
        "tgn:7003678",
        "tgn:7000084",
        "tgn:7029392"
    ],
    "tgn:id":7089322,
    "tgn:name":"Volpertsberg",
    "tgn:placetype":[
        "aat:300008777"
    ]
},
  "bbox": [],
  "geometry": {"coordinates":[8.333333,50.716667],"type":"Point"}
}