{
  "id": 7358958,
  "type": "Feature",
  "properties": {
    "tgn:hierarchy":[
        "tgn:7358958",
        "tgn:1000001",
        "tgn:7005589",
        "tgn:7005560",
        "tgn:7029392"
    ],
    "tgn:id":7358958,
    "tgn:name":"Rancho Diez de Marzo",
    "tgn:placetype":[
        "aat:300000241"
    ]
},
  "bbox": [],
  "geometry": {"coordinates":[-99.733333,27.016667],"type":"Point"}
}