<<<<<<< HEAD
{
  "id": 7476024,
  "type": "Feature",
  "properties": {
    "tgn:hierarchy":[
        "tgn:7476024",
        "tgn:7488858",
        "tgn:1000004",
        "tgn:1000141",
        "tgn:7029392"
    ],
    "tgn:id":7476024,
    "tgn:name":"Guangfu Qiao",
    "tgn:placetype":[
        "aat:300007836"
    ]
},
  "bbox": [],
  "geometry": {"coordinates":[120.760325,23.898385],"type":"Point"}
}
=======
{"geometry":{"type":"Point","coordinates":[120.760325,23.898385]},"type":"Feature","properties":{"hierarchy":["tgn:7476024","tgn:7488858","tgn:1000004","tgn:1000141","tgn:7029392"],"placetype":["aat:300007836"],"id":7476024,"name:xx":"Guangfu Qiao"}}
>>>>>>> 03f74aca74312dbeaf24d7e61306dd6a786dc3d0
