{
  "id": 7384878,
  "type": "Feature",
  "properties": {
    "tgn:hierarchy":[
        "tgn:7384878",
        "tgn:7005586",
        "tgn:1000001",
        "tgn:7005560",
        "tgn:7029392"
    ],
    "tgn:id":7384878,
    "tgn:name":"Nevada",
    "tgn:placetype":[
        "aat:300008347"
    ]
},
  "bbox": [],
  "geometry": {"coordinates":[-103.883333,20.966667],"type":"Point"}
}