{
  "id": 1097233,
  "type": "Feature",
  "properties": {
    "tgn:hierarchy":[
        "tgn:1097233",
        "tgn:7000490",
        "tgn:1000006",
        "tgn:7001834",
        "tgn:7029392"
    ],
    "tgn:id":1097233,
    "tgn:name":"Kellerberrin",
    "tgn:placetype":[
        "aat:300008347"
    ]
},
  "bbox": [],
  "geometry": {"coordinates":[117.6833,-31.6667],"type":"Point"}
}