{
  "id": 2265686,
  "type": "Feature",
  "properties": {
    "tgn:hierarchy":[
        "tgn:2265686",
        "tgn:1000001",
        "tgn:7012149",
        "tgn:2000985",
        "tgn:7007520",
        "tgn:7029392"
    ],
    "tgn:id":2265686,
    "tgn:name":"Crapo Creek",
    "tgn:placetype":[
        "aat:300008706"
    ]
},
  "bbox": [],
  "geometry": {"coordinates":[-84.1667,44.3167],"type":"Point"}
}