{
  "id": 2659120,
  "type": "Feature",
  "properties": {
    "tgn:hierarchy":[
        "tgn:2659120",
        "tgn:1000001",
        "tgn:7012149",
        "tgn:2001714",
        "tgn:7007708",
        "tgn:7029392"
    ],
    "tgn:id":2659120,
    "tgn:name":"Shevlin",
    "tgn:placetype":[
        "aat:300008347"
    ]
},
  "bbox": [],
  "geometry": {"coordinates":[-121.6667,43.1333],"type":"Point"}
}