{
  "id": 2748975,
  "type": "Feature",
  "properties": {
    "tgn:hierarchy":[
        "tgn:2748975",
        "tgn:1000001",
        "tgn:7012149",
        "tgn:2001139",
        "tgn:7007522",
        "tgn:7029392"
    ],
    "tgn:id":2748975,
    "tgn:name":"Wallace",
    "tgn:placetype":[
        "aat:300008347"
    ]
},
  "bbox": [],
  "geometry": {"coordinates":[-89.7167,34.3667],"type":"Point"}
}