{
  "id": 1009281,
  "type": "Feature",
  "properties": {
    "tgn:hierarchy":[
        "tgn:1009281",
        "tgn:1000004",
        "tgn:7000381",
        "tgn:7029392"
    ],
    "tgn:id":1009281,
    "tgn:name":"Sudong",
    "tgn:placetype":[
        "aat:300008791"
    ]
},
  "bbox": [],
  "geometry": {"coordinates":[103.7333,1.2167],"type":"Point"}
}