{
  "id": 7264974,
  "type": "Feature",
  "properties": {
    "tgn:hierarchy":[
        "tgn:7264974",
        "tgn:1000003",
        "tgn:7003624",
        "tgn:7016845",
        "tgn:7029392"
    ],
    "tgn:id":7264974,
    "tgn:name:nl":"Kruisland, Polder",
    "tgn:placetype":[
        "aat:300006163"
    ]
},
  "bbox": [],
  "geometry": {"coordinates":[4.416667,51.566667],"type":"Point"}
}