{
  "id": 2323608,
  "type": "Feature",
  "properties": {
    "tgn:hierarchy":[
        "tgn:2323608",
        "tgn:2000107",
        "tgn:1000001",
        "tgn:7016172",
        "tgn:7012149",
        "tgn:7029392"
    ],
    "tgn:id":2323608,
    "tgn:name":"Farris Creek",
    "tgn:placetype":[
        "aat:300008706"
    ]
},
  "bbox": [],
  "geometry": {"coordinates":[-92.3167,36.1167],"type":"Point"}
}