{
  "id": 2209984,
  "type": "Feature",
  "properties": {
    "tgn:hierarchy":[
        "tgn:2209984",
        "tgn:1000001",
        "tgn:7016172",
        "tgn:7012149",
        "tgn:2000151",
        "tgn:7029392"
    ],
    "tgn:id":2209984,
    "tgn:name":"Burton",
    "tgn:placetype":[
        "aat:300008347"
    ]
},
  "bbox": [],
  "geometry": {"coordinates":[-89.85,35.9167],"type":"Point"}
}