{
  "id": 7429631,
  "type": "Feature",
  "properties": {
    "tgn:hierarchy":[
        "tgn:7429631",
        "tgn:7005583",
        "tgn:1000001",
        "tgn:7005560",
        "tgn:7029392"
    ],
    "tgn:id":7429631,
    "tgn:name":"Benito Juarez",
    "tgn:placetype":[
        "aat:300008347"
    ]
},
  "bbox": [],
  "geometry": {"coordinates":[-104.616667,24.016667],"type":"Point"}
}