{
  "id": 7445848,
  "type": "Feature",
  "properties": {
    "tgn:hierarchy":[
        "tgn:7445848",
        "tgn:7002443",
        "tgn:1000003",
        "tgn:7018966",
        "tgn:7008591",
        "tgn:7029392"
    ],
    "tgn:id":7445848,
    "tgn:name:en":"Sully",
    "tgn:placetype":[
        "aat:300008347"
    ]
},
  "bbox": [],
  "geometry": {"coordinates":[-3.218333,51.406389],"type":"Point"}
}