{
  "id": 7307749,
  "type": "Feature",
  "properties": {
    "tgn:hierarchy":[
        "tgn:7307749",
        "tgn:7002760",
        "tgn:1000003",
        "tgn:1000095",
        "tgn:7029392"
    ],
    "tgn:id":7307749,
    "tgn:name":"Llano",
    "tgn:placetype":[
        "aat:300008347"
    ]
},
  "bbox": [],
  "geometry": {"coordinates":[-3.983333,42.983333],"type":"Point"}
}