{
  "id": 2529474,
  "type": "Feature",
  "properties": {
    "tgn:hierarchy":[
        "tgn:2529474",
        "tgn:1000001",
        "tgn:2001411",
        "tgn:7012149",
        "tgn:7007526",
        "tgn:7029392"
    ],
    "tgn:id":2529474,
    "tgn:name":"Mud Lake",
    "tgn:placetype":[
        "aat:300008680"
    ]
},
  "bbox": [],
  "geometry": {"coordinates":[-116.9167,41.2833],"type":"Point"}
}