{
  "id": 2707619,
  "type": "Feature",
  "properties": {
    "tgn:hierarchy":[
        "tgn:2707619",
        "tgn:1000001",
        "tgn:7012149",
        "tgn:2000486",
        "tgn:7007250",
        "tgn:7029392"
    ],
    "tgn:id":2707619,
    "tgn:name":"Sweetwater Canal",
    "tgn:placetype":[
        "aat:300006075"
    ]
},
  "bbox": [],
  "geometry": {"coordinates":[-116.8333,46.3167],"type":"Point"}
}