<<<<<<< HEAD
{
  "id": 2337409,
  "type": "Feature",
  "properties": {
    "tgn:hierarchy":[
        "tgn:2337409",
        "tgn:1000001",
        "tgn:7012149",
        "tgn:2002273",
        "tgn:7013961",
        "tgn:7029392"
    ],
    "tgn:id":2337409,
    "tgn:name":"Fowler Branch",
    "tgn:placetype":[
        "aat:300008699"
    ]
},
  "bbox": [],
  "geometry": {"coordinates":[-82.0,37.95],"type":"Point"}
}
=======
{"geometry":{"type":"Point","coordinates":[-82.000000,37.950000]},"type":"Feature","properties":{"hierarchy":["tgn:2337409","tgn:1000001","tgn:7012149","tgn:2002273","tgn:7013961","tgn:7029392"],"placetype":["aat:300008699"],"id":2337409,"name:xx":"Fowler Branch"}}
>>>>>>> 03f74aca74312dbeaf24d7e61306dd6a786dc3d0
