{
  "id": 2113913,
  "type": "Feature",
  "properties": {
    "tgn:hierarchy":[
        "tgn:2113913",
        "tgn:1000001",
        "tgn:7012149",
        "tgn:2002161",
        "tgn:7007919",
        "tgn:7029392"
    ],
    "tgn:id":2113913,
    "tgn:name":"Reynolds Store",
    "tgn:placetype":[
        "aat:300008347",
        "aat:300387210"
    ]
},
  "bbox": [],
  "geometry": {"coordinates":[-78.2833,39.3667],"type":"Point"}
}