{
  "id": 7539847,
  "type": "Feature",
  "properties": {
    "tgn:hierarchy":[
        "tgn:7539847",
        "tgn:7001242",
        "tgn:7016833",
        "tgn:7029392"
    ],
    "tgn:id":7539847,
    "tgn:name:en":"Masrab al Qarn",
    "tgn:placetype":[
        "aat:300000626"
    ]
},
  "bbox": [],
  "geometry": {"coordinates":[25.55,31.683333],"type":"Point"}
}