{
  "id": 7469564,
  "type": "Feature",
  "properties": {
    "tgn:hierarchy":[
        "tgn:7469564",
        "tgn:1000004",
        "tgn:7490934",
        "tgn:1000141",
        "tgn:7029392"
    ],
    "tgn:id":7469564,
    "tgn:name":"Zhonglun",
    "tgn:placetype":[
        "aat:300008347"
    ]
},
  "bbox": [],
  "geometry": {"coordinates":[120.150995,23.29097],"type":"Point"}
}