{
  "id": 7468657,
  "type": "Feature",
  "properties": {
    "tgn:hierarchy":[
        "tgn:7468657",
        "tgn:1000004",
        "tgn:7467799",
        "tgn:1000141",
        "tgn:7029392"
    ],
    "tgn:id":7468657,
    "tgn:name":"Chaitoujing",
    "tgn:placetype":[
        "aat:300008347"
    ]
},
  "bbox": [],
  "geometry": {"coordinates":[120.600734,23.938228],"type":"Point"}
}