{
  "id": 2161672,
  "type": "Feature",
  "properties": {
    "tgn:hierarchy":[
        "tgn:2161672",
        "tgn:1000001",
        "tgn:2001596",
        "tgn:7012149",
        "tgn:7007705",
        "tgn:7029392"
    ],
    "tgn:id":2161672,
    "tgn:name":"Belle Lake",
    "tgn:placetype":[
        "aat:300008680"
    ]
},
  "bbox": [],
  "geometry": {"coordinates":[-99.9833,48.8833],"type":"Point"}
}