{
  "id": 7102309,
  "type": "Feature",
  "properties": {
    "tgn:hierarchy":[
        "tgn:7102309",
        "tgn:1000003",
        "tgn:7003687",
        "tgn:7000084",
        "tgn:7029392"
    ],
    "tgn:id":7102309,
    "tgn:name":"Salau",
    "tgn:placetype":[
        "aat:300000206"
    ]
},
  "bbox": [],
  "geometry": {"coordinates":[11.35,52.433333],"type":"Point"}
}