{
  "id": 2405334,
  "type": "Feature",
  "properties": {
    "tgn:hierarchy":[
        "tgn:2405334",
        "tgn:1000001",
        "tgn:7012149",
        "tgn:2000487",
        "tgn:7007250",
        "tgn:7029392"
    ],
    "tgn:id":2405334,
    "tgn:name":"Huffman Springs",
    "tgn:placetype":[
        "aat:300008697"
    ]
},
  "bbox": [],
  "geometry": {"coordinates":[-112.75,42.1833],"type":"Point"}
}