{
  "id": 2042055,
  "type": "Feature",
  "properties": {
    "tgn:hierarchy":[
        "tgn:2042055",
        "tgn:1000001",
        "tgn:7012149",
        "tgn:2000850",
        "tgn:7007255",
        "tgn:7029392"
    ],
    "tgn:id":2042055,
    "tgn:name":"Wray Gap",
    "tgn:placetype":[
        "aat:300008347"
    ]
},
  "bbox": [],
  "geometry": {"coordinates":[-84.85,36.7833],"type":"Point"}
}