{
  "id": 7292081,
  "type": "Feature",
  "properties": {
    "tgn:hierarchy":[
        "tgn:7292081",
        "tgn:1001702",
        "tgn:1000049",
        "tgn:1000002",
        "tgn:7029392"
    ],
    "tgn:id":7292081,
    "tgn:name":"Emilia, Cabo",
    "tgn:placetype":[
        "aat:300386846"
    ]
},
  "bbox": [],
  "geometry": {"coordinates":[-71.45,-54.883333],"type":"Point"}
}