{
  "id": 7536434,
  "type": "Feature",
  "properties": {
    "tgn:hierarchy":[
        "tgn:7536434",
        "tgn:7001242",
        "tgn:7016833",
        "tgn:1001113",
        "tgn:7029392"
    ],
    "tgn:id":7536434,
    "tgn:name:en":"Kafr as Saw\u0101limah",
    "tgn:placetype":[
        "aat:300008347"
    ]
},
  "bbox": [],
  "geometry": {"coordinates":[31.983333,30.783333],"type":"Point"}
}