{
  "id": 2319757,
  "type": "Feature",
  "properties": {
    "tgn:hierarchy":[
        "tgn:2319757",
        "tgn:1000001",
        "tgn:7012149",
        "tgn:1002742",
        "tgn:7007920",
        "tgn:7029392"
    ],
    "tgn:id":2319757,
    "tgn:name":"Eureka Lake",
    "tgn:placetype":[
        "aat:300008680"
    ]
},
  "bbox": [],
  "geometry": {"coordinates":[-120.5667,48.75],"type":"Point"}
}