{
  "id": 7199235,
  "type": "Feature",
  "properties": {
    "tgn:hierarchy":[
        "tgn:7199235",
        "tgn:1000003",
        "tgn:7000094",
        "tgn:7000084",
        "tgn:7029392"
    ],
    "tgn:id":7199235,
    "tgn:name":"Eichenfelde",
    "tgn:placetype":[
        "aat:300008347"
    ]
},
  "bbox": [],
  "geometry": {"coordinates":[13.783333,53.816667],"type":"Point"}
}