{
  "id": 1082712,
  "type": "Feature",
  "properties": {
    "tgn:hierarchy":[
        "tgn:1082712",
        "tgn:7000317",
        "tgn:1000004",
        "tgn:7018057",
        "tgn:1000128",
        "tgn:7029392"
    ],
    "tgn:id":1082712,
    "tgn:name":"Bukit Mertajam",
    "tgn:placetype":[
        "aat:300008347"
    ]
},
  "bbox": [],
  "geometry": {"coordinates":[100.4667,5.3667],"type":"Point"}
}