{
  "id": 7105938,
  "type": "Feature",
  "properties": {
    "tgn:hierarchy":[
        "tgn:7105938",
        "tgn:7003692",
        "tgn:1000003",
        "tgn:7000084",
        "tgn:7029392"
    ],
    "tgn:id":7105938,
    "tgn:name":"Schlesis",
    "tgn:placetype":[
        "aat:300000206"
    ]
},
  "bbox": [],
  "geometry": {"coordinates":[9.883333,47.85],"type":"Point"}
}