{
  "id": 7280787,
  "type": "Feature",
  "properties": {
    "tgn:hierarchy":[
        "tgn:7280787",
        "tgn:1001702",
        "tgn:1000049",
        "tgn:1000002",
        "tgn:7029392"
    ],
    "tgn:id":7280787,
    "tgn:name":"Silva Palma, Estuario",
    "tgn:placetype":[
        "aat:300008676"
    ]
},
  "bbox": [],
  "geometry": {"coordinates":[-71.766667,-53.45],"type":"Point"}
}