{
  "id": 7223859,
  "type": "Feature",
  "properties": {
    "tgn:hierarchy":[
        "tgn:7223859",
        "tgn:7002681",
        "tgn:7001395",
        "tgn:1000003",
        "tgn:1000074",
        "tgn:7029392"
    ],
    "tgn:id":7223859,
    "tgn:name":"Ilias, Hagios",
    "tgn:placetype":[
        "aat:300008795"
    ]
},
  "bbox": [],
  "geometry": {"coordinates":[24.466667,38.066667],"type":"Point"}
}