<<<<<<< HEAD
{
  "id": 2157705,
  "type": "Feature",
  "properties": {
    "tgn:hierarchy":[
        "tgn:2157705",
        "tgn:1000001",
        "tgn:7012149",
        "tgn:2002127",
        "tgn:7007827",
        "tgn:7029392"
    ],
    "tgn:id":2157705,
    "tgn:name":"Beaver Dam Wash",
    "tgn:placetype":[
        "aat:300008761"
    ]
},
  "bbox": [],
  "geometry": {"coordinates":[-113.9833,37.0],"type":"Point"}
}
=======
{"geometry":{"type":"Point","coordinates":[-113.983300,37.000000]},"type":"Feature","properties":{"hierarchy":["tgn:2157705","tgn:1000001","tgn:7012149","tgn:2002127","tgn:7007827","tgn:7029392"],"placetype":["aat:300008761"],"id":2157705,"name:xx":"Beaver Dam Wash"}}
>>>>>>> 03f74aca74312dbeaf24d7e61306dd6a786dc3d0
