{
  "id": 2441967,
  "type": "Feature",
  "properties": {
    "tgn:hierarchy":[
        "tgn:2441967",
        "tgn:1000001",
        "tgn:7012149",
        "tgn:2000975",
        "tgn:7007520",
        "tgn:7029392"
    ],
    "tgn:id":2441967,
    "tgn:name":"Koops Creek",
    "tgn:placetype":[
        "aat:300008706"
    ]
},
  "bbox": [],
  "geometry": {"coordinates":[-87.8833,46.55],"type":"Point"}
}