{
  "id": 7133937,
  "type": "Feature",
  "properties": {
    "tgn:hierarchy":[
        "tgn:7133937",
        "tgn:1000003",
        "tgn:7003676",
        "tgn:7000084",
        "tgn:7029392"
    ],
    "tgn:id":7133937,
    "tgn:name":"Moorweide",
    "tgn:placetype":[
        "aat:300008347"
    ]
},
  "bbox": [],
  "geometry": {"coordinates":[8.95,52.933333],"type":"Point"}
}