{
  "id": 2511981,
  "type": "Feature",
  "properties": {
    "tgn:hierarchy":[
        "tgn:2511981",
        "tgn:1000001",
        "tgn:1002479",
        "tgn:7012149",
        "tgn:7007240",
        "tgn:7029392"
    ],
    "tgn:id":2511981,
    "tgn:name":"Mill Bayou",
    "tgn:placetype":[
        "aat:300132316"
    ]
},
  "bbox": [],
  "geometry": {"coordinates":[-82.4333,27.6833],"type":"Point"}
}