{
  "id": 2262548,
  "type": "Feature",
  "properties": {
    "tgn:hierarchy":[
        "tgn:2262548",
        "tgn:2002238",
        "tgn:1000001",
        "tgn:7012149",
        "tgn:7007920",
        "tgn:7029392"
    ],
    "tgn:id":2262548,
    "tgn:name":"Cow Lake",
    "tgn:placetype":[
        "aat:300006191"
    ]
},
  "bbox": [],
  "geometry": {"coordinates":[-118.1667,47.1167],"type":"Point"}
}