<<<<<<< HEAD
{
  "id": 7359949,
  "type": "Feature",
  "properties": {
    "tgn:hierarchy":[
        "tgn:7359949",
        "tgn:1000001",
        "tgn:1001960",
        "tgn:7005560",
        "tgn:7029392"
    ],
    "tgn:id":7359949,
    "tgn:name":"Conejos, Sierra",
    "tgn:placetype":[
        "aat:300008795"
    ]
},
  "bbox": [],
  "geometry": {"coordinates":[-110.0,29.483333],"type":"Point"}
}
=======
{"geometry":{"type":"Point","coordinates":[-110.000000,29.483333]},"type":"Feature","properties":{"hierarchy":["tgn:7359949","tgn:1000001","tgn:1001960","tgn:7005560","tgn:7029392"],"placetype":["aat:300008795"],"id":7359949,"name:xx":"Conejos, Sierra"}}
>>>>>>> 03f74aca74312dbeaf24d7e61306dd6a786dc3d0
