{
  "id": 2506887,
  "type": "Feature",
  "properties": {
    "tgn:hierarchy":[
        "tgn:2506887",
        "tgn:1000001",
        "tgn:7012149",
        "tgn:2000182",
        "tgn:7007157",
        "tgn:7029392"
    ],
    "tgn:id":2506887,
    "tgn:name":"Mesquite Drain 3",
    "tgn:placetype":[
        "aat:300006075"
    ]
},
  "bbox": [],
  "geometry": {"coordinates":[-115.4667,32.8667],"type":"Point"}
}