<<<<<<< HEAD
{
  "id": 7025632,
  "type": "Feature",
  "properties": {
    "tgn:hierarchy":[
        "tgn:7025632",
        "tgn:7002445",
        "tgn:1000003",
        "tgn:7012077",
        "tgn:7008591",
        "tgn:7029392"
    ],
    "tgn:id":7025632,
    "tgn:name:en":"Little Torrington",
    "tgn:placetype":[
        "aat:300008347"
    ]
},
  "bbox": [],
  "geometry": {"coordinates":[-4.183333,50.933333],"type":"Point"}
}
=======
{"geometry":{"type":"Point","coordinates":[-4.183333,50.933333]},"type":"Feature","properties":{"hierarchy":["tgn:7025632","tgn:7002445","tgn:1000003","tgn:7012077","tgn:7008591","tgn:7029392"],"placetype":["aat:300008347"],"name:en":"Little Torrington","id":7025632}}
>>>>>>> 03f74aca74312dbeaf24d7e61306dd6a786dc3d0
