{
  "id": 2750754,
  "type": "Feature",
  "properties": {
    "tgn:hierarchy":[
        "tgn:2750754",
        "tgn:7006450",
        "tgn:1000001",
        "tgn:2124076",
        "tgn:7012149",
        "tgn:7029392"
    ],
    "tgn:id":2750754,
    "tgn:name":"Ward Creek",
    "tgn:placetype":[
        "aat:300008706"
    ]
},
  "bbox": [],
  "geometry": {"coordinates":[-131.6333,55.4667],"type":"Point"}
}