{
  "id": 7467830,
  "type": "Feature",
  "properties": {
    "tgn:hierarchy":[
        "tgn:7467830",
        "tgn:7001004",
        "tgn:1000004",
        "tgn:1000141",
        "tgn:7029392"
    ],
    "tgn:id":7467830,
    "tgn:name":"Huli",
    "tgn:placetype":[
        "aat:300008347"
    ]
},
  "bbox": [],
  "geometry": {"coordinates":[120.377778,22.885833],"type":"Point"}
}