{
  "id": 7472776,
  "type": "Feature",
  "properties": {
    "tgn:hierarchy":[
        "tgn:7472776",
        "tgn:1000004",
        "tgn:7001013",
        "tgn:1000141",
        "tgn:7029392"
    ],
    "tgn:id":7472776,
    "tgn:name":"Wushulin",
    "tgn:placetype":[
        "aat:300008347"
    ]
},
  "bbox": [],
  "geometry": {"coordinates":[121.211389,24.883333],"type":"Point"}
}