{
  "id": 7503682,
  "type": "Feature",
  "properties": {
    "tgn:hierarchy":[
        "tgn:7503682",
        "tgn:1000004",
        "tgn:7001009",
        "tgn:1000141",
        "tgn:7029392"
    ],
    "tgn:id":7503682,
    "tgn:name":"Bazhangli",
    "tgn:placetype":[
        "aat:300008347"
    ]
},
  "bbox": [],
  "geometry": {"coordinates":[120.537755,24.232631],"type":"Point"}
}