{
  "id": 7590573,
  "type": "Feature",
  "properties": {
    "tgn:hierarchy":[
        "tgn:7590573",
        "tgn:1000004",
        "tgn:7000198",
        "tgn:7000799",
        "tgn:7029392"
    ],
    "tgn:id":7590573,
    "tgn:name:en":"Nahoa Chh\u016bl Katha",
    "tgn:placetype":[
        "aat:300008699"
    ]
},
  "bbox": [],
  "geometry": {"coordinates":[74.372222,33.847222],"type":"Point"}
}