{
  "id": 2762078,
  "type": "Feature",
  "properties": {
    "tgn:hierarchy":[
        "tgn:2762078",
        "tgn:1000001",
        "tgn:1002614",
        "tgn:7012149",
        "tgn:7007526",
        "tgn:7029392"
    ],
    "tgn:id":2762078,
    "tgn:name":"West Side Canal",
    "tgn:placetype":[
        "aat:300006075"
    ]
},
  "bbox": [],
  "geometry": {"coordinates":[-119.1833,38.85],"type":"Point"}
}