{
  "id": 1137529,
  "type": "Feature",
  "properties": {
    "tgn:hierarchy":[
        "tgn:1137529",
        "tgn:1000004",
        "tgn:6003034",
        "tgn:7018214",
        "tgn:7002435",
        "tgn:7029392"
    ],
    "tgn:id":1137529,
    "tgn:name":"Yashkino",
    "tgn:placetype":[
        "aat:300008347"
    ]
},
  "bbox": [],
  "geometry": {"coordinates":[85.3833,55.8833],"type":"Point"}
}