{
  "id": 2140739,
  "type": "Feature",
  "properties": {
    "tgn:hierarchy":[
        "tgn:2140739",
        "tgn:1000001",
        "tgn:7012149",
        "tgn:2000838",
        "tgn:7007255",
        "tgn:7029392"
    ],
    "tgn:id":2140739,
    "tgn:name":"Auxier Ridge",
    "tgn:placetype":[
        "aat:300266640"
    ]
},
  "bbox": [],
  "geometry": {"coordinates":[-83.6667,37.8333],"type":"Point"}
}