{
  "id": 2716735,
  "type": "Feature",
  "properties": {
    "tgn:hierarchy":[
        "tgn:2716735",
        "tgn:1000001",
        "tgn:7012149",
        "tgn:2001457",
        "tgn:7007566",
        "tgn:7029392"
    ],
    "tgn:id":2716735,
    "tgn:name":"The Tungsten Mine",
    "tgn:placetype":[
        "aat:300000390"
    ]
},
  "bbox": [],
  "geometry": {"coordinates":[-105.7667,36.2167],"type":"Point"}
}