{
  "id": 2328073,
  "type": "Feature",
  "properties": {
    "tgn:hierarchy":[
        "tgn:2328073",
        "tgn:1000001",
        "tgn:7012149",
        "tgn:2001706",
        "tgn:7007708",
        "tgn:7029392"
    ],
    "tgn:id":2328073,
    "tgn:name":"Fish Mountain",
    "tgn:placetype":[
        "aat:300008798"
    ]
},
  "bbox": [],
  "geometry": {"coordinates":[-122.4167,43.0667],"type":"Point"}
}