{
  "id": 2730882,
  "type": "Feature",
  "properties": {
    "tgn:hierarchy":[
        "tgn:2730882",
        "tgn:1000001",
        "tgn:7012149",
        "tgn:2001714",
        "tgn:7007708",
        "tgn:7029392"
    ],
    "tgn:id":2730882,
    "tgn:name":"Tub Spring",
    "tgn:placetype":[
        "aat:300008697"
    ]
},
  "bbox": [],
  "geometry": {"coordinates":[-121.0167,42.3167],"type":"Point"}
}