{
  "id": 2482747,
  "type": "Feature",
  "properties": {
    "tgn:hierarchy":[
        "tgn:2482747",
        "tgn:1000001",
        "tgn:7012149",
        "tgn:2001856",
        "tgn:7007825",
        "tgn:7029392"
    ],
    "tgn:id":2482747,
    "tgn:name":"Largo",
    "tgn:placetype":[
        "aat:300008347"
    ]
},
  "bbox": [],
  "geometry": {"coordinates":[-88.0833,35.55],"type":"Point"}
}