{
  "id": 1063005,
  "type": "Feature",
  "properties": {
    "tgn:hierarchy":[
        "tgn:1063005",
        "tgn:1000403",
        "tgn:1000003",
        "tgn:1000097",
        "tgn:7029392"
    ],
    "tgn:id":1063005,
    "tgn:name":"Gagnef",
    "tgn:placetype":[
        "aat:300008347"
    ]
},
  "bbox": [],
  "geometry": {"coordinates":[15.0833,60.5833],"type":"Point"}
}