{
  "id": 1031267,
  "type": "Feature",
  "properties": {
    "tgn:hierarchy":[
        "tgn:1031267",
        "tgn:7024077",
        "tgn:1000003",
        "tgn:1000069",
        "tgn:7029392"
    ],
    "tgn:id":1031267,
    "tgn:name":"Aura",
    "tgn:placetype":[
        "aat:300008347"
    ]
},
  "bbox": [],
  "geometry": {"coordinates":[22.5833,60.6167],"type":"Point"}
}