{
  "id": 2715049,
  "type": "Feature",
  "properties": {
    "tgn:hierarchy":[
        "tgn:2715049",
        "tgn:2000090",
        "tgn:1000001",
        "tgn:7006451",
        "tgn:7012149",
        "tgn:7029392"
    ],
    "tgn:id":2715049,
    "tgn:name":"Tenney Pond",
    "tgn:placetype":[
        "aat:300008680"
    ]
},
  "bbox": [],
  "geometry": {"coordinates":[-109.0667,33.7833],"type":"Point"}
}