<<<<<<< HEAD
{
  "id": 2259514,
  "type": "Feature",
  "properties": {
    "tgn:hierarchy":[
        "tgn:2259514",
        "tgn:1000001",
        "tgn:7012149",
        "tgn:2001440",
        "tgn:7007566",
        "tgn:7029392"
    ],
    "tgn:id":2259514,
    "tgn:name":"Cottonwood Tank",
    "tgn:placetype":[
        "aat:300006191"
    ]
},
  "bbox": [],
  "geometry": {"coordinates":[-108.2833,31.4],"type":"Point"}
}
=======
{"geometry":{"type":"Point","coordinates":[-108.283300,31.400000]},"type":"Feature","properties":{"hierarchy":["tgn:2259514","tgn:1000001","tgn:7012149","tgn:2001440","tgn:7007566","tgn:7029392"],"placetype":["aat:300006191"],"id":2259514,"name:xx":"Cottonwood Tank"}}
>>>>>>> 03f74aca74312dbeaf24d7e61306dd6a786dc3d0
