{
  "id": 2533372,
  "type": "Feature",
  "properties": {
    "tgn:hierarchy":[
        "tgn:2533372",
        "tgn:1000001",
        "tgn:2001586",
        "tgn:7012149",
        "tgn:7007705",
        "tgn:7029392"
    ],
    "tgn:id":2533372,
    "tgn:name":"Muskrat Creek",
    "tgn:placetype":[
        "aat:300008706"
    ]
},
  "bbox": [],
  "geometry": {"coordinates":[-101.5333,46.9167],"type":"Point"}
}