{
  "id": 2629710,
  "type": "Feature",
  "properties": {
    "tgn:hierarchy":[
        "tgn:2629710",
        "tgn:1000001",
        "tgn:7012149",
        "tgn:1002682",
        "tgn:7007710",
        "tgn:7029392"
    ],
    "tgn:id":2629710,
    "tgn:name":"Ross Common Creek",
    "tgn:placetype":[
        "aat:300008706"
    ]
},
  "bbox": [],
  "geometry": {"coordinates":[-75.25,40.8833],"type":"Point"}
}