{
  "id": 2173324,
  "type": "Feature",
  "properties": {
    "tgn:hierarchy":[
        "tgn:2173324",
        "tgn:1000001",
        "tgn:7012149",
        "tgn:7007251",
        "tgn:7029392"
    ],
    "tgn:id":2173324,
    "tgn:name":"Birch Creek",
    "tgn:placetype":[
        "aat:300008706"
    ]
},
  "bbox": [],
  "geometry": {"coordinates":[-87.7167,38.85],"type":"Point"}
}