{
  "id": 7160595,
  "type": "Feature",
  "properties": {
    "tgn:hierarchy":[
        "tgn:7160595",
        "tgn:7003669",
        "tgn:1000003",
        "tgn:7000084",
        "tgn:7029392"
    ],
    "tgn:id":7160595,
    "tgn:name":"Hof",
    "tgn:placetype":[
        "aat:300008347"
    ]
},
  "bbox": [],
  "geometry": {"coordinates":[11.816667,47.816667],"type":"Point"}
}