{
  "id": 7387531,
  "type": "Feature",
  "properties": {
    "tgn:hierarchy":[
        "tgn:7387531",
        "tgn:7005586",
        "tgn:1000001",
        "tgn:7005560",
        "tgn:7029392"
    ],
    "tgn:id":7387531,
    "tgn:name":"Portezuelo Nuevo",
    "tgn:placetype":[
        "aat:300008347"
    ]
},
  "bbox": [],
  "geometry": {"coordinates":[-103.266667,19.616667],"type":"Point"}
}