{
  "id": 7228441,
  "type": "Feature",
  "properties": {
    "tgn:hierarchy":[
        "tgn:7228441",
        "tgn:7002715",
        "tgn:7002731",
        "tgn:1000003",
        "tgn:1000074",
        "tgn:7029392"
    ],
    "tgn:id":7228441,
    "tgn:name":"Kassandrin\u00f3n",
    "tgn:placetype":[
        "aat:300008347"
    ]
},
  "bbox": [],
  "geometry": {"coordinates":[23.45,40.016667],"type":"Point"}
}