<<<<<<< HEAD
{
  "id": 2156339,
  "type": "Feature",
  "properties": {
    "tgn:hierarchy":[
        "tgn:2156339",
        "tgn:1000001",
        "tgn:2001473",
        "tgn:7012149",
        "tgn:7007709",
        "tgn:7029392"
    ],
    "tgn:id":2156339,
    "tgn:name":"Bearpen Knob",
    "tgn:placetype":[
        "aat:300008798"
    ]
},
  "bbox": [],
  "geometry": {"coordinates":[-82.3833,35.6833],"type":"Point"}
}
=======
{"geometry":{"type":"Point","coordinates":[-82.383300,35.683300]},"type":"Feature","properties":{"hierarchy":["tgn:2156339","tgn:1000001","tgn:2001473","tgn:7012149","tgn:7007709","tgn:7029392"],"placetype":["aat:300008798"],"id":2156339,"name:xx":"Bearpen Knob"}}
>>>>>>> 03f74aca74312dbeaf24d7e61306dd6a786dc3d0
