{
  "id": 2303333,
  "type": "Feature",
  "properties": {
    "tgn:hierarchy":[
        "tgn:2303333",
        "tgn:1000001",
        "tgn:7012149",
        "tgn:7007157",
        "tgn:2000186",
        "tgn:7029392"
    ],
    "tgn:id":2303333,
    "tgn:name":"Eagle Creek",
    "tgn:placetype":[
        "aat:300008706"
    ]
},
  "bbox": [],
  "geometry": {"coordinates":[-120.1833,41.2667],"type":"Point"}
}