{
  "id": 7390759,
  "type": "Feature",
  "properties": {
    "tgn:hierarchy":[
        "tgn:7390759",
        "tgn:1001853",
        "tgn:1000001",
        "tgn:7005560",
        "tgn:7029392"
    ],
    "tgn:id":7390759,
    "tgn:name":"Rancho San Jos\u00e9 de Colete",
    "tgn:placetype":[
        "aat:300008347"
    ]
},
  "bbox": [],
  "geometry": {"coordinates":[-101.116667,28.016667],"type":"Point"}
}