{
  "id": 2492173,
  "type": "Feature",
  "properties": {
    "tgn:hierarchy":[
        "tgn:2492173",
        "tgn:1000001",
        "tgn:2001638",
        "tgn:7012149",
        "tgn:7007707",
        "tgn:7029392"
    ],
    "tgn:id":2492173,
    "tgn:name":"Marcy, Mount",
    "tgn:placetype":[
        "aat:300008798"
    ]
},
  "bbox": [],
  "geometry": {"coordinates":[-98.65,34.7333],"type":"Point"}
}