{
  "id": 7329976,
  "type": "Feature",
  "properties": {
    "tgn:hierarchy":[
        "tgn:7329976",
        "tgn:7002804",
        "tgn:1000003",
        "tgn:7002793",
        "tgn:1000095",
        "tgn:7029392"
    ],
    "tgn:id":7329976,
    "tgn:name":"Huerta Parri",
    "tgn:placetype":[
        "aat:300008347"
    ]
},
  "bbox": [],
  "geometry": {"coordinates":[0.016667,38.833333],"type":"Point"}
}