{
  "id": 7307623,
  "type": "Feature",
  "properties": {
    "tgn:hierarchy":[
        "tgn:7307623",
        "tgn:7002759",
        "tgn:7008909",
        "tgn:1000003",
        "tgn:1000095",
        "tgn:7029392"
    ],
    "tgn:id":7307623,
    "tgn:name":"L\u00fapera, Sierra de",
    "tgn:placetype":[
        "aat:300266640"
    ]
},
  "bbox": [],
  "geometry": {"coordinates":[-0.116667,42.383333],"type":"Point"}
}