{
  "id": 7029866,
  "type": "Feature",
  "properties": {
    "tgn:hierarchy":[
        "tgn:7029866",
        "tgn:7002445",
        "tgn:1000003",
        "tgn:7008166",
        "tgn:7008591",
        "tgn:7029392"
    ],
    "tgn:id":7029866,
    "tgn:name:en":"Bilton",
    "tgn:placetype":[
        "aat:300008347",
        "aat:300008372"
    ]
},
  "bbox": [],
  "geometry": {"coordinates":[-1.542,54.001],"type":"Point"}
}