{
  "id": 2378981,
  "type": "Feature",
  "properties": {
    "tgn:hierarchy":[
        "tgn:2378981",
        "tgn:1000001",
        "tgn:7012149",
        "tgn:2001448",
        "tgn:7007566",
        "tgn:7029392"
    ],
    "tgn:id":2378981,
    "tgn:name":"Hartford Canyon",
    "tgn:placetype":[
        "aat:300008761"
    ]
},
  "bbox": [],
  "geometry": {"coordinates":[-103.9167,34.8333],"type":"Point"}
}