{
  "id": 7095908,
  "type": "Feature",
  "properties": {
    "tgn:hierarchy":[
        "tgn:7095908",
        "tgn:1000003",
        "tgn:7003687",
        "tgn:7000084",
        "tgn:7029392"
    ],
    "tgn:id":7095908,
    "tgn:name":"Schwerzau",
    "tgn:placetype":[
        "aat:300008347"
    ]
},
  "bbox": [],
  "geometry": {"coordinates":[12.166667,51.116667],"type":"Point"}
}