{
  "id": 7452182,
  "type": "Feature",
  "properties": {
    "tgn:hierarchy":[
        "tgn:7452182",
        "tgn:7002445",
        "tgn:1000003",
        "tgn:7008165",
        "tgn:7008591",
        "tgn:7029392"
    ],
    "tgn:id":7452182,
    "tgn:name:en":"Fowberry Tower",
    "tgn:placetype":[
        "aat:300387502"
    ]
},
  "bbox": [],
  "geometry": {"coordinates":[-1.933333,55.55],"type":"Point"}
}