{
  "id": 7080976,
  "type": "Feature",
  "properties": {
    "tgn:hierarchy":[
        "tgn:7080976",
        "tgn:1000003",
        "tgn:7003688",
        "tgn:7000084",
        "tgn:7029392"
    ],
    "tgn:id":7080976,
    "tgn:name":"W\u00f6ppenstieg",
    "tgn:placetype":[
        "aat:300000206"
    ]
},
  "bbox": [],
  "geometry": {"coordinates":[9.083333,53.933333],"type":"Point"}
}