{
  "id": 2096077,
  "type": "Feature",
  "properties": {
    "tgn:hierarchy":[
        "tgn:2096077",
        "tgn:1000001",
        "tgn:7012149",
        "tgn:2001753",
        "tgn:7007712",
        "tgn:7029392"
    ],
    "tgn:id":2096077,
    "tgn:name":"Kershaw",
    "tgn:placetype":[
        "aat:300008347"
    ]
},
  "bbox": [],
  "geometry": {"coordinates":[-80.5833,34.55],"type":"Point"}
}