{
  "id": 2485861,
  "type": "Feature",
  "properties": {
    "tgn:hierarchy":[
        "tgn:2485861",
        "tgn:2002101",
        "tgn:1000001",
        "tgn:7012149",
        "tgn:7007827",
        "tgn:7029392"
    ],
    "tgn:id":2485861,
    "tgn:name":"LeBaron Lake",
    "tgn:placetype":[
        "aat:300006191"
    ]
},
  "bbox": [],
  "geometry": {"coordinates":[-112.3833,38.2167],"type":"Point"}
}