{
  "id": 2627007,
  "type": "Feature",
  "properties": {
    "tgn:hierarchy":[
        "tgn:2627007",
        "tgn:1000001",
        "tgn:7012149",
        "tgn:1002802",
        "tgn:7007706",
        "tgn:7029392"
    ],
    "tgn:id":2627007,
    "tgn:name":"Rocky Run",
    "tgn:placetype":[
        "aat:300008699"
    ]
},
  "bbox": [],
  "geometry": {"coordinates":[-84.6833,39.8167],"type":"Point"}
}