{
  "id": 2696255,
  "type": "Feature",
  "properties": {
    "tgn:hierarchy":[
        "tgn:2696255",
        "tgn:1000001",
        "tgn:7006451",
        "tgn:2000094",
        "tgn:7012149",
        "tgn:7029392"
    ],
    "tgn:id":2696255,
    "tgn:name":"Stone Cabin Spring",
    "tgn:placetype":[
        "aat:300008697"
    ]
},
  "bbox": [],
  "geometry": {"coordinates":[-110.3667,32.4667],"type":"Point"}
}