{
  "id": 2281254,
  "type": "Feature",
  "properties": {
    "tgn:hierarchy":[
        "tgn:2281254",
        "tgn:1000001",
        "tgn:7012149",
        "tgn:2000639",
        "tgn:7007253",
        "tgn:7029392"
    ],
    "tgn:id":2281254,
    "tgn:name":"Deep River",
    "tgn:placetype":[
        "aat:300008707"
    ]
},
  "bbox": [],
  "geometry": {"coordinates":[-92.55,41.6167],"type":"Point"}
}