{
  "id": 2452149,
  "type": "Feature",
  "properties": {
    "tgn:hierarchy":[
        "tgn:2452149",
        "tgn:1000001",
        "tgn:7012149",
        "tgn:2001613",
        "tgn:7007706",
        "tgn:7029392"
    ],
    "tgn:id":2452149,
    "tgn:name":"Little Blackjack Branch",
    "tgn:placetype":[
        "aat:300008699"
    ]
},
  "bbox": [],
  "geometry": {"coordinates":[-82.4833,39.45],"type":"Point"}
}