{
  "id": 2589209,
  "type": "Feature",
  "properties": {
    "tgn:hierarchy":[
        "tgn:2589209",
        "tgn:1002648",
        "tgn:1000001",
        "tgn:1008191",
        "tgn:7012149",
        "tgn:7007249",
        "tgn:7029392"
    ],
    "tgn:id":2589209,
    "tgn:name":"Pohakunui",
    "tgn:placetype":[
        "aat:300008798"
    ]
},
  "bbox": [],
  "geometry": {"coordinates":[-157.05,21.1833],"type":"Point"}
}