{
  "id": 7194160,
  "type": "Feature",
  "properties": {
    "tgn:hierarchy":[
        "tgn:7194160",
        "tgn:1000003",
        "tgn:7003676",
        "tgn:7000084",
        "tgn:7029392"
    ],
    "tgn:id":7194160,
    "tgn:name":"Deppoldshausen",
    "tgn:placetype":[
        "aat:300387173"
    ]
},
  "bbox": [],
  "geometry": {"coordinates":[9.966667,51.583333],"type":"Point"}
}