{
  "id": 2660802,
  "type": "Feature",
  "properties": {
    "tgn:hierarchy":[
        "tgn:2660802",
        "tgn:1000001",
        "tgn:2000922",
        "tgn:7012149",
        "tgn:7007515",
        "tgn:7029392"
    ],
    "tgn:id":2660802,
    "tgn:name":"Shorey Brook",
    "tgn:placetype":[
        "aat:300008699"
    ]
},
  "bbox": [],
  "geometry": {"coordinates":[-68.0333,44.85],"type":"Point"}
}