{
  "id": 2471358,
  "type": "Feature",
  "properties": {
    "tgn:hierarchy":[
        "tgn:2471358",
        "tgn:1000001",
        "tgn:7012149",
        "tgn:2000276",
        "tgn:7007240",
        "tgn:7029392"
    ],
    "tgn:id":2471358,
    "tgn:name":"Lost Lake",
    "tgn:placetype":[
        "aat:300008680"
    ]
},
  "bbox": [],
  "geometry": {"coordinates":[-84.3833,30.35],"type":"Point"}
}