{
  "id": 1042637,
  "type": "Feature",
  "properties": {
    "tgn:hierarchy":[
        "tgn:1042637",
        "tgn:7003497",
        "tgn:7001201",
        "tgn:1000003",
        "tgn:1000078",
        "tgn:7029392"
    ],
    "tgn:id":1042637,
    "tgn:name":"Baltimore",
    "tgn:placetype":[
        "aat:300008347"
    ]
},
  "bbox": [],
  "geometry": {"coordinates":[-9.3667,51.4833],"type":"Point"}
}