{
  "id": 2367597,
  "type": "Feature",
  "properties": {
    "tgn:hierarchy":[
        "tgn:2367597",
        "tgn:1000001",
        "tgn:2001705",
        "tgn:7012149",
        "tgn:7007708",
        "tgn:7029392"
    ],
    "tgn:id":2367597,
    "tgn:name":"Grouse Lake",
    "tgn:placetype":[
        "aat:300008680"
    ]
},
  "bbox": [],
  "geometry": {"coordinates":[-121.9333,43.6833],"type":"Point"}
}