<<<<<<< HEAD
{
  "id": 2762098,
  "type": "Feature",
  "properties": {
    "tgn:hierarchy":[
        "tgn:2762098",
        "tgn:1000001",
        "tgn:2000463",
        "tgn:7012149",
        "tgn:7007250",
        "tgn:7029392"
    ],
    "tgn:id":2762098,
    "tgn:name":"West Side Reservoir",
    "tgn:placetype":[
        "aat:300006191"
    ]
},
  "bbox": [],
  "geometry": {"coordinates":[-113.2167,43.4],"type":"Point"}
}
=======
{"geometry":{"type":"Point","coordinates":[-113.216700,43.400000]},"type":"Feature","properties":{"hierarchy":["tgn:2762098","tgn:1000001","tgn:2000463","tgn:7012149","tgn:7007250","tgn:7029392"],"placetype":["aat:300006191"],"id":2762098,"name:xx":"West Side Reservoir"}}
>>>>>>> 03f74aca74312dbeaf24d7e61306dd6a786dc3d0
