{
  "id": 1107736,
  "type": "Feature",
  "properties": {
    "tgn:hierarchy":[
        "tgn:1107736",
        "tgn:1001768",
        "tgn:1000049",
        "tgn:1000002",
        "tgn:1008543",
        "tgn:7029392"
    ],
    "tgn:id":1107736,
    "tgn:name":"Rana Kao, Volc\u00e1n",
    "tgn:placetype":[
        "aat:300386986",
        "aat:300132325"
    ]
},
  "bbox": [],
  "geometry": {"coordinates":[-109.45,-27.183333],"type":"Point"}
}