{
  "id": 7557247,
  "type": "Feature",
  "properties": {
    "tgn:hierarchy":[
        "tgn:7557247",
        "tgn:1000004",
        "tgn:7000198",
        "tgn:7016694",
        "tgn:7029392"
    ],
    "tgn:id":7557247,
    "tgn:name:en":"S\u0101landi River",
    "tgn:placetype":[
        "aat:300008699"
    ]
},
  "bbox": [],
  "geometry": {"coordinates":[86.67768,20.790664],"type":"Point"}
}