{
  "id": 2425785,
  "type": "Feature",
  "properties": {
    "tgn:hierarchy":[
        "tgn:2425785",
        "tgn:1000001",
        "tgn:7012149",
        "tgn:2002379",
        "tgn:7007923",
        "tgn:7029392"
    ],
    "tgn:id":2425785,
    "tgn:name":"Jojo Mountain",
    "tgn:placetype":[
        "aat:300008798"
    ]
},
  "bbox": [],
  "geometry": {"coordinates":[-109.2667,43.95],"type":"Point"}
}