{
  "id": 2248640,
  "type": "Feature",
  "properties": {
    "tgn:hierarchy":[
        "tgn:2248640",
        "tgn:1000001",
        "tgn:7012149",
        "tgn:7007157",
        "tgn:7029392"
    ],
    "tgn:id":2248640,
    "tgn:name":"Cold Spring Mountain",
    "tgn:placetype":[
        "aat:300008798"
    ]
},
  "bbox": [],
  "geometry": {"coordinates":[-122.4833,39.0833],"type":"Point"}
}