{
  "id": 1088176,
  "type": "Feature",
  "properties": {
    "tgn:hierarchy":[
        "tgn:1088176",
        "tgn:7001242",
        "tgn:1001546",
        "tgn:1000153",
        "tgn:7029392"
    ],
    "tgn:id":1088176,
    "tgn:name":"Buea",
    "tgn:placetype":[
        "aat:300008347",
        "aat:300387223"
    ]
},
  "bbox": [],
  "geometry": {"coordinates":[9.2167,4.15],"type":"Point"}
}