{
  "id": 7096009,
  "type": "Feature",
  "properties": {
    "tgn:hierarchy":[
        "tgn:7096009",
        "tgn:1000003",
        "tgn:7003688",
        "tgn:7000084",
        "tgn:7029392"
    ],
    "tgn:id":7096009,
    "tgn:name":"Schwanholm",
    "tgn:placetype":[
        "aat:300000206"
    ]
},
  "bbox": [],
  "geometry": {"coordinates":[9.783333,54.683333],"type":"Point"}
}