{
  "id": 1062140,
  "type": "Feature",
  "properties": {
    "tgn:hierarchy":[
        "tgn:1062140",
        "tgn:7002847",
        "tgn:1001647",
        "tgn:1000003",
        "tgn:1000095",
        "tgn:7029392"
    ],
    "tgn:id":1062140,
    "tgn:name":"La Puebla de Montalb\u00e1n",
    "tgn:placetype":[
        "aat:300008347"
    ]
},
  "bbox": [],
  "geometry": {"coordinates":[-4.35,39.866667],"type":"Point"}
}