{
  "id": 2715052,
  "type": "Feature",
  "properties": {
    "tgn:hierarchy":[
        "tgn:2715052",
        "tgn:2000090",
        "tgn:1000001",
        "tgn:7006451",
        "tgn:7012149",
        "tgn:7029392"
    ],
    "tgn:id":2715052,
    "tgn:name":"Tenney Tank",
    "tgn:placetype":[
        "aat:300006191"
    ]
},
  "bbox": [],
  "geometry": {"coordinates":[-109.0833,33.7833],"type":"Point"}
}