{
  "id": 2746567,
  "type": "Feature",
  "properties": {
    "tgn:hierarchy":[
        "tgn:2746567",
        "tgn:1000001",
        "tgn:2001740",
        "tgn:7012149",
        "tgn:7007712",
        "tgn:7029392"
    ],
    "tgn:id":2746567,
    "tgn:name":"Wachovia Hills",
    "tgn:placetype":[
        "aat:300008347"
    ]
},
  "bbox": [],
  "geometry": {"coordinates":[-79.6833,34.2833],"type":"Point"}
}