{
  "id": 2648180,
  "type": "Feature",
  "properties": {
    "tgn:hierarchy":[
        "tgn:2648180",
        "tgn:1000001",
        "tgn:7012149",
        "tgn:7007157",
        "tgn:2000184",
        "tgn:7029392"
    ],
    "tgn:id":2648180,
    "tgn:name":"Schoonamaker Lake",
    "tgn:placetype":[
        "aat:300008680"
    ]
},
  "bbox": [],
  "geometry": {"coordinates":[-121.0333,40.7667],"type":"Point"}
}