{
  "id": 2343116,
  "type": "Feature",
  "properties": {
    "tgn:hierarchy":[
        "tgn:2343116",
        "tgn:1000001",
        "tgn:2002256",
        "tgn:7012149",
        "tgn:7013961",
        "tgn:7029392"
    ],
    "tgn:id":2343116,
    "tgn:name":"Gabel Knob",
    "tgn:placetype":[
        "aat:300008798"
    ]
},
  "bbox": [],
  "geometry": {"coordinates":[-80.65,38.7833],"type":"Point"}
}