<<<<<<< HEAD
{
  "id": 2409402,
  "type": "Feature",
  "properties": {
    "tgn:hierarchy":[
        "tgn:2409402",
        "tgn:1000001",
        "tgn:2000460",
        "tgn:7012149",
        "tgn:7007250",
        "tgn:7029392"
    ],
    "tgn:id":2409402,
    "tgn:name":"Idaho Lakeview Mine",
    "tgn:placetype":[
        "aat:300000390"
    ]
},
  "bbox": [],
  "geometry": {"coordinates":[-116.4667,47.9],"type":"Point"}
}
=======
{"geometry":{"type":"Point","coordinates":[-116.466700,47.900000]},"type":"Feature","properties":{"hierarchy":["tgn:2409402","tgn:1000001","tgn:2000460","tgn:7012149","tgn:7007250","tgn:7029392"],"placetype":["aat:300000390"],"id":2409402,"name:xx":"Idaho Lakeview Mine"}}
>>>>>>> 03f74aca74312dbeaf24d7e61306dd6a786dc3d0
