<<<<<<< HEAD
{
  "id": 2336200,
  "type": "Feature",
  "properties": {
    "tgn:hierarchy":[
        "tgn:2336200",
        "tgn:1000001",
        "tgn:2001424",
        "tgn:7012149",
        "tgn:7007564",
        "tgn:7029392"
    ],
    "tgn:id":2336200,
    "tgn:name":"Foster Pond",
    "tgn:placetype":[
        "aat:300008680"
    ]
},
  "bbox": [],
  "geometry": {"coordinates":[-71.7833,43.5833],"type":"Point"}
}
=======
{"geometry":{"type":"Point","coordinates":[-71.783300,43.583300]},"type":"Feature","properties":{"hierarchy":["tgn:2336200","tgn:1000001","tgn:2001424","tgn:7012149","tgn:7007564","tgn:7029392"],"placetype":["aat:300008680"],"id":2336200,"name:xx":"Foster Pond"}}
>>>>>>> 03f74aca74312dbeaf24d7e61306dd6a786dc3d0
