{
  "id": 7528150,
  "type": "Feature",
  "properties": {
    "tgn:hierarchy":[
        "tgn:7528150",
        "tgn:7001242",
        "tgn:7016833",
        "tgn:7001334",
        "tgn:7029392"
    ],
    "tgn:id":7528150,
    "tgn:name:en":"Qasr Umm el-Nasim",
    "tgn:placetype":[
        "aat:300006909"
    ]
},
  "bbox": [],
  "geometry": {"coordinates":[30.55,25.366667],"type":"Point"}
}