{
  "id": 7213438,
  "type": "Feature",
  "properties": {
    "tgn:hierarchy":[
        "tgn:7213438",
        "tgn:1000003",
        "tgn:7003676",
        "tgn:7000084",
        "tgn:7029392"
    ],
    "tgn:id":7213438,
    "tgn:name":"Bobrink",
    "tgn:placetype":[
        "aat:300000206"
    ]
},
  "bbox": [],
  "geometry": {"coordinates":[8.716667,52.666667],"type":"Point"}
}