{
  "id": 7354683,
  "type": "Feature",
  "properties": {
    "tgn:hierarchy":[
        "tgn:7354683",
        "tgn:7005583",
        "tgn:1000001",
        "tgn:7005560",
        "tgn:7029392"
    ],
    "tgn:id":7354683,
    "tgn:name":"Casta\u00f1eda",
    "tgn:placetype":[
        "aat:300008347"
    ]
},
  "bbox": [],
  "geometry": {"coordinates":[-105.833333,26.166667],"type":"Point"}
}