{
  "id": 1045239,
  "type": "Feature",
  "properties": {
    "tgn:hierarchy":[
        "tgn:1045239",
        "tgn:1003447",
        "tgn:7007850",
        "tgn:1000003",
        "tgn:1000080",
        "tgn:7029392"
    ],
    "tgn:id":1045239,
    "tgn:name":"Marcedusa",
    "tgn:placetype":[
        "aat:300008347"
    ]
},
  "bbox": [],
  "geometry": {"coordinates":[16.833333,39.033333],"type":"Point"}
}