{
  "id": 2480229,
  "type": "Feature",
  "properties": {
    "tgn:hierarchy":[
        "tgn:2480229",
        "tgn:1000001",
        "tgn:7012149",
        "tgn:2000930",
        "tgn:7007515",
        "tgn:7029392"
    ],
    "tgn:id":2480229,
    "tgn:name":"Lake Parlin",
    "tgn:placetype":[
        "aat:300008347"
    ]
},
  "bbox": [],
  "geometry": {"coordinates":[-70.0833,45.5167],"type":"Point"}
}