{
  "id": 1079925,
  "type": "Feature",
  "properties": {
    "tgn:hierarchy":[
        "tgn:1079925",
        "tgn:1000985",
        "tgn:7016529",
        "tgn:7016531",
        "tgn:1000004",
        "tgn:1000120",
        "tgn:7029392"
    ],
    "tgn:id":1079925,
    "tgn:name":"Erimo",
    "tgn:placetype":[
        "aat:300008347"
    ]
},
  "bbox": [],
  "geometry": {"coordinates":[143.25,41.9333],"type":"Point"}
}