{
  "id": 7279981,
  "type": "Feature",
  "properties": {
    "tgn:hierarchy":[
        "tgn:7279981",
        "tgn:7016598",
        "tgn:1000049",
        "tgn:1000002",
        "tgn:7029392"
    ],
    "tgn:id":7279981,
    "tgn:name":"Refresco",
    "tgn:placetype":[
        "aat:300008347"
    ]
},
  "bbox": [],
  "geometry": {"coordinates":[-69.766667,-23.416667],"type":"Point"}
}