{
  "id": 7084488,
  "type": "Feature",
  "properties": {
    "tgn:hierarchy":[
        "tgn:7084488",
        "tgn:7000096",
        "tgn:1000003",
        "tgn:7000084",
        "tgn:7029392"
    ],
    "tgn:id":7084488,
    "tgn:name":"Wildgrube",
    "tgn:placetype":[
        "aat:300008347"
    ]
},
  "bbox": [],
  "geometry": {"coordinates":[13.383333,51.583333],"type":"Point"}
}