{
  "id": 7116612,
  "type": "Feature",
  "properties": {
    "tgn:hierarchy":[
        "tgn:7116612",
        "tgn:1000003",
        "tgn:7003677",
        "tgn:7000084",
        "tgn:7029392"
    ],
    "tgn:id":7116612,
    "tgn:name":"Otterbeck",
    "tgn:placetype":[
        "aat:300000206"
    ]
},
  "bbox": [],
  "geometry": {"coordinates":[6.983333,51.316667],"type":"Point"}
}