<<<<<<< HEAD
{
  "id": 7116612,
  "type": "Feature",
  "properties": {
    "tgn:hierarchy":[
        "tgn:7116612",
        "tgn:1000003",
        "tgn:7003677",
        "tgn:7000084",
        "tgn:7029392"
    ],
    "tgn:id":7116612,
    "tgn:name":"Otterbeck",
    "tgn:placetype":[
        "aat:300000206"
    ]
},
  "bbox": [],
  "geometry": {"coordinates":[6.983333,51.316667],"type":"Point"}
}
=======
{"geometry":{"type":"Point","coordinates":[6.983333,51.316667]},"type":"Feature","properties":{"hierarchy":["tgn:7116612","tgn:1000003","tgn:7003677","tgn:7000084","tgn:7029392"],"placetype":["aat:300000206"],"id":7116612,"name:xx":"Otterbeck"}}
>>>>>>> 03f74aca74312dbeaf24d7e61306dd6a786dc3d0
