{
  "id": 2189136,
  "type": "Feature",
  "properties": {
    "tgn:hierarchy":[
        "tgn:2189136",
        "tgn:1002366",
        "tgn:1000001",
        "tgn:7012149",
        "tgn:7007159",
        "tgn:7029392"
    ],
    "tgn:id":2189136,
    "tgn:name":"Bound Swamp",
    "tgn:placetype":[
        "aat:300008905"
    ]
},
  "bbox": [],
  "geometry": {"coordinates":[-73.3667,41.4167],"type":"Point"}
}