{
  "id": 2586241,
  "type": "Feature",
  "properties": {
    "tgn:hierarchy":[
        "tgn:2586241",
        "tgn:1000001",
        "tgn:2001014",
        "tgn:7012149",
        "tgn:7007521",
        "tgn:7029392"
    ],
    "tgn:id":2586241,
    "tgn:name":"Pit Lake",
    "tgn:placetype":[
        "aat:300008680"
    ]
},
  "bbox": [],
  "geometry": {"coordinates":[-90.4333,47.8833],"type":"Point"}
}