{
  "id": 7290785,
  "type": "Feature",
  "properties": {
    "tgn:hierarchy":[
        "tgn:7290785",
        "tgn:7002464",
        "tgn:1000049",
        "tgn:1000002",
        "tgn:7029392"
    ],
    "tgn:id":7290785,
    "tgn:name":"Cuya, Cerro",
    "tgn:placetype":[
        "aat:300008777"
    ]
},
  "bbox": [],
  "geometry": {"coordinates":[-70.133333,-19.15],"type":"Point"}
}