{
  "id": 1044093,
  "type": "Feature",
  "properties": {
    "tgn:hierarchy":[
        "tgn:1044093",
        "tgn:7003129",
        "tgn:1000003",
        "tgn:7008516",
        "tgn:1000080",
        "tgn:7029392"
    ],
    "tgn:id":1044093,
    "tgn:name":"Castrocaro Terme",
    "tgn:placetype":[
        "aat:300008347"
    ]
},
  "bbox": [],
  "geometry": {"coordinates":[11.95,44.166667],"type":"Point"}
}