<<<<<<< HEAD
{
  "id": 2338160,
  "type": "Feature",
  "properties": {
    "tgn:hierarchy":[
        "tgn:2338160",
        "tgn:1002338",
        "tgn:1000001",
        "tgn:7012149",
        "tgn:7007516",
        "tgn:7029392"
    ],
    "tgn:id":2338160,
    "tgn:name":"Fox Point",
    "tgn:placetype":[
        "aat:300008850"
    ]
},
  "bbox": [],
  "geometry": {"coordinates":[-76.1,38.2833],"type":"Point"}
}
=======
{"geometry":{"type":"Point","coordinates":[-76.100000,38.283300]},"type":"Feature","properties":{"hierarchy":["tgn:2338160","tgn:1002338","tgn:1000001","tgn:7012149","tgn:7007516","tgn:7029392"],"placetype":["aat:300008850"],"id":2338160,"name:xx":"Fox Point"}}
>>>>>>> 03f74aca74312dbeaf24d7e61306dd6a786dc3d0
