{
  "id": 7501651,
  "type": "Feature",
  "properties": {
    "tgn:hierarchy":[
        "tgn:7501651",
        "tgn:7488858",
        "tgn:1000004",
        "tgn:1000141",
        "tgn:7029392"
    ],
    "tgn:id":7501651,
    "tgn:name":"Beizhukeng",
    "tgn:placetype":[
        "aat:300008347"
    ]
},
  "bbox": [],
  "geometry": {"coordinates":[120.865235,24.027897],"type":"Point"}
}