{
  "id": 1058063,
  "type": "Feature",
  "properties": {
    "tgn:hierarchy":[
        "tgn:1058063",
        "tgn:1000004",
        "tgn:4008031",
        "tgn:7018214",
        "tgn:7002435",
        "tgn:7029392"
    ],
    "tgn:id":1058063,
    "tgn:name":"Oskuy",
    "tgn:placetype":[
        "aat:300008347"
    ]
},
  "bbox": [],
  "geometry": {"coordinates":[32.0833,59.2833],"type":"Point"}
}