{
  "id": 7128766,
  "type": "Feature",
  "properties": {
    "tgn:hierarchy":[
        "tgn:7128766",
        "tgn:7003692",
        "tgn:1000003",
        "tgn:7000084",
        "tgn:7029392"
    ],
    "tgn:id":7128766,
    "tgn:name":"Niederwald",
    "tgn:placetype":[
        "aat:300008863"
    ]
},
  "bbox": [],
  "geometry": {"coordinates":[8.516667,49.066667],"type":"Point"}
}