{
  "id": 7438548,
  "type": "Feature",
  "properties": {
    "tgn:hierarchy":[
        "tgn:7438548",
        "tgn:7005586",
        "tgn:1000001",
        "tgn:7005560",
        "tgn:7029392"
    ],
    "tgn:id":7438548,
    "tgn:name":"Saucillo",
    "tgn:placetype":[
        "aat:300008347"
    ]
},
  "bbox": [],
  "geometry": {"coordinates":[-104.133333,21.033333],"type":"Point"}
}