{
  "id": 1030682,
  "type": "Feature",
  "properties": {
    "tgn:hierarchy":[
        "tgn:1030682",
        "tgn:7002445",
        "tgn:1000003",
        "tgn:7008145",
        "tgn:7008591",
        "tgn:7029392"
    ],
    "tgn:id":1030682,
    "tgn:name":"South Oxhey",
    "tgn:placetype":[
        "aat:300008347"
    ]
},
  "bbox": [],
  "geometry": {"coordinates":[-0.3833,51.6333],"type":"Point"}
}