<<<<<<< HEAD
{
  "id": 7177236,
  "type": "Feature",
  "properties": {
    "tgn:hierarchy":[
        "tgn:7177236",
        "tgn:1000003",
        "tgn:7000094",
        "tgn:7000084",
        "tgn:7029392"
    ],
    "tgn:id":7177236,
    "tgn:name":"Gustavshof",
    "tgn:placetype":[
        "aat:300000206"
    ]
},
  "bbox": [],
  "geometry": {"coordinates":[11.45,53.883333],"type":"Point"}
}
=======
{"geometry":{"type":"Point","coordinates":[11.450000,53.883333]},"type":"Feature","properties":{"hierarchy":["tgn:7177236","tgn:1000003","tgn:7000094","tgn:7000084","tgn:7029392"],"placetype":["aat:300000206"],"id":7177236,"name:xx":"Gustavshof"}}
>>>>>>> 03f74aca74312dbeaf24d7e61306dd6a786dc3d0
