{
  "id": 1140456,
  "type": "Feature",
  "properties": {
    "tgn:hierarchy":[
        "tgn:1140456",
        "tgn:7000895",
        "tgn:1000004",
        "tgn:1001010",
        "tgn:1000120",
        "tgn:7029392"
    ],
    "tgn:id":1140456,
    "tgn:name":"Kiso",
    "tgn:placetype":[
        "aat:300008347"
    ]
},
  "bbox": [],
  "geometry": {"coordinates":[137.7833,35.9333],"type":"Point"}
}