{
  "id": 7101615,
  "type": "Feature",
  "properties": {
    "tgn:hierarchy":[
        "tgn:7101615",
        "tgn:7003669",
        "tgn:1000003",
        "tgn:7000084",
        "tgn:7029392"
    ],
    "tgn:id":7101615,
    "tgn:name":"Salzgattern",
    "tgn:placetype":[
        "aat:300008347"
    ]
},
  "bbox": [],
  "geometry": {"coordinates":[13.533333,48.716667],"type":"Point"}
}