{
  "id": 7306506,
  "type": "Feature",
  "properties": {
    "tgn:hierarchy":[
        "tgn:7306506",
        "tgn:7002825",
        "tgn:7016622",
        "tgn:1000003",
        "tgn:1000095",
        "tgn:7029392"
    ],
    "tgn:id":7306506,
    "tgn:name":"Los Roquerillos, Bajo de",
    "tgn:placetype":[
        "aat:300387036"
    ]
},
  "bbox": [],
  "geometry": {"coordinates":[-15.45,28.15],"type":"Point"}
}