<<<<<<< HEAD
{
  "id": 7243257,
  "type": "Feature",
  "properties": {
    "tgn:hierarchy":[
        "tgn:7243257",
        "tgn:7007877",
        "tgn:1000003",
        "tgn:1000063",
        "tgn:4012014",
        "tgn:7029392"
    ],
    "tgn:id":7243257,
    "tgn:name":"La Queue de Lerche",
    "tgn:placetype":[
        "aat:300008347"
    ]
},
  "bbox": [],
  "geometry": {"coordinates":[4.383333,50.083333],"type":"Point"}
}
=======
{"geometry":{"type":"Point","coordinates":[4.383333,50.083333]},"type":"Feature","properties":{"hierarchy":["tgn:7243257","tgn:7007877","tgn:1000003","tgn:1000063","tgn:4012014","tgn:7029392"],"placetype":["aat:300008347"],"id":7243257,"name:xx":"La Queue de Lerche"}}
>>>>>>> 03f74aca74312dbeaf24d7e61306dd6a786dc3d0
