<<<<<<< HEAD
{
  "id": 2705233,
  "type": "Feature",
  "properties": {
    "tgn:hierarchy":[
        "tgn:2705233",
        "tgn:1000001",
        "tgn:7012149",
        "tgn:2000492",
        "tgn:7007250",
        "tgn:7029392"
    ],
    "tgn:id":2705233,
    "tgn:name":"Superior Mine",
    "tgn:placetype":[
        "aat:300000390"
    ]
},
  "bbox": [],
  "geometry": {"coordinates":[-111.3,43.7],"type":"Point"}
}
=======
{"geometry":{"type":"Point","coordinates":[-111.300000,43.700000]},"type":"Feature","properties":{"hierarchy":["tgn:2705233","tgn:1000001","tgn:7012149","tgn:2000492","tgn:7007250","tgn:7029392"],"placetype":["aat:300000390"],"id":2705233,"name:xx":"Superior Mine"}}
>>>>>>> 03f74aca74312dbeaf24d7e61306dd6a786dc3d0
