{
  "id": 7491295,
  "type": "Feature",
  "properties": {
    "tgn:hierarchy":[
        "tgn:7491295",
        "tgn:1000004",
        "tgn:1000454",
        "tgn:1000141",
        "tgn:7029392"
    ],
    "tgn:id":7491295,
    "tgn:name":"Banqiao Shi",
    "tgn:placetype":[
        "aat:300387173"
    ]
},
  "bbox": [],
  "geometry": {"coordinates":[121.45,25.016667],"type":"Point"}
}