{
  "id": 2308475,
  "type": "Feature",
  "properties": {
    "tgn:hierarchy":[
        "tgn:2308475",
        "tgn:1000001",
        "tgn:7012149",
        "tgn:1002898",
        "tgn:7007826",
        "tgn:7029392"
    ],
    "tgn:id":2308475,
    "tgn:name":"East Mill Creek",
    "tgn:placetype":[
        "aat:300008706"
    ]
},
  "bbox": [],
  "geometry": {"coordinates":[-95.2667,32.4833],"type":"Point"}
}