{
  "id": 2461854,
  "type": "Feature",
  "properties": {
    "tgn:hierarchy":[
        "tgn:2461854",
        "tgn:1000001",
        "tgn:7006451",
        "tgn:2000093",
        "tgn:7012149",
        "tgn:7029392"
    ],
    "tgn:id":2461854,
    "tgn:name":"Little Trap Spring",
    "tgn:placetype":[
        "aat:300008697"
    ]
},
  "bbox": [],
  "geometry": {"coordinates":[-110.1333,33.9667],"type":"Point"}
}