{
  "id": 2614378,
  "type": "Feature",
  "properties": {
    "tgn:hierarchy":[
        "tgn:2614378",
        "tgn:1000001",
        "tgn:7012149",
        "tgn:2002114",
        "tgn:7007827",
        "tgn:7029392"
    ],
    "tgn:id":2614378,
    "tgn:name":"Reid Canal",
    "tgn:placetype":[
        "aat:300006075"
    ]
},
  "bbox": [],
  "geometry": {"coordinates":[-112.6833,39.3833],"type":"Point"}
}