{
  "id": 7048121,
  "type": "Feature",
  "properties": {
    "tgn:hierarchy":[
        "tgn:7048121",
        "tgn:1000003",
        "tgn:7003122",
        "tgn:1001753",
        "tgn:1000080",
        "tgn:7029392"
    ],
    "tgn:id":7048121,
    "tgn:name":"Casa Maccari",
    "tgn:placetype":[
        "aat:300008347"
    ]
},
  "bbox": [],
  "geometry": {"coordinates":[15.066667,36.766667],"type":"Point"}
}