{
  "id": 2162518,
  "type": "Feature",
  "properties": {
    "tgn:hierarchy":[
        "tgn:2162518",
        "tgn:7006450",
        "tgn:1000001",
        "tgn:2124089",
        "tgn:7012149",
        "tgn:7029392"
    ],
    "tgn:id":2162518,
    "tgn:name":"Ben Stewart, Mount",
    "tgn:placetype":[
        "aat:300008798"
    ]
},
  "bbox": [],
  "geometry": {"coordinates":[-134.55,58.2667],"type":"Point"}
}