{
  "id": 7015335,
  "type": "Feature",
  "properties": {
    "tgn:hierarchy":[
        "tgn:7015335",
        "tgn:1000001",
        "tgn:7012149",
        "tgn:7007157",
        "tgn:7023900",
        "tgn:1002608",
        "tgn:7029392"
    ],
    "tgn:id":7015335,
    "tgn:name":"Pacoima",
    "tgn:placetype":[
        "aat:300000745"
    ]
},
  "bbox": [],
  "geometry": {"coordinates":[-118.4167,34.25],"type":"Point"}
}