{
  "id": 2092225,
  "type": "Feature",
  "properties": {
    "tgn:hierarchy":[
        "tgn:2092225",
        "tgn:1000001",
        "tgn:7012149",
        "tgn:1003008",
        "tgn:7007710",
        "tgn:7029392"
    ],
    "tgn:id":2092225,
    "tgn:name":"Preston Park",
    "tgn:placetype":[
        "aat:300008347"
    ]
},
  "bbox": [],
  "geometry": {"coordinates":[-75.35,41.8667],"type":"Point"}
}