{
  "id": 2373779,
  "type": "Feature",
  "properties": {
    "tgn:hierarchy":[
        "tgn:2373779",
        "tgn:1000001",
        "tgn:7012149",
        "tgn:2000203",
        "tgn:7007158",
        "tgn:7029392"
    ],
    "tgn:id":2373779,
    "tgn:name":"Hamilton Peak",
    "tgn:placetype":[
        "aat:300008798"
    ]
},
  "bbox": [],
  "geometry": {"coordinates":[-105.4667,37.55],"type":"Point"}
}