{
  "id": 2294568,
  "type": "Feature",
  "properties": {
    "tgn:hierarchy":[
        "tgn:2294568",
        "tgn:1000001",
        "tgn:2001704",
        "tgn:7012149",
        "tgn:7007708",
        "tgn:7029392"
    ],
    "tgn:id":2294568,
    "tgn:name":"Doyle Point",
    "tgn:placetype":[
        "aat:300008850"
    ]
},
  "bbox": [],
  "geometry": {"coordinates":[-124.4167,42.4167],"type":"Point"}
}