{
  "id": 2437215,
  "type": "Feature",
  "properties": {
    "tgn:hierarchy":[
        "tgn:2437215",
        "tgn:7006450",
        "tgn:1000001",
        "tgn:7012149",
        "tgn:2000085",
        "tgn:7029392"
    ],
    "tgn:id":2437215,
    "tgn:name":"Kimball Glacier",
    "tgn:placetype":[
        "aat:300008835"
    ]
},
  "bbox": [],
  "geometry": {"coordinates":[-144.6167,63.2667],"type":"Point"}
}