{
  "id": 2174669,
  "type": "Feature",
  "properties": {
    "tgn:hierarchy":[
        "tgn:2174669",
        "tgn:1000001",
        "tgn:7012149",
        "tgn:7007256",
        "tgn:7029392"
    ],
    "tgn:id":2174669,
    "tgn:name":"Bistineau, Lake",
    "tgn:placetype":[
        "aat:300006191"
    ]
},
  "bbox": [],
  "geometry": {"coordinates":[-93.4167,32.3167],"type":"Point"}
}