{
  "id": 2311965,
  "type": "Feature",
  "properties": {
    "tgn:hierarchy":[
        "tgn:2311965",
        "tgn:1002247",
        "tgn:1000001",
        "tgn:7012149",
        "tgn:7007516",
        "tgn:7029392"
    ],
    "tgn:id":2311965,
    "tgn:name":"Egg Hill",
    "tgn:placetype":[
        "aat:300008798"
    ]
},
  "bbox": [],
  "geometry": {"coordinates":[-75.8833,39.65],"type":"Point"}
}