{
  "id": 7467950,
  "type": "Feature",
  "properties": {
    "tgn:hierarchy":[
        "tgn:7467950",
        "tgn:1000004",
        "tgn:7001013",
        "tgn:1000141",
        "tgn:7029392"
    ],
    "tgn:id":7467950,
    "tgn:name":"Zhentou Shan",
    "tgn:placetype":[
        "aat:300008795"
    ]
},
  "bbox": [],
  "geometry": {"coordinates":[121.333771,24.811658],"type":"Point"}
}