{
  "id": 2654378,
  "type": "Feature",
  "properties": {
    "tgn:hierarchy":[
        "tgn:2654378",
        "tgn:1000001",
        "tgn:7012149",
        "tgn:2000654",
        "tgn:7007253",
        "tgn:7029392"
    ],
    "tgn:id":2654378,
    "tgn:name":"Shady Oak",
    "tgn:placetype":[
        "aat:300008347"
    ]
},
  "bbox": [],
  "geometry": {"coordinates":[-94.15,42.45],"type":"Point"}
}