{
  "id": 2534770,
  "type": "Feature",
  "properties": {
    "tgn:hierarchy":[
        "tgn:2534770",
        "tgn:1000001",
        "tgn:7012149",
        "tgn:1002545",
        "tgn:7007157",
        "tgn:7029392"
    ],
    "tgn:id":2534770,
    "tgn:name":"Nagel Canyon",
    "tgn:placetype":[
        "aat:300008761"
    ]
},
  "bbox": [],
  "geometry": {"coordinates":[-118.3167,35.3667],"type":"Point"}
}