{
  "id": 1061335,
  "type": "Feature",
  "properties": {
    "tgn:hierarchy":[
        "tgn:1061335",
        "tgn:1000004",
        "tgn:7013361",
        "tgn:7018214",
        "tgn:7002435",
        "tgn:7029392"
    ],
    "tgn:id":1061335,
    "tgn:name":"Volonga",
    "tgn:placetype":[
        "aat:300008347"
    ]
},
  "bbox": [],
  "geometry": {"coordinates":[47.7333,67.0833],"type":"Point"}
}