{
  "id": 2263606,
  "type": "Feature",
  "properties": {
    "tgn:hierarchy":[
        "tgn:2263606",
        "tgn:1000001",
        "tgn:7012149",
        "tgn:2001722",
        "tgn:7007708",
        "tgn:7029392"
    ],
    "tgn:id":2263606,
    "tgn:name":"Coye Ditch",
    "tgn:placetype":[
        "aat:300006075"
    ]
},
  "bbox": [],
  "geometry": {"coordinates":[-117.2333,45.3333],"type":"Point"}
}