{
  "id": 7591371,
  "type": "Feature",
  "properties": {
    "tgn:hierarchy":[
        "tgn:7591371",
        "tgn:1000004",
        "tgn:7000198",
        "tgn:7000799",
        "tgn:7029392"
    ],
    "tgn:id":7591371,
    "tgn:name:en":"Phatw\u0101l",
    "tgn:placetype":[
        "aat:300008347"
    ]
},
  "bbox": [],
  "geometry": {"coordinates":[74.877967,32.60371],"type":"Point"}
}