{
  "id": 2786327,
  "type": "Feature",
  "properties": {
    "tgn:hierarchy":[
        "tgn:2786327",
        "tgn:1000001",
        "tgn:7012149",
        "tgn:7014589",
        "tgn:7007515",
        "tgn:7029392"
    ],
    "tgn:id":2786327,
    "tgn:name":"Youngs Point",
    "tgn:placetype":[
        "aat:300008850"
    ]
},
  "bbox": [],
  "geometry": {"coordinates":[-67.0833,44.8833],"type":"Point"}
}