{
  "id": 7415712,
  "type": "Feature",
  "properties": {
    "tgn:hierarchy":[
        "tgn:7415712",
        "tgn:1000001",
        "tgn:7005591",
        "tgn:7005560",
        "tgn:7029392"
    ],
    "tgn:id":7415712,
    "tgn:name:es":"Santa Isabel de la Reforma",
    "tgn:placetype":[
        "aat:300008347"
    ]
},
  "bbox": [],
  "geometry": {"coordinates":[-95.953611,16.969444],"type":"Point"}
}