{
  "id": 2669069,
  "type": "Feature",
  "properties": {
    "tgn:hierarchy":[
        "tgn:2669069",
        "tgn:7002659",
        "tgn:1000001",
        "tgn:7012149",
        "tgn:2000039",
        "tgn:7029392"
    ],
    "tgn:id":2669069,
    "tgn:name":"Sledge Creek",
    "tgn:placetype":[
        "aat:300008706"
    ]
},
  "bbox": [],
  "geometry": {"coordinates":[-87.3333,34.4333],"type":"Point"}
}