{
  "id": 2195893,
  "type": "Feature",
  "properties": {
    "tgn:hierarchy":[
        "tgn:2195893",
        "tgn:1000001",
        "tgn:7012149",
        "tgn:2000836",
        "tgn:7007255",
        "tgn:7029392"
    ],
    "tgn:id":2195893,
    "tgn:name":"Broadtree Branch",
    "tgn:placetype":[
        "aat:300008699"
    ]
},
  "bbox": [],
  "geometry": {"coordinates":[-83.2833,37.3833],"type":"Point"}
}