{
  "id": 2568336,
  "type": "Feature",
  "properties": {
    "tgn:hierarchy":[
        "tgn:2568336",
        "tgn:1000001",
        "tgn:7012149",
        "tgn:2000218",
        "tgn:7007158",
        "tgn:7029392"
    ],
    "tgn:id":2568336,
    "tgn:name":"Park Creek",
    "tgn:placetype":[
        "aat:300008706"
    ]
},
  "bbox": [],
  "geometry": {"coordinates":[-107.25,38.0333],"type":"Point"}
}