<<<<<<< HEAD
{
  "id": 2409285,
  "type": "Feature",
  "properties": {
    "tgn:hierarchy":[
        "tgn:2409285",
        "tgn:1000001",
        "tgn:7012149",
        "tgn:1002789",
        "tgn:7007710",
        "tgn:7029392"
    ],
    "tgn:id":2409285,
    "tgn:name":"Icks Pond",
    "tgn:placetype":[
        "aat:300006191"
    ]
},
  "bbox": [],
  "geometry": {"coordinates":[-75.2,41.2667],"type":"Point"}
}
=======
{"geometry":{"type":"Point","coordinates":[-75.200000,41.266700]},"type":"Feature","properties":{"hierarchy":["tgn:2409285","tgn:1000001","tgn:7012149","tgn:1002789","tgn:7007710","tgn:7029392"],"placetype":["aat:300006191"],"id":2409285,"name:xx":"Icks Pond"}}
>>>>>>> 03f74aca74312dbeaf24d7e61306dd6a786dc3d0
