{
  "id": 7403708,
  "type": "Feature",
  "properties": {
    "tgn:hierarchy":[
        "tgn:7403708",
        "tgn:7005585",
        "tgn:1000001",
        "tgn:7005560",
        "tgn:7029392"
    ],
    "tgn:id":7403708,
    "tgn:name":"La Llave",
    "tgn:placetype":[
        "aat:300008347"
    ]
},
  "bbox": [],
  "geometry": {"coordinates":[-100.816667,17.35],"type":"Point"}
}