{
  "id": 2757371,
  "type": "Feature",
  "properties": {
    "tgn:hierarchy":[
        "tgn:2757371",
        "tgn:1000001",
        "tgn:2001705",
        "tgn:7012149",
        "tgn:7007708",
        "tgn:7029392"
    ],
    "tgn:id":2757371,
    "tgn:name":"West Basin Canyon",
    "tgn:placetype":[
        "aat:300008761"
    ]
},
  "bbox": [],
  "geometry": {"coordinates":[-120.95,43.7833],"type":"Point"}
}