{
  "id": 1043793,
  "type": "Feature",
  "properties": {
    "tgn:hierarchy":[
        "tgn:1043793",
        "tgn:1003506",
        "tgn:1000003",
        "tgn:7002993",
        "tgn:1000080",
        "tgn:7029392"
    ],
    "tgn:id":1043793,
    "tgn:name":"Campoformido",
    "tgn:placetype":[
        "aat:300008347",
        "aat:300008375"
    ]
},
  "bbox": [],
  "geometry": {"coordinates":[13.1625,46.020833],"type":"Point"}
}