{
  "id": 2466656,
  "type": "Feature",
  "properties": {
    "tgn:hierarchy":[
        "tgn:2466656",
        "tgn:1000001",
        "tgn:7012149",
        "tgn:2001614",
        "tgn:7007706",
        "tgn:7029392"
    ],
    "tgn:id":2466656,
    "tgn:name":"Long Branch",
    "tgn:placetype":[
        "aat:300008699"
    ]
},
  "bbox": [],
  "geometry": {"coordinates":[-82.6667,39.15],"type":"Point"}
}