{
  "id": 2028818,
  "type": "Feature",
  "properties": {
    "tgn:hierarchy":[
        "tgn:2028818",
        "tgn:1000001",
        "tgn:7012149",
        "tgn:1002524",
        "tgn:7007251",
        "tgn:7029392"
    ],
    "tgn:id":2028818,
    "tgn:name":"Lockhaven",
    "tgn:placetype":[
        "aat:300008347",
        "aat:300387210"
    ]
},
  "bbox": [],
  "geometry": {"coordinates":[-90.2833,38.9333],"type":"Point"}
}