{
  "id": 2095534,
  "type": "Feature",
  "properties": {
    "tgn:hierarchy":[
        "tgn:2095534",
        "tgn:1000001",
        "tgn:2001735",
        "tgn:7012149",
        "tgn:7007712",
        "tgn:7029392"
    ],
    "tgn:id":2095534,
    "tgn:name":"Cherokee Falls",
    "tgn:placetype":[
        "aat:300008347"
    ]
},
  "bbox": [],
  "geometry": {"coordinates":[-81.5333,35.05],"type":"Point"}
}