{
  "id": 2588661,
  "type": "Feature",
  "properties": {
    "tgn:hierarchy":[
        "tgn:2588661",
        "tgn:1000001",
        "tgn:1002213",
        "tgn:7012149",
        "tgn:7007710",
        "tgn:7029392"
    ],
    "tgn:id":2588661,
    "tgn:name":"Plumstead Hill",
    "tgn:placetype":[
        "aat:300008798"
    ]
},
  "bbox": [],
  "geometry": {"coordinates":[-75.0833,40.3667],"type":"Point"}
}