<<<<<<< HEAD
{
  "id": 2154198,
  "type": "Feature",
  "properties": {
    "tgn:hierarchy":[
        "tgn:2154198",
        "tgn:1000001",
        "tgn:7012149",
        "tgn:2001164",
        "tgn:7007522",
        "tgn:7029392"
    ],
    "tgn:id":2154198,
    "tgn:name":"Bear Creek",
    "tgn:placetype":[
        "aat:300008706"
    ]
},
  "bbox": [],
  "geometry": {"coordinates":[-91.4,31.1667],"type":"Point"}
}
=======
{"geometry":{"type":"Point","coordinates":[-91.400000,31.166700]},"type":"Feature","properties":{"hierarchy":["tgn:2154198","tgn:1000001","tgn:7012149","tgn:2001164","tgn:7007522","tgn:7029392"],"placetype":["aat:300008706"],"id":2154198,"name:xx":"Bear Creek"}}
>>>>>>> 03f74aca74312dbeaf24d7e61306dd6a786dc3d0
