{
  "id": 2075211,
  "type": "Feature",
  "properties": {
    "tgn:hierarchy":[
        "tgn:2075211",
        "tgn:1000001",
        "tgn:7012149",
        "tgn:2001546",
        "tgn:7007709",
        "tgn:7029392"
    ],
    "tgn:id":2075211,
    "tgn:name":"Indian Trail",
    "tgn:placetype":[
        "aat:300008347"
    ]
},
  "bbox": [],
  "geometry": {"coordinates":[-80.6667,35.0667],"type":"Point"}
}