{
  "id": 7458326,
  "type": "Feature",
  "properties": {
    "tgn:hierarchy":[
        "tgn:7458326",
        "tgn:7002444",
        "tgn:1000003",
        "tgn:7008082",
        "tgn:7008591",
        "tgn:7029392"
    ],
    "tgn:id":7458326,
    "tgn:name:en":"Newton Point",
    "tgn:placetype":[
        "aat:300386846"
    ]
},
  "bbox": [],
  "geometry": {"coordinates":[-4.166667,57.85],"type":"Point"}
}