{
  "id": 2155724,
  "type": "Feature",
  "properties": {
    "tgn:hierarchy":[
        "tgn:2155724",
        "tgn:1000001",
        "tgn:1002601",
        "tgn:7012149",
        "tgn:7007159",
        "tgn:7029392"
    ],
    "tgn:id":2155724,
    "tgn:name":"Bear Swamp",
    "tgn:placetype":[
        "aat:300008905"
    ]
},
  "bbox": [],
  "geometry": {"coordinates":[-73.3167,41.7833],"type":"Point"}
}