{
  "id": 1088541,
  "type": "Feature",
  "properties": {
    "tgn:hierarchy":[
        "tgn:1088541",
        "tgn:7001242",
        "tgn:1000970",
        "tgn:1000156",
        "tgn:7029392"
    ],
    "tgn:id":1088541,
    "tgn:name":"Mass\u00e9nya",
    "tgn:placetype":[
        "aat:300008347"
    ]
},
  "bbox": [],
  "geometry": {"coordinates":[16.15,11.35],"type":"Point"}
}