{
  "id": 7188429,
  "type": "Feature",
  "properties": {
    "tgn:hierarchy":[
        "tgn:7188429",
        "tgn:1000003",
        "tgn:7003677",
        "tgn:7000084",
        "tgn:7029392"
    ],
    "tgn:id":7188429,
    "tgn:name":"Eissingort",
    "tgn:placetype":[
        "aat:300387200"
    ]
},
  "bbox": [],
  "geometry": {"coordinates":[7.166667,52.05],"type":"Point"}
}