<<<<<<< HEAD
{
  "id": 2336520,
  "type": "Feature",
  "properties": {
    "tgn:hierarchy":[
        "tgn:2336520",
        "tgn:1000001",
        "tgn:7006451",
        "tgn:2000093",
        "tgn:7012149",
        "tgn:7029392"
    ],
    "tgn:id":2336520,
    "tgn:name":"Four Diamond Tank",
    "tgn:placetype":[
        "aat:300006191"
    ]
},
  "bbox": [],
  "geometry": {"coordinates":[-110.1333,33.7167],"type":"Point"}
}
=======
{"geometry":{"type":"Point","coordinates":[-110.133300,33.716700]},"type":"Feature","properties":{"hierarchy":["tgn:2336520","tgn:1000001","tgn:7006451","tgn:2000093","tgn:7012149","tgn:7029392"],"placetype":["aat:300006191"],"id":2336520,"name:xx":"Four Diamond Tank"}}
>>>>>>> 03f74aca74312dbeaf24d7e61306dd6a786dc3d0
