{
  "id": 7080788,
  "type": "Feature",
  "properties": {
    "tgn:hierarchy":[
        "tgn:7080788",
        "tgn:7000096",
        "tgn:1000003",
        "tgn:7000084",
        "tgn:7029392"
    ],
    "tgn:id":7080788,
    "tgn:name":"W\u00f6hrdenswiesen",
    "tgn:placetype":[
        "aat:300386990"
    ]
},
  "bbox": [],
  "geometry": {"coordinates":[12.733333,52.35],"type":"Point"}
}