{
  "id": 1136194,
  "type": "Feature",
  "properties": {
    "tgn:hierarchy":[
        "tgn:1136194",
        "tgn:1000001",
        "tgn:7012149",
        "tgn:1002607",
        "tgn:7007706",
        "tgn:7029392"
    ],
    "tgn:id":1136194,
    "tgn:name":"Powdermaker Ditch",
    "tgn:placetype":[
        "aat:300006178"
    ]
},
  "bbox": [],
  "geometry": {"coordinates":[-82.0333,41.4833],"type":"Point"}
}