{
  "id": 7526615,
  "type": "Feature",
  "properties": {
    "tgn:hierarchy":[
        "tgn:7526615",
        "tgn:7001242",
        "tgn:7016833",
        "tgn:1001091",
        "tgn:7029392"
    ],
    "tgn:id":7526615,
    "tgn:name":"Madrasat \u0162aha \u1e28usayn",
    "tgn:placetype":[
        "aat:300006495"
    ]
},
  "bbox": [],
  "geometry": {"coordinates":[31.308985,30.123692],"type":"Point"}
}