{
  "id": 2559257,
  "type": "Feature",
  "properties": {
    "tgn:hierarchy":[
        "tgn:2559257",
        "tgn:1000001",
        "tgn:1002260",
        "tgn:7012149",
        "tgn:7007920",
        "tgn:7029392"
    ],
    "tgn:id":2559257,
    "tgn:name":"Onemile Creek",
    "tgn:placetype":[
        "aat:300008706"
    ]
},
  "bbox": [],
  "geometry": {"coordinates":[-120.6833,48.2833],"type":"Point"}
}