{
  "id": 2566197,
  "type": "Feature",
  "properties": {
    "tgn:hierarchy":[
        "tgn:2566197",
        "tgn:1000001",
        "tgn:7012149",
        "tgn:2000234",
        "tgn:7007158",
        "tgn:7029392"
    ],
    "tgn:id":2566197,
    "tgn:name":"Palmers Lake",
    "tgn:placetype":[
        "aat:300006191"
    ]
},
  "bbox": [],
  "geometry": {"coordinates":[-108.2667,38.15],"type":"Point"}
}