{
  "id": 2671859,
  "type": "Feature",
  "properties": {
    "tgn:hierarchy":[
        "tgn:2671859",
        "tgn:2000106",
        "tgn:1000001",
        "tgn:7016172",
        "tgn:7012149",
        "tgn:7029392"
    ],
    "tgn:id":2671859,
    "tgn:name":"Smith Prairie",
    "tgn:placetype":[
        "aat:300055621"
    ]
},
  "bbox": [],
  "geometry": {"coordinates":[-91.8667,33.1667],"type":"Point"}
}