<<<<<<< HEAD
{
  "id": 7475578,
  "type": "Feature",
  "properties": {
    "tgn:hierarchy":[
        "tgn:7475578",
        "tgn:1000004",
        "tgn:7489179",
        "tgn:1000141",
        "tgn:7029392"
    ],
    "tgn:id":7475578,
    "tgn:name":"Dongnanxing",
    "tgn:placetype":[
        "aat:300008347"
    ]
},
  "bbox": [],
  "geometry": {"coordinates":[121.80133,24.728312],"type":"Point"}
}
=======
{"geometry":{"type":"Point","coordinates":[121.801330,24.728312]},"type":"Feature","properties":{"hierarchy":["tgn:7475578","tgn:1000004","tgn:7489179","tgn:1000141","tgn:7029392"],"placetype":["aat:300008347"],"id":7475578,"name:xx":"Dongnanxing"}}
>>>>>>> 03f74aca74312dbeaf24d7e61306dd6a786dc3d0
