{
  "id": 7186437,
  "type": "Feature",
  "properties": {
    "tgn:hierarchy":[
        "tgn:7186437",
        "tgn:1000003",
        "tgn:7003689",
        "tgn:7000084",
        "tgn:7029392"
    ],
    "tgn:id":7186437,
    "tgn:name":"Grabsleben",
    "tgn:placetype":[
        "aat:300008347"
    ]
},
  "bbox": [],
  "geometry": {"coordinates":[10.833333,50.933333],"type":"Point"}
}