{
  "id": 7354672,
  "type": "Feature",
  "properties": {
    "tgn:hierarchy":[
        "tgn:7354672",
        "tgn:1000001",
        "tgn:7005595",
        "tgn:7005560",
        "tgn:7029392"
    ],
    "tgn:id":7354672,
    "tgn:name":"Castillo",
    "tgn:placetype":[
        "aat:300008347"
    ]
},
  "bbox": [],
  "geometry": {"coordinates":[-106.65,24.116667],"type":"Point"}
}