<<<<<<< HEAD
{
  "id": 7354672,
  "type": "Feature",
  "properties": {
    "tgn:hierarchy":[
        "tgn:7354672",
        "tgn:1000001",
        "tgn:7005595",
        "tgn:7005560",
        "tgn:7029392"
    ],
    "tgn:id":7354672,
    "tgn:name":"Castillo",
    "tgn:placetype":[
        "aat:300008347"
    ]
},
  "bbox": [],
  "geometry": {"coordinates":[-106.65,24.116667],"type":"Point"}
}
=======
{"geometry":{"type":"Point","coordinates":[-106.650000,24.116667]},"type":"Feature","properties":{"hierarchy":["tgn:7354672","tgn:1000001","tgn:7005595","tgn:7005560","tgn:7029392"],"placetype":["aat:300008347"],"id":7354672,"name:xx":"Castillo"}}
>>>>>>> 03f74aca74312dbeaf24d7e61306dd6a786dc3d0
