{
  "id": 1042589,
  "type": "Feature",
  "properties": {
    "tgn:hierarchy":[
        "tgn:1042589",
        "tgn:7001199",
        "tgn:7003495",
        "tgn:1000003",
        "tgn:1000078",
        "tgn:7029392"
    ],
    "tgn:id":1042589,
    "tgn:name":"Aughrim",
    "tgn:placetype":[
        "aat:300008347"
    ]
},
  "bbox": [],
  "geometry": {"coordinates":[-6.3333,52.8667],"type":"Point"}
}