{
  "id": 7312151,
  "type": "Feature",
  "properties": {
    "tgn:hierarchy":[
        "tgn:7312151",
        "tgn:1001695",
        "tgn:1000049",
        "tgn:1000002",
        "tgn:7029392"
    ],
    "tgn:id":7312151,
    "tgn:name":"Las Cardas, Portezuelo",
    "tgn:placetype":[
        "aat:300259572"
    ]
},
  "bbox": [],
  "geometry": {"coordinates":[-71.683333,-34.55],"type":"Point"}
}