{
  "id": 1078208,
  "type": "Feature",
  "properties": {
    "tgn:hierarchy":[
        "tgn:1078208",
        "tgn:1000004",
        "tgn:1001336",
        "tgn:1000116",
        "tgn:7029392"
    ],
    "tgn:id":1078208,
    "tgn:name":"Nangakelawit",
    "tgn:placetype":[
        "aat:300008347"
    ]
},
  "bbox": [],
  "geometry": {"coordinates":[112.4333,0.3833],"type":"Point"}
}