{
  "id": 7300899,
  "type": "Feature",
  "properties": {
    "tgn:hierarchy":[
        "tgn:7300899",
        "tgn:7002844",
        "tgn:7030216",
        "tgn:1000003",
        "tgn:1000095",
        "tgn:7029392"
    ],
    "tgn:id":7300899,
    "tgn:name":"Mora de Ebro",
    "tgn:placetype":[
        "aat:300008347"
    ]
},
  "bbox": [],
  "geometry": {"coordinates":[0.633333,41.083333],"type":"Point"}
}