{
  "id": 2626944,
  "type": "Feature",
  "properties": {
    "tgn:hierarchy":[
        "tgn:2626944",
        "tgn:1000001",
        "tgn:7012149",
        "tgn:1003047",
        "tgn:7007710",
        "tgn:7029392"
    ],
    "tgn:id":2626944,
    "tgn:name":"Rocky Ridge",
    "tgn:placetype":[
        "aat:300266640"
    ]
},
  "bbox": [],
  "geometry": {"coordinates":[-76.75,39.75],"type":"Point"}
}