<<<<<<< HEAD
{
  "id": 7178746,
  "type": "Feature",
  "properties": {
    "tgn:hierarchy":[
        "tgn:7178746",
        "tgn:7003669",
        "tgn:1000003",
        "tgn:7000084",
        "tgn:7029392"
    ],
    "tgn:id":7178746,
    "tgn:name":"Haidhof",
    "tgn:placetype":[
        "aat:300000206"
    ]
},
  "bbox": [],
  "geometry": {"coordinates":[12.9,48.816667],"type":"Point"}
}
=======
{"geometry":{"type":"Point","coordinates":[12.900000,48.816667]},"type":"Feature","properties":{"hierarchy":["tgn:7178746","tgn:7003669","tgn:1000003","tgn:7000084","tgn:7029392"],"placetype":["aat:300000206"],"id":7178746,"name:xx":"Haidhof"}}
>>>>>>> 03f74aca74312dbeaf24d7e61306dd6a786dc3d0
