{
  "id": 7439622,
  "type": "Feature",
  "properties": {
    "tgn:hierarchy":[
        "tgn:7439622",
        "tgn:1000001",
        "tgn:1001906",
        "tgn:7005560",
        "tgn:7029392"
    ],
    "tgn:id":7439622,
    "tgn:name":"Santa Cruz",
    "tgn:placetype":[
        "aat:300008347"
    ]
},
  "bbox": [],
  "geometry": {"coordinates":[-105.216667,21.433333],"type":"Point"}
}