{
  "id": 7001072,
  "type": "Feature",
  "properties": {
    "tgn:hierarchy":[
        "tgn:7001072",
        "tgn:7001242",
        "tgn:1002089",
        "tgn:1000205",
        "tgn:7029392"
    ],
    "tgn:id":7001072,
    "tgn:name":"Kasserine",
    "tgn:placetype":[
        "aat:300008347",
        "aat:300387220",
        "aat:300008375"
    ]
},
  "bbox": [],
  "geometry": {"coordinates":[8.7167,35.2167],"type":"Point"}
}