{
  "id": 2236782,
  "type": "Feature",
  "properties": {
    "tgn:hierarchy":[
        "tgn:2236782",
        "tgn:1000001",
        "tgn:7012149",
        "tgn:2002376",
        "tgn:7007923",
        "tgn:7029392"
    ],
    "tgn:id":2236782,
    "tgn:name":"Child Creek",
    "tgn:placetype":[
        "aat:300008706"
    ]
},
  "bbox": [],
  "geometry": {"coordinates":[-111.0333,42.6833],"type":"Point"}
}