{
  "id": 2530486,
  "type": "Feature",
  "properties": {
    "tgn:hierarchy":[
        "tgn:2530486",
        "tgn:1000001",
        "tgn:7012149",
        "tgn:2000181",
        "tgn:7007157",
        "tgn:7029392"
    ],
    "tgn:id":2530486,
    "tgn:name":"Muddy Creek",
    "tgn:placetype":[
        "aat:300008706"
    ]
},
  "bbox": [],
  "geometry": {"coordinates":[-123.7167,40.4833],"type":"Point"}
}