{
  "id": 2227485,
  "type": "Feature",
  "properties": {
    "tgn:hierarchy":[
        "tgn:2227485",
        "tgn:1000001",
        "tgn:7012149",
        "tgn:2001868",
        "tgn:7007825",
        "tgn:7029392"
    ],
    "tgn:id":2227485,
    "tgn:name":"Cave Spring Valley",
    "tgn:placetype":[
        "aat:300008761"
    ]
},
  "bbox": [],
  "geometry": {"coordinates":[-83.3333,36.25],"type":"Point"}
}