{
  "id": 1104305,
  "type": "Feature",
  "properties": {
    "tgn:hierarchy":[
        "tgn:1104305",
        "tgn:7000490",
        "tgn:1000006",
        "tgn:7001828",
        "tgn:7029392"
    ],
    "tgn:id":1104305,
    "tgn:name":"Coolumburra Hill",
    "tgn:placetype":[
        "aat:300008795"
    ]
},
  "bbox": [],
  "geometry": {"coordinates":[150.1667,-35.0167],"type":"Point"}
}