{
  "id": 2184693,
  "type": "Feature",
  "properties": {
    "tgn:hierarchy":[
        "tgn:2184693",
        "tgn:2001628",
        "tgn:1000001",
        "tgn:7012149",
        "tgn:7007707",
        "tgn:7029392"
    ],
    "tgn:id":2184693,
    "tgn:name":"Boecher Lake",
    "tgn:placetype":[
        "aat:300006191"
    ]
},
  "bbox": [],
  "geometry": {"coordinates":[-98.4167,35.9333],"type":"Point"}
}