{
  "id": 2367081,
  "type": "Feature",
  "properties": {
    "tgn:hierarchy":[
        "tgn:2367081",
        "tgn:1000001",
        "tgn:7012149",
        "tgn:7007157",
        "tgn:2000187",
        "tgn:7029392"
    ],
    "tgn:id":2367081,
    "tgn:name":"Grizzly Ridge",
    "tgn:placetype":[
        "aat:300266640"
    ]
},
  "bbox": [],
  "geometry": {"coordinates":[-120.6833,39.9167],"type":"Point"}
}