{
  "id": 7456907,
  "type": "Feature",
  "properties": {
    "tgn:hierarchy":[
        "tgn:7456907",
        "tgn:7002444",
        "tgn:1000003",
        "tgn:7008082",
        "tgn:7008591",
        "tgn:7029392"
    ],
    "tgn:id":7456907,
    "tgn:name:en":"Nun Bank",
    "tgn:placetype":[
        "aat:300386970"
    ]
},
  "bbox": [],
  "geometry": {"coordinates":[-4.916667,58.916667],"type":"Point"}
}