{
  "id": 2127918,
  "type": "Feature",
  "properties": {
    "tgn:hierarchy":[
        "tgn:2127918",
        "tgn:1000001",
        "tgn:7012149",
        "tgn:2001884",
        "tgn:7007825",
        "tgn:7029392"
    ],
    "tgn:id":2127918,
    "tgn:name":"Alaska Light Bar",
    "tgn:placetype":[
        "aat:300132348"
    ]
},
  "bbox": [],
  "geometry": {"coordinates":[-89.55,36.3333],"type":"Point"}
}