{
  "id": 7522597,
  "type": "Feature",
  "properties": {
    "tgn:hierarchy":[
        "tgn:7522597",
        "tgn:7001242",
        "tgn:7016833",
        "tgn:1001335",
        "tgn:7029392"
    ],
    "tgn:id":7522597,
    "tgn:name:en":"Dhahab, Jaz\u012brat adh",
    "tgn:placetype":[
        "aat:300008791"
    ]
},
  "bbox": [],
  "geometry": {"coordinates":[30.553333,31.205833],"type":"Point"}
}