{
  "id": 2646427,
  "type": "Feature",
  "properties": {
    "tgn:hierarchy":[
        "tgn:2646427",
        "tgn:1000001",
        "tgn:7012149",
        "tgn:7018871",
        "tgn:7007920",
        "tgn:7029392"
    ],
    "tgn:id":2646427,
    "tgn:name":"Sawyer, Mount",
    "tgn:placetype":[
        "aat:300008798"
    ]
},
  "bbox": [],
  "geometry": {"coordinates":[-121.2167,47.6667],"type":"Point"}
}