{
  "id": 7144814,
  "type": "Feature",
  "properties": {
    "tgn:hierarchy":[
        "tgn:7144814",
        "tgn:7000096",
        "tgn:1000003",
        "tgn:7000084",
        "tgn:7029392"
    ],
    "tgn:id":7144814,
    "tgn:name":"Kolonie Vorheide",
    "tgn:placetype":[
        "aat:300008347"
    ]
},
  "bbox": [],
  "geometry": {"coordinates":[14.233333,52.166667],"type":"Point"}
}