{
  "id": 2515409,
  "type": "Feature",
  "properties": {
    "tgn:hierarchy":[
        "tgn:2515409",
        "tgn:1000001",
        "tgn:7012149",
        "tgn:2000346",
        "tgn:7007248",
        "tgn:7029392"
    ],
    "tgn:id":2515409,
    "tgn:name":"Millpond Ridge",
    "tgn:placetype":[
        "aat:300266640"
    ]
},
  "bbox": [],
  "geometry": {"coordinates":[-84.2167,34.9667],"type":"Point"}
}