{
  "id": 7142612,
  "type": "Feature",
  "properties": {
    "tgn:hierarchy":[
        "tgn:7142612",
        "tgn:7000096",
        "tgn:1000003",
        "tgn:7000084",
        "tgn:7029392"
    ],
    "tgn:id":7142612,
    "tgn:name":"Lindenhof",
    "tgn:placetype":[
        "aat:300000206"
    ]
},
  "bbox": [],
  "geometry": {"coordinates":[13.216667,53.033333],"type":"Point"}
}