{
  "id": 2756493,
  "type": "Feature",
  "properties": {
    "tgn:hierarchy":[
        "tgn:2756493",
        "tgn:1000001",
        "tgn:2002241",
        "tgn:7012149",
        "tgn:7007920",
        "tgn:7029392"
    ],
    "tgn:id":2756493,
    "tgn:name":"Weller Butte",
    "tgn:placetype":[
        "aat:300008798"
    ]
},
  "bbox": [],
  "geometry": {"coordinates":[-117.6667,46.0333],"type":"Point"}
}