{
  "id": 2416729,
  "type": "Feature",
  "properties": {
    "tgn:hierarchy":[
        "tgn:2416729",
        "tgn:1000001",
        "tgn:2001941",
        "tgn:7012149",
        "tgn:7007826",
        "tgn:7029392"
    ],
    "tgn:id":2416729,
    "tgn:name":"Jack Mountain",
    "tgn:placetype":[
        "aat:300008798"
    ]
},
  "bbox": [],
  "geometry": {"coordinates":[-98.7833,29.6833],"type":"Point"}
}