{
  "id": 7174328,
  "type": "Feature",
  "properties": {
    "tgn:hierarchy":[
        "tgn:7174328",
        "tgn:1000003",
        "tgn:7000094",
        "tgn:7000084",
        "tgn:7029392"
    ],
    "tgn:id":7174328,
    "tgn:name":"Gro\u00dfes Kl\u00fctz-Hoved",
    "tgn:placetype":[
        "aat:300387499"
    ]
},
  "bbox": [],
  "geometry": {"coordinates":[11.183333,54.016667],"type":"Point"}
}