{
  "id": 2412184,
  "type": "Feature",
  "properties": {
    "tgn:hierarchy":[
        "tgn:2412184",
        "tgn:1000001",
        "tgn:7012149",
        "tgn:1002545",
        "tgn:7007157",
        "tgn:7029392"
    ],
    "tgn:id":2412184,
    "tgn:name":"Indian Spring",
    "tgn:placetype":[
        "aat:300008697"
    ]
},
  "bbox": [],
  "geometry": {"coordinates":[-120.15,35.6833],"type":"Point"}
}