{
  "id": 7310094,
  "type": "Feature",
  "properties": {
    "tgn:hierarchy":[
        "tgn:7310094",
        "tgn:1001708",
        "tgn:1000049",
        "tgn:1000002",
        "tgn:7029392"
    ],
    "tgn:id":7310094,
    "tgn:name":"Ortiga, Quebrada",
    "tgn:placetype":[
        "aat:300008699"
    ]
},
  "bbox": [],
  "geometry": {"coordinates":[-70.433333,-33.25],"type":"Point"}
}