{
  "id": 7363777,
  "type": "Feature",
  "properties": {
    "tgn:hierarchy":[
        "tgn:7363777",
        "tgn:1000001",
        "tgn:7005597",
        "tgn:7005560",
        "tgn:7029392"
    ],
    "tgn:id":7363777,
    "tgn:name":"El Moquetito",
    "tgn:placetype":[
        "aat:300008347"
    ]
},
  "bbox": [],
  "geometry": {"coordinates":[-97.766667,25.483333],"type":"Point"}
}