{
  "id": 2346622,
  "type": "Feature",
  "properties": {
    "tgn:hierarchy":[
        "tgn:2346622",
        "tgn:1000001",
        "tgn:7012149",
        "tgn:2002371",
        "tgn:7007923",
        "tgn:7029392"
    ],
    "tgn:id":2346622,
    "tgn:name":"Gaylord Lake",
    "tgn:placetype":[
        "aat:300008680"
    ]
},
  "bbox": [],
  "geometry": {"coordinates":[-109.1667,42.8667],"type":"Point"}
}