{
  "id": 1020653,
  "type": "Feature",
  "properties": {
    "tgn:hierarchy":[
        "tgn:1020653",
        "tgn:7006064",
        "tgn:1000047",
        "tgn:7002455",
        "tgn:1000002",
        "tgn:7029392"
    ],
    "tgn:id":1020653,
    "tgn:name":"Aracati",
    "tgn:placetype":[
        "aat:300008347"
    ]
},
  "bbox": [],
  "geometry": {"coordinates":[-37.75,-4.5333],"type":"Point"}
}