{
  "id": 7486406,
  "type": "Feature",
  "properties": {
    "tgn:hierarchy":[
        "tgn:7486406",
        "tgn:1000004",
        "tgn:7001014",
        "tgn:1000141",
        "tgn:7029392"
    ],
    "tgn:id":7486406,
    "tgn:name":"Xinhua",
    "tgn:placetype":[
        "aat:300008347"
    ]
},
  "bbox": [],
  "geometry": {"coordinates":[120.577477,23.779947],"type":"Point"}
}