{
  "id": 7297997,
  "type": "Feature",
  "properties": {
    "tgn:hierarchy":[
        "tgn:7297997",
        "tgn:7001122",
        "tgn:1000003",
        "tgn:7002765",
        "tgn:1000095",
        "tgn:7029392"
    ],
    "tgn:id":7297997,
    "tgn:name":"Serra, Punta den",
    "tgn:placetype":[
        "aat:300386846"
    ]
},
  "bbox": [],
  "geometry": {"coordinates":[1.516667,39.116667],"type":"Point"}
}