{
  "id": 2218979,
  "type": "Feature",
  "properties": {
    "tgn:hierarchy":[
        "tgn:2218979",
        "tgn:1000001",
        "tgn:7016172",
        "tgn:2000113",
        "tgn:7012149",
        "tgn:7029392"
    ],
    "tgn:id":2218979,
    "tgn:name":"Caney Canal",
    "tgn:placetype":[
        "aat:300006075"
    ]
},
  "bbox": [],
  "geometry": {"coordinates":[-91.3667,33.0167],"type":"Point"}
}