{
  "id": 2438911,
  "type": "Feature",
  "properties": {
    "tgn:hierarchy":[
        "tgn:2438911",
        "tgn:1000001",
        "tgn:7006451",
        "tgn:7012149",
        "tgn:2000100",
        "tgn:7029392"
    ],
    "tgn:id":2438911,
    "tgn:name":"Kinnison Wash",
    "tgn:placetype":[
        "aat:300008701"
    ]
},
  "bbox": [],
  "geometry": {"coordinates":[-110.8167,32.1167],"type":"Point"}
}