{
  "id": 2338989,
  "type": "Feature",
  "properties": {
    "tgn:hierarchy":[
        "tgn:2338989",
        "tgn:1000001",
        "tgn:7012149",
        "tgn:2001308",
        "tgn:7007524",
        "tgn:7029392"
    ],
    "tgn:id":2338989,
    "tgn:name":"Franklin Hills",
    "tgn:placetype":[
        "aat:300386831"
    ]
},
  "bbox": [],
  "geometry": {"coordinates":[-109.8833,46.05],"type":"Point"}
}