{
  "id": 7485125,
  "type": "Feature",
  "properties": {
    "tgn:hierarchy":[
        "tgn:7485125",
        "tgn:1000004",
        "tgn:7467799",
        "tgn:1000141",
        "tgn:7029392"
    ],
    "tgn:id":7485125,
    "tgn:name":"Zhanghua Binhai Gongyequ",
    "tgn:placetype":[
        "aat:300387302"
    ]
},
  "bbox": [],
  "geometry": {"coordinates":[120.39,24.070556],"type":"Point"}
}