<<<<<<< HEAD
{
  "id": 7485125,
  "type": "Feature",
  "properties": {
    "tgn:hierarchy":[
        "tgn:7485125",
        "tgn:1000004",
        "tgn:7467799",
        "tgn:1000141",
        "tgn:7029392"
    ],
    "tgn:id":7485125,
    "tgn:name":"Zhanghua Binhai Gongyequ",
    "tgn:placetype":[
        "aat:300387302"
    ]
},
  "bbox": [],
  "geometry": {"coordinates":[120.39,24.070556],"type":"Point"}
}
=======
{"geometry":{"type":"Point","coordinates":[120.390000,24.070556]},"type":"Feature","properties":{"hierarchy":["tgn:7485125","tgn:1000004","tgn:7467799","tgn:1000141","tgn:7029392"],"placetype":["aat:300387302"],"id":7485125,"name:xx":"Zhanghua Binhai Gongyequ"}}
>>>>>>> 03f74aca74312dbeaf24d7e61306dd6a786dc3d0
