{
  "id": 2452203,
  "type": "Feature",
  "properties": {
    "tgn:hierarchy":[
        "tgn:2452203",
        "tgn:1000001",
        "tgn:7012149",
        "tgn:7007157",
        "tgn:1002937",
        "tgn:7029392"
    ],
    "tgn:id":2452203,
    "tgn:name":"Little Blue Creek",
    "tgn:placetype":[
        "aat:300008706"
    ]
},
  "bbox": [],
  "geometry": {"coordinates":[-121.7167,39.15],"type":"Point"}
}