<<<<<<< HEAD
{
  "id": 2150696,
  "type": "Feature",
  "properties": {
    "tgn:hierarchy":[
        "tgn:2150696",
        "tgn:1000001",
        "tgn:7012149",
        "tgn:2001869",
        "tgn:7007825",
        "tgn:7029392"
    ],
    "tgn:id":2150696,
    "tgn:name":"Bass Bay Marina",
    "tgn:placetype":[
        "aat:300008678"
    ]
},
  "bbox": [],
  "geometry": {"coordinates":[-85.1167,35.2],"type":"Point"}
}
=======
{"geometry":{"type":"Point","coordinates":[-85.116700,35.200000]},"type":"Feature","properties":{"hierarchy":["tgn:2150696","tgn:1000001","tgn:7012149","tgn:2001869","tgn:7007825","tgn:7029392"],"placetype":["aat:300008678"],"id":2150696,"name:xx":"Bass Bay Marina"}}
>>>>>>> 03f74aca74312dbeaf24d7e61306dd6a786dc3d0
