{
  "id": 2335522,
  "type": "Feature",
  "properties": {
    "tgn:hierarchy":[
        "tgn:2335522",
        "tgn:1000001",
        "tgn:7012149",
        "tgn:2000891",
        "tgn:7007256",
        "tgn:7029392"
    ],
    "tgn:id":2335522,
    "tgn:name":"Fort Saint Phillip",
    "tgn:placetype":[
        "aat:300008347"
    ]
},
  "bbox": [],
  "geometry": {"coordinates":[-89.45,29.35],"type":"Point"}
}