{
  "id": 7165627,
  "type": "Feature",
  "properties": {
    "tgn:hierarchy":[
        "tgn:7165627",
        "tgn:1000003",
        "tgn:7003676",
        "tgn:7000084",
        "tgn:7029392"
    ],
    "tgn:id":7165627,
    "tgn:name":"Harkebr\u00fcgge",
    "tgn:placetype":[
        "aat:300008347"
    ]
},
  "bbox": [],
  "geometry": {"coordinates":[7.816667,53.116667],"type":"Point"}
}