{
  "id": 7109450,
  "type": "Feature",
  "properties": {
    "tgn:hierarchy":[
        "tgn:7109450",
        "tgn:7003669",
        "tgn:1000003",
        "tgn:7000084",
        "tgn:7029392"
    ],
    "tgn:id":7109450,
    "tgn:name":"Randersacker",
    "tgn:placetype":[
        "aat:300008347"
    ]
},
  "bbox": [],
  "geometry": {"coordinates":[9.9825,49.759444],"type":"Point"}
}