{
  "id": 2271460,
  "type": "Feature",
  "properties": {
    "tgn:hierarchy":[
        "tgn:2271460",
        "tgn:1000001",
        "tgn:7012149",
        "tgn:1002793",
        "tgn:7007240",
        "tgn:7029392"
    ],
    "tgn:id":2271460,
    "tgn:name":"Cumbee Drain",
    "tgn:placetype":[
        "aat:300008699"
    ]
},
  "bbox": [],
  "geometry": {"coordinates":[-81.9333,28.2833],"type":"Point"}
}