{
  "id": 2715292,
  "type": "Feature",
  "properties": {
    "tgn:hierarchy":[
        "tgn:2715292",
        "tgn:1000001",
        "tgn:7012149",
        "tgn:2001256",
        "tgn:7007523",
        "tgn:7029392"
    ],
    "tgn:id":2715292,
    "tgn:name":"Terell Branch",
    "tgn:placetype":[
        "aat:300008699"
    ]
},
  "bbox": [],
  "geometry": {"coordinates":[-92.9167,37.15],"type":"Point"}
}