{
  "id": 2093221,
  "type": "Feature",
  "properties": {
    "tgn:hierarchy":[
        "tgn:2093221",
        "tgn:1000001",
        "tgn:1002249",
        "tgn:7012149",
        "tgn:7007710",
        "tgn:7029392"
    ],
    "tgn:id":2093221,
    "tgn:name":"South Philipsburg",
    "tgn:placetype":[
        "aat:300008347"
    ]
},
  "bbox": [],
  "geometry": {"coordinates":[-78.2167,40.8833],"type":"Point"}
}