{
  "id": 2271154,
  "type": "Feature",
  "properties": {
    "tgn:hierarchy":[
        "tgn:2271154",
        "tgn:1000001",
        "tgn:7012149",
        "tgn:2001449",
        "tgn:7007566",
        "tgn:7029392"
    ],
    "tgn:id":2271154,
    "tgn:name":"Cuesta Colorada, Arroyo",
    "tgn:placetype":[
        "aat:300008699"
    ]
},
  "bbox": [],
  "geometry": {"coordinates":[-105.85,36.0333],"type":"Point"}
}