{
  "id": 7334746,
  "type": "Feature",
  "properties": {
    "tgn:hierarchy":[
        "tgn:7334746",
        "tgn:7002818",
        "tgn:1001647",
        "tgn:1000003",
        "tgn:1000095",
        "tgn:7029392"
    ],
    "tgn:id":7334746,
    "tgn:name":"El Pozuelo",
    "tgn:placetype":[
        "aat:300008347"
    ]
},
  "bbox": [],
  "geometry": {"coordinates":[-2.266667,40.616667],"type":"Point"}
}