{
  "id": 7589239,
  "type": "Feature",
  "properties": {
    "tgn:hierarchy":[
        "tgn:7589239",
        "tgn:1000004",
        "tgn:7000198",
        "tgn:1001977",
        "tgn:7029392"
    ],
    "tgn:id":7589239,
    "tgn:name:en":"Middle Ground",
    "tgn:placetype":[
        "aat:300387036"
    ]
},
  "bbox": [],
  "geometry": {"coordinates":[88.0925,21.380278],"type":"Point"}
}