{
  "id": 1016464,
  "type": "Feature",
  "properties": {
    "tgn:hierarchy":[
        "tgn:1016464",
        "tgn:7014980",
        "tgn:1000001",
        "tgn:7004641",
        "tgn:7029392"
    ],
    "tgn:id":1016464,
    "tgn:name":"Salisbury",
    "tgn:placetype":[
        "aat:300008347",
        "aat:300008372"
    ]
},
  "bbox": [],
  "geometry": {"coordinates":[-61.45,15.4333],"type":"Point"}
}