{
  "id": 2347620,
  "type": "Feature",
  "properties": {
    "tgn:hierarchy":[
        "tgn:2347620",
        "tgn:1000001",
        "tgn:2001418",
        "tgn:7012149",
        "tgn:7007526",
        "tgn:7029392"
    ],
    "tgn:id":2347620,
    "tgn:name":"Georges Canyon",
    "tgn:placetype":[
        "aat:300008761"
    ]
},
  "bbox": [],
  "geometry": {"coordinates":[-116.7667,38.35],"type":"Point"}
}