{
  "id": 7214634,
  "type": "Feature",
  "properties": {
    "tgn:hierarchy":[
        "tgn:7214634",
        "tgn:7003669",
        "tgn:1000003",
        "tgn:7000084",
        "tgn:7029392"
    ],
    "tgn:id":7214634,
    "tgn:name":"Birkenberg",
    "tgn:placetype":[
        "aat:300008777"
    ]
},
  "bbox": [],
  "geometry": {"coordinates":[10.083333,50.366667],"type":"Point"}
}