{
  "id": 2517386,
  "type": "Feature",
  "properties": {
    "tgn:hierarchy":[
        "tgn:2517386",
        "tgn:1000001",
        "tgn:7012149",
        "tgn:1002634",
        "tgn:7007523",
        "tgn:7029392"
    ],
    "tgn:id":2517386,
    "tgn:name":"Minnow Branch",
    "tgn:placetype":[
        "aat:300008699"
    ]
},
  "bbox": [],
  "geometry": {"coordinates":[-91.4333,39.7167],"type":"Point"}
}