<<<<<<< HEAD
{
  "id": 2331233,
  "type": "Feature",
  "properties": {
    "tgn:hierarchy":[
        "tgn:2331233",
        "tgn:1000001",
        "tgn:2002368",
        "tgn:7012149",
        "tgn:7007923",
        "tgn:7029392"
    ],
    "tgn:id":2331233,
    "tgn:name":"Flat Top Mountain",
    "tgn:placetype":[
        "aat:300008798"
    ]
},
  "bbox": [],
  "geometry": {"coordinates":[-107.8333,41.1833],"type":"Point"}
}
=======
{"geometry":{"type":"Point","coordinates":[-107.833300,41.183300]},"type":"Feature","properties":{"hierarchy":["tgn:2331233","tgn:1000001","tgn:2002368","tgn:7012149","tgn:7007923","tgn:7029392"],"placetype":["aat:300008798"],"id":2331233,"name:xx":"Flat Top Mountain"}}
>>>>>>> 03f74aca74312dbeaf24d7e61306dd6a786dc3d0
