{
  "id": 7501485,
  "type": "Feature",
  "properties": {
    "tgn:hierarchy":[
        "tgn:7501485",
        "tgn:1000004",
        "tgn:7490934",
        "tgn:1000141",
        "tgn:7029392"
    ],
    "tgn:id":7501485,
    "tgn:name":"Shazikeng",
    "tgn:placetype":[
        "aat:300008347"
    ]
},
  "bbox": [],
  "geometry": {"coordinates":[120.370556,22.915],"type":"Point"}
}