{
  "id": 1085610,
  "type": "Feature",
  "properties": {
    "tgn:hierarchy":[
        "tgn:1085610",
        "tgn:7005193",
        "tgn:1000004",
        "tgn:7000975",
        "tgn:1000142",
        "tgn:7029392"
    ],
    "tgn:id":1085610,
    "tgn:name":"Nong Bua Lamphu",
    "tgn:placetype":[
        "aat:300008347"
    ]
},
  "bbox": [],
  "geometry": {"coordinates":[102.4167,17.1833],"type":"Point"}
}