{
  "id": 7359167,
  "type": "Feature",
  "properties": {
    "tgn:hierarchy":[
        "tgn:7359167",
        "tgn:7005587",
        "tgn:1000001",
        "tgn:7005560",
        "tgn:7029392"
    ],
    "tgn:id":7359167,
    "tgn:name":"Cruz de la Mano",
    "tgn:placetype":[
        "aat:300008347"
    ]
},
  "bbox": [],
  "geometry": {"coordinates":[-98.516667,20.35],"type":"Point"}
}