{
  "id": 7567900,
  "type": "Feature",
  "properties": {
    "tgn:hierarchy":[
        "tgn:7567900",
        "tgn:1001828",
        "tgn:1000004",
        "tgn:7000198",
        "tgn:7029392"
    ],
    "tgn:id":7567900,
    "tgn:name:en":"Sult\u0101npur",
    "tgn:placetype":[
        "aat:300008347"
    ]
},
  "bbox": [],
  "geometry": {"coordinates":[78.088611,17.721389],"type":"Point"}
}