{
  "id": 2464014,
  "type": "Feature",
  "properties": {
    "tgn:hierarchy":[
        "tgn:2464014",
        "tgn:1000001",
        "tgn:2001429",
        "tgn:7012149",
        "tgn:7007566",
        "tgn:7029392"
    ],
    "tgn:id":2464014,
    "tgn:name":"Loco Tank",
    "tgn:placetype":[
        "aat:300006191"
    ]
},
  "bbox": [],
  "geometry": {"coordinates":[-108.8667,34.1667],"type":"Point"}
}