{
  "id": 2004920,
  "type": "Feature",
  "properties": {
    "tgn:hierarchy":[
        "tgn:2004920",
        "tgn:7002659",
        "tgn:1000001",
        "tgn:7012149",
        "tgn:2000029",
        "tgn:7029392"
    ],
    "tgn:id":2004920,
    "tgn:name":"Piney Bend",
    "tgn:placetype":[
        "aat:300008347",
        "aat:300387210"
    ]
},
  "bbox": [],
  "geometry": {"coordinates":[-87.9833,34.45],"type":"Point"}
}