{
  "id": 2231228,
  "type": "Feature",
  "properties": {
    "tgn:hierarchy":[
        "tgn:2231228",
        "tgn:7030516",
        "tgn:7006450",
        "tgn:1000001",
        "tgn:7012149",
        "tgn:7029392"
    ],
    "tgn:id":2231228,
    "tgn:name":"Chagulak Island",
    "tgn:placetype":[
        "aat:300008791"
    ]
},
  "bbox": [],
  "geometry": {"coordinates":[-171.1333,52.5667],"type":"Point"}
}