{
  "id": 2264241,
  "type": "Feature",
  "properties": {
    "tgn:hierarchy":[
        "tgn:2264241",
        "tgn:1000001",
        "tgn:2001339",
        "tgn:7012149",
        "tgn:7007525",
        "tgn:7029392"
    ],
    "tgn:id":2264241,
    "tgn:name":"Cozad Canal",
    "tgn:placetype":[
        "aat:300006075"
    ]
},
  "bbox": [],
  "geometry": {"coordinates":[-100.0167,40.9167],"type":"Point"}
}