{
  "id": 2032414,
  "type": "Feature",
  "properties": {
    "tgn:hierarchy":[
        "tgn:2032414",
        "tgn:1000001",
        "tgn:7012149",
        "tgn:2000545",
        "tgn:7007252",
        "tgn:7029392"
    ],
    "tgn:id":2032414,
    "tgn:name":"Johnstown",
    "tgn:placetype":[
        "aat:300008347"
    ]
},
  "bbox": [],
  "geometry": {"coordinates":[-87.3167,38.75],"type":"Point"}
}