{
  "id": 2542974,
  "type": "Feature",
  "properties": {
    "tgn:hierarchy":[
        "tgn:2542974",
        "tgn:1000001",
        "tgn:7012149",
        "tgn:7007157",
        "tgn:1002858",
        "tgn:7029392"
    ],
    "tgn:id":2542974,
    "tgn:name":"Nombre, Canyon",
    "tgn:placetype":[
        "aat:300008761"
    ]
},
  "bbox": [],
  "geometry": {"coordinates":[-116.15,32.8167],"type":"Point"}
}