{
  "id": 7442617,
  "type": "Feature",
  "properties": {
    "tgn:hierarchy":[
        "tgn:7442617",
        "tgn:7002445",
        "tgn:7008116",
        "tgn:1000003",
        "tgn:7008591",
        "tgn:7029392"
    ],
    "tgn:id":7442617,
    "tgn:name:en":"Outer Gulland",
    "tgn:placetype":[
        "aat:300011692"
    ]
},
  "bbox": [],
  "geometry": {"coordinates":[-5.025,50.591667],"type":"Point"}
}