{
  "id": 2243099,
  "type": "Feature",
  "properties": {
    "tgn:hierarchy":[
        "tgn:2243099",
        "tgn:1000001",
        "tgn:7012149",
        "tgn:1002517",
        "tgn:7007523",
        "tgn:7029392"
    ],
    "tgn:id":2243099,
    "tgn:name":"Clear Lake",
    "tgn:placetype":[
        "aat:300006191"
    ]
},
  "bbox": [],
  "geometry": {"coordinates":[-90.5333,38.05],"type":"Point"}
}