{
  "id": 2206115,
  "type": "Feature",
  "properties": {
    "tgn:hierarchy":[
        "tgn:2206115",
        "tgn:1000001",
        "tgn:7012149",
        "tgn:2002121",
        "tgn:7007827",
        "tgn:7029392"
    ],
    "tgn:id":2206115,
    "tgn:name":"Bull Spring",
    "tgn:placetype":[
        "aat:300008697"
    ]
},
  "bbox": [],
  "geometry": {"coordinates":[-111.7833,38.7333],"type":"Point"}
}