{
  "id": 7435776,
  "type": "Feature",
  "properties": {
    "tgn:hierarchy":[
        "tgn:7435776",
        "tgn:7005581",
        "tgn:1000001",
        "tgn:7005560",
        "tgn:7029392"
    ],
    "tgn:id":7435776,
    "tgn:name":"Zanja, Laguna de la",
    "tgn:placetype":[
        "aat:300008680"
    ]
},
  "bbox": [],
  "geometry": {"coordinates":[-105.916667,29.333333],"type":"Point"}
}