{
  "id": 2294869,
  "type": "Feature",
  "properties": {
    "tgn:hierarchy":[
        "tgn:2294869",
        "tgn:1000001",
        "tgn:7012149",
        "tgn:2002188",
        "tgn:7007919",
        "tgn:7029392"
    ],
    "tgn:id":2294869,
    "tgn:name":"Drake Branch",
    "tgn:placetype":[
        "aat:300008699"
    ]
},
  "bbox": [],
  "geometry": {"coordinates":[-82.3333,36.7667],"type":"Point"}
}