{
  "id": 7508306,
  "type": "Feature",
  "properties": {
    "tgn:hierarchy":[
        "tgn:7508306",
        "tgn:1008380",
        "tgn:7520093",
        "tgn:1000226",
        "tgn:1000006",
        "tgn:7029392"
    ],
    "tgn:id":7508306,
    "tgn:name:en":"Oroua River",
    "tgn:placetype":[
        "aat:300008699"
    ]
},
  "bbox": [],
  "geometry": {"coordinates":[175.433333,-40.433333],"type":"Point"}
}