<<<<<<< HEAD
{
  "id": 7360801,
  "type": "Feature",
  "properties": {
    "tgn:hierarchy":[
        "tgn:7360801",
        "tgn:1001853",
        "tgn:1000001",
        "tgn:7005560",
        "tgn:7029392"
    ],
    "tgn:id":7360801,
    "tgn:name":"Ejido Dos de Abril",
    "tgn:placetype":[
        "aat:300008347"
    ]
},
  "bbox": [],
  "geometry": {"coordinates":[-101.566667,25.35],"type":"Point"}
}
=======
{"geometry":{"type":"Point","coordinates":[-101.566667,25.350000]},"type":"Feature","properties":{"hierarchy":["tgn:7360801","tgn:1001853","tgn:1000001","tgn:7005560","tgn:7029392"],"placetype":["aat:300008347"],"id":7360801,"name:xx":"Ejido Dos de Abril"}}
>>>>>>> 03f74aca74312dbeaf24d7e61306dd6a786dc3d0
