{
  "id": 2237100,
  "type": "Feature",
  "properties": {
    "tgn:hierarchy":[
        "tgn:2237100",
        "tgn:2000454",
        "tgn:1000001",
        "tgn:7012149",
        "tgn:7007250",
        "tgn:7029392"
    ],
    "tgn:id":2237100,
    "tgn:name":"Chimney Creek",
    "tgn:placetype":[
        "aat:300008706"
    ]
},
  "bbox": [],
  "geometry": {"coordinates":[-112.45,42.7167],"type":"Point"}
}