{
  "id": 1102038,
  "type": "Feature",
  "properties": {
    "tgn:hierarchy":[
        "tgn:1102038",
        "tgn:1000001",
        "tgn:7012149",
        "tgn:7007157",
        "tgn:7014005",
        "tgn:7029392"
    ],
    "tgn:id":1102038,
    "tgn:name":"Golden Gate National Recreation Area",
    "tgn:placetype":[
        "aat:300000510"
    ]
},
  "bbox": [],
  "geometry": {"coordinates":[-122.5167,37.85],"type":"Point"}
}