{
  "id": 2542879,
  "type": "Feature",
  "properties": {
    "tgn:hierarchy":[
        "tgn:2542879",
        "tgn:1000001",
        "tgn:7012149",
        "tgn:2001879",
        "tgn:7007825",
        "tgn:7029392"
    ],
    "tgn:id":2542879,
    "tgn:name":"Nolan Hollow",
    "tgn:placetype":[
        "aat:300008761"
    ]
},
  "bbox": [],
  "geometry": {"coordinates":[-87.5667,36.0667],"type":"Point"}
}