<<<<<<< HEAD
{
  "id": 7373746,
  "type": "Feature",
  "properties": {
    "tgn:hierarchy":[
        "tgn:7373746",
        "tgn:1000001",
        "tgn:7005589",
        "tgn:7005560",
        "tgn:7029392"
    ],
    "tgn:id":7373746,
    "tgn:name":"La Graniza",
    "tgn:placetype":[
        "aat:300008347"
    ]
},
  "bbox": [],
  "geometry": {"coordinates":[-100.016667,26.8],"type":"Point"}
}
=======
{"geometry":{"type":"Point","coordinates":[-100.016667,26.800000]},"type":"Feature","properties":{"hierarchy":["tgn:7373746","tgn:1000001","tgn:7005589","tgn:7005560","tgn:7029392"],"placetype":["aat:300008347"],"id":7373746,"name:xx":"La Graniza"}}
>>>>>>> 03f74aca74312dbeaf24d7e61306dd6a786dc3d0
