{
  "id": 2545533,
  "type": "Feature",
  "properties": {
    "tgn:hierarchy":[
        "tgn:2545533",
        "tgn:1000001",
        "tgn:7012149",
        "tgn:7007706",
        "tgn:7029392"
    ],
    "tgn:id":2545533,
    "tgn:name":"North Fork Buffalo Creek",
    "tgn:placetype":[
        "aat:300008706"
    ]
},
  "bbox": [],
  "geometry": {"coordinates":[-81.45,39.8667],"type":"Point"}
}