{
  "id": 2221505,
  "type": "Feature",
  "properties": {
    "tgn:hierarchy":[
        "tgn:2221505",
        "tgn:7006450",
        "tgn:1000001",
        "tgn:7030547",
        "tgn:7012149",
        "tgn:7029392"
    ],
    "tgn:id":2221505,
    "tgn:name":"Caribou Lake",
    "tgn:placetype":[
        "aat:300008680"
    ]
},
  "bbox": [],
  "geometry": {"coordinates":[-152.45,63.55],"type":"Point"}
}