{
  "id": 7109916,
  "type": "Feature",
  "properties": {
    "tgn:hierarchy":[
        "tgn:7109916",
        "tgn:7003669",
        "tgn:1000003",
        "tgn:7000084",
        "tgn:7029392"
    ],
    "tgn:id":7109916,
    "tgn:name":"Rammersberg",
    "tgn:placetype":[
        "aat:300008347"
    ]
},
  "bbox": [],
  "geometry": {"coordinates":[11.633333,49.233333],"type":"Point"}
}