{
  "id": 2531396,
  "type": "Feature",
  "properties": {
    "tgn:hierarchy":[
        "tgn:2531396",
        "tgn:1000001",
        "tgn:2002368",
        "tgn:7012149",
        "tgn:7007923",
        "tgn:7029392"
    ],
    "tgn:id":2531396,
    "tgn:name":"Mule Creek",
    "tgn:placetype":[
        "aat:300008706"
    ]
},
  "bbox": [],
  "geometry": {"coordinates":[-106.35,41.55],"type":"Point"}
}