<<<<<<< HEAD
{
  "id": 7477395,
  "type": "Feature",
  "properties": {
    "tgn:hierarchy":[
        "tgn:7477395",
        "tgn:1000004",
        "tgn:1000454",
        "tgn:1000141",
        "tgn:7029392"
    ],
    "tgn:id":7477395,
    "tgn:name":"Fenglin Qiao",
    "tgn:placetype":[
        "aat:300007836"
    ]
},
  "bbox": [],
  "geometry": {"coordinates":[121.762155,25.098642],"type":"Point"}
}
=======
{"geometry":{"type":"Point","coordinates":[121.762155,25.098642]},"type":"Feature","properties":{"hierarchy":["tgn:7477395","tgn:1000004","tgn:1000454","tgn:1000141","tgn:7029392"],"placetype":["aat:300007836"],"id":7477395,"name:xx":"Fenglin Qiao"}}
>>>>>>> 03f74aca74312dbeaf24d7e61306dd6a786dc3d0
