{
  "id": 7477395,
  "type": "Feature",
  "properties": {
    "tgn:hierarchy":[
        "tgn:7477395",
        "tgn:1000004",
        "tgn:1000454",
        "tgn:1000141",
        "tgn:7029392"
    ],
    "tgn:id":7477395,
    "tgn:name":"Fenglin Qiao",
    "tgn:placetype":[
        "aat:300007836"
    ]
},
  "bbox": [],
  "geometry": {"coordinates":[121.762155,25.098642],"type":"Point"}
}