{
  "id": 7276912,
  "type": "Feature",
  "properties": {
    "tgn:hierarchy":[
        "tgn:7276912",
        "tgn:1001630",
        "tgn:1000049",
        "tgn:1000002",
        "tgn:7029392"
    ],
    "tgn:id":7276912,
    "tgn:name":"Yerbas Buenas, Quebrada",
    "tgn:placetype":[
        "aat:300266554",
        "aat:300008699"
    ]
},
  "bbox": [],
  "geometry": {"coordinates":[-69.616667,-27.283333],"type":"Point"}
}