{
  "id": 7506598,
  "type": "Feature",
  "properties": {
    "tgn:hierarchy":[
        "tgn:7506598",
        "tgn:1009227",
        "tgn:1000226",
        "tgn:7018437",
        "tgn:1000006",
        "tgn:7029392"
    ],
    "tgn:id":7506598,
    "tgn:name:en":"Roaring Torrent",
    "tgn:placetype":[
        "aat:300008699"
    ]
},
  "bbox": [],
  "geometry": {"coordinates":[169.333333,-44.033333],"type":"Point"}
}