{
  "id": 2203024,
  "type": "Feature",
  "properties": {
    "tgn:hierarchy":[
        "tgn:2203024",
        "tgn:1000001",
        "tgn:7012149",
        "tgn:7007709",
        "tgn:7029392"
    ],
    "tgn:id":2203024,
    "tgn:name":"Buckeye Spring",
    "tgn:placetype":[
        "aat:300008697"
    ]
},
  "bbox": [],
  "geometry": {"coordinates":[-81.8833,36.1833],"type":"Point"}
}