{
  "id": 2557217,
  "type": "Feature",
  "properties": {
    "tgn:hierarchy":[
        "tgn:2557217",
        "tgn:1002933",
        "tgn:1000001",
        "tgn:7012149",
        "tgn:7007239",
        "tgn:7029392"
    ],
    "tgn:id":2557217,
    "tgn:name":"Old Inlet Point",
    "tgn:placetype":[
        "aat:300008850"
    ]
},
  "bbox": [],
  "geometry": {"coordinates":[-75.05,38.45],"type":"Point"}
}