{
  "id": 2443292,
  "type": "Feature",
  "properties": {
    "tgn:hierarchy":[
        "tgn:2443292",
        "tgn:1000001",
        "tgn:7012149",
        "tgn:2000182",
        "tgn:7007157",
        "tgn:7029392"
    ],
    "tgn:id":2443292,
    "tgn:name":"L Drain",
    "tgn:placetype":[
        "aat:300006075"
    ]
},
  "bbox": [],
  "geometry": {"coordinates":[-115.4667,33.1833],"type":"Point"}
}