{
  "id": 7521083,
  "type": "Feature",
  "properties": {
    "tgn:hierarchy":[
        "tgn:7521083",
        "tgn:7001242",
        "tgn:7016833",
        "tgn:1001123",
        "tgn:7029392"
    ],
    "tgn:id":7521083,
    "tgn:name":"Al Mall\u0101\u1e29ah",
    "tgn:placetype":[
        "aat:300266556"
    ]
},
  "bbox": [],
  "geometry": {"coordinates":[32.373218,31.174534],"type":"Point"}
}