{
  "id": 2013206,
  "type": "Feature",
  "properties": {
    "tgn:hierarchy":[
        "tgn:2013206",
        "tgn:1000001",
        "tgn:7012149",
        "tgn:7007157",
        "tgn:1002828",
        "tgn:7029392"
    ],
    "tgn:id":2013206,
    "tgn:name":"Palm Desert",
    "tgn:placetype":[
        "aat:300008347"
    ]
},
  "bbox": [],
  "geometry": {"coordinates":[-116.3667,33.7167],"type":"Point"}
}