{
  "id": 7329324,
  "type": "Feature",
  "properties": {
    "tgn:hierarchy":[
        "tgn:7329324",
        "tgn:7002758",
        "tgn:7002830",
        "tgn:1000003",
        "tgn:1000095",
        "tgn:7029392"
    ],
    "tgn:id":7329324,
    "tgn:name":"Pinillos, Punta",
    "tgn:placetype":[
        "aat:300386846"
    ]
},
  "bbox": [],
  "geometry": {"coordinates":[-5.116667,36.433333],"type":"Point"}
}