{
  "id": 2271675,
  "type": "Feature",
  "properties": {
    "tgn:hierarchy":[
        "tgn:2271675",
        "tgn:1000001",
        "tgn:7012149",
        "tgn:2001716",
        "tgn:7007708",
        "tgn:7029392"
    ],
    "tgn:id":2271675,
    "tgn:name":"Cummins Ridge",
    "tgn:placetype":[
        "aat:300266640"
    ]
},
  "bbox": [],
  "geometry": {"coordinates":[-124.0333,44.2333],"type":"Point"}
}