{
  "id": 7540897,
  "type": "Feature",
  "properties": {
    "tgn:hierarchy":[
        "tgn:7540897",
        "tgn:7001242",
        "tgn:7001105",
        "tgn:7016833",
        "tgn:7029392"
    ],
    "tgn:id":7540897,
    "tgn:name:en":"Qaryat at Ta'm\u012br as Siy\u0101\u1e29\u012byah",
    "tgn:placetype":[
        "aat:300008347"
    ]
},
  "bbox": [],
  "geometry": {"coordinates":[30.469496,29.415527],"type":"Point"}
}