{
  "id": 7060832,
  "type": "Feature",
  "properties": {
    "tgn:hierarchy":[
        "tgn:7060832",
        "tgn:1000003",
        "tgn:7003678",
        "tgn:7000084",
        "tgn:7029392"
    ],
    "tgn:id":7060832,
    "tgn:name":"Altmorschen, Forst",
    "tgn:placetype":[
        "aat:300008863"
    ]
},
  "bbox": [],
  "geometry": {"coordinates":[9.583333,51.083333],"type":"Point"}
}