{
  "id": 1053531,
  "type": "Feature",
  "properties": {
    "tgn:hierarchy":[
        "tgn:1053531",
        "tgn:1000004",
        "tgn:1003405",
        "tgn:7018214",
        "tgn:7002435",
        "tgn:7029392"
    ],
    "tgn:id":1053531,
    "tgn:name":"Dar'yevka",
    "tgn:placetype":[
        "aat:300008347"
    ]
},
  "bbox": [],
  "geometry": {"coordinates":[39.6833,47.6833],"type":"Point"}
}