{
  "id": 7389102,
  "type": "Feature",
  "properties": {
    "tgn:hierarchy":[
        "tgn:7389102",
        "tgn:7005586",
        "tgn:1000001",
        "tgn:7005560",
        "tgn:7029392"
    ],
    "tgn:id":7389102,
    "tgn:name":"Quelit\u00e1n",
    "tgn:placetype":[
        "aat:300008347"
    ]
},
  "bbox": [],
  "geometry": {"coordinates":[-104.833333,19.783333],"type":"Point"}
}