{
  "id": 2327436,
  "type": "Feature",
  "properties": {
    "tgn:hierarchy":[
        "tgn:2327436",
        "tgn:1000001",
        "tgn:7012149",
        "tgn:2002121",
        "tgn:7007827",
        "tgn:7029392"
    ],
    "tgn:id":2327436,
    "tgn:name":"First Spring Hollow",
    "tgn:placetype":[
        "aat:300008761"
    ]
},
  "bbox": [],
  "geometry": {"coordinates":[-112.3167,38.5167],"type":"Point"}
}