{
  "id": 2654694,
  "type": "Feature",
  "properties": {
    "tgn:hierarchy":[
        "tgn:2654694",
        "tgn:7013388",
        "tgn:1000001",
        "tgn:7012149",
        "tgn:7007517",
        "tgn:7029392"
    ],
    "tgn:id":2654694,
    "tgn:name":"Shaker Pond",
    "tgn:placetype":[
        "aat:300006191"
    ]
},
  "bbox": [],
  "geometry": {"coordinates":[-73.2167,42.2333],"type":"Point"}
}