<<<<<<< HEAD
{
  "id": 2258765,
  "type": "Feature",
  "properties": {
    "tgn:hierarchy":[
        "tgn:2258765",
        "tgn:1000001",
        "tgn:7006451",
        "tgn:2000092",
        "tgn:7012149",
        "tgn:7029392"
    ],
    "tgn:id":2258765,
    "tgn:name":"Cottonwood Cove",
    "tgn:placetype":[
        "aat:300008761"
    ]
},
  "bbox": [],
  "geometry": {"coordinates":[-112.0,36.9333],"type":"Point"}
}
=======
{"geometry":{"type":"Point","coordinates":[-112.000000,36.933300]},"type":"Feature","properties":{"hierarchy":["tgn:2258765","tgn:1000001","tgn:7006451","tgn:2000092","tgn:7012149","tgn:7029392"],"placetype":["aat:300008761"],"id":2258765,"name:xx":"Cottonwood Cove"}}
>>>>>>> 03f74aca74312dbeaf24d7e61306dd6a786dc3d0
