{
  "id": 7067111,
  "type": "Feature",
  "properties": {
    "tgn:hierarchy":[
        "tgn:7067111",
        "tgn:1000003",
        "tgn:7003688",
        "tgn:7000084",
        "tgn:7029392"
    ],
    "tgn:id":7067111,
    "tgn:name":"St\u00f6rmerkaten",
    "tgn:placetype":[
        "aat:300000206"
    ]
},
  "bbox": [],
  "geometry": {"coordinates":[10.216667,53.516667],"type":"Point"}
}