<<<<<<< HEAD
{
  "id": 2150427,
  "type": "Feature",
  "properties": {
    "tgn:hierarchy":[
        "tgn:2150427",
        "tgn:1000001",
        "tgn:2002370",
        "tgn:7012149",
        "tgn:7007923",
        "tgn:7029392"
    ],
    "tgn:id":2150427,
    "tgn:name":"Basin Draw",
    "tgn:placetype":[
        "aat:300008761"
    ]
},
  "bbox": [],
  "geometry": {"coordinates":[-104.7833,44.6],"type":"Point"}
}
=======
{"geometry":{"type":"Point","coordinates":[-104.783300,44.600000]},"type":"Feature","properties":{"hierarchy":["tgn:2150427","tgn:1000001","tgn:2002370","tgn:7012149","tgn:7007923","tgn:7029392"],"placetype":["aat:300008761"],"id":2150427,"name:xx":"Basin Draw"}}
>>>>>>> 03f74aca74312dbeaf24d7e61306dd6a786dc3d0
