{
  "id": 7382692,
  "type": "Feature",
  "properties": {
    "tgn:hierarchy":[
        "tgn:7382692",
        "tgn:1000001",
        "tgn:1001960",
        "tgn:7005560",
        "tgn:7029392"
    ],
    "tgn:id":7382692,
    "tgn:name":"Noria de Santa Cruz",
    "tgn:placetype":[
        "aat:300008347"
    ]
},
  "bbox": [],
  "geometry": {"coordinates":[-110.616667,31.333333],"type":"Point"}
}