{
  "id": 2541442,
  "type": "Feature",
  "properties": {
    "tgn:hierarchy":[
        "tgn:2541442",
        "tgn:1002483",
        "tgn:7019080",
        "tgn:1000001",
        "tgn:7012149",
        "tgn:7007249",
        "tgn:7029392"
    ],
    "tgn:id":2541442,
    "tgn:name":"Nihoa Gulch",
    "tgn:placetype":[
        "aat:300008761"
    ]
},
  "bbox": [],
  "geometry": {"coordinates":[-158.2167,21.55],"type":"Point"}
}