{
  "id": 1033978,
  "type": "Feature",
  "properties": {
    "tgn:hierarchy":[
        "tgn:1033978",
        "tgn:1000003",
        "tgn:7002883",
        "tgn:1000070",
        "tgn:7029392"
    ],
    "tgn:id":1033978,
    "tgn:name":"Les Clayes-sous-Bois",
    "tgn:placetype":[
        "aat:300008347"
    ]
},
  "bbox": [],
  "geometry": {"coordinates":[1.9833,48.8167],"type":"Point"}
}