{
  "id": 2293105,
  "type": "Feature",
  "properties": {
    "tgn:hierarchy":[
        "tgn:2293105",
        "tgn:1000001",
        "tgn:7012149",
        "tgn:2000476",
        "tgn:7007250",
        "tgn:7029392"
    ],
    "tgn:id":2293105,
    "tgn:name":"Doty Draw",
    "tgn:placetype":[
        "aat:300008761"
    ]
},
  "bbox": [],
  "geometry": {"coordinates":[-116.0167,46.1667],"type":"Point"}
}