{
  "id": 2662735,
  "type": "Feature",
  "properties": {
    "tgn:hierarchy":[
        "tgn:2662735",
        "tgn:1000001",
        "tgn:7006451",
        "tgn:7012149",
        "tgn:2000100",
        "tgn:7029392"
    ],
    "tgn:id":2662735,
    "tgn:name":"Sikul Himatk Wash",
    "tgn:placetype":[
        "aat:300008699"
    ]
},
  "bbox": [],
  "geometry": {"coordinates":[-112.0333,32.1167],"type":"Point"}
}