<<<<<<< HEAD
{
  "id": 7378280,
  "type": "Feature",
  "properties": {
    "tgn:hierarchy":[
        "tgn:7378280",
        "tgn:1000001",
        "tgn:7005597",
        "tgn:7005560",
        "tgn:7029392"
    ],
    "tgn:id":7378280,
    "tgn:name":"La Presa",
    "tgn:placetype":[
        "aat:300266554",
        "aat:300008699"
    ]
},
  "bbox": [],
  "geometry": {"coordinates":[-99.016667,23.9],"type":"Point"}
}
=======
{"geometry":{"type":"Point","coordinates":[-99.016667,23.900000]},"type":"Feature","properties":{"hierarchy":["tgn:7378280","tgn:1000001","tgn:7005597","tgn:7005560","tgn:7029392"],"placetype":["aat:300266554","aat:300008699"],"id":7378280,"name:xx":"La Presa"}}
>>>>>>> 03f74aca74312dbeaf24d7e61306dd6a786dc3d0
