{
  "id": 2599108,
  "type": "Feature",
  "properties": {
    "tgn:hierarchy":[
        "tgn:2599108",
        "tgn:1000001",
        "tgn:7012149",
        "tgn:1002763",
        "tgn:7007255",
        "tgn:7029392"
    ],
    "tgn:id":2599108,
    "tgn:name":"Priors Branch",
    "tgn:placetype":[
        "aat:300008699"
    ]
},
  "bbox": [],
  "geometry": {"coordinates":[-84.95,38.5833],"type":"Point"}
}