<<<<<<< HEAD
{
  "id": 2406546,
  "type": "Feature",
  "properties": {
    "tgn:hierarchy":[
        "tgn:2406546",
        "tgn:7006450",
        "tgn:1000001",
        "tgn:2124053",
        "tgn:7012149",
        "tgn:7029392"
    ],
    "tgn:id":2406546,
    "tgn:name":"Hungryman Creek",
    "tgn:placetype":[
        "aat:300008706"
    ]
},
  "bbox": [],
  "geometry": {"coordinates":[-150.95,62.4],"type":"Point"}
}
=======
{"geometry":{"type":"Point","coordinates":[-150.950000,62.400000]},"type":"Feature","properties":{"hierarchy":["tgn:2406546","tgn:7006450","tgn:1000001","tgn:2124053","tgn:7012149","tgn:7029392"],"placetype":["aat:300008706"],"id":2406546,"name:xx":"Hungryman Creek"}}
>>>>>>> 03f74aca74312dbeaf24d7e61306dd6a786dc3d0
