{
  "id": 7098543,
  "type": "Feature",
  "properties": {
    "tgn:hierarchy":[
        "tgn:7098543",
        "tgn:1000003",
        "tgn:7003678",
        "tgn:7000084",
        "tgn:7029392"
    ],
    "tgn:id":7098543,
    "tgn:name":"Semd",
    "tgn:placetype":[
        "aat:300008347"
    ]
},
  "bbox": [],
  "geometry": {"coordinates":[8.885833,49.873333],"type":"Point"}
}