<<<<<<< HEAD
{
  "id": 7375570,
  "type": "Feature",
  "properties": {
    "tgn:hierarchy":[
        "tgn:7375570",
        "tgn:7005583",
        "tgn:1000001",
        "tgn:7005560",
        "tgn:7029392"
    ],
    "tgn:id":7375570,
    "tgn:name":"La Quesera",
    "tgn:placetype":[
        "aat:300008347"
    ]
},
  "bbox": [],
  "geometry": {"coordinates":[-105.6,26.183333],"type":"Point"}
}
=======
{"geometry":{"type":"Point","coordinates":[-105.600000,26.183333]},"type":"Feature","properties":{"hierarchy":["tgn:7375570","tgn:7005583","tgn:1000001","tgn:7005560","tgn:7029392"],"placetype":["aat:300008347"],"id":7375570,"name:xx":"La Quesera"}}
>>>>>>> 03f74aca74312dbeaf24d7e61306dd6a786dc3d0
