{
  "id": 2340494,
  "type": "Feature",
  "properties": {
    "tgn:hierarchy":[
        "tgn:2340494",
        "tgn:1000001",
        "tgn:7012149",
        "tgn:1002676",
        "tgn:7007240",
        "tgn:7029392"
    ],
    "tgn:id":2340494,
    "tgn:name":"French Reef",
    "tgn:placetype":[
        "aat:300132348"
    ]
},
  "bbox": [],
  "geometry": {"coordinates":[-80.35,25.0333],"type":"Point"}
}