{
  "id": 2171729,
  "type": "Feature",
  "properties": {
    "tgn:hierarchy":[
        "tgn:2171729",
        "tgn:1000001",
        "tgn:2001418",
        "tgn:7012149",
        "tgn:7007526",
        "tgn:7029392"
    ],
    "tgn:id":2171729,
    "tgn:name":"Big Tono",
    "tgn:placetype":[
        "aat:300000390"
    ]
},
  "bbox": [],
  "geometry": {"coordinates":[-117.2333,38.05],"type":"Point"}
}