{
  "id": 2215767,
  "type": "Feature",
  "properties": {
    "tgn:hierarchy":[
        "tgn:2215767",
        "tgn:1000001",
        "tgn:7012149",
        "tgn:2000488",
        "tgn:7007250",
        "tgn:7029392"
    ],
    "tgn:id":2215767,
    "tgn:name":"Camel Creek",
    "tgn:placetype":[
        "aat:300008706"
    ]
},
  "bbox": [],
  "geometry": {"coordinates":[-116.6167,42.5667],"type":"Point"}
}