{
  "id": 1010306,
  "type": "Feature",
  "properties": {
    "tgn:hierarchy":[
        "tgn:1010306",
        "tgn:1000738",
        "tgn:1000001",
        "tgn:7005562",
        "tgn:7029392"
    ],
    "tgn:id":1010306,
    "tgn:name":"Solentiname, Archipi\u00e9lago de",
    "tgn:placetype":[
        "aat:300386854"
    ]
},
  "bbox": [],
  "geometry": {"coordinates":[-84.99,11.172],"type":"Point"}
}