{
  "id": 2515715,
  "type": "Feature",
  "properties": {
    "tgn:hierarchy":[
        "tgn:2515715",
        "tgn:1000001",
        "tgn:7012149",
        "tgn:2001488",
        "tgn:7007709",
        "tgn:7029392"
    ],
    "tgn:id":2515715,
    "tgn:name":"Milltail Creek",
    "tgn:placetype":[
        "aat:300008706"
    ]
},
  "bbox": [],
  "geometry": {"coordinates":[-75.85,35.7667],"type":"Point"}
}