{
  "id": 2312891,
  "type": "Feature",
  "properties": {
    "tgn:hierarchy":[
        "tgn:2312891",
        "tgn:1000001",
        "tgn:7012149",
        "tgn:2002118",
        "tgn:7007827",
        "tgn:7029392"
    ],
    "tgn:id":2312891,
    "tgn:name":"El Sid Condominium",
    "tgn:placetype":[
        "aat:300008347"
    ]
},
  "bbox": [],
  "geometry": {"coordinates":[-111.8667,40.6333],"type":"Point"}
}