{
  "id": 1014429,
  "type": "Feature",
  "properties": {
    "tgn:hierarchy":[
        "tgn:1014429",
        "tgn:7013022",
        "tgn:7005685",
        "tgn:1000001",
        "tgn:7005802",
        "tgn:7029392"
    ],
    "tgn:id":1014429,
    "tgn:name":"Fourchu",
    "tgn:placetype":[
        "aat:300008347"
    ]
},
  "bbox": [],
  "geometry": {"coordinates":[-60.2833,45.7167],"type":"Point"}
}