{
  "id": 2265476,
  "type": "Feature",
  "properties": {
    "tgn:hierarchy":[
        "tgn:2265476",
        "tgn:1000001",
        "tgn:7012149",
        "tgn:1002897",
        "tgn:7007920",
        "tgn:7029392"
    ],
    "tgn:id":2265476,
    "tgn:name":"Crane Lake",
    "tgn:placetype":[
        "aat:300008680"
    ]
},
  "bbox": [],
  "geometry": {"coordinates":[-122.05,46.1833],"type":"Point"}
}