{
  "id": 2476896,
  "type": "Feature",
  "properties": {
    "tgn:hierarchy":[
        "tgn:2476896",
        "tgn:1000001",
        "tgn:7012149",
        "tgn:1002742",
        "tgn:7007920",
        "tgn:7029392"
    ],
    "tgn:id":2476896,
    "tgn:name":"Lyman Creek",
    "tgn:placetype":[
        "aat:300008706"
    ]
},
  "bbox": [],
  "geometry": {"coordinates":[-119.0167,48.5167],"type":"Point"}
}