{
  "id": 7132952,
  "type": "Feature",
  "properties": {
    "tgn:hierarchy":[
        "tgn:7132952",
        "tgn:1000003",
        "tgn:7003688",
        "tgn:7000084",
        "tgn:7029392"
    ],
    "tgn:id":7132952,
    "tgn:name":"M\u00fchlenberg",
    "tgn:placetype":[
        "aat:300000206"
    ]
},
  "bbox": [],
  "geometry": {"coordinates":[10.316667,54.216667],"type":"Point"}
}