{
  "id": 7447079,
  "type": "Feature",
  "properties": {
    "tgn:hierarchy":[
        "tgn:7447079",
        "tgn:7002445",
        "tgn:1000003",
        "tgn:7019057",
        "tgn:7008591",
        "tgn:7029392"
    ],
    "tgn:id":7447079,
    "tgn:name:en":"Skeffling",
    "tgn:placetype":[
        "aat:300008347"
    ]
},
  "bbox": [],
  "geometry": {"coordinates":[0.066667,53.65],"type":"Point"}
}