{
  "id": 1068208,
  "type": "Feature",
  "properties": {
    "tgn:hierarchy":[
        "tgn:1068208",
        "tgn:1000004",
        "tgn:7002081",
        "tgn:1000111",
        "tgn:7029392"
    ],
    "tgn:id":1068208,
    "tgn:name":"Gaochun",
    "tgn:placetype":[
        "aat:300008347"
    ]
},
  "bbox": [],
  "geometry": {"coordinates":[118.8167,31.3333],"type":"Point"}
}