{
  "id": 7278644,
  "type": "Feature",
  "properties": {
    "tgn:hierarchy":[
        "tgn:7278644",
        "tgn:1001702",
        "tgn:1000049",
        "tgn:1000002",
        "tgn:7029392"
    ],
    "tgn:id":7278644,
    "tgn:name":"Tasbani, Punta",
    "tgn:placetype":[
        "aat:300386846"
    ]
},
  "bbox": [],
  "geometry": {"coordinates":[-68.333333,-55.083333],"type":"Point"}
}