<<<<<<< HEAD
{
  "id": 2703482,
  "type": "Feature",
  "properties": {
    "tgn:hierarchy":[
        "tgn:2703482",
        "tgn:1000001",
        "tgn:7012149",
        "tgn:1002742",
        "tgn:7007920",
        "tgn:7029392"
    ],
    "tgn:id":2703482,
    "tgn:name":"Summit Lake",
    "tgn:placetype":[
        "aat:300008680"
    ]
},
  "bbox": [],
  "geometry": {"coordinates":[-119.15,48.2667],"type":"Point"}
}
=======
{"geometry":{"type":"Point","coordinates":[-119.150000,48.266700]},"type":"Feature","properties":{"hierarchy":["tgn:2703482","tgn:1000001","tgn:7012149","tgn:1002742","tgn:7007920","tgn:7029392"],"placetype":["aat:300008680"],"id":2703482,"name:xx":"Summit Lake"}}
>>>>>>> 03f74aca74312dbeaf24d7e61306dd6a786dc3d0
