<<<<<<< HEAD
{
  "id": 7244422,
  "type": "Feature",
  "properties": {
    "tgn:hierarchy":[
        "tgn:7244422",
        "tgn:7003457",
        "tgn:1000003",
        "tgn:1000063",
        "tgn:7018236",
        "tgn:7029392"
    ],
    "tgn:id":7244422,
    "tgn:name":"Kruisstraat",
    "tgn:placetype":[
        "aat:300008347"
    ]
},
  "bbox": [],
  "geometry": {"coordinates":[3.58779,51.108843],"type":"Point"}
}
=======
{"geometry":{"type":"Point","coordinates":[3.587790,51.108843]},"type":"Feature","properties":{"hierarchy":["tgn:7244422","tgn:7003457","tgn:1000003","tgn:1000063","tgn:7018236","tgn:7029392"],"placetype":["aat:300008347"],"id":7244422,"name:xx":"Kruisstraat"}}
>>>>>>> 03f74aca74312dbeaf24d7e61306dd6a786dc3d0
