{
  "id": 2750311,
  "type": "Feature",
  "properties": {
    "tgn:hierarchy":[
        "tgn:2750311",
        "tgn:1000001",
        "tgn:7012149",
        "tgn:2002008",
        "tgn:7007826",
        "tgn:7029392"
    ],
    "tgn:id":2750311,
    "tgn:name":"Wampler Hill",
    "tgn:placetype":[
        "aat:300008798"
    ]
},
  "bbox": [],
  "geometry": {"coordinates":[-97.9833,33.0667],"type":"Point"}
}