{
  "id": 2526871,
  "type": "Feature",
  "properties": {
    "tgn:hierarchy":[
        "tgn:2526871",
        "tgn:1000001",
        "tgn:2002314",
        "tgn:7012149",
        "tgn:7007922",
        "tgn:7029392"
    ],
    "tgn:id":2526871,
    "tgn:name":"Mound Creek",
    "tgn:placetype":[
        "aat:300008706"
    ]
},
  "bbox": [],
  "geometry": {"coordinates":[-90.65,44.6167],"type":"Point"}
}