{
  "id": 7075513,
  "type": "Feature",
  "properties": {
    "tgn:hierarchy":[
        "tgn:7075513",
        "tgn:1000003",
        "tgn:7003678",
        "tgn:7000084",
        "tgn:7029392"
    ],
    "tgn:id":7075513,
    "tgn:name":"Hausen-Oes",
    "tgn:placetype":[
        "aat:300008347"
    ]
},
  "bbox": [],
  "geometry": {"coordinates":[8.616667,50.416667],"type":"Point"}
}