{
  "id": 7159664,
  "type": "Feature",
  "properties": {
    "tgn:hierarchy":[
        "tgn:7159664",
        "tgn:7003669",
        "tgn:1000003",
        "tgn:7000084",
        "tgn:7029392"
    ],
    "tgn:id":7159664,
    "tgn:name":"Hofham",
    "tgn:placetype":[
        "aat:300008347"
    ]
},
  "bbox": [],
  "geometry": {"coordinates":[12.966667,47.833333],"type":"Point"}
}