{
  "id": 7508075,
  "type": "Feature",
  "properties": {
    "tgn:hierarchy":[
        "tgn:7508075",
        "tgn:1009227",
        "tgn:1000226",
        "tgn:1000006",
        "tgn:7016850",
        "tgn:7029392"
    ],
    "tgn:id":7508075,
    "tgn:name:en":"Paroa",
    "tgn:placetype":[
        "aat:300008347"
    ]
},
  "bbox": [],
  "geometry": {"coordinates":[171.166667,-42.516667],"type":"Point"}
}