{
  "id": 1138907,
  "type": "Feature",
  "properties": {
    "tgn:hierarchy":[
        "tgn:1138907",
        "tgn:1000004",
        "tgn:7002076",
        "tgn:1000111",
        "tgn:7029392"
    ],
    "tgn:id":1138907,
    "tgn:name":"Deqing",
    "tgn:placetype":[
        "aat:300008347"
    ]
},
  "bbox": [],
  "geometry": {"coordinates":[120.0833,30.55],"type":"Point"}
}