{
  "id": 2645609,
  "type": "Feature",
  "properties": {
    "tgn:hierarchy":[
        "tgn:2645609",
        "tgn:1000001",
        "tgn:7006451",
        "tgn:2000093",
        "tgn:7012149",
        "tgn:7029392"
    ],
    "tgn:id":2645609,
    "tgn:name":"Sawmill",
    "tgn:placetype":[
        "aat:300008347"
    ]
},
  "bbox": [],
  "geometry": {"coordinates":[-110.3833,33.6167],"type":"Point"}
}