{
  "id": 2671091,
  "type": "Feature",
  "properties": {
    "tgn:hierarchy":[
        "tgn:2671091",
        "tgn:1000001",
        "tgn:7012149",
        "tgn:2001677",
        "tgn:7007707",
        "tgn:7029392"
    ],
    "tgn:id":2671091,
    "tgn:name":"Smith Creek",
    "tgn:placetype":[
        "aat:300008706"
    ]
},
  "bbox": [],
  "geometry": {"coordinates":[-97.2167,35.5667],"type":"Point"}
}