{
  "id": 1124944,
  "type": "Feature",
  "properties": {
    "tgn:hierarchy":[
        "tgn:1124944",
        "tgn:1000003",
        "tgn:7003122",
        "tgn:1001737",
        "tgn:1000080",
        "tgn:7029392"
    ],
    "tgn:id":1124944,
    "tgn:name":"Ippari",
    "tgn:placetype":[
        "aat:300008707"
    ]
},
  "bbox": [],
  "geometry": {"coordinates":[14.4333,36.8667],"type":"Point"}
}