{
  "id": 2447033,
  "type": "Feature",
  "properties": {
    "tgn:hierarchy":[
        "tgn:2447033",
        "tgn:1000001",
        "tgn:7012149",
        "tgn:2001852",
        "tgn:7007825",
        "tgn:7029392"
    ],
    "tgn:id":2447033,
    "tgn:name":"Liberty Lake",
    "tgn:placetype":[
        "aat:300008680"
    ]
},
  "bbox": [],
  "geometry": {"coordinates":[-86.0333,35.6333],"type":"Point"}
}