{
  "id": 2462227,
  "type": "Feature",
  "properties": {
    "tgn:hierarchy":[
        "tgn:2462227",
        "tgn:1000001",
        "tgn:1002276",
        "tgn:7012149",
        "tgn:7007708",
        "tgn:7029392"
    ],
    "tgn:id":2462227,
    "tgn:name":"Little Wallooskee River",
    "tgn:placetype":[
        "aat:300008707"
    ]
},
  "bbox": [],
  "geometry": {"coordinates":[-123.7333,46.1333],"type":"Point"}
}