{
  "id": 2048087,
  "type": "Feature",
  "properties": {
    "tgn:hierarchy":[
        "tgn:2048087",
        "tgn:2000934",
        "tgn:1000001",
        "tgn:7012149",
        "tgn:7007516",
        "tgn:7029392"
    ],
    "tgn:id":2048087,
    "tgn:name":"North Branch",
    "tgn:placetype":[
        "aat:300387016"
    ]
},
  "bbox": [],
  "geometry": {"coordinates":[-78.7167,39.5833],"type":"Point"}
}