{
  "id": 2435304,
  "type": "Feature",
  "properties": {
    "tgn:hierarchy":[
        "tgn:2435304",
        "tgn:1000001",
        "tgn:2000860",
        "tgn:7012149",
        "tgn:7007256",
        "tgn:7029392"
    ],
    "tgn:id":2435304,
    "tgn:name":"Kepler Creek Lake",
    "tgn:placetype":[
        "aat:300006191"
    ]
},
  "bbox": [],
  "geometry": {"coordinates":[-93.15,32.3167],"type":"Point"}
}