{
  "id": 7005448,
  "type": "Feature",
  "properties": {
    "tgn:hierarchy":[
        "tgn:7005448",
        "tgn:1000001",
        "tgn:7005441",
        "tgn:7029392"
    ],
    "tgn:id":7005448,
    "tgn:name":"Caba\u00f1as",
    "tgn:placetype":[
        "aat:300008631",
        "aat:300387064",
        "aat:300000772"
    ]
},
  "bbox": [],
  "geometry": {"coordinates":[-88.75,13.8667],"type":"Point"}
}