{
  "id": 2543985,
  "type": "Feature",
  "properties": {
    "tgn:hierarchy":[
        "tgn:2543985",
        "tgn:1000001",
        "tgn:2001789",
        "tgn:7012149",
        "tgn:7007713",
        "tgn:7029392"
    ],
    "tgn:id":2543985,
    "tgn:name":"North Branch Cobb Creek",
    "tgn:placetype":[
        "aat:300008706"
    ]
},
  "bbox": [],
  "geometry": {"coordinates":[-96.6333,44.6833],"type":"Point"}
}