{
  "id": 2245080,
  "type": "Feature",
  "properties": {
    "tgn:hierarchy":[
        "tgn:2245080",
        "tgn:7006450",
        "tgn:1000001",
        "tgn:2124012",
        "tgn:7012149",
        "tgn:7029392"
    ],
    "tgn:id":2245080,
    "tgn:name":"Clover Rock",
    "tgn:placetype":[
        "aat:300008791"
    ]
},
  "bbox": [],
  "geometry": {"coordinates":[-153.8167,57.65],"type":"Point"}
}