<<<<<<< HEAD
{
  "id": 2764957,
  "type": "Feature",
  "properties": {
    "tgn:hierarchy":[
        "tgn:2764957",
        "tgn:1000001",
        "tgn:2001096",
        "tgn:7012149",
        "tgn:7007522",
        "tgn:7029392"
    ],
    "tgn:id":2764957,
    "tgn:name":"Whisky Branch",
    "tgn:placetype":[
        "aat:300008699"
    ]
},
  "bbox": [],
  "geometry": {"coordinates":[-90.85,31.95],"type":"Point"}
}
=======
{"geometry":{"type":"Point","coordinates":[-90.850000,31.950000]},"type":"Feature","properties":{"hierarchy":["tgn:2764957","tgn:1000001","tgn:2001096","tgn:7012149","tgn:7007522","tgn:7029392"],"placetype":["aat:300008699"],"id":2764957,"name:xx":"Whisky Branch"}}
>>>>>>> 03f74aca74312dbeaf24d7e61306dd6a786dc3d0
