{
  "id": 2764957,
  "type": "Feature",
  "properties": {
    "tgn:hierarchy":[
        "tgn:2764957",
        "tgn:1000001",
        "tgn:2001096",
        "tgn:7012149",
        "tgn:7007522",
        "tgn:7029392"
    ],
    "tgn:id":2764957,
    "tgn:name":"Whisky Branch",
    "tgn:placetype":[
        "aat:300008699"
    ]
},
  "bbox": [],
  "geometry": {"coordinates":[-90.85,31.95],"type":"Point"}
}