{
  "id": 2402897,
  "type": "Feature",
  "properties": {
    "tgn:hierarchy":[
        "tgn:2402897",
        "tgn:1000001",
        "tgn:7012149",
        "tgn:2001896",
        "tgn:7007825",
        "tgn:7029392"
    ],
    "tgn:id":2402897,
    "tgn:name":"Hotspur Branch",
    "tgn:placetype":[
        "aat:300008699"
    ]
},
  "bbox": [],
  "geometry": {"coordinates":[-86.8667,35.6167],"type":"Point"}
}