{
  "id": 2322881,
  "type": "Feature",
  "properties": {
    "tgn:hierarchy":[
        "tgn:2322881",
        "tgn:1000001",
        "tgn:7012149",
        "tgn:1002350",
        "tgn:7007157",
        "tgn:7029392"
    ],
    "tgn:id":2322881,
    "tgn:name":"Fannette Island",
    "tgn:placetype":[
        "aat:300008791"
    ]
},
  "bbox": [],
  "geometry": {"coordinates":[-120.0833,38.95],"type":"Point"}
}