{
  "id": 7591263,
  "type": "Feature",
  "properties": {
    "tgn:hierarchy":[
        "tgn:7591263",
        "tgn:1000004",
        "tgn:7000198",
        "tgn:7000799",
        "tgn:7029392"
    ],
    "tgn:id":7591263,
    "tgn:name:en":"Budw\u0101l",
    "tgn:placetype":[
        "aat:300008347"
    ]
},
  "bbox": [],
  "geometry": {"coordinates":[74.47681,32.806863],"type":"Point"}
}