{
  "id": 7020475,
  "type": "Feature",
  "properties": {
    "tgn:hierarchy":[
        "tgn:7020475",
        "tgn:1000001",
        "tgn:7012149",
        "tgn:2001279",
        "tgn:7007524",
        "tgn:7029392"
    ],
    "tgn:id":7020475,
    "tgn:name":"Snow Cap Mine",
    "tgn:placetype":[
        "aat:300000390"
    ]
},
  "bbox": [],
  "geometry": {"coordinates":[-113.15,46.4833],"type":"Point"}
}