{
  "id": 7277598,
  "type": "Feature",
  "properties": {
    "tgn:hierarchy":[
        "tgn:7277598",
        "tgn:1001702",
        "tgn:1000049",
        "tgn:1000002",
        "tgn:7029392"
    ],
    "tgn:id":7277598,
    "tgn:name":"Wilshere, Fiordo",
    "tgn:placetype":[
        "aat:300008676"
    ]
},
  "bbox": [],
  "geometry": {"coordinates":[-74.65,-50.016667],"type":"Point"}
}