{
  "id": 1003959,
  "type": "Feature",
  "properties": {
    "tgn:hierarchy":[
        "tgn:1003959",
        "tgn:1000003",
        "tgn:7003677",
        "tgn:7000084",
        "tgn:7005154",
        "tgn:7029392"
    ],
    "tgn:id":1003959,
    "tgn:name":"Altenhagen",
    "tgn:placetype":[
        "aat:300000745",
        "aat:300387332"
    ]
},
  "bbox": [],
  "geometry": {"coordinates":[7.466667,51.366667],"type":"Point"}
}