<<<<<<< HEAD
{
  "id": 2766018,
  "type": "Feature",
  "properties": {
    "tgn:hierarchy":[
        "tgn:2766018",
        "tgn:1000001",
        "tgn:2001432",
        "tgn:7012149",
        "tgn:7007566",
        "tgn:7029392"
    ],
    "tgn:id":2766018,
    "tgn:name":"White Horse",
    "tgn:placetype":[
        "aat:300000390"
    ]
},
  "bbox": [],
  "geometry": {"coordinates":[-105.2333,36.6167],"type":"Point"}
}
=======
{"geometry":{"type":"Point","coordinates":[-105.233300,36.616700]},"type":"Feature","properties":{"hierarchy":["tgn:2766018","tgn:1000001","tgn:2001432","tgn:7012149","tgn:7007566","tgn:7029392"],"placetype":["aat:300000390"],"id":2766018,"name:xx":"White Horse"}}
>>>>>>> 03f74aca74312dbeaf24d7e61306dd6a786dc3d0
