{
  "id": 1014957,
  "type": "Feature",
  "properties": {
    "tgn:hierarchy":[
        "tgn:1014957",
        "tgn:7005685",
        "tgn:1000001",
        "tgn:7013154",
        "tgn:7029392"
    ],
    "tgn:id":1014957,
    "tgn:name":"New Hamburg",
    "tgn:placetype":[
        "aat:300008347"
    ]
},
  "bbox": [],
  "geometry": {"coordinates":[-80.7167,43.3833],"type":"Point"}
}