{
  "id": 7516917,
  "type": "Feature",
  "properties": {
    "tgn:hierarchy":[
        "tgn:7516917",
        "tgn:1009227",
        "tgn:1000226",
        "tgn:7016822",
        "tgn:1000006",
        "tgn:7029392"
    ],
    "tgn:id":7516917,
    "tgn:name:en":"Nugget Hill",
    "tgn:placetype":[
        "aat:300008795"
    ]
},
  "bbox": [],
  "geometry": {"coordinates":[167.916667,-45.816667],"type":"Point"}
}