<<<<<<< HEAD
{
  "id": 7356465,
  "type": "Feature",
  "properties": {
    "tgn:hierarchy":[
        "tgn:7356465",
        "tgn:1000001",
        "tgn:7005601",
        "tgn:7005560",
        "tgn:7029392"
    ],
    "tgn:id":7356465,
    "tgn:name":"China, Cerro de la",
    "tgn:placetype":[
        "aat:300008795"
    ]
},
  "bbox": [],
  "geometry": {"coordinates":[-102.133333,24.9],"type":"Point"}
}
=======
{"geometry":{"type":"Point","coordinates":[-102.133333,24.900000]},"type":"Feature","properties":{"hierarchy":["tgn:7356465","tgn:1000001","tgn:7005601","tgn:7005560","tgn:7029392"],"placetype":["aat:300008795"],"id":7356465,"name:xx":"China, Cerro de la"}}
>>>>>>> 03f74aca74312dbeaf24d7e61306dd6a786dc3d0
