{
  "id": 2446463,
  "type": "Feature",
  "properties": {
    "tgn:hierarchy":[
        "tgn:2446463",
        "tgn:1000001",
        "tgn:7012149",
        "tgn:7007158",
        "tgn:2000240",
        "tgn:7029392"
    ],
    "tgn:id":2446463,
    "tgn:name":"Lewis Lake",
    "tgn:placetype":[
        "aat:300008680"
    ]
},
  "bbox": [],
  "geometry": {"coordinates":[-107.1833,39.3333],"type":"Point"}
}