{
  "id": 7443238,
  "type": "Feature",
  "properties": {
    "tgn:hierarchy":[
        "tgn:7443238",
        "tgn:7002444",
        "tgn:1000003",
        "tgn:7008094",
        "tgn:7008591",
        "tgn:7029392"
    ],
    "tgn:id":7443238,
    "tgn:name:en":"Veilish Point",
    "tgn:placetype":[
        "aat:300386846"
    ]
},
  "bbox": [],
  "geometry": {"coordinates":[-7.35,57.666667],"type":"Point"}
}