<<<<<<< HEAD
{
  "id": 2405601,
  "type": "Feature",
  "properties": {
    "tgn:hierarchy":[
        "tgn:2405601",
        "tgn:1000001",
        "tgn:7012149",
        "tgn:2001254",
        "tgn:7007523",
        "tgn:7029392"
    ],
    "tgn:id":2405601,
    "tgn:name":"Hughes Mountain",
    "tgn:placetype":[
        "aat:300008798"
    ]
},
  "bbox": [],
  "geometry": {"coordinates":[-90.7,37.8],"type":"Point"}
}
=======
{"geometry":{"type":"Point","coordinates":[-90.700000,37.800000]},"type":"Feature","properties":{"hierarchy":["tgn:2405601","tgn:1000001","tgn:7012149","tgn:2001254","tgn:7007523","tgn:7029392"],"placetype":["aat:300008798"],"id":2405601,"name:xx":"Hughes Mountain"}}
>>>>>>> 03f74aca74312dbeaf24d7e61306dd6a786dc3d0
