{
  "id": 1046390,
  "type": "Feature",
  "properties": {
    "tgn:hierarchy":[
        "tgn:1046390",
        "tgn:1003489",
        "tgn:7004610",
        "tgn:1000003",
        "tgn:1000080",
        "tgn:7029392"
    ],
    "tgn:id":1046390,
    "tgn:name":"Rotonda",
    "tgn:placetype":[
        "aat:300008347"
    ]
},
  "bbox": [],
  "geometry": {"coordinates":[16.033333,39.95],"type":"Point"}
}