{
  "id": 2496262,
  "type": "Feature",
  "properties": {
    "tgn:hierarchy":[
        "tgn:2496262",
        "tgn:1000001",
        "tgn:7012149",
        "tgn:2001950",
        "tgn:7007826",
        "tgn:7029392"
    ],
    "tgn:id":2496262,
    "tgn:name":"Matagorda Island",
    "tgn:placetype":[
        "aat:300008791"
    ]
},
  "bbox": [],
  "geometry": {"coordinates":[-96.6333,28.2167],"type":"Point"}
}