{
  "id": 7449005,
  "type": "Feature",
  "properties": {
    "tgn:hierarchy":[
        "tgn:7449005",
        "tgn:7002445",
        "tgn:1000003",
        "tgn:7011430",
        "tgn:7008591",
        "tgn:7029392"
    ],
    "tgn:id":7449005,
    "tgn:name:en":"Rookley",
    "tgn:placetype":[
        "aat:300008347"
    ]
},
  "bbox": [],
  "geometry": {"coordinates":[-1.283333,50.65],"type":"Point"}
}