{
  "id": 7492994,
  "type": "Feature",
  "properties": {
    "tgn:hierarchy":[
        "tgn:7492994",
        "tgn:7001010",
        "tgn:1000004",
        "tgn:1000141",
        "tgn:7029392"
    ],
    "tgn:id":7492994,
    "tgn:name":"Nan Xi",
    "tgn:placetype":[
        "aat:300008699"
    ]
},
  "bbox": [],
  "geometry": {"coordinates":[121.23,23.140278],"type":"Point"}
}