{
  "id": 7219190,
  "type": "Feature",
  "properties": {
    "tgn:hierarchy":[
        "tgn:7219190",
        "tgn:7011170",
        "tgn:7002715",
        "tgn:1000003",
        "tgn:1000074",
        "tgn:7029392"
    ],
    "tgn:id":7219190,
    "tgn:name":"Vounoplayi\u00e1",
    "tgn:placetype":[
        "aat:300008347"
    ]
},
  "bbox": [],
  "geometry": {"coordinates":[24.533333,41.333333],"type":"Point"}
}