{
  "id": 7124570,
  "type": "Feature",
  "properties": {
    "tgn:hierarchy":[
        "tgn:7124570",
        "tgn:7003669",
        "tgn:1000003",
        "tgn:7000084",
        "tgn:7029392"
    ],
    "tgn:id":7124570,
    "tgn:name":"Niederding",
    "tgn:placetype":[
        "aat:300008347"
    ]
},
  "bbox": [],
  "geometry": {"coordinates":[11.85,48.316667],"type":"Point"}
}