{
  "id": 5002058,
  "type": "Feature",
  "properties": {
    "tgn:hierarchy":[
        "tgn:5002058",
        "tgn:7009084",
        "tgn:7004154",
        "tgn:1000003",
        "tgn:1000080",
        "tgn:7029392"
    ],
    "tgn:id":5002058,
    "tgn:name":"Caporciano",
    "tgn:placetype":[
        "aat:300008347"
    ]
},
  "bbox": [],
  "geometry": {"coordinates":[13.666,42.2333],"type":"Point"}
}