{
  "id": 7536603,
  "type": "Feature",
  "properties": {
    "tgn:hierarchy":[
        "tgn:7536603",
        "tgn:7001242",
        "tgn:7016833",
        "tgn:1001418",
        "tgn:7029392"
    ],
    "tgn:id":7536603,
    "tgn:name:en":"Giwai, Qaret el",
    "tgn:placetype":[
        "aat:300008777"
    ]
},
  "bbox": [],
  "geometry": {"coordinates":[26.022744,30.673104],"type":"Point"}
}