{
  "id": 7399072,
  "type": "Feature",
  "properties": {
    "tgn:hierarchy":[
        "tgn:7399072",
        "tgn:1000001",
        "tgn:1001893",
        "tgn:7005560",
        "tgn:7029392"
    ],
    "tgn:id":7399072,
    "tgn:name":"Cuadrilla Vieja",
    "tgn:placetype":[
        "aat:300008347"
    ]
},
  "bbox": [],
  "geometry": {"coordinates":[-99.998333,19.508056],"type":"Point"}
}