<<<<<<< HEAD
{
  "id": 2760633,
  "type": "Feature",
  "properties": {
    "tgn:hierarchy":[
        "tgn:2760633",
        "tgn:1000001",
        "tgn:7012149",
        "tgn:2000491",
        "tgn:7007250",
        "tgn:7029392"
    ],
    "tgn:id":2760633,
    "tgn:name":"West Fork Willow Creek",
    "tgn:placetype":[
        "aat:300008706"
    ]
},
  "bbox": [],
  "geometry": {"coordinates":[-115.7667,47.4333],"type":"Point"}
}
=======
{"geometry":{"type":"Point","coordinates":[-115.766700,47.433300]},"type":"Feature","properties":{"hierarchy":["tgn:2760633","tgn:1000001","tgn:7012149","tgn:2000491","tgn:7007250","tgn:7029392"],"placetype":["aat:300008706"],"id":2760633,"name:xx":"West Fork Willow Creek"}}
>>>>>>> 03f74aca74312dbeaf24d7e61306dd6a786dc3d0
