{
  "id": 7399151,
  "type": "Feature",
  "properties": {
    "tgn:hierarchy":[
        "tgn:7399151",
        "tgn:1000001",
        "tgn:1001893",
        "tgn:7005560",
        "tgn:7029392"
    ],
    "tgn:id":7399151,
    "tgn:name":"Laguna Seca",
    "tgn:placetype":[
        "aat:300008347"
    ]
},
  "bbox": [],
  "geometry": {"coordinates":[-99.999167,19.346389],"type":"Point"}
}