{
  "id": 7554517,
  "type": "Feature",
  "properties": {
    "tgn:hierarchy":[
        "tgn:7554517",
        "tgn:7001819",
        "tgn:1000004",
        "tgn:7000198",
        "tgn:7029392"
    ],
    "tgn:id":7554517,
    "tgn:name:en":"Noju",
    "tgn:placetype":[
        "aat:300008347"
    ]
},
  "bbox": [],
  "geometry": {"coordinates":[93.555407,27.24419],"type":"Point"}
}