{
  "id": 7579167,
  "type": "Feature",
  "properties": {
    "tgn:hierarchy":[
        "tgn:7579167",
        "tgn:1000004",
        "tgn:7000198",
        "tgn:7016788",
        "tgn:7029392"
    ],
    "tgn:id":7579167,
    "tgn:name:en":"Tarn\u0101u",
    "tgn:placetype":[
        "aat:300008347"
    ]
},
  "bbox": [],
  "geometry": {"coordinates":[74.127069,27.140572],"type":"Point"}
}