{
  "id": 7381166,
  "type": "Feature",
  "properties": {
    "tgn:hierarchy":[
        "tgn:7381166",
        "tgn:1000001",
        "tgn:7005591",
        "tgn:7005560",
        "tgn:7029392"
    ],
    "tgn:id":7381166,
    "tgn:name":"L\u00f3pez",
    "tgn:placetype":[
        "aat:300008347"
    ]
},
  "bbox": [],
  "geometry": {"coordinates":[-94.966667,16.45],"type":"Point"}
}