{
  "id": 7402329,
  "type": "Feature",
  "properties": {
    "tgn:hierarchy":[
        "tgn:7402329",
        "tgn:1000001",
        "tgn:1001937",
        "tgn:7005560",
        "tgn:7029392"
    ],
    "tgn:id":7402329,
    "tgn:name":"Holbox",
    "tgn:placetype":[
        "aat:300008347"
    ]
},
  "bbox": [],
  "geometry": {"coordinates":[-87.375,21.516667],"type":"Point"}
}