{
  "id": 2681131,
  "type": "Feature",
  "properties": {
    "tgn:hierarchy":[
        "tgn:2681131",
        "tgn:1000001",
        "tgn:1002461",
        "tgn:7012149",
        "tgn:7007159",
        "tgn:7029392"
    ],
    "tgn:id":2681131,
    "tgn:name":"South Mountain",
    "tgn:placetype":[
        "aat:300008798"
    ]
},
  "bbox": [],
  "geometry": {"coordinates":[-72.8167,41.55],"type":"Point"}
}