{
  "id": 2425384,
  "type": "Feature",
  "properties": {
    "tgn:hierarchy":[
        "tgn:2425384",
        "tgn:1000001",
        "tgn:7006451",
        "tgn:2000092",
        "tgn:7012149",
        "tgn:7029392"
    ],
    "tgn:id":2425384,
    "tgn:name":"Johnson Run",
    "tgn:placetype":[
        "aat:300008701"
    ]
},
  "bbox": [],
  "geometry": {"coordinates":[-112.4833,36.9167],"type":"Point"}
}