{
  "id": 2128867,
  "type": "Feature",
  "properties": {
    "tgn:hierarchy":[
        "tgn:2128867",
        "tgn:1000001",
        "tgn:7012149",
        "tgn:7007250",
        "tgn:7029392"
    ],
    "tgn:id":2128867,
    "tgn:name":"Alex Creek",
    "tgn:placetype":[
        "aat:300008706"
    ]
},
  "bbox": [],
  "geometry": {"coordinates":[-115.7333,45.1833],"type":"Point"}
}