<<<<<<< HEAD
{
  "id": 2258209,
  "type": "Feature",
  "properties": {
    "tgn:hierarchy":[
        "tgn:2258209",
        "tgn:1000001",
        "tgn:7012149",
        "tgn:2000885",
        "tgn:7007256",
        "tgn:7029392"
    ],
    "tgn:id":2258209,
    "tgn:name":"Coteau Bourgeois",
    "tgn:placetype":[
        "aat:300008347"
    ]
},
  "bbox": [],
  "geometry": {"coordinates":[-90.75,30.25],"type":"Point"}
}
=======
{"geometry":{"type":"Point","coordinates":[-90.750000,30.250000]},"type":"Feature","properties":{"hierarchy":["tgn:2258209","tgn:1000001","tgn:7012149","tgn:2000885","tgn:7007256","tgn:7029392"],"placetype":["aat:300008347"],"id":2258209,"name:xx":"Coteau Bourgeois"}}
>>>>>>> 03f74aca74312dbeaf24d7e61306dd6a786dc3d0
