{
  "id": 2645886,
  "type": "Feature",
  "properties": {
    "tgn:hierarchy":[
        "tgn:2645886",
        "tgn:1000001",
        "tgn:7012149",
        "tgn:7007158",
        "tgn:2000250",
        "tgn:7029392"
    ],
    "tgn:id":2645886,
    "tgn:name":"Sawmill Gulch",
    "tgn:placetype":[
        "aat:300008761"
    ]
},
  "bbox": [],
  "geometry": {"coordinates":[-106.0833,39.45],"type":"Point"}
}