{
  "id": 1095603,
  "type": "Feature",
  "properties": {
    "tgn:hierarchy":[
        "tgn:1095603",
        "tgn:7001242",
        "tgn:7016833",
        "tgn:1001088",
        "tgn:7029392"
    ],
    "tgn:id":1095603,
    "tgn:name:en":"Minb\u0101l",
    "tgn:placetype":[
        "aat:300008347"
    ]
},
  "bbox": [],
  "geometry": {"coordinates":[30.681667,28.408753],"type":"Point"}
}