{
  "id": 7334122,
  "type": "Feature",
  "properties": {
    "tgn:hierarchy":[
        "tgn:7334122",
        "tgn:7002760",
        "tgn:1000003",
        "tgn:1000095",
        "tgn:7029392"
    ],
    "tgn:id":7334122,
    "tgn:name":"El Tejo",
    "tgn:placetype":[
        "aat:300008347"
    ]
},
  "bbox": [],
  "geometry": {"coordinates":[-4.316667,43.383333],"type":"Point"}
}