{
  "id": 2733787,
  "type": "Feature",
  "properties": {
    "tgn:hierarchy":[
        "tgn:2733787",
        "tgn:2001087",
        "tgn:1000001",
        "tgn:7012149",
        "tgn:7007522",
        "tgn:7029392"
    ],
    "tgn:id":2733787,
    "tgn:name":"Turner Creek",
    "tgn:placetype":[
        "aat:300008706"
    ]
},
  "bbox": [],
  "geometry": {"coordinates":[-88.5333,34.9667],"type":"Point"}
}