{
  "id": 7287513,
  "type": "Feature",
  "properties": {
    "tgn:hierarchy":[
        "tgn:7287513",
        "tgn:1001702",
        "tgn:1000049",
        "tgn:1000002",
        "tgn:7029392"
    ],
    "tgn:id":7287513,
    "tgn:name":"Gallant, Caleta",
    "tgn:placetype":[
        "aat:300008678"
    ]
},
  "bbox": [],
  "geometry": {"coordinates":[-71.966667,-53.666667],"type":"Point"}
}