{
  "id": 2335338,
  "type": "Feature",
  "properties": {
    "tgn:hierarchy":[
        "tgn:2335338",
        "tgn:1000001",
        "tgn:7012149",
        "tgn:2002087",
        "tgn:7007826",
        "tgn:7029392"
    ],
    "tgn:id":2335338,
    "tgn:name":"Fort Inge",
    "tgn:placetype":[
        "aat:300008347"
    ]
},
  "bbox": [],
  "geometry": {"coordinates":[-99.75,29.1667],"type":"Point"}
}