<<<<<<< HEAD
{
  "id": 2335338,
  "type": "Feature",
  "properties": {
    "tgn:hierarchy":[
        "tgn:2335338",
        "tgn:1000001",
        "tgn:7012149",
        "tgn:2002087",
        "tgn:7007826",
        "tgn:7029392"
    ],
    "tgn:id":2335338,
    "tgn:name":"Fort Inge",
    "tgn:placetype":[
        "aat:300008347"
    ]
},
  "bbox": [],
  "geometry": {"coordinates":[-99.75,29.1667],"type":"Point"}
}
=======
{"geometry":{"type":"Point","coordinates":[-99.750000,29.166700]},"type":"Feature","properties":{"hierarchy":["tgn:2335338","tgn:1000001","tgn:7012149","tgn:2002087","tgn:7007826","tgn:7029392"],"placetype":["aat:300008347"],"id":2335338,"name:xx":"Fort Inge"}}
>>>>>>> 03f74aca74312dbeaf24d7e61306dd6a786dc3d0
