{
  "id": 7157525,
  "type": "Feature",
  "properties": {
    "tgn:hierarchy":[
        "tgn:7157525",
        "tgn:1000003",
        "tgn:7003688",
        "tgn:7000084",
        "tgn:7029392"
    ],
    "tgn:id":7157525,
    "tgn:name":"Kitzeberg",
    "tgn:placetype":[
        "aat:300008347"
    ]
},
  "bbox": [],
  "geometry": {"coordinates":[10.183333,54.366667],"type":"Point"}
}