{
  "id": 2171333,
  "type": "Feature",
  "properties": {
    "tgn:hierarchy":[
        "tgn:2171333",
        "tgn:1000001",
        "tgn:7012149",
        "tgn:1002779",
        "tgn:7007710",
        "tgn:7029392"
    ],
    "tgn:id":2171333,
    "tgn:name":"Big Spring Run",
    "tgn:placetype":[
        "aat:300008699"
    ]
},
  "bbox": [],
  "geometry": {"coordinates":[-77.65,40.25],"type":"Point"}
}