{
  "id": 7454306,
  "type": "Feature",
  "properties": {
    "tgn:hierarchy":[
        "tgn:7454306",
        "tgn:5000432",
        "tgn:7002444",
        "tgn:1000003",
        "tgn:7008591",
        "tgn:7029392"
    ],
    "tgn:id":7454306,
    "tgn:name:en":"Deecastle",
    "tgn:placetype":[
        "aat:300387502"
    ]
},
  "bbox": [],
  "geometry": {"coordinates":[-2.933333,57.066667],"type":"Point"}
}