{
  "id": 2468448,
  "type": "Feature",
  "properties": {
    "tgn:hierarchy":[
        "tgn:2468448",
        "tgn:1000001",
        "tgn:7012149",
        "tgn:2001455",
        "tgn:7007566",
        "tgn:7029392"
    ],
    "tgn:id":2468448,
    "tgn:name":"Long Point",
    "tgn:placetype":[
        "aat:300008850"
    ]
},
  "bbox": [],
  "geometry": {"coordinates":[-107.1833,33.2333],"type":"Point"}
}