{
  "id": 7526706,
  "type": "Feature",
  "properties": {
    "tgn:hierarchy":[
        "tgn:7526706",
        "tgn:7001242",
        "tgn:7016833",
        "tgn:1001418",
        "tgn:7029392"
    ],
    "tgn:id":7526706,
    "tgn:name:en":"Wasihka",
    "tgn:placetype":[
        "aat:300055621"
    ]
},
  "bbox": [],
  "geometry": {"coordinates":[26.716667,28.85],"type":"Point"}
}