{
  "id": 2193782,
  "type": "Feature",
  "properties": {
    "tgn:hierarchy":[
        "tgn:2193782",
        "tgn:1000001",
        "tgn:7012149",
        "tgn:7007922",
        "tgn:7029392"
    ],
    "tgn:id":2193782,
    "tgn:name":"Brey Valley",
    "tgn:placetype":[
        "aat:300008761"
    ]
},
  "bbox": [],
  "geometry": {"coordinates":[-90.5167,43.7333],"type":"Point"}
}