{
  "id": 7236102,
  "type": "Feature",
  "properties": {
    "tgn:hierarchy":[
        "tgn:7236102",
        "tgn:7011270",
        "tgn:7002674",
        "tgn:1000003",
        "tgn:1000074",
        "tgn:7029392"
    ],
    "tgn:id":7236102,
    "tgn:name":"\u00c9vros, \u00c1kra",
    "tgn:placetype":[
        "aat:300008850"
    ]
},
  "bbox": [],
  "geometry": {"coordinates":[25.466667,37.466667],"type":"Point"}
}