{
  "id": 2399826,
  "type": "Feature",
  "properties": {
    "tgn:hierarchy":[
        "tgn:2399826",
        "tgn:1000001",
        "tgn:2001703",
        "tgn:7012149",
        "tgn:7007708",
        "tgn:7029392"
    ],
    "tgn:id":2399826,
    "tgn:name":"Horse Butte",
    "tgn:placetype":[
        "aat:300008798"
    ]
},
  "bbox": [],
  "geometry": {"coordinates":[-120.8667,44.05],"type":"Point"}
}