{
  "id": 7056507,
  "type": "Feature",
  "properties": {
    "tgn:hierarchy":[
        "tgn:7056507",
        "tgn:7005869",
        "tgn:1000003",
        "tgn:7003237",
        "tgn:1000080",
        "tgn:7029392"
    ],
    "tgn:id":7056507,
    "tgn:name":"Binanuova",
    "tgn:placetype":[
        "aat:300008347"
    ]
},
  "bbox": [],
  "geometry": {"coordinates":[10.166667,45.233333],"type":"Point"}
}