{
  "id": 2743750,
  "type": "Feature",
  "properties": {
    "tgn:hierarchy":[
        "tgn:2743750",
        "tgn:1000001",
        "tgn:2000541",
        "tgn:7012149",
        "tgn:7007252",
        "tgn:7029392"
    ],
    "tgn:id":2743750,
    "tgn:name":"Veale Creek",
    "tgn:placetype":[
        "aat:300008706"
    ]
},
  "bbox": [],
  "geometry": {"coordinates":[-87.0167,38.6167],"type":"Point"}
}