{
  "id": 7470298,
  "type": "Feature",
  "properties": {
    "tgn:hierarchy":[
        "tgn:7470298",
        "tgn:7468018",
        "tgn:1000004",
        "tgn:1000141",
        "tgn:7029392"
    ],
    "tgn:id":7470298,
    "tgn:name":"Zhushan",
    "tgn:placetype":[
        "aat:300008347"
    ]
},
  "bbox": [],
  "geometry": {"coordinates":[120.518987,23.455812],"type":"Point"}
}