{
  "id": 7543911,
  "type": "Feature",
  "properties": {
    "tgn:hierarchy":[
        "tgn:7543911",
        "tgn:7001242",
        "tgn:7016833",
        "tgn:1001079",
        "tgn:7029392"
    ],
    "tgn:id":7543911,
    "tgn:name:en":"Tir'at an Na\u015fr",
    "tgn:placetype":[
        "aat:300006075"
    ]
},
  "bbox": [],
  "geometry": {"coordinates":[29.772273,30.982325],"type":"Point"}
}