{
  "id": 2229091,
  "type": "Feature",
  "properties": {
    "tgn:hierarchy":[
        "tgn:2229091",
        "tgn:1000001",
        "tgn:1002174",
        "tgn:7012149",
        "tgn:7007826",
        "tgn:7029392"
    ],
    "tgn:id":2229091,
    "tgn:name":"Cedar Knob",
    "tgn:placetype":[
        "aat:300008798"
    ]
},
  "bbox": [],
  "geometry": {"coordinates":[-97.6333,30.9833],"type":"Point"}
}