{
  "id": 2701461,
  "type": "Feature",
  "properties": {
    "tgn:hierarchy":[
        "tgn:2701461",
        "tgn:1000001",
        "tgn:7012149",
        "tgn:2002304",
        "tgn:7013961",
        "tgn:7029392"
    ],
    "tgn:id":2701461,
    "tgn:name":"Sugar Run",
    "tgn:placetype":[
        "aat:300008699"
    ]
},
  "bbox": [],
  "geometry": {"coordinates":[-81.4667,37.5833],"type":"Point"}
}