{
  "id": 7587283,
  "type": "Feature",
  "properties": {
    "tgn:hierarchy":[
        "tgn:7587283",
        "tgn:1000004",
        "tgn:1001832",
        "tgn:7000198",
        "tgn:7029392"
    ],
    "tgn:id":7587283,
    "tgn:name:en":"Kaiphundai",
    "tgn:placetype":[
        "aat:300008347"
    ]
},
  "bbox": [],
  "geometry": {"coordinates":[93.218589,24.788491],"type":"Point"}
}