{
  "id": 7421217,
  "type": "Feature",
  "properties": {
    "tgn:hierarchy":[
        "tgn:7421217",
        "tgn:1000001",
        "tgn:7005589",
        "tgn:7005560",
        "tgn:7029392"
    ],
    "tgn:id":7421217,
    "tgn:name:es":"Las Hormigas",
    "tgn:placetype":[
        "aat:300008347"
    ]
},
  "bbox": [],
  "geometry": {"coordinates":[-98.658333,25.449167],"type":"Point"}
}