{
  "id": 2213559,
  "type": "Feature",
  "properties": {
    "tgn:hierarchy":[
        "tgn:2213559",
        "tgn:1000001",
        "tgn:7012149",
        "tgn:1002576",
        "tgn:7007520",
        "tgn:7029392"
    ],
    "tgn:id":2213559,
    "tgn:name":"Cable Drain",
    "tgn:placetype":[
        "aat:300006075"
    ]
},
  "bbox": [],
  "geometry": {"coordinates":[-83.25,43.2833],"type":"Point"}
}