{
  "id": 2365968,
  "type": "Feature",
  "properties": {
    "tgn:hierarchy":[
        "tgn:2365968",
        "tgn:1000001",
        "tgn:2001841",
        "tgn:7012149",
        "tgn:7007825",
        "tgn:7029392"
    ],
    "tgn:id":2365968,
    "tgn:name":"Grey Ridge",
    "tgn:placetype":[
        "aat:300266640"
    ]
},
  "bbox": [],
  "geometry": {"coordinates":[-84.05,35.7667],"type":"Point"}
}