{
  "id": 7493189,
  "type": "Feature",
  "properties": {
    "tgn:hierarchy":[
        "tgn:7493189",
        "tgn:7468018",
        "tgn:1000004",
        "tgn:1000141",
        "tgn:7029392"
    ],
    "tgn:id":7493189,
    "tgn:name":"Yeziliao Xi",
    "tgn:placetype":[
        "aat:300008699"
    ]
},
  "bbox": [],
  "geometry": {"coordinates":[120.475131,23.5777],"type":"Point"}
}