{
  "id": 1116976,
  "type": "Feature",
  "properties": {
    "tgn:hierarchy":[
        "tgn:1116976",
        "tgn:7005735",
        "tgn:7005685",
        "tgn:1000001",
        "tgn:7029392"
    ],
    "tgn:id":1116976,
    "tgn:name":"Lanezi Lake",
    "tgn:placetype":[
        "aat:300008680"
    ]
},
  "bbox": [],
  "geometry": {"coordinates":[-120.9333,53.05],"type":"Point"}
}