{
  "id": 7566620,
  "type": "Feature",
  "properties": {
    "tgn:hierarchy":[
        "tgn:7566620",
        "tgn:1000004",
        "tgn:7000198",
        "tgn:7016722",
        "tgn:7029392"
    ],
    "tgn:id":7566620,
    "tgn:name:en":"Naw\u0101da Jamni",
    "tgn:placetype":[
        "aat:300008347"
    ]
},
  "bbox": [],
  "geometry": {"coordinates":[79.785457,26.671911],"type":"Point"}
}