{
  "id": 7130970,
  "type": "Feature",
  "properties": {
    "tgn:hierarchy":[
        "tgn:7130970",
        "tgn:7003692",
        "tgn:1000003",
        "tgn:7000084",
        "tgn:7029392"
    ],
    "tgn:id":7130970,
    "tgn:name":"Mehlishofen",
    "tgn:placetype":[
        "aat:300000206"
    ]
},
  "bbox": [],
  "geometry": {"coordinates":[9.583333,47.85],"type":"Point"}
}