{
  "id": 2263149,
  "type": "Feature",
  "properties": {
    "tgn:hierarchy":[
        "tgn:2263149",
        "tgn:1000001",
        "tgn:7012149",
        "tgn:7007712",
        "tgn:7029392"
    ],
    "tgn:id":2263149,
    "tgn:name":"Cowpen Swamp",
    "tgn:placetype":[
        "aat:300008699"
    ]
},
  "bbox": [],
  "geometry": {"coordinates":[-80.3833,34.1167],"type":"Point"}
}