{
  "id": 2682374,
  "type": "Feature",
  "properties": {
    "tgn:hierarchy":[
        "tgn:2682374",
        "tgn:1000001",
        "tgn:7012149",
        "tgn:2000560",
        "tgn:7007252",
        "tgn:7029392"
    ],
    "tgn:id":2682374,
    "tgn:name":"South Willow Pond Ditch",
    "tgn:placetype":[
        "aat:300006075"
    ]
},
  "bbox": [],
  "geometry": {"coordinates":[-87.4333,37.95],"type":"Point"}
}