{
  "id": 2037410,
  "type": "Feature",
  "properties": {
    "tgn:hierarchy":[
        "tgn:2037410",
        "tgn:1000001",
        "tgn:7012149",
        "tgn:2000763",
        "tgn:7007254",
        "tgn:7029392"
    ],
    "tgn:id":2037410,
    "tgn:name":"Yates Center",
    "tgn:placetype":[
        "aat:300008347"
    ]
},
  "bbox": [],
  "geometry": {"coordinates":[-95.7167,37.8667],"type":"Point"}
}