<<<<<<< HEAD
{
  "id": 2761181,
  "type": "Feature",
  "properties": {
    "tgn:hierarchy":[
        "tgn:2761181",
        "tgn:1000001",
        "tgn:2001409",
        "tgn:7012149",
        "tgn:7007526",
        "tgn:7029392"
    ],
    "tgn:id":2761181,
    "tgn:name":"West Lee Drain",
    "tgn:placetype":[
        "aat:300006075"
    ]
},
  "bbox": [],
  "geometry": {"coordinates":[-118.7167,39.3333],"type":"Point"}
}
=======
{"geometry":{"type":"Point","coordinates":[-118.716700,39.333300]},"type":"Feature","properties":{"hierarchy":["tgn:2761181","tgn:1000001","tgn:2001409","tgn:7012149","tgn:7007526","tgn:7029392"],"placetype":["aat:300006075"],"id":2761181,"name:xx":"West Lee Drain"}}
>>>>>>> 03f74aca74312dbeaf24d7e61306dd6a786dc3d0
