{
  "id": 7590856,
  "type": "Feature",
  "properties": {
    "tgn:hierarchy":[
        "tgn:7590856",
        "tgn:1000004",
        "tgn:7000198",
        "tgn:7000799",
        "tgn:7029392"
    ],
    "tgn:id":7590856,
    "tgn:name:en":"Sh\u012bn Mahinyu",
    "tgn:placetype":[
        "aat:300008795"
    ]
},
  "bbox": [],
  "geometry": {"coordinates":[74.431238,33.904781],"type":"Point"}
}