<<<<<<< HEAD
{
  "id": 2153996,
  "type": "Feature",
  "properties": {
    "tgn:hierarchy":[
        "tgn:2153996",
        "tgn:1000001",
        "tgn:2000108",
        "tgn:7016172",
        "tgn:7012149",
        "tgn:7029392"
    ],
    "tgn:id":2153996,
    "tgn:name":"Bear Creek",
    "tgn:placetype":[
        "aat:300008706"
    ]
},
  "bbox": [],
  "geometry": {"coordinates":[-94.05,36.3333],"type":"Point"}
}
=======
{"geometry":{"type":"Point","coordinates":[-94.050000,36.333300]},"type":"Feature","properties":{"hierarchy":["tgn:2153996","tgn:1000001","tgn:2000108","tgn:7016172","tgn:7012149","tgn:7029392"],"placetype":["aat:300008706"],"id":2153996,"name:xx":"Bear Creek"}}
>>>>>>> 03f74aca74312dbeaf24d7e61306dd6a786dc3d0
