{
  "id": 7257414,
  "type": "Feature",
  "properties": {
    "tgn:hierarchy":[
        "tgn:7257414",
        "tgn:7593113",
        "tgn:7016620",
        "tgn:7593112",
        "tgn:1000001",
        "tgn:7029392"
    ],
    "tgn:id":7257414,
    "tgn:name:nl":"San Jos\u00e9",
    "tgn:placetype":[
        "aat:300387200"
    ]
},
  "bbox": [],
  "geometry": {"coordinates":[-68.233333,12.116667],"type":"Point"}
}