<<<<<<< HEAD
{
  "id": 7350743,
  "type": "Feature",
  "properties": {
    "tgn:hierarchy":[
        "tgn:7350743",
        "tgn:1001835",
        "tgn:1000001",
        "tgn:7005560",
        "tgn:7029392"
    ],
    "tgn:id":7350743,
    "tgn:name":"Blanco, Pe\u00f1asco",
    "tgn:placetype":[
        "aat:300008777"
    ]
},
  "bbox": [],
  "geometry": {"coordinates":[-116.633333,32.466667],"type":"Point"}
}
=======
{"geometry":{"type":"Point","coordinates":[-116.633333,32.466667]},"type":"Feature","properties":{"hierarchy":["tgn:7350743","tgn:1001835","tgn:1000001","tgn:7005560","tgn:7029392"],"placetype":["aat:300008777"],"id":7350743,"name:xx":"Blanco, Pe\u00f1asco"}}
>>>>>>> 03f74aca74312dbeaf24d7e61306dd6a786dc3d0
