{
  "id": 7157943,
  "type": "Feature",
  "properties": {
    "tgn:hierarchy":[
        "tgn:7157943",
        "tgn:7003669",
        "tgn:1000003",
        "tgn:7000084",
        "tgn:7029392"
    ],
    "tgn:id":7157943,
    "tgn:name":"Kirschfurt",
    "tgn:placetype":[
        "aat:300008347"
    ]
},
  "bbox": [],
  "geometry": {"coordinates":[9.318056,49.743611],"type":"Point"}
}