{
  "id": 7571455,
  "type": "Feature",
  "properties": {
    "tgn:hierarchy":[
        "tgn:7571455",
        "tgn:1000004",
        "tgn:7000198",
        "tgn:1001895",
        "tgn:7029392"
    ],
    "tgn:id":7571455,
    "tgn:name:en":"H\u0101tgarh",
    "tgn:placetype":[
        "aat:300008347"
    ]
},
  "bbox": [],
  "geometry": {"coordinates":[73.75,20.533333],"type":"Point"}
}