{
  "id": 2425645,
  "type": "Feature",
  "properties": {
    "tgn:hierarchy":[
        "tgn:2425645",
        "tgn:1000001",
        "tgn:2000955",
        "tgn:7012149",
        "tgn:7007520",
        "tgn:7029392"
    ],
    "tgn:id":2425645,
    "tgn:name":"Johnston Creek",
    "tgn:placetype":[
        "aat:300008706"
    ]
},
  "bbox": [],
  "geometry": {"coordinates":[-86.85,45.8833],"type":"Point"}
}