{
  "id": 2579833,
  "type": "Feature",
  "properties": {
    "tgn:hierarchy":[
        "tgn:2579833",
        "tgn:1000001",
        "tgn:7006451",
        "tgn:2000093",
        "tgn:7012149",
        "tgn:7029392"
    ],
    "tgn:id":2579833,
    "tgn:name":"Picture Mountain",
    "tgn:placetype":[
        "aat:300008798"
    ]
},
  "bbox": [],
  "geometry": {"coordinates":[-111.15,33.9167],"type":"Point"}
}