{
  "id": 1095765,
  "type": "Feature",
  "properties": {
    "tgn:hierarchy":[
        "tgn:1095765",
        "tgn:7001242",
        "tgn:7016833",
        "tgn:1001088",
        "tgn:7029392"
    ],
    "tgn:id":1095765,
    "tgn:name":"Z\u0101wiyat al Judh\u0101m\u012b",
    "tgn:placetype":[
        "aat:300008347"
    ]
},
  "bbox": [],
  "geometry": {"coordinates":[30.90046,28.707335],"type":"Point"}
}