{
  "id": 7347236,
  "type": "Feature",
  "properties": {
    "tgn:hierarchy":[
        "tgn:7347236",
        "tgn:7002808",
        "tgn:7030216",
        "tgn:1000003",
        "tgn:1000095",
        "tgn:7029392"
    ],
    "tgn:id":7347236,
    "tgn:name":"Ba\u00f1eras",
    "tgn:placetype":[
        "aat:300008347"
    ]
},
  "bbox": [],
  "geometry": {"coordinates":[1.581446,41.279799],"type":"Point"}
}