{
  "id": 1083242,
  "type": "Feature",
  "properties": {
    "tgn:hierarchy":[
        "tgn:1083242",
        "tgn:1000004",
        "tgn:7004497",
        "tgn:1000131",
        "tgn:7029392"
    ],
    "tgn:id":1083242,
    "tgn:name":"Fins",
    "tgn:placetype":[
        "aat:300008347"
    ]
},
  "bbox": [],
  "geometry": {"coordinates":[59.2167,22.9333],"type":"Point"}
}