{
  "id": 7305689,
  "type": "Feature",
  "properties": {
    "tgn:hierarchy":[
        "tgn:7305689",
        "tgn:7002758",
        "tgn:7002821",
        "tgn:1000003",
        "tgn:1000095",
        "tgn:7029392"
    ],
    "tgn:id":7305689,
    "tgn:name":"Las Fuentezuelas",
    "tgn:placetype":[
        "aat:300008347"
    ]
},
  "bbox": [],
  "geometry": {"coordinates":[-3.266667,36.966667],"type":"Point"}
}