{
  "id": 2504899,
  "type": "Feature",
  "properties": {
    "tgn:hierarchy":[
        "tgn:2504899",
        "tgn:1000001",
        "tgn:7012149",
        "tgn:2002170",
        "tgn:7007919",
        "tgn:7029392"
    ],
    "tgn:id":2504899,
    "tgn:name":"Medlock",
    "tgn:placetype":[
        "aat:300008347"
    ]
},
  "bbox": [],
  "geometry": {"coordinates":[-78.15,38.0167],"type":"Point"}
}