{
  "id": 2077203,
  "type": "Feature",
  "properties": {
    "tgn:hierarchy":[
        "tgn:2077203",
        "tgn:1000001",
        "tgn:7012149",
        "tgn:2001509",
        "tgn:7007709",
        "tgn:7029392"
    ],
    "tgn:id":2077203,
    "tgn:name":"Whitley Heights",
    "tgn:placetype":[
        "aat:300008347"
    ]
},
  "bbox": [],
  "geometry": {"coordinates":[-78.3833,35.55],"type":"Point"}
}