{
  "id": 1075759,
  "type": "Feature",
  "properties": {
    "tgn:hierarchy":[
        "tgn:1075759",
        "tgn:1000004",
        "tgn:7000198",
        "tgn:7001797",
        "tgn:7029392"
    ],
    "tgn:id":1075759,
    "tgn:name":"Karur",
    "tgn:placetype":[
        "aat:300008347"
    ]
},
  "bbox": [],
  "geometry": {"coordinates":[78.083333,10.95],"type":"Point"}
}