{
  "id": 2125419,
  "type": "Feature",
  "properties": {
    "tgn:hierarchy":[
        "tgn:2125419",
        "tgn:1000001",
        "tgn:7012149",
        "tgn:1002977",
        "tgn:7007240",
        "tgn:7029392"
    ],
    "tgn:id":2125419,
    "tgn:name":"Acorn Fish Lake",
    "tgn:placetype":[
        "aat:300008680"
    ]
},
  "bbox": [],
  "geometry": {"coordinates":[-81.1333,28.8667],"type":"Point"}
}