<<<<<<< HEAD
{
  "id": 7361016,
  "type": "Feature",
  "properties": {
    "tgn:hierarchy":[
        "tgn:7361016",
        "tgn:7005581",
        "tgn:1000001",
        "tgn:7005560",
        "tgn:7029392"
    ],
    "tgn:id":7361016,
    "tgn:name":"El Nogal Y Anexas",
    "tgn:placetype":[
        "aat:300008347"
    ]
},
  "bbox": [],
  "geometry": {"coordinates":[-107.066667,28.35],"type":"Point"}
}
=======
{"geometry":{"type":"Point","coordinates":[-107.066667,28.350000]},"type":"Feature","properties":{"hierarchy":["tgn:7361016","tgn:7005581","tgn:1000001","tgn:7005560","tgn:7029392"],"placetype":["aat:300008347"],"id":7361016,"name:xx":"El Nogal Y Anexas"}}
>>>>>>> 03f74aca74312dbeaf24d7e61306dd6a786dc3d0
