<<<<<<< HEAD
{
  "id": 7361825,
  "type": "Feature",
  "properties": {
    "tgn:hierarchy":[
        "tgn:7361825",
        "tgn:7005586",
        "tgn:1000001",
        "tgn:7005560",
        "tgn:7029392"
    ],
    "tgn:id":7361825,
    "tgn:name":"El Laurel",
    "tgn:placetype":[
        "aat:300000241"
    ]
},
  "bbox": [],
  "geometry": {"coordinates":[-102.85,19.816667],"type":"Point"}
}
=======
{"geometry":{"type":"Point","coordinates":[-102.850000,19.816667]},"type":"Feature","properties":{"hierarchy":["tgn:7361825","tgn:7005586","tgn:1000001","tgn:7005560","tgn:7029392"],"placetype":["aat:300000241"],"id":7361825,"name:xx":"El Laurel"}}
>>>>>>> 03f74aca74312dbeaf24d7e61306dd6a786dc3d0
