{
  "id": 7072787,
  "type": "Feature",
  "properties": {
    "tgn:hierarchy":[
        "tgn:7072787",
        "tgn:7000096",
        "tgn:1000003",
        "tgn:7000084",
        "tgn:7029392"
    ],
    "tgn:id":7072787,
    "tgn:name":"Striesow",
    "tgn:placetype":[
        "aat:300008347"
    ]
},
  "bbox": [],
  "geometry": {"coordinates":[14.266667,51.816667],"type":"Point"}
}