<<<<<<< HEAD
{
  "id": 7358490,
  "type": "Feature",
  "properties": {
    "tgn:hierarchy":[
        "tgn:7358490",
        "tgn:7005581",
        "tgn:1000001",
        "tgn:7005560",
        "tgn:7029392"
    ],
    "tgn:id":7358490,
    "tgn:name":"Colorada, Laguna",
    "tgn:placetype":[
        "aat:300008680"
    ]
},
  "bbox": [],
  "geometry": {"coordinates":[-105.116667,27.983333],"type":"Point"}
}
=======
{"geometry":{"type":"Point","coordinates":[-105.116667,27.983333]},"type":"Feature","properties":{"hierarchy":["tgn:7358490","tgn:7005581","tgn:1000001","tgn:7005560","tgn:7029392"],"placetype":["aat:300008680"],"id":7358490,"name:xx":"Colorada, Laguna"}}
>>>>>>> 03f74aca74312dbeaf24d7e61306dd6a786dc3d0
