{
  "id": 2428722,
  "type": "Feature",
  "properties": {
    "tgn:hierarchy":[
        "tgn:2428722",
        "tgn:1000001",
        "tgn:7012149",
        "tgn:2000386",
        "tgn:7007248",
        "tgn:7029392"
    ],
    "tgn:id":2428722,
    "tgn:name":"Julienton River",
    "tgn:placetype":[
        "aat:300008707"
    ]
},
  "bbox": [],
  "geometry": {"coordinates":[-81.3167,31.6167],"type":"Point"}
}