<<<<<<< HEAD
{
  "id": 2407561,
  "type": "Feature",
  "properties": {
    "tgn:hierarchy":[
        "tgn:2407561",
        "tgn:7002659",
        "tgn:1000001",
        "tgn:7012149",
        "tgn:2000044",
        "tgn:7029392"
    ],
    "tgn:id":2407561,
    "tgn:name":"Huntsville Spring Branch",
    "tgn:placetype":[
        "aat:300008699"
    ]
},
  "bbox": [],
  "geometry": {"coordinates":[-86.6,34.7333],"type":"Point"}
}
=======
{"geometry":{"type":"Point","coordinates":[-86.600000,34.733300]},"type":"Feature","properties":{"hierarchy":["tgn:2407561","tgn:7002659","tgn:1000001","tgn:7012149","tgn:2000044","tgn:7029392"],"placetype":["aat:300008699"],"id":2407561,"name:xx":"Huntsville Spring Branch"}}
>>>>>>> 03f74aca74312dbeaf24d7e61306dd6a786dc3d0
