{
  "id": 7109449,
  "type": "Feature",
  "properties": {
    "tgn:hierarchy":[
        "tgn:7109449",
        "tgn:7003669",
        "tgn:1000003",
        "tgn:7000084",
        "tgn:7029392"
    ],
    "tgn:id":7109449,
    "tgn:name":"Randling",
    "tgn:placetype":[
        "aat:300008347"
    ]
},
  "bbox": [],
  "geometry": {"coordinates":[12.483333,48.05],"type":"Point"}
}