{
  "id": 2606024,
  "type": "Feature",
  "properties": {
    "tgn:hierarchy":[
        "tgn:2606024",
        "tgn:1000001",
        "tgn:7012149",
        "tgn:2000494",
        "tgn:7007250",
        "tgn:7029392"
    ],
    "tgn:id":2606024,
    "tgn:name":"Rainbow Spring",
    "tgn:placetype":[
        "aat:300008697"
    ]
},
  "bbox": [],
  "geometry": {"coordinates":[-115.6167,44.9667],"type":"Point"}
}