<<<<<<< HEAD
{
  "id": 2257135,
  "type": "Feature",
  "properties": {
    "tgn:hierarchy":[
        "tgn:2257135",
        "tgn:1000001",
        "tgn:7012149",
        "tgn:7007157",
        "tgn:1002956",
        "tgn:7029392"
    ],
    "tgn:id":2257135,
    "tgn:name":"Corner Creek",
    "tgn:placetype":[
        "aat:300008706"
    ]
},
  "bbox": [],
  "geometry": {"coordinates":[-118.6667,36.4],"type":"Point"}
}
=======
{"geometry":{"type":"Point","coordinates":[-118.666700,36.400000]},"type":"Feature","properties":{"hierarchy":["tgn:2257135","tgn:1000001","tgn:7012149","tgn:7007157","tgn:1002956","tgn:7029392"],"placetype":["aat:300008706"],"id":2257135,"name:xx":"Corner Creek"}}
>>>>>>> 03f74aca74312dbeaf24d7e61306dd6a786dc3d0
