{
  "id": 2473159,
  "type": "Feature",
  "properties": {
    "tgn:hierarchy":[
        "tgn:2473159",
        "tgn:1000001",
        "tgn:7012149",
        "tgn:7007828",
        "tgn:7029392"
    ],
    "tgn:id":2473159,
    "tgn:name":"Lowell Mountains",
    "tgn:placetype":[
        "aat:300386831"
    ]
},
  "bbox": [],
  "geometry": {"coordinates":[-72.3833,44.7667],"type":"Point"}
}