<<<<<<< HEAD
{
  "id": 7353779,
  "type": "Feature",
  "properties": {
    "tgn:hierarchy":[
        "tgn:7353779",
        "tgn:1000001",
        "tgn:7005589",
        "tgn:7005560",
        "tgn:7029392"
    ],
    "tgn:id":7353779,
    "tgn:name":"Antojo Allende",
    "tgn:placetype":[
        "aat:300008347"
    ]
},
  "bbox": [],
  "geometry": {"coordinates":[-99.983333,25.35],"type":"Point"}
}
=======
{"geometry":{"type":"Point","coordinates":[-99.983333,25.350000]},"type":"Feature","properties":{"hierarchy":["tgn:7353779","tgn:1000001","tgn:7005589","tgn:7005560","tgn:7029392"],"placetype":["aat:300008347"],"id":7353779,"name:xx":"Antojo Allende"}}
>>>>>>> 03f74aca74312dbeaf24d7e61306dd6a786dc3d0
