{
  "id": 7240198,
  "type": "Feature",
  "properties": {
    "tgn:hierarchy":[
        "tgn:7240198",
        "tgn:7003457",
        "tgn:1000003",
        "tgn:1000063",
        "tgn:7018236",
        "tgn:7029392"
    ],
    "tgn:id":7240198,
    "tgn:name":"Eindeken",
    "tgn:placetype":[
        "aat:300008347"
    ]
},
  "bbox": [],
  "geometry": {"coordinates":[3.991265,51.14366],"type":"Point"}
}