{
  "id": 7515464,
  "type": "Feature",
  "properties": {
    "tgn:hierarchy":[
        "tgn:7515464",
        "tgn:1009227",
        "tgn:1000226",
        "tgn:7016822",
        "tgn:1000006",
        "tgn:7029392"
    ],
    "tgn:id":7515464,
    "tgn:name:en":"Onoua",
    "tgn:placetype":[
        "aat:300386846"
    ]
},
  "bbox": [],
  "geometry": {"coordinates":[-176.233333,-44.233333],"type":"Point"}
}