{
  "id": 7051122,
  "type": "Feature",
  "properties": {
    "tgn:hierarchy":[
        "tgn:7051122",
        "tgn:1003440",
        "tgn:1000003",
        "tgn:7003124",
        "tgn:1000080",
        "tgn:7029392"
    ],
    "tgn:id":7051122,
    "tgn:name":"Schwarzenstein",
    "tgn:placetype":[
        "aat:300008795"
    ]
},
  "bbox": [],
  "geometry": {"coordinates":[11.866667,47.016667],"type":"Point"}
}