{
  "id": 2346092,
  "type": "Feature",
  "properties": {
    "tgn:hierarchy":[
        "tgn:2346092",
        "tgn:1000001",
        "tgn:7012149",
        "tgn:2001511",
        "tgn:7007709",
        "tgn:7029392"
    ],
    "tgn:id":2346092,
    "tgn:name":"Gasters Creek",
    "tgn:placetype":[
        "aat:300008706"
    ]
},
  "bbox": [],
  "geometry": {"coordinates":[-79.15,35.4333],"type":"Point"}
}