{
  "id": 2594851,
  "type": "Feature",
  "properties": {
    "tgn:hierarchy":[
        "tgn:2594851",
        "tgn:1000001",
        "tgn:7012149",
        "tgn:7014589",
        "tgn:7007515",
        "tgn:7029392"
    ],
    "tgn:id":2594851,
    "tgn:name":"Possum Lake",
    "tgn:placetype":[
        "aat:300008680"
    ]
},
  "bbox": [],
  "geometry": {"coordinates":[-67.6833,45.0167],"type":"Point"}
}