<<<<<<< HEAD
{
  "id": 7054511,
  "type": "Feature",
  "properties": {
    "tgn:hierarchy":[
        "tgn:7054511",
        "tgn:7004610",
        "tgn:1000003",
        "tgn:1000080",
        "tgn:7029392"
    ],
    "tgn:id":7054511,
    "tgn:name":"Lucania",
    "tgn:placetype":[
        "aat:300387346"
    ]
},
  "bbox": [],
  "geometry": {"coordinates":[16.0,40.5],"type":"Point"}
}
=======
{"geometry":{"type":"Point","coordinates":[16.000000,40.500000]},"type":"Feature","properties":{"hierarchy":["tgn:7054511","tgn:7004610","tgn:1000003","tgn:1000080","tgn:7029392"],"placetype":["aat:300387346"],"id":7054511,"name:xx":"Lucania"}}
>>>>>>> 03f74aca74312dbeaf24d7e61306dd6a786dc3d0
