{
  "id": 1011427,
  "type": "Feature",
  "properties": {
    "tgn:hierarchy":[
        "tgn:1011427",
        "tgn:7018484",
        "tgn:7004543",
        "tgn:1000004",
        "tgn:7004542",
        "tgn:1000111",
        "tgn:7029392"
    ],
    "tgn:id":1011427,
    "tgn:name":"Hok Tsui",
    "tgn:placetype":[
        "aat:300387499"
    ]
},
  "bbox": [],
  "geometry": {"coordinates":[114.2667,22.2167],"type":"Point"}
}