{
  "id": 1104993,
  "type": "Feature",
  "properties": {
    "tgn:hierarchy":[
        "tgn:1104993",
        "tgn:1000001",
        "tgn:7012149",
        "tgn:1002423",
        "tgn:7007568",
        "tgn:7029392"
    ],
    "tgn:id":1104993,
    "tgn:name":"Hunter Mountain",
    "tgn:placetype":[
        "aat:300008795"
    ]
},
  "bbox": [],
  "geometry": {"coordinates":[-74.2167,42.1667],"type":"Point"}
}