{
  "id": 2001016,
  "type": "Feature",
  "properties": {
    "tgn:hierarchy":[
        "tgn:2001016",
        "tgn:1000001",
        "tgn:7012149",
        "tgn:7007521",
        "tgn:7029392"
    ],
    "tgn:id":2001016,
    "tgn:name":"Crow Wing",
    "tgn:placetype":[
        "aat:300387145",
        "aat:300000771"
    ]
},
  "bbox": [],
  "geometry": {"coordinates":[-94.0833,46.4667],"type":"Point"}
}