{
  "id": 7513493,
  "type": "Feature",
  "properties": {
    "tgn:hierarchy":[
        "tgn:7513493",
        "tgn:1009227",
        "tgn:7001866",
        "tgn:1000226",
        "tgn:1000006",
        "tgn:7029392"
    ],
    "tgn:id":7513493,
    "tgn:name:en":"Glenallan Stream",
    "tgn:placetype":[
        "aat:300008699"
    ]
},
  "bbox": [],
  "geometry": {"coordinates":[172.766667,-42.616667],"type":"Point"}
}