{
  "id": 1103810,
  "type": "Feature",
  "properties": {
    "tgn:hierarchy":[
        "tgn:1103810",
        "tgn:7000897",
        "tgn:1001040",
        "tgn:1000004",
        "tgn:1000120",
        "tgn:7029392"
    ],
    "tgn:id":1103810,
    "tgn:name":"Azamiga-dake",
    "tgn:placetype":[
        "aat:300008795"
    ]
},
  "bbox": [],
  "geometry": {"coordinates":[131.7833,34.3333],"type":"Point"}
}