{
  "id": 2221334,
  "type": "Feature",
  "properties": {
    "tgn:hierarchy":[
        "tgn:2221334",
        "tgn:1000001",
        "tgn:7012149",
        "tgn:2000908",
        "tgn:7007256",
        "tgn:7029392"
    ],
    "tgn:id":2221334,
    "tgn:name":"Carencro Lake",
    "tgn:placetype":[
        "aat:300008680"
    ]
},
  "bbox": [],
  "geometry": {"coordinates":[-91.0667,29.3833],"type":"Point"}
}