{
  "id": 2707195,
  "type": "Feature",
  "properties": {
    "tgn:hierarchy":[
        "tgn:2707195",
        "tgn:1000001",
        "tgn:7012149",
        "tgn:2000476",
        "tgn:7007250",
        "tgn:7029392"
    ],
    "tgn:id":2707195,
    "tgn:name":"Swede Ridge",
    "tgn:placetype":[
        "aat:300266640"
    ]
},
  "bbox": [],
  "geometry": {"coordinates":[-115.8833,45.8833],"type":"Point"}
}