{
  "id": 1121052,
  "type": "Feature",
  "properties": {
    "tgn:hierarchy":[
        "tgn:1121052",
        "tgn:1003353",
        "tgn:1000004",
        "tgn:7014786",
        "tgn:7029392"
    ],
    "tgn:id":1121052,
    "tgn:name":"Aksengir",
    "tgn:placetype":[
        "aat:300008707"
    ]
},
  "bbox": [],
  "geometry": {"coordinates":[76.2333,43.6667],"type":"Point"}
}