{
  "id": 2676006,
  "type": "Feature",
  "properties": {
    "tgn:hierarchy":[
        "tgn:2676006",
        "tgn:1000001",
        "tgn:7012149",
        "tgn:2000227",
        "tgn:7007158",
        "tgn:7029392"
    ],
    "tgn:id":2676006,
    "tgn:name":"Sopris Mine",
    "tgn:placetype":[
        "aat:300000390"
    ]
},
  "bbox": [],
  "geometry": {"coordinates":[-104.55,37.1167],"type":"Point"}
}