{
  "id": 2119152,
  "type": "Feature",
  "properties": {
    "tgn:hierarchy":[
        "tgn:2119152",
        "tgn:1000001",
        "tgn:7012149",
        "tgn:2002286",
        "tgn:7013961",
        "tgn:7029392"
    ],
    "tgn:id":2119152,
    "tgn:name":"Maxwell",
    "tgn:placetype":[
        "aat:300008347",
        "aat:300387210"
    ]
},
  "bbox": [],
  "geometry": {"coordinates":[-81.1167,39.3333],"type":"Point"}
}