{
  "id": 2248416,
  "type": "Feature",
  "properties": {
    "tgn:hierarchy":[
        "tgn:2248416",
        "tgn:1000001",
        "tgn:1002245",
        "tgn:7012149",
        "tgn:7007568",
        "tgn:7029392"
    ],
    "tgn:id":2248416,
    "tgn:name":"Cold Spring",
    "tgn:placetype":[
        "aat:300008347"
    ]
},
  "bbox": [],
  "geometry": {"coordinates":[-78.85,42.0833],"type":"Point"}
}