{
  "id": 2117469,
  "type": "Feature",
  "properties": {
    "tgn:hierarchy":[
        "tgn:2117469",
        "tgn:1000001",
        "tgn:7012149",
        "tgn:2002284",
        "tgn:7013961",
        "tgn:7029392"
    ],
    "tgn:id":2117469,
    "tgn:name":"Birch River",
    "tgn:placetype":[
        "aat:300008347"
    ]
},
  "bbox": [],
  "geometry": {"coordinates":[-80.75,38.4833],"type":"Point"}
}