{
  "id": 2238682,
  "type": "Feature",
  "properties": {
    "tgn:hierarchy":[
        "tgn:2238682",
        "tgn:1000001",
        "tgn:7012149",
        "tgn:2002112",
        "tgn:7007827",
        "tgn:7029392"
    ],
    "tgn:id":2238682,
    "tgn:name":"Chriss Creek",
    "tgn:placetype":[
        "aat:300008706"
    ]
},
  "bbox": [],
  "geometry": {"coordinates":[-111.9333,39.4167],"type":"Point"}
}