{
  "id": 2622654,
  "type": "Feature",
  "properties": {
    "tgn:hierarchy":[
        "tgn:2622654",
        "tgn:1000001",
        "tgn:7012149",
        "tgn:2001230",
        "tgn:7007523",
        "tgn:7029392"
    ],
    "tgn:id":2622654,
    "tgn:name":"Robinson Creek",
    "tgn:placetype":[
        "aat:300008706"
    ]
},
  "bbox": [],
  "geometry": {"coordinates":[-91.6333,37.9833],"type":"Point"}
}