{
  "id": 7193814,
  "type": "Feature",
  "properties": {
    "tgn:hierarchy":[
        "tgn:7193814",
        "tgn:7000096",
        "tgn:1000003",
        "tgn:7000084",
        "tgn:7029392"
    ],
    "tgn:id":7193814,
    "tgn:name":"Fischerwall",
    "tgn:placetype":[
        "aat:300000206"
    ]
},
  "bbox": [],
  "geometry": {"coordinates":[13.183333,53.066667],"type":"Point"}
}