{
  "id": 2755952,
  "type": "Feature",
  "properties": {
    "tgn:hierarchy":[
        "tgn:2755952",
        "tgn:1000001",
        "tgn:7012149",
        "tgn:2000214",
        "tgn:7007158",
        "tgn:7029392"
    ],
    "tgn:id":2755952,
    "tgn:name":"Weible Peak",
    "tgn:placetype":[
        "aat:300008798"
    ]
},
  "bbox": [],
  "geometry": {"coordinates":[-107.65,39.5167],"type":"Point"}
}