{
  "id": 5003645,
  "type": "Feature",
  "properties": {
    "tgn:hierarchy":[
        "tgn:5003645",
        "tgn:1000004",
        "tgn:7000784",
        "tgn:1000140",
        "tgn:7029392"
    ],
    "tgn:id":5003645,
    "tgn:name":"Hosn Soleiman",
    "tgn:placetype":[
        "aat:300008347",
        "aat:300008375"
    ]
},
  "bbox": [],
  "geometry": {"coordinates":[36.25,34.9333],"type":"Point"}
}