<<<<<<< HEAD
{
  "id": 7178103,
  "type": "Feature",
  "properties": {
    "tgn:hierarchy":[
        "tgn:7178103",
        "tgn:1000003",
        "tgn:7003689",
        "tgn:7000084",
        "tgn:7029392"
    ],
    "tgn:id":7178103,
    "tgn:name":"Hafer-Bach",
    "tgn:placetype":[
        "aat:300008699"
    ]
},
  "bbox": [],
  "geometry": {"coordinates":[10.7,51.5],"type":"Point"}
}
=======
{"geometry":{"type":"Point","coordinates":[10.700000,51.500000]},"type":"Feature","properties":{"hierarchy":["tgn:7178103","tgn:1000003","tgn:7003689","tgn:7000084","tgn:7029392"],"placetype":["aat:300008699"],"id":7178103,"name:xx":"Hafer-Bach"}}
>>>>>>> 03f74aca74312dbeaf24d7e61306dd6a786dc3d0
