{
  "id": 2759556,
  "type": "Feature",
  "properties": {
    "tgn:hierarchy":[
        "tgn:2759556",
        "tgn:1000001",
        "tgn:7012149",
        "tgn:2001284",
        "tgn:7007524",
        "tgn:7029392"
    ],
    "tgn:id":2759556,
    "tgn:name":"West Fork Falls Creek",
    "tgn:placetype":[
        "aat:300008706"
    ]
},
  "bbox": [],
  "geometry": {"coordinates":[-112.5833,47.1833],"type":"Point"}
}