{
  "id": 2440330,
  "type": "Feature",
  "properties": {
    "tgn:hierarchy":[
        "tgn:2440330",
        "tgn:1000001",
        "tgn:7012149",
        "tgn:7007252",
        "tgn:7029392"
    ],
    "tgn:id":2440330,
    "tgn:name":"Klondike Creek",
    "tgn:placetype":[
        "aat:300008706"
    ]
},
  "bbox": [],
  "geometry": {"coordinates":[-86.3333,39.7167],"type":"Point"}
}