{
  "id": 7149876,
  "type": "Feature",
  "properties": {
    "tgn:hierarchy":[
        "tgn:7149876",
        "tgn:7003692",
        "tgn:1000003",
        "tgn:7000084",
        "tgn:7029392"
    ],
    "tgn:id":7149876,
    "tgn:name":"Kr\u00e4uterbrunnenberg",
    "tgn:placetype":[
        "aat:300008777"
    ]
},
  "bbox": [],
  "geometry": {"coordinates":[9.983333,48.166667],"type":"Point"}
}