{
  "id": 7592175,
  "type": "Feature",
  "properties": {
    "tgn:hierarchy":[
        "tgn:7592175",
        "tgn:1000004",
        "tgn:7000198",
        "tgn:7000799",
        "tgn:7029392"
    ],
    "tgn:id":7592175,
    "tgn:name:en":"Mattu",
    "tgn:placetype":[
        "aat:300008347"
    ]
},
  "bbox": [],
  "geometry": {"coordinates":[74.528462,32.809082],"type":"Point"}
}