<<<<<<< HEAD
{
  "id": 2339197,
  "type": "Feature",
  "properties": {
    "tgn:hierarchy":[
        "tgn:2339197",
        "tgn:1000001",
        "tgn:2001263",
        "tgn:7012149",
        "tgn:7007524",
        "tgn:7029392"
    ],
    "tgn:id":2339197,
    "tgn:name":"Franks Spring",
    "tgn:placetype":[
        "aat:300008697"
    ]
},
  "bbox": [],
  "geometry": {"coordinates":[-111.2833,46.4833],"type":"Point"}
}
=======
{"geometry":{"type":"Point","coordinates":[-111.283300,46.483300]},"type":"Feature","properties":{"hierarchy":["tgn:2339197","tgn:1000001","tgn:2001263","tgn:7012149","tgn:7007524","tgn:7029392"],"placetype":["aat:300008697"],"id":2339197,"name:xx":"Franks Spring"}}
>>>>>>> 03f74aca74312dbeaf24d7e61306dd6a786dc3d0
