{
  "id": 2074156,
  "type": "Feature",
  "properties": {
    "tgn:hierarchy":[
        "tgn:2074156",
        "tgn:1000001",
        "tgn:2001481",
        "tgn:7012149",
        "tgn:7007709",
        "tgn:7029392"
    ],
    "tgn:id":2074156,
    "tgn:name":"Coalville",
    "tgn:placetype":[
        "aat:300008347",
        "aat:300387210"
    ]
},
  "bbox": [],
  "geometry": {"coordinates":[-83.8833,35.1833],"type":"Point"}
}