{
  "id": 7087831,
  "type": "Feature",
  "properties": {
    "tgn:hierarchy":[
        "tgn:7087831",
        "tgn:7003669",
        "tgn:1000003",
        "tgn:7000084",
        "tgn:7029392"
    ],
    "tgn:id":7087831,
    "tgn:name":"Wangering",
    "tgn:placetype":[
        "aat:300000206"
    ]
},
  "bbox": [],
  "geometry": {"coordinates":[13.133333,48.783333],"type":"Point"}
}