{
  "id": 7298723,
  "type": "Feature",
  "properties": {
    "tgn:hierarchy":[
        "tgn:7298723",
        "tgn:7002810",
        "tgn:7001158",
        "tgn:1000003",
        "tgn:1000095",
        "tgn:7029392"
    ],
    "tgn:id":7298723,
    "tgn:name":"Vadocondes",
    "tgn:placetype":[
        "aat:300008347"
    ]
},
  "bbox": [],
  "geometry": {"coordinates":[-3.566667,41.65],"type":"Point"}
}