<<<<<<< HEAD
{
  "id": 7027159,
  "type": "Feature",
  "properties": {
    "tgn:hierarchy":[
        "tgn:7027159",
        "tgn:7002445",
        "tgn:1000003",
        "tgn:7008143",
        "tgn:7008591",
        "tgn:7029392"
    ],
    "tgn:id":7027159,
    "tgn:name":"Venn's Green",
    "tgn:placetype":[
        "aat:300008347",
        "aat:300008372"
    ]
},
  "bbox": [],
  "geometry": {"coordinates":[-2.6833,52.1333],"type":"Point"}
}
=======
{"geometry":{"type":"Point","coordinates":[-2.683300,52.133300]},"type":"Feature","properties":{"hierarchy":["tgn:7027159","tgn:7002445","tgn:1000003","tgn:7008143","tgn:7008591","tgn:7029392"],"placetype":["aat:300008347","aat:300008372"],"id":7027159,"name:xx":"Venn's Green"}}
>>>>>>> 03f74aca74312dbeaf24d7e61306dd6a786dc3d0
