{
  "id": 7507830,
  "type": "Feature",
  "properties": {
    "tgn:hierarchy":[
        "tgn:7507830",
        "tgn:1008380",
        "tgn:1000226",
        "tgn:7000512",
        "tgn:1000006",
        "tgn:7029392"
    ],
    "tgn:id":7507830,
    "tgn:name:en":"Pikarere",
    "tgn:placetype":[
        "aat:300008777"
    ]
},
  "bbox": [],
  "geometry": {"coordinates":[174.816667,-41.116667],"type":"Point"}
}