{
  "id": 1026571,
  "type": "Feature",
  "properties": {
    "tgn:hierarchy":[
        "tgn:1026571",
        "tgn:7003457",
        "tgn:1000003",
        "tgn:1000063",
        "tgn:7018236",
        "tgn:7029392"
    ],
    "tgn:id":1026571,
    "tgn:name":"Lokeren",
    "tgn:placetype":[
        "aat:300008347"
    ]
},
  "bbox": [],
  "geometry": {"coordinates":[3.99339,51.103636],"type":"Point"}
}