{
  "id": 2724493,
  "type": "Feature",
  "properties": {
    "tgn:hierarchy":[
        "tgn:2724493",
        "tgn:1000001",
        "tgn:7012149",
        "tgn:2002266",
        "tgn:7013961",
        "tgn:7029392"
    ],
    "tgn:id":2724493,
    "tgn:name":"Tom Williams Hollow",
    "tgn:placetype":[
        "aat:300008761"
    ]
},
  "bbox": [],
  "geometry": {"coordinates":[-78.8667,39.0667],"type":"Point"}
}