<<<<<<< HEAD
{
  "id": 7114608,
  "type": "Feature",
  "properties": {
    "tgn:hierarchy":[
        "tgn:7114608",
        "tgn:7003692",
        "tgn:1000003",
        "tgn:7000084",
        "tgn:7029392"
    ],
    "tgn:id":7114608,
    "tgn:name":"Riedenberg",
    "tgn:placetype":[
        "aat:300008347"
    ]
},
  "bbox": [],
  "geometry": {"coordinates":[9.216667,48.733333],"type":"Point"}
}
=======
{"geometry":{"type":"Point","coordinates":[9.216667,48.733333]},"type":"Feature","properties":{"hierarchy":["tgn:7114608","tgn:7003692","tgn:1000003","tgn:7000084","tgn:7029392"],"placetype":["aat:300008347"],"id":7114608,"name:xx":"Riedenberg"}}
>>>>>>> 03f74aca74312dbeaf24d7e61306dd6a786dc3d0
