{
  "id": 7512941,
  "type": "Feature",
  "properties": {
    "tgn:hierarchy":[
        "tgn:7512941",
        "tgn:7016670",
        "tgn:1008380",
        "tgn:1000226",
        "tgn:1000006",
        "tgn:7029392"
    ],
    "tgn:id":7512941,
    "tgn:name:en":"Haumoana",
    "tgn:placetype":[
        "aat:300008347"
    ]
},
  "bbox": [],
  "geometry": {"coordinates":[176.95,-39.616667],"type":"Point"}
}