{
  "id": 2503002,
  "type": "Feature",
  "properties": {
    "tgn:hierarchy":[
        "tgn:2503002",
        "tgn:1000001",
        "tgn:7012149",
        "tgn:2002356",
        "tgn:7007922",
        "tgn:7029392"
    ],
    "tgn:id":2503002,
    "tgn:name":"McNamar Lake",
    "tgn:placetype":[
        "aat:300008680"
    ]
},
  "bbox": [],
  "geometry": {"coordinates":[-90.3667,45.2333],"type":"Point"}
}