{
  "id": 7282444,
  "type": "Feature",
  "properties": {
    "tgn:hierarchy":[
        "tgn:7282444",
        "tgn:1001623",
        "tgn:1000049",
        "tgn:1000002",
        "tgn:7029392"
    ],
    "tgn:id":7282444,
    "tgn:name":"Phipps, Islote",
    "tgn:placetype":[
        "aat:300008791"
    ]
},
  "bbox": [],
  "geometry": {"coordinates":[-74.633333,-48.066667],"type":"Point"}
}