{
  "id": 2740293,
  "type": "Feature",
  "properties": {
    "tgn:hierarchy":[
        "tgn:2740293",
        "tgn:1000001",
        "tgn:7012149",
        "tgn:7007157",
        "tgn:1002915",
        "tgn:7029392"
    ],
    "tgn:id":2740293,
    "tgn:name":"Upper Lateral Number Two And One Half",
    "tgn:placetype":[
        "aat:300006075"
    ]
},
  "bbox": [],
  "geometry": {"coordinates":[-120.8333,37.55],"type":"Point"}
}