{
  "id": 1009300,
  "type": "Feature",
  "properties": {
    "tgn:hierarchy":[
        "tgn:1009300",
        "tgn:1001301",
        "tgn:1000004",
        "tgn:1000122",
        "tgn:7029392"
    ],
    "tgn:id":1009300,
    "tgn:name":"Sunwi-do",
    "tgn:placetype":[
        "aat:300008791"
    ]
},
  "bbox": [],
  "geometry": {"coordinates":[125.25,37.7167],"type":"Point"}
}