{
  "id": 1004278,
  "type": "Feature",
  "properties": {
    "tgn:hierarchy":[
        "tgn:1004278",
        "tgn:7005685",
        "tgn:1000001",
        "tgn:7013154",
        "tgn:7029392"
    ],
    "tgn:id":1004278,
    "tgn:name":"Chippawa",
    "tgn:placetype":[
        "aat:300008347"
    ]
},
  "bbox": [],
  "geometry": {"coordinates":[-79.05,-43.0833],"type":"Point"}
}