{
  "id": 2712269,
  "type": "Feature",
  "properties": {
    "tgn:hierarchy":[
        "tgn:2712269",
        "tgn:1000001",
        "tgn:2002245",
        "tgn:7012149",
        "tgn:7007920",
        "tgn:7029392"
    ],
    "tgn:id":2712269,
    "tgn:name":"Tatman Mountain",
    "tgn:placetype":[
        "aat:300008798"
    ]
},
  "bbox": [],
  "geometry": {"coordinates":[-117.5833,46.3667],"type":"Point"}
}