{
  "id": 2389193,
  "type": "Feature",
  "properties": {
    "tgn:hierarchy":[
        "tgn:2389193",
        "tgn:1000001",
        "tgn:7012149",
        "tgn:1002517",
        "tgn:7007523",
        "tgn:7029392"
    ],
    "tgn:id":2389193,
    "tgn:name":"Hidden Valley Lake",
    "tgn:placetype":[
        "aat:300006191"
    ]
},
  "bbox": [],
  "geometry": {"coordinates":[-90.6833,38.2833],"type":"Point"}
}