{
  "id": 2245928,
  "type": "Feature",
  "properties": {
    "tgn:hierarchy":[
        "tgn:2245928",
        "tgn:1000001",
        "tgn:7012149",
        "tgn:2000555",
        "tgn:7007252",
        "tgn:7029392"
    ],
    "tgn:id":2245928,
    "tgn:name":"Coal Knobs",
    "tgn:placetype":[
        "aat:300008798"
    ]
},
  "bbox": [],
  "geometry": {"coordinates":[-87.0667,37.9333],"type":"Point"}
}