{
  "id": 2650502,
  "type": "Feature",
  "properties": {
    "tgn:hierarchy":[
        "tgn:2650502",
        "tgn:1000001",
        "tgn:7012149",
        "tgn:1002521",
        "tgn:7007920",
        "tgn:7029392"
    ],
    "tgn:id":2650502,
    "tgn:name":"Seattle, Mount",
    "tgn:placetype":[
        "aat:300008798"
    ]
},
  "bbox": [],
  "geometry": {"coordinates":[-123.5667,47.7167],"type":"Point"}
}