{
  "id": 2715179,
  "type": "Feature",
  "properties": {
    "tgn:hierarchy":[
        "tgn:2715179",
        "tgn:1000001",
        "tgn:7012149",
        "tgn:2000966",
        "tgn:7007520",
        "tgn:7029392"
    ],
    "tgn:id":2715179,
    "tgn:name":"Tepee Creek",
    "tgn:placetype":[
        "aat:300008706"
    ]
},
  "bbox": [],
  "geometry": {"coordinates":[-88.8667,46.3667],"type":"Point"}
}