{
  "id": 2532041,
  "type": "Feature",
  "properties": {
    "tgn:hierarchy":[
        "tgn:2532041",
        "tgn:1002933",
        "tgn:1000001",
        "tgn:7012149",
        "tgn:7007239",
        "tgn:7029392"
    ],
    "tgn:id":2532041,
    "tgn:name":"Munchy Branch",
    "tgn:placetype":[
        "aat:300008699"
    ]
},
  "bbox": [],
  "geometry": {"coordinates":[-75.1167,38.7167],"type":"Point"}
}