{
  "id": 7588186,
  "type": "Feature",
  "properties": {
    "tgn:hierarchy":[
        "tgn:7588186",
        "tgn:1000004",
        "tgn:7000198",
        "tgn:1001977",
        "tgn:7029392"
    ],
    "tgn:id":7588186,
    "tgn:name:en":"Karulia",
    "tgn:placetype":[
        "aat:300008347"
    ]
},
  "bbox": [],
  "geometry": {"coordinates":[88.728056,22.676667],"type":"Point"}
}