{
  "id": 2332166,
  "type": "Feature",
  "properties": {
    "tgn:hierarchy":[
        "tgn:2332166",
        "tgn:1000001",
        "tgn:2002109",
        "tgn:7012149",
        "tgn:7007827",
        "tgn:7029392"
    ],
    "tgn:id":2332166,
    "tgn:name":"Flint Seep",
    "tgn:placetype":[
        "aat:300008697"
    ]
},
  "bbox": [],
  "geometry": {"coordinates":[-110.1333,38.1333],"type":"Point"}
}