{
  "id": 2409602,
  "type": "Feature",
  "properties": {
    "tgn:hierarchy":[
        "tgn:2409602",
        "tgn:1000001",
        "tgn:7012149",
        "tgn:2001707",
        "tgn:7007708",
        "tgn:7029392"
    ],
    "tgn:id":2409602,
    "tgn:name":"Igo",
    "tgn:placetype":[
        "aat:300008347"
    ]
},
  "bbox": [],
  "geometry": {"coordinates":[-120.2667,45.25],"type":"Point"}
}