<<<<<<< HEAD
{
  "id": 2409602,
  "type": "Feature",
  "properties": {
    "tgn:hierarchy":[
        "tgn:2409602",
        "tgn:1000001",
        "tgn:7012149",
        "tgn:2001707",
        "tgn:7007708",
        "tgn:7029392"
    ],
    "tgn:id":2409602,
    "tgn:name":"Igo",
    "tgn:placetype":[
        "aat:300008347"
    ]
},
  "bbox": [],
  "geometry": {"coordinates":[-120.2667,45.25],"type":"Point"}
}
=======
{"geometry":{"type":"Point","coordinates":[-120.266700,45.250000]},"type":"Feature","properties":{"hierarchy":["tgn:2409602","tgn:1000001","tgn:7012149","tgn:2001707","tgn:7007708","tgn:7029392"],"placetype":["aat:300008347"],"id":2409602,"name:xx":"Igo"}}
>>>>>>> 03f74aca74312dbeaf24d7e61306dd6a786dc3d0
