{
  "id": 7147630,
  "type": "Feature",
  "properties": {
    "tgn:hierarchy":[
        "tgn:7147630",
        "tgn:1000003",
        "tgn:7003676",
        "tgn:7000084",
        "tgn:7029392"
    ],
    "tgn:id":7147630,
    "tgn:name":"F\u00f6rsterei Kr\u00e4he",
    "tgn:placetype":[
        "aat:300004792"
    ]
},
  "bbox": [],
  "geometry": {"coordinates":[9.283333,52.65],"type":"Point"}
}