{
  "id": 2154804,
  "type": "Feature",
  "properties": {
    "tgn:hierarchy":[
        "tgn:2154804",
        "tgn:1000001",
        "tgn:7019982",
        "tgn:7012149",
        "tgn:7007517",
        "tgn:7029392"
    ],
    "tgn:id":2154804,
    "tgn:name":"Bear Hill",
    "tgn:placetype":[
        "aat:300008798"
    ]
},
  "bbox": [],
  "geometry": {"coordinates":[-72.2667,42.0333],"type":"Point"}
}