<<<<<<< HEAD
{
  "id": 2154804,
  "type": "Feature",
  "properties": {
    "tgn:hierarchy":[
        "tgn:2154804",
        "tgn:1000001",
        "tgn:7019982",
        "tgn:7012149",
        "tgn:7007517",
        "tgn:7029392"
    ],
    "tgn:id":2154804,
    "tgn:name":"Bear Hill",
    "tgn:placetype":[
        "aat:300008798"
    ]
},
  "bbox": [],
  "geometry": {"coordinates":[-72.2667,42.0333],"type":"Point"}
}
=======
{"geometry":{"type":"Point","coordinates":[-72.266700,42.033300]},"type":"Feature","properties":{"hierarchy":["tgn:2154804","tgn:1000001","tgn:7019982","tgn:7012149","tgn:7007517","tgn:7029392"],"placetype":["aat:300008798"],"id":2154804,"name:xx":"Bear Hill"}}
>>>>>>> 03f74aca74312dbeaf24d7e61306dd6a786dc3d0
