{
  "id": 2077157,
  "type": "Feature",
  "properties": {
    "tgn:hierarchy":[
        "tgn:2077157",
        "tgn:1000001",
        "tgn:7012149",
        "tgn:2001521",
        "tgn:7007709",
        "tgn:7029392"
    ],
    "tgn:id":2077157,
    "tgn:name":"West Philadelphia",
    "tgn:placetype":[
        "aat:300008347",
        "aat:300387210"
    ]
},
  "bbox": [],
  "geometry": {"coordinates":[-79.65,35.3667],"type":"Point"}
}