<<<<<<< HEAD
{
  "id": 7248945,
  "type": "Feature",
  "properties": {
    "tgn:hierarchy":[
        "tgn:7248945",
        "tgn:7003465",
        "tgn:1000003",
        "tgn:1000063",
        "tgn:4012014",
        "tgn:7029392"
    ],
    "tgn:id":7248945,
    "tgn:name":"Brochamp aux Plates Aires",
    "tgn:placetype":[
        "aat:300008347"
    ]
},
  "bbox": [],
  "geometry": {"coordinates":[5.133333,50.1],"type":"Point"}
}
=======
{"geometry":{"type":"Point","coordinates":[5.133333,50.100000]},"type":"Feature","properties":{"hierarchy":["tgn:7248945","tgn:7003465","tgn:1000003","tgn:1000063","tgn:4012014","tgn:7029392"],"placetype":["aat:300008347"],"id":7248945,"name:xx":"Brochamp aux Plates Aires"}}
>>>>>>> 03f74aca74312dbeaf24d7e61306dd6a786dc3d0
