<<<<<<< HEAD
{
  "id": 2157882,
  "type": "Feature",
  "properties": {
    "tgn:hierarchy":[
        "tgn:2157882",
        "tgn:2001563",
        "tgn:1000001",
        "tgn:7012149",
        "tgn:7007705",
        "tgn:7029392"
    ],
    "tgn:id":2157882,
    "tgn:name":"Beaver Lake",
    "tgn:placetype":[
        "aat:300008680"
    ]
},
  "bbox": [],
  "geometry": {"coordinates":[-102.6333,48.85],"type":"Point"}
}
=======
{"geometry":{"type":"Point","coordinates":[-102.633300,48.850000]},"type":"Feature","properties":{"hierarchy":["tgn:2157882","tgn:2001563","tgn:1000001","tgn:7012149","tgn:7007705","tgn:7029392"],"placetype":["aat:300008680"],"id":2157882,"name:xx":"Beaver Lake"}}
>>>>>>> 03f74aca74312dbeaf24d7e61306dd6a786dc3d0
