{
  "id": 1036479,
  "type": "Feature",
  "properties": {
    "tgn:hierarchy":[
        "tgn:1036479",
        "tgn:1000003",
        "tgn:7000094",
        "tgn:7000084",
        "tgn:7029392"
    ],
    "tgn:id":1036479,
    "tgn:name":"Boizenburg",
    "tgn:placetype":[
        "aat:300008347"
    ]
},
  "bbox": [],
  "geometry": {"coordinates":[10.716667,53.383333],"type":"Point"}
}