{
  "id": 2662817,
  "type": "Feature",
  "properties": {
    "tgn:hierarchy":[
        "tgn:2662817",
        "tgn:1000001",
        "tgn:1002213",
        "tgn:7012149",
        "tgn:7007710",
        "tgn:7029392"
    ],
    "tgn:id":2662817,
    "tgn:name":"Siles",
    "tgn:placetype":[
        "aat:300008347"
    ]
},
  "bbox": [],
  "geometry": {"coordinates":[-74.9667,40.15],"type":"Point"}
}