{
  "id": 1072098,
  "type": "Feature",
  "properties": {
    "tgn:hierarchy":[
        "tgn:1072098",
        "tgn:1000004",
        "tgn:7001745",
        "tgn:1000111",
        "tgn:7029392"
    ],
    "tgn:id":1072098,
    "tgn:name":"Talimuashili",
    "tgn:placetype":[
        "aat:300008347"
    ]
},
  "bbox": [],
  "geometry": {"coordinates":[77.05,39.1333],"type":"Point"}
}