<<<<<<< HEAD
{
  "id": 2760760,
  "type": "Feature",
  "properties": {
    "tgn:hierarchy":[
        "tgn:2760760",
        "tgn:1000001",
        "tgn:7012149",
        "tgn:1002966",
        "tgn:7007826",
        "tgn:7029392"
    ],
    "tgn:id":2760760,
    "tgn:name":"West Greasy Creek",
    "tgn:placetype":[
        "aat:300008706"
    ]
},
  "bbox": [],
  "geometry": {"coordinates":[-94.9,32.8667],"type":"Point"}
}
=======
{"geometry":{"type":"Point","coordinates":[-94.900000,32.866700]},"type":"Feature","properties":{"hierarchy":["tgn:2760760","tgn:1000001","tgn:7012149","tgn:1002966","tgn:7007826","tgn:7029392"],"placetype":["aat:300008706"],"id":2760760,"name:xx":"West Greasy Creek"}}
>>>>>>> 03f74aca74312dbeaf24d7e61306dd6a786dc3d0
