{
  "id": 1099114,
  "type": "Feature",
  "properties": {
    "tgn:hierarchy":[
        "tgn:1099114",
        "tgn:1008380",
        "tgn:7520093",
        "tgn:1000226",
        "tgn:1000006",
        "tgn:7029392"
    ],
    "tgn:id":1099114,
    "tgn:name:en":"Ohura",
    "tgn:placetype":[
        "aat:300008347"
    ]
},
  "bbox": [],
  "geometry": {"coordinates":[174.983333,-38.833333],"type":"Point"}
}