{
  "id": 2450994,
  "type": "Feature",
  "properties": {
    "tgn:hierarchy":[
        "tgn:2450994",
        "tgn:1000001",
        "tgn:7012149",
        "tgn:2002249",
        "tgn:7007920",
        "tgn:7029392"
    ],
    "tgn:id":2450994,
    "tgn:name":"Litter Creek",
    "tgn:placetype":[
        "aat:300008706"
    ]
},
  "bbox": [],
  "geometry": {"coordinates":[-117.05,47.9333],"type":"Point"}
}