{
  "id": 7318541,
  "type": "Feature",
  "properties": {
    "tgn:hierarchy":[
        "tgn:7318541",
        "tgn:1001708",
        "tgn:1000049",
        "tgn:1000002",
        "tgn:7029392"
    ],
    "tgn:id":7318541,
    "tgn:name":"Coraz\u00f3n, Quebrada del",
    "tgn:placetype":[
        "aat:300008699"
    ]
},
  "bbox": [],
  "geometry": {"coordinates":[-70.55,-33.766667],"type":"Point"}
}