{
  "id": 2533159,
  "type": "Feature",
  "properties": {
    "tgn:hierarchy":[
        "tgn:2533159",
        "tgn:7006450",
        "tgn:1000001",
        "tgn:7012149",
        "tgn:7019760",
        "tgn:7029392"
    ],
    "tgn:id":2533159,
    "tgn:name":"Muse Island",
    "tgn:placetype":[
        "aat:300008791"
    ]
},
  "bbox": [],
  "geometry": {"coordinates":[-133.95,57.45],"type":"Point"}
}