{
  "id": 1094427,
  "type": "Feature",
  "properties": {
    "tgn:hierarchy":[
        "tgn:1094427",
        "tgn:7001242",
        "tgn:1001112",
        "tgn:1000201",
        "tgn:7029392"
    ],
    "tgn:id":1094427,
    "tgn:name":"Sahaba",
    "tgn:placetype":[
        "aat:300008347"
    ]
},
  "bbox": [],
  "geometry": {"coordinates":[30.4667,18.9167],"type":"Point"}
}