{
  "id": 7085304,
  "type": "Feature",
  "properties": {
    "tgn:hierarchy":[
        "tgn:7085304",
        "tgn:7003692",
        "tgn:1000003",
        "tgn:7000084",
        "tgn:7029392"
    ],
    "tgn:id":7085304,
    "tgn:name":"Werfental",
    "tgn:placetype":[
        "aat:300008761"
    ]
},
  "bbox": [],
  "geometry": {"coordinates":[9.466667,48.266667],"type":"Point"}
}