{
  "id": 2278272,
  "type": "Feature",
  "properties": {
    "tgn:hierarchy":[
        "tgn:2278272",
        "tgn:1000001",
        "tgn:7012149",
        "tgn:2000909",
        "tgn:7007256",
        "tgn:7029392"
    ],
    "tgn:id":2278272,
    "tgn:name":"De Loutre Basin",
    "tgn:placetype":[
        "aat:300386845"
    ]
},
  "bbox": [],
  "geometry": {"coordinates":[-92.1333,32.6667],"type":"Point"}
}