{
  "id": 7472207,
  "type": "Feature",
  "properties": {
    "tgn:hierarchy":[
        "tgn:7472207",
        "tgn:1000004",
        "tgn:7001014",
        "tgn:1000141",
        "tgn:7029392"
    ],
    "tgn:id":7472207,
    "tgn:name":"Citong Yihao Qiao",
    "tgn:placetype":[
        "aat:300007836"
    ]
},
  "bbox": [],
  "geometry": {"coordinates":[120.508029,23.751456],"type":"Point"}
}