<<<<<<< HEAD
{
  "id": 7352827,
  "type": "Feature",
  "properties": {
    "tgn:hierarchy":[
        "tgn:7352827",
        "tgn:1000001",
        "tgn:1001893",
        "tgn:7005560",
        "tgn:7029392"
    ],
    "tgn:id":7352827,
    "tgn:name":"Alto del Tapanco, Cerro",
    "tgn:placetype":[
        "aat:300008795"
    ]
},
  "bbox": [],
  "geometry": {"coordinates":[-106.833333,25.65],"type":"Point"}
}
=======
{"geometry":{"type":"Point","coordinates":[-106.833333,25.650000]},"type":"Feature","properties":{"hierarchy":["tgn:7352827","tgn:1000001","tgn:1001893","tgn:7005560","tgn:7029392"],"placetype":["aat:300008795"],"id":7352827,"name:xx":"Alto del Tapanco, Cerro"}}
>>>>>>> 03f74aca74312dbeaf24d7e61306dd6a786dc3d0
