{
  "id": 2713550,
  "type": "Feature",
  "properties": {
    "tgn:hierarchy":[
        "tgn:2713550",
        "tgn:1000001",
        "tgn:7012149",
        "tgn:2000226",
        "tgn:7007158",
        "tgn:7029392"
    ],
    "tgn:id":2713550,
    "tgn:name":"Teakettle Canyon",
    "tgn:placetype":[
        "aat:300008761"
    ]
},
  "bbox": [],
  "geometry": {"coordinates":[-105.4833,40.7833],"type":"Point"}
}