{
  "id": 2582313,
  "type": "Feature",
  "properties": {
    "tgn:hierarchy":[
        "tgn:2582313",
        "tgn:1000001",
        "tgn:2002370",
        "tgn:7012149",
        "tgn:7007923",
        "tgn:7029392"
    ],
    "tgn:id":2582313,
    "tgn:name":"Pine Creek",
    "tgn:placetype":[
        "aat:300008706"
    ]
},
  "bbox": [],
  "geometry": {"coordinates":[-104.35,44.7667],"type":"Point"}
}