<<<<<<< HEAD
{
  "id": 2250220,
  "type": "Feature",
  "properties": {
    "tgn:hierarchy":[
        "tgn:2250220",
        "tgn:7002659",
        "tgn:1000001",
        "tgn:2000016",
        "tgn:7012149",
        "tgn:7029392"
    ],
    "tgn:id":2250220,
    "tgn:name":"Collins Mountain",
    "tgn:placetype":[
        "aat:300008798"
    ]
},
  "bbox": [],
  "geometry": {"coordinates":[-87.5167,34.6],"type":"Point"}
}
=======
{"geometry":{"type":"Point","coordinates":[-87.516700,34.600000]},"type":"Feature","properties":{"hierarchy":["tgn:2250220","tgn:7002659","tgn:1000001","tgn:2000016","tgn:7012149","tgn:7029392"],"placetype":["aat:300008798"],"id":2250220,"name:xx":"Collins Mountain"}}
>>>>>>> 03f74aca74312dbeaf24d7e61306dd6a786dc3d0
