{
  "id": 7004824,
  "type": "Feature",
  "properties": {
    "tgn:hierarchy":[
        "tgn:7004824",
        "tgn:7016579",
        "tgn:7000895",
        "tgn:1000004",
        "tgn:1000120",
        "tgn:7029392"
    ],
    "tgn:id":7004824,
    "tgn:name":"Toyohashi",
    "tgn:placetype":[
        "aat:300008347",
        "aat:300008389"
    ]
},
  "bbox": [],
  "geometry": {"coordinates":[137.3667,34.7667],"type":"Point"}
}