<<<<<<< HEAD
{
  "id": 2255203,
  "type": "Feature",
  "properties": {
    "tgn:hierarchy":[
        "tgn:2255203",
        "tgn:1000001",
        "tgn:7012149",
        "tgn:2002187",
        "tgn:7007919",
        "tgn:7029392"
    ],
    "tgn:id":2255203,
    "tgn:name":"Cooper Mountain",
    "tgn:placetype":[
        "aat:300008798"
    ]
},
  "bbox": [],
  "geometry": {"coordinates":[-79.0167,38.4833],"type":"Point"}
}
=======
{"geometry":{"type":"Point","coordinates":[-79.016700,38.483300]},"type":"Feature","properties":{"hierarchy":["tgn:2255203","tgn:1000001","tgn:7012149","tgn:2002187","tgn:7007919","tgn:7029392"],"placetype":["aat:300008798"],"id":2255203,"name:xx":"Cooper Mountain"}}
>>>>>>> 03f74aca74312dbeaf24d7e61306dd6a786dc3d0
