{
  "id": 7583639,
  "type": "Feature",
  "properties": {
    "tgn:hierarchy":[
        "tgn:7583639",
        "tgn:1000004",
        "tgn:7000198",
        "tgn:7016883",
        "tgn:7029392"
    ],
    "tgn:id":7583639,
    "tgn:name:en":"Machhr\u0101i Khurd",
    "tgn:placetype":[
        "aat:300008347"
    ]
},
  "bbox": [],
  "geometry": {"coordinates":[76.185707,30.589925],"type":"Point"}
}