{
  "id": 7315041,
  "type": "Feature",
  "properties": {
    "tgn:hierarchy":[
        "tgn:7315041",
        "tgn:1001768",
        "tgn:1000049",
        "tgn:1000002",
        "tgn:7029392"
    ],
    "tgn:id":7315041,
    "tgn:name":"Las Rosas",
    "tgn:placetype":[
        "aat:300008347"
    ]
},
  "bbox": [],
  "geometry": {"coordinates":[-71.45,-33.066667],"type":"Point"}
}