{
  "id": 2579484,
  "type": "Feature",
  "properties": {
    "tgn:hierarchy":[
        "tgn:2579484",
        "tgn:1000001",
        "tgn:7016172",
        "tgn:7012149",
        "tgn:2000155",
        "tgn:7029392"
    ],
    "tgn:id":2579484,
    "tgn:name":"Pickert Point",
    "tgn:placetype":[
        "aat:300008850"
    ]
},
  "bbox": [],
  "geometry": {"coordinates":[-93.3333,36.0667],"type":"Point"}
}