{
  "id": 2050372,
  "type": "Feature",
  "properties": {
    "tgn:hierarchy":[
        "tgn:2050372",
        "tgn:1000001",
        "tgn:7019982",
        "tgn:7012149",
        "tgn:7007517",
        "tgn:7029392"
    ],
    "tgn:id":2050372,
    "tgn:name":"Palmer",
    "tgn:placetype":[
        "aat:300008347"
    ]
},
  "bbox": [],
  "geometry": {"coordinates":[-72.3167,42.15],"type":"Point"}
}