{
  "id": 7462448,
  "type": "Feature",
  "properties": {
    "tgn:hierarchy":[
        "tgn:7462448",
        "tgn:7002445",
        "tgn:1000003",
        "tgn:7008157",
        "tgn:7008591",
        "tgn:7029392"
    ],
    "tgn:id":7462448,
    "tgn:name:en":"Inner Dowsing",
    "tgn:placetype":[
        "aat:300387036"
    ]
},
  "bbox": [],
  "geometry": {"coordinates":[0.583333,53.266667],"type":"Point"}
}