{
  "id": 7592171,
  "type": "Feature",
  "properties": {
    "tgn:hierarchy":[
        "tgn:7592171",
        "tgn:1000004",
        "tgn:7000198",
        "tgn:7000799",
        "tgn:7029392"
    ],
    "tgn:id":7592171,
    "tgn:name:en":"Garhi Bishna",
    "tgn:placetype":[
        "aat:300008347"
    ]
},
  "bbox": [],
  "geometry": {"coordinates":[74.568056,32.829167],"type":"Point"}
}