{
  "id": 1127670,
  "type": "Feature",
  "properties": {
    "tgn:hierarchy":[
        "tgn:1127670",
        "tgn:1000583",
        "tgn:1000050",
        "tgn:1000002",
        "tgn:7029392"
    ],
    "tgn:id":1127670,
    "tgn:name":"Negro",
    "tgn:placetype":[
        "aat:300008707"
    ]
},
  "bbox": [],
  "geometry": {"coordinates":[-74.65,5.7333],"type":"Point"}
}