{
  "id": 7516360,
  "type": "Feature",
  "properties": {
    "tgn:hierarchy":[
        "tgn:7516360",
        "tgn:1008380",
        "tgn:7520093",
        "tgn:1000226",
        "tgn:1000006",
        "tgn:7029392"
    ],
    "tgn:id":7516360,
    "tgn:name:en":"Langdon",
    "tgn:placetype":[
        "aat:300008795"
    ]
},
  "bbox": [],
  "geometry": {"coordinates":[175.45,-39.033333],"type":"Point"}
}