{
  "id": 7221197,
  "type": "Feature",
  "properties": {
    "tgn:hierarchy":[
        "tgn:7221197",
        "tgn:7011164",
        "tgn:7002674",
        "tgn:1000003",
        "tgn:1000074",
        "tgn:7029392"
    ],
    "tgn:id":7221197,
    "tgn:name":"Paid\u00e1kia",
    "tgn:placetype":[
        "aat:300266640"
    ]
},
  "bbox": [],
  "geometry": {"coordinates":[26.791389,37.801389],"type":"Point"}
}