{
  "id": 2582843,
  "type": "Feature",
  "properties": {
    "tgn:hierarchy":[
        "tgn:2582843",
        "tgn:1000001",
        "tgn:2001738",
        "tgn:7012149",
        "tgn:7007712",
        "tgn:7029392"
    ],
    "tgn:id":2582843,
    "tgn:name":"Pine Island",
    "tgn:placetype":[
        "aat:300008791"
    ]
},
  "bbox": [],
  "geometry": {"coordinates":[-80.35,33.4667],"type":"Point"}
}