{
  "id": 7541561,
  "type": "Feature",
  "properties": {
    "tgn:hierarchy":[
        "tgn:7541561",
        "tgn:7001242",
        "tgn:7016833",
        "tgn:7000123",
        "tgn:7029392"
    ],
    "tgn:id":7541561,
    "tgn:name:en":"An Najmah",
    "tgn:placetype":[
        "aat:300008347"
    ]
},
  "bbox": [],
  "geometry": {"coordinates":[32.136319,26.158829],"type":"Point"}
}