{
  "id": 1030065,
  "type": "Feature",
  "properties": {
    "tgn:hierarchy":[
        "tgn:1030065",
        "tgn:7002445",
        "tgn:1000003",
        "tgn:7008117",
        "tgn:7008591",
        "tgn:7029392"
    ],
    "tgn:id":1030065,
    "tgn:name:en":"Milnthorpe",
    "tgn:placetype":[
        "aat:300008347"
    ]
},
  "bbox": [],
  "geometry": {"coordinates":[-2.766667,54.216667],"type":"Point"}
}