<<<<<<< HEAD
{
  "id": 2768657,
  "type": "Feature",
  "properties": {
    "tgn:hierarchy":[
        "tgn:2768657",
        "tgn:7002659",
        "tgn:1000001",
        "tgn:2000016",
        "tgn:7012149",
        "tgn:7029392"
    ],
    "tgn:id":2768657,
    "tgn:name":"Whitley Branch",
    "tgn:placetype":[
        "aat:300008699"
    ]
},
  "bbox": [],
  "geometry": {"coordinates":[-87.9,34.7167],"type":"Point"}
}
=======
{"geometry":{"type":"Point","coordinates":[-87.900000,34.716700]},"type":"Feature","properties":{"hierarchy":["tgn:2768657","tgn:7002659","tgn:1000001","tgn:2000016","tgn:7012149","tgn:7029392"],"placetype":["aat:300008699"],"id":2768657,"name:xx":"Whitley Branch"}}
>>>>>>> 03f74aca74312dbeaf24d7e61306dd6a786dc3d0
