{
  "id": 2481890,
  "type": "Feature",
  "properties": {
    "tgn:hierarchy":[
        "tgn:2481890",
        "tgn:1000001",
        "tgn:7012149",
        "tgn:2000206",
        "tgn:7007158",
        "tgn:7029392"
    ],
    "tgn:id":2481890,
    "tgn:name":"Landsend Peak",
    "tgn:placetype":[
        "aat:300008798"
    ]
},
  "bbox": [],
  "geometry": {"coordinates":[-107.55,38.7667],"type":"Point"}
}