{
  "id": 2020219,
  "type": "Feature",
  "properties": {
    "tgn:hierarchy":[
        "tgn:2020219",
        "tgn:1000001",
        "tgn:7012149",
        "tgn:2000279",
        "tgn:7007240",
        "tgn:7029392"
    ],
    "tgn:id":2020219,
    "tgn:name":"Lovett",
    "tgn:placetype":[
        "aat:300387016"
    ]
},
  "bbox": [],
  "geometry": {"coordinates":[-83.5667,30.6167],"type":"Point"}
}