{
  "id": 2672862,
  "type": "Feature",
  "properties": {
    "tgn:hierarchy":[
        "tgn:2672862",
        "tgn:1000001",
        "tgn:7012149",
        "tgn:2000227",
        "tgn:7007158",
        "tgn:7029392"
    ],
    "tgn:id":2672862,
    "tgn:name":"Snake Canyon",
    "tgn:placetype":[
        "aat:300008761"
    ]
},
  "bbox": [],
  "geometry": {"coordinates":[-104.9167,37.1667],"type":"Point"}
}