{
  "id": 7567089,
  "type": "Feature",
  "properties": {
    "tgn:hierarchy":[
        "tgn:7567089",
        "tgn:1000004",
        "tgn:7000198",
        "tgn:7001797",
        "tgn:7029392"
    ],
    "tgn:id":7567089,
    "tgn:name:en":"Ko-Su-Mani Nagar",
    "tgn:placetype":[
        "aat:300000745"
    ]
},
  "bbox": [],
  "geometry": {"coordinates":[80.235833,13.053333],"type":"Point"}
}