{
  "id": 2032599,
  "type": "Feature",
  "properties": {
    "tgn:hierarchy":[
        "tgn:2032599",
        "tgn:1000001",
        "tgn:7012149",
        "tgn:1002396",
        "tgn:7007252",
        "tgn:7029392"
    ],
    "tgn:id":2032599,
    "tgn:name":"Leiters Ford",
    "tgn:placetype":[
        "aat:300008347"
    ]
},
  "bbox": [],
  "geometry": {"coordinates":[-86.3833,41.1167],"type":"Point"}
}