{
  "id": 7333949,
  "type": "Feature",
  "properties": {
    "tgn:hierarchy":[
        "tgn:7333949",
        "tgn:7001165",
        "tgn:1000003",
        "tgn:7002793",
        "tgn:1000095",
        "tgn:7029392"
    ],
    "tgn:id":7333949,
    "tgn:name":"\u00c9nguera, Sierra de",
    "tgn:placetype":[
        "aat:300266640"
    ]
},
  "bbox": [],
  "geometry": {"coordinates":[-0.75,38.983333],"type":"Point"}
}