{
  "id": 1132776,
  "type": "Feature",
  "properties": {
    "tgn:hierarchy":[
        "tgn:1132776",
        "tgn:1000001",
        "tgn:7012149",
        "tgn:1003017",
        "tgn:7007710",
        "tgn:7029392"
    ],
    "tgn:id":1132776,
    "tgn:name":"Chartiers Run",
    "tgn:placetype":[
        "aat:300008706"
    ]
},
  "bbox": [],
  "geometry": {"coordinates":[-79.6667,40.5667],"type":"Point"}
}