<<<<<<< HEAD
{
  "id": 7470257,
  "type": "Feature",
  "properties": {
    "tgn:hierarchy":[
        "tgn:7470257",
        "tgn:1000004",
        "tgn:7001009",
        "tgn:1000141",
        "tgn:7029392"
    ],
    "tgn:id":7470257,
    "tgn:name":"Shanghengshan",
    "tgn:placetype":[
        "aat:300008347"
    ]
},
  "bbox": [],
  "geometry": {"coordinates":[120.629509,24.20965],"type":"Point"}
}
=======
{"geometry":{"type":"Point","coordinates":[120.629509,24.209650]},"type":"Feature","properties":{"hierarchy":["tgn:7470257","tgn:1000004","tgn:7001009","tgn:1000141","tgn:7029392"],"placetype":["aat:300008347"],"id":7470257,"name:xx":"Shanghengshan"}}
>>>>>>> 03f74aca74312dbeaf24d7e61306dd6a786dc3d0
