{
  "id": 7470257,
  "type": "Feature",
  "properties": {
    "tgn:hierarchy":[
        "tgn:7470257",
        "tgn:1000004",
        "tgn:7001009",
        "tgn:1000141",
        "tgn:7029392"
    ],
    "tgn:id":7470257,
    "tgn:name":"Shanghengshan",
    "tgn:placetype":[
        "aat:300008347"
    ]
},
  "bbox": [],
  "geometry": {"coordinates":[120.629509,24.20965],"type":"Point"}
}