{
  "id": 2121546,
  "type": "Feature",
  "properties": {
    "tgn:hierarchy":[
        "tgn:2121546",
        "tgn:1000001",
        "tgn:7012149",
        "tgn:2002359",
        "tgn:7007922",
        "tgn:7029392"
    ],
    "tgn:id":2121546,
    "tgn:name":"Lac du Flambeau",
    "tgn:placetype":[
        "aat:300008347"
    ]
},
  "bbox": [],
  "geometry": {"coordinates":[-89.8833,45.9667],"type":"Point"}
}