{
  "id": 1023622,
  "type": "Feature",
  "properties": {
    "tgn:hierarchy":[
        "tgn:1023622",
        "tgn:1001657",
        "tgn:1000049",
        "tgn:1000002",
        "tgn:7029392"
    ],
    "tgn:id":1023622,
    "tgn:name":"Salamanca",
    "tgn:placetype":[
        "aat:300008347"
    ]
},
  "bbox": [],
  "geometry": {"coordinates":[-70.972222,-31.775],"type":"Point"}
}