{
  "id": 7453164,
  "type": "Feature",
  "properties": {
    "tgn:hierarchy":[
        "tgn:7453164",
        "tgn:7002443",
        "tgn:1000003",
        "tgn:7008050",
        "tgn:7008591",
        "tgn:7029392"
    ],
    "tgn:id":7453164,
    "tgn:name:en":"Doldowlod House",
    "tgn:placetype":[
        "aat:300004792"
    ]
},
  "bbox": [],
  "geometry": {"coordinates":[-3.45,52.233333],"type":"Point"}
}