<<<<<<< HEAD
{
  "id": 2762117,
  "type": "Feature",
  "properties": {
    "tgn:hierarchy":[
        "tgn:2762117",
        "tgn:1000001",
        "tgn:7012149",
        "tgn:2002340",
        "tgn:7007922",
        "tgn:7029392"
    ],
    "tgn:id":2762117,
    "tgn:name":"West Silver Lake",
    "tgn:placetype":[
        "aat:300006191"
    ]
},
  "bbox": [],
  "geometry": {"coordinates":[-90.7167,43.95],"type":"Point"}
}
=======
{"geometry":{"type":"Point","coordinates":[-90.716700,43.950000]},"type":"Feature","properties":{"hierarchy":["tgn:2762117","tgn:1000001","tgn:7012149","tgn:2002340","tgn:7007922","tgn:7029392"],"placetype":["aat:300006191"],"id":2762117,"name:xx":"West Silver Lake"}}
>>>>>>> 03f74aca74312dbeaf24d7e61306dd6a786dc3d0
