{
  "id": 7305758,
  "type": "Feature",
  "properties": {
    "tgn:hierarchy":[
        "tgn:7305758",
        "tgn:7008912",
        "tgn:7030216",
        "tgn:1000003",
        "tgn:1000095",
        "tgn:7029392"
    ],
    "tgn:id":7305758,
    "tgn:name":"Mayor, Lago",
    "tgn:placetype":[
        "aat:300008680"
    ]
},
  "bbox": [],
  "geometry": {"coordinates":[0.983333,42.616667],"type":"Point"}
}