{
  "id": 2784994,
  "type": "Feature",
  "properties": {
    "tgn:hierarchy":[
        "tgn:2784994",
        "tgn:1000001",
        "tgn:7012149",
        "tgn:7007157",
        "tgn:2000185",
        "tgn:7029392"
    ],
    "tgn:id":2784994,
    "tgn:name":"Yellow Hound Ridge",
    "tgn:placetype":[
        "aat:300266640"
    ]
},
  "bbox": [],
  "geometry": {"coordinates":[-123.4333,38.8167],"type":"Point"}
}