{
  "id": 1017747,
  "type": "Feature",
  "properties": {
    "tgn:hierarchy":[
        "tgn:1017747",
        "tgn:7005580",
        "tgn:1000001",
        "tgn:7005560",
        "tgn:7029392"
    ],
    "tgn:id":1017747,
    "tgn:name":"Las Delicias",
    "tgn:placetype":[
        "aat:300008347"
    ]
},
  "bbox": [],
  "geometry": {"coordinates":[-91.85,15.966667],"type":"Point"}
}