{
  "id": 7373622,
  "type": "Feature",
  "properties": {
    "tgn:hierarchy":[
        "tgn:7373622",
        "tgn:7005581",
        "tgn:1000001",
        "tgn:7005560",
        "tgn:7029392"
    ],
    "tgn:id":7373622,
    "tgn:name":"La Arenosa, Arroyo",
    "tgn:placetype":[
        "aat:300008699"
    ]
},
  "bbox": [],
  "geometry": {"coordinates":[-104.066667,29.333333],"type":"Point"}
}