<<<<<<< HEAD
{
  "id": 7373622,
  "type": "Feature",
  "properties": {
    "tgn:hierarchy":[
        "tgn:7373622",
        "tgn:7005581",
        "tgn:1000001",
        "tgn:7005560",
        "tgn:7029392"
    ],
    "tgn:id":7373622,
    "tgn:name":"La Arenosa, Arroyo",
    "tgn:placetype":[
        "aat:300008699"
    ]
},
  "bbox": [],
  "geometry": {"coordinates":[-104.066667,29.333333],"type":"Point"}
}
=======
{"geometry":{"type":"Point","coordinates":[-104.066667,29.333333]},"type":"Feature","properties":{"hierarchy":["tgn:7373622","tgn:7005581","tgn:1000001","tgn:7005560","tgn:7029392"],"placetype":["aat:300008699"],"id":7373622,"name:xx":"La Arenosa, Arroyo"}}
>>>>>>> 03f74aca74312dbeaf24d7e61306dd6a786dc3d0
