{
  "id": 2231956,
  "type": "Feature",
  "properties": {
    "tgn:hierarchy":[
        "tgn:2231956",
        "tgn:1000001",
        "tgn:7012149",
        "tgn:7007157",
        "tgn:1002684",
        "tgn:7029392"
    ],
    "tgn:id":2231956,
    "tgn:name":"Chamisal Ridge",
    "tgn:placetype":[
        "aat:300266640"
    ]
},
  "bbox": [],
  "geometry": {"coordinates":[-121.8167,36.4667],"type":"Point"}
}