{
  "id": 7380807,
  "type": "Feature",
  "properties": {
    "tgn:hierarchy":[
        "tgn:7380807",
        "tgn:7005580",
        "tgn:1000001",
        "tgn:7005560",
        "tgn:7029392"
    ],
    "tgn:id":7380807,
    "tgn:name":"Los Limones",
    "tgn:placetype":[
        "aat:300008347"
    ]
},
  "bbox": [],
  "geometry": {"coordinates":[-93.833333,16.166667],"type":"Point"}
}