{
  "id": 7285254,
  "type": "Feature",
  "properties": {
    "tgn:hierarchy":[
        "tgn:7285254",
        "tgn:7002464",
        "tgn:1000049",
        "tgn:1000002",
        "tgn:7029392"
    ],
    "tgn:id":7285254,
    "tgn:name":"Quero, Aguada de",
    "tgn:placetype":[
        "aat:300008697"
    ]
},
  "bbox": [],
  "geometry": {"coordinates":[-69.833333,-18.666667],"type":"Point"}
}