{
  "id": 2729621,
  "type": "Feature",
  "properties": {
    "tgn:hierarchy":[
        "tgn:2729621",
        "tgn:1000001",
        "tgn:7012149",
        "tgn:2001157",
        "tgn:7007522",
        "tgn:7029392"
    ],
    "tgn:id":2729621,
    "tgn:name":"Trotter Landing",
    "tgn:placetype":[
        "aat:300008347"
    ]
},
  "bbox": [],
  "geometry": {"coordinates":[-90.5167,34.5333],"type":"Point"}
}