{
  "id": 7066706,
  "type": "Feature",
  "properties": {
    "tgn:hierarchy":[
        "tgn:7066706",
        "tgn:7003692",
        "tgn:1000003",
        "tgn:7000084",
        "tgn:7029392"
    ],
    "tgn:id":7066706,
    "tgn:name":"St\u00f6cken",
    "tgn:placetype":[
        "aat:300000206"
    ]
},
  "bbox": [],
  "geometry": {"coordinates":[8.05,48.316667],"type":"Point"}
}