<<<<<<< HEAD
{
  "id": 7487783,
  "type": "Feature",
  "properties": {
    "tgn:hierarchy":[
        "tgn:7487783",
        "tgn:1000004",
        "tgn:7489179",
        "tgn:1000141",
        "tgn:7029392"
    ],
    "tgn:id":7487783,
    "tgn:name:en":"Ta Nan Ao, River",
    "tgn:placetype":[
        "aat:300008699"
    ]
},
  "bbox": [],
  "geometry": {"coordinates":[121.816111,24.45],"type":"Point"}
}
=======
{"geometry":{"type":"Point","coordinates":[121.816111,24.450000]},"type":"Feature","properties":{"hierarchy":["tgn:7487783","tgn:1000004","tgn:7489179","tgn:1000141","tgn:7029392"],"placetype":["aat:300008699"],"name:en":"Ta Nan Ao, River","id":7487783}}
>>>>>>> 03f74aca74312dbeaf24d7e61306dd6a786dc3d0
