{
  "id": 7315972,
  "type": "Feature",
  "properties": {
    "tgn:hierarchy":[
        "tgn:7315972",
        "tgn:1001692",
        "tgn:1000049",
        "tgn:1000002",
        "tgn:7029392"
    ],
    "tgn:id":7315972,
    "tgn:name":"Cayulfu",
    "tgn:placetype":[
        "aat:300008347"
    ]
},
  "bbox": [],
  "geometry": {"coordinates":[-73.216667,-39.333333],"type":"Point"}
}