{
  "id": 2743402,
  "type": "Feature",
  "properties": {
    "tgn:hierarchy":[
        "tgn:2743402",
        "tgn:1000001",
        "tgn:7012149",
        "tgn:2001720",
        "tgn:7007708",
        "tgn:7029392"
    ],
    "tgn:id":2743402,
    "tgn:name":"Vansycle",
    "tgn:placetype":[
        "aat:300008347"
    ]
},
  "bbox": [],
  "geometry": {"coordinates":[-118.7167,45.9333],"type":"Point"}
}