{
  "id": 7037888,
  "type": "Feature",
  "properties": {
    "tgn:hierarchy":[
        "tgn:7037888",
        "tgn:1003464",
        "tgn:1000003",
        "tgn:7003241",
        "tgn:1000080",
        "tgn:7029392"
    ],
    "tgn:id":7037888,
    "tgn:name":"Vandra, Torrente",
    "tgn:placetype":[
        "aat:300008699"
    ]
},
  "bbox": [],
  "geometry": {"coordinates":[14.133333,41.55],"type":"Point"}
}