{
  "id": 2724387,
  "type": "Feature",
  "properties": {
    "tgn:hierarchy":[
        "tgn:2724387",
        "tgn:1008293",
        "tgn:1000001",
        "tgn:1002705",
        "tgn:7012149",
        "tgn:7007517",
        "tgn:7029392"
    ],
    "tgn:id":2724387,
    "tgn:name":"Tom Nevers Swamp",
    "tgn:placetype":[
        "aat:300008905"
    ]
},
  "bbox": [],
  "geometry": {"coordinates":[-69.9833,41.25],"type":"Point"}
}