{
  "id": 2651963,
  "type": "Feature",
  "properties": {
    "tgn:hierarchy":[
        "tgn:2651963",
        "tgn:1000001",
        "tgn:7012149",
        "tgn:1003042",
        "tgn:7007920",
        "tgn:7029392"
    ],
    "tgn:id":2651963,
    "tgn:name":"Selah Creek",
    "tgn:placetype":[
        "aat:300008706"
    ]
},
  "bbox": [],
  "geometry": {"coordinates":[-120.0667,46.5833],"type":"Point"}
}