{
  "id": 7399997,
  "type": "Feature",
  "properties": {
    "tgn:hierarchy":[
        "tgn:7399997",
        "tgn:1000001",
        "tgn:7005593",
        "tgn:7005560",
        "tgn:7029392"
    ],
    "tgn:id":7399997,
    "tgn:name":"El Malacate, Cerro",
    "tgn:placetype":[
        "aat:300008795"
    ]
},
  "bbox": [],
  "geometry": {"coordinates":[-99.65,21.380556],"type":"Point"}
}