{
  "id": 1019240,
  "type": "Feature",
  "properties": {
    "tgn:hierarchy":[
        "tgn:1019240",
        "tgn:1001160",
        "tgn:7006477",
        "tgn:1000002",
        "tgn:7029392"
    ],
    "tgn:id":1019240,
    "tgn:name":"Cabildo",
    "tgn:placetype":[
        "aat:300008347"
    ]
},
  "bbox": [],
  "geometry": {"coordinates":[-61.8333,-38.4667],"type":"Point"}
}