{
  "id": 7576534,
  "type": "Feature",
  "properties": {
    "tgn:hierarchy":[
        "tgn:7576534",
        "tgn:1000004",
        "tgn:7000198",
        "tgn:7031786",
        "tgn:7029392"
    ],
    "tgn:id":7576534,
    "tgn:name:en":"Kandogal",
    "tgn:placetype":[
        "aat:300008347"
    ]
},
  "bbox": [],
  "geometry": {"coordinates":[78.216667,30.233333],"type":"Point"}
}