{
  "id": 7435830,
  "type": "Feature",
  "properties": {
    "tgn:hierarchy":[
        "tgn:7435830",
        "tgn:1000001",
        "tgn:7005595",
        "tgn:7005560",
        "tgn:7029392"
    ],
    "tgn:id":7435830,
    "tgn:name":"Soquitit\u00e1n",
    "tgn:placetype":[
        "aat:300008347"
    ]
},
  "bbox": [],
  "geometry": {"coordinates":[-106.696111,24.189722],"type":"Point"}
}