{
  "id": 2262983,
  "type": "Feature",
  "properties": {
    "tgn:hierarchy":[
        "tgn:2262983",
        "tgn:1000001",
        "tgn:7012149",
        "tgn:2001750",
        "tgn:7007712",
        "tgn:7029392"
    ],
    "tgn:id":2262983,
    "tgn:name":"Cowford Swamp",
    "tgn:placetype":[
        "aat:300008699"
    ]
},
  "bbox": [],
  "geometry": {"coordinates":[-79.0833,33.7167],"type":"Point"}
}