{
  "id": 2497857,
  "type": "Feature",
  "properties": {
    "tgn:hierarchy":[
        "tgn:2497857",
        "tgn:1000001",
        "tgn:7012149",
        "tgn:2001926",
        "tgn:7007825",
        "tgn:7029392"
    ],
    "tgn:id":2497857,
    "tgn:name":"Mayflower",
    "tgn:placetype":[
        "aat:300008347"
    ]
},
  "bbox": [],
  "geometry": {"coordinates":[-82.5333,36.3167],"type":"Point"}
}