{
  "id": 7246837,
  "type": "Feature",
  "properties": {
    "tgn:hierarchy":[
        "tgn:7246837",
        "tgn:7003465",
        "tgn:1000003",
        "tgn:1000063",
        "tgn:4012014",
        "tgn:7029392"
    ],
    "tgn:id":7246837,
    "tgn:name":"Croisette de Rossignol",
    "tgn:placetype":[
        "aat:300008863"
    ]
},
  "bbox": [],
  "geometry": {"coordinates":[5.466667,49.733333],"type":"Point"}
}