{
  "id": 7252152,
  "type": "Feature",
  "properties": {
    "tgn:hierarchy":[
        "tgn:7252152",
        "tgn:7007877",
        "tgn:1000003",
        "tgn:1000063",
        "tgn:4012014",
        "tgn:7029392"
    ],
    "tgn:id":7252152,
    "tgn:name":"Menu Bois",
    "tgn:placetype":[
        "aat:300008863"
    ]
},
  "bbox": [],
  "geometry": {"coordinates":[4.166667,50.383333],"type":"Point"}
}