{
  "id": 2426635,
  "type": "Feature",
  "properties": {
    "tgn:hierarchy":[
        "tgn:2426635",
        "tgn:2124017",
        "tgn:7006450",
        "tgn:1000001",
        "tgn:7012149",
        "tgn:7029392"
    ],
    "tgn:id":2426635,
    "tgn:name":"Jones Lake",
    "tgn:placetype":[
        "aat:300008680"
    ]
},
  "bbox": [],
  "geometry": {"coordinates":[-149.95,61.1833],"type":"Point"}
}