{
  "id": 2055058,
  "type": "Feature",
  "properties": {
    "tgn:hierarchy":[
        "tgn:2055058",
        "tgn:1000001",
        "tgn:2001010",
        "tgn:7012149",
        "tgn:7007521",
        "tgn:7029392"
    ],
    "tgn:id":2055058,
    "tgn:name":"Montevideo",
    "tgn:placetype":[
        "aat:300008347"
    ]
},
  "bbox": [],
  "geometry": {"coordinates":[-95.7167,44.9333],"type":"Point"}
}