{
  "id": 7475722,
  "type": "Feature",
  "properties": {
    "tgn:hierarchy":[
        "tgn:7475722",
        "tgn:7488858",
        "tgn:1000004",
        "tgn:1000141",
        "tgn:7029392"
    ],
    "tgn:id":7475722,
    "tgn:name":"Yanhe Guozhong",
    "tgn:placetype":[
        "aat:300006495"
    ]
},
  "bbox": [],
  "geometry": {"coordinates":[120.6824,23.752177],"type":"Point"}
}