<<<<<<< HEAD
{
  "id": 7475722,
  "type": "Feature",
  "properties": {
    "tgn:hierarchy":[
        "tgn:7475722",
        "tgn:7488858",
        "tgn:1000004",
        "tgn:1000141",
        "tgn:7029392"
    ],
    "tgn:id":7475722,
    "tgn:name":"Yanhe Guozhong",
    "tgn:placetype":[
        "aat:300006495"
    ]
},
  "bbox": [],
  "geometry": {"coordinates":[120.6824,23.752177],"type":"Point"}
}
=======
{"geometry":{"type":"Point","coordinates":[120.682400,23.752177]},"type":"Feature","properties":{"hierarchy":["tgn:7475722","tgn:7488858","tgn:1000004","tgn:1000141","tgn:7029392"],"placetype":["aat:300006495"],"id":7475722,"name:xx":"Yanhe Guozhong"}}
>>>>>>> 03f74aca74312dbeaf24d7e61306dd6a786dc3d0
