{
  "id": 2609376,
  "type": "Feature",
  "properties": {
    "tgn:hierarchy":[
        "tgn:2609376",
        "tgn:1000001",
        "tgn:7012149",
        "tgn:2002371",
        "tgn:7007923",
        "tgn:7029392"
    ],
    "tgn:id":2609376,
    "tgn:name":"Ray Lake",
    "tgn:placetype":[
        "aat:300006191"
    ]
},
  "bbox": [],
  "geometry": {"coordinates":[-108.8167,42.95],"type":"Point"}
}