<<<<<<< HEAD
{
  "id": 2253464,
  "type": "Feature",
  "properties": {
    "tgn:hierarchy":[
        "tgn:2253464",
        "tgn:2002101",
        "tgn:1000001",
        "tgn:7012149",
        "tgn:7007827",
        "tgn:7029392"
    ],
    "tgn:id":2253464,
    "tgn:name":"Cook Corner",
    "tgn:placetype":[
        "aat:300008347"
    ]
},
  "bbox": [],
  "geometry": {"coordinates":[-113.0333,38.2833],"type":"Point"}
}
=======
{"geometry":{"type":"Point","coordinates":[-113.033300,38.283300]},"type":"Feature","properties":{"hierarchy":["tgn:2253464","tgn:2002101","tgn:1000001","tgn:7012149","tgn:7007827","tgn:7029392"],"placetype":["aat:300008347"],"id":2253464,"name:xx":"Cook Corner"}}
>>>>>>> 03f74aca74312dbeaf24d7e61306dd6a786dc3d0
