{
  "id": 7132646,
  "type": "Feature",
  "properties": {
    "tgn:hierarchy":[
        "tgn:7132646",
        "tgn:1000003",
        "tgn:7003678",
        "tgn:7000084",
        "tgn:7029392"
    ],
    "tgn:id":7132646,
    "tgn:name":"Landkreis Marburg-Biedenkopf",
    "tgn:placetype":[
        "aat:300387198"
    ]
},
  "bbox": [],
  "geometry": {"coordinates":[8.777778,50.840278],"type":"Point"}
}