<<<<<<< HEAD
{
  "id": 7173831,
  "type": "Feature",
  "properties": {
    "tgn:hierarchy":[
        "tgn:7173831",
        "tgn:1000003",
        "tgn:7003689",
        "tgn:7000084",
        "tgn:7029392"
    ],
    "tgn:id":7173831,
    "tgn:name":"Gro\u00dfmonra",
    "tgn:placetype":[
        "aat:300008347"
    ]
},
  "bbox": [],
  "geometry": {"coordinates":[11.3,51.216667],"type":"Point"}
}
=======
{"geometry":{"type":"Point","coordinates":[11.300000,51.216667]},"type":"Feature","properties":{"hierarchy":["tgn:7173831","tgn:1000003","tgn:7003689","tgn:7000084","tgn:7029392"],"placetype":["aat:300008347"],"id":7173831,"name:xx":"Gro\u00dfmonra"}}
>>>>>>> 03f74aca74312dbeaf24d7e61306dd6a786dc3d0
