{
  "id": 7496719,
  "type": "Feature",
  "properties": {
    "tgn:hierarchy":[
        "tgn:7496719",
        "tgn:1000004",
        "tgn:1000454",
        "tgn:1000141",
        "tgn:7029392"
    ],
    "tgn:id":7496719,
    "tgn:name":"Longshanyan",
    "tgn:placetype":[
        "aat:300008347"
    ]
},
  "bbox": [],
  "geometry": {"coordinates":[121.354925,24.871716],"type":"Point"}
}