{
  "id": 7369245,
  "type": "Feature",
  "properties": {
    "tgn:hierarchy":[
        "tgn:7369245",
        "tgn:1000001",
        "tgn:7005597",
        "tgn:7005560",
        "tgn:7029392"
    ],
    "tgn:id":7369245,
    "tgn:name":"Hoya Concepci\u00f3n",
    "tgn:placetype":[
        "aat:300008347"
    ]
},
  "bbox": [],
  "geometry": {"coordinates":[-99.866667,23.35],"type":"Point"}
}