{
  "id": 2129169,
  "type": "Feature",
  "properties": {
    "tgn:hierarchy":[
        "tgn:2129169",
        "tgn:7006450",
        "tgn:1000001",
        "tgn:2124053",
        "tgn:7012149",
        "tgn:7029392"
    ],
    "tgn:id":2129169,
    "tgn:name":"Alger Peak",
    "tgn:placetype":[
        "aat:300008798"
    ]
},
  "bbox": [],
  "geometry": {"coordinates":[-152.55,61.9333],"type":"Point"}
}