{
  "id": 7195220,
  "type": "Feature",
  "properties": {
    "tgn:hierarchy":[
        "tgn:7195220",
        "tgn:1000003",
        "tgn:7003677",
        "tgn:7000084",
        "tgn:7029392"
    ],
    "tgn:id":7195220,
    "tgn:name":"Diedrichshof",
    "tgn:placetype":[
        "aat:300000206"
    ]
},
  "bbox": [],
  "geometry": {"coordinates":[7.466667,50.766667],"type":"Point"}
}