{
  "id": 1039076,
  "type": "Feature",
  "properties": {
    "tgn:hierarchy":[
        "tgn:1039076",
        "tgn:7003692",
        "tgn:1000003",
        "tgn:7000084",
        "tgn:7029392"
    ],
    "tgn:id":1039076,
    "tgn:name":"Feldstetten",
    "tgn:placetype":[
        "aat:300008347"
    ]
},
  "bbox": [],
  "geometry": {"coordinates":[9.633333,48.483333],"type":"Point"}
}