<<<<<<< HEAD
{
  "id": 2330842,
  "type": "Feature",
  "properties": {
    "tgn:hierarchy":[
        "tgn:2330842",
        "tgn:1000001",
        "tgn:7012149",
        "tgn:7007157",
        "tgn:1002656",
        "tgn:7029392"
    ],
    "tgn:id":2330842,
    "tgn:name":"Flat Pond",
    "tgn:placetype":[
        "aat:300008680"
    ]
},
  "bbox": [],
  "geometry": {"coordinates":[-120.75,37.0333],"type":"Point"}
}
=======
{"geometry":{"type":"Point","coordinates":[-120.750000,37.033300]},"type":"Feature","properties":{"hierarchy":["tgn:2330842","tgn:1000001","tgn:7012149","tgn:7007157","tgn:1002656","tgn:7029392"],"placetype":["aat:300008680"],"id":2330842,"name:xx":"Flat Pond"}}
>>>>>>> 03f74aca74312dbeaf24d7e61306dd6a786dc3d0
