{
  "id": 2330842,
  "type": "Feature",
  "properties": {
    "tgn:hierarchy":[
        "tgn:2330842",
        "tgn:1000001",
        "tgn:7012149",
        "tgn:7007157",
        "tgn:1002656",
        "tgn:7029392"
    ],
    "tgn:id":2330842,
    "tgn:name":"Flat Pond",
    "tgn:placetype":[
        "aat:300008680"
    ]
},
  "bbox": [],
  "geometry": {"coordinates":[-120.75,37.0333],"type":"Point"}
}