{
  "id": 2550656,
  "type": "Feature",
  "properties": {
    "tgn:hierarchy":[
        "tgn:2550656",
        "tgn:1000001",
        "tgn:7012149",
        "tgn:1002350",
        "tgn:7007157",
        "tgn:7029392"
    ],
    "tgn:id":2550656,
    "tgn:name":"Norton Ravine",
    "tgn:placetype":[
        "aat:300008761"
    ]
},
  "bbox": [],
  "geometry": {"coordinates":[-121.0167,38.8167],"type":"Point"}
}