{
  "id": 7255580,
  "type": "Feature",
  "properties": {
    "tgn:hierarchy":[
        "tgn:7255580",
        "tgn:7003466",
        "tgn:1000003",
        "tgn:1000063",
        "tgn:4012014",
        "tgn:7029392"
    ],
    "tgn:id":7255580,
    "tgn:name":"Rosette, Bois de",
    "tgn:placetype":[
        "aat:300008863"
    ]
},
  "bbox": [],
  "geometry": {"coordinates":[4.483333,50.216667],"type":"Point"}
}