{
  "id": 2613245,
  "type": "Feature",
  "properties": {
    "tgn:hierarchy":[
        "tgn:2613245",
        "tgn:1000001",
        "tgn:7012149",
        "tgn:2001109",
        "tgn:7007522",
        "tgn:7029392"
    ],
    "tgn:id":2613245,
    "tgn:name":"Reed Branch",
    "tgn:placetype":[
        "aat:300008699"
    ]
},
  "bbox": [],
  "geometry": {"coordinates":[-88.95,30.6167],"type":"Point"}
}