<<<<<<< HEAD
{
  "id": 2256429,
  "type": "Feature",
  "properties": {
    "tgn:hierarchy":[
        "tgn:2256429",
        "tgn:7006450",
        "tgn:1000001",
        "tgn:7012149",
        "tgn:2000088",
        "tgn:7029392"
    ],
    "tgn:id":2256429,
    "tgn:name":"Cora Point",
    "tgn:placetype":[
        "aat:300008850"
    ]
},
  "bbox": [],
  "geometry": {"coordinates":[-134.1,55.9],"type":"Point"}
}
=======
{"geometry":{"type":"Point","coordinates":[-134.100000,55.900000]},"type":"Feature","properties":{"hierarchy":["tgn:2256429","tgn:7006450","tgn:1000001","tgn:7012149","tgn:2000088","tgn:7029392"],"placetype":["aat:300008850"],"id":2256429,"name:xx":"Cora Point"}}
>>>>>>> 03f74aca74312dbeaf24d7e61306dd6a786dc3d0
