{
  "id": 2648318,
  "type": "Feature",
  "properties": {
    "tgn:hierarchy":[
        "tgn:2648318",
        "tgn:7013349",
        "tgn:1000001",
        "tgn:7012149",
        "tgn:7007708",
        "tgn:7029392"
    ],
    "tgn:id":2648318,
    "tgn:name":"Schuck Waterhole",
    "tgn:placetype":[
        "aat:300006191"
    ]
},
  "bbox": [],
  "geometry": {"coordinates":[-117.4667,44.65],"type":"Point"}
}