{
  "id": 1058607,
  "type": "Feature",
  "properties": {
    "tgn:hierarchy":[
        "tgn:1058607",
        "tgn:1000004",
        "tgn:7011572",
        "tgn:7018214",
        "tgn:7002435",
        "tgn:7029392"
    ],
    "tgn:id":1058607,
    "tgn:name":"Porogi",
    "tgn:placetype":[
        "aat:300008347"
    ]
},
  "bbox": [],
  "geometry": {"coordinates":[30.7833,59.7667],"type":"Point"}
}