<<<<<<< HEAD
{
  "id": 2707172,
  "type": "Feature",
  "properties": {
    "tgn:hierarchy":[
        "tgn:2707172",
        "tgn:1000001",
        "tgn:2001008",
        "tgn:7012149",
        "tgn:7007521",
        "tgn:7029392"
    ],
    "tgn:id":2707172,
    "tgn:name":"Swede Lake",
    "tgn:placetype":[
        "aat:300008680"
    ]
},
  "bbox": [],
  "geometry": {"coordinates":[-93.8167,44.9167],"type":"Point"}
}
=======
{"geometry":{"type":"Point","coordinates":[-93.816700,44.916700]},"type":"Feature","properties":{"hierarchy":["tgn:2707172","tgn:1000001","tgn:2001008","tgn:7012149","tgn:7007521","tgn:7029392"],"placetype":["aat:300008680"],"id":2707172,"name:xx":"Swede Lake"}}
>>>>>>> 03f74aca74312dbeaf24d7e61306dd6a786dc3d0
