{
  "id": 2768693,
  "type": "Feature",
  "properties": {
    "tgn:hierarchy":[
        "tgn:2768693",
        "tgn:1000001",
        "tgn:7012149",
        "tgn:2000888",
        "tgn:7007256",
        "tgn:7029392"
    ],
    "tgn:id":2768693,
    "tgn:name":"Whitlock Creek",
    "tgn:placetype":[
        "aat:300008706"
    ]
},
  "bbox": [],
  "geometry": {"coordinates":[-93.4333,31.7167],"type":"Point"}
}