{
  "id": 2511463,
  "type": "Feature",
  "properties": {
    "tgn:hierarchy":[
        "tgn:2511463",
        "tgn:1000001",
        "tgn:7012149",
        "tgn:2000917",
        "tgn:7007256",
        "tgn:7029392"
    ],
    "tgn:id":2511463,
    "tgn:name":"Mile Branch",
    "tgn:placetype":[
        "aat:300008699"
    ]
},
  "bbox": [],
  "geometry": {"coordinates":[-92.85,32.05],"type":"Point"}
}