{
  "id": 7053223,
  "type": "Feature",
  "properties": {
    "tgn:hierarchy":[
        "tgn:7053223",
        "tgn:7003138",
        "tgn:1000003",
        "tgn:7003080",
        "tgn:1000080",
        "tgn:7029392"
    ],
    "tgn:id":7053223,
    "tgn:name":"Monte Maggiore",
    "tgn:placetype":[
        "aat:300008347"
    ]
},
  "bbox": [],
  "geometry": {"coordinates":[12.683333,42.15],"type":"Point"}
}