{
  "id": 7526726,
  "type": "Feature",
  "properties": {
    "tgn:hierarchy":[
        "tgn:7526726",
        "tgn:7001242",
        "tgn:7016833",
        "tgn:7001335",
        "tgn:7029392"
    ],
    "tgn:id":7526726,
    "tgn:name":"\u0162\u012bnah, Sahl a\u0163",
    "tgn:placetype":[
        "aat:300008805"
    ]
},
  "bbox": [],
  "geometry": {"coordinates":[32.593334,31.037859],"type":"Point"}
}