{
  "id": 7279532,
  "type": "Feature",
  "properties": {
    "tgn:hierarchy":[
        "tgn:7279532",
        "tgn:1001623",
        "tgn:1000049",
        "tgn:1000002",
        "tgn:7029392"
    ],
    "tgn:id":7279532,
    "tgn:name":"Raquel, Punta",
    "tgn:placetype":[
        "aat:300386846"
    ]
},
  "bbox": [],
  "geometry": {"coordinates":[-73.983333,-47.95],"type":"Point"}
}