<<<<<<< HEAD
{
  "id": 7485951,
  "type": "Feature",
  "properties": {
    "tgn:hierarchy":[
        "tgn:7485951",
        "tgn:7488858",
        "tgn:1000004",
        "tgn:1000141",
        "tgn:7029392"
    ],
    "tgn:id":7485951,
    "tgn:name":"Yuanweikeng",
    "tgn:placetype":[
        "aat:300008699"
    ]
},
  "bbox": [],
  "geometry": {"coordinates":[120.656389,23.733333],"type":"Point"}
}
=======
{"geometry":{"type":"Point","coordinates":[120.656389,23.733333]},"type":"Feature","properties":{"hierarchy":["tgn:7485951","tgn:7488858","tgn:1000004","tgn:1000141","tgn:7029392"],"placetype":["aat:300008699"],"id":7485951,"name:xx":"Yuanweikeng"}}
>>>>>>> 03f74aca74312dbeaf24d7e61306dd6a786dc3d0
