{
  "id": 2505939,
  "type": "Feature",
  "properties": {
    "tgn:hierarchy":[
        "tgn:2505939",
        "tgn:1000001",
        "tgn:7012149",
        "tgn:7007157",
        "tgn:1002863",
        "tgn:7029392"
    ],
    "tgn:id":2505939,
    "tgn:name":"Mercury Belle Mine",
    "tgn:placetype":[
        "aat:300000390"
    ]
},
  "bbox": [],
  "geometry": {"coordinates":[-120.45,35.2667],"type":"Point"}
}