<<<<<<< HEAD
{
  "id": 2337989,
  "type": "Feature",
  "properties": {
    "tgn:hierarchy":[
        "tgn:2337989",
        "tgn:1000001",
        "tgn:7012149",
        "tgn:2002111",
        "tgn:7007827",
        "tgn:7029392"
    ],
    "tgn:id":2337989,
    "tgn:name":"Fox Hollow Spring",
    "tgn:placetype":[
        "aat:300008697"
    ]
},
  "bbox": [],
  "geometry": {"coordinates":[-112.55,38.0],"type":"Point"}
}
=======
{"geometry":{"type":"Point","coordinates":[-112.550000,38.000000]},"type":"Feature","properties":{"hierarchy":["tgn:2337989","tgn:1000001","tgn:7012149","tgn:2002111","tgn:7007827","tgn:7029392"],"placetype":["aat:300008697"],"id":2337989,"name:xx":"Fox Hollow Spring"}}
>>>>>>> 03f74aca74312dbeaf24d7e61306dd6a786dc3d0
