{
  "id": 2340191,
  "type": "Feature",
  "properties": {
    "tgn:hierarchy":[
        "tgn:2340191",
        "tgn:1000001",
        "tgn:7012149",
        "tgn:2000926",
        "tgn:7007515",
        "tgn:7029392"
    ],
    "tgn:id":2340191,
    "tgn:name":"French Brook",
    "tgn:placetype":[
        "aat:300008699"
    ]
},
  "bbox": [],
  "geometry": {"coordinates":[-70.9833,44.4167],"type":"Point"}
}