{
  "id": 1006365,
  "type": "Feature",
  "properties": {
    "tgn:hierarchy":[
        "tgn:1006365",
        "tgn:1000223",
        "tgn:1000006",
        "tgn:7029392"
    ],
    "tgn:id":1006365,
    "tgn:name":"Baaba",
    "tgn:placetype":[
        "aat:300008791"
    ]
},
  "bbox": [],
  "geometry": {"coordinates":[163.9667,-20.0167],"type":"Point"}
}