{
  "id": 1095924,
  "type": "Feature",
  "properties": {
    "tgn:hierarchy":[
        "tgn:1095924",
        "tgn:1001187",
        "tgn:7001242",
        "tgn:1000209",
        "tgn:7029392"
    ],
    "tgn:id":1095924,
    "tgn:name":"Kabwe",
    "tgn:placetype":[
        "aat:300008347",
        "aat:300387223",
        "aat:300387305",
        "aat:300008375",
        "aat:300387270"
    ]
},
  "bbox": [],
  "geometry": {"coordinates":[28.4167,-14.4833],"type":"Point"}
}