{
  "id": 2447553,
  "type": "Feature",
  "properties": {
    "tgn:hierarchy":[
        "tgn:2447553",
        "tgn:1000001",
        "tgn:7013677",
        "tgn:7012149",
        "tgn:7007712",
        "tgn:7029392"
    ],
    "tgn:id":2447553,
    "tgn:name":"Lick Fork",
    "tgn:placetype":[
        "aat:300008699"
    ]
},
  "bbox": [],
  "geometry": {"coordinates":[-82.05,33.7333],"type":"Point"}
}