<<<<<<< HEAD
{
  "id": 2400767,
  "type": "Feature",
  "properties": {
    "tgn:hierarchy":[
        "tgn:2400767",
        "tgn:1002172",
        "tgn:1000001",
        "tgn:7012149",
        "tgn:7007710",
        "tgn:7029392"
    ],
    "tgn:id":2400767,
    "tgn:name":"Horse Pen Hollow",
    "tgn:placetype":[
        "aat:300008761"
    ]
},
  "bbox": [],
  "geometry": {"coordinates":[-78.4,39.9167],"type":"Point"}
}
=======
{"geometry":{"type":"Point","coordinates":[-78.400000,39.916700]},"type":"Feature","properties":{"hierarchy":["tgn:2400767","tgn:1002172","tgn:1000001","tgn:7012149","tgn:7007710","tgn:7029392"],"placetype":["aat:300008761"],"id":2400767,"name:xx":"Horse Pen Hollow"}}
>>>>>>> 03f74aca74312dbeaf24d7e61306dd6a786dc3d0
