{
  "id": 2435443,
  "type": "Feature",
  "properties": {
    "tgn:hierarchy":[
        "tgn:2435443",
        "tgn:1000001",
        "tgn:7012149",
        "tgn:1002545",
        "tgn:7007157",
        "tgn:7029392"
    ],
    "tgn:id":2435443,
    "tgn:name":"Kernell",
    "tgn:placetype":[
        "aat:300008347"
    ]
},
  "bbox": [],
  "geometry": {"coordinates":[-119.3333,35.75],"type":"Point"}
}