{
  "id": 7592891,
  "type": "Feature",
  "properties": {
    "tgn:hierarchy":[
        "tgn:7592891",
        "tgn:1000004",
        "tgn:7000198",
        "tgn:7000799",
        "tgn:7029392"
    ],
    "tgn:id":7592891,
    "tgn:name:en":"Mangler",
    "tgn:placetype":[
        "aat:300008347"
    ]
},
  "bbox": [],
  "geometry": {"coordinates":[74.300625,33.064055],"type":"Point"}
}