{
  "id": 2727832,
  "type": "Feature",
  "properties": {
    "tgn:hierarchy":[
        "tgn:2727832",
        "tgn:1000001",
        "tgn:2001747",
        "tgn:7012149",
        "tgn:7007712",
        "tgn:7029392"
    ],
    "tgn:id":2727832,
    "tgn:name":"Trammell Lake",
    "tgn:placetype":[
        "aat:300006191"
    ]
},
  "bbox": [],
  "geometry": {"coordinates":[-82.5333,35.1167],"type":"Point"}
}