{
  "id": 7377772,
  "type": "Feature",
  "properties": {
    "tgn:hierarchy":[
        "tgn:7377772",
        "tgn:1000001",
        "tgn:1001960",
        "tgn:7005560",
        "tgn:7029392"
    ],
    "tgn:id":7377772,
    "tgn:name":"La Ventura",
    "tgn:placetype":[
        "aat:300008347"
    ]
},
  "bbox": [],
  "geometry": {"coordinates":[-109.816667,30.25],"type":"Point"}
}