{
  "id": 7296014,
  "type": "Feature",
  "properties": {
    "tgn:hierarchy":[
        "tgn:7296014",
        "tgn:7002760",
        "tgn:1000003",
        "tgn:1000095",
        "tgn:7029392"
    ],
    "tgn:id":7296014,
    "tgn:name":"Galizano, Monte",
    "tgn:placetype":[
        "aat:300008795"
    ]
},
  "bbox": [],
  "geometry": {"coordinates":[-3.6275,43.470556],"type":"Point"}
}