{
  "id": 7034393,
  "type": "Feature",
  "properties": {
    "tgn:hierarchy":[
        "tgn:7034393",
        "tgn:1001641",
        "tgn:1000003",
        "tgn:7003121",
        "tgn:1000080",
        "tgn:7029392"
    ],
    "tgn:id":7034393,
    "tgn:name":"Torre delle Stelle",
    "tgn:placetype":[
        "aat:300008347"
    ]
},
  "bbox": [],
  "geometry": {"coordinates":[9.394722,39.149167],"type":"Point"}
}