{
  "id": 2546756,
  "type": "Feature",
  "properties": {
    "tgn:hierarchy":[
        "tgn:2546756",
        "tgn:1000001",
        "tgn:7012149",
        "tgn:2001286",
        "tgn:7007524",
        "tgn:7029392"
    ],
    "tgn:id":2546756,
    "tgn:name":"North Fork Meadow Creek",
    "tgn:placetype":[
        "aat:300008706"
    ]
},
  "bbox": [],
  "geometry": {"coordinates":[-116.0167,48.8333],"type":"Point"}
}