{
  "id": 7443879,
  "type": "Feature",
  "properties": {
    "tgn:hierarchy":[
        "tgn:7443879",
        "tgn:7002444",
        "tgn:1000003",
        "tgn:7009907",
        "tgn:7008591",
        "tgn:7029392"
    ],
    "tgn:id":7443879,
    "tgn:name:en":"West Skerries",
    "tgn:placetype":[
        "aat:300011692"
    ]
},
  "bbox": [],
  "geometry": {"coordinates":[-2.966667,59.033333],"type":"Point"}
}