{
  "id": 7353948,
  "type": "Feature",
  "properties": {
    "tgn:hierarchy":[
        "tgn:7353948",
        "tgn:7005581",
        "tgn:1000001",
        "tgn:7005560",
        "tgn:7029392"
    ],
    "tgn:id":7353948,
    "tgn:name":"Casa Colorada",
    "tgn:placetype":[
        "aat:300008347"
    ]
},
  "bbox": [],
  "geometry": {"coordinates":[-108.583333,27.566667],"type":"Point"}
}