{
  "id": 2376410,
  "type": "Feature",
  "properties": {
    "tgn:hierarchy":[
        "tgn:2376410",
        "tgn:1000001",
        "tgn:7012149",
        "tgn:2001455",
        "tgn:7007566",
        "tgn:7029392"
    ],
    "tgn:id":2376410,
    "tgn:name":"Harding",
    "tgn:placetype":[
        "aat:300000390"
    ]
},
  "bbox": [],
  "geometry": {"coordinates":[-107.2167,33.0333],"type":"Point"}
}