{
  "id": 7067282,
  "type": "Feature",
  "properties": {
    "tgn:hierarchy":[
        "tgn:7067282",
        "tgn:7000096",
        "tgn:1000003",
        "tgn:7000084",
        "tgn:7029392"
    ],
    "tgn:id":7067282,
    "tgn:name":"Stollense",
    "tgn:placetype":[
        "aat:300008699"
    ]
},
  "bbox": [],
  "geometry": {"coordinates":[12.316667,52.666667],"type":"Point"}
}