{
  "id": 2587096,
  "type": "Feature",
  "properties": {
    "tgn:hierarchy":[
        "tgn:2587096",
        "tgn:1000001",
        "tgn:2001176",
        "tgn:7012149",
        "tgn:7007523",
        "tgn:7029392"
    ],
    "tgn:id":2587096,
    "tgn:name":"Platanus",
    "tgn:placetype":[
        "aat:300008347"
    ]
},
  "bbox": [],
  "geometry": {"coordinates":[-90.25,36.5333],"type":"Point"}
}