{
  "id": 2126814,
  "type": "Feature",
  "properties": {
    "tgn:hierarchy":[
        "tgn:2126814",
        "tgn:1000001",
        "tgn:7012149",
        "tgn:2002383",
        "tgn:7007923",
        "tgn:7029392"
    ],
    "tgn:id":2126814,
    "tgn:name":"Agropyron Reservoir",
    "tgn:placetype":[
        "aat:300006191"
    ]
},
  "bbox": [],
  "geometry": {"coordinates":[-108.3167,41.05],"type":"Point"}
}