{
  "id": 7216345,
  "type": "Feature",
  "properties": {
    "tgn:hierarchy":[
        "tgn:7216345",
        "tgn:7003692",
        "tgn:1000003",
        "tgn:7000084",
        "tgn:7029392"
    ],
    "tgn:id":7216345,
    "tgn:name":"Aidlingen",
    "tgn:placetype":[
        "aat:300008347"
    ]
},
  "bbox": [],
  "geometry": {"coordinates":[8.916667,48.666667],"type":"Point"}
}