{
  "id": 1122262,
  "type": "Feature",
  "properties": {
    "tgn:hierarchy":[
        "tgn:1122262",
        "tgn:7001242",
        "tgn:1000149",
        "tgn:1000943",
        "tgn:7029392"
    ],
    "tgn:id":1122262,
    "tgn:name":"Buenga",
    "tgn:placetype":[
        "aat:300008707"
    ]
},
  "bbox": [],
  "geometry": {"coordinates":[15.9833,-6.2167],"type":"Point"}
}