{
  "id": 2332310,
  "type": "Feature",
  "properties": {
    "tgn:hierarchy":[
        "tgn:2332310",
        "tgn:1000001",
        "tgn:7012149",
        "tgn:7014589",
        "tgn:7007515",
        "tgn:7029392"
    ],
    "tgn:id":2332310,
    "tgn:name":"Flood Lake",
    "tgn:placetype":[
        "aat:300008680"
    ]
},
  "bbox": [],
  "geometry": {"coordinates":[-67.8167,45.3667],"type":"Point"}
}