<<<<<<< HEAD
{
  "id": 2332310,
  "type": "Feature",
  "properties": {
    "tgn:hierarchy":[
        "tgn:2332310",
        "tgn:1000001",
        "tgn:7012149",
        "tgn:7014589",
        "tgn:7007515",
        "tgn:7029392"
    ],
    "tgn:id":2332310,
    "tgn:name":"Flood Lake",
    "tgn:placetype":[
        "aat:300008680"
    ]
},
  "bbox": [],
  "geometry": {"coordinates":[-67.8167,45.3667],"type":"Point"}
}
=======
{"geometry":{"type":"Point","coordinates":[-67.816700,45.366700]},"type":"Feature","properties":{"hierarchy":["tgn:2332310","tgn:1000001","tgn:7012149","tgn:7014589","tgn:7007515","tgn:7029392"],"placetype":["aat:300008680"],"id":2332310,"name:xx":"Flood Lake"}}
>>>>>>> 03f74aca74312dbeaf24d7e61306dd6a786dc3d0
