<<<<<<< HEAD
{
  "id": 7487141,
  "type": "Feature",
  "properties": {
    "tgn:hierarchy":[
        "tgn:7487141",
        "tgn:7487020",
        "tgn:1000004",
        "tgn:1000141",
        "tgn:7029392"
    ],
    "tgn:id":7487141,
    "tgn:name":"Baishixia",
    "tgn:placetype":[
        "aat:300008347"
    ]
},
  "bbox": [],
  "geometry": {"coordinates":[120.846344,24.464157],"type":"Point"}
}
=======
{"geometry":{"type":"Point","coordinates":[120.846344,24.464157]},"type":"Feature","properties":{"hierarchy":["tgn:7487141","tgn:7487020","tgn:1000004","tgn:1000141","tgn:7029392"],"placetype":["aat:300008347"],"id":7487141,"name:xx":"Baishixia"}}
>>>>>>> 03f74aca74312dbeaf24d7e61306dd6a786dc3d0
