{
  "id": 7487141,
  "type": "Feature",
  "properties": {
    "tgn:hierarchy":[
        "tgn:7487141",
        "tgn:7487020",
        "tgn:1000004",
        "tgn:1000141",
        "tgn:7029392"
    ],
    "tgn:id":7487141,
    "tgn:name":"Baishixia",
    "tgn:placetype":[
        "aat:300008347"
    ]
},
  "bbox": [],
  "geometry": {"coordinates":[120.846344,24.464157],"type":"Point"}
}