{
  "id": 7231249,
  "type": "Feature",
  "properties": {
    "tgn:hierarchy":[
        "tgn:7231249",
        "tgn:7011369",
        "tgn:7017076",
        "tgn:1000003",
        "tgn:1000074",
        "tgn:7029392"
    ],
    "tgn:id":7231249,
    "tgn:name":"Kh\u00e1nia",
    "tgn:placetype":[
        "aat:300008347"
    ]
},
  "bbox": [],
  "geometry": {"coordinates":[21.916667,36.916667],"type":"Point"}
}