{
  "id": 2369734,
  "type": "Feature",
  "properties": {
    "tgn:hierarchy":[
        "tgn:2369734",
        "tgn:1000001",
        "tgn:7012149",
        "tgn:1002387",
        "tgn:7007710",
        "tgn:7029392"
    ],
    "tgn:id":2369734,
    "tgn:name":"Gunter Valley Reservoir",
    "tgn:placetype":[
        "aat:300006191"
    ]
},
  "bbox": [],
  "geometry": {"coordinates":[-77.6667,40.1333],"type":"Point"}
}