{
  "id": 1054563,
  "type": "Feature",
  "properties": {
    "tgn:hierarchy":[
        "tgn:1054563",
        "tgn:7011701",
        "tgn:1000003",
        "tgn:7006657",
        "tgn:7029392"
    ],
    "tgn:id":1054563,
    "tgn:name":"Yanovichi",
    "tgn:placetype":[
        "aat:300008347"
    ]
},
  "bbox": [],
  "geometry": {"coordinates":[30.7167,55.3333],"type":"Point"}
}