{
  "id": 7234226,
  "type": "Feature",
  "properties": {
    "tgn:hierarchy":[
        "tgn:7234226",
        "tgn:7002711",
        "tgn:7001338",
        "tgn:1000003",
        "tgn:1000074",
        "tgn:7029392"
    ],
    "tgn:id":7234226,
    "tgn:name":"Avl\u00e1ki, \u00c1kra",
    "tgn:placetype":[
        "aat:300008850"
    ]
},
  "bbox": [],
  "geometry": {"coordinates":[19.409444,39.840278],"type":"Point"}
}