{
  "id": 7028978,
  "type": "Feature",
  "properties": {
    "tgn:hierarchy":[
        "tgn:7028978",
        "tgn:7002445",
        "tgn:1000003",
        "tgn:7019057",
        "tgn:7008591",
        "tgn:7029392"
    ],
    "tgn:id":7028978,
    "tgn:name":"Foston-on-the-Wolds",
    "tgn:placetype":[
        "aat:300008347",
        "aat:300008372"
    ]
},
  "bbox": [],
  "geometry": {"coordinates":[-0.316667,53.983333],"type":"Point"}
}