{
  "id": 2122393,
  "type": "Feature",
  "properties": {
    "tgn:hierarchy":[
        "tgn:2122393",
        "tgn:1000001",
        "tgn:7020939",
        "tgn:7012149",
        "tgn:7007922",
        "tgn:7029392"
    ],
    "tgn:id":2122393,
    "tgn:name":"Silica",
    "tgn:placetype":[
        "aat:300008347"
    ]
},
  "bbox": [],
  "geometry": {"coordinates":[-88.3333,43.85],"type":"Point"}
}