{
  "id": 2554903,
  "type": "Feature",
  "properties": {
    "tgn:hierarchy":[
        "tgn:2554903",
        "tgn:1000001",
        "tgn:2001645",
        "tgn:7012149",
        "tgn:7007707",
        "tgn:7029392"
    ],
    "tgn:id":2554903,
    "tgn:name":"Oats Canyon",
    "tgn:placetype":[
        "aat:300008761"
    ]
},
  "bbox": [],
  "geometry": {"coordinates":[-99.5167,36.0333],"type":"Point"}
}