{
  "id": 7066396,
  "type": "Feature",
  "properties": {
    "tgn:hierarchy":[
        "tgn:7066396",
        "tgn:1000003",
        "tgn:7000094",
        "tgn:7000084",
        "tgn:7029392"
    ],
    "tgn:id":7066396,
    "tgn:name":"Uhtlat-See",
    "tgn:placetype":[
        "aat:300008688"
    ]
},
  "bbox": [],
  "geometry": {"coordinates":[14.15,53.266667],"type":"Point"}
}