{
  "id": 7583596,
  "type": "Feature",
  "properties": {
    "tgn:hierarchy":[
        "tgn:7583596",
        "tgn:1000004",
        "tgn:7000198",
        "tgn:1001894",
        "tgn:7029392"
    ],
    "tgn:id":7583596,
    "tgn:name:en":"Gudai",
    "tgn:placetype":[
        "aat:300008347"
    ]
},
  "bbox": [],
  "geometry": {"coordinates":[78.961335,25.183852],"type":"Point"}
}