{
  "id": 2626585,
  "type": "Feature",
  "properties": {
    "tgn:hierarchy":[
        "tgn:2626585",
        "tgn:1000001",
        "tgn:7012149",
        "tgn:2001556",
        "tgn:7007709",
        "tgn:7029392"
    ],
    "tgn:id":2626585,
    "tgn:name":"Rocky Knob",
    "tgn:placetype":[
        "aat:300008798"
    ]
},
  "bbox": [],
  "geometry": {"coordinates":[-82.4167,35.8833],"type":"Point"}
}