{
  "id": 1127851,
  "type": "Feature",
  "properties": {
    "tgn:hierarchy":[
        "tgn:1127851",
        "tgn:1000001",
        "tgn:7012149",
        "tgn:7007255",
        "tgn:7029392"
    ],
    "tgn:id":1127851,
    "tgn:name":"Nolin",
    "tgn:placetype":[
        "aat:300008707"
    ]
},
  "bbox": [],
  "geometry": {"coordinates":[-85.7833,37.5333],"type":"Point"}
}