<<<<<<< HEAD
{
  "id": 7050491,
  "type": "Feature",
  "properties": {
    "tgn:hierarchy":[
        "tgn:7050491",
        "tgn:1003440",
        "tgn:1000003",
        "tgn:7003124",
        "tgn:1000080",
        "tgn:7029392"
    ],
    "tgn:id":7050491,
    "tgn:name":"Laste",
    "tgn:placetype":[
        "aat:300008347"
    ]
},
  "bbox": [],
  "geometry": {"coordinates":[11.45,46.8],"type":"Point"}
}
=======
{"geometry":{"type":"Point","coordinates":[11.450000,46.800000]},"type":"Feature","properties":{"hierarchy":["tgn:7050491","tgn:1003440","tgn:1000003","tgn:7003124","tgn:1000080","tgn:7029392"],"placetype":["aat:300008347"],"id":7050491,"name:xx":"Laste"}}
>>>>>>> 03f74aca74312dbeaf24d7e61306dd6a786dc3d0
