<<<<<<< HEAD
{
  "id": 7472909,
  "type": "Feature",
  "properties": {
    "tgn:hierarchy":[
        "tgn:7472909",
        "tgn:1000004",
        "tgn:7004300",
        "tgn:1000141",
        "tgn:7029392"
    ],
    "tgn:id":7472909,
    "tgn:name":"Xifeng Si",
    "tgn:placetype":[
        "aat:300007595"
    ]
},
  "bbox": [],
  "geometry": {"coordinates":[119.512318,23.598574],"type":"Point"}
}
=======
{"geometry":{"type":"Point","coordinates":[119.512318,23.598574]},"type":"Feature","properties":{"hierarchy":["tgn:7472909","tgn:1000004","tgn:7004300","tgn:1000141","tgn:7029392"],"placetype":["aat:300007595"],"id":7472909,"name:xx":"Xifeng Si"}}
>>>>>>> 03f74aca74312dbeaf24d7e61306dd6a786dc3d0
