{
  "id": 2776879,
  "type": "Feature",
  "properties": {
    "tgn:hierarchy":[
        "tgn:2776879",
        "tgn:1000001",
        "tgn:7006451",
        "tgn:2000093",
        "tgn:7012149",
        "tgn:7029392"
    ],
    "tgn:id":2776879,
    "tgn:name":"Windsor Spring",
    "tgn:placetype":[
        "aat:300008697"
    ]
},
  "bbox": [],
  "geometry": {"coordinates":[-111.4667,34.05],"type":"Point"}
}