{
  "id": 1083546,
  "type": "Feature",
  "properties": {
    "tgn:hierarchy":[
        "tgn:1083546",
        "tgn:1000004",
        "tgn:1001490",
        "tgn:1000133",
        "tgn:7029392"
    ],
    "tgn:id":1083546,
    "tgn:name":"Kamalia",
    "tgn:placetype":[
        "aat:300008347"
    ]
},
  "bbox": [],
  "geometry": {"coordinates":[72.6667,30.2333],"type":"Point"}
}