{
  "id": 2414756,
  "type": "Feature",
  "properties": {
    "tgn:hierarchy":[
        "tgn:2414756",
        "tgn:1000001",
        "tgn:7016172",
        "tgn:7012149",
        "tgn:2000137",
        "tgn:7029392"
    ],
    "tgn:id":2414756,
    "tgn:name":"Isaac West Mountain",
    "tgn:placetype":[
        "aat:300008798"
    ]
},
  "bbox": [],
  "geometry": {"coordinates":[-92.0167,35.95],"type":"Point"}
}