{
  "id": 2362786,
  "type": "Feature",
  "properties": {
    "tgn:hierarchy":[
        "tgn:2362786",
        "tgn:1000001",
        "tgn:7012149",
        "tgn:7014589",
        "tgn:7007515",
        "tgn:7029392"
    ],
    "tgn:id":2362786,
    "tgn:name":"Great Meadow",
    "tgn:placetype":[
        "aat:300008905"
    ]
},
  "bbox": [],
  "geometry": {"coordinates":[-67.5833,44.95],"type":"Point"}
}