{
  "id": 2290634,
  "type": "Feature",
  "properties": {
    "tgn:hierarchy":[
        "tgn:2290634",
        "tgn:1000001",
        "tgn:7012149",
        "tgn:2001706",
        "tgn:7007708",
        "tgn:7029392"
    ],
    "tgn:id":2290634,
    "tgn:name":"Doerner Reservoir",
    "tgn:placetype":[
        "aat:300006191"
    ]
},
  "bbox": [],
  "geometry": {"coordinates":[-123.4667,43.2833],"type":"Point"}
}