{
  "id": 2044255,
  "type": "Feature",
  "properties": {
    "tgn:hierarchy":[
        "tgn:2044255",
        "tgn:1000001",
        "tgn:2000861",
        "tgn:7012149",
        "tgn:7007256",
        "tgn:7029392"
    ],
    "tgn:id":2044255,
    "tgn:name":"Wardview",
    "tgn:placetype":[
        "aat:300008347",
        "aat:300387210"
    ]
},
  "bbox": [],
  "geometry": {"coordinates":[-93.7833,32.95],"type":"Point"}
}