{
  "id": 2478936,
  "type": "Feature",
  "properties": {
    "tgn:hierarchy":[
        "tgn:2478936",
        "tgn:1000001",
        "tgn:7012149",
        "tgn:2002252",
        "tgn:7007920",
        "tgn:7029392"
    ],
    "tgn:id":2478936,
    "tgn:name":"Magee Hill",
    "tgn:placetype":[
        "aat:300008798"
    ]
},
  "bbox": [],
  "geometry": {"coordinates":[-117.95,46.6333],"type":"Point"}
}