{
  "id": 2067273,
  "type": "Feature",
  "properties": {
    "tgn:hierarchy":[
        "tgn:2067273",
        "tgn:1000001",
        "tgn:7012149",
        "tgn:2001444",
        "tgn:7007566",
        "tgn:7029392"
    ],
    "tgn:id":2067273,
    "tgn:name":"Nutt",
    "tgn:placetype":[
        "aat:300387016"
    ]
},
  "bbox": [],
  "geometry": {"coordinates":[-107.4333,32.5667],"type":"Point"}
}