{
  "id": 2547623,
  "type": "Feature",
  "properties": {
    "tgn:hierarchy":[
        "tgn:2547623",
        "tgn:1000001",
        "tgn:7012149",
        "tgn:7018871",
        "tgn:7007920",
        "tgn:7029392"
    ],
    "tgn:id":2547623,
    "tgn:name":"North Fork Tolt Watershed",
    "tgn:placetype":[
        "aat:300055621"
    ]
},
  "bbox": [],
  "geometry": {"coordinates":[-121.65,47.7333],"type":"Point"}
}