{
  "id": 2729777,
  "type": "Feature",
  "properties": {
    "tgn:hierarchy":[
        "tgn:2729777",
        "tgn:1000001",
        "tgn:2002109",
        "tgn:7012149",
        "tgn:7007827",
        "tgn:7029392"
    ],
    "tgn:id":2729777,
    "tgn:name":"Trough Spring",
    "tgn:placetype":[
        "aat:300008697"
    ]
},
  "bbox": [],
  "geometry": {"coordinates":[-112.2167,37.5667],"type":"Point"}
}