{
  "id": 2381342,
  "type": "Feature",
  "properties": {
    "tgn:hierarchy":[
        "tgn:2381342",
        "tgn:1000001",
        "tgn:7012149",
        "tgn:2002194",
        "tgn:7007919",
        "tgn:7029392"
    ],
    "tgn:id":2381342,
    "tgn:name":"Hawthorne Knob",
    "tgn:placetype":[
        "aat:300008798"
    ]
},
  "bbox": [],
  "geometry": {"coordinates":[-81.6833,36.7167],"type":"Point"}
}