{
  "id": 1088484,
  "type": "Feature",
  "properties": {
    "tgn:hierarchy":[
        "tgn:1088484",
        "tgn:7001242",
        "tgn:1000970",
        "tgn:1000156",
        "tgn:7029392"
    ],
    "tgn:id":1088484,
    "tgn:name":"Bomboyo",
    "tgn:placetype":[
        "aat:300008347"
    ]
},
  "bbox": [],
  "geometry": {"coordinates":[15.4667,12.0167],"type":"Point"}
}