{
  "id": 7400382,
  "type": "Feature",
  "properties": {
    "tgn:hierarchy":[
        "tgn:7400382",
        "tgn:1000001",
        "tgn:7005599",
        "tgn:7005560",
        "tgn:7029392"
    ],
    "tgn:id":7400382,
    "tgn:name":"Agua Nacida",
    "tgn:placetype":[
        "aat:300008347"
    ]
},
  "bbox": [],
  "geometry": {"coordinates":[-98.083333,21.266667],"type":"Point"}
}