{
  "id": 7388267,
  "type": "Feature",
  "properties": {
    "tgn:hierarchy":[
        "tgn:7388267",
        "tgn:1000001",
        "tgn:7005591",
        "tgn:7005560",
        "tgn:7029392"
    ],
    "tgn:id":7388267,
    "tgn:name":"Piedra, R\u00edo",
    "tgn:placetype":[
        "aat:300008699"
    ]
},
  "bbox": [],
  "geometry": {"coordinates":[-98.266667,16.25],"type":"Point"}
}