{
  "id": 7029922,
  "type": "Feature",
  "properties": {
    "tgn:hierarchy":[
        "tgn:7029922",
        "tgn:7019053",
        "tgn:7002445",
        "tgn:1000003",
        "tgn:7029505",
        "tgn:7008591",
        "tgn:7029392"
    ],
    "tgn:id":7029922,
    "tgn:name":"Clifton",
    "tgn:placetype":[
        "aat:300008347",
        "aat:300008372"
    ]
},
  "bbox": [],
  "geometry": {"coordinates":[-1.22,53.451],"type":"Point"}
}