{
  "id": 2051078,
  "type": "Feature",
  "properties": {
    "tgn:hierarchy":[
        "tgn:2051078",
        "tgn:1000001",
        "tgn:7012149",
        "tgn:1002540",
        "tgn:7007520",
        "tgn:7029392"
    ],
    "tgn:id":2051078,
    "tgn:name":"Alaska",
    "tgn:placetype":[
        "aat:300008347"
    ]
},
  "bbox": [],
  "geometry": {"coordinates":[-85.4667,42.8333],"type":"Point"}
}