{
  "id": 2268840,
  "type": "Feature",
  "properties": {
    "tgn:hierarchy":[
        "tgn:2268840",
        "tgn:1000001",
        "tgn:7012149",
        "tgn:2002264",
        "tgn:7013961",
        "tgn:7029392"
    ],
    "tgn:id":2268840,
    "tgn:name":"Cross Mountain",
    "tgn:placetype":[
        "aat:300008798"
    ]
},
  "bbox": [],
  "geometry": {"coordinates":[-80.5833,37.9667],"type":"Point"}
}