{
  "id": 7501274,
  "type": "Feature",
  "properties": {
    "tgn:hierarchy":[
        "tgn:7501274",
        "tgn:1000004",
        "tgn:7467799",
        "tgn:1000141",
        "tgn:7029392"
    ],
    "tgn:id":7501274,
    "tgn:name":"Xinxingzhuang",
    "tgn:placetype":[
        "aat:300008347"
    ]
},
  "bbox": [],
  "geometry": {"coordinates":[120.517885,24.018568],"type":"Point"}
}