{
  "id": 7513741,
  "type": "Feature",
  "properties": {
    "tgn:hierarchy":[
        "tgn:7513741",
        "tgn:1009227",
        "tgn:1000226",
        "tgn:7016822",
        "tgn:1000006",
        "tgn:7029392"
    ],
    "tgn:id":7513741,
    "tgn:name:en":"Fork River",
    "tgn:placetype":[
        "aat:300008699"
    ]
},
  "bbox": [],
  "geometry": {"coordinates":[168.25,-44.15],"type":"Point"}
}