{
  "id": 7282831,
  "type": "Feature",
  "properties": {
    "tgn:hierarchy":[
        "tgn:7282831",
        "tgn:1001702",
        "tgn:1000049",
        "tgn:1000002",
        "tgn:7029392"
    ],
    "tgn:id":7282831,
    "tgn:name":"Peligroso, Arrecife",
    "tgn:placetype":[
        "aat:300008808"
    ]
},
  "bbox": [],
  "geometry": {"coordinates":[-69.066667,-55.683333],"type":"Point"}
}