{
  "id": 7304093,
  "type": "Feature",
  "properties": {
    "tgn:hierarchy":[
        "tgn:7304093",
        "tgn:7002803",
        "tgn:1001647",
        "tgn:1000003",
        "tgn:1000095",
        "tgn:7029392"
    ],
    "tgn:id":7304093,
    "tgn:name":"Nava, Rambla de la",
    "tgn:placetype":[
        "aat:300266554",
        "aat:300008699"
    ]
},
  "bbox": [],
  "geometry": {"coordinates":[-2.05,38.433333],"type":"Point"}
}