{
  "id": 2482570,
  "type": "Feature",
  "properties": {
    "tgn:hierarchy":[
        "tgn:2482570",
        "tgn:2000918",
        "tgn:1000001",
        "tgn:7012149",
        "tgn:7007515",
        "tgn:7029392"
    ],
    "tgn:id":2482570,
    "tgn:name":"Lapham Brook",
    "tgn:placetype":[
        "aat:300008699"
    ]
},
  "bbox": [],
  "geometry": {"coordinates":[-70.3167,44.1667],"type":"Point"}
}