<<<<<<< HEAD
{
  "id": 7176360,
  "type": "Feature",
  "properties": {
    "tgn:hierarchy":[
        "tgn:7176360",
        "tgn:1000003",
        "tgn:7000094",
        "tgn:7000084",
        "tgn:7029392"
    ],
    "tgn:id":7176360,
    "tgn:name":"Gr\u00fcnow",
    "tgn:placetype":[
        "aat:300008347"
    ]
},
  "bbox": [],
  "geometry": {"coordinates":[13.316667,53.35],"type":"Point"}
}
=======
{"geometry":{"type":"Point","coordinates":[13.316667,53.350000]},"type":"Feature","properties":{"hierarchy":["tgn:7176360","tgn:1000003","tgn:7000094","tgn:7000084","tgn:7029392"],"placetype":["aat:300008347"],"id":7176360,"name:xx":"Gr\u00fcnow"}}
>>>>>>> 03f74aca74312dbeaf24d7e61306dd6a786dc3d0
