{
  "id": 7394433,
  "type": "Feature",
  "properties": {
    "tgn:hierarchy":[
        "tgn:7394433",
        "tgn:7005583",
        "tgn:1000001",
        "tgn:7005560",
        "tgn:7029392"
    ],
    "tgn:id":7394433,
    "tgn:name":"Rancho San Jose",
    "tgn:placetype":[
        "aat:300000241"
    ]
},
  "bbox": [],
  "geometry": {"coordinates":[-104.266667,26.55],"type":"Point"}
}