<<<<<<< HEAD
{
  "id": 2765873,
  "type": "Feature",
  "properties": {
    "tgn:hierarchy":[
        "tgn:2765873",
        "tgn:1000001",
        "tgn:7012149",
        "tgn:2002187",
        "tgn:7007919",
        "tgn:7029392"
    ],
    "tgn:id":2765873,
    "tgn:name":"White Grass Knob",
    "tgn:placetype":[
        "aat:300008798"
    ]
},
  "bbox": [],
  "geometry": {"coordinates":[-79.0,38.7167],"type":"Point"}
}
=======
{"geometry":{"type":"Point","coordinates":[-79.000000,38.716700]},"type":"Feature","properties":{"hierarchy":["tgn:2765873","tgn:1000001","tgn:7012149","tgn:2002187","tgn:7007919","tgn:7029392"],"placetype":["aat:300008798"],"id":2765873,"name:xx":"White Grass Knob"}}
>>>>>>> 03f74aca74312dbeaf24d7e61306dd6a786dc3d0
