{
  "id": 1065265,
  "type": "Feature",
  "properties": {
    "tgn:hierarchy":[
        "tgn:1065265",
        "tgn:1000003",
        "tgn:7015085",
        "tgn:7006670",
        "tgn:7029392"
    ],
    "tgn:id":1065265,
    "tgn:name":"Stara Fu\u017eina",
    "tgn:placetype":[
        "aat:300008347"
    ]
},
  "bbox": [],
  "geometry": {"coordinates":[13.8833,46.2833],"type":"Point"}
}