{
  "id": 7117184,
  "type": "Feature",
  "properties": {
    "tgn:hierarchy":[
        "tgn:7117184",
        "tgn:7003669",
        "tgn:1000003",
        "tgn:7000084",
        "tgn:7029392"
    ],
    "tgn:id":7117184,
    "tgn:name":"Oehrberg",
    "tgn:placetype":[
        "aat:300008347"
    ]
},
  "bbox": [],
  "geometry": {"coordinates":[9.916667,50.25],"type":"Point"}
}