<<<<<<< HEAD
{
  "id": 7117184,
  "type": "Feature",
  "properties": {
    "tgn:hierarchy":[
        "tgn:7117184",
        "tgn:7003669",
        "tgn:1000003",
        "tgn:7000084",
        "tgn:7029392"
    ],
    "tgn:id":7117184,
    "tgn:name":"Oehrberg",
    "tgn:placetype":[
        "aat:300008347"
    ]
},
  "bbox": [],
  "geometry": {"coordinates":[9.916667,50.25],"type":"Point"}
}
=======
{"geometry":{"type":"Point","coordinates":[9.916667,50.250000]},"type":"Feature","properties":{"hierarchy":["tgn:7117184","tgn:7003669","tgn:1000003","tgn:7000084","tgn:7029392"],"placetype":["aat:300008347"],"id":7117184,"name:xx":"Oehrberg"}}
>>>>>>> 03f74aca74312dbeaf24d7e61306dd6a786dc3d0
