{
  "id": 7476013,
  "type": "Feature",
  "properties": {
    "tgn:hierarchy":[
        "tgn:7476013",
        "tgn:7488858",
        "tgn:1000004",
        "tgn:1000141",
        "tgn:7029392"
    ],
    "tgn:id":7476013,
    "tgn:name":"Xiufeng Qiao",
    "tgn:placetype":[
        "aat:300007836"
    ]
},
  "bbox": [],
  "geometry": {"coordinates":[120.772469,23.776118],"type":"Point"}
}