{
  "id": 7467348,
  "type": "Feature",
  "properties": {
    "tgn:hierarchy":[
        "tgn:7467348",
        "tgn:7001004",
        "tgn:1000004",
        "tgn:1000141",
        "tgn:7029392"
    ],
    "tgn:id":7467348,
    "tgn:name":"Jianshan",
    "tgn:placetype":[
        "aat:300008347"
    ]
},
  "bbox": [],
  "geometry": {"coordinates":[120.365278,22.8175],"type":"Point"}
}