{
  "id": 2406041,
  "type": "Feature",
  "properties": {
    "tgn:hierarchy":[
        "tgn:2406041",
        "tgn:1000001",
        "tgn:7012149",
        "tgn:2000181",
        "tgn:7007157",
        "tgn:7029392"
    ],
    "tgn:id":2406041,
    "tgn:name":"Humbug Creek",
    "tgn:placetype":[
        "aat:300008706"
    ]
},
  "bbox": [],
  "geometry": {"coordinates":[-123.75,40.6667],"type":"Point"}
}