{
  "id": 7143219,
  "type": "Feature",
  "properties": {
    "tgn:hierarchy":[
        "tgn:7143219",
        "tgn:7003669",
        "tgn:1000003",
        "tgn:7000084",
        "tgn:7029392"
    ],
    "tgn:id":7143219,
    "tgn:name":"Loh",
    "tgn:placetype":[
        "aat:300000206"
    ]
},
  "bbox": [],
  "geometry": {"coordinates":[12.95,48.35],"type":"Point"}
}