{
  "id": 7496768,
  "type": "Feature",
  "properties": {
    "tgn:hierarchy":[
        "tgn:7496768",
        "tgn:7001004",
        "tgn:1000004",
        "tgn:1000141",
        "tgn:7029392"
    ],
    "tgn:id":7496768,
    "tgn:name":"Minzu Luqiao",
    "tgn:placetype":[
        "aat:300007836"
    ]
},
  "bbox": [],
  "geometry": {"coordinates":[120.314213,22.637098],"type":"Point"}
}