{
  "id": 7397349,
  "type": "Feature",
  "properties": {
    "tgn:hierarchy":[
        "tgn:7397349",
        "tgn:1000001",
        "tgn:7005592",
        "tgn:7005560",
        "tgn:7029392"
    ],
    "tgn:id":7397349,
    "tgn:name":"San Salvador el Verde",
    "tgn:placetype":[
        "aat:300008347"
    ]
},
  "bbox": [],
  "geometry": {"coordinates":[-98.516667,19.266667],"type":"Point"}
}