{
  "id": 2490358,
  "type": "Feature",
  "properties": {
    "tgn:hierarchy":[
        "tgn:2490358",
        "tgn:1000001",
        "tgn:7012149",
        "tgn:2000362",
        "tgn:7007248",
        "tgn:7029392"
    ],
    "tgn:id":2490358,
    "tgn:name":"Mangham Lake West",
    "tgn:placetype":[
        "aat:300006191"
    ]
},
  "bbox": [],
  "geometry": {"coordinates":[-84.0833,33.7167],"type":"Point"}
}