{
  "id": 2744956,
  "type": "Feature",
  "properties": {
    "tgn:hierarchy":[
        "tgn:2744956",
        "tgn:1000001",
        "tgn:2000949",
        "tgn:7012149",
        "tgn:7007520",
        "tgn:7029392"
    ],
    "tgn:id":2744956,
    "tgn:name":"View, Lake",
    "tgn:placetype":[
        "aat:300008680"
    ]
},
  "bbox": [],
  "geometry": {"coordinates":[-85.85,44.7167],"type":"Point"}
}