{
  "id": 7510407,
  "type": "Feature",
  "properties": {
    "tgn:hierarchy":[
        "tgn:7510407",
        "tgn:1009227",
        "tgn:1000226",
        "tgn:7016822",
        "tgn:1000006",
        "tgn:7029392"
    ],
    "tgn:id":7510407,
    "tgn:name:en":"Big Island",
    "tgn:placetype":[
        "aat:300008791"
    ]
},
  "bbox": [],
  "geometry": {"coordinates":[167.516667,-47.133333],"type":"Point"}
}