{
  "id": 7588379,
  "type": "Feature",
  "properties": {
    "tgn:hierarchy":[
        "tgn:7588379",
        "tgn:1000004",
        "tgn:7000198",
        "tgn:7000799",
        "tgn:7029392"
    ],
    "tgn:id":7588379,
    "tgn:name:en":"Chhambar Kin\u0101r",
    "tgn:placetype":[
        "aat:300008347"
    ]
},
  "bbox": [],
  "geometry": {"coordinates":[74.25586,33.847321],"type":"Point"}
}