{
  "id": 2639195,
  "type": "Feature",
  "properties": {
    "tgn:hierarchy":[
        "tgn:2639195",
        "tgn:1000001",
        "tgn:7012149",
        "tgn:7007157",
        "tgn:7014516",
        "tgn:7029392"
    ],
    "tgn:id":2639195,
    "tgn:name":"Salt Point",
    "tgn:placetype":[
        "aat:300008850"
    ]
},
  "bbox": [],
  "geometry": {"coordinates":[-123.3167,38.55],"type":"Point"}
}