{
  "id": 7147066,
  "type": "Feature",
  "properties": {
    "tgn:hierarchy":[
        "tgn:7147066",
        "tgn:1000003",
        "tgn:7003688",
        "tgn:7000084",
        "tgn:7029392"
    ],
    "tgn:id":7147066,
    "tgn:name":"K\u00f6nigsteinshof",
    "tgn:placetype":[
        "aat:300000206"
    ]
},
  "bbox": [],
  "geometry": {"coordinates":[8.75,54.75],"type":"Point"}
}