{
  "id": 7499266,
  "type": "Feature",
  "properties": {
    "tgn:hierarchy":[
        "tgn:7499266",
        "tgn:1000004",
        "tgn:7001009",
        "tgn:1000141",
        "tgn:7029392"
    ],
    "tgn:id":7499266,
    "tgn:name":"Dongyixiang",
    "tgn:placetype":[
        "aat:300008347"
    ]
},
  "bbox": [],
  "geometry": {"coordinates":[120.871932,24.086919],"type":"Point"}
}