{
  "id": 2776192,
  "type": "Feature",
  "properties": {
    "tgn:hierarchy":[
        "tgn:2776192",
        "tgn:1000001",
        "tgn:7012149",
        "tgn:2001721",
        "tgn:7007708",
        "tgn:7029392"
    ],
    "tgn:id":2776192,
    "tgn:name":"Wilts Creek",
    "tgn:placetype":[
        "aat:300008706"
    ]
},
  "bbox": [],
  "geometry": {"coordinates":[-118.3667,45.25],"type":"Point"}
}