{
  "id": 7237327,
  "type": "Feature",
  "properties": {
    "tgn:hierarchy":[
        "tgn:7237327",
        "tgn:7011330",
        "tgn:7002674",
        "tgn:1000003",
        "tgn:1000074",
        "tgn:7029392"
    ],
    "tgn:id":7237327,
    "tgn:name":"\u00c1yioi The\u00f3dhoroi, \u00c1kra",
    "tgn:placetype":[
        "aat:300008850"
    ]
},
  "bbox": [],
  "geometry": {"coordinates":[27.083333,35.433333],"type":"Point"}
}