{
  "id": 2524675,
  "type": "Feature",
  "properties": {
    "tgn:hierarchy":[
        "tgn:2524675",
        "tgn:1000001",
        "tgn:7012149",
        "tgn:7007157",
        "tgn:1002608",
        "tgn:7029392"
    ],
    "tgn:id":2524675,
    "tgn:name":"Mormon Island",
    "tgn:placetype":[
        "aat:300008791"
    ]
},
  "bbox": [],
  "geometry": {"coordinates":[-118.25,33.75],"type":"Point"}
}