<<<<<<< HEAD
{
  "id": 7479080,
  "type": "Feature",
  "properties": {
    "tgn:hierarchy":[
        "tgn:7479080",
        "tgn:1000004",
        "tgn:7001009",
        "tgn:1000141",
        "tgn:7029392"
    ],
    "tgn:id":7479080,
    "tgn:name":"Linwuju Huanshan Baohusuo",
    "tgn:placetype":[
        "aat:300387503"
    ]
},
  "bbox": [],
  "geometry": {"coordinates":[121.281111,24.324167],"type":"Point"}
}
=======
{"geometry":{"type":"Point","coordinates":[121.281111,24.324167]},"type":"Feature","properties":{"hierarchy":["tgn:7479080","tgn:1000004","tgn:7001009","tgn:1000141","tgn:7029392"],"placetype":["aat:300387503"],"id":7479080,"name:xx":"Linwuju Huanshan Baohusuo"}}
>>>>>>> 03f74aca74312dbeaf24d7e61306dd6a786dc3d0
