{
  "id": 2341326,
  "type": "Feature",
  "properties": {
    "tgn:hierarchy":[
        "tgn:2341326",
        "tgn:1000001",
        "tgn:7012149",
        "tgn:7014543",
        "tgn:7007248",
        "tgn:7029392"
    ],
    "tgn:id":2341326,
    "tgn:name":"Frog Bottom Creek",
    "tgn:placetype":[
        "aat:300008706"
    ]
},
  "bbox": [],
  "geometry": {"coordinates":[-84.7667,32.1167],"type":"Point"}
}