{
  "id": 7156152,
  "type": "Feature",
  "properties": {
    "tgn:hierarchy":[
        "tgn:7156152",
        "tgn:1000003",
        "tgn:7003689",
        "tgn:7000084",
        "tgn:7029392"
    ],
    "tgn:id":7156152,
    "tgn:name":"Kirch-Berg",
    "tgn:placetype":[
        "aat:300008777"
    ]
},
  "bbox": [],
  "geometry": {"coordinates":[11.466667,50.566667],"type":"Point"}
}