{
  "id": 7411365,
  "type": "Feature",
  "properties": {
    "tgn:hierarchy":[
        "tgn:7411365",
        "tgn:7005587",
        "tgn:1000001",
        "tgn:7005560",
        "tgn:7029392"
    ],
    "tgn:id":7411365,
    "tgn:name:es":"Dema\u00f1i",
    "tgn:placetype":[
        "aat:300008347"
    ]
},
  "bbox": [],
  "geometry": {"coordinates":[-98.983333,20.933333],"type":"Point"}
}