{
  "id": 2594236,
  "type": "Feature",
  "properties": {
    "tgn:hierarchy":[
        "tgn:2594236",
        "tgn:1000001",
        "tgn:2002254",
        "tgn:7012149",
        "tgn:7013961",
        "tgn:7029392"
    ],
    "tgn:id":2594236,
    "tgn:name":"Porter Farm Spring",
    "tgn:placetype":[
        "aat:300008697"
    ]
},
  "bbox": [],
  "geometry": {"coordinates":[-78.0333,39.3167],"type":"Point"}
}