{
  "id": 1122265,
  "type": "Feature",
  "properties": {
    "tgn:hierarchy":[
        "tgn:1122265",
        "tgn:1000001",
        "tgn:7016172",
        "tgn:7012149",
        "tgn:2000149",
        "tgn:7029392"
    ],
    "tgn:id":1122265,
    "tgn:name":"Buffalo",
    "tgn:placetype":[
        "aat:300008707"
    ]
},
  "bbox": [],
  "geometry": {"coordinates":[-92.4167,36.1667],"type":"Point"}
}