{
  "id": 2104056,
  "type": "Feature",
  "properties": {
    "tgn:hierarchy":[
        "tgn:2104056",
        "tgn:1000001",
        "tgn:7012149",
        "tgn:2002024",
        "tgn:7007826",
        "tgn:7029392"
    ],
    "tgn:id":2104056,
    "tgn:name":"Emberson",
    "tgn:placetype":[
        "aat:300008347",
        "aat:300387210"
    ]
},
  "bbox": [],
  "geometry": {"coordinates":[-95.65,33.75],"type":"Point"}
}