{
  "id": 2444143,
  "type": "Feature",
  "properties": {
    "tgn:hierarchy":[
        "tgn:2444143",
        "tgn:1000001",
        "tgn:7012149",
        "tgn:1002384",
        "tgn:7007523",
        "tgn:7029392"
    ],
    "tgn:id":2444143,
    "tgn:name":"Labadie Power Plant Reservoir",
    "tgn:placetype":[
        "aat:300006191"
    ]
},
  "bbox": [],
  "geometry": {"coordinates":[-90.8333,38.55],"type":"Point"}
}