{
  "id": 7322024,
  "type": "Feature",
  "properties": {
    "tgn:hierarchy":[
        "tgn:7322024",
        "tgn:1001768",
        "tgn:1000049",
        "tgn:1000002",
        "tgn:7029392"
    ],
    "tgn:id":7322024,
    "tgn:name":"Bayas, Cerro",
    "tgn:placetype":[
        "aat:300008777"
    ]
},
  "bbox": [],
  "geometry": {"coordinates":[-71.25,-32.533333],"type":"Point"}
}