{
  "id": 2654871,
  "type": "Feature",
  "properties": {
    "tgn:hierarchy":[
        "tgn:2654871",
        "tgn:1000001",
        "tgn:2000921",
        "tgn:7012149",
        "tgn:7007515",
        "tgn:7029392"
    ],
    "tgn:id":2654871,
    "tgn:name":"Shallow Pond",
    "tgn:placetype":[
        "aat:300008680"
    ]
},
  "bbox": [],
  "geometry": {"coordinates":[-70.5333,45.25],"type":"Point"}
}