{
  "id": 2267576,
  "type": "Feature",
  "properties": {
    "tgn:hierarchy":[
        "tgn:2267576",
        "tgn:1000001",
        "tgn:7012149",
        "tgn:2002196",
        "tgn:7007919",
        "tgn:7029392"
    ],
    "tgn:id":2267576,
    "tgn:name":"Crockett Knob",
    "tgn:placetype":[
        "aat:300008798"
    ]
},
  "bbox": [],
  "geometry": {"coordinates":[-80.85,36.9667],"type":"Point"}
}