{
  "id": 2499645,
  "type": "Feature",
  "properties": {
    "tgn:hierarchy":[
        "tgn:2499645",
        "tgn:1000001",
        "tgn:2001414",
        "tgn:7012149",
        "tgn:7007526",
        "tgn:7029392"
    ],
    "tgn:id":2499645,
    "tgn:name":"McConnell Creek",
    "tgn:placetype":[
        "aat:300008706"
    ]
},
  "bbox": [],
  "geometry": {"coordinates":[-117.6667,41.55],"type":"Point"}
}