{
  "id": 7242223,
  "type": "Feature",
  "properties": {
    "tgn:hierarchy":[
        "tgn:7242223",
        "tgn:7003461",
        "tgn:1000003",
        "tgn:1000063",
        "tgn:7018236",
        "tgn:7029392"
    ],
    "tgn:id":7242223,
    "tgn:name":"Locht",
    "tgn:placetype":[
        "aat:300008347"
    ]
},
  "bbox": [],
  "geometry": {"coordinates":[5.366667,51.15],"type":"Point"}
}