{
  "id": 7589779,
  "type": "Feature",
  "properties": {
    "tgn:hierarchy":[
        "tgn:7589779",
        "tgn:1000004",
        "tgn:7000198",
        "tgn:7016883",
        "tgn:7029392"
    ],
    "tgn:id":7589779,
    "tgn:name:en":"Mahd\u012bpur",
    "tgn:placetype":[
        "aat:300008347"
    ]
},
  "bbox": [],
  "geometry": {"coordinates":[76.122052,30.742982],"type":"Point"}
}