{
  "id": 2026041,
  "type": "Feature",
  "properties": {
    "tgn:hierarchy":[
        "tgn:2026041",
        "tgn:1000001",
        "tgn:7012149",
        "tgn:2000491",
        "tgn:7007250",
        "tgn:7029392"
    ],
    "tgn:id":2026041,
    "tgn:name":"Prichard",
    "tgn:placetype":[
        "aat:300008347"
    ]
},
  "bbox": [],
  "geometry": {"coordinates":[-115.9667,47.65],"type":"Point"}
}