{
  "id": 2289526,
  "type": "Feature",
  "properties": {
    "tgn:hierarchy":[
        "tgn:2289526",
        "tgn:1000001",
        "tgn:1002188",
        "tgn:7012149",
        "tgn:7007252",
        "tgn:7029392"
    ],
    "tgn:id":2289526,
    "tgn:name":"Dixon Creek",
    "tgn:placetype":[
        "aat:300008706"
    ]
},
  "bbox": [],
  "geometry": {"coordinates":[-86.65,40.0833],"type":"Point"}
}