{
  "id": 7036177,
  "type": "Feature",
  "properties": {
    "tgn:hierarchy":[
        "tgn:7036177",
        "tgn:7003164",
        "tgn:1000003",
        "tgn:7009760",
        "tgn:1000080",
        "tgn:7029392"
    ],
    "tgn:id":7036177,
    "tgn:name":"Zuccale, Punta di",
    "tgn:placetype":[
        "aat:300386846"
    ]
},
  "bbox": [],
  "geometry": {"coordinates":[10.35,42.75],"type":"Point"}
}