{
  "id": 7308087,
  "type": "Feature",
  "properties": {
    "tgn:hierarchy":[
        "tgn:7308087",
        "tgn:1001702",
        "tgn:1000049",
        "tgn:1000002",
        "tgn:7029392"
    ],
    "tgn:id":7308087,
    "tgn:name":"Medio Canal, Isla",
    "tgn:placetype":[
        "aat:300008791"
    ]
},
  "bbox": [],
  "geometry": {"coordinates":[-73.033333,-52.066667],"type":"Point"}
}