{
  "id": 1021917,
  "type": "Feature",
  "properties": {
    "tgn:hierarchy":[
        "tgn:1021917",
        "tgn:1001898",
        "tgn:7002454",
        "tgn:1000047",
        "tgn:1000002",
        "tgn:7029392"
    ],
    "tgn:id":1021917,
    "tgn:name":"Lad\u00e1rio",
    "tgn:placetype":[
        "aat:300008347"
    ]
},
  "bbox": [],
  "geometry": {"coordinates":[-57.5833,-19.0167],"type":"Point"}
}