{
  "id": 7146028,
  "type": "Feature",
  "properties": {
    "tgn:hierarchy":[
        "tgn:7146028",
        "tgn:1000003",
        "tgn:7003677",
        "tgn:7000084",
        "tgn:7029392"
    ],
    "tgn:id":7146028,
    "tgn:name":"Kn\u00e4pchen",
    "tgn:placetype":[
        "aat:300008347"
    ]
},
  "bbox": [],
  "geometry": {"coordinates":[6.85,51.333333],"type":"Point"}
}