{
  "id": 2529382,
  "type": "Feature",
  "properties": {
    "tgn:hierarchy":[
        "tgn:2529382",
        "tgn:2000944",
        "tgn:1000001",
        "tgn:7012149",
        "tgn:7007520",
        "tgn:7029392"
    ],
    "tgn:id":2529382,
    "tgn:name":"Mud Lake",
    "tgn:placetype":[
        "aat:300008680"
    ]
},
  "bbox": [],
  "geometry": {"coordinates":[-83.4833,45.0333],"type":"Point"}
}