{
  "id": 2761599,
  "type": "Feature",
  "properties": {
    "tgn:hierarchy":[
        "tgn:2761599",
        "tgn:1000001",
        "tgn:7012149",
        "tgn:1002521",
        "tgn:7007920",
        "tgn:7029392"
    ],
    "tgn:id":2761599,
    "tgn:name":"West Peak",
    "tgn:placetype":[
        "aat:300008798"
    ]
},
  "bbox": [],
  "geometry": {"coordinates":[-123.3333,47.7167],"type":"Point"}
}