<<<<<<< HEAD
{
  "id": 2761599,
  "type": "Feature",
  "properties": {
    "tgn:hierarchy":[
        "tgn:2761599",
        "tgn:1000001",
        "tgn:7012149",
        "tgn:1002521",
        "tgn:7007920",
        "tgn:7029392"
    ],
    "tgn:id":2761599,
    "tgn:name":"West Peak",
    "tgn:placetype":[
        "aat:300008798"
    ]
},
  "bbox": [],
  "geometry": {"coordinates":[-123.3333,47.7167],"type":"Point"}
}
=======
{"geometry":{"type":"Point","coordinates":[-123.333300,47.716700]},"type":"Feature","properties":{"hierarchy":["tgn:2761599","tgn:1000001","tgn:7012149","tgn:1002521","tgn:7007920","tgn:7029392"],"placetype":["aat:300008798"],"id":2761599,"name:xx":"West Peak"}}
>>>>>>> 03f74aca74312dbeaf24d7e61306dd6a786dc3d0
