{
  "id": 2432190,
  "type": "Feature",
  "properties": {
    "tgn:hierarchy":[
        "tgn:2432190",
        "tgn:1000001",
        "tgn:7016172",
        "tgn:7012149",
        "tgn:2000160",
        "tgn:7029392"
    ],
    "tgn:id":2432190,
    "tgn:name":"Kaylo Creek",
    "tgn:placetype":[
        "aat:300008706"
    ]
},
  "bbox": [],
  "geometry": {"coordinates":[-90.7167,35.45],"type":"Point"}
}