{
  "id": 7509907,
  "type": "Feature",
  "properties": {
    "tgn:hierarchy":[
        "tgn:7509907",
        "tgn:1009227",
        "tgn:1000226",
        "tgn:1000006",
        "tgn:7016850",
        "tgn:7029392"
    ],
    "tgn:id":7509907,
    "tgn:name:en":"Waihapi Creek",
    "tgn:placetype":[
        "aat:300008699"
    ]
},
  "bbox": [],
  "geometry": {"coordinates":[169.916667,-43.383333],"type":"Point"}
}