{
  "id": 2110306,
  "type": "Feature",
  "properties": {
    "tgn:hierarchy":[
        "tgn:2110306",
        "tgn:1000001",
        "tgn:7012149",
        "tgn:2002178",
        "tgn:7007919",
        "tgn:7029392"
    ],
    "tgn:id":2110306,
    "tgn:name":"Alma",
    "tgn:placetype":[
        "aat:300008347"
    ]
},
  "bbox": [],
  "geometry": {"coordinates":[-78.55,38.5833],"type":"Point"}
}