<<<<<<< HEAD
{
  "id": 7117522,
  "type": "Feature",
  "properties": {
    "tgn:hierarchy":[
        "tgn:7117522",
        "tgn:1000003",
        "tgn:7003677",
        "tgn:7000084",
        "tgn:7029392"
    ],
    "tgn:id":7117522,
    "tgn:name":"Osthusen",
    "tgn:placetype":[
        "aat:300387200"
    ]
},
  "bbox": [],
  "geometry": {"coordinates":[8.266667,51.7],"type":"Point"}
}
=======
{"geometry":{"type":"Point","coordinates":[8.266667,51.700000]},"type":"Feature","properties":{"hierarchy":["tgn:7117522","tgn:1000003","tgn:7003677","tgn:7000084","tgn:7029392"],"placetype":["aat:300387200"],"id":7117522,"name:xx":"Osthusen"}}
>>>>>>> 03f74aca74312dbeaf24d7e61306dd6a786dc3d0
