{
  "id": 2009022,
  "type": "Feature",
  "properties": {
    "tgn:hierarchy":[
        "tgn:2009022",
        "tgn:1000001",
        "tgn:7016172",
        "tgn:7012149",
        "tgn:2000135",
        "tgn:7029392"
    ],
    "tgn:id":2009022,
    "tgn:name":"Nashville",
    "tgn:placetype":[
        "aat:300008347"
    ]
},
  "bbox": [],
  "geometry": {"coordinates":[-93.8333,33.9333],"type":"Point"}
}