{
  "id": 2169138,
  "type": "Feature",
  "properties": {
    "tgn:hierarchy":[
        "tgn:2169138",
        "tgn:1000001",
        "tgn:7012149",
        "tgn:2000797",
        "tgn:7007255",
        "tgn:7029392"
    ],
    "tgn:id":2169138,
    "tgn:name":"Big Jonathan Branch",
    "tgn:placetype":[
        "aat:300008699"
    ]
},
  "bbox": [],
  "geometry": {"coordinates":[-83.0667,36.9333],"type":"Point"}
}