{
  "id": 2677870,
  "type": "Feature",
  "properties": {
    "tgn:hierarchy":[
        "tgn:2677870",
        "tgn:1000001",
        "tgn:7012149",
        "tgn:1002356",
        "tgn:7007568",
        "tgn:7029392"
    ],
    "tgn:id":2677870,
    "tgn:name":"South Entrance Outer Channel",
    "tgn:placetype":[
        "aat:300006075"
    ]
},
  "bbox": [],
  "geometry": {"coordinates":[-78.8667,42.8333],"type":"Point"}
}