<<<<<<< HEAD
{
  "id": 2765450,
  "type": "Feature",
  "properties": {
    "tgn:hierarchy":[
        "tgn:2765450",
        "tgn:1000001",
        "tgn:7012149",
        "tgn:2000893",
        "tgn:7007256",
        "tgn:7029392"
    ],
    "tgn:id":2765450,
    "tgn:name":"White Branch",
    "tgn:placetype":[
        "aat:300008699"
    ]
},
  "bbox": [],
  "geometry": {"coordinates":[-92.7667,31.4167],"type":"Point"}
}
=======
{"geometry":{"type":"Point","coordinates":[-92.766700,31.416700]},"type":"Feature","properties":{"hierarchy":["tgn:2765450","tgn:1000001","tgn:7012149","tgn:2000893","tgn:7007256","tgn:7029392"],"placetype":["aat:300008699"],"id":2765450,"name:xx":"White Branch"}}
>>>>>>> 03f74aca74312dbeaf24d7e61306dd6a786dc3d0
