{
  "id": 2765450,
  "type": "Feature",
  "properties": {
    "tgn:hierarchy":[
        "tgn:2765450",
        "tgn:1000001",
        "tgn:7012149",
        "tgn:2000893",
        "tgn:7007256",
        "tgn:7029392"
    ],
    "tgn:id":2765450,
    "tgn:name":"White Branch",
    "tgn:placetype":[
        "aat:300008699"
    ]
},
  "bbox": [],
  "geometry": {"coordinates":[-92.7667,31.4167],"type":"Point"}
}