{
  "id": 7169029,
  "type": "Feature",
  "properties": {
    "tgn:hierarchy":[
        "tgn:7169029",
        "tgn:1000003",
        "tgn:7003676",
        "tgn:7000084",
        "tgn:7029392"
    ],
    "tgn:id":7169029,
    "tgn:name":"Harmelingen",
    "tgn:placetype":[
        "aat:300008347"
    ]
},
  "bbox": [],
  "geometry": {"coordinates":[9.933333,53.033333],"type":"Point"}
}