{
  "id": 7182953,
  "type": "Feature",
  "properties": {
    "tgn:hierarchy":[
        "tgn:7182953",
        "tgn:1000003",
        "tgn:7003676",
        "tgn:7000084",
        "tgn:7029392"
    ],
    "tgn:id":7182953,
    "tgn:name":"Gehrden",
    "tgn:placetype":[
        "aat:300000206"
    ]
},
  "bbox": [],
  "geometry": {"coordinates":[8.85,53.15],"type":"Point"}
}