{
  "id": 7576647,
  "type": "Feature",
  "properties": {
    "tgn:hierarchy":[
        "tgn:7576647",
        "tgn:1000004",
        "tgn:7000198",
        "tgn:1001886",
        "tgn:7029392"
    ],
    "tgn:id":7576647,
    "tgn:name:en":"Kotikulam",
    "tgn:placetype":[
        "aat:300007783"
    ]
},
  "bbox": [],
  "geometry": {"coordinates":[75.05,12.416667],"type":"Point"}
}