{
  "id": 2661757,
  "type": "Feature",
  "properties": {
    "tgn:hierarchy":[
        "tgn:2661757",
        "tgn:1000001",
        "tgn:7012149",
        "tgn:2002178",
        "tgn:7007919",
        "tgn:7029392"
    ],
    "tgn:id":2661757,
    "tgn:name":"Shuler Island",
    "tgn:placetype":[
        "aat:300008791"
    ]
},
  "bbox": [],
  "geometry": {"coordinates":[-78.6167,38.4833],"type":"Point"}
}