{
  "id": 2608729,
  "type": "Feature",
  "properties": {
    "tgn:hierarchy":[
        "tgn:2608729",
        "tgn:1000001",
        "tgn:7012149",
        "tgn:7007157",
        "tgn:1002956",
        "tgn:7029392"
    ],
    "tgn:id":2608729,
    "tgn:name":"Rattlesnake Ridge",
    "tgn:placetype":[
        "aat:300266640"
    ]
},
  "bbox": [],
  "geometry": {"coordinates":[-118.7333,35.95],"type":"Point"}
}