{
  "id": 7494497,
  "type": "Feature",
  "properties": {
    "tgn:hierarchy":[
        "tgn:7494497",
        "tgn:7001010",
        "tgn:1000004",
        "tgn:1000141",
        "tgn:7029392"
    ],
    "tgn:id":7494497,
    "tgn:name":"Xifu Guoxiao",
    "tgn:placetype":[
        "aat:300006495"
    ]
},
  "bbox": [],
  "geometry": {"coordinates":[121.430079,23.636519],"type":"Point"}
}