{
  "id": 1124676,
  "type": "Feature",
  "properties": {
    "tgn:hierarchy":[
        "tgn:1124676",
        "tgn:1000001",
        "tgn:7012149",
        "tgn:7007566",
        "tgn:7029392"
    ],
    "tgn:id":1124676,
    "tgn:name":"Hondo, Rio",
    "tgn:placetype":[
        "aat:300008707"
    ]
},
  "bbox": [],
  "geometry": {"coordinates":[-105.2667,33.3667],"type":"Point"}
}