<<<<<<< HEAD
{
  "id": 2762936,
  "type": "Feature",
  "properties": {
    "tgn:hierarchy":[
        "tgn:2762936",
        "tgn:1000001",
        "tgn:7012149",
        "tgn:2001720",
        "tgn:7007708",
        "tgn:7029392"
    ],
    "tgn:id":2762936,
    "tgn:name":"Westland F Canal",
    "tgn:placetype":[
        "aat:300006075"
    ]
},
  "bbox": [],
  "geometry": {"coordinates":[-119.35,45.8333],"type":"Point"}
}
=======
{"geometry":{"type":"Point","coordinates":[-119.350000,45.833300]},"type":"Feature","properties":{"hierarchy":["tgn:2762936","tgn:1000001","tgn:7012149","tgn:2001720","tgn:7007708","tgn:7029392"],"placetype":["aat:300006075"],"id":2762936,"name:xx":"Westland F Canal"}}
>>>>>>> 03f74aca74312dbeaf24d7e61306dd6a786dc3d0
