{
  "id": 1050582,
  "type": "Feature",
  "properties": {
    "tgn:hierarchy":[
        "tgn:1050582",
        "tgn:7002444",
        "tgn:1000003",
        "tgn:7008076",
        "tgn:7008591",
        "tgn:7029392"
    ],
    "tgn:id":1050582,
    "tgn:name":"Dairsie",
    "tgn:placetype":[
        "aat:300008347",
        "aat:300008372"
    ]
},
  "bbox": [],
  "geometry": {"coordinates":[-2.95,56.35],"type":"Point"}
}