<<<<<<< HEAD
{
  "id": 7356341,
  "type": "Feature",
  "properties": {
    "tgn:hierarchy":[
        "tgn:7356341",
        "tgn:1000001",
        "tgn:1001960",
        "tgn:7005560",
        "tgn:7029392"
    ],
    "tgn:id":7356341,
    "tgn:name":"Carnero, Sierra",
    "tgn:placetype":[
        "aat:300008795"
    ]
},
  "bbox": [],
  "geometry": {"coordinates":[-111.416667,29.55],"type":"Point"}
}
=======
{"geometry":{"type":"Point","coordinates":[-111.416667,29.550000]},"type":"Feature","properties":{"hierarchy":["tgn:7356341","tgn:1000001","tgn:1001960","tgn:7005560","tgn:7029392"],"placetype":["aat:300008795"],"id":7356341,"name:xx":"Carnero, Sierra"}}
>>>>>>> 03f74aca74312dbeaf24d7e61306dd6a786dc3d0
