<<<<<<< HEAD
{
  "id": 7482707,
  "type": "Feature",
  "properties": {
    "tgn:hierarchy":[
        "tgn:7482707",
        "tgn:7001010",
        "tgn:1000004",
        "tgn:1000141",
        "tgn:7029392"
    ],
    "tgn:id":7482707,
    "tgn:name":"Wujiabeng Shan",
    "tgn:placetype":[
        "aat:300008798"
    ]
},
  "bbox": [],
  "geometry": {"coordinates":[121.324444,24.026944],"type":"Point"}
}
=======
{"geometry":{"type":"Point","coordinates":[121.324444,24.026944]},"type":"Feature","properties":{"hierarchy":["tgn:7482707","tgn:7001010","tgn:1000004","tgn:1000141","tgn:7029392"],"placetype":["aat:300008798"],"id":7482707,"name:xx":"Wujiabeng Shan"}}
>>>>>>> 03f74aca74312dbeaf24d7e61306dd6a786dc3d0
