{
  "id": 2232250,
  "type": "Feature",
  "properties": {
    "tgn:hierarchy":[
        "tgn:2232250",
        "tgn:7002659",
        "tgn:1000001",
        "tgn:7012149",
        "tgn:2000044",
        "tgn:7029392"
    ],
    "tgn:id":2232250,
    "tgn:name":"Chandler Hollow",
    "tgn:placetype":[
        "aat:300008761"
    ]
},
  "bbox": [],
  "geometry": {"coordinates":[-86.3833,34.65],"type":"Point"}
}