{
  "id": 7178957,
  "type": "Feature",
  "properties": {
    "tgn:hierarchy":[
        "tgn:7178957",
        "tgn:7003669",
        "tgn:1000003",
        "tgn:7000084",
        "tgn:7029392"
    ],
    "tgn:id":7178957,
    "tgn:name":"Haiden",
    "tgn:placetype":[
        "aat:300000206"
    ]
},
  "bbox": [],
  "geometry": {"coordinates":[13.05,48.483333],"type":"Point"}
}