<<<<<<< HEAD
{
  "id": 7178957,
  "type": "Feature",
  "properties": {
    "tgn:hierarchy":[
        "tgn:7178957",
        "tgn:7003669",
        "tgn:1000003",
        "tgn:7000084",
        "tgn:7029392"
    ],
    "tgn:id":7178957,
    "tgn:name":"Haiden",
    "tgn:placetype":[
        "aat:300000206"
    ]
},
  "bbox": [],
  "geometry": {"coordinates":[13.05,48.483333],"type":"Point"}
}
=======
{"geometry":{"type":"Point","coordinates":[13.050000,48.483333]},"type":"Feature","properties":{"hierarchy":["tgn:7178957","tgn:7003669","tgn:1000003","tgn:7000084","tgn:7029392"],"placetype":["aat:300000206"],"id":7178957,"name:xx":"Haiden"}}
>>>>>>> 03f74aca74312dbeaf24d7e61306dd6a786dc3d0
