{
  "id": 2724270,
  "type": "Feature",
  "properties": {
    "tgn:hierarchy":[
        "tgn:2724270",
        "tgn:1000001",
        "tgn:7012149",
        "tgn:7022542",
        "tgn:7007825",
        "tgn:7029392"
    ],
    "tgn:id":2724270,
    "tgn:name":"Tom Foeman Creek",
    "tgn:placetype":[
        "aat:300008706"
    ]
},
  "bbox": [],
  "geometry": {"coordinates":[-84.5333,35.3667],"type":"Point"}
}