{
  "id": 7144522,
  "type": "Feature",
  "properties": {
    "tgn:hierarchy":[
        "tgn:7144522",
        "tgn:7003692",
        "tgn:1000003",
        "tgn:7000084",
        "tgn:7029392"
    ],
    "tgn:id":7144522,
    "tgn:name":"Kottspiel",
    "tgn:placetype":[
        "aat:300008347"
    ]
},
  "bbox": [],
  "geometry": {"coordinates":[9.911944,49.018889],"type":"Point"}
}