{
  "id": 2242887,
  "type": "Feature",
  "properties": {
    "tgn:hierarchy":[
        "tgn:2242887",
        "tgn:1000001",
        "tgn:7006451",
        "tgn:2000095",
        "tgn:7012149",
        "tgn:7029392"
    ],
    "tgn:id":2242887,
    "tgn:name":"Clear Cut Tank",
    "tgn:placetype":[
        "aat:300006191"
    ]
},
  "bbox": [],
  "geometry": {"coordinates":[-109.3667,33.6667],"type":"Point"}
}