{
  "id": 7191229,
  "type": "Feature",
  "properties": {
    "tgn:hierarchy":[
        "tgn:7191229",
        "tgn:7003669",
        "tgn:1000003",
        "tgn:7000084",
        "tgn:7029392"
    ],
    "tgn:id":7191229,
    "tgn:name":"Faulenberg",
    "tgn:placetype":[
        "aat:300008777"
    ]
},
  "bbox": [],
  "geometry": {"coordinates":[11.75,49.25],"type":"Point"}
}