<<<<<<< HEAD
{
  "id": 2252484,
  "type": "Feature",
  "properties": {
    "tgn:hierarchy":[
        "tgn:2252484",
        "tgn:1000001",
        "tgn:7012149",
        "tgn:2002248",
        "tgn:7007920",
        "tgn:7029392"
    ],
    "tgn:id":2252484,
    "tgn:name":"Conklin Lake",
    "tgn:placetype":[
        "aat:300008680"
    ]
},
  "bbox": [],
  "geometry": {"coordinates":[-117.1833,48.2667],"type":"Point"}
}
=======
{"geometry":{"type":"Point","coordinates":[-117.183300,48.266700]},"type":"Feature","properties":{"hierarchy":["tgn:2252484","tgn:1000001","tgn:7012149","tgn:2002248","tgn:7007920","tgn:7029392"],"placetype":["aat:300008680"],"id":2252484,"name:xx":"Conklin Lake"}}
>>>>>>> 03f74aca74312dbeaf24d7e61306dd6a786dc3d0
