{
  "id": 2252484,
  "type": "Feature",
  "properties": {
    "tgn:hierarchy":[
        "tgn:2252484",
        "tgn:1000001",
        "tgn:7012149",
        "tgn:2002248",
        "tgn:7007920",
        "tgn:7029392"
    ],
    "tgn:id":2252484,
    "tgn:name":"Conklin Lake",
    "tgn:placetype":[
        "aat:300008680"
    ]
},
  "bbox": [],
  "geometry": {"coordinates":[-117.1833,48.2667],"type":"Point"}
}