{
  "id": 7495897,
  "type": "Feature",
  "properties": {
    "tgn:hierarchy":[
        "tgn:7495897",
        "tgn:7468018",
        "tgn:1000004",
        "tgn:1000141",
        "tgn:7029392"
    ],
    "tgn:id":7495897,
    "tgn:name":"Xinzhuangzi",
    "tgn:placetype":[
        "aat:300008347"
    ]
},
  "bbox": [],
  "geometry": {"coordinates":[120.265222,23.524865],"type":"Point"}
}