{
  "id": 7587580,
  "type": "Feature",
  "properties": {
    "tgn:hierarchy":[
        "tgn:7587580",
        "tgn:1000004",
        "tgn:7000198",
        "tgn:1001977",
        "tgn:7029392"
    ],
    "tgn:id":7587580,
    "tgn:name:en":"Hatugan",
    "tgn:placetype":[
        "aat:300008347"
    ]
},
  "bbox": [],
  "geometry": {"coordinates":[88.250128,22.17304],"type":"Point"}
}