<<<<<<< HEAD
{
  "id": 7117235,
  "type": "Feature",
  "properties": {
    "tgn:hierarchy":[
        "tgn:7117235",
        "tgn:1000003",
        "tgn:7003685",
        "tgn:7000084",
        "tgn:7029392"
    ],
    "tgn:id":7117235,
    "tgn:name":"Oberstrahwalde",
    "tgn:placetype":[
        "aat:300008347"
    ]
},
  "bbox": [],
  "geometry": {"coordinates":[14.716667,51.033333],"type":"Point"}
}
=======
{"geometry":{"type":"Point","coordinates":[14.716667,51.033333]},"type":"Feature","properties":{"hierarchy":["tgn:7117235","tgn:1000003","tgn:7003685","tgn:7000084","tgn:7029392"],"placetype":["aat:300008347"],"id":7117235,"name:xx":"Oberstrahwalde"}}
>>>>>>> 03f74aca74312dbeaf24d7e61306dd6a786dc3d0
