{
  "id": 7117235,
  "type": "Feature",
  "properties": {
    "tgn:hierarchy":[
        "tgn:7117235",
        "tgn:1000003",
        "tgn:7003685",
        "tgn:7000084",
        "tgn:7029392"
    ],
    "tgn:id":7117235,
    "tgn:name":"Oberstrahwalde",
    "tgn:placetype":[
        "aat:300008347"
    ]
},
  "bbox": [],
  "geometry": {"coordinates":[14.716667,51.033333],"type":"Point"}
}