{
  "id": 1065336,
  "type": "Feature",
  "properties": {
    "tgn:hierarchy":[
        "tgn:1065336",
        "tgn:7017309",
        "tgn:1000003",
        "tgn:7006663",
        "tgn:7029392"
    ],
    "tgn:id":1065336,
    "tgn:name":"Vodnjan",
    "tgn:placetype":[
        "aat:300008347"
    ]
},
  "bbox": [],
  "geometry": {"coordinates":[13.8667,44.9833],"type":"Point"}
}