<<<<<<< HEAD
{
  "id": 7483744,
  "type": "Feature",
  "properties": {
    "tgn:hierarchy":[
        "tgn:7483744",
        "tgn:1000004",
        "tgn:7490934",
        "tgn:1000141",
        "tgn:7029392"
    ],
    "tgn:id":7483744,
    "tgn:name":"Cisheng Qiao",
    "tgn:placetype":[
        "aat:300007836"
    ]
},
  "bbox": [],
  "geometry": {"coordinates":[120.422222,23.3375],"type":"Point"}
}
=======
{"geometry":{"type":"Point","coordinates":[120.422222,23.337500]},"type":"Feature","properties":{"hierarchy":["tgn:7483744","tgn:1000004","tgn:7490934","tgn:1000141","tgn:7029392"],"placetype":["aat:300007836"],"id":7483744,"name:xx":"Cisheng Qiao"}}
>>>>>>> 03f74aca74312dbeaf24d7e61306dd6a786dc3d0
