<<<<<<< HEAD
{
  "id": 7376453,
  "type": "Feature",
  "properties": {
    "tgn:hierarchy":[
        "tgn:7376453",
        "tgn:7005586",
        "tgn:1000001",
        "tgn:7005560",
        "tgn:7029392"
    ],
    "tgn:id":7376453,
    "tgn:name":"La Sabinilla",
    "tgn:placetype":[
        "aat:300000241"
    ]
},
  "bbox": [],
  "geometry": {"coordinates":[-103.066667,20.0],"type":"Point"}
}
=======
{"geometry":{"type":"Point","coordinates":[-103.066667,20.000000]},"type":"Feature","properties":{"hierarchy":["tgn:7376453","tgn:7005586","tgn:1000001","tgn:7005560","tgn:7029392"],"placetype":["aat:300000241"],"id":7376453,"name:xx":"La Sabinilla"}}
>>>>>>> 03f74aca74312dbeaf24d7e61306dd6a786dc3d0
