{
  "id": 2629949,
  "type": "Feature",
  "properties": {
    "tgn:hierarchy":[
        "tgn:2629949",
        "tgn:1000001",
        "tgn:2001432",
        "tgn:7012149",
        "tgn:7007566",
        "tgn:7029392"
    ],
    "tgn:id":2629949,
    "tgn:name":"Ross Spring",
    "tgn:placetype":[
        "aat:300008697"
    ]
},
  "bbox": [],
  "geometry": {"coordinates":[-104.2167,36.9167],"type":"Point"}
}