{
  "id": 7038240,
  "type": "Feature",
  "properties": {
    "tgn:hierarchy":[
        "tgn:7038240",
        "tgn:7003006",
        "tgn:1000003",
        "tgn:7002997",
        "tgn:1000080",
        "tgn:7029392"
    ],
    "tgn:id":7038240,
    "tgn:name":"Torresella",
    "tgn:placetype":[
        "aat:300008347"
    ]
},
  "bbox": [],
  "geometry": {"coordinates":[12.889444,45.756111],"type":"Point"}
}