{
  "id": 2346026,
  "type": "Feature",
  "properties": {
    "tgn:hierarchy":[
        "tgn:2346026",
        "tgn:1000001",
        "tgn:1002289",
        "tgn:7012149",
        "tgn:7007240",
        "tgn:7029392"
    ],
    "tgn:id":2346026,
    "tgn:name":"Gaskin Bay",
    "tgn:placetype":[
        "aat:300132316"
    ]
},
  "bbox": [],
  "geometry": {"coordinates":[-81.4667,25.8333],"type":"Point"}
}