{
  "id": 7050485,
  "type": "Feature",
  "properties": {
    "tgn:hierarchy":[
        "tgn:7050485",
        "tgn:1003447",
        "tgn:7007850",
        "tgn:1000003",
        "tgn:1000080",
        "tgn:7029392"
    ],
    "tgn:id":7050485,
    "tgn:name":"La Taverna",
    "tgn:placetype":[
        "aat:300008347"
    ]
},
  "bbox": [],
  "geometry": {"coordinates":[16.166667,38.966667],"type":"Point"}
}