{
  "id": 7297368,
  "type": "Feature",
  "properties": {
    "tgn:hierarchy":[
        "tgn:7297368",
        "tgn:7008911",
        "tgn:1000003",
        "tgn:7002763",
        "tgn:1000095",
        "tgn:7029392"
    ],
    "tgn:id":7297368,
    "tgn:name":"Tain\u00e1s",
    "tgn:placetype":[
        "aat:300008347"
    ]
},
  "bbox": [],
  "geometry": {"coordinates":[-6.433333,43.183333],"type":"Point"}
}