{
  "id": 7156114,
  "type": "Feature",
  "properties": {
    "tgn:hierarchy":[
        "tgn:7156114",
        "tgn:7003669",
        "tgn:1000003",
        "tgn:7000084",
        "tgn:7029392"
    ],
    "tgn:id":7156114,
    "tgn:name":"Kleinanglhof",
    "tgn:placetype":[
        "aat:300008347"
    ]
},
  "bbox": [],
  "geometry": {"coordinates":[12.166667,49.166667],"type":"Point"}
}