{
  "id": 2352148,
  "type": "Feature",
  "properties": {
    "tgn:hierarchy":[
        "tgn:2352148",
        "tgn:1000001",
        "tgn:1002223",
        "tgn:7012149",
        "tgn:7007523",
        "tgn:7029392"
    ],
    "tgn:id":2352148,
    "tgn:name":"Glover Lake",
    "tgn:placetype":[
        "aat:300006191"
    ]
},
  "bbox": [],
  "geometry": {"coordinates":[-91.8833,38.8333],"type":"Point"}
}