{
  "id": 7511383,
  "type": "Feature",
  "properties": {
    "tgn:hierarchy":[
        "tgn:7511383",
        "tgn:1008380",
        "tgn:7000507",
        "tgn:1000226",
        "tgn:1000006",
        "tgn:7029392"
    ],
    "tgn:id":7511383,
    "tgn:name:en":"Murimotu",
    "tgn:placetype":[
        "aat:300008791"
    ]
},
  "bbox": [],
  "geometry": {"coordinates":[173.05,-34.416667],"type":"Point"}
}