{
  "id": 1077769,
  "type": "Feature",
  "properties": {
    "tgn:hierarchy":[
        "tgn:1077769",
        "tgn:1000004",
        "tgn:7003970",
        "tgn:1000116",
        "tgn:7029392"
    ],
    "tgn:id":1077769,
    "tgn:name":"Kai",
    "tgn:placetype":[
        "aat:300008347"
    ]
},
  "bbox": [],
  "geometry": {"coordinates":[136.5333,-2.25],"type":"Point"}
}