{
  "id": 2579977,
  "type": "Feature",
  "properties": {
    "tgn:hierarchy":[
        "tgn:2579977",
        "tgn:1000001",
        "tgn:7012149",
        "tgn:2001977",
        "tgn:7007826",
        "tgn:7029392"
    ],
    "tgn:id":2579977,
    "tgn:name":"Piedra Tank",
    "tgn:placetype":[
        "aat:300006191"
    ]
},
  "bbox": [],
  "geometry": {"coordinates":[-98.6833,27.9833],"type":"Point"}
}