{
  "id": 7559739,
  "type": "Feature",
  "properties": {
    "tgn:hierarchy":[
        "tgn:7559739",
        "tgn:1000004",
        "tgn:7000198",
        "tgn:7016722",
        "tgn:7029392"
    ],
    "tgn:id":7559739,
    "tgn:name:en":"Bhuria",
    "tgn:placetype":[
        "aat:300008057"
    ]
},
  "bbox": [],
  "geometry": {"coordinates":[79.488433,27.754475],"type":"Point"}
}