<<<<<<< HEAD
{
  "id": 2252427,
  "type": "Feature",
  "properties": {
    "tgn:hierarchy":[
        "tgn:2252427",
        "tgn:1000001",
        "tgn:7012149",
        "tgn:2000181",
        "tgn:7007157",
        "tgn:7029392"
    ],
    "tgn:id":2252427,
    "tgn:name":"Conical Rock",
    "tgn:placetype":[
        "aat:300008791"
    ]
},
  "bbox": [],
  "geometry": {"coordinates":[-124.35,40.25],"type":"Point"}
}
=======
{"geometry":{"type":"Point","coordinates":[-124.350000,40.250000]},"type":"Feature","properties":{"hierarchy":["tgn:2252427","tgn:1000001","tgn:7012149","tgn:2000181","tgn:7007157","tgn:7029392"],"placetype":["aat:300008791"],"id":2252427,"name:xx":"Conical Rock"}}
>>>>>>> 03f74aca74312dbeaf24d7e61306dd6a786dc3d0
