{
  "id": 2498821,
  "type": "Feature",
  "properties": {
    "tgn:hierarchy":[
        "tgn:2498821",
        "tgn:1000001",
        "tgn:7012149",
        "tgn:1002426",
        "tgn:7007255",
        "tgn:7029392"
    ],
    "tgn:id":2498821,
    "tgn:name":"McCall Hollow",
    "tgn:placetype":[
        "aat:300008761"
    ]
},
  "bbox": [],
  "geometry": {"coordinates":[-82.8667,38.3833],"type":"Point"}
}