{
  "id": 2311579,
  "type": "Feature",
  "properties": {
    "tgn:hierarchy":[
        "tgn:2311579",
        "tgn:1000001",
        "tgn:7012149",
        "tgn:7007255",
        "tgn:7029392"
    ],
    "tgn:id":2311579,
    "tgn:name":"Edward Branch",
    "tgn:placetype":[
        "aat:300008699"
    ]
},
  "bbox": [],
  "geometry": {"coordinates":[-83.6333,37.85],"type":"Point"}
}