{
  "id": 2681813,
  "type": "Feature",
  "properties": {
    "tgn:hierarchy":[
        "tgn:2681813",
        "tgn:1000001",
        "tgn:2001428",
        "tgn:7012149",
        "tgn:7007566",
        "tgn:7029392"
    ],
    "tgn:id":2681813,
    "tgn:name":"South Sandia Peak",
    "tgn:placetype":[
        "aat:300008798"
    ]
},
  "bbox": [],
  "geometry": {"coordinates":[-106.4167,35.1167],"type":"Point"}
}