{
  "id": 7016225,
  "type": "Feature",
  "properties": {
    "tgn:hierarchy":[
        "tgn:7016225",
        "tgn:1000001",
        "tgn:2001431",
        "tgn:7012149",
        "tgn:7007566",
        "tgn:7029392"
    ],
    "tgn:id":7016225,
    "tgn:name":"Bluewater",
    "tgn:placetype":[
        "aat:300008347",
        "aat:300387016"
    ]
},
  "bbox": [],
  "geometry": {"coordinates":[-107.9833,35.25],"type":"Point"}
}