<<<<<<< HEAD
{
  "id": 7354523,
  "type": "Feature",
  "properties": {
    "tgn:hierarchy":[
        "tgn:7354523",
        "tgn:1000001",
        "tgn:1001937",
        "tgn:7005560",
        "tgn:7029392"
    ],
    "tgn:id":7354523,
    "tgn:name":"Chunhuas",
    "tgn:placetype":[
        "aat:300008347"
    ]
},
  "bbox": [],
  "geometry": {"coordinates":[-89.2,18.2],"type":"Point"}
}
=======
{"geometry":{"type":"Point","coordinates":[-89.200000,18.200000]},"type":"Feature","properties":{"hierarchy":["tgn:7354523","tgn:1000001","tgn:1001937","tgn:7005560","tgn:7029392"],"placetype":["aat:300008347"],"id":7354523,"name:xx":"Chunhuas"}}
>>>>>>> 03f74aca74312dbeaf24d7e61306dd6a786dc3d0
