{
  "id": 7041312,
  "type": "Feature",
  "properties": {
    "tgn:hierarchy":[
        "tgn:7041312",
        "tgn:1003478",
        "tgn:1000003",
        "tgn:7003120",
        "tgn:1000080",
        "tgn:7029392"
    ],
    "tgn:id":7041312,
    "tgn:name":"San Michele",
    "tgn:placetype":[
        "aat:300008347"
    ]
},
  "bbox": [],
  "geometry": {"coordinates":[8.433333,46.366667],"type":"Point"}
}