{
  "id": 7509203,
  "type": "Feature",
  "properties": {
    "tgn:hierarchy":[
        "tgn:7509203",
        "tgn:7000509",
        "tgn:1008380",
        "tgn:1000226",
        "tgn:1000006",
        "tgn:7029392"
    ],
    "tgn:id":7509203,
    "tgn:name:en":"Waimangu",
    "tgn:placetype":[
        "aat:300008347"
    ]
},
  "bbox": [],
  "geometry": {"coordinates":[176.383333,-38.283333],"type":"Point"}
}