{
  "id": 2672855,
  "type": "Feature",
  "properties": {
    "tgn:hierarchy":[
        "tgn:2672855",
        "tgn:1000001",
        "tgn:7006451",
        "tgn:7012149",
        "tgn:2000099",
        "tgn:7029392"
    ],
    "tgn:id":2672855,
    "tgn:name":"Snake Butte",
    "tgn:placetype":[
        "aat:300008798"
    ]
},
  "bbox": [],
  "geometry": {"coordinates":[-110.4333,35.6333],"type":"Point"}
}