{
  "id": 2232026,
  "type": "Feature",
  "properties": {
    "tgn:hierarchy":[
        "tgn:2232026",
        "tgn:7002659",
        "tgn:1000001",
        "tgn:2000004",
        "tgn:7012149",
        "tgn:7029392"
    ],
    "tgn:id":2232026,
    "tgn:name":"Champion Creek",
    "tgn:placetype":[
        "aat:300008706"
    ]
},
  "bbox": [],
  "geometry": {"coordinates":[-86.4333,33.9167],"type":"Point"}
}