{
  "id": 2583138,
  "type": "Feature",
  "properties": {
    "tgn:hierarchy":[
        "tgn:2583138",
        "tgn:1000001",
        "tgn:2001819",
        "tgn:7012149",
        "tgn:7007713",
        "tgn:7029392"
    ],
    "tgn:id":2583138,
    "tgn:name":"Pine Lakes Addition",
    "tgn:placetype":[
        "aat:300008347"
    ]
},
  "bbox": [],
  "geometry": {"coordinates":[-96.6333,43.55],"type":"Point"}
}