{
  "id": 2336600,
  "type": "Feature",
  "properties": {
    "tgn:hierarchy":[
        "tgn:2336600",
        "tgn:1000001",
        "tgn:7012149",
        "tgn:2001454",
        "tgn:7007566",
        "tgn:7029392"
    ],
    "tgn:id":2336600,
    "tgn:name":"Four Mile Reservoir",
    "tgn:placetype":[
        "aat:300006191"
    ]
},
  "bbox": [],
  "geometry": {"coordinates":[-105.8667,35.6833],"type":"Point"}
}