<<<<<<< HEAD
{
  "id": 2336600,
  "type": "Feature",
  "properties": {
    "tgn:hierarchy":[
        "tgn:2336600",
        "tgn:1000001",
        "tgn:7012149",
        "tgn:2001454",
        "tgn:7007566",
        "tgn:7029392"
    ],
    "tgn:id":2336600,
    "tgn:name":"Four Mile Reservoir",
    "tgn:placetype":[
        "aat:300006191"
    ]
},
  "bbox": [],
  "geometry": {"coordinates":[-105.8667,35.6833],"type":"Point"}
}
=======
{"geometry":{"type":"Point","coordinates":[-105.866700,35.683300]},"type":"Feature","properties":{"hierarchy":["tgn:2336600","tgn:1000001","tgn:7012149","tgn:2001454","tgn:7007566","tgn:7029392"],"placetype":["aat:300006191"],"id":2336600,"name:xx":"Four Mile Reservoir"}}
>>>>>>> 03f74aca74312dbeaf24d7e61306dd6a786dc3d0
