{
  "id": 2602617,
  "type": "Feature",
  "properties": {
    "tgn:hierarchy":[
        "tgn:2602617",
        "tgn:1000001",
        "tgn:1002302",
        "tgn:7012149",
        "tgn:7007568",
        "tgn:7029392"
    ],
    "tgn:id":2602617,
    "tgn:name":"Quail Hollow",
    "tgn:placetype":[
        "aat:300008761"
    ]
},
  "bbox": [],
  "geometry": {"coordinates":[-76.1333,42.4833],"type":"Point"}
}