{
  "id": 7195984,
  "type": "Feature",
  "properties": {
    "tgn:hierarchy":[
        "tgn:7195984",
        "tgn:1000003",
        "tgn:7003687",
        "tgn:7000084",
        "tgn:7029392"
    ],
    "tgn:id":7195984,
    "tgn:name":"Dorfstelle Brelkendorf",
    "tgn:placetype":[
        "aat:300055621"
    ]
},
  "bbox": [],
  "geometry": {"coordinates":[11.883333,51.633333],"type":"Point"}
}