{
  "id": 7547612,
  "type": "Feature",
  "properties": {
    "tgn:hierarchy":[
        "tgn:7547612",
        "tgn:7001819",
        "tgn:1000004",
        "tgn:7000198",
        "tgn:7029392"
    ],
    "tgn:id":7547612,
    "tgn:name:en":"Ahui River",
    "tgn:placetype":[
        "aat:300008699"
    ]
},
  "bbox": [],
  "geometry": {"coordinates":[95.809327,28.492343],"type":"Point"}
}