{
  "id": 7548608,
  "type": "Feature",
  "properties": {
    "tgn:hierarchy":[
        "tgn:7548608",
        "tgn:1000004",
        "tgn:7000198",
        "tgn:7016788",
        "tgn:7029392"
    ],
    "tgn:id":7548608,
    "tgn:name:en":"B\u016bndi Road",
    "tgn:placetype":[
        "aat:300007783"
    ]
},
  "bbox": [],
  "geometry": {"coordinates":[75.937502,25.32378],"type":"Point"}
}