<<<<<<< HEAD
{
  "id": 7362107,
  "type": "Feature",
  "properties": {
    "tgn:hierarchy":[
        "tgn:7362107",
        "tgn:1000001",
        "tgn:1001960",
        "tgn:7005560",
        "tgn:7029392"
    ],
    "tgn:id":7362107,
    "tgn:name":"El Denuncio",
    "tgn:placetype":[
        "aat:300008347"
    ]
},
  "bbox": [],
  "geometry": {"coordinates":[-109.15,27.116667],"type":"Point"}
}
=======
{"geometry":{"type":"Point","coordinates":[-109.150000,27.116667]},"type":"Feature","properties":{"hierarchy":["tgn:7362107","tgn:1000001","tgn:1001960","tgn:7005560","tgn:7029392"],"placetype":["aat:300008347"],"id":7362107,"name:xx":"El Denuncio"}}
>>>>>>> 03f74aca74312dbeaf24d7e61306dd6a786dc3d0
