{
  "id": 7193138,
  "type": "Feature",
  "properties": {
    "tgn:hierarchy":[
        "tgn:7193138",
        "tgn:1000003",
        "tgn:7003678",
        "tgn:7000084",
        "tgn:7029392"
    ],
    "tgn:id":7193138,
    "tgn:name":"Fleckenb\u00fchl",
    "tgn:placetype":[
        "aat:300000206"
    ]
},
  "bbox": [],
  "geometry": {"coordinates":[8.816667,50.866667],"type":"Point"}
}