{
  "id": 2515992,
  "type": "Feature",
  "properties": {
    "tgn:hierarchy":[
        "tgn:2515992",
        "tgn:1000001",
        "tgn:1002275",
        "tgn:7012149",
        "tgn:7007920",
        "tgn:7029392"
    ],
    "tgn:id":2515992,
    "tgn:name":"Mimsi Marsh",
    "tgn:placetype":[
        "aat:300008905"
    ]
},
  "bbox": [],
  "geometry": {"coordinates":[-122.5167,45.5833],"type":"Point"}
}