{
  "id": 7044963,
  "type": "Feature",
  "properties": {
    "tgn:hierarchy":[
        "tgn:7044963",
        "tgn:7003158",
        "tgn:1000003",
        "tgn:7003124",
        "tgn:1000080",
        "tgn:7029392"
    ],
    "tgn:id":7044963,
    "tgn:name":"Forti",
    "tgn:placetype":[
        "aat:300008347"
    ]
},
  "bbox": [],
  "geometry": {"coordinates":[10.666667,46.083333],"type":"Point"}
}