<<<<<<< HEAD
{
  "id": 7366898,
  "type": "Feature",
  "properties": {
    "tgn:hierarchy":[
        "tgn:7366898",
        "tgn:7005581",
        "tgn:1000001",
        "tgn:7005560",
        "tgn:7029392"
    ],
    "tgn:id":7366898,
    "tgn:name":"Esp\u00edritu Santo, Sierra del",
    "tgn:placetype":[
        "aat:300008795"
    ]
},
  "bbox": [],
  "geometry": {"coordinates":[-104.3,28.05],"type":"Point"}
}
=======
{"geometry":{"type":"Point","coordinates":[-104.300000,28.050000]},"type":"Feature","properties":{"hierarchy":["tgn:7366898","tgn:7005581","tgn:1000001","tgn:7005560","tgn:7029392"],"placetype":["aat:300008795"],"id":7366898,"name:xx":"Esp\u00edritu Santo, Sierra del"}}
>>>>>>> 03f74aca74312dbeaf24d7e61306dd6a786dc3d0
