{
  "id": 1086991,
  "type": "Feature",
  "properties": {
    "tgn:hierarchy":[
        "tgn:1086991",
        "tgn:7000420",
        "tgn:7018452",
        "tgn:1000004",
        "tgn:1000144",
        "tgn:7029392"
    ],
    "tgn:id":1086991,
    "tgn:name":"Yalvac",
    "tgn:placetype":[
        "aat:300008347",
        "aat:300008375"
    ]
},
  "bbox": [],
  "geometry": {"coordinates":[31.1833,38.2833],"type":"Point"}
}