<<<<<<< HEAD
{
  "id": 2254663,
  "type": "Feature",
  "properties": {
    "tgn:hierarchy":[
        "tgn:2254663",
        "tgn:1000001",
        "tgn:7012149",
        "tgn:2000961",
        "tgn:7007520",
        "tgn:7029392"
    ],
    "tgn:id":2254663,
    "tgn:name":"Coon Lake",
    "tgn:placetype":[
        "aat:300008680"
    ]
},
  "bbox": [],
  "geometry": {"coordinates":[-85.5333,44.7],"type":"Point"}
}
=======
{"geometry":{"type":"Point","coordinates":[-85.533300,44.700000]},"type":"Feature","properties":{"hierarchy":["tgn:2254663","tgn:1000001","tgn:7012149","tgn:2000961","tgn:7007520","tgn:7029392"],"placetype":["aat:300008680"],"id":2254663,"name:xx":"Coon Lake"}}
>>>>>>> 03f74aca74312dbeaf24d7e61306dd6a786dc3d0
