{
  "id": 7528440,
  "type": "Feature",
  "properties": {
    "tgn:hierarchy":[
        "tgn:7528440",
        "tgn:7001242",
        "tgn:7016833",
        "tgn:1001087",
        "tgn:7029392"
    ],
    "tgn:id":7528440,
    "tgn:name":"Sh\u016bsh\u0101y",
    "tgn:placetype":[
        "aat:300008347"
    ]
},
  "bbox": [],
  "geometry": {"coordinates":[31.002211,30.326455],"type":"Point"}
}