{
  "id": 7126215,
  "type": "Feature",
  "properties": {
    "tgn:hierarchy":[
        "tgn:7126215",
        "tgn:1000003",
        "tgn:7003676",
        "tgn:7000084",
        "tgn:7029392"
    ],
    "tgn:id":7126215,
    "tgn:name":"Nord Edewecht",
    "tgn:placetype":[
        "aat:300008347"
    ]
},
  "bbox": [],
  "geometry": {"coordinates":[7.983333,53.133333],"type":"Point"}
}