{
  "id": 2111457,
  "type": "Feature",
  "properties": {
    "tgn:hierarchy":[
        "tgn:2111457",
        "tgn:1000001",
        "tgn:7012149",
        "tgn:1002667",
        "tgn:7007919",
        "tgn:7029392"
    ],
    "tgn:id":2111457,
    "tgn:name":"Deltaville",
    "tgn:placetype":[
        "aat:300008347"
    ]
},
  "bbox": [],
  "geometry": {"coordinates":[-76.3333,37.55],"type":"Point"}
}