{
  "id": 2482256,
  "type": "Feature",
  "properties": {
    "tgn:hierarchy":[
        "tgn:2482256",
        "tgn:1000001",
        "tgn:7012149",
        "tgn:2000279",
        "tgn:7007240",
        "tgn:7029392"
    ],
    "tgn:id":2482256,
    "tgn:name":"Langford Pond",
    "tgn:placetype":[
        "aat:300008680"
    ]
},
  "bbox": [],
  "geometry": {"coordinates":[-83.2667,30.5333],"type":"Point"}
}