{
  "id": 4002405,
  "type": "Feature",
  "properties": {
    "tgn:hierarchy":[
        "tgn:4002405",
        "tgn:1003506",
        "tgn:1000003",
        "tgn:7002993",
        "tgn:1000080",
        "tgn:7029392"
    ],
    "tgn:id":4002405,
    "tgn:name":"Cavazzo Carnico",
    "tgn:placetype":[
        "aat:300008347"
    ]
},
  "bbox": [],
  "geometry": {"coordinates":[13.043611,46.370556],"type":"Point"}
}