{
  "id": 2061855,
  "type": "Feature",
  "properties": {
    "tgn:hierarchy":[
        "tgn:2061855",
        "tgn:1000001",
        "tgn:2001260",
        "tgn:7012149",
        "tgn:7007524",
        "tgn:7029392"
    ],
    "tgn:id":2061855,
    "tgn:name":"Wise River",
    "tgn:placetype":[
        "aat:300008347"
    ]
},
  "bbox": [],
  "geometry": {"coordinates":[-112.9333,45.7833],"type":"Point"}
}