{
  "id": 1137812,
  "type": "Feature",
  "properties": {
    "tgn:hierarchy":[
        "tgn:1137812",
        "tgn:1000004",
        "tgn:7011497",
        "tgn:7002435",
        "tgn:7029392"
    ],
    "tgn:id":1137812,
    "tgn:name":"Kuropatkino",
    "tgn:placetype":[
        "aat:300008347"
    ]
},
  "bbox": [],
  "geometry": {"coordinates":[45.3333,46.5333],"type":"Point"}
}