{
  "id": 2239298,
  "type": "Feature",
  "properties": {
    "tgn:hierarchy":[
        "tgn:2239298",
        "tgn:1000001",
        "tgn:2001483",
        "tgn:7012149",
        "tgn:7007709",
        "tgn:7029392"
    ],
    "tgn:id":2239298,
    "tgn:name":"Chunky Gal Mountain",
    "tgn:placetype":[
        "aat:300008798"
    ]
},
  "bbox": [],
  "geometry": {"coordinates":[-83.5667,35.0167],"type":"Point"}
}