<<<<<<< HEAD
{
  "id": 7055308,
  "type": "Feature",
  "properties": {
    "tgn:hierarchy":[
        "tgn:7055308",
        "tgn:7003013",
        "tgn:7003005",
        "tgn:1000003",
        "tgn:1000080",
        "tgn:7029392"
    ],
    "tgn:id":7055308,
    "tgn:name":"Miseno, Porto di",
    "tgn:placetype":[
        "aat:300132316"
    ]
},
  "bbox": [],
  "geometry": {"coordinates":[14.083333,40.783333],"type":"Point"}
}
=======
{"geometry":{"type":"Point","coordinates":[14.083333,40.783333]},"type":"Feature","properties":{"hierarchy":["tgn:7055308","tgn:7003013","tgn:7003005","tgn:1000003","tgn:1000080","tgn:7029392"],"placetype":["aat:300132316"],"id":7055308,"name:xx":"Miseno, Porto di"}}
>>>>>>> 03f74aca74312dbeaf24d7e61306dd6a786dc3d0
