{
  "id": 2392078,
  "type": "Feature",
  "properties": {
    "tgn:hierarchy":[
        "tgn:2392078",
        "tgn:1000001",
        "tgn:7012149",
        "tgn:1002767",
        "tgn:7007920",
        "tgn:7029392"
    ],
    "tgn:id":2392078,
    "tgn:name":"Hines",
    "tgn:placetype":[
        "aat:300008347"
    ]
},
  "bbox": [],
  "geometry": {"coordinates":[-124.05,46.5667],"type":"Point"}
}