{
  "id": 7232606,
  "type": "Feature",
  "properties": {
    "tgn:hierarchy":[
        "tgn:7232606",
        "tgn:7002752",
        "tgn:7001399",
        "tgn:1000003",
        "tgn:1000074",
        "tgn:7029392"
    ],
    "tgn:id":7232606,
    "tgn:name":"Mago\u00fala",
    "tgn:placetype":[
        "aat:300008347"
    ]
},
  "bbox": [],
  "geometry": {"coordinates":[22.083333,39.816667],"type":"Point"}
}