<<<<<<< HEAD
{
  "id": 7175589,
  "type": "Feature",
  "properties": {
    "tgn:hierarchy":[
        "tgn:7175589",
        "tgn:1000003",
        "tgn:7000094",
        "tgn:7000084",
        "tgn:7029392"
    ],
    "tgn:id":7175589,
    "tgn:name":"Gro\u00df W\u00fcstenfelde",
    "tgn:placetype":[
        "aat:300008347"
    ]
},
  "bbox": [],
  "geometry": {"coordinates":[12.55,53.883333],"type":"Point"}
}
=======
{"geometry":{"type":"Point","coordinates":[12.550000,53.883333]},"type":"Feature","properties":{"hierarchy":["tgn:7175589","tgn:1000003","tgn:7000094","tgn:7000084","tgn:7029392"],"placetype":["aat:300008347"],"id":7175589,"name:xx":"Gro\u00df W\u00fcstenfelde"}}
>>>>>>> 03f74aca74312dbeaf24d7e61306dd6a786dc3d0
