{
  "id": 1123753,
  "type": "Feature",
  "properties": {
    "tgn:hierarchy":[
        "tgn:1123753",
        "tgn:7001242",
        "tgn:7016752",
        "tgn:7593699",
        "tgn:7029392"
    ],
    "tgn:id":1123753,
    "tgn:name":"Endja, Oued",
    "tgn:placetype":[
        "aat:300008707"
    ]
},
  "bbox": [],
  "geometry": {"coordinates":[6.264,36.539],"type":"Point"}
}