{
  "id": 2179215,
  "type": "Feature",
  "properties": {
    "tgn:hierarchy":[
        "tgn:2179215",
        "tgn:1000001",
        "tgn:7012149",
        "tgn:7007524",
        "tgn:7029392"
    ],
    "tgn:id":2179215,
    "tgn:name":"Blake Creek",
    "tgn:placetype":[
        "aat:300008706"
    ]
},
  "bbox": [],
  "geometry": {"coordinates":[-109.5667,46.6833],"type":"Point"}
}