{
  "id": 2320435,
  "type": "Feature",
  "properties": {
    "tgn:hierarchy":[
        "tgn:2320435",
        "tgn:1000001",
        "tgn:7012149",
        "tgn:2000877",
        "tgn:7007256",
        "tgn:7029392"
    ],
    "tgn:id":2320435,
    "tgn:name":"Evergreen Plantation",
    "tgn:placetype":[
        "aat:300008347"
    ]
},
  "bbox": [],
  "geometry": {"coordinates":[-91.1833,30.2667],"type":"Point"}
}