{
  "id": 7323786,
  "type": "Feature",
  "properties": {
    "tgn:hierarchy":[
        "tgn:7323786",
        "tgn:7002820",
        "tgn:7030216",
        "tgn:1000003",
        "tgn:1000095",
        "tgn:7029392"
    ],
    "tgn:id":7323786,
    "tgn:name":"Roig, Cabo",
    "tgn:placetype":[
        "aat:300008850"
    ]
},
  "bbox": [],
  "geometry": {"coordinates":[3.181263,41.876052],"type":"Point"}
}