<<<<<<< HEAD
{
  "id": 2333233,
  "type": "Feature",
  "properties": {
    "tgn:hierarchy":[
        "tgn:2333233",
        "tgn:1000001",
        "tgn:7012149",
        "tgn:2001670",
        "tgn:7007707",
        "tgn:7029392"
    ],
    "tgn:id":2333233,
    "tgn:name":"Fobb",
    "tgn:placetype":[
        "aat:300008347"
    ]
},
  "bbox": [],
  "geometry": {"coordinates":[-96.8333,33.9],"type":"Point"}
}
=======
{"geometry":{"type":"Point","coordinates":[-96.833300,33.900000]},"type":"Feature","properties":{"hierarchy":["tgn:2333233","tgn:1000001","tgn:7012149","tgn:2001670","tgn:7007707","tgn:7029392"],"placetype":["aat:300008347"],"id":2333233,"name:xx":"Fobb"}}
>>>>>>> 03f74aca74312dbeaf24d7e61306dd6a786dc3d0
