{
  "id": 2394174,
  "type": "Feature",
  "properties": {
    "tgn:hierarchy":[
        "tgn:2394174",
        "tgn:1000001",
        "tgn:7012149",
        "tgn:2002110",
        "tgn:7007827",
        "tgn:7029392"
    ],
    "tgn:id":2394174,
    "tgn:name":"Hogan Spring",
    "tgn:placetype":[
        "aat:300008697"
    ]
},
  "bbox": [],
  "geometry": {"coordinates":[-109.2667,38.95],"type":"Point"}
}