{
  "id": 2689725,
  "type": "Feature",
  "properties": {
    "tgn:hierarchy":[
        "tgn:2689725",
        "tgn:1000001",
        "tgn:7012149",
        "tgn:2001455",
        "tgn:7007566",
        "tgn:7029392"
    ],
    "tgn:id":2689725,
    "tgn:name":"Squaw Tit Canyon",
    "tgn:placetype":[
        "aat:300008761"
    ]
},
  "bbox": [],
  "geometry": {"coordinates":[-106.6333,32.95],"type":"Point"}
}