{
  "id": 2741366,
  "type": "Feature",
  "properties": {
    "tgn:hierarchy":[
        "tgn:2741366",
        "tgn:1000001",
        "tgn:7012149",
        "tgn:2000917",
        "tgn:7007256",
        "tgn:7029392"
    ],
    "tgn:id":2741366,
    "tgn:name":"Upshaw Creek",
    "tgn:placetype":[
        "aat:300008706"
    ]
},
  "bbox": [],
  "geometry": {"coordinates":[-92.85,31.8833],"type":"Point"}
}