{
  "id": 2443486,
  "type": "Feature",
  "properties": {
    "tgn:hierarchy":[
        "tgn:2443486",
        "tgn:1000001",
        "tgn:7012149",
        "tgn:2000908",
        "tgn:7007256",
        "tgn:7029392"
    ],
    "tgn:id":2443486,
    "tgn:name":"La Cache, Bayou",
    "tgn:placetype":[
        "aat:300008699"
    ]
},
  "bbox": [],
  "geometry": {"coordinates":[-90.6167,29.55],"type":"Point"}
}