{
  "id": 7403126,
  "type": "Feature",
  "properties": {
    "tgn:hierarchy":[
        "tgn:7403126",
        "tgn:1000001",
        "tgn:7005600",
        "tgn:7005560",
        "tgn:7029392"
    ],
    "tgn:id":7403126,
    "tgn:name":"Xcorralcat",
    "tgn:placetype":[
        "aat:300008347"
    ]
},
  "bbox": [],
  "geometry": {"coordinates":[-90.120833,20.741667],"type":"Point"}
}