{
  "id": 1030133,
  "type": "Feature",
  "properties": {
    "tgn:hierarchy":[
        "tgn:1030133",
        "tgn:7002445",
        "tgn:1000003",
        "tgn:7008153",
        "tgn:7008591",
        "tgn:7029392"
    ],
    "tgn:id":1030133,
    "tgn:name":"Nettlestead",
    "tgn:placetype":[
        "aat:300008347",
        "aat:300008372"
    ]
},
  "bbox": [],
  "geometry": {"coordinates":[0.4167,51.25],"type":"Point"}
}