{
  "id": 2544704,
  "type": "Feature",
  "properties": {
    "tgn:hierarchy":[
        "tgn:2544704",
        "tgn:1000001",
        "tgn:7012149",
        "tgn:7016056",
        "tgn:7007520",
        "tgn:7029392"
    ],
    "tgn:id":2544704,
    "tgn:name":"North Channel Saint Clair River",
    "tgn:placetype":[
        "aat:300008707"
    ]
},
  "bbox": [],
  "geometry": {"coordinates":[-82.6167,42.6167],"type":"Point"}
}