{
  "id": 7100661,
  "type": "Feature",
  "properties": {
    "tgn:hierarchy":[
        "tgn:7100661",
        "tgn:7003692",
        "tgn:1000003",
        "tgn:7000084",
        "tgn:7029392"
    ],
    "tgn:id":7100661,
    "tgn:name":"Schabelhof",
    "tgn:placetype":[
        "aat:300000206"
    ]
},
  "bbox": [],
  "geometry": {"coordinates":[8.516667,48.016667],"type":"Point"}
}