{
  "id": 2211593,
  "type": "Feature",
  "properties": {
    "tgn:hierarchy":[
        "tgn:2211593",
        "tgn:1000001",
        "tgn:7012149",
        "tgn:7007525",
        "tgn:7029392"
    ],
    "tgn:id":2211593,
    "tgn:name":"Buttermilk Creek",
    "tgn:placetype":[
        "aat:300008706"
    ]
},
  "bbox": [],
  "geometry": {"coordinates":[-96.4167,41.5333],"type":"Point"}
}