{
  "id": 7552668,
  "type": "Feature",
  "properties": {
    "tgn:hierarchy":[
        "tgn:7552668",
        "tgn:7001819",
        "tgn:1000004",
        "tgn:7000198",
        "tgn:7029392"
    ],
    "tgn:id":7552668,
    "tgn:name:en":"Mrambon",
    "tgn:placetype":[
        "aat:300008347"
    ]
},
  "bbox": [],
  "geometry": {"coordinates":[95.789097,28.396223],"type":"Point"}
}