{
  "id": 7060252,
  "type": "Feature",
  "properties": {
    "tgn:hierarchy":[
        "tgn:7060252",
        "tgn:7000096",
        "tgn:1000003",
        "tgn:7000084",
        "tgn:7029392"
    ],
    "tgn:id":7060252,
    "tgn:name":"Adolf von Hahnkekanal",
    "tgn:placetype":[
        "aat:300006075"
    ]
},
  "bbox": [],
  "geometry": {"coordinates":[12.933333,52.55],"type":"Point"}
}