<<<<<<< HEAD
{
  "id": 7356508,
  "type": "Feature",
  "properties": {
    "tgn:hierarchy":[
        "tgn:7356508",
        "tgn:1000001",
        "tgn:7005596",
        "tgn:7005560",
        "tgn:7029392"
    ],
    "tgn:id":7356508,
    "tgn:name":"Chiltepec, Barra de",
    "tgn:placetype":[
        "aat:300386885"
    ]
},
  "bbox": [],
  "geometry": {"coordinates":[-93.083333,18.433333],"type":"Point"}
}
=======
{"geometry":{"type":"Point","coordinates":[-93.083333,18.433333]},"type":"Feature","properties":{"hierarchy":["tgn:7356508","tgn:1000001","tgn:7005596","tgn:7005560","tgn:7029392"],"placetype":["aat:300386885"],"id":7356508,"name:xx":"Chiltepec, Barra de"}}
>>>>>>> 03f74aca74312dbeaf24d7e61306dd6a786dc3d0
