{
  "id": 7023369,
  "type": "Feature",
  "properties": {
    "tgn:hierarchy":[
        "tgn:7023369",
        "tgn:1000001",
        "tgn:7012149",
        "tgn:7007712",
        "tgn:7029392"
    ],
    "tgn:id":7023369,
    "tgn:name":"Marco Millpond",
    "tgn:placetype":[
        "aat:300006191"
    ]
},
  "bbox": [],
  "geometry": {"coordinates":[-80.1167,34.2667],"type":"Point"}
}