<<<<<<< HEAD
{
  "id": 7023369,
  "type": "Feature",
  "properties": {
    "tgn:hierarchy":[
        "tgn:7023369",
        "tgn:1000001",
        "tgn:7012149",
        "tgn:7007712",
        "tgn:7029392"
    ],
    "tgn:id":7023369,
    "tgn:name":"Marco Millpond",
    "tgn:placetype":[
        "aat:300006191"
    ]
},
  "bbox": [],
  "geometry": {"coordinates":[-80.1167,34.2667],"type":"Point"}
}
=======
{"geometry":{"type":"Point","coordinates":[-80.116700,34.266700]},"type":"Feature","properties":{"hierarchy":["tgn:7023369","tgn:1000001","tgn:7012149","tgn:7007712","tgn:7029392"],"placetype":["aat:300006191"],"id":7023369,"name:xx":"Marco Millpond"}}
>>>>>>> 03f74aca74312dbeaf24d7e61306dd6a786dc3d0
