{
  "id": 7417966,
  "type": "Feature",
  "properties": {
    "tgn:hierarchy":[
        "tgn:7417966",
        "tgn:1000001",
        "tgn:7005591",
        "tgn:7005560",
        "tgn:7029392"
    ],
    "tgn:id":7417966,
    "tgn:name:es":"San Bartolo Salinas",
    "tgn:placetype":[
        "aat:300008347"
    ]
},
  "bbox": [],
  "geometry": {"coordinates":[-98.201667,17.8125],"type":"Point"}
}