{
  "id": 7413479,
  "type": "Feature",
  "properties": {
    "tgn:hierarchy":[
        "tgn:7413479",
        "tgn:7005580",
        "tgn:1000001",
        "tgn:7005560",
        "tgn:7029392"
    ],
    "tgn:id":7413479,
    "tgn:name":"El Amatal",
    "tgn:placetype":[
        "aat:300008347"
    ]
},
  "bbox": [],
  "geometry": {"coordinates":[-92.995833,16.633333],"type":"Point"}
}