{
  "id": 7293903,
  "type": "Feature",
  "properties": {
    "tgn:hierarchy":[
        "tgn:7293903",
        "tgn:7008912",
        "tgn:7030216",
        "tgn:1000003",
        "tgn:1000095",
        "tgn:7029392"
    ],
    "tgn:id":7293903,
    "tgn:name":"Vilach",
    "tgn:placetype":[
        "aat:300008347"
    ]
},
  "bbox": [],
  "geometry": {"coordinates":[0.798614,42.721173],"type":"Point"}
}