{
  "id": 2261956,
  "type": "Feature",
  "properties": {
    "tgn:hierarchy":[
        "tgn:2261956",
        "tgn:2000105",
        "tgn:1000001",
        "tgn:7016172",
        "tgn:7012149",
        "tgn:7029392"
    ],
    "tgn:id":2261956,
    "tgn:name":"Covington Lake",
    "tgn:placetype":[
        "aat:300008680"
    ]
},
  "bbox": [],
  "geometry": {"coordinates":[-91.0833,34.2667],"type":"Point"}
}