{
  "id": 7049176,
  "type": "Feature",
  "properties": {
    "tgn:hierarchy":[
        "tgn:7049176",
        "tgn:7009084",
        "tgn:7004154",
        "tgn:1000003",
        "tgn:1000080",
        "tgn:7029392"
    ],
    "tgn:id":7049176,
    "tgn:name":"Diavolo, Passo del",
    "tgn:placetype":[
        "aat:300259572"
    ]
},
  "bbox": [],
  "geometry": {"coordinates":[13.75,41.866667],"type":"Point"}
}