{
  "id": 2704021,
  "type": "Feature",
  "properties": {
    "tgn:hierarchy":[
        "tgn:2704021",
        "tgn:1000001",
        "tgn:2001418",
        "tgn:7012149",
        "tgn:7007526",
        "tgn:7029392"
    ],
    "tgn:id":2704021,
    "tgn:name":"Sundown Reservoir",
    "tgn:placetype":[
        "aat:300006191"
    ]
},
  "bbox": [],
  "geometry": {"coordinates":[-116.2333,37.4333],"type":"Point"}
}