{
  "id": 7457267,
  "type": "Feature",
  "properties": {
    "tgn:hierarchy":[
        "tgn:7457267",
        "tgn:7002445",
        "tgn:1000003",
        "tgn:7012032",
        "tgn:7008591",
        "tgn:7029392"
    ],
    "tgn:id":7457267,
    "tgn:name:en":"Mark",
    "tgn:placetype":[
        "aat:300008347"
    ]
},
  "bbox": [],
  "geometry": {"coordinates":[-2.888611,51.227778],"type":"Point"}
}