{
  "id": 2164311,
  "type": "Feature",
  "properties": {
    "tgn:hierarchy":[
        "tgn:2164311",
        "tgn:1000001",
        "tgn:7012149",
        "tgn:2001872",
        "tgn:7007825",
        "tgn:7029392"
    ],
    "tgn:id":2164311,
    "tgn:name":"Berry Branch",
    "tgn:placetype":[
        "aat:300008699"
    ]
},
  "bbox": [],
  "geometry": {"coordinates":[-88.0833,35.35],"type":"Point"}
}