{
  "id": 2339201,
  "type": "Feature",
  "properties": {
    "tgn:hierarchy":[
        "tgn:2339201",
        "tgn:2000090",
        "tgn:1000001",
        "tgn:7006451",
        "tgn:7012149",
        "tgn:7029392"
    ],
    "tgn:id":2339201,
    "tgn:name":"Franks Tank",
    "tgn:placetype":[
        "aat:300006191"
    ]
},
  "bbox": [],
  "geometry": {"coordinates":[-109.65,34.75],"type":"Point"}
}