{
  "id": 7132786,
  "type": "Feature",
  "properties": {
    "tgn:hierarchy":[
        "tgn:7132786",
        "tgn:1000003",
        "tgn:7003688",
        "tgn:7000084",
        "tgn:7029392"
    ],
    "tgn:id":7132786,
    "tgn:name":"M\u00f6rderkoppel",
    "tgn:placetype":[
        "aat:300008863"
    ]
},
  "bbox": [],
  "geometry": {"coordinates":[9.85,54.733333],"type":"Point"}
}