<<<<<<< HEAD
{
  "id": 7485693,
  "type": "Feature",
  "properties": {
    "tgn:hierarchy":[
        "tgn:7485693",
        "tgn:1000004",
        "tgn:7492971",
        "tgn:1000141",
        "tgn:7029392"
    ],
    "tgn:id":7485693,
    "tgn:name":"Sichong Xikou",
    "tgn:placetype":[
        "aat:300387057"
    ]
},
  "bbox": [],
  "geometry": {"coordinates":[120.707222,22.063889],"type":"Point"}
}
=======
{"geometry":{"type":"Point","coordinates":[120.707222,22.063889]},"type":"Feature","properties":{"hierarchy":["tgn:7485693","tgn:1000004","tgn:7492971","tgn:1000141","tgn:7029392"],"placetype":["aat:300387057"],"id":7485693,"name:xx":"Sichong Xikou"}}
>>>>>>> 03f74aca74312dbeaf24d7e61306dd6a786dc3d0
