{
  "id": 2203982,
  "type": "Feature",
  "properties": {
    "tgn:hierarchy":[
        "tgn:2203982",
        "tgn:1000001",
        "tgn:7012149",
        "tgn:7007919",
        "tgn:7029392"
    ],
    "tgn:id":2203982,
    "tgn:name":"Buckyard Branch",
    "tgn:placetype":[
        "aat:300008699"
    ]
},
  "bbox": [],
  "geometry": {"coordinates":[-77.05,37.8167],"type":"Point"}
}