{
  "id": 2374744,
  "type": "Feature",
  "properties": {
    "tgn:hierarchy":[
        "tgn:2374744",
        "tgn:1000001",
        "tgn:2001260",
        "tgn:7012149",
        "tgn:7007524",
        "tgn:7029392"
    ],
    "tgn:id":2374744,
    "tgn:name":"Hands Ditch",
    "tgn:placetype":[
        "aat:300006075"
    ]
},
  "bbox": [],
  "geometry": {"coordinates":[-112.7167,45.1333],"type":"Point"}
}