{
  "id": 2581384,
  "type": "Feature",
  "properties": {
    "tgn:hierarchy":[
        "tgn:2581384",
        "tgn:1000001",
        "tgn:2001411",
        "tgn:7012149",
        "tgn:7007526",
        "tgn:7029392"
    ],
    "tgn:id":2581384,
    "tgn:name":"Pilot Creek Valley",
    "tgn:placetype":[
        "aat:300008761"
    ]
},
  "bbox": [],
  "geometry": {"coordinates":[-114.15,41.1833],"type":"Point"}
}