{
  "id": 7498612,
  "type": "Feature",
  "properties": {
    "tgn:hierarchy":[
        "tgn:7498612",
        "tgn:1000004",
        "tgn:1000454",
        "tgn:1000141",
        "tgn:7029392"
    ],
    "tgn:id":7498612,
    "tgn:name":"Fengzilin Shan",
    "tgn:placetype":[
        "aat:300008798"
    ]
},
  "bbox": [],
  "geometry": {"coordinates":[121.6428,25.0018],"type":"Point"}
}