{
  "id": 2107539,
  "type": "Feature",
  "properties": {
    "tgn:hierarchy":[
        "tgn:2107539",
        "tgn:1000001",
        "tgn:7012149",
        "tgn:1002535",
        "tgn:7007826",
        "tgn:7029392"
    ],
    "tgn:id":2107539,
    "tgn:name":"Scurry",
    "tgn:placetype":[
        "aat:300008347"
    ]
},
  "bbox": [],
  "geometry": {"coordinates":[-96.3667,32.5167],"type":"Point"}
}