<<<<<<< HEAD
{
  "id": 2256366,
  "type": "Feature",
  "properties": {
    "tgn:hierarchy":[
        "tgn:2256366",
        "tgn:1000001",
        "tgn:2001702",
        "tgn:7012149",
        "tgn:7007708",
        "tgn:7029392"
    ],
    "tgn:id":2256366,
    "tgn:name":"Copple Creek",
    "tgn:placetype":[
        "aat:300008706"
    ]
},
  "bbox": [],
  "geometry": {"coordinates":[-124.0667,43.5667],"type":"Point"}
}
=======
{"geometry":{"type":"Point","coordinates":[-124.066700,43.566700]},"type":"Feature","properties":{"hierarchy":["tgn:2256366","tgn:1000001","tgn:2001702","tgn:7012149","tgn:7007708","tgn:7029392"],"placetype":["aat:300008706"],"id":2256366,"name:xx":"Copple Creek"}}
>>>>>>> 03f74aca74312dbeaf24d7e61306dd6a786dc3d0
