{
  "id": 2328789,
  "type": "Feature",
  "properties": {
    "tgn:hierarchy":[
        "tgn:2328789",
        "tgn:1000001",
        "tgn:7012149",
        "tgn:2001529",
        "tgn:7007709",
        "tgn:7029392"
    ],
    "tgn:id":2328789,
    "tgn:name":"Fishing Branch",
    "tgn:placetype":[
        "aat:300008699"
    ]
},
  "bbox": [],
  "geometry": {"coordinates":[-78.9333,36.45],"type":"Point"}
}