{
  "id": 2290212,
  "type": "Feature",
  "properties": {
    "tgn:hierarchy":[
        "tgn:2290212",
        "tgn:1000001",
        "tgn:7012149",
        "tgn:2002331",
        "tgn:7007922",
        "tgn:7029392"
    ],
    "tgn:id":2290212,
    "tgn:name":"Dodge Chute",
    "tgn:placetype":[
        "aat:300008699"
    ]
},
  "bbox": [],
  "geometry": {"coordinates":[-91.3333,43.95],"type":"Point"}
}