<<<<<<< HEAD
{
  "id": 7023546,
  "type": "Feature",
  "properties": {
    "tgn:hierarchy":[
        "tgn:7023546",
        "tgn:1000001",
        "tgn:7012149",
        "tgn:7007255",
        "tgn:7029392"
    ],
    "tgn:id":7023546,
    "tgn:name":"Swango Fork",
    "tgn:placetype":[
        "aat:300008699"
    ]
},
  "bbox": [],
  "geometry": {"coordinates":[-83.4833,37.8333],"type":"Point"}
}
=======
{"geometry":{"type":"Point","coordinates":[-83.483300,37.833300]},"type":"Feature","properties":{"hierarchy":["tgn:7023546","tgn:1000001","tgn:7012149","tgn:7007255","tgn:7029392"],"placetype":["aat:300008699"],"id":7023546,"name:xx":"Swango Fork"}}
>>>>>>> 03f74aca74312dbeaf24d7e61306dd6a786dc3d0
