{
  "id": 7023546,
  "type": "Feature",
  "properties": {
    "tgn:hierarchy":[
        "tgn:7023546",
        "tgn:1000001",
        "tgn:7012149",
        "tgn:7007255",
        "tgn:7029392"
    ],
    "tgn:id":7023546,
    "tgn:name":"Swango Fork",
    "tgn:placetype":[
        "aat:300008699"
    ]
},
  "bbox": [],
  "geometry": {"coordinates":[-83.4833,37.8333],"type":"Point"}
}