{
  "id": 2477463,
  "type": "Feature",
  "properties": {
    "tgn:hierarchy":[
        "tgn:2477463",
        "tgn:1000001",
        "tgn:7012149",
        "tgn:2002250",
        "tgn:7007920",
        "tgn:7029392"
    ],
    "tgn:id":2477463,
    "tgn:name":"Lyons Hill",
    "tgn:placetype":[
        "aat:300008798"
    ]
},
  "bbox": [],
  "geometry": {"coordinates":[-117.8167,48.0167],"type":"Point"}
}