{
  "id": 7040277,
  "type": "Feature",
  "properties": {
    "tgn:hierarchy":[
        "tgn:7040277",
        "tgn:7005880",
        "tgn:1000003",
        "tgn:7003237",
        "tgn:1000080",
        "tgn:7029392"
    ],
    "tgn:id":7040277,
    "tgn:name":"Sarginesco",
    "tgn:placetype":[
        "aat:300008347"
    ]
},
  "bbox": [],
  "geometry": {"coordinates":[10.616667,45.166667],"type":"Point"}
}