<<<<<<< HEAD
{
  "id": 7350459,
  "type": "Feature",
  "properties": {
    "tgn:hierarchy":[
        "tgn:7350459",
        "tgn:7005581",
        "tgn:1000001",
        "tgn:7005560",
        "tgn:7029392"
    ],
    "tgn:id":7350459,
    "tgn:name":"Apache, Mesa del",
    "tgn:placetype":[
        "aat:300008811"
    ]
},
  "bbox": [],
  "geometry": {"coordinates":[-106.95,29.75],"type":"Point"}
}
=======
{"geometry":{"type":"Point","coordinates":[-106.950000,29.750000]},"type":"Feature","properties":{"hierarchy":["tgn:7350459","tgn:7005581","tgn:1000001","tgn:7005560","tgn:7029392"],"placetype":["aat:300008811"],"id":7350459,"name:xx":"Apache, Mesa del"}}
>>>>>>> 03f74aca74312dbeaf24d7e61306dd6a786dc3d0
