{
  "id": 2612892,
  "type": "Feature",
  "properties": {
    "tgn:hierarchy":[
        "tgn:2612892",
        "tgn:1000001",
        "tgn:7012149",
        "tgn:2001964",
        "tgn:7007826",
        "tgn:7029392"
    ],
    "tgn:id":2612892,
    "tgn:name":"Redmond Branch",
    "tgn:placetype":[
        "aat:300008699"
    ]
},
  "bbox": [],
  "geometry": {"coordinates":[-97.05,33.6333],"type":"Point"}
}