{
  "id": 1129648,
  "type": "Feature",
  "properties": {
    "tgn:hierarchy":[
        "tgn:1129648",
        "tgn:1000001",
        "tgn:7012149",
        "tgn:7007157",
        "tgn:7029392"
    ],
    "tgn:id":1129648,
    "tgn:name":"Santa Margarita",
    "tgn:placetype":[
        "aat:300008707"
    ]
},
  "bbox": [],
  "geometry": {"coordinates":[-117.1333,33.4667],"type":"Point"}
}