<<<<<<< HEAD
{
  "id": 2405278,
  "type": "Feature",
  "properties": {
    "tgn:hierarchy":[
        "tgn:2405278",
        "tgn:1000001",
        "tgn:7012149",
        "tgn:1002594",
        "tgn:7007920",
        "tgn:7029392"
    ],
    "tgn:id":2405278,
    "tgn:name":"Huffaker Mountain",
    "tgn:placetype":[
        "aat:300008798"
    ]
},
  "bbox": [],
  "geometry": {"coordinates":[-121.9833,46.4667],"type":"Point"}
}
=======
{"geometry":{"type":"Point","coordinates":[-121.983300,46.466700]},"type":"Feature","properties":{"hierarchy":["tgn:2405278","tgn:1000001","tgn:7012149","tgn:1002594","tgn:7007920","tgn:7029392"],"placetype":["aat:300008798"],"id":2405278,"name:xx":"Huffaker Mountain"}}
>>>>>>> 03f74aca74312dbeaf24d7e61306dd6a786dc3d0
