{
  "id": 7140122,
  "type": "Feature",
  "properties": {
    "tgn:hierarchy":[
        "tgn:7140122",
        "tgn:7003669",
        "tgn:1000003",
        "tgn:7000084",
        "tgn:7029392"
    ],
    "tgn:id":7140122,
    "tgn:name":"Lindahof",
    "tgn:placetype":[
        "aat:300000206"
    ]
},
  "bbox": [],
  "geometry": {"coordinates":[13.183333,48.616667],"type":"Point"}
}