{
  "id": 7450918,
  "type": "Feature",
  "properties": {
    "tgn:hierarchy":[
        "tgn:7450918",
        "tgn:7002444",
        "tgn:1000003",
        "tgn:7008082",
        "tgn:7008591",
        "tgn:7029392"
    ],
    "tgn:id":7450918,
    "tgn:name:en":"Easter Fearn Burn",
    "tgn:placetype":[
        "aat:300008699"
    ]
},
  "bbox": [],
  "geometry": {"coordinates":[-4.283333,57.85],"type":"Point"}
}