{
  "id": 7201191,
  "type": "Feature",
  "properties": {
    "tgn:hierarchy":[
        "tgn:7201191",
        "tgn:7003669",
        "tgn:1000003",
        "tgn:7000084",
        "tgn:7029392"
    ],
    "tgn:id":7201191,
    "tgn:name":"Dumpf",
    "tgn:placetype":[
        "aat:300008347"
    ]
},
  "bbox": [],
  "geometry": {"coordinates":[12.85,49.116667],"type":"Point"}
}