{
  "id": 2242832,
  "type": "Feature",
  "properties": {
    "tgn:hierarchy":[
        "tgn:2242832",
        "tgn:1000001",
        "tgn:7012149",
        "tgn:2002385",
        "tgn:7007923",
        "tgn:7029392"
    ],
    "tgn:id":2242832,
    "tgn:name":"Clear Creek",
    "tgn:placetype":[
        "aat:300008706"
    ]
},
  "bbox": [],
  "geometry": {"coordinates":[-110.6167,41.0667],"type":"Point"}
}