{
  "id": 2168375,
  "type": "Feature",
  "properties": {
    "tgn:hierarchy":[
        "tgn:2168375",
        "tgn:1000001",
        "tgn:7012149",
        "tgn:2000930",
        "tgn:7007515",
        "tgn:7029392"
    ],
    "tgn:id":2168375,
    "tgn:name":"Big Grenier Pond",
    "tgn:placetype":[
        "aat:300008680"
    ]
},
  "bbox": [],
  "geometry": {"coordinates":[-70.2333,45.9667],"type":"Point"}
}