<<<<<<< HEAD
{
  "id": 7056115,
  "type": "Feature",
  "properties": {
    "tgn:hierarchy":[
        "tgn:7056115",
        "tgn:1000003",
        "tgn:7003122",
        "tgn:1000080",
        "tgn:7029392"
    ],
    "tgn:id":7056115,
    "tgn:name":"Lentini, Lago di",
    "tgn:placetype":[
        "aat:300008680"
    ]
},
  "bbox": [],
  "geometry": {"coordinates":[14.95,37.316667],"type":"Point"}
}
=======
{"geometry":{"type":"Point","coordinates":[14.950000,37.316667]},"type":"Feature","properties":{"hierarchy":["tgn:7056115","tgn:1000003","tgn:7003122","tgn:1000080","tgn:7029392"],"placetype":["aat:300008680"],"id":7056115,"name:xx":"Lentini, Lago di"}}
>>>>>>> 03f74aca74312dbeaf24d7e61306dd6a786dc3d0
