{
  "id": 2577956,
  "type": "Feature",
  "properties": {
    "tgn:hierarchy":[
        "tgn:2577956",
        "tgn:1000001",
        "tgn:7012149",
        "tgn:7014589",
        "tgn:7007515",
        "tgn:7029392"
    ],
    "tgn:id":2577956,
    "tgn:name":"Pettegrove Point",
    "tgn:placetype":[
        "aat:300008850"
    ]
},
  "bbox": [],
  "geometry": {"coordinates":[-67.1333,45.1167],"type":"Point"}
}