{
  "id": 2698817,
  "type": "Feature",
  "properties": {
    "tgn:hierarchy":[
        "tgn:2698817",
        "tgn:1000001",
        "tgn:7012149",
        "tgn:2001056",
        "tgn:7007521",
        "tgn:7029392"
    ],
    "tgn:id":2698817,
    "tgn:name":"Strawberry Creek",
    "tgn:placetype":[
        "aat:300008706"
    ]
},
  "bbox": [],
  "geometry": {"coordinates":[-92.5833,46.15],"type":"Point"}
}