{
  "id": 1134859,
  "type": "Feature",
  "properties": {
    "tgn:hierarchy":[
        "tgn:1134859",
        "tgn:1001160",
        "tgn:7006477",
        "tgn:1000002",
        "tgn:7029392"
    ],
    "tgn:id":1134859,
    "tgn:name":"Torres, Arroyo",
    "tgn:placetype":[
        "aat:300008706"
    ]
},
  "bbox": [],
  "geometry": {"coordinates":[-58.75,-34.65],"type":"Point"}
}