{
  "id": 2643408,
  "type": "Feature",
  "properties": {
    "tgn:hierarchy":[
        "tgn:2643408",
        "tgn:1000001",
        "tgn:7012149",
        "tgn:2002118",
        "tgn:7007827",
        "tgn:7029392"
    ],
    "tgn:id":2643408,
    "tgn:name":"Sandy Hills",
    "tgn:placetype":[
        "aat:300008347"
    ]
},
  "bbox": [],
  "geometry": {"coordinates":[-111.85,40.5667],"type":"Point"}
}