{
  "id": 7212764,
  "type": "Feature",
  "properties": {
    "tgn:hierarchy":[
        "tgn:7212764",
        "tgn:1000003",
        "tgn:7003678",
        "tgn:7000084",
        "tgn:7029392"
    ],
    "tgn:id":7212764,
    "tgn:name":"Bocks-Berg",
    "tgn:placetype":[
        "aat:300008777"
    ]
},
  "bbox": [],
  "geometry": {"coordinates":[8.85,49.566667],"type":"Point"}
}