{
  "id": 7295107,
  "type": "Feature",
  "properties": {
    "tgn:hierarchy":[
        "tgn:7295107",
        "tgn:7002834",
        "tgn:1000003",
        "tgn:7002786",
        "tgn:1000095",
        "tgn:7029392"
    ],
    "tgn:id":7295107,
    "tgn:name":"Mondui\u00f1a, Arenal de",
    "tgn:placetype":[
        "aat:300008816"
    ]
},
  "bbox": [],
  "geometry": {"coordinates":[-8.805556,42.191667],"type":"Point"}
}