{
  "id": 7540629,
  "type": "Feature",
  "properties": {
    "tgn:hierarchy":[
        "tgn:7540629",
        "tgn:7001242",
        "tgn:7016833",
        "tgn:7000122",
        "tgn:7029392"
    ],
    "tgn:id":7540629,
    "tgn:name:en":"Sayy\u0101lah, Na\u015fb as",
    "tgn:placetype":[
        "aat:300008777"
    ]
},
  "bbox": [],
  "geometry": {"coordinates":[32.984384,22.105576],"type":"Point"}
}