{
  "id": 7533732,
  "type": "Feature",
  "properties": {
    "tgn:hierarchy":[
        "tgn:7533732",
        "tgn:7001242",
        "tgn:7016833",
        "tgn:7001312",
        "tgn:7029392"
    ],
    "tgn:id":7533732,
    "tgn:name:en":"Kafr Ism\u0101'\u012bl",
    "tgn:placetype":[
        "aat:300008347"
    ]
},
  "bbox": [],
  "geometry": {"coordinates":[31.216735,30.640289],"type":"Point"}
}