{
  "id": 2315714,
  "type": "Feature",
  "properties": {
    "tgn:hierarchy":[
        "tgn:2315714",
        "tgn:1000001",
        "tgn:7012149",
        "tgn:2001923",
        "tgn:7007825",
        "tgn:7029392"
    ],
    "tgn:id":2315714,
    "tgn:name":"Ellison Hollow",
    "tgn:placetype":[
        "aat:300008761"
    ]
},
  "bbox": [],
  "geometry": {"coordinates":[-83.8667,36.35],"type":"Point"}
}