{
  "id": 7429451,
  "type": "Feature",
  "properties": {
    "tgn:hierarchy":[
        "tgn:7429451",
        "tgn:7005583",
        "tgn:1000001",
        "tgn:7005560",
        "tgn:7029392"
    ],
    "tgn:id":7429451,
    "tgn:name":"Metales",
    "tgn:placetype":[
        "aat:300008347"
    ]
},
  "bbox": [],
  "geometry": {"coordinates":[-104.216667,24.233333],"type":"Point"}
}