{
  "id": 1107074,
  "type": "Feature",
  "properties": {
    "tgn:hierarchy":[
        "tgn:1107074",
        "tgn:1000004",
        "tgn:7002087",
        "tgn:1000111",
        "tgn:7029392"
    ],
    "tgn:id":1107074,
    "tgn:name":"Zhuanping Shan",
    "tgn:placetype":[
        "aat:300008795"
    ]
},
  "bbox": [],
  "geometry": {"coordinates":[103.6167,29.1167],"type":"Point"}
}