{
  "id": 2003119,
  "type": "Feature",
  "properties": {
    "tgn:hierarchy":[
        "tgn:2003119",
        "tgn:7002659",
        "tgn:1000001",
        "tgn:7012149",
        "tgn:2000028",
        "tgn:7029392"
    ],
    "tgn:id":2003119,
    "tgn:name":"Cleveland",
    "tgn:placetype":[
        "aat:300008347"
    ]
},
  "bbox": [],
  "geometry": {"coordinates":[-87.6333,33.6833],"type":"Point"}
}