{
  "id": 1055790,
  "type": "Feature",
  "properties": {
    "tgn:hierarchy":[
        "tgn:1055790",
        "tgn:6001445",
        "tgn:1000004",
        "tgn:7018214",
        "tgn:7002435",
        "tgn:7029392"
    ],
    "tgn:id":1055790,
    "tgn:name":"Krasneno",
    "tgn:placetype":[
        "aat:300008347"
    ]
},
  "bbox": [],
  "geometry": {"coordinates":[174.3333,64.6167],"type":"Point"}
}