{
  "id": 2539676,
  "type": "Feature",
  "properties": {
    "tgn:hierarchy":[
        "tgn:2539676",
        "tgn:1000001",
        "tgn:7012149",
        "tgn:1002876",
        "tgn:7007710",
        "tgn:7029392"
    ],
    "tgn:id":2539676,
    "tgn:name":"New Silver Brook",
    "tgn:placetype":[
        "aat:300008347"
    ]
},
  "bbox": [],
  "geometry": {"coordinates":[-75.9667,40.8833],"type":"Point"}
}