{
  "id": 7268197,
  "type": "Feature",
  "properties": {
    "tgn:concordances":{
        "gn:id":"2750005"
    },
    "tgn:hierarchy":[
        "tgn:7268197",
        "tgn:7003614",
        "tgn:1000003",
        "tgn:7016845",
        "tgn:7029392"
    ],
    "tgn:id":7268197,
    "tgn:name:nl":"Nooit Gedacht",
    "tgn:placetype":[
        "aat:300008347"
    ]
},
  "bbox": [],
  "geometry": {"coordinates":[6.666667,52.966667],"type":"Point"}
}