{
  "id": 4009892,
  "type": "Feature",
  "properties": {
    "tgn:hierarchy":[
        "tgn:4009892",
        "tgn:7001158",
        "tgn:7002848",
        "tgn:1000003",
        "tgn:1000095",
        "tgn:7029392"
    ],
    "tgn:id":4009892,
    "tgn:name":"San Cebri\u00e1n de Mazote",
    "tgn:placetype":[
        "aat:300008347"
    ]
},
  "bbox": [],
  "geometry": {"coordinates":[-5.15,41.683333],"type":"Point"}
}