{
  "id": 2750657,
  "type": "Feature",
  "properties": {
    "tgn:hierarchy":[
        "tgn:2750657",
        "tgn:1000001",
        "tgn:7012149",
        "tgn:2001029",
        "tgn:7007521",
        "tgn:7029392"
    ],
    "tgn:id":2750657,
    "tgn:name":"Warburg Lake",
    "tgn:placetype":[
        "aat:300008680"
    ]
},
  "bbox": [],
  "geometry": {"coordinates":[-93.6833,47.25],"type":"Point"}
}