{
  "id": 7366998,
  "type": "Feature",
  "properties": {
    "tgn:hierarchy":[
        "tgn:7366998",
        "tgn:7005583",
        "tgn:1000001",
        "tgn:7005560",
        "tgn:7029392"
    ],
    "tgn:id":7366998,
    "tgn:name":"Estacas",
    "tgn:placetype":[
        "aat:300008347"
    ]
},
  "bbox": [],
  "geometry": {"coordinates":[-105.933333,25.133333],"type":"Point"}
}