{
  "id": 7364474,
  "type": "Feature",
  "properties": {
    "tgn:hierarchy":[
        "tgn:7364474",
        "tgn:1001853",
        "tgn:1000001",
        "tgn:7005560",
        "tgn:7029392"
    ],
    "tgn:id":7364474,
    "tgn:name":"Fern\u00e1ndez",
    "tgn:placetype":[
        "aat:300008347"
    ]
},
  "bbox": [],
  "geometry": {"coordinates":[-100.45,28.216667],"type":"Point"}
}