{
  "id": 2579398,
  "type": "Feature",
  "properties": {
    "tgn:hierarchy":[
        "tgn:2579398",
        "tgn:1000001",
        "tgn:2001017",
        "tgn:7012149",
        "tgn:7007521",
        "tgn:7029392"
    ],
    "tgn:id":2579398,
    "tgn:name":"Pickerel Lake",
    "tgn:placetype":[
        "aat:300008680"
    ]
},
  "bbox": [],
  "geometry": {"coordinates":[-93.1167,44.9167],"type":"Point"}
}