{
  "id": 2076219,
  "type": "Feature",
  "properties": {
    "tgn:hierarchy":[
        "tgn:2076219",
        "tgn:1000001",
        "tgn:7013557",
        "tgn:7012149",
        "tgn:7007709",
        "tgn:7029392"
    ],
    "tgn:id":2076219,
    "tgn:name":"Purley",
    "tgn:placetype":[
        "aat:300008347"
    ]
},
  "bbox": [],
  "geometry": {"coordinates":[-79.35,36.4667],"type":"Point"}
}