{
  "id": 7131663,
  "type": "Feature",
  "properties": {
    "tgn:hierarchy":[
        "tgn:7131663",
        "tgn:1000003",
        "tgn:7003678",
        "tgn:7000084",
        "tgn:7029392"
    ],
    "tgn:id":7131663,
    "tgn:name":"Mechtildshausen",
    "tgn:placetype":[
        "aat:300008347"
    ]
},
  "bbox": [],
  "geometry": {"coordinates":[8.324742,50.041754],"type":"Point"}
}