{
  "id": 2448065,
  "type": "Feature",
  "properties": {
    "tgn:hierarchy":[
        "tgn:2448065",
        "tgn:1000001",
        "tgn:7012149",
        "tgn:7007827",
        "tgn:7029392"
    ],
    "tgn:id":2448065,
    "tgn:name":"Lighthouse Canyon",
    "tgn:placetype":[
        "aat:300008761"
    ]
},
  "bbox": [],
  "geometry": {"coordinates":[-110.1667,39.4667],"type":"Point"}
}