<<<<<<< HEAD
{
  "id": 2254706,
  "type": "Feature",
  "properties": {
    "tgn:hierarchy":[
        "tgn:2254706",
        "tgn:1000001",
        "tgn:7012149",
        "tgn:2001714",
        "tgn:7007708",
        "tgn:7029392"
    ],
    "tgn:id":2254706,
    "tgn:name":"Coon Point",
    "tgn:placetype":[
        "aat:300008850"
    ]
},
  "bbox": [],
  "geometry": {"coordinates":[-122.0333,42.4167],"type":"Point"}
}
=======
{"geometry":{"type":"Point","coordinates":[-122.033300,42.416700]},"type":"Feature","properties":{"hierarchy":["tgn:2254706","tgn:1000001","tgn:7012149","tgn:2001714","tgn:7007708","tgn:7029392"],"placetype":["aat:300008850"],"id":2254706,"name:xx":"Coon Point"}}
>>>>>>> 03f74aca74312dbeaf24d7e61306dd6a786dc3d0
