{
  "id": 2388446,
  "type": "Feature",
  "properties": {
    "tgn:hierarchy":[
        "tgn:2388446",
        "tgn:1000001",
        "tgn:2001479",
        "tgn:7012149",
        "tgn:7007709",
        "tgn:7029392"
    ],
    "tgn:id":2388446,
    "tgn:name":"Hickory, Lake",
    "tgn:placetype":[
        "aat:300006191"
    ]
},
  "bbox": [],
  "geometry": {"coordinates":[-81.1833,35.7167],"type":"Point"}
}