{
  "id": 2669786,
  "type": "Feature",
  "properties": {
    "tgn:hierarchy":[
        "tgn:2669786",
        "tgn:1000001",
        "tgn:7012149",
        "tgn:2002035",
        "tgn:7007826",
        "tgn:7029392"
    ],
    "tgn:id":2669786,
    "tgn:name":"Sling Hollow",
    "tgn:placetype":[
        "aat:300008761"
    ]
},
  "bbox": [],
  "geometry": {"coordinates":[-98.5333,28.4167],"type":"Point"}
}