{
  "id": 2697147,
  "type": "Feature",
  "properties": {
    "tgn:hierarchy":[
        "tgn:2697147",
        "tgn:1000001",
        "tgn:7012149",
        "tgn:2000930",
        "tgn:7007515",
        "tgn:7029392"
    ],
    "tgn:id":2697147,
    "tgn:name":"Stony Brook Pond",
    "tgn:placetype":[
        "aat:300008680"
    ]
},
  "bbox": [],
  "geometry": {"coordinates":[-70.1833,45.35],"type":"Point"}
}