{
  "id": 7135882,
  "type": "Feature",
  "properties": {
    "tgn:hierarchy":[
        "tgn:7135882",
        "tgn:7000096",
        "tgn:1000003",
        "tgn:7000084",
        "tgn:7029392"
    ],
    "tgn:id":7135882,
    "tgn:name":"M\u00fchlenholz",
    "tgn:placetype":[
        "aat:300008863"
    ]
},
  "bbox": [],
  "geometry": {"coordinates":[11.95,52.983333],"type":"Point"}
}