{
  "id": 7011959,
  "type": "Feature",
  "properties": {
    "tgn:hierarchy":[
        "tgn:7011959",
        "tgn:7002445",
        "tgn:1000003",
        "tgn:7008175",
        "tgn:7008591",
        "tgn:7029392"
    ],
    "tgn:id":7011959,
    "tgn:name:en":"Blindley Heath",
    "tgn:placetype":[
        "aat:300008347"
    ]
},
  "bbox": [],
  "geometry": {"coordinates":[-0.05,51.183333],"type":"Point"}
}