<<<<<<< HEAD
{
  "id": 7489604,
  "type": "Feature",
  "properties": {
    "tgn:hierarchy":[
        "tgn:7489604",
        "tgn:1000004",
        "tgn:7489179",
        "tgn:1000141",
        "tgn:7029392"
    ],
    "tgn:id":7489604,
    "tgn:name":"Guoling",
    "tgn:placetype":[
        "aat:300008347"
    ]
},
  "bbox": [],
  "geometry": {"coordinates":[121.815278,24.766667],"type":"Point"}
}
=======
{"geometry":{"type":"Point","coordinates":[121.815278,24.766667]},"type":"Feature","properties":{"hierarchy":["tgn:7489604","tgn:1000004","tgn:7489179","tgn:1000141","tgn:7029392"],"placetype":["aat:300008347"],"id":7489604,"name:xx":"Guoling"}}
>>>>>>> 03f74aca74312dbeaf24d7e61306dd6a786dc3d0
