{
  "id": 7489604,
  "type": "Feature",
  "properties": {
    "tgn:hierarchy":[
        "tgn:7489604",
        "tgn:1000004",
        "tgn:7489179",
        "tgn:1000141",
        "tgn:7029392"
    ],
    "tgn:id":7489604,
    "tgn:name":"Guoling",
    "tgn:placetype":[
        "aat:300008347"
    ]
},
  "bbox": [],
  "geometry": {"coordinates":[121.815278,24.766667],"type":"Point"}
}