{
  "id": 7418611,
  "type": "Feature",
  "properties": {
    "tgn:hierarchy":[
        "tgn:7418611",
        "tgn:1001835",
        "tgn:1000001",
        "tgn:7005560",
        "tgn:7029392"
    ],
    "tgn:id":7418611,
    "tgn:name":"Miramontes",
    "tgn:placetype":[
        "aat:300008347"
    ]
},
  "bbox": [],
  "geometry": {"coordinates":[-116.549167,32.088333],"type":"Point"}
}