{
  "id": 2654507,
  "type": "Feature",
  "properties": {
    "tgn:hierarchy":[
        "tgn:2654507",
        "tgn:1000001",
        "tgn:7012149",
        "tgn:2001519",
        "tgn:7007709",
        "tgn:7029392"
    ],
    "tgn:id":2654507,
    "tgn:name":"Shafords Lake",
    "tgn:placetype":[
        "aat:300006191"
    ]
},
  "bbox": [],
  "geometry": {"coordinates":[-82.05,35.8667],"type":"Point"}
}