<<<<<<< HEAD
{
  "id": 2760817,
  "type": "Feature",
  "properties": {
    "tgn:hierarchy":[
        "tgn:2760817",
        "tgn:1000001",
        "tgn:7012149",
        "tgn:1002497",
        "tgn:7007706",
        "tgn:7029392"
    ],
    "tgn:id":2760817,
    "tgn:name":"West Hartland",
    "tgn:placetype":[
        "aat:300008347"
    ]
},
  "bbox": [],
  "geometry": {"coordinates":[-82.5333,41.2],"type":"Point"}
}
=======
{"geometry":{"type":"Point","coordinates":[-82.533300,41.200000]},"type":"Feature","properties":{"hierarchy":["tgn:2760817","tgn:1000001","tgn:7012149","tgn:1002497","tgn:7007706","tgn:7029392"],"placetype":["aat:300008347"],"id":2760817,"name:xx":"West Hartland"}}
>>>>>>> 03f74aca74312dbeaf24d7e61306dd6a786dc3d0
