{
  "id": 2518192,
  "type": "Feature",
  "properties": {
    "tgn:hierarchy":[
        "tgn:2518192",
        "tgn:1000001",
        "tgn:7012149",
        "tgn:7029392"
    ],
    "tgn:id":2518192,
    "tgn:name":"Missionary Ridge",
    "tgn:placetype":[
        "aat:300266640"
    ]
},
  "bbox": [],
  "geometry": {"coordinates":[-85.2667,34.9833],"type":"Point"}
}