{
  "id": 1079673,
  "type": "Feature",
  "properties": {
    "tgn:hierarchy":[
        "tgn:1079673",
        "tgn:7016579",
        "tgn:7000895",
        "tgn:1000004",
        "tgn:1000120",
        "tgn:7029392"
    ],
    "tgn:id":1079673,
    "tgn:name":"\u014cguchi",
    "tgn:placetype":[
        "aat:300008347"
    ]
},
  "bbox": [],
  "geometry": {"coordinates":[136.9167,35.3333],"type":"Point"}
}