{
  "id": 1140673,
  "type": "Feature",
  "properties": {
    "tgn:hierarchy":[
        "tgn:1140673",
        "tgn:1000004",
        "tgn:1001371",
        "tgn:7000299",
        "tgn:7029392"
    ],
    "tgn:id":1140673,
    "tgn:name":"K\u014fch'ang",
    "tgn:placetype":[
        "aat:300008347"
    ]
},
  "bbox": [],
  "geometry": {"coordinates":[127.9167,35.6833],"type":"Point"}
}