{
  "id": 7044370,
  "type": "Feature",
  "properties": {
    "tgn:hierarchy":[
        "tgn:7044370",
        "tgn:1003468",
        "tgn:1000003",
        "tgn:7010380",
        "tgn:1000080",
        "tgn:7029392"
    ],
    "tgn:id":7044370,
    "tgn:name":"Castrignano del Capo",
    "tgn:placetype":[
        "aat:300008347"
    ]
},
  "bbox": [],
  "geometry": {"coordinates":[18.333333,39.833333],"type":"Point"}
}