{
  "id": 7134418,
  "type": "Feature",
  "properties": {
    "tgn:hierarchy":[
        "tgn:7134418",
        "tgn:1000003",
        "tgn:7003676",
        "tgn:7000084",
        "tgn:7029392"
    ],
    "tgn:id":7134418,
    "tgn:name":"Mooraue",
    "tgn:placetype":[
        "aat:300008699"
    ]
},
  "bbox": [],
  "geometry": {"coordinates":[8.933333,53.666667],"type":"Point"}
}