{
  "id": 1016890,
  "type": "Feature",
  "properties": {
    "tgn:hierarchy":[
        "tgn:1016890",
        "tgn:7005557",
        "tgn:7018540",
        "tgn:1000001",
        "tgn:7005556",
        "tgn:7029392"
    ],
    "tgn:id":1016890,
    "tgn:name":"Savanna-la-Mar",
    "tgn:placetype":[
        "aat:300008347"
    ]
},
  "bbox": [],
  "geometry": {"coordinates":[-78.1333,18.218],"type":"Point"}
}