<<<<<<< HEAD
{
  "id": 2765404,
  "type": "Feature",
  "properties": {
    "tgn:hierarchy":[
        "tgn:2765404",
        "tgn:1000001",
        "tgn:7012149",
        "tgn:7014589",
        "tgn:7007515",
        "tgn:7029392"
    ],
    "tgn:id":2765404,
    "tgn:name":"White Birch Island",
    "tgn:placetype":[
        "aat:300008791"
    ]
},
  "bbox": [],
  "geometry": {"coordinates":[-67.8667,45.1],"type":"Point"}
}
=======
{"geometry":{"type":"Point","coordinates":[-67.866700,45.100000]},"type":"Feature","properties":{"hierarchy":["tgn:2765404","tgn:1000001","tgn:7012149","tgn:7014589","tgn:7007515","tgn:7029392"],"placetype":["aat:300008791"],"id":2765404,"name:xx":"White Birch Island"}}
>>>>>>> 03f74aca74312dbeaf24d7e61306dd6a786dc3d0
