{
  "id": 2570798,
  "type": "Feature",
  "properties": {
    "tgn:hierarchy":[
        "tgn:2570798",
        "tgn:1000001",
        "tgn:7012149",
        "tgn:1003005",
        "tgn:7007520",
        "tgn:7029392"
    ],
    "tgn:id":2570798,
    "tgn:name":"Patter Drain",
    "tgn:placetype":[
        "aat:300006075"
    ]
},
  "bbox": [],
  "geometry": {"coordinates":[-83.3833,42.3833],"type":"Point"}
}