{
  "id": 2731323,
  "type": "Feature",
  "properties": {
    "tgn:hierarchy":[
        "tgn:2731323",
        "tgn:1000001",
        "tgn:7012149",
        "tgn:2000183",
        "tgn:7007157",
        "tgn:7029392"
    ],
    "tgn:id":2731323,
    "tgn:name":"Tucki Wash",
    "tgn:placetype":[
        "aat:300008699"
    ]
},
  "bbox": [],
  "geometry": {"coordinates":[-117.1167,36.4833],"type":"Point"}
}