<<<<<<< HEAD
{
  "id": 7023491,
  "type": "Feature",
  "properties": {
    "tgn:hierarchy":[
        "tgn:7023491",
        "tgn:1000001",
        "tgn:7012149",
        "tgn:7007255",
        "tgn:7029392"
    ],
    "tgn:id":7023491,
    "tgn:name":"State Road Fork",
    "tgn:placetype":[
        "aat:300008699"
    ]
},
  "bbox": [],
  "geometry": {"coordinates":[-82.9833,37.7833],"type":"Point"}
}
=======
{"geometry":{"type":"Point","coordinates":[-82.983300,37.783300]},"type":"Feature","properties":{"hierarchy":["tgn:7023491","tgn:1000001","tgn:7012149","tgn:7007255","tgn:7029392"],"placetype":["aat:300008699"],"id":7023491,"name:xx":"State Road Fork"}}
>>>>>>> 03f74aca74312dbeaf24d7e61306dd6a786dc3d0
