{
  "id": 7023491,
  "type": "Feature",
  "properties": {
    "tgn:hierarchy":[
        "tgn:7023491",
        "tgn:1000001",
        "tgn:7012149",
        "tgn:7007255",
        "tgn:7029392"
    ],
    "tgn:id":7023491,
    "tgn:name":"State Road Fork",
    "tgn:placetype":[
        "aat:300008699"
    ]
},
  "bbox": [],
  "geometry": {"coordinates":[-82.9833,37.7833],"type":"Point"}
}