{
  "id": 2452216,
  "type": "Feature",
  "properties": {
    "tgn:hierarchy":[
        "tgn:2452216",
        "tgn:1000001",
        "tgn:7012149",
        "tgn:2000488",
        "tgn:7007250",
        "tgn:7029392"
    ],
    "tgn:id":2452216,
    "tgn:name":"Little Blue Creek Reservoir",
    "tgn:placetype":[
        "aat:300006191"
    ]
},
  "bbox": [],
  "geometry": {"coordinates":[-116.1167,42.2833],"type":"Point"}
}