{
  "id": 7304594,
  "type": "Feature",
  "properties": {
    "tgn:hierarchy":[
        "tgn:7304594",
        "tgn:7002758",
        "tgn:1001316",
        "tgn:1000003",
        "tgn:1000095",
        "tgn:7029392"
    ],
    "tgn:id":7304594,
    "tgn:name":"Lentisquillo, Loma del",
    "tgn:placetype":[
        "aat:300008777"
    ]
},
  "bbox": [],
  "geometry": {"coordinates":[-3.95,38.316667],"type":"Point"}
}