{
  "id": 2577379,
  "type": "Feature",
  "properties": {
    "tgn:hierarchy":[
        "tgn:2577379",
        "tgn:1000001",
        "tgn:7012149",
        "tgn:7007157",
        "tgn:7014516",
        "tgn:7029392"
    ],
    "tgn:id":2577379,
    "tgn:name":"Peters Springs",
    "tgn:placetype":[
        "aat:300008697"
    ]
},
  "bbox": [],
  "geometry": {"coordinates":[-122.6667,38.4333],"type":"Point"}
}