{
  "id": 2781147,
  "type": "Feature",
  "properties": {
    "tgn:hierarchy":[
        "tgn:2781147",
        "tgn:7006450",
        "tgn:1000001",
        "tgn:7012149",
        "tgn:2000089",
        "tgn:7029392"
    ],
    "tgn:id":2781147,
    "tgn:name":"Wooden Canoe Lake",
    "tgn:placetype":[
        "aat:300008680"
    ]
},
  "bbox": [],
  "geometry": {"coordinates":[-148.9667,64.85],"type":"Point"}
}