{
  "id": 7406794,
  "type": "Feature",
  "properties": {
    "tgn:hierarchy":[
        "tgn:7406794",
        "tgn:7005585",
        "tgn:1000001",
        "tgn:7005560",
        "tgn:7029392"
    ],
    "tgn:id":7406794,
    "tgn:name":"Zoyatitlapapa",
    "tgn:placetype":[
        "aat:300008347"
    ]
},
  "bbox": [],
  "geometry": {"coordinates":[-98.45,17.833333],"type":"Point"}
}