{
  "id": 2207852,
  "type": "Feature",
  "properties": {
    "tgn:hierarchy":[
        "tgn:2207852",
        "tgn:1000001",
        "tgn:7012149",
        "tgn:2002167",
        "tgn:7007919",
        "tgn:7029392"
    ],
    "tgn:id":2207852,
    "tgn:name":"Burgess Creek",
    "tgn:placetype":[
        "aat:300008706"
    ]
},
  "bbox": [],
  "geometry": {"coordinates":[-79.8333,36.5667],"type":"Point"}
}