{
  "id": 2033296,
  "type": "Feature",
  "properties": {
    "tgn:hierarchy":[
        "tgn:2033296",
        "tgn:1000001",
        "tgn:7012149",
        "tgn:1002487",
        "tgn:7007252",
        "tgn:7029392"
    ],
    "tgn:id":2033296,
    "tgn:name":"Phlox",
    "tgn:placetype":[
        "aat:300008347"
    ]
},
  "bbox": [],
  "geometry": {"coordinates":[-85.9167,40.4167],"type":"Point"}
}