{
  "id": 2604346,
  "type": "Feature",
  "properties": {
    "tgn:hierarchy":[
        "tgn:2604346",
        "tgn:1000001",
        "tgn:7012149",
        "tgn:2000226",
        "tgn:7007158",
        "tgn:7029392"
    ],
    "tgn:id":2604346,
    "tgn:name":"Rabbit Creek",
    "tgn:placetype":[
        "aat:300008706"
    ]
},
  "bbox": [],
  "geometry": {"coordinates":[-105.3333,40.8167],"type":"Point"}
}