{
  "id": 7582865,
  "type": "Feature",
  "properties": {
    "tgn:hierarchy":[
        "tgn:7582865",
        "tgn:1000004",
        "tgn:7000198",
        "tgn:7016722",
        "tgn:7029392"
    ],
    "tgn:id":7582865,
    "tgn:name:en":"Bangaw\u0101n",
    "tgn:placetype":[
        "aat:300008347"
    ]
},
  "bbox": [],
  "geometry": {"coordinates":[79.044078,27.980562],"type":"Point"}
}