{
  "id": 2399784,
  "type": "Feature",
  "properties": {
    "tgn:hierarchy":[
        "tgn:2399784",
        "tgn:1000001",
        "tgn:7012149",
        "tgn:2001116",
        "tgn:7007522",
        "tgn:7029392"
    ],
    "tgn:id":2399784,
    "tgn:name":"Horse Branch",
    "tgn:placetype":[
        "aat:300008699"
    ]
},
  "bbox": [],
  "geometry": {"coordinates":[-89.0333,31.8667],"type":"Point"}
}