{
  "id": 2577753,
  "type": "Feature",
  "properties": {
    "tgn:hierarchy":[
        "tgn:2577753",
        "tgn:1000001",
        "tgn:2002366",
        "tgn:7012149",
        "tgn:7007923",
        "tgn:7029392"
    ],
    "tgn:id":2577753,
    "tgn:name":"Petes Hole",
    "tgn:placetype":[
        "aat:300386845"
    ]
},
  "bbox": [],
  "geometry": {"coordinates":[-107.8833,44.7667],"type":"Point"}
}