<<<<<<< HEAD
{
  "id": 7026337,
  "type": "Feature",
  "properties": {
    "tgn:hierarchy":[
        "tgn:7026337",
        "tgn:1000003",
        "tgn:7011664",
        "tgn:7006660",
        "tgn:7029392"
    ],
    "tgn:id":7026337,
    "tgn:name":"Pomortsy",
    "tgn:placetype":[
        "aat:300008347"
    ]
},
  "bbox": [],
  "geometry": {"coordinates":[25.4333,48.9667],"type":"Point"}
}
=======
{"geometry":{"type":"Point","coordinates":[25.433300,48.966700]},"type":"Feature","properties":{"hierarchy":["tgn:7026337","tgn:1000003","tgn:7011664","tgn:7006660","tgn:7029392"],"placetype":["aat:300008347"],"id":7026337,"name:xx":"Pomortsy"}}
>>>>>>> 03f74aca74312dbeaf24d7e61306dd6a786dc3d0
