{
  "id": 2684002,
  "type": "Feature",
  "properties": {
    "tgn:hierarchy":[
        "tgn:2684002",
        "tgn:7002659",
        "tgn:1000001",
        "tgn:7012149",
        "tgn:2000041",
        "tgn:7029392"
    ],
    "tgn:id":2684002,
    "tgn:name":"Spencer Cave",
    "tgn:placetype":[
        "aat:300008746"
    ]
},
  "bbox": [],
  "geometry": {"coordinates":[-87.0333,34.9167],"type":"Point"}
}