{
  "id": 1002325,
  "type": "Feature",
  "properties": {
    "tgn:hierarchy":[
        "tgn:1002325",
        "tgn:1000001",
        "tgn:7012149",
        "tgn:7007252",
        "tgn:7029392"
    ],
    "tgn:id":1002325,
    "tgn:name":"Decatur",
    "tgn:placetype":[
        "aat:300387145",
        "aat:300000771"
    ]
},
  "bbox": [],
  "geometry": {"coordinates":[-85.4833,39.3333],"type":"Point"}
}