{
  "id": 7369038,
  "type": "Feature",
  "properties": {
    "tgn:hierarchy":[
        "tgn:7369038",
        "tgn:7005581",
        "tgn:1000001",
        "tgn:7005560",
        "tgn:7029392"
    ],
    "tgn:id":7369038,
    "tgn:name":"Guadalupe",
    "tgn:placetype":[
        "aat:300008347"
    ]
},
  "bbox": [],
  "geometry": {"coordinates":[-105.116667,27.65],"type":"Point"}
}