<<<<<<< HEAD
{
  "id": 2333934,
  "type": "Feature",
  "properties": {
    "tgn:hierarchy":[
        "tgn:2333934",
        "tgn:1000001",
        "tgn:7012149",
        "tgn:2001305",
        "tgn:7007524",
        "tgn:7029392"
    ],
    "tgn:id":2333934,
    "tgn:name":"Ford Creek",
    "tgn:placetype":[
        "aat:300008706"
    ]
},
  "bbox": [],
  "geometry": {"coordinates":[-104.6833,48.75],"type":"Point"}
}
=======
{"geometry":{"type":"Point","coordinates":[-104.683300,48.750000]},"type":"Feature","properties":{"hierarchy":["tgn:2333934","tgn:1000001","tgn:7012149","tgn:2001305","tgn:7007524","tgn:7029392"],"placetype":["aat:300008706"],"id":2333934,"name:xx":"Ford Creek"}}
>>>>>>> 03f74aca74312dbeaf24d7e61306dd6a786dc3d0
