{
  "id": 7567081,
  "type": "Feature",
  "properties": {
    "tgn:hierarchy":[
        "tgn:7567081",
        "tgn:1000004",
        "tgn:7000198",
        "tgn:7001797",
        "tgn:7029392"
    ],
    "tgn:id":7567081,
    "tgn:name:en":"Velachcheri",
    "tgn:placetype":[
        "aat:300000745"
    ]
},
  "bbox": [],
  "geometry": {"coordinates":[80.217778,12.979722],"type":"Point"}
}