{
  "id": 1084544,
  "type": "Feature",
  "properties": {
    "tgn:hierarchy":[
        "tgn:1084544",
        "tgn:1000004",
        "tgn:1001174",
        "tgn:1000135",
        "tgn:7029392"
    ],
    "tgn:id":1084544,
    "tgn:name":"Paracale",
    "tgn:placetype":[
        "aat:300008347"
    ]
},
  "bbox": [],
  "geometry": {"coordinates":[122.7667,14.25],"type":"Point"}
}