{
  "id": 2107717,
  "type": "Feature",
  "properties": {
    "tgn:hierarchy":[
        "tgn:2107717",
        "tgn:1000001",
        "tgn:7012149",
        "tgn:1002251",
        "tgn:7007826",
        "tgn:7029392"
    ],
    "tgn:id":2107717,
    "tgn:name":"Smith Point",
    "tgn:placetype":[
        "aat:300008347"
    ]
},
  "bbox": [],
  "geometry": {"coordinates":[-94.75,29.5333],"type":"Point"}
}