{
  "id": 2563310,
  "type": "Feature",
  "properties": {
    "tgn:hierarchy":[
        "tgn:2563310",
        "tgn:1000001",
        "tgn:7012149",
        "tgn:2000844",
        "tgn:7007255",
        "tgn:7029392"
    ],
    "tgn:id":2563310,
    "tgn:name":"Owl Creek",
    "tgn:placetype":[
        "aat:300008706"
    ]
},
  "bbox": [],
  "geometry": {"coordinates":[-85.3167,37.4167],"type":"Point"}
}