{
  "id": 2466652,
  "type": "Feature",
  "properties": {
    "tgn:hierarchy":[
        "tgn:2466652",
        "tgn:1000001",
        "tgn:7012149",
        "tgn:2001552",
        "tgn:7007709",
        "tgn:7029392"
    ],
    "tgn:id":2466652,
    "tgn:name":"Long Branch",
    "tgn:placetype":[
        "aat:300008699"
    ]
},
  "bbox": [],
  "geometry": {"coordinates":[-77.9167,35.4667],"type":"Point"}
}