{
  "id": 7581213,
  "type": "Feature",
  "properties": {
    "tgn:hierarchy":[
        "tgn:7581213",
        "tgn:1000004",
        "tgn:7000198",
        "tgn:7001797",
        "tgn:7029392"
    ],
    "tgn:id":7581213,
    "tgn:name:en":"Ved\u0101lai",
    "tgn:placetype":[
        "aat:300008347"
    ]
},
  "bbox": [],
  "geometry": {"coordinates":[79.116667,9.266667],"type":"Point"}
}