{
  "id": 2731244,
  "type": "Feature",
  "properties": {
    "tgn:hierarchy":[
        "tgn:2731244",
        "tgn:1000001",
        "tgn:7012149",
        "tgn:2000279",
        "tgn:7007240",
        "tgn:7029392"
    ],
    "tgn:id":2731244,
    "tgn:name":"Tucker Pond",
    "tgn:placetype":[
        "aat:300008680"
    ]
},
  "bbox": [],
  "geometry": {"coordinates":[-83.5333,30.5833],"type":"Point"}
}