{
  "id": 2280309,
  "type": "Feature",
  "properties": {
    "tgn:hierarchy":[
        "tgn:2280309",
        "tgn:7030516",
        "tgn:7006450",
        "tgn:1000001",
        "tgn:7012149",
        "tgn:7029392"
    ],
    "tgn:id":2280309,
    "tgn:name":"Deceit Point",
    "tgn:placetype":[
        "aat:300008850"
    ]
},
  "bbox": [],
  "geometry": {"coordinates":[-177.3167,51.6833],"type":"Point"}
}