{
  "id": 7294811,
  "type": "Feature",
  "properties": {
    "tgn:hierarchy":[
        "tgn:7294811",
        "tgn:7016598",
        "tgn:1000049",
        "tgn:1000002",
        "tgn:7029392"
    ],
    "tgn:id":7294811,
    "tgn:name":"Abra de Justo, Cerro",
    "tgn:placetype":[
        "aat:300008777"
    ]
},
  "bbox": [],
  "geometry": {"coordinates":[-68.716667,-21.833333],"type":"Point"}
}