{
  "id": 7377632,
  "type": "Feature",
  "properties": {
    "tgn:hierarchy":[
        "tgn:7377632",
        "tgn:1000001",
        "tgn:7005595",
        "tgn:7005560",
        "tgn:7029392"
    ],
    "tgn:id":7377632,
    "tgn:name":"Las Cabras",
    "tgn:placetype":[
        "aat:300008347"
    ]
},
  "bbox": [],
  "geometry": {"coordinates":[-105.966667,22.766667],"type":"Point"}
}