<<<<<<< HEAD
{
  "id": 7377632,
  "type": "Feature",
  "properties": {
    "tgn:hierarchy":[
        "tgn:7377632",
        "tgn:1000001",
        "tgn:7005595",
        "tgn:7005560",
        "tgn:7029392"
    ],
    "tgn:id":7377632,
    "tgn:name":"Las Cabras",
    "tgn:placetype":[
        "aat:300008347"
    ]
},
  "bbox": [],
  "geometry": {"coordinates":[-105.966667,22.766667],"type":"Point"}
}
=======
{"geometry":{"type":"Point","coordinates":[-105.966667,22.766667]},"type":"Feature","properties":{"hierarchy":["tgn:7377632","tgn:1000001","tgn:7005595","tgn:7005560","tgn:7029392"],"placetype":["aat:300008347"],"id":7377632,"name:xx":"Las Cabras"}}
>>>>>>> 03f74aca74312dbeaf24d7e61306dd6a786dc3d0
