{
  "id": 2038085,
  "type": "Feature",
  "properties": {
    "tgn:hierarchy":[
        "tgn:2038085",
        "tgn:1000001",
        "tgn:7012149",
        "tgn:2000805",
        "tgn:7007255",
        "tgn:7029392"
    ],
    "tgn:id":2038085,
    "tgn:name":"Carrie",
    "tgn:placetype":[
        "aat:300008347"
    ]
},
  "bbox": [],
  "geometry": {"coordinates":[-83.0167,37.3167],"type":"Point"}
}