{
  "id": 2590993,
  "type": "Feature",
  "properties": {
    "tgn:hierarchy":[
        "tgn:2590993",
        "tgn:1000001",
        "tgn:7012149",
        "tgn:2001722",
        "tgn:7007708",
        "tgn:7029392"
    ],
    "tgn:id":2590993,
    "tgn:name":"Poley-Allen Ditch",
    "tgn:placetype":[
        "aat:300006075"
    ]
},
  "bbox": [],
  "geometry": {"coordinates":[-117.4333,45.4833],"type":"Point"}
}