{
  "id": 2730820,
  "type": "Feature",
  "properties": {
    "tgn:hierarchy":[
        "tgn:2730820",
        "tgn:1000001",
        "tgn:7012149",
        "tgn:2002128",
        "tgn:7007827",
        "tgn:7029392"
    ],
    "tgn:id":2730820,
    "tgn:name":"Tub Ditch",
    "tgn:placetype":[
        "aat:300006075"
    ]
},
  "bbox": [],
  "geometry": {"coordinates":[-111.55,38.3167],"type":"Point"}
}