{
  "id": 2347197,
  "type": "Feature",
  "properties": {
    "tgn:hierarchy":[
        "tgn:2347197",
        "tgn:1000001",
        "tgn:2001473",
        "tgn:7012149",
        "tgn:7007709",
        "tgn:7029392"
    ],
    "tgn:id":2347197,
    "tgn:name":"Gentry Branch",
    "tgn:placetype":[
        "aat:300008699"
    ]
},
  "bbox": [],
  "geometry": {"coordinates":[-82.5167,35.75],"type":"Point"}
}