{
  "id": 2274673,
  "type": "Feature",
  "properties": {
    "tgn:hierarchy":[
        "tgn:2274673",
        "tgn:7006450",
        "tgn:1000001",
        "tgn:7012149",
        "tgn:7029392"
    ],
    "tgn:id":2274673,
    "tgn:name":"Dalzell Creek",
    "tgn:placetype":[
        "aat:300008706"
    ]
},
  "bbox": [],
  "geometry": {"coordinates":[-153.15,62.15],"type":"Point"}
}