{
  "id": 2371846,
  "type": "Feature",
  "properties": {
    "tgn:hierarchy":[
        "tgn:2371846",
        "tgn:2002365",
        "tgn:1000001",
        "tgn:7012149",
        "tgn:7007923",
        "tgn:7029392"
    ],
    "tgn:id":2371846,
    "tgn:name":"Haley And Hoge Ditch",
    "tgn:placetype":[
        "aat:300006075"
    ]
},
  "bbox": [],
  "geometry": {"coordinates":[-105.7833,41.15],"type":"Point"}
}