{
  "id": 7297629,
  "type": "Feature",
  "properties": {
    "tgn:hierarchy":[
        "tgn:7297629",
        "tgn:7008911",
        "tgn:1000003",
        "tgn:7002763",
        "tgn:1000095",
        "tgn:7029392"
    ],
    "tgn:id":7297629,
    "tgn:name":"Soto de Rey",
    "tgn:placetype":[
        "aat:300008347"
    ]
},
  "bbox": [],
  "geometry": {"coordinates":[-5.95,43.35],"type":"Point"}
}