<<<<<<< HEAD
{
  "id": 2400535,
  "type": "Feature",
  "properties": {
    "tgn:hierarchy":[
        "tgn:2400535",
        "tgn:1000001",
        "tgn:7012149",
        "tgn:2000488",
        "tgn:7007250",
        "tgn:7029392"
    ],
    "tgn:id":2400535,
    "tgn:name":"Horse Lake",
    "tgn:placetype":[
        "aat:300008680"
    ]
},
  "bbox": [],
  "geometry": {"coordinates":[-115.3,42.0667],"type":"Point"}
}
=======
{"geometry":{"type":"Point","coordinates":[-115.300000,42.066700]},"type":"Feature","properties":{"hierarchy":["tgn:2400535","tgn:1000001","tgn:7012149","tgn:2000488","tgn:7007250","tgn:7029392"],"placetype":["aat:300008680"],"id":2400535,"name:xx":"Horse Lake"}}
>>>>>>> 03f74aca74312dbeaf24d7e61306dd6a786dc3d0
