<<<<<<< HEAD
{
  "id": 7488214,
  "type": "Feature",
  "properties": {
    "tgn:hierarchy":[
        "tgn:7488214",
        "tgn:1000004",
        "tgn:7471332",
        "tgn:1000141",
        "tgn:7029392"
    ],
    "tgn:id":7488214,
    "tgn:name":"Nankengkou",
    "tgn:placetype":[
        "aat:300008347"
    ]
},
  "bbox": [],
  "geometry": {"coordinates":[121.009444,24.731944],"type":"Point"}
}
=======
{"geometry":{"type":"Point","coordinates":[121.009444,24.731944]},"type":"Feature","properties":{"hierarchy":["tgn:7488214","tgn:1000004","tgn:7471332","tgn:1000141","tgn:7029392"],"placetype":["aat:300008347"],"id":7488214,"name:xx":"Nankengkou"}}
>>>>>>> 03f74aca74312dbeaf24d7e61306dd6a786dc3d0
