{
  "id": 7254988,
  "type": "Feature",
  "properties": {
    "tgn:hierarchy":[
        "tgn:7254988",
        "tgn:7003460",
        "tgn:1000003",
        "tgn:1000063",
        "tgn:4012014",
        "tgn:7029392"
    ],
    "tgn:id":7254988,
    "tgn:name":"Viernay",
    "tgn:placetype":[
        "aat:300008347"
    ]
},
  "bbox": [],
  "geometry": {"coordinates":[5.489665,50.705198],"type":"Point"}
}