{
  "id": 2221854,
  "type": "Feature",
  "properties": {
    "tgn:hierarchy":[
        "tgn:2221854",
        "tgn:1000001",
        "tgn:7012149",
        "tgn:2001136",
        "tgn:7007522",
        "tgn:7029392"
    ],
    "tgn:id":2221854,
    "tgn:name":"Carlton Branch",
    "tgn:placetype":[
        "aat:300008699"
    ]
},
  "bbox": [],
  "geometry": {"coordinates":[-89.0667,32.45],"type":"Point"}
}