{
  "id": 2315492,
  "type": "Feature",
  "properties": {
    "tgn:hierarchy":[
        "tgn:2315492",
        "tgn:1000001",
        "tgn:7012149",
        "tgn:1002454",
        "tgn:7007826",
        "tgn:7029392"
    ],
    "tgn:id":2315492,
    "tgn:name":"Ellis Branch",
    "tgn:placetype":[
        "aat:300008699"
    ]
},
  "bbox": [],
  "geometry": {"coordinates":[-94.2333,30.3333],"type":"Point"}
}