<<<<<<< HEAD
{
  "id": 7050761,
  "type": "Feature",
  "properties": {
    "tgn:hierarchy":[
        "tgn:7050761",
        "tgn:1000003",
        "tgn:1001651",
        "tgn:7003122",
        "tgn:1000080",
        "tgn:7029392"
    ],
    "tgn:id":7050761,
    "tgn:name":"Casa Nicchiara",
    "tgn:placetype":[
        "aat:300008347"
    ]
},
  "bbox": [],
  "geometry": {"coordinates":[14.75,37.266667],"type":"Point"}
}
=======
{"geometry":{"type":"Point","coordinates":[14.750000,37.266667]},"type":"Feature","properties":{"hierarchy":["tgn:7050761","tgn:1000003","tgn:1001651","tgn:7003122","tgn:1000080","tgn:7029392"],"placetype":["aat:300008347"],"id":7050761,"name:xx":"Casa Nicchiara"}}
>>>>>>> 03f74aca74312dbeaf24d7e61306dd6a786dc3d0
