{
  "id": 7381436,
  "type": "Feature",
  "properties": {
    "tgn:hierarchy":[
        "tgn:7381436",
        "tgn:1000001",
        "tgn:7005597",
        "tgn:7005560",
        "tgn:7029392"
    ],
    "tgn:id":7381436,
    "tgn:name":"Los Mimbres",
    "tgn:placetype":[
        "aat:300008699"
    ]
},
  "bbox": [],
  "geometry": {"coordinates":[-99.483333,23.45],"type":"Point"}
}