{
  "id": 2088362,
  "type": "Feature",
  "properties": {
    "tgn:hierarchy":[
        "tgn:2088362",
        "tgn:1000001",
        "tgn:1002225",
        "tgn:7012149",
        "tgn:7007710",
        "tgn:7029392"
    ],
    "tgn:id":2088362,
    "tgn:name":"Fallentimber",
    "tgn:placetype":[
        "aat:300008347"
    ]
},
  "bbox": [],
  "geometry": {"coordinates":[-78.4833,40.6833],"type":"Point"}
}