{
  "id": 7007656,
  "type": "Feature",
  "properties": {
    "tgn:hierarchy":[
        "tgn:7007656",
        "tgn:1000003",
        "tgn:7024118",
        "tgn:7006366",
        "tgn:7029392"
    ],
    "tgn:id":7007656,
    "tgn:name":"Elbla\u031cg",
    "tgn:placetype":[
        "aat:300008347",
        "aat:300008389",
        "aat:300387223",
        "aat:300387302"
    ]
},
  "bbox": [],
  "geometry": {"coordinates":[19.4167,54.1667],"type":"Point"}
}