{
  "id": 7220251,
  "type": "Feature",
  "properties": {
    "tgn:hierarchy":[
        "tgn:7220251",
        "tgn:7002711",
        "tgn:7001338",
        "tgn:1000003",
        "tgn:1000074",
        "tgn:7029392"
    ],
    "tgn:id":7220251,
    "tgn:name":"Velon\u00e1des",
    "tgn:placetype":[
        "aat:300008347"
    ]
},
  "bbox": [],
  "geometry": {"coordinates":[19.708611,39.752778],"type":"Point"}
}