{
  "id": 7416713,
  "type": "Feature",
  "properties": {
    "tgn:hierarchy":[
        "tgn:7416713",
        "tgn:7005584",
        "tgn:1000001",
        "tgn:7005560",
        "tgn:7029392"
    ],
    "tgn:id":7416713,
    "tgn:name":"Las Presitas de G\u00f5mez",
    "tgn:placetype":[
        "aat:300008347"
    ]
},
  "bbox": [],
  "geometry": {"coordinates":[-101.770833,20.563889],"type":"Point"}
}