{
  "id": 7325172,
  "type": "Feature",
  "properties": {
    "tgn:hierarchy":[
        "tgn:7325172",
        "tgn:7002831",
        "tgn:1000003",
        "tgn:7002786",
        "tgn:1000095",
        "tgn:7029392"
    ],
    "tgn:id":7325172,
    "tgn:name":"Santa Eulalia",
    "tgn:placetype":[
        "aat:300008347"
    ]
},
  "bbox": [],
  "geometry": {"coordinates":[-7.05,42.366667],"type":"Point"}
}