{
  "id": 2610479,
  "type": "Feature",
  "properties": {
    "tgn:hierarchy":[
        "tgn:2610479",
        "tgn:1000001",
        "tgn:7012149",
        "tgn:7007157",
        "tgn:1002957",
        "tgn:7029392"
    ],
    "tgn:id":2610479,
    "tgn:name":"Red Canyon Lake",
    "tgn:placetype":[
        "aat:300008680"
    ]
},
  "bbox": [],
  "geometry": {"coordinates":[-119.75,38.1333],"type":"Point"}
}