{
  "id": 2671324,
  "type": "Feature",
  "properties": {
    "tgn:hierarchy":[
        "tgn:2671324",
        "tgn:1000001",
        "tgn:2000317",
        "tgn:7012149",
        "tgn:7007248",
        "tgn:7029392"
    ],
    "tgn:id":2671324,
    "tgn:name":"Smith Hill",
    "tgn:placetype":[
        "aat:300008798"
    ]
},
  "bbox": [],
  "geometry": {"coordinates":[-84.9333,32.3333],"type":"Point"}
}