{
  "id": 7235286,
  "type": "Feature",
  "properties": {
    "tgn:hierarchy":[
        "tgn:7235286",
        "tgn:7002690",
        "tgn:7012056",
        "tgn:1000003",
        "tgn:1000074",
        "tgn:7029392"
    ],
    "tgn:id":7235286,
    "tgn:name":"Flathi\u00e1kai",
    "tgn:placetype":[
        "aat:300008347"
    ]
},
  "bbox": [],
  "geometry": {"coordinates":[24.966667,35.016667],"type":"Point"}
}