{
  "id": 2006437,
  "type": "Feature",
  "properties": {
    "tgn:hierarchy":[
        "tgn:2006437",
        "tgn:7006450",
        "tgn:1000001",
        "tgn:7012149",
        "tgn:2000086",
        "tgn:7029392"
    ],
    "tgn:id":2006437,
    "tgn:name":"Tonsina",
    "tgn:placetype":[
        "aat:300008347"
    ]
},
  "bbox": [],
  "geometry": {"coordinates":[-145.1667,61.65],"type":"Point"}
}