{
  "id": 7016353,
  "type": "Feature",
  "properties": {
    "tgn:hierarchy":[
        "tgn:7016353",
        "tgn:1000001",
        "tgn:7012149",
        "tgn:2001866",
        "tgn:7007825",
        "tgn:7029392"
    ],
    "tgn:id":7016353,
    "tgn:name":"Fairview",
    "tgn:placetype":[
        "aat:300008347",
        "aat:300387210"
    ]
},
  "bbox": [],
  "geometry": {"coordinates":[-82.75,36.2167],"type":"Point"}
}