{
  "id": 7554049,
  "type": "Feature",
  "properties": {
    "tgn:hierarchy":[
        "tgn:7554049",
        "tgn:1000004",
        "tgn:1001842",
        "tgn:7000198",
        "tgn:7029392"
    ],
    "tgn:id":7554049,
    "tgn:name:en":"Niranjanpur",
    "tgn:placetype":[
        "aat:300008347"
    ]
},
  "bbox": [],
  "geometry": {"coordinates":[84.553577,25.170107],"type":"Point"}
}