{
  "id": 7536711,
  "type": "Feature",
  "properties": {
    "tgn:hierarchy":[
        "tgn:7536711",
        "tgn:7001242",
        "tgn:1001059",
        "tgn:7016833",
        "tgn:7029392"
    ],
    "tgn:id":7536711,
    "tgn:name":"Kafr 'Azz\u0101m",
    "tgn:placetype":[
        "aat:300008347"
    ]
},
  "bbox": [],
  "geometry": {"coordinates":[31.510679,30.834481],"type":"Point"}
}