<<<<<<< HEAD
{
  "id": 2251278,
  "type": "Feature",
  "properties": {
    "tgn:hierarchy":[
        "tgn:2251278",
        "tgn:1000001",
        "tgn:2001417",
        "tgn:7012149",
        "tgn:7007526",
        "tgn:7029392"
    ],
    "tgn:id":2251278,
    "tgn:name":"Combination Mining Company Mine",
    "tgn:placetype":[
        "aat:300000390"
    ]
},
  "bbox": [],
  "geometry": {"coordinates":[-118.35,38.2833],"type":"Point"}
}
=======
{"geometry":{"type":"Point","coordinates":[-118.350000,38.283300]},"type":"Feature","properties":{"hierarchy":["tgn:2251278","tgn:1000001","tgn:2001417","tgn:7012149","tgn:7007526","tgn:7029392"],"placetype":["aat:300000390"],"id":2251278,"name:xx":"Combination Mining Company Mine"}}
>>>>>>> 03f74aca74312dbeaf24d7e61306dd6a786dc3d0
