{
  "id": 2687465,
  "type": "Feature",
  "properties": {
    "tgn:hierarchy":[
        "tgn:2687465",
        "tgn:2002307",
        "tgn:1000001",
        "tgn:7012149",
        "tgn:7007922",
        "tgn:7029392"
    ],
    "tgn:id":2687465,
    "tgn:name":"Spring Lake",
    "tgn:placetype":[
        "aat:300008680"
    ]
},
  "bbox": [],
  "geometry": {"coordinates":[-92.0333,45.5667],"type":"Point"}
}