{
  "id": 7026236,
  "type": "Feature",
  "properties": {
    "tgn:hierarchy":[
        "tgn:7026236",
        "tgn:7002445",
        "tgn:1000003",
        "tgn:7011901",
        "tgn:7008591",
        "tgn:7029392"
    ],
    "tgn:id":7026236,
    "tgn:name":"Stantonbury",
    "tgn:placetype":[
        "aat:300008347"
    ]
},
  "bbox": [],
  "geometry": {"coordinates":[-0.7667,52.05],"type":"Point"}
}