<<<<<<< HEAD
{
  "id": 7356786,
  "type": "Feature",
  "properties": {
    "tgn:hierarchy":[
        "tgn:7356786",
        "tgn:7005580",
        "tgn:1000001",
        "tgn:7005560",
        "tgn:7029392"
    ],
    "tgn:id":7356786,
    "tgn:name":"Carrillo Puerto",
    "tgn:placetype":[
        "aat:300008347"
    ]
},
  "bbox": [],
  "geometry": {"coordinates":[-92.166667,15.016667],"type":"Point"}
}
=======
{"geometry":{"type":"Point","coordinates":[-92.166667,15.016667]},"type":"Feature","properties":{"hierarchy":["tgn:7356786","tgn:7005580","tgn:1000001","tgn:7005560","tgn:7029392"],"placetype":["aat:300008347"],"id":7356786,"name:xx":"Carrillo Puerto"}}
>>>>>>> 03f74aca74312dbeaf24d7e61306dd6a786dc3d0
