{
  "id": 7356786,
  "type": "Feature",
  "properties": {
    "tgn:hierarchy":[
        "tgn:7356786",
        "tgn:7005580",
        "tgn:1000001",
        "tgn:7005560",
        "tgn:7029392"
    ],
    "tgn:id":7356786,
    "tgn:name":"Carrillo Puerto",
    "tgn:placetype":[
        "aat:300008347"
    ]
},
  "bbox": [],
  "geometry": {"coordinates":[-92.166667,15.016667],"type":"Point"}
}