{
  "id": 1068102,
  "type": "Feature",
  "properties": {
    "tgn:hierarchy":[
        "tgn:1068102",
        "tgn:1000004",
        "tgn:7002087",
        "tgn:1000111",
        "tgn:7029392"
    ],
    "tgn:id":1068102,
    "tgn:name":"Fuji",
    "tgn:placetype":[
        "aat:300008347"
    ]
},
  "bbox": [],
  "geometry": {"coordinates":[105.3833,29.15],"type":"Point"}
}