{
  "id": 2252899,
  "type": "Feature",
  "properties": {
    "tgn:hierarchy":[
        "tgn:2252899",
        "tgn:1002716",
        "tgn:1000001",
        "tgn:7012149",
        "tgn:7007711",
        "tgn:7029392"
    ],
    "tgn:id":2252899,
    "tgn:name":"Conrad Cave",
    "tgn:placetype":[
        "aat:300008746"
    ]
},
  "bbox": [],
  "geometry": {"coordinates":[-71.2833,41.4667],"type":"Point"}
}