{
  "id": 7492623,
  "type": "Feature",
  "properties": {
    "tgn:hierarchy":[
        "tgn:7492623",
        "tgn:7001010",
        "tgn:1000004",
        "tgn:1000141",
        "tgn:7029392"
    ],
    "tgn:id":7492623,
    "tgn:name":"Bilin Shan",
    "tgn:placetype":[
        "aat:300008798"
    ]
},
  "bbox": [],
  "geometry": {"coordinates":[121.538091,24.280021],"type":"Point"}
}