<<<<<<< HEAD
{
  "id": 7374202,
  "type": "Feature",
  "properties": {
    "tgn:hierarchy":[
        "tgn:7374202",
        "tgn:1000001",
        "tgn:7005589",
        "tgn:7005560",
        "tgn:7029392"
    ],
    "tgn:id":7374202,
    "tgn:name":"Rancho Laguna",
    "tgn:placetype":[
        "aat:300000241"
    ]
},
  "bbox": [],
  "geometry": {"coordinates":[-99.833333,25.466667],"type":"Point"}
}
=======
{"geometry":{"type":"Point","coordinates":[-99.833333,25.466667]},"type":"Feature","properties":{"hierarchy":["tgn:7374202","tgn:1000001","tgn:7005589","tgn:7005560","tgn:7029392"],"placetype":["aat:300000241"],"id":7374202,"name:xx":"Rancho Laguna"}}
>>>>>>> 03f74aca74312dbeaf24d7e61306dd6a786dc3d0
