{
  "id": 2741337,
  "type": "Feature",
  "properties": {
    "tgn:hierarchy":[
        "tgn:2741337",
        "tgn:1000001",
        "tgn:7012149",
        "tgn:2001520",
        "tgn:7007709",
        "tgn:7029392"
    ],
    "tgn:id":2741337,
    "tgn:name":"Upper Wood Run",
    "tgn:placetype":[
        "aat:300008699"
    ]
},
  "bbox": [],
  "geometry": {"coordinates":[-80.0167,35.3167],"type":"Point"}
}