{
  "id": 2207537,
  "type": "Feature",
  "properties": {
    "tgn:hierarchy":[
        "tgn:2207537",
        "tgn:1000001",
        "tgn:2000592",
        "tgn:7012149",
        "tgn:7007253",
        "tgn:7029392"
    ],
    "tgn:id":2207537,
    "tgn:name":"Bur Oak Lake",
    "tgn:placetype":[
        "aat:300008680"
    ]
},
  "bbox": [],
  "geometry": {"coordinates":[-94.75,43.2833],"type":"Point"}
}