{
  "id": 2751308,
  "type": "Feature",
  "properties": {
    "tgn:hierarchy":[
        "tgn:2751308",
        "tgn:1000001",
        "tgn:7012149",
        "tgn:7007157",
        "tgn:2000189",
        "tgn:7029392"
    ],
    "tgn:id":2751308,
    "tgn:name":"Warm Spring",
    "tgn:placetype":[
        "aat:300008697"
    ]
},
  "bbox": [],
  "geometry": {"coordinates":[-122.2667,41.6833],"type":"Point"}
}