{
  "id": 7034904,
  "type": "Feature",
  "properties": {
    "tgn:hierarchy":[
        "tgn:7034904",
        "tgn:1003500",
        "tgn:1000003",
        "tgn:7010380",
        "tgn:1000080",
        "tgn:7029392"
    ],
    "tgn:id":7034904,
    "tgn:name":"Il Posto",
    "tgn:placetype":[
        "aat:300386846"
    ]
},
  "bbox": [],
  "geometry": {"coordinates":[17.169444,40.447778],"type":"Point"}
}