<<<<<<< HEAD
{
  "id": 7173152,
  "type": "Feature",
  "properties": {
    "tgn:hierarchy":[
        "tgn:7173152",
        "tgn:7003669",
        "tgn:1000003",
        "tgn:7000084",
        "tgn:7029392"
    ],
    "tgn:id":7173152,
    "tgn:name":"Greiters",
    "tgn:placetype":[
        "aat:300000206"
    ]
},
  "bbox": [],
  "geometry": {"coordinates":[10.2,47.766667],"type":"Point"}
}
=======
{"geometry":{"type":"Point","coordinates":[10.200000,47.766667]},"type":"Feature","properties":{"hierarchy":["tgn:7173152","tgn:7003669","tgn:1000003","tgn:7000084","tgn:7029392"],"placetype":["aat:300000206"],"id":7173152,"name:xx":"Greiters"}}
>>>>>>> 03f74aca74312dbeaf24d7e61306dd6a786dc3d0
