{
  "id": 7566110,
  "type": "Feature",
  "properties": {
    "tgn:hierarchy":[
        "tgn:7566110",
        "tgn:1000004",
        "tgn:7000198",
        "tgn:7016722",
        "tgn:7029392"
    ],
    "tgn:id":7566110,
    "tgn:name:en":"Kars\u0101n",
    "tgn:placetype":[
        "aat:300008347"
    ]
},
  "bbox": [],
  "geometry": {"coordinates":[79.428119,26.002252],"type":"Point"}
}