{
  "id": 2428772,
  "type": "Feature",
  "properties": {
    "tgn:hierarchy":[
        "tgn:2428772",
        "tgn:1000001",
        "tgn:7012149",
        "tgn:2001458",
        "tgn:7007566",
        "tgn:7029392"
    ],
    "tgn:id":2428772,
    "tgn:name":"Jumanes Knob",
    "tgn:placetype":[
        "aat:300008798"
    ]
},
  "bbox": [],
  "geometry": {"coordinates":[-106.0333,34.5167],"type":"Point"}
}