{
  "id": 2223095,
  "type": "Feature",
  "properties": {
    "tgn:hierarchy":[
        "tgn:2223095",
        "tgn:1000001",
        "tgn:7012149",
        "tgn:7007826",
        "tgn:7029392"
    ],
    "tgn:id":2223095,
    "tgn:name":"Carroll Creek",
    "tgn:placetype":[
        "aat:300008706"
    ]
},
  "bbox": [],
  "geometry": {"coordinates":[-95.4833,33.0667],"type":"Point"}
}