<<<<<<< HEAD
{
  "id": 2405768,
  "type": "Feature",
  "properties": {
    "tgn:hierarchy":[
        "tgn:2405768",
        "tgn:1000001",
        "tgn:7012149",
        "tgn:7007240",
        "tgn:7029392"
    ],
    "tgn:id":2405768,
    "tgn:name":"Hulett Branch",
    "tgn:placetype":[
        "aat:300008699"
    ]
},
  "bbox": [],
  "geometry": {"coordinates":[-81.2667,29.6],"type":"Point"}
}
=======
{"geometry":{"type":"Point","coordinates":[-81.266700,29.600000]},"type":"Feature","properties":{"hierarchy":["tgn:2405768","tgn:1000001","tgn:7012149","tgn:7007240","tgn:7029392"],"placetype":["aat:300008699"],"id":2405768,"name:xx":"Hulett Branch"}}
>>>>>>> 03f74aca74312dbeaf24d7e61306dd6a786dc3d0
