{
  "id": 1028878,
  "type": "Feature",
  "properties": {
    "tgn:hierarchy":[
        "tgn:1028878",
        "tgn:7002445",
        "tgn:1000003",
        "tgn:7019017",
        "tgn:7008591",
        "tgn:7029392"
    ],
    "tgn:id":1028878,
    "tgn:name:en":"Clevedon",
    "tgn:placetype":[
        "aat:300008347"
    ]
},
  "bbox": [],
  "geometry": {"coordinates":[-2.8525,51.435278],"type":"Point"}
}