{
  "id": 7567997,
  "type": "Feature",
  "properties": {
    "tgn:hierarchy":[
        "tgn:7567997",
        "tgn:1001828",
        "tgn:1000004",
        "tgn:7000198",
        "tgn:7029392"
    ],
    "tgn:id":7567997,
    "tgn:name:en":"Utarpalli",
    "tgn:placetype":[
        "aat:300008347"
    ]
},
  "bbox": [],
  "geometry": {"coordinates":[78.066667,17.548333],"type":"Point"}
}