{
  "id": 2299985,
  "type": "Feature",
  "properties": {
    "tgn:hierarchy":[
        "tgn:2299985",
        "tgn:1000001",
        "tgn:7012149",
        "tgn:1002581",
        "tgn:7007710",
        "tgn:7029392"
    ],
    "tgn:id":2299985,
    "tgn:name":"Duffy, Lake",
    "tgn:placetype":[
        "aat:300006191"
    ]
},
  "bbox": [],
  "geometry": {"coordinates":[-76.4833,40.2333],"type":"Point"}
}