{
  "id": 1025054,
  "type": "Feature",
  "properties": {
    "tgn:hierarchy":[
        "tgn:1025054",
        "tgn:1001963",
        "tgn:1000002",
        "tgn:1000059",
        "tgn:7029392"
    ],
    "tgn:id":1025054,
    "tgn:name":"Car\u00fapano",
    "tgn:placetype":[
        "aat:300008347",
        "aat:300008389",
        "aat:300387512",
        "aat:300120599"
    ]
},
  "bbox": [],
  "geometry": {"coordinates":[-63.2333,10.65],"type":"Point"}
}