<<<<<<< HEAD
{
  "id": 7118255,
  "type": "Feature",
  "properties": {
    "tgn:hierarchy":[
        "tgn:7118255",
        "tgn:7003692",
        "tgn:1000003",
        "tgn:7000084",
        "tgn:7029392"
    ],
    "tgn:id":7118255,
    "tgn:name":"Peterstal",
    "tgn:placetype":[
        "aat:300008347"
    ]
},
  "bbox": [],
  "geometry": {"coordinates":[8.7525,49.449167],"type":"Point"}
}
=======
{"geometry":{"type":"Point","coordinates":[8.752500,49.449167]},"type":"Feature","properties":{"hierarchy":["tgn:7118255","tgn:7003692","tgn:1000003","tgn:7000084","tgn:7029392"],"placetype":["aat:300008347"],"id":7118255,"name:xx":"Peterstal"}}
>>>>>>> 03f74aca74312dbeaf24d7e61306dd6a786dc3d0
