{
  "id": 2380586,
  "type": "Feature",
  "properties": {
    "tgn:hierarchy":[
        "tgn:2380586",
        "tgn:2000258",
        "tgn:1000001",
        "tgn:7012149",
        "tgn:7007240",
        "tgn:7029392"
    ],
    "tgn:id":2380586,
    "tgn:name":"Haven Point",
    "tgn:placetype":[
        "aat:300008850"
    ]
},
  "bbox": [],
  "geometry": {"coordinates":[-85.65,30.25],"type":"Point"}
}