{
  "id": 7482336,
  "type": "Feature",
  "properties": {
    "tgn:hierarchy":[
        "tgn:7482336",
        "tgn:1000004",
        "tgn:7490934",
        "tgn:1000141",
        "tgn:7029392"
    ],
    "tgn:id":7482336,
    "tgn:name":"Fuxing",
    "tgn:placetype":[
        "aat:300008347"
    ]
},
  "bbox": [],
  "geometry": {"coordinates":[120.535278,23.206667],"type":"Point"}
}