<<<<<<< HEAD
{
  "id": 7482336,
  "type": "Feature",
  "properties": {
    "tgn:hierarchy":[
        "tgn:7482336",
        "tgn:1000004",
        "tgn:7490934",
        "tgn:1000141",
        "tgn:7029392"
    ],
    "tgn:id":7482336,
    "tgn:name":"Fuxing",
    "tgn:placetype":[
        "aat:300008347"
    ]
},
  "bbox": [],
  "geometry": {"coordinates":[120.535278,23.206667],"type":"Point"}
}
=======
{"geometry":{"type":"Point","coordinates":[120.535278,23.206667]},"type":"Feature","properties":{"hierarchy":["tgn:7482336","tgn:1000004","tgn:7490934","tgn:1000141","tgn:7029392"],"placetype":["aat:300008347"],"id":7482336,"name:xx":"Fuxing"}}
>>>>>>> 03f74aca74312dbeaf24d7e61306dd6a786dc3d0
