{
  "id": 2351891,
  "type": "Feature",
  "properties": {
    "tgn:hierarchy":[
        "tgn:2351891",
        "tgn:1000001",
        "tgn:7012149",
        "tgn:1002950",
        "tgn:7007568",
        "tgn:7029392"
    ],
    "tgn:id":2351891,
    "tgn:name":"Glenwood Creek",
    "tgn:placetype":[
        "aat:300008706"
    ]
},
  "bbox": [],
  "geometry": {"coordinates":[-76.5833,42.4333],"type":"Point"}
}