{
  "id": 2317150,
  "type": "Feature",
  "properties": {
    "tgn:hierarchy":[
        "tgn:2317150",
        "tgn:2000766",
        "tgn:1000001",
        "tgn:7012149",
        "tgn:7007255",
        "tgn:7029392"
    ],
    "tgn:id":2317150,
    "tgn:name":"Emma Cook Hollow",
    "tgn:placetype":[
        "aat:300008761"
    ]
},
  "bbox": [],
  "geometry": {"coordinates":[-86.1333,36.65],"type":"Point"}
}