<<<<<<< HEAD
{
  "id": 2764857,
  "type": "Feature",
  "properties": {
    "tgn:hierarchy":[
        "tgn:2764857",
        "tgn:7006450",
        "tgn:1000001",
        "tgn:2124053",
        "tgn:7012149",
        "tgn:7029392"
    ],
    "tgn:id":2764857,
    "tgn:name":"Whiskey Lake",
    "tgn:placetype":[
        "aat:300008680"
    ]
},
  "bbox": [],
  "geometry": {"coordinates":[-151.4,61.9833],"type":"Point"}
}
=======
{"geometry":{"type":"Point","coordinates":[-151.400000,61.983300]},"type":"Feature","properties":{"hierarchy":["tgn:2764857","tgn:7006450","tgn:1000001","tgn:2124053","tgn:7012149","tgn:7029392"],"placetype":["aat:300008680"],"id":2764857,"name:xx":"Whiskey Lake"}}
>>>>>>> 03f74aca74312dbeaf24d7e61306dd6a786dc3d0
