{
  "id": 2237196,
  "type": "Feature",
  "properties": {
    "tgn:hierarchy":[
        "tgn:2237196",
        "tgn:1000001",
        "tgn:7012149",
        "tgn:2000545",
        "tgn:7007252",
        "tgn:7029392"
    ],
    "tgn:id":2237196,
    "tgn:name":"Chimney Pier Hills",
    "tgn:placetype":[
        "aat:300386831"
    ]
},
  "bbox": [],
  "geometry": {"coordinates":[-87.55,38.55],"type":"Point"}
}