{
  "id": 2382264,
  "type": "Feature",
  "properties": {
    "tgn:hierarchy":[
        "tgn:2382264",
        "tgn:1000001",
        "tgn:2000957",
        "tgn:7012149",
        "tgn:7007520",
        "tgn:7029392"
    ],
    "tgn:id":2382264,
    "tgn:name":"Hayon Creek",
    "tgn:placetype":[
        "aat:300008706"
    ]
},
  "bbox": [],
  "geometry": {"coordinates":[-85.0167,42.5167],"type":"Point"}
}