{
  "id": 2785591,
  "type": "Feature",
  "properties": {
    "tgn:hierarchy":[
        "tgn:2785591",
        "tgn:1000001",
        "tgn:7012149",
        "tgn:2001251",
        "tgn:7007523",
        "tgn:7029392"
    ],
    "tgn:id":2785591,
    "tgn:name":"Yocum Creek",
    "tgn:placetype":[
        "aat:300008706"
    ]
},
  "bbox": [],
  "geometry": {"coordinates":[-92.9833,36.5667],"type":"Point"}
}