{
  "id": 2483011,
  "type": "Feature",
  "properties": {
    "tgn:hierarchy":[
        "tgn:2483011",
        "tgn:1000001",
        "tgn:7012149",
        "tgn:2001311",
        "tgn:7007524",
        "tgn:7029392"
    ],
    "tgn:id":2483011,
    "tgn:name":"Larsens Reservoir",
    "tgn:placetype":[
        "aat:300006191"
    ]
},
  "bbox": [],
  "geometry": {"coordinates":[-107.5333,46.2667],"type":"Point"}
}