{
  "id": 7226774,
  "type": "Feature",
  "properties": {
    "tgn:hierarchy":[
        "tgn:7226774",
        "tgn:7011167",
        "tgn:7001338",
        "tgn:1000003",
        "tgn:1000074",
        "tgn:7029392"
    ],
    "tgn:id":7226774,
    "tgn:name":"M\u00f3dia, Nis\u00eddes",
    "tgn:placetype":[
        "aat:300008791"
    ]
},
  "bbox": [],
  "geometry": {"coordinates":[21.019722,38.426111],"type":"Point"}
}