{
  "id": 7501038,
  "type": "Feature",
  "properties": {
    "tgn:hierarchy":[
        "tgn:7501038",
        "tgn:7001004",
        "tgn:1000004",
        "tgn:1000141",
        "tgn:7029392"
    ],
    "tgn:id":7501038,
    "tgn:name":"Detian Tang",
    "tgn:placetype":[
        "aat:300007595"
    ]
},
  "bbox": [],
  "geometry": {"coordinates":[120.305556,22.764722],"type":"Point"}
}