{
  "id": 2109538,
  "type": "Feature",
  "properties": {
    "tgn:hierarchy":[
        "tgn:2109538",
        "tgn:1000001",
        "tgn:1002361",
        "tgn:7012149",
        "tgn:7007828",
        "tgn:7029392"
    ],
    "tgn:id":2109538,
    "tgn:name":"Concord",
    "tgn:placetype":[
        "aat:300008347"
    ]
},
  "bbox": [],
  "geometry": {"coordinates":[-71.8833,44.4167],"type":"Point"}
}