{
  "id": 2482055,
  "type": "Feature",
  "properties": {
    "tgn:hierarchy":[
        "tgn:2482055",
        "tgn:1000001",
        "tgn:7012149",
        "tgn:2001711",
        "tgn:7007708",
        "tgn:7029392"
    ],
    "tgn:id":2482055,
    "tgn:name":"Lane and Shephard Reservoirs",
    "tgn:placetype":[
        "aat:300006191"
    ]
},
  "bbox": [],
  "geometry": {"coordinates":[-122.8667,42.6167],"type":"Point"}
}