{
  "id": 7589206,
  "type": "Feature",
  "properties": {
    "tgn:hierarchy":[
        "tgn:7589206",
        "tgn:1000004",
        "tgn:7000198",
        "tgn:7000799",
        "tgn:7029392"
    ],
    "tgn:id":7589206,
    "tgn:name:en":"K\u0101nga",
    "tgn:placetype":[
        "aat:300008347"
    ]
},
  "bbox": [],
  "geometry": {"coordinates":[74.206478,33.462818],"type":"Point"}
}