{
  "id": 2204048,
  "type": "Feature",
  "properties": {
    "tgn:hierarchy":[
        "tgn:2204048",
        "tgn:1000001",
        "tgn:1002695",
        "tgn:7012149",
        "tgn:7007565",
        "tgn:7029392"
    ],
    "tgn:id":2204048,
    "tgn:name":"Budd Lake",
    "tgn:placetype":[
        "aat:300006191"
    ]
},
  "bbox": [],
  "geometry": {"coordinates":[-74.75,40.85],"type":"Point"}
}