{
  "id": 7324546,
  "type": "Feature",
  "properties": {
    "tgn:hierarchy":[
        "tgn:7324546",
        "tgn:7002760",
        "tgn:1000003",
        "tgn:1000095",
        "tgn:7029392"
    ],
    "tgn:id":7324546,
    "tgn:name":"San Pedro",
    "tgn:placetype":[
        "aat:300008347"
    ]
},
  "bbox": [],
  "geometry": {"coordinates":[-4.566667,43.183333],"type":"Point"}
}