{
  "id": 7468870,
  "type": "Feature",
  "properties": {
    "tgn:hierarchy":[
        "tgn:7468870",
        "tgn:7488858",
        "tgn:1000004",
        "tgn:1000141",
        "tgn:7029392"
    ],
    "tgn:id":7468870,
    "tgn:name":"Xincuo",
    "tgn:placetype":[
        "aat:300008347"
    ]
},
  "bbox": [],
  "geometry": {"coordinates":[120.659608,23.842957],"type":"Point"}
}