<<<<<<< HEAD
{
  "id": 7487002,
  "type": "Feature",
  "properties": {
    "tgn:hierarchy":[
        "tgn:7487002",
        "tgn:1000004",
        "tgn:7490934",
        "tgn:1000141",
        "tgn:7029392"
    ],
    "tgn:id":7487002,
    "tgn:name":"Kanzicuo",
    "tgn:placetype":[
        "aat:300000745"
    ]
},
  "bbox": [],
  "geometry": {"coordinates":[120.288333,22.961667],"type":"Point"}
}
=======
{"geometry":{"type":"Point","coordinates":[120.288333,22.961667]},"type":"Feature","properties":{"hierarchy":["tgn:7487002","tgn:1000004","tgn:7490934","tgn:1000141","tgn:7029392"],"placetype":["aat:300000745"],"id":7487002,"name:xx":"Kanzicuo"}}
>>>>>>> 03f74aca74312dbeaf24d7e61306dd6a786dc3d0
