{
  "id": 7318825,
  "type": "Feature",
  "properties": {
    "tgn:hierarchy":[
        "tgn:7318825",
        "tgn:1001623",
        "tgn:1000049",
        "tgn:1000002",
        "tgn:7029392"
    ],
    "tgn:id":7318825,
    "tgn:name":"Barrientos, Bah\u00eda",
    "tgn:placetype":[
        "aat:300132316"
    ]
},
  "bbox": [],
  "geometry": {"coordinates":[-75.583333,-46.766667],"type":"Point"}
}