{
  "id": 7588040,
  "type": "Feature",
  "properties": {
    "tgn:hierarchy":[
        "tgn:7588040",
        "tgn:1000004",
        "tgn:7000198",
        "tgn:1001997",
        "tgn:7029392"
    ],
    "tgn:id":7588040,
    "tgn:name:en":"Maibi Khunou",
    "tgn:placetype":[
        "aat:300008347"
    ]
},
  "bbox": [],
  "geometry": {"coordinates":[94.130321,24.493915],"type":"Point"}
}