{
  "id": 7244977,
  "type": "Feature",
  "properties": {
    "tgn:hierarchy":[
        "tgn:7244977",
        "tgn:7007877",
        "tgn:1000003",
        "tgn:1000063",
        "tgn:4012014",
        "tgn:7029392"
    ],
    "tgn:id":7244977,
    "tgn:name":"Aveau, Bois d'",
    "tgn:placetype":[
        "aat:300008863"
    ]
},
  "bbox": [],
  "geometry": {"coordinates":[4.033333,50.35],"type":"Point"}
}