{
  "id": 2529518,
  "type": "Feature",
  "properties": {
    "tgn:hierarchy":[
        "tgn:2529518",
        "tgn:1000001",
        "tgn:7012149",
        "tgn:1002927",
        "tgn:7007710",
        "tgn:7029392"
    ],
    "tgn:id":2529518,
    "tgn:name":"Mud Lake",
    "tgn:placetype":[
        "aat:300008680"
    ]
},
  "bbox": [],
  "geometry": {"coordinates":[-76.6833,41.3667],"type":"Point"}
}