{
  "id": 7254152,
  "type": "Feature",
  "properties": {
    "tgn:hierarchy":[
        "tgn:7254152",
        "tgn:7003456",
        "tgn:1000003",
        "tgn:1000063",
        "tgn:7018236",
        "tgn:7029392"
    ],
    "tgn:id":7254152,
    "tgn:name":"Kasteel van Schoten",
    "tgn:placetype":[
        "aat:300005567"
    ]
},
  "bbox": [],
  "geometry": {"coordinates":[4.483333,51.233333],"type":"Point"}
}