{
  "id": 2548572,
  "type": "Feature",
  "properties": {
    "tgn:hierarchy":[
        "tgn:2548572",
        "tgn:1000001",
        "tgn:7012149",
        "tgn:2001455",
        "tgn:7007566",
        "tgn:7029392"
    ],
    "tgn:id":2548572,
    "tgn:name":"North Monticello Point",
    "tgn:placetype":[
        "aat:300008850"
    ]
},
  "bbox": [],
  "geometry": {"coordinates":[-107.1667,33.3167],"type":"Point"}
}