{
  "id": 2555122,
  "type": "Feature",
  "properties": {
    "tgn:hierarchy":[
        "tgn:2555122",
        "tgn:1000001",
        "tgn:7012149",
        "tgn:2001524",
        "tgn:7007709",
        "tgn:7029392"
    ],
    "tgn:id":2555122,
    "tgn:name":"Ocean City Beach",
    "tgn:placetype":[
        "aat:300008347"
    ]
},
  "bbox": [],
  "geometry": {"coordinates":[-77.4833,34.45],"type":"Point"}
}