{
  "id": 2413282,
  "type": "Feature",
  "properties": {
    "tgn:hierarchy":[
        "tgn:2413282",
        "tgn:1000001",
        "tgn:7012149",
        "tgn:2000969",
        "tgn:7007520",
        "tgn:7029392"
    ],
    "tgn:id":2413282,
    "tgn:name":"Intermediate Lake",
    "tgn:placetype":[
        "aat:300008680"
    ]
},
  "bbox": [],
  "geometry": {"coordinates":[-88.7167,48.0167],"type":"Point"}
}