{
  "id": 7549289,
  "type": "Feature",
  "properties": {
    "tgn:hierarchy":[
        "tgn:7549289",
        "tgn:1000004",
        "tgn:7000198",
        "tgn:1001977",
        "tgn:7029392"
    ],
    "tgn:id":7549289,
    "tgn:name:en":"Chakchoka",
    "tgn:placetype":[
        "aat:300008347"
    ]
},
  "bbox": [],
  "geometry": {"coordinates":[89.809178,26.472365],"type":"Point"}
}