{
  "id": 2714915,
  "type": "Feature",
  "properties": {
    "tgn:hierarchy":[
        "tgn:2714915",
        "tgn:1000001",
        "tgn:7012149",
        "tgn:2002383",
        "tgn:7007923",
        "tgn:7029392"
    ],
    "tgn:id":2714915,
    "tgn:name":"Tenmile Reservoir Number 3",
    "tgn:placetype":[
        "aat:300006191"
    ]
},
  "bbox": [],
  "geometry": {"coordinates":[-108.6333,41.6667],"type":"Point"}
}