{
  "id": 7080984,
  "type": "Feature",
  "properties": {
    "tgn:hierarchy":[
        "tgn:7080984",
        "tgn:1000003",
        "tgn:7000094",
        "tgn:7000084",
        "tgn:7029392"
    ],
    "tgn:id":7080984,
    "tgn:name":"W\u00f6pkendorf",
    "tgn:placetype":[
        "aat:300008347"
    ]
},
  "bbox": [],
  "geometry": {"coordinates":[12.516667,54.116667],"type":"Point"}
}