{
  "id": 2362540,
  "type": "Feature",
  "properties": {
    "tgn:hierarchy":[
        "tgn:2362540",
        "tgn:1000001",
        "tgn:7016172",
        "tgn:7012149",
        "tgn:2000149",
        "tgn:7029392"
    ],
    "tgn:id":2362540,
    "tgn:name":"Greasy Shoal",
    "tgn:placetype":[
        "aat:300132348"
    ]
},
  "bbox": [],
  "geometry": {"coordinates":[-92.4167,36.0833],"type":"Point"}
}