{
  "id": 7186383,
  "type": "Feature",
  "properties": {
    "tgn:hierarchy":[
        "tgn:7186383",
        "tgn:7003669",
        "tgn:1000003",
        "tgn:7000084",
        "tgn:7029392"
    ],
    "tgn:id":7186383,
    "tgn:name":"Gerholz",
    "tgn:placetype":[
        "aat:300008347"
    ]
},
  "bbox": [],
  "geometry": {"coordinates":[10.15,47.633333],"type":"Point"}
}