{
  "id": 2495258,
  "type": "Feature",
  "properties": {
    "tgn:hierarchy":[
        "tgn:2495258",
        "tgn:1000001",
        "tgn:7012149",
        "tgn:2001883",
        "tgn:7007825",
        "tgn:7029392"
    ],
    "tgn:id":2495258,
    "tgn:name":"Mary Hill",
    "tgn:placetype":[
        "aat:300008798"
    ]
},
  "bbox": [],
  "geometry": {"coordinates":[-83.7667,35.9833],"type":"Point"}
}