{
  "id": 7571058,
  "type": "Feature",
  "properties": {
    "tgn:hierarchy":[
        "tgn:7571058",
        "tgn:1000004",
        "tgn:7000198",
        "tgn:7000799",
        "tgn:7029392"
    ],
    "tgn:id":7571058,
    "tgn:name:en":"Kallar",
    "tgn:placetype":[
        "aat:300008347"
    ]
},
  "bbox": [],
  "geometry": {"coordinates":[74.30417,33.294043],"type":"Point"}
}