{
  "id": 2236917,
  "type": "Feature",
  "properties": {
    "tgn:hierarchy":[
        "tgn:2236917",
        "tgn:1000001",
        "tgn:7012149",
        "tgn:7007825",
        "tgn:7029392"
    ],
    "tgn:id":2236917,
    "tgn:name":"Chilhowee Shoals",
    "tgn:placetype":[
        "aat:300132348"
    ]
},
  "bbox": [],
  "geometry": {"coordinates":[-84.0667,35.5333],"type":"Point"}
}