{
  "id": 2218298,
  "type": "Feature",
  "properties": {
    "tgn:hierarchy":[
        "tgn:2218298",
        "tgn:1002247",
        "tgn:1000001",
        "tgn:7012149",
        "tgn:7007516",
        "tgn:7029392"
    ],
    "tgn:id":2218298,
    "tgn:name":"Canal View Estates",
    "tgn:placetype":[
        "aat:300008347"
    ]
},
  "bbox": [],
  "geometry": {"coordinates":[-75.7833,39.5333],"type":"Point"}
}