{
  "id": 2451274,
  "type": "Feature",
  "properties": {
    "tgn:hierarchy":[
        "tgn:2451274",
        "tgn:1000001",
        "tgn:7012149",
        "tgn:7007157",
        "tgn:2000186",
        "tgn:7029392"
    ],
    "tgn:id":2451274,
    "tgn:name":"Little Baldy",
    "tgn:placetype":[
        "aat:300008798"
    ]
},
  "bbox": [],
  "geometry": {"coordinates":[-120.2667,41.6333],"type":"Point"}
}