{
  "id": 7495753,
  "type": "Feature",
  "properties": {
    "tgn:hierarchy":[
        "tgn:7495753",
        "tgn:7488858",
        "tgn:1000004",
        "tgn:1000141",
        "tgn:7029392"
    ],
    "tgn:id":7495753,
    "tgn:name":"Beishizi",
    "tgn:placetype":[
        "aat:300008347"
    ]
},
  "bbox": [],
  "geometry": {"coordinates":[120.738844,23.815782],"type":"Point"}
}