{
  "id": 1065197,
  "type": "Feature",
  "properties": {
    "tgn:hierarchy":[
        "tgn:1065197",
        "tgn:1000003",
        "tgn:7006669",
        "tgn:7029392"
    ],
    "tgn:id":1065197,
    "tgn:name":"Pre\u0161evo",
    "tgn:placetype":[
        "aat:300008347"
    ]
},
  "bbox": [],
  "geometry": {"coordinates":[21.6167,42.2667],"type":"Point"}
}