{
  "id": 7177907,
  "type": "Feature",
  "properties": {
    "tgn:hierarchy":[
        "tgn:7177907",
        "tgn:7003669",
        "tgn:1000003",
        "tgn:7000084",
        "tgn:7029392"
    ],
    "tgn:id":7177907,
    "tgn:name":"Guntendorf",
    "tgn:placetype":[
        "aat:300387200"
    ]
},
  "bbox": [],
  "geometry": {"coordinates":[12.483333,48.533333],"type":"Point"}
}