{
  "id": 2498371,
  "type": "Feature",
  "properties": {
    "tgn:hierarchy":[
        "tgn:2498371",
        "tgn:1000001",
        "tgn:7012149",
        "tgn:7007158",
        "tgn:7029392"
    ],
    "tgn:id":2498371,
    "tgn:name":"Mc Kay Fork",
    "tgn:placetype":[
        "aat:300008699"
    ]
},
  "bbox": [],
  "geometry": {"coordinates":[-108.5667,39.3667],"type":"Point"}
}