{
  "id": 7586924,
  "type": "Feature",
  "properties": {
    "tgn:hierarchy":[
        "tgn:7586924",
        "tgn:1000004",
        "tgn:7000198",
        "tgn:7000799",
        "tgn:7029392"
    ],
    "tgn:id":7586924,
    "tgn:name:en":"Ankol",
    "tgn:placetype":[
        "aat:300008347"
    ]
},
  "bbox": [],
  "geometry": {"coordinates":[74.633171,34.205733],"type":"Point"}
}