{
  "id": 2698287,
  "type": "Feature",
  "properties": {
    "tgn:hierarchy":[
        "tgn:2698287",
        "tgn:1000001",
        "tgn:1002934",
        "tgn:7012149",
        "tgn:7007565",
        "tgn:7029392"
    ],
    "tgn:id":2698287,
    "tgn:name":"Straders Pond",
    "tgn:placetype":[
        "aat:300008680"
    ]
},
  "bbox": [],
  "geometry": {"coordinates":[-74.6833,41.0333],"type":"Point"}
}