{
  "id": 2122402,
  "type": "Feature",
  "properties": {
    "tgn:hierarchy":[
        "tgn:2122402",
        "tgn:1000001",
        "tgn:7012149",
        "tgn:1002522",
        "tgn:7007922",
        "tgn:7029392"
    ],
    "tgn:id":2122402,
    "tgn:name":"Slabtown",
    "tgn:placetype":[
        "aat:300008347",
        "aat:300387210"
    ]
},
  "bbox": [],
  "geometry": {"coordinates":[-88.6333,42.9667],"type":"Point"}
}