<<<<<<< HEAD
{
  "id": 7374462,
  "type": "Feature",
  "properties": {
    "tgn:hierarchy":[
        "tgn:7374462",
        "tgn:1000001",
        "tgn:7005589",
        "tgn:7005560",
        "tgn:7029392"
    ],
    "tgn:id":7374462,
    "tgn:name":"Laguna Seca",
    "tgn:placetype":[
        "aat:300008347"
    ]
},
  "bbox": [],
  "geometry": {"coordinates":[-99.916667,25.483333],"type":"Point"}
}
=======
{"geometry":{"type":"Point","coordinates":[-99.916667,25.483333]},"type":"Feature","properties":{"hierarchy":["tgn:7374462","tgn:1000001","tgn:7005589","tgn:7005560","tgn:7029392"],"placetype":["aat:300008347"],"id":7374462,"name:xx":"Laguna Seca"}}
>>>>>>> 03f74aca74312dbeaf24d7e61306dd6a786dc3d0
