{
  "id": 2571643,
  "type": "Feature",
  "properties": {
    "tgn:hierarchy":[
        "tgn:2571643",
        "tgn:1000001",
        "tgn:7012149",
        "tgn:2000886",
        "tgn:7007256",
        "tgn:7029392"
    ],
    "tgn:id":2571643,
    "tgn:name":"Paw Paw Island",
    "tgn:placetype":[
        "aat:300008791"
    ]
},
  "bbox": [],
  "geometry": {"coordinates":[-90.9833,32.4333],"type":"Point"}
}