{
  "id": 7564118,
  "type": "Feature",
  "properties": {
    "tgn:hierarchy":[
        "tgn:7564118",
        "tgn:1000004",
        "tgn:7000198",
        "tgn:1001894",
        "tgn:7029392"
    ],
    "tgn:id":7564118,
    "tgn:name:en":"Panautha Protected Forest",
    "tgn:placetype":[
        "aat:300008865"
    ]
},
  "bbox": [],
  "geometry": {"coordinates":[79.4502,24.8882],"type":"Point"}
}