<<<<<<< HEAD
{
  "id": 7023603,
  "type": "Feature",
  "properties": {
    "tgn:hierarchy":[
        "tgn:7023603",
        "tgn:1000001",
        "tgn:7012149",
        "tgn:7029392"
    ],
    "tgn:id":7023603,
    "tgn:name":"OE Spring",
    "tgn:placetype":[
        "aat:300008697"
    ]
},
  "bbox": [],
  "geometry": {"coordinates":[-111.0333,42.8333],"type":"Point"}
}
=======
{"geometry":{"type":"Point","coordinates":[-111.033300,42.833300]},"type":"Feature","properties":{"hierarchy":["tgn:7023603","tgn:1000001","tgn:7012149","tgn:7029392"],"placetype":["aat:300008697"],"id":7023603,"name:xx":"OE Spring"}}
>>>>>>> 03f74aca74312dbeaf24d7e61306dd6a786dc3d0
