<<<<<<< HEAD
{
  "id": 7174391,
  "type": "Feature",
  "properties": {
    "tgn:hierarchy":[
        "tgn:7174391",
        "tgn:7003669",
        "tgn:1000003",
        "tgn:7000084",
        "tgn:7029392"
    ],
    "tgn:id":7174391,
    "tgn:name":"Gronetseck",
    "tgn:placetype":[
        "aat:300008795"
    ]
},
  "bbox": [],
  "geometry": {"coordinates":[11.65,47.716667],"type":"Point"}
}
=======
{"geometry":{"type":"Point","coordinates":[11.650000,47.716667]},"type":"Feature","properties":{"hierarchy":["tgn:7174391","tgn:7003669","tgn:1000003","tgn:7000084","tgn:7029392"],"placetype":["aat:300008795"],"id":7174391,"name:xx":"Gronetseck"}}
>>>>>>> 03f74aca74312dbeaf24d7e61306dd6a786dc3d0
