{
  "id": 2235859,
  "type": "Feature",
  "properties": {
    "tgn:hierarchy":[
        "tgn:2235859",
        "tgn:1000001",
        "tgn:7012149",
        "tgn:2002276",
        "tgn:7013961",
        "tgn:7029392"
    ],
    "tgn:id":2235859,
    "tgn:name":"Chestnut Ridge",
    "tgn:placetype":[
        "aat:300266640"
    ]
},
  "bbox": [],
  "geometry": {"coordinates":[-80.55,39.9167],"type":"Point"}
}