{
  "id": 7232846,
  "type": "Feature",
  "properties": {
    "tgn:hierarchy":[
        "tgn:7232846",
        "tgn:7002739",
        "tgn:7017076",
        "tgn:1000003",
        "tgn:1000074",
        "tgn:7029392"
    ],
    "tgn:id":7232846,
    "tgn:name":"\u00cdria",
    "tgn:placetype":[
        "aat:300008347"
    ]
},
  "bbox": [],
  "geometry": {"coordinates":[23.018647,37.485156],"type":"Point"}
}