{
  "id": 1137141,
  "type": "Feature",
  "properties": {
    "tgn:hierarchy":[
        "tgn:1137141",
        "tgn:1000004",
        "tgn:7011457",
        "tgn:7014786",
        "tgn:7029392"
    ],
    "tgn:id":1137141,
    "tgn:name":"Aksu",
    "tgn:placetype":[
        "aat:300008347"
    ]
},
  "bbox": [],
  "geometry": {"coordinates":[53.1833,50.8833],"type":"Point"}
}