{
  "id": 7494028,
  "type": "Feature",
  "properties": {
    "tgn:hierarchy":[
        "tgn:7494028",
        "tgn:1000004",
        "tgn:7491221",
        "tgn:1000141",
        "tgn:7029392"
    ],
    "tgn:id":7494028,
    "tgn:name":"Qilin Shan",
    "tgn:placetype":[
        "aat:300008798"
    ]
},
  "bbox": [],
  "geometry": {"coordinates":[121.321644,23.117791],"type":"Point"}
}