{
  "id": 2633644,
  "type": "Feature",
  "properties": {
    "tgn:hierarchy":[
        "tgn:2633644",
        "tgn:1000001",
        "tgn:7012149",
        "tgn:2002299",
        "tgn:7013961",
        "tgn:7029392"
    ],
    "tgn:id":2633644,
    "tgn:name":"Rush Branch",
    "tgn:placetype":[
        "aat:300008699"
    ]
},
  "bbox": [],
  "geometry": {"coordinates":[-82.4833,38.1167],"type":"Point"}
}