<<<<<<< HEAD
{
  "id": 2768611,
  "type": "Feature",
  "properties": {
    "tgn:hierarchy":[
        "tgn:2768611",
        "tgn:1000001",
        "tgn:7012149",
        "tgn:1002667",
        "tgn:7007919",
        "tgn:7029392"
    ],
    "tgn:id":2768611,
    "tgn:name":"Whiting Creek",
    "tgn:placetype":[
        "aat:300008706"
    ]
},
  "bbox": [],
  "geometry": {"coordinates":[-76.4833,37.5833],"type":"Point"}
}
=======
{"geometry":{"type":"Point","coordinates":[-76.483300,37.583300]},"type":"Feature","properties":{"hierarchy":["tgn:2768611","tgn:1000001","tgn:7012149","tgn:1002667","tgn:7007919","tgn:7029392"],"placetype":["aat:300008706"],"id":2768611,"name:xx":"Whiting Creek"}}
>>>>>>> 03f74aca74312dbeaf24d7e61306dd6a786dc3d0
