{
  "id": 7499636,
  "type": "Feature",
  "properties": {
    "tgn:hierarchy":[
        "tgn:7499636",
        "tgn:1000004",
        "tgn:7492971",
        "tgn:1000141",
        "tgn:7029392"
    ],
    "tgn:id":7499636,
    "tgn:name":"Datong Guoxiao",
    "tgn:placetype":[
        "aat:300006495"
    ]
},
  "bbox": [],
  "geometry": {"coordinates":[120.4766,22.6662],"type":"Point"}
}