{
  "id": 7129785,
  "type": "Feature",
  "properties": {
    "tgn:hierarchy":[
        "tgn:7129785",
        "tgn:7003692",
        "tgn:1000003",
        "tgn:7000084",
        "tgn:7029392"
    ],
    "tgn:id":7129785,
    "tgn:name":"Michelshof",
    "tgn:placetype":[
        "aat:300000206"
    ]
},
  "bbox": [],
  "geometry": {"coordinates":[9.533333,48.033333],"type":"Point"}
}