<<<<<<< HEAD
{
  "id": 2158571,
  "type": "Feature",
  "properties": {
    "tgn:hierarchy":[
        "tgn:2158571",
        "tgn:1000001",
        "tgn:7012149",
        "tgn:1003048",
        "tgn:7007919",
        "tgn:7029392"
    ],
    "tgn:id":2158571,
    "tgn:name":"Beaverdam Pond",
    "tgn:placetype":[
        "aat:300006191"
    ]
},
  "bbox": [],
  "geometry": {"coordinates":[-76.6333,37.3167],"type":"Point"}
}
=======
{"geometry":{"type":"Point","coordinates":[-76.633300,37.316700]},"type":"Feature","properties":{"hierarchy":["tgn:2158571","tgn:1000001","tgn:7012149","tgn:1003048","tgn:7007919","tgn:7029392"],"placetype":["aat:300006191"],"id":2158571,"name:xx":"Beaverdam Pond"}}
>>>>>>> 03f74aca74312dbeaf24d7e61306dd6a786dc3d0
