{
  "id": 7317081,
  "type": "Feature",
  "properties": {
    "tgn:hierarchy":[
        "tgn:7317081",
        "tgn:1001699",
        "tgn:1000049",
        "tgn:1000002",
        "tgn:7029392"
    ],
    "tgn:id":7317081,
    "tgn:name":"Chipana, Isla",
    "tgn:placetype":[
        "aat:300008791"
    ]
},
  "bbox": [],
  "geometry": {"coordinates":[-73.759722,-44.208889],"type":"Point"}
}