{
  "id": 7558059,
  "type": "Feature",
  "properties": {
    "tgn:hierarchy":[
        "tgn:7558059",
        "tgn:1001828",
        "tgn:1000004",
        "tgn:7000198",
        "tgn:7029392"
    ],
    "tgn:id":7558059,
    "tgn:name:en":"Pudi, Point",
    "tgn:placetype":[
        "aat:300386846"
    ]
},
  "bbox": [],
  "geometry": {"coordinates":[80.25,13.783333],"type":"Point"}
}