{
  "id": 2544108,
  "type": "Feature",
  "properties": {
    "tgn:hierarchy":[
        "tgn:2544108",
        "tgn:1000001",
        "tgn:7012149",
        "tgn:2001199",
        "tgn:7007523",
        "tgn:7029392"
    ],
    "tgn:id":2544108,
    "tgn:name":"North Branch Jordan Creek",
    "tgn:placetype":[
        "aat:300008706"
    ]
},
  "bbox": [],
  "geometry": {"coordinates":[-93.25,37.2167],"type":"Point"}
}