{
  "id": 7593281,
  "type": "Feature",
  "properties": {
    "tgn:hierarchy":[
        "tgn:7593281",
        "tgn:1001277",
        "tgn:7002560",
        "tgn:1000051",
        "tgn:1000002",
        "tgn:7029392"
    ],
    "tgn:id":7593281,
    "tgn:name":"Balao Chico",
    "tgn:placetype":[
        "aat:300008347"
    ]
},
  "bbox": [],
  "geometry": {"coordinates":[-77.74,-2.754],"type":"Point"}
}