{
  "id": 7306605,
  "type": "Feature",
  "properties": {
    "tgn:hierarchy":[
        "tgn:7306605",
        "tgn:7008911",
        "tgn:1000003",
        "tgn:7002763",
        "tgn:1000095",
        "tgn:7029392"
    ],
    "tgn:id":7306605,
    "tgn:name":"Lomes",
    "tgn:placetype":[
        "aat:300008347"
    ]
},
  "bbox": [],
  "geometry": {"coordinates":[-6.566667,43.216667],"type":"Point"}
}