{
  "id": 2484642,
  "type": "Feature",
  "properties": {
    "tgn:hierarchy":[
        "tgn:2484642",
        "tgn:1000001",
        "tgn:2002255",
        "tgn:7012149",
        "tgn:7013961",
        "tgn:7029392"
    ],
    "tgn:id":2484642,
    "tgn:name":"Laurel Lick Branch",
    "tgn:placetype":[
        "aat:300008699"
    ]
},
  "bbox": [],
  "geometry": {"coordinates":[-81.6667,37.9667],"type":"Point"}
}