{
  "id": 2507709,
  "type": "Feature",
  "properties": {
    "tgn:hierarchy":[
        "tgn:2507709",
        "tgn:1000001",
        "tgn:7016102",
        "tgn:7012149",
        "tgn:7007516",
        "tgn:7029392"
    ],
    "tgn:id":2507709,
    "tgn:name":"Michaels Mill Dam",
    "tgn:placetype":[
        "aat:300006191"
    ]
},
  "bbox": [],
  "geometry": {"coordinates":[-76.25,39.5667],"type":"Point"}
}