{
  "id": 2446038,
  "type": "Feature",
  "properties": {
    "tgn:hierarchy":[
        "tgn:2446038",
        "tgn:1000001",
        "tgn:7012149",
        "tgn:1003038",
        "tgn:7007517",
        "tgn:7029392"
    ],
    "tgn:id":2446038,
    "tgn:name":"Leveau Island",
    "tgn:placetype":[
        "aat:300008791"
    ]
},
  "bbox": [],
  "geometry": {"coordinates":[-72.25,42.4333],"type":"Point"}
}