<<<<<<< HEAD
{
  "id": 7023402,
  "type": "Feature",
  "properties": {
    "tgn:hierarchy":[
        "tgn:7023402",
        "tgn:1000001",
        "tgn:7012149",
        "tgn:2000216",
        "tgn:7007158",
        "tgn:7029392"
    ],
    "tgn:id":7023402,
    "tgn:name":"McMahon Reservoir",
    "tgn:placetype":[
        "aat:300006191"
    ]
},
  "bbox": [],
  "geometry": {"coordinates":[-106.5667,40.1667],"type":"Point"}
}
=======
{"geometry":{"type":"Point","coordinates":[-106.566700,40.166700]},"type":"Feature","properties":{"hierarchy":["tgn:7023402","tgn:1000001","tgn:7012149","tgn:2000216","tgn:7007158","tgn:7029392"],"placetype":["aat:300006191"],"id":7023402,"name:xx":"McMahon Reservoir"}}
>>>>>>> 03f74aca74312dbeaf24d7e61306dd6a786dc3d0
