{
  "id": 7591251,
  "type": "Feature",
  "properties": {
    "tgn:hierarchy":[
        "tgn:7591251",
        "tgn:1000004",
        "tgn:7000198",
        "tgn:7031786",
        "tgn:7029392"
    ],
    "tgn:id":7591251,
    "tgn:name:en":"Lachhm\u012bpur",
    "tgn:placetype":[
        "aat:300008347"
    ]
},
  "bbox": [],
  "geometry": {"coordinates":[77.78795,30.437283],"type":"Point"}
}