{
  "id": 7514815,
  "type": "Feature",
  "properties": {
    "tgn:hierarchy":[
        "tgn:7514815",
        "tgn:1009227",
        "tgn:7001866",
        "tgn:1000226",
        "tgn:1000006",
        "tgn:7029392"
    ],
    "tgn:id":7514815,
    "tgn:name:en":"Dalethorpe",
    "tgn:placetype":[
        "aat:300000206"
    ]
},
  "bbox": [],
  "geometry": {"coordinates":[171.866667,-43.383333],"type":"Point"}
}