{
  "id": 7585994,
  "type": "Feature",
  "properties": {
    "tgn:hierarchy":[
        "tgn:7585994",
        "tgn:1000004",
        "tgn:7000198",
        "tgn:7000799",
        "tgn:7029392"
    ],
    "tgn:id":7585994,
    "tgn:name:en":"Chhatargul Pethapur",
    "tgn:placetype":[
        "aat:300008347"
    ]
},
  "bbox": [],
  "geometry": {"coordinates":[74.866667,34.315278],"type":"Point"}
}