{
  "id": 1055403,
  "type": "Feature",
  "properties": {
    "tgn:hierarchy":[
        "tgn:1055403",
        "tgn:1000004",
        "tgn:6004412",
        "tgn:7018214",
        "tgn:7002435",
        "tgn:7029392"
    ],
    "tgn:id":1055403,
    "tgn:name":"Knyazevka",
    "tgn:placetype":[
        "aat:300008347"
    ]
},
  "bbox": [],
  "geometry": {"coordinates":[74.1667,57.5833],"type":"Point"}
}