{
  "id": 1092395,
  "type": "Feature",
  "properties": {
    "tgn:hierarchy":[
        "tgn:1092395",
        "tgn:7001242",
        "tgn:1001412",
        "tgn:1000185",
        "tgn:7029392"
    ],
    "tgn:id":1092395,
    "tgn:name":"Inyanga",
    "tgn:placetype":[
        "aat:300008347"
    ]
},
  "bbox": [],
  "geometry": {"coordinates":[32.7667,-18.2167],"type":"Point"}
}