{
  "id": 2117138,
  "type": "Feature",
  "properties": {
    "tgn:hierarchy":[
        "tgn:2117138",
        "tgn:1000001",
        "tgn:7012149",
        "tgn:7018871",
        "tgn:7007920",
        "tgn:7029392"
    ],
    "tgn:id":2117138,
    "tgn:name":"Wieser",
    "tgn:placetype":[
        "aat:300387016"
    ]
},
  "bbox": [],
  "geometry": {"coordinates":[-122.2167,47.4167],"type":"Point"}
}