{
  "id": 7474197,
  "type": "Feature",
  "properties": {
    "tgn:hierarchy":[
        "tgn:7474197",
        "tgn:1000004",
        "tgn:1000454",
        "tgn:1000141",
        "tgn:7029392"
    ],
    "tgn:id":7474197,
    "tgn:name":"Xikeng",
    "tgn:placetype":[
        "aat:300008761"
    ]
},
  "bbox": [],
  "geometry": {"coordinates":[121.588748,24.812414],"type":"Point"}
}