<<<<<<< HEAD
{
  "id": 7474197,
  "type": "Feature",
  "properties": {
    "tgn:hierarchy":[
        "tgn:7474197",
        "tgn:1000004",
        "tgn:1000454",
        "tgn:1000141",
        "tgn:7029392"
    ],
    "tgn:id":7474197,
    "tgn:name":"Xikeng",
    "tgn:placetype":[
        "aat:300008761"
    ]
},
  "bbox": [],
  "geometry": {"coordinates":[121.588748,24.812414],"type":"Point"}
}
=======
{"geometry":{"type":"Point","coordinates":[121.588748,24.812414]},"type":"Feature","properties":{"hierarchy":["tgn:7474197","tgn:1000004","tgn:1000454","tgn:1000141","tgn:7029392"],"placetype":["aat:300008761"],"id":7474197,"name:xx":"Xikeng"}}
>>>>>>> 03f74aca74312dbeaf24d7e61306dd6a786dc3d0
