{
  "id": 7004684,
  "type": "Feature",
  "properties": {
    "tgn:hierarchy":[
        "tgn:7004684",
        "tgn:7003669",
        "tgn:1000003",
        "tgn:7000084",
        "tgn:7029392"
    ],
    "tgn:id":7004684,
    "tgn:name":"Seeon",
    "tgn:placetype":[
        "aat:300008347"
    ]
},
  "bbox": [],
  "geometry": {"coordinates":[12.45,47.9833],"type":"Point"}
}