{
  "id": 2564614,
  "type": "Feature",
  "properties": {
    "tgn:hierarchy":[
        "tgn:2564614",
        "tgn:1000001",
        "tgn:1002257",
        "tgn:7012149",
        "tgn:7007919",
        "tgn:7029392"
    ],
    "tgn:id":2564614,
    "tgn:name":"Packs Point",
    "tgn:placetype":[
        "aat:300008850"
    ]
},
  "bbox": [],
  "geometry": {"coordinates":[-77.25,37.3167],"type":"Point"}
}