{
  "id": 2582393,
  "type": "Feature",
  "properties": {
    "tgn:hierarchy":[
        "tgn:2582393",
        "tgn:1000001",
        "tgn:7006451",
        "tgn:7012149",
        "tgn:2000103",
        "tgn:7029392"
    ],
    "tgn:id":2582393,
    "tgn:name":"Pine Flat Tank",
    "tgn:placetype":[
        "aat:300006191"
    ]
},
  "bbox": [],
  "geometry": {"coordinates":[-112.8667,34.9667],"type":"Point"}
}