{
  "id": 7297130,
  "type": "Feature",
  "properties": {
    "tgn:hierarchy":[
        "tgn:7297130",
        "tgn:7002824",
        "tgn:1000003",
        "tgn:7002786",
        "tgn:1000095",
        "tgn:7029392"
    ],
    "tgn:id":7297130,
    "tgn:name":"Tarr\u00edo",
    "tgn:placetype":[
        "aat:300008347"
    ]
},
  "bbox": [],
  "geometry": {"coordinates":[-9.033333,42.666667],"type":"Point"}
}