{
  "id": 7022897,
  "type": "Feature",
  "properties": {
    "tgn:hierarchy":[
        "tgn:7022897",
        "tgn:1000001",
        "tgn:7012149",
        "tgn:7007825",
        "tgn:7029392"
    ],
    "tgn:id":7022897,
    "tgn:name":"Rotten Fork Wolf River",
    "tgn:placetype":[
        "aat:300008707"
    ]
},
  "bbox": [],
  "geometry": {"coordinates":[-84.9333,36.5833],"type":"Point"}
}