<<<<<<< HEAD
{
  "id": 7022897,
  "type": "Feature",
  "properties": {
    "tgn:hierarchy":[
        "tgn:7022897",
        "tgn:1000001",
        "tgn:7012149",
        "tgn:7007825",
        "tgn:7029392"
    ],
    "tgn:id":7022897,
    "tgn:name":"Rotten Fork Wolf River",
    "tgn:placetype":[
        "aat:300008707"
    ]
},
  "bbox": [],
  "geometry": {"coordinates":[-84.9333,36.5833],"type":"Point"}
}
=======
{"geometry":{"type":"Point","coordinates":[-84.933300,36.583300]},"type":"Feature","properties":{"hierarchy":["tgn:7022897","tgn:1000001","tgn:7012149","tgn:7007825","tgn:7029392"],"placetype":["aat:300008707"],"id":7022897,"name:xx":"Rotten Fork Wolf River"}}
>>>>>>> 03f74aca74312dbeaf24d7e61306dd6a786dc3d0
