<<<<<<< HEAD
{
  "id": 7244185,
  "type": "Feature",
  "properties": {
    "tgn:hierarchy":[
        "tgn:7244185",
        "tgn:7003458",
        "tgn:1000003",
        "tgn:1000063",
        "tgn:7018236",
        "tgn:7029392"
    ],
    "tgn:id":7244185,
    "tgn:name":"Kapelhoek",
    "tgn:placetype":[
        "aat:300008347"
    ]
},
  "bbox": [],
  "geometry": {"coordinates":[3.183333,50.833333],"type":"Point"}
}
=======
{"geometry":{"type":"Point","coordinates":[3.183333,50.833333]},"type":"Feature","properties":{"hierarchy":["tgn:7244185","tgn:7003458","tgn:1000003","tgn:1000063","tgn:7018236","tgn:7029392"],"placetype":["aat:300008347"],"id":7244185,"name:xx":"Kapelhoek"}}
>>>>>>> 03f74aca74312dbeaf24d7e61306dd6a786dc3d0
