{
  "id": 7277202,
  "type": "Feature",
  "properties": {
    "tgn:hierarchy":[
        "tgn:7277202",
        "tgn:1001702",
        "tgn:1000049",
        "tgn:1000002",
        "tgn:7029392"
    ],
    "tgn:id":7277202,
    "tgn:name":"Victoria, Paso",
    "tgn:placetype":[
        "aat:300387026"
    ]
},
  "bbox": [],
  "geometry": {"coordinates":[-73.716667,-52.016667],"type":"Point"}
}