{
  "id": 7193098,
  "type": "Feature",
  "properties": {
    "tgn:hierarchy":[
        "tgn:7193098",
        "tgn:7003669",
        "tgn:1000003",
        "tgn:7000084",
        "tgn:7029392"
    ],
    "tgn:id":7193098,
    "tgn:name":"Frauenberg",
    "tgn:placetype":[
        "aat:300008777"
    ]
},
  "bbox": [],
  "geometry": {"coordinates":[11.583333,49.35],"type":"Point"}
}