{
  "id": 2306966,
  "type": "Feature",
  "properties": {
    "tgn:hierarchy":[
        "tgn:2306966",
        "tgn:1000001",
        "tgn:7012149",
        "tgn:2001850",
        "tgn:7007825",
        "tgn:7029392"
    ],
    "tgn:id":2306966,
    "tgn:name":"East Fork Lick Run",
    "tgn:placetype":[
        "aat:300008699"
    ]
},
  "bbox": [],
  "geometry": {"coordinates":[-85.4167,36.5833],"type":"Point"}
}