<<<<<<< HEAD
{
  "id": 7372527,
  "type": "Feature",
  "properties": {
    "tgn:hierarchy":[
        "tgn:7372527",
        "tgn:7005580",
        "tgn:1000001",
        "tgn:7005560",
        "tgn:7029392"
    ],
    "tgn:id":7372527,
    "tgn:name":"Lacantum, R\u00edo",
    "tgn:placetype":[
        "aat:300008699"
    ]
},
  "bbox": [],
  "geometry": {"coordinates":[-90.65,16.6],"type":"Point"}
}
=======
{"geometry":{"type":"Point","coordinates":[-90.650000,16.600000]},"type":"Feature","properties":{"hierarchy":["tgn:7372527","tgn:7005580","tgn:1000001","tgn:7005560","tgn:7029392"],"placetype":["aat:300008699"],"id":7372527,"name:xx":"Lacantum, R\u00edo"}}
>>>>>>> 03f74aca74312dbeaf24d7e61306dd6a786dc3d0
