<<<<<<< HEAD
{
  "id": 2157963,
  "type": "Feature",
  "properties": {
    "tgn:hierarchy":[
        "tgn:2157963",
        "tgn:1000001",
        "tgn:7012149",
        "tgn:2001461",
        "tgn:7007568",
        "tgn:7029392"
    ],
    "tgn:id":2157963,
    "tgn:name":"Beaver Meadow Brook",
    "tgn:placetype":[
        "aat:300008699"
    ]
},
  "bbox": [],
  "geometry": {"coordinates":[-73.6,44.1167],"type":"Point"}
}
=======
{"geometry":{"type":"Point","coordinates":[-73.600000,44.116700]},"type":"Feature","properties":{"hierarchy":["tgn:2157963","tgn:1000001","tgn:7012149","tgn:2001461","tgn:7007568","tgn:7029392"],"placetype":["aat:300008699"],"id":2157963,"name:xx":"Beaver Meadow Brook"}}
>>>>>>> 03f74aca74312dbeaf24d7e61306dd6a786dc3d0
