{
  "id": 7168678,
  "type": "Feature",
  "properties": {
    "tgn:hierarchy":[
        "tgn:7168678",
        "tgn:1000003",
        "tgn:7003676",
        "tgn:7000084",
        "tgn:7029392"
    ],
    "tgn:id":7168678,
    "tgn:name":"Der Heber",
    "tgn:placetype":[
        "aat:300008795"
    ]
},
  "bbox": [],
  "geometry": {"coordinates":[10.083333,51.916667],"type":"Point"}
}