{
  "id": 7035528,
  "type": "Feature",
  "properties": {
    "tgn:hierarchy":[
        "tgn:7035528",
        "tgn:1003505",
        "tgn:1000003",
        "tgn:7002993",
        "tgn:1000080",
        "tgn:7029392"
    ],
    "tgn:id":7035528,
    "tgn:name":"Isonzo, Foce dell'",
    "tgn:placetype":[
        "aat:300387057"
    ]
},
  "bbox": [],
  "geometry": {"coordinates":[13.553611,45.725556],"type":"Point"}
}