{
  "id": 2204923,
  "type": "Feature",
  "properties": {
    "tgn:hierarchy":[
        "tgn:2204923",
        "tgn:1000001",
        "tgn:7012149",
        "tgn:2002175",
        "tgn:7007919",
        "tgn:7029392"
    ],
    "tgn:id":2204923,
    "tgn:name":"Buford Island",
    "tgn:placetype":[
        "aat:300008791"
    ]
},
  "bbox": [],
  "geometry": {"coordinates":[-78.65,37.6667],"type":"Point"}
}