{
  "id": 2647218,
  "type": "Feature",
  "properties": {
    "tgn:hierarchy":[
        "tgn:2647218",
        "tgn:1000001",
        "tgn:7012149",
        "tgn:1002926",
        "tgn:7007568",
        "tgn:7029392"
    ],
    "tgn:id":2647218,
    "tgn:name":"Schillings Lake",
    "tgn:placetype":[
        "aat:300008680"
    ]
},
  "bbox": [],
  "geometry": {"coordinates":[-74.75,41.5667],"type":"Point"}
}