{
  "id": 2183847,
  "type": "Feature",
  "properties": {
    "tgn:hierarchy":[
        "tgn:2183847",
        "tgn:1000001",
        "tgn:7012149",
        "tgn:2001821",
        "tgn:7007713",
        "tgn:7029392"
    ],
    "tgn:id":2183847,
    "tgn:name":"Boarding House Gulch",
    "tgn:placetype":[
        "aat:300008761"
    ]
},
  "bbox": [],
  "geometry": {"coordinates":[-103.5167,44.0833],"type":"Point"}
}