{
  "id": 2706215,
  "type": "Feature",
  "properties": {
    "tgn:hierarchy":[
        "tgn:2706215",
        "tgn:1000001",
        "tgn:7012149",
        "tgn:2001281",
        "tgn:7007524",
        "tgn:7029392"
    ],
    "tgn:id":2706215,
    "tgn:name":"Swamp Creek",
    "tgn:placetype":[
        "aat:300008706"
    ]
},
  "bbox": [],
  "geometry": {"coordinates":[-111.8167,46.25],"type":"Point"}
}