<<<<<<< HEAD
{
  "id": 7054094,
  "type": "Feature",
  "properties": {
    "tgn:hierarchy":[
        "tgn:7054094",
        "tgn:7005852",
        "tgn:1000003",
        "tgn:7003237",
        "tgn:1000080",
        "tgn:7029392"
    ],
    "tgn:id":7054094,
    "tgn:name":"Lurago d'Erba",
    "tgn:placetype":[
        "aat:300008347"
    ]
},
  "bbox": [],
  "geometry": {"coordinates":[9.116667,45.766667],"type":"Point"}
}
=======
{"geometry":{"type":"Point","coordinates":[9.116667,45.766667]},"type":"Feature","properties":{"hierarchy":["tgn:7054094","tgn:7005852","tgn:1000003","tgn:7003237","tgn:1000080","tgn:7029392"],"placetype":["aat:300008347"],"id":7054094,"name:xx":"Lurago d'Erba"}}
>>>>>>> 03f74aca74312dbeaf24d7e61306dd6a786dc3d0
