{
  "id": 7435439,
  "type": "Feature",
  "properties": {
    "tgn:hierarchy":[
        "tgn:7435439",
        "tgn:1001853",
        "tgn:1000001",
        "tgn:7005560",
        "tgn:7029392"
    ],
    "tgn:id":7435439,
    "tgn:name":"Rancho de Valencia",
    "tgn:placetype":[
        "aat:300000241"
    ]
},
  "bbox": [],
  "geometry": {"coordinates":[-102.35,29.316667],"type":"Point"}
}