<<<<<<< HEAD
{
  "id": 2253361,
  "type": "Feature",
  "properties": {
    "tgn:hierarchy":[
        "tgn:2253361",
        "tgn:1000001",
        "tgn:7012149",
        "tgn:1002749",
        "tgn:7007240",
        "tgn:7029392"
    ],
    "tgn:id":2253361,
    "tgn:name":"Conway, Lake",
    "tgn:placetype":[
        "aat:300008680"
    ]
},
  "bbox": [],
  "geometry": {"coordinates":[-81.35,28.4667],"type":"Point"}
}
=======
{"geometry":{"type":"Point","coordinates":[-81.350000,28.466700]},"type":"Feature","properties":{"hierarchy":["tgn:2253361","tgn:1000001","tgn:7012149","tgn:1002749","tgn:7007240","tgn:7029392"],"placetype":["aat:300008680"],"id":2253361,"name:xx":"Conway, Lake"}}
>>>>>>> 03f74aca74312dbeaf24d7e61306dd6a786dc3d0
