{
  "id": 7473897,
  "type": "Feature",
  "properties": {
    "tgn:hierarchy":[
        "tgn:7473897",
        "tgn:7488858",
        "tgn:1000004",
        "tgn:1000141",
        "tgn:7029392"
    ],
    "tgn:id":7473897,
    "tgn:name":"Dongyan Xi",
    "tgn:placetype":[
        "aat:300008699"
    ]
},
  "bbox": [],
  "geometry": {"coordinates":[121.102778,24.012778],"type":"Point"}
}