<<<<<<< HEAD
{
  "id": 7477798,
  "type": "Feature",
  "properties": {
    "tgn:hierarchy":[
        "tgn:7477798",
        "tgn:1000004",
        "tgn:7004300",
        "tgn:1000141",
        "tgn:7029392"
    ],
    "tgn:id":7477798,
    "tgn:name":"Xiwei Yugang",
    "tgn:placetype":[
        "aat:300008678"
    ]
},
  "bbox": [],
  "geometry": {"coordinates":[119.583985,23.580761],"type":"Point"}
}
=======
{"geometry":{"type":"Point","coordinates":[119.583985,23.580761]},"type":"Feature","properties":{"hierarchy":["tgn:7477798","tgn:1000004","tgn:7004300","tgn:1000141","tgn:7029392"],"placetype":["aat:300008678"],"id":7477798,"name:xx":"Xiwei Yugang"}}
>>>>>>> 03f74aca74312dbeaf24d7e61306dd6a786dc3d0
