{
  "id": 7311077,
  "type": "Feature",
  "properties": {
    "tgn:hierarchy":[
        "tgn:7311077",
        "tgn:1001657",
        "tgn:1000049",
        "tgn:1000002",
        "tgn:7029392"
    ],
    "tgn:id":7311077,
    "tgn:name":"Negro, Cerro",
    "tgn:placetype":[
        "aat:300008798"
    ]
},
  "bbox": [],
  "geometry": {"coordinates":[-70.466667,-32.116667],"type":"Point"}
}