{
  "id": 7428116,
  "type": "Feature",
  "properties": {
    "tgn:hierarchy":[
        "tgn:7428116",
        "tgn:1000001",
        "tgn:7005594",
        "tgn:7005560",
        "tgn:7029392"
    ],
    "tgn:id":7428116,
    "tgn:name":"San Juan de Vanegas",
    "tgn:placetype":[
        "aat:300008347"
    ]
},
  "bbox": [],
  "geometry": {"coordinates":[-100.866667,23.85],"type":"Point"}
}