{
  "id": 7560124,
  "type": "Feature",
  "properties": {
    "tgn:hierarchy":[
        "tgn:7560124",
        "tgn:1000004",
        "tgn:7000198",
        "tgn:7016788",
        "tgn:7029392"
    ],
    "tgn:id":7560124,
    "tgn:name:en":"Sinw\u0101r",
    "tgn:placetype":[
        "aat:300008347"
    ]
},
  "bbox": [],
  "geometry": {"coordinates":[75.632978,26.9237],"type":"Point"}
}