{
  "id": 7513580,
  "type": "Feature",
  "properties": {
    "tgn:hierarchy":[
        "tgn:7513580",
        "tgn:1009227",
        "tgn:1000226",
        "tgn:1000006",
        "tgn:7016850",
        "tgn:7029392"
    ],
    "tgn:id":7513580,
    "tgn:name:en":"Gate Creek",
    "tgn:placetype":[
        "aat:300008699"
    ]
},
  "bbox": [],
  "geometry": {"coordinates":[169.433333,-43.683333],"type":"Point"}
}