{
  "id": 2310563,
  "type": "Feature",
  "properties": {
    "tgn:hierarchy":[
        "tgn:2310563",
        "tgn:1000001",
        "tgn:2001264",
        "tgn:7012149",
        "tgn:7007524",
        "tgn:7029392"
    ],
    "tgn:id":2310563,
    "tgn:name":"Echo Lake",
    "tgn:placetype":[
        "aat:300008680"
    ]
},
  "bbox": [],
  "geometry": {"coordinates":[-109.7333,45.1167],"type":"Point"}
}