{
  "id": 2117093,
  "type": "Feature",
  "properties": {
    "tgn:hierarchy":[
        "tgn:2117093",
        "tgn:1000001",
        "tgn:7012149",
        "tgn:1002552",
        "tgn:7007920",
        "tgn:7029392"
    ],
    "tgn:id":2117093,
    "tgn:name":"Wautauga Beach",
    "tgn:placetype":[
        "aat:300008347"
    ]
},
  "bbox": [],
  "geometry": {"coordinates":[-122.5333,47.5833],"type":"Point"}
}