{
  "id": 2142674,
  "type": "Feature",
  "properties": {
    "tgn:hierarchy":[
        "tgn:2142674",
        "tgn:1000001",
        "tgn:7012149",
        "tgn:7007157",
        "tgn:1002841",
        "tgn:7029392"
    ],
    "tgn:id":2142674,
    "tgn:name":"Badger Creek",
    "tgn:placetype":[
        "aat:300008706"
    ]
},
  "bbox": [],
  "geometry": {"coordinates":[-121.1667,38.3833],"type":"Point"}
}