{
  "id": 7385500,
  "type": "Feature",
  "properties": {
    "tgn:hierarchy":[
        "tgn:7385500",
        "tgn:7005581",
        "tgn:1000001",
        "tgn:7005560",
        "tgn:7029392"
    ],
    "tgn:id":7385500,
    "tgn:name":"Ojo del Berrendo",
    "tgn:placetype":[
        "aat:300008347"
    ]
},
  "bbox": [],
  "geometry": {"coordinates":[-107.033333,30.45],"type":"Point"}
}