{
  "id": 7196125,
  "type": "Feature",
  "properties": {
    "tgn:hierarchy":[
        "tgn:7196125",
        "tgn:1000003",
        "tgn:7003677",
        "tgn:7000084",
        "tgn:7029392"
    ],
    "tgn:id":7196125,
    "tgn:name":"De Witt",
    "tgn:placetype":[
        "aat:300008680"
    ]
},
  "bbox": [],
  "geometry": {"coordinates":[6.233333,51.316667],"type":"Point"}
}