{
  "id": 2121472,
  "type": "Feature",
  "properties": {
    "tgn:hierarchy":[
        "tgn:2121472",
        "tgn:1000001",
        "tgn:7012149",
        "tgn:7014350",
        "tgn:7007922",
        "tgn:7029392"
    ],
    "tgn:id":2121472,
    "tgn:name":"Janesville",
    "tgn:placetype":[
        "aat:300008347"
    ]
},
  "bbox": [],
  "geometry": {"coordinates":[-89.0167,42.6667],"type":"Point"}
}