{
  "id": 2670959,
  "type": "Feature",
  "properties": {
    "tgn:hierarchy":[
        "tgn:2670959",
        "tgn:1000001",
        "tgn:7012149",
        "tgn:7007157",
        "tgn:1003046",
        "tgn:7029392"
    ],
    "tgn:id":2670959,
    "tgn:name":"Smith Creek",
    "tgn:placetype":[
        "aat:300008706"
    ]
},
  "bbox": [],
  "geometry": {"coordinates":[-121.9167,38.75],"type":"Point"}
}