{
  "id": 2673051,
  "type": "Feature",
  "properties": {
    "tgn:hierarchy":[
        "tgn:2673051",
        "tgn:1000001",
        "tgn:7012149",
        "tgn:2000891",
        "tgn:7007256",
        "tgn:7029392"
    ],
    "tgn:id":2673051,
    "tgn:name":"Snake Island",
    "tgn:placetype":[
        "aat:300008791"
    ]
},
  "bbox": [],
  "geometry": {"coordinates":[-89.55,29.6333],"type":"Point"}
}