{
  "id": 7002627,
  "type": "Feature",
  "properties": {
    "tgn:hierarchy":[
        "tgn:7002627",
        "tgn:1001410",
        "tgn:1000004",
        "tgn:7018451",
        "tgn:1000144",
        "tgn:7029392"
    ],
    "tgn:id":7002627,
    "tgn:name":"Akhisar",
    "tgn:placetype":[
        "aat:300008347",
        "aat:300000810",
        "aat:300019705",
        "aat:300008375"
    ]
},
  "bbox": [],
  "geometry": {"coordinates":[27.840065,38.918524],"type":"Point"}
}