{
  "id": 2606197,
  "type": "Feature",
  "properties": {
    "tgn:hierarchy":[
        "tgn:2606197",
        "tgn:1000001",
        "tgn:7012149",
        "tgn:7007157",
        "tgn:2000189",
        "tgn:7029392"
    ],
    "tgn:id":2606197,
    "tgn:name":"Rainy Lake",
    "tgn:placetype":[
        "aat:300008680"
    ]
},
  "bbox": [],
  "geometry": {"coordinates":[-123.2333,41.55],"type":"Point"}
}