{
  "id": 2518470,
  "type": "Feature",
  "properties": {
    "tgn:hierarchy":[
        "tgn:2518470",
        "tgn:1000001",
        "tgn:2001425",
        "tgn:7012149",
        "tgn:7007564",
        "tgn:7029392"
    ],
    "tgn:id":2518470,
    "tgn:name":"Mitchell Brook",
    "tgn:placetype":[
        "aat:300008699"
    ]
},
  "bbox": [],
  "geometry": {"coordinates":[-71.8167,43.45],"type":"Point"}
}