{
  "id": 2413190,
  "type": "Feature",
  "properties": {
    "tgn:hierarchy":[
        "tgn:2413190",
        "tgn:1000001",
        "tgn:7012149",
        "tgn:2000488",
        "tgn:7007250",
        "tgn:7029392"
    ],
    "tgn:id":2413190,
    "tgn:name":"Inside Lakes",
    "tgn:placetype":[
        "aat:300008680"
    ]
},
  "bbox": [],
  "geometry": {"coordinates":[-115.5667,42.2833],"type":"Point"}
}