{
  "id": 7427664,
  "type": "Feature",
  "properties": {
    "tgn:hierarchy":[
        "tgn:7427664",
        "tgn:1000001",
        "tgn:7005594",
        "tgn:7005560",
        "tgn:7029392"
    ],
    "tgn:id":7427664,
    "tgn:name":"Cerro Pez, Laguna",
    "tgn:placetype":[
        "aat:300008680"
    ]
},
  "bbox": [],
  "geometry": {"coordinates":[-98.366667,22.166667],"type":"Point"}
}