{
  "id": 7035593,
  "type": "Feature",
  "properties": {
    "tgn:hierarchy":[
        "tgn:7035593",
        "tgn:7002991",
        "tgn:1000003",
        "tgn:7002997",
        "tgn:1000080",
        "tgn:7029392"
    ],
    "tgn:id":7035593,
    "tgn:name":"Casera Venal",
    "tgn:placetype":[
        "aat:300008347"
    ]
},
  "bbox": [],
  "geometry": {"coordinates":[12.424444,46.199167],"type":"Point"}
}