{
  "id": 2398313,
  "type": "Feature",
  "properties": {
    "tgn:hierarchy":[
        "tgn:2398313",
        "tgn:1000001",
        "tgn:7016172",
        "tgn:7012149",
        "tgn:2000148",
        "tgn:7029392"
    ],
    "tgn:id":2398313,
    "tgn:name":"Hooper Hollow",
    "tgn:placetype":[
        "aat:300008761"
    ]
},
  "bbox": [],
  "geometry": {"coordinates":[-93.6833,35.85],"type":"Point"}
}