{
  "id": 2199694,
  "type": "Feature",
  "properties": {
    "tgn:hierarchy":[
        "tgn:2199694",
        "tgn:1000001",
        "tgn:7012149",
        "tgn:2000510",
        "tgn:7007251",
        "tgn:7029392"
    ],
    "tgn:id":2199694,
    "tgn:name":"Brush Lake",
    "tgn:placetype":[
        "aat:300008680"
    ]
},
  "bbox": [],
  "geometry": {"coordinates":[-91.0667,40.7333],"type":"Point"}
}