{
  "id": 2726624,
  "type": "Feature",
  "properties": {
    "tgn:hierarchy":[
        "tgn:2726624",
        "tgn:7013349",
        "tgn:1000001",
        "tgn:7012149",
        "tgn:7007708",
        "tgn:7029392"
    ],
    "tgn:id":2726624,
    "tgn:name":"Town Gulch",
    "tgn:placetype":[
        "aat:300008761"
    ]
},
  "bbox": [],
  "geometry": {"coordinates":[-117.3167,44.8667],"type":"Point"}
}