{
  "id": 7348047,
  "type": "Feature",
  "properties": {
    "tgn:hierarchy":[
        "tgn:7348047",
        "tgn:7002804",
        "tgn:1000003",
        "tgn:7002793",
        "tgn:1000095",
        "tgn:7029392"
    ],
    "tgn:id":7348047,
    "tgn:name":"Abanilla, Rambla de",
    "tgn:placetype":[
        "aat:300266554",
        "aat:300008699"
    ]
},
  "bbox": [],
  "geometry": {"coordinates":[-0.966667,38.15],"type":"Point"}
}