{
  "id": 7397549,
  "type": "Feature",
  "properties": {
    "tgn:hierarchy":[
        "tgn:7397549",
        "tgn:7005586",
        "tgn:1000001",
        "tgn:7005560",
        "tgn:7029392"
    ],
    "tgn:id":7397549,
    "tgn:name":"San Nicol\u00e1s",
    "tgn:placetype":[
        "aat:300008347"
    ]
},
  "bbox": [],
  "geometry": {"coordinates":[-103.25,20.183333],"type":"Point"}
}