{
  "id": 2342360,
  "type": "Feature",
  "properties": {
    "tgn:hierarchy":[
        "tgn:2342360",
        "tgn:1000001",
        "tgn:2002134",
        "tgn:7012149",
        "tgn:7007828",
        "tgn:7029392"
    ],
    "tgn:id":2342360,
    "tgn:name":"Fuller Hill",
    "tgn:placetype":[
        "aat:300008798"
    ]
},
  "bbox": [],
  "geometry": {"coordinates":[-72.2833,44.1667],"type":"Point"}
}