{
  "id": 7410403,
  "type": "Feature",
  "properties": {
    "tgn:hierarchy":[
        "tgn:7410403",
        "tgn:1000001",
        "tgn:7005590",
        "tgn:7005560",
        "tgn:7029392"
    ],
    "tgn:id":7410403,
    "tgn:name":"Las Pilas",
    "tgn:placetype":[
        "aat:300008347"
    ]
},
  "bbox": [],
  "geometry": {"coordinates":[-101.616667,18.683333],"type":"Point"}
}