{
  "id": 7560409,
  "type": "Feature",
  "properties": {
    "tgn:hierarchy":[
        "tgn:7560409",
        "tgn:1000004",
        "tgn:7000198",
        "tgn:7016788",
        "tgn:7029392"
    ],
    "tgn:id":7560409,
    "tgn:name:en":"M\u0101ngiy\u0101w\u0101s",
    "tgn:placetype":[
        "aat:300008347"
    ]
},
  "bbox": [],
  "geometry": {"coordinates":[75.735163,26.859736],"type":"Point"}
}