{
  "id": 2038626,
  "type": "Feature",
  "properties": {
    "tgn:hierarchy":[
        "tgn:2038626",
        "tgn:1000001",
        "tgn:1002237",
        "tgn:7012149",
        "tgn:7007255",
        "tgn:7029392"
    ],
    "tgn:id":2038626,
    "tgn:name":"Easterday",
    "tgn:placetype":[
        "aat:300008347",
        "aat:300387210"
    ]
},
  "bbox": [],
  "geometry": {"coordinates":[-85.0667,38.6667],"type":"Point"}
}