{
  "id": 7299336,
  "type": "Feature",
  "properties": {
    "tgn:hierarchy":[
        "tgn:7299336",
        "tgn:7002758",
        "tgn:1001316",
        "tgn:1000003",
        "tgn:1000095",
        "tgn:7029392"
    ],
    "tgn:id":7299336,
    "tgn:name":"Tobaruela",
    "tgn:placetype":[
        "aat:300008347"
    ]
},
  "bbox": [],
  "geometry": {"coordinates":[-3.633333,38.066667],"type":"Point"}
}