{
  "id": 2627066,
  "type": "Feature",
  "properties": {
    "tgn:hierarchy":[
        "tgn:2627066",
        "tgn:1000001",
        "tgn:7012149",
        "tgn:2000329",
        "tgn:7007248",
        "tgn:7029392"
    ],
    "tgn:id":2627066,
    "tgn:name":"Rocky Shoals Estates",
    "tgn:placetype":[
        "aat:300008347"
    ]
},
  "bbox": [],
  "geometry": {"coordinates":[-84.6333,33.3667],"type":"Point"}
}