{
  "id": 2033048,
  "type": "Feature",
  "properties": {
    "tgn:hierarchy":[
        "tgn:2033048",
        "tgn:1000001",
        "tgn:7012149",
        "tgn:1002569",
        "tgn:7007252",
        "tgn:7029392"
    ],
    "tgn:id":2033048,
    "tgn:name":"New Chicago",
    "tgn:placetype":[
        "aat:300008347"
    ]
},
  "bbox": [],
  "geometry": {"coordinates":[-87.2667,41.55],"type":"Point"}
}