{
  "id": 2577792,
  "type": "Feature",
  "properties": {
    "tgn:hierarchy":[
        "tgn:2577792",
        "tgn:1000001",
        "tgn:7006451",
        "tgn:2000093",
        "tgn:7012149",
        "tgn:7029392"
    ],
    "tgn:id":2577792,
    "tgn:name":"Petes Spring",
    "tgn:placetype":[
        "aat:300008697"
    ]
},
  "bbox": [],
  "geometry": {"coordinates":[-111.6667,34.2167],"type":"Point"}
}