{
  "id": 7549937,
  "type": "Feature",
  "properties": {
    "tgn:hierarchy":[
        "tgn:7549937",
        "tgn:1000004",
        "tgn:7000198",
        "tgn:1001894",
        "tgn:7029392"
    ],
    "tgn:id":7549937,
    "tgn:name:en":"Bilehra",
    "tgn:placetype":[
        "aat:300008347"
    ]
},
  "bbox": [],
  "geometry": {"coordinates":[78.730678,23.646365],"type":"Point"}
}