<<<<<<< HEAD
{
  "id": 2256088,
  "type": "Feature",
  "properties": {
    "tgn:hierarchy":[
        "tgn:2256088",
        "tgn:1000001",
        "tgn:2001704",
        "tgn:7012149",
        "tgn:7007708",
        "tgn:7029392"
    ],
    "tgn:id":2256088,
    "tgn:name":"Copper Mountain",
    "tgn:placetype":[
        "aat:300008798"
    ]
},
  "bbox": [],
  "geometry": {"coordinates":[-124.1667,42.7167],"type":"Point"}
}
=======
{"geometry":{"type":"Point","coordinates":[-124.166700,42.716700]},"type":"Feature","properties":{"hierarchy":["tgn:2256088","tgn:1000001","tgn:2001704","tgn:7012149","tgn:7007708","tgn:7029392"],"placetype":["aat:300008798"],"id":2256088,"name:xx":"Copper Mountain"}}
>>>>>>> 03f74aca74312dbeaf24d7e61306dd6a786dc3d0
