{
  "id": 7108784,
  "type": "Feature",
  "properties": {
    "tgn:hierarchy":[
        "tgn:7108784",
        "tgn:1000003",
        "tgn:7003685",
        "tgn:7000084",
        "tgn:7029392"
    ],
    "tgn:id":7108784,
    "tgn:name":"Forstw\u00e4rter Rabenberg",
    "tgn:placetype":[
        "aat:300004792"
    ]
},
  "bbox": [],
  "geometry": {"coordinates":[12.733333,50.466667],"type":"Point"}
}