<<<<<<< HEAD
{
  "id": 7478495,
  "type": "Feature",
  "properties": {
    "tgn:hierarchy":[
        "tgn:7478495",
        "tgn:1000004",
        "tgn:7489179",
        "tgn:1000141",
        "tgn:7029392"
    ],
    "tgn:id":7478495,
    "tgn:name":"Luodong Guozhong",
    "tgn:placetype":[
        "aat:300006495"
    ]
},
  "bbox": [],
  "geometry": {"coordinates":[121.766775,24.681524],"type":"Point"}
}
=======
{"geometry":{"type":"Point","coordinates":[121.766775,24.681524]},"type":"Feature","properties":{"hierarchy":["tgn:7478495","tgn:1000004","tgn:7489179","tgn:1000141","tgn:7029392"],"placetype":["aat:300006495"],"id":7478495,"name:xx":"Luodong Guozhong"}}
>>>>>>> 03f74aca74312dbeaf24d7e61306dd6a786dc3d0
