{
  "id": 7321529,
  "type": "Feature",
  "properties": {
    "tgn:hierarchy":[
        "tgn:7321529",
        "tgn:1001702",
        "tgn:1000049",
        "tgn:1000002",
        "tgn:7029392"
    ],
    "tgn:id":7321529,
    "tgn:name":"Broome, Pen\u00ednsula",
    "tgn:placetype":[
        "aat:300008804"
    ]
},
  "bbox": [],
  "geometry": {"coordinates":[-74.433333,-49.383333],"type":"Point"}
}