{
  "id": 1103848,
  "type": "Feature",
  "properties": {
    "tgn:hierarchy":[
        "tgn:1103848",
        "tgn:1000001",
        "tgn:7012149",
        "tgn:2002382",
        "tgn:7007923",
        "tgn:7029392"
    ],
    "tgn:id":1103848,
    "tgn:name":"Bald Knoll",
    "tgn:placetype":[
        "aat:300008795"
    ]
},
  "bbox": [],
  "geometry": {"coordinates":[-110.4833,42.3833],"type":"Point"}
}