{
  "id": 7221913,
  "type": "Feature",
  "properties": {
    "tgn:hierarchy":[
        "tgn:7221913",
        "tgn:7011270",
        "tgn:7002674",
        "tgn:1000003",
        "tgn:1000074",
        "tgn:7029392"
    ],
    "tgn:id":7221913,
    "tgn:name":"Potam\u00f3s",
    "tgn:placetype":[
        "aat:300008347"
    ]
},
  "bbox": [],
  "geometry": {"coordinates":[25.338965,36.437643],"type":"Point"}
}