{
  "id": 2328562,
  "type": "Feature",
  "properties": {
    "tgn:hierarchy":[
        "tgn:2328562",
        "tgn:1000001",
        "tgn:7012149",
        "tgn:7007922",
        "tgn:7029392"
    ],
    "tgn:id":2328562,
    "tgn:name":"Fisher River",
    "tgn:placetype":[
        "aat:300008707"
    ]
},
  "bbox": [],
  "geometry": {"coordinates":[-90.7667,45.2333],"type":"Point"}
}