{
  "id": 7546366,
  "type": "Feature",
  "properties": {
    "tgn:hierarchy":[
        "tgn:7546366",
        "tgn:1000004",
        "tgn:1001832",
        "tgn:7000198",
        "tgn:7029392"
    ],
    "tgn:id":7546366,
    "tgn:name:en":"Baut B\u0101z\u0101r",
    "tgn:placetype":[
        "aat:300008347"
    ]
},
  "bbox": [],
  "geometry": {"coordinates":[92.689559,25.736568],"type":"Point"}
}