{
  "id": 2429569,
  "type": "Feature",
  "properties": {
    "tgn:hierarchy":[
        "tgn:2429569",
        "tgn:1000001",
        "tgn:2001267",
        "tgn:7012149",
        "tgn:7007524",
        "tgn:7029392"
    ],
    "tgn:id":2429569,
    "tgn:name":"Juniper Spring",
    "tgn:placetype":[
        "aat:300008697"
    ]
},
  "bbox": [],
  "geometry": {"coordinates":[-109.5667,48.0167],"type":"Point"}
}