{
  "id": 7443725,
  "type": "Feature",
  "properties": {
    "tgn:hierarchy":[
        "tgn:7443725",
        "tgn:7002445",
        "tgn:1000003",
        "tgn:7026532",
        "tgn:7008591",
        "tgn:7029392"
    ],
    "tgn:id":7443725,
    "tgn:name:en":"Upper Stratton",
    "tgn:placetype":[
        "aat:300008347"
    ]
},
  "bbox": [],
  "geometry": {"coordinates":[-1.766667,51.583333],"type":"Point"}
}