{
  "id": 2010994,
  "type": "Feature",
  "properties": {
    "tgn:hierarchy":[
        "tgn:2010994",
        "tgn:1000001",
        "tgn:1002218",
        "tgn:7012149",
        "tgn:7007157",
        "tgn:7029392"
    ],
    "tgn:id":2010994,
    "tgn:name":"Dayton",
    "tgn:placetype":[
        "aat:300008347"
    ]
},
  "bbox": [],
  "geometry": {"coordinates":[-121.8667,39.6333],"type":"Point"}
}