{
  "id": 7390014,
  "type": "Feature",
  "properties": {
    "tgn:hierarchy":[
        "tgn:7390014",
        "tgn:7005583",
        "tgn:1000001",
        "tgn:7005560",
        "tgn:7029392"
    ],
    "tgn:id":7390014,
    "tgn:name":"Rancho En Medio",
    "tgn:placetype":[
        "aat:300008347"
    ]
},
  "bbox": [],
  "geometry": {"coordinates":[-105.85,26.633333],"type":"Point"}
}