{
  "id": 2488274,
  "type": "Feature",
  "properties": {
    "tgn:hierarchy":[
        "tgn:2488274",
        "tgn:1000001",
        "tgn:7012149",
        "tgn:7007158",
        "tgn:2000248",
        "tgn:7029392"
    ],
    "tgn:id":2488274,
    "tgn:name":"Magpie Number 2 Mine",
    "tgn:placetype":[
        "aat:300000390"
    ]
},
  "bbox": [],
  "geometry": {"coordinates":[-108.8333,38.0833],"type":"Point"}
}