<<<<<<< HEAD
{
  "id": 7378267,
  "type": "Feature",
  "properties": {
    "tgn:hierarchy":[
        "tgn:7378267",
        "tgn:1001853",
        "tgn:1000001",
        "tgn:7005560",
        "tgn:7029392"
    ],
    "tgn:id":7378267,
    "tgn:name":"Las Conchas",
    "tgn:placetype":[
        "aat:300008347"
    ]
},
  "bbox": [],
  "geometry": {"coordinates":[-101.516667,28.1],"type":"Point"}
}
=======
{"geometry":{"type":"Point","coordinates":[-101.516667,28.100000]},"type":"Feature","properties":{"hierarchy":["tgn:7378267","tgn:1001853","tgn:1000001","tgn:7005560","tgn:7029392"],"placetype":["aat:300008347"],"id":7378267,"name:xx":"Las Conchas"}}
>>>>>>> 03f74aca74312dbeaf24d7e61306dd6a786dc3d0
