{
  "id": 2407941,
  "type": "Feature",
  "properties": {
    "tgn:hierarchy":[
        "tgn:2407941",
        "tgn:1000001",
        "tgn:7012149",
        "tgn:2000909",
        "tgn:7007256",
        "tgn:7029392"
    ],
    "tgn:id":2407941,
    "tgn:name":"Hurricane Creek",
    "tgn:placetype":[
        "aat:300008706"
    ]
},
  "bbox": [],
  "geometry": {"coordinates":[-92.2833,32.6333],"type":"Point"}
}