<<<<<<< HEAD
{
  "id": 2158748,
  "type": "Feature",
  "properties": {
    "tgn:hierarchy":[
        "tgn:2158748",
        "tgn:1000001",
        "tgn:7012149",
        "tgn:1002966",
        "tgn:7007826",
        "tgn:7029392"
    ],
    "tgn:id":2158748,
    "tgn:name":"Beck Branch",
    "tgn:placetype":[
        "aat:300008699"
    ]
},
  "bbox": [],
  "geometry": {"coordinates":[-95.1,32.75],"type":"Point"}
}
=======
{"geometry":{"type":"Point","coordinates":[-95.100000,32.750000]},"type":"Feature","properties":{"hierarchy":["tgn:2158748","tgn:1000001","tgn:7012149","tgn:1002966","tgn:7007826","tgn:7029392"],"placetype":["aat:300008699"],"id":2158748,"name:xx":"Beck Branch"}}
>>>>>>> 03f74aca74312dbeaf24d7e61306dd6a786dc3d0
