{
  "id": 7283305,
  "type": "Feature",
  "properties": {
    "tgn:hierarchy":[
        "tgn:7283305",
        "tgn:1001657",
        "tgn:1000049",
        "tgn:1000002",
        "tgn:7029392"
    ],
    "tgn:id":7283305,
    "tgn:name":"Pangue, Quebrada",
    "tgn:placetype":[
        "aat:300008699"
    ]
},
  "bbox": [],
  "geometry": {"coordinates":[-71.466667,-31.75],"type":"Point"}
}