{
  "id": 7468464,
  "type": "Feature",
  "properties": {
    "tgn:hierarchy":[
        "tgn:7468464",
        "tgn:7488858",
        "tgn:1000004",
        "tgn:1000141",
        "tgn:7029392"
    ],
    "tgn:id":7468464,
    "tgn:name":"Fengguidou Shan",
    "tgn:placetype":[
        "aat:300008798"
    ]
},
  "bbox": [],
  "geometry": {"coordinates":[120.849722,23.653333],"type":"Point"}
}