{
  "id": 2273123,
  "type": "Feature",
  "properties": {
    "tgn:hierarchy":[
        "tgn:2273123",
        "tgn:1000001",
        "tgn:7012149",
        "tgn:2002360",
        "tgn:7007922",
        "tgn:7029392"
    ],
    "tgn:id":2273123,
    "tgn:name":"Cyclone Lake",
    "tgn:placetype":[
        "aat:300008680"
    ]
},
  "bbox": [],
  "geometry": {"coordinates":[-91.9333,45.8167],"type":"Point"}
}