{
  "id": 7307956,
  "type": "Feature",
  "properties": {
    "tgn:hierarchy":[
        "tgn:7307956",
        "tgn:1001623",
        "tgn:1000049",
        "tgn:1000002",
        "tgn:7029392"
    ],
    "tgn:id":7307956,
    "tgn:name":"Monaguillo, Punta",
    "tgn:placetype":[
        "aat:300386846"
    ]
},
  "bbox": [],
  "geometry": {"coordinates":[-74.183333,-47.166667],"type":"Point"}
}