{
  "id": 2321209,
  "type": "Feature",
  "properties": {
    "tgn:hierarchy":[
        "tgn:2321209",
        "tgn:1000001",
        "tgn:7006451",
        "tgn:7012149",
        "tgn:2000103",
        "tgn:7029392"
    ],
    "tgn:id":2321209,
    "tgn:name":"Fair Oaks",
    "tgn:placetype":[
        "aat:300008347"
    ]
},
  "bbox": [],
  "geometry": {"coordinates":[-112.75,34.7167],"type":"Point"}
}