{
  "id": 1046654,
  "type": "Feature",
  "properties": {
    "tgn:hierarchy":[
        "tgn:1046654",
        "tgn:1003455",
        "tgn:1000003",
        "tgn:7010380",
        "tgn:1000080",
        "tgn:7029392"
    ],
    "tgn:id":1046654,
    "tgn:name":"Sannicandro Garganico",
    "tgn:placetype":[
        "aat:300008347"
    ]
},
  "bbox": [],
  "geometry": {"coordinates":[15.566667,41.833333],"type":"Point"}
}