<<<<<<< HEAD
{
  "id": 2764272,
  "type": "Feature",
  "properties": {
    "tgn:hierarchy":[
        "tgn:2764272",
        "tgn:1000001",
        "tgn:7012149",
        "tgn:1002590",
        "tgn:7007826",
        "tgn:7029392"
    ],
    "tgn:id":2764272,
    "tgn:name":"Wheelock Creek",
    "tgn:placetype":[
        "aat:300008706"
    ]
},
  "bbox": [],
  "geometry": {"coordinates":[-96.0,31.3833],"type":"Point"}
}
=======
{"geometry":{"type":"Point","coordinates":[-96.000000,31.383300]},"type":"Feature","properties":{"hierarchy":["tgn:2764272","tgn:1000001","tgn:7012149","tgn:1002590","tgn:7007826","tgn:7029392"],"placetype":["aat:300008706"],"id":2764272,"name:xx":"Wheelock Creek"}}
>>>>>>> 03f74aca74312dbeaf24d7e61306dd6a786dc3d0
