{
  "id": 7054889,
  "type": "Feature",
  "properties": {
    "tgn:hierarchy":[
        "tgn:7054889",
        "tgn:7003170",
        "tgn:1000003",
        "tgn:7003125",
        "tgn:1000080",
        "tgn:7029392"
    ],
    "tgn:id":7054889,
    "tgn:name":"Molino Corsi",
    "tgn:placetype":[
        "aat:300008347"
    ]
},
  "bbox": [],
  "geometry": {"coordinates":[12.416667,43.483333],"type":"Point"}
}