<<<<<<< HEAD
{
  "id": 7357996,
  "type": "Feature",
  "properties": {
    "tgn:hierarchy":[
        "tgn:7357996",
        "tgn:7005581",
        "tgn:1000001",
        "tgn:7005560",
        "tgn:7029392"
    ],
    "tgn:id":7357996,
    "tgn:name":"Cotera, Cerro",
    "tgn:placetype":[
        "aat:300008795"
    ]
},
  "bbox": [],
  "geometry": {"coordinates":[-107.883333,28.95],"type":"Point"}
}
=======
{"geometry":{"type":"Point","coordinates":[-107.883333,28.950000]},"type":"Feature","properties":{"hierarchy":["tgn:7357996","tgn:7005581","tgn:1000001","tgn:7005560","tgn:7029392"],"placetype":["aat:300008795"],"id":7357996,"name:xx":"Cotera, Cerro"}}
>>>>>>> 03f74aca74312dbeaf24d7e61306dd6a786dc3d0
