{
  "id": 2572130,
  "type": "Feature",
  "properties": {
    "tgn:hierarchy":[
        "tgn:2572130",
        "tgn:1000001",
        "tgn:7012149",
        "tgn:7014612",
        "tgn:7007568",
        "tgn:7029392"
    ],
    "tgn:id":2572130,
    "tgn:name":"Pea Pond",
    "tgn:placetype":[
        "aat:300008680"
    ]
},
  "bbox": [],
  "geometry": {"coordinates":[-73.6167,41.2167],"type":"Point"}
}