{
  "id": 2352672,
  "type": "Feature",
  "properties": {
    "tgn:hierarchy":[
        "tgn:2352672",
        "tgn:1000001",
        "tgn:7012149",
        "tgn:2000183",
        "tgn:7007157",
        "tgn:7029392"
    ],
    "tgn:id":2352672,
    "tgn:name":"Goat Spring",
    "tgn:placetype":[
        "aat:300008697"
    ]
},
  "bbox": [],
  "geometry": {"coordinates":[-118.1667,37.4167],"type":"Point"}
}