{
  "id": 2690347,
  "type": "Feature",
  "properties": {
    "tgn:hierarchy":[
        "tgn:2690347",
        "tgn:1000001",
        "tgn:7012149",
        "tgn:2002385",
        "tgn:7007923",
        "tgn:7029392"
    ],
    "tgn:id":2690347,
    "tgn:name":"Stagecoach Hollow",
    "tgn:placetype":[
        "aat:300008761"
    ]
},
  "bbox": [],
  "geometry": {"coordinates":[-110.9167,41.1667],"type":"Point"}
}