{
  "id": 2457071,
  "type": "Feature",
  "properties": {
    "tgn:hierarchy":[
        "tgn:2457071",
        "tgn:1000001",
        "tgn:7012149",
        "tgn:1002977",
        "tgn:7007240",
        "tgn:7029392"
    ],
    "tgn:id":2457071,
    "tgn:name":"Little Lake",
    "tgn:placetype":[
        "aat:300008680"
    ]
},
  "bbox": [],
  "geometry": {"coordinates":[-81.1667,28.8333],"type":"Point"}
}