{
  "id": 2370407,
  "type": "Feature",
  "properties": {
    "tgn:hierarchy":[
        "tgn:2370407",
        "tgn:1000001",
        "tgn:7012149",
        "tgn:1002769",
        "tgn:7007826",
        "tgn:7029392"
    ],
    "tgn:id":2370407,
    "tgn:name":"H and H Lake",
    "tgn:placetype":[
        "aat:300006191"
    ]
},
  "bbox": [],
  "geometry": {"coordinates":[-94.45,32.1667],"type":"Point"}
}