{
  "id": 7572568,
  "type": "Feature",
  "properties": {
    "tgn:hierarchy":[
        "tgn:7572568",
        "tgn:1001828",
        "tgn:1000004",
        "tgn:7000198",
        "tgn:7029392"
    ],
    "tgn:id":7572568,
    "tgn:name:en":"Erraguntlakota",
    "tgn:placetype":[
        "aat:300008347"
    ]
},
  "bbox": [],
  "geometry": {"coordinates":[79.283333,13.966667],"type":"Point"}
}