{
  "id": 1132496,
  "type": "Feature",
  "properties": {
    "tgn:hierarchy":[
        "tgn:1132496",
        "tgn:1000001",
        "tgn:7012149",
        "tgn:7029392"
    ],
    "tgn:id":1132496,
    "tgn:name":"Bitter Creek",
    "tgn:placetype":[
        "aat:300008706"
    ]
},
  "bbox": [],
  "geometry": {"coordinates":[-105.6667,44.75],"type":"Point"}
}