{
  "id": 2440149,
  "type": "Feature",
  "properties": {
    "tgn:hierarchy":[
        "tgn:2440149",
        "tgn:1000001",
        "tgn:2000582",
        "tgn:7012149",
        "tgn:7007253",
        "tgn:7029392"
    ],
    "tgn:id":2440149,
    "tgn:name":"Kleinlein Creek",
    "tgn:placetype":[
        "aat:300008706"
    ]
},
  "bbox": [],
  "geometry": {"coordinates":[-91.5333,42.6833],"type":"Point"}
}