{
  "id": 7527720,
  "type": "Feature",
  "properties": {
    "tgn:hierarchy":[
        "tgn:7527720",
        "tgn:7001242",
        "tgn:7016833",
        "tgn:1001142",
        "tgn:7029392"
    ],
    "tgn:id":7527720,
    "tgn:name:en":"Umm al Jan\u0101z\u012br",
    "tgn:placetype":[
        "aat:300008347"
    ]
},
  "bbox": [],
  "geometry": {"coordinates":[31.019925,28.982946],"type":"Point"}
}