{
  "id": 2562389,
  "type": "Feature",
  "properties": {
    "tgn:hierarchy":[
        "tgn:2562389",
        "tgn:1000001",
        "tgn:7012149",
        "tgn:2002361",
        "tgn:7007922",
        "tgn:7029392"
    ],
    "tgn:id":2562389,
    "tgn:name":"Ottman Lake",
    "tgn:placetype":[
        "aat:300008680"
    ]
},
  "bbox": [],
  "geometry": {"coordinates":[-89.1667,44.3333],"type":"Point"}
}