{
  "id": 7075511,
  "type": "Feature",
  "properties": {
    "tgn:hierarchy":[
        "tgn:7075511",
        "tgn:7003669",
        "tgn:1000003",
        "tgn:7000084",
        "tgn:7029392"
    ],
    "tgn:id":7075511,
    "tgn:name":"Weigelsberg",
    "tgn:placetype":[
        "aat:300008795"
    ]
},
  "bbox": [],
  "geometry": {"coordinates":[12.959722,49.098333],"type":"Point"}
}