{
  "id": 7078649,
  "type": "Feature",
  "properties": {
    "tgn:hierarchy":[
        "tgn:7078649",
        "tgn:7000096",
        "tgn:1000003",
        "tgn:7000084",
        "tgn:7029392"
    ],
    "tgn:id":7078649,
    "tgn:name":"Wurzel-Berg",
    "tgn:placetype":[
        "aat:300008777"
    ]
},
  "bbox": [],
  "geometry": {"coordinates":[13.55,52.116667],"type":"Point"}
}