{
  "id": 2041247,
  "type": "Feature",
  "properties": {
    "tgn:hierarchy":[
        "tgn:2041247",
        "tgn:1000001",
        "tgn:7012149",
        "tgn:2000828",
        "tgn:7007255",
        "tgn:7029392"
    ],
    "tgn:id":2041247,
    "tgn:name":"Shady Grove",
    "tgn:placetype":[
        "aat:300008347",
        "aat:300387210"
    ]
},
  "bbox": [],
  "geometry": {"coordinates":[-85.6667,37.15],"type":"Point"}
}