{
  "id": 7218154,
  "type": "Feature",
  "properties": {
    "tgn:hierarchy":[
        "tgn:7218154",
        "tgn:7011330",
        "tgn:7002674",
        "tgn:1000003",
        "tgn:1000074",
        "tgn:7029392"
    ],
    "tgn:id":7218154,
    "tgn:name":"Trago\u00fasa, Vrachonis\u00edda",
    "tgn:placetype":[
        "aat:300008791"
    ]
},
  "bbox": [],
  "geometry": {"coordinates":[27.705833,36.2225],"type":"Point"}
}