{
  "id": 1031565,
  "type": "Feature",
  "properties": {
    "tgn:hierarchy":[
        "tgn:1031565",
        "tgn:1001475",
        "tgn:1000003",
        "tgn:1000069",
        "tgn:7029392"
    ],
    "tgn:id":1031565,
    "tgn:name":"Sotkamo",
    "tgn:placetype":[
        "aat:300008347"
    ]
},
  "bbox": [],
  "geometry": {"coordinates":[28.4667,64.1833],"type":"Point"}
}