{
  "id": 2508363,
  "type": "Feature",
  "properties": {
    "tgn:hierarchy":[
        "tgn:2508363",
        "tgn:1000001",
        "tgn:2001429",
        "tgn:7012149",
        "tgn:7007566",
        "tgn:7029392"
    ],
    "tgn:id":2508363,
    "tgn:name":"Middle Canyon Tank Number 1",
    "tgn:placetype":[
        "aat:300006191"
    ]
},
  "bbox": [],
  "geometry": {"coordinates":[-108.5833,33.75],"type":"Point"}
}