{
  "id": 7444466,
  "type": "Feature",
  "properties": {
    "tgn:hierarchy":[
        "tgn:7444466",
        "tgn:7002445",
        "tgn:1000003",
        "tgn:7008180",
        "tgn:7008591",
        "tgn:7029392"
    ],
    "tgn:id":7444466,
    "tgn:name:en":"Gastard",
    "tgn:placetype":[
        "aat:300008347"
    ]
},
  "bbox": [],
  "geometry": {"coordinates":[-2.166667,51.415833],"type":"Point"}
}