{
  "id": 7415361,
  "type": "Feature",
  "properties": {
    "tgn:hierarchy":[
        "tgn:7415361",
        "tgn:7005584",
        "tgn:1000001",
        "tgn:7005560",
        "tgn:7029392"
    ],
    "tgn:id":7415361,
    "tgn:name":"El Sauz",
    "tgn:placetype":[
        "aat:300008347"
    ]
},
  "bbox": [],
  "geometry": {"coordinates":[-100.138889,21.036667],"type":"Point"}
}