{
  "id": 2209652,
  "type": "Feature",
  "properties": {
    "tgn:hierarchy":[
        "tgn:2209652",
        "tgn:1000001",
        "tgn:2000922",
        "tgn:7012149",
        "tgn:7007515",
        "tgn:7029392"
    ],
    "tgn:id":2209652,
    "tgn:name":"Burrett Swamp",
    "tgn:placetype":[
        "aat:300008905"
    ]
},
  "bbox": [],
  "geometry": {"coordinates":[-68.55,44.4167],"type":"Point"}
}