{
  "id": 7401484,
  "type": "Feature",
  "properties": {
    "tgn:hierarchy":[
        "tgn:7401484",
        "tgn:1000001",
        "tgn:7005599",
        "tgn:7005560",
        "tgn:7029392"
    ],
    "tgn:id":7401484,
    "tgn:name":"El Naranjal",
    "tgn:placetype":[
        "aat:300008347"
    ]
},
  "bbox": [],
  "geometry": {"coordinates":[-94.416667,17.836111],"type":"Point"}
}