<<<<<<< HEAD
{
  "id": 2337664,
  "type": "Feature",
  "properties": {
    "tgn:hierarchy":[
        "tgn:2337664",
        "tgn:1000001",
        "tgn:2001703",
        "tgn:7012149",
        "tgn:7007708",
        "tgn:7029392"
    ],
    "tgn:id":2337664,
    "tgn:name":"Fox Canyon Creek",
    "tgn:placetype":[
        "aat:300008706"
    ]
},
  "bbox": [],
  "geometry": {"coordinates":[-120.2,44.2667],"type":"Point"}
}
=======
{"geometry":{"type":"Point","coordinates":[-120.200000,44.266700]},"type":"Feature","properties":{"hierarchy":["tgn:2337664","tgn:1000001","tgn:2001703","tgn:7012149","tgn:7007708","tgn:7029392"],"placetype":["aat:300008706"],"id":2337664,"name:xx":"Fox Canyon Creek"}}
>>>>>>> 03f74aca74312dbeaf24d7e61306dd6a786dc3d0
