<<<<<<< HEAD
{
  "id": 7367875,
  "type": "Feature",
  "properties": {
    "tgn:hierarchy":[
        "tgn:7367875",
        "tgn:1000001",
        "tgn:7005590",
        "tgn:7005560",
        "tgn:7029392"
    ],
    "tgn:id":7367875,
    "tgn:name":"Felipe Angeles",
    "tgn:placetype":[
        "aat:300008347"
    ]
},
  "bbox": [],
  "geometry": {"coordinates":[-102.666667,19.1],"type":"Point"}
}
=======
{"geometry":{"type":"Point","coordinates":[-102.666667,19.100000]},"type":"Feature","properties":{"hierarchy":["tgn:7367875","tgn:1000001","tgn:7005590","tgn:7005560","tgn:7029392"],"placetype":["aat:300008347"],"id":7367875,"name:xx":"Felipe Angeles"}}
>>>>>>> 03f74aca74312dbeaf24d7e61306dd6a786dc3d0
