{
  "id": 2211689,
  "type": "Feature",
  "properties": {
    "tgn:hierarchy":[
        "tgn:2211689",
        "tgn:1000001",
        "tgn:7012149",
        "tgn:2002348",
        "tgn:7007922",
        "tgn:7029392"
    ],
    "tgn:id":2211689,
    "tgn:name":"Butternut Lake",
    "tgn:placetype":[
        "aat:300008680"
    ]
},
  "bbox": [],
  "geometry": {"coordinates":[-90.5167,45.9667],"type":"Point"}
}