{
  "id": 2364935,
  "type": "Feature",
  "properties": {
    "tgn:hierarchy":[
        "tgn:2364935",
        "tgn:1000001",
        "tgn:7006451",
        "tgn:2000093",
        "tgn:7012149",
        "tgn:7029392"
    ],
    "tgn:id":2364935,
    "tgn:name":"Greenhorn Canyon",
    "tgn:placetype":[
        "aat:300008761"
    ]
},
  "bbox": [],
  "geometry": {"coordinates":[-111.5667,34.3167],"type":"Point"}
}