{
  "id": 7141772,
  "type": "Feature",
  "properties": {
    "tgn:hierarchy":[
        "tgn:7141772",
        "tgn:7003692",
        "tgn:1000003",
        "tgn:7000084",
        "tgn:7029392"
    ],
    "tgn:id":7141772,
    "tgn:name":"Mailand",
    "tgn:placetype":[
        "aat:300008347"
    ]
},
  "bbox": [],
  "geometry": {"coordinates":[10.016667,47.85],"type":"Point"}
}