{
  "id": 7175993,
  "type": "Feature",
  "properties": {
    "tgn:hierarchy":[
        "tgn:7175993",
        "tgn:1000003",
        "tgn:7003677",
        "tgn:7000084",
        "tgn:7029392"
    ],
    "tgn:id":7175993,
    "tgn:name":"Grevenbr\u00fcck",
    "tgn:placetype":[
        "aat:300008347"
    ]
},
  "bbox": [],
  "geometry": {"coordinates":[8.016667,51.133333],"type":"Point"}
}