{
  "id": 7190170,
  "type": "Feature",
  "properties": {
    "tgn:hierarchy":[
        "tgn:7190170",
        "tgn:1000003",
        "tgn:7003676",
        "tgn:7000084",
        "tgn:7029392"
    ],
    "tgn:id":7190170,
    "tgn:name":"Ellierode",
    "tgn:placetype":[
        "aat:300008347"
    ]
},
  "bbox": [],
  "geometry": {"coordinates":[10.066667,51.833333],"type":"Point"}
}