{
  "id": 2326070,
  "type": "Feature",
  "properties": {
    "tgn:hierarchy":[
        "tgn:2326070",
        "tgn:2001731",
        "tgn:1000001",
        "tgn:7012149",
        "tgn:7007712",
        "tgn:7029392"
    ],
    "tgn:id":2326070,
    "tgn:name":"Fig Island",
    "tgn:placetype":[
        "aat:300008791"
    ]
},
  "bbox": [],
  "geometry": {"coordinates":[-80.5667,32.4167],"type":"Point"}
}