{
  "id": 7343347,
  "type": "Feature",
  "properties": {
    "tgn:hierarchy":[
        "tgn:7343347",
        "tgn:7002815",
        "tgn:1000003",
        "tgn:7002793",
        "tgn:1000095",
        "tgn:7029392"
    ],
    "tgn:id":7343347,
    "tgn:name":"Cana, Rambla de la",
    "tgn:placetype":[
        "aat:300266554",
        "aat:300008699"
    ]
},
  "bbox": [],
  "geometry": {"coordinates":[-0.183333,40.566667],"type":"Point"}
}