<<<<<<< HEAD
{
  "id": 7485852,
  "type": "Feature",
  "properties": {
    "tgn:hierarchy":[
        "tgn:7485852",
        "tgn:1000004",
        "tgn:7004300",
        "tgn:1000141",
        "tgn:7029392"
    ],
    "tgn:id":7485852,
    "tgn:name":"Biwei",
    "tgn:placetype":[
        "aat:300386846"
    ]
},
  "bbox": [],
  "geometry": {"coordinates":[119.491111,23.353333],"type":"Point"}
}
=======
{"geometry":{"type":"Point","coordinates":[119.491111,23.353333]},"type":"Feature","properties":{"hierarchy":["tgn:7485852","tgn:1000004","tgn:7004300","tgn:1000141","tgn:7029392"],"placetype":["aat:300386846"],"id":7485852,"name:xx":"Biwei"}}
>>>>>>> 03f74aca74312dbeaf24d7e61306dd6a786dc3d0
