{
  "id": 2739613,
  "type": "Feature",
  "properties": {
    "tgn:hierarchy":[
        "tgn:2739613",
        "tgn:1000001",
        "tgn:7006451",
        "tgn:2000095",
        "tgn:7012149",
        "tgn:7029392"
    ],
    "tgn:id":2739613,
    "tgn:name":"Upper Cienega Spring",
    "tgn:placetype":[
        "aat:300008697"
    ]
},
  "bbox": [],
  "geometry": {"coordinates":[-109.1333,33.2833],"type":"Point"}
}