{
  "id": 7518701,
  "type": "Feature",
  "properties": {
    "tgn:hierarchy":[
        "tgn:7518701",
        "tgn:1009227",
        "tgn:1000226",
        "tgn:7018437",
        "tgn:1000006",
        "tgn:7029392"
    ],
    "tgn:id":7518701,
    "tgn:name:en":"Aviemore",
    "tgn:placetype":[
        "aat:300000206"
    ]
},
  "bbox": [],
  "geometry": {"coordinates":[170.233333,-44.616667],"type":"Point"}
}