{
  "id": 2561151,
  "type": "Feature",
  "properties": {
    "tgn:hierarchy":[
        "tgn:2561151",
        "tgn:1000001",
        "tgn:7012149",
        "tgn:2001454",
        "tgn:7007566",
        "tgn:7029392"
    ],
    "tgn:id":2561151,
    "tgn:name":"Ortiz",
    "tgn:placetype":[
        "aat:300008347",
        "aat:300167671"
    ]
},
  "bbox": [],
  "geometry": {"coordinates":[-106.15,35.3333],"type":"Point"}
}