{
  "id": 2191827,
  "type": "Feature",
  "properties": {
    "tgn:hierarchy":[
        "tgn:2191827",
        "tgn:2000661",
        "tgn:1000001",
        "tgn:7012149",
        "tgn:7007254",
        "tgn:7029392"
    ],
    "tgn:id":2191827,
    "tgn:name":"Bradshaw Creek",
    "tgn:placetype":[
        "aat:300008706"
    ]
},
  "bbox": [],
  "geometry": {"coordinates":[-95.2667,38.1333],"type":"Point"}
}