{
  "id": 2729661,
  "type": "Feature",
  "properties": {
    "tgn:hierarchy":[
        "tgn:2729661",
        "tgn:7006450",
        "tgn:1000001",
        "tgn:7012149",
        "tgn:2000088",
        "tgn:7029392"
    ],
    "tgn:id":2729661,
    "tgn:name":"Trouble Island",
    "tgn:placetype":[
        "aat:300008791"
    ]
},
  "bbox": [],
  "geometry": {"coordinates":[-133.6667,56.45],"type":"Point"}
}