{
  "id": 7003245,
  "type": "Feature",
  "properties": {
    "tgn:hierarchy":[
        "tgn:7003245",
        "tgn:7003029",
        "tgn:1000003",
        "tgn:1000062",
        "tgn:7029392"
    ],
    "tgn:id":7003245,
    "tgn:name":"Volders",
    "tgn:placetype":[
        "aat:300008347"
    ]
},
  "bbox": [],
  "geometry": {"coordinates":[11.5667,47.2833],"type":"Point"}
}