{
  "id": 2183236,
  "type": "Feature",
  "properties": {
    "tgn:hierarchy":[
        "tgn:2183236",
        "tgn:1000001",
        "tgn:7012149",
        "tgn:7007919",
        "tgn:7029392"
    ],
    "tgn:id":2183236,
    "tgn:name":"Bluestone Creek",
    "tgn:placetype":[
        "aat:300008706"
    ]
},
  "bbox": [],
  "geometry": {"coordinates":[-78.5167,36.8833],"type":"Point"}
}