{
  "id": 7445155,
  "type": "Feature",
  "properties": {
    "tgn:hierarchy":[
        "tgn:7445155",
        "tgn:7002444",
        "tgn:1000003",
        "tgn:7019152",
        "tgn:7008591",
        "tgn:7029392"
    ],
    "tgn:id":7445155,
    "tgn:name:en":"Trinafour",
    "tgn:placetype":[
        "aat:300008347"
    ]
},
  "bbox": [],
  "geometry": {"coordinates":[-4.083333,56.75],"type":"Point"}
}