<<<<<<< HEAD
{
  "id": 2401138,
  "type": "Feature",
  "properties": {
    "tgn:hierarchy":[
        "tgn:2401138",
        "tgn:1000001",
        "tgn:7012149",
        "tgn:2002382",
        "tgn:7007923",
        "tgn:7029392"
    ],
    "tgn:id":2401138,
    "tgn:name":"Horsefly Ditch",
    "tgn:placetype":[
        "aat:300006075"
    ]
},
  "bbox": [],
  "geometry": {"coordinates":[-110.1167,43.0],"type":"Point"}
}
=======
{"geometry":{"type":"Point","coordinates":[-110.116700,43.000000]},"type":"Feature","properties":{"hierarchy":["tgn:2401138","tgn:1000001","tgn:7012149","tgn:2002382","tgn:7007923","tgn:7029392"],"placetype":["aat:300006075"],"id":2401138,"name:xx":"Horsefly Ditch"}}
>>>>>>> 03f74aca74312dbeaf24d7e61306dd6a786dc3d0
