{
  "id": 2238807,
  "type": "Feature",
  "properties": {
    "tgn:hierarchy":[
        "tgn:2238807",
        "tgn:1000001",
        "tgn:7012149",
        "tgn:7007157",
        "tgn:1002791",
        "tgn:7029392"
    ],
    "tgn:id":2238807,
    "tgn:name":"Christian Valley",
    "tgn:placetype":[
        "aat:300008761"
    ]
},
  "bbox": [],
  "geometry": {"coordinates":[-121.0333,38.9667],"type":"Point"}
}