{
  "id": 7584385,
  "type": "Feature",
  "properties": {
    "tgn:hierarchy":[
        "tgn:7584385",
        "tgn:1000004",
        "tgn:7000198",
        "tgn:1001894",
        "tgn:7029392"
    ],
    "tgn:id":7584385,
    "tgn:name:en":"K\u0101nti",
    "tgn:placetype":[
        "aat:300008347"
    ]
},
  "bbox": [],
  "geometry": {"coordinates":[78.791195,24.836741],"type":"Point"}
}