{
  "id": 7204119,
  "type": "Feature",
  "properties": {
    "tgn:hierarchy":[
        "tgn:7204119",
        "tgn:1000003",
        "tgn:7003676",
        "tgn:7000084",
        "tgn:7029392"
    ],
    "tgn:id":7204119,
    "tgn:name":"F\u00f6rsterei Borstlerbrink",
    "tgn:placetype":[
        "aat:300004792"
    ]
},
  "bbox": [],
  "geometry": {"coordinates":[9.083333,52.35],"type":"Point"}
}