{
  "id": 1032134,
  "type": "Feature",
  "properties": {
    "tgn:hierarchy":[
        "tgn:1032134",
        "tgn:1000003",
        "tgn:7002890",
        "tgn:1000070",
        "tgn:7029392"
    ],
    "tgn:id":1032134,
    "tgn:name":"Betz",
    "tgn:placetype":[
        "aat:300008347"
    ]
},
  "bbox": [],
  "geometry": {"coordinates":[2.9833,49.15],"type":"Point"}
}