{
  "id": 2179519,
  "type": "Feature",
  "properties": {
    "tgn:hierarchy":[
        "tgn:2179519",
        "tgn:1000001",
        "tgn:7012149",
        "tgn:7007157",
        "tgn:7029392"
    ],
    "tgn:id":2179519,
    "tgn:name":"Blanco Mountain",
    "tgn:placetype":[
        "aat:300008798"
    ]
},
  "bbox": [],
  "geometry": {"coordinates":[-118.15,37.45],"type":"Point"}
}