{
  "id": 2298400,
  "type": "Feature",
  "properties": {
    "tgn:hierarchy":[
        "tgn:2298400",
        "tgn:1000001",
        "tgn:7012149",
        "tgn:1002701",
        "tgn:7007706",
        "tgn:7029392"
    ],
    "tgn:id":2298400,
    "tgn:name":"Dry Riffle Run",
    "tgn:placetype":[
        "aat:300008699"
    ]
},
  "bbox": [],
  "geometry": {"coordinates":[-81.8333,39.7667],"type":"Point"}
}