{
  "id": 1075428,
  "type": "Feature",
  "properties": {
    "tgn:hierarchy":[
        "tgn:1075428",
        "tgn:1000004",
        "tgn:7000198",
        "tgn:1001894",
        "tgn:7029392"
    ],
    "tgn:id":1075428,
    "tgn:name:en":"H\u0101t P\u012bplia",
    "tgn:placetype":[
        "aat:300008347"
    ]
},
  "bbox": [],
  "geometry": {"coordinates":[76.300471,22.76989],"type":"Point"}
}