{
  "id": 2673422,
  "type": "Feature",
  "properties": {
    "tgn:hierarchy":[
        "tgn:2673422",
        "tgn:1000001",
        "tgn:2000317",
        "tgn:7012149",
        "tgn:7007248",
        "tgn:7029392"
    ],
    "tgn:id":2673422,
    "tgn:name":"Snelling Pond",
    "tgn:placetype":[
        "aat:300006191"
    ]
},
  "bbox": [],
  "geometry": {"coordinates":[-84.7167,32.45],"type":"Point"}
}