{
  "id": 7286635,
  "type": "Feature",
  "properties": {
    "tgn:hierarchy":[
        "tgn:7286635",
        "tgn:1001702",
        "tgn:1000049",
        "tgn:1000002",
        "tgn:7029392"
    ],
    "tgn:id":7286635,
    "tgn:name":"Guffern, Islas",
    "tgn:placetype":[
        "aat:300008791"
    ]
},
  "bbox": [],
  "geometry": {"coordinates":[-68.066667,-55.433333],"type":"Point"}
}