{
  "id": 2052918,
  "type": "Feature",
  "properties": {
    "tgn:hierarchy":[
        "tgn:2052918",
        "tgn:1000001",
        "tgn:7012149",
        "tgn:1002737",
        "tgn:7007520",
        "tgn:7029392"
    ],
    "tgn:id":2052918,
    "tgn:name":"Oxbow",
    "tgn:placetype":[
        "aat:300008347"
    ]
},
  "bbox": [],
  "geometry": {"coordinates":[-83.4667,42.6333],"type":"Point"}
}