{
  "id": 2601646,
  "type": "Feature",
  "properties": {
    "tgn:hierarchy":[
        "tgn:2601646",
        "tgn:1000001",
        "tgn:7012149",
        "tgn:1002613",
        "tgn:7007710",
        "tgn:7029392"
    ],
    "tgn:id":2601646,
    "tgn:name":"Puterbaugh Mountain",
    "tgn:placetype":[
        "aat:300008798"
    ]
},
  "bbox": [],
  "geometry": {"coordinates":[-77.25,41.2833],"type":"Point"}
}