{
  "id": 2122894,
  "type": "Feature",
  "properties": {
    "tgn:hierarchy":[
        "tgn:2122894",
        "tgn:1000001",
        "tgn:2002370",
        "tgn:7012149",
        "tgn:7007923",
        "tgn:7029392"
    ],
    "tgn:id":2122894,
    "tgn:name":"Devils Tower",
    "tgn:placetype":[
        "aat:300008347"
    ]
},
  "bbox": [],
  "geometry": {"coordinates":[-104.6833,44.5833],"type":"Point"}
}