<<<<<<< HEAD
{
  "id": 2409245,
  "type": "Feature",
  "properties": {
    "tgn:hierarchy":[
        "tgn:2409245",
        "tgn:1000001",
        "tgn:2001412",
        "tgn:7012149",
        "tgn:7007526",
        "tgn:7029392"
    ],
    "tgn:id":2409245,
    "tgn:name":"Icehouse Canyon",
    "tgn:placetype":[
        "aat:300008761"
    ]
},
  "bbox": [],
  "geometry": {"coordinates":[-117.9167,37.7],"type":"Point"}
}
=======
{"geometry":{"type":"Point","coordinates":[-117.916700,37.700000]},"type":"Feature","properties":{"hierarchy":["tgn:2409245","tgn:1000001","tgn:2001412","tgn:7012149","tgn:7007526","tgn:7029392"],"placetype":["aat:300008761"],"id":2409245,"name:xx":"Icehouse Canyon"}}
>>>>>>> 03f74aca74312dbeaf24d7e61306dd6a786dc3d0
