{
  "id": 2320557,
  "type": "Feature",
  "properties": {
    "tgn:hierarchy":[
        "tgn:2320557",
        "tgn:1000001",
        "tgn:7012149",
        "tgn:7007920",
        "tgn:7029392"
    ],
    "tgn:id":2320557,
    "tgn:name":"Ewart Creek",
    "tgn:placetype":[
        "aat:300008706"
    ]
},
  "bbox": [],
  "geometry": {"coordinates":[-120.15,48.9833],"type":"Point"}
}