{
  "id": 2395579,
  "type": "Feature",
  "properties": {
    "tgn:hierarchy":[
        "tgn:2395579",
        "tgn:7002659",
        "tgn:1000001",
        "tgn:7012149",
        "tgn:7029392"
    ],
    "tgn:id":2395579,
    "tgn:name":"Holley Mill Creek",
    "tgn:placetype":[
        "aat:300008706"
    ]
},
  "bbox": [],
  "geometry": {"coordinates":[-86.0833,31.2167],"type":"Point"}
}