<<<<<<< HEAD
{
  "id": 2258261,
  "type": "Feature",
  "properties": {
    "tgn:hierarchy":[
        "tgn:2258261",
        "tgn:7014651",
        "tgn:1000001",
        "tgn:7012149",
        "tgn:7007516",
        "tgn:7029392"
    ],
    "tgn:id":2258261,
    "tgn:name":"Cottage Grove Beach",
    "tgn:placetype":[
        "aat:300008347"
    ]
},
  "bbox": [],
  "geometry": {"coordinates":[-76.5,39.15],"type":"Point"}
}
=======
{"geometry":{"type":"Point","coordinates":[-76.500000,39.150000]},"type":"Feature","properties":{"hierarchy":["tgn:2258261","tgn:7014651","tgn:1000001","tgn:7012149","tgn:7007516","tgn:7029392"],"placetype":["aat:300008347"],"id":2258261,"name:xx":"Cottage Grove Beach"}}
>>>>>>> 03f74aca74312dbeaf24d7e61306dd6a786dc3d0
