{
  "id": 2097734,
  "type": "Feature",
  "properties": {
    "tgn:hierarchy":[
        "tgn:2097734",
        "tgn:1000001",
        "tgn:7012149",
        "tgn:2001919",
        "tgn:7007825",
        "tgn:7029392"
    ],
    "tgn:id":2097734,
    "tgn:name":"Angeltown",
    "tgn:placetype":[
        "aat:300008347",
        "aat:300387210"
    ]
},
  "bbox": [],
  "geometry": {"coordinates":[-86.3333,36.5333],"type":"Point"}
}