{
  "id": 2516451,
  "type": "Feature",
  "properties": {
    "tgn:hierarchy":[
        "tgn:2516451",
        "tgn:1000001",
        "tgn:7012149",
        "tgn:2001455",
        "tgn:7007566",
        "tgn:7029392"
    ],
    "tgn:id":2516451,
    "tgn:name":"Mineral Creek",
    "tgn:placetype":[
        "aat:300008706"
    ]
},
  "bbox": [],
  "geometry": {"coordinates":[-107.7667,32.9667],"type":"Point"}
}