{
  "id": 7317363,
  "type": "Feature",
  "properties": {
    "tgn:hierarchy":[
        "tgn:7317363",
        "tgn:1001768",
        "tgn:1000049",
        "tgn:1000002",
        "tgn:7029392"
    ],
    "tgn:id":7317363,
    "tgn:name":"Chilicauqu\u00e9n, Rinc\u00f3n de",
    "tgn:placetype":[
        "aat:300008761"
    ]
},
  "bbox": [],
  "geometry": {"coordinates":[-70.983333,-32.516667],"type":"Point"}
}