{
  "id": 1025861,
  "type": "Feature",
  "properties": {
    "tgn:hierarchy":[
        "tgn:1025861",
        "tgn:7003025",
        "tgn:1000003",
        "tgn:1000062",
        "tgn:7029392"
    ],
    "tgn:id":1025861,
    "tgn:name":"Moosbrunn",
    "tgn:placetype":[
        "aat:300008347"
    ]
},
  "bbox": [],
  "geometry": {"coordinates":[16.4667,48.0167],"type":"Point"}
}