{
  "id": 7389014,
  "type": "Feature",
  "properties": {
    "tgn:hierarchy":[
        "tgn:7389014",
        "tgn:1000001",
        "tgn:1001960",
        "tgn:7005560",
        "tgn:7029392"
    ],
    "tgn:id":7389014,
    "tgn:name":"Pozo Verde",
    "tgn:placetype":[
        "aat:300008347"
    ]
},
  "bbox": [],
  "geometry": {"coordinates":[-111.633333,31.466667],"type":"Point"}
}