<<<<<<< HEAD
{
  "id": 2333706,
  "type": "Feature",
  "properties": {
    "tgn:hierarchy":[
        "tgn:2333706",
        "tgn:1000001",
        "tgn:7012149",
        "tgn:2001897",
        "tgn:7007825",
        "tgn:7029392"
    ],
    "tgn:id":2333706,
    "tgn:name":"Fooshee Peninsula",
    "tgn:placetype":[
        "aat:300008850"
    ]
},
  "bbox": [],
  "geometry": {"coordinates":[-84.75,35.6667],"type":"Point"}
}
=======
{"geometry":{"type":"Point","coordinates":[-84.750000,35.666700]},"type":"Feature","properties":{"hierarchy":["tgn:2333706","tgn:1000001","tgn:7012149","tgn:2001897","tgn:7007825","tgn:7029392"],"placetype":["aat:300008850"],"id":2333706,"name:xx":"Fooshee Peninsula"}}
>>>>>>> 03f74aca74312dbeaf24d7e61306dd6a786dc3d0
