{
  "id": 1129956,
  "type": "Feature",
  "properties": {
    "tgn:hierarchy":[
        "tgn:1129956",
        "tgn:1000004",
        "tgn:1000111",
        "tgn:7029392"
    ],
    "tgn:id":1129956,
    "tgn:name":"Shi He",
    "tgn:placetype":[
        "aat:300008707"
    ]
},
  "bbox": [],
  "geometry": {"coordinates":[114.4333,32.2833],"type":"Point"}
}