{
  "id": 7194669,
  "type": "Feature",
  "properties": {
    "tgn:hierarchy":[
        "tgn:7194669",
        "tgn:1000003",
        "tgn:7003689",
        "tgn:7000084",
        "tgn:7029392"
    ],
    "tgn:id":7194669,
    "tgn:name":"Dornheim",
    "tgn:placetype":[
        "aat:300008347"
    ]
},
  "bbox": [],
  "geometry": {"coordinates":[10.983333,50.833333],"type":"Point"}
}