{
  "id": 7201031,
  "type": "Feature",
  "properties": {
    "tgn:hierarchy":[
        "tgn:7201031",
        "tgn:1000003",
        "tgn:7003682",
        "tgn:7000084",
        "tgn:7029392"
    ],
    "tgn:id":7201031,
    "tgn:name":"Ehscheid",
    "tgn:placetype":[
        "aat:300008777"
    ]
},
  "bbox": [],
  "geometry": {"coordinates":[7.966667,49.35],"type":"Point"}
}