{
  "id": 7545644,
  "type": "Feature",
  "properties": {
    "tgn:hierarchy":[
        "tgn:7545644",
        "tgn:1000004",
        "tgn:7000198",
        "tgn:1001894",
        "tgn:7029392"
    ],
    "tgn:id":7545644,
    "tgn:name:en":"Barod",
    "tgn:placetype":[
        "aat:300008347"
    ]
},
  "bbox": [],
  "geometry": {"coordinates":[77.507802,24.367341],"type":"Point"}
}