{
  "id": 2080572,
  "type": "Feature",
  "properties": {
    "tgn:hierarchy":[
        "tgn:2080572",
        "tgn:1000001",
        "tgn:7012149",
        "tgn:1002627",
        "tgn:7007706",
        "tgn:7029392"
    ],
    "tgn:id":2080572,
    "tgn:name":"Maple Ridge",
    "tgn:placetype":[
        "aat:300008347"
    ]
},
  "bbox": [],
  "geometry": {"coordinates":[-81.05,40.9167],"type":"Point"}
}