{
  "id": 2037255,
  "type": "Feature",
  "properties": {
    "tgn:hierarchy":[
        "tgn:2037255",
        "tgn:1000001",
        "tgn:7012149",
        "tgn:2000722",
        "tgn:7007254",
        "tgn:7029392"
    ],
    "tgn:id":2037255,
    "tgn:name":"Tyro",
    "tgn:placetype":[
        "aat:300008347"
    ]
},
  "bbox": [],
  "geometry": {"coordinates":[-95.8167,37.0333],"type":"Point"}
}