{
  "id": 2318322,
  "type": "Feature",
  "properties": {
    "tgn:hierarchy":[
        "tgn:2318322",
        "tgn:1000001",
        "tgn:7012149",
        "tgn:2001765",
        "tgn:7007712",
        "tgn:7029392"
    ],
    "tgn:id":2318322,
    "tgn:name":"Ephriam Branch",
    "tgn:placetype":[
        "aat:300008699"
    ]
},
  "bbox": [],
  "geometry": {"coordinates":[-81.9167,34.0167],"type":"Point"}
}