{
  "id": 7199198,
  "type": "Feature",
  "properties": {
    "tgn:hierarchy":[
        "tgn:7199198",
        "tgn:1000003",
        "tgn:7003688",
        "tgn:7000084",
        "tgn:7029392"
    ],
    "tgn:id":7199198,
    "tgn:name":"Drelsdorfer Osterfeld",
    "tgn:placetype":[
        "aat:300008347"
    ]
},
  "bbox": [],
  "geometry": {"coordinates":[9.083333,54.616667],"type":"Point"}
}