{
  "id": 7381686,
  "type": "Feature",
  "properties": {
    "tgn:hierarchy":[
        "tgn:7381686",
        "tgn:1000001",
        "tgn:7005590",
        "tgn:7005560",
        "tgn:7029392"
    ],
    "tgn:id":7381686,
    "tgn:name":"Los Nogales",
    "tgn:placetype":[
        "aat:300008347"
    ]
},
  "bbox": [],
  "geometry": {"coordinates":[-102.15,19.85],"type":"Point"}
}