{
  "id": 2490774,
  "type": "Feature",
  "properties": {
    "tgn:hierarchy":[
        "tgn:2490774",
        "tgn:7023902",
        "tgn:1000001",
        "tgn:7012149",
        "tgn:7007249",
        "tgn:7029392"
    ],
    "tgn:id":2490774,
    "tgn:name":"Mano Point",
    "tgn:placetype":[
        "aat:300008850"
    ]
},
  "bbox": [],
  "geometry": {"coordinates":[-155.95,19.85],"type":"Point"}
}