{
  "id": 7519199,
  "type": "Feature",
  "properties": {
    "tgn:hierarchy":[
        "tgn:7519199",
        "tgn:1009227",
        "tgn:1000226",
        "tgn:7016822",
        "tgn:1000006",
        "tgn:1010303",
        "tgn:7029392"
    ],
    "tgn:id":7519199,
    "tgn:name:en":"Broughton Island",
    "tgn:placetype":[
        "aat:300008791"
    ]
},
  "bbox": [],
  "geometry": {"coordinates":[166.583333,-48.033333],"type":"Point"}
}