{
  "id": 2578716,
  "type": "Feature",
  "properties": {
    "tgn:hierarchy":[
        "tgn:2578716",
        "tgn:1000001",
        "tgn:7012149",
        "tgn:7007255",
        "tgn:7029392"
    ],
    "tgn:id":2578716,
    "tgn:name":"Phillips Creek",
    "tgn:placetype":[
        "aat:300008706"
    ]
},
  "bbox": [],
  "geometry": {"coordinates":[-83.5833,38.55],"type":"Point"}
}