{
  "id": 7560841,
  "type": "Feature",
  "properties": {
    "tgn:hierarchy":[
        "tgn:7560841",
        "tgn:1000004",
        "tgn:7000198",
        "tgn:7016722",
        "tgn:7029392"
    ],
    "tgn:id":7560841,
    "tgn:name:en":"Himmatpur",
    "tgn:placetype":[
        "aat:300008347"
    ]
},
  "bbox": [],
  "geometry": {"coordinates":[79.252229,26.42521],"type":"Point"}
}