{
  "id": 7570495,
  "type": "Feature",
  "properties": {
    "tgn:hierarchy":[
        "tgn:7570495",
        "tgn:1001828",
        "tgn:1000004",
        "tgn:7000198",
        "tgn:7029392"
    ],
    "tgn:id":7570495,
    "tgn:name:en":"Dharm\u0101ram",
    "tgn:placetype":[
        "aat:300008347"
    ]
},
  "bbox": [],
  "geometry": {"coordinates":[78.299167,17.907222],"type":"Point"}
}