{
  "id": 7589500,
  "type": "Feature",
  "properties": {
    "tgn:hierarchy":[
        "tgn:7589500",
        "tgn:1000004",
        "tgn:7000198",
        "tgn:7000799",
        "tgn:7029392"
    ],
    "tgn:id":7589500,
    "tgn:name:en":"Thal",
    "tgn:placetype":[
        "aat:300008347"
    ]
},
  "bbox": [],
  "geometry": {"coordinates":[74.974361,32.797192],"type":"Point"}
}