{
  "id": 1068748,
  "type": "Feature",
  "properties": {
    "tgn:hierarchy":[
        "tgn:1068748",
        "tgn:1000004",
        "tgn:7002076",
        "tgn:1000111",
        "tgn:7029392"
    ],
    "tgn:id":1068748,
    "tgn:name":"Hezhen",
    "tgn:placetype":[
        "aat:300008347"
    ]
},
  "bbox": [],
  "geometry": {"coordinates":[120.1667,29.9333],"type":"Point"}
}