{
  "id": 7444983,
  "type": "Feature",
  "properties": {
    "tgn:hierarchy":[
        "tgn:7444983",
        "tgn:7002443",
        "tgn:1000003",
        "tgn:7018993",
        "tgn:7008591",
        "tgn:7029392"
    ],
    "tgn:id":7444983,
    "tgn:name:en":"Tufton",
    "tgn:placetype":[
        "aat:300008347"
    ]
},
  "bbox": [],
  "geometry": {"coordinates":[-4.850556,51.918889],"type":"Point"}
}