{
  "id": 7425291,
  "type": "Feature",
  "properties": {
    "tgn:hierarchy":[
        "tgn:7425291",
        "tgn:7005581",
        "tgn:1000001",
        "tgn:7005560",
        "tgn:7029392"
    ],
    "tgn:id":7425291,
    "tgn:name":"San Pedro",
    "tgn:placetype":[
        "aat:300008347"
    ]
},
  "bbox": [],
  "geometry": {"coordinates":[-106.616667,27.133333],"type":"Point"}
}