{
  "id": 2108042,
  "type": "Feature",
  "properties": {
    "tgn:hierarchy":[
        "tgn:2108042",
        "tgn:1000001",
        "tgn:7012149",
        "tgn:2002029",
        "tgn:7007826",
        "tgn:7029392"
    ],
    "tgn:id":2108042,
    "tgn:name":"Three Rivers",
    "tgn:placetype":[
        "aat:300008347"
    ]
},
  "bbox": [],
  "geometry": {"coordinates":[-98.1667,28.45],"type":"Point"}
}