{
  "id": 2508396,
  "type": "Feature",
  "properties": {
    "tgn:hierarchy":[
        "tgn:2508396",
        "tgn:1000001",
        "tgn:7012149",
        "tgn:7007826",
        "tgn:7029392"
    ],
    "tgn:id":2508396,
    "tgn:name":"Middle Coffee Creek",
    "tgn:placetype":[
        "aat:300008706"
    ]
},
  "bbox": [],
  "geometry": {"coordinates":[-99.2333,33.85],"type":"Point"}
}