{
  "id": 7392500,
  "type": "Feature",
  "properties": {
    "tgn:hierarchy":[
        "tgn:7392500",
        "tgn:1000001",
        "tgn:7005589",
        "tgn:7005560",
        "tgn:7029392"
    ],
    "tgn:id":7392500,
    "tgn:name":"Rancho Los Nogales",
    "tgn:placetype":[
        "aat:300008347"
    ]
},
  "bbox": [],
  "geometry": {"coordinates":[-100.066667,24.883333],"type":"Point"}
}