<<<<<<< HEAD
{
  "id": 7176495,
  "type": "Feature",
  "properties": {
    "tgn:hierarchy":[
        "tgn:7176495",
        "tgn:1000003",
        "tgn:7003677",
        "tgn:7000084",
        "tgn:7029392"
    ],
    "tgn:id":7176495,
    "tgn:name":"H\u00e4hnchen",
    "tgn:placetype":[
        "aat:300008777"
    ]
},
  "bbox": [],
  "geometry": {"coordinates":[6.75,50.55],"type":"Point"}
}
=======
{"geometry":{"type":"Point","coordinates":[6.750000,50.550000]},"type":"Feature","properties":{"hierarchy":["tgn:7176495","tgn:1000003","tgn:7003677","tgn:7000084","tgn:7029392"],"placetype":["aat:300008777"],"id":7176495,"name:xx":"H\u00e4hnchen"}}
>>>>>>> 03f74aca74312dbeaf24d7e61306dd6a786dc3d0
