{
  "id": 7292895,
  "type": "Feature",
  "properties": {
    "tgn:hierarchy":[
        "tgn:7292895",
        "tgn:1001708",
        "tgn:1000049",
        "tgn:1000002",
        "tgn:7029392"
    ],
    "tgn:id":7292895,
    "tgn:name":"El Crucero",
    "tgn:placetype":[
        "aat:300008777"
    ]
},
  "bbox": [],
  "geometry": {"coordinates":[-71.416667,-33.916667],"type":"Point"}
}