{
  "id": 7334607,
  "type": "Feature",
  "properties": {
    "tgn:hierarchy":[
        "tgn:7334607",
        "tgn:1001439",
        "tgn:1000003",
        "tgn:7002797",
        "tgn:1000095",
        "tgn:7029392"
    ],
    "tgn:id":7334607,
    "tgn:name":"El Puerto",
    "tgn:placetype":[
        "aat:300008347"
    ]
},
  "bbox": [],
  "geometry": {"coordinates":[-1.25,37.566667],"type":"Point"}
}