{
  "id": 7592950,
  "type": "Feature",
  "properties": {
    "tgn:hierarchy":[
        "tgn:7592950",
        "tgn:1000004",
        "tgn:7000198",
        "tgn:7000799",
        "tgn:7029392"
    ],
    "tgn:id":7592950,
    "tgn:name:en":"N\u0101gbani",
    "tgn:placetype":[
        "aat:300008347"
    ]
},
  "bbox": [],
  "geometry": {"coordinates":[74.769016,32.780544],"type":"Point"}
}