{
  "id": 2632022,
  "type": "Feature",
  "properties": {
    "tgn:hierarchy":[
        "tgn:2632022",
        "tgn:1000001",
        "tgn:7012149",
        "tgn:1002263",
        "tgn:7007826",
        "tgn:7029392"
    ],
    "tgn:id":2632022,
    "tgn:name":"Rowe Branch",
    "tgn:placetype":[
        "aat:300008699"
    ]
},
  "bbox": [],
  "geometry": {"coordinates":[-95.15,31.8167],"type":"Point"}
}