{
  "id": 7519637,
  "type": "Feature",
  "properties": {
    "tgn:hierarchy":[
        "tgn:7519637",
        "tgn:1009227",
        "tgn:1000226",
        "tgn:7016729",
        "tgn:1000006",
        "tgn:7029392"
    ],
    "tgn:id":7519637,
    "tgn:name:en":"Bluff Creek",
    "tgn:placetype":[
        "aat:300008699"
    ]
},
  "bbox": [],
  "geometry": {"coordinates":[173.333333,-41.616667],"type":"Point"}
}