{
  "id": 7440277,
  "type": "Feature",
  "properties": {
    "tgn:hierarchy":[
        "tgn:7440277",
        "tgn:1000001",
        "tgn:7005591",
        "tgn:7005560",
        "tgn:7029392"
    ],
    "tgn:id":7440277,
    "tgn:name":"Santa Catarina Lachatao",
    "tgn:placetype":[
        "aat:300008347"
    ]
},
  "bbox": [],
  "geometry": {"coordinates":[-96.466667,17.25],"type":"Point"}
}