{
  "id": 2448543,
  "type": "Feature",
  "properties": {
    "tgn:hierarchy":[
        "tgn:2448543",
        "tgn:1000001",
        "tgn:7012149",
        "tgn:2000230",
        "tgn:7007158",
        "tgn:7029392"
    ],
    "tgn:id":2448543,
    "tgn:name":"Lily Lake",
    "tgn:placetype":[
        "aat:300006191"
    ]
},
  "bbox": [],
  "geometry": {"coordinates":[-107.95,39.0667],"type":"Point"}
}