{
  "id": 2280637,
  "type": "Feature",
  "properties": {
    "tgn:hierarchy":[
        "tgn:2280637",
        "tgn:1000001",
        "tgn:2001418",
        "tgn:7012149",
        "tgn:7007526",
        "tgn:7029392"
    ],
    "tgn:id":2280637,
    "tgn:name":"Deep Canyon",
    "tgn:placetype":[
        "aat:300008761"
    ]
},
  "bbox": [],
  "geometry": {"coordinates":[-117.55,39.0333],"type":"Point"}
}