{
  "id": 2422984,
  "type": "Feature",
  "properties": {
    "tgn:hierarchy":[
        "tgn:2422984",
        "tgn:7006450",
        "tgn:1000001",
        "tgn:7012149",
        "tgn:2000085",
        "tgn:7029392"
    ],
    "tgn:id":2422984,
    "tgn:name":"Joe Lake",
    "tgn:placetype":[
        "aat:300008680"
    ]
},
  "bbox": [],
  "geometry": {"coordinates":[-142.2667,63.1167],"type":"Point"}
}