{
  "id": 7073880,
  "type": "Feature",
  "properties": {
    "tgn:hierarchy":[
        "tgn:7073880",
        "tgn:1000003",
        "tgn:7003688",
        "tgn:7000084",
        "tgn:7029392"
    ],
    "tgn:id":7073880,
    "tgn:name":"S\u00fcderbrarupfeld",
    "tgn:placetype":[
        "aat:300000206"
    ]
},
  "bbox": [],
  "geometry": {"coordinates":[9.766667,54.633333],"type":"Point"}
}