{
  "id": 1097688,
  "type": "Feature",
  "properties": {
    "tgn:hierarchy":[
        "tgn:1097688",
        "tgn:7000490",
        "tgn:1000006",
        "tgn:7001830",
        "tgn:7029392"
    ],
    "tgn:id":1097688,
    "tgn:name":"Mulgowie",
    "tgn:placetype":[
        "aat:300008347"
    ]
},
  "bbox": [],
  "geometry": {"coordinates":[152.3667,-27.7333],"type":"Point"}
}