{
  "id": 2585654,
  "type": "Feature",
  "properties": {
    "tgn:hierarchy":[
        "tgn:2585654",
        "tgn:1000001",
        "tgn:7006451",
        "tgn:2000093",
        "tgn:7012149",
        "tgn:7029392"
    ],
    "tgn:id":2585654,
    "tgn:name":"Pioneer Mountain",
    "tgn:placetype":[
        "aat:300008798"
    ]
},
  "bbox": [],
  "geometry": {"coordinates":[-110.8333,33.2333],"type":"Point"}
}