{
  "id": 7498299,
  "type": "Feature",
  "properties": {
    "tgn:hierarchy":[
        "tgn:7498299",
        "tgn:7001004",
        "tgn:1000004",
        "tgn:1000141",
        "tgn:7029392"
    ],
    "tgn:id":7498299,
    "tgn:name":"Xiaofentian",
    "tgn:placetype":[
        "aat:300008347"
    ]
},
  "bbox": [],
  "geometry": {"coordinates":[120.574362,22.886127],"type":"Point"}
}