{
  "id": 7415480,
  "type": "Feature",
  "properties": {
    "tgn:hierarchy":[
        "tgn:7415480",
        "tgn:1000001",
        "tgn:7005591",
        "tgn:7005560",
        "tgn:7029392"
    ],
    "tgn:id":7415480,
    "tgn:name:es":"San Miguel",
    "tgn:placetype":[
        "aat:300008347"
    ]
},
  "bbox": [],
  "geometry": {"coordinates":[-96.123889,16.436944],"type":"Point"}
}