{
  "id": 7401219,
  "type": "Feature",
  "properties": {
    "tgn:hierarchy":[
        "tgn:7401219",
        "tgn:1000001",
        "tgn:7005599",
        "tgn:7005560",
        "tgn:7029392"
    ],
    "tgn:id":7401219,
    "tgn:name":"Tecuanapa",
    "tgn:placetype":[
        "aat:300008347"
    ]
},
  "bbox": [],
  "geometry": {"coordinates":[-97.133333,19.325],"type":"Point"}
}