{
  "id": 7276783,
  "type": "Feature",
  "properties": {
    "tgn:hierarchy":[
        "tgn:7276783",
        "tgn:1001699",
        "tgn:1000049",
        "tgn:1000002",
        "tgn:7029392"
    ],
    "tgn:id":7276783,
    "tgn:name":"R\u00edo Coquiao",
    "tgn:placetype":[
        "aat:300008699"
    ]
},
  "bbox": [],
  "geometry": {"coordinates":[-73.81,-41.939444],"type":"Point"}
}