{
  "id": 2713694,
  "type": "Feature",
  "properties": {
    "tgn:hierarchy":[
        "tgn:2713694",
        "tgn:1000001",
        "tgn:7012149",
        "tgn:1002502",
        "tgn:7007520",
        "tgn:7029392"
    ],
    "tgn:id":2713694,
    "tgn:name":"Teaspoon Hill",
    "tgn:placetype":[
        "aat:300008798"
    ]
},
  "bbox": [],
  "geometry": {"coordinates":[-84.4333,42.4667],"type":"Point"}
}