{
  "id": 7135265,
  "type": "Feature",
  "properties": {
    "tgn:hierarchy":[
        "tgn:7135265",
        "tgn:1000003",
        "tgn:7003688",
        "tgn:7000084",
        "tgn:7029392"
    ],
    "tgn:id":7135265,
    "tgn:name":"M\u00f6zen",
    "tgn:placetype":[
        "aat:300008347"
    ]
},
  "bbox": [],
  "geometry": {"coordinates":[10.25,53.916667],"type":"Point"}
}