{
  "id": 7022372,
  "type": "Feature",
  "properties": {
    "tgn:hierarchy":[
        "tgn:7022372",
        "tgn:1000001",
        "tgn:7012149",
        "tgn:7014097",
        "tgn:7007158",
        "tgn:7029392"
    ],
    "tgn:id":7022372,
    "tgn:name":"Bighorn Reservoir",
    "tgn:placetype":[
        "aat:300006191"
    ]
},
  "bbox": [],
  "geometry": {"coordinates":[-105.05,38.8167],"type":"Point"}
}