{
  "id": 7415741,
  "type": "Feature",
  "properties": {
    "tgn:hierarchy":[
        "tgn:7415741",
        "tgn:1000001",
        "tgn:7005591",
        "tgn:7005560",
        "tgn:7029392"
    ],
    "tgn:id":7415741,
    "tgn:name:es":"Piedra Liza",
    "tgn:placetype":[
        "aat:300008347"
    ]
},
  "bbox": [],
  "geometry": {"coordinates":[-97.522222,16.636111],"type":"Point"}
}