{
  "id": 2584489,
  "type": "Feature",
  "properties": {
    "tgn:hierarchy":[
        "tgn:2584489",
        "tgn:1002338",
        "tgn:1000001",
        "tgn:7012149",
        "tgn:7007516",
        "tgn:7029392"
    ],
    "tgn:id":2584489,
    "tgn:name":"Piney Island Cove",
    "tgn:placetype":[
        "aat:300132316"
    ]
},
  "bbox": [],
  "geometry": {"coordinates":[-76.0333,38.1833],"type":"Point"}
}