{
  "id": 7442845,
  "type": "Feature",
  "properties": {
    "tgn:hierarchy":[
        "tgn:7442845",
        "tgn:7002445",
        "tgn:1000003",
        "tgn:7008185",
        "tgn:7008591",
        "tgn:7029392"
    ],
    "tgn:id":7442845,
    "tgn:name:en":"Bawdsey Anchorage",
    "tgn:placetype":[
        "aat:300386968"
    ]
},
  "bbox": [],
  "geometry": {"coordinates":[1.533333,51.966667],"type":"Point"}
}