{
  "id": 2055763,
  "type": "Feature",
  "properties": {
    "tgn:hierarchy":[
        "tgn:2055763",
        "tgn:1000001",
        "tgn:7012149",
        "tgn:2001030",
        "tgn:7007521",
        "tgn:7029392"
    ],
    "tgn:id":2055763,
    "tgn:name":"Wilder",
    "tgn:placetype":[
        "aat:300008347"
    ]
},
  "bbox": [],
  "geometry": {"coordinates":[-95.1833,43.8167],"type":"Point"}
}