{
  "id": 7484902,
  "type": "Feature",
  "properties": {
    "tgn:hierarchy":[
        "tgn:7484902",
        "tgn:1000004",
        "tgn:7490934",
        "tgn:1000141",
        "tgn:7029392"
    ],
    "tgn:id":7484902,
    "tgn:name":"Xiaqiedong",
    "tgn:placetype":[
        "aat:300387033"
    ]
},
  "bbox": [],
  "geometry": {"coordinates":[120.375278,23.358889],"type":"Point"}
}