{
  "id": 7467601,
  "type": "Feature",
  "properties": {
    "tgn:hierarchy":[
        "tgn:7467601",
        "tgn:7001010",
        "tgn:1000004",
        "tgn:1000141",
        "tgn:7029392"
    ],
    "tgn:id":7467601,
    "tgn:name":"Asanglaijia",
    "tgn:placetype":[
        "aat:300132356"
    ]
},
  "bbox": [],
  "geometry": {"coordinates":[121.207778,23.379167],"type":"Point"}
}