{
  "id": 7274457,
  "type": "Feature",
  "properties": {
    "tgn:concordances":{
        "gn:id":"2743497"
    },
    "tgn:hierarchy":[
        "tgn:7274457",
        "tgn:7003619",
        "tgn:1000003",
        "tgn:7016845",
        "tgn:7029392"
    ],
    "tgn:id":7274457,
    "tgn:name:nl":"Zwiep",
    "tgn:placetype":[
        "aat:300008347"
    ]
},
  "bbox": [],
  "geometry": {"coordinates":[6.45,52.15],"type":"Point"}
}