{
  "id": 1008332,
  "type": "Feature",
  "properties": {
    "tgn:hierarchy":[
        "tgn:1008332",
        "tgn:1001188",
        "tgn:1010003",
        "tgn:1000233",
        "tgn:1000006",
        "tgn:7029392"
    ],
    "tgn:id":1008332,
    "tgn:name":"Nggela Sule",
    "tgn:placetype":[
        "aat:300008791"
    ]
},
  "bbox": [],
  "geometry": {"coordinates":[160.25,-9.0833],"type":"Point"}
}