<<<<<<< HEAD
{
  "id": 7364021,
  "type": "Feature",
  "properties": {
    "tgn:hierarchy":[
        "tgn:7364021",
        "tgn:1001853",
        "tgn:1000001",
        "tgn:7005560",
        "tgn:7029392"
    ],
    "tgn:id":7364021,
    "tgn:name":"El Barril",
    "tgn:placetype":[
        "aat:300008347"
    ]
},
  "bbox": [],
  "geometry": {"coordinates":[-101.116667,25.866667],"type":"Point"}
}
=======
{"geometry":{"type":"Point","coordinates":[-101.116667,25.866667]},"type":"Feature","properties":{"hierarchy":["tgn:7364021","tgn:1001853","tgn:1000001","tgn:7005560","tgn:7029392"],"placetype":["aat:300008347"],"id":7364021,"name:xx":"El Barril"}}
>>>>>>> 03f74aca74312dbeaf24d7e61306dd6a786dc3d0
