{
  "id": 7364021,
  "type": "Feature",
  "properties": {
    "tgn:hierarchy":[
        "tgn:7364021",
        "tgn:1001853",
        "tgn:1000001",
        "tgn:7005560",
        "tgn:7029392"
    ],
    "tgn:id":7364021,
    "tgn:name":"El Barril",
    "tgn:placetype":[
        "aat:300008347"
    ]
},
  "bbox": [],
  "geometry": {"coordinates":[-101.116667,25.866667],"type":"Point"}
}