{
  "id": 2246757,
  "type": "Feature",
  "properties": {
    "tgn:hierarchy":[
        "tgn:2246757",
        "tgn:1000001",
        "tgn:7016172",
        "tgn:7012149",
        "tgn:2000147",
        "tgn:7029392"
    ],
    "tgn:id":2246757,
    "tgn:name":"Coburn Brake",
    "tgn:placetype":[
        "aat:300008680"
    ]
},
  "bbox": [],
  "geometry": {"coordinates":[-91.7833,34.4833],"type":"Point"}
}