{
  "id": 7571285,
  "type": "Feature",
  "properties": {
    "tgn:hierarchy":[
        "tgn:7571285",
        "tgn:1000004",
        "tgn:1001832",
        "tgn:7000198",
        "tgn:7029392"
    ],
    "tgn:id":7571285,
    "tgn:name:en":"J\u0101muguri",
    "tgn:placetype":[
        "aat:300008347"
    ]
},
  "bbox": [],
  "geometry": {"coordinates":[93.963746,26.387402],"type":"Point"}
}