{
  "id": 7308810,
  "type": "Feature",
  "properties": {
    "tgn:hierarchy":[
        "tgn:7308810",
        "tgn:1001623",
        "tgn:1000049",
        "tgn:1000002",
        "tgn:7029392"
    ],
    "tgn:id":7308810,
    "tgn:name":"Magdalena",
    "tgn:placetype":[
        "aat:300000206"
    ]
},
  "bbox": [],
  "geometry": {"coordinates":[-71.55,-44.45],"type":"Point"}
}