{
  "id": 7587741,
  "type": "Feature",
  "properties": {
    "tgn:hierarchy":[
        "tgn:7587741",
        "tgn:1000004",
        "tgn:1001832",
        "tgn:7000198",
        "tgn:7029392"
    ],
    "tgn:id":7587741,
    "tgn:name:en":"Thindawl",
    "tgn:placetype":[
        "aat:300008347"
    ]
},
  "bbox": [],
  "geometry": {"coordinates":[92.700494,24.178275],"type":"Point"}
}