{
  "id": 2727752,
  "type": "Feature",
  "properties": {
    "tgn:hierarchy":[
        "tgn:2727752",
        "tgn:1000001",
        "tgn:7012149",
        "tgn:7007250",
        "tgn:7029392"
    ],
    "tgn:id":2727752,
    "tgn:name":"Trailer Lakes",
    "tgn:placetype":[
        "aat:300008680"
    ]
},
  "bbox": [],
  "geometry": {"coordinates":[-115.0667,44.15],"type":"Point"}
}