{
  "id": 7440687,
  "type": "Feature",
  "properties": {
    "tgn:hierarchy":[
        "tgn:7440687",
        "tgn:1000001",
        "tgn:7005591",
        "tgn:7005560",
        "tgn:7029392"
    ],
    "tgn:id":7440687,
    "tgn:name":"Santa Mar\u00eda",
    "tgn:placetype":[
        "aat:300008347"
    ]
},
  "bbox": [],
  "geometry": {"coordinates":[-95.233333,16.316667],"type":"Point"}
}