{
  "id": 2036173,
  "type": "Feature",
  "properties": {
    "tgn:hierarchy":[
        "tgn:2036173",
        "tgn:1000001",
        "tgn:7012149",
        "tgn:2000726",
        "tgn:7007254",
        "tgn:7029392"
    ],
    "tgn:id":2036173,
    "tgn:name":"Chanute",
    "tgn:placetype":[
        "aat:300008347"
    ]
},
  "bbox": [],
  "geometry": {"coordinates":[-95.45,37.6667],"type":"Point"}
}