{
  "id": 2475529,
  "type": "Feature",
  "properties": {
    "tgn:hierarchy":[
        "tgn:2475529",
        "tgn:1000001",
        "tgn:2001367",
        "tgn:7012149",
        "tgn:7007525",
        "tgn:7029392"
    ],
    "tgn:id":2475529,
    "tgn:name":"Luckey Creek",
    "tgn:placetype":[
        "aat:300008706"
    ]
},
  "bbox": [],
  "geometry": {"coordinates":[-99.6833,42.7667],"type":"Point"}
}