{
  "id": 7591025,
  "type": "Feature",
  "properties": {
    "tgn:hierarchy":[
        "tgn:7591025",
        "tgn:1000004",
        "tgn:7000198",
        "tgn:7000799",
        "tgn:7029392"
    ],
    "tgn:id":7591025,
    "tgn:name:en":"Pail",
    "tgn:placetype":[
        "aat:300008347"
    ]
},
  "bbox": [],
  "geometry": {"coordinates":[74.375,32.994444],"type":"Point"}
}