{
  "id": 1031320,
  "type": "Feature",
  "properties": {
    "tgn:hierarchy":[
        "tgn:1031320",
        "tgn:7024077",
        "tgn:1000003",
        "tgn:1000069",
        "tgn:7029392"
    ],
    "tgn:id":1031320,
    "tgn:name":"J\u00e4rvel\u00e4",
    "tgn:placetype":[
        "aat:300008347"
    ]
},
  "bbox": [],
  "geometry": {"coordinates":[25.2833,60.8667],"type":"Point"}
}