{
  "id": 2720159,
  "type": "Feature",
  "properties": {
    "tgn:hierarchy":[
        "tgn:2720159",
        "tgn:1000001",
        "tgn:7012149",
        "tgn:2002270",
        "tgn:7013961",
        "tgn:7029392"
    ],
    "tgn:id":2720159,
    "tgn:name":"Threemile Fork",
    "tgn:placetype":[
        "aat:300008699"
    ]
},
  "bbox": [],
  "geometry": {"coordinates":[-81.5333,38.45],"type":"Point"}
}