{
  "id": 7146828,
  "type": "Feature",
  "properties": {
    "tgn:hierarchy":[
        "tgn:7146828",
        "tgn:1000003",
        "tgn:7003678",
        "tgn:7000084",
        "tgn:7029392"
    ],
    "tgn:id":7146828,
    "tgn:name":"Konradsdorf",
    "tgn:placetype":[
        "aat:300000206"
    ]
},
  "bbox": [],
  "geometry": {"coordinates":[9.016667,50.35],"type":"Point"}
}