{
  "id": 2755608,
  "type": "Feature",
  "properties": {
    "tgn:hierarchy":[
        "tgn:2755608",
        "tgn:1000001",
        "tgn:7012149",
        "tgn:2001054",
        "tgn:7007521",
        "tgn:7029392"
    ],
    "tgn:id":2755608,
    "tgn:name":"Wedel Lake",
    "tgn:placetype":[
        "aat:300008680"
    ]
},
  "bbox": [],
  "geometry": {"coordinates":[-96.1333,46.35],"type":"Point"}
}