<<<<<<< HEAD
{
  "id": 7369582,
  "type": "Feature",
  "properties": {
    "tgn:hierarchy":[
        "tgn:7369582",
        "tgn:1001853",
        "tgn:1000001",
        "tgn:7005560",
        "tgn:7029392"
    ],
    "tgn:id":7369582,
    "tgn:name":"Kakanapo, Loma del",
    "tgn:placetype":[
        "aat:300008777"
    ]
},
  "bbox": [],
  "geometry": {"coordinates":[-101.183333,27.7],"type":"Point"}
}
=======
{"geometry":{"type":"Point","coordinates":[-101.183333,27.700000]},"type":"Feature","properties":{"hierarchy":["tgn:7369582","tgn:1001853","tgn:1000001","tgn:7005560","tgn:7029392"],"placetype":["aat:300008777"],"id":7369582,"name:xx":"Kakanapo, Loma del"}}
>>>>>>> 03f74aca74312dbeaf24d7e61306dd6a786dc3d0
