{
  "id": 1010653,
  "type": "Feature",
  "properties": {
    "tgn:hierarchy":[
        "tgn:1010653",
        "tgn:7030516",
        "tgn:7006450",
        "tgn:1000001",
        "tgn:7012149",
        "tgn:7029392"
    ],
    "tgn:id":1010653,
    "tgn:name":"East Cape",
    "tgn:placetype":[
        "aat:300008850"
    ]
},
  "bbox": [],
  "geometry": {"coordinates":[179.45,51.3667],"type":"Point"}
}