{
  "id": 7353240,
  "type": "Feature",
  "properties": {
    "tgn:hierarchy":[
        "tgn:7353240",
        "tgn:7005583",
        "tgn:1000001",
        "tgn:7005560",
        "tgn:7029392"
    ],
    "tgn:id":7353240,
    "tgn:name":"Anc\u00f3n",
    "tgn:placetype":[
        "aat:300008347"
    ]
},
  "bbox": [],
  "geometry": {"coordinates":[-105.166667,25.683333],"type":"Point"}
}