{
  "id": 1121423,
  "type": "Feature",
  "properties": {
    "tgn:hierarchy":[
        "tgn:1121423",
        "tgn:7000897",
        "tgn:1001040",
        "tgn:1000004",
        "tgn:1000120",
        "tgn:7029392"
    ],
    "tgn:id":1121423,
    "tgn:name":"Asa",
    "tgn:placetype":[
        "aat:300008707"
    ]
},
  "bbox": [],
  "geometry": {"coordinates":[131.15,34.0167],"type":"Point"}
}