<<<<<<< HEAD
{
  "id": 7023198,
  "type": "Feature",
  "properties": {
    "tgn:hierarchy":[
        "tgn:7023198",
        "tgn:7002870",
        "tgn:1000003",
        "tgn:1000070",
        "tgn:7029392"
    ],
    "tgn:id":7023198,
    "tgn:name":"Andlau",
    "tgn:placetype":[
        "aat:300008347"
    ]
},
  "bbox": [],
  "geometry": {"coordinates":[7.4167,48.3833],"type":"Point"}
}
=======
{"geometry":{"type":"Point","coordinates":[7.416700,48.383300]},"type":"Feature","properties":{"hierarchy":["tgn:7023198","tgn:7002870","tgn:1000003","tgn:1000070","tgn:7029392"],"placetype":["aat:300008347"],"id":7023198,"name:xx":"Andlau"}}
>>>>>>> 03f74aca74312dbeaf24d7e61306dd6a786dc3d0
