{
  "id": 2480975,
  "type": "Feature",
  "properties": {
    "tgn:hierarchy":[
        "tgn:2480975",
        "tgn:1000001",
        "tgn:2001786",
        "tgn:7012149",
        "tgn:7007713",
        "tgn:7029392"
    ],
    "tgn:id":2480975,
    "tgn:name":"Lakota Lake",
    "tgn:placetype":[
        "aat:300006191"
    ]
},
  "bbox": [],
  "geometry": {"coordinates":[-103.3833,43.85],"type":"Point"}
}