{
  "id": 2377492,
  "type": "Feature",
  "properties": {
    "tgn:hierarchy":[
        "tgn:2377492",
        "tgn:1000001",
        "tgn:7012149",
        "tgn:2001292",
        "tgn:7007524",
        "tgn:7029392"
    ],
    "tgn:id":2377492,
    "tgn:name":"Harper Coulee",
    "tgn:placetype":[
        "aat:300008761"
    ]
},
  "bbox": [],
  "geometry": {"coordinates":[-108.4833,46.2333],"type":"Point"}
}