{
  "id": 7220347,
  "type": "Feature",
  "properties": {
    "tgn:hierarchy":[
        "tgn:7220347",
        "tgn:7002706",
        "tgn:7002705",
        "tgn:1000003",
        "tgn:1000074",
        "tgn:7029392"
    ],
    "tgn:id":7220347,
    "tgn:name":"Giann\u00edtsion",
    "tgn:placetype":[
        "aat:300008347"
    ]
},
  "bbox": [],
  "geometry": {"coordinates":[21.1525,39.360833],"type":"Point"}
}