{
  "id": 2349146,
  "type": "Feature",
  "properties": {
    "tgn:hierarchy":[
        "tgn:2349146",
        "tgn:1000001",
        "tgn:7012149",
        "tgn:1002899",
        "tgn:7007920",
        "tgn:7029392"
    ],
    "tgn:id":2349146,
    "tgn:name":"Gilbert Creek",
    "tgn:placetype":[
        "aat:300008706"
    ]
},
  "bbox": [],
  "geometry": {"coordinates":[-121.6333,47.9833],"type":"Point"}
}