<<<<<<< HEAD
{
  "id": 7375882,
  "type": "Feature",
  "properties": {
    "tgn:hierarchy":[
        "tgn:7375882",
        "tgn:7005581",
        "tgn:1000001",
        "tgn:7005560",
        "tgn:7029392"
    ],
    "tgn:id":7375882,
    "tgn:name":"Rancho Las Tunas",
    "tgn:placetype":[
        "aat:300000241"
    ]
},
  "bbox": [],
  "geometry": {"coordinates":[-107.05,28.5],"type":"Point"}
}
=======
{"geometry":{"type":"Point","coordinates":[-107.050000,28.500000]},"type":"Feature","properties":{"hierarchy":["tgn:7375882","tgn:7005581","tgn:1000001","tgn:7005560","tgn:7029392"],"placetype":["aat:300000241"],"id":7375882,"name:xx":"Rancho Las Tunas"}}
>>>>>>> 03f74aca74312dbeaf24d7e61306dd6a786dc3d0
