{
  "id": 7208433,
  "type": "Feature",
  "properties": {
    "tgn:hierarchy":[
        "tgn:7208433",
        "tgn:1000003",
        "tgn:7003677",
        "tgn:7000084",
        "tgn:7029392"
    ],
    "tgn:id":7208433,
    "tgn:name":"Berg",
    "tgn:placetype":[
        "aat:300008347"
    ]
},
  "bbox": [],
  "geometry": {"coordinates":[6.133333,51.016667],"type":"Point"}
}