{
  "id": 2565108,
  "type": "Feature",
  "properties": {
    "tgn:hierarchy":[
        "tgn:2565108",
        "tgn:1000001",
        "tgn:7012149",
        "tgn:2001297",
        "tgn:7007524",
        "tgn:7029392"
    ],
    "tgn:id":2565108,
    "tgn:name":"Paget Reservoir Number Two",
    "tgn:placetype":[
        "aat:300006191"
    ]
},
  "bbox": [],
  "geometry": {"coordinates":[-106.1667,45.3833],"type":"Point"}
}