{
  "id": 7151595,
  "type": "Feature",
  "properties": {
    "tgn:hierarchy":[
        "tgn:7151595",
        "tgn:1000003",
        "tgn:7003685",
        "tgn:7000084",
        "tgn:7029392"
    ],
    "tgn:id":7151595,
    "tgn:name":"K\u00e4mpfer-Berge",
    "tgn:placetype":[
        "aat:300008777"
    ]
},
  "bbox": [],
  "geometry": {"coordinates":[14.833333,51.166667],"type":"Point"}
}