{
  "id": 1062556,
  "type": "Feature",
  "properties": {
    "tgn:hierarchy":[
        "tgn:1062556",
        "tgn:7001165",
        "tgn:1000003",
        "tgn:7002793",
        "tgn:1000095",
        "tgn:7029392"
    ],
    "tgn:id":1062556,
    "tgn:name":"Torre Baja",
    "tgn:placetype":[
        "aat:300008347"
    ]
},
  "bbox": [],
  "geometry": {"coordinates":[-1.25,40.116667],"type":"Point"}
}