<<<<<<< HEAD
{
  "id": 2252073,
  "type": "Feature",
  "properties": {
    "tgn:hierarchy":[
        "tgn:2252073",
        "tgn:1000001",
        "tgn:7012149",
        "tgn:2001716",
        "tgn:7007708",
        "tgn:7029392"
    ],
    "tgn:id":2252073,
    "tgn:name":"Condon Butte",
    "tgn:placetype":[
        "aat:300008798"
    ]
},
  "bbox": [],
  "geometry": {"coordinates":[-121.8333,44.2167],"type":"Point"}
}
=======
{"geometry":{"type":"Point","coordinates":[-121.833300,44.216700]},"type":"Feature","properties":{"hierarchy":["tgn:2252073","tgn:1000001","tgn:7012149","tgn:2001716","tgn:7007708","tgn:7029392"],"placetype":["aat:300008798"],"id":2252073,"name:xx":"Condon Butte"}}
>>>>>>> 03f74aca74312dbeaf24d7e61306dd6a786dc3d0
