{
  "id": 2619479,
  "type": "Feature",
  "properties": {
    "tgn:hierarchy":[
        "tgn:2619479",
        "tgn:2000195",
        "tgn:1000001",
        "tgn:7012149",
        "tgn:7007158",
        "tgn:7029392"
    ],
    "tgn:id":2619479,
    "tgn:name":"Rincon Bonito Canyon",
    "tgn:placetype":[
        "aat:300008761"
    ]
},
  "bbox": [],
  "geometry": {"coordinates":[-107.0667,37.0167],"type":"Point"}
}