{
  "id": 2650341,
  "type": "Feature",
  "properties": {
    "tgn:hierarchy":[
        "tgn:2650341",
        "tgn:1000001",
        "tgn:7012149",
        "tgn:1002767",
        "tgn:7007920",
        "tgn:7029392"
    ],
    "tgn:id":2650341,
    "tgn:name":"Seaport",
    "tgn:placetype":[
        "aat:300008347",
        "aat:300167671"
    ]
},
  "bbox": [],
  "geometry": {"coordinates":[-123.95,46.5833],"type":"Point"}
}