{
  "id": 7500067,
  "type": "Feature",
  "properties": {
    "tgn:hierarchy":[
        "tgn:7500067",
        "tgn:7001010",
        "tgn:1000004",
        "tgn:1000141",
        "tgn:7029392"
    ],
    "tgn:id":7500067,
    "tgn:name":"Yuancheng Xi",
    "tgn:placetype":[
        "aat:300008699"
    ]
},
  "bbox": [],
  "geometry": {"coordinates":[121.328049,23.321995],"type":"Point"}
}