<<<<<<< HEAD
{
  "id": 7362706,
  "type": "Feature",
  "properties": {
    "tgn:hierarchy":[
        "tgn:7362706",
        "tgn:1000001",
        "tgn:7005599",
        "tgn:7005560",
        "tgn:7029392"
    ],
    "tgn:id":7362706,
    "tgn:name":"El Marqu\u00e9s",
    "tgn:placetype":[
        "aat:300008347"
    ]
},
  "bbox": [],
  "geometry": {"coordinates":[-95.583333,18.523611],"type":"Point"}
}
=======
{"geometry":{"type":"Point","coordinates":[-95.583333,18.523611]},"type":"Feature","properties":{"hierarchy":["tgn:7362706","tgn:1000001","tgn:7005599","tgn:7005560","tgn:7029392"],"placetype":["aat:300008347"],"id":7362706,"name:xx":"El Marqu\u00e9s"}}
>>>>>>> 03f74aca74312dbeaf24d7e61306dd6a786dc3d0
