{
  "id": 2418186,
  "type": "Feature",
  "properties": {
    "tgn:hierarchy":[
        "tgn:2418186",
        "tgn:2000002",
        "tgn:7002659",
        "tgn:1000001",
        "tgn:7012149",
        "tgn:7029392"
    ],
    "tgn:id":2418186,
    "tgn:name":"Jacksons Pond",
    "tgn:placetype":[
        "aat:300006191"
    ]
},
  "bbox": [],
  "geometry": {"coordinates":[-85.6333,31.7333],"type":"Point"}
}