<<<<<<< HEAD
{
  "id": 2159575,
  "type": "Feature",
  "properties": {
    "tgn:hierarchy":[
        "tgn:2159575",
        "tgn:1000001",
        "tgn:7012149",
        "tgn:2001252",
        "tgn:7007523",
        "tgn:7029392"
    ],
    "tgn:id":2159575,
    "tgn:name":"Bee Rock Hollow",
    "tgn:placetype":[
        "aat:300008761"
    ]
},
  "bbox": [],
  "geometry": {"coordinates":[-91.7667,37.3167],"type":"Point"}
}
=======
{"geometry":{"type":"Point","coordinates":[-91.766700,37.316700]},"type":"Feature","properties":{"hierarchy":["tgn:2159575","tgn:1000001","tgn:7012149","tgn:2001252","tgn:7007523","tgn:7029392"],"placetype":["aat:300008761"],"id":2159575,"name:xx":"Bee Rock Hollow"}}
>>>>>>> 03f74aca74312dbeaf24d7e61306dd6a786dc3d0
