{
  "id": 7331690,
  "type": "Feature",
  "properties": {
    "tgn:hierarchy":[
        "tgn:7331690",
        "tgn:7001165",
        "tgn:1000003",
        "tgn:7002793",
        "tgn:1000095",
        "tgn:7029392"
    ],
    "tgn:id":7331690,
    "tgn:name":"La Pobleta",
    "tgn:placetype":[
        "aat:300008347"
    ]
},
  "bbox": [],
  "geometry": {"coordinates":[-0.816667,39.833333],"type":"Point"}
}