{
  "id": 7584126,
  "type": "Feature",
  "properties": {
    "tgn:hierarchy":[
        "tgn:7584126",
        "tgn:1000004",
        "tgn:7000198",
        "tgn:1001894",
        "tgn:7029392"
    ],
    "tgn:id":7584126,
    "tgn:name:en":"M\u0101ch\u012bgarh Reserved Forest",
    "tgn:placetype":[
        "aat:300008865"
    ]
},
  "bbox": [],
  "geometry": {"coordinates":[78.984434,24.955679],"type":"Point"}
}