{
  "id": 2104529,
  "type": "Feature",
  "properties": {
    "tgn:hierarchy":[
        "tgn:2104529",
        "tgn:1000001",
        "tgn:7012149",
        "tgn:2002089",
        "tgn:7007826",
        "tgn:7029392"
    ],
    "tgn:id":2104529,
    "tgn:name":"Grandfalls",
    "tgn:placetype":[
        "aat:300008347"
    ]
},
  "bbox": [],
  "geometry": {"coordinates":[-102.85,31.3333],"type":"Point"}
}