{
  "id": 7471940,
  "type": "Feature",
  "properties": {
    "tgn:hierarchy":[
        "tgn:7471940",
        "tgn:7001010",
        "tgn:1000004",
        "tgn:1000141",
        "tgn:7029392"
    ],
    "tgn:id":7471940,
    "tgn:name":"Chongde Suidao",
    "tgn:placetype":[
        "aat:300007899"
    ]
},
  "bbox": [],
  "geometry": {"coordinates":[121.662453,24.195952],"type":"Point"}
}