{
  "id": 2709818,
  "type": "Feature",
  "properties": {
    "tgn:hierarchy":[
        "tgn:2709818",
        "tgn:1000001",
        "tgn:7012149",
        "tgn:7007157",
        "tgn:1002828",
        "tgn:7029392"
    ],
    "tgn:id":2709818,
    "tgn:name":"Tahquitz Peak",
    "tgn:placetype":[
        "aat:300008798"
    ]
},
  "bbox": [],
  "geometry": {"coordinates":[-116.6667,33.75],"type":"Point"}
}