{
  "id": 7350668,
  "type": "Feature",
  "properties": {
    "tgn:hierarchy":[
        "tgn:7350668",
        "tgn:1000001",
        "tgn:7005595",
        "tgn:7005560",
        "tgn:7029392"
    ],
    "tgn:id":7350668,
    "tgn:name":"Baila",
    "tgn:placetype":[
        "aat:300008347"
    ]
},
  "bbox": [],
  "geometry": {"coordinates":[-106.972778,24.182778],"type":"Point"}
}