{
  "id": 2359475,
  "type": "Feature",
  "properties": {
    "tgn:hierarchy":[
        "tgn:2359475",
        "tgn:1000001",
        "tgn:2002107",
        "tgn:7012149",
        "tgn:7007827",
        "tgn:7029392"
    ],
    "tgn:id":2359475,
    "tgn:name":"Grant Hansen Reservoir Number Three",
    "tgn:placetype":[
        "aat:300006191"
    ]
},
  "bbox": [],
  "geometry": {"coordinates":[-110.2667,40.2333],"type":"Point"}
}