<<<<<<< HEAD
{
  "id": 7373059,
  "type": "Feature",
  "properties": {
    "tgn:hierarchy":[
        "tgn:7373059",
        "tgn:7005581",
        "tgn:1000001",
        "tgn:7005560",
        "tgn:7029392"
    ],
    "tgn:id":7373059,
    "tgn:name":"La Chata",
    "tgn:placetype":[
        "aat:300008347"
    ]
},
  "bbox": [],
  "geometry": {"coordinates":[-101.85,26.65],"type":"Point"}
}
=======
{"geometry":{"type":"Point","coordinates":[-101.850000,26.650000]},"type":"Feature","properties":{"hierarchy":["tgn:7373059","tgn:7005581","tgn:1000001","tgn:7005560","tgn:7029392"],"placetype":["aat:300008347"],"id":7373059,"name:xx":"La Chata"}}
>>>>>>> 03f74aca74312dbeaf24d7e61306dd6a786dc3d0
