{
  "id": 7338377,
  "type": "Feature",
  "properties": {
    "tgn:hierarchy":[
        "tgn:7338377",
        "tgn:7002849",
        "tgn:1000003",
        "tgn:7009604",
        "tgn:1000095",
        "tgn:7029392"
    ],
    "tgn:id":7338377,
    "tgn:name":"Cazanes",
    "tgn:placetype":[
        "aat:300008347"
    ]
},
  "bbox": [],
  "geometry": {"coordinates":[-5.45,43.483333],"type":"Point"}
}