{
  "id": 2547649,
  "type": "Feature",
  "properties": {
    "tgn:hierarchy":[
        "tgn:2547649",
        "tgn:1000001",
        "tgn:7012149",
        "tgn:2000203",
        "tgn:7007158",
        "tgn:7029392"
    ],
    "tgn:id":2547649,
    "tgn:name":"North Fork Trinchera Creek",
    "tgn:placetype":[
        "aat:300008706"
    ]
},
  "bbox": [],
  "geometry": {"coordinates":[-105.1667,37.3667],"type":"Point"}
}