{
  "id": 7117466,
  "type": "Feature",
  "properties": {
    "tgn:hierarchy":[
        "tgn:7117466",
        "tgn:7003669",
        "tgn:1000003",
        "tgn:7000084",
        "tgn:7029392"
    ],
    "tgn:id":7117466,
    "tgn:name":"Obersteinbach",
    "tgn:placetype":[
        "aat:300008347"
    ]
},
  "bbox": [],
  "geometry": {"coordinates":[11.433333,47.716667],"type":"Point"}
}