<<<<<<< HEAD
{
  "id": 7056082,
  "type": "Feature",
  "properties": {
    "tgn:hierarchy":[
        "tgn:7056082",
        "tgn:1003440",
        "tgn:1000003",
        "tgn:7003124",
        "tgn:1000080",
        "tgn:7029392"
    ],
    "tgn:id":7056082,
    "tgn:name":"Mezzaselva",
    "tgn:placetype":[
        "aat:300008347"
    ]
},
  "bbox": [],
  "geometry": {"coordinates":[11.566667,46.8],"type":"Point"}
}
=======
{"geometry":{"type":"Point","coordinates":[11.566667,46.800000]},"type":"Feature","properties":{"hierarchy":["tgn:7056082","tgn:1003440","tgn:1000003","tgn:7003124","tgn:1000080","tgn:7029392"],"placetype":["aat:300008347"],"id":7056082,"name:xx":"Mezzaselva"}}
>>>>>>> 03f74aca74312dbeaf24d7e61306dd6a786dc3d0
