{
  "id": 1097288,
  "type": "Feature",
  "properties": {
    "tgn:hierarchy":[
        "tgn:1097288",
        "tgn:7000490",
        "tgn:1000006",
        "tgn:7006238",
        "tgn:7029392"
    ],
    "tgn:id":1097288,
    "tgn:name":"Kooyong",
    "tgn:placetype":[
        "aat:300008347"
    ]
},
  "bbox": [],
  "geometry": {"coordinates":[145.0333,-37.8333],"type":"Point"}
}