{
  "id": 2123163,
  "type": "Feature",
  "properties": {
    "tgn:hierarchy":[
        "tgn:2123163",
        "tgn:1000001",
        "tgn:7012149",
        "tgn:2002381",
        "tgn:7007923",
        "tgn:7029392"
    ],
    "tgn:id":2123163,
    "tgn:name":"Sheridan",
    "tgn:placetype":[
        "aat:300008347"
    ]
},
  "bbox": [],
  "geometry": {"coordinates":[-106.95,44.7833],"type":"Point"}
}