{
  "id": 7331477,
  "type": "Feature",
  "properties": {
    "tgn:hierarchy":[
        "tgn:7331477",
        "tgn:7002759",
        "tgn:7002843",
        "tgn:1000003",
        "tgn:1000095",
        "tgn:7029392"
    ],
    "tgn:id":7331477,
    "tgn:name":"La Puebla de Valverde",
    "tgn:placetype":[
        "aat:300008347"
    ]
},
  "bbox": [],
  "geometry": {"coordinates":[-0.916667,40.216667],"type":"Point"}
}