{
  "id": 7256510,
  "type": "Feature",
  "properties": {
    "tgn:hierarchy":[
        "tgn:7256510",
        "tgn:7003461",
        "tgn:1000003",
        "tgn:1000063",
        "tgn:7018236",
        "tgn:7029392"
    ],
    "tgn:id":7256510,
    "tgn:name":"Wiemismeer",
    "tgn:placetype":[
        "aat:300008347"
    ]
},
  "bbox": [],
  "geometry": {"coordinates":[5.566667,50.95],"type":"Point"}
}