{
  "id": 2535605,
  "type": "Feature",
  "properties": {
    "tgn:hierarchy":[
        "tgn:2535605",
        "tgn:1000001",
        "tgn:2002366",
        "tgn:7012149",
        "tgn:7007923",
        "tgn:7029392"
    ],
    "tgn:id":2535605,
    "tgn:name":"Narrows River, The",
    "tgn:placetype":[
        "aat:300008699"
    ]
},
  "bbox": [],
  "geometry": {"coordinates":[-108.2167,44.9333],"type":"Point"}
}