{
  "id": 2749298,
  "type": "Feature",
  "properties": {
    "tgn:hierarchy":[
        "tgn:2749298",
        "tgn:1000001",
        "tgn:7012149",
        "tgn:1003008",
        "tgn:7007710",
        "tgn:7029392"
    ],
    "tgn:id":2749298,
    "tgn:name":"Wallerville Pond",
    "tgn:placetype":[
        "aat:300008680"
    ]
},
  "bbox": [],
  "geometry": {"coordinates":[-75.2667,41.85],"type":"Point"}
}