{
  "id": 7518633,
  "type": "Feature",
  "properties": {
    "tgn:hierarchy":[
        "tgn:7518633",
        "tgn:7000508",
        "tgn:1008380",
        "tgn:1000226",
        "tgn:1000006",
        "tgn:7029392"
    ],
    "tgn:id":7518633,
    "tgn:name:en":"Awhitu Central",
    "tgn:placetype":[
        "aat:300008347"
    ]
},
  "bbox": [],
  "geometry": {"coordinates":[174.583333,-37.083333],"type":"Point"}
}