<<<<<<< HEAD
{
  "id": 2409989,
  "type": "Feature",
  "properties": {
    "tgn:hierarchy":[
        "tgn:2409989",
        "tgn:1000001",
        "tgn:7012149",
        "tgn:2000182",
        "tgn:7007157",
        "tgn:7029392"
    ],
    "tgn:id":2409989,
    "tgn:name":"Imperial Waterfowl Management Area",
    "tgn:placetype":[
        "aat:300055621"
    ]
},
  "bbox": [],
  "geometry": {"coordinates":[-115.5,33.0667],"type":"Point"}
}
=======
{"geometry":{"type":"Point","coordinates":[-115.500000,33.066700]},"type":"Feature","properties":{"hierarchy":["tgn:2409989","tgn:1000001","tgn:7012149","tgn:2000182","tgn:7007157","tgn:7029392"],"placetype":["aat:300055621"],"id":2409989,"name:xx":"Imperial Waterfowl Management Area"}}
>>>>>>> 03f74aca74312dbeaf24d7e61306dd6a786dc3d0
