<<<<<<< HEAD
{
  "id": 2762617,
  "type": "Feature",
  "properties": {
    "tgn:hierarchy":[
        "tgn:2762617",
        "tgn:1000001",
        "tgn:7012149",
        "tgn:1002690",
        "tgn:7007710",
        "tgn:7029392"
    ],
    "tgn:id":2762617,
    "tgn:name":"Westbury",
    "tgn:placetype":[
        "aat:300008347"
    ]
},
  "bbox": [],
  "geometry": {"coordinates":[-75.1,40.15],"type":"Point"}
}
=======
{"geometry":{"type":"Point","coordinates":[-75.100000,40.150000]},"type":"Feature","properties":{"hierarchy":["tgn:2762617","tgn:1000001","tgn:7012149","tgn:1002690","tgn:7007710","tgn:7029392"],"placetype":["aat:300008347"],"id":2762617,"name:xx":"Westbury"}}
>>>>>>> 03f74aca74312dbeaf24d7e61306dd6a786dc3d0
