{
  "id": 1120014,
  "type": "Feature",
  "properties": {
    "tgn:hierarchy":[
        "tgn:1120014",
        "tgn:1000004",
        "tgn:7011573",
        "tgn:7018214",
        "tgn:7002435",
        "tgn:7029392"
    ],
    "tgn:id":1120014,
    "tgn:name":"Klyaz'minskoye Vodokhranilishche",
    "tgn:placetype":[
        "aat:300006191"
    ]
},
  "bbox": [],
  "geometry": {"coordinates":[37.5833,55.9833],"type":"Point"}
}