{
  "id": 2342516,
  "type": "Feature",
  "properties": {
    "tgn:hierarchy":[
        "tgn:2342516",
        "tgn:1000001",
        "tgn:7012149",
        "tgn:2002163",
        "tgn:7007919",
        "tgn:7029392"
    ],
    "tgn:id":2342516,
    "tgn:name":"Fullstream, Lake",
    "tgn:placetype":[
        "aat:300006191"
    ]
},
  "bbox": [],
  "geometry": {"coordinates":[-77.75,37.65],"type":"Point"}
}