{
  "id": 2034372,
  "type": "Feature",
  "properties": {
    "tgn:hierarchy":[
        "tgn:2034372",
        "tgn:1000001",
        "tgn:7012149",
        "tgn:2000633",
        "tgn:7007253",
        "tgn:7029392"
    ],
    "tgn:id":2034372,
    "tgn:name":"Blanchard",
    "tgn:placetype":[
        "aat:300008347"
    ]
},
  "bbox": [],
  "geometry": {"coordinates":[-95.2167,40.5667],"type":"Point"}
}