{
  "id": 2720581,
  "type": "Feature",
  "properties": {
    "tgn:hierarchy":[
        "tgn:2720581",
        "tgn:1000001",
        "tgn:7012149",
        "tgn:2002125",
        "tgn:7007827",
        "tgn:7029392"
    ],
    "tgn:id":2720581,
    "tgn:name":"Thurber Ridge",
    "tgn:placetype":[
        "aat:300266640"
    ]
},
  "bbox": [],
  "geometry": {"coordinates":[-111.5667,40.0167],"type":"Point"}
}