{
  "id": 7288314,
  "type": "Feature",
  "properties": {
    "tgn:hierarchy":[
        "tgn:7288314",
        "tgn:1001768",
        "tgn:1000049",
        "tgn:1000002",
        "tgn:7029392"
    ],
    "tgn:id":7288314,
    "tgn:name":"La Champa",
    "tgn:placetype":[
        "aat:300008347"
    ]
},
  "bbox": [],
  "geometry": {"coordinates":[-71.133333,-32.85],"type":"Point"}
}