{
  "id": 2673546,
  "type": "Feature",
  "properties": {
    "tgn:hierarchy":[
        "tgn:2673546",
        "tgn:1000001",
        "tgn:7012149",
        "tgn:2001197",
        "tgn:7007523",
        "tgn:7029392"
    ],
    "tgn:id":2673546,
    "tgn:name":"Snipe Slough",
    "tgn:placetype":[
        "aat:300008699"
    ]
},
  "bbox": [],
  "geometry": {"coordinates":[-90.05,36.2333],"type":"Point"}
}