{
  "id": 7562107,
  "type": "Feature",
  "properties": {
    "tgn:hierarchy":[
        "tgn:7562107",
        "tgn:1000004",
        "tgn:7000198",
        "tgn:7016722",
        "tgn:7029392"
    ],
    "tgn:id":7562107,
    "tgn:name:en":"Lakhanpura",
    "tgn:placetype":[
        "aat:300008347"
    ]
},
  "bbox": [],
  "geometry": {"coordinates":[79.180655,26.825361],"type":"Point"}
}