{
  "id": 1030363,
  "type": "Feature",
  "properties": {
    "tgn:hierarchy":[
        "tgn:1030363",
        "tgn:7002445",
        "tgn:7008114",
        "tgn:1000003",
        "tgn:7008591",
        "tgn:7029392"
    ],
    "tgn:id":1030363,
    "tgn:name:en":"Poynton",
    "tgn:placetype":[
        "aat:300008347"
    ]
},
  "bbox": [],
  "geometry": {"coordinates":[-2.116667,53.35],"type":"Point"}
}