{
  "id": 1099947,
  "type": "Feature",
  "properties": {
    "tgn:hierarchy":[
        "tgn:1099947",
        "tgn:1000001",
        "tgn:1001937",
        "tgn:7005560",
        "tgn:7029392"
    ],
    "tgn:id":1099947,
    "tgn:name:en":"Tulum, Ruinas de",
    "tgn:placetype":[
        "aat:300008347",
        "aat:300387007",
        "aat:300000810",
        "aat:300167671"
    ]
},
  "bbox": [],
  "geometry": {"coordinates":[-87.466667,20.216667],"type":"Point"}
}