{
  "id": 7414376,
  "type": "Feature",
  "properties": {
    "tgn:hierarchy":[
        "tgn:7414376",
        "tgn:7005580",
        "tgn:1000001",
        "tgn:7005560",
        "tgn:7029392"
    ],
    "tgn:id":7414376,
    "tgn:name":"El P\u00e1jaro, Cord\u00f3n",
    "tgn:placetype":[
        "aat:300008795"
    ]
},
  "bbox": [],
  "geometry": {"coordinates":[-93.883333,16.958333],"type":"Point"}
}