{
  "id": 2590629,
  "type": "Feature",
  "properties": {
    "tgn:hierarchy":[
        "tgn:2590629",
        "tgn:1000001",
        "tgn:7012149",
        "tgn:2002374",
        "tgn:7007923",
        "tgn:7029392"
    ],
    "tgn:id":2590629,
    "tgn:name":"Pole Creek",
    "tgn:placetype":[
        "aat:300008706"
    ]
},
  "bbox": [],
  "geometry": {"coordinates":[-106.9833,44.1833],"type":"Point"}
}