{
  "id": 7109715,
  "type": "Feature",
  "properties": {
    "tgn:hierarchy":[
        "tgn:7109715",
        "tgn:1000003",
        "tgn:7003678",
        "tgn:7000084",
        "tgn:7029392"
    ],
    "tgn:id":7109715,
    "tgn:name":"Quast",
    "tgn:placetype":[
        "aat:300008777"
    ]
},
  "bbox": [],
  "geometry": {"coordinates":[9.033333,51.483333],"type":"Point"}
}