{
  "id": 7462501,
  "type": "Feature",
  "properties": {
    "tgn:hierarchy":[
        "tgn:7462501",
        "tgn:7002445",
        "tgn:1000003",
        "tgn:7008155",
        "tgn:7008591",
        "tgn:7029392"
    ],
    "tgn:id":7462501,
    "tgn:name:en":"Higham on the Hill",
    "tgn:placetype":[
        "aat:300008347"
    ]
},
  "bbox": [],
  "geometry": {"coordinates":[-1.433333,52.55],"type":"Point"}
}