{
  "id": 7375119,
  "type": "Feature",
  "properties": {
    "tgn:hierarchy":[
        "tgn:7375119",
        "tgn:7005583",
        "tgn:1000001",
        "tgn:7005560",
        "tgn:7029392"
    ],
    "tgn:id":7375119,
    "tgn:name":"La Puerta de Cabrera",
    "tgn:placetype":[
        "aat:300008347"
    ]
},
  "bbox": [],
  "geometry": {"coordinates":[-105.25,26.05],"type":"Point"}
}