{
  "id": 2106975,
  "type": "Feature",
  "properties": {
    "tgn:hierarchy":[
        "tgn:2106975",
        "tgn:1000001",
        "tgn:7012149",
        "tgn:2002002",
        "tgn:7007826",
        "tgn:7029392"
    ],
    "tgn:id":2106975,
    "tgn:name":"Puerto Rico",
    "tgn:placetype":[
        "aat:300008347",
        "aat:300387210"
    ]
},
  "bbox": [],
  "geometry": {"coordinates":[-98.3333,26.6333],"type":"Point"}
}