{
  "id": 7583208,
  "type": "Feature",
  "properties": {
    "tgn:hierarchy":[
        "tgn:7583208",
        "tgn:1000004",
        "tgn:7000198",
        "tgn:7016722",
        "tgn:7029392"
    ],
    "tgn:id":7583208,
    "tgn:name:en":"Kachnoda Minor",
    "tgn:placetype":[
        "aat:300006075"
    ]
},
  "bbox": [],
  "geometry": {"coordinates":[78.530794,24.724375],"type":"Point"}
}