{
  "id": 7284146,
  "type": "Feature",
  "properties": {
    "tgn:hierarchy":[
        "tgn:7284146",
        "tgn:1001699",
        "tgn:1000049",
        "tgn:1000002",
        "tgn:7029392"
    ],
    "tgn:id":7284146,
    "tgn:name":"Puntiagudo, Cerro",
    "tgn:placetype":[
        "aat:300008795"
    ]
},
  "bbox": [],
  "geometry": {"coordinates":[-72.266667,-40.966667],"type":"Point"}
}