{
  "id": 7512163,
  "type": "Feature",
  "properties": {
    "tgn:hierarchy":[
        "tgn:7512163",
        "tgn:1009227",
        "tgn:1000226",
        "tgn:7016729",
        "tgn:1000006",
        "tgn:7029392"
    ],
    "tgn:id":7512163,
    "tgn:name:en":"Jam Stream",
    "tgn:placetype":[
        "aat:300008699"
    ]
},
  "bbox": [],
  "geometry": {"coordinates":[173.716667,-42.066667],"type":"Point"}
}