{
  "id": 1002182,
  "type": "Feature",
  "properties": {
    "tgn:hierarchy":[
        "tgn:1002182",
        "tgn:1000001",
        "tgn:7012149",
        "tgn:7007520",
        "tgn:7029392"
    ],
    "tgn:id":1002182,
    "tgn:name":"Berrien",
    "tgn:placetype":[
        "aat:300387145",
        "aat:300000771"
    ]
},
  "bbox": [],
  "geometry": {"coordinates":[-86.4167,41.95],"type":"Point"}
}