{
  "id": 2197114,
  "type": "Feature",
  "properties": {
    "tgn:hierarchy":[
        "tgn:2197114",
        "tgn:1000001",
        "tgn:7012149",
        "tgn:2000437",
        "tgn:7007248",
        "tgn:7029392"
    ],
    "tgn:id":2197114,
    "tgn:name":"Brotherton Creek",
    "tgn:placetype":[
        "aat:300008706"
    ]
},
  "bbox": [],
  "geometry": {"coordinates":[-85.35,34.85],"type":"Point"}
}