{
  "id": 2645436,
  "type": "Feature",
  "properties": {
    "tgn:hierarchy":[
        "tgn:2645436",
        "tgn:1000001",
        "tgn:1002359",
        "tgn:7012149",
        "tgn:7007517",
        "tgn:7029392"
    ],
    "tgn:id":2645436,
    "tgn:name":"Savin Hill",
    "tgn:placetype":[
        "aat:300008798"
    ]
},
  "bbox": [],
  "geometry": {"coordinates":[-70.8667,42.6167],"type":"Point"}
}