<<<<<<< HEAD
{
  "id": 7170823,
  "type": "Feature",
  "properties": {
    "tgn:hierarchy":[
        "tgn:7170823",
        "tgn:7003669",
        "tgn:1000003",
        "tgn:7000084",
        "tgn:7029392"
    ],
    "tgn:id":7170823,
    "tgn:name":"Hirschth\u00fcrl",
    "tgn:placetype":[
        "aat:300008347"
    ]
},
  "bbox": [],
  "geometry": {"coordinates":[11.166667,48.183333],"type":"Point"}
}
=======
{"geometry":{"type":"Point","coordinates":[11.166667,48.183333]},"type":"Feature","properties":{"hierarchy":["tgn:7170823","tgn:7003669","tgn:1000003","tgn:7000084","tgn:7029392"],"placetype":["aat:300008347"],"id":7170823,"name:xx":"Hirschth\u00fcrl"}}
>>>>>>> 03f74aca74312dbeaf24d7e61306dd6a786dc3d0
