<<<<<<< HEAD
{
  "id": 7362979,
  "type": "Feature",
  "properties": {
    "tgn:hierarchy":[
        "tgn:7362979",
        "tgn:1000001",
        "tgn:7005599",
        "tgn:7005560",
        "tgn:7029392"
    ],
    "tgn:id":7362979,
    "tgn:name":"El Alquitr\u00e1n",
    "tgn:placetype":[
        "aat:300008347"
    ]
},
  "bbox": [],
  "geometry": {"coordinates":[-94.566667,17.8],"type":"Point"}
}
=======
{"geometry":{"type":"Point","coordinates":[-94.566667,17.800000]},"type":"Feature","properties":{"hierarchy":["tgn:7362979","tgn:1000001","tgn:7005599","tgn:7005560","tgn:7029392"],"placetype":["aat:300008347"],"id":7362979,"name:xx":"El Alquitr\u00e1n"}}
>>>>>>> 03f74aca74312dbeaf24d7e61306dd6a786dc3d0
