{
  "id": 2243784,
  "type": "Feature",
  "properties": {
    "tgn:hierarchy":[
        "tgn:2243784",
        "tgn:1000001",
        "tgn:7012149",
        "tgn:1002547",
        "tgn:7007919",
        "tgn:7029392"
    ],
    "tgn:id":2243784,
    "tgn:name":"Cleve Marsh",
    "tgn:placetype":[
        "aat:300008905"
    ]
},
  "bbox": [],
  "geometry": {"coordinates":[-77.2333,38.1833],"type":"Point"}
}