{
  "id": 2583128,
  "type": "Feature",
  "properties": {
    "tgn:hierarchy":[
        "tgn:2583128",
        "tgn:1000001",
        "tgn:7012149",
        "tgn:2000416",
        "tgn:7007248",
        "tgn:7029392"
    ],
    "tgn:id":2583128,
    "tgn:name":"Pine Lake Estates",
    "tgn:placetype":[
        "aat:300008347"
    ]
},
  "bbox": [],
  "geometry": {"coordinates":[-84.8667,31.05],"type":"Point"}
}