{
  "id": 2433323,
  "type": "Feature",
  "properties": {
    "tgn:hierarchy":[
        "tgn:2433323",
        "tgn:1000001",
        "tgn:7012149",
        "tgn:7007157",
        "tgn:7014516",
        "tgn:7029392"
    ],
    "tgn:id":2433323,
    "tgn:name":"Kelley Creek",
    "tgn:placetype":[
        "aat:300008706"
    ]
},
  "bbox": [],
  "geometry": {"coordinates":[-122.9333,38.6167],"type":"Point"}
}