{
  "id": 7232861,
  "type": "Feature",
  "properties": {
    "tgn:hierarchy":[
        "tgn:7232861",
        "tgn:7002681",
        "tgn:7001395",
        "tgn:1000003",
        "tgn:1000074",
        "tgn:7029392"
    ],
    "tgn:id":7232861,
    "tgn:name":"Irakl\u00e9ous, Lim\u00e9nas",
    "tgn:placetype":[
        "aat:300008678"
    ]
},
  "bbox": [],
  "geometry": {"coordinates":[23.608333,37.958333],"type":"Point"}
}