{
  "id": 2731991,
  "type": "Feature",
  "properties": {
    "tgn:hierarchy":[
        "tgn:2731991",
        "tgn:7006450",
        "tgn:1000001",
        "tgn:2124012",
        "tgn:7012149",
        "tgn:7029392"
    ],
    "tgn:id":2731991,
    "tgn:name":"Tungulara Mountain",
    "tgn:placetype":[
        "aat:300008798"
    ]
},
  "bbox": [],
  "geometry": {"coordinates":[-154.1833,56.9833],"type":"Point"}
}