<<<<<<< HEAD
{
  "id": 7361048,
  "type": "Feature",
  "properties": {
    "tgn:hierarchy":[
        "tgn:7361048",
        "tgn:7005581",
        "tgn:1000001",
        "tgn:7005560",
        "tgn:7029392"
    ],
    "tgn:id":7361048,
    "tgn:name":"El Colorado",
    "tgn:placetype":[
        "aat:300008347"
    ]
},
  "bbox": [],
  "geometry": {"coordinates":[-108.4,29.866667],"type":"Point"}
}
=======
{"geometry":{"type":"Point","coordinates":[-108.400000,29.866667]},"type":"Feature","properties":{"hierarchy":["tgn:7361048","tgn:7005581","tgn:1000001","tgn:7005560","tgn:7029392"],"placetype":["aat:300008347"],"id":7361048,"name:xx":"El Colorado"}}
>>>>>>> 03f74aca74312dbeaf24d7e61306dd6a786dc3d0
