{
  "id": 1012190,
  "type": "Feature",
  "properties": {
    "tgn:hierarchy":[
        "tgn:1012190",
        "tgn:7593359",
        "tgn:1000001",
        "tgn:7005562",
        "tgn:7029392"
    ],
    "tgn:id":1012190,
    "tgn:name":"Mono, Punta",
    "tgn:placetype":[
        "aat:300386846"
    ]
},
  "bbox": [],
  "geometry": {"coordinates":[-83.645,11.595],"type":"Point"}
}