{
  "id": 2410880,
  "type": "Feature",
  "properties": {
    "tgn:hierarchy":[
        "tgn:2410880",
        "tgn:1000001",
        "tgn:1002245",
        "tgn:7012149",
        "tgn:7007568",
        "tgn:7029392"
    ],
    "tgn:id":2410880,
    "tgn:name":"Indian Creek",
    "tgn:placetype":[
        "aat:300008706"
    ]
},
  "bbox": [],
  "geometry": {"coordinates":[-78.5667,42.4167],"type":"Point"}
}