{
  "id": 2060023,
  "type": "Feature",
  "properties": {
    "tgn:hierarchy":[
        "tgn:2060023",
        "tgn:1000001",
        "tgn:7012149",
        "tgn:7016167",
        "tgn:7007523",
        "tgn:7029392"
    ],
    "tgn:id":2060023,
    "tgn:name":"Ozark View",
    "tgn:placetype":[
        "aat:300008347"
    ]
},
  "bbox": [],
  "geometry": {"coordinates":[-90.45,38.5667],"type":"Point"}
}