{
  "id": 2671555,
  "type": "Feature",
  "properties": {
    "tgn:hierarchy":[
        "tgn:2671555",
        "tgn:1000001",
        "tgn:7012149",
        "tgn:2000911",
        "tgn:7007256",
        "tgn:7029392"
    ],
    "tgn:id":2671555,
    "tgn:name":"Smith Lake",
    "tgn:placetype":[
        "aat:300008680"
    ]
},
  "bbox": [],
  "geometry": {"coordinates":[-93.5167,31.0167],"type":"Point"}
}