{
  "id": 1116948,
  "type": "Feature",
  "properties": {
    "tgn:hierarchy":[
        "tgn:1116948",
        "tgn:1000001",
        "tgn:7012149",
        "tgn:1003002",
        "tgn:7007922",
        "tgn:7029392"
    ],
    "tgn:id":1116948,
    "tgn:name":"La Belle, Lac",
    "tgn:placetype":[
        "aat:300008680"
    ]
},
  "bbox": [],
  "geometry": {"coordinates":[-88.5167,43.1167],"type":"Point"}
}