{
  "id": 2015531,
  "type": "Feature",
  "properties": {
    "tgn:hierarchy":[
        "tgn:2015531",
        "tgn:1000001",
        "tgn:2000198",
        "tgn:7012149",
        "tgn:7007158",
        "tgn:7029392"
    ],
    "tgn:id":2015531,
    "tgn:name":"Eldorado Springs",
    "tgn:placetype":[
        "aat:300008347"
    ]
},
  "bbox": [],
  "geometry": {"coordinates":[-105.2667,39.9167],"type":"Point"}
}