{
  "id": 2588813,
  "type": "Feature",
  "properties": {
    "tgn:hierarchy":[
        "tgn:2588813",
        "tgn:7006450",
        "tgn:1000001",
        "tgn:7012149",
        "tgn:2000089",
        "tgn:7029392"
    ],
    "tgn:id":2588813,
    "tgn:name":"Pocahontas Hot Springs",
    "tgn:placetype":[
        "aat:300008697"
    ]
},
  "bbox": [],
  "geometry": {"coordinates":[-154.0167,65.9667],"type":"Point"}
}