{
  "id": 7407046,
  "type": "Feature",
  "properties": {
    "tgn:hierarchy":[
        "tgn:7407046",
        "tgn:7005585",
        "tgn:1000001",
        "tgn:7005560",
        "tgn:7029392"
    ],
    "tgn:id":7407046,
    "tgn:name":"Quiahuitepec",
    "tgn:placetype":[
        "aat:300008347"
    ]
},
  "bbox": [],
  "geometry": {"coordinates":[-98.933333,16.925],"type":"Point"}
}