{
  "id": 7318500,
  "type": "Feature",
  "properties": {
    "tgn:hierarchy":[
        "tgn:7318500",
        "tgn:1001702",
        "tgn:1000049",
        "tgn:1000002",
        "tgn:7029392"
    ],
    "tgn:id":7318500,
    "tgn:name":"Charles, Cabo",
    "tgn:placetype":[
        "aat:300386846"
    ]
},
  "bbox": [],
  "geometry": {"coordinates":[-72.316667,-53.233333],"type":"Point"}
}