{
  "id": 2681400,
  "type": "Feature",
  "properties": {
    "tgn:hierarchy":[
        "tgn:2681400",
        "tgn:7006450",
        "tgn:1000001",
        "tgn:7012149",
        "tgn:7019760",
        "tgn:7029392"
    ],
    "tgn:id":2681400,
    "tgn:name":"South Point",
    "tgn:placetype":[
        "aat:300008850"
    ]
},
  "bbox": [],
  "geometry": {"coordinates":[-134.4667,57.5333],"type":"Point"}
}