{
  "id": 2067663,
  "type": "Feature",
  "properties": {
    "tgn:hierarchy":[
        "tgn:2067663",
        "tgn:1000001",
        "tgn:7012149",
        "tgn:2001437",
        "tgn:7007566",
        "tgn:7029392"
    ],
    "tgn:id":2067663,
    "tgn:name":"Vanadium",
    "tgn:placetype":[
        "aat:300008347"
    ]
},
  "bbox": [],
  "geometry": {"coordinates":[-108.1167,32.7667],"type":"Point"}
}