{
  "id": 1024454,
  "type": "Feature",
  "properties": {
    "tgn:hierarchy":[
        "tgn:1024454",
        "tgn:1000518",
        "tgn:1000002",
        "tgn:1000056",
        "tgn:7029392"
    ],
    "tgn:id":1024454,
    "tgn:name":"Chiquintirca",
    "tgn:placetype":[
        "aat:300008347"
    ]
},
  "bbox": [],
  "geometry": {"coordinates":[-73.6833,-13.15],"type":"Point"}
}