{
  "id": 7512449,
  "type": "Feature",
  "properties": {
    "tgn:hierarchy":[
        "tgn:7512449",
        "tgn:1009227",
        "tgn:1000226",
        "tgn:7016822",
        "tgn:1000006",
        "tgn:7029392"
    ],
    "tgn:id":7512449,
    "tgn:name:en":"Howells Point",
    "tgn:placetype":[
        "aat:300386846"
    ]
},
  "bbox": [],
  "geometry": {"coordinates":[168.033333,-46.383333],"type":"Point"}
}