{
  "id": 2379954,
  "type": "Feature",
  "properties": {
    "tgn:hierarchy":[
        "tgn:2379954",
        "tgn:1000001",
        "tgn:7012149",
        "tgn:7007157",
        "tgn:1002915",
        "tgn:7029392"
    ],
    "tgn:id":2379954,
    "tgn:name":"Hatch Drain",
    "tgn:placetype":[
        "aat:300006075"
    ]
},
  "bbox": [],
  "geometry": {"coordinates":[-121.0167,37.5167],"type":"Point"}
}