{
  "id": 2533777,
  "type": "Feature",
  "properties": {
    "tgn:hierarchy":[
        "tgn:2533777",
        "tgn:1000001",
        "tgn:7012149",
        "tgn:2001914",
        "tgn:7007825",
        "tgn:7029392"
    ],
    "tgn:id":2533777,
    "tgn:name":"Mutton Hollow",
    "tgn:placetype":[
        "aat:300008761"
    ]
},
  "bbox": [],
  "geometry": {"coordinates":[-83.5667,35.9667],"type":"Point"}
}