{
  "id": 7217403,
  "type": "Feature",
  "properties": {
    "tgn:hierarchy":[
        "tgn:7217403",
        "tgn:7002728",
        "tgn:7002715",
        "tgn:1000003",
        "tgn:1000074",
        "tgn:7029392"
    ],
    "tgn:id":7217403,
    "tgn:name":"Gypsoch\u00f3rion",
    "tgn:placetype":[
        "aat:300008347"
    ]
},
  "bbox": [],
  "geometry": {"coordinates":[22.238333,40.822222],"type":"Point"}
}