{
  "id": 7424178,
  "type": "Feature",
  "properties": {
    "tgn:hierarchy":[
        "tgn:7424178",
        "tgn:1000001",
        "tgn:7005601",
        "tgn:7005560",
        "tgn:7029392"
    ],
    "tgn:id":7424178,
    "tgn:name":"El Machete, Cerro",
    "tgn:placetype":[
        "aat:300008795"
    ]
},
  "bbox": [],
  "geometry": {"coordinates":[-102.983333,22.316667],"type":"Point"}
}