{
  "id": 7397477,
  "type": "Feature",
  "properties": {
    "tgn:hierarchy":[
        "tgn:7397477",
        "tgn:1001835",
        "tgn:1000001",
        "tgn:7005560",
        "tgn:7029392"
    ],
    "tgn:id":7397477,
    "tgn:name":"Santa Rosa, Sierra",
    "tgn:placetype":[
        "aat:300008795"
    ]
},
  "bbox": [],
  "geometry": {"coordinates":[-114.883333,30.75],"type":"Point"}
}