{
  "id": 7196213,
  "type": "Feature",
  "properties": {
    "tgn:hierarchy":[
        "tgn:7196213",
        "tgn:7003692",
        "tgn:1000003",
        "tgn:7000084",
        "tgn:7029392"
    ],
    "tgn:id":7196213,
    "tgn:name":"D\u00f6rfle",
    "tgn:placetype":[
        "aat:300000745"
    ]
},
  "bbox": [],
  "geometry": {"coordinates":[8.133333,47.633333],"type":"Point"}
}