{
  "id": 7321246,
  "type": "Feature",
  "properties": {
    "tgn:hierarchy":[
        "tgn:7321246",
        "tgn:1001657",
        "tgn:1000049",
        "tgn:1000002",
        "tgn:7029392"
    ],
    "tgn:id":7321246,
    "tgn:name":"Buitre, Cerro",
    "tgn:placetype":[
        "aat:300008795"
    ]
},
  "bbox": [],
  "geometry": {"coordinates":[-70.85,-30.333333],"type":"Point"}
}