<<<<<<< HEAD
{
  "id": 7022485,
  "type": "Feature",
  "properties": {
    "tgn:hierarchy":[
        "tgn:7022485",
        "tgn:1000001",
        "tgn:7012149",
        "tgn:7029392"
    ],
    "tgn:id":7022485,
    "tgn:name":"Yankee Bar",
    "tgn:placetype":[
        "aat:300132348"
    ]
},
  "bbox": [],
  "geometry": {"coordinates":[-89.85,35.6333],"type":"Point"}
}
=======
{"geometry":{"type":"Point","coordinates":[-89.850000,35.633300]},"type":"Feature","properties":{"hierarchy":["tgn:7022485","tgn:1000001","tgn:7012149","tgn:7029392"],"placetype":["aat:300132348"],"id":7022485,"name:xx":"Yankee Bar"}}
>>>>>>> 03f74aca74312dbeaf24d7e61306dd6a786dc3d0
