{
  "id": 1057627,
  "type": "Feature",
  "properties": {
    "tgn:hierarchy":[
        "tgn:1057627",
        "tgn:7012076",
        "tgn:1000003",
        "tgn:7006660",
        "tgn:7029392"
    ],
    "tgn:id":1057627,
    "tgn:name":"Novoamvrosiyivs'ke",
    "tgn:placetype":[
        "aat:300008347"
    ]
},
  "bbox": [],
  "geometry": {"coordinates":[38.4833,47.8167],"type":"Point"}
}