{
  "id": 2322735,
  "type": "Feature",
  "properties": {
    "tgn:hierarchy":[
        "tgn:2322735",
        "tgn:7006450",
        "tgn:1000001",
        "tgn:7012149",
        "tgn:2124002",
        "tgn:7029392"
    ],
    "tgn:id":2322735,
    "tgn:name":"False Lindenberg Head",
    "tgn:placetype":[
        "aat:300008850"
    ]
},
  "bbox": [],
  "geometry": {"coordinates":[-135.0833,57.4667],"type":"Point"}
}