{
  "id": 1050063,
  "type": "Feature",
  "properties": {
    "tgn:hierarchy":[
        "tgn:1050063",
        "tgn:1000003",
        "tgn:7004276",
        "tgn:1000091",
        "tgn:7029392"
    ],
    "tgn:id":1050063,
    "tgn:name":"C\u0103lug\u0103reni",
    "tgn:placetype":[
        "aat:300008347"
    ]
},
  "bbox": [],
  "geometry": {"coordinates":[25.9833,44.1833],"type":"Point"}
}