{
  "id": 2059838,
  "type": "Feature",
  "properties": {
    "tgn:hierarchy":[
        "tgn:2059838",
        "tgn:1000001",
        "tgn:7012149",
        "tgn:2001214",
        "tgn:7007523",
        "tgn:7029392"
    ],
    "tgn:id":2059838,
    "tgn:name":"Needles",
    "tgn:placetype":[
        "aat:300387016"
    ]
},
  "bbox": [],
  "geometry": {"coordinates":[-93.1333,39.7833],"type":"Point"}
}