{
  "id": 7307742,
  "type": "Feature",
  "properties": {
    "tgn:hierarchy":[
        "tgn:7307742",
        "tgn:7002836",
        "tgn:7016622",
        "tgn:1000003",
        "tgn:1000095",
        "tgn:7029392"
    ],
    "tgn:id":7307742,
    "tgn:name":"Llano, Playa del",
    "tgn:placetype":[
        "aat:300008816"
    ]
},
  "bbox": [],
  "geometry": {"coordinates":[-16.15,28.516667],"type":"Point"}
}