{
  "id": 2762444,
  "type": "Feature",
  "properties": {
    "tgn:hierarchy":[
        "tgn:2762444",
        "tgn:1000001",
        "tgn:7012149",
        "tgn:1002979",
        "tgn:7007920",
        "tgn:7029392"
    ],
    "tgn:id":2762444,
    "tgn:name":"West Valley Creek",
    "tgn:placetype":[
        "aat:300008706"
    ]
},
  "bbox": [],
  "geometry": {"coordinates":[-123.5167,46.2833],"type":"Point"}
}