<<<<<<< HEAD
{
  "id": 2762444,
  "type": "Feature",
  "properties": {
    "tgn:hierarchy":[
        "tgn:2762444",
        "tgn:1000001",
        "tgn:7012149",
        "tgn:1002979",
        "tgn:7007920",
        "tgn:7029392"
    ],
    "tgn:id":2762444,
    "tgn:name":"West Valley Creek",
    "tgn:placetype":[
        "aat:300008706"
    ]
},
  "bbox": [],
  "geometry": {"coordinates":[-123.5167,46.2833],"type":"Point"}
}
=======
{"geometry":{"type":"Point","coordinates":[-123.516700,46.283300]},"type":"Feature","properties":{"hierarchy":["tgn:2762444","tgn:1000001","tgn:7012149","tgn:1002979","tgn:7007920","tgn:7029392"],"placetype":["aat:300008706"],"id":2762444,"name:xx":"West Valley Creek"}}
>>>>>>> 03f74aca74312dbeaf24d7e61306dd6a786dc3d0
