{
  "id": 2744293,
  "type": "Feature",
  "properties": {
    "tgn:hierarchy":[
        "tgn:2744293",
        "tgn:1000001",
        "tgn:7012149",
        "tgn:1002449",
        "tgn:7013961",
        "tgn:7029392"
    ],
    "tgn:id":2744293,
    "tgn:name":"Vermont Terrace",
    "tgn:placetype":[
        "aat:300008347"
    ]
},
  "bbox": [],
  "geometry": {"coordinates":[-80.5667,40.4167],"type":"Point"}
}