{
  "id": 2455904,
  "type": "Feature",
  "properties": {
    "tgn:hierarchy":[
        "tgn:2455904",
        "tgn:1000001",
        "tgn:2001596",
        "tgn:7012149",
        "tgn:7007705",
        "tgn:7029392"
    ],
    "tgn:id":2455904,
    "tgn:name":"Little Gurr Lake",
    "tgn:placetype":[
        "aat:300008680"
    ]
},
  "bbox": [],
  "geometry": {"coordinates":[-99.8667,48.6833],"type":"Point"}
}