{
  "id": 2297063,
  "type": "Feature",
  "properties": {
    "tgn:hierarchy":[
        "tgn:2297063",
        "tgn:1000001",
        "tgn:7012149",
        "tgn:1002485",
        "tgn:7007826",
        "tgn:7029392"
    ],
    "tgn:id":2297063,
    "tgn:name":"Dry Creek",
    "tgn:placetype":[
        "aat:300008706"
    ]
},
  "bbox": [],
  "geometry": {"coordinates":[-95.5167,33.0667],"type":"Point"}
}