{
  "id": 7261520,
  "type": "Feature",
  "properties": {
    "tgn:concordances":{
        "gn:id":"2756415"
    },
    "tgn:hierarchy":[
        "tgn:7261520",
        "tgn:1000003",
        "tgn:7003613",
        "tgn:7016845",
        "tgn:7029392"
    ],
    "tgn:id":7261520,
    "tgn:name:nl":"Eekeburen",
    "tgn:placetype":[
        "aat:300008347"
    ]
},
  "bbox": [],
  "geometry": {"coordinates":[6.35,53.216667],"type":"Point"}
}