<<<<<<< HEAD
{
  "id": 7368117,
  "type": "Feature",
  "properties": {
    "tgn:hierarchy":[
        "tgn:7368117",
        "tgn:1000001",
        "tgn:7005599",
        "tgn:7005560",
        "tgn:7029392"
    ],
    "tgn:id":7368117,
    "tgn:name":"Hato Quemado",
    "tgn:placetype":[
        "aat:300007783"
    ]
},
  "bbox": [],
  "geometry": {"coordinates":[-96.2,18.35],"type":"Point"}
}
=======
{"geometry":{"type":"Point","coordinates":[-96.200000,18.350000]},"type":"Feature","properties":{"hierarchy":["tgn:7368117","tgn:1000001","tgn:7005599","tgn:7005560","tgn:7029392"],"placetype":["aat:300007783"],"id":7368117,"name:xx":"Hato Quemado"}}
>>>>>>> 03f74aca74312dbeaf24d7e61306dd6a786dc3d0
