{
  "id": 7111033,
  "type": "Feature",
  "properties": {
    "tgn:hierarchy":[
        "tgn:7111033",
        "tgn:1000003",
        "tgn:7003684",
        "tgn:7000084",
        "tgn:7029392"
    ],
    "tgn:id":7111033,
    "tgn:name":"Renglisch-Berg",
    "tgn:placetype":[
        "aat:300008777"
    ]
},
  "bbox": [],
  "geometry": {"coordinates":[6.45,49.516667],"type":"Point"}
}