{
  "id": 2175373,
  "type": "Feature",
  "properties": {
    "tgn:hierarchy":[
        "tgn:2175373",
        "tgn:1000001",
        "tgn:7012149",
        "tgn:7007157",
        "tgn:7029392"
    ],
    "tgn:id":2175373,
    "tgn:name":"Black Butte River",
    "tgn:placetype":[
        "aat:300008707"
    ]
},
  "bbox": [],
  "geometry": {"coordinates":[-122.85,39.5833],"type":"Point"}
}