{
  "id": 7276653,
  "type": "Feature",
  "properties": {
    "tgn:hierarchy":[
        "tgn:7276653",
        "tgn:1001630",
        "tgn:1000049",
        "tgn:1000002",
        "tgn:7029392"
    ],
    "tgn:id":7276653,
    "tgn:name":"Zanj\u00f3n",
    "tgn:placetype":[
        "aat:300008347"
    ]
},
  "bbox": [],
  "geometry": {"coordinates":[-70.833333,-28.15],"type":"Point"}
}