{
  "id": 2663325,
  "type": "Feature",
  "properties": {
    "tgn:hierarchy":[
        "tgn:2663325",
        "tgn:1002202",
        "tgn:1000001",
        "tgn:7012149",
        "tgn:7007711",
        "tgn:7029392"
    ],
    "tgn:id":2663325,
    "tgn:name":"Silver Creek",
    "tgn:placetype":[
        "aat:300008706"
    ]
},
  "bbox": [],
  "geometry": {"coordinates":[-71.2667,41.6833],"type":"Point"}
}