{
  "id": 7386081,
  "type": "Feature",
  "properties": {
    "tgn:hierarchy":[
        "tgn:7386081",
        "tgn:1001853",
        "tgn:1000001",
        "tgn:7005560",
        "tgn:7029392"
    ],
    "tgn:id":7386081,
    "tgn:name":"Prieta, Sierra",
    "tgn:placetype":[
        "aat:300008795"
    ]
},
  "bbox": [],
  "geometry": {"coordinates":[-102.266667,25.366667],"type":"Point"}
}