{
  "id": 7276595,
  "type": "Feature",
  "properties": {
    "tgn:hierarchy":[
        "tgn:7276595",
        "tgn:1001702",
        "tgn:1000049",
        "tgn:1000002",
        "tgn:7029392"
    ],
    "tgn:id":7276595,
    "tgn:name":"Limones, Cerro",
    "tgn:placetype":[
        "aat:300008795"
    ]
},
  "bbox": [],
  "geometry": {"coordinates":[-72.416667,-53.966667],"type":"Point"}
}