{
  "id": 7154495,
  "type": "Feature",
  "properties": {
    "tgn:hierarchy":[
        "tgn:7154495",
        "tgn:7003669",
        "tgn:1000003",
        "tgn:7000084",
        "tgn:7029392"
    ],
    "tgn:id":7154495,
    "tgn:name":"Irnberg",
    "tgn:placetype":[
        "aat:300008347"
    ]
},
  "bbox": [],
  "geometry": {"coordinates":[11.85,47.933333],"type":"Point"}
}