{
  "id": 7500337,
  "type": "Feature",
  "properties": {
    "tgn:hierarchy":[
        "tgn:7500337",
        "tgn:1000004",
        "tgn:7492971",
        "tgn:1000141",
        "tgn:7029392"
    ],
    "tgn:id":7500337,
    "tgn:name":"Ligang Guozhong",
    "tgn:placetype":[
        "aat:300006495"
    ]
},
  "bbox": [],
  "geometry": {"coordinates":[120.496667,22.771667],"type":"Point"}
}