<<<<<<< HEAD
{
  "id": 2251289,
  "type": "Feature",
  "properties": {
    "tgn:hierarchy":[
        "tgn:2251289",
        "tgn:1000001",
        "tgn:7012149",
        "tgn:2000812",
        "tgn:7007255",
        "tgn:7029392"
    ],
    "tgn:id":2251289,
    "tgn:name":"Combs Branch",
    "tgn:placetype":[
        "aat:300008699"
    ]
},
  "bbox": [],
  "geometry": {"coordinates":[-82.8,37.1333],"type":"Point"}
}
=======
{"geometry":{"type":"Point","coordinates":[-82.800000,37.133300]},"type":"Feature","properties":{"hierarchy":["tgn:2251289","tgn:1000001","tgn:7012149","tgn:2000812","tgn:7007255","tgn:7029392"],"placetype":["aat:300008699"],"id":2251289,"name:xx":"Combs Branch"}}
>>>>>>> 03f74aca74312dbeaf24d7e61306dd6a786dc3d0
