{
  "id": 7221902,
  "type": "Feature",
  "properties": {
    "tgn:hierarchy":[
        "tgn:7221902",
        "tgn:7002681",
        "tgn:7001395",
        "tgn:1000003",
        "tgn:1000074",
        "tgn:7029392"
    ],
    "tgn:id":7221902,
    "tgn:name":"Pothit\u00f3, Vr\u00e1chos",
    "tgn:placetype":[
        "aat:300011692"
    ]
},
  "bbox": [],
  "geometry": {"coordinates":[23.872697,37.763918],"type":"Point"}
}