{
  "id": 7573421,
  "type": "Feature",
  "properties": {
    "tgn:hierarchy":[
        "tgn:7573421",
        "tgn:1000004",
        "tgn:7000198",
        "tgn:7016788",
        "tgn:7029392"
    ],
    "tgn:id":7573421,
    "tgn:name:en":"G\u0101ng\u012by\u0101sar",
    "tgn:placetype":[
        "aat:300008347"
    ]
},
  "bbox": [],
  "geometry": {"coordinates":[75.151324,28.271844],"type":"Point"}
}