{
  "id": 2302822,
  "type": "Feature",
  "properties": {
    "tgn:hierarchy":[
        "tgn:2302822",
        "tgn:1000001",
        "tgn:7012149",
        "tgn:7014589",
        "tgn:7007515",
        "tgn:7029392"
    ],
    "tgn:id":2302822,
    "tgn:name":"Dyer Cove Point",
    "tgn:placetype":[
        "aat:300008850"
    ]
},
  "bbox": [],
  "geometry": {"coordinates":[-67.7833,45.2167],"type":"Point"}
}