{
  "id": 7537091,
  "type": "Feature",
  "properties": {
    "tgn:hierarchy":[
        "tgn:7537091",
        "tgn:7001242",
        "tgn:7016833",
        "tgn:1001335",
        "tgn:7029392"
    ],
    "tgn:id":7537091,
    "tgn:name:en":"Qunbur, Ra's",
    "tgn:placetype":[
        "aat:300386846"
    ]
},
  "bbox": [],
  "geometry": {"coordinates":[30.87,31.428333],"type":"Point"}
}