{
  "id": 7568314,
  "type": "Feature",
  "properties": {
    "tgn:hierarchy":[
        "tgn:7568314",
        "tgn:1000004",
        "tgn:7000198",
        "tgn:1001996",
        "tgn:7029392"
    ],
    "tgn:id":7568314,
    "tgn:name:en":"K\u0101hal ka Jubbar",
    "tgn:placetype":[
        "aat:300008347"
    ]
},
  "bbox": [],
  "geometry": {"coordinates":[77.058056,31.204167],"type":"Point"}
}