{
  "id": 2321843,
  "type": "Feature",
  "properties": {
    "tgn:hierarchy":[
        "tgn:2321843",
        "tgn:1000001",
        "tgn:7012149",
        "tgn:2001721",
        "tgn:7007708",
        "tgn:7029392"
    ],
    "tgn:id":2321843,
    "tgn:name":"Fake Creek",
    "tgn:placetype":[
        "aat:300008706"
    ]
},
  "bbox": [],
  "geometry": {"coordinates":[-117.4333,45.0833],"type":"Point"}
}