{
  "id": 2215770,
  "type": "Feature",
  "properties": {
    "tgn:hierarchy":[
        "tgn:2215770",
        "tgn:1000001",
        "tgn:7012149",
        "tgn:1002654",
        "tgn:7007706",
        "tgn:7029392"
    ],
    "tgn:id":2215770,
    "tgn:name":"Camel Creek",
    "tgn:placetype":[
        "aat:300008706"
    ]
},
  "bbox": [],
  "geometry": {"coordinates":[-81.9667,41.0833],"type":"Point"}
}