{
  "id": 1011424,
  "type": "Feature",
  "properties": {
    "tgn:hierarchy":[
        "tgn:1011424",
        "tgn:7002443",
        "tgn:1000003",
        "tgn:7018993",
        "tgn:7008591",
        "tgn:7029392"
    ],
    "tgn:id":1011424,
    "tgn:name:en":"Cemaes Head",
    "tgn:placetype":[
        "aat:300008850",
        "aat:300387499"
    ]
},
  "bbox": [],
  "geometry": {"coordinates":[-4.733333,52.116667],"type":"Point"}
}