{
  "id": 2463758,
  "type": "Feature",
  "properties": {
    "tgn:hierarchy":[
        "tgn:2463758",
        "tgn:1000001",
        "tgn:7014352",
        "tgn:7012149",
        "tgn:7007564",
        "tgn:7029392"
    ],
    "tgn:id":2463758,
    "tgn:name":"Locke Point",
    "tgn:placetype":[
        "aat:300008850"
    ]
},
  "bbox": [],
  "geometry": {"coordinates":[-70.8167,42.8833],"type":"Point"}
}