{
  "id": 2666459,
  "type": "Feature",
  "properties": {
    "tgn:hierarchy":[
        "tgn:2666459",
        "tgn:1000001",
        "tgn:2002243",
        "tgn:7012149",
        "tgn:7007920",
        "tgn:7029392"
    ],
    "tgn:id":2666459,
    "tgn:name":"Sixmile Creek",
    "tgn:placetype":[
        "aat:300008706"
    ]
},
  "bbox": [],
  "geometry": {"coordinates":[-118.4667,47.9667],"type":"Point"}
}