{
  "id": 2406684,
  "type": "Feature",
  "properties": {
    "tgn:hierarchy":[
        "tgn:2406684",
        "tgn:1002146",
        "tgn:1000001",
        "tgn:7012149",
        "tgn:7007157",
        "tgn:7029392"
    ],
    "tgn:id":2406684,
    "tgn:name":"Hunt Gulch",
    "tgn:placetype":[
        "aat:300008761"
    ]
},
  "bbox": [],
  "geometry": {"coordinates":[-120.75,38.3333],"type":"Point"}
}