<<<<<<< HEAD
{
  "id": 2254351,
  "type": "Feature",
  "properties": {
    "tgn:hierarchy":[
        "tgn:2254351",
        "tgn:1000001",
        "tgn:2000677",
        "tgn:7012149",
        "tgn:7007254",
        "tgn:7029392"
    ],
    "tgn:id":2254351,
    "tgn:name":"Coon Creek",
    "tgn:placetype":[
        "aat:300008706"
    ]
},
  "bbox": [],
  "geometry": {"coordinates":[-96.6333,37.2667],"type":"Point"}
}
=======
{"geometry":{"type":"Point","coordinates":[-96.633300,37.266700]},"type":"Feature","properties":{"hierarchy":["tgn:2254351","tgn:1000001","tgn:2000677","tgn:7012149","tgn:7007254","tgn:7029392"],"placetype":["aat:300008706"],"id":2254351,"name:xx":"Coon Creek"}}
>>>>>>> 03f74aca74312dbeaf24d7e61306dd6a786dc3d0
