{
  "id": 7143302,
  "type": "Feature",
  "properties": {
    "tgn:hierarchy":[
        "tgn:7143302",
        "tgn:7003669",
        "tgn:1000003",
        "tgn:7000084",
        "tgn:7029392"
    ],
    "tgn:id":7143302,
    "tgn:name":"Linden",
    "tgn:placetype":[
        "aat:300008347"
    ]
},
  "bbox": [],
  "geometry": {"coordinates":[11.316667,49.716667],"type":"Point"}
}