{
  "id": 2458399,
  "type": "Feature",
  "properties": {
    "tgn:hierarchy":[
        "tgn:2458399",
        "tgn:7006450",
        "tgn:1000001",
        "tgn:7012149",
        "tgn:2000086",
        "tgn:7029392"
    ],
    "tgn:id":2458399,
    "tgn:name":"Little Mummy Island",
    "tgn:placetype":[
        "aat:300008791"
    ]
},
  "bbox": [],
  "geometry": {"coordinates":[-146.0333,60.4667],"type":"Point"}
}