{
  "id": 7526803,
  "type": "Feature",
  "properties": {
    "tgn:hierarchy":[
        "tgn:7526803",
        "tgn:7001242",
        "tgn:7016833",
        "tgn:1001418",
        "tgn:7029392"
    ],
    "tgn:id":7526803,
    "tgn:name:en":"Wihish, Q\u00e2r\u00e2t el",
    "tgn:placetype":[
        "aat:300008777"
    ]
},
  "bbox": [],
  "geometry": {"coordinates":[26.745333,30.074003],"type":"Point"}
}