{
  "id": 7167298,
  "type": "Feature",
  "properties": {
    "tgn:hierarchy":[
        "tgn:7167298",
        "tgn:7000096",
        "tgn:1000003",
        "tgn:7000084",
        "tgn:7029392"
    ],
    "tgn:id":7167298,
    "tgn:name":"Haltepunkt Hegerm\u00fchle",
    "tgn:placetype":[
        "aat:300007783"
    ]
},
  "bbox": [],
  "geometry": {"coordinates":[13.866667,52.548611],"type":"Point"}
}