{
  "id": 7410329,
  "type": "Feature",
  "properties": {
    "tgn:hierarchy":[
        "tgn:7410329",
        "tgn:1000001",
        "tgn:1001893",
        "tgn:7005560",
        "tgn:7029392"
    ],
    "tgn:id":7410329,
    "tgn:name":"Cruz Vidriada",
    "tgn:placetype":[
        "aat:300008347"
    ]
},
  "bbox": [],
  "geometry": {"coordinates":[-99.633333,18.983333],"type":"Point"}
}