{
  "id": 2365966,
  "type": "Feature",
  "properties": {
    "tgn:hierarchy":[
        "tgn:2365966",
        "tgn:1000001",
        "tgn:7012149",
        "tgn:2001456",
        "tgn:7007566",
        "tgn:7029392"
    ],
    "tgn:id":2365966,
    "tgn:name":"Grey Ridge",
    "tgn:placetype":[
        "aat:300266640"
    ]
},
  "bbox": [],
  "geometry": {"coordinates":[-106.5833,34.2667],"type":"Point"}
}