{
  "id": 7572334,
  "type": "Feature",
  "properties": {
    "tgn:hierarchy":[
        "tgn:7572334",
        "tgn:1000004",
        "tgn:7000198",
        "tgn:1001895",
        "tgn:7029392"
    ],
    "tgn:id":7572334,
    "tgn:name:en":"Gorai",
    "tgn:placetype":[
        "aat:300008347"
    ]
},
  "bbox": [],
  "geometry": {"coordinates":[72.783333,19.25],"type":"Point"}
}