<<<<<<< HEAD
{
  "id": 2150269,
  "type": "Feature",
  "properties": {
    "tgn:hierarchy":[
        "tgn:2150269",
        "tgn:1000001",
        "tgn:7012149",
        "tgn:2000970",
        "tgn:7007520",
        "tgn:7029392"
    ],
    "tgn:id":2150269,
    "tgn:name":"Basford Lake",
    "tgn:placetype":[
        "aat:300008680"
    ]
},
  "bbox": [],
  "geometry": {"coordinates":[-85.9333,43.8333],"type":"Point"}
}
=======
{"geometry":{"type":"Point","coordinates":[-85.933300,43.833300]},"type":"Feature","properties":{"hierarchy":["tgn:2150269","tgn:1000001","tgn:7012149","tgn:2000970","tgn:7007520","tgn:7029392"],"placetype":["aat:300008680"],"id":2150269,"name:xx":"Basford Lake"}}
>>>>>>> 03f74aca74312dbeaf24d7e61306dd6a786dc3d0
