{
  "id": 2098890,
  "type": "Feature",
  "properties": {
    "tgn:hierarchy":[
        "tgn:2098890",
        "tgn:1000001",
        "tgn:7012149",
        "tgn:2001930",
        "tgn:7007825",
        "tgn:7029392"
    ],
    "tgn:id":2098890,
    "tgn:name":"Duplex",
    "tgn:placetype":[
        "aat:300008347",
        "aat:300387210"
    ]
},
  "bbox": [],
  "geometry": {"coordinates":[-86.8333,35.7333],"type":"Point"}
}