{
  "id": 2700147,
  "type": "Feature",
  "properties": {
    "tgn:hierarchy":[
        "tgn:2700147",
        "tgn:1000001",
        "tgn:7012149",
        "tgn:2001488",
        "tgn:7007709",
        "tgn:7029392"
    ],
    "tgn:id":2700147,
    "tgn:name":"Stumpy Point Bay",
    "tgn:placetype":[
        "aat:300132316"
    ]
},
  "bbox": [],
  "geometry": {"coordinates":[-75.75,35.6833],"type":"Point"}
}