{
  "id": 2388150,
  "type": "Feature",
  "properties": {
    "tgn:hierarchy":[
        "tgn:2388150",
        "tgn:1000001",
        "tgn:2001749",
        "tgn:7012149",
        "tgn:7007712",
        "tgn:7029392"
    ],
    "tgn:id":2388150,
    "tgn:name":"Hickory Hill",
    "tgn:placetype":[
        "aat:300008347"
    ]
},
  "bbox": [],
  "geometry": {"coordinates":[-81.0833,32.8167],"type":"Point"}
}