{
  "id": 7523273,
  "type": "Feature",
  "properties": {
    "tgn:hierarchy":[
        "tgn:7523273",
        "tgn:7001242",
        "tgn:7016833",
        "tgn:7001334",
        "tgn:7029392"
    ],
    "tgn:id":7523273,
    "tgn:name:en":"D\u016bsh, Tall",
    "tgn:placetype":[
        "aat:300008777"
    ]
},
  "bbox": [],
  "geometry": {"coordinates":[30.716667,24.583333],"type":"Point"}
}