<<<<<<< HEAD
{
  "id": 7358173,
  "type": "Feature",
  "properties": {
    "tgn:hierarchy":[
        "tgn:7358173",
        "tgn:1000001",
        "tgn:7005597",
        "tgn:7005560",
        "tgn:7029392"
    ],
    "tgn:id":7358173,
    "tgn:name":"Ejido Nuevo Emiliano Portes",
    "tgn:placetype":[
        "aat:300008347"
    ]
},
  "bbox": [],
  "geometry": {"coordinates":[-98.183333,24.95],"type":"Point"}
}
=======
{"geometry":{"type":"Point","coordinates":[-98.183333,24.950000]},"type":"Feature","properties":{"hierarchy":["tgn:7358173","tgn:1000001","tgn:7005597","tgn:7005560","tgn:7029392"],"placetype":["aat:300008347"],"id":7358173,"name:xx":"Ejido Nuevo Emiliano Portes"}}
>>>>>>> 03f74aca74312dbeaf24d7e61306dd6a786dc3d0
