{
  "id": 2524254,
  "type": "Feature",
  "properties": {
    "tgn:hierarchy":[
        "tgn:2524254",
        "tgn:1000001",
        "tgn:7012149",
        "tgn:1002932",
        "tgn:7007710",
        "tgn:7029392"
    ],
    "tgn:id":2524254,
    "tgn:name":"Morgan Hill",
    "tgn:placetype":[
        "aat:300008798"
    ]
},
  "bbox": [],
  "geometry": {"coordinates":[-75.7167,41.7333],"type":"Point"}
}