{
  "id": 2682207,
  "type": "Feature",
  "properties": {
    "tgn:hierarchy":[
        "tgn:2682207",
        "tgn:7006450",
        "tgn:1000001",
        "tgn:7012149",
        "tgn:2000089",
        "tgn:7029392"
    ],
    "tgn:id":2682207,
    "tgn:name":"South Twin Creek",
    "tgn:placetype":[
        "aat:300008706"
    ]
},
  "bbox": [],
  "geometry": {"coordinates":[-148.6167,67.6667],"type":"Point"}
}