{
  "id": 1027995,
  "type": "Feature",
  "properties": {
    "tgn:hierarchy":[
        "tgn:1027995",
        "tgn:7594006",
        "tgn:1000003",
        "tgn:1000066",
        "tgn:7029392"
    ],
    "tgn:id":1027995,
    "tgn:name":"Laven",
    "tgn:placetype":[
        "aat:300008347"
    ]
},
  "bbox": [],
  "geometry": {"coordinates":[9.7333,56.1167],"type":"Point"}
}