{
  "id": 7510757,
  "type": "Feature",
  "properties": {
    "tgn:hierarchy":[
        "tgn:7510757",
        "tgn:1009227",
        "tgn:1000226",
        "tgn:7016822",
        "tgn:1000006",
        "tgn:7029392"
    ],
    "tgn:id":7510757,
    "tgn:name:en":"South Cape",
    "tgn:placetype":[
        "aat:300008850"
    ]
},
  "bbox": [],
  "geometry": {"coordinates":[167.566667,-47.283333],"type":"Point"}
}