{
  "id": 7223822,
  "type": "Feature",
  "properties": {
    "tgn:hierarchy":[
        "tgn:7223822",
        "tgn:7002739",
        "tgn:7017076",
        "tgn:1000003",
        "tgn:1000074",
        "tgn:7029392"
    ],
    "tgn:id":7223822,
    "tgn:name":"\u00d3nia \u00d3ri",
    "tgn:placetype":[
        "aat:300008795"
    ]
},
  "bbox": [],
  "geometry": {"coordinates":[22.95,37.866667],"type":"Point"}
}