{
  "id": 7446413,
  "type": "Feature",
  "properties": {
    "tgn:hierarchy":[
        "tgn:7446413",
        "tgn:7002444",
        "tgn:5000440",
        "tgn:1000003",
        "tgn:7008591",
        "tgn:7029392"
    ],
    "tgn:id":7446413,
    "tgn:name:en":"Sauchie",
    "tgn:placetype":[
        "aat:300008347"
    ]
},
  "bbox": [],
  "geometry": {"coordinates":[-3.766667,56.133333],"type":"Point"}
}