<<<<<<< HEAD
{
  "id": 2761949,
  "type": "Feature",
  "properties": {
    "tgn:hierarchy":[
        "tgn:2761949",
        "tgn:1000001",
        "tgn:7012149",
        "tgn:7014612",
        "tgn:7007568",
        "tgn:7029392"
    ],
    "tgn:id":2761949,
    "tgn:name":"West Rock",
    "tgn:placetype":[
        "aat:300132348"
    ]
},
  "bbox": [],
  "geometry": {"coordinates":[-73.7,40.9167],"type":"Point"}
}
=======
{"geometry":{"type":"Point","coordinates":[-73.700000,40.916700]},"type":"Feature","properties":{"hierarchy":["tgn:2761949","tgn:1000001","tgn:7012149","tgn:7014612","tgn:7007568","tgn:7029392"],"placetype":["aat:300132348"],"id":2761949,"name:xx":"West Rock"}}
>>>>>>> 03f74aca74312dbeaf24d7e61306dd6a786dc3d0
