{
  "id": 2329143,
  "type": "Feature",
  "properties": {
    "tgn:hierarchy":[
        "tgn:2329143",
        "tgn:1000001",
        "tgn:2001429",
        "tgn:7012149",
        "tgn:7007566",
        "tgn:7029392"
    ],
    "tgn:id":2329143,
    "tgn:name":"Fitzgerald Cienega",
    "tgn:placetype":[
        "aat:300008905"
    ]
},
  "bbox": [],
  "geometry": {"coordinates":[-108.6833,33.9667],"type":"Point"}
}