{
  "id": 2222532,
  "type": "Feature",
  "properties": {
    "tgn:hierarchy":[
        "tgn:2222532",
        "tgn:2000456",
        "tgn:1000001",
        "tgn:7012149",
        "tgn:7007250",
        "tgn:7029392"
    ],
    "tgn:id":2222532,
    "tgn:name":"Carpenter Mountain",
    "tgn:placetype":[
        "aat:300008798"
    ]
},
  "bbox": [],
  "geometry": {"coordinates":[-116.4667,47.05],"type":"Point"}
}