{
  "id": 2476040,
  "type": "Feature",
  "properties": {
    "tgn:hierarchy":[
        "tgn:2476040",
        "tgn:7006450",
        "tgn:1000001",
        "tgn:7012149",
        "tgn:2000089",
        "tgn:7029392"
    ],
    "tgn:id":2476040,
    "tgn:name":"Luke Lake",
    "tgn:placetype":[
        "aat:300008680"
    ]
},
  "bbox": [],
  "geometry": {"coordinates":[-147.9667,66.3667],"type":"Point"}
}