{
  "id": 7591930,
  "type": "Feature",
  "properties": {
    "tgn:hierarchy":[
        "tgn:7591930",
        "tgn:1000004",
        "tgn:7000198",
        "tgn:7000799",
        "tgn:7029392"
    ],
    "tgn:id":7591930,
    "tgn:name:en":"Kotari",
    "tgn:placetype":[
        "aat:300008347"
    ]
},
  "bbox": [],
  "geometry": {"coordinates":[74.242847,33.2422],"type":"Point"}
}