{
  "id": 2553398,
  "type": "Feature",
  "properties": {
    "tgn:hierarchy":[
        "tgn:2553398",
        "tgn:1000001",
        "tgn:7012149",
        "tgn:2000904",
        "tgn:7007256",
        "tgn:7029392"
    ],
    "tgn:id":2553398,
    "tgn:name":"Oak Bayou",
    "tgn:placetype":[
        "aat:300008699"
    ]
},
  "bbox": [],
  "geometry": {"coordinates":[-91.2833,29.65],"type":"Point"}
}