{
  "id": 2628846,
  "type": "Feature",
  "properties": {
    "tgn:hierarchy":[
        "tgn:2628846",
        "tgn:1000001",
        "tgn:2001023",
        "tgn:7012149",
        "tgn:7007521",
        "tgn:7029392"
    ],
    "tgn:id":2628846,
    "tgn:name":"Roscoe Center",
    "tgn:placetype":[
        "aat:300008347"
    ]
},
  "bbox": [],
  "geometry": {"coordinates":[-92.7167,44.25],"type":"Point"}
}