{
  "id": 2131049,
  "type": "Feature",
  "properties": {
    "tgn:hierarchy":[
        "tgn:2131049",
        "tgn:1000001",
        "tgn:7012149",
        "tgn:7020792",
        "tgn:7007524",
        "tgn:7029392"
    ],
    "tgn:id":2131049,
    "tgn:name":"Alpha Mine",
    "tgn:placetype":[
        "aat:300000390"
    ]
},
  "bbox": [],
  "geometry": {"coordinates":[-112.9333,46.0833],"type":"Point"}
}