{
  "id": 7405585,
  "type": "Feature",
  "properties": {
    "tgn:hierarchy":[
        "tgn:7405585",
        "tgn:7005585",
        "tgn:1000001",
        "tgn:7005560",
        "tgn:7029392"
    ],
    "tgn:id":7405585,
    "tgn:name":"Los Limones, Cerros",
    "tgn:placetype":[
        "aat:300008795"
    ]
},
  "bbox": [],
  "geometry": {"coordinates":[-101.583333,17.833333],"type":"Point"}
}