{
  "id": 7469005,
  "type": "Feature",
  "properties": {
    "tgn:hierarchy":[
        "tgn:7469005",
        "tgn:1000004",
        "tgn:1000454",
        "tgn:1000141",
        "tgn:7029392"
    ],
    "tgn:id":7469005,
    "tgn:name":"Fujicun",
    "tgn:placetype":[
        "aat:300008347"
    ]
},
  "bbox": [],
  "geometry": {"coordinates":[121.531365,25.286871],"type":"Point"}
}