{
  "id": 7358546,
  "type": "Feature",
  "properties": {
    "tgn:hierarchy":[
        "tgn:7358546",
        "tgn:7005581",
        "tgn:1000001",
        "tgn:7005560",
        "tgn:7029392"
    ],
    "tgn:id":7358546,
    "tgn:name":"Del Gaucho, Arroyo",
    "tgn:placetype":[
        "aat:300266554",
        "aat:300008699"
    ]
},
  "bbox": [],
  "geometry": {"coordinates":[-105.866667,31.233333],"type":"Point"}
}