{
  "id": 7292440,
  "type": "Feature",
  "properties": {
    "tgn:hierarchy":[
        "tgn:7292440",
        "tgn:1001708",
        "tgn:1000049",
        "tgn:1000002",
        "tgn:7029392"
    ],
    "tgn:id":7292440,
    "tgn:name":"El Encalioto, Quebrada",
    "tgn:placetype":[
        "aat:300008699"
    ]
},
  "bbox": [],
  "geometry": {"coordinates":[-70.65,-33.883333],"type":"Point"}
}