<<<<<<< HEAD
{
  "id": 2768628,
  "type": "Feature",
  "properties": {
    "tgn:hierarchy":[
        "tgn:2768628",
        "tgn:1002201",
        "tgn:1000001",
        "tgn:7012149",
        "tgn:7007517",
        "tgn:7029392"
    ],
    "tgn:id":2768628,
    "tgn:name":"Whiting Pond",
    "tgn:placetype":[
        "aat:300006191"
    ]
},
  "bbox": [],
  "geometry": {"coordinates":[-71.3333,41.9833],"type":"Point"}
}
=======
{"geometry":{"type":"Point","coordinates":[-71.333300,41.983300]},"type":"Feature","properties":{"hierarchy":["tgn:2768628","tgn:1002201","tgn:1000001","tgn:7012149","tgn:7007517","tgn:7029392"],"placetype":["aat:300006191"],"id":2768628,"name:xx":"Whiting Pond"}}
>>>>>>> 03f74aca74312dbeaf24d7e61306dd6a786dc3d0
