{
  "id": 2270065,
  "type": "Feature",
  "properties": {
    "tgn:hierarchy":[
        "tgn:2270065",
        "tgn:1000001",
        "tgn:7012149",
        "tgn:2001919",
        "tgn:7007825",
        "tgn:7029392"
    ],
    "tgn:id":2270065,
    "tgn:name":"Crutcher Lake",
    "tgn:placetype":[
        "aat:300008680"
    ]
},
  "bbox": [],
  "geometry": {"coordinates":[-86.5667,36.3667],"type":"Point"}
}