{
  "id": 7261209,
  "type": "Feature",
  "properties": {
    "tgn:hierarchy":[
        "tgn:7261209",
        "tgn:1000003",
        "tgn:7003613",
        "tgn:7016845",
        "tgn:7029392"
    ],
    "tgn:id":7261209,
    "tgn:name:nl":"Groote Tjariet",
    "tgn:placetype":[
        "aat:300008699"
    ]
},
  "bbox": [],
  "geometry": {"coordinates":[6.866667,53.433333],"type":"Point"}
}