{
  "id": 7164790,
  "type": "Feature",
  "properties": {
    "tgn:hierarchy":[
        "tgn:7164790",
        "tgn:1000003",
        "tgn:7003678",
        "tgn:7000084",
        "tgn:7029392"
    ],
    "tgn:id":7164790,
    "tgn:name":"Hundsr\u00fcck",
    "tgn:placetype":[
        "aat:300008777"
    ]
},
  "bbox": [],
  "geometry": {"coordinates":[10.05,51.133333],"type":"Point"}
}