{
  "id": 7184611,
  "type": "Feature",
  "properties": {
    "tgn:hierarchy":[
        "tgn:7184611",
        "tgn:1000003",
        "tgn:7003678",
        "tgn:7000084",
        "tgn:7029392"
    ],
    "tgn:id":7184611,
    "tgn:name":"Gichen-Bach",
    "tgn:placetype":[
        "aat:300008699"
    ]
},
  "bbox": [],
  "geometry": {"coordinates":[9.85,50.433333],"type":"Point"}
}