{
  "id": 2177151,
  "type": "Feature",
  "properties": {
    "tgn:hierarchy":[
        "tgn:2177151",
        "tgn:1000001",
        "tgn:7012149",
        "tgn:2002048",
        "tgn:7007826",
        "tgn:7029392"
    ],
    "tgn:id":2177151,
    "tgn:name":"Black Point",
    "tgn:placetype":[
        "aat:300008798"
    ]
},
  "bbox": [],
  "geometry": {"coordinates":[-100.1667,32.35],"type":"Point"}
}