{
  "id": 7369809,
  "type": "Feature",
  "properties": {
    "tgn:hierarchy":[
        "tgn:7369809",
        "tgn:1001853",
        "tgn:1000001",
        "tgn:7005560",
        "tgn:7029392"
    ],
    "tgn:id":7369809,
    "tgn:name":"Garc\u00eda",
    "tgn:placetype":[
        "aat:300008347"
    ]
},
  "bbox": [],
  "geometry": {"coordinates":[-101.083333,27.65],"type":"Point"}
}