{
  "id": 2768560,
  "type": "Feature",
  "properties": {
    "tgn:hierarchy":[
        "tgn:2768560",
        "tgn:1000001",
        "tgn:7012149",
        "tgn:1002924",
        "tgn:7007568",
        "tgn:7029392"
    ],
    "tgn:id":2768560,
    "tgn:name":"Whitewood Point",
    "tgn:placetype":[
        "aat:300008850"
    ]
},
  "bbox": [],
  "geometry": {"coordinates":[-73.4833,40.9167],"type":"Point"}
}