{
  "id": 2652462,
  "type": "Feature",
  "properties": {
    "tgn:hierarchy":[
        "tgn:2652462",
        "tgn:1000001",
        "tgn:7012149",
        "tgn:2002191",
        "tgn:7007919",
        "tgn:7029392"
    ],
    "tgn:id":2652462,
    "tgn:name":"Seng Mountain",
    "tgn:placetype":[
        "aat:300008798"
    ]
},
  "bbox": [],
  "geometry": {"coordinates":[-81.5167,36.7167],"type":"Point"}
}