{
  "id": 2425978,
  "type": "Feature",
  "properties": {
    "tgn:hierarchy":[
        "tgn:2425978",
        "tgn:1000001",
        "tgn:7012149",
        "tgn:2001452",
        "tgn:7007566",
        "tgn:7029392"
    ],
    "tgn:id":2425978,
    "tgn:name":"Jones Arroyo",
    "tgn:placetype":[
        "aat:300008699"
    ]
},
  "bbox": [],
  "geometry": {"coordinates":[-108.0333,36.75],"type":"Point"}
}