{
  "id": 2753596,
  "type": "Feature",
  "properties": {
    "tgn:hierarchy":[
        "tgn:2753596",
        "tgn:1000001",
        "tgn:7012149",
        "tgn:2001914",
        "tgn:7007825",
        "tgn:7029392"
    ],
    "tgn:id":2753596,
    "tgn:name":"Waters Estate Lake",
    "tgn:placetype":[
        "aat:300006191"
    ]
},
  "bbox": [],
  "geometry": {"coordinates":[-83.5833,35.8667],"type":"Point"}
}