<<<<<<< HEAD
{
  "id": 7115422,
  "type": "Feature",
  "properties": {
    "tgn:hierarchy":[
        "tgn:7115422",
        "tgn:1000003",
        "tgn:7000094",
        "tgn:7000084",
        "tgn:7029392"
    ],
    "tgn:id":7115422,
    "tgn:name":"Pageluns Berge",
    "tgn:placetype":[
        "aat:300008777"
    ]
},
  "bbox": [],
  "geometry": {"coordinates":[14.05,54.033333],"type":"Point"}
}
=======
{"geometry":{"type":"Point","coordinates":[14.050000,54.033333]},"type":"Feature","properties":{"hierarchy":["tgn:7115422","tgn:1000003","tgn:7000094","tgn:7000084","tgn:7029392"],"placetype":["aat:300008777"],"id":7115422,"name:xx":"Pageluns Berge"}}
>>>>>>> 03f74aca74312dbeaf24d7e61306dd6a786dc3d0
