{
  "id": 7209918,
  "type": "Feature",
  "properties": {
    "tgn:hierarchy":[
        "tgn:7209918",
        "tgn:7003669",
        "tgn:1000003",
        "tgn:7000084",
        "tgn:7029392"
    ],
    "tgn:id":7209918,
    "tgn:name":"Berlach-Berg",
    "tgn:placetype":[
        "aat:300008777"
    ]
},
  "bbox": [],
  "geometry": {"coordinates":[10.916667,47.816667],"type":"Point"}
}