{
  "id": 2297540,
  "type": "Feature",
  "properties": {
    "tgn:hierarchy":[
        "tgn:2297540",
        "tgn:1000001",
        "tgn:7012149",
        "tgn:2001280",
        "tgn:7007524",
        "tgn:7029392"
    ],
    "tgn:id":2297540,
    "tgn:name":"Dry Fork Coulee",
    "tgn:placetype":[
        "aat:300008761"
    ]
},
  "bbox": [],
  "geometry": {"coordinates":[-109.8833,48.3833],"type":"Point"}
}