{
  "id": 2574727,
  "type": "Feature",
  "properties": {
    "tgn:hierarchy":[
        "tgn:2574727",
        "tgn:1000001",
        "tgn:7012149",
        "tgn:2000488",
        "tgn:7007250",
        "tgn:7029392"
    ],
    "tgn:id":2574727,
    "tgn:name":"Pence Butte",
    "tgn:placetype":[
        "aat:300008798"
    ]
},
  "bbox": [],
  "geometry": {"coordinates":[-115.5667,42.75],"type":"Point"}
}