{
  "id": 2282704,
  "type": "Feature",
  "properties": {
    "tgn:hierarchy":[
        "tgn:2282704",
        "tgn:1000001",
        "tgn:7006451",
        "tgn:2000095",
        "tgn:7012149",
        "tgn:7029392"
    ],
    "tgn:id":2282704,
    "tgn:name":"Deerhead Creek",
    "tgn:placetype":[
        "aat:300008706"
    ]
},
  "bbox": [],
  "geometry": {"coordinates":[-109.4167,33.2167],"type":"Point"}
}