{
  "id": 7066749,
  "type": "Feature",
  "properties": {
    "tgn:hierarchy":[
        "tgn:7066749",
        "tgn:7003669",
        "tgn:1000003",
        "tgn:7000084",
        "tgn:7029392"
    ],
    "tgn:id":7066749,
    "tgn:name":"St\u00f6ckaten",
    "tgn:placetype":[
        "aat:300008347"
    ]
},
  "bbox": [],
  "geometry": {"coordinates":[11.833333,50.35],"type":"Point"}
}