<<<<<<< HEAD
{
  "id": 2257922,
  "type": "Feature",
  "properties": {
    "tgn:hierarchy":[
        "tgn:2257922",
        "tgn:1000001",
        "tgn:7012149",
        "tgn:2001717",
        "tgn:7007708",
        "tgn:7029392"
    ],
    "tgn:id":2257922,
    "tgn:name":"Corset Creek",
    "tgn:placetype":[
        "aat:300008706"
    ]
},
  "bbox": [],
  "geometry": {"coordinates":[-122.0667,44.6667],"type":"Point"}
}
=======
{"geometry":{"type":"Point","coordinates":[-122.066700,44.666700]},"type":"Feature","properties":{"hierarchy":["tgn:2257922","tgn:1000001","tgn:7012149","tgn:2001717","tgn:7007708","tgn:7029392"],"placetype":["aat:300008706"],"id":2257922,"name:xx":"Corset Creek"}}
>>>>>>> 03f74aca74312dbeaf24d7e61306dd6a786dc3d0
