{
  "id": 2629269,
  "type": "Feature",
  "properties": {
    "tgn:hierarchy":[
        "tgn:2629269",
        "tgn:2000858",
        "tgn:1000001",
        "tgn:7012149",
        "tgn:7007256",
        "tgn:7029392"
    ],
    "tgn:id":2629269,
    "tgn:name":"Roseaux, Lac aux",
    "tgn:placetype":[
        "aat:300008680"
    ]
},
  "bbox": [],
  "geometry": {"coordinates":[-91.8833,31.05],"type":"Point"}
}