{
  "id": 2309781,
  "type": "Feature",
  "properties": {
    "tgn:hierarchy":[
        "tgn:2309781",
        "tgn:7002659",
        "tgn:1000001",
        "tgn:7012149",
        "tgn:2000062",
        "tgn:7029392"
    ],
    "tgn:id":2309781,
    "tgn:name":"Eastern Hills",
    "tgn:placetype":[
        "aat:300008347"
    ]
},
  "bbox": [],
  "geometry": {"coordinates":[-87.4167,33.15],"type":"Point"}
}