{
  "id": 2761652,
  "type": "Feature",
  "properties": {
    "tgn:hierarchy":[
        "tgn:2761652",
        "tgn:1000001",
        "tgn:7012149",
        "tgn:7007253",
        "tgn:7029392"
    ],
    "tgn:id":2761652,
    "tgn:name":"West Platte River",
    "tgn:placetype":[
        "aat:300008707"
    ]
},
  "bbox": [],
  "geometry": {"coordinates":[-94.4333,41.0833],"type":"Point"}
}