<<<<<<< HEAD
{
  "id": 2761652,
  "type": "Feature",
  "properties": {
    "tgn:hierarchy":[
        "tgn:2761652",
        "tgn:1000001",
        "tgn:7012149",
        "tgn:7007253",
        "tgn:7029392"
    ],
    "tgn:id":2761652,
    "tgn:name":"West Platte River",
    "tgn:placetype":[
        "aat:300008707"
    ]
},
  "bbox": [],
  "geometry": {"coordinates":[-94.4333,41.0833],"type":"Point"}
}
=======
{"geometry":{"type":"Point","coordinates":[-94.433300,41.083300]},"type":"Feature","properties":{"hierarchy":["tgn:2761652","tgn:1000001","tgn:7012149","tgn:7007253","tgn:7029392"],"placetype":["aat:300008707"],"id":2761652,"name:xx":"West Platte River"}}
>>>>>>> 03f74aca74312dbeaf24d7e61306dd6a786dc3d0
