{
  "id": 7352683,
  "type": "Feature",
  "properties": {
    "tgn:hierarchy":[
        "tgn:7352683",
        "tgn:1000001",
        "tgn:1001960",
        "tgn:7005560",
        "tgn:7029392"
    ],
    "tgn:id":7352683,
    "tgn:name":"Basura, Cerro",
    "tgn:placetype":[
        "aat:300008795"
    ]
},
  "bbox": [],
  "geometry": {"coordinates":[-112.278056,30.905278],"type":"Point"}
}