{
  "id": 2326032,
  "type": "Feature",
  "properties": {
    "tgn:hierarchy":[
        "tgn:2326032",
        "tgn:1000001",
        "tgn:2001411",
        "tgn:7012149",
        "tgn:7007526",
        "tgn:7029392"
    ],
    "tgn:id":2326032,
    "tgn:name":"Fifth Street Wash Reservoir",
    "tgn:placetype":[
        "aat:300006191"
    ]
},
  "bbox": [],
  "geometry": {"coordinates":[-115.7667,40.8333],"type":"Point"}
}