{
  "id": 2574943,
  "type": "Feature",
  "properties": {
    "tgn:hierarchy":[
        "tgn:2574943",
        "tgn:1000001",
        "tgn:7012149",
        "tgn:2002164",
        "tgn:7007919",
        "tgn:7029392"
    ],
    "tgn:id":2574943,
    "tgn:name":"Penitentiary Hill",
    "tgn:placetype":[
        "aat:300008798"
    ]
},
  "bbox": [],
  "geometry": {"coordinates":[-81.1833,36.5667],"type":"Point"}
}