{
  "id": 7084807,
  "type": "Feature",
  "properties": {
    "tgn:hierarchy":[
        "tgn:7084807",
        "tgn:1000003",
        "tgn:7003676",
        "tgn:7000084",
        "tgn:7029392"
    ],
    "tgn:id":7084807,
    "tgn:name":"Wetzleben",
    "tgn:placetype":[
        "aat:300008347"
    ]
},
  "bbox": [],
  "geometry": {"coordinates":[10.716667,52.066667],"type":"Point"}
}