{
  "id": 2725220,
  "type": "Feature",
  "properties": {
    "tgn:hierarchy":[
        "tgn:2725220",
        "tgn:1000001",
        "tgn:2001418",
        "tgn:7012149",
        "tgn:7007526",
        "tgn:7029392"
    ],
    "tgn:id":2725220,
    "tgn:name":"Tonopah City Mine",
    "tgn:placetype":[
        "aat:300000390"
    ]
},
  "bbox": [],
  "geometry": {"coordinates":[-117.2167,38.05],"type":"Point"}
}