{
  "id": 2167265,
  "type": "Feature",
  "properties": {
    "tgn:hierarchy":[
        "tgn:2167265",
        "tgn:1000001",
        "tgn:1002479",
        "tgn:7012149",
        "tgn:7007240",
        "tgn:7029392"
    ],
    "tgn:id":2167265,
    "tgn:name":"Big Cockroach Mound",
    "tgn:placetype":[
        "aat:300008798"
    ]
},
  "bbox": [],
  "geometry": {"coordinates":[-82.5167,27.6833],"type":"Point"}
}