{
  "id": 2036308,
  "type": "Feature",
  "properties": {
    "tgn:hierarchy":[
        "tgn:2036308",
        "tgn:1000001",
        "tgn:7012149",
        "tgn:2000764",
        "tgn:7007254",
        "tgn:7029392"
    ],
    "tgn:id":2036308,
    "tgn:name":"Edwardsville",
    "tgn:placetype":[
        "aat:300008347"
    ]
},
  "bbox": [],
  "geometry": {"coordinates":[-94.8167,39.05],"type":"Point"}
}