{
  "id": 2021172,
  "type": "Feature",
  "properties": {
    "tgn:hierarchy":[
        "tgn:2021172",
        "tgn:2000257",
        "tgn:1000001",
        "tgn:7012149",
        "tgn:7007240",
        "tgn:7029392"
    ],
    "tgn:id":2021172,
    "tgn:name":"Sanderson",
    "tgn:placetype":[
        "aat:300008347"
    ]
},
  "bbox": [],
  "geometry": {"coordinates":[-82.2667,30.25],"type":"Point"}
}