{
  "id": 2329321,
  "type": "Feature",
  "properties": {
    "tgn:hierarchy":[
        "tgn:2329321",
        "tgn:1000001",
        "tgn:7006451",
        "tgn:7012149",
        "tgn:2000099",
        "tgn:7029392"
    ],
    "tgn:id":2329321,
    "tgn:name":"Five Houses Butte",
    "tgn:placetype":[
        "aat:300266640"
    ]
},
  "bbox": [],
  "geometry": {"coordinates":[-110.3333,35.7667],"type":"Point"}
}