{
  "id": 2587112,
  "type": "Feature",
  "properties": {
    "tgn:hierarchy":[
        "tgn:2587112",
        "tgn:7006450",
        "tgn:1000001",
        "tgn:7012149",
        "tgn:2000085",
        "tgn:7029392"
    ],
    "tgn:id":2587112,
    "tgn:name":"Plateau Lake",
    "tgn:placetype":[
        "aat:300008680"
    ]
},
  "bbox": [],
  "geometry": {"coordinates":[-144.4167,63.6167],"type":"Point"}
}