{
  "id": 7283630,
  "type": "Feature",
  "properties": {
    "tgn:hierarchy":[
        "tgn:7283630",
        "tgn:1001699",
        "tgn:1000049",
        "tgn:1000002",
        "tgn:7029392"
    ],
    "tgn:id":7283630,
    "tgn:name":"Pantanoso, Estero",
    "tgn:placetype":[
        "aat:300008699"
    ]
},
  "bbox": [],
  "geometry": {"coordinates":[-72.65,-40.416667],"type":"Point"}
}