<<<<<<< HEAD
{
  "id": 7173605,
  "type": "Feature",
  "properties": {
    "tgn:hierarchy":[
        "tgn:7173605",
        "tgn:1000003",
        "tgn:7003676",
        "tgn:7000084",
        "tgn:7029392"
    ],
    "tgn:id":7173605,
    "tgn:name":"Gro\u00df Ottenhaus",
    "tgn:placetype":[
        "aat:300000206"
    ]
},
  "bbox": [],
  "geometry": {"coordinates":[10.116667,52.583333],"type":"Point"}
}
=======
{"geometry":{"type":"Point","coordinates":[10.116667,52.583333]},"type":"Feature","properties":{"hierarchy":["tgn:7173605","tgn:1000003","tgn:7003676","tgn:7000084","tgn:7029392"],"placetype":["aat:300000206"],"id":7173605,"name:xx":"Gro\u00df Ottenhaus"}}
>>>>>>> 03f74aca74312dbeaf24d7e61306dd6a786dc3d0
