{
  "id": 7173605,
  "type": "Feature",
  "properties": {
    "tgn:hierarchy":[
        "tgn:7173605",
        "tgn:1000003",
        "tgn:7003676",
        "tgn:7000084",
        "tgn:7029392"
    ],
    "tgn:id":7173605,
    "tgn:name":"Gro\u00df Ottenhaus",
    "tgn:placetype":[
        "aat:300000206"
    ]
},
  "bbox": [],
  "geometry": {"coordinates":[10.116667,52.583333],"type":"Point"}
}