{
  "id": 2340397,
  "type": "Feature",
  "properties": {
    "tgn:hierarchy":[
        "tgn:2340397",
        "tgn:1000001",
        "tgn:7012149",
        "tgn:7007157",
        "tgn:2000187",
        "tgn:7029392"
    ],
    "tgn:id":2340397,
    "tgn:name":"French Hotel Creek",
    "tgn:placetype":[
        "aat:300008706"
    ]
},
  "bbox": [],
  "geometry": {"coordinates":[-121.2667,39.85],"type":"Point"}
}