<<<<<<< HEAD
{
  "id": 7366872,
  "type": "Feature",
  "properties": {
    "tgn:hierarchy":[
        "tgn:7366872",
        "tgn:1000001",
        "tgn:7005595",
        "tgn:7005560",
        "tgn:7029392"
    ],
    "tgn:id":7366872,
    "tgn:name":"Rancho El Rinconcito",
    "tgn:placetype":[
        "aat:300000241"
    ]
},
  "bbox": [],
  "geometry": {"coordinates":[-107.716667,25.466667],"type":"Point"}
}
=======
{"geometry":{"type":"Point","coordinates":[-107.716667,25.466667]},"type":"Feature","properties":{"hierarchy":["tgn:7366872","tgn:1000001","tgn:7005595","tgn:7005560","tgn:7029392"],"placetype":["aat:300000241"],"id":7366872,"name:xx":"Rancho El Rinconcito"}}
>>>>>>> 03f74aca74312dbeaf24d7e61306dd6a786dc3d0
