{
  "id": 2517460,
  "type": "Feature",
  "properties": {
    "tgn:hierarchy":[
        "tgn:2517460",
        "tgn:1000001",
        "tgn:7012149",
        "tgn:2001207",
        "tgn:7007523",
        "tgn:7029392"
    ],
    "tgn:id":2517460,
    "tgn:name":"Minor Creek",
    "tgn:placetype":[
        "aat:300008706"
    ]
},
  "bbox": [],
  "geometry": {"coordinates":[-90.6833,37.5667],"type":"Point"}
}