{
  "id": 7418044,
  "type": "Feature",
  "properties": {
    "tgn:hierarchy":[
        "tgn:7418044",
        "tgn:1000001",
        "tgn:7005591",
        "tgn:7005560",
        "tgn:7029392"
    ],
    "tgn:id":7418044,
    "tgn:name:es":"Ojo de Agua",
    "tgn:placetype":[
        "aat:300008347"
    ]
},
  "bbox": [],
  "geometry": {"coordinates":[-94.257778,16.282778],"type":"Point"}
}