{
  "id": 2299168,
  "type": "Feature",
  "properties": {
    "tgn:hierarchy":[
        "tgn:2299168",
        "tgn:2002305",
        "tgn:1000001",
        "tgn:7012149",
        "tgn:7007922",
        "tgn:7029392"
    ],
    "tgn:id":2299168,
    "tgn:name":"Duck Creek",
    "tgn:placetype":[
        "aat:300008706"
    ]
},
  "bbox": [],
  "geometry": {"coordinates":[-89.7333,43.9167],"type":"Point"}
}