{
  "id": 2637533,
  "type": "Feature",
  "properties": {
    "tgn:hierarchy":[
        "tgn:2637533",
        "tgn:1000001",
        "tgn:7012149",
        "tgn:1002827",
        "tgn:7007252",
        "tgn:7029392"
    ],
    "tgn:id":2637533,
    "tgn:name":"Saint Magdalen",
    "tgn:placetype":[
        "aat:300008347"
    ]
},
  "bbox": [],
  "geometry": {"coordinates":[-85.3833,38.95],"type":"Point"}
}