{
  "id": 7509540,
  "type": "Feature",
  "properties": {
    "tgn:hierarchy":[
        "tgn:7509540",
        "tgn:1008380",
        "tgn:1000226",
        "tgn:7018426",
        "tgn:1000006",
        "tgn:7029392"
    ],
    "tgn:id":7509540,
    "tgn:name:en":"Waikato River",
    "tgn:placetype":[
        "aat:300008699"
    ]
},
  "bbox": [],
  "geometry": {"coordinates":[174.716667,-37.383333],"type":"Point"}
}