<<<<<<< HEAD
{
  "id": 7479173,
  "type": "Feature",
  "properties": {
    "tgn:hierarchy":[
        "tgn:7479173",
        "tgn:1000004",
        "tgn:7490934",
        "tgn:1000141",
        "tgn:7029392"
    ],
    "tgn:id":7479173,
    "tgn:name":"Jiali Rongminzhijia",
    "tgn:placetype":[
        "aat:300005433"
    ]
},
  "bbox": [],
  "geometry": {"coordinates":[120.123333,23.103889],"type":"Point"}
}
=======
{"geometry":{"type":"Point","coordinates":[120.123333,23.103889]},"type":"Feature","properties":{"hierarchy":["tgn:7479173","tgn:1000004","tgn:7490934","tgn:1000141","tgn:7029392"],"placetype":["aat:300005433"],"id":7479173,"name:xx":"Jiali Rongminzhijia"}}
>>>>>>> 03f74aca74312dbeaf24d7e61306dd6a786dc3d0
