<<<<<<< HEAD
{
  "id": 2330363,
  "type": "Feature",
  "properties": {
    "tgn:hierarchy":[
        "tgn:2330363",
        "tgn:1000001",
        "tgn:2000861",
        "tgn:7012149",
        "tgn:7007256",
        "tgn:7029392"
    ],
    "tgn:id":2330363,
    "tgn:name":"Flat Branch",
    "tgn:placetype":[
        "aat:300008699"
    ]
},
  "bbox": [],
  "geometry": {"coordinates":[-93.6,32.85],"type":"Point"}
}
=======
{"geometry":{"type":"Point","coordinates":[-93.600000,32.850000]},"type":"Feature","properties":{"hierarchy":["tgn:2330363","tgn:1000001","tgn:2000861","tgn:7012149","tgn:7007256","tgn:7029392"],"placetype":["aat:300008699"],"id":2330363,"name:xx":"Flat Branch"}}
>>>>>>> 03f74aca74312dbeaf24d7e61306dd6a786dc3d0
