{
  "id": 7075693,
  "type": "Feature",
  "properties": {
    "tgn:hierarchy":[
        "tgn:7075693",
        "tgn:1000003",
        "tgn:7003685",
        "tgn:7000084",
        "tgn:7029392"
    ],
    "tgn:id":7075693,
    "tgn:name":"Zittauer Stadtwald",
    "tgn:placetype":[
        "aat:300008863"
    ]
},
  "bbox": [],
  "geometry": {"coordinates":[14.766667,50.85],"type":"Point"}
}