{
  "id": 7588673,
  "type": "Feature",
  "properties": {
    "tgn:hierarchy":[
        "tgn:7588673",
        "tgn:1000004",
        "tgn:7000198",
        "tgn:7000799",
        "tgn:7029392"
    ],
    "tgn:id":7588673,
    "tgn:name:en":"Mangi\u0101l",
    "tgn:placetype":[
        "aat:300008347"
    ]
},
  "bbox": [],
  "geometry": {"coordinates":[74.08901,33.792784],"type":"Point"}
}