{
  "id": 2441901,
  "type": "Feature",
  "properties": {
    "tgn:hierarchy":[
        "tgn:2441901",
        "tgn:1000001",
        "tgn:7012149",
        "tgn:2001286",
        "tgn:7007524",
        "tgn:7029392"
    ],
    "tgn:id":2441901,
    "tgn:name":"Koo Koo Creek",
    "tgn:placetype":[
        "aat:300008706"
    ]
},
  "bbox": [],
  "geometry": {"coordinates":[-115.6833,48.9667],"type":"Point"}
}