{
  "id": 1012455,
  "type": "Feature",
  "properties": {
    "tgn:hierarchy":[
        "tgn:1012455",
        "tgn:1000004",
        "tgn:1001609",
        "tgn:1000135",
        "tgn:7029392"
    ],
    "tgn:id":1012455,
    "tgn:name":"Santa Cruz Point",
    "tgn:placetype":[
        "aat:300386846"
    ]
},
  "bbox": [],
  "geometry": {"coordinates":[119.8667,15.7333],"type":"Point"}
}