{
  "id": 2647948,
  "type": "Feature",
  "properties": {
    "tgn:hierarchy":[
        "tgn:2647948",
        "tgn:1000001",
        "tgn:7012149",
        "tgn:2001713",
        "tgn:7007708",
        "tgn:7029392"
    ],
    "tgn:id":2647948,
    "tgn:name":"Schoolhouse Creek",
    "tgn:placetype":[
        "aat:300008706"
    ]
},
  "bbox": [],
  "geometry": {"coordinates":[-123.35,42.5333],"type":"Point"}
}