{
  "id": 2490943,
  "type": "Feature",
  "properties": {
    "tgn:hierarchy":[
        "tgn:2490943",
        "tgn:1000001",
        "tgn:7012149",
        "tgn:2002363",
        "tgn:7007922",
        "tgn:7029392"
    ],
    "tgn:id":2490943,
    "tgn:name":"Mansur Bay",
    "tgn:placetype":[
        "aat:300132316"
    ]
},
  "bbox": [],
  "geometry": {"coordinates":[-88.45,44.1333],"type":"Point"}
}