{
  "id": 2733087,
  "type": "Feature",
  "properties": {
    "tgn:hierarchy":[
        "tgn:2733087",
        "tgn:2000767",
        "tgn:1000001",
        "tgn:7012149",
        "tgn:7007255",
        "tgn:7029392"
    ],
    "tgn:id":2733087,
    "tgn:name":"Turkey Lake",
    "tgn:placetype":[
        "aat:300006191"
    ]
},
  "bbox": [],
  "geometry": {"coordinates":[-89.0333,37.1667],"type":"Point"}
}