<<<<<<< HEAD
{
  "id": 2762736,
  "type": "Feature",
  "properties": {
    "tgn:hierarchy":[
        "tgn:2762736",
        "tgn:1000001",
        "tgn:2001418",
        "tgn:7012149",
        "tgn:7007526",
        "tgn:7029392"
    ],
    "tgn:id":2762736,
    "tgn:name":"Western Extension Mine",
    "tgn:placetype":[
        "aat:300000390"
    ]
},
  "bbox": [],
  "geometry": {"coordinates":[-116.4,38.3667],"type":"Point"}
}
=======
{"geometry":{"type":"Point","coordinates":[-116.400000,38.366700]},"type":"Feature","properties":{"hierarchy":["tgn:2762736","tgn:1000001","tgn:2001418","tgn:7012149","tgn:7007526","tgn:7029392"],"placetype":["aat:300000390"],"id":2762736,"name:xx":"Western Extension Mine"}}
>>>>>>> 03f74aca74312dbeaf24d7e61306dd6a786dc3d0
