{
  "id": 7184566,
  "type": "Feature",
  "properties": {
    "tgn:hierarchy":[
        "tgn:7184566",
        "tgn:1000003",
        "tgn:7003676",
        "tgn:7000084",
        "tgn:7029392"
    ],
    "tgn:id":7184566,
    "tgn:name":"Giehlermoor",
    "tgn:placetype":[
        "aat:300008347"
    ]
},
  "bbox": [],
  "geometry": {"coordinates":[8.95,53.333333],"type":"Point"}
}