<<<<<<< HEAD
{
  "id": 7111612,
  "type": "Feature",
  "properties": {
    "tgn:hierarchy":[
        "tgn:7111612",
        "tgn:7003692",
        "tgn:1000003",
        "tgn:7000084",
        "tgn:7029392"
    ],
    "tgn:id":7111612,
    "tgn:name":"Risiberg",
    "tgn:placetype":[
        "aat:300008347"
    ]
},
  "bbox": [],
  "geometry": {"coordinates":[8.816667,48.05],"type":"Point"}
}
=======
{"geometry":{"type":"Point","coordinates":[8.816667,48.050000]},"type":"Feature","properties":{"hierarchy":["tgn:7111612","tgn:7003692","tgn:1000003","tgn:7000084","tgn:7029392"],"placetype":["aat:300008347"],"id":7111612,"name:xx":"Risiberg"}}
>>>>>>> 03f74aca74312dbeaf24d7e61306dd6a786dc3d0
