{
  "id": 2657570,
  "type": "Feature",
  "properties": {
    "tgn:hierarchy":[
        "tgn:2657570",
        "tgn:1000001",
        "tgn:7012149",
        "tgn:2000491",
        "tgn:7007250",
        "tgn:7029392"
    ],
    "tgn:id":2657570,
    "tgn:name":"Shehee Gulch",
    "tgn:placetype":[
        "aat:300008761"
    ]
},
  "bbox": [],
  "geometry": {"coordinates":[-115.95,47.6333],"type":"Point"}
}