<<<<<<< HEAD
{
  "id": 7246257,
  "type": "Feature",
  "properties": {
    "tgn:hierarchy":[
        "tgn:7246257",
        "tgn:7003460",
        "tgn:1000003",
        "tgn:1000063",
        "tgn:4012014",
        "tgn:7029392"
    ],
    "tgn:id":7246257,
    "tgn:name":"Borgeuc\u00e9",
    "tgn:placetype":[
        "aat:300008347"
    ]
},
  "bbox": [],
  "geometry": {"coordinates":[6.033333,50.383333],"type":"Point"}
}
=======
{"geometry":{"type":"Point","coordinates":[6.033333,50.383333]},"type":"Feature","properties":{"hierarchy":["tgn:7246257","tgn:7003460","tgn:1000003","tgn:1000063","tgn:4012014","tgn:7029392"],"placetype":["aat:300008347"],"id":7246257,"name:xx":"Borgeuc\u00e9"}}
>>>>>>> 03f74aca74312dbeaf24d7e61306dd6a786dc3d0
