<<<<<<< HEAD
{
  "id": 7373412,
  "type": "Feature",
  "properties": {
    "tgn:hierarchy":[
        "tgn:7373412",
        "tgn:7005581",
        "tgn:1000001",
        "tgn:7005560",
        "tgn:7029392"
    ],
    "tgn:id":7373412,
    "tgn:name":"Rancho La Ci\u00e9naga",
    "tgn:placetype":[
        "aat:300000241"
    ]
},
  "bbox": [],
  "geometry": {"coordinates":[-105.05,29.4],"type":"Point"}
}
=======
{"geometry":{"type":"Point","coordinates":[-105.050000,29.400000]},"type":"Feature","properties":{"hierarchy":["tgn:7373412","tgn:7005581","tgn:1000001","tgn:7005560","tgn:7029392"],"placetype":["aat:300000241"],"id":7373412,"name:xx":"Rancho La Ci\u00e9naga"}}
>>>>>>> 03f74aca74312dbeaf24d7e61306dd6a786dc3d0
