{
  "id": 2362544,
  "type": "Feature",
  "properties": {
    "tgn:hierarchy":[
        "tgn:2362544",
        "tgn:1000001",
        "tgn:7016172",
        "tgn:7012149",
        "tgn:2000146",
        "tgn:7029392"
    ],
    "tgn:id":2362544,
    "tgn:name":"Greasy Valley",
    "tgn:placetype":[
        "aat:300008761"
    ]
},
  "bbox": [],
  "geometry": {"coordinates":[-93.5667,35.25],"type":"Point"}
}