{
  "id": 7030668,
  "type": "Feature",
  "properties": {
    "tgn:hierarchy":[
        "tgn:7030668",
        "tgn:1003567",
        "tgn:7002445",
        "tgn:1000003",
        "tgn:7029507",
        "tgn:7008591",
        "tgn:7029392"
    ],
    "tgn:id":7030668,
    "tgn:name:en":"Wilsden",
    "tgn:placetype":[
        "aat:300008347",
        "aat:300008372"
    ]
},
  "bbox": [],
  "geometry": {"coordinates":[-1.866667,53.816667],"type":"Point"}
}