{
  "id": 2751943,
  "type": "Feature",
  "properties": {
    "tgn:hierarchy":[
        "tgn:2751943",
        "tgn:1000001",
        "tgn:7012149",
        "tgn:2001274",
        "tgn:7007524",
        "tgn:7029392"
    ],
    "tgn:id":2751943,
    "tgn:name":"Warrior Creek",
    "tgn:placetype":[
        "aat:300008706"
    ]
},
  "bbox": [],
  "geometry": {"coordinates":[-113.6667,47.8167],"type":"Point"}
}