{
  "id": 7342236,
  "type": "Feature",
  "properties": {
    "tgn:hierarchy":[
        "tgn:7342236",
        "tgn:7008911",
        "tgn:1000003",
        "tgn:7002763",
        "tgn:1000095",
        "tgn:7029392"
    ],
    "tgn:id":7342236,
    "tgn:name":"Cam\u00e1s",
    "tgn:placetype":[
        "aat:300008347"
    ]
},
  "bbox": [],
  "geometry": {"coordinates":[-5.45,43.383333],"type":"Point"}
}