{
  "id": 2331926,
  "type": "Feature",
  "properties": {
    "tgn:hierarchy":[
        "tgn:2331926",
        "tgn:1000001",
        "tgn:7012149",
        "tgn:2000930",
        "tgn:7007515",
        "tgn:7029392"
    ],
    "tgn:id":2331926,
    "tgn:name":"Fletcher Ponds",
    "tgn:placetype":[
        "aat:300008680"
    ]
},
  "bbox": [],
  "geometry": {"coordinates":[-69.9333,45.6667],"type":"Point"}
}