<<<<<<< HEAD
{
  "id": 2331926,
  "type": "Feature",
  "properties": {
    "tgn:hierarchy":[
        "tgn:2331926",
        "tgn:1000001",
        "tgn:7012149",
        "tgn:2000930",
        "tgn:7007515",
        "tgn:7029392"
    ],
    "tgn:id":2331926,
    "tgn:name":"Fletcher Ponds",
    "tgn:placetype":[
        "aat:300008680"
    ]
},
  "bbox": [],
  "geometry": {"coordinates":[-69.9333,45.6667],"type":"Point"}
}
=======
{"geometry":{"type":"Point","coordinates":[-69.933300,45.666700]},"type":"Feature","properties":{"hierarchy":["tgn:2331926","tgn:1000001","tgn:7012149","tgn:2000930","tgn:7007515","tgn:7029392"],"placetype":["aat:300008680"],"id":2331926,"name:xx":"Fletcher Ponds"}}
>>>>>>> 03f74aca74312dbeaf24d7e61306dd6a786dc3d0
