{
  "id": 2550853,
  "type": "Feature",
  "properties": {
    "tgn:hierarchy":[
        "tgn:2550853",
        "tgn:7002659",
        "tgn:1000001",
        "tgn:2000011",
        "tgn:7012149",
        "tgn:7029392"
    ],
    "tgn:id":2550853,
    "tgn:name":"Norwood Pond",
    "tgn:placetype":[
        "aat:300006191"
    ]
},
  "bbox": [],
  "geometry": {"coordinates":[-88.0833,32.15],"type":"Point"}
}