{
  "id": 2293564,
  "type": "Feature",
  "properties": {
    "tgn:hierarchy":[
        "tgn:2293564",
        "tgn:1000001",
        "tgn:7006451",
        "tgn:7012149",
        "tgn:2000103",
        "tgn:7029392"
    ],
    "tgn:id":2293564,
    "tgn:name":"Double Tank",
    "tgn:placetype":[
        "aat:300006191"
    ]
},
  "bbox": [],
  "geometry": {"coordinates":[-111.7667,34.1333],"type":"Point"}
}