{
  "id": 2404142,
  "type": "Feature",
  "properties": {
    "tgn:hierarchy":[
        "tgn:2404142",
        "tgn:1000001",
        "tgn:7012149",
        "tgn:2001852",
        "tgn:7007825",
        "tgn:7029392"
    ],
    "tgn:id":2404142,
    "tgn:name":"Howland Hollow",
    "tgn:placetype":[
        "aat:300008761"
    ]
},
  "bbox": [],
  "geometry": {"coordinates":[-86.1833,35.65],"type":"Point"}
}