{
  "id": 7219622,
  "type": "Feature",
  "properties": {
    "tgn:hierarchy":[
        "tgn:7219622",
        "tgn:7011330",
        "tgn:7002674",
        "tgn:1000003",
        "tgn:1000074",
        "tgn:7029392"
    ],
    "tgn:id":7219622,
    "tgn:name":"Evangelistr\u00eda",
    "tgn:placetype":[
        "aat:300007466"
    ]
},
  "bbox": [],
  "geometry": {"coordinates":[26.930278,36.736389],"type":"Point"}
}