{
  "id": 2561259,
  "type": "Feature",
  "properties": {
    "tgn:hierarchy":[
        "tgn:2561259",
        "tgn:7002659",
        "tgn:1000001",
        "tgn:2000012",
        "tgn:7012149",
        "tgn:7029392"
    ],
    "tgn:id":2561259,
    "tgn:name":"Osage Woodyard Landing",
    "tgn:placetype":[
        "aat:300008347"
    ]
},
  "bbox": [],
  "geometry": {"coordinates":[-88.1333,31.85],"type":"Point"}
}