{
  "id": 7422728,
  "type": "Feature",
  "properties": {
    "tgn:hierarchy":[
        "tgn:7422728",
        "tgn:1000001",
        "tgn:1001960",
        "tgn:7005560",
        "tgn:7029392"
    ],
    "tgn:id":7422728,
    "tgn:name":"El Batamote",
    "tgn:placetype":[
        "aat:300008347"
    ]
},
  "bbox": [],
  "geometry": {"coordinates":[-111.908611,30.781111],"type":"Point"}
}