{
  "id": 2693003,
  "type": "Feature",
  "properties": {
    "tgn:hierarchy":[
        "tgn:2693003",
        "tgn:1000001",
        "tgn:7016172",
        "tgn:7012149",
        "tgn:7029392"
    ],
    "tgn:id":2693003,
    "tgn:name":"Steep Bank Creek",
    "tgn:placetype":[
        "aat:300008706"
    ]
},
  "bbox": [],
  "geometry": {"coordinates":[-91.3667,35.9333],"type":"Point"}
}