{
  "id": 2085896,
  "type": "Feature",
  "properties": {
    "tgn:hierarchy":[
        "tgn:2085896",
        "tgn:1000001",
        "tgn:7012149",
        "tgn:7014185",
        "tgn:7007710",
        "tgn:7029392"
    ],
    "tgn:id":2085896,
    "tgn:name":"Albany",
    "tgn:placetype":[
        "aat:300008347"
    ]
},
  "bbox": [],
  "geometry": {"coordinates":[-79.8667,40.0333],"type":"Point"}
}