{
  "id": 2401797,
  "type": "Feature",
  "properties": {
    "tgn:hierarchy":[
        "tgn:2401797",
        "tgn:1000001",
        "tgn:7012149",
        "tgn:2001189",
        "tgn:7007523",
        "tgn:7029392"
    ],
    "tgn:id":2401797,
    "tgn:name":"Horseshoe Lake",
    "tgn:placetype":[
        "aat:300008680"
    ]
},
  "bbox": [],
  "geometry": {"coordinates":[-93.0333,38.9167],"type":"Point"}
}