{
  "id": 7025871,
  "type": "Feature",
  "properties": {
    "tgn:hierarchy":[
        "tgn:7025871",
        "tgn:7002445",
        "tgn:1000003",
        "tgn:7011961",
        "tgn:7008591",
        "tgn:7029392"
    ],
    "tgn:id":7025871,
    "tgn:name:ang":"Contone",
    "tgn:placetype":[
        "aat:300008347"
    ]
},
  "bbox": [],
  "geometry": {"coordinates":[-2.5667,50.95],"type":"Point"}
}