{
  "id": 2477063,
  "type": "Feature",
  "properties": {
    "tgn:hierarchy":[
        "tgn:2477063",
        "tgn:1000001",
        "tgn:7012149",
        "tgn:1002793",
        "tgn:7007240",
        "tgn:7029392"
    ],
    "tgn:id":2477063,
    "tgn:name":"Lynchburg",
    "tgn:placetype":[
        "aat:300008347"
    ]
},
  "bbox": [],
  "geometry": {"coordinates":[-81.75,28.0833],"type":"Point"}
}