{
  "id": 2785884,
  "type": "Feature",
  "properties": {
    "tgn:hierarchy":[
        "tgn:2785884",
        "tgn:1000001",
        "tgn:7012149",
        "tgn:2001708",
        "tgn:7007708",
        "tgn:7029392"
    ],
    "tgn:id":2785884,
    "tgn:name":"York and Rannels Mine",
    "tgn:placetype":[
        "aat:300000390"
    ]
},
  "bbox": [],
  "geometry": {"coordinates":[-119.2833,44.1833],"type":"Point"}
}