{
  "id": 2432873,
  "type": "Feature",
  "properties": {
    "tgn:hierarchy":[
        "tgn:2432873",
        "tgn:7002659",
        "tgn:1000001",
        "tgn:2000016",
        "tgn:7012149",
        "tgn:7029392"
    ],
    "tgn:id":2432873,
    "tgn:name":"Keeton Cave",
    "tgn:placetype":[
        "aat:300008746"
    ]
},
  "bbox": [],
  "geometry": {"coordinates":[-87.75,34.7167],"type":"Point"}
}