{
  "id": 7332303,
  "type": "Feature",
  "properties": {
    "tgn:hierarchy":[
        "tgn:7332303",
        "tgn:7002760",
        "tgn:1000003",
        "tgn:1000095",
        "tgn:7029392"
    ],
    "tgn:id":7332303,
    "tgn:name":"Labarces",
    "tgn:placetype":[
        "aat:300008347"
    ]
},
  "bbox": [],
  "geometry": {"coordinates":[-4.383333,43.333333],"type":"Point"}
}