{
  "id": 2673372,
  "type": "Feature",
  "properties": {
    "tgn:hierarchy":[
        "tgn:2673372",
        "tgn:1000001",
        "tgn:7012149",
        "tgn:2002336",
        "tgn:7007922",
        "tgn:7029392"
    ],
    "tgn:id":2673372,
    "tgn:name":"Snell",
    "tgn:placetype":[
        "aat:300008347"
    ]
},
  "bbox": [],
  "geometry": {"coordinates":[-89.2833,45.05],"type":"Point"}
}