{
  "id": 2155136,
  "type": "Feature",
  "properties": {
    "tgn:hierarchy":[
        "tgn:2155136",
        "tgn:1000001",
        "tgn:7012149",
        "tgn:2002249",
        "tgn:7007920",
        "tgn:7029392"
    ],
    "tgn:id":2155136,
    "tgn:name":"Bear Lake",
    "tgn:placetype":[
        "aat:300008680"
    ]
},
  "bbox": [],
  "geometry": {"coordinates":[-117.35,47.9167],"type":"Point"}
}