<<<<<<< HEAD
{
  "id": 2155136,
  "type": "Feature",
  "properties": {
    "tgn:hierarchy":[
        "tgn:2155136",
        "tgn:1000001",
        "tgn:7012149",
        "tgn:2002249",
        "tgn:7007920",
        "tgn:7029392"
    ],
    "tgn:id":2155136,
    "tgn:name":"Bear Lake",
    "tgn:placetype":[
        "aat:300008680"
    ]
},
  "bbox": [],
  "geometry": {"coordinates":[-117.35,47.9167],"type":"Point"}
}
=======
{"geometry":{"type":"Point","coordinates":[-117.350000,47.916700]},"type":"Feature","properties":{"hierarchy":["tgn:2155136","tgn:1000001","tgn:7012149","tgn:2002249","tgn:7007920","tgn:7029392"],"placetype":["aat:300008680"],"id":2155136,"name:xx":"Bear Lake"}}
>>>>>>> 03f74aca74312dbeaf24d7e61306dd6a786dc3d0
