<<<<<<< HEAD
{
  "id": 2158822,
  "type": "Feature",
  "properties": {
    "tgn:hierarchy":[
        "tgn:2158822",
        "tgn:1000001",
        "tgn:7012149",
        "tgn:1003041",
        "tgn:7007710",
        "tgn:7029392"
    ],
    "tgn:id":2158822,
    "tgn:name":"Becker Brook",
    "tgn:placetype":[
        "aat:300008699"
    ]
},
  "bbox": [],
  "geometry": {"coordinates":[-76.2167,41.45],"type":"Point"}
}
=======
{"geometry":{"type":"Point","coordinates":[-76.216700,41.450000]},"type":"Feature","properties":{"hierarchy":["tgn:2158822","tgn:1000001","tgn:7012149","tgn:1003041","tgn:7007710","tgn:7029392"],"placetype":["aat:300008699"],"id":2158822,"name:xx":"Becker Brook"}}
>>>>>>> 03f74aca74312dbeaf24d7e61306dd6a786dc3d0
