{
  "id": 7314155,
  "type": "Feature",
  "properties": {
    "tgn:hierarchy":[
        "tgn:7314155",
        "tgn:1001695",
        "tgn:1000049",
        "tgn:1000002",
        "tgn:7029392"
    ],
    "tgn:id":7314155,
    "tgn:name":"Los Maitenes, Cerro",
    "tgn:placetype":[
        "aat:300008795"
    ]
},
  "bbox": [],
  "geometry": {"coordinates":[-71.566667,-34.366667],"type":"Point"}
}