{
  "id": 2696194,
  "type": "Feature",
  "properties": {
    "tgn:hierarchy":[
        "tgn:2696194",
        "tgn:1000001",
        "tgn:7012149",
        "tgn:2001718",
        "tgn:7007708",
        "tgn:7029392"
    ],
    "tgn:id":2696194,
    "tgn:name":"Stone",
    "tgn:placetype":[
        "aat:300008347"
    ]
},
  "bbox": [],
  "geometry": {"coordinates":[-117.4833,44.2167],"type":"Point"}
}