{
  "id": 1117623,
  "type": "Feature",
  "properties": {
    "tgn:hierarchy":[
        "tgn:1117623",
        "tgn:7003024",
        "tgn:1000003",
        "tgn:1000062",
        "tgn:7029392"
    ],
    "tgn:id":1117623,
    "tgn:name":"Ossiacher See",
    "tgn:placetype":[
        "aat:300008680"
    ]
},
  "bbox": [],
  "geometry": {"coordinates":[13.9167,46.6667],"type":"Point"}
}