{
  "id": 1054056,
  "type": "Feature",
  "properties": {
    "tgn:hierarchy":[
        "tgn:1054056",
        "tgn:1003373",
        "tgn:1000004",
        "tgn:7018214",
        "tgn:7002435",
        "tgn:7029392"
    ],
    "tgn:id":1054056,
    "tgn:name":"Golumet",
    "tgn:placetype":[
        "aat:300008347"
    ]
},
  "bbox": [],
  "geometry": {"coordinates":[102.3667,53.0833],"type":"Point"}
}