{
  "id": 2455309,
  "type": "Feature",
  "properties": {
    "tgn:hierarchy":[
        "tgn:2455309",
        "tgn:1000001",
        "tgn:7012149",
        "tgn:2002010",
        "tgn:7007826",
        "tgn:7029392"
    ],
    "tgn:id":2455309,
    "tgn:name":"Little Flattop",
    "tgn:placetype":[
        "aat:300008798"
    ]
},
  "bbox": [],
  "geometry": {"coordinates":[-104.6667,30.6333],"type":"Point"}
}