{
  "id": 2482243,
  "type": "Feature",
  "properties": {
    "tgn:hierarchy":[
        "tgn:2482243",
        "tgn:1000001",
        "tgn:7012149",
        "tgn:7007568",
        "tgn:7029392"
    ],
    "tgn:id":2482243,
    "tgn:name":"Langford Creek",
    "tgn:placetype":[
        "aat:300008706"
    ]
},
  "bbox": [],
  "geometry": {"coordinates":[-76.5333,42.25],"type":"Point"}
}