{
  "id": 7386001,
  "type": "Feature",
  "properties": {
    "tgn:hierarchy":[
        "tgn:7386001",
        "tgn:1001836",
        "tgn:1000001",
        "tgn:7005560",
        "tgn:7029392"
    ],
    "tgn:id":7386001,
    "tgn:name":"Prieta, Punta",
    "tgn:placetype":[
        "aat:300386846"
    ]
},
  "bbox": [],
  "geometry": {"coordinates":[-110.333333,24.233333],"type":"Point"}
}