{
  "id": 1075203,
  "type": "Feature",
  "properties": {
    "tgn:hierarchy":[
        "tgn:1075203",
        "tgn:1000004",
        "tgn:1001869",
        "tgn:7000198",
        "tgn:7029392"
    ],
    "tgn:id":1075203,
    "tgn:name":"Diod\u0101r",
    "tgn:placetype":[
        "aat:300008347"
    ]
},
  "bbox": [],
  "geometry": {"coordinates":[71.774013,24.108713],"type":"Point"}
}