{
  "id": 7197138,
  "type": "Feature",
  "properties": {
    "tgn:hierarchy":[
        "tgn:7197138",
        "tgn:7003692",
        "tgn:1000003",
        "tgn:7000084",
        "tgn:7029392"
    ],
    "tgn:id":7197138,
    "tgn:name":"Doma",
    "tgn:placetype":[
        "aat:300008777"
    ]
},
  "bbox": [],
  "geometry": {"coordinates":[8.75,48.683333],"type":"Point"}
}