{
  "id": 2318674,
  "type": "Feature",
  "properties": {
    "tgn:hierarchy":[
        "tgn:2318674",
        "tgn:1000001",
        "tgn:7016172",
        "tgn:7012149",
        "tgn:2000142",
        "tgn:7029392"
    ],
    "tgn:id":2318674,
    "tgn:name":"Eron Reach",
    "tgn:placetype":[
        "aat:300008699"
    ]
},
  "bbox": [],
  "geometry": {"coordinates":[-91.1833,35.8833],"type":"Point"}
}