{
  "id": 2770626,
  "type": "Feature",
  "properties": {
    "tgn:hierarchy":[
        "tgn:2770626",
        "tgn:1000001",
        "tgn:7012149",
        "tgn:7007516",
        "tgn:7029392"
    ],
    "tgn:id":2770626,
    "tgn:name":"Wildcat Branch",
    "tgn:placetype":[
        "aat:300008699"
    ]
},
  "bbox": [],
  "geometry": {"coordinates":[-76.3833,39.4833],"type":"Point"}
}