{
  "id": 7497342,
  "type": "Feature",
  "properties": {
    "tgn:hierarchy":[
        "tgn:7497342",
        "tgn:1000004",
        "tgn:7001009",
        "tgn:1000141",
        "tgn:7029392"
    ],
    "tgn:id":7497342,
    "tgn:name":"Guangfu Guozhong",
    "tgn:placetype":[
        "aat:300006495"
    ]
},
  "bbox": [],
  "geometry": {"coordinates":[120.698311,24.042099],"type":"Point"}
}