{
  "id": 7505384,
  "type": "Feature",
  "properties": {
    "tgn:hierarchy":[
        "tgn:7505384",
        "tgn:1009227",
        "tgn:1000226",
        "tgn:7018437",
        "tgn:1000006",
        "tgn:7029392"
    ],
    "tgn:id":7505384,
    "tgn:name:en":"Wickliffe Bay",
    "tgn:placetype":[
        "aat:300132316"
    ]
},
  "bbox": [],
  "geometry": {"coordinates":[170.733333,-45.833333],"type":"Point"}
}