{
  "id": 7151468,
  "type": "Feature",
  "properties": {
    "tgn:hierarchy":[
        "tgn:7151468",
        "tgn:1000003",
        "tgn:7003688",
        "tgn:7000084",
        "tgn:7029392"
    ],
    "tgn:id":7151468,
    "tgn:name":"Jerrisbek",
    "tgn:placetype":[
        "aat:300008699"
    ]
},
  "bbox": [],
  "geometry": {"coordinates":[9.333333,54.566667],"type":"Point"}
}