{
  "id": 2590481,
  "type": "Feature",
  "properties": {
    "tgn:hierarchy":[
        "tgn:2590481",
        "tgn:1000001",
        "tgn:7012149",
        "tgn:7007250",
        "tgn:7029392"
    ],
    "tgn:id":2590481,
    "tgn:name":"Pole Canyon",
    "tgn:placetype":[
        "aat:300008761"
    ]
},
  "bbox": [],
  "geometry": {"coordinates":[-112.4833,42.7333],"type":"Point"}
}