{
  "id": 2586675,
  "type": "Feature",
  "properties": {
    "tgn:hierarchy":[
        "tgn:2586675",
        "tgn:1000001",
        "tgn:7006451",
        "tgn:7012149",
        "tgn:2000099",
        "tgn:7029392"
    ],
    "tgn:id":2586675,
    "tgn:name":"Pivahn-hon-kya-pi",
    "tgn:placetype":[
        "aat:300008347"
    ]
},
  "bbox": [],
  "geometry": {"coordinates":[-110.6833,35.8833],"type":"Point"}
}