{
  "id": 2023753,
  "type": "Feature",
  "properties": {
    "tgn:hierarchy":[
        "tgn:2023753",
        "tgn:1000001",
        "tgn:7012149",
        "tgn:2000437",
        "tgn:7007248",
        "tgn:7029392"
    ],
    "tgn:id":2023753,
    "tgn:name":"Noble",
    "tgn:placetype":[
        "aat:300008347"
    ]
},
  "bbox": [],
  "geometry": {"coordinates":[-85.25,34.7667],"type":"Point"}
}