{
  "id": 2771657,
  "type": "Feature",
  "properties": {
    "tgn:hierarchy":[
        "tgn:2771657",
        "tgn:1000001",
        "tgn:7012149",
        "tgn:1003008",
        "tgn:7007710",
        "tgn:7029392"
    ],
    "tgn:id":2771657,
    "tgn:name":"Wildwood Lake",
    "tgn:placetype":[
        "aat:300006191"
    ]
},
  "bbox": [],
  "geometry": {"coordinates":[-75.3333,41.4333],"type":"Point"}
}