{
  "id": 2145533,
  "type": "Feature",
  "properties": {
    "tgn:hierarchy":[
        "tgn:2145533",
        "tgn:1000001",
        "tgn:7012149",
        "tgn:1003017",
        "tgn:7007710",
        "tgn:7029392"
    ],
    "tgn:id":2145533,
    "tgn:name":"Baldwin Creek",
    "tgn:placetype":[
        "aat:300008706"
    ]
},
  "bbox": [],
  "geometry": {"coordinates":[-79.0167,40.3333],"type":"Point"}
}