{
  "id": 7107762,
  "type": "Feature",
  "properties": {
    "tgn:hierarchy":[
        "tgn:7107762",
        "tgn:1000003",
        "tgn:7003685",
        "tgn:7000084",
        "tgn:7029392"
    ],
    "tgn:id":7107762,
    "tgn:name":"Reibitz",
    "tgn:placetype":[
        "aat:300008347"
    ]
},
  "bbox": [],
  "geometry": {"coordinates":[12.466667,51.55],"type":"Point"}
}