{
  "id": 2380246,
  "type": "Feature",
  "properties": {
    "tgn:hierarchy":[
        "tgn:2380246",
        "tgn:1000001",
        "tgn:1002389",
        "tgn:7012149",
        "tgn:7007828",
        "tgn:7029392"
    ],
    "tgn:id":2380246,
    "tgn:name":"Hathaway Point",
    "tgn:placetype":[
        "aat:300008850"
    ]
},
  "bbox": [],
  "geometry": {"coordinates":[-73.1667,44.7667],"type":"Point"}
}