{
  "id": 7367358,
  "type": "Feature",
  "properties": {
    "tgn:hierarchy":[
        "tgn:7367358",
        "tgn:7005586",
        "tgn:1000001",
        "tgn:7005560",
        "tgn:7029392"
    ],
    "tgn:id":7367358,
    "tgn:name":"El Tunal",
    "tgn:placetype":[
        "aat:300008347"
    ]
},
  "bbox": [],
  "geometry": {"coordinates":[-105.116667,19.716667],"type":"Point"}
}