{
  "id": 2163694,
  "type": "Feature",
  "properties": {
    "tgn:hierarchy":[
        "tgn:2163694",
        "tgn:1000001",
        "tgn:7012149",
        "tgn:2000510",
        "tgn:7007251",
        "tgn:7029392"
    ],
    "tgn:id":2163694,
    "tgn:name":"Benton Bay",
    "tgn:placetype":[
        "aat:300132316"
    ]
},
  "bbox": [],
  "geometry": {"coordinates":[-90.9333,40.9833],"type":"Point"}
}