{
  "id": 7097270,
  "type": "Feature",
  "properties": {
    "tgn:hierarchy":[
        "tgn:7097270",
        "tgn:1000003",
        "tgn:7003676",
        "tgn:7000084",
        "tgn:7029392"
    ],
    "tgn:id":7097270,
    "tgn:name":"Sothel",
    "tgn:placetype":[
        "aat:300008347"
    ]
},
  "bbox": [],
  "geometry": {"coordinates":[9.45,53.216667],"type":"Point"}
}