{
  "id": 2498449,
  "type": "Feature",
  "properties": {
    "tgn:hierarchy":[
        "tgn:2498449",
        "tgn:1000001",
        "tgn:7012149",
        "tgn:2002053",
        "tgn:7007826",
        "tgn:7029392"
    ],
    "tgn:id":2498449,
    "tgn:name":"McAdams Peak",
    "tgn:placetype":[
        "aat:300008798"
    ]
},
  "bbox": [],
  "geometry": {"coordinates":[-98.4167,32.8833],"type":"Point"}
}