{
  "id": 2428588,
  "type": "Feature",
  "properties": {
    "tgn:hierarchy":[
        "tgn:2428588",
        "tgn:1000001",
        "tgn:2001431",
        "tgn:7012149",
        "tgn:7007566",
        "tgn:7029392"
    ],
    "tgn:id":2428588,
    "tgn:name":"Jug Tank",
    "tgn:placetype":[
        "aat:300006191"
    ]
},
  "bbox": [],
  "geometry": {"coordinates":[-107.7667,34.6167],"type":"Point"}
}