{
  "id": 7404568,
  "type": "Feature",
  "properties": {
    "tgn:hierarchy":[
        "tgn:7404568",
        "tgn:7005585",
        "tgn:1000001",
        "tgn:7005560",
        "tgn:7029392"
    ],
    "tgn:id":7404568,
    "tgn:name":"Yerba Santa, Cerro",
    "tgn:placetype":[
        "aat:300008795"
    ]
},
  "bbox": [],
  "geometry": {"coordinates":[-99.65,17.083333],"type":"Point"}
}