{
  "id": 1070449,
  "type": "Feature",
  "properties": {
    "tgn:hierarchy":[
        "tgn:1070449",
        "tgn:1000956",
        "tgn:1000004",
        "tgn:1000111",
        "tgn:7029392"
    ],
    "tgn:id":1070449,
    "tgn:name":"Mentougou",
    "tgn:placetype":[
        "aat:300008347"
    ]
},
  "bbox": [],
  "geometry": {"coordinates":[116.0833,39.9167],"type":"Point"}
}