{
  "id": 2593408,
  "type": "Feature",
  "properties": {
    "tgn:hierarchy":[
        "tgn:2593408",
        "tgn:1000001",
        "tgn:1002724",
        "tgn:7012149",
        "tgn:7007517",
        "tgn:7029392"
    ],
    "tgn:id":2593408,
    "tgn:name":"Populatic Pond",
    "tgn:placetype":[
        "aat:300008680"
    ]
},
  "bbox": [],
  "geometry": {"coordinates":[-71.3667,42.1167],"type":"Point"}
}