{
  "id": 7565503,
  "type": "Feature",
  "properties": {
    "tgn:hierarchy":[
        "tgn:7565503",
        "tgn:1000004",
        "tgn:7000198",
        "tgn:7016722",
        "tgn:7029392"
    ],
    "tgn:id":7565503,
    "tgn:name:en":"Bhit\u0101ri N\u0101la",
    "tgn:placetype":[
        "aat:300008699"
    ]
},
  "bbox": [],
  "geometry": {"coordinates":[79.511275,26.279022],"type":"Point"}
}