{
  "id": 7268696,
  "type": "Feature",
  "properties": {
    "tgn:concordances":{
        "gn:id":"2748564"
    },
    "tgn:hierarchy":[
        "tgn:7268696",
        "tgn:1000003",
        "tgn:7003635",
        "tgn:7016845",
        "tgn:7029392"
    ],
    "tgn:id":7268696,
    "tgn:name:nl":"Plankendorp",
    "tgn:placetype":[
        "aat:300008347"
    ]
},
  "bbox": [],
  "geometry": {"coordinates":[3.716667,51.566667],"type":"Point"}
}