{
  "id": 7138354,
  "type": "Feature",
  "properties": {
    "tgn:hierarchy":[
        "tgn:7138354",
        "tgn:1000003",
        "tgn:7000094",
        "tgn:7000084",
        "tgn:7029392"
    ],
    "tgn:id":7138354,
    "tgn:name":"Lange See",
    "tgn:placetype":[
        "aat:300008680"
    ]
},
  "bbox": [],
  "geometry": {"coordinates":[13.383333,53.633333],"type":"Point"}
}