{
  "id": 2462874,
  "type": "Feature",
  "properties": {
    "tgn:hierarchy":[
        "tgn:2462874",
        "tgn:1000001",
        "tgn:7012149",
        "tgn:1002987",
        "tgn:7007706",
        "tgn:7029392"
    ],
    "tgn:id":2462874,
    "tgn:name":"Littles Run",
    "tgn:placetype":[
        "aat:300008699"
    ]
},
  "bbox": [],
  "geometry": {"coordinates":[-84.1167,39.2833],"type":"Point"}
}