{
  "id": 7562336,
  "type": "Feature",
  "properties": {
    "tgn:hierarchy":[
        "tgn:7562336",
        "tgn:1000004",
        "tgn:7000198",
        "tgn:7016722",
        "tgn:7029392"
    ],
    "tgn:id":7562336,
    "tgn:name:en":"Nagla Budhp\u0101lsingh",
    "tgn:placetype":[
        "aat:300008347"
    ]
},
  "bbox": [],
  "geometry": {"coordinates":[79.477356,27.949167],"type":"Point"}
}