{
  "id": 2668367,
  "type": "Feature",
  "properties": {
    "tgn:hierarchy":[
        "tgn:2668367",
        "tgn:1000001",
        "tgn:7012149",
        "tgn:7007157",
        "tgn:2000189",
        "tgn:7029392"
    ],
    "tgn:id":2668367,
    "tgn:name":"Slagger",
    "tgn:placetype":[
        "aat:300008347"
    ]
},
  "bbox": [],
  "geometry": {"coordinates":[-121.7167,41.3167],"type":"Point"}
}