{
  "id": 7227346,
  "type": "Feature",
  "properties": {
    "tgn:hierarchy":[
        "tgn:7227346",
        "tgn:7002690",
        "tgn:7012056",
        "tgn:1000003",
        "tgn:1000074",
        "tgn:7029392"
    ],
    "tgn:id":7227346,
    "tgn:name":"K\u00e1to Gar\u00edpa",
    "tgn:placetype":[
        "aat:300000745"
    ]
},
  "bbox": [],
  "geometry": {"coordinates":[25.25,35.083333],"type":"Point"}
}