{
  "id": 1104988,
  "type": "Feature",
  "properties": {
    "tgn:hierarchy":[
        "tgn:1104988",
        "tgn:7000665",
        "tgn:1000223",
        "tgn:1000006",
        "tgn:7029392"
    ],
    "tgn:id":1104988,
    "tgn:name":"Humboldt, Mont",
    "tgn:placetype":[
        "aat:300008795"
    ]
},
  "bbox": [],
  "geometry": {"coordinates":[166.4833,-21.9167],"type":"Point"}
}