{
  "id": 2688945,
  "type": "Feature",
  "properties": {
    "tgn:hierarchy":[
        "tgn:2688945",
        "tgn:2002142",
        "tgn:1000001",
        "tgn:7012149",
        "tgn:7007919",
        "tgn:7029392"
    ],
    "tgn:id":2688945,
    "tgn:name":"Spy Run",
    "tgn:placetype":[
        "aat:300008699"
    ]
},
  "bbox": [],
  "geometry": {"coordinates":[-79.1167,37.8833],"type":"Point"}
}