<<<<<<< HEAD
{
  "id": 7367680,
  "type": "Feature",
  "properties": {
    "tgn:hierarchy":[
        "tgn:7367680",
        "tgn:7005586",
        "tgn:1000001",
        "tgn:7005560",
        "tgn:7029392"
    ],
    "tgn:id":7367680,
    "tgn:name":"El Potrerillo",
    "tgn:placetype":[
        "aat:300266554",
        "aat:300008699"
    ]
},
  "bbox": [],
  "geometry": {"coordinates":[-105.05,20.266667],"type":"Point"}
}
=======
{"geometry":{"type":"Point","coordinates":[-105.050000,20.266667]},"type":"Feature","properties":{"hierarchy":["tgn:7367680","tgn:7005586","tgn:1000001","tgn:7005560","tgn:7029392"],"placetype":["aat:300266554","aat:300008699"],"id":7367680,"name:xx":"El Potrerillo"}}
>>>>>>> 03f74aca74312dbeaf24d7e61306dd6a786dc3d0
