{
  "id": 7367680,
  "type": "Feature",
  "properties": {
    "tgn:hierarchy":[
        "tgn:7367680",
        "tgn:7005586",
        "tgn:1000001",
        "tgn:7005560",
        "tgn:7029392"
    ],
    "tgn:id":7367680,
    "tgn:name":"El Potrerillo",
    "tgn:placetype":[
        "aat:300266554",
        "aat:300008699"
    ]
},
  "bbox": [],
  "geometry": {"coordinates":[-105.05,20.266667],"type":"Point"}
}