{
  "id": 7530406,
  "type": "Feature",
  "properties": {
    "tgn:hierarchy":[
        "tgn:7530406",
        "tgn:7001242",
        "tgn:7016833",
        "tgn:1001113",
        "tgn:7029392"
    ],
    "tgn:id":7530406,
    "tgn:name":"Kafr al La\u1e29\u0101yisah",
    "tgn:placetype":[
        "aat:300008347"
    ]
},
  "bbox": [],
  "geometry": {"coordinates":[31.746795,30.613836],"type":"Point"}
}