{
  "id": 7089858,
  "type": "Feature",
  "properties": {
    "tgn:hierarchy":[
        "tgn:7089858",
        "tgn:7003669",
        "tgn:1000003",
        "tgn:7000084",
        "tgn:7029392"
    ],
    "tgn:id":7089858,
    "tgn:name":"Unterubermoos",
    "tgn:placetype":[
        "aat:300008347"
    ]
},
  "bbox": [],
  "geometry": {"coordinates":[12.133333,48.066667],"type":"Point"}
}