{
  "id": 2092702,
  "type": "Feature",
  "properties": {
    "tgn:hierarchy":[
        "tgn:2092702",
        "tgn:1002172",
        "tgn:1000001",
        "tgn:7012149",
        "tgn:7007710",
        "tgn:7029392"
    ],
    "tgn:id":2092702,
    "tgn:name":"Ryot",
    "tgn:placetype":[
        "aat:300008347"
    ]
},
  "bbox": [],
  "geometry": {"coordinates":[-78.6333,40.1333],"type":"Point"}
}