{
  "id": 2127998,
  "type": "Feature",
  "properties": {
    "tgn:hierarchy":[
        "tgn:2127998",
        "tgn:1000001",
        "tgn:7012149",
        "tgn:1003038",
        "tgn:7007517",
        "tgn:7029392"
    ],
    "tgn:id":2127998,
    "tgn:name":"Albee Meadow",
    "tgn:placetype":[
        "aat:300008905"
    ]
},
  "bbox": [],
  "geometry": {"coordinates":[-72.25,42.6833],"type":"Point"}
}