{
  "id": 7008974,
  "type": "Feature",
  "properties": {
    "tgn:hierarchy":[
        "tgn:7008974",
        "tgn:1000003",
        "tgn:7002888",
        "tgn:1000070",
        "tgn:7029392"
    ],
    "tgn:id":7008974,
    "tgn:name":"Briey",
    "tgn:placetype":[
        "aat:300008347"
    ]
},
  "bbox": [],
  "geometry": {"coordinates":[5.95,49.25],"type":"Point"}
}