{
  "id": 2465648,
  "type": "Feature",
  "properties": {
    "tgn:hierarchy":[
        "tgn:2465648",
        "tgn:1000001",
        "tgn:7012149",
        "tgn:2000217",
        "tgn:7007158",
        "tgn:7029392"
    ],
    "tgn:id":2465648,
    "tgn:name":"Lone Pine Ditch",
    "tgn:placetype":[
        "aat:300006075"
    ]
},
  "bbox": [],
  "geometry": {"coordinates":[-106.9667,38.6333],"type":"Point"}
}