{
  "id": 1056718,
  "type": "Feature",
  "properties": {
    "tgn:hierarchy":[
        "tgn:1056718",
        "tgn:1000004",
        "tgn:7011573",
        "tgn:7018214",
        "tgn:7002435",
        "tgn:7029392"
    ],
    "tgn:id":1056718,
    "tgn:name":"Malaya Dubna",
    "tgn:placetype":[
        "aat:300008347"
    ]
},
  "bbox": [],
  "geometry": {"coordinates":[38.9667,55.8667],"type":"Point"}
}