{
  "id": 7564616,
  "type": "Feature",
  "properties": {
    "tgn:hierarchy":[
        "tgn:7564616",
        "tgn:1000004",
        "tgn:7000198",
        "tgn:7016722",
        "tgn:7029392"
    ],
    "tgn:id":7564616,
    "tgn:name:en":"Husepura",
    "tgn:placetype":[
        "aat:300008347"
    ]
},
  "bbox": [],
  "geometry": {"coordinates":[79.31543,26.36439],"type":"Point"}
}