{
  "id": 7233668,
  "type": "Feature",
  "properties": {
    "tgn:hierarchy":[
        "tgn:7233668",
        "tgn:7002680",
        "tgn:7001395",
        "tgn:1000003",
        "tgn:1000074",
        "tgn:7029392"
    ],
    "tgn:id":7233668,
    "tgn:name":"Dhikh\u00e1li, \u00d3rmos",
    "tgn:placetype":[
        "aat:300132316"
    ]
},
  "bbox": [],
  "geometry": {"coordinates":[20.783333,38.65],"type":"Point"}
}