{
  "id": 2707363,
  "type": "Feature",
  "properties": {
    "tgn:hierarchy":[
        "tgn:2707363",
        "tgn:1000001",
        "tgn:7012149",
        "tgn:2001310",
        "tgn:7007524",
        "tgn:7029392"
    ],
    "tgn:id":2707363,
    "tgn:name":"Sweet Grass Hills",
    "tgn:placetype":[
        "aat:300008697"
    ]
},
  "bbox": [],
  "geometry": {"coordinates":[-111.5333,48.95],"type":"Point"}
}