{
  "id": 2076159,
  "type": "Feature",
  "properties": {
    "tgn:hierarchy":[
        "tgn:2076159",
        "tgn:1000001",
        "tgn:7012149",
        "tgn:2001550",
        "tgn:7007709",
        "tgn:7029392"
    ],
    "tgn:id":2076159,
    "tgn:name":"Plymouth",
    "tgn:placetype":[
        "aat:300008347"
    ]
},
  "bbox": [],
  "geometry": {"coordinates":[-76.7333,35.8667],"type":"Point"}
}