{
  "id": 2479526,
  "type": "Feature",
  "properties": {
    "tgn:hierarchy":[
        "tgn:2479526",
        "tgn:1000001",
        "tgn:7012149",
        "tgn:2001446",
        "tgn:7007566",
        "tgn:7029392"
    ],
    "tgn:id":2479526,
    "tgn:name":"Laizy Daisy",
    "tgn:placetype":[
        "aat:300000390"
    ]
},
  "bbox": [],
  "geometry": {"coordinates":[-105.05,36.2333],"type":"Point"}
}