{
  "id": 2130183,
  "type": "Feature",
  "properties": {
    "tgn:hierarchy":[
        "tgn:2130183",
        "tgn:1000001",
        "tgn:7012149",
        "tgn:7007157",
        "tgn:1002857",
        "tgn:7029392"
    ],
    "tgn:id":2130183,
    "tgn:name":"Allen Peak",
    "tgn:placetype":[
        "aat:300008798"
    ]
},
  "bbox": [],
  "geometry": {"coordinates":[-116.9833,34.0667],"type":"Point"}
}