{
  "id": 2176724,
  "type": "Feature",
  "properties": {
    "tgn:hierarchy":[
        "tgn:2176724",
        "tgn:1000001",
        "tgn:7012149",
        "tgn:2001446",
        "tgn:7007566",
        "tgn:7029392"
    ],
    "tgn:id":2176724,
    "tgn:name":"Black Mesa Spring",
    "tgn:placetype":[
        "aat:300008697"
    ]
},
  "bbox": [],
  "geometry": {"coordinates":[-105.05,35.9333],"type":"Point"}
}