{
  "id": 2746345,
  "type": "Feature",
  "properties": {
    "tgn:hierarchy":[
        "tgn:2746345",
        "tgn:1000001",
        "tgn:7012149",
        "tgn:2001766",
        "tgn:7007712",
        "tgn:7029392"
    ],
    "tgn:id":2746345,
    "tgn:name":"W E Morris Jr Lake",
    "tgn:placetype":[
        "aat:300006191"
    ]
},
  "bbox": [],
  "geometry": {"coordinates":[-82.0833,35.0833],"type":"Point"}
}