<<<<<<< HEAD
{
  "id": 2252482,
  "type": "Feature",
  "properties": {
    "tgn:hierarchy":[
        "tgn:2252482",
        "tgn:1000001",
        "tgn:2001260",
        "tgn:7012149",
        "tgn:7007524",
        "tgn:7029392"
    ],
    "tgn:id":2252482,
    "tgn:name":"Conklin Lake",
    "tgn:placetype":[
        "aat:300008680"
    ]
},
  "bbox": [],
  "geometry": {"coordinates":[-111.5167,44.6833],"type":"Point"}
}
=======
{"geometry":{"type":"Point","coordinates":[-111.516700,44.683300]},"type":"Feature","properties":{"hierarchy":["tgn:2252482","tgn:1000001","tgn:2001260","tgn:7012149","tgn:7007524","tgn:7029392"],"placetype":["aat:300008680"],"id":2252482,"name:xx":"Conklin Lake"}}
>>>>>>> 03f74aca74312dbeaf24d7e61306dd6a786dc3d0
