<<<<<<< HEAD
{
  "id": 2158206,
  "type": "Feature",
  "properties": {
    "tgn:hierarchy":[
        "tgn:2158206",
        "tgn:1000001",
        "tgn:7012149",
        "tgn:2000837",
        "tgn:7007255",
        "tgn:7029392"
    ],
    "tgn:id":2158206,
    "tgn:name":"Beaver Ridge",
    "tgn:placetype":[
        "aat:300266640"
    ]
},
  "bbox": [],
  "geometry": {"coordinates":[-82.2833,37.3333],"type":"Point"}
}
=======
{"geometry":{"type":"Point","coordinates":[-82.283300,37.333300]},"type":"Feature","properties":{"hierarchy":["tgn:2158206","tgn:1000001","tgn:7012149","tgn:2000837","tgn:7007255","tgn:7029392"],"placetype":["aat:300266640"],"id":2158206,"name:xx":"Beaver Ridge"}}
>>>>>>> 03f74aca74312dbeaf24d7e61306dd6a786dc3d0
