{
  "id": 2255657,
  "type": "Feature",
  "properties": {
    "tgn:hierarchy":[
        "tgn:2255657",
        "tgn:1002201",
        "tgn:1000001",
        "tgn:7012149",
        "tgn:7007517",
        "tgn:7029392"
    ],
    "tgn:id":2255657,
    "tgn:name":"Copicut River",
    "tgn:placetype":[
        "aat:300008707"
    ]
},
  "bbox": [],
  "geometry": {"coordinates":[-71.0333,41.7167],"type":"Point"}
}