<<<<<<< HEAD
{
  "id": 2255657,
  "type": "Feature",
  "properties": {
    "tgn:hierarchy":[
        "tgn:2255657",
        "tgn:1002201",
        "tgn:1000001",
        "tgn:7012149",
        "tgn:7007517",
        "tgn:7029392"
    ],
    "tgn:id":2255657,
    "tgn:name":"Copicut River",
    "tgn:placetype":[
        "aat:300008707"
    ]
},
  "bbox": [],
  "geometry": {"coordinates":[-71.0333,41.7167],"type":"Point"}
}
=======
{"geometry":{"type":"Point","coordinates":[-71.033300,41.716700]},"type":"Feature","properties":{"hierarchy":["tgn:2255657","tgn:1002201","tgn:1000001","tgn:7012149","tgn:7007517","tgn:7029392"],"placetype":["aat:300008707"],"id":2255657,"name:xx":"Copicut River"}}
>>>>>>> 03f74aca74312dbeaf24d7e61306dd6a786dc3d0
