{
  "id": 2280207,
  "type": "Feature",
  "properties": {
    "tgn:hierarchy":[
        "tgn:2280207",
        "tgn:1000001",
        "tgn:7006451",
        "tgn:7012149",
        "tgn:2000098",
        "tgn:7029392"
    ],
    "tgn:id":2280207,
    "tgn:name":"Death Valley Spring",
    "tgn:placetype":[
        "aat:300008697"
    ]
},
  "bbox": [],
  "geometry": {"coordinates":[-113.25,36.3667],"type":"Point"}
}