{
  "id": 2776914,
  "type": "Feature",
  "properties": {
    "tgn:hierarchy":[
        "tgn:2776914",
        "tgn:1000001",
        "tgn:7016172",
        "tgn:7012149",
        "tgn:2000147",
        "tgn:7029392"
    ],
    "tgn:id":2776914,
    "tgn:name":"Windwood Heights",
    "tgn:placetype":[
        "aat:300008347"
    ]
},
  "bbox": [],
  "geometry": {"coordinates":[-91.9667,34.9333],"type":"Point"}
}