{
  "id": 7086198,
  "type": "Feature",
  "properties": {
    "tgn:hierarchy":[
        "tgn:7086198",
        "tgn:1000003",
        "tgn:7003687",
        "tgn:7000084",
        "tgn:7029392"
    ],
    "tgn:id":7086198,
    "tgn:name":"Weiden",
    "tgn:placetype":[
        "aat:300008347"
    ]
},
  "bbox": [],
  "geometry": {"coordinates":[12.383333,51.983333],"type":"Point"}
}