<<<<<<< HEAD
{
  "id": 7354221,
  "type": "Feature",
  "properties": {
    "tgn:hierarchy":[
        "tgn:7354221",
        "tgn:1000001",
        "tgn:7005601",
        "tgn:7005560",
        "tgn:7029392"
    ],
    "tgn:id":7354221,
    "tgn:name":"Casas Coloradas",
    "tgn:placetype":[
        "aat:300008347"
    ]
},
  "bbox": [],
  "geometry": {"coordinates":[-102.5,22.616667],"type":"Point"}
}
=======
{"geometry":{"type":"Point","coordinates":[-102.500000,22.616667]},"type":"Feature","properties":{"hierarchy":["tgn:7354221","tgn:1000001","tgn:7005601","tgn:7005560","tgn:7029392"],"placetype":["aat:300008347"],"id":7354221,"name:xx":"Casas Coloradas"}}
>>>>>>> 03f74aca74312dbeaf24d7e61306dd6a786dc3d0
