<<<<<<< HEAD
{
  "id": 7177786,
  "type": "Feature",
  "properties": {
    "tgn:hierarchy":[
        "tgn:7177786",
        "tgn:7003669",
        "tgn:1000003",
        "tgn:7000084",
        "tgn:7029392"
    ],
    "tgn:id":7177786,
    "tgn:name":"Hankofen",
    "tgn:placetype":[
        "aat:300008347"
    ]
},
  "bbox": [],
  "geometry": {"coordinates":[12.583333,48.75],"type":"Point"}
}
=======
{"geometry":{"type":"Point","coordinates":[12.583333,48.750000]},"type":"Feature","properties":{"hierarchy":["tgn:7177786","tgn:7003669","tgn:1000003","tgn:7000084","tgn:7029392"],"placetype":["aat:300008347"],"id":7177786,"name:xx":"Hankofen"}}
>>>>>>> 03f74aca74312dbeaf24d7e61306dd6a786dc3d0
