<<<<<<< HEAD
{
  "id": 2767694,
  "type": "Feature",
  "properties": {
    "tgn:hierarchy":[
        "tgn:2767694",
        "tgn:1000001",
        "tgn:7012149",
        "tgn:2002353",
        "tgn:7007922",
        "tgn:7029392"
    ],
    "tgn:id":2767694,
    "tgn:name":"Whitefish Lake",
    "tgn:placetype":[
        "aat:300008680"
    ]
},
  "bbox": [],
  "geometry": {"coordinates":[-91.4333,45.85],"type":"Point"}
}
=======
{"geometry":{"type":"Point","coordinates":[-91.433300,45.850000]},"type":"Feature","properties":{"hierarchy":["tgn:2767694","tgn:1000001","tgn:7012149","tgn:2002353","tgn:7007922","tgn:7029392"],"placetype":["aat:300008680"],"id":2767694,"name:xx":"Whitefish Lake"}}
>>>>>>> 03f74aca74312dbeaf24d7e61306dd6a786dc3d0
