{
  "id": 2767694,
  "type": "Feature",
  "properties": {
    "tgn:hierarchy":[
        "tgn:2767694",
        "tgn:1000001",
        "tgn:7012149",
        "tgn:2002353",
        "tgn:7007922",
        "tgn:7029392"
    ],
    "tgn:id":2767694,
    "tgn:name":"Whitefish Lake",
    "tgn:placetype":[
        "aat:300008680"
    ]
},
  "bbox": [],
  "geometry": {"coordinates":[-91.4333,45.85],"type":"Point"}
}