{
  "id": 1017201,
  "type": "Feature",
  "properties": {
    "tgn:hierarchy":[
        "tgn:1017201",
        "tgn:1000001",
        "tgn:7005589",
        "tgn:7005560",
        "tgn:7029392"
    ],
    "tgn:id":1017201,
    "tgn:name":"Ci\u00e9nega de Flores",
    "tgn:placetype":[
        "aat:300008347"
    ]
},
  "bbox": [],
  "geometry": {"coordinates":[-100.183333,25.95],"type":"Point"}
}