{
  "id": 7587257,
  "type": "Feature",
  "properties": {
    "tgn:hierarchy":[
        "tgn:7587257",
        "tgn:7001819",
        "tgn:1000004",
        "tgn:7000198",
        "tgn:7029392"
    ],
    "tgn:id":7587257,
    "tgn:name:en":"Raddar",
    "tgn:placetype":[
        "aat:300008347"
    ]
},
  "bbox": [],
  "geometry": {"coordinates":[93.543905,27.233288],"type":"Point"}
}