{
  "id": 2007048,
  "type": "Feature",
  "properties": {
    "tgn:hierarchy":[
        "tgn:2007048",
        "tgn:1000001",
        "tgn:7006451",
        "tgn:2000095",
        "tgn:7012149",
        "tgn:7029392"
    ],
    "tgn:id":2007048,
    "tgn:name":"Morenci",
    "tgn:placetype":[
        "aat:300008347"
    ]
},
  "bbox": [],
  "geometry": {"coordinates":[-109.35,33.0667],"type":"Point"}
}