{
  "id": 1025219,
  "type": "Feature",
  "properties": {
    "tgn:hierarchy":[
        "tgn:1025219",
        "tgn:1001866",
        "tgn:1000002",
        "tgn:1000059",
        "tgn:7029392"
    ],
    "tgn:id":1025219,
    "tgn:name":"Ortiz",
    "tgn:placetype":[
        "aat:300008347"
    ]
},
  "bbox": [],
  "geometry": {"coordinates":[-67.3333,9.6167],"type":"Point"}
}