{
  "id": 2525905,
  "type": "Feature",
  "properties": {
    "tgn:hierarchy":[
        "tgn:2525905",
        "tgn:1000001",
        "tgn:1002361",
        "tgn:7012149",
        "tgn:7007828",
        "tgn:7029392"
    ],
    "tgn:id":2525905,
    "tgn:name":"Mosher Meadow Brook",
    "tgn:placetype":[
        "aat:300008699"
    ]
},
  "bbox": [],
  "geometry": {"coordinates":[-71.8167,44.9667],"type":"Point"}
}