{
  "id": 7010281,
  "type": "Feature",
  "properties": {
    "tgn:hierarchy":[
        "tgn:7010281",
        "tgn:7002445",
        "tgn:1000003",
        "tgn:7008117",
        "tgn:7008591",
        "tgn:7029392"
    ],
    "tgn:id":7010281,
    "tgn:name:en":"Carlisle",
    "tgn:placetype":[
        "aat:300008347",
        "aat:300008416",
        "aat:300264742",
        "aat:300387235",
        "aat:300387220",
        "aat:300008375",
        "aat:300387302"
    ]
},
  "bbox": [],
  "geometry": {"coordinates":[-2.933333,54.883333],"type":"Point"}
}