{
  "id": 2755263,
  "type": "Feature",
  "properties": {
    "tgn:hierarchy":[
        "tgn:2755263",
        "tgn:2002240",
        "tgn:1000001",
        "tgn:7012149",
        "tgn:7007920",
        "tgn:7029392"
    ],
    "tgn:id":2755263,
    "tgn:name":"Webber Canyon",
    "tgn:placetype":[
        "aat:300008761"
    ]
},
  "bbox": [],
  "geometry": {"coordinates":[-119.4167,46.15],"type":"Point"}
}