{
  "id": 7189841,
  "type": "Feature",
  "properties": {
    "tgn:hierarchy":[
        "tgn:7189841",
        "tgn:1000003",
        "tgn:7003684",
        "tgn:7000084",
        "tgn:7029392"
    ],
    "tgn:id":7189841,
    "tgn:name":"Eschberg",
    "tgn:placetype":[
        "aat:300000206"
    ]
},
  "bbox": [],
  "geometry": {"coordinates":[7.05,49.233333],"type":"Point"}
}