{
  "id": 7561054,
  "type": "Feature",
  "properties": {
    "tgn:hierarchy":[
        "tgn:7561054",
        "tgn:1000004",
        "tgn:7000198",
        "tgn:7016722",
        "tgn:7029392"
    ],
    "tgn:id":7561054,
    "tgn:name:en":"Udaypur",
    "tgn:placetype":[
        "aat:300008347"
    ]
},
  "bbox": [],
  "geometry": {"coordinates":[79.443631,27.103737],"type":"Point"}
}