{
  "id": 7267606,
  "type": "Feature",
  "properties": {
    "tgn:hierarchy":[
        "tgn:7267606",
        "tgn:1000003",
        "tgn:7003632",
        "tgn:7016845",
        "tgn:7029392"
    ],
    "tgn:id":7267606,
    "tgn:name:nl":"Rhin",
    "tgn:placetype":[
        "aat:300008699"
    ]
},
  "bbox": [],
  "geometry": {"coordinates":[4.083333,51.966667],"type":"Point"}
}