{
  "id": 7215522,
  "type": "Feature",
  "properties": {
    "tgn:hierarchy":[
        "tgn:7215522",
        "tgn:1000003",
        "tgn:7003676",
        "tgn:7000084",
        "tgn:7029392"
    ],
    "tgn:id":7215522,
    "tgn:name":"Adelebsener Wald",
    "tgn:placetype":[
        "aat:300008863"
    ]
},
  "bbox": [],
  "geometry": {"coordinates":[9.716667,51.583333],"type":"Point"}
}