{
  "id": 7512645,
  "type": "Feature",
  "properties": {
    "tgn:hierarchy":[
        "tgn:7512645",
        "tgn:1008380",
        "tgn:1000226",
        "tgn:7016827",
        "tgn:1000006",
        "tgn:7029392"
    ],
    "tgn:id":7512645,
    "tgn:name:en":"Hiwi",
    "tgn:placetype":[
        "aat:300008795"
    ]
},
  "bbox": [],
  "geometry": {"coordinates":[174.683333,-39.65],"type":"Point"}
}