{
  "id": 2641685,
  "type": "Feature",
  "properties": {
    "tgn:hierarchy":[
        "tgn:2641685",
        "tgn:1000001",
        "tgn:7012149",
        "tgn:2000229",
        "tgn:7007158",
        "tgn:7029392"
    ],
    "tgn:id":2641685,
    "tgn:name":"Sand Hill Ditch",
    "tgn:placetype":[
        "aat:300006075"
    ]
},
  "bbox": [],
  "geometry": {"coordinates":[-103.3167,40.45],"type":"Point"}
}