{
  "id": 7218351,
  "type": "Feature",
  "properties": {
    "tgn:hierarchy":[
        "tgn:7218351",
        "tgn:7002735",
        "tgn:7017076",
        "tgn:1000003",
        "tgn:1000074",
        "tgn:7029392"
    ],
    "tgn:id":7218351,
    "tgn:name":"Xerovo\u00fana",
    "tgn:placetype":[
        "aat:300008795",
        "aat:300008798"
    ]
},
  "bbox": [],
  "geometry": {"coordinates":[22.216667,37.166667],"type":"Point"}
}