{
  "id": 1116210,
  "type": "Feature",
  "properties": {
    "tgn:hierarchy":[
        "tgn:1116210",
        "tgn:7005685",
        "tgn:1000001",
        "tgn:7005734",
        "tgn:1102566",
        "tgn:7029392"
    ],
    "tgn:id":1116210,
    "tgn:name":"Elbow Lake",
    "tgn:placetype":[
        "aat:300008680"
    ]
},
  "bbox": [],
  "geometry": {"coordinates":[-100.8667,54.85],"type":"Point"}
}