{
  "id": 2231332,
  "type": "Feature",
  "properties": {
    "tgn:hierarchy":[
        "tgn:2231332",
        "tgn:1000001",
        "tgn:7012149",
        "tgn:1002263",
        "tgn:7007826",
        "tgn:7029392"
    ],
    "tgn:id":2231332,
    "tgn:name":"Chain of Lakes",
    "tgn:placetype":[
        "aat:300008680"
    ]
},
  "bbox": [],
  "geometry": {"coordinates":[-95.2167,31.5667],"type":"Point"}
}