<<<<<<< HEAD
{
  "id": 2400998,
  "type": "Feature",
  "properties": {
    "tgn:hierarchy":[
        "tgn:2400998",
        "tgn:2000090",
        "tgn:1000001",
        "tgn:7006451",
        "tgn:7012149",
        "tgn:7029392"
    ],
    "tgn:id":2400998,
    "tgn:name":"Horse Tank",
    "tgn:placetype":[
        "aat:300006191"
    ]
},
  "bbox": [],
  "geometry": {"coordinates":[-109.35,33.8],"type":"Point"}
}
=======
{"geometry":{"type":"Point","coordinates":[-109.350000,33.800000]},"type":"Feature","properties":{"hierarchy":["tgn:2400998","tgn:2000090","tgn:1000001","tgn:7006451","tgn:7012149","tgn:7029392"],"placetype":["aat:300006191"],"id":2400998,"name:xx":"Horse Tank"}}
>>>>>>> 03f74aca74312dbeaf24d7e61306dd6a786dc3d0
