{
  "id": 7184837,
  "type": "Feature",
  "properties": {
    "tgn:hierarchy":[
        "tgn:7184837",
        "tgn:7003669",
        "tgn:1000003",
        "tgn:7000084",
        "tgn:7029392"
    ],
    "tgn:id":7184837,
    "tgn:name":"Gewald",
    "tgn:placetype":[
        "aat:300000206"
    ]
},
  "bbox": [],
  "geometry": {"coordinates":[12.066667,49.05],"type":"Point"}
}