{
  "id": 2268552,
  "type": "Feature",
  "properties": {
    "tgn:hierarchy":[
        "tgn:2268552",
        "tgn:1000001",
        "tgn:7012149",
        "tgn:1002552",
        "tgn:7007920",
        "tgn:7029392"
    ],
    "tgn:id":2268552,
    "tgn:name":"Crosby",
    "tgn:placetype":[
        "aat:300008347"
    ]
},
  "bbox": [],
  "geometry": {"coordinates":[-122.85,47.5667],"type":"Point"}
}