{
  "id": 7034726,
  "type": "Feature",
  "properties": {
    "tgn:hierarchy":[
        "tgn:7034726",
        "tgn:1000003",
        "tgn:7003142",
        "tgn:7003236",
        "tgn:1000080",
        "tgn:7029392"
    ],
    "tgn:id":7034726,
    "tgn:name":"Rovereto",
    "tgn:placetype":[
        "aat:300008347"
    ]
},
  "bbox": [],
  "geometry": {"coordinates":[9.435556,44.295],"type":"Point"}
}