{
  "id": 7431619,
  "type": "Feature",
  "properties": {
    "tgn:hierarchy":[
        "tgn:7431619",
        "tgn:1001853",
        "tgn:1000001",
        "tgn:7005560",
        "tgn:7029392"
    ],
    "tgn:id":7431619,
    "tgn:name":"Los Toros",
    "tgn:placetype":[
        "aat:300008347"
    ]
},
  "bbox": [],
  "geometry": {"coordinates":[-102.333333,28.45],"type":"Point"}
}