{
  "id": 7233508,
  "type": "Feature",
  "properties": {
    "tgn:hierarchy":[
        "tgn:7233508",
        "tgn:7002751",
        "tgn:7001399",
        "tgn:1000003",
        "tgn:1000074",
        "tgn:7029392"
    ],
    "tgn:id":7233508,
    "tgn:name":"Almiro\u00fa, \u00c1kra",
    "tgn:placetype":[
        "aat:300008850"
    ]
},
  "bbox": [],
  "geometry": {"coordinates":[22.883333,39.183333],"type":"Point"}
}