<<<<<<< HEAD
{
  "id": 2334409,
  "type": "Feature",
  "properties": {
    "tgn:hierarchy":[
        "tgn:2334409",
        "tgn:1000001",
        "tgn:1002934",
        "tgn:7012149",
        "tgn:7007565",
        "tgn:7029392"
    ],
    "tgn:id":2334409,
    "tgn:name":"Forest Lake",
    "tgn:placetype":[
        "aat:300006191"
    ]
},
  "bbox": [],
  "geometry": {"coordinates":[-74.7167,40.9667],"type":"Point"}
}
=======
{"geometry":{"type":"Point","coordinates":[-74.716700,40.966700]},"type":"Feature","properties":{"hierarchy":["tgn:2334409","tgn:1000001","tgn:1002934","tgn:7012149","tgn:7007565","tgn:7029392"],"placetype":["aat:300006191"],"id":2334409,"name:xx":"Forest Lake"}}
>>>>>>> 03f74aca74312dbeaf24d7e61306dd6a786dc3d0
