{
  "id": 2334409,
  "type": "Feature",
  "properties": {
    "tgn:hierarchy":[
        "tgn:2334409",
        "tgn:1000001",
        "tgn:1002934",
        "tgn:7012149",
        "tgn:7007565",
        "tgn:7029392"
    ],
    "tgn:id":2334409,
    "tgn:name":"Forest Lake",
    "tgn:placetype":[
        "aat:300006191"
    ]
},
  "bbox": [],
  "geometry": {"coordinates":[-74.7167,40.9667],"type":"Point"}
}