{
  "id": 7312190,
  "type": "Feature",
  "properties": {
    "tgn:hierarchy":[
        "tgn:7312190",
        "tgn:1001768",
        "tgn:1000049",
        "tgn:1000002",
        "tgn:7029392"
    ],
    "tgn:id":7312190,
    "tgn:name":"Las Caletas",
    "tgn:placetype":[
        "aat:300387200"
    ]
},
  "bbox": [],
  "geometry": {"coordinates":[-70.533333,-32.833333],"type":"Point"}
}