{
  "id": 1140358,
  "type": "Feature",
  "properties": {
    "tgn:hierarchy":[
        "tgn:1140358",
        "tgn:1000004",
        "tgn:7000894",
        "tgn:7016797",
        "tgn:1000120",
        "tgn:7029392"
    ],
    "tgn:id":1140358,
    "tgn:name":"G\u014ddo",
    "tgn:placetype":[
        "aat:300008347"
    ]
},
  "bbox": [],
  "geometry": {"coordinates":[139.7333,35.85],"type":"Point"}
}