<<<<<<< HEAD
{
  "id": 7472390,
  "type": "Feature",
  "properties": {
    "tgn:hierarchy":[
        "tgn:7472390",
        "tgn:7001010",
        "tgn:1000004",
        "tgn:1000141",
        "tgn:7029392"
    ],
    "tgn:id":7472390,
    "tgn:name":"Ping'an Gong",
    "tgn:placetype":[
        "aat:300007595"
    ]
},
  "bbox": [],
  "geometry": {"coordinates":[121.655281,24.164271],"type":"Point"}
}
=======
{"geometry":{"type":"Point","coordinates":[121.655281,24.164271]},"type":"Feature","properties":{"hierarchy":["tgn:7472390","tgn:7001010","tgn:1000004","tgn:1000141","tgn:7029392"],"placetype":["aat:300007595"],"id":7472390,"name:xx":"Ping'an Gong"}}
>>>>>>> 03f74aca74312dbeaf24d7e61306dd6a786dc3d0
