{
  "id": 7472390,
  "type": "Feature",
  "properties": {
    "tgn:hierarchy":[
        "tgn:7472390",
        "tgn:7001010",
        "tgn:1000004",
        "tgn:1000141",
        "tgn:7029392"
    ],
    "tgn:id":7472390,
    "tgn:name":"Ping'an Gong",
    "tgn:placetype":[
        "aat:300007595"
    ]
},
  "bbox": [],
  "geometry": {"coordinates":[121.655281,24.164271],"type":"Point"}
}