{
  "id": 7469001,
  "type": "Feature",
  "properties": {
    "tgn:hierarchy":[
        "tgn:7469001",
        "tgn:1000004",
        "tgn:7489179",
        "tgn:1000141",
        "tgn:7029392"
    ],
    "tgn:id":7469001,
    "tgn:name":"Xianghe Cun",
    "tgn:placetype":[
        "aat:300387173"
    ]
},
  "bbox": [],
  "geometry": {"coordinates":[121.800676,24.632461],"type":"Point"}
}