{
  "id": 2536661,
  "type": "Feature",
  "properties": {
    "tgn:hierarchy":[
        "tgn:2536661",
        "tgn:1000001",
        "tgn:7012149",
        "tgn:1002564",
        "tgn:7007710",
        "tgn:7029392"
    ],
    "tgn:id":2536661,
    "tgn:name":"Nebraska",
    "tgn:placetype":[
        "aat:300008347"
    ]
},
  "bbox": [],
  "geometry": {"coordinates":[-75.5333,41.5167],"type":"Point"}
}