{
  "id": 7257731,
  "type": "Feature",
  "properties": {
    "tgn:hierarchy":[
        "tgn:7257731",
        "tgn:7003614",
        "tgn:1000003",
        "tgn:7016845",
        "tgn:7029392"
    ],
    "tgn:id":7257731,
    "tgn:name:nl":"Balinger- en Mantingerzand",
    "tgn:placetype":[
        "aat:300008178"
    ]
},
  "bbox": [],
  "geometry": {"coordinates":[6.616667,52.783333],"type":"Point"}
}