{
  "id": 7146710,
  "type": "Feature",
  "properties": {
    "tgn:hierarchy":[
        "tgn:7146710",
        "tgn:1000003",
        "tgn:7003676",
        "tgn:7000084",
        "tgn:7029392"
    ],
    "tgn:id":7146710,
    "tgn:name":"Klostermoor",
    "tgn:placetype":[
        "aat:300008347"
    ]
},
  "bbox": [],
  "geometry": {"coordinates":[8.933333,53.166667],"type":"Point"}
}