{
  "id": 2704306,
  "type": "Feature",
  "properties": {
    "tgn:hierarchy":[
        "tgn:2704306",
        "tgn:1000001",
        "tgn:7012149",
        "tgn:7007256",
        "tgn:7029392"
    ],
    "tgn:id":2704306,
    "tgn:name":"Sunny Point",
    "tgn:placetype":[
        "aat:300008850"
    ]
},
  "bbox": [],
  "geometry": {"coordinates":[-93.65,32.3833],"type":"Point"}
}