<<<<<<< HEAD
{
  "id": 2405360,
  "type": "Feature",
  "properties": {
    "tgn:hierarchy":[
        "tgn:2405360",
        "tgn:1000001",
        "tgn:2001596",
        "tgn:7012149",
        "tgn:7007705",
        "tgn:7029392"
    ],
    "tgn:id":2405360,
    "tgn:name":"Hufty Lake",
    "tgn:placetype":[
        "aat:300008680"
    ]
},
  "bbox": [],
  "geometry": {"coordinates":[-99.7667,48.9333],"type":"Point"}
}
=======
{"geometry":{"type":"Point","coordinates":[-99.766700,48.933300]},"type":"Feature","properties":{"hierarchy":["tgn:2405360","tgn:1000001","tgn:2001596","tgn:7012149","tgn:7007705","tgn:7029392"],"placetype":["aat:300008680"],"id":2405360,"name:xx":"Hufty Lake"}}
>>>>>>> 03f74aca74312dbeaf24d7e61306dd6a786dc3d0
