{
  "id": 2357246,
  "type": "Feature",
  "properties": {
    "tgn:hierarchy":[
        "tgn:2357246",
        "tgn:1000001",
        "tgn:7012149",
        "tgn:2000933",
        "tgn:7007515",
        "tgn:7029392"
    ],
    "tgn:id":2357246,
    "tgn:name":"Goulds Rocks",
    "tgn:placetype":[
        "aat:300132348"
    ]
},
  "bbox": [],
  "geometry": {"coordinates":[-70.5333,43.3167],"type":"Point"}
}