{
  "id": 2723937,
  "type": "Feature",
  "properties": {
    "tgn:hierarchy":[
        "tgn:2723937",
        "tgn:1000001",
        "tgn:7012149",
        "tgn:2000850",
        "tgn:7007255",
        "tgn:7029392"
    ],
    "tgn:id":2723937,
    "tgn:name":"Toler Ridge",
    "tgn:placetype":[
        "aat:300266640"
    ]
},
  "bbox": [],
  "geometry": {"coordinates":[-84.9167,36.9167],"type":"Point"}
}