{
  "id": 2757453,
  "type": "Feature",
  "properties": {
    "tgn:hierarchy":[
        "tgn:2757453",
        "tgn:1000001",
        "tgn:7012149",
        "tgn:2000217",
        "tgn:7007158",
        "tgn:7029392"
    ],
    "tgn:id":2757453,
    "tgn:name":"West Beckwith Mountain",
    "tgn:placetype":[
        "aat:300008798"
    ]
},
  "bbox": [],
  "geometry": {"coordinates":[-107.2667,38.85],"type":"Point"}
}