{
  "id": 2458711,
  "type": "Feature",
  "properties": {
    "tgn:hierarchy":[
        "tgn:2458711",
        "tgn:1000001",
        "tgn:1002480",
        "tgn:7012149",
        "tgn:7007564",
        "tgn:7029392"
    ],
    "tgn:id":2458711,
    "tgn:name":"Little Ottarnic Pond",
    "tgn:placetype":[
        "aat:300008680"
    ]
},
  "bbox": [],
  "geometry": {"coordinates":[-71.4333,42.7667],"type":"Point"}
}