{
  "id": 2473856,
  "type": "Feature",
  "properties": {
    "tgn:hierarchy":[
        "tgn:2473856",
        "tgn:1000001",
        "tgn:7012149",
        "tgn:7007158",
        "tgn:2000246",
        "tgn:7029392"
    ],
    "tgn:id":2473856,
    "tgn:name":"Lower Gulch",
    "tgn:placetype":[
        "aat:300008761"
    ]
},
  "bbox": [],
  "geometry": {"coordinates":[-106.85,38.2333],"type":"Point"}
}