{
  "id": 2202134,
  "type": "Feature",
  "properties": {
    "tgn:hierarchy":[
        "tgn:2202134",
        "tgn:1000001",
        "tgn:7012149",
        "tgn:2000494",
        "tgn:7007250",
        "tgn:7029392"
    ],
    "tgn:id":2202134,
    "tgn:name":"Buck Lake",
    "tgn:placetype":[
        "aat:300008680"
    ]
},
  "bbox": [],
  "geometry": {"coordinates":[-115.2667,44.7833],"type":"Point"}
}