{
  "id": 2227732,
  "type": "Feature",
  "properties": {
    "tgn:hierarchy":[
        "tgn:2227732",
        "tgn:1000001",
        "tgn:1002207",
        "tgn:7012149",
        "tgn:7007240",
        "tgn:7029392"
    ],
    "tgn:id":2227732,
    "tgn:name":"Cayuga, Lake",
    "tgn:placetype":[
        "aat:300008680"
    ]
},
  "bbox": [],
  "geometry": {"coordinates":[-80.0833,26.1833],"type":"Point"}
}