<<<<<<< HEAD
{
  "id": 2157772,
  "type": "Feature",
  "properties": {
    "tgn:hierarchy":[
        "tgn:2157772",
        "tgn:1000001",
        "tgn:7012149",
        "tgn:2000926",
        "tgn:7007515",
        "tgn:7029392"
    ],
    "tgn:id":2157772,
    "tgn:name":"Beaver Island",
    "tgn:placetype":[
        "aat:300008791"
    ]
},
  "bbox": [],
  "geometry": {"coordinates":[-70.9,44.8833],"type":"Point"}
}
=======
{"geometry":{"type":"Point","coordinates":[-70.900000,44.883300]},"type":"Feature","properties":{"hierarchy":["tgn:2157772","tgn:1000001","tgn:7012149","tgn:2000926","tgn:7007515","tgn:7029392"],"placetype":["aat:300008791"],"id":2157772,"name:xx":"Beaver Island"}}
>>>>>>> 03f74aca74312dbeaf24d7e61306dd6a786dc3d0
