{
  "id": 7043281,
  "type": "Feature",
  "properties": {
    "tgn:hierarchy":[
        "tgn:7043281",
        "tgn:7003127",
        "tgn:1000003",
        "tgn:7008516",
        "tgn:1000080",
        "tgn:7029392"
    ],
    "tgn:id":7043281,
    "tgn:name":"Quarto Inferiore",
    "tgn:placetype":[
        "aat:300008347"
    ]
},
  "bbox": [],
  "geometry": {"coordinates":[11.416667,44.533333],"type":"Point"}
}