{
  "id": 2194671,
  "type": "Feature",
  "properties": {
    "tgn:hierarchy":[
        "tgn:2194671",
        "tgn:1000001",
        "tgn:7012149",
        "tgn:2002191",
        "tgn:7007919",
        "tgn:7029392"
    ],
    "tgn:id":2194671,
    "tgn:name":"Brier Cove",
    "tgn:placetype":[
        "aat:300008761"
    ]
},
  "bbox": [],
  "geometry": {"coordinates":[-81.7833,36.9333],"type":"Point"}
}