{
  "id": 2718332,
  "type": "Feature",
  "properties": {
    "tgn:hierarchy":[
        "tgn:2718332",
        "tgn:1000001",
        "tgn:7012149",
        "tgn:2001708",
        "tgn:7007708",
        "tgn:7029392"
    ],
    "tgn:id":2718332,
    "tgn:name":"Thompson Gulch",
    "tgn:placetype":[
        "aat:300008761"
    ]
},
  "bbox": [],
  "geometry": {"coordinates":[-118.9167,44.2167],"type":"Point"}
}