{
  "id": 2440376,
  "type": "Feature",
  "properties": {
    "tgn:hierarchy":[
        "tgn:2440376",
        "tgn:1000001",
        "tgn:7012149",
        "tgn:2002382",
        "tgn:7007923",
        "tgn:7029392"
    ],
    "tgn:id":2440376,
    "tgn:name":"Klondike Peak",
    "tgn:placetype":[
        "aat:300008798"
    ]
},
  "bbox": [],
  "geometry": {"coordinates":[-109.6833,43.2333],"type":"Point"}
}