{
  "id": 7091123,
  "type": "Feature",
  "properties": {
    "tgn:hierarchy":[
        "tgn:7091123",
        "tgn:7003692",
        "tgn:1000003",
        "tgn:7000084",
        "tgn:7029392"
    ],
    "tgn:id":7091123,
    "tgn:name":"Vogelsang",
    "tgn:placetype":[
        "aat:300000206"
    ]
},
  "bbox": [],
  "geometry": {"coordinates":[9.45,47.783333],"type":"Point"}
}