<<<<<<< HEAD
{
  "id": 2336961,
  "type": "Feature",
  "properties": {
    "tgn:hierarchy":[
        "tgn:2336961",
        "tgn:1000001",
        "tgn:7012149",
        "tgn:2002371",
        "tgn:7007923",
        "tgn:7029392"
    ],
    "tgn:id":2336961,
    "tgn:name":"Fourmile Creek",
    "tgn:placetype":[
        "aat:300008706"
    ]
},
  "bbox": [],
  "geometry": {"coordinates":[-109.7667,43.6667],"type":"Point"}
}
=======
{"geometry":{"type":"Point","coordinates":[-109.766700,43.666700]},"type":"Feature","properties":{"hierarchy":["tgn:2336961","tgn:1000001","tgn:7012149","tgn:2002371","tgn:7007923","tgn:7029392"],"placetype":["aat:300008706"],"id":2336961,"name:xx":"Fourmile Creek"}}
>>>>>>> 03f74aca74312dbeaf24d7e61306dd6a786dc3d0
