<<<<<<< HEAD
{
  "id": 2336575,
  "type": "Feature",
  "properties": {
    "tgn:hierarchy":[
        "tgn:2336575",
        "tgn:1000001",
        "tgn:7006451",
        "tgn:7012149",
        "tgn:2000102",
        "tgn:7029392"
    ],
    "tgn:id":2336575,
    "tgn:name":"Four Metals Mine",
    "tgn:placetype":[
        "aat:300000390"
    ]
},
  "bbox": [],
  "geometry": {"coordinates":[-110.7333,31.3833],"type":"Point"}
}
=======
{"geometry":{"type":"Point","coordinates":[-110.733300,31.383300]},"type":"Feature","properties":{"hierarchy":["tgn:2336575","tgn:1000001","tgn:7006451","tgn:7012149","tgn:2000102","tgn:7029392"],"placetype":["aat:300000390"],"id":2336575,"name:xx":"Four Metals Mine"}}
>>>>>>> 03f74aca74312dbeaf24d7e61306dd6a786dc3d0
