{
  "id": 7155720,
  "type": "Feature",
  "properties": {
    "tgn:hierarchy":[
        "tgn:7155720",
        "tgn:1000003",
        "tgn:7003678",
        "tgn:7000084",
        "tgn:7029392"
    ],
    "tgn:id":7155720,
    "tgn:name":"Kirchditmold",
    "tgn:placetype":[
        "aat:300000745"
    ]
},
  "bbox": [],
  "geometry": {"coordinates":[9.45,51.316667],"type":"Point"}
}