{
  "id": 2687737,
  "type": "Feature",
  "properties": {
    "tgn:hierarchy":[
        "tgn:2687737",
        "tgn:1000001",
        "tgn:1002310",
        "tgn:7012149",
        "tgn:7007710",
        "tgn:7029392"
    ],
    "tgn:id":2687737,
    "tgn:name":"Spring Run Manor",
    "tgn:placetype":[
        "aat:300008347"
    ]
},
  "bbox": [],
  "geometry": {"coordinates":[-76.9667,40.1667],"type":"Point"}
}