{
  "id": 2363843,
  "type": "Feature",
  "properties": {
    "tgn:hierarchy":[
        "tgn:2363843",
        "tgn:1000001",
        "tgn:7012149",
        "tgn:2001980",
        "tgn:7007826",
        "tgn:7029392"
    ],
    "tgn:id":2363843,
    "tgn:name":"Green Lake",
    "tgn:placetype":[
        "aat:300008680"
    ]
},
  "bbox": [],
  "geometry": {"coordinates":[-100.0833,30.2167],"type":"Point"}
}