{
  "id": 2168795,
  "type": "Feature",
  "properties": {
    "tgn:hierarchy":[
        "tgn:2168795",
        "tgn:1000001",
        "tgn:7012149",
        "tgn:2002113",
        "tgn:7007827",
        "tgn:7029392"
    ],
    "tgn:id":2168795,
    "tgn:name":"Big Hollow Wash",
    "tgn:placetype":[
        "aat:300008761"
    ]
},
  "bbox": [],
  "geometry": {"coordinates":[-111.2167,37.4167],"type":"Point"}
}