{
  "id": 2387941,
  "type": "Feature",
  "properties": {
    "tgn:hierarchy":[
        "tgn:2387941",
        "tgn:1000001",
        "tgn:7012149",
        "tgn:2001520",
        "tgn:7007709",
        "tgn:7029392"
    ],
    "tgn:id":2387941,
    "tgn:name":"Hickory Branch",
    "tgn:placetype":[
        "aat:300008699"
    ]
},
  "bbox": [],
  "geometry": {"coordinates":[-79.7833,35.35],"type":"Point"}
}