{
  "id": 2181627,
  "type": "Feature",
  "properties": {
    "tgn:hierarchy":[
        "tgn:2181627",
        "tgn:1000001",
        "tgn:7012149",
        "tgn:7007157",
        "tgn:7029392"
    ],
    "tgn:id":2181627,
    "tgn:name":"Blue Hole",
    "tgn:placetype":[
        "aat:300008680"
    ]
},
  "bbox": [],
  "geometry": {"coordinates":[-120.1333,38.4833],"type":"Point"}
}