{
  "id": 2154268,
  "type": "Feature",
  "properties": {
    "tgn:hierarchy":[
        "tgn:2154268",
        "tgn:1000001",
        "tgn:7012149",
        "tgn:7016021",
        "tgn:7007568",
        "tgn:7029392"
    ],
    "tgn:id":2154268,
    "tgn:name":"Bear Creek",
    "tgn:placetype":[
        "aat:300008706"
    ]
},
  "bbox": [],
  "geometry": {"coordinates":[-74.9167,44.3833],"type":"Point"}
}