{
  "id": 7365955,
  "type": "Feature",
  "properties": {
    "tgn:hierarchy":[
        "tgn:7365955",
        "tgn:1000001",
        "tgn:7005595",
        "tgn:7005560",
        "tgn:7029392"
    ],
    "tgn:id":7365955,
    "tgn:name":"El Tastecito",
    "tgn:placetype":[
        "aat:300008347"
    ]
},
  "bbox": [],
  "geometry": {"coordinates":[-107.383333,25.983333],"type":"Point"}
}