{
  "id": 7053357,
  "type": "Feature",
  "properties": {
    "tgn:hierarchy":[
        "tgn:7053357",
        "tgn:7015163",
        "tgn:1000003",
        "tgn:7003121",
        "tgn:1000080",
        "tgn:7029392"
    ],
    "tgn:id":7053357,
    "tgn:name":"Pozzu d'Ussi, Monte",
    "tgn:placetype":[
        "aat:300008777"
    ]
},
  "bbox": [],
  "geometry": {"coordinates":[8.25,40.783333],"type":"Point"}
}