{
  "id": 2689139,
  "type": "Feature",
  "properties": {
    "tgn:hierarchy":[
        "tgn:2689139",
        "tgn:7006450",
        "tgn:1000001",
        "tgn:7019698",
        "tgn:7012149",
        "tgn:7029392"
    ],
    "tgn:id":2689139,
    "tgn:name":"Squarehead Cove",
    "tgn:placetype":[
        "aat:300132316"
    ]
},
  "bbox": [],
  "geometry": {"coordinates":[-152.65,60.2333],"type":"Point"}
}