{
  "id": 2461037,
  "type": "Feature",
  "properties": {
    "tgn:hierarchy":[
        "tgn:2461037",
        "tgn:2001732",
        "tgn:1000001",
        "tgn:7012149",
        "tgn:7007712",
        "tgn:7029392"
    ],
    "tgn:id":2461037,
    "tgn:name":"Little Solomon Lake",
    "tgn:placetype":[
        "aat:300008905"
    ]
},
  "bbox": [],
  "geometry": {"coordinates":[-80.0333,33.4833],"type":"Point"}
}