{
  "id": 1048374,
  "type": "Feature",
  "properties": {
    "tgn:hierarchy":[
        "tgn:1048374",
        "tgn:7002448",
        "tgn:1000003",
        "tgn:7019206",
        "tgn:7008591",
        "tgn:7029392"
    ],
    "tgn:id":1048374,
    "tgn:name:en":"Killeter",
    "tgn:placetype":[
        "aat:300008347"
    ]
},
  "bbox": [],
  "geometry": {"coordinates":[-7.683333,54.666667],"type":"Point"}
}