{
  "id": 2374175,
  "type": "Feature",
  "properties": {
    "tgn:hierarchy":[
        "tgn:2374175",
        "tgn:1000001",
        "tgn:7016172",
        "tgn:7012149",
        "tgn:2000178",
        "tgn:7029392"
    ],
    "tgn:id":2374175,
    "tgn:name":"Hammond Lake",
    "tgn:placetype":[
        "aat:300008680"
    ]
},
  "bbox": [],
  "geometry": {"coordinates":[-91.3167,34.9833],"type":"Point"}
}