{
  "id": 7328264,
  "type": "Feature",
  "properties": {
    "tgn:hierarchy":[
        "tgn:7328264",
        "tgn:7002820",
        "tgn:7030216",
        "tgn:1000003",
        "tgn:1000095",
        "tgn:7029392"
    ],
    "tgn:id":7328264,
    "tgn:name":"Remol\u00f3, Coll de",
    "tgn:placetype":[
        "aat:300259572"
    ]
},
  "bbox": [],
  "geometry": {"coordinates":[2.059886,42.294255],"type":"Point"}
}