{
  "id": 2548075,
  "type": "Feature",
  "properties": {
    "tgn:hierarchy":[
        "tgn:2548075",
        "tgn:1000001",
        "tgn:1002284",
        "tgn:7012149",
        "tgn:7007568",
        "tgn:7029392"
    ],
    "tgn:id":2548075,
    "tgn:name":"North Hill",
    "tgn:placetype":[
        "aat:300008798"
    ]
},
  "bbox": [],
  "geometry": {"coordinates":[-73.7667,44.4667],"type":"Point"}
}