{
  "id": 7094010,
  "type": "Feature",
  "properties": {
    "tgn:hierarchy":[
        "tgn:7094010",
        "tgn:7000096",
        "tgn:1000003",
        "tgn:7000084",
        "tgn:7029392"
    ],
    "tgn:id":7094010,
    "tgn:name":"Sch\u00f6now",
    "tgn:placetype":[
        "aat:300008347"
    ]
},
  "bbox": [],
  "geometry": {"coordinates":[14.15,53.183333],"type":"Point"}
}