{
  "id": 2034779,
  "type": "Feature",
  "properties": {
    "tgn:hierarchy":[
        "tgn:2034779",
        "tgn:2000567",
        "tgn:1000001",
        "tgn:7012149",
        "tgn:7007253",
        "tgn:7029392"
    ],
    "tgn:id":2034779,
    "tgn:name":"Finchford",
    "tgn:placetype":[
        "aat:300008347"
    ]
},
  "bbox": [],
  "geometry": {"coordinates":[-92.5333,42.6167],"type":"Point"}
}