{
  "id": 2673963,
  "type": "Feature",
  "properties": {
    "tgn:hierarchy":[
        "tgn:2673963",
        "tgn:1000001",
        "tgn:7012149",
        "tgn:2001717",
        "tgn:7007708",
        "tgn:7029392"
    ],
    "tgn:id":2673963,
    "tgn:name":"Snow Peak Log Pond",
    "tgn:placetype":[
        "aat:300006191"
    ]
},
  "bbox": [],
  "geometry": {"coordinates":[-122.8667,44.5833],"type":"Point"}
}