{
  "id": 7587867,
  "type": "Feature",
  "properties": {
    "tgn:hierarchy":[
        "tgn:7587867",
        "tgn:1000004",
        "tgn:7000198",
        "tgn:7000799",
        "tgn:7029392"
    ],
    "tgn:id":7587867,
    "tgn:name:en":"Sirb\u0101gh",
    "tgn:placetype":[
        "aat:300008347"
    ]
},
  "bbox": [],
  "geometry": {"coordinates":[74.898611,34.033333],"type":"Point"}
}