{
  "id": 2589782,
  "type": "Feature",
  "properties": {
    "tgn:hierarchy":[
        "tgn:2589782",
        "tgn:1000001",
        "tgn:7012149",
        "tgn:2002124",
        "tgn:7007827",
        "tgn:7029392"
    ],
    "tgn:id":2589782,
    "tgn:name":"Point Spring",
    "tgn:placetype":[
        "aat:300008697"
    ]
},
  "bbox": [],
  "geometry": {"coordinates":[-109.4333,40.65],"type":"Point"}
}