{
  "id": 2450784,
  "type": "Feature",
  "properties": {
    "tgn:hierarchy":[
        "tgn:2450784",
        "tgn:1000001",
        "tgn:7012149",
        "tgn:2001713",
        "tgn:7007708",
        "tgn:7029392"
    ],
    "tgn:id":2450784,
    "tgn:name":"Lippert Reservoir Number Two",
    "tgn:placetype":[
        "aat:300006191"
    ]
},
  "bbox": [],
  "geometry": {"coordinates":[-123.25,42.2667],"type":"Point"}
}