{
  "id": 7220761,
  "type": "Feature",
  "properties": {
    "tgn:hierarchy":[
        "tgn:7220761",
        "tgn:7011170",
        "tgn:7002715",
        "tgn:1000003",
        "tgn:1000074",
        "tgn:7029392"
    ],
    "tgn:id":7220761,
    "tgn:name":"Tsar\u00ed, \u00d3rmos",
    "tgn:placetype":[
        "aat:300132316"
    ]
},
  "bbox": [],
  "geometry": {"coordinates":[24.484444,40.951111],"type":"Point"}
}