<<<<<<< HEAD
{
  "id": 2765524,
  "type": "Feature",
  "properties": {
    "tgn:hierarchy":[
        "tgn:2765524",
        "tgn:1000001",
        "tgn:7012149",
        "tgn:2001276",
        "tgn:7007524",
        "tgn:7029392"
    ],
    "tgn:id":2765524,
    "tgn:name":"White Buttes",
    "tgn:placetype":[
        "aat:300008798"
    ]
},
  "bbox": [],
  "geometry": {"coordinates":[-106.2667,47.3],"type":"Point"}
}
=======
{"geometry":{"type":"Point","coordinates":[-106.266700,47.300000]},"type":"Feature","properties":{"hierarchy":["tgn:2765524","tgn:1000001","tgn:7012149","tgn:2001276","tgn:7007524","tgn:7029392"],"placetype":["aat:300008798"],"id":2765524,"name:xx":"White Buttes"}}
>>>>>>> 03f74aca74312dbeaf24d7e61306dd6a786dc3d0
