{
  "id": 7482902,
  "type": "Feature",
  "properties": {
    "tgn:hierarchy":[
        "tgn:7482902",
        "tgn:7468018",
        "tgn:1000004",
        "tgn:1000141",
        "tgn:7029392"
    ],
    "tgn:id":7482902,
    "tgn:name":"Tiantouqi",
    "tgn:placetype":[
        "aat:300008347"
    ]
},
  "bbox": [],
  "geometry": {"coordinates":[120.564444,23.5825],"type":"Point"}
}