{
  "id": 7517163,
  "type": "Feature",
  "properties": {
    "tgn:hierarchy":[
        "tgn:7517163",
        "tgn:1008380",
        "tgn:7520093",
        "tgn:1000226",
        "tgn:1000006",
        "tgn:7029392"
    ],
    "tgn:id":7517163,
    "tgn:name:en":"Mangaehuehu Stream",
    "tgn:placetype":[
        "aat:300008699"
    ]
},
  "bbox": [],
  "geometry": {"coordinates":[175.466667,-39.483333],"type":"Point"}
}