{
  "id": 7221464,
  "type": "Feature",
  "properties": {
    "tgn:hierarchy":[
        "tgn:7221464",
        "tgn:7011164",
        "tgn:7002674",
        "tgn:1000003",
        "tgn:1000074",
        "tgn:7029392"
    ],
    "tgn:id":7221464,
    "tgn:name":"Vr\u00fdsai",
    "tgn:placetype":[
        "aat:300008347"
    ]
},
  "bbox": [],
  "geometry": {"coordinates":[26.738333,37.798333],"type":"Point"}
}