{
  "id": 1053484,
  "type": "Feature",
  "properties": {
    "tgn:hierarchy":[
        "tgn:1053484",
        "tgn:1000004",
        "tgn:1003363",
        "tgn:7014786",
        "tgn:7029392"
    ],
    "tgn:id":1053484,
    "tgn:name":"D\u017eezdy",
    "tgn:placetype":[
        "aat:300008347"
    ]
},
  "bbox": [],
  "geometry": {"coordinates":[67.0833,48.0667],"type":"Point"}
}