{
  "id": 2366354,
  "type": "Feature",
  "properties": {
    "tgn:hierarchy":[
        "tgn:2366354",
        "tgn:1000001",
        "tgn:7012149",
        "tgn:2000441",
        "tgn:7007248",
        "tgn:7029392"
    ],
    "tgn:id":2366354,
    "tgn:name":"Griffith Branch",
    "tgn:placetype":[
        "aat:300008699"
    ]
},
  "bbox": [],
  "geometry": {"coordinates":[-82.7333,32.85],"type":"Point"}
}