{
  "id": 7569731,
  "type": "Feature",
  "properties": {
    "tgn:hierarchy":[
        "tgn:7569731",
        "tgn:1000004",
        "tgn:7000198",
        "tgn:7031786",
        "tgn:7029392"
    ],
    "tgn:id":7569731,
    "tgn:name:en":"Gaw\u0101lgaon",
    "tgn:placetype":[
        "aat:300008347"
    ]
},
  "bbox": [],
  "geometry": {"coordinates":[78.618125,29.952076],"type":"Point"}
}