{
  "id": 7317673,
  "type": "Feature",
  "properties": {
    "tgn:hierarchy":[
        "tgn:7317673",
        "tgn:7016598",
        "tgn:1000049",
        "tgn:1000002",
        "tgn:7029392"
    ],
    "tgn:id":7317673,
    "tgn:name":"Colupo, Cerro",
    "tgn:placetype":[
        "aat:300008795"
    ]
},
  "bbox": [],
  "geometry": {"coordinates":[-69.966667,-22.416667],"type":"Point"}
}