{
  "id": 7252695,
  "type": "Feature",
  "properties": {
    "tgn:hierarchy":[
        "tgn:7252695",
        "tgn:7003456",
        "tgn:1000003",
        "tgn:1000063",
        "tgn:7018236",
        "tgn:7029392"
    ],
    "tgn:id":7252695,
    "tgn:name":"Sint-Jozef",
    "tgn:placetype":[
        "aat:300008347"
    ]
},
  "bbox": [],
  "geometry": {"coordinates":[4.293742,51.031894],"type":"Point"}
}