{
  "id": 1114566,
  "type": "Feature",
  "properties": {
    "tgn:hierarchy":[
        "tgn:1114566",
        "tgn:7005735",
        "tgn:7005685",
        "tgn:1000001",
        "tgn:7029392"
    ],
    "tgn:id":1114566,
    "tgn:name":"Bute Inlet",
    "tgn:placetype":[
        "aat:300185707"
    ]
},
  "bbox": [],
  "geometry": {"coordinates":[-124.9167,50.5833],"type":"Point"}
}