{
  "id": 1059206,
  "type": "Feature",
  "properties": {
    "tgn:hierarchy":[
        "tgn:1059206",
        "tgn:1000004",
        "tgn:7012215",
        "tgn:7006653",
        "tgn:7029392"
    ],
    "tgn:id":1059206,
    "tgn:name":"Sartichala",
    "tgn:placetype":[
        "aat:300008347"
    ]
},
  "bbox": [],
  "geometry": {"coordinates":[45.1833,41.7167],"type":"Point"}
}