<<<<<<< HEAD
{
  "id": 7247791,
  "type": "Feature",
  "properties": {
    "tgn:hierarchy":[
        "tgn:7247791",
        "tgn:7003456",
        "tgn:1000003",
        "tgn:1000063",
        "tgn:7018236",
        "tgn:7029392"
    ],
    "tgn:id":7247791,
    "tgn:name":"Duivelshoek",
    "tgn:placetype":[
        "aat:300008347"
    ]
},
  "bbox": [],
  "geometry": {"coordinates":[4.565105,51.046475],"type":"Point"}
}
=======
{"geometry":{"type":"Point","coordinates":[4.565105,51.046475]},"type":"Feature","properties":{"hierarchy":["tgn:7247791","tgn:7003456","tgn:1000003","tgn:1000063","tgn:7018236","tgn:7029392"],"placetype":["aat:300008347"],"id":7247791,"name:xx":"Duivelshoek"}}
>>>>>>> 03f74aca74312dbeaf24d7e61306dd6a786dc3d0
