{
  "id": 2321957,
  "type": "Feature",
  "properties": {
    "tgn:hierarchy":[
        "tgn:2321957",
        "tgn:1000001",
        "tgn:7012149",
        "tgn:2001843",
        "tgn:7007825",
        "tgn:7029392"
    ],
    "tgn:id":2321957,
    "tgn:name":"Fall Branch",
    "tgn:placetype":[
        "aat:300008699"
    ]
},
  "bbox": [],
  "geometry": {"coordinates":[-84.1667,36.5667],"type":"Point"}
}