{
  "id": 7103271,
  "type": "Feature",
  "properties": {
    "tgn:hierarchy":[
        "tgn:7103271",
        "tgn:1000003",
        "tgn:7003677",
        "tgn:7000084",
        "tgn:7029392"
    ],
    "tgn:id":7103271,
    "tgn:name":"Sabbenhausen",
    "tgn:placetype":[
        "aat:300008347"
    ]
},
  "bbox": [],
  "geometry": {"coordinates":[9.283333,51.916667],"type":"Point"}
}