{
  "id": 2290236,
  "type": "Feature",
  "properties": {
    "tgn:hierarchy":[
        "tgn:2290236",
        "tgn:1000001",
        "tgn:7012149",
        "tgn:2001288",
        "tgn:7007524",
        "tgn:7029392"
    ],
    "tgn:id":2290236,
    "tgn:name":"Dodge Ditch",
    "tgn:placetype":[
        "aat:300006075"
    ]
},
  "bbox": [],
  "geometry": {"coordinates":[-111.9333,45.7667],"type":"Point"}
}