{
  "id": 2412862,
  "type": "Feature",
  "properties": {
    "tgn:hierarchy":[
        "tgn:2412862",
        "tgn:1000001",
        "tgn:7012149",
        "tgn:7007157",
        "tgn:2000185",
        "tgn:7029392"
    ],
    "tgn:id":2412862,
    "tgn:name":"Ingram",
    "tgn:placetype":[
        "aat:300008347"
    ]
},
  "bbox": [],
  "geometry": {"coordinates":[-123.1667,38.8833],"type":"Point"}
}