<<<<<<< HEAD
{
  "id": 7470346,
  "type": "Feature",
  "properties": {
    "tgn:hierarchy":[
        "tgn:7470346",
        "tgn:1000004",
        "tgn:7467799",
        "tgn:1000141",
        "tgn:7029392"
    ],
    "tgn:id":7470346,
    "tgn:name":"Xizhou",
    "tgn:placetype":[
        "aat:300008347"
    ]
},
  "bbox": [],
  "geometry": {"coordinates":[120.495305,23.853254],"type":"Point"}
}
=======
{"geometry":{"type":"Point","coordinates":[120.495305,23.853254]},"type":"Feature","properties":{"hierarchy":["tgn:7470346","tgn:1000004","tgn:7467799","tgn:1000141","tgn:7029392"],"placetype":["aat:300008347"],"id":7470346,"name:xx":"Xizhou"}}
>>>>>>> 03f74aca74312dbeaf24d7e61306dd6a786dc3d0
