<<<<<<< HEAD
{
  "id": 7355794,
  "type": "Feature",
  "properties": {
    "tgn:hierarchy":[
        "tgn:7355794",
        "tgn:7005581",
        "tgn:1000001",
        "tgn:7005560",
        "tgn:7029392"
    ],
    "tgn:id":7355794,
    "tgn:name":"Rancho Chico",
    "tgn:placetype":[
        "aat:300000241"
    ]
},
  "bbox": [],
  "geometry": {"coordinates":[-104.816667,27.15],"type":"Point"}
}
=======
{"geometry":{"type":"Point","coordinates":[-104.816667,27.150000]},"type":"Feature","properties":{"hierarchy":["tgn:7355794","tgn:7005581","tgn:1000001","tgn:7005560","tgn:7029392"],"placetype":["aat:300000241"],"id":7355794,"name:xx":"Rancho Chico"}}
>>>>>>> 03f74aca74312dbeaf24d7e61306dd6a786dc3d0
