{
  "id": 2598906,
  "type": "Feature",
  "properties": {
    "tgn:hierarchy":[
        "tgn:2598906",
        "tgn:1000001",
        "tgn:2001746",
        "tgn:7012149",
        "tgn:7007712",
        "tgn:7029392"
    ],
    "tgn:id":2598906,
    "tgn:name":"Prince Creek",
    "tgn:placetype":[
        "aat:300008706"
    ]
},
  "bbox": [],
  "geometry": {"coordinates":[-79.3667,33.4833],"type":"Point"}
}