{
  "id": 1098490,
  "type": "Feature",
  "properties": {
    "tgn:hierarchy":[
        "tgn:1098490",
        "tgn:7000490",
        "tgn:1000006",
        "tgn:7001828",
        "tgn:7029392"
    ],
    "tgn:id":1098490,
    "tgn:name":"Weilmoringle",
    "tgn:placetype":[
        "aat:300008347"
    ]
},
  "bbox": [],
  "geometry": {"coordinates":[146.9167,-29.2667],"type":"Point"}
}