{
  "id": 2712974,
  "type": "Feature",
  "properties": {
    "tgn:hierarchy":[
        "tgn:2712974",
        "tgn:7002659",
        "tgn:1000001",
        "tgn:7012149",
        "tgn:2000031",
        "tgn:7029392"
    ],
    "tgn:id":2712974,
    "tgn:name":"Taylor Lake",
    "tgn:placetype":[
        "aat:300006191"
    ]
},
  "bbox": [],
  "geometry": {"coordinates":[-87.8667,32.75],"type":"Point"}
}