{
  "id": 7194179,
  "type": "Feature",
  "properties": {
    "tgn:hierarchy":[
        "tgn:7194179",
        "tgn:1000003",
        "tgn:7003689",
        "tgn:7000084",
        "tgn:7029392"
    ],
    "tgn:id":7194179,
    "tgn:name":"D\u00e4nischer Berg",
    "tgn:placetype":[
        "aat:300008777"
    ]
},
  "bbox": [],
  "geometry": {"coordinates":[10.333333,50.783333],"type":"Point"}
}