{
  "id": 7306486,
  "type": "Feature",
  "properties": {
    "tgn:hierarchy":[
        "tgn:7306486",
        "tgn:7002849",
        "tgn:1000003",
        "tgn:7009604",
        "tgn:1000095",
        "tgn:7029392"
    ],
    "tgn:id":7306486,
    "tgn:name":"Malax",
    "tgn:placetype":[
        "aat:300008347"
    ]
},
  "bbox": [],
  "geometry": {"coordinates":[-2.544941,43.284284],"type":"Point"}
}