<<<<<<< HEAD
{
  "id": 7355596,
  "type": "Feature",
  "properties": {
    "tgn:hierarchy":[
        "tgn:7355596",
        "tgn:1000001",
        "tgn:7005599",
        "tgn:7005560",
        "tgn:7029392"
    ],
    "tgn:id":7355596,
    "tgn:name":"Chichipilco",
    "tgn:placetype":[
        "aat:300008347"
    ]
},
  "bbox": [],
  "geometry": {"coordinates":[-95.8,18.566667],"type":"Point"}
}
=======
{"geometry":{"type":"Point","coordinates":[-95.800000,18.566667]},"type":"Feature","properties":{"hierarchy":["tgn:7355596","tgn:1000001","tgn:7005599","tgn:7005560","tgn:7029392"],"placetype":["aat:300008347"],"id":7355596,"name:xx":"Chichipilco"}}
>>>>>>> 03f74aca74312dbeaf24d7e61306dd6a786dc3d0
