{
  "id": 7333445,
  "type": "Feature",
  "properties": {
    "tgn:hierarchy":[
        "tgn:7333445",
        "tgn:7002758",
        "tgn:7002823",
        "tgn:1000003",
        "tgn:1000095",
        "tgn:7029392"
    ],
    "tgn:id":7333445,
    "tgn:name":"Estaci\u00f3n de Gil M\u00e1rquez",
    "tgn:placetype":[
        "aat:300008347"
    ]
},
  "bbox": [],
  "geometry": {"coordinates":[-6.85,37.85],"type":"Point"}
}