{
  "id": 2445618,
  "type": "Feature",
  "properties": {
    "tgn:hierarchy":[
        "tgn:2445618",
        "tgn:1000001",
        "tgn:7012149",
        "tgn:7016021",
        "tgn:7007568",
        "tgn:7029392"
    ],
    "tgn:id":2445618,
    "tgn:name":"Leonard Brook",
    "tgn:placetype":[
        "aat:300008699"
    ]
},
  "bbox": [],
  "geometry": {"coordinates":[-74.9667,44.4833],"type":"Point"}
}