{
  "id": 7587800,
  "type": "Feature",
  "properties": {
    "tgn:hierarchy":[
        "tgn:7587800",
        "tgn:1000004",
        "tgn:7000198",
        "tgn:7000799",
        "tgn:7029392"
    ],
    "tgn:id":7587800,
    "tgn:name:en":"B\u0101bagund",
    "tgn:placetype":[
        "aat:300008347"
    ]
},
  "bbox": [],
  "geometry": {"coordinates":[74.557746,34.119454],"type":"Point"}
}