<<<<<<< HEAD
{
  "id": 7483192,
  "type": "Feature",
  "properties": {
    "tgn:hierarchy":[
        "tgn:7483192",
        "tgn:1000004",
        "tgn:7001014",
        "tgn:1000141",
        "tgn:7029392"
    ],
    "tgn:id":7483192,
    "tgn:name":"Shuijing",
    "tgn:placetype":[
        "aat:300387033"
    ]
},
  "bbox": [],
  "geometry": {"coordinates":[120.186944,23.529167],"type":"Point"}
}
=======
{"geometry":{"type":"Point","coordinates":[120.186944,23.529167]},"type":"Feature","properties":{"hierarchy":["tgn:7483192","tgn:1000004","tgn:7001014","tgn:1000141","tgn:7029392"],"placetype":["aat:300387033"],"id":7483192,"name:xx":"Shuijing"}}
>>>>>>> 03f74aca74312dbeaf24d7e61306dd6a786dc3d0
