{
  "id": 7546956,
  "type": "Feature",
  "properties": {
    "tgn:hierarchy":[
        "tgn:7546956",
        "tgn:1000004",
        "tgn:7000198",
        "tgn:1001886",
        "tgn:7029392"
    ],
    "tgn:id":7546956,
    "tgn:name:en":"B\u0101l\u016bssheri",
    "tgn:placetype":[
        "aat:300008347"
    ]
},
  "bbox": [],
  "geometry": {"coordinates":[75.833333,11.45],"type":"Point"}
}