{
  "id": 7418934,
  "type": "Feature",
  "properties": {
    "tgn:hierarchy":[
        "tgn:7418934",
        "tgn:1000001",
        "tgn:7005589",
        "tgn:7005560",
        "tgn:7029392"
    ],
    "tgn:id":7418934,
    "tgn:name:es":"Pur\u00edsima",
    "tgn:placetype":[
        "aat:300008347"
    ]
},
  "bbox": [],
  "geometry": {"coordinates":[-100.347778,24.384722],"type":"Point"}
}