{
  "id": 2629695,
  "type": "Feature",
  "properties": {
    "tgn:hierarchy":[
        "tgn:2629695",
        "tgn:1000001",
        "tgn:7012149",
        "tgn:2001233",
        "tgn:7007523",
        "tgn:7029392"
    ],
    "tgn:id":2629695,
    "tgn:name":"Ross Bridge",
    "tgn:placetype":[
        "aat:300008347"
    ]
},
  "bbox": [],
  "geometry": {"coordinates":[-92.0333,37.65],"type":"Point"}
}