{
  "id": 2108390,
  "type": "Feature",
  "properties": {
    "tgn:hierarchy":[
        "tgn:2108390",
        "tgn:1000001",
        "tgn:7012149",
        "tgn:1003034",
        "tgn:7007826",
        "tgn:7029392"
    ],
    "tgn:id":2108390,
    "tgn:name":"Webster",
    "tgn:placetype":[
        "aat:300008347",
        "aat:300387210"
    ]
},
  "bbox": [],
  "geometry": {"coordinates":[-95.3167,32.9167],"type":"Point"}
}