{
  "id": 7361638,
  "type": "Feature",
  "properties": {
    "tgn:hierarchy":[
        "tgn:7361638",
        "tgn:1000001",
        "tgn:7005599",
        "tgn:7005560",
        "tgn:7029392"
    ],
    "tgn:id":7361638,
    "tgn:name":"El \u00d3rgano",
    "tgn:placetype":[
        "aat:300008347"
    ]
},
  "bbox": [],
  "geometry": {"coordinates":[-98.016667,21.333333],"type":"Point"}
}