<<<<<<< HEAD
{
  "id": 2256851,
  "type": "Feature",
  "properties": {
    "tgn:hierarchy":[
        "tgn:2256851",
        "tgn:1000001",
        "tgn:7012149",
        "tgn:2000471",
        "tgn:7007250",
        "tgn:7029392"
    ],
    "tgn:id":2256851,
    "tgn:name":"Corker Creek",
    "tgn:placetype":[
        "aat:300008706"
    ]
},
  "bbox": [],
  "geometry": {"coordinates":[-115.35,43.2167],"type":"Point"}
}
=======
{"geometry":{"type":"Point","coordinates":[-115.350000,43.216700]},"type":"Feature","properties":{"hierarchy":["tgn:2256851","tgn:1000001","tgn:7012149","tgn:2000471","tgn:7007250","tgn:7029392"],"placetype":["aat:300008706"],"id":2256851,"name:xx":"Corker Creek"}}
>>>>>>> 03f74aca74312dbeaf24d7e61306dd6a786dc3d0
