{
  "id": 7330127,
  "type": "Feature",
  "properties": {
    "tgn:hierarchy":[
        "tgn:7330127",
        "tgn:7002803",
        "tgn:1001647",
        "tgn:1000003",
        "tgn:1000095",
        "tgn:7029392"
    ],
    "tgn:id":7330127,
    "tgn:name":"Estaci\u00f3n Hoya del Pozo",
    "tgn:placetype":[
        "aat:300007783"
    ]
},
  "bbox": [],
  "geometry": {"coordinates":[-2.083333,39.15],"type":"Point"}
}