{
  "id": 7013545,
  "type": "Feature",
  "properties": {
    "tgn:hierarchy":[
        "tgn:7013545",
        "tgn:1000001",
        "tgn:7012149",
        "tgn:2000207",
        "tgn:7007158",
        "tgn:7029392"
    ],
    "tgn:id":7013545,
    "tgn:name":"Denver",
    "tgn:placetype":[
        "aat:300387234",
        "aat:300387277",
        "aat:300008347",
        "aat:300008416",
        "aat:300387218",
        "aat:300008389",
        "aat:300264742",
        "aat:300387512",
        "aat:300387305",
        "aat:300387221",
        "aat:300387270",
        "aat:300387302",
        "aat:300387307",
        "aat:300387300",
        "aat:300387291"
    ]
},
  "bbox": [],
  "geometry": {"coordinates":[-104.9833,39.7333],"type":"Point"}
}