{
  "id": 2040354,
  "type": "Feature",
  "properties": {
    "tgn:hierarchy":[
        "tgn:2040354",
        "tgn:1002169",
        "tgn:1000001",
        "tgn:7012149",
        "tgn:7007255",
        "tgn:7029392"
    ],
    "tgn:id":2040354,
    "tgn:name":"Moores Ferry",
    "tgn:placetype":[
        "aat:300008347"
    ]
},
  "bbox": [],
  "geometry": {"coordinates":[-83.6167,38.1667],"type":"Point"}
}