{
  "id": 2485440,
  "type": "Feature",
  "properties": {
    "tgn:hierarchy":[
        "tgn:2485440",
        "tgn:1000001",
        "tgn:7012149",
        "tgn:2000808",
        "tgn:7007255",
        "tgn:7029392"
    ],
    "tgn:id":2485440,
    "tgn:name":"Lawson Hollow",
    "tgn:placetype":[
        "aat:300008761"
    ]
},
  "bbox": [],
  "geometry": {"coordinates":[-84.1667,37.2833],"type":"Point"}
}