{
  "id": 2287273,
  "type": "Feature",
  "properties": {
    "tgn:hierarchy":[
        "tgn:2287273",
        "tgn:7006450",
        "tgn:1000001",
        "tgn:7012149",
        "tgn:7019760",
        "tgn:7029392"
    ],
    "tgn:id":2287273,
    "tgn:name":"Dicks Arm",
    "tgn:placetype":[
        "aat:300132316"
    ]
},
  "bbox": [],
  "geometry": {"coordinates":[-136.6167,58.2167],"type":"Point"}
}