<<<<<<< HEAD
{
  "id": 7118371,
  "type": "Feature",
  "properties": {
    "tgn:hierarchy":[
        "tgn:7118371",
        "tgn:1000003",
        "tgn:7003682",
        "tgn:7000084",
        "tgn:7029392"
    ],
    "tgn:id":7118371,
    "tgn:name":"Pommer Bach",
    "tgn:placetype":[
        "aat:300008699"
    ]
},
  "bbox": [],
  "geometry": {"coordinates":[7.266667,50.166667],"type":"Point"}
}
=======
{"geometry":{"type":"Point","coordinates":[7.266667,50.166667]},"type":"Feature","properties":{"hierarchy":["tgn:7118371","tgn:1000003","tgn:7003682","tgn:7000084","tgn:7029392"],"placetype":["aat:300008699"],"id":7118371,"name:xx":"Pommer Bach"}}
>>>>>>> 03f74aca74312dbeaf24d7e61306dd6a786dc3d0
