{
  "id": 7299284,
  "type": "Feature",
  "properties": {
    "tgn:hierarchy":[
        "tgn:7299284",
        "tgn:7002820",
        "tgn:7030216",
        "tgn:1000003",
        "tgn:1000095",
        "tgn:7029392"
    ],
    "tgn:id":7299284,
    "tgn:name":"Tosas",
    "tgn:placetype":[
        "aat:300008347"
    ]
},
  "bbox": [],
  "geometry": {"coordinates":[2.016025,42.321379],"type":"Point"}
}