{
  "id": 7200257,
  "type": "Feature",
  "properties": {
    "tgn:hierarchy":[
        "tgn:7200257",
        "tgn:7003669",
        "tgn:1000003",
        "tgn:7000084",
        "tgn:7029392"
    ],
    "tgn:id":7200257,
    "tgn:name":"D\u00fcrrenhembach",
    "tgn:placetype":[
        "aat:300008347"
    ]
},
  "bbox": [],
  "geometry": {"coordinates":[11.216667,49.333333],"type":"Point"}
}