{
  "id": 2328937,
  "type": "Feature",
  "properties": {
    "tgn:hierarchy":[
        "tgn:2328937",
        "tgn:1000001",
        "tgn:7012149",
        "tgn:1002782",
        "tgn:7007710",
        "tgn:7029392"
    ],
    "tgn:id":2328937,
    "tgn:name":"Fishtown",
    "tgn:placetype":[
        "aat:300008347"
    ]
},
  "bbox": [],
  "geometry": {"coordinates":[-75.1333,39.95],"type":"Point"}
}