<<<<<<< HEAD
{
  "id": 7371474,
  "type": "Feature",
  "properties": {
    "tgn:hierarchy":[
        "tgn:7371474",
        "tgn:1000001",
        "tgn:7005589",
        "tgn:7005560",
        "tgn:7029392"
    ],
    "tgn:id":7371474,
    "tgn:name":"Hacienda San Patricio",
    "tgn:placetype":[
        "aat:300008347"
    ]
},
  "bbox": [],
  "geometry": {"coordinates":[-100.633333,27.233333],"type":"Point"}
}
=======
{"geometry":{"type":"Point","coordinates":[-100.633333,27.233333]},"type":"Feature","properties":{"hierarchy":["tgn:7371474","tgn:1000001","tgn:7005589","tgn:7005560","tgn:7029392"],"placetype":["aat:300008347"],"id":7371474,"name:xx":"Hacienda San Patricio"}}
>>>>>>> 03f74aca74312dbeaf24d7e61306dd6a786dc3d0
