{
  "id": 2425699,
  "type": "Feature",
  "properties": {
    "tgn:hierarchy":[
        "tgn:2425699",
        "tgn:1000001",
        "tgn:7012149",
        "tgn:2001909",
        "tgn:7007825",
        "tgn:7029392"
    ],
    "tgn:id":2425699,
    "tgn:name":"Johnston Valley",
    "tgn:placetype":[
        "aat:300008761"
    ]
},
  "bbox": [],
  "geometry": {"coordinates":[-84.45,35.8333],"type":"Point"}
}