{
  "id": 2284611,
  "type": "Feature",
  "properties": {
    "tgn:hierarchy":[
        "tgn:2284611",
        "tgn:1000001",
        "tgn:7012149",
        "tgn:7007157",
        "tgn:1002857",
        "tgn:7029392"
    ],
    "tgn:id":2284611,
    "tgn:name":"Desert Knolls Wash",
    "tgn:placetype":[
        "aat:300008699"
    ]
},
  "bbox": [],
  "geometry": {"coordinates":[-117.2167,34.5167],"type":"Point"}
}