{
  "id": 2566908,
  "type": "Feature",
  "properties": {
    "tgn:hierarchy":[
        "tgn:2566908",
        "tgn:7002659",
        "tgn:1000001",
        "tgn:7012149",
        "tgn:7029392"
    ],
    "tgn:id":2566908,
    "tgn:name":"Panther Creek",
    "tgn:placetype":[
        "aat:300008706"
    ]
},
  "bbox": [],
  "geometry": {"coordinates":[-86.15,31.8167],"type":"Point"}
}