{
  "id": 7341434,
  "type": "Feature",
  "properties": {
    "tgn:hierarchy":[
        "tgn:7341434",
        "tgn:7008911",
        "tgn:1000003",
        "tgn:7002763",
        "tgn:1000095",
        "tgn:7029392"
    ],
    "tgn:id":7341434,
    "tgn:name":"Besapi\u00e9",
    "tgn:placetype":[
        "aat:300008347"
    ]
},
  "bbox": [],
  "geometry": {"coordinates":[-6.633333,43.333333],"type":"Point"}
}