{
  "id": 7178289,
  "type": "Feature",
  "properties": {
    "tgn:hierarchy":[
        "tgn:7178289",
        "tgn:7003669",
        "tgn:1000003",
        "tgn:7000084",
        "tgn:7029392"
    ],
    "tgn:id":7178289,
    "tgn:name":"Hainberg",
    "tgn:placetype":[
        "aat:300008777"
    ]
},
  "bbox": [],
  "geometry": {"coordinates":[11.716667,49.433333],"type":"Point"}
}