{
  "id": 7071843,
  "type": "Feature",
  "properties": {
    "tgn:hierarchy":[
        "tgn:7071843",
        "tgn:1000003",
        "tgn:7003688",
        "tgn:7000084",
        "tgn:7029392"
    ],
    "tgn:id":7071843,
    "tgn:name":"Struvenh\u00fcttener Moor",
    "tgn:placetype":[
        "aat:300386886"
    ]
},
  "bbox": [],
  "geometry": {"coordinates":[10.033333,53.883333],"type":"Point"}
}