{
  "id": 7434181,
  "type": "Feature",
  "properties": {
    "tgn:hierarchy":[
        "tgn:7434181",
        "tgn:1001835",
        "tgn:1000001",
        "tgn:7005560",
        "tgn:7029392"
    ],
    "tgn:id":7434181,
    "tgn:name":"P\u00f3lvora",
    "tgn:placetype":[
        "aat:300008347"
    ]
},
  "bbox": [],
  "geometry": {"coordinates":[-115.190278,32.5475],"type":"Point"}
}