<<<<<<< HEAD
{
  "id": 2258467,
  "type": "Feature",
  "properties": {
    "tgn:hierarchy":[
        "tgn:2258467",
        "tgn:1000001",
        "tgn:7012149",
        "tgn:7007157",
        "tgn:1002656",
        "tgn:7029392"
    ],
    "tgn:id":2258467,
    "tgn:name":"Cotton Lateral",
    "tgn:placetype":[
        "aat:300006075"
    ]
},
  "bbox": [],
  "geometry": {"coordinates":[-120.5667,37.4],"type":"Point"}
}
=======
{"geometry":{"type":"Point","coordinates":[-120.566700,37.400000]},"type":"Feature","properties":{"hierarchy":["tgn:2258467","tgn:1000001","tgn:7012149","tgn:7007157","tgn:1002656","tgn:7029392"],"placetype":["aat:300006075"],"id":2258467,"name:xx":"Cotton Lateral"}}
>>>>>>> 03f74aca74312dbeaf24d7e61306dd6a786dc3d0
