{
  "id": 7049456,
  "type": "Feature",
  "properties": {
    "tgn:hierarchy":[
        "tgn:7049456",
        "tgn:1000003",
        "tgn:7003142",
        "tgn:7003236",
        "tgn:1000080",
        "tgn:7029392"
    ],
    "tgn:id":7049456,
    "tgn:name":"Stazione Genova Cornigliano",
    "tgn:placetype":[
        "aat:300007783"
    ]
},
  "bbox": [],
  "geometry": {"coordinates":[8.866667,44.416667],"type":"Point"}
}