{
  "id": 7126842,
  "type": "Feature",
  "properties": {
    "tgn:hierarchy":[
        "tgn:7126842",
        "tgn:1000003",
        "tgn:7003677",
        "tgn:7000084",
        "tgn:7029392"
    ],
    "tgn:id":7126842,
    "tgn:name":"Oberberg",
    "tgn:placetype":[
        "aat:300008347"
    ]
},
  "bbox": [],
  "geometry": {"coordinates":[7.25,51.083333],"type":"Point"}
}