{
  "id": 1132261,
  "type": "Feature",
  "properties": {
    "tgn:hierarchy":[
        "tgn:1132261",
        "tgn:1000001",
        "tgn:7012149",
        "tgn:7007923",
        "tgn:7029392"
    ],
    "tgn:id":1132261,
    "tgn:name":"Antelope Creek",
    "tgn:placetype":[
        "aat:300008706"
    ]
},
  "bbox": [],
  "geometry": {"coordinates":[-107.95,43.45],"type":"Point"}
}