<<<<<<< HEAD
{
  "id": 7471953,
  "type": "Feature",
  "properties": {
    "tgn:hierarchy":[
        "tgn:7471953",
        "tgn:7001010",
        "tgn:1000004",
        "tgn:1000141",
        "tgn:7029392"
    ],
    "tgn:id":7471953,
    "tgn:name":"Jiali Guoxiao",
    "tgn:placetype":[
        "aat:300006495"
    ]
},
  "bbox": [],
  "geometry": {"coordinates":[121.60891,24.015179],"type":"Point"}
}
=======
{"geometry":{"type":"Point","coordinates":[121.608910,24.015179]},"type":"Feature","properties":{"hierarchy":["tgn:7471953","tgn:7001010","tgn:1000004","tgn:1000141","tgn:7029392"],"placetype":["aat:300006495"],"id":7471953,"name:xx":"Jiali Guoxiao"}}
>>>>>>> 03f74aca74312dbeaf24d7e61306dd6a786dc3d0
