{
  "id": 2213176,
  "type": "Feature",
  "properties": {
    "tgn:hierarchy":[
        "tgn:2213176",
        "tgn:1000001",
        "tgn:7012149",
        "tgn:7007568",
        "tgn:7029392"
    ],
    "tgn:id":2213176,
    "tgn:name":"Cabin Brook",
    "tgn:placetype":[
        "aat:300008699"
    ]
},
  "bbox": [],
  "geometry": {"coordinates":[-75.4167,42.1333],"type":"Point"}
}