<<<<<<< HEAD
{
  "id": 7173398,
  "type": "Feature",
  "properties": {
    "tgn:hierarchy":[
        "tgn:7173398",
        "tgn:1000003",
        "tgn:7003685",
        "tgn:7000084",
        "tgn:7029392"
    ],
    "tgn:id":7173398,
    "tgn:name":"Gro\u00dfrasch\u00fctz",
    "tgn:placetype":[
        "aat:300008347"
    ]
},
  "bbox": [],
  "geometry": {"coordinates":[13.5,51.283333],"type":"Point"}
}
=======
{"geometry":{"type":"Point","coordinates":[13.500000,51.283333]},"type":"Feature","properties":{"hierarchy":["tgn:7173398","tgn:1000003","tgn:7003685","tgn:7000084","tgn:7029392"],"placetype":["aat:300008347"],"id":7173398,"name:xx":"Gro\u00dfrasch\u00fctz"}}
>>>>>>> 03f74aca74312dbeaf24d7e61306dd6a786dc3d0
