{
  "id": 7499071,
  "type": "Feature",
  "properties": {
    "tgn:hierarchy":[
        "tgn:7499071",
        "tgn:1000004",
        "tgn:1000959",
        "tgn:1000141",
        "tgn:7029392"
    ],
    "tgn:id":7499071,
    "tgn:name":"Minsheng Guozhong",
    "tgn:placetype":[
        "aat:300006495"
    ]
},
  "bbox": [],
  "geometry": {"coordinates":[121.56709,25.059793],"type":"Point"}
}