{
  "id": 7225115,
  "type": "Feature",
  "properties": {
    "tgn:hierarchy":[
        "tgn:7225115",
        "tgn:7002751",
        "tgn:7001399",
        "tgn:1000003",
        "tgn:1000074",
        "tgn:7029392"
    ],
    "tgn:id":7225115,
    "tgn:name":"R\u00e9pion, Nis\u00eds",
    "tgn:placetype":[
        "aat:300008791"
    ]
},
  "bbox": [],
  "geometry": {"coordinates":[23.533333,39.15],"type":"Point"}
}