{
  "id": 2289370,
  "type": "Feature",
  "properties": {
    "tgn:hierarchy":[
        "tgn:2289370",
        "tgn:1000001",
        "tgn:7012149",
        "tgn:2000495",
        "tgn:7007250",
        "tgn:7029392"
    ],
    "tgn:id":2289370,
    "tgn:name":"Dixie Creek",
    "tgn:placetype":[
        "aat:300008706"
    ]
},
  "bbox": [],
  "geometry": {"coordinates":[-116.5833,44.4333],"type":"Point"}
}