<<<<<<< HEAD
{
  "id": 2409907,
  "type": "Feature",
  "properties": {
    "tgn:hierarchy":[
        "tgn:2409907",
        "tgn:1000001",
        "tgn:7012149",
        "tgn:2000928",
        "tgn:7007515",
        "tgn:7029392"
    ],
    "tgn:id":2409907,
    "tgn:name":"Imlos Pond",
    "tgn:placetype":[
        "aat:300008680"
    ]
},
  "bbox": [],
  "geometry": {"coordinates":[-69.15,46.1833],"type":"Point"}
}
=======
{"geometry":{"type":"Point","coordinates":[-69.150000,46.183300]},"type":"Feature","properties":{"hierarchy":["tgn:2409907","tgn:1000001","tgn:7012149","tgn:2000928","tgn:7007515","tgn:7029392"],"placetype":["aat:300008680"],"id":2409907,"name:xx":"Imlos Pond"}}
>>>>>>> 03f74aca74312dbeaf24d7e61306dd6a786dc3d0
