{
  "id": 7154804,
  "type": "Feature",
  "properties": {
    "tgn:hierarchy":[
        "tgn:7154804",
        "tgn:1000003",
        "tgn:7003689",
        "tgn:7000084",
        "tgn:7029392"
    ],
    "tgn:id":7154804,
    "tgn:name":"Kirchremda",
    "tgn:placetype":[
        "aat:300008347"
    ]
},
  "bbox": [],
  "geometry": {"coordinates":[11.233333,50.766667],"type":"Point"}
}