{
  "id": 7323166,
  "type": "Feature",
  "properties": {
    "tgn:hierarchy":[
        "tgn:7323166",
        "tgn:7002831",
        "tgn:1000003",
        "tgn:7002786",
        "tgn:1000095",
        "tgn:7029392"
    ],
    "tgn:id":7323166,
    "tgn:name":"Rubiales",
    "tgn:placetype":[
        "aat:300008347"
    ]
},
  "bbox": [],
  "geometry": {"coordinates":[-7.05,42.15],"type":"Point"}
}