{
  "id": 2380484,
  "type": "Feature",
  "properties": {
    "tgn:hierarchy":[
        "tgn:2380484",
        "tgn:1000001",
        "tgn:7012149",
        "tgn:7007157",
        "tgn:7014516",
        "tgn:7029392"
    ],
    "tgn:id":2380484,
    "tgn:name":"Haupt Creek",
    "tgn:placetype":[
        "aat:300008706"
    ]
},
  "bbox": [],
  "geometry": {"coordinates":[-123.25,38.6167],"type":"Point"}
}