{
  "id": 2449865,
  "type": "Feature",
  "properties": {
    "tgn:hierarchy":[
        "tgn:2449865",
        "tgn:1000001",
        "tgn:7016172",
        "tgn:7012149",
        "tgn:2000166",
        "tgn:7029392"
    ],
    "tgn:id":2449865,
    "tgn:name":"Linder Island",
    "tgn:placetype":[
        "aat:300008791"
    ]
},
  "bbox": [],
  "geometry": {"coordinates":[-90.5833,34.95],"type":"Point"}
}