{
  "id": 2491579,
  "type": "Feature",
  "properties": {
    "tgn:hierarchy":[
        "tgn:2491579",
        "tgn:1000001",
        "tgn:1002477",
        "tgn:7012149",
        "tgn:7007240",
        "tgn:7029392"
    ],
    "tgn:id":2491579,
    "tgn:name":"Maple River",
    "tgn:placetype":[
        "aat:300008707"
    ]
},
  "bbox": [],
  "geometry": {"coordinates":[-80.9833,27.25],"type":"Point"}
}