{
  "id": 2213625,
  "type": "Feature",
  "properties": {
    "tgn:hierarchy":[
        "tgn:2213625",
        "tgn:1000001",
        "tgn:7012149",
        "tgn:2001457",
        "tgn:7007566",
        "tgn:7029392"
    ],
    "tgn:id":2213625,
    "tgn:name":"Cabresto Creek",
    "tgn:placetype":[
        "aat:300008706"
    ]
},
  "bbox": [],
  "geometry": {"coordinates":[-105.3167,36.7667],"type":"Point"}
}