{
  "id": 7048329,
  "type": "Feature",
  "properties": {
    "tgn:hierarchy":[
        "tgn:7048329",
        "tgn:1003430",
        "tgn:1000003",
        "tgn:7003126",
        "tgn:1000080",
        "tgn:7029392"
    ],
    "tgn:id":7048329,
    "tgn:name":"Emarese",
    "tgn:placetype":[
        "aat:300008347"
    ]
},
  "bbox": [],
  "geometry": {"coordinates":[7.683333,45.716667],"type":"Point"}
}