<<<<<<< HEAD
{
  "id": 2251563,
  "type": "Feature",
  "properties": {
    "tgn:hierarchy":[
        "tgn:2251563",
        "tgn:1000001",
        "tgn:2000670",
        "tgn:7012149",
        "tgn:7007254",
        "tgn:7029392"
    ],
    "tgn:id":2251563,
    "tgn:name":"Commonwealth",
    "tgn:placetype":[
        "aat:300008347"
    ]
},
  "bbox": [],
  "geometry": {"coordinates":[-94.7333,37.0],"type":"Point"}
}
=======
{"geometry":{"type":"Point","coordinates":[-94.733300,37.000000]},"type":"Feature","properties":{"hierarchy":["tgn:2251563","tgn:1000001","tgn:2000670","tgn:7012149","tgn:7007254","tgn:7029392"],"placetype":["aat:300008347"],"id":2251563,"name:xx":"Commonwealth"}}
>>>>>>> 03f74aca74312dbeaf24d7e61306dd6a786dc3d0
