<<<<<<< HEAD
{
  "id": 2400214,
  "type": "Feature",
  "properties": {
    "tgn:hierarchy":[
        "tgn:2400214",
        "tgn:1000001",
        "tgn:7012149",
        "tgn:7014510",
        "tgn:7007920",
        "tgn:7029392"
    ],
    "tgn:id":2400214,
    "tgn:name":"Horse Creek",
    "tgn:placetype":[
        "aat:300008706"
    ]
},
  "bbox": [],
  "geometry": {"coordinates":[-121.2,48.3333],"type":"Point"}
}
=======
{"geometry":{"type":"Point","coordinates":[-121.200000,48.333300]},"type":"Feature","properties":{"hierarchy":["tgn:2400214","tgn:1000001","tgn:7012149","tgn:7014510","tgn:7007920","tgn:7029392"],"placetype":["aat:300008706"],"id":2400214,"name:xx":"Horse Creek"}}
>>>>>>> 03f74aca74312dbeaf24d7e61306dd6a786dc3d0
