{
  "id": 2247976,
  "type": "Feature",
  "properties": {
    "tgn:hierarchy":[
        "tgn:2247976",
        "tgn:1000001",
        "tgn:2000460",
        "tgn:7012149",
        "tgn:7007250",
        "tgn:7029392"
    ],
    "tgn:id":2247976,
    "tgn:name":"Colburn Lake",
    "tgn:placetype":[
        "aat:300008680"
    ]
},
  "bbox": [],
  "geometry": {"coordinates":[-116.6167,48.3667],"type":"Point"}
}