{
  "id": 1054082,
  "type": "Feature",
  "properties": {
    "tgn:hierarchy":[
        "tgn:1054082",
        "tgn:1000004",
        "tgn:1003418",
        "tgn:7018214",
        "tgn:7002435",
        "tgn:7029392"
    ],
    "tgn:id":1054082,
    "tgn:name":"Gorelki",
    "tgn:placetype":[
        "aat:300008347"
    ]
},
  "bbox": [],
  "geometry": {"coordinates":[37.6333,54.25],"type":"Point"}
}