{
  "id": 7268669,
  "type": "Feature",
  "properties": {
    "tgn:concordances":{
        "gn:id":"2749920"
    },
    "tgn:hierarchy":[
        "tgn:7268669",
        "tgn:1000003",
        "tgn:7006951",
        "tgn:7016845",
        "tgn:7029392"
    ],
    "tgn:id":7268669,
    "tgn:name:nl":"Noordermeer",
    "tgn:placetype":[
        "aat:300008347"
    ]
},
  "bbox": [],
  "geometry": {"coordinates":[4.983333,52.683333],"type":"Point"}
}