{
  "id": 7556669,
  "type": "Feature",
  "properties": {
    "tgn:hierarchy":[
        "tgn:7556669",
        "tgn:1000004",
        "tgn:7000198",
        "tgn:1001895",
        "tgn:7029392"
    ],
    "tgn:id":7556669,
    "tgn:name:en":"Pimpalner",
    "tgn:placetype":[
        "aat:300008347"
    ]
},
  "bbox": [],
  "geometry": {"coordinates":[75.285821,18.043168],"type":"Point"}
}