{
  "id": 1086585,
  "type": "Feature",
  "properties": {
    "tgn:hierarchy":[
        "tgn:1086585",
        "tgn:1001232",
        "tgn:1000004",
        "tgn:7018450",
        "tgn:1000144",
        "tgn:7029392"
    ],
    "tgn:id":1086585,
    "tgn:name":"Kesan",
    "tgn:placetype":[
        "aat:300008347"
    ]
},
  "bbox": [],
  "geometry": {"coordinates":[26.6167,40.8667],"type":"Point"}
}