{
  "id": 7066879,
  "type": "Feature",
  "properties": {
    "tgn:hierarchy":[
        "tgn:7066879",
        "tgn:7003669",
        "tgn:1000003",
        "tgn:7000084",
        "tgn:7029392"
    ],
    "tgn:id":7066879,
    "tgn:name":"Still-Bach",
    "tgn:placetype":[
        "aat:300008699"
    ]
},
  "bbox": [],
  "geometry": {"coordinates":[12.766667,48.033333],"type":"Point"}
}