{
  "id": 7473195,
  "type": "Feature",
  "properties": {
    "tgn:hierarchy":[
        "tgn:7473195",
        "tgn:1000004",
        "tgn:7471332",
        "tgn:1000141",
        "tgn:7029392"
    ],
    "tgn:id":7473195,
    "tgn:name":"Yebakan Xi",
    "tgn:placetype":[
        "aat:300008699"
    ]
},
  "bbox": [],
  "geometry": {"coordinates":[121.108611,24.548056],"type":"Point"}
}