{
  "id": 7480974,
  "type": "Feature",
  "properties": {
    "tgn:hierarchy":[
        "tgn:7480974",
        "tgn:7001010",
        "tgn:1000004",
        "tgn:1000141",
        "tgn:7029392"
    ],
    "tgn:id":7480974,
    "tgn:name":"Xinyi Guoxiao",
    "tgn:placetype":[
        "aat:300006495"
    ]
},
  "bbox": [],
  "geometry": {"coordinates":[121.606389,23.971111],"type":"Point"}
}