<<<<<<< HEAD
{
  "id": 7485169,
  "type": "Feature",
  "properties": {
    "tgn:hierarchy":[
        "tgn:7485169",
        "tgn:1000004",
        "tgn:7491221",
        "tgn:1000141",
        "tgn:7029392"
    ],
    "tgn:id":7485169,
    "tgn:name":"Zhongxing Erhao Qiao",
    "tgn:placetype":[
        "aat:300007836"
    ]
},
  "bbox": [],
  "geometry": {"coordinates":[121.271667,22.990833],"type":"Point"}
}
=======
{"geometry":{"type":"Point","coordinates":[121.271667,22.990833]},"type":"Feature","properties":{"hierarchy":["tgn:7485169","tgn:1000004","tgn:7491221","tgn:1000141","tgn:7029392"],"placetype":["aat:300007836"],"id":7485169,"name:xx":"Zhongxing Erhao Qiao"}}
>>>>>>> 03f74aca74312dbeaf24d7e61306dd6a786dc3d0
