{
  "id": 7583630,
  "type": "Feature",
  "properties": {
    "tgn:hierarchy":[
        "tgn:7583630",
        "tgn:1000004",
        "tgn:7000198",
        "tgn:7016883",
        "tgn:7029392"
    ],
    "tgn:id":7583630,
    "tgn:name:en":"Bar\u012bma",
    "tgn:placetype":[
        "aat:300008347"
    ]
},
  "bbox": [],
  "geometry": {"coordinates":[76.147975,30.545655],"type":"Point"}
}