{
  "id": 2216790,
  "type": "Feature",
  "properties": {
    "tgn:hierarchy":[
        "tgn:2216790",
        "tgn:1000001",
        "tgn:2001592",
        "tgn:7012149",
        "tgn:7007705",
        "tgn:7029392"
    ],
    "tgn:id":2216790,
    "tgn:name":"Camp Grafton",
    "tgn:placetype":[
        "aat:300008347"
    ]
},
  "bbox": [],
  "geometry": {"coordinates":[-98.9167,48.05],"type":"Point"}
}