{
  "id": 7276637,
  "type": "Feature",
  "properties": {
    "tgn:hierarchy":[
        "tgn:7276637",
        "tgn:1001630",
        "tgn:1000049",
        "tgn:1000002",
        "tgn:7029392"
    ],
    "tgn:id":7276637,
    "tgn:name":"Iglesia Colorada",
    "tgn:placetype":[
        "aat:300008347"
    ]
},
  "bbox": [],
  "geometry": {"coordinates":[-69.876667,-28.152222],"type":"Point"}
}