{
  "id": 7564399,
  "type": "Feature",
  "properties": {
    "tgn:hierarchy":[
        "tgn:7564399",
        "tgn:1000004",
        "tgn:7000198",
        "tgn:7016722",
        "tgn:7029392"
    ],
    "tgn:id":7564399,
    "tgn:name:en":"Ratn\u0101pur",
    "tgn:placetype":[
        "aat:300008347"
    ]
},
  "bbox": [],
  "geometry": {"coordinates":[79.724699,26.97192],"type":"Point"}
}