<<<<<<< HEAD
{
  "id": 2402839,
  "type": "Feature",
  "properties": {
    "tgn:hierarchy":[
        "tgn:2402839",
        "tgn:1000001",
        "tgn:7012149",
        "tgn:2001889",
        "tgn:7007825",
        "tgn:7029392"
    ],
    "tgn:id":2402839,
    "tgn:name":"Hotchkiss Creek",
    "tgn:placetype":[
        "aat:300008706"
    ]
},
  "bbox": [],
  "geometry": {"coordinates":[-84.3,35.8167],"type":"Point"}
}
=======
{"geometry":{"type":"Point","coordinates":[-84.300000,35.816700]},"type":"Feature","properties":{"hierarchy":["tgn:2402839","tgn:1000001","tgn:7012149","tgn:2001889","tgn:7007825","tgn:7029392"],"placetype":["aat:300008706"],"id":2402839,"name:xx":"Hotchkiss Creek"}}
>>>>>>> 03f74aca74312dbeaf24d7e61306dd6a786dc3d0
