{
  "id": 1068737,
  "type": "Feature",
  "properties": {
    "tgn:hierarchy":[
        "tgn:1068737",
        "tgn:1000004",
        "tgn:1001678",
        "tgn:1000111",
        "tgn:7029392"
    ],
    "tgn:id":1068737,
    "tgn:name":"Hexian",
    "tgn:placetype":[
        "aat:300008347"
    ]
},
  "bbox": [],
  "geometry": {"coordinates":[111.7167,24.25],"type":"Point"}
}