<<<<<<< HEAD
{
  "id": 7023073,
  "type": "Feature",
  "properties": {
    "tgn:hierarchy":[
        "tgn:7023073",
        "tgn:1000001",
        "tgn:7012149",
        "tgn:7029392"
    ],
    "tgn:id":7023073,
    "tgn:name":"Harmony Creek",
    "tgn:placetype":[
        "aat:300008706"
    ]
},
  "bbox": [],
  "geometry": {"coordinates":[-111.05,42.7167],"type":"Point"}
}
=======
{"geometry":{"type":"Point","coordinates":[-111.050000,42.716700]},"type":"Feature","properties":{"hierarchy":["tgn:7023073","tgn:1000001","tgn:7012149","tgn:7029392"],"placetype":["aat:300008706"],"id":7023073,"name:xx":"Harmony Creek"}}
>>>>>>> 03f74aca74312dbeaf24d7e61306dd6a786dc3d0
