{
  "id": 7249452,
  "type": "Feature",
  "properties": {
    "tgn:hierarchy":[
        "tgn:7249452",
        "tgn:7003461",
        "tgn:1000003",
        "tgn:1000063",
        "tgn:7018236",
        "tgn:7029392"
    ],
    "tgn:id":7249452,
    "tgn:name":"Nieuwenhoven",
    "tgn:placetype":[
        "aat:300005567"
    ]
},
  "bbox": [],
  "geometry": {"coordinates":[5.209089,50.856419],"type":"Point"}
}