{
  "id": 7073102,
  "type": "Feature",
  "properties": {
    "tgn:hierarchy":[
        "tgn:7073102",
        "tgn:1000003",
        "tgn:7000094",
        "tgn:7000084",
        "tgn:7029392"
    ],
    "tgn:id":7073102,
    "tgn:name":"Tannenhof",
    "tgn:placetype":[
        "aat:300008347"
    ]
},
  "bbox": [],
  "geometry": {"coordinates":[11.983333,53.516667],"type":"Point"}
}