<<<<<<< HEAD
{
  "id": 2338093,
  "type": "Feature",
  "properties": {
    "tgn:hierarchy":[
        "tgn:2338093",
        "tgn:1000001",
        "tgn:7012149",
        "tgn:2002342",
        "tgn:7007922",
        "tgn:7029392"
    ],
    "tgn:id":2338093,
    "tgn:name":"Fox Lake",
    "tgn:placetype":[
        "aat:300008680"
    ]
},
  "bbox": [],
  "geometry": {"coordinates":[-89.5667,45.5667],"type":"Point"}
}
=======
{"geometry":{"type":"Point","coordinates":[-89.566700,45.566700]},"type":"Feature","properties":{"hierarchy":["tgn:2338093","tgn:1000001","tgn:7012149","tgn:2002342","tgn:7007922","tgn:7029392"],"placetype":["aat:300008680"],"id":2338093,"name:xx":"Fox Lake"}}
>>>>>>> 03f74aca74312dbeaf24d7e61306dd6a786dc3d0
