{
  "id": 2076545,
  "type": "Feature",
  "properties": {
    "tgn:hierarchy":[
        "tgn:2076545",
        "tgn:1000001",
        "tgn:7012149",
        "tgn:2001501",
        "tgn:7007709",
        "tgn:7029392"
    ],
    "tgn:id":2076545,
    "tgn:name":"Scotland Neck",
    "tgn:placetype":[
        "aat:300008347"
    ]
},
  "bbox": [],
  "geometry": {"coordinates":[-77.4167,36.1167],"type":"Point"}
}