{
  "id": 1010510,
  "type": "Feature",
  "properties": {
    "tgn:hierarchy":[
        "tgn:1010510",
        "tgn:7001242",
        "tgn:1002070",
        "tgn:1000205",
        "tgn:7029392"
    ],
    "tgn:id":1010510,
    "tgn:name":"Blanc, Cap",
    "tgn:placetype":[
        "aat:300008850"
    ]
},
  "bbox": [],
  "geometry": {"coordinates":[9.8667,37.3333],"type":"Point"}
}