{
  "id": 2348438,
  "type": "Feature",
  "properties": {
    "tgn:hierarchy":[
        "tgn:2348438",
        "tgn:1000001",
        "tgn:7012149",
        "tgn:1002521",
        "tgn:7007920",
        "tgn:7029392"
    ],
    "tgn:id":2348438,
    "tgn:name":"Giants Graveyard",
    "tgn:placetype":[
        "aat:300008791"
    ]
},
  "bbox": [],
  "geometry": {"coordinates":[-124.55,47.85],"type":"Point"}
}