<<<<<<< HEAD
{
  "id": 7058635,
  "type": "Feature",
  "properties": {
    "tgn:hierarchy":[
        "tgn:7058635",
        "tgn:1001724",
        "tgn:1000003",
        "tgn:7003121",
        "tgn:1000080",
        "tgn:7029392"
    ],
    "tgn:id":7058635,
    "tgn:name":"Altana, Riu",
    "tgn:placetype":[
        "aat:300008699"
    ]
},
  "bbox": [],
  "geometry": {"coordinates":[9.4,40.616667],"type":"Point"}
}
=======
{"geometry":{"type":"Point","coordinates":[9.400000,40.616667]},"type":"Feature","properties":{"hierarchy":["tgn:7058635","tgn:1001724","tgn:1000003","tgn:7003121","tgn:1000080","tgn:7029392"],"placetype":["aat:300008699"],"id":7058635,"name:xx":"Altana, Riu"}}
>>>>>>> 03f74aca74312dbeaf24d7e61306dd6a786dc3d0
