{
  "id": 2720967,
  "type": "Feature",
  "properties": {
    "tgn:hierarchy":[
        "tgn:2720967",
        "tgn:1000001",
        "tgn:7012149",
        "tgn:2001930",
        "tgn:7007825",
        "tgn:7029392"
    ],
    "tgn:id":2720967,
    "tgn:name":"Tidwell Branch",
    "tgn:placetype":[
        "aat:300008699"
    ]
},
  "bbox": [],
  "geometry": {"coordinates":[-87.1667,35.9167],"type":"Point"}
}