{
  "id": 7562437,
  "type": "Feature",
  "properties": {
    "tgn:hierarchy":[
        "tgn:7562437",
        "tgn:1000004",
        "tgn:7000198",
        "tgn:7016722",
        "tgn:7029392"
    ],
    "tgn:id":7562437,
    "tgn:name:en":"Nagaria Hard\u0101s",
    "tgn:placetype":[
        "aat:300008347"
    ]
},
  "bbox": [],
  "geometry": {"coordinates":[79.277736,27.91607],"type":"Point"}
}