<<<<<<< HEAD
{
  "id": 7366067,
  "type": "Feature",
  "properties": {
    "tgn:hierarchy":[
        "tgn:7366067",
        "tgn:7005581",
        "tgn:1000001",
        "tgn:7005560",
        "tgn:7029392"
    ],
    "tgn:id":7366067,
    "tgn:name":"Gallinas, Puerto de las",
    "tgn:placetype":[
        "aat:300259572"
    ]
},
  "bbox": [],
  "geometry": {"coordinates":[-105.166667,28.7],"type":"Point"}
}
=======
{"geometry":{"type":"Point","coordinates":[-105.166667,28.700000]},"type":"Feature","properties":{"hierarchy":["tgn:7366067","tgn:7005581","tgn:1000001","tgn:7005560","tgn:7029392"],"placetype":["aat:300259572"],"id":7366067,"name:xx":"Gallinas, Puerto de las"}}
>>>>>>> 03f74aca74312dbeaf24d7e61306dd6a786dc3d0
