{
  "id": 5003073,
  "type": "Feature",
  "properties": {
    "tgn:hierarchy":[
        "tgn:5003073",
        "tgn:7003170",
        "tgn:1000003",
        "tgn:7003125",
        "tgn:1000080",
        "tgn:7029392"
    ],
    "tgn:id":5003073,
    "tgn:name":"Campi",
    "tgn:placetype":[
        "aat:300008347"
    ]
},
  "bbox": [],
  "geometry": {"coordinates":[13.083333,42.85],"type":"Point"}
}