<<<<<<< HEAD
{
  "id": 2255380,
  "type": "Feature",
  "properties": {
    "tgn:hierarchy":[
        "tgn:2255380",
        "tgn:1000001",
        "tgn:7012149",
        "tgn:2000415",
        "tgn:7007248",
        "tgn:7029392"
    ],
    "tgn:id":2255380,
    "tgn:name":"Cooperville",
    "tgn:placetype":[
        "aat:300008347"
    ]
},
  "bbox": [],
  "geometry": {"coordinates":[-81.7,32.5833],"type":"Point"}
}
=======
{"geometry":{"type":"Point","coordinates":[-81.700000,32.583300]},"type":"Feature","properties":{"hierarchy":["tgn:2255380","tgn:1000001","tgn:7012149","tgn:2000415","tgn:7007248","tgn:7029392"],"placetype":["aat:300008347"],"id":2255380,"name:xx":"Cooperville"}}
>>>>>>> 03f74aca74312dbeaf24d7e61306dd6a786dc3d0
