<<<<<<< HEAD
{
  "id": 2334612,
  "type": "Feature",
  "properties": {
    "tgn:hierarchy":[
        "tgn:2334612",
        "tgn:1000001",
        "tgn:2002317",
        "tgn:7012149",
        "tgn:7007922",
        "tgn:7029392"
    ],
    "tgn:id":2334612,
    "tgn:name":"Forestville Flowage",
    "tgn:placetype":[
        "aat:300006191"
    ]
},
  "bbox": [],
  "geometry": {"coordinates":[-87.4833,44.6833],"type":"Point"}
}
=======
{"geometry":{"type":"Point","coordinates":[-87.483300,44.683300]},"type":"Feature","properties":{"hierarchy":["tgn:2334612","tgn:1000001","tgn:2002317","tgn:7012149","tgn:7007922","tgn:7029392"],"placetype":["aat:300006191"],"id":2334612,"name:xx":"Forestville Flowage"}}
>>>>>>> 03f74aca74312dbeaf24d7e61306dd6a786dc3d0
