{
  "id": 2685464,
  "type": "Feature",
  "properties": {
    "tgn:hierarchy":[
        "tgn:2685464",
        "tgn:1000001",
        "tgn:7012149",
        "tgn:7014589",
        "tgn:7007515",
        "tgn:7029392"
    ],
    "tgn:id":2685464,
    "tgn:name":"Sprague Neck",
    "tgn:placetype":[
        "aat:300008850"
    ]
},
  "bbox": [],
  "geometry": {"coordinates":[-67.3167,44.65],"type":"Point"}
}