{
  "id": 2129973,
  "type": "Feature",
  "properties": {
    "tgn:hierarchy":[
        "tgn:2129973",
        "tgn:1000001",
        "tgn:7012149",
        "tgn:2001716",
        "tgn:7007708",
        "tgn:7029392"
    ],
    "tgn:id":2129973,
    "tgn:name":"Allen Creek",
    "tgn:placetype":[
        "aat:300008706"
    ]
},
  "bbox": [],
  "geometry": {"coordinates":[-122.8667,43.65],"type":"Point"}
}