{
  "id": 2509927,
  "type": "Feature",
  "properties": {
    "tgn:hierarchy":[
        "tgn:2509927",
        "tgn:1000001",
        "tgn:7012149",
        "tgn:2001532",
        "tgn:7007709",
        "tgn:7029392"
    ],
    "tgn:id":2509927,
    "tgn:name":"Middle Mountain",
    "tgn:placetype":[
        "aat:300008798"
    ]
},
  "bbox": [],
  "geometry": {"coordinates":[-79.75,35.6333],"type":"Point"}
}