{
  "id": 2348854,
  "type": "Feature",
  "properties": {
    "tgn:hierarchy":[
        "tgn:2348854",
        "tgn:1000001",
        "tgn:7012149",
        "tgn:2001515",
        "tgn:7007709",
        "tgn:7029392"
    ],
    "tgn:id":2348854,
    "tgn:name":"Gibson Ridge",
    "tgn:placetype":[
        "aat:300266640"
    ]
},
  "bbox": [],
  "geometry": {"coordinates":[-83.4333,35.1667],"type":"Point"}
}