{
  "id": 2423050,
  "type": "Feature",
  "properties": {
    "tgn:hierarchy":[
        "tgn:2423050",
        "tgn:1000001",
        "tgn:7012149",
        "tgn:2000208",
        "tgn:7007158",
        "tgn:7029392"
    ],
    "tgn:id":2423050,
    "tgn:name":"Joe Redd Reservoir",
    "tgn:placetype":[
        "aat:300006191"
    ]
},
  "bbox": [],
  "geometry": {"coordinates":[-108.2333,37.7667],"type":"Point"}
}