{
  "id": 2659551,
  "type": "Feature",
  "properties": {
    "tgn:hierarchy":[
        "tgn:2659551",
        "tgn:1000001",
        "tgn:7012149",
        "tgn:1002751",
        "tgn:7007568",
        "tgn:7029392"
    ],
    "tgn:id":2659551,
    "tgn:name":"Shingle Kill",
    "tgn:placetype":[
        "aat:300008699"
    ]
},
  "bbox": [],
  "geometry": {"coordinates":[-74.7167,41.45],"type":"Point"}
}