{
  "id": 7044711,
  "type": "Feature",
  "properties": {
    "tgn:hierarchy":[
        "tgn:7044711",
        "tgn:7003006",
        "tgn:1000003",
        "tgn:7002997",
        "tgn:1000080",
        "tgn:7029392"
    ],
    "tgn:id":7044711,
    "tgn:name":"Cortellazzo, Porto di",
    "tgn:placetype":[
        "aat:300185707"
    ]
},
  "bbox": [],
  "geometry": {"coordinates":[12.729167,45.532778],"type":"Point"}
}