{
  "id": 1048438,
  "type": "Feature",
  "properties": {
    "tgn:hierarchy":[
        "tgn:1048438",
        "tgn:7003646",
        "tgn:1000003",
        "tgn:1000088",
        "tgn:7029392"
    ],
    "tgn:id":1048438,
    "tgn:name":"\u00d8ystese",
    "tgn:placetype":[
        "aat:300008347"
    ]
},
  "bbox": [],
  "geometry": {"coordinates":[6.2167,60.3833],"type":"Point"}
}