{
  "id": 2296799,
  "type": "Feature",
  "properties": {
    "tgn:hierarchy":[
        "tgn:2296799",
        "tgn:1000001",
        "tgn:2000699",
        "tgn:7012149",
        "tgn:7007254",
        "tgn:7029392"
    ],
    "tgn:id":2296799,
    "tgn:name":"Dry Creek",
    "tgn:placetype":[
        "aat:300008706"
    ]
},
  "bbox": [],
  "geometry": {"coordinates":[-97.4167,38.15],"type":"Point"}
}