{
  "id": 7505138,
  "type": "Feature",
  "properties": {
    "tgn:hierarchy":[
        "tgn:7505138",
        "tgn:1009227",
        "tgn:1000226",
        "tgn:7016822",
        "tgn:1000006",
        "tgn:7029392"
    ],
    "tgn:id":7505138,
    "tgn:name:en":"Duris Point",
    "tgn:placetype":[
        "aat:300386846"
    ]
},
  "bbox": [],
  "geometry": {"coordinates":[169.136111,-52.556667],"type":"Point"}
}