{
  "id": 7244201,
  "type": "Feature",
  "properties": {
    "tgn:hierarchy":[
        "tgn:7244201",
        "tgn:7003457",
        "tgn:1000003",
        "tgn:1000063",
        "tgn:7018236",
        "tgn:7029392"
    ],
    "tgn:id":7244201,
    "tgn:name":"Kamperstraat",
    "tgn:placetype":[
        "aat:300008347"
    ]
},
  "bbox": [],
  "geometry": {"coordinates":[3.766667,50.85],"type":"Point"}
}