{
  "id": 7237579,
  "type": "Feature",
  "properties": {
    "tgn:hierarchy":[
        "tgn:7237579",
        "tgn:7003456",
        "tgn:1000003",
        "tgn:1000063",
        "tgn:7018236",
        "tgn:7029392"
    ],
    "tgn:id":7237579,
    "tgn:name":"Herenthout",
    "tgn:placetype":[
        "aat:300008347"
    ]
},
  "bbox": [],
  "geometry": {"coordinates":[4.755722,51.140101],"type":"Point"}
}