{
  "id": 2377060,
  "type": "Feature",
  "properties": {
    "tgn:hierarchy":[
        "tgn:2377060",
        "tgn:1000001",
        "tgn:7012149",
        "tgn:2000837",
        "tgn:7007255",
        "tgn:7029392"
    ],
    "tgn:id":2377060,
    "tgn:name":"Harless Creek",
    "tgn:placetype":[
        "aat:300008706"
    ]
},
  "bbox": [],
  "geometry": {"coordinates":[-82.3667,37.3833],"type":"Point"}
}