{
  "id": 2697992,
  "type": "Feature",
  "properties": {
    "tgn:hierarchy":[
        "tgn:2697992",
        "tgn:1000001",
        "tgn:7012149",
        "tgn:2000213",
        "tgn:7007158",
        "tgn:7029392"
    ],
    "tgn:id":2697992,
    "tgn:name":"Stout Creek Lakes",
    "tgn:placetype":[
        "aat:300008680"
    ]
},
  "bbox": [],
  "geometry": {"coordinates":[-105.8833,37.35],"type":"Point"}
}