{
  "id": 2254083,
  "type": "Feature",
  "properties": {
    "tgn:hierarchy":[
        "tgn:2254083",
        "tgn:7002659",
        "tgn:1000001",
        "tgn:7012149",
        "tgn:7029392"
    ],
    "tgn:id":2254083,
    "tgn:name":"Cooley Creek",
    "tgn:placetype":[
        "aat:300008706"
    ]
},
  "bbox": [],
  "geometry": {"coordinates":[-87.0667,33.2833],"type":"Point"}
}