{
  "id": 2658401,
  "type": "Feature",
  "properties": {
    "tgn:hierarchy":[
        "tgn:2658401",
        "tgn:2000919",
        "tgn:1000001",
        "tgn:7012149",
        "tgn:7007515",
        "tgn:7029392"
    ],
    "tgn:id":2658401,
    "tgn:name":"Shepherd Brook Mountain",
    "tgn:placetype":[
        "aat:300008798"
    ]
},
  "bbox": [],
  "geometry": {"coordinates":[-69.25,46.6833],"type":"Point"}
}