{
  "id": 2151074,
  "type": "Feature",
  "properties": {
    "tgn:hierarchy":[
        "tgn:2151074",
        "tgn:1000001",
        "tgn:2002323",
        "tgn:7012149",
        "tgn:7007922",
        "tgn:7029392"
    ],
    "tgn:id":2151074,
    "tgn:name":"Bastile Lake",
    "tgn:placetype":[
        "aat:300008680"
    ]
},
  "bbox": [],
  "geometry": {"coordinates":[-88.7333,45.8167],"type":"Point"}
}