<<<<<<< HEAD
{
  "id": 2151074,
  "type": "Feature",
  "properties": {
    "tgn:hierarchy":[
        "tgn:2151074",
        "tgn:1000001",
        "tgn:2002323",
        "tgn:7012149",
        "tgn:7007922",
        "tgn:7029392"
    ],
    "tgn:id":2151074,
    "tgn:name":"Bastile Lake",
    "tgn:placetype":[
        "aat:300008680"
    ]
},
  "bbox": [],
  "geometry": {"coordinates":[-88.7333,45.8167],"type":"Point"}
}
=======
{"geometry":{"type":"Point","coordinates":[-88.733300,45.816700]},"type":"Feature","properties":{"hierarchy":["tgn:2151074","tgn:1000001","tgn:2002323","tgn:7012149","tgn:7007922","tgn:7029392"],"placetype":["aat:300008680"],"id":2151074,"name:xx":"Bastile Lake"}}
>>>>>>> 03f74aca74312dbeaf24d7e61306dd6a786dc3d0
