{
  "id": 2673929,
  "type": "Feature",
  "properties": {
    "tgn:hierarchy":[
        "tgn:2673929",
        "tgn:1000001",
        "tgn:7012149",
        "tgn:2001277",
        "tgn:7007524",
        "tgn:7029392"
    ],
    "tgn:id":2673929,
    "tgn:name":"Snow Moon Lake",
    "tgn:placetype":[
        "aat:300008680"
    ]
},
  "bbox": [],
  "geometry": {"coordinates":[-113.6333,48.7667],"type":"Point"}
}