{
  "id": 7503483,
  "type": "Feature",
  "properties": {
    "tgn:hierarchy":[
        "tgn:7503483",
        "tgn:7001004",
        "tgn:1000004",
        "tgn:1000141",
        "tgn:7029392"
    ],
    "tgn:id":7503483,
    "tgn:name":"Xidi",
    "tgn:placetype":[
        "aat:300008347"
    ]
},
  "bbox": [],
  "geometry": {"coordinates":[120.435556,22.982222],"type":"Point"}
}