{
  "id": 2656605,
  "type": "Feature",
  "properties": {
    "tgn:hierarchy":[
        "tgn:2656605",
        "tgn:1000001",
        "tgn:2001413",
        "tgn:7012149",
        "tgn:7007526",
        "tgn:7029392"
    ],
    "tgn:id":2656605,
    "tgn:name":"Sheep Corral Spring",
    "tgn:placetype":[
        "aat:300008697"
    ]
},
  "bbox": [],
  "geometry": {"coordinates":[-116.55,39.85],"type":"Point"}
}