{
  "id": 2764527,
  "type": "Feature",
  "properties": {
    "tgn:hierarchy":[
        "tgn:2764527",
        "tgn:7013349",
        "tgn:1000001",
        "tgn:7012149",
        "tgn:7007708",
        "tgn:7029392"
    ],
    "tgn:id":2764527,
    "tgn:name":"Whipple Gulch",
    "tgn:placetype":[
        "aat:300008761"
    ]
},
  "bbox": [],
  "geometry": {"coordinates":[-117.9667,44.5833],"type":"Point"}
}