{
  "id": 7577754,
  "type": "Feature",
  "properties": {
    "tgn:hierarchy":[
        "tgn:7577754",
        "tgn:1000004",
        "tgn:7000198",
        "tgn:1001895",
        "tgn:7029392"
    ],
    "tgn:id":7577754,
    "tgn:name:en":"Kas\u0101ra",
    "tgn:placetype":[
        "aat:300008347"
    ]
},
  "bbox": [],
  "geometry": {"coordinates":[73.483333,19.633333],"type":"Point"}
}