{
  "id": 7588614,
  "type": "Feature",
  "properties": {
    "tgn:hierarchy":[
        "tgn:7588614",
        "tgn:1000004",
        "tgn:7000198",
        "tgn:1001977",
        "tgn:7029392"
    ],
    "tgn:id":7588614,
    "tgn:name:en":"G\u0101bb\u0101ria",
    "tgn:placetype":[
        "aat:300008347"
    ]
},
  "bbox": [],
  "geometry": {"coordinates":[88.808946,22.299482],"type":"Point"}
}