{
  "id": 7352452,
  "type": "Feature",
  "properties": {
    "tgn:hierarchy":[
        "tgn:7352452",
        "tgn:7005587",
        "tgn:1000001",
        "tgn:7005560",
        "tgn:7029392"
    ],
    "tgn:id":7352452,
    "tgn:name":"Atecoxco",
    "tgn:placetype":[
        "aat:300008347"
    ]
},
  "bbox": [],
  "geometry": {"coordinates":[-98.466667,20.816667],"type":"Point"}
}