{
  "id": 7341168,
  "type": "Feature",
  "properties": {
    "tgn:hierarchy":[
        "tgn:7341168",
        "tgn:7002759",
        "tgn:7008909",
        "tgn:1000003",
        "tgn:1000095",
        "tgn:7029392"
    ],
    "tgn:id":7341168,
    "tgn:name":"Broto, Valle de",
    "tgn:placetype":[
        "aat:300008761"
    ]
},
  "bbox": [],
  "geometry": {"coordinates":[-0.116667,42.566667],"type":"Point"}
}