{
  "id": 7471703,
  "type": "Feature",
  "properties": {
    "tgn:hierarchy":[
        "tgn:7471703",
        "tgn:1000004",
        "tgn:7471332",
        "tgn:1000141",
        "tgn:7029392"
    ],
    "tgn:id":7471703,
    "tgn:name":"Xiahengkeng",
    "tgn:placetype":[
        "aat:300008347"
    ]
},
  "bbox": [],
  "geometry": {"coordinates":[121.125833,24.806111],"type":"Point"}
}