{
  "id": 7573183,
  "type": "Feature",
  "properties": {
    "tgn:hierarchy":[
        "tgn:7573183",
        "tgn:1000004",
        "tgn:1001871",
        "tgn:7000198",
        "tgn:7029392"
    ],
    "tgn:id":7573183,
    "tgn:name:en":"Jui",
    "tgn:placetype":[
        "aat:300008347"
    ]
},
  "bbox": [],
  "geometry": {"coordinates":[75.95,28.65],"type":"Point"}
}