<<<<<<< HEAD
{
  "id": 7174134,
  "type": "Feature",
  "properties": {
    "tgn:hierarchy":[
        "tgn:7174134",
        "tgn:7000096",
        "tgn:1000003",
        "tgn:7000084",
        "tgn:7029392"
    ],
    "tgn:id":7174134,
    "tgn:name":"Gro\u00dfer Mewenbruch",
    "tgn:placetype":[
        "aat:300008905"
    ]
},
  "bbox": [],
  "geometry": {"coordinates":[13.366667,53.166667],"type":"Point"}
}
=======
{"geometry":{"type":"Point","coordinates":[13.366667,53.166667]},"type":"Feature","properties":{"hierarchy":["tgn:7174134","tgn:7000096","tgn:1000003","tgn:7000084","tgn:7029392"],"placetype":["aat:300008905"],"id":7174134,"name:xx":"Gro\u00dfer Mewenbruch"}}
>>>>>>> 03f74aca74312dbeaf24d7e61306dd6a786dc3d0
