{
  "id": 7449137,
  "type": "Feature",
  "properties": {
    "tgn:hierarchy":[
        "tgn:7449137",
        "tgn:7002445",
        "tgn:1000003",
        "tgn:5000227",
        "tgn:7008591",
        "tgn:7029392"
    ],
    "tgn:id":7449137,
    "tgn:name:en":"Sedgeberrow",
    "tgn:placetype":[
        "aat:300008347"
    ]
},
  "bbox": [],
  "geometry": {"coordinates":[-1.966667,52.033333],"type":"Point"}
}