{
  "id": 1094148,
  "type": "Feature",
  "properties": {
    "tgn:hierarchy":[
        "tgn:1094148",
        "tgn:7001242",
        "tgn:1001071",
        "tgn:1000201",
        "tgn:7029392"
    ],
    "tgn:id":1094148,
    "tgn:name":"El Geteina",
    "tgn:placetype":[
        "aat:300008347"
    ]
},
  "bbox": [],
  "geometry": {"coordinates":[32.3667,14.8333],"type":"Point"}
}