{
  "id": 2656331,
  "type": "Feature",
  "properties": {
    "tgn:hierarchy":[
        "tgn:2656331",
        "tgn:1000001",
        "tgn:7012149",
        "tgn:2000476",
        "tgn:7007250",
        "tgn:7029392"
    ],
    "tgn:id":2656331,
    "tgn:name":"Shearer Peak",
    "tgn:placetype":[
        "aat:300008798"
    ]
},
  "bbox": [],
  "geometry": {"coordinates":[-114.8833,46.0333],"type":"Point"}
}