{
  "id": 7572111,
  "type": "Feature",
  "properties": {
    "tgn:hierarchy":[
        "tgn:7572111",
        "tgn:1000004",
        "tgn:7000198",
        "tgn:1001894",
        "tgn:7029392"
    ],
    "tgn:id":7572111,
    "tgn:name:en":"Gadgucha Alot",
    "tgn:placetype":[
        "aat:300007783"
    ]
},
  "bbox": [],
  "geometry": {"coordinates":[75.540104,23.766203],"type":"Point"}
}