{
  "id": 7323293,
  "type": "Feature",
  "properties": {
    "tgn:hierarchy":[
        "tgn:7323293",
        "tgn:7002808",
        "tgn:7030216",
        "tgn:1000003",
        "tgn:1000095",
        "tgn:7029392"
    ],
    "tgn:id":7323293,
    "tgn:name":"Rota, Cerro de la",
    "tgn:placetype":[
        "aat:300008795"
    ]
},
  "bbox": [],
  "geometry": {"coordinates":[1.886827,42.209774],"type":"Point"}
}