{
  "id": 7535625,
  "type": "Feature",
  "properties": {
    "tgn:hierarchy":[
        "tgn:7535625",
        "tgn:7001242",
        "tgn:7016833",
        "tgn:7001334",
        "tgn:7029392"
    ],
    "tgn:id":7535625,
    "tgn:name:en":"Ghaz\u0101l al Mustajiddah, 'Ayn",
    "tgn:placetype":[
        "aat:300008697"
    ]
},
  "bbox": [],
  "geometry": {"coordinates":[30.65,25.75],"type":"Point"}
}