{
  "id": 2057790,
  "type": "Feature",
  "properties": {
    "tgn:hierarchy":[
        "tgn:2057790",
        "tgn:1000001",
        "tgn:7012149",
        "tgn:2001127",
        "tgn:7007522",
        "tgn:7029392"
    ],
    "tgn:id":2057790,
    "tgn:name":"Wildwood",
    "tgn:placetype":[
        "aat:300008347",
        "aat:300387210"
    ]
},
  "bbox": [],
  "geometry": {"coordinates":[-90.2333,33.6167],"type":"Point"}
}