{
  "id": 7402930,
  "type": "Feature",
  "properties": {
    "tgn:hierarchy":[
        "tgn:7402930",
        "tgn:1000001",
        "tgn:1001906",
        "tgn:7005560",
        "tgn:7029392"
    ],
    "tgn:id":7402930,
    "tgn:name":"Campo Viejo",
    "tgn:placetype":[
        "aat:300008347"
    ]
},
  "bbox": [],
  "geometry": {"coordinates":[-104.233333,21.875],"type":"Point"}
}