{
  "id": 2702487,
  "type": "Feature",
  "properties": {
    "tgn:hierarchy":[
        "tgn:2702487",
        "tgn:1000001",
        "tgn:7012149",
        "tgn:1002402",
        "tgn:7007523",
        "tgn:7029392"
    ],
    "tgn:id":2702487,
    "tgn:name":"Sulphur Branch",
    "tgn:placetype":[
        "aat:300008699"
    ]
},
  "bbox": [],
  "geometry": {"coordinates":[-91.5667,38.3167],"type":"Point"}
}