{
  "id": 1076009,
  "type": "Feature",
  "properties": {
    "tgn:hierarchy":[
        "tgn:1076009",
        "tgn:1000004",
        "tgn:7000198",
        "tgn:1001894",
        "tgn:7029392"
    ],
    "tgn:id":1076009,
    "tgn:name:en":"Lah\u0101r",
    "tgn:placetype":[
        "aat:300008347"
    ]
},
  "bbox": [],
  "geometry": {"coordinates":[78.941371,26.194008],"type":"Point"}
}