{
  "id": 2784718,
  "type": "Feature",
  "properties": {
    "tgn:hierarchy":[
        "tgn:2784718",
        "tgn:2002240",
        "tgn:1000001",
        "tgn:7012149",
        "tgn:7007920",
        "tgn:7029392"
    ],
    "tgn:id":2784718,
    "tgn:name":"Yellepit Pond",
    "tgn:placetype":[
        "aat:300008680"
    ]
},
  "bbox": [],
  "geometry": {"coordinates":[-118.9667,46.0167],"type":"Point"}
}