{
  "id": 2440670,
  "type": "Feature",
  "properties": {
    "tgn:hierarchy":[
        "tgn:2440670",
        "tgn:1000001",
        "tgn:7012149",
        "tgn:7020681",
        "tgn:7007256",
        "tgn:7029392"
    ],
    "tgn:id":2440670,
    "tgn:name":"Knight Bay",
    "tgn:placetype":[
        "aat:300132316"
    ]
},
  "bbox": [],
  "geometry": {"coordinates":[-90.5333,29.95],"type":"Point"}
}