{
  "id": 7450431,
  "type": "Feature",
  "properties": {
    "tgn:hierarchy":[
        "tgn:7450431",
        "tgn:7002445",
        "tgn:1000003",
        "tgn:7012034",
        "tgn:7008591",
        "tgn:7029392"
    ],
    "tgn:id":7450431,
    "tgn:name:en":"Eardiston",
    "tgn:placetype":[
        "aat:300008347"
    ]
},
  "bbox": [],
  "geometry": {"coordinates":[-2.933333,52.816667],"type":"Point"}
}