{
  "id": 7314238,
  "type": "Feature",
  "properties": {
    "tgn:hierarchy":[
        "tgn:7314238",
        "tgn:1001705",
        "tgn:1000049",
        "tgn:1000002",
        "tgn:7029392"
    ],
    "tgn:id":7314238,
    "tgn:name":"Lontu\u00e9, R\u00edo",
    "tgn:placetype":[
        "aat:300008699"
    ]
},
  "bbox": [],
  "geometry": {"coordinates":[-71.383333,-34.983333],"type":"Point"}
}