{
  "id": 7510377,
  "type": "Feature",
  "properties": {
    "tgn:hierarchy":[
        "tgn:7510377",
        "tgn:1009227",
        "tgn:1000226",
        "tgn:7016822",
        "tgn:1000006",
        "tgn:7029392"
    ],
    "tgn:id":7510377,
    "tgn:name:en":"Te Hau Mountain",
    "tgn:placetype":[
        "aat:300008795"
    ]
},
  "bbox": [],
  "geometry": {"coordinates":[167.933333,-44.566667],"type":"Point"}
}