{
  "id": 2230604,
  "type": "Feature",
  "properties": {
    "tgn:hierarchy":[
        "tgn:2230604",
        "tgn:1000001",
        "tgn:7006451",
        "tgn:2000093",
        "tgn:7012149",
        "tgn:7029392"
    ],
    "tgn:id":2230604,
    "tgn:name":"Center Ridge Tank",
    "tgn:placetype":[
        "aat:300006191"
    ]
},
  "bbox": [],
  "geometry": {"coordinates":[-111.0667,33.7667],"type":"Point"}
}