{
  "id": 1118773,
  "type": "Feature",
  "properties": {
    "tgn:hierarchy":[
        "tgn:1118773",
        "tgn:7005685",
        "tgn:1000001",
        "tgn:7005734",
        "tgn:7029392"
    ],
    "tgn:id":1118773,
    "tgn:name":"Wuskwatim Lake",
    "tgn:placetype":[
        "aat:300008680"
    ]
},
  "bbox": [],
  "geometry": {"coordinates":[-98.55,55.55],"type":"Point"}
}