{
  "id": 2650956,
  "type": "Feature",
  "properties": {
    "tgn:hierarchy":[
        "tgn:2650956",
        "tgn:1000001",
        "tgn:7012149",
        "tgn:1002472",
        "tgn:7007568",
        "tgn:7029392"
    ],
    "tgn:id":2650956,
    "tgn:name":"Second Lake",
    "tgn:placetype":[
        "aat:300008680"
    ]
},
  "bbox": [],
  "geometry": {"coordinates":[-74.9333,43.5833],"type":"Point"}
}