{
  "id": 7552719,
  "type": "Feature",
  "properties": {
    "tgn:hierarchy":[
        "tgn:7552719",
        "tgn:1000004",
        "tgn:7000198",
        "tgn:1001894",
        "tgn:7029392"
    ],
    "tgn:id":7552719,
    "tgn:name:en":"M\u0101not",
    "tgn:placetype":[
        "aat:300008347"
    ]
},
  "bbox": [],
  "geometry": {"coordinates":[80.510946,22.734437],"type":"Point"}
}