{
  "id": 2492846,
  "type": "Feature",
  "properties": {
    "tgn:hierarchy":[
        "tgn:2492846",
        "tgn:7006450",
        "tgn:1000001",
        "tgn:2124012",
        "tgn:7012149",
        "tgn:7029392"
    ],
    "tgn:id":2492846,
    "tgn:name":"Mark Lake",
    "tgn:placetype":[
        "aat:300008680"
    ]
},
  "bbox": [],
  "geometry": {"coordinates":[-154.1333,56.5333],"type":"Point"}
}