{
  "id": 7406844,
  "type": "Feature",
  "properties": {
    "tgn:hierarchy":[
        "tgn:7406844",
        "tgn:7005585",
        "tgn:1000001",
        "tgn:7005560",
        "tgn:7029392"
    ],
    "tgn:id":7406844,
    "tgn:name":"La Neblina, Cerro",
    "tgn:placetype":[
        "aat:300008795"
    ]
},
  "bbox": [],
  "geometry": {"coordinates":[-100.341667,17.183333],"type":"Point"}
}