{
  "id": 7416176,
  "type": "Feature",
  "properties": {
    "tgn:hierarchy":[
        "tgn:7416176",
        "tgn:1000001",
        "tgn:7005591",
        "tgn:7005560",
        "tgn:7029392"
    ],
    "tgn:id":7416176,
    "tgn:name:es":"The Real",
    "tgn:placetype":[
        "aat:300008347"
    ]
},
  "bbox": [],
  "geometry": {"coordinates":[-95.132778,17.111944],"type":"Point"}
}