{
  "id": 7274196,
  "type": "Feature",
  "properties": {
    "tgn:hierarchy":[
        "tgn:7274196",
        "tgn:1000003",
        "tgn:7006951",
        "tgn:7016845",
        "tgn:7029392"
    ],
    "tgn:id":7274196,
    "tgn:name:nl":"Zuiderlegmeerpolder",
    "tgn:placetype":[
        "aat:300006163"
    ]
},
  "bbox": [],
  "geometry": {"coordinates":[4.75,52.233333],"type":"Point"}
}