{
  "id": 7121829,
  "type": "Feature",
  "properties": {
    "tgn:hierarchy":[
        "tgn:7121829",
        "tgn:1000003",
        "tgn:7003688",
        "tgn:7000084",
        "tgn:7029392"
    ],
    "tgn:id":7121829,
    "tgn:name":"Pinnsee",
    "tgn:placetype":[
        "aat:300008688"
    ]
},
  "bbox": [],
  "geometry": {"coordinates":[10.733333,53.633333],"type":"Point"}
}