{
  "id": 2060953,
  "type": "Feature",
  "properties": {
    "tgn:hierarchy":[
        "tgn:2060953",
        "tgn:1000001",
        "tgn:7012149",
        "tgn:1002634",
        "tgn:7007523",
        "tgn:7029392"
    ],
    "tgn:id":2060953,
    "tgn:name":"Woodland",
    "tgn:placetype":[
        "aat:300008347"
    ]
},
  "bbox": [],
  "geometry": {"coordinates":[-91.5833,39.75],"type":"Point"}
}