{
  "id": 2520189,
  "type": "Feature",
  "properties": {
    "tgn:hierarchy":[
        "tgn:2520189",
        "tgn:1000001",
        "tgn:2001410",
        "tgn:7012149",
        "tgn:7007526",
        "tgn:7029392"
    ],
    "tgn:id":2520189,
    "tgn:name":"Moms Cave",
    "tgn:placetype":[
        "aat:300008746"
    ]
},
  "bbox": [],
  "geometry": {"coordinates":[-116.1333,36.2667],"type":"Point"}
}