<<<<<<< HEAD
{
  "id": 2158889,
  "type": "Feature",
  "properties": {
    "tgn:hierarchy":[
        "tgn:2158889",
        "tgn:1000001",
        "tgn:7012149",
        "tgn:2001927",
        "tgn:7007825",
        "tgn:7029392"
    ],
    "tgn:id":2158889,
    "tgn:name":"Beckham Hollow Branch",
    "tgn:placetype":[
        "aat:300008699"
    ]
},
  "bbox": [],
  "geometry": {"coordinates":[-87.9167,35.2667],"type":"Point"}
}
=======
{"geometry":{"type":"Point","coordinates":[-87.916700,35.266700]},"type":"Feature","properties":{"hierarchy":["tgn:2158889","tgn:1000001","tgn:7012149","tgn:2001927","tgn:7007825","tgn:7029392"],"placetype":["aat:300008699"],"id":2158889,"name:xx":"Beckham Hollow Branch"}}
>>>>>>> 03f74aca74312dbeaf24d7e61306dd6a786dc3d0
