{
  "id": 2136189,
  "type": "Feature",
  "properties": {
    "tgn:hierarchy":[
        "tgn:2136189",
        "tgn:1000001",
        "tgn:7012149",
        "tgn:2001524",
        "tgn:7007709",
        "tgn:7029392"
    ],
    "tgn:id":2136189,
    "tgn:name":"Aragona Village",
    "tgn:placetype":[
        "aat:300008347"
    ]
},
  "bbox": [],
  "geometry": {"coordinates":[-77.3333,34.75],"type":"Point"}
}