{
  "id": 7232986,
  "type": "Feature",
  "properties": {
    "tgn:hierarchy":[
        "tgn:7232986",
        "tgn:7002752",
        "tgn:7001399",
        "tgn:1000003",
        "tgn:1000074",
        "tgn:7029392"
    ],
    "tgn:id":7232986,
    "tgn:name":"L\u00e1pata",
    "tgn:placetype":[
        "aat:300008795"
    ]
},
  "bbox": [],
  "geometry": {"coordinates":[21.441389,39.49],"type":"Point"}
}