<<<<<<< HEAD
{
  "id": 7481951,
  "type": "Feature",
  "properties": {
    "tgn:hierarchy":[
        "tgn:7481951",
        "tgn:1000004",
        "tgn:7489179",
        "tgn:1000141",
        "tgn:7029392"
    ],
    "tgn:id":7481951,
    "tgn:name":"Qilan Senlin Youlequ",
    "tgn:placetype":[
        "aat:300008187"
    ]
},
  "bbox": [],
  "geometry": {"coordinates":[121.493333,24.579722],"type":"Point"}
}
=======
{"geometry":{"type":"Point","coordinates":[121.493333,24.579722]},"type":"Feature","properties":{"hierarchy":["tgn:7481951","tgn:1000004","tgn:7489179","tgn:1000141","tgn:7029392"],"placetype":["aat:300008187"],"id":7481951,"name:xx":"Qilan Senlin Youlequ"}}
>>>>>>> 03f74aca74312dbeaf24d7e61306dd6a786dc3d0
