{
  "id": 2276700,
  "type": "Feature",
  "properties": {
    "tgn:hierarchy":[
        "tgn:2276700",
        "tgn:1000001",
        "tgn:2000317",
        "tgn:7012149",
        "tgn:7007248",
        "tgn:7029392"
    ],
    "tgn:id":2276700,
    "tgn:name":"Davidson Hill",
    "tgn:placetype":[
        "aat:300008798"
    ]
},
  "bbox": [],
  "geometry": {"coordinates":[-84.9167,32.35],"type":"Point"}
}