{
  "id": 2681335,
  "type": "Feature",
  "properties": {
    "tgn:hierarchy":[
        "tgn:2681335",
        "tgn:1000001",
        "tgn:7012149",
        "tgn:2002123",
        "tgn:7007827",
        "tgn:7029392"
    ],
    "tgn:id":2681335,
    "tgn:name":"South Peak",
    "tgn:placetype":[
        "aat:300008798"
    ]
},
  "bbox": [],
  "geometry": {"coordinates":[-113.8833,40.0333],"type":"Point"}
}