{
  "id": 2289080,
  "type": "Feature",
  "properties": {
    "tgn:hierarchy":[
        "tgn:2289080",
        "tgn:1000001",
        "tgn:7012149",
        "tgn:7007158",
        "tgn:2000243",
        "tgn:7029392"
    ],
    "tgn:id":2289080,
    "tgn:name":"Divide Creek Reservoir Number 2",
    "tgn:placetype":[
        "aat:300006191"
    ]
},
  "bbox": [],
  "geometry": {"coordinates":[-108.5333,40.2167],"type":"Point"}
}