{
  "id": 2477818,
  "type": "Feature",
  "properties": {
    "tgn:hierarchy":[
        "tgn:2477818",
        "tgn:1000001",
        "tgn:7012149",
        "tgn:2000811",
        "tgn:7007255",
        "tgn:7029392"
    ],
    "tgn:id":2477818,
    "tgn:name":"MacIntosh Creek",
    "tgn:placetype":[
        "aat:300008706"
    ]
},
  "bbox": [],
  "geometry": {"coordinates":[-83.2667,37.1833],"type":"Point"}
}