{
  "id": 7058385,
  "type": "Feature",
  "properties": {
    "tgn:hierarchy":[
        "tgn:7058385",
        "tgn:1003428",
        "tgn:1000003",
        "tgn:7003120",
        "tgn:1000080",
        "tgn:7029392"
    ],
    "tgn:id":7058385,
    "tgn:name":"Bormida, Fiume",
    "tgn:placetype":[
        "aat:300008699"
    ]
},
  "bbox": [],
  "geometry": {"coordinates":[8.666667,44.933333],"type":"Point"}
}