{
  "id": 2424673,
  "type": "Feature",
  "properties": {
    "tgn:hierarchy":[
        "tgn:2424673",
        "tgn:1000001",
        "tgn:7012149",
        "tgn:2002030",
        "tgn:7007826",
        "tgn:7029392"
    ],
    "tgn:id":2424673,
    "tgn:name":"Johnson Creek",
    "tgn:placetype":[
        "aat:300008706"
    ]
},
  "bbox": [],
  "geometry": {"coordinates":[-98.65,30.5833],"type":"Point"}
}