{
  "id": 2628492,
  "type": "Feature",
  "properties": {
    "tgn:hierarchy":[
        "tgn:2628492",
        "tgn:1000001",
        "tgn:7012149",
        "tgn:7007157",
        "tgn:1002901",
        "tgn:7029392"
    ],
    "tgn:id":2628492,
    "tgn:name":"Roos Cut",
    "tgn:placetype":[
        "aat:300006075"
    ]
},
  "bbox": [],
  "geometry": {"coordinates":[-122.0667,38.15],"type":"Point"}
}