{
  "id": 7581809,
  "type": "Feature",
  "properties": {
    "tgn:hierarchy":[
        "tgn:7581809",
        "tgn:1000004",
        "tgn:1001869",
        "tgn:7000198",
        "tgn:7029392"
    ],
    "tgn:id":7581809,
    "tgn:name:en":"T\u0101jpuri",
    "tgn:placetype":[
        "aat:300008347"
    ]
},
  "bbox": [],
  "geometry": {"coordinates":[72.906625,23.553657],"type":"Point"}
}