{
  "id": 2706669,
  "type": "Feature",
  "properties": {
    "tgn:hierarchy":[
        "tgn:2706669",
        "tgn:1000001",
        "tgn:7012149",
        "tgn:2002117",
        "tgn:7007827",
        "tgn:7029392"
    ],
    "tgn:id":2706669,
    "tgn:name":"Swan Peak Pond",
    "tgn:placetype":[
        "aat:300008680"
    ]
},
  "bbox": [],
  "geometry": {"coordinates":[-111.4667,41.9833],"type":"Point"}
}