<<<<<<< HEAD
{
  "id": 2706669,
  "type": "Feature",
  "properties": {
    "tgn:hierarchy":[
        "tgn:2706669",
        "tgn:1000001",
        "tgn:7012149",
        "tgn:2002117",
        "tgn:7007827",
        "tgn:7029392"
    ],
    "tgn:id":2706669,
    "tgn:name":"Swan Peak Pond",
    "tgn:placetype":[
        "aat:300008680"
    ]
},
  "bbox": [],
  "geometry": {"coordinates":[-111.4667,41.9833],"type":"Point"}
}
=======
{"geometry":{"type":"Point","coordinates":[-111.466700,41.983300]},"type":"Feature","properties":{"hierarchy":["tgn:2706669","tgn:1000001","tgn:7012149","tgn:2002117","tgn:7007827","tgn:7029392"],"placetype":["aat:300008680"],"id":2706669,"name:xx":"Swan Peak Pond"}}
>>>>>>> 03f74aca74312dbeaf24d7e61306dd6a786dc3d0
