{
  "id": 2007911,
  "type": "Feature",
  "properties": {
    "tgn:hierarchy":[
        "tgn:2007911",
        "tgn:1000001",
        "tgn:7016172",
        "tgn:7012149",
        "tgn:2000124",
        "tgn:7029392"
    ],
    "tgn:id":2007911,
    "tgn:name":"Carthage",
    "tgn:placetype":[
        "aat:300008347"
    ]
},
  "bbox": [],
  "geometry": {"coordinates":[-92.55,34.0667],"type":"Point"}
}