{
  "id": 2626603,
  "type": "Feature",
  "properties": {
    "tgn:hierarchy":[
        "tgn:2626603",
        "tgn:1000001",
        "tgn:7012149",
        "tgn:2002114",
        "tgn:7007827",
        "tgn:7029392"
    ],
    "tgn:id":2626603,
    "tgn:name":"Rocky Knoll",
    "tgn:placetype":[
        "aat:300008798"
    ]
},
  "bbox": [],
  "geometry": {"coordinates":[-112.8833,39.1667],"type":"Point"}
}