<<<<<<< HEAD
{
  "id": 2250273,
  "type": "Feature",
  "properties": {
    "tgn:hierarchy":[
        "tgn:2250273",
        "tgn:1000001",
        "tgn:7016172",
        "tgn:7012149",
        "tgn:7029392"
    ],
    "tgn:id":2250273,
    "tgn:name":"Collins Shoals",
    "tgn:placetype":[
        "aat:300132348"
    ]
},
  "bbox": [],
  "geometry": {"coordinates":[-93.3833,35.3333],"type":"Point"}
}
=======
{"geometry":{"type":"Point","coordinates":[-93.383300,35.333300]},"type":"Feature","properties":{"hierarchy":["tgn:2250273","tgn:1000001","tgn:7016172","tgn:7012149","tgn:7029392"],"placetype":["aat:300132348"],"id":2250273,"name:xx":"Collins Shoals"}}
>>>>>>> 03f74aca74312dbeaf24d7e61306dd6a786dc3d0
