{
  "id": 7090148,
  "type": "Feature",
  "properties": {
    "tgn:hierarchy":[
        "tgn:7090148",
        "tgn:7003669",
        "tgn:1000003",
        "tgn:7000084",
        "tgn:7029392"
    ],
    "tgn:id":7090148,
    "tgn:name":"Wabach",
    "tgn:placetype":[
        "aat:300000206"
    ]
},
  "bbox": [],
  "geometry": {"coordinates":[12.433333,48.066667],"type":"Point"}
}