{
  "id": 2142130,
  "type": "Feature",
  "properties": {
    "tgn:hierarchy":[
        "tgn:2142130",
        "tgn:1000001",
        "tgn:7012149",
        "tgn:2002195",
        "tgn:7007919",
        "tgn:7029392"
    ],
    "tgn:id":2142130,
    "tgn:name":"Back Creek Lake",
    "tgn:placetype":[
        "aat:300006191"
    ]
},
  "bbox": [],
  "geometry": {"coordinates":[-82.6667,36.9667],"type":"Point"}
}