{
  "id": 2127772,
  "type": "Feature",
  "properties": {
    "tgn:hierarchy":[
        "tgn:2127772",
        "tgn:2000090",
        "tgn:1000001",
        "tgn:7006451",
        "tgn:7012149",
        "tgn:7029392"
    ],
    "tgn:id":2127772,
    "tgn:name":"Alamo Spring",
    "tgn:placetype":[
        "aat:300008697"
    ]
},
  "bbox": [],
  "geometry": {"coordinates":[-109.6833,36.3333],"type":"Point"}
}