{
  "id": 7285446,
  "type": "Feature",
  "properties": {
    "tgn:hierarchy":[
        "tgn:7285446",
        "tgn:1001699",
        "tgn:1000049",
        "tgn:1000002",
        "tgn:7029392"
    ],
    "tgn:id":7285446,
    "tgn:name":"Quenuir",
    "tgn:placetype":[
        "aat:300000206"
    ]
},
  "bbox": [],
  "geometry": {"coordinates":[-73.766667,-41.533333],"type":"Point"}
}