{
  "id": 2174256,
  "type": "Feature",
  "properties": {
    "tgn:hierarchy":[
        "tgn:2174256",
        "tgn:1000001",
        "tgn:2001414",
        "tgn:7012149",
        "tgn:7007526",
        "tgn:7029392"
    ],
    "tgn:id":2174256,
    "tgn:name":"Birthday Mine",
    "tgn:placetype":[
        "aat:300000390"
    ]
},
  "bbox": [],
  "geometry": {"coordinates":[-117.5833,41.8167],"type":"Point"}
}