{
  "id": 2368266,
  "type": "Feature",
  "properties": {
    "tgn:hierarchy":[
        "tgn:2368266",
        "tgn:1000001",
        "tgn:7012149",
        "tgn:2002380",
        "tgn:7007923",
        "tgn:7029392"
    ],
    "tgn:id":2368266,
    "tgn:name":"Guernsey Fish Pond",
    "tgn:placetype":[
        "aat:300006191"
    ]
},
  "bbox": [],
  "geometry": {"coordinates":[-104.7333,42.25],"type":"Point"}
}