{
  "id": 2368959,
  "type": "Feature",
  "properties": {
    "tgn:hierarchy":[
        "tgn:2368959",
        "tgn:1000001",
        "tgn:7012149",
        "tgn:7007240",
        "tgn:7029392"
    ],
    "tgn:id":2368959,
    "tgn:name":"Gum Branch",
    "tgn:placetype":[
        "aat:300008699"
    ]
},
  "bbox": [],
  "geometry": {"coordinates":[-81.1833,27.6333],"type":"Point"}
}