{
  "id": 7498193,
  "type": "Feature",
  "properties": {
    "tgn:hierarchy":[
        "tgn:7498193",
        "tgn:7001004",
        "tgn:1000004",
        "tgn:1000141",
        "tgn:7029392"
    ],
    "tgn:id":7498193,
    "tgn:name":"Baxi Shan",
    "tgn:placetype":[
        "aat:300387002"
    ]
},
  "bbox": [],
  "geometry": {"coordinates":[120.849535,23.387471],"type":"Point"}
}