{
  "id": 2603550,
  "type": "Feature",
  "properties": {
    "tgn:hierarchy":[
        "tgn:2603550",
        "tgn:1000001",
        "tgn:7012149",
        "tgn:7007158",
        "tgn:2000250",
        "tgn:7029392"
    ],
    "tgn:id":2603550,
    "tgn:name":"Queen-of-the-West Mine",
    "tgn:placetype":[
        "aat:300000390"
    ]
},
  "bbox": [],
  "geometry": {"coordinates":[-106.1833,39.4333],"type":"Point"}
}