{
  "id": 2018733,
  "type": "Feature",
  "properties": {
    "tgn:hierarchy":[
        "tgn:2018733",
        "tgn:1000001",
        "tgn:1002477",
        "tgn:7012149",
        "tgn:7007240",
        "tgn:7029392"
    ],
    "tgn:id":2018733,
    "tgn:name":"Brighton",
    "tgn:placetype":[
        "aat:300008347"
    ]
},
  "bbox": [],
  "geometry": {"coordinates":[-81.0833,27.2167],"type":"Point"}
}