{
  "id": 2143570,
  "type": "Feature",
  "properties": {
    "tgn:hierarchy":[
        "tgn:2143570",
        "tgn:1000001",
        "tgn:2000952",
        "tgn:7012149",
        "tgn:7007520",
        "tgn:7029392"
    ],
    "tgn:id":2143570,
    "tgn:name":"Baileys Lake",
    "tgn:placetype":[
        "aat:300008680"
    ]
},
  "bbox": [],
  "geometry": {"coordinates":[-83.75,45.9667],"type":"Point"}
}