{
  "id": 7148443,
  "type": "Feature",
  "properties": {
    "tgn:hierarchy":[
        "tgn:7148443",
        "tgn:7000096",
        "tgn:1000003",
        "tgn:7000084",
        "tgn:7029392"
    ],
    "tgn:id":7148443,
    "tgn:name":"Krummer Pfuhl",
    "tgn:placetype":[
        "aat:300008688"
    ]
},
  "bbox": [],
  "geometry": {"coordinates":[14.133333,52.466667],"type":"Point"}
}