{
  "id": 2190245,
  "type": "Feature",
  "properties": {
    "tgn:hierarchy":[
        "tgn:2190245",
        "tgn:1000001",
        "tgn:2001701",
        "tgn:7012149",
        "tgn:7007708",
        "tgn:7029392"
    ],
    "tgn:id":2190245,
    "tgn:name":"Box",
    "tgn:placetype":[
        "aat:300008347"
    ]
},
  "bbox": [],
  "geometry": {"coordinates":[-123.7167,44.2833],"type":"Point"}
}