{
  "id": 2719551,
  "type": "Feature",
  "properties": {
    "tgn:hierarchy":[
        "tgn:2719551",
        "tgn:1000001",
        "tgn:7006451",
        "tgn:7012149",
        "tgn:2000097",
        "tgn:7029392"
    ],
    "tgn:id":2719551,
    "tgn:name":"Three Fountains",
    "tgn:placetype":[
        "aat:300008347"
    ]
},
  "bbox": [],
  "geometry": {"coordinates":[-112.1833,33.5167],"type":"Point"}
}