{
  "id": 1121875,
  "type": "Feature",
  "properties": {
    "tgn:hierarchy":[
        "tgn:1121875",
        "tgn:1000003",
        "tgn:7029392"
    ],
    "tgn:id":1121875,
    "tgn:name:eu":"Bidasoa, R\u00edo",
    "tgn:name:fr":"Bidassoa",
    "tgn:placetype":[
        "aat:300008707"
    ]
},
  "bbox": [],
  "geometry": {"coordinates":[-1.7833,43.3667],"type":"Point"}
}