{
  "id": 2505757,
  "type": "Feature",
  "properties": {
    "tgn:hierarchy":[
        "tgn:2505757",
        "tgn:1000001",
        "tgn:7012149",
        "tgn:7007157",
        "tgn:1002828",
        "tgn:7029392"
    ],
    "tgn:id":2505757,
    "tgn:name":"Menifee Valley",
    "tgn:placetype":[
        "aat:300386845"
    ]
},
  "bbox": [],
  "geometry": {"coordinates":[-117.1667,33.6833],"type":"Point"}
}