{
  "id": 7420013,
  "type": "Feature",
  "properties": {
    "tgn:hierarchy":[
        "tgn:7420013",
        "tgn:7005584",
        "tgn:1000001",
        "tgn:7005560",
        "tgn:7029392"
    ],
    "tgn:id":7420013,
    "tgn:name":"Joconoxtle",
    "tgn:placetype":[
        "aat:300008347"
    ]
},
  "bbox": [],
  "geometry": {"coordinates":[-100.376667,21.616111],"type":"Point"}
}