{
  "id": 7305782,
  "type": "Feature",
  "properties": {
    "tgn:hierarchy":[
        "tgn:7305782",
        "tgn:7002842",
        "tgn:7001158",
        "tgn:1000003",
        "tgn:1000095",
        "tgn:7029392"
    ],
    "tgn:id":7305782,
    "tgn:name":"Manzanares, R\u00edo",
    "tgn:placetype":[
        "aat:300008699"
    ]
},
  "bbox": [],
  "geometry": {"coordinates":[-3.083333,41.466667],"type":"Point"}
}