{
  "id": 1022319,
  "type": "Feature",
  "properties": {
    "tgn:hierarchy":[
        "tgn:1022319",
        "tgn:7012827",
        "tgn:7002454",
        "tgn:1000047",
        "tgn:1000002",
        "tgn:7029392"
    ],
    "tgn:id":1022319,
    "tgn:name":"Palmin\u00f3polis",
    "tgn:placetype":[
        "aat:300008347"
    ]
},
  "bbox": [],
  "geometry": {"coordinates":[-50.1333,-16.7833],"type":"Point"}
}