{
  "id": 1095637,
  "type": "Feature",
  "properties": {
    "tgn:hierarchy":[
        "tgn:1095637",
        "tgn:7001242",
        "tgn:7016833",
        "tgn:1001083",
        "tgn:7029392"
    ],
    "tgn:id":1095637,
    "tgn:name:en":"Nazlat as Samm\u0101n",
    "tgn:placetype":[
        "aat:300008347"
    ]
},
  "bbox": [],
  "geometry": {"coordinates":[31.133333,29.983333],"type":"Point"}
}