{
  "id": 7227456,
  "type": "Feature",
  "properties": {
    "tgn:hierarchy":[
        "tgn:7227456",
        "tgn:7002709",
        "tgn:7002705",
        "tgn:1000003",
        "tgn:1000074",
        "tgn:7029392"
    ],
    "tgn:id":7227456,
    "tgn:name":"Gkr\u00edka",
    "tgn:placetype":[
        "aat:300008347"
    ]
},
  "bbox": [],
  "geometry": {"coordinates":[20.423889,39.465],"type":"Point"}
}