<<<<<<< HEAD
{
  "id": 2402113,
  "type": "Feature",
  "properties": {
    "tgn:hierarchy":[
        "tgn:2402113",
        "tgn:1000001",
        "tgn:7012149",
        "tgn:2002035",
        "tgn:7007826",
        "tgn:7029392"
    ],
    "tgn:id":2402113,
    "tgn:name":"Horseshoe Tank",
    "tgn:placetype":[
        "aat:300006191"
    ]
},
  "bbox": [],
  "geometry": {"coordinates":[-98.3833,28.5333],"type":"Point"}
}
=======
{"geometry":{"type":"Point","coordinates":[-98.383300,28.533300]},"type":"Feature","properties":{"hierarchy":["tgn:2402113","tgn:1000001","tgn:7012149","tgn:2002035","tgn:7007826","tgn:7029392"],"placetype":["aat:300006191"],"id":2402113,"name:xx":"Horseshoe Tank"}}
>>>>>>> 03f74aca74312dbeaf24d7e61306dd6a786dc3d0
