{
  "id": 2402113,
  "type": "Feature",
  "properties": {
    "tgn:hierarchy":[
        "tgn:2402113",
        "tgn:1000001",
        "tgn:7012149",
        "tgn:2002035",
        "tgn:7007826",
        "tgn:7029392"
    ],
    "tgn:id":2402113,
    "tgn:name":"Horseshoe Tank",
    "tgn:placetype":[
        "aat:300006191"
    ]
},
  "bbox": [],
  "geometry": {"coordinates":[-98.3833,28.5333],"type":"Point"}
}