{
  "id": 2130654,
  "type": "Feature",
  "properties": {
    "tgn:hierarchy":[
        "tgn:2130654",
        "tgn:1000001",
        "tgn:7012149",
        "tgn:2000290",
        "tgn:7007240",
        "tgn:7029392"
    ],
    "tgn:id":2130654,
    "tgn:name":"Alligator Point",
    "tgn:placetype":[
        "aat:300008850"
    ]
},
  "bbox": [],
  "geometry": {"coordinates":[-86.2167,30.4167],"type":"Point"}
}