{
  "id": 2525168,
  "type": "Feature",
  "properties": {
    "tgn:hierarchy":[
        "tgn:2525168",
        "tgn:1000001",
        "tgn:7012149",
        "tgn:2001420",
        "tgn:7007526",
        "tgn:7029392"
    ],
    "tgn:id":2525168,
    "tgn:name":"Morris Shaft",
    "tgn:placetype":[
        "aat:300000390"
    ]
},
  "bbox": [],
  "geometry": {"coordinates":[-115.0167,39.25],"type":"Point"}
}