{
  "id": 1125244,
  "type": "Feature",
  "properties": {
    "tgn:hierarchy":[
        "tgn:1125244",
        "tgn:1000003",
        "tgn:7002883",
        "tgn:1000070",
        "tgn:7029392"
    ],
    "tgn:id":1125244,
    "tgn:name":"Juine",
    "tgn:placetype":[
        "aat:300008707"
    ]
},
  "bbox": [],
  "geometry": {"coordinates":[2.3833,48.5333],"type":"Point"}
}