{
  "id": 2693287,
  "type": "Feature",
  "properties": {
    "tgn:hierarchy":[
        "tgn:2693287",
        "tgn:7006450",
        "tgn:1000001",
        "tgn:7012149",
        "tgn:2000082",
        "tgn:7029392"
    ],
    "tgn:id":2693287,
    "tgn:name":"Steers Mine",
    "tgn:placetype":[
        "aat:300000390"
    ]
},
  "bbox": [],
  "geometry": {"coordinates":[-131.9667,55.6167],"type":"Point"}
}