{
  "id": 7426012,
  "type": "Feature",
  "properties": {
    "tgn:hierarchy":[
        "tgn:7426012",
        "tgn:7005581",
        "tgn:1000001",
        "tgn:7005560",
        "tgn:7029392"
    ],
    "tgn:id":7426012,
    "tgn:name":"El Naranjito",
    "tgn:placetype":[
        "aat:300008347"
    ]
},
  "bbox": [],
  "geometry": {"coordinates":[-107.366667,26.633333],"type":"Point"}
}