<<<<<<< HEAD
{
  "id": 7059225,
  "type": "Feature",
  "properties": {
    "tgn:hierarchy":[
        "tgn:7059225",
        "tgn:1000660",
        "tgn:1000002",
        "tgn:1000056",
        "tgn:7029392"
    ],
    "tgn:id":7059225,
    "tgn:name":"Huancaco",
    "tgn:placetype":[
        "aat:300008347"
    ]
},
  "bbox": [],
  "geometry": {"coordinates":[-78.783,-8.433],"type":"Point"}
}
=======
{"geometry":{"type":"Point","coordinates":[-78.783000,-8.433000]},"type":"Feature","properties":{"hierarchy":["tgn:7059225","tgn:1000660","tgn:1000002","tgn:1000056","tgn:7029392"],"placetype":["aat:300008347"],"id":7059225,"name:xx":"Huancaco"}}
>>>>>>> 03f74aca74312dbeaf24d7e61306dd6a786dc3d0
