{
  "id": 2168845,
  "type": "Feature",
  "properties": {
    "tgn:hierarchy":[
        "tgn:2168845",
        "tgn:1000001",
        "tgn:7012149",
        "tgn:2002268",
        "tgn:7013961",
        "tgn:7029392"
    ],
    "tgn:id":2168845,
    "tgn:name":"Big Horse Lake",
    "tgn:placetype":[
        "aat:300006191"
    ]
},
  "bbox": [],
  "geometry": {"coordinates":[-81.75,38.7833],"type":"Point"}
}