{
  "id": 7009133,
  "type": "Feature",
  "properties": {
    "tgn:hierarchy":[
        "tgn:7009133",
        "tgn:7002444",
        "tgn:1000003",
        "tgn:7019085",
        "tgn:7008591",
        "tgn:7029392"
    ],
    "tgn:id":7009133,
    "tgn:name:en":"Ayr",
    "tgn:placetype":[
        "aat:300008347",
        "aat:300008416",
        "aat:300264742",
        "aat:300387220",
        "aat:300008375",
        "aat:300387249",
        "aat:300387302",
        "aat:300120599",
        "aat:300387291",
        "aat:300387286"
    ]
},
  "bbox": [],
  "geometry": {"coordinates":[-4.616667,55.45],"type":"Point"}
}