{
  "id": 2463709,
  "type": "Feature",
  "properties": {
    "tgn:hierarchy":[
        "tgn:2463709",
        "tgn:1000001",
        "tgn:7012149",
        "tgn:7007710",
        "tgn:7029392"
    ],
    "tgn:id":2463709,
    "tgn:name":"Lock Ridge",
    "tgn:placetype":[
        "aat:300266640"
    ]
},
  "bbox": [],
  "geometry": {"coordinates":[-77.1833,40.5833],"type":"Point"}
}