{
  "id": 2634727,
  "type": "Feature",
  "properties": {
    "tgn:hierarchy":[
        "tgn:2634727",
        "tgn:1000001",
        "tgn:7012149",
        "tgn:1003038",
        "tgn:7007517",
        "tgn:7029392"
    ],
    "tgn:id":2634727,
    "tgn:name":"Rutland Brook",
    "tgn:placetype":[
        "aat:300008699"
    ]
},
  "bbox": [],
  "geometry": {"coordinates":[-72.1167,42.4333],"type":"Point"}
}