<<<<<<< HEAD
{
  "id": 7480672,
  "type": "Feature",
  "properties": {
    "tgn:hierarchy":[
        "tgn:7480672",
        "tgn:7468018",
        "tgn:1000004",
        "tgn:1000141",
        "tgn:7029392"
    ],
    "tgn:id":7480672,
    "tgn:name":"Budai Guoxiao",
    "tgn:placetype":[
        "aat:300006495"
    ]
},
  "bbox": [],
  "geometry": {"coordinates":[120.1721,23.3814],"type":"Point"}
}
=======
{"geometry":{"type":"Point","coordinates":[120.172100,23.381400]},"type":"Feature","properties":{"hierarchy":["tgn:7480672","tgn:7468018","tgn:1000004","tgn:1000141","tgn:7029392"],"placetype":["aat:300006495"],"id":7480672,"name:xx":"Budai Guoxiao"}}
>>>>>>> 03f74aca74312dbeaf24d7e61306dd6a786dc3d0
