{
  "id": 2443965,
  "type": "Feature",
  "properties": {
    "tgn:hierarchy":[
        "tgn:2443965",
        "tgn:1000001",
        "tgn:7006451",
        "tgn:7012149",
        "tgn:2000097",
        "tgn:7029392"
    ],
    "tgn:id":2443965,
    "tgn:name":"La Terraza",
    "tgn:placetype":[
        "aat:300008347"
    ]
},
  "bbox": [],
  "geometry": {"coordinates":[-112.1833,33.45],"type":"Point"}
}