{
  "id": 7505574,
  "type": "Feature",
  "properties": {
    "tgn:hierarchy":[
        "tgn:7505574",
        "tgn:1008380",
        "tgn:7000507",
        "tgn:1000226",
        "tgn:1000006",
        "tgn:7029392"
    ],
    "tgn:id":7505574,
    "tgn:name:en":"Whangaroa Peninsula",
    "tgn:placetype":[
        "aat:300008804"
    ]
},
  "bbox": [],
  "geometry": {"coordinates":[174.383333,-35.366667],"type":"Point"}
}