{
  "id": 7403818,
  "type": "Feature",
  "properties": {
    "tgn:hierarchy":[
        "tgn:7403818",
        "tgn:7005578",
        "tgn:1000001",
        "tgn:7005560",
        "tgn:7029392"
    ],
    "tgn:id":7403818,
    "tgn:name":"El Morrongo",
    "tgn:placetype":[
        "aat:300008347"
    ]
},
  "bbox": [],
  "geometry": {"coordinates":[-90.958333,18.816667],"type":"Point"}
}