{
  "id": 2285011,
  "type": "Feature",
  "properties": {
    "tgn:hierarchy":[
        "tgn:2285011",
        "tgn:1000001",
        "tgn:7012149",
        "tgn:7007157",
        "tgn:1002684",
        "tgn:7029392"
    ],
    "tgn:id":2285011,
    "tgn:name":"Devil Hill",
    "tgn:placetype":[
        "aat:300008798"
    ]
},
  "bbox": [],
  "geometry": {"coordinates":[-121.8833,36.55],"type":"Point"}
}