{
  "id": 2584724,
  "type": "Feature",
  "properties": {
    "tgn:hierarchy":[
        "tgn:2584724",
        "tgn:1000001",
        "tgn:7012149",
        "tgn:2002250",
        "tgn:7007920",
        "tgn:7029392"
    ],
    "tgn:id":2584724,
    "tgn:name":"Pingston Creek",
    "tgn:placetype":[
        "aat:300008706"
    ]
},
  "bbox": [],
  "geometry": {"coordinates":[-117.9667,48.65],"type":"Point"}
}