{
  "id": 7539409,
  "type": "Feature",
  "properties": {
    "tgn:hierarchy":[
        "tgn:7539409",
        "tgn:7001242",
        "tgn:7016833",
        "tgn:7001336",
        "tgn:7029392"
    ],
    "tgn:id":7539409,
    "tgn:name:en":"Qad Ibn Hadd\u0101n",
    "tgn:placetype":[
        "aat:300008808"
    ]
},
  "bbox": [],
  "geometry": {"coordinates":[34.09288,27.790564],"type":"Point"}
}