{
  "id": 2275444,
  "type": "Feature",
  "properties": {
    "tgn:hierarchy":[
        "tgn:2275444",
        "tgn:7002659",
        "tgn:1000001",
        "tgn:7012149",
        "tgn:2000031",
        "tgn:7029392"
    ],
    "tgn:id":2275444,
    "tgn:name":"Danoe Branch",
    "tgn:placetype":[
        "aat:300008699"
    ]
},
  "bbox": [],
  "geometry": {"coordinates":[-87.95,32.85],"type":"Point"}
}