{
  "id": 7400737,
  "type": "Feature",
  "properties": {
    "tgn:hierarchy":[
        "tgn:7400737",
        "tgn:1000001",
        "tgn:7005599",
        "tgn:7005560",
        "tgn:7029392"
    ],
    "tgn:id":7400737,
    "tgn:name":"La Palma",
    "tgn:placetype":[
        "aat:300008347"
    ]
},
  "bbox": [],
  "geometry": {"coordinates":[-95.058333,18.55],"type":"Point"}
}