{
  "id": 7580001,
  "type": "Feature",
  "properties": {
    "tgn:hierarchy":[
        "tgn:7580001",
        "tgn:1000004",
        "tgn:1001869",
        "tgn:7000198",
        "tgn:7029392"
    ],
    "tgn:id":7580001,
    "tgn:name:en":"Ut\u0101vli River",
    "tgn:placetype":[
        "aat:300008699"
    ]
},
  "bbox": [],
  "geometry": {"coordinates":[71.833333,22.183333],"type":"Point"}
}