{
  "id": 7315747,
  "type": "Feature",
  "properties": {
    "tgn:hierarchy":[
        "tgn:7315747",
        "tgn:1001695",
        "tgn:1000049",
        "tgn:1000002",
        "tgn:7029392"
    ],
    "tgn:id":7315747,
    "tgn:name":"Cerrillos",
    "tgn:placetype":[
        "aat:300008347"
    ]
},
  "bbox": [],
  "geometry": {"coordinates":[-70.983333,-34.25],"type":"Point"}
}