{
  "id": 7243124,
  "type": "Feature",
  "properties": {
    "tgn:hierarchy":[
        "tgn:7243124",
        "tgn:7007877",
        "tgn:1000003",
        "tgn:1000063",
        "tgn:4012014",
        "tgn:7029392"
    ],
    "tgn:id":7243124,
    "tgn:name":"Lumenne",
    "tgn:placetype":[
        "aat:300008347"
    ]
},
  "bbox": [],
  "geometry": {"coordinates":[3.722255,50.763557],"type":"Point"}
}