<<<<<<< HEAD
{
  "id": 2153343,
  "type": "Feature",
  "properties": {
    "tgn:hierarchy":[
        "tgn:2153343",
        "tgn:1000001",
        "tgn:7012149",
        "tgn:2001722",
        "tgn:7007708",
        "tgn:7029392"
    ],
    "tgn:id":2153343,
    "tgn:name":"Bean Creek",
    "tgn:placetype":[
        "aat:300008706"
    ]
},
  "bbox": [],
  "geometry": {"coordinates":[-116.6,45.75],"type":"Point"}
}
=======
{"geometry":{"type":"Point","coordinates":[-116.600000,45.750000]},"type":"Feature","properties":{"hierarchy":["tgn:2153343","tgn:1000001","tgn:7012149","tgn:2001722","tgn:7007708","tgn:7029392"],"placetype":["aat:300008706"],"id":2153343,"name:xx":"Bean Creek"}}
>>>>>>> 03f74aca74312dbeaf24d7e61306dd6a786dc3d0
