{
  "id": 2495365,
  "type": "Feature",
  "properties": {
    "tgn:hierarchy":[
        "tgn:2495365",
        "tgn:1000001",
        "tgn:7012149",
        "tgn:2000225",
        "tgn:7007158",
        "tgn:7029392"
    ],
    "tgn:id":2495365,
    "tgn:name":"Mary S Mine",
    "tgn:placetype":[
        "aat:300000390"
    ]
},
  "bbox": [],
  "geometry": {"coordinates":[-107.95,37.4333],"type":"Point"}
}