{
  "id": 7032081,
  "type": "Feature",
  "properties": {
    "tgn:hierarchy":[
        "tgn:7032081",
        "tgn:1000003",
        "tgn:7003515",
        "tgn:7029392"
    ],
    "tgn:id":7032081,
    "tgn:name":"Mauren",
    "tgn:placetype":[
        "aat:300387064",
        "aat:300387330"
    ]
},
  "bbox": [],
  "geometry": {"coordinates":[9.558,47.215],"type":"Point"}
}