{
  "id": 2127344,
  "type": "Feature",
  "properties": {
    "tgn:hierarchy":[
        "tgn:2127344",
        "tgn:1000001",
        "tgn:7012149",
        "tgn:2002341",
        "tgn:7007922",
        "tgn:7029392"
    ],
    "tgn:id":2127344,
    "tgn:name":"Ajax Island",
    "tgn:placetype":[
        "aat:300008791"
    ]
},
  "bbox": [],
  "geometry": {"coordinates":[-87.85,44.8833],"type":"Point"}
}