{
  "id": 2630586,
  "type": "Feature",
  "properties": {
    "tgn:hierarchy":[
        "tgn:2630586",
        "tgn:1000001",
        "tgn:7012149",
        "tgn:2002114",
        "tgn:7007827",
        "tgn:7029392"
    ],
    "tgn:id":2630586,
    "tgn:name":"Round Hill",
    "tgn:placetype":[
        "aat:300008798"
    ]
},
  "bbox": [],
  "geometry": {"coordinates":[-112.0833,39.05],"type":"Point"}
}