{
  "id": 2176228,
  "type": "Feature",
  "properties": {
    "tgn:hierarchy":[
        "tgn:2176228",
        "tgn:1000001",
        "tgn:7012149",
        "tgn:2001440",
        "tgn:7007566",
        "tgn:7029392"
    ],
    "tgn:id":2176228,
    "tgn:name":"Black Hills",
    "tgn:placetype":[
        "aat:300386831"
    ]
},
  "bbox": [],
  "geometry": {"coordinates":[-108.8667,32.5833],"type":"Point"}
}