{
  "id": 7435965,
  "type": "Feature",
  "properties": {
    "tgn:hierarchy":[
        "tgn:7435965",
        "tgn:1000001",
        "tgn:1001960",
        "tgn:7005560",
        "tgn:7029392"
    ],
    "tgn:id":7435965,
    "tgn:name":"Tesota, Cerro",
    "tgn:placetype":[
        "aat:300008795"
    ]
},
  "bbox": [],
  "geometry": {"coordinates":[-111.883333,30.35],"type":"Point"}
}