<<<<<<< HEAD
{
  "id": 7178132,
  "type": "Feature",
  "properties": {
    "tgn:hierarchy":[
        "tgn:7178132",
        "tgn:7003669",
        "tgn:1000003",
        "tgn:7000084",
        "tgn:7029392"
    ],
    "tgn:id":7178132,
    "tgn:name":"Gundihausen",
    "tgn:placetype":[
        "aat:300008347"
    ]
},
  "bbox": [],
  "geometry": {"coordinates":[12.133333,48.45],"type":"Point"}
}
=======
{"geometry":{"type":"Point","coordinates":[12.133333,48.450000]},"type":"Feature","properties":{"hierarchy":["tgn:7178132","tgn:7003669","tgn:1000003","tgn:7000084","tgn:7029392"],"placetype":["aat:300008347"],"id":7178132,"name:xx":"Gundihausen"}}
>>>>>>> 03f74aca74312dbeaf24d7e61306dd6a786dc3d0
