{
  "id": 1025173,
  "type": "Feature",
  "properties": {
    "tgn:hierarchy":[
        "tgn:1025173",
        "tgn:1001861",
        "tgn:1000002",
        "tgn:1000059",
        "tgn:7029392"
    ],
    "tgn:id":1025173,
    "tgn:name":"La Vela de Coro",
    "tgn:placetype":[
        "aat:300008347"
    ]
},
  "bbox": [],
  "geometry": {"coordinates":[-69.5667,11.45],"type":"Point"}
}