{
  "id": 2701076,
  "type": "Feature",
  "properties": {
    "tgn:hierarchy":[
        "tgn:2701076",
        "tgn:1000001",
        "tgn:7012149",
        "tgn:2002287",
        "tgn:7013961",
        "tgn:7029392"
    ],
    "tgn:id":2701076,
    "tgn:name":"Sugar Creek",
    "tgn:placetype":[
        "aat:300008706"
    ]
},
  "bbox": [],
  "geometry": {"coordinates":[-80.2333,38.2833],"type":"Point"}
}