{
  "id": 2250142,
  "type": "Feature",
  "properties": {
    "tgn:hierarchy":[
        "tgn:2250142",
        "tgn:1000001",
        "tgn:7012149",
        "tgn:7007255",
        "tgn:7029392"
    ],
    "tgn:id":2250142,
    "tgn:name":"Collins Fork",
    "tgn:placetype":[
        "aat:300008699"
    ]
},
  "bbox": [],
  "geometry": {"coordinates":[-83.8667,36.95],"type":"Point"}
}