{
  "id": 2725290,
  "type": "Feature",
  "properties": {
    "tgn:hierarchy":[
        "tgn:2725290",
        "tgn:1000001",
        "tgn:2001435",
        "tgn:7012149",
        "tgn:7007566",
        "tgn:7029392"
    ],
    "tgn:id":2725290,
    "tgn:name":"Tonuco Mountains",
    "tgn:placetype":[
        "aat:300386831"
    ]
},
  "bbox": [],
  "geometry": {"coordinates":[-106.9667,32.5833],"type":"Point"}
}