{
  "id": 7118927,
  "type": "Feature",
  "properties": {
    "tgn:hierarchy":[
        "tgn:7118927",
        "tgn:7000096",
        "tgn:1000003",
        "tgn:7000084",
        "tgn:7029392"
    ],
    "tgn:id":7118927,
    "tgn:name":"Pessiner Heide",
    "tgn:placetype":[
        "aat:300008863"
    ]
},
  "bbox": [],
  "geometry": {"coordinates":[12.683333,52.666667],"type":"Point"}
}