<<<<<<< HEAD
{
  "id": 7118927,
  "type": "Feature",
  "properties": {
    "tgn:hierarchy":[
        "tgn:7118927",
        "tgn:7000096",
        "tgn:1000003",
        "tgn:7000084",
        "tgn:7029392"
    ],
    "tgn:id":7118927,
    "tgn:name":"Pessiner Heide",
    "tgn:placetype":[
        "aat:300008863"
    ]
},
  "bbox": [],
  "geometry": {"coordinates":[12.683333,52.666667],"type":"Point"}
}
=======
{"geometry":{"type":"Point","coordinates":[12.683333,52.666667]},"type":"Feature","properties":{"hierarchy":["tgn:7118927","tgn:7000096","tgn:1000003","tgn:7000084","tgn:7029392"],"placetype":["aat:300008863"],"id":7118927,"name:xx":"Pessiner Heide"}}
>>>>>>> 03f74aca74312dbeaf24d7e61306dd6a786dc3d0
