{
  "id": 2647631,
  "type": "Feature",
  "properties": {
    "tgn:hierarchy":[
        "tgn:2647631",
        "tgn:1000001",
        "tgn:2002367",
        "tgn:7012149",
        "tgn:7007923",
        "tgn:7029392"
    ],
    "tgn:id":2647631,
    "tgn:name":"School Creek",
    "tgn:placetype":[
        "aat:300008706"
    ]
},
  "bbox": [],
  "geometry": {"coordinates":[-105.15,43.5667],"type":"Point"}
}