{
  "id": 7115048,
  "type": "Feature",
  "properties": {
    "tgn:hierarchy":[
        "tgn:7115048",
        "tgn:1000003",
        "tgn:7003688",
        "tgn:7000084",
        "tgn:7029392"
    ],
    "tgn:id":7115048,
    "tgn:name":"Osterhavetoft",
    "tgn:placetype":[
        "aat:300000206"
    ]
},
  "bbox": [],
  "geometry": {"coordinates":[9.533333,54.65],"type":"Point"}
}