<<<<<<< HEAD
{
  "id": 7024942,
  "type": "Feature",
  "properties": {
    "tgn:hierarchy":[
        "tgn:7024942",
        "tgn:7002445",
        "tgn:7008103",
        "tgn:1000003",
        "tgn:7008591",
        "tgn:7029392"
    ],
    "tgn:id":7024942,
    "tgn:name":"Harlington",
    "tgn:name:ang":"Herlingdone",
    "tgn:placetype":[
        "aat:300008347"
    ]
},
  "bbox": [],
  "geometry": {"coordinates":[-0.483333,51.95],"type":"Point"}
}
=======
{"geometry":{"type":"Point","coordinates":[-0.483333,51.950000]},"type":"Feature","properties":{"hierarchy":["tgn:7024942","tgn:7002445","tgn:7008103","tgn:1000003","tgn:7008591","tgn:7029392"],"placetype":["aat:300008347"],"id":7024942,"name:xx":"Harlington","name:ang":"Herlingdone"}}
>>>>>>> 03f74aca74312dbeaf24d7e61306dd6a786dc3d0
