{
  "id": 2759266,
  "type": "Feature",
  "properties": {
    "tgn:hierarchy":[
        "tgn:2759266",
        "tgn:1000001",
        "tgn:7012149",
        "tgn:7029392"
    ],
    "tgn:id":2759266,
    "tgn:name":"West Fork Chestnut Creek",
    "tgn:placetype":[
        "aat:300008706"
    ]
},
  "bbox": [],
  "geometry": {"coordinates":[-80.9167,36.5333],"type":"Point"}
}