<<<<<<< HEAD
{
  "id": 7175871,
  "type": "Feature",
  "properties": {
    "tgn:hierarchy":[
        "tgn:7175871",
        "tgn:1000003",
        "tgn:7003676",
        "tgn:7000084",
        "tgn:7029392"
    ],
    "tgn:id":7175871,
    "tgn:name":"Gro\u00dfe Schweimke",
    "tgn:placetype":[
        "aat:300008699"
    ]
},
  "bbox": [],
  "geometry": {"coordinates":[10.3,51.7],"type":"Point"}
}
=======
{"geometry":{"type":"Point","coordinates":[10.300000,51.700000]},"type":"Feature","properties":{"hierarchy":["tgn:7175871","tgn:1000003","tgn:7003676","tgn:7000084","tgn:7029392"],"placetype":["aat:300008699"],"id":7175871,"name:xx":"Gro\u00dfe Schweimke"}}
>>>>>>> 03f74aca74312dbeaf24d7e61306dd6a786dc3d0
