{
  "id": 2487331,
  "type": "Feature",
  "properties": {
    "tgn:hierarchy":[
        "tgn:2487331",
        "tgn:1000001",
        "tgn:2000775",
        "tgn:7012149",
        "tgn:7007255",
        "tgn:7029392"
    ],
    "tgn:id":2487331,
    "tgn:name":"Leetown",
    "tgn:placetype":[
        "aat:300008347"
    ]
},
  "bbox": [],
  "geometry": {"coordinates":[-86.7333,37.1333],"type":"Point"}
}