{
  "id": 2190195,
  "type": "Feature",
  "properties": {
    "tgn:hierarchy":[
        "tgn:2190195",
        "tgn:1000001",
        "tgn:7012149",
        "tgn:1002817",
        "tgn:7007523",
        "tgn:7029392"
    ],
    "tgn:id":2190195,
    "tgn:name":"Bowmans Lake",
    "tgn:placetype":[
        "aat:300006191"
    ]
},
  "bbox": [],
  "geometry": {"coordinates":[-91.45,39.6333],"type":"Point"}
}