{
  "id": 7409533,
  "type": "Feature",
  "properties": {
    "tgn:hierarchy":[
        "tgn:7409533",
        "tgn:1000001",
        "tgn:7005590",
        "tgn:7005560",
        "tgn:7029392"
    ],
    "tgn:id":7409533,
    "tgn:name":"El Bellotal",
    "tgn:placetype":[
        "aat:300008347"
    ]
},
  "bbox": [],
  "geometry": {"coordinates":[-100.233333,20.148611],"type":"Point"}
}