{
  "id": 7038452,
  "type": "Feature",
  "properties": {
    "tgn:hierarchy":[
        "tgn:7038452",
        "tgn:7003170",
        "tgn:1000003",
        "tgn:7003125",
        "tgn:1000080",
        "tgn:7029392"
    ],
    "tgn:id":7038452,
    "tgn:name":"Tolagna, Monte",
    "tgn:placetype":[
        "aat:300008795"
    ]
},
  "bbox": [],
  "geometry": {"coordinates":[12.95,42.983333],"type":"Point"}
}