{
  "id": 7299025,
  "type": "Feature",
  "properties": {
    "tgn:hierarchy":[
        "tgn:7299025",
        "tgn:7002811",
        "tgn:1000003",
        "tgn:7003837",
        "tgn:1000095",
        "tgn:7029392"
    ],
    "tgn:id":7299025,
    "tgn:name":"Trampal, Puerto del",
    "tgn:placetype":[
        "aat:300259572"
    ]
},
  "bbox": [],
  "geometry": {"coordinates":[-6.283333,39.166667],"type":"Point"}
}