{
  "id": 2692040,
  "type": "Feature",
  "properties": {
    "tgn:hierarchy":[
        "tgn:2692040",
        "tgn:1000001",
        "tgn:7012149",
        "tgn:2001718",
        "tgn:7007708",
        "tgn:7029392"
    ],
    "tgn:id":2692040,
    "tgn:name":"State Line Reservoir",
    "tgn:placetype":[
        "aat:300006191"
    ]
},
  "bbox": [],
  "geometry": {"coordinates":[-117.05,42.45],"type":"Point"}
}