{
  "id": 7436744,
  "type": "Feature",
  "properties": {
    "tgn:hierarchy":[
        "tgn:7436744",
        "tgn:1000001",
        "tgn:7005595",
        "tgn:7005560",
        "tgn:7029392"
    ],
    "tgn:id":7436744,
    "tgn:name":"Sivirojoa",
    "tgn:placetype":[
        "aat:300008347"
    ]
},
  "bbox": [],
  "geometry": {"coordinates":[-108.766667,26.183333],"type":"Point"}
}