{
  "id": 2489673,
  "type": "Feature",
  "properties": {
    "tgn:hierarchy":[
        "tgn:2489673",
        "tgn:1000001",
        "tgn:7012149",
        "tgn:1002481",
        "tgn:7007520",
        "tgn:7029392"
    ],
    "tgn:id":2489673,
    "tgn:name":"Mallory Lake Drain",
    "tgn:placetype":[
        "aat:300008699"
    ]
},
  "bbox": [],
  "geometry": {"coordinates":[-84.3833,41.8167],"type":"Point"}
}