{
  "id": 7124056,
  "type": "Feature",
  "properties": {
    "tgn:hierarchy":[
        "tgn:7124056",
        "tgn:7003669",
        "tgn:1000003",
        "tgn:7000084",
        "tgn:7029392"
    ],
    "tgn:id":7124056,
    "tgn:name":"Nieder-Hasling",
    "tgn:placetype":[
        "aat:300000206"
    ]
},
  "bbox": [],
  "geometry": {"coordinates":[12.916667,48.266667],"type":"Point"}
}