{
  "id": 7242208,
  "type": "Feature",
  "properties": {
    "tgn:hierarchy":[
        "tgn:7242208",
        "tgn:7003457",
        "tgn:1000003",
        "tgn:1000063",
        "tgn:7018236",
        "tgn:7029392"
    ],
    "tgn:id":7242208,
    "tgn:name":"Loever",
    "tgn:placetype":[
        "aat:300008347"
    ]
},
  "bbox": [],
  "geometry": {"coordinates":[4.10557,51.215275],"type":"Point"}
}