{
  "id": 2442926,
  "type": "Feature",
  "properties": {
    "tgn:hierarchy":[
        "tgn:2442926",
        "tgn:1000001",
        "tgn:1002236",
        "tgn:7012149",
        "tgn:7007252",
        "tgn:7029392"
    ],
    "tgn:id":2442926,
    "tgn:name":"Kuns Ditch",
    "tgn:placetype":[
        "aat:300006075"
    ]
},
  "bbox": [],
  "geometry": {"coordinates":[-86.5167,40.5333],"type":"Point"}
}