{
  "id": 2181748,
  "type": "Feature",
  "properties": {
    "tgn:hierarchy":[
        "tgn:2181748",
        "tgn:1000001",
        "tgn:7020676",
        "tgn:7012149",
        "tgn:7007256",
        "tgn:7029392"
    ],
    "tgn:id":2181748,
    "tgn:name":"Blue Islands",
    "tgn:placetype":[
        "aat:300386853"
    ]
},
  "bbox": [],
  "geometry": {"coordinates":[-93.65,29.95],"type":"Point"}
}