{
  "id": 2611993,
  "type": "Feature",
  "properties": {
    "tgn:hierarchy":[
        "tgn:2611993",
        "tgn:1000001",
        "tgn:7012149",
        "tgn:2002122",
        "tgn:7007827",
        "tgn:7029392"
    ],
    "tgn:id":2611993,
    "tgn:name":"Red Rock",
    "tgn:placetype":[
        "aat:300008798"
    ]
},
  "bbox": [],
  "geometry": {"coordinates":[-111.1667,41.15],"type":"Point"}
}