{
  "id": 7518412,
  "type": "Feature",
  "properties": {
    "tgn:hierarchy":[
        "tgn:7518412",
        "tgn:1008380",
        "tgn:1000226",
        "tgn:7000512",
        "tgn:1000006",
        "tgn:7029392"
    ],
    "tgn:id":7518412,
    "tgn:name:en":"Matarawa",
    "tgn:placetype":[
        "aat:300008347"
    ]
},
  "bbox": [],
  "geometry": {"coordinates":[175.45,-41.05],"type":"Point"}
}