{
  "id": 7219241,
  "type": "Feature",
  "properties": {
    "tgn:hierarchy":[
        "tgn:7219241",
        "tgn:7011270",
        "tgn:7002674",
        "tgn:1000003",
        "tgn:1000074",
        "tgn:7029392"
    ],
    "tgn:id":7219241,
    "tgn:name":"V\u00f3thonas",
    "tgn:placetype":[
        "aat:300008347"
    ]
},
  "bbox": [],
  "geometry": {"coordinates":[25.450135,36.394188],"type":"Point"}
}