{
  "id": 2565750,
  "type": "Feature",
  "properties": {
    "tgn:hierarchy":[
        "tgn:2565750",
        "tgn:1007657",
        "tgn:1002534",
        "tgn:1000001",
        "tgn:7012149",
        "tgn:7007249",
        "tgn:7029392"
    ],
    "tgn:id":2565750,
    "tgn:name":"Palehua",
    "tgn:placetype":[
        "aat:300008798"
    ]
},
  "bbox": [],
  "geometry": {"coordinates":[-159.5167,22.0333],"type":"Point"}
}