{
  "id": 7282745,
  "type": "Feature",
  "properties": {
    "tgn:hierarchy":[
        "tgn:7282745",
        "tgn:1001699",
        "tgn:1000049",
        "tgn:1000002",
        "tgn:7029392"
    ],
    "tgn:id":7282745,
    "tgn:name":"Pe\u00f1a Sola, Roca",
    "tgn:placetype":[
        "aat:300011692"
    ]
},
  "bbox": [],
  "geometry": {"coordinates":[-73.466667,-39.833333],"type":"Point"}
}