{
  "id": 7410915,
  "type": "Feature",
  "properties": {
    "tgn:hierarchy":[
        "tgn:7410915",
        "tgn:7005587",
        "tgn:1000001",
        "tgn:7005560",
        "tgn:7029392"
    ],
    "tgn:id":7410915,
    "tgn:name:es":"El \u00c1lamo",
    "tgn:placetype":[
        "aat:300008347"
    ]
},
  "bbox": [],
  "geometry": {"coordinates":[-99.408333,20.745833],"type":"Point"}
}