{
  "id": 7431293,
  "type": "Feature",
  "properties": {
    "tgn:hierarchy":[
        "tgn:7431293",
        "tgn:7005581",
        "tgn:1000001",
        "tgn:7005560",
        "tgn:7029392"
    ],
    "tgn:id":7431293,
    "tgn:name":"Alfredo V. Bonfil",
    "tgn:placetype":[
        "aat:300008347"
    ]
},
  "bbox": [],
  "geometry": {"coordinates":[-106.583333,31.783333],"type":"Point"}
}