<<<<<<< HEAD
{
  "id": 2259301,
  "type": "Feature",
  "properties": {
    "tgn:hierarchy":[
        "tgn:2259301",
        "tgn:1000001",
        "tgn:7012149",
        "tgn:2002110",
        "tgn:7007827",
        "tgn:7029392"
    ],
    "tgn:id":2259301,
    "tgn:name":"Cottonwood Point",
    "tgn:placetype":[
        "aat:300008798"
    ]
},
  "bbox": [],
  "geometry": {"coordinates":[-109.6,39.15],"type":"Point"}
}
=======
{"geometry":{"type":"Point","coordinates":[-109.600000,39.150000]},"type":"Feature","properties":{"hierarchy":["tgn:2259301","tgn:1000001","tgn:7012149","tgn:2002110","tgn:7007827","tgn:7029392"],"placetype":["aat:300008798"],"id":2259301,"name:xx":"Cottonwood Point"}}
>>>>>>> 03f74aca74312dbeaf24d7e61306dd6a786dc3d0
