{
  "id": 7420809,
  "type": "Feature",
  "properties": {
    "tgn:hierarchy":[
        "tgn:7420809",
        "tgn:1001836",
        "tgn:1000001",
        "tgn:7005560",
        "tgn:7029392"
    ],
    "tgn:id":7420809,
    "tgn:name":"Las \u00c1nimas, Mesa",
    "tgn:placetype":[
        "aat:300008811"
    ]
},
  "bbox": [],
  "geometry": {"coordinates":[-111.6875,25.953056],"type":"Point"}
}