{
  "id": 2242330,
  "type": "Feature",
  "properties": {
    "tgn:hierarchy":[
        "tgn:2242330",
        "tgn:1000001",
        "tgn:7012149",
        "tgn:2000885",
        "tgn:7007256",
        "tgn:7029392"
    ],
    "tgn:id":2242330,
    "tgn:name":"Clayton Bayou",
    "tgn:placetype":[
        "aat:300008699"
    ]
},
  "bbox": [],
  "geometry": {"coordinates":[-90.95,30.5667],"type":"Point"}
}