{
  "id": 7304664,
  "type": "Feature",
  "properties": {
    "tgn:hierarchy":[
        "tgn:7304664",
        "tgn:7002842",
        "tgn:7001158",
        "tgn:1000003",
        "tgn:1000095",
        "tgn:7029392"
    ],
    "tgn:id":7304664,
    "tgn:name":"Ledrado",
    "tgn:placetype":[
        "aat:300008347"
    ]
},
  "bbox": [],
  "geometry": {"coordinates":[-2.383333,42.016667],"type":"Point"}
}