{
  "id": 1033821,
  "type": "Feature",
  "properties": {
    "tgn:hierarchy":[
        "tgn:1033821",
        "tgn:1000003",
        "tgn:7002888",
        "tgn:1000070",
        "tgn:7029392"
    ],
    "tgn:id":1033821,
    "tgn:name":"Ban-Saint-Martin",
    "tgn:placetype":[
        "aat:300008347"
    ]
},
  "bbox": [],
  "geometry": {"coordinates":[6.15,49.1167],"type":"Point"}
}