{
  "id": 2012654,
  "type": "Feature",
  "properties": {
    "tgn:hierarchy":[
        "tgn:2012654",
        "tgn:1002146",
        "tgn:1000001",
        "tgn:7012149",
        "tgn:7007157",
        "tgn:7029392"
    ],
    "tgn:id":2012654,
    "tgn:name":"Bonnefoy",
    "tgn:placetype":[
        "aat:300008347"
    ]
},
  "bbox": [],
  "geometry": {"coordinates":[-120.75,38.35],"type":"Point"}
}