{
  "id": 2786063,
  "type": "Feature",
  "properties": {
    "tgn:hierarchy":[
        "tgn:2786063",
        "tgn:1000001",
        "tgn:7012149",
        "tgn:2000226",
        "tgn:7007158",
        "tgn:7029392"
    ],
    "tgn:id":2786063,
    "tgn:name":"Young Gulch",
    "tgn:placetype":[
        "aat:300008761"
    ]
},
  "bbox": [],
  "geometry": {"coordinates":[-105.3167,40.6167],"type":"Point"}
}