{
  "id": 2315662,
  "type": "Feature",
  "properties": {
    "tgn:hierarchy":[
        "tgn:2315662",
        "tgn:1000001",
        "tgn:2002146",
        "tgn:7012149",
        "tgn:7007919",
        "tgn:7029392"
    ],
    "tgn:id":2315662,
    "tgn:name":"Ellis Run",
    "tgn:placetype":[
        "aat:300008699"
    ]
},
  "bbox": [],
  "geometry": {"coordinates":[-79.7333,37.4333],"type":"Point"}
}