{
  "id": 2320169,
  "type": "Feature",
  "properties": {
    "tgn:hierarchy":[
        "tgn:2320169",
        "tgn:1000001",
        "tgn:7012149",
        "tgn:2001881",
        "tgn:7007825",
        "tgn:7029392"
    ],
    "tgn:id":2320169,
    "tgn:name":"Evans Shoals",
    "tgn:placetype":[
        "aat:300132348"
    ]
},
  "bbox": [],
  "geometry": {"coordinates":[-83.2833,36.0333],"type":"Point"}
}