<<<<<<< HEAD
{
  "id": 2152322,
  "type": "Feature",
  "properties": {
    "tgn:hierarchy":[
        "tgn:2152322",
        "tgn:1000001",
        "tgn:7012149",
        "tgn:2001297",
        "tgn:7007524",
        "tgn:7029392"
    ],
    "tgn:id":2152322,
    "tgn:name":"Bay Horse Creek",
    "tgn:placetype":[
        "aat:300008706"
    ]
},
  "bbox": [],
  "geometry": {"coordinates":[-105.6,45.0333],"type":"Point"}
}
=======
{"geometry":{"type":"Point","coordinates":[-105.600000,45.033300]},"type":"Feature","properties":{"hierarchy":["tgn:2152322","tgn:1000001","tgn:7012149","tgn:2001297","tgn:7007524","tgn:7029392"],"placetype":["aat:300008706"],"id":2152322,"name:xx":"Bay Horse Creek"}}
>>>>>>> 03f74aca74312dbeaf24d7e61306dd6a786dc3d0
