<<<<<<< HEAD
{
  "id": 7171710,
  "type": "Feature",
  "properties": {
    "tgn:hierarchy":[
        "tgn:7171710",
        "tgn:1000003",
        "tgn:7003677",
        "tgn:7000084",
        "tgn:7029392"
    ],
    "tgn:id":7171710,
    "tgn:name":"Hembergen",
    "tgn:placetype":[
        "aat:300008347"
    ]
},
  "bbox": [],
  "geometry": {"coordinates":[7.6,52.15],"type":"Point"}
}
=======
{"geometry":{"type":"Point","coordinates":[7.600000,52.150000]},"type":"Feature","properties":{"hierarchy":["tgn:7171710","tgn:1000003","tgn:7003677","tgn:7000084","tgn:7029392"],"placetype":["aat:300008347"],"id":7171710,"name:xx":"Hembergen"}}
>>>>>>> 03f74aca74312dbeaf24d7e61306dd6a786dc3d0
