{
  "id": 7142863,
  "type": "Feature",
  "properties": {
    "tgn:hierarchy":[
        "tgn:7142863",
        "tgn:1000003",
        "tgn:7003682",
        "tgn:7000084",
        "tgn:7029392"
    ],
    "tgn:id":7142863,
    "tgn:name":"Lindenberg",
    "tgn:placetype":[
        "aat:300008347"
    ]
},
  "bbox": [],
  "geometry": {"coordinates":[8.098611,49.380278],"type":"Point"}
}