{
  "id": 2380598,
  "type": "Feature",
  "properties": {
    "tgn:hierarchy":[
        "tgn:2380598",
        "tgn:1000001",
        "tgn:2000925",
        "tgn:7012149",
        "tgn:7007515",
        "tgn:7029392"
    ],
    "tgn:id":2380598,
    "tgn:name":"Havener Ledge",
    "tgn:placetype":[
        "aat:300132348"
    ]
},
  "bbox": [],
  "geometry": {"coordinates":[-69.3667,44.0167],"type":"Point"}
}