{
  "id": 7282614,
  "type": "Feature",
  "properties": {
    "tgn:hierarchy":[
        "tgn:7282614",
        "tgn:7016598",
        "tgn:1000049",
        "tgn:1000002",
        "tgn:7029392"
    ],
    "tgn:id":7282614,
    "tgn:name":"Perdices, Cerro",
    "tgn:placetype":[
        "aat:300008795"
    ]
},
  "bbox": [],
  "geometry": {"coordinates":[-68.216667,-21.916667],"type":"Point"}
}