{
  "id": 2296863,
  "type": "Feature",
  "properties": {
    "tgn:hierarchy":[
        "tgn:2296863",
        "tgn:1000001",
        "tgn:7012149",
        "tgn:2001256",
        "tgn:7007523",
        "tgn:7029392"
    ],
    "tgn:id":2296863,
    "tgn:name":"Dry Creek",
    "tgn:placetype":[
        "aat:300008706"
    ]
},
  "bbox": [],
  "geometry": {"coordinates":[-92.8667,37.1667],"type":"Point"}
}