{
  "id": 7299616,
  "type": "Feature",
  "properties": {
    "tgn:hierarchy":[
        "tgn:7299616",
        "tgn:7002811",
        "tgn:1000003",
        "tgn:7003837",
        "tgn:1000095",
        "tgn:7029392"
    ],
    "tgn:id":7299616,
    "tgn:name":"Valderrey, Charca de",
    "tgn:placetype":[
        "aat:300008688"
    ]
},
  "bbox": [],
  "geometry": {"coordinates":[-6.216667,39.116667],"type":"Point"}
}