{
  "id": 2757893,
  "type": "Feature",
  "properties": {
    "tgn:hierarchy":[
        "tgn:2757893",
        "tgn:1000001",
        "tgn:2000958",
        "tgn:7012149",
        "tgn:7007520",
        "tgn:7029392"
    ],
    "tgn:id":2757893,
    "tgn:name":"West Branch Maple River",
    "tgn:placetype":[
        "aat:300008707"
    ]
},
  "bbox": [],
  "geometry": {"coordinates":[-84.9167,45.5167],"type":"Point"}
}