{
  "id": 2566499,
  "type": "Feature",
  "properties": {
    "tgn:hierarchy":[
        "tgn:2566499",
        "tgn:1000001",
        "tgn:2001599",
        "tgn:7012149",
        "tgn:7007705",
        "tgn:7029392"
    ],
    "tgn:id":2566499,
    "tgn:name":"Pamplin Hills",
    "tgn:placetype":[
        "aat:300386831"
    ]
},
  "bbox": [],
  "geometry": {"coordinates":[-101.05,46.0667],"type":"Point"}
}