{
  "id": 2628360,
  "type": "Feature",
  "properties": {
    "tgn:hierarchy":[
        "tgn:2628360",
        "tgn:7030515",
        "tgn:7006450",
        "tgn:1000001",
        "tgn:7012149",
        "tgn:7029392"
    ],
    "tgn:id":2628360,
    "tgn:name":"Rona Islands",
    "tgn:placetype":[
        "aat:300386853"
    ]
},
  "bbox": [],
  "geometry": {"coordinates":[-161.8333,54.9833],"type":"Point"}
}