{
  "id": 2704770,
  "type": "Feature",
  "properties": {
    "tgn:hierarchy":[
        "tgn:2704770",
        "tgn:1000001",
        "tgn:7012149",
        "tgn:1002784",
        "tgn:7007706",
        "tgn:7029392"
    ],
    "tgn:id":2704770,
    "tgn:name":"Sunset Hill Estate Lake",
    "tgn:placetype":[
        "aat:300006191"
    ]
},
  "bbox": [],
  "geometry": {"coordinates":[-83.1667,39.7833],"type":"Point"}
}