{
  "id": 2537830,
  "type": "Feature",
  "properties": {
    "tgn:hierarchy":[
        "tgn:2537830",
        "tgn:1000001",
        "tgn:2001009",
        "tgn:7012149",
        "tgn:7007521",
        "tgn:7029392"
    ],
    "tgn:id":2537830,
    "tgn:name":"Nellie Lake",
    "tgn:placetype":[
        "aat:300008680"
    ]
},
  "bbox": [],
  "geometry": {"coordinates":[-94.2167,46.9833],"type":"Point"}
}