{
  "id": 2418965,
  "type": "Feature",
  "properties": {
    "tgn:hierarchy":[
        "tgn:2418965",
        "tgn:1000001",
        "tgn:7012149",
        "tgn:2001979",
        "tgn:7007826",
        "tgn:7029392"
    ],
    "tgn:id":2418965,
    "tgn:name":"James Lake",
    "tgn:placetype":[
        "aat:300008680"
    ]
},
  "bbox": [],
  "geometry": {"coordinates":[-102.5167,31.9833],"type":"Point"}
}