{
  "id": 2082325,
  "type": "Feature",
  "properties": {
    "tgn:hierarchy":[
        "tgn:2082325",
        "tgn:1000001",
        "tgn:7012149",
        "tgn:1003039",
        "tgn:7007706",
        "tgn:7029392"
    ],
    "tgn:id":2082325,
    "tgn:name":"Upper Sandusky",
    "tgn:placetype":[
        "aat:300008347"
    ]
},
  "bbox": [],
  "geometry": {"coordinates":[-83.2667,40.8167],"type":"Point"}
}