{
  "id": 7283353,
  "type": "Feature",
  "properties": {
    "tgn:hierarchy":[
        "tgn:7283353",
        "tgn:7016598",
        "tgn:1000049",
        "tgn:1000002",
        "tgn:7029392"
    ],
    "tgn:id":7283353,
    "tgn:name":"Estaci\u00f3n Pan de Az\u00facar",
    "tgn:placetype":[
        "aat:300007783"
    ]
},
  "bbox": [],
  "geometry": {"coordinates":[-68.683333,-24.116667],"type":"Point"}
}