<<<<<<< HEAD
{
  "id": 2336785,
  "type": "Feature",
  "properties": {
    "tgn:hierarchy":[
        "tgn:2336785",
        "tgn:1000001",
        "tgn:7012149",
        "tgn:2001898",
        "tgn:7007825",
        "tgn:7029392"
    ],
    "tgn:id":2336785,
    "tgn:name":"Fourmile Bridge",
    "tgn:placetype":[
        "aat:300008347"
    ]
},
  "bbox": [],
  "geometry": {"coordinates":[-84.2167,35.5667],"type":"Point"}
}
=======
{"geometry":{"type":"Point","coordinates":[-84.216700,35.566700]},"type":"Feature","properties":{"hierarchy":["tgn:2336785","tgn:1000001","tgn:7012149","tgn:2001898","tgn:7007825","tgn:7029392"],"placetype":["aat:300008347"],"id":2336785,"name:xx":"Fourmile Bridge"}}
>>>>>>> 03f74aca74312dbeaf24d7e61306dd6a786dc3d0
