{
  "id": 2383301,
  "type": "Feature",
  "properties": {
    "tgn:hierarchy":[
        "tgn:2383301",
        "tgn:1000001",
        "tgn:7012149",
        "tgn:2001296",
        "tgn:7007524",
        "tgn:7029392"
    ],
    "tgn:id":2383301,
    "tgn:name":"Heart Butte",
    "tgn:placetype":[
        "aat:300008798"
    ]
},
  "bbox": [],
  "geometry": {"coordinates":[-112.9167,48.2333],"type":"Point"}
}