{
  "id": 7439032,
  "type": "Feature",
  "properties": {
    "tgn:hierarchy":[
        "tgn:7439032",
        "tgn:1000001",
        "tgn:1001960",
        "tgn:7005560",
        "tgn:7029392"
    ],
    "tgn:id":7439032,
    "tgn:name":"Tezal, Cerro",
    "tgn:placetype":[
        "aat:300008795"
    ]
},
  "bbox": [],
  "geometry": {"coordinates":[-111.233333,28.25],"type":"Point"}
}