{
  "id": 7568454,
  "type": "Feature",
  "properties": {
    "tgn:hierarchy":[
        "tgn:7568454",
        "tgn:1000004",
        "tgn:7000198",
        "tgn:7016788",
        "tgn:7029392"
    ],
    "tgn:id":7568454,
    "tgn:name:en":"Mitharia",
    "tgn:placetype":[
        "aat:300008347"
    ]
},
  "bbox": [],
  "geometry": {"coordinates":[73.921457,28.945845],"type":"Point"}
}