{
  "id": 2631004,
  "type": "Feature",
  "properties": {
    "tgn:hierarchy":[
        "tgn:2631004",
        "tgn:1000001",
        "tgn:7012149",
        "tgn:1003019",
        "tgn:7007826",
        "tgn:7029392"
    ],
    "tgn:id":2631004,
    "tgn:name":"Round Mott",
    "tgn:placetype":[
        "aat:300008347"
    ]
},
  "bbox": [],
  "geometry": {"coordinates":[-96.45,29.2167],"type":"Point"}
}