{
  "id": 2112590,
  "type": "Feature",
  "properties": {
    "tgn:hierarchy":[
        "tgn:2112590",
        "tgn:1000001",
        "tgn:7012149",
        "tgn:1002511",
        "tgn:7007919",
        "tgn:7029392"
    ],
    "tgn:id":2112590,
    "tgn:name":"Lakewood",
    "tgn:placetype":[
        "aat:300008347",
        "aat:300387210"
    ]
},
  "bbox": [],
  "geometry": {"coordinates":[-76.75,37.2333],"type":"Point"}
}