<<<<<<< HEAD
{
  "id": 7242758,
  "type": "Feature",
  "properties": {
    "tgn:hierarchy":[
        "tgn:7242758",
        "tgn:7003465",
        "tgn:1000003",
        "tgn:1000063",
        "tgn:4012014",
        "tgn:7029392"
    ],
    "tgn:id":7242758,
    "tgn:name":"Les Buissons",
    "tgn:placetype":[
        "aat:300008347"
    ]
},
  "bbox": [],
  "geometry": {"coordinates":[5.533333,49.883333],"type":"Point"}
}
=======
{"geometry":{"type":"Point","coordinates":[5.533333,49.883333]},"type":"Feature","properties":{"hierarchy":["tgn:7242758","tgn:7003465","tgn:1000003","tgn:1000063","tgn:4012014","tgn:7029392"],"placetype":["aat:300008347"],"id":7242758,"name:xx":"Les Buissons"}}
>>>>>>> 03f74aca74312dbeaf24d7e61306dd6a786dc3d0
