{
  "id": 7242758,
  "type": "Feature",
  "properties": {
    "tgn:hierarchy":[
        "tgn:7242758",
        "tgn:7003465",
        "tgn:1000003",
        "tgn:1000063",
        "tgn:4012014",
        "tgn:7029392"
    ],
    "tgn:id":7242758,
    "tgn:name":"Les Buissons",
    "tgn:placetype":[
        "aat:300008347"
    ]
},
  "bbox": [],
  "geometry": {"coordinates":[5.533333,49.883333],"type":"Point"}
}