{
  "id": 1108099,
  "type": "Feature",
  "properties": {
    "tgn:hierarchy":[
        "tgn:1108099",
        "tgn:7004732",
        "tgn:1000004",
        "tgn:7004542",
        "tgn:1000111",
        "tgn:7029392"
    ],
    "tgn:id":1108099,
    "tgn:name":"Sz Tsz Shan",
    "tgn:placetype":[
        "aat:300008777"
    ]
},
  "bbox": [],
  "geometry": {"coordinates":[114.1833,22.35],"type":"Point"}
}