{
  "id": 2496353,
  "type": "Feature",
  "properties": {
    "tgn:hierarchy":[
        "tgn:2496353",
        "tgn:1000001",
        "tgn:7012149",
        "tgn:2000882",
        "tgn:7007256",
        "tgn:7029392"
    ],
    "tgn:id":2496353,
    "tgn:name":"Matherne, Bayou",
    "tgn:placetype":[
        "aat:300008699"
    ]
},
  "bbox": [],
  "geometry": {"coordinates":[-90.3833,29.6667],"type":"Point"}
}