{
  "id": 2087022,
  "type": "Feature",
  "properties": {
    "tgn:hierarchy":[
        "tgn:2087022",
        "tgn:1000001",
        "tgn:7012149",
        "tgn:1002586",
        "tgn:7007710",
        "tgn:7029392"
    ],
    "tgn:id":2087022,
    "tgn:name":"Catasauqua",
    "tgn:placetype":[
        "aat:300008347"
    ]
},
  "bbox": [],
  "geometry": {"coordinates":[-75.4667,40.65],"type":"Point"}
}