{
  "id": 7558864,
  "type": "Feature",
  "properties": {
    "tgn:hierarchy":[
        "tgn:7558864",
        "tgn:1000004",
        "tgn:7000198",
        "tgn:1001578",
        "tgn:7029392"
    ],
    "tgn:id":7558864,
    "tgn:name:en":"Rengdil",
    "tgn:placetype":[
        "aat:300008347"
    ]
},
  "bbox": [],
  "geometry": {"coordinates":[92.384251,24.048367],"type":"Point"}
}