{
  "id": 2586000,
  "type": "Feature",
  "properties": {
    "tgn:hierarchy":[
        "tgn:2586000",
        "tgn:1000001",
        "tgn:1003037",
        "tgn:7012149",
        "tgn:7007516",
        "tgn:7029392"
    ],
    "tgn:id":2586000,
    "tgn:name":"Pirate Islands",
    "tgn:placetype":[
        "aat:300386853"
    ]
},
  "bbox": [],
  "geometry": {"coordinates":[-75.2333,38.0833],"type":"Point"}
}