{
  "id": 7292070,
  "type": "Feature",
  "properties": {
    "tgn:hierarchy":[
        "tgn:7292070",
        "tgn:1001630",
        "tgn:1000049",
        "tgn:1000002",
        "tgn:7029392"
    ],
    "tgn:id":7292070,
    "tgn:name":"Filomena, Quebrada",
    "tgn:placetype":[
        "aat:300266554",
        "aat:300008699"
    ]
},
  "bbox": [],
  "geometry": {"coordinates":[-69.566667,-26.716667],"type":"Point"}
}