{
  "id": 7150845,
  "type": "Feature",
  "properties": {
    "tgn:hierarchy":[
        "tgn:7150845",
        "tgn:1000003",
        "tgn:7000094",
        "tgn:7000084",
        "tgn:7029392"
    ],
    "tgn:id":7150845,
    "tgn:name":"Labussee",
    "tgn:placetype":[
        "aat:300008680"
    ]
},
  "bbox": [],
  "geometry": {"coordinates":[12.883333,53.216667],"type":"Point"}
}