{
  "id": 2170553,
  "type": "Feature",
  "properties": {
    "tgn:hierarchy":[
        "tgn:2170553",
        "tgn:1000001",
        "tgn:1002278",
        "tgn:7012149",
        "tgn:7007710",
        "tgn:7029392"
    ],
    "tgn:id":2170553,
    "tgn:name":"Big Run",
    "tgn:placetype":[
        "aat:300008699"
    ]
},
  "bbox": [],
  "geometry": {"coordinates":[-78.2167,41.0167],"type":"Point"}
}