{
  "id": 1045076,
  "type": "Feature",
  "properties": {
    "tgn:hierarchy":[
        "tgn:1045076",
        "tgn:1000003",
        "tgn:1007846",
        "tgn:7003122",
        "tgn:1001762",
        "tgn:1000080",
        "tgn:7029392"
    ],
    "tgn:id":1045076,
    "tgn:name":"Levanzo",
    "tgn:placetype":[
        "aat:300008347"
    ]
},
  "bbox": [],
  "geometry": {"coordinates":[12.333333,37.983333],"type":"Point"}
}