{
  "id": 7557489,
  "type": "Feature",
  "properties": {
    "tgn:hierarchy":[
        "tgn:7557489",
        "tgn:1000004",
        "tgn:7000198",
        "tgn:7016694",
        "tgn:7029392"
    ],
    "tgn:id":7557489,
    "tgn:name:en":"Parimal",
    "tgn:placetype":[
        "aat:300008347"
    ]
},
  "bbox": [],
  "geometry": {"coordinates":[84.066667,19.233333],"type":"Point"}
}