{
  "id": 2122431,
  "type": "Feature",
  "properties": {
    "tgn:hierarchy":[
        "tgn:2122431",
        "tgn:1000001",
        "tgn:7012149",
        "tgn:2002360",
        "tgn:7007922",
        "tgn:7029392"
    ],
    "tgn:id":2122431,
    "tgn:name":"Spooner",
    "tgn:placetype":[
        "aat:300008347"
    ]
},
  "bbox": [],
  "geometry": {"coordinates":[-91.8833,45.8167],"type":"Point"}
}