{
  "id": 2057942,
  "type": "Feature",
  "properties": {
    "tgn:hierarchy":[
        "tgn:2057942",
        "tgn:1000001",
        "tgn:7012149",
        "tgn:1002671",
        "tgn:7007523",
        "tgn:7029392"
    ],
    "tgn:id":2057942,
    "tgn:name":"Aurora Springs",
    "tgn:placetype":[
        "aat:300008347"
    ]
},
  "bbox": [],
  "geometry": {"coordinates":[-92.5833,38.3167],"type":"Point"}
}