{
  "id": 7292914,
  "type": "Feature",
  "properties": {
    "tgn:hierarchy":[
        "tgn:7292914",
        "tgn:1001708",
        "tgn:1000049",
        "tgn:1000002",
        "tgn:7029392"
    ],
    "tgn:id":7292914,
    "tgn:name":"El Convento",
    "tgn:placetype":[
        "aat:300000206"
    ]
},
  "bbox": [],
  "geometry": {"coordinates":[-71.633333,-33.783333],"type":"Point"}
}