{
  "id": 2318757,
  "type": "Feature",
  "properties": {
    "tgn:hierarchy":[
        "tgn:2318757",
        "tgn:1000001",
        "tgn:7012149",
        "tgn:2002099",
        "tgn:7007826",
        "tgn:7029392"
    ],
    "tgn:id":2318757,
    "tgn:name":"Esado Tank",
    "tgn:placetype":[
        "aat:300006191"
    ]
},
  "bbox": [],
  "geometry": {"coordinates":[-99.0667,26.8333],"type":"Point"}
}