{
  "id": 2581042,
  "type": "Feature",
  "properties": {
    "tgn:hierarchy":[
        "tgn:2581042",
        "tgn:2002308",
        "tgn:1000001",
        "tgn:7012149",
        "tgn:7007922",
        "tgn:7029392"
    ],
    "tgn:id":2581042,
    "tgn:name":"Pike River",
    "tgn:placetype":[
        "aat:300008347"
    ]
},
  "bbox": [],
  "geometry": {"coordinates":[-91.2333,46.45],"type":"Point"}
}