<<<<<<< HEAD
{
  "id": 7489085,
  "type": "Feature",
  "properties": {
    "tgn:hierarchy":[
        "tgn:7489085",
        "tgn:7468018",
        "tgn:1000004",
        "tgn:1000141",
        "tgn:7029392"
    ],
    "tgn:id":7489085,
    "tgn:name":"Yizhishan",
    "tgn:placetype":[
        "aat:300008347"
    ]
},
  "bbox": [],
  "geometry": {"coordinates":[120.616667,23.55],"type":"Point"}
}
=======
{"geometry":{"type":"Point","coordinates":[120.616667,23.550000]},"type":"Feature","properties":{"hierarchy":["tgn:7489085","tgn:7468018","tgn:1000004","tgn:1000141","tgn:7029392"],"placetype":["aat:300008347"],"id":7489085,"name:xx":"Yizhishan"}}
>>>>>>> 03f74aca74312dbeaf24d7e61306dd6a786dc3d0
