{
  "id": 7516261,
  "type": "Feature",
  "properties": {
    "tgn:hierarchy":[
        "tgn:7516261",
        "tgn:1009227",
        "tgn:7001866",
        "tgn:1000226",
        "tgn:1000006",
        "tgn:7029392"
    ],
    "tgn:id":7516261,
    "tgn:name:en":"Levels",
    "tgn:placetype":[
        "aat:300008347"
    ]
},
  "bbox": [],
  "geometry": {"coordinates":[171.216667,-44.333333],"type":"Point"}
}