{
  "id": 1130284,
  "type": "Feature",
  "properties": {
    "tgn:hierarchy":[
        "tgn:1130284",
        "tgn:1000003",
        "tgn:7003151",
        "tgn:7003237",
        "tgn:1000080",
        "tgn:7029392"
    ],
    "tgn:id":1130284,
    "tgn:name":"Staffora",
    "tgn:placetype":[
        "aat:300008707",
        "aat:300008699"
    ]
},
  "bbox": [],
  "geometry": {"coordinates":[9.016667,45.066667],"type":"Point"}
}