{
  "id": 2232638,
  "type": "Feature",
  "properties": {
    "tgn:hierarchy":[
        "tgn:2232638",
        "tgn:1000001",
        "tgn:1002272",
        "tgn:7012149",
        "tgn:7007710",
        "tgn:7029392"
    ],
    "tgn:id":2232638,
    "tgn:name":"Chapel Run",
    "tgn:placetype":[
        "aat:300008699"
    ]
},
  "bbox": [],
  "geometry": {"coordinates":[-79.25,41.3833],"type":"Point"}
}