{
  "id": 2066841,
  "type": "Feature",
  "properties": {
    "tgn:hierarchy":[
        "tgn:2066841",
        "tgn:1000001",
        "tgn:2001432",
        "tgn:7012149",
        "tgn:7007566",
        "tgn:7029392"
    ],
    "tgn:id":2066841,
    "tgn:name":"Colmor",
    "tgn:placetype":[
        "aat:300387016"
    ]
},
  "bbox": [],
  "geometry": {"coordinates":[-104.6333,36.2167],"type":"Point"}
}