<<<<<<< HEAD
{
  "id": 7022310,
  "type": "Feature",
  "properties": {
    "tgn:hierarchy":[
        "tgn:7022310",
        "tgn:1000001",
        "tgn:7012149",
        "tgn:2000358",
        "tgn:7007248",
        "tgn:7029392"
    ],
    "tgn:id":7022310,
    "tgn:name":"Atha, Lake",
    "tgn:placetype":[
        "aat:300006191"
    ]
},
  "bbox": [],
  "geometry": {"coordinates":[-84.05,33.9],"type":"Point"}
}
=======
{"geometry":{"type":"Point","coordinates":[-84.050000,33.900000]},"type":"Feature","properties":{"hierarchy":["tgn:7022310","tgn:1000001","tgn:7012149","tgn:2000358","tgn:7007248","tgn:7029392"],"placetype":["aat:300006191"],"id":7022310,"name:xx":"Atha, Lake"}}
>>>>>>> 03f74aca74312dbeaf24d7e61306dd6a786dc3d0
