{
  "id": 2625504,
  "type": "Feature",
  "properties": {
    "tgn:hierarchy":[
        "tgn:2625504",
        "tgn:1000001",
        "tgn:7012149",
        "tgn:7014185",
        "tgn:7007710",
        "tgn:7029392"
    ],
    "tgn:id":2625504,
    "tgn:name":"Rocks Works",
    "tgn:placetype":[
        "aat:300008347"
    ]
},
  "bbox": [],
  "geometry": {"coordinates":[-79.8833,39.8333],"type":"Point"}
}