{
  "id": 2131102,
  "type": "Feature",
  "properties": {
    "tgn:hierarchy":[
        "tgn:2131102",
        "tgn:1000001",
        "tgn:7012149",
        "tgn:2001300",
        "tgn:7007524",
        "tgn:7029392"
    ],
    "tgn:id":2131102,
    "tgn:name":"Alpine Creek",
    "tgn:placetype":[
        "aat:300008706"
    ]
},
  "bbox": [],
  "geometry": {"coordinates":[-113.5833,45.8667],"type":"Point"}
}