{
  "id": 1121216,
  "type": "Feature",
  "properties": {
    "tgn:hierarchy":[
        "tgn:1121216",
        "tgn:1000003",
        "tgn:7002882",
        "tgn:1000070",
        "tgn:7029392"
    ],
    "tgn:id":1121216,
    "tgn:name":"Andelle",
    "tgn:placetype":[
        "aat:300008707"
    ]
},
  "bbox": [],
  "geometry": {"coordinates":[1.7333,49.3333],"type":"Point"}
}