{
  "id": 7423025,
  "type": "Feature",
  "properties": {
    "tgn:hierarchy":[
        "tgn:7423025",
        "tgn:1000001",
        "tgn:7005601",
        "tgn:7005560",
        "tgn:7029392"
    ],
    "tgn:id":7423025,
    "tgn:name":"Azozuaque",
    "tgn:placetype":[
        "aat:300008347"
    ]
},
  "bbox": [],
  "geometry": {"coordinates":[-103.333333,21.566667],"type":"Point"}
}