<<<<<<< HEAD
{
  "id": 2337251,
  "type": "Feature",
  "properties": {
    "tgn:hierarchy":[
        "tgn:2337251",
        "tgn:1000001",
        "tgn:7012149",
        "tgn:2000205",
        "tgn:7007158",
        "tgn:7029392"
    ],
    "tgn:id":2337251,
    "tgn:name":"Fourth Newlin Creek",
    "tgn:placetype":[
        "aat:300008706"
    ]
},
  "bbox": [],
  "geometry": {"coordinates":[-105.2,38.2167],"type":"Point"}
}
=======
{"geometry":{"type":"Point","coordinates":[-105.200000,38.216700]},"type":"Feature","properties":{"hierarchy":["tgn:2337251","tgn:1000001","tgn:7012149","tgn:2000205","tgn:7007158","tgn:7029392"],"placetype":["aat:300008706"],"id":2337251,"name:xx":"Fourth Newlin Creek"}}
>>>>>>> 03f74aca74312dbeaf24d7e61306dd6a786dc3d0
