{
  "id": 7481704,
  "type": "Feature",
  "properties": {
    "tgn:hierarchy":[
        "tgn:7481704",
        "tgn:1000004",
        "tgn:7001009",
        "tgn:1000141",
        "tgn:7029392"
    ],
    "tgn:id":7481704,
    "tgn:name":"Hupan Shan",
    "tgn:placetype":[
        "aat:300008798"
    ]
},
  "bbox": [],
  "geometry": {"coordinates":[121.093611,24.319722],"type":"Point"}
}