<<<<<<< HEAD
{
  "id": 7481704,
  "type": "Feature",
  "properties": {
    "tgn:hierarchy":[
        "tgn:7481704",
        "tgn:1000004",
        "tgn:7001009",
        "tgn:1000141",
        "tgn:7029392"
    ],
    "tgn:id":7481704,
    "tgn:name":"Hupan Shan",
    "tgn:placetype":[
        "aat:300008798"
    ]
},
  "bbox": [],
  "geometry": {"coordinates":[121.093611,24.319722],"type":"Point"}
}
=======
{"geometry":{"type":"Point","coordinates":[121.093611,24.319722]},"type":"Feature","properties":{"hierarchy":["tgn:7481704","tgn:1000004","tgn:7001009","tgn:1000141","tgn:7029392"],"placetype":["aat:300008798"],"id":7481704,"name:xx":"Hupan Shan"}}
>>>>>>> 03f74aca74312dbeaf24d7e61306dd6a786dc3d0
