{
  "id": 7479750,
  "type": "Feature",
  "properties": {
    "tgn:hierarchy":[
        "tgn:7479750",
        "tgn:1000004",
        "tgn:7490934",
        "tgn:1000141",
        "tgn:7029392"
    ],
    "tgn:id":7479750,
    "tgn:name":"Nanguang Zhongxue",
    "tgn:placetype":[
        "aat:300006495"
    ]
},
  "bbox": [],
  "geometry": {"coordinates":[120.315278,23.299167],"type":"Point"}
}