{
  "id": 2643133,
  "type": "Feature",
  "properties": {
    "tgn:hierarchy":[
        "tgn:2643133",
        "tgn:1000001",
        "tgn:7012149",
        "tgn:1002626",
        "tgn:7007826",
        "tgn:7029392"
    ],
    "tgn:id":2643133,
    "tgn:name":"Sandy Branch",
    "tgn:placetype":[
        "aat:300008699"
    ]
},
  "bbox": [],
  "geometry": {"coordinates":[-96.1333,30.8667],"type":"Point"}
}