{
  "id": 2668104,
  "type": "Feature",
  "properties": {
    "tgn:hierarchy":[
        "tgn:2668104",
        "tgn:1000001",
        "tgn:7006451",
        "tgn:7012149",
        "tgn:2000097",
        "tgn:7029392"
    ],
    "tgn:id":2668104,
    "tgn:name":"Skyline Heights",
    "tgn:placetype":[
        "aat:300008347"
    ]
},
  "bbox": [],
  "geometry": {"coordinates":[-112.0333,33.5333],"type":"Point"}
}