{
  "id": 1085070,
  "type": "Feature",
  "properties": {
    "tgn:hierarchy":[
        "tgn:1085070",
        "tgn:1000004",
        "tgn:7593756",
        "tgn:1000140",
        "tgn:7029392"
    ],
    "tgn:id":1085070,
    "tgn:name":"Al Kiswah",
    "tgn:placetype":[
        "aat:300008347"
    ]
},
  "bbox": [],
  "geometry": {"coordinates":[36.2667,33.35],"type":"Point"}
}