{
  "id": 2401149,
  "type": "Feature",
  "properties": {
    "tgn:hierarchy":[
        "tgn:2401149",
        "tgn:1000001",
        "tgn:7012149",
        "tgn:2001289",
        "tgn:7007524",
        "tgn:7029392"
    ],
    "tgn:id":2401149,
    "tgn:name":"Horsefly Spring",
    "tgn:placetype":[
        "aat:300008697"
    ]
},
  "bbox": [],
  "geometry": {"coordinates":[-110.8833,46.7167],"type":"Point"}
}