{
  "id": 2568740,
  "type": "Feature",
  "properties": {
    "tgn:hierarchy":[
        "tgn:2568740",
        "tgn:1000001",
        "tgn:7012149",
        "tgn:2000931",
        "tgn:7007515",
        "tgn:7029392"
    ],
    "tgn:id":2568740,
    "tgn:name":"Parker Cove",
    "tgn:placetype":[
        "aat:300132316"
    ]
},
  "bbox": [],
  "geometry": {"coordinates":[-68.8667,44.35],"type":"Point"}
}