{
  "id": 7412988,
  "type": "Feature",
  "properties": {
    "tgn:hierarchy":[
        "tgn:7412988",
        "tgn:1000001",
        "tgn:7005596",
        "tgn:7005560",
        "tgn:7029392"
    ],
    "tgn:id":7412988,
    "tgn:name:es":"Guerrero",
    "tgn:placetype":[
        "aat:300008347"
    ]
},
  "bbox": [],
  "geometry": {"coordinates":[-92.754167,17.408333],"type":"Point"}
}