{
  "id": 2420752,
  "type": "Feature",
  "properties": {
    "tgn:hierarchy":[
        "tgn:2420752",
        "tgn:1000001",
        "tgn:7012149",
        "tgn:2001880",
        "tgn:7007825",
        "tgn:7029392"
    ],
    "tgn:id":2420752,
    "tgn:name":"Jennings Creek",
    "tgn:placetype":[
        "aat:300008706"
    ]
},
  "bbox": [],
  "geometry": {"coordinates":[-85.8167,36.4333],"type":"Point"}
}