{
  "id": 7048369,
  "type": "Feature",
  "properties": {
    "tgn:hierarchy":[
        "tgn:7048369",
        "tgn:7003005",
        "tgn:7003014",
        "tgn:1000003",
        "tgn:1000080",
        "tgn:7029392"
    ],
    "tgn:id":7048369,
    "tgn:name":"Stazione Eboli-Campagna",
    "tgn:placetype":[
        "aat:300007783"
    ]
},
  "bbox": [],
  "geometry": {"coordinates":[15.066667,40.616667],"type":"Point"}
}