{
  "id": 2581525,
  "type": "Feature",
  "properties": {
    "tgn:hierarchy":[
        "tgn:2581525",
        "tgn:1000001",
        "tgn:7016172",
        "tgn:2000109",
        "tgn:7012149",
        "tgn:7029392"
    ],
    "tgn:id":2581525,
    "tgn:name":"Pilot Mountain",
    "tgn:placetype":[
        "aat:300008798"
    ]
},
  "bbox": [],
  "geometry": {"coordinates":[-93.0333,36.1167],"type":"Point"}
}