{
  "id": 7073656,
  "type": "Feature",
  "properties": {
    "tgn:hierarchy":[
        "tgn:7073656",
        "tgn:1000003",
        "tgn:7003688",
        "tgn:7000084",
        "tgn:7029392"
    ],
    "tgn:id":7073656,
    "tgn:name":"S\u00fcderhever",
    "tgn:placetype":[
        "aat:300008713"
    ]
},
  "bbox": [],
  "geometry": {"coordinates":[8.533333,54.366667],"type":"Point"}
}