<<<<<<< HEAD
{
  "id": 7476094,
  "type": "Feature",
  "properties": {
    "tgn:hierarchy":[
        "tgn:7476094",
        "tgn:7488858",
        "tgn:1000004",
        "tgn:1000141",
        "tgn:7029392"
    ],
    "tgn:id":7476094,
    "tgn:name":"Benjihu",
    "tgn:placetype":[
        "aat:300008347"
    ]
},
  "bbox": [],
  "geometry": {"coordinates":[120.754236,23.843089],"type":"Point"}
}
=======
{"geometry":{"type":"Point","coordinates":[120.754236,23.843089]},"type":"Feature","properties":{"hierarchy":["tgn:7476094","tgn:7488858","tgn:1000004","tgn:1000141","tgn:7029392"],"placetype":["aat:300008347"],"id":7476094,"name:xx":"Benjihu"}}
>>>>>>> 03f74aca74312dbeaf24d7e61306dd6a786dc3d0
