{
  "id": 7025800,
  "type": "Feature",
  "properties": {
    "tgn:hierarchy":[
        "tgn:7025800",
        "tgn:7002445",
        "tgn:1000003",
        "tgn:7012077",
        "tgn:7008591",
        "tgn:7029392"
    ],
    "tgn:id":7025800,
    "tgn:name:ang":"Wenneham",
    "tgn:placetype":[
        "aat:300008347"
    ]
},
  "bbox": [],
  "geometry": {"coordinates":[-4.15,51.1167],"type":"Point"}
}