{
  "id": 2121389,
  "type": "Feature",
  "properties": {
    "tgn:hierarchy":[
        "tgn:2121389",
        "tgn:1000001",
        "tgn:2002312",
        "tgn:7012149",
        "tgn:7007922",
        "tgn:7029392"
    ],
    "tgn:id":2121389,
    "tgn:name":"Hilbert",
    "tgn:placetype":[
        "aat:300008347"
    ]
},
  "bbox": [],
  "geometry": {"coordinates":[-88.15,44.1333],"type":"Point"}
}