{
  "id": 2393468,
  "type": "Feature",
  "properties": {
    "tgn:hierarchy":[
        "tgn:2393468",
        "tgn:1002141",
        "tgn:1000001",
        "tgn:7012149",
        "tgn:7007568",
        "tgn:7029392"
    ],
    "tgn:id":2393468,
    "tgn:name":"Hog Brook",
    "tgn:placetype":[
        "aat:300008699"
    ]
},
  "bbox": [],
  "geometry": {"coordinates":[-78.0333,42.0667],"type":"Point"}
}