{
  "id": 2207762,
  "type": "Feature",
  "properties": {
    "tgn:hierarchy":[
        "tgn:2207762",
        "tgn:7002659",
        "tgn:1000001",
        "tgn:2000020",
        "tgn:7012149",
        "tgn:7029392"
    ],
    "tgn:id":2207762,
    "tgn:name":"Burgan Branch",
    "tgn:placetype":[
        "aat:300008699"
    ]
},
  "bbox": [],
  "geometry": {"coordinates":[-86.4333,31.6333],"type":"Point"}
}