{
  "id": 2279961,
  "type": "Feature",
  "properties": {
    "tgn:hierarchy":[
        "tgn:2279961",
        "tgn:1000001",
        "tgn:7006451",
        "tgn:7012149",
        "tgn:2000098",
        "tgn:7029392"
    ],
    "tgn:id":2279961,
    "tgn:name":"Dean Mine",
    "tgn:placetype":[
        "aat:300000390"
    ]
},
  "bbox": [],
  "geometry": {"coordinates":[-113.8667,35.1167],"type":"Point"}
}