{
  "id": 1093025,
  "type": "Feature",
  "properties": {
    "tgn:hierarchy":[
        "tgn:1093025",
        "tgn:7001242",
        "tgn:7017582",
        "tgn:1000193",
        "tgn:7029392"
    ],
    "tgn:id":1093025,
    "tgn:name":"Douglas",
    "tgn:placetype":[
        "aat:300008347"
    ]
},
  "bbox": [],
  "geometry": {"coordinates":[23.7833,-29.0667],"type":"Point"}
}