{
  "id": 7225690,
  "type": "Feature",
  "properties": {
    "tgn:hierarchy":[
        "tgn:7225690",
        "tgn:7002690",
        "tgn:7012056",
        "tgn:1000003",
        "tgn:1000074",
        "tgn:7029392"
    ],
    "tgn:id":7225690,
    "tgn:name":"Navt\u00edlos, Vr\u00e1khos",
    "tgn:placetype":[
        "aat:300011692"
    ]
},
  "bbox": [],
  "geometry": {"coordinates":[23.216667,35.95],"type":"Point"}
}