{
  "id": 2266583,
  "type": "Feature",
  "properties": {
    "tgn:hierarchy":[
        "tgn:2266583",
        "tgn:1000001",
        "tgn:7012149",
        "tgn:2001146",
        "tgn:7007522",
        "tgn:7029392"
    ],
    "tgn:id":2266583,
    "tgn:name":"Creekwood Place",
    "tgn:placetype":[
        "aat:300008347"
    ]
},
  "bbox": [],
  "geometry": {"coordinates":[-90.0167,32.3333],"type":"Point"}
}