{
  "id": 7337161,
  "type": "Feature",
  "properties": {
    "tgn:hierarchy":[
        "tgn:7337161",
        "tgn:7002834",
        "tgn:1000003",
        "tgn:7002786",
        "tgn:1000095",
        "tgn:7029392"
    ],
    "tgn:id":7337161,
    "tgn:name":"Codeseda",
    "tgn:placetype":[
        "aat:300008347"
    ]
},
  "bbox": [],
  "geometry": {"coordinates":[-8.433333,42.616667],"type":"Point"}
}