{
  "id": 2283460,
  "type": "Feature",
  "properties": {
    "tgn:hierarchy":[
        "tgn:2283460",
        "tgn:1000001",
        "tgn:7012149",
        "tgn:2001751",
        "tgn:7007712",
        "tgn:7029392"
    ],
    "tgn:id":2283460,
    "tgn:name":"Deloss Island",
    "tgn:placetype":[
        "aat:300008791"
    ]
},
  "bbox": [],
  "geometry": {"coordinates":[-80.8667,32.5167],"type":"Point"}
}