{
  "id": 7417847,
  "type": "Feature",
  "properties": {
    "tgn:hierarchy":[
        "tgn:7417847",
        "tgn:7005584",
        "tgn:1000001",
        "tgn:7005560",
        "tgn:7029392"
    ],
    "tgn:id":7417847,
    "tgn:name":"El Tanquecito",
    "tgn:placetype":[
        "aat:300008347"
    ]
},
  "bbox": [],
  "geometry": {"coordinates":[-100.501389,20.3125],"type":"Point"}
}