{
  "id": 7538337,
  "type": "Feature",
  "properties": {
    "tgn:hierarchy":[
        "tgn:7538337",
        "tgn:7001242",
        "tgn:7016833",
        "tgn:1001113",
        "tgn:7029392"
    ],
    "tgn:id":7538337,
    "tgn:name:en":"Rim\u0101l, Jaz\u012brat ar",
    "tgn:placetype":[
        "aat:300008777"
    ]
},
  "bbox": [],
  "geometry": {"coordinates":[31.868478,30.899721],"type":"Point"}
}