<<<<<<< HEAD
{
  "id": 2159183,
  "type": "Feature",
  "properties": {
    "tgn:hierarchy":[
        "tgn:2159183",
        "tgn:1000001",
        "tgn:7012149",
        "tgn:2000491",
        "tgn:7007250",
        "tgn:7029392"
    ],
    "tgn:id":2159183,
    "tgn:name":"Bedrock Gulch",
    "tgn:placetype":[
        "aat:300008761"
    ]
},
  "bbox": [],
  "geometry": {"coordinates":[-115.85,47.65],"type":"Point"}
}
=======
{"geometry":{"type":"Point","coordinates":[-115.850000,47.650000]},"type":"Feature","properties":{"hierarchy":["tgn:2159183","tgn:1000001","tgn:7012149","tgn:2000491","tgn:7007250","tgn:7029392"],"placetype":["aat:300008761"],"id":2159183,"name:xx":"Bedrock Gulch"}}
>>>>>>> 03f74aca74312dbeaf24d7e61306dd6a786dc3d0
