<<<<<<< HEAD
{
  "id": 2155033,
  "type": "Feature",
  "properties": {
    "tgn:hierarchy":[
        "tgn:2155033",
        "tgn:1000001",
        "tgn:7012149",
        "tgn:7007157",
        "tgn:7014004",
        "tgn:7029392"
    ],
    "tgn:id":2155033,
    "tgn:name":"Bear Lake",
    "tgn:placetype":[
        "aat:300006191"
    ]
},
  "bbox": [],
  "geometry": {"coordinates":[-120.2167,37.3667],"type":"Point"}
}
=======
{"geometry":{"type":"Point","coordinates":[-120.216700,37.366700]},"type":"Feature","properties":{"hierarchy":["tgn:2155033","tgn:1000001","tgn:7012149","tgn:7007157","tgn:7014004","tgn:7029392"],"placetype":["aat:300006191"],"id":2155033,"name:xx":"Bear Lake"}}
>>>>>>> 03f74aca74312dbeaf24d7e61306dd6a786dc3d0
