{
  "id": 2318973,
  "type": "Feature",
  "properties": {
    "tgn:hierarchy":[
        "tgn:2318973",
        "tgn:1000001",
        "tgn:7012149",
        "tgn:7007157",
        "tgn:1002867",
        "tgn:7029392"
    ],
    "tgn:id":2318973,
    "tgn:name":"Espada Creek",
    "tgn:placetype":[
        "aat:300008706"
    ]
},
  "bbox": [],
  "geometry": {"coordinates":[-120.4833,34.5667],"type":"Point"}
}