{
  "id": 1059745,
  "type": "Feature",
  "properties": {
    "tgn:hierarchy":[
        "tgn:1059745",
        "tgn:1000004",
        "tgn:7011531",
        "tgn:7018214",
        "tgn:7002435",
        "tgn:7029392"
    ],
    "tgn:id":1059745,
    "tgn:name":"Staroderevyankovskaya",
    "tgn:placetype":[
        "aat:300008347"
    ]
},
  "bbox": [],
  "geometry": {"coordinates":[38.9667,46.1167],"type":"Point"}
}