{
  "id": 7090114,
  "type": "Feature",
  "properties": {
    "tgn:hierarchy":[
        "tgn:7090114",
        "tgn:1000003",
        "tgn:7003688",
        "tgn:7000084",
        "tgn:7029392"
    ],
    "tgn:id":7090114,
    "tgn:name":"Unterstes Holz",
    "tgn:placetype":[
        "aat:300008863"
    ]
},
  "bbox": [],
  "geometry": {"coordinates":[10.65,53.516667],"type":"Point"}
}