{
  "id": 7267402,
  "type": "Feature",
  "properties": {
    "tgn:hierarchy":[
        "tgn:7267402",
        "tgn:7003619",
        "tgn:1000003",
        "tgn:7016845",
        "tgn:7029392"
    ],
    "tgn:id":7267402,
    "tgn:name:nl":"Onzalige Bossen",
    "tgn:placetype":[
        "aat:300008178"
    ]
},
  "bbox": [],
  "geometry": {"coordinates":[6.033333,52.05],"type":"Point"}
}