{
  "id": 7419109,
  "type": "Feature",
  "properties": {
    "tgn:hierarchy":[
        "tgn:7419109",
        "tgn:7005584",
        "tgn:1000001",
        "tgn:7005560",
        "tgn:7029392"
    ],
    "tgn:id":7419109,
    "tgn:name":"Los Amoles, Cerros",
    "tgn:placetype":[
        "aat:300008795"
    ]
},
  "bbox": [],
  "geometry": {"coordinates":[-100.150278,21.165278],"type":"Point"}
}