{
  "id": 2129606,
  "type": "Feature",
  "properties": {
    "tgn:hierarchy":[
        "tgn:2129606",
        "tgn:1000001",
        "tgn:7012149",
        "tgn:1002742",
        "tgn:7007920",
        "tgn:7029392"
    ],
    "tgn:id":2129606,
    "tgn:name":"Alkali Pond",
    "tgn:placetype":[
        "aat:300008680"
    ]
},
  "bbox": [],
  "geometry": {"coordinates":[-119.55,48.1333],"type":"Point"}
}