<<<<<<< HEAD
{
  "id": 7359244,
  "type": "Feature",
  "properties": {
    "tgn:hierarchy":[
        "tgn:7359244",
        "tgn:1000001",
        "tgn:7005589",
        "tgn:7005560",
        "tgn:7029392"
    ],
    "tgn:id":7359244,
    "tgn:name":"Rancho Divisadero",
    "tgn:placetype":[
        "aat:300000241"
    ]
},
  "bbox": [],
  "geometry": {"coordinates":[-100.166667,26.966667],"type":"Point"}
}
=======
{"geometry":{"type":"Point","coordinates":[-100.166667,26.966667]},"type":"Feature","properties":{"hierarchy":["tgn:7359244","tgn:1000001","tgn:7005589","tgn:7005560","tgn:7029392"],"placetype":["aat:300000241"],"id":7359244,"name:xx":"Rancho Divisadero"}}
>>>>>>> 03f74aca74312dbeaf24d7e61306dd6a786dc3d0
