{
  "id": 7317030,
  "type": "Feature",
  "properties": {
    "tgn:hierarchy":[
        "tgn:7317030",
        "tgn:1001699",
        "tgn:1000049",
        "tgn:1000002",
        "tgn:7029392"
    ],
    "tgn:id":7317030,
    "tgn:name":"Coihueco, Estero",
    "tgn:placetype":[
        "aat:300008699"
    ]
},
  "bbox": [],
  "geometry": {"coordinates":[-72.633333,-39.716667],"type":"Point"}
}