{
  "id": 2597266,
  "type": "Feature",
  "properties": {
    "tgn:hierarchy":[
        "tgn:2597266",
        "tgn:7002659",
        "tgn:1000001",
        "tgn:7012149",
        "tgn:2000065",
        "tgn:7029392"
    ],
    "tgn:id":2597266,
    "tgn:name":"Prairie Creek",
    "tgn:placetype":[
        "aat:300008706"
    ]
},
  "bbox": [],
  "geometry": {"coordinates":[-87.1167,31.8667],"type":"Point"}
}