{
  "id": 2237747,
  "type": "Feature",
  "properties": {
    "tgn:hierarchy":[
        "tgn:2237747",
        "tgn:1000001",
        "tgn:7012149",
        "tgn:1002767",
        "tgn:7007920",
        "tgn:7029392"
    ],
    "tgn:id":2237747,
    "tgn:name":"Chinook River",
    "tgn:placetype":[
        "aat:300008707"
    ]
},
  "bbox": [],
  "geometry": {"coordinates":[-123.8667,46.2667],"type":"Point"}
}