<<<<<<< HEAD
{
  "id": 2154265,
  "type": "Feature",
  "properties": {
    "tgn:hierarchy":[
        "tgn:2154265",
        "tgn:1000001",
        "tgn:1002245",
        "tgn:7012149",
        "tgn:7007568",
        "tgn:7029392"
    ],
    "tgn:id":2154265,
    "tgn:name":"Bear Creek",
    "tgn:placetype":[
        "aat:300008706"
    ]
},
  "bbox": [],
  "geometry": {"coordinates":[-78.5,42.35],"type":"Point"}
}
=======
{"geometry":{"type":"Point","coordinates":[-78.500000,42.350000]},"type":"Feature","properties":{"hierarchy":["tgn:2154265","tgn:1000001","tgn:1002245","tgn:7012149","tgn:7007568","tgn:7029392"],"placetype":["aat:300008706"],"id":2154265,"name:xx":"Bear Creek"}}
>>>>>>> 03f74aca74312dbeaf24d7e61306dd6a786dc3d0
