{
  "id": 2285808,
  "type": "Feature",
  "properties": {
    "tgn:hierarchy":[
        "tgn:2285808",
        "tgn:1000001",
        "tgn:7012149",
        "tgn:7014510",
        "tgn:7007920",
        "tgn:7029392"
    ],
    "tgn:id":2285808,
    "tgn:name":"Devils Playground",
    "tgn:placetype":[
        "aat:300055621"
    ]
},
  "bbox": [],
  "geometry": {"coordinates":[-122.7333,48.6167],"type":"Point"}
}