{
  "id": 7302675,
  "type": "Feature",
  "properties": {
    "tgn:hierarchy":[
        "tgn:7302675",
        "tgn:7002849",
        "tgn:1000003",
        "tgn:7009604",
        "tgn:1000095",
        "tgn:7029392"
    ],
    "tgn:id":7302675,
    "tgn:name":"Ond\u00e1rroa, R\u00eda de",
    "tgn:placetype":[
        "aat:300266571"
    ]
},
  "bbox": [],
  "geometry": {"coordinates":[-2.416667,43.333333],"type":"Point"}
}