{
  "id": 2160345,
  "type": "Feature",
  "properties": {
    "tgn:hierarchy":[
        "tgn:2160345",
        "tgn:1000001",
        "tgn:7006451",
        "tgn:7012149",
        "tgn:2000101",
        "tgn:7029392"
    ],
    "tgn:id":2160345,
    "tgn:name":"Beehive Tank",
    "tgn:placetype":[
        "aat:300006191"
    ]
},
  "bbox": [],
  "geometry": {"coordinates":[-111.0333,32.8667],"type":"Point"}
}