<<<<<<< HEAD
{
  "id": 7483375,
  "type": "Feature",
  "properties": {
    "tgn:hierarchy":[
        "tgn:7483375",
        "tgn:1000004",
        "tgn:7489179",
        "tgn:1000141",
        "tgn:7029392"
    ],
    "tgn:id":7483375,
    "tgn:name":"Gengfang Xi",
    "tgn:placetype":[
        "aat:300008699"
    ]
},
  "bbox": [],
  "geometry": {"coordinates":[121.864722,24.902222],"type":"Point"}
}
=======
{"geometry":{"type":"Point","coordinates":[121.864722,24.902222]},"type":"Feature","properties":{"hierarchy":["tgn:7483375","tgn:1000004","tgn:7489179","tgn:1000141","tgn:7029392"],"placetype":["aat:300008699"],"id":7483375,"name:xx":"Gengfang Xi"}}
>>>>>>> 03f74aca74312dbeaf24d7e61306dd6a786dc3d0
