{
  "id": 7382571,
  "type": "Feature",
  "properties": {
    "tgn:hierarchy":[
        "tgn:7382571",
        "tgn:7005575",
        "tgn:1000001",
        "tgn:7005560",
        "tgn:7029392"
    ],
    "tgn:id":7382571,
    "tgn:name":"Olivar de los Padres",
    "tgn:placetype":[
        "aat:300008347"
    ]
},
  "bbox": [],
  "geometry": {"coordinates":[-99.216667,19.333333],"type":"Point"}
}