{
  "id": 7572156,
  "type": "Feature",
  "properties": {
    "tgn:hierarchy":[
        "tgn:7572156",
        "tgn:1000004",
        "tgn:1001869",
        "tgn:7000198",
        "tgn:7029392"
    ],
    "tgn:id":7572156,
    "tgn:name:en":"Had\u0101d",
    "tgn:placetype":[
        "aat:300008347"
    ]
},
  "bbox": [],
  "geometry": {"coordinates":[72.975937,24.265771],"type":"Point"}
}