{
  "id": 2672166,
  "type": "Feature",
  "properties": {
    "tgn:hierarchy":[
        "tgn:2672166",
        "tgn:1000001",
        "tgn:2000465",
        "tgn:7012149",
        "tgn:7007250",
        "tgn:7029392"
    ],
    "tgn:id":2672166,
    "tgn:name":"Smiths Island",
    "tgn:placetype":[
        "aat:300008791"
    ]
},
  "bbox": [],
  "geometry": {"coordinates":[-116.8667,43.5833],"type":"Point"}
}