<<<<<<< HEAD
{
  "id": 7053999,
  "type": "Feature",
  "properties": {
    "tgn:hierarchy":[
        "tgn:7053999",
        "tgn:7003139",
        "tgn:1000003",
        "tgn:7003080",
        "tgn:1000080",
        "tgn:7029392"
    ],
    "tgn:id":7053999,
    "tgn:name":"Montecalvello",
    "tgn:placetype":[
        "aat:300008347"
    ]
},
  "bbox": [],
  "geometry": {"coordinates":[12.216667,42.55],"type":"Point"}
}
=======
{"geometry":{"type":"Point","coordinates":[12.216667,42.550000]},"type":"Feature","properties":{"hierarchy":["tgn:7053999","tgn:7003139","tgn:1000003","tgn:7003080","tgn:1000080","tgn:7029392"],"placetype":["aat:300008347"],"id":7053999,"name:xx":"Montecalvello"}}
>>>>>>> 03f74aca74312dbeaf24d7e61306dd6a786dc3d0
