{
  "id": 7359762,
  "type": "Feature",
  "properties": {
    "tgn:hierarchy":[
        "tgn:7359762",
        "tgn:7005580",
        "tgn:1000001",
        "tgn:7005560",
        "tgn:7029392"
    ],
    "tgn:id":7359762,
    "tgn:name":"Cuauht\u00e9moc",
    "tgn:placetype":[
        "aat:300008347"
    ]
},
  "bbox": [],
  "geometry": {"coordinates":[-92.231111,14.611111],"type":"Point"}
}