{
  "id": 2202681,
  "type": "Feature",
  "properties": {
    "tgn:hierarchy":[
        "tgn:2202681",
        "tgn:1000001",
        "tgn:2001418",
        "tgn:7012149",
        "tgn:7007526",
        "tgn:7029392"
    ],
    "tgn:id":2202681,
    "tgn:name":"Buck Water Spring",
    "tgn:placetype":[
        "aat:300008697"
    ]
},
  "bbox": [],
  "geometry": {"coordinates":[-115.95,37.8667],"type":"Point"}
}