{
  "id": 2482546,
  "type": "Feature",
  "properties": {
    "tgn:hierarchy":[
        "tgn:2482546",
        "tgn:1000001",
        "tgn:7012149",
        "tgn:2001286",
        "tgn:7007524",
        "tgn:7029392"
    ],
    "tgn:id":2482546,
    "tgn:name":"Lap Creek",
    "tgn:placetype":[
        "aat:300008706"
    ]
},
  "bbox": [],
  "geometry": {"coordinates":[-115.7167,48.8833],"type":"Point"}
}