{
  "id": 7024945,
  "type": "Feature",
  "properties": {
    "tgn:hierarchy":[
        "tgn:7024945",
        "tgn:7002445",
        "tgn:7008103",
        "tgn:1000003",
        "tgn:7008591",
        "tgn:7029392"
    ],
    "tgn:id":7024945,
    "tgn:name":"Hinwick",
    "tgn:placetype":[
        "aat:300008347"
    ]
},
  "bbox": [],
  "geometry": {"coordinates":[-0.6167,52.2333],"type":"Point"}
}