{
  "id": 7299109,
  "type": "Feature",
  "properties": {
    "tgn:hierarchy":[
        "tgn:7299109",
        "tgn:7001165",
        "tgn:1000003",
        "tgn:7002793",
        "tgn:1000095",
        "tgn:7029392"
    ],
    "tgn:id":7299109,
    "tgn:name":"Tollo, Barranco del",
    "tgn:placetype":[
        "aat:300266554",
        "aat:300008699"
    ]
},
  "bbox": [],
  "geometry": {"coordinates":[-1.366667,39.366667],"type":"Point"}
}