{
  "id": 7192193,
  "type": "Feature",
  "properties": {
    "tgn:hierarchy":[
        "tgn:7192193",
        "tgn:1000003",
        "tgn:7003677",
        "tgn:7000084",
        "tgn:7029392"
    ],
    "tgn:id":7192193,
    "tgn:name":"Freialdenhoven",
    "tgn:placetype":[
        "aat:300008347"
    ]
},
  "bbox": [],
  "geometry": {"coordinates":[6.25,50.933333],"type":"Point"}
}