<<<<<<< HEAD
{
  "id": 7352968,
  "type": "Feature",
  "properties": {
    "tgn:hierarchy":[
        "tgn:7352968",
        "tgn:7005583",
        "tgn:1000001",
        "tgn:7005560",
        "tgn:7029392"
    ],
    "tgn:id":7352968,
    "tgn:name":"Batea",
    "tgn:placetype":[
        "aat:300008347"
    ]
},
  "bbox": [],
  "geometry": {"coordinates":[-105.833333,25.366667],"type":"Point"}
}
=======
{"geometry":{"type":"Point","coordinates":[-105.833333,25.366667]},"type":"Feature","properties":{"hierarchy":["tgn:7352968","tgn:7005583","tgn:1000001","tgn:7005560","tgn:7029392"],"placetype":["aat:300008347"],"id":7352968,"name:xx":"Batea"}}
>>>>>>> 03f74aca74312dbeaf24d7e61306dd6a786dc3d0
