<<<<<<< HEAD
{
  "id": 2157205,
  "type": "Feature",
  "properties": {
    "tgn:hierarchy":[
        "tgn:2157205",
        "tgn:1002146",
        "tgn:1000001",
        "tgn:7012149",
        "tgn:7007157",
        "tgn:7029392"
    ],
    "tgn:id":2157205,
    "tgn:name":"Beaver Creek",
    "tgn:placetype":[
        "aat:300008706"
    ]
},
  "bbox": [],
  "geometry": {"coordinates":[-120.3,38.5167],"type":"Point"}
}
=======
{"geometry":{"type":"Point","coordinates":[-120.300000,38.516700]},"type":"Feature","properties":{"hierarchy":["tgn:2157205","tgn:1002146","tgn:1000001","tgn:7012149","tgn:7007157","tgn:7029392"],"placetype":["aat:300008706"],"id":2157205,"name:xx":"Beaver Creek"}}
>>>>>>> 03f74aca74312dbeaf24d7e61306dd6a786dc3d0
