{
  "id": 7260126,
  "type": "Feature",
  "properties": {
    "tgn:hierarchy":[
        "tgn:7260126",
        "tgn:1000003",
        "tgn:7003624",
        "tgn:7016845",
        "tgn:7029392"
    ],
    "tgn:id":7260126,
    "tgn:name:nl":"De Huisvennen",
    "tgn:placetype":[
        "aat:300387200"
    ]
},
  "bbox": [],
  "geometry": {"coordinates":[4.916667,51.466667],"type":"Point"}
}