{
  "id": 2603012,
  "type": "Feature",
  "properties": {
    "tgn:hierarchy":[
        "tgn:2603012",
        "tgn:1000001",
        "tgn:7012149",
        "tgn:2001849",
        "tgn:7007825",
        "tgn:7029392"
    ],
    "tgn:id":2603012,
    "tgn:name":"Quarry Cave",
    "tgn:placetype":[
        "aat:300008746"
    ]
},
  "bbox": [],
  "geometry": {"coordinates":[-83.5833,36.4667],"type":"Point"}
}