{
  "id": 7412754,
  "type": "Feature",
  "properties": {
    "tgn:hierarchy":[
        "tgn:7412754",
        "tgn:7005587",
        "tgn:1000001",
        "tgn:7005560",
        "tgn:7029392"
    ],
    "tgn:id":7412754,
    "tgn:name:es":"Agua Hedionda",
    "tgn:placetype":[
        "aat:300008347"
    ]
},
  "bbox": [],
  "geometry": {"coordinates":[-99.072222,21.005556],"type":"Point"}
}