{
  "id": 2077699,
  "type": "Feature",
  "properties": {
    "tgn:hierarchy":[
        "tgn:2077699",
        "tgn:2001557",
        "tgn:1000001",
        "tgn:7012149",
        "tgn:7007705",
        "tgn:7029392"
    ],
    "tgn:id":2077699,
    "tgn:name":"Haynes",
    "tgn:placetype":[
        "aat:300008347"
    ]
},
  "bbox": [],
  "geometry": {"coordinates":[-102.4667,45.9667],"type":"Point"}
}