{
  "id": 7550260,
  "type": "Feature",
  "properties": {
    "tgn:hierarchy":[
        "tgn:7550260",
        "tgn:1000004",
        "tgn:7000198",
        "tgn:7016788",
        "tgn:7029392"
    ],
    "tgn:id":7550260,
    "tgn:name:en":"Chandr\u0101vati",
    "tgn:placetype":[
        "aat:300008347"
    ]
},
  "bbox": [],
  "geometry": {"coordinates":[72.743394,24.442596],"type":"Point"}
}