{
  "id": 2278747,
  "type": "Feature",
  "properties": {
    "tgn:hierarchy":[
        "tgn:2278747",
        "tgn:1000001",
        "tgn:7012149",
        "tgn:7007523",
        "tgn:7029392"
    ],
    "tgn:id":2278747,
    "tgn:name":"Dead Horse Hollow",
    "tgn:placetype":[
        "aat:300008761"
    ]
},
  "bbox": [],
  "geometry": {"coordinates":[-91.7667,37.3833],"type":"Point"}
}