{
  "id": 7556703,
  "type": "Feature",
  "properties": {
    "tgn:hierarchy":[
        "tgn:7556703",
        "tgn:1000004",
        "tgn:7000198",
        "tgn:7016722",
        "tgn:7029392"
    ],
    "tgn:id":7556703,
    "tgn:name:en":"Saidpur",
    "tgn:placetype":[
        "aat:300008347"
    ]
},
  "bbox": [],
  "geometry": {"coordinates":[77.908833,28.611],"type":"Point"}
}