{
  "id": 1092068,
  "type": "Feature",
  "properties": {
    "tgn:hierarchy":[
        "tgn:1092068",
        "tgn:7001242",
        "tgn:7015047",
        "tgn:1000182",
        "tgn:7029392"
    ],
    "tgn:id":1092068,
    "tgn:name":"Isanlu Makutu",
    "tgn:placetype":[
        "aat:300008347"
    ]
},
  "bbox": [],
  "geometry": {"coordinates":[5.8333,8.3333],"type":"Point"}
}