{
  "id": 7280557,
  "type": "Feature",
  "properties": {
    "tgn:hierarchy":[
        "tgn:7280557",
        "tgn:1001702",
        "tgn:1000049",
        "tgn:1000002",
        "tgn:7029392"
    ],
    "tgn:id":7280557,
    "tgn:name":"Sivewright, Bah\u00eda",
    "tgn:placetype":[
        "aat:300132316"
    ]
},
  "bbox": [],
  "geometry": {"coordinates":[-73.733333,-52.583333],"type":"Point"}
}