{
  "id": 2076820,
  "type": "Feature",
  "properties": {
    "tgn:hierarchy":[
        "tgn:2076820",
        "tgn:2001467",
        "tgn:1000001",
        "tgn:7012149",
        "tgn:7007709",
        "tgn:7029392"
    ],
    "tgn:id":2076820,
    "tgn:name":"Sturgills",
    "tgn:placetype":[
        "aat:300008347",
        "aat:300387210"
    ]
},
  "bbox": [],
  "geometry": {"coordinates":[-81.4833,36.55],"type":"Point"}
}