{
  "id": 2201064,
  "type": "Feature",
  "properties": {
    "tgn:hierarchy":[
        "tgn:2201064",
        "tgn:1000001",
        "tgn:1002328",
        "tgn:7012149",
        "tgn:7007568",
        "tgn:7029392"
    ],
    "tgn:id":2201064,
    "tgn:name":"Brydon Lake",
    "tgn:placetype":[
        "aat:300008680"
    ]
},
  "bbox": [],
  "geometry": {"coordinates":[-74.8667,42.1833],"type":"Point"}
}