{
  "id": 7560791,
  "type": "Feature",
  "properties": {
    "tgn:hierarchy":[
        "tgn:7560791",
        "tgn:1000004",
        "tgn:7000198",
        "tgn:7016722",
        "tgn:7029392"
    ],
    "tgn:id":7560791,
    "tgn:name:en":"Udhann\u0101pur",
    "tgn:placetype":[
        "aat:300008347"
    ]
},
  "bbox": [],
  "geometry": {"coordinates":[79.589335,27.551796],"type":"Point"}
}