{
  "id": 2193575,
  "type": "Feature",
  "properties": {
    "tgn:hierarchy":[
        "tgn:2193575",
        "tgn:1000001",
        "tgn:7012149",
        "tgn:2001752",
        "tgn:7007712",
        "tgn:7029392"
    ],
    "tgn:id":2193575,
    "tgn:name":"Brevards Spring",
    "tgn:placetype":[
        "aat:300008697"
    ]
},
  "bbox": [],
  "geometry": {"coordinates":[-80.5833,34.25],"type":"Point"}
}