{
  "id": 2039528,
  "type": "Feature",
  "properties": {
    "tgn:hierarchy":[
        "tgn:2039528",
        "tgn:1000001",
        "tgn:2000769",
        "tgn:7012149",
        "tgn:7007255",
        "tgn:7029392"
    ],
    "tgn:id":2039528,
    "tgn:name":"Ingram",
    "tgn:placetype":[
        "aat:300008347"
    ]
},
  "bbox": [],
  "geometry": {"coordinates":[-83.7833,36.7167],"type":"Point"}
}