{
  "id": 7480144,
  "type": "Feature",
  "properties": {
    "tgn:hierarchy":[
        "tgn:7480144",
        "tgn:1000004",
        "tgn:7471332",
        "tgn:1000141",
        "tgn:7029392"
    ],
    "tgn:id":7480144,
    "tgn:name":"Hexing Gongyuan Gongmu",
    "tgn:placetype":[
        "aat:300266755"
    ]
},
  "bbox": [],
  "geometry": {"coordinates":[121.044167,24.927222],"type":"Point"}
}