{
  "id": 2310981,
  "type": "Feature",
  "properties": {
    "tgn:hierarchy":[
        "tgn:2310981",
        "tgn:1000001",
        "tgn:7012149",
        "tgn:2000892",
        "tgn:7007256",
        "tgn:7029392"
    ],
    "tgn:id":2310981,
    "tgn:name":"Eden",
    "tgn:placetype":[
        "aat:300008347"
    ]
},
  "bbox": [],
  "geometry": {"coordinates":[-91.7667,30.9667],"type":"Point"}
}