{
  "id": 7220566,
  "type": "Feature",
  "properties": {
    "tgn:hierarchy":[
        "tgn:7220566",
        "tgn:7002706",
        "tgn:7002705",
        "tgn:1000003",
        "tgn:1000074",
        "tgn:7029392"
    ],
    "tgn:id":7220566,
    "tgn:name":"Vatani\u00e1da R\u00e9ma",
    "tgn:placetype":[
        "aat:300008699"
    ]
},
  "bbox": [],
  "geometry": {"coordinates":[21.347778,39.21],"type":"Point"}
}