{
  "id": 7160413,
  "type": "Feature",
  "properties": {
    "tgn:hierarchy":[
        "tgn:7160413",
        "tgn:1000003",
        "tgn:7003677",
        "tgn:7000084",
        "tgn:7029392"
    ],
    "tgn:id":7160413,
    "tgn:name":"Holz",
    "tgn:placetype":[
        "aat:300000206"
    ]
},
  "bbox": [],
  "geometry": {"coordinates":[7.366667,50.983333],"type":"Point"}
}