{
  "id": 2104575,
  "type": "Feature",
  "properties": {
    "tgn:hierarchy":[
        "tgn:2104575",
        "tgn:1000001",
        "tgn:7012149",
        "tgn:1002485",
        "tgn:7007826",
        "tgn:7029392"
    ],
    "tgn:id":2104575,
    "tgn:name":"Greenview",
    "tgn:placetype":[
        "aat:300008347",
        "aat:300387210"
    ]
},
  "bbox": [],
  "geometry": {"coordinates":[-95.7167,33.0167],"type":"Point"}
}