<<<<<<< HEAD
{
  "id": 7373711,
  "type": "Feature",
  "properties": {
    "tgn:hierarchy":[
        "tgn:7373711",
        "tgn:1000001",
        "tgn:7005599",
        "tgn:7005560",
        "tgn:7029392"
    ],
    "tgn:id":7373711,
    "tgn:name":"La Avanzada",
    "tgn:placetype":[
        "aat:300008347"
    ]
},
  "bbox": [],
  "geometry": {"coordinates":[-97.9,20.933333],"type":"Point"}
}
=======
{"geometry":{"type":"Point","coordinates":[-97.900000,20.933333]},"type":"Feature","properties":{"hierarchy":["tgn:7373711","tgn:1000001","tgn:7005599","tgn:7005560","tgn:7029392"],"placetype":["aat:300008347"],"id":7373711,"name:xx":"La Avanzada"}}
>>>>>>> 03f74aca74312dbeaf24d7e61306dd6a786dc3d0
