<<<<<<< HEAD
{
  "id": 7246507,
  "type": "Feature",
  "properties": {
    "tgn:hierarchy":[
        "tgn:7246507",
        "tgn:7007877",
        "tgn:1000003",
        "tgn:1000063",
        "tgn:4012014",
        "tgn:7029392"
    ],
    "tgn:id":7246507,
    "tgn:name":"Ferme du Bosquet",
    "tgn:placetype":[
        "aat:300000206"
    ]
},
  "bbox": [],
  "geometry": {"coordinates":[3.816667,50.666667],"type":"Point"}
}
=======
{"geometry":{"type":"Point","coordinates":[3.816667,50.666667]},"type":"Feature","properties":{"hierarchy":["tgn:7246507","tgn:7007877","tgn:1000003","tgn:1000063","tgn:4012014","tgn:7029392"],"placetype":["aat:300000206"],"id":7246507,"name:xx":"Ferme du Bosquet"}}
>>>>>>> 03f74aca74312dbeaf24d7e61306dd6a786dc3d0
