{
  "id": 2502996,
  "type": "Feature",
  "properties": {
    "tgn:hierarchy":[
        "tgn:2502996",
        "tgn:1000001",
        "tgn:7016172",
        "tgn:7012149",
        "tgn:2000168",
        "tgn:7029392"
    ],
    "tgn:id":2502996,
    "tgn:name":"McNally Creek",
    "tgn:placetype":[
        "aat:300008706"
    ]
},
  "bbox": [],
  "geometry": {"coordinates":[-94.1833,34.9667],"type":"Point"}
}