<<<<<<< HEAD
{
  "id": 2255725,
  "type": "Feature",
  "properties": {
    "tgn:hierarchy":[
        "tgn:2255725",
        "tgn:1000001",
        "tgn:7006451",
        "tgn:7012149",
        "tgn:2000103",
        "tgn:7029392"
    ],
    "tgn:id":2255725,
    "tgn:name":"Copper Basin Road Spring",
    "tgn:placetype":[
        "aat:300008697"
    ]
},
  "bbox": [],
  "geometry": {"coordinates":[-112.55,34.4667],"type":"Point"}
}
=======
{"geometry":{"type":"Point","coordinates":[-112.550000,34.466700]},"type":"Feature","properties":{"hierarchy":["tgn:2255725","tgn:1000001","tgn:7006451","tgn:7012149","tgn:2000103","tgn:7029392"],"placetype":["aat:300008697"],"id":2255725,"name:xx":"Copper Basin Road Spring"}}
>>>>>>> 03f74aca74312dbeaf24d7e61306dd6a786dc3d0
