{
  "id": 2429083,
  "type": "Feature",
  "properties": {
    "tgn:hierarchy":[
        "tgn:2429083",
        "tgn:7006450",
        "tgn:1000001",
        "tgn:7019674",
        "tgn:7012149",
        "tgn:7029392"
    ],
    "tgn:id":2429083,
    "tgn:name":"Junction Creek",
    "tgn:placetype":[
        "aat:300008706"
    ]
},
  "bbox": [],
  "geometry": {"coordinates":[-146.3667,64.3333],"type":"Point"}
}