{
  "id": 2399943,
  "type": "Feature",
  "properties": {
    "tgn:hierarchy":[
        "tgn:2399943",
        "tgn:1000001",
        "tgn:2002104",
        "tgn:7012149",
        "tgn:7007827",
        "tgn:7029392"
    ],
    "tgn:id":2399943,
    "tgn:name":"Horse Canyon",
    "tgn:placetype":[
        "aat:300008761"
    ]
},
  "bbox": [],
  "geometry": {"coordinates":[-110.9167,39.55],"type":"Point"}
}