{
  "id": 2388744,
  "type": "Feature",
  "properties": {
    "tgn:hierarchy":[
        "tgn:2388744",
        "tgn:7006450",
        "tgn:1000001",
        "tgn:7012149",
        "tgn:2000082",
        "tgn:7029392"
    ],
    "tgn:id":2388744,
    "tgn:name":"Hidden Creek",
    "tgn:placetype":[
        "aat:300008706"
    ]
},
  "bbox": [],
  "geometry": {"coordinates":[-131.5167,56.1833],"type":"Point"}
}