{
  "id": 2586171,
  "type": "Feature",
  "properties": {
    "tgn:hierarchy":[
        "tgn:2586171",
        "tgn:1000001",
        "tgn:7019560",
        "tgn:7012149",
        "tgn:7007566",
        "tgn:7029392"
    ],
    "tgn:id":2586171,
    "tgn:name":"Pisnel Tank",
    "tgn:placetype":[
        "aat:300006191"
    ]
},
  "bbox": [],
  "geometry": {"coordinates":[-104.55,34.0333],"type":"Point"}
}