{
  "id": 1014893,
  "type": "Feature",
  "properties": {
    "tgn:hierarchy":[
        "tgn:1014893",
        "tgn:7005685",
        "tgn:1000001",
        "tgn:7013154",
        "tgn:7029392"
    ],
    "tgn:id":1014893,
    "tgn:name":"Madawaska",
    "tgn:placetype":[
        "aat:300008347"
    ]
},
  "bbox": [],
  "geometry": {"coordinates":[-77.9833,45.5167],"type":"Point"}
}