{
  "id": 7411384,
  "type": "Feature",
  "properties": {
    "tgn:hierarchy":[
        "tgn:7411384",
        "tgn:7005587",
        "tgn:1000001",
        "tgn:7005560",
        "tgn:7029392"
    ],
    "tgn:id":7411384,
    "tgn:name:es":"Agua del Cuervo",
    "tgn:placetype":[
        "aat:300008347"
    ]
},
  "bbox": [],
  "geometry": {"coordinates":[-98.923611,20.827778],"type":"Point"}
}