{
  "id": 7298617,
  "type": "Feature",
  "properties": {
    "tgn:hierarchy":[
        "tgn:7298617",
        "tgn:7008912",
        "tgn:7030216",
        "tgn:1000003",
        "tgn:1000095",
        "tgn:7029392"
    ],
    "tgn:id":7298617,
    "tgn:name":"Torms",
    "tgn:placetype":[
        "aat:300008347"
    ]
},
  "bbox": [],
  "geometry": {"coordinates":[0.716667,41.383333],"type":"Point"}
}