{
  "id": 7463202,
  "type": "Feature",
  "properties": {
    "tgn:hierarchy":[
        "tgn:7463202",
        "tgn:7002445",
        "tgn:1000003",
        "tgn:7008129",
        "tgn:7008591",
        "tgn:7029392"
    ],
    "tgn:id":7463202,
    "tgn:name:en":"Long Shoal",
    "tgn:placetype":[
        "aat:300387036"
    ]
},
  "bbox": [],
  "geometry": {"coordinates":[0.433333,50.75],"type":"Point"}
}