<<<<<<< HEAD
{
  "id": 7376042,
  "type": "Feature",
  "properties": {
    "tgn:hierarchy":[
        "tgn:7376042",
        "tgn:1000001",
        "tgn:7005597",
        "tgn:7005560",
        "tgn:7029392"
    ],
    "tgn:id":7376042,
    "tgn:name":"La Regina",
    "tgn:placetype":[
        "aat:300008347"
    ]
},
  "bbox": [],
  "geometry": {"coordinates":[-99.583333,27.366667],"type":"Point"}
}
=======
{"geometry":{"type":"Point","coordinates":[-99.583333,27.366667]},"type":"Feature","properties":{"hierarchy":["tgn:7376042","tgn:1000001","tgn:7005597","tgn:7005560","tgn:7029392"],"placetype":["aat:300008347"],"id":7376042,"name:xx":"La Regina"}}
>>>>>>> 03f74aca74312dbeaf24d7e61306dd6a786dc3d0
