{
  "id": 1071172,
  "type": "Feature",
  "properties": {
    "tgn:hierarchy":[
        "tgn:1071172",
        "tgn:1000004",
        "tgn:7002079",
        "tgn:1000111",
        "tgn:7029392"
    ],
    "tgn:id":1071172,
    "tgn:name":"Quanxishi",
    "tgn:placetype":[
        "aat:300008347"
    ]
},
  "bbox": [],
  "geometry": {"coordinates":[112.7333,26.8833],"type":"Point"}
}