{
  "id": 1052600,
  "type": "Feature",
  "properties": {
    "tgn:hierarchy":[
        "tgn:1052600",
        "tgn:1000004",
        "tgn:7012259",
        "tgn:7006661",
        "tgn:7029392"
    ],
    "tgn:id":1052600,
    "tgn:name":"Beshkent",
    "tgn:placetype":[
        "aat:300008347"
    ]
},
  "bbox": [],
  "geometry": {"coordinates":[65.65,38.8667],"type":"Point"}
}