<<<<<<< HEAD
{
  "id": 2408076,
  "type": "Feature",
  "properties": {
    "tgn:hierarchy":[
        "tgn:2408076",
        "tgn:1000001",
        "tgn:7012149",
        "tgn:2001917",
        "tgn:7007825",
        "tgn:7029392"
    ],
    "tgn:id":2408076,
    "tgn:name":"Hurricane Hollow",
    "tgn:placetype":[
        "aat:300008761"
    ]
},
  "bbox": [],
  "geometry": {"coordinates":[-87.8167,36.3667],"type":"Point"}
}
=======
{"geometry":{"type":"Point","coordinates":[-87.816700,36.366700]},"type":"Feature","properties":{"hierarchy":["tgn:2408076","tgn:1000001","tgn:7012149","tgn:2001917","tgn:7007825","tgn:7029392"],"placetype":["aat:300008761"],"id":2408076,"name:xx":"Hurricane Hollow"}}
>>>>>>> 03f74aca74312dbeaf24d7e61306dd6a786dc3d0
