<<<<<<< HEAD
{
  "id": 7170464,
  "type": "Feature",
  "properties": {
    "tgn:hierarchy":[
        "tgn:7170464",
        "tgn:1000003",
        "tgn:7003689",
        "tgn:7000084",
        "tgn:7029392"
    ],
    "tgn:id":7170464,
    "tgn:name":"Hesserode",
    "tgn:placetype":[
        "aat:300008347"
    ]
},
  "bbox": [],
  "geometry": {"coordinates":[10.783333,50.85],"type":"Point"}
}
=======
{"geometry":{"type":"Point","coordinates":[10.783333,50.850000]},"type":"Feature","properties":{"hierarchy":["tgn:7170464","tgn:1000003","tgn:7003689","tgn:7000084","tgn:7029392"],"placetype":["aat:300008347"],"id":7170464,"name:xx":"Hesserode"}}
>>>>>>> 03f74aca74312dbeaf24d7e61306dd6a786dc3d0
