{
  "id": 2534639,
  "type": "Feature",
  "properties": {
    "tgn:hierarchy":[
        "tgn:2534639",
        "tgn:1000001",
        "tgn:7020680",
        "tgn:7012149",
        "tgn:7007256",
        "tgn:7029392"
    ],
    "tgn:id":2534639,
    "tgn:name":"Na Bonchasse, Bayou",
    "tgn:placetype":[
        "aat:300008699"
    ]
},
  "bbox": [],
  "geometry": {"coordinates":[-93.7167,32.0167],"type":"Point"}
}