{
  "id": 2517150,
  "type": "Feature",
  "properties": {
    "tgn:hierarchy":[
        "tgn:2517150",
        "tgn:1000001",
        "tgn:7012149",
        "tgn:1002576",
        "tgn:7007520",
        "tgn:7029392"
    ],
    "tgn:id":2517150,
    "tgn:name":"Minnawanna, Lake",
    "tgn:placetype":[
        "aat:300006191"
    ]
},
  "bbox": [],
  "geometry": {"coordinates":[-83.35,42.9333],"type":"Point"}
}