{
  "id": 7235525,
  "type": "Feature",
  "properties": {
    "tgn:hierarchy":[
        "tgn:7235525",
        "tgn:7011170",
        "tgn:7002715",
        "tgn:1000003",
        "tgn:1000074",
        "tgn:7029392"
    ],
    "tgn:id":7235525,
    "tgn:name":"F\u00edlippoi",
    "tgn:placetype":[
        "aat:300008347"
    ]
},
  "bbox": [],
  "geometry": {"coordinates":[24.333333,41.033333],"type":"Point"}
}