{
  "id": 7441324,
  "type": "Feature",
  "properties": {
    "tgn:hierarchy":[
        "tgn:7441324",
        "tgn:1001835",
        "tgn:1000001",
        "tgn:7005560",
        "tgn:7029392"
    ],
    "tgn:id":7441324,
    "tgn:name":"Santa Isabel",
    "tgn:placetype":[
        "aat:300008347"
    ]
},
  "bbox": [],
  "geometry": {"coordinates":[-113.35,28.383333],"type":"Point"}
}