{
  "id": 7383293,
  "type": "Feature",
  "properties": {
    "tgn:hierarchy":[
        "tgn:7383293",
        "tgn:7005586",
        "tgn:1000001",
        "tgn:7005560",
        "tgn:7029392"
    ],
    "tgn:id":7383293,
    "tgn:name":"Orozco",
    "tgn:placetype":[
        "aat:300007783"
    ]
},
  "bbox": [],
  "geometry": {"coordinates":[-102.383333,20.533333],"type":"Point"}
}