<<<<<<< HEAD
{
  "id": 2330239,
  "type": "Feature",
  "properties": {
    "tgn:hierarchy":[
        "tgn:2330239",
        "tgn:1000001",
        "tgn:7012149",
        "tgn:2002111",
        "tgn:7007827",
        "tgn:7029392"
    ],
    "tgn:id":2330239,
    "tgn:name":"Flanigan Arch",
    "tgn:placetype":[
        "aat:300386837"
    ]
},
  "bbox": [],
  "geometry": {"coordinates":[-112.9167,37.6333],"type":"Point"}
}
=======
{"geometry":{"type":"Point","coordinates":[-112.916700,37.633300]},"type":"Feature","properties":{"hierarchy":["tgn:2330239","tgn:1000001","tgn:7012149","tgn:2002111","tgn:7007827","tgn:7029392"],"placetype":["aat:300386837"],"id":2330239,"name:xx":"Flanigan Arch"}}
>>>>>>> 03f74aca74312dbeaf24d7e61306dd6a786dc3d0
