<<<<<<< HEAD
{
  "id": 7489795,
  "type": "Feature",
  "properties": {
    "tgn:hierarchy":[
        "tgn:7489795",
        "tgn:1000004",
        "tgn:7490934",
        "tgn:1000141",
        "tgn:7029392"
    ],
    "tgn:id":7489795,
    "tgn:name":"Xiachangduanshu",
    "tgn:placetype":[
        "aat:300008347"
    ]
},
  "bbox": [],
  "geometry": {"coordinates":[120.321667,23.354722],"type":"Point"}
}
=======
{"geometry":{"type":"Point","coordinates":[120.321667,23.354722]},"type":"Feature","properties":{"hierarchy":["tgn:7489795","tgn:1000004","tgn:7490934","tgn:1000141","tgn:7029392"],"placetype":["aat:300008347"],"id":7489795,"name:xx":"Xiachangduanshu"}}
>>>>>>> 03f74aca74312dbeaf24d7e61306dd6a786dc3d0
