{
  "id": 2384514,
  "type": "Feature",
  "properties": {
    "tgn:hierarchy":[
        "tgn:2384514",
        "tgn:1000001",
        "tgn:2002368",
        "tgn:7012149",
        "tgn:7007923",
        "tgn:7029392"
    ],
    "tgn:id":2384514,
    "tgn:name":"Hell Creek",
    "tgn:placetype":[
        "aat:300008706"
    ]
},
  "bbox": [],
  "geometry": {"coordinates":[-106.8667,41.1167],"type":"Point"}
}