{
  "id": 2442217,
  "type": "Feature",
  "properties": {
    "tgn:hierarchy":[
        "tgn:2442217",
        "tgn:1000001",
        "tgn:7012149",
        "tgn:7007157",
        "tgn:1002857",
        "tgn:7029392"
    ],
    "tgn:id":2442217,
    "tgn:name":"Kramer Arch",
    "tgn:placetype":[
        "aat:300386837"
    ]
},
  "bbox": [],
  "geometry": {"coordinates":[-116.8333,34.95],"type":"Point"}
}