{
  "id": 1112537,
  "type": "Feature",
  "properties": {
    "tgn:hierarchy":[
        "tgn:1112537",
        "tgn:7001242",
        "tgn:7016833",
        "tgn:7001335",
        "tgn:7029392"
    ],
    "tgn:id":1112537,
    "tgn:name":"\u0162\u012bnah, J\u016bnah a\u0163",
    "tgn:placetype":[
        "aat:300132316"
    ]
},
  "bbox": [],
  "geometry": {"coordinates":[32.685545,31.158018],"type":"Point"}
}