{
  "id": 7108144,
  "type": "Feature",
  "properties": {
    "tgn:hierarchy":[
        "tgn:7108144",
        "tgn:7003669",
        "tgn:1000003",
        "tgn:7000084",
        "tgn:7029392"
    ],
    "tgn:id":7108144,
    "tgn:name":"Reithof",
    "tgn:placetype":[
        "aat:300000206"
    ]
},
  "bbox": [],
  "geometry": {"coordinates":[13.433333,48.65],"type":"Point"}
}