{
  "id": 7166355,
  "type": "Feature",
  "properties": {
    "tgn:hierarchy":[
        "tgn:7166355",
        "tgn:1000003",
        "tgn:7003682",
        "tgn:7000084",
        "tgn:7029392"
    ],
    "tgn:id":7166355,
    "tgn:name":"Heistert",
    "tgn:placetype":[
        "aat:300000206"
    ]
},
  "bbox": [],
  "geometry": {"coordinates":[6.833333,50.466667],"type":"Point"}
}