{
  "id": 1084914,
  "type": "Feature",
  "properties": {
    "tgn:hierarchy":[
        "tgn:1084914",
        "tgn:7000678",
        "tgn:7003866",
        "tgn:1000004",
        "tgn:1000137",
        "tgn:7029392"
    ],
    "tgn:id":1084914,
    "tgn:name":"Umm al-Birak",
    "tgn:placetype":[
        "aat:300008347"
    ]
},
  "bbox": [],
  "geometry": {"coordinates":[39.2167,23.4333],"type":"Point"}
}