{
  "id": 2529674,
  "type": "Feature",
  "properties": {
    "tgn:hierarchy":[
        "tgn:2529674",
        "tgn:1000001",
        "tgn:7012149",
        "tgn:1002829",
        "tgn:7007255",
        "tgn:7029392"
    ],
    "tgn:id":2529674,
    "tgn:name":"Mud Lick",
    "tgn:placetype":[
        "aat:300008699"
    ]
},
  "bbox": [],
  "geometry": {"coordinates":[-84.0833,38.5333],"type":"Point"}
}