{
  "id": 1060432,
  "type": "Feature",
  "properties": {
    "tgn:hierarchy":[
        "tgn:1060432",
        "tgn:1000003",
        "tgn:7011661",
        "tgn:7006660",
        "tgn:7029392"
    ],
    "tgn:id":1060432,
    "tgn:name":"Trylisy",
    "tgn:placetype":[
        "aat:300008347"
    ]
},
  "bbox": [],
  "geometry": {"coordinates":[29.8333,49.9833],"type":"Point"}
}