{
  "id": 2715242,
  "type": "Feature",
  "properties": {
    "tgn:hierarchy":[
        "tgn:2715242",
        "tgn:1000001",
        "tgn:2001946",
        "tgn:7012149",
        "tgn:7007826",
        "tgn:7029392"
    ],
    "tgn:id":2715242,
    "tgn:name":"Tepee Pole Canyon",
    "tgn:placetype":[
        "aat:300008761"
    ]
},
  "bbox": [],
  "geometry": {"coordinates":[-101.3333,34.6833],"type":"Point"}
}