{
  "id": 1014158,
  "type": "Feature",
  "properties": {
    "tgn:hierarchy":[
        "tgn:1014158",
        "tgn:7005685",
        "tgn:7005807",
        "tgn:1000001",
        "tgn:7005801",
        "tgn:7029392"
    ],
    "tgn:id":1014158,
    "tgn:name":"Boyds Cove",
    "tgn:placetype":[
        "aat:300008347"
    ]
},
  "bbox": [],
  "geometry": {"coordinates":[-54.6667,49.4167],"type":"Point"}
}