{
  "id": 7387054,
  "type": "Feature",
  "properties": {
    "tgn:hierarchy":[
        "tgn:7387054",
        "tgn:7016644",
        "tgn:1000001",
        "tgn:7005560",
        "tgn:7029392"
    ],
    "tgn:id":7387054,
    "tgn:name":"Pueblo Nuevo",
    "tgn:placetype":[
        "aat:300008347"
    ]
},
  "bbox": [],
  "geometry": {"coordinates":[-103.916667,19.316667],"type":"Point"}
}