{
  "id": 7328254,
  "type": "Feature",
  "properties": {
    "tgn:hierarchy":[
        "tgn:7328254",
        "tgn:7002844",
        "tgn:7030216",
        "tgn:1000003",
        "tgn:1000095",
        "tgn:7029392"
    ],
    "tgn:id":7328254,
    "tgn:name":"Renau",
    "tgn:placetype":[
        "aat:300008347"
    ]
},
  "bbox": [],
  "geometry": {"coordinates":[1.310832,41.224484],"type":"Point"}
}