{
  "id": 2489848,
  "type": "Feature",
  "properties": {
    "tgn:hierarchy":[
        "tgn:2489848",
        "tgn:1000001",
        "tgn:7006451",
        "tgn:7012149",
        "tgn:2000103",
        "tgn:7029392"
    ],
    "tgn:id":2489848,
    "tgn:name":"Malpais Tank",
    "tgn:placetype":[
        "aat:300006191"
    ]
},
  "bbox": [],
  "geometry": {"coordinates":[-111.9333,34.8167],"type":"Point"}
}