{
  "id": 2663016,
  "type": "Feature",
  "properties": {
    "tgn:hierarchy":[
        "tgn:2663016",
        "tgn:1000001",
        "tgn:2001413",
        "tgn:7012149",
        "tgn:7007526",
        "tgn:7029392"
    ],
    "tgn:id":2663016,
    "tgn:name":"Silver Bell Mine",
    "tgn:placetype":[
        "aat:300000390"
    ]
},
  "bbox": [],
  "geometry": {"coordinates":[-115.8333,39.7333],"type":"Point"}
}