{
  "id": 7487630,
  "type": "Feature",
  "properties": {
    "tgn:hierarchy":[
        "tgn:7487630",
        "tgn:7001010",
        "tgn:1000004",
        "tgn:1000141",
        "tgn:7029392"
    ],
    "tgn:id":7487630,
    "tgn:name":"Kexin",
    "tgn:placetype":[
        "aat:300132356"
    ]
},
  "bbox": [],
  "geometry": {"coordinates":[121.199722,23.345556],"type":"Point"}
}