{
  "id": 7522586,
  "type": "Feature",
  "properties": {
    "tgn:hierarchy":[
        "tgn:7522586",
        "tgn:7001242",
        "tgn:7016833",
        "tgn:1001225",
        "tgn:7029392"
    ],
    "tgn:id":7522586,
    "tgn:name:en":"Dhayl Umm \u1e28usayn",
    "tgn:placetype":[
        "aat:300266559"
    ]
},
  "bbox": [],
  "geometry": {"coordinates":[31.893811,31.444943],"type":"Point"}
}