{
  "id": 1045474,
  "type": "Feature",
  "properties": {
    "tgn:hierarchy":[
        "tgn:1045474",
        "tgn:7009084",
        "tgn:7003000",
        "tgn:1000003",
        "tgn:1000080",
        "tgn:7029392"
    ],
    "tgn:id":1045474,
    "tgn:name":"Montazzoli",
    "tgn:placetype":[
        "aat:300008347"
    ]
},
  "bbox": [],
  "geometry": {"coordinates":[14.433333,41.95],"type":"Point"}
}