{
  "id": 1094782,
  "type": "Feature",
  "properties": {
    "tgn:hierarchy":[
        "tgn:1094782",
        "tgn:7001242",
        "tgn:1001713",
        "tgn:1000203",
        "tgn:7029392"
    ],
    "tgn:id":1094782,
    "tgn:name":"Nagaga",
    "tgn:placetype":[
        "aat:300008347"
    ]
},
  "bbox": [],
  "geometry": {"coordinates":[39.15,-10.9167],"type":"Point"}
}