{
  "id": 2727328,
  "type": "Feature",
  "properties": {
    "tgn:hierarchy":[
        "tgn:2727328",
        "tgn:1000001",
        "tgn:7012149",
        "tgn:2000933",
        "tgn:7007515",
        "tgn:7029392"
    ],
    "tgn:id":2727328,
    "tgn:name":"Trafton Brook",
    "tgn:placetype":[
        "aat:300008699"
    ]
},
  "bbox": [],
  "geometry": {"coordinates":[-70.75,43.4667],"type":"Point"}
}