{
  "id": 2507438,
  "type": "Feature",
  "properties": {
    "tgn:hierarchy":[
        "tgn:2507438",
        "tgn:1000001",
        "tgn:7012149",
        "tgn:2002342",
        "tgn:7007922",
        "tgn:7029392"
    ],
    "tgn:id":2507438,
    "tgn:name":"Meyer Lake",
    "tgn:placetype":[
        "aat:300008680"
    ]
},
  "bbox": [],
  "geometry": {"coordinates":[-89.8333,45.8167],"type":"Point"}
}