{
  "id": 7540310,
  "type": "Feature",
  "properties": {
    "tgn:hierarchy":[
        "tgn:7540310",
        "tgn:7001242",
        "tgn:7016833",
        "tgn:7000122",
        "tgn:7029392"
    ],
    "tgn:id":7540310,
    "tgn:name:en":"Naj' al \u1e28awsh",
    "tgn:placetype":[
        "aat:300008347"
    ]
},
  "bbox": [],
  "geometry": {"coordinates":[32.916667,24.733333],"type":"Point"}
}