{
  "id": 2614419,
  "type": "Feature",
  "properties": {
    "tgn:hierarchy":[
        "tgn:2614419",
        "tgn:1000001",
        "tgn:7012149",
        "tgn:2001546",
        "tgn:7007709",
        "tgn:7029392"
    ],
    "tgn:id":2614419,
    "tgn:name":"Reid Lake Number Two",
    "tgn:placetype":[
        "aat:300006191"
    ]
},
  "bbox": [],
  "geometry": {"coordinates":[-80.7667,35.0167],"type":"Point"}
}