{
  "id": 1083971,
  "type": "Feature",
  "properties": {
    "tgn:hierarchy":[
        "tgn:1083971",
        "tgn:1000004",
        "tgn:1001540",
        "tgn:1000135",
        "tgn:7029392"
    ],
    "tgn:id":1083971,
    "tgn:name":"Bacon",
    "tgn:placetype":[
        "aat:300008347"
    ]
},
  "bbox": [],
  "geometry": {"coordinates":[124.05,13.05],"type":"Point"}
}