{
  "id": 7437718,
  "type": "Feature",
  "properties": {
    "tgn:hierarchy":[
        "tgn:7437718",
        "tgn:1000001",
        "tgn:7005588",
        "tgn:7005560",
        "tgn:7029392"
    ],
    "tgn:id":7437718,
    "tgn:name":"Tinajas",
    "tgn:placetype":[
        "aat:300008347"
    ]
},
  "bbox": [],
  "geometry": {"coordinates":[-99.433333,18.766667],"type":"Point"}
}