{
  "id": 7035651,
  "type": "Feature",
  "properties": {
    "tgn:hierarchy":[
        "tgn:7035651",
        "tgn:7003006",
        "tgn:1000003",
        "tgn:7002997",
        "tgn:1000080",
        "tgn:7029392"
    ],
    "tgn:id":7035651,
    "tgn:name":"Brenta, Valle di",
    "tgn:placetype":[
        "aat:300008679"
    ]
},
  "bbox": [],
  "geometry": {"coordinates":[12.246111,45.1975],"type":"Point"}
}