{
  "id": 7349698,
  "type": "Feature",
  "properties": {
    "tgn:hierarchy":[
        "tgn:7349698",
        "tgn:1000001",
        "tgn:1001893",
        "tgn:7005560",
        "tgn:7029392"
    ],
    "tgn:id":7349698,
    "tgn:name":"San Antonio Acahualco",
    "tgn:placetype":[
        "aat:300008347"
    ]
},
  "bbox": [],
  "geometry": {"coordinates":[-99.775556,19.276944],"type":"Point"}
}