{
  "id": 7461948,
  "type": "Feature",
  "properties": {
    "tgn:hierarchy":[
        "tgn:7461948",
        "tgn:7002444",
        "tgn:1000003",
        "tgn:7008082",
        "tgn:7008591",
        "tgn:7029392"
    ],
    "tgn:id":7461948,
    "tgn:name:en":"Isauld Point",
    "tgn:placetype":[
        "aat:300386846"
    ]
},
  "bbox": [],
  "geometry": {"coordinates":[-3.766667,58.566667],"type":"Point"}
}