{
  "id": 7552610,
  "type": "Feature",
  "properties": {
    "tgn:hierarchy":[
        "tgn:7552610",
        "tgn:1009838",
        "tgn:7000204",
        "tgn:1000004",
        "tgn:7000198",
        "tgn:1009218",
        "tgn:7029392"
    ],
    "tgn:id":7552610,
    "tgn:name:en":"Mannar Ghat",
    "tgn:placetype":[
        "aat:300008347"
    ]
},
  "bbox": [],
  "geometry": {"coordinates":[92.716667,11.766667],"type":"Point"}
}