{
  "id": 2003336,
  "type": "Feature",
  "properties": {
    "tgn:hierarchy":[
        "tgn:2003336",
        "tgn:7002659",
        "tgn:1000001",
        "tgn:2000008",
        "tgn:7012149",
        "tgn:7029392"
    ],
    "tgn:id":2003336,
    "tgn:name":"Doublehead",
    "tgn:placetype":[
        "aat:300008347",
        "aat:300387210"
    ]
},
  "bbox": [],
  "geometry": {"coordinates":[-85.3833,33.0833],"type":"Point"}
}