{
  "id": 7139376,
  "type": "Feature",
  "properties": {
    "tgn:hierarchy":[
        "tgn:7139376",
        "tgn:7003669",
        "tgn:1000003",
        "tgn:7000084",
        "tgn:7029392"
    ],
    "tgn:id":7139376,
    "tgn:name":"Leingart",
    "tgn:placetype":[
        "aat:300008347"
    ]
},
  "bbox": [],
  "geometry": {"coordinates":[13.183333,48.55],"type":"Point"}
}