{
  "id": 7577138,
  "type": "Feature",
  "properties": {
    "tgn:hierarchy":[
        "tgn:7577138",
        "tgn:1000004",
        "tgn:7000198",
        "tgn:7000799",
        "tgn:7029392"
    ],
    "tgn:id":7577138,
    "tgn:name:en":"Lingzi T\u0101ng",
    "tgn:placetype":[
        "aat:300008805"
    ]
},
  "bbox": [],
  "geometry": {"coordinates":[79.300049,34.820478],"type":"Point"}
}