{
  "id": 2304305,
  "type": "Feature",
  "properties": {
    "tgn:hierarchy":[
        "tgn:2304305",
        "tgn:7013349",
        "tgn:1000001",
        "tgn:7012149",
        "tgn:7007708",
        "tgn:7029392"
    ],
    "tgn:id":2304305,
    "tgn:name":"Earl Spring",
    "tgn:placetype":[
        "aat:300008697"
    ]
},
  "bbox": [],
  "geometry": {"coordinates":[-118.35,44.6667],"type":"Point"}
}