{
  "id": 7305103,
  "type": "Feature",
  "properties": {
    "tgn:hierarchy":[
        "tgn:7305103",
        "tgn:7002811",
        "tgn:1000003",
        "tgn:7003837",
        "tgn:1000095",
        "tgn:7029392"
    ],
    "tgn:id":7305103,
    "tgn:name":"Las Batuecas",
    "tgn:placetype":[
        "aat:300132356"
    ]
},
  "bbox": [],
  "geometry": {"coordinates":[-6.133333,40.466667],"type":"Point"}
}