{
  "id": 2184446,
  "type": "Feature",
  "properties": {
    "tgn:hierarchy":[
        "tgn:2184446",
        "tgn:1000001",
        "tgn:7012149",
        "tgn:1002827",
        "tgn:7007252",
        "tgn:7029392"
    ],
    "tgn:id":2184446,
    "tgn:name":"Bobs Creek",
    "tgn:placetype":[
        "aat:300008706"
    ]
},
  "bbox": [],
  "geometry": {"coordinates":[-85.15,39.2667],"type":"Point"}
}