{
  "id": 1022545,
  "type": "Feature",
  "properties": {
    "tgn:hierarchy":[
        "tgn:1022545",
        "tgn:7006064",
        "tgn:1000047",
        "tgn:7002455",
        "tgn:1000002",
        "tgn:7029392"
    ],
    "tgn:id":1022545,
    "tgn:name":"Poranga",
    "tgn:placetype":[
        "aat:300008347"
    ]
},
  "bbox": [],
  "geometry": {"coordinates":[-40.9167,-4.7333],"type":"Point"}
}