{
  "id": 7492521,
  "type": "Feature",
  "properties": {
    "tgn:hierarchy":[
        "tgn:7492521",
        "tgn:7001010",
        "tgn:1000004",
        "tgn:1000141",
        "tgn:7029392"
    ],
    "tgn:id":7492521,
    "tgn:name":"Shanli",
    "tgn:placetype":[
        "aat:300008347"
    ]
},
  "bbox": [],
  "geometry": {"coordinates":[121.313014,23.429874],"type":"Point"}
}