{
  "id": 7348459,
  "type": "Feature",
  "properties": {
    "tgn:hierarchy":[
        "tgn:7348459",
        "tgn:7002805",
        "tgn:7002758",
        "tgn:1000003",
        "tgn:1000095",
        "tgn:7029392"
    ],
    "tgn:id":7348459,
    "tgn:name":"Adra, R\u00edo de",
    "tgn:placetype":[
        "aat:300008699"
    ]
},
  "bbox": [],
  "geometry": {"coordinates":[-2.983333,36.733333],"type":"Point"}
}