{
  "id": 2579519,
  "type": "Feature",
  "properties": {
    "tgn:hierarchy":[
        "tgn:2579519",
        "tgn:1000001",
        "tgn:7012149",
        "tgn:2000933",
        "tgn:7007515",
        "tgn:7029392"
    ],
    "tgn:id":2579519,
    "tgn:name":"Picket Mountain",
    "tgn:placetype":[
        "aat:300008798"
    ]
},
  "bbox": [],
  "geometry": {"coordinates":[-70.85,43.6333],"type":"Point"}
}