{
  "id": 2645789,
  "type": "Feature",
  "properties": {
    "tgn:hierarchy":[
        "tgn:2645789",
        "tgn:1000001",
        "tgn:7012149",
        "tgn:2000410",
        "tgn:7007248",
        "tgn:7029392"
    ],
    "tgn:id":2645789,
    "tgn:name":"Sawmill Creek",
    "tgn:placetype":[
        "aat:300008706"
    ]
},
  "bbox": [],
  "geometry": {"coordinates":[-83.4833,34.8167],"type":"Point"}
}