{
  "id": 2243606,
  "type": "Feature",
  "properties": {
    "tgn:hierarchy":[
        "tgn:2243606",
        "tgn:1000001",
        "tgn:7012149",
        "tgn:2001233",
        "tgn:7007523",
        "tgn:7029392"
    ],
    "tgn:id":2243606,
    "tgn:name":"Clemens Creek",
    "tgn:placetype":[
        "aat:300008706"
    ]
},
  "bbox": [],
  "geometry": {"coordinates":[-92.15,37.9667],"type":"Point"}
}