{
  "id": 2260207,
  "type": "Feature",
  "properties": {
    "tgn:hierarchy":[
        "tgn:2260207",
        "tgn:1000001",
        "tgn:2001745",
        "tgn:7012149",
        "tgn:7007712",
        "tgn:7029392"
    ],
    "tgn:id":2260207,
    "tgn:name":"Country Manor",
    "tgn:placetype":[
        "aat:300008347"
    ]
},
  "bbox": [],
  "geometry": {"coordinates":[-79.7167,34.15],"type":"Point"}
}