{
  "id": 1075603,
  "type": "Feature",
  "properties": {
    "tgn:hierarchy":[
        "tgn:1075603",
        "tgn:1000004",
        "tgn:7000198",
        "tgn:7016722",
        "tgn:7029392"
    ],
    "tgn:id":1075603,
    "tgn:name:en":"Jaswantnagar",
    "tgn:placetype":[
        "aat:300008347"
    ]
},
  "bbox": [],
  "geometry": {"coordinates":[78.901868,26.882335],"type":"Point"}
}