{
  "id": 2420504,
  "type": "Feature",
  "properties": {
    "tgn:hierarchy":[
        "tgn:2420504",
        "tgn:1000001",
        "tgn:7012149",
        "tgn:1002352",
        "tgn:7007710",
        "tgn:7029392"
    ],
    "tgn:id":2420504,
    "tgn:name":"Jenkins Hollow",
    "tgn:placetype":[
        "aat:300008761"
    ]
},
  "bbox": [],
  "geometry": {"coordinates":[-78.55,41.5333],"type":"Point"}
}