{
  "id": 7284771,
  "type": "Feature",
  "properties": {
    "tgn:hierarchy":[
        "tgn:7284771",
        "tgn:1001708",
        "tgn:1000049",
        "tgn:1000002",
        "tgn:7029392"
    ],
    "tgn:id":7284771,
    "tgn:name":"Quilhuica, Cerro",
    "tgn:placetype":[
        "aat:300008795"
    ]
},
  "bbox": [],
  "geometry": {"coordinates":[-70.866667,-33.266667],"type":"Point"}
}