{
  "id": 7001873,
  "type": "Feature",
  "properties": {
    "tgn:hierarchy":[
        "tgn:7001873",
        "tgn:1000004",
        "tgn:7002084",
        "tgn:1000111",
        "tgn:7029392"
    ],
    "tgn:id":7001873,
    "tgn:name":"Lan-t'ien",
    "tgn:placetype":[
        "aat:300387006",
        "aat:300391489",
        "aat:300387173"
    ]
},
  "bbox": [],
  "geometry": {"coordinates":[109.371389,34.095833],"type":"Point"}
}