{
  "id": 2011088,
  "type": "Feature",
  "properties": {
    "tgn:hierarchy":[
        "tgn:2011088",
        "tgn:1002138",
        "tgn:1000001",
        "tgn:2011085",
        "tgn:7012149",
        "tgn:7007157",
        "tgn:7029392"
    ],
    "tgn:id":2011088,
    "tgn:name":"San Ramon Village",
    "tgn:placetype":[
        "aat:300000745"
    ]
},
  "bbox": [],
  "geometry": {"coordinates":[-121.9167,37.7167],"type":"Point"}
}