{
  "id": 2598960,
  "type": "Feature",
  "properties": {
    "tgn:hierarchy":[
        "tgn:2598960",
        "tgn:1000001",
        "tgn:7012149",
        "tgn:2001852",
        "tgn:7007825",
        "tgn:7029392"
    ],
    "tgn:id":2598960,
    "tgn:name":"Prince Spring",
    "tgn:placetype":[
        "aat:300008697"
    ]
},
  "bbox": [],
  "geometry": {"coordinates":[-85.8833,35.1333],"type":"Point"}
}