{
  "id": 7440138,
  "type": "Feature",
  "properties": {
    "tgn:hierarchy":[
        "tgn:7440138",
        "tgn:1000001",
        "tgn:1001960",
        "tgn:7005560",
        "tgn:7029392"
    ],
    "tgn:id":7440138,
    "tgn:name":"San Pedro, Bah\u00eda",
    "tgn:placetype":[
        "aat:300132317"
    ]
},
  "bbox": [],
  "geometry": {"coordinates":[-111.283333,28.083333],"type":"Point"}
}