{
  "id": 7316302,
  "type": "Feature",
  "properties": {
    "tgn:hierarchy":[
        "tgn:7316302",
        "tgn:1001708",
        "tgn:1000049",
        "tgn:1000002",
        "tgn:7029392"
    ],
    "tgn:id":7316302,
    "tgn:name":"Card\u00f3n",
    "tgn:placetype":[
        "aat:300008777"
    ]
},
  "bbox": [],
  "geometry": {"coordinates":[-71.716667,-33.75],"type":"Point"}
}