{
  "id": 2273615,
  "type": "Feature",
  "properties": {
    "tgn:hierarchy":[
        "tgn:2273615",
        "tgn:2000919",
        "tgn:1000001",
        "tgn:7012149",
        "tgn:7007515",
        "tgn:7029392"
    ],
    "tgn:id":2273615,
    "tgn:name":"Cyr Mountain",
    "tgn:placetype":[
        "aat:300008798"
    ]
},
  "bbox": [],
  "geometry": {"coordinates":[-68.2833,47.2833],"type":"Point"}
}