{
  "id": 7129487,
  "type": "Feature",
  "properties": {
    "tgn:hierarchy":[
        "tgn:7129487",
        "tgn:7003692",
        "tgn:1000003",
        "tgn:7000084",
        "tgn:7029392"
    ],
    "tgn:id":7129487,
    "tgn:name":"Bahnhof Mannheim-Rheinau",
    "tgn:placetype":[
        "aat:300007783"
    ]
},
  "bbox": [],
  "geometry": {"coordinates":[8.535,49.424167],"type":"Point"}
}