{
  "id": 7167900,
  "type": "Feature",
  "properties": {
    "tgn:hierarchy":[
        "tgn:7167900",
        "tgn:1000003",
        "tgn:7003677",
        "tgn:7000084",
        "tgn:7029392"
    ],
    "tgn:id":7167900,
    "tgn:name":"Harth",
    "tgn:placetype":[
        "aat:300008347"
    ]
},
  "bbox": [],
  "geometry": {"coordinates":[7.466667,50.833333],"type":"Point"}
}