{
  "id": 1026275,
  "type": "Feature",
  "properties": {
    "tgn:hierarchy":[
        "tgn:1026275",
        "tgn:7003457",
        "tgn:1000003",
        "tgn:1000063",
        "tgn:7018236",
        "tgn:7029392"
    ],
    "tgn:id":1026275,
    "tgn:name":"Adegem",
    "tgn:placetype":[
        "aat:300008347"
    ]
},
  "bbox": [],
  "geometry": {"coordinates":[3.495398,51.205094],"type":"Point"}
}