{
  "id": 1107612,
  "type": "Feature",
  "properties": {
    "tgn:hierarchy":[
        "tgn:1107612",
        "tgn:7008911",
        "tgn:1000003",
        "tgn:7002763",
        "tgn:1000095",
        "tgn:7029392"
    ],
    "tgn:id":1107612,
    "tgn:name":"Ubi\u00f1a, Pe\u00f1a",
    "tgn:placetype":[
        "aat:300008798"
    ]
},
  "bbox": [],
  "geometry": {"coordinates":[-5.95,43.016667],"type":"Point"}
}