<<<<<<< HEAD
{
  "id": 2400656,
  "type": "Feature",
  "properties": {
    "tgn:hierarchy":[
        "tgn:2400656",
        "tgn:1000001",
        "tgn:7012149",
        "tgn:2001723",
        "tgn:7007708",
        "tgn:7029392"
    ],
    "tgn:id":2400656,
    "tgn:name":"Horse Mountain",
    "tgn:placetype":[
        "aat:300008798"
    ]
},
  "bbox": [],
  "geometry": {"coordinates":[-120.3833,44.8667],"type":"Point"}
}
=======
{"geometry":{"type":"Point","coordinates":[-120.383300,44.866700]},"type":"Feature","properties":{"hierarchy":["tgn:2400656","tgn:1000001","tgn:7012149","tgn:2001723","tgn:7007708","tgn:7029392"],"placetype":["aat:300008798"],"id":2400656,"name:xx":"Horse Mountain"}}
>>>>>>> 03f74aca74312dbeaf24d7e61306dd6a786dc3d0
