{
  "id": 1036055,
  "type": "Feature",
  "properties": {
    "tgn:hierarchy":[
        "tgn:1036055",
        "tgn:1000003",
        "tgn:1000070",
        "tgn:7002897",
        "tgn:7029392"
    ],
    "tgn:id":1036055,
    "tgn:name":"Verclause",
    "tgn:placetype":[
        "aat:300008347"
    ]
},
  "bbox": [],
  "geometry": {"coordinates":[5.4333,44.3833],"type":"Point"}
}