{
  "id": 7050770,
  "type": "Feature",
  "properties": {
    "tgn:hierarchy":[
        "tgn:7050770",
        "tgn:1003478",
        "tgn:1000003",
        "tgn:7003120",
        "tgn:1000080",
        "tgn:7029392"
    ],
    "tgn:id":7050770,
    "tgn:name":"Nezza",
    "tgn:placetype":[
        "aat:300008347"
    ]
},
  "bbox": [],
  "geometry": {"coordinates":[8.383333,46.183333],"type":"Point"}
}