{
  "id": 2651738,
  "type": "Feature",
  "properties": {
    "tgn:hierarchy":[
        "tgn:2651738",
        "tgn:1000001",
        "tgn:7012149",
        "tgn:2000213",
        "tgn:7007158",
        "tgn:7029392"
    ],
    "tgn:id":2651738,
    "tgn:name":"Seep Springs Draw",
    "tgn:placetype":[
        "aat:300008761"
    ]
},
  "bbox": [],
  "geometry": {"coordinates":[-105.2667,38.5833],"type":"Point"}
}