{
  "id": 7268210,
  "type": "Feature",
  "properties": {
    "tgn:hierarchy":[
        "tgn:7268210",
        "tgn:1000003",
        "tgn:7003626",
        "tgn:7016845",
        "tgn:7029392"
    ],
    "tgn:id":7268210,
    "tgn:name:nl":"Landgoed de Noetselenberg",
    "tgn:placetype":[
        "aat:300387502"
    ]
},
  "bbox": [],
  "geometry": {"coordinates":[6.433333,52.333333],"type":"Point"}
}