{
  "id": 7430253,
  "type": "Feature",
  "properties": {
    "tgn:hierarchy":[
        "tgn:7430253",
        "tgn:1001853",
        "tgn:1000001",
        "tgn:7005560",
        "tgn:7029392"
    ],
    "tgn:id":7430253,
    "tgn:name":"El Bragado",
    "tgn:placetype":[
        "aat:300008347"
    ]
},
  "bbox": [],
  "geometry": {"coordinates":[-101.15,26.866667],"type":"Point"}
}