{
  "id": 7355018,
  "type": "Feature",
  "properties": {
    "tgn:hierarchy":[
        "tgn:7355018",
        "tgn:1000001",
        "tgn:7005600",
        "tgn:7005560",
        "tgn:7029392"
    ],
    "tgn:id":7355018,
    "tgn:name":"Cansap",
    "tgn:placetype":[
        "aat:300008347"
    ]
},
  "bbox": [],
  "geometry": {"coordinates":[-89.783333,20.833333],"type":"Point"}
}