<<<<<<< HEAD
{
  "id": 2258965,
  "type": "Feature",
  "properties": {
    "tgn:hierarchy":[
        "tgn:2258965",
        "tgn:1000001",
        "tgn:7012149",
        "tgn:2001831",
        "tgn:7007713",
        "tgn:7029392"
    ],
    "tgn:id":2258965,
    "tgn:name":"Cottonwood Creek",
    "tgn:placetype":[
        "aat:300008706"
    ]
},
  "bbox": [],
  "geometry": {"coordinates":[-100.0833,43.4],"type":"Point"}
}
=======
{"geometry":{"type":"Point","coordinates":[-100.083300,43.400000]},"type":"Feature","properties":{"hierarchy":["tgn:2258965","tgn:1000001","tgn:7012149","tgn:2001831","tgn:7007713","tgn:7029392"],"placetype":["aat:300008706"],"id":2258965,"name:xx":"Cottonwood Creek"}}
>>>>>>> 03f74aca74312dbeaf24d7e61306dd6a786dc3d0
