{
  "id": 7228416,
  "type": "Feature",
  "properties": {
    "tgn:hierarchy":[
        "tgn:7228416",
        "tgn:7002725",
        "tgn:7002715",
        "tgn:1000003",
        "tgn:1000074",
        "tgn:7029392"
    ],
    "tgn:id":7228416,
    "tgn:name":"Kastaner\u00ed",
    "tgn:placetype":[
        "aat:300008347"
    ]
},
  "bbox": [],
  "geometry": {"coordinates":[22.382222,40.975556],"type":"Point"}
}