{
  "id": 7045373,
  "type": "Feature",
  "properties": {
    "tgn:hierarchy":[
        "tgn:7045373",
        "tgn:7009084",
        "tgn:7004154",
        "tgn:1000003",
        "tgn:1000080",
        "tgn:7029392"
    ],
    "tgn:id":7045373,
    "tgn:name":"Forcella",
    "tgn:placetype":[
        "aat:300008347"
    ]
},
  "bbox": [],
  "geometry": {"coordinates":[13.25,42.316667],"type":"Point"}
}