{
  "id": 7158419,
  "type": "Feature",
  "properties": {
    "tgn:hierarchy":[
        "tgn:7158419",
        "tgn:1000003",
        "tgn:7003677",
        "tgn:7000084",
        "tgn:7029392"
    ],
    "tgn:id":7158419,
    "tgn:name":"Holler Heide",
    "tgn:placetype":[
        "aat:300386887"
    ]
},
  "bbox": [],
  "geometry": {"coordinates":[6.15,51.25],"type":"Point"}
}