{
  "id": 7535854,
  "type": "Feature",
  "properties": {
    "tgn:hierarchy":[
        "tgn:7535854",
        "tgn:7001242",
        "tgn:7016833",
        "tgn:1001088",
        "tgn:7029392"
    ],
    "tgn:id":7535854,
    "tgn:name:en":"Kafr al Mad\u0101wir",
    "tgn:placetype":[
        "aat:300008347"
    ]
},
  "bbox": [],
  "geometry": {"coordinates":[30.816667,28.666667],"type":"Point"}
}