{
  "id": 7587942,
  "type": "Feature",
  "properties": {
    "tgn:hierarchy":[
        "tgn:7587942",
        "tgn:1000004",
        "tgn:7000198",
        "tgn:7000799",
        "tgn:7029392"
    ],
    "tgn:id":7587942,
    "tgn:name:en":"K\u0101rahom",
    "tgn:placetype":[
        "aat:300008347"
    ]
},
  "bbox": [],
  "geometry": {"coordinates":[74.51892,34.061674],"type":"Point"}
}