<<<<<<< HEAD
{
  "id": 2253635,
  "type": "Feature",
  "properties": {
    "tgn:hierarchy":[
        "tgn:2253635",
        "tgn:1000001",
        "tgn:7012149",
        "tgn:2001304",
        "tgn:7007524",
        "tgn:7029392"
    ],
    "tgn:id":2253635,
    "tgn:name":"Cook Mountain",
    "tgn:placetype":[
        "aat:300008798"
    ]
},
  "bbox": [],
  "geometry": {"coordinates":[-114.9167,47.75],"type":"Point"}
}
=======
{"geometry":{"type":"Point","coordinates":[-114.916700,47.750000]},"type":"Feature","properties":{"hierarchy":["tgn:2253635","tgn:1000001","tgn:7012149","tgn:2001304","tgn:7007524","tgn:7029392"],"placetype":["aat:300008798"],"id":2253635,"name:xx":"Cook Mountain"}}
>>>>>>> 03f74aca74312dbeaf24d7e61306dd6a786dc3d0
