{
  "id": 2248033,
  "type": "Feature",
  "properties": {
    "tgn:hierarchy":[
        "tgn:2248033",
        "tgn:1000001",
        "tgn:1002328",
        "tgn:7012149",
        "tgn:7007568",
        "tgn:7029392"
    ],
    "tgn:id":2248033,
    "tgn:name":"Colchester Mountain",
    "tgn:placetype":[
        "aat:300008798"
    ]
},
  "bbox": [],
  "geometry": {"coordinates":[-75.0333,42.1333],"type":"Point"}
}