{
  "id": 1023293,
  "type": "Feature",
  "properties": {
    "tgn:hierarchy":[
        "tgn:1023293",
        "tgn:1001942",
        "tgn:1000047",
        "tgn:7002457",
        "tgn:1000002",
        "tgn:7029392"
    ],
    "tgn:id":1023293,
    "tgn:name":"V\u00e1rzea das Mo\u00e7as",
    "tgn:placetype":[
        "aat:300008347"
    ]
},
  "bbox": [],
  "geometry": {"coordinates":[-42.9667,-22.95],"type":"Point"}
}