{
  "id": 7493825,
  "type": "Feature",
  "properties": {
    "tgn:hierarchy":[
        "tgn:7493825",
        "tgn:1000004",
        "tgn:1000454",
        "tgn:1000141",
        "tgn:7029392"
    ],
    "tgn:id":7493825,
    "tgn:name":"Daqiutian Shan",
    "tgn:placetype":[
        "aat:300008798"
    ]
},
  "bbox": [],
  "geometry": {"coordinates":[121.492623,24.917278],"type":"Point"}
}