{
  "id": 2260120,
  "type": "Feature",
  "properties": {
    "tgn:hierarchy":[
        "tgn:2260120",
        "tgn:1000001",
        "tgn:7012149",
        "tgn:2001534",
        "tgn:7007709",
        "tgn:7029392"
    ],
    "tgn:id":2260120,
    "tgn:name":"Country Club Lake",
    "tgn:placetype":[
        "aat:300006191"
    ]
},
  "bbox": [],
  "geometry": {"coordinates":[-79.25,34.6833],"type":"Point"}
}