{
  "id": 2786738,
  "type": "Feature",
  "properties": {
    "tgn:hierarchy":[
        "tgn:2786738",
        "tgn:1000001",
        "tgn:7012149",
        "tgn:2001843",
        "tgn:7007825",
        "tgn:7029392"
    ],
    "tgn:id":2786738,
    "tgn:name":"Zeb Mountain",
    "tgn:placetype":[
        "aat:300008798"
    ]
},
  "bbox": [],
  "geometry": {"coordinates":[-84.2667,36.4833],"type":"Point"}
}