{
  "id": 7113264,
  "type": "Feature",
  "properties": {
    "tgn:hierarchy":[
        "tgn:7113264",
        "tgn:7003669",
        "tgn:1000003",
        "tgn:7000084",
        "tgn:7029392"
    ],
    "tgn:id":7113264,
    "tgn:name":"Rieselberg",
    "tgn:placetype":[
        "aat:300008777"
    ]
},
  "bbox": [],
  "geometry": {"coordinates":[11.733333,49.266667],"type":"Point"}
}