{
  "id": 2359145,
  "type": "Feature",
  "properties": {
    "tgn:hierarchy":[
        "tgn:2359145",
        "tgn:1000001",
        "tgn:7012149",
        "tgn:7007157",
        "tgn:1002857",
        "tgn:7029392"
    ],
    "tgn:id":2359145,
    "tgn:name":"Granite Peak Plateau",
    "tgn:placetype":[
        "aat:300008798"
    ]
},
  "bbox": [],
  "geometry": {"coordinates":[-115.6833,34.7833],"type":"Point"}
}