{
  "id": 2234226,
  "type": "Feature",
  "properties": {
    "tgn:hierarchy":[
        "tgn:2234226",
        "tgn:7030516",
        "tgn:7006450",
        "tgn:1000001",
        "tgn:7012149",
        "tgn:7029392"
    ],
    "tgn:id":2234226,
    "tgn:name":"Chelan Bank",
    "tgn:placetype":[
        "aat:300132348"
    ]
},
  "bbox": [],
  "geometry": {"coordinates":[-166.55,54.0667],"type":"Point"}
}