{
  "id": 7547920,
  "type": "Feature",
  "properties": {
    "tgn:hierarchy":[
        "tgn:7547920",
        "tgn:1000004",
        "tgn:7000198",
        "tgn:7016788",
        "tgn:7029392"
    ],
    "tgn:id":7547920,
    "tgn:name:en":"Bhaisl\u0101na",
    "tgn:placetype":[
        "aat:300008347"
    ]
},
  "bbox": [],
  "geometry": {"coordinates":[75.116667,27.05],"type":"Point"}
}