{
  "id": 7227804,
  "type": "Feature",
  "properties": {
    "tgn:hierarchy":[
        "tgn:7227804",
        "tgn:7002751",
        "tgn:7001399",
        "tgn:1000003",
        "tgn:1000074",
        "tgn:7029392"
    ],
    "tgn:id":7227804,
    "tgn:name":"Go\u00faves, \u00d3rmos",
    "tgn:placetype":[
        "aat:300132316"
    ]
},
  "bbox": [],
  "geometry": {"coordinates":[23.25,39.033333],"type":"Point"}
}