{
  "id": 7345626,
  "type": "Feature",
  "properties": {
    "tgn:hierarchy":[
        "tgn:7345626",
        "tgn:7007088",
        "tgn:1000003",
        "tgn:7009604",
        "tgn:1000095",
        "tgn:7029392"
    ],
    "tgn:id":7345626,
    "tgn:name":"Ali",
    "tgn:placetype":[
        "aat:300008347"
    ]
},
  "bbox": [],
  "geometry": {"coordinates":[-2.701697,42.854758],"type":"Point"}
}