{
  "id": 2168531,
  "type": "Feature",
  "properties": {
    "tgn:hierarchy":[
        "tgn:2168531",
        "tgn:1000001",
        "tgn:7012149",
        "tgn:2000291",
        "tgn:7007240",
        "tgn:7029392"
    ],
    "tgn:id":2168531,
    "tgn:name":"Big Hill",
    "tgn:placetype":[
        "aat:300008798"
    ]
},
  "bbox": [],
  "geometry": {"coordinates":[-85.7667,30.6667],"type":"Point"}
}