{
  "id": 2359951,
  "type": "Feature",
  "properties": {
    "tgn:hierarchy":[
        "tgn:2359951",
        "tgn:7002659",
        "tgn:1000001",
        "tgn:7012149",
        "tgn:2000060",
        "tgn:7029392"
    ],
    "tgn:id":2359951,
    "tgn:name":"Grasmere",
    "tgn:placetype":[
        "aat:300008347"
    ]
},
  "bbox": [],
  "geometry": {"coordinates":[-86.3167,33.3833],"type":"Point"}
}