{
  "id": 2633006,
  "type": "Feature",
  "properties": {
    "tgn:hierarchy":[
        "tgn:2633006",
        "tgn:1000001",
        "tgn:7012149",
        "tgn:7007158",
        "tgn:2000244",
        "tgn:7029392"
    ],
    "tgn:id":2633006,
    "tgn:name":"Rudifor Lake",
    "tgn:placetype":[
        "aat:300008680"
    ]
},
  "bbox": [],
  "geometry": {"coordinates":[-106.6667,37.5167],"type":"Point"}
}