{
  "id": 7368147,
  "type": "Feature",
  "properties": {
    "tgn:hierarchy":[
        "tgn:7368147",
        "tgn:1001835",
        "tgn:1000001",
        "tgn:7005560",
        "tgn:7029392"
    ],
    "tgn:id":7368147,
    "tgn:name":"Granja El Gandul",
    "tgn:placetype":[
        "aat:300008347"
    ]
},
  "bbox": [],
  "geometry": {"coordinates":[-116.716667,32.483333],"type":"Point"}
}