{
  "id": 2012854,
  "type": "Feature",
  "properties": {
    "tgn:hierarchy":[
        "tgn:2012854",
        "tgn:1000001",
        "tgn:7012149",
        "tgn:7007157",
        "tgn:1002857",
        "tgn:7029392"
    ],
    "tgn:id":2012854,
    "tgn:name":"Mount Baldy",
    "tgn:placetype":[
        "aat:300008347"
    ]
},
  "bbox": [],
  "geometry": {"coordinates":[-117.65,34.2333],"type":"Point"}
}