{
  "id": 7272281,
  "type": "Feature",
  "properties": {
    "tgn:concordances":{
        "gn:id":"2745693"
    },
    "tgn:hierarchy":[
        "tgn:7272281",
        "tgn:1000003",
        "tgn:7003622",
        "tgn:7016845",
        "tgn:7029392"
    ],
    "tgn:id":7272281,
    "tgn:name:nl":"Veld-Oostenrijk",
    "tgn:placetype":[
        "aat:300008347"
    ]
},
  "bbox": [],
  "geometry": {"coordinates":[6.05,51.466667],"type":"Point"}
}