{
  "id": 2074460,
  "type": "Feature",
  "properties": {
    "tgn:hierarchy":[
        "tgn:2074460",
        "tgn:1000001",
        "tgn:7012149",
        "tgn:2001534",
        "tgn:7007709",
        "tgn:7029392"
    ],
    "tgn:id":2074460,
    "tgn:name":"Echo",
    "tgn:placetype":[
        "aat:300008347",
        "aat:300387210"
    ]
},
  "bbox": [],
  "geometry": {"coordinates":[-79.2667,34.4833],"type":"Point"}
}