{
  "id": 2199962,
  "type": "Feature",
  "properties": {
    "tgn:hierarchy":[
        "tgn:2199962",
        "tgn:1000001",
        "tgn:7012149",
        "tgn:2001543",
        "tgn:7007709",
        "tgn:7029392"
    ],
    "tgn:id":2199962,
    "tgn:name":"Brushy Branch",
    "tgn:placetype":[
        "aat:300008699"
    ]
},
  "bbox": [],
  "geometry": {"coordinates":[-83.6167,35.5333],"type":"Point"}
}