<<<<<<< HEAD
{
  "id": 7249128,
  "type": "Feature",
  "properties": {
    "tgn:hierarchy":[
        "tgn:7249128",
        "tgn:7003456",
        "tgn:1000003",
        "tgn:1000063",
        "tgn:7018236",
        "tgn:7029392"
    ],
    "tgn:id":7249128,
    "tgn:name":"Plinkenberg",
    "tgn:placetype":[
        "aat:300005567"
    ]
},
  "bbox": [],
  "geometry": {"coordinates":[4.466667,51.216667],"type":"Point"}
}
=======
{"geometry":{"type":"Point","coordinates":[4.466667,51.216667]},"type":"Feature","properties":{"hierarchy":["tgn:7249128","tgn:7003456","tgn:1000003","tgn:1000063","tgn:7018236","tgn:7029392"],"placetype":["aat:300005567"],"id":7249128,"name:xx":"Plinkenberg"}}
>>>>>>> 03f74aca74312dbeaf24d7e61306dd6a786dc3d0
