{
  "id": 2261471,
  "type": "Feature",
  "properties": {
    "tgn:hierarchy":[
        "tgn:2261471",
        "tgn:1000001",
        "tgn:7012149",
        "tgn:2001029",
        "tgn:7007521",
        "tgn:7029392"
    ],
    "tgn:id":2261471,
    "tgn:name":"Courtney Lake",
    "tgn:placetype":[
        "aat:300008680"
    ]
},
  "bbox": [],
  "geometry": {"coordinates":[-93.4833,47.5833],"type":"Point"}
}