{
  "id": 7467413,
  "type": "Feature",
  "properties": {
    "tgn:hierarchy":[
        "tgn:7467413",
        "tgn:1000004",
        "tgn:7491221",
        "tgn:1000141",
        "tgn:7029392"
    ],
    "tgn:id":7467413,
    "tgn:name":"Jianshi Qiao",
    "tgn:placetype":[
        "aat:300007836"
    ]
},
  "bbox": [],
  "geometry": {"coordinates":[121.260545,22.908197],"type":"Point"}
}