<<<<<<< HEAD
{
  "id": 7058135,
  "type": "Feature",
  "properties": {
    "tgn:hierarchy":[
        "tgn:7058135",
        "tgn:7003166",
        "tgn:1000003",
        "tgn:7009760",
        "tgn:1000080",
        "tgn:7029392"
    ],
    "tgn:id":7058135,
    "tgn:name":"Brancorsi",
    "tgn:placetype":[
        "aat:300008347"
    ]
},
  "bbox": [],
  "geometry": {"coordinates":[10.65,43.15],"type":"Point"}
}
=======
{"geometry":{"type":"Point","coordinates":[10.650000,43.150000]},"type":"Feature","properties":{"hierarchy":["tgn:7058135","tgn:7003166","tgn:1000003","tgn:7009760","tgn:1000080","tgn:7029392"],"placetype":["aat:300008347"],"id":7058135,"name:xx":"Brancorsi"}}
>>>>>>> 03f74aca74312dbeaf24d7e61306dd6a786dc3d0
