{
  "id": 2549149,
  "type": "Feature",
  "properties": {
    "tgn:hierarchy":[
        "tgn:2549149",
        "tgn:1000001",
        "tgn:7012149",
        "tgn:2001454",
        "tgn:7007566",
        "tgn:7029392"
    ],
    "tgn:id":2549149,
    "tgn:name":"North Red Bird",
    "tgn:placetype":[
        "aat:300000390"
    ]
},
  "bbox": [],
  "geometry": {"coordinates":[-106.2333,35.65],"type":"Point"}
}