{
  "id": 2637434,
  "type": "Feature",
  "properties": {
    "tgn:hierarchy":[
        "tgn:2637434",
        "tgn:2000090",
        "tgn:1000001",
        "tgn:7006451",
        "tgn:7012149",
        "tgn:7029392"
    ],
    "tgn:id":2637434,
    "tgn:name":"Saint Josephs Reservoir",
    "tgn:placetype":[
        "aat:300006191"
    ]
},
  "bbox": [],
  "geometry": {"coordinates":[-109.3333,33.9833],"type":"Point"}
}