{
  "id": 2083507,
  "type": "Feature",
  "properties": {
    "tgn:hierarchy":[
        "tgn:2083507",
        "tgn:1000001",
        "tgn:7012149",
        "tgn:2001694",
        "tgn:7007707",
        "tgn:7029392"
    ],
    "tgn:id":2083507,
    "tgn:name":"Leonard",
    "tgn:placetype":[
        "aat:300008347"
    ]
},
  "bbox": [],
  "geometry": {"coordinates":[-95.7833,35.9167],"type":"Point"}
}