{
  "id": 2629994,
  "type": "Feature",
  "properties": {
    "tgn:hierarchy":[
        "tgn:2629994",
        "tgn:1000001",
        "tgn:2000863",
        "tgn:7012149",
        "tgn:7007256",
        "tgn:7029392"
    ],
    "tgn:id":2629994,
    "tgn:name":"Rossignol",
    "tgn:placetype":[
        "aat:300008347"
    ]
},
  "bbox": [],
  "geometry": {"coordinates":[-92.9833,30.1167],"type":"Point"}
}