<<<<<<< HEAD
{
  "id": 7174227,
  "type": "Feature",
  "properties": {
    "tgn:hierarchy":[
        "tgn:7174227",
        "tgn:7003692",
        "tgn:1000003",
        "tgn:7000084",
        "tgn:7029392"
    ],
    "tgn:id":7174227,
    "tgn:name":"Grunbach",
    "tgn:placetype":[
        "aat:300008347"
    ]
},
  "bbox": [],
  "geometry": {"coordinates":[9.416667,48.816667],"type":"Point"}
}
=======
{"geometry":{"type":"Point","coordinates":[9.416667,48.816667]},"type":"Feature","properties":{"hierarchy":["tgn:7174227","tgn:7003692","tgn:1000003","tgn:7000084","tgn:7029392"],"placetype":["aat:300008347"],"id":7174227,"name:xx":"Grunbach"}}
>>>>>>> 03f74aca74312dbeaf24d7e61306dd6a786dc3d0
