{
  "id": 1018303,
  "type": "Feature",
  "properties": {
    "tgn:hierarchy":[
        "tgn:1018303",
        "tgn:1000001",
        "tgn:7005591",
        "tgn:7005560",
        "tgn:7029392"
    ],
    "tgn:id":1018303,
    "tgn:name":"Santa Mar\u00eda Colotepec",
    "tgn:placetype":[
        "aat:300008347"
    ]
},
  "bbox": [],
  "geometry": {"coordinates":[-96.916667,15.883333],"type":"Point"}
}