{
  "id": 2233676,
  "type": "Feature",
  "properties": {
    "tgn:hierarchy":[
        "tgn:2233676",
        "tgn:1000001",
        "tgn:7012149",
        "tgn:2000560",
        "tgn:7007252",
        "tgn:7029392"
    ],
    "tgn:id":2233676,
    "tgn:name":"Chase Lake",
    "tgn:placetype":[
        "aat:300006191"
    ]
},
  "bbox": [],
  "geometry": {"coordinates":[-87.35,37.95],"type":"Point"}
}