{
  "id": 2713727,
  "type": "Feature",
  "properties": {
    "tgn:hierarchy":[
        "tgn:2713727",
        "tgn:1000001",
        "tgn:2001260",
        "tgn:7012149",
        "tgn:7007524",
        "tgn:7029392"
    ],
    "tgn:id":2713727,
    "tgn:name":"Tebo Ditch Number 13",
    "tgn:placetype":[
        "aat:300006075"
    ]
},
  "bbox": [],
  "geometry": {"coordinates":[-113.3333,45.25],"type":"Point"}
}