<<<<<<< HEAD
{
  "id": 7471398,
  "type": "Feature",
  "properties": {
    "tgn:hierarchy":[
        "tgn:7471398",
        "tgn:7468018",
        "tgn:1000004",
        "tgn:1000141",
        "tgn:7029392"
    ],
    "tgn:id":7471398,
    "tgn:name":"Zhuoshui Xi",
    "tgn:placetype":[
        "aat:300008699"
    ]
},
  "bbox": [],
  "geometry": {"coordinates":[120.520556,23.498889],"type":"Point"}
}
=======
{"geometry":{"type":"Point","coordinates":[120.520556,23.498889]},"type":"Feature","properties":{"hierarchy":["tgn:7471398","tgn:7468018","tgn:1000004","tgn:1000141","tgn:7029392"],"placetype":["aat:300008699"],"id":7471398,"name:xx":"Zhuoshui Xi"}}
>>>>>>> 03f74aca74312dbeaf24d7e61306dd6a786dc3d0
