{
  "id": 2548999,
  "type": "Feature",
  "properties": {
    "tgn:hierarchy":[
        "tgn:2548999",
        "tgn:1002933",
        "tgn:1000001",
        "tgn:7012149",
        "tgn:7007239",
        "tgn:7029392"
    ],
    "tgn:id":2548999,
    "tgn:name":"North Prong",
    "tgn:placetype":[
        "aat:300008699"
    ]
},
  "bbox": [],
  "geometry": {"coordinates":[-75.35,38.8167],"type":"Point"}
}