{
  "id": 2786468,
  "type": "Feature",
  "properties": {
    "tgn:hierarchy":[
        "tgn:2786468",
        "tgn:1000001",
        "tgn:7012149",
        "tgn:7007157",
        "tgn:1002857",
        "tgn:7029392"
    ],
    "tgn:id":2786468,
    "tgn:name":"Yucca Mine",
    "tgn:placetype":[
        "aat:300000390"
    ]
},
  "bbox": [],
  "geometry": {"coordinates":[-115.9167,35.45],"type":"Point"}
}