{
  "id": 2110637,
  "type": "Feature",
  "properties": {
    "tgn:hierarchy":[
        "tgn:2110637",
        "tgn:1000001",
        "tgn:7012149",
        "tgn:2002187",
        "tgn:7007919",
        "tgn:7029392"
    ],
    "tgn:id":2110637,
    "tgn:name":"Bergton",
    "tgn:placetype":[
        "aat:300008347"
    ]
},
  "bbox": [],
  "geometry": {"coordinates":[-78.9333,38.75],"type":"Point"}
}