<<<<<<< HEAD
{
  "id": 2338670,
  "type": "Feature",
  "properties": {
    "tgn:hierarchy":[
        "tgn:2338670",
        "tgn:1000001",
        "tgn:7012149",
        "tgn:2002196",
        "tgn:7007919",
        "tgn:7029392"
    ],
    "tgn:id":2338670,
    "tgn:name":"Francis Mill Creek",
    "tgn:placetype":[
        "aat:300008706"
    ]
},
  "bbox": [],
  "geometry": {"coordinates":[-81.0833,36.7667],"type":"Point"}
}
=======
{"geometry":{"type":"Point","coordinates":[-81.083300,36.766700]},"type":"Feature","properties":{"hierarchy":["tgn:2338670","tgn:1000001","tgn:7012149","tgn:2002196","tgn:7007919","tgn:7029392"],"placetype":["aat:300008706"],"id":2338670,"name:xx":"Francis Mill Creek"}}
>>>>>>> 03f74aca74312dbeaf24d7e61306dd6a786dc3d0
