{
  "id": 7337562,
  "type": "Feature",
  "properties": {
    "tgn:hierarchy":[
        "tgn:7337562",
        "tgn:7002839",
        "tgn:7001158",
        "tgn:1000003",
        "tgn:1000095",
        "tgn:7029392"
    ],
    "tgn:id":7337562,
    "tgn:name":"Chico, R\u00edo",
    "tgn:placetype":[
        "aat:300008699"
    ]
},
  "bbox": [],
  "geometry": {"coordinates":[-4.316667,40.883333],"type":"Point"}
}