<<<<<<< HEAD
{
  "id": 2768230,
  "type": "Feature",
  "properties": {
    "tgn:hierarchy":[
        "tgn:2768230",
        "tgn:1000001",
        "tgn:2002254",
        "tgn:7012149",
        "tgn:7013961",
        "tgn:7029392"
    ],
    "tgn:id":2768230,
    "tgn:name":"Whites Knob",
    "tgn:placetype":[
        "aat:300008798"
    ]
},
  "bbox": [],
  "geometry": {"coordinates":[-78.1167,39.55],"type":"Point"}
}
=======
{"geometry":{"type":"Point","coordinates":[-78.116700,39.550000]},"type":"Feature","properties":{"hierarchy":["tgn:2768230","tgn:1000001","tgn:2002254","tgn:7012149","tgn:7013961","tgn:7029392"],"placetype":["aat:300008798"],"id":2768230,"name:xx":"Whites Knob"}}
>>>>>>> 03f74aca74312dbeaf24d7e61306dd6a786dc3d0
