{
  "id": 2730861,
  "type": "Feature",
  "properties": {
    "tgn:hierarchy":[
        "tgn:2730861",
        "tgn:1000001",
        "tgn:7012149",
        "tgn:7014185",
        "tgn:7007710",
        "tgn:7029392"
    ],
    "tgn:id":2730861,
    "tgn:name":"Tub Run Cave",
    "tgn:placetype":[
        "aat:300008746"
    ]
},
  "bbox": [],
  "geometry": {"coordinates":[-79.4333,39.7833],"type":"Point"}
}