{
  "id": 2121983,
  "type": "Feature",
  "properties": {
    "tgn:hierarchy":[
        "tgn:2121983",
        "tgn:1000001",
        "tgn:1002316",
        "tgn:7012149",
        "tgn:7007922",
        "tgn:7029392"
    ],
    "tgn:id":2121983,
    "tgn:name":"Nora",
    "tgn:placetype":[
        "aat:300008347",
        "aat:300387210"
    ]
},
  "bbox": [],
  "geometry": {"coordinates":[-89.15,43.0167],"type":"Point"}
}