{
  "id": 7507098,
  "type": "Feature",
  "properties": {
    "tgn:hierarchy":[
        "tgn:7507098",
        "tgn:1009227",
        "tgn:1000226",
        "tgn:7018437",
        "tgn:1000006",
        "tgn:7029392"
    ],
    "tgn:id":7507098,
    "tgn:name:en":"Quoin Point",
    "tgn:placetype":[
        "aat:300386846"
    ]
},
  "bbox": [],
  "geometry": {"coordinates":[170.166667,-46.166667],"type":"Point"}
}