{
  "id": 7108245,
  "type": "Feature",
  "properties": {
    "tgn:hierarchy":[
        "tgn:7108245",
        "tgn:7003669",
        "tgn:1000003",
        "tgn:7000084",
        "tgn:7029392"
    ],
    "tgn:id":7108245,
    "tgn:name":"Rehenb\u00fchl",
    "tgn:placetype":[
        "aat:300008347"
    ]
},
  "bbox": [],
  "geometry": {"coordinates":[10.85,49.133333],"type":"Point"}
}