{
  "id": 2196201,
  "type": "Feature",
  "properties": {
    "tgn:hierarchy":[
        "tgn:2196201",
        "tgn:1000001",
        "tgn:7012149",
        "tgn:2000355",
        "tgn:7007248",
        "tgn:7029392"
    ],
    "tgn:id":2196201,
    "tgn:name":"Brogdon Hill",
    "tgn:placetype":[
        "aat:300008798"
    ]
},
  "bbox": [],
  "geometry": {"coordinates":[-84.9167,34.5333],"type":"Point"}
}