{
  "id": 1134836,
  "type": "Feature",
  "properties": {
    "tgn:hierarchy":[
        "tgn:1134836",
        "tgn:7016099",
        "tgn:1000001",
        "tgn:7012149",
        "tgn:7007516",
        "tgn:7029392"
    ],
    "tgn:id":1134836,
    "tgn:name":"Timber Run",
    "tgn:placetype":[
        "aat:300008706"
    ]
},
  "bbox": [],
  "geometry": {"coordinates":[-76.8333,39.4333],"type":"Point"}
}