{
  "id": 2474058,
  "type": "Feature",
  "properties": {
    "tgn:hierarchy":[
        "tgn:2474058",
        "tgn:1000001",
        "tgn:2000318",
        "tgn:7012149",
        "tgn:7007248",
        "tgn:7029392"
    ],
    "tgn:id":2474058,
    "tgn:name":"Lower Lake",
    "tgn:placetype":[
        "aat:300006191"
    ]
},
  "bbox": [],
  "geometry": {"coordinates":[-85.3333,34.4333],"type":"Point"}
}