{
  "id": 7287300,
  "type": "Feature",
  "properties": {
    "tgn:hierarchy":[
        "tgn:7287300",
        "tgn:1001699",
        "tgn:1000049",
        "tgn:1000002",
        "tgn:7029392"
    ],
    "tgn:id":7287300,
    "tgn:name":"Garrao Chico, Isla",
    "tgn:placetype":[
        "aat:300008791"
    ]
},
  "bbox": [],
  "geometry": {"coordinates":[-73.733333,-44.316667],"type":"Point"}
}