{
  "id": 2750472,
  "type": "Feature",
  "properties": {
    "tgn:hierarchy":[
        "tgn:2750472",
        "tgn:1000001",
        "tgn:1002601",
        "tgn:7012149",
        "tgn:7007159",
        "tgn:7029392"
    ],
    "tgn:id":2750472,
    "tgn:name":"Wannuppee Islands",
    "tgn:placetype":[
        "aat:300386853"
    ]
},
  "bbox": [],
  "geometry": {"coordinates":[-73.4167,41.5833],"type":"Point"}
}