{
  "id": 2431557,
  "type": "Feature",
  "properties": {
    "tgn:hierarchy":[
        "tgn:2431557",
        "tgn:1000001",
        "tgn:7012149",
        "tgn:1003041",
        "tgn:7007710",
        "tgn:7029392"
    ],
    "tgn:id":2431557,
    "tgn:name":"Kasson Brook",
    "tgn:placetype":[
        "aat:300008347"
    ]
},
  "bbox": [],
  "geometry": {"coordinates":[-76.1333,41.4667],"type":"Point"}
}