{
  "id": 7270202,
  "type": "Feature",
  "properties": {
    "tgn:hierarchy":[
        "tgn:7270202",
        "tgn:1000003",
        "tgn:7003613",
        "tgn:7016845",
        "tgn:7029392"
    ],
    "tgn:id":7270202,
    "tgn:name:nl":"Mussel-Aa",
    "tgn:placetype":[
        "aat:300008699"
    ]
},
  "bbox": [],
  "geometry": {"coordinates":[7.083333,53.05],"type":"Point"}
}