{
  "id": 2622657,
  "type": "Feature",
  "properties": {
    "tgn:hierarchy":[
        "tgn:2622657",
        "tgn:1000001",
        "tgn:2001364",
        "tgn:7012149",
        "tgn:7007525",
        "tgn:7029392"
    ],
    "tgn:id":2622657,
    "tgn:name":"Robinson Creek",
    "tgn:placetype":[
        "aat:300008706"
    ]
},
  "bbox": [],
  "geometry": {"coordinates":[-96.0833,40.2833],"type":"Point"}
}