{
  "id": 2016950,
  "type": "Feature",
  "properties": {
    "tgn:hierarchy":[
        "tgn:2016950",
        "tgn:1000001",
        "tgn:1003028",
        "tgn:7012149",
        "tgn:7007159",
        "tgn:7029392"
    ],
    "tgn:id":2016950,
    "tgn:name":"Grosvenor Dale",
    "tgn:placetype":[
        "aat:300008347"
    ]
},
  "bbox": [],
  "geometry": {"coordinates":[-71.8833,41.9667],"type":"Point"}
}