{
  "id": 7578418,
  "type": "Feature",
  "properties": {
    "tgn:hierarchy":[
        "tgn:7578418",
        "tgn:1000004",
        "tgn:7000198",
        "tgn:1001895",
        "tgn:7029392"
    ],
    "tgn:id":7578418,
    "tgn:name:en":"Sirasgaon",
    "tgn:placetype":[
        "aat:300008347"
    ]
},
  "bbox": [],
  "geometry": {"coordinates":[77.680278,21.330833],"type":"Point"}
}