{
  "id": 2513161,
  "type": "Feature",
  "properties": {
    "tgn:hierarchy":[
        "tgn:2513161",
        "tgn:1000001",
        "tgn:7012149",
        "tgn:2000481",
        "tgn:7007250",
        "tgn:7029392"
    ],
    "tgn:id":2513161,
    "tgn:name":"Mill Creek Lake",
    "tgn:placetype":[
        "aat:300006191"
    ]
},
  "bbox": [],
  "geometry": {"coordinates":[-113.3333,44.3833],"type":"Point"}
}