{
  "id": 2083208,
  "type": "Feature",
  "properties": {
    "tgn:hierarchy":[
        "tgn:2083208",
        "tgn:1000001",
        "tgn:7012149",
        "tgn:2001663",
        "tgn:7007707",
        "tgn:7029392"
    ],
    "tgn:id":2083208,
    "tgn:name":"Fallis",
    "tgn:placetype":[
        "aat:300008347"
    ]
},
  "bbox": [],
  "geometry": {"coordinates":[-97.1167,35.7333],"type":"Point"}
}