{
  "id": 2432274,
  "type": "Feature",
  "properties": {
    "tgn:hierarchy":[
        "tgn:2432274",
        "tgn:7023902",
        "tgn:1000001",
        "tgn:7012149",
        "tgn:7007249",
        "tgn:7029392"
    ],
    "tgn:id":2432274,
    "tgn:name":"Kealakaha Stream",
    "tgn:placetype":[
        "aat:300008699"
    ]
},
  "bbox": [],
  "geometry": {"coordinates":[-155.3333,19.9167],"type":"Point"}
}