{
  "id": 7511811,
  "type": "Feature",
  "properties": {
    "tgn:hierarchy":[
        "tgn:7511811",
        "tgn:1008380",
        "tgn:7000507",
        "tgn:1000226",
        "tgn:1000006",
        "tgn:7029392"
    ],
    "tgn:id":7511811,
    "tgn:name:en":"Kanono Pa",
    "tgn:placetype":[
        "aat:300008777"
    ]
},
  "bbox": [],
  "geometry": {"coordinates":[174.166667,-36.366667],"type":"Point"}
}