{
  "id": 7403753,
  "type": "Feature",
  "properties": {
    "tgn:hierarchy":[
        "tgn:7403753",
        "tgn:7005585",
        "tgn:1000001",
        "tgn:7005560",
        "tgn:7029392"
    ],
    "tgn:id":7403753,
    "tgn:name":"La Mesa del Cerro Azul",
    "tgn:placetype":[
        "aat:300008347"
    ]
},
  "bbox": [],
  "geometry": {"coordinates":[-100.641667,17.75],"type":"Point"}
}