{
  "id": 7547840,
  "type": "Feature",
  "properties": {
    "tgn:hierarchy":[
        "tgn:7547840",
        "tgn:1000004",
        "tgn:7000198",
        "tgn:1001882",
        "tgn:7029392"
    ],
    "tgn:id":7547840,
    "tgn:name:en":"Bannigere",
    "tgn:placetype":[
        "aat:300008347"
    ]
},
  "bbox": [],
  "geometry": {"coordinates":[77.433333,12.75],"type":"Point"}
}