{
  "id": 2063185,
  "type": "Feature",
  "properties": {
    "tgn:hierarchy":[
        "tgn:2063185",
        "tgn:1000001",
        "tgn:7012149",
        "tgn:1002999",
        "tgn:7007526",
        "tgn:7029392"
    ],
    "tgn:id":2063185,
    "tgn:name":"Vya",
    "tgn:placetype":[
        "aat:300008347",
        "aat:300387210"
    ]
},
  "bbox": [],
  "geometry": {"coordinates":[-119.85,41.5833],"type":"Point"}
}