{
  "id": 2153813,
  "type": "Feature",
  "properties": {
    "tgn:hierarchy":[
        "tgn:2153813",
        "tgn:1000001",
        "tgn:7012149",
        "tgn:7007157",
        "tgn:1002684",
        "tgn:7029392"
    ],
    "tgn:id":2153813,
    "tgn:name":"Bear Canyon",
    "tgn:placetype":[
        "aat:300008761"
    ]
},
  "bbox": [],
  "geometry": {"coordinates":[-121.35,36.15],"type":"Point"}
}