<<<<<<< HEAD
{
  "id": 7178248,
  "type": "Feature",
  "properties": {
    "tgn:hierarchy":[
        "tgn:7178248",
        "tgn:7003669",
        "tgn:1000003",
        "tgn:7000084",
        "tgn:7029392"
    ],
    "tgn:id":7178248,
    "tgn:name":"Haindlfing",
    "tgn:placetype":[
        "aat:300008347"
    ]
},
  "bbox": [],
  "geometry": {"coordinates":[11.716667,48.433333],"type":"Point"}
}
=======
{"geometry":{"type":"Point","coordinates":[11.716667,48.433333]},"type":"Feature","properties":{"hierarchy":["tgn:7178248","tgn:7003669","tgn:1000003","tgn:7000084","tgn:7029392"],"placetype":["aat:300008347"],"id":7178248,"name:xx":"Haindlfing"}}
>>>>>>> 03f74aca74312dbeaf24d7e61306dd6a786dc3d0
