<<<<<<< HEAD
{
  "id": 2338189,
  "type": "Feature",
  "properties": {
    "tgn:hierarchy":[
        "tgn:2338189",
        "tgn:1000001",
        "tgn:7012149",
        "tgn:1002924",
        "tgn:7007568",
        "tgn:7029392"
    ],
    "tgn:id":2338189,
    "tgn:name":"Fox Pond",
    "tgn:placetype":[
        "aat:300008680"
    ]
},
  "bbox": [],
  "geometry": {"coordinates":[-72.8,40.8833],"type":"Point"}
}
=======
{"geometry":{"type":"Point","coordinates":[-72.800000,40.883300]},"type":"Feature","properties":{"hierarchy":["tgn:2338189","tgn:1000001","tgn:7012149","tgn:1002924","tgn:7007568","tgn:7029392"],"placetype":["aat:300008680"],"id":2338189,"name:xx":"Fox Pond"}}
>>>>>>> 03f74aca74312dbeaf24d7e61306dd6a786dc3d0
