{
  "id": 7314197,
  "type": "Feature",
  "properties": {
    "tgn:hierarchy":[
        "tgn:7314197",
        "tgn:1001695",
        "tgn:1000049",
        "tgn:1000002",
        "tgn:7029392"
    ],
    "tgn:id":7314197,
    "tgn:name":"Estaci\u00f3n Loreto",
    "tgn:placetype":[
        "aat:300007783"
    ]
},
  "bbox": [],
  "geometry": {"coordinates":[-71.033333,-34.266667],"type":"Point"}
}