{
  "id": 2183267,
  "type": "Feature",
  "properties": {
    "tgn:hierarchy":[
        "tgn:2183267",
        "tgn:1000001",
        "tgn:7012149",
        "tgn:2001448",
        "tgn:7007566",
        "tgn:7029392"
    ],
    "tgn:id":2183267,
    "tgn:name":"Bluewater Creek",
    "tgn:placetype":[
        "aat:300008706"
    ]
},
  "bbox": [],
  "geometry": {"coordinates":[-103.8333,35.0667],"type":"Point"}
}