{
  "id": 7055484,
  "type": "Feature",
  "properties": {
    "tgn:hierarchy":[
        "tgn:7055484",
        "tgn:7003127",
        "tgn:1000003",
        "tgn:7008516",
        "tgn:1000080",
        "tgn:7029392"
    ],
    "tgn:id":7055484,
    "tgn:name":"Podere San Pancrazio",
    "tgn:placetype":[
        "aat:300008347"
    ]
},
  "bbox": [],
  "geometry": {"coordinates":[11.383333,44.716667],"type":"Point"}
}