{
  "id": 1018430,
  "type": "Feature",
  "properties": {
    "tgn:hierarchy":[
        "tgn:1018430",
        "tgn:7005578",
        "tgn:1000001",
        "tgn:7005560",
        "tgn:7029392"
    ],
    "tgn:id":1018430,
    "tgn:name":"Tenabo",
    "tgn:placetype":[
        "aat:300008347"
    ]
},
  "bbox": [],
  "geometry": {"coordinates":[-90.233333,20.05],"type":"Point"}
}