{
  "id": 2637183,
  "type": "Feature",
  "properties": {
    "tgn:hierarchy":[
        "tgn:2637183",
        "tgn:1000001",
        "tgn:1002294",
        "tgn:7012149",
        "tgn:7007710",
        "tgn:7029392"
    ],
    "tgn:id":2637183,
    "tgn:name":"Saint Gabriel Hill",
    "tgn:placetype":[
        "aat:300008798"
    ]
},
  "bbox": [],
  "geometry": {"coordinates":[-76.35,41.2333],"type":"Point"}
}