<<<<<<< HEAD
{
  "id": 7243354,
  "type": "Feature",
  "properties": {
    "tgn:hierarchy":[
        "tgn:7243354",
        "tgn:7003456",
        "tgn:1000003",
        "tgn:1000063",
        "tgn:7018236",
        "tgn:7029392"
    ],
    "tgn:id":7243354,
    "tgn:name":"Kruiningenhoeve",
    "tgn:placetype":[
        "aat:300000206"
    ]
},
  "bbox": [],
  "geometry": {"coordinates":[4.483333,51.233333],"type":"Point"}
}
=======
{"geometry":{"type":"Point","coordinates":[4.483333,51.233333]},"type":"Feature","properties":{"hierarchy":["tgn:7243354","tgn:7003456","tgn:1000003","tgn:1000063","tgn:7018236","tgn:7029392"],"placetype":["aat:300000206"],"id":7243354,"name:xx":"Kruiningenhoeve"}}
>>>>>>> 03f74aca74312dbeaf24d7e61306dd6a786dc3d0
