{
  "id": 7482529,
  "type": "Feature",
  "properties": {
    "tgn:hierarchy":[
        "tgn:7482529",
        "tgn:1000004",
        "tgn:7490934",
        "tgn:1000141",
        "tgn:7029392"
    ],
    "tgn:id":7482529,
    "tgn:name":"Gongguan",
    "tgn:placetype":[
        "aat:300008347"
    ]
},
  "bbox": [],
  "geometry": {"coordinates":[120.363294,23.175759],"type":"Point"}
}