{
  "id": 2748563,
  "type": "Feature",
  "properties": {
    "tgn:hierarchy":[
        "tgn:2748563",
        "tgn:1000001",
        "tgn:7012149",
        "tgn:7007157",
        "tgn:2000188",
        "tgn:7029392"
    ],
    "tgn:id":2748563,
    "tgn:name":"Walker Mine",
    "tgn:placetype":[
        "aat:300000390"
    ]
},
  "bbox": [],
  "geometry": {"coordinates":[-122.4167,40.65],"type":"Point"}
}