{
  "id": 2093047,
  "type": "Feature",
  "properties": {
    "tgn:hierarchy":[
        "tgn:2093047",
        "tgn:1000001",
        "tgn:7012149",
        "tgn:1002494",
        "tgn:7007710",
        "tgn:7029392"
    ],
    "tgn:id":2093047,
    "tgn:name":"Shirleysburg",
    "tgn:placetype":[
        "aat:300008347"
    ]
},
  "bbox": [],
  "geometry": {"coordinates":[-77.8667,40.2833],"type":"Point"}
}