{
  "id": 2415663,
  "type": "Feature",
  "properties": {
    "tgn:hierarchy":[
        "tgn:2415663",
        "tgn:1000001",
        "tgn:7012149",
        "tgn:2001456",
        "tgn:7007566",
        "tgn:7029392"
    ],
    "tgn:id":2415663,
    "tgn:name":"Italian Canyon",
    "tgn:placetype":[
        "aat:300008761"
    ]
},
  "bbox": [],
  "geometry": {"coordinates":[-107.15,33.9333],"type":"Point"}
}