{
  "id": 7133849,
  "type": "Feature",
  "properties": {
    "tgn:hierarchy":[
        "tgn:7133849",
        "tgn:1000003",
        "tgn:7003677",
        "tgn:7000084",
        "tgn:7029392"
    ],
    "tgn:id":7133849,
    "tgn:name":"M\u00fcnchheide",
    "tgn:placetype":[
        "aat:300008347"
    ]
},
  "bbox": [],
  "geometry": {"coordinates":[6.516667,51.266667],"type":"Point"}
}