<<<<<<< HEAD
{
  "id": 2338156,
  "type": "Feature",
  "properties": {
    "tgn:hierarchy":[
        "tgn:2338156",
        "tgn:7006450",
        "tgn:1000001",
        "tgn:7012149",
        "tgn:2124005",
        "tgn:7029392"
    ],
    "tgn:id":2338156,
    "tgn:name":"Fox Point",
    "tgn:placetype":[
        "aat:300008798"
    ]
},
  "bbox": [],
  "geometry": {"coordinates":[-143.8667,69.3],"type":"Point"}
}
=======
{"geometry":{"type":"Point","coordinates":[-143.866700,69.300000]},"type":"Feature","properties":{"hierarchy":["tgn:2338156","tgn:7006450","tgn:1000001","tgn:7012149","tgn:2124005","tgn:7029392"],"placetype":["aat:300008798"],"id":2338156,"name:xx":"Fox Point"}}
>>>>>>> 03f74aca74312dbeaf24d7e61306dd6a786dc3d0
