{
  "id": 2498258,
  "type": "Feature",
  "properties": {
    "tgn:hierarchy":[
        "tgn:2498258",
        "tgn:1000001",
        "tgn:1002245",
        "tgn:7012149",
        "tgn:7007568",
        "tgn:7029392"
    ],
    "tgn:id":2498258,
    "tgn:name":"Mc Cann Hollow",
    "tgn:placetype":[
        "aat:300008761"
    ]
},
  "bbox": [],
  "geometry": {"coordinates":[-78.45,42.05],"type":"Point"}
}