{
  "id": 7456116,
  "type": "Feature",
  "properties": {
    "tgn:hierarchy":[
        "tgn:7456116",
        "tgn:7002444",
        "tgn:1000003",
        "tgn:7008082",
        "tgn:7008591",
        "tgn:7029392"
    ],
    "tgn:id":7456116,
    "tgn:name:en":"Droma, Loch",
    "tgn:placetype":[
        "aat:300008680"
    ]
},
  "bbox": [],
  "geometry": {"coordinates":[-4.916667,57.733333],"type":"Point"}
}