{
  "id": 2460125,
  "type": "Feature",
  "properties": {
    "tgn:hierarchy":[
        "tgn:2460125",
        "tgn:1000001",
        "tgn:7012149",
        "tgn:2001120",
        "tgn:7007522",
        "tgn:7029392"
    ],
    "tgn:id":2460125,
    "tgn:name":"Little Ross Branch",
    "tgn:placetype":[
        "aat:300008699"
    ]
},
  "bbox": [],
  "geometry": {"coordinates":[-88.55,32.7333],"type":"Point"}
}