<<<<<<< HEAD
{
  "id": 2332459,
  "type": "Feature",
  "properties": {
    "tgn:hierarchy":[
        "tgn:2332459",
        "tgn:7006450",
        "tgn:1000001",
        "tgn:7012149",
        "tgn:2000089",
        "tgn:7029392"
    ],
    "tgn:id":2332459,
    "tgn:name":"Florence Islands",
    "tgn:placetype":[
        "aat:300386853"
    ]
},
  "bbox": [],
  "geometry": {"coordinates":[-154.8667,65.8],"type":"Point"}
}
=======
{"geometry":{"type":"Point","coordinates":[-154.866700,65.800000]},"type":"Feature","properties":{"hierarchy":["tgn:2332459","tgn:7006450","tgn:1000001","tgn:7012149","tgn:2000089","tgn:7029392"],"placetype":["aat:300386853"],"id":2332459,"name:xx":"Florence Islands"}}
>>>>>>> 03f74aca74312dbeaf24d7e61306dd6a786dc3d0
