{
  "id": 7040708,
  "type": "Feature",
  "properties": {
    "tgn:hierarchy":[
        "tgn:7040708",
        "tgn:7002994",
        "tgn:1000003",
        "tgn:7002997",
        "tgn:1000080",
        "tgn:7029392"
    ],
    "tgn:id":7040708,
    "tgn:name":"San Pietro Viminario",
    "tgn:placetype":[
        "aat:300008347"
    ]
},
  "bbox": [],
  "geometry": {"coordinates":[11.816667,45.233333],"type":"Point"}
}