{
  "id": 1070478,
  "type": "Feature",
  "properties": {
    "tgn:hierarchy":[
        "tgn:1070478",
        "tgn:1000004",
        "tgn:7002079",
        "tgn:1000111",
        "tgn:7029392"
    ],
    "tgn:id":1070478,
    "tgn:name":"Miluo",
    "tgn:placetype":[
        "aat:300008347"
    ]
},
  "bbox": [],
  "geometry": {"coordinates":[113.0833,28.8333],"type":"Point"}
}