{
  "id": 2326630,
  "type": "Feature",
  "properties": {
    "tgn:hierarchy":[
        "tgn:2326630",
        "tgn:1002172",
        "tgn:1000001",
        "tgn:7012149",
        "tgn:7007710",
        "tgn:7029392"
    ],
    "tgn:id":2326630,
    "tgn:name":"Finlyville",
    "tgn:placetype":[
        "aat:300008347"
    ]
},
  "bbox": [],
  "geometry": {"coordinates":[-78.1833,40.15],"type":"Point"}
}