{
  "id": 2216711,
  "type": "Feature",
  "properties": {
    "tgn:hierarchy":[
        "tgn:2216711",
        "tgn:1000001",
        "tgn:2001411",
        "tgn:7012149",
        "tgn:7007526",
        "tgn:7029392"
    ],
    "tgn:id":2216711,
    "tgn:name":"Camp Draw",
    "tgn:placetype":[
        "aat:300008761"
    ]
},
  "bbox": [],
  "geometry": {"coordinates":[-115.4167,41.75],"type":"Point"}
}