{
  "id": 7024016,
  "type": "Feature",
  "properties": {
    "tgn:hierarchy":[
        "tgn:7024016",
        "tgn:1000225",
        "tgn:1000006",
        "tgn:7029392"
    ],
    "tgn:id":7024016,
    "tgn:name":"Malampa",
    "tgn:placetype":[
        "aat:300387064",
        "aat:300000774"
    ]
},
  "bbox": [],
  "geometry": {"coordinates":[167.75,-16.25],"type":"Point"}
}