{
  "id": 1077093,
  "type": "Feature",
  "properties": {
    "tgn:hierarchy":[
        "tgn:1077093",
        "tgn:1000004",
        "tgn:7000198",
        "tgn:1001882",
        "tgn:7029392"
    ],
    "tgn:id":1077093,
    "tgn:name:en":"T\u0101l\u012bkota",
    "tgn:placetype":[
        "aat:300008347"
    ]
},
  "bbox": [],
  "geometry": {"coordinates":[76.31,-16.476],"type":"Point"}
}