{
  "id": 2176926,
  "type": "Feature",
  "properties": {
    "tgn:hierarchy":[
        "tgn:2176926",
        "tgn:2001423",
        "tgn:1000001",
        "tgn:7012149",
        "tgn:7007564",
        "tgn:7029392"
    ],
    "tgn:id":2176926,
    "tgn:name":"Black Mountain Cabin",
    "tgn:placetype":[
        "aat:300008347"
    ]
},
  "bbox": [],
  "geometry": {"coordinates":[-71.1667,44.1833],"type":"Point"}
}