{
  "id": 7128936,
  "type": "Feature",
  "properties": {
    "tgn:hierarchy":[
        "tgn:7128936",
        "tgn:7003692",
        "tgn:1000003",
        "tgn:7000084",
        "tgn:7029392"
    ],
    "tgn:id":7128936,
    "tgn:name":"Nordwasser",
    "tgn:placetype":[
        "aat:300000206"
    ]
},
  "bbox": [],
  "geometry": {"coordinates":[8.166667,48.466667],"type":"Point"}
}