<<<<<<< HEAD
{
  "id": 7358545,
  "type": "Feature",
  "properties": {
    "tgn:hierarchy":[
        "tgn:7358545",
        "tgn:7005578",
        "tgn:1000001",
        "tgn:7005560",
        "tgn:7029392"
    ],
    "tgn:id":7358545,
    "tgn:name":"Delia",
    "tgn:placetype":[
        "aat:300008347"
    ]
},
  "bbox": [],
  "geometry": {"coordinates":[-90.65,18.516667],"type":"Point"}
}
=======
{"geometry":{"type":"Point","coordinates":[-90.650000,18.516667]},"type":"Feature","properties":{"hierarchy":["tgn:7358545","tgn:7005578","tgn:1000001","tgn:7005560","tgn:7029392"],"placetype":["aat:300008347"],"id":7358545,"name:xx":"Delia"}}
>>>>>>> 03f74aca74312dbeaf24d7e61306dd6a786dc3d0
