{
  "id": 7580934,
  "type": "Feature",
  "properties": {
    "tgn:hierarchy":[
        "tgn:7580934",
        "tgn:1000004",
        "tgn:7000198",
        "tgn:7016694",
        "tgn:7029392"
    ],
    "tgn:id":7580934,
    "tgn:name:en":"Sunger",
    "tgn:placetype":[
        "aat:300008347"
    ]
},
  "bbox": [],
  "geometry": {"coordinates":[83.116667,19.466667],"type":"Point"}
}