{
  "id": 2622445,
  "type": "Feature",
  "properties": {
    "tgn:hierarchy":[
        "tgn:2622445",
        "tgn:1000001",
        "tgn:7012149",
        "tgn:7007825",
        "tgn:7029392"
    ],
    "tgn:id":2622445,
    "tgn:name":"Robinette Creek",
    "tgn:placetype":[
        "aat:300008706"
    ]
},
  "bbox": [],
  "geometry": {"coordinates":[-87.6167,35.3833],"type":"Point"}
}