{
  "id": 7324740,
  "type": "Feature",
  "properties": {
    "tgn:hierarchy":[
        "tgn:7324740",
        "tgn:7002820",
        "tgn:7030216",
        "tgn:1000003",
        "tgn:1000095",
        "tgn:7029392"
    ],
    "tgn:id":7324740,
    "tgn:name":"Santa Magdalena de Cambrils, Sierra",
    "tgn:placetype":[
        "aat:300266640"
    ]
},
  "bbox": [],
  "geometry": {"coordinates":[2.335081,42.165668],"type":"Point"}
}