{
  "id": 7061376,
  "type": "Feature",
  "properties": {
    "tgn:hierarchy":[
        "tgn:7061376",
        "tgn:7003669",
        "tgn:1000003",
        "tgn:7000084",
        "tgn:7029392"
    ],
    "tgn:id":7061376,
    "tgn:name":"Landkreis Aschaffenburg",
    "tgn:placetype":[
        "aat:300387198"
    ]
},
  "bbox": [],
  "geometry": {"coordinates":[9.231667,50.026389],"type":"Point"}
}