{
  "id": 2189890,
  "type": "Feature",
  "properties": {
    "tgn:hierarchy":[
        "tgn:2189890",
        "tgn:1000001",
        "tgn:7012149",
        "tgn:2001274",
        "tgn:7007524",
        "tgn:7029392"
    ],
    "tgn:id":2189890,
    "tgn:name":"Bowl Creek",
    "tgn:placetype":[
        "aat:300008706"
    ]
},
  "bbox": [],
  "geometry": {"coordinates":[-112.8833,47.9667],"type":"Point"}
}