{
  "id": 7388599,
  "type": "Feature",
  "properties": {
    "tgn:hierarchy":[
        "tgn:7388599",
        "tgn:1000001",
        "tgn:7005597",
        "tgn:7005560",
        "tgn:7029392"
    ],
    "tgn:id":7388599,
    "tgn:name":"Potros, Isla de los",
    "tgn:placetype":[
        "aat:300008791"
    ]
},
  "bbox": [],
  "geometry": {"coordinates":[-97.533333,25.083333],"type":"Point"}
}