{
  "id": 7041904,
  "type": "Feature",
  "properties": {
    "tgn:hierarchy":[
        "tgn:7041904",
        "tgn:1003455",
        "tgn:1000003",
        "tgn:7010380",
        "tgn:1000080",
        "tgn:7029392"
    ],
    "tgn:id":7041904,
    "tgn:name":"Sacro, Monte",
    "tgn:placetype":[
        "aat:300008795"
    ]
},
  "bbox": [],
  "geometry": {"coordinates":[16.033333,41.75],"type":"Point"}
}