{
  "id": 1006951,
  "type": "Feature",
  "properties": {
    "tgn:hierarchy":[
        "tgn:1006951",
        "tgn:1000001",
        "tgn:7012149",
        "tgn:1002521",
        "tgn:7007920",
        "tgn:7029392"
    ],
    "tgn:id":1006951,
    "tgn:name":"Destruction Island",
    "tgn:placetype":[
        "aat:300008791"
    ]
},
  "bbox": [],
  "geometry": {"coordinates":[-124.4833,47.6667],"type":"Point"}
}