{
  "id": 2644148,
  "type": "Feature",
  "properties": {
    "tgn:hierarchy":[
        "tgn:2644148",
        "tgn:1000001",
        "tgn:7012149",
        "tgn:7007157",
        "tgn:1002828",
        "tgn:7029392"
    ],
    "tgn:id":2644148,
    "tgn:name":"Santa Rosa Spring",
    "tgn:placetype":[
        "aat:300008697"
    ]
},
  "bbox": [],
  "geometry": {"coordinates":[-116.45,33.5333],"type":"Point"}
}