{
  "id": 7495693,
  "type": "Feature",
  "properties": {
    "tgn:hierarchy":[
        "tgn:7495693",
        "tgn:1000004",
        "tgn:7491221",
        "tgn:1000141",
        "tgn:7029392"
    ],
    "tgn:id":7495693,
    "tgn:name":"Shuimubei Xi",
    "tgn:placetype":[
        "aat:300008699"
    ]
},
  "bbox": [],
  "geometry": {"coordinates":[121.475343,23.403369],"type":"Point"}
}