{
  "id": 7237230,
  "type": "Feature",
  "properties": {
    "tgn:hierarchy":[
        "tgn:7237230",
        "tgn:7002715",
        "tgn:7002731",
        "tgn:1000003",
        "tgn:1000074",
        "tgn:7029392"
    ],
    "tgn:id":7237230,
    "tgn:name":"Dom\u00faz R\u00e9ma",
    "tgn:placetype":[
        "aat:300008699"
    ]
},
  "bbox": [],
  "geometry": {"coordinates":[23.583333,40.616667],"type":"Point"}
}