{
  "id": 2323739,
  "type": "Feature",
  "properties": {
    "tgn:hierarchy":[
        "tgn:2323739",
        "tgn:1000001",
        "tgn:7006451",
        "tgn:7012149",
        "tgn:2000098",
        "tgn:7029392"
    ],
    "tgn:id":2323739,
    "tgn:name":"Faught Canyon",
    "tgn:placetype":[
        "aat:300008761"
    ]
},
  "bbox": [],
  "geometry": {"coordinates":[-113.3333,35.4833],"type":"Point"}
}