{
  "id": 2231812,
  "type": "Feature",
  "properties": {
    "tgn:hierarchy":[
        "tgn:2231812",
        "tgn:2000665",
        "tgn:1000001",
        "tgn:7012149",
        "tgn:7007254",
        "tgn:7029392"
    ],
    "tgn:id":2231812,
    "tgn:name":"Chambers Branch",
    "tgn:placetype":[
        "aat:300008699"
    ]
},
  "bbox": [],
  "geometry": {"coordinates":[-94.7667,37.75],"type":"Point"}
}