{
  "id": 2182422,
  "type": "Feature",
  "properties": {
    "tgn:hierarchy":[
        "tgn:2182422",
        "tgn:1000001",
        "tgn:7012149",
        "tgn:2002115",
        "tgn:7007827",
        "tgn:7029392"
    ],
    "tgn:id":2182422,
    "tgn:name":"Blue Ridge",
    "tgn:placetype":[
        "aat:300266640"
    ]
},
  "bbox": [],
  "geometry": {"coordinates":[-111.3667,41.2833],"type":"Point"}
}