{
  "id": 2714220,
  "type": "Feature",
  "properties": {
    "tgn:hierarchy":[
        "tgn:2714220",
        "tgn:1000001",
        "tgn:7012149",
        "tgn:7007157",
        "tgn:2000190",
        "tgn:7029392"
    ],
    "tgn:id":2714220,
    "tgn:name":"Telephone Ridge",
    "tgn:placetype":[
        "aat:300266640"
    ]
},
  "bbox": [],
  "geometry": {"coordinates":[-122.7833,39.8833],"type":"Point"}
}