{
  "id": 2283821,
  "type": "Feature",
  "properties": {
    "tgn:hierarchy":[
        "tgn:2283821",
        "tgn:7006450",
        "tgn:1000001",
        "tgn:7012149",
        "tgn:2000089",
        "tgn:7029392"
    ],
    "tgn:id":2283821,
    "tgn:name":"Deniktaw Ridge",
    "tgn:placetype":[
        "aat:300266640"
    ]
},
  "bbox": [],
  "geometry": {"coordinates":[-155.05,65.9167],"type":"Point"}
}