{
  "id": 1072489,
  "type": "Feature",
  "properties": {
    "tgn:hierarchy":[
        "tgn:1072489",
        "tgn:1000004",
        "tgn:1000960",
        "tgn:1000111",
        "tgn:7029392"
    ],
    "tgn:id":1072489,
    "tgn:name":"Wangwenzhuang",
    "tgn:placetype":[
        "aat:300008347"
    ]
},
  "bbox": [],
  "geometry": {"coordinates":[117.2667,38.8833],"type":"Point"}
}