<<<<<<< HEAD
{
  "id": 7482063,
  "type": "Feature",
  "properties": {
    "tgn:hierarchy":[
        "tgn:7482063",
        "tgn:1000004",
        "tgn:7492971",
        "tgn:1000141",
        "tgn:7029392"
    ],
    "tgn:id":7482063,
    "tgn:name":"Xinhe Qiao",
    "tgn:placetype":[
        "aat:300007836"
    ]
},
  "bbox": [],
  "geometry": {"coordinates":[120.611842,22.567625],"type":"Point"}
}
=======
{"geometry":{"type":"Point","coordinates":[120.611842,22.567625]},"type":"Feature","properties":{"hierarchy":["tgn:7482063","tgn:1000004","tgn:7492971","tgn:1000141","tgn:7029392"],"placetype":["aat:300007836"],"id":7482063,"name:xx":"Xinhe Qiao"}}
>>>>>>> 03f74aca74312dbeaf24d7e61306dd6a786dc3d0
