{
  "id": 7482063,
  "type": "Feature",
  "properties": {
    "tgn:hierarchy":[
        "tgn:7482063",
        "tgn:1000004",
        "tgn:7492971",
        "tgn:1000141",
        "tgn:7029392"
    ],
    "tgn:id":7482063,
    "tgn:name":"Xinhe Qiao",
    "tgn:placetype":[
        "aat:300007836"
    ]
},
  "bbox": [],
  "geometry": {"coordinates":[120.611842,22.567625],"type":"Point"}
}