<<<<<<< HEAD
{
  "id": 7352639,
  "type": "Feature",
  "properties": {
    "tgn:hierarchy":[
        "tgn:7352639",
        "tgn:7005586",
        "tgn:1000001",
        "tgn:7005560",
        "tgn:7029392"
    ],
    "tgn:id":7352639,
    "tgn:name":"Atengo, R\u00edo",
    "tgn:placetype":[
        "aat:300008699"
    ]
},
  "bbox": [],
  "geometry": {"coordinates":[-103.883333,22.05],"type":"Point"}
}
=======
{"geometry":{"type":"Point","coordinates":[-103.883333,22.050000]},"type":"Feature","properties":{"hierarchy":["tgn:7352639","tgn:7005586","tgn:1000001","tgn:7005560","tgn:7029392"],"placetype":["aat:300008699"],"id":7352639,"name:xx":"Atengo, R\u00edo"}}
>>>>>>> 03f74aca74312dbeaf24d7e61306dd6a786dc3d0
