{
  "id": 7410758,
  "type": "Feature",
  "properties": {
    "tgn:hierarchy":[
        "tgn:7410758",
        "tgn:1000001",
        "tgn:1001893",
        "tgn:7005560",
        "tgn:7029392"
    ],
    "tgn:id":7410758,
    "tgn:name":"El Madro\u00f1o",
    "tgn:placetype":[
        "aat:300008347"
    ]
},
  "bbox": [],
  "geometry": {"coordinates":[-100.05,19.35],"type":"Point"}
}