{
  "id": 7477039,
  "type": "Feature",
  "properties": {
    "tgn:hierarchy":[
        "tgn:7477039",
        "tgn:1000004",
        "tgn:7001013",
        "tgn:1000141",
        "tgn:7029392"
    ],
    "tgn:id":7477039,
    "tgn:name":"Gangqi",
    "tgn:placetype":[
        "aat:300008347"
    ]
},
  "bbox": [],
  "geometry": {"coordinates":[121.228322,25.009309],"type":"Point"}
}