{
  "id": 2103309,
  "type": "Feature",
  "properties": {
    "tgn:hierarchy":[
        "tgn:2103309",
        "tgn:1000001",
        "tgn:7012149",
        "tgn:1002769",
        "tgn:7007826",
        "tgn:7029392"
    ],
    "tgn:id":2103309,
    "tgn:name":"Clayton",
    "tgn:placetype":[
        "aat:300008347"
    ]
},
  "bbox": [],
  "geometry": {"coordinates":[-94.4667,32.0833],"type":"Point"}
}