{
  "id": 7513021,
  "type": "Feature",
  "properties": {
    "tgn:hierarchy":[
        "tgn:7513021",
        "tgn:1009227",
        "tgn:1000226",
        "tgn:7016822",
        "tgn:1000006",
        "tgn:7029392"
    ],
    "tgn:id":7513021,
    "tgn:name:en":"Hapuka Rock",
    "tgn:placetype":[
        "aat:300011692"
    ]
},
  "bbox": [],
  "geometry": {"coordinates":[167.816667,-46.466667],"type":"Point"}
}