{
  "id": 2477140,
  "type": "Feature",
  "properties": {
    "tgn:hierarchy":[
        "tgn:2477140",
        "tgn:1000001",
        "tgn:7012149",
        "tgn:2002129",
        "tgn:7007827",
        "tgn:7029392"
    ],
    "tgn:id":2477140,
    "tgn:name":"Lynn Canal",
    "tgn:placetype":[
        "aat:300006075"
    ]
},
  "bbox": [],
  "geometry": {"coordinates":[-111.95,41.2333],"type":"Point"}
}