{
  "id": 7490459,
  "type": "Feature",
  "properties": {
    "tgn:hierarchy":[
        "tgn:7490459",
        "tgn:1000004",
        "tgn:1000959",
        "tgn:1000141",
        "tgn:7029392"
    ],
    "tgn:id":7490459,
    "tgn:name":"Sanzhangli",
    "tgn:placetype":[
        "aat:300000745"
    ]
},
  "bbox": [],
  "geometry": {"coordinates":[121.56271,25.029901],"type":"Point"}
}