{
  "id": 7312338,
  "type": "Feature",
  "properties": {
    "tgn:hierarchy":[
        "tgn:7312338",
        "tgn:7016598",
        "tgn:1000049",
        "tgn:1000002",
        "tgn:7029392"
    ],
    "tgn:id":7312338,
    "tgn:name":"Lari, Pampa de",
    "tgn:placetype":[
        "aat:300008805"
    ]
},
  "bbox": [],
  "geometry": {"coordinates":[-67.25,-23.716667],"type":"Point"}
}