{
  "id": 2313332,
  "type": "Feature",
  "properties": {
    "tgn:hierarchy":[
        "tgn:2313332",
        "tgn:1000001",
        "tgn:7012149",
        "tgn:2000183",
        "tgn:7007157",
        "tgn:7029392"
    ],
    "tgn:id":2313332,
    "tgn:name":"Elderberry Canyon",
    "tgn:placetype":[
        "aat:300008761"
    ]
},
  "bbox": [],
  "geometry": {"coordinates":[-118.65,37.35],"type":"Point"}
}