{
  "id": 1057385,
  "type": "Feature",
  "properties": {
    "tgn:hierarchy":[
        "tgn:1057385",
        "tgn:1000003",
        "tgn:7011999",
        "tgn:7006660",
        "tgn:7029392"
    ],
    "tgn:id":1057385,
    "tgn:name":"Nemirov",
    "tgn:placetype":[
        "aat:300008347"
    ]
},
  "bbox": [],
  "geometry": {"coordinates":[28.8333,48.9667],"type":"Point"}
}