{
  "id": 7589042,
  "type": "Feature",
  "properties": {
    "tgn:hierarchy":[
        "tgn:7589042",
        "tgn:1000004",
        "tgn:7000198",
        "tgn:7000799",
        "tgn:7029392"
    ],
    "tgn:id":7589042,
    "tgn:name:en":"Khera Bagle",
    "tgn:placetype":[
        "aat:300008347"
    ]
},
  "bbox": [],
  "geometry": {"coordinates":[74.061111,33.165278],"type":"Point"}
}