{
  "id": 2734608,
  "type": "Feature",
  "properties": {
    "tgn:hierarchy":[
        "tgn:2734608",
        "tgn:1000001",
        "tgn:2001477",
        "tgn:7012149",
        "tgn:7007709",
        "tgn:7029392"
    ],
    "tgn:id":2734608,
    "tgn:name":"Tusk Creek",
    "tgn:placetype":[
        "aat:300008706"
    ]
},
  "bbox": [],
  "geometry": {"coordinates":[-76.5167,34.7333],"type":"Point"}
}