{
  "id": 2399262,
  "type": "Feature",
  "properties": {
    "tgn:hierarchy":[
        "tgn:2399262",
        "tgn:1000001",
        "tgn:2000773",
        "tgn:7012149",
        "tgn:7007255",
        "tgn:7029392"
    ],
    "tgn:id":2399262,
    "tgn:name":"Horn Back Mill",
    "tgn:placetype":[
        "aat:300008347"
    ]
},
  "bbox": [],
  "geometry": {"coordinates":[-86.3833,37.5667],"type":"Point"}
}