{
  "id": 7500456,
  "type": "Feature",
  "properties": {
    "tgn:hierarchy":[
        "tgn:7500456",
        "tgn:1000004",
        "tgn:7492971",
        "tgn:1000141",
        "tgn:7029392"
    ],
    "tgn:id":7500456,
    "tgn:name":"Sanduo Guoxiao",
    "tgn:placetype":[
        "aat:300006495"
    ]
},
  "bbox": [],
  "geometry": {"coordinates":[120.486111,22.748611],"type":"Point"}
}