{
  "id": 2568346,
  "type": "Feature",
  "properties": {
    "tgn:hierarchy":[
        "tgn:2568346",
        "tgn:1000001",
        "tgn:7012149",
        "tgn:2001300",
        "tgn:7007524",
        "tgn:7029392"
    ],
    "tgn:id":2568346,
    "tgn:name":"Park Creek",
    "tgn:placetype":[
        "aat:300008706"
    ]
},
  "bbox": [],
  "geometry": {"coordinates":[-113.55,45.8833],"type":"Point"}
}