{
  "id": 1115000,
  "type": "Feature",
  "properties": {
    "tgn:hierarchy":[
        "tgn:1115000",
        "tgn:7005685",
        "tgn:1000001",
        "tgn:7013154",
        "tgn:7029392"
    ],
    "tgn:id":1115000,
    "tgn:name":"Melville Sound",
    "tgn:placetype":[
        "aat:300266558"
    ]
},
  "bbox": [],
  "geometry": {"coordinates":[-81.0833,44.95],"type":"Point"}
}