{
  "id": 7401637,
  "type": "Feature",
  "properties": {
    "tgn:hierarchy":[
        "tgn:7401637",
        "tgn:1000001",
        "tgn:7005599",
        "tgn:7005560",
        "tgn:7029392"
    ],
    "tgn:id":7401637,
    "tgn:name":"Caba\u00f1as",
    "tgn:placetype":[
        "aat:300008347"
    ]
},
  "bbox": [],
  "geometry": {"coordinates":[-94.995833,18.095833],"type":"Point"}
}