{
  "id": 2340909,
  "type": "Feature",
  "properties": {
    "tgn:hierarchy":[
        "tgn:2340909",
        "tgn:1000001",
        "tgn:2002369",
        "tgn:7012149",
        "tgn:7007923",
        "tgn:7029392"
    ],
    "tgn:id":2340909,
    "tgn:name":"Friday Draw",
    "tgn:placetype":[
        "aat:300008761"
    ]
},
  "bbox": [],
  "geometry": {"coordinates":[-105.8167,43.3667],"type":"Point"}
}