{
  "id": 2198875,
  "type": "Feature",
  "properties": {
    "tgn:hierarchy":[
        "tgn:2198875",
        "tgn:1000001",
        "tgn:7012149",
        "tgn:2002035",
        "tgn:7007826",
        "tgn:7029392"
    ],
    "tgn:id":2198875,
    "tgn:name":"Bruce Branch",
    "tgn:placetype":[
        "aat:300008699"
    ]
},
  "bbox": [],
  "geometry": {"coordinates":[-98.5667,28.55],"type":"Point"}
}