{
  "id": 7075228,
  "type": "Feature",
  "properties": {
    "tgn:hierarchy":[
        "tgn:7075228",
        "tgn:7000096",
        "tgn:1000003",
        "tgn:7000084",
        "tgn:7029392"
    ],
    "tgn:id":7075228,
    "tgn:name":"Zootzen",
    "tgn:placetype":[
        "aat:300008347"
    ]
},
  "bbox": [],
  "geometry": {"coordinates":[12.583333,53.133333],"type":"Point"}
}