{
  "id": 2144548,
  "type": "Feature",
  "properties": {
    "tgn:hierarchy":[
        "tgn:2144548",
        "tgn:1000001",
        "tgn:7012149",
        "tgn:2000210",
        "tgn:7007158",
        "tgn:7029392"
    ],
    "tgn:id":2144548,
    "tgn:name":"Balanced Rock Spring",
    "tgn:placetype":[
        "aat:300008697"
    ]
},
  "bbox": [],
  "geometry": {"coordinates":[-106.7667,39.8833],"type":"Point"}
}