{
  "id": 1056114,
  "type": "Feature",
  "properties": {
    "tgn:hierarchy":[
        "tgn:1056114",
        "tgn:1000004",
        "tgn:7012215",
        "tgn:7006653",
        "tgn:7029392"
    ],
    "tgn:id":1056114,
    "tgn:name":"Kurdgelauri",
    "tgn:placetype":[
        "aat:300008347"
    ]
},
  "bbox": [],
  "geometry": {"coordinates":[45.5167,41.9333],"type":"Point"}
}