{
  "id": 2510164,
  "type": "Feature",
  "properties": {
    "tgn:hierarchy":[
        "tgn:2510164",
        "tgn:1000001",
        "tgn:7012149",
        "tgn:2001914",
        "tgn:7007825",
        "tgn:7029392"
    ],
    "tgn:id":2510164,
    "tgn:name":"Middle Prong Little Pigeon River",
    "tgn:placetype":[
        "aat:300008707"
    ]
},
  "bbox": [],
  "geometry": {"coordinates":[-83.3167,35.6833],"type":"Point"}
}