{
  "id": 2770244,
  "type": "Feature",
  "properties": {
    "tgn:hierarchy":[
        "tgn:2770244",
        "tgn:7006450",
        "tgn:1000001",
        "tgn:7012149",
        "tgn:2000079",
        "tgn:7029392"
    ],
    "tgn:id":2770244,
    "tgn:name":"Wild Goose Pipeline",
    "tgn:placetype":[
        "aat:300006075"
    ]
},
  "bbox": [],
  "geometry": {"coordinates":[-165.1833,64.9333],"type":"Point"}
}