<<<<<<< HEAD
{
  "id": 2765443,
  "type": "Feature",
  "properties": {
    "tgn:hierarchy":[
        "tgn:2765443",
        "tgn:1000001",
        "tgn:7012149",
        "tgn:2000290",
        "tgn:7007240",
        "tgn:7029392"
    ],
    "tgn:id":2765443,
    "tgn:name":"White Branch",
    "tgn:placetype":[
        "aat:300008699"
    ]
},
  "bbox": [],
  "geometry": {"coordinates":[-86.1,30.5833],"type":"Point"}
}
=======
{"geometry":{"type":"Point","coordinates":[-86.100000,30.583300]},"type":"Feature","properties":{"hierarchy":["tgn:2765443","tgn:1000001","tgn:7012149","tgn:2000290","tgn:7007240","tgn:7029392"],"placetype":["aat:300008699"],"id":2765443,"name:xx":"White Branch"}}
>>>>>>> 03f74aca74312dbeaf24d7e61306dd6a786dc3d0
