{
  "id": 2369913,
  "type": "Feature",
  "properties": {
    "tgn:hierarchy":[
        "tgn:2369913",
        "tgn:1000001",
        "tgn:7012149",
        "tgn:7007250",
        "tgn:7029392"
    ],
    "tgn:id":2369913,
    "tgn:name":"Gustafson Lateral",
    "tgn:placetype":[
        "aat:300006075"
    ]
},
  "bbox": [],
  "geometry": {"coordinates":[-112.0333,43.4333],"type":"Point"}
}