{
  "id": 2269926,
  "type": "Feature",
  "properties": {
    "tgn:hierarchy":[
        "tgn:2269926",
        "tgn:1000001",
        "tgn:7012149",
        "tgn:7007568",
        "tgn:7029392"
    ],
    "tgn:id":2269926,
    "tgn:name":"Crum Creek",
    "tgn:placetype":[
        "aat:300008706"
    ]
},
  "bbox": [],
  "geometry": {"coordinates":[-74.6167,43.0833],"type":"Point"}
}