{
  "id": 7538692,
  "type": "Feature",
  "properties": {
    "tgn:hierarchy":[
        "tgn:7538692",
        "tgn:7001242",
        "tgn:1001075",
        "tgn:7016833",
        "tgn:7029392"
    ],
    "tgn:id":7538692,
    "tgn:name:en":"Nitm\u0101 wa Kafr Ghar\u012bn, Jaz\u012brat",
    "tgn:placetype":[
        "aat:300008791"
    ]
},
  "bbox": [],
  "geometry": {"coordinates":[30.782778,30.756389],"type":"Point"}
}