{
  "id": 2516134,
  "type": "Feature",
  "properties": {
    "tgn:hierarchy":[
        "tgn:2516134",
        "tgn:1000001",
        "tgn:7012149",
        "tgn:2001710",
        "tgn:7007708",
        "tgn:7029392"
    ],
    "tgn:id":2516134,
    "tgn:name":"Mine Creek",
    "tgn:placetype":[
        "aat:300008706"
    ]
},
  "bbox": [],
  "geometry": {"coordinates":[-121.55,45.3167],"type":"Point"}
}