{
  "id": 2534930,
  "type": "Feature",
  "properties": {
    "tgn:hierarchy":[
        "tgn:2534930",
        "tgn:2002137",
        "tgn:1000001",
        "tgn:7012149",
        "tgn:7007919",
        "tgn:7029392"
    ],
    "tgn:id":2534930,
    "tgn:name":"Naked Creek",
    "tgn:placetype":[
        "aat:300008706"
    ]
},
  "bbox": [],
  "geometry": {"coordinates":[-78.4667,38.1333],"type":"Point"}
}