<<<<<<< HEAD
{
  "id": 2406831,
  "type": "Feature",
  "properties": {
    "tgn:hierarchy":[
        "tgn:2406831",
        "tgn:1000001",
        "tgn:7012149",
        "tgn:2000230",
        "tgn:7007158",
        "tgn:7029392"
    ],
    "tgn:id":2406831,
    "tgn:name":"Hunter Canyon",
    "tgn:placetype":[
        "aat:300008761"
    ]
},
  "bbox": [],
  "geometry": {"coordinates":[-108.5667,39.4333],"type":"Point"}
}
=======
{"geometry":{"type":"Point","coordinates":[-108.566700,39.433300]},"type":"Feature","properties":{"hierarchy":["tgn:2406831","tgn:1000001","tgn:7012149","tgn:2000230","tgn:7007158","tgn:7029392"],"placetype":["aat:300008761"],"id":2406831,"name:xx":"Hunter Canyon"}}
>>>>>>> 03f74aca74312dbeaf24d7e61306dd6a786dc3d0
