{
  "id": 2446685,
  "type": "Feature",
  "properties": {
    "tgn:hierarchy":[
        "tgn:2446685",
        "tgn:1000001",
        "tgn:7012149",
        "tgn:2000486",
        "tgn:7007250",
        "tgn:7029392"
    ],
    "tgn:id":2446685,
    "tgn:name":"Lewiston Hill",
    "tgn:placetype":[
        "aat:300008798"
    ]
},
  "bbox": [],
  "geometry": {"coordinates":[-116.9667,46.45],"type":"Point"}
}