{
  "id": 7495758,
  "type": "Feature",
  "properties": {
    "tgn:hierarchy":[
        "tgn:7495758",
        "tgn:7488858",
        "tgn:1000004",
        "tgn:1000141",
        "tgn:7029392"
    ],
    "tgn:id":7495758,
    "tgn:name":"Zhongxin",
    "tgn:placetype":[
        "aat:300008347"
    ]
},
  "bbox": [],
  "geometry": {"coordinates":[120.748316,23.915879],"type":"Point"}
}