{
  "id": 2008842,
  "type": "Feature",
  "properties": {
    "tgn:hierarchy":[
        "tgn:2008842",
        "tgn:1000001",
        "tgn:7016172",
        "tgn:2000116",
        "tgn:7012149",
        "tgn:7029392"
    ],
    "tgn:id":2008842,
    "tgn:name":"McJester",
    "tgn:placetype":[
        "aat:300008347",
        "aat:300387210"
    ]
},
  "bbox": [],
  "geometry": {"coordinates":[-91.8167,35.4667],"type":"Point"}
}