{
  "id": 2786561,
  "type": "Feature",
  "properties": {
    "tgn:hierarchy":[
        "tgn:2786561",
        "tgn:1000001",
        "tgn:7012149",
        "tgn:1002553",
        "tgn:7007920",
        "tgn:7029392"
    ],
    "tgn:id":2786561,
    "tgn:name":"Yvonne, Lake",
    "tgn:placetype":[
        "aat:300008680"
    ]
},
  "bbox": [],
  "geometry": {"coordinates":[-121.3333,47.3667],"type":"Point"}
}