{
  "id": 2367605,
  "type": "Feature",
  "properties": {
    "tgn:hierarchy":[
        "tgn:2367605",
        "tgn:1000001",
        "tgn:7012149",
        "tgn:2001288",
        "tgn:7007524",
        "tgn:7029392"
    ],
    "tgn:id":2367605,
    "tgn:name":"Grouse Mine",
    "tgn:placetype":[
        "aat:300000390"
    ]
},
  "bbox": [],
  "geometry": {"coordinates":[-112.15,45.5667],"type":"Point"}
}