<<<<<<< HEAD
{
  "id": 2254170,
  "type": "Feature",
  "properties": {
    "tgn:hierarchy":[
        "tgn:2254170",
        "tgn:1000001",
        "tgn:2000460",
        "tgn:7012149",
        "tgn:7007250",
        "tgn:7029392"
    ],
    "tgn:id":2254170,
    "tgn:name":"Coolin Mountain",
    "tgn:placetype":[
        "aat:300008798"
    ]
},
  "bbox": [],
  "geometry": {"coordinates":[-116.85,48.45],"type":"Point"}
}
=======
{"geometry":{"type":"Point","coordinates":[-116.850000,48.450000]},"type":"Feature","properties":{"hierarchy":["tgn:2254170","tgn:1000001","tgn:2000460","tgn:7012149","tgn:7007250","tgn:7029392"],"placetype":["aat:300008798"],"id":2254170,"name:xx":"Coolin Mountain"}}
>>>>>>> 03f74aca74312dbeaf24d7e61306dd6a786dc3d0
