{
  "id": 2254170,
  "type": "Feature",
  "properties": {
    "tgn:hierarchy":[
        "tgn:2254170",
        "tgn:1000001",
        "tgn:2000460",
        "tgn:7012149",
        "tgn:7007250",
        "tgn:7029392"
    ],
    "tgn:id":2254170,
    "tgn:name":"Coolin Mountain",
    "tgn:placetype":[
        "aat:300008798"
    ]
},
  "bbox": [],
  "geometry": {"coordinates":[-116.85,48.45],"type":"Point"}
}