{
  "id": 2339845,
  "type": "Feature",
  "properties": {
    "tgn:hierarchy":[
        "tgn:2339845",
        "tgn:1000001",
        "tgn:2001409",
        "tgn:7012149",
        "tgn:7007526",
        "tgn:7029392"
    ],
    "tgn:id":2339845,
    "tgn:name":"Freeman Creek",
    "tgn:placetype":[
        "aat:300008706"
    ]
},
  "bbox": [],
  "geometry": {"coordinates":[-118.2167,39.5833],"type":"Point"}
}