<<<<<<< HEAD
{
  "id": 2339845,
  "type": "Feature",
  "properties": {
    "tgn:hierarchy":[
        "tgn:2339845",
        "tgn:1000001",
        "tgn:2001409",
        "tgn:7012149",
        "tgn:7007526",
        "tgn:7029392"
    ],
    "tgn:id":2339845,
    "tgn:name":"Freeman Creek",
    "tgn:placetype":[
        "aat:300008706"
    ]
},
  "bbox": [],
  "geometry": {"coordinates":[-118.2167,39.5833],"type":"Point"}
}
=======
{"geometry":{"type":"Point","coordinates":[-118.216700,39.583300]},"type":"Feature","properties":{"hierarchy":["tgn:2339845","tgn:1000001","tgn:2001409","tgn:7012149","tgn:7007526","tgn:7029392"],"placetype":["aat:300008706"],"id":2339845,"name:xx":"Freeman Creek"}}
>>>>>>> 03f74aca74312dbeaf24d7e61306dd6a786dc3d0
