{
  "id": 2240590,
  "type": "Feature",
  "properties": {
    "tgn:hierarchy":[
        "tgn:2240590",
        "tgn:1000001",
        "tgn:1002270",
        "tgn:7012149",
        "tgn:7007708",
        "tgn:7029392"
    ],
    "tgn:id":2240590,
    "tgn:name":"Clackamas Lake",
    "tgn:placetype":[
        "aat:300008680"
    ]
},
  "bbox": [],
  "geometry": {"coordinates":[-121.7333,45.0833],"type":"Point"}
}