<<<<<<< HEAD
{
  "id": 7360408,
  "type": "Feature",
  "properties": {
    "tgn:hierarchy":[
        "tgn:7360408",
        "tgn:7005581",
        "tgn:1000001",
        "tgn:7005560",
        "tgn:7029392"
    ],
    "tgn:id":7360408,
    "tgn:name":"Contrabando, Cerro",
    "tgn:placetype":[
        "aat:300008795"
    ]
},
  "bbox": [],
  "geometry": {"coordinates":[-106.016667,28.85],"type":"Point"}
}
=======
{"geometry":{"type":"Point","coordinates":[-106.016667,28.850000]},"type":"Feature","properties":{"hierarchy":["tgn:7360408","tgn:7005581","tgn:1000001","tgn:7005560","tgn:7029392"],"placetype":["aat:300008795"],"id":7360408,"name:xx":"Contrabando, Cerro"}}
>>>>>>> 03f74aca74312dbeaf24d7e61306dd6a786dc3d0
