{
  "id": 7283227,
  "type": "Feature",
  "properties": {
    "tgn:hierarchy":[
        "tgn:7283227",
        "tgn:1001630",
        "tgn:1000049",
        "tgn:1000002",
        "tgn:7029392"
    ],
    "tgn:id":7283227,
    "tgn:name":"Palmira, Cerro",
    "tgn:placetype":[
        "aat:300008795"
    ]
},
  "bbox": [],
  "geometry": {"coordinates":[-70.233333,-27.95],"type":"Point"}
}