{
  "id": 1028313,
  "type": "Feature",
  "properties": {
    "tgn:hierarchy":[
        "tgn:1028313",
        "tgn:7002445",
        "tgn:1000003",
        "tgn:7008134",
        "tgn:7008591",
        "tgn:7029392"
    ],
    "tgn:id":1028313,
    "tgn:name:en":"Angmering",
    "tgn:placetype":[
        "aat:300008347"
    ]
},
  "bbox": [],
  "geometry": {"coordinates":[-0.483333,50.816667],"type":"Point"}
}