<<<<<<< HEAD
{
  "id": 2401446,
  "type": "Feature",
  "properties": {
    "tgn:hierarchy":[
        "tgn:2401446",
        "tgn:1000001",
        "tgn:2002369",
        "tgn:7012149",
        "tgn:7007923",
        "tgn:7029392"
    ],
    "tgn:id":2401446,
    "tgn:name":"Horseshoe Bend Creek",
    "tgn:placetype":[
        "aat:300008706"
    ]
},
  "bbox": [],
  "geometry": {"coordinates":[-105.8333,42.55],"type":"Point"}
}
=======
{"geometry":{"type":"Point","coordinates":[-105.833300,42.550000]},"type":"Feature","properties":{"hierarchy":["tgn:2401446","tgn:1000001","tgn:2002369","tgn:7012149","tgn:7007923","tgn:7029392"],"placetype":["aat:300008706"],"id":2401446,"name:xx":"Horseshoe Bend Creek"}}
>>>>>>> 03f74aca74312dbeaf24d7e61306dd6a786dc3d0
