{
  "id": 7341663,
  "type": "Feature",
  "properties": {
    "tgn:hierarchy":[
        "tgn:7341663",
        "tgn:7002804",
        "tgn:1000003",
        "tgn:7002793",
        "tgn:1000095",
        "tgn:7029392"
    ],
    "tgn:id":7341663,
    "tgn:name":"Bombarda, Punta",
    "tgn:placetype":[
        "aat:300386846"
    ]
},
  "bbox": [],
  "geometry": {"coordinates":[-0.05,38.55],"type":"Point"}
}