{
  "id": 7180978,
  "type": "Feature",
  "properties": {
    "tgn:hierarchy":[
        "tgn:7180978",
        "tgn:7003669",
        "tgn:1000003",
        "tgn:7000084",
        "tgn:7029392"
    ],
    "tgn:id":7180978,
    "tgn:name":"Gash\u00fctte",
    "tgn:placetype":[
        "aat:300000206"
    ]
},
  "bbox": [],
  "geometry": {"coordinates":[13.016667,49.133333],"type":"Point"}
}