{
  "id": 7535948,
  "type": "Feature",
  "properties": {
    "tgn:hierarchy":[
        "tgn:7535948",
        "tgn:7001242",
        "tgn:7016833",
        "tgn:1001418",
        "tgn:7029392"
    ],
    "tgn:id":7535948,
    "tgn:name:en":"Imb\u00e2y\u00eeh, 'Alam",
    "tgn:placetype":[
        "aat:300008777"
    ]
},
  "bbox": [],
  "geometry": {"coordinates":[29.61525,30.716653],"type":"Point"}
}