{
  "id": 1108371,
  "type": "Feature",
  "properties": {
    "tgn:hierarchy":[
        "tgn:1108371",
        "tgn:1003489",
        "tgn:7004610",
        "tgn:1000003",
        "tgn:1000080",
        "tgn:7029392"
    ],
    "tgn:id":1108371,
    "tgn:name":"Croce dello Scrivano, Passo",
    "tgn:placetype":[
        "aat:300259572"
    ]
},
  "bbox": [],
  "geometry": {"coordinates":[15.8333,40.5667],"type":"Point"}
}