{
  "id": 7109842,
  "type": "Feature",
  "properties": {
    "tgn:hierarchy":[
        "tgn:7109842",
        "tgn:7003692",
        "tgn:1000003",
        "tgn:7000084",
        "tgn:7029392"
    ],
    "tgn:id":7109842,
    "tgn:name":"Rechberg",
    "tgn:placetype":[
        "aat:300008777"
    ]
},
  "bbox": [],
  "geometry": {"coordinates":[8.383333,47.633333],"type":"Point"}
}