{
  "id": 1101914,
  "type": "Feature",
  "properties": {
    "tgn:hierarchy":[
        "tgn:1101914",
        "tgn:7001242",
        "tgn:1000179",
        "tgn:7593686",
        "tgn:7029392"
    ],
    "tgn:id":1101914,
    "tgn:name":"Toubkal, Parc National du",
    "tgn:placetype":[
        "aat:300008189"
    ]
},
  "bbox": [],
  "geometry": {"coordinates":[-7.9167,31.0833],"type":"Point"}
}