{
  "id": 7267340,
  "type": "Feature",
  "properties": {
    "tgn:concordances":{
        "gn:id":"2748884"
    },
    "tgn:hierarchy":[
        "tgn:7267340",
        "tgn:7003619",
        "tgn:1000003",
        "tgn:7016845",
        "tgn:7029392"
    ],
    "tgn:id":7267340,
    "tgn:name:nl":"Oud-Zevenaar",
    "tgn:placetype":[
        "aat:300008347"
    ]
},
  "bbox": [],
  "geometry": {"coordinates":[6.083333,51.916667],"type":"Point"}
}