{
  "id": 2671671,
  "type": "Feature",
  "properties": {
    "tgn:hierarchy":[
        "tgn:2671671",
        "tgn:1000001",
        "tgn:7012149",
        "tgn:1002701",
        "tgn:7007706",
        "tgn:7029392"
    ],
    "tgn:id":2671671,
    "tgn:name":"Smith Mill",
    "tgn:placetype":[
        "aat:300008347"
    ]
},
  "bbox": [],
  "geometry": {"coordinates":[-81.85,39.9167],"type":"Point"}
}