{
  "id": 7581172,
  "type": "Feature",
  "properties": {
    "tgn:hierarchy":[
        "tgn:7581172",
        "tgn:1000004",
        "tgn:7000198",
        "tgn:7016722",
        "tgn:7029392"
    ],
    "tgn:id":7581172,
    "tgn:name:en":"Tirkaulia",
    "tgn:placetype":[
        "aat:300008347"
    ]
},
  "bbox": [],
  "geometry": {"coordinates":[80.486696,28.467274],"type":"Point"}
}