{
  "id": 2451672,
  "type": "Feature",
  "properties": {
    "tgn:hierarchy":[
        "tgn:2451672",
        "tgn:1000001",
        "tgn:7012149",
        "tgn:7007923",
        "tgn:7029392"
    ],
    "tgn:id":2451672,
    "tgn:name":"Little Bear Creek",
    "tgn:placetype":[
        "aat:300008706"
    ]
},
  "bbox": [],
  "geometry": {"coordinates":[-104.9833,41.4833],"type":"Point"}
}