{
  "id": 2086901,
  "type": "Feature",
  "properties": {
    "tgn:hierarchy":[
        "tgn:2086901",
        "tgn:1000001",
        "tgn:7012149",
        "tgn:1002378",
        "tgn:7007710",
        "tgn:7029392"
    ],
    "tgn:id":2086901,
    "tgn:name":"Byromtown",
    "tgn:placetype":[
        "aat:300008347",
        "aat:300387210"
    ]
},
  "bbox": [],
  "geometry": {"coordinates":[-79.05,41.5167],"type":"Point"}
}