{
  "id": 2477886,
  "type": "Feature",
  "properties": {
    "tgn:hierarchy":[
        "tgn:2477886",
        "tgn:1000001",
        "tgn:7012149",
        "tgn:1002817",
        "tgn:7007523",
        "tgn:7029392"
    ],
    "tgn:id":2477886,
    "tgn:name":"Mace Branch",
    "tgn:placetype":[
        "aat:300008699"
    ]
},
  "bbox": [],
  "geometry": {"coordinates":[-91.6333,39.4167],"type":"Point"}
}