{
  "id": 2765463,
  "type": "Feature",
  "properties": {
    "tgn:hierarchy":[
        "tgn:2765463",
        "tgn:1000001",
        "tgn:7012149",
        "tgn:2001662",
        "tgn:7007707",
        "tgn:7029392"
    ],
    "tgn:id":2765463,
    "tgn:name":"White Branch",
    "tgn:placetype":[
        "aat:300008699"
    ]
},
  "bbox": [],
  "geometry": {"coordinates":[-94.7833,34.85],"type":"Point"}
}