{
  "id": 2173912,
  "type": "Feature",
  "properties": {
    "tgn:hierarchy":[
        "tgn:2173912",
        "tgn:1000001",
        "tgn:2000863",
        "tgn:7012149",
        "tgn:7007256",
        "tgn:7029392"
    ],
    "tgn:id":2173912,
    "tgn:name":"Bird Island Bay",
    "tgn:placetype":[
        "aat:300132316"
    ]
},
  "bbox": [],
  "geometry": {"coordinates":[-93.1833,30.2833],"type":"Point"}
}