{
  "id": 7443559,
  "type": "Feature",
  "properties": {
    "tgn:hierarchy":[
        "tgn:7443559",
        "tgn:7008696",
        "tgn:7002448",
        "tgn:1000003",
        "tgn:7008591",
        "tgn:7029392"
    ],
    "tgn:id":7443559,
    "tgn:name:en":"Corliss Lough",
    "tgn:placetype":[
        "aat:300008680"
    ]
},
  "bbox": [],
  "geometry": {"coordinates":[-6.644167,54.098056],"type":"Point"}
}