{
  "id": 7269336,
  "type": "Feature",
  "properties": {
    "tgn:concordances":{
        "gn:id":"2749055"
    },
    "tgn:hierarchy":[
        "tgn:7269336",
        "tgn:7003614",
        "tgn:1000003",
        "tgn:7016845",
        "tgn:7029392"
    ],
    "tgn:id":7269336,
    "tgn:name:nl":"Oudemolen",
    "tgn:placetype":[
        "aat:300008347"
    ]
},
  "bbox": [],
  "geometry": {"coordinates":[6.65,53.05],"type":"Point"}
}