{
  "id": 2536193,
  "type": "Feature",
  "properties": {
    "tgn:hierarchy":[
        "tgn:2536193",
        "tgn:1000001",
        "tgn:2001705",
        "tgn:7012149",
        "tgn:7007708",
        "tgn:7029392"
    ],
    "tgn:id":2536193,
    "tgn:name":"Navaho Lake",
    "tgn:placetype":[
        "aat:300008680"
    ]
},
  "bbox": [],
  "geometry": {"coordinates":[-121.9167,43.8167],"type":"Point"}
}