<<<<<<< HEAD
{
  "id": 7477981,
  "type": "Feature",
  "properties": {
    "tgn:hierarchy":[
        "tgn:7477981",
        "tgn:7001010",
        "tgn:1000004",
        "tgn:1000141",
        "tgn:7029392"
    ],
    "tgn:id":7477981,
    "tgn:name":"Tonglan Guoxiao",
    "tgn:placetype":[
        "aat:300006495"
    ]
},
  "bbox": [],
  "geometry": {"coordinates":[121.507338,23.947216],"type":"Point"}
}
=======
{"geometry":{"type":"Point","coordinates":[121.507338,23.947216]},"type":"Feature","properties":{"hierarchy":["tgn:7477981","tgn:7001010","tgn:1000004","tgn:1000141","tgn:7029392"],"placetype":["aat:300006495"],"id":7477981,"name:xx":"Tonglan Guoxiao"}}
>>>>>>> 03f74aca74312dbeaf24d7e61306dd6a786dc3d0
