{
  "id": 2570178,
  "type": "Feature",
  "properties": {
    "tgn:hierarchy":[
        "tgn:2570178",
        "tgn:1000001",
        "tgn:1002270",
        "tgn:7012149",
        "tgn:7007708",
        "tgn:7029392"
    ],
    "tgn:id":2570178,
    "tgn:name":"Paste Creek",
    "tgn:placetype":[
        "aat:300008706"
    ]
},
  "bbox": [],
  "geometry": {"coordinates":[-122.0167,44.9833],"type":"Point"}
}