{
  "id": 2427294,
  "type": "Feature",
  "properties": {
    "tgn:hierarchy":[
        "tgn:2427294",
        "tgn:1000001",
        "tgn:7012149",
        "tgn:2001549",
        "tgn:7007709",
        "tgn:7029392"
    ],
    "tgn:id":2427294,
    "tgn:name":"Jordan Creek",
    "tgn:placetype":[
        "aat:300008706"
    ]
},
  "bbox": [],
  "geometry": {"coordinates":[-78.05,36.4667],"type":"Point"}
}