{
  "id": 1098411,
  "type": "Feature",
  "properties": {
    "tgn:hierarchy":[
        "tgn:1098411",
        "tgn:7000490",
        "tgn:1000006",
        "tgn:7001831",
        "tgn:7029392"
    ],
    "tgn:id":1098411,
    "tgn:name":"Verran",
    "tgn:placetype":[
        "aat:300008347"
    ]
},
  "bbox": [],
  "geometry": {"coordinates":[136.2667,-33.8333],"type":"Point"}
}