<<<<<<< HEAD
{
  "id": 2403184,
  "type": "Feature",
  "properties": {
    "tgn:hierarchy":[
        "tgn:2403184",
        "tgn:1000001",
        "tgn:7012149",
        "tgn:2001441",
        "tgn:7007566",
        "tgn:7029392"
    ],
    "tgn:id":2403184,
    "tgn:name":"House Lake",
    "tgn:placetype":[
        "aat:300008680"
    ]
},
  "bbox": [],
  "geometry": {"coordinates":[-103.4833,33.3667],"type":"Point"}
}
=======
{"geometry":{"type":"Point","coordinates":[-103.483300,33.366700]},"type":"Feature","properties":{"hierarchy":["tgn:2403184","tgn:1000001","tgn:7012149","tgn:2001441","tgn:7007566","tgn:7029392"],"placetype":["aat:300008680"],"id":2403184,"name:xx":"House Lake"}}
>>>>>>> 03f74aca74312dbeaf24d7e61306dd6a786dc3d0
