{
  "id": 2422555,
  "type": "Feature",
  "properties": {
    "tgn:hierarchy":[
        "tgn:2422555",
        "tgn:1000001",
        "tgn:7012149",
        "tgn:1002995",
        "tgn:7007710",
        "tgn:7029392"
    ],
    "tgn:id":2422555,
    "tgn:name":"Jo-ann, Lake",
    "tgn:placetype":[
        "aat:300006191"
    ]
},
  "bbox": [],
  "geometry": {"coordinates":[-80.0333,40.25],"type":"Point"}
}