{
  "id": 2251741,
  "type": "Feature",
  "properties": {
    "tgn:hierarchy":[
        "tgn:2251741",
        "tgn:1000001",
        "tgn:7012149",
        "tgn:7007522",
        "tgn:7029392"
    ],
    "tgn:id":2251741,
    "tgn:name":"Compton Creek",
    "tgn:placetype":[
        "aat:300008706"
    ]
},
  "bbox": [],
  "geometry": {"coordinates":[-91.0667,31.5833],"type":"Point"}
}