<<<<<<< HEAD
{
  "id": 2251741,
  "type": "Feature",
  "properties": {
    "tgn:hierarchy":[
        "tgn:2251741",
        "tgn:1000001",
        "tgn:7012149",
        "tgn:7007522",
        "tgn:7029392"
    ],
    "tgn:id":2251741,
    "tgn:name":"Compton Creek",
    "tgn:placetype":[
        "aat:300008706"
    ]
},
  "bbox": [],
  "geometry": {"coordinates":[-91.0667,31.5833],"type":"Point"}
}
=======
{"geometry":{"type":"Point","coordinates":[-91.066700,31.583300]},"type":"Feature","properties":{"hierarchy":["tgn:2251741","tgn:1000001","tgn:7012149","tgn:7007522","tgn:7029392"],"placetype":["aat:300008706"],"id":2251741,"name:xx":"Compton Creek"}}
>>>>>>> 03f74aca74312dbeaf24d7e61306dd6a786dc3d0
