{
  "id": 2110182,
  "type": "Feature",
  "properties": {
    "tgn:hierarchy":[
        "tgn:2110182",
        "tgn:1000001",
        "tgn:1002840",
        "tgn:7012149",
        "tgn:7007828",
        "tgn:7029392"
    ],
    "tgn:id":2110182,
    "tgn:name":"West Pawlet",
    "tgn:placetype":[
        "aat:300008347"
    ]
},
  "bbox": [],
  "geometry": {"coordinates":[-73.25,43.35],"type":"Point"}
}