{
  "id": 7266743,
  "type": "Feature",
  "properties": {
    "tgn:concordances":{
        "gn:id":"2754123"
    },
    "tgn:hierarchy":[
        "tgn:7266743",
        "tgn:1000003",
        "tgn:7003624",
        "tgn:7016845",
        "tgn:7029392"
    ],
    "tgn:id":7266743,
    "tgn:name:nl":"Heuvels",
    "tgn:placetype":[
        "aat:300008347"
    ]
},
  "bbox": [],
  "geometry": {"coordinates":[5.633333,51.766667],"type":"Point"}
}