<<<<<<< HEAD
{
  "id": 7362696,
  "type": "Feature",
  "properties": {
    "tgn:hierarchy":[
        "tgn:7362696",
        "tgn:7005581",
        "tgn:1000001",
        "tgn:7005560",
        "tgn:7029392"
    ],
    "tgn:id":7362696,
    "tgn:name":"El Alamillo",
    "tgn:placetype":[
        "aat:300008347"
    ]
},
  "bbox": [],
  "geometry": {"coordinates":[-107.533333,29.333333],"type":"Point"}
}
=======
{"geometry":{"type":"Point","coordinates":[-107.533333,29.333333]},"type":"Feature","properties":{"hierarchy":["tgn:7362696","tgn:7005581","tgn:1000001","tgn:7005560","tgn:7029392"],"placetype":["aat:300008347"],"id":7362696,"name:xx":"El Alamillo"}}
>>>>>>> 03f74aca74312dbeaf24d7e61306dd6a786dc3d0
