{
  "id": 7187496,
  "type": "Feature",
  "properties": {
    "tgn:hierarchy":[
        "tgn:7187496",
        "tgn:1000003",
        "tgn:7003677",
        "tgn:7000084",
        "tgn:7029392"
    ],
    "tgn:id":7187496,
    "tgn:name":"Elisenh\u00f6he",
    "tgn:placetype":[
        "aat:300000206"
    ]
},
  "bbox": [],
  "geometry": {"coordinates":[9.316667,51.666667],"type":"Point"}
}