{
  "id": 2697176,
  "type": "Feature",
  "properties": {
    "tgn:hierarchy":[
        "tgn:2697176",
        "tgn:1000001",
        "tgn:7012149",
        "tgn:2001866",
        "tgn:7007825",
        "tgn:7029392"
    ],
    "tgn:id":2697176,
    "tgn:name":"Stony Cove",
    "tgn:placetype":[
        "aat:300008761"
    ]
},
  "bbox": [],
  "geometry": {"coordinates":[-82.75,36.0167],"type":"Point"}
}