<<<<<<< HEAD
{
  "id": 2762004,
  "type": "Feature",
  "properties": {
    "tgn:hierarchy":[
        "tgn:2762004",
        "tgn:1000001",
        "tgn:7012149",
        "tgn:2001439",
        "tgn:7007566",
        "tgn:7029392"
    ],
    "tgn:id":2762004,
    "tgn:name":"West Sand Springs",
    "tgn:placetype":[
        "aat:300008697"
    ]
},
  "bbox": [],
  "geometry": {"coordinates":[-103.3833,35.4833],"type":"Point"}
}
=======
{"geometry":{"type":"Point","coordinates":[-103.383300,35.483300]},"type":"Feature","properties":{"hierarchy":["tgn:2762004","tgn:1000001","tgn:7012149","tgn:2001439","tgn:7007566","tgn:7029392"],"placetype":["aat:300008697"],"id":2762004,"name:xx":"West Sand Springs"}}
>>>>>>> 03f74aca74312dbeaf24d7e61306dd6a786dc3d0
