{
  "id": 2052273,
  "type": "Feature",
  "properties": {
    "tgn:hierarchy":[
        "tgn:2052273",
        "tgn:1000001",
        "tgn:7012149",
        "tgn:2000960",
        "tgn:7007520",
        "tgn:7029392"
    ],
    "tgn:id":2052273,
    "tgn:name":"Ironwood",
    "tgn:placetype":[
        "aat:300008347"
    ]
},
  "bbox": [],
  "geometry": {"coordinates":[-90.1667,46.45],"type":"Point"}
}