{
  "id": 2650527,
  "type": "Feature",
  "properties": {
    "tgn:hierarchy":[
        "tgn:2650527",
        "tgn:1000001",
        "tgn:7014352",
        "tgn:7012149",
        "tgn:7007564",
        "tgn:7029392"
    ],
    "tgn:id":2650527,
    "tgn:name":"Seavey Pond",
    "tgn:placetype":[
        "aat:300006191"
    ]
},
  "bbox": [],
  "geometry": {"coordinates":[-71.25,42.8167],"type":"Point"}
}