{
  "id": 2550845,
  "type": "Feature",
  "properties": {
    "tgn:hierarchy":[
        "tgn:2550845",
        "tgn:1000001",
        "tgn:2001181",
        "tgn:7012149",
        "tgn:7007523",
        "tgn:7029392"
    ],
    "tgn:id":2550845,
    "tgn:name":"Norwood Hollow",
    "tgn:placetype":[
        "aat:300008761"
    ]
},
  "bbox": [],
  "geometry": {"coordinates":[-90.9667,37.05],"type":"Point"}
}