{
  "id": 7508618,
  "type": "Feature",
  "properties": {
    "tgn:hierarchy":[
        "tgn:7508618",
        "tgn:1008380",
        "tgn:1000226",
        "tgn:7000512",
        "tgn:1000006",
        "tgn:7029392"
    ],
    "tgn:id":7508618,
    "tgn:name:en":"Otahome Stream",
    "tgn:placetype":[
        "aat:300008699"
    ]
},
  "bbox": [],
  "geometry": {"coordinates":[176.15,-40.95],"type":"Point"}
}