{
  "id": 2114374,
  "type": "Feature",
  "properties": {
    "tgn:hierarchy":[
        "tgn:2114374",
        "tgn:1000001",
        "tgn:7012149",
        "tgn:2002179",
        "tgn:7007919",
        "tgn:7029392"
    ],
    "tgn:id":2114374,
    "tgn:name":"Stella",
    "tgn:placetype":[
        "aat:300008347",
        "aat:300387210"
    ]
},
  "bbox": [],
  "geometry": {"coordinates":[-80.0833,36.6167],"type":"Point"}
}