{
  "id": 7071983,
  "type": "Feature",
  "properties": {
    "tgn:hierarchy":[
        "tgn:7071983",
        "tgn:7003692",
        "tgn:1000003",
        "tgn:7000084",
        "tgn:7029392"
    ],
    "tgn:id":7071983,
    "tgn:name":"Taubergrund",
    "tgn:placetype":[
        "aat:300055621"
    ]
},
  "bbox": [],
  "geometry": {"coordinates":[9.833333,49.433333],"type":"Point"}
}