{
  "id": 2186854,
  "type": "Feature",
  "properties": {
    "tgn:hierarchy":[
        "tgn:2186854",
        "tgn:1000001",
        "tgn:7012149",
        "tgn:2001190",
        "tgn:7007523",
        "tgn:7029392"
    ],
    "tgn:id":2186854,
    "tgn:name":"Bonito Iron Mine",
    "tgn:placetype":[
        "aat:300000390"
    ]
},
  "bbox": [],
  "geometry": {"coordinates":[-91.4167,37.85],"type":"Point"}
}