{
  "id": 2676646,
  "type": "Feature",
  "properties": {
    "tgn:hierarchy":[
        "tgn:2676646",
        "tgn:1000001",
        "tgn:7012149",
        "tgn:2001506",
        "tgn:7007709",
        "tgn:7029392"
    ],
    "tgn:id":2676646,
    "tgn:name":"South Bitterswash Creek",
    "tgn:placetype":[
        "aat:300008706"
    ]
},
  "bbox": [],
  "geometry": {"coordinates":[-75.8333,35.15],"type":"Point"}
}