<<<<<<< HEAD
{
  "id": 2259877,
  "type": "Feature",
  "properties": {
    "tgn:hierarchy":[
        "tgn:2259877",
        "tgn:1000001",
        "tgn:7012149",
        "tgn:2000881",
        "tgn:7007256",
        "tgn:7029392"
    ],
    "tgn:id":2259877,
    "tgn:name":"Coulee Lantier",
    "tgn:placetype":[
        "aat:300008699"
    ]
},
  "bbox": [],
  "geometry": {"coordinates":[-91.9833,30.3333],"type":"Point"}
}
=======
{"geometry":{"type":"Point","coordinates":[-91.983300,30.333300]},"type":"Feature","properties":{"hierarchy":["tgn:2259877","tgn:1000001","tgn:7012149","tgn:2000881","tgn:7007256","tgn:7029392"],"placetype":["aat:300008699"],"id":2259877,"name:xx":"Coulee Lantier"}}
>>>>>>> 03f74aca74312dbeaf24d7e61306dd6a786dc3d0
