{
  "id": 2770815,
  "type": "Feature",
  "properties": {
    "tgn:hierarchy":[
        "tgn:2770815",
        "tgn:1000001",
        "tgn:7012149",
        "tgn:2001218",
        "tgn:7007523",
        "tgn:7029392"
    ],
    "tgn:id":2770815,
    "tgn:name":"Wildcat Creek",
    "tgn:placetype":[
        "aat:300008706"
    ]
},
  "bbox": [],
  "geometry": {"coordinates":[-93.5333,40.45],"type":"Point"}
}