{
  "id": 2413436,
  "type": "Feature",
  "properties": {
    "tgn:hierarchy":[
        "tgn:2413436",
        "tgn:1000001",
        "tgn:7006451",
        "tgn:2000092",
        "tgn:7012149",
        "tgn:7029392"
    ],
    "tgn:id":2413436,
    "tgn:name":"Iowa Camp Spring",
    "tgn:placetype":[
        "aat:300008697"
    ]
},
  "bbox": [],
  "geometry": {"coordinates":[-111.4167,34.8833],"type":"Point"}
}