{
  "id": 2549219,
  "type": "Feature",
  "properties": {
    "tgn:hierarchy":[
        "tgn:2549219",
        "tgn:1000001",
        "tgn:2001477",
        "tgn:7012149",
        "tgn:7007709",
        "tgn:7029392"
    ],
    "tgn:id":2549219,
    "tgn:name":"North River",
    "tgn:placetype":[
        "aat:300008707"
    ]
},
  "bbox": [],
  "geometry": {"coordinates":[-76.6167,34.8333],"type":"Point"}
}