<<<<<<< HEAD
{
  "id": 7478317,
  "type": "Feature",
  "properties": {
    "tgn:hierarchy":[
        "tgn:7478317",
        "tgn:7487020",
        "tgn:1000004",
        "tgn:1000141",
        "tgn:7029392"
    ],
    "tgn:id":7478317,
    "tgn:name":"Baiyun Si",
    "tgn:placetype":[
        "aat:300007595"
    ]
},
  "bbox": [],
  "geometry": {"coordinates":[120.990771,24.626797],"type":"Point"}
}
=======
{"geometry":{"type":"Point","coordinates":[120.990771,24.626797]},"type":"Feature","properties":{"hierarchy":["tgn:7478317","tgn:7487020","tgn:1000004","tgn:1000141","tgn:7029392"],"placetype":["aat:300007595"],"id":7478317,"name:xx":"Baiyun Si"}}
>>>>>>> 03f74aca74312dbeaf24d7e61306dd6a786dc3d0
