{
  "id": 2518400,
  "type": "Feature",
  "properties": {
    "tgn:hierarchy":[
        "tgn:2518400",
        "tgn:2000919",
        "tgn:1000001",
        "tgn:7012149",
        "tgn:7007515",
        "tgn:7029392"
    ],
    "tgn:id":2518400,
    "tgn:name":"Mitchel Mountain",
    "tgn:placetype":[
        "aat:300008798"
    ]
},
  "bbox": [],
  "geometry": {"coordinates":[-67.9667,45.85],"type":"Point"}
}