{
  "id": 2511719,
  "type": "Feature",
  "properties": {
    "tgn:hierarchy":[
        "tgn:2511719",
        "tgn:1000001",
        "tgn:7012149",
        "tgn:2001767",
        "tgn:7007712",
        "tgn:7029392"
    ],
    "tgn:id":2511719,
    "tgn:name":"Milford",
    "tgn:placetype":[
        "aat:300008347"
    ]
},
  "bbox": [],
  "geometry": {"coordinates":[-80.5333,33.7333],"type":"Point"}
}