{
  "id": 7408531,
  "type": "Feature",
  "properties": {
    "tgn:hierarchy":[
        "tgn:7408531",
        "tgn:1000001",
        "tgn:1001893",
        "tgn:7005560",
        "tgn:7029392"
    ],
    "tgn:id":7408531,
    "tgn:name":"Buenavista",
    "tgn:placetype":[
        "aat:300008347"
    ]
},
  "bbox": [],
  "geometry": {"coordinates":[-99.583333,20.1875],"type":"Point"}
}