{
  "id": 2560762,
  "type": "Feature",
  "properties": {
    "tgn:hierarchy":[
        "tgn:2560762",
        "tgn:1000001",
        "tgn:7012149",
        "tgn:7007708",
        "tgn:7029392"
    ],
    "tgn:id":2560762,
    "tgn:name":"Oriental Creek",
    "tgn:placetype":[
        "aat:300008706"
    ]
},
  "bbox": [],
  "geometry": {"coordinates":[-118.7333,45.0167],"type":"Point"}
}