{
  "id": 7481770,
  "type": "Feature",
  "properties": {
    "tgn:hierarchy":[
        "tgn:7481770",
        "tgn:1000004",
        "tgn:7001013",
        "tgn:1000141",
        "tgn:7029392"
    ],
    "tgn:id":7481770,
    "tgn:name":"Dapi",
    "tgn:placetype":[
        "aat:300387033"
    ]
},
  "bbox": [],
  "geometry": {"coordinates":[121.138333,24.995556],"type":"Point"}
}