<<<<<<< HEAD
{
  "id": 7481770,
  "type": "Feature",
  "properties": {
    "tgn:hierarchy":[
        "tgn:7481770",
        "tgn:1000004",
        "tgn:7001013",
        "tgn:1000141",
        "tgn:7029392"
    ],
    "tgn:id":7481770,
    "tgn:name":"Dapi",
    "tgn:placetype":[
        "aat:300387033"
    ]
},
  "bbox": [],
  "geometry": {"coordinates":[121.138333,24.995556],"type":"Point"}
}
=======
{"geometry":{"type":"Point","coordinates":[121.138333,24.995556]},"type":"Feature","properties":{"hierarchy":["tgn:7481770","tgn:1000004","tgn:7001013","tgn:1000141","tgn:7029392"],"placetype":["aat:300387033"],"id":7481770,"name:xx":"Dapi"}}
>>>>>>> 03f74aca74312dbeaf24d7e61306dd6a786dc3d0
