{
  "id": 7577675,
  "type": "Feature",
  "properties": {
    "tgn:hierarchy":[
        "tgn:7577675",
        "tgn:1000004",
        "tgn:7000198",
        "tgn:7000799",
        "tgn:7029392"
    ],
    "tgn:id":7577675,
    "tgn:name:en":"Kartse",
    "tgn:placetype":[
        "aat:300008347"
    ]
},
  "bbox": [],
  "geometry": {"coordinates":[76.016667,34.266667],"type":"Point"}
}