{
  "id": 2642726,
  "type": "Feature",
  "properties": {
    "tgn:hierarchy":[
        "tgn:2642726",
        "tgn:1000001",
        "tgn:2001411",
        "tgn:7012149",
        "tgn:7007526",
        "tgn:7029392"
    ],
    "tgn:id":2642726,
    "tgn:name":"Sandhill Spring",
    "tgn:placetype":[
        "aat:300008697"
    ]
},
  "bbox": [],
  "geometry": {"coordinates":[-115.5333,40.8167],"type":"Point"}
}