{
  "id": 7028216,
  "type": "Feature",
  "properties": {
    "tgn:hierarchy":[
        "tgn:7028216",
        "tgn:7002445",
        "tgn:1000003",
        "tgn:7008157",
        "tgn:7008591",
        "tgn:7029392"
    ],
    "tgn:id":7028216,
    "tgn:name":"Willingham by Stow",
    "tgn:placetype":[
        "aat:300008347",
        "aat:300008372"
    ]
},
  "bbox": [],
  "geometry": {"coordinates":[-0.694,53.35],"type":"Point"}
}