{
  "id": 2730897,
  "type": "Feature",
  "properties": {
    "tgn:hierarchy":[
        "tgn:2730897",
        "tgn:1000001",
        "tgn:7012149",
        "tgn:2001719",
        "tgn:7007708",
        "tgn:7029392"
    ],
    "tgn:id":2730897,
    "tgn:name":"Tub Springs",
    "tgn:placetype":[
        "aat:300008697"
    ]
},
  "bbox": [],
  "geometry": {"coordinates":[-119.6667,45.6667],"type":"Point"}
}