{
  "id": 2205473,
  "type": "Feature",
  "properties": {
    "tgn:hierarchy":[
        "tgn:2205473",
        "tgn:1000001",
        "tgn:7012149",
        "tgn:1002476",
        "tgn:7007706",
        "tgn:7029392"
    ],
    "tgn:id":2205473,
    "tgn:name":"Bull Creek",
    "tgn:placetype":[
        "aat:300008706"
    ]
},
  "bbox": [],
  "geometry": {"coordinates":[-83.55,39.3167],"type":"Point"}
}