{
  "id": 2656488,
  "type": "Feature",
  "properties": {
    "tgn:hierarchy":[
        "tgn:2656488",
        "tgn:1000001",
        "tgn:2001429",
        "tgn:7012149",
        "tgn:7007566",
        "tgn:7029392"
    ],
    "tgn:id":2656488,
    "tgn:name":"Sheep Basin",
    "tgn:placetype":[
        "aat:300386845"
    ]
},
  "bbox": [],
  "geometry": {"coordinates":[-108.7167,33.5833],"type":"Point"}
}