{
  "id": 2554675,
  "type": "Feature",
  "properties": {
    "tgn:hierarchy":[
        "tgn:2554675",
        "tgn:1000001",
        "tgn:7016172",
        "tgn:7012149",
        "tgn:2000165",
        "tgn:7029392"
    ],
    "tgn:id":2554675,
    "tgn:name":"Oaks Hill",
    "tgn:placetype":[
        "aat:300008798"
    ]
},
  "bbox": [],
  "geometry": {"coordinates":[-91.2333,36.2833],"type":"Point"}
}