{
  "id": 2026619,
  "type": "Feature",
  "properties": {
    "tgn:hierarchy":[
        "tgn:2026619",
        "tgn:1000001",
        "tgn:7012149",
        "tgn:2000514",
        "tgn:7007251",
        "tgn:7029392"
    ],
    "tgn:id":2026619,
    "tgn:name":"Blanding",
    "tgn:placetype":[
        "aat:300387016"
    ]
},
  "bbox": [],
  "geometry": {"coordinates":[-90.3833,42.2667],"type":"Point"}
}