{
  "id": 7048567,
  "type": "Feature",
  "properties": {
    "tgn:hierarchy":[
        "tgn:7048567",
        "tgn:7015163",
        "tgn:1000003",
        "tgn:7003121",
        "tgn:1000080",
        "tgn:7029392"
    ],
    "tgn:id":7048567,
    "tgn:name":"Casale Garibaldi",
    "tgn:placetype":[
        "aat:300008347"
    ]
},
  "bbox": [],
  "geometry": {"coordinates":[9.45,41.216667],"type":"Point"}
}