{
  "id": 7583045,
  "type": "Feature",
  "properties": {
    "tgn:hierarchy":[
        "tgn:7583045",
        "tgn:1000004",
        "tgn:7000198",
        "tgn:1001894",
        "tgn:7029392"
    ],
    "tgn:id":7583045,
    "tgn:name:en":"Basiy\u0101gond Reserved Forest",
    "tgn:placetype":[
        "aat:300008865"
    ]
},
  "bbox": [],
  "geometry": {"coordinates":[78.507988,24.023422],"type":"Point"}
}