<<<<<<< HEAD
{
  "id": 7482311,
  "type": "Feature",
  "properties": {
    "tgn:hierarchy":[
        "tgn:7482311",
        "tgn:1000004",
        "tgn:7001009",
        "tgn:1000141",
        "tgn:7029392"
    ],
    "tgn:id":7482311,
    "tgn:name":"Pintian Shan Qianfeng",
    "tgn:placetype":[
        "aat:300008798"
    ]
},
  "bbox": [],
  "geometry": {"coordinates":[121.269722,24.4275],"type":"Point"}
}
=======
{"geometry":{"type":"Point","coordinates":[121.269722,24.427500]},"type":"Feature","properties":{"hierarchy":["tgn:7482311","tgn:1000004","tgn:7001009","tgn:1000141","tgn:7029392"],"placetype":["aat:300008798"],"id":7482311,"name:xx":"Pintian Shan Qianfeng"}}
>>>>>>> 03f74aca74312dbeaf24d7e61306dd6a786dc3d0
