{
  "id": 7482311,
  "type": "Feature",
  "properties": {
    "tgn:hierarchy":[
        "tgn:7482311",
        "tgn:1000004",
        "tgn:7001009",
        "tgn:1000141",
        "tgn:7029392"
    ],
    "tgn:id":7482311,
    "tgn:name":"Pintian Shan Qianfeng",
    "tgn:placetype":[
        "aat:300008798"
    ]
},
  "bbox": [],
  "geometry": {"coordinates":[121.269722,24.4275],"type":"Point"}
}