{
  "id": 7388925,
  "type": "Feature",
  "properties": {
    "tgn:hierarchy":[
        "tgn:7388925",
        "tgn:7005581",
        "tgn:1000001",
        "tgn:7005560",
        "tgn:7029392"
    ],
    "tgn:id":7388925,
    "tgn:name":"Pastorias, Sierra",
    "tgn:placetype":[
        "aat:300008795"
    ]
},
  "bbox": [],
  "geometry": {"coordinates":[-105.95,28.383333],"type":"Point"}
}