{
  "id": 2734599,
  "type": "Feature",
  "properties": {
    "tgn:hierarchy":[
        "tgn:2734599",
        "tgn:1000001",
        "tgn:7006451",
        "tgn:7012149",
        "tgn:2000104",
        "tgn:7029392"
    ],
    "tgn:id":2734599,
    "tgn:name":"Tuseral Tank",
    "tgn:placetype":[
        "aat:300006191"
    ]
},
  "bbox": [],
  "geometry": {"coordinates":[-113.7333,32.1833],"type":"Point"}
}