{
  "id": 2588714,
  "type": "Feature",
  "properties": {
    "tgn:hierarchy":[
        "tgn:2588714",
        "tgn:1000001",
        "tgn:7012149",
        "tgn:2002030",
        "tgn:7007826",
        "tgn:7029392"
    ],
    "tgn:id":2588714,
    "tgn:name":"Pluto Mountain",
    "tgn:placetype":[
        "aat:300008798"
    ]
},
  "bbox": [],
  "geometry": {"coordinates":[-98.6833,30.6167],"type":"Point"}
}