{
  "id": 2263577,
  "type": "Feature",
  "properties": {
    "tgn:hierarchy":[
        "tgn:2263577",
        "tgn:1000001",
        "tgn:7013368",
        "tgn:7012149",
        "tgn:7007709",
        "tgn:7029392"
    ],
    "tgn:id":2263577,
    "tgn:name":"Coxs Crossroads",
    "tgn:placetype":[
        "aat:300008347"
    ]
},
  "bbox": [],
  "geometry": {"coordinates":[-76.95,35.3667],"type":"Point"}
}