{
  "id": 2453966,
  "type": "Feature",
  "properties": {
    "tgn:hierarchy":[
        "tgn:2453966",
        "tgn:1000001",
        "tgn:7012149",
        "tgn:7007240",
        "tgn:7029392"
    ],
    "tgn:id":2453966,
    "tgn:name":"Little Creek",
    "tgn:placetype":[
        "aat:300008706"
    ]
},
  "bbox": [],
  "geometry": {"coordinates":[-85.4667,30.9667],"type":"Point"}
}