{
  "id": 2548669,
  "type": "Feature",
  "properties": {
    "tgn:hierarchy":[
        "tgn:2548669",
        "tgn:1000001",
        "tgn:7012149",
        "tgn:2002129",
        "tgn:7007827",
        "tgn:7029392"
    ],
    "tgn:id":2548669,
    "tgn:name":"North Ogden Canal",
    "tgn:placetype":[
        "aat:300006075"
    ]
},
  "bbox": [],
  "geometry": {"coordinates":[-111.95,41.2833],"type":"Point"}
}