{
  "id": 7066097,
  "type": "Feature",
  "properties": {
    "tgn:hierarchy":[
        "tgn:7066097",
        "tgn:7003669",
        "tgn:1000003",
        "tgn:7000084",
        "tgn:7029392"
    ],
    "tgn:id":7066097,
    "tgn:name":"Truschenhof",
    "tgn:placetype":[
        "aat:300000206"
    ]
},
  "bbox": [],
  "geometry": {"coordinates":[10.866667,50.133333],"type":"Point"}
}