<<<<<<< HEAD
{
  "id": 2402722,
  "type": "Feature",
  "properties": {
    "tgn:hierarchy":[
        "tgn:2402722",
        "tgn:2000195",
        "tgn:1000001",
        "tgn:7012149",
        "tgn:7007158",
        "tgn:7029392"
    ],
    "tgn:id":2402722,
    "tgn:name":"Hot Springs",
    "tgn:placetype":[
        "aat:300008697"
    ]
},
  "bbox": [],
  "geometry": {"coordinates":[-107.0,37.25],"type":"Point"}
}
=======
{"geometry":{"type":"Point","coordinates":[-107.000000,37.250000]},"type":"Feature","properties":{"hierarchy":["tgn:2402722","tgn:2000195","tgn:1000001","tgn:7012149","tgn:7007158","tgn:7029392"],"placetype":["aat:300008697"],"id":2402722,"name:xx":"Hot Springs"}}
>>>>>>> 03f74aca74312dbeaf24d7e61306dd6a786dc3d0
