<<<<<<< HEAD
{
  "id": 2254552,
  "type": "Feature",
  "properties": {
    "tgn:hierarchy":[
        "tgn:2254552",
        "tgn:7002659",
        "tgn:1000001",
        "tgn:2000016",
        "tgn:7012149",
        "tgn:7029392"
    ],
    "tgn:id":2254552,
    "tgn:name":"Coon Hollow",
    "tgn:placetype":[
        "aat:300008761"
    ]
},
  "bbox": [],
  "geometry": {"coordinates":[-87.9667,34.8667],"type":"Point"}
}
=======
{"geometry":{"type":"Point","coordinates":[-87.966700,34.866700]},"type":"Feature","properties":{"hierarchy":["tgn:2254552","tgn:7002659","tgn:1000001","tgn:2000016","tgn:7012149","tgn:7029392"],"placetype":["aat:300008761"],"id":2254552,"name:xx":"Coon Hollow"}}
>>>>>>> 03f74aca74312dbeaf24d7e61306dd6a786dc3d0
