{
  "id": 2532797,
  "type": "Feature",
  "properties": {
    "tgn:hierarchy":[
        "tgn:2532797",
        "tgn:1000001",
        "tgn:7012149",
        "tgn:2000420",
        "tgn:7007248",
        "tgn:7029392"
    ],
    "tgn:id":2532797,
    "tgn:name":"Murphys Mill Pond",
    "tgn:placetype":[
        "aat:300006191"
    ]
},
  "bbox": [],
  "geometry": {"coordinates":[-84.2167,32.0333],"type":"Point"}
}