{
  "id": 2291729,
  "type": "Feature",
  "properties": {
    "tgn:hierarchy":[
        "tgn:2291729",
        "tgn:1000001",
        "tgn:7012149",
        "tgn:2001241",
        "tgn:7007523",
        "tgn:7029392"
    ],
    "tgn:id":2291729,
    "tgn:name":"Dolomite Mines",
    "tgn:placetype":[
        "aat:300000390"
    ]
},
  "bbox": [],
  "geometry": {"coordinates":[-90.5167,37.8833],"type":"Point"}
}