{
  "id": 2338808,
  "type": "Feature",
  "properties": {
    "tgn:hierarchy":[
        "tgn:2338808",
        "tgn:1000001",
        "tgn:7012149",
        "tgn:2000230",
        "tgn:7007158",
        "tgn:7029392"
    ],
    "tgn:id":2338808,
    "tgn:name":"Frank Moore Canyon",
    "tgn:placetype":[
        "aat:300008761"
    ]
},
  "bbox": [],
  "geometry": {"coordinates":[-108.7667,38.8667],"type":"Point"}
}