<<<<<<< HEAD
{
  "id": 7356204,
  "type": "Feature",
  "properties": {
    "tgn:hierarchy":[
        "tgn:7356204",
        "tgn:1000001",
        "tgn:1001893",
        "tgn:7005560",
        "tgn:7029392"
    ],
    "tgn:id":7356204,
    "tgn:name":"Caribe, Mar",
    "tgn:placetype":[
        "aat:300008694"
    ]
},
  "bbox": [],
  "geometry": {"coordinates":[-75.0,15.0],"type":"Point"}
}
=======
{"geometry":{"type":"Point","coordinates":[-75.000000,15.000000]},"type":"Feature","properties":{"hierarchy":["tgn:7356204","tgn:1000001","tgn:1001893","tgn:7005560","tgn:7029392"],"placetype":["aat:300008694"],"id":7356204,"name:xx":"Caribe, Mar"}}
>>>>>>> 03f74aca74312dbeaf24d7e61306dd6a786dc3d0
