{
  "id": 2329082,
  "type": "Feature",
  "properties": {
    "tgn:hierarchy":[
        "tgn:2329082",
        "tgn:7013388",
        "tgn:1000001",
        "tgn:7012149",
        "tgn:7007517",
        "tgn:7029392"
    ],
    "tgn:id":2329082,
    "tgn:name":"Fitch, Mount",
    "tgn:placetype":[
        "aat:300008798"
    ]
},
  "bbox": [],
  "geometry": {"coordinates":[-73.15,42.65],"type":"Point"}
}