{
  "id": 2143081,
  "type": "Feature",
  "properties": {
    "tgn:hierarchy":[
        "tgn:2143081",
        "tgn:7002659",
        "tgn:1000001",
        "tgn:7012149",
        "tgn:2000035",
        "tgn:7029392"
    ],
    "tgn:id":2143081,
    "tgn:name":"Bags Ditch Cave",
    "tgn:placetype":[
        "aat:300008746"
    ]
},
  "bbox": [],
  "geometry": {"coordinates":[-86.2667,34.8667],"type":"Point"}
}