{
  "id": 1052011,
  "type": "Feature",
  "properties": {
    "tgn:hierarchy":[
        "tgn:1052011",
        "tgn:1000004",
        "tgn:7011498",
        "tgn:7002435",
        "tgn:7029392"
    ],
    "tgn:id":1052011,
    "tgn:name":"Akyar",
    "tgn:placetype":[
        "aat:300008347"
    ]
},
  "bbox": [],
  "geometry": {"coordinates":[58.2167,51.8667],"type":"Point"}
}