<<<<<<< HEAD
{
  "id": 7366036,
  "type": "Feature",
  "properties": {
    "tgn:hierarchy":[
        "tgn:7366036",
        "tgn:1000001",
        "tgn:7005597",
        "tgn:7005560",
        "tgn:7029392"
    ],
    "tgn:id":7366036,
    "tgn:name":"El Tej\u00f3n",
    "tgn:placetype":[
        "aat:300008347"
    ]
},
  "bbox": [],
  "geometry": {"coordinates":[-98.033333,25.066667],"type":"Point"}
}
=======
{"geometry":{"type":"Point","coordinates":[-98.033333,25.066667]},"type":"Feature","properties":{"hierarchy":["tgn:7366036","tgn:1000001","tgn:7005597","tgn:7005560","tgn:7029392"],"placetype":["aat:300008347"],"id":7366036,"name:xx":"El Tej\u00f3n"}}
>>>>>>> 03f74aca74312dbeaf24d7e61306dd6a786dc3d0
