{
  "id": 7536997,
  "type": "Feature",
  "properties": {
    "tgn:hierarchy":[
        "tgn:7536997",
        "tgn:7001242",
        "tgn:7016833",
        "tgn:1001113",
        "tgn:7029392"
    ],
    "tgn:id":7536997,
    "tgn:name":"Kafr Dimy\u0101n",
    "tgn:placetype":[
        "aat:300008347"
    ]
},
  "bbox": [],
  "geometry": {"coordinates":[31.512957,30.692509],"type":"Point"}
}