{
  "id": 7217620,
  "type": "Feature",
  "properties": {
    "tgn:hierarchy":[
        "tgn:7217620",
        "tgn:7011164",
        "tgn:7002674",
        "tgn:1000003",
        "tgn:1000074",
        "tgn:7029392"
    ],
    "tgn:id":7217620,
    "tgn:name":"Kl\u00edma, \u00d3rmos",
    "tgn:placetype":[
        "aat:300185707"
    ]
},
  "bbox": [],
  "geometry": {"coordinates":[26.600556,37.678333],"type":"Point"}
}