{
  "id": 2709112,
  "type": "Feature",
  "properties": {
    "tgn:hierarchy":[
        "tgn:2709112",
        "tgn:2000090",
        "tgn:1000001",
        "tgn:7006451",
        "tgn:7012149",
        "tgn:7029392"
    ],
    "tgn:id":2709112,
    "tgn:name":"Tabahinez Mesa",
    "tgn:placetype":[
        "aat:300008798"
    ]
},
  "bbox": [],
  "geometry": {"coordinates":[-109.8833,36.0667],"type":"Point"}
}