{
  "id": 2360568,
  "type": "Feature",
  "properties": {
    "tgn:hierarchy":[
        "tgn:2360568",
        "tgn:1000001",
        "tgn:7012149",
        "tgn:2002188",
        "tgn:7007919",
        "tgn:7029392"
    ],
    "tgn:id":2360568,
    "tgn:name":"Grassy Creek",
    "tgn:placetype":[
        "aat:300008347"
    ]
},
  "bbox": [],
  "geometry": {"coordinates":[-82.3333,36.7667],"type":"Point"}
}