{
  "id": 2376738,
  "type": "Feature",
  "properties": {
    "tgn:hierarchy":[
        "tgn:2376738",
        "tgn:1000001",
        "tgn:7012149",
        "tgn:2001110",
        "tgn:7007522",
        "tgn:7029392"
    ],
    "tgn:id":2376738,
    "tgn:name":"Hardy Creek",
    "tgn:placetype":[
        "aat:300008706"
    ]
},
  "bbox": [],
  "geometry": {"coordinates":[-90.25,32.2833],"type":"Point"}
}