{
  "id": 7410677,
  "type": "Feature",
  "properties": {
    "tgn:hierarchy":[
        "tgn:7410677",
        "tgn:7005580",
        "tgn:1000001",
        "tgn:7005560",
        "tgn:7029392"
    ],
    "tgn:id":7410677,
    "tgn:name":"La L\u00ednea",
    "tgn:placetype":[
        "aat:300008347"
    ]
},
  "bbox": [],
  "geometry": {"coordinates":[-94.033333,16.133333],"type":"Point"}
}