{
  "id": 7218843,
  "type": "Feature",
  "properties": {
    "tgn:hierarchy":[
        "tgn:7218843",
        "tgn:7011161",
        "tgn:7002674",
        "tgn:1000003",
        "tgn:1000074",
        "tgn:7029392"
    ],
    "tgn:id":7218843,
    "tgn:name":"Katr\u00e1ris R\u00e9ma",
    "tgn:placetype":[
        "aat:300008699"
    ]
},
  "bbox": [],
  "geometry": {"coordinates":[26.036667,38.204722],"type":"Point"}
}