{
  "id": 2245519,
  "type": "Feature",
  "properties": {
    "tgn:hierarchy":[
        "tgn:2245519",
        "tgn:1000001",
        "tgn:7012149",
        "tgn:7029392"
    ],
    "tgn:id":2245519,
    "tgn:name":"Coahulla Creek",
    "tgn:placetype":[
        "aat:300008706"
    ]
},
  "bbox": [],
  "geometry": {"coordinates":[-84.85,35.1333],"type":"Point"}
}