{
  "id": 7366414,
  "type": "Feature",
  "properties": {
    "tgn:hierarchy":[
        "tgn:7366414",
        "tgn:1000001",
        "tgn:1001906",
        "tgn:7005560",
        "tgn:7029392"
    ],
    "tgn:id":7366414,
    "tgn:name":"El Resbal\u00f3n",
    "tgn:placetype":[
        "aat:300008347"
    ]
},
  "bbox": [],
  "geometry": {"coordinates":[-105.300278,22.398889],"type":"Point"}
}