{
  "id": 1122680,
  "type": "Feature",
  "properties": {
    "tgn:hierarchy":[
        "tgn:1122680",
        "tgn:1000004",
        "tgn:7029392"
    ],
    "tgn:id":1122680,
    "tgn:name":"Chang Chenmo",
    "tgn:placetype":[
        "aat:300008707"
    ]
},
  "bbox": [],
  "geometry": {"coordinates":[78.3167,34.2833],"type":"Point"}
}