{
  "id": 2694500,
  "type": "Feature",
  "properties": {
    "tgn:hierarchy":[
        "tgn:2694500",
        "tgn:1000001",
        "tgn:7012149",
        "tgn:7007523",
        "tgn:7029392"
    ],
    "tgn:id":2694500,
    "tgn:name":"Stewart Creek",
    "tgn:placetype":[
        "aat:300008706"
    ]
},
  "bbox": [],
  "geometry": {"coordinates":[-92.8333,37.05],"type":"Point"}
}