{
  "id": 2775982,
  "type": "Feature",
  "properties": {
    "tgn:hierarchy":[
        "tgn:2775982",
        "tgn:1000001",
        "tgn:1002359",
        "tgn:7012149",
        "tgn:7007517",
        "tgn:7029392"
    ],
    "tgn:id":2775982,
    "tgn:name":"Wilson Pond",
    "tgn:placetype":[
        "aat:300008680"
    ]
},
  "bbox": [],
  "geometry": {"coordinates":[-70.9333,42.6833],"type":"Point"}
}