{
  "id": 2756143,
  "type": "Feature",
  "properties": {
    "tgn:hierarchy":[
        "tgn:2756143",
        "tgn:7002659",
        "tgn:1000001",
        "tgn:7012149",
        "tgn:2000023",
        "tgn:7029392"
    ],
    "tgn:id":2756143,
    "tgn:name":"Weissinger Lakes",
    "tgn:placetype":[
        "aat:300006191"
    ]
},
  "bbox": [],
  "geometry": {"coordinates":[-87.3333,32.3833],"type":"Point"}
}