<<<<<<< HEAD
{
  "id": 2765279,
  "type": "Feature",
  "properties": {
    "tgn:hierarchy":[
        "tgn:2765279",
        "tgn:1000001",
        "tgn:7012149",
        "tgn:7007157",
        "tgn:1002608",
        "tgn:7029392"
    ],
    "tgn:id":2765279,
    "tgn:name":"Whitaker Peak",
    "tgn:placetype":[
        "aat:300008798"
    ]
},
  "bbox": [],
  "geometry": {"coordinates":[-118.7333,34.5667],"type":"Point"}
}
=======
{"geometry":{"type":"Point","coordinates":[-118.733300,34.566700]},"type":"Feature","properties":{"hierarchy":["tgn:2765279","tgn:1000001","tgn:7012149","tgn:7007157","tgn:1002608","tgn:7029392"],"placetype":["aat:300008798"],"id":2765279,"name:xx":"Whitaker Peak"}}
>>>>>>> 03f74aca74312dbeaf24d7e61306dd6a786dc3d0
