{
  "id": 7266221,
  "type": "Feature",
  "properties": {
    "tgn:concordances":{
        "gn:id":"2754632"
    },
    "tgn:hierarchy":[
        "tgn:7266221",
        "tgn:7003619",
        "tgn:1000003",
        "tgn:7016845",
        "tgn:7029392"
    ],
    "tgn:id":7266221,
    "tgn:name:nl":"Heesselt",
    "tgn:placetype":[
        "aat:300008347"
    ]
},
  "bbox": [],
  "geometry": {"coordinates":[5.35,51.816667],"type":"Point"}
}