{
  "id": 2581402,
  "type": "Feature",
  "properties": {
    "tgn:hierarchy":[
        "tgn:2581402",
        "tgn:1000001",
        "tgn:2000952",
        "tgn:7012149",
        "tgn:7007520",
        "tgn:7029392"
    ],
    "tgn:id":2581402,
    "tgn:name":"Pilot Island",
    "tgn:placetype":[
        "aat:300008791"
    ]
},
  "bbox": [],
  "geometry": {"coordinates":[-84.1333,46.1667],"type":"Point"}
}