{
  "id": 7570713,
  "type": "Feature",
  "properties": {
    "tgn:hierarchy":[
        "tgn:7570713",
        "tgn:1000004",
        "tgn:7000198",
        "tgn:1001996",
        "tgn:7029392"
    ],
    "tgn:id":7570713,
    "tgn:name:en":"Ghanala",
    "tgn:placetype":[
        "aat:300008347"
    ]
},
  "bbox": [],
  "geometry": {"coordinates":[76.641825,31.867347],"type":"Point"}
}