{
  "id": 7311035,
  "type": "Feature",
  "properties": {
    "tgn:hierarchy":[
        "tgn:7311035",
        "tgn:7016598",
        "tgn:1000049",
        "tgn:1000002",
        "tgn:7029392"
    ],
    "tgn:id":7311035,
    "tgn:name":"Oficina Prosperidad",
    "tgn:placetype":[
        "aat:300000517"
    ]
},
  "bbox": [],
  "geometry": {"coordinates":[-69.616667,-21.966667],"type":"Point"}
}