<<<<<<< HEAD
{
  "id": 2258042,
  "type": "Feature",
  "properties": {
    "tgn:hierarchy":[
        "tgn:2258042",
        "tgn:1000001",
        "tgn:7012149",
        "tgn:2000973",
        "tgn:7007520",
        "tgn:7029392"
    ],
    "tgn:id":2258042,
    "tgn:name":"Coryell Island",
    "tgn:placetype":[
        "aat:300008791"
    ]
},
  "bbox": [],
  "geometry": {"coordinates":[-84.2833,45.95],"type":"Point"}
}
=======
{"geometry":{"type":"Point","coordinates":[-84.283300,45.950000]},"type":"Feature","properties":{"hierarchy":["tgn:2258042","tgn:1000001","tgn:7012149","tgn:2000973","tgn:7007520","tgn:7029392"],"placetype":["aat:300008791"],"id":2258042,"name:xx":"Coryell Island"}}
>>>>>>> 03f74aca74312dbeaf24d7e61306dd6a786dc3d0
