{
  "id": 2466232,
  "type": "Feature",
  "properties": {
    "tgn:hierarchy":[
        "tgn:2466232",
        "tgn:1000001",
        "tgn:7006451",
        "tgn:2000092",
        "tgn:7012149",
        "tgn:7029392"
    ],
    "tgn:id":2466232,
    "tgn:name":"Lonesome Tank",
    "tgn:placetype":[
        "aat:300006191"
    ]
},
  "bbox": [],
  "geometry": {"coordinates":[-110.8333,34.2833],"type":"Point"}
}