{
  "id": 2644742,
  "type": "Feature",
  "properties": {
    "tgn:hierarchy":[
        "tgn:2644742",
        "tgn:1000001",
        "tgn:7012149",
        "tgn:7014612",
        "tgn:7007568",
        "tgn:7029392"
    ],
    "tgn:id":2644742,
    "tgn:name":"Sarles Hill",
    "tgn:placetype":[
        "aat:300008798"
    ]
},
  "bbox": [],
  "geometry": {"coordinates":[-73.7833,41.1333],"type":"Point"}
}