{
  "id": 7203472,
  "type": "Feature",
  "properties": {
    "tgn:hierarchy":[
        "tgn:7203472",
        "tgn:1000003",
        "tgn:7003676",
        "tgn:7000084",
        "tgn:7029392"
    ],
    "tgn:id":7203472,
    "tgn:name":"Bosserbruch",
    "tgn:placetype":[
        "aat:300008863"
    ]
},
  "bbox": [],
  "geometry": {"coordinates":[9.416667,52.733333],"type":"Point"}
}