{
  "id": 7263309,
  "type": "Feature",
  "properties": {
    "tgn:hierarchy":[
        "tgn:7263309",
        "tgn:7003615",
        "tgn:1000003",
        "tgn:7016845",
        "tgn:7029392"
    ],
    "tgn:id":7263309,
    "tgn:name:nl":"Ellertocht",
    "tgn:placetype":[
        "aat:300006075"
    ]
},
  "bbox": [],
  "geometry": {"coordinates":[5.816667,52.483333],"type":"Point"}
}