{
  "id": 7031129,
  "type": "Feature",
  "properties": {
    "tgn:hierarchy":[
        "tgn:7031129",
        "tgn:7002445",
        "tgn:1000003",
        "tgn:7008167",
        "tgn:7008591",
        "tgn:7029392"
    ],
    "tgn:id":7031129,
    "tgn:name:en":"Ossington",
    "tgn:placetype":[
        "aat:300008347",
        "aat:300008372"
    ]
},
  "bbox": [],
  "geometry": {"coordinates":[-0.866667,53.166667],"type":"Point"}
}