{
  "id": 7539250,
  "type": "Feature",
  "properties": {
    "tgn:hierarchy":[
        "tgn:7539250",
        "tgn:7001242",
        "tgn:7016833",
        "tgn:7001336",
        "tgn:7029392"
    ],
    "tgn:id":7539250,
    "tgn:name:en":"Mayyah, Sharm al",
    "tgn:placetype":[
        "aat:300132316"
    ]
},
  "bbox": [],
  "geometry": {"coordinates":[34.295736,27.85643],"type":"Point"}
}