{
  "id": 1032663,
  "type": "Feature",
  "properties": {
    "tgn:hierarchy":[
        "tgn:1032663",
        "tgn:1000003",
        "tgn:7002880",
        "tgn:1000070",
        "tgn:7029392"
    ],
    "tgn:id":1032663,
    "tgn:name":"Chevillon",
    "tgn:placetype":[
        "aat:300008347"
    ]
},
  "bbox": [],
  "geometry": {"coordinates":[5.1333,48.5333],"type":"Point"}
}