{
  "id": 7000436,
  "type": "Feature",
  "properties": {
    "tgn:hierarchy":[
        "tgn:7000436",
        "tgn:7001242",
        "tgn:1001774",
        "tgn:1000192",
        "tgn:7029392"
    ],
    "tgn:id":7000436,
    "tgn:name":"Berbera",
    "tgn:placetype":[
        "aat:300008347",
        "aat:300387219",
        "aat:300008375",
        "aat:300120599"
    ]
},
  "bbox": [],
  "geometry": {"coordinates":[45.0333,10.4667],"type":"Point"}
}