{
  "id": 7534893,
  "type": "Feature",
  "properties": {
    "tgn:hierarchy":[
        "tgn:7534893",
        "tgn:7001242",
        "tgn:7016833",
        "tgn:1001087",
        "tgn:7029392"
    ],
    "tgn:id":7534893,
    "tgn:name":"Kafr Absh\u012bsh",
    "tgn:placetype":[
        "aat:300008347"
    ]
},
  "bbox": [],
  "geometry": {"coordinates":[31.088916,30.485853],"type":"Point"}
}