{
  "id": 2148806,
  "type": "Feature",
  "properties": {
    "tgn:hierarchy":[
        "tgn:2148806",
        "tgn:2001732",
        "tgn:1000001",
        "tgn:7012149",
        "tgn:7007712",
        "tgn:7029392"
    ],
    "tgn:id":2148806,
    "tgn:name":"Barnett Island",
    "tgn:placetype":[
        "aat:300008791"
    ]
},
  "bbox": [],
  "geometry": {"coordinates":[-79.6833,33.1833],"type":"Point"}
}