{
  "id": 7287459,
  "type": "Feature",
  "properties": {
    "tgn:hierarchy":[
        "tgn:7287459",
        "tgn:1001702",
        "tgn:1000049",
        "tgn:1000002",
        "tgn:7029392"
    ],
    "tgn:id":7287459,
    "tgn:name":"Goose, Isla",
    "tgn:placetype":[
        "aat:300008791"
    ]
},
  "bbox": [],
  "geometry": {"coordinates":[-69.816667,-55.333333],"type":"Point"}
}