{
  "id": 2785557,
  "type": "Feature",
  "properties": {
    "tgn:hierarchy":[
        "tgn:2785557",
        "tgn:1000001",
        "tgn:2001702",
        "tgn:7012149",
        "tgn:7007708",
        "tgn:7029392"
    ],
    "tgn:id":2785557,
    "tgn:name":"Yoakam Hill",
    "tgn:placetype":[
        "aat:300008798"
    ]
},
  "bbox": [],
  "geometry": {"coordinates":[-124.2667,43.3167],"type":"Point"}
}