{
  "id": 7527913,
  "type": "Feature",
  "properties": {
    "tgn:hierarchy":[
        "tgn:7527913",
        "tgn:7001242",
        "tgn:7016833",
        "tgn:1001113",
        "tgn:7029392"
    ],
    "tgn:id":7527913,
    "tgn:name":"Umm '\u0100mir, Jaz\u012brat",
    "tgn:placetype":[
        "aat:300008791"
    ]
},
  "bbox": [],
  "geometry": {"coordinates":[31.666667,30.433333],"type":"Point"}
}