{
  "id": 7272891,
  "type": "Feature",
  "properties": {
    "tgn:concordances":{
        "gn:id":"2745146"
    },
    "tgn:hierarchy":[
        "tgn:7272891",
        "tgn:7003614",
        "tgn:1000003",
        "tgn:7016845",
        "tgn:7029392"
    ],
    "tgn:id":7272891,
    "tgn:name:nl":"Vuile Riete",
    "tgn:placetype":[
        "aat:300008347"
    ]
},
  "bbox": [],
  "geometry": {"coordinates":[6.483333,52.633333],"type":"Point"}
}