{
  "id": 2263439,
  "type": "Feature",
  "properties": {
    "tgn:hierarchy":[
        "tgn:2263439",
        "tgn:1000001",
        "tgn:7012149",
        "tgn:2002164",
        "tgn:7007919",
        "tgn:7029392"
    ],
    "tgn:id":2263439,
    "tgn:name":"Cox Mill",
    "tgn:placetype":[
        "aat:300008347"
    ]
},
  "bbox": [],
  "geometry": {"coordinates":[-80.8833,36.6167],"type":"Point"}
}