{
  "id": 1010534,
  "type": "Feature",
  "properties": {
    "tgn:hierarchy":[
        "tgn:1010534",
        "tgn:1008380",
        "tgn:7000507",
        "tgn:1000226",
        "tgn:1000006",
        "tgn:7029392"
    ],
    "tgn:id":1010534,
    "tgn:name:en":"Brett, Cape",
    "tgn:placetype":[
        "aat:300008850"
    ]
},
  "bbox": [],
  "geometry": {"coordinates":[174.333333,-35.166667],"type":"Point"}
}