<<<<<<< HEAD
{
  "id": 2338569,
  "type": "Feature",
  "properties": {
    "tgn:hierarchy":[
        "tgn:2338569",
        "tgn:1000001",
        "tgn:7012149",
        "tgn:2002374",
        "tgn:7007923",
        "tgn:7029392"
    ],
    "tgn:id":2338569,
    "tgn:name":"Frances Ditch",
    "tgn:placetype":[
        "aat:300006075"
    ]
},
  "bbox": [],
  "geometry": {"coordinates":[-106.85,43.8667],"type":"Point"}
}
=======
{"geometry":{"type":"Point","coordinates":[-106.850000,43.866700]},"type":"Feature","properties":{"hierarchy":["tgn:2338569","tgn:1000001","tgn:7012149","tgn:2002374","tgn:7007923","tgn:7029392"],"placetype":["aat:300006075"],"id":2338569,"name:xx":"Frances Ditch"}}
>>>>>>> 03f74aca74312dbeaf24d7e61306dd6a786dc3d0
