{
  "id": 7572477,
  "type": "Feature",
  "properties": {
    "tgn:hierarchy":[
        "tgn:7572477",
        "tgn:1000004",
        "tgn:7000198",
        "tgn:7016788",
        "tgn:7029392"
    ],
    "tgn:id":7572477,
    "tgn:name:en":"Jhir",
    "tgn:placetype":[
        "aat:300007783"
    ]
},
  "bbox": [],
  "geometry": {"coordinates":[76.115583,26.852296],"type":"Point"}
}