{
  "id": 2719973,
  "type": "Feature",
  "properties": {
    "tgn:hierarchy":[
        "tgn:2719973",
        "tgn:1000001",
        "tgn:7016172",
        "tgn:7012149",
        "tgn:2000164",
        "tgn:7029392"
    ],
    "tgn:id":2719973,
    "tgn:name":"Three, Lake Number",
    "tgn:placetype":[
        "aat:300006191"
    ]
},
  "bbox": [],
  "geometry": {"coordinates":[-92.2333,34.7833],"type":"Point"}
}