{
  "id": 7208331,
  "type": "Feature",
  "properties": {
    "tgn:hierarchy":[
        "tgn:7208331",
        "tgn:7003692",
        "tgn:1000003",
        "tgn:7000084",
        "tgn:7029392"
    ],
    "tgn:id":7208331,
    "tgn:name":"Bahnh\u00f6fle",
    "tgn:placetype":[
        "aat:300387200"
    ]
},
  "bbox": [],
  "geometry": {"coordinates":[9.566667,48.55],"type":"Point"}
}