{
  "id": 1122070,
  "type": "Feature",
  "properties": {
    "tgn:hierarchy":[
        "tgn:1122070",
        "tgn:1000003",
        "tgn:7029392"
    ],
    "tgn:id":1122070,
    "tgn:name":"Velyka Kam-yanka",
    "tgn:placetype":[
        "aat:300008707"
    ]
},
  "bbox": [],
  "geometry": {"coordinates":[40.0333,48.35],"type":"Point"}
}