{
  "id": 2134422,
  "type": "Feature",
  "properties": {
    "tgn:hierarchy":[
        "tgn:2134422",
        "tgn:1000001",
        "tgn:7012149",
        "tgn:2002010",
        "tgn:7007826",
        "tgn:7029392"
    ],
    "tgn:id":2134422,
    "tgn:name":"Annie, Mount",
    "tgn:placetype":[
        "aat:300008798"
    ]
},
  "bbox": [],
  "geometry": {"coordinates":[-103.9833,30.8667],"type":"Point"}
}