{
  "id": 7218544,
  "type": "Feature",
  "properties": {
    "tgn:hierarchy":[
        "tgn:7218544",
        "tgn:7011171",
        "tgn:7001395",
        "tgn:1000003",
        "tgn:1000074",
        "tgn:7029392"
    ],
    "tgn:id":7218544,
    "tgn:name":"Agno\u00fa, Orm\u00edskos",
    "tgn:placetype":[
        "aat:300185707"
    ]
},
  "bbox": [],
  "geometry": {"coordinates":[24.549167,38.776667],"type":"Point"}
}