<<<<<<< HEAD
{
  "id": 7375249,
  "type": "Feature",
  "properties": {
    "tgn:hierarchy":[
        "tgn:7375249",
        "tgn:1000001",
        "tgn:1001960",
        "tgn:7005560",
        "tgn:7029392"
    ],
    "tgn:id":7375249,
    "tgn:name":"Rancho Las Pulgas",
    "tgn:placetype":[
        "aat:300000241"
    ]
},
  "bbox": [],
  "geometry": {"coordinates":[-108.6,30.15],"type":"Point"}
}
=======
{"geometry":{"type":"Point","coordinates":[-108.600000,30.150000]},"type":"Feature","properties":{"hierarchy":["tgn:7375249","tgn:1000001","tgn:1001960","tgn:7005560","tgn:7029392"],"placetype":["aat:300000241"],"id":7375249,"name:xx":"Rancho Las Pulgas"}}
>>>>>>> 03f74aca74312dbeaf24d7e61306dd6a786dc3d0
