{
  "id": 2249237,
  "type": "Feature",
  "properties": {
    "tgn:hierarchy":[
        "tgn:2249237",
        "tgn:1000001",
        "tgn:7012149",
        "tgn:2000996",
        "tgn:7007520",
        "tgn:7029392"
    ],
    "tgn:id":2249237,
    "tgn:name":"Cole Point",
    "tgn:placetype":[
        "aat:300008850"
    ]
},
  "bbox": [],
  "geometry": {"coordinates":[-86.3833,45.7833],"type":"Point"}
}