{
  "id": 2589546,
  "type": "Feature",
  "properties": {
    "tgn:hierarchy":[
        "tgn:2589546",
        "tgn:7006450",
        "tgn:1000001",
        "tgn:7012149",
        "tgn:7019760",
        "tgn:7029392"
    ],
    "tgn:id":2589546,
    "tgn:name":"League, Point",
    "tgn:placetype":[
        "aat:300008850"
    ]
},
  "bbox": [],
  "geometry": {"coordinates":[-133.6667,57.6167],"type":"Point"}
}