{
  "id": 2292237,
  "type": "Feature",
  "properties": {
    "tgn:hierarchy":[
        "tgn:2292237",
        "tgn:1000001",
        "tgn:7012149",
        "tgn:7007157",
        "tgn:2000186",
        "tgn:7029392"
    ],
    "tgn:id":2292237,
    "tgn:name":"Donica Mountain",
    "tgn:placetype":[
        "aat:300008798"
    ]
},
  "bbox": [],
  "geometry": {"coordinates":[-121.15,41.3167],"type":"Point"}
}