{
  "id": 7020976,
  "type": "Feature",
  "properties": {
    "tgn:hierarchy":[
        "tgn:7020976",
        "tgn:1000001",
        "tgn:7012149",
        "tgn:2000488",
        "tgn:7007250",
        "tgn:7029392"
    ],
    "tgn:id":7020976,
    "tgn:name":"Twin Springs",
    "tgn:placetype":[
        "aat:300008697"
    ]
},
  "bbox": [],
  "geometry": {"coordinates":[-114.6333,42.0333],"type":"Point"}
}