{
  "id": 2675452,
  "type": "Feature",
  "properties": {
    "tgn:hierarchy":[
        "tgn:2675452",
        "tgn:1000001",
        "tgn:1002213",
        "tgn:7012149",
        "tgn:7007710",
        "tgn:7029392"
    ],
    "tgn:id":2675452,
    "tgn:name":"Solebury Mountain",
    "tgn:placetype":[
        "aat:300008798"
    ]
},
  "bbox": [],
  "geometry": {"coordinates":[-74.9667,40.3333],"type":"Point"}
}