{
  "id": 7342841,
  "type": "Feature",
  "properties": {
    "tgn:hierarchy":[
        "tgn:7342841",
        "tgn:7008911",
        "tgn:1000003",
        "tgn:7002763",
        "tgn:1000095",
        "tgn:7029392"
    ],
    "tgn:id":7342841,
    "tgn:name":"Cardes",
    "tgn:placetype":[
        "aat:300008347"
    ]
},
  "bbox": [],
  "geometry": {"coordinates":[-5.333333,43.333333],"type":"Point"}
}