{
  "id": 1098197,
  "type": "Feature",
  "properties": {
    "tgn:hierarchy":[
        "tgn:1098197",
        "tgn:7000490",
        "tgn:1000006",
        "tgn:7001830",
        "tgn:7029392"
    ],
    "tgn:id":1098197,
    "tgn:name":"Southbrook",
    "tgn:placetype":[
        "aat:300008347"
    ]
},
  "bbox": [],
  "geometry": {"coordinates":[151.7167,-27.6833],"type":"Point"}
}