{
  "id": 2697665,
  "type": "Feature",
  "properties": {
    "tgn:hierarchy":[
        "tgn:2697665",
        "tgn:1000001",
        "tgn:7012149",
        "tgn:1002439",
        "tgn:7007252",
        "tgn:7029392"
    ],
    "tgn:id":2697665,
    "tgn:name":"Stop Branch",
    "tgn:placetype":[
        "aat:300008699"
    ]
},
  "bbox": [],
  "geometry": {"coordinates":[-85.9167,39.9833],"type":"Point"}
}