{
  "id": 2532097,
  "type": "Feature",
  "properties": {
    "tgn:hierarchy":[
        "tgn:2532097",
        "tgn:1000001",
        "tgn:7020680",
        "tgn:7012149",
        "tgn:7007256",
        "tgn:7029392"
    ],
    "tgn:id":2532097,
    "tgn:name":"Mundy Bayou",
    "tgn:placetype":[
        "aat:300008699"
    ]
},
  "bbox": [],
  "geometry": {"coordinates":[-93.5667,32.0333],"type":"Point"}
}