<<<<<<< HEAD
{
  "id": 2407118,
  "type": "Feature",
  "properties": {
    "tgn:hierarchy":[
        "tgn:2407118",
        "tgn:1000001",
        "tgn:7012149",
        "tgn:7007568",
        "tgn:7029392"
    ],
    "tgn:id":2407118,
    "tgn:name":"Hunters Creek",
    "tgn:placetype":[
        "aat:300008706"
    ]
},
  "bbox": [],
  "geometry": {"coordinates":[-74.15,36.2667],"type":"Point"}
}
=======
{"geometry":{"type":"Point","coordinates":[-74.150000,36.266700]},"type":"Feature","properties":{"hierarchy":["tgn:2407118","tgn:1000001","tgn:7012149","tgn:7007568","tgn:7029392"],"placetype":["aat:300008706"],"id":2407118,"name:xx":"Hunters Creek"}}
>>>>>>> 03f74aca74312dbeaf24d7e61306dd6a786dc3d0
