{
  "id": 2407118,
  "type": "Feature",
  "properties": {
    "tgn:hierarchy":[
        "tgn:2407118",
        "tgn:1000001",
        "tgn:7012149",
        "tgn:7007568",
        "tgn:7029392"
    ],
    "tgn:id":2407118,
    "tgn:name":"Hunters Creek",
    "tgn:placetype":[
        "aat:300008706"
    ]
},
  "bbox": [],
  "geometry": {"coordinates":[-74.15,36.2667],"type":"Point"}
}