{
  "id": 2282180,
  "type": "Feature",
  "properties": {
    "tgn:hierarchy":[
        "tgn:2282180",
        "tgn:1000001",
        "tgn:2002107",
        "tgn:7012149",
        "tgn:7007827",
        "tgn:7029392"
    ],
    "tgn:id":2282180,
    "tgn:name":"Deer Lake",
    "tgn:placetype":[
        "aat:300006191"
    ]
},
  "bbox": [],
  "geometry": {"coordinates":[-110.35,40.6667],"type":"Point"}
}