{
  "id": 7325116,
  "type": "Feature",
  "properties": {
    "tgn:hierarchy":[
        "tgn:7325116",
        "tgn:7002760",
        "tgn:1000003",
        "tgn:1000095",
        "tgn:7029392"
    ],
    "tgn:id":7325116,
    "tgn:name":"San Vicente de la Barquera, R\u00eda de",
    "tgn:placetype":[
        "aat:300266571"
    ]
},
  "bbox": [],
  "geometry": {"coordinates":[-4.383333,43.383333],"type":"Point"}
}