{
  "id": 7587881,
  "type": "Feature",
  "properties": {
    "tgn:hierarchy":[
        "tgn:7587881",
        "tgn:1000004",
        "tgn:7000198",
        "tgn:7000799",
        "tgn:7029392"
    ],
    "tgn:id":7587881,
    "tgn:name:en":"Manganw\u0101r",
    "tgn:placetype":[
        "aat:300008347"
    ]
},
  "bbox": [],
  "geometry": {"coordinates":[74.832907,34.010065],"type":"Point"}
}