{
  "id": 1093110,
  "type": "Feature",
  "properties": {
    "tgn:hierarchy":[
        "tgn:1093110",
        "tgn:7001242",
        "tgn:7017584",
        "tgn:1000193",
        "tgn:7029392"
    ],
    "tgn:id":1093110,
    "tgn:name":"Graafwater",
    "tgn:placetype":[
        "aat:300008347"
    ]
},
  "bbox": [],
  "geometry": {"coordinates":[18.5333,-32.1333],"type":"Point"}
}