{
  "id": 2496860,
  "type": "Feature",
  "properties": {
    "tgn:hierarchy":[
        "tgn:2496860",
        "tgn:1000001",
        "tgn:7012149",
        "tgn:2002047",
        "tgn:7007826",
        "tgn:7029392"
    ],
    "tgn:id":2496860,
    "tgn:name":"Mattox",
    "tgn:placetype":[
        "aat:300008347"
    ]
},
  "bbox": [],
  "geometry": {"coordinates":[-93.7667,30.9833],"type":"Point"}
}