{
  "id": 7550825,
  "type": "Feature",
  "properties": {
    "tgn:hierarchy":[
        "tgn:7550825",
        "tgn:1000004",
        "tgn:7000198",
        "tgn:7016694",
        "tgn:7029392"
    ],
    "tgn:id":7550825,
    "tgn:name:en":"Digapahandi",
    "tgn:placetype":[
        "aat:300008347"
    ]
},
  "bbox": [],
  "geometry": {"coordinates":[84.583333,19.366667],"type":"Point"}
}