{
  "id": 2369066,
  "type": "Feature",
  "properties": {
    "tgn:hierarchy":[
        "tgn:2369066",
        "tgn:1002933",
        "tgn:1000001",
        "tgn:7012149",
        "tgn:7007239",
        "tgn:7029392"
    ],
    "tgn:id":2369066,
    "tgn:name":"Gum Crossroads",
    "tgn:placetype":[
        "aat:300008347"
    ]
},
  "bbox": [],
  "geometry": {"coordinates":[-75.4667,38.65],"type":"Point"}
}