{
  "id": 2667519,
  "type": "Feature",
  "properties": {
    "tgn:hierarchy":[
        "tgn:2667519",
        "tgn:7006450",
        "tgn:1000001",
        "tgn:7019698",
        "tgn:7012149",
        "tgn:7029392"
    ],
    "tgn:id":2667519,
    "tgn:name":"Skookum Glacier",
    "tgn:placetype":[
        "aat:300008835"
    ]
},
  "bbox": [],
  "geometry": {"coordinates":[-148.8833,60.7167],"type":"Point"}
}