{
  "id": 2673829,
  "type": "Feature",
  "properties": {
    "tgn:hierarchy":[
        "tgn:2673829",
        "tgn:7006450",
        "tgn:1000001",
        "tgn:7012149",
        "tgn:2000079",
        "tgn:7029392"
    ],
    "tgn:id":2673829,
    "tgn:name":"Snow Gulch",
    "tgn:placetype":[
        "aat:300008761"
    ]
},
  "bbox": [],
  "geometry": {"coordinates":[-165.3833,64.5833],"type":"Point"}
}