{
  "id": 7229826,
  "type": "Feature",
  "properties": {
    "tgn:hierarchy":[
        "tgn:7229826",
        "tgn:4003963",
        "tgn:7001395",
        "tgn:1000003",
        "tgn:1000074",
        "tgn:7029392"
    ],
    "tgn:id":7229826,
    "tgn:name":"Khris\u00f3n",
    "tgn:placetype":[
        "aat:300008347"
    ]
},
  "bbox": [],
  "geometry": {"coordinates":[22.466667,38.466667],"type":"Point"}
}