{
  "id": 1108309,
  "type": "Feature",
  "properties": {
    "tgn:hierarchy":[
        "tgn:1108309",
        "tgn:1000004",
        "tgn:7012212",
        "tgn:7006655",
        "tgn:7029392"
    ],
    "tgn:id":1108309,
    "tgn:name":"\u010cijir\u010dik, pereval",
    "tgn:placetype":[
        "aat:300259572"
    ]
},
  "bbox": [],
  "geometry": {"coordinates":[73.3333,40.25],"type":"Point"}
}