{
  "id": 2665171,
  "type": "Feature",
  "properties": {
    "tgn:hierarchy":[
        "tgn:2665171",
        "tgn:1000001",
        "tgn:7012149",
        "tgn:2001111",
        "tgn:7007522",
        "tgn:7029392"
    ],
    "tgn:id":2665171,
    "tgn:name":"Sims Lake",
    "tgn:placetype":[
        "aat:300008680"
    ]
},
  "bbox": [],
  "geometry": {"coordinates":[-89.8333,33.05],"type":"Point"}
}