{
  "id": 2742824,
  "type": "Feature",
  "properties": {
    "tgn:hierarchy":[
        "tgn:2742824",
        "tgn:1000001",
        "tgn:7012149",
        "tgn:2000493",
        "tgn:7007250",
        "tgn:7029392"
    ],
    "tgn:id":2742824,
    "tgn:name":"Van Eaton Spring",
    "tgn:placetype":[
        "aat:300008697"
    ]
},
  "bbox": [],
  "geometry": {"coordinates":[-114.35,42.1167],"type":"Point"}
}