{
  "id": 2374594,
  "type": "Feature",
  "properties": {
    "tgn:hierarchy":[
        "tgn:2374594",
        "tgn:1000001",
        "tgn:2001945",
        "tgn:7012149",
        "tgn:7007826",
        "tgn:7029392"
    ],
    "tgn:id":2374594,
    "tgn:name":"Hancock Hill",
    "tgn:placetype":[
        "aat:300008798"
    ]
},
  "bbox": [],
  "geometry": {"coordinates":[-103.6333,30.3667],"type":"Point"}
}