{
  "id": 7279172,
  "type": "Feature",
  "properties": {
    "tgn:hierarchy":[
        "tgn:7279172",
        "tgn:7002464",
        "tgn:1000049",
        "tgn:1000002",
        "tgn:7029392"
    ],
    "tgn:id":7279172,
    "tgn:name":"Rosapata",
    "tgn:placetype":[
        "aat:300008347"
    ]
},
  "bbox": [],
  "geometry": {"coordinates":[-69.233333,-18.033333],"type":"Point"}
}