{
  "id": 1103867,
  "type": "Feature",
  "properties": {
    "tgn:hierarchy":[
        "tgn:1103867",
        "tgn:7005405",
        "tgn:1000001",
        "tgn:7005388",
        "tgn:7029392"
    ],
    "tgn:id":1103867,
    "tgn:name":"la Bandera, Alto de",
    "tgn:placetype":[
        "aat:300008795"
    ]
},
  "bbox": [],
  "geometry": {"coordinates":[-70.626,18.813],"type":"Point"}
}