<<<<<<< HEAD
{
  "id": 7117889,
  "type": "Feature",
  "properties": {
    "tgn:hierarchy":[
        "tgn:7117889",
        "tgn:7003692",
        "tgn:1000003",
        "tgn:7000084",
        "tgn:7029392"
    ],
    "tgn:id":7117889,
    "tgn:name":"Obersimonswald",
    "tgn:placetype":[
        "aat:300387173"
    ]
},
  "bbox": [],
  "geometry": {"coordinates":[8.1,48.066667],"type":"Point"}
}
=======
{"geometry":{"type":"Point","coordinates":[8.100000,48.066667]},"type":"Feature","properties":{"hierarchy":["tgn:7117889","tgn:7003692","tgn:1000003","tgn:7000084","tgn:7029392"],"placetype":["aat:300387173"],"id":7117889,"name:xx":"Obersimonswald"}}
>>>>>>> 03f74aca74312dbeaf24d7e61306dd6a786dc3d0
