{
  "id": 2558571,
  "type": "Feature",
  "properties": {
    "tgn:hierarchy":[
        "tgn:2558571",
        "tgn:1000001",
        "tgn:1002753",
        "tgn:7012149",
        "tgn:7007828",
        "tgn:7029392"
    ],
    "tgn:id":2558571,
    "tgn:name":"Oliver Hill",
    "tgn:placetype":[
        "aat:300008798"
    ]
},
  "bbox": [],
  "geometry": {"coordinates":[-72.0667,44.8833],"type":"Point"}
}