{
  "id": 2118399,
  "type": "Feature",
  "properties": {
    "tgn:hierarchy":[
        "tgn:2118399",
        "tgn:1000001",
        "tgn:7012149",
        "tgn:2002294",
        "tgn:7013961",
        "tgn:7029392"
    ],
    "tgn:id":2118399,
    "tgn:name":"Glenray",
    "tgn:placetype":[
        "aat:300008347"
    ]
},
  "bbox": [],
  "geometry": {"coordinates":[-80.6667,37.7167],"type":"Point"}
}