<<<<<<< HEAD
{
  "id": 2258675,
  "type": "Feature",
  "properties": {
    "tgn:hierarchy":[
        "tgn:2258675",
        "tgn:1000001",
        "tgn:7012149",
        "tgn:7007157",
        "tgn:1002857",
        "tgn:7029392"
    ],
    "tgn:id":2258675,
    "tgn:name":"Cottonwood Canyon",
    "tgn:placetype":[
        "aat:300008761"
    ]
},
  "bbox": [],
  "geometry": {"coordinates":[-115.3833,35.2167],"type":"Point"}
}
=======
{"geometry":{"type":"Point","coordinates":[-115.383300,35.216700]},"type":"Feature","properties":{"hierarchy":["tgn:2258675","tgn:1000001","tgn:7012149","tgn:7007157","tgn:1002857","tgn:7029392"],"placetype":["aat:300008761"],"id":2258675,"name:xx":"Cottonwood Canyon"}}
>>>>>>> 03f74aca74312dbeaf24d7e61306dd6a786dc3d0
