<<<<<<< HEAD
{
  "id": 2339155,
  "type": "Feature",
  "properties": {
    "tgn:hierarchy":[
        "tgn:2339155",
        "tgn:1000001",
        "tgn:7012149",
        "tgn:1002816",
        "tgn:7007826",
        "tgn:7029392"
    ],
    "tgn:id":2339155,
    "tgn:name":"Franks Creek",
    "tgn:placetype":[
        "aat:300008706"
    ]
},
  "bbox": [],
  "geometry": {"coordinates":[-95.7167,32.85],"type":"Point"}
}
=======
{"geometry":{"type":"Point","coordinates":[-95.716700,32.850000]},"type":"Feature","properties":{"hierarchy":["tgn:2339155","tgn:1000001","tgn:7012149","tgn:1002816","tgn:7007826","tgn:7029392"],"placetype":["aat:300008706"],"id":2339155,"name:xx":"Franks Creek"}}
>>>>>>> 03f74aca74312dbeaf24d7e61306dd6a786dc3d0
