{
  "id": 2424259,
  "type": "Feature",
  "properties": {
    "tgn:hierarchy":[
        "tgn:2424259",
        "tgn:1000001",
        "tgn:7012149",
        "tgn:2000897",
        "tgn:7007256",
        "tgn:7029392"
    ],
    "tgn:id":2424259,
    "tgn:name":"Johnson Bay",
    "tgn:placetype":[
        "aat:300132316"
    ]
},
  "bbox": [],
  "geometry": {"coordinates":[-89.2833,30.05],"type":"Point"}
}