{
  "id": 7310847,
  "type": "Feature",
  "properties": {
    "tgn:hierarchy":[
        "tgn:7310847",
        "tgn:1001623",
        "tgn:1000049",
        "tgn:1000002",
        "tgn:7029392"
    ],
    "tgn:id":7310847,
    "tgn:name":"Negro Juan, Estero",
    "tgn:placetype":[
        "aat:300008699"
    ]
},
  "bbox": [],
  "geometry": {"coordinates":[-71.616667,-45.283333],"type":"Point"}
}