{
  "id": 2278920,
  "type": "Feature",
  "properties": {
    "tgn:hierarchy":[
        "tgn:2278920",
        "tgn:1000001",
        "tgn:7012149",
        "tgn:2000809",
        "tgn:7007255",
        "tgn:7029392"
    ],
    "tgn:id":2278920,
    "tgn:name":"Dead Man Hollow",
    "tgn:placetype":[
        "aat:300008761"
    ]
},
  "bbox": [],
  "geometry": {"coordinates":[-82.8333,38.1167],"type":"Point"}
}