{
  "id": 2483775,
  "type": "Feature",
  "properties": {
    "tgn:hierarchy":[
        "tgn:2483775",
        "tgn:1000001",
        "tgn:2002107",
        "tgn:7012149",
        "tgn:7007827",
        "tgn:7029392"
    ],
    "tgn:id":2483775,
    "tgn:name":"Lateral Number 3",
    "tgn:placetype":[
        "aat:300006075"
    ]
},
  "bbox": [],
  "geometry": {"coordinates":[-110.0333,40.45],"type":"Point"}
}