{
  "id": 7558504,
  "type": "Feature",
  "properties": {
    "tgn:hierarchy":[
        "tgn:7558504",
        "tgn:1000004",
        "tgn:7000198",
        "tgn:7016722",
        "tgn:7029392"
    ],
    "tgn:id":7558504,
    "tgn:name:en":"Pur\u0101ha Nad\u012b",
    "tgn:placetype":[
        "aat:300008699"
    ]
},
  "bbox": [],
  "geometry": {"coordinates":[79.526894,26.720731],"type":"Point"}
}