{
  "id": 2776451,
  "type": "Feature",
  "properties": {
    "tgn:hierarchy":[
        "tgn:2776451",
        "tgn:1000001",
        "tgn:7012149",
        "tgn:7007923",
        "tgn:7029392"
    ],
    "tgn:id":2776451,
    "tgn:name":"Wind River Lake",
    "tgn:placetype":[
        "aat:300008680"
    ]
},
  "bbox": [],
  "geometry": {"coordinates":[-110.05,43.7333],"type":"Point"}
}