{
  "id": 7301661,
  "type": "Feature",
  "properties": {
    "tgn:hierarchy":[
        "tgn:7301661",
        "tgn:7002804",
        "tgn:1000003",
        "tgn:7002793",
        "tgn:1000095",
        "tgn:7029392"
    ],
    "tgn:id":7301661,
    "tgn:name":"Moj\u00f3n, Los Escull del",
    "tgn:placetype":[
        "aat:300011692"
    ]
},
  "bbox": [],
  "geometry": {"coordinates":[-0.75,37.85],"type":"Point"}
}