{
  "id": 2135075,
  "type": "Feature",
  "properties": {
    "tgn:hierarchy":[
        "tgn:2135075",
        "tgn:1000001",
        "tgn:2000467",
        "tgn:7012149",
        "tgn:7007250",
        "tgn:7029392"
    ],
    "tgn:id":2135075,
    "tgn:name":"Antelope Valley",
    "tgn:placetype":[
        "aat:300008761"
    ]
},
  "bbox": [],
  "geometry": {"coordinates":[-114.2667,42.3667],"type":"Point"}
}