{
  "id": 2437974,
  "type": "Feature",
  "properties": {
    "tgn:hierarchy":[
        "tgn:2437974",
        "tgn:1000001",
        "tgn:7012149",
        "tgn:1003042",
        "tgn:7007920",
        "tgn:7029392"
    ],
    "tgn:id":2437974,
    "tgn:name":"King Mountain",
    "tgn:placetype":[
        "aat:300008798"
    ]
},
  "bbox": [],
  "geometry": {"coordinates":[-121.4167,46.05],"type":"Point"}
}