{
  "id": 2271583,
  "type": "Feature",
  "properties": {
    "tgn:hierarchy":[
        "tgn:2271583",
        "tgn:1000001",
        "tgn:7012149",
        "tgn:2000181",
        "tgn:7007157",
        "tgn:7029392"
    ],
    "tgn:id":2271583,
    "tgn:name":"Cummings Creek",
    "tgn:placetype":[
        "aat:300008706"
    ]
},
  "bbox": [],
  "geometry": {"coordinates":[-123.9333,40.5167],"type":"Point"}
}