{
  "id": 7327260,
  "type": "Feature",
  "properties": {
    "tgn:hierarchy":[
        "tgn:7327260",
        "tgn:7008911",
        "tgn:1000003",
        "tgn:7002763",
        "tgn:1000095",
        "tgn:7029392"
    ],
    "tgn:id":7327260,
    "tgn:name":"Panizales",
    "tgn:placetype":[
        "aat:300008347"
    ]
},
  "bbox": [],
  "geometry": {"coordinates":[-5.883333,43.466667],"type":"Point"}
}