{
  "id": 7399685,
  "type": "Feature",
  "properties": {
    "tgn:hierarchy":[
        "tgn:7399685",
        "tgn:1000001",
        "tgn:7005593",
        "tgn:7005560",
        "tgn:7029392"
    ],
    "tgn:id":7399685,
    "tgn:name":"Mesa de Ram\u00edrez",
    "tgn:placetype":[
        "aat:300008347"
    ]
},
  "bbox": [],
  "geometry": {"coordinates":[-99.991667,20.926389],"type":"Point"}
}