{
  "id": 2154535,
  "type": "Feature",
  "properties": {
    "tgn:hierarchy":[
        "tgn:2154535",
        "tgn:1000001",
        "tgn:7006451",
        "tgn:7012149",
        "tgn:2000103",
        "tgn:7029392"
    ],
    "tgn:id":2154535,
    "tgn:name":"Bear Creek Tank",
    "tgn:placetype":[
        "aat:300006191"
    ]
},
  "bbox": [],
  "geometry": {"coordinates":[-113.2333,34.8667],"type":"Point"}
}