{
  "id": 7579957,
  "type": "Feature",
  "properties": {
    "tgn:hierarchy":[
        "tgn:7579957",
        "tgn:7001819",
        "tgn:1000004",
        "tgn:7000198",
        "tgn:7029392"
    ],
    "tgn:id":7579957,
    "tgn:name:en":"Tethaliang",
    "tgn:placetype":[
        "aat:300008347"
    ]
},
  "bbox": [],
  "geometry": {"coordinates":[96.118603,28.182777],"type":"Point"}
}