{
  "id": 7053502,
  "type": "Feature",
  "properties": {
    "tgn:hierarchy":[
        "tgn:7053502",
        "tgn:1003450",
        "tgn:7007850",
        "tgn:1000003",
        "tgn:1000080",
        "tgn:7029392"
    ],
    "tgn:id":7053502,
    "tgn:name":"Papa, Monte del",
    "tgn:placetype":[
        "aat:300008795"
    ]
},
  "bbox": [],
  "geometry": {"coordinates":[15.833333,40.133333],"type":"Point"}
}