{
  "id": 1080155,
  "type": "Feature",
  "properties": {
    "tgn:hierarchy":[
        "tgn:1080155",
        "tgn:7016675",
        "tgn:1000004",
        "tgn:7031843",
        "tgn:7000896",
        "tgn:1000120",
        "tgn:7029392"
    ],
    "tgn:id":1080155,
    "tgn:name":"Hokudan",
    "tgn:placetype":[
        "aat:300008347"
    ]
},
  "bbox": [],
  "geometry": {"coordinates":[134.9333,34.5333],"type":"Point"}
}