{
  "id": 2142872,
  "type": "Feature",
  "properties": {
    "tgn:hierarchy":[
        "tgn:2142872",
        "tgn:1000001",
        "tgn:7006451",
        "tgn:7012149",
        "tgn:2000103",
        "tgn:7029392"
    ],
    "tgn:id":2142872,
    "tgn:name":"Badger Spring Wash",
    "tgn:placetype":[
        "aat:300008699"
    ]
},
  "bbox": [],
  "geometry": {"coordinates":[-112.1167,34.2833],"type":"Point"}
}