{
  "id": 7034152,
  "type": "Feature",
  "properties": {
    "tgn:hierarchy":[
        "tgn:7034152",
        "tgn:1003468",
        "tgn:1000003",
        "tgn:7010380",
        "tgn:1000080",
        "tgn:7029392"
    ],
    "tgn:id":7034152,
    "tgn:name":"Masseria Gagliardi",
    "tgn:placetype":[
        "aat:300000206"
    ]
},
  "bbox": [],
  "geometry": {"coordinates":[18.096389,40.445556],"type":"Point"}
}