{
  "id": 7321303,
  "type": "Feature",
  "properties": {
    "tgn:hierarchy":[
        "tgn:7321303",
        "tgn:1001702",
        "tgn:1000049",
        "tgn:1000002",
        "tgn:7029392"
    ],
    "tgn:id":7321303,
    "tgn:name":"Bivouac, Isla",
    "tgn:placetype":[
        "aat:300008791"
    ]
},
  "bbox": [],
  "geometry": {"coordinates":[-71.666667,-54.05],"type":"Point"}
}