{
  "id": 7403128,
  "type": "Feature",
  "properties": {
    "tgn:hierarchy":[
        "tgn:7403128",
        "tgn:1000001",
        "tgn:7005600",
        "tgn:7005560",
        "tgn:7029392"
    ],
    "tgn:id":7403128,
    "tgn:name":"San Sim\u00f3n",
    "tgn:placetype":[
        "aat:300008347"
    ]
},
  "bbox": [],
  "geometry": {"coordinates":[-90.283333,20.670833],"type":"Point"}
}