{
  "id": 7427878,
  "type": "Feature",
  "properties": {
    "tgn:hierarchy":[
        "tgn:7427878",
        "tgn:1000001",
        "tgn:7005594",
        "tgn:7005560",
        "tgn:7029392"
    ],
    "tgn:id":7427878,
    "tgn:name":"Los Gavilanes",
    "tgn:placetype":[
        "aat:300008347"
    ]
},
  "bbox": [],
  "geometry": {"coordinates":[-99.033333,22.05],"type":"Point"}
}