{
  "id": 2734892,
  "type": "Feature",
  "properties": {
    "tgn:hierarchy":[
        "tgn:2734892",
        "tgn:1000001",
        "tgn:7012149",
        "tgn:2001110",
        "tgn:7007522",
        "tgn:7029392"
    ],
    "tgn:id":2734892,
    "tgn:name":"Twelvemile Creek",
    "tgn:placetype":[
        "aat:300008706"
    ]
},
  "bbox": [],
  "geometry": {"coordinates":[-90.5833,32.1667],"type":"Point"}
}