{
  "id": 7344661,
  "type": "Feature",
  "properties": {
    "tgn:hierarchy":[
        "tgn:7344661",
        "tgn:7008911",
        "tgn:1000003",
        "tgn:7002763",
        "tgn:1000095",
        "tgn:7029392"
    ],
    "tgn:id":7344661,
    "tgn:name":"Anduerga",
    "tgn:placetype":[
        "aat:300008347"
    ]
},
  "bbox": [],
  "geometry": {"coordinates":[-5.916667,43.45],"type":"Point"}
}