{
  "id": 2466423,
  "type": "Feature",
  "properties": {
    "tgn:hierarchy":[
        "tgn:2466423",
        "tgn:1000001",
        "tgn:7012149",
        "tgn:2000278",
        "tgn:7007240",
        "tgn:7029392"
    ],
    "tgn:id":2466423,
    "tgn:name":"Long Branch",
    "tgn:placetype":[
        "aat:300008699"
    ]
},
  "bbox": [],
  "geometry": {"coordinates":[-84.8833,30.4167],"type":"Point"}
}