{
  "id": 2751656,
  "type": "Feature",
  "properties": {
    "tgn:hierarchy":[
        "tgn:2751656",
        "tgn:1000001",
        "tgn:7012149",
        "tgn:2001500",
        "tgn:7007709",
        "tgn:7029392"
    ],
    "tgn:id":2751656,
    "tgn:name":"Warnersville",
    "tgn:placetype":[
        "aat:300008347"
    ]
},
  "bbox": [],
  "geometry": {"coordinates":[-79.7833,36.05],"type":"Point"}
}