{
  "id": 1062283,
  "type": "Feature",
  "properties": {
    "tgn:hierarchy":[
        "tgn:1062283",
        "tgn:7002824",
        "tgn:1000003",
        "tgn:7002786",
        "tgn:1000095",
        "tgn:7029392"
    ],
    "tgn:id":1062283,
    "tgn:name":"Muros",
    "tgn:placetype":[
        "aat:300008347"
    ]
},
  "bbox": [],
  "geometry": {"coordinates":[-9.033333,42.783333],"type":"Point"}
}