{
  "id": 2402383,
  "type": "Feature",
  "properties": {
    "tgn:hierarchy":[
        "tgn:2402383",
        "tgn:1000001",
        "tgn:7016172",
        "tgn:7012149",
        "tgn:2000162",
        "tgn:7029392"
    ],
    "tgn:id":2402383,
    "tgn:name":"Horton Mountain",
    "tgn:placetype":[
        "aat:300008798"
    ]
},
  "bbox": [],
  "geometry": {"coordinates":[-93.2667,35.3667],"type":"Point"}
}