<<<<<<< HEAD
{
  "id": 2402383,
  "type": "Feature",
  "properties": {
    "tgn:hierarchy":[
        "tgn:2402383",
        "tgn:1000001",
        "tgn:7016172",
        "tgn:7012149",
        "tgn:2000162",
        "tgn:7029392"
    ],
    "tgn:id":2402383,
    "tgn:name":"Horton Mountain",
    "tgn:placetype":[
        "aat:300008798"
    ]
},
  "bbox": [],
  "geometry": {"coordinates":[-93.2667,35.3667],"type":"Point"}
}
=======
{"geometry":{"type":"Point","coordinates":[-93.266700,35.366700]},"type":"Feature","properties":{"hierarchy":["tgn:2402383","tgn:1000001","tgn:7016172","tgn:7012149","tgn:2000162","tgn:7029392"],"placetype":["aat:300008798"],"id":2402383,"name:xx":"Horton Mountain"}}
>>>>>>> 03f74aca74312dbeaf24d7e61306dd6a786dc3d0
