<<<<<<< HEAD
{
  "id": 2333709,
  "type": "Feature",
  "properties": {
    "tgn:hierarchy":[
        "tgn:2333709",
        "tgn:1000001",
        "tgn:2002133",
        "tgn:7012149",
        "tgn:7007828",
        "tgn:7029392"
    ],
    "tgn:id":2333709,
    "tgn:name":"Foot Brook",
    "tgn:placetype":[
        "aat:300008699"
    ]
},
  "bbox": [],
  "geometry": {"coordinates":[-72.6833,44.7],"type":"Point"}
}
=======
{"geometry":{"type":"Point","coordinates":[-72.683300,44.700000]},"type":"Feature","properties":{"hierarchy":["tgn:2333709","tgn:1000001","tgn:2002133","tgn:7012149","tgn:7007828","tgn:7029392"],"placetype":["aat:300008699"],"id":2333709,"name:xx":"Foot Brook"}}
>>>>>>> 03f74aca74312dbeaf24d7e61306dd6a786dc3d0
