{
  "id": 7591491,
  "type": "Feature",
  "properties": {
    "tgn:hierarchy":[
        "tgn:7591491",
        "tgn:1000004",
        "tgn:7000198",
        "tgn:7000799",
        "tgn:7029392"
    ],
    "tgn:id":7591491,
    "tgn:name:en":"Kagi\u0101ni",
    "tgn:placetype":[
        "aat:300008697"
    ]
},
  "bbox": [],
  "geometry": {"coordinates":[74.616667,32.965278],"type":"Point"}
}