<<<<<<< HEAD
{
  "id": 2768323,
  "type": "Feature",
  "properties": {
    "tgn:hierarchy":[
        "tgn:2768323",
        "tgn:1000001",
        "tgn:7012149",
        "tgn:2001500",
        "tgn:7007709",
        "tgn:7029392"
    ],
    "tgn:id":2768323,
    "tgn:name":"Whitesell Lake Number One",
    "tgn:placetype":[
        "aat:300006191"
    ]
},
  "bbox": [],
  "geometry": {"coordinates":[-79.5833,36.15],"type":"Point"}
}
=======
{"geometry":{"type":"Point","coordinates":[-79.583300,36.150000]},"type":"Feature","properties":{"hierarchy":["tgn:2768323","tgn:1000001","tgn:7012149","tgn:2001500","tgn:7007709","tgn:7029392"],"placetype":["aat:300006191"],"id":2768323,"name:xx":"Whitesell Lake Number One"}}
>>>>>>> 03f74aca74312dbeaf24d7e61306dd6a786dc3d0
