{
  "id": 2345183,
  "type": "Feature",
  "properties": {
    "tgn:hierarchy":[
        "tgn:2345183",
        "tgn:1000001",
        "tgn:7012149",
        "tgn:2000214",
        "tgn:7007158",
        "tgn:7029392"
    ],
    "tgn:id":2345183,
    "tgn:name":"Garfield Creek",
    "tgn:placetype":[
        "aat:300008699"
    ]
},
  "bbox": [],
  "geometry": {"coordinates":[-107.55,39.55],"type":"Point"}
}