{
  "id": 2515684,
  "type": "Feature",
  "properties": {
    "tgn:hierarchy":[
        "tgn:2515684",
        "tgn:1000001",
        "tgn:7012149",
        "tgn:2002302",
        "tgn:7013961",
        "tgn:7029392"
    ],
    "tgn:id":2515684,
    "tgn:name":"Millstone Hollow",
    "tgn:placetype":[
        "aat:300008761"
    ]
},
  "bbox": [],
  "geometry": {"coordinates":[-81.35,38.95],"type":"Point"}
}