{
  "id": 7372192,
  "type": "Feature",
  "properties": {
    "tgn:hierarchy":[
        "tgn:7372192",
        "tgn:7005586",
        "tgn:1000001",
        "tgn:7005560",
        "tgn:7029392"
    ],
    "tgn:id":7372192,
    "tgn:name":"La Ca\u00f1ada",
    "tgn:placetype":[
        "aat:300006191"
    ]
},
  "bbox": [],
  "geometry": {"coordinates":[-102.933333,20.483333],"type":"Point"}
}