{
  "id": 2357450,
  "type": "Feature",
  "properties": {
    "tgn:hierarchy":[
        "tgn:2357450",
        "tgn:1000001",
        "tgn:7006451",
        "tgn:7012149",
        "tgn:2000103",
        "tgn:7029392"
    ],
    "tgn:id":2357450,
    "tgn:name":"Government Spring",
    "tgn:placetype":[
        "aat:300008697"
    ]
},
  "bbox": [],
  "geometry": {"coordinates":[-112.15,34.2333],"type":"Point"}
}