{
  "id": 7321191,
  "type": "Feature",
  "properties": {
    "tgn:hierarchy":[
        "tgn:7321191",
        "tgn:7016598",
        "tgn:1000049",
        "tgn:1000002",
        "tgn:7029392"
    ],
    "tgn:id":7321191,
    "tgn:name":"Campana",
    "tgn:placetype":[
        "aat:300387033"
    ]
},
  "bbox": [],
  "geometry": {"coordinates":[-69.633333,-25.05],"type":"Point"}
}