{
  "id": 7507383,
  "type": "Feature",
  "properties": {
    "tgn:hierarchy":[
        "tgn:7507383",
        "tgn:1008380",
        "tgn:7520093",
        "tgn:1000226",
        "tgn:1000006",
        "tgn:7029392"
    ],
    "tgn:id":7507383,
    "tgn:name:en":"Pukekino",
    "tgn:placetype":[
        "aat:300008795"
    ]
},
  "bbox": [],
  "geometry": {"coordinates":[175.483333,-40.75],"type":"Point"}
}