{
  "id": 7257683,
  "type": "Feature",
  "properties": {
    "tgn:concordances":{
        "gn:id":"2758747"
    },
    "tgn:hierarchy":[
        "tgn:7257683",
        "tgn:7003616",
        "tgn:1000003",
        "tgn:7016845",
        "tgn:7029392"
    ],
    "tgn:id":7257683,
    "tgn:name:nl":"Boer",
    "tgn:placetype":[
        "aat:300008347"
    ]
},
  "bbox": [],
  "geometry": {"coordinates":[5.566667,53.216667],"type":"Point"}
}