{
  "id": 2034908,
  "type": "Feature",
  "properties": {
    "tgn:hierarchy":[
        "tgn:2034908",
        "tgn:1000001",
        "tgn:7012149",
        "tgn:2000632",
        "tgn:7007253",
        "tgn:7029392"
    ],
    "tgn:id":2034908,
    "tgn:name":"Harris",
    "tgn:placetype":[
        "aat:300008347"
    ]
},
  "bbox": [],
  "geometry": {"coordinates":[-95.4333,43.4333],"type":"Point"}
}