{
  "id": 1001478,
  "type": "Feature",
  "properties": {
    "tgn:hierarchy":[
        "tgn:1001478",
        "tgn:1000004",
        "tgn:1000122",
        "tgn:7029392"
    ],
    "tgn:id":1001478,
    "tgn:name:en":"North P'y\u014fngan",
    "tgn:placetype":[
        "aat:300387064",
        "aat:300000774"
    ]
},
  "bbox": [],
  "geometry": {"coordinates":[125.3333,40.1667],"type":"Point"}
}