{
  "id": 7235539,
  "type": "Feature",
  "properties": {
    "tgn:hierarchy":[
        "tgn:7235539",
        "tgn:4003773",
        "tgn:7001395",
        "tgn:1000003",
        "tgn:1000074",
        "tgn:7029392"
    ],
    "tgn:id":7235539,
    "tgn:name":"Filiadh\u00f3n",
    "tgn:placetype":[
        "aat:300008347"
    ]
},
  "bbox": [],
  "geometry": {"coordinates":[22.483333,39.066667],"type":"Point"}
}