{
  "id": 2665257,
  "type": "Feature",
  "properties": {
    "tgn:hierarchy":[
        "tgn:2665257",
        "tgn:1000001",
        "tgn:7012149",
        "tgn:7016021",
        "tgn:7007568",
        "tgn:7029392"
    ],
    "tgn:id":2665257,
    "tgn:name":"Sinclair Corner",
    "tgn:placetype":[
        "aat:300008347"
    ]
},
  "bbox": [],
  "geometry": {"coordinates":[-74.8833,44.6333],"type":"Point"}
}