{
  "id": 2626247,
  "type": "Feature",
  "properties": {
    "tgn:hierarchy":[
        "tgn:2626247",
        "tgn:1000001",
        "tgn:7012149",
        "tgn:2001297",
        "tgn:7007524",
        "tgn:7029392"
    ],
    "tgn:id":2626247,
    "tgn:name":"Rocky Crossing Reservoir",
    "tgn:placetype":[
        "aat:300006191"
    ]
},
  "bbox": [],
  "geometry": {"coordinates":[-105.95,45.25],"type":"Point"}
}