{
  "id": 2243071,
  "type": "Feature",
  "properties": {
    "tgn:hierarchy":[
        "tgn:2243071",
        "tgn:1000001",
        "tgn:7012149",
        "tgn:2001041",
        "tgn:7007521",
        "tgn:7029392"
    ],
    "tgn:id":2243071,
    "tgn:name":"Clear Lake",
    "tgn:placetype":[
        "aat:300008680"
    ]
},
  "bbox": [],
  "geometry": {"coordinates":[-94.25,44.75],"type":"Point"}
}