{
  "id": 2272666,
  "type": "Feature",
  "properties": {
    "tgn:hierarchy":[
        "tgn:2272666",
        "tgn:1000001",
        "tgn:1002461",
        "tgn:7012149",
        "tgn:7007159",
        "tgn:7029392"
    ],
    "tgn:id":2272666,
    "tgn:name":"Cussgutter Brook",
    "tgn:placetype":[
        "aat:300008699"
    ]
},
  "bbox": [],
  "geometry": {"coordinates":[-72.9333,41.6333],"type":"Point"}
}