{
  "id": 7003138,
  "type": "Feature",
  "properties": {
    "tgn:hierarchy":[
        "tgn:7003138",
        "tgn:1000003",
        "tgn:7003080",
        "tgn:1000080",
        "tgn:7029392"
    ],
    "tgn:id":7003138,
    "tgn:name":"Roma",
    "tgn:placetype":[
        "aat:300387145",
        "aat:300000774"
    ]
},
  "bbox": [],
  "geometry": {"coordinates":[12.666667,41.966667],"type":"Point"}
}