{
  "id": 7185291,
  "type": "Feature",
  "properties": {
    "tgn:hierarchy":[
        "tgn:7185291",
        "tgn:1000003",
        "tgn:7003687",
        "tgn:7000084",
        "tgn:7029392"
    ],
    "tgn:id":7185291,
    "tgn:name":"Gertrudshof",
    "tgn:placetype":[
        "aat:300008347"
    ]
},
  "bbox": [],
  "geometry": {"coordinates":[13.016667,51.75],"type":"Point"}
}