{
  "id": 7580285,
  "type": "Feature",
  "properties": {
    "tgn:hierarchy":[
        "tgn:7580285",
        "tgn:1000004",
        "tgn:7000198",
        "tgn:1001895",
        "tgn:7029392"
    ],
    "tgn:id":7580285,
    "tgn:name:en":"Vad\u0101libhui",
    "tgn:placetype":[
        "aat:300008347"
    ]
},
  "bbox": [],
  "geometry": {"coordinates":[74.116667,20.283333],"type":"Point"}
}