{
  "id": 2437963,
  "type": "Feature",
  "properties": {
    "tgn:hierarchy":[
        "tgn:2437963",
        "tgn:1000001",
        "tgn:7012149",
        "tgn:7007524",
        "tgn:7029392"
    ],
    "tgn:id":2437963,
    "tgn:name":"King Mountain",
    "tgn:placetype":[
        "aat:300008798"
    ]
},
  "bbox": [],
  "geometry": {"coordinates":[-113.1667,46.7333],"type":"Point"}
}