{
  "id": 7420319,
  "type": "Feature",
  "properties": {
    "tgn:hierarchy":[
        "tgn:7420319",
        "tgn:1000001",
        "tgn:7005589",
        "tgn:7005560",
        "tgn:7029392"
    ],
    "tgn:id":7420319,
    "tgn:name:es":"El Antrisco, Sierra",
    "tgn:placetype":[
        "aat:300008795"
    ]
},
  "bbox": [],
  "geometry": {"coordinates":[-100.718611,26.014167],"type":"Point"}
}