{
  "id": 2630345,
  "type": "Feature",
  "properties": {
    "tgn:hierarchy":[
        "tgn:2630345",
        "tgn:1000001",
        "tgn:7012149",
        "tgn:2000435",
        "tgn:7007248",
        "tgn:7029392"
    ],
    "tgn:id":2630345,
    "tgn:name":"Rough Mountain",
    "tgn:placetype":[
        "aat:300008798"
    ]
},
  "bbox": [],
  "geometry": {"coordinates":[-83.8667,34.7167],"type":"Point"}
}