{
  "id": 7145594,
  "type": "Feature",
  "properties": {
    "tgn:hierarchy":[
        "tgn:7145594",
        "tgn:1000003",
        "tgn:7000094",
        "tgn:7000084",
        "tgn:7029392"
    ],
    "tgn:id":7145594,
    "tgn:name":"Klein Wardow",
    "tgn:placetype":[
        "aat:300008347"
    ]
},
  "bbox": [],
  "geometry": {"coordinates":[12.416667,53.933333],"type":"Point"}
}