{
  "id": 2344559,
  "type": "Feature",
  "properties": {
    "tgn:hierarchy":[
        "tgn:2344559",
        "tgn:1000001",
        "tgn:7012149",
        "tgn:2000914",
        "tgn:7007256",
        "tgn:7029392"
    ],
    "tgn:id":2344559,
    "tgn:name":"Gar Pond",
    "tgn:placetype":[
        "aat:300008680"
    ]
},
  "bbox": [],
  "geometry": {"coordinates":[-91.2667,30.5167],"type":"Point"}
}