{
  "id": 7450879,
  "type": "Feature",
  "properties": {
    "tgn:hierarchy":[
        "tgn:7450879",
        "tgn:7002445",
        "tgn:1000003",
        "tgn:7008166",
        "tgn:7008591",
        "tgn:7029392"
    ],
    "tgn:id":7450879,
    "tgn:name:en":"East Harlsey",
    "tgn:placetype":[
        "aat:300008347"
    ]
},
  "bbox": [],
  "geometry": {"coordinates":[-1.35,54.383333],"type":"Point"}
}