{
  "id": 7580443,
  "type": "Feature",
  "properties": {
    "tgn:hierarchy":[
        "tgn:7580443",
        "tgn:1000004",
        "tgn:7000198",
        "tgn:1001895",
        "tgn:7029392"
    ],
    "tgn:id":7580443,
    "tgn:name:en":"V\u0101ghur River",
    "tgn:placetype":[
        "aat:300008699"
    ]
},
  "bbox": [],
  "geometry": {"coordinates":[75.693649,21.094687],"type":"Point"}
}