<<<<<<< HEAD
{
  "id": 7481939,
  "type": "Feature",
  "properties": {
    "tgn:hierarchy":[
        "tgn:7481939",
        "tgn:1000004",
        "tgn:7001013",
        "tgn:1000141",
        "tgn:7029392"
    ],
    "tgn:id":7481939,
    "tgn:name":"Taiping Shan",
    "tgn:placetype":[
        "aat:300008798"
    ]
},
  "bbox": [],
  "geometry": {"coordinates":[121.235,24.811111],"type":"Point"}
}
=======
{"geometry":{"type":"Point","coordinates":[121.235000,24.811111]},"type":"Feature","properties":{"hierarchy":["tgn:7481939","tgn:1000004","tgn:7001013","tgn:1000141","tgn:7029392"],"placetype":["aat:300008798"],"id":7481939,"name:xx":"Taiping Shan"}}
>>>>>>> 03f74aca74312dbeaf24d7e61306dd6a786dc3d0
