{
  "id": 7481939,
  "type": "Feature",
  "properties": {
    "tgn:hierarchy":[
        "tgn:7481939",
        "tgn:1000004",
        "tgn:7001013",
        "tgn:1000141",
        "tgn:7029392"
    ],
    "tgn:id":7481939,
    "tgn:name":"Taiping Shan",
    "tgn:placetype":[
        "aat:300008798"
    ]
},
  "bbox": [],
  "geometry": {"coordinates":[121.235,24.811111],"type":"Point"}
}