<<<<<<< HEAD
{
  "id": 2760886,
  "type": "Feature",
  "properties": {
    "tgn:hierarchy":[
        "tgn:2760886",
        "tgn:1000001",
        "tgn:7012149",
        "tgn:7007826",
        "tgn:7029392"
    ],
    "tgn:id":2760886,
    "tgn:name":"West Hill Creek",
    "tgn:placetype":[
        "aat:300008706"
    ]
},
  "bbox": [],
  "geometry": {"coordinates":[-101.4833,35.6],"type":"Point"}
}
=======
{"geometry":{"type":"Point","coordinates":[-101.483300,35.600000]},"type":"Feature","properties":{"hierarchy":["tgn:2760886","tgn:1000001","tgn:7012149","tgn:7007826","tgn:7029392"],"placetype":["aat:300008706"],"id":2760886,"name:xx":"West Hill Creek"}}
>>>>>>> 03f74aca74312dbeaf24d7e61306dd6a786dc3d0
