{
  "id": 2476309,
  "type": "Feature",
  "properties": {
    "tgn:hierarchy":[
        "tgn:2476309",
        "tgn:1000001",
        "tgn:7012149",
        "tgn:2001274",
        "tgn:7007524",
        "tgn:7029392"
    ],
    "tgn:id":2476309,
    "tgn:name":"Lunch Creek",
    "tgn:placetype":[
        "aat:300008706"
    ]
},
  "bbox": [],
  "geometry": {"coordinates":[-113.4667,48.1667],"type":"Point"}
}