{
  "id": 7229333,
  "type": "Feature",
  "properties": {
    "tgn:hierarchy":[
        "tgn:7229333",
        "tgn:7002752",
        "tgn:7001399",
        "tgn:1000003",
        "tgn:1000074",
        "tgn:7029392"
    ],
    "tgn:id":7229333,
    "tgn:name":"Lazar\u00e1dhes",
    "tgn:placetype":[
        "aat:300008347"
    ]
},
  "bbox": [],
  "geometry": {"coordinates":[21.85,40.016667],"type":"Point"}
}