{
  "id": 2421538,
  "type": "Feature",
  "properties": {
    "tgn:hierarchy":[
        "tgn:2421538",
        "tgn:2000090",
        "tgn:1000001",
        "tgn:7006451",
        "tgn:7012149",
        "tgn:7029392"
    ],
    "tgn:id":2421538,
    "tgn:name":"Jessie Spring Marsh",
    "tgn:placetype":[
        "aat:300008905"
    ]
},
  "bbox": [],
  "geometry": {"coordinates":[-109.3167,33.95],"type":"Point"}
}