<<<<<<< HEAD
{
  "id": 7379317,
  "type": "Feature",
  "properties": {
    "tgn:hierarchy":[
        "tgn:7379317",
        "tgn:1000001",
        "tgn:7005595",
        "tgn:7005560",
        "tgn:7029392"
    ],
    "tgn:id":7379317,
    "tgn:name":"Mezquitillos, Arroyo",
    "tgn:placetype":[
        "aat:300266554",
        "aat:300008699"
    ]
},
  "bbox": [],
  "geometry": {"coordinates":[-108.133333,26.900278],"type":"Point"}
}
=======
{"geometry":{"type":"Point","coordinates":[-108.133333,26.900278]},"type":"Feature","properties":{"hierarchy":["tgn:7379317","tgn:1000001","tgn:7005595","tgn:7005560","tgn:7029392"],"placetype":["aat:300266554","aat:300008699"],"id":7379317,"name:xx":"Mezquitillos, Arroyo"}}
>>>>>>> 03f74aca74312dbeaf24d7e61306dd6a786dc3d0
