{
  "id": 2564158,
  "type": "Feature",
  "properties": {
    "tgn:hierarchy":[
        "tgn:2564158",
        "tgn:1000001",
        "tgn:2001428",
        "tgn:7012149",
        "tgn:7007566",
        "tgn:7029392"
    ],
    "tgn:id":2564158,
    "tgn:name":"P and G Claims",
    "tgn:placetype":[
        "aat:300000390"
    ]
},
  "bbox": [],
  "geometry": {"coordinates":[-106.3667,35.0667],"type":"Point"}
}