{
  "id": 2578184,
  "type": "Feature",
  "properties": {
    "tgn:hierarchy":[
        "tgn:2578184",
        "tgn:1000001",
        "tgn:7012149",
        "tgn:1002646",
        "tgn:7007826",
        "tgn:7029392"
    ],
    "tgn:id":2578184,
    "tgn:name":"Peyton Creek",
    "tgn:placetype":[
        "aat:300008706"
    ]
},
  "bbox": [],
  "geometry": {"coordinates":[-95.8667,28.9167],"type":"Point"}
}