{
  "id": 1072798,
  "type": "Feature",
  "properties": {
    "tgn:hierarchy":[
        "tgn:1072798",
        "tgn:1000004",
        "tgn:7002372",
        "tgn:1000111",
        "tgn:7029392"
    ],
    "tgn:id":1072798,
    "tgn:name":"Xianru",
    "tgn:placetype":[
        "aat:300008347"
    ]
},
  "bbox": [],
  "geometry": {"coordinates":[128.0333,43.1833],"type":"Point"}
}