{
  "id": 7060353,
  "type": "Feature",
  "properties": {
    "tgn:hierarchy":[
        "tgn:7060353",
        "tgn:1000003",
        "tgn:7003678",
        "tgn:7000084",
        "tgn:7029392"
    ],
    "tgn:id":7060353,
    "tgn:name":"Albshausen",
    "tgn:placetype":[
        "aat:300008347"
    ]
},
  "bbox": [],
  "geometry": {"coordinates":[9.516667,51.183333],"type":"Point"}
}