{
  "id": 7548542,
  "type": "Feature",
  "properties": {
    "tgn:hierarchy":[
        "tgn:7548542",
        "tgn:1000004",
        "tgn:7031781",
        "tgn:7000198",
        "tgn:7029392"
    ],
    "tgn:id":7548542,
    "tgn:name:en":"Dudma Falls",
    "tgn:placetype":[
        "aat:300008736"
    ]
},
  "bbox": [],
  "geometry": {"coordinates":[82.45,18.516667],"type":"Point"}
}