{
  "id": 2069004,
  "type": "Feature",
  "properties": {
    "tgn:hierarchy":[
        "tgn:2069004",
        "tgn:1000001",
        "tgn:7012149",
        "tgn:1002518",
        "tgn:7007568",
        "tgn:7029392"
    ],
    "tgn:id":2069004,
    "tgn:name":"East Rodman",
    "tgn:placetype":[
        "aat:300008347",
        "aat:300387210"
    ]
},
  "bbox": [],
  "geometry": {"coordinates":[-75.85,43.8667],"type":"Point"}
}