{
  "id": 1129278,
  "type": "Feature",
  "properties": {
    "tgn:hierarchy":[
        "tgn:1129278",
        "tgn:1000004",
        "tgn:1000109",
        "tgn:7029392"
    ],
    "tgn:id":1129278,
    "tgn:name":"S\u00ean, St\u0153ng",
    "tgn:placetype":[
        "aat:300008707"
    ]
},
  "bbox": [],
  "geometry": {"coordinates":[104.4667,12.5333],"type":"Point"}
}