{
  "id": 7060028,
  "type": "Feature",
  "properties": {
    "tgn:hierarchy":[
        "tgn:7060028",
        "tgn:1000003",
        "tgn:7003685",
        "tgn:7000084",
        "tgn:7029392"
    ],
    "tgn:id":7060028,
    "tgn:name":"Algier",
    "tgn:placetype":[
        "aat:300008347"
    ]
},
  "bbox": [],
  "geometry": {"coordinates":[14.933333,51.333333],"type":"Point"}
}