{
  "id": 1118697,
  "type": "Feature",
  "properties": {
    "tgn:hierarchy":[
        "tgn:1118697",
        "tgn:1000003",
        "tgn:7003688",
        "tgn:7000084",
        "tgn:7029392"
    ],
    "tgn:id":1118697,
    "tgn:name":"Westensee",
    "tgn:placetype":[
        "aat:300008680"
    ]
},
  "bbox": [],
  "geometry": {"coordinates":[9.95,54.283333],"type":"Point"}
}