{
  "id": 7321028,
  "type": "Feature",
  "properties": {
    "tgn:hierarchy":[
        "tgn:7321028",
        "tgn:1001702",
        "tgn:1000049",
        "tgn:1000002",
        "tgn:7029392"
    ],
    "tgn:id":7321028,
    "tgn:name":"Bunster, Islotes",
    "tgn:placetype":[
        "aat:300008791"
    ]
},
  "bbox": [],
  "geometry": {"coordinates":[-74.383333,-48.766667],"type":"Point"}
}