{
  "id": 7213739,
  "type": "Feature",
  "properties": {
    "tgn:hierarchy":[
        "tgn:7213739",
        "tgn:7003692",
        "tgn:1000003",
        "tgn:7000084",
        "tgn:7029392"
    ],
    "tgn:id":7213739,
    "tgn:name":"Birkj\u00f6rglehof",
    "tgn:placetype":[
        "aat:300000206"
    ]
},
  "bbox": [],
  "geometry": {"coordinates":[8.016667,47.983333],"type":"Point"}
}