{
  "id": 2397223,
  "type": "Feature",
  "properties": {
    "tgn:hierarchy":[
        "tgn:2397223",
        "tgn:1000001",
        "tgn:7012149",
        "tgn:2002374",
        "tgn:7007923",
        "tgn:7029392"
    ],
    "tgn:id":2397223,
    "tgn:name":"Hondo Creek",
    "tgn:placetype":[
        "aat:300008706"
    ]
},
  "bbox": [],
  "geometry": {"coordinates":[-106.95,44.2833],"type":"Point"}
}