{
  "id": 2261131,
  "type": "Feature",
  "properties": {
    "tgn:hierarchy":[
        "tgn:2261131",
        "tgn:1000001",
        "tgn:7012149",
        "tgn:2001033",
        "tgn:7007521",
        "tgn:7029392"
    ],
    "tgn:id":2261131,
    "tgn:name":"County Ditch Number Twentyone",
    "tgn:placetype":[
        "aat:300006075"
    ]
},
  "bbox": [],
  "geometry": {"coordinates":[-97.0667,48.7333],"type":"Point"}
}