{
  "id": 7138447,
  "type": "Feature",
  "properties": {
    "tgn:hierarchy":[
        "tgn:7138447",
        "tgn:7003692",
        "tgn:1000003",
        "tgn:7000084",
        "tgn:7029392"
    ],
    "tgn:id":7138447,
    "tgn:name":"Lemberg",
    "tgn:placetype":[
        "aat:300008347"
    ]
},
  "bbox": [],
  "geometry": {"coordinates":[9.666667,49.116667],"type":"Point"}
}