{
  "id": 7527117,
  "type": "Feature",
  "properties": {
    "tgn:hierarchy":[
        "tgn:7527117",
        "tgn:7001242",
        "tgn:7016833",
        "tgn:1001418",
        "tgn:7029392"
    ],
    "tgn:id":7527117,
    "tgn:name:en":"Sidi N\u00e2gi",
    "tgn:placetype":[
        "aat:300007558"
    ]
},
  "bbox": [],
  "geometry": {"coordinates":[26.995479,30.878635],"type":"Point"}
}