{
  "id": 2317957,
  "type": "Feature",
  "properties": {
    "tgn:hierarchy":[
        "tgn:2317957",
        "tgn:1000001",
        "tgn:2001816",
        "tgn:7012149",
        "tgn:7007713",
        "tgn:7029392"
    ],
    "tgn:id":2317957,
    "tgn:name":"Englishman Butte",
    "tgn:placetype":[
        "aat:300008798"
    ]
},
  "bbox": [],
  "geometry": {"coordinates":[-103.05,44.5667],"type":"Point"}
}