{
  "id": 2095676,
  "type": "Feature",
  "properties": {
    "tgn:hierarchy":[
        "tgn:2095676",
        "tgn:2001725",
        "tgn:1000001",
        "tgn:7012149",
        "tgn:7007712",
        "tgn:7029392"
    ],
    "tgn:id":2095676,
    "tgn:name":"Donalds",
    "tgn:placetype":[
        "aat:300008347"
    ]
},
  "bbox": [],
  "geometry": {"coordinates":[-82.3333,34.3667],"type":"Point"}
}