{
  "id": 2744866,
  "type": "Feature",
  "properties": {
    "tgn:hierarchy":[
        "tgn:2744866",
        "tgn:1000001",
        "tgn:7012149",
        "tgn:2001457",
        "tgn:7007566",
        "tgn:7029392"
    ],
    "tgn:id":2744866,
    "tgn:name":"Vidal, Valle",
    "tgn:placetype":[
        "aat:300008761"
    ]
},
  "bbox": [],
  "geometry": {"coordinates":[-105.2667,36.7167],"type":"Point"}
}