{
  "id": 7147656,
  "type": "Feature",
  "properties": {
    "tgn:hierarchy":[
        "tgn:7147656",
        "tgn:1000003",
        "tgn:7000094",
        "tgn:7000084",
        "tgn:7029392"
    ],
    "tgn:id":7147656,
    "tgn:name":"Kyritz",
    "tgn:placetype":[
        "aat:300008347"
    ]
},
  "bbox": [],
  "geometry": {"coordinates":[14.35,53.366667],"type":"Point"}
}