{
  "id": 7530487,
  "type": "Feature",
  "properties": {
    "tgn:hierarchy":[
        "tgn:7530487",
        "tgn:7001242",
        "tgn:7016833",
        "tgn:1001083",
        "tgn:7029392"
    ],
    "tgn:id":7530487,
    "tgn:name":"Kan\u012bsat al Mas\u012b\u1e29",
    "tgn:placetype":[
        "aat:300007466"
    ]
},
  "bbox": [],
  "geometry": {"coordinates":[31.204383,30.083846],"type":"Point"}
}