{
  "id": 2555137,
  "type": "Feature",
  "properties": {
    "tgn:hierarchy":[
        "tgn:2555137",
        "tgn:1000001",
        "tgn:7012149",
        "tgn:2002371",
        "tgn:7007923",
        "tgn:7029392"
    ],
    "tgn:id":2555137,
    "tgn:name":"Ocean Lake Habitat Reservoir Number 5",
    "tgn:placetype":[
        "aat:300006191"
    ]
},
  "bbox": [],
  "geometry": {"coordinates":[-109.1167,43.1833],"type":"Point"}
}