{
  "id": 7161994,
  "type": "Feature",
  "properties": {
    "tgn:hierarchy":[
        "tgn:7161994",
        "tgn:1000003",
        "tgn:7003676",
        "tgn:7000084",
        "tgn:7029392"
    ],
    "tgn:id":7161994,
    "tgn:name":"Idafehn",
    "tgn:placetype":[
        "aat:300008347"
    ]
},
  "bbox": [],
  "geometry": {"coordinates":[7.633333,53.15],"type":"Point"}
}