{
  "id": 7532260,
  "type": "Feature",
  "properties": {
    "tgn:hierarchy":[
        "tgn:7532260",
        "tgn:7001242",
        "tgn:7016833",
        "tgn:1001091",
        "tgn:7029392"
    ],
    "tgn:id":7532260,
    "tgn:name":"Mad\u0101fin al Arman",
    "tgn:placetype":[
        "aat:300266755"
    ]
},
  "bbox": [],
  "geometry": {"coordinates":[31.332267,30.078426],"type":"Point"}
}