{
  "id": 2611113,
  "type": "Feature",
  "properties": {
    "tgn:hierarchy":[
        "tgn:2611113",
        "tgn:1000001",
        "tgn:7006451",
        "tgn:7012149",
        "tgn:2000100",
        "tgn:7029392"
    ],
    "tgn:id":2611113,
    "tgn:name":"Red Hill Tank",
    "tgn:placetype":[
        "aat:300006191"
    ]
},
  "bbox": [],
  "geometry": {"coordinates":[-111.1833,31.5667],"type":"Point"}
}