{
  "id": 2781158,
  "type": "Feature",
  "properties": {
    "tgn:hierarchy":[
        "tgn:2781158",
        "tgn:1000001",
        "tgn:7012149",
        "tgn:2000493",
        "tgn:7007250",
        "tgn:7029392"
    ],
    "tgn:id":2781158,
    "tgn:name":"Wooden Shoe Spring",
    "tgn:placetype":[
        "aat:300008697"
    ]
},
  "bbox": [],
  "geometry": {"coordinates":[-114.2833,42.2667],"type":"Point"}
}