<<<<<<< HEAD
{
  "id": 7355391,
  "type": "Feature",
  "properties": {
    "tgn:hierarchy":[
        "tgn:7355391",
        "tgn:1000001",
        "tgn:1001960",
        "tgn:7005560",
        "tgn:7029392"
    ],
    "tgn:id":7355391,
    "tgn:name":"Cedros",
    "tgn:placetype":[
        "aat:300008347"
    ]
},
  "bbox": [],
  "geometry": {"coordinates":[-109.25,27.716667],"type":"Point"}
}
=======
{"geometry":{"type":"Point","coordinates":[-109.250000,27.716667]},"type":"Feature","properties":{"hierarchy":["tgn:7355391","tgn:1000001","tgn:1001960","tgn:7005560","tgn:7029392"],"placetype":["aat:300008347"],"id":7355391,"name:xx":"Cedros"}}
>>>>>>> 03f74aca74312dbeaf24d7e61306dd6a786dc3d0
