{
  "id": 2561581,
  "type": "Feature",
  "properties": {
    "tgn:hierarchy":[
        "tgn:2561581",
        "tgn:1000001",
        "tgn:7012149",
        "tgn:7007826",
        "tgn:7029392"
    ],
    "tgn:id":2561581,
    "tgn:name":"Osman Draw",
    "tgn:placetype":[
        "aat:300008761"
    ]
},
  "bbox": [],
  "geometry": {"coordinates":[-101.7833,30.1333],"type":"Point"}
}