{
  "id": 2238488,
  "type": "Feature",
  "properties": {
    "tgn:hierarchy":[
        "tgn:2238488",
        "tgn:1000001",
        "tgn:2001410",
        "tgn:7012149",
        "tgn:7007526",
        "tgn:7029392"
    ],
    "tgn:id":2238488,
    "tgn:name":"Cholla Cove",
    "tgn:placetype":[
        "aat:300132316"
    ]
},
  "bbox": [],
  "geometry": {"coordinates":[-114.5833,35.25],"type":"Point"}
}