{
  "id": 1124504,
  "type": "Feature",
  "properties": {
    "tgn:hierarchy":[
        "tgn:1124504",
        "tgn:7001242",
        "tgn:1000185",
        "tgn:7029392"
    ],
    "tgn:id":1124504,
    "tgn:name":"Gweru",
    "tgn:placetype":[
        "aat:300008707"
    ]
},
  "bbox": [],
  "geometry": {"coordinates":[28.616,-18.766],"type":"Point"}
}