{
  "id": 7007787,
  "type": "Feature",
  "properties": {
    "tgn:hierarchy":[
        "tgn:7007787",
        "tgn:1000003",
        "tgn:7003141",
        "tgn:7003236",
        "tgn:1044940",
        "tgn:1000080",
        "tgn:7029392"
    ],
    "tgn:id":7007787,
    "tgn:name":"Oneglia",
    "tgn:placetype":[
        "aat:300000745",
        "aat:300387330",
        "aat:300387339"
    ]
},
  "bbox": [],
  "geometry": {"coordinates":[8.033333,43.883333],"type":"Point"}
}