{
  "id": 2594452,
  "type": "Feature",
  "properties": {
    "tgn:hierarchy":[
        "tgn:2594452",
        "tgn:1000001",
        "tgn:7012149",
        "tgn:2000905",
        "tgn:7007256",
        "tgn:7029392"
    ],
    "tgn:id":2594452,
    "tgn:name":"Porters Island",
    "tgn:placetype":[
        "aat:300008791"
    ]
},
  "bbox": [],
  "geometry": {"coordinates":[-89.7167,30.35],"type":"Point"}
}