{
  "id": 2564518,
  "type": "Feature",
  "properties": {
    "tgn:hierarchy":[
        "tgn:2564518",
        "tgn:1000001",
        "tgn:7013686",
        "tgn:7012149",
        "tgn:7007517",
        "tgn:7029392"
    ],
    "tgn:id":2564518,
    "tgn:name":"Packardville",
    "tgn:placetype":[
        "aat:300008347"
    ]
},
  "bbox": [],
  "geometry": {"coordinates":[-72.3833,42.3333],"type":"Point"}
}