{
  "id": 2195004,
  "type": "Feature",
  "properties": {
    "tgn:hierarchy":[
        "tgn:2195004",
        "tgn:1000001",
        "tgn:1002934",
        "tgn:7012149",
        "tgn:7007565",
        "tgn:7029392"
    ],
    "tgn:id":2195004,
    "tgn:name":"Brighton Lake",
    "tgn:placetype":[
        "aat:300006191"
    ]
},
  "bbox": [],
  "geometry": {"coordinates":[-74.7667,40.9833],"type":"Point"}
}