{
  "id": 2719341,
  "type": "Feature",
  "properties": {
    "tgn:hierarchy":[
        "tgn:2719341",
        "tgn:1000001",
        "tgn:2124025",
        "tgn:7012149",
        "tgn:7007516",
        "tgn:7029392"
    ],
    "tgn:id":2719341,
    "tgn:name":"Three Bridges Branch",
    "tgn:placetype":[
        "aat:300008699"
    ]
},
  "bbox": [],
  "geometry": {"coordinates":[-75.9833,39.0333],"type":"Point"}
}