{
  "id": 7236072,
  "type": "Feature",
  "properties": {
    "tgn:hierarchy":[
        "tgn:7236072",
        "tgn:7002718",
        "tgn:7002715",
        "tgn:1000003",
        "tgn:1000074",
        "tgn:7029392"
    ],
    "tgn:id":7236072,
    "tgn:name":"Exokh\u00ed",
    "tgn:placetype":[
        "aat:300008347"
    ]
},
  "bbox": [],
  "geometry": {"coordinates":[21.866667,40.466667],"type":"Point"}
}