{
  "id": 2177831,
  "type": "Feature",
  "properties": {
    "tgn:hierarchy":[
        "tgn:2177831",
        "tgn:2000292",
        "tgn:1000001",
        "tgn:7012149",
        "tgn:7007248",
        "tgn:7029392"
    ],
    "tgn:id":2177831,
    "tgn:name":"Black Water Creek",
    "tgn:placetype":[
        "aat:300008706"
    ]
},
  "bbox": [],
  "geometry": {"coordinates":[-82.4333,31.7833],"type":"Point"}
}