{
  "id": 7294667,
  "type": "Feature",
  "properties": {
    "tgn:hierarchy":[
        "tgn:7294667",
        "tgn:7001122",
        "tgn:1000003",
        "tgn:7002765",
        "tgn:1000095",
        "tgn:7029392"
    ],
    "tgn:id":7294667,
    "tgn:name":"Vent, Punta d'es",
    "tgn:placetype":[
        "aat:300386846"
    ]
},
  "bbox": [],
  "geometry": {"coordinates":[3.216667,39.95],"type":"Point"}
}