{
  "id": 7016279,
  "type": "Feature",
  "properties": {
    "tgn:hierarchy":[
        "tgn:7016279",
        "tgn:1000001",
        "tgn:7012149",
        "tgn:2000514",
        "tgn:7007251",
        "tgn:7029392"
    ],
    "tgn:id":7016279,
    "tgn:name":"Menominee",
    "tgn:placetype":[
        "aat:300008347",
        "aat:300387016"
    ]
},
  "bbox": [],
  "geometry": {"coordinates":[-90.5167,42.4833],"type":"Point"}
}