<<<<<<< HEAD
{
  "id": 2338479,
  "type": "Feature",
  "properties": {
    "tgn:hierarchy":[
        "tgn:2338479",
        "tgn:1000001",
        "tgn:7006451",
        "tgn:7012149",
        "tgn:2000102",
        "tgn:7029392"
    ],
    "tgn:id":2338479,
    "tgn:name":"Fraguita Peak",
    "tgn:placetype":[
        "aat:300008798"
    ]
},
  "bbox": [],
  "geometry": {"coordinates":[-111.3167,31.5],"type":"Point"}
}
=======
{"geometry":{"type":"Point","coordinates":[-111.316700,31.500000]},"type":"Feature","properties":{"hierarchy":["tgn:2338479","tgn:1000001","tgn:7006451","tgn:7012149","tgn:2000102","tgn:7029392"],"placetype":["aat:300008798"],"id":2338479,"name:xx":"Fraguita Peak"}}
>>>>>>> 03f74aca74312dbeaf24d7e61306dd6a786dc3d0
