{
  "id": 2647916,
  "type": "Feature",
  "properties": {
    "tgn:hierarchy":[
        "tgn:2647916",
        "tgn:1000001",
        "tgn:7012149",
        "tgn:2001442",
        "tgn:7007566",
        "tgn:7029392"
    ],
    "tgn:id":2647916,
    "tgn:name":"Schoolhouse Canyon",
    "tgn:placetype":[
        "aat:300008761"
    ]
},
  "bbox": [],
  "geometry": {"coordinates":[-105.7167,33.4167],"type":"Point"}
}