<<<<<<< HEAD
{
  "id": 7351457,
  "type": "Feature",
  "properties": {
    "tgn:hierarchy":[
        "tgn:7351457",
        "tgn:1000001",
        "tgn:1001960",
        "tgn:7005560",
        "tgn:7029392"
    ],
    "tgn:id":7351457,
    "tgn:name":"Bomi",
    "tgn:placetype":[
        "aat:300008347"
    ]
},
  "bbox": [],
  "geometry": {"coordinates":[-109.666667,29.05],"type":"Point"}
}
=======
{"geometry":{"type":"Point","coordinates":[-109.666667,29.050000]},"type":"Feature","properties":{"hierarchy":["tgn:7351457","tgn:1000001","tgn:1001960","tgn:7005560","tgn:7029392"],"placetype":["aat:300008347"],"id":7351457,"name:xx":"Bomi"}}
>>>>>>> 03f74aca74312dbeaf24d7e61306dd6a786dc3d0
