{
  "id": 2667752,
  "type": "Feature",
  "properties": {
    "tgn:hierarchy":[
        "tgn:2667752",
        "tgn:1000001",
        "tgn:7012149",
        "tgn:2001714",
        "tgn:7007708",
        "tgn:7029392"
    ],
    "tgn:id":2667752,
    "tgn:name":"Skunk Butte",
    "tgn:placetype":[
        "aat:300008798"
    ]
},
  "bbox": [],
  "geometry": {"coordinates":[-121.55,42.5167],"type":"Point"}
}