{
  "id": 2180026,
  "type": "Feature",
  "properties": {
    "tgn:hierarchy":[
        "tgn:2180026",
        "tgn:1000001",
        "tgn:7012149",
        "tgn:7007713",
        "tgn:7029392"
    ],
    "tgn:id":2180026,
    "tgn:name":"Blind Creek",
    "tgn:placetype":[
        "aat:300008706"
    ]
},
  "bbox": [],
  "geometry": {"coordinates":[-96.7667,43.0833],"type":"Point"}
}