{
  "id": 7053691,
  "type": "Feature",
  "properties": {
    "tgn:hierarchy":[
        "tgn:7053691",
        "tgn:7004597",
        "tgn:1000003",
        "tgn:7008516",
        "tgn:1000080",
        "tgn:7029392"
    ],
    "tgn:id":7053691,
    "tgn:name":"Madonna dei Ponticelli",
    "tgn:placetype":[
        "aat:300008347"
    ]
},
  "bbox": [],
  "geometry": {"coordinates":[10.95,44.816667],"type":"Point"}
}