{
  "id": 2737987,
  "type": "Feature",
  "properties": {
    "tgn:hierarchy":[
        "tgn:2737987",
        "tgn:7006450",
        "tgn:1000001",
        "tgn:2124012",
        "tgn:7012149",
        "tgn:7029392"
    ],
    "tgn:id":2737987,
    "tgn:name":"Uganik River",
    "tgn:placetype":[
        "aat:300008707"
    ]
},
  "bbox": [],
  "geometry": {"coordinates":[-153.1333,57.4333],"type":"Point"}
}