{
  "id": 4009541,
  "type": "Feature",
  "properties": {
    "tgn:hierarchy":[
        "tgn:4009541",
        "tgn:1003530",
        "tgn:1000003",
        "tgn:1001780",
        "tgn:7029392"
    ],
    "tgn:id":4009541,
    "tgn:name":"S\u00e1zava",
    "tgn:placetype":[
        "aat:300008347"
    ]
},
  "bbox": [],
  "geometry": {"coordinates":[15.8667,49.5667],"type":"Point"}
}