{
  "id": 7187796,
  "type": "Feature",
  "properties": {
    "tgn:hierarchy":[
        "tgn:7187796",
        "tgn:1000003",
        "tgn:7003677",
        "tgn:7000084",
        "tgn:7029392"
    ],
    "tgn:id":7187796,
    "tgn:name":"Ettmann",
    "tgn:placetype":[
        "aat:300000206"
    ]
},
  "bbox": [],
  "geometry": {"coordinates":[7.35,51.783333],"type":"Point"}
}