{
  "id": 2328377,
  "type": "Feature",
  "properties": {
    "tgn:hierarchy":[
        "tgn:2328377",
        "tgn:1000001",
        "tgn:2001785",
        "tgn:7012149",
        "tgn:7007713",
        "tgn:7029392"
    ],
    "tgn:id":2328377,
    "tgn:name":"Fisher Creek",
    "tgn:placetype":[
        "aat:300008706"
    ]
},
  "bbox": [],
  "geometry": {"coordinates":[-100.45,45.7167],"type":"Point"}
}