<<<<<<< HEAD
{
  "id": 2400346,
  "type": "Feature",
  "properties": {
    "tgn:hierarchy":[
        "tgn:2400346",
        "tgn:1000001",
        "tgn:2000316",
        "tgn:7012149",
        "tgn:7007248",
        "tgn:7029392"
    ],
    "tgn:id":2400346,
    "tgn:name":"Horse Hammock",
    "tgn:placetype":[
        "aat:300008791"
    ]
},
  "bbox": [],
  "geometry": {"coordinates":[-81.0667,31.8167],"type":"Point"}
}
=======
{"geometry":{"type":"Point","coordinates":[-81.066700,31.816700]},"type":"Feature","properties":{"hierarchy":["tgn:2400346","tgn:1000001","tgn:2000316","tgn:7012149","tgn:7007248","tgn:7029392"],"placetype":["aat:300008791"],"id":2400346,"name:xx":"Horse Hammock"}}
>>>>>>> 03f74aca74312dbeaf24d7e61306dd6a786dc3d0
