{
  "id": 7045358,
  "type": "Feature",
  "properties": {
    "tgn:hierarchy":[
        "tgn:7045358",
        "tgn:7003006",
        "tgn:1000003",
        "tgn:7002997",
        "tgn:1000080",
        "tgn:7029392"
    ],
    "tgn:id":7045358,
    "tgn:name":"Fossacoccola",
    "tgn:placetype":[
        "aat:300008347"
    ]
},
  "bbox": [],
  "geometry": {"coordinates":[12.133333,45.133333],"type":"Point"}
}