<<<<<<< HEAD
{
  "id": 2154210,
  "type": "Feature",
  "properties": {
    "tgn:hierarchy":[
        "tgn:2154210",
        "tgn:1000001",
        "tgn:7012149",
        "tgn:1002517",
        "tgn:7007523",
        "tgn:7029392"
    ],
    "tgn:id":2154210,
    "tgn:name":"Bear Creek",
    "tgn:placetype":[
        "aat:300008706"
    ]
},
  "bbox": [],
  "geometry": {"coordinates":[-90.5333,38.45],"type":"Point"}
}
=======
{"geometry":{"type":"Point","coordinates":[-90.533300,38.450000]},"type":"Feature","properties":{"hierarchy":["tgn:2154210","tgn:1000001","tgn:7012149","tgn:1002517","tgn:7007523","tgn:7029392"],"placetype":["aat:300008706"],"id":2154210,"name:xx":"Bear Creek"}}
>>>>>>> 03f74aca74312dbeaf24d7e61306dd6a786dc3d0
