{
  "id": 2082117,
  "type": "Feature",
  "properties": {
    "tgn:hierarchy":[
        "tgn:2082117",
        "tgn:1000001",
        "tgn:7012149",
        "tgn:1002596",
        "tgn:7007706",
        "tgn:7029392"
    ],
    "tgn:id":2082117,
    "tgn:name":"Summit Station",
    "tgn:placetype":[
        "aat:300008347"
    ]
},
  "bbox": [],
  "geometry": {"coordinates":[-82.75,39.9833],"type":"Point"}
}