{
  "id": 2213011,
  "type": "Feature",
  "properties": {
    "tgn:hierarchy":[
        "tgn:2213011",
        "tgn:1000001",
        "tgn:7012149",
        "tgn:2001455",
        "tgn:7007566",
        "tgn:7029392"
    ],
    "tgn:id":2213011,
    "tgn:name":"Caballo Reservoir",
    "tgn:placetype":[
        "aat:300006191"
    ]
},
  "bbox": [],
  "geometry": {"coordinates":[-107.2833,32.8833],"type":"Point"}
}