{
  "id": 7030480,
  "type": "Feature",
  "properties": {
    "tgn:hierarchy":[
        "tgn:7030480",
        "tgn:7019048",
        "tgn:7002445",
        "tgn:1000003",
        "tgn:7029505",
        "tgn:7008591",
        "tgn:7029392"
    ],
    "tgn:id":7030480,
    "tgn:name":"Roughbirchworth",
    "tgn:placetype":[
        "aat:300008347"
    ]
},
  "bbox": [],
  "geometry": {"coordinates":[-1.61,53.501],"type":"Point"}
}