{
  "id": 7286728,
  "type": "Feature",
  "properties": {
    "tgn:hierarchy":[
        "tgn:7286728",
        "tgn:1001705",
        "tgn:1000049",
        "tgn:1000002",
        "tgn:7029392"
    ],
    "tgn:id":7286728,
    "tgn:name":"Guaqu\u00e9n",
    "tgn:placetype":[
        "aat:300008347"
    ]
},
  "bbox": [],
  "geometry": {"coordinates":[-71.716667,-35.116667],"type":"Point"}
}