<<<<<<< HEAD
{
  "id": 7481999,
  "type": "Feature",
  "properties": {
    "tgn:hierarchy":[
        "tgn:7481999",
        "tgn:1000004",
        "tgn:7490934",
        "tgn:1000141",
        "tgn:7029392"
    ],
    "tgn:id":7481999,
    "tgn:name":"Wujiu",
    "tgn:placetype":[
        "aat:300008347"
    ]
},
  "bbox": [],
  "geometry": {"coordinates":[120.275028,23.033315],"type":"Point"}
}
=======
{"geometry":{"type":"Point","coordinates":[120.275028,23.033315]},"type":"Feature","properties":{"hierarchy":["tgn:7481999","tgn:1000004","tgn:7490934","tgn:1000141","tgn:7029392"],"placetype":["aat:300008347"],"id":7481999,"name:xx":"Wujiu"}}
>>>>>>> 03f74aca74312dbeaf24d7e61306dd6a786dc3d0
