{
  "id": 7497981,
  "type": "Feature",
  "properties": {
    "tgn:hierarchy":[
        "tgn:7497981",
        "tgn:1000957",
        "tgn:1000004",
        "tgn:1000141",
        "tgn:7029392"
    ],
    "tgn:id":7497981,
    "tgn:name":"Xiding He",
    "tgn:placetype":[
        "aat:300008699"
    ]
},
  "bbox": [],
  "geometry": {"coordinates":[121.73472,25.132654],"type":"Point"}
}