<<<<<<< HEAD
{
  "id": 7350810,
  "type": "Feature",
  "properties": {
    "tgn:hierarchy":[
        "tgn:7350810",
        "tgn:1000001",
        "tgn:7005589",
        "tgn:7005560",
        "tgn:7029392"
    ],
    "tgn:id":7350810,
    "tgn:name":"Cabeza de Toro de Rafael Mart\u00ednez",
    "tgn:placetype":[
        "aat:300008347"
    ]
},
  "bbox": [],
  "geometry": {"coordinates":[-99.1,25.683333],"type":"Point"}
}
=======
{"geometry":{"type":"Point","coordinates":[-99.100000,25.683333]},"type":"Feature","properties":{"hierarchy":["tgn:7350810","tgn:1000001","tgn:7005589","tgn:7005560","tgn:7029392"],"placetype":["aat:300008347"],"id":7350810,"name:xx":"Cabeza de Toro de Rafael Mart\u00ednez"}}
>>>>>>> 03f74aca74312dbeaf24d7e61306dd6a786dc3d0
