{
  "id": 2177875,
  "type": "Feature",
  "properties": {
    "tgn:hierarchy":[
        "tgn:2177875",
        "tgn:1000001",
        "tgn:7012149",
        "tgn:2000892",
        "tgn:7007256",
        "tgn:7029392"
    ],
    "tgn:id":2177875,
    "tgn:name":"Black, Bayou",
    "tgn:placetype":[
        "aat:300008699"
    ]
},
  "bbox": [],
  "geometry": {"coordinates":[-91.5333,30.5833],"type":"Point"}
}