{
  "id": 2665572,
  "type": "Feature",
  "properties": {
    "tgn:hierarchy":[
        "tgn:2665572",
        "tgn:1000001",
        "tgn:7012149",
        "tgn:2001236",
        "tgn:7007523",
        "tgn:7029392"
    ],
    "tgn:id":2665572,
    "tgn:name":"Sinking Creek",
    "tgn:placetype":[
        "aat:300008706"
    ]
},
  "bbox": [],
  "geometry": {"coordinates":[-91.05,37.3833],"type":"Point"}
}