<<<<<<< HEAD
{
  "id": 2155065,
  "type": "Feature",
  "properties": {
    "tgn:hierarchy":[
        "tgn:2155065",
        "tgn:1000001",
        "tgn:7012149",
        "tgn:2000987",
        "tgn:7007520",
        "tgn:7029392"
    ],
    "tgn:id":2155065,
    "tgn:name":"Bear Lake",
    "tgn:placetype":[
        "aat:300008680"
    ]
},
  "bbox": [],
  "geometry": {"coordinates":[-85.35,44.0167],"type":"Point"}
}
=======
{"geometry":{"type":"Point","coordinates":[-85.350000,44.016700]},"type":"Feature","properties":{"hierarchy":["tgn:2155065","tgn:1000001","tgn:7012149","tgn:2000987","tgn:7007520","tgn:7029392"],"placetype":["aat:300008680"],"id":2155065,"name:xx":"Bear Lake"}}
>>>>>>> 03f74aca74312dbeaf24d7e61306dd6a786dc3d0
