{
  "id": 2786256,
  "type": "Feature",
  "properties": {
    "tgn:hierarchy":[
        "tgn:2786256",
        "tgn:1000001",
        "tgn:1002223",
        "tgn:7012149",
        "tgn:7007523",
        "tgn:7029392"
    ],
    "tgn:id":2786256,
    "tgn:name":"Youngs Creek",
    "tgn:placetype":[
        "aat:300008706"
    ]
},
  "bbox": [],
  "geometry": {"coordinates":[-91.9833,38.8333],"type":"Point"}
}