{
  "id": 7521035,
  "type": "Feature",
  "properties": {
    "tgn:hierarchy":[
        "tgn:7521035",
        "tgn:7001242",
        "tgn:7016833",
        "tgn:1001418",
        "tgn:7029392"
    ],
    "tgn:id":7521035,
    "tgn:name:en":"Jubb '\u0100fiyah",
    "tgn:placetype":[
        "aat:300006207"
    ]
},
  "bbox": [],
  "geometry": {"coordinates":[26.183333,29.566667],"type":"Point"}
}