{
  "id": 7474162,
  "type": "Feature",
  "properties": {
    "tgn:hierarchy":[
        "tgn:7474162",
        "tgn:1000004",
        "tgn:1000454",
        "tgn:1000141",
        "tgn:7029392"
    ],
    "tgn:id":7474162,
    "tgn:name":"Dingnei",
    "tgn:placetype":[
        "aat:300008347"
    ]
},
  "bbox": [],
  "geometry": {"coordinates":[121.753243,25.097397],"type":"Point"}
}