{
  "id": 1126961,
  "type": "Feature",
  "properties": {
    "tgn:hierarchy":[
        "tgn:1126961",
        "tgn:1000003",
        "tgn:7002883",
        "tgn:1000070",
        "tgn:7029392"
    ],
    "tgn:id":1126961,
    "tgn:name":"Mauldre",
    "tgn:placetype":[
        "aat:300008707"
    ]
},
  "bbox": [],
  "geometry": {"coordinates":[1.8167,48.9833],"type":"Point"}
}