{
  "id": 2251325,
  "type": "Feature",
  "properties": {
    "tgn:hierarchy":[
        "tgn:2251325",
        "tgn:1000001",
        "tgn:2002148",
        "tgn:7012149",
        "tgn:7007919",
        "tgn:7029392"
    ],
    "tgn:id":2251325,
    "tgn:name":"Combs Ridge",
    "tgn:placetype":[
        "aat:300266640"
    ]
},
  "bbox": [],
  "geometry": {"coordinates":[-82.0667,37.0667],"type":"Point"}
}