{
  "id": 2296702,
  "type": "Feature",
  "properties": {
    "tgn:hierarchy":[
        "tgn:2296702",
        "tgn:1000001",
        "tgn:7012149",
        "tgn:7007157",
        "tgn:1002972",
        "tgn:7029392"
    ],
    "tgn:id":2296702,
    "tgn:name":"Dry Creek",
    "tgn:placetype":[
        "aat:300008706"
    ]
},
  "bbox": [],
  "geometry": {"coordinates":[-118.9667,34.75],"type":"Point"}
}