{
  "id": 2519057,
  "type": "Feature",
  "properties": {
    "tgn:hierarchy":[
        "tgn:2519057",
        "tgn:1000001",
        "tgn:1002246",
        "tgn:7012149",
        "tgn:7007568",
        "tgn:7029392"
    ],
    "tgn:id":2519057,
    "tgn:name":"Moat, The",
    "tgn:placetype":[
        "aat:300008905"
    ]
},
  "bbox": [],
  "geometry": {"coordinates":[-76.6833,43.3333],"type":"Point"}
}