{
  "id": 2571545,
  "type": "Feature",
  "properties": {
    "tgn:hierarchy":[
        "tgn:2571545",
        "tgn:1000001",
        "tgn:2001581",
        "tgn:7012149",
        "tgn:7007705",
        "tgn:7029392"
    ],
    "tgn:id":2571545,
    "tgn:name":"Paulson Lake",
    "tgn:placetype":[
        "aat:300008680"
    ]
},
  "bbox": [],
  "geometry": {"coordinates":[-100.6833,47.9833],"type":"Point"}
}