{
  "id": 2453050,
  "type": "Feature",
  "properties": {
    "tgn:hierarchy":[
        "tgn:2453050",
        "tgn:1002149",
        "tgn:1000001",
        "tgn:7012149",
        "tgn:7007826",
        "tgn:7029392"
    ],
    "tgn:id":2453050,
    "tgn:name":"Little Caney Creek",
    "tgn:placetype":[
        "aat:300008706"
    ]
},
  "bbox": [],
  "geometry": {"coordinates":[-94.2667,31.1333],"type":"Point"}
}