<<<<<<< HEAD
{
  "id": 7357671,
  "type": "Feature",
  "properties": {
    "tgn:hierarchy":[
        "tgn:7357671",
        "tgn:1000001",
        "tgn:7005593",
        "tgn:7005560",
        "tgn:7029392"
    ],
    "tgn:id":7357671,
    "tgn:name":"Culata",
    "tgn:placetype":[
        "aat:300008347"
    ]
},
  "bbox": [],
  "geometry": {"coordinates":[-99.7,20.916667],"type":"Point"}
}
=======
{"geometry":{"type":"Point","coordinates":[-99.700000,20.916667]},"type":"Feature","properties":{"hierarchy":["tgn:7357671","tgn:1000001","tgn:7005593","tgn:7005560","tgn:7029392"],"placetype":["aat:300008347"],"id":7357671,"name:xx":"Culata"}}
>>>>>>> 03f74aca74312dbeaf24d7e61306dd6a786dc3d0
