{
  "id": 2623535,
  "type": "Feature",
  "properties": {
    "tgn:hierarchy":[
        "tgn:2623535",
        "tgn:1000001",
        "tgn:7012149",
        "tgn:2000474",
        "tgn:7007250",
        "tgn:7029392"
    ],
    "tgn:id":2623535,
    "tgn:name":"Rock Creek",
    "tgn:placetype":[
        "aat:300008706"
    ]
},
  "bbox": [],
  "geometry": {"coordinates":[-116.4167,44.05],"type":"Point"}
}