<<<<<<< HEAD
{
  "id": 7110023,
  "type": "Feature",
  "properties": {
    "tgn:hierarchy":[
        "tgn:7110023",
        "tgn:1000003",
        "tgn:7003676",
        "tgn:7000084",
        "tgn:7029392"
    ],
    "tgn:id":7110023,
    "tgn:name":"Reiherplate",
    "tgn:placetype":[
        "aat:300132350"
    ]
},
  "bbox": [],
  "geometry": {"coordinates":[8.483333,53.4],"type":"Point"}
}
=======
{"geometry":{"type":"Point","coordinates":[8.483333,53.400000]},"type":"Feature","properties":{"hierarchy":["tgn:7110023","tgn:1000003","tgn:7003676","tgn:7000084","tgn:7029392"],"placetype":["aat:300132350"],"id":7110023,"name:xx":"Reiherplate"}}
>>>>>>> 03f74aca74312dbeaf24d7e61306dd6a786dc3d0
