{
  "id": 2298958,
  "type": "Feature",
  "properties": {
    "tgn:hierarchy":[
        "tgn:2298958",
        "tgn:1000001",
        "tgn:7012149",
        "tgn:1002950",
        "tgn:7007568",
        "tgn:7029392"
    ],
    "tgn:id":2298958,
    "tgn:name":"Duboise Corner",
    "tgn:placetype":[
        "aat:300008347"
    ]
},
  "bbox": [],
  "geometry": {"coordinates":[-76.55,42.4833],"type":"Point"}
}