<<<<<<< HEAD
{
  "id": 7357329,
  "type": "Feature",
  "properties": {
    "tgn:hierarchy":[
        "tgn:7357329",
        "tgn:7005581",
        "tgn:1000001",
        "tgn:7005560",
        "tgn:7029392"
    ],
    "tgn:id":7357329,
    "tgn:name":"Carros de Green",
    "tgn:placetype":[
        "aat:300387007"
    ]
},
  "bbox": [],
  "geometry": {"coordinates":[-108.0,28.533333],"type":"Point"}
}
=======
{"geometry":{"type":"Point","coordinates":[-108.000000,28.533333]},"type":"Feature","properties":{"hierarchy":["tgn:7357329","tgn:7005581","tgn:1000001","tgn:7005560","tgn:7029392"],"placetype":["aat:300387007"],"id":7357329,"name:xx":"Carros de Green"}}
>>>>>>> 03f74aca74312dbeaf24d7e61306dd6a786dc3d0
