{
  "id": 2232434,
  "type": "Feature",
  "properties": {
    "tgn:hierarchy":[
        "tgn:2232434",
        "tgn:7006450",
        "tgn:1000001",
        "tgn:7012149",
        "tgn:2000086",
        "tgn:7029392"
    ],
    "tgn:id":2232434,
    "tgn:name":"Channel Rock",
    "tgn:placetype":[
        "aat:300008791"
    ]
},
  "bbox": [],
  "geometry": {"coordinates":[-147.8833,60.3833],"type":"Point"}
}