{
  "id": 7402787,
  "type": "Feature",
  "properties": {
    "tgn:hierarchy":[
        "tgn:7402787",
        "tgn:1000001",
        "tgn:1001937",
        "tgn:7005560",
        "tgn:7029392"
    ],
    "tgn:id":7402787,
    "tgn:name":"Vallarta",
    "tgn:placetype":[
        "aat:300008347"
    ]
},
  "bbox": [],
  "geometry": {"coordinates":[-87.066667,20.863889],"type":"Point"}
}