{
  "id": 1031012,
  "type": "Feature",
  "properties": {
    "tgn:hierarchy":[
        "tgn:1031012",
        "tgn:7002445",
        "tgn:1000003",
        "tgn:7012032",
        "tgn:7008591",
        "tgn:7029392"
    ],
    "tgn:id":1031012,
    "tgn:name:en":"Watchet",
    "tgn:placetype":[
        "aat:300008347"
    ]
},
  "bbox": [],
  "geometry": {"coordinates":[-3.327778,51.178889],"type":"Point"}
}