{
  "id": 2236509,
  "type": "Feature",
  "properties": {
    "tgn:hierarchy":[
        "tgn:2236509",
        "tgn:7002659",
        "tgn:1000001",
        "tgn:7012149",
        "tgn:2000053",
        "tgn:7029392"
    ],
    "tgn:id":2236509,
    "tgn:name":"Chicken Swamp Branch",
    "tgn:placetype":[
        "aat:300008699"
    ]
},
  "bbox": [],
  "geometry": {"coordinates":[-88.0667,33.4667],"type":"Point"}
}