{
  "id": 7548656,
  "type": "Feature",
  "properties": {
    "tgn:hierarchy":[
        "tgn:7548656",
        "tgn:1000004",
        "tgn:7000198",
        "tgn:7016694",
        "tgn:7029392"
    ],
    "tgn:id":7548656,
    "tgn:name:en":"Deppegurha",
    "tgn:placetype":[
        "aat:300008347"
    ]
},
  "bbox": [],
  "geometry": {"coordinates":[83.716667,19.383333],"type":"Point"}
}