{
  "id": 2632910,
  "type": "Feature",
  "properties": {
    "tgn:hierarchy":[
        "tgn:2632910",
        "tgn:1000001",
        "tgn:7012149",
        "tgn:2001706",
        "tgn:7007708",
        "tgn:7029392"
    ],
    "tgn:id":2632910,
    "tgn:name":"Ruckles",
    "tgn:placetype":[
        "aat:300008347"
    ]
},
  "bbox": [],
  "geometry": {"coordinates":[-123.3333,43.05],"type":"Point"}
}