{
  "id": 7168598,
  "type": "Feature",
  "properties": {
    "tgn:hierarchy":[
        "tgn:7168598",
        "tgn:1000003",
        "tgn:7003676",
        "tgn:7000084",
        "tgn:7029392"
    ],
    "tgn:id":7168598,
    "tgn:name":"Harrendorf",
    "tgn:placetype":[
        "aat:300008347"
    ]
},
  "bbox": [],
  "geometry": {"coordinates":[8.733333,53.35],"type":"Point"}
}