{
  "id": 2392759,
  "type": "Feature",
  "properties": {
    "tgn:hierarchy":[
        "tgn:2392759",
        "tgn:1000001",
        "tgn:7012149",
        "tgn:1002512",
        "tgn:7007252",
        "tgn:7029392"
    ],
    "tgn:id":2392759,
    "tgn:name":"Hobbs Ditch",
    "tgn:placetype":[
        "aat:300006075"
    ]
},
  "bbox": [],
  "geometry": {"coordinates":[-87.15,41.1833],"type":"Point"}
}