{
  "id": 7156056,
  "type": "Feature",
  "properties": {
    "tgn:hierarchy":[
        "tgn:7156056",
        "tgn:7003669",
        "tgn:1000003",
        "tgn:7000084",
        "tgn:7029392"
    ],
    "tgn:id":7156056,
    "tgn:name":"Kleingern",
    "tgn:placetype":[
        "aat:300387200"
    ]
},
  "bbox": [],
  "geometry": {"coordinates":[13.366667,48.533333],"type":"Point"}
}