{
  "id": 2168224,
  "type": "Feature",
  "properties": {
    "tgn:hierarchy":[
        "tgn:2168224",
        "tgn:1000001",
        "tgn:7016172",
        "tgn:7012149",
        "tgn:2000161",
        "tgn:7029392"
    ],
    "tgn:id":2168224,
    "tgn:name":"Big Fork",
    "tgn:placetype":[
        "aat:300008699"
    ]
},
  "bbox": [],
  "geometry": {"coordinates":[-94.0167,34.4333],"type":"Point"}
}