{
  "id": 7338989,
  "type": "Feature",
  "properties": {
    "tgn:hierarchy":[
        "tgn:7338989",
        "tgn:7002759",
        "tgn:7002845",
        "tgn:1000003",
        "tgn:1000095",
        "tgn:7029392"
    ],
    "tgn:id":7338989,
    "tgn:name":"El Castellar",
    "tgn:placetype":[
        "aat:300008347"
    ]
},
  "bbox": [],
  "geometry": {"coordinates":[-1.05,41.783333],"type":"Point"}
}