<<<<<<< HEAD
{
  "id": 2150507,
  "type": "Feature",
  "properties": {
    "tgn:hierarchy":[
        "tgn:2150507",
        "tgn:7013388",
        "tgn:1000001",
        "tgn:7012149",
        "tgn:7007517",
        "tgn:7029392"
    ],
    "tgn:id":2150507,
    "tgn:name":"Basin Pond Brook",
    "tgn:placetype":[
        "aat:300008699"
    ]
},
  "bbox": [],
  "geometry": {"coordinates":[-73.1667,42.3],"type":"Point"}
}
=======
{"geometry":{"type":"Point","coordinates":[-73.166700,42.300000]},"type":"Feature","properties":{"hierarchy":["tgn:2150507","tgn:7013388","tgn:1000001","tgn:7012149","tgn:7007517","tgn:7029392"],"placetype":["aat:300008699"],"id":2150507,"name:xx":"Basin Pond Brook"}}
>>>>>>> 03f74aca74312dbeaf24d7e61306dd6a786dc3d0
