{
  "id": 2680437,
  "type": "Feature",
  "properties": {
    "tgn:hierarchy":[
        "tgn:2680437",
        "tgn:1000001",
        "tgn:7012149",
        "tgn:2002371",
        "tgn:7007923",
        "tgn:7029392"
    ],
    "tgn:id":2680437,
    "tgn:name":"South Fork Willow Creek",
    "tgn:placetype":[
        "aat:300008706"
    ]
},
  "bbox": [],
  "geometry": {"coordinates":[-109.3833,43.15],"type":"Point"}
}