{
  "id": 2160641,
  "type": "Feature",
  "properties": {
    "tgn:hierarchy":[
        "tgn:2160641",
        "tgn:1000001",
        "tgn:2001941",
        "tgn:7012149",
        "tgn:7007826",
        "tgn:7029392"
    ],
    "tgn:id":2160641,
    "tgn:name":"Beitel Creek",
    "tgn:placetype":[
        "aat:300008706"
    ]
},
  "bbox": [],
  "geometry": {"coordinates":[-98.3833,29.5667],"type":"Point"}
}