{
  "id": 2083117,
  "type": "Feature",
  "properties": {
    "tgn:hierarchy":[
        "tgn:2083117",
        "tgn:1000001",
        "tgn:2001643",
        "tgn:7012149",
        "tgn:7007707",
        "tgn:7029392"
    ],
    "tgn:id":2083117,
    "tgn:name":"Dennis",
    "tgn:placetype":[
        "aat:300008347",
        "aat:300387210"
    ]
},
  "bbox": [],
  "geometry": {"coordinates":[-94.8833,36.5333],"type":"Point"}
}