{
  "id": 7314164,
  "type": "Feature",
  "properties": {
    "tgn:hierarchy":[
        "tgn:7314164",
        "tgn:1001708",
        "tgn:1000049",
        "tgn:1000002",
        "tgn:7029392"
    ],
    "tgn:id":7314164,
    "tgn:name":"Los Maitenes",
    "tgn:placetype":[
        "aat:300008347"
    ]
},
  "bbox": [],
  "geometry": {"coordinates":[-70.366667,-33.316667],"type":"Point"}
}