{
  "id": 2212630,
  "type": "Feature",
  "properties": {
    "tgn:hierarchy":[
        "tgn:2212630",
        "tgn:1000001",
        "tgn:7012149",
        "tgn:2001619",
        "tgn:7007706",
        "tgn:7029392"
    ],
    "tgn:id":2212630,
    "tgn:name":"Byrne",
    "tgn:placetype":[
        "aat:300008347"
    ]
},
  "bbox": [],
  "geometry": {"coordinates":[-81.4667,39.8333],"type":"Point"}
}