{
  "id": 1031071,
  "type": "Feature",
  "properties": {
    "tgn:hierarchy":[
        "tgn:1031071",
        "tgn:7002445",
        "tgn:1000003",
        "tgn:7008132",
        "tgn:7008591",
        "tgn:7029392"
    ],
    "tgn:id":1031071,
    "tgn:name":"Westbury-on-Severn",
    "tgn:placetype":[
        "aat:300008347",
        "aat:300008372"
    ]
},
  "bbox": [],
  "geometry": {"coordinates":[-2.416667,51.816667],"type":"Point"}
}