<<<<<<< HEAD
{
  "id": 7480809,
  "type": "Feature",
  "properties": {
    "tgn:hierarchy":[
        "tgn:7480809",
        "tgn:7001010",
        "tgn:1000004",
        "tgn:1000141",
        "tgn:7029392"
    ],
    "tgn:id":7480809,
    "tgn:name":"Shoufeng Tifang",
    "tgn:placetype":[
        "aat:300006156"
    ]
},
  "bbox": [],
  "geometry": {"coordinates":[121.537222,23.861111],"type":"Point"}
}
=======
{"geometry":{"type":"Point","coordinates":[121.537222,23.861111]},"type":"Feature","properties":{"hierarchy":["tgn:7480809","tgn:7001010","tgn:1000004","tgn:1000141","tgn:7029392"],"placetype":["aat:300006156"],"id":7480809,"name:xx":"Shoufeng Tifang"}}
>>>>>>> 03f74aca74312dbeaf24d7e61306dd6a786dc3d0
