{
  "id": 2751777,
  "type": "Feature",
  "properties": {
    "tgn:hierarchy":[
        "tgn:2751777",
        "tgn:1000001",
        "tgn:2001786",
        "tgn:7012149",
        "tgn:7007713",
        "tgn:7029392"
    ],
    "tgn:id":2751777,
    "tgn:name":"Warren Gulch Spring",
    "tgn:placetype":[
        "aat:300008697"
    ]
},
  "bbox": [],
  "geometry": {"coordinates":[-103.7167,43.75],"type":"Point"}
}