{
  "id": 7151540,
  "type": "Feature",
  "properties": {
    "tgn:hierarchy":[
        "tgn:7151540",
        "tgn:1000003",
        "tgn:7003688",
        "tgn:7000084",
        "tgn:7029392"
    ],
    "tgn:id":7151540,
    "tgn:name":"Kattberg",
    "tgn:placetype":[
        "aat:300008347"
    ]
},
  "bbox": [],
  "geometry": {"coordinates":[9.616667,54.766667],"type":"Point"}
}