<<<<<<< HEAD
{
  "id": 2405557,
  "type": "Feature",
  "properties": {
    "tgn:hierarchy":[
        "tgn:2405557",
        "tgn:1000001",
        "tgn:2001481",
        "tgn:7012149",
        "tgn:7007709",
        "tgn:7029392"
    ],
    "tgn:id":2405557,
    "tgn:name":"Hughes Hollow",
    "tgn:placetype":[
        "aat:300008761"
    ]
},
  "bbox": [],
  "geometry": {"coordinates":[-84.0333,35.0],"type":"Point"}
}
=======
{"geometry":{"type":"Point","coordinates":[-84.033300,35.000000]},"type":"Feature","properties":{"hierarchy":["tgn:2405557","tgn:1000001","tgn:2001481","tgn:7012149","tgn:7007709","tgn:7029392"],"placetype":["aat:300008761"],"id":2405557,"name:xx":"Hughes Hollow"}}
>>>>>>> 03f74aca74312dbeaf24d7e61306dd6a786dc3d0
