{
  "id": 2341360,
  "type": "Feature",
  "properties": {
    "tgn:hierarchy":[
        "tgn:2341360",
        "tgn:1000001",
        "tgn:2001702",
        "tgn:7012149",
        "tgn:7007708",
        "tgn:7029392"
    ],
    "tgn:id":2341360,
    "tgn:name":"Frog Creek",
    "tgn:placetype":[
        "aat:300008706"
    ]
},
  "bbox": [],
  "geometry": {"coordinates":[-123.9167,43.4833],"type":"Point"}
}