{
  "id": 7341188,
  "type": "Feature",
  "properties": {
    "tgn:hierarchy":[
        "tgn:7341188",
        "tgn:7002834",
        "tgn:1000003",
        "tgn:7002786",
        "tgn:1000095",
        "tgn:7029392"
    ],
    "tgn:id":7341188,
    "tgn:name":"Bri\u00f1a, R\u00edo",
    "tgn:placetype":[
        "aat:300008699"
    ]
},
  "bbox": [],
  "geometry": {"coordinates":[-8.716667,41.983333],"type":"Point"}
}