{
  "id": 2276955,
  "type": "Feature",
  "properties": {
    "tgn:hierarchy":[
        "tgn:2276955",
        "tgn:1000001",
        "tgn:7012149",
        "tgn:2002125",
        "tgn:7007827",
        "tgn:7029392"
    ],
    "tgn:id":2276955,
    "tgn:name":"Davis Canyon",
    "tgn:placetype":[
        "aat:300008761"
    ]
},
  "bbox": [],
  "geometry": {"coordinates":[-111.5667,40.3167],"type":"Point"}
}