{
  "id": 2300038,
  "type": "Feature",
  "properties": {
    "tgn:hierarchy":[
        "tgn:2300038",
        "tgn:1000001",
        "tgn:7012149",
        "tgn:2001892",
        "tgn:7007825",
        "tgn:7029392"
    ],
    "tgn:id":2300038,
    "tgn:name":"Dug Hollow",
    "tgn:placetype":[
        "aat:300008761"
    ]
},
  "bbox": [],
  "geometry": {"coordinates":[-85.95,36.45],"type":"Point"}
}