{
  "id": 7324030,
  "type": "Feature",
  "properties": {
    "tgn:hierarchy":[
        "tgn:7324030",
        "tgn:7002844",
        "tgn:7030216",
        "tgn:1000003",
        "tgn:1000095",
        "tgn:7029392"
    ],
    "tgn:id":7324030,
    "tgn:name":"Santas Creus",
    "tgn:placetype":[
        "aat:300008347"
    ]
},
  "bbox": [],
  "geometry": {"coordinates":[1.363598,41.346306],"type":"Point"}
}