{
  "id": 7155758,
  "type": "Feature",
  "properties": {
    "tgn:hierarchy":[
        "tgn:7155758",
        "tgn:7003669",
        "tgn:1000003",
        "tgn:7000084",
        "tgn:7029392"
    ],
    "tgn:id":7155758,
    "tgn:name":"Kenzen-K\u00f6pfel",
    "tgn:placetype":[
        "aat:300008795"
    ]
},
  "bbox": [],
  "geometry": {"coordinates":[10.85,47.566667],"type":"Point"}
}