{
  "id": 2499991,
  "type": "Feature",
  "properties": {
    "tgn:hierarchy":[
        "tgn:2499991",
        "tgn:7002659",
        "tgn:1000001",
        "tgn:7012149",
        "tgn:2000028",
        "tgn:7029392"
    ],
    "tgn:id":2499991,
    "tgn:name":"McCracken Mountain",
    "tgn:placetype":[
        "aat:300008798"
    ]
},
  "bbox": [],
  "geometry": {"coordinates":[-87.7833,33.5833],"type":"Point"}
}