{
  "id": 2079742,
  "type": "Feature",
  "properties": {
    "tgn:hierarchy":[
        "tgn:2079742",
        "tgn:1000001",
        "tgn:1002295",
        "tgn:7012149",
        "tgn:7007706",
        "tgn:7029392"
    ],
    "tgn:id":2079742,
    "tgn:name":"Glasgow",
    "tgn:placetype":[
        "aat:300008347"
    ]
},
  "bbox": [],
  "geometry": {"coordinates":[-80.6833,40.65],"type":"Point"}
}