<<<<<<< HEAD
{
  "id": 7488906,
  "type": "Feature",
  "properties": {
    "tgn:hierarchy":[
        "tgn:7488906",
        "tgn:1000004",
        "tgn:1000454",
        "tgn:1000141",
        "tgn:7029392"
    ],
    "tgn:id":7488906,
    "tgn:name":"Hutou Shan",
    "tgn:placetype":[
        "aat:300387002"
    ]
},
  "bbox": [],
  "geometry": {"coordinates":[121.463789,25.172293],"type":"Point"}
}
=======
{"geometry":{"type":"Point","coordinates":[121.463789,25.172293]},"type":"Feature","properties":{"hierarchy":["tgn:7488906","tgn:1000004","tgn:1000454","tgn:1000141","tgn:7029392"],"placetype":["aat:300387002"],"id":7488906,"name:xx":"Hutou Shan"}}
>>>>>>> 03f74aca74312dbeaf24d7e61306dd6a786dc3d0
