{
  "id": 2404458,
  "type": "Feature",
  "properties": {
    "tgn:hierarchy":[
        "tgn:2404458",
        "tgn:1000001",
        "tgn:7012149",
        "tgn:1002873",
        "tgn:7007568",
        "tgn:7029392"
    ],
    "tgn:id":2404458,
    "tgn:name":"Hubbard Hill",
    "tgn:placetype":[
        "aat:300008798"
    ]
},
  "bbox": [],
  "geometry": {"coordinates":[-74.3333,42.4333],"type":"Point"}
}