<<<<<<< HEAD
{
  "id": 2404458,
  "type": "Feature",
  "properties": {
    "tgn:hierarchy":[
        "tgn:2404458",
        "tgn:1000001",
        "tgn:7012149",
        "tgn:1002873",
        "tgn:7007568",
        "tgn:7029392"
    ],
    "tgn:id":2404458,
    "tgn:name":"Hubbard Hill",
    "tgn:placetype":[
        "aat:300008798"
    ]
},
  "bbox": [],
  "geometry": {"coordinates":[-74.3333,42.4333],"type":"Point"}
}
=======
{"geometry":{"type":"Point","coordinates":[-74.333300,42.433300]},"type":"Feature","properties":{"hierarchy":["tgn:2404458","tgn:1000001","tgn:7012149","tgn:1002873","tgn:7007568","tgn:7029392"],"placetype":["aat:300008798"],"id":2404458,"name:xx":"Hubbard Hill"}}
>>>>>>> 03f74aca74312dbeaf24d7e61306dd6a786dc3d0
