{
  "id": 7064545,
  "type": "Feature",
  "properties": {
    "tgn:hierarchy":[
        "tgn:7064545",
        "tgn:7003692",
        "tgn:1000003",
        "tgn:7000084",
        "tgn:7029392"
    ],
    "tgn:id":7064545,
    "tgn:name":"Unterambringen",
    "tgn:placetype":[
        "aat:300008347"
    ]
},
  "bbox": [],
  "geometry": {"coordinates":[7.733333,47.916667],"type":"Point"}
}