{
  "id": 7040187,
  "type": "Feature",
  "properties": {
    "tgn:hierarchy":[
        "tgn:7040187",
        "tgn:7005126",
        "tgn:1000003",
        "tgn:7003120",
        "tgn:1000080",
        "tgn:7029392"
    ],
    "tgn:id":7040187,
    "tgn:name":"Sautron, T\u00eate de",
    "tgn:placetype":[
        "aat:300008798"
    ]
},
  "bbox": [],
  "geometry": {"coordinates":[6.883333,44.483333],"type":"Point"}
}