{
  "id": 2249559,
  "type": "Feature",
  "properties": {
    "tgn:hierarchy":[
        "tgn:2249559",
        "tgn:1000001",
        "tgn:2000923",
        "tgn:7012149",
        "tgn:7007515",
        "tgn:7029392"
    ],
    "tgn:id":2249559,
    "tgn:name":"Coles",
    "tgn:placetype":[
        "aat:300008347"
    ]
},
  "bbox": [],
  "geometry": {"coordinates":[-69.4833,44.45],"type":"Point"}
}