{
  "id": 2570304,
  "type": "Feature",
  "properties": {
    "tgn:hierarchy":[
        "tgn:2570304",
        "tgn:1000001",
        "tgn:7012149",
        "tgn:2000208",
        "tgn:7007158",
        "tgn:7029392"
    ],
    "tgn:id":2570304,
    "tgn:name":"Pat Canyon Reservoir",
    "tgn:placetype":[
        "aat:300006191"
    ]
},
  "bbox": [],
  "geometry": {"coordinates":[-108.6667,37.85],"type":"Point"}
}