{
  "id": 7238574,
  "type": "Feature",
  "properties": {
    "tgn:hierarchy":[
        "tgn:7238574",
        "tgn:7003456",
        "tgn:1000003",
        "tgn:1000063",
        "tgn:7018236",
        "tgn:7029392"
    ],
    "tgn:id":7238574,
    "tgn:name":"Gallifort",
    "tgn:placetype":[
        "aat:300008347"
    ]
},
  "bbox": [],
  "geometry": {"coordinates":[4.459906,51.223982],"type":"Point"}
}