{
  "id": 7504070,
  "type": "Feature",
  "properties": {
    "tgn:hierarchy":[
        "tgn:7504070",
        "tgn:1008380",
        "tgn:7000507",
        "tgn:1000226",
        "tgn:1000006",
        "tgn:7029392"
    ],
    "tgn:id":7504070,
    "tgn:name:en":"Wekaweka",
    "tgn:placetype":[
        "aat:300008347"
    ]
},
  "bbox": [],
  "geometry": {"coordinates":[173.55,-35.566667],"type":"Point"}
}