{
  "id": 2147402,
  "type": "Feature",
  "properties": {
    "tgn:hierarchy":[
        "tgn:2147402",
        "tgn:1000001",
        "tgn:7012149",
        "tgn:1002793",
        "tgn:7007240",
        "tgn:7029392"
    ],
    "tgn:id":2147402,
    "tgn:name":"Barber Branch",
    "tgn:placetype":[
        "aat:300008699"
    ]
},
  "bbox": [],
  "geometry": {"coordinates":[-81.8167,27.8333],"type":"Point"}
}