{
  "id": 2495480,
  "type": "Feature",
  "properties": {
    "tgn:hierarchy":[
        "tgn:2495480",
        "tgn:1000001",
        "tgn:2001939",
        "tgn:7012149",
        "tgn:7007826",
        "tgn:7029392"
    ],
    "tgn:id":2495480,
    "tgn:name":"Marys Creek",
    "tgn:placetype":[
        "aat:300008706"
    ]
},
  "bbox": [],
  "geometry": {"coordinates":[-99.3167,33.4833],"type":"Point"}
}