<<<<<<< HEAD
{
  "id": 2766237,
  "type": "Feature",
  "properties": {
    "tgn:hierarchy":[
        "tgn:2766237",
        "tgn:1000001",
        "tgn:7012149",
        "tgn:2002333",
        "tgn:7007922",
        "tgn:7029392"
    ],
    "tgn:id":2766237,
    "tgn:name":"White Lake Creek",
    "tgn:placetype":[
        "aat:300008706"
    ]
},
  "bbox": [],
  "geometry": {"coordinates":[-88.75,45.15],"type":"Point"}
}
=======
{"geometry":{"type":"Point","coordinates":[-88.750000,45.150000]},"type":"Feature","properties":{"hierarchy":["tgn:2766237","tgn:1000001","tgn:7012149","tgn:2002333","tgn:7007922","tgn:7029392"],"placetype":["aat:300008706"],"id":2766237,"name:xx":"White Lake Creek"}}
>>>>>>> 03f74aca74312dbeaf24d7e61306dd6a786dc3d0
