{
  "id": 2564747,
  "type": "Feature",
  "properties": {
    "tgn:hierarchy":[
        "tgn:2564747",
        "tgn:1000001",
        "tgn:7012149",
        "tgn:7007251",
        "tgn:7029392"
    ],
    "tgn:id":2564747,
    "tgn:name":"Paddock Creek",
    "tgn:placetype":[
        "aat:300008706"
    ]
},
  "bbox": [],
  "geometry": {"coordinates":[-89.9167,39.0667],"type":"Point"}
}