{
  "id": 2554252,
  "type": "Feature",
  "properties": {
    "tgn:hierarchy":[
        "tgn:2554252",
        "tgn:1000001",
        "tgn:7012149",
        "tgn:2002125",
        "tgn:7007827",
        "tgn:7029392"
    ],
    "tgn:id":2554252,
    "tgn:name":"Oak Springs Hollow",
    "tgn:placetype":[
        "aat:300008761"
    ]
},
  "bbox": [],
  "geometry": {"coordinates":[-112.0833,40.4333],"type":"Point"}
}