{
  "id": 7237326,
  "type": "Feature",
  "properties": {
    "tgn:hierarchy":[
        "tgn:7237326",
        "tgn:7002681",
        "tgn:7001395",
        "tgn:1000003",
        "tgn:1000074",
        "tgn:7029392"
    ],
    "tgn:id":7237326,
    "tgn:name":"\u00c1gioi The\u00f3doroi, \u00c1kra",
    "tgn:placetype":[
        "aat:300008850"
    ]
},
  "bbox": [],
  "geometry": {"coordinates":[23.138448,37.922775],"type":"Point"}
}