{
  "id": 7592471,
  "type": "Feature",
  "properties": {
    "tgn:hierarchy":[
        "tgn:7592471",
        "tgn:1000004",
        "tgn:7000198",
        "tgn:7000799",
        "tgn:7029392"
    ],
    "tgn:id":7592471,
    "tgn:name:en":"Grauri",
    "tgn:placetype":[
        "aat:300008347"
    ]
},
  "bbox": [],
  "geometry": {"coordinates":[74.177778,33.168056],"type":"Point"}
}