<<<<<<< HEAD
{
  "id": 2764331,
  "type": "Feature",
  "properties": {
    "tgn:hierarchy":[
        "tgn:2764331",
        "tgn:1000001",
        "tgn:7012149",
        "tgn:2000808",
        "tgn:7007255",
        "tgn:7029392"
    ],
    "tgn:id":2764331,
    "tgn:name":"Whetstone Branch",
    "tgn:placetype":[
        "aat:300008699"
    ]
},
  "bbox": [],
  "geometry": {"coordinates":[-84.3,36.9667],"type":"Point"}
}
=======
{"geometry":{"type":"Point","coordinates":[-84.300000,36.966700]},"type":"Feature","properties":{"hierarchy":["tgn:2764331","tgn:1000001","tgn:7012149","tgn:2000808","tgn:7007255","tgn:7029392"],"placetype":["aat:300008699"],"id":2764331,"name:xx":"Whetstone Branch"}}
>>>>>>> 03f74aca74312dbeaf24d7e61306dd6a786dc3d0
