{
  "id": 7291036,
  "type": "Feature",
  "properties": {
    "tgn:hierarchy":[
        "tgn:7291036",
        "tgn:1001702",
        "tgn:1000049",
        "tgn:1000002",
        "tgn:7029392"
    ],
    "tgn:id":7291036,
    "tgn:name":"Cuevas, Punta",
    "tgn:placetype":[
        "aat:300386846"
    ]
},
  "bbox": [],
  "geometry": {"coordinates":[-72.616667,-51.916667],"type":"Point"}
}