<<<<<<< HEAD
{
  "id": 2155888,
  "type": "Feature",
  "properties": {
    "tgn:hierarchy":[
        "tgn:2155888",
        "tgn:1000001",
        "tgn:7012149",
        "tgn:7007157",
        "tgn:1002869",
        "tgn:7029392"
    ],
    "tgn:id":2155888,
    "tgn:name":"Bear Valley",
    "tgn:placetype":[
        "aat:300008761"
    ]
},
  "bbox": [],
  "geometry": {"coordinates":[-121.85,37.0167],"type":"Point"}
}
=======
{"geometry":{"type":"Point","coordinates":[-121.850000,37.016700]},"type":"Feature","properties":{"hierarchy":["tgn:2155888","tgn:1000001","tgn:7012149","tgn:7007157","tgn:1002869","tgn:7029392"],"placetype":["aat:300008761"],"id":2155888,"name:xx":"Bear Valley"}}
>>>>>>> 03f74aca74312dbeaf24d7e61306dd6a786dc3d0
