{
  "id": 7584064,
  "type": "Feature",
  "properties": {
    "tgn:hierarchy":[
        "tgn:7584064",
        "tgn:1000004",
        "tgn:7000198",
        "tgn:7016883",
        "tgn:7029392"
    ],
    "tgn:id":7584064,
    "tgn:name:en":"Taura",
    "tgn:placetype":[
        "aat:300008347"
    ]
},
  "bbox": [],
  "geometry": {"coordinates":[76.587658,30.214657],"type":"Point"}
}