{
  "id": 2154155,
  "type": "Feature",
  "properties": {
    "tgn:hierarchy":[
        "tgn:2154155",
        "tgn:1002147",
        "tgn:1000001",
        "tgn:7012149",
        "tgn:7007255",
        "tgn:7029392"
    ],
    "tgn:id":2154155,
    "tgn:name":"Bear Creek",
    "tgn:placetype":[
        "aat:300008706"
    ]
},
  "bbox": [],
  "geometry": {"coordinates":[-84.9667,37.95],"type":"Point"}
}