<<<<<<< HEAD
{
  "id": 2152595,
  "type": "Feature",
  "properties": {
    "tgn:hierarchy":[
        "tgn:2152595",
        "tgn:1000001",
        "tgn:1002369",
        "tgn:7012149",
        "tgn:7007251",
        "tgn:7029392"
    ],
    "tgn:id":2152595,
    "tgn:name":"Bayle City",
    "tgn:placetype":[
        "aat:300008347"
    ]
},
  "bbox": [],
  "geometry": {"coordinates":[-89.15,39.1],"type":"Point"}
}
=======
{"geometry":{"type":"Point","coordinates":[-89.150000,39.100000]},"type":"Feature","properties":{"hierarchy":["tgn:2152595","tgn:1000001","tgn:1002369","tgn:7012149","tgn:7007251","tgn:7029392"],"placetype":["aat:300008347"],"id":2152595,"name:xx":"Bayle City"}}
>>>>>>> 03f74aca74312dbeaf24d7e61306dd6a786dc3d0
