{
  "id": 7057132,
  "type": "Feature",
  "properties": {
    "tgn:hierarchy":[
        "tgn:7057132",
        "tgn:1001730",
        "tgn:1000003",
        "tgn:7003121",
        "tgn:1000080",
        "tgn:7029392"
    ],
    "tgn:id":7057132,
    "tgn:name":"Bannari d'Usellus",
    "tgn:placetype":[
        "aat:300008347"
    ]
},
  "bbox": [],
  "geometry": {"coordinates":[8.819444,39.796944],"type":"Point"}
}