{
  "id": 2091742,
  "type": "Feature",
  "properties": {
    "tgn:hierarchy":[
        "tgn:2091742",
        "tgn:1000001",
        "tgn:1002213",
        "tgn:7012149",
        "tgn:7007710",
        "tgn:7029392"
    ],
    "tgn:id":2091742,
    "tgn:name":"Penndel",
    "tgn:placetype":[
        "aat:300008347"
    ]
},
  "bbox": [],
  "geometry": {"coordinates":[-74.9167,40.15],"type":"Point"}
}