{
  "id": 7286832,
  "type": "Feature",
  "properties": {
    "tgn:hierarchy":[
        "tgn:7286832",
        "tgn:1001623",
        "tgn:1000049",
        "tgn:1000002",
        "tgn:7029392"
    ],
    "tgn:id":7286832,
    "tgn:name":"Guayanec, Isla",
    "tgn:placetype":[
        "aat:300008791"
    ]
},
  "bbox": [],
  "geometry": {"coordinates":[-73.433333,-44.75],"type":"Point"}
}