{
  "id": 2676144,
  "type": "Feature",
  "properties": {
    "tgn:hierarchy":[
        "tgn:2676144",
        "tgn:1000001",
        "tgn:7012149",
        "tgn:2000350",
        "tgn:7007248",
        "tgn:7029392"
    ],
    "tgn:id":2676144,
    "tgn:name":"Sosby Pond",
    "tgn:placetype":[
        "aat:300006191"
    ]
},
  "bbox": [],
  "geometry": {"coordinates":[-83.2667,34.4167],"type":"Point"}
}