{
  "id": 7443131,
  "type": "Feature",
  "properties": {
    "tgn:hierarchy":[
        "tgn:7443131",
        "tgn:7019094",
        "tgn:7002444",
        "tgn:1000003",
        "tgn:7008591",
        "tgn:7029392"
    ],
    "tgn:id":7443131,
    "tgn:name:en":"Whitehouse",
    "tgn:placetype":[
        "aat:300008347"
    ]
},
  "bbox": [],
  "geometry": {"coordinates":[-5.483333,55.783333],"type":"Point"}
}