{
  "id": 7208440,
  "type": "Feature",
  "properties": {
    "tgn:hierarchy":[
        "tgn:7208440",
        "tgn:7003669",
        "tgn:1000003",
        "tgn:7000084",
        "tgn:7029392"
    ],
    "tgn:id":7208440,
    "tgn:name":"Beham",
    "tgn:placetype":[
        "aat:300000206"
    ]
},
  "bbox": [],
  "geometry": {"coordinates":[11.833333,47.783333],"type":"Point"}
}