{
  "id": 2392680,
  "type": "Feature",
  "properties": {
    "tgn:hierarchy":[
        "tgn:2392680",
        "tgn:1000001",
        "tgn:2001424",
        "tgn:7012149",
        "tgn:7007564",
        "tgn:7029392"
    ],
    "tgn:id":2392680,
    "tgn:name":"Hobart Hill",
    "tgn:placetype":[
        "aat:300008798"
    ]
},
  "bbox": [],
  "geometry": {"coordinates":[-71.8167,43.6833],"type":"Point"}
}