{
  "id": 7129507,
  "type": "Feature",
  "properties": {
    "tgn:hierarchy":[
        "tgn:7129507",
        "tgn:1000003",
        "tgn:7003688",
        "tgn:7000084",
        "tgn:7029392"
    ],
    "tgn:id":7129507,
    "tgn:name":"Mannecker",
    "tgn:placetype":[
        "aat:300008347"
    ]
},
  "bbox": [],
  "geometry": {"coordinates":[9.133333,54.283333],"type":"Point"}
}