{
  "id": 7471017,
  "type": "Feature",
  "properties": {
    "tgn:hierarchy":[
        "tgn:7471017",
        "tgn:1000004",
        "tgn:7001014",
        "tgn:1000141",
        "tgn:7029392"
    ],
    "tgn:id":7471017,
    "tgn:name":"Erlun",
    "tgn:placetype":[
        "aat:300008347"
    ]
},
  "bbox": [],
  "geometry": {"coordinates":[120.413397,23.770454],"type":"Point"}
}