<<<<<<< HEAD
{
  "id": 2158125,
  "type": "Feature",
  "properties": {
    "tgn:hierarchy":[
        "tgn:2158125",
        "tgn:1000001",
        "tgn:7012149",
        "tgn:1003008",
        "tgn:7007710",
        "tgn:7029392"
    ],
    "tgn:id":2158125,
    "tgn:name":"Beaver Pond",
    "tgn:placetype":[
        "aat:300006191"
    ]
},
  "bbox": [],
  "geometry": {"coordinates":[-75.4,41.8833],"type":"Point"}
}
=======
{"geometry":{"type":"Point","coordinates":[-75.400000,41.883300]},"type":"Feature","properties":{"hierarchy":["tgn:2158125","tgn:1000001","tgn:7012149","tgn:1003008","tgn:7007710","tgn:7029392"],"placetype":["aat:300006191"],"id":2158125,"name:xx":"Beaver Pond"}}
>>>>>>> 03f74aca74312dbeaf24d7e61306dd6a786dc3d0
