{
  "id": 7522182,
  "type": "Feature",
  "properties": {
    "tgn:hierarchy":[
        "tgn:7522182",
        "tgn:7001242",
        "tgn:7016833",
        "tgn:7001336",
        "tgn:7029392"
    ],
    "tgn:id":7522182,
    "tgn:name":"Ruways\u0101t Ab\u016b R\u016bthah",
    "tgn:placetype":[
        "aat:300008798"
    ]
},
  "bbox": [],
  "geometry": {"coordinates":[33.846111,29.712778],"type":"Point"}
}