<<<<<<< HEAD
{
  "id": 2761583,
  "type": "Feature",
  "properties": {
    "tgn:hierarchy":[
        "tgn:2761583",
        "tgn:7030516",
        "tgn:7006450",
        "tgn:1000001",
        "tgn:7012149",
        "tgn:7029392"
    ],
    "tgn:id":2761583,
    "tgn:name":"West Peak",
    "tgn:placetype":[
        "aat:300008798"
    ]
},
  "bbox": [],
  "geometry": {"coordinates":[173.2,52.9167],"type":"Point"}
}
=======
{"geometry":{"type":"Point","coordinates":[173.200000,52.916700]},"type":"Feature","properties":{"hierarchy":["tgn:2761583","tgn:7030516","tgn:7006450","tgn:1000001","tgn:7012149","tgn:7029392"],"placetype":["aat:300008798"],"id":2761583,"name:xx":"West Peak"}}
>>>>>>> 03f74aca74312dbeaf24d7e61306dd6a786dc3d0
