{
  "id": 7232304,
  "type": "Feature",
  "properties": {
    "tgn:hierarchy":[
        "tgn:7232304",
        "tgn:7002715",
        "tgn:7002729",
        "tgn:1000003",
        "tgn:1000074",
        "tgn:7029392"
    ],
    "tgn:id":7232304,
    "tgn:name":"Ko\u00fakkos",
    "tgn:placetype":[
        "aat:300008347"
    ]
},
  "bbox": [],
  "geometry": {"coordinates":[22.515,40.384167],"type":"Point"}
}