{
  "id": 2094583,
  "type": "Feature",
  "properties": {
    "tgn:hierarchy":[
        "tgn:2094583",
        "tgn:1000001",
        "tgn:7012149",
        "tgn:1002612",
        "tgn:7007710",
        "tgn:7029392"
    ],
    "tgn:id":2094583,
    "tgn:name":"Wilkes-Barre Township",
    "tgn:placetype":[
        "aat:300008347"
    ]
},
  "bbox": [],
  "geometry": {"coordinates":[-75.85,41.2167],"type":"Point"}
}