<<<<<<< HEAD
{
  "id": 2403095,
  "type": "Feature",
  "properties": {
    "tgn:hierarchy":[
        "tgn:2403095",
        "tgn:1000001",
        "tgn:2001476",
        "tgn:7012149",
        "tgn:7007709",
        "tgn:7029392"
    ],
    "tgn:id":2403095,
    "tgn:name":"House Branch",
    "tgn:placetype":[
        "aat:300008699"
    ]
},
  "bbox": [],
  "geometry": {"coordinates":[-81.65,35.9833],"type":"Point"}
}
=======
{"geometry":{"type":"Point","coordinates":[-81.650000,35.983300]},"type":"Feature","properties":{"hierarchy":["tgn:2403095","tgn:1000001","tgn:2001476","tgn:7012149","tgn:7007709","tgn:7029392"],"placetype":["aat:300008699"],"id":2403095,"name:xx":"House Branch"}}
>>>>>>> 03f74aca74312dbeaf24d7e61306dd6a786dc3d0
