{
  "id": 2173009,
  "type": "Feature",
  "properties": {
    "tgn:hierarchy":[
        "tgn:2173009",
        "tgn:1000001",
        "tgn:2001704",
        "tgn:7012149",
        "tgn:7007708",
        "tgn:7029392"
    ],
    "tgn:id":2173009,
    "tgn:name":"Billys Creek",
    "tgn:placetype":[
        "aat:300008706"
    ]
},
  "bbox": [],
  "geometry": {"coordinates":[-124.0667,42.6167],"type":"Point"}
}