<<<<<<< HEAD
{
  "id": 7023502,
  "type": "Feature",
  "properties": {
    "tgn:hierarchy":[
        "tgn:7023502",
        "tgn:1000001",
        "tgn:7012149",
        "tgn:7007710",
        "tgn:7029392"
    ],
    "tgn:id":7023502,
    "tgn:name":"Stone Chimney Hollow",
    "tgn:placetype":[
        "aat:300008761"
    ]
},
  "bbox": [],
  "geometry": {"coordinates":[-78.2667,41.6333],"type":"Point"}
}
=======
{"geometry":{"type":"Point","coordinates":[-78.266700,41.633300]},"type":"Feature","properties":{"hierarchy":["tgn:7023502","tgn:1000001","tgn:7012149","tgn:7007710","tgn:7029392"],"placetype":["aat:300008761"],"id":7023502,"name:xx":"Stone Chimney Hollow"}}
>>>>>>> 03f74aca74312dbeaf24d7e61306dd6a786dc3d0
