{
  "id": 2245620,
  "type": "Feature",
  "properties": {
    "tgn:hierarchy":[
        "tgn:2245620",
        "tgn:1000001",
        "tgn:2001413",
        "tgn:7012149",
        "tgn:7007526",
        "tgn:7029392"
    ],
    "tgn:id":2245620,
    "tgn:name":"Coal Burner Spring",
    "tgn:placetype":[
        "aat:300008697"
    ]
},
  "bbox": [],
  "geometry": {"coordinates":[-116.2667,39.1833],"type":"Point"}
}