{
  "id": 2608848,
  "type": "Feature",
  "properties": {
    "tgn:hierarchy":[
        "tgn:2608848",
        "tgn:1000001",
        "tgn:2002370",
        "tgn:7012149",
        "tgn:7007923",
        "tgn:7029392"
    ],
    "tgn:id":2608848,
    "tgn:name":"Rattlesnake Spring Number 3",
    "tgn:placetype":[
        "aat:300008697"
    ]
},
  "bbox": [],
  "geometry": {"coordinates":[-104.1167,44.3167],"type":"Point"}
}