<<<<<<< HEAD
{
  "id": 2157021,
  "type": "Feature",
  "properties": {
    "tgn:hierarchy":[
        "tgn:2157021",
        "tgn:1000001",
        "tgn:7012149",
        "tgn:2001274",
        "tgn:7007524",
        "tgn:7029392"
    ],
    "tgn:id":2157021,
    "tgn:name":"Beaver Bay",
    "tgn:placetype":[
        "aat:300132316"
    ]
},
  "bbox": [],
  "geometry": {"coordinates":[-114.3833,48.4333],"type":"Point"}
}
=======
{"geometry":{"type":"Point","coordinates":[-114.383300,48.433300]},"type":"Feature","properties":{"hierarchy":["tgn:2157021","tgn:1000001","tgn:7012149","tgn:2001274","tgn:7007524","tgn:7029392"],"placetype":["aat:300132316"],"id":2157021,"name:xx":"Beaver Bay"}}
>>>>>>> 03f74aca74312dbeaf24d7e61306dd6a786dc3d0
