{
  "id": 7296648,
  "type": "Feature",
  "properties": {
    "tgn:hierarchy":[
        "tgn:7296648",
        "tgn:7001158",
        "tgn:7002850",
        "tgn:1000003",
        "tgn:1000095",
        "tgn:7029392"
    ],
    "tgn:id":7296648,
    "tgn:name":"Villalube",
    "tgn:placetype":[
        "aat:300008347"
    ]
},
  "bbox": [],
  "geometry": {"coordinates":[-5.533333,41.616667],"type":"Point"}
}