<<<<<<< HEAD
{
  "id": 2154703,
  "type": "Feature",
  "properties": {
    "tgn:hierarchy":[
        "tgn:2154703",
        "tgn:1000001",
        "tgn:7012149",
        "tgn:7007524",
        "tgn:7029392"
    ],
    "tgn:id":2154703,
    "tgn:name":"Bear Gulch",
    "tgn:placetype":[
        "aat:300008699"
    ]
},
  "bbox": [],
  "geometry": {"coordinates":[-111.7833,46.3],"type":"Point"}
}
=======
{"geometry":{"type":"Point","coordinates":[-111.783300,46.300000]},"type":"Feature","properties":{"hierarchy":["tgn:2154703","tgn:1000001","tgn:7012149","tgn:7007524","tgn:7029392"],"placetype":["aat:300008699"],"id":2154703,"name:xx":"Bear Gulch"}}
>>>>>>> 03f74aca74312dbeaf24d7e61306dd6a786dc3d0
