<<<<<<< HEAD
{
  "id": 7240113,
  "type": "Feature",
  "properties": {
    "tgn:hierarchy":[
        "tgn:7240113",
        "tgn:7003458",
        "tgn:1000003",
        "tgn:1000063",
        "tgn:7018236",
        "tgn:7029392"
    ],
    "tgn:id":7240113,
    "tgn:name":"Hoogte",
    "tgn:placetype":[
        "aat:300008347"
    ]
},
  "bbox": [],
  "geometry": {"coordinates":[3.249572,50.939329],"type":"Point"}
}
=======
{"geometry":{"type":"Point","coordinates":[3.249572,50.939329]},"type":"Feature","properties":{"hierarchy":["tgn:7240113","tgn:7003458","tgn:1000003","tgn:1000063","tgn:7018236","tgn:7029392"],"placetype":["aat:300008347"],"id":7240113,"name:xx":"Hoogte"}}
>>>>>>> 03f74aca74312dbeaf24d7e61306dd6a786dc3d0
