{
  "id": 2232173,
  "type": "Feature",
  "properties": {
    "tgn:hierarchy":[
        "tgn:2232173",
        "tgn:1000001",
        "tgn:2000950",
        "tgn:7012149",
        "tgn:7007520",
        "tgn:7029392"
    ],
    "tgn:id":2232173,
    "tgn:name":"Chanda Creek",
    "tgn:placetype":[
        "aat:300008706"
    ]
},
  "bbox": [],
  "geometry": {"coordinates":[-85.1167,45.1833],"type":"Point"}
}