{
  "id": 2564351,
  "type": "Feature",
  "properties": {
    "tgn:hierarchy":[
        "tgn:2564351",
        "tgn:1000001",
        "tgn:7012149",
        "tgn:2001444",
        "tgn:7007566",
        "tgn:7029392"
    ],
    "tgn:id":2564351,
    "tgn:name":"Pacheco Mine",
    "tgn:placetype":[
        "aat:300000390"
    ]
},
  "bbox": [],
  "geometry": {"coordinates":[-107.6167,32.0333],"type":"Point"}
}