{
  "id": 7455582,
  "type": "Feature",
  "properties": {
    "tgn:hierarchy":[
        "tgn:7455582",
        "tgn:7002444",
        "tgn:7008074",
        "tgn:1000003",
        "tgn:7008591",
        "tgn:7029392"
    ],
    "tgn:id":7455582,
    "tgn:name:en":"Castle Loch",
    "tgn:placetype":[
        "aat:300008680"
    ]
},
  "bbox": [],
  "geometry": {"coordinates":[-4.666667,54.833333],"type":"Point"}
}