{
  "id": 2158632,
  "type": "Feature",
  "properties": {
    "tgn:hierarchy":[
        "tgn:2158632",
        "tgn:1000001",
        "tgn:7012149",
        "tgn:2001288",
        "tgn:7007524",
        "tgn:7029392"
    ],
    "tgn:id":2158632,
    "tgn:name":"Beaverhead Rock",
    "tgn:placetype":[
        "aat:300008798"
    ]
},
  "bbox": [],
  "geometry": {"coordinates":[-112.45,45.3833],"type":"Point"}
}