{
  "id": 7469198,
  "type": "Feature",
  "properties": {
    "tgn:hierarchy":[
        "tgn:7469198",
        "tgn:7488858",
        "tgn:1000004",
        "tgn:1000141",
        "tgn:7029392"
    ],
    "tgn:id":7469198,
    "tgn:name":"Fuxing",
    "tgn:placetype":[
        "aat:300008347"
    ]
},
  "bbox": [],
  "geometry": {"coordinates":[120.968182,24.007837],"type":"Point"}
}