{
  "id": 2138419,
  "type": "Feature",
  "properties": {
    "tgn:hierarchy":[
        "tgn:2138419",
        "tgn:1000001",
        "tgn:7012149",
        "tgn:1002358",
        "tgn:7007710",
        "tgn:7029392"
    ],
    "tgn:id":2138419,
    "tgn:name":"Asbury",
    "tgn:placetype":[
        "aat:300008347"
    ]
},
  "bbox": [],
  "geometry": {"coordinates":[-80.1667,42.0667],"type":"Point"}
}