{
  "id": 1057382,
  "type": "Feature",
  "properties": {
    "tgn:hierarchy":[
        "tgn:1057382",
        "tgn:1000004",
        "tgn:7011565",
        "tgn:7018214",
        "tgn:7002435",
        "tgn:7029392"
    ],
    "tgn:id":1057382,
    "tgn:name":"Neman",
    "tgn:placetype":[
        "aat:300008347"
    ]
},
  "bbox": [],
  "geometry": {"coordinates":[22.0333,55.0333],"type":"Point"}
}