<<<<<<< HEAD
{
  "id": 2766423,
  "type": "Feature",
  "properties": {
    "tgn:hierarchy":[
        "tgn:2766423",
        "tgn:1000001",
        "tgn:7012149",
        "tgn:2001750",
        "tgn:7007712",
        "tgn:7029392"
    ],
    "tgn:id":2766423,
    "tgn:name":"White Oak",
    "tgn:placetype":[
        "aat:300008347"
    ]
},
  "bbox": [],
  "geometry": {"coordinates":[-79.0667,33.8667],"type":"Point"}
}
=======
{"geometry":{"type":"Point","coordinates":[-79.066700,33.866700]},"type":"Feature","properties":{"hierarchy":["tgn:2766423","tgn:1000001","tgn:7012149","tgn:2001750","tgn:7007712","tgn:7029392"],"placetype":["aat:300008347"],"id":2766423,"name:xx":"White Oak"}}
>>>>>>> 03f74aca74312dbeaf24d7e61306dd6a786dc3d0
