<<<<<<< HEAD
{
  "id": 2403420,
  "type": "Feature",
  "properties": {
    "tgn:hierarchy":[
        "tgn:2403420",
        "tgn:1000001",
        "tgn:7012149",
        "tgn:2001274",
        "tgn:7007524",
        "tgn:7029392"
    ],
    "tgn:id":2403420,
    "tgn:name":"Houston Point",
    "tgn:placetype":[
        "aat:300008850"
    ]
},
  "bbox": [],
  "geometry": {"coordinates":[-114.35,48.4333],"type":"Point"}
}
=======
{"geometry":{"type":"Point","coordinates":[-114.350000,48.433300]},"type":"Feature","properties":{"hierarchy":["tgn:2403420","tgn:1000001","tgn:7012149","tgn:2001274","tgn:7007524","tgn:7029392"],"placetype":["aat:300008850"],"id":2403420,"name:xx":"Houston Point"}}
>>>>>>> 03f74aca74312dbeaf24d7e61306dd6a786dc3d0
