{
  "id": 2329542,
  "type": "Feature",
  "properties": {
    "tgn:hierarchy":[
        "tgn:2329542",
        "tgn:1000001",
        "tgn:7012149",
        "tgn:7007157",
        "tgn:1002861",
        "tgn:7029392"
    ],
    "tgn:id":2329542,
    "tgn:name":"Five West, Lateral",
    "tgn:placetype":[
        "aat:300006075"
    ]
},
  "bbox": [],
  "geometry": {"coordinates":[-121.3833,37.6667],"type":"Point"}
}