{
  "id": 2634824,
  "type": "Feature",
  "properties": {
    "tgn:hierarchy":[
        "tgn:2634824",
        "tgn:1000001",
        "tgn:1002236",
        "tgn:7012149",
        "tgn:7007252",
        "tgn:7029392"
    ],
    "tgn:id":2634824,
    "tgn:name":"Ryan Appleton Ditch",
    "tgn:placetype":[
        "aat:300006075"
    ]
},
  "bbox": [],
  "geometry": {"coordinates":[-86.4667,40.65],"type":"Point"}
}