{
  "id": 2563187,
  "type": "Feature",
  "properties": {
    "tgn:hierarchy":[
        "tgn:2563187",
        "tgn:7030516",
        "tgn:7006450",
        "tgn:1000001",
        "tgn:7012149",
        "tgn:7029392"
    ],
    "tgn:id":2563187,
    "tgn:name":"Owens Ridge",
    "tgn:placetype":[
        "aat:300266640"
    ]
},
  "bbox": [],
  "geometry": {"coordinates":[173.0167,52.95],"type":"Point"}
}