{
  "id": 7023263,
  "type": "Feature",
  "properties": {
    "tgn:hierarchy":[
        "tgn:7023263",
        "tgn:1000001",
        "tgn:7012149",
        "tgn:7007248",
        "tgn:7029392"
    ],
    "tgn:id":7023263,
    "tgn:name":"Little Mulberry River",
    "tgn:placetype":[
        "aat:300008707"
    ]
},
  "bbox": [],
  "geometry": {"coordinates":[-83.9167,34.0667],"type":"Point"}
}