{
  "id": 2623122,
  "type": "Feature",
  "properties": {
    "tgn:hierarchy":[
        "tgn:2623122",
        "tgn:2000256",
        "tgn:1000001",
        "tgn:7012149",
        "tgn:7007240",
        "tgn:7029392"
    ],
    "tgn:id":2623122,
    "tgn:name":"Rochelle",
    "tgn:placetype":[
        "aat:300008347"
    ]
},
  "bbox": [],
  "geometry": {"coordinates":[-82.2167,29.5833],"type":"Point"}
}