{
  "id": 2219750,
  "type": "Feature",
  "properties": {
    "tgn:hierarchy":[
        "tgn:2219750",
        "tgn:2002365",
        "tgn:1000001",
        "tgn:7012149",
        "tgn:7007923",
        "tgn:7029392"
    ],
    "tgn:id":2219750,
    "tgn:name":"Canteen Creek",
    "tgn:placetype":[
        "aat:300008706"
    ]
},
  "bbox": [],
  "geometry": {"coordinates":[-105.3667,41.6667],"type":"Point"}
}