{
  "id": 2289632,
  "type": "Feature",
  "properties": {
    "tgn:hierarchy":[
        "tgn:2289632",
        "tgn:1000001",
        "tgn:7012149",
        "tgn:7007157",
        "tgn:1002901",
        "tgn:7029392"
    ],
    "tgn:id":2289632,
    "tgn:name":"Dixon Ridge",
    "tgn:placetype":[
        "aat:300266640"
    ]
},
  "bbox": [],
  "geometry": {"coordinates":[-121.8333,38.4333],"type":"Point"}
}