{
  "id": 7124632,
  "type": "Feature",
  "properties": {
    "tgn:hierarchy":[
        "tgn:7124632",
        "tgn:1000003",
        "tgn:7003687",
        "tgn:7000084",
        "tgn:7029392"
    ],
    "tgn:id":7124632,
    "tgn:name":"Neu Goldbeck",
    "tgn:placetype":[
        "aat:300000206"
    ]
},
  "bbox": [],
  "geometry": {"coordinates":[11.95,52.866667],"type":"Point"}
}