{
  "id": 7103176,
  "type": "Feature",
  "properties": {
    "tgn:hierarchy":[
        "tgn:7103176",
        "tgn:1000003",
        "tgn:7000094",
        "tgn:7000084",
        "tgn:7029392"
    ],
    "tgn:id":7103176,
    "tgn:name":"Sankt Georg",
    "tgn:placetype":[
        "aat:300008347"
    ]
},
  "bbox": [],
  "geometry": {"coordinates":[13.25,53.55],"type":"Point"}
}