{
  "id": 2168771,
  "type": "Feature",
  "properties": {
    "tgn:hierarchy":[
        "tgn:2168771",
        "tgn:1000001",
        "tgn:7012149",
        "tgn:7007825",
        "tgn:7029392"
    ],
    "tgn:id":2168771,
    "tgn:name":"Big Hollow Branch",
    "tgn:placetype":[
        "aat:300008699"
    ]
},
  "bbox": [],
  "geometry": {"coordinates":[-85.1667,36.4667],"type":"Point"}
}