{
  "id": 1081056,
  "type": "Feature",
  "properties": {
    "tgn:hierarchy":[
        "tgn:1081056",
        "tgn:1000971",
        "tgn:1000004",
        "tgn:7000894",
        "tgn:1000120",
        "tgn:7029392"
    ],
    "tgn:id":1081056,
    "tgn:name":"Nosaka",
    "tgn:placetype":[
        "aat:300008347"
    ]
},
  "bbox": [],
  "geometry": {"coordinates":[140.5667,35.65],"type":"Point"}
}