{
  "id": 2041257,
  "type": "Feature",
  "properties": {
    "tgn:hierarchy":[
        "tgn:2041257",
        "tgn:1000001",
        "tgn:7012149",
        "tgn:2000823",
        "tgn:7007255",
        "tgn:7029392"
    ],
    "tgn:id":2041257,
    "tgn:name":"Sharpe",
    "tgn:placetype":[
        "aat:300008347"
    ]
},
  "bbox": [],
  "geometry": {"coordinates":[-88.45,36.9667],"type":"Point"}
}