{
  "id": 2472906,
  "type": "Feature",
  "properties": {
    "tgn:hierarchy":[
        "tgn:2472906",
        "tgn:1000001",
        "tgn:7012149",
        "tgn:2001247",
        "tgn:7007523",
        "tgn:7029392"
    ],
    "tgn:id":2472906,
    "tgn:name":"Low Gap",
    "tgn:placetype":[
        "aat:300008798"
    ]
},
  "bbox": [],
  "geometry": {"coordinates":[-91.5667,37.0833],"type":"Point"}
}