{
  "id": 2706172,
  "type": "Feature",
  "properties": {
    "tgn:hierarchy":[
        "tgn:2706172",
        "tgn:1000001",
        "tgn:7014423",
        "tgn:7012149",
        "tgn:7007517",
        "tgn:7029392"
    ],
    "tgn:id":2706172,
    "tgn:name":"Swamp Brook",
    "tgn:placetype":[
        "aat:300008699"
    ]
},
  "bbox": [],
  "geometry": {"coordinates":[-70.8167,42.0667],"type":"Point"}
}