{
  "id": 2101993,
  "type": "Feature",
  "properties": {
    "tgn:hierarchy":[
        "tgn:2101993",
        "tgn:1000001",
        "tgn:7012149",
        "tgn:2001914",
        "tgn:7007825",
        "tgn:7029392"
    ],
    "tgn:id":2101993,
    "tgn:name":"Walnut Grove",
    "tgn:placetype":[
        "aat:300008347"
    ]
},
  "bbox": [],
  "geometry": {"coordinates":[-83.4667,35.8667],"type":"Point"}
}