{
  "id": 7236132,
  "type": "Feature",
  "properties": {
    "tgn:hierarchy":[
        "tgn:7236132",
        "tgn:7002750",
        "tgn:7001399",
        "tgn:1000003",
        "tgn:1000074",
        "tgn:7029392"
    ],
    "tgn:id":7236132,
    "tgn:name":"Evangelism\u00f3s",
    "tgn:placetype":[
        "aat:300008347"
    ]
},
  "bbox": [],
  "geometry": {"coordinates":[22.516667,39.834722],"type":"Point"}
}