<<<<<<< HEAD
{
  "id": 2250660,
  "type": "Feature",
  "properties": {
    "tgn:hierarchy":[
        "tgn:2250660",
        "tgn:1000001",
        "tgn:7012149",
        "tgn:2001451",
        "tgn:7007566",
        "tgn:7029392"
    ],
    "tgn:id":2250660,
    "tgn:name":"Colorado, Arroyo",
    "tgn:placetype":[
        "aat:300008699"
    ]
},
  "bbox": [],
  "geometry": {"coordinates":[-106.4167,35.2833],"type":"Point"}
}
=======
{"geometry":{"type":"Point","coordinates":[-106.416700,35.283300]},"type":"Feature","properties":{"hierarchy":["tgn:2250660","tgn:1000001","tgn:7012149","tgn:2001451","tgn:7007566","tgn:7029392"],"placetype":["aat:300008699"],"id":2250660,"name:xx":"Colorado, Arroyo"}}
>>>>>>> 03f74aca74312dbeaf24d7e61306dd6a786dc3d0
