{
  "id": 7486150,
  "type": "Feature",
  "properties": {
    "tgn:hierarchy":[
        "tgn:7486150",
        "tgn:1000004",
        "tgn:7491221",
        "tgn:1000141",
        "tgn:7029392"
    ],
    "tgn:id":7486150,
    "tgn:name":"Huiyaozi",
    "tgn:placetype":[
        "aat:300008347"
    ]
},
  "bbox": [],
  "geometry": {"coordinates":[121.128251,22.768846],"type":"Point"}
}