{
  "id": 1079884,
  "type": "Feature",
  "properties": {
    "tgn:hierarchy":[
        "tgn:1079884",
        "tgn:1000004",
        "tgn:1000962",
        "tgn:7000896",
        "tgn:1000120",
        "tgn:7029392"
    ],
    "tgn:id":1079884,
    "tgn:name":"Chihaya-akasaka-mura",
    "tgn:placetype":[
        "aat:300008347"
    ]
},
  "bbox": [],
  "geometry": {"coordinates":[135.65,34.4333],"type":"Point"}
}