{
  "id": 7476308,
  "type": "Feature",
  "properties": {
    "tgn:hierarchy":[
        "tgn:7476308",
        "tgn:7488858",
        "tgn:1000004",
        "tgn:1000141",
        "tgn:7029392"
    ],
    "tgn:id":7476308,
    "tgn:name":"Fanzitian Shan",
    "tgn:placetype":[
        "aat:300008798"
    ]
},
  "bbox": [],
  "geometry": {"coordinates":[120.942121,23.866231],"type":"Point"}
}