{
  "id": 2748028,
  "type": "Feature",
  "properties": {
    "tgn:hierarchy":[
        "tgn:2748028",
        "tgn:1000001",
        "tgn:7012149",
        "tgn:2000931",
        "tgn:7007515",
        "tgn:7029392"
    ],
    "tgn:id":2748028,
    "tgn:name":"Waldo, Mount",
    "tgn:placetype":[
        "aat:300008798"
    ]
},
  "bbox": [],
  "geometry": {"coordinates":[-68.8833,44.5667],"type":"Point"}
}