{
  "id": 2771722,
  "type": "Feature",
  "properties": {
    "tgn:hierarchy":[
        "tgn:2771722",
        "tgn:1000001",
        "tgn:2000925",
        "tgn:7012149",
        "tgn:7007515",
        "tgn:7029392"
    ],
    "tgn:id":2771722,
    "tgn:name":"Wiley Brook",
    "tgn:placetype":[
        "aat:300008699"
    ]
},
  "bbox": [],
  "geometry": {"coordinates":[-69.55,43.95],"type":"Point"}
}