{
  "id": 7353501,
  "type": "Feature",
  "properties": {
    "tgn:hierarchy":[
        "tgn:7353501",
        "tgn:1000001",
        "tgn:7005599",
        "tgn:7005560",
        "tgn:7029392"
    ],
    "tgn:id":7353501,
    "tgn:name":"Angustias",
    "tgn:placetype":[
        "aat:300008347"
    ]
},
  "bbox": [],
  "geometry": {"coordinates":[-94.833333,17.65],"type":"Point"}
}