{
  "id": 7288504,
  "type": "Feature",
  "properties": {
    "tgn:hierarchy":[
        "tgn:7288504",
        "tgn:7016598",
        "tgn:1000049",
        "tgn:1000002",
        "tgn:7029392"
    ],
    "tgn:id":7288504,
    "tgn:name":"Lagunita, Pampa",
    "tgn:placetype":[
        "aat:300008805"
    ]
},
  "bbox": [],
  "geometry": {"coordinates":[-68.266667,-21.95],"type":"Point"}
}