{
  "id": 2586233,
  "type": "Feature",
  "properties": {
    "tgn:hierarchy":[
        "tgn:2586233",
        "tgn:1000001",
        "tgn:7012149",
        "tgn:2001924",
        "tgn:7007825",
        "tgn:7029392"
    ],
    "tgn:id":2586233,
    "tgn:name":"Pit Cave",
    "tgn:placetype":[
        "aat:300008746"
    ]
},
  "bbox": [],
  "geometry": {"coordinates":[-85.5667,35.7667],"type":"Point"}
}