{
  "id": 7562180,
  "type": "Feature",
  "properties": {
    "tgn:hierarchy":[
        "tgn:7562180",
        "tgn:1000004",
        "tgn:7000198",
        "tgn:7016722",
        "tgn:7029392"
    ],
    "tgn:id":7562180,
    "tgn:name:en":"Sult\u0101npur",
    "tgn:placetype":[
        "aat:300008347"
    ]
},
  "bbox": [],
  "geometry": {"coordinates":[79.035645,27.831056],"type":"Point"}
}