{
  "id": 2740086,
  "type": "Feature",
  "properties": {
    "tgn:hierarchy":[
        "tgn:2740086",
        "tgn:1000001",
        "tgn:7012149",
        "tgn:2000814",
        "tgn:7007255",
        "tgn:7029392"
    ],
    "tgn:id":2740086,
    "tgn:name":"Upper Hodge Landing",
    "tgn:placetype":[
        "aat:300008347"
    ]
},
  "bbox": [],
  "geometry": {"coordinates":[-88.45,37.0333],"type":"Point"}
}