{
  "id": 2357677,
  "type": "Feature",
  "properties": {
    "tgn:hierarchy":[
        "tgn:2357677",
        "tgn:1000001",
        "tgn:7012149",
        "tgn:2000429",
        "tgn:7007248",
        "tgn:7029392"
    ],
    "tgn:id":2357677,
    "tgn:name":"Grace Branch",
    "tgn:placetype":[
        "aat:300008699"
    ]
},
  "bbox": [],
  "geometry": {"coordinates":[-82.2833,32.0167],"type":"Point"}
}