{
  "id": 7294358,
  "type": "Feature",
  "properties": {
    "tgn:hierarchy":[
        "tgn:7294358",
        "tgn:7002824",
        "tgn:1000003",
        "tgn:7002786",
        "tgn:1000095",
        "tgn:7029392"
    ],
    "tgn:id":7294358,
    "tgn:name":"Veiga",
    "tgn:placetype":[
        "aat:300008347"
    ]
},
  "bbox": [],
  "geometry": {"coordinates":[-8.416667,43.25],"type":"Point"}
}