<<<<<<< HEAD
{
  "id": 2159649,
  "type": "Feature",
  "properties": {
    "tgn:hierarchy":[
        "tgn:2159649",
        "tgn:1000001",
        "tgn:1002286",
        "tgn:7012149",
        "tgn:7007710",
        "tgn:7029392"
    ],
    "tgn:id":2159649,
    "tgn:name":"Bee Tree Draft",
    "tgn:placetype":[
        "aat:300008761"
    ]
},
  "bbox": [],
  "geometry": {"coordinates":[-77.95,41.35],"type":"Point"}
}
=======
{"geometry":{"type":"Point","coordinates":[-77.950000,41.350000]},"type":"Feature","properties":{"hierarchy":["tgn:2159649","tgn:1000001","tgn:1002286","tgn:7012149","tgn:7007710","tgn:7029392"],"placetype":["aat:300008761"],"id":2159649,"name:xx":"Bee Tree Draft"}}
>>>>>>> 03f74aca74312dbeaf24d7e61306dd6a786dc3d0
