{
  "id": 2505162,
  "type": "Feature",
  "properties": {
    "tgn:hierarchy":[
        "tgn:2505162",
        "tgn:2000918",
        "tgn:1000001",
        "tgn:7012149",
        "tgn:7007515",
        "tgn:7029392"
    ],
    "tgn:id":2505162,
    "tgn:name":"Megquier Hill",
    "tgn:placetype":[
        "aat:300008798"
    ]
},
  "bbox": [],
  "geometry": {"coordinates":[-70.4333,44.0333],"type":"Point"}
}