{
  "id": 7325693,
  "type": "Feature",
  "properties": {
    "tgn:hierarchy":[
        "tgn:7325693",
        "tgn:7002844",
        "tgn:7030216",
        "tgn:1000003",
        "tgn:1000095",
        "tgn:7029392"
    ],
    "tgn:id":7325693,
    "tgn:name":"San Magin, Barranco de",
    "tgn:placetype":[
        "aat:300008699"
    ]
},
  "bbox": [],
  "geometry": {"coordinates":[1.390684,41.477229],"type":"Point"}
}