{
  "id": 2566641,
  "type": "Feature",
  "properties": {
    "tgn:hierarchy":[
        "tgn:2566641",
        "tgn:1000001",
        "tgn:2002109",
        "tgn:7012149",
        "tgn:7007827",
        "tgn:7029392"
    ],
    "tgn:id":2566641,
    "tgn:name":"Panguitch Canal",
    "tgn:placetype":[
        "aat:300006075"
    ]
},
  "bbox": [],
  "geometry": {"coordinates":[-112.45,37.8833],"type":"Point"}
}