{
  "id": 2310363,
  "type": "Feature",
  "properties": {
    "tgn:hierarchy":[
        "tgn:2310363",
        "tgn:1000001",
        "tgn:7012149",
        "tgn:1002679",
        "tgn:7007520",
        "tgn:7029392"
    ],
    "tgn:id":2310363,
    "tgn:name":"Eby Drain",
    "tgn:placetype":[
        "aat:300008699"
    ]
},
  "bbox": [],
  "geometry": {"coordinates":[-83.4833,41.9833],"type":"Point"}
}