{
  "id": 7468196,
  "type": "Feature",
  "properties": {
    "tgn:hierarchy":[
        "tgn:7468196",
        "tgn:1000004",
        "tgn:7491221",
        "tgn:1000141",
        "tgn:7029392"
    ],
    "tgn:id":7468196,
    "tgn:name":"Jiangjunyan",
    "tgn:placetype":[
        "aat:300008347"
    ]
},
  "bbox": [],
  "geometry": {"coordinates":[121.496389,22.674444],"type":"Point"}
}