{
  "id": 2765422,
  "type": "Feature",
  "properties": {
    "tgn:hierarchy":[
        "tgn:2765422",
        "tgn:7002659",
        "tgn:1000001",
        "tgn:7012149",
        "tgn:2000023",
        "tgn:7029392"
    ],
    "tgn:id":2765422,
    "tgn:name":"White Bluff Bar",
    "tgn:placetype":[
        "aat:300132348"
    ]
},
  "bbox": [],
  "geometry": {"coordinates":[-87.15,32.2667],"type":"Point"}
}