<<<<<<< HEAD
{
  "id": 2765422,
  "type": "Feature",
  "properties": {
    "tgn:hierarchy":[
        "tgn:2765422",
        "tgn:7002659",
        "tgn:1000001",
        "tgn:7012149",
        "tgn:2000023",
        "tgn:7029392"
    ],
    "tgn:id":2765422,
    "tgn:name":"White Bluff Bar",
    "tgn:placetype":[
        "aat:300132348"
    ]
},
  "bbox": [],
  "geometry": {"coordinates":[-87.15,32.2667],"type":"Point"}
}
=======
{"geometry":{"type":"Point","coordinates":[-87.150000,32.266700]},"type":"Feature","properties":{"hierarchy":["tgn:2765422","tgn:7002659","tgn:1000001","tgn:7012149","tgn:2000023","tgn:7029392"],"placetype":["aat:300132348"],"id":2765422,"name:xx":"White Bluff Bar"}}
>>>>>>> 03f74aca74312dbeaf24d7e61306dd6a786dc3d0
