{
  "id": 7119197,
  "type": "Feature",
  "properties": {
    "tgn:hierarchy":[
        "tgn:7119197",
        "tgn:1000003",
        "tgn:7003685",
        "tgn:7000084",
        "tgn:7029392"
    ],
    "tgn:id":7119197,
    "tgn:name":"Peres",
    "tgn:placetype":[
        "aat:300008347"
    ]
},
  "bbox": [],
  "geometry": {"coordinates":[12.333333,51.183333],"type":"Point"}
}