{
  "id": 7401882,
  "type": "Feature",
  "properties": {
    "tgn:hierarchy":[
        "tgn:7401882",
        "tgn:1000001",
        "tgn:7005599",
        "tgn:7005560",
        "tgn:7029392"
    ],
    "tgn:id":7401882,
    "tgn:name":"Universidad Veracruzana",
    "tgn:placetype":[
        "aat:300006610"
    ]
},
  "bbox": [],
  "geometry": {"coordinates":[-96.216667,19.166667],"type":"Point"}
}