<<<<<<< HEAD
{
  "id": 2766984,
  "type": "Feature",
  "properties": {
    "tgn:hierarchy":[
        "tgn:2766984",
        "tgn:1000001",
        "tgn:7012149",
        "tgn:2001882",
        "tgn:7007825",
        "tgn:7029392"
    ],
    "tgn:id":2766984,
    "tgn:name":"White Prospect",
    "tgn:placetype":[
        "aat:300000390"
    ]
},
  "bbox": [],
  "geometry": {"coordinates":[-81.9333,36.4167],"type":"Point"}
}
=======
{"geometry":{"type":"Point","coordinates":[-81.933300,36.416700]},"type":"Feature","properties":{"hierarchy":["tgn:2766984","tgn:1000001","tgn:7012149","tgn:2001882","tgn:7007825","tgn:7029392"],"placetype":["aat:300000390"],"id":2766984,"name:xx":"White Prospect"}}
>>>>>>> 03f74aca74312dbeaf24d7e61306dd6a786dc3d0
