{
  "id": 7508200,
  "type": "Feature",
  "properties": {
    "tgn:hierarchy":[
        "tgn:7508200",
        "tgn:1008380",
        "tgn:1000226",
        "tgn:7018426",
        "tgn:1000006",
        "tgn:7029392"
    ],
    "tgn:id":7508200,
    "tgn:name:en":"Papanui Point",
    "tgn:placetype":[
        "aat:300386846"
    ]
},
  "bbox": [],
  "geometry": {"coordinates":[174.766667,-37.883333],"type":"Point"}
}