{
  "id": 2349598,
  "type": "Feature",
  "properties": {
    "tgn:hierarchy":[
        "tgn:2349598",
        "tgn:1000001",
        "tgn:2002136",
        "tgn:7012149",
        "tgn:7007828",
        "tgn:7029392"
    ],
    "tgn:id":2349598,
    "tgn:name":"Gillespie Peak",
    "tgn:placetype":[
        "aat:300008798"
    ]
},
  "bbox": [],
  "geometry": {"coordinates":[-72.9667,43.8667],"type":"Point"}
}