{
  "id": 2239329,
  "type": "Feature",
  "properties": {
    "tgn:hierarchy":[
        "tgn:2239329",
        "tgn:1000001",
        "tgn:7012149",
        "tgn:2001453",
        "tgn:7007566",
        "tgn:7029392"
    ],
    "tgn:id":2239329,
    "tgn:name":"Chupinas Rincon Pasture",
    "tgn:placetype":[
        "aat:300055621"
    ]
},
  "bbox": [],
  "geometry": {"coordinates":[-105.0333,35.2667],"type":"Point"}
}