{
  "id": 7581068,
  "type": "Feature",
  "properties": {
    "tgn:hierarchy":[
        "tgn:7581068",
        "tgn:1000004",
        "tgn:7000198",
        "tgn:1001895",
        "tgn:7029392"
    ],
    "tgn:id":7581068,
    "tgn:name:en":"V\u0101rna River",
    "tgn:placetype":[
        "aat:300008699"
    ]
},
  "bbox": [],
  "geometry": {"coordinates":[74.533333,16.85],"type":"Point"}
}