<<<<<<< HEAD
{
  "id": 2400667,
  "type": "Feature",
  "properties": {
    "tgn:hierarchy":[
        "tgn:2400667",
        "tgn:1000001",
        "tgn:7012149",
        "tgn:2002119",
        "tgn:7007827",
        "tgn:7029392"
    ],
    "tgn:id":2400667,
    "tgn:name":"Horse Mountain",
    "tgn:placetype":[
        "aat:300008798"
    ]
},
  "bbox": [],
  "geometry": {"coordinates":[-109.7667,37.8667],"type":"Point"}
}
=======
{"geometry":{"type":"Point","coordinates":[-109.766700,37.866700]},"type":"Feature","properties":{"hierarchy":["tgn:2400667","tgn:1000001","tgn:7012149","tgn:2002119","tgn:7007827","tgn:7029392"],"placetype":["aat:300008798"],"id":2400667,"name:xx":"Horse Mountain"}}
>>>>>>> 03f74aca74312dbeaf24d7e61306dd6a786dc3d0
