<<<<<<< HEAD
{
  "id": 7378898,
  "type": "Feature",
  "properties": {
    "tgn:hierarchy":[
        "tgn:7378898",
        "tgn:7005583",
        "tgn:1000001",
        "tgn:7005560",
        "tgn:7029392"
    ],
    "tgn:id":7378898,
    "tgn:name":"M\u00e9xico",
    "tgn:placetype":[
        "aat:300008347"
    ]
},
  "bbox": [],
  "geometry": {"coordinates":[-105.9,26.7],"type":"Point"}
}
=======
{"geometry":{"type":"Point","coordinates":[-105.900000,26.700000]},"type":"Feature","properties":{"hierarchy":["tgn:7378898","tgn:7005583","tgn:1000001","tgn:7005560","tgn:7029392"],"placetype":["aat:300008347"],"id":7378898,"name:xx":"M\u00e9xico"}}
>>>>>>> 03f74aca74312dbeaf24d7e61306dd6a786dc3d0
