{
  "id": 7232906,
  "type": "Feature",
  "properties": {
    "tgn:hierarchy":[
        "tgn:7232906",
        "tgn:7002739",
        "tgn:7017076",
        "tgn:1000003",
        "tgn:1000074",
        "tgn:7029392"
    ],
    "tgn:id":7232906,
    "tgn:name":"\u00cdnakhos Potam\u00f3s",
    "tgn:placetype":[
        "aat:300008699"
    ]
},
  "bbox": [],
  "geometry": {"coordinates":[22.75,37.583333],"type":"Point"}
}