{
  "id": 7405447,
  "type": "Feature",
  "properties": {
    "tgn:hierarchy":[
        "tgn:7405447",
        "tgn:7016644",
        "tgn:1000001",
        "tgn:7005560",
        "tgn:7029392"
    ],
    "tgn:id":7405447,
    "tgn:name":"El Huizalacate",
    "tgn:placetype":[
        "aat:300008347"
    ]
},
  "bbox": [],
  "geometry": {"coordinates":[-103.786111,19.1625],"type":"Point"}
}