{
  "id": 2135661,
  "type": "Feature",
  "properties": {
    "tgn:hierarchy":[
        "tgn:2135661",
        "tgn:1000001",
        "tgn:7006451",
        "tgn:7012149",
        "tgn:2000103",
        "tgn:7029392"
    ],
    "tgn:id":2135661,
    "tgn:name":"Apache Tank",
    "tgn:placetype":[
        "aat:300006191"
    ]
},
  "bbox": [],
  "geometry": {"coordinates":[-113.3167,35.15],"type":"Point"}
}