{
  "id": 7289957,
  "type": "Feature",
  "properties": {
    "tgn:hierarchy":[
        "tgn:7289957",
        "tgn:1001695",
        "tgn:1000049",
        "tgn:1000002",
        "tgn:7029392"
    ],
    "tgn:id":7289957,
    "tgn:name":"El Barco",
    "tgn:placetype":[
        "aat:300000206"
    ]
},
  "bbox": [],
  "geometry": {"coordinates":[-71.416667,-34.466667],"type":"Point"}
}