<<<<<<< HEAD
{
  "id": 2152190,
  "type": "Feature",
  "properties": {
    "tgn:hierarchy":[
        "tgn:2152190",
        "tgn:7002659",
        "tgn:1000001",
        "tgn:2000019",
        "tgn:7012149",
        "tgn:7029392"
    ],
    "tgn:id":2152190,
    "tgn:name":"Bay Branch",
    "tgn:placetype":[
        "aat:300008699"
    ]
},
  "bbox": [],
  "geometry": {"coordinates":[-86.4667,31.3],"type":"Point"}
}
=======
{"geometry":{"type":"Point","coordinates":[-86.466700,31.300000]},"type":"Feature","properties":{"hierarchy":["tgn:2152190","tgn:7002659","tgn:1000001","tgn:2000019","tgn:7012149","tgn:7029392"],"placetype":["aat:300008699"],"id":2152190,"name:xx":"Bay Branch"}}
>>>>>>> 03f74aca74312dbeaf24d7e61306dd6a786dc3d0
