{
  "id": 7427837,
  "type": "Feature",
  "properties": {
    "tgn:hierarchy":[
        "tgn:7427837",
        "tgn:1000001",
        "tgn:7005594",
        "tgn:7005560",
        "tgn:7029392"
    ],
    "tgn:id":7427837,
    "tgn:name":"Le\u00f3n Garc\u00eda",
    "tgn:placetype":[
        "aat:300008347"
    ]
},
  "bbox": [],
  "geometry": {"coordinates":[-98.966667,22.016667],"type":"Point"}
}