{
  "id": 2529410,
  "type": "Feature",
  "properties": {
    "tgn:hierarchy":[
        "tgn:2529410",
        "tgn:1000001",
        "tgn:7012149",
        "tgn:7007521",
        "tgn:7029392"
    ],
    "tgn:id":2529410,
    "tgn:name":"Mud Lake",
    "tgn:placetype":[
        "aat:300008680"
    ]
},
  "bbox": [],
  "geometry": {"coordinates":[-93.0167,45.25],"type":"Point"}
}