{
  "id": 2105197,
  "type": "Feature",
  "properties": {
    "tgn:hierarchy":[
        "tgn:2105197",
        "tgn:1000001",
        "tgn:7012149",
        "tgn:2002076",
        "tgn:7007826",
        "tgn:7029392"
    ],
    "tgn:id":2105197,
    "tgn:name":"Ivan",
    "tgn:placetype":[
        "aat:300008347",
        "aat:300387210"
    ]
},
  "bbox": [],
  "geometry": {"coordinates":[-98.7167,32.8667],"type":"Point"}
}