<<<<<<< HEAD
{
  "id": 2250968,
  "type": "Feature",
  "properties": {
    "tgn:hierarchy":[
        "tgn:2250968",
        "tgn:1000001",
        "tgn:7012149",
        "tgn:2000226",
        "tgn:7007158",
        "tgn:7029392"
    ],
    "tgn:id":2250968,
    "tgn:name":"Columbine Ditch",
    "tgn:placetype":[
        "aat:300006075"
    ]
},
  "bbox": [],
  "geometry": {"coordinates":[-105.7667,40.7833],"type":"Point"}
}
=======
{"geometry":{"type":"Point","coordinates":[-105.766700,40.783300]},"type":"Feature","properties":{"hierarchy":["tgn:2250968","tgn:1000001","tgn:7012149","tgn:2000226","tgn:7007158","tgn:7029392"],"placetype":["aat:300006075"],"id":2250968,"name:xx":"Columbine Ditch"}}
>>>>>>> 03f74aca74312dbeaf24d7e61306dd6a786dc3d0
