{
  "id": 2250968,
  "type": "Feature",
  "properties": {
    "tgn:hierarchy":[
        "tgn:2250968",
        "tgn:1000001",
        "tgn:7012149",
        "tgn:2000226",
        "tgn:7007158",
        "tgn:7029392"
    ],
    "tgn:id":2250968,
    "tgn:name":"Columbine Ditch",
    "tgn:placetype":[
        "aat:300006075"
    ]
},
  "bbox": [],
  "geometry": {"coordinates":[-105.7667,40.7833],"type":"Point"}
}