{
  "id": 7507642,
  "type": "Feature",
  "properties": {
    "tgn:hierarchy":[
        "tgn:7507642",
        "tgn:1009227",
        "tgn:1000226",
        "tgn:7018437",
        "tgn:1000006",
        "tgn:7029392"
    ],
    "tgn:id":7507642,
    "tgn:name:en":"Poolburn",
    "tgn:placetype":[
        "aat:300008699"
    ]
},
  "bbox": [],
  "geometry": {"coordinates":[169.733333,-45.066667],"type":"Point"}
}