{
  "id": 2357755,
  "type": "Feature",
  "properties": {
    "tgn:hierarchy":[
        "tgn:2357755",
        "tgn:1000001",
        "tgn:2001183",
        "tgn:7012149",
        "tgn:7007523",
        "tgn:7029392"
    ],
    "tgn:id":2357755,
    "tgn:name":"Graceland",
    "tgn:placetype":[
        "aat:300008347"
    ]
},
  "bbox": [],
  "geometry": {"coordinates":[-93.75,37.75],"type":"Point"}
}