<<<<<<< HEAD
{
  "id": 2406704,
  "type": "Feature",
  "properties": {
    "tgn:hierarchy":[
        "tgn:2406704",
        "tgn:1000001",
        "tgn:7012149",
        "tgn:2002270",
        "tgn:7013961",
        "tgn:7029392"
    ],
    "tgn:id":2406704,
    "tgn:name":"Hunt Hollow",
    "tgn:placetype":[
        "aat:300008761"
    ]
},
  "bbox": [],
  "geometry": {"coordinates":[-81.45,38.2833],"type":"Point"}
}
=======
{"geometry":{"type":"Point","coordinates":[-81.450000,38.283300]},"type":"Feature","properties":{"hierarchy":["tgn:2406704","tgn:1000001","tgn:7012149","tgn:2002270","tgn:7013961","tgn:7029392"],"placetype":["aat:300008761"],"id":2406704,"name:xx":"Hunt Hollow"}}
>>>>>>> 03f74aca74312dbeaf24d7e61306dd6a786dc3d0
