{
  "id": 7214236,
  "type": "Feature",
  "properties": {
    "tgn:hierarchy":[
        "tgn:7214236",
        "tgn:1000003",
        "tgn:7003676",
        "tgn:7000084",
        "tgn:7029392"
    ],
    "tgn:id":7214236,
    "tgn:name":"Beverloh",
    "tgn:placetype":[
        "aat:300008777"
    ]
},
  "bbox": [],
  "geometry": {"coordinates":[9.95,52.733333],"type":"Point"}
}