{
  "id": 7310057,
  "type": "Feature",
  "properties": {
    "tgn:hierarchy":[
        "tgn:7310057",
        "tgn:1001695",
        "tgn:1000049",
        "tgn:1000002",
        "tgn:7029392"
    ],
    "tgn:id":7310057,
    "tgn:name":"Miraflores",
    "tgn:placetype":[
        "aat:300000206"
    ]
},
  "bbox": [],
  "geometry": {"coordinates":[-70.633333,-34.133333],"type":"Point"}
}