{
  "id": 2290877,
  "type": "Feature",
  "properties": {
    "tgn:hierarchy":[
        "tgn:2290877",
        "tgn:7006450",
        "tgn:1000001",
        "tgn:7012149",
        "tgn:2000082",
        "tgn:7029392"
    ],
    "tgn:id":2290877,
    "tgn:name":"Dog Island",
    "tgn:placetype":[
        "aat:300008791"
    ]
},
  "bbox": [],
  "geometry": {"coordinates":[-131.3167,54.9833],"type":"Point"}
}