{
  "id": 2313025,
  "type": "Feature",
  "properties": {
    "tgn:hierarchy":[
        "tgn:2313025",
        "tgn:1000001",
        "tgn:7012149",
        "tgn:2000527",
        "tgn:7007251",
        "tgn:7029392"
    ],
    "tgn:id":2313025,
    "tgn:name":"Elbow",
    "tgn:placetype":[
        "aat:300008347"
    ]
},
  "bbox": [],
  "geometry": {"coordinates":[-88.1167,38.6333],"type":"Point"}
}