{
  "id": 7438581,
  "type": "Feature",
  "properties": {
    "tgn:hierarchy":[
        "tgn:7438581",
        "tgn:7005586",
        "tgn:1000001",
        "tgn:7005560",
        "tgn:7029392"
    ],
    "tgn:id":7438581,
    "tgn:name":"Tierra Dura",
    "tgn:placetype":[
        "aat:300008347"
    ]
},
  "bbox": [],
  "geometry": {"coordinates":[-104.416667,20.466667],"type":"Point"}
}