{
  "id": 7590933,
  "type": "Feature",
  "properties": {
    "tgn:hierarchy":[
        "tgn:7590933",
        "tgn:1000004",
        "tgn:7000198",
        "tgn:7000799",
        "tgn:7029392"
    ],
    "tgn:id":7590933,
    "tgn:name:en":"Be\u0101spur",
    "tgn:placetype":[
        "aat:300008347"
    ]
},
  "bbox": [],
  "geometry": {"coordinates":[74.766667,32.534722],"type":"Point"}
}