{
  "id": 2212345,
  "type": "Feature",
  "properties": {
    "tgn:hierarchy":[
        "tgn:2212345",
        "tgn:1000001",
        "tgn:7012149",
        "tgn:1002787",
        "tgn:7007523",
        "tgn:7029392"
    ],
    "tgn:id":2212345,
    "tgn:name":"Buzzards Roost",
    "tgn:placetype":[
        "aat:300008347"
    ]
},
  "bbox": [],
  "geometry": {"coordinates":[-91.1667,39.3667],"type":"Point"}
}