<<<<<<< HEAD
{
  "id": 7361505,
  "type": "Feature",
  "properties": {
    "tgn:hierarchy":[
        "tgn:7361505",
        "tgn:1000001",
        "tgn:7005597",
        "tgn:7005560",
        "tgn:7029392"
    ],
    "tgn:id":7361505,
    "tgn:name":"El Corral Quemodo",
    "tgn:placetype":[
        "aat:300008347"
    ]
},
  "bbox": [],
  "geometry": {"coordinates":[-98.633333,25.1],"type":"Point"}
}
=======
{"geometry":{"type":"Point","coordinates":[-98.633333,25.100000]},"type":"Feature","properties":{"hierarchy":["tgn:7361505","tgn:1000001","tgn:7005597","tgn:7005560","tgn:7029392"],"placetype":["aat:300008347"],"id":7361505,"name:xx":"El Corral Quemodo"}}
>>>>>>> 03f74aca74312dbeaf24d7e61306dd6a786dc3d0
