{
  "id": 1015324,
  "type": "Feature",
  "properties": {
    "tgn:hierarchy":[
        "tgn:1015324",
        "tgn:7005685",
        "tgn:1000001",
        "tgn:7005804",
        "tgn:7029392"
    ],
    "tgn:id":1015324,
    "tgn:name":"Brossard",
    "tgn:placetype":[
        "aat:300008347",
        "aat:300008389",
        "aat:300387308",
        "aat:300265612"
    ]
},
  "bbox": [],
  "geometry": {"coordinates":[-73.5333,45.4667],"type":"Point"}
}