{
  "id": 2403366,
  "type": "Feature",
  "properties": {
    "tgn:hierarchy":[
        "tgn:2403366",
        "tgn:1000001",
        "tgn:7012149",
        "tgn:2001927",
        "tgn:7007825",
        "tgn:7029392"
    ],
    "tgn:id":2403366,
    "tgn:name":"Houston Cave",
    "tgn:placetype":[
        "aat:300008746"
    ]
},
  "bbox": [],
  "geometry": {"coordinates":[-87.9167,35.2333],"type":"Point"}
}