<<<<<<< HEAD
{
  "id": 7371701,
  "type": "Feature",
  "properties": {
    "tgn:hierarchy":[
        "tgn:7371701",
        "tgn:1000001",
        "tgn:7005599",
        "tgn:7005560",
        "tgn:7029392"
    ],
    "tgn:id":7371701,
    "tgn:name":"La Ensenada",
    "tgn:placetype":[
        "aat:300008347"
    ]
},
  "bbox": [],
  "geometry": {"coordinates":[-98.416667,21.633333],"type":"Point"}
}
=======
{"geometry":{"type":"Point","coordinates":[-98.416667,21.633333]},"type":"Feature","properties":{"hierarchy":["tgn:7371701","tgn:1000001","tgn:7005599","tgn:7005560","tgn:7029392"],"placetype":["aat:300008347"],"id":7371701,"name:xx":"La Ensenada"}}
>>>>>>> 03f74aca74312dbeaf24d7e61306dd6a786dc3d0
