{
  "id": 2489907,
  "type": "Feature",
  "properties": {
    "tgn:hierarchy":[
        "tgn:2489907",
        "tgn:1000001",
        "tgn:1002257",
        "tgn:7012149",
        "tgn:7007919",
        "tgn:7029392"
    ],
    "tgn:id":2489907,
    "tgn:name":"Malvern Hill",
    "tgn:placetype":[
        "aat:300008798"
    ]
},
  "bbox": [],
  "geometry": {"coordinates":[-77.2333,37.3833],"type":"Point"}
}