{
  "id": 2236844,
  "type": "Feature",
  "properties": {
    "tgn:hierarchy":[
        "tgn:2236844",
        "tgn:1000001",
        "tgn:7012149",
        "tgn:2001955",
        "tgn:7007826",
        "tgn:7029392"
    ],
    "tgn:id":2236844,
    "tgn:name":"Childress, Lake",
    "tgn:placetype":[
        "aat:300006191"
    ]
},
  "bbox": [],
  "geometry": {"coordinates":[-100.35,34.4667],"type":"Point"}
}