{
  "id": 7034374,
  "type": "Feature",
  "properties": {
    "tgn:hierarchy":[
        "tgn:7034374",
        "tgn:1001641",
        "tgn:1000003",
        "tgn:7003121",
        "tgn:1000080",
        "tgn:7029392"
    ],
    "tgn:id":7034374,
    "tgn:name":"Porto Columbu - Perd'e Sali",
    "tgn:placetype":[
        "aat:300008347"
    ]
},
  "bbox": [],
  "geometry": {"coordinates":[9.022778,39.023611],"type":"Point"}
}