{
  "id": 7565346,
  "type": "Feature",
  "properties": {
    "tgn:hierarchy":[
        "tgn:7565346",
        "tgn:1000004",
        "tgn:7000198",
        "tgn:1001894",
        "tgn:7029392"
    ],
    "tgn:id":7565346,
    "tgn:name:en":"Sew\u0101r",
    "tgn:placetype":[
        "aat:300167671"
    ]
},
  "bbox": [],
  "geometry": {"coordinates":[79.056122,24.739799],"type":"Point"}
}