{
  "id": 1075109,
  "type": "Feature",
  "properties": {
    "tgn:hierarchy":[
        "tgn:1075109",
        "tgn:1000004",
        "tgn:1001869",
        "tgn:7000198",
        "tgn:7029392"
    ],
    "tgn:id":1075109,
    "tgn:name:en":"Dedi\u0101p\u0101da",
    "tgn:placetype":[
        "aat:300008347"
    ]
},
  "bbox": [],
  "geometry": {"coordinates":[73.583333,21.633333],"type":"Point"}
}