{
  "id": 1102874,
  "type": "Feature",
  "properties": {
    "tgn:hierarchy":[
        "tgn:1102874",
        "tgn:7000490",
        "tgn:1000006",
        "tgn:7001828",
        "tgn:7001923",
        "tgn:7029392"
    ],
    "tgn:id":1102874,
    "tgn:name":"Hyde Park",
    "tgn:placetype":[
        "aat:300008187"
    ]
},
  "bbox": [],
  "geometry": {"coordinates":[151.2167,-33.8833],"type":"Point"}
}