<<<<<<< HEAD
{
  "id": 2250426,
  "type": "Feature",
  "properties": {
    "tgn:hierarchy":[
        "tgn:2250426",
        "tgn:1000001",
        "tgn:7012149",
        "tgn:2001915",
        "tgn:7007825",
        "tgn:7029392"
    ],
    "tgn:id":2250426,
    "tgn:name":"Colonial Country Club Sixteenth Hole Lake",
    "tgn:placetype":[
        "aat:300006191"
    ]
},
  "bbox": [],
  "geometry": {"coordinates":[-89.7833,35.1833],"type":"Point"}
}
=======
{"geometry":{"type":"Point","coordinates":[-89.783300,35.183300]},"type":"Feature","properties":{"hierarchy":["tgn:2250426","tgn:1000001","tgn:7012149","tgn:2001915","tgn:7007825","tgn:7029392"],"placetype":["aat:300006191"],"id":2250426,"name:xx":"Colonial Country Club Sixteenth Hole Lake"}}
>>>>>>> 03f74aca74312dbeaf24d7e61306dd6a786dc3d0
