<<<<<<< HEAD
{
  "id": 7377190,
  "type": "Feature",
  "properties": {
    "tgn:hierarchy":[
        "tgn:7377190",
        "tgn:7005586",
        "tgn:1000001",
        "tgn:7005560",
        "tgn:7029392"
    ],
    "tgn:id":7377190,
    "tgn:name":"Las Animas, Cordon",
    "tgn:placetype":[
        "aat:300008795"
    ]
},
  "bbox": [],
  "geometry": {"coordinates":[-105.016667,20.566667],"type":"Point"}
}
=======
{"geometry":{"type":"Point","coordinates":[-105.016667,20.566667]},"type":"Feature","properties":{"hierarchy":["tgn:7377190","tgn:7005586","tgn:1000001","tgn:7005560","tgn:7029392"],"placetype":["aat:300008795"],"id":7377190,"name:xx":"Las Animas, Cordon"}}
>>>>>>> 03f74aca74312dbeaf24d7e61306dd6a786dc3d0
