{
  "id": 7377190,
  "type": "Feature",
  "properties": {
    "tgn:hierarchy":[
        "tgn:7377190",
        "tgn:7005586",
        "tgn:1000001",
        "tgn:7005560",
        "tgn:7029392"
    ],
    "tgn:id":7377190,
    "tgn:name":"Las Animas, Cordon",
    "tgn:placetype":[
        "aat:300008795"
    ]
},
  "bbox": [],
  "geometry": {"coordinates":[-105.016667,20.566667],"type":"Point"}
}