{
  "id": 7085084,
  "type": "Feature",
  "properties": {
    "tgn:hierarchy":[
        "tgn:7085084",
        "tgn:7000096",
        "tgn:1000003",
        "tgn:7000084",
        "tgn:7029392"
    ],
    "tgn:id":7085084,
    "tgn:name":"Werlsee",
    "tgn:placetype":[
        "aat:300008680"
    ]
},
  "bbox": [],
  "geometry": {"coordinates":[13.816667,52.416667],"type":"Point"}
}