{
  "id": 7457757,
  "type": "Feature",
  "properties": {
    "tgn:hierarchy":[
        "tgn:7457757",
        "tgn:7002445",
        "tgn:1000003",
        "tgn:7008160",
        "tgn:7008591",
        "tgn:7029392"
    ],
    "tgn:id":7457757,
    "tgn:name:en":"Lynn Channel",
    "tgn:placetype":[
        "aat:300008713"
    ]
},
  "bbox": [],
  "geometry": {"coordinates":[0.283333,52.916667],"type":"Point"}
}