{
  "id": 7415425,
  "type": "Feature",
  "properties": {
    "tgn:hierarchy":[
        "tgn:7415425",
        "tgn:7005584",
        "tgn:1000001",
        "tgn:7005560",
        "tgn:7029392"
    ],
    "tgn:id":7415425,
    "tgn:name":"Presa Las Trojes del Molino",
    "tgn:placetype":[
        "aat:300006191"
    ]
},
  "bbox": [],
  "geometry": {"coordinates":[-101.394444,21.558611],"type":"Point"}
}