{
  "id": 7548285,
  "type": "Feature",
  "properties": {
    "tgn:hierarchy":[
        "tgn:7548285",
        "tgn:1000004",
        "tgn:7000198",
        "tgn:7031783",
        "tgn:7029392"
    ],
    "tgn:id":7548285,
    "tgn:name:en":"Bara B\u0101na",
    "tgn:placetype":[
        "aat:300008347"
    ]
},
  "bbox": [],
  "geometry": {"coordinates":[85.917637,22.638949],"type":"Point"}
}