<<<<<<< HEAD
{
  "id": 2401137,
  "type": "Feature",
  "properties": {
    "tgn:hierarchy":[
        "tgn:2401137",
        "tgn:1000001",
        "tgn:7012149",
        "tgn:2001284",
        "tgn:7007524",
        "tgn:7029392"
    ],
    "tgn:id":2401137,
    "tgn:name":"Horsefly Creek",
    "tgn:placetype":[
        "aat:300008706"
    ]
},
  "bbox": [],
  "geometry": {"coordinates":[-112.4167,46.9667],"type":"Point"}
}
=======
{"geometry":{"type":"Point","coordinates":[-112.416700,46.966700]},"type":"Feature","properties":{"hierarchy":["tgn:2401137","tgn:1000001","tgn:7012149","tgn:2001284","tgn:7007524","tgn:7029392"],"placetype":["aat:300008706"],"id":2401137,"name:xx":"Horsefly Creek"}}
>>>>>>> 03f74aca74312dbeaf24d7e61306dd6a786dc3d0
