{
  "id": 2366309,
  "type": "Feature",
  "properties": {
    "tgn:hierarchy":[
        "tgn:2366309",
        "tgn:1000001",
        "tgn:2002109",
        "tgn:7012149",
        "tgn:7007827",
        "tgn:7029392"
    ],
    "tgn:id":2366309,
    "tgn:name":"Griffin Point",
    "tgn:placetype":[
        "aat:300008798"
    ]
},
  "bbox": [],
  "geometry": {"coordinates":[-111.8167,37.8667],"type":"Point"}
}