{
  "id": 2185064,
  "type": "Feature",
  "properties": {
    "tgn:hierarchy":[
        "tgn:2185064",
        "tgn:1000001",
        "tgn:2000868",
        "tgn:7012149",
        "tgn:7007256",
        "tgn:7029392"
    ],
    "tgn:id":2185064,
    "tgn:name":"Boggy Bayou",
    "tgn:placetype":[
        "aat:300008699"
    ]
},
  "bbox": [],
  "geometry": {"coordinates":[-91.5833,31.3833],"type":"Point"}
}