{
  "id": 2485214,
  "type": "Feature",
  "properties": {
    "tgn:hierarchy":[
        "tgn:2485214",
        "tgn:1000001",
        "tgn:7012149",
        "tgn:7029392"
    ],
    "tgn:id":2485214,
    "tgn:name":"Lawrence Branch",
    "tgn:placetype":[
        "aat:300008699"
    ]
},
  "bbox": [],
  "geometry": {"coordinates":[-88.2333,36.4667],"type":"Point"}
}