{
  "id": 4004147,
  "type": "Feature",
  "properties": {
    "tgn:hierarchy":[
        "tgn:4004147",
        "tgn:7594006",
        "tgn:1000003",
        "tgn:1000066",
        "tgn:7029392"
    ],
    "tgn:id":4004147,
    "tgn:name":"Fur",
    "tgn:placetype":[
        "aat:300008791"
    ]
},
  "bbox": [],
  "geometry": {"coordinates":[9.016429,56.827254],"type":"Point"}
}