<<<<<<< HEAD
{
  "id": 7362482,
  "type": "Feature",
  "properties": {
    "tgn:hierarchy":[
        "tgn:7362482",
        "tgn:7005586",
        "tgn:1000001",
        "tgn:7005560",
        "tgn:7029392"
    ],
    "tgn:id":7362482,
    "tgn:name":"El Durazno",
    "tgn:placetype":[
        "aat:300008347"
    ]
},
  "bbox": [],
  "geometry": {"coordinates":[-102.966667,21.1],"type":"Point"}
}
=======
{"geometry":{"type":"Point","coordinates":[-102.966667,21.100000]},"type":"Feature","properties":{"hierarchy":["tgn:7362482","tgn:7005586","tgn:1000001","tgn:7005560","tgn:7029392"],"placetype":["aat:300008347"],"id":7362482,"name:xx":"El Durazno"}}
>>>>>>> 03f74aca74312dbeaf24d7e61306dd6a786dc3d0
