{
  "id": 7364567,
  "type": "Feature",
  "properties": {
    "tgn:hierarchy":[
        "tgn:7364567",
        "tgn:1000001",
        "tgn:7005591",
        "tgn:7005560",
        "tgn:7029392"
    ],
    "tgn:id":7364567,
    "tgn:name":"Figueroa",
    "tgn:placetype":[
        "aat:300008347"
    ]
},
  "bbox": [],
  "geometry": {"coordinates":[-96.383333,15.783333],"type":"Point"}
}