<<<<<<< HEAD
{
  "id": 7473394,
  "type": "Feature",
  "properties": {
    "tgn:hierarchy":[
        "tgn:7473394",
        "tgn:1000004",
        "tgn:7490934",
        "tgn:1000141",
        "tgn:7029392"
    ],
    "tgn:id":7473394,
    "tgn:name":"Yanqian",
    "tgn:placetype":[
        "aat:300008347"
    ]
},
  "bbox": [],
  "geometry": {"coordinates":[120.47,23.340833],"type":"Point"}
}
=======
{"geometry":{"type":"Point","coordinates":[120.470000,23.340833]},"type":"Feature","properties":{"hierarchy":["tgn:7473394","tgn:1000004","tgn:7490934","tgn:1000141","tgn:7029392"],"placetype":["aat:300008347"],"id":7473394,"name:xx":"Yanqian"}}
>>>>>>> 03f74aca74312dbeaf24d7e61306dd6a786dc3d0
