{
  "id": 1042960,
  "type": "Feature",
  "properties": {
    "tgn:hierarchy":[
        "tgn:1042960",
        "tgn:7001199",
        "tgn:7003491",
        "tgn:1000003",
        "tgn:1000078",
        "tgn:7029392"
    ],
    "tgn:id":1042960,
    "tgn:name":"Oldcastle",
    "tgn:placetype":[
        "aat:300008347"
    ]
},
  "bbox": [],
  "geometry": {"coordinates":[-7.1667,53.7667],"type":"Point"}
}