{
  "id": 7593347,
  "type": "Feature",
  "properties": {
    "tgn:hierarchy":[
        "tgn:7593347",
        "tgn:1006881",
        "tgn:1001914",
        "tgn:1000002",
        "tgn:1000059",
        "tgn:7029392"
    ],
    "tgn:id":7593347,
    "tgn:name":"Ruinas de Nueva C\u00e1diz",
    "tgn:placetype":[
        "aat:300000810"
    ]
},
  "bbox": [],
  "geometry": {"coordinates":[-64.146,10.82],"type":"Point"}
}