<<<<<<< HEAD
{
  "id": 7366088,
  "type": "Feature",
  "properties": {
    "tgn:hierarchy":[
        "tgn:7366088",
        "tgn:1000001",
        "tgn:7005599",
        "tgn:7005560",
        "tgn:7029392"
    ],
    "tgn:id":7366088,
    "tgn:name":"Gallega, Arrecife de la",
    "tgn:placetype":[
        "aat:300008808"
    ]
},
  "bbox": [],
  "geometry": {"coordinates":[-96.133333,19.2],"type":"Point"}
}
=======
{"geometry":{"type":"Point","coordinates":[-96.133333,19.200000]},"type":"Feature","properties":{"hierarchy":["tgn:7366088","tgn:1000001","tgn:7005599","tgn:7005560","tgn:7029392"],"placetype":["aat:300008808"],"id":7366088,"name:xx":"Gallega, Arrecife de la"}}
>>>>>>> 03f74aca74312dbeaf24d7e61306dd6a786dc3d0
