{
  "id": 2669738,
  "type": "Feature",
  "properties": {
    "tgn:hierarchy":[
        "tgn:2669738",
        "tgn:1000001",
        "tgn:7012149",
        "tgn:2000183",
        "tgn:7007157",
        "tgn:7029392"
    ],
    "tgn:id":2669738,
    "tgn:name":"Slim Lake",
    "tgn:placetype":[
        "aat:300008680"
    ]
},
  "bbox": [],
  "geometry": {"coordinates":[-118.35,36.75],"type":"Point"}
}