<<<<<<< HEAD
{
  "id": 2338960,
  "type": "Feature",
  "properties": {
    "tgn:hierarchy":[
        "tgn:2338960",
        "tgn:1000001",
        "tgn:7012149",
        "tgn:7007920",
        "tgn:7029392"
    ],
    "tgn:id":2338960,
    "tgn:name":"Franklin D Roosevelt Lake",
    "tgn:placetype":[
        "aat:300006191"
    ]
},
  "bbox": [],
  "geometry": {"coordinates":[-118.9667,47.95],"type":"Point"}
}
=======
{"geometry":{"type":"Point","coordinates":[-118.966700,47.950000]},"type":"Feature","properties":{"hierarchy":["tgn:2338960","tgn:1000001","tgn:7012149","tgn:7007920","tgn:7029392"],"placetype":["aat:300006191"],"id":2338960,"name:xx":"Franklin D Roosevelt Lake"}}
>>>>>>> 03f74aca74312dbeaf24d7e61306dd6a786dc3d0
