{
  "id": 1102205,
  "type": "Feature",
  "properties": {
    "tgn:hierarchy":[
        "tgn:1102205",
        "tgn:1000001",
        "tgn:7012149",
        "tgn:7007157",
        "tgn:7029392"
    ],
    "tgn:id":1102205,
    "tgn:name":"Castle Crags State Park",
    "tgn:placetype":[
        "aat:300008192"
    ]
},
  "bbox": [],
  "geometry": {"coordinates":[-122.35,41.1667],"type":"Point"}
}