{
  "id": 2363313,
  "type": "Feature",
  "properties": {
    "tgn:hierarchy":[
        "tgn:2363313",
        "tgn:1000001",
        "tgn:7012149",
        "tgn:2000227",
        "tgn:7007158",
        "tgn:7029392"
    ],
    "tgn:id":2363313,
    "tgn:name":"Green Canyon",
    "tgn:placetype":[
        "aat:300008761"
    ]
},
  "bbox": [],
  "geometry": {"coordinates":[-104.6667,37.4333],"type":"Point"}
}