{
  "id": 7177121,
  "type": "Feature",
  "properties": {
    "tgn:hierarchy":[
        "tgn:7177121",
        "tgn:1000003",
        "tgn:7003677",
        "tgn:7000084",
        "tgn:7029392"
    ],
    "tgn:id":7177121,
    "tgn:name":"Halemeier",
    "tgn:placetype":[
        "aat:300000206"
    ]
},
  "bbox": [],
  "geometry": {"coordinates":[8.566667,52.05],"type":"Point"}
}