{
  "id": 2502804,
  "type": "Feature",
  "properties": {
    "tgn:hierarchy":[
        "tgn:2502804",
        "tgn:1000001",
        "tgn:7006451",
        "tgn:7012149",
        "tgn:2000097",
        "tgn:7029392"
    ],
    "tgn:id":2502804,
    "tgn:name":"McMicken Dam Outlet Channel",
    "tgn:placetype":[
        "aat:300006075"
    ]
},
  "bbox": [],
  "geometry": {"coordinates":[-112.3833,33.6833],"type":"Point"}
}