{
  "id": 7469857,
  "type": "Feature",
  "properties": {
    "tgn:hierarchy":[
        "tgn:7469857",
        "tgn:7487020",
        "tgn:1000004",
        "tgn:1000141",
        "tgn:7029392"
    ],
    "tgn:id":7469857,
    "tgn:name":"Zhongzhuang",
    "tgn:placetype":[
        "aat:300008347"
    ]
},
  "bbox": [],
  "geometry": {"coordinates":[120.729722,24.331944],"type":"Point"}
}