{
  "id": 2475740,
  "type": "Feature",
  "properties": {
    "tgn:hierarchy":[
        "tgn:2475740",
        "tgn:1000001",
        "tgn:7012149",
        "tgn:1002682",
        "tgn:7007710",
        "tgn:7029392"
    ],
    "tgn:id":2475740,
    "tgn:name":"Lucky Run",
    "tgn:placetype":[
        "aat:300008699"
    ]
},
  "bbox": [],
  "geometry": {"coordinates":[-75.2167,41.1667],"type":"Point"}
}