{
  "id": 2245057,
  "type": "Feature",
  "properties": {
    "tgn:hierarchy":[
        "tgn:2245057",
        "tgn:1000001",
        "tgn:7012149",
        "tgn:2002168",
        "tgn:7007919",
        "tgn:7029392"
    ],
    "tgn:id":2245057,
    "tgn:name":"Clover Lick Hollow",
    "tgn:placetype":[
        "aat:300008761"
    ]
},
  "bbox": [],
  "geometry": {"coordinates":[-79.45,38.25],"type":"Point"}
}