{
  "id": 2422015,
  "type": "Feature",
  "properties": {
    "tgn:hierarchy":[
        "tgn:2422015",
        "tgn:1000001",
        "tgn:7012149",
        "tgn:1002785",
        "tgn:7007920",
        "tgn:7029392"
    ],
    "tgn:id":2422015,
    "tgn:name":"Jim Creek",
    "tgn:placetype":[
        "aat:300008706"
    ]
},
  "bbox": [],
  "geometry": {"coordinates":[-121.6333,47.05],"type":"Point"}
}