<<<<<<< HEAD
{
  "id": 7470733,
  "type": "Feature",
  "properties": {
    "tgn:hierarchy":[
        "tgn:7470733",
        "tgn:1000004",
        "tgn:7001009",
        "tgn:1000141",
        "tgn:7029392"
    ],
    "tgn:id":7470733,
    "tgn:name":"Chuyun Shan",
    "tgn:placetype":[
        "aat:300008798"
    ]
},
  "bbox": [],
  "geometry": {"coordinates":[120.898279,24.227942],"type":"Point"}
}
=======
{"geometry":{"type":"Point","coordinates":[120.898279,24.227942]},"type":"Feature","properties":{"hierarchy":["tgn:7470733","tgn:1000004","tgn:7001009","tgn:1000141","tgn:7029392"],"placetype":["aat:300008798"],"id":7470733,"name:xx":"Chuyun Shan"}}
>>>>>>> 03f74aca74312dbeaf24d7e61306dd6a786dc3d0
