{
  "id": 7266098,
  "type": "Feature",
  "properties": {
    "tgn:concordances":{
        "gn:id":"2754818"
    },
    "tgn:hierarchy":[
        "tgn:7266098",
        "tgn:1000003",
        "tgn:7003622",
        "tgn:7016845",
        "tgn:7029392"
    ],
    "tgn:id":7266098,
    "tgn:name:nl":"Harles",
    "tgn:placetype":[
        "aat:300008347"
    ]
},
  "bbox": [],
  "geometry": {"coordinates":[5.983333,50.783333],"type":"Point"}
}