{
  "id": 7139441,
  "type": "Feature",
  "properties": {
    "tgn:hierarchy":[
        "tgn:7139441",
        "tgn:7003669",
        "tgn:1000003",
        "tgn:7000084",
        "tgn:7029392"
    ],
    "tgn:id":7139441,
    "tgn:name":"Lausbach",
    "tgn:placetype":[
        "aat:300000206"
    ]
},
  "bbox": [],
  "geometry": {"coordinates":[12.166667,48.45],"type":"Point"}
}