<<<<<<< HEAD
{
  "id": 7354873,
  "type": "Feature",
  "properties": {
    "tgn:hierarchy":[
        "tgn:7354873",
        "tgn:7005581",
        "tgn:1000001",
        "tgn:7005560",
        "tgn:7029392"
    ],
    "tgn:id":7354873,
    "tgn:name":"Cane, Cerro",
    "tgn:placetype":[
        "aat:300008795"
    ]
},
  "bbox": [],
  "geometry": {"coordinates":[-106.683333,30.166667],"type":"Point"}
}
=======
{"geometry":{"type":"Point","coordinates":[-106.683333,30.166667]},"type":"Feature","properties":{"hierarchy":["tgn:7354873","tgn:7005581","tgn:1000001","tgn:7005560","tgn:7029392"],"placetype":["aat:300008795"],"id":7354873,"name:xx":"Cane, Cerro"}}
>>>>>>> 03f74aca74312dbeaf24d7e61306dd6a786dc3d0
