{
  "id": 7425668,
  "type": "Feature",
  "properties": {
    "tgn:hierarchy":[
        "tgn:7425668",
        "tgn:1000001",
        "tgn:7005594",
        "tgn:7005560",
        "tgn:7029392"
    ],
    "tgn:id":7425668,
    "tgn:name":"La Noria",
    "tgn:placetype":[
        "aat:300008347"
    ]
},
  "bbox": [],
  "geometry": {"coordinates":[-100.733333,22.383333],"type":"Point"}
}