{
  "id": 7453023,
  "type": "Feature",
  "properties": {
    "tgn:hierarchy":[
        "tgn:7453023",
        "tgn:7002444",
        "tgn:1000003",
        "tgn:7019091",
        "tgn:7008591",
        "tgn:7029392"
    ],
    "tgn:id":7453023,
    "tgn:name:en":"Clauchlands Point",
    "tgn:placetype":[
        "aat:300386846"
    ]
},
  "bbox": [],
  "geometry": {"coordinates":[-5.083333,55.55],"type":"Point"}
}