{
  "id": 2173865,
  "type": "Feature",
  "properties": {
    "tgn:hierarchy":[
        "tgn:2173865",
        "tgn:7006450",
        "tgn:1000001",
        "tgn:2124089",
        "tgn:7012149",
        "tgn:7029392"
    ],
    "tgn:id":2173865,
    "tgn:name":"Bird Island",
    "tgn:placetype":[
        "aat:300008791"
    ]
},
  "bbox": [],
  "geometry": {"coordinates":[-134.8333,58.4833],"type":"Point"}
}