{
  "id": 2716215,
  "type": "Feature",
  "properties": {
    "tgn:hierarchy":[
        "tgn:2716215",
        "tgn:1000001",
        "tgn:7012149",
        "tgn:2000648",
        "tgn:7007253",
        "tgn:7029392"
    ],
    "tgn:id":2716215,
    "tgn:name":"Thayer Lake",
    "tgn:placetype":[
        "aat:300006191"
    ]
},
  "bbox": [],
  "geometry": {"coordinates":[-94.05,41.0167],"type":"Point"}
}