<<<<<<< HEAD
{
  "id": 2403716,
  "type": "Feature",
  "properties": {
    "tgn:hierarchy":[
        "tgn:2403716",
        "tgn:1000001",
        "tgn:7012149",
        "tgn:7007158",
        "tgn:7029392"
    ],
    "tgn:id":2403716,
    "tgn:name":"Howard Mountain",
    "tgn:placetype":[
        "aat:300008798"
    ]
},
  "bbox": [],
  "geometry": {"coordinates":[-105.8833,40.4167],"type":"Point"}
}
=======
{"geometry":{"type":"Point","coordinates":[-105.883300,40.416700]},"type":"Feature","properties":{"hierarchy":["tgn:2403716","tgn:1000001","tgn:7012149","tgn:7007158","tgn:7029392"],"placetype":["aat:300008798"],"id":2403716,"name:xx":"Howard Mountain"}}
>>>>>>> 03f74aca74312dbeaf24d7e61306dd6a786dc3d0
