{
  "id": 2403716,
  "type": "Feature",
  "properties": {
    "tgn:hierarchy":[
        "tgn:2403716",
        "tgn:1000001",
        "tgn:7012149",
        "tgn:7007158",
        "tgn:7029392"
    ],
    "tgn:id":2403716,
    "tgn:name":"Howard Mountain",
    "tgn:placetype":[
        "aat:300008798"
    ]
},
  "bbox": [],
  "geometry": {"coordinates":[-105.8833,40.4167],"type":"Point"}
}