{
  "id": 7558679,
  "type": "Feature",
  "properties": {
    "tgn:hierarchy":[
        "tgn:7558679",
        "tgn:1000004",
        "tgn:7000198",
        "tgn:7016788",
        "tgn:7029392"
    ],
    "tgn:id":7558679,
    "tgn:name:en":"Rel\u0101wan",
    "tgn:placetype":[
        "aat:300008347"
    ]
},
  "bbox": [],
  "geometry": {"coordinates":[76.666667,25.25],"type":"Point"}
}