{
  "id": 2426246,
  "type": "Feature",
  "properties": {
    "tgn:hierarchy":[
        "tgn:2426246",
        "tgn:1000001",
        "tgn:7012149",
        "tgn:7007158",
        "tgn:7029392"
    ],
    "tgn:id":2426246,
    "tgn:name":"Jones Creek",
    "tgn:placetype":[
        "aat:300008706"
    ]
},
  "bbox": [],
  "geometry": {"coordinates":[-105.4167,39.4667],"type":"Point"}
}