{
  "id": 7243784,
  "type": "Feature",
  "properties": {
    "tgn:hierarchy":[
        "tgn:7243784",
        "tgn:7003456",
        "tgn:1000003",
        "tgn:1000063",
        "tgn:7018236",
        "tgn:7029392"
    ],
    "tgn:id":7243784,
    "tgn:name":"Hulseinde",
    "tgn:placetype":[
        "aat:300008347"
    ]
},
  "bbox": [],
  "geometry": {"coordinates":[4.85,51.133333],"type":"Point"}
}