{
  "id": 2689843,
  "type": "Feature",
  "properties": {
    "tgn:hierarchy":[
        "tgn:2689843",
        "tgn:1000001",
        "tgn:7012149",
        "tgn:2001146",
        "tgn:7007522",
        "tgn:7029392"
    ],
    "tgn:id":2689843,
    "tgn:name":"Squirrel Branch",
    "tgn:placetype":[
        "aat:300008699"
    ]
},
  "bbox": [],
  "geometry": {"coordinates":[-90.1333,32.2167],"type":"Point"}
}