{
  "id": 2568034,
  "type": "Feature",
  "properties": {
    "tgn:hierarchy":[
        "tgn:2568034",
        "tgn:1000001",
        "tgn:7012149",
        "tgn:2001456",
        "tgn:7007566",
        "tgn:7029392"
    ],
    "tgn:id":2568034,
    "tgn:name":"Paraje",
    "tgn:placetype":[
        "aat:300008347",
        "aat:300167671"
    ]
},
  "bbox": [],
  "geometry": {"coordinates":[-107.05,33.55],"type":"Point"}
}