{
  "id": 7366276,
  "type": "Feature",
  "properties": {
    "tgn:hierarchy":[
        "tgn:7366276",
        "tgn:1001853",
        "tgn:1000001",
        "tgn:7005560",
        "tgn:7029392"
    ],
    "tgn:id":7366276,
    "tgn:name":"Escuadra, Cerro de la",
    "tgn:placetype":[
        "aat:300008795"
    ]
},
  "bbox": [],
  "geometry": {"coordinates":[-103.366667,27.766667],"type":"Point"}
}