{
  "id": 2187497,
  "type": "Feature",
  "properties": {
    "tgn:hierarchy":[
        "tgn:2187497",
        "tgn:1000001",
        "tgn:7016172",
        "tgn:7012149",
        "tgn:2000170",
        "tgn:7029392"
    ],
    "tgn:id":2187497,
    "tgn:name":"Booneville Lake",
    "tgn:placetype":[
        "aat:300006191"
    ]
},
  "bbox": [],
  "geometry": {"coordinates":[-94.05,35.1333],"type":"Point"}
}