{
  "id": 2714558,
  "type": "Feature",
  "properties": {
    "tgn:hierarchy":[
        "tgn:2714558",
        "tgn:7002659",
        "tgn:1000001",
        "tgn:7012149",
        "tgn:2000025",
        "tgn:7029392"
    ],
    "tgn:id":2714558,
    "tgn:name":"Ten Cedars Estates",
    "tgn:placetype":[
        "aat:300008347"
    ]
},
  "bbox": [],
  "geometry": {"coordinates":[-86.2333,32.65],"type":"Point"}
}