{
  "id": 2694713,
  "type": "Feature",
  "properties": {
    "tgn:hierarchy":[
        "tgn:2694713",
        "tgn:1000001",
        "tgn:2001417",
        "tgn:7012149",
        "tgn:7007526",
        "tgn:7029392"
    ],
    "tgn:id":2694713,
    "tgn:name":"Stewart Spring",
    "tgn:placetype":[
        "aat:300008697"
    ]
},
  "bbox": [],
  "geometry": {"coordinates":[-117.9167,38.5833],"type":"Point"}
}