{
  "id": 7483055,
  "type": "Feature",
  "properties": {
    "tgn:hierarchy":[
        "tgn:7483055",
        "tgn:7468018",
        "tgn:1000004",
        "tgn:1000141",
        "tgn:7029392"
    ],
    "tgn:id":7483055,
    "tgn:name":"Laiji Daqiao",
    "tgn:placetype":[
        "aat:300007836"
    ]
},
  "bbox": [],
  "geometry": {"coordinates":[120.738611,23.526667],"type":"Point"}
}