{
  "id": 2209335,
  "type": "Feature",
  "properties": {
    "tgn:hierarchy":[
        "tgn:2209335",
        "tgn:1000001",
        "tgn:2001411",
        "tgn:7012149",
        "tgn:7007526",
        "tgn:7029392"
    ],
    "tgn:id":2209335,
    "tgn:name":"Burnt Reservoir",
    "tgn:placetype":[
        "aat:300006191"
    ]
},
  "bbox": [],
  "geometry": {"coordinates":[-114.0667,41.8167],"type":"Point"}
}