{
  "id": 7506241,
  "type": "Feature",
  "properties": {
    "tgn:hierarchy":[
        "tgn:7506241",
        "tgn:1009227",
        "tgn:7001866",
        "tgn:1000226",
        "tgn:1000006",
        "tgn:7029392"
    ],
    "tgn:id":7506241,
    "tgn:name:en":"Saint Albans",
    "tgn:placetype":[
        "aat:300008347"
    ]
},
  "bbox": [],
  "geometry": {"coordinates":[172.616667,-43.516667],"type":"Point"}
}