<<<<<<< HEAD
{
  "id": 2333844,
  "type": "Feature",
  "properties": {
    "tgn:hierarchy":[
        "tgn:2333844",
        "tgn:1000001",
        "tgn:2001424",
        "tgn:7012149",
        "tgn:7007564",
        "tgn:7029392"
    ],
    "tgn:id":2333844,
    "tgn:name":"Forbes Mountain",
    "tgn:placetype":[
        "aat:300008798"
    ]
},
  "bbox": [],
  "geometry": {"coordinates":[-71.8167,43.5667],"type":"Point"}
}
=======
{"geometry":{"type":"Point","coordinates":[-71.816700,43.566700]},"type":"Feature","properties":{"hierarchy":["tgn:2333844","tgn:1000001","tgn:2001424","tgn:7012149","tgn:7007564","tgn:7029392"],"placetype":["aat:300008798"],"id":2333844,"name:xx":"Forbes Mountain"}}
>>>>>>> 03f74aca74312dbeaf24d7e61306dd6a786dc3d0
