{
  "id": 2473805,
  "type": "Feature",
  "properties": {
    "tgn:hierarchy":[
        "tgn:2473805",
        "tgn:7002659",
        "tgn:1000001",
        "tgn:7012149",
        "tgn:2000050",
        "tgn:7029392"
    ],
    "tgn:id":2473805,
    "tgn:name":"Lower Gause Bar",
    "tgn:placetype":[
        "aat:300132348"
    ]
},
  "bbox": [],
  "geometry": {"coordinates":[-86.3667,32.4167],"type":"Point"}
}