{
  "id": 2546163,
  "type": "Feature",
  "properties": {
    "tgn:hierarchy":[
        "tgn:2546163",
        "tgn:1000001",
        "tgn:7012149",
        "tgn:7007157",
        "tgn:1002621",
        "tgn:7029392"
    ],
    "tgn:id":2546163,
    "tgn:name":"North Fork Fine Gold Creek",
    "tgn:placetype":[
        "aat:300008706"
    ]
},
  "bbox": [],
  "geometry": {"coordinates":[-119.65,37.25],"type":"Point"}
}