{
  "id": 2151278,
  "type": "Feature",
  "properties": {
    "tgn:hierarchy":[
        "tgn:2151278",
        "tgn:1000001",
        "tgn:7014423",
        "tgn:7012149",
        "tgn:7007517",
        "tgn:7029392"
    ],
    "tgn:id":2151278,
    "tgn:name":"Bates Brook",
    "tgn:placetype":[
        "aat:300008699"
    ]
},
  "bbox": [],
  "geometry": {"coordinates":[-70.9333,41.85],"type":"Point"}
}