{
  "id": 2599735,
  "type": "Feature",
  "properties": {
    "tgn:hierarchy":[
        "tgn:2599735",
        "tgn:1000001",
        "tgn:7012149",
        "tgn:2001915",
        "tgn:7007825",
        "tgn:7029392"
    ],
    "tgn:id":2599735,
    "tgn:name":"Prosperity",
    "tgn:placetype":[
        "aat:300008347"
    ]
},
  "bbox": [],
  "geometry": {"coordinates":[-89.8667,35.25],"type":"Point"}
}