{
  "id": 2294637,
  "type": "Feature",
  "properties": {
    "tgn:hierarchy":[
        "tgn:2294637",
        "tgn:1000001",
        "tgn:7012149",
        "tgn:2001607",
        "tgn:7007705",
        "tgn:7029392"
    ],
    "tgn:id":2294637,
    "tgn:name":"Drady",
    "tgn:placetype":[
        "aat:300008347"
    ]
},
  "bbox": [],
  "geometry": {"coordinates":[-101.4167,48.15],"type":"Point"}
}