{
  "id": 2297341,
  "type": "Feature",
  "properties": {
    "tgn:hierarchy":[
        "tgn:2297341",
        "tgn:1000001",
        "tgn:7016172",
        "tgn:7012149",
        "tgn:2000128",
        "tgn:7029392"
    ],
    "tgn:id":2297341,
    "tgn:name":"Dry Fork",
    "tgn:placetype":[
        "aat:300008699"
    ]
},
  "bbox": [],
  "geometry": {"coordinates":[-93.95,35.6833],"type":"Point"}
}