{
  "id": 7307422,
  "type": "Feature",
  "properties": {
    "tgn:hierarchy":[
        "tgn:7307422",
        "tgn:7001122",
        "tgn:1000003",
        "tgn:7002765",
        "tgn:1000095",
        "tgn:7029392"
    ],
    "tgn:id":7307422,
    "tgn:name":"Mabres, Punta",
    "tgn:placetype":[
        "aat:300386846"
    ]
},
  "bbox": [],
  "geometry": {"coordinates":[4.283333,39.816667],"type":"Point"}
}