{
  "id": 2761693,
  "type": "Feature",
  "properties": {
    "tgn:hierarchy":[
        "tgn:2761693",
        "tgn:1000001",
        "tgn:7012149",
        "tgn:2001914",
        "tgn:7007825",
        "tgn:7029392"
    ],
    "tgn:id":2761693,
    "tgn:name":"West Point",
    "tgn:placetype":[
        "aat:300008798"
    ]
},
  "bbox": [],
  "geometry": {"coordinates":[-83.45,35.65],"type":"Point"}
}