{
  "id": 7168494,
  "type": "Feature",
  "properties": {
    "tgn:hierarchy":[
        "tgn:7168494",
        "tgn:7000096",
        "tgn:1000003",
        "tgn:7000084",
        "tgn:7029392"
    ],
    "tgn:id":7168494,
    "tgn:name":"Hasselwiesen",
    "tgn:placetype":[
        "aat:300386990"
    ]
},
  "bbox": [],
  "geometry": {"coordinates":[12.566667,52.666667],"type":"Point"}
}