{
  "id": 7186583,
  "type": "Feature",
  "properties": {
    "tgn:hierarchy":[
        "tgn:7186583",
        "tgn:1000003",
        "tgn:7003687",
        "tgn:7000084",
        "tgn:7029392"
    ],
    "tgn:id":7186583,
    "tgn:name":"Gladdenstedt",
    "tgn:placetype":[
        "aat:300008347"
    ]
},
  "bbox": [],
  "geometry": {"coordinates":[10.883333,52.65],"type":"Point"}
}