{
  "id": 1010485,
  "type": "Feature",
  "properties": {
    "tgn:hierarchy":[
        "tgn:1010485",
        "tgn:6001445",
        "tgn:1000004",
        "tgn:7018214",
        "tgn:7002435",
        "tgn:7029392"
    ],
    "tgn:id":1010485,
    "tgn:name":"Barykova, Mys",
    "tgn:placetype":[
        "aat:300008850"
    ]
},
  "bbox": [],
  "geometry": {"coordinates":[179.5167,63.1167],"type":"Point"}
}