{
  "id": 2231900,
  "type": "Feature",
  "properties": {
    "tgn:hierarchy":[
        "tgn:2231900",
        "tgn:1000001",
        "tgn:7012149",
        "tgn:1002691",
        "tgn:7007826",
        "tgn:7029392"
    ],
    "tgn:id":2231900,
    "tgn:name":"Chambers Pond",
    "tgn:placetype":[
        "aat:300008905"
    ]
},
  "bbox": [],
  "geometry": {"coordinates":[-95.2667,30.1333],"type":"Point"}
}