{
  "id": 2436305,
  "type": "Feature",
  "properties": {
    "tgn:hierarchy":[
        "tgn:2436305",
        "tgn:7006450",
        "tgn:1000001",
        "tgn:7012149",
        "tgn:2000089",
        "tgn:7029392"
    ],
    "tgn:id":2436305,
    "tgn:name":"Khotol Mountain",
    "tgn:placetype":[
        "aat:300008798"
    ]
},
  "bbox": [],
  "geometry": {"coordinates":[-157.8833,64.1667],"type":"Point"}
}