{
  "id": 2461372,
  "type": "Feature",
  "properties": {
    "tgn:hierarchy":[
        "tgn:2461372",
        "tgn:1000001",
        "tgn:1002218",
        "tgn:7012149",
        "tgn:7007157",
        "tgn:7029392"
    ],
    "tgn:id":2461372,
    "tgn:name":"Little Sucker Run",
    "tgn:placetype":[
        "aat:300008699"
    ]
},
  "bbox": [],
  "geometry": {"coordinates":[-121.2667,39.5833],"type":"Point"}
}