{
  "id": 2664564,
  "type": "Feature",
  "properties": {
    "tgn:hierarchy":[
        "tgn:2664564",
        "tgn:1000001",
        "tgn:2001476",
        "tgn:7012149",
        "tgn:7007709",
        "tgn:7029392"
    ],
    "tgn:id":2664564,
    "tgn:name":"Simmons Branch",
    "tgn:placetype":[
        "aat:300008699"
    ]
},
  "bbox": [],
  "geometry": {"coordinates":[-81.6833,35.9833],"type":"Point"}
}