{
  "id": 2450381,
  "type": "Feature",
  "properties": {
    "tgn:hierarchy":[
        "tgn:2450381",
        "tgn:1000001",
        "tgn:2001741",
        "tgn:7012149",
        "tgn:7007712",
        "tgn:7029392"
    ],
    "tgn:id":2450381,
    "tgn:name":"Linkside",
    "tgn:placetype":[
        "aat:300008347"
    ]
},
  "bbox": [],
  "geometry": {"coordinates":[-79.3167,34.45],"type":"Point"}
}