{
  "id": 2467554,
  "type": "Feature",
  "properties": {
    "tgn:hierarchy":[
        "tgn:2467554",
        "tgn:1000001",
        "tgn:7012149",
        "tgn:2002087",
        "tgn:7007826",
        "tgn:7029392"
    ],
    "tgn:id":2467554,
    "tgn:name":"Long Hollow",
    "tgn:placetype":[
        "aat:300008761"
    ]
},
  "bbox": [],
  "geometry": {"coordinates":[-99.8667,29.5667],"type":"Point"}
}