{
  "id": 2560167,
  "type": "Feature",
  "properties": {
    "tgn:hierarchy":[
        "tgn:2560167",
        "tgn:1000001",
        "tgn:7012149",
        "tgn:2000282",
        "tgn:7007240",
        "tgn:7029392"
    ],
    "tgn:id":2560167,
    "tgn:name":"Orange Point",
    "tgn:placetype":[
        "aat:300008850"
    ]
},
  "bbox": [],
  "geometry": {"coordinates":[-81.6667,29.45],"type":"Point"}
}