{
  "id": 7389084,
  "type": "Feature",
  "properties": {
    "tgn:hierarchy":[
        "tgn:7389084",
        "tgn:7005586",
        "tgn:1000001",
        "tgn:7005560",
        "tgn:7029392"
    ],
    "tgn:id":7389084,
    "tgn:name":"Quemado",
    "tgn:placetype":[
        "aat:300007783"
    ]
},
  "bbox": [],
  "geometry": {"coordinates":[-103.566667,19.85],"type":"Point"}
}