{
  "id": 7309128,
  "type": "Feature",
  "properties": {
    "tgn:hierarchy":[
        "tgn:7309128",
        "tgn:1001637",
        "tgn:1000049",
        "tgn:1000002",
        "tgn:7029392"
    ],
    "tgn:id":7309128,
    "tgn:name":"Macal, Estero",
    "tgn:placetype":[
        "aat:300008699"
    ]
},
  "bbox": [],
  "geometry": {"coordinates":[-73.25,-37.35],"type":"Point"}
}