{
  "id": 7250257,
  "type": "Feature",
  "properties": {
    "tgn:hierarchy":[
        "tgn:7250257",
        "tgn:7003466",
        "tgn:1000003",
        "tgn:1000063",
        "tgn:4012014",
        "tgn:7029392"
    ],
    "tgn:id":7250257,
    "tgn:name":"Moulin, \u00c9tang du",
    "tgn:placetype":[
        "aat:300008688"
    ]
},
  "bbox": [],
  "geometry": {"coordinates":[5.20334,50.221738],"type":"Point"}
}