{
  "id": 1047415,
  "type": "Feature",
  "properties": {
    "tgn:hierarchy":[
        "tgn:1047415",
        "tgn:7003158",
        "tgn:1000003",
        "tgn:7003124",
        "tgn:1000080",
        "tgn:7029392"
    ],
    "tgn:id":1047415,
    "tgn:name":"Vigo di Fassa",
    "tgn:placetype":[
        "aat:300008347"
    ]
},
  "bbox": [],
  "geometry": {"coordinates":[11.666667,46.416667],"type":"Point"}
}