{
  "id": 7465909,
  "type": "Feature",
  "properties": {
    "tgn:hierarchy":[
        "tgn:7465909",
        "tgn:7002444",
        "tgn:1000003",
        "tgn:7009907",
        "tgn:7008591",
        "tgn:7029392"
    ],
    "tgn:id":7465909,
    "tgn:name:en":"Barrel of Butter",
    "tgn:placetype":[
        "aat:300011692"
    ]
},
  "bbox": [],
  "geometry": {"coordinates":[-3.116667,58.883333],"type":"Point"}
}