{
  "id": 2427171,
  "type": "Feature",
  "properties": {
    "tgn:hierarchy":[
        "tgn:2427171",
        "tgn:1000001",
        "tgn:7016172",
        "tgn:2000110",
        "tgn:7012149",
        "tgn:7029392"
    ],
    "tgn:id":2427171,
    "tgn:name":"Jordan Branch",
    "tgn:placetype":[
        "aat:300008699"
    ]
},
  "bbox": [],
  "geometry": {"coordinates":[-92.2833,33.4167],"type":"Point"}
}