{
  "id": 2393100,
  "type": "Feature",
  "properties": {
    "tgn:hierarchy":[
        "tgn:2393100",
        "tgn:1000001",
        "tgn:7012149",
        "tgn:2001920",
        "tgn:7007825",
        "tgn:7029392"
    ],
    "tgn:id":2393100,
    "tgn:name":"Hodges Creek",
    "tgn:placetype":[
        "aat:300008706"
    ]
},
  "bbox": [],
  "geometry": {"coordinates":[-89.7833,35.55],"type":"Point"}
}