{
  "id": 1116809,
  "type": "Feature",
  "properties": {
    "tgn:hierarchy":[
        "tgn:1116809",
        "tgn:7005685",
        "tgn:1000001",
        "tgn:7013154",
        "tgn:7029392"
    ],
    "tgn:id":1116809,
    "tgn:name":"Kawagama Lake",
    "tgn:placetype":[
        "aat:300008680"
    ]
},
  "bbox": [],
  "geometry": {"coordinates":[-78.75,45.2833],"type":"Point"}
}