{
  "id": 7591823,
  "type": "Feature",
  "properties": {
    "tgn:hierarchy":[
        "tgn:7591823",
        "tgn:1000004",
        "tgn:7000198",
        "tgn:7000799",
        "tgn:7029392"
    ],
    "tgn:id":7591823,
    "tgn:name:en":"B\u0101\u012bw\u0101li Khad",
    "tgn:placetype":[
        "aat:300266554",
        "aat:300008699"
    ]
},
  "bbox": [],
  "geometry": {"coordinates":[74.8125,32.955556],"type":"Point"}
}