{
  "id": 1058553,
  "type": "Feature",
  "properties": {
    "tgn:hierarchy":[
        "tgn:1058553",
        "tgn:7011552",
        "tgn:1000004",
        "tgn:7018214",
        "tgn:7002435",
        "tgn:7029392"
    ],
    "tgn:id":1058553,
    "tgn:name":"Pologoye Zaymishche",
    "tgn:placetype":[
        "aat:300008347"
    ]
},
  "bbox": [],
  "geometry": {"coordinates":[45.9667,48.4667],"type":"Point"}
}