{
  "id": 2724803,
  "type": "Feature",
  "properties": {
    "tgn:hierarchy":[
        "tgn:2724803",
        "tgn:1000001",
        "tgn:7012149",
        "tgn:2002290",
        "tgn:7013961",
        "tgn:7029392"
    ],
    "tgn:id":2724803,
    "tgn:name":"Tommy Ridge",
    "tgn:placetype":[
        "aat:300266640"
    ]
},
  "bbox": [],
  "geometry": {"coordinates":[-81.25,37.5833],"type":"Point"}
}