{
  "id": 7422712,
  "type": "Feature",
  "properties": {
    "tgn:hierarchy":[
        "tgn:7422712",
        "tgn:1000001",
        "tgn:1001960",
        "tgn:7005560",
        "tgn:7029392"
    ],
    "tgn:id":7422712,
    "tgn:name":"Las Palomas",
    "tgn:placetype":[
        "aat:300008347"
    ]
},
  "bbox": [],
  "geometry": {"coordinates":[-109.933333,28.05],"type":"Point"}
}