{
  "id": 2673662,
  "type": "Feature",
  "properties": {
    "tgn:hierarchy":[
        "tgn:2673662",
        "tgn:1000001",
        "tgn:7012149",
        "tgn:2001284",
        "tgn:7007524",
        "tgn:7029392"
    ],
    "tgn:id":2673662,
    "tgn:name":"Snow Bird Mine",
    "tgn:placetype":[
        "aat:300000390"
    ]
},
  "bbox": [],
  "geometry": {"coordinates":[-112.3333,46.7167],"type":"Point"}
}