<<<<<<< HEAD
{
  "id": 2766176,
  "type": "Feature",
  "properties": {
    "tgn:hierarchy":[
        "tgn:2766176",
        "tgn:1000001",
        "tgn:7012149",
        "tgn:1002509",
        "tgn:7007520",
        "tgn:7029392"
    ],
    "tgn:id":2766176,
    "tgn:name":"White Lake",
    "tgn:placetype":[
        "aat:300008680"
    ]
},
  "bbox": [],
  "geometry": {"coordinates":[-84.3333,42.35],"type":"Point"}
}
=======
{"geometry":{"type":"Point","coordinates":[-84.333300,42.350000]},"type":"Feature","properties":{"hierarchy":["tgn:2766176","tgn:1000001","tgn:7012149","tgn:1002509","tgn:7007520","tgn:7029392"],"placetype":["aat:300008680"],"id":2766176,"name:xx":"White Lake"}}
>>>>>>> 03f74aca74312dbeaf24d7e61306dd6a786dc3d0
