{
  "id": 1098646,
  "type": "Feature",
  "properties": {
    "tgn:hierarchy":[
        "tgn:1098646",
        "tgn:7000490",
        "tgn:1000006",
        "tgn:7006238",
        "tgn:7029392"
    ],
    "tgn:id":1098646,
    "tgn:name":"Yarrawonga",
    "tgn:placetype":[
        "aat:300008347"
    ]
},
  "bbox": [],
  "geometry": {"coordinates":[145.9833,-36.0333],"type":"Point"}
}