{
  "id": 1051644,
  "type": "Feature",
  "properties": {
    "tgn:hierarchy":[
        "tgn:1051644",
        "tgn:1000004",
        "tgn:7017317",
        "tgn:7018214",
        "tgn:7002435",
        "tgn:7029392"
    ],
    "tgn:id":1051644,
    "tgn:name":"Shishovka",
    "tgn:placetype":[
        "aat:300008347"
    ]
},
  "bbox": [],
  "geometry": {"coordinates":[38.8667,58.8667],"type":"Point"}
}