{
  "id": 2279688,
  "type": "Feature",
  "properties": {
    "tgn:hierarchy":[
        "tgn:2279688",
        "tgn:1000001",
        "tgn:7012149",
        "tgn:7007157",
        "tgn:1002857",
        "tgn:7029392"
    ],
    "tgn:id":2279688,
    "tgn:name":"Deadmans Lake",
    "tgn:placetype":[
        "aat:300008680"
    ]
},
  "bbox": [],
  "geometry": {"coordinates":[-116.7667,34.2167],"type":"Point"}
}