<<<<<<< HEAD
{
  "id": 7361696,
  "type": "Feature",
  "properties": {
    "tgn:hierarchy":[
        "tgn:7361696",
        "tgn:1000001",
        "tgn:7005597",
        "tgn:7005560",
        "tgn:7029392"
    ],
    "tgn:id":7361696,
    "tgn:name":"El Canelo",
    "tgn:placetype":[
        "aat:300008347"
    ]
},
  "bbox": [],
  "geometry": {"coordinates":[-97.983333,25.166667],"type":"Point"}
}
=======
{"geometry":{"type":"Point","coordinates":[-97.983333,25.166667]},"type":"Feature","properties":{"hierarchy":["tgn:7361696","tgn:1000001","tgn:7005597","tgn:7005560","tgn:7029392"],"placetype":["aat:300008347"],"id":7361696,"name:xx":"El Canelo"}}
>>>>>>> 03f74aca74312dbeaf24d7e61306dd6a786dc3d0
