{
  "id": 2625039,
  "type": "Feature",
  "properties": {
    "tgn:hierarchy":[
        "tgn:2625039",
        "tgn:7002659",
        "tgn:1000001",
        "tgn:7012149",
        "tgn:2000051",
        "tgn:7029392"
    ],
    "tgn:id":2625039,
    "tgn:name":"Rock Waterfall Cave",
    "tgn:placetype":[
        "aat:300008746"
    ]
},
  "bbox": [],
  "geometry": {"coordinates":[-86.8667,34.4667],"type":"Point"}
}