{
  "id": 2205775,
  "type": "Feature",
  "properties": {
    "tgn:hierarchy":[
        "tgn:2205775",
        "tgn:1000001",
        "tgn:7012149",
        "tgn:2002371",
        "tgn:7007923",
        "tgn:7029392"
    ],
    "tgn:id":2205775,
    "tgn:name":"Bull Lake Glacier",
    "tgn:placetype":[
        "aat:300008835"
    ]
},
  "bbox": [],
  "geometry": {"coordinates":[-109.5833,43.1167],"type":"Point"}
}