{
  "id": 7367191,
  "type": "Feature",
  "properties": {
    "tgn:hierarchy":[
        "tgn:7367191",
        "tgn:1000001",
        "tgn:7005599",
        "tgn:7005560",
        "tgn:7029392"
    ],
    "tgn:id":7367191,
    "tgn:name":"El Tule",
    "tgn:placetype":[
        "aat:300008347"
    ]
},
  "bbox": [],
  "geometry": {"coordinates":[-98.433333,21.533333],"type":"Point"}
}