{
  "id": 7436932,
  "type": "Feature",
  "properties": {
    "tgn:hierarchy":[
        "tgn:7436932",
        "tgn:1000001",
        "tgn:7005595",
        "tgn:7005560",
        "tgn:7029392"
    ],
    "tgn:id":7436932,
    "tgn:name":"Sitio de Arriba",
    "tgn:placetype":[
        "aat:300008347"
    ]
},
  "bbox": [],
  "geometry": {"coordinates":[-107.616667,25.466667],"type":"Point"}
}