{
  "id": 7428946,
  "type": "Feature",
  "properties": {
    "tgn:hierarchy":[
        "tgn:7428946",
        "tgn:1001853",
        "tgn:1000001",
        "tgn:7005560",
        "tgn:7029392"
    ],
    "tgn:id":7428946,
    "tgn:name":"El Barril, Cerro",
    "tgn:placetype":[
        "aat:300008795"
    ]
},
  "bbox": [],
  "geometry": {"coordinates":[-101.15,25.85],"type":"Point"}
}