{
  "id": 7435725,
  "type": "Feature",
  "properties": {
    "tgn:hierarchy":[
        "tgn:7435725",
        "tgn:1000001",
        "tgn:7005596",
        "tgn:7005560",
        "tgn:7029392"
    ],
    "tgn:id":7435725,
    "tgn:name":"Torno Largo",
    "tgn:placetype":[
        "aat:300008347"
    ]
},
  "bbox": [],
  "geometry": {"coordinates":[-93.733333,17.683333],"type":"Point"}
}