{
  "id": 7152560,
  "type": "Feature",
  "properties": {
    "tgn:hierarchy":[
        "tgn:7152560",
        "tgn:7003669",
        "tgn:1000003",
        "tgn:7000084",
        "tgn:7029392"
    ],
    "tgn:id":7152560,
    "tgn:name":"Kabisbach",
    "tgn:placetype":[
        "aat:300008699"
    ]
},
  "bbox": [],
  "geometry": {"coordinates":[10.916667,48.533333],"type":"Point"}
}