<<<<<<< HEAD
{
  "id": 7111080,
  "type": "Feature",
  "properties": {
    "tgn:hierarchy":[
        "tgn:7111080",
        "tgn:1000003",
        "tgn:7000094",
        "tgn:7000084",
        "tgn:7029392"
    ],
    "tgn:id":7111080,
    "tgn:name":"Rollenhagener Berge",
    "tgn:placetype":[
        "aat:300008777"
    ]
},
  "bbox": [],
  "geometry": {"coordinates":[13.216667,53.35],"type":"Point"}
}
=======
{"geometry":{"type":"Point","coordinates":[13.216667,53.350000]},"type":"Feature","properties":{"hierarchy":["tgn:7111080","tgn:1000003","tgn:7000094","tgn:7000084","tgn:7029392"],"placetype":["aat:300008777"],"id":7111080,"name:xx":"Rollenhagener Berge"}}
>>>>>>> 03f74aca74312dbeaf24d7e61306dd6a786dc3d0
