<<<<<<< HEAD
{
  "id": 2761609,
  "type": "Feature",
  "properties": {
    "tgn:hierarchy":[
        "tgn:2761609",
        "tgn:1000001",
        "tgn:1002200",
        "tgn:7012149",
        "tgn:7007240",
        "tgn:7029392"
    ],
    "tgn:id":2761609,
    "tgn:name":"West Pepper Creek",
    "tgn:placetype":[
        "aat:300008706"
    ]
},
  "bbox": [],
  "geometry": {"coordinates":[-80.6,28.5667],"type":"Point"}
}
=======
{"geometry":{"type":"Point","coordinates":[-80.600000,28.566700]},"type":"Feature","properties":{"hierarchy":["tgn:2761609","tgn:1000001","tgn:1002200","tgn:7012149","tgn:7007240","tgn:7029392"],"placetype":["aat:300008706"],"id":2761609,"name:xx":"West Pepper Creek"}}
>>>>>>> 03f74aca74312dbeaf24d7e61306dd6a786dc3d0
