{
  "id": 7336056,
  "type": "Feature",
  "properties": {
    "tgn:hierarchy":[
        "tgn:7336056",
        "tgn:7002759",
        "tgn:7008909",
        "tgn:1000003",
        "tgn:1000095",
        "tgn:7029392"
    ],
    "tgn:id":7336056,
    "tgn:name":"Fumanal",
    "tgn:placetype":[
        "aat:300008347"
    ]
},
  "bbox": [],
  "geometry": {"coordinates":[0.24061,42.355634],"type":"Point"}
}