{
  "id": 2094701,
  "type": "Feature",
  "properties": {
    "tgn:hierarchy":[
        "tgn:2094701",
        "tgn:1000001",
        "tgn:1002213",
        "tgn:7012149",
        "tgn:7007710",
        "tgn:7029392"
    ],
    "tgn:id":2094701,
    "tgn:name":"Woodside",
    "tgn:placetype":[
        "aat:300008347"
    ]
},
  "bbox": [],
  "geometry": {"coordinates":[-74.8667,40.2167],"type":"Point"}
}