{
  "id": 2316417,
  "type": "Feature",
  "properties": {
    "tgn:hierarchy":[
        "tgn:2316417",
        "tgn:1000001",
        "tgn:7012149",
        "tgn:7014589",
        "tgn:7007515",
        "tgn:7029392"
    ],
    "tgn:id":2316417,
    "tgn:name":"Elsemore Landing",
    "tgn:placetype":[
        "aat:300008347"
    ]
},
  "bbox": [],
  "geometry": {"coordinates":[-67.8833,45.1667],"type":"Point"}
}