{
  "id": 2769479,
  "type": "Feature",
  "properties": {
    "tgn:hierarchy":[
        "tgn:2769479",
        "tgn:1000001",
        "tgn:2001637",
        "tgn:7012149",
        "tgn:7007707",
        "tgn:7029392"
    ],
    "tgn:id":2769479,
    "tgn:name":"Wide Springs",
    "tgn:placetype":[
        "aat:300008697"
    ]
},
  "bbox": [],
  "geometry": {"coordinates":[-96.4667,34.4167],"type":"Point"}
}