<<<<<<< HEAD
{
  "id": 2765740,
  "type": "Feature",
  "properties": {
    "tgn:hierarchy":[
        "tgn:2765740",
        "tgn:1000001",
        "tgn:7012149",
        "tgn:2002384",
        "tgn:7007923",
        "tgn:7029392"
    ],
    "tgn:id":2765740,
    "tgn:name":"White Creek",
    "tgn:placetype":[
        "aat:300008706"
    ]
},
  "bbox": [],
  "geometry": {"coordinates":[-110.7167,44.4833],"type":"Point"}
}
=======
{"geometry":{"type":"Point","coordinates":[-110.716700,44.483300]},"type":"Feature","properties":{"hierarchy":["tgn:2765740","tgn:1000001","tgn:7012149","tgn:2002384","tgn:7007923","tgn:7029392"],"placetype":["aat:300008706"],"id":2765740,"name:xx":"White Creek"}}
>>>>>>> 03f74aca74312dbeaf24d7e61306dd6a786dc3d0
