{
  "id": 2765740,
  "type": "Feature",
  "properties": {
    "tgn:hierarchy":[
        "tgn:2765740",
        "tgn:1000001",
        "tgn:7012149",
        "tgn:2002384",
        "tgn:7007923",
        "tgn:7029392"
    ],
    "tgn:id":2765740,
    "tgn:name":"White Creek",
    "tgn:placetype":[
        "aat:300008706"
    ]
},
  "bbox": [],
  "geometry": {"coordinates":[-110.7167,44.4833],"type":"Point"}
}