{
  "id": 2457778,
  "type": "Feature",
  "properties": {
    "tgn:hierarchy":[
        "tgn:2457778",
        "tgn:7006450",
        "tgn:1000001",
        "tgn:7012149",
        "tgn:2000089",
        "tgn:7029392"
    ],
    "tgn:id":2457778,
    "tgn:name":"Little Melozitna River",
    "tgn:placetype":[
        "aat:300008707"
    ]
},
  "bbox": [],
  "geometry": {"coordinates":[-154.05,65.1667],"type":"Point"}
}