{
  "id": 7572539,
  "type": "Feature",
  "properties": {
    "tgn:hierarchy":[
        "tgn:7572539",
        "tgn:1000004",
        "tgn:7000198",
        "tgn:7016722",
        "tgn:7029392"
    ],
    "tgn:id":7572539,
    "tgn:name:en":"Faithfulganj",
    "tgn:placetype":[
        "aat:300000745"
    ]
},
  "bbox": [],
  "geometry": {"coordinates":[80.333333,26.45],"type":"Point"}
}