<<<<<<< HEAD
{
  "id": 2765499,
  "type": "Feature",
  "properties": {
    "tgn:hierarchy":[
        "tgn:2765499",
        "tgn:1000001",
        "tgn:7012149",
        "tgn:1002882",
        "tgn:7007568",
        "tgn:7029392"
    ],
    "tgn:id":2765499,
    "tgn:name":"White Brook",
    "tgn:placetype":[
        "aat:300008699"
    ]
},
  "bbox": [],
  "geometry": {"coordinates":[-76.8333,42.95],"type":"Point"}
}
=======
{"geometry":{"type":"Point","coordinates":[-76.833300,42.950000]},"type":"Feature","properties":{"hierarchy":["tgn:2765499","tgn:1000001","tgn:7012149","tgn:1002882","tgn:7007568","tgn:7029392"],"placetype":["aat:300008699"],"id":2765499,"name:xx":"White Brook"}}
>>>>>>> 03f74aca74312dbeaf24d7e61306dd6a786dc3d0
