{
  "id": 2162126,
  "type": "Feature",
  "properties": {
    "tgn:hierarchy":[
        "tgn:2162126",
        "tgn:1000001",
        "tgn:7012149",
        "tgn:2001860",
        "tgn:7007825",
        "tgn:7029392"
    ],
    "tgn:id":2162126,
    "tgn:name":"Belmont",
    "tgn:placetype":[
        "aat:300008347"
    ]
},
  "bbox": [],
  "geometry": {"coordinates":[-89.4833,35.3833],"type":"Point"}
}