{
  "id": 7041487,
  "type": "Feature",
  "properties": {
    "tgn:hierarchy":[
        "tgn:7041487",
        "tgn:1003440",
        "tgn:1000003",
        "tgn:7003124",
        "tgn:1000080",
        "tgn:7029392"
    ],
    "tgn:id":7041487,
    "tgn:name":"Hoher Lorenzenberg",
    "tgn:placetype":[
        "aat:300008798"
    ]
},
  "bbox": [],
  "geometry": {"coordinates":[11.433333,46.966667],"type":"Point"}
}