{
  "id": 2159108,
  "type": "Feature",
  "properties": {
    "tgn:hierarchy":[
        "tgn:2159108",
        "tgn:1000001",
        "tgn:1002240",
        "tgn:7012149",
        "tgn:7007255",
        "tgn:7029392"
    ],
    "tgn:id":2159108,
    "tgn:name":"Bedford Branch",
    "tgn:placetype":[
        "aat:300008699"
    ]
},
  "bbox": [],
  "geometry": {"coordinates":[-83.35,38.35],"type":"Point"}
}