{
  "id": 2076901,
  "type": "Feature",
  "properties": {
    "tgn:hierarchy":[
        "tgn:2076901",
        "tgn:1000001",
        "tgn:7012149",
        "tgn:2001516",
        "tgn:7007709",
        "tgn:7029392"
    ],
    "tgn:id":2076901,
    "tgn:name":"Terry Fork",
    "tgn:placetype":[
        "aat:300008347",
        "aat:300387210"
    ]
},
  "bbox": [],
  "geometry": {"coordinates":[-82.4333,35.8167],"type":"Point"}
}