{
  "id": 2175582,
  "type": "Feature",
  "properties": {
    "tgn:hierarchy":[
        "tgn:2175582",
        "tgn:1000001",
        "tgn:7012149",
        "tgn:7007158",
        "tgn:2000243",
        "tgn:7029392"
    ],
    "tgn:id":2175582,
    "tgn:name":"Black Cedar Draw",
    "tgn:placetype":[
        "aat:300008761"
    ]
},
  "bbox": [],
  "geometry": {"coordinates":[-108.7167,39.9333],"type":"Point"}
}