{
  "id": 7127180,
  "type": "Feature",
  "properties": {
    "tgn:hierarchy":[
        "tgn:7127180",
        "tgn:7003669",
        "tgn:1000003",
        "tgn:7000084",
        "tgn:7029392"
    ],
    "tgn:id":7127180,
    "tgn:name":"Obernhof",
    "tgn:placetype":[
        "aat:300008347"
    ]
},
  "bbox": [],
  "geometry": {"coordinates":[12.366667,48.083333],"type":"Point"}
}