{
  "id": 7133626,
  "type": "Feature",
  "properties": {
    "tgn:hierarchy":[
        "tgn:7133626",
        "tgn:7003669",
        "tgn:1000003",
        "tgn:7000084",
        "tgn:7029392"
    ],
    "tgn:id":7133626,
    "tgn:name":"M\u00fchlb\u00fchl",
    "tgn:placetype":[
        "aat:300008347"
    ]
},
  "bbox": [],
  "geometry": {"coordinates":[11.933333,49.966667],"type":"Point"}
}