<<<<<<< HEAD
{
  "id": 7360028,
  "type": "Feature",
  "properties": {
    "tgn:hierarchy":[
        "tgn:7360028",
        "tgn:7005585",
        "tgn:1000001",
        "tgn:7005560",
        "tgn:7029392"
    ],
    "tgn:id":7360028,
    "tgn:name":"Cuchara, Cerro",
    "tgn:placetype":[
        "aat:300008795"
    ]
},
  "bbox": [],
  "geometry": {"coordinates":[-101.533333,17.9],"type":"Point"}
}
=======
{"geometry":{"type":"Point","coordinates":[-101.533333,17.900000]},"type":"Feature","properties":{"hierarchy":["tgn:7360028","tgn:7005585","tgn:1000001","tgn:7005560","tgn:7029392"],"placetype":["aat:300008795"],"id":7360028,"name:xx":"Cuchara, Cerro"}}
>>>>>>> 03f74aca74312dbeaf24d7e61306dd6a786dc3d0
