{
  "id": 2321594,
  "type": "Feature",
  "properties": {
    "tgn:hierarchy":[
        "tgn:2321594",
        "tgn:1000001",
        "tgn:7012149",
        "tgn:1002552",
        "tgn:7007920",
        "tgn:7029392"
    ],
    "tgn:id":2321594,
    "tgn:name":"Fairview",
    "tgn:placetype":[
        "aat:300008347"
    ]
},
  "bbox": [],
  "geometry": {"coordinates":[-122.6667,47.6167],"type":"Point"}
}