{
  "id": 2613797,
  "type": "Feature",
  "properties": {
    "tgn:hierarchy":[
        "tgn:2613797",
        "tgn:2000296",
        "tgn:1000001",
        "tgn:7012149",
        "tgn:7007248",
        "tgn:7029392"
    ],
    "tgn:id":2613797,
    "tgn:name":"Reedy Creek",
    "tgn:placetype":[
        "aat:300008706"
    ]
},
  "bbox": [],
  "geometry": {"coordinates":[-83.2333,33.0167],"type":"Point"}
}