{
  "id": 2637967,
  "type": "Feature",
  "properties": {
    "tgn:hierarchy":[
        "tgn:2637967",
        "tgn:1000001",
        "tgn:7012149",
        "tgn:2000203",
        "tgn:7007158",
        "tgn:7029392"
    ],
    "tgn:id":2637967,
    "tgn:name":"Salazar Number 1 Reservoir",
    "tgn:placetype":[
        "aat:300006191"
    ]
},
  "bbox": [],
  "geometry": {"coordinates":[-105.4167,37.2167],"type":"Point"}
}