{
  "id": 7045839,
  "type": "Feature",
  "properties": {
    "tgn:hierarchy":[
        "tgn:7045839",
        "tgn:7005765",
        "tgn:1000003",
        "tgn:7003237",
        "tgn:1000080",
        "tgn:7029392"
    ],
    "tgn:id":7045839,
    "tgn:name":"Flero",
    "tgn:placetype":[
        "aat:300008347"
    ]
},
  "bbox": [],
  "geometry": {"coordinates":[10.183333,45.483333],"type":"Point"}
}