{
  "id": 2658540,
  "type": "Feature",
  "properties": {
    "tgn:hierarchy":[
        "tgn:2658540",
        "tgn:7016099",
        "tgn:1000001",
        "tgn:7012149",
        "tgn:7007516",
        "tgn:7029392"
    ],
    "tgn:id":2658540,
    "tgn:name":"Shepperd",
    "tgn:placetype":[
        "aat:300008347"
    ]
},
  "bbox": [],
  "geometry": {"coordinates":[-76.5667,39.5833],"type":"Point"}
}