<<<<<<< HEAD
{
  "id": 7364305,
  "type": "Feature",
  "properties": {
    "tgn:hierarchy":[
        "tgn:7364305",
        "tgn:1000001",
        "tgn:7005601",
        "tgn:7005560",
        "tgn:7029392"
    ],
    "tgn:id":7364305,
    "tgn:name":"El Berrendo",
    "tgn:placetype":[
        "aat:300167671"
    ]
},
  "bbox": [],
  "geometry": {"coordinates":[-102.0,24.4],"type":"Point"}
}
=======
{"geometry":{"type":"Point","coordinates":[-102.000000,24.400000]},"type":"Feature","properties":{"hierarchy":["tgn:7364305","tgn:1000001","tgn:7005601","tgn:7005560","tgn:7029392"],"placetype":["aat:300167671"],"id":7364305,"name:xx":"El Berrendo"}}
>>>>>>> 03f74aca74312dbeaf24d7e61306dd6a786dc3d0
