{
  "id": 7273633,
  "type": "Feature",
  "properties": {
    "tgn:concordances":{
        "gn:id":"2744341"
    },
    "tgn:hierarchy":[
        "tgn:7273633",
        "tgn:1000003",
        "tgn:7003613",
        "tgn:7016845",
        "tgn:7029392"
    ],
    "tgn:id":7273633,
    "tgn:name:nl":"Winschoterhoogebrug",
    "tgn:placetype":[
        "aat:300008347"
    ]
},
  "bbox": [],
  "geometry": {"coordinates":[7.05,53.133333],"type":"Point"}
}