{
  "id": 2683961,
  "type": "Feature",
  "properties": {
    "tgn:hierarchy":[
        "tgn:2683961",
        "tgn:7002659",
        "tgn:1000001",
        "tgn:7012149",
        "tgn:2000031",
        "tgn:7029392"
    ],
    "tgn:id":2683961,
    "tgn:name":"Spencer Branch",
    "tgn:placetype":[
        "aat:300008699"
    ]
},
  "bbox": [],
  "geometry": {"coordinates":[-87.95,33.0167],"type":"Point"}
}