{
  "id": 2634642,
  "type": "Feature",
  "properties": {
    "tgn:hierarchy":[
        "tgn:2634642",
        "tgn:1002165",
        "tgn:1000001",
        "tgn:7012149",
        "tgn:7007517",
        "tgn:7029392"
    ],
    "tgn:id":2634642,
    "tgn:name":"Ruth Pond",
    "tgn:placetype":[
        "aat:300008680"
    ]
},
  "bbox": [],
  "geometry": {"coordinates":[-70.0167,41.75],"type":"Point"}
}