{
  "id": 2692729,
  "type": "Feature",
  "properties": {
    "tgn:hierarchy":[
        "tgn:2692729",
        "tgn:1000001",
        "tgn:2001260",
        "tgn:7012149",
        "tgn:7007524",
        "tgn:7029392"
    ],
    "tgn:id":2692729,
    "tgn:name":"Steel Creek",
    "tgn:placetype":[
        "aat:300008706"
    ]
},
  "bbox": [],
  "geometry": {"coordinates":[-113.0667,45.3333],"type":"Point"}
}