{
  "id": 7556961,
  "type": "Feature",
  "properties": {
    "tgn:hierarchy":[
        "tgn:7556961",
        "tgn:1000004",
        "tgn:7000198",
        "tgn:1001895",
        "tgn:7029392"
    ],
    "tgn:id":7556961,
    "tgn:name:en":"S\u0101kli",
    "tgn:placetype":[
        "aat:300008347"
    ]
},
  "bbox": [],
  "geometry": {"coordinates":[75.63067,21.169715],"type":"Point"}
}