{
  "id": 7316086,
  "type": "Feature",
  "properties": {
    "tgn:hierarchy":[
        "tgn:7316086",
        "tgn:1001708",
        "tgn:1000049",
        "tgn:1000002",
        "tgn:7029392"
    ],
    "tgn:id":7316086,
    "tgn:name":"Casas de El Retiro",
    "tgn:placetype":[
        "aat:300008347"
    ]
},
  "bbox": [],
  "geometry": {"coordinates":[-70.833333,-33.616667],"type":"Point"}
}