{
  "id": 7281621,
  "type": "Feature",
  "properties": {
    "tgn:hierarchy":[
        "tgn:7281621",
        "tgn:1001630",
        "tgn:1000049",
        "tgn:1000002",
        "tgn:7029392"
    ],
    "tgn:id":7281621,
    "tgn:name":"San Antonio, Quebrada",
    "tgn:placetype":[
        "aat:300266554",
        "aat:300008699"
    ]
},
  "bbox": [],
  "geometry": {"coordinates":[-70.05,-27.883333],"type":"Point"}
}