{
  "id": 2435134,
  "type": "Feature",
  "properties": {
    "tgn:hierarchy":[
        "tgn:2435134",
        "tgn:1000001",
        "tgn:7012149",
        "tgn:2000790",
        "tgn:7007255",
        "tgn:7029392"
    ],
    "tgn:id":2435134,
    "tgn:name":"Kentucky Point",
    "tgn:placetype":[
        "aat:300008850"
    ]
},
  "bbox": [],
  "geometry": {"coordinates":[-89.4833,36.5667],"type":"Point"}
}