{
  "id": 7137607,
  "type": "Feature",
  "properties": {
    "tgn:hierarchy":[
        "tgn:7137607",
        "tgn:7003669",
        "tgn:1000003",
        "tgn:7000084",
        "tgn:7029392"
    ],
    "tgn:id":7137607,
    "tgn:name":"Baun",
    "tgn:placetype":[
        "aat:300000206"
    ]
},
  "bbox": [],
  "geometry": {"coordinates":[11.533333,47.716667],"type":"Point"}
}