{
  "id": 2530712,
  "type": "Feature",
  "properties": {
    "tgn:hierarchy":[
        "tgn:2530712",
        "tgn:1002933",
        "tgn:1000001",
        "tgn:7012149",
        "tgn:7007239",
        "tgn:7029392"
    ],
    "tgn:id":2530712,
    "tgn:name":"Muddy Neck",
    "tgn:placetype":[
        "aat:300008850"
    ]
},
  "bbox": [],
  "geometry": {"coordinates":[-75.0833,38.5167],"type":"Point"}
}