{
  "id": 7546794,
  "type": "Feature",
  "properties": {
    "tgn:hierarchy":[
        "tgn:7546794",
        "tgn:1000004",
        "tgn:7000198",
        "tgn:7000799",
        "tgn:7029392"
    ],
    "tgn:id":7546794,
    "tgn:name:en":"Aphen",
    "tgn:placetype":[
        "aat:300008347"
    ]
},
  "bbox": [],
  "geometry": {"coordinates":[76.123689,33.267816],"type":"Point"}
}