{
  "id": 2609808,
  "type": "Feature",
  "properties": {
    "tgn:hierarchy":[
        "tgn:2609808",
        "tgn:1000001",
        "tgn:7012149",
        "tgn:2001657",
        "tgn:7007707",
        "tgn:7029392"
    ],
    "tgn:id":2609808,
    "tgn:name":"Ream, Lake",
    "tgn:placetype":[
        "aat:300006191"
    ]
},
  "bbox": [],
  "geometry": {"coordinates":[-96.4167,34.3333],"type":"Point"}
}