{
  "id": 2689071,
  "type": "Feature",
  "properties": {
    "tgn:hierarchy":[
        "tgn:2689071",
        "tgn:1000001",
        "tgn:7012149",
        "tgn:2001290",
        "tgn:7007524",
        "tgn:7029392"
    ],
    "tgn:id":2689071,
    "tgn:name":"Square Lake",
    "tgn:placetype":[
        "aat:300008680"
    ]
},
  "bbox": [],
  "geometry": {"coordinates":[-115.35,47.25],"type":"Point"}
}