{
  "id": 2369098,
  "type": "Feature",
  "properties": {
    "tgn:hierarchy":[
        "tgn:2369098",
        "tgn:1000001",
        "tgn:2002255",
        "tgn:7012149",
        "tgn:7013961",
        "tgn:7029392"
    ],
    "tgn:id":2369098,
    "tgn:name":"Gum Hollow",
    "tgn:placetype":[
        "aat:300008761"
    ]
},
  "bbox": [],
  "geometry": {"coordinates":[-81.9167,38.0667],"type":"Point"}
}