{
  "id": 2377107,
  "type": "Feature",
  "properties": {
    "tgn:hierarchy":[
        "tgn:2377107",
        "tgn:1000001",
        "tgn:7012149",
        "tgn:2002165",
        "tgn:7007919",
        "tgn:7029392"
    ],
    "tgn:id":2377107,
    "tgn:name":"Harlow Farm Pond",
    "tgn:placetype":[
        "aat:300006191"
    ]
},
  "bbox": [],
  "geometry": {"coordinates":[-78.3667,38.1833],"type":"Point"}
}