{
  "id": 7308212,
  "type": "Feature",
  "properties": {
    "tgn:hierarchy":[
        "tgn:7308212",
        "tgn:1001702",
        "tgn:1000049",
        "tgn:1000002",
        "tgn:7029392"
    ],
    "tgn:id":7308212,
    "tgn:name":"Mayne, Puerto",
    "tgn:placetype":[
        "aat:300008678"
    ]
},
  "bbox": [],
  "geometry": {"coordinates":[-74.083333,-51.316667],"type":"Point"}
}