{
  "id": 2649596,
  "type": "Feature",
  "properties": {
    "tgn:hierarchy":[
        "tgn:2649596",
        "tgn:1000001",
        "tgn:7012149",
        "tgn:7007158",
        "tgn:2000247",
        "tgn:7029392"
    ],
    "tgn:id":2649596,
    "tgn:name":"Scout Lake",
    "tgn:placetype":[
        "aat:300008680"
    ]
},
  "bbox": [],
  "geometry": {"coordinates":[-107.7667,37.6333],"type":"Point"}
}