{
  "id": 7388109,
  "type": "Feature",
  "properties": {
    "tgn:hierarchy":[
        "tgn:7388109",
        "tgn:1001853",
        "tgn:1000001",
        "tgn:7005560",
        "tgn:7029392"
    ],
    "tgn:id":7388109,
    "tgn:name":"Rancho Pico Et\u00e9reo",
    "tgn:placetype":[
        "aat:300000241"
    ]
},
  "bbox": [],
  "geometry": {"coordinates":[-102.566667,29.333333],"type":"Point"}
}