{
  "id": 7018684,
  "type": "Feature",
  "properties": {
    "tgn:hierarchy":[
        "tgn:7018684",
        "tgn:1000003",
        "tgn:1000091",
        "tgn:7029392"
    ],
    "tgn:id":7018684,
    "tgn:name":"Semenicului, Mun\u0163ii",
    "tgn:placetype":[
        "aat:300008795"
    ]
},
  "bbox": [],
  "geometry": {"coordinates":[22.083,45.083],"type":"Point"}
}