{
  "id": 1080301,
  "type": "Feature",
  "properties": {
    "tgn:hierarchy":[
        "tgn:1080301",
        "tgn:1000004",
        "tgn:1000962",
        "tgn:7000896",
        "tgn:1000120",
        "tgn:7029392"
    ],
    "tgn:id":1080301,
    "tgn:name":"Izumi-\u014dtsu",
    "tgn:placetype":[
        "aat:300008347"
    ]
},
  "bbox": [],
  "geometry": {"coordinates":[135.3667,34.4833],"type":"Point"}
}