{
  "id": 2271565,
  "type": "Feature",
  "properties": {
    "tgn:hierarchy":[
        "tgn:2271565",
        "tgn:1000001",
        "tgn:2001638",
        "tgn:7012149",
        "tgn:7007707",
        "tgn:7029392"
    ],
    "tgn:id":2271565,
    "tgn:name":"Cumming, Mountain",
    "tgn:placetype":[
        "aat:300008798"
    ]
},
  "bbox": [],
  "geometry": {"coordinates":[-98.4667,34.7167],"type":"Point"}
}