{
  "id": 2151046,
  "type": "Feature",
  "properties": {
    "tgn:hierarchy":[
        "tgn:2151046",
        "tgn:1000001",
        "tgn:7012149",
        "tgn:1002743",
        "tgn:7007240",
        "tgn:7029392"
    ],
    "tgn:id":2151046,
    "tgn:name":"Basswood Estates",
    "tgn:placetype":[
        "aat:300008347"
    ]
},
  "bbox": [],
  "geometry": {"coordinates":[-80.85,27.2667],"type":"Point"}
}