{
  "id": 2147244,
  "type": "Feature",
  "properties": {
    "tgn:hierarchy":[
        "tgn:2147244",
        "tgn:1000001",
        "tgn:7022387",
        "tgn:7012149",
        "tgn:2001129",
        "tgn:7007522",
        "tgn:7029392"
    ],
    "tgn:id":2147244,
    "tgn:name":"Bar Number 2",
    "tgn:placetype":[
        "aat:300132348"
    ]
},
  "bbox": [],
  "geometry": {"coordinates":[-88.3667,33.35],"type":"Point"}
}