{
  "id": 2558368,
  "type": "Feature",
  "properties": {
    "tgn:hierarchy":[
        "tgn:2558368",
        "tgn:7006450",
        "tgn:1000001",
        "tgn:7012149",
        "tgn:2124002",
        "tgn:7029392"
    ],
    "tgn:id":2558368,
    "tgn:name":"Olga Point",
    "tgn:placetype":[
        "aat:300008850"
    ]
},
  "bbox": [],
  "geometry": {"coordinates":[-135.5167,57.2167],"type":"Point"}
}