{
  "id": 7374958,
  "type": "Feature",
  "properties": {
    "tgn:hierarchy":[
        "tgn:7374958",
        "tgn:1000001",
        "tgn:7005597",
        "tgn:7005560",
        "tgn:7029392"
    ],
    "tgn:id":7374958,
    "tgn:name":"La Misi\u00f3n",
    "tgn:placetype":[
        "aat:300008347"
    ]
},
  "bbox": [],
  "geometry": {"coordinates":[-98.833333,26.316667],"type":"Point"}
}