{
  "id": 7485093,
  "type": "Feature",
  "properties": {
    "tgn:hierarchy":[
        "tgn:7485093",
        "tgn:7488858",
        "tgn:1000004",
        "tgn:1000141",
        "tgn:7029392"
    ],
    "tgn:id":7485093,
    "tgn:name":"Wenquan Qiao",
    "tgn:placetype":[
        "aat:300007836"
    ]
},
  "bbox": [],
  "geometry": {"coordinates":[121.183333,24.021667],"type":"Point"}
}