<<<<<<< HEAD
{
  "id": 7485093,
  "type": "Feature",
  "properties": {
    "tgn:hierarchy":[
        "tgn:7485093",
        "tgn:7488858",
        "tgn:1000004",
        "tgn:1000141",
        "tgn:7029392"
    ],
    "tgn:id":7485093,
    "tgn:name":"Wenquan Qiao",
    "tgn:placetype":[
        "aat:300007836"
    ]
},
  "bbox": [],
  "geometry": {"coordinates":[121.183333,24.021667],"type":"Point"}
}
=======
{"geometry":{"type":"Point","coordinates":[121.183333,24.021667]},"type":"Feature","properties":{"hierarchy":["tgn:7485093","tgn:7488858","tgn:1000004","tgn:1000141","tgn:7029392"],"placetype":["aat:300007836"],"id":7485093,"name:xx":"Wenquan Qiao"}}
>>>>>>> 03f74aca74312dbeaf24d7e61306dd6a786dc3d0
