{
  "id": 1126929,
  "type": "Feature",
  "properties": {
    "tgn:hierarchy":[
        "tgn:1126929",
        "tgn:1001861",
        "tgn:1000002",
        "tgn:1000059",
        "tgn:7029392"
    ],
    "tgn:id":1126929,
    "tgn:name":"Mat\u00edcora, R\u00edo",
    "tgn:placetype":[
        "aat:300008707"
    ]
},
  "bbox": [],
  "geometry": {"coordinates":[-71.15,11.05],"type":"Point"}
}