{
  "id": 2745689,
  "type": "Feature",
  "properties": {
    "tgn:hierarchy":[
        "tgn:2745689",
        "tgn:1000001",
        "tgn:7012149",
        "tgn:2000217",
        "tgn:7007158",
        "tgn:7029392"
    ],
    "tgn:id":2745689,
    "tgn:name":"Virginia Ditch",
    "tgn:placetype":[
        "aat:300006075"
    ]
},
  "bbox": [],
  "geometry": {"coordinates":[-107.45,38.6833],"type":"Point"}
}