{
  "id": 1095340,
  "type": "Feature",
  "properties": {
    "tgn:hierarchy":[
        "tgn:1095340",
        "tgn:7001242",
        "tgn:1001075",
        "tgn:7016833",
        "tgn:7029392"
    ],
    "tgn:id":1095340,
    "tgn:name:en":"An Nubayrah",
    "tgn:placetype":[
        "aat:300008347"
    ]
},
  "bbox": [],
  "geometry": {"coordinates":[30.586145,30.904041],"type":"Point"}
}