{
  "id": 2758529,
  "type": "Feature",
  "properties": {
    "tgn:hierarchy":[
        "tgn:2758529",
        "tgn:1000001",
        "tgn:7012149",
        "tgn:7007525",
        "tgn:7029392"
    ],
    "tgn:id":2758529,
    "tgn:name":"West Chute",
    "tgn:placetype":[
        "aat:300008699"
    ]
},
  "bbox": [],
  "geometry": {"coordinates":[-95.85,40.7833],"type":"Point"}
}