{
  "id": 2101958,
  "type": "Feature",
  "properties": {
    "tgn:hierarchy":[
        "tgn:2101958",
        "tgn:1000001",
        "tgn:7012149",
        "tgn:2001895",
        "tgn:7007825",
        "tgn:7029392"
    ],
    "tgn:id":2101958,
    "tgn:name":"Verona",
    "tgn:placetype":[
        "aat:300008347",
        "aat:300387210"
    ]
},
  "bbox": [],
  "geometry": {"coordinates":[-86.7667,35.5167],"type":"Point"}
}