{
  "id": 2530459,
  "type": "Feature",
  "properties": {
    "tgn:hierarchy":[
        "tgn:2530459",
        "tgn:1000001",
        "tgn:7012149",
        "tgn:1002810",
        "tgn:7007568",
        "tgn:7029392"
    ],
    "tgn:id":2530459,
    "tgn:name":"Muddy Brook",
    "tgn:placetype":[
        "aat:300008699"
    ]
},
  "bbox": [],
  "geometry": {"coordinates":[-73.6167,41.4333],"type":"Point"}
}