{
  "id": 2254611,
  "type": "Feature",
  "properties": {
    "tgn:hierarchy":[
        "tgn:2254611",
        "tgn:1000001",
        "tgn:7012149",
        "tgn:2002175",
        "tgn:7007919",
        "tgn:7029392"
    ],
    "tgn:id":2254611,
    "tgn:name":"Coon Hollow",
    "tgn:placetype":[
        "aat:300008761"
    ]
},
  "bbox": [],
  "geometry": {"coordinates":[-78.7833,37.7167],"type":"Point"}
}