<<<<<<< HEAD
{
  "id": 2402625,
  "type": "Feature",
  "properties": {
    "tgn:hierarchy":[
        "tgn:2402625",
        "tgn:1000001",
        "tgn:7012149",
        "tgn:7029392"
    ],
    "tgn:id":2402625,
    "tgn:name":"Hot Creek",
    "tgn:placetype":[
        "aat:300008706"
    ]
},
  "bbox": [],
  "geometry": {"coordinates":[-114.4333,42.0],"type":"Point"}
}
=======
{"geometry":{"type":"Point","coordinates":[-114.433300,42.000000]},"type":"Feature","properties":{"hierarchy":["tgn:2402625","tgn:1000001","tgn:7012149","tgn:7029392"],"placetype":["aat:300008706"],"id":2402625,"name:xx":"Hot Creek"}}
>>>>>>> 03f74aca74312dbeaf24d7e61306dd6a786dc3d0
