{
  "id": 1040126,
  "type": "Feature",
  "properties": {
    "tgn:hierarchy":[
        "tgn:1040126",
        "tgn:7003669",
        "tgn:1000003",
        "tgn:7000084",
        "tgn:7029392"
    ],
    "tgn:id":1040126,
    "tgn:name":"Lindau",
    "tgn:placetype":[
        "aat:300008347",
        "aat:300008389",
        "aat:300387512",
        "aat:300387292"
    ]
},
  "bbox": [],
  "geometry": {"coordinates":[9.683333,47.55],"type":"Point"}
}