{
  "id": 2388382,
  "type": "Feature",
  "properties": {
    "tgn:hierarchy":[
        "tgn:2388382",
        "tgn:1000001",
        "tgn:7012149",
        "tgn:2001862",
        "tgn:7007825",
        "tgn:7029392"
    ],
    "tgn:id":2388382,
    "tgn:name":"Hickory Ridge",
    "tgn:placetype":[
        "aat:300266640"
    ]
},
  "bbox": [],
  "geometry": {"coordinates":[-86.0667,35.0667],"type":"Point"}
}