{
  "id": 2553944,
  "type": "Feature",
  "properties": {
    "tgn:hierarchy":[
        "tgn:2553944",
        "tgn:1000001",
        "tgn:7012149",
        "tgn:2001027",
        "tgn:7007521",
        "tgn:7029392"
    ],
    "tgn:id":2553944,
    "tgn:name":"Oak Lake",
    "tgn:placetype":[
        "aat:300008680"
    ]
},
  "bbox": [],
  "geometry": {"coordinates":[-94.7167,47.1667],"type":"Point"}
}