<<<<<<< HEAD
{
  "id": 2764759,
  "type": "Feature",
  "properties": {
    "tgn:hierarchy":[
        "tgn:2764759",
        "tgn:1000001",
        "tgn:7012149",
        "tgn:2001717",
        "tgn:7007708",
        "tgn:7029392"
    ],
    "tgn:id":2764759,
    "tgn:name":"Whiskey Creek",
    "tgn:placetype":[
        "aat:300008706"
    ]
},
  "bbox": [],
  "geometry": {"coordinates":[-121.8,44.5667],"type":"Point"}
}
=======
{"geometry":{"type":"Point","coordinates":[-121.800000,44.566700]},"type":"Feature","properties":{"hierarchy":["tgn:2764759","tgn:1000001","tgn:7012149","tgn:2001717","tgn:7007708","tgn:7029392"],"placetype":["aat:300008706"],"id":2764759,"name:xx":"Whiskey Creek"}}
>>>>>>> 03f74aca74312dbeaf24d7e61306dd6a786dc3d0
