{
  "id": 2720631,
  "type": "Feature",
  "properties": {
    "tgn:hierarchy":[
        "tgn:2720631",
        "tgn:1000001",
        "tgn:7012149",
        "tgn:2000350",
        "tgn:7007248",
        "tgn:7029392"
    ],
    "tgn:id":2720631,
    "tgn:name":"Thurmond Pond",
    "tgn:placetype":[
        "aat:300006191"
    ]
},
  "bbox": [],
  "geometry": {"coordinates":[-83.2833,34.4333],"type":"Point"}
}