{
  "id": 7276228,
  "type": "Feature",
  "properties": {
    "tgn:hierarchy":[
        "tgn:7276228",
        "tgn:1001657",
        "tgn:1000049",
        "tgn:1000002",
        "tgn:7029392"
    ],
    "tgn:id":7276228,
    "tgn:name":"Tilo",
    "tgn:placetype":[
        "aat:300000206"
    ]
},
  "bbox": [],
  "geometry": {"coordinates":[-70.366667,-29.866667],"type":"Point"}
}