{
  "id": 7002229,
  "type": "Feature",
  "properties": {
    "tgn:hierarchy":[
        "tgn:7002229",
        "tgn:1000004",
        "tgn:1001477",
        "tgn:1000122",
        "tgn:7029392"
    ],
    "tgn:id":7002229,
    "tgn:name":"Unsan",
    "tgn:placetype":[
        "aat:300008347"
    ]
},
  "bbox": [],
  "geometry": {"coordinates":[126.0167,39.3833],"type":"Point"}
}