{
  "id": 7492927,
  "type": "Feature",
  "properties": {
    "tgn:hierarchy":[
        "tgn:7492927",
        "tgn:7488858",
        "tgn:1000004",
        "tgn:1000141",
        "tgn:7029392"
    ],
    "tgn:id":7492927,
    "tgn:name":"Songbailun Shan",
    "tgn:placetype":[
        "aat:300008795"
    ]
},
  "bbox": [],
  "geometry": {"coordinates":[120.8759,23.834972],"type":"Point"}
}