{
  "id": 2633841,
  "type": "Feature",
  "properties": {
    "tgn:hierarchy":[
        "tgn:2633841",
        "tgn:1000001",
        "tgn:2001788",
        "tgn:7012149",
        "tgn:7007713",
        "tgn:7029392"
    ],
    "tgn:id":2633841,
    "tgn:name":"Rush Lake",
    "tgn:placetype":[
        "aat:300008680"
    ]
},
  "bbox": [],
  "geometry": {"coordinates":[-97.3667,45.35],"type":"Point"}
}