{
  "id": 1089712,
  "type": "Feature",
  "properties": {
    "tgn:hierarchy":[
        "tgn:1089712",
        "tgn:7001242",
        "tgn:7017564",
        "tgn:7001658",
        "tgn:7029392"
    ],
    "tgn:id":1089712,
    "tgn:name":"Aruaddin",
    "tgn:placetype":[
        "aat:300008347"
    ]
},
  "bbox": [],
  "geometry": {"coordinates":[38.7167,16.25],"type":"Point"}
}