<<<<<<< HEAD
{
  "id": 2157549,
  "type": "Feature",
  "properties": {
    "tgn:hierarchy":[
        "tgn:2157549",
        "tgn:1000001",
        "tgn:7012149",
        "tgn:2002377",
        "tgn:7007923",
        "tgn:7029392"
    ],
    "tgn:id":2157549,
    "tgn:name":"Beaver Creek",
    "tgn:placetype":[
        "aat:300008706"
    ]
},
  "bbox": [],
  "geometry": {"coordinates":[-106.2167,42.7],"type":"Point"}
}
=======
{"geometry":{"type":"Point","coordinates":[-106.216700,42.700000]},"type":"Feature","properties":{"hierarchy":["tgn:2157549","tgn:1000001","tgn:7012149","tgn:2002377","tgn:7007923","tgn:7029392"],"placetype":["aat:300008706"],"id":2157549,"name:xx":"Beaver Creek"}}
>>>>>>> 03f74aca74312dbeaf24d7e61306dd6a786dc3d0
