{
  "id": 7495024,
  "type": "Feature",
  "properties": {
    "tgn:hierarchy":[
        "tgn:7495024",
        "tgn:1000004",
        "tgn:7467799",
        "tgn:1000141",
        "tgn:7029392"
    ],
    "tgn:id":7495024,
    "tgn:name":"Xianan",
    "tgn:placetype":[
        "aat:300008347"
    ]
},
  "bbox": [],
  "geometry": {"coordinates":[120.547453,23.968144],"type":"Point"}
}