{
  "id": 7550581,
  "type": "Feature",
  "properties": {
    "tgn:hierarchy":[
        "tgn:7550581",
        "tgn:1000004",
        "tgn:7000198",
        "tgn:7016694",
        "tgn:7029392"
    ],
    "tgn:id":7550581,
    "tgn:name:en":"D\u0101l Pah\u0101r",
    "tgn:placetype":[
        "aat:300008777"
    ]
},
  "bbox": [],
  "geometry": {"coordinates":[85.398026,21.972413],"type":"Point"}
}