{
  "id": 7336412,
  "type": "Feature",
  "properties": {
    "tgn:hierarchy":[
        "tgn:7336412",
        "tgn:7002805",
        "tgn:7002758",
        "tgn:1000003",
        "tgn:1000095",
        "tgn:7029392"
    ],
    "tgn:id":7336412,
    "tgn:name":"Genoveses, Morr\u00f3n de los",
    "tgn:placetype":[
        "aat:300008795"
    ]
},
  "bbox": [],
  "geometry": {"coordinates":[-2.116667,36.733333],"type":"Point"}
}