{
  "id": 1041394,
  "type": "Feature",
  "properties": {
    "tgn:hierarchy":[
        "tgn:1041394",
        "tgn:7003669",
        "tgn:1000003",
        "tgn:7000084",
        "tgn:7029392"
    ],
    "tgn:id":1041394,
    "tgn:name":"Teisendorf",
    "tgn:placetype":[
        "aat:300008347"
    ]
},
  "bbox": [],
  "geometry": {"coordinates":[12.816667,47.85],"type":"Point"}
}