{
  "id": 7226572,
  "type": "Feature",
  "properties": {
    "tgn:hierarchy":[
        "tgn:7226572",
        "tgn:7002707",
        "tgn:7002705",
        "tgn:1000003",
        "tgn:1000074",
        "tgn:7029392"
    ],
    "tgn:id":7226572,
    "tgn:name":"Prits\u00edkovo",
    "tgn:placetype":[
        "aat:300008347"
    ]
},
  "bbox": [],
  "geometry": {"coordinates":[20.55,39.833333],"type":"Point"}
}