{
  "id": 2715170,
  "type": "Feature",
  "properties": {
    "tgn:hierarchy":[
        "tgn:2715170",
        "tgn:1000001",
        "tgn:7012149",
        "tgn:7007524",
        "tgn:7029392"
    ],
    "tgn:id":2715170,
    "tgn:name":"Tepee Coulee",
    "tgn:placetype":[
        "aat:300008761"
    ]
},
  "bbox": [],
  "geometry": {"coordinates":[-109.3667,46.7333],"type":"Point"}
}