{
  "id": 2493237,
  "type": "Feature",
  "properties": {
    "tgn:hierarchy":[
        "tgn:2493237",
        "tgn:7006450",
        "tgn:1000001",
        "tgn:2124012",
        "tgn:7012149",
        "tgn:7029392"
    ],
    "tgn:id":2493237,
    "tgn:name":"Marmot Cape",
    "tgn:placetype":[
        "aat:300008850"
    ]
},
  "bbox": [],
  "geometry": {"coordinates":[-151.85,58.15],"type":"Point"}
}