{
  "id": 7369744,
  "type": "Feature",
  "properties": {
    "tgn:hierarchy":[
        "tgn:7369744",
        "tgn:7005578",
        "tgn:1000001",
        "tgn:7005560",
        "tgn:7029392"
    ],
    "tgn:id":7369744,
    "tgn:name":"Jaina, Isla",
    "tgn:placetype":[
        "aat:300008791"
    ]
},
  "bbox": [],
  "geometry": {"coordinates":[-90.533333,20.233333],"type":"Point"}
}