{
  "id": 7009247,
  "type": "Feature",
  "properties": {
    "tgn:hierarchy":[
        "tgn:7009247",
        "tgn:7002870",
        "tgn:1000003",
        "tgn:1000070",
        "tgn:7029392"
    ],
    "tgn:id":7009247,
    "tgn:name":"Kaysersberg",
    "tgn:placetype":[
        "aat:300008347"
    ]
},
  "bbox": [],
  "geometry": {"coordinates":[7.2667,48.15],"type":"Point"}
}