{
  "id": 7286882,
  "type": "Feature",
  "properties": {
    "tgn:hierarchy":[
        "tgn:7286882",
        "tgn:1001702",
        "tgn:1000049",
        "tgn:1000002",
        "tgn:7029392"
    ],
    "tgn:id":7286882,
    "tgn:name":"Guanaco, Isla",
    "tgn:placetype":[
        "aat:300008791"
    ]
},
  "bbox": [],
  "geometry": {"coordinates":[-72.666667,-51.666667],"type":"Point"}
}