{
  "id": 7226180,
  "type": "Feature",
  "properties": {
    "tgn:hierarchy":[
        "tgn:7226180",
        "tgn:4003773",
        "tgn:7001395",
        "tgn:1000003",
        "tgn:1000074",
        "tgn:7029392"
    ],
    "tgn:id":7226180,
    "tgn:name":"Pros\u00edlion",
    "tgn:placetype":[
        "aat:300008347"
    ]
},
  "bbox": [],
  "geometry": {"coordinates":[22.333333,38.583333],"type":"Point"}
}