{
  "id": 4005761,
  "type": "Feature",
  "properties": {
    "tgn:hierarchy":[
        "tgn:4005761",
        "tgn:7011506",
        "tgn:1000003",
        "tgn:1001780",
        "tgn:7029392"
    ],
    "tgn:id":4005761,
    "tgn:name":"Ml\u00fdny",
    "tgn:placetype":[
        "aat:300008347"
    ]
},
  "bbox": [],
  "geometry": {"coordinates":[14.8833,49.3333],"type":"Point"}
}