<<<<<<< HEAD
{
  "id": 2336652,
  "type": "Feature",
  "properties": {
    "tgn:hierarchy":[
        "tgn:2336652",
        "tgn:1000001",
        "tgn:1002289",
        "tgn:7012149",
        "tgn:7007240",
        "tgn:7029392"
    ],
    "tgn:id":2336652,
    "tgn:name":"Four Seasons",
    "tgn:placetype":[
        "aat:300008347"
    ]
},
  "bbox": [],
  "geometry": {"coordinates":[-81.75,26.2667],"type":"Point"}
}
=======
{"geometry":{"type":"Point","coordinates":[-81.750000,26.266700]},"type":"Feature","properties":{"hierarchy":["tgn:2336652","tgn:1000001","tgn:1002289","tgn:7012149","tgn:7007240","tgn:7029392"],"placetype":["aat:300008347"],"id":2336652,"name:xx":"Four Seasons"}}
>>>>>>> 03f74aca74312dbeaf24d7e61306dd6a786dc3d0
