<<<<<<< HEAD
{
  "id": 2252651,
  "type": "Feature",
  "properties": {
    "tgn:hierarchy":[
        "tgn:2252651",
        "tgn:1000001",
        "tgn:2000272",
        "tgn:7012149",
        "tgn:7007240",
        "tgn:7029392"
    ],
    "tgn:id":2252651,
    "tgn:name":"Connely Field",
    "tgn:placetype":[
        "aat:300008791"
    ]
},
  "bbox": [],
  "geometry": {"coordinates":[-85.85,30.7167],"type":"Point"}
}
=======
{"geometry":{"type":"Point","coordinates":[-85.850000,30.716700]},"type":"Feature","properties":{"hierarchy":["tgn:2252651","tgn:1000001","tgn:2000272","tgn:7012149","tgn:7007240","tgn:7029392"],"placetype":["aat:300008791"],"id":2252651,"name:xx":"Connely Field"}}
>>>>>>> 03f74aca74312dbeaf24d7e61306dd6a786dc3d0
