{
  "id": 7109405,
  "type": "Feature",
  "properties": {
    "tgn:hierarchy":[
        "tgn:7109405",
        "tgn:7003692",
        "tgn:1000003",
        "tgn:7000084",
        "tgn:7029392"
    ],
    "tgn:id":7109405,
    "tgn:name":"Rankbach",
    "tgn:placetype":[
        "aat:300008699"
    ]
},
  "bbox": [],
  "geometry": {"coordinates":[8.916667,48.766667],"type":"Point"}
}