{
  "id": 7497152,
  "type": "Feature",
  "properties": {
    "tgn:hierarchy":[
        "tgn:7497152",
        "tgn:1000004",
        "tgn:7001009",
        "tgn:1000141",
        "tgn:7029392"
    ],
    "tgn:id":7497152,
    "tgn:name":"Xinyi Guoxiao",
    "tgn:placetype":[
        "aat:300006495"
    ]
},
  "bbox": [],
  "geometry": {"coordinates":[120.6694,24.1224],"type":"Point"}
}