{
  "id": 4010645,
  "type": "Feature",
  "properties": {
    "tgn:hierarchy":[
        "tgn:4010645",
        "tgn:7002445",
        "tgn:1000003",
        "tgn:7008168",
        "tgn:7008591",
        "tgn:7029392"
    ],
    "tgn:id":4010645,
    "tgn:name:en":"South Leigh",
    "tgn:placetype":[
        "aat:300008347"
    ]
},
  "bbox": [],
  "geometry": {"coordinates":[-1.433333,51.766667],"type":"Point"}
}