{
  "id": 7213264,
  "type": "Feature",
  "properties": {
    "tgn:hierarchy":[
        "tgn:7213264",
        "tgn:1000003",
        "tgn:7000094",
        "tgn:7000084",
        "tgn:7029392"
    ],
    "tgn:id":7213264,
    "tgn:name":"Bobzin",
    "tgn:placetype":[
        "aat:300008347"
    ]
},
  "bbox": [],
  "geometry": {"coordinates":[11.15,53.483333],"type":"Point"}
}