{
  "id": 7518683,
  "type": "Feature",
  "properties": {
    "tgn:hierarchy":[
        "tgn:7518683",
        "tgn:7000509",
        "tgn:1008380",
        "tgn:1000226",
        "tgn:1000006",
        "tgn:7029392"
    ],
    "tgn:id":7518683,
    "tgn:name:en":"Awakaponga",
    "tgn:placetype":[
        "aat:300008347"
    ]
},
  "bbox": [],
  "geometry": {"coordinates":[176.766667,-37.933333],"type":"Point"}
}