{
  "id": 7358620,
  "type": "Feature",
  "properties": {
    "tgn:hierarchy":[
        "tgn:7358620",
        "tgn:1001835",
        "tgn:1000001",
        "tgn:7005560",
        "tgn:7029392"
    ],
    "tgn:id":7358620,
    "tgn:name":"Veracruz N\u00famero Uno",
    "tgn:placetype":[
        "aat:300008347"
    ]
},
  "bbox": [],
  "geometry": {"coordinates":[-115.079444,32.393889],"type":"Point"}
}