{
  "id": 2263481,
  "type": "Feature",
  "properties": {
    "tgn:hierarchy":[
        "tgn:2263481",
        "tgn:1000001",
        "tgn:7012149",
        "tgn:2002190",
        "tgn:7007919",
        "tgn:7029392"
    ],
    "tgn:id":2263481,
    "tgn:name":"Cox Ridge",
    "tgn:placetype":[
        "aat:300266640"
    ]
},
  "bbox": [],
  "geometry": {"coordinates":[-78.45,38.8833],"type":"Point"}
}