<<<<<<< HEAD
{
  "id": 2255754,
  "type": "Feature",
  "properties": {
    "tgn:hierarchy":[
        "tgn:2255754",
        "tgn:1000001",
        "tgn:7012149",
        "tgn:7007157",
        "tgn:2000189",
        "tgn:7029392"
    ],
    "tgn:id":2255754,
    "tgn:name":"Copper Butte",
    "tgn:placetype":[
        "aat:300008798"
    ]
},
  "bbox": [],
  "geometry": {"coordinates":[-123.1,41.9333],"type":"Point"}
}
=======
{"geometry":{"type":"Point","coordinates":[-123.100000,41.933300]},"type":"Feature","properties":{"hierarchy":["tgn:2255754","tgn:1000001","tgn:7012149","tgn:7007157","tgn:2000189","tgn:7029392"],"placetype":["aat:300008798"],"id":2255754,"name:xx":"Copper Butte"}}
>>>>>>> 03f74aca74312dbeaf24d7e61306dd6a786dc3d0
