{
  "id": 2590154,
  "type": "Feature",
  "properties": {
    "tgn:hierarchy":[
        "tgn:2590154",
        "tgn:7013349",
        "tgn:1000001",
        "tgn:7012149",
        "tgn:7007708",
        "tgn:7029392"
    ],
    "tgn:id":2590154,
    "tgn:name":"Poison Spring",
    "tgn:placetype":[
        "aat:300008697"
    ]
},
  "bbox": [],
  "geometry": {"coordinates":[-117.1833,44.7333],"type":"Point"}
}