{
  "id": 7322372,
  "type": "Feature",
  "properties": {
    "tgn:hierarchy":[
        "tgn:7322372",
        "tgn:1001699",
        "tgn:1000049",
        "tgn:1000002",
        "tgn:7029392"
    ],
    "tgn:id":7322372,
    "tgn:name":"Caicura, Farallones",
    "tgn:placetype":[
        "aat:300008791"
    ]
},
  "bbox": [],
  "geometry": {"coordinates":[-72.683333,-41.733333],"type":"Point"}
}