{
  "id": 2457783,
  "type": "Feature",
  "properties": {
    "tgn:hierarchy":[
        "tgn:2457783",
        "tgn:1000001",
        "tgn:7012149",
        "tgn:1002899",
        "tgn:7007920",
        "tgn:7029392"
    ],
    "tgn:id":2457783,
    "tgn:name":"Little Menzel Lake",
    "tgn:placetype":[
        "aat:300008680"
    ]
},
  "bbox": [],
  "geometry": {"coordinates":[-121.9667,48.0333],"type":"Point"}
}