{
  "id": 1102406,
  "type": "Feature",
  "properties": {
    "tgn:hierarchy":[
        "tgn:1102406",
        "tgn:1000001",
        "tgn:7012149",
        "tgn:1002797",
        "tgn:7007706",
        "tgn:7029392"
    ],
    "tgn:id":1102406,
    "tgn:name":"Nelson-Kennedy Ledges State Park",
    "tgn:placetype":[
        "aat:300008192"
    ]
},
  "bbox": [],
  "geometry": {"coordinates":[-81.0333,41.3167],"type":"Point"}
}