{
  "id": 2226645,
  "type": "Feature",
  "properties": {
    "tgn:hierarchy":[
        "tgn:2226645",
        "tgn:1000001",
        "tgn:7012149",
        "tgn:2001914",
        "tgn:7007825",
        "tgn:7029392"
    ],
    "tgn:id":2226645,
    "tgn:name":"Catron Branch",
    "tgn:placetype":[
        "aat:300008699"
    ]
},
  "bbox": [],
  "geometry": {"coordinates":[-83.5667,35.65],"type":"Point"}
}