{
  "id": 7341887,
  "type": "Feature",
  "properties": {
    "tgn:hierarchy":[
        "tgn:7341887",
        "tgn:7002759",
        "tgn:7008909",
        "tgn:1000003",
        "tgn:1000095",
        "tgn:7029392"
    ],
    "tgn:id":7341887,
    "tgn:name":"Bielsa",
    "tgn:placetype":[
        "aat:300008347"
    ]
},
  "bbox": [],
  "geometry": {"coordinates":[0.21858,42.633465],"type":"Point"}
}