{
  "id": 7248004,
  "type": "Feature",
  "properties": {
    "tgn:hierarchy":[
        "tgn:7248004",
        "tgn:7018239",
        "tgn:1000003",
        "tgn:1000063",
        "tgn:7018236",
        "tgn:7029392"
    ],
    "tgn:id":7248004,
    "tgn:name":"Beisberg",
    "tgn:placetype":[
        "aat:300008347"
    ]
},
  "bbox": [],
  "geometry": {"coordinates":[4.209409,50.783448],"type":"Point"}
}