{
  "id": 7506708,
  "type": "Feature",
  "properties": {
    "tgn:hierarchy":[
        "tgn:7506708",
        "tgn:1009227",
        "tgn:1000226",
        "tgn:7016822",
        "tgn:1000006",
        "tgn:7029392"
    ],
    "tgn:id":7506708,
    "tgn:name:en":"Revolver Bay",
    "tgn:placetype":[
        "aat:300132316"
    ]
},
  "bbox": [],
  "geometry": {"coordinates":[166.733333,-46.083333],"type":"Point"}
}