{
  "id": 7473491,
  "type": "Feature",
  "properties": {
    "tgn:hierarchy":[
        "tgn:7473491",
        "tgn:1000004",
        "tgn:7490934",
        "tgn:1000141",
        "tgn:7029392"
    ],
    "tgn:id":7473491,
    "tgn:name":"Yanshui Xi",
    "tgn:placetype":[
        "aat:300008699"
    ]
},
  "bbox": [],
  "geometry": {"coordinates":[120.15,23.003611],"type":"Point"}
}