<<<<<<< HEAD
{
  "id": 7473491,
  "type": "Feature",
  "properties": {
    "tgn:hierarchy":[
        "tgn:7473491",
        "tgn:1000004",
        "tgn:7490934",
        "tgn:1000141",
        "tgn:7029392"
    ],
    "tgn:id":7473491,
    "tgn:name":"Yanshui Xi",
    "tgn:placetype":[
        "aat:300008699"
    ]
},
  "bbox": [],
  "geometry": {"coordinates":[120.15,23.003611],"type":"Point"}
}
=======
{"geometry":{"type":"Point","coordinates":[120.150000,23.003611]},"type":"Feature","properties":{"hierarchy":["tgn:7473491","tgn:1000004","tgn:7490934","tgn:1000141","tgn:7029392"],"placetype":["aat:300008699"],"id":7473491,"name:xx":"Yanshui Xi"}}
>>>>>>> 03f74aca74312dbeaf24d7e61306dd6a786dc3d0
