{
  "id": 2123216,
  "type": "Feature",
  "properties": {
    "tgn:hierarchy":[
        "tgn:2123216",
        "tgn:1000001",
        "tgn:7012149",
        "tgn:2002385",
        "tgn:7007923",
        "tgn:7029392"
    ],
    "tgn:id":2123216,
    "tgn:name":"Verne",
    "tgn:placetype":[
        "aat:300387016"
    ]
},
  "bbox": [],
  "geometry": {"coordinates":[-110.0833,41.5667],"type":"Point"}
}