<<<<<<< HEAD
{
  "id": 7020146,
  "type": "Feature",
  "properties": {
    "tgn:hierarchy":[
        "tgn:7020146",
        "tgn:1000001",
        "tgn:2001472",
        "tgn:7012149",
        "tgn:7007709",
        "tgn:7029392"
    ],
    "tgn:id":7020146,
    "tgn:name":"Long Bays",
    "tgn:placetype":[
        "aat:300008905"
    ]
},
  "bbox": [],
  "geometry": {"coordinates":[-78.5,34.0167],"type":"Point"}
}
=======
{"geometry":{"type":"Point","coordinates":[-78.500000,34.016700]},"type":"Feature","properties":{"hierarchy":["tgn:7020146","tgn:1000001","tgn:2001472","tgn:7012149","tgn:7007709","tgn:7029392"],"placetype":["aat:300008905"],"id":7020146,"name:xx":"Long Bays"}}
>>>>>>> 03f74aca74312dbeaf24d7e61306dd6a786dc3d0
