{
  "id": 7421302,
  "type": "Feature",
  "properties": {
    "tgn:hierarchy":[
        "tgn:7421302",
        "tgn:1001836",
        "tgn:1000001",
        "tgn:7005560",
        "tgn:7029392"
    ],
    "tgn:id":7421302,
    "tgn:name":"Parque Natural de La Laguna de San Ignacio",
    "tgn:placetype":[
        "aat:300008187"
    ]
},
  "bbox": [],
  "geometry": {"coordinates":[-113.1875,27.0625],"type":"Point"}
}