{
  "id": 2519070,
  "type": "Feature",
  "properties": {
    "tgn:hierarchy":[
        "tgn:2519070",
        "tgn:1002648",
        "tgn:1000001",
        "tgn:1008191",
        "tgn:7012149",
        "tgn:7007249",
        "tgn:7029392"
    ],
    "tgn:id":2519070,
    "tgn:name":"Moaula Ridge",
    "tgn:placetype":[
        "aat:300266640"
    ]
},
  "bbox": [],
  "geometry": {"coordinates":[-156.9333,21.1667],"type":"Point"}
}