{
  "id": 2584754,
  "type": "Feature",
  "properties": {
    "tgn:hierarchy":[
        "tgn:2584754",
        "tgn:7002659",
        "tgn:1000001",
        "tgn:2000005",
        "tgn:7012149",
        "tgn:7029392"
    ],
    "tgn:id":2584754,
    "tgn:name":"Pinhook Creek",
    "tgn:placetype":[
        "aat:300008706"
    ]
},
  "bbox": [],
  "geometry": {"coordinates":[-85.85,32.0833],"type":"Point"}
}