{
  "id": 7232248,
  "type": "Feature",
  "properties": {
    "tgn:hierarchy":[
        "tgn:7232248",
        "tgn:7002707",
        "tgn:7002705",
        "tgn:1000003",
        "tgn:1000074",
        "tgn:7029392"
    ],
    "tgn:id":7232248,
    "tgn:name":"Makr\u00ednon",
    "tgn:placetype":[
        "aat:300008347"
    ]
},
  "bbox": [],
  "geometry": {"coordinates":[20.966944,39.868056],"type":"Point"}
}