{
  "id": 2506428,
  "type": "Feature",
  "properties": {
    "tgn:hierarchy":[
        "tgn:2506428",
        "tgn:1000001",
        "tgn:7012149",
        "tgn:2001821",
        "tgn:7007713",
        "tgn:7029392"
    ],
    "tgn:id":2506428,
    "tgn:name":"Merritt Peak",
    "tgn:placetype":[
        "aat:300008798"
    ]
},
  "bbox": [],
  "geometry": {"coordinates":[-103.55,44.1167],"type":"Point"}
}