{
  "id": 7586471,
  "type": "Feature",
  "properties": {
    "tgn:hierarchy":[
        "tgn:7586471",
        "tgn:1000004",
        "tgn:7000198",
        "tgn:7000799",
        "tgn:7029392"
    ],
    "tgn:id":7586471,
    "tgn:name:en":"Katsdogar",
    "tgn:placetype":[
        "aat:300008699"
    ]
},
  "bbox": [],
  "geometry": {"coordinates":[74.258333,34.475],"type":"Point"}
}