{
  "id": 2378663,
  "type": "Feature",
  "properties": {
    "tgn:hierarchy":[
        "tgn:2378663",
        "tgn:1000001",
        "tgn:2001099",
        "tgn:7012149",
        "tgn:7007522",
        "tgn:7029392"
    ],
    "tgn:id":2378663,
    "tgn:name":"Harrs Place",
    "tgn:placetype":[
        "aat:300008347"
    ]
},
  "bbox": [],
  "geometry": {"coordinates":[-90.5667,34.1667],"type":"Point"}
}