<<<<<<< HEAD
{
  "id": 2158848,
  "type": "Feature",
  "properties": {
    "tgn:hierarchy":[
        "tgn:2158848",
        "tgn:1000001",
        "tgn:7012149",
        "tgn:2001718",
        "tgn:7007708",
        "tgn:7029392"
    ],
    "tgn:id":2158848,
    "tgn:name":"Becker Ponds",
    "tgn:placetype":[
        "aat:300006191"
    ]
},
  "bbox": [],
  "geometry": {"coordinates":[-116.9667,44.0333],"type":"Point"}
}
=======
{"geometry":{"type":"Point","coordinates":[-116.966700,44.033300]},"type":"Feature","properties":{"hierarchy":["tgn:2158848","tgn:1000001","tgn:7012149","tgn:2001718","tgn:7007708","tgn:7029392"],"placetype":["aat:300006191"],"id":2158848,"name:xx":"Becker Ponds"}}
>>>>>>> 03f74aca74312dbeaf24d7e61306dd6a786dc3d0
