{
  "id": 7404968,
  "type": "Feature",
  "properties": {
    "tgn:hierarchy":[
        "tgn:7404968",
        "tgn:7016644",
        "tgn:1000001",
        "tgn:7005560",
        "tgn:7029392"
    ],
    "tgn:id":7404968,
    "tgn:name":"El Quemado",
    "tgn:placetype":[
        "aat:300008347"
    ]
},
  "bbox": [],
  "geometry": {"coordinates":[-104.158333,19.047222],"type":"Point"}
}