{
  "id": 2557099,
  "type": "Feature",
  "properties": {
    "tgn:hierarchy":[
        "tgn:2557099",
        "tgn:1000001",
        "tgn:7012149",
        "tgn:7022542",
        "tgn:7007825",
        "tgn:7029392"
    ],
    "tgn:id":2557099,
    "tgn:name":"Old Harmon Cave",
    "tgn:placetype":[
        "aat:300008746"
    ]
},
  "bbox": [],
  "geometry": {"coordinates":[-84.7667,35.45],"type":"Point"}
}