{
  "id": 7206334,
  "type": "Feature",
  "properties": {
    "tgn:hierarchy":[
        "tgn:7206334",
        "tgn:1000003",
        "tgn:7003677",
        "tgn:7000084",
        "tgn:7029392"
    ],
    "tgn:id":7206334,
    "tgn:name":"F\u00f6rsterei Dahl",
    "tgn:placetype":[
        "aat:300004792"
    ]
},
  "bbox": [],
  "geometry": {"coordinates":[8.866667,51.683333],"type":"Point"}
}