{
  "id": 7101891,
  "type": "Feature",
  "properties": {
    "tgn:hierarchy":[
        "tgn:7101891",
        "tgn:7003669",
        "tgn:1000003",
        "tgn:7000084",
        "tgn:7029392"
    ],
    "tgn:id":7101891,
    "tgn:name":"Sallingbach",
    "tgn:placetype":[
        "aat:300008699"
    ]
},
  "bbox": [],
  "geometry": {"coordinates":[11.85,48.816667],"type":"Point"}
}