{
  "id": 2314570,
  "type": "Feature",
  "properties": {
    "tgn:hierarchy":[
        "tgn:2314570",
        "tgn:1000001",
        "tgn:1002340",
        "tgn:7012149",
        "tgn:7007526",
        "tgn:7029392"
    ],
    "tgn:id":2314570,
    "tgn:name":"Elk Point",
    "tgn:placetype":[
        "aat:300008850"
    ]
},
  "bbox": [],
  "geometry": {"coordinates":[-119.95,38.9833],"type":"Point"}
}