{
  "id": 7424037,
  "type": "Feature",
  "properties": {
    "tgn:hierarchy":[
        "tgn:7424037",
        "tgn:1000001",
        "tgn:1001960",
        "tgn:7005560",
        "tgn:7029392"
    ],
    "tgn:id":7424037,
    "tgn:name":"Santo Domingo",
    "tgn:placetype":[
        "aat:300008347"
    ]
},
  "bbox": [],
  "geometry": {"coordinates":[-109.233333,29.383333],"type":"Point"}
}