<<<<<<< HEAD
{
  "id": 7176974,
  "type": "Feature",
  "properties": {
    "tgn:hierarchy":[
        "tgn:7176974",
        "tgn:1000003",
        "tgn:7003687",
        "tgn:7000084",
        "tgn:7029392"
    ],
    "tgn:id":7176974,
    "tgn:name":"Hagental",
    "tgn:placetype":[
        "aat:300008761"
    ]
},
  "bbox": [],
  "geometry": {"coordinates":[11.133333,51.716667],"type":"Point"}
}
=======
{"geometry":{"type":"Point","coordinates":[11.133333,51.716667]},"type":"Feature","properties":{"hierarchy":["tgn:7176974","tgn:1000003","tgn:7003687","tgn:7000084","tgn:7029392"],"placetype":["aat:300008761"],"id":7176974,"name:xx":"Hagental"}}
>>>>>>> 03f74aca74312dbeaf24d7e61306dd6a786dc3d0
