{
  "id": 7533615,
  "type": "Feature",
  "properties": {
    "tgn:hierarchy":[
        "tgn:7533615",
        "tgn:7001242",
        "tgn:7016833",
        "tgn:7001336",
        "tgn:7029392"
    ],
    "tgn:id":7533615,
    "tgn:name:en":"J\u0101rrah, Ra's",
    "tgn:placetype":[
        "aat:300386846"
    ]
},
  "bbox": [],
  "geometry": {"coordinates":[33.759924,28.026233],"type":"Point"}
}