{
  "id": 2067585,
  "type": "Feature",
  "properties": {
    "tgn:hierarchy":[
        "tgn:2067585",
        "tgn:1000001",
        "tgn:7012149",
        "tgn:2001444",
        "tgn:7007566",
        "tgn:7029392"
    ],
    "tgn:id":2067585,
    "tgn:name":"Sunshine",
    "tgn:placetype":[
        "aat:300008347",
        "aat:300387210"
    ]
},
  "bbox": [],
  "geometry": {"coordinates":[-107.7333,32.1333],"type":"Point"}
}