{
  "id": 2207310,
  "type": "Feature",
  "properties": {
    "tgn:hierarchy":[
        "tgn:2207310",
        "tgn:1000001",
        "tgn:7012149",
        "tgn:7007923",
        "tgn:7029392"
    ],
    "tgn:id":2207310,
    "tgn:name":"Bunker Hill",
    "tgn:placetype":[
        "aat:300008798"
    ]
},
  "bbox": [],
  "geometry": {"coordinates":[-106.0667,41.3833],"type":"Point"}
}