{
  "id": 7412904,
  "type": "Feature",
  "properties": {
    "tgn:hierarchy":[
        "tgn:7412904",
        "tgn:7005587",
        "tgn:1000001",
        "tgn:7005560",
        "tgn:7029392"
    ],
    "tgn:id":7412904,
    "tgn:name:es":"La Presa",
    "tgn:placetype":[
        "aat:300008347"
    ]
},
  "bbox": [],
  "geometry": {"coordinates":[-99.755556,20.491667],"type":"Point"}
}