{
  "id": 2152665,
  "type": "Feature",
  "properties": {
    "tgn:hierarchy":[
        "tgn:2152665",
        "tgn:1000001",
        "tgn:7012149",
        "tgn:7007566",
        "tgn:7029392"
    ],
    "tgn:id":2152665,
    "tgn:name":"Bayo Canyon",
    "tgn:placetype":[
        "aat:300008761"
    ]
},
  "bbox": [],
  "geometry": {"coordinates":[-106.2833,35.8833],"type":"Point"}
}