<<<<<<< HEAD
{
  "id": 2152665,
  "type": "Feature",
  "properties": {
    "tgn:hierarchy":[
        "tgn:2152665",
        "tgn:1000001",
        "tgn:7012149",
        "tgn:7007566",
        "tgn:7029392"
    ],
    "tgn:id":2152665,
    "tgn:name":"Bayo Canyon",
    "tgn:placetype":[
        "aat:300008761"
    ]
},
  "bbox": [],
  "geometry": {"coordinates":[-106.2833,35.8833],"type":"Point"}
}
=======
{"geometry":{"type":"Point","coordinates":[-106.283300,35.883300]},"type":"Feature","properties":{"hierarchy":["tgn:2152665","tgn:1000001","tgn:7012149","tgn:7007566","tgn:7029392"],"placetype":["aat:300008761"],"id":2152665,"name:xx":"Bayo Canyon"}}
>>>>>>> 03f74aca74312dbeaf24d7e61306dd6a786dc3d0
