{
  "id": 7085624,
  "type": "Feature",
  "properties": {
    "tgn:hierarchy":[
        "tgn:7085624",
        "tgn:1000003",
        "tgn:7003688",
        "tgn:7000084",
        "tgn:7029392"
    ],
    "tgn:id":7085624,
    "tgn:name":"Walle",
    "tgn:placetype":[
        "aat:300387200"
    ]
},
  "bbox": [],
  "geometry": {"coordinates":[8.966667,54.166667],"type":"Point"}
}