{
  "id": 7043462,
  "type": "Feature",
  "properties": {
    "tgn:hierarchy":[
        "tgn:7043462",
        "tgn:1000003",
        "tgn:7003152",
        "tgn:7003237",
        "tgn:1000080",
        "tgn:7029392"
    ],
    "tgn:id":7043462,
    "tgn:name":"Premadio",
    "tgn:placetype":[
        "aat:300008347"
    ]
},
  "bbox": [],
  "geometry": {"coordinates":[10.35,46.483333],"type":"Point"}
}