{
  "id": 7403923,
  "type": "Feature",
  "properties": {
    "tgn:hierarchy":[
        "tgn:7403923",
        "tgn:7005585",
        "tgn:1000001",
        "tgn:7005560",
        "tgn:7029392"
    ],
    "tgn:id":7403923,
    "tgn:name":"Xinacantla",
    "tgn:placetype":[
        "aat:300008347"
    ]
},
  "bbox": [],
  "geometry": {"coordinates":[-99.133333,17.375],"type":"Point"}
}