{
  "id": 2426695,
  "type": "Feature",
  "properties": {
    "tgn:hierarchy":[
        "tgn:2426695",
        "tgn:1000001",
        "tgn:7012149",
        "tgn:2001452",
        "tgn:7007566",
        "tgn:7029392"
    ],
    "tgn:id":2426695,
    "tgn:name":"Jones Lake",
    "tgn:placetype":[
        "aat:300006191"
    ]
},
  "bbox": [],
  "geometry": {"coordinates":[-108.2833,36.95],"type":"Point"}
}