{
  "id": 2122458,
  "type": "Feature",
  "properties": {
    "tgn:hierarchy":[
        "tgn:2122458",
        "tgn:1000001",
        "tgn:7012149",
        "tgn:2002343",
        "tgn:7007922",
        "tgn:7029392"
    ],
    "tgn:id":2122458,
    "tgn:name":"Stephensville",
    "tgn:placetype":[
        "aat:300008347"
    ]
},
  "bbox": [],
  "geometry": {"coordinates":[-88.5833,44.3667],"type":"Point"}
}