{
  "id": 2088645,
  "type": "Feature",
  "properties": {
    "tgn:hierarchy":[
        "tgn:2088645",
        "tgn:1000001",
        "tgn:1002272",
        "tgn:7012149",
        "tgn:7007710",
        "tgn:7029392"
    ],
    "tgn:id":2088645,
    "tgn:name":"Fryburg",
    "tgn:placetype":[
        "aat:300008347"
    ]
},
  "bbox": [],
  "geometry": {"coordinates":[-79.4333,41.35],"type":"Point"}
}