{
  "id": 2039617,
  "type": "Feature",
  "properties": {
    "tgn:hierarchy":[
        "tgn:2039617",
        "tgn:2000765",
        "tgn:1000001",
        "tgn:7012149",
        "tgn:7007255",
        "tgn:7029392"
    ],
    "tgn:id":2039617,
    "tgn:name":"Joppa",
    "tgn:placetype":[
        "aat:300008347",
        "aat:300387210"
    ]
},
  "bbox": [],
  "geometry": {"coordinates":[-85.2333,37.05],"type":"Point"}
}