{
  "id": 2079843,
  "type": "Feature",
  "properties": {
    "tgn:hierarchy":[
        "tgn:2079843",
        "tgn:1000001",
        "tgn:7012149",
        "tgn:1002424",
        "tgn:7007706",
        "tgn:7029392"
    ],
    "tgn:id":2079843,
    "tgn:name":"Gunnerville",
    "tgn:placetype":[
        "aat:300008347"
    ]
},
  "bbox": [],
  "geometry": {"coordinates":[-83.75,39.5833],"type":"Point"}
}