{
  "id": 2743851,
  "type": "Feature",
  "properties": {
    "tgn:hierarchy":[
        "tgn:2743851",
        "tgn:1000001",
        "tgn:7006451",
        "tgn:7012149",
        "tgn:7029392"
    ],
    "tgn:id":2743851,
    "tgn:name":"Vekol Mountains",
    "tgn:placetype":[
        "aat:300386831"
    ]
},
  "bbox": [],
  "geometry": {"coordinates":[-112.1167,32.5833],"type":"Point"}
}