{
  "id": 2324135,
  "type": "Feature",
  "properties": {
    "tgn:hierarchy":[
        "tgn:2324135",
        "tgn:1000001",
        "tgn:1002695",
        "tgn:7012149",
        "tgn:7007565",
        "tgn:7029392"
    ],
    "tgn:id":2324135,
    "tgn:name":"Fayson Lakes",
    "tgn:placetype":[
        "aat:300008680"
    ]
},
  "bbox": [],
  "geometry": {"coordinates":[-74.35,40.9667],"type":"Point"}
}