<<<<<<< HEAD
{
  "id": 2334618,
  "type": "Feature",
  "properties": {
    "tgn:hierarchy":[
        "tgn:2334618",
        "tgn:1002169",
        "tgn:1000001",
        "tgn:7012149",
        "tgn:7007255",
        "tgn:7029392"
    ],
    "tgn:id":2334618,
    "tgn:name":"Forge Creek",
    "tgn:placetype":[
        "aat:300008706"
    ]
},
  "bbox": [],
  "geometry": {"coordinates":[-83.75,38.25],"type":"Point"}
}
=======
{"geometry":{"type":"Point","coordinates":[-83.750000,38.250000]},"type":"Feature","properties":{"hierarchy":["tgn:2334618","tgn:1002169","tgn:1000001","tgn:7012149","tgn:7007255","tgn:7029392"],"placetype":["aat:300008706"],"id":2334618,"name:xx":"Forge Creek"}}
>>>>>>> 03f74aca74312dbeaf24d7e61306dd6a786dc3d0
