{
  "id": 7185479,
  "type": "Feature",
  "properties": {
    "tgn:hierarchy":[
        "tgn:7185479",
        "tgn:1000003",
        "tgn:7003678",
        "tgn:7000084",
        "tgn:7029392"
    ],
    "tgn:id":7185479,
    "tgn:name":"Gerten-Berg",
    "tgn:placetype":[
        "aat:300008777"
    ]
},
  "bbox": [],
  "geometry": {"coordinates":[9.066667,51.433333],"type":"Point"}
}