{
  "id": 2204637,
  "type": "Feature",
  "properties": {
    "tgn:hierarchy":[
        "tgn:2204637",
        "tgn:1000001",
        "tgn:7012149",
        "tgn:2000796",
        "tgn:7007255",
        "tgn:7029392"
    ],
    "tgn:id":2204637,
    "tgn:name":"Buffalo Lake",
    "tgn:placetype":[
        "aat:300006191"
    ]
},
  "bbox": [],
  "geometry": {"coordinates":[-85.8333,37.6833],"type":"Point"}
}