{
  "id": 7351820,
  "type": "Feature",
  "properties": {
    "tgn:hierarchy":[
        "tgn:7351820",
        "tgn:1000001",
        "tgn:7005595",
        "tgn:7005560",
        "tgn:7029392"
    ],
    "tgn:id":7351820,
    "tgn:name":"Bar\u00edometo",
    "tgn:placetype":[
        "aat:300008347"
    ]
},
  "bbox": [],
  "geometry": {"coordinates":[-107.662222,24.764444],"type":"Point"}
}