{
  "id": 7533695,
  "type": "Feature",
  "properties": {
    "tgn:hierarchy":[
        "tgn:7533695",
        "tgn:7001242",
        "tgn:7016833",
        "tgn:1001142",
        "tgn:7029392"
    ],
    "tgn:id":7533695,
    "tgn:name:en":"Kafr Man\u015f\u016br",
    "tgn:placetype":[
        "aat:300008347"
    ]
},
  "bbox": [],
  "geometry": {"coordinates":[30.016667,28.983333],"type":"Point"}
}