{
  "id": 7221030,
  "type": "Feature",
  "properties": {
    "tgn:hierarchy":[
        "tgn:7221030",
        "tgn:7002681",
        "tgn:7001395",
        "tgn:1000003",
        "tgn:1000074",
        "tgn:7029392"
    ],
    "tgn:id":7221030,
    "tgn:name":"Zogko\u00fa, Orm\u00edskos",
    "tgn:placetype":[
        "aat:300132316"
    ]
},
  "bbox": [],
  "geometry": {"coordinates":[23.575515,37.358953],"type":"Point"}
}