{
  "id": 1125647,
  "type": "Feature",
  "properties": {
    "tgn:hierarchy":[
        "tgn:1125647",
        "tgn:7003692",
        "tgn:1000003",
        "tgn:7000084",
        "tgn:7029392"
    ],
    "tgn:id":1125647,
    "tgn:name":"Kocher",
    "tgn:placetype":[
        "aat:300008707",
        "aat:300008699"
    ]
},
  "bbox": [],
  "geometry": {"coordinates":[9.202778,49.223611],"type":"Point"}
}