{
  "id": 2137196,
  "type": "Feature",
  "properties": {
    "tgn:hierarchy":[
        "tgn:2137196",
        "tgn:1000001",
        "tgn:7012149",
        "tgn:7014612",
        "tgn:7007568",
        "tgn:7029392"
    ],
    "tgn:id":2137196,
    "tgn:name":"Armawalk",
    "tgn:placetype":[
        "aat:300008347"
    ]
},
  "bbox": [],
  "geometry": {"coordinates":[-73.7667,41.2833],"type":"Point"}
}