{
  "id": 2695497,
  "type": "Feature",
  "properties": {
    "tgn:hierarchy":[
        "tgn:2695497",
        "tgn:7006450",
        "tgn:1000001",
        "tgn:7012149",
        "tgn:7019760",
        "tgn:7029392"
    ],
    "tgn:id":2695497,
    "tgn:name":"Stink Creek",
    "tgn:placetype":[
        "aat:300008706"
    ]
},
  "bbox": [],
  "geometry": {"coordinates":[-134.4167,58.1167],"type":"Point"}
}