{
  "id": 2658589,
  "type": "Feature",
  "properties": {
    "tgn:hierarchy":[
        "tgn:2658589",
        "tgn:1000001",
        "tgn:7012149",
        "tgn:1002486",
        "tgn:7007826",
        "tgn:7029392"
    ],
    "tgn:id":2658589,
    "tgn:name":"Sheridan Branch",
    "tgn:placetype":[
        "aat:300008699"
    ]
},
  "bbox": [],
  "geometry": {"coordinates":[-95.3333,31.5167],"type":"Point"}
}