{
  "id": 7558928,
  "type": "Feature",
  "properties": {
    "tgn:hierarchy":[
        "tgn:7558928",
        "tgn:1000004",
        "tgn:1001832",
        "tgn:7000198",
        "tgn:7029392"
    ],
    "tgn:id":7558928,
    "tgn:name:en":"Saralbh\u0101nga River",
    "tgn:placetype":[
        "aat:300008699"
    ]
},
  "bbox": [],
  "geometry": {"coordinates":[90.259077,26.444336],"type":"Point"}
}