{
  "id": 2312900,
  "type": "Feature",
  "properties": {
    "tgn:hierarchy":[
        "tgn:2312900",
        "tgn:1000001",
        "tgn:7006451",
        "tgn:7012149",
        "tgn:2000097",
        "tgn:7029392"
    ],
    "tgn:id":2312900,
    "tgn:name":"El Tigre Mine",
    "tgn:placetype":[
        "aat:300000390"
    ]
},
  "bbox": [],
  "geometry": {"coordinates":[-113.1833,33.7333],"type":"Point"}
}