{
  "id": 7096004,
  "type": "Feature",
  "properties": {
    "tgn:hierarchy":[
        "tgn:7096004",
        "tgn:7003669",
        "tgn:1000003",
        "tgn:7000084",
        "tgn:7029392"
    ],
    "tgn:id":7096004,
    "tgn:name":"Schwan See",
    "tgn:placetype":[
        "aat:300008680"
    ]
},
  "bbox": [],
  "geometry": {"coordinates":[10.716667,47.55],"type":"Point"}
}