{
  "id": 7568514,
  "type": "Feature",
  "properties": {
    "tgn:hierarchy":[
        "tgn:7568514",
        "tgn:1000004",
        "tgn:7000198",
        "tgn:7016788",
        "tgn:7029392"
    ],
    "tgn:id":7568514,
    "tgn:name:en":"Sapt\u012bja",
    "tgn:placetype":[
        "aat:300008347"
    ]
},
  "bbox": [],
  "geometry": {"coordinates":[75.719049,25.348775],"type":"Point"}
}