<<<<<<< HEAD
{
  "id": 2255550,
  "type": "Feature",
  "properties": {
    "tgn:hierarchy":[
        "tgn:2255550",
        "tgn:1000001",
        "tgn:7012149",
        "tgn:2002044",
        "tgn:7007826",
        "tgn:7029392"
    ],
    "tgn:id":2255550,
    "tgn:name":"Copeland Creek",
    "tgn:placetype":[
        "aat:300008706"
    ]
},
  "bbox": [],
  "geometry": {"coordinates":[-97.4833,33.7],"type":"Point"}
}
=======
{"geometry":{"type":"Point","coordinates":[-97.483300,33.700000]},"type":"Feature","properties":{"hierarchy":["tgn:2255550","tgn:1000001","tgn:7012149","tgn:2002044","tgn:7007826","tgn:7029392"],"placetype":["aat:300008706"],"id":2255550,"name:xx":"Copeland Creek"}}
>>>>>>> 03f74aca74312dbeaf24d7e61306dd6a786dc3d0
