{
  "id": 2574410,
  "type": "Feature",
  "properties": {
    "tgn:hierarchy":[
        "tgn:2574410",
        "tgn:1000001",
        "tgn:7012149",
        "tgn:2001718",
        "tgn:7007708",
        "tgn:7029392"
    ],
    "tgn:id":2574410,
    "tgn:name":"Pelican Point",
    "tgn:placetype":[
        "aat:300008850"
    ]
},
  "bbox": [],
  "geometry": {"coordinates":[-117.3333,43.4167],"type":"Point"}
}