{
  "id": 2121914,
  "type": "Feature",
  "properties": {
    "tgn:hierarchy":[
        "tgn:2121914",
        "tgn:1000001",
        "tgn:2002324",
        "tgn:7012149",
        "tgn:7007922",
        "tgn:7029392"
    ],
    "tgn:id":2121914,
    "tgn:name":"Muscoda",
    "tgn:placetype":[
        "aat:300008347"
    ]
},
  "bbox": [],
  "geometry": {"coordinates":[-90.4333,43.1833],"type":"Point"}
}