{
  "id": 2178341,
  "type": "Feature",
  "properties": {
    "tgn:hierarchy":[
        "tgn:2178341",
        "tgn:1000001",
        "tgn:7012149",
        "tgn:2002359",
        "tgn:7007922",
        "tgn:7029392"
    ],
    "tgn:id":2178341,
    "tgn:name":"Blackjack Springs",
    "tgn:placetype":[
        "aat:300008697"
    ]
},
  "bbox": [],
  "geometry": {"coordinates":[-89.0833,45.9833],"type":"Point"}
}