{
  "id": 2148993,
  "type": "Feature",
  "properties": {
    "tgn:hierarchy":[
        "tgn:2148993",
        "tgn:1000001",
        "tgn:7012149",
        "tgn:1002926",
        "tgn:7007568",
        "tgn:7029392"
    ],
    "tgn:id":2148993,
    "tgn:name":"Barnhardt Pond",
    "tgn:placetype":[
        "aat:300008680"
    ]
},
  "bbox": [],
  "geometry": {"coordinates":[-74.9667,41.6833],"type":"Point"}
}