<<<<<<< HEAD
{
  "id": 7362708,
  "type": "Feature",
  "properties": {
    "tgn:hierarchy":[
        "tgn:7362708",
        "tgn:7005584",
        "tgn:1000001",
        "tgn:7005560",
        "tgn:7029392"
    ],
    "tgn:id":7362708,
    "tgn:name":"El M\u00e1rmol",
    "tgn:placetype":[
        "aat:300008347"
    ]
},
  "bbox": [],
  "geometry": {"coordinates":[-101.566667,20.833333],"type":"Point"}
}
=======
{"geometry":{"type":"Point","coordinates":[-101.566667,20.833333]},"type":"Feature","properties":{"hierarchy":["tgn:7362708","tgn:7005584","tgn:1000001","tgn:7005560","tgn:7029392"],"placetype":["aat:300008347"],"id":7362708,"name:xx":"El M\u00e1rmol"}}
>>>>>>> 03f74aca74312dbeaf24d7e61306dd6a786dc3d0
