{
  "id": 7057326,
  "type": "Feature",
  "properties": {
    "tgn:hierarchy":[
        "tgn:7057326",
        "tgn:7003168",
        "tgn:1000003",
        "tgn:7009760",
        "tgn:1000080",
        "tgn:7029392"
    ],
    "tgn:id":7057326,
    "tgn:name":"Badesse",
    "tgn:placetype":[
        "aat:300008347"
    ]
},
  "bbox": [],
  "geometry": {"coordinates":[11.266667,43.383333],"type":"Point"}
}