{
  "id": 7152859,
  "type": "Feature",
  "properties": {
    "tgn:hierarchy":[
        "tgn:7152859",
        "tgn:1000003",
        "tgn:7003688",
        "tgn:7000084",
        "tgn:7029392"
    ],
    "tgn:id":7152859,
    "tgn:name":"J\u00e4gers Berg",
    "tgn:placetype":[
        "aat:300008777"
    ]
},
  "bbox": [],
  "geometry": {"coordinates":[10.35,54.416667],"type":"Point"}
}