{
  "id": 2327134,
  "type": "Feature",
  "properties": {
    "tgn:hierarchy":[
        "tgn:2327134",
        "tgn:7006450",
        "tgn:1000001",
        "tgn:7012149",
        "tgn:2124014",
        "tgn:7029392"
    ],
    "tgn:id":2327134,
    "tgn:name":"First Chance Creek",
    "tgn:placetype":[
        "aat:300008706"
    ]
},
  "bbox": [],
  "geometry": {"coordinates":[-161.9167,65.8333],"type":"Point"}
}