{
  "id": 7046171,
  "type": "Feature",
  "properties": {
    "tgn:hierarchy":[
        "tgn:7046171",
        "tgn:7015163",
        "tgn:1000003",
        "tgn:7003121",
        "tgn:1000080",
        "tgn:7029392"
    ],
    "tgn:id":7046171,
    "tgn:name":"Camicia, Cala",
    "tgn:placetype":[
        "aat:300132317"
    ]
},
  "bbox": [],
  "geometry": {"coordinates":[9.416667,41.216667],"type":"Point"}
}