{
  "id": 2155988,
  "type": "Feature",
  "properties": {
    "tgn:hierarchy":[
        "tgn:2155988",
        "tgn:1000001",
        "tgn:2001260",
        "tgn:7012149",
        "tgn:7007524",
        "tgn:7029392"
    ],
    "tgn:id":2155988,
    "tgn:name":"Bear Wallow Creek",
    "tgn:placetype":[
        "aat:300008706"
    ]
},
  "bbox": [],
  "geometry": {"coordinates":[-113.1667,45.4833],"type":"Point"}
}