<<<<<<< HEAD
{
  "id": 2155988,
  "type": "Feature",
  "properties": {
    "tgn:hierarchy":[
        "tgn:2155988",
        "tgn:1000001",
        "tgn:2001260",
        "tgn:7012149",
        "tgn:7007524",
        "tgn:7029392"
    ],
    "tgn:id":2155988,
    "tgn:name":"Bear Wallow Creek",
    "tgn:placetype":[
        "aat:300008706"
    ]
},
  "bbox": [],
  "geometry": {"coordinates":[-113.1667,45.4833],"type":"Point"}
}
=======
{"geometry":{"type":"Point","coordinates":[-113.166700,45.483300]},"type":"Feature","properties":{"hierarchy":["tgn:2155988","tgn:1000001","tgn:2001260","tgn:7012149","tgn:7007524","tgn:7029392"],"placetype":["aat:300008706"],"id":2155988,"name:xx":"Bear Wallow Creek"}}
>>>>>>> 03f74aca74312dbeaf24d7e61306dd6a786dc3d0
