{
  "id": 7590141,
  "type": "Feature",
  "properties": {
    "tgn:hierarchy":[
        "tgn:7590141",
        "tgn:1000004",
        "tgn:7000198",
        "tgn:7000799",
        "tgn:7029392"
    ],
    "tgn:id":7590141,
    "tgn:name:en":"Hapatpathri",
    "tgn:placetype":[
        "aat:300008347"
    ]
},
  "bbox": [],
  "geometry": {"coordinates":[74.333333,33.863889],"type":"Point"}
}