<<<<<<< HEAD
{
  "id": 2337581,
  "type": "Feature",
  "properties": {
    "tgn:hierarchy":[
        "tgn:2337581",
        "tgn:2000001",
        "tgn:7002659",
        "tgn:1000001",
        "tgn:7012149",
        "tgn:7029392"
    ],
    "tgn:id":2337581,
    "tgn:name":"Fox Branch",
    "tgn:placetype":[
        "aat:300008699"
    ]
},
  "bbox": [],
  "geometry": {"coordinates":[-87.7,30.6333],"type":"Point"}
}
=======
{"geometry":{"type":"Point","coordinates":[-87.700000,30.633300]},"type":"Feature","properties":{"hierarchy":["tgn:2337581","tgn:2000001","tgn:7002659","tgn:1000001","tgn:7012149","tgn:7029392"],"placetype":["aat:300008699"],"id":2337581,"name:xx":"Fox Branch"}}
>>>>>>> 03f74aca74312dbeaf24d7e61306dd6a786dc3d0
