{
  "id": 2119440,
  "type": "Feature",
  "properties": {
    "tgn:hierarchy":[
        "tgn:2119440",
        "tgn:1000001",
        "tgn:7012149",
        "tgn:2002278",
        "tgn:7013961",
        "tgn:7029392"
    ],
    "tgn:id":2119440,
    "tgn:name":"Oakvale",
    "tgn:placetype":[
        "aat:300008347"
    ]
},
  "bbox": [],
  "geometry": {"coordinates":[-80.95,37.3333],"type":"Point"}
}