{
  "id": 2573604,
  "type": "Feature",
  "properties": {
    "tgn:hierarchy":[
        "tgn:2573604",
        "tgn:1000001",
        "tgn:2000198",
        "tgn:7012149",
        "tgn:7007158",
        "tgn:7029392"
    ],
    "tgn:id":2573604,
    "tgn:name":"Peck Gulch",
    "tgn:placetype":[
        "aat:300008761"
    ]
},
  "bbox": [],
  "geometry": {"coordinates":[-105.4833,40.0667],"type":"Point"}
}