{
  "id": 2591460,
  "type": "Feature",
  "properties": {
    "tgn:hierarchy":[
        "tgn:2591460",
        "tgn:1000001",
        "tgn:7012149",
        "tgn:2000734",
        "tgn:7007254",
        "tgn:7029392"
    ],
    "tgn:id":2591460,
    "tgn:name":"Pomeroy Creek",
    "tgn:placetype":[
        "aat:300008706"
    ]
},
  "bbox": [],
  "geometry": {"coordinates":[-96.15,39.35],"type":"Point"}
}