{
  "id": 7018542,
  "type": "Feature",
  "properties": {
    "tgn:hierarchy":[
        "tgn:7018542",
        "tgn:7005557",
        "tgn:7018538",
        "tgn:1000001",
        "tgn:7005556",
        "tgn:7029392"
    ],
    "tgn:id":7018542,
    "tgn:name":"Maggotty",
    "tgn:placetype":[
        "aat:300008347",
        "aat:300008375"
    ]
},
  "bbox": [],
  "geometry": {"coordinates":[-77.763,18.16],"type":"Point"}
}