{
  "id": 7312416,
  "type": "Feature",
  "properties": {
    "tgn:hierarchy":[
        "tgn:7312416",
        "tgn:7002464",
        "tgn:1000049",
        "tgn:1000002",
        "tgn:7029392"
    ],
    "tgn:id":7312416,
    "tgn:name":"Larga, Punta",
    "tgn:placetype":[
        "aat:300386846"
    ]
},
  "bbox": [],
  "geometry": {"coordinates":[-70.133333,-20.283333],"type":"Point"}
}