<<<<<<< HEAD
{
  "id": 7369158,
  "type": "Feature",
  "properties": {
    "tgn:hierarchy":[
        "tgn:7369158",
        "tgn:7005581",
        "tgn:1000001",
        "tgn:7005560",
        "tgn:7029392"
    ],
    "tgn:id":7369158,
    "tgn:name":"Ju\u00e1rez y Reforma",
    "tgn:placetype":[
        "aat:300008347"
    ]
},
  "bbox": [],
  "geometry": {"coordinates":[-106.166667,31.433333],"type":"Point"}
}
=======
{"geometry":{"type":"Point","coordinates":[-106.166667,31.433333]},"type":"Feature","properties":{"hierarchy":["tgn:7369158","tgn:7005581","tgn:1000001","tgn:7005560","tgn:7029392"],"placetype":["aat:300008347"],"id":7369158,"name:xx":"Ju\u00e1rez y Reforma"}}
>>>>>>> 03f74aca74312dbeaf24d7e61306dd6a786dc3d0
