{
  "id": 2371064,
  "type": "Feature",
  "properties": {
    "tgn:hierarchy":[
        "tgn:2371064",
        "tgn:1000001",
        "tgn:7012149",
        "tgn:2001716",
        "tgn:7007708",
        "tgn:7029392"
    ],
    "tgn:id":2371064,
    "tgn:name":"Hagan Block Research Natural Area",
    "tgn:placetype":[
        "aat:300008863"
    ]
},
  "bbox": [],
  "geometry": {"coordinates":[-122.4167,44.1667],"type":"Point"}
}