{
  "id": 7401961,
  "type": "Feature",
  "properties": {
    "tgn:hierarchy":[
        "tgn:7401961",
        "tgn:1000001",
        "tgn:7005599",
        "tgn:7005560",
        "tgn:7029392"
    ],
    "tgn:id":7401961,
    "tgn:name":"La Ceiba",
    "tgn:placetype":[
        "aat:300008347"
    ]
},
  "bbox": [],
  "geometry": {"coordinates":[-96.547222,19.197222],"type":"Point"}
}