{
  "id": 7181690,
  "type": "Feature",
  "properties": {
    "tgn:hierarchy":[
        "tgn:7181690",
        "tgn:7000096",
        "tgn:1000003",
        "tgn:7000084",
        "tgn:7029392"
    ],
    "tgn:id":7181690,
    "tgn:name":"Ganzer",
    "tgn:placetype":[
        "aat:300008347"
    ]
},
  "bbox": [],
  "geometry": {"coordinates":[12.566667,52.883333],"type":"Point"}
}