{
  "id": 2261084,
  "type": "Feature",
  "properties": {
    "tgn:hierarchy":[
        "tgn:2261084",
        "tgn:1000001",
        "tgn:2001012",
        "tgn:7012149",
        "tgn:7007521",
        "tgn:7029392"
    ],
    "tgn:id":2261084,
    "tgn:name":"County Ditch Number Twentyeight",
    "tgn:placetype":[
        "aat:300006075"
    ]
},
  "bbox": [],
  "geometry": {"coordinates":[-96.7833,47.0333],"type":"Point"}
}