{
  "id": 2034864,
  "type": "Feature",
  "properties": {
    "tgn:hierarchy":[
        "tgn:2034864",
        "tgn:1000001",
        "tgn:7012149",
        "tgn:2000620",
        "tgn:7007253",
        "tgn:7029392"
    ],
    "tgn:id":2034864,
    "tgn:name":"Granite",
    "tgn:placetype":[
        "aat:300008347",
        "aat:300387210"
    ]
},
  "bbox": [],
  "geometry": {"coordinates":[-96.55,43.4667],"type":"Point"}
}