{
  "id": 2342547,
  "type": "Feature",
  "properties": {
    "tgn:hierarchy":[
        "tgn:2342547",
        "tgn:1000001",
        "tgn:7012149",
        "tgn:2001446",
        "tgn:7007566",
        "tgn:7029392"
    ],
    "tgn:id":2342547,
    "tgn:name":"Fulton 1 Santa Fe",
    "tgn:placetype":[
        "aat:300000390"
    ]
},
  "bbox": [],
  "geometry": {"coordinates":[-104.6667,35.8833],"type":"Point"}
}