{
  "id": 7042549,
  "type": "Feature",
  "properties": {
    "tgn:hierarchy":[
        "tgn:7042549",
        "tgn:7009084",
        "tgn:7004154",
        "tgn:1000003",
        "tgn:1000080",
        "tgn:7029392"
    ],
    "tgn:id":7042549,
    "tgn:name":"Salle",
    "tgn:placetype":[
        "aat:300008347"
    ]
},
  "bbox": [],
  "geometry": {"coordinates":[13.95,42.166667],"type":"Point"}
}