<<<<<<< HEAD
{
  "id": 7113058,
  "type": "Feature",
  "properties": {
    "tgn:hierarchy":[
        "tgn:7113058",
        "tgn:7003692",
        "tgn:1000003",
        "tgn:7000084",
        "tgn:7029392"
    ],
    "tgn:id":7113058,
    "tgn:name":"Reuteh\u00f6fe",
    "tgn:placetype":[
        "aat:300000206"
    ]
},
  "bbox": [],
  "geometry": {"coordinates":[9.2,47.783333],"type":"Point"}
}
=======
{"geometry":{"type":"Point","coordinates":[9.200000,47.783333]},"type":"Feature","properties":{"hierarchy":["tgn:7113058","tgn:7003692","tgn:1000003","tgn:7000084","tgn:7029392"],"placetype":["aat:300000206"],"id":7113058,"name:xx":"Reuteh\u00f6fe"}}
>>>>>>> 03f74aca74312dbeaf24d7e61306dd6a786dc3d0
