{
  "id": 7180784,
  "type": "Feature",
  "properties": {
    "tgn:hierarchy":[
        "tgn:7180784",
        "tgn:1000003",
        "tgn:7003685",
        "tgn:7000084",
        "tgn:7029392"
    ],
    "tgn:id":7180784,
    "tgn:name":"Gassenreuth",
    "tgn:placetype":[
        "aat:300008347"
    ]
},
  "bbox": [],
  "geometry": {"coordinates":[12.05,50.333333],"type":"Point"}
}