{
  "id": 2619827,
  "type": "Feature",
  "properties": {
    "tgn:hierarchy":[
        "tgn:2619827",
        "tgn:1000001",
        "tgn:7012149",
        "tgn:2000620",
        "tgn:7007253",
        "tgn:7029392"
    ],
    "tgn:id":2619827,
    "tgn:name":"Rio Grande Creek",
    "tgn:placetype":[
        "aat:300008706"
    ]
},
  "bbox": [],
  "geometry": {"coordinates":[-95.9667,43.3667],"type":"Point"}
}