{
  "id": 2086535,
  "type": "Feature",
  "properties": {
    "tgn:hierarchy":[
        "tgn:2086535",
        "tgn:1000001",
        "tgn:1002249",
        "tgn:7012149",
        "tgn:7007710",
        "tgn:7029392"
    ],
    "tgn:id":2086535,
    "tgn:name":"Boalsburg",
    "tgn:placetype":[
        "aat:300008347"
    ]
},
  "bbox": [],
  "geometry": {"coordinates":[-77.7833,40.7667],"type":"Point"}
}