{
  "id": 7419673,
  "type": "Feature",
  "properties": {
    "tgn:hierarchy":[
        "tgn:7419673",
        "tgn:1001836",
        "tgn:1000001",
        "tgn:7005560",
        "tgn:7029392"
    ],
    "tgn:id":7419673,
    "tgn:name":"Los M\u00e9danos Partidos",
    "tgn:placetype":[
        "aat:300008347"
    ]
},
  "bbox": [],
  "geometry": {"coordinates":[-109.995833,22.887778],"type":"Point"}
}