{
  "id": 2637941,
  "type": "Feature",
  "properties": {
    "tgn:hierarchy":[
        "tgn:2637941",
        "tgn:1000001",
        "tgn:7012149",
        "tgn:2001924",
        "tgn:7007825",
        "tgn:7029392"
    ],
    "tgn:id":2637941,
    "tgn:name":"Salamander Pit",
    "tgn:placetype":[
        "aat:300008746"
    ]
},
  "bbox": [],
  "geometry": {"coordinates":[-85.5167,35.7167],"type":"Point"}
}