{
  "id": 7348263,
  "type": "Feature",
  "properties": {
    "tgn:hierarchy":[
        "tgn:7348263",
        "tgn:7002825",
        "tgn:7016622",
        "tgn:1000003",
        "tgn:1000095",
        "tgn:7029392"
    ],
    "tgn:id":7348263,
    "tgn:name":"\u00c1guila, Playa del",
    "tgn:placetype":[
        "aat:300008816"
    ]
},
  "bbox": [],
  "geometry": {"coordinates":[-14.016667,28.65],"type":"Point"}
}