{
  "id": 7234775,
  "type": "Feature",
  "properties": {
    "tgn:hierarchy":[
        "tgn:7234775",
        "tgn:7002725",
        "tgn:7002715",
        "tgn:1000003",
        "tgn:1000074",
        "tgn:7029392"
    ],
    "tgn:id":7234775,
    "tgn:name":"Bouts\u00e1va",
    "tgn:placetype":[
        "aat:300008699"
    ]
},
  "bbox": [],
  "geometry": {"coordinates":[22.55,40.95],"type":"Point"}
}