{
  "id": 7488853,
  "type": "Feature",
  "properties": {
    "tgn:hierarchy":[
        "tgn:7488853",
        "tgn:1000004",
        "tgn:7001009",
        "tgn:1000141",
        "tgn:7029392"
    ],
    "tgn:id":7488853,
    "tgn:name":"Nantun",
    "tgn:placetype":[
        "aat:300000745"
    ]
},
  "bbox": [],
  "geometry": {"coordinates":[120.638592,24.138612],"type":"Point"}
}