<<<<<<< HEAD
{
  "id": 7248802,
  "type": "Feature",
  "properties": {
    "tgn:hierarchy":[
        "tgn:7248802",
        "tgn:7018237",
        "tgn:1000003",
        "tgn:1000063",
        "tgn:7029392"
    ],
    "tgn:id":7248802,
    "tgn:name":"Boetendaal",
    "tgn:placetype":[
        "aat:300005567"
    ]
},
  "bbox": [],
  "geometry": {"coordinates":[4.35,50.8],"type":"Point"}
}
=======
{"geometry":{"type":"Point","coordinates":[4.350000,50.800000]},"type":"Feature","properties":{"hierarchy":["tgn:7248802","tgn:7018237","tgn:1000003","tgn:1000063","tgn:7029392"],"placetype":["aat:300005567"],"id":7248802,"name:xx":"Boetendaal"}}
>>>>>>> 03f74aca74312dbeaf24d7e61306dd6a786dc3d0
