{
  "id": 1019479,
  "type": "Feature",
  "properties": {
    "tgn:hierarchy":[
        "tgn:1019479",
        "tgn:1001160",
        "tgn:7006477",
        "tgn:1000002",
        "tgn:7029392"
    ],
    "tgn:id":1019479,
    "tgn:name":"Gar\u00edn",
    "tgn:placetype":[
        "aat:300008347"
    ]
},
  "bbox": [],
  "geometry": {"coordinates":[-58.7333,-34.4333],"type":"Point"}
}