{
  "id": 2711563,
  "type": "Feature",
  "properties": {
    "tgn:hierarchy":[
        "tgn:2711563",
        "tgn:1000001",
        "tgn:7006451",
        "tgn:2000092",
        "tgn:7012149",
        "tgn:7029392"
    ],
    "tgn:id":2711563,
    "tgn:name":"Tappan Wash",
    "tgn:placetype":[
        "aat:300008699"
    ]
},
  "bbox": [],
  "geometry": {"coordinates":[-111.7667,35.8667],"type":"Point"}
}