{
  "id": 2741680,
  "type": "Feature",
  "properties": {
    "tgn:hierarchy":[
        "tgn:2741680",
        "tgn:1000001",
        "tgn:2001432",
        "tgn:7012149",
        "tgn:7007566",
        "tgn:7029392"
    ],
    "tgn:id":2741680,
    "tgn:name":"Ute Gulch",
    "tgn:placetype":[
        "aat:300008761"
    ]
},
  "bbox": [],
  "geometry": {"coordinates":[-105.0667,36.5167],"type":"Point"}
}