{
  "id": 7312631,
  "type": "Feature",
  "properties": {
    "tgn:hierarchy":[
        "tgn:7312631",
        "tgn:1001695",
        "tgn:1000049",
        "tgn:1000002",
        "tgn:7029392"
    ],
    "tgn:id":7312631,
    "tgn:name":"La Quinta",
    "tgn:placetype":[
        "aat:300000206"
    ]
},
  "bbox": [],
  "geometry": {"coordinates":[-70.966667,-34.383333],"type":"Point"}
}