{
  "id": 7504310,
  "type": "Feature",
  "properties": {
    "tgn:hierarchy":[
        "tgn:7504310",
        "tgn:1009227",
        "tgn:1000226",
        "tgn:7018437",
        "tgn:1000006",
        "tgn:7029392"
    ],
    "tgn:id":7504310,
    "tgn:name:en":"Waitoi Creek",
    "tgn:placetype":[
        "aat:300008699"
    ]
},
  "bbox": [],
  "geometry": {"coordinates":[169.983333,-45.25],"type":"Point"}
}