{
  "id": 7499811,
  "type": "Feature",
  "properties": {
    "tgn:hierarchy":[
        "tgn:7499811",
        "tgn:7001010",
        "tgn:1000004",
        "tgn:1000141",
        "tgn:7029392"
    ],
    "tgn:id":7499811,
    "tgn:name":"Tiefen Qiao",
    "tgn:placetype":[
        "aat:300007836"
    ]
},
  "bbox": [],
  "geometry": {"coordinates":[121.343912,23.345154],"type":"Point"}
}