{
  "id": 7169916,
  "type": "Feature",
  "properties": {
    "tgn:hierarchy":[
        "tgn:7169916",
        "tgn:7003669",
        "tgn:1000003",
        "tgn:7000084",
        "tgn:7029392"
    ],
    "tgn:id":7169916,
    "tgn:name":"Hoch Berg",
    "tgn:placetype":[
        "aat:300008795"
    ]
},
  "bbox": [],
  "geometry": {"coordinates":[11.566667,47.616667],"type":"Point"}
}