{
  "id": 7484764,
  "type": "Feature",
  "properties": {
    "tgn:hierarchy":[
        "tgn:7484764",
        "tgn:1000004",
        "tgn:7001009",
        "tgn:1000141",
        "tgn:7029392"
    ],
    "tgn:id":7484764,
    "tgn:name":"Jicuo",
    "tgn:placetype":[
        "aat:300008347"
    ]
},
  "bbox": [],
  "geometry": {"coordinates":[120.613611,24.371389],"type":"Point"}
}