{
  "id": 2540927,
  "type": "Feature",
  "properties": {
    "tgn:hierarchy":[
        "tgn:2540927",
        "tgn:1000001",
        "tgn:7012149",
        "tgn:2002372",
        "tgn:7007923",
        "tgn:7029392"
    ],
    "tgn:id":2540927,
    "tgn:name":"Nichols Canyon",
    "tgn:placetype":[
        "aat:300008761"
    ]
},
  "bbox": [],
  "geometry": {"coordinates":[-104.1833,42.6167],"type":"Point"}
}