{
  "id": 1095578,
  "type": "Feature",
  "properties": {
    "tgn:hierarchy":[
        "tgn:1095578",
        "tgn:7001242",
        "tgn:1001075",
        "tgn:7016833",
        "tgn:7029392"
    ],
    "tgn:id":1095578,
    "tgn:name:en":"Ma\u1e29allat Kayl",
    "tgn:placetype":[
        "aat:300008347"
    ]
},
  "bbox": [],
  "geometry": {"coordinates":[30.289433,31.009994],"type":"Point"}
}