<<<<<<< HEAD
{
  "id": 2339726,
  "type": "Feature",
  "properties": {
    "tgn:hierarchy":[
        "tgn:2339726",
        "tgn:1000001",
        "tgn:7012149",
        "tgn:2002100",
        "tgn:7007826",
        "tgn:7029392"
    ],
    "tgn:id":2339726,
    "tgn:name":"Freed Tank",
    "tgn:placetype":[
        "aat:300006191"
    ]
},
  "bbox": [],
  "geometry": {"coordinates":[-99.7,28.8333],"type":"Point"}
}
=======
{"geometry":{"type":"Point","coordinates":[-99.700000,28.833300]},"type":"Feature","properties":{"hierarchy":["tgn:2339726","tgn:1000001","tgn:7012149","tgn:2002100","tgn:7007826","tgn:7029392"],"placetype":["aat:300006191"],"id":2339726,"name:xx":"Freed Tank"}}
>>>>>>> 03f74aca74312dbeaf24d7e61306dd6a786dc3d0
