{
  "id": 2663220,
  "type": "Feature",
  "properties": {
    "tgn:hierarchy":[
        "tgn:2663220",
        "tgn:1000001",
        "tgn:2000696",
        "tgn:7012149",
        "tgn:7007254",
        "tgn:7029392"
    ],
    "tgn:id":2663220,
    "tgn:name":"Silver Creek",
    "tgn:placetype":[
        "aat:300008706"
    ]
},
  "bbox": [],
  "geometry": {"coordinates":[-96.5333,37.8167],"type":"Point"}
}