<<<<<<< HEAD
{
  "id": 7372294,
  "type": "Feature",
  "properties": {
    "tgn:hierarchy":[
        "tgn:7372294",
        "tgn:1000001",
        "tgn:7005597",
        "tgn:7005560",
        "tgn:7029392"
    ],
    "tgn:id":7372294,
    "tgn:name":"La Noria",
    "tgn:placetype":[
        "aat:300008347"
    ]
},
  "bbox": [],
  "geometry": {"coordinates":[-98.566667,24.5],"type":"Point"}
}
=======
{"geometry":{"type":"Point","coordinates":[-98.566667,24.500000]},"type":"Feature","properties":{"hierarchy":["tgn:7372294","tgn:1000001","tgn:7005597","tgn:7005560","tgn:7029392"],"placetype":["aat:300008347"],"id":7372294,"name:xx":"La Noria"}}
>>>>>>> 03f74aca74312dbeaf24d7e61306dd6a786dc3d0
