{
  "id": 1059825,
  "type": "Feature",
  "properties": {
    "tgn:hierarchy":[
        "tgn:1059825",
        "tgn:1000003",
        "tgn:1003410",
        "tgn:7006660",
        "tgn:7029392"
    ],
    "tgn:id":1059825,
    "tgn:name":"Stepanovka",
    "tgn:placetype":[
        "aat:300008347"
    ]
},
  "bbox": [],
  "geometry": {"coordinates":[34.6167,50.9667],"type":"Point"}
}