{
  "id": 7322696,
  "type": "Feature",
  "properties": {
    "tgn:hierarchy":[
        "tgn:7322696",
        "tgn:7002758",
        "tgn:1001316",
        "tgn:1000003",
        "tgn:1000095",
        "tgn:7029392"
    ],
    "tgn:id":7322696,
    "tgn:name":"Salograr, Arroyo del",
    "tgn:placetype":[
        "aat:300008699"
    ]
},
  "bbox": [],
  "geometry": {"coordinates":[-3.833333,37.416667],"type":"Point"}
}