{
  "id": 7396405,
  "type": "Feature",
  "properties": {
    "tgn:hierarchy":[
        "tgn:7396405",
        "tgn:1000001",
        "tgn:1001906",
        "tgn:7005560",
        "tgn:7029392"
    ],
    "tgn:id":7396405,
    "tgn:name":"San Miguel",
    "tgn:placetype":[
        "aat:300008347"
    ]
},
  "bbox": [],
  "geometry": {"coordinates":[-105.281944,22.335],"type":"Point"}
}