{
  "id": 2289792,
  "type": "Feature",
  "properties": {
    "tgn:hierarchy":[
        "tgn:2289792",
        "tgn:1000001",
        "tgn:7016172",
        "tgn:7012149",
        "tgn:2000167",
        "tgn:7029392"
    ],
    "tgn:id":2289792,
    "tgn:name":"Dobbs Creek",
    "tgn:placetype":[
        "aat:300008706"
    ]
},
  "bbox": [],
  "geometry": {"coordinates":[-92.65,34.55],"type":"Point"}
}