{
  "id": 7228513,
  "type": "Feature",
  "properties": {
    "tgn:hierarchy":[
        "tgn:7228513",
        "tgn:7011270",
        "tgn:7002674",
        "tgn:1000003",
        "tgn:1000074",
        "tgn:7029392"
    ],
    "tgn:id":7228513,
    "tgn:name":"Gl\u00e1ros, Vrachonis\u00edda",
    "tgn:placetype":[
        "aat:300008791"
    ]
},
  "bbox": [],
  "geometry": {"coordinates":[25.605278,36.916944],"type":"Point"}
}