{
  "id": 1121061,
  "type": "Feature",
  "properties": {
    "tgn:hierarchy":[
        "tgn:1121061",
        "tgn:7002659",
        "tgn:1000001",
        "tgn:7012149",
        "tgn:7029392"
    ],
    "tgn:id":1121061,
    "tgn:name":"Alabama",
    "tgn:placetype":[
        "aat:300008707"
    ]
},
  "bbox": [],
  "geometry": {"coordinates":[-86.2667,32.4833],"type":"Point"}
}