{
  "id": 7008625,
  "type": "Feature",
  "properties": {
    "tgn:hierarchy":[
        "tgn:7008625",
        "tgn:7002836",
        "tgn:7016622",
        "tgn:1000003",
        "tgn:1000095",
        "tgn:1009410",
        "tgn:7029392"
    ],
    "tgn:id":7008625,
    "tgn:name":"Santa Cruz de Tenerife",
    "tgn:placetype":[
        "aat:300008347",
        "aat:300387220"
    ]
},
  "bbox": [],
  "geometry": {"coordinates":[-16.233333,28.45],"type":"Point"}
}