{
  "id": 2162924,
  "type": "Feature",
  "properties": {
    "tgn:hierarchy":[
        "tgn:2162924",
        "tgn:1000001",
        "tgn:7012149",
        "tgn:2002023",
        "tgn:7007826",
        "tgn:7029392"
    ],
    "tgn:id":2162924,
    "tgn:name":"Benjamin, Lake",
    "tgn:placetype":[
        "aat:300006191"
    ]
},
  "bbox": [],
  "geometry": {"coordinates":[-99.7833,33.55],"type":"Point"}
}