{
  "id": 7499146,
  "type": "Feature",
  "properties": {
    "tgn:hierarchy":[
        "tgn:7499146",
        "tgn:1000004",
        "tgn:7001009",
        "tgn:1000141",
        "tgn:7029392"
    ],
    "tgn:id":7499146,
    "tgn:name":"Hongxianquankeng Xi",
    "tgn:placetype":[
        "aat:300008699"
    ]
},
  "bbox": [],
  "geometry": {"coordinates":[120.71574,24.01548],"type":"Point"}
}