{
  "id": 7047933,
  "type": "Feature",
  "properties": {
    "tgn:hierarchy":[
        "tgn:7047933",
        "tgn:7003165",
        "tgn:1000003",
        "tgn:7009760",
        "tgn:1000080",
        "tgn:7029392"
    ],
    "tgn:id":7047933,
    "tgn:name":"Fabbrica",
    "tgn:placetype":[
        "aat:300008347"
    ]
},
  "bbox": [],
  "geometry": {"coordinates":[10.316667,44.116667],"type":"Point"}
}