{
  "id": 7159229,
  "type": "Feature",
  "properties": {
    "tgn:hierarchy":[
        "tgn:7159229",
        "tgn:7003669",
        "tgn:1000003",
        "tgn:7000084",
        "tgn:7029392"
    ],
    "tgn:id":7159229,
    "tgn:name":"Hofoldinger Forst",
    "tgn:placetype":[
        "aat:300008863"
    ]
},
  "bbox": [],
  "geometry": {"coordinates":[11.716667,47.95],"type":"Point"}
}