{
  "id": 2469045,
  "type": "Feature",
  "properties": {
    "tgn:hierarchy":[
        "tgn:2469045",
        "tgn:1000001",
        "tgn:7012149",
        "tgn:1002742",
        "tgn:7007920",
        "tgn:7029392"
    ],
    "tgn:id":2469045,
    "tgn:name":"Long Swamp",
    "tgn:placetype":[
        "aat:300008905"
    ]
},
  "bbox": [],
  "geometry": {"coordinates":[-119.9333,48.85],"type":"Point"}
}