{
  "id": 2560253,
  "type": "Feature",
  "properties": {
    "tgn:hierarchy":[
        "tgn:2560253",
        "tgn:1000001",
        "tgn:2001264",
        "tgn:7012149",
        "tgn:7007524",
        "tgn:7029392"
    ],
    "tgn:id":2560253,
    "tgn:name":"Orchard Canal",
    "tgn:placetype":[
        "aat:300006075"
    ]
},
  "bbox": [],
  "geometry": {"coordinates":[-108.8833,45.3333],"type":"Point"}
}