{
  "id": 7500200,
  "type": "Feature",
  "properties": {
    "tgn:hierarchy":[
        "tgn:7500200",
        "tgn:7001004",
        "tgn:1000004",
        "tgn:1000141",
        "tgn:7029392"
    ],
    "tgn:id":7500200,
    "tgn:name":"Gaoxiong Kexue Jishu Xueyuan",
    "tgn:placetype":[
        "aat:300006610"
    ]
},
  "bbox": [],
  "geometry": {"coordinates":[120.328601,22.648506],"type":"Point"}
}