<<<<<<< HEAD
{
  "id": 2769716,
  "type": "Feature",
  "properties": {
    "tgn:hierarchy":[
        "tgn:2769716",
        "tgn:7014201",
        "tgn:1000001",
        "tgn:7012149",
        "tgn:7007239",
        "tgn:7029392"
    ],
    "tgn:id":2769716,
    "tgn:name":"Wiggins Mill",
    "tgn:placetype":[
        "aat:300008347"
    ]
},
  "bbox": [],
  "geometry": {"coordinates":[-75.7,39.4],"type":"Point"}
}
=======
{"geometry":{"type":"Point","coordinates":[-75.700000,39.400000]},"type":"Feature","properties":{"hierarchy":["tgn:2769716","tgn:7014201","tgn:1000001","tgn:7012149","tgn:7007239","tgn:7029392"],"placetype":["aat:300008347"],"id":2769716,"name:xx":"Wiggins Mill"}}
>>>>>>> 03f74aca74312dbeaf24d7e61306dd6a786dc3d0
