{
  "id": 7003135,
  "type": "Feature",
  "properties": {
    "tgn:hierarchy":[
        "tgn:7003135",
        "tgn:1000003",
        "tgn:7003080",
        "tgn:1000080",
        "tgn:7029392"
    ],
    "tgn:id":7003135,
    "tgn:name":"Frosinone",
    "tgn:placetype":[
        "aat:300387145",
        "aat:300000774"
    ]
},
  "bbox": [],
  "geometry": {"coordinates":[13.45,41.616667],"type":"Point"}
}