{
  "id": 2630239,
  "type": "Feature",
  "properties": {
    "tgn:hierarchy":[
        "tgn:2630239",
        "tgn:1000001",
        "tgn:7012149",
        "tgn:7007707",
        "tgn:7029392"
    ],
    "tgn:id":2630239,
    "tgn:name":"Rough Creek",
    "tgn:placetype":[
        "aat:300008706"
    ]
},
  "bbox": [],
  "geometry": {"coordinates":[-98.8667,35.8333],"type":"Point"}
}