{
  "id": 7540474,
  "type": "Feature",
  "properties": {
    "tgn:hierarchy":[
        "tgn:7540474",
        "tgn:7001242",
        "tgn:7016833",
        "tgn:1001114",
        "tgn:7029392"
    ],
    "tgn:id":7540474,
    "tgn:name:en":"Naj' ar Rubay'\u0101t",
    "tgn:placetype":[
        "aat:300008347"
    ]
},
  "bbox": [],
  "geometry": {"coordinates":[30.666667,27.633333],"type":"Point"}
}