{
  "id": 7552077,
  "type": "Feature",
  "properties": {
    "tgn:hierarchy":[
        "tgn:7552077",
        "tgn:1000004",
        "tgn:1001842",
        "tgn:7000198",
        "tgn:7029392"
    ],
    "tgn:id":7552077,
    "tgn:name:en":"Deodha Bhadaur",
    "tgn:placetype":[
        "aat:300008347"
    ]
},
  "bbox": [],
  "geometry": {"coordinates":[86.113109,26.623117],"type":"Point"}
}