{
  "id": 2306117,
  "type": "Feature",
  "properties": {
    "tgn:hierarchy":[
        "tgn:2306117",
        "tgn:1000001",
        "tgn:7012149",
        "tgn:2002387",
        "tgn:7007923",
        "tgn:7029392"
    ],
    "tgn:id":2306117,
    "tgn:name":"East Fork Beaver Creek",
    "tgn:placetype":[
        "aat:300008706"
    ]
},
  "bbox": [],
  "geometry": {"coordinates":[-104.4333,43.95],"type":"Point"}
}