{
  "id": 2263524,
  "type": "Feature",
  "properties": {
    "tgn:hierarchy":[
        "tgn:2263524",
        "tgn:1000001",
        "tgn:7012149",
        "tgn:2002271",
        "tgn:7013961",
        "tgn:7029392"
    ],
    "tgn:id":2263524,
    "tgn:name":"Cox Town",
    "tgn:placetype":[
        "aat:300008347"
    ]
},
  "bbox": [],
  "geometry": {"coordinates":[-80.4667,39.0167],"type":"Point"}
}