{
  "id": 1081283,
  "type": "Feature",
  "properties": {
    "tgn:hierarchy":[
        "tgn:1081283",
        "tgn:1000004",
        "tgn:7000896",
        "tgn:7000277",
        "tgn:1000120",
        "tgn:7029392"
    ],
    "tgn:id":1081283,
    "tgn:name":"Shiga",
    "tgn:placetype":[
        "aat:300008347"
    ]
},
  "bbox": [],
  "geometry": {"coordinates":[135.9167,35.15],"type":"Point"}
}