{
  "id": 2297087,
  "type": "Feature",
  "properties": {
    "tgn:hierarchy":[
        "tgn:2297087",
        "tgn:1000001",
        "tgn:7012149",
        "tgn:2001960",
        "tgn:7007826",
        "tgn:7029392"
    ],
    "tgn:id":2297087,
    "tgn:name":"Dry Creek",
    "tgn:placetype":[
        "aat:300008706"
    ]
},
  "bbox": [],
  "geometry": {"coordinates":[-100.0167,34.95],"type":"Point"}
}