{
  "id": 1048635,
  "type": "Feature",
  "properties": {
    "tgn:hierarchy":[
        "tgn:1048635",
        "tgn:7003646",
        "tgn:1000003",
        "tgn:1000088",
        "tgn:7029392"
    ],
    "tgn:id":1048635,
    "tgn:name":"Leirvik",
    "tgn:placetype":[
        "aat:300008347"
    ]
},
  "bbox": [],
  "geometry": {"coordinates":[5.5167,59.7833],"type":"Point"}
}