{
  "id": 2547292,
  "type": "Feature",
  "properties": {
    "tgn:hierarchy":[
        "tgn:2547292",
        "tgn:1000001",
        "tgn:7012149",
        "tgn:2000232",
        "tgn:7007158",
        "tgn:7029392"
    ],
    "tgn:id":2547292,
    "tgn:name":"North Fork Sand Wash",
    "tgn:placetype":[
        "aat:300008761"
    ]
},
  "bbox": [],
  "geometry": {"coordinates":[-108.55,40.8333],"type":"Point"}
}