{
  "id": 7532423,
  "type": "Feature",
  "properties": {
    "tgn:hierarchy":[
        "tgn:7532423",
        "tgn:7001242",
        "tgn:7016833",
        "tgn:1001091",
        "tgn:7029392"
    ],
    "tgn:id":7532423,
    "tgn:name:en":"Heliopolis Hospital",
    "tgn:placetype":[
        "aat:300006676"
    ]
},
  "bbox": [],
  "geometry": {"coordinates":[31.337283,30.106384],"type":"Point"}
}