<<<<<<< HEAD
{
  "id": 7366082,
  "type": "Feature",
  "properties": {
    "tgn:hierarchy":[
        "tgn:7366082",
        "tgn:1000001",
        "tgn:7005599",
        "tgn:7005560",
        "tgn:7029392"
    ],
    "tgn:id":7366082,
    "tgn:name":"Galleguilla, Arrecife",
    "tgn:placetype":[
        "aat:300008808"
    ]
},
  "bbox": [],
  "geometry": {"coordinates":[-96.116667,19.233333],"type":"Point"}
}
=======
{"geometry":{"type":"Point","coordinates":[-96.116667,19.233333]},"type":"Feature","properties":{"hierarchy":["tgn:7366082","tgn:1000001","tgn:7005599","tgn:7005560","tgn:7029392"],"placetype":["aat:300008808"],"id":7366082,"name:xx":"Galleguilla, Arrecife"}}
>>>>>>> 03f74aca74312dbeaf24d7e61306dd6a786dc3d0
