{
  "id": 2483858,
  "type": "Feature",
  "properties": {
    "tgn:hierarchy":[
        "tgn:2483858",
        "tgn:1000001",
        "tgn:7012149",
        "tgn:7007923",
        "tgn:7029392"
    ],
    "tgn:id":2483858,
    "tgn:name":"Lateral W 135",
    "tgn:placetype":[
        "aat:300006075"
    ]
},
  "bbox": [],
  "geometry": {"coordinates":[-108.55,44.6833],"type":"Point"}
}