{
  "id": 2006727,
  "type": "Feature",
  "properties": {
    "tgn:hierarchy":[
        "tgn:2006727",
        "tgn:1000001",
        "tgn:7006451",
        "tgn:7012149",
        "tgn:2000103",
        "tgn:7029392"
    ],
    "tgn:id":2006727,
    "tgn:name":"Del Rio",
    "tgn:placetype":[
        "aat:300008347",
        "aat:300387210"
    ]
},
  "bbox": [],
  "geometry": {"coordinates":[-112.4333,34.8167],"type":"Point"}
}