{
  "id": 7235930,
  "type": "Feature",
  "properties": {
    "tgn:hierarchy":[
        "tgn:7235930",
        "tgn:7011270",
        "tgn:7002674",
        "tgn:1000003",
        "tgn:1000074",
        "tgn:7029392"
    ],
    "tgn:id":7235930,
    "tgn:name":"\u00c1yios Ye\u00f3ryios",
    "tgn:placetype":[
        "aat:300008347"
    ]
},
  "bbox": [],
  "geometry": {"coordinates":[25.466667,36.866667],"type":"Point"}
}