{
  "id": 7414727,
  "type": "Feature",
  "properties": {
    "tgn:hierarchy":[
        "tgn:7414727",
        "tgn:7005584",
        "tgn:1000001",
        "tgn:7005560",
        "tgn:7029392"
    ],
    "tgn:id":7414727,
    "tgn:name":"Cerro Blanco",
    "tgn:placetype":[
        "aat:300008347"
    ]
},
  "bbox": [],
  "geometry": {"coordinates":[-101.296667,20.302222],"type":"Point"}
}