<<<<<<< HEAD
{
  "id": 2768279,
  "type": "Feature",
  "properties": {
    "tgn:hierarchy":[
        "tgn:2768279",
        "tgn:2002137",
        "tgn:1000001",
        "tgn:7012149",
        "tgn:7007919",
        "tgn:7029392"
    ],
    "tgn:id":2768279,
    "tgn:name":"Whites Pond",
    "tgn:placetype":[
        "aat:300006191"
    ]
},
  "bbox": [],
  "geometry": {"coordinates":[-78.7333,38.05],"type":"Point"}
}
=======
{"geometry":{"type":"Point","coordinates":[-78.733300,38.050000]},"type":"Feature","properties":{"hierarchy":["tgn:2768279","tgn:2002137","tgn:1000001","tgn:7012149","tgn:7007919","tgn:7029392"],"placetype":["aat:300006191"],"id":2768279,"name:xx":"Whites Pond"}}
>>>>>>> 03f74aca74312dbeaf24d7e61306dd6a786dc3d0
