{
  "id": 2768279,
  "type": "Feature",
  "properties": {
    "tgn:hierarchy":[
        "tgn:2768279",
        "tgn:2002137",
        "tgn:1000001",
        "tgn:7012149",
        "tgn:7007919",
        "tgn:7029392"
    ],
    "tgn:id":2768279,
    "tgn:name":"Whites Pond",
    "tgn:placetype":[
        "aat:300006191"
    ]
},
  "bbox": [],
  "geometry": {"coordinates":[-78.7333,38.05],"type":"Point"}
}