{
  "id": 2238472,
  "type": "Feature",
  "properties": {
    "tgn:hierarchy":[
        "tgn:2238472",
        "tgn:1000001",
        "tgn:7012149",
        "tgn:7007240",
        "tgn:7029392"
    ],
    "tgn:id":2238472,
    "tgn:name":"Chokoloskee Bay",
    "tgn:placetype":[
        "aat:300132316"
    ]
},
  "bbox": [],
  "geometry": {"coordinates":[-81.35,25.8167],"type":"Point"}
}