{
  "id": 7363431,
  "type": "Feature",
  "properties": {
    "tgn:hierarchy":[
        "tgn:7363431",
        "tgn:1000001",
        "tgn:1001960",
        "tgn:7005560",
        "tgn:7029392"
    ],
    "tgn:id":7363431,
    "tgn:name":"El \u00c1lamo",
    "tgn:placetype":[
        "aat:300008347"
    ]
},
  "bbox": [],
  "geometry": {"coordinates":[-110.366667,28.666667],"type":"Point"}
}