{
  "id": 7534312,
  "type": "Feature",
  "properties": {
    "tgn:hierarchy":[
        "tgn:7534312",
        "tgn:7001242",
        "tgn:1001059",
        "tgn:7016833",
        "tgn:7029392"
    ],
    "tgn:id":7534312,
    "tgn:name:en":"Ma\u1e29jar Sha\u0163\u0101",
    "tgn:placetype":[
        "aat:300008791"
    ]
},
  "bbox": [],
  "geometry": {"coordinates":[31.875096,31.417254],"type":"Point"}
}