<<<<<<< HEAD
{
  "id": 2250301,
  "type": "Feature",
  "properties": {
    "tgn:hierarchy":[
        "tgn:2250301",
        "tgn:1000001",
        "tgn:7012149",
        "tgn:2000420",
        "tgn:7007248",
        "tgn:7029392"
    ],
    "tgn:id":2250301,
    "tgn:name":"Collins, Lake",
    "tgn:placetype":[
        "aat:300006191"
    ]
},
  "bbox": [],
  "geometry": {"coordinates":[-84.25,32.0833],"type":"Point"}
}
=======
{"geometry":{"type":"Point","coordinates":[-84.250000,32.083300]},"type":"Feature","properties":{"hierarchy":["tgn:2250301","tgn:1000001","tgn:7012149","tgn:2000420","tgn:7007248","tgn:7029392"],"placetype":["aat:300006191"],"id":2250301,"name:xx":"Collins, Lake"}}
>>>>>>> 03f74aca74312dbeaf24d7e61306dd6a786dc3d0
