{
  "id": 2734088,
  "type": "Feature",
  "properties": {
    "tgn:hierarchy":[
        "tgn:2734088",
        "tgn:1000001",
        "tgn:7012149",
        "tgn:2001761",
        "tgn:7007712",
        "tgn:7029392"
    ],
    "tgn:id":2734088,
    "tgn:name":"Turnip Top",
    "tgn:placetype":[
        "aat:300008798"
    ]
},
  "bbox": [],
  "geometry": {"coordinates":[-83.0833,34.8167],"type":"Point"}
}