{
  "id": 2650271,
  "type": "Feature",
  "properties": {
    "tgn:hierarchy":[
        "tgn:2650271",
        "tgn:7030515",
        "tgn:7006450",
        "tgn:1000001",
        "tgn:7012149",
        "tgn:7029392"
    ],
    "tgn:id":2650271,
    "tgn:name":"Sealion Point",
    "tgn:placetype":[
        "aat:300008850"
    ]
},
  "bbox": [],
  "geometry": {"coordinates":[-164.9333,54.5667],"type":"Point"}
}