{
  "id": 7388006,
  "type": "Feature",
  "properties": {
    "tgn:hierarchy":[
        "tgn:7388006",
        "tgn:1000001",
        "tgn:7005599",
        "tgn:7005560",
        "tgn:7029392"
    ],
    "tgn:id":7388006,
    "tgn:name":"Paso de la Palma",
    "tgn:placetype":[
        "aat:300008347"
    ]
},
  "bbox": [],
  "geometry": {"coordinates":[-96.55,19.933333],"type":"Point"}
}