{
  "id": 2612442,
  "type": "Feature",
  "properties": {
    "tgn:hierarchy":[
        "tgn:2612442",
        "tgn:1000001",
        "tgn:7012149",
        "tgn:2002250",
        "tgn:7007920",
        "tgn:7029392"
    ],
    "tgn:id":2612442,
    "tgn:name":"Red Top Mountain",
    "tgn:placetype":[
        "aat:300008798"
    ]
},
  "bbox": [],
  "geometry": {"coordinates":[-117.5333,48.95],"type":"Point"}
}