{
  "id": 7518698,
  "type": "Feature",
  "properties": {
    "tgn:hierarchy":[
        "tgn:7518698",
        "tgn:1009227",
        "tgn:7001866",
        "tgn:1000226",
        "tgn:1000006",
        "tgn:7029392"
    ],
    "tgn:id":7518698,
    "tgn:name:en":"Avoca River",
    "tgn:placetype":[
        "aat:300008699"
    ]
},
  "bbox": [],
  "geometry": {"coordinates":[171.55,-43.183333],"type":"Point"}
}