{
  "id": 7567161,
  "type": "Feature",
  "properties": {
    "tgn:hierarchy":[
        "tgn:7567161",
        "tgn:1000004",
        "tgn:1001871",
        "tgn:7000198",
        "tgn:7029392"
    ],
    "tgn:id":7567161,
    "tgn:name:en":"Dh\u0101ni Faiz\u0101b\u0101d",
    "tgn:placetype":[
        "aat:300008347"
    ]
},
  "bbox": [],
  "geometry": {"coordinates":[76.113889,28.113889],"type":"Point"}
}