{
  "id": 2178782,
  "type": "Feature",
  "properties": {
    "tgn:hierarchy":[
        "tgn:2178782",
        "tgn:1000001",
        "tgn:7012149",
        "tgn:7022208",
        "tgn:7007919",
        "tgn:7029392"
    ],
    "tgn:id":2178782,
    "tgn:name":"Blackwalnut Ridge",
    "tgn:placetype":[
        "aat:300266640"
    ]
},
  "bbox": [],
  "geometry": {"coordinates":[-76.35,37.1333],"type":"Point"}
}