{
  "id": 7073282,
  "type": "Feature",
  "properties": {
    "tgn:hierarchy":[
        "tgn:7073282",
        "tgn:7003692",
        "tgn:1000003",
        "tgn:7000084",
        "tgn:7029392"
    ],
    "tgn:id":7073282,
    "tgn:name":"Teu\u00dferbad",
    "tgn:placetype":[
        "aat:300008347"
    ]
},
  "bbox": [],
  "geometry": {"coordinates":[9.383333,49.083333],"type":"Point"}
}