{
  "id": 2139738,
  "type": "Feature",
  "properties": {
    "tgn:hierarchy":[
        "tgn:2139738",
        "tgn:1000001",
        "tgn:7006451",
        "tgn:7012149",
        "tgn:2000098",
        "tgn:7029392"
    ],
    "tgn:id":2139738,
    "tgn:name":"Atkin-Larson Tank",
    "tgn:placetype":[
        "aat:300006191"
    ]
},
  "bbox": [],
  "geometry": {"coordinates":[-113.4833,36.4667],"type":"Point"}
}