<<<<<<< HEAD
{
  "id": 2337372,
  "type": "Feature",
  "properties": {
    "tgn:hierarchy":[
        "tgn:2337372",
        "tgn:1000001",
        "tgn:7012149",
        "tgn:7019676",
        "tgn:7007566",
        "tgn:7029392"
    ],
    "tgn:id":2337372,
    "tgn:name":"Foutz Number Three Mine",
    "tgn:placetype":[
        "aat:300000390"
    ]
},
  "bbox": [],
  "geometry": {"coordinates":[-108.55,35.5667],"type":"Point"}
}
=======
{"geometry":{"type":"Point","coordinates":[-108.550000,35.566700]},"type":"Feature","properties":{"hierarchy":["tgn:2337372","tgn:1000001","tgn:7012149","tgn:7019676","tgn:7007566","tgn:7029392"],"placetype":["aat:300000390"],"id":2337372,"name:xx":"Foutz Number Three Mine"}}
>>>>>>> 03f74aca74312dbeaf24d7e61306dd6a786dc3d0
