{
  "id": 7202901,
  "type": "Feature",
  "properties": {
    "tgn:hierarchy":[
        "tgn:7202901",
        "tgn:1000003",
        "tgn:7003677",
        "tgn:7000084",
        "tgn:7029392"
    ],
    "tgn:id":7202901,
    "tgn:name":"Brockmann",
    "tgn:placetype":[
        "aat:300000206"
    ]
},
  "bbox": [],
  "geometry": {"coordinates":[7.45,51.983333],"type":"Point"}
}