{
  "id": 7156334,
  "type": "Feature",
  "properties": {
    "tgn:hierarchy":[
        "tgn:7156334",
        "tgn:1000003",
        "tgn:7003688",
        "tgn:7000084",
        "tgn:7029392"
    ],
    "tgn:id":7156334,
    "tgn:name":"Klei",
    "tgn:placetype":[
        "aat:300000206"
    ]
},
  "bbox": [],
  "geometry": {"coordinates":[8.65,54.316667],"type":"Point"}
}