{
  "id": 7154447,
  "type": "Feature",
  "properties": {
    "tgn:hierarchy":[
        "tgn:7154447",
        "tgn:7003692",
        "tgn:1000003",
        "tgn:7000084",
        "tgn:7029392"
    ],
    "tgn:id":7154447,
    "tgn:name":"Jockelehof",
    "tgn:placetype":[
        "aat:300000206"
    ]
},
  "bbox": [],
  "geometry": {"coordinates":[7.983333,47.933333],"type":"Point"}
}