{
  "id": 1078486,
  "type": "Feature",
  "properties": {
    "tgn:hierarchy":[
        "tgn:1078486",
        "tgn:1000004",
        "tgn:1001549",
        "tgn:1000116",
        "tgn:7029392"
    ],
    "tgn:id":1078486,
    "tgn:name":"Sanggona",
    "tgn:placetype":[
        "aat:300008347"
    ]
},
  "bbox": [],
  "geometry": {"coordinates":[121.7667,-3.8667],"type":"Point"}
}