{
  "id": 2552716,
  "type": "Feature",
  "properties": {
    "tgn:hierarchy":[
        "tgn:2552716",
        "tgn:1002648",
        "tgn:1000001",
        "tgn:7019158",
        "tgn:7012149",
        "tgn:7007249",
        "tgn:7029392"
    ],
    "tgn:id":2552716,
    "tgn:name":"Nuu",
    "tgn:placetype":[
        "aat:300008347"
    ]
},
  "bbox": [],
  "geometry": {"coordinates":[-156.1833,20.6167],"type":"Point"}
}