{
  "id": 7519143,
  "type": "Feature",
  "properties": {
    "tgn:hierarchy":[
        "tgn:7519143",
        "tgn:1009227",
        "tgn:1000226",
        "tgn:7016822",
        "tgn:1000006",
        "tgn:7029392"
    ],
    "tgn:id":7519143,
    "tgn:name:en":"Annick Peak",
    "tgn:placetype":[
        "aat:300008798"
    ]
},
  "bbox": [],
  "geometry": {"coordinates":[167.933333,-45.05],"type":"Point"}
}