<<<<<<< HEAD
{
  "id": 2258171,
  "type": "Feature",
  "properties": {
    "tgn:hierarchy":[
        "tgn:2258171",
        "tgn:1000001",
        "tgn:2001092",
        "tgn:7012149",
        "tgn:7007522",
        "tgn:7029392"
    ],
    "tgn:id":2258171,
    "tgn:name":"Costner Lake",
    "tgn:placetype":[
        "aat:300006191"
    ]
},
  "bbox": [],
  "geometry": {"coordinates":[-89.4,34.1],"type":"Point"}
}
=======
{"geometry":{"type":"Point","coordinates":[-89.400000,34.100000]},"type":"Feature","properties":{"hierarchy":["tgn:2258171","tgn:1000001","tgn:2001092","tgn:7012149","tgn:7007522","tgn:7029392"],"placetype":["aat:300006191"],"id":2258171,"name:xx":"Costner Lake"}}
>>>>>>> 03f74aca74312dbeaf24d7e61306dd6a786dc3d0
