{
  "id": 7464832,
  "type": "Feature",
  "properties": {
    "tgn:hierarchy":[
        "tgn:7464832",
        "tgn:7002444",
        "tgn:1000003",
        "tgn:7008082",
        "tgn:7008591",
        "tgn:7029392"
    ],
    "tgn:id":7464832,
    "tgn:name:en":"Achnashellach Station",
    "tgn:placetype":[
        "aat:300007783"
    ]
},
  "bbox": [],
  "geometry": {"coordinates":[-5.333333,57.483333],"type":"Point"}
}