{
  "id": 7475698,
  "type": "Feature",
  "properties": {
    "tgn:hierarchy":[
        "tgn:7475698",
        "tgn:7487020",
        "tgn:1000004",
        "tgn:1000141",
        "tgn:7029392"
    ],
    "tgn:id":7475698,
    "tgn:name":"Xiayuanlin",
    "tgn:placetype":[
        "aat:300008347"
    ]
},
  "bbox": [],
  "geometry": {"coordinates":[120.954529,24.640513],"type":"Point"}
}