<<<<<<< HEAD
{
  "id": 7475698,
  "type": "Feature",
  "properties": {
    "tgn:hierarchy":[
        "tgn:7475698",
        "tgn:7487020",
        "tgn:1000004",
        "tgn:1000141",
        "tgn:7029392"
    ],
    "tgn:id":7475698,
    "tgn:name":"Xiayuanlin",
    "tgn:placetype":[
        "aat:300008347"
    ]
},
  "bbox": [],
  "geometry": {"coordinates":[120.954529,24.640513],"type":"Point"}
}
=======
{"geometry":{"type":"Point","coordinates":[120.954529,24.640513]},"type":"Feature","properties":{"hierarchy":["tgn:7475698","tgn:7487020","tgn:1000004","tgn:1000141","tgn:7029392"],"placetype":["aat:300008347"],"id":7475698,"name:xx":"Xiayuanlin"}}
>>>>>>> 03f74aca74312dbeaf24d7e61306dd6a786dc3d0
