{
  "id": 2572069,
  "type": "Feature",
  "properties": {
    "tgn:hierarchy":[
        "tgn:2572069",
        "tgn:7006450",
        "tgn:1000001",
        "tgn:7012149",
        "tgn:2000089",
        "tgn:7029392"
    ],
    "tgn:id":2572069,
    "tgn:name":"Paystreak Creek",
    "tgn:placetype":[
        "aat:300008706"
    ]
},
  "bbox": [],
  "geometry": {"coordinates":[-148.0667,65.6167],"type":"Point"}
}