<<<<<<< HEAD
{
  "id": 2253870,
  "type": "Feature",
  "properties": {
    "tgn:hierarchy":[
        "tgn:2253870",
        "tgn:1000001",
        "tgn:2000462",
        "tgn:7012149",
        "tgn:7007250",
        "tgn:7029392"
    ],
    "tgn:id":2253870,
    "tgn:name":"Cooks Peak",
    "tgn:placetype":[
        "aat:300008798"
    ]
},
  "bbox": [],
  "geometry": {"coordinates":[-116.55,48.7],"type":"Point"}
}
=======
{"geometry":{"type":"Point","coordinates":[-116.550000,48.700000]},"type":"Feature","properties":{"hierarchy":["tgn:2253870","tgn:1000001","tgn:2000462","tgn:7012149","tgn:7007250","tgn:7029392"],"placetype":["aat:300008798"],"id":2253870,"name:xx":"Cooks Peak"}}
>>>>>>> 03f74aca74312dbeaf24d7e61306dd6a786dc3d0
