{
  "id": 2428700,
  "type": "Feature",
  "properties": {
    "tgn:hierarchy":[
        "tgn:2428700",
        "tgn:2001837",
        "tgn:1000001",
        "tgn:7012149",
        "tgn:7007825",
        "tgn:7029392"
    ],
    "tgn:id":2428700,
    "tgn:name":"Julians Rock",
    "tgn:placetype":[
        "aat:300008798"
    ]
},
  "bbox": [],
  "geometry": {"coordinates":[-84.2667,36.15],"type":"Point"}
}