{
  "id": 1139279,
  "type": "Feature",
  "properties": {
    "tgn:hierarchy":[
        "tgn:1139279",
        "tgn:1000004",
        "tgn:1001390",
        "tgn:1000111",
        "tgn:7029392"
    ],
    "tgn:id":1139279,
    "tgn:name":"Liujiahe",
    "tgn:placetype":[
        "aat:300008347"
    ]
},
  "bbox": [],
  "geometry": {"coordinates":[123.9667,40.6667],"type":"Point"}
}