<<<<<<< HEAD
{
  "id": 7172523,
  "type": "Feature",
  "properties": {
    "tgn:hierarchy":[
        "tgn:7172523",
        "tgn:1000003",
        "tgn:7003676",
        "tgn:7000084",
        "tgn:7029392"
    ],
    "tgn:id":7172523,
    "tgn:name":"Hexen Berge",
    "tgn:placetype":[
        "aat:300008777"
    ]
},
  "bbox": [],
  "geometry": {"coordinates":[7.6,52.65],"type":"Point"}
}
=======
{"geometry":{"type":"Point","coordinates":[7.600000,52.650000]},"type":"Feature","properties":{"hierarchy":["tgn:7172523","tgn:1000003","tgn:7003676","tgn:7000084","tgn:7029392"],"placetype":["aat:300008777"],"id":7172523,"name:xx":"Hexen Berge"}}
>>>>>>> 03f74aca74312dbeaf24d7e61306dd6a786dc3d0
