{
  "id": 2282617,
  "type": "Feature",
  "properties": {
    "tgn:hierarchy":[
        "tgn:2282617",
        "tgn:1000001",
        "tgn:7012149",
        "tgn:2002250",
        "tgn:7007920",
        "tgn:7029392"
    ],
    "tgn:id":2282617,
    "tgn:name":"Deer Trail Mine",
    "tgn:placetype":[
        "aat:300000390"
    ]
},
  "bbox": [],
  "geometry": {"coordinates":[-118.0833,48.0333],"type":"Point"}
}