{
  "id": 7181861,
  "type": "Feature",
  "properties": {
    "tgn:hierarchy":[
        "tgn:7181861",
        "tgn:1000003",
        "tgn:7003678",
        "tgn:7000084",
        "tgn:7029392"
    ],
    "tgn:id":7181861,
    "tgn:name":"Geise Berg",
    "tgn:placetype":[
        "aat:300008777"
    ]
},
  "bbox": [],
  "geometry": {"coordinates":[9.083333,50.616667],"type":"Point"}
}