{
  "id": 2767222,
  "type": "Feature",
  "properties": {
    "tgn:hierarchy":[
        "tgn:2767222",
        "tgn:1000001",
        "tgn:7012149",
        "tgn:2001718",
        "tgn:7007708",
        "tgn:7029392"
    ],
    "tgn:id":2767222,
    "tgn:name":"White Rock Reservoir",
    "tgn:placetype":[
        "aat:300006191"
    ]
},
  "bbox": [],
  "geometry": {"coordinates":[-117.6833,42.9833],"type":"Point"}
}