{
  "id": 7483237,
  "type": "Feature",
  "properties": {
    "tgn:hierarchy":[
        "tgn:7483237",
        "tgn:1000004",
        "tgn:1000454",
        "tgn:1000141",
        "tgn:7029392"
    ],
    "tgn:id":7483237,
    "tgn:name":"Kuolai Yihao Qiao",
    "tgn:placetype":[
        "aat:300007836"
    ]
},
  "bbox": [],
  "geometry": {"coordinates":[121.775278,24.968333],"type":"Point"}
}