{
  "id": 7454225,
  "type": "Feature",
  "properties": {
    "tgn:hierarchy":[
        "tgn:7454225",
        "tgn:7002445",
        "tgn:7019021",
        "tgn:1000003",
        "tgn:7008591",
        "tgn:7029392"
    ],
    "tgn:id":7454225,
    "tgn:name:en":"Chelwood",
    "tgn:placetype":[
        "aat:300008347"
    ]
},
  "bbox": [],
  "geometry": {"coordinates":[-2.527778,51.354167],"type":"Point"}
}