{
  "id": 7543346,
  "type": "Feature",
  "properties": {
    "tgn:hierarchy":[
        "tgn:7543346",
        "tgn:7001242",
        "tgn:7016833",
        "tgn:1001113",
        "tgn:7029392"
    ],
    "tgn:id":7543346,
    "tgn:name":"Kafr an Na\u1e11\u0101r\u00e1",
    "tgn:placetype":[
        "aat:300008347"
    ]
},
  "bbox": [],
  "geometry": {"coordinates":[31.572559,30.757134],"type":"Point"}
}