{
  "id": 7279558,
  "type": "Feature",
  "properties": {
    "tgn:hierarchy":[
        "tgn:7279558",
        "tgn:1001768",
        "tgn:1000049",
        "tgn:1000002",
        "tgn:7029392"
    ],
    "tgn:id":7279558,
    "tgn:name":"Rinc\u00f3n Madre del Agua",
    "tgn:placetype":[
        "aat:300000206"
    ]
},
  "bbox": [],
  "geometry": {"coordinates":[-71.316667,-32.65],"type":"Point"}
}