<<<<<<< HEAD
{
  "id": 2259125,
  "type": "Feature",
  "properties": {
    "tgn:hierarchy":[
        "tgn:2259125",
        "tgn:1000001",
        "tgn:7012149",
        "tgn:7007158",
        "tgn:2000253",
        "tgn:7029392"
    ],
    "tgn:id":2259125,
    "tgn:name":"Cottonwood Extension Ditch",
    "tgn:placetype":[
        "aat:300006075"
    ]
},
  "bbox": [],
  "geometry": {"coordinates":[-105.0333,40.05],"type":"Point"}
}
=======
{"geometry":{"type":"Point","coordinates":[-105.033300,40.050000]},"type":"Feature","properties":{"hierarchy":["tgn:2259125","tgn:1000001","tgn:7012149","tgn:7007158","tgn:2000253","tgn:7029392"],"placetype":["aat:300006075"],"id":2259125,"name:xx":"Cottonwood Extension Ditch"}}
>>>>>>> 03f74aca74312dbeaf24d7e61306dd6a786dc3d0
