{
  "id": 2153961,
  "type": "Feature",
  "properties": {
    "tgn:hierarchy":[
        "tgn:2153961",
        "tgn:7002659",
        "tgn:1000001",
        "tgn:7012149",
        "tgn:2000062",
        "tgn:7029392"
    ],
    "tgn:id":2153961,
    "tgn:name":"Bear Creek",
    "tgn:placetype":[
        "aat:300008706"
    ]
},
  "bbox": [],
  "geometry": {"coordinates":[-87.4833,33.5833],"type":"Point"}
}