{
  "id": 2496223,
  "type": "Feature",
  "properties": {
    "tgn:hierarchy":[
        "tgn:2496223",
        "tgn:1000001",
        "tgn:7012149",
        "tgn:2001821",
        "tgn:7007713",
        "tgn:7029392"
    ],
    "tgn:id":2496223,
    "tgn:name":"Mastiff Mine",
    "tgn:placetype":[
        "aat:300000390"
    ]
},
  "bbox": [],
  "geometry": {"coordinates":[-103.7333,43.9333],"type":"Point"}
}