{
  "id": 7158463,
  "type": "Feature",
  "properties": {
    "tgn:hierarchy":[
        "tgn:7158463",
        "tgn:7003692",
        "tgn:1000003",
        "tgn:7000084",
        "tgn:7029392"
    ],
    "tgn:id":7158463,
    "tgn:name":"Hohenwittlingen",
    "tgn:placetype":[
        "aat:300000206"
    ]
},
  "bbox": [],
  "geometry": {"coordinates":[9.433333,48.466667],"type":"Point"}
}