<<<<<<< HEAD
{
  "id": 7059715,
  "type": "Feature",
  "properties": {
    "tgn:hierarchy":[
        "tgn:7059715",
        "tgn:7003669",
        "tgn:1000003",
        "tgn:7000084",
        "tgn:7029392"
    ],
    "tgn:id":7059715,
    "tgn:name":"Allerfing",
    "tgn:placetype":[
        "aat:300008347"
    ]
},
  "bbox": [],
  "geometry": {"coordinates":[12.8,48.0],"type":"Point"}
}
=======
{"geometry":{"type":"Point","coordinates":[12.800000,48.000000]},"type":"Feature","properties":{"hierarchy":["tgn:7059715","tgn:7003669","tgn:1000003","tgn:7000084","tgn:7029392"],"placetype":["aat:300008347"],"id":7059715,"name:xx":"Allerfing"}}
>>>>>>> 03f74aca74312dbeaf24d7e61306dd6a786dc3d0
