{
  "id": 7564201,
  "type": "Feature",
  "properties": {
    "tgn:hierarchy":[
        "tgn:7564201",
        "tgn:1000004",
        "tgn:7000198",
        "tgn:7016722",
        "tgn:7029392"
    ],
    "tgn:id":7564201,
    "tgn:name:en":"Ban\u012bp\u0101ra Mahar\u0101j",
    "tgn:placetype":[
        "aat:300008347"
    ]
},
  "bbox": [],
  "geometry": {"coordinates":[79.87485,26.539991],"type":"Point"}
}