{
  "id": 7482589,
  "type": "Feature",
  "properties": {
    "tgn:hierarchy":[
        "tgn:7482589",
        "tgn:1000004",
        "tgn:7001014",
        "tgn:1000141",
        "tgn:7029392"
    ],
    "tgn:id":7482589,
    "tgn:name":"Xinwen",
    "tgn:placetype":[
        "aat:300008347"
    ]
},
  "bbox": [],
  "geometry": {"coordinates":[120.195833,23.525833],"type":"Point"}
}