{
  "id": 2407736,
  "type": "Feature",
  "properties": {
    "tgn:hierarchy":[
        "tgn:2407736",
        "tgn:1000001",
        "tgn:7012149",
        "tgn:1002422",
        "tgn:7007251",
        "tgn:7029392"
    ],
    "tgn:id":2407736,
    "tgn:name":"Hurricane",
    "tgn:placetype":[
        "aat:300008347"
    ]
},
  "bbox": [],
  "geometry": {"coordinates":[-90.4833,39.2833],"type":"Point"}
}