{
  "id": 7418888,
  "type": "Feature",
  "properties": {
    "tgn:hierarchy":[
        "tgn:7418888",
        "tgn:7005584",
        "tgn:1000001",
        "tgn:7005560",
        "tgn:7029392"
    ],
    "tgn:id":7418888,
    "tgn:name":"Bego\u00f1a",
    "tgn:placetype":[
        "aat:300008347"
    ]
},
  "bbox": [],
  "geometry": {"coordinates":[-100.383889,21.120833],"type":"Point"}
}