{
  "id": 7039895,
  "type": "Feature",
  "properties": {
    "tgn:hierarchy":[
        "tgn:7039895",
        "tgn:7003137",
        "tgn:1000003",
        "tgn:7003080",
        "tgn:1000080",
        "tgn:7029392"
    ],
    "tgn:id":7039895,
    "tgn:name":"Selci",
    "tgn:placetype":[
        "aat:300008347"
    ]
},
  "bbox": [],
  "geometry": {"coordinates":[12.616667,42.316667],"type":"Point"}
}