{
  "id": 7145281,
  "type": "Feature",
  "properties": {
    "tgn:hierarchy":[
        "tgn:7145281",
        "tgn:1000003",
        "tgn:7003687",
        "tgn:7000084",
        "tgn:7029392"
    ],
    "tgn:id":7145281,
    "tgn:name":"Vorwerk Kolno",
    "tgn:placetype":[
        "aat:300000206"
    ]
},
  "bbox": [],
  "geometry": {"coordinates":[11.85,51.866667],"type":"Point"}
}