<<<<<<< HEAD
{
  "id": 2251025,
  "type": "Feature",
  "properties": {
    "tgn:hierarchy":[
        "tgn:2251025",
        "tgn:2001000",
        "tgn:1000001",
        "tgn:7012149",
        "tgn:7007521",
        "tgn:7029392"
    ],
    "tgn:id":2251025,
    "tgn:name":"Columbus Lake",
    "tgn:placetype":[
        "aat:300008680"
    ]
},
  "bbox": [],
  "geometry": {"coordinates":[-93.05,45.2333],"type":"Point"}
}
=======
{"geometry":{"type":"Point","coordinates":[-93.050000,45.233300]},"type":"Feature","properties":{"hierarchy":["tgn:2251025","tgn:2001000","tgn:1000001","tgn:7012149","tgn:7007521","tgn:7029392"],"placetype":["aat:300008680"],"id":2251025,"name:xx":"Columbus Lake"}}
>>>>>>> 03f74aca74312dbeaf24d7e61306dd6a786dc3d0
