{
  "id": 2170604,
  "type": "Feature",
  "properties": {
    "tgn:hierarchy":[
        "tgn:2170604",
        "tgn:1000001",
        "tgn:7012149",
        "tgn:2002303",
        "tgn:7013961",
        "tgn:7029392"
    ],
    "tgn:id":2170604,
    "tgn:name":"Big Run",
    "tgn:placetype":[
        "aat:300008699"
    ]
},
  "bbox": [],
  "geometry": {"coordinates":[-81.4833,39.3167],"type":"Point"}
}