{
  "id": 2534273,
  "type": "Feature",
  "properties": {
    "tgn:hierarchy":[
        "tgn:2534273",
        "tgn:7019177",
        "tgn:1000001",
        "tgn:7012149",
        "tgn:7007253",
        "tgn:7029392"
    ],
    "tgn:id":2534273,
    "tgn:name":"Mystic Reservoir",
    "tgn:placetype":[
        "aat:300006191"
    ]
},
  "bbox": [],
  "geometry": {"coordinates":[-92.9333,40.7833],"type":"Point"}
}