{
  "id": 2441909,
  "type": "Feature",
  "properties": {
    "tgn:hierarchy":[
        "tgn:2441909",
        "tgn:7006450",
        "tgn:1000001",
        "tgn:7012149",
        "tgn:2124002",
        "tgn:7029392"
    ],
    "tgn:id":2441909,
    "tgn:name":"Kook Lake",
    "tgn:placetype":[
        "aat:300008680"
    ]
},
  "bbox": [],
  "geometry": {"coordinates":[-134.9667,57.65],"type":"Point"}
}