{
  "id": 2353531,
  "type": "Feature",
  "properties": {
    "tgn:hierarchy":[
        "tgn:2353531",
        "tgn:1000001",
        "tgn:7012149",
        "tgn:7007158",
        "tgn:2000250",
        "tgn:7029392"
    ],
    "tgn:id":2353531,
    "tgn:name":"Gold Hill",
    "tgn:placetype":[
        "aat:300008798"
    ]
},
  "bbox": [],
  "geometry": {"coordinates":[-106.0333,39.5333],"type":"Point"}
}