{
  "id": 7453441,
  "type": "Feature",
  "properties": {
    "tgn:hierarchy":[
        "tgn:7453441",
        "tgn:7002444",
        "tgn:1000003",
        "tgn:7019085",
        "tgn:7008591",
        "tgn:7029392"
    ],
    "tgn:id":7453441,
    "tgn:name:en":"Craigneil",
    "tgn:placetype":[
        "aat:300004792"
    ]
},
  "bbox": [],
  "geometry": {"coordinates":[-4.916667,55.133333],"type":"Point"}
}