<<<<<<< HEAD
{
  "id": 2335404,
  "type": "Feature",
  "properties": {
    "tgn:hierarchy":[
        "tgn:2335404",
        "tgn:1000001",
        "tgn:7006451",
        "tgn:7012149",
        "tgn:2000103",
        "tgn:7029392"
    ],
    "tgn:id":2335404,
    "tgn:name":"Fort Misery",
    "tgn:placetype":[
        "aat:300008347"
    ]
},
  "bbox": [],
  "geometry": {"coordinates":[-112.35,34.1333],"type":"Point"}
}
=======
{"geometry":{"type":"Point","coordinates":[-112.350000,34.133300]},"type":"Feature","properties":{"hierarchy":["tgn:2335404","tgn:1000001","tgn:7006451","tgn:7012149","tgn:2000103","tgn:7029392"],"placetype":["aat:300008347"],"id":2335404,"name:xx":"Fort Misery"}}
>>>>>>> 03f74aca74312dbeaf24d7e61306dd6a786dc3d0
