{
  "id": 7545698,
  "type": "Feature",
  "properties": {
    "tgn:hierarchy":[
        "tgn:7545698",
        "tgn:1000004",
        "tgn:7000198",
        "tgn:7016722",
        "tgn:7029392"
    ],
    "tgn:id":7545698,
    "tgn:name:en":"Bh\u012bta",
    "tgn:placetype":[
        "aat:300008347"
    ]
},
  "bbox": [],
  "geometry": {"coordinates":[81.790809,25.309421],"type":"Point"}
}