{
  "id": 2210680,
  "type": "Feature",
  "properties": {
    "tgn:hierarchy":[
        "tgn:2210680",
        "tgn:1000001",
        "tgn:2002109",
        "tgn:7012149",
        "tgn:7007827",
        "tgn:7029392"
    ],
    "tgn:id":2210680,
    "tgn:name":"Butch Cassidy Draw",
    "tgn:placetype":[
        "aat:300008761"
    ]
},
  "bbox": [],
  "geometry": {"coordinates":[-112.2667,37.7667],"type":"Point"}
}