{
  "id": 2707105,
  "type": "Feature",
  "properties": {
    "tgn:hierarchy":[
        "tgn:2707105",
        "tgn:1000001",
        "tgn:7012149",
        "tgn:2000490",
        "tgn:7007250",
        "tgn:7029392"
    ],
    "tgn:id":2707105,
    "tgn:name":"Swede Canyon",
    "tgn:placetype":[
        "aat:300008761"
    ]
},
  "bbox": [],
  "geometry": {"coordinates":[-112.7667,42.6333],"type":"Point"}
}