{
  "id": 7336600,
  "type": "Feature",
  "properties": {
    "tgn:hierarchy":[
        "tgn:7336600",
        "tgn:7001122",
        "tgn:1000003",
        "tgn:7002765",
        "tgn:1000095",
        "tgn:7029392"
    ],
    "tgn:id":7336600,
    "tgn:name":"Eubarca, Cabo",
    "tgn:placetype":[
        "aat:300008850"
    ]
},
  "bbox": [],
  "geometry": {"coordinates":[1.35,39.066667],"type":"Point"}
}