{
  "id": 2557905,
  "type": "Feature",
  "properties": {
    "tgn:hierarchy":[
        "tgn:2557905",
        "tgn:2001771",
        "tgn:1000001",
        "tgn:7012149",
        "tgn:7007713",
        "tgn:7029392"
    ],
    "tgn:id":2557905,
    "tgn:name":"Old Stickney Lake",
    "tgn:placetype":[
        "aat:300006191"
    ]
},
  "bbox": [],
  "geometry": {"coordinates":[-98.3333,43.5833],"type":"Point"}
}