{
  "id": 1011132,
  "type": "Feature",
  "properties": {
    "tgn:hierarchy":[
        "tgn:1011132",
        "tgn:1006711",
        "tgn:7005685",
        "tgn:1000001",
        "tgn:7005802",
        "tgn:7029392"
    ],
    "tgn:id":1011132,
    "tgn:name":"Sable, Cape",
    "tgn:placetype":[
        "aat:300008850"
    ]
},
  "bbox": [],
  "geometry": {"coordinates":[-65.6167,43.3833],"type":"Point"}
}