{
  "id": 2688314,
  "type": "Feature",
  "properties": {
    "tgn:hierarchy":[
        "tgn:2688314",
        "tgn:1000001",
        "tgn:2000469",
        "tgn:7012149",
        "tgn:7007250",
        "tgn:7029392"
    ],
    "tgn:id":2688314,
    "tgn:name":"Spruce Creek",
    "tgn:placetype":[
        "aat:300008706"
    ]
},
  "bbox": [],
  "geometry": {"coordinates":[-115.0333,46.6167],"type":"Point"}
}