{
  "id": 2307881,
  "type": "Feature",
  "properties": {
    "tgn:hierarchy":[
        "tgn:2307881",
        "tgn:7006450",
        "tgn:1000001",
        "tgn:7019698",
        "tgn:7012149",
        "tgn:7029392"
    ],
    "tgn:id":2307881,
    "tgn:name":"East Glacier Creek",
    "tgn:placetype":[
        "aat:300008706"
    ]
},
  "bbox": [],
  "geometry": {"coordinates":[-153.0833,59.95],"type":"Point"}
}