{
  "id": 7079913,
  "type": "Feature",
  "properties": {
    "tgn:hierarchy":[
        "tgn:7079913",
        "tgn:7003669",
        "tgn:1000003",
        "tgn:7000084",
        "tgn:7029392"
    ],
    "tgn:id":7079913,
    "tgn:name":"Wolfetsried",
    "tgn:placetype":[
        "aat:300000206"
    ]
},
  "bbox": [],
  "geometry": {"coordinates":[11.25,47.816667],"type":"Point"}
}