{
  "id": 2436522,
  "type": "Feature",
  "properties": {
    "tgn:hierarchy":[
        "tgn:2436522",
        "tgn:1000001",
        "tgn:7012149",
        "tgn:1002494",
        "tgn:7007710",
        "tgn:7029392"
    ],
    "tgn:id":2436522,
    "tgn:name":"Kidd Cave",
    "tgn:placetype":[
        "aat:300008746"
    ]
},
  "bbox": [],
  "geometry": {"coordinates":[-77.8667,40.4667],"type":"Point"}
}