{
  "id": 2726515,
  "type": "Feature",
  "properties": {
    "tgn:hierarchy":[
        "tgn:2726515",
        "tgn:1000001",
        "tgn:7012149",
        "tgn:2001110",
        "tgn:7007522",
        "tgn:7029392"
    ],
    "tgn:id":2726515,
    "tgn:name":"Town Creek",
    "tgn:placetype":[
        "aat:300008706"
    ]
},
  "bbox": [],
  "geometry": {"coordinates":[-90.2333,32.35],"type":"Point"}
}