{
  "id": 2059167,
  "type": "Feature",
  "properties": {
    "tgn:hierarchy":[
        "tgn:2059167",
        "tgn:1000001",
        "tgn:7012149",
        "tgn:2001231",
        "tgn:7007523",
        "tgn:7029392"
    ],
    "tgn:id":2059167,
    "tgn:name":"Iatan",
    "tgn:placetype":[
        "aat:300008347"
    ]
},
  "bbox": [],
  "geometry": {"coordinates":[-94.9667,39.4667],"type":"Point"}
}