<<<<<<< HEAD
{
  "id": 7471905,
  "type": "Feature",
  "properties": {
    "tgn:hierarchy":[
        "tgn:7471905",
        "tgn:1000004",
        "tgn:7490934",
        "tgn:1000141",
        "tgn:7029392"
    ],
    "tgn:id":7471905,
    "tgn:name":"Wencuobu Xi",
    "tgn:placetype":[
        "aat:300008699"
    ]
},
  "bbox": [],
  "geometry": {"coordinates":[120.266667,23.266667],"type":"Point"}
}
=======
{"geometry":{"type":"Point","coordinates":[120.266667,23.266667]},"type":"Feature","properties":{"hierarchy":["tgn:7471905","tgn:1000004","tgn:7490934","tgn:1000141","tgn:7029392"],"placetype":["aat:300008699"],"id":7471905,"name:xx":"Wencuobu Xi"}}
>>>>>>> 03f74aca74312dbeaf24d7e61306dd6a786dc3d0
