{
  "id": 7580390,
  "type": "Feature",
  "properties": {
    "tgn:hierarchy":[
        "tgn:7580390",
        "tgn:1000004",
        "tgn:1001842",
        "tgn:7000198",
        "tgn:7029392"
    ],
    "tgn:id":7580390,
    "tgn:name:en":"Sukh\u0101nagar",
    "tgn:placetype":[
        "aat:300008347"
    ]
},
  "bbox": [],
  "geometry": {"coordinates":[86.929164,26.290631],"type":"Point"}
}