{
  "id": 7592892,
  "type": "Feature",
  "properties": {
    "tgn:hierarchy":[
        "tgn:7592892",
        "tgn:1000004",
        "tgn:7000198",
        "tgn:7000799",
        "tgn:7029392"
    ],
    "tgn:id":7592892,
    "tgn:name:en":"Panduri",
    "tgn:placetype":[
        "aat:300008347"
    ]
},
  "bbox": [],
  "geometry": {"coordinates":[74.267162,33.042131],"type":"Point"}
}