{
  "id": 1024549,
  "type": "Feature",
  "properties": {
    "tgn:hierarchy":[
        "tgn:1024549",
        "tgn:1000665",
        "tgn:1000002",
        "tgn:1000056",
        "tgn:7029392"
    ],
    "tgn:id":1024549,
    "tgn:name":"Illimo",
    "tgn:placetype":[
        "aat:300008347"
    ]
},
  "bbox": [],
  "geometry": {"coordinates":[-79.85,-6.4667],"type":"Point"}
}