{
  "id": 7271224,
  "type": "Feature",
  "properties": {
    "tgn:hierarchy":[
        "tgn:7271224",
        "tgn:1000003",
        "tgn:7003635",
        "tgn:7016845",
        "tgn:7029392"
    ],
    "tgn:id":7271224,
    "tgn:name:nl":"Stavenissepolder",
    "tgn:placetype":[
        "aat:300006163"
    ]
},
  "bbox": [],
  "geometry": {"coordinates":[4.033333,51.583333],"type":"Point"}
}