{
  "id": 2277750,
  "type": "Feature",
  "properties": {
    "tgn:hierarchy":[
        "tgn:2277750",
        "tgn:1000001",
        "tgn:7012149",
        "tgn:2001503",
        "tgn:7007709",
        "tgn:7029392"
    ],
    "tgn:id":2277750,
    "tgn:name":"Dawn Branch",
    "tgn:placetype":[
        "aat:300008699"
    ]
},
  "bbox": [],
  "geometry": {"coordinates":[-82.95,35.5667],"type":"Point"}
}