{
  "id": 2251506,
  "type": "Feature",
  "properties": {
    "tgn:hierarchy":[
        "tgn:2251506",
        "tgn:1000001",
        "tgn:7012149",
        "tgn:7015666",
        "tgn:7007825",
        "tgn:7029392"
    ],
    "tgn:id":2251506,
    "tgn:name":"Commissary Hollow",
    "tgn:placetype":[
        "aat:300008761"
    ]
},
  "bbox": [],
  "geometry": {"coordinates":[-87.3333,35.8167],"type":"Point"}
}