{
  "id": 7284349,
  "type": "Feature",
  "properties": {
    "tgn:hierarchy":[
        "tgn:7284349",
        "tgn:7016598",
        "tgn:1000049",
        "tgn:1000002",
        "tgn:7029392"
    ],
    "tgn:id":7284349,
    "tgn:name":"Punta Larga",
    "tgn:placetype":[
        "aat:300387033"
    ]
},
  "bbox": [],
  "geometry": {"coordinates":[-69.083333,-23.016667],"type":"Point"}
}