{
  "id": 2137650,
  "type": "Feature",
  "properties": {
    "tgn:hierarchy":[
        "tgn:2137650",
        "tgn:1000001",
        "tgn:7006451",
        "tgn:7012149",
        "tgn:2000103",
        "tgn:7029392"
    ],
    "tgn:id":2137650,
    "tgn:name":"Arnold Place",
    "tgn:placetype":[
        "aat:300008347"
    ]
},
  "bbox": [],
  "geometry": {"coordinates":[-111.9167,34.45],"type":"Point"}
}