{
  "id": 2699713,
  "type": "Feature",
  "properties": {
    "tgn:hierarchy":[
        "tgn:2699713",
        "tgn:1000001",
        "tgn:7012149",
        "tgn:2000476",
        "tgn:7007250",
        "tgn:7029392"
    ],
    "tgn:id":2699713,
    "tgn:name":"Stub Creek",
    "tgn:placetype":[
        "aat:300008706"
    ]
},
  "bbox": [],
  "geometry": {"coordinates":[-115.4667,46.1833],"type":"Point"}
}