{
  "id": 2307384,
  "type": "Feature",
  "properties": {
    "tgn:hierarchy":[
        "tgn:2307384",
        "tgn:2001170",
        "tgn:1000001",
        "tgn:7012149",
        "tgn:7007523",
        "tgn:7029392"
    ],
    "tgn:id":2307384,
    "tgn:name":"East Fork Rock Creek",
    "tgn:placetype":[
        "aat:300008706"
    ]
},
  "bbox": [],
  "geometry": {"coordinates":[-93.6833,36.6667],"type":"Point"}
}