{
  "id": 1118731,
  "type": "Feature",
  "properties": {
    "tgn:hierarchy":[
        "tgn:1118731",
        "tgn:7005694",
        "tgn:7005685",
        "tgn:1000001",
        "tgn:7029392"
    ],
    "tgn:id":1118731,
    "tgn:name":"Winagami Lake",
    "tgn:placetype":[
        "aat:300008680"
    ]
},
  "bbox": [],
  "geometry": {"coordinates":[-116.6667,55.6333],"type":"Point"}
}