{
  "id": 7341581,
  "type": "Feature",
  "properties": {
    "tgn:hierarchy":[
        "tgn:7341581",
        "tgn:7002820",
        "tgn:7030216",
        "tgn:1000003",
        "tgn:1000095",
        "tgn:7029392"
    ],
    "tgn:id":7341581,
    "tgn:name":"Blanca, Isla",
    "tgn:placetype":[
        "aat:300008791"
    ]
},
  "bbox": [],
  "geometry": {"coordinates":[3.218057,41.937973],"type":"Point"}
}