{
  "id": 2254112,
  "type": "Feature",
  "properties": {
    "tgn:hierarchy":[
        "tgn:2254112",
        "tgn:2000106",
        "tgn:1000001",
        "tgn:7016172",
        "tgn:7012149",
        "tgn:7029392"
    ],
    "tgn:id":2254112,
    "tgn:name":"Cooley Lake",
    "tgn:placetype":[
        "aat:300008680"
    ]
},
  "bbox": [],
  "geometry": {"coordinates":[-92.0833,33.0333],"type":"Point"}
}