{
  "id": 2623762,
  "type": "Feature",
  "properties": {
    "tgn:hierarchy":[
        "tgn:2623762",
        "tgn:1000001",
        "tgn:7012149",
        "tgn:2002015",
        "tgn:7007826",
        "tgn:7029392"
    ],
    "tgn:id":2623762,
    "tgn:name":"Rock Creek",
    "tgn:placetype":[
        "aat:300008706"
    ]
},
  "bbox": [],
  "geometry": {"coordinates":[-98.6333,29.8167],"type":"Point"}
}