{
  "id": 7224069,
  "type": "Feature",
  "properties": {
    "tgn:hierarchy":[
        "tgn:7224069",
        "tgn:7002721",
        "tgn:7002715",
        "tgn:1000003",
        "tgn:1000074",
        "tgn:7029392"
    ],
    "tgn:id":7224069,
    "tgn:name":"Pyrosti\u00e1",
    "tgn:placetype":[
        "aat:300008795"
    ]
},
  "bbox": [],
  "geometry": {"coordinates":[21.174722,39.917778],"type":"Point"}
}