{
  "id": 7468599,
  "type": "Feature",
  "properties": {
    "tgn:hierarchy":[
        "tgn:7468599",
        "tgn:1000004",
        "tgn:7492971",
        "tgn:1000141",
        "tgn:7029392"
    ],
    "tgn:id":7468599,
    "tgn:name":"Xinbu",
    "tgn:placetype":[
        "aat:300008347"
    ]
},
  "bbox": [],
  "geometry": {"coordinates":[120.543611,22.441111],"type":"Point"}
}