{
  "id": 2733611,
  "type": "Feature",
  "properties": {
    "tgn:hierarchy":[
        "tgn:2733611",
        "tgn:1000001",
        "tgn:7012149",
        "tgn:2001851",
        "tgn:7007825",
        "tgn:7029392"
    ],
    "tgn:id":2733611,
    "tgn:name":"Turnalay Creek",
    "tgn:placetype":[
        "aat:300008706"
    ]
},
  "bbox": [],
  "geometry": {"coordinates":[-83.0833,35.8167],"type":"Point"}
}