{
  "id": 2104430,
  "type": "Feature",
  "properties": {
    "tgn:hierarchy":[
        "tgn:2104430",
        "tgn:1000001",
        "tgn:7012149",
        "tgn:1002769",
        "tgn:7007826",
        "tgn:7029392"
    ],
    "tgn:id":2104430,
    "tgn:name":"Gary",
    "tgn:placetype":[
        "aat:300008347"
    ]
},
  "bbox": [],
  "geometry": {"coordinates":[-94.3667,32.0167],"type":"Point"}
}