{
  "id": 7114070,
  "type": "Feature",
  "properties": {
    "tgn:hierarchy":[
        "tgn:7114070",
        "tgn:1000003",
        "tgn:7003677",
        "tgn:7000084",
        "tgn:7029392"
    ],
    "tgn:id":7114070,
    "tgn:name":"Rommelsheim",
    "tgn:placetype":[
        "aat:300008347"
    ]
},
  "bbox": [],
  "geometry": {"coordinates":[6.55,50.783333],"type":"Point"}
}