{
  "id": 2548596,
  "type": "Feature",
  "properties": {
    "tgn:hierarchy":[
        "tgn:2548596",
        "tgn:7013388",
        "tgn:1000001",
        "tgn:7012149",
        "tgn:7007517",
        "tgn:7029392"
    ],
    "tgn:id":2548596,
    "tgn:name":"North Mountain",
    "tgn:placetype":[
        "aat:300008798"
    ]
},
  "bbox": [],
  "geometry": {"coordinates":[-73.15,42.5167],"type":"Point"}
}