<<<<<<< HEAD
{
  "id": 7111662,
  "type": "Feature",
  "properties": {
    "tgn:hierarchy":[
        "tgn:7111662",
        "tgn:1000003",
        "tgn:7003676",
        "tgn:7000084",
        "tgn:7029392"
    ],
    "tgn:id":7111662,
    "tgn:name":"Richtmoor",
    "tgn:placetype":[
        "aat:300386886"
    ]
},
  "bbox": [],
  "geometry": {"coordinates":[8.1,52.916667],"type":"Point"}
}
=======
{"geometry":{"type":"Point","coordinates":[8.100000,52.916667]},"type":"Feature","properties":{"hierarchy":["tgn:7111662","tgn:1000003","tgn:7003676","tgn:7000084","tgn:7029392"],"placetype":["aat:300386886"],"id":7111662,"name:xx":"Richtmoor"}}
>>>>>>> 03f74aca74312dbeaf24d7e61306dd6a786dc3d0
