{
  "id": 2378280,
  "type": "Feature",
  "properties": {
    "tgn:hierarchy":[
        "tgn:2378280",
        "tgn:1000001",
        "tgn:7012149",
        "tgn:2001714",
        "tgn:7007708",
        "tgn:7029392"
    ],
    "tgn:id":2378280,
    "tgn:name":"Harris Reservoir",
    "tgn:placetype":[
        "aat:300006191"
    ]
},
  "bbox": [],
  "geometry": {"coordinates":[-121.6333,42.5833],"type":"Point"}
}