{
  "id": 7495005,
  "type": "Feature",
  "properties": {
    "tgn:hierarchy":[
        "tgn:7495005",
        "tgn:7468018",
        "tgn:1000004",
        "tgn:1000141",
        "tgn:7029392"
    ],
    "tgn:id":7495005,
    "tgn:name":"Guoxi",
    "tgn:placetype":[
        "aat:300008347"
    ]
},
  "bbox": [],
  "geometry": {"coordinates":[120.502451,23.603462],"type":"Point"}
}