{
  "id": 1060700,
  "type": "Feature",
  "properties": {
    "tgn:hierarchy":[
        "tgn:1060700",
        "tgn:1003391",
        "tgn:1000003",
        "tgn:7006657",
        "tgn:7029392"
    ],
    "tgn:id":1060700,
    "tgn:name":"Urechye",
    "tgn:placetype":[
        "aat:300008347"
    ]
},
  "bbox": [],
  "geometry": {"coordinates":[27.8333,52.9833],"type":"Point"}
}