<<<<<<< HEAD
{
  "id": 2404284,
  "type": "Feature",
  "properties": {
    "tgn:hierarchy":[
        "tgn:2404284",
        "tgn:1000001",
        "tgn:7012149",
        "tgn:2000933",
        "tgn:7007515",
        "tgn:7029392"
    ],
    "tgn:id":2404284,
    "tgn:name":"Hoyt Neck",
    "tgn:placetype":[
        "aat:300008850"
    ]
},
  "bbox": [],
  "geometry": {"coordinates":[-70.3667,43.4],"type":"Point"}
}
=======
{"geometry":{"type":"Point","coordinates":[-70.366700,43.400000]},"type":"Feature","properties":{"hierarchy":["tgn:2404284","tgn:1000001","tgn:7012149","tgn:2000933","tgn:7007515","tgn:7029392"],"placetype":["aat:300008850"],"id":2404284,"name:xx":"Hoyt Neck"}}
>>>>>>> 03f74aca74312dbeaf24d7e61306dd6a786dc3d0
