{
  "id": 1087397,
  "type": "Feature",
  "properties": {
    "tgn:hierarchy":[
        "tgn:1087397",
        "tgn:7001242",
        "tgn:7016752",
        "tgn:1000779",
        "tgn:7029392"
    ],
    "tgn:id":1087397,
    "tgn:name":"Bou Khadra",
    "tgn:placetype":[
        "aat:300008347"
    ]
},
  "bbox": [],
  "geometry": {"coordinates":[8.05,35.75],"type":"Point"}
}