{
  "id": 2087228,
  "type": "Feature",
  "properties": {
    "tgn:hierarchy":[
        "tgn:2087228",
        "tgn:1000001",
        "tgn:1002233",
        "tgn:7012149",
        "tgn:7007710",
        "tgn:7029392"
    ],
    "tgn:id":2087228,
    "tgn:name":"Christmans",
    "tgn:placetype":[
        "aat:300008347"
    ]
},
  "bbox": [],
  "geometry": {"coordinates":[-75.6333,40.9667],"type":"Point"}
}