{
  "id": 1115341,
  "type": "Feature",
  "properties": {
    "tgn:hierarchy":[
        "tgn:1115341",
        "tgn:1003489",
        "tgn:7004610",
        "tgn:1000003",
        "tgn:1000080",
        "tgn:7029392"
    ],
    "tgn:id":1115341,
    "tgn:name":"Abate Alonia, Lago di",
    "tgn:placetype":[
        "aat:300008680"
    ]
},
  "bbox": [],
  "geometry": {"coordinates":[15.75,41.0167],"type":"Point"}
}