<<<<<<< HEAD
{
  "id": 7366737,
  "type": "Feature",
  "properties": {
    "tgn:hierarchy":[
        "tgn:7366737",
        "tgn:7005583",
        "tgn:1000001",
        "tgn:7005560",
        "tgn:7029392"
    ],
    "tgn:id":7366737,
    "tgn:name":"Espinal, Sierra del",
    "tgn:placetype":[
        "aat:300008795"
    ]
},
  "bbox": [],
  "geometry": {"coordinates":[-106.833333,25.1],"type":"Point"}
}
=======
{"geometry":{"type":"Point","coordinates":[-106.833333,25.100000]},"type":"Feature","properties":{"hierarchy":["tgn:7366737","tgn:7005583","tgn:1000001","tgn:7005560","tgn:7029392"],"placetype":["aat:300008795"],"id":7366737,"name:xx":"Espinal, Sierra del"}}
>>>>>>> 03f74aca74312dbeaf24d7e61306dd6a786dc3d0
