{
  "id": 4012263,
  "type": "Feature",
  "properties": {
    "tgn:hierarchy":[
        "tgn:4012263",
        "tgn:7002445",
        "tgn:1000003",
        "tgn:7008160",
        "tgn:7008591",
        "tgn:7029392"
    ],
    "tgn:id":4012263,
    "tgn:name:en":"Wilby",
    "tgn:placetype":[
        "aat:300008347",
        "aat:300008372"
    ]
},
  "bbox": [],
  "geometry": {"coordinates":[0.983333,52.466667],"type":"Point"}
}