{
  "id": 2607860,
  "type": "Feature",
  "properties": {
    "tgn:hierarchy":[
        "tgn:2607860",
        "tgn:1000001",
        "tgn:1002260",
        "tgn:7012149",
        "tgn:7007920",
        "tgn:7029392"
    ],
    "tgn:id":2607860,
    "tgn:name":"Rat Creek",
    "tgn:placetype":[
        "aat:300008706"
    ]
},
  "bbox": [],
  "geometry": {"coordinates":[-120.7667,47.4833],"type":"Point"}
}