{
  "id": 1011078,
  "type": "Feature",
  "properties": {
    "tgn:hierarchy":[
        "tgn:1011078",
        "tgn:7001242",
        "tgn:1000179",
        "tgn:7593681",
        "tgn:7029392"
    ],
    "tgn:id":1011078,
    "tgn:name":"Quilates, Cap",
    "tgn:placetype":[
        "aat:300008850"
    ]
},
  "bbox": [],
  "geometry": {"coordinates":[-3.65,35.25],"type":"Point"}
}