{
  "id": 2724747,
  "type": "Feature",
  "properties": {
    "tgn:hierarchy":[
        "tgn:2724747",
        "tgn:1000001",
        "tgn:7012149",
        "tgn:1002449",
        "tgn:7013961",
        "tgn:7029392"
    ],
    "tgn:id":2724747,
    "tgn:name":"Tomlinson Run",
    "tgn:placetype":[
        "aat:300008699"
    ]
},
  "bbox": [],
  "geometry": {"coordinates":[-80.5833,40.5333],"type":"Point"}
}