{
  "id": 7434662,
  "type": "Feature",
  "properties": {
    "tgn:hierarchy":[
        "tgn:7434662",
        "tgn:1000001",
        "tgn:7005592",
        "tgn:7005560",
        "tgn:7029392"
    ],
    "tgn:id":7434662,
    "tgn:name":"Zonquimixtla",
    "tgn:placetype":[
        "aat:300008347"
    ]
},
  "bbox": [],
  "geometry": {"coordinates":[-97.266667,20.083333],"type":"Point"}
}