<<<<<<< HEAD
{
  "id": 7363935,
  "type": "Feature",
  "properties": {
    "tgn:hierarchy":[
        "tgn:7363935",
        "tgn:7005579",
        "tgn:1000001",
        "tgn:7005560",
        "tgn:7029392"
    ],
    "tgn:id":7363935,
    "tgn:name":"El Chiquihuite",
    "tgn:placetype":[
        "aat:300008347"
    ]
},
  "bbox": [],
  "geometry": {"coordinates":[-102.133333,22.133333],"type":"Point"}
}
=======
{"geometry":{"type":"Point","coordinates":[-102.133333,22.133333]},"type":"Feature","properties":{"hierarchy":["tgn:7363935","tgn:7005579","tgn:1000001","tgn:7005560","tgn:7029392"],"placetype":["aat:300008347"],"id":7363935,"name:xx":"El Chiquihuite"}}
>>>>>>> 03f74aca74312dbeaf24d7e61306dd6a786dc3d0
