{
  "id": 1055460,
  "type": "Feature",
  "properties": {
    "tgn:hierarchy":[
        "tgn:1055460",
        "tgn:4000818",
        "tgn:1000004",
        "tgn:7018214",
        "tgn:7002435",
        "tgn:7029392"
    ],
    "tgn:id":1055460,
    "tgn:name":"Kodino",
    "tgn:placetype":[
        "aat:300008347"
    ]
},
  "bbox": [],
  "geometry": {"coordinates":[39.9333,63.7167],"type":"Point"}
}