{
  "id": 7414259,
  "type": "Feature",
  "properties": {
    "tgn:hierarchy":[
        "tgn:7414259",
        "tgn:7005587",
        "tgn:1000001",
        "tgn:7005560",
        "tgn:7029392"
    ],
    "tgn:id":7414259,
    "tgn:name:es":"Las Pilas",
    "tgn:placetype":[
        "aat:300008347"
    ]
},
  "bbox": [],
  "geometry": {"coordinates":[-99.130556,20.673611],"type":"Point"}
}