{
  "id": 2645844,
  "type": "Feature",
  "properties": {
    "tgn:hierarchy":[
        "tgn:2645844",
        "tgn:1000001",
        "tgn:7012149",
        "tgn:2001913",
        "tgn:7007825",
        "tgn:7029392"
    ],
    "tgn:id":2645844,
    "tgn:name":"Sawmill Creek",
    "tgn:placetype":[
        "aat:300008706"
    ]
},
  "bbox": [],
  "geometry": {"coordinates":[-85.3167,35.35],"type":"Point"}
}