{
  "id": 7503752,
  "type": "Feature",
  "properties": {
    "tgn:hierarchy":[
        "tgn:7503752",
        "tgn:1000004",
        "tgn:7492971",
        "tgn:1000141",
        "tgn:7029392"
    ],
    "tgn:id":7503752,
    "tgn:name":"Jiuru Tifang",
    "tgn:placetype":[
        "aat:300006156"
    ]
},
  "bbox": [],
  "geometry": {"coordinates":[120.468889,22.7575],"type":"Point"}
}