{
  "id": 2372940,
  "type": "Feature",
  "properties": {
    "tgn:hierarchy":[
        "tgn:2372940",
        "tgn:1000001",
        "tgn:2000459",
        "tgn:7012149",
        "tgn:7007250",
        "tgn:7029392"
    ],
    "tgn:id":2372940,
    "tgn:name":"Halley Placer Mine",
    "tgn:placetype":[
        "aat:300000390"
    ]
},
  "bbox": [],
  "geometry": {"coordinates":[-115.9333,43.9333],"type":"Point"}
}