<<<<<<< HEAD
{
  "id": 7484385,
  "type": "Feature",
  "properties": {
    "tgn:hierarchy":[
        "tgn:7484385",
        "tgn:1000004",
        "tgn:7492971",
        "tgn:1000141",
        "tgn:7029392"
    ],
    "tgn:id":7484385,
    "tgn:name":"Fangshan Wuhao Suidao",
    "tgn:placetype":[
        "aat:300007899"
    ]
},
  "bbox": [],
  "geometry": {"coordinates":[120.692778,22.283333],"type":"Point"}
}
=======
{"geometry":{"type":"Point","coordinates":[120.692778,22.283333]},"type":"Feature","properties":{"hierarchy":["tgn:7484385","tgn:1000004","tgn:7492971","tgn:1000141","tgn:7029392"],"placetype":["aat:300007899"],"id":7484385,"name:xx":"Fangshan Wuhao Suidao"}}
>>>>>>> 03f74aca74312dbeaf24d7e61306dd6a786dc3d0
