{
  "id": 2034402,
  "type": "Feature",
  "properties": {
    "tgn:hierarchy":[
        "tgn:2034402",
        "tgn:1000001",
        "tgn:7012149",
        "tgn:2000652",
        "tgn:7007253",
        "tgn:7029392"
    ],
    "tgn:id":2034402,
    "tgn:name":"Brighton",
    "tgn:placetype":[
        "aat:300008347"
    ]
},
  "bbox": [],
  "geometry": {"coordinates":[-91.8167,41.1667],"type":"Point"}
}