{
  "id": 2136650,
  "type": "Feature",
  "properties": {
    "tgn:hierarchy":[
        "tgn:2136650",
        "tgn:1000001",
        "tgn:7012149",
        "tgn:1002570",
        "tgn:7007706",
        "tgn:7029392"
    ],
    "tgn:id":2136650,
    "tgn:name":"Arcola Creek",
    "tgn:placetype":[
        "aat:300008706"
    ]
},
  "bbox": [],
  "geometry": {"coordinates":[-81.1167,41.7833],"type":"Point"}
}