{
  "id": 7277561,
  "type": "Feature",
  "properties": {
    "tgn:hierarchy":[
        "tgn:7277561",
        "tgn:1001637",
        "tgn:1000049",
        "tgn:1000002",
        "tgn:7029392"
    ],
    "tgn:id":7277561,
    "tgn:name":"El Alamo",
    "tgn:placetype":[
        "aat:300008347"
    ]
},
  "bbox": [],
  "geometry": {"coordinates":[-73.102778,-36.683333],"type":"Point"}
}