{
  "id": 7544839,
  "type": "Feature",
  "properties": {
    "tgn:hierarchy":[
        "tgn:7544839",
        "tgn:1000004",
        "tgn:1001842",
        "tgn:7000198",
        "tgn:7029392"
    ],
    "tgn:id":7544839,
    "tgn:name:en":"Bhapti\u0101hi",
    "tgn:placetype":[
        "aat:300008347"
    ]
},
  "bbox": [],
  "geometry": {"coordinates":[86.737154,26.31847],"type":"Point"}
}