<<<<<<< HEAD
{
  "id": 2766702,
  "type": "Feature",
  "properties": {
    "tgn:hierarchy":[
        "tgn:2766702",
        "tgn:1000001",
        "tgn:7012149",
        "tgn:2001531",
        "tgn:7007709",
        "tgn:7029392"
    ],
    "tgn:id":2766702,
    "tgn:name":"White Oak Mountain",
    "tgn:placetype":[
        "aat:300008798"
    ]
},
  "bbox": [],
  "geometry": {"coordinates":[-82.2,35.2667],"type":"Point"}
}
=======
{"geometry":{"type":"Point","coordinates":[-82.200000,35.266700]},"type":"Feature","properties":{"hierarchy":["tgn:2766702","tgn:1000001","tgn:7012149","tgn:2001531","tgn:7007709","tgn:7029392"],"placetype":["aat:300008798"],"id":2766702,"name:xx":"White Oak Mountain"}}
>>>>>>> 03f74aca74312dbeaf24d7e61306dd6a786dc3d0
