{
  "id": 7349666,
  "type": "Feature",
  "properties": {
    "tgn:hierarchy":[
        "tgn:7349666",
        "tgn:1000001",
        "tgn:7005600",
        "tgn:7005560",
        "tgn:7029392"
    ],
    "tgn:id":7349666,
    "tgn:name":"Acanc\u00fan",
    "tgn:placetype":[
        "aat:300008347"
    ]
},
  "bbox": [],
  "geometry": {"coordinates":[-88.283333,21.233333],"type":"Point"}
}