{
  "id": 2605895,
  "type": "Feature",
  "properties": {
    "tgn:hierarchy":[
        "tgn:2605895",
        "tgn:1000001",
        "tgn:2001260",
        "tgn:7012149",
        "tgn:7007524",
        "tgn:7029392"
    ],
    "tgn:id":2605895,
    "tgn:name":"Rainbow Lake",
    "tgn:placetype":[
        "aat:300008680"
    ]
},
  "bbox": [],
  "geometry": {"coordinates":[-112.8667,45.5167],"type":"Point"}
}