{
  "id": 7055728,
  "type": "Feature",
  "properties": {
    "tgn:hierarchy":[
        "tgn:7055728",
        "tgn:7003008",
        "tgn:1000003",
        "tgn:7002997",
        "tgn:1000080",
        "tgn:7029392"
    ],
    "tgn:id":7055728,
    "tgn:name":"Lev\u00e0",
    "tgn:placetype":[
        "aat:300008347"
    ]
},
  "bbox": [],
  "geometry": {"coordinates":[11.533333,45.65],"type":"Point"}
}