{
  "id": 1116434,
  "type": "Feature",
  "properties": {
    "tgn:hierarchy":[
        "tgn:1116434",
        "tgn:7005685",
        "tgn:1000001",
        "tgn:7013154",
        "tgn:7029392"
    ],
    "tgn:id":1116434,
    "tgn:name":"Goose Lake",
    "tgn:placetype":[
        "aat:300008680"
    ]
},
  "bbox": [],
  "geometry": {"coordinates":[-82.5167,42.5167],"type":"Point"}
}