<<<<<<< HEAD
{
  "id": 7178689,
  "type": "Feature",
  "properties": {
    "tgn:hierarchy":[
        "tgn:7178689",
        "tgn:7003692",
        "tgn:1000003",
        "tgn:7000084",
        "tgn:7029392"
    ],
    "tgn:id":7178689,
    "tgn:name":"Hammerstadt",
    "tgn:placetype":[
        "aat:300008347"
    ]
},
  "bbox": [],
  "geometry": {"coordinates":[10.05,48.85],"type":"Point"}
}
=======
{"geometry":{"type":"Point","coordinates":[10.050000,48.850000]},"type":"Feature","properties":{"hierarchy":["tgn:7178689","tgn:7003692","tgn:1000003","tgn:7000084","tgn:7029392"],"placetype":["aat:300008347"],"id":7178689,"name:xx":"Hammerstadt"}}
>>>>>>> 03f74aca74312dbeaf24d7e61306dd6a786dc3d0
