<<<<<<< HEAD
{
  "id": 2254813,
  "type": "Feature",
  "properties": {
    "tgn:hierarchy":[
        "tgn:2254813",
        "tgn:1000001",
        "tgn:7012149",
        "tgn:2000238",
        "tgn:7007158",
        "tgn:7029392"
    ],
    "tgn:id":2254813,
    "tgn:name":"Cooney Lake",
    "tgn:placetype":[
        "aat:300008680"
    ]
},
  "bbox": [],
  "geometry": {"coordinates":[-106.1667,39.3],"type":"Point"}
}
=======
{"geometry":{"type":"Point","coordinates":[-106.166700,39.300000]},"type":"Feature","properties":{"hierarchy":["tgn:2254813","tgn:1000001","tgn:7012149","tgn:2000238","tgn:7007158","tgn:7029392"],"placetype":["aat:300008680"],"id":2254813,"name:xx":"Cooney Lake"}}
>>>>>>> 03f74aca74312dbeaf24d7e61306dd6a786dc3d0
