{
  "id": 2504121,
  "type": "Feature",
  "properties": {
    "tgn:hierarchy":[
        "tgn:2504121",
        "tgn:1000001",
        "tgn:7012149",
        "tgn:2001279",
        "tgn:7007524",
        "tgn:7029392"
    ],
    "tgn:id":2504121,
    "tgn:name":"Meadow Lakes",
    "tgn:placetype":[
        "aat:300008680"
    ]
},
  "bbox": [],
  "geometry": {"coordinates":[-113.0667,46.2833],"type":"Point"}
}