{
  "id": 7579616,
  "type": "Feature",
  "properties": {
    "tgn:hierarchy":[
        "tgn:7579616",
        "tgn:1000004",
        "tgn:7000198",
        "tgn:1001894",
        "tgn:7029392"
    ],
    "tgn:id":7579616,
    "tgn:name:en":"Sondwa",
    "tgn:placetype":[
        "aat:300008347"
    ]
},
  "bbox": [],
  "geometry": {"coordinates":[74.374145,22.115842],"type":"Point"}
}