{
  "id": 2778451,
  "type": "Feature",
  "properties": {
    "tgn:hierarchy":[
        "tgn:2778451",
        "tgn:1000001",
        "tgn:7012149",
        "tgn:2001456",
        "tgn:7007566",
        "tgn:7029392"
    ],
    "tgn:id":2778451,
    "tgn:name":"Withers Tank",
    "tgn:placetype":[
        "aat:300006191"
    ]
},
  "bbox": [],
  "geometry": {"coordinates":[-106.25,33.7167],"type":"Point"}
}