{
  "id": 7280832,
  "type": "Feature",
  "properties": {
    "tgn:hierarchy":[
        "tgn:7280832",
        "tgn:1001692",
        "tgn:1000049",
        "tgn:1000002",
        "tgn:7029392"
    ],
    "tgn:id":7280832,
    "tgn:name":"Santa Mar\u00eda",
    "tgn:placetype":[
        "aat:300000206"
    ]
},
  "bbox": [],
  "geometry": {"coordinates":[-72.25,-38.066667],"type":"Point"}
}