<<<<<<< HEAD
{
  "id": 2700280,
  "type": "Feature",
  "properties": {
    "tgn:hierarchy":[
        "tgn:2700280",
        "tgn:1000001",
        "tgn:7012149",
        "tgn:7007708",
        "tgn:7029392"
    ],
    "tgn:id":2700280,
    "tgn:name":"Sturgis Fork",
    "tgn:placetype":[
        "aat:300008699"
    ]
},
  "bbox": [],
  "geometry": {"coordinates":[-123.35,42.0833],"type":"Point"}
}
=======
{"geometry":{"type":"Point","coordinates":[-123.350000,42.083300]},"type":"Feature","properties":{"hierarchy":["tgn:2700280","tgn:1000001","tgn:7012149","tgn:7007708","tgn:7029392"],"placetype":["aat:300008699"],"id":2700280,"name:xx":"Sturgis Fork"}}
>>>>>>> 03f74aca74312dbeaf24d7e61306dd6a786dc3d0
