{
  "id": 7433602,
  "type": "Feature",
  "properties": {
    "tgn:hierarchy":[
        "tgn:7433602",
        "tgn:1000001",
        "tgn:1001960",
        "tgn:7005560",
        "tgn:7029392"
    ],
    "tgn:id":7433602,
    "tgn:name":"Yavaros, Punta de",
    "tgn:placetype":[
        "aat:300386846"
    ]
},
  "bbox": [],
  "geometry": {"coordinates":[-109.483333,26.683333],"type":"Point"}
}