{
  "id": 1018386,
  "type": "Feature",
  "properties": {
    "tgn:hierarchy":[
        "tgn:1018386",
        "tgn:1000001",
        "tgn:7005594",
        "tgn:7005560",
        "tgn:7029392"
    ],
    "tgn:id":1018386,
    "tgn:name":"Tanque de Dolores",
    "tgn:placetype":[
        "aat:300008347"
    ]
},
  "bbox": [],
  "geometry": {"coordinates":[-101.166667,23.666667],"type":"Point"}
}