{
  "id": 7148208,
  "type": "Feature",
  "properties": {
    "tgn:hierarchy":[
        "tgn:7148208",
        "tgn:1000003",
        "tgn:7003682",
        "tgn:7000084",
        "tgn:7029392"
    ],
    "tgn:id":7148208,
    "tgn:name":"Krumscheid",
    "tgn:placetype":[
        "aat:300008347"
    ]
},
  "bbox": [],
  "geometry": {"coordinates":[7.466667,50.666667],"type":"Point"}
}