{
  "id": 2108812,
  "type": "Feature",
  "properties": {
    "tgn:hierarchy":[
        "tgn:2108812",
        "tgn:1000001",
        "tgn:7012149",
        "tgn:2002114",
        "tgn:7007827",
        "tgn:7029392"
    ],
    "tgn:id":2108812,
    "tgn:name":"Delta",
    "tgn:placetype":[
        "aat:300008347"
    ]
},
  "bbox": [],
  "geometry": {"coordinates":[-112.5667,39.35],"type":"Point"}
}