{
  "id": 1084224,
  "type": "Feature",
  "properties": {
    "tgn:hierarchy":[
        "tgn:1084224",
        "tgn:1000004",
        "tgn:1001231",
        "tgn:1000135",
        "tgn:7029392"
    ],
    "tgn:id":1084224,
    "tgn:name":"Giporlos",
    "tgn:placetype":[
        "aat:300008347"
    ]
},
  "bbox": [],
  "geometry": {"coordinates":[125.45,11.1167],"type":"Point"}
}