{
  "id": 7443275,
  "type": "Feature",
  "properties": {
    "tgn:hierarchy":[
        "tgn:7443275",
        "tgn:7002445",
        "tgn:1000003",
        "tgn:7019066",
        "tgn:7008591",
        "tgn:7029392"
    ],
    "tgn:id":7443275,
    "tgn:name:en":"Teesside County Borough",
    "tgn:placetype":[
        "aat:300000745"
    ]
},
  "bbox": [],
  "geometry": {"coordinates":[-1.233333,54.566667],"type":"Point"}
}