<<<<<<< HEAD
{
  "id": 2401602,
  "type": "Feature",
  "properties": {
    "tgn:hierarchy":[
        "tgn:2401602",
        "tgn:7006450",
        "tgn:1000001",
        "tgn:7012149",
        "tgn:2000088",
        "tgn:7029392"
    ],
    "tgn:id":2401602,
    "tgn:name":"Horseshoe Island",
    "tgn:placetype":[
        "aat:300008791"
    ]
},
  "bbox": [],
  "geometry": {"coordinates":[-133.7167,56.7833],"type":"Point"}
}
=======
{"geometry":{"type":"Point","coordinates":[-133.716700,56.783300]},"type":"Feature","properties":{"hierarchy":["tgn:2401602","tgn:7006450","tgn:1000001","tgn:7012149","tgn:2000088","tgn:7029392"],"placetype":["aat:300008791"],"id":2401602,"name:xx":"Horseshoe Island"}}
>>>>>>> 03f74aca74312dbeaf24d7e61306dd6a786dc3d0
