{
  "id": 7463490,
  "type": "Feature",
  "properties": {
    "tgn:hierarchy":[
        "tgn:7463490",
        "tgn:7002444",
        "tgn:1000003",
        "tgn:7008082",
        "tgn:7008591",
        "tgn:7029392"
    ],
    "tgn:id":7463490,
    "tgn:name:en":"Lentran Point",
    "tgn:placetype":[
        "aat:300386846"
    ]
},
  "bbox": [],
  "geometry": {"coordinates":[-4.366667,57.483333],"type":"Point"}
}