{
  "id": 7197309,
  "type": "Feature",
  "properties": {
    "tgn:hierarchy":[
        "tgn:7197309",
        "tgn:1000003",
        "tgn:7000094",
        "tgn:7000084",
        "tgn:7029392"
    ],
    "tgn:id":7197309,
    "tgn:name":"D\u00e4nscheburg",
    "tgn:placetype":[
        "aat:300008347"
    ]
},
  "bbox": [],
  "geometry": {"coordinates":[12.416667,54.133333],"type":"Point"}
}