{
  "id": 7241942,
  "type": "Feature",
  "properties": {
    "tgn:hierarchy":[
        "tgn:7241942",
        "tgn:7018238",
        "tgn:1000003",
        "tgn:1000063",
        "tgn:4012014",
        "tgn:7029392"
    ],
    "tgn:id":7241942,
    "tgn:name":"Linsmeau",
    "tgn:placetype":[
        "aat:300008347"
    ]
},
  "bbox": [],
  "geometry": {"coordinates":[4.999772,50.735615],"type":"Point"}
}