{
  "id": 7069821,
  "type": "Feature",
  "properties": {
    "tgn:hierarchy":[
        "tgn:7069821",
        "tgn:1000003",
        "tgn:7000094",
        "tgn:7000084",
        "tgn:7029392"
    ],
    "tgn:id":7069821,
    "tgn:name":"Todenhagener Holz",
    "tgn:placetype":[
        "aat:300008863"
    ]
},
  "bbox": [],
  "geometry": {"coordinates":[12.633333,54.216667],"type":"Point"}
}