{
  "id": 2661419,
  "type": "Feature",
  "properties": {
    "tgn:hierarchy":[
        "tgn:2661419",
        "tgn:1000001",
        "tgn:7012149",
        "tgn:7007157",
        "tgn:1002956",
        "tgn:7029392"
    ],
    "tgn:id":2661419,
    "tgn:name":"Shotgun Creek",
    "tgn:placetype":[
        "aat:300008706"
    ]
},
  "bbox": [],
  "geometry": {"coordinates":[-118.5333,36.3833],"type":"Point"}
}