{
  "id": 7587854,
  "type": "Feature",
  "properties": {
    "tgn:hierarchy":[
        "tgn:7587854",
        "tgn:1000004",
        "tgn:7000198",
        "tgn:7000799",
        "tgn:7029392"
    ],
    "tgn:id":7587854,
    "tgn:name:en":"Thirdu",
    "tgn:placetype":[
        "aat:300008347"
    ]
},
  "bbox": [],
  "geometry": {"coordinates":[75.522162,32.867591],"type":"Point"}
}