{
  "id": 2307050,
  "type": "Feature",
  "properties": {
    "tgn:hierarchy":[
        "tgn:2307050",
        "tgn:1000001",
        "tgn:7012149",
        "tgn:7007157",
        "tgn:1002867",
        "tgn:7029392"
    ],
    "tgn:id":2307050,
    "tgn:name":"East Fork Maria Ygnacio Creek",
    "tgn:placetype":[
        "aat:300008706"
    ]
},
  "bbox": [],
  "geometry": {"coordinates":[-119.7667,34.4667],"type":"Point"}
}