{
  "id": 2122841,
  "type": "Feature",
  "properties": {
    "tgn:hierarchy":[
        "tgn:2122841",
        "tgn:1000001",
        "tgn:2002369",
        "tgn:7012149",
        "tgn:7007923",
        "tgn:7029392"
    ],
    "tgn:id":2122841,
    "tgn:name":"Carey",
    "tgn:placetype":[
        "aat:300387016"
    ]
},
  "bbox": [],
  "geometry": {"coordinates":[-105.6667,42.85],"type":"Point"}
}