{
  "id": 2563283,
  "type": "Feature",
  "properties": {
    "tgn:hierarchy":[
        "tgn:2563283",
        "tgn:1000001",
        "tgn:7012149",
        "tgn:7007158",
        "tgn:2000253",
        "tgn:7029392"
    ],
    "tgn:id":2563283,
    "tgn:name":"Owl Creek",
    "tgn:placetype":[
        "aat:300008706"
    ]
},
  "bbox": [],
  "geometry": {"coordinates":[-104.7833,40.9833],"type":"Point"}
}