{
  "id": 2394057,
  "type": "Feature",
  "properties": {
    "tgn:hierarchy":[
        "tgn:2394057",
        "tgn:1000001",
        "tgn:2001411",
        "tgn:7012149",
        "tgn:7007526",
        "tgn:7029392"
    ],
    "tgn:id":2394057,
    "tgn:name":"Hog Tommy Hill",
    "tgn:placetype":[
        "aat:300008798"
    ]
},
  "bbox": [],
  "geometry": {"coordinates":[-115.55,40.75],"type":"Point"}
}