{
  "id": 7222929,
  "type": "Feature",
  "properties": {
    "tgn:hierarchy":[
        "tgn:7222929",
        "tgn:7011170",
        "tgn:7002715",
        "tgn:1000003",
        "tgn:1000074",
        "tgn:7029392"
    ],
    "tgn:id":7222929,
    "tgn:name":"Sidhin\u00ed",
    "tgn:placetype":[
        "aat:300008347"
    ]
},
  "bbox": [],
  "geometry": {"coordinates":[25.016667,41.083333],"type":"Point"}
}