{
  "id": 2599436,
  "type": "Feature",
  "properties": {
    "tgn:hierarchy":[
        "tgn:2599436",
        "tgn:1000001",
        "tgn:7012149",
        "tgn:2000965",
        "tgn:7007520",
        "tgn:7029392"
    ],
    "tgn:id":2599436,
    "tgn:name":"Proper Creek",
    "tgn:placetype":[
        "aat:300008706"
    ]
},
  "bbox": [],
  "geometry": {"coordinates":[-83.6333,44.2333],"type":"Point"}
}