{
  "id": 2546911,
  "type": "Feature",
  "properties": {
    "tgn:hierarchy":[
        "tgn:2546911",
        "tgn:1000001",
        "tgn:7012149",
        "tgn:2002384",
        "tgn:7007923",
        "tgn:7029392"
    ],
    "tgn:id":2546911,
    "tgn:name":"North Fork North Boone Creek",
    "tgn:placetype":[
        "aat:300008706"
    ]
},
  "bbox": [],
  "geometry": {"coordinates":[-110.85,44.0833],"type":"Point"}
}