<<<<<<< HEAD
{
  "id": 2409538,
  "type": "Feature",
  "properties": {
    "tgn:hierarchy":[
        "tgn:2409538",
        "tgn:1000001",
        "tgn:7012149",
        "tgn:2001883",
        "tgn:7007825",
        "tgn:7029392"
    ],
    "tgn:id":2409538,
    "tgn:name":"Idlewood Acres",
    "tgn:placetype":[
        "aat:300008347"
    ]
},
  "bbox": [],
  "geometry": {"coordinates":[-84.0,36.0167],"type":"Point"}
}
=======
{"geometry":{"type":"Point","coordinates":[-84.000000,36.016700]},"type":"Feature","properties":{"hierarchy":["tgn:2409538","tgn:1000001","tgn:7012149","tgn:2001883","tgn:7007825","tgn:7029392"],"placetype":["aat:300008347"],"id":2409538,"name:xx":"Idlewood Acres"}}
>>>>>>> 03f74aca74312dbeaf24d7e61306dd6a786dc3d0
