{
  "id": 7144416,
  "type": "Feature",
  "properties": {
    "tgn:hierarchy":[
        "tgn:7144416",
        "tgn:1000003",
        "tgn:7003677",
        "tgn:7000084",
        "tgn:7029392"
    ],
    "tgn:id":7144416,
    "tgn:name":"K\u00f6ckelwicker Feld",
    "tgn:placetype":[
        "aat:300386990"
    ]
},
  "bbox": [],
  "geometry": {"coordinates":[6.833333,52.066667],"type":"Point"}
}