{
  "id": 2308771,
  "type": "Feature",
  "properties": {
    "tgn:hierarchy":[
        "tgn:2308771",
        "tgn:1000001",
        "tgn:7012149",
        "tgn:2000933",
        "tgn:7007515",
        "tgn:7029392"
    ],
    "tgn:id":2308771,
    "tgn:name":"East Point",
    "tgn:placetype":[
        "aat:300008850"
    ]
},
  "bbox": [],
  "geometry": {"coordinates":[-70.6167,43.1333],"type":"Point"}
}