{
  "id": 7225002,
  "type": "Feature",
  "properties": {
    "tgn:hierarchy":[
        "tgn:7225002",
        "tgn:7002707",
        "tgn:7002705",
        "tgn:1000003",
        "tgn:1000074",
        "tgn:7029392"
    ],
    "tgn:id":7225002,
    "tgn:name":"Sto\u00fala",
    "tgn:placetype":[
        "aat:300008347"
    ]
},
  "bbox": [],
  "geometry": {"coordinates":[21.001389,39.452222],"type":"Point"}
}