{
  "id": 7229275,
  "type": "Feature",
  "properties": {
    "tgn:hierarchy":[
        "tgn:7229275",
        "tgn:7002681",
        "tgn:7001395",
        "tgn:1000003",
        "tgn:1000074",
        "tgn:7029392"
    ],
    "tgn:id":7229275,
    "tgn:name":"Frig\u00e1nion",
    "tgn:placetype":[
        "aat:300008347"
    ]
},
  "bbox": [],
  "geometry": {"coordinates":[24.383333,38.083333],"type":"Point"}
}