{
  "id": 2653314,
  "type": "Feature",
  "properties": {
    "tgn:hierarchy":[
        "tgn:2653314",
        "tgn:7002659",
        "tgn:1000001",
        "tgn:7012149",
        "tgn:2000056",
        "tgn:7029392"
    ],
    "tgn:id":2653314,
    "tgn:name":"Sevenmile Creek",
    "tgn:placetype":[
        "aat:300008706"
    ]
},
  "bbox": [],
  "geometry": {"coordinates":[-85.05,32.4167],"type":"Point"}
}