<<<<<<< HEAD
{
  "id": 2330121,
  "type": "Feature",
  "properties": {
    "tgn:hierarchy":[
        "tgn:2330121",
        "tgn:1000001",
        "tgn:7012149",
        "tgn:2000930",
        "tgn:7007515",
        "tgn:7029392"
    ],
    "tgn:id":2330121,
    "tgn:name":"Flagstaff Mountain",
    "tgn:placetype":[
        "aat:300008798"
    ]
},
  "bbox": [],
  "geometry": {"coordinates":[-70.3,45.2333],"type":"Point"}
}
=======
{"geometry":{"type":"Point","coordinates":[-70.300000,45.233300]},"type":"Feature","properties":{"hierarchy":["tgn:2330121","tgn:1000001","tgn:7012149","tgn:2000930","tgn:7007515","tgn:7029392"],"placetype":["aat:300008798"],"id":2330121,"name:xx":"Flagstaff Mountain"}}
>>>>>>> 03f74aca74312dbeaf24d7e61306dd6a786dc3d0
