{
  "id": 1091338,
  "type": "Feature",
  "properties": {
    "tgn:hierarchy":[
        "tgn:1091338",
        "tgn:7001242",
        "tgn:1000179",
        "tgn:7593681",
        "tgn:7029392"
    ],
    "tgn:id":1091338,
    "tgn:name":"Ait Youssef ou Ali",
    "tgn:placetype":[
        "aat:300008347",
        "aat:300387323"
    ]
},
  "bbox": [],
  "geometry": {"coordinates":[-3.861,35.183],"type":"Point"}
}