{
  "id": 1019355,
  "type": "Feature",
  "properties": {
    "tgn:hierarchy":[
        "tgn:1019355",
        "tgn:1001195",
        "tgn:7006477",
        "tgn:1000002",
        "tgn:7029392"
    ],
    "tgn:id":1019355,
    "tgn:name":"Coronel Du Graty",
    "tgn:placetype":[
        "aat:300008347"
    ]
},
  "bbox": [],
  "geometry": {"coordinates":[-60.9333,-27.6667],"type":"Point"}
}