{
  "id": 2233726,
  "type": "Feature",
  "properties": {
    "tgn:hierarchy":[
        "tgn:2233726",
        "tgn:1000001",
        "tgn:7012149",
        "tgn:1002758",
        "tgn:7007568",
        "tgn:7029392"
    ],
    "tgn:id":2233726,
    "tgn:name":"Chase Pond",
    "tgn:placetype":[
        "aat:300008680"
    ]
},
  "bbox": [],
  "geometry": {"coordinates":[-75.9833,43.35],"type":"Point"}
}