{
  "id": 2349371,
  "type": "Feature",
  "properties": {
    "tgn:hierarchy":[
        "tgn:2349371",
        "tgn:7006450",
        "tgn:1000001",
        "tgn:7012149",
        "tgn:2000089",
        "tgn:7029392"
    ],
    "tgn:id":2349371,
    "tgn:name":"Giles Bay",
    "tgn:placetype":[
        "aat:300132316"
    ]
},
  "bbox": [],
  "geometry": {"coordinates":[-152.3167,63.85],"type":"Point"}
}