{
  "id": 1069779,
  "type": "Feature",
  "properties": {
    "tgn:hierarchy":[
        "tgn:1069779",
        "tgn:1000004",
        "tgn:7002087",
        "tgn:1000111",
        "tgn:7029392"
    ],
    "tgn:id":1069779,
    "tgn:name":"Lianjiechang",
    "tgn:placetype":[
        "aat:300008347"
    ]
},
  "bbox": [],
  "geometry": {"coordinates":[104.4667,29.7667],"type":"Point"}
}