{
  "id": 7353995,
  "type": "Feature",
  "properties": {
    "tgn:hierarchy":[
        "tgn:7353995",
        "tgn:7005581",
        "tgn:1000001",
        "tgn:7005560",
        "tgn:7029392"
    ],
    "tgn:id":7353995,
    "tgn:name":"Campo 15",
    "tgn:placetype":[
        "aat:300008347"
    ]
},
  "bbox": [],
  "geometry": {"coordinates":[-106.883333,28.616667],"type":"Point"}
}