{
  "id": 2648978,
  "type": "Feature",
  "properties": {
    "tgn:hierarchy":[
        "tgn:2648978",
        "tgn:1000001",
        "tgn:2000459",
        "tgn:7012149",
        "tgn:7007250",
        "tgn:7029392"
    ],
    "tgn:id":2648978,
    "tgn:name":"Scott Creek",
    "tgn:placetype":[
        "aat:300008706"
    ]
},
  "bbox": [],
  "geometry": {"coordinates":[-115.75,44.1833],"type":"Point"}
}