{
  "id": 2327797,
  "type": "Feature",
  "properties": {
    "tgn:hierarchy":[
        "tgn:2327797",
        "tgn:1000001",
        "tgn:2001413",
        "tgn:7012149",
        "tgn:7007526",
        "tgn:7029392"
    ],
    "tgn:id":2327797,
    "tgn:name":"Fish Creek Valley",
    "tgn:placetype":[
        "aat:300386845"
    ]
},
  "bbox": [],
  "geometry": {"coordinates":[-115.9833,39.2833],"type":"Point"}
}