{
  "id": 7399850,
  "type": "Feature",
  "properties": {
    "tgn:hierarchy":[
        "tgn:7399850",
        "tgn:1000001",
        "tgn:7005593",
        "tgn:7005560",
        "tgn:7029392"
    ],
    "tgn:id":7399850,
    "tgn:name":"Mavi",
    "tgn:placetype":[
        "aat:300008347"
    ]
},
  "bbox": [],
  "geometry": {"coordinates":[-99.508333,21.155556],"type":"Point"}
}