{
  "id": 2457472,
  "type": "Feature",
  "properties": {
    "tgn:hierarchy":[
        "tgn:2457472",
        "tgn:1000001",
        "tgn:7012149",
        "tgn:7007708",
        "tgn:7029392"
    ],
    "tgn:id":2457472,
    "tgn:name":"Little Lookingglass Creek",
    "tgn:placetype":[
        "aat:300008706"
    ]
},
  "bbox": [],
  "geometry": {"coordinates":[-117.9333,45.85],"type":"Point"}
}