<<<<<<< HEAD
{
  "id": 2155563,
  "type": "Feature",
  "properties": {
    "tgn:hierarchy":[
        "tgn:2155563",
        "tgn:1000001",
        "tgn:7012149",
        "tgn:1002613",
        "tgn:7007710",
        "tgn:7029392"
    ],
    "tgn:id":2155563,
    "tgn:name":"Bear Run",
    "tgn:placetype":[
        "aat:300008699"
    ]
},
  "bbox": [],
  "geometry": {"coordinates":[-77.1667,41.45],"type":"Point"}
}
=======
{"geometry":{"type":"Point","coordinates":[-77.166700,41.450000]},"type":"Feature","properties":{"hierarchy":["tgn:2155563","tgn:1000001","tgn:7012149","tgn:1002613","tgn:7007710","tgn:7029392"],"placetype":["aat:300008699"],"id":2155563,"name:xx":"Bear Run"}}
>>>>>>> 03f74aca74312dbeaf24d7e61306dd6a786dc3d0
