{
  "id": 2690711,
  "type": "Feature",
  "properties": {
    "tgn:hierarchy":[
        "tgn:2690711",
        "tgn:1000001",
        "tgn:7012149",
        "tgn:2000911",
        "tgn:7007256",
        "tgn:7029392"
    ],
    "tgn:id":2690711,
    "tgn:name":"Standard",
    "tgn:placetype":[
        "aat:300008347"
    ]
},
  "bbox": [],
  "geometry": {"coordinates":[-93.35,31.15],"type":"Point"}
}