{
  "id": 7005869,
  "type": "Feature",
  "properties": {
    "tgn:hierarchy":[
        "tgn:7005869",
        "tgn:1000003",
        "tgn:7003237",
        "tgn:1000080",
        "tgn:7029392"
    ],
    "tgn:id":7005869,
    "tgn:name":"Cremona",
    "tgn:placetype":[
        "aat:300387145",
        "aat:300000774"
    ]
},
  "bbox": [],
  "geometry": {"coordinates":[9.933333,45.233333],"type":"Point"}
}