{
  "id": 2431309,
  "type": "Feature",
  "properties": {
    "tgn:hierarchy":[
        "tgn:2431309",
        "tgn:1000001",
        "tgn:7012149",
        "tgn:1002487",
        "tgn:7007252",
        "tgn:7029392"
    ],
    "tgn:id":2431309,
    "tgn:name":"Kappa Corner",
    "tgn:placetype":[
        "aat:300008347"
    ]
},
  "bbox": [],
  "geometry": {"coordinates":[-86.2667,40.5167],"type":"Point"}
}