{
  "id": 7010926,
  "type": "Feature",
  "properties": {
    "tgn:hierarchy":[
        "tgn:7010926",
        "tgn:7002745",
        "tgn:7017076",
        "tgn:1000003",
        "tgn:1000074",
        "tgn:7029392"
    ],
    "tgn:id":7010926,
    "tgn:name":"Mistr\u00e1s",
    "tgn:placetype":[
        "aat:300008347",
        "aat:300000810",
        "aat:300008372",
        "aat:300263063"
    ]
},
  "bbox": [],
  "geometry": {"coordinates":[22.366667,37.066667],"type":"Point"}
}