{
  "id": 2721922,
  "type": "Feature",
  "properties": {
    "tgn:hierarchy":[
        "tgn:2721922",
        "tgn:1000001",
        "tgn:2001014",
        "tgn:7012149",
        "tgn:7007521",
        "tgn:7029392"
    ],
    "tgn:id":2721922,
    "tgn:name":"Timber Lake",
    "tgn:placetype":[
        "aat:300008680"
    ]
},
  "bbox": [],
  "geometry": {"coordinates":[-90.9833,47.75],"type":"Point"}
}