{
  "id": 2125631,
  "type": "Feature",
  "properties": {
    "tgn:hierarchy":[
        "tgn:2125631",
        "tgn:1000001",
        "tgn:7012149",
        "tgn:7007157",
        "tgn:1002566",
        "tgn:7029392"
    ],
    "tgn:id":2125631,
    "tgn:name":"Adams",
    "tgn:placetype":[
        "aat:300008347"
    ]
},
  "bbox": [],
  "geometry": {"coordinates":[-122.7167,38.85],"type":"Point"}
}