{
  "id": 7531941,
  "type": "Feature",
  "properties": {
    "tgn:hierarchy":[
        "tgn:7531941",
        "tgn:7001242",
        "tgn:7016833",
        "tgn:1001091",
        "tgn:7029392"
    ],
    "tgn:id":7531941,
    "tgn:name":"Masjid Na\u015fr al Isl\u0101m",
    "tgn:placetype":[
        "aat:300007544"
    ]
},
  "bbox": [],
  "geometry": {"coordinates":[31.233162,30.087432],"type":"Point"}
}