<<<<<<< HEAD
{
  "id": 7355214,
  "type": "Feature",
  "properties": {
    "tgn:hierarchy":[
        "tgn:7355214",
        "tgn:1001835",
        "tgn:1000001",
        "tgn:7005560",
        "tgn:7029392"
    ],
    "tgn:id":7355214,
    "tgn:name":"Cantil, Cerro el",
    "tgn:placetype":[
        "aat:300008795"
    ]
},
  "bbox": [],
  "geometry": {"coordinates":[-116.616667,31.666667],"type":"Point"}
}
=======
{"geometry":{"type":"Point","coordinates":[-116.616667,31.666667]},"type":"Feature","properties":{"hierarchy":["tgn:7355214","tgn:1001835","tgn:1000001","tgn:7005560","tgn:7029392"],"placetype":["aat:300008795"],"id":7355214,"name:xx":"Cantil, Cerro el"}}
>>>>>>> 03f74aca74312dbeaf24d7e61306dd6a786dc3d0
