{
  "id": 7483693,
  "type": "Feature",
  "properties": {
    "tgn:hierarchy":[
        "tgn:7483693",
        "tgn:7468018",
        "tgn:1000004",
        "tgn:1000141",
        "tgn:7029392"
    ],
    "tgn:id":7483693,
    "tgn:name":"Minquan Qiao",
    "tgn:placetype":[
        "aat:300007836"
    ]
},
  "bbox": [],
  "geometry": {"coordinates":[120.569167,23.236944],"type":"Point"}
}