<<<<<<< HEAD
{
  "id": 7483693,
  "type": "Feature",
  "properties": {
    "tgn:hierarchy":[
        "tgn:7483693",
        "tgn:7468018",
        "tgn:1000004",
        "tgn:1000141",
        "tgn:7029392"
    ],
    "tgn:id":7483693,
    "tgn:name":"Minquan Qiao",
    "tgn:placetype":[
        "aat:300007836"
    ]
},
  "bbox": [],
  "geometry": {"coordinates":[120.569167,23.236944],"type":"Point"}
}
=======
{"geometry":{"type":"Point","coordinates":[120.569167,23.236944]},"type":"Feature","properties":{"hierarchy":["tgn:7483693","tgn:7468018","tgn:1000004","tgn:1000141","tgn:7029392"],"placetype":["aat:300007836"],"id":7483693,"name:xx":"Minquan Qiao"}}
>>>>>>> 03f74aca74312dbeaf24d7e61306dd6a786dc3d0
