{
  "id": 2544077,
  "type": "Feature",
  "properties": {
    "tgn:hierarchy":[
        "tgn:2544077",
        "tgn:1000001",
        "tgn:1002182",
        "tgn:7012149",
        "tgn:7007520",
        "tgn:7029392"
    ],
    "tgn:id":2544077,
    "tgn:name":"North Branch Hickory Creek",
    "tgn:placetype":[
        "aat:300008706"
    ]
},
  "bbox": [],
  "geometry": {"coordinates":[-86.4167,41.9667],"type":"Point"}
}