{
  "id": 2159725,
  "type": "Feature",
  "properties": {
    "tgn:hierarchy":[
        "tgn:2159725",
        "tgn:1002176",
        "tgn:1000001",
        "tgn:7012149",
        "tgn:7007828",
        "tgn:7029392"
    ],
    "tgn:id":2159725,
    "tgn:name":"Beebe Pond",
    "tgn:placetype":[
        "aat:300008680"
    ]
},
  "bbox": [],
  "geometry": {"coordinates":[-73.0167,43.05],"type":"Point"}
}