{
  "id": 2668141,
  "type": "Feature",
  "properties": {
    "tgn:hierarchy":[
        "tgn:2668141",
        "tgn:1000001",
        "tgn:1002219",
        "tgn:7012149",
        "tgn:7007157",
        "tgn:7029392"
    ],
    "tgn:id":2668141,
    "tgn:name":"Skyrocket Mine",
    "tgn:placetype":[
        "aat:300000390"
    ]
},
  "bbox": [],
  "geometry": {"coordinates":[-120.6833,37.9833],"type":"Point"}
}