{
  "id": 2739284,
  "type": "Feature",
  "properties": {
    "tgn:hierarchy":[
        "tgn:2739284",
        "tgn:1000001",
        "tgn:7012149",
        "tgn:2001036",
        "tgn:7007521",
        "tgn:7029392"
    ],
    "tgn:id":2739284,
    "tgn:name":"Upland Lake",
    "tgn:placetype":[
        "aat:300008680"
    ]
},
  "bbox": [],
  "geometry": {"coordinates":[-91.65,47.4333],"type":"Point"}
}