{
  "id": 7490731,
  "type": "Feature",
  "properties": {
    "tgn:hierarchy":[
        "tgn:7490731",
        "tgn:7001004",
        "tgn:1000004",
        "tgn:1000141",
        "tgn:7029392"
    ],
    "tgn:id":7490731,
    "tgn:name":"Papaxi Xi",
    "tgn:placetype":[
        "aat:300008699"
    ]
},
  "bbox": [],
  "geometry": {"coordinates":[120.832156,23.288468],"type":"Point"}
}