<<<<<<< HEAD
{
  "id": 7247458,
  "type": "Feature",
  "properties": {
    "tgn:hierarchy":[
        "tgn:7247458",
        "tgn:7003456",
        "tgn:1000003",
        "tgn:1000063",
        "tgn:7018236",
        "tgn:7029392"
    ],
    "tgn:id":7247458,
    "tgn:name":"De Beunt",
    "tgn:placetype":[
        "aat:300008347"
    ]
},
  "bbox": [],
  "geometry": {"coordinates":[4.5,51.1],"type":"Point"}
}
=======
{"geometry":{"type":"Point","coordinates":[4.500000,51.100000]},"type":"Feature","properties":{"hierarchy":["tgn:7247458","tgn:7003456","tgn:1000003","tgn:1000063","tgn:7018236","tgn:7029392"],"placetype":["aat:300008347"],"id":7247458,"name:xx":"De Beunt"}}
>>>>>>> 03f74aca74312dbeaf24d7e61306dd6a786dc3d0
