{
  "id": 2304615,
  "type": "Feature",
  "properties": {
    "tgn:hierarchy":[
        "tgn:2304615",
        "tgn:2000943",
        "tgn:1000001",
        "tgn:7012149",
        "tgn:7007520",
        "tgn:7029392"
    ],
    "tgn:id":2304615,
    "tgn:name":"East Bay",
    "tgn:placetype":[
        "aat:300132316"
    ]
},
  "bbox": [],
  "geometry": {"coordinates":[-85.9333,46.6667],"type":"Point"}
}