{
  "id": 2043297,
  "type": "Feature",
  "properties": {
    "tgn:hierarchy":[
        "tgn:2043297",
        "tgn:2000857",
        "tgn:1000001",
        "tgn:7012149",
        "tgn:7007256",
        "tgn:7029392"
    ],
    "tgn:id":2043297,
    "tgn:name":"Little Texas",
    "tgn:placetype":[
        "aat:300008347",
        "aat:300387210"
    ]
},
  "bbox": [],
  "geometry": {"coordinates":[-91.0167,29.8667],"type":"Point"}
}