{
  "id": 7561509,
  "type": "Feature",
  "properties": {
    "tgn:hierarchy":[
        "tgn:7561509",
        "tgn:1000004",
        "tgn:7000198",
        "tgn:7016722",
        "tgn:7029392"
    ],
    "tgn:id":7561509,
    "tgn:name:en":"Nagla Kaly\u0101npur",
    "tgn:placetype":[
        "aat:300008347"
    ]
},
  "bbox": [],
  "geometry": {"coordinates":[79.354888,27.14389],"type":"Point"}
}