{
  "id": 2144906,
  "type": "Feature",
  "properties": {
    "tgn:hierarchy":[
        "tgn:2144906",
        "tgn:1000001",
        "tgn:2000779",
        "tgn:7012149",
        "tgn:7007255",
        "tgn:7029392"
    ],
    "tgn:id":2144906,
    "tgn:name":"Bald Knob",
    "tgn:placetype":[
        "aat:300008798"
    ]
},
  "bbox": [],
  "geometry": {"coordinates":[-85.0167,37.45],"type":"Point"}
}