<<<<<<< HEAD
{
  "id": 2762832,
  "type": "Feature",
  "properties": {
    "tgn:hierarchy":[
        "tgn:2762832",
        "tgn:1000001",
        "tgn:7012149",
        "tgn:1002681",
        "tgn:7007568",
        "tgn:7029392"
    ],
    "tgn:id":2762832,
    "tgn:name":"Westfall",
    "tgn:placetype":[
        "aat:300008347"
    ]
},
  "bbox": [],
  "geometry": {"coordinates":[-77.6167,43.1],"type":"Point"}
}
=======
{"geometry":{"type":"Point","coordinates":[-77.616700,43.100000]},"type":"Feature","properties":{"hierarchy":["tgn:2762832","tgn:1000001","tgn:7012149","tgn:1002681","tgn:7007568","tgn:7029392"],"placetype":["aat:300008347"],"id":2762832,"name:xx":"Westfall"}}
>>>>>>> 03f74aca74312dbeaf24d7e61306dd6a786dc3d0
