{
  "id": 7320576,
  "type": "Feature",
  "properties": {
    "tgn:hierarchy":[
        "tgn:7320576",
        "tgn:1001702",
        "tgn:1000049",
        "tgn:1000002",
        "tgn:7029392"
    ],
    "tgn:id":7320576,
    "tgn:name":"Cabeza, Islote",
    "tgn:placetype":[
        "aat:300008791"
    ]
},
  "bbox": [],
  "geometry": {"coordinates":[-72.233333,-53.133333],"type":"Point"}
}