{
  "id": 2511362,
  "type": "Feature",
  "properties": {
    "tgn:hierarchy":[
        "tgn:2511362",
        "tgn:1000001",
        "tgn:7012149",
        "tgn:2001875",
        "tgn:7007825",
        "tgn:7029392"
    ],
    "tgn:id":2511362,
    "tgn:name":"Milam Pond",
    "tgn:placetype":[
        "aat:300006191"
    ]
},
  "bbox": [],
  "geometry": {"coordinates":[-88.4333,35.7167],"type":"Point"}
}