{
  "id": 2091077,
  "type": "Feature",
  "properties": {
    "tgn:hierarchy":[
        "tgn:2091077",
        "tgn:1000001",
        "tgn:7012149",
        "tgn:1002995",
        "tgn:7007710",
        "tgn:7029392"
    ],
    "tgn:id":2091077,
    "tgn:name":"Murry Hill",
    "tgn:placetype":[
        "aat:300008347"
    ]
},
  "bbox": [],
  "geometry": {"coordinates":[-80.15,40.2667],"type":"Point"}
}