{
  "id": 2681935,
  "type": "Feature",
  "properties": {
    "tgn:hierarchy":[
        "tgn:2681935",
        "tgn:2002130",
        "tgn:1000001",
        "tgn:7012149",
        "tgn:7007828",
        "tgn:7029392"
    ],
    "tgn:id":2681935,
    "tgn:name":"South Slang Creek",
    "tgn:placetype":[
        "aat:300008706"
    ]
},
  "bbox": [],
  "geometry": {"coordinates":[-73.2667,44.1667],"type":"Point"}
}