{
  "id": 1014569,
  "type": "Feature",
  "properties": {
    "tgn:hierarchy":[
        "tgn:1014569",
        "tgn:7005685",
        "tgn:1000001",
        "tgn:7013154",
        "tgn:7029392"
    ],
    "tgn:id":1014569,
    "tgn:name":"Ayr",
    "tgn:placetype":[
        "aat:300008347"
    ]
},
  "bbox": [],
  "geometry": {"coordinates":[-80.45,43.2833],"type":"Point"}
}