{
  "id": 2322549,
  "type": "Feature",
  "properties": {
    "tgn:hierarchy":[
        "tgn:2322549",
        "tgn:1000001",
        "tgn:7012149",
        "tgn:2001622",
        "tgn:7007706",
        "tgn:7029392"
    ],
    "tgn:id":2322549,
    "tgn:name":"Falls Creek",
    "tgn:placetype":[
        "aat:300008706"
    ]
},
  "bbox": [],
  "geometry": {"coordinates":[-81.7667,39.3833],"type":"Point"}
}