{
  "id": 7503459,
  "type": "Feature",
  "properties": {
    "tgn:hierarchy":[
        "tgn:7503459",
        "tgn:7487020",
        "tgn:1000004",
        "tgn:1000141",
        "tgn:7029392"
    ],
    "tgn:id":7503459,
    "tgn:name":"Baimei Qiao",
    "tgn:placetype":[
        "aat:300007836"
    ]
},
  "bbox": [],
  "geometry": {"coordinates":[121.043889,24.595278],"type":"Point"}
}