{
  "id": 7306835,
  "type": "Feature",
  "properties": {
    "tgn:hierarchy":[
        "tgn:7306835",
        "tgn:1001439",
        "tgn:1000003",
        "tgn:7002797",
        "tgn:1000095",
        "tgn:7029392"
    ],
    "tgn:id":7306835,
    "tgn:name":"Lo Gea",
    "tgn:placetype":[
        "aat:300008347"
    ]
},
  "bbox": [],
  "geometry": {"coordinates":[-1.016667,37.883333],"type":"Point"}
}