{
  "id": 2169521,
  "type": "Feature",
  "properties": {
    "tgn:hierarchy":[
        "tgn:2169521",
        "tgn:1000001",
        "tgn:7012149",
        "tgn:1002676",
        "tgn:7007240",
        "tgn:7029392"
    ],
    "tgn:id":2169521,
    "tgn:name":"Big Mangrove Key",
    "tgn:placetype":[
        "aat:300008791"
    ]
},
  "bbox": [],
  "geometry": {"coordinates":[-81.3167,24.6667],"type":"Point"}
}