{
  "id": 2269022,
  "type": "Feature",
  "properties": {
    "tgn:hierarchy":[
        "tgn:2269022",
        "tgn:1000001",
        "tgn:7012149",
        "tgn:2001447",
        "tgn:7007566",
        "tgn:7029392"
    ],
    "tgn:id":2269022,
    "tgn:name":"Crossroad Tank",
    "tgn:placetype":[
        "aat:300006191"
    ]
},
  "bbox": [],
  "geometry": {"coordinates":[-106.25,33.2167],"type":"Point"}
}