{
  "id": 2258207,
  "type": "Feature",
  "properties": {
    "tgn:hierarchy":[
        "tgn:2258207",
        "tgn:7006450",
        "tgn:1000001",
        "tgn:7012149",
        "tgn:2000088",
        "tgn:7029392"
    ],
    "tgn:id":2258207,
    "tgn:name":"Cote, Mount",
    "tgn:placetype":[
        "aat:300008798"
    ]
},
  "bbox": [],
  "geometry": {"coordinates":[-131.8333,56.5833],"type":"Point"}
}