<<<<<<< HEAD
{
  "id": 2258207,
  "type": "Feature",
  "properties": {
    "tgn:hierarchy":[
        "tgn:2258207",
        "tgn:7006450",
        "tgn:1000001",
        "tgn:7012149",
        "tgn:2000088",
        "tgn:7029392"
    ],
    "tgn:id":2258207,
    "tgn:name":"Cote, Mount",
    "tgn:placetype":[
        "aat:300008798"
    ]
},
  "bbox": [],
  "geometry": {"coordinates":[-131.8333,56.5833],"type":"Point"}
}
=======
{"geometry":{"type":"Point","coordinates":[-131.833300,56.583300]},"type":"Feature","properties":{"hierarchy":["tgn:2258207","tgn:7006450","tgn:1000001","tgn:7012149","tgn:2000088","tgn:7029392"],"placetype":["aat:300008798"],"id":2258207,"name:xx":"Cote, Mount"}}
>>>>>>> 03f74aca74312dbeaf24d7e61306dd6a786dc3d0
