{
  "id": 1076691,
  "type": "Feature",
  "properties": {
    "tgn:hierarchy":[
        "tgn:1076691",
        "tgn:1000004",
        "tgn:7000198",
        "tgn:7000799",
        "tgn:7029392"
    ],
    "tgn:id":1076691,
    "tgn:name":"Ramban",
    "tgn:placetype":[
        "aat:300008347"
    ]
},
  "bbox": [],
  "geometry": {"coordinates":[75.239465,33.241009],"type":"Point"}
}