{
  "id": 1056394,
  "type": "Feature",
  "properties": {
    "tgn:hierarchy":[
        "tgn:1056394",
        "tgn:1000004",
        "tgn:7011573",
        "tgn:7018214",
        "tgn:7002435",
        "tgn:7029392"
    ],
    "tgn:id":1056394,
    "tgn:name":"Lepeshki",
    "tgn:placetype":[
        "aat:300008347"
    ]
},
  "bbox": [],
  "geometry": {"coordinates":[38.1167,56.0833],"type":"Point"}
}