{
  "id": 7289304,
  "type": "Feature",
  "properties": {
    "tgn:hierarchy":[
        "tgn:7289304",
        "tgn:1001702",
        "tgn:1000049",
        "tgn:1000002",
        "tgn:7029392"
    ],
    "tgn:id":7289304,
    "tgn:name":"Inmanuel, Bah\u00eda",
    "tgn:placetype":[
        "aat:300132316"
    ]
},
  "bbox": [],
  "geometry": {"coordinates":[-72.416667,-54.366667],"type":"Point"}
}