<<<<<<< HEAD
{
  "id": 7375739,
  "type": "Feature",
  "properties": {
    "tgn:hierarchy":[
        "tgn:7375739",
        "tgn:1000001",
        "tgn:7005599",
        "tgn:7005560",
        "tgn:7029392"
    ],
    "tgn:id":7375739,
    "tgn:name":"Las Tijeras",
    "tgn:placetype":[
        "aat:300008347"
    ]
},
  "bbox": [],
  "geometry": {"coordinates":[-98.083333,22.366667],"type":"Point"}
}
=======
{"geometry":{"type":"Point","coordinates":[-98.083333,22.366667]},"type":"Feature","properties":{"hierarchy":["tgn:7375739","tgn:1000001","tgn:7005599","tgn:7005560","tgn:7029392"],"placetype":["aat:300008347"],"id":7375739,"name:xx":"Las Tijeras"}}
>>>>>>> 03f74aca74312dbeaf24d7e61306dd6a786dc3d0
