<<<<<<< HEAD
{
  "id": 2763612,
  "type": "Feature",
  "properties": {
    "tgn:hierarchy":[
        "tgn:2763612",
        "tgn:1002300",
        "tgn:1000001",
        "tgn:7012149",
        "tgn:7007564",
        "tgn:7029392"
    ],
    "tgn:id":2763612,
    "tgn:name":"Whaleback Pond",
    "tgn:placetype":[
        "aat:300008680"
    ]
},
  "bbox": [],
  "geometry": {"coordinates":[-71.05,44.8167],"type":"Point"}
}
=======
{"geometry":{"type":"Point","coordinates":[-71.050000,44.816700]},"type":"Feature","properties":{"hierarchy":["tgn:2763612","tgn:1002300","tgn:1000001","tgn:7012149","tgn:7007564","tgn:7029392"],"placetype":["aat:300008680"],"id":2763612,"name:xx":"Whaleback Pond"}}
>>>>>>> 03f74aca74312dbeaf24d7e61306dd6a786dc3d0
