{
  "id": 2643674,
  "type": "Feature",
  "properties": {
    "tgn:hierarchy":[
        "tgn:2643674",
        "tgn:1000001",
        "tgn:2001733",
        "tgn:7012149",
        "tgn:7007712",
        "tgn:7029392"
    ],
    "tgn:id":2643674,
    "tgn:name":"Sandy Run",
    "tgn:placetype":[
        "aat:300008347"
    ]
},
  "bbox": [],
  "geometry": {"coordinates":[-80.95,33.7833],"type":"Point"}
}