{
  "id": 2504981,
  "type": "Feature",
  "properties": {
    "tgn:hierarchy":[
        "tgn:2504981",
        "tgn:1000001",
        "tgn:2000198",
        "tgn:7012149",
        "tgn:7007158",
        "tgn:7029392"
    ],
    "tgn:id":2504981,
    "tgn:name":"Meeker Ridge",
    "tgn:placetype":[
        "aat:300266640"
    ]
},
  "bbox": [],
  "geometry": {"coordinates":[-105.5833,40.2333],"type":"Point"}
}