{
  "id": 2480096,
  "type": "Feature",
  "properties": {
    "tgn:hierarchy":[
        "tgn:2480096",
        "tgn:1000001",
        "tgn:7012149",
        "tgn:1002659",
        "tgn:7007710",
        "tgn:7029392"
    ],
    "tgn:id":2480096,
    "tgn:name":"Lake Latonka",
    "tgn:placetype":[
        "aat:300006191"
    ]
},
  "bbox": [],
  "geometry": {"coordinates":[-80.1833,41.2667],"type":"Point"}
}