{
  "id": 7317815,
  "type": "Feature",
  "properties": {
    "tgn:hierarchy":[
        "tgn:7317815",
        "tgn:1001630",
        "tgn:1000049",
        "tgn:1000002",
        "tgn:7029392"
    ],
    "tgn:id":7317815,
    "tgn:name":"Chicharra, Cerro",
    "tgn:placetype":[
        "aat:300008777"
    ]
},
  "bbox": [],
  "geometry": {"coordinates":[-71.05,-28.333333],"type":"Point"}
}