{
  "id": 7579287,
  "type": "Feature",
  "properties": {
    "tgn:hierarchy":[
        "tgn:7579287",
        "tgn:1000004",
        "tgn:1001869",
        "tgn:7000198",
        "tgn:7029392"
    ],
    "tgn:id":7579287,
    "tgn:name:en":"T\u0101r\u0101pur",
    "tgn:placetype":[
        "aat:300007783"
    ]
},
  "bbox": [],
  "geometry": {"coordinates":[72.683333,22.466667],"type":"Point"}
}