<<<<<<< HEAD
{
  "id": 7020833,
  "type": "Feature",
  "properties": {
    "tgn:hierarchy":[
        "tgn:7020833",
        "tgn:2000453",
        "tgn:1000001",
        "tgn:7012149",
        "tgn:7007250",
        "tgn:7029392"
    ],
    "tgn:id":7020833,
    "tgn:name":"Louise Creek",
    "tgn:placetype":[
        "aat:300008706"
    ]
},
  "bbox": [],
  "geometry": {"coordinates":[-116.4667,45.2333],"type":"Point"}
}
=======
{"geometry":{"type":"Point","coordinates":[-116.466700,45.233300]},"type":"Feature","properties":{"hierarchy":["tgn:7020833","tgn:2000453","tgn:1000001","tgn:7012149","tgn:7007250","tgn:7029392"],"placetype":["aat:300008706"],"id":7020833,"name:xx":"Louise Creek"}}
>>>>>>> 03f74aca74312dbeaf24d7e61306dd6a786dc3d0
