<<<<<<< HEAD
{
  "id": 2404193,
  "type": "Feature",
  "properties": {
    "tgn:hierarchy":[
        "tgn:2404193",
        "tgn:1000001",
        "tgn:7012149",
        "tgn:1002481",
        "tgn:7007520",
        "tgn:7029392"
    ],
    "tgn:id":2404193,
    "tgn:name":"Hoxie Drain",
    "tgn:placetype":[
        "aat:300008699"
    ]
},
  "bbox": [],
  "geometry": {"coordinates":[-84.4333,41.95],"type":"Point"}
}
=======
{"geometry":{"type":"Point","coordinates":[-84.433300,41.950000]},"type":"Feature","properties":{"hierarchy":["tgn:2404193","tgn:1000001","tgn:7012149","tgn:1002481","tgn:7007520","tgn:7029392"],"placetype":["aat:300008699"],"id":2404193,"name:xx":"Hoxie Drain"}}
>>>>>>> 03f74aca74312dbeaf24d7e61306dd6a786dc3d0
