{
  "id": 7150506,
  "type": "Feature",
  "properties": {
    "tgn:hierarchy":[
        "tgn:7150506",
        "tgn:7000096",
        "tgn:1000003",
        "tgn:7000084",
        "tgn:7029392"
    ],
    "tgn:id":7150506,
    "tgn:name":"Krohns-Berg",
    "tgn:placetype":[
        "aat:300008777"
    ]
},
  "bbox": [],
  "geometry": {"coordinates":[11.966667,53.016667],"type":"Point"}
}