{
  "id": 7556571,
  "type": "Feature",
  "properties": {
    "tgn:hierarchy":[
        "tgn:7556571",
        "tgn:1000004",
        "tgn:7000198",
        "tgn:7016788",
        "tgn:7029392"
    ],
    "tgn:id":7556571,
    "tgn:name:en":"Pilauda",
    "tgn:placetype":[
        "aat:300008347"
    ]
},
  "bbox": [],
  "geometry": {"coordinates":[76.837604,26.595322],"type":"Point"}
}