{
  "id": 2138829,
  "type": "Feature",
  "properties": {
    "tgn:hierarchy":[
        "tgn:2138829",
        "tgn:1000001",
        "tgn:2001260",
        "tgn:7012149",
        "tgn:7007524",
        "tgn:7029392"
    ],
    "tgn:id":2138829,
    "tgn:name":"Ashbough Spring",
    "tgn:placetype":[
        "aat:300008697"
    ]
},
  "bbox": [],
  "geometry": {"coordinates":[-112.65,44.8167],"type":"Point"}
}