{
  "id": 2412607,
  "type": "Feature",
  "properties": {
    "tgn:hierarchy":[
        "tgn:2412607",
        "tgn:1000001",
        "tgn:7012149",
        "tgn:2000285",
        "tgn:7007240",
        "tgn:7029392"
    ],
    "tgn:id":2412607,
    "tgn:name":"Indigo Creek",
    "tgn:placetype":[
        "aat:300008706"
    ]
},
  "bbox": [],
  "geometry": {"coordinates":[-86.8167,30.5167],"type":"Point"}
}