<<<<<<< HEAD
{
  "id": 7370907,
  "type": "Feature",
  "properties": {
    "tgn:hierarchy":[
        "tgn:7370907",
        "tgn:7005586",
        "tgn:1000001",
        "tgn:7005560",
        "tgn:7029392"
    ],
    "tgn:id":7370907,
    "tgn:name":"Jes\u00fas Mar\u00eda",
    "tgn:placetype":[
        "aat:300008347"
    ]
},
  "bbox": [],
  "geometry": {"coordinates":[-103.933333,20.366667],"type":"Point"}
}
=======
{"geometry":{"type":"Point","coordinates":[-103.933333,20.366667]},"type":"Feature","properties":{"hierarchy":["tgn:7370907","tgn:7005586","tgn:1000001","tgn:7005560","tgn:7029392"],"placetype":["aat:300008347"],"id":7370907,"name:xx":"Jes\u00fas Mar\u00eda"}}
>>>>>>> 03f74aca74312dbeaf24d7e61306dd6a786dc3d0
