{
  "id": 2734956,
  "type": "Feature",
  "properties": {
    "tgn:hierarchy":[
        "tgn:2734956",
        "tgn:1000001",
        "tgn:2001703",
        "tgn:7012149",
        "tgn:7007708",
        "tgn:7029392"
    ],
    "tgn:id":2734956,
    "tgn:name":"Twelvemile Reservoir Number One",
    "tgn:placetype":[
        "aat:300006191"
    ]
},
  "bbox": [],
  "geometry": {"coordinates":[-119.9333,43.7667],"type":"Point"}
}