{
  "id": 7381118,
  "type": "Feature",
  "properties": {
    "tgn:hierarchy":[
        "tgn:7381118",
        "tgn:1001835",
        "tgn:1000001",
        "tgn:7005560",
        "tgn:7029392"
    ],
    "tgn:id":7381118,
    "tgn:name":"Medio Camino",
    "tgn:placetype":[
        "aat:300008347"
    ]
},
  "bbox": [],
  "geometry": {"coordinates":[-116.905833,32.174444],"type":"Point"}
}