<<<<<<< HEAD
{
  "id": 2159993,
  "type": "Feature",
  "properties": {
    "tgn:hierarchy":[
        "tgn:2159993",
        "tgn:1000001",
        "tgn:7012149",
        "tgn:2000474",
        "tgn:7007250",
        "tgn:7029392"
    ],
    "tgn:id":2159993,
    "tgn:name":"Beech Lake",
    "tgn:placetype":[
        "aat:300008680"
    ]
},
  "bbox": [],
  "geometry": {"coordinates":[-116.2833,44.25],"type":"Point"}
}
=======
{"geometry":{"type":"Point","coordinates":[-116.283300,44.250000]},"type":"Feature","properties":{"hierarchy":["tgn:2159993","tgn:1000001","tgn:7012149","tgn:2000474","tgn:7007250","tgn:7029392"],"placetype":["aat:300008680"],"id":2159993,"name:xx":"Beech Lake"}}
>>>>>>> 03f74aca74312dbeaf24d7e61306dd6a786dc3d0
