<<<<<<< HEAD
{
  "id": 2406957,
  "type": "Feature",
  "properties": {
    "tgn:hierarchy":[
        "tgn:2406957",
        "tgn:1000001",
        "tgn:7012149",
        "tgn:2002326",
        "tgn:7007922",
        "tgn:7029392"
    ],
    "tgn:id":2406957,
    "tgn:name":"Hunter Hollow",
    "tgn:placetype":[
        "aat:300008761"
    ]
},
  "bbox": [],
  "geometry": {"coordinates":[-90.1833,43.0667],"type":"Point"}
}
=======
{"geometry":{"type":"Point","coordinates":[-90.183300,43.066700]},"type":"Feature","properties":{"hierarchy":["tgn:2406957","tgn:1000001","tgn:7012149","tgn:2002326","tgn:7007922","tgn:7029392"],"placetype":["aat:300008761"],"id":2406957,"name:xx":"Hunter Hollow"}}
>>>>>>> 03f74aca74312dbeaf24d7e61306dd6a786dc3d0
