<<<<<<< HEAD
{
  "id": 7474496,
  "type": "Feature",
  "properties": {
    "tgn:hierarchy":[
        "tgn:7474496",
        "tgn:7468018",
        "tgn:1000004",
        "tgn:1000141",
        "tgn:7029392"
    ],
    "tgn:id":7474496,
    "tgn:name":"Wanqiao",
    "tgn:placetype":[
        "aat:300008347"
    ]
},
  "bbox": [],
  "geometry": {"coordinates":[120.487356,23.500205],"type":"Point"}
}
=======
{"geometry":{"type":"Point","coordinates":[120.487356,23.500205]},"type":"Feature","properties":{"hierarchy":["tgn:7474496","tgn:7468018","tgn:1000004","tgn:1000141","tgn:7029392"],"placetype":["aat:300008347"],"id":7474496,"name:xx":"Wanqiao"}}
>>>>>>> 03f74aca74312dbeaf24d7e61306dd6a786dc3d0
