{
  "id": 7416685,
  "type": "Feature",
  "properties": {
    "tgn:hierarchy":[
        "tgn:7416685",
        "tgn:1000001",
        "tgn:7005591",
        "tgn:7005560",
        "tgn:7029392"
    ],
    "tgn:id":7416685,
    "tgn:name:es":"Pie del Cerro",
    "tgn:placetype":[
        "aat:300008347"
    ]
},
  "bbox": [],
  "geometry": {"coordinates":[-97.414444,16.107778],"type":"Point"}
}