{
  "id": 7385149,
  "type": "Feature",
  "properties": {
    "tgn:hierarchy":[
        "tgn:7385149",
        "tgn:7005578",
        "tgn:1000001",
        "tgn:7005560",
        "tgn:7029392"
    ],
    "tgn:id":7385149,
    "tgn:name":"Nilch\u00ed",
    "tgn:placetype":[
        "aat:300008347"
    ]
},
  "bbox": [],
  "geometry": {"coordinates":[-90.266667,19.833333],"type":"Point"}
}