{
  "id": 7556726,
  "type": "Feature",
  "properties": {
    "tgn:hierarchy":[
        "tgn:7556726",
        "tgn:1000004",
        "tgn:7000198",
        "tgn:1001996",
        "tgn:7029392"
    ],
    "tgn:id":7556726,
    "tgn:name:en":"Sahel",
    "tgn:placetype":[
        "aat:300008347"
    ]
},
  "bbox": [],
  "geometry": {"coordinates":[76.666667,32.066667],"type":"Point"}
}