{
  "id": 7385587,
  "type": "Feature",
  "properties": {
    "tgn:hierarchy":[
        "tgn:7385587",
        "tgn:1000001",
        "tgn:7005600",
        "tgn:7005560",
        "tgn:7029392"
    ],
    "tgn:id":7385587,
    "tgn:name":"Nohalal",
    "tgn:placetype":[
        "aat:300387007"
    ]
},
  "bbox": [],
  "geometry": {"coordinates":[-90.083333,20.966667],"type":"Point"}
}