{
  "id": 7419358,
  "type": "Feature",
  "properties": {
    "tgn:hierarchy":[
        "tgn:7419358",
        "tgn:1000001",
        "tgn:7005589",
        "tgn:7005560",
        "tgn:7029392"
    ],
    "tgn:id":7419358,
    "tgn:name:es":"Estaci\u00f3n Mesa",
    "tgn:placetype":[
        "aat:300007783"
    ]
},
  "bbox": [],
  "geometry": {"coordinates":[-100.249444,27.201111],"type":"Point"}
}