{
  "id": 1121401,
  "type": "Feature",
  "properties": {
    "tgn:hierarchy":[
        "tgn:1121401",
        "tgn:7003139",
        "tgn:1000003",
        "tgn:7003080",
        "tgn:1000080",
        "tgn:7029392"
    ],
    "tgn:id":1121401,
    "tgn:name":"Arrone",
    "tgn:placetype":[
        "aat:300008707",
        "aat:300008699"
    ]
},
  "bbox": [],
  "geometry": {"coordinates":[12.183333,41.866667],"type":"Point"}
}