{
  "id": 7023097,
  "type": "Feature",
  "properties": {
    "tgn:hierarchy":[
        "tgn:7023097",
        "tgn:1000001",
        "tgn:7012149",
        "tgn:7007568",
        "tgn:7029392"
    ],
    "tgn:id":7023097,
    "tgn:name":"Schenevus Creek",
    "tgn:placetype":[
        "aat:300008706"
    ]
},
  "bbox": [],
  "geometry": {"coordinates":[-74.65,42.65],"type":"Point"}
}