<<<<<<< HEAD
{
  "id": 7023097,
  "type": "Feature",
  "properties": {
    "tgn:hierarchy":[
        "tgn:7023097",
        "tgn:1000001",
        "tgn:7012149",
        "tgn:7007568",
        "tgn:7029392"
    ],
    "tgn:id":7023097,
    "tgn:name":"Schenevus Creek",
    "tgn:placetype":[
        "aat:300008706"
    ]
},
  "bbox": [],
  "geometry": {"coordinates":[-74.65,42.65],"type":"Point"}
}
=======
{"geometry":{"type":"Point","coordinates":[-74.650000,42.650000]},"type":"Feature","properties":{"hierarchy":["tgn:7023097","tgn:1000001","tgn:7012149","tgn:7007568","tgn:7029392"],"placetype":["aat:300008706"],"id":7023097,"name:xx":"Schenevus Creek"}}
>>>>>>> 03f74aca74312dbeaf24d7e61306dd6a786dc3d0
