<<<<<<< HEAD
{
  "id": 2256188,
  "type": "Feature",
  "properties": {
    "tgn:hierarchy":[
        "tgn:2256188",
        "tgn:1000001",
        "tgn:7016172",
        "tgn:7012149",
        "tgn:2000175",
        "tgn:7029392"
    ],
    "tgn:id":2256188,
    "tgn:name":"Copper Spring Hollow",
    "tgn:placetype":[
        "aat:300008761"
    ]
},
  "bbox": [],
  "geometry": {"coordinates":[-92.5667,35.5],"type":"Point"}
}
=======
{"geometry":{"type":"Point","coordinates":[-92.566700,35.500000]},"type":"Feature","properties":{"hierarchy":["tgn:2256188","tgn:1000001","tgn:7016172","tgn:7012149","tgn:2000175","tgn:7029392"],"placetype":["aat:300008761"],"id":2256188,"name:xx":"Copper Spring Hollow"}}
>>>>>>> 03f74aca74312dbeaf24d7e61306dd6a786dc3d0
