{
  "id": 2655839,
  "type": "Feature",
  "properties": {
    "tgn:hierarchy":[
        "tgn:2655839",
        "tgn:7006450",
        "tgn:1000001",
        "tgn:7012149",
        "tgn:2124005",
        "tgn:7029392"
    ],
    "tgn:id":2655839,
    "tgn:name":"Shaviovik River",
    "tgn:placetype":[
        "aat:300008707"
    ]
},
  "bbox": [],
  "geometry": {"coordinates":[-146.95,69.2167],"type":"Point"}
}