{
  "id": 7471014,
  "type": "Feature",
  "properties": {
    "tgn:hierarchy":[
        "tgn:7471014",
        "tgn:1000004",
        "tgn:1000454",
        "tgn:1000141",
        "tgn:7029392"
    ],
    "tgn:id":7471014,
    "tgn:name":"Erbazhang",
    "tgn:placetype":[
        "aat:300008347"
    ]
},
  "bbox": [],
  "geometry": {"coordinates":[121.488502,24.99685],"type":"Point"}
}