<<<<<<< HEAD
{
  "id": 7471014,
  "type": "Feature",
  "properties": {
    "tgn:hierarchy":[
        "tgn:7471014",
        "tgn:1000004",
        "tgn:1000454",
        "tgn:1000141",
        "tgn:7029392"
    ],
    "tgn:id":7471014,
    "tgn:name":"Erbazhang",
    "tgn:placetype":[
        "aat:300008347"
    ]
},
  "bbox": [],
  "geometry": {"coordinates":[121.488502,24.99685],"type":"Point"}
}
=======
{"geometry":{"type":"Point","coordinates":[121.488502,24.996850]},"type":"Feature","properties":{"hierarchy":["tgn:7471014","tgn:1000004","tgn:1000454","tgn:1000141","tgn:7029392"],"placetype":["aat:300008347"],"id":7471014,"name:xx":"Erbazhang"}}
>>>>>>> 03f74aca74312dbeaf24d7e61306dd6a786dc3d0
