{
  "id": 7555162,
  "type": "Feature",
  "properties": {
    "tgn:hierarchy":[
        "tgn:7555162",
        "tgn:7016678",
        "tgn:7000204",
        "tgn:1006722",
        "tgn:1000004",
        "tgn:7000198",
        "tgn:7029392"
    ],
    "tgn:id":7555162,
    "tgn:name:en":"Oukchaung",
    "tgn:placetype":[
        "aat:300008347"
    ]
},
  "bbox": [],
  "geometry": {"coordinates":[92.716667,9.15],"type":"Point"}
}