{
  "id": 2406384,
  "type": "Feature",
  "properties": {
    "tgn:hierarchy":[
        "tgn:2406384",
        "tgn:1000001",
        "tgn:7012149",
        "tgn:7007826",
        "tgn:7029392"
    ],
    "tgn:id":2406384,
    "tgn:name":"Hunger Creek",
    "tgn:placetype":[
        "aat:300008706"
    ]
},
  "bbox": [],
  "geometry": {"coordinates":[-99.8667,30.0333],"type":"Point"}
}