{
  "id": 7288704,
  "type": "Feature",
  "properties": {
    "tgn:hierarchy":[
        "tgn:7288704",
        "tgn:1001768",
        "tgn:1000049",
        "tgn:1000002",
        "tgn:7029392"
    ],
    "tgn:id":7288704,
    "tgn:name":"Laguna Verde, Bah\u00eda",
    "tgn:placetype":[
        "aat:300132316"
    ]
},
  "bbox": [],
  "geometry": {"coordinates":[-71.717222,-33.066667],"type":"Point"}
}