<<<<<<< HEAD
{
  "id": 7028999,
  "type": "Feature",
  "properties": {
    "tgn:hierarchy":[
        "tgn:7028999",
        "tgn:7002445",
        "tgn:1000003",
        "tgn:7019064",
        "tgn:7008591",
        "tgn:7029392"
    ],
    "tgn:id":7028999,
    "tgn:name":"Stockton on the Forest",
    "tgn:placetype":[
        "aat:300008347",
        "aat:300008372"
    ]
},
  "bbox": [],
  "geometry": {"coordinates":[-1.0,53.984],"type":"Point"}
}
=======
{"geometry":{"type":"Point","coordinates":[-1.000000,53.984000]},"type":"Feature","properties":{"hierarchy":["tgn:7028999","tgn:7002445","tgn:1000003","tgn:7019064","tgn:7008591","tgn:7029392"],"placetype":["aat:300008347","aat:300008372"],"id":7028999,"name:xx":"Stockton on the Forest"}}
>>>>>>> 03f74aca74312dbeaf24d7e61306dd6a786dc3d0
