{
  "id": 2702015,
  "type": "Feature",
  "properties": {
    "tgn:hierarchy":[
        "tgn:2702015",
        "tgn:1000001",
        "tgn:7012149",
        "tgn:7007157",
        "tgn:1002957",
        "tgn:7029392"
    ],
    "tgn:id":2702015,
    "tgn:name":"Sugarpine Creek",
    "tgn:placetype":[
        "aat:300008706"
    ]
},
  "bbox": [],
  "geometry": {"coordinates":[-120.0833,38.1167],"type":"Point"}
}