{
  "id": 1099635,
  "type": "Feature",
  "properties": {
    "tgn:hierarchy":[
        "tgn:1099635",
        "tgn:1007992",
        "tgn:1001407",
        "tgn:1000233",
        "tgn:1000006",
        "tgn:7029392"
    ],
    "tgn:id":1099635,
    "tgn:name":"Oteotea",
    "tgn:placetype":[
        "aat:300008347"
    ]
},
  "bbox": [],
  "geometry": {"coordinates":[161.1833,-9.0833],"type":"Point"}
}