{
  "id": 1022725,
  "type": "Feature",
  "properties": {
    "tgn:hierarchy":[
        "tgn:1022725",
        "tgn:1001898",
        "tgn:7002454",
        "tgn:1000047",
        "tgn:1000002",
        "tgn:7029392"
    ],
    "tgn:id":1022725,
    "tgn:name":"Rochedinho",
    "tgn:placetype":[
        "aat:300008347"
    ]
},
  "bbox": [],
  "geometry": {"coordinates":[-54.55,-20.2333],"type":"Point"}
}