{
  "id": 1017996,
  "type": "Feature",
  "properties": {
    "tgn:hierarchy":[
        "tgn:1017996",
        "tgn:1000001",
        "tgn:7005590",
        "tgn:7005560",
        "tgn:7029392"
    ],
    "tgn:id":1017996,
    "tgn:name":"Panind\u00edcuaro",
    "tgn:placetype":[
        "aat:300008347"
    ]
},
  "bbox": [],
  "geometry": {"coordinates":[-101.766667,19.966667],"type":"Point"}
}