<<<<<<< HEAD
{
  "id": 7368236,
  "type": "Feature",
  "properties": {
    "tgn:hierarchy":[
        "tgn:7368236",
        "tgn:1000001",
        "tgn:7005595",
        "tgn:7005560",
        "tgn:7029392"
    ],
    "tgn:id":7368236,
    "tgn:name":"Jotagua",
    "tgn:placetype":[
        "aat:300008347"
    ]
},
  "bbox": [],
  "geometry": {"coordinates":[-107.270278,24.865],"type":"Point"}
}
=======
{"geometry":{"type":"Point","coordinates":[-107.270278,24.865000]},"type":"Feature","properties":{"hierarchy":["tgn:7368236","tgn:1000001","tgn:7005595","tgn:7005560","tgn:7029392"],"placetype":["aat:300008347"],"id":7368236,"name:xx":"Jotagua"}}
>>>>>>> 03f74aca74312dbeaf24d7e61306dd6a786dc3d0
