{
  "id": 7411850,
  "type": "Feature",
  "properties": {
    "tgn:hierarchy":[
        "tgn:7411850",
        "tgn:7005587",
        "tgn:1000001",
        "tgn:7005560",
        "tgn:7029392"
    ],
    "tgn:id":7411850,
    "tgn:name:es":"Ocomul",
    "tgn:placetype":[
        "aat:300008347"
    ]
},
  "bbox": [],
  "geometry": {"coordinates":[-98.302778,20.8125],"type":"Point"}
}