<<<<<<< HEAD
{
  "id": 7248669,
  "type": "Feature",
  "properties": {
    "tgn:hierarchy":[
        "tgn:7248669",
        "tgn:7003458",
        "tgn:1000003",
        "tgn:1000063",
        "tgn:7018236",
        "tgn:7029392"
    ],
    "tgn:id":7248669,
    "tgn:name":"Blauw Kasteel",
    "tgn:placetype":[
        "aat:300000206"
    ]
},
  "bbox": [],
  "geometry": {"coordinates":[3.283333,51.15],"type":"Point"}
}
=======
{"geometry":{"type":"Point","coordinates":[3.283333,51.150000]},"type":"Feature","properties":{"hierarchy":["tgn:7248669","tgn:7003458","tgn:1000003","tgn:1000063","tgn:7018236","tgn:7029392"],"placetype":["aat:300000206"],"id":7248669,"name:xx":"Blauw Kasteel"}}
>>>>>>> 03f74aca74312dbeaf24d7e61306dd6a786dc3d0
