{
  "id": 2351051,
  "type": "Feature",
  "properties": {
    "tgn:hierarchy":[
        "tgn:2351051",
        "tgn:1000001",
        "tgn:7012149",
        "tgn:7007157",
        "tgn:1002675",
        "tgn:7029392"
    ],
    "tgn:id":2351051,
    "tgn:name":"Glass Creek",
    "tgn:placetype":[
        "aat:300008706"
    ]
},
  "bbox": [],
  "geometry": {"coordinates":[-119.0667,37.7167],"type":"Point"}
}