{
  "id": 7591058,
  "type": "Feature",
  "properties": {
    "tgn:hierarchy":[
        "tgn:7591058",
        "tgn:1000004",
        "tgn:7000198",
        "tgn:7000799",
        "tgn:7029392"
    ],
    "tgn:id":7591058,
    "tgn:name:en":"Chak J\u0101far",
    "tgn:placetype":[
        "aat:300008347"
    ]
},
  "bbox": [],
  "geometry": {"coordinates":[74.745046,32.802025],"type":"Point"}
}