{
  "id": 2141102,
  "type": "Feature",
  "properties": {
    "tgn:hierarchy":[
        "tgn:2141102",
        "tgn:1000001",
        "tgn:7012149",
        "tgn:7007256",
        "tgn:7029392"
    ],
    "tgn:id":2141102,
    "tgn:name":"Avrico Canal",
    "tgn:placetype":[
        "aat:300006075"
    ]
},
  "bbox": [],
  "geometry": {"coordinates":[-92.4333,30.0167],"type":"Point"}
}