{
  "id": 7067923,
  "type": "Feature",
  "properties": {
    "tgn:hierarchy":[
        "tgn:7067923",
        "tgn:7003692",
        "tgn:1000003",
        "tgn:7000084",
        "tgn:7029392"
    ],
    "tgn:id":7067923,
    "tgn:name":"Torkel",
    "tgn:placetype":[
        "aat:300000206"
    ]
},
  "bbox": [],
  "geometry": {"coordinates":[9.333333,47.733333],"type":"Point"}
}