{
  "id": 7225344,
  "type": "Feature",
  "properties": {
    "tgn:hierarchy":[
        "tgn:7225344",
        "tgn:7002739",
        "tgn:7017076",
        "tgn:1000003",
        "tgn:1000074",
        "tgn:7029392"
    ],
    "tgn:id":7225344,
    "tgn:name":"Stef\u00e1nion",
    "tgn:placetype":[
        "aat:300008347"
    ]
},
  "bbox": [],
  "geometry": {"coordinates":[22.833333,37.75],"type":"Point"}
}