{
  "id": 7234871,
  "type": "Feature",
  "properties": {
    "tgn:hierarchy":[
        "tgn:7234871",
        "tgn:7002748",
        "tgn:7001399",
        "tgn:1000003",
        "tgn:1000074",
        "tgn:7029392"
    ],
    "tgn:id":7234871,
    "tgn:name":"Arg\u00fdrion",
    "tgn:placetype":[
        "aat:300008347"
    ]
},
  "bbox": [],
  "geometry": {"coordinates":[21.416111,39.192778],"type":"Point"}
}