{
  "id": 7375676,
  "type": "Feature",
  "properties": {
    "tgn:hierarchy":[
        "tgn:7375676",
        "tgn:1000001",
        "tgn:1001960",
        "tgn:7005560",
        "tgn:7029392"
    ],
    "tgn:id":7375676,
    "tgn:name":"Rancho La Rastra",
    "tgn:placetype":[
        "aat:300000241"
    ]
},
  "bbox": [],
  "geometry": {"coordinates":[-111.366667,30.216667],"type":"Point"}
}