<<<<<<< HEAD
{
  "id": 2250454,
  "type": "Feature",
  "properties": {
    "tgn:hierarchy":[
        "tgn:2250454",
        "tgn:1000001",
        "tgn:2001748",
        "tgn:7012149",
        "tgn:7007712",
        "tgn:7029392"
    ],
    "tgn:id":2250454,
    "tgn:name":"Colonial Heights",
    "tgn:placetype":[
        "aat:300008347"
    ]
},
  "bbox": [],
  "geometry": {"coordinates":[-82.0167,34.1667],"type":"Point"}
}
=======
{"geometry":{"type":"Point","coordinates":[-82.016700,34.166700]},"type":"Feature","properties":{"hierarchy":["tgn:2250454","tgn:1000001","tgn:2001748","tgn:7012149","tgn:7007712","tgn:7029392"],"placetype":["aat:300008347"],"id":2250454,"name:xx":"Colonial Heights"}}
>>>>>>> 03f74aca74312dbeaf24d7e61306dd6a786dc3d0
