{
  "id": 7510635,
  "type": "Feature",
  "properties": {
    "tgn:hierarchy":[
        "tgn:7510635",
        "tgn:1009227",
        "tgn:1000226",
        "tgn:7016822",
        "tgn:1000006",
        "tgn:7029392"
    ],
    "tgn:id":7510635,
    "tgn:name:en":"Te Awainanga",
    "tgn:placetype":[
        "aat:300008699"
    ]
},
  "bbox": [],
  "geometry": {"coordinates":[-176.416667,-43.966667],"type":"Point"}
}