<<<<<<< HEAD
{
  "id": 2250949,
  "type": "Feature",
  "properties": {
    "tgn:hierarchy":[
        "tgn:2250949",
        "tgn:1000001",
        "tgn:7012149",
        "tgn:7007708",
        "tgn:7029392"
    ],
    "tgn:id":2250949,
    "tgn:name":"Columbia Wilderness",
    "tgn:placetype":[
        "aat:300008863"
    ]
},
  "bbox": [],
  "geometry": {"coordinates":[-121.8333,45.5833],"type":"Point"}
}
=======
{"geometry":{"type":"Point","coordinates":[-121.833300,45.583300]},"type":"Feature","properties":{"hierarchy":["tgn:2250949","tgn:1000001","tgn:7012149","tgn:7007708","tgn:7029392"],"placetype":["aat:300008863"],"id":2250949,"name:xx":"Columbia Wilderness"}}
>>>>>>> 03f74aca74312dbeaf24d7e61306dd6a786dc3d0
