{
  "id": 7358614,
  "type": "Feature",
  "properties": {
    "tgn:hierarchy":[
        "tgn:7358614",
        "tgn:1000001",
        "tgn:7005589",
        "tgn:7005560",
        "tgn:7029392"
    ],
    "tgn:id":7358614,
    "tgn:name":"Ejido Vista Hermosa",
    "tgn:placetype":[
        "aat:300008347"
    ]
},
  "bbox": [],
  "geometry": {"coordinates":[-99.636667,24.769167],"type":"Point"}
}