{
  "id": 2708950,
  "type": "Feature",
  "properties": {
    "tgn:hierarchy":[
        "tgn:2708950",
        "tgn:1000001",
        "tgn:7012149",
        "tgn:2001312",
        "tgn:7007524",
        "tgn:7029392"
    ],
    "tgn:id":2708950,
    "tgn:name":"T C Drop Dam Reservoir",
    "tgn:placetype":[
        "aat:300006191"
    ]
},
  "bbox": [],
  "geometry": {"coordinates":[-106.9833,47.9833],"type":"Point"}
}