{
  "id": 7515636,
  "type": "Feature",
  "properties": {
    "tgn:hierarchy":[
        "tgn:7515636",
        "tgn:7000509",
        "tgn:1008380",
        "tgn:1000226",
        "tgn:1000006",
        "tgn:7029392"
    ],
    "tgn:id":7515636,
    "tgn:name:en":"Motunau",
    "tgn:placetype":[
        "aat:300008791"
    ]
},
  "bbox": [],
  "geometry": {"coordinates":[176.566667,-37.666667],"type":"Point"}
}