{
  "id": 1016379,
  "type": "Feature",
  "properties": {
    "tgn:hierarchy":[
        "tgn:1016379",
        "tgn:1001271",
        "tgn:1000001",
        "tgn:7004624",
        "tgn:7029392"
    ],
    "tgn:id":1016379,
    "tgn:name":"Mabay",
    "tgn:placetype":[
        "aat:300008347"
    ]
},
  "bbox": [],
  "geometry": {"coordinates":[-76.6667,20.2667],"type":"Point"}
}