{
  "id": 7325943,
  "type": "Feature",
  "properties": {
    "tgn:hierarchy":[
        "tgn:7325943",
        "tgn:7002759",
        "tgn:7002845",
        "tgn:1000003",
        "tgn:1000095",
        "tgn:7029392"
    ],
    "tgn:id":7325943,
    "tgn:name":"San Juli\u00e1n, Barranco de",
    "tgn:placetype":[
        "aat:300008699"
    ]
},
  "bbox": [],
  "geometry": {"coordinates":[-0.75,42.283333],"type":"Point"}
}