{
  "id": 2732034,
  "type": "Feature",
  "properties": {
    "tgn:hierarchy":[
        "tgn:2732034",
        "tgn:1000001",
        "tgn:2001841",
        "tgn:7012149",
        "tgn:7007825",
        "tgn:7029392"
    ],
    "tgn:id":2732034,
    "tgn:name":"Tunnel Branch",
    "tgn:placetype":[
        "aat:300008699"
    ]
},
  "bbox": [],
  "geometry": {"coordinates":[-83.9333,35.4667],"type":"Point"}
}