{
  "id": 1139121,
  "type": "Feature",
  "properties": {
    "tgn:hierarchy":[
        "tgn:1139121",
        "tgn:1000004",
        "tgn:7002084",
        "tgn:1000111",
        "tgn:7029392"
    ],
    "tgn:id":1139121,
    "tgn:name":"Huaxian",
    "tgn:placetype":[
        "aat:300008347"
    ]
},
  "bbox": [],
  "geometry": {"coordinates":[109.7833,34.55],"type":"Point"}
}