{
  "id": 7499269,
  "type": "Feature",
  "properties": {
    "tgn:hierarchy":[
        "tgn:7499269",
        "tgn:1000004",
        "tgn:7001009",
        "tgn:1000141",
        "tgn:7029392"
    ],
    "tgn:id":7499269,
    "tgn:name":"Hengping",
    "tgn:placetype":[
        "aat:300008347"
    ]
},
  "bbox": [],
  "geometry": {"coordinates":[120.800712,24.240471],"type":"Point"}
}