{
  "id": 2212217,
  "type": "Feature",
  "properties": {
    "tgn:hierarchy":[
        "tgn:2212217",
        "tgn:1000001",
        "tgn:7012149",
        "tgn:2000447",
        "tgn:7007248",
        "tgn:7029392"
    ],
    "tgn:id":2212217,
    "tgn:name":"Buzzard Roost",
    "tgn:placetype":[
        "aat:300008905"
    ]
},
  "bbox": [],
  "geometry": {"coordinates":[-83.25,31.8667],"type":"Point"}
}