{
  "id": 7003320,
  "type": "Feature",
  "properties": {
    "tgn:hierarchy":[
        "tgn:7003320",
        "tgn:7003321",
        "tgn:7003030",
        "tgn:1000003",
        "tgn:1000062",
        "tgn:7029392"
    ],
    "tgn:id":7003320,
    "tgn:name":"Neuwaldegg",
    "tgn:placetype":[
        "aat:300000874"
    ]
},
  "bbox": [],
  "geometry": {"coordinates":[16.2833,48.2333],"type":"Point"}
}