<<<<<<< HEAD
{
  "id": 2334843,
  "type": "Feature",
  "properties": {
    "tgn:hierarchy":[
        "tgn:2334843",
        "tgn:1000001",
        "tgn:7012149",
        "tgn:7007709",
        "tgn:7029392"
    ],
    "tgn:id":2334843,
    "tgn:name":"Fork Swamp",
    "tgn:placetype":[
        "aat:300008699"
    ]
},
  "bbox": [],
  "geometry": {"coordinates":[-77.1167,35.4],"type":"Point"}
}
=======
{"geometry":{"type":"Point","coordinates":[-77.116700,35.400000]},"type":"Feature","properties":{"hierarchy":["tgn:2334843","tgn:1000001","tgn:7012149","tgn:7007709","tgn:7029392"],"placetype":["aat:300008699"],"id":2334843,"name:xx":"Fork Swamp"}}
>>>>>>> 03f74aca74312dbeaf24d7e61306dd6a786dc3d0
