{
  "id": 7407857,
  "type": "Feature",
  "properties": {
    "tgn:hierarchy":[
        "tgn:7407857",
        "tgn:1000001",
        "tgn:1001893",
        "tgn:7005560",
        "tgn:7029392"
    ],
    "tgn:id":7407857,
    "tgn:name":"El Porvenir",
    "tgn:placetype":[
        "aat:300008347"
    ]
},
  "bbox": [],
  "geometry": {"coordinates":[-100.075,19.725],"type":"Point"}
}