{
  "id": 7017068,
  "type": "Feature",
  "properties": {
    "tgn:hierarchy":[
        "tgn:7017068",
        "tgn:1000003",
        "tgn:7002885",
        "tgn:1000070",
        "tgn:7029392"
    ],
    "tgn:id":7017068,
    "tgn:name":"Lunel",
    "tgn:placetype":[
        "aat:300008347"
    ]
},
  "bbox": [],
  "geometry": {"coordinates":[4.1333,43.6667],"type":"Point"}
}