{
  "id": 1107180,
  "type": "Feature",
  "properties": {
    "tgn:hierarchy":[
        "tgn:1107180",
        "tgn:7018591",
        "tgn:7005559",
        "tgn:1000001",
        "tgn:7005556",
        "tgn:7029392"
    ],
    "tgn:id":1107180,
    "tgn:name":"Catherines Peak",
    "tgn:placetype":[
        "aat:300008795",
        "aat:300008798"
    ]
},
  "bbox": [],
  "geometry": {"coordinates":[-76.702,18.076],"type":"Point"}
}