{
  "id": 1066670,
  "type": "Feature",
  "properties": {
    "tgn:hierarchy":[
        "tgn:1066670",
        "tgn:1000004",
        "tgn:7002087",
        "tgn:1000111",
        "tgn:7029392"
    ],
    "tgn:id":1066670,
    "tgn:name":"Baishaba",
    "tgn:placetype":[
        "aat:300008347"
    ]
},
  "bbox": [],
  "geometry": {"coordinates":[106.35,30.05],"type":"Point"}
}