<<<<<<< HEAD
{
  "id": 2258925,
  "type": "Feature",
  "properties": {
    "tgn:hierarchy":[
        "tgn:2258925",
        "tgn:1000001",
        "tgn:7012149",
        "tgn:7007526",
        "tgn:7029392"
    ],
    "tgn:id":2258925,
    "tgn:name":"Cottonwood Creek",
    "tgn:placetype":[
        "aat:300008706"
    ]
},
  "bbox": [],
  "geometry": {"coordinates":[-117.2,39.1333],"type":"Point"}
}
=======
{"geometry":{"type":"Point","coordinates":[-117.200000,39.133300]},"type":"Feature","properties":{"hierarchy":["tgn:2258925","tgn:1000001","tgn:7012149","tgn:7007526","tgn:7029392"],"placetype":["aat:300008706"],"id":2258925,"name:xx":"Cottonwood Creek"}}
>>>>>>> 03f74aca74312dbeaf24d7e61306dd6a786dc3d0
