<<<<<<< HEAD
{
  "id": 7054705,
  "type": "Feature",
  "properties": {
    "tgn:hierarchy":[
        "tgn:7054705",
        "tgn:7003170",
        "tgn:1000003",
        "tgn:7003125",
        "tgn:1000080",
        "tgn:7029392"
    ],
    "tgn:id":7054705,
    "tgn:name":"Pompagnano",
    "tgn:placetype":[
        "aat:300008347"
    ]
},
  "bbox": [],
  "geometry": {"coordinates":[12.7,42.683333],"type":"Point"}
}
=======
{"geometry":{"type":"Point","coordinates":[12.700000,42.683333]},"type":"Feature","properties":{"hierarchy":["tgn:7054705","tgn:7003170","tgn:1000003","tgn:7003125","tgn:1000080","tgn:7029392"],"placetype":["aat:300008347"],"id":7054705,"name:xx":"Pompagnano"}}
>>>>>>> 03f74aca74312dbeaf24d7e61306dd6a786dc3d0
