{
  "id": 7269528,
  "type": "Feature",
  "properties": {
    "tgn:concordances":{
        "gn:id":"2751079"
    },
    "tgn:hierarchy":[
        "tgn:7269528",
        "tgn:1000003",
        "tgn:7003622",
        "tgn:7016845",
        "tgn:7029392"
    ],
    "tgn:id":7269528,
    "tgn:name:nl":"Maxet",
    "tgn:placetype":[
        "aat:300008347"
    ]
},
  "bbox": [],
  "geometry": {"coordinates":[5.866667,51.25],"type":"Point"}
}