{
  "id": 2692926,
  "type": "Feature",
  "properties": {
    "tgn:hierarchy":[
        "tgn:2692926",
        "tgn:7030515",
        "tgn:7006450",
        "tgn:1000001",
        "tgn:7012149",
        "tgn:7029392"
    ],
    "tgn:id":2692926,
    "tgn:name":"Steelhead Creek",
    "tgn:placetype":[
        "aat:300008706"
    ]
},
  "bbox": [],
  "geometry": {"coordinates":[-161.9333,55.5833],"type":"Point"}
}