{
  "id": 7301529,
  "type": "Feature",
  "properties": {
    "tgn:hierarchy":[
        "tgn:7301529",
        "tgn:7002824",
        "tgn:1000003",
        "tgn:7002786",
        "tgn:1000095",
        "tgn:7029392"
    ],
    "tgn:id":7301529,
    "tgn:name":"Mira, R\u00edo",
    "tgn:placetype":[
        "aat:300008699"
    ]
},
  "bbox": [],
  "geometry": {"coordinates":[-8.766667,43.083333],"type":"Point"}
}