{
  "id": 2630797,
  "type": "Feature",
  "properties": {
    "tgn:hierarchy":[
        "tgn:2630797",
        "tgn:1000001",
        "tgn:7012149",
        "tgn:2000882",
        "tgn:7007256",
        "tgn:7029392"
    ],
    "tgn:id":2630797,
    "tgn:name":"Round Lake",
    "tgn:placetype":[
        "aat:300132316"
    ]
},
  "bbox": [],
  "geometry": {"coordinates":[-90.1667,29.4667],"type":"Point"}
}