{
  "id": 2669659,
  "type": "Feature",
  "properties": {
    "tgn:hierarchy":[
        "tgn:2669659",
        "tgn:1000001",
        "tgn:7012149",
        "tgn:2001274",
        "tgn:7007524",
        "tgn:7029392"
    ],
    "tgn:id":2669659,
    "tgn:name":"Slideout Peak",
    "tgn:placetype":[
        "aat:300008798"
    ]
},
  "bbox": [],
  "geometry": {"coordinates":[-113.05,48.0167],"type":"Point"}
}