{
  "id": 7088030,
  "type": "Feature",
  "properties": {
    "tgn:hierarchy":[
        "tgn:7088030",
        "tgn:1000003",
        "tgn:7003687",
        "tgn:7000084",
        "tgn:7029392"
    ],
    "tgn:id":7088030,
    "tgn:name":"Wedderstedt",
    "tgn:placetype":[
        "aat:300008347"
    ]
},
  "bbox": [],
  "geometry": {"coordinates":[11.233333,51.833333],"type":"Point"}
}