{
  "id": 2636908,
  "type": "Feature",
  "properties": {
    "tgn:hierarchy":[
        "tgn:2636908",
        "tgn:1000001",
        "tgn:7012149",
        "tgn:2001713",
        "tgn:7007708",
        "tgn:7029392"
    ],
    "tgn:id":2636908,
    "tgn:name":"Sailor Gulch",
    "tgn:placetype":[
        "aat:300008761"
    ]
},
  "bbox": [],
  "geometry": {"coordinates":[-123.6333,42.5333],"type":"Point"}
}