{
  "id": 2264194,
  "type": "Feature",
  "properties": {
    "tgn:hierarchy":[
        "tgn:2264194",
        "tgn:1000001",
        "tgn:7012149",
        "tgn:7029392"
    ],
    "tgn:id":2264194,
    "tgn:name":"Coyote Valley",
    "tgn:placetype":[
        "aat:300008761"
    ]
},
  "bbox": [],
  "geometry": {"coordinates":[-112.0667,36.85],"type":"Point"}
}