{
  "id": 7416223,
  "type": "Feature",
  "properties": {
    "tgn:hierarchy":[
        "tgn:7416223",
        "tgn:1000001",
        "tgn:7005591",
        "tgn:7005560",
        "tgn:7029392"
    ],
    "tgn:id":7416223,
    "tgn:name:es":"Cruz Grande",
    "tgn:placetype":[
        "aat:300008347"
    ]
},
  "bbox": [],
  "geometry": {"coordinates":[-96.445556,15.946944],"type":"Point"}
}