{
  "id": 7576424,
  "type": "Feature",
  "properties": {
    "tgn:hierarchy":[
        "tgn:7576424",
        "tgn:1000004",
        "tgn:7000198",
        "tgn:7000799",
        "tgn:7029392"
    ],
    "tgn:id":7576424,
    "tgn:name:en":"K\u0101ndhot",
    "tgn:placetype":[
        "aat:300008347"
    ]
},
  "bbox": [],
  "geometry": {"coordinates":[75.722752,33.143197],"type":"Point"}
}