{
  "id": 2499201,
  "type": "Feature",
  "properties": {
    "tgn:hierarchy":[
        "tgn:2499201",
        "tgn:2002238",
        "tgn:1000001",
        "tgn:7012149",
        "tgn:7007920",
        "tgn:7029392"
    ],
    "tgn:id":2499201,
    "tgn:name":"McChesney Spring",
    "tgn:placetype":[
        "aat:300008697"
    ]
},
  "bbox": [],
  "geometry": {"coordinates":[-118.5333,46.7667],"type":"Point"}
}