<<<<<<< HEAD
{
  "id": 7052416,
  "type": "Feature",
  "properties": {
    "tgn:hierarchy":[
        "tgn:7052416",
        "tgn:1003429",
        "tgn:1000003",
        "tgn:7003240",
        "tgn:1000080",
        "tgn:7029392"
    ],
    "tgn:id":7052416,
    "tgn:name":"Montoro",
    "tgn:placetype":[
        "aat:300008347"
    ]
},
  "bbox": [],
  "geometry": {"coordinates":[13.416667,43.45],"type":"Point"}
}
=======
{"geometry":{"type":"Point","coordinates":[13.416667,43.450000]},"type":"Feature","properties":{"hierarchy":["tgn:7052416","tgn:1003429","tgn:1000003","tgn:7003240","tgn:1000080","tgn:7029392"],"placetype":["aat:300008347"],"id":7052416,"name:xx":"Montoro"}}
>>>>>>> 03f74aca74312dbeaf24d7e61306dd6a786dc3d0
