{
  "id": 7588369,
  "type": "Feature",
  "properties": {
    "tgn:hierarchy":[
        "tgn:7588369",
        "tgn:1000004",
        "tgn:7000198",
        "tgn:1003539",
        "tgn:7029392"
    ],
    "tgn:id":7588369,
    "tgn:name:en":"Mawdem",
    "tgn:placetype":[
        "aat:300008347"
    ]
},
  "bbox": [],
  "geometry": {"coordinates":[91.973607,25.227796],"type":"Point"}
}