{
  "id": 2422305,
  "type": "Feature",
  "properties": {
    "tgn:hierarchy":[
        "tgn:2422305",
        "tgn:1000001",
        "tgn:2000923",
        "tgn:7012149",
        "tgn:7007515",
        "tgn:7029392"
    ],
    "tgn:id":2422305,
    "tgn:name":"Jimmie Pond",
    "tgn:placetype":[
        "aat:300008680"
    ]
},
  "bbox": [],
  "geometry": {"coordinates":[-69.85,44.2667],"type":"Point"}
}