{
  "id": 2201023,
  "type": "Feature",
  "properties": {
    "tgn:hierarchy":[
        "tgn:2201023",
        "tgn:1000001",
        "tgn:7012149",
        "tgn:7007709",
        "tgn:7029392"
    ],
    "tgn:id":2201023,
    "tgn:name":"Bryants Knob",
    "tgn:placetype":[
        "aat:300008798"
    ]
},
  "bbox": [],
  "geometry": {"coordinates":[-80.9667,36.3833],"type":"Point"}
}