{
  "id": 1108357,
  "type": "Feature",
  "properties": {
    "tgn:hierarchy":[
        "tgn:1108357",
        "tgn:1000001",
        "tgn:7012149",
        "tgn:7007157",
        "tgn:1002857",
        "tgn:7029392"
    ],
    "tgn:id":1108357,
    "tgn:name":"Cajon Summit",
    "tgn:placetype":[
        "aat:300259572"
    ]
},
  "bbox": [],
  "geometry": {"coordinates":[-117.4333,34.3333],"type":"Point"}
}