{
  "id": 2386300,
  "type": "Feature",
  "properties": {
    "tgn:hierarchy":[
        "tgn:2386300",
        "tgn:1000001",
        "tgn:7012149",
        "tgn:2002274",
        "tgn:7013961",
        "tgn:7029392"
    ],
    "tgn:id":2386300,
    "tgn:name":"Hensley Knob",
    "tgn:placetype":[
        "aat:300008798"
    ]
},
  "bbox": [],
  "geometry": {"coordinates":[-81.7333,37.4833],"type":"Point"}
}