{
  "id": 2280585,
  "type": "Feature",
  "properties": {
    "tgn:hierarchy":[
        "tgn:2280585",
        "tgn:1000001",
        "tgn:7012149",
        "tgn:2001151",
        "tgn:7007522",
        "tgn:7029392"
    ],
    "tgn:id":2280585,
    "tgn:name":"Deep Branch",
    "tgn:placetype":[
        "aat:300008699"
    ]
},
  "bbox": [],
  "geometry": {"coordinates":[-88.8833,30.85],"type":"Point"}
}