{
  "id": 2311410,
  "type": "Feature",
  "properties": {
    "tgn:hierarchy":[
        "tgn:2311410",
        "tgn:1000001",
        "tgn:7012149",
        "tgn:1002392",
        "tgn:7007157",
        "tgn:7029392"
    ],
    "tgn:id":2311410,
    "tgn:name":"Edmiston",
    "tgn:placetype":[
        "aat:300008347"
    ]
},
  "bbox": [],
  "geometry": {"coordinates":[-119.5333,36.7667],"type":"Point"}
}