{
  "id": 2539897,
  "type": "Feature",
  "properties": {
    "tgn:hierarchy":[
        "tgn:2539897",
        "tgn:1000001",
        "tgn:7012149",
        "tgn:7007157",
        "tgn:1002675",
        "tgn:7029392"
    ],
    "tgn:id":2539897,
    "tgn:name":"New York Hill",
    "tgn:placetype":[
        "aat:300008798"
    ]
},
  "bbox": [],
  "geometry": {"coordinates":[-119.1167,38.35],"type":"Point"}
}