{
  "id": 2201553,
  "type": "Feature",
  "properties": {
    "tgn:hierarchy":[
        "tgn:2201553",
        "tgn:1000001",
        "tgn:7012149",
        "tgn:7007157",
        "tgn:2000186",
        "tgn:7029392"
    ],
    "tgn:id":2201553,
    "tgn:name":"Buck Creek",
    "tgn:placetype":[
        "aat:300008706"
    ]
},
  "bbox": [],
  "geometry": {"coordinates":[-120.25,41.8833],"type":"Point"}
}