{
  "id": 1034878,
  "type": "Feature",
  "properties": {
    "tgn:hierarchy":[
        "tgn:1034878",
        "tgn:1000003",
        "tgn:7012216",
        "tgn:1000070",
        "tgn:7029392"
    ],
    "tgn:id":1034878,
    "tgn:name":"Plo\u00ebrmel",
    "tgn:placetype":[
        "aat:300008347"
    ]
},
  "bbox": [],
  "geometry": {"coordinates":[-2.3833,47.9333],"type":"Point"}
}