{
  "id": 7485276,
  "type": "Feature",
  "properties": {
    "tgn:hierarchy":[
        "tgn:7485276",
        "tgn:1000004",
        "tgn:7492971",
        "tgn:1000141",
        "tgn:7029392"
    ],
    "tgn:id":7485276,
    "tgn:name":"Wanyinggong Ci",
    "tgn:placetype":[
        "aat:300007595"
    ]
},
  "bbox": [],
  "geometry": {"coordinates":[120.692222,22.187222],"type":"Point"}
}