<<<<<<< HEAD
{
  "id": 2156071,
  "type": "Feature",
  "properties": {
    "tgn:hierarchy":[
        "tgn:2156071",
        "tgn:1000001",
        "tgn:7012149",
        "tgn:1002516",
        "tgn:7007255",
        "tgn:7029392"
    ],
    "tgn:id":2156071,
    "tgn:name":"Bearcamp Run",
    "tgn:placetype":[
        "aat:300008699"
    ]
},
  "bbox": [],
  "geometry": {"coordinates":[-85.7833,38.0667],"type":"Point"}
}
=======
{"geometry":{"type":"Point","coordinates":[-85.783300,38.066700]},"type":"Feature","properties":{"hierarchy":["tgn:2156071","tgn:1000001","tgn:7012149","tgn:1002516","tgn:7007255","tgn:7029392"],"placetype":["aat:300008699"],"id":2156071,"name:xx":"Bearcamp Run"}}
>>>>>>> 03f74aca74312dbeaf24d7e61306dd6a786dc3d0
