{
  "id": 2712807,
  "type": "Feature",
  "properties": {
    "tgn:hierarchy":[
        "tgn:2712807",
        "tgn:1000001",
        "tgn:7012149",
        "tgn:2002384",
        "tgn:7007923",
        "tgn:7029392"
    ],
    "tgn:id":2712807,
    "tgn:name":"Taylor Creek",
    "tgn:placetype":[
        "aat:300008706"
    ]
},
  "bbox": [],
  "geometry": {"coordinates":[-110.9167,43.3833],"type":"Point"}
}