<<<<<<< HEAD
{
  "id": 2331270,
  "type": "Feature",
  "properties": {
    "tgn:hierarchy":[
        "tgn:2331270",
        "tgn:1000001",
        "tgn:7012149",
        "tgn:2000392",
        "tgn:7007248",
        "tgn:7029392"
    ],
    "tgn:id":2331270,
    "tgn:name":"Flat, The",
    "tgn:placetype":[
        "aat:300008905"
    ]
},
  "bbox": [],
  "geometry": {"coordinates":[-84.1833,31.25],"type":"Point"}
}
=======
{"geometry":{"type":"Point","coordinates":[-84.183300,31.250000]},"type":"Feature","properties":{"hierarchy":["tgn:2331270","tgn:1000001","tgn:7012149","tgn:2000392","tgn:7007248","tgn:7029392"],"placetype":["aat:300008905"],"id":2331270,"name:xx":"Flat, The"}}
>>>>>>> 03f74aca74312dbeaf24d7e61306dd6a786dc3d0
