{
  "id": 1139628,
  "type": "Feature",
  "properties": {
    "tgn:hierarchy":[
        "tgn:1139628",
        "tgn:1000004",
        "tgn:1001390",
        "tgn:1000111",
        "tgn:7029392"
    ],
    "tgn:id":1139628,
    "tgn:name":"Shuangtaizi",
    "tgn:placetype":[
        "aat:300008347"
    ]
},
  "bbox": [],
  "geometry": {"coordinates":[121.2333,41.1833],"type":"Point"}
}