{
  "id": 7249410,
  "type": "Feature",
  "properties": {
    "tgn:hierarchy":[
        "tgn:7249410",
        "tgn:7003457",
        "tgn:1000003",
        "tgn:1000063",
        "tgn:7018236",
        "tgn:7029392"
    ],
    "tgn:id":7249410,
    "tgn:name":"Oudenhoek",
    "tgn:placetype":[
        "aat:300008347"
    ]
},
  "bbox": [],
  "geometry": {"coordinates":[3.854564,50.963031],"type":"Point"}
}