{
  "id": 2523939,
  "type": "Feature",
  "properties": {
    "tgn:hierarchy":[
        "tgn:2523939",
        "tgn:1000001",
        "tgn:7012149",
        "tgn:2000810",
        "tgn:7007255",
        "tgn:7029392"
    ],
    "tgn:id":2523939,
    "tgn:name":"Moreland Hollow",
    "tgn:placetype":[
        "aat:300008761"
    ]
},
  "bbox": [],
  "geometry": {"coordinates":[-83.75,37.6833],"type":"Point"}
}