<<<<<<< HEAD
{
  "id": 2336018,
  "type": "Feature",
  "properties": {
    "tgn:hierarchy":[
        "tgn:2336018",
        "tgn:1000001",
        "tgn:7012149",
        "tgn:2002250",
        "tgn:7007920",
        "tgn:7029392"
    ],
    "tgn:id":2336018,
    "tgn:name":"Foster Canyon",
    "tgn:placetype":[
        "aat:300008761"
    ]
},
  "bbox": [],
  "geometry": {"coordinates":[-117.8333,48.45],"type":"Point"}
}
=======
{"geometry":{"type":"Point","coordinates":[-117.833300,48.450000]},"type":"Feature","properties":{"hierarchy":["tgn:2336018","tgn:1000001","tgn:7012149","tgn:2002250","tgn:7007920","tgn:7029392"],"placetype":["aat:300008761"],"id":2336018,"name:xx":"Foster Canyon"}}
>>>>>>> 03f74aca74312dbeaf24d7e61306dd6a786dc3d0
