{
  "id": 2336018,
  "type": "Feature",
  "properties": {
    "tgn:hierarchy":[
        "tgn:2336018",
        "tgn:1000001",
        "tgn:7012149",
        "tgn:2002250",
        "tgn:7007920",
        "tgn:7029392"
    ],
    "tgn:id":2336018,
    "tgn:name":"Foster Canyon",
    "tgn:placetype":[
        "aat:300008761"
    ]
},
  "bbox": [],
  "geometry": {"coordinates":[-117.8333,48.45],"type":"Point"}
}