{
  "id": 2746410,
  "type": "Feature",
  "properties": {
    "tgn:hierarchy":[
        "tgn:2746410",
        "tgn:1000001",
        "tgn:7006451",
        "tgn:2000095",
        "tgn:7012149",
        "tgn:7029392"
    ],
    "tgn:id":2746410,
    "tgn:name":"W S Mountain",
    "tgn:placetype":[
        "aat:300008798"
    ]
},
  "bbox": [],
  "geometry": {"coordinates":[-109.0667,33.5167],"type":"Point"}
}