{
  "id": 7264957,
  "type": "Feature",
  "properties": {
    "tgn:concordances":{
        "gn:id":"2753553"
    },
    "tgn:hierarchy":[
        "tgn:7264957",
        "tgn:1000003",
        "tgn:7003624",
        "tgn:7016845",
        "tgn:7029392"
    ],
    "tgn:id":7264957,
    "tgn:name:nl":"Houterd",
    "tgn:placetype":[
        "aat:300008347"
    ]
},
  "bbox": [],
  "geometry": {"coordinates":[5.433333,51.65],"type":"Point"}
}