{
  "id": 2667389,
  "type": "Feature",
  "properties": {
    "tgn:hierarchy":[
        "tgn:2667389",
        "tgn:1000001",
        "tgn:1002260",
        "tgn:7012149",
        "tgn:7007920",
        "tgn:7029392"
    ],
    "tgn:id":2667389,
    "tgn:name":"Skinney Creek",
    "tgn:placetype":[
        "aat:300008706"
    ]
},
  "bbox": [],
  "geometry": {"coordinates":[-120.7667,47.7333],"type":"Point"}
}