{
  "id": 7573116,
  "type": "Feature",
  "properties": {
    "tgn:hierarchy":[
        "tgn:7573116",
        "tgn:7001819",
        "tgn:1000004",
        "tgn:7000198",
        "tgn:7029392"
    ],
    "tgn:id":7573116,
    "tgn:name:en":"Idilin",
    "tgn:placetype":[
        "aat:300008347"
    ]
},
  "bbox": [],
  "geometry": {"coordinates":[96.005254,28.668746],"type":"Point"}
}