{
  "id": 7023272,
  "type": "Feature",
  "properties": {
    "tgn:hierarchy":[
        "tgn:7023272",
        "tgn:1000001",
        "tgn:7012149",
        "tgn:7007520",
        "tgn:7029392"
    ],
    "tgn:id":7023272,
    "tgn:name":"Little Robinson Lake",
    "tgn:placetype":[
        "aat:300008680"
    ]
},
  "bbox": [],
  "geometry": {"coordinates":[-85.8167,43.5167],"type":"Point"}
}