<<<<<<< HEAD
{
  "id": 7360578,
  "type": "Feature",
  "properties": {
    "tgn:hierarchy":[
        "tgn:7360578",
        "tgn:1001853",
        "tgn:1000001",
        "tgn:7005560",
        "tgn:7029392"
    ],
    "tgn:id":7360578,
    "tgn:name":"Codornices",
    "tgn:placetype":[
        "aat:300008347"
    ]
},
  "bbox": [],
  "geometry": {"coordinates":[-103.266667,25.616667],"type":"Point"}
}
=======
{"geometry":{"type":"Point","coordinates":[-103.266667,25.616667]},"type":"Feature","properties":{"hierarchy":["tgn:7360578","tgn:1001853","tgn:1000001","tgn:7005560","tgn:7029392"],"placetype":["aat:300008347"],"id":7360578,"name:xx":"Codornices"}}
>>>>>>> 03f74aca74312dbeaf24d7e61306dd6a786dc3d0
