{
  "id": 7560993,
  "type": "Feature",
  "properties": {
    "tgn:hierarchy":[
        "tgn:7560993",
        "tgn:1000004",
        "tgn:7000198",
        "tgn:7016722",
        "tgn:7029392"
    ],
    "tgn:id":7560993,
    "tgn:name:en":"T\u0101t\u0101rpur",
    "tgn:placetype":[
        "aat:300008347"
    ]
},
  "bbox": [],
  "geometry": {"coordinates":[79.136672,27.845772],"type":"Point"}
}