{
  "id": 7234861,
  "type": "Feature",
  "properties": {
    "tgn:hierarchy":[
        "tgn:7234861",
        "tgn:7002690",
        "tgn:7012056",
        "tgn:1000003",
        "tgn:1000074",
        "tgn:7029392"
    ],
    "tgn:id":7234861,
    "tgn:name":"Aryiro\u00fapolis",
    "tgn:placetype":[
        "aat:300008347"
    ]
},
  "bbox": [],
  "geometry": {"coordinates":[24.333333,35.283333],"type":"Point"}
}