{
  "id": 2493457,
  "type": "Feature",
  "properties": {
    "tgn:hierarchy":[
        "tgn:2493457",
        "tgn:1000001",
        "tgn:7012149",
        "tgn:7007256",
        "tgn:7029392"
    ],
    "tgn:id":2493457,
    "tgn:name":"Marsh Bayou",
    "tgn:placetype":[
        "aat:300008699"
    ]
},
  "bbox": [],
  "geometry": {"coordinates":[-93.1833,30.4833],"type":"Point"}
}