{
  "id": 7443528,
  "type": "Feature",
  "properties": {
    "tgn:hierarchy":[
        "tgn:7443528",
        "tgn:7002445",
        "tgn:1000003",
        "tgn:7008168",
        "tgn:7008591",
        "tgn:7029392"
    ],
    "tgn:id":7443528,
    "tgn:name:en":"Tiddington",
    "tgn:placetype":[
        "aat:300007783"
    ]
},
  "bbox": [],
  "geometry": {"coordinates":[-1.066667,51.733333],"type":"Point"}
}