<<<<<<< HEAD
{
  "id": 7478927,
  "type": "Feature",
  "properties": {
    "tgn:hierarchy":[
        "tgn:7478927",
        "tgn:1000004",
        "tgn:7489179",
        "tgn:1000141",
        "tgn:7029392"
    ],
    "tgn:id":7478927,
    "tgn:name":"Yueming Xincun",
    "tgn:placetype":[
        "aat:300000498"
    ]
},
  "bbox": [],
  "geometry": {"coordinates":[121.857769,24.61054],"type":"Point"}
}
=======
{"geometry":{"type":"Point","coordinates":[121.857769,24.610540]},"type":"Feature","properties":{"hierarchy":["tgn:7478927","tgn:1000004","tgn:7489179","tgn:1000141","tgn:7029392"],"placetype":["aat:300000498"],"id":7478927,"name:xx":"Yueming Xincun"}}
>>>>>>> 03f74aca74312dbeaf24d7e61306dd6a786dc3d0
