{
  "id": 2652521,
  "type": "Feature",
  "properties": {
    "tgn:hierarchy":[
        "tgn:2652521",
        "tgn:1000001",
        "tgn:7012149",
        "tgn:1002954",
        "tgn:7007826",
        "tgn:7029392"
    ],
    "tgn:id":2652521,
    "tgn:name":"Sentell Lake",
    "tgn:placetype":[
        "aat:300006191"
    ]
},
  "bbox": [],
  "geometry": {"coordinates":[-95.3833,30.95],"type":"Point"}
}