{
  "id": 7444609,
  "type": "Feature",
  "properties": {
    "tgn:hierarchy":[
        "tgn:7444609",
        "tgn:7002445",
        "tgn:1000003",
        "tgn:7008166",
        "tgn:7008591",
        "tgn:7029392"
    ],
    "tgn:id":7444609,
    "tgn:name:en":"West Cottingwith",
    "tgn:placetype":[
        "aat:300008347"
    ]
},
  "bbox": [],
  "geometry": {"coordinates":[-0.95,53.85],"type":"Point"}
}