{
  "id": 2541305,
  "type": "Feature",
  "properties": {
    "tgn:hierarchy":[
        "tgn:2541305",
        "tgn:1000001",
        "tgn:7012149",
        "tgn:2001050",
        "tgn:7007521",
        "tgn:7029392"
    ],
    "tgn:id":2541305,
    "tgn:name":"Nicollet Bay",
    "tgn:placetype":[
        "aat:300132316"
    ]
},
  "bbox": [],
  "geometry": {"coordinates":[-94.2167,44.2833],"type":"Point"}
}