{
  "id": 2286463,
  "type": "Feature",
  "properties": {
    "tgn:hierarchy":[
        "tgn:2286463",
        "tgn:1000001",
        "tgn:7012149",
        "tgn:7007252",
        "tgn:7029392"
    ],
    "tgn:id":2286463,
    "tgn:name":"Diamond Creek",
    "tgn:placetype":[
        "aat:300008706"
    ]
},
  "bbox": [],
  "geometry": {"coordinates":[-87.15,39.6167],"type":"Point"}
}