{
  "id": 7277389,
  "type": "Feature",
  "properties": {
    "tgn:hierarchy":[
        "tgn:7277389",
        "tgn:1001702",
        "tgn:1000049",
        "tgn:1000002",
        "tgn:7029392"
    ],
    "tgn:id":7277389,
    "tgn:name":"Wyatt, Bah\u00eda",
    "tgn:placetype":[
        "aat:300132316"
    ]
},
  "bbox": [],
  "geometry": {"coordinates":[-69.316667,-55.516667],"type":"Point"}
}