{
  "id": 2596667,
  "type": "Feature",
  "properties": {
    "tgn:hierarchy":[
        "tgn:2596667",
        "tgn:1000001",
        "tgn:7012149",
        "tgn:2000826",
        "tgn:7007255",
        "tgn:7029392"
    ],
    "tgn:id":2596667,
    "tgn:name":"Powell Branch",
    "tgn:placetype":[
        "aat:300008699"
    ]
},
  "bbox": [],
  "geometry": {"coordinates":[-83.5833,37.8333],"type":"Point"}
}