{
  "id": 1044999,
  "type": "Feature",
  "properties": {
    "tgn:hierarchy":[
        "tgn:1044999",
        "tgn:7003128",
        "tgn:1000003",
        "tgn:7008516",
        "tgn:1000080",
        "tgn:7029392"
    ],
    "tgn:id":1044999,
    "tgn:name":"Lagosanto",
    "tgn:placetype":[
        "aat:300008347"
    ]
},
  "bbox": [],
  "geometry": {"coordinates":[12.143611,44.758611],"type":"Point"}
}