<<<<<<< HEAD
{
  "id": 2151473,
  "type": "Feature",
  "properties": {
    "tgn:hierarchy":[
        "tgn:2151473",
        "tgn:1000001",
        "tgn:7012149",
        "tgn:2002124",
        "tgn:7007827",
        "tgn:7029392"
    ],
    "tgn:id":2151473,
    "tgn:name":"Bathtub Trough",
    "tgn:placetype":[
        "aat:300008761"
    ]
},
  "bbox": [],
  "geometry": {"coordinates":[-109.9667,40.5667],"type":"Point"}
}
=======
{"geometry":{"type":"Point","coordinates":[-109.966700,40.566700]},"type":"Feature","properties":{"hierarchy":["tgn:2151473","tgn:1000001","tgn:7012149","tgn:2002124","tgn:7007827","tgn:7029392"],"placetype":["aat:300008761"],"id":2151473,"name:xx":"Bathtub Trough"}}
>>>>>>> 03f74aca74312dbeaf24d7e61306dd6a786dc3d0
