{
  "id": 1023432,
  "type": "Feature",
  "properties": {
    "tgn:hierarchy":[
        "tgn:1023432",
        "tgn:7593328",
        "tgn:1000049",
        "tgn:1000002",
        "tgn:7029392"
    ],
    "tgn:id":1023432,
    "tgn:name":"Corral",
    "tgn:placetype":[
        "aat:300008347"
    ]
},
  "bbox": [],
  "geometry": {"coordinates":[-73.433333,-39.866667],"type":"Point"}
}