{
  "id": 2554157,
  "type": "Feature",
  "properties": {
    "tgn:hierarchy":[
        "tgn:2554157",
        "tgn:1000001",
        "tgn:7012149",
        "tgn:2002120",
        "tgn:7007827",
        "tgn:7029392"
    ],
    "tgn:id":2554157,
    "tgn:name":"Oak Ridge Spring",
    "tgn:placetype":[
        "aat:300008697"
    ]
},
  "bbox": [],
  "geometry": {"coordinates":[-111.4167,39.4167],"type":"Point"}
}