{
  "id": 7524376,
  "type": "Feature",
  "properties": {
    "tgn:hierarchy":[
        "tgn:7524376",
        "tgn:7001242",
        "tgn:7016833",
        "tgn:1001335",
        "tgn:7029392"
    ],
    "tgn:id":7524376,
    "tgn:name:en":"Bis\u0101\u0163, Ra's",
    "tgn:placetype":[
        "aat:300386846"
    ]
},
  "bbox": [],
  "geometry": {"coordinates":[30.685278,31.453611],"type":"Point"}
}