{
  "id": 7400717,
  "type": "Feature",
  "properties": {
    "tgn:hierarchy":[
        "tgn:7400717",
        "tgn:1000001",
        "tgn:7005599",
        "tgn:7005560",
        "tgn:7029392"
    ],
    "tgn:id":7400717,
    "tgn:name":"Barranca de Lim\u00f3n",
    "tgn:placetype":[
        "aat:300008347"
    ]
},
  "bbox": [],
  "geometry": {"coordinates":[-95.638889,18.55],"type":"Point"}
}