{
  "id": 7208125,
  "type": "Feature",
  "properties": {
    "tgn:hierarchy":[
        "tgn:7208125",
        "tgn:1000003",
        "tgn:7003677",
        "tgn:7000084",
        "tgn:7029392"
    ],
    "tgn:id":7208125,
    "tgn:name":"Colonia Ulpia Traiana",
    "tgn:placetype":[
        "aat:300387007"
    ]
},
  "bbox": [],
  "geometry": {"coordinates":[6.45,51.666667],"type":"Point"}
}