{
  "id": 2644694,
  "type": "Feature",
  "properties": {
    "tgn:hierarchy":[
        "tgn:2644694",
        "tgn:1000001",
        "tgn:7012149",
        "tgn:2002122",
        "tgn:7007827",
        "tgn:7029392"
    ],
    "tgn:id":2644694,
    "tgn:name":"Sargent Lake",
    "tgn:placetype":[
        "aat:300008680"
    ]
},
  "bbox": [],
  "geometry": {"coordinates":[-110.3833,40.9167],"type":"Point"}
}