{
  "id": 7303286,
  "type": "Feature",
  "properties": {
    "tgn:hierarchy":[
        "tgn:7303286",
        "tgn:7007088",
        "tgn:1000003",
        "tgn:7009604",
        "tgn:1000095",
        "tgn:7029392"
    ],
    "tgn:id":7303286,
    "tgn:name":"Oyardo",
    "tgn:placetype":[
        "aat:300008347"
    ]
},
  "bbox": [],
  "geometry": {"coordinates":[-2.928181,42.988852],"type":"Point"}
}