{
  "id": 2391193,
  "type": "Feature",
  "properties": {
    "tgn:hierarchy":[
        "tgn:2391193",
        "tgn:1000001",
        "tgn:7012149",
        "tgn:2001288",
        "tgn:7007524",
        "tgn:7029392"
    ],
    "tgn:id":2391193,
    "tgn:name":"Hill Reservoir",
    "tgn:placetype":[
        "aat:300006191"
    ]
},
  "bbox": [],
  "geometry": {"coordinates":[-112.0333,45.5333],"type":"Point"}
}