<<<<<<< HEAD
{
  "id": 7249995,
  "type": "Feature",
  "properties": {
    "tgn:hierarchy":[
        "tgn:7249995",
        "tgn:7003456",
        "tgn:1000003",
        "tgn:1000063",
        "tgn:7018236",
        "tgn:7029392"
    ],
    "tgn:id":7249995,
    "tgn:name":"Morkhoven",
    "tgn:placetype":[
        "aat:300008347"
    ]
},
  "bbox": [],
  "geometry": {"coordinates":[4.818774,51.11888],"type":"Point"}
}
=======
{"geometry":{"type":"Point","coordinates":[4.818774,51.118880]},"type":"Feature","properties":{"hierarchy":["tgn:7249995","tgn:7003456","tgn:1000003","tgn:1000063","tgn:7018236","tgn:7029392"],"placetype":["aat:300008347"],"id":7249995,"name:xx":"Morkhoven"}}
>>>>>>> 03f74aca74312dbeaf24d7e61306dd6a786dc3d0
