{
  "id": 2118567,
  "type": "Feature",
  "properties": {
    "tgn:hierarchy":[
        "tgn:2118567",
        "tgn:1000001",
        "tgn:7012149",
        "tgn:2002264",
        "tgn:7013961",
        "tgn:7029392"
    ],
    "tgn:id":2118567,
    "tgn:name":"Henning",
    "tgn:placetype":[
        "aat:300008347",
        "aat:300387210"
    ]
},
  "bbox": [],
  "geometry": {"coordinates":[-80.35,37.8833],"type":"Point"}
}