{
  "id": 7288177,
  "type": "Feature",
  "properties": {
    "tgn:hierarchy":[
        "tgn:7288177",
        "tgn:1001702",
        "tgn:1000049",
        "tgn:1000002",
        "tgn:7029392"
    ],
    "tgn:id":7288177,
    "tgn:name":"Hunter, Cabo",
    "tgn:placetype":[
        "aat:300386846"
    ]
},
  "bbox": [],
  "geometry": {"coordinates":[-72.866667,-53.45],"type":"Point"}
}