{
  "id": 7075043,
  "type": "Feature",
  "properties": {
    "tgn:hierarchy":[
        "tgn:7075043",
        "tgn:1000003",
        "tgn:7000094",
        "tgn:7000084",
        "tgn:7029392"
    ],
    "tgn:id":7075043,
    "tgn:name":"Thiessower Steintrendel",
    "tgn:placetype":[
        "aat:300011692"
    ]
},
  "bbox": [],
  "geometry": {"coordinates":[13.766667,54.266667],"type":"Point"}
}