{
  "id": 7430706,
  "type": "Feature",
  "properties": {
    "tgn:hierarchy":[
        "tgn:7430706",
        "tgn:1001853",
        "tgn:1000001",
        "tgn:7005560",
        "tgn:7029392"
    ],
    "tgn:id":7430706,
    "tgn:name":"Mar\u00edas",
    "tgn:placetype":[
        "aat:300008347"
    ]
},
  "bbox": [],
  "geometry": {"coordinates":[-102.766667,27.233333],"type":"Point"}
}