{
  "id": 2424843,
  "type": "Feature",
  "properties": {
    "tgn:hierarchy":[
        "tgn:2424843",
        "tgn:1000001",
        "tgn:7012149",
        "tgn:2000224",
        "tgn:7007158",
        "tgn:7029392"
    ],
    "tgn:id":2424843,
    "tgn:name":"Johnson Gulch",
    "tgn:placetype":[
        "aat:300008761"
    ]
},
  "bbox": [],
  "geometry": {"coordinates":[-106.25,39.25],"type":"Point"}
}