{
  "id": 1083426,
  "type": "Feature",
  "properties": {
    "tgn:hierarchy":[
        "tgn:1083426",
        "tgn:1000004",
        "tgn:1001490",
        "tgn:1000133",
        "tgn:7029392"
    ],
    "tgn:id":1083426,
    "tgn:name":"Derawar Fort",
    "tgn:placetype":[
        "aat:300008347"
    ]
},
  "bbox": [],
  "geometry": {"coordinates":[71.3333,28.7667],"type":"Point"}
}