{
  "id": 7523398,
  "type": "Feature",
  "properties": {
    "tgn:hierarchy":[
        "tgn:7523398",
        "tgn:7001242",
        "tgn:7016833",
        "tgn:1001335",
        "tgn:7029392"
    ],
    "tgn:id":7523398,
    "tgn:name:en":"Bash\u0101r\u016bsh, Jaz\u012brat al",
    "tgn:placetype":[
        "aat:300008791"
    ]
},
  "bbox": [],
  "geometry": {"coordinates":[30.801306,31.452553],"type":"Point"}
}