{
  "id": 2368026,
  "type": "Feature",
  "properties": {
    "tgn:hierarchy":[
        "tgn:2368026",
        "tgn:1000001",
        "tgn:7012149",
        "tgn:2001284",
        "tgn:7007524",
        "tgn:7029392"
    ],
    "tgn:id":2368026,
    "tgn:name":"Gruells Bar Mine",
    "tgn:placetype":[
        "aat:300000390"
    ]
},
  "bbox": [],
  "geometry": {"coordinates":[-111.7333,46.65],"type":"Point"}
}