{
  "id": 7040814,
  "type": "Feature",
  "properties": {
    "tgn:hierarchy":[
        "tgn:7040814",
        "tgn:7003163",
        "tgn:1000003",
        "tgn:7009760",
        "tgn:1000080",
        "tgn:7029392"
    ],
    "tgn:id":7040814,
    "tgn:name":"Santa Maria a Vezzano",
    "tgn:placetype":[
        "aat:300008347"
    ]
},
  "bbox": [],
  "geometry": {"coordinates":[11.45,43.983333],"type":"Point"}
}