<<<<<<< HEAD
{
  "id": 2151991,
  "type": "Feature",
  "properties": {
    "tgn:hierarchy":[
        "tgn:2151991",
        "tgn:1000001",
        "tgn:7012149",
        "tgn:2000421",
        "tgn:7007248",
        "tgn:7029392"
    ],
    "tgn:id":2151991,
    "tgn:name":"Baughville",
    "tgn:placetype":[
        "aat:300008347"
    ]
},
  "bbox": [],
  "geometry": {"coordinates":[-84.6667,32.65],"type":"Point"}
}
=======
{"geometry":{"type":"Point","coordinates":[-84.666700,32.650000]},"type":"Feature","properties":{"hierarchy":["tgn:2151991","tgn:1000001","tgn:7012149","tgn:2000421","tgn:7007248","tgn:7029392"],"placetype":["aat:300008347"],"id":2151991,"name:xx":"Baughville"}}
>>>>>>> 03f74aca74312dbeaf24d7e61306dd6a786dc3d0
