<<<<<<< HEAD
{
  "id": 7171114,
  "type": "Feature",
  "properties": {
    "tgn:hierarchy":[
        "tgn:7171114",
        "tgn:1000003",
        "tgn:7003682",
        "tgn:7000084",
        "tgn:7029392"
    ],
    "tgn:id":7171114,
    "tgn:name":"Himmel-Berg",
    "tgn:placetype":[
        "aat:300008777"
    ]
},
  "bbox": [],
  "geometry": {"coordinates":[7.85,50.433333],"type":"Point"}
}
=======
{"geometry":{"type":"Point","coordinates":[7.850000,50.433333]},"type":"Feature","properties":{"hierarchy":["tgn:7171114","tgn:1000003","tgn:7003682","tgn:7000084","tgn:7029392"],"placetype":["aat:300008777"],"id":7171114,"name:xx":"Himmel-Berg"}}
>>>>>>> 03f74aca74312dbeaf24d7e61306dd6a786dc3d0
