{
  "id": 7407122,
  "type": "Feature",
  "properties": {
    "tgn:hierarchy":[
        "tgn:7407122",
        "tgn:7005585",
        "tgn:1000001",
        "tgn:7005560",
        "tgn:7029392"
    ],
    "tgn:id":7407122,
    "tgn:name":"Los Pinos",
    "tgn:placetype":[
        "aat:300008347"
    ]
},
  "bbox": [],
  "geometry": {"coordinates":[-100.683333,17.316667],"type":"Point"}
}