{
  "id": 7345716,
  "type": "Feature",
  "properties": {
    "tgn:hierarchy":[
        "tgn:7345716",
        "tgn:7002849",
        "tgn:1000003",
        "tgn:7009604",
        "tgn:1000095",
        "tgn:7029392"
    ],
    "tgn:id":7345716,
    "tgn:name":"Albiz",
    "tgn:placetype":[
        "aat:300008347"
    ]
},
  "bbox": [],
  "geometry": {"coordinates":[-2.639042,43.260467],"type":"Point"}
}