{
  "id": 2301908,
  "type": "Feature",
  "properties": {
    "tgn:hierarchy":[
        "tgn:2301908",
        "tgn:7013349",
        "tgn:1000001",
        "tgn:7012149",
        "tgn:7007708",
        "tgn:7029392"
    ],
    "tgn:id":2301908,
    "tgn:name":"Durkee Valley",
    "tgn:placetype":[
        "aat:300008761"
    ]
},
  "bbox": [],
  "geometry": {"coordinates":[-117.5167,44.5667],"type":"Point"}
}