{
  "id": 7592974,
  "type": "Feature",
  "properties": {
    "tgn:hierarchy":[
        "tgn:7592974",
        "tgn:1000004",
        "tgn:7000198",
        "tgn:7000799",
        "tgn:7029392"
    ],
    "tgn:id":7592974,
    "tgn:name:en":"Assarw\u0101n",
    "tgn:placetype":[
        "aat:300008347"
    ]
},
  "bbox": [],
  "geometry": {"coordinates":[74.776546,32.8221],"type":"Point"}
}