{
  "id": 7509314,
  "type": "Feature",
  "properties": {
    "tgn:hierarchy":[
        "tgn:7509314",
        "tgn:1009227",
        "tgn:7001866",
        "tgn:1000226",
        "tgn:1000006",
        "tgn:7029392"
    ],
    "tgn:id":7509314,
    "tgn:name:en":"Thomas, Mount",
    "tgn:placetype":[
        "aat:300008795"
    ]
},
  "bbox": [],
  "geometry": {"coordinates":[172.35,-43.166667],"type":"Point"}
}