{
  "id": 2655585,
  "type": "Feature",
  "properties": {
    "tgn:hierarchy":[
        "tgn:2655585",
        "tgn:1000001",
        "tgn:7012149",
        "tgn:7021277",
        "tgn:7007707",
        "tgn:7029392"
    ],
    "tgn:id":2655585,
    "tgn:name":"Sharper Creek",
    "tgn:placetype":[
        "aat:300008706"
    ]
},
  "bbox": [],
  "geometry": {"coordinates":[-95.75,35.3167],"type":"Point"}
}