{
  "id": 2459463,
  "type": "Feature",
  "properties": {
    "tgn:hierarchy":[
        "tgn:2459463",
        "tgn:1000001",
        "tgn:7012149",
        "tgn:2001221",
        "tgn:7007523",
        "tgn:7029392"
    ],
    "tgn:id":2459463,
    "tgn:name":"Little Proctor Creek",
    "tgn:placetype":[
        "aat:300008706"
    ]
},
  "bbox": [],
  "geometry": {"coordinates":[-92.8833,38.25],"type":"Point"}
}