<<<<<<< HEAD
{
  "id": 2154569,
  "type": "Feature",
  "properties": {
    "tgn:hierarchy":[
        "tgn:2154569",
        "tgn:1000001",
        "tgn:7012149",
        "tgn:7007705",
        "tgn:7029392"
    ],
    "tgn:id":2154569,
    "tgn:name":"Bear Den Creek",
    "tgn:placetype":[
        "aat:300008706"
    ]
},
  "bbox": [],
  "geometry": {"coordinates":[-102.9167,47.7333],"type":"Point"}
}
=======
{"geometry":{"type":"Point","coordinates":[-102.916700,47.733300]},"type":"Feature","properties":{"hierarchy":["tgn:2154569","tgn:1000001","tgn:7012149","tgn:7007705","tgn:7029392"],"placetype":["aat:300008706"],"id":2154569,"name:xx":"Bear Den Creek"}}
>>>>>>> 03f74aca74312dbeaf24d7e61306dd6a786dc3d0
