{
  "id": 7343490,
  "type": "Feature",
  "properties": {
    "tgn:hierarchy":[
        "tgn:7343490",
        "tgn:1001439",
        "tgn:1000003",
        "tgn:7002797",
        "tgn:1000095",
        "tgn:7029392"
    ],
    "tgn:id":7343490,
    "tgn:name":"Casas del Moj\u00f3n",
    "tgn:placetype":[
        "aat:300008347"
    ]
},
  "bbox": [],
  "geometry": {"coordinates":[-0.966667,37.616667],"type":"Point"}
}