{
  "id": 2231410,
  "type": "Feature",
  "properties": {
    "tgn:hierarchy":[
        "tgn:2231410",
        "tgn:1000001",
        "tgn:2001181",
        "tgn:7012149",
        "tgn:7007523",
        "tgn:7029392"
    ],
    "tgn:id":2231410,
    "tgn:name":"Chalk Bank Hollow",
    "tgn:placetype":[
        "aat:300008761"
    ]
},
  "bbox": [],
  "geometry": {"coordinates":[-90.8667,36.9333],"type":"Point"}
}