{
  "id": 7086785,
  "type": "Feature",
  "properties": {
    "tgn:hierarchy":[
        "tgn:7086785",
        "tgn:7003669",
        "tgn:1000003",
        "tgn:7000084",
        "tgn:7029392"
    ],
    "tgn:id":7086785,
    "tgn:name":"Waldheim",
    "tgn:placetype":[
        "aat:300008347"
    ]
},
  "bbox": [],
  "geometry": {"coordinates":[10.45,49.433333],"type":"Point"}
}