{
  "id": 2657875,
  "type": "Feature",
  "properties": {
    "tgn:hierarchy":[
        "tgn:2657875",
        "tgn:1002933",
        "tgn:1000001",
        "tgn:7012149",
        "tgn:7007239",
        "tgn:7029392"
    ],
    "tgn:id":2657875,
    "tgn:name":"Shell Landing Cove",
    "tgn:placetype":[
        "aat:300132316"
    ]
},
  "bbox": [],
  "geometry": {"coordinates":[-75.1333,38.65],"type":"Point"}
}