{
  "id": 1021742,
  "type": "Feature",
  "properties": {
    "tgn:hierarchy":[
        "tgn:1021742",
        "tgn:7005437",
        "tgn:1000047",
        "tgn:7002455",
        "tgn:1000002",
        "tgn:7029392"
    ],
    "tgn:id":1021742,
    "tgn:name":"Itapetim",
    "tgn:placetype":[
        "aat:300008347"
    ]
},
  "bbox": [],
  "geometry": {"coordinates":[-37.1833,-7.3667],"type":"Point"}
}