{
  "id": 1111007,
  "type": "Feature",
  "properties": {
    "tgn:hierarchy":[
        "tgn:1111007",
        "tgn:7002445",
        "tgn:1000003",
        "tgn:7012077",
        "tgn:7008591",
        "tgn:7029392"
    ],
    "tgn:id":1111007,
    "tgn:name":"South Hams",
    "tgn:placetype":[
        "aat:300008805"
    ]
},
  "bbox": [],
  "geometry": {"coordinates":[-3.8333,50.3667],"type":"Point"}
}