{
  "id": 7324501,
  "type": "Feature",
  "properties": {
    "tgn:hierarchy":[
        "tgn:7324501",
        "tgn:7002818",
        "tgn:1001647",
        "tgn:1000003",
        "tgn:1000095",
        "tgn:7029392"
    ],
    "tgn:id":7324501,
    "tgn:name":"Santa Mar\u00eda de los Llanos",
    "tgn:placetype":[
        "aat:300008347"
    ]
},
  "bbox": [],
  "geometry": {"coordinates":[-2.866667,39.483333],"type":"Point"}
}