{
  "id": 2001253,
  "type": "Feature",
  "properties": {
    "tgn:hierarchy":[
        "tgn:2001253",
        "tgn:1000001",
        "tgn:7012149",
        "tgn:7007523",
        "tgn:7029392"
    ],
    "tgn:id":2001253,
    "tgn:name":"Vernon",
    "tgn:placetype":[
        "aat:300387145",
        "aat:300000771"
    ]
},
  "bbox": [],
  "geometry": {"coordinates":[-94.35,37.85],"type":"Point"}
}