{
  "id": 7141863,
  "type": "Feature",
  "properties": {
    "tgn:hierarchy":[
        "tgn:7141863",
        "tgn:1000003",
        "tgn:7003677",
        "tgn:7000084",
        "tgn:7029392"
    ],
    "tgn:id":7141863,
    "tgn:name":"Lohrwardt",
    "tgn:placetype":[
        "aat:300000206"
    ]
},
  "bbox": [],
  "geometry": {"coordinates":[6.45,51.716667],"type":"Point"}
}