<<<<<<< HEAD
{
  "id": 2255195,
  "type": "Feature",
  "properties": {
    "tgn:hierarchy":[
        "tgn:2255195",
        "tgn:1000001",
        "tgn:7012149",
        "tgn:7007158",
        "tgn:2000250",
        "tgn:7029392"
    ],
    "tgn:id":2255195,
    "tgn:name":"Cooper Mountain",
    "tgn:placetype":[
        "aat:300008798"
    ]
},
  "bbox": [],
  "geometry": {"coordinates":[-105.8167,39.6],"type":"Point"}
}
=======
{"geometry":{"type":"Point","coordinates":[-105.816700,39.600000]},"type":"Feature","properties":{"hierarchy":["tgn:2255195","tgn:1000001","tgn:7012149","tgn:7007158","tgn:2000250","tgn:7029392"],"placetype":["aat:300008798"],"id":2255195,"name:xx":"Cooper Mountain"}}
>>>>>>> 03f74aca74312dbeaf24d7e61306dd6a786dc3d0
