{
  "id": 2465312,
  "type": "Feature",
  "properties": {
    "tgn:hierarchy":[
        "tgn:2465312",
        "tgn:1000001",
        "tgn:7012149",
        "tgn:2002377",
        "tgn:7007923",
        "tgn:7029392"
    ],
    "tgn:id":2465312,
    "tgn:name":"Lone Bear Ditch Number 2",
    "tgn:placetype":[
        "aat:300006075"
    ]
},
  "bbox": [],
  "geometry": {"coordinates":[-106.1167,42.6667],"type":"Point"}
}