{
  "id": 7561649,
  "type": "Feature",
  "properties": {
    "tgn:hierarchy":[
        "tgn:7561649",
        "tgn:1000004",
        "tgn:7000198",
        "tgn:7016722",
        "tgn:7029392"
    ],
    "tgn:id":7561649,
    "tgn:name:en":"Ballam ka Nagla",
    "tgn:placetype":[
        "aat:300008347"
    ]
},
  "bbox": [],
  "geometry": {"coordinates":[79.097324,26.813221],"type":"Point"}
}