{
  "id": 7300986,
  "type": "Feature",
  "properties": {
    "tgn:hierarchy":[
        "tgn:7300986",
        "tgn:7002758",
        "tgn:7002821",
        "tgn:1000003",
        "tgn:1000095",
        "tgn:7029392"
    ],
    "tgn:id":7300986,
    "tgn:name":"Montilla, Sierra de",
    "tgn:placetype":[
        "aat:300266640"
    ]
},
  "bbox": [],
  "geometry": {"coordinates":[-2.533333,37.883333],"type":"Point"}
}