{
  "id": 2636002,
  "type": "Feature",
  "properties": {
    "tgn:hierarchy":[
        "tgn:2636002",
        "tgn:1000001",
        "tgn:2001816",
        "tgn:7012149",
        "tgn:7007713",
        "tgn:7029392"
    ],
    "tgn:id":2636002,
    "tgn:name":"Saddle Butte",
    "tgn:placetype":[
        "aat:300008798"
    ]
},
  "bbox": [],
  "geometry": {"coordinates":[-102.8833,44.7667],"type":"Point"}
}