{
  "id": 4011505,
  "type": "Feature",
  "properties": {
    "tgn:hierarchy":[
        "tgn:4011505",
        "tgn:7002445",
        "tgn:1000003",
        "tgn:7008118",
        "tgn:7008591",
        "tgn:7029392"
    ],
    "tgn:id":4011505,
    "tgn:name:en":"Unstone",
    "tgn:placetype":[
        "aat:300008347"
    ]
},
  "bbox": [],
  "geometry": {"coordinates":[-1.433333,53.283333],"type":"Point"}
}