{
  "id": 2658104,
  "type": "Feature",
  "properties": {
    "tgn:hierarchy":[
        "tgn:2658104",
        "tgn:1000001",
        "tgn:7012149",
        "tgn:7029392"
    ],
    "tgn:id":2658104,
    "tgn:name":"Shelter Brook",
    "tgn:placetype":[
        "aat:300008699"
    ]
},
  "bbox": [],
  "geometry": {"coordinates":[-70.9833,44.5333],"type":"Point"}
}