{
  "id": 2089489,
  "type": "Feature",
  "properties": {
    "tgn:hierarchy":[
        "tgn:2089489",
        "tgn:1000001",
        "tgn:1002266",
        "tgn:7012149",
        "tgn:7007710",
        "tgn:7029392"
    ],
    "tgn:id":2089489,
    "tgn:name":"Icedale",
    "tgn:placetype":[
        "aat:300008347",
        "aat:300387210"
    ]
},
  "bbox": [],
  "geometry": {"coordinates":[-75.8167,40.0667],"type":"Point"}
}