{
  "id": 7309130,
  "type": "Feature",
  "properties": {
    "tgn:hierarchy":[
        "tgn:7309130",
        "tgn:1001705",
        "tgn:1000049",
        "tgn:1000002",
        "tgn:7029392"
    ],
    "tgn:id":7309130,
    "tgn:name":"Macal",
    "tgn:placetype":[
        "aat:300008347"
    ]
},
  "bbox": [],
  "geometry": {"coordinates":[-72.15,-35.183333],"type":"Point"}
}