{
  "id": 7590138,
  "type": "Feature",
  "properties": {
    "tgn:hierarchy":[
        "tgn:7590138",
        "tgn:1000004",
        "tgn:7000198",
        "tgn:7000799",
        "tgn:7029392"
    ],
    "tgn:id":7590138,
    "tgn:name:en":"Kin\u0101ri Forest",
    "tgn:placetype":[
        "aat:300008863"
    ]
},
  "bbox": [],
  "geometry": {"coordinates":[74.252778,33.854167],"type":"Point"}
}