{
  "id": 7585141,
  "type": "Feature",
  "properties": {
    "tgn:hierarchy":[
        "tgn:7585141",
        "tgn:1000004",
        "tgn:7000198",
        "tgn:7016788",
        "tgn:7029392"
    ],
    "tgn:id":7585141,
    "tgn:name:en":"Limri ki Dh\u0101ni",
    "tgn:placetype":[
        "aat:300008347"
    ]
},
  "bbox": [],
  "geometry": {"coordinates":[75.4673,28.1934],"type":"Point"}
}