{
  "id": 7561795,
  "type": "Feature",
  "properties": {
    "tgn:hierarchy":[
        "tgn:7561795",
        "tgn:1000004",
        "tgn:7000198",
        "tgn:7016722",
        "tgn:7029392"
    ],
    "tgn:id":7561795,
    "tgn:name:en":"Nagla Cham\u0101r\u0101n",
    "tgn:placetype":[
        "aat:300008347"
    ]
},
  "bbox": [],
  "geometry": {"coordinates":[79.277434,27.113406],"type":"Point"}
}