{
  "id": 2473758,
  "type": "Feature",
  "properties": {
    "tgn:hierarchy":[
        "tgn:2473758",
        "tgn:1000001",
        "tgn:7012149",
        "tgn:2000488",
        "tgn:7007250",
        "tgn:7029392"
    ],
    "tgn:id":2473758,
    "tgn:name":"Lower Flat Spring",
    "tgn:placetype":[
        "aat:300008697"
    ]
},
  "bbox": [],
  "geometry": {"coordinates":[-116.8667,43.0667],"type":"Point"}
}