{
  "id": 2094220,
  "type": "Feature",
  "properties": {
    "tgn:hierarchy":[
        "tgn:2094220",
        "tgn:1000001",
        "tgn:1002308",
        "tgn:7012149",
        "tgn:7007710",
        "tgn:7029392"
    ],
    "tgn:id":2094220,
    "tgn:name":"Watson Run",
    "tgn:placetype":[
        "aat:300008347",
        "aat:300387210"
    ]
},
  "bbox": [],
  "geometry": {"coordinates":[-80.2167,41.5833],"type":"Point"}
}