<<<<<<< HEAD
{
  "id": 2331284,
  "type": "Feature",
  "properties": {
    "tgn:hierarchy":[
        "tgn:2331284",
        "tgn:1000001",
        "tgn:7012149",
        "tgn:1002440",
        "tgn:7007568",
        "tgn:7029392"
    ],
    "tgn:id":2331284,
    "tgn:name":"Flatfish Pond",
    "tgn:placetype":[
        "aat:300008680"
    ]
},
  "bbox": [],
  "geometry": {"coordinates":[-74.5667,43.9667],"type":"Point"}
}
=======
{"geometry":{"type":"Point","coordinates":[-74.566700,43.966700]},"type":"Feature","properties":{"hierarchy":["tgn:2331284","tgn:1000001","tgn:7012149","tgn:1002440","tgn:7007568","tgn:7029392"],"placetype":["aat:300008680"],"id":2331284,"name:xx":"Flatfish Pond"}}
>>>>>>> 03f74aca74312dbeaf24d7e61306dd6a786dc3d0
