{
  "id": 2026808,
  "type": "Feature",
  "properties": {
    "tgn:hierarchy":[
        "tgn:2026808",
        "tgn:1000001",
        "tgn:7012149",
        "tgn:7019014",
        "tgn:7007251",
        "tgn:7029392"
    ],
    "tgn:id":2026808,
    "tgn:name":"Burtons Bridge",
    "tgn:placetype":[
        "aat:300008347"
    ]
},
  "bbox": [],
  "geometry": {"coordinates":[-88.2167,42.2667],"type":"Point"}
}