{
  "id": 2616523,
  "type": "Feature",
  "properties": {
    "tgn:hierarchy":[
        "tgn:2616523",
        "tgn:1000001",
        "tgn:7012149",
        "tgn:1002798",
        "tgn:7007252",
        "tgn:7029392"
    ],
    "tgn:id":2616523,
    "tgn:name":"Rice Lake",
    "tgn:placetype":[
        "aat:300006191"
    ]
},
  "bbox": [],
  "geometry": {"coordinates":[-86.9833,41.5833],"type":"Point"}
}