{
  "id": 7513846,
  "type": "Feature",
  "properties": {
    "tgn:hierarchy":[
        "tgn:7513846",
        "tgn:1009227",
        "tgn:1000226",
        "tgn:7016822",
        "tgn:1000006",
        "tgn:7029392"
    ],
    "tgn:id":7513846,
    "tgn:name:en":"Fish Rock",
    "tgn:placetype":[
        "aat:300011692"
    ]
},
  "bbox": [],
  "geometry": {"coordinates":[168.166667,-46.85],"type":"Point"}
}