{
  "id": 2662506,
  "type": "Feature",
  "properties": {
    "tgn:hierarchy":[
        "tgn:2662506",
        "tgn:1000001",
        "tgn:7012149",
        "tgn:1002669",
        "tgn:7007710",
        "tgn:7029392"
    ],
    "tgn:id":2662506,
    "tgn:name":"Siglerville Cave Number Three",
    "tgn:placetype":[
        "aat:300008746"
    ]
},
  "bbox": [],
  "geometry": {"coordinates":[-77.5167,40.7333],"type":"Point"}
}