{
  "id": 2471354,
  "type": "Feature",
  "properties": {
    "tgn:hierarchy":[
        "tgn:2471354",
        "tgn:1000001",
        "tgn:1002477",
        "tgn:7012149",
        "tgn:7007240",
        "tgn:7029392"
    ],
    "tgn:id":2471354,
    "tgn:name":"Lost Lake",
    "tgn:placetype":[
        "aat:300008680"
    ]
},
  "bbox": [],
  "geometry": {"coordinates":[-81.3667,27.2667],"type":"Point"}
}