{
  "id": 7366282,
  "type": "Feature",
  "properties": {
    "tgn:hierarchy":[
        "tgn:7366282",
        "tgn:1000001",
        "tgn:1001893",
        "tgn:7005560",
        "tgn:7029392"
    ],
    "tgn:id":7366282,
    "tgn:name":"Escorpio, Cerro",
    "tgn:placetype":[
        "aat:300008795"
    ]
},
  "bbox": [],
  "geometry": {"coordinates":[-99.116667,19.566667],"type":"Point"}
}