{
  "id": 2667662,
  "type": "Feature",
  "properties": {
    "tgn:hierarchy":[
        "tgn:2667662",
        "tgn:1000001",
        "tgn:7012149",
        "tgn:2001284",
        "tgn:7007524",
        "tgn:7029392"
    ],
    "tgn:id":2667662,
    "tgn:name":"Skull Gulch",
    "tgn:placetype":[
        "aat:300008761"
    ]
},
  "bbox": [],
  "geometry": {"coordinates":[-112.5167,47.2333],"type":"Point"}
}