{
  "id": 7017218,
  "type": "Feature",
  "properties": {
    "tgn:hierarchy":[
        "tgn:7017218",
        "tgn:7002871",
        "tgn:1000003",
        "tgn:1000070",
        "tgn:7029392"
    ],
    "tgn:id":7017218,
    "tgn:name":"Puy de D\u00f4me",
    "tgn:placetype":[
        "aat:300008795"
    ]
},
  "bbox": [],
  "geometry": {"coordinates":[2.9333,45.7667],"type":"Point"}
}