{
  "id": 2508790,
  "type": "Feature",
  "properties": {
    "tgn:hierarchy":[
        "tgn:2508790",
        "tgn:7006450",
        "tgn:1000001",
        "tgn:7012149",
        "tgn:2000086",
        "tgn:7029392"
    ],
    "tgn:id":2508790,
    "tgn:name":"Middle Fork Bremner River",
    "tgn:placetype":[
        "aat:300008707"
    ]
},
  "bbox": [],
  "geometry": {"coordinates":[-143.55,60.8667],"type":"Point"}
}