{
  "id": 7406389,
  "type": "Feature",
  "properties": {
    "tgn:hierarchy":[
        "tgn:7406389",
        "tgn:7005585",
        "tgn:1000001",
        "tgn:7005560",
        "tgn:7029392"
    ],
    "tgn:id":7406389,
    "tgn:name":"La Yerbabuena",
    "tgn:placetype":[
        "aat:300008347"
    ]
},
  "bbox": [],
  "geometry": {"coordinates":[-99.916667,18.433333],"type":"Point"}
}