<<<<<<< HEAD
{
  "id": 7485246,
  "type": "Feature",
  "properties": {
    "tgn:hierarchy":[
        "tgn:7485246",
        "tgn:1000004",
        "tgn:7492971",
        "tgn:1000141",
        "tgn:7029392"
    ],
    "tgn:id":7485246,
    "tgn:name":"Shiwu Huguan Suo",
    "tgn:placetype":[
        "aat:300387503"
    ]
},
  "bbox": [],
  "geometry": {"coordinates":[120.7525,22.133056],"type":"Point"}
}
=======
{"geometry":{"type":"Point","coordinates":[120.752500,22.133056]},"type":"Feature","properties":{"hierarchy":["tgn:7485246","tgn:1000004","tgn:7492971","tgn:1000141","tgn:7029392"],"placetype":["aat:300387503"],"id":7485246,"name:xx":"Shiwu Huguan Suo"}}
>>>>>>> 03f74aca74312dbeaf24d7e61306dd6a786dc3d0
