{
  "id": 7389829,
  "type": "Feature",
  "properties": {
    "tgn:hierarchy":[
        "tgn:7389829",
        "tgn:1001853",
        "tgn:1000001",
        "tgn:7005560",
        "tgn:7029392"
    ],
    "tgn:id":7389829,
    "tgn:name":"Rancho El Tule",
    "tgn:placetype":[
        "aat:300008347"
    ]
},
  "bbox": [],
  "geometry": {"coordinates":[-101.016667,28.616667],"type":"Point"}
}