<<<<<<< HEAD
{
  "id": 7478199,
  "type": "Feature",
  "properties": {
    "tgn:hierarchy":[
        "tgn:7478199",
        "tgn:1000004",
        "tgn:7001013",
        "tgn:1000141",
        "tgn:7029392"
    ],
    "tgn:id":7478199,
    "tgn:name":"Bianzitou",
    "tgn:placetype":[
        "aat:300008347"
    ]
},
  "bbox": [],
  "geometry": {"coordinates":[121.181386,25.056662],"type":"Point"}
}
=======
{"geometry":{"type":"Point","coordinates":[121.181386,25.056662]},"type":"Feature","properties":{"hierarchy":["tgn:7478199","tgn:1000004","tgn:7001013","tgn:1000141","tgn:7029392"],"placetype":["aat:300008347"],"id":7478199,"name:xx":"Bianzitou"}}
>>>>>>> 03f74aca74312dbeaf24d7e61306dd6a786dc3d0
