{
  "id": 2132444,
  "type": "Feature",
  "properties": {
    "tgn:hierarchy":[
        "tgn:2132444",
        "tgn:1000001",
        "tgn:7012149",
        "tgn:1002679",
        "tgn:7007520",
        "tgn:7029392"
    ],
    "tgn:id":2132444,
    "tgn:name":"Amos Palmer Drain",
    "tgn:placetype":[
        "aat:300008699"
    ]
},
  "bbox": [],
  "geometry": {"coordinates":[-83.5833,42.05],"type":"Point"}
}