{
  "id": 7422419,
  "type": "Feature",
  "properties": {
    "tgn:hierarchy":[
        "tgn:7422419",
        "tgn:1000001",
        "tgn:7005601",
        "tgn:7005560",
        "tgn:7029392"
    ],
    "tgn:id":7422419,
    "tgn:name":"San Jer\u00f3nimo",
    "tgn:placetype":[
        "aat:300008347"
    ]
},
  "bbox": [],
  "geometry": {"coordinates":[-103.15,23.15],"type":"Point"}
}