{
  "id": 7056305,
  "type": "Feature",
  "properties": {
    "tgn:hierarchy":[
        "tgn:7056305",
        "tgn:7003164",
        "tgn:1000003",
        "tgn:7009760",
        "tgn:1000080",
        "tgn:7029392"
    ],
    "tgn:id":7056305,
    "tgn:name":"Pila",
    "tgn:placetype":[
        "aat:300008347"
    ]
},
  "bbox": [],
  "geometry": {"coordinates":[10.216667,42.766667],"type":"Point"}
}