{
  "id": 2502075,
  "type": "Feature",
  "properties": {
    "tgn:hierarchy":[
        "tgn:2502075",
        "tgn:1000001",
        "tgn:7012149",
        "tgn:2001281",
        "tgn:7007524",
        "tgn:7029392"
    ],
    "tgn:id":2502075,
    "tgn:name":"McKenzie Gulch",
    "tgn:placetype":[
        "aat:300008761"
    ]
},
  "bbox": [],
  "geometry": {"coordinates":[-112.15,46.3333],"type":"Point"}
}