{
  "id": 2165949,
  "type": "Feature",
  "properties": {
    "tgn:hierarchy":[
        "tgn:2165949",
        "tgn:1000001",
        "tgn:7012149",
        "tgn:2001390",
        "tgn:7007525",
        "tgn:7029392"
    ],
    "tgn:id":2165949,
    "tgn:name":"Big Anne Spring",
    "tgn:placetype":[
        "aat:300008697"
    ]
},
  "bbox": [],
  "geometry": {"coordinates":[-99.4833,42.8333],"type":"Point"}
}