<<<<<<< HEAD
{
  "id": 7112353,
  "type": "Feature",
  "properties": {
    "tgn:hierarchy":[
        "tgn:7112353",
        "tgn:1000003",
        "tgn:7003677",
        "tgn:7000084",
        "tgn:7029392"
    ],
    "tgn:id":7112353,
    "tgn:name":"Rheinhausen",
    "tgn:placetype":[
        "aat:300387173"
    ]
},
  "bbox": [],
  "geometry": {"coordinates":[6.75,51.416667],"type":"Point"}
}
=======
{"geometry":{"type":"Point","coordinates":[6.750000,51.416667]},"type":"Feature","properties":{"hierarchy":["tgn:7112353","tgn:1000003","tgn:7003677","tgn:7000084","tgn:7029392"],"placetype":["aat:300387173"],"id":7112353,"name:xx":"Rheinhausen"}}
>>>>>>> 03f74aca74312dbeaf24d7e61306dd6a786dc3d0
