{
  "id": 2570629,
  "type": "Feature",
  "properties": {
    "tgn:hierarchy":[
        "tgn:2570629",
        "tgn:1000001",
        "tgn:7012149",
        "tgn:2001029",
        "tgn:7007521",
        "tgn:7029392"
    ],
    "tgn:id":2570629,
    "tgn:name":"Patrick Mine",
    "tgn:placetype":[
        "aat:300000390"
    ]
},
  "bbox": [],
  "geometry": {"coordinates":[-93.2167,47.35],"type":"Point"}
}