{
  "id": 2616198,
  "type": "Feature",
  "properties": {
    "tgn:hierarchy":[
        "tgn:2616198",
        "tgn:1000001",
        "tgn:7012149",
        "tgn:1002506",
        "tgn:7007919",
        "tgn:7029392"
    ],
    "tgn:id":2616198,
    "tgn:name":"Rhodes, Lake",
    "tgn:placetype":[
        "aat:300006191"
    ]
},
  "bbox": [],
  "geometry": {"coordinates":[-76.6333,36.8667],"type":"Point"}
}