{
  "id": 2733471,
  "type": "Feature",
  "properties": {
    "tgn:hierarchy":[
        "tgn:2733471",
        "tgn:1000001",
        "tgn:7012149",
        "tgn:1002958",
        "tgn:7007706",
        "tgn:7029392"
    ],
    "tgn:id":2733471,
    "tgn:name":"Turkeyfoot Run",
    "tgn:placetype":[
        "aat:300008699"
    ]
},
  "bbox": [],
  "geometry": {"coordinates":[-81.5833,40.5833],"type":"Point"}
}