{
  "id": 2218305,
  "type": "Feature",
  "properties": {
    "tgn:hierarchy":[
        "tgn:2218305",
        "tgn:1000001",
        "tgn:1003023",
        "tgn:7012149",
        "tgn:7007516",
        "tgn:7029392"
    ],
    "tgn:id":2218305,
    "tgn:name":"Canal, The",
    "tgn:placetype":[
        "aat:300008699"
    ]
},
  "bbox": [],
  "geometry": {"coordinates":[-75.8333,38.35],"type":"Point"}
}