<<<<<<< HEAD
{
  "id": 7020045,
  "type": "Feature",
  "properties": {
    "tgn:hierarchy":[
        "tgn:7020045",
        "tgn:1000001",
        "tgn:7012149",
        "tgn:1002352",
        "tgn:7007710",
        "tgn:7029392"
    ],
    "tgn:id":7020045,
    "tgn:name":"Laurel Run Reservoir",
    "tgn:placetype":[
        "aat:300006191"
    ]
},
  "bbox": [],
  "geometry": {"coordinates":[-78.55,41.3667],"type":"Point"}
}
=======
{"geometry":{"type":"Point","coordinates":[-78.550000,41.366700]},"type":"Feature","properties":{"hierarchy":["tgn:7020045","tgn:1000001","tgn:7012149","tgn:1002352","tgn:7007710","tgn:7029392"],"placetype":["aat:300006191"],"id":7020045,"name:xx":"Laurel Run Reservoir"}}
>>>>>>> 03f74aca74312dbeaf24d7e61306dd6a786dc3d0
