{
  "id": 2629178,
  "type": "Feature",
  "properties": {
    "tgn:hierarchy":[
        "tgn:2629178",
        "tgn:1000001",
        "tgn:7012149",
        "tgn:1003008",
        "tgn:7007710",
        "tgn:7029392"
    ],
    "tgn:id":2629178,
    "tgn:name":"Rose Pond",
    "tgn:placetype":[
        "aat:300008680"
    ]
},
  "bbox": [],
  "geometry": {"coordinates":[-75.2167,41.7167],"type":"Point"}
}