<<<<<<< HEAD
{
  "id": 2157583,
  "type": "Feature",
  "properties": {
    "tgn:hierarchy":[
        "tgn:2157583",
        "tgn:7002659",
        "tgn:1000001",
        "tgn:7012149",
        "tgn:2000057",
        "tgn:7029392"
    ],
    "tgn:id":2157583,
    "tgn:name":"Beaver Creek Valley",
    "tgn:placetype":[
        "aat:300008761"
    ]
},
  "bbox": [],
  "geometry": {"coordinates":[-86.4,33.65],"type":"Point"}
}
=======
{"geometry":{"type":"Point","coordinates":[-86.400000,33.650000]},"type":"Feature","properties":{"hierarchy":["tgn:2157583","tgn:7002659","tgn:1000001","tgn:7012149","tgn:2000057","tgn:7029392"],"placetype":["aat:300008761"],"id":2157583,"name:xx":"Beaver Creek Valley"}}
>>>>>>> 03f74aca74312dbeaf24d7e61306dd6a786dc3d0
