{
  "id": 2487679,
  "type": "Feature",
  "properties": {
    "tgn:hierarchy":[
        "tgn:2487679",
        "tgn:1000001",
        "tgn:7012149",
        "tgn:2002298",
        "tgn:7013961",
        "tgn:7029392"
    ],
    "tgn:id":2487679,
    "tgn:name":"Left Fork Little Sand Run",
    "tgn:placetype":[
        "aat:300008699"
    ]
},
  "bbox": [],
  "geometry": {"coordinates":[-80.1667,38.95],"type":"Point"}
}