<<<<<<< HEAD
{
  "id": 7473440,
  "type": "Feature",
  "properties": {
    "tgn:hierarchy":[
        "tgn:7473440",
        "tgn:1000004",
        "tgn:1000454",
        "tgn:1000141",
        "tgn:7029392"
    ],
    "tgn:id":7473440,
    "tgn:name":"Chepingliao",
    "tgn:placetype":[
        "aat:300008347"
    ]
},
  "bbox": [],
  "geometry": {"coordinates":[121.612884,25.117263],"type":"Point"}
}
=======
{"geometry":{"type":"Point","coordinates":[121.612884,25.117263]},"type":"Feature","properties":{"hierarchy":["tgn:7473440","tgn:1000004","tgn:1000454","tgn:1000141","tgn:7029392"],"placetype":["aat:300008347"],"id":7473440,"name:xx":"Chepingliao"}}
>>>>>>> 03f74aca74312dbeaf24d7e61306dd6a786dc3d0
