{
  "id": 2321325,
  "type": "Feature",
  "properties": {
    "tgn:hierarchy":[
        "tgn:2321325",
        "tgn:1000001",
        "tgn:7012149",
        "tgn:1003044",
        "tgn:7007708",
        "tgn:7029392"
    ],
    "tgn:id":2321325,
    "tgn:name":"Fairdale",
    "tgn:placetype":[
        "aat:300008347"
    ]
},
  "bbox": [],
  "geometry": {"coordinates":[-123.3333,45.35],"type":"Point"}
}