<<<<<<< HEAD
{
  "id": 7246594,
  "type": "Feature",
  "properties": {
    "tgn:hierarchy":[
        "tgn:7246594",
        "tgn:7003458",
        "tgn:1000003",
        "tgn:1000063",
        "tgn:7018236",
        "tgn:7029392"
    ],
    "tgn:id":7246594,
    "tgn:name":"Dode Manhoek",
    "tgn:placetype":[
        "aat:300008347"
    ]
},
  "bbox": [],
  "geometry": {"coordinates":[2.620451,51.00621],"type":"Point"}
}
=======
{"geometry":{"type":"Point","coordinates":[2.620451,51.006210]},"type":"Feature","properties":{"hierarchy":["tgn:7246594","tgn:7003458","tgn:1000003","tgn:1000063","tgn:7018236","tgn:7029392"],"placetype":["aat:300008347"],"id":7246594,"name:xx":"Dode Manhoek"}}
>>>>>>> 03f74aca74312dbeaf24d7e61306dd6a786dc3d0
