{
  "id": 7467547,
  "type": "Feature",
  "properties": {
    "tgn:hierarchy":[
        "tgn:7467547",
        "tgn:1000004",
        "tgn:7491221",
        "tgn:1000141",
        "tgn:7029392"
    ],
    "tgn:id":7467547,
    "tgn:name":"Shikejian Shan",
    "tgn:placetype":[
        "aat:300008798"
    ]
},
  "bbox": [],
  "geometry": {"coordinates":[120.740556,22.449444],"type":"Point"}
}