{
  "id": 2297594,
  "type": "Feature",
  "properties": {
    "tgn:hierarchy":[
        "tgn:2297594",
        "tgn:1000001",
        "tgn:7012149",
        "tgn:2001721",
        "tgn:7007708",
        "tgn:7029392"
    ],
    "tgn:id":2297594,
    "tgn:name":"Dry Fork Jordan Creek",
    "tgn:placetype":[
        "aat:300008706"
    ]
},
  "bbox": [],
  "geometry": {"coordinates":[-118.15,45.15],"type":"Point"}
}