{
  "id": 7586428,
  "type": "Feature",
  "properties": {
    "tgn:hierarchy":[
        "tgn:7586428",
        "tgn:1000004",
        "tgn:7000198",
        "tgn:7000799",
        "tgn:7029392"
    ],
    "tgn:id":7586428,
    "tgn:name:en":"Trewa",
    "tgn:placetype":[
        "aat:300008795"
    ]
},
  "bbox": [],
  "geometry": {"coordinates":[74.819147,34.398226],"type":"Point"}
}