{
  "id": 2460504,
  "type": "Feature",
  "properties": {
    "tgn:hierarchy":[
        "tgn:2460504",
        "tgn:1000001",
        "tgn:7012149",
        "tgn:2001234",
        "tgn:7007523",
        "tgn:7029392"
    ],
    "tgn:id":2460504,
    "tgn:name":"Little Sandy Creek",
    "tgn:placetype":[
        "aat:300008706"
    ]
},
  "bbox": [],
  "geometry": {"coordinates":[-92.8833,40.4833],"type":"Point"}
}