{
  "id": 7517703,
  "type": "Feature",
  "properties": {
    "tgn:hierarchy":[
        "tgn:7517703",
        "tgn:1009227",
        "tgn:1000226",
        "tgn:7520095",
        "tgn:1000006",
        "tgn:7029392"
    ],
    "tgn:id":7517703,
    "tgn:name:en":"Kitty Creek",
    "tgn:placetype":[
        "aat:300008699"
    ]
},
  "bbox": [],
  "geometry": {"coordinates":[172.85,-40.85],"type":"Point"}
}