{
  "id": 7557913,
  "type": "Feature",
  "properties": {
    "tgn:hierarchy":[
        "tgn:7557913",
        "tgn:1000004",
        "tgn:7000198",
        "tgn:7016694",
        "tgn:7029392"
    ],
    "tgn:id":7557913,
    "tgn:name:en":"Pottangi",
    "tgn:placetype":[
        "aat:300008347"
    ]
},
  "bbox": [],
  "geometry": {"coordinates":[82.966667,18.566667],"type":"Point"}
}