{
  "id": 7427269,
  "type": "Feature",
  "properties": {
    "tgn:hierarchy":[
        "tgn:7427269",
        "tgn:1000001",
        "tgn:7005594",
        "tgn:7005560",
        "tgn:7029392"
    ],
    "tgn:id":7427269,
    "tgn:name":"El Cl\u00e9rigo",
    "tgn:placetype":[
        "aat:300008347"
    ]
},
  "bbox": [],
  "geometry": {"coordinates":[-101.083333,23.016667],"type":"Point"}
}