{
  "id": 1103462,
  "type": "Feature",
  "properties": {
    "tgn:hierarchy":[
        "tgn:1103462",
        "tgn:7002445",
        "tgn:7008114",
        "tgn:1000003",
        "tgn:7008591",
        "tgn:7029392"
    ],
    "tgn:id":1103462,
    "tgn:name:en":"Delamere Forest",
    "tgn:placetype":[
        "aat:300008863",
        "aat:300132451"
    ]
},
  "bbox": [],
  "geometry": {"coordinates":[-2.683333,53.233333],"type":"Point"}
}