<<<<<<< HEAD
{
  "id": 2402550,
  "type": "Feature",
  "properties": {
    "tgn:hierarchy":[
        "tgn:2402550",
        "tgn:2000296",
        "tgn:1000001",
        "tgn:7012149",
        "tgn:7007248",
        "tgn:7029392"
    ],
    "tgn:id":2402550,
    "tgn:name":"Hospital Lake Number Two",
    "tgn:placetype":[
        "aat:300006191"
    ]
},
  "bbox": [],
  "geometry": {"coordinates":[-83.2,33.0167],"type":"Point"}
}
=======
{"geometry":{"type":"Point","coordinates":[-83.200000,33.016700]},"type":"Feature","properties":{"hierarchy":["tgn:2402550","tgn:2000296","tgn:1000001","tgn:7012149","tgn:7007248","tgn:7029392"],"placetype":["aat:300006191"],"id":2402550,"name:xx":"Hospital Lake Number Two"}}
>>>>>>> 03f74aca74312dbeaf24d7e61306dd6a786dc3d0
