{
  "id": 1029486,
  "type": "Feature",
  "properties": {
    "tgn:hierarchy":[
        "tgn:1029486",
        "tgn:7002445",
        "tgn:1000003",
        "tgn:7019054",
        "tgn:7008591",
        "tgn:7029392"
    ],
    "tgn:id":1029486,
    "tgn:name:en":"Haxey",
    "tgn:placetype":[
        "aat:300008347",
        "aat:300008372"
    ]
},
  "bbox": [],
  "geometry": {"coordinates":[-0.833333,53.483333],"type":"Point"}
}