{
  "id": 2604101,
  "type": "Feature",
  "properties": {
    "tgn:hierarchy":[
        "tgn:2604101",
        "tgn:7006450",
        "tgn:1000001",
        "tgn:7012149",
        "tgn:2000086",
        "tgn:7029392"
    ],
    "tgn:id":2604101,
    "tgn:name":"Quintino Sella Glacier",
    "tgn:placetype":[
        "aat:300008835"
    ]
},
  "bbox": [],
  "geometry": {"coordinates":[-141.0167,60.5333],"type":"Point"}
}