{
  "id": 2686071,
  "type": "Feature",
  "properties": {
    "tgn:hierarchy":[
        "tgn:2686071",
        "tgn:1000001",
        "tgn:7012149",
        "tgn:2000234",
        "tgn:7007158",
        "tgn:7029392"
    ],
    "tgn:id":2686071,
    "tgn:name":"Spring Canyon",
    "tgn:placetype":[
        "aat:300008761"
    ]
},
  "bbox": [],
  "geometry": {"coordinates":[-108.8667,38.2333],"type":"Point"}
}