{
  "id": 2023041,
  "type": "Feature",
  "properties": {
    "tgn:hierarchy":[
        "tgn:2023041",
        "tgn:1000001",
        "tgn:7012149",
        "tgn:2000361",
        "tgn:7007248",
        "tgn:7029392"
    ],
    "tgn:id":2023041,
    "tgn:name":"Granite Hill",
    "tgn:placetype":[
        "aat:300387210",
        "aat:300008798"
    ]
},
  "bbox": [],
  "geometry": {"coordinates":[-82.9333,33.2833],"type":"Point"}
}