{
  "id": 2694627,
  "type": "Feature",
  "properties": {
    "tgn:hierarchy":[
        "tgn:2694627",
        "tgn:1000001",
        "tgn:1002410",
        "tgn:7012149",
        "tgn:7007565",
        "tgn:7029392"
    ],
    "tgn:id":2694627,
    "tgn:name":"Stewart Lake",
    "tgn:placetype":[
        "aat:300006191"
    ]
},
  "bbox": [],
  "geometry": {"coordinates":[-75.1333,39.8333],"type":"Point"}
}