{
  "id": 2051900,
  "type": "Feature",
  "properties": {
    "tgn:hierarchy":[
        "tgn:2051900",
        "tgn:1000001",
        "tgn:7012149",
        "tgn:2000992",
        "tgn:7007520",
        "tgn:7029392"
    ],
    "tgn:id":2051900,
    "tgn:name":"Fenmore",
    "tgn:placetype":[
        "aat:300008347",
        "aat:300387210"
    ]
},
  "bbox": [],
  "geometry": {"coordinates":[-84.3333,43.1667],"type":"Point"}
}