{
  "id": 7316219,
  "type": "Feature",
  "properties": {
    "tgn:hierarchy":[
        "tgn:7316219",
        "tgn:7016598",
        "tgn:1000049",
        "tgn:1000002",
        "tgn:7029392"
    ],
    "tgn:id":7316219,
    "tgn:name":"Casado, Cerro",
    "tgn:placetype":[
        "aat:300008795"
    ]
},
  "bbox": [],
  "geometry": {"coordinates":[-69.016667,-23.35],"type":"Point"}
}