{
  "id": 2509858,
  "type": "Feature",
  "properties": {
    "tgn:hierarchy":[
        "tgn:2509858",
        "tgn:1000001",
        "tgn:7012149",
        "tgn:2002119",
        "tgn:7007827",
        "tgn:7029392"
    ],
    "tgn:id":2509858,
    "tgn:name":"Middle Mesa",
    "tgn:placetype":[
        "aat:300008798"
    ]
},
  "bbox": [],
  "geometry": {"coordinates":[-109.1333,38.1833],"type":"Point"}
}