{
  "id": 7304885,
  "type": "Feature",
  "properties": {
    "tgn:hierarchy":[
        "tgn:7304885",
        "tgn:7002803",
        "tgn:1001647",
        "tgn:1000003",
        "tgn:1000095",
        "tgn:7029392"
    ],
    "tgn:id":7304885,
    "tgn:name":"La Urbina",
    "tgn:placetype":[
        "aat:300008347"
    ]
},
  "bbox": [],
  "geometry": {"coordinates":[-2.766667,39.166667],"type":"Point"}
}