{
  "id": 2509761,
  "type": "Feature",
  "properties": {
    "tgn:hierarchy":[
        "tgn:2509761",
        "tgn:1000001",
        "tgn:7012149",
        "tgn:2000981",
        "tgn:7007520",
        "tgn:7029392"
    ],
    "tgn:id":2509761,
    "tgn:name":"Middle Lake",
    "tgn:placetype":[
        "aat:300008680"
    ]
},
  "bbox": [],
  "geometry": {"coordinates":[-85.2833,43.3167],"type":"Point"}
}