<<<<<<< HEAD
{
  "id": 7357358,
  "type": "Feature",
  "properties": {
    "tgn:hierarchy":[
        "tgn:7357358",
        "tgn:7005586",
        "tgn:1000001",
        "tgn:7005560",
        "tgn:7029392"
    ],
    "tgn:id":7357358,
    "tgn:name":"Cuisillos",
    "tgn:placetype":[
        "aat:300008347"
    ]
},
  "bbox": [],
  "geometry": {"coordinates":[-103.766667,20.6],"type":"Point"}
}
=======
{"geometry":{"type":"Point","coordinates":[-103.766667,20.600000]},"type":"Feature","properties":{"hierarchy":["tgn:7357358","tgn:7005586","tgn:1000001","tgn:7005560","tgn:7029392"],"placetype":["aat:300008347"],"id":7357358,"name:xx":"Cuisillos"}}
>>>>>>> 03f74aca74312dbeaf24d7e61306dd6a786dc3d0
