{
  "id": 7497596,
  "type": "Feature",
  "properties": {
    "tgn:hierarchy":[
        "tgn:7497596",
        "tgn:1000004",
        "tgn:7001013",
        "tgn:1000141",
        "tgn:7029392"
    ],
    "tgn:id":7497596,
    "tgn:name":"Dakuai Xi Ling",
    "tgn:placetype":[
        "aat:300008777"
    ]
},
  "bbox": [],
  "geometry": {"coordinates":[121.330421,25.016606],"type":"Point"}
}