{
  "id": 2523445,
  "type": "Feature",
  "properties": {
    "tgn:hierarchy":[
        "tgn:2523445",
        "tgn:7006450",
        "tgn:1000001",
        "tgn:7019674",
        "tgn:7012149",
        "tgn:7029392"
    ],
    "tgn:id":2523445,
    "tgn:name":"Moose Gulch",
    "tgn:placetype":[
        "aat:300008761"
    ]
},
  "bbox": [],
  "geometry": {"coordinates":[-148.0667,64.85],"type":"Point"}
}