{
  "id": 7292570,
  "type": "Feature",
  "properties": {
    "tgn:hierarchy":[
        "tgn:7292570",
        "tgn:1001630",
        "tgn:1000049",
        "tgn:1000002",
        "tgn:7029392"
    ],
    "tgn:id":7292570,
    "tgn:name":"El Tofo, Sierra",
    "tgn:placetype":[
        "aat:300008795"
    ]
},
  "bbox": [],
  "geometry": {"coordinates":[-71.216667,-28.916667],"type":"Point"}
}