{
  "id": 7362914,
  "type": "Feature",
  "properties": {
    "tgn:hierarchy":[
        "tgn:7362914",
        "tgn:1000001",
        "tgn:7005597",
        "tgn:7005560",
        "tgn:7029392"
    ],
    "tgn:id":7362914,
    "tgn:name":"El Marrano",
    "tgn:placetype":[
        "aat:300266554",
        "aat:300008699"
    ]
},
  "bbox": [],
  "geometry": {"coordinates":[-99.683333,23.133333],"type":"Point"}
}