<<<<<<< HEAD
{
  "id": 7242392,
  "type": "Feature",
  "properties": {
    "tgn:hierarchy":[
        "tgn:7242392",
        "tgn:7007877",
        "tgn:1000003",
        "tgn:1000063",
        "tgn:4012014",
        "tgn:7029392"
    ],
    "tgn:id":7242392,
    "tgn:name":"Ferme de Lombisoeuil",
    "tgn:placetype":[
        "aat:300000206"
    ]
},
  "bbox": [],
  "geometry": {"coordinates":[3.95,50.6],"type":"Point"}
}
=======
{"geometry":{"type":"Point","coordinates":[3.950000,50.600000]},"type":"Feature","properties":{"hierarchy":["tgn:7242392","tgn:7007877","tgn:1000003","tgn:1000063","tgn:4012014","tgn:7029392"],"placetype":["aat:300000206"],"id":7242392,"name:xx":"Ferme de Lombisoeuil"}}
>>>>>>> 03f74aca74312dbeaf24d7e61306dd6a786dc3d0
