{
  "id": 7365703,
  "type": "Feature",
  "properties": {
    "tgn:hierarchy":[
        "tgn:7365703",
        "tgn:7005580",
        "tgn:1000001",
        "tgn:7005560",
        "tgn:7029392"
    ],
    "tgn:id":7365703,
    "tgn:name":"El Refugio",
    "tgn:placetype":[
        "aat:300008347"
    ]
},
  "bbox": [],
  "geometry": {"coordinates":[-93.783333,15.933333],"type":"Point"}
}