{
  "id": 2202016,
  "type": "Feature",
  "properties": {
    "tgn:hierarchy":[
        "tgn:2202016",
        "tgn:1000001",
        "tgn:7012149",
        "tgn:2000926",
        "tgn:7007515",
        "tgn:7029392"
    ],
    "tgn:id":2202016,
    "tgn:name":"Buck Island",
    "tgn:placetype":[
        "aat:300008791"
    ]
},
  "bbox": [],
  "geometry": {"coordinates":[-70.9167,44.15],"type":"Point"}
}