{
  "id": 2022719,
  "type": "Feature",
  "properties": {
    "tgn:hierarchy":[
        "tgn:2022719",
        "tgn:1000001",
        "tgn:7012149",
        "tgn:2000329",
        "tgn:7007248",
        "tgn:7029392"
    ],
    "tgn:id":2022719,
    "tgn:name":"Dresden",
    "tgn:placetype":[
        "aat:300008347",
        "aat:300387210"
    ]
},
  "bbox": [],
  "geometry": {"coordinates":[-84.9167,33.35],"type":"Point"}
}