{
  "id": 1093340,
  "type": "Feature",
  "properties": {
    "tgn:hierarchy":[
        "tgn:1093340",
        "tgn:7001242",
        "tgn:7016749",
        "tgn:1000193",
        "tgn:7029392"
    ],
    "tgn:id":1093340,
    "tgn:name":"Magudu",
    "tgn:placetype":[
        "aat:300008347"
    ]
},
  "bbox": [],
  "geometry": {"coordinates":[31.6667,-27.5333],"type":"Point"}
}