{
  "id": 2401474,
  "type": "Feature",
  "properties": {
    "tgn:hierarchy":[
        "tgn:2401474",
        "tgn:1000001",
        "tgn:7012149",
        "tgn:7014344",
        "tgn:7007919",
        "tgn:7029392"
    ],
    "tgn:id":2401474,
    "tgn:name":"Horseshoe Branch",
    "tgn:placetype":[
        "aat:300008699"
    ]
},
  "bbox": [],
  "geometry": {"coordinates":[-79.8833,37.2333],"type":"Point"}
}