{
  "id": 1075105,
  "type": "Feature",
  "properties": {
    "tgn:hierarchy":[
        "tgn:1075105",
        "tgn:1000004",
        "tgn:7000198",
        "tgn:1001977",
        "tgn:7029392"
    ],
    "tgn:id":1075105,
    "tgn:name:en":"Debagr\u0101m",
    "tgn:placetype":[
        "aat:300008347"
    ]
},
  "bbox": [],
  "geometry": {"coordinates":[88.30083,23.688317],"type":"Point"}
}