{
  "id": 2347425,
  "type": "Feature",
  "properties": {
    "tgn:hierarchy":[
        "tgn:2347425",
        "tgn:1000001",
        "tgn:7012149",
        "tgn:2001029",
        "tgn:7007521",
        "tgn:7029392"
    ],
    "tgn:id":2347425,
    "tgn:name":"George Lake",
    "tgn:placetype":[
        "aat:300008680"
    ]
},
  "bbox": [],
  "geometry": {"coordinates":[-93.45,47.55],"type":"Point"}
}