{
  "id": 7217097,
  "type": "Feature",
  "properties": {
    "tgn:hierarchy":[
        "tgn:7217097",
        "tgn:7002741",
        "tgn:7017076",
        "tgn:1000003",
        "tgn:1000074",
        "tgn:7029392"
    ],
    "tgn:id":7217097,
    "tgn:name":"Zemeno\u00fa, Sten\u00f3n",
    "tgn:placetype":[
        "aat:300259572"
    ]
},
  "bbox": [],
  "geometry": {"coordinates":[22.666667,38.483333],"type":"Point"}
}