{
  "id": 7497013,
  "type": "Feature",
  "properties": {
    "tgn:hierarchy":[
        "tgn:7497013",
        "tgn:7001004",
        "tgn:1000004",
        "tgn:1000141",
        "tgn:7029392"
    ],
    "tgn:id":7497013,
    "tgn:name":"Xiaogang Gaozhong",
    "tgn:placetype":[
        "aat:300006495"
    ]
},
  "bbox": [],
  "geometry": {"coordinates":[120.356008,22.564468],"type":"Point"}
}