{
  "id": 2747731,
  "type": "Feature",
  "properties": {
    "tgn:hierarchy":[
        "tgn:2747731",
        "tgn:1007657",
        "tgn:1002534",
        "tgn:1000001",
        "tgn:7012149",
        "tgn:7007249",
        "tgn:7029392"
    ],
    "tgn:id":2747731,
    "tgn:name":"Waipuni",
    "tgn:placetype":[
        "aat:300008798"
    ]
},
  "bbox": [],
  "geometry": {"coordinates":[-159.4667,22.1667],"type":"Point"}
}