{
  "id": 7492103,
  "type": "Feature",
  "properties": {
    "tgn:hierarchy":[
        "tgn:7492103",
        "tgn:7487020",
        "tgn:1000004",
        "tgn:1000141",
        "tgn:7029392"
    ],
    "tgn:id":7492103,
    "tgn:name":"Dananwo",
    "tgn:placetype":[
        "aat:300008347"
    ]
},
  "bbox": [],
  "geometry": {"coordinates":[120.707859,24.514921],"type":"Point"}
}