{
  "id": 7421432,
  "type": "Feature",
  "properties": {
    "tgn:hierarchy":[
        "tgn:7421432",
        "tgn:1000001",
        "tgn:7005589",
        "tgn:7005560",
        "tgn:7029392"
    ],
    "tgn:id":7421432,
    "tgn:name:es":"La Jacinta",
    "tgn:placetype":[
        "aat:300008347"
    ]
},
  "bbox": [],
  "geometry": {"coordinates":[-100.445833,25.350556],"type":"Point"}
}