<<<<<<< HEAD
{
  "id": 2158633,
  "type": "Feature",
  "properties": {
    "tgn:hierarchy":[
        "tgn:2158633",
        "tgn:1000001",
        "tgn:7006451",
        "tgn:7012149",
        "tgn:2000103",
        "tgn:7029392"
    ],
    "tgn:id":2158633,
    "tgn:name":"Beaverhead Spring",
    "tgn:placetype":[
        "aat:300008697"
    ]
},
  "bbox": [],
  "geometry": {"coordinates":[-111.7833,34.7],"type":"Point"}
}
=======
{"geometry":{"type":"Point","coordinates":[-111.783300,34.700000]},"type":"Feature","properties":{"hierarchy":["tgn:2158633","tgn:1000001","tgn:7006451","tgn:7012149","tgn:2000103","tgn:7029392"],"placetype":["aat:300008697"],"id":2158633,"name:xx":"Beaverhead Spring"}}
>>>>>>> 03f74aca74312dbeaf24d7e61306dd6a786dc3d0
