{
  "id": 7517368,
  "type": "Feature",
  "properties": {
    "tgn:hierarchy":[
        "tgn:7517368",
        "tgn:1008380",
        "tgn:7000507",
        "tgn:1000226",
        "tgn:1000006",
        "tgn:7029392"
    ],
    "tgn:id":7517368,
    "tgn:name:en":"North Anchorage",
    "tgn:placetype":[
        "aat:300386968"
    ]
},
  "bbox": [],
  "geometry": {"coordinates":[-177.916667,-29.216667],"type":"Point"}
}