{
  "id": 2054340,
  "type": "Feature",
  "properties": {
    "tgn:hierarchy":[
        "tgn:2054340",
        "tgn:1000001",
        "tgn:2001013",
        "tgn:7012149",
        "tgn:7007521",
        "tgn:7029392"
    ],
    "tgn:id":2054340,
    "tgn:name":"Ebro",
    "tgn:placetype":[
        "aat:300008347"
    ]
},
  "bbox": [],
  "geometry": {"coordinates":[-95.5167,47.4833],"type":"Point"}
}