{
  "id": 2408513,
  "type": "Feature",
  "properties": {
    "tgn:hierarchy":[
        "tgn:2408513",
        "tgn:1000001",
        "tgn:7012149",
        "tgn:2002284",
        "tgn:7013961",
        "tgn:7029392"
    ],
    "tgn:id":2408513,
    "tgn:name":"Hutchison Branch",
    "tgn:placetype":[
        "aat:300008699"
    ]
},
  "bbox": [],
  "geometry": {"coordinates":[-80.9333,38.3167],"type":"Point"}
}