{
  "id": 2478573,
  "type": "Feature",
  "properties": {
    "tgn:hierarchy":[
        "tgn:2478573",
        "tgn:1000001",
        "tgn:7012149",
        "tgn:2000340",
        "tgn:7007248",
        "tgn:7029392"
    ],
    "tgn:id":2478573,
    "tgn:name":"Maddox Lake",
    "tgn:placetype":[
        "aat:300006191"
    ]
},
  "bbox": [],
  "geometry": {"coordinates":[-84.85,31.2833],"type":"Point"}
}