{
  "id": 7500389,
  "type": "Feature",
  "properties": {
    "tgn:hierarchy":[
        "tgn:7500389",
        "tgn:1000004",
        "tgn:7001009",
        "tgn:1000141",
        "tgn:7029392"
    ],
    "tgn:id":7500389,
    "tgn:name":"Meiguo Malixun Xuexiao",
    "tgn:placetype":[
        "aat:300006495"
    ]
},
  "bbox": [],
  "geometry": {"coordinates":[120.6814,24.187],"type":"Point"}
}