{
  "id": 2598965,
  "type": "Feature",
  "properties": {
    "tgn:hierarchy":[
        "tgn:2598965",
        "tgn:7006450",
        "tgn:1000001",
        "tgn:7012149",
        "tgn:2000079",
        "tgn:7029392"
    ],
    "tgn:id":2598965,
    "tgn:name":"Prince of Wales Creek",
    "tgn:placetype":[
        "aat:300008706"
    ]
},
  "bbox": [],
  "geometry": {"coordinates":[-167.7667,65.55],"type":"Point"}
}