<<<<<<< HEAD
{
  "id": 2155919,
  "type": "Feature",
  "properties": {
    "tgn:hierarchy":[
        "tgn:2155919",
        "tgn:1000001",
        "tgn:7012149",
        "tgn:7007157",
        "tgn:2000189",
        "tgn:7029392"
    ],
    "tgn:id":2155919,
    "tgn:name":"Bear Valley Creek",
    "tgn:placetype":[
        "aat:300008706"
    ]
},
  "bbox": [],
  "geometry": {"coordinates":[-123.5667,41.6833],"type":"Point"}
}
=======
{"geometry":{"type":"Point","coordinates":[-123.566700,41.683300]},"type":"Feature","properties":{"hierarchy":["tgn:2155919","tgn:1000001","tgn:7012149","tgn:7007157","tgn:2000189","tgn:7029392"],"placetype":["aat:300008706"],"id":2155919,"name:xx":"Bear Valley Creek"}}
>>>>>>> 03f74aca74312dbeaf24d7e61306dd6a786dc3d0
