{
  "id": 2318370,
  "type": "Feature",
  "properties": {
    "tgn:hierarchy":[
        "tgn:2318370",
        "tgn:1000001",
        "tgn:7012149",
        "tgn:2001156",
        "tgn:7007522",
        "tgn:7029392"
    ],
    "tgn:id":2318370,
    "tgn:name":"Epps Branch",
    "tgn:placetype":[
        "aat:300008699"
    ]
},
  "bbox": [],
  "geometry": {"coordinates":[-88.1833,34.4667],"type":"Point"}
}