{
  "id": 7299717,
  "type": "Feature",
  "properties": {
    "tgn:hierarchy":[
        "tgn:7299717",
        "tgn:7002759",
        "tgn:7002845",
        "tgn:1000003",
        "tgn:1000095",
        "tgn:7029392"
    ],
    "tgn:id":7299717,
    "tgn:name":"Torres de Berrell\u00e9n",
    "tgn:placetype":[
        "aat:300008347"
    ]
},
  "bbox": [],
  "geometry": {"coordinates":[-1.066667,41.75],"type":"Point"}
}