<<<<<<< HEAD
{
  "id": 2761898,
  "type": "Feature",
  "properties": {
    "tgn:hierarchy":[
        "tgn:2761898",
        "tgn:1000001",
        "tgn:7012149",
        "tgn:2000221",
        "tgn:7007158",
        "tgn:7029392"
    ],
    "tgn:id":2761898,
    "tgn:name":"West Resort Creek",
    "tgn:placetype":[
        "aat:300008706"
    ]
},
  "bbox": [],
  "geometry": {"coordinates":[-105.3333,39.4833],"type":"Point"}
}
=======
{"geometry":{"type":"Point","coordinates":[-105.333300,39.483300]},"type":"Feature","properties":{"hierarchy":["tgn:2761898","tgn:1000001","tgn:7012149","tgn:2000221","tgn:7007158","tgn:7029392"],"placetype":["aat:300008706"],"id":2761898,"name:xx":"West Resort Creek"}}
>>>>>>> 03f74aca74312dbeaf24d7e61306dd6a786dc3d0
