{
  "id": 1042879,
  "type": "Feature",
  "properties": {
    "tgn:hierarchy":[
        "tgn:1042879",
        "tgn:7003499",
        "tgn:7001201",
        "tgn:1000003",
        "tgn:1000078",
        "tgn:7029392"
    ],
    "tgn:id":1042879,
    "tgn:name":"Kilmallock",
    "tgn:placetype":[
        "aat:300008347"
    ]
},
  "bbox": [],
  "geometry": {"coordinates":[-8.5833,52.4167],"type":"Point"}
}