{
  "id": 2730200,
  "type": "Feature",
  "properties": {
    "tgn:hierarchy":[
        "tgn:2730200",
        "tgn:1000001",
        "tgn:7012149",
        "tgn:7013941",
        "tgn:7007568",
        "tgn:7029392"
    ],
    "tgn:id":2730200,
    "tgn:name":"Trout River",
    "tgn:placetype":[
        "aat:300008707"
    ]
},
  "bbox": [],
  "geometry": {"coordinates":[-74.1667,44.7833],"type":"Point"}
}