{
  "id": 7482898,
  "type": "Feature",
  "properties": {
    "tgn:hierarchy":[
        "tgn:7482898",
        "tgn:1000004",
        "tgn:7001014",
        "tgn:1000141",
        "tgn:7029392"
    ],
    "tgn:id":7482898,
    "tgn:name":"Tianbu",
    "tgn:placetype":[
        "aat:300008347"
    ]
},
  "bbox": [],
  "geometry": {"coordinates":[120.582778,23.730278],"type":"Point"}
}