{
  "id": 7503643,
  "type": "Feature",
  "properties": {
    "tgn:hierarchy":[
        "tgn:7503643",
        "tgn:1000004",
        "tgn:7491221",
        "tgn:1000141",
        "tgn:7029392"
    ],
    "tgn:id":7503643,
    "tgn:name":"Jinfeng Qiao",
    "tgn:placetype":[
        "aat:300007836"
    ]
},
  "bbox": [],
  "geometry": {"coordinates":[120.971944,22.595],"type":"Point"}
}