{
  "id": 7385221,
  "type": "Feature",
  "properties": {
    "tgn:hierarchy":[
        "tgn:7385221",
        "tgn:7016644",
        "tgn:1000001",
        "tgn:7005560",
        "tgn:7029392"
    ],
    "tgn:id":7385221,
    "tgn:name":"Ojo de Agua, Punta",
    "tgn:placetype":[
        "aat:300386846"
    ]
},
  "bbox": [],
  "geometry": {"coordinates":[-104.35,19.05],"type":"Point"}
}