<<<<<<< HEAD
{
  "id": 7488668,
  "type": "Feature",
  "properties": {
    "tgn:hierarchy":[
        "tgn:7488668",
        "tgn:1000004",
        "tgn:7491221",
        "tgn:1000141",
        "tgn:7029392"
    ],
    "tgn:id":7488668,
    "tgn:name":"Nanshiningbu Xi",
    "tgn:placetype":[
        "aat:300008699"
    ]
},
  "bbox": [],
  "geometry": {"coordinates":[121.382305,23.241325],"type":"Point"}
}
=======
{"geometry":{"type":"Point","coordinates":[121.382305,23.241325]},"type":"Feature","properties":{"hierarchy":["tgn:7488668","tgn:1000004","tgn:7491221","tgn:1000141","tgn:7029392"],"placetype":["aat:300008699"],"id":7488668,"name:xx":"Nanshiningbu Xi"}}
>>>>>>> 03f74aca74312dbeaf24d7e61306dd6a786dc3d0
