{
  "id": 2771276,
  "type": "Feature",
  "properties": {
    "tgn:hierarchy":[
        "tgn:2771276",
        "tgn:1000001",
        "tgn:7012149",
        "tgn:1002728",
        "tgn:7007709",
        "tgn:7029392"
    ],
    "tgn:id":2771276,
    "tgn:name":"Wildcat Swamp",
    "tgn:placetype":[
        "aat:300008699"
    ]
},
  "bbox": [],
  "geometry": {"coordinates":[-77.3833,36.4333],"type":"Point"}
}