{
  "id": 7047862,
  "type": "Feature",
  "properties": {
    "tgn:hierarchy":[
        "tgn:7047862",
        "tgn:1003460",
        "tgn:1000003",
        "tgn:7009760",
        "tgn:1000080",
        "tgn:7029392"
    ],
    "tgn:id":7047862,
    "tgn:name":"Grande, Cala",
    "tgn:placetype":[
        "aat:300132317"
    ]
},
  "bbox": [],
  "geometry": {"coordinates":[11.083333,42.433333],"type":"Point"}
}