{
  "id": 1037546,
  "type": "Feature",
  "properties": {
    "tgn:hierarchy":[
        "tgn:1037546",
        "tgn:7000096",
        "tgn:1000003",
        "tgn:7000084",
        "tgn:7029392"
    ],
    "tgn:id":1037546,
    "tgn:name":"R\u00fcdnitz",
    "tgn:placetype":[
        "aat:300008347"
    ]
},
  "bbox": [],
  "geometry": {"coordinates":[13.616667,52.716667],"type":"Point"}
}