{
  "id": 7129398,
  "type": "Feature",
  "properties": {
    "tgn:hierarchy":[
        "tgn:7129398",
        "tgn:1000003",
        "tgn:7003687",
        "tgn:7000084",
        "tgn:7029392"
    ],
    "tgn:id":7129398,
    "tgn:name":"Mellin",
    "tgn:placetype":[
        "aat:300008347"
    ]
},
  "bbox": [],
  "geometry": {"coordinates":[10.983333,52.65],"type":"Point"}
}