{
  "id": 2531535,
  "type": "Feature",
  "properties": {
    "tgn:hierarchy":[
        "tgn:2531535",
        "tgn:1000001",
        "tgn:7012149",
        "tgn:7018871",
        "tgn:7007920",
        "tgn:7029392"
    ],
    "tgn:id":2531535,
    "tgn:name":"Mule Spring",
    "tgn:placetype":[
        "aat:300008697"
    ]
},
  "bbox": [],
  "geometry": {"coordinates":[-121.6167,47.1833],"type":"Point"}
}