{
  "id": 2130915,
  "type": "Feature",
  "properties": {
    "tgn:hierarchy":[
        "tgn:2130915",
        "tgn:1000001",
        "tgn:7016172",
        "tgn:2000121",
        "tgn:7012149",
        "tgn:7029392"
    ],
    "tgn:id":2130915,
    "tgn:name":"Alma, Lake",
    "tgn:placetype":[
        "aat:300006191"
    ]
},
  "bbox": [],
  "geometry": {"coordinates":[-94.2167,35.4833],"type":"Point"}
}