{
  "id": 7538561,
  "type": "Feature",
  "properties": {
    "tgn:hierarchy":[
        "tgn:7538561",
        "tgn:7001242",
        "tgn:7016833",
        "tgn:1001114",
        "tgn:7029392"
    ],
    "tgn:id":7538561,
    "tgn:name:en":"Ma\u015fra', \u1e28aw\u1e11",
    "tgn:placetype":[
        "aat:300343519"
    ]
},
  "bbox": [],
  "geometry": {"coordinates":[31.05,27.216667],"type":"Point"}
}