{
  "id": 7007876,
  "type": "Feature",
  "properties": {
    "tgn:hierarchy":[
        "tgn:7007876",
        "tgn:7003456",
        "tgn:1000003",
        "tgn:1000063",
        "tgn:7018236",
        "tgn:7029392"
    ],
    "tgn:id":7007876,
    "tgn:name":"Duffel",
    "tgn:placetype":[
        "aat:300008347"
    ]
},
  "bbox": [],
  "geometry": {"coordinates":[4.501418,51.095756],"type":"Point"}
}