<<<<<<< HEAD
{
  "id": 2153480,
  "type": "Feature",
  "properties": {
    "tgn:hierarchy":[
        "tgn:2153480",
        "tgn:1000001",
        "tgn:2000769",
        "tgn:7012149",
        "tgn:7007255",
        "tgn:7029392"
    ],
    "tgn:id":2153480,
    "tgn:name":"Beans Fork",
    "tgn:placetype":[
        "aat:300008699"
    ]
},
  "bbox": [],
  "geometry": {"coordinates":[-83.7833,36.6333],"type":"Point"}
}
=======
{"geometry":{"type":"Point","coordinates":[-83.783300,36.633300]},"type":"Feature","properties":{"hierarchy":["tgn:2153480","tgn:1000001","tgn:2000769","tgn:7012149","tgn:7007255","tgn:7029392"],"placetype":["aat:300008699"],"id":2153480,"name:xx":"Beans Fork"}}
>>>>>>> 03f74aca74312dbeaf24d7e61306dd6a786dc3d0
