{
  "id": 2534232,
  "type": "Feature",
  "properties": {
    "tgn:hierarchy":[
        "tgn:2534232",
        "tgn:1000001",
        "tgn:7012149",
        "tgn:2002005",
        "tgn:7007826",
        "tgn:7029392"
    ],
    "tgn:id":2534232,
    "tgn:name":"Mystery Tank",
    "tgn:placetype":[
        "aat:300006191"
    ]
},
  "bbox": [],
  "geometry": {"coordinates":[-105.3667,31.4167],"type":"Point"}
}