{
  "id": 2222234,
  "type": "Feature",
  "properties": {
    "tgn:hierarchy":[
        "tgn:2222234",
        "tgn:1000001",
        "tgn:7012149",
        "tgn:1002790",
        "tgn:7007240",
        "tgn:7029392"
    ],
    "tgn:id":2222234,
    "tgn:name":"Carol, Lake",
    "tgn:placetype":[
        "aat:300008680"
    ]
},
  "bbox": [],
  "geometry": {"coordinates":[-82.7833,27.8333],"type":"Point"}
}