{
  "id": 2370639,
  "type": "Feature",
  "properties": {
    "tgn:hierarchy":[
        "tgn:2370639",
        "tgn:1000001",
        "tgn:2001350",
        "tgn:7012149",
        "tgn:7007525",
        "tgn:7029392"
    ],
    "tgn:id":2370639,
    "tgn:name":"Hackberry Lake",
    "tgn:placetype":[
        "aat:300008680"
    ]
},
  "bbox": [],
  "geometry": {"coordinates":[-102.4333,41.7167],"type":"Point"}
}