{
  "id": 2458592,
  "type": "Feature",
  "properties": {
    "tgn:hierarchy":[
        "tgn:2458592",
        "tgn:1000001",
        "tgn:7012149",
        "tgn:7007157",
        "tgn:2000187",
        "tgn:7029392"
    ],
    "tgn:id":2458592,
    "tgn:name":"Little North Valley Creek",
    "tgn:placetype":[
        "aat:300008706"
    ]
},
  "bbox": [],
  "geometry": {"coordinates":[-121.3833,39.95],"type":"Point"}
}