{
  "id": 7387426,
  "type": "Feature",
  "properties": {
    "tgn:hierarchy":[
        "tgn:7387426",
        "tgn:7005580",
        "tgn:1000001",
        "tgn:7005560",
        "tgn:7029392"
    ],
    "tgn:id":7387426,
    "tgn:name":"Portaceli",
    "tgn:placetype":[
        "aat:300008347"
    ]
},
  "bbox": [],
  "geometry": {"coordinates":[-93.133333,16.466667],"type":"Point"}
}