<<<<<<< HEAD
{
  "id": 7368434,
  "type": "Feature",
  "properties": {
    "tgn:hierarchy":[
        "tgn:7368434",
        "tgn:1000001",
        "tgn:7005590",
        "tgn:7005560",
        "tgn:7029392"
    ],
    "tgn:id":7368434,
    "tgn:name":"Joya de Ballesteros",
    "tgn:placetype":[
        "aat:300008347"
    ]
},
  "bbox": [],
  "geometry": {"coordinates":[-103.0,19.0],"type":"Point"}
}
=======
{"geometry":{"type":"Point","coordinates":[-103.000000,19.000000]},"type":"Feature","properties":{"hierarchy":["tgn:7368434","tgn:1000001","tgn:7005590","tgn:7005560","tgn:7029392"],"placetype":["aat:300008347"],"id":7368434,"name:xx":"Joya de Ballesteros"}}
>>>>>>> 03f74aca74312dbeaf24d7e61306dd6a786dc3d0
