{
  "id": 7312296,
  "type": "Feature",
  "properties": {
    "tgn:hierarchy":[
        "tgn:7312296",
        "tgn:1001768",
        "tgn:1000049",
        "tgn:1000002",
        "tgn:7029392"
    ],
    "tgn:id":7312296,
    "tgn:name":"Las Achupallas",
    "tgn:placetype":[
        "aat:300008347"
    ]
},
  "bbox": [],
  "geometry": {"coordinates":[-70.616667,-32.516667],"type":"Point"}
}