{
  "id": 2515421,
  "type": "Feature",
  "properties": {
    "tgn:hierarchy":[
        "tgn:2515421",
        "tgn:1000001",
        "tgn:7012149",
        "tgn:7029392"
    ],
    "tgn:id":2515421,
    "tgn:name":"Millrace Slough",
    "tgn:placetype":[
        "aat:300008699"
    ]
},
  "bbox": [],
  "geometry": {"coordinates":[-88.1167,37.7167],"type":"Point"}
}