{
  "id": 2482276,
  "type": "Feature",
  "properties": {
    "tgn:hierarchy":[
        "tgn:2482276",
        "tgn:1000001",
        "tgn:7012149",
        "tgn:1002897",
        "tgn:7007920",
        "tgn:7029392"
    ],
    "tgn:id":2482276,
    "tgn:name":"Langille Creek",
    "tgn:placetype":[
        "aat:300008706"
    ]
},
  "bbox": [],
  "geometry": {"coordinates":[-121.8167,46.3333],"type":"Point"}
}