<<<<<<< HEAD
{
  "id": 7352362,
  "type": "Feature",
  "properties": {
    "tgn:hierarchy":[
        "tgn:7352362",
        "tgn:1000001",
        "tgn:7005597",
        "tgn:7005560",
        "tgn:7029392"
    ],
    "tgn:id":7352362,
    "tgn:name":"Barril, Cerro del",
    "tgn:placetype":[
        "aat:300008795"
    ]
},
  "bbox": [],
  "geometry": {"coordinates":[-99.083333,24.633333],"type":"Point"}
}
=======
{"geometry":{"type":"Point","coordinates":[-99.083333,24.633333]},"type":"Feature","properties":{"hierarchy":["tgn:7352362","tgn:1000001","tgn:7005597","tgn:7005560","tgn:7029392"],"placetype":["aat:300008795"],"id":7352362,"name:xx":"Barril, Cerro del"}}
>>>>>>> 03f74aca74312dbeaf24d7e61306dd6a786dc3d0
