{
  "id": 2198773,
  "type": "Feature",
  "properties": {
    "tgn:hierarchy":[
        "tgn:2198773",
        "tgn:2002137",
        "tgn:1000001",
        "tgn:7012149",
        "tgn:7007919",
        "tgn:7029392"
    ],
    "tgn:id":2198773,
    "tgn:name":"Brownsville",
    "tgn:placetype":[
        "aat:300008347"
    ]
},
  "bbox": [],
  "geometry": {"coordinates":[-78.6833,38.05],"type":"Point"}
}