{
  "id": 7241097,
  "type": "Feature",
  "properties": {
    "tgn:hierarchy":[
        "tgn:7241097",
        "tgn:7003457",
        "tgn:1000003",
        "tgn:1000063",
        "tgn:7018236",
        "tgn:7029392"
    ],
    "tgn:id":7241097,
    "tgn:name":"Hendeken",
    "tgn:placetype":[
        "aat:300008347"
    ]
},
  "bbox": [],
  "geometry": {"coordinates":[3.716667,51.233333],"type":"Point"}
}