<<<<<<< HEAD
{
  "id": 2766929,
  "type": "Feature",
  "properties": {
    "tgn:hierarchy":[
        "tgn:2766929",
        "tgn:1000001",
        "tgn:2001477",
        "tgn:7012149",
        "tgn:7007709",
        "tgn:7029392"
    ],
    "tgn:id":2766929,
    "tgn:name":"White Point",
    "tgn:placetype":[
        "aat:300008850"
    ]
},
  "bbox": [],
  "geometry": {"coordinates":[-76.55,34.7],"type":"Point"}
}
=======
{"geometry":{"type":"Point","coordinates":[-76.550000,34.700000]},"type":"Feature","properties":{"hierarchy":["tgn:2766929","tgn:1000001","tgn:2001477","tgn:7012149","tgn:7007709","tgn:7029392"],"placetype":["aat:300008850"],"id":2766929,"name:xx":"White Point"}}
>>>>>>> 03f74aca74312dbeaf24d7e61306dd6a786dc3d0
