{
  "id": 7571581,
  "type": "Feature",
  "properties": {
    "tgn:hierarchy":[
        "tgn:7571581",
        "tgn:1000004",
        "tgn:7000198",
        "tgn:7016722",
        "tgn:7029392"
    ],
    "tgn:id":7571581,
    "tgn:name:en":"Kaml\u0101pur",
    "tgn:placetype":[
        "aat:300008347"
    ]
},
  "bbox": [],
  "geometry": {"coordinates":[80.819312,27.381127],"type":"Point"}
}