{
  "id": 7154985,
  "type": "Feature",
  "properties": {
    "tgn:hierarchy":[
        "tgn:7154985",
        "tgn:7003692",
        "tgn:1000003",
        "tgn:7000084",
        "tgn:7029392"
    ],
    "tgn:id":7154985,
    "tgn:name":"Kleine Hasbach",
    "tgn:placetype":[
        "aat:300008863"
    ]
},
  "bbox": [],
  "geometry": {"coordinates":[9.15,49.383333],"type":"Point"}
}