{
  "id": 2253016,
  "type": "Feature",
  "properties": {
    "tgn:hierarchy":[
        "tgn:2253016",
        "tgn:1000001",
        "tgn:7012149",
        "tgn:7007157",
        "tgn:1002608",
        "tgn:7029392"
    ],
    "tgn:id":2253016,
    "tgn:name":"Consolidated Slip",
    "tgn:placetype":[
        "aat:300008678"
    ]
},
  "bbox": [],
  "geometry": {"coordinates":[-118.2333,33.7667],"type":"Point"}
}