{
  "id": 2389126,
  "type": "Feature",
  "properties": {
    "tgn:hierarchy":[
        "tgn:2389126",
        "tgn:1000001",
        "tgn:7006451",
        "tgn:7012149",
        "tgn:2000101",
        "tgn:7029392"
    ],
    "tgn:id":2389126,
    "tgn:name":"Hidden Valley",
    "tgn:placetype":[
        "aat:300008761"
    ]
},
  "bbox": [],
  "geometry": {"coordinates":[-112.1833,32.9833],"type":"Point"}
}