{
  "id": 7188424,
  "type": "Feature",
  "properties": {
    "tgn:hierarchy":[
        "tgn:7188424",
        "tgn:1000003",
        "tgn:7003676",
        "tgn:7000084",
        "tgn:7029392"
    ],
    "tgn:id":7188424,
    "tgn:name":"Eistruper Berg",
    "tgn:placetype":[
        "aat:300008777"
    ]
},
  "bbox": [],
  "geometry": {"coordinates":[8.133333,52.25],"type":"Point"}
}