{
  "id": 2144416,
  "type": "Feature",
  "properties": {
    "tgn:hierarchy":[
        "tgn:2144416",
        "tgn:1000001",
        "tgn:7012149",
        "tgn:2002251",
        "tgn:7007920",
        "tgn:7029392"
    ],
    "tgn:id":2144416,
    "tgn:name":"Baker-Langdon",
    "tgn:placetype":[
        "aat:300008347"
    ]
},
  "bbox": [],
  "geometry": {"coordinates":[-118.3167,46.0167],"type":"Point"}
}