{
  "id": 7489270,
  "type": "Feature",
  "properties": {
    "tgn:hierarchy":[
        "tgn:7489270",
        "tgn:1000004",
        "tgn:7490934",
        "tgn:1000141",
        "tgn:7029392"
    ],
    "tgn:id":7489270,
    "tgn:name":"Neibukeng",
    "tgn:placetype":[
        "aat:300008347"
    ]
},
  "bbox": [],
  "geometry": {"coordinates":[120.425035,23.155626],"type":"Point"}
}