{
  "id": 7535758,
  "type": "Feature",
  "properties": {
    "tgn:hierarchy":[
        "tgn:7535758",
        "tgn:7001242",
        "tgn:7016833",
        "tgn:1001113",
        "tgn:7029392"
    ],
    "tgn:id":7535758,
    "tgn:name:en":"Kafr al 'Iy\u0101d\u0101t",
    "tgn:placetype":[
        "aat:300008347"
    ]
},
  "bbox": [],
  "geometry": {"coordinates":[31.816667,30.716667],"type":"Point"}
}