<<<<<<< HEAD
{
  "id": 2404871,
  "type": "Feature",
  "properties": {
    "tgn:hierarchy":[
        "tgn:2404871",
        "tgn:1000001",
        "tgn:7012149",
        "tgn:2001714",
        "tgn:7007708",
        "tgn:7029392"
    ],
    "tgn:id":2404871,
    "tgn:name":"Huckleberry Spring",
    "tgn:placetype":[
        "aat:300008697"
    ]
},
  "bbox": [],
  "geometry": {"coordinates":[-121.5833,43.1833],"type":"Point"}
}
=======
{"geometry":{"type":"Point","coordinates":[-121.583300,43.183300]},"type":"Feature","properties":{"hierarchy":["tgn:2404871","tgn:1000001","tgn:7012149","tgn:2001714","tgn:7007708","tgn:7029392"],"placetype":["aat:300008697"],"id":2404871,"name:xx":"Huckleberry Spring"}}
>>>>>>> 03f74aca74312dbeaf24d7e61306dd6a786dc3d0
