{
  "id": 2494107,
  "type": "Feature",
  "properties": {
    "tgn:hierarchy":[
        "tgn:2494107",
        "tgn:1000001",
        "tgn:7012149",
        "tgn:1002636",
        "tgn:7007708",
        "tgn:7029392"
    ],
    "tgn:id":2494107,
    "tgn:name":"Marten Buttes",
    "tgn:placetype":[
        "aat:300008798"
    ]
},
  "bbox": [],
  "geometry": {"coordinates":[-122.1833,44.7833],"type":"Point"}
}