{
  "id": 7562825,
  "type": "Feature",
  "properties": {
    "tgn:hierarchy":[
        "tgn:7562825",
        "tgn:1000004",
        "tgn:7000198",
        "tgn:7016722",
        "tgn:7029392"
    ],
    "tgn:id":7562825,
    "tgn:name:en":"Bhareta",
    "tgn:placetype":[
        "aat:300008347"
    ]
},
  "bbox": [],
  "geometry": {"coordinates":[79.119747,26.484653],"type":"Point"}
}