{
  "id": 2527572,
  "type": "Feature",
  "properties": {
    "tgn:hierarchy":[
        "tgn:2527572",
        "tgn:7013388",
        "tgn:1000001",
        "tgn:7012149",
        "tgn:7007517",
        "tgn:7029392"
    ],
    "tgn:id":2527572,
    "tgn:name":"Mount Washington State Forest",
    "tgn:placetype":[
        "aat:300008863"
    ]
},
  "bbox": [],
  "geometry": {"coordinates":[-73.4667,42.1333],"type":"Point"}
}