<<<<<<< HEAD
{
  "id": 7484998,
  "type": "Feature",
  "properties": {
    "tgn:hierarchy":[
        "tgn:7484998",
        "tgn:7488858",
        "tgn:1000004",
        "tgn:1000141",
        "tgn:7029392"
    ],
    "tgn:id":7484998,
    "tgn:name":"Huisun Ling",
    "tgn:placetype":[
        "aat:300008798"
    ]
},
  "bbox": [],
  "geometry": {"coordinates":[121.033889,24.094167],"type":"Point"}
}
=======
{"geometry":{"type":"Point","coordinates":[121.033889,24.094167]},"type":"Feature","properties":{"hierarchy":["tgn:7484998","tgn:7488858","tgn:1000004","tgn:1000141","tgn:7029392"],"placetype":["aat:300008798"],"id":7484998,"name:xx":"Huisun Ling"}}
>>>>>>> 03f74aca74312dbeaf24d7e61306dd6a786dc3d0
