{
  "id": 2526903,
  "type": "Feature",
  "properties": {
    "tgn:hierarchy":[
        "tgn:2526903",
        "tgn:2002101",
        "tgn:1000001",
        "tgn:7012149",
        "tgn:7007827",
        "tgn:7029392"
    ],
    "tgn:id":2526903,
    "tgn:name":"Mound Pond",
    "tgn:placetype":[
        "aat:300008680"
    ]
},
  "bbox": [],
  "geometry": {"coordinates":[-113.0333,38.1833],"type":"Point"}
}