{
  "id": 7004107,
  "type": "Feature",
  "properties": {
    "tgn:hierarchy":[
        "tgn:7004107",
        "tgn:7003248",
        "tgn:1000003",
        "tgn:7010380",
        "tgn:1000080",
        "tgn:7029392"
    ],
    "tgn:id":7004107,
    "tgn:name":"Ruvo di Puglia",
    "tgn:placetype":[
        "aat:300387277",
        "aat:300008347",
        "aat:300387235",
        "aat:300008375"
    ]
},
  "bbox": [],
  "geometry": {"coordinates":[16.483333,41.116667],"type":"Point"}
}