{
  "id": 1078797,
  "type": "Feature",
  "properties": {
    "tgn:hierarchy":[
        "tgn:1078797",
        "tgn:1000004",
        "tgn:1001548",
        "tgn:1000116",
        "tgn:7029392"
    ],
    "tgn:id":1078797,
    "tgn:name":"Tokala",
    "tgn:placetype":[
        "aat:300008347"
    ]
},
  "bbox": [],
  "geometry": {"coordinates":[121.7167,-1.7833],"type":"Point"}
}