{
  "id": 7393202,
  "type": "Feature",
  "properties": {
    "tgn:hierarchy":[
        "tgn:7393202",
        "tgn:1000001",
        "tgn:1001960",
        "tgn:7005560",
        "tgn:7029392"
    ],
    "tgn:id":7393202,
    "tgn:name":"Rancho San Jorge",
    "tgn:placetype":[
        "aat:300000241"
    ]
},
  "bbox": [],
  "geometry": {"coordinates":[-110.366667,29.616667],"type":"Point"}
}