{
  "id": 2639051,
  "type": "Feature",
  "properties": {
    "tgn:hierarchy":[
        "tgn:2639051",
        "tgn:1002157",
        "tgn:1000001",
        "tgn:7012149",
        "tgn:7007565",
        "tgn:7029392"
    ],
    "tgn:id":2639051,
    "tgn:name":"Salt Island",
    "tgn:placetype":[
        "aat:300008791"
    ]
},
  "bbox": [],
  "geometry": {"coordinates":[-74.3333,39.4667],"type":"Point"}
}