{
  "id": 2455783,
  "type": "Feature",
  "properties": {
    "tgn:hierarchy":[
        "tgn:2455783",
        "tgn:1000001",
        "tgn:7012149",
        "tgn:2001206",
        "tgn:7007523",
        "tgn:7029392"
    ],
    "tgn:id":2455783,
    "tgn:name":"Little Greasy Creek",
    "tgn:placetype":[
        "aat:300008706"
    ]
},
  "bbox": [],
  "geometry": {"coordinates":[-91.7667,36.7333],"type":"Point"}
}