{
  "id": 2169741,
  "type": "Feature",
  "properties": {
    "tgn:hierarchy":[
        "tgn:2169741",
        "tgn:1000001",
        "tgn:2002263",
        "tgn:7012149",
        "tgn:7013961",
        "tgn:7029392"
    ],
    "tgn:id":2169741,
    "tgn:name":"Big Mountain",
    "tgn:placetype":[
        "aat:300008798"
    ]
},
  "bbox": [],
  "geometry": {"coordinates":[-79.1833,38.95],"type":"Point"}
}