{
  "id": 2729695,
  "type": "Feature",
  "properties": {
    "tgn:hierarchy":[
        "tgn:2729695",
        "tgn:1000001",
        "tgn:2002150",
        "tgn:7012149",
        "tgn:7007919",
        "tgn:7029392"
    ],
    "tgn:id":2729695,
    "tgn:name":"Troublesome Creek",
    "tgn:placetype":[
        "aat:300008706"
    ]
},
  "bbox": [],
  "geometry": {"coordinates":[-79.1833,37.2333],"type":"Point"}
}