{
  "id": 1038190,
  "type": "Feature",
  "properties": {
    "tgn:hierarchy":[
        "tgn:1038190",
        "tgn:7003692",
        "tgn:1000003",
        "tgn:7000084",
        "tgn:7029392"
    ],
    "tgn:id":1038190,
    "tgn:name":"Altglash\u00fctten",
    "tgn:placetype":[
        "aat:300008347"
    ]
},
  "bbox": [],
  "geometry": {"coordinates":[8.116667,47.85],"type":"Point"}
}