{
  "id": 2193632,
  "type": "Feature",
  "properties": {
    "tgn:hierarchy":[
        "tgn:2193632",
        "tgn:1000001",
        "tgn:7012149",
        "tgn:2002281",
        "tgn:7013961",
        "tgn:7029392"
    ],
    "tgn:id":2193632,
    "tgn:name":"Brewer Hill",
    "tgn:placetype":[
        "aat:300008347"
    ]
},
  "bbox": [],
  "geometry": {"coordinates":[-79.9833,39.65],"type":"Point"}
}