{
  "id": 2240246,
  "type": "Feature",
  "properties": {
    "tgn:hierarchy":[
        "tgn:2240246",
        "tgn:1000001",
        "tgn:7012149",
        "tgn:2001447",
        "tgn:7007566",
        "tgn:7029392"
    ],
    "tgn:id":2240246,
    "tgn:name":"Cirhuelas Canyon",
    "tgn:placetype":[
        "aat:300008761"
    ]
},
  "bbox": [],
  "geometry": {"coordinates":[-105.7667,33.0667],"type":"Point"}
}