{
  "id": 7548091,
  "type": "Feature",
  "properties": {
    "tgn:hierarchy":[
        "tgn:7548091",
        "tgn:1000004",
        "tgn:7000198",
        "tgn:1001895",
        "tgn:7029392"
    ],
    "tgn:id":7548091,
    "tgn:name:en":"Bhalwani",
    "tgn:placetype":[
        "aat:300007783"
    ]
},
  "bbox": [],
  "geometry": {"coordinates":[75.207089,18.21064],"type":"Point"}
}