{
  "id": 1137330,
  "type": "Feature",
  "properties": {
    "tgn:hierarchy":[
        "tgn:1137330",
        "tgn:1000004",
        "tgn:7011628",
        "tgn:7014835",
        "tgn:7029392"
    ],
    "tgn:id":1137330,
    "tgn:name":"Buston",
    "tgn:placetype":[
        "aat:300008347"
    ]
},
  "bbox": [],
  "geometry": {"coordinates":[69.3167,40.5167],"type":"Point"}
}