{
  "id": 2497914,
  "type": "Feature",
  "properties": {
    "tgn:hierarchy":[
        "tgn:2497914",
        "tgn:1000001",
        "tgn:7012149",
        "tgn:2000885",
        "tgn:7007256",
        "tgn:7029392"
    ],
    "tgn:id":2497914,
    "tgn:name":"Mayhaw Branch",
    "tgn:placetype":[
        "aat:300008699"
    ]
},
  "bbox": [],
  "geometry": {"coordinates":[-90.65,30.5333],"type":"Point"}
}