{
  "id": 1035511,
  "type": "Feature",
  "properties": {
    "tgn:hierarchy":[
        "tgn:1035511",
        "tgn:1000003",
        "tgn:7002883",
        "tgn:1000070",
        "tgn:7029392"
    ],
    "tgn:id":1035511,
    "tgn:name":"Saint-R\u00e9my-l'Honor\u00e9",
    "tgn:placetype":[
        "aat:300008347"
    ]
},
  "bbox": [],
  "geometry": {"coordinates":[1.8833,48.75],"type":"Point"}
}