{
  "id": 7206500,
  "type": "Feature",
  "properties": {
    "tgn:hierarchy":[
        "tgn:7206500",
        "tgn:7003669",
        "tgn:1000003",
        "tgn:7000084",
        "tgn:7029392"
    ],
    "tgn:id":7206500,
    "tgn:name":"Buch-Wald",
    "tgn:placetype":[
        "aat:300008863"
    ]
},
  "bbox": [],
  "geometry": {"coordinates":[10.966667,47.833333],"type":"Point"}
}