<<<<<<< HEAD
{
  "id": 2151501,
  "type": "Feature",
  "properties": {
    "tgn:hierarchy":[
        "tgn:2151501",
        "tgn:1000001",
        "tgn:7012149",
        "tgn:2000378",
        "tgn:7007248",
        "tgn:7029392"
    ],
    "tgn:id":2151501,
    "tgn:name":"Batson",
    "tgn:placetype":[
        "aat:300008347"
    ]
},
  "bbox": [],
  "geometry": {"coordinates":[-83.0667,32.3],"type":"Point"}
}
=======
{"geometry":{"type":"Point","coordinates":[-83.066700,32.300000]},"type":"Feature","properties":{"hierarchy":["tgn:2151501","tgn:1000001","tgn:7012149","tgn:2000378","tgn:7007248","tgn:7029392"],"placetype":["aat:300008347"],"id":2151501,"name:xx":"Batson"}}
>>>>>>> 03f74aca74312dbeaf24d7e61306dd6a786dc3d0
