{
  "id": 2306005,
  "type": "Feature",
  "properties": {
    "tgn:hierarchy":[
        "tgn:2306005",
        "tgn:1000001",
        "tgn:7012149",
        "tgn:1002586",
        "tgn:7007710",
        "tgn:7029392"
    ],
    "tgn:id":2306005,
    "tgn:name":"East Fogelsville",
    "tgn:placetype":[
        "aat:300008347"
    ]
},
  "bbox": [],
  "geometry": {"coordinates":[-75.6167,40.5833],"type":"Point"}
}