{
  "id": 1050521,
  "type": "Feature",
  "properties": {
    "tgn:hierarchy":[
        "tgn:1050521",
        "tgn:7002444",
        "tgn:1000003",
        "tgn:7019100",
        "tgn:7008591",
        "tgn:7029392"
    ],
    "tgn:id":1050521,
    "tgn:name:en":"Chapelhall",
    "tgn:placetype":[
        "aat:300008347"
    ]
},
  "bbox": [],
  "geometry": {"coordinates":[-3.933333,55.833333],"type":"Point"}
}