{
  "id": 2202062,
  "type": "Feature",
  "properties": {
    "tgn:hierarchy":[
        "tgn:2202062",
        "tgn:1000001",
        "tgn:7012149",
        "tgn:2000832",
        "tgn:7007255",
        "tgn:7029392"
    ],
    "tgn:id":2202062,
    "tgn:name":"Buck Knob",
    "tgn:placetype":[
        "aat:300008798"
    ]
},
  "bbox": [],
  "geometry": {"coordinates":[-87.1167,37.1833],"type":"Point"}
}