{
  "id": 2760211,
  "type": "Feature",
  "properties": {
    "tgn:hierarchy":[
        "tgn:2760211",
        "tgn:1000001",
        "tgn:2002109",
        "tgn:7012149",
        "tgn:7007827",
        "tgn:7029392"
    ],
    "tgn:id":2760211,
    "tgn:name":"West Fork Reservoir",
    "tgn:placetype":[
        "aat:300006191"
    ]
},
  "bbox": [],
  "geometry": {"coordinates":[-111.4833,38.0333],"type":"Point"}
}