{
  "id": 1126728,
  "type": "Feature",
  "properties": {
    "tgn:hierarchy":[
        "tgn:1126728",
        "tgn:1000003",
        "tgn:7006541",
        "tgn:7029392"
    ],
    "tgn:id":1126728,
    "tgn:name":"Malta",
    "tgn:placetype":[
        "aat:300008707"
    ]
},
  "bbox": [],
  "geometry": {"coordinates":[26.8833,56.7333],"type":"Point"}
}