{
  "id": 7569647,
  "type": "Feature",
  "properties": {
    "tgn:hierarchy":[
        "tgn:7569647",
        "tgn:1000004",
        "tgn:7000198",
        "tgn:7016788",
        "tgn:7029392"
    ],
    "tgn:id":7569647,
    "tgn:name:en":"M\u0101ngli Kal\u0101n",
    "tgn:placetype":[
        "aat:300008347"
    ]
},
  "bbox": [],
  "geometry": {"coordinates":[75.504167,25.521944],"type":"Point"}
}