{
  "id": 7489799,
  "type": "Feature",
  "properties": {
    "tgn:hierarchy":[
        "tgn:7489799",
        "tgn:1000004",
        "tgn:7001014",
        "tgn:1000141",
        "tgn:7029392"
    ],
    "tgn:id":7489799,
    "tgn:name":"Shezikeng",
    "tgn:placetype":[
        "aat:300008347"
    ]
},
  "bbox": [],
  "geometry": {"coordinates":[120.623333,23.693333],"type":"Point"}
}