<<<<<<< HEAD
{
  "id": 7489799,
  "type": "Feature",
  "properties": {
    "tgn:hierarchy":[
        "tgn:7489799",
        "tgn:1000004",
        "tgn:7001014",
        "tgn:1000141",
        "tgn:7029392"
    ],
    "tgn:id":7489799,
    "tgn:name":"Shezikeng",
    "tgn:placetype":[
        "aat:300008347"
    ]
},
  "bbox": [],
  "geometry": {"coordinates":[120.623333,23.693333],"type":"Point"}
}
=======
{"geometry":{"type":"Point","coordinates":[120.623333,23.693333]},"type":"Feature","properties":{"hierarchy":["tgn:7489799","tgn:1000004","tgn:7001014","tgn:1000141","tgn:7029392"],"placetype":["aat:300008347"],"id":7489799,"name:xx":"Shezikeng"}}
>>>>>>> 03f74aca74312dbeaf24d7e61306dd6a786dc3d0
