<<<<<<< HEAD
{
  "id": 7483557,
  "type": "Feature",
  "properties": {
    "tgn:hierarchy":[
        "tgn:7483557",
        "tgn:1000004",
        "tgn:7471332",
        "tgn:1000141",
        "tgn:7029392"
    ],
    "tgn:id":7483557,
    "tgn:name":"Jiugang Daqiao",
    "tgn:placetype":[
        "aat:300007836"
    ]
},
  "bbox": [],
  "geometry": {"coordinates":[120.941111,24.842222],"type":"Point"}
}
=======
{"geometry":{"type":"Point","coordinates":[120.941111,24.842222]},"type":"Feature","properties":{"hierarchy":["tgn:7483557","tgn:1000004","tgn:7471332","tgn:1000141","tgn:7029392"],"placetype":["aat:300007836"],"id":7483557,"name:xx":"Jiugang Daqiao"}}
>>>>>>> 03f74aca74312dbeaf24d7e61306dd6a786dc3d0
