<<<<<<< HEAD
{
  "id": 2765011,
  "type": "Feature",
  "properties": {
    "tgn:hierarchy":[
        "tgn:2765011",
        "tgn:2002142",
        "tgn:1000001",
        "tgn:7012149",
        "tgn:7007919",
        "tgn:7029392"
    ],
    "tgn:id":2765011,
    "tgn:name":"Whisky Creek",
    "tgn:placetype":[
        "aat:300008706"
    ]
},
  "bbox": [],
  "geometry": {"coordinates":[-79.2333,38.2167],"type":"Point"}
}
=======
{"geometry":{"type":"Point","coordinates":[-79.233300,38.216700]},"type":"Feature","properties":{"hierarchy":["tgn:2765011","tgn:2002142","tgn:1000001","tgn:7012149","tgn:7007919","tgn:7029392"],"placetype":["aat:300008706"],"id":2765011,"name:xx":"Whisky Creek"}}
>>>>>>> 03f74aca74312dbeaf24d7e61306dd6a786dc3d0
