{
  "id": 7590958,
  "type": "Feature",
  "properties": {
    "tgn:hierarchy":[
        "tgn:7590958",
        "tgn:1000004",
        "tgn:7000198",
        "tgn:7000799",
        "tgn:7029392"
    ],
    "tgn:id":7590958,
    "tgn:name:en":"Gura Man\u0101hasam",
    "tgn:placetype":[
        "aat:300008347"
    ]
},
  "bbox": [],
  "geometry": {"coordinates":[74.572229,32.775986],"type":"Point"}
}