{
  "id": 7031636,
  "type": "Feature",
  "properties": {
    "tgn:hierarchy":[
        "tgn:7031636",
        "tgn:7001242",
        "tgn:7015031",
        "tgn:7001660",
        "tgn:7029392"
    ],
    "tgn:id":7031636,
    "tgn:name":"Kolonyama",
    "tgn:placetype":[
        "aat:300008347"
    ]
},
  "bbox": [],
  "geometry": {"coordinates":[27.745,-29.066],"type":"Point"}
}