{
  "id": 1101358,
  "type": "Feature",
  "properties": {
    "tgn:hierarchy":[
        "tgn:1101358",
        "tgn:7003655",
        "tgn:1000003",
        "tgn:1000088",
        "tgn:7029392"
    ],
    "tgn:id":1101358,
    "tgn:name":"\u00c5nderdalen Nasjonalpark",
    "tgn:placetype":[
        "aat:300008189"
    ]
},
  "bbox": [],
  "geometry": {"coordinates":[17.2833,69.2333],"type":"Point"}
}