<<<<<<< HEAD
{
  "id": 7368526,
  "type": "Feature",
  "properties": {
    "tgn:hierarchy":[
        "tgn:7368526",
        "tgn:7005586",
        "tgn:1000001",
        "tgn:7005560",
        "tgn:7029392"
    ],
    "tgn:id":7368526,
    "tgn:name":"Juanacatita",
    "tgn:placetype":[
        "aat:300266554",
        "aat:300008699"
    ]
},
  "bbox": [],
  "geometry": {"coordinates":[-104.066667,21.183333],"type":"Point"}
}
=======
{"geometry":{"type":"Point","coordinates":[-104.066667,21.183333]},"type":"Feature","properties":{"hierarchy":["tgn:7368526","tgn:7005586","tgn:1000001","tgn:7005560","tgn:7029392"],"placetype":["aat:300266554","aat:300008699"],"id":7368526,"name:xx":"Juanacatita"}}
>>>>>>> 03f74aca74312dbeaf24d7e61306dd6a786dc3d0
