{
  "id": 7306305,
  "type": "Feature",
  "properties": {
    "tgn:hierarchy":[
        "tgn:7306305",
        "tgn:7002758",
        "tgn:7002821",
        "tgn:1000003",
        "tgn:1000095",
        "tgn:7029392"
    ],
    "tgn:id":7306305,
    "tgn:name":"Los Sevillanos",
    "tgn:placetype":[
        "aat:300008347"
    ]
},
  "bbox": [],
  "geometry": {"coordinates":[-3.166667,36.816667],"type":"Point"}
}