{
  "id": 7589234,
  "type": "Feature",
  "properties": {
    "tgn:hierarchy":[
        "tgn:7589234",
        "tgn:1000004",
        "tgn:7000198",
        "tgn:1001977",
        "tgn:7029392"
    ],
    "tgn:id":7589234,
    "tgn:name:en":"Upper Long Sand",
    "tgn:placetype":[
        "aat:300387036"
    ]
},
  "bbox": [],
  "geometry": {"coordinates":[87.966944,21.578333],"type":"Point"}
}