{
  "id": 7410276,
  "type": "Feature",
  "properties": {
    "tgn:hierarchy":[
        "tgn:7410276",
        "tgn:1000001",
        "tgn:7005592",
        "tgn:7005560",
        "tgn:7029392"
    ],
    "tgn:id":7410276,
    "tgn:name":"Ahuacatl\u00e1n",
    "tgn:placetype":[
        "aat:300008347"
    ]
},
  "bbox": [],
  "geometry": {"coordinates":[-97.55,19.883333],"type":"Point"}
}