{
  "id": 1013608,
  "type": "Feature",
  "properties": {
    "tgn:hierarchy":[
        "tgn:1013608",
        "tgn:7005735",
        "tgn:7005685",
        "tgn:1000001",
        "tgn:7029392"
    ],
    "tgn:id":1013608,
    "tgn:name":"Lund",
    "tgn:placetype":[
        "aat:300008347"
    ]
},
  "bbox": [],
  "geometry": {"coordinates":[-124.7667,50.0167],"type":"Point"}
}