{
  "id": 7435278,
  "type": "Feature",
  "properties": {
    "tgn:hierarchy":[
        "tgn:7435278",
        "tgn:1000001",
        "tgn:1001960",
        "tgn:7005560",
        "tgn:7029392"
    ],
    "tgn:id":7435278,
    "tgn:name":"Estaci\u00f3n Torres",
    "tgn:placetype":[
        "aat:300007783"
    ]
},
  "bbox": [],
  "geometry": {"coordinates":[-114.316667,31.733333],"type":"Point"}
}