{
  "id": 2296108,
  "type": "Feature",
  "properties": {
    "tgn:hierarchy":[
        "tgn:2296108",
        "tgn:1000001",
        "tgn:7012149",
        "tgn:7007248",
        "tgn:7029392"
    ],
    "tgn:id":2296108,
    "tgn:name":"Dry Branch",
    "tgn:placetype":[
        "aat:300008699"
    ]
},
  "bbox": [],
  "geometry": {"coordinates":[-85.2333,34.8333],"type":"Point"}
}