{
  "id": 2051918,
  "type": "Feature",
  "properties": {
    "tgn:hierarchy":[
        "tgn:2051918",
        "tgn:1000001",
        "tgn:7012149",
        "tgn:1003005",
        "tgn:7007520",
        "tgn:7029392"
    ],
    "tgn:id":2051918,
    "tgn:name":"Flat Rock",
    "tgn:placetype":[
        "aat:300008347"
    ]
},
  "bbox": [],
  "geometry": {"coordinates":[-83.2833,42.0833],"type":"Point"}
}