{
  "id": 2461091,
  "type": "Feature",
  "properties": {
    "tgn:hierarchy":[
        "tgn:2461091",
        "tgn:1000001",
        "tgn:7012149",
        "tgn:1003038",
        "tgn:7007517",
        "tgn:7029392"
    ],
    "tgn:id":2461091,
    "tgn:name":"Little Spectacle Pond",
    "tgn:placetype":[
        "aat:300008680"
    ]
},
  "bbox": [],
  "geometry": {"coordinates":[-71.6833,42.5167],"type":"Point"}
}