{
  "id": 1123482,
  "type": "Feature",
  "properties": {
    "tgn:hierarchy":[
        "tgn:1123482",
        "tgn:7003496",
        "tgn:7001201",
        "tgn:1000003",
        "tgn:1000078",
        "tgn:7029392"
    ],
    "tgn:id":1123482,
    "tgn:name":"Doonbeg",
    "tgn:placetype":[
        "aat:300008707"
    ]
},
  "bbox": [],
  "geometry": {"coordinates":[-9.5333,52.7333],"type":"Point"}
}