{
  "id": 7592417,
  "type": "Feature",
  "properties": {
    "tgn:hierarchy":[
        "tgn:7592417",
        "tgn:1000004",
        "tgn:7000198",
        "tgn:7000799",
        "tgn:7029392"
    ],
    "tgn:id":7592417,
    "tgn:name:en":"Domel",
    "tgn:placetype":[
        "aat:300008347"
    ]
},
  "bbox": [],
  "geometry": {"coordinates":[74.958333,32.888889],"type":"Point"}
}