<<<<<<< HEAD
{
  "id": 2407212,
  "type": "Feature",
  "properties": {
    "tgn:hierarchy":[
        "tgn:2407212",
        "tgn:1000001",
        "tgn:7012149",
        "tgn:2001708",
        "tgn:7007708",
        "tgn:7029392"
    ],
    "tgn:id":2407212,
    "tgn:name":"Hunters Spring",
    "tgn:placetype":[
        "aat:300008697"
    ]
},
  "bbox": [],
  "geometry": {"coordinates":[-118.8667,44.8833],"type":"Point"}
}
=======
{"geometry":{"type":"Point","coordinates":[-118.866700,44.883300]},"type":"Feature","properties":{"hierarchy":["tgn:2407212","tgn:1000001","tgn:7012149","tgn:2001708","tgn:7007708","tgn:7029392"],"placetype":["aat:300008697"],"id":2407212,"name:xx":"Hunters Spring"}}
>>>>>>> 03f74aca74312dbeaf24d7e61306dd6a786dc3d0
