{
  "id": 1098205,
  "type": "Feature",
  "properties": {
    "tgn:hierarchy":[
        "tgn:1098205",
        "tgn:7000490",
        "tgn:1000006",
        "tgn:7001834",
        "tgn:7029392"
    ],
    "tgn:id":1098205,
    "tgn:name":"Springvale",
    "tgn:placetype":[
        "aat:300008347"
    ]
},
  "bbox": [],
  "geometry": {"coordinates":[127.5833,-17.8667],"type":"Point"}
}