{
  "id": 1082322,
  "type": "Feature",
  "properties": {
    "tgn:hierarchy":[
        "tgn:1082322",
        "tgn:1001194",
        "tgn:1000004",
        "tgn:7000299",
        "tgn:7029392"
    ],
    "tgn:id":1082322,
    "tgn:name":"Osu-ri",
    "tgn:placetype":[
        "aat:300008347"
    ]
},
  "bbox": [],
  "geometry": {"coordinates":[127.3167,35.5333],"type":"Point"}
}