{
  "id": 7549698,
  "type": "Feature",
  "properties": {
    "tgn:hierarchy":[
        "tgn:7549698",
        "tgn:1000004",
        "tgn:1001871",
        "tgn:7000198",
        "tgn:7029392"
    ],
    "tgn:id":7549698,
    "tgn:name:en":"Dhantori",
    "tgn:placetype":[
        "aat:300008347"
    ]
},
  "bbox": [],
  "geometry": {"coordinates":[76.880029,30.076209],"type":"Point"}
}