{
  "id": 7162821,
  "type": "Feature",
  "properties": {
    "tgn:hierarchy":[
        "tgn:7162821",
        "tgn:1000003",
        "tgn:7003676",
        "tgn:7000084",
        "tgn:7029392"
    ],
    "tgn:id":7162821,
    "tgn:name":"Hornbostel",
    "tgn:placetype":[
        "aat:300008347"
    ]
},
  "bbox": [],
  "geometry": {"coordinates":[9.833333,52.683333],"type":"Point"}
}