<<<<<<< HEAD
{
  "id": 7173626,
  "type": "Feature",
  "properties": {
    "tgn:hierarchy":[
        "tgn:7173626",
        "tgn:7000096",
        "tgn:1000003",
        "tgn:7000084",
        "tgn:7029392"
    ],
    "tgn:id":7173626,
    "tgn:name":"Gro\u00df Nuhnen",
    "tgn:placetype":[
        "aat:300000206"
    ]
},
  "bbox": [],
  "geometry": {"coordinates":[14.5,52.333333],"type":"Point"}
}
=======
{"geometry":{"type":"Point","coordinates":[14.500000,52.333333]},"type":"Feature","properties":{"hierarchy":["tgn:7173626","tgn:7000096","tgn:1000003","tgn:7000084","tgn:7029392"],"placetype":["aat:300000206"],"id":7173626,"name:xx":"Gro\u00df Nuhnen"}}
>>>>>>> 03f74aca74312dbeaf24d7e61306dd6a786dc3d0
