{
  "id": 2702356,
  "type": "Feature",
  "properties": {
    "tgn:hierarchy":[
        "tgn:2702356",
        "tgn:1000001",
        "tgn:7012149",
        "tgn:2002248",
        "tgn:7007920",
        "tgn:7029392"
    ],
    "tgn:id":2702356,
    "tgn:name":"Sullivan Lake",
    "tgn:placetype":[
        "aat:300006191"
    ]
},
  "bbox": [],
  "geometry": {"coordinates":[-117.2833,48.8333],"type":"Point"}
}