<<<<<<< HEAD
{
  "id": 7240514,
  "type": "Feature",
  "properties": {
    "tgn:hierarchy":[
        "tgn:7240514",
        "tgn:7003466",
        "tgn:1000003",
        "tgn:1000063",
        "tgn:4012014",
        "tgn:7029392"
    ],
    "tgn:id":7240514,
    "tgn:name":"Fagnolle",
    "tgn:placetype":[
        "aat:300008699"
    ]
},
  "bbox": [],
  "geometry": {"coordinates":[4.533333,50.083333],"type":"Point"}
}
=======
{"geometry":{"type":"Point","coordinates":[4.533333,50.083333]},"type":"Feature","properties":{"hierarchy":["tgn:7240514","tgn:7003466","tgn:1000003","tgn:1000063","tgn:4012014","tgn:7029392"],"placetype":["aat:300008699"],"id":7240514,"name:xx":"Fagnolle"}}
>>>>>>> 03f74aca74312dbeaf24d7e61306dd6a786dc3d0
