<<<<<<< HEAD
{
  "id": 2253486,
  "type": "Feature",
  "properties": {
    "tgn:hierarchy":[
        "tgn:2253486",
        "tgn:1000001",
        "tgn:7012149",
        "tgn:7007522",
        "tgn:7029392"
    ],
    "tgn:id":2253486,
    "tgn:name":"Cook Creek",
    "tgn:placetype":[
        "aat:300008706"
    ]
},
  "bbox": [],
  "geometry": {"coordinates":[-88.95,34.65],"type":"Point"}
}
=======
{"geometry":{"type":"Point","coordinates":[-88.950000,34.650000]},"type":"Feature","properties":{"hierarchy":["tgn:2253486","tgn:1000001","tgn:7012149","tgn:7007522","tgn:7029392"],"placetype":["aat:300008706"],"id":2253486,"name:xx":"Cook Creek"}}
>>>>>>> 03f74aca74312dbeaf24d7e61306dd6a786dc3d0
