{
  "id": 2489296,
  "type": "Feature",
  "properties": {
    "tgn:hierarchy":[
        "tgn:2489296",
        "tgn:7030516",
        "tgn:7006450",
        "tgn:1000001",
        "tgn:7012149",
        "tgn:7029392"
    ],
    "tgn:id":2489296,
    "tgn:name":"Makushin Bay",
    "tgn:placetype":[
        "aat:300132316"
    ]
},
  "bbox": [],
  "geometry": {"coordinates":[-166.95,53.7333],"type":"Point"}
}