{
  "id": 7222069,
  "type": "Feature",
  "properties": {
    "tgn:hierarchy":[
        "tgn:7222069",
        "tgn:7002715",
        "tgn:7002731",
        "tgn:1000003",
        "tgn:1000074",
        "tgn:7029392"
    ],
    "tgn:id":7222069,
    "tgn:name":"Mikr\u00f3n Monast\u00edrion",
    "tgn:placetype":[
        "aat:300008347"
    ]
},
  "bbox": [],
  "geometry": {"coordinates":[22.541389,40.705833],"type":"Point"}
}