<<<<<<< HEAD
{
  "id": 7051443,
  "type": "Feature",
  "properties": {
    "tgn:hierarchy":[
        "tgn:7051443",
        "tgn:7015163",
        "tgn:1000003",
        "tgn:7003121",
        "tgn:1000080",
        "tgn:7029392"
    ],
    "tgn:id":7051443,
    "tgn:name":"Piana, Isola",
    "tgn:placetype":[
        "aat:300008791"
    ]
},
  "bbox": [],
  "geometry": {"coordinates":[8.140278,40.603056],"type":"Point"}
}
=======
{"geometry":{"type":"Point","coordinates":[8.140278,40.603056]},"type":"Feature","properties":{"hierarchy":["tgn:7051443","tgn:7015163","tgn:1000003","tgn:7003121","tgn:1000080","tgn:7029392"],"placetype":["aat:300008791"],"id":7051443,"name:xx":"Piana, Isola"}}
>>>>>>> 03f74aca74312dbeaf24d7e61306dd6a786dc3d0
