{
  "id": 1079871,
  "type": "Feature",
  "properties": {
    "tgn:hierarchy":[
        "tgn:1079871",
        "tgn:1000004",
        "tgn:7000894",
        "tgn:1001032",
        "tgn:1000120",
        "tgn:7029392"
    ],
    "tgn:id":1079871,
    "tgn:name":"Bubai",
    "tgn:placetype":[
        "aat:300008347"
    ]
},
  "bbox": [],
  "geometry": {"coordinates":[139.4833,35.6667],"type":"Point"}
}