{
  "id": 2587079,
  "type": "Feature",
  "properties": {
    "tgn:hierarchy":[
        "tgn:2587079",
        "tgn:1000001",
        "tgn:2001430",
        "tgn:7012149",
        "tgn:7007566",
        "tgn:7029392"
    ],
    "tgn:id":2587079,
    "tgn:name":"Plaster Plant",
    "tgn:placetype":[
        "aat:300000390"
    ]
},
  "bbox": [],
  "geometry": {"coordinates":[-104.3167,33.5833],"type":"Point"}
}