<<<<<<< HEAD
{
  "id": 2402637,
  "type": "Feature",
  "properties": {
    "tgn:hierarchy":[
        "tgn:2402637",
        "tgn:1000001",
        "tgn:2001411",
        "tgn:7012149",
        "tgn:7007526",
        "tgn:7029392"
    ],
    "tgn:id":2402637,
    "tgn:name":"Hot Creek Spring",
    "tgn:placetype":[
        "aat:300008697"
    ]
},
  "bbox": [],
  "geometry": {"coordinates":[-116.5,41.1667],"type":"Point"}
}
=======
{"geometry":{"type":"Point","coordinates":[-116.500000,41.166700]},"type":"Feature","properties":{"hierarchy":["tgn:2402637","tgn:1000001","tgn:2001411","tgn:7012149","tgn:7007526","tgn:7029392"],"placetype":["aat:300008697"],"id":2402637,"name:xx":"Hot Creek Spring"}}
>>>>>>> 03f74aca74312dbeaf24d7e61306dd6a786dc3d0
