{
  "id": 2441445,
  "type": "Feature",
  "properties": {
    "tgn:hierarchy":[
        "tgn:2441445",
        "tgn:1000001",
        "tgn:7012149",
        "tgn:7007826",
        "tgn:7029392"
    ],
    "tgn:id":2441445,
    "tgn:name":"Knust Draw",
    "tgn:placetype":[
        "aat:300008761"
    ]
},
  "bbox": [],
  "geometry": {"coordinates":[-100.0667,30.3167],"type":"Point"}
}