<<<<<<< HEAD
{
  "id": 7020524,
  "type": "Feature",
  "properties": {
    "tgn:hierarchy":[
        "tgn:7020524",
        "tgn:1000001",
        "tgn:7012149",
        "tgn:2001551",
        "tgn:7007709",
        "tgn:7029392"
    ],
    "tgn:id":7020524,
    "tgn:name":"Rich Mountain Bald",
    "tgn:placetype":[
        "aat:300008798"
    ]
},
  "bbox": [],
  "geometry": {"coordinates":[-81.7167,36.3],"type":"Point"}
}
=======
{"geometry":{"type":"Point","coordinates":[-81.716700,36.300000]},"type":"Feature","properties":{"hierarchy":["tgn:7020524","tgn:1000001","tgn:7012149","tgn:2001551","tgn:7007709","tgn:7029392"],"placetype":["aat:300008798"],"id":7020524,"name:xx":"Rich Mountain Bald"}}
>>>>>>> 03f74aca74312dbeaf24d7e61306dd6a786dc3d0
