{
  "id": 7104237,
  "type": "Feature",
  "properties": {
    "tgn:hierarchy":[
        "tgn:7104237",
        "tgn:1000003",
        "tgn:7003684",
        "tgn:7000084",
        "tgn:7029392"
    ],
    "tgn:id":7104237,
    "tgn:name":"Schnorr",
    "tgn:placetype":[
        "aat:300008777"
    ]
},
  "bbox": [],
  "geometry": {"coordinates":[6.933333,49.566667],"type":"Point"}
}