{
  "id": 2061950,
  "type": "Feature",
  "properties": {
    "tgn:hierarchy":[
        "tgn:2061950",
        "tgn:1000001",
        "tgn:7012149",
        "tgn:2001392",
        "tgn:7007525",
        "tgn:7029392"
    ],
    "tgn:id":2061950,
    "tgn:name":"Bellevue",
    "tgn:placetype":[
        "aat:300008347"
    ]
},
  "bbox": [],
  "geometry": {"coordinates":[-95.8833,41.1333],"type":"Point"}
}