{
  "id": 2551675,
  "type": "Feature",
  "properties": {
    "tgn:hierarchy":[
        "tgn:2551675",
        "tgn:1000001",
        "tgn:7012149",
        "tgn:2000851",
        "tgn:7007255",
        "tgn:7029392"
    ],
    "tgn:id":2551675,
    "tgn:name":"Number 4, Mine",
    "tgn:placetype":[
        "aat:300000390"
    ]
},
  "bbox": [],
  "geometry": {"coordinates":[-87.8667,37.4833],"type":"Point"}
}