{
  "id": 7283586,
  "type": "Feature",
  "properties": {
    "tgn:hierarchy":[
        "tgn:7283586",
        "tgn:7016598",
        "tgn:1000049",
        "tgn:1000002",
        "tgn:7029392"
    ],
    "tgn:id":7283586,
    "tgn:name":"Paita, Roca",
    "tgn:placetype":[
        "aat:300011692"
    ]
},
  "bbox": [],
  "geometry": {"coordinates":[-70.433333,-23.65],"type":"Point"}
}