{
  "id": 7521428,
  "type": "Feature",
  "properties": {
    "tgn:hierarchy":[
        "tgn:7521428",
        "tgn:7001242",
        "tgn:7016833",
        "tgn:1001113",
        "tgn:7029392"
    ],
    "tgn:id":7521428,
    "tgn:name":"Ab\u016b \u1e28amm\u0101d",
    "tgn:placetype":[
        "aat:300007783"
    ]
},
  "bbox": [],
  "geometry": {"coordinates":[31.67708,30.536148],"type":"Point"}
}