{
  "id": 7467683,
  "type": "Feature",
  "properties": {
    "tgn:hierarchy":[
        "tgn:7467683",
        "tgn:1000004",
        "tgn:7491221",
        "tgn:1000141",
        "tgn:7029392"
    ],
    "tgn:id":7467683,
    "tgn:name":"Zhitian",
    "tgn:placetype":[
        "aat:300008347"
    ]
},
  "bbox": [],
  "geometry": {"coordinates":[121.385594,23.109998],"type":"Point"}
}