{
  "id": 2455765,
  "type": "Feature",
  "properties": {
    "tgn:hierarchy":[
        "tgn:2455765",
        "tgn:1000001",
        "tgn:7016172",
        "tgn:7012149",
        "tgn:2000177",
        "tgn:7029392"
    ],
    "tgn:id":2455765,
    "tgn:name":"Little Gravel Slough",
    "tgn:placetype":[
        "aat:300008699"
    ]
},
  "bbox": [],
  "geometry": {"coordinates":[-91.5833,35.1833],"type":"Point"}
}