{
  "id": 2569035,
  "type": "Feature",
  "properties": {
    "tgn:hierarchy":[
        "tgn:2569035",
        "tgn:1000001",
        "tgn:7012149",
        "tgn:2002288",
        "tgn:7013961",
        "tgn:7029392"
    ],
    "tgn:id":2569035,
    "tgn:name":"Parker Run",
    "tgn:placetype":[
        "aat:300008699"
    ]
},
  "bbox": [],
  "geometry": {"coordinates":[-79.6667,39.5833],"type":"Point"}
}