{
  "id": 1027777,
  "type": "Feature",
  "properties": {
    "tgn:hierarchy":[
        "tgn:1027777",
        "tgn:1000003",
        "tgn:7594009",
        "tgn:1000066",
        "tgn:7029392"
    ],
    "tgn:id":1027777,
    "tgn:name":"Ebberup",
    "tgn:placetype":[
        "aat:300008347"
    ]
},
  "bbox": [],
  "geometry": {"coordinates":[9.9833,55.2333],"type":"Point"}
}