<<<<<<< HEAD
{
  "id": 2768674,
  "type": "Feature",
  "properties": {
    "tgn:hierarchy":[
        "tgn:2768674",
        "tgn:7002659",
        "tgn:1000001",
        "tgn:7012149",
        "tgn:2000045",
        "tgn:7029392"
    ],
    "tgn:id":2768674,
    "tgn:name":"Whitley Lake",
    "tgn:placetype":[
        "aat:300006191"
    ]
},
  "bbox": [],
  "geometry": {"coordinates":[-87.6333,32.25],"type":"Point"}
}
=======
{"geometry":{"type":"Point","coordinates":[-87.633300,32.250000]},"type":"Feature","properties":{"hierarchy":["tgn:2768674","tgn:7002659","tgn:1000001","tgn:7012149","tgn:2000045","tgn:7029392"],"placetype":["aat:300006191"],"id":2768674,"name:xx":"Whitley Lake"}}
>>>>>>> 03f74aca74312dbeaf24d7e61306dd6a786dc3d0
