{
  "id": 7296432,
  "type": "Feature",
  "properties": {
    "tgn:hierarchy":[
        "tgn:7296432",
        "tgn:7008911",
        "tgn:1000003",
        "tgn:7002763",
        "tgn:1000095",
        "tgn:7029392"
    ],
    "tgn:id":7296432,
    "tgn:name":"Villamart\u00edn",
    "tgn:placetype":[
        "aat:300008347"
    ]
},
  "bbox": [],
  "geometry": {"coordinates":[-7.033333,43.233333],"type":"Point"}
}