{
  "id": 2081602,
  "type": "Feature",
  "properties": {
    "tgn:hierarchy":[
        "tgn:2081602",
        "tgn:1000001",
        "tgn:7012149",
        "tgn:1002917",
        "tgn:7007706",
        "tgn:7029392"
    ],
    "tgn:id":2081602,
    "tgn:name":"Richville",
    "tgn:placetype":[
        "aat:300008347"
    ]
},
  "bbox": [],
  "geometry": {"coordinates":[-81.4667,40.75],"type":"Point"}
}