{
  "id": 2245363,
  "type": "Feature",
  "properties": {
    "tgn:hierarchy":[
        "tgn:2245363",
        "tgn:1000001",
        "tgn:7012149",
        "tgn:1002821",
        "tgn:7007568",
        "tgn:7029392"
    ],
    "tgn:id":2245363,
    "tgn:name":"Clums Corner",
    "tgn:placetype":[
        "aat:300008347"
    ]
},
  "bbox": [],
  "geometry": {"coordinates":[-73.5667,42.75],"type":"Point"}
}