{
  "id": 7467552,
  "type": "Feature",
  "properties": {
    "tgn:hierarchy":[
        "tgn:7467552",
        "tgn:7487020",
        "tgn:1000004",
        "tgn:1000141",
        "tgn:7029392"
    ],
    "tgn:id":7467552,
    "tgn:name":"Zhikeng",
    "tgn:placetype":[
        "aat:300008347"
    ]
},
  "bbox": [],
  "geometry": {"coordinates":[120.734167,24.437778],"type":"Point"}
}