<<<<<<< HEAD
{
  "id": 2766147,
  "type": "Feature",
  "properties": {
    "tgn:hierarchy":[
        "tgn:2766147",
        "tgn:1000001",
        "tgn:2000470",
        "tgn:7012149",
        "tgn:7007250",
        "tgn:7029392"
    ],
    "tgn:id":2766147,
    "tgn:name":"White Knob Summit",
    "tgn:placetype":[
        "aat:300008798"
    ]
},
  "bbox": [],
  "geometry": {"coordinates":[-113.7167,43.8667],"type":"Point"}
}
=======
{"geometry":{"type":"Point","coordinates":[-113.716700,43.866700]},"type":"Feature","properties":{"hierarchy":["tgn:2766147","tgn:1000001","tgn:2000470","tgn:7012149","tgn:7007250","tgn:7029392"],"placetype":["aat:300008798"],"id":2766147,"name:xx":"White Knob Summit"}}
>>>>>>> 03f74aca74312dbeaf24d7e61306dd6a786dc3d0
