{
  "id": 7178632,
  "type": "Feature",
  "properties": {
    "tgn:hierarchy":[
        "tgn:7178632",
        "tgn:1000003",
        "tgn:7003676",
        "tgn:7000084",
        "tgn:7029392"
    ],
    "tgn:id":7178632,
    "tgn:name":"Guhreitzen",
    "tgn:placetype":[
        "aat:300008347"
    ]
},
  "bbox": [],
  "geometry": {"coordinates":[10.983333,52.95],"type":"Point"}
}