{
  "id": 1084352,
  "type": "Feature",
  "properties": {
    "tgn:hierarchy":[
        "tgn:1084352",
        "tgn:1000004",
        "tgn:1001557",
        "tgn:1000135",
        "tgn:7029392"
    ],
    "tgn:id":1084352,
    "tgn:name":"Lianga",
    "tgn:placetype":[
        "aat:300008347"
    ]
},
  "bbox": [],
  "geometry": {"coordinates":[126.0833,8.6333],"type":"Point"}
}