{
  "id": 7095370,
  "type": "Feature",
  "properties": {
    "tgn:hierarchy":[
        "tgn:7095370",
        "tgn:1000003",
        "tgn:7003688",
        "tgn:7000084",
        "tgn:7029392"
    ],
    "tgn:id":7095370,
    "tgn:name":"Sch\u00fclp",
    "tgn:placetype":[
        "aat:300008347"
    ]
},
  "bbox": [],
  "geometry": {"coordinates":[8.933333,54.25],"type":"Point"}
}