{
  "id": 2498784,
  "type": "Feature",
  "properties": {
    "tgn:hierarchy":[
        "tgn:2498784",
        "tgn:1000001",
        "tgn:7012149",
        "tgn:1003042",
        "tgn:7007920",
        "tgn:7029392"
    ],
    "tgn:id":2498784,
    "tgn:name":"McCall Basin",
    "tgn:placetype":[
        "aat:300386845"
    ]
},
  "bbox": [],
  "geometry": {"coordinates":[-121.4167,46.5333],"type":"Point"}
}