{
  "id": 2354282,
  "type": "Feature",
  "properties": {
    "tgn:hierarchy":[
        "tgn:2354282",
        "tgn:1000001",
        "tgn:7012149",
        "tgn:7007157",
        "tgn:1002956",
        "tgn:7029392"
    ],
    "tgn:id":2354282,
    "tgn:name":"Golden Trout Creek",
    "tgn:placetype":[
        "aat:300008706"
    ]
},
  "bbox": [],
  "geometry": {"coordinates":[-118.2333,36.45],"type":"Point"}
}