{
  "id": 7424121,
  "type": "Feature",
  "properties": {
    "tgn:hierarchy":[
        "tgn:7424121",
        "tgn:1000001",
        "tgn:7005597",
        "tgn:7005560",
        "tgn:7029392"
    ],
    "tgn:id":7424121,
    "tgn:name":"Veinte de Noviembre",
    "tgn:placetype":[
        "aat:300008347"
    ]
},
  "bbox": [],
  "geometry": {"coordinates":[-99.783333,22.966667],"type":"Point"}
}