{
  "id": 2071839,
  "type": "Feature",
  "properties": {
    "tgn:hierarchy":[
        "tgn:2071839",
        "tgn:1000001",
        "tgn:7012149",
        "tgn:7013941",
        "tgn:7007568",
        "tgn:7029392"
    ],
    "tgn:id":2071839,
    "tgn:name":"Rainbow Lake",
    "tgn:placetype":[
        "aat:300008347"
    ]
},
  "bbox": [],
  "geometry": {"coordinates":[-74.1667,44.4667],"type":"Point"}
}