{
  "id": 1024917,
  "type": "Feature",
  "properties": {
    "tgn:hierarchy":[
        "tgn:1024917",
        "tgn:7002650",
        "tgn:1000002",
        "tgn:1000058",
        "tgn:7029392"
    ],
    "tgn:id":1024917,
    "tgn:name":"La Paloma",
    "tgn:placetype":[
        "aat:300008347"
    ]
},
  "bbox": [],
  "geometry": {"coordinates":[-54.1333,-34.6167],"type":"Point"}
}