{
  "id": 7237494,
  "type": "Feature",
  "properties": {
    "tgn:hierarchy":[
        "tgn:7237494",
        "tgn:7002745",
        "tgn:7017076",
        "tgn:1000003",
        "tgn:1000074",
        "tgn:7029392"
    ],
    "tgn:id":7237494,
    "tgn:name":"Dhri",
    "tgn:placetype":[
        "aat:300008347"
    ]
},
  "bbox": [],
  "geometry": {"coordinates":[22.366667,36.483333],"type":"Point"}
}