{
  "id": 2022270,
  "type": "Feature",
  "properties": {
    "tgn:hierarchy":[
        "tgn:2022270",
        "tgn:1000001",
        "tgn:7012149",
        "tgn:2000411",
        "tgn:7007248",
        "tgn:7029392"
    ],
    "tgn:id":2022270,
    "tgn:name":"Brooksville",
    "tgn:placetype":[
        "aat:300008347",
        "aat:300387210"
    ]
},
  "bbox": [],
  "geometry": {"coordinates":[-84.65,31.8667],"type":"Point"}
}