{
  "id": 7220505,
  "type": "Feature",
  "properties": {
    "tgn:hierarchy":[
        "tgn:7220505",
        "tgn:7011163",
        "tgn:7002674",
        "tgn:1000003",
        "tgn:1000074",
        "tgn:7029392"
    ],
    "tgn:id":7220505,
    "tgn:name":"Petr\u00e1s, \u00c1kra",
    "tgn:placetype":[
        "aat:300386846"
    ]
},
  "bbox": [],
  "geometry": {"coordinates":[26.5175,38.970556],"type":"Point"}
}