{
  "id": 2350915,
  "type": "Feature",
  "properties": {
    "tgn:hierarchy":[
        "tgn:2350915",
        "tgn:1000001",
        "tgn:7012149",
        "tgn:2000183",
        "tgn:7007157",
        "tgn:7029392"
    ],
    "tgn:id":2350915,
    "tgn:name":"Gladstone Mine",
    "tgn:placetype":[
        "aat:300000390"
    ]
},
  "bbox": [],
  "geometry": {"coordinates":[-116.3833,35.8667],"type":"Point"}
}