{
  "id": 2734520,
  "type": "Feature",
  "properties": {
    "tgn:hierarchy":[
        "tgn:2734520",
        "tgn:1000001",
        "tgn:7012149",
        "tgn:2001906",
        "tgn:7007825",
        "tgn:7029392"
    ],
    "tgn:id":2734520,
    "tgn:name":"Turtletown Creek",
    "tgn:placetype":[
        "aat:300008706"
    ]
},
  "bbox": [],
  "geometry": {"coordinates":[-84.3333,35.0667],"type":"Point"}
}