{
  "id": 2423869,
  "type": "Feature",
  "properties": {
    "tgn:hierarchy":[
        "tgn:2423869",
        "tgn:1000001",
        "tgn:7012149",
        "tgn:7007713",
        "tgn:7029392"
    ],
    "tgn:id":2423869,
    "tgn:name":"Johnny Creek",
    "tgn:placetype":[
        "aat:300008706"
    ]
},
  "bbox": [],
  "geometry": {"coordinates":[-100.65,43.9167],"type":"Point"}
}