{
  "id": 1081019,
  "type": "Feature",
  "properties": {
    "tgn:hierarchy":[
        "tgn:1081019",
        "tgn:7000895",
        "tgn:1000004",
        "tgn:7016854",
        "tgn:1000120",
        "tgn:7029392"
    ],
    "tgn:id":1081019,
    "tgn:name":"Nirasaki",
    "tgn:placetype":[
        "aat:300008347"
    ]
},
  "bbox": [],
  "geometry": {"coordinates":[138.45,35.75],"type":"Point"}
}