{
  "id": 7295450,
  "type": "Feature",
  "properties": {
    "tgn:hierarchy":[
        "tgn:7295450",
        "tgn:7002835",
        "tgn:7001158",
        "tgn:1000003",
        "tgn:1000095",
        "tgn:7029392"
    ],
    "tgn:id":7295450,
    "tgn:name":"Villaverde de Guare\u00f1a",
    "tgn:placetype":[
        "aat:300008347"
    ]
},
  "bbox": [],
  "geometry": {"coordinates":[-5.516667,41.066667],"type":"Point"}
}