<<<<<<< HEAD
{
  "id": 7354377,
  "type": "Feature",
  "properties": {
    "tgn:hierarchy":[
        "tgn:7354377",
        "tgn:1000001",
        "tgn:7005599",
        "tgn:7005560",
        "tgn:7029392"
    ],
    "tgn:id":7354377,
    "tgn:name":"Cascajal, Arroyo",
    "tgn:placetype":[
        "aat:300008699"
    ]
},
  "bbox": [],
  "geometry": {"coordinates":[-94.15,17.633333],"type":"Point"}
}
=======
{"geometry":{"type":"Point","coordinates":[-94.150000,17.633333]},"type":"Feature","properties":{"hierarchy":["tgn:7354377","tgn:1000001","tgn:7005599","tgn:7005560","tgn:7029392"],"placetype":["aat:300008699"],"id":7354377,"name:xx":"Cascajal, Arroyo"}}
>>>>>>> 03f74aca74312dbeaf24d7e61306dd6a786dc3d0
