{
  "id": 7354377,
  "type": "Feature",
  "properties": {
    "tgn:hierarchy":[
        "tgn:7354377",
        "tgn:1000001",
        "tgn:7005599",
        "tgn:7005560",
        "tgn:7029392"
    ],
    "tgn:id":7354377,
    "tgn:name":"Cascajal, Arroyo",
    "tgn:placetype":[
        "aat:300008699"
    ]
},
  "bbox": [],
  "geometry": {"coordinates":[-94.15,17.633333],"type":"Point"}
}