{
  "id": 2579677,
  "type": "Feature",
  "properties": {
    "tgn:hierarchy":[
        "tgn:2579677",
        "tgn:1000001",
        "tgn:7012149",
        "tgn:7007157",
        "tgn:7014005",
        "tgn:7029392"
    ],
    "tgn:id":2579677,
    "tgn:name":"Pickleweed Inlet",
    "tgn:placetype":[
        "aat:300132316"
    ]
},
  "bbox": [],
  "geometry": {"coordinates":[-122.5167,37.8833],"type":"Point"}
}