{
  "id": 2375106,
  "type": "Feature",
  "properties": {
    "tgn:hierarchy":[
        "tgn:2375106",
        "tgn:1000001",
        "tgn:7012149",
        "tgn:2001293",
        "tgn:7007524",
        "tgn:7029392"
    ],
    "tgn:id":2375106,
    "tgn:name":"Hanlon Hill",
    "tgn:placetype":[
        "aat:300008798"
    ]
},
  "bbox": [],
  "geometry": {"coordinates":[-110.6333,45.0667],"type":"Point"}
}