{
  "id": 2371960,
  "type": "Feature",
  "properties": {
    "tgn:hierarchy":[
        "tgn:2371960",
        "tgn:1000001",
        "tgn:7012149",
        "tgn:7016020",
        "tgn:7007710",
        "tgn:7029392"
    ],
    "tgn:id":2371960,
    "tgn:name":"Half Mile Run",
    "tgn:placetype":[
        "aat:300008699"
    ]
},
  "bbox": [],
  "geometry": {"coordinates":[-78.2333,41.65],"type":"Point"}
}