{
  "id": 1119507,
  "type": "Feature",
  "properties": {
    "tgn:hierarchy":[
        "tgn:1119507",
        "tgn:7002445",
        "tgn:7018909",
        "tgn:1000003",
        "tgn:7008136",
        "tgn:7008591",
        "tgn:7029392"
    ],
    "tgn:id":1119507,
    "tgn:name":"Brent Reservoir",
    "tgn:placetype":[
        "aat:300006191"
    ]
},
  "bbox": [],
  "geometry": {"coordinates":[-0.25,51.5667],"type":"Point"}
}