{
  "id": 7553188,
  "type": "Feature",
  "properties": {
    "tgn:hierarchy":[
        "tgn:7553188",
        "tgn:1000004",
        "tgn:7000198",
        "tgn:1001998",
        "tgn:7029392"
    ],
    "tgn:id":7553188,
    "tgn:name:en":"Mullianpui",
    "tgn:placetype":[
        "aat:300008347"
    ]
},
  "bbox": [],
  "geometry": {"coordinates":[92.56553,22.678053],"type":"Point"}
}