{
  "id": 2157393,
  "type": "Feature",
  "properties": {
    "tgn:hierarchy":[
        "tgn:2157393",
        "tgn:1000001",
        "tgn:7012149",
        "tgn:2001609",
        "tgn:7007705",
        "tgn:7029392"
    ],
    "tgn:id":2157393,
    "tgn:name":"Beaver Creek",
    "tgn:placetype":[
        "aat:300008706"
    ]
},
  "bbox": [],
  "geometry": {"coordinates":[-103.2333,48.2833],"type":"Point"}
}