{
  "id": 2455165,
  "type": "Feature",
  "properties": {
    "tgn:hierarchy":[
        "tgn:2455165",
        "tgn:1000001",
        "tgn:7012149",
        "tgn:7007920",
        "tgn:7029392"
    ],
    "tgn:id":2455165,
    "tgn:name":"Little Falls Reservoir",
    "tgn:placetype":[
        "aat:300006191"
    ]
},
  "bbox": [],
  "geometry": {"coordinates":[-117.9167,47.8167],"type":"Point"}
}