{
  "id": 2008903,
  "type": "Feature",
  "properties": {
    "tgn:hierarchy":[
        "tgn:2008903",
        "tgn:1000001",
        "tgn:7016172",
        "tgn:2000114",
        "tgn:7012149",
        "tgn:7029392"
    ],
    "tgn:id":2008903,
    "tgn:name":"Meeks Settlement",
    "tgn:placetype":[
        "aat:300008347"
    ]
},
  "bbox": [],
  "geometry": {"coordinates":[-93.3833,34.0333],"type":"Point"}
}