{
  "id": 2455541,
  "type": "Feature",
  "properties": {
    "tgn:hierarchy":[
        "tgn:2455541",
        "tgn:1000001",
        "tgn:7012149",
        "tgn:2000960",
        "tgn:7007520",
        "tgn:7029392"
    ],
    "tgn:id":2455541,
    "tgn:name":"Little Giant Creek",
    "tgn:placetype":[
        "aat:300008706"
    ]
},
  "bbox": [],
  "geometry": {"coordinates":[-89.65,46.4333],"type":"Point"}
}