{
  "id": 7232276,
  "type": "Feature",
  "properties": {
    "tgn:hierarchy":[
        "tgn:7232276",
        "tgn:7002745",
        "tgn:7017076",
        "tgn:1000003",
        "tgn:1000074",
        "tgn:7029392"
    ],
    "tgn:id":7232276,
    "tgn:name":"Makri\u00e1 Po\u00fanda, \u00c1kra",
    "tgn:placetype":[
        "aat:300008850"
    ]
},
  "bbox": [],
  "geometry": {"coordinates":[23.083333,36.433333],"type":"Point"}
}