{
  "id": 7262945,
  "type": "Feature",
  "properties": {
    "tgn:hierarchy":[
        "tgn:7262945",
        "tgn:7003614",
        "tgn:1000003",
        "tgn:7016845",
        "tgn:7029392"
    ],
    "tgn:id":7262945,
    "tgn:name:nl":"Dalerpeel",
    "tgn:placetype":[
        "aat:300387502"
    ]
},
  "bbox": [],
  "geometry": {"coordinates":[6.65,52.683333],"type":"Point"}
}