<<<<<<< HEAD
{
  "id": 2255347,
  "type": "Feature",
  "properties": {
    "tgn:hierarchy":[
        "tgn:2255347",
        "tgn:7002659",
        "tgn:1000001",
        "tgn:7012149",
        "tgn:2000035",
        "tgn:7029392"
    ],
    "tgn:id":2255347,
    "tgn:name":"Coopers Mill",
    "tgn:placetype":[
        "aat:300008347"
    ]
},
  "bbox": [],
  "geometry": {"coordinates":[-85.7833,34.9333],"type":"Point"}
}
=======
{"geometry":{"type":"Point","coordinates":[-85.783300,34.933300]},"type":"Feature","properties":{"hierarchy":["tgn:2255347","tgn:7002659","tgn:1000001","tgn:7012149","tgn:2000035","tgn:7029392"],"placetype":["aat:300008347"],"id":2255347,"name:xx":"Coopers Mill"}}
>>>>>>> 03f74aca74312dbeaf24d7e61306dd6a786dc3d0
