{
  "id": 7070112,
  "type": "Feature",
  "properties": {
    "tgn:hierarchy":[
        "tgn:7070112",
        "tgn:1000003",
        "tgn:7003678",
        "tgn:7000084",
        "tgn:7029392"
    ],
    "tgn:id":7070112,
    "tgn:name":"Stein-Berg",
    "tgn:placetype":[
        "aat:300008777"
    ]
},
  "bbox": [],
  "geometry": {"coordinates":[9.316667,51.25],"type":"Point"}
}