{
  "id": 7184055,
  "type": "Feature",
  "properties": {
    "tgn:hierarchy":[
        "tgn:7184055",
        "tgn:1000003",
        "tgn:7003689",
        "tgn:7000084",
        "tgn:7029392"
    ],
    "tgn:id":7184055,
    "tgn:name":"G\u00f6dissa",
    "tgn:placetype":[
        "aat:300008347"
    ]
},
  "bbox": [],
  "geometry": {"coordinates":[12.366667,50.95],"type":"Point"}
}