{
  "id": 2517192,
  "type": "Feature",
  "properties": {
    "tgn:hierarchy":[
        "tgn:2517192",
        "tgn:1000001",
        "tgn:7012149",
        "tgn:2002123",
        "tgn:7007827",
        "tgn:7029392"
    ],
    "tgn:id":2517192,
    "tgn:name":"Minnehaha Spring",
    "tgn:placetype":[
        "aat:300008697"
    ]
},
  "bbox": [],
  "geometry": {"coordinates":[-113.7667,40.0833],"type":"Point"}
}