{
  "id": 7327914,
  "type": "Feature",
  "properties": {
    "tgn:hierarchy":[
        "tgn:7327914",
        "tgn:7001122",
        "tgn:1000003",
        "tgn:7002765",
        "tgn:1000095",
        "tgn:7029392"
    ],
    "tgn:id":7327914,
    "tgn:name":"Pudent, Estanque",
    "tgn:placetype":[
        "aat:300008679"
    ]
},
  "bbox": [],
  "geometry": {"coordinates":[1.433333,38.716667],"type":"Point"}
}