{
  "id": 7020256,
  "type": "Feature",
  "properties": {
    "tgn:hierarchy":[
        "tgn:7020256",
        "tgn:1000001",
        "tgn:7012149",
        "tgn:1002924",
        "tgn:7007568",
        "tgn:7029392"
    ],
    "tgn:id":7020256,
    "tgn:name":"Noyack",
    "tgn:placetype":[
        "aat:300008347"
    ]
},
  "bbox": [],
  "geometry": {"coordinates":[-72.3333,40.9833],"type":"Point"}
}