<<<<<<< HEAD
{
  "id": 7020256,
  "type": "Feature",
  "properties": {
    "tgn:hierarchy":[
        "tgn:7020256",
        "tgn:1000001",
        "tgn:7012149",
        "tgn:1002924",
        "tgn:7007568",
        "tgn:7029392"
    ],
    "tgn:id":7020256,
    "tgn:name":"Noyack",
    "tgn:placetype":[
        "aat:300008347"
    ]
},
  "bbox": [],
  "geometry": {"coordinates":[-72.3333,40.9833],"type":"Point"}
}
=======
{"geometry":{"type":"Point","coordinates":[-72.333300,40.983300]},"type":"Feature","properties":{"hierarchy":["tgn:7020256","tgn:1000001","tgn:7012149","tgn:1002924","tgn:7007568","tgn:7029392"],"placetype":["aat:300008347"],"id":7020256,"name:xx":"Noyack"}}
>>>>>>> 03f74aca74312dbeaf24d7e61306dd6a786dc3d0
