{
  "id": 7173407,
  "type": "Feature",
  "properties": {
    "tgn:hierarchy":[
        "tgn:7173407",
        "tgn:1000003",
        "tgn:7000094",
        "tgn:7000084",
        "tgn:7029392"
    ],
    "tgn:id":7173407,
    "tgn:name":"Gro\u00df Quassow",
    "tgn:placetype":[
        "aat:300008347"
    ]
},
  "bbox": [],
  "geometry": {"coordinates":[13.016667,53.316667],"type":"Point"}
}