{
  "id": 2159862,
  "type": "Feature",
  "properties": {
    "tgn:hierarchy":[
        "tgn:2159862",
        "tgn:7002659",
        "tgn:1000001",
        "tgn:7012149",
        "tgn:2000023",
        "tgn:7029392"
    ],
    "tgn:id":2159862,
    "tgn:name":"Beech Creek Swamp",
    "tgn:placetype":[
        "aat:300008905"
    ]
},
  "bbox": [],
  "geometry": {"coordinates":[-86.9833,32.45],"type":"Point"}
}