<<<<<<< HEAD
{
  "id": 2159862,
  "type": "Feature",
  "properties": {
    "tgn:hierarchy":[
        "tgn:2159862",
        "tgn:7002659",
        "tgn:1000001",
        "tgn:7012149",
        "tgn:2000023",
        "tgn:7029392"
    ],
    "tgn:id":2159862,
    "tgn:name":"Beech Creek Swamp",
    "tgn:placetype":[
        "aat:300008905"
    ]
},
  "bbox": [],
  "geometry": {"coordinates":[-86.9833,32.45],"type":"Point"}
}
=======
{"geometry":{"type":"Point","coordinates":[-86.983300,32.450000]},"type":"Feature","properties":{"hierarchy":["tgn:2159862","tgn:7002659","tgn:1000001","tgn:7012149","tgn:2000023","tgn:7029392"],"placetype":["aat:300008905"],"id":2159862,"name:xx":"Beech Creek Swamp"}}
>>>>>>> 03f74aca74312dbeaf24d7e61306dd6a786dc3d0
