{
  "id": 2523432,
  "type": "Feature",
  "properties": {
    "tgn:hierarchy":[
        "tgn:2523432",
        "tgn:1000001",
        "tgn:2000469",
        "tgn:7012149",
        "tgn:7007250",
        "tgn:7029392"
    ],
    "tgn:id":2523432,
    "tgn:name":"Moose Creek Buttes",
    "tgn:placetype":[
        "aat:300008798"
    ]
},
  "bbox": [],
  "geometry": {"coordinates":[-115.1667,46.7333],"type":"Point"}
}