{
  "id": 2260289,
  "type": "Feature",
  "properties": {
    "tgn:hierarchy":[
        "tgn:2260289",
        "tgn:1000001",
        "tgn:7012149",
        "tgn:1002554",
        "tgn:7007920",
        "tgn:7029392"
    ],
    "tgn:id":2260289,
    "tgn:name":"Counts Butte",
    "tgn:placetype":[
        "aat:300008798"
    ]
},
  "bbox": [],
  "geometry": {"coordinates":[-120.9667,45.8833],"type":"Point"}
}