{
  "id": 1055975,
  "type": "Feature",
  "properties": {
    "tgn:hierarchy":[
        "tgn:1055975",
        "tgn:1000004",
        "tgn:7011573",
        "tgn:7018214",
        "tgn:7002435",
        "tgn:7029392"
    ],
    "tgn:id":1055975,
    "tgn:name":"Kuchino",
    "tgn:placetype":[
        "aat:300008347"
    ]
},
  "bbox": [],
  "geometry": {"coordinates":[37.9667,55.75],"type":"Point"}
}