{
  "id": 2107665,
  "type": "Feature",
  "properties": {
    "tgn:hierarchy":[
        "tgn:2107665",
        "tgn:1000001",
        "tgn:7012149",
        "tgn:2001979",
        "tgn:7007826",
        "tgn:7029392"
    ],
    "tgn:id":2107665,
    "tgn:name":"Sid Richardson",
    "tgn:placetype":[
        "aat:300387016"
    ]
},
  "bbox": [],
  "geometry": {"coordinates":[-102.4833,31.7667],"type":"Point"}
}