{
  "id": 2052027,
  "type": "Feature",
  "properties": {
    "tgn:hierarchy":[
        "tgn:2052027",
        "tgn:1002140",
        "tgn:1000001",
        "tgn:7012149",
        "tgn:7007520",
        "tgn:7029392"
    ],
    "tgn:id":2052027,
    "tgn:name":"Glenn Haven Shores",
    "tgn:placetype":[
        "aat:300008347"
    ]
},
  "bbox": [],
  "geometry": {"coordinates":[-86.2333,42.4833],"type":"Point"}
}