{
  "id": 2389930,
  "type": "Feature",
  "properties": {
    "tgn:hierarchy":[
        "tgn:2389930",
        "tgn:1000001",
        "tgn:7012149",
        "tgn:7007157",
        "tgn:1002858",
        "tgn:7029392"
    ],
    "tgn:id":2389930,
    "tgn:name":"High Point",
    "tgn:placetype":[
        "aat:300008798"
    ]
},
  "bbox": [],
  "geometry": {"coordinates":[-116.8333,33.35],"type":"Point"}
}