{
  "id": 2447928,
  "type": "Feature",
  "properties": {
    "tgn:hierarchy":[
        "tgn:2447928",
        "tgn:2000090",
        "tgn:1000001",
        "tgn:7006451",
        "tgn:7012149",
        "tgn:7029392"
    ],
    "tgn:id":2447928,
    "tgn:name":"Liegler Tank",
    "tgn:placetype":[
        "aat:300006191"
    ]
},
  "bbox": [],
  "geometry": {"coordinates":[-109.8167,34.2333],"type":"Point"}
}