{
  "id": 7284823,
  "type": "Feature",
  "properties": {
    "tgn:hierarchy":[
        "tgn:7284823",
        "tgn:1001637",
        "tgn:1000049",
        "tgn:1000002",
        "tgn:7029392"
    ],
    "tgn:id":7284823,
    "tgn:name":"Pullay, Estero",
    "tgn:placetype":[
        "aat:300008699"
    ]
},
  "bbox": [],
  "geometry": {"coordinates":[-72.783333,-36.033333],"type":"Point"}
}