{
  "id": 2184178,
  "type": "Feature",
  "properties": {
    "tgn:hierarchy":[
        "tgn:2184178",
        "tgn:1000001",
        "tgn:2001260",
        "tgn:7012149",
        "tgn:7007524",
        "tgn:7029392"
    ],
    "tgn:id":2184178,
    "tgn:name":"Bob Ingersoll Mine",
    "tgn:placetype":[
        "aat:300000390"
    ]
},
  "bbox": [],
  "geometry": {"coordinates":[-112.95,45.1667],"type":"Point"}
}