{
  "id": 1112189,
  "type": "Feature",
  "properties": {
    "tgn:hierarchy":[
        "tgn:1112189",
        "tgn:7003025",
        "tgn:1000003",
        "tgn:1000062",
        "tgn:7029392"
    ],
    "tgn:id":1112189,
    "tgn:name":"Tullner Feld",
    "tgn:placetype":[
        "aat:300387346"
    ]
},
  "bbox": [],
  "geometry": {"coordinates":[16.1667,48.3167],"type":"Point"}
}