{
  "id": 7585428,
  "type": "Feature",
  "properties": {
    "tgn:hierarchy":[
        "tgn:7585428",
        "tgn:1000004",
        "tgn:1001871",
        "tgn:7000198",
        "tgn:7029392"
    ],
    "tgn:id":7585428,
    "tgn:name:en":"Jauy\u0101nw\u0101li Johri",
    "tgn:placetype":[
        "aat:300008688"
    ]
},
  "bbox": [],
  "geometry": {"coordinates":[75.644352,28.819379],"type":"Point"}
}