{
  "id": 7077751,
  "type": "Feature",
  "properties": {
    "tgn:hierarchy":[
        "tgn:7077751",
        "tgn:1000003",
        "tgn:7003678",
        "tgn:7000084",
        "tgn:7029392"
    ],
    "tgn:id":7077751,
    "tgn:name":"Alheim",
    "tgn:placetype":[
        "aat:300387173"
    ]
},
  "bbox": [],
  "geometry": {"coordinates":[9.683333,51.033333],"type":"Point"}
}