{
  "id": 2717268,
  "type": "Feature",
  "properties": {
    "tgn:hierarchy":[
        "tgn:2717268",
        "tgn:7006450",
        "tgn:1000001",
        "tgn:7012149",
        "tgn:2000085",
        "tgn:7029392"
    ],
    "tgn:id":2717268,
    "tgn:name":"Thirteen Gulch",
    "tgn:placetype":[
        "aat:300008761"
    ]
},
  "bbox": [],
  "geometry": {"coordinates":[-142.0167,65.1333],"type":"Point"}
}