{
  "id": 7269347,
  "type": "Feature",
  "properties": {
    "tgn:hierarchy":[
        "tgn:7269347",
        "tgn:7003616",
        "tgn:1000003",
        "tgn:7016845",
        "tgn:7029392"
    ],
    "tgn:id":7269347,
    "tgn:name:nl":"Oudemeer",
    "tgn:placetype":[
        "aat:300006075"
    ]
},
  "bbox": [],
  "geometry": {"coordinates":[5.566667,53.15],"type":"Point"}
}