{
  "id": 7513730,
  "type": "Feature",
  "properties": {
    "tgn:hierarchy":[
        "tgn:7513730",
        "tgn:1009227",
        "tgn:1000226",
        "tgn:7018437",
        "tgn:1000006",
        "tgn:7029392"
    ],
    "tgn:id":7513730,
    "tgn:name:en":"Fortification Creek",
    "tgn:placetype":[
        "aat:300008699"
    ]
},
  "bbox": [],
  "geometry": {"coordinates":[169.666667,-45.566667],"type":"Point"}
}