{
  "id": 1049976,
  "type": "Feature",
  "properties": {
    "tgn:hierarchy":[
        "tgn:1049976",
        "tgn:7003826",
        "tgn:1000003",
        "tgn:1000090",
        "tgn:7029392"
    ],
    "tgn:id":1049976,
    "tgn:name":"Vila Nova de Gaia",
    "tgn:placetype":[
        "aat:300008347"
    ]
},
  "bbox": [],
  "geometry": {"coordinates":[-8.617,41.133],"type":"Point"}
}