{
  "id": 2732525,
  "type": "Feature",
  "properties": {
    "tgn:hierarchy":[
        "tgn:2732525",
        "tgn:1000001",
        "tgn:7006451",
        "tgn:2000092",
        "tgn:7012149",
        "tgn:7029392"
    ],
    "tgn:id":2732525,
    "tgn:name":"Turkey Creek",
    "tgn:placetype":[
        "aat:300008706"
    ]
},
  "bbox": [],
  "geometry": {"coordinates":[-111.0667,34.3833],"type":"Point"}
}