{
  "id": 2667349,
  "type": "Feature",
  "properties": {
    "tgn:hierarchy":[
        "tgn:2667349",
        "tgn:1000001",
        "tgn:7012149",
        "tgn:1002545",
        "tgn:7007157",
        "tgn:7029392"
    ],
    "tgn:id":2667349,
    "tgn:name":"Skinner Peak",
    "tgn:placetype":[
        "aat:300008798"
    ]
},
  "bbox": [],
  "geometry": {"coordinates":[-118.1167,35.5667],"type":"Point"}
}