{
  "id": 2536503,
  "type": "Feature",
  "properties": {
    "tgn:hierarchy":[
        "tgn:2536503",
        "tgn:1000001",
        "tgn:7012149",
        "tgn:2000893",
        "tgn:7007256",
        "tgn:7029392"
    ],
    "tgn:id":2536503,
    "tgn:name":"Neals Bay",
    "tgn:placetype":[
        "aat:300132316"
    ]
},
  "bbox": [],
  "geometry": {"coordinates":[-92.4333,30.9667],"type":"Point"}
}