{
  "id": 2661076,
  "type": "Feature",
  "properties": {
    "tgn:hierarchy":[
        "tgn:2661076",
        "tgn:1000001",
        "tgn:7016106",
        "tgn:7012149",
        "tgn:7007516",
        "tgn:7029392"
    ],
    "tgn:id":2661076,
    "tgn:name":"Short Hill",
    "tgn:placetype":[
        "aat:300008798"
    ]
},
  "bbox": [],
  "geometry": {"coordinates":[-77.6333,39.5333],"type":"Point"}
}