{
  "id": 2092635,
  "type": "Feature",
  "properties": {
    "tgn:hierarchy":[
        "tgn:2092635",
        "tgn:1000001",
        "tgn:7012149",
        "tgn:1002613",
        "tgn:7007710",
        "tgn:7029392"
    ],
    "tgn:id":2092635,
    "tgn:name":"Ross Siding",
    "tgn:placetype":[
        "aat:300008347"
    ]
},
  "bbox": [],
  "geometry": {"coordinates":[-77.4667,41.4167],"type":"Point"}
}