{
  "id": 7513653,
  "type": "Feature",
  "properties": {
    "tgn:hierarchy":[
        "tgn:7513653",
        "tgn:1009227",
        "tgn:7001866",
        "tgn:1000226",
        "tgn:1000006",
        "tgn:7029392"
    ],
    "tgn:id":7513653,
    "tgn:name:en":"Freds Stream",
    "tgn:placetype":[
        "aat:300008699"
    ]
},
  "bbox": [],
  "geometry": {"coordinates":[172.566667,-42.483333],"type":"Point"}
}