{
  "id": 2605371,
  "type": "Feature",
  "properties": {
    "tgn:hierarchy":[
        "tgn:2605371",
        "tgn:1000001",
        "tgn:7012149",
        "tgn:2001448",
        "tgn:7007566",
        "tgn:7029392"
    ],
    "tgn:id":2605371,
    "tgn:name":"Ragland Hill",
    "tgn:placetype":[
        "aat:300008798"
    ]
},
  "bbox": [],
  "geometry": {"coordinates":[-103.7333,34.8167],"type":"Point"}
}