<<<<<<< HEAD
{
  "id": 7379451,
  "type": "Feature",
  "properties": {
    "tgn:hierarchy":[
        "tgn:7379451",
        "tgn:7005581",
        "tgn:1000001",
        "tgn:7005560",
        "tgn:7029392"
    ],
    "tgn:id":7379451,
    "tgn:name":"Los Tanques",
    "tgn:placetype":[
        "aat:300008347"
    ]
},
  "bbox": [],
  "geometry": {"coordinates":[-107.483333,28.1],"type":"Point"}
}
=======
{"geometry":{"type":"Point","coordinates":[-107.483333,28.100000]},"type":"Feature","properties":{"hierarchy":["tgn:7379451","tgn:7005581","tgn:1000001","tgn:7005560","tgn:7029392"],"placetype":["aat:300008347"],"id":7379451,"name:xx":"Los Tanques"}}
>>>>>>> 03f74aca74312dbeaf24d7e61306dd6a786dc3d0
