{
  "id": 7282467,
  "type": "Feature",
  "properties": {
    "tgn:hierarchy":[
        "tgn:7282467",
        "tgn:1001695",
        "tgn:1000049",
        "tgn:1000002",
        "tgn:7029392"
    ],
    "tgn:id":7282467,
    "tgn:name":"Peumo, Loma del",
    "tgn:placetype":[
        "aat:300008795"
    ]
},
  "bbox": [],
  "geometry": {"coordinates":[-71.183333,-34.216667],"type":"Point"}
}