{
  "id": 2458183,
  "type": "Feature",
  "properties": {
    "tgn:hierarchy":[
        "tgn:2458183",
        "tgn:1000001",
        "tgn:7012149",
        "tgn:2002118",
        "tgn:7007827",
        "tgn:7029392"
    ],
    "tgn:id":2458183,
    "tgn:name":"Little Mountain",
    "tgn:placetype":[
        "aat:300008798"
    ]
},
  "bbox": [],
  "geometry": {"coordinates":[-111.6833,40.7833],"type":"Point"}
}