<<<<<<< HEAD
{
  "id": 2762946,
  "type": "Feature",
  "properties": {
    "tgn:hierarchy":[
        "tgn:2762946",
        "tgn:1000001",
        "tgn:7012149",
        "tgn:1002565",
        "tgn:7007252",
        "tgn:7029392"
    ],
    "tgn:id":2762946,
    "tgn:name":"Westler Lake",
    "tgn:placetype":[
        "aat:300008680"
    ]
},
  "bbox": [],
  "geometry": {"coordinates":[-85.4,41.5333],"type":"Point"}
}
=======
{"geometry":{"type":"Point","coordinates":[-85.400000,41.533300]},"type":"Feature","properties":{"hierarchy":["tgn:2762946","tgn:1000001","tgn:7012149","tgn:1002565","tgn:7007252","tgn:7029392"],"placetype":["aat:300008680"],"id":2762946,"name:xx":"Westler Lake"}}
>>>>>>> 03f74aca74312dbeaf24d7e61306dd6a786dc3d0
