{
  "id": 2591964,
  "type": "Feature",
  "properties": {
    "tgn:hierarchy":[
        "tgn:2591964",
        "tgn:1002201",
        "tgn:1000001",
        "tgn:7012149",
        "tgn:7007517",
        "tgn:7029392"
    ],
    "tgn:id":2591964,
    "tgn:name":"Pond Swamp",
    "tgn:placetype":[
        "aat:300008905"
    ]
},
  "bbox": [],
  "geometry": {"coordinates":[-71.0833,41.7333],"type":"Point"}
}