{
  "id": 7293260,
  "type": "Feature",
  "properties": {
    "tgn:hierarchy":[
        "tgn:7293260",
        "tgn:7002758",
        "tgn:7002823",
        "tgn:1000003",
        "tgn:1000095",
        "tgn:7029392"
    ],
    "tgn:id":7293260,
    "tgn:name":"Casa de la Mogea",
    "tgn:placetype":[
        "aat:300005433"
    ]
},
  "bbox": [],
  "geometry": {"coordinates":[-6.514444,37.039722],"type":"Point"}
}