{
  "id": 7325519,
  "type": "Feature",
  "properties": {
    "tgn:hierarchy":[
        "tgn:7325519",
        "tgn:7002759",
        "tgn:7002845",
        "tgn:1000003",
        "tgn:1000095",
        "tgn:7029392"
    ],
    "tgn:id":7325519,
    "tgn:name":"San Benito, Barranco de",
    "tgn:placetype":[
        "aat:300266554",
        "aat:300008699"
    ]
},
  "bbox": [],
  "geometry": {"coordinates":[-0.483333,41.616667],"type":"Point"}
}