{
  "id": 1106044,
  "type": "Feature",
  "properties": {
    "tgn:hierarchy":[
        "tgn:1106044",
        "tgn:1007114",
        "tgn:7001635",
        "tgn:7001242",
        "tgn:7001632",
        "tgn:7029392"
    ],
    "tgn:id":1106044,
    "tgn:name":"Pico",
    "tgn:placetype":[
        "aat:300008795"
    ]
},
  "bbox": [],
  "geometry": {"coordinates":[-24.35,14.9333],"type":"Point"}
}