{
  "id": 7255964,
  "type": "Feature",
  "properties": {
    "tgn:hierarchy":[
        "tgn:7255964",
        "tgn:7003457",
        "tgn:1000003",
        "tgn:1000063",
        "tgn:7018236",
        "tgn:7029392"
    ],
    "tgn:id":7255964,
    "tgn:name":"Singelberg",
    "tgn:placetype":[
        "aat:300008347"
    ]
},
  "bbox": [],
  "geometry": {"coordinates":[4.242005,51.234665],"type":"Point"}
}