{
  "id": 2406537,
  "type": "Feature",
  "properties": {
    "tgn:hierarchy":[
        "tgn:2406537",
        "tgn:1000001",
        "tgn:7012149",
        "tgn:1002999",
        "tgn:7007526",
        "tgn:7029392"
    ],
    "tgn:id":2406537,
    "tgn:name":"Hungry Spring",
    "tgn:placetype":[
        "aat:300008697"
    ]
},
  "bbox": [],
  "geometry": {"coordinates":[-119.7167,39.75],"type":"Point"}
}