<<<<<<< HEAD
{
  "id": 7056116,
  "type": "Feature",
  "properties": {
    "tgn:hierarchy":[
        "tgn:7056116",
        "tgn:1000003",
        "tgn:7003122",
        "tgn:1000080",
        "tgn:7029392"
    ],
    "tgn:id":7056116,
    "tgn:name":"Lentini, Fosso di",
    "tgn:placetype":[
        "aat:300008699"
    ]
},
  "bbox": [],
  "geometry": {"coordinates":[15.066667,37.333333],"type":"Point"}
}
=======
{"geometry":{"type":"Point","coordinates":[15.066667,37.333333]},"type":"Feature","properties":{"hierarchy":["tgn:7056116","tgn:1000003","tgn:7003122","tgn:1000080","tgn:7029392"],"placetype":["aat:300008699"],"id":7056116,"name:xx":"Lentini, Fosso di"}}
>>>>>>> 03f74aca74312dbeaf24d7e61306dd6a786dc3d0
