{
  "id": 2759402,
  "type": "Feature",
  "properties": {
    "tgn:hierarchy":[
        "tgn:2759402",
        "tgn:2002365",
        "tgn:1000001",
        "tgn:7012149",
        "tgn:7007923",
        "tgn:7029392"
    ],
    "tgn:id":2759402,
    "tgn:name":"West Fork Dale Creek",
    "tgn:placetype":[
        "aat:300008706"
    ]
},
  "bbox": [],
  "geometry": {"coordinates":[-105.4167,41.0333],"type":"Point"}
}