{
  "id": 2103940,
  "type": "Feature",
  "properties": {
    "tgn:hierarchy":[
        "tgn:2103940",
        "tgn:1000001",
        "tgn:7012149",
        "tgn:2001983",
        "tgn:7007826",
        "tgn:7029392"
    ],
    "tgn:id":2103940,
    "tgn:name":"Ector",
    "tgn:placetype":[
        "aat:300008347"
    ]
},
  "bbox": [],
  "geometry": {"coordinates":[-96.2667,33.5667],"type":"Point"}
}