{
  "id": 7148137,
  "type": "Feature",
  "properties": {
    "tgn:hierarchy":[
        "tgn:7148137",
        "tgn:7003669",
        "tgn:1000003",
        "tgn:7000084",
        "tgn:7029392"
    ],
    "tgn:id":7148137,
    "tgn:name":"Kurzenaltheim",
    "tgn:placetype":[
        "aat:300008347"
    ]
},
  "bbox": [],
  "geometry": {"coordinates":[10.783333,49.033333],"type":"Point"}
}