{
  "id": 2509688,
  "type": "Feature",
  "properties": {
    "tgn:hierarchy":[
        "tgn:2509688",
        "tgn:1000001",
        "tgn:7012149",
        "tgn:1002977",
        "tgn:7007240",
        "tgn:7029392"
    ],
    "tgn:id":2509688,
    "tgn:name":"Middle Island",
    "tgn:placetype":[
        "aat:300008791"
    ]
},
  "bbox": [],
  "geometry": {"coordinates":[-80.7833,28.85],"type":"Point"}
}