{
  "id": 2101845,
  "type": "Feature",
  "properties": {
    "tgn:hierarchy":[
        "tgn:2101845",
        "tgn:1000001",
        "tgn:2001841",
        "tgn:7012149",
        "tgn:7007825",
        "tgn:7029392"
    ],
    "tgn:id":2101845,
    "tgn:name":"Townsend",
    "tgn:placetype":[
        "aat:300008347"
    ]
},
  "bbox": [],
  "geometry": {"coordinates":[-83.75,35.6667],"type":"Point"}
}