{
  "id": 2335103,
  "type": "Feature",
  "properties": {
    "tgn:hierarchy":[
        "tgn:2335103",
        "tgn:1000001",
        "tgn:7012149",
        "tgn:2001274",
        "tgn:7007524",
        "tgn:7029392"
    ],
    "tgn:id":2335103,
    "tgn:name":"Forster Mountain",
    "tgn:placetype":[
        "aat:300008798"
    ]
},
  "bbox": [],
  "geometry": {"coordinates":[-113.4833,48.1833],"type":"Point"}
}