{
  "id": 2677108,
  "type": "Feature",
  "properties": {
    "tgn:hierarchy":[
        "tgn:2677108",
        "tgn:1000001",
        "tgn:7012149",
        "tgn:7007520",
        "tgn:7029392"
    ],
    "tgn:id":2677108,
    "tgn:name":"South Branch Rice Creek",
    "tgn:placetype":[
        "aat:300008706"
    ]
},
  "bbox": [],
  "geometry": {"coordinates":[-84.65,42.25],"type":"Point"}
}