{
  "id": 7146596,
  "type": "Feature",
  "properties": {
    "tgn:hierarchy":[
        "tgn:7146596",
        "tgn:7003669",
        "tgn:1000003",
        "tgn:7000084",
        "tgn:7029392"
    ],
    "tgn:id":7146596,
    "tgn:name":"Kopfsberg",
    "tgn:placetype":[
        "aat:300008347"
    ]
},
  "bbox": [],
  "geometry": {"coordinates":[13.433333,48.483333],"type":"Point"}
}