{
  "id": 2668755,
  "type": "Feature",
  "properties": {
    "tgn:hierarchy":[
        "tgn:2668755",
        "tgn:1000001",
        "tgn:7012149",
        "tgn:2001854",
        "tgn:7007825",
        "tgn:7029392"
    ],
    "tgn:id":2668755,
    "tgn:name":"Slatestone Branch",
    "tgn:placetype":[
        "aat:300008699"
    ]
},
  "bbox": [],
  "geometry": {"coordinates":[-85.0667,36.0667],"type":"Point"}
}