<<<<<<< HEAD
{
  "id": 7484560,
  "type": "Feature",
  "properties": {
    "tgn:hierarchy":[
        "tgn:7484560",
        "tgn:1000004",
        "tgn:7492971",
        "tgn:1000141",
        "tgn:7029392"
    ],
    "tgn:id":7484560,
    "tgn:name":"Beiqiwei",
    "tgn:placetype":[
        "aat:300387033"
    ]
},
  "bbox": [],
  "geometry": {"coordinates":[120.581667,22.404167],"type":"Point"}
}
=======
{"geometry":{"type":"Point","coordinates":[120.581667,22.404167]},"type":"Feature","properties":{"hierarchy":["tgn:7484560","tgn:1000004","tgn:7492971","tgn:1000141","tgn:7029392"],"placetype":["aat:300387033"],"id":7484560,"name:xx":"Beiqiwei"}}
>>>>>>> 03f74aca74312dbeaf24d7e61306dd6a786dc3d0
