{
  "id": 2601402,
  "type": "Feature",
  "properties": {
    "tgn:hierarchy":[
        "tgn:2601402",
        "tgn:1000001",
        "tgn:7012149",
        "tgn:2000230",
        "tgn:7007158",
        "tgn:7029392"
    ],
    "tgn:id":2601402,
    "tgn:name":"Purdy Mesa",
    "tgn:placetype":[
        "aat:300008798"
    ]
},
  "bbox": [],
  "geometry": {"coordinates":[-108.2833,39.95],"type":"Point"}
}