{
  "id": 2365898,
  "type": "Feature",
  "properties": {
    "tgn:hierarchy":[
        "tgn:2365898",
        "tgn:1000001",
        "tgn:7012149",
        "tgn:2001903",
        "tgn:7007825",
        "tgn:7029392"
    ],
    "tgn:id":2365898,
    "tgn:name":"Grey",
    "tgn:placetype":[
        "aat:300008347"
    ]
},
  "bbox": [],
  "geometry": {"coordinates":[-85.3833,36.4667],"type":"Point"}
}