{
  "id": 1108209,
  "type": "Feature",
  "properties": {
    "tgn:hierarchy":[
        "tgn:1108209",
        "tgn:7003712",
        "tgn:7003670",
        "tgn:1000003",
        "tgn:7000084",
        "tgn:7029392"
    ],
    "tgn:id":1108209,
    "tgn:name":"Sch\u00e4ferberg",
    "tgn:placetype":[
        "aat:300008777"
    ]
},
  "bbox": [],
  "geometry": {"coordinates":[13.133333,52.416667],"type":"Point"}
}