{
  "id": 7437063,
  "type": "Feature",
  "properties": {
    "tgn:hierarchy":[
        "tgn:7437063",
        "tgn:7005585",
        "tgn:1000001",
        "tgn:7005560",
        "tgn:7029392"
    ],
    "tgn:id":7437063,
    "tgn:name":"Tepetlapa",
    "tgn:placetype":[
        "aat:300008347"
    ]
},
  "bbox": [],
  "geometry": {"coordinates":[-99.416667,18.55],"type":"Point"}
}