{
  "id": 2130027,
  "type": "Feature",
  "properties": {
    "tgn:hierarchy":[
        "tgn:2130027",
        "tgn:1000001",
        "tgn:7012149",
        "tgn:2000964",
        "tgn:7007520",
        "tgn:7029392"
    ],
    "tgn:id":2130027,
    "tgn:name":"Allen Drain",
    "tgn:placetype":[
        "aat:300006075"
    ]
},
  "bbox": [],
  "geometry": {"coordinates":[-82.7833,43.7667],"type":"Point"}
}