{
  "id": 7186295,
  "type": "Feature",
  "properties": {
    "tgn:hierarchy":[
        "tgn:7186295",
        "tgn:7000096",
        "tgn:1000003",
        "tgn:7000084",
        "tgn:7029392"
    ],
    "tgn:id":7186295,
    "tgn:name":"Golischa-Graben",
    "tgn:placetype":[
        "aat:300008699"
    ]
},
  "bbox": [],
  "geometry": {"coordinates":[14.466667,51.65],"type":"Point"}
}