{
  "id": 7491138,
  "type": "Feature",
  "properties": {
    "tgn:hierarchy":[
        "tgn:7491138",
        "tgn:1000004",
        "tgn:7492971",
        "tgn:1000141",
        "tgn:7029392"
    ],
    "tgn:id":7491138,
    "tgn:name":"Shiwen",
    "tgn:placetype":[
        "aat:300008347"
    ]
},
  "bbox": [],
  "geometry": {"coordinates":[120.663056,22.368611],"type":"Point"}
}