{
  "id": 1007073,
  "type": "Feature",
  "properties": {
    "tgn:hierarchy":[
        "tgn:1007073",
        "tgn:7018312",
        "tgn:1000001",
        "tgn:7004545",
        "tgn:7029392"
    ],
    "tgn:id":1007073,
    "tgn:name":"Fajou, \u00celet \u00e0",
    "tgn:placetype":[
        "aat:300386852"
    ]
},
  "bbox": [],
  "geometry": {"coordinates":[-61.5833,16.35],"type":"Point"}
}