{
  "id": 2700658,
  "type": "Feature",
  "properties": {
    "tgn:hierarchy":[
        "tgn:2700658",
        "tgn:1000001",
        "tgn:1002278",
        "tgn:7012149",
        "tgn:7007710",
        "tgn:7029392"
    ],
    "tgn:id":2700658,
    "tgn:name":"Sucker Run",
    "tgn:placetype":[
        "aat:300008699"
    ]
},
  "bbox": [],
  "geometry": {"coordinates":[-78.5833,40.8167],"type":"Point"}
}