{
  "id": 7033675,
  "type": "Feature",
  "properties": {
    "tgn:hierarchy":[
        "tgn:7033675",
        "tgn:7003129",
        "tgn:1000003",
        "tgn:7008516",
        "tgn:1000080",
        "tgn:7029392"
    ],
    "tgn:id":7033675,
    "tgn:name":"Massa",
    "tgn:placetype":[
        "aat:300008347"
    ]
},
  "bbox": [],
  "geometry": {"coordinates":[12.333333,44.094167],"type":"Point"}
}