{
  "id": 2302770,
  "type": "Feature",
  "properties": {
    "tgn:hierarchy":[
        "tgn:2302770",
        "tgn:1000001",
        "tgn:7012149",
        "tgn:2001752",
        "tgn:7007712",
        "tgn:7029392"
    ],
    "tgn:id":2302770,
    "tgn:name":"Dye Mill Branch",
    "tgn:placetype":[
        "aat:300008699"
    ]
},
  "bbox": [],
  "geometry": {"coordinates":[-80.65,34.5167],"type":"Point"}
}