{
  "id": 1006931,
  "type": "Feature",
  "properties": {
    "tgn:hierarchy":[
        "tgn:1006931",
        "tgn:1000004",
        "tgn:7001796",
        "tgn:1000111",
        "tgn:7029392"
    ],
    "tgn:id":1006931,
    "tgn:name":"Dayu Shan",
    "tgn:placetype":[
        "aat:300008791"
    ]
},
  "bbox": [],
  "geometry": {"coordinates":[120.35,26.95],"type":"Point"}
}