<<<<<<< HEAD
{
  "id": 7473876,
  "type": "Feature",
  "properties": {
    "tgn:hierarchy":[
        "tgn:7473876",
        "tgn:1000004",
        "tgn:7490934",
        "tgn:1000141",
        "tgn:7029392"
    ],
    "tgn:id":7473876,
    "tgn:name":"Dunzijiao",
    "tgn:placetype":[
        "aat:300008347"
    ]
},
  "bbox": [],
  "geometry": {"coordinates":[120.470556,23.281944],"type":"Point"}
}
=======
{"geometry":{"type":"Point","coordinates":[120.470556,23.281944]},"type":"Feature","properties":{"hierarchy":["tgn:7473876","tgn:1000004","tgn:7490934","tgn:1000141","tgn:7029392"],"placetype":["aat:300008347"],"id":7473876,"name:xx":"Dunzijiao"}}
>>>>>>> 03f74aca74312dbeaf24d7e61306dd6a786dc3d0
