{
  "id": 2065825,
  "type": "Feature",
  "properties": {
    "tgn:hierarchy":[
        "tgn:2065825",
        "tgn:1002227",
        "tgn:1000001",
        "tgn:7012149",
        "tgn:7007565",
        "tgn:7029392"
    ],
    "tgn:id":2065825,
    "tgn:name":"Penbryn",
    "tgn:placetype":[
        "aat:300008347",
        "aat:300387210"
    ]
},
  "bbox": [],
  "geometry": {"coordinates":[-74.9333,39.75],"type":"Point"}
}