{
  "id": 7109198,
  "type": "Feature",
  "properties": {
    "tgn:hierarchy":[
        "tgn:7109198",
        "tgn:7003669",
        "tgn:1000003",
        "tgn:7000084",
        "tgn:7029392"
    ],
    "tgn:id":7109198,
    "tgn:name":"Ransbach",
    "tgn:placetype":[
        "aat:300008347"
    ]
},
  "bbox": [],
  "geometry": {"coordinates":[11.75,49.316667],"type":"Point"}
}