{
  "id": 7510779,
  "type": "Feature",
  "properties": {
    "tgn:hierarchy":[
        "tgn:7510779",
        "tgn:1009227",
        "tgn:1000226",
        "tgn:7520095",
        "tgn:1000006",
        "tgn:7029392"
    ],
    "tgn:id":7510779,
    "tgn:name:en":"South Branch Mokihinui River",
    "tgn:placetype":[
        "aat:300008699"
    ]
},
  "bbox": [],
  "geometry": {"coordinates":[172.183333,-41.55],"type":"Point"}
}