<<<<<<< HEAD
{
  "id": 7378779,
  "type": "Feature",
  "properties": {
    "tgn:hierarchy":[
        "tgn:7378779",
        "tgn:1000001",
        "tgn:7005595",
        "tgn:7005560",
        "tgn:7029392"
    ],
    "tgn:id":7378779,
    "tgn:name":"Los Cedros",
    "tgn:placetype":[
        "aat:300008347"
    ]
},
  "bbox": [],
  "geometry": {"coordinates":[-106.971111,24.845556],"type":"Point"}
}
=======
{"geometry":{"type":"Point","coordinates":[-106.971111,24.845556]},"type":"Feature","properties":{"hierarchy":["tgn:7378779","tgn:1000001","tgn:7005595","tgn:7005560","tgn:7029392"],"placetype":["aat:300008347"],"id":7378779,"name:xx":"Los Cedros"}}
>>>>>>> 03f74aca74312dbeaf24d7e61306dd6a786dc3d0
