{
  "id": 7523472,
  "type": "Feature",
  "properties": {
    "tgn:hierarchy":[
        "tgn:7523472",
        "tgn:7001242",
        "tgn:7016833",
        "tgn:1001114",
        "tgn:7029392"
    ],
    "tgn:id":7523472,
    "tgn:name:en":"Duwaynah",
    "tgn:placetype":[
        "aat:300008347"
    ]
},
  "bbox": [],
  "geometry": {"coordinates":[31.266835,27.059505],"type":"Point"}
}