{
  "id": 2460703,
  "type": "Feature",
  "properties": {
    "tgn:hierarchy":[
        "tgn:2460703",
        "tgn:1000001",
        "tgn:7012149",
        "tgn:2000978",
        "tgn:7007520",
        "tgn:7029392"
    ],
    "tgn:id":2460703,
    "tgn:name":"Little Shakey Creek",
    "tgn:placetype":[
        "aat:300008706"
    ]
},
  "bbox": [],
  "geometry": {"coordinates":[-87.6667,45.5333],"type":"Point"}
}