{
  "id": 7557273,
  "type": "Feature",
  "properties": {
    "tgn:hierarchy":[
        "tgn:7557273",
        "tgn:1000004",
        "tgn:1001842",
        "tgn:7000198",
        "tgn:7029392"
    ],
    "tgn:id":7557273,
    "tgn:name:en":"Saksoh\u0101ra",
    "tgn:placetype":[
        "aat:300008347"
    ]
},
  "bbox": [],
  "geometry": {"coordinates":[85.70144,25.36354],"type":"Point"}
}