{
  "id": 7502648,
  "type": "Feature",
  "properties": {
    "tgn:hierarchy":[
        "tgn:7502648",
        "tgn:1000004",
        "tgn:7491221",
        "tgn:1000141",
        "tgn:7029392"
    ],
    "tgn:id":7502648,
    "tgn:name":"Jianadian Xi",
    "tgn:placetype":[
        "aat:300008699"
    ]
},
  "bbox": [],
  "geometry": {"coordinates":[121.159167,22.997778],"type":"Point"}
}