{
  "id": 2236920,
  "type": "Feature",
  "properties": {
    "tgn:hierarchy":[
        "tgn:2236920",
        "tgn:1000001",
        "tgn:1002219",
        "tgn:7012149",
        "tgn:7007157",
        "tgn:7029392"
    ],
    "tgn:id":2236920,
    "tgn:name":"Chili Camp Gulch",
    "tgn:placetype":[
        "aat:300008761"
    ]
},
  "bbox": [],
  "geometry": {"coordinates":[-120.8333,38.1833],"type":"Point"}
}