{
  "id": 1071012,
  "type": "Feature",
  "properties": {
    "tgn:hierarchy":[
        "tgn:1071012",
        "tgn:1000004",
        "tgn:7002076",
        "tgn:1000111",
        "tgn:7029392"
    ],
    "tgn:id":1071012,
    "tgn:name":"Qiaoxiazhen",
    "tgn:placetype":[
        "aat:300008347"
    ]
},
  "bbox": [],
  "geometry": {"coordinates":[120.55,28.1667],"type":"Point"}
}