{
  "id": 7437426,
  "type": "Feature",
  "properties": {
    "tgn:hierarchy":[
        "tgn:7437426",
        "tgn:7005583",
        "tgn:1000001",
        "tgn:7005560",
        "tgn:7029392"
    ],
    "tgn:id":7437426,
    "tgn:name":"Sext\u00edn, Rio de",
    "tgn:placetype":[
        "aat:300008699"
    ]
},
  "bbox": [],
  "geometry": {"coordinates":[-105.083333,25.683333],"type":"Point"}
}