{
  "id": 2205503,
  "type": "Feature",
  "properties": {
    "tgn:hierarchy":[
        "tgn:2205503",
        "tgn:1000001",
        "tgn:7012149",
        "tgn:7007712",
        "tgn:7029392"
    ],
    "tgn:id":2205503,
    "tgn:name":"Bull Creek",
    "tgn:placetype":[
        "aat:300008706"
    ]
},
  "bbox": [],
  "geometry": {"coordinates":[-79.1333,33.65],"type":"Point"}
}