{
  "id": 2138179,
  "type": "Feature",
  "properties": {
    "tgn:hierarchy":[
        "tgn:2138179",
        "tgn:2002240",
        "tgn:1000001",
        "tgn:7012149",
        "tgn:7007920",
        "tgn:7029392"
    ],
    "tgn:id":2138179,
    "tgn:name":"Artesian Coulee",
    "tgn:placetype":[
        "aat:300008761"
    ]
},
  "bbox": [],
  "geometry": {"coordinates":[-119.8167,45.8667],"type":"Point"}
}