{
  "id": 7557323,
  "type": "Feature",
  "properties": {
    "tgn:hierarchy":[
        "tgn:7557323",
        "tgn:1000004",
        "tgn:7000198",
        "tgn:7001797",
        "tgn:7029392"
    ],
    "tgn:id":7557323,
    "tgn:name:en":"P\u0101ppamb\u0101di",
    "tgn:placetype":[
        "aat:300008347"
    ]
},
  "bbox": [],
  "geometry": {"coordinates":[77.95,11.65],"type":"Point"}
}