{
  "id": 2742898,
  "type": "Feature",
  "properties": {
    "tgn:hierarchy":[
        "tgn:2742898",
        "tgn:1000001",
        "tgn:7012149",
        "tgn:1002920",
        "tgn:7007568",
        "tgn:7029392"
    ],
    "tgn:id":2742898,
    "tgn:name":"Van Keuren Lake",
    "tgn:placetype":[
        "aat:300008680"
    ]
},
  "bbox": [],
  "geometry": {"coordinates":[-77.1667,42.3167],"type":"Point"}
}