{
  "id": 7038387,
  "type": "Feature",
  "properties": {
    "tgn:hierarchy":[
        "tgn:7038387",
        "tgn:7003170",
        "tgn:1000003",
        "tgn:7003125",
        "tgn:1000080",
        "tgn:7029392"
    ],
    "tgn:id":7038387,
    "tgn:name":"Torchiagina",
    "tgn:placetype":[
        "aat:300008347"
    ]
},
  "bbox": [],
  "geometry": {"coordinates":[12.533333,43.116667],"type":"Point"}
}