{
  "id": 7311354,
  "type": "Feature",
  "properties": {
    "tgn:hierarchy":[
        "tgn:7311354",
        "tgn:1001702",
        "tgn:1000049",
        "tgn:1000002",
        "tgn:7029392"
    ],
    "tgn:id":7311354,
    "tgn:name":"Negra, Punta",
    "tgn:placetype":[
        "aat:300386846"
    ]
},
  "bbox": [],
  "geometry": {"coordinates":[-72.75,-53.283333],"type":"Point"}
}