{
  "id": 2764739,
  "type": "Feature",
  "properties": {
    "tgn:hierarchy":[
        "tgn:2764739",
        "tgn:1000001",
        "tgn:7012149",
        "tgn:2000657",
        "tgn:7007253",
        "tgn:7029392"
    ],
    "tgn:id":2764739,
    "tgn:name":"Whiskey Creek",
    "tgn:placetype":[
        "aat:300008706"
    ]
},
  "bbox": [],
  "geometry": {"coordinates":[-96.1167,42.25],"type":"Point"}
}