{
  "id": 7520540,
  "type": "Feature",
  "properties": {
    "tgn:hierarchy":[
        "tgn:7520540",
        "tgn:7001242",
        "tgn:7016833",
        "tgn:7029392"
    ],
    "tgn:id":7520540,
    "tgn:name:en":"Ab\u016b \u0162urayf\u012b, W\u0101d\u012b",
    "tgn:placetype":[
        "aat:300379998"
    ]
},
  "bbox": [],
  "geometry": {"coordinates":[31.44533,29.502238],"type":"Point"}
}