{
  "id": 7167854,
  "type": "Feature",
  "properties": {
    "tgn:hierarchy":[
        "tgn:7167854",
        "tgn:7003669",
        "tgn:1000003",
        "tgn:7000084",
        "tgn:7029392"
    ],
    "tgn:id":7167854,
    "tgn:name":"Hatthal",
    "tgn:placetype":[
        "aat:300000206"
    ]
},
  "bbox": [],
  "geometry": {"coordinates":[12.35,48.05],"type":"Point"}
}