{
  "id": 7483140,
  "type": "Feature",
  "properties": {
    "tgn:hierarchy":[
        "tgn:7483140",
        "tgn:1000004",
        "tgn:7001009",
        "tgn:1000141",
        "tgn:7029392"
    ],
    "tgn:id":7483140,
    "tgn:name":"Guishan Qiao",
    "tgn:placetype":[
        "aat:300007836"
    ]
},
  "bbox": [],
  "geometry": {"coordinates":[120.640833,24.331389],"type":"Point"}
}