{
  "id": 2532628,
  "type": "Feature",
  "properties": {
    "tgn:hierarchy":[
        "tgn:2532628",
        "tgn:1000001",
        "tgn:7012149",
        "tgn:1002794",
        "tgn:7007708",
        "tgn:7029392"
    ],
    "tgn:id":2532628,
    "tgn:name":"Murphy Hill",
    "tgn:placetype":[
        "aat:300008798"
    ]
},
  "bbox": [],
  "geometry": {"coordinates":[-123.6833,45.05],"type":"Point"}
}