{
  "id": 2202918,
  "type": "Feature",
  "properties": {
    "tgn:hierarchy":[
        "tgn:2202918",
        "tgn:1000001",
        "tgn:7012149",
        "tgn:7007157",
        "tgn:7014004",
        "tgn:7029392"
    ],
    "tgn:id":2202918,
    "tgn:name":"Buckeye Hill",
    "tgn:placetype":[
        "aat:300008798"
    ]
},
  "bbox": [],
  "geometry": {"coordinates":[-119.9333,37.3167],"type":"Point"}
}