{
  "id": 1016022,
  "type": "Feature",
  "properties": {
    "tgn:hierarchy":[
        "tgn:1016022",
        "tgn:7005685",
        "tgn:1000001",
        "tgn:7005805",
        "tgn:7029392"
    ],
    "tgn:id":1016022,
    "tgn:name":"Meacham",
    "tgn:placetype":[
        "aat:300008347"
    ]
},
  "bbox": [],
  "geometry": {"coordinates":[-105.7833,52.1167],"type":"Point"}
}