{
  "id": 7145576,
  "type": "Feature",
  "properties": {
    "tgn:hierarchy":[
        "tgn:7145576",
        "tgn:1000003",
        "tgn:7003676",
        "tgn:7000084",
        "tgn:7029392"
    ],
    "tgn:id":7145576,
    "tgn:name":"Kniestedt",
    "tgn:placetype":[
        "aat:300000745"
    ]
},
  "bbox": [],
  "geometry": {"coordinates":[10.383333,52.066667],"type":"Point"}
}