{
  "id": 7361480,
  "type": "Feature",
  "properties": {
    "tgn:hierarchy":[
        "tgn:7361480",
        "tgn:1000001",
        "tgn:7005599",
        "tgn:7005560",
        "tgn:7029392"
    ],
    "tgn:id":7361480,
    "tgn:name":"El Coyol",
    "tgn:placetype":[
        "aat:300008347"
    ]
},
  "bbox": [],
  "geometry": {"coordinates":[-96.683333,19.116667],"type":"Point"}
}