<<<<<<< HEAD
{
  "id": 7480980,
  "type": "Feature",
  "properties": {
    "tgn:hierarchy":[
        "tgn:7480980",
        "tgn:7001010",
        "tgn:1000004",
        "tgn:1000141",
        "tgn:7029392"
    ],
    "tgn:id":7480980,
    "tgn:name":"Hualian",
    "tgn:placetype":[
        "aat:300006676"
    ]
},
  "bbox": [],
  "geometry": {"coordinates":[121.611389,23.979167],"type":"Point"}
}
=======
{"geometry":{"type":"Point","coordinates":[121.611389,23.979167]},"type":"Feature","properties":{"hierarchy":["tgn:7480980","tgn:7001010","tgn:1000004","tgn:1000141","tgn:7029392"],"placetype":["aat:300006676"],"id":7480980,"name:xx":"Hualian"}}
>>>>>>> 03f74aca74312dbeaf24d7e61306dd6a786dc3d0
