{
  "id": 7480980,
  "type": "Feature",
  "properties": {
    "tgn:hierarchy":[
        "tgn:7480980",
        "tgn:7001010",
        "tgn:1000004",
        "tgn:1000141",
        "tgn:7029392"
    ],
    "tgn:id":7480980,
    "tgn:name":"Hualian",
    "tgn:placetype":[
        "aat:300006676"
    ]
},
  "bbox": [],
  "geometry": {"coordinates":[121.611389,23.979167],"type":"Point"}
}