{
  "id": 2050421,
  "type": "Feature",
  "properties": {
    "tgn:hierarchy":[
        "tgn:2050421",
        "tgn:1000001",
        "tgn:7013686",
        "tgn:7012149",
        "tgn:7007517",
        "tgn:7029392"
    ],
    "tgn:id":2050421,
    "tgn:name":"Plainville",
    "tgn:placetype":[
        "aat:300008347",
        "aat:300387210"
    ]
},
  "bbox": [],
  "geometry": {"coordinates":[-72.55,42.3667],"type":"Point"}
}