{
  "id": 2528564,
  "type": "Feature",
  "properties": {
    "tgn:hierarchy":[
        "tgn:2528564",
        "tgn:1000001",
        "tgn:7012149",
        "tgn:2001987",
        "tgn:7007826",
        "tgn:7029392"
    ],
    "tgn:id":2528564,
    "tgn:name":"Muchacho Tank",
    "tgn:placetype":[
        "aat:300006191"
    ]
},
  "bbox": [],
  "geometry": {"coordinates":[-99.25,28.8167],"type":"Point"}
}