{
  "id": 7033569,
  "type": "Feature",
  "properties": {
    "tgn:hierarchy":[
        "tgn:7033569",
        "tgn:7003133",
        "tgn:1000003",
        "tgn:7008516",
        "tgn:1000080",
        "tgn:7029392"
    ],
    "tgn:id":7033569,
    "tgn:name":"Bonifica di Val Mezzaca",
    "tgn:placetype":[
        "aat:300387200"
    ]
},
  "bbox": [],
  "geometry": {"coordinates":[12.145556,44.517222],"type":"Point"}
}