{
  "id": 1128562,
  "type": "Feature",
  "properties": {
    "tgn:hierarchy":[
        "tgn:1128562",
        "tgn:7005126",
        "tgn:1000003",
        "tgn:7003120",
        "tgn:1000080",
        "tgn:7029392"
    ],
    "tgn:id":1128562,
    "tgn:name":"Pesio",
    "tgn:placetype":[
        "aat:300008707",
        "aat:300008699"
    ]
},
  "bbox": [],
  "geometry": {"coordinates":[7.883333,44.466667],"type":"Point"}
}