{
  "id": 2740013,
  "type": "Feature",
  "properties": {
    "tgn:hierarchy":[
        "tgn:2740013",
        "tgn:1000001",
        "tgn:7012149",
        "tgn:2002359",
        "tgn:7007922",
        "tgn:7029392"
    ],
    "tgn:id":2740013,
    "tgn:name":"Upper Gresham Lake",
    "tgn:placetype":[
        "aat:300008680"
    ]
},
  "bbox": [],
  "geometry": {"coordinates":[-89.7333,46.0667],"type":"Point"}
}