<<<<<<< HEAD
{
  "id": 7360996,
  "type": "Feature",
  "properties": {
    "tgn:hierarchy":[
        "tgn:7360996",
        "tgn:7005581",
        "tgn:1000001",
        "tgn:7005560",
        "tgn:7029392"
    ],
    "tgn:id":7360996,
    "tgn:name":"El Borreguero",
    "tgn:placetype":[
        "aat:300008347"
    ]
},
  "bbox": [],
  "geometry": {"coordinates":[-106.783333,28.5],"type":"Point"}
}
=======
{"geometry":{"type":"Point","coordinates":[-106.783333,28.500000]},"type":"Feature","properties":{"hierarchy":["tgn:7360996","tgn:7005581","tgn:1000001","tgn:7005560","tgn:7029392"],"placetype":["aat:300008347"],"id":7360996,"name:xx":"El Borreguero"}}
>>>>>>> 03f74aca74312dbeaf24d7e61306dd6a786dc3d0
