{
  "id": 2129226,
  "type": "Feature",
  "properties": {
    "tgn:hierarchy":[
        "tgn:2129226",
        "tgn:1000001",
        "tgn:7012149",
        "tgn:1002298",
        "tgn:7007157",
        "tgn:7029392"
    ],
    "tgn:id":2129226,
    "tgn:name":"Alhambra Valley",
    "tgn:placetype":[
        "aat:300008761"
    ]
},
  "bbox": [],
  "geometry": {"coordinates":[-122.15,37.9333],"type":"Point"}
}