{
  "id": 7066113,
  "type": "Feature",
  "properties": {
    "tgn:hierarchy":[
        "tgn:7066113",
        "tgn:1000003",
        "tgn:7003677",
        "tgn:7000084",
        "tgn:7029392"
    ],
    "tgn:id":7066113,
    "tgn:name":"Trostheide",
    "tgn:placetype":[
        "aat:300000206"
    ]
},
  "bbox": [],
  "geometry": {"coordinates":[8.216667,51.833333],"type":"Point"}
}