{
  "id": 2531118,
  "type": "Feature",
  "properties": {
    "tgn:hierarchy":[
        "tgn:2531118",
        "tgn:1000001",
        "tgn:7012149",
        "tgn:7019676",
        "tgn:7007566",
        "tgn:7029392"
    ],
    "tgn:id":2531118,
    "tgn:name":"Mulatto Canyon",
    "tgn:placetype":[
        "aat:300008761"
    ]
},
  "bbox": [],
  "geometry": {"coordinates":[-107.7667,35.4167],"type":"Point"}
}