{
  "id": 7470841,
  "type": "Feature",
  "properties": {
    "tgn:hierarchy":[
        "tgn:7470841",
        "tgn:1000004",
        "tgn:7490934",
        "tgn:1000141",
        "tgn:7029392"
    ],
    "tgn:id":7470841,
    "tgn:name":"Jiuxionglin",
    "tgn:placetype":[
        "aat:300008347"
    ]
},
  "bbox": [],
  "geometry": {"coordinates":[120.368333,22.965],"type":"Point"}
}