{
  "id": 7574434,
  "type": "Feature",
  "properties": {
    "tgn:hierarchy":[
        "tgn:7574434",
        "tgn:1000004",
        "tgn:7000198",
        "tgn:7000799",
        "tgn:7029392"
    ],
    "tgn:id":7574434,
    "tgn:name:en":"Kungi La",
    "tgn:placetype":[
        "aat:300259572"
    ]
},
  "bbox": [],
  "geometry": {"coordinates":[76.526098,34.105615],"type":"Point"}
}