{
  "id": 7513477,
  "type": "Feature",
  "properties": {
    "tgn:hierarchy":[
        "tgn:7513477",
        "tgn:1009227",
        "tgn:7001866",
        "tgn:1000226",
        "tgn:1000006",
        "tgn:7029392"
    ],
    "tgn:id":7513477,
    "tgn:name:en":"Glendhu",
    "tgn:placetype":[
        "aat:300008795"
    ]
},
  "bbox": [],
  "geometry": {"coordinates":[173.033333,-42.966667],"type":"Point"}
}