{
  "id": 7302644,
  "type": "Feature",
  "properties": {
    "tgn:hierarchy":[
        "tgn:7302644",
        "tgn:7002816",
        "tgn:1001647",
        "tgn:1000003",
        "tgn:1000095",
        "tgn:7029392"
    ],
    "tgn:id":7302644,
    "tgn:name":"Pajonales, Sierra de los",
    "tgn:placetype":[
        "aat:300266640"
    ]
},
  "bbox": [],
  "geometry": {"coordinates":[-4.733333,39.083333],"type":"Point"}
}