<<<<<<< HEAD
{
  "id": 2409787,
  "type": "Feature",
  "properties": {
    "tgn:hierarchy":[
        "tgn:2409787",
        "tgn:1000001",
        "tgn:7012149",
        "tgn:7014510",
        "tgn:7007920",
        "tgn:7029392"
    ],
    "tgn:id":2409787,
    "tgn:name":"Illabot Lake",
    "tgn:placetype":[
        "aat:300008680"
    ]
},
  "bbox": [],
  "geometry": {"coordinates":[-121.3667,48.4167],"type":"Point"}
}
=======
{"geometry":{"type":"Point","coordinates":[-121.366700,48.416700]},"type":"Feature","properties":{"hierarchy":["tgn:2409787","tgn:1000001","tgn:7012149","tgn:7014510","tgn:7007920","tgn:7029392"],"placetype":["aat:300008680"],"id":2409787,"name:xx":"Illabot Lake"}}
>>>>>>> 03f74aca74312dbeaf24d7e61306dd6a786dc3d0
