{
  "id": 2409787,
  "type": "Feature",
  "properties": {
    "tgn:hierarchy":[
        "tgn:2409787",
        "tgn:1000001",
        "tgn:7012149",
        "tgn:7014510",
        "tgn:7007920",
        "tgn:7029392"
    ],
    "tgn:id":2409787,
    "tgn:name":"Illabot Lake",
    "tgn:placetype":[
        "aat:300008680"
    ]
},
  "bbox": [],
  "geometry": {"coordinates":[-121.3667,48.4167],"type":"Point"}
}