{
  "id": 2468103,
  "type": "Feature",
  "properties": {
    "tgn:hierarchy":[
        "tgn:2468103",
        "tgn:1000001",
        "tgn:7012149",
        "tgn:2002326",
        "tgn:7007922",
        "tgn:7029392"
    ],
    "tgn:id":2468103,
    "tgn:name":"Long Lake",
    "tgn:placetype":[
        "aat:300008680"
    ]
},
  "bbox": [],
  "geometry": {"coordinates":[-90.3833,43.1833],"type":"Point"}
}