{
  "id": 7486599,
  "type": "Feature",
  "properties": {
    "tgn:hierarchy":[
        "tgn:7486599",
        "tgn:1000004",
        "tgn:7001014",
        "tgn:1000141",
        "tgn:7029392"
    ],
    "tgn:id":7486599,
    "tgn:name":"Mashancuo",
    "tgn:placetype":[
        "aat:300008347"
    ]
},
  "bbox": [],
  "geometry": {"coordinates":[120.240556,23.715833],"type":"Point"}
}