<<<<<<< HEAD
{
  "id": 7486599,
  "type": "Feature",
  "properties": {
    "tgn:hierarchy":[
        "tgn:7486599",
        "tgn:1000004",
        "tgn:7001014",
        "tgn:1000141",
        "tgn:7029392"
    ],
    "tgn:id":7486599,
    "tgn:name":"Mashancuo",
    "tgn:placetype":[
        "aat:300008347"
    ]
},
  "bbox": [],
  "geometry": {"coordinates":[120.240556,23.715833],"type":"Point"}
}
=======
{"geometry":{"type":"Point","coordinates":[120.240556,23.715833]},"type":"Feature","properties":{"hierarchy":["tgn:7486599","tgn:1000004","tgn:7001014","tgn:1000141","tgn:7029392"],"placetype":["aat:300008347"],"id":7486599,"name:xx":"Mashancuo"}}
>>>>>>> 03f74aca74312dbeaf24d7e61306dd6a786dc3d0
