<<<<<<< HEAD
{
  "id": 7059274,
  "type": "Feature",
  "properties": {
    "tgn:hierarchy":[
        "tgn:7059274",
        "tgn:7003669",
        "tgn:1000003",
        "tgn:7000084",
        "tgn:7029392"
    ],
    "tgn:id":7059274,
    "tgn:name":"Alter Main",
    "tgn:placetype":[
        "aat:300008680"
    ]
},
  "bbox": [],
  "geometry": {"coordinates":[10.183333,50.0],"type":"Point"}
}
=======
{"geometry":{"type":"Point","coordinates":[10.183333,50.000000]},"type":"Feature","properties":{"hierarchy":["tgn:7059274","tgn:7003669","tgn:1000003","tgn:7000084","tgn:7029392"],"placetype":["aat:300008680"],"id":7059274,"name:xx":"Alter Main"}}
>>>>>>> 03f74aca74312dbeaf24d7e61306dd6a786dc3d0
