{
  "id": 7181417,
  "type": "Feature",
  "properties": {
    "tgn:hierarchy":[
        "tgn:7181417",
        "tgn:7000096",
        "tgn:1000003",
        "tgn:7000084",
        "tgn:7029392"
    ],
    "tgn:id":7181417,
    "tgn:name":"Garrey",
    "tgn:placetype":[
        "aat:300008347"
    ]
},
  "bbox": [],
  "geometry": {"coordinates":[12.666667,52.016667],"type":"Point"}
}