{
  "id": 7428268,
  "type": "Feature",
  "properties": {
    "tgn:hierarchy":[
        "tgn:7428268",
        "tgn:1000001",
        "tgn:7005601",
        "tgn:7005560",
        "tgn:7029392"
    ],
    "tgn:id":7428268,
    "tgn:name":"El Duraznillo, Arroyo",
    "tgn:placetype":[
        "aat:300266554",
        "aat:300008699"
    ]
},
  "bbox": [],
  "geometry": {"coordinates":[-101.916667,23.866667],"type":"Point"}
}