{
  "id": 2727732,
  "type": "Feature",
  "properties": {
    "tgn:hierarchy":[
        "tgn:2727732",
        "tgn:1000001",
        "tgn:7006451",
        "tgn:2000095",
        "tgn:7012149",
        "tgn:7029392"
    ],
    "tgn:id":2727732,
    "tgn:name":"Trail Tank",
    "tgn:placetype":[
        "aat:300006191"
    ]
},
  "bbox": [],
  "geometry": {"coordinates":[-109.35,33.3333],"type":"Point"}
}