{
  "id": 2203145,
  "type": "Feature",
  "properties": {
    "tgn:hierarchy":[
        "tgn:2203145",
        "tgn:1000001",
        "tgn:7012149",
        "tgn:2002162",
        "tgn:7007919",
        "tgn:7029392"
    ],
    "tgn:id":2203145,
    "tgn:name":"Buckhorn Branch",
    "tgn:placetype":[
        "aat:300008699"
    ]
},
  "bbox": [],
  "geometry": {"coordinates":[-80.9833,37.2667],"type":"Point"}
}