{
  "id": 7497994,
  "type": "Feature",
  "properties": {
    "tgn:hierarchy":[
        "tgn:7497994",
        "tgn:1000957",
        "tgn:1000004",
        "tgn:1000141",
        "tgn:7029392"
    ],
    "tgn:id":7497994,
    "tgn:name":"Fuxing Suidao",
    "tgn:placetype":[
        "aat:300007899"
    ]
},
  "bbox": [],
  "geometry": {"coordinates":[121.741603,25.14798],"type":"Point"}
}