{
  "id": 7471443,
  "type": "Feature",
  "properties": {
    "tgn:hierarchy":[
        "tgn:7471443",
        "tgn:1000004",
        "tgn:7491221",
        "tgn:1000141",
        "tgn:7029392"
    ],
    "tgn:id":7471443,
    "tgn:name":"Shichuan",
    "tgn:placetype":[
        "aat:300008347"
    ]
},
  "bbox": [],
  "geometry": {"coordinates":[121.187346,22.793018],"type":"Point"}
}