{
  "id": 7212929,
  "type": "Feature",
  "properties": {
    "tgn:hierarchy":[
        "tgn:7212929",
        "tgn:1000003",
        "tgn:7003677",
        "tgn:7000084",
        "tgn:7029392"
    ],
    "tgn:id":7212929,
    "tgn:name":"Bahnhof Bonn Nord",
    "tgn:placetype":[
        "aat:300007783"
    ]
},
  "bbox": [],
  "geometry": {"coordinates":[7.066667,50.75],"type":"Point"}
}