<<<<<<< HEAD
{
  "id": 2400456,
  "type": "Feature",
  "properties": {
    "tgn:hierarchy":[
        "tgn:2400456",
        "tgn:1000001",
        "tgn:7012149",
        "tgn:2002111",
        "tgn:7007827",
        "tgn:7029392"
    ],
    "tgn:id":2400456,
    "tgn:name":"Horse Hollow",
    "tgn:placetype":[
        "aat:300008761"
    ]
},
  "bbox": [],
  "geometry": {"coordinates":[-113.0,37.5333],"type":"Point"}
}
=======
{"geometry":{"type":"Point","coordinates":[-113.000000,37.533300]},"type":"Feature","properties":{"hierarchy":["tgn:2400456","tgn:1000001","tgn:7012149","tgn:2002111","tgn:7007827","tgn:7029392"],"placetype":["aat:300008761"],"id":2400456,"name:xx":"Horse Hollow"}}
>>>>>>> 03f74aca74312dbeaf24d7e61306dd6a786dc3d0
