{
  "id": 2594577,
  "type": "Feature",
  "properties": {
    "tgn:hierarchy":[
        "tgn:2594577",
        "tgn:1000001",
        "tgn:7012149",
        "tgn:2001718",
        "tgn:7007708",
        "tgn:7029392"
    ],
    "tgn:id":2594577,
    "tgn:name":"Portugese Spring",
    "tgn:placetype":[
        "aat:300008697"
    ]
},
  "bbox": [],
  "geometry": {"coordinates":[-117.6667,42.3167],"type":"Point"}
}