{
  "id": 2762685,
  "type": "Feature",
  "properties": {
    "tgn:hierarchy":[
        "tgn:2762685",
        "tgn:1000001",
        "tgn:2001735",
        "tgn:7012149",
        "tgn:7007712",
        "tgn:7029392"
    ],
    "tgn:id":2762685,
    "tgn:name":"Westerly Park",
    "tgn:placetype":[
        "aat:300008347"
    ]
},
  "bbox": [],
  "geometry": {"coordinates":[-81.6667,35.0833],"type":"Point"}
}