{
  "id": 1015483,
  "type": "Feature",
  "properties": {
    "tgn:hierarchy":[
        "tgn:1015483",
        "tgn:7005685",
        "tgn:1000001",
        "tgn:7005804",
        "tgn:7029392"
    ],
    "tgn:id":1015483,
    "tgn:name":"Lennoxville",
    "tgn:placetype":[
        "aat:300008347"
    ]
},
  "bbox": [],
  "geometry": {"coordinates":[-71.85,45.3667],"type":"Point"}
}