{
  "id": 2457516,
  "type": "Feature",
  "properties": {
    "tgn:hierarchy":[
        "tgn:2457516",
        "tgn:1000001",
        "tgn:7012149",
        "tgn:2001718",
        "tgn:7007708",
        "tgn:7029392"
    ],
    "tgn:id":2457516,
    "tgn:name":"Little Louse Canyon",
    "tgn:placetype":[
        "aat:300008761"
    ]
},
  "bbox": [],
  "geometry": {"coordinates":[-117.6833,42.1333],"type":"Point"}
}