{
  "id": 2744418,
  "type": "Feature",
  "properties": {
    "tgn:hierarchy":[
        "tgn:2744418",
        "tgn:1000001",
        "tgn:7012149",
        "tgn:2000986",
        "tgn:7007520",
        "tgn:7029392"
    ],
    "tgn:id":2744418,
    "tgn:name":"Very Sudden Pond",
    "tgn:placetype":[
        "aat:300008680"
    ]
},
  "bbox": [],
  "geometry": {"coordinates":[-88.8833,46.7333],"type":"Point"}
}