{
  "id": 1018878,
  "type": "Feature",
  "properties": {
    "tgn:hierarchy":[
        "tgn:1018878",
        "tgn:1001201",
        "tgn:1000001",
        "tgn:7005565",
        "tgn:7029392"
    ],
    "tgn:id":1018878,
    "tgn:name":"Cais\u00e1n",
    "tgn:placetype":[
        "aat:300008347"
    ]
},
  "bbox": [],
  "geometry": {"coordinates":[-82.75,8.7667],"type":"Point"}
}