{
  "id": 7565986,
  "type": "Feature",
  "properties": {
    "tgn:hierarchy":[
        "tgn:7565986",
        "tgn:1000004",
        "tgn:7000198",
        "tgn:7016722",
        "tgn:7029392"
    ],
    "tgn:id":7565986,
    "tgn:name:en":"Purwa Gaja",
    "tgn:placetype":[
        "aat:300008347"
    ]
},
  "bbox": [],
  "geometry": {"coordinates":[79.733029,26.76783],"type":"Point"}
}