{
  "id": 2475983,
  "type": "Feature",
  "properties": {
    "tgn:hierarchy":[
        "tgn:2475983",
        "tgn:1000001",
        "tgn:7012149",
        "tgn:2001721",
        "tgn:7007708",
        "tgn:7029392"
    ],
    "tgn:id":2475983,
    "tgn:name":"Luger Spring",
    "tgn:placetype":[
        "aat:300008697"
    ]
},
  "bbox": [],
  "geometry": {"coordinates":[-117.95,45.7667],"type":"Point"}
}