{
  "id": 2715231,
  "type": "Feature",
  "properties": {
    "tgn:hierarchy":[
        "tgn:2715231",
        "tgn:1000001",
        "tgn:7012149",
        "tgn:2001274",
        "tgn:7007524",
        "tgn:7029392"
    ],
    "tgn:id":2715231,
    "tgn:name":"Tepee Mountain",
    "tgn:placetype":[
        "aat:300008798"
    ]
},
  "bbox": [],
  "geometry": {"coordinates":[-114.8167,47.8667],"type":"Point"}
}