{
  "id": 2085667,
  "type": "Feature",
  "properties": {
    "tgn:hierarchy":[
        "tgn:2085667",
        "tgn:1000001",
        "tgn:7012149",
        "tgn:2001723",
        "tgn:7007708",
        "tgn:7029392"
    ],
    "tgn:id":2085667,
    "tgn:name":"Twickenham",
    "tgn:placetype":[
        "aat:300008347",
        "aat:300387210"
    ]
},
  "bbox": [],
  "geometry": {"coordinates":[-120.1667,44.7333],"type":"Point"}
}