{
  "id": 2433232,
  "type": "Feature",
  "properties": {
    "tgn:hierarchy":[
        "tgn:2433232",
        "tgn:1000001",
        "tgn:2002310",
        "tgn:7012149",
        "tgn:7007922",
        "tgn:7029392"
    ],
    "tgn:id":2433232,
    "tgn:name":"Keller Island",
    "tgn:placetype":[
        "aat:300008791"
    ]
},
  "bbox": [],
  "geometry": {"coordinates":[-91.85,44.2167],"type":"Point"}
}