{
  "id": 7325127,
  "type": "Feature",
  "properties": {
    "tgn:hierarchy":[
        "tgn:7325127",
        "tgn:7002824",
        "tgn:1000003",
        "tgn:7002786",
        "tgn:1000095",
        "tgn:7029392"
    ],
    "tgn:id":7325127,
    "tgn:name":"San Vicente, Isla de",
    "tgn:placetype":[
        "aat:300008791"
    ]
},
  "bbox": [],
  "geometry": {"coordinates":[-7.833333,43.716667],"type":"Point"}
}