{
  "id": 1097088,
  "type": "Feature",
  "properties": {
    "tgn:hierarchy":[
        "tgn:1097088",
        "tgn:7000490",
        "tgn:1000006",
        "tgn:7001828",
        "tgn:7029392"
    ],
    "tgn:id":1097088,
    "tgn:name":"Hatfield",
    "tgn:placetype":[
        "aat:300008347"
    ]
},
  "bbox": [],
  "geometry": {"coordinates":[143.7833,-33.8833],"type":"Point"}
}