{
  "id": 2421864,
  "type": "Feature",
  "properties": {
    "tgn:hierarchy":[
        "tgn:2421864",
        "tgn:1000001",
        "tgn:2001432",
        "tgn:7012149",
        "tgn:7007566",
        "tgn:7029392"
    ],
    "tgn:id":2421864,
    "tgn:name":"Jill",
    "tgn:placetype":[
        "aat:300000390"
    ]
},
  "bbox": [],
  "geometry": {"coordinates":[-105.1833,36.6333],"type":"Point"}
}