{
  "id": 2408765,
  "type": "Feature",
  "properties": {
    "tgn:hierarchy":[
        "tgn:2408765",
        "tgn:1000001",
        "tgn:7012149",
        "tgn:7018871",
        "tgn:7007920",
        "tgn:7029392"
    ],
    "tgn:id":2408765,
    "tgn:name":"Hyde Lake",
    "tgn:placetype":[
        "aat:300008680"
    ]
},
  "bbox": [],
  "geometry": {"coordinates":[-121.9333,47.2833],"type":"Point"}
}