<<<<<<< HEAD
{
  "id": 2408765,
  "type": "Feature",
  "properties": {
    "tgn:hierarchy":[
        "tgn:2408765",
        "tgn:1000001",
        "tgn:7012149",
        "tgn:7018871",
        "tgn:7007920",
        "tgn:7029392"
    ],
    "tgn:id":2408765,
    "tgn:name":"Hyde Lake",
    "tgn:placetype":[
        "aat:300008680"
    ]
},
  "bbox": [],
  "geometry": {"coordinates":[-121.9333,47.2833],"type":"Point"}
}
=======
{"geometry":{"type":"Point","coordinates":[-121.933300,47.283300]},"type":"Feature","properties":{"hierarchy":["tgn:2408765","tgn:1000001","tgn:7012149","tgn:7018871","tgn:7007920","tgn:7029392"],"placetype":["aat:300008680"],"id":2408765,"name:xx":"Hyde Lake"}}
>>>>>>> 03f74aca74312dbeaf24d7e61306dd6a786dc3d0
