{
  "id": 1072886,
  "type": "Feature",
  "properties": {
    "tgn:hierarchy":[
        "tgn:1072886",
        "tgn:1000004",
        "tgn:7001796",
        "tgn:1000111",
        "tgn:7029392"
    ],
    "tgn:id":1072886,
    "tgn:name":"Xiaotao",
    "tgn:placetype":[
        "aat:300008347"
    ]
},
  "bbox": [],
  "geometry": {"coordinates":[117.1333,25.7333],"type":"Point"}
}