{
  "id": 2295504,
  "type": "Feature",
  "properties": {
    "tgn:hierarchy":[
        "tgn:2295504",
        "tgn:1000001",
        "tgn:7012149",
        "tgn:2001455",
        "tgn:7007566",
        "tgn:7029392"
    ],
    "tgn:id":2295504,
    "tgn:name":"Dripping Spring",
    "tgn:placetype":[
        "aat:300008697"
    ]
},
  "bbox": [],
  "geometry": {"coordinates":[-106.5167,33.35],"type":"Point"}
}