{
  "id": 2531225,
  "type": "Feature",
  "properties": {
    "tgn:hierarchy":[
        "tgn:2531225",
        "tgn:1002201",
        "tgn:1000001",
        "tgn:7012149",
        "tgn:7007517",
        "tgn:7029392"
    ],
    "tgn:id":2531225,
    "tgn:name":"Mulberry Meadow Brook",
    "tgn:placetype":[
        "aat:300008699"
    ]
},
  "bbox": [],
  "geometry": {"coordinates":[-71.1333,42.0167],"type":"Point"}
}