{
  "id": 2167475,
  "type": "Feature",
  "properties": {
    "tgn:hierarchy":[
        "tgn:2167475",
        "tgn:1000001",
        "tgn:7012149",
        "tgn:1002618",
        "tgn:7007251",
        "tgn:7029392"
    ],
    "tgn:id":2167475,
    "tgn:name":"Big Creek",
    "tgn:placetype":[
        "aat:300008706"
    ]
},
  "bbox": [],
  "geometry": {"coordinates":[-88.85,39.7333],"type":"Point"}
}