<<<<<<< HEAD
{
  "id": 7352324,
  "type": "Feature",
  "properties": {
    "tgn:hierarchy":[
        "tgn:7352324",
        "tgn:7005579",
        "tgn:1000001",
        "tgn:7005560",
        "tgn:7029392"
    ],
    "tgn:id":7352324,
    "tgn:name":"Brownsville",
    "tgn:placetype":[
        "aat:300008347"
    ]
},
  "bbox": [],
  "geometry": {"coordinates":[-102.35,22.0],"type":"Point"}
}
=======
{"geometry":{"type":"Point","coordinates":[-102.350000,22.000000]},"type":"Feature","properties":{"hierarchy":["tgn:7352324","tgn:7005579","tgn:1000001","tgn:7005560","tgn:7029392"],"placetype":["aat:300008347"],"id":7352324,"name:xx":"Brownsville"}}
>>>>>>> 03f74aca74312dbeaf24d7e61306dd6a786dc3d0
