{
  "id": 7070348,
  "type": "Feature",
  "properties": {
    "tgn:hierarchy":[
        "tgn:7070348",
        "tgn:7003669",
        "tgn:1000003",
        "tgn:7000084",
        "tgn:7029392"
    ],
    "tgn:id":7070348,
    "tgn:name":"Stein-Bach",
    "tgn:placetype":[
        "aat:300008699"
    ]
},
  "bbox": [],
  "geometry": {"coordinates":[11.316667,47.783333],"type":"Point"}
}