{
  "id": 1099840,
  "type": "Feature",
  "properties": {
    "tgn:hierarchy":[
        "tgn:1099840",
        "tgn:1000001",
        "tgn:1001937",
        "tgn:7005560",
        "tgn:7029392"
    ],
    "tgn:id":1099840,
    "tgn:name":"Monos",
    "tgn:placetype":[
        "aat:300008347",
        "aat:300387007",
        "aat:300167671"
    ]
},
  "bbox": [],
  "geometry": {"coordinates":[-89.033333,18.45],"type":"Point"}
}