{
  "id": 2733654,
  "type": "Feature",
  "properties": {
    "tgn:hierarchy":[
        "tgn:2733654",
        "tgn:1000001",
        "tgn:7012149",
        "tgn:2000476",
        "tgn:7007250",
        "tgn:7029392"
    ],
    "tgn:id":2733654,
    "tgn:name":"Turnbull Creek",
    "tgn:placetype":[
        "aat:300008706"
    ]
},
  "bbox": [],
  "geometry": {"coordinates":[-116.1333,45.5333],"type":"Point"}
}