{
  "id": 7122009,
  "type": "Feature",
  "properties": {
    "tgn:hierarchy":[
        "tgn:7122009",
        "tgn:1000003",
        "tgn:7003677",
        "tgn:7000084",
        "tgn:7029392"
    ],
    "tgn:id":7122009,
    "tgn:name":"Nergena",
    "tgn:placetype":[
        "aat:300387200"
    ]
},
  "bbox": [],
  "geometry": {"coordinates":[6.066667,51.716667],"type":"Point"}
}