{
  "id": 2489324,
  "type": "Feature",
  "properties": {
    "tgn:hierarchy":[
        "tgn:2489324",
        "tgn:1002648",
        "tgn:1000001",
        "tgn:1008191",
        "tgn:7012149",
        "tgn:7007249",
        "tgn:7029392"
    ],
    "tgn:id":2489324,
    "tgn:name":"Malae Gulch",
    "tgn:placetype":[
        "aat:300008761"
    ]
},
  "bbox": [],
  "geometry": {"coordinates":[-156.85,21.0833],"type":"Point"}
}