{
  "id": 2675660,
  "type": "Feature",
  "properties": {
    "tgn:hierarchy":[
        "tgn:2675660",
        "tgn:1000001",
        "tgn:2002105",
        "tgn:7012149",
        "tgn:7007827",
        "tgn:7029392"
    ],
    "tgn:id":2675660,
    "tgn:name":"Sols Canyon",
    "tgn:placetype":[
        "aat:300008761"
    ]
},
  "bbox": [],
  "geometry": {"coordinates":[-109.8667,40.9167],"type":"Point"}
}