{
  "id": 2441281,
  "type": "Feature",
  "properties": {
    "tgn:hierarchy":[
        "tgn:2441281",
        "tgn:1000001",
        "tgn:2001411",
        "tgn:7012149",
        "tgn:7007526",
        "tgn:7029392"
    ],
    "tgn:id":2441281,
    "tgn:name":"Knowlton Mine",
    "tgn:placetype":[
        "aat:300000390"
    ]
},
  "bbox": [],
  "geometry": {"coordinates":[-114.0667,40.2333],"type":"Point"}
}