{
  "id": 2632606,
  "type": "Feature",
  "properties": {
    "tgn:hierarchy":[
        "tgn:2632606",
        "tgn:1000001",
        "tgn:7012149",
        "tgn:2002299",
        "tgn:7013961",
        "tgn:7029392"
    ],
    "tgn:id":2632606,
    "tgn:name":"Rubens Branch",
    "tgn:placetype":[
        "aat:300008699"
    ]
},
  "bbox": [],
  "geometry": {"coordinates":[-82.3667,38.2833],"type":"Point"}
}