{
  "id": 7196189,
  "type": "Feature",
  "properties": {
    "tgn:hierarchy":[
        "tgn:7196189",
        "tgn:1000003",
        "tgn:7003682",
        "tgn:7000084",
        "tgn:7029392"
    ],
    "tgn:id":7196189,
    "tgn:name":"Daxelberg",
    "tgn:placetype":[
        "aat:300008777"
    ]
},
  "bbox": [],
  "geometry": {"coordinates":[6.666667,50.116667],"type":"Point"}
}