{
  "id": 2662482,
  "type": "Feature",
  "properties": {
    "tgn:hierarchy":[
        "tgn:2662482",
        "tgn:1000001",
        "tgn:7012149",
        "tgn:2001299",
        "tgn:7007524",
        "tgn:7029392"
    ],
    "tgn:id":2662482,
    "tgn:name":"Sig Spring",
    "tgn:placetype":[
        "aat:300008697"
    ]
},
  "bbox": [],
  "geometry": {"coordinates":[-105.7167,46.8667],"type":"Point"}
}