{
  "id": 2724226,
  "type": "Feature",
  "properties": {
    "tgn:hierarchy":[
        "tgn:2724226",
        "tgn:1000001",
        "tgn:7012149",
        "tgn:2000214",
        "tgn:7007158",
        "tgn:7029392"
    ],
    "tgn:id":2724226,
    "tgn:name":"Tom Creek",
    "tgn:placetype":[
        "aat:300008706"
    ]
},
  "bbox": [],
  "geometry": {"coordinates":[-108.3667,39.65],"type":"Point"}
}