{
  "id": 2611127,
  "type": "Feature",
  "properties": {
    "tgn:hierarchy":[
        "tgn:2611127",
        "tgn:1000001",
        "tgn:7006451",
        "tgn:7012149",
        "tgn:2000104",
        "tgn:7029392"
    ],
    "tgn:id":2611127,
    "tgn:name":"Red Hills",
    "tgn:placetype":[
        "aat:300008798"
    ]
},
  "bbox": [],
  "geometry": {"coordinates":[-113.3833,33.6667],"type":"Point"}
}