{
  "id": 2728985,
  "type": "Feature",
  "properties": {
    "tgn:hierarchy":[
        "tgn:2728985",
        "tgn:1000001",
        "tgn:7012149",
        "tgn:2001711",
        "tgn:7007708",
        "tgn:7029392"
    ],
    "tgn:id":2728985,
    "tgn:name":"Trickle Creek",
    "tgn:placetype":[
        "aat:300008706"
    ]
},
  "bbox": [],
  "geometry": {"coordinates":[-122.9167,42.2167],"type":"Point"}
}