{
  "id": 7136971,
  "type": "Feature",
  "properties": {
    "tgn:hierarchy":[
        "tgn:7136971",
        "tgn:7003692",
        "tgn:1000003",
        "tgn:7000084",
        "tgn:7029392"
    ],
    "tgn:id":7136971,
    "tgn:name":"La\u00dfbach",
    "tgn:placetype":[
        "aat:300008347"
    ]
},
  "bbox": [],
  "geometry": {"coordinates":[9.816667,49.266667],"type":"Point"}
}