{
  "id": 7367057,
  "type": "Feature",
  "properties": {
    "tgn:hierarchy":[
        "tgn:7367057",
        "tgn:1000001",
        "tgn:7005597",
        "tgn:7005560",
        "tgn:7029392"
    ],
    "tgn:id":7367057,
    "tgn:name":"El Pich\u00f3n",
    "tgn:placetype":[
        "aat:300008347"
    ]
},
  "bbox": [],
  "geometry": {"coordinates":[-97.983333,22.666667],"type":"Point"}
}