{
  "id": 2068373,
  "type": "Feature",
  "properties": {
    "tgn:hierarchy":[
        "tgn:2068373",
        "tgn:1000001",
        "tgn:7012149",
        "tgn:1003040",
        "tgn:7007568",
        "tgn:7029392"
    ],
    "tgn:id":2068373,
    "tgn:name":"Castile",
    "tgn:placetype":[
        "aat:300008347"
    ]
},
  "bbox": [],
  "geometry": {"coordinates":[-78.05,42.6167],"type":"Point"}
}