{
  "id": 7030662,
  "type": "Feature",
  "properties": {
    "tgn:hierarchy":[
        "tgn:7030662",
        "tgn:7002445",
        "tgn:1000003",
        "tgn:7008166",
        "tgn:7008591",
        "tgn:7029392"
    ],
    "tgn:id":7030662,
    "tgn:name":"West Marton",
    "tgn:name:ang":"Martun",
    "tgn:placetype":[
        "aat:300008347",
        "aat:300008372"
    ]
},
  "bbox": [],
  "geometry": {"coordinates":[-2.166667,53.95],"type":"Point"}
}