{
  "id": 1138716,
  "type": "Feature",
  "properties": {
    "tgn:hierarchy":[
        "tgn:1138716",
        "tgn:1000003",
        "tgn:7015085",
        "tgn:7006670",
        "tgn:7029392"
    ],
    "tgn:id":1138716,
    "tgn:name":"Ribnica",
    "tgn:placetype":[
        "aat:300008347",
        "aat:300008375"
    ]
},
  "bbox": [],
  "geometry": {"coordinates":[15.2667,46.5333],"type":"Point"}
}