{
  "id": 7228497,
  "type": "Feature",
  "properties": {
    "tgn:hierarchy":[
        "tgn:7228497",
        "tgn:7011170",
        "tgn:7002715",
        "tgn:1000003",
        "tgn:1000074",
        "tgn:7029392"
    ],
    "tgn:id":7228497,
    "tgn:name":"Glif\u00e1dha",
    "tgn:placetype":[
        "aat:300008347"
    ]
},
  "bbox": [],
  "geometry": {"coordinates":[25.233333,40.983333],"type":"Point"}
}