{
  "id": 2720050,
  "type": "Feature",
  "properties": {
    "tgn:hierarchy":[
        "tgn:2720050",
        "tgn:1000001",
        "tgn:7016172",
        "tgn:7012149",
        "tgn:2000160",
        "tgn:7029392"
    ],
    "tgn:id":2720050,
    "tgn:name":"Threemile Creek",
    "tgn:placetype":[
        "aat:300008706"
    ]
},
  "bbox": [],
  "geometry": {"coordinates":[-91.0167,35.6333],"type":"Point"}
}