<<<<<<< HEAD
{
  "id": 7243321,
  "type": "Feature",
  "properties": {
    "tgn:hierarchy":[
        "tgn:7243321",
        "tgn:7007877",
        "tgn:1000003",
        "tgn:1000063",
        "tgn:4012014",
        "tgn:7029392"
    ],
    "tgn:id":7243321,
    "tgn:name":"Les Neuf Maisons",
    "tgn:placetype":[
        "aat:300008347"
    ]
},
  "bbox": [],
  "geometry": {"coordinates":[4.366667,50.05],"type":"Point"}
}
=======
{"geometry":{"type":"Point","coordinates":[4.366667,50.050000]},"type":"Feature","properties":{"hierarchy":["tgn:7243321","tgn:7007877","tgn:1000003","tgn:1000063","tgn:4012014","tgn:7029392"],"placetype":["aat:300008347"],"id":7243321,"name:xx":"Les Neuf Maisons"}}
>>>>>>> 03f74aca74312dbeaf24d7e61306dd6a786dc3d0
