<<<<<<< HEAD
{
  "id": 7364205,
  "type": "Feature",
  "properties": {
    "tgn:hierarchy":[
        "tgn:7364205",
        "tgn:1000001",
        "tgn:7005597",
        "tgn:7005560",
        "tgn:7029392"
    ],
    "tgn:id":7364205,
    "tgn:name":"El Cipr\u00e9s",
    "tgn:placetype":[
        "aat:300008347"
    ]
},
  "bbox": [],
  "geometry": {"coordinates":[-98.75,26.283333],"type":"Point"}
}
=======
{"geometry":{"type":"Point","coordinates":[-98.750000,26.283333]},"type":"Feature","properties":{"hierarchy":["tgn:7364205","tgn:1000001","tgn:7005597","tgn:7005560","tgn:7029392"],"placetype":["aat:300008347"],"id":7364205,"name:xx":"El Cipr\u00e9s"}}
>>>>>>> 03f74aca74312dbeaf24d7e61306dd6a786dc3d0
