{
  "id": 7401058,
  "type": "Feature",
  "properties": {
    "tgn:hierarchy":[
        "tgn:7401058",
        "tgn:1000001",
        "tgn:7005599",
        "tgn:7005560",
        "tgn:7029392"
    ],
    "tgn:id":7401058,
    "tgn:name":"Paso del Perro",
    "tgn:placetype":[
        "aat:300008347"
    ]
},
  "bbox": [],
  "geometry": {"coordinates":[-97.941667,20.85],"type":"Point"}
}