{
  "id": 2664496,
  "type": "Feature",
  "properties": {
    "tgn:hierarchy":[
        "tgn:2664496",
        "tgn:1000001",
        "tgn:7012149",
        "tgn:7007922",
        "tgn:7029392"
    ],
    "tgn:id":2664496,
    "tgn:name":"Simes Creek",
    "tgn:placetype":[
        "aat:300008706"
    ]
},
  "bbox": [],
  "geometry": {"coordinates":[-90.8833,44.7667],"type":"Point"}
}