{
  "id": 2456919,
  "type": "Feature",
  "properties": {
    "tgn:hierarchy":[
        "tgn:2456919",
        "tgn:1000001",
        "tgn:7012149",
        "tgn:7007254",
        "tgn:7029392"
    ],
    "tgn:id":2456919,
    "tgn:name":"Little Kaw Creek",
    "tgn:placetype":[
        "aat:300008706"
    ]
},
  "bbox": [],
  "geometry": {"coordinates":[-94.95,39.0833],"type":"Point"}
}