{
  "id": 2033138,
  "type": "Feature",
  "properties": {
    "tgn:hierarchy":[
        "tgn:2033138",
        "tgn:1000001",
        "tgn:7013619",
        "tgn:7012149",
        "tgn:7007252",
        "tgn:7029392"
    ],
    "tgn:id":2033138,
    "tgn:name":"Norton",
    "tgn:placetype":[
        "aat:300008347",
        "aat:300387210"
    ]
},
  "bbox": [],
  "geometry": {"coordinates":[-86.6667,38.4833],"type":"Point"}
}