{
  "id": 2163407,
  "type": "Feature",
  "properties": {
    "tgn:hierarchy":[
        "tgn:2163407",
        "tgn:1000001",
        "tgn:7012149",
        "tgn:2002266",
        "tgn:7013961",
        "tgn:7029392"
    ],
    "tgn:id":2163407,
    "tgn:name":"Bens Hill",
    "tgn:placetype":[
        "aat:300008798"
    ]
},
  "bbox": [],
  "geometry": {"coordinates":[-78.7167,38.9667],"type":"Point"}
}