{
  "id": 7330944,
  "type": "Feature",
  "properties": {
    "tgn:hierarchy":[
        "tgn:7330944",
        "tgn:7010420",
        "tgn:1000003",
        "tgn:7002795",
        "tgn:1000095",
        "tgn:7029392"
    ],
    "tgn:id":7330944,
    "tgn:name":"Guatel Primero, Arroyo",
    "tgn:placetype":[
        "aat:300008699"
    ]
},
  "bbox": [],
  "geometry": {"coordinates":[-4.05,40.633333],"type":"Point"}
}