{
  "id": 2730802,
  "type": "Feature",
  "properties": {
    "tgn:hierarchy":[
        "tgn:2730802",
        "tgn:1000001",
        "tgn:7012149",
        "tgn:1002899",
        "tgn:7007920",
        "tgn:7029392"
    ],
    "tgn:id":2730802,
    "tgn:name":"Tualco Valley",
    "tgn:placetype":[
        "aat:300386845"
    ]
},
  "bbox": [],
  "geometry": {"coordinates":[-121.9667,47.8167],"type":"Point"}
}