{
  "id": 2356535,
  "type": "Feature",
  "properties": {
    "tgn:hierarchy":[
        "tgn:2356535",
        "tgn:1000001",
        "tgn:7012149",
        "tgn:2001717",
        "tgn:7007708",
        "tgn:7029392"
    ],
    "tgn:id":2356535,
    "tgn:name":"Gordon Lakes",
    "tgn:placetype":[
        "aat:300008680"
    ]
},
  "bbox": [],
  "geometry": {"coordinates":[-122.25,44.35],"type":"Point"}
}