<<<<<<< HEAD
{
  "id": 2406778,
  "type": "Feature",
  "properties": {
    "tgn:hierarchy":[
        "tgn:2406778",
        "tgn:1000001",
        "tgn:7012149",
        "tgn:2002384",
        "tgn:7007923",
        "tgn:7029392"
    ],
    "tgn:id":2406778,
    "tgn:name":"Hunt, Mount",
    "tgn:placetype":[
        "aat:300008798"
    ]
},
  "bbox": [],
  "geometry": {"coordinates":[-110.85,43.6167],"type":"Point"}
}
=======
{"geometry":{"type":"Point","coordinates":[-110.850000,43.616700]},"type":"Feature","properties":{"hierarchy":["tgn:2406778","tgn:1000001","tgn:7012149","tgn:2002384","tgn:7007923","tgn:7029392"],"placetype":["aat:300008798"],"id":2406778,"name:xx":"Hunt, Mount"}}
>>>>>>> 03f74aca74312dbeaf24d7e61306dd6a786dc3d0
