<<<<<<< HEAD
{
  "id": 7248515,
  "type": "Feature",
  "properties": {
    "tgn:hierarchy":[
        "tgn:7248515",
        "tgn:7003457",
        "tgn:1000003",
        "tgn:1000063",
        "tgn:7018236",
        "tgn:7029392"
    ],
    "tgn:id":7248515,
    "tgn:name":"Billegem",
    "tgn:placetype":[
        "aat:300008347"
    ]
},
  "bbox": [],
  "geometry": {"coordinates":[3.958209,50.985602],"type":"Point"}
}
=======
{"geometry":{"type":"Point","coordinates":[3.958209,50.985602]},"type":"Feature","properties":{"hierarchy":["tgn:7248515","tgn:7003457","tgn:1000003","tgn:1000063","tgn:7018236","tgn:7029392"],"placetype":["aat:300008347"],"id":7248515,"name:xx":"Billegem"}}
>>>>>>> 03f74aca74312dbeaf24d7e61306dd6a786dc3d0
