<<<<<<< HEAD
{
  "id": 2335568,
  "type": "Feature",
  "properties": {
    "tgn:hierarchy":[
        "tgn:2335568",
        "tgn:1000001",
        "tgn:7006451",
        "tgn:7012149",
        "tgn:2000103",
        "tgn:7029392"
    ],
    "tgn:id":2335568,
    "tgn:name":"Fort Verde Estates",
    "tgn:placetype":[
        "aat:300008347"
    ]
},
  "bbox": [],
  "geometry": {"coordinates":[-111.85,34.5333],"type":"Point"}
}
=======
{"geometry":{"type":"Point","coordinates":[-111.850000,34.533300]},"type":"Feature","properties":{"hierarchy":["tgn:2335568","tgn:1000001","tgn:7006451","tgn:7012149","tgn:2000103","tgn:7029392"],"placetype":["aat:300008347"],"id":2335568,"name:xx":"Fort Verde Estates"}}
>>>>>>> 03f74aca74312dbeaf24d7e61306dd6a786dc3d0
