{
  "id": 7381477,
  "type": "Feature",
  "properties": {
    "tgn:hierarchy":[
        "tgn:7381477",
        "tgn:1000001",
        "tgn:7005594",
        "tgn:7005560",
        "tgn:7029392"
    ],
    "tgn:id":7381477,
    "tgn:name":"Malpa\u00eds, Cerro",
    "tgn:placetype":[
        "aat:300008795"
    ]
},
  "bbox": [],
  "geometry": {"coordinates":[-101.916667,22.733333],"type":"Point"}
}