<<<<<<< HEAD
{
  "id": 7359182,
  "type": "Feature",
  "properties": {
    "tgn:hierarchy":[
        "tgn:7359182",
        "tgn:7005581",
        "tgn:1000001",
        "tgn:7005560",
        "tgn:7029392"
    ],
    "tgn:id":7359182,
    "tgn:name":"Rancho de la Cruz",
    "tgn:placetype":[
        "aat:300000241"
    ]
},
  "bbox": [],
  "geometry": {"coordinates":[-108.1,31.033333],"type":"Point"}
}
=======
{"geometry":{"type":"Point","coordinates":[-108.100000,31.033333]},"type":"Feature","properties":{"hierarchy":["tgn:7359182","tgn:7005581","tgn:1000001","tgn:7005560","tgn:7029392"],"placetype":["aat:300000241"],"id":7359182,"name:xx":"Rancho de la Cruz"}}
>>>>>>> 03f74aca74312dbeaf24d7e61306dd6a786dc3d0
