{
  "id": 2706390,
  "type": "Feature",
  "properties": {
    "tgn:hierarchy":[
        "tgn:2706390",
        "tgn:1000001",
        "tgn:1002271",
        "tgn:7012149",
        "tgn:7007920",
        "tgn:7029392"
    ],
    "tgn:id":2706390,
    "tgn:name":"Swan Bay",
    "tgn:placetype":[
        "aat:300132316"
    ]
},
  "bbox": [],
  "geometry": {"coordinates":[-124.5833,48.1167],"type":"Point"}
}