{
  "id": 1078554,
  "type": "Feature",
  "properties": {
    "tgn:hierarchy":[
        "tgn:1078554",
        "tgn:1000004",
        "tgn:1001548",
        "tgn:1000116",
        "tgn:7029392"
    ],
    "tgn:id":1078554,
    "tgn:name":"Siboa",
    "tgn:placetype":[
        "aat:300008347"
    ]
},
  "bbox": [],
  "geometry": {"coordinates":[120.0333,0.5167],"type":"Point"}
}