{
  "id": 2203134,
  "type": "Feature",
  "properties": {
    "tgn:hierarchy":[
        "tgn:2203134",
        "tgn:1000001",
        "tgn:7012149",
        "tgn:2000804",
        "tgn:7007255",
        "tgn:7029392"
    ],
    "tgn:id":2203134,
    "tgn:name":"Buckhorn Branch",
    "tgn:placetype":[
        "aat:300008699"
    ]
},
  "bbox": [],
  "geometry": {"coordinates":[-82.9167,37.8333],"type":"Point"}
}