{
  "id": 7322274,
  "type": "Feature",
  "properties": {
    "tgn:hierarchy":[
        "tgn:7322274",
        "tgn:1001702",
        "tgn:1000049",
        "tgn:1000002",
        "tgn:7029392"
    ],
    "tgn:id":7322274,
    "tgn:name":"Barros Luco, Fiordo",
    "tgn:placetype":[
        "aat:300132316"
    ]
},
  "bbox": [],
  "geometry": {"coordinates":[-75.288611,-50.1575],"type":"Point"}
}