{
  "id": 7379899,
  "type": "Feature",
  "properties": {
    "tgn:hierarchy":[
        "tgn:7379899",
        "tgn:1000001",
        "tgn:7005589",
        "tgn:7005560",
        "tgn:7029392"
    ],
    "tgn:id":7379899,
    "tgn:name":"Los Vilareales",
    "tgn:placetype":[
        "aat:300008347"
    ]
},
  "bbox": [],
  "geometry": {"coordinates":[-99.75,25.666667],"type":"Point"}
}