{
  "id": 2183583,
  "type": "Feature",
  "properties": {
    "tgn:hierarchy":[
        "tgn:2183583",
        "tgn:1000001",
        "tgn:7012149",
        "tgn:2000928",
        "tgn:7007515",
        "tgn:7029392"
    ],
    "tgn:id":2183583,
    "tgn:name":"Bluffer Pond",
    "tgn:placetype":[
        "aat:300008680"
    ]
},
  "bbox": [],
  "geometry": {"coordinates":[-69.0833,46.3667],"type":"Point"}
}