{
  "id": 2468786,
  "type": "Feature",
  "properties": {
    "tgn:hierarchy":[
        "tgn:2468786",
        "tgn:1000001",
        "tgn:7012149",
        "tgn:2001309",
        "tgn:7007524",
        "tgn:7029392"
    ],
    "tgn:id":2468786,
    "tgn:name":"Long Ridge",
    "tgn:placetype":[
        "aat:300266640"
    ]
},
  "bbox": [],
  "geometry": {"coordinates":[-112.5833,47.7333],"type":"Point"}
}