{
  "id": 7353825,
  "type": "Feature",
  "properties": {
    "tgn:hierarchy":[
        "tgn:7353825",
        "tgn:1000001",
        "tgn:7005591",
        "tgn:7005560",
        "tgn:7029392"
    ],
    "tgn:id":7353825,
    "tgn:name":"Chocanuc",
    "tgn:placetype":[
        "aat:300008347"
    ]
},
  "bbox": [],
  "geometry": {"coordinates":[-97.633333,16.383333],"type":"Point"}
}