{
  "id": 7222868,
  "type": "Feature",
  "properties": {
    "tgn:hierarchy":[
        "tgn:7222868",
        "tgn:4003773",
        "tgn:7001395",
        "tgn:1000003",
        "tgn:1000074",
        "tgn:7029392"
    ],
    "tgn:id":7222868,
    "tgn:name":"Mesin\u00f3 Khor\u00edon",
    "tgn:placetype":[
        "aat:300008347"
    ]
},
  "bbox": [],
  "geometry": {"coordinates":[21.983333,38.416667],"type":"Point"}
}