{
  "id": 2263831,
  "type": "Feature",
  "properties": {
    "tgn:hierarchy":[
        "tgn:2263831",
        "tgn:1000001",
        "tgn:7012149",
        "tgn:7007827",
        "tgn:7029392"
    ],
    "tgn:id":2263831,
    "tgn:name":"Coyote Creek",
    "tgn:placetype":[
        "aat:300008706"
    ]
},
  "bbox": [],
  "geometry": {"coordinates":[-112.45,38.1333],"type":"Point"}
}