{
  "id": 7351622,
  "type": "Feature",
  "properties": {
    "tgn:hierarchy":[
        "tgn:7351622",
        "tgn:7005581",
        "tgn:1000001",
        "tgn:7005560",
        "tgn:7029392"
    ],
    "tgn:id":7351622,
    "tgn:name":"Boquilla, Arroyo",
    "tgn:placetype":[
        "aat:300008699"
    ]
},
  "bbox": [],
  "geometry": {"coordinates":[-104.816667,29.35],"type":"Point"}
}