{
  "id": 7151216,
  "type": "Feature",
  "properties": {
    "tgn:hierarchy":[
        "tgn:7151216",
        "tgn:1000003",
        "tgn:7003685",
        "tgn:7000084",
        "tgn:7029392"
    ],
    "tgn:id":7151216,
    "tgn:name":"Kaisa",
    "tgn:placetype":[
        "aat:300008347"
    ]
},
  "bbox": [],
  "geometry": {"coordinates":[13.083333,51.433333],"type":"Point"}
}