{
  "id": 7220620,
  "type": "Feature",
  "properties": {
    "tgn:hierarchy":[
        "tgn:7220620",
        "tgn:4003773",
        "tgn:7001395",
        "tgn:1000003",
        "tgn:1000074",
        "tgn:7029392"
    ],
    "tgn:id":7220620,
    "tgn:name":"Sel\u00edsta",
    "tgn:placetype":[
        "aat:300008347"
    ]
},
  "bbox": [],
  "geometry": {"coordinates":[21.61,39.0625],"type":"Point"}
}