{
  "id": 2436108,
  "type": "Feature",
  "properties": {
    "tgn:hierarchy":[
        "tgn:2436108",
        "tgn:1000001",
        "tgn:1002218",
        "tgn:7012149",
        "tgn:7007157",
        "tgn:7029392"
    ],
    "tgn:id":2436108,
    "tgn:name":"Keyser Creek",
    "tgn:placetype":[
        "aat:300008706"
    ]
},
  "bbox": [],
  "geometry": {"coordinates":[-121.4667,39.95],"type":"Point"}
}