<<<<<<< HEAD
{
  "id": 2259146,
  "type": "Feature",
  "properties": {
    "tgn:hierarchy":[
        "tgn:2259146",
        "tgn:1000001",
        "tgn:7012149",
        "tgn:7007158",
        "tgn:2000246",
        "tgn:7029392"
    ],
    "tgn:id":2259146,
    "tgn:name":"Cottonwood Gulch",
    "tgn:placetype":[
        "aat:300008761"
    ]
},
  "bbox": [],
  "geometry": {"coordinates":[-106.8333,38.3667],"type":"Point"}
}
=======
{"geometry":{"type":"Point","coordinates":[-106.833300,38.366700]},"type":"Feature","properties":{"hierarchy":["tgn:2259146","tgn:1000001","tgn:7012149","tgn:7007158","tgn:2000246","tgn:7029392"],"placetype":["aat:300008761"],"id":2259146,"name:xx":"Cottonwood Gulch"}}
>>>>>>> 03f74aca74312dbeaf24d7e61306dd6a786dc3d0
