{
  "id": 2424823,
  "type": "Feature",
  "properties": {
    "tgn:hierarchy":[
        "tgn:2424823",
        "tgn:1000001",
        "tgn:7012149",
        "tgn:7007826",
        "tgn:7029392"
    ],
    "tgn:id":2424823,
    "tgn:name":"Johnson Fork",
    "tgn:placetype":[
        "aat:300008699"
    ]
},
  "bbox": [],
  "geometry": {"coordinates":[-99.6833,30.2167],"type":"Point"}
}