{
  "id": 7197814,
  "type": "Feature",
  "properties": {
    "tgn:hierarchy":[
        "tgn:7197814",
        "tgn:7003692",
        "tgn:1000003",
        "tgn:7000084",
        "tgn:7029392"
    ],
    "tgn:id":7197814,
    "tgn:name":"Eck",
    "tgn:placetype":[
        "aat:300000206"
    ]
},
  "bbox": [],
  "geometry": {"coordinates":[9.966667,47.733333],"type":"Point"}
}