{
  "id": 7393680,
  "type": "Feature",
  "properties": {
    "tgn:hierarchy":[
        "tgn:7393680",
        "tgn:7005579",
        "tgn:1000001",
        "tgn:7005560",
        "tgn:7029392"
    ],
    "tgn:id":7393680,
    "tgn:name":"San Francisco, R\u00edo de",
    "tgn:placetype":[
        "aat:300008699"
    ]
},
  "bbox": [],
  "geometry": {"coordinates":[-102.333333,21.85],"type":"Point"}
}