{
  "id": 2210040,
  "type": "Feature",
  "properties": {
    "tgn:hierarchy":[
        "tgn:2210040",
        "tgn:1000001",
        "tgn:7012149",
        "tgn:2001304",
        "tgn:7007524",
        "tgn:7029392"
    ],
    "tgn:id":2210040,
    "tgn:name":"Burton Creek",
    "tgn:placetype":[
        "aat:300008706"
    ]
},
  "bbox": [],
  "geometry": {"coordinates":[-115.7333,47.85],"type":"Point"}
}