{
  "id": 2328513,
  "type": "Feature",
  "properties": {
    "tgn:hierarchy":[
        "tgn:2328513",
        "tgn:1000001",
        "tgn:7006451",
        "tgn:2000093",
        "tgn:7012149",
        "tgn:7029392"
    ],
    "tgn:id":2328513,
    "tgn:name":"Fisher Mesa",
    "tgn:placetype":[
        "aat:300008798"
    ]
},
  "bbox": [],
  "geometry": {"coordinates":[-111.3833,34.1167],"type":"Point"}
}