{
  "id": 7040012,
  "type": "Feature",
  "properties": {
    "tgn:hierarchy":[
        "tgn:7040012",
        "tgn:1003489",
        "tgn:7004610",
        "tgn:1000003",
        "tgn:1000080",
        "tgn:7029392"
    ],
    "tgn:id":7040012,
    "tgn:name":"Sciosci",
    "tgn:placetype":[
        "aat:300008347"
    ]
},
  "bbox": [],
  "geometry": {"coordinates":[15.683333,40.733333],"type":"Point"}
}