{
  "id": 7116538,
  "type": "Feature",
  "properties": {
    "tgn:hierarchy":[
        "tgn:7116538",
        "tgn:7003669",
        "tgn:1000003",
        "tgn:7000084",
        "tgn:7029392"
    ],
    "tgn:id":7116538,
    "tgn:name":"Ober-Wald",
    "tgn:placetype":[
        "aat:300008863"
    ]
},
  "bbox": [],
  "geometry": {"coordinates":[10.766667,47.916667],"type":"Point"}
}