{
  "id": 7496876,
  "type": "Feature",
  "properties": {
    "tgn:hierarchy":[
        "tgn:7496876",
        "tgn:1000004",
        "tgn:7001009",
        "tgn:1000141",
        "tgn:7029392"
    ],
    "tgn:id":7496876,
    "tgn:name":"Shekou Guoxiao",
    "tgn:placetype":[
        "aat:300006495"
    ]
},
  "bbox": [],
  "geometry": {"coordinates":[120.684746,24.245389],"type":"Point"}
}