{
  "id": 1040652,
  "type": "Feature",
  "properties": {
    "tgn:hierarchy":[
        "tgn:1040652",
        "tgn:1000003",
        "tgn:7003677",
        "tgn:7000084",
        "tgn:7029392"
    ],
    "tgn:id":1040652,
    "tgn:name":"Ostb\u00fcren",
    "tgn:placetype":[
        "aat:300008347"
    ]
},
  "bbox": [],
  "geometry": {"coordinates":[7.766667,51.516667],"type":"Point"}
}