{
  "id": 1125459,
  "type": "Feature",
  "properties": {
    "tgn:hierarchy":[
        "tgn:1125459",
        "tgn:7006450",
        "tgn:1000001",
        "tgn:7012149",
        "tgn:2000087",
        "tgn:7029392"
    ],
    "tgn:id":1125459,
    "tgn:name":"Kashunuk",
    "tgn:placetype":[
        "aat:300008707"
    ]
},
  "bbox": [],
  "geometry": {"coordinates":[-162.9167,61.8667],"type":"Point"}
}