{
  "id": 7544422,
  "type": "Feature",
  "properties": {
    "tgn:hierarchy":[
        "tgn:7544422",
        "tgn:7001242",
        "tgn:1001075",
        "tgn:7016833",
        "tgn:7029392"
    ],
    "tgn:id":7544422,
    "tgn:name:en":"Tir'at Jal\u0101l",
    "tgn:placetype":[
        "aat:300006075"
    ]
},
  "bbox": [],
  "geometry": {"coordinates":[30.143452,30.910855],"type":"Point"}
}