{
  "id": 2438613,
  "type": "Feature",
  "properties": {
    "tgn:hierarchy":[
        "tgn:2438613",
        "tgn:1000001",
        "tgn:7012149",
        "tgn:2001918",
        "tgn:7007825",
        "tgn:7029392"
    ],
    "tgn:id":2438613,
    "tgn:name":"Kingsley Hills",
    "tgn:placetype":[
        "aat:300008347"
    ]
},
  "bbox": [],
  "geometry": {"coordinates":[-82.4833,36.5667],"type":"Point"}
}