{
  "id": 2125115,
  "type": "Feature",
  "properties": {
    "tgn:hierarchy":[
        "tgn:2125115",
        "tgn:1000001",
        "tgn:1002174",
        "tgn:7012149",
        "tgn:7007826",
        "tgn:7029392"
    ],
    "tgn:id":2125115,
    "tgn:name":"Academy",
    "tgn:placetype":[
        "aat:300008347"
    ]
},
  "bbox": [],
  "geometry": {"coordinates":[-97.3333,30.9667],"type":"Point"}
}