{
  "id": 2323533,
  "type": "Feature",
  "properties": {
    "tgn:hierarchy":[
        "tgn:2323533",
        "tgn:1000001",
        "tgn:7012149",
        "tgn:2000928",
        "tgn:7007515",
        "tgn:7029392"
    ],
    "tgn:id":2323533,
    "tgn:name":"Farrar Brook",
    "tgn:placetype":[
        "aat:300008699"
    ]
},
  "bbox": [],
  "geometry": {"coordinates":[-69.2833,45.6833],"type":"Point"}
}