{
  "id": 7152024,
  "type": "Feature",
  "properties": {
    "tgn:hierarchy":[
        "tgn:7152024",
        "tgn:7003669",
        "tgn:1000003",
        "tgn:7000084",
        "tgn:7029392"
    ],
    "tgn:id":7152024,
    "tgn:name":"Kasten",
    "tgn:placetype":[
        "aat:300000206"
    ]
},
  "bbox": [],
  "geometry": {"coordinates":[12.25,48.116667],"type":"Point"}
}