<<<<<<< HEAD
{
  "id": 2338832,
  "type": "Feature",
  "properties": {
    "tgn:hierarchy":[
        "tgn:2338832",
        "tgn:1000001",
        "tgn:2001429",
        "tgn:7012149",
        "tgn:7007566",
        "tgn:7029392"
    ],
    "tgn:id":2338832,
    "tgn:name":"Frank Tank",
    "tgn:placetype":[
        "aat:300006191"
    ]
},
  "bbox": [],
  "geometry": {"coordinates":[-108.8833,33.9],"type":"Point"}
}
=======
{"geometry":{"type":"Point","coordinates":[-108.883300,33.900000]},"type":"Feature","properties":{"hierarchy":["tgn:2338832","tgn:1000001","tgn:2001429","tgn:7012149","tgn:7007566","tgn:7029392"],"placetype":["aat:300006191"],"id":2338832,"name:xx":"Frank Tank"}}
>>>>>>> 03f74aca74312dbeaf24d7e61306dd6a786dc3d0
