{
  "id": 7369221,
  "type": "Feature",
  "properties": {
    "tgn:hierarchy":[
        "tgn:7369221",
        "tgn:1000001",
        "tgn:7005597",
        "tgn:7005560",
        "tgn:7029392"
    ],
    "tgn:id":7369221,
    "tgn:name":"Guadalupe",
    "tgn:placetype":[
        "aat:300387033"
    ]
},
  "bbox": [],
  "geometry": {"coordinates":[-98.283333,23.433333],"type":"Point"}
}