<<<<<<< HEAD
{
  "id": 7369221,
  "type": "Feature",
  "properties": {
    "tgn:hierarchy":[
        "tgn:7369221",
        "tgn:1000001",
        "tgn:7005597",
        "tgn:7005560",
        "tgn:7029392"
    ],
    "tgn:id":7369221,
    "tgn:name":"Guadalupe",
    "tgn:placetype":[
        "aat:300387033"
    ]
},
  "bbox": [],
  "geometry": {"coordinates":[-98.283333,23.433333],"type":"Point"}
}
=======
{"geometry":{"type":"Point","coordinates":[-98.283333,23.433333]},"type":"Feature","properties":{"hierarchy":["tgn:7369221","tgn:1000001","tgn:7005597","tgn:7005560","tgn:7029392"],"placetype":["aat:300387033"],"id":7369221,"name:xx":"Guadalupe"}}
>>>>>>> 03f74aca74312dbeaf24d7e61306dd6a786dc3d0
