{
  "id": 7414778,
  "type": "Feature",
  "properties": {
    "tgn:hierarchy":[
        "tgn:7414778",
        "tgn:1000001",
        "tgn:7005591",
        "tgn:7005560",
        "tgn:7029392"
    ],
    "tgn:id":7414778,
    "tgn:name:es":"Estaci\u00f3n Charis",
    "tgn:placetype":[
        "aat:300007783"
    ]
},
  "bbox": [],
  "geometry": {"coordinates":[-94.914444,16.475],"type":"Point"}
}