{
  "id": 7077529,
  "type": "Feature",
  "properties": {
    "tgn:hierarchy":[
        "tgn:7077529",
        "tgn:1000003",
        "tgn:7003687",
        "tgn:7000084",
        "tgn:7029392"
    ],
    "tgn:id":7077529,
    "tgn:name":"B\u00edl\u00fd Hal\u0161trov",
    "tgn:placetype":[
        "aat:300008699"
    ]
},
  "bbox": [],
  "geometry": {"coordinates":[11.95,51.433333],"type":"Point"}
}