{
  "id": 2632905,
  "type": "Feature",
  "properties": {
    "tgn:hierarchy":[
        "tgn:2632905",
        "tgn:1000001",
        "tgn:7012149",
        "tgn:2000363",
        "tgn:7007248",
        "tgn:7029392"
    ],
    "tgn:id":2632905,
    "tgn:name":"Ruckers Lake",
    "tgn:placetype":[
        "aat:300006191"
    ]
},
  "bbox": [],
  "geometry": {"coordinates":[-84.7833,32.6833],"type":"Point"}
}