{
  "id": 7448579,
  "type": "Feature",
  "properties": {
    "tgn:hierarchy":[
        "tgn:7448579",
        "tgn:7002443",
        "tgn:1000003",
        "tgn:7018993",
        "tgn:7008591",
        "tgn:7029392"
    ],
    "tgn:id":7448579,
    "tgn:name:en":"Talbenny",
    "tgn:placetype":[
        "aat:300008347"
    ]
},
  "bbox": [],
  "geometry": {"coordinates":[-5.1325,51.764722],"type":"Point"}
}