{
  "id": 7577799,
  "type": "Feature",
  "properties": {
    "tgn:hierarchy":[
        "tgn:7577799",
        "tgn:1001828",
        "tgn:1000004",
        "tgn:7000198",
        "tgn:7029392"
    ],
    "tgn:id":7577799,
    "tgn:name:en":"Kulkulapalli",
    "tgn:placetype":[
        "aat:300008347"
    ]
},
  "bbox": [],
  "geometry": {"coordinates":[78.716667,16.916667],"type":"Point"}
}