{
  "id": 2168327,
  "type": "Feature",
  "properties": {
    "tgn:hierarchy":[
        "tgn:2168327",
        "tgn:1002157",
        "tgn:1000001",
        "tgn:7012149",
        "tgn:7007565",
        "tgn:7029392"
    ],
    "tgn:id":2168327,
    "tgn:name":"Big Goose Pond",
    "tgn:placetype":[
        "aat:300008680"
    ]
},
  "bbox": [],
  "geometry": {"coordinates":[-74.6667,39.5167],"type":"Point"}
}