{
  "id": 1076106,
  "type": "Feature",
  "properties": {
    "tgn:hierarchy":[
        "tgn:1076106",
        "tgn:1000004",
        "tgn:7000198",
        "tgn:1001977",
        "tgn:7029392"
    ],
    "tgn:id":1076106,
    "tgn:name:en":"Magra H\u0101t",
    "tgn:placetype":[
        "aat:300008347"
    ]
},
  "bbox": [],
  "geometry": {"coordinates":[88.368792,22.238432],"type":"Point"}
}