{
  "id": 1135002,
  "type": "Feature",
  "properties": {
    "tgn:hierarchy":[
        "tgn:1135002",
        "tgn:1000001",
        "tgn:7012149",
        "tgn:7007157",
        "tgn:1002566",
        "tgn:7029392"
    ],
    "tgn:id":1135002,
    "tgn:name":"Welch Creek",
    "tgn:placetype":[
        "aat:300008706"
    ]
},
  "bbox": [],
  "geometry": {"coordinates":[-123.0167,39.45],"type":"Point"}
}