{
  "id": 2176802,
  "type": "Feature",
  "properties": {
    "tgn:hierarchy":[
        "tgn:2176802",
        "tgn:1000001",
        "tgn:7012149",
        "tgn:7007157",
        "tgn:1002956",
        "tgn:7029392"
    ],
    "tgn:id":2176802,
    "tgn:name":"Black Mountain",
    "tgn:placetype":[
        "aat:300008798"
    ]
},
  "bbox": [],
  "geometry": {"coordinates":[-118.2333,35.85],"type":"Point"}
}