{
  "id": 7367518,
  "type": "Feature",
  "properties": {
    "tgn:hierarchy":[
        "tgn:7367518",
        "tgn:1001853",
        "tgn:1000001",
        "tgn:7005560",
        "tgn:7029392"
    ],
    "tgn:id":7367518,
    "tgn:name":"Rancho El Veinte",
    "tgn:placetype":[
        "aat:300000241"
    ]
},
  "bbox": [],
  "geometry": {"coordinates":[-102.866667,29.033333],"type":"Point"}
}