{
  "id": 2256596,
  "type": "Feature",
  "properties": {
    "tgn:hierarchy":[
        "tgn:2256596",
        "tgn:1000001",
        "tgn:7012149",
        "tgn:7007157",
        "tgn:1002869",
        "tgn:7029392"
    ],
    "tgn:id":2256596,
    "tgn:name":"Corcoran Lagoon",
    "tgn:placetype":[
        "aat:300008680"
    ]
},
  "bbox": [],
  "geometry": {"coordinates":[-121.9667,36.95],"type":"Point"}
}