{
  "id": 7539267,
  "type": "Feature",
  "properties": {
    "tgn:hierarchy":[
        "tgn:7539267",
        "tgn:7001242",
        "tgn:7016833",
        "tgn:1001080",
        "tgn:7029392"
    ],
    "tgn:id":7539267,
    "tgn:name:en":"Matr\u016bk, Birkat al",
    "tgn:placetype":[
        "aat:300008680"
    ]
},
  "bbox": [],
  "geometry": {"coordinates":[32.016692,30.534486],"type":"Point"}
}