{
  "id": 2337401,
  "type": "Feature",
  "properties": {
    "tgn:hierarchy":[
        "tgn:2337401",
        "tgn:1000001",
        "tgn:7012149",
        "tgn:1002874",
        "tgn:7007251",
        "tgn:7029392"
    ],
    "tgn:id":2337401,
    "tgn:name":"Fowler Branch",
    "tgn:placetype":[
        "aat:300008699"
    ]
},
  "bbox": [],
  "geometry": {"coordinates":[-90.65,40.2167],"type":"Point"}
}