{
  "id": 7321738,
  "type": "Feature",
  "properties": {
    "tgn:hierarchy":[
        "tgn:7321738",
        "tgn:1001630",
        "tgn:1000049",
        "tgn:1000002",
        "tgn:7029392"
    ],
    "tgn:id":7321738,
    "tgn:name":"Breitas, Aguada",
    "tgn:placetype":[
        "aat:300008697"
    ]
},
  "bbox": [],
  "geometry": {"coordinates":[-70.916667,-28.783333],"type":"Point"}
}