{
  "id": 2231417,
  "type": "Feature",
  "properties": {
    "tgn:hierarchy":[
        "tgn:2231417",
        "tgn:1000001",
        "tgn:2002368",
        "tgn:7012149",
        "tgn:7007923",
        "tgn:7029392"
    ],
    "tgn:id":2231417,
    "tgn:name":"Chalk Bluff",
    "tgn:placetype":[
        "aat:300008798"
    ]
},
  "bbox": [],
  "geometry": {"coordinates":[-106.5833,42.05],"type":"Point"}
}