<<<<<<< HEAD
{
  "id": 2767312,
  "type": "Feature",
  "properties": {
    "tgn:hierarchy":[
        "tgn:2767312",
        "tgn:1000001",
        "tgn:7012149",
        "tgn:2002168",
        "tgn:7007919",
        "tgn:7029392"
    ],
    "tgn:id":2767312,
    "tgn:name":"White Run",
    "tgn:placetype":[
        "aat:300008699"
    ]
},
  "bbox": [],
  "geometry": {"coordinates":[-79.5833,38.4167],"type":"Point"}
}
=======
{"geometry":{"type":"Point","coordinates":[-79.583300,38.416700]},"type":"Feature","properties":{"hierarchy":["tgn:2767312","tgn:1000001","tgn:7012149","tgn:2002168","tgn:7007919","tgn:7029392"],"placetype":["aat:300008699"],"id":2767312,"name:xx":"White Run"}}
>>>>>>> 03f74aca74312dbeaf24d7e61306dd6a786dc3d0
