{
  "id": 2767312,
  "type": "Feature",
  "properties": {
    "tgn:hierarchy":[
        "tgn:2767312",
        "tgn:1000001",
        "tgn:7012149",
        "tgn:2002168",
        "tgn:7007919",
        "tgn:7029392"
    ],
    "tgn:id":2767312,
    "tgn:name":"White Run",
    "tgn:placetype":[
        "aat:300008699"
    ]
},
  "bbox": [],
  "geometry": {"coordinates":[-79.5833,38.4167],"type":"Point"}
}