{
  "id": 7389865,
  "type": "Feature",
  "properties": {
    "tgn:hierarchy":[
        "tgn:7389865",
        "tgn:1000001",
        "tgn:1001960",
        "tgn:7005560",
        "tgn:7029392"
    ],
    "tgn:id":7389865,
    "tgn:name":"Represito",
    "tgn:placetype":[
        "aat:300008347"
    ]
},
  "bbox": [],
  "geometry": {"coordinates":[-110.983333,29.983333],"type":"Point"}
}