{
  "id": 2098863,
  "type": "Feature",
  "properties": {
    "tgn:hierarchy":[
        "tgn:2098863",
        "tgn:1000001",
        "tgn:7012149",
        "tgn:2001881",
        "tgn:7007825",
        "tgn:7029392"
    ],
    "tgn:id":2098863,
    "tgn:name":"Douglas Estates",
    "tgn:placetype":[
        "aat:300008347"
    ]
},
  "bbox": [],
  "geometry": {"coordinates":[-83.35,35.9833],"type":"Point"}
}