{
  "id": 2166245,
  "type": "Feature",
  "properties": {
    "tgn:hierarchy":[
        "tgn:2166245",
        "tgn:1000001",
        "tgn:2002319",
        "tgn:7012149",
        "tgn:7007922",
        "tgn:7029392"
    ],
    "tgn:id":2166245,
    "tgn:name":"Big Beaver Creek",
    "tgn:placetype":[
        "aat:300008706"
    ]
},
  "bbox": [],
  "geometry": {"coordinates":[-92.0167,45.15],"type":"Point"}
}