{
  "id": 7541820,
  "type": "Feature",
  "properties": {
    "tgn:hierarchy":[
        "tgn:7541820",
        "tgn:7001242",
        "tgn:7001105",
        "tgn:7016833",
        "tgn:7029392"
    ],
    "tgn:id":7541820,
    "tgn:name:en":"Al Mash\u0101riqah",
    "tgn:placetype":[
        "aat:300008347"
    ]
},
  "bbox": [],
  "geometry": {"coordinates":[30.989332,29.010402],"type":"Point"}
}