{
  "id": 7453621,
  "type": "Feature",
  "properties": {
    "tgn:hierarchy":[
        "tgn:7453621",
        "tgn:7019140",
        "tgn:7002444",
        "tgn:1000003",
        "tgn:7008591",
        "tgn:7029392"
    ],
    "tgn:id":7453621,
    "tgn:name:en":"Digby Water",
    "tgn:placetype":[
        "aat:300008699"
    ]
},
  "bbox": [],
  "geometry": {"coordinates":[-2.833333,56.466667],"type":"Point"}
}