<<<<<<< HEAD
{
  "id": 2409056,
  "type": "Feature",
  "properties": {
    "tgn:hierarchy":[
        "tgn:2409056",
        "tgn:1000001",
        "tgn:7012149",
        "tgn:7007256",
        "tgn:7029392"
    ],
    "tgn:id":2409056,
    "tgn:name":"Ice Branch",
    "tgn:placetype":[
        "aat:300008699"
    ]
},
  "bbox": [],
  "geometry": {"coordinates":[-92.3833,32.1167],"type":"Point"}
}
=======
{"geometry":{"type":"Point","coordinates":[-92.383300,32.116700]},"type":"Feature","properties":{"hierarchy":["tgn:2409056","tgn:1000001","tgn:7012149","tgn:7007256","tgn:7029392"],"placetype":["aat:300008699"],"id":2409056,"name:xx":"Ice Branch"}}
>>>>>>> 03f74aca74312dbeaf24d7e61306dd6a786dc3d0
