{
  "id": 2279527,
  "type": "Feature",
  "properties": {
    "tgn:hierarchy":[
        "tgn:2279527",
        "tgn:1000001",
        "tgn:7012149",
        "tgn:2001447",
        "tgn:7007566",
        "tgn:7029392"
    ],
    "tgn:id":2279527,
    "tgn:name":"Deadman Lake",
    "tgn:placetype":[
        "aat:300008680"
    ]
},
  "bbox": [],
  "geometry": {"coordinates":[-105.3167,33.2333],"type":"Point"}
}