{
  "id": 7047040,
  "type": "Feature",
  "properties": {
    "tgn:hierarchy":[
        "tgn:7047040",
        "tgn:7003167",
        "tgn:1000003",
        "tgn:7009760",
        "tgn:1000080",
        "tgn:7029392"
    ],
    "tgn:id":7047040,
    "tgn:name":"Grotte",
    "tgn:placetype":[
        "aat:300008347"
    ]
},
  "bbox": [],
  "geometry": {"coordinates":[10.716667,44.05],"type":"Point"}
}