{
  "id": 2733341,
  "type": "Feature",
  "properties": {
    "tgn:hierarchy":[
        "tgn:2733341",
        "tgn:1000001",
        "tgn:7012149",
        "tgn:2001437",
        "tgn:7007566",
        "tgn:7029392"
    ],
    "tgn:id":2733341,
    "tgn:name":"Turkey Run Canyon",
    "tgn:placetype":[
        "aat:300008761"
    ]
},
  "bbox": [],
  "geometry": {"coordinates":[-107.8333,32.95],"type":"Point"}
}