{
  "id": 2649866,
  "type": "Feature",
  "properties": {
    "tgn:hierarchy":[
        "tgn:2649866",
        "tgn:1000001",
        "tgn:2001429",
        "tgn:7012149",
        "tgn:7007566",
        "tgn:7029392"
    ],
    "tgn:id":2649866,
    "tgn:name":"Scrub Oak Tank",
    "tgn:placetype":[
        "aat:300006191"
    ]
},
  "bbox": [],
  "geometry": {"coordinates":[-108.3167,33.4833],"type":"Point"}
}