{
  "id": 2505023,
  "type": "Feature",
  "properties": {
    "tgn:hierarchy":[
        "tgn:2505023",
        "tgn:1000001",
        "tgn:7016172",
        "tgn:7012149",
        "tgn:2000137",
        "tgn:7029392"
    ],
    "tgn:id":2505023,
    "tgn:name":"Meeks Mountain",
    "tgn:placetype":[
        "aat:300008798"
    ]
},
  "bbox": [],
  "geometry": {"coordinates":[-91.95,35.95],"type":"Point"}
}