{
  "id": 7307374,
  "type": "Feature",
  "properties": {
    "tgn:hierarchy":[
        "tgn:7307374",
        "tgn:7002832",
        "tgn:7001158",
        "tgn:1000003",
        "tgn:1000095",
        "tgn:7029392"
    ],
    "tgn:id":7307374,
    "tgn:name":"Madrazos, Arroyo de los",
    "tgn:placetype":[
        "aat:300008699"
    ]
},
  "bbox": [],
  "geometry": {"coordinates":[-4.55,41.816667],"type":"Point"}
}