{
  "id": 2759164,
  "type": "Feature",
  "properties": {
    "tgn:hierarchy":[
        "tgn:2759164",
        "tgn:1000001",
        "tgn:7012149",
        "tgn:2002383",
        "tgn:7007923",
        "tgn:7029392"
    ],
    "tgn:id":2759164,
    "tgn:name":"West Fork Buckhorn Canyon",
    "tgn:placetype":[
        "aat:300008761"
    ]
},
  "bbox": [],
  "geometry": {"coordinates":[-110.0333,42.2333],"type":"Point"}
}