{
  "id": 2749695,
  "type": "Feature",
  "properties": {
    "tgn:hierarchy":[
        "tgn:2749695",
        "tgn:1000001",
        "tgn:7012149",
        "tgn:1002606",
        "tgn:7007706",
        "tgn:7029392"
    ],
    "tgn:id":2749695,
    "tgn:name":"Walnut Grove",
    "tgn:placetype":[
        "aat:300008347"
    ]
},
  "bbox": [],
  "geometry": {"coordinates":[-83.6167,40.4167],"type":"Point"}
}