<<<<<<< HEAD
{
  "id": 2407192,
  "type": "Feature",
  "properties": {
    "tgn:hierarchy":[
        "tgn:2407192",
        "tgn:1000001",
        "tgn:7012149",
        "tgn:2001868",
        "tgn:7007825",
        "tgn:7029392"
    ],
    "tgn:id":2407192,
    "tgn:name":"Hunters Ridge",
    "tgn:placetype":[
        "aat:300008347"
    ]
},
  "bbox": [],
  "geometry": {"coordinates":[-83.4,36.15],"type":"Point"}
}
=======
{"geometry":{"type":"Point","coordinates":[-83.400000,36.150000]},"type":"Feature","properties":{"hierarchy":["tgn:2407192","tgn:1000001","tgn:7012149","tgn:2001868","tgn:7007825","tgn:7029392"],"placetype":["aat:300008347"],"id":2407192,"name:xx":"Hunters Ridge"}}
>>>>>>> 03f74aca74312dbeaf24d7e61306dd6a786dc3d0
