{
  "id": 7549908,
  "type": "Feature",
  "properties": {
    "tgn:hierarchy":[
        "tgn:7549908",
        "tgn:7016678",
        "tgn:7000204",
        "tgn:1000004",
        "tgn:7000198",
        "tgn:7029392"
    ],
    "tgn:id":7549908,
    "tgn:name:en":"Coral Reef",
    "tgn:placetype":[
        "aat:300008808"
    ]
},
  "bbox": [],
  "geometry": {"coordinates":[93.466667,7.75],"type":"Point"}
}