{
  "id": 2422928,
  "type": "Feature",
  "properties": {
    "tgn:hierarchy":[
        "tgn:2422928",
        "tgn:1000001",
        "tgn:7012149",
        "tgn:7014128",
        "tgn:7007709",
        "tgn:7029392"
    ],
    "tgn:id":2422928,
    "tgn:name":"Joe Hamme Jr Lake",
    "tgn:placetype":[
        "aat:300006191"
    ]
},
  "bbox": [],
  "geometry": {"coordinates":[-78.5333,36.2167],"type":"Point"}
}