{
  "id": 7117195,
  "type": "Feature",
  "properties": {
    "tgn:hierarchy":[
        "tgn:7117195",
        "tgn:7003692",
        "tgn:1000003",
        "tgn:7000084",
        "tgn:7029392"
    ],
    "tgn:id":7117195,
    "tgn:name":"Obertal",
    "tgn:placetype":[
        "aat:300387200"
    ]
},
  "bbox": [],
  "geometry": {"coordinates":[8.233333,48.05],"type":"Point"}
}