{
  "id": 2530030,
  "type": "Feature",
  "properties": {
    "tgn:hierarchy":[
        "tgn:2530030",
        "tgn:1000001",
        "tgn:2001428",
        "tgn:7012149",
        "tgn:7007566",
        "tgn:7029392"
    ],
    "tgn:id":2530030,
    "tgn:name":"Mud Spring",
    "tgn:placetype":[
        "aat:300008697"
    ]
},
  "bbox": [],
  "geometry": {"coordinates":[-106.3833,35.1167],"type":"Point"}
}