{
  "id": 7433301,
  "type": "Feature",
  "properties": {
    "tgn:hierarchy":[
        "tgn:7433301",
        "tgn:1000001",
        "tgn:7005588",
        "tgn:7005560",
        "tgn:7029392"
    ],
    "tgn:id":7433301,
    "tgn:name":"Tlacotenco",
    "tgn:placetype":[
        "aat:300008347"
    ]
},
  "bbox": [],
  "geometry": {"coordinates":[-99.094444,19.015],"type":"Point"}
}