<<<<<<< HEAD
{
  "id": 7171593,
  "type": "Feature",
  "properties": {
    "tgn:hierarchy":[
        "tgn:7171593",
        "tgn:1000003",
        "tgn:7003677",
        "tgn:7000084",
        "tgn:7029392"
    ],
    "tgn:id":7171593,
    "tgn:name":"Hillerscheid",
    "tgn:placetype":[
        "aat:300008347"
    ]
},
  "bbox": [],
  "geometry": {"coordinates":[7.466667,50.933333],"type":"Point"}
}
=======
{"geometry":{"type":"Point","coordinates":[7.466667,50.933333]},"type":"Feature","properties":{"hierarchy":["tgn:7171593","tgn:1000003","tgn:7003677","tgn:7000084","tgn:7029392"],"placetype":["aat:300008347"],"id":7171593,"name:xx":"Hillerscheid"}}
>>>>>>> 03f74aca74312dbeaf24d7e61306dd6a786dc3d0
