{
  "id": 2354645,
  "type": "Feature",
  "properties": {
    "tgn:hierarchy":[
        "tgn:2354645",
        "tgn:1000001",
        "tgn:7016172",
        "tgn:2000109",
        "tgn:7012149",
        "tgn:7029392"
    ],
    "tgn:id":2354645,
    "tgn:name":"Gooch Hollow",
    "tgn:placetype":[
        "aat:300008761"
    ]
},
  "bbox": [],
  "geometry": {"coordinates":[-92.9833,36.25],"type":"Point"}
}