{
  "id": 2611427,
  "type": "Feature",
  "properties": {
    "tgn:hierarchy":[
        "tgn:2611427",
        "tgn:1000001",
        "tgn:7012149",
        "tgn:1002839",
        "tgn:7007826",
        "tgn:7029392"
    ],
    "tgn:id":2611427,
    "tgn:name":"Red Level",
    "tgn:placetype":[
        "aat:300008347"
    ]
},
  "bbox": [],
  "geometry": {"coordinates":[-94.9667,32.3333],"type":"Point"}
}