{
  "id": 1069881,
  "type": "Feature",
  "properties": {
    "tgn:hierarchy":[
        "tgn:1069881",
        "tgn:1000004",
        "tgn:1000960",
        "tgn:1000111",
        "tgn:7029392"
    ],
    "tgn:id":1069881,
    "tgn:name":"Linhezhuang",
    "tgn:placetype":[
        "aat:300008347"
    ]
},
  "bbox": [],
  "geometry": {"coordinates":[117.65,40.0667],"type":"Point"}
}