{
  "id": 7515335,
  "type": "Feature",
  "properties": {
    "tgn:hierarchy":[
        "tgn:7515335",
        "tgn:1009227",
        "tgn:1000226",
        "tgn:7018437",
        "tgn:1000006",
        "tgn:7029392"
    ],
    "tgn:id":7515335,
    "tgn:name:en":"Centaur Peaks",
    "tgn:placetype":[
        "aat:300008798"
    ]
},
  "bbox": [],
  "geometry": {"coordinates":[168.583333,-44.633333],"type":"Point"}
}