{
  "id": 2730518,
  "type": "Feature",
  "properties": {
    "tgn:hierarchy":[
        "tgn:2730518",
        "tgn:1000001",
        "tgn:7012149",
        "tgn:2001449",
        "tgn:7007566",
        "tgn:7029392"
    ],
    "tgn:id":2730518,
    "tgn:name":"Trujillo Reservoir",
    "tgn:placetype":[
        "aat:300006191"
    ]
},
  "bbox": [],
  "geometry": {"coordinates":[-107.3333,36.65],"type":"Point"}
}