<<<<<<< HEAD
{
  "id": 7376297,
  "type": "Feature",
  "properties": {
    "tgn:hierarchy":[
        "tgn:7376297",
        "tgn:1000001",
        "tgn:7005589",
        "tgn:7005560",
        "tgn:7029392"
    ],
    "tgn:id":7376297,
    "tgn:name":"Rancho La Rosa",
    "tgn:placetype":[
        "aat:300000241"
    ]
},
  "bbox": [],
  "geometry": {"coordinates":[-99.966667,25.116667],"type":"Point"}
}
=======
{"geometry":{"type":"Point","coordinates":[-99.966667,25.116667]},"type":"Feature","properties":{"hierarchy":["tgn:7376297","tgn:1000001","tgn:7005589","tgn:7005560","tgn:7029392"],"placetype":["aat:300000241"],"id":7376297,"name:xx":"Rancho La Rosa"}}
>>>>>>> 03f74aca74312dbeaf24d7e61306dd6a786dc3d0
