{
  "id": 1008074,
  "type": "Feature",
  "properties": {
    "tgn:hierarchy":[
        "tgn:1008074",
        "tgn:7002444",
        "tgn:1000003",
        "tgn:7008082",
        "tgn:7008591",
        "tgn:7029392"
    ],
    "tgn:id":1008074,
    "tgn:name:en":"Martin, Isle",
    "tgn:placetype":[
        "aat:300008791"
    ]
},
  "bbox": [],
  "geometry": {"coordinates":[-5.233333,57.95],"type":"Point"}
}