{
  "id": 2389813,
  "type": "Feature",
  "properties": {
    "tgn:hierarchy":[
        "tgn:2389813",
        "tgn:1000001",
        "tgn:7006451",
        "tgn:2000091",
        "tgn:7012149",
        "tgn:7029392"
    ],
    "tgn:id":2389813,
    "tgn:name":"High Lonesome Spring",
    "tgn:placetype":[
        "aat:300008697"
    ]
},
  "bbox": [],
  "geometry": {"coordinates":[-109.3667,31.6333],"type":"Point"}
}