{
  "id": 2484772,
  "type": "Feature",
  "properties": {
    "tgn:hierarchy":[
        "tgn:2484772",
        "tgn:1000001",
        "tgn:7012149",
        "tgn:2002296",
        "tgn:7013961",
        "tgn:7029392"
    ],
    "tgn:id":2484772,
    "tgn:name":"Laurel Run",
    "tgn:placetype":[
        "aat:300008699"
    ]
},
  "bbox": [],
  "geometry": {"coordinates":[-79.7167,39.0333],"type":"Point"}
}