<<<<<<< HEAD
{
  "id": 2150571,
  "type": "Feature",
  "properties": {
    "tgn:hierarchy":[
        "tgn:2150571",
        "tgn:1000001",
        "tgn:7012149",
        "tgn:2000476",
        "tgn:7007250",
        "tgn:7029392"
    ],
    "tgn:id":2150571,
    "tgn:name":"Basin, The",
    "tgn:placetype":[
        "aat:300386845"
    ]
},
  "bbox": [],
  "geometry": {"coordinates":[-116.3667,45.8833],"type":"Point"}
}
=======
{"geometry":{"type":"Point","coordinates":[-116.366700,45.883300]},"type":"Feature","properties":{"hierarchy":["tgn:2150571","tgn:1000001","tgn:7012149","tgn:2000476","tgn:7007250","tgn:7029392"],"placetype":["aat:300386845"],"id":2150571,"name:xx":"Basin, The"}}
>>>>>>> 03f74aca74312dbeaf24d7e61306dd6a786dc3d0
