{
  "id": 1082101,
  "type": "Feature",
  "properties": {
    "tgn:hierarchy":[
        "tgn:1082101",
        "tgn:1001284",
        "tgn:1000004",
        "tgn:1000122",
        "tgn:7029392"
    ],
    "tgn:id":1082101,
    "tgn:name":"S\u014fngnae-ri",
    "tgn:placetype":[
        "aat:300008347"
    ]
},
  "bbox": [],
  "geometry": {"coordinates":[126.9833,39.4333],"type":"Point"}
}