{
  "id": 7054391,
  "type": "Feature",
  "properties": {
    "tgn:hierarchy":[
        "tgn:7054391",
        "tgn:1001724",
        "tgn:1000003",
        "tgn:7003121",
        "tgn:1000080",
        "tgn:7029392"
    ],
    "tgn:id":7054391,
    "tgn:name":"Paglia, Porto de sa",
    "tgn:placetype":[
        "aat:300008678"
    ]
},
  "bbox": [],
  "geometry": {"coordinates":[9.65,39.55],"type":"Point"}
}