<<<<<<< HEAD
{
  "id": 7054391,
  "type": "Feature",
  "properties": {
    "tgn:hierarchy":[
        "tgn:7054391",
        "tgn:1001724",
        "tgn:1000003",
        "tgn:7003121",
        "tgn:1000080",
        "tgn:7029392"
    ],
    "tgn:id":7054391,
    "tgn:name":"Paglia, Porto de sa",
    "tgn:placetype":[
        "aat:300008678"
    ]
},
  "bbox": [],
  "geometry": {"coordinates":[9.65,39.55],"type":"Point"}
}
=======
{"geometry":{"type":"Point","coordinates":[9.650000,39.550000]},"type":"Feature","properties":{"hierarchy":["tgn:7054391","tgn:1001724","tgn:1000003","tgn:7003121","tgn:1000080","tgn:7029392"],"placetype":["aat:300008678"],"id":7054391,"name:xx":"Paglia, Porto de sa"}}
>>>>>>> 03f74aca74312dbeaf24d7e61306dd6a786dc3d0
