{
  "id": 2101894,
  "type": "Feature",
  "properties": {
    "tgn:hierarchy":[
        "tgn:2101894",
        "tgn:1000001",
        "tgn:7012149",
        "tgn:2001866",
        "tgn:7007825",
        "tgn:7029392"
    ],
    "tgn:id":2101894,
    "tgn:name":"Tusculum",
    "tgn:placetype":[
        "aat:300008347"
    ]
},
  "bbox": [],
  "geometry": {"coordinates":[-82.75,36.1667],"type":"Point"}
}