{
  "id": 2077327,
  "type": "Feature",
  "properties": {
    "tgn:hierarchy":[
        "tgn:2077327",
        "tgn:2001467",
        "tgn:1000001",
        "tgn:7012149",
        "tgn:7007709",
        "tgn:7029392"
    ],
    "tgn:id":2077327,
    "tgn:name":"Woodford",
    "tgn:placetype":[
        "aat:300008347",
        "aat:300387210"
    ]
},
  "bbox": [],
  "geometry": {"coordinates":[-81.5833,36.3333],"type":"Point"}
}