{
  "id": 2088159,
  "type": "Feature",
  "properties": {
    "tgn:hierarchy":[
        "tgn:2088159",
        "tgn:1000001",
        "tgn:7012149",
        "tgn:7016020",
        "tgn:7007710",
        "tgn:7029392"
    ],
    "tgn:id":2088159,
    "tgn:name":"Eldred",
    "tgn:placetype":[
        "aat:300008347"
    ]
},
  "bbox": [],
  "geometry": {"coordinates":[-78.3833,41.95],"type":"Point"}
}