{
  "id": 2320236,
  "type": "Feature",
  "properties": {
    "tgn:hierarchy":[
        "tgn:2320236",
        "tgn:2000943",
        "tgn:1000001",
        "tgn:7012149",
        "tgn:7007520",
        "tgn:7029392"
    ],
    "tgn:id":2320236,
    "tgn:name":"Evelyn",
    "tgn:placetype":[
        "aat:300008347"
    ]
},
  "bbox": [],
  "geometry": {"coordinates":[-86.5333,46.3667],"type":"Point"}
}