<<<<<<< HEAD
{
  "id": 7477333,
  "type": "Feature",
  "properties": {
    "tgn:hierarchy":[
        "tgn:7477333",
        "tgn:1000004",
        "tgn:7001013",
        "tgn:1000141",
        "tgn:7029392"
    ],
    "tgn:id":7477333,
    "tgn:name":"Fanzipojiao",
    "tgn:placetype":[
        "aat:300008347"
    ]
},
  "bbox": [],
  "geometry": {"coordinates":[121.153568,25.01059],"type":"Point"}
}
=======
{"geometry":{"type":"Point","coordinates":[121.153568,25.010590]},"type":"Feature","properties":{"hierarchy":["tgn:7477333","tgn:1000004","tgn:7001013","tgn:1000141","tgn:7029392"],"placetype":["aat:300008347"],"id":7477333,"name:xx":"Fanzipojiao"}}
>>>>>>> 03f74aca74312dbeaf24d7e61306dd6a786dc3d0
