{
  "id": 2291873,
  "type": "Feature",
  "properties": {
    "tgn:hierarchy":[
        "tgn:2291873",
        "tgn:1000001",
        "tgn:7012149",
        "tgn:7007923",
        "tgn:7029392"
    ],
    "tgn:id":2291873,
    "tgn:name":"Dome Peak",
    "tgn:placetype":[
        "aat:300008798"
    ]
},
  "bbox": [],
  "geometry": {"coordinates":[-107.3667,44.5833],"type":"Point"}
}