{
  "id": 7035321,
  "type": "Feature",
  "properties": {
    "tgn:hierarchy":[
        "tgn:7035321",
        "tgn:1003488",
        "tgn:1000003",
        "tgn:7002993",
        "tgn:1000080",
        "tgn:7029392"
    ],
    "tgn:id":7035321,
    "tgn:name":"Contron",
    "tgn:placetype":[
        "aat:300008347"
    ]
},
  "bbox": [],
  "geometry": {"coordinates":[12.487778,46.235833],"type":"Point"}
}