<<<<<<< HEAD
{
  "id": 2250827,
  "type": "Feature",
  "properties": {
    "tgn:hierarchy":[
        "tgn:2250827",
        "tgn:1000001",
        "tgn:2001412",
        "tgn:7012149",
        "tgn:7007526",
        "tgn:7029392"
    ],
    "tgn:id":2250827,
    "tgn:name":"Columbia",
    "tgn:placetype":[
        "aat:300008347"
    ]
},
  "bbox": [],
  "geometry": {"coordinates":[-117.2167,37.7167],"type":"Point"}
}
=======
{"geometry":{"type":"Point","coordinates":[-117.216700,37.716700]},"type":"Feature","properties":{"hierarchy":["tgn:2250827","tgn:1000001","tgn:2001412","tgn:7012149","tgn:7007526","tgn:7029392"],"placetype":["aat:300008347"],"id":2250827,"name:xx":"Columbia"}}
>>>>>>> 03f74aca74312dbeaf24d7e61306dd6a786dc3d0
