{
  "id": 7052320,
  "type": "Feature",
  "properties": {
    "tgn:hierarchy":[
        "tgn:7052320",
        "tgn:7003136",
        "tgn:1000003",
        "tgn:7003080",
        "tgn:1000080",
        "tgn:7029392"
    ],
    "tgn:id":7052320,
    "tgn:name":"Pellegrino, Monte",
    "tgn:placetype":[
        "aat:300008795"
    ]
},
  "bbox": [],
  "geometry": {"coordinates":[13.05,40.966667],"type":"Point"}
}