{
  "id": 7353723,
  "type": "Feature",
  "properties": {
    "tgn:hierarchy":[
        "tgn:7353723",
        "tgn:1000001",
        "tgn:7005597",
        "tgn:7005560",
        "tgn:7029392"
    ],
    "tgn:id":7353723,
    "tgn:name":"Buey",
    "tgn:placetype":[
        "aat:300008347"
    ]
},
  "bbox": [],
  "geometry": {"coordinates":[-99.95,23.05],"type":"Point"}
}