{
  "id": 2572628,
  "type": "Feature",
  "properties": {
    "tgn:hierarchy":[
        "tgn:2572628",
        "tgn:1002648",
        "tgn:1000001",
        "tgn:7019158",
        "tgn:7012149",
        "tgn:7007249",
        "tgn:7029392"
    ],
    "tgn:id":2572628,
    "tgn:name":"Peahi Reservoir",
    "tgn:placetype":[
        "aat:300006191"
    ]
},
  "bbox": [],
  "geometry": {"coordinates":[-156.2667,20.9167],"type":"Point"}
}