<<<<<<< HEAD
{
  "id": 2760570,
  "type": "Feature",
  "properties": {
    "tgn:hierarchy":[
        "tgn:2760570",
        "tgn:2001088",
        "tgn:1000001",
        "tgn:7012149",
        "tgn:7007522",
        "tgn:7029392"
    ],
    "tgn:id":2760570,
    "tgn:name":"West Fork Waggoner Creek",
    "tgn:placetype":[
        "aat:300008706"
    ]
},
  "bbox": [],
  "geometry": {"coordinates":[-90.9667,31.2],"type":"Point"}
}
=======
{"geometry":{"type":"Point","coordinates":[-90.966700,31.200000]},"type":"Feature","properties":{"hierarchy":["tgn:2760570","tgn:2001088","tgn:1000001","tgn:7012149","tgn:7007522","tgn:7029392"],"placetype":["aat:300008706"],"id":2760570,"name:xx":"West Fork Waggoner Creek"}}
>>>>>>> 03f74aca74312dbeaf24d7e61306dd6a786dc3d0
