{
  "id": 7518629,
  "type": "Feature",
  "properties": {
    "tgn:hierarchy":[
        "tgn:7518629",
        "tgn:1009227",
        "tgn:1000226",
        "tgn:7016822",
        "tgn:1000006",
        "tgn:7029392"
    ],
    "tgn:id":7518629,
    "tgn:name:en":"Azimuth, Mount",
    "tgn:placetype":[
        "aat:300008795"
    ]
},
  "bbox": [],
  "geometry": {"coordinates":[169.116667,-52.516667],"type":"Point"}
}