{
  "id": 2478193,
  "type": "Feature",
  "properties": {
    "tgn:hierarchy":[
        "tgn:2478193",
        "tgn:1000001",
        "tgn:7012149",
        "tgn:2001962",
        "tgn:7007826",
        "tgn:7029392"
    ],
    "tgn:id":2478193,
    "tgn:name":"Mackey Branch",
    "tgn:placetype":[
        "aat:300008699"
    ]
},
  "bbox": [],
  "geometry": {"coordinates":[-98.3167,31.9167],"type":"Point"}
}