{
  "id": 2582555,
  "type": "Feature",
  "properties": {
    "tgn:hierarchy":[
        "tgn:2582555",
        "tgn:1000001",
        "tgn:7012149",
        "tgn:2000356",
        "tgn:7007248",
        "tgn:7029392"
    ],
    "tgn:id":2582555,
    "tgn:name":"Pine Hill",
    "tgn:placetype":[
        "aat:300008347"
    ]
},
  "bbox": [],
  "geometry": {"coordinates":[-84.2667,30.7167],"type":"Point"}
}