{
  "id": 1023931,
  "type": "Feature",
  "properties": {
    "tgn:hierarchy":[
        "tgn:1023931",
        "tgn:1000050",
        "tgn:1002106",
        "tgn:1000002",
        "tgn:7029392"
    ],
    "tgn:id":1023931,
    "tgn:name":"Puerto As\u00eds",
    "tgn:placetype":[
        "aat:300008347"
    ]
},
  "bbox": [],
  "geometry": {"coordinates":[-76.5167,0.5167],"type":"Point"}
}