<<<<<<< HEAD
{
  "id": 7059932,
  "type": "Feature",
  "properties": {
    "tgn:hierarchy":[
        "tgn:7059932",
        "tgn:1000003",
        "tgn:7003677",
        "tgn:7000084",
        "tgn:7029392"
    ],
    "tgn:id":7059932,
    "tgn:name":"Aggerh\u00fctte",
    "tgn:placetype":[
        "aat:300008347"
    ]
},
  "bbox": [],
  "geometry": {"coordinates":[7.266667,50.916667],"type":"Point"}
}
=======
{"geometry":{"type":"Point","coordinates":[7.266667,50.916667]},"type":"Feature","properties":{"hierarchy":["tgn:7059932","tgn:1000003","tgn:7003677","tgn:7000084","tgn:7029392"],"placetype":["aat:300008347"],"id":7059932,"name:xx":"Aggerh\u00fctte"}}
>>>>>>> 03f74aca74312dbeaf24d7e61306dd6a786dc3d0
