<<<<<<< HEAD
{
  "id": 2151354,
  "type": "Feature",
  "properties": {
    "tgn:hierarchy":[
        "tgn:2151354",
        "tgn:1000001",
        "tgn:7012149",
        "tgn:1002580",
        "tgn:7007710",
        "tgn:7029392"
    ],
    "tgn:id":2151354,
    "tgn:name":"Bates Lake",
    "tgn:placetype":[
        "aat:300008680"
    ]
},
  "bbox": [],
  "geometry": {"coordinates":[-80.1667,40.85],"type":"Point"}
}
=======
{"geometry":{"type":"Point","coordinates":[-80.166700,40.850000]},"type":"Feature","properties":{"hierarchy":["tgn:2151354","tgn:1000001","tgn:7012149","tgn:1002580","tgn:7007710","tgn:7029392"],"placetype":["aat:300008680"],"id":2151354,"name:xx":"Bates Lake"}}
>>>>>>> 03f74aca74312dbeaf24d7e61306dd6a786dc3d0
