<<<<<<< HEAD
{
  "id": 2256579,
  "type": "Feature",
  "properties": {
    "tgn:hierarchy":[
        "tgn:2256579",
        "tgn:1000001",
        "tgn:7012149",
        "tgn:1002628",
        "tgn:7007240",
        "tgn:7029392"
    ],
    "tgn:id":2256579,
    "tgn:name":"Corbit Branch",
    "tgn:placetype":[
        "aat:300008699"
    ]
},
  "bbox": [],
  "geometry": {"coordinates":[-82.3,27.4333],"type":"Point"}
}
=======
{"geometry":{"type":"Point","coordinates":[-82.300000,27.433300]},"type":"Feature","properties":{"hierarchy":["tgn:2256579","tgn:1000001","tgn:7012149","tgn:1002628","tgn:7007240","tgn:7029392"],"placetype":["aat:300008699"],"id":2256579,"name:xx":"Corbit Branch"}}
>>>>>>> 03f74aca74312dbeaf24d7e61306dd6a786dc3d0
