{
  "id": 2131589,
  "type": "Feature",
  "properties": {
    "tgn:hierarchy":[
        "tgn:2131589",
        "tgn:2000196",
        "tgn:1000001",
        "tgn:7012149",
        "tgn:7007158",
        "tgn:7029392"
    ],
    "tgn:id":2131589,
    "tgn:name":"Alum Spring",
    "tgn:placetype":[
        "aat:300008697"
    ]
},
  "bbox": [],
  "geometry": {"coordinates":[-103.05,37.55],"type":"Point"}
}