{
  "id": 7215950,
  "type": "Feature",
  "properties": {
    "tgn:hierarchy":[
        "tgn:7215950",
        "tgn:1000003",
        "tgn:7003677",
        "tgn:7000084",
        "tgn:7029392"
    ],
    "tgn:id":7215950,
    "tgn:name":"Achenbach",
    "tgn:placetype":[
        "aat:300008347"
    ]
},
  "bbox": [],
  "geometry": {"coordinates":[7.966667,50.866667],"type":"Point"}
}