{
  "id": 7268946,
  "type": "Feature",
  "properties": {
    "tgn:hierarchy":[
        "tgn:7268946",
        "tgn:1000003",
        "tgn:7003627",
        "tgn:7016845",
        "tgn:7029392"
    ],
    "tgn:id":7268946,
    "tgn:name:nl":"Praamgracht",
    "tgn:placetype":[
        "aat:300006075"
    ]
},
  "bbox": [],
  "geometry": {"coordinates":[5.266667,52.183333],"type":"Point"}
}