{
  "id": 2192154,
  "type": "Feature",
  "properties": {
    "tgn:hierarchy":[
        "tgn:2192154",
        "tgn:1000001",
        "tgn:2001418",
        "tgn:7012149",
        "tgn:7007526",
        "tgn:7029392"
    ],
    "tgn:id":2192154,
    "tgn:name":"Bramer Spring",
    "tgn:placetype":[
        "aat:300008697"
    ]
},
  "bbox": [],
  "geometry": {"coordinates":[-116.25,36.35],"type":"Point"}
}