{
  "id": 7592315,
  "type": "Feature",
  "properties": {
    "tgn:hierarchy":[
        "tgn:7592315",
        "tgn:1000004",
        "tgn:7000198",
        "tgn:7000799",
        "tgn:7029392"
    ],
    "tgn:id":7592315,
    "tgn:name:en":"Sarw\u0101l",
    "tgn:placetype":[
        "aat:300008347"
    ]
},
  "bbox": [],
  "geometry": {"coordinates":[74.85,32.748611],"type":"Point"}
}