{
  "id": 2403375,
  "type": "Feature",
  "properties": {
    "tgn:hierarchy":[
        "tgn:2403375",
        "tgn:1000001",
        "tgn:7012149",
        "tgn:7007157",
        "tgn:1002857",
        "tgn:7029392"
    ],
    "tgn:id":2403375,
    "tgn:name":"Houston Creek",
    "tgn:placetype":[
        "aat:300008706"
    ]
},
  "bbox": [],
  "geometry": {"coordinates":[-117.2667,34.2333],"type":"Point"}
}