{
  "id": 2213558,
  "type": "Feature",
  "properties": {
    "tgn:hierarchy":[
        "tgn:2213558",
        "tgn:1000001",
        "tgn:7012149",
        "tgn:7029392"
    ],
    "tgn:id":2213558,
    "tgn:name":"Cable Creek",
    "tgn:placetype":[
        "aat:300008706"
    ]
},
  "bbox": [],
  "geometry": {"coordinates":[-117.05,47.6833],"type":"Point"}
}