<<<<<<< HEAD
{
  "id": 2335133,
  "type": "Feature",
  "properties": {
    "tgn:hierarchy":[
        "tgn:2335133",
        "tgn:1000001",
        "tgn:7006451",
        "tgn:7012149",
        "tgn:2000099",
        "tgn:7029392"
    ],
    "tgn:id":2335133,
    "tgn:name":"Fort Apache Tank",
    "tgn:placetype":[
        "aat:300006191"
    ]
},
  "bbox": [],
  "geometry": {"coordinates":[-109.9667,33.7833],"type":"Point"}
}
=======
{"geometry":{"type":"Point","coordinates":[-109.966700,33.783300]},"type":"Feature","properties":{"hierarchy":["tgn:2335133","tgn:1000001","tgn:7006451","tgn:7012149","tgn:2000099","tgn:7029392"],"placetype":["aat:300006191"],"id":2335133,"name:xx":"Fort Apache Tank"}}
>>>>>>> 03f74aca74312dbeaf24d7e61306dd6a786dc3d0
