{
  "id": 7393141,
  "type": "Feature",
  "properties": {
    "tgn:hierarchy":[
        "tgn:7393141",
        "tgn:1000001",
        "tgn:7005589",
        "tgn:7005560",
        "tgn:7029392"
    ],
    "tgn:id":7393141,
    "tgn:name":"San Francisco",
    "tgn:placetype":[
        "aat:300008347"
    ]
},
  "bbox": [],
  "geometry": {"coordinates":[-99.933333,23.95],"type":"Point"}
}