{
  "id": 7515048,
  "type": "Feature",
  "properties": {
    "tgn:hierarchy":[
        "tgn:7515048",
        "tgn:1009227",
        "tgn:1000226",
        "tgn:7018437",
        "tgn:1000006",
        "tgn:7029392"
    ],
    "tgn:id":7515048,
    "tgn:name:en":"Cannibal Bay",
    "tgn:placetype":[
        "aat:300132316"
    ]
},
  "bbox": [],
  "geometry": {"coordinates":[169.766667,-46.483333],"type":"Point"}
}