<<<<<<< HEAD
{
  "id": 2337079,
  "type": "Feature",
  "properties": {
    "tgn:hierarchy":[
        "tgn:2337079",
        "tgn:1000001",
        "tgn:7012149",
        "tgn:1003017",
        "tgn:7007710",
        "tgn:7029392"
    ],
    "tgn:id":2337079,
    "tgn:name":"Fourmile Run",
    "tgn:placetype":[
        "aat:300008699"
    ]
},
  "bbox": [],
  "geometry": {"coordinates":[-79.45,40.2833],"type":"Point"}
}
=======
{"geometry":{"type":"Point","coordinates":[-79.450000,40.283300]},"type":"Feature","properties":{"hierarchy":["tgn:2337079","tgn:1000001","tgn:7012149","tgn:1003017","tgn:7007710","tgn:7029392"],"placetype":["aat:300008699"],"id":2337079,"name:xx":"Fourmile Run"}}
>>>>>>> 03f74aca74312dbeaf24d7e61306dd6a786dc3d0
