{
  "id": 2143292,
  "type": "Feature",
  "properties": {
    "tgn:hierarchy":[
        "tgn:2143292",
        "tgn:1000001",
        "tgn:7012149",
        "tgn:7007523",
        "tgn:7029392"
    ],
    "tgn:id":2143292,
    "tgn:name":"Bailey Creek",
    "tgn:placetype":[
        "aat:300008706"
    ]
},
  "bbox": [],
  "geometry": {"coordinates":[-91.75,38.05],"type":"Point"}
}