{
  "id": 7398049,
  "type": "Feature",
  "properties": {
    "tgn:hierarchy":[
        "tgn:7398049",
        "tgn:1000001",
        "tgn:1001960",
        "tgn:7005560",
        "tgn:7029392"
    ],
    "tgn:id":7398049,
    "tgn:name":"Guipuzcoana, Ca\u00f1ada",
    "tgn:placetype":[
        "aat:300008773"
    ]
},
  "bbox": [],
  "geometry": {"coordinates":[-110.606667,30.888611],"type":"Point"}
}