{
  "id": 2744094,
  "type": "Feature",
  "properties": {
    "tgn:hierarchy":[
        "tgn:2744094",
        "tgn:1000001",
        "tgn:7012149",
        "tgn:2000234",
        "tgn:7007158",
        "tgn:7029392"
    ],
    "tgn:id":2744094,
    "tgn:name":"Veo Ditch",
    "tgn:placetype":[
        "aat:300006075"
    ]
},
  "bbox": [],
  "geometry": {"coordinates":[-107.55,38.35],"type":"Point"}
}