<<<<<<< HEAD
{
  "id": 2336391,
  "type": "Feature",
  "properties": {
    "tgn:hierarchy":[
        "tgn:2336391",
        "tgn:1000001",
        "tgn:7012149",
        "tgn:1003020",
        "tgn:7007920",
        "tgn:7029392"
    ],
    "tgn:id":2336391,
    "tgn:name":"Fountain Lake",
    "tgn:placetype":[
        "aat:300008680"
    ]
},
  "bbox": [],
  "geometry": {"coordinates":[-122.4167,48.9],"type":"Point"}
}
=======
{"geometry":{"type":"Point","coordinates":[-122.416700,48.900000]},"type":"Feature","properties":{"hierarchy":["tgn:2336391","tgn:1000001","tgn:7012149","tgn:1003020","tgn:7007920","tgn:7029392"],"placetype":["aat:300008680"],"id":2336391,"name:xx":"Fountain Lake"}}
>>>>>>> 03f74aca74312dbeaf24d7e61306dd6a786dc3d0
