{
  "id": 2268842,
  "type": "Feature",
  "properties": {
    "tgn:hierarchy":[
        "tgn:2268842",
        "tgn:1000001",
        "tgn:7012149",
        "tgn:2000232",
        "tgn:7007158",
        "tgn:7029392"
    ],
    "tgn:id":2268842,
    "tgn:name":"Cross Mountain Canyon",
    "tgn:placetype":[
        "aat:300008761"
    ]
},
  "bbox": [],
  "geometry": {"coordinates":[-108.3333,40.4667],"type":"Point"}
}