{
  "id": 2515976,
  "type": "Feature",
  "properties": {
    "tgn:hierarchy":[
        "tgn:2515976",
        "tgn:1000001",
        "tgn:7012149",
        "tgn:2001756",
        "tgn:7007712",
        "tgn:7029392"
    ],
    "tgn:id":2515976,
    "tgn:name":"Mims",
    "tgn:placetype":[
        "aat:300008347"
    ]
},
  "bbox": [],
  "geometry": {"coordinates":[-81.4833,33.8333],"type":"Point"}
}