{
  "id": 1018918,
  "type": "Feature",
  "properties": {
    "tgn:hierarchy":[
        "tgn:1018918",
        "tgn:7017440",
        "tgn:1000001",
        "tgn:7004643",
        "tgn:7029392"
    ],
    "tgn:id":1018918,
    "tgn:name":"Boca Chica",
    "tgn:placetype":[
        "aat:300008347"
    ]
},
  "bbox": [],
  "geometry": {"coordinates":[-66.5333,17.9833],"type":"Point"}
}