{
  "id": 7253018,
  "type": "Feature",
  "properties": {
    "tgn:hierarchy":[
        "tgn:7253018",
        "tgn:7007877",
        "tgn:1000003",
        "tgn:1000063",
        "tgn:4012014",
        "tgn:7029392"
    ],
    "tgn:id":7253018,
    "tgn:name":"Trieu Gilson",
    "tgn:placetype":[
        "aat:300008347"
    ]
},
  "bbox": [],
  "geometry": {"coordinates":[4.483333,50.35],"type":"Point"}
}