{
  "id": 7332028,
  "type": "Feature",
  "properties": {
    "tgn:hierarchy":[
        "tgn:7332028",
        "tgn:7002826",
        "tgn:7001158",
        "tgn:1000003",
        "tgn:1000095",
        "tgn:7029392"
    ],
    "tgn:id":7332028,
    "tgn:name":"Lagunas de Somoza",
    "tgn:placetype":[
        "aat:300008347"
    ]
},
  "bbox": [],
  "geometry": {"coordinates":[-6.183333,42.383333],"type":"Point"}
}