{
  "id": 7046849,
  "type": "Feature",
  "properties": {
    "tgn:hierarchy":[
        "tgn:7046849",
        "tgn:1000003",
        "tgn:7003122",
        "tgn:7003157",
        "tgn:1000080",
        "tgn:7029392"
    ],
    "tgn:id":7046849,
    "tgn:name":"Case Levito",
    "tgn:placetype":[
        "aat:300008347"
    ]
},
  "bbox": [],
  "geometry": {"coordinates":[15.35,38.133333],"type":"Point"}
}