{
  "id": 2153955,
  "type": "Feature",
  "properties": {
    "tgn:hierarchy":[
        "tgn:2153955",
        "tgn:7002659",
        "tgn:1000001",
        "tgn:7012149",
        "tgn:2000064",
        "tgn:7029392"
    ],
    "tgn:id":2153955,
    "tgn:name":"Bear Creek",
    "tgn:placetype":[
        "aat:300008706"
    ]
},
  "bbox": [],
  "geometry": {"coordinates":[-88.2167,31.2667],"type":"Point"}
}