<<<<<<< HEAD
{
  "id": 2764188,
  "type": "Feature",
  "properties": {
    "tgn:hierarchy":[
        "tgn:2764188",
        "tgn:1000001",
        "tgn:7012149",
        "tgn:1002999",
        "tgn:7007526",
        "tgn:7029392"
    ],
    "tgn:id":2764188,
    "tgn:name":"Wheeler Ranch Prospect",
    "tgn:placetype":[
        "aat:300000390"
    ]
},
  "bbox": [],
  "geometry": {"coordinates":[-119.8333,39.45],"type":"Point"}
}
=======
{"geometry":{"type":"Point","coordinates":[-119.833300,39.450000]},"type":"Feature","properties":{"hierarchy":["tgn:2764188","tgn:1000001","tgn:7012149","tgn:1002999","tgn:7007526","tgn:7029392"],"placetype":["aat:300000390"],"id":2764188,"name:xx":"Wheeler Ranch Prospect"}}
>>>>>>> 03f74aca74312dbeaf24d7e61306dd6a786dc3d0
