{
  "id": 2764188,
  "type": "Feature",
  "properties": {
    "tgn:hierarchy":[
        "tgn:2764188",
        "tgn:1000001",
        "tgn:7012149",
        "tgn:1002999",
        "tgn:7007526",
        "tgn:7029392"
    ],
    "tgn:id":2764188,
    "tgn:name":"Wheeler Ranch Prospect",
    "tgn:placetype":[
        "aat:300000390"
    ]
},
  "bbox": [],
  "geometry": {"coordinates":[-119.8333,39.45],"type":"Point"}
}