{
  "id": 2564153,
  "type": "Feature",
  "properties": {
    "tgn:hierarchy":[
        "tgn:2564153",
        "tgn:1000001",
        "tgn:7012149",
        "tgn:2001708",
        "tgn:7007708",
        "tgn:7029392"
    ],
    "tgn:id":2564153,
    "tgn:name":"P Y X Mine",
    "tgn:placetype":[
        "aat:300000390"
    ]
},
  "bbox": [],
  "geometry": {"coordinates":[-118.4333,44.7167],"type":"Point"}
}