{
  "id": 2419167,
  "type": "Feature",
  "properties": {
    "tgn:hierarchy":[
        "tgn:2419167",
        "tgn:1000001",
        "tgn:7012149",
        "tgn:2001514",
        "tgn:7007709",
        "tgn:7029392"
    ],
    "tgn:id":2419167,
    "tgn:name":"Jamison Mountain",
    "tgn:placetype":[
        "aat:300008798"
    ]
},
  "bbox": [],
  "geometry": {"coordinates":[-81.9333,35.65],"type":"Point"}
}