{
  "id": 2163949,
  "type": "Feature",
  "properties": {
    "tgn:hierarchy":[
        "tgn:2163949",
        "tgn:1000001",
        "tgn:7012149",
        "tgn:2000984",
        "tgn:7007520",
        "tgn:7029392"
    ],
    "tgn:id":2163949,
    "tgn:name":"Berger Pond",
    "tgn:placetype":[
        "aat:300008680"
    ]
},
  "bbox": [],
  "geometry": {"coordinates":[-85.7667,43.6667],"type":"Point"}
}