{
  "id": 2428360,
  "type": "Feature",
  "properties": {
    "tgn:hierarchy":[
        "tgn:2428360",
        "tgn:1000001",
        "tgn:7012149",
        "tgn:7007521",
        "tgn:7029392"
    ],
    "tgn:id":2428360,
    "tgn:name":"Judicial Ditch Number Three",
    "tgn:placetype":[
        "aat:300006075"
    ]
},
  "bbox": [],
  "geometry": {"coordinates":[-96.95,48.5333],"type":"Point"}
}