{
  "id": 7126783,
  "type": "Feature",
  "properties": {
    "tgn:hierarchy":[
        "tgn:7126783",
        "tgn:1000003",
        "tgn:7003685",
        "tgn:7000084",
        "tgn:7029392"
    ],
    "tgn:id":7126783,
    "tgn:name":"Oberhelmsdorf",
    "tgn:placetype":[
        "aat:300008347"
    ]
},
  "bbox": [],
  "geometry": {"coordinates":[14.05,51.033333],"type":"Point"}
}