{
  "id": 1080803,
  "type": "Feature",
  "properties": {
    "tgn:hierarchy":[
        "tgn:1080803",
        "tgn:7000895",
        "tgn:1000004",
        "tgn:7016854",
        "tgn:1000120",
        "tgn:7029392"
    ],
    "tgn:id":1080803,
    "tgn:name":"Misaka",
    "tgn:placetype":[
        "aat:300008347"
    ]
},
  "bbox": [],
  "geometry": {"coordinates":[138.6667,35.6333],"type":"Point"}
}