{
  "id": 7503403,
  "type": "Feature",
  "properties": {
    "tgn:hierarchy":[
        "tgn:7503403",
        "tgn:1000004",
        "tgn:7001009",
        "tgn:1000141",
        "tgn:7029392"
    ],
    "tgn:id":7503403,
    "tgn:name":"Zhaocuo",
    "tgn:placetype":[
        "aat:300008347"
    ]
},
  "bbox": [],
  "geometry": {"coordinates":[120.845932,24.2748],"type":"Point"}
}