{
  "id": 7361945,
  "type": "Feature",
  "properties": {
    "tgn:hierarchy":[
        "tgn:7361945",
        "tgn:7005581",
        "tgn:1000001",
        "tgn:7005560",
        "tgn:7029392"
    ],
    "tgn:id":7361945,
    "tgn:name":"Rancho El Cubano",
    "tgn:placetype":[
        "aat:300000241"
    ]
},
  "bbox": [],
  "geometry": {"coordinates":[-104.733333,28.666667],"type":"Point"}
}