<<<<<<< HEAD
{
  "id": 2339878,
  "type": "Feature",
  "properties": {
    "tgn:hierarchy":[
        "tgn:2339878",
        "tgn:7002659",
        "tgn:1000001",
        "tgn:7012149",
        "tgn:2000039",
        "tgn:7029392"
    ],
    "tgn:id":2339878,
    "tgn:name":"Freeman Hollow",
    "tgn:placetype":[
        "aat:300008761"
    ]
},
  "bbox": [],
  "geometry": {"coordinates":[-87.15,34.3333],"type":"Point"}
}
=======
{"geometry":{"type":"Point","coordinates":[-87.150000,34.333300]},"type":"Feature","properties":{"hierarchy":["tgn:2339878","tgn:7002659","tgn:1000001","tgn:7012149","tgn:2000039","tgn:7029392"],"placetype":["aat:300008761"],"id":2339878,"name:xx":"Freeman Hollow"}}
>>>>>>> 03f74aca74312dbeaf24d7e61306dd6a786dc3d0
