{
  "id": 7161208,
  "type": "Feature",
  "properties": {
    "tgn:hierarchy":[
        "tgn:7161208",
        "tgn:1000003",
        "tgn:7000094",
        "tgn:7000084",
        "tgn:7029392"
    ],
    "tgn:id":7161208,
    "tgn:name":"Hoher Ort",
    "tgn:placetype":[
        "aat:300386846"
    ]
},
  "bbox": [],
  "geometry": {"coordinates":[13.933333,54.033333],"type":"Point"}
}