{
  "id": 2020441,
  "type": "Feature",
  "properties": {
    "tgn:hierarchy":[
        "tgn:2020441",
        "tgn:1000001",
        "tgn:7012149",
        "tgn:2000283",
        "tgn:7007240",
        "tgn:7029392"
    ],
    "tgn:id":2020441,
    "tgn:name":"Moultrie",
    "tgn:placetype":[
        "aat:300008347",
        "aat:300387210"
    ]
},
  "bbox": [],
  "geometry": {"coordinates":[-81.3167,29.8167],"type":"Point"}
}