{
  "id": 7072077,
  "type": "Feature",
  "properties": {
    "tgn:hierarchy":[
        "tgn:7072077",
        "tgn:7003669",
        "tgn:1000003",
        "tgn:7000084",
        "tgn:7029392"
    ],
    "tgn:id":7072077,
    "tgn:name":"Strullendorf",
    "tgn:placetype":[
        "aat:300008347"
    ]
},
  "bbox": [],
  "geometry": {"coordinates":[10.983333,49.833333],"type":"Point"}
}