{
  "id": 2436721,
  "type": "Feature",
  "properties": {
    "tgn:hierarchy":[
        "tgn:2436721",
        "tgn:7006450",
        "tgn:1000001",
        "tgn:7012149",
        "tgn:2000088",
        "tgn:7029392"
    ],
    "tgn:id":2436721,
    "tgn:name":"Kikahe River",
    "tgn:placetype":[
        "aat:300008707"
    ]
},
  "bbox": [],
  "geometry": {"coordinates":[-131.85,56.5167],"type":"Point"}
}