<<<<<<< HEAD
{
  "id": 7367912,
  "type": "Feature",
  "properties": {
    "tgn:hierarchy":[
        "tgn:7367912",
        "tgn:1000001",
        "tgn:1001906",
        "tgn:7005560",
        "tgn:7029392"
    ],
    "tgn:id":7367912,
    "tgn:name":"El Salto",
    "tgn:placetype":[
        "aat:300008347"
    ]
},
  "bbox": [],
  "geometry": {"coordinates":[-105.266667,22.39],"type":"Point"}
}
=======
{"geometry":{"type":"Point","coordinates":[-105.266667,22.390000]},"type":"Feature","properties":{"hierarchy":["tgn:7367912","tgn:1000001","tgn:1001906","tgn:7005560","tgn:7029392"],"placetype":["aat:300008347"],"id":7367912,"name:xx":"El Salto"}}
>>>>>>> 03f74aca74312dbeaf24d7e61306dd6a786dc3d0
