{
  "id": 7518957,
  "type": "Feature",
  "properties": {
    "tgn:hierarchy":[
        "tgn:7518957",
        "tgn:1009227",
        "tgn:1000226",
        "tgn:7016822",
        "tgn:1000006",
        "tgn:7029392"
    ],
    "tgn:id":7518957,
    "tgn:name:en":"Burns, Mount",
    "tgn:placetype":[
        "aat:300008795"
    ]
},
  "bbox": [],
  "geometry": {"coordinates":[167.416667,-45.733333],"type":"Point"}
}