{
  "id": 7481300,
  "type": "Feature",
  "properties": {
    "tgn:hierarchy":[
        "tgn:7481300",
        "tgn:1000004",
        "tgn:7471332",
        "tgn:1000141",
        "tgn:7029392"
    ],
    "tgn:id":7481300,
    "tgn:name":"Dongguang Guoxiao",
    "tgn:placetype":[
        "aat:300006495"
    ]
},
  "bbox": [],
  "geometry": {"coordinates":[121.175278,24.776111],"type":"Point"}
}