<<<<<<< HEAD
{
  "id": 7481300,
  "type": "Feature",
  "properties": {
    "tgn:hierarchy":[
        "tgn:7481300",
        "tgn:1000004",
        "tgn:7471332",
        "tgn:1000141",
        "tgn:7029392"
    ],
    "tgn:id":7481300,
    "tgn:name":"Dongguang Guoxiao",
    "tgn:placetype":[
        "aat:300006495"
    ]
},
  "bbox": [],
  "geometry": {"coordinates":[121.175278,24.776111],"type":"Point"}
}
=======
{"geometry":{"type":"Point","coordinates":[121.175278,24.776111]},"type":"Feature","properties":{"hierarchy":["tgn:7481300","tgn:1000004","tgn:7471332","tgn:1000141","tgn:7029392"],"placetype":["aat:300006495"],"id":7481300,"name:xx":"Dongguang Guoxiao"}}
>>>>>>> 03f74aca74312dbeaf24d7e61306dd6a786dc3d0
