{
  "id": 7335145,
  "type": "Feature",
  "properties": {
    "tgn:hierarchy":[
        "tgn:7335145",
        "tgn:7002825",
        "tgn:7016622",
        "tgn:1000003",
        "tgn:1000095",
        "tgn:7029392"
    ],
    "tgn:id":7335145,
    "tgn:name":"Fuego, Caletas del",
    "tgn:placetype":[
        "aat:300132317"
    ]
},
  "bbox": [],
  "geometry": {"coordinates":[-13.733333,28.866667],"type":"Point"}
}