{
  "id": 2186624,
  "type": "Feature",
  "properties": {
    "tgn:hierarchy":[
        "tgn:2186624",
        "tgn:1000001",
        "tgn:2001260",
        "tgn:7012149",
        "tgn:7007524",
        "tgn:7029392"
    ],
    "tgn:id":2186624,
    "tgn:name":"Boner Knob",
    "tgn:placetype":[
        "aat:300008798"
    ]
},
  "bbox": [],
  "geometry": {"coordinates":[-112.95,45.7333],"type":"Point"}
}