{
  "id": 2231155,
  "type": "Feature",
  "properties": {
    "tgn:hierarchy":[
        "tgn:2231155",
        "tgn:1000001",
        "tgn:7013942",
        "tgn:7012149",
        "tgn:7007517",
        "tgn:7029392"
    ],
    "tgn:id":2231155,
    "tgn:name":"Chadwick Brook",
    "tgn:placetype":[
        "aat:300008699"
    ]
},
  "bbox": [],
  "geometry": {"coordinates":[-72.6833,42.5167],"type":"Point"}
}