{
  "id": 2571768,
  "type": "Feature",
  "properties": {
    "tgn:hierarchy":[
        "tgn:2571768",
        "tgn:1000001",
        "tgn:2002259",
        "tgn:7012149",
        "tgn:7013961",
        "tgn:7029392"
    ],
    "tgn:id":2571768,
    "tgn:name":"Paxton",
    "tgn:placetype":[
        "aat:300008347"
    ]
},
  "bbox": [],
  "geometry": {"coordinates":[-81.1667,38.4833],"type":"Point"}
}