{
  "id": 7332538,
  "type": "Feature",
  "properties": {
    "tgn:hierarchy":[
        "tgn:7332538",
        "tgn:7002808",
        "tgn:7030216",
        "tgn:1000003",
        "tgn:1000095",
        "tgn:7029392"
    ],
    "tgn:id":7332538,
    "tgn:name":"La Ametlla",
    "tgn:placetype":[
        "aat:300008347"
    ]
},
  "bbox": [],
  "geometry": {"coordinates":[2.261242,41.669665],"type":"Point"}
}