{
  "id": 7246901,
  "type": "Feature",
  "properties": {
    "tgn:hierarchy":[
        "tgn:7246901",
        "tgn:7003458",
        "tgn:1000003",
        "tgn:1000063",
        "tgn:7018236",
        "tgn:7029392"
    ],
    "tgn:id":7246901,
    "tgn:name":"Donkbeek",
    "tgn:placetype":[
        "aat:300008699"
    ]
},
  "bbox": [],
  "geometry": {"coordinates":[2.95,51.116667],"type":"Point"}
}