<<<<<<< HEAD
{
  "id": 7478903,
  "type": "Feature",
  "properties": {
    "tgn:hierarchy":[
        "tgn:7478903",
        "tgn:1000004",
        "tgn:7490934",
        "tgn:1000141",
        "tgn:7029392"
    ],
    "tgn:id":7478903,
    "tgn:name":"Guwei",
    "tgn:placetype":[
        "aat:300008347"
    ]
},
  "bbox": [],
  "geometry": {"coordinates":[120.150278,23.120556],"type":"Point"}
}
=======
{"geometry":{"type":"Point","coordinates":[120.150278,23.120556]},"type":"Feature","properties":{"hierarchy":["tgn:7478903","tgn:1000004","tgn:7490934","tgn:1000141","tgn:7029392"],"placetype":["aat:300008347"],"id":7478903,"name:xx":"Guwei"}}
>>>>>>> 03f74aca74312dbeaf24d7e61306dd6a786dc3d0
