{
  "id": 7243448,
  "type": "Feature",
  "properties": {
    "tgn:hierarchy":[
        "tgn:7243448",
        "tgn:7003457",
        "tgn:1000003",
        "tgn:1000063",
        "tgn:7018236",
        "tgn:7029392"
    ],
    "tgn:id":7243448,
    "tgn:name":"Kruisstraat",
    "tgn:placetype":[
        "aat:300008347"
    ]
},
  "bbox": [],
  "geometry": {"coordinates":[3.833333,50.783333],"type":"Point"}
}