{
  "id": 2029116,
  "type": "Feature",
  "properties": {
    "tgn:hierarchy":[
        "tgn:2029116",
        "tgn:1000001",
        "tgn:7012149",
        "tgn:2000531",
        "tgn:7007251",
        "tgn:7029392"
    ],
    "tgn:id":2029116,
    "tgn:name":"Modena",
    "tgn:placetype":[
        "aat:300008347",
        "aat:300387210"
    ]
},
  "bbox": [],
  "geometry": {"coordinates":[-89.75,41.1333],"type":"Point"}
}