{
  "id": 7073663,
  "type": "Feature",
  "properties": {
    "tgn:hierarchy":[
        "tgn:7073663",
        "tgn:1000003",
        "tgn:7003688",
        "tgn:7000084",
        "tgn:7029392"
    ],
    "tgn:id":7073663,
    "tgn:name":"S\u00fcderhastedt",
    "tgn:placetype":[
        "aat:300008347"
    ]
},
  "bbox": [],
  "geometry": {"coordinates":[9.216667,54.05],"type":"Point"}
}