{
  "id": 2254758,
  "type": "Feature",
  "properties": {
    "tgn:hierarchy":[
        "tgn:2254758",
        "tgn:1000001",
        "tgn:7012149",
        "tgn:2002009",
        "tgn:7007826",
        "tgn:7029392"
    ],
    "tgn:id":2254758,
    "tgn:name":"Coon Swamp",
    "tgn:placetype":[
        "aat:300008905"
    ]
},
  "bbox": [],
  "geometry": {"coordinates":[-94.05,30.2667],"type":"Point"}
}