<<<<<<< HEAD
{
  "id": 2254758,
  "type": "Feature",
  "properties": {
    "tgn:hierarchy":[
        "tgn:2254758",
        "tgn:1000001",
        "tgn:7012149",
        "tgn:2002009",
        "tgn:7007826",
        "tgn:7029392"
    ],
    "tgn:id":2254758,
    "tgn:name":"Coon Swamp",
    "tgn:placetype":[
        "aat:300008905"
    ]
},
  "bbox": [],
  "geometry": {"coordinates":[-94.05,30.2667],"type":"Point"}
}
=======
{"geometry":{"type":"Point","coordinates":[-94.050000,30.266700]},"type":"Feature","properties":{"hierarchy":["tgn:2254758","tgn:1000001","tgn:7012149","tgn:2002009","tgn:7007826","tgn:7029392"],"placetype":["aat:300008905"],"id":2254758,"name:xx":"Coon Swamp"}}
>>>>>>> 03f74aca74312dbeaf24d7e61306dd6a786dc3d0
