{
  "id": 2507359,
  "type": "Feature",
  "properties": {
    "tgn:hierarchy":[
        "tgn:2507359",
        "tgn:1000001",
        "tgn:2001418",
        "tgn:7012149",
        "tgn:7007526",
        "tgn:7029392"
    ],
    "tgn:id":2507359,
    "tgn:name":"Mexican Mine",
    "tgn:placetype":[
        "aat:300000390"
    ]
},
  "bbox": [],
  "geometry": {"coordinates":[-116.6333,36.7667],"type":"Point"}
}