{
  "id": 2618479,
  "type": "Feature",
  "properties": {
    "tgn:hierarchy":[
        "tgn:2618479",
        "tgn:1000001",
        "tgn:2002258",
        "tgn:7012149",
        "tgn:7013961",
        "tgn:7029392"
    ],
    "tgn:id":2618479,
    "tgn:name":"Right Fork Crummis Creek",
    "tgn:placetype":[
        "aat:300008706"
    ]
},
  "bbox": [],
  "geometry": {"coordinates":[-81.0333,38.75],"type":"Point"}
}