{
  "id": 2543847,
  "type": "Feature",
  "properties": {
    "tgn:hierarchy":[
        "tgn:2543847",
        "tgn:1000001",
        "tgn:7016172",
        "tgn:2000114",
        "tgn:7012149",
        "tgn:7029392"
    ],
    "tgn:id":2543847,
    "tgn:name":"North Boat Ditch",
    "tgn:placetype":[
        "aat:300006075"
    ]
},
  "bbox": [],
  "geometry": {"coordinates":[-93.1333,33.9833],"type":"Point"}
}