{
  "id": 2752139,
  "type": "Feature",
  "properties": {
    "tgn:hierarchy":[
        "tgn:2752139",
        "tgn:1000001",
        "tgn:7012149",
        "tgn:2001504",
        "tgn:7007709",
        "tgn:7029392"
    ],
    "tgn:id":2752139,
    "tgn:name":"Wash Creek",
    "tgn:placetype":[
        "aat:300008706"
    ]
},
  "bbox": [],
  "geometry": {"coordinates":[-82.4833,35.3167],"type":"Point"}
}