<<<<<<< HEAD
{
  "id": 7175603,
  "type": "Feature",
  "properties": {
    "tgn:hierarchy":[
        "tgn:7175603",
        "tgn:1000003",
        "tgn:7003685",
        "tgn:7000084",
        "tgn:7029392"
    ],
    "tgn:id":7175603,
    "tgn:name":"Gro\u00dfw\u00f6lkau",
    "tgn:placetype":[
        "aat:300008347"
    ]
},
  "bbox": [],
  "geometry": {"coordinates":[12.483333,51.5],"type":"Point"}
}
=======
{"geometry":{"type":"Point","coordinates":[12.483333,51.500000]},"type":"Feature","properties":{"hierarchy":["tgn:7175603","tgn:1000003","tgn:7003685","tgn:7000084","tgn:7029392"],"placetype":["aat:300008347"],"id":7175603,"name:xx":"Gro\u00dfw\u00f6lkau"}}
>>>>>>> 03f74aca74312dbeaf24d7e61306dd6a786dc3d0
