<<<<<<< HEAD
{
  "id": 2765793,
  "type": "Feature",
  "properties": {
    "tgn:hierarchy":[
        "tgn:2765793",
        "tgn:1000001",
        "tgn:7012149",
        "tgn:7007566",
        "tgn:7029392"
    ],
    "tgn:id":2765793,
    "tgn:name":"White Draw",
    "tgn:placetype":[
        "aat:300008761"
    ]
},
  "bbox": [],
  "geometry": {"coordinates":[-103.9333,34.1167],"type":"Point"}
}
=======
{"geometry":{"type":"Point","coordinates":[-103.933300,34.116700]},"type":"Feature","properties":{"hierarchy":["tgn:2765793","tgn:1000001","tgn:7012149","tgn:7007566","tgn:7029392"],"placetype":["aat:300008761"],"id":2765793,"name:xx":"White Draw"}}
>>>>>>> 03f74aca74312dbeaf24d7e61306dd6a786dc3d0
