{
  "id": 2275512,
  "type": "Feature",
  "properties": {
    "tgn:hierarchy":[
        "tgn:2275512",
        "tgn:1000001",
        "tgn:2124001",
        "tgn:7012149",
        "tgn:7007516",
        "tgn:7029392"
    ],
    "tgn:id":2275512,
    "tgn:name":"Danville",
    "tgn:placetype":[
        "aat:300008347"
    ]
},
  "bbox": [],
  "geometry": {"coordinates":[-76.9167,38.6833],"type":"Point"}
}