{
  "id": 7264376,
  "type": "Feature",
  "properties": {
    "tgn:concordances":{
        "gn:id":"2752365"
    },
    "tgn:hierarchy":[
        "tgn:7264376",
        "tgn:7003616",
        "tgn:1000003",
        "tgn:7016845",
        "tgn:7029392"
    ],
    "tgn:id":7264376,
    "tgn:name:nl":"Koufurderrige",
    "tgn:placetype":[
        "aat:300008347"
    ]
},
  "bbox": [],
  "geometry": {"coordinates":[5.65,52.95],"type":"Point"}
}