{
  "id": 2378558,
  "type": "Feature",
  "properties": {
    "tgn:hierarchy":[
        "tgn:2378558",
        "tgn:1000001",
        "tgn:7012149",
        "tgn:2002127",
        "tgn:7007827",
        "tgn:7029392"
    ],
    "tgn:id":2378558,
    "tgn:name":"Harrison Peak",
    "tgn:placetype":[
        "aat:300008798"
    ]
},
  "bbox": [],
  "geometry": {"coordinates":[-113.5333,37.4833],"type":"Point"}
}