{
  "id": 2686852,
  "type": "Feature",
  "properties": {
    "tgn:hierarchy":[
        "tgn:2686852",
        "tgn:1000001",
        "tgn:7012149",
        "tgn:1002516",
        "tgn:7007255",
        "tgn:7029392"
    ],
    "tgn:id":2686852,
    "tgn:name":"Spring Ditch",
    "tgn:placetype":[
        "aat:300006075"
    ]
},
  "bbox": [],
  "geometry": {"coordinates":[-85.6667,38.15],"type":"Point"}
}