{
  "id": 7324181,
  "type": "Feature",
  "properties": {
    "tgn:hierarchy":[
        "tgn:7324181",
        "tgn:7001158",
        "tgn:7002848",
        "tgn:1000003",
        "tgn:1000095",
        "tgn:7029392"
    ],
    "tgn:id":7324181,
    "tgn:name":"Sang\u00fceno, Arroyo",
    "tgn:placetype":[
        "aat:300008699"
    ]
},
  "bbox": [],
  "geometry": {"coordinates":[-4.633333,41.516667],"type":"Point"}
}