{
  "id": 7416116,
  "type": "Feature",
  "properties": {
    "tgn:hierarchy":[
        "tgn:7416116",
        "tgn:7005584",
        "tgn:1000001",
        "tgn:7005560",
        "tgn:7029392"
    ],
    "tgn:id":7416116,
    "tgn:name":"Presa San Bartolo",
    "tgn:placetype":[
        "aat:300006191"
    ]
},
  "bbox": [],
  "geometry": {"coordinates":[-101.031111,21.601389],"type":"Point"}
}