{
  "id": 2436681,
  "type": "Feature",
  "properties": {
    "tgn:hierarchy":[
        "tgn:2436681",
        "tgn:7006450",
        "tgn:1000001",
        "tgn:7012149",
        "tgn:2000079",
        "tgn:7029392"
    ],
    "tgn:id":2436681,
    "tgn:name":"Kigezruk Creek",
    "tgn:placetype":[
        "aat:300008706"
    ]
},
  "bbox": [],
  "geometry": {"coordinates":[-167.65,65.5333],"type":"Point"}
}