{
  "id": 2352667,
  "type": "Feature",
  "properties": {
    "tgn:hierarchy":[
        "tgn:2352667",
        "tgn:1000001",
        "tgn:7006451",
        "tgn:2000094",
        "tgn:7012149",
        "tgn:7029392"
    ],
    "tgn:id":2352667,
    "tgn:name":"Goat Spring",
    "tgn:placetype":[
        "aat:300008697"
    ]
},
  "bbox": [],
  "geometry": {"coordinates":[-109.7667,33.0667],"type":"Point"}
}