{
  "id": 2455305,
  "type": "Feature",
  "properties": {
    "tgn:hierarchy":[
        "tgn:2455305",
        "tgn:1000001",
        "tgn:7012149",
        "tgn:7007158",
        "tgn:2000243",
        "tgn:7029392"
    ],
    "tgn:id":2455305,
    "tgn:name":"Little Flat Tops",
    "tgn:placetype":[
        "aat:300008798"
    ]
},
  "bbox": [],
  "geometry": {"coordinates":[-107.0333,40.0833],"type":"Point"}
}