{
  "id": 2544405,
  "type": "Feature",
  "properties": {
    "tgn:hierarchy":[
        "tgn:2544405",
        "tgn:1000001",
        "tgn:7012149",
        "tgn:7007254",
        "tgn:7029392"
    ],
    "tgn:id":2544405,
    "tgn:name":"North Branch Verdigris River",
    "tgn:placetype":[
        "aat:300008707"
    ]
},
  "bbox": [],
  "geometry": {"coordinates":[-96.35,38.0833],"type":"Point"}
}