{
  "id": 7537014,
  "type": "Feature",
  "properties": {
    "tgn:hierarchy":[
        "tgn:7537014",
        "tgn:7001242",
        "tgn:7016833",
        "tgn:1001079",
        "tgn:7029392"
    ],
    "tgn:id":7537014,
    "tgn:name:en":"S\u0101niyat al \u1e28\u0101jj Khal\u012bl",
    "tgn:placetype":[
        "aat:300006207"
    ]
},
  "bbox": [],
  "geometry": {"coordinates":[29.766667,30.983333],"type":"Point"}
}