{
  "id": 2025994,
  "type": "Feature",
  "properties": {
    "tgn:hierarchy":[
        "tgn:2025994",
        "tgn:1000001",
        "tgn:7012149",
        "tgn:2000493",
        "tgn:7007250",
        "tgn:7029392"
    ],
    "tgn:id":2025994,
    "tgn:name":"Peavey",
    "tgn:placetype":[
        "aat:300387016"
    ]
},
  "bbox": [],
  "geometry": {"coordinates":[-114.65,42.5833],"type":"Point"}
}