{
  "id": 2708540,
  "type": "Feature",
  "properties": {
    "tgn:hierarchy":[
        "tgn:2708540",
        "tgn:7014651",
        "tgn:1000001",
        "tgn:7012149",
        "tgn:7007516",
        "tgn:7029392"
    ],
    "tgn:id":2708540,
    "tgn:name":"Sycamore Point",
    "tgn:placetype":[
        "aat:300008850"
    ]
},
  "bbox": [],
  "geometry": {"coordinates":[-76.4667,38.9667],"type":"Point"}
}