{
  "id": 7439952,
  "type": "Feature",
  "properties": {
    "tgn:hierarchy":[
        "tgn:7439952",
        "tgn:7005584",
        "tgn:1000001",
        "tgn:7005560",
        "tgn:7029392"
    ],
    "tgn:id":7439952,
    "tgn:name":"San Mart\u00edn",
    "tgn:placetype":[
        "aat:300008347"
    ]
},
  "bbox": [],
  "geometry": {"coordinates":[-100.583333,20.233333],"type":"Point"}
}