{
  "id": 1095244,
  "type": "Feature",
  "properties": {
    "tgn:hierarchy":[
        "tgn:1095244",
        "tgn:7001242",
        "tgn:7016833",
        "tgn:1001088",
        "tgn:7029392"
    ],
    "tgn:id":1095244,
    "tgn:name:en":"Al Basqal\u016bn",
    "tgn:placetype":[
        "aat:300008347"
    ]
},
  "bbox": [],
  "geometry": {"coordinates":[30.738254,28.70441],"type":"Point"}
}