{
  "id": 7285820,
  "type": "Feature",
  "properties": {
    "tgn:hierarchy":[
        "tgn:7285820",
        "tgn:1001657",
        "tgn:1000049",
        "tgn:1000002",
        "tgn:7029392"
    ],
    "tgn:id":7285820,
    "tgn:name":"Piuquenes, Morro",
    "tgn:placetype":[
        "aat:300008798"
    ]
},
  "bbox": [],
  "geometry": {"coordinates":[-70.45,-32.216667],"type":"Point"}
}