{
  "id": 7218842,
  "type": "Feature",
  "properties": {
    "tgn:hierarchy":[
        "tgn:7218842",
        "tgn:7011161",
        "tgn:7002674",
        "tgn:1000003",
        "tgn:1000074",
        "tgn:7029392"
    ],
    "tgn:id":7218842,
    "tgn:name":"S\u00f3mata",
    "tgn:placetype":[
        "aat:300387200"
    ]
},
  "bbox": [],
  "geometry": {"coordinates":[26.057222,38.251389],"type":"Point"}
}