<<<<<<< HEAD
{
  "id": 7374336,
  "type": "Feature",
  "properties": {
    "tgn:hierarchy":[
        "tgn:7374336",
        "tgn:1000001",
        "tgn:7005590",
        "tgn:7005560",
        "tgn:7029392"
    ],
    "tgn:id":7374336,
    "tgn:name":"La Beata, Cerro",
    "tgn:placetype":[
        "aat:300008795"
    ]
},
  "bbox": [],
  "geometry": {"coordinates":[-102.2,19.95],"type":"Point"}
}
=======
{"geometry":{"type":"Point","coordinates":[-102.200000,19.950000]},"type":"Feature","properties":{"hierarchy":["tgn:7374336","tgn:1000001","tgn:7005590","tgn:7005560","tgn:7029392"],"placetype":["aat:300008795"],"id":7374336,"name:xx":"La Beata, Cerro"}}
>>>>>>> 03f74aca74312dbeaf24d7e61306dd6a786dc3d0
