{
  "id": 7468999,
  "type": "Feature",
  "properties": {
    "tgn:hierarchy":[
        "tgn:7468999",
        "tgn:1000004",
        "tgn:7001009",
        "tgn:1000141",
        "tgn:7029392"
    ],
    "tgn:id":7468999,
    "tgn:name":"Xianggu Qiao",
    "tgn:placetype":[
        "aat:300007836"
    ]
},
  "bbox": [],
  "geometry": {"coordinates":[121.325833,24.356667],"type":"Point"}
}