{
  "id": 5000440,
  "type": "Feature",
  "properties": {
    "tgn:hierarchy":[
        "tgn:5000440",
        "tgn:7002444",
        "tgn:1000003",
        "tgn:7008591",
        "tgn:7029392"
    ],
    "tgn:id":5000440,
    "tgn:name":"Clackmannanshire",
    "tgn:placetype":[
        "aat:300387145",
        "aat:300000771",
        "aat:300387071"
    ]
},
  "bbox": [],
  "geometry": {"coordinates":[-3.9167,56.0833],"type":"Point"}
}