{
  "id": 2520163,
  "type": "Feature",
  "properties": {
    "tgn:hierarchy":[
        "tgn:2520163",
        "tgn:1000001",
        "tgn:7012149",
        "tgn:2001718",
        "tgn:7007708",
        "tgn:7029392"
    ],
    "tgn:id":2520163,
    "tgn:name":"Moltham Reservoir Five",
    "tgn:placetype":[
        "aat:300006191"
    ]
},
  "bbox": [],
  "geometry": {"coordinates":[-117.8667,44.25],"type":"Point"}
}