{
  "id": 2366691,
  "type": "Feature",
  "properties": {
    "tgn:hierarchy":[
        "tgn:2366691",
        "tgn:1000001",
        "tgn:1002229",
        "tgn:7012149",
        "tgn:7007710",
        "tgn:7029392"
    ],
    "tgn:id":2366691,
    "tgn:name":"Grindstone Hollow",
    "tgn:placetype":[
        "aat:300008761"
    ]
},
  "bbox": [],
  "geometry": {"coordinates":[-78.15,41.35],"type":"Point"}
}