{
  "id": 7502120,
  "type": "Feature",
  "properties": {
    "tgn:hierarchy":[
        "tgn:7502120",
        "tgn:7001004",
        "tgn:1000004",
        "tgn:1000141",
        "tgn:7029392"
    ],
    "tgn:id":7502120,
    "tgn:name":"Meilan Erhao Diaoqiao",
    "tgn:placetype":[
        "aat:300007836"
    ]
},
  "bbox": [],
  "geometry": {"coordinates":[120.809722,23.233333],"type":"Point"}
}