{
  "id": 2212388,
  "type": "Feature",
  "properties": {
    "tgn:hierarchy":[
        "tgn:2212388",
        "tgn:1000001",
        "tgn:7012149",
        "tgn:2001666",
        "tgn:7007707",
        "tgn:7029392"
    ],
    "tgn:id":2212388,
    "tgn:name":"Byars Lake",
    "tgn:placetype":[
        "aat:300006191"
    ]
},
  "bbox": [],
  "geometry": {"coordinates":[-97.0667,34.85],"type":"Point"}
}