{
  "id": 7001332,
  "type": "Feature",
  "properties": {
    "tgn:hierarchy":[
        "tgn:7001332",
        "tgn:1001285",
        "tgn:1000004",
        "tgn:1000122",
        "tgn:7029392"
    ],
    "tgn:id":7001332,
    "tgn:name":"Ch\u014fngjin",
    "tgn:placetype":[
        "aat:300008347",
        "aat:300008389",
        "aat:300387223"
    ]
},
  "bbox": [],
  "geometry": {"coordinates":[129.9167,41.8333],"type":"Point"}
}