{
  "id": 7325594,
  "type": "Feature",
  "properties": {
    "tgn:hierarchy":[
        "tgn:7325594",
        "tgn:7002839",
        "tgn:7001158",
        "tgn:1000003",
        "tgn:1000095",
        "tgn:7029392"
    ],
    "tgn:id":7325594,
    "tgn:name":"Santiuste de San Juan Bautista",
    "tgn:placetype":[
        "aat:300008347"
    ]
},
  "bbox": [],
  "geometry": {"coordinates":[-4.566667,41.15],"type":"Point"}
}