{
  "id": 2251087,
  "type": "Feature",
  "properties": {
    "tgn:hierarchy":[
        "tgn:2251087",
        "tgn:1000001",
        "tgn:7012149",
        "tgn:2001237",
        "tgn:7007523",
        "tgn:7029392"
    ],
    "tgn:id":2251087,
    "tgn:name":"Colvin Bay",
    "tgn:placetype":[
        "aat:300132316"
    ]
},
  "bbox": [],
  "geometry": {"coordinates":[-90.9167,36.75],"type":"Point"}
}