{
  "id": 2426009,
  "type": "Feature",
  "properties": {
    "tgn:hierarchy":[
        "tgn:2426009",
        "tgn:7002659",
        "tgn:1000001",
        "tgn:7012149",
        "tgn:2000060",
        "tgn:7029392"
    ],
    "tgn:id":2426009,
    "tgn:name":"Jones Blue Eye Lake",
    "tgn:placetype":[
        "aat:300006191"
    ]
},
  "bbox": [],
  "geometry": {"coordinates":[-86.05,33.6333],"type":"Point"}
}