{
  "id": 1031782,
  "type": "Feature",
  "properties": {
    "tgn:hierarchy":[
        "tgn:1031782",
        "tgn:1000003",
        "tgn:1000070",
        "tgn:7002897",
        "tgn:7029392"
    ],
    "tgn:id":1031782,
    "tgn:name":"Andr\u00e9zieux Bouth\u00e9on",
    "tgn:placetype":[
        "aat:300008347"
    ]
},
  "bbox": [],
  "geometry": {"coordinates":[4.3667,45.5333],"type":"Point"}
}