<<<<<<< HEAD
{
  "id": 7172396,
  "type": "Feature",
  "properties": {
    "tgn:hierarchy":[
        "tgn:7172396",
        "tgn:1000003",
        "tgn:7003677",
        "tgn:7000084",
        "tgn:7029392"
    ],
    "tgn:id":7172396,
    "tgn:name":"Hellkuhl",
    "tgn:placetype":[
        "aat:300000206"
    ]
},
  "bbox": [],
  "geometry": {"coordinates":[7.4,51.766667],"type":"Point"}
}
=======
{"geometry":{"type":"Point","coordinates":[7.400000,51.766667]},"type":"Feature","properties":{"hierarchy":["tgn:7172396","tgn:1000003","tgn:7003677","tgn:7000084","tgn:7029392"],"placetype":["aat:300000206"],"id":7172396,"name:xx":"Hellkuhl"}}
>>>>>>> 03f74aca74312dbeaf24d7e61306dd6a786dc3d0
