{
  "id": 7210899,
  "type": "Feature",
  "properties": {
    "tgn:hierarchy":[
        "tgn:7210899",
        "tgn:1000003",
        "tgn:7003682",
        "tgn:7000084",
        "tgn:7029392"
    ],
    "tgn:id":7210899,
    "tgn:name":"Beindersheim",
    "tgn:placetype":[
        "aat:300008347"
    ]
},
  "bbox": [],
  "geometry": {"coordinates":[8.319444,49.560556],"type":"Point"}
}