{
  "id": 7105522,
  "type": "Feature",
  "properties": {
    "tgn:hierarchy":[
        "tgn:7105522",
        "tgn:1000003",
        "tgn:7003678",
        "tgn:7000084",
        "tgn:7029392"
    ],
    "tgn:id":7105522,
    "tgn:name":"Schien Berg",
    "tgn:placetype":[
        "aat:300008777"
    ]
},
  "bbox": [],
  "geometry": {"coordinates":[10.116667,51.05],"type":"Point"}
}