{
  "id": 7537780,
  "type": "Feature",
  "properties": {
    "tgn:hierarchy":[
        "tgn:7537780",
        "tgn:7001242",
        "tgn:7001311",
        "tgn:7016833",
        "tgn:7029392"
    ],
    "tgn:id":7537780,
    "tgn:name:en":"Ranga, W\u00e2di",
    "tgn:placetype":[
        "aat:300379998"
    ]
},
  "bbox": [],
  "geometry": {"coordinates":[35.23271,24.395771],"type":"Point"}
}