{
  "id": 7412633,
  "type": "Feature",
  "properties": {
    "tgn:hierarchy":[
        "tgn:7412633",
        "tgn:1000001",
        "tgn:7005598",
        "tgn:7005560",
        "tgn:7029392"
    ],
    "tgn:id":7412633,
    "tgn:name":"Axotla del Monte",
    "tgn:placetype":[
        "aat:300008347"
    ]
},
  "bbox": [],
  "geometry": {"coordinates":[-98.170833,19.25],"type":"Point"}
}