{
  "id": 2489004,
  "type": "Feature",
  "properties": {
    "tgn:hierarchy":[
        "tgn:2489004",
        "tgn:1000001",
        "tgn:7012149",
        "tgn:1002350",
        "tgn:7007157",
        "tgn:7029392"
    ],
    "tgn:id":2489004,
    "tgn:name":"Maine Bar Canyon",
    "tgn:placetype":[
        "aat:300008761"
    ]
},
  "bbox": [],
  "geometry": {"coordinates":[-120.9333,38.9167],"type":"Point"}
}