{
  "id": 7531907,
  "type": "Feature",
  "properties": {
    "tgn:hierarchy":[
        "tgn:7531907",
        "tgn:7001242",
        "tgn:7016833",
        "tgn:1001091",
        "tgn:7029392"
    ],
    "tgn:id":7531907,
    "tgn:name":"Kan\u012bsat M\u0101rm\u012bn\u0101 al 'Aj\u0101yb\u012b",
    "tgn:placetype":[
        "aat:300007466"
    ]
},
  "bbox": [],
  "geometry": {"coordinates":[31.246121,30.064325],"type":"Point"}
}