{
  "id": 2230603,
  "type": "Feature",
  "properties": {
    "tgn:hierarchy":[
        "tgn:2230603",
        "tgn:1000001",
        "tgn:7012149",
        "tgn:1002779",
        "tgn:7007710",
        "tgn:7029392"
    ],
    "tgn:id":2230603,
    "tgn:name":"Center Ridge",
    "tgn:placetype":[
        "aat:300266640"
    ]
},
  "bbox": [],
  "geometry": {"coordinates":[-77.5333,40.2667],"type":"Point"}
}