{
  "id": 7360791,
  "type": "Feature",
  "properties": {
    "tgn:hierarchy":[
        "tgn:7360791",
        "tgn:1001853",
        "tgn:1000001",
        "tgn:7005560",
        "tgn:7029392"
    ],
    "tgn:id":7360791,
    "tgn:name":"Ejido El Cinco",
    "tgn:placetype":[
        "aat:300008347"
    ]
},
  "bbox": [],
  "geometry": {"coordinates":[-101.633333,25.183333],"type":"Point"}
}