<<<<<<< HEAD
{
  "id": 7360791,
  "type": "Feature",
  "properties": {
    "tgn:hierarchy":[
        "tgn:7360791",
        "tgn:1001853",
        "tgn:1000001",
        "tgn:7005560",
        "tgn:7029392"
    ],
    "tgn:id":7360791,
    "tgn:name":"Ejido El Cinco",
    "tgn:placetype":[
        "aat:300008347"
    ]
},
  "bbox": [],
  "geometry": {"coordinates":[-101.633333,25.183333],"type":"Point"}
}
=======
{"geometry":{"type":"Point","coordinates":[-101.633333,25.183333]},"type":"Feature","properties":{"hierarchy":["tgn:7360791","tgn:1001853","tgn:1000001","tgn:7005560","tgn:7029392"],"placetype":["aat:300008347"],"id":7360791,"name:xx":"Ejido El Cinco"}}
>>>>>>> 03f74aca74312dbeaf24d7e61306dd6a786dc3d0
