{
  "id": 2092128,
  "type": "Feature",
  "properties": {
    "tgn:hierarchy":[
        "tgn:2092128",
        "tgn:1000001",
        "tgn:7012149",
        "tgn:1002682",
        "tgn:7007710",
        "tgn:7029392"
    ],
    "tgn:id":2092128,
    "tgn:name":"Pocono Farms East",
    "tgn:placetype":[
        "aat:300008347"
    ]
},
  "bbox": [],
  "geometry": {"coordinates":[-75.3333,41.15],"type":"Point"}
}