{
  "id": 2140865,
  "type": "Feature",
  "properties": {
    "tgn:hierarchy":[
        "tgn:2140865",
        "tgn:1000001",
        "tgn:7012149",
        "tgn:2001502",
        "tgn:7007709",
        "tgn:7029392"
    ],
    "tgn:id":2140865,
    "tgn:name":"Avents Creek",
    "tgn:placetype":[
        "aat:300008706"
    ]
},
  "bbox": [],
  "geometry": {"coordinates":[-78.8833,35.5333],"type":"Point"}
}