{
  "id": 2041680,
  "type": "Feature",
  "properties": {
    "tgn:hierarchy":[
        "tgn:2041680",
        "tgn:1000001",
        "tgn:7012149",
        "tgn:2000845",
        "tgn:7007255",
        "tgn:7029392"
    ],
    "tgn:id":2041680,
    "tgn:name":"Trenton",
    "tgn:placetype":[
        "aat:300008347"
    ]
},
  "bbox": [],
  "geometry": {"coordinates":[-87.25,36.7167],"type":"Point"}
}