{
  "id": 2359172,
  "type": "Feature",
  "properties": {
    "tgn:hierarchy":[
        "tgn:2359172",
        "tgn:1000001",
        "tgn:7006451",
        "tgn:7012149",
        "tgn:2000097",
        "tgn:7029392"
    ],
    "tgn:id":2359172,
    "tgn:name":"Granite Reef Estates",
    "tgn:placetype":[
        "aat:300008347"
    ]
},
  "bbox": [],
  "geometry": {"coordinates":[-111.6833,33.4333],"type":"Point"}
}