<<<<<<< HEAD
{
  "id": 7026359,
  "type": "Feature",
  "properties": {
    "tgn:hierarchy":[
        "tgn:7026359",
        "tgn:7002445",
        "tgn:1000003",
        "tgn:7008131",
        "tgn:7008591",
        "tgn:7029392"
    ],
    "tgn:id":7026359,
    "tgn:name:en":"Tillingham",
    "tgn:placetype":[
        "aat:300008347",
        "aat:300008372"
    ]
},
  "bbox": [],
  "geometry": {"coordinates":[0.883333,51.683333],"type":"Point"}
}
=======
{"geometry":{"type":"Point","coordinates":[0.883333,51.683333]},"type":"Feature","properties":{"hierarchy":["tgn:7026359","tgn:7002445","tgn:1000003","tgn:7008131","tgn:7008591","tgn:7029392"],"placetype":["aat:300008347","aat:300008372"],"name:en":"Tillingham","id":7026359}}
>>>>>>> 03f74aca74312dbeaf24d7e61306dd6a786dc3d0
