{
  "id": 1119630,
  "type": "Feature",
  "properties": {
    "tgn:hierarchy":[
        "tgn:1119630",
        "tgn:7017440",
        "tgn:1000001",
        "tgn:7004643",
        "tgn:7029392"
    ],
    "tgn:id":1119630,
    "tgn:name":"Coamo, Lago",
    "tgn:placetype":[
        "aat:300006191"
    ]
},
  "bbox": [],
  "geometry": {"coordinates":[-66.3833,18.0167],"type":"Point"}
}