{
  "id": 2776568,
  "type": "Feature",
  "properties": {
    "tgn:hierarchy":[
        "tgn:2776568",
        "tgn:1000001",
        "tgn:1002194",
        "tgn:7012149",
        "tgn:7007710",
        "tgn:7029392"
    ],
    "tgn:id":2776568,
    "tgn:name":"Windham",
    "tgn:placetype":[
        "aat:300008347"
    ]
},
  "bbox": [],
  "geometry": {"coordinates":[-76.2833,41.9667],"type":"Point"}
}