{
  "id": 2318181,
  "type": "Feature",
  "properties": {
    "tgn:hierarchy":[
        "tgn:2318181",
        "tgn:1000001",
        "tgn:7006451",
        "tgn:7012149",
        "tgn:2000097",
        "tgn:7029392"
    ],
    "tgn:id":2318181,
    "tgn:name":"Enterprise Canal",
    "tgn:placetype":[
        "aat:300006075"
    ]
},
  "bbox": [],
  "geometry": {"coordinates":[-112.75,33.1833],"type":"Point"}
}