{
  "id": 2040568,
  "type": "Feature",
  "properties": {
    "tgn:hierarchy":[
        "tgn:2040568",
        "tgn:1000001",
        "tgn:7012149",
        "tgn:2000787",
        "tgn:7007255",
        "tgn:7029392"
    ],
    "tgn:id":2040568,
    "tgn:name":"Oak Ridge",
    "tgn:placetype":[
        "aat:300008347",
        "aat:300387210"
    ]
},
  "bbox": [],
  "geometry": {"coordinates":[-86.2333,37.2833],"type":"Point"}
}