<<<<<<< HEAD
{
  "id": 2258434,
  "type": "Feature",
  "properties": {
    "tgn:hierarchy":[
        "tgn:2258434",
        "tgn:1000001",
        "tgn:2002261",
        "tgn:7012149",
        "tgn:7013961",
        "tgn:7029392"
    ],
    "tgn:id":2258434,
    "tgn:name":"Cotton Hill",
    "tgn:placetype":[
        "aat:300008347"
    ]
},
  "bbox": [],
  "geometry": {"coordinates":[-81.1333,38.1],"type":"Point"}
}
=======
{"geometry":{"type":"Point","coordinates":[-81.133300,38.100000]},"type":"Feature","properties":{"hierarchy":["tgn:2258434","tgn:1000001","tgn:2002261","tgn:7012149","tgn:7013961","tgn:7029392"],"placetype":["aat:300008347"],"id":2258434,"name:xx":"Cotton Hill"}}
>>>>>>> 03f74aca74312dbeaf24d7e61306dd6a786dc3d0
