{
  "id": 2189030,
  "type": "Feature",
  "properties": {
    "tgn:hierarchy":[
        "tgn:2189030",
        "tgn:1000001",
        "tgn:7012149",
        "tgn:1002468",
        "tgn:7007252",
        "tgn:7029392"
    ],
    "tgn:id":2189030,
    "tgn:name":"Boulder Run",
    "tgn:placetype":[
        "aat:300008699"
    ]
},
  "bbox": [],
  "geometry": {"coordinates":[-85.3667,39.8833],"type":"Point"}
}