{
  "id": 7351483,
  "type": "Feature",
  "properties": {
    "tgn:hierarchy":[
        "tgn:7351483",
        "tgn:1001836",
        "tgn:1000001",
        "tgn:7005560",
        "tgn:7029392"
    ],
    "tgn:id":7351483,
    "tgn:name":"Arranca Cabellos, Punta",
    "tgn:placetype":[
        "aat:300386846"
    ]
},
  "bbox": [],
  "geometry": {"coordinates":[-110.3125,24.359444],"type":"Point"}
}