{
  "id": 2604125,
  "type": "Feature",
  "properties": {
    "tgn:hierarchy":[
        "tgn:2604125",
        "tgn:1000001",
        "tgn:2001435",
        "tgn:7012149",
        "tgn:7007566",
        "tgn:7029392"
    ],
    "tgn:id":2604125,
    "tgn:name":"Quirke Lake",
    "tgn:placetype":[
        "aat:300008680"
    ]
},
  "bbox": [],
  "geometry": {"coordinates":[-106.4167,32.0167],"type":"Point"}
}