{
  "id": 2249368,
  "type": "Feature",
  "properties": {
    "tgn:hierarchy":[
        "tgn:2249368",
        "tgn:1000001",
        "tgn:7016172",
        "tgn:7012149",
        "tgn:2000130",
        "tgn:7029392"
    ],
    "tgn:id":2249368,
    "tgn:name":"Coleman Creek",
    "tgn:placetype":[
        "aat:300008706"
    ]
},
  "bbox": [],
  "geometry": {"coordinates":[-93.0667,34.65],"type":"Point"}
}