{
  "id": 1138697,
  "type": "Feature",
  "properties": {
    "tgn:hierarchy":[
        "tgn:1138697",
        "tgn:1000004",
        "tgn:1003379",
        "tgn:7018214",
        "tgn:7002435",
        "tgn:7029392"
    ],
    "tgn:id":1138697,
    "tgn:name":"Zuyevka",
    "tgn:placetype":[
        "aat:300008347"
    ]
},
  "bbox": [],
  "geometry": {"coordinates":[51.0167,58.3667],"type":"Point"}
}