{
  "id": 7107423,
  "type": "Feature",
  "properties": {
    "tgn:hierarchy":[
        "tgn:7107423",
        "tgn:7003669",
        "tgn:1000003",
        "tgn:7000084",
        "tgn:7029392"
    ],
    "tgn:id":7107423,
    "tgn:name":"Ragaul",
    "tgn:placetype":[
        "aat:300008347"
    ]
},
  "bbox": [],
  "geometry": {"coordinates":[13.233333,48.683333],"type":"Point"}
}