{
  "id": 2591387,
  "type": "Feature",
  "properties": {
    "tgn:hierarchy":[
        "tgn:2591387",
        "tgn:1000001",
        "tgn:2001810",
        "tgn:7012149",
        "tgn:7007713",
        "tgn:7029392"
    ],
    "tgn:id":2591387,
    "tgn:name":"Polo Creek",
    "tgn:placetype":[
        "aat:300008706"
    ]
},
  "bbox": [],
  "geometry": {"coordinates":[-103.75,44.3833],"type":"Point"}
}