{
  "id": 2357329,
  "type": "Feature",
  "properties": {
    "tgn:hierarchy":[
        "tgn:2357329",
        "tgn:1000001",
        "tgn:7006451",
        "tgn:7012149",
        "tgn:7029392"
    ],
    "tgn:id":2357329,
    "tgn:name":"Government Canyon",
    "tgn:placetype":[
        "aat:300008761"
    ]
},
  "bbox": [],
  "geometry": {"coordinates":[-112.1333,35.0167],"type":"Point"}
}