{
  "id": 1023466,
  "type": "Feature",
  "properties": {
    "tgn:hierarchy":[
        "tgn:1023466",
        "tgn:1001768",
        "tgn:1000049",
        "tgn:1000002",
        "tgn:1008543",
        "tgn:7029392"
    ],
    "tgn:id":1023466,
    "tgn:name":"Hanga Roa",
    "tgn:placetype":[
        "aat:300008347"
    ]
},
  "bbox": [],
  "geometry": {"coordinates":[-109.433333,-27.15],"type":"Point"}
}