{
  "id": 7593467,
  "type": "Feature",
  "properties": {
    "tgn:hierarchy":[
        "tgn:7593467",
        "tgn:7005412",
        "tgn:1000001",
        "tgn:7005388",
        "tgn:7029392"
    ],
    "tgn:id":7593467,
    "tgn:name":"Banano",
    "tgn:placetype":[
        "aat:300008347"
    ]
},
  "bbox": [],
  "geometry": {"coordinates":[-71.733,18.15],"type":"Point"}
}