{
  "id": 2609355,
  "type": "Feature",
  "properties": {
    "tgn:hierarchy":[
        "tgn:2609355",
        "tgn:1000001",
        "tgn:7012149",
        "tgn:7014612",
        "tgn:7007568",
        "tgn:7029392"
    ],
    "tgn:id":2609355,
    "tgn:name":"Ray Hill",
    "tgn:placetype":[
        "aat:300008798"
    ]
},
  "bbox": [],
  "geometry": {"coordinates":[-73.7333,41.2167],"type":"Point"}
}