{
  "id": 2221351,
  "type": "Feature",
  "properties": {
    "tgn:hierarchy":[
        "tgn:2221351",
        "tgn:1000001",
        "tgn:7012149",
        "tgn:7029392"
    ],
    "tgn:id":2221351,
    "tgn:name":"Carey Branch",
    "tgn:placetype":[
        "aat:300008699"
    ]
},
  "bbox": [],
  "geometry": {"coordinates":[-75.2333,38.45],"type":"Point"}
}