<<<<<<< HEAD
{
  "id": 2259646,
  "type": "Feature",
  "properties": {
    "tgn:hierarchy":[
        "tgn:2259646",
        "tgn:1000001",
        "tgn:7012149",
        "tgn:7007157",
        "tgn:2000189",
        "tgn:7029392"
    ],
    "tgn:id":2259646,
    "tgn:name":"Cougar Butte",
    "tgn:placetype":[
        "aat:300008798"
    ]
},
  "bbox": [],
  "geometry": {"coordinates":[-121.4667,41.65],"type":"Point"}
}
=======
{"geometry":{"type":"Point","coordinates":[-121.466700,41.650000]},"type":"Feature","properties":{"hierarchy":["tgn:2259646","tgn:1000001","tgn:7012149","tgn:7007157","tgn:2000189","tgn:7029392"],"placetype":["aat:300008798"],"id":2259646,"name:xx":"Cougar Butte"}}
>>>>>>> 03f74aca74312dbeaf24d7e61306dd6a786dc3d0
