{
  "id": 2259646,
  "type": "Feature",
  "properties": {
    "tgn:hierarchy":[
        "tgn:2259646",
        "tgn:1000001",
        "tgn:7012149",
        "tgn:7007157",
        "tgn:2000189",
        "tgn:7029392"
    ],
    "tgn:id":2259646,
    "tgn:name":"Cougar Butte",
    "tgn:placetype":[
        "aat:300008798"
    ]
},
  "bbox": [],
  "geometry": {"coordinates":[-121.4667,41.65],"type":"Point"}
}