{
  "id": 7029857,
  "type": "Feature",
  "properties": {
    "tgn:hierarchy":[
        "tgn:7029857",
        "tgn:7019038",
        "tgn:7002445",
        "tgn:1000003",
        "tgn:7029507",
        "tgn:7008591",
        "tgn:7029392"
    ],
    "tgn:id":7029857,
    "tgn:name:en":"Beeston",
    "tgn:placetype":[
        "aat:300008347",
        "aat:300000745",
        "aat:300008372"
    ]
},
  "bbox": [],
  "geometry": {"coordinates":[-1.576,53.767],"type":"Point"}
}