{
  "id": 1094049,
  "type": "Feature",
  "properties": {
    "tgn:hierarchy":[
        "tgn:1094049",
        "tgn:7001242",
        "tgn:1000179",
        "tgn:1000200",
        "tgn:7029392"
    ],
    "tgn:id":1094049,
    "tgn:name":"Bir Anzarane",
    "tgn:placetype":[
        "aat:300008347"
    ]
},
  "bbox": [],
  "geometry": {"coordinates":[-14.55,23.9333],"type":"Point"}
}