{
  "id": 7319779,
  "type": "Feature",
  "properties": {
    "tgn:hierarchy":[
        "tgn:7319779",
        "tgn:1001699",
        "tgn:1000049",
        "tgn:1000002",
        "tgn:7029392"
    ],
    "tgn:id":7319779,
    "tgn:name":"Ahinco, R\u00edo",
    "tgn:placetype":[
        "aat:300008699"
    ]
},
  "bbox": [],
  "geometry": {"coordinates":[-73.633333,-41.783333],"type":"Point"}
}