{
  "id": 2510135,
  "type": "Feature",
  "properties": {
    "tgn:hierarchy":[
        "tgn:2510135",
        "tgn:1000001",
        "tgn:7012149",
        "tgn:2001517",
        "tgn:7007709",
        "tgn:7029392"
    ],
    "tgn:id":2510135,
    "tgn:name":"Middle Prong",
    "tgn:placetype":[
        "aat:300008699"
    ]
},
  "bbox": [],
  "geometry": {"coordinates":[-76.8167,35.85],"type":"Point"}
}