{
  "id": 2185952,
  "type": "Feature",
  "properties": {
    "tgn:hierarchy":[
        "tgn:2185952",
        "tgn:1000001",
        "tgn:2001174",
        "tgn:7012149",
        "tgn:7007523",
        "tgn:7029392"
    ],
    "tgn:id":2185952,
    "tgn:name":"Bollinger Branch",
    "tgn:placetype":[
        "aat:300008699"
    ]
},
  "bbox": [],
  "geometry": {"coordinates":[-89.9833,37.45],"type":"Point"}
}