{
  "id": 2382608,
  "type": "Feature",
  "properties": {
    "tgn:hierarchy":[
        "tgn:2382608",
        "tgn:1000001",
        "tgn:7012149",
        "tgn:2001821",
        "tgn:7007713",
        "tgn:7029392"
    ],
    "tgn:id":2382608,
    "tgn:name":"Hayward",
    "tgn:placetype":[
        "aat:300008347"
    ]
},
  "bbox": [],
  "geometry": {"coordinates":[-103.3333,43.8667],"type":"Point"}
}