{
  "id": 7332793,
  "type": "Feature",
  "properties": {
    "tgn:hierarchy":[
        "tgn:7332793",
        "tgn:7002836",
        "tgn:7016622",
        "tgn:1000003",
        "tgn:1000095",
        "tgn:7029392"
    ],
    "tgn:id":7332793,
    "tgn:name":"Ingleses, Atalaya de los",
    "tgn:placetype":[
        "aat:300008795"
    ]
},
  "bbox": [],
  "geometry": {"coordinates":[-16.133333,28.533333],"type":"Point"}
}