{
  "id": 7270789,
  "type": "Feature",
  "properties": {
    "tgn:hierarchy":[
        "tgn:7270789",
        "tgn:1000003",
        "tgn:7003624",
        "tgn:7016845",
        "tgn:7029392"
    ],
    "tgn:id":7270789,
    "tgn:name:nl":"Sint Antoniegorzen",
    "tgn:placetype":[
        "aat:300387200"
    ]
},
  "bbox": [],
  "geometry": {"coordinates":[4.416667,51.683333],"type":"Point"}
}