{
  "id": 2778606,
  "type": "Feature",
  "properties": {
    "tgn:hierarchy":[
        "tgn:2778606",
        "tgn:2001563",
        "tgn:1000001",
        "tgn:7012149",
        "tgn:7007705",
        "tgn:7029392"
    ],
    "tgn:id":2778606,
    "tgn:name":"Woburn",
    "tgn:placetype":[
        "aat:300008347"
    ]
},
  "bbox": [],
  "geometry": {"coordinates":[-102.4167,48.8167],"type":"Point"}
}