{
  "id": 7366161,
  "type": "Feature",
  "properties": {
    "tgn:hierarchy":[
        "tgn:7366161",
        "tgn:7005583",
        "tgn:1000001",
        "tgn:7005560",
        "tgn:7029392"
    ],
    "tgn:id":7366161,
    "tgn:name":"Rancho El Refugio",
    "tgn:placetype":[
        "aat:300000241"
    ]
},
  "bbox": [],
  "geometry": {"coordinates":[-104.616667,25.416667],"type":"Point"}
}