{
  "id": 7101904,
  "type": "Feature",
  "properties": {
    "tgn:hierarchy":[
        "tgn:7101904",
        "tgn:7003669",
        "tgn:1000003",
        "tgn:7000084",
        "tgn:7029392"
    ],
    "tgn:id":7101904,
    "tgn:name":"Rumpfing",
    "tgn:placetype":[
        "aat:300000206"
    ]
},
  "bbox": [],
  "geometry": {"coordinates":[12.333333,48.383333],"type":"Point"}
}