{
  "id": 2229892,
  "type": "Feature",
  "properties": {
    "tgn:hierarchy":[
        "tgn:2229892",
        "tgn:1000001",
        "tgn:7012149",
        "tgn:2002005",
        "tgn:7007826",
        "tgn:7029392"
    ],
    "tgn:id":2229892,
    "tgn:name":"Cedar Tank",
    "tgn:placetype":[
        "aat:300006191"
    ]
},
  "bbox": [],
  "geometry": {"coordinates":[-104.9833,31.35],"type":"Point"}
}