{
  "id": 2296435,
  "type": "Feature",
  "properties": {
    "tgn:hierarchy":[
        "tgn:2296435",
        "tgn:1000001",
        "tgn:7006451",
        "tgn:7012149",
        "tgn:2000102",
        "tgn:7029392"
    ],
    "tgn:id":2296435,
    "tgn:name":"Dry Canyon",
    "tgn:placetype":[
        "aat:300008761"
    ]
},
  "bbox": [],
  "geometry": {"coordinates":[-110.75,31.65],"type":"Point"}
}