{
  "id": 2668622,
  "type": "Feature",
  "properties": {
    "tgn:hierarchy":[
        "tgn:2668622",
        "tgn:1000001",
        "tgn:7012149",
        "tgn:2000476",
        "tgn:7007250",
        "tgn:7029392"
    ],
    "tgn:id":2668622,
    "tgn:name":"Slate Point",
    "tgn:placetype":[
        "aat:300008798"
    ]
},
  "bbox": [],
  "geometry": {"coordinates":[-116.1167,45.5833],"type":"Point"}
}