{
  "id": 7531489,
  "type": "Feature",
  "properties": {
    "tgn:hierarchy":[
        "tgn:7531489",
        "tgn:7001242",
        "tgn:7016833",
        "tgn:1001091",
        "tgn:7029392"
    ],
    "tgn:id":7531489,
    "tgn:name":"Al Hay'ah al 'Arab\u012byah lil Ta\u015fn\u012b'",
    "tgn:placetype":[
        "aat:300004792"
    ]
},
  "bbox": [],
  "geometry": {"coordinates":[31.405021,30.086176],"type":"Point"}
}