{
  "id": 2509897,
  "type": "Feature",
  "properties": {
    "tgn:hierarchy":[
        "tgn:2509897",
        "tgn:1000001",
        "tgn:7012149",
        "tgn:2000210",
        "tgn:7007158",
        "tgn:7029392"
    ],
    "tgn:id":2509897,
    "tgn:name":"Middle Mountain",
    "tgn:placetype":[
        "aat:300008798"
    ]
},
  "bbox": [],
  "geometry": {"coordinates":[-106.5167,39.4333],"type":"Point"}
}