{
  "id": 2498602,
  "type": "Feature",
  "properties": {
    "tgn:hierarchy":[
        "tgn:2498602",
        "tgn:7006450",
        "tgn:1000001",
        "tgn:7019698",
        "tgn:7012149",
        "tgn:7029392"
    ],
    "tgn:id":2498602,
    "tgn:name":"McArthur River",
    "tgn:placetype":[
        "aat:300008707"
    ]
},
  "bbox": [],
  "geometry": {"coordinates":[-152.35,61.1167],"type":"Point"}
}