{
  "id": 2449247,
  "type": "Feature",
  "properties": {
    "tgn:hierarchy":[
        "tgn:2449247",
        "tgn:1000001",
        "tgn:1002349",
        "tgn:7012149",
        "tgn:7007251",
        "tgn:7029392"
    ],
    "tgn:id":2449247,
    "tgn:name":"Limestone Creek",
    "tgn:placetype":[
        "aat:300008706"
    ]
},
  "bbox": [],
  "geometry": {"coordinates":[-88.7333,38.9333],"type":"Point"}
}