{
  "id": 7587762,
  "type": "Feature",
  "properties": {
    "tgn:hierarchy":[
        "tgn:7587762",
        "tgn:1000004",
        "tgn:1001832",
        "tgn:7000198",
        "tgn:7029392"
    ],
    "tgn:id":7587762,
    "tgn:name:en":"Medum",
    "tgn:placetype":[
        "aat:300008347"
    ]
},
  "bbox": [],
  "geometry": {"coordinates":[93.267297,27.134308],"type":"Point"}
}