{
  "id": 2215635,
  "type": "Feature",
  "properties": {
    "tgn:hierarchy":[
        "tgn:2215635",
        "tgn:1000001",
        "tgn:7012149",
        "tgn:2001716",
        "tgn:7007708",
        "tgn:7029392"
    ],
    "tgn:id":2215635,
    "tgn:name":"Camas Swale Creek",
    "tgn:placetype":[
        "aat:300008706"
    ]
},
  "bbox": [],
  "geometry": {"coordinates":[-123.1333,43.8667],"type":"Point"}
}