<<<<<<< HEAD
{
  "id": 7378101,
  "type": "Feature",
  "properties": {
    "tgn:hierarchy":[
        "tgn:7378101",
        "tgn:1000001",
        "tgn:7005595",
        "tgn:7005560",
        "tgn:7029392"
    ],
    "tgn:id":7378101,
    "tgn:name":"Rancho Las Chicuras",
    "tgn:placetype":[
        "aat:300000241"
    ]
},
  "bbox": [],
  "geometry": {"coordinates":[-108.1,26.883333],"type":"Point"}
}
=======
{"geometry":{"type":"Point","coordinates":[-108.100000,26.883333]},"type":"Feature","properties":{"hierarchy":["tgn:7378101","tgn:1000001","tgn:7005595","tgn:7005560","tgn:7029392"],"placetype":["aat:300000241"],"id":7378101,"name:xx":"Rancho Las Chicuras"}}
>>>>>>> 03f74aca74312dbeaf24d7e61306dd6a786dc3d0
