{
  "id": 2239878,
  "type": "Feature",
  "properties": {
    "tgn:hierarchy":[
        "tgn:2239878",
        "tgn:1000001",
        "tgn:7006451",
        "tgn:7012149",
        "tgn:2000097",
        "tgn:7029392"
    ],
    "tgn:id":2239878,
    "tgn:name":"Cimarron",
    "tgn:placetype":[
        "aat:300008347"
    ]
},
  "bbox": [],
  "geometry": {"coordinates":[-111.9833,33.3833],"type":"Point"}
}