{
  "id": 2189487,
  "type": "Feature",
  "properties": {
    "tgn:hierarchy":[
        "tgn:2189487",
        "tgn:1000001",
        "tgn:1002665",
        "tgn:7012149",
        "tgn:7007517",
        "tgn:7029392"
    ],
    "tgn:id":2189487,
    "tgn:name":"Bow Brook Reservoir",
    "tgn:placetype":[
        "aat:300006191"
    ]
},
  "bbox": [],
  "geometry": {"coordinates":[-71.65,42.5333],"type":"Point"}
}