{
  "id": 7498707,
  "type": "Feature",
  "properties": {
    "tgn:hierarchy":[
        "tgn:7498707",
        "tgn:1000004",
        "tgn:7001009",
        "tgn:1000141",
        "tgn:7029392"
    ],
    "tgn:id":7498707,
    "tgn:name":"Shuntian Gong",
    "tgn:placetype":[
        "aat:300007595"
    ]
},
  "bbox": [],
  "geometry": {"coordinates":[120.602337,24.08019],"type":"Point"}
}