{
  "id": 2457440,
  "type": "Feature",
  "properties": {
    "tgn:hierarchy":[
        "tgn:2457440",
        "tgn:1000001",
        "tgn:7016172",
        "tgn:7012149",
        "tgn:2000152",
        "tgn:7029392"
    ],
    "tgn:id":2457440,
    "tgn:name":"Little Long Lake",
    "tgn:placetype":[
        "aat:300008680"
    ]
},
  "bbox": [],
  "geometry": {"coordinates":[-91.0667,34.3667],"type":"Point"}
}