{
  "id": 1082256,
  "type": "Feature",
  "properties": {
    "tgn:hierarchy":[
        "tgn:1082256",
        "tgn:1001193",
        "tgn:1006792",
        "tgn:1000004",
        "tgn:7000299",
        "tgn:7029392"
    ],
    "tgn:id":1082256,
    "tgn:name":"Kach'i-ri",
    "tgn:placetype":[
        "aat:300008347"
    ]
},
  "bbox": [],
  "geometry": {"coordinates":[126.1167,34.4333],"type":"Point"}
}