<<<<<<< HEAD
{
  "id": 2405348,
  "type": "Feature",
  "properties": {
    "tgn:hierarchy":[
        "tgn:2405348",
        "tgn:2000858",
        "tgn:1000001",
        "tgn:7012149",
        "tgn:7007256",
        "tgn:7029392"
    ],
    "tgn:id":2405348,
    "tgn:name":"Huffpower, Bayou",
    "tgn:placetype":[
        "aat:300008699"
    ]
},
  "bbox": [],
  "geometry": {"coordinates":[-92.2,30.95],"type":"Point"}
}
=======
{"geometry":{"type":"Point","coordinates":[-92.200000,30.950000]},"type":"Feature","properties":{"hierarchy":["tgn:2405348","tgn:2000858","tgn:1000001","tgn:7012149","tgn:7007256","tgn:7029392"],"placetype":["aat:300008699"],"id":2405348,"name:xx":"Huffpower, Bayou"}}
>>>>>>> 03f74aca74312dbeaf24d7e61306dd6a786dc3d0
