{
  "id": 2685386,
  "type": "Feature",
  "properties": {
    "tgn:hierarchy":[
        "tgn:2685386",
        "tgn:7002659",
        "tgn:1000001",
        "tgn:7012149",
        "tgn:2000027",
        "tgn:7029392"
    ],
    "tgn:id":2685386,
    "tgn:name":"Spout Spring Hollow",
    "tgn:placetype":[
        "aat:300008761"
    ]
},
  "bbox": [],
  "geometry": {"coordinates":[-86.05,34.1167],"type":"Point"}
}