{
  "id": 2391705,
  "type": "Feature",
  "properties": {
    "tgn:hierarchy":[
        "tgn:2391705",
        "tgn:1000001",
        "tgn:7012149",
        "tgn:1002612",
        "tgn:7007710",
        "tgn:7029392"
    ],
    "tgn:id":2391705,
    "tgn:name":"Hillside Colliery",
    "tgn:placetype":[
        "aat:300000390"
    ]
},
  "bbox": [],
  "geometry": {"coordinates":[-75.7333,41.3333],"type":"Point"}
}