{
  "id": 2654716,
  "type": "Feature",
  "properties": {
    "tgn:hierarchy":[
        "tgn:2654716",
        "tgn:1000001",
        "tgn:1002665",
        "tgn:7012149",
        "tgn:7007517",
        "tgn:7029392"
    ],
    "tgn:id":2654716,
    "tgn:name":"Shakerhill",
    "tgn:placetype":[
        "aat:300008347"
    ]
},
  "bbox": [],
  "geometry": {"coordinates":[-71.1667,42.45],"type":"Point"}
}