{
  "id": 7388397,
  "type": "Feature",
  "properties": {
    "tgn:hierarchy":[
        "tgn:7388397",
        "tgn:1001836",
        "tgn:1000001",
        "tgn:7005560",
        "tgn:7029392"
    ],
    "tgn:id":7388397,
    "tgn:name":"Puerto San Andresito",
    "tgn:placetype":[
        "aat:300008347"
    ]
},
  "bbox": [],
  "geometry": {"coordinates":[-112.116389,25.805278],"type":"Point"}
}