{
  "id": 7588833,
  "type": "Feature",
  "properties": {
    "tgn:hierarchy":[
        "tgn:7588833",
        "tgn:1000004",
        "tgn:7000198",
        "tgn:7000799",
        "tgn:7029392"
    ],
    "tgn:id":7588833,
    "tgn:name:en":"Babri Gali",
    "tgn:placetype":[
        "aat:300259572"
    ]
},
  "bbox": [],
  "geometry": {"coordinates":[74.141667,33.572222],"type":"Point"}
}