{
  "id": 7442914,
  "type": "Feature",
  "properties": {
    "tgn:hierarchy":[
        "tgn:7442914",
        "tgn:7002445",
        "tgn:1000003",
        "tgn:7008166",
        "tgn:7008591",
        "tgn:7029392"
    ],
    "tgn:id":7442914,
    "tgn:name:en":"Whitewall Corner",
    "tgn:placetype":[
        "aat:300008347"
    ]
},
  "bbox": [],
  "geometry": {"coordinates":[-0.783333,54.116667],"type":"Point"}
}