{
  "id": 7508745,
  "type": "Feature",
  "properties": {
    "tgn:hierarchy":[
        "tgn:7508745",
        "tgn:1008380",
        "tgn:1000226",
        "tgn:7016827",
        "tgn:1000006",
        "tgn:7029392"
    ],
    "tgn:id":7508745,
    "tgn:name:en":"Otikoki",
    "tgn:placetype":[
        "aat:300008795"
    ]
},
  "bbox": [],
  "geometry": {"coordinates":[174.966667,-39.316667],"type":"Point"}
}