{
  "id": 1097130,
  "type": "Feature",
  "properties": {
    "tgn:hierarchy":[
        "tgn:1097130",
        "tgn:7000490",
        "tgn:1000006",
        "tgn:7001831",
        "tgn:7029392"
    ],
    "tgn:id":1097130,
    "tgn:name":"Hookina",
    "tgn:placetype":[
        "aat:300008347"
    ]
},
  "bbox": [],
  "geometry": {"coordinates":[138.3333,-31.75],"type":"Point"}
}