{
  "id": 2319556,
  "type": "Feature",
  "properties": {
    "tgn:hierarchy":[
        "tgn:2319556",
        "tgn:1000001",
        "tgn:2001643",
        "tgn:7012149",
        "tgn:7007707",
        "tgn:7029392"
    ],
    "tgn:id":2319556,
    "tgn:name":"Eucha, Lake",
    "tgn:placetype":[
        "aat:300006191"
    ]
},
  "bbox": [],
  "geometry": {"coordinates":[-94.9333,36.3667],"type":"Point"}
}