{
  "id": 2268067,
  "type": "Feature",
  "properties": {
    "tgn:hierarchy":[
        "tgn:2268067",
        "tgn:1000001",
        "tgn:7012149",
        "tgn:2001300",
        "tgn:7007524",
        "tgn:7029392"
    ],
    "tgn:id":2268067,
    "tgn:name":"Crooked Creek",
    "tgn:placetype":[
        "aat:300008706"
    ]
},
  "bbox": [],
  "geometry": {"coordinates":[-113.75,46.2667],"type":"Point"}
}