<<<<<<< HEAD
{
  "id": 7487567,
  "type": "Feature",
  "properties": {
    "tgn:hierarchy":[
        "tgn:7487567",
        "tgn:7001010",
        "tgn:1000004",
        "tgn:1000141",
        "tgn:7029392"
    ],
    "tgn:id":7487567,
    "tgn:name":"Hualian Gang",
    "tgn:placetype":[
        "aat:300008678"
    ]
},
  "bbox": [],
  "geometry": {"coordinates":[121.631111,23.9825],"type":"Point"}
}
=======
{"geometry":{"type":"Point","coordinates":[121.631111,23.982500]},"type":"Feature","properties":{"hierarchy":["tgn:7487567","tgn:7001010","tgn:1000004","tgn:1000141","tgn:7029392"],"placetype":["aat:300008678"],"id":7487567,"name:xx":"Hualian Gang"}}
>>>>>>> 03f74aca74312dbeaf24d7e61306dd6a786dc3d0
