{
  "id": 2564528,
  "type": "Feature",
  "properties": {
    "tgn:hierarchy":[
        "tgn:2564528",
        "tgn:1000001",
        "tgn:7012149",
        "tgn:2001199",
        "tgn:7007523",
        "tgn:7029392"
    ],
    "tgn:id":2564528,
    "tgn:name":"Packer Branch",
    "tgn:placetype":[
        "aat:300008699"
    ]
},
  "bbox": [],
  "geometry": {"coordinates":[-93.2333,37.2333],"type":"Point"}
}