{
  "id": 2736741,
  "type": "Feature",
  "properties": {
    "tgn:hierarchy":[
        "tgn:2736741",
        "tgn:1000001",
        "tgn:7012149",
        "tgn:1002472",
        "tgn:7007568",
        "tgn:7029392"
    ],
    "tgn:id":2736741,
    "tgn:name":"Twin Vlys",
    "tgn:placetype":[
        "aat:300008905"
    ]
},
  "bbox": [],
  "geometry": {"coordinates":[-74.85,43.3167],"type":"Point"}
}