{
  "id": 2178529,
  "type": "Feature",
  "properties": {
    "tgn:hierarchy":[
        "tgn:2178529",
        "tgn:1000001",
        "tgn:7012149",
        "tgn:2002186",
        "tgn:7007919",
        "tgn:7029392"
    ],
    "tgn:id":2178529,
    "tgn:name":"Blacks Creek",
    "tgn:placetype":[
        "aat:300008706"
    ]
},
  "bbox": [],
  "geometry": {"coordinates":[-79.6667,37.7333],"type":"Point"}
}