<<<<<<< HEAD
{
  "id": 2256208,
  "type": "Feature",
  "properties": {
    "tgn:hierarchy":[
        "tgn:2256208",
        "tgn:1002201",
        "tgn:1000001",
        "tgn:7012149",
        "tgn:7007517",
        "tgn:7029392"
    ],
    "tgn:id":2256208,
    "tgn:name":"Copper Works",
    "tgn:placetype":[
        "aat:300008347"
    ]
},
  "bbox": [],
  "geometry": {"coordinates":[-71.1667,41.9333],"type":"Point"}
}
=======
{"geometry":{"type":"Point","coordinates":[-71.166700,41.933300]},"type":"Feature","properties":{"hierarchy":["tgn:2256208","tgn:1002201","tgn:1000001","tgn:7012149","tgn:7007517","tgn:7029392"],"placetype":["aat:300008347"],"id":2256208,"name:xx":"Copper Works"}}
>>>>>>> 03f74aca74312dbeaf24d7e61306dd6a786dc3d0
