{
  "id": 7452853,
  "type": "Feature",
  "properties": {
    "tgn:hierarchy":[
        "tgn:7452853",
        "tgn:7002445",
        "tgn:7008116",
        "tgn:1000003",
        "tgn:7008591",
        "tgn:7029392"
    ],
    "tgn:id":7452853,
    "tgn:name:en":"Cape Cornwall Bank",
    "tgn:placetype":[
        "aat:300386970"
    ]
},
  "bbox": [],
  "geometry": {"coordinates":[-5.816667,50.233333],"type":"Point"}
}