{
  "id": 2042319,
  "type": "Feature",
  "properties": {
    "tgn:hierarchy":[
        "tgn:2042319",
        "tgn:1000001",
        "tgn:7012149",
        "tgn:2000909",
        "tgn:7007256",
        "tgn:7029392"
    ],
    "tgn:id":2042319,
    "tgn:name":"Bernice",
    "tgn:placetype":[
        "aat:300008347"
    ]
},
  "bbox": [],
  "geometry": {"coordinates":[-92.65,32.8167],"type":"Point"}
}