{
  "id": 2593992,
  "type": "Feature",
  "properties": {
    "tgn:hierarchy":[
        "tgn:2593992",
        "tgn:7006450",
        "tgn:1000001",
        "tgn:7012149",
        "tgn:2000088",
        "tgn:7029392"
    ],
    "tgn:id":2593992,
    "tgn:name":"Portage Bay",
    "tgn:placetype":[
        "aat:300132316"
    ]
},
  "bbox": [],
  "geometry": {"coordinates":[-133.8833,56.9333],"type":"Point"}
}