{
  "id": 7230917,
  "type": "Feature",
  "properties": {
    "tgn:hierarchy":[
        "tgn:7230917",
        "tgn:7002718",
        "tgn:7002715",
        "tgn:1000003",
        "tgn:1000074",
        "tgn:7029392"
    ],
    "tgn:id":7230917,
    "tgn:name":"Char\u00edessa",
    "tgn:placetype":[
        "aat:300008347"
    ]
},
  "bbox": [],
  "geometry": {"coordinates":[22.166667,40.651944],"type":"Point"}
}