{
  "id": 7228012,
  "type": "Feature",
  "properties": {
    "tgn:hierarchy":[
        "tgn:7228012",
        "tgn:7002751",
        "tgn:7001399",
        "tgn:1000003",
        "tgn:1000074",
        "tgn:7029392"
    ],
    "tgn:id":7228012,
    "tgn:name":"Kastron\u00edsia",
    "tgn:placetype":[
        "aat:300008791"
    ]
},
  "bbox": [],
  "geometry": {"coordinates":[23.466667,39.216667],"type":"Point"}
}