{
  "id": 7573815,
  "type": "Feature",
  "properties": {
    "tgn:hierarchy":[
        "tgn:7573815",
        "tgn:1000004",
        "tgn:1001869",
        "tgn:7000198",
        "tgn:7029392"
    ],
    "tgn:id":7573815,
    "tgn:name:en":"Itola",
    "tgn:placetype":[
        "aat:300007783"
    ]
},
  "bbox": [],
  "geometry": {"coordinates":[73.166667,22.15],"type":"Point"}
}