<<<<<<< HEAD
{
  "id": 2259679,
  "type": "Feature",
  "properties": {
    "tgn:hierarchy":[
        "tgn:2259679",
        "tgn:1000001",
        "tgn:7012149",
        "tgn:2000494",
        "tgn:7007250",
        "tgn:7029392"
    ],
    "tgn:id":2259679,
    "tgn:name":"Cougar Creek",
    "tgn:placetype":[
        "aat:300008706"
    ]
},
  "bbox": [],
  "geometry": {"coordinates":[-115.05,44.8333],"type":"Point"}
}
=======
{"geometry":{"type":"Point","coordinates":[-115.050000,44.833300]},"type":"Feature","properties":{"hierarchy":["tgn:2259679","tgn:1000001","tgn:7012149","tgn:2000494","tgn:7007250","tgn:7029392"],"placetype":["aat:300008706"],"id":2259679,"name:xx":"Cougar Creek"}}
>>>>>>> 03f74aca74312dbeaf24d7e61306dd6a786dc3d0
