{
  "id": 2010874,
  "type": "Feature",
  "properties": {
    "tgn:hierarchy":[
        "tgn:2010874",
        "tgn:1000001",
        "tgn:7012149",
        "tgn:7007157",
        "tgn:1002841",
        "tgn:7029392"
    ],
    "tgn:id":2010874,
    "tgn:name":"Courtland",
    "tgn:placetype":[
        "aat:300008347"
    ]
},
  "bbox": [],
  "geometry": {"coordinates":[-121.5667,38.3167],"type":"Point"}
}