{
  "id": 7371864,
  "type": "Feature",
  "properties": {
    "tgn:hierarchy":[
        "tgn:7371864",
        "tgn:1001853",
        "tgn:1000001",
        "tgn:7005560",
        "tgn:7029392"
    ],
    "tgn:id":7371864,
    "tgn:name":"Lampacitos",
    "tgn:placetype":[
        "aat:300007783"
    ]
},
  "bbox": [],
  "geometry": {"coordinates":[-101.266667,27.333333],"type":"Point"}
}