{
  "id": 2202706,
  "type": "Feature",
  "properties": {
    "tgn:hierarchy":[
        "tgn:2202706",
        "tgn:1000001",
        "tgn:7006451",
        "tgn:2000093",
        "tgn:7012149",
        "tgn:7029392"
    ],
    "tgn:id":2202706,
    "tgn:name":"Buckaroo Tank",
    "tgn:placetype":[
        "aat:300006191"
    ]
},
  "bbox": [],
  "geometry": {"coordinates":[-111.0667,33.9167],"type":"Point"}
}