{
  "id": 2630697,
  "type": "Feature",
  "properties": {
    "tgn:hierarchy":[
        "tgn:2630697",
        "tgn:7002659",
        "tgn:1000001",
        "tgn:7012149",
        "tgn:2000051",
        "tgn:7029392"
    ],
    "tgn:id":2630697,
    "tgn:name":"Round Knob",
    "tgn:placetype":[
        "aat:300008798"
    ]
},
  "bbox": [],
  "geometry": {"coordinates":[-86.5667,34.5167],"type":"Point"}
}