{
  "id": 2301586,
  "type": "Feature",
  "properties": {
    "tgn:hierarchy":[
        "tgn:2301586",
        "tgn:1000001",
        "tgn:7012149",
        "tgn:2001067",
        "tgn:7007521",
        "tgn:7029392"
    ],
    "tgn:id":2301586,
    "tgn:name":"Dunwoody Junction",
    "tgn:placetype":[
        "aat:300008347"
    ]
},
  "bbox": [],
  "geometry": {"coordinates":[-92.8667,47.45],"type":"Point"}
}