<<<<<<< HEAD
{
  "id": 2760115,
  "type": "Feature",
  "properties": {
    "tgn:hierarchy":[
        "tgn:2760115",
        "tgn:1000001",
        "tgn:7012149",
        "tgn:2001708",
        "tgn:7007708",
        "tgn:7029392"
    ],
    "tgn:id":2760115,
    "tgn:name":"West Fork Pine Creek",
    "tgn:placetype":[
        "aat:300008706"
    ]
},
  "bbox": [],
  "geometry": {"coordinates":[-118.85,44.3333],"type":"Point"}
}
=======
{"geometry":{"type":"Point","coordinates":[-118.850000,44.333300]},"type":"Feature","properties":{"hierarchy":["tgn:2760115","tgn:1000001","tgn:7012149","tgn:2001708","tgn:7007708","tgn:7029392"],"placetype":["aat:300008706"],"id":2760115,"name:xx":"West Fork Pine Creek"}}
>>>>>>> 03f74aca74312dbeaf24d7e61306dd6a786dc3d0
