<<<<<<< HEAD
{
  "id": 2251746,
  "type": "Feature",
  "properties": {
    "tgn:hierarchy":[
        "tgn:2251746",
        "tgn:1000001",
        "tgn:7012149",
        "tgn:1002892",
        "tgn:7007520",
        "tgn:7029392"
    ],
    "tgn:id":2251746,
    "tgn:name":"Compton Drain",
    "tgn:placetype":[
        "aat:300006075"
    ]
},
  "bbox": [],
  "geometry": {"coordinates":[-83.9833,43.0667],"type":"Point"}
}
=======
{"geometry":{"type":"Point","coordinates":[-83.983300,43.066700]},"type":"Feature","properties":{"hierarchy":["tgn:2251746","tgn:1000001","tgn:7012149","tgn:1002892","tgn:7007520","tgn:7029392"],"placetype":["aat:300006075"],"id":2251746,"name:xx":"Compton Drain"}}
>>>>>>> 03f74aca74312dbeaf24d7e61306dd6a786dc3d0
