{
  "id": 2251746,
  "type": "Feature",
  "properties": {
    "tgn:hierarchy":[
        "tgn:2251746",
        "tgn:1000001",
        "tgn:7012149",
        "tgn:1002892",
        "tgn:7007520",
        "tgn:7029392"
    ],
    "tgn:id":2251746,
    "tgn:name":"Compton Drain",
    "tgn:placetype":[
        "aat:300006075"
    ]
},
  "bbox": [],
  "geometry": {"coordinates":[-83.9833,43.0667],"type":"Point"}
}