{
  "id": 7414724,
  "type": "Feature",
  "properties": {
    "tgn:hierarchy":[
        "tgn:7414724",
        "tgn:7005584",
        "tgn:1000001",
        "tgn:7005560",
        "tgn:7029392"
    ],
    "tgn:id":7414724,
    "tgn:name":"Benito Ju\u00e1rez",
    "tgn:placetype":[
        "aat:300008347"
    ]
},
  "bbox": [],
  "geometry": {"coordinates":[-101.273333,20.359722],"type":"Point"}
}