{
  "id": 7098968,
  "type": "Feature",
  "properties": {
    "tgn:hierarchy":[
        "tgn:7098968",
        "tgn:1000003",
        "tgn:7003677",
        "tgn:7000084",
        "tgn:7029392"
    ],
    "tgn:id":7098968,
    "tgn:name":"Seller-Berg",
    "tgn:placetype":[
        "aat:300008795"
    ]
},
  "bbox": [],
  "geometry": {"coordinates":[8.583333,51.133333],"type":"Point"}
}