{
  "id": 1040845,
  "type": "Feature",
  "properties": {
    "tgn:hierarchy":[
        "tgn:1040845",
        "tgn:7003669",
        "tgn:1000003",
        "tgn:7000084",
        "tgn:7029392"
    ],
    "tgn:id":1040845,
    "tgn:name":"Regenstauf",
    "tgn:placetype":[
        "aat:300008347"
    ]
},
  "bbox": [],
  "geometry": {"coordinates":[12.129167,49.121667],"type":"Point"}
}