<<<<<<< HEAD
{
  "id": 2768960,
  "type": "Feature",
  "properties": {
    "tgn:hierarchy":[
        "tgn:2768960",
        "tgn:1000001",
        "tgn:7012149",
        "tgn:1002540",
        "tgn:7007520",
        "tgn:7029392"
    ],
    "tgn:id":2768960,
    "tgn:name":"Whitneyville",
    "tgn:placetype":[
        "aat:300008347"
    ]
},
  "bbox": [],
  "geometry": {"coordinates":[-85.45,42.8667],"type":"Point"}
}
=======
{"geometry":{"type":"Point","coordinates":[-85.450000,42.866700]},"type":"Feature","properties":{"hierarchy":["tgn:2768960","tgn:1000001","tgn:7012149","tgn:1002540","tgn:7007520","tgn:7029392"],"placetype":["aat:300008347"],"id":2768960,"name:xx":"Whitneyville"}}
>>>>>>> 03f74aca74312dbeaf24d7e61306dd6a786dc3d0
