{
  "id": 2435693,
  "type": "Feature",
  "properties": {
    "tgn:hierarchy":[
        "tgn:2435693",
        "tgn:7006450",
        "tgn:1000001",
        "tgn:7012149",
        "tgn:2000089",
        "tgn:7029392"
    ],
    "tgn:id":2435693,
    "tgn:name":"Ketchem Dome",
    "tgn:placetype":[
        "aat:300008798"
    ]
},
  "bbox": [],
  "geometry": {"coordinates":[-144.7833,65.45],"type":"Point"}
}