{
  "id": 2690966,
  "type": "Feature",
  "properties": {
    "tgn:hierarchy":[
        "tgn:2690966",
        "tgn:1000001",
        "tgn:7012149",
        "tgn:7007712",
        "tgn:7029392"
    ],
    "tgn:id":2690966,
    "tgn:name":"Stanley Branch",
    "tgn:placetype":[
        "aat:300008699"
    ]
},
  "bbox": [],
  "geometry": {"coordinates":[-80.15,33.05],"type":"Point"}
}