{
  "id": 2358757,
  "type": "Feature",
  "properties": {
    "tgn:hierarchy":[
        "tgn:2358757",
        "tgn:1000001",
        "tgn:1002283",
        "tgn:7012149",
        "tgn:7007520",
        "tgn:7029392"
    ],
    "tgn:id":2358757,
    "tgn:name":"Granger Drain",
    "tgn:placetype":[
        "aat:300006075"
    ]
},
  "bbox": [],
  "geometry": {"coordinates":[-84.6667,42.9833],"type":"Point"}
}