{
  "id": 1066785,
  "type": "Feature",
  "properties": {
    "tgn:hierarchy":[
        "tgn:1066785",
        "tgn:1000004",
        "tgn:7001800",
        "tgn:1000111",
        "tgn:7029392"
    ],
    "tgn:id":1066785,
    "tgn:name":"Baoting",
    "tgn:placetype":[
        "aat:300008347"
    ]
},
  "bbox": [],
  "geometry": {"coordinates":[109.7333,18.7667],"type":"Point"}
}