{
  "id": 7334057,
  "type": "Feature",
  "properties": {
    "tgn:hierarchy":[
        "tgn:7334057",
        "tgn:7010420",
        "tgn:1000003",
        "tgn:7002795",
        "tgn:1000095",
        "tgn:7029392"
    ],
    "tgn:id":7334057,
    "tgn:name":"El Vell\u00f3n",
    "tgn:placetype":[
        "aat:300008347"
    ]
},
  "bbox": [],
  "geometry": {"coordinates":[-3.583333,40.766667],"type":"Point"}
}