{
  "id": 7034746,
  "type": "Feature",
  "properties": {
    "tgn:hierarchy":[
        "tgn:7034746",
        "tgn:1000003",
        "tgn:7003236",
        "tgn:1000080",
        "tgn:7029392"
    ],
    "tgn:id":7034746,
    "tgn:name":"Chiappe, Punta",
    "tgn:placetype":[
        "aat:300386846"
    ]
},
  "bbox": [],
  "geometry": {"coordinates":[9.295,44.321111],"type":"Point"}
}