{
  "id": 2323050,
  "type": "Feature",
  "properties": {
    "tgn:hierarchy":[
        "tgn:2323050",
        "tgn:1000001",
        "tgn:7012149",
        "tgn:1002891",
        "tgn:7007708",
        "tgn:7029392"
    ],
    "tgn:id":2323050,
    "tgn:name":"Fargher",
    "tgn:placetype":[
        "aat:300008347"
    ]
},
  "bbox": [],
  "geometry": {"coordinates":[-121.0167,45.25],"type":"Point"}
}