{
  "id": 2075328,
  "type": "Feature",
  "properties": {
    "tgn:hierarchy":[
        "tgn:2075328",
        "tgn:1000001",
        "tgn:7012149",
        "tgn:2001548",
        "tgn:7007709",
        "tgn:7029392"
    ],
    "tgn:id":2075328,
    "tgn:name":"Kennebec",
    "tgn:placetype":[
        "aat:300008347",
        "aat:300387210"
    ]
},
  "bbox": [],
  "geometry": {"coordinates":[-78.7333,35.5333],"type":"Point"}
}