{
  "id": 2397233,
  "type": "Feature",
  "properties": {
    "tgn:hierarchy":[
        "tgn:2397233",
        "tgn:1000001",
        "tgn:7012149",
        "tgn:2002099",
        "tgn:7007826",
        "tgn:7029392"
    ],
    "tgn:id":2397233,
    "tgn:name":"Hondo Tank",
    "tgn:placetype":[
        "aat:300006191"
    ]
},
  "bbox": [],
  "geometry": {"coordinates":[-99.1667,26.9667],"type":"Point"}
}