{
  "id": 2462246,
  "type": "Feature",
  "properties": {
    "tgn:hierarchy":[
        "tgn:2462246",
        "tgn:1000001",
        "tgn:7012149",
        "tgn:2001676",
        "tgn:7007707",
        "tgn:7029392"
    ],
    "tgn:id":2462246,
    "tgn:name":"Little Walnut Creek",
    "tgn:placetype":[
        "aat:300008706"
    ]
},
  "bbox": [],
  "geometry": {"coordinates":[-96.45,35.5333],"type":"Point"}
}