{
  "id": 1029332,
  "type": "Feature",
  "properties": {
    "tgn:hierarchy":[
        "tgn:1029332",
        "tgn:7002445",
        "tgn:1000003",
        "tgn:7011430",
        "tgn:7008591",
        "tgn:7029392"
    ],
    "tgn:id":1029332,
    "tgn:name:en":"Godshill",
    "tgn:placetype":[
        "aat:300008347"
    ]
},
  "bbox": [],
  "geometry": {"coordinates":[-1.25,50.616667],"type":"Point"}
}