{
  "id": 1071463,
  "type": "Feature",
  "properties": {
    "tgn:hierarchy":[
        "tgn:1071463",
        "tgn:1000004",
        "tgn:7002078",
        "tgn:1000111",
        "tgn:7029392"
    ],
    "tgn:id":1071463,
    "tgn:name":"Shangjin",
    "tgn:placetype":[
        "aat:300008347"
    ]
},
  "bbox": [],
  "geometry": {"coordinates":[110.05,33.15],"type":"Point"}
}