{
  "id": 4008294,
  "type": "Feature",
  "properties": {
    "tgn:hierarchy":[
        "tgn:4008294",
        "tgn:1000003",
        "tgn:7003687",
        "tgn:7000084",
        "tgn:7029392"
    ],
    "tgn:id":4008294,
    "tgn:name":"Osmarsleben",
    "tgn:placetype":[
        "aat:300008347"
    ]
},
  "bbox": [],
  "geometry": {"coordinates":[11.616667,51.783333],"type":"Point"}
}