{
  "id": 2313353,
  "type": "Feature",
  "properties": {
    "tgn:hierarchy":[
        "tgn:2313353",
        "tgn:1000001",
        "tgn:7012149",
        "tgn:2001190",
        "tgn:7007523",
        "tgn:7029392"
    ],
    "tgn:id":2313353,
    "tgn:name":"Elders Lake",
    "tgn:placetype":[
        "aat:300006191"
    ]
},
  "bbox": [],
  "geometry": {"coordinates":[-91.3667,38.0167],"type":"Point"}
}