{
  "id": 7347514,
  "type": "Feature",
  "properties": {
    "tgn:hierarchy":[
        "tgn:7347514",
        "tgn:7002807",
        "tgn:1000003",
        "tgn:7003837",
        "tgn:1000095",
        "tgn:7029392"
    ],
    "tgn:id":7347514,
    "tgn:name":"Arrozao, Sierra del",
    "tgn:placetype":[
        "aat:300266640"
    ]
},
  "bbox": [],
  "geometry": {"coordinates":[-5.766667,38.75],"type":"Point"}
}