<<<<<<< HEAD
{
  "id": 7362576,
  "type": "Feature",
  "properties": {
    "tgn:hierarchy":[
        "tgn:7362576",
        "tgn:1000001",
        "tgn:1001960",
        "tgn:7005560",
        "tgn:7029392"
    ],
    "tgn:id":7362576,
    "tgn:name":"El Carrizal de Jaime",
    "tgn:placetype":[
        "aat:300008347"
    ]
},
  "bbox": [],
  "geometry": {"coordinates":[-109.483333,28.25],"type":"Point"}
}
=======
{"geometry":{"type":"Point","coordinates":[-109.483333,28.250000]},"type":"Feature","properties":{"hierarchy":["tgn:7362576","tgn:1000001","tgn:1001960","tgn:7005560","tgn:7029392"],"placetype":["aat:300008347"],"id":7362576,"name:xx":"El Carrizal de Jaime"}}
>>>>>>> 03f74aca74312dbeaf24d7e61306dd6a786dc3d0
