{
  "id": 7542389,
  "type": "Feature",
  "properties": {
    "tgn:hierarchy":[
        "tgn:7542389",
        "tgn:7001242",
        "tgn:1001059",
        "tgn:7016833",
        "tgn:7029392"
    ],
    "tgn:id":7542389,
    "tgn:name:en":"Kafr ash Shabr\u0101w\u012b",
    "tgn:placetype":[
        "aat:300008347"
    ]
},
  "bbox": [],
  "geometry": {"coordinates":[31.290953,30.916705],"type":"Point"}
}