{
  "id": 7395442,
  "type": "Feature",
  "properties": {
    "tgn:hierarchy":[
        "tgn:7395442",
        "tgn:1000001",
        "tgn:7005592",
        "tgn:7005560",
        "tgn:7029392"
    ],
    "tgn:id":7395442,
    "tgn:name":"San Jos\u00e9 Ixtapa",
    "tgn:placetype":[
        "aat:300008347"
    ]
},
  "bbox": [],
  "geometry": {"coordinates":[-97.466667,18.716667],"type":"Point"}
}