{
  "id": 7571061,
  "type": "Feature",
  "properties": {
    "tgn:hierarchy":[
        "tgn:7571061",
        "tgn:1000004",
        "tgn:7000198",
        "tgn:1001886",
        "tgn:7029392"
    ],
    "tgn:id":7571061,
    "tgn:name:en":"Kall\u0101r",
    "tgn:placetype":[
        "aat:300008347"
    ]
},
  "bbox": [],
  "geometry": {"coordinates":[77.15,9.816667],"type":"Point"}
}