{
  "id": 7567459,
  "type": "Feature",
  "properties": {
    "tgn:hierarchy":[
        "tgn:7567459",
        "tgn:1001828",
        "tgn:1000004",
        "tgn:7000198",
        "tgn:7029392"
    ],
    "tgn:id":7567459,
    "tgn:name:en":"Nakka V\u0101gu",
    "tgn:placetype":[
        "aat:300008699"
    ]
},
  "bbox": [],
  "geometry": {"coordinates":[78.152222,17.653889],"type":"Point"}
}