<<<<<<< HEAD
{
  "id": 2762347,
  "type": "Feature",
  "properties": {
    "tgn:hierarchy":[
        "tgn:2762347",
        "tgn:1000001",
        "tgn:1002359",
        "tgn:7012149",
        "tgn:7007517",
        "tgn:7029392"
    ],
    "tgn:id":2762347,
    "tgn:name":"West Town Landing",
    "tgn:placetype":[
        "aat:300008347"
    ]
},
  "bbox": [],
  "geometry": {"coordinates":[-70.8667,42.5],"type":"Point"}
}
=======
{"geometry":{"type":"Point","coordinates":[-70.866700,42.500000]},"type":"Feature","properties":{"hierarchy":["tgn:2762347","tgn:1000001","tgn:1002359","tgn:7012149","tgn:7007517","tgn:7029392"],"placetype":["aat:300008347"],"id":2762347,"name:xx":"West Town Landing"}}
>>>>>>> 03f74aca74312dbeaf24d7e61306dd6a786dc3d0
