{
  "id": 1027616,
  "type": "Feature",
  "properties": {
    "tgn:hierarchy":[
        "tgn:1027616",
        "tgn:7593919",
        "tgn:1000003",
        "tgn:1001780",
        "tgn:7029392"
    ],
    "tgn:id":1027616,
    "tgn:name":"V\u0161epadly",
    "tgn:placetype":[
        "aat:300008347"
    ]
},
  "bbox": [],
  "geometry": {"coordinates":[13.1167,49.45],"type":"Point"}
}