{
  "id": 2634019,
  "type": "Feature",
  "properties": {
    "tgn:hierarchy":[
        "tgn:2634019",
        "tgn:2001731",
        "tgn:1000001",
        "tgn:7012149",
        "tgn:7007712",
        "tgn:7029392"
    ],
    "tgn:id":2634019,
    "tgn:name":"Russ Point",
    "tgn:placetype":[
        "aat:300008850"
    ]
},
  "bbox": [],
  "geometry": {"coordinates":[-80.4667,32.3333],"type":"Point"}
}