{
  "id": 7564359,
  "type": "Feature",
  "properties": {
    "tgn:hierarchy":[
        "tgn:7564359",
        "tgn:1000004",
        "tgn:7000198",
        "tgn:7016788",
        "tgn:7029392"
    ],
    "tgn:id":7564359,
    "tgn:name:en":"Basi ka Dhora",
    "tgn:placetype":[
        "aat:300008750"
    ]
},
  "bbox": [],
  "geometry": {"coordinates":[74.237961,28.213684],"type":"Point"}
}