{
  "id": 2460483,
  "type": "Feature",
  "properties": {
    "tgn:hierarchy":[
        "tgn:2460483",
        "tgn:7002659",
        "tgn:1000001",
        "tgn:7012149",
        "tgn:2000062",
        "tgn:7029392"
    ],
    "tgn:id":2460483,
    "tgn:name":"Little Sandy Creek",
    "tgn:placetype":[
        "aat:300008706"
    ]
},
  "bbox": [],
  "geometry": {"coordinates":[-87.45,33.1333],"type":"Point"}
}