{
  "id": 7518054,
  "type": "Feature",
  "properties": {
    "tgn:hierarchy":[
        "tgn:7518054",
        "tgn:1009227",
        "tgn:1000226",
        "tgn:7520095",
        "tgn:1000006",
        "tgn:7029392"
    ],
    "tgn:id":7518054,
    "tgn:name:en":"Maitland Creek",
    "tgn:placetype":[
        "aat:300008699"
    ]
},
  "bbox": [],
  "geometry": {"coordinates":[172.983333,-41.683333],"type":"Point"}
}