{
  "id": 7483100,
  "type": "Feature",
  "properties": {
    "tgn:hierarchy":[
        "tgn:7483100",
        "tgn:7468018",
        "tgn:1000004",
        "tgn:1000141",
        "tgn:7029392"
    ],
    "tgn:id":7483100,
    "tgn:name":"Jiananyunfeng",
    "tgn:placetype":[
        "aat:300008798"
    ]
},
  "bbox": [],
  "geometry": {"coordinates":[120.730833,23.611111],"type":"Point"}
}