{
  "id": 1051796,
  "type": "Feature",
  "properties": {
    "tgn:hierarchy":[
        "tgn:1051796",
        "tgn:1000004",
        "tgn:7011523",
        "tgn:7002435",
        "tgn:7029392"
    ],
    "tgn:id":1051796,
    "tgn:name":"Zhegalovo",
    "tgn:placetype":[
        "aat:300008347"
    ]
},
  "bbox": [],
  "geometry": {"coordinates":[43.4167,54.7333],"type":"Point"}
}