{
  "id": 7468352,
  "type": "Feature",
  "properties": {
    "tgn:hierarchy":[
        "tgn:7468352",
        "tgn:1000004",
        "tgn:7491221",
        "tgn:1000141",
        "tgn:7029392"
    ],
    "tgn:id":7468352,
    "tgn:name":"Jianhe Li",
    "tgn:placetype":[
        "aat:300387173"
    ]
},
  "bbox": [],
  "geometry": {"coordinates":[121.061944,22.738333],"type":"Point"}
}