{
  "id": 1052760,
  "type": "Feature",
  "properties": {
    "tgn:hierarchy":[
        "tgn:1052760",
        "tgn:1000004",
        "tgn:7011573",
        "tgn:7018214",
        "tgn:7002435",
        "tgn:7029392"
    ],
    "tgn:id":1052760,
    "tgn:name":"Bespyatovo",
    "tgn:placetype":[
        "aat:300008347"
    ]
},
  "bbox": [],
  "geometry": {"coordinates":[38.9167,54.75],"type":"Point"}
}