{
  "id": 7239100,
  "type": "Feature",
  "properties": {
    "tgn:hierarchy":[
        "tgn:7239100",
        "tgn:7003457",
        "tgn:1000003",
        "tgn:1000063",
        "tgn:7018236",
        "tgn:7029392"
    ],
    "tgn:id":7239100,
    "tgn:name":"Groenstraat",
    "tgn:placetype":[
        "aat:300008347"
    ]
},
  "bbox": [],
  "geometry": {"coordinates":[3.833333,50.85],"type":"Point"}
}