{
  "id": 2243943,
  "type": "Feature",
  "properties": {
    "tgn:hierarchy":[
        "tgn:2243943",
        "tgn:1000001",
        "tgn:2000260",
        "tgn:7012149",
        "tgn:7007240",
        "tgn:7029392"
    ],
    "tgn:id":2243943,
    "tgn:name":"Clewis Swamp",
    "tgn:placetype":[
        "aat:300008905"
    ]
},
  "bbox": [],
  "geometry": {"coordinates":[-85.25,30.3667],"type":"Point"}
}