{
  "id": 7314216,
  "type": "Feature",
  "properties": {
    "tgn:hierarchy":[
        "tgn:7314216",
        "tgn:1001702",
        "tgn:1000049",
        "tgn:1000002",
        "tgn:7029392"
    ],
    "tgn:id":7314216,
    "tgn:name":"L\u00f3pez, Islotes",
    "tgn:placetype":[
        "aat:300008791"
    ]
},
  "bbox": [],
  "geometry": {"coordinates":[-72.316667,-54.033333],"type":"Point"}
}