{
  "id": 7105111,
  "type": "Feature",
  "properties": {
    "tgn:hierarchy":[
        "tgn:7105111",
        "tgn:1000003",
        "tgn:7000094",
        "tgn:7000084",
        "tgn:7029392"
    ],
    "tgn:id":7105111,
    "tgn:name":"Scharfstorf",
    "tgn:placetype":[
        "aat:300008347"
    ]
},
  "bbox": [],
  "geometry": {"coordinates":[11.416667,53.833333],"type":"Point"}
}