{
  "id": 2380682,
  "type": "Feature",
  "properties": {
    "tgn:hierarchy":[
        "tgn:2380682",
        "tgn:1000001",
        "tgn:7012149",
        "tgn:2001217",
        "tgn:7007523",
        "tgn:7029392"
    ],
    "tgn:id":2380682,
    "tgn:name":"Haw Branch",
    "tgn:placetype":[
        "aat:300008699"
    ]
},
  "bbox": [],
  "geometry": {"coordinates":[-90.4833,37.55],"type":"Point"}
}