{
  "id": 7553453,
  "type": "Feature",
  "properties": {
    "tgn:hierarchy":[
        "tgn:7553453",
        "tgn:1000004",
        "tgn:7000198",
        "tgn:1001894",
        "tgn:7029392"
    ],
    "tgn:id":7553453,
    "tgn:name:en":"Mungw\u0101ni Kal\u0101n",
    "tgn:placetype":[
        "aat:300008347"
    ]
},
  "bbox": [],
  "geometry": {"coordinates":[79.423352,22.168008],"type":"Point"}
}