{
  "id": 2592135,
  "type": "Feature",
  "properties": {
    "tgn:hierarchy":[
        "tgn:2592135",
        "tgn:1000001",
        "tgn:7012149",
        "tgn:2000891",
        "tgn:7007256",
        "tgn:7029392"
    ],
    "tgn:id":2592135,
    "tgn:name":"Pontons Bay",
    "tgn:placetype":[
        "aat:300008680"
    ]
},
  "bbox": [],
  "geometry": {"coordinates":[-89.75,29.6333],"type":"Point"}
}