{
  "id": 2566179,
  "type": "Feature",
  "properties": {
    "tgn:hierarchy":[
        "tgn:2566179",
        "tgn:1000001",
        "tgn:7012149",
        "tgn:2000930",
        "tgn:7007515",
        "tgn:7029392"
    ],
    "tgn:id":2566179,
    "tgn:name":"Palmer Stream",
    "tgn:placetype":[
        "aat:300008699"
    ]
},
  "bbox": [],
  "geometry": {"coordinates":[-69.7167,45.1667],"type":"Point"}
}