{
  "id": 2715024,
  "type": "Feature",
  "properties": {
    "tgn:hierarchy":[
        "tgn:2715024",
        "tgn:1000001",
        "tgn:7012149",
        "tgn:2001872",
        "tgn:7007825",
        "tgn:7029392"
    ],
    "tgn:id":2715024,
    "tgn:name":"Tennessee River Pulp And Paper West Lake",
    "tgn:placetype":[
        "aat:300006191"
    ]
},
  "bbox": [],
  "geometry": {"coordinates":[-88.2667,35.05],"type":"Point"}
}