{
  "id": 7560842,
  "type": "Feature",
  "properties": {
    "tgn:hierarchy":[
        "tgn:7560842",
        "tgn:1000004",
        "tgn:7000198",
        "tgn:7016722",
        "tgn:7029392"
    ],
    "tgn:id":7560842,
    "tgn:name:en":"Bera",
    "tgn:placetype":[
        "aat:300008347"
    ]
},
  "bbox": [],
  "geometry": {"coordinates":[79.279346,26.433917],"type":"Point"}
}