{
  "id": 7413091,
  "type": "Feature",
  "properties": {
    "tgn:hierarchy":[
        "tgn:7413091",
        "tgn:1000001",
        "tgn:7005598",
        "tgn:7005560",
        "tgn:7029392"
    ],
    "tgn:id":7413091,
    "tgn:name":"El Capul\u00edn",
    "tgn:placetype":[
        "aat:300008347"
    ]
},
  "bbox": [],
  "geometry": {"coordinates":[-97.904167,19.452778],"type":"Point"}
}