{
  "id": 7114846,
  "type": "Feature",
  "properties": {
    "tgn:hierarchy":[
        "tgn:7114846",
        "tgn:1000003",
        "tgn:7003682",
        "tgn:7000084",
        "tgn:7029392"
    ],
    "tgn:id":7114846,
    "tgn:name":"Olkenbach",
    "tgn:placetype":[
        "aat:300008347"
    ]
},
  "bbox": [],
  "geometry": {"coordinates":[6.983333,50.016667],"type":"Point"}
}