{
  "id": 2273269,
  "type": "Feature",
  "properties": {
    "tgn:hierarchy":[
        "tgn:2273269",
        "tgn:1000001",
        "tgn:7012149",
        "tgn:2002039",
        "tgn:7007826",
        "tgn:7029392"
    ],
    "tgn:id":2273269,
    "tgn:name":"Cypress Cove",
    "tgn:placetype":[
        "aat:300132316"
    ]
},
  "bbox": [],
  "geometry": {"coordinates":[-98.9833,29.5833],"type":"Point"}
}