{
  "id": 2495976,
  "type": "Feature",
  "properties": {
    "tgn:hierarchy":[
        "tgn:2495976",
        "tgn:2002139",
        "tgn:1000001",
        "tgn:7012149",
        "tgn:7007919",
        "tgn:7029392"
    ],
    "tgn:id":2495976,
    "tgn:name":"Masons Corner",
    "tgn:placetype":[
        "aat:300008347"
    ]
},
  "bbox": [],
  "geometry": {"coordinates":[-77.8833,37.4167],"type":"Point"}
}