{
  "id": 2316910,
  "type": "Feature",
  "properties": {
    "tgn:hierarchy":[
        "tgn:2316910",
        "tgn:1000001",
        "tgn:2002314",
        "tgn:7012149",
        "tgn:7007922",
        "tgn:7029392"
    ],
    "tgn:id":2316910,
    "tgn:name":"Emerson Lake",
    "tgn:placetype":[
        "aat:300006191"
    ]
},
  "bbox": [],
  "geometry": {"coordinates":[-90.8833,44.5167],"type":"Point"}
}