<<<<<<< HEAD
{
  "id": 7376513,
  "type": "Feature",
  "properties": {
    "tgn:hierarchy":[
        "tgn:7376513",
        "tgn:1000001",
        "tgn:7005589",
        "tgn:7005560",
        "tgn:7029392"
    ],
    "tgn:id":7376513,
    "tgn:name":"Las Lajitas",
    "tgn:placetype":[
        "aat:300008347"
    ]
},
  "bbox": [],
  "geometry": {"coordinates":[-99.416667,26.45],"type":"Point"}
}
=======
{"geometry":{"type":"Point","coordinates":[-99.416667,26.450000]},"type":"Feature","properties":{"hierarchy":["tgn:7376513","tgn:1000001","tgn:7005589","tgn:7005560","tgn:7029392"],"placetype":["aat:300008347"],"id":7376513,"name:xx":"Las Lajitas"}}
>>>>>>> 03f74aca74312dbeaf24d7e61306dd6a786dc3d0
