{
  "id": 2693606,
  "type": "Feature",
  "properties": {
    "tgn:hierarchy":[
        "tgn:2693606",
        "tgn:1000001",
        "tgn:7012149",
        "tgn:2002111",
        "tgn:7007827",
        "tgn:7029392"
    ],
    "tgn:id":2693606,
    "tgn:name":"Stephens Canyon",
    "tgn:placetype":[
        "aat:300008761"
    ]
},
  "bbox": [],
  "geometry": {"coordinates":[-113.0167,37.6833],"type":"Point"}
}