{
  "id": 7238892,
  "type": "Feature",
  "properties": {
    "tgn:hierarchy":[
        "tgn:7238892",
        "tgn:7007877",
        "tgn:1000003",
        "tgn:1000063",
        "tgn:4012014",
        "tgn:7029392"
    ],
    "tgn:id":7238892,
    "tgn:name":"Haut Doux",
    "tgn:placetype":[
        "aat:300008347"
    ]
},
  "bbox": [],
  "geometry": {"coordinates":[3.593611,50.636818],"type":"Point"}
}