{
  "id": 2644084,
  "type": "Feature",
  "properties": {
    "tgn:hierarchy":[
        "tgn:2644084",
        "tgn:1000001",
        "tgn:7012149",
        "tgn:7007157",
        "tgn:1002867",
        "tgn:7029392"
    ],
    "tgn:id":2644084,
    "tgn:name":"Santa Maria Canyon",
    "tgn:placetype":[
        "aat:300008761"
    ]
},
  "bbox": [],
  "geometry": {"coordinates":[-120.25,34.9167],"type":"Point"}
}