{
  "id": 7586195,
  "type": "Feature",
  "properties": {
    "tgn:hierarchy":[
        "tgn:7586195",
        "tgn:1000004",
        "tgn:7000198",
        "tgn:7000799",
        "tgn:7029392"
    ],
    "tgn:id":7586195,
    "tgn:name:en":"Tsondar",
    "tgn:placetype":[
        "aat:300008347"
    ]
},
  "bbox": [],
  "geometry": {"coordinates":[74.911221,34.321115],"type":"Point"}
}