{
  "id": 2323582,
  "type": "Feature",
  "properties": {
    "tgn:hierarchy":[
        "tgn:2323582",
        "tgn:1000001",
        "tgn:7012149",
        "tgn:1002451",
        "tgn:7007919",
        "tgn:7029392"
    ],
    "tgn:id":2323582,
    "tgn:name":"Farrington",
    "tgn:placetype":[
        "aat:300008347"
    ]
},
  "bbox": [],
  "geometry": {"coordinates":[-77.5833,37.7167],"type":"Point"}
}