<<<<<<< HEAD
{
  "id": 7023377,
  "type": "Feature",
  "properties": {
    "tgn:hierarchy":[
        "tgn:7023377",
        "tgn:1000001",
        "tgn:7012149",
        "tgn:7007524",
        "tgn:7029392"
    ],
    "tgn:id":7023377,
    "tgn:name":"Martinsdale Reservoir",
    "tgn:placetype":[
        "aat:300006191"
    ]
},
  "bbox": [],
  "geometry": {"coordinates":[-110.2667,46.45],"type":"Point"}
}
=======
{"geometry":{"type":"Point","coordinates":[-110.266700,46.450000]},"type":"Feature","properties":{"hierarchy":["tgn:7023377","tgn:1000001","tgn:7012149","tgn:7007524","tgn:7029392"],"placetype":["aat:300006191"],"id":7023377,"name:xx":"Martinsdale Reservoir"}}
>>>>>>> 03f74aca74312dbeaf24d7e61306dd6a786dc3d0
