{
  "id": 7199746,
  "type": "Feature",
  "properties": {
    "tgn:hierarchy":[
        "tgn:7199746",
        "tgn:7003669",
        "tgn:1000003",
        "tgn:7000084",
        "tgn:7029392"
    ],
    "tgn:id":7199746,
    "tgn:name":"Edlhof",
    "tgn:placetype":[
        "aat:300000206"
    ]
},
  "bbox": [],
  "geometry": {"coordinates":[13.566667,48.566667],"type":"Point"}
}