{
  "id": 7043714,
  "type": "Feature",
  "properties": {
    "tgn:hierarchy":[
        "tgn:7043714",
        "tgn:7003005",
        "tgn:7003014",
        "tgn:1000003",
        "tgn:1000080",
        "tgn:7029392"
    ],
    "tgn:id":7043714,
    "tgn:name":"Galdo",
    "tgn:placetype":[
        "aat:300008347"
    ]
},
  "bbox": [],
  "geometry": {"coordinates":[15.316667,40.566667],"type":"Point"}
}