{
  "id": 7173491,
  "type": "Feature",
  "properties": {
    "tgn:hierarchy":[
        "tgn:7173491",
        "tgn:1000003",
        "tgn:7000094",
        "tgn:7000084",
        "tgn:7029392"
    ],
    "tgn:id":7173491,
    "tgn:name":"Gro\u00df B\u00fcnzow",
    "tgn:placetype":[
        "aat:300008347"
    ]
},
  "bbox": [],
  "geometry": {"coordinates":[13.666667,53.933333],"type":"Point"}
}