{
  "id": 7415911,
  "type": "Feature",
  "properties": {
    "tgn:hierarchy":[
        "tgn:7415911",
        "tgn:1000001",
        "tgn:7005591",
        "tgn:7005560",
        "tgn:7029392"
    ],
    "tgn:id":7415911,
    "tgn:name:es":"Santa Mar\u00eda Coyotepec",
    "tgn:placetype":[
        "aat:300008347"
    ]
},
  "bbox": [],
  "geometry": {"coordinates":[-96.699167,16.976944],"type":"Point"}
}