{
  "id": 2419015,
  "type": "Feature",
  "properties": {
    "tgn:hierarchy":[
        "tgn:2419015",
        "tgn:1000001",
        "tgn:2002146",
        "tgn:7012149",
        "tgn:7007919",
        "tgn:7029392"
    ],
    "tgn:id":2419015,
    "tgn:name":"James River Cave",
    "tgn:placetype":[
        "aat:300008746"
    ]
},
  "bbox": [],
  "geometry": {"coordinates":[-79.7333,37.5667],"type":"Point"}
}