{
  "id": 7007664,
  "type": "Feature",
  "properties": {
    "tgn:hierarchy":[
        "tgn:7007664",
        "tgn:7002807",
        "tgn:1000003",
        "tgn:7003837",
        "tgn:1000095",
        "tgn:7029392"
    ],
    "tgn:id":7007664,
    "tgn:name:es":"M\u00e9rida",
    "tgn:placetype":[
        "aat:300008347",
        "aat:300387218",
        "aat:300387220",
        "aat:300008375"
    ]
},
  "bbox": [],
  "geometry": {"coordinates":[-6.333333,38.916667],"type":"Point"}
}