{
  "id": 7132766,
  "type": "Feature",
  "properties": {
    "tgn:hierarchy":[
        "tgn:7132766",
        "tgn:1000003",
        "tgn:7003676",
        "tgn:7000084",
        "tgn:7029392"
    ],
    "tgn:id":7132766,
    "tgn:name":"Morgenland",
    "tgn:placetype":[
        "aat:300000206"
    ]
},
  "bbox": [],
  "geometry": {"coordinates":[8.75,52.633333],"type":"Point"}
}