{
  "id": 7451336,
  "type": "Feature",
  "properties": {
    "tgn:hierarchy":[
        "tgn:7451336",
        "tgn:7002444",
        "tgn:1000003",
        "tgn:7008072",
        "tgn:7008591",
        "tgn:7029392"
    ],
    "tgn:id":7451336,
    "tgn:name:en":"Dye Water",
    "tgn:placetype":[
        "aat:300008699"
    ]
},
  "bbox": [],
  "geometry": {"coordinates":[-2.45,55.833333],"type":"Point"}
}