{
  "id": 7090591,
  "type": "Feature",
  "properties": {
    "tgn:hierarchy":[
        "tgn:7090591",
        "tgn:7003692",
        "tgn:1000003",
        "tgn:7000084",
        "tgn:7029392"
    ],
    "tgn:id":7090591,
    "tgn:name":"Untersch\u00f6nbrunn",
    "tgn:placetype":[
        "aat:300008347"
    ]
},
  "bbox": [],
  "geometry": {"coordinates":[8.933333,49.416667],"type":"Point"}
}