{
  "id": 2224304,
  "type": "Feature",
  "properties": {
    "tgn:hierarchy":[
        "tgn:2224304",
        "tgn:1000001",
        "tgn:7012149",
        "tgn:7007157",
        "tgn:1002957",
        "tgn:7029392"
    ],
    "tgn:id":2224304,
    "tgn:name":"Cascade Creek",
    "tgn:placetype":[
        "aat:300008706"
    ]
},
  "bbox": [],
  "geometry": {"coordinates":[-119.9167,38.2667],"type":"Point"}
}