{
  "id": 7554320,
  "type": "Feature",
  "properties": {
    "tgn:hierarchy":[
        "tgn:7554320",
        "tgn:1000004",
        "tgn:7018318",
        "tgn:7000198",
        "tgn:7029392"
    ],
    "tgn:id":7554320,
    "tgn:name:en":"Nogorcem",
    "tgn:placetype":[
        "aat:300008347"
    ]
},
  "bbox": [],
  "geometry": {"coordinates":[74.033333,15.016667],"type":"Point"}
}