{
  "id": 2487812,
  "type": "Feature",
  "properties": {
    "tgn:hierarchy":[
        "tgn:2487812",
        "tgn:1000001",
        "tgn:2002109",
        "tgn:7012149",
        "tgn:7007827",
        "tgn:7029392"
    ],
    "tgn:id":2487812,
    "tgn:name":"Left Fork Sanford Creek",
    "tgn:placetype":[
        "aat:300008706"
    ]
},
  "bbox": [],
  "geometry": {"coordinates":[-112.3167,37.9833],"type":"Point"}
}