{
  "id": 7593542,
  "type": "Feature",
  "properties": {
    "tgn:hierarchy":[
        "tgn:7593542",
        "tgn:7005424",
        "tgn:1000001",
        "tgn:7005388",
        "tgn:7029392"
    ],
    "tgn:id":7593542,
    "tgn:name":"Esperanza",
    "tgn:placetype":[
        "aat:300008347"
    ]
},
  "bbox": [],
  "geometry": {"coordinates":[-70.985,19.584],"type":"Point"}
}