{
  "id": 7354793,
  "type": "Feature",
  "properties": {
    "tgn:hierarchy":[
        "tgn:7354793",
        "tgn:7005579",
        "tgn:1000001",
        "tgn:7005560",
        "tgn:7029392"
    ],
    "tgn:id":7354793,
    "tgn:name":"Churubusco",
    "tgn:placetype":[
        "aat:300008347"
    ]
},
  "bbox": [],
  "geometry": {"coordinates":[-102.283333,21.75],"type":"Point"}
}