{
  "id": 7135270,
  "type": "Feature",
  "properties": {
    "tgn:hierarchy":[
        "tgn:7135270",
        "tgn:1000003",
        "tgn:7003676",
        "tgn:7000084",
        "tgn:7029392"
    ],
    "tgn:id":7135270,
    "tgn:name":"M\u00f6wensteert",
    "tgn:placetype":[
        "aat:300387036"
    ]
},
  "bbox": [],
  "geometry": {"coordinates":[6.733333,53.516667],"type":"Point"}
}