{
  "id": 7137254,
  "type": "Feature",
  "properties": {
    "tgn:hierarchy":[
        "tgn:7137254",
        "tgn:1000003",
        "tgn:7003676",
        "tgn:7000084",
        "tgn:7029392"
    ],
    "tgn:id":7137254,
    "tgn:name":"Liet-Berg",
    "tgn:placetype":[
        "aat:300008777"
    ]
},
  "bbox": [],
  "geometry": {"coordinates":[9.883333,51.85],"type":"Point"}
}