{
  "id": 2180920,
  "type": "Feature",
  "properties": {
    "tgn:hierarchy":[
        "tgn:2180920",
        "tgn:1000001",
        "tgn:7012149",
        "tgn:2001206",
        "tgn:7007523",
        "tgn:7029392"
    ],
    "tgn:id":2180920,
    "tgn:name":"Blowing Springs",
    "tgn:placetype":[
        "aat:300008697"
    ]
},
  "bbox": [],
  "geometry": {"coordinates":[-91.6667,36.85],"type":"Point"}
}