{
  "id": 2669324,
  "type": "Feature",
  "properties": {
    "tgn:hierarchy":[
        "tgn:2669324",
        "tgn:1000001",
        "tgn:7006451",
        "tgn:2000094",
        "tgn:7012149",
        "tgn:7029392"
    ],
    "tgn:id":2669324,
    "tgn:name":"Slick Rock Basin",
    "tgn:placetype":[
        "aat:300386845"
    ]
},
  "bbox": [],
  "geometry": {"coordinates":[-109.35,32.7667],"type":"Point"}
}