<<<<<<< HEAD
{
  "id": 2257958,
  "type": "Feature",
  "properties": {
    "tgn:hierarchy":[
        "tgn:2257958",
        "tgn:1000001",
        "tgn:7012149",
        "tgn:7007157",
        "tgn:1002858",
        "tgn:7029392"
    ],
    "tgn:id":2257958,
    "tgn:name":"Corte Madera Mountain",
    "tgn:placetype":[
        "aat:300008798"
    ]
},
  "bbox": [],
  "geometry": {"coordinates":[-116.5833,32.75],"type":"Point"}
}
=======
{"geometry":{"type":"Point","coordinates":[-116.583300,32.750000]},"type":"Feature","properties":{"hierarchy":["tgn:2257958","tgn:1000001","tgn:7012149","tgn:7007157","tgn:1002858","tgn:7029392"],"placetype":["aat:300008798"],"id":2257958,"name:xx":"Corte Madera Mountain"}}
>>>>>>> 03f74aca74312dbeaf24d7e61306dd6a786dc3d0
