{
  "id": 2200654,
  "type": "Feature",
  "properties": {
    "tgn:hierarchy":[
        "tgn:2200654",
        "tgn:1000001",
        "tgn:7012149",
        "tgn:2000799",
        "tgn:7007255",
        "tgn:7029392"
    ],
    "tgn:id":2200654,
    "tgn:name":"Brushy Slough",
    "tgn:placetype":[
        "aat:300008699"
    ]
},
  "bbox": [],
  "geometry": {"coordinates":[-87.6833,37.85],"type":"Point"}
}