{
  "id": 2001219,
  "type": "Feature",
  "properties": {
    "tgn:hierarchy":[
        "tgn:2001219",
        "tgn:1000001",
        "tgn:7012149",
        "tgn:7007523",
        "tgn:7029392"
    ],
    "tgn:id":2001219,
    "tgn:name":"Mississippi",
    "tgn:placetype":[
        "aat:300387145",
        "aat:300000771"
    ]
},
  "bbox": [],
  "geometry": {"coordinates":[-89.3167,36.8167],"type":"Point"}
}