{
  "id": 2698266,
  "type": "Feature",
  "properties": {
    "tgn:hierarchy":[
        "tgn:2698266",
        "tgn:1000001",
        "tgn:7012149",
        "tgn:2001289",
        "tgn:7007524",
        "tgn:7029392"
    ],
    "tgn:id":2698266,
    "tgn:name":"Stoyanoff Lake",
    "tgn:placetype":[
        "aat:300006191"
    ]
},
  "bbox": [],
  "geometry": {"coordinates":[-111.25,46.6833],"type":"Point"}
}