{
  "id": 7584856,
  "type": "Feature",
  "properties": {
    "tgn:hierarchy":[
        "tgn:7584856",
        "tgn:1000004",
        "tgn:7000198",
        "tgn:1001894",
        "tgn:7029392"
    ],
    "tgn:id":7584856,
    "tgn:name:en":"Gambh\u012briya",
    "tgn:placetype":[
        "aat:300008347"
    ]
},
  "bbox": [],
  "geometry": {"coordinates":[78.108928,24.058561],"type":"Point"}
}