{
  "id": 7264599,
  "type": "Feature",
  "properties": {
    "tgn:hierarchy":[
        "tgn:7264599",
        "tgn:1000003",
        "tgn:7003613",
        "tgn:7016845",
        "tgn:7029392"
    ],
    "tgn:id":7264599,
    "tgn:name:nl":"Linthorst-Homanpolder",
    "tgn:placetype":[
        "aat:300006163"
    ]
},
  "bbox": [],
  "geometry": {"coordinates":[6.45,53.416667],"type":"Point"}
}