{
  "id": 2587206,
  "type": "Feature",
  "properties": {
    "tgn:hierarchy":[
        "tgn:2587206",
        "tgn:1000001",
        "tgn:7012149",
        "tgn:7007523",
        "tgn:7029392"
    ],
    "tgn:id":2587206,
    "tgn:name":"Platte Purchase",
    "tgn:placetype":[
        "aat:300055621"
    ]
},
  "bbox": [],
  "geometry": {"coordinates":[-95.75,40.55],"type":"Point"}
}