{
  "id": 7493332,
  "type": "Feature",
  "properties": {
    "tgn:hierarchy":[
        "tgn:7493332",
        "tgn:7487020",
        "tgn:1000004",
        "tgn:1000141",
        "tgn:7029392"
    ],
    "tgn:id":7493332,
    "tgn:name":"Lixiangping",
    "tgn:placetype":[
        "aat:300008347"
    ]
},
  "bbox": [],
  "geometry": {"coordinates":[120.884017,24.461693],"type":"Point"}
}