{
  "id": 2418076,
  "type": "Feature",
  "properties": {
    "tgn:hierarchy":[
        "tgn:2418076",
        "tgn:1000001",
        "tgn:2001413",
        "tgn:7012149",
        "tgn:7007526",
        "tgn:7029392"
    ],
    "tgn:id":2418076,
    "tgn:name":"Jackson Shaft",
    "tgn:placetype":[
        "aat:300000390"
    ]
},
  "bbox": [],
  "geometry": {"coordinates":[-115.9833,39.4833],"type":"Point"}
}