{
  "id": 7002158,
  "type": "Feature",
  "properties": {
    "tgn:hierarchy":[
        "tgn:7002158",
        "tgn:7002161",
        "tgn:1000004",
        "tgn:1000108",
        "tgn:7029392"
    ],
    "tgn:id":7002158,
    "tgn:name":"Pyu",
    "tgn:placetype":[
        "aat:300008347"
    ]
},
  "bbox": [],
  "geometry": {"coordinates":[96.4667,18.4833],"type":"Point"}
}