{
  "id": 7368974,
  "type": "Feature",
  "properties": {
    "tgn:hierarchy":[
        "tgn:7368974",
        "tgn:7005578",
        "tgn:1000001",
        "tgn:7005560",
        "tgn:7029392"
    ],
    "tgn:id":7368974,
    "tgn:name":"Ju\u00e1rez",
    "tgn:placetype":[
        "aat:300008347"
    ]
},
  "bbox": [],
  "geometry": {"coordinates":[-90.833333,19.15],"type":"Point"}
}