{
  "id": 2691831,
  "type": "Feature",
  "properties": {
    "tgn:hierarchy":[
        "tgn:2691831",
        "tgn:1000001",
        "tgn:7006451",
        "tgn:2000091",
        "tgn:7012149",
        "tgn:7029392"
    ],
    "tgn:id":2691831,
    "tgn:name":"Starvation Canyon",
    "tgn:placetype":[
        "aat:300008761"
    ]
},
  "bbox": [],
  "geometry": {"coordinates":[-109.0833,31.5167],"type":"Point"}
}