{
  "id": 2347009,
  "type": "Feature",
  "properties": {
    "tgn:hierarchy":[
        "tgn:2347009",
        "tgn:7006450",
        "tgn:1000001",
        "tgn:7019698",
        "tgn:7012149",
        "tgn:7029392"
    ],
    "tgn:id":2347009,
    "tgn:name":"Gene Lake",
    "tgn:placetype":[
        "aat:300008680"
    ]
},
  "bbox": [],
  "geometry": {"coordinates":[-150.4667,60.8333],"type":"Point"}
}