{
  "id": 2757271,
  "type": "Feature",
  "properties": {
    "tgn:hierarchy":[
        "tgn:2757271",
        "tgn:1000001",
        "tgn:7012149",
        "tgn:2002347",
        "tgn:7007922",
        "tgn:7029392"
    ],
    "tgn:id":2757271,
    "tgn:name":"West Almond",
    "tgn:placetype":[
        "aat:300008347"
    ]
},
  "bbox": [],
  "geometry": {"coordinates":[-89.45,44.2833],"type":"Point"}
}