<<<<<<< HEAD
{
  "id": 7486112,
  "type": "Feature",
  "properties": {
    "tgn:hierarchy":[
        "tgn:7486112",
        "tgn:7001010",
        "tgn:1000004",
        "tgn:1000141",
        "tgn:7029392"
    ],
    "tgn:id":7486112,
    "tgn:name":"Wenquan Qiao",
    "tgn:placetype":[
        "aat:300007836"
    ]
},
  "bbox": [],
  "geometry": {"coordinates":[121.490833,24.201944],"type":"Point"}
}
=======
{"geometry":{"type":"Point","coordinates":[121.490833,24.201944]},"type":"Feature","properties":{"hierarchy":["tgn:7486112","tgn:7001010","tgn:1000004","tgn:1000141","tgn:7029392"],"placetype":["aat:300007836"],"id":7486112,"name:xx":"Wenquan Qiao"}}
>>>>>>> 03f74aca74312dbeaf24d7e61306dd6a786dc3d0
