{
  "id": 2220105,
  "type": "Feature",
  "properties": {
    "tgn:hierarchy":[
        "tgn:2220105",
        "tgn:7006450",
        "tgn:1000001",
        "tgn:2124089",
        "tgn:7012149",
        "tgn:7029392"
    ],
    "tgn:id":2220105,
    "tgn:name":"Canyon Island",
    "tgn:placetype":[
        "aat:300008791"
    ]
},
  "bbox": [],
  "geometry": {"coordinates":[-133.6667,58.5333],"type":"Point"}
}