{
  "id": 7520592,
  "type": "Feature",
  "properties": {
    "tgn:hierarchy":[
        "tgn:7520592",
        "tgn:7001242",
        "tgn:1001075",
        "tgn:7016833",
        "tgn:7029392"
    ],
    "tgn:id":7520592,
    "tgn:name:en":"Al Kafr al Jad\u012bd",
    "tgn:placetype":[
        "aat:300008347"
    ]
},
  "bbox": [],
  "geometry": {"coordinates":[30.640485,31.065649],"type":"Point"}
}