<<<<<<< HEAD
{
  "id": 7245542,
  "type": "Feature",
  "properties": {
    "tgn:hierarchy":[
        "tgn:7245542",
        "tgn:7007877",
        "tgn:1000003",
        "tgn:1000063",
        "tgn:4012014",
        "tgn:7029392"
    ],
    "tgn:id":7245542,
    "tgn:name":"Beaumont, Ruisseau de",
    "tgn:placetype":[
        "aat:300008699"
    ]
},
  "bbox": [],
  "geometry": {"coordinates":[4.25,50.216667],"type":"Point"}
}
=======
{"geometry":{"type":"Point","coordinates":[4.250000,50.216667]},"type":"Feature","properties":{"hierarchy":["tgn:7245542","tgn:7007877","tgn:1000003","tgn:1000063","tgn:4012014","tgn:7029392"],"placetype":["aat:300008699"],"id":7245542,"name:xx":"Beaumont, Ruisseau de"}}
>>>>>>> 03f74aca74312dbeaf24d7e61306dd6a786dc3d0
