<<<<<<< HEAD
{
  "id": 7117938,
  "type": "Feature",
  "properties": {
    "tgn:hierarchy":[
        "tgn:7117938",
        "tgn:7003669",
        "tgn:1000003",
        "tgn:7000084",
        "tgn:7029392"
    ],
    "tgn:id":7117938,
    "tgn:name":"Oberschwillach",
    "tgn:placetype":[
        "aat:300008347"
    ]
},
  "bbox": [],
  "geometry": {"coordinates":[11.916667,48.216667],"type":"Point"}
}
=======
{"geometry":{"type":"Point","coordinates":[11.916667,48.216667]},"type":"Feature","properties":{"hierarchy":["tgn:7117938","tgn:7003669","tgn:1000003","tgn:7000084","tgn:7029392"],"placetype":["aat:300008347"],"id":7117938,"name:xx":"Oberschwillach"}}
>>>>>>> 03f74aca74312dbeaf24d7e61306dd6a786dc3d0
