{
  "id": 7117938,
  "type": "Feature",
  "properties": {
    "tgn:hierarchy":[
        "tgn:7117938",
        "tgn:7003669",
        "tgn:1000003",
        "tgn:7000084",
        "tgn:7029392"
    ],
    "tgn:id":7117938,
    "tgn:name":"Oberschwillach",
    "tgn:placetype":[
        "aat:300008347"
    ]
},
  "bbox": [],
  "geometry": {"coordinates":[11.916667,48.216667],"type":"Point"}
}