{
  "id": 1116003,
  "type": "Feature",
  "properties": {
    "tgn:hierarchy":[
        "tgn:1116003",
        "tgn:7005685",
        "tgn:1000001",
        "tgn:7013154",
        "tgn:7029392"
    ],
    "tgn:id":1116003,
    "tgn:name":"Crane Lake",
    "tgn:placetype":[
        "aat:300008680"
    ]
},
  "bbox": [],
  "geometry": {"coordinates":[-79.95,45.2167],"type":"Point"}
}