{
  "id": 1029815,
  "type": "Feature",
  "properties": {
    "tgn:hierarchy":[
        "tgn:1029815",
        "tgn:7002445",
        "tgn:1000003",
        "tgn:7008143",
        "tgn:7008591",
        "tgn:7029392"
    ],
    "tgn:id":1029815,
    "tgn:name:en":"Leintwardine",
    "tgn:placetype":[
        "aat:300008347",
        "aat:300387007",
        "aat:300387238",
        "aat:300006909",
        "aat:300008372"
    ]
},
  "bbox": [],
  "geometry": {"coordinates":[-2.866667,52.366667],"type":"Point"}
}