{
  "id": 7358870,
  "type": "Feature",
  "properties": {
    "tgn:hierarchy":[
        "tgn:7358870",
        "tgn:7005581",
        "tgn:1000001",
        "tgn:7005560",
        "tgn:7029392"
    ],
    "tgn:id":7358870,
    "tgn:name":"El Aguaje",
    "tgn:placetype":[
        "aat:300008347"
    ]
},
  "bbox": [],
  "geometry": {"coordinates":[-105.716667,26.916667],"type":"Point"}
}