<<<<<<< HEAD
{
  "id": 2409704,
  "type": "Feature",
  "properties": {
    "tgn:hierarchy":[
        "tgn:2409704",
        "tgn:7006450",
        "tgn:1000001",
        "tgn:7012149",
        "tgn:2124005",
        "tgn:7029392"
    ],
    "tgn:id":2409704,
    "tgn:name":"Ikiakpaurak Valley",
    "tgn:placetype":[
        "aat:300008761"
    ]
},
  "bbox": [],
  "geometry": {"coordinates":[-145.3333,69.45],"type":"Point"}
}
=======
{"geometry":{"type":"Point","coordinates":[-145.333300,69.450000]},"type":"Feature","properties":{"hierarchy":["tgn:2409704","tgn:7006450","tgn:1000001","tgn:7012149","tgn:2124005","tgn:7029392"],"placetype":["aat:300008761"],"id":2409704,"name:xx":"Ikiakpaurak Valley"}}
>>>>>>> 03f74aca74312dbeaf24d7e61306dd6a786dc3d0
