{
  "id": 2417292,
  "type": "Feature",
  "properties": {
    "tgn:hierarchy":[
        "tgn:2417292",
        "tgn:1000001",
        "tgn:7012149",
        "tgn:2001556",
        "tgn:7007709",
        "tgn:7029392"
    ],
    "tgn:id":2417292,
    "tgn:name":"Jacks Creek",
    "tgn:placetype":[
        "aat:300008706"
    ]
},
  "bbox": [],
  "geometry": {"coordinates":[-82.3333,35.9167],"type":"Point"}
}