{
  "id": 7183638,
  "type": "Feature",
  "properties": {
    "tgn:hierarchy":[
        "tgn:7183638",
        "tgn:1000003",
        "tgn:7003687",
        "tgn:7000084",
        "tgn:7029392"
    ],
    "tgn:id":7183638,
    "tgn:name":"G\u00f6hren",
    "tgn:placetype":[
        "aat:300008347"
    ]
},
  "bbox": [],
  "geometry": {"coordinates":[12.133333,51.35],"type":"Point"}
}