{
  "id": 2695961,
  "type": "Feature",
  "properties": {
    "tgn:hierarchy":[
        "tgn:2695961",
        "tgn:1000001",
        "tgn:7012149",
        "tgn:7007250",
        "tgn:7029392"
    ],
    "tgn:id":2695961,
    "tgn:name":"Stockton Creek",
    "tgn:placetype":[
        "aat:300008706"
    ]
},
  "bbox": [],
  "geometry": {"coordinates":[-111.8667,42.3333],"type":"Point"}
}