{
  "id": 1111701,
  "type": "Feature",
  "properties": {
    "tgn:hierarchy":[
        "tgn:1111701",
        "tgn:7002445",
        "tgn:1000003",
        "tgn:7011961",
        "tgn:7008591",
        "tgn:7029392"
    ],
    "tgn:id":1111701,
    "tgn:name":"Lydden",
    "tgn:placetype":[
        "aat:300008707"
    ]
},
  "bbox": [],
  "geometry": {"coordinates":[-2.3667,50.9333],"type":"Point"}
}