{
  "id": 7542990,
  "type": "Feature",
  "properties": {
    "tgn:hierarchy":[
        "tgn:7542990",
        "tgn:7001242",
        "tgn:7016833",
        "tgn:7001336",
        "tgn:7029392"
    ],
    "tgn:id":7542990,
    "tgn:name:en":"Umm Masma', Jabal",
    "tgn:placetype":[
        "aat:300008795"
    ]
},
  "bbox": [],
  "geometry": {"coordinates":[34.264488,28.675323],"type":"Point"}
}