{
  "id": 2265081,
  "type": "Feature",
  "properties": {
    "tgn:hierarchy":[
        "tgn:2265081",
        "tgn:2000946",
        "tgn:1000001",
        "tgn:7012149",
        "tgn:7007520",
        "tgn:7029392"
    ],
    "tgn:id":2265081,
    "tgn:name":"Cranberry Lake",
    "tgn:placetype":[
        "aat:300008680"
    ]
},
  "bbox": [],
  "geometry": {"coordinates":[-83.5833,44.1167],"type":"Point"}
}