{
  "id": 7423518,
  "type": "Feature",
  "properties": {
    "tgn:hierarchy":[
        "tgn:7423518",
        "tgn:1000001",
        "tgn:7005590",
        "tgn:7005560",
        "tgn:7029392"
    ],
    "tgn:id":7423518,
    "tgn:name":"La Cebadilla",
    "tgn:placetype":[
        "aat:300008347"
    ]
},
  "bbox": [],
  "geometry": {"coordinates":[-101.841667,19.1175],"type":"Point"}
}