{
  "id": 7358076,
  "type": "Feature",
  "properties": {
    "tgn:hierarchy":[
        "tgn:7358076",
        "tgn:7005587",
        "tgn:1000001",
        "tgn:7005560",
        "tgn:7029392"
    ],
    "tgn:id":7358076,
    "tgn:name":"Dado",
    "tgn:placetype":[
        "aat:300008347"
    ]
},
  "bbox": [],
  "geometry": {"coordinates":[-99.333333,20.316667],"type":"Point"}
}