{
  "id": 2099343,
  "type": "Feature",
  "properties": {
    "tgn:hierarchy":[
        "tgn:2099343",
        "tgn:1000001",
        "tgn:7012149",
        "tgn:2001854",
        "tgn:7007825",
        "tgn:7029392"
    ],
    "tgn:id":2099343,
    "tgn:name":"Grassy Cove",
    "tgn:placetype":[
        "aat:300008347"
    ]
},
  "bbox": [],
  "geometry": {"coordinates":[-84.9167,35.8333],"type":"Point"}
}