{
  "id": 2245243,
  "type": "Feature",
  "properties": {
    "tgn:hierarchy":[
        "tgn:2245243",
        "tgn:1000001",
        "tgn:1002359",
        "tgn:7012149",
        "tgn:7007517",
        "tgn:7029392"
    ],
    "tgn:id":2245243,
    "tgn:name":"Club Head Creek",
    "tgn:placetype":[
        "aat:300008706"
    ]
},
  "bbox": [],
  "geometry": {"coordinates":[-70.8333,42.7333],"type":"Point"}
}