<<<<<<< HEAD
{
  "id": 2155029,
  "type": "Feature",
  "properties": {
    "tgn:hierarchy":[
        "tgn:2155029",
        "tgn:1000001",
        "tgn:1002218",
        "tgn:7012149",
        "tgn:7007157",
        "tgn:7029392"
    ],
    "tgn:id":2155029,
    "tgn:name":"Bear Lake",
    "tgn:placetype":[
        "aat:300008680"
    ]
},
  "bbox": [],
  "geometry": {"coordinates":[-121.6667,39.9167],"type":"Point"}
}
=======
{"geometry":{"type":"Point","coordinates":[-121.666700,39.916700]},"type":"Feature","properties":{"hierarchy":["tgn:2155029","tgn:1000001","tgn:1002218","tgn:7012149","tgn:7007157","tgn:7029392"],"placetype":["aat:300008680"],"id":2155029,"name:xx":"Bear Lake"}}
>>>>>>> 03f74aca74312dbeaf24d7e61306dd6a786dc3d0
