{
  "id": 2155029,
  "type": "Feature",
  "properties": {
    "tgn:hierarchy":[
        "tgn:2155029",
        "tgn:1000001",
        "tgn:1002218",
        "tgn:7012149",
        "tgn:7007157",
        "tgn:7029392"
    ],
    "tgn:id":2155029,
    "tgn:name":"Bear Lake",
    "tgn:placetype":[
        "aat:300008680"
    ]
},
  "bbox": [],
  "geometry": {"coordinates":[-121.6667,39.9167],"type":"Point"}
}