<<<<<<< HEAD
{
  "id": 2159787,
  "type": "Feature",
  "properties": {
    "tgn:hierarchy":[
        "tgn:2159787",
        "tgn:1000001",
        "tgn:7012149",
        "tgn:2000182",
        "tgn:7007157",
        "tgn:7029392"
    ],
    "tgn:id":2159787,
    "tgn:name":"Beech Canal",
    "tgn:placetype":[
        "aat:300006075"
    ]
},
  "bbox": [],
  "geometry": {"coordinates":[-115.5333,32.6833],"type":"Point"}
}
=======
{"geometry":{"type":"Point","coordinates":[-115.533300,32.683300]},"type":"Feature","properties":{"hierarchy":["tgn:2159787","tgn:1000001","tgn:7012149","tgn:2000182","tgn:7007157","tgn:7029392"],"placetype":["aat:300006075"],"id":2159787,"name:xx":"Beech Canal"}}
>>>>>>> 03f74aca74312dbeaf24d7e61306dd6a786dc3d0
