{
  "id": 2765514,
  "type": "Feature",
  "properties": {
    "tgn:hierarchy":[
        "tgn:2765514",
        "tgn:1000001",
        "tgn:2001577",
        "tgn:7012149",
        "tgn:7007705",
        "tgn:7029392"
    ],
    "tgn:id":2765514,
    "tgn:name":"White Butte",
    "tgn:placetype":[
        "aat:300008798"
    ]
},
  "bbox": [],
  "geometry": {"coordinates":[-102.3667,46.5833],"type":"Point"}
}