{
  "id": 7588616,
  "type": "Feature",
  "properties": {
    "tgn:hierarchy":[
        "tgn:7588616",
        "tgn:1000004",
        "tgn:7000198",
        "tgn:1001894",
        "tgn:7029392"
    ],
    "tgn:id":7588616,
    "tgn:name:en":"Samd\u0101ha",
    "tgn:placetype":[
        "aat:300008347"
    ]
},
  "bbox": [],
  "geometry": {"coordinates":[81.031175,27.923376],"type":"Point"}
}