<<<<<<< HEAD
{
  "id": 2331194,
  "type": "Feature",
  "properties": {
    "tgn:hierarchy":[
        "tgn:2331194",
        "tgn:1000001",
        "tgn:7012149",
        "tgn:7019676",
        "tgn:7007566",
        "tgn:7029392"
    ],
    "tgn:id":2331194,
    "tgn:name":"Flat Top Mine",
    "tgn:placetype":[
        "aat:300000390"
    ]
},
  "bbox": [],
  "geometry": {"coordinates":[-107.8167,35.3167],"type":"Point"}
}
=======
{"geometry":{"type":"Point","coordinates":[-107.816700,35.316700]},"type":"Feature","properties":{"hierarchy":["tgn:2331194","tgn:1000001","tgn:7012149","tgn:7019676","tgn:7007566","tgn:7029392"],"placetype":["aat:300000390"],"id":2331194,"name:xx":"Flat Top Mine"}}
>>>>>>> 03f74aca74312dbeaf24d7e61306dd6a786dc3d0
