{
  "id": 7318243,
  "type": "Feature",
  "properties": {
    "tgn:hierarchy":[
        "tgn:7318243",
        "tgn:7016598",
        "tgn:1000049",
        "tgn:1000002",
        "tgn:7029392"
    ],
    "tgn:id":7318243,
    "tgn:name":"Chela, Arroyo de",
    "tgn:placetype":[
        "aat:300008699"
    ]
},
  "bbox": [],
  "geometry": {"coordinates":[-68.683333,-21.433333],"type":"Point"}
}