{
  "id": 7503277,
  "type": "Feature",
  "properties": {
    "tgn:hierarchy":[
        "tgn:7503277",
        "tgn:7001004",
        "tgn:1000004",
        "tgn:1000141",
        "tgn:7029392"
    ],
    "tgn:id":7503277,
    "tgn:name":"Woniu",
    "tgn:placetype":[
        "aat:300008347"
    ]
},
  "bbox": [],
  "geometry": {"coordinates":[120.381944,22.778611],"type":"Point"}
}