{
  "id": 1057399,
  "type": "Feature",
  "properties": {
    "tgn:hierarchy":[
        "tgn:1057399",
        "tgn:1000004",
        "tgn:7011572",
        "tgn:7018214",
        "tgn:7002435",
        "tgn:7029392"
    ],
    "tgn:id":1057399,
    "tgn:name":"Nesterkovo",
    "tgn:placetype":[
        "aat:300008347"
    ]
},
  "bbox": [],
  "geometry": {"coordinates":[30.55,59.1667],"type":"Point"}
}