{
  "id": 7445805,
  "type": "Feature",
  "properties": {
    "tgn:hierarchy":[
        "tgn:7445805",
        "tgn:7002445",
        "tgn:1000003",
        "tgn:7008160",
        "tgn:7008591",
        "tgn:7029392"
    ],
    "tgn:id":7445805,
    "tgn:name:en":"Ring Mere",
    "tgn:placetype":[
        "aat:300008688"
    ]
},
  "bbox": [],
  "geometry": {"coordinates":[0.816667,52.466667],"type":"Point"}
}