{
  "id": 7590780,
  "type": "Feature",
  "properties": {
    "tgn:hierarchy":[
        "tgn:7590780",
        "tgn:1000004",
        "tgn:7000198",
        "tgn:7000799",
        "tgn:7029392"
    ],
    "tgn:id":7590780,
    "tgn:name:en":"Dab Karm D\u012bn",
    "tgn:placetype":[
        "aat:300008347"
    ]
},
  "bbox": [],
  "geometry": {"coordinates":[74.733333,32.833333],"type":"Point"}
}