{
  "id": 7167273,
  "type": "Feature",
  "properties": {
    "tgn:hierarchy":[
        "tgn:7167273",
        "tgn:7000096",
        "tgn:1000003",
        "tgn:7000084",
        "tgn:7029392"
    ],
    "tgn:id":7167273,
    "tgn:name":"Forsthaus Heinersbr\u00fcck",
    "tgn:placetype":[
        "aat:300004792"
    ]
},
  "bbox": [],
  "geometry": {"coordinates":[14.533333,51.833333],"type":"Point"}
}