<<<<<<< HEAD
{
  "id": 2255905,
  "type": "Feature",
  "properties": {
    "tgn:hierarchy":[
        "tgn:2255905",
        "tgn:1000001",
        "tgn:7012149",
        "tgn:2000180",
        "tgn:7007157",
        "tgn:7029392"
    ],
    "tgn:id":2255905,
    "tgn:name":"Copper Creek Mine",
    "tgn:placetype":[
        "aat:300000390"
    ]
},
  "bbox": [],
  "geometry": {"coordinates":[-124.0167,41.9167],"type":"Point"}
}
=======
{"geometry":{"type":"Point","coordinates":[-124.016700,41.916700]},"type":"Feature","properties":{"hierarchy":["tgn:2255905","tgn:1000001","tgn:7012149","tgn:2000180","tgn:7007157","tgn:7029392"],"placetype":["aat:300000390"],"id":2255905,"name:xx":"Copper Creek Mine"}}
>>>>>>> 03f74aca74312dbeaf24d7e61306dd6a786dc3d0
