{
  "id": 2169682,
  "type": "Feature",
  "properties": {
    "tgn:hierarchy":[
        "tgn:2169682",
        "tgn:1000001",
        "tgn:7012149",
        "tgn:2000960",
        "tgn:7007520",
        "tgn:7029392"
    ],
    "tgn:id":2169682,
    "tgn:name":"Big Mosquito Lake",
    "tgn:placetype":[
        "aat:300008680"
    ]
},
  "bbox": [],
  "geometry": {"coordinates":[-89.4667,46.2333],"type":"Point"}
}