<<<<<<< HEAD
{
  "id": 7351776,
  "type": "Feature",
  "properties": {
    "tgn:hierarchy":[
        "tgn:7351776",
        "tgn:7005581",
        "tgn:1000001",
        "tgn:7005560",
        "tgn:7029392"
    ],
    "tgn:id":7351776,
    "tgn:name":"Arroyo de Amores",
    "tgn:placetype":[
        "aat:300008347"
    ]
},
  "bbox": [],
  "geometry": {"coordinates":[-107.716667,26.266667],"type":"Point"}
}
=======
{"geometry":{"type":"Point","coordinates":[-107.716667,26.266667]},"type":"Feature","properties":{"hierarchy":["tgn:7351776","tgn:7005581","tgn:1000001","tgn:7005560","tgn:7029392"],"placetype":["aat:300008347"],"id":7351776,"name:xx":"Arroyo de Amores"}}
>>>>>>> 03f74aca74312dbeaf24d7e61306dd6a786dc3d0
