{
  "id": 7351776,
  "type": "Feature",
  "properties": {
    "tgn:hierarchy":[
        "tgn:7351776",
        "tgn:7005581",
        "tgn:1000001",
        "tgn:7005560",
        "tgn:7029392"
    ],
    "tgn:id":7351776,
    "tgn:name":"Arroyo de Amores",
    "tgn:placetype":[
        "aat:300008347"
    ]
},
  "bbox": [],
  "geometry": {"coordinates":[-107.716667,26.266667],"type":"Point"}
}