{
  "id": 7124582,
  "type": "Feature",
  "properties": {
    "tgn:hierarchy":[
        "tgn:7124582",
        "tgn:7003692",
        "tgn:1000003",
        "tgn:7000084",
        "tgn:7029392"
    ],
    "tgn:id":7124582,
    "tgn:name":"Neunstadt",
    "tgn:placetype":[
        "aat:300008347"
    ]
},
  "bbox": [],
  "geometry": {"coordinates":[10.183333,48.95],"type":"Point"}
}