{
  "id": 2102156,
  "type": "Feature",
  "properties": {
    "tgn:hierarchy":[
        "tgn:2102156",
        "tgn:1000001",
        "tgn:7012149",
        "tgn:2001903",
        "tgn:7007825",
        "tgn:7029392"
    ],
    "tgn:id":2102156,
    "tgn:name":"Wirmingham",
    "tgn:placetype":[
        "aat:300008347",
        "aat:300387210"
    ]
},
  "bbox": [],
  "geometry": {"coordinates":[-85.1833,36.4833],"type":"Point"}
}