{
  "id": 1104522,
  "type": "Feature",
  "properties": {
    "tgn:hierarchy":[
        "tgn:1104522",
        "tgn:7017442",
        "tgn:1000001",
        "tgn:7004643",
        "tgn:7029392"
    ],
    "tgn:id":1104522,
    "tgn:name":"El Yunque",
    "tgn:placetype":[
        "aat:300008795"
    ]
},
  "bbox": [],
  "geometry": {"coordinates":[-65.8333,18.3333],"type":"Point"}
}