{
  "id": 7503674,
  "type": "Feature",
  "properties": {
    "tgn:hierarchy":[
        "tgn:7503674",
        "tgn:1000004",
        "tgn:7001009",
        "tgn:1000141",
        "tgn:7029392"
    ],
    "tgn:id":7503674,
    "tgn:name":"Jingyi Daxue",
    "tgn:placetype":[
        "aat:300006610"
    ]
},
  "bbox": [],
  "geometry": {"coordinates":[120.577484,24.228645],"type":"Point"}
}