{
  "id": 7257413,
  "type": "Feature",
  "properties": {
    "tgn:hierarchy":[
        "tgn:7257413",
        "tgn:7593113",
        "tgn:7016620",
        "tgn:7593112",
        "tgn:1000001",
        "tgn:7029392"
    ],
    "tgn:id":7257413,
    "tgn:name:nl":"San Juan",
    "tgn:placetype":[
        "aat:300387200"
    ]
},
  "bbox": [],
  "geometry": {"coordinates":[-68.366667,12.25],"type":"Point"}
}