{
  "id": 7321479,
  "type": "Feature",
  "properties": {
    "tgn:hierarchy":[
        "tgn:7321479",
        "tgn:7016598",
        "tgn:1000049",
        "tgn:1000002",
        "tgn:7029392"
    ],
    "tgn:id":7321479,
    "tgn:name":"Buena Esperanza",
    "tgn:placetype":[
        "aat:300007783"
    ]
},
  "bbox": [],
  "geometry": {"coordinates":[-70.833333,-28.566667],"type":"Point"}
}