{
  "id": 7264017,
  "type": "Feature",
  "properties": {
    "tgn:concordances":{
        "gn:id":"6544906"
    },
    "tgn:hierarchy":[
        "tgn:7264017",
        "tgn:1000003",
        "tgn:7003635",
        "tgn:7016845",
        "tgn:7029392"
    ],
    "tgn:id":7264017,
    "tgn:name:nl":"Kamperhoek",
    "tgn:placetype":[
        "aat:300008347"
    ]
},
  "bbox": [],
  "geometry": {"coordinates":[3.966667,51.35],"type":"Point"}
}