<<<<<<< HEAD
{
  "id": 2405637,
  "type": "Feature",
  "properties": {
    "tgn:hierarchy":[
        "tgn:2405637",
        "tgn:1000001",
        "tgn:7012149",
        "tgn:2000977",
        "tgn:7007520",
        "tgn:7029392"
    ],
    "tgn:id":2405637,
    "tgn:name":"Hughes Swamp",
    "tgn:placetype":[
        "aat:300008905"
    ]
},
  "bbox": [],
  "geometry": {"coordinates":[-85.2167,43.6667],"type":"Point"}
}
=======
{"geometry":{"type":"Point","coordinates":[-85.216700,43.666700]},"type":"Feature","properties":{"hierarchy":["tgn:2405637","tgn:1000001","tgn:7012149","tgn:2000977","tgn:7007520","tgn:7029392"],"placetype":["aat:300008905"],"id":2405637,"name:xx":"Hughes Swamp"}}
>>>>>>> 03f74aca74312dbeaf24d7e61306dd6a786dc3d0
