{
  "id": 7227462,
  "type": "Feature",
  "properties": {
    "tgn:hierarchy":[
        "tgn:7227462",
        "tgn:7002751",
        "tgn:7001399",
        "tgn:1000003",
        "tgn:1000074",
        "tgn:7029392"
    ],
    "tgn:id":7227462,
    "tgn:name":"Long\u00edtsion",
    "tgn:placetype":[
        "aat:300008347"
    ]
},
  "bbox": [],
  "geometry": {"coordinates":[22.566667,38.983333],"type":"Point"}
}