{
  "id": 7275095,
  "type": "Feature",
  "properties": {
    "tgn:hierarchy":[
        "tgn:7275095",
        "tgn:1001657",
        "tgn:1000049",
        "tgn:1000002",
        "tgn:7029392"
    ],
    "tgn:id":7275095,
    "tgn:name":"Vinilla, Portezuelo",
    "tgn:placetype":[
        "aat:300259572"
    ]
},
  "bbox": [],
  "geometry": {"coordinates":[-71.366667,-30.233333],"type":"Point"}
}