{
  "id": 7281844,
  "type": "Feature",
  "properties": {
    "tgn:hierarchy":[
        "tgn:7281844",
        "tgn:7002464",
        "tgn:1000049",
        "tgn:1000002",
        "tgn:7029392"
    ],
    "tgn:id":7281844,
    "tgn:name":"San Andr\u00e9s, Quebrada",
    "tgn:placetype":[
        "aat:300266554",
        "aat:300008699"
    ]
},
  "bbox": [],
  "geometry": {"coordinates":[-69.55,-18.45],"type":"Point"}
}