{
  "id": 4012792,
  "type": "Feature",
  "properties": {
    "tgn:hierarchy":[
        "tgn:4012792",
        "tgn:7003138",
        "tgn:1000003",
        "tgn:7003080",
        "tgn:1000080",
        "tgn:7000874",
        "tgn:7029392"
    ],
    "tgn:id":4012792,
    "tgn:name":"Borgo",
    "tgn:placetype":[
        "aat:300387336"
    ]
},
  "bbox": [],
  "geometry": {"coordinates":[17.233333,40.483333],"type":"Point"}
}