{
  "id": 7295340,
  "type": "Feature",
  "properties": {
    "tgn:hierarchy":[
        "tgn:7295340",
        "tgn:7002808",
        "tgn:7030216",
        "tgn:1000003",
        "tgn:1000095",
        "tgn:7029392"
    ],
    "tgn:id":7295340,
    "tgn:name":"Nacional, D\u00e1rsena",
    "tgn:placetype":[
        "aat:300120801"
    ]
},
  "bbox": [],
  "geometry": {"coordinates":[2.179167,41.376389],"type":"Point"}
}