{
  "id": 7067010,
  "type": "Feature",
  "properties": {
    "tgn:hierarchy":[
        "tgn:7067010",
        "tgn:7003692",
        "tgn:1000003",
        "tgn:7000084",
        "tgn:7029392"
    ],
    "tgn:id":7067010,
    "tgn:name":"Stetten am Heuchelberg",
    "tgn:placetype":[
        "aat:300008347"
    ]
},
  "bbox": [],
  "geometry": {"coordinates":[9.008056,49.130833],"type":"Point"}
}