{
  "id": 7385349,
  "type": "Feature",
  "properties": {
    "tgn:hierarchy":[
        "tgn:7385349",
        "tgn:1000001",
        "tgn:7005599",
        "tgn:7005560",
        "tgn:7029392"
    ],
    "tgn:id":7385349,
    "tgn:name":"Monte Castillo",
    "tgn:placetype":[
        "aat:300008347"
    ]
},
  "bbox": [],
  "geometry": {"coordinates":[-96.083333,18.966667],"type":"Point"}
}