{
  "id": 2509011,
  "type": "Feature",
  "properties": {
    "tgn:hierarchy":[
        "tgn:2509011",
        "tgn:1000001",
        "tgn:7012149",
        "tgn:1002378",
        "tgn:7007710",
        "tgn:7029392"
    ],
    "tgn:id":2509011,
    "tgn:name":"Middle Fork Run",
    "tgn:placetype":[
        "aat:300008699"
    ]
},
  "bbox": [],
  "geometry": {"coordinates":[-79.2667,41.5833],"type":"Point"}
}