{
  "id": 2655616,
  "type": "Feature",
  "properties": {
    "tgn:hierarchy":[
        "tgn:2655616",
        "tgn:1002227",
        "tgn:1000001",
        "tgn:7012149",
        "tgn:7007565",
        "tgn:7029392"
    ],
    "tgn:id":2655616,
    "tgn:name":"Sharps Corner",
    "tgn:placetype":[
        "aat:300008347"
    ]
},
  "bbox": [],
  "geometry": {"coordinates":[-74.95,39.7833],"type":"Point"}
}