{
  "id": 1006985,
  "type": "Feature",
  "properties": {
    "tgn:hierarchy":[
        "tgn:1006985",
        "tgn:7018508",
        "tgn:1010363",
        "tgn:1000220",
        "tgn:1000006",
        "tgn:7029392"
    ],
    "tgn:id":1006985,
    "tgn:name":"Dublon",
    "tgn:placetype":[
        "aat:300008791"
    ]
},
  "bbox": [],
  "geometry": {"coordinates":[151.9167,7.4167],"type":"Point"}
}