<<<<<<< HEAD
{
  "id": 2250825,
  "type": "Feature",
  "properties": {
    "tgn:hierarchy":[
        "tgn:2250825",
        "tgn:1000001",
        "tgn:7012149",
        "tgn:7014589",
        "tgn:7007515",
        "tgn:7029392"
    ],
    "tgn:id":2250825,
    "tgn:name":"Columbia",
    "tgn:placetype":[
        "aat:300008347"
    ]
},
  "bbox": [],
  "geometry": {"coordinates":[-67.7667,44.65],"type":"Point"}
}
=======
{"geometry":{"type":"Point","coordinates":[-67.766700,44.650000]},"type":"Feature","properties":{"hierarchy":["tgn:2250825","tgn:1000001","tgn:7012149","tgn:7014589","tgn:7007515","tgn:7029392"],"placetype":["aat:300008347"],"id":2250825,"name:xx":"Columbia"}}
>>>>>>> 03f74aca74312dbeaf24d7e61306dd6a786dc3d0
