{
  "id": 1096834,
  "type": "Feature",
  "properties": {
    "tgn:hierarchy":[
        "tgn:1096834",
        "tgn:7000490",
        "tgn:1000006",
        "tgn:7001829",
        "tgn:7029392"
    ],
    "tgn:id":1096834,
    "tgn:name":"Elliott",
    "tgn:placetype":[
        "aat:300008347"
    ]
},
  "bbox": [],
  "geometry": {"coordinates":[133.5333,-17.55],"type":"Point"}
}