{
  "id": 2314386,
  "type": "Feature",
  "properties": {
    "tgn:hierarchy":[
        "tgn:2314386",
        "tgn:1000001",
        "tgn:7012149",
        "tgn:2000476",
        "tgn:7007250",
        "tgn:7029392"
    ],
    "tgn:id":2314386,
    "tgn:name":"Elk Horn Spring",
    "tgn:placetype":[
        "aat:300008697"
    ]
},
  "bbox": [],
  "geometry": {"coordinates":[-116.4333,45.5833],"type":"Point"}
}