{
  "id": 2575023,
  "type": "Feature",
  "properties": {
    "tgn:hierarchy":[
        "tgn:2575023",
        "tgn:1000001",
        "tgn:1002249",
        "tgn:7012149",
        "tgn:7007710",
        "tgn:7029392"
    ],
    "tgn:id":2575023,
    "tgn:name":"Penn Spring Reservoir",
    "tgn:placetype":[
        "aat:300006191"
    ]
},
  "bbox": [],
  "geometry": {"coordinates":[-77.6167,40.7667],"type":"Point"}
}