{
  "id": 2696639,
  "type": "Feature",
  "properties": {
    "tgn:hierarchy":[
        "tgn:2696639",
        "tgn:1000001",
        "tgn:7012149",
        "tgn:2002268",
        "tgn:7013961",
        "tgn:7029392"
    ],
    "tgn:id":2696639,
    "tgn:name":"Stone Ridge",
    "tgn:placetype":[
        "aat:300266640"
    ]
},
  "bbox": [],
  "geometry": {"coordinates":[-81.7333,38.7833],"type":"Point"}
}