{
  "id": 2463519,
  "type": "Feature",
  "properties": {
    "tgn:hierarchy":[
        "tgn:2463519",
        "tgn:2000934",
        "tgn:1000001",
        "tgn:7012149",
        "tgn:7007516",
        "tgn:7029392"
    ],
    "tgn:id":2463519,
    "tgn:name":"Loar Hill",
    "tgn:placetype":[
        "aat:300008798"
    ]
},
  "bbox": [],
  "geometry": {"coordinates":[-78.8667,39.6167],"type":"Point"}
}