{
  "id": 2459953,
  "type": "Feature",
  "properties": {
    "tgn:hierarchy":[
        "tgn:2459953",
        "tgn:2001002",
        "tgn:1000001",
        "tgn:7012149",
        "tgn:7007521",
        "tgn:7029392"
    ],
    "tgn:id":2459953,
    "tgn:name":"Little Rock Creek",
    "tgn:placetype":[
        "aat:300008706"
    ]
},
  "bbox": [],
  "geometry": {"coordinates":[-94.9833,47.7833],"type":"Point"}
}