{
  "id": 7166508,
  "type": "Feature",
  "properties": {
    "tgn:hierarchy":[
        "tgn:7166508",
        "tgn:1000003",
        "tgn:7003689",
        "tgn:7000084",
        "tgn:7029392"
    ],
    "tgn:id":7166508,
    "tgn:name":"Haselkoppe",
    "tgn:placetype":[
        "aat:300008777"
    ]
},
  "bbox": [],
  "geometry": {"coordinates":[10.95,50.783333],"type":"Point"}
}