{
  "id": 2614474,
  "type": "Feature",
  "properties": {
    "tgn:hierarchy":[
        "tgn:2614474",
        "tgn:1000001",
        "tgn:7012149",
        "tgn:2002250",
        "tgn:7007920",
        "tgn:7029392"
    ],
    "tgn:id":2614474,
    "tgn:name":"Reik Gulch",
    "tgn:placetype":[
        "aat:300008761"
    ]
},
  "bbox": [],
  "geometry": {"coordinates":[-117.6333,48.35],"type":"Point"}
}