{
  "id": 7490371,
  "type": "Feature",
  "properties": {
    "tgn:hierarchy":[
        "tgn:7490371",
        "tgn:1000004",
        "tgn:7004300",
        "tgn:1000141",
        "tgn:7029392"
    ],
    "tgn:id":7490371,
    "tgn:name":"Daqiao Jiao",
    "tgn:placetype":[
        "aat:300008791"
    ]
},
  "bbox": [],
  "geometry": {"coordinates":[119.5975,23.796389],"type":"Point"}
}