{
  "id": 7296074,
  "type": "Feature",
  "properties": {
    "tgn:hierarchy":[
        "tgn:7296074",
        "tgn:7002826",
        "tgn:7001158",
        "tgn:1000003",
        "tgn:1000095",
        "tgn:7029392"
    ],
    "tgn:id":7296074,
    "tgn:name":"Yugueros",
    "tgn:placetype":[
        "aat:300008347"
    ]
},
  "bbox": [],
  "geometry": {"coordinates":[-5.166667,42.816667],"type":"Point"}
}