{
  "id": 2617312,
  "type": "Feature",
  "properties": {
    "tgn:hierarchy":[
        "tgn:2617312",
        "tgn:1000001",
        "tgn:7012149",
        "tgn:7007252",
        "tgn:7029392"
    ],
    "tgn:id":2617312,
    "tgn:name":"Richland Creek",
    "tgn:placetype":[
        "aat:300008706"
    ]
},
  "bbox": [],
  "geometry": {"coordinates":[-86.6167,39.1833],"type":"Point"}
}