{
  "id": 7318762,
  "type": "Feature",
  "properties": {
    "tgn:hierarchy":[
        "tgn:7318762",
        "tgn:1001699",
        "tgn:1000049",
        "tgn:1000002",
        "tgn:7029392"
    ],
    "tgn:id":7318762,
    "tgn:name":"Bonito, Estero",
    "tgn:placetype":[
        "aat:300132317"
    ]
},
  "bbox": [],
  "geometry": {"coordinates":[-72.583333,-42.133333],"type":"Point"}
}