{
  "id": 7225291,
  "type": "Feature",
  "properties": {
    "tgn:hierarchy":[
        "tgn:7225291",
        "tgn:7002707",
        "tgn:7002705",
        "tgn:1000003",
        "tgn:1000074",
        "tgn:7029392"
    ],
    "tgn:id":7225291,
    "tgn:name":"Neg\u00e1des",
    "tgn:placetype":[
        "aat:300008347"
    ]
},
  "bbox": [],
  "geometry": {"coordinates":[20.848056,39.864167],"type":"Point"}
}