{
  "id": 7339823,
  "type": "Feature",
  "properties": {
    "tgn:hierarchy":[
        "tgn:7339823",
        "tgn:7008912",
        "tgn:7030216",
        "tgn:1000003",
        "tgn:1000095",
        "tgn:7029392"
    ],
    "tgn:id":7339823,
    "tgn:name":"Com\u00fa, Barranco del",
    "tgn:placetype":[
        "aat:300266554",
        "aat:300008699"
    ]
},
  "bbox": [],
  "geometry": {"coordinates":[0.733333,41.45],"type":"Point"}
}