{
  "id": 7318288,
  "type": "Feature",
  "properties": {
    "tgn:hierarchy":[
        "tgn:7318288",
        "tgn:1001699",
        "tgn:1000049",
        "tgn:1000002",
        "tgn:7029392"
    ],
    "tgn:id":7318288,
    "tgn:name":"Chauchil, Bajo",
    "tgn:placetype":[
        "aat:300387036"
    ]
},
  "bbox": [],
  "geometry": {"coordinates":[-72.815556,-41.976389],"type":"Point"}
}