{
  "id": 2491748,
  "type": "Feature",
  "properties": {
    "tgn:hierarchy":[
        "tgn:2491748",
        "tgn:1000001",
        "tgn:7012149",
        "tgn:2001854",
        "tgn:7007825",
        "tgn:7029392"
    ],
    "tgn:id":2491748,
    "tgn:name":"Maplewood Estates",
    "tgn:placetype":[
        "aat:300008347"
    ]
},
  "bbox": [],
  "geometry": {"coordinates":[-85.0167,35.95],"type":"Point"}
}