{
  "id": 2284093,
  "type": "Feature",
  "properties": {
    "tgn:hierarchy":[
        "tgn:2284093",
        "tgn:1000001",
        "tgn:1002217",
        "tgn:7012149",
        "tgn:7007710",
        "tgn:7029392"
    ],
    "tgn:id":2284093,
    "tgn:name":"Dennys Mills",
    "tgn:placetype":[
        "aat:300008347"
    ]
},
  "bbox": [],
  "geometry": {"coordinates":[-79.7167,40.7667],"type":"Point"}
}