{
  "id": 7481757,
  "type": "Feature",
  "properties": {
    "tgn:hierarchy":[
        "tgn:7481757",
        "tgn:1000004",
        "tgn:7001013",
        "tgn:1000141",
        "tgn:7029392"
    ],
    "tgn:id":7481757,
    "tgn:name":"Yuanwu Pi",
    "tgn:placetype":[
        "aat:300008688"
    ]
},
  "bbox": [],
  "geometry": {"coordinates":[121.253889,24.955556],"type":"Point"}
}