<<<<<<< HEAD
{
  "id": 2769563,
  "type": "Feature",
  "properties": {
    "tgn:hierarchy":[
        "tgn:2769563",
        "tgn:1000001",
        "tgn:2000924",
        "tgn:7012149",
        "tgn:7007515",
        "tgn:7029392"
    ],
    "tgn:id":2769563,
    "tgn:name":"Widow Island",
    "tgn:placetype":[
        "aat:300008791"
    ]
},
  "bbox": [],
  "geometry": {"coordinates":[-68.8167,44.1167],"type":"Point"}
}
=======
{"geometry":{"type":"Point","coordinates":[-68.816700,44.116700]},"type":"Feature","properties":{"hierarchy":["tgn:2769563","tgn:1000001","tgn:2000924","tgn:7012149","tgn:7007515","tgn:7029392"],"placetype":["aat:300008791"],"id":2769563,"name:xx":"Widow Island"}}
>>>>>>> 03f74aca74312dbeaf24d7e61306dd6a786dc3d0
