{
  "id": 7005366,
  "type": "Feature",
  "properties": {
    "tgn:hierarchy":[
        "tgn:7005366",
        "tgn:1000003",
        "tgn:7003143",
        "tgn:7003236",
        "tgn:1000080",
        "tgn:7029392"
    ],
    "tgn:id":7005366,
    "tgn:name":"Portovenere",
    "tgn:placetype":[
        "aat:300008347",
        "aat:300263063"
    ]
},
  "bbox": [],
  "geometry": {"coordinates":[9.85,44.05],"type":"Point"}
}