{
  "id": 2520351,
  "type": "Feature",
  "properties": {
    "tgn:hierarchy":[
        "tgn:2520351",
        "tgn:2000453",
        "tgn:1000001",
        "tgn:7012149",
        "tgn:7007250",
        "tgn:7029392"
    ],
    "tgn:id":2520351,
    "tgn:name":"Monday Gulch",
    "tgn:placetype":[
        "aat:300008761"
    ]
},
  "bbox": [],
  "geometry": {"coordinates":[-116.4667,44.4833],"type":"Point"}
}