<<<<<<< HEAD
{
  "id": 7370959,
  "type": "Feature",
  "properties": {
    "tgn:hierarchy":[
        "tgn:7370959",
        "tgn:1001836",
        "tgn:1000001",
        "tgn:7005560",
        "tgn:7029392"
    ],
    "tgn:id":7370959,
    "tgn:name":"Gorda de Adentro, Banco",
    "tgn:placetype":[
        "aat:300386970"
    ]
},
  "bbox": [],
  "geometry": {"coordinates":[-109.516667,23.033333],"type":"Point"}
}
=======
{"geometry":{"type":"Point","coordinates":[-109.516667,23.033333]},"type":"Feature","properties":{"hierarchy":["tgn:7370959","tgn:1001836","tgn:1000001","tgn:7005560","tgn:7029392"],"placetype":["aat:300386970"],"id":7370959,"name:xx":"Gorda de Adentro, Banco"}}
>>>>>>> 03f74aca74312dbeaf24d7e61306dd6a786dc3d0
