{
  "id": 2781463,
  "type": "Feature",
  "properties": {
    "tgn:hierarchy":[
        "tgn:2781463",
        "tgn:1000001",
        "tgn:7012149",
        "tgn:2001899",
        "tgn:7007825",
        "tgn:7029392"
    ],
    "tgn:id":2781463,
    "tgn:name":"Woodlawn Estates",
    "tgn:placetype":[
        "aat:300008347"
    ]
},
  "bbox": [],
  "geometry": {"coordinates":[-87.4167,36.55],"type":"Point"}
}