{
  "id": 1014211,
  "type": "Feature",
  "properties": {
    "tgn:hierarchy":[
        "tgn:1014211",
        "tgn:7005685",
        "tgn:7005807",
        "tgn:1000001",
        "tgn:7005801",
        "tgn:7029392"
    ],
    "tgn:id":1014211,
    "tgn:name":"Garnish",
    "tgn:placetype":[
        "aat:300008347"
    ]
},
  "bbox": [],
  "geometry": {"coordinates":[-55.3667,47.2333],"type":"Point"}
}