<<<<<<< HEAD
{
  "id": 7022233,
  "type": "Feature",
  "properties": {
    "tgn:hierarchy":[
        "tgn:7022233",
        "tgn:2002131",
        "tgn:1000001",
        "tgn:7012149",
        "tgn:7007828",
        "tgn:7029392"
    ],
    "tgn:id":7022233,
    "tgn:name":"Joes Pond",
    "tgn:placetype":[
        "aat:300008347"
    ]
},
  "bbox": [],
  "geometry": {"coordinates":[-72.1667,44.4167],"type":"Point"}
}
=======
{"geometry":{"type":"Point","coordinates":[-72.166700,44.416700]},"type":"Feature","properties":{"hierarchy":["tgn:7022233","tgn:2002131","tgn:1000001","tgn:7012149","tgn:7007828","tgn:7029392"],"placetype":["aat:300008347"],"id":7022233,"name:xx":"Joes Pond"}}
>>>>>>> 03f74aca74312dbeaf24d7e61306dd6a786dc3d0
