{
  "id": 7436912,
  "type": "Feature",
  "properties": {
    "tgn:hierarchy":[
        "tgn:7436912",
        "tgn:1000001",
        "tgn:1001960",
        "tgn:7005560",
        "tgn:7029392"
    ],
    "tgn:id":7436912,
    "tgn:name":"Tapiro",
    "tgn:placetype":[
        "aat:300008347"
    ]
},
  "bbox": [],
  "geometry": {"coordinates":[-110.316667,31.133333],"type":"Point"}
}