{
  "id": 7158460,
  "type": "Feature",
  "properties": {
    "tgn:hierarchy":[
        "tgn:7158460",
        "tgn:1000003",
        "tgn:7003688",
        "tgn:7000084",
        "tgn:7029392"
    ],
    "tgn:id":7158460,
    "tgn:name":"Hohenw\u00fchren",
    "tgn:placetype":[
        "aat:300008347"
    ]
},
  "bbox": [],
  "geometry": {"coordinates":[10.233333,54.183333],"type":"Point"}
}