{
  "id": 7247932,
  "type": "Feature",
  "properties": {
    "tgn:hierarchy":[
        "tgn:7247932",
        "tgn:7007877",
        "tgn:1000003",
        "tgn:1000063",
        "tgn:4012014",
        "tgn:7029392"
    ],
    "tgn:id":7247932,
    "tgn:name":"Chenu",
    "tgn:placetype":[
        "aat:300008347"
    ]
},
  "bbox": [],
  "geometry": {"coordinates":[4.227036,50.606912],"type":"Point"}
}