{
  "id": 7042515,
  "type": "Feature",
  "properties": {
    "tgn:hierarchy":[
        "tgn:7042515",
        "tgn:7002996",
        "tgn:1000003",
        "tgn:7002997",
        "tgn:1000080",
        "tgn:7029392"
    ],
    "tgn:id":7042515,
    "tgn:name":"Salvatronda",
    "tgn:placetype":[
        "aat:300008347"
    ]
},
  "bbox": [],
  "geometry": {"coordinates":[11.966667,45.666667],"type":"Point"}
}