{
  "id": 7166409,
  "type": "Feature",
  "properties": {
    "tgn:hierarchy":[
        "tgn:7166409",
        "tgn:7000096",
        "tgn:1000003",
        "tgn:7000084",
        "tgn:7029392"
    ],
    "tgn:id":7166409,
    "tgn:name":"Heide-Berg",
    "tgn:placetype":[
        "aat:300008777"
    ]
},
  "bbox": [],
  "geometry": {"coordinates":[11.95,53.083333],"type":"Point"}
}