{
  "id": 7015312,
  "type": "Feature",
  "properties": {
    "tgn:hierarchy":[
        "tgn:7015312",
        "tgn:7001242",
        "tgn:1002119",
        "tgn:1000205",
        "tgn:7029392"
    ],
    "tgn:id":7015312,
    "tgn:name":"Sousse",
    "tgn:placetype":[
        "aat:300008347",
        "aat:300387308",
        "aat:300008375",
        "aat:300120599"
    ]
},
  "bbox": [],
  "geometry": {"coordinates":[10.6333,35.8333],"type":"Point"}
}