<<<<<<< HEAD
{
  "id": 7488558,
  "type": "Feature",
  "properties": {
    "tgn:hierarchy":[
        "tgn:7488558",
        "tgn:1000004",
        "tgn:7490934",
        "tgn:1000141",
        "tgn:7029392"
    ],
    "tgn:id":7488558,
    "tgn:name":"Nanshijiao",
    "tgn:placetype":[
        "aat:300008347"
    ]
},
  "bbox": [],
  "geometry": {"coordinates":[120.2625,23.184722],"type":"Point"}
}
=======
{"geometry":{"type":"Point","coordinates":[120.262500,23.184722]},"type":"Feature","properties":{"hierarchy":["tgn:7488558","tgn:1000004","tgn:7490934","tgn:1000141","tgn:7029392"],"placetype":["aat:300008347"],"id":7488558,"name:xx":"Nanshijiao"}}
>>>>>>> 03f74aca74312dbeaf24d7e61306dd6a786dc3d0
