{
  "id": 2689660,
  "type": "Feature",
  "properties": {
    "tgn:hierarchy":[
        "tgn:2689660",
        "tgn:1000001",
        "tgn:7012149",
        "tgn:7007157",
        "tgn:2000185",
        "tgn:7029392"
    ],
    "tgn:id":2689660,
    "tgn:name":"Squaw Rock",
    "tgn:placetype":[
        "aat:300008798"
    ]
},
  "bbox": [],
  "geometry": {"coordinates":[-123.4167,38.8667],"type":"Point"}
}