{
  "id": 2289335,
  "type": "Feature",
  "properties": {
    "tgn:hierarchy":[
        "tgn:2289335",
        "tgn:1000001",
        "tgn:7012149",
        "tgn:2000852",
        "tgn:7007255",
        "tgn:7029392"
    ],
    "tgn:id":2289335,
    "tgn:name":"Dixie",
    "tgn:placetype":[
        "aat:300008347"
    ]
},
  "bbox": [],
  "geometry": {"coordinates":[-84.05,36.6833],"type":"Point"}
}