{
  "id": 2190630,
  "type": "Feature",
  "properties": {
    "tgn:hierarchy":[
        "tgn:2190630",
        "tgn:1000001",
        "tgn:2001260",
        "tgn:7012149",
        "tgn:7007524",
        "tgn:7029392"
    ],
    "tgn:id":2190630,
    "tgn:name":"Box Springs",
    "tgn:placetype":[
        "aat:300008697"
    ]
},
  "bbox": [],
  "geometry": {"coordinates":[-112.45,44.8667],"type":"Point"}
}