{
  "id": 7309713,
  "type": "Feature",
  "properties": {
    "tgn:hierarchy":[
        "tgn:7309713",
        "tgn:1001702",
        "tgn:1000049",
        "tgn:1000002",
        "tgn:7029392"
    ],
    "tgn:id":7309713,
    "tgn:name":"Notch, Cabo",
    "tgn:placetype":[
        "aat:300386846"
    ]
},
  "bbox": [],
  "geometry": {"coordinates":[-75.465278,-50.279722],"type":"Point"}
}