{
  "id": 2137439,
  "type": "Feature",
  "properties": {
    "tgn:hierarchy":[
        "tgn:2137439",
        "tgn:1000001",
        "tgn:7012149",
        "tgn:7007706",
        "tgn:7029392"
    ],
    "tgn:id":2137439,
    "tgn:name":"Armstrong Run",
    "tgn:placetype":[
        "aat:300008699"
    ]
},
  "bbox": [],
  "geometry": {"coordinates":[-81.1833,40.75],"type":"Point"}
}