{
  "id": 2079961,
  "type": "Feature",
  "properties": {
    "tgn:hierarchy":[
        "tgn:2079961",
        "tgn:1000001",
        "tgn:1002313",
        "tgn:7012149",
        "tgn:7007706",
        "tgn:7029392"
    ],
    "tgn:id":2079961,
    "tgn:name":"Highland Heights",
    "tgn:placetype":[
        "aat:300008347"
    ]
},
  "bbox": [],
  "geometry": {"coordinates":[-81.4667,41.55],"type":"Point"}
}