{
  "id": 7156627,
  "type": "Feature",
  "properties": {
    "tgn:hierarchy":[
        "tgn:7156627",
        "tgn:7003669",
        "tgn:1000003",
        "tgn:7000084",
        "tgn:7029392"
    ],
    "tgn:id":7156627,
    "tgn:name":"Kinsau",
    "tgn:placetype":[
        "aat:300008347"
    ]
},
  "bbox": [],
  "geometry": {"coordinates":[10.916667,47.883333],"type":"Point"}
}