{
  "id": 7424839,
  "type": "Feature",
  "properties": {
    "tgn:hierarchy":[
        "tgn:7424839",
        "tgn:1000001",
        "tgn:7005601",
        "tgn:7005560",
        "tgn:7029392"
    ],
    "tgn:id":7424839,
    "tgn:name":"Laguna de Arriba",
    "tgn:placetype":[
        "aat:300008347"
    ]
},
  "bbox": [],
  "geometry": {"coordinates":[-102.383333,22.725],"type":"Point"}
}