{
  "id": 2579587,
  "type": "Feature",
  "properties": {
    "tgn:hierarchy":[
        "tgn:2579587",
        "tgn:1000001",
        "tgn:7012149",
        "tgn:2000927",
        "tgn:7007515",
        "tgn:7029392"
    ],
    "tgn:id":2579587,
    "tgn:name":"Pickett Mountain",
    "tgn:placetype":[
        "aat:300008798"
    ]
},
  "bbox": [],
  "geometry": {"coordinates":[-68.4333,46.1167],"type":"Point"}
}