{
  "id": 2426445,
  "type": "Feature",
  "properties": {
    "tgn:hierarchy":[
        "tgn:2426445",
        "tgn:1000001",
        "tgn:7012149",
        "tgn:1002717",
        "tgn:7007252",
        "tgn:7029392"
    ],
    "tgn:id":2426445,
    "tgn:name":"Jones Ditch",
    "tgn:placetype":[
        "aat:300006075"
    ]
},
  "bbox": [],
  "geometry": {"coordinates":[-87.3667,40.8667],"type":"Point"}
}