{
  "id": 7416241,
  "type": "Feature",
  "properties": {
    "tgn:hierarchy":[
        "tgn:7416241",
        "tgn:1000001",
        "tgn:7005591",
        "tgn:7005560",
        "tgn:7029392"
    ],
    "tgn:id":7416241,
    "tgn:name:es":"Tonameca, Barra",
    "tgn:placetype":[
        "aat:300185707"
    ]
},
  "bbox": [],
  "geometry": {"coordinates":[-96.718056,15.718611],"type":"Point"}
}