{
  "id": 2696447,
  "type": "Feature",
  "properties": {
    "tgn:hierarchy":[
        "tgn:2696447",
        "tgn:1000001",
        "tgn:2001818",
        "tgn:7012149",
        "tgn:7007713",
        "tgn:7029392"
    ],
    "tgn:id":2696447,
    "tgn:name":"Stone House Lake",
    "tgn:placetype":[
        "aat:300008680"
    ]
},
  "bbox": [],
  "geometry": {"coordinates":[-97.8167,43.8667],"type":"Point"}
}