{
  "id": 7500803,
  "type": "Feature",
  "properties": {
    "tgn:hierarchy":[
        "tgn:7500803",
        "tgn:1000004",
        "tgn:7467799",
        "tgn:1000141",
        "tgn:7029392"
    ],
    "tgn:id":7500803,
    "tgn:name":"Shuiyuetai",
    "tgn:placetype":[
        "aat:300008347"
    ]
},
  "bbox": [],
  "geometry": {"coordinates":[120.588203,24.048012],"type":"Point"}
}