{
  "id": 7288307,
  "type": "Feature",
  "properties": {
    "tgn:hierarchy":[
        "tgn:7288307",
        "tgn:7016598",
        "tgn:1000049",
        "tgn:1000002",
        "tgn:7029392"
    ],
    "tgn:id":7288307,
    "tgn:name":"La Charcona",
    "tgn:placetype":[
        "aat:300387200"
    ]
},
  "bbox": [],
  "geometry": {"coordinates":[-70.416667,-25.133333],"type":"Point"}
}