{
  "id": 7421255,
  "type": "Feature",
  "properties": {
    "tgn:hierarchy":[
        "tgn:7421255",
        "tgn:1001836",
        "tgn:1000001",
        "tgn:7005560",
        "tgn:7029392"
    ],
    "tgn:id":7421255,
    "tgn:name":"San Pedro, R\u00edo",
    "tgn:placetype":[
        "aat:300008699"
    ]
},
  "bbox": [],
  "geometry": {"coordinates":[-112.718611,26.781111],"type":"Point"}
}