{
  "id": 7423212,
  "type": "Feature",
  "properties": {
    "tgn:hierarchy":[
        "tgn:7423212",
        "tgn:1000001",
        "tgn:1001960",
        "tgn:7005560",
        "tgn:7029392"
    ],
    "tgn:id":7423212,
    "tgn:name":"La Salina, Punta",
    "tgn:placetype":[
        "aat:300386846"
    ]
},
  "bbox": [],
  "geometry": {"coordinates":[-113.116667,31.066667],"type":"Point"}
}