{
  "id": 2058959,
  "type": "Feature",
  "properties": {
    "tgn:hierarchy":[
        "tgn:2058959",
        "tgn:1000001",
        "tgn:7012149",
        "tgn:2001250",
        "tgn:7007523",
        "tgn:7029392"
    ],
    "tgn:id":2058959,
    "tgn:name":"Green Castle",
    "tgn:placetype":[
        "aat:300008347"
    ]
},
  "bbox": [],
  "geometry": {"coordinates":[-92.8667,40.25],"type":"Point"}
}