{
  "id": 7260539,
  "type": "Feature",
  "properties": {
    "tgn:concordances":{
        "gn:id":"2756009"
    },
    "tgn:hierarchy":[
        "tgn:7260539",
        "tgn:7003619",
        "tgn:1000003",
        "tgn:7016845",
        "tgn:7029392"
    ],
    "tgn:id":7260539,
    "tgn:name:nl":"Essebroek",
    "tgn:placetype":[
        "aat:300008347"
    ]
},
  "bbox": [],
  "geometry": {"coordinates":[5.483333,51.966667],"type":"Point"}
}