{
  "id": 7328216,
  "type": "Feature",
  "properties": {
    "tgn:hierarchy":[
        "tgn:7328216",
        "tgn:7002826",
        "tgn:7001158",
        "tgn:1000003",
        "tgn:1000095",
        "tgn:7029392"
    ],
    "tgn:id":7328216,
    "tgn:name":"Represa del Condado",
    "tgn:placetype":[
        "aat:300008347"
    ]
},
  "bbox": [],
  "geometry": {"coordinates":[-5.416667,42.65],"type":"Point"}
}