{
  "id": 2367183,
  "type": "Feature",
  "properties": {
    "tgn:hierarchy":[
        "tgn:2367183",
        "tgn:1000001",
        "tgn:7012149",
        "tgn:2000887",
        "tgn:7007256",
        "tgn:7029392"
    ],
    "tgn:id":2367183,
    "tgn:name":"Groom Slash",
    "tgn:placetype":[
        "aat:300008699"
    ]
},
  "bbox": [],
  "geometry": {"coordinates":[-91.9667,32.95],"type":"Point"}
}