{
  "id": 2696371,
  "type": "Feature",
  "properties": {
    "tgn:hierarchy":[
        "tgn:2696371",
        "tgn:1000001",
        "tgn:7012149",
        "tgn:2002342",
        "tgn:7007922",
        "tgn:7029392"
    ],
    "tgn:id":2696371,
    "tgn:name":"Stone Creek",
    "tgn:placetype":[
        "aat:300008706"
    ]
},
  "bbox": [],
  "geometry": {"coordinates":[-89.9667,45.8333],"type":"Point"}
}