{
  "id": 7301024,
  "type": "Feature",
  "properties": {
    "tgn:hierarchy":[
        "tgn:7301024",
        "tgn:7002807",
        "tgn:1000003",
        "tgn:7003837",
        "tgn:1000095",
        "tgn:7029392"
    ],
    "tgn:id":7301024,
    "tgn:name":"Montes",
    "tgn:placetype":[
        "aat:300008347"
    ]
},
  "bbox": [],
  "geometry": {"coordinates":[-6.65,38.433333],"type":"Point"}
}