{
  "id": 7571459,
  "type": "Feature",
  "properties": {
    "tgn:hierarchy":[
        "tgn:7571459",
        "tgn:1000004",
        "tgn:7031781",
        "tgn:7000198",
        "tgn:7029392"
    ],
    "tgn:id":7571459,
    "tgn:name:en":"Hataud",
    "tgn:placetype":[
        "aat:300008347"
    ]
},
  "bbox": [],
  "geometry": {"coordinates":[82.433333,21.583333],"type":"Point"}
}