{
  "id": 2438781,
  "type": "Feature",
  "properties": {
    "tgn:hierarchy":[
        "tgn:2438781",
        "tgn:1000001",
        "tgn:7012149",
        "tgn:1002700",
        "tgn:7007520",
        "tgn:7029392"
    ],
    "tgn:id":2438781,
    "tgn:name":"Kinne Drain",
    "tgn:placetype":[
        "aat:300006075"
    ]
},
  "bbox": [],
  "geometry": {"coordinates":[-85.9333,43.2333],"type":"Point"}
}