{
  "id": 7431830,
  "type": "Feature",
  "properties": {
    "tgn:hierarchy":[
        "tgn:7431830",
        "tgn:1001853",
        "tgn:1000001",
        "tgn:7005560",
        "tgn:7029392"
    ],
    "tgn:id":7431830,
    "tgn:name":"El Gavil\u00e1n",
    "tgn:placetype":[
        "aat:300008347"
    ]
},
  "bbox": [],
  "geometry": {"coordinates":[-100.75,28.516667],"type":"Point"}
}