{
  "id": 2706848,
  "type": "Feature",
  "properties": {
    "tgn:hierarchy":[
        "tgn:2706848",
        "tgn:1000001",
        "tgn:1002260",
        "tgn:7012149",
        "tgn:7007920",
        "tgn:7029392"
    ],
    "tgn:id":2706848,
    "tgn:name":"Swanson Gulch",
    "tgn:placetype":[
        "aat:300008761"
    ]
},
  "bbox": [],
  "geometry": {"coordinates":[-120.0667,47.95],"type":"Point"}
}