<<<<<<< HEAD
{
  "id": 2405976,
  "type": "Feature",
  "properties": {
    "tgn:hierarchy":[
        "tgn:2405976",
        "tgn:1000001",
        "tgn:2001419",
        "tgn:7012149",
        "tgn:7007526",
        "tgn:7029392"
    ],
    "tgn:id":2405976,
    "tgn:name":"Humboldt Canyon",
    "tgn:placetype":[
        "aat:300008761"
    ]
},
  "bbox": [],
  "geometry": {"coordinates":[-118.1833,40.55],"type":"Point"}
}
=======
{"geometry":{"type":"Point","coordinates":[-118.183300,40.550000]},"type":"Feature","properties":{"hierarchy":["tgn:2405976","tgn:1000001","tgn:2001419","tgn:7012149","tgn:7007526","tgn:7029392"],"placetype":["aat:300008761"],"id":2405976,"name:xx":"Humboldt Canyon"}}
>>>>>>> 03f74aca74312dbeaf24d7e61306dd6a786dc3d0
