{
  "id": 2229743,
  "type": "Feature",
  "properties": {
    "tgn:hierarchy":[
        "tgn:2229743",
        "tgn:1000001",
        "tgn:2001842",
        "tgn:7012149",
        "tgn:7007825",
        "tgn:7029392"
    ],
    "tgn:id":2229743,
    "tgn:name":"Cedar Spring",
    "tgn:placetype":[
        "aat:300008347"
    ]
},
  "bbox": [],
  "geometry": {"coordinates":[-84.7833,35.05],"type":"Point"}
}