{
  "id": 7366439,
  "type": "Feature",
  "properties": {
    "tgn:hierarchy":[
        "tgn:7366439",
        "tgn:7005578",
        "tgn:1000001",
        "tgn:7005560",
        "tgn:7029392"
    ],
    "tgn:id":7366439,
    "tgn:name":"Esperanza",
    "tgn:placetype":[
        "aat:300008347"
    ]
},
  "bbox": [],
  "geometry": {"coordinates":[-90.95,18.866667],"type":"Point"}
}