{
  "id": 2144515,
  "type": "Feature",
  "properties": {
    "tgn:hierarchy":[
        "tgn:2144515",
        "tgn:1000001",
        "tgn:7012149",
        "tgn:2001869",
        "tgn:7007825",
        "tgn:7029392"
    ],
    "tgn:id":2144515,
    "tgn:name":"Bakewell Mountain",
    "tgn:placetype":[
        "aat:300008798"
    ]
},
  "bbox": [],
  "geometry": {"coordinates":[-85.15,35.35],"type":"Point"}
}