{
  "id": 7387352,
  "type": "Feature",
  "properties": {
    "tgn:hierarchy":[
        "tgn:7387352",
        "tgn:1000001",
        "tgn:7005600",
        "tgn:7005560",
        "tgn:7029392"
    ],
    "tgn:id":7387352,
    "tgn:name":"Petectunich",
    "tgn:placetype":[
        "aat:300008347"
    ]
},
  "bbox": [],
  "geometry": {"coordinates":[-89.466667,20.833333],"type":"Point"}
}