{
  "id": 7398219,
  "type": "Feature",
  "properties": {
    "tgn:hierarchy":[
        "tgn:7398219",
        "tgn:1000001",
        "tgn:1001960",
        "tgn:7005560",
        "tgn:7029392"
    ],
    "tgn:id":7398219,
    "tgn:name":"Tescalama",
    "tgn:placetype":[
        "aat:300266554",
        "aat:300008699"
    ]
},
  "bbox": [],
  "geometry": {"coordinates":[-111.056389,30.834167],"type":"Point"}
}