{
  "id": 7420475,
  "type": "Feature",
  "properties": {
    "tgn:hierarchy":[
        "tgn:7420475",
        "tgn:7005584",
        "tgn:1000001",
        "tgn:7005560",
        "tgn:7029392"
    ],
    "tgn:id":7420475,
    "tgn:name":"San Salvador de Ahorcados",
    "tgn:placetype":[
        "aat:300008347"
    ]
},
  "bbox": [],
  "geometry": {"coordinates":[-100.296667,21.383889],"type":"Point"}
}