{
  "id": 2318599,
  "type": "Feature",
  "properties": {
    "tgn:hierarchy":[
        "tgn:2318599",
        "tgn:1000001",
        "tgn:7012149",
        "tgn:2000491",
        "tgn:7007250",
        "tgn:7029392"
    ],
    "tgn:id":2318599,
    "tgn:name":"Erlmo",
    "tgn:placetype":[
        "aat:300008347"
    ]
},
  "bbox": [],
  "geometry": {"coordinates":[-116.0333,47.25],"type":"Point"}
}