{
  "id": 2137018,
  "type": "Feature",
  "properties": {
    "tgn:hierarchy":[
        "tgn:2137018",
        "tgn:1000001",
        "tgn:7012149",
        "tgn:7007157",
        "tgn:1002915",
        "tgn:7029392"
    ],
    "tgn:id":2137018,
    "tgn:name":"Arkansas Creek",
    "tgn:placetype":[
        "aat:300008706"
    ]
},
  "bbox": [],
  "geometry": {"coordinates":[-121.35,37.55],"type":"Point"}
}