{
  "id": 2088599,
  "type": "Feature",
  "properties": {
    "tgn:hierarchy":[
        "tgn:2088599",
        "tgn:1002153",
        "tgn:1000001",
        "tgn:7012149",
        "tgn:7007710",
        "tgn:7029392"
    ],
    "tgn:id":2088599,
    "tgn:name":"Fredericksburg",
    "tgn:placetype":[
        "aat:300008347"
    ]
},
  "bbox": [],
  "geometry": {"coordinates":[-79.6833,41.0167],"type":"Point"}
}