{
  "id": 2357064,
  "type": "Feature",
  "properties": {
    "tgn:hierarchy":[
        "tgn:2357064",
        "tgn:1000001",
        "tgn:7020939",
        "tgn:7012149",
        "tgn:7007922",
        "tgn:7029392"
    ],
    "tgn:id":2357064,
    "tgn:name":"Gothic Mill Pond",
    "tgn:placetype":[
        "aat:300006191"
    ]
},
  "bbox": [],
  "geometry": {"coordinates":[-88.8167,43.8333],"type":"Point"}
}