{
  "id": 2416407,
  "type": "Feature",
  "properties": {
    "tgn:hierarchy":[
        "tgn:2416407",
        "tgn:1000001",
        "tgn:2001474",
        "tgn:7012149",
        "tgn:7007709",
        "tgn:7029392"
    ],
    "tgn:id":2416407,
    "tgn:name":"Jack Branch",
    "tgn:placetype":[
        "aat:300008699"
    ]
},
  "bbox": [],
  "geometry": {"coordinates":[-81.8167,35.6833],"type":"Point"}
}