{
  "id": 1066659,
  "type": "Feature",
  "properties": {
    "tgn:hierarchy":[
        "tgn:1066659",
        "tgn:1000004",
        "tgn:7002081",
        "tgn:1000111",
        "tgn:7029392"
    ],
    "tgn:id":1066659,
    "tgn:name":"Baimuqiao",
    "tgn:placetype":[
        "aat:300008347"
    ]
},
  "bbox": [],
  "geometry": {"coordinates":[120.3167,32.0167],"type":"Point"}
}