{
  "id": 2370960,
  "type": "Feature",
  "properties": {
    "tgn:hierarchy":[
        "tgn:2370960",
        "tgn:1000001",
        "tgn:7012149",
        "tgn:1002980",
        "tgn:7007826",
        "tgn:7029392"
    ],
    "tgn:id":2370960,
    "tgn:name":"Hadley Creek",
    "tgn:placetype":[
        "aat:300008706"
    ]
},
  "bbox": [],
  "geometry": {"coordinates":[-95.5667,30.7333],"type":"Point"}
}