<<<<<<< HEAD
{
  "id": 7023814,
  "type": "Feature",
  "properties": {
    "tgn:hierarchy":[
        "tgn:7023814",
        "tgn:2002240",
        "tgn:1000001",
        "tgn:7012149",
        "tgn:7007920",
        "tgn:7029392"
    ],
    "tgn:id":7023814,
    "tgn:name":"Prosser",
    "tgn:placetype":[
        "aat:300008347",
        "aat:300008416",
        "aat:300008375"
    ]
},
  "bbox": [],
  "geometry": {"coordinates":[-119.7667,46.2],"type":"Point"}
}
=======
{"geometry":{"type":"Point","coordinates":[-119.766700,46.200000]},"type":"Feature","properties":{"hierarchy":["tgn:7023814","tgn:2002240","tgn:1000001","tgn:7012149","tgn:7007920","tgn:7029392"],"placetype":["aat:300008347","aat:300008416","aat:300008375"],"id":7023814,"name:xx":"Prosser"}}
>>>>>>> 03f74aca74312dbeaf24d7e61306dd6a786dc3d0
