{
  "id": 2520086,
  "type": "Feature",
  "properties": {
    "tgn:hierarchy":[
        "tgn:2520086",
        "tgn:1000001",
        "tgn:7012149",
        "tgn:2001502",
        "tgn:7007709",
        "tgn:7029392"
    ],
    "tgn:id":2520086,
    "tgn:name":"Molly Branch",
    "tgn:placetype":[
        "aat:300008699"
    ]
},
  "bbox": [],
  "geometry": {"coordinates":[-78.8333,35.3667],"type":"Point"}
}