<<<<<<< HEAD
{
  "id": 2157653,
  "type": "Feature",
  "properties": {
    "tgn:hierarchy":[
        "tgn:2157653",
        "tgn:1000001",
        "tgn:7012149",
        "tgn:2002371",
        "tgn:7007923",
        "tgn:7029392"
    ],
    "tgn:id":2157653,
    "tgn:name":"Beaver Dam Ditch",
    "tgn:placetype":[
        "aat:300006075"
    ]
},
  "bbox": [],
  "geometry": {"coordinates":[-108.6667,42.3833],"type":"Point"}
}
=======
{"geometry":{"type":"Point","coordinates":[-108.666700,42.383300]},"type":"Feature","properties":{"hierarchy":["tgn:2157653","tgn:1000001","tgn:7012149","tgn:2002371","tgn:7007923","tgn:7029392"],"placetype":["aat:300006075"],"id":2157653,"name:xx":"Beaver Dam Ditch"}}
>>>>>>> 03f74aca74312dbeaf24d7e61306dd6a786dc3d0
