{
  "id": 2163236,
  "type": "Feature",
  "properties": {
    "tgn:hierarchy":[
        "tgn:2163236",
        "tgn:1000001",
        "tgn:7012149",
        "tgn:1002977",
        "tgn:7007240",
        "tgn:7029392"
    ],
    "tgn:id":2163236,
    "tgn:name":"Bennett Swamp",
    "tgn:placetype":[
        "aat:300008905"
    ]
},
  "bbox": [],
  "geometry": {"coordinates":[-81.1333,29.1667],"type":"Point"}
}