{
  "id": 2273621,
  "type": "Feature",
  "properties": {
    "tgn:hierarchy":[
        "tgn:2273621",
        "tgn:1000001",
        "tgn:7012149",
        "tgn:2000821",
        "tgn:7007255",
        "tgn:7029392"
    ],
    "tgn:id":2273621,
    "tgn:name":"Cyrus",
    "tgn:placetype":[
        "aat:300008347"
    ]
},
  "bbox": [],
  "geometry": {"coordinates":[-83.0333,37.7833],"type":"Point"}
}