{
  "id": 2563025,
  "type": "Feature",
  "properties": {
    "tgn:hierarchy":[
        "tgn:2563025",
        "tgn:1000001",
        "tgn:7012149",
        "tgn:2000430",
        "tgn:7007248",
        "tgn:7029392"
    ],
    "tgn:id":2563025,
    "tgn:name":"Owenby Cove",
    "tgn:placetype":[
        "aat:300386845"
    ]
},
  "bbox": [],
  "geometry": {"coordinates":[-83.6333,34.9667],"type":"Point"}
}