{
  "id": 7301670,
  "type": "Feature",
  "properties": {
    "tgn:hierarchy":[
        "tgn:7301670",
        "tgn:7002806",
        "tgn:7001158",
        "tgn:1000003",
        "tgn:1000095",
        "tgn:7029392"
    ],
    "tgn:id":7301670,
    "tgn:name":"Minine, R\u00edo",
    "tgn:placetype":[
        "aat:300008699"
    ]
},
  "bbox": [],
  "geometry": {"coordinates":[-5.116667,41.066667],"type":"Point"}
}