{
  "id": 2130127,
  "type": "Feature",
  "properties": {
    "tgn:hierarchy":[
        "tgn:2130127",
        "tgn:1000001",
        "tgn:7012149",
        "tgn:1002588",
        "tgn:7007520",
        "tgn:7029392"
    ],
    "tgn:id":2130127,
    "tgn:name":"Allen Lake",
    "tgn:placetype":[
        "aat:300008680"
    ]
},
  "bbox": [],
  "geometry": {"coordinates":[-84.1833,42.05],"type":"Point"}
}