{
  "id": 1135049,
  "type": "Feature",
  "properties": {
    "tgn:hierarchy":[
        "tgn:1135049",
        "tgn:1000001",
        "tgn:7012149",
        "tgn:7007826",
        "tgn:7029392"
    ],
    "tgn:id":1135049,
    "tgn:name":"White Rock Creek",
    "tgn:placetype":[
        "aat:300008706"
    ]
},
  "bbox": [],
  "geometry": {"coordinates":[-96.7833,33.1333],"type":"Point"}
}