{
  "id": 2581731,
  "type": "Feature",
  "properties": {
    "tgn:hierarchy":[
        "tgn:2581731",
        "tgn:1000001",
        "tgn:7006451",
        "tgn:2000093",
        "tgn:7012149",
        "tgn:7029392"
    ],
    "tgn:id":2581731,
    "tgn:name":"Pinal Mountains",
    "tgn:placetype":[
        "aat:300008798"
    ]
},
  "bbox": [],
  "geometry": {"coordinates":[-110.8167,33.2667],"type":"Point"}
}