{
  "id": 2249917,
  "type": "Feature",
  "properties": {
    "tgn:hierarchy":[
        "tgn:2249917",
        "tgn:7002659",
        "tgn:1000001",
        "tgn:7012149",
        "tgn:2000041",
        "tgn:7029392"
    ],
    "tgn:id":2249917,
    "tgn:name":"Collier Branch",
    "tgn:placetype":[
        "aat:300008699"
    ]
},
  "bbox": [],
  "geometry": {"coordinates":[-86.9167,34.8333],"type":"Point"}
}