{
  "id": 2568611,
  "type": "Feature",
  "properties": {
    "tgn:hierarchy":[
        "tgn:2568611",
        "tgn:1000001",
        "tgn:7012149",
        "tgn:2001138",
        "tgn:7007522",
        "tgn:7029392"
    ],
    "tgn:id":2568611,
    "tgn:name":"Parkdale",
    "tgn:placetype":[
        "aat:300008347"
    ]
},
  "bbox": [],
  "geometry": {"coordinates":[-88.8167,33.4667],"type":"Point"}
}