<<<<<<< HEAD
{
  "id": 7050389,
  "type": "Feature",
  "properties": {
    "tgn:hierarchy":[
        "tgn:7050389",
        "tgn:1003429",
        "tgn:1000003",
        "tgn:7003240",
        "tgn:1000080",
        "tgn:7029392"
    ],
    "tgn:id":7050389,
    "tgn:name":"Mazzangrugno",
    "tgn:placetype":[
        "aat:300008347"
    ]
},
  "bbox": [],
  "geometry": {"coordinates":[13.316667,43.516667],"type":"Point"}
}
=======
{"geometry":{"type":"Point","coordinates":[13.316667,43.516667]},"type":"Feature","properties":{"hierarchy":["tgn:7050389","tgn:1003429","tgn:1000003","tgn:7003240","tgn:1000080","tgn:7029392"],"placetype":["aat:300008347"],"id":7050389,"name:xx":"Mazzangrugno"}}
>>>>>>> 03f74aca74312dbeaf24d7e61306dd6a786dc3d0
