{
  "id": 2419528,
  "type": "Feature",
  "properties": {
    "tgn:hierarchy":[
        "tgn:2419528",
        "tgn:1000001",
        "tgn:7012149",
        "tgn:1002839",
        "tgn:7007826",
        "tgn:7029392"
    ],
    "tgn:id":2419528,
    "tgn:name":"Jarrell Creek",
    "tgn:placetype":[
        "aat:300008706"
    ]
},
  "bbox": [],
  "geometry": {"coordinates":[-94.6833,32.0833],"type":"Point"}
}