{
  "id": 2220279,
  "type": "Feature",
  "properties": {
    "tgn:hierarchy":[
        "tgn:2220279",
        "tgn:1000001",
        "tgn:7012149",
        "tgn:2000823",
        "tgn:7007255",
        "tgn:7029392"
    ],
    "tgn:id":2220279,
    "tgn:name":"Cap Spring",
    "tgn:placetype":[
        "aat:300008697"
    ]
},
  "bbox": [],
  "geometry": {"coordinates":[-88.2333,36.8667],"type":"Point"}
}