{
  "id": 2386171,
  "type": "Feature",
  "properties": {
    "tgn:hierarchy":[
        "tgn:2386171",
        "tgn:7002659",
        "tgn:1000001",
        "tgn:7012149",
        "tgn:2000045",
        "tgn:7029392"
    ],
    "tgn:id":2386171,
    "tgn:name":"Henry, Lake",
    "tgn:placetype":[
        "aat:300006191"
    ]
},
  "bbox": [],
  "geometry": {"coordinates":[-87.7333,32.4167],"type":"Point"}
}