{
  "id": 7294840,
  "type": "Feature",
  "properties": {
    "tgn:hierarchy":[
        "tgn:7294840",
        "tgn:7002464",
        "tgn:1000049",
        "tgn:1000002",
        "tgn:7029392"
    ],
    "tgn:id":7294840,
    "tgn:name":"Apacheta de Santaile, Paso",
    "tgn:placetype":[
        "aat:300259572"
    ]
},
  "bbox": [],
  "geometry": {"coordinates":[-68.516667,-19.916667],"type":"Point"}
}