{
  "id": 2269744,
  "type": "Feature",
  "properties": {
    "tgn:hierarchy":[
        "tgn:2269744",
        "tgn:1000001",
        "tgn:7012149",
        "tgn:2002125",
        "tgn:7007827",
        "tgn:7029392"
    ],
    "tgn:id":2269744,
    "tgn:name":"Crown Point Number 3",
    "tgn:placetype":[
        "aat:300000390"
    ]
},
  "bbox": [],
  "geometry": {"coordinates":[-112.0833,39.9333],"type":"Point"}
}