{
  "id": 2708980,
  "type": "Feature",
  "properties": {
    "tgn:hierarchy":[
        "tgn:2708980",
        "tgn:1000001",
        "tgn:7012149",
        "tgn:7007157",
        "tgn:1002915",
        "tgn:7029392"
    ],
    "tgn:id":2708980,
    "tgn:name":"T Island",
    "tgn:placetype":[
        "aat:300008791"
    ]
},
  "bbox": [],
  "geometry": {"coordinates":[-120.8667,37.8333],"type":"Point"}
}