<<<<<<< HEAD
{
  "id": 7473204,
  "type": "Feature",
  "properties": {
    "tgn:hierarchy":[
        "tgn:7473204",
        "tgn:1000004",
        "tgn:7001013",
        "tgn:1000141",
        "tgn:7029392"
    ],
    "tgn:id":7473204,
    "tgn:name":"Yeheng",
    "tgn:placetype":[
        "aat:300008347"
    ]
},
  "bbox": [],
  "geometry": {"coordinates":[121.374722,24.67],"type":"Point"}
}
=======
{"geometry":{"type":"Point","coordinates":[121.374722,24.670000]},"type":"Feature","properties":{"hierarchy":["tgn:7473204","tgn:1000004","tgn:7001013","tgn:1000141","tgn:7029392"],"placetype":["aat:300008347"],"id":7473204,"name:xx":"Yeheng"}}
>>>>>>> 03f74aca74312dbeaf24d7e61306dd6a786dc3d0
