{
  "id": 7347867,
  "type": "Feature",
  "properties": {
    "tgn:hierarchy":[
        "tgn:7347867",
        "tgn:7002826",
        "tgn:7001158",
        "tgn:1000003",
        "tgn:1000095",
        "tgn:7029392"
    ],
    "tgn:id":7347867,
    "tgn:name":"Albaredos",
    "tgn:placetype":[
        "aat:300008347"
    ]
},
  "bbox": [],
  "geometry": {"coordinates":[-7.033333,42.583333],"type":"Point"}
}