{
  "id": 1067784,
  "type": "Feature",
  "properties": {
    "tgn:hierarchy":[
        "tgn:1067784",
        "tgn:1000004",
        "tgn:7002078",
        "tgn:1000111",
        "tgn:7029392"
    ],
    "tgn:id":1067784,
    "tgn:name":"Dongjielang",
    "tgn:placetype":[
        "aat:300008347"
    ]
},
  "bbox": [],
  "geometry": {"coordinates":[115.95,31.05],"type":"Point"}
}