{
  "id": 7523684,
  "type": "Feature",
  "properties": {
    "tgn:hierarchy":[
        "tgn:7523684",
        "tgn:7001242",
        "tgn:1001075",
        "tgn:7016833",
        "tgn:7029392"
    ],
    "tgn:id":7523684,
    "tgn:name:en":"A\u015f \u015eaww\u0101f",
    "tgn:placetype":[
        "aat:300008347"
    ]
},
  "bbox": [],
  "geometry": {"coordinates":[30.776315,30.690232],"type":"Point"}
}