{
  "id": 7431851,
  "type": "Feature",
  "properties": {
    "tgn:hierarchy":[
        "tgn:7431851",
        "tgn:1001853",
        "tgn:1000001",
        "tgn:7005560",
        "tgn:7029392"
    ],
    "tgn:id":7431851,
    "tgn:name":"Los Cabezones",
    "tgn:placetype":[
        "aat:300008347"
    ]
},
  "bbox": [],
  "geometry": {"coordinates":[-101.916667,28.533333],"type":"Point"}
}