{
  "id": 2349879,
  "type": "Feature",
  "properties": {
    "tgn:hierarchy":[
        "tgn:2349879",
        "tgn:1000001",
        "tgn:7012149",
        "tgn:2000930",
        "tgn:7007515",
        "tgn:7029392"
    ],
    "tgn:id":2349879,
    "tgn:name":"Gilman Pond",
    "tgn:placetype":[
        "aat:300008680"
    ]
},
  "bbox": [],
  "geometry": {"coordinates":[-70.05,44.95],"type":"Point"}
}