{
  "id": 2134716,
  "type": "Feature",
  "properties": {
    "tgn:hierarchy":[
        "tgn:2134716",
        "tgn:1000001",
        "tgn:2001370",
        "tgn:7012149",
        "tgn:7007525",
        "tgn:7029392"
    ],
    "tgn:id":2134716,
    "tgn:name":"Antelope Creek",
    "tgn:placetype":[
        "aat:300008706"
    ]
},
  "bbox": [],
  "geometry": {"coordinates":[-96.5833,40.7333],"type":"Point"}
}