{
  "id": 2312482,
  "type": "Feature",
  "properties": {
    "tgn:hierarchy":[
        "tgn:2312482",
        "tgn:1000001",
        "tgn:7006451",
        "tgn:2000092",
        "tgn:7012149",
        "tgn:7029392"
    ],
    "tgn:id":2312482,
    "tgn:name":"Eighty-nine Tank",
    "tgn:placetype":[
        "aat:300006191"
    ]
},
  "bbox": [],
  "geometry": {"coordinates":[-111.5833,35.3333],"type":"Point"}
}