{
  "id": 7031753,
  "type": "Feature",
  "properties": {
    "tgn:hierarchy":[
        "tgn:7031753",
        "tgn:7003820",
        "tgn:1000003",
        "tgn:1000090",
        "tgn:7029392"
    ],
    "tgn:id":7031753,
    "tgn:name":"Condeixa-a-Nova",
    "tgn:placetype":[
        "aat:300008347",
        "aat:300008375"
    ]
},
  "bbox": [],
  "geometry": {"coordinates":[-8.498,40.115],"type":"Point"}
}