{
  "id": 2000222,
  "type": "Feature",
  "properties": {
    "tgn:hierarchy":[
        "tgn:2000222",
        "tgn:1000001",
        "tgn:7012149",
        "tgn:7007158",
        "tgn:7029392"
    ],
    "tgn:id":2000222,
    "tgn:name":"Kiowa",
    "tgn:placetype":[
        "aat:300387145",
        "aat:300000771"
    ]
},
  "bbox": [],
  "geometry": {"coordinates":[-102.8167,38.4333],"type":"Point"}
}