{
  "id": 7421952,
  "type": "Feature",
  "properties": {
    "tgn:hierarchy":[
        "tgn:7421952",
        "tgn:1000001",
        "tgn:7005601",
        "tgn:7005560",
        "tgn:7029392"
    ],
    "tgn:id":7421952,
    "tgn:name":"Santa Isabel",
    "tgn:placetype":[
        "aat:300008347"
    ]
},
  "bbox": [],
  "geometry": {"coordinates":[-104.066667,22.583333],"type":"Point"}
}