{
  "id": 2660448,
  "type": "Feature",
  "properties": {
    "tgn:hierarchy":[
        "tgn:2660448",
        "tgn:1000001",
        "tgn:2000308",
        "tgn:7012149",
        "tgn:7007248",
        "tgn:7029392"
    ],
    "tgn:id":2660448,
    "tgn:name":"Shoemaker Lake",
    "tgn:placetype":[
        "aat:300006191"
    ]
},
  "bbox": [],
  "geometry": {"coordinates":[-81.6167,33.0667],"type":"Point"}
}