{
  "id": 7001194,
  "type": "Feature",
  "properties": {
    "tgn:hierarchy":[
        "tgn:7001194",
        "tgn:7001242",
        "tgn:7016833",
        "tgn:7000123",
        "tgn:7029392"
    ],
    "tgn:id":7001194,
    "tgn:name:en":"Armant",
    "tgn:placetype":[
        "aat:300008347",
        "aat:300000810"
    ]
},
  "bbox": [],
  "geometry": {"coordinates":[32.545067,25.618974],"type":"Point"}
}