{
  "id": 2755635,
  "type": "Feature",
  "properties": {
    "tgn:hierarchy":[
        "tgn:2755635",
        "tgn:7006450",
        "tgn:1000001",
        "tgn:7012149",
        "tgn:7019760",
        "tgn:7029392"
    ],
    "tgn:id":2755635,
    "tgn:name":"Wedge Mountain",
    "tgn:placetype":[
        "aat:300008798"
    ]
},
  "bbox": [],
  "geometry": {"coordinates":[-136.1833,57.9833],"type":"Point"}
}