{
  "id": 7324931,
  "type": "Feature",
  "properties": {
    "tgn:hierarchy":[
        "tgn:7324931",
        "tgn:7002810",
        "tgn:7001158",
        "tgn:1000003",
        "tgn:1000095",
        "tgn:7029392"
    ],
    "tgn:id":7324931,
    "tgn:name":"San Vicente de Villamez\u00e1n",
    "tgn:placetype":[
        "aat:300008347"
    ]
},
  "bbox": [],
  "geometry": {"coordinates":[-3.916667,42.983333],"type":"Point"}
}