{
  "id": 7592484,
  "type": "Feature",
  "properties": {
    "tgn:hierarchy":[
        "tgn:7592484",
        "tgn:1000004",
        "tgn:7000198",
        "tgn:7000799",
        "tgn:7029392"
    ],
    "tgn:id":7592484,
    "tgn:name:en":"Kaintha",
    "tgn:placetype":[
        "aat:300008347"
    ]
},
  "bbox": [],
  "geometry": {"coordinates":[74.965278,32.727778],"type":"Point"}
}