{
  "id": 2246616,
  "type": "Feature",
  "properties": {
    "tgn:hierarchy":[
        "tgn:2246616",
        "tgn:1000001",
        "tgn:7012149",
        "tgn:1002993",
        "tgn:7007568",
        "tgn:7029392"
    ],
    "tgn:id":2246616,
    "tgn:name":"Cobble, The",
    "tgn:placetype":[
        "aat:300008798"
    ]
},
  "bbox": [],
  "geometry": {"coordinates":[-73.4333,43.0167],"type":"Point"}
}