{
  "id": 2137573,
  "type": "Feature",
  "properties": {
    "tgn:hierarchy":[
        "tgn:2137573",
        "tgn:1000001",
        "tgn:7012149",
        "tgn:2000181",
        "tgn:7007157",
        "tgn:7029392"
    ],
    "tgn:id":2137573,
    "tgn:name":"Arnold Creek",
    "tgn:placetype":[
        "aat:300008706"
    ]
},
  "bbox": [],
  "geometry": {"coordinates":[-123.8333,40.3833],"type":"Point"}
}