{
  "id": 2017908,
  "type": "Feature",
  "properties": {
    "tgn:hierarchy":[
        "tgn:2017908",
        "tgn:7014201",
        "tgn:1000001",
        "tgn:7012149",
        "tgn:7007239",
        "tgn:7029392"
    ],
    "tgn:id":2017908,
    "tgn:name":"Gumwood",
    "tgn:placetype":[
        "aat:300008347",
        "aat:300387210"
    ]
},
  "bbox": [],
  "geometry": {"coordinates":[-75.5167,39.7833],"type":"Point"}
}