{
  "id": 2221662,
  "type": "Feature",
  "properties": {
    "tgn:hierarchy":[
        "tgn:2221662",
        "tgn:7006450",
        "tgn:1000001",
        "tgn:7012149",
        "tgn:2000085",
        "tgn:7029392"
    ],
    "tgn:id":2221662,
    "tgn:name":"Carline Creek",
    "tgn:placetype":[
        "aat:300008706"
    ]
},
  "bbox": [],
  "geometry": {"coordinates":[-141.1167,64.0333],"type":"Point"}
}