{
  "id": 2148336,
  "type": "Feature",
  "properties": {
    "tgn:hierarchy":[
        "tgn:2148336",
        "tgn:1000001",
        "tgn:7012149",
        "tgn:2002114",
        "tgn:7007827",
        "tgn:7029392"
    ],
    "tgn:id":2148336,
    "tgn:name":"Barn Canyon",
    "tgn:placetype":[
        "aat:300008761"
    ]
},
  "bbox": [],
  "geometry": {"coordinates":[-113.4167,38.9333],"type":"Point"}
}