{
  "id": 7173960,
  "type": "Feature",
  "properties": {
    "tgn:hierarchy":[
        "tgn:7173960",
        "tgn:7003669",
        "tgn:1000003",
        "tgn:7000084",
        "tgn:7029392"
    ],
    "tgn:id":7173960,
    "tgn:name":"Gro\u00dfbachwald",
    "tgn:placetype":[
        "aat:300008863"
    ]
},
  "bbox": [],
  "geometry": {"coordinates":[10.583333,49.683333],"type":"Point"}
}