<<<<<<< HEAD
{
  "id": 7173960,
  "type": "Feature",
  "properties": {
    "tgn:hierarchy":[
        "tgn:7173960",
        "tgn:7003669",
        "tgn:1000003",
        "tgn:7000084",
        "tgn:7029392"
    ],
    "tgn:id":7173960,
    "tgn:name":"Gro\u00dfbachwald",
    "tgn:placetype":[
        "aat:300008863"
    ]
},
  "bbox": [],
  "geometry": {"coordinates":[10.583333,49.683333],"type":"Point"}
}
=======
{"geometry":{"type":"Point","coordinates":[10.583333,49.683333]},"type":"Feature","properties":{"hierarchy":["tgn:7173960","tgn:7003669","tgn:1000003","tgn:7000084","tgn:7029392"],"placetype":["aat:300008863"],"id":7173960,"name:xx":"Gro\u00dfbachwald"}}
>>>>>>> 03f74aca74312dbeaf24d7e61306dd6a786dc3d0
