{
  "id": 1129439,
  "type": "Feature",
  "properties": {
    "tgn:hierarchy":[
        "tgn:1129439",
        "tgn:7016640",
        "tgn:1000050",
        "tgn:1000002",
        "tgn:7029392"
    ],
    "tgn:id":1129439,
    "tgn:name":"Salaqu\u00ed",
    "tgn:placetype":[
        "aat:300008707"
    ]
},
  "bbox": [],
  "geometry": {"coordinates":[-77.1167,7.45],"type":"Point"}
}