{
  "id": 7329593,
  "type": "Feature",
  "properties": {
    "tgn:hierarchy":[
        "tgn:7329593",
        "tgn:7001165",
        "tgn:1000003",
        "tgn:7002793",
        "tgn:1000095",
        "tgn:7029392"
    ],
    "tgn:id":7329593,
    "tgn:name":"Pinedo",
    "tgn:placetype":[
        "aat:300008347"
    ]
},
  "bbox": [],
  "geometry": {"coordinates":[-0.333333,39.416667],"type":"Point"}
}