<<<<<<< HEAD
{
  "id": 7350785,
  "type": "Feature",
  "properties": {
    "tgn:hierarchy":[
        "tgn:7350785",
        "tgn:7005580",
        "tgn:1000001",
        "tgn:7005560",
        "tgn:7029392"
    ],
    "tgn:id":7350785,
    "tgn:name":"Baja",
    "tgn:placetype":[
        "aat:300008347"
    ]
},
  "bbox": [],
  "geometry": {"coordinates":[-91.8,16.533333],"type":"Point"}
}
=======
{"geometry":{"type":"Point","coordinates":[-91.800000,16.533333]},"type":"Feature","properties":{"hierarchy":["tgn:7350785","tgn:7005580","tgn:1000001","tgn:7005560","tgn:7029392"],"placetype":["aat:300008347"],"id":7350785,"name:xx":"Baja"}}
>>>>>>> 03f74aca74312dbeaf24d7e61306dd6a786dc3d0
