{
  "id": 7120388,
  "type": "Feature",
  "properties": {
    "tgn:hierarchy":[
        "tgn:7120388",
        "tgn:1000003",
        "tgn:7000094",
        "tgn:7000084",
        "tgn:7029392"
    ],
    "tgn:id":7120388,
    "tgn:name":"Pr\u00e4gel-Bach",
    "tgn:placetype":[
        "aat:300008699"
    ]
},
  "bbox": [],
  "geometry": {"coordinates":[13.633333,54.033333],"type":"Point"}
}