{
  "id": 2187373,
  "type": "Feature",
  "properties": {
    "tgn:hierarchy":[
        "tgn:2187373",
        "tgn:1000001",
        "tgn:2001411",
        "tgn:7012149",
        "tgn:7007526",
        "tgn:7029392"
    ],
    "tgn:id":2187373,
    "tgn:name":"Boone Canyon",
    "tgn:placetype":[
        "aat:300008761"
    ]
},
  "bbox": [],
  "geometry": {"coordinates":[-114.4167,40.15],"type":"Point"}
}