{
  "id": 1035608,
  "type": "Feature",
  "properties": {
    "tgn:hierarchy":[
        "tgn:1035608",
        "tgn:1000003",
        "tgn:7001097",
        "tgn:1000070",
        "tgn:7029392"
    ],
    "tgn:id":1035608,
    "tgn:name":"Samer",
    "tgn:placetype":[
        "aat:300008347"
    ]
},
  "bbox": [],
  "geometry": {"coordinates":[1.75,50.6333],"type":"Point"}
}