{
  "id": 2551714,
  "type": "Feature",
  "properties": {
    "tgn:hierarchy":[
        "tgn:2551714",
        "tgn:1000001",
        "tgn:7012149",
        "tgn:1002553",
        "tgn:7007920",
        "tgn:7029392"
    ],
    "tgn:id":2551714,
    "tgn:name":"Number 5 Canyon",
    "tgn:placetype":[
        "aat:300008761"
    ]
},
  "bbox": [],
  "geometry": {"coordinates":[-120.9667,47.2167],"type":"Point"}
}