{
  "id": 2206265,
  "type": "Feature",
  "properties": {
    "tgn:hierarchy":[
        "tgn:2206265",
        "tgn:1002132",
        "tgn:1000001",
        "tgn:7012149",
        "tgn:7007919",
        "tgn:7029392"
    ],
    "tgn:id":2206265,
    "tgn:name":"Bullbegger Creek",
    "tgn:placetype":[
        "aat:300008706"
    ]
},
  "bbox": [],
  "geometry": {"coordinates":[-75.55,37.9667],"type":"Point"}
}