{
  "id": 2264787,
  "type": "Feature",
  "properties": {
    "tgn:hierarchy":[
        "tgn:2264787",
        "tgn:1000001",
        "tgn:7012149",
        "tgn:2001496",
        "tgn:7007709",
        "tgn:7029392"
    ],
    "tgn:id":2264787,
    "tgn:name":"Craig Heights",
    "tgn:placetype":[
        "aat:300008347"
    ]
},
  "bbox": [],
  "geometry": {"coordinates":[-81.0833,35.3667],"type":"Point"}
}