{
  "id": 2006666,
  "type": "Feature",
  "properties": {
    "tgn:hierarchy":[
        "tgn:2006666",
        "tgn:1000001",
        "tgn:7006451",
        "tgn:7012149",
        "tgn:2000097",
        "tgn:7029392"
    ],
    "tgn:id":2006666,
    "tgn:name":"Citrus Park",
    "tgn:placetype":[
        "aat:300387016"
    ]
},
  "bbox": [],
  "geometry": {"coordinates":[-112.4333,33.5333],"type":"Point"}
}