{
  "id": 7344321,
  "type": "Feature",
  "properties": {
    "tgn:hierarchy":[
        "tgn:7344321",
        "tgn:7008912",
        "tgn:7030216",
        "tgn:1000003",
        "tgn:1000095",
        "tgn:7029392"
    ],
    "tgn:id":7344321,
    "tgn:name":"Arr\u00e9s",
    "tgn:placetype":[
        "aat:300008347"
    ]
},
  "bbox": [],
  "geometry": {"coordinates":[0.71233,42.757417],"type":"Point"}
}