{
  "id": 2455941,
  "type": "Feature",
  "properties": {
    "tgn:hierarchy":[
        "tgn:2455941",
        "tgn:1000001",
        "tgn:7012149",
        "tgn:2001044",
        "tgn:7007521",
        "tgn:7029392"
    ],
    "tgn:id":2455941,
    "tgn:name":"Little Hall Lake",
    "tgn:placetype":[
        "aat:300008680"
    ]
},
  "bbox": [],
  "geometry": {"coordinates":[-94.3667,43.6333],"type":"Point"}
}