{
  "id": 2665581,
  "type": "Feature",
  "properties": {
    "tgn:hierarchy":[
        "tgn:2665581",
        "tgn:1000001",
        "tgn:7012149",
        "tgn:2001851",
        "tgn:7007825",
        "tgn:7029392"
    ],
    "tgn:id":2665581,
    "tgn:name":"Sinking Creek",
    "tgn:placetype":[
        "aat:300008706"
    ]
},
  "bbox": [],
  "geometry": {"coordinates":[-83.0333,36.0333],"type":"Point"}
}