{
  "id": 7189651,
  "type": "Feature",
  "properties": {
    "tgn:hierarchy":[
        "tgn:7189651",
        "tgn:1000003",
        "tgn:7003677",
        "tgn:7000084",
        "tgn:7029392"
    ],
    "tgn:id":7189651,
    "tgn:name":"Entenplatz",
    "tgn:placetype":[
        "aat:300008347"
    ]
},
  "bbox": [],
  "geometry": {"coordinates":[6.15,50.733333],"type":"Point"}
}