{
  "id": 7400132,
  "type": "Feature",
  "properties": {
    "tgn:hierarchy":[
        "tgn:7400132",
        "tgn:1000001",
        "tgn:7005593",
        "tgn:7005560",
        "tgn:7029392"
    ],
    "tgn:id":7400132,
    "tgn:name":"El Pozo, R\u00edo",
    "tgn:placetype":[
        "aat:300008699"
    ]
},
  "bbox": [],
  "geometry": {"coordinates":[-99.329167,21.536111],"type":"Point"}
}