<<<<<<< HEAD
{
  "id": 2400080,
  "type": "Feature",
  "properties": {
    "tgn:hierarchy":[
        "tgn:2400080",
        "tgn:1000001",
        "tgn:2000867",
        "tgn:7012149",
        "tgn:7007256",
        "tgn:7029392"
    ],
    "tgn:id":2400080,
    "tgn:name":"Horse Creek",
    "tgn:placetype":[
        "aat:300008706"
    ]
},
  "bbox": [],
  "geometry": {"coordinates":[-92.9167,32.8],"type":"Point"}
}
=======
{"geometry":{"type":"Point","coordinates":[-92.916700,32.800000]},"type":"Feature","properties":{"hierarchy":["tgn:2400080","tgn:1000001","tgn:2000867","tgn:7012149","tgn:7007256","tgn:7029392"],"placetype":["aat:300008706"],"id":2400080,"name:xx":"Horse Creek"}}
>>>>>>> 03f74aca74312dbeaf24d7e61306dd6a786dc3d0
