{
  "id": 7568115,
  "type": "Feature",
  "properties": {
    "tgn:hierarchy":[
        "tgn:7568115",
        "tgn:1000004",
        "tgn:7000198",
        "tgn:7031786",
        "tgn:7029392"
    ],
    "tgn:id":7568115,
    "tgn:name:en":"\u0100ughi Forest Chauki",
    "tgn:placetype":[
        "aat:300387503"
    ]
},
  "bbox": [],
  "geometry": {"coordinates":[78.623451,29.773969],"type":"Point"}
}