{
  "id": 2215302,
  "type": "Feature",
  "properties": {
    "tgn:hierarchy":[
        "tgn:2215302",
        "tgn:1000001",
        "tgn:7012149",
        "tgn:2001761",
        "tgn:7007712",
        "tgn:7029392"
    ],
    "tgn:id":2215302,
    "tgn:name":"Callas Mountain",
    "tgn:placetype":[
        "aat:300008798"
    ]
},
  "bbox": [],
  "geometry": {"coordinates":[-83.1667,34.8833],"type":"Point"}
}