{
  "id": 1099439,
  "type": "Feature",
  "properties": {
    "tgn:hierarchy":[
        "tgn:1099439",
        "tgn:7006160",
        "tgn:1000898",
        "tgn:1000006",
        "tgn:7029392"
    ],
    "tgn:id":1099439,
    "tgn:name":"Bua",
    "tgn:placetype":[
        "aat:300008347"
    ]
},
  "bbox": [],
  "geometry": {"coordinates":[147.55,-6.7333],"type":"Point"}
}