{
  "id": 7404440,
  "type": "Feature",
  "properties": {
    "tgn:hierarchy":[
        "tgn:7404440",
        "tgn:7005585",
        "tgn:1000001",
        "tgn:7005560",
        "tgn:7029392"
    ],
    "tgn:id":7404440,
    "tgn:name":"El B\u00e1lsamo",
    "tgn:placetype":[
        "aat:300008347"
    ]
},
  "bbox": [],
  "geometry": {"coordinates":[-100.916667,18.083333],"type":"Point"}
}