{
  "id": 7118593,
  "type": "Feature",
  "properties": {
    "tgn:hierarchy":[
        "tgn:7118593",
        "tgn:1000003",
        "tgn:7003682",
        "tgn:7000084",
        "tgn:7029392"
    ],
    "tgn:id":7118593,
    "tgn:name":"P\u00f6lsenhof",
    "tgn:placetype":[
        "aat:300000206"
    ]
},
  "bbox": [],
  "geometry": {"coordinates":[6.316667,49.833333],"type":"Point"}
}