<<<<<<< HEAD
{
  "id": 7118593,
  "type": "Feature",
  "properties": {
    "tgn:hierarchy":[
        "tgn:7118593",
        "tgn:1000003",
        "tgn:7003682",
        "tgn:7000084",
        "tgn:7029392"
    ],
    "tgn:id":7118593,
    "tgn:name":"P\u00f6lsenhof",
    "tgn:placetype":[
        "aat:300000206"
    ]
},
  "bbox": [],
  "geometry": {"coordinates":[6.316667,49.833333],"type":"Point"}
}
=======
{"geometry":{"type":"Point","coordinates":[6.316667,49.833333]},"type":"Feature","properties":{"hierarchy":["tgn:7118593","tgn:1000003","tgn:7003682","tgn:7000084","tgn:7029392"],"placetype":["aat:300000206"],"id":7118593,"name:xx":"P\u00f6lsenhof"}}
>>>>>>> 03f74aca74312dbeaf24d7e61306dd6a786dc3d0
