{
  "id": 7334940,
  "type": "Feature",
  "properties": {
    "tgn:hierarchy":[
        "tgn:7334940",
        "tgn:7002758",
        "tgn:7002830",
        "tgn:1000003",
        "tgn:1000095",
        "tgn:7029392"
    ],
    "tgn:id":7334940,
    "tgn:name":"Fuengirola, R\u00edo de",
    "tgn:placetype":[
        "aat:300008699"
    ]
},
  "bbox": [],
  "geometry": {"coordinates":[-4.633333,36.533333],"type":"Point"}
}