{
  "id": 2746425,
  "type": "Feature",
  "properties": {
    "tgn:hierarchy":[
        "tgn:2746425",
        "tgn:7002659",
        "tgn:1000001",
        "tgn:7012149",
        "tgn:2000023",
        "tgn:7029392"
    ],
    "tgn:id":2746425,
    "tgn:name":"W W Weissinger Number 4 Lake",
    "tgn:placetype":[
        "aat:300006191"
    ]
},
  "bbox": [],
  "geometry": {"coordinates":[-87.3667,32.3833],"type":"Point"}
}