{
  "id": 2395704,
  "type": "Feature",
  "properties": {
    "tgn:hierarchy":[
        "tgn:2395704",
        "tgn:1000001",
        "tgn:7012149",
        "tgn:2001927",
        "tgn:7007825",
        "tgn:7029392"
    ],
    "tgn:id":2395704,
    "tgn:name":"Hollis Prospect",
    "tgn:placetype":[
        "aat:300000390"
    ]
},
  "bbox": [],
  "geometry": {"coordinates":[-87.6167,35.0333],"type":"Point"}
}