{
  "id": 7322442,
  "type": "Feature",
  "properties": {
    "tgn:hierarchy":[
        "tgn:7322442",
        "tgn:7002842",
        "tgn:7001158",
        "tgn:1000003",
        "tgn:1000095",
        "tgn:7029392"
    ],
    "tgn:id":7322442,
    "tgn:name":"Santerv\u00e1s del Burgo",
    "tgn:placetype":[
        "aat:300008347"
    ]
},
  "bbox": [],
  "geometry": {"coordinates":[-3.15,41.716667],"type":"Point"}
}