<<<<<<< HEAD
{
  "id": 2768239,
  "type": "Feature",
  "properties": {
    "tgn:hierarchy":[
        "tgn:2768239",
        "tgn:1002178",
        "tgn:1000001",
        "tgn:7012149",
        "tgn:7007565",
        "tgn:7029392"
    ],
    "tgn:id":2768239,
    "tgn:name":"Whites Lake",
    "tgn:placetype":[
        "aat:300006191"
    ]
},
  "bbox": [],
  "geometry": {"coordinates":[-74.1167,41.0],"type":"Point"}
}
=======
{"geometry":{"type":"Point","coordinates":[-74.116700,41.000000]},"type":"Feature","properties":{"hierarchy":["tgn:2768239","tgn:1002178","tgn:1000001","tgn:7012149","tgn:7007565","tgn:7029392"],"placetype":["aat:300006191"],"id":2768239,"name:xx":"Whites Lake"}}
>>>>>>> 03f74aca74312dbeaf24d7e61306dd6a786dc3d0
