{
  "id": 7391568,
  "type": "Feature",
  "properties": {
    "tgn:hierarchy":[
        "tgn:7391568",
        "tgn:1001835",
        "tgn:1000001",
        "tgn:7005560",
        "tgn:7029392"
    ],
    "tgn:id":7391568,
    "tgn:name":"Rancho Santo Domingo",
    "tgn:placetype":[
        "aat:300008347"
    ]
},
  "bbox": [],
  "geometry": {"coordinates":[-116.366667,31.633333],"type":"Point"}
}