<<<<<<< HEAD
{
  "id": 7354632,
  "type": "Feature",
  "properties": {
    "tgn:hierarchy":[
        "tgn:7354632",
        "tgn:1000001",
        "tgn:7005597",
        "tgn:7005560",
        "tgn:7029392"
    ],
    "tgn:id":7354632,
    "tgn:name":"Charco A\u00f1ejo",
    "tgn:placetype":[
        "aat:300008347"
    ]
},
  "bbox": [],
  "geometry": {"coordinates":[-98.5,25.65],"type":"Point"}
}
=======
{"geometry":{"type":"Point","coordinates":[-98.500000,25.650000]},"type":"Feature","properties":{"hierarchy":["tgn:7354632","tgn:1000001","tgn:7005597","tgn:7005560","tgn:7029392"],"placetype":["aat:300008347"],"id":7354632,"name:xx":"Charco A\u00f1ejo"}}
>>>>>>> 03f74aca74312dbeaf24d7e61306dd6a786dc3d0
