{
  "id": 2170478,
  "type": "Feature",
  "properties": {
    "tgn:hierarchy":[
        "tgn:2170478",
        "tgn:1000001",
        "tgn:7012149",
        "tgn:1002594",
        "tgn:7007920",
        "tgn:7029392"
    ],
    "tgn:id":2170478,
    "tgn:name":"Big Roger Creek",
    "tgn:placetype":[
        "aat:300008706"
    ]
},
  "bbox": [],
  "geometry": {"coordinates":[-123.2167,46.4667],"type":"Point"}
}