{
  "id": 7182081,
  "type": "Feature",
  "properties": {
    "tgn:hierarchy":[
        "tgn:7182081",
        "tgn:7003669",
        "tgn:1000003",
        "tgn:7000084",
        "tgn:7029392"
    ],
    "tgn:id":7182081,
    "tgn:name":"Geisalpen-Horn",
    "tgn:placetype":[
        "aat:300008795"
    ]
},
  "bbox": [],
  "geometry": {"coordinates":[10.316667,47.416667],"type":"Point"}
}