{
  "id": 2520171,
  "type": "Feature",
  "properties": {
    "tgn:hierarchy":[
        "tgn:2520171",
        "tgn:1000001",
        "tgn:7012149",
        "tgn:7007713",
        "tgn:7029392"
    ],
    "tgn:id":2520171,
    "tgn:name":"Molumby Slough",
    "tgn:placetype":[
        "aat:300008680"
    ]
},
  "bbox": [],
  "geometry": {"coordinates":[-96.9833,44.1833],"type":"Point"}
}