{
  "id": 2567482,
  "type": "Feature",
  "properties": {
    "tgn:hierarchy":[
        "tgn:2567482",
        "tgn:1000001",
        "tgn:1002665",
        "tgn:7012149",
        "tgn:7007517",
        "tgn:7029392"
    ],
    "tgn:id":2567482,
    "tgn:name":"Paper Mill Village",
    "tgn:placetype":[
        "aat:300008347"
    ]
},
  "bbox": [],
  "geometry": {"coordinates":[-71.5833,42.6167],"type":"Point"}
}