{
  "id": 7488122,
  "type": "Feature",
  "properties": {
    "tgn:hierarchy":[
        "tgn:7488122",
        "tgn:1000004",
        "tgn:7492971",
        "tgn:1000141",
        "tgn:7029392"
    ],
    "tgn:id":7488122,
    "tgn:name":"Nanrenlu",
    "tgn:placetype":[
        "aat:300008347"
    ]
},
  "bbox": [],
  "geometry": {"coordinates":[120.891667,22.088333],"type":"Point"}
}