{
  "id": 2552246,
  "type": "Feature",
  "properties": {
    "tgn:hierarchy":[
        "tgn:2552246",
        "tgn:1000001",
        "tgn:2001099",
        "tgn:7012149",
        "tgn:7007522",
        "tgn:7029392"
    ],
    "tgn:id":2552246,
    "tgn:name":"Number Sixtyfive, Island",
    "tgn:placetype":[
        "aat:300008791"
    ]
},
  "bbox": [],
  "geometry": {"coordinates":[-90.9167,34.2333],"type":"Point"}
}