<<<<<<< HEAD
{
  "id": 2335034,
  "type": "Feature",
  "properties": {
    "tgn:hierarchy":[
        "tgn:2335034",
        "tgn:1000001",
        "tgn:7012149",
        "tgn:2000220",
        "tgn:7007158",
        "tgn:7029392"
    ],
    "tgn:id":2335034,
    "tgn:name":"Forrest Ditch",
    "tgn:placetype":[
        "aat:300006075"
    ]
},
  "bbox": [],
  "geometry": {"coordinates":[-106.3167,40.5167],"type":"Point"}
}
=======
{"geometry":{"type":"Point","coordinates":[-106.316700,40.516700]},"type":"Feature","properties":{"hierarchy":["tgn:2335034","tgn:1000001","tgn:7012149","tgn:2000220","tgn:7007158","tgn:7029392"],"placetype":["aat:300006075"],"id":2335034,"name:xx":"Forrest Ditch"}}
>>>>>>> 03f74aca74312dbeaf24d7e61306dd6a786dc3d0
