{
  "id": 7445310,
  "type": "Feature",
  "properties": {
    "tgn:hierarchy":[
        "tgn:7445310",
        "tgn:7002444",
        "tgn:1000003",
        "tgn:7009907",
        "tgn:7008591",
        "tgn:7029392"
    ],
    "tgn:id":7445310,
    "tgn:name:en":"Weatherness Sound",
    "tgn:placetype":[
        "aat:300266558"
    ]
},
  "bbox": [],
  "geometry": {"coordinates":[-2.833333,59.25],"type":"Point"}
}