{
  "id": 7494391,
  "type": "Feature",
  "properties": {
    "tgn:hierarchy":[
        "tgn:7494391",
        "tgn:7488858",
        "tgn:1000004",
        "tgn:1000141",
        "tgn:7029392"
    ],
    "tgn:id":7494391,
    "tgn:name":"Fengshuiping",
    "tgn:placetype":[
        "aat:300008347"
    ]
},
  "bbox": [],
  "geometry": {"coordinates":[120.7204,23.9585],"type":"Point"}
}