{
  "id": 1072102,
  "type": "Feature",
  "properties": {
    "tgn:hierarchy":[
        "tgn:1072102",
        "tgn:1000004",
        "tgn:1001390",
        "tgn:1000111",
        "tgn:7029392"
    ],
    "tgn:id":1072102,
    "tgn:name":"Tandian",
    "tgn:placetype":[
        "aat:300008347"
    ]
},
  "bbox": [],
  "geometry": {"coordinates":[124.7833,40.6167],"type":"Point"}
}