{
  "id": 7554229,
  "type": "Feature",
  "properties": {
    "tgn:hierarchy":[
        "tgn:7554229",
        "tgn:1001828",
        "tgn:1000004",
        "tgn:7000198",
        "tgn:7029392"
    ],
    "tgn:id":7554229,
    "tgn:name:en":"Nish\u0101nkonda",
    "tgn:placetype":[
        "aat:300008795"
    ]
},
  "bbox": [],
  "geometry": {"coordinates":[79.583333,15.516667],"type":"Point"}
}