{
  "id": 2634158,
  "type": "Feature",
  "properties": {
    "tgn:hierarchy":[
        "tgn:2634158",
        "tgn:1000001",
        "tgn:2002257",
        "tgn:7012149",
        "tgn:7013961",
        "tgn:7029392"
    ],
    "tgn:id":2634158,
    "tgn:name":"Russell Creek",
    "tgn:placetype":[
        "aat:300008706"
    ]
},
  "bbox": [],
  "geometry": {"coordinates":[-82.35,38.3833],"type":"Point"}
}