{
  "id": 2498399,
  "type": "Feature",
  "properties": {
    "tgn:hierarchy":[
        "tgn:2498399",
        "tgn:1000001",
        "tgn:7012149",
        "tgn:7007158",
        "tgn:2000245",
        "tgn:7029392"
    ],
    "tgn:id":2498399,
    "tgn:name":"Mc Kinley Ditch Number 2",
    "tgn:placetype":[
        "aat:300006075"
    ]
},
  "bbox": [],
  "geometry": {"coordinates":[-107.25,40.6333],"type":"Point"}
}