{
  "id": 2311951,
  "type": "Feature",
  "properties": {
    "tgn:hierarchy":[
        "tgn:2311951",
        "tgn:1000001",
        "tgn:7012149",
        "tgn:1002562",
        "tgn:7007251",
        "tgn:7029392"
    ],
    "tgn:id":2311951,
    "tgn:name":"Egg Bag Creek",
    "tgn:placetype":[
        "aat:300008706"
    ]
},
  "bbox": [],
  "geometry": {"coordinates":[-88.9667,41.1333],"type":"Point"}
}