{
  "id": 7408176,
  "type": "Feature",
  "properties": {
    "tgn:hierarchy":[
        "tgn:7408176",
        "tgn:1000001",
        "tgn:7005590",
        "tgn:7005560",
        "tgn:7029392"
    ],
    "tgn:id":7408176,
    "tgn:name":"La Pastoria, R\u00edo",
    "tgn:placetype":[
        "aat:300008699"
    ]
},
  "bbox": [],
  "geometry": {"coordinates":[-101.883333,19.083333],"type":"Point"}
}