{
  "id": 7342948,
  "type": "Feature",
  "properties": {
    "tgn:hierarchy":[
        "tgn:7342948",
        "tgn:7002824",
        "tgn:1000003",
        "tgn:7002786",
        "tgn:1000095",
        "tgn:7029392"
    ],
    "tgn:id":7342948,
    "tgn:name":"Caldebarcos, Punta de",
    "tgn:placetype":[
        "aat:300386846"
    ]
},
  "bbox": [],
  "geometry": {"coordinates":[-9.133333,42.85],"type":"Point"}
}