{
  "id": 2065941,
  "type": "Feature",
  "properties": {
    "tgn:hierarchy":[
        "tgn:2065941",
        "tgn:1000001",
        "tgn:1002410",
        "tgn:7012149",
        "tgn:7007565",
        "tgn:7029392"
    ],
    "tgn:id":2065941,
    "tgn:name":"Porchtown",
    "tgn:placetype":[
        "aat:300008347"
    ]
},
  "bbox": [],
  "geometry": {"coordinates":[-75.0833,39.5833],"type":"Point"}
}