{
  "id": 7475887,
  "type": "Feature",
  "properties": {
    "tgn:hierarchy":[
        "tgn:7475887",
        "tgn:1000004",
        "tgn:7467799",
        "tgn:1000141",
        "tgn:7029392"
    ],
    "tgn:id":7475887,
    "tgn:name":"Shoutian Gong",
    "tgn:placetype":[
        "aat:300007595"
    ]
},
  "bbox": [],
  "geometry": {"coordinates":[120.618598,23.807302],"type":"Point"}
}