{
  "id": 7053331,
  "type": "Feature",
  "properties": {
    "tgn:hierarchy":[
        "tgn:7053331",
        "tgn:7002996",
        "tgn:1000003",
        "tgn:7002997",
        "tgn:1000080",
        "tgn:7029392"
    ],
    "tgn:id":7053331,
    "tgn:name":"Madonna di Vallio",
    "tgn:placetype":[
        "aat:300008347"
    ]
},
  "bbox": [],
  "geometry": {"coordinates":[12.416111,45.637222],"type":"Point"}
}