{
  "id": 2019965,
  "type": "Feature",
  "properties": {
    "tgn:hierarchy":[
        "tgn:2019965",
        "tgn:1000001",
        "tgn:1002207",
        "tgn:7012149",
        "tgn:7007240",
        "tgn:7029392"
    ],
    "tgn:id":2019965,
    "tgn:name":"Kendall Green",
    "tgn:placetype":[
        "aat:300008347"
    ]
},
  "bbox": [],
  "geometry": {"coordinates":[-80.1167,26.25],"type":"Point"}
}