{
  "id": 2560151,
  "type": "Feature",
  "properties": {
    "tgn:hierarchy":[
        "tgn:2560151",
        "tgn:1000001",
        "tgn:1002313",
        "tgn:7012149",
        "tgn:7007706",
        "tgn:7029392"
    ],
    "tgn:id":2560151,
    "tgn:name":"Orange Hill",
    "tgn:placetype":[
        "aat:300008798"
    ]
},
  "bbox": [],
  "geometry": {"coordinates":[-81.4333,41.4833],"type":"Point"}
}