{
  "id": 7149617,
  "type": "Feature",
  "properties": {
    "tgn:hierarchy":[
        "tgn:7149617",
        "tgn:7003669",
        "tgn:1000003",
        "tgn:7000084",
        "tgn:7029392"
    ],
    "tgn:id":7149617,
    "tgn:name":"Krebshof",
    "tgn:placetype":[
        "aat:300000206"
    ]
},
  "bbox": [],
  "geometry": {"coordinates":[10.316667,49.183333],"type":"Point"}
}