{
  "id": 2136593,
  "type": "Feature",
  "properties": {
    "tgn:hierarchy":[
        "tgn:2136593",
        "tgn:1000001",
        "tgn:1002479",
        "tgn:7012149",
        "tgn:7007240",
        "tgn:7029392"
    ],
    "tgn:id":2136593,
    "tgn:name":"Archie Creek",
    "tgn:placetype":[
        "aat:300008706"
    ]
},
  "bbox": [],
  "geometry": {"coordinates":[-82.35,27.8833],"type":"Point"}
}