{
  "id": 2754385,
  "type": "Feature",
  "properties": {
    "tgn:hierarchy":[
        "tgn:2754385",
        "tgn:1000001",
        "tgn:7012149",
        "tgn:7007922",
        "tgn:7029392"
    ],
    "tgn:id":2754385,
    "tgn:name":"Waupaca River",
    "tgn:placetype":[
        "aat:300008707"
    ]
},
  "bbox": [],
  "geometry": {"coordinates":[-89.2667,44.4167],"type":"Point"}
}