{
  "id": 7325452,
  "type": "Feature",
  "properties": {
    "tgn:hierarchy":[
        "tgn:7325452",
        "tgn:7002804",
        "tgn:1000003",
        "tgn:7002793",
        "tgn:1000095",
        "tgn:7029392"
    ],
    "tgn:id":7325452,
    "tgn:name":"San Mart\u00edn, Cabo de",
    "tgn:placetype":[
        "aat:300386846"
    ]
},
  "bbox": [],
  "geometry": {"coordinates":[0.266667,38.766667],"type":"Point"}
}