{
  "id": 2745529,
  "type": "Feature",
  "properties": {
    "tgn:hierarchy":[
        "tgn:2745529",
        "tgn:1000001",
        "tgn:7012149",
        "tgn:2001657",
        "tgn:7007707",
        "tgn:7029392"
    ],
    "tgn:id":2745529,
    "tgn:name":"Viola Spring",
    "tgn:placetype":[
        "aat:300008697"
    ]
},
  "bbox": [],
  "geometry": {"coordinates":[-96.5167,34.3667],"type":"Point"}
}