<<<<<<< HEAD
{
  "id": 2760803,
  "type": "Feature",
  "properties": {
    "tgn:hierarchy":[
        "tgn:2760803",
        "tgn:1000001",
        "tgn:2000327",
        "tgn:7012149",
        "tgn:7007248",
        "tgn:7029392"
    ],
    "tgn:id":2760803,
    "tgn:name":"West Hampton",
    "tgn:placetype":[
        "aat:300008347"
    ]
},
  "bbox": [],
  "geometry": {"coordinates":[-82.0667,33.5167],"type":"Point"}
}
=======
{"geometry":{"type":"Point","coordinates":[-82.066700,33.516700]},"type":"Feature","properties":{"hierarchy":["tgn:2760803","tgn:1000001","tgn:2000327","tgn:7012149","tgn:7007248","tgn:7029392"],"placetype":["aat:300008347"],"id":2760803,"name:xx":"West Hampton"}}
>>>>>>> 03f74aca74312dbeaf24d7e61306dd6a786dc3d0
