{
  "id": 2412971,
  "type": "Feature",
  "properties": {
    "tgn:hierarchy":[
        "tgn:2412971",
        "tgn:7006450",
        "tgn:1000001",
        "tgn:7019698",
        "tgn:7012149",
        "tgn:7029392"
    ],
    "tgn:id":2412971,
    "tgn:name":"Iniskin Shoal",
    "tgn:placetype":[
        "aat:300132348"
    ]
},
  "bbox": [],
  "geometry": {"coordinates":[-153.45,59.6167],"type":"Point"}
}