<<<<<<< HEAD
{
  "id": 2407249,
  "type": "Feature",
  "properties": {
    "tgn:hierarchy":[
        "tgn:2407249",
        "tgn:1000001",
        "tgn:1002228",
        "tgn:7012149",
        "tgn:7007709",
        "tgn:7029392"
    ],
    "tgn:id":2407249,
    "tgn:name":"Hunting Creek",
    "tgn:placetype":[
        "aat:300008706"
    ]
},
  "bbox": [],
  "geometry": {"coordinates":[-75.9833,36.2333],"type":"Point"}
}
=======
{"geometry":{"type":"Point","coordinates":[-75.983300,36.233300]},"type":"Feature","properties":{"hierarchy":["tgn:2407249","tgn:1000001","tgn:1002228","tgn:7012149","tgn:7007709","tgn:7029392"],"placetype":["aat:300008706"],"id":2407249,"name:xx":"Hunting Creek"}}
>>>>>>> 03f74aca74312dbeaf24d7e61306dd6a786dc3d0
