{
  "id": 7485334,
  "type": "Feature",
  "properties": {
    "tgn:hierarchy":[
        "tgn:7485334",
        "tgn:7468018",
        "tgn:1000004",
        "tgn:1000141",
        "tgn:7029392"
    ],
    "tgn:id":7485334,
    "tgn:name":"Yaopingliao",
    "tgn:placetype":[
        "aat:300008347"
    ]
},
  "bbox": [],
  "geometry": {"coordinates":[120.588333,23.573889],"type":"Point"}
}