{
  "id": 2163725,
  "type": "Feature",
  "properties": {
    "tgn:hierarchy":[
        "tgn:2163725",
        "tgn:1000001",
        "tgn:7012149",
        "tgn:2001289",
        "tgn:7007524",
        "tgn:7029392"
    ],
    "tgn:id":2163725,
    "tgn:name":"Benton Gulch",
    "tgn:placetype":[
        "aat:300008761"
    ]
},
  "bbox": [],
  "geometry": {"coordinates":[-111.3667,46.6333],"type":"Point"}
}