{
  "id": 7476798,
  "type": "Feature",
  "properties": {
    "tgn:hierarchy":[
        "tgn:7476798",
        "tgn:7001010",
        "tgn:1000004",
        "tgn:1000141",
        "tgn:7029392"
    ],
    "tgn:id":7476798,
    "tgn:name":"Wufu",
    "tgn:placetype":[
        "aat:300008347"
    ]
},
  "bbox": [],
  "geometry": {"coordinates":[121.505911,23.914347],"type":"Point"}
}