{
  "id": 2233383,
  "type": "Feature",
  "properties": {
    "tgn:hierarchy":[
        "tgn:2233383",
        "tgn:1000001",
        "tgn:7012149",
        "tgn:2001556",
        "tgn:7007709",
        "tgn:7029392"
    ],
    "tgn:id":2233383,
    "tgn:name":"Charlie Creek",
    "tgn:placetype":[
        "aat:300008706"
    ]
},
  "bbox": [],
  "geometry": {"coordinates":[-82.4167,36.0167],"type":"Point"}
}