{
  "id": 2235998,
  "type": "Feature",
  "properties": {
    "tgn:hierarchy":[
        "tgn:2235998",
        "tgn:1000001",
        "tgn:7012149",
        "tgn:2001132",
        "tgn:7007522",
        "tgn:7029392"
    ],
    "tgn:id":2235998,
    "tgn:name":"Chewalla Lake",
    "tgn:placetype":[
        "aat:300006191"
    ]
},
  "bbox": [],
  "geometry": {"coordinates":[-89.3333,34.7667],"type":"Point"}
}