{
  "id": 7470868,
  "type": "Feature",
  "properties": {
    "tgn:hierarchy":[
        "tgn:7470868",
        "tgn:1000004",
        "tgn:7490934",
        "tgn:1000141",
        "tgn:7029392"
    ],
    "tgn:id":7470868,
    "tgn:name":"Jiuchongqiao",
    "tgn:placetype":[
        "aat:300008347"
    ]
},
  "bbox": [],
  "geometry": {"coordinates":[120.416678,23.2056],"type":"Point"}
}