{
  "id": 2227945,
  "type": "Feature",
  "properties": {
    "tgn:hierarchy":[
        "tgn:2227945",
        "tgn:1000001",
        "tgn:2001181",
        "tgn:7012149",
        "tgn:7007523",
        "tgn:7029392"
    ],
    "tgn:id":2227945,
    "tgn:name":"Cedar Bluff Creek",
    "tgn:placetype":[
        "aat:300008706"
    ]
},
  "bbox": [],
  "geometry": {"coordinates":[-91.1167,36.8333],"type":"Point"}
}