{
  "id": 2225265,
  "type": "Feature",
  "properties": {
    "tgn:hierarchy":[
        "tgn:2225265",
        "tgn:1002176",
        "tgn:1000001",
        "tgn:7012149",
        "tgn:7007828",
        "tgn:7029392"
    ],
    "tgn:id":2225265,
    "tgn:name":"Castle Meadow",
    "tgn:placetype":[
        "aat:300008905"
    ]
},
  "bbox": [],
  "geometry": {"coordinates":[-73.0167,42.9333],"type":"Point"}
}