{
  "id": 1096369,
  "type": "Feature",
  "properties": {
    "tgn:hierarchy":[
        "tgn:1096369",
        "tgn:7000490",
        "tgn:1000006",
        "tgn:7001828",
        "tgn:7029392"
    ],
    "tgn:id":1096369,
    "tgn:name":"Brewongle",
    "tgn:placetype":[
        "aat:300008347"
    ]
},
  "bbox": [],
  "geometry": {"coordinates":[149.7167,-33.4833],"type":"Point"}
}