{
  "id": 2737864,
  "type": "Feature",
  "properties": {
    "tgn:hierarchy":[
        "tgn:2737864",
        "tgn:1000001",
        "tgn:7012149",
        "tgn:1002645",
        "tgn:7007920",
        "tgn:7029392"
    ],
    "tgn:id":2737864,
    "tgn:name":"U Lake",
    "tgn:placetype":[
        "aat:300008680"
    ]
},
  "bbox": [],
  "geometry": {"coordinates":[-123.0667,47.4167],"type":"Point"}
}