{
  "id": 7494513,
  "type": "Feature",
  "properties": {
    "tgn:hierarchy":[
        "tgn:7494513",
        "tgn:7468018",
        "tgn:1000004",
        "tgn:1000141",
        "tgn:7029392"
    ],
    "tgn:id":7494513,
    "tgn:name":"Jialinhu",
    "tgn:placetype":[
        "aat:300008347"
    ]
},
  "bbox": [],
  "geometry": {"coordinates":[120.513727,23.264727],"type":"Point"}
}