{
  "id": 7407899,
  "type": "Feature",
  "properties": {
    "tgn:hierarchy":[
        "tgn:7407899",
        "tgn:1000001",
        "tgn:1001893",
        "tgn:7005560",
        "tgn:7029392"
    ],
    "tgn:id":7407899,
    "tgn:name":"El Salitre",
    "tgn:placetype":[
        "aat:300008347"
    ]
},
  "bbox": [],
  "geometry": {"coordinates":[-100.245833,18.779167],"type":"Point"}
}