{
  "id": 7513170,
  "type": "Feature",
  "properties": {
    "tgn:hierarchy":[
        "tgn:7513170",
        "tgn:1009227",
        "tgn:1000226",
        "tgn:1000006",
        "tgn:7016850",
        "tgn:7029392"
    ],
    "tgn:id":7513170,
    "tgn:name:en":"Griffiths Glacier",
    "tgn:placetype":[
        "aat:300008835"
    ]
},
  "bbox": [],
  "geometry": {"coordinates":[171.266667,-42.983333],"type":"Point"}
}