{
  "id": 1036349,
  "type": "Feature",
  "properties": {
    "tgn:hierarchy":[
        "tgn:1036349",
        "tgn:1000003",
        "tgn:7003689",
        "tgn:7000084",
        "tgn:7029392"
    ],
    "tgn:id":1036349,
    "tgn:name":"Andisleben",
    "tgn:placetype":[
        "aat:300008347"
    ]
},
  "bbox": [],
  "geometry": {"coordinates":[10.916667,51.083333],"type":"Point"}
}