<<<<<<< HEAD
{
  "id": 7113838,
  "type": "Feature",
  "properties": {
    "tgn:hierarchy":[
        "tgn:7113838",
        "tgn:1000003",
        "tgn:7003687",
        "tgn:7000084",
        "tgn:7029392"
    ],
    "tgn:id":7113838,
    "tgn:name":"R\u00f6nne Berge",
    "tgn:placetype":[
        "aat:300008777"
    ]
},
  "bbox": [],
  "geometry": {"coordinates":[11.0,51.816667],"type":"Point"}
}
=======
{"geometry":{"type":"Point","coordinates":[11.000000,51.816667]},"type":"Feature","properties":{"hierarchy":["tgn:7113838","tgn:1000003","tgn:7003687","tgn:7000084","tgn:7029392"],"placetype":["aat:300008777"],"id":7113838,"name:xx":"R\u00f6nne Berge"}}
>>>>>>> 03f74aca74312dbeaf24d7e61306dd6a786dc3d0
