{
  "id": 7251995,
  "type": "Feature",
  "properties": {
    "tgn:hierarchy":[
        "tgn:7251995",
        "tgn:7003460",
        "tgn:1000003",
        "tgn:1000063",
        "tgn:4012014",
        "tgn:7029392"
    ],
    "tgn:id":7251995,
    "tgn:name":"Meilvenn",
    "tgn:placetype":[
        "aat:300008347"
    ]
},
  "bbox": [],
  "geometry": {"coordinates":[6.037222,50.327222],"type":"Point"}
}