{
  "id": 7480556,
  "type": "Feature",
  "properties": {
    "tgn:hierarchy":[
        "tgn:7480556",
        "tgn:1000004",
        "tgn:7471332",
        "tgn:1000141",
        "tgn:7029392"
    ],
    "tgn:id":7480556,
    "tgn:name":"Nankeng Qiao",
    "tgn:placetype":[
        "aat:300007836"
    ]
},
  "bbox": [],
  "geometry": {"coordinates":[121.153333,24.844167],"type":"Point"}
}