{
  "id": 2053765,
  "type": "Feature",
  "properties": {
    "tgn:hierarchy":[
        "tgn:2053765",
        "tgn:1002166",
        "tgn:1000001",
        "tgn:7012149",
        "tgn:7007520",
        "tgn:7029392"
    ],
    "tgn:id":2053765,
    "tgn:name":"Woodland",
    "tgn:placetype":[
        "aat:300008347"
    ]
},
  "bbox": [],
  "geometry": {"coordinates":[-85.1333,42.7167],"type":"Point"}
}