{
  "id": 2298556,
  "type": "Feature",
  "properties": {
    "tgn:hierarchy":[
        "tgn:2298556",
        "tgn:1000001",
        "tgn:7012149",
        "tgn:2000220",
        "tgn:7007158",
        "tgn:7029392"
    ],
    "tgn:id":2298556,
    "tgn:name":"Dry Run Ditch",
    "tgn:placetype":[
        "aat:300006075"
    ]
},
  "bbox": [],
  "geometry": {"coordinates":[-106.5333,40.75],"type":"Point"}
}