{
  "id": 2052767,
  "type": "Feature",
  "properties": {
    "tgn:hierarchy":[
        "tgn:2052767",
        "tgn:1000001",
        "tgn:7012149",
        "tgn:1002617",
        "tgn:7007520",
        "tgn:7029392"
    ],
    "tgn:id":2052767,
    "tgn:name":"New Baltimore",
    "tgn:placetype":[
        "aat:300008347"
    ]
},
  "bbox": [],
  "geometry": {"coordinates":[-82.7333,42.6667],"type":"Point"}
}