<<<<<<< HEAD
{
  "id": 7172334,
  "type": "Feature",
  "properties": {
    "tgn:hierarchy":[
        "tgn:7172334",
        "tgn:1000003",
        "tgn:7000094",
        "tgn:7000084",
        "tgn:7029392"
    ],
    "tgn:id":7172334,
    "tgn:name":"Herrenholz",
    "tgn:placetype":[
        "aat:300008863"
    ]
},
  "bbox": [],
  "geometry": {"coordinates":[12.016667,53.75],"type":"Point"}
}
=======
{"geometry":{"type":"Point","coordinates":[12.016667,53.750000]},"type":"Feature","properties":{"hierarchy":["tgn:7172334","tgn:1000003","tgn:7000094","tgn:7000084","tgn:7029392"],"placetype":["aat:300008863"],"id":7172334,"name:xx":"Herrenholz"}}
>>>>>>> 03f74aca74312dbeaf24d7e61306dd6a786dc3d0
