{
  "id": 2225218,
  "type": "Feature",
  "properties": {
    "tgn:hierarchy":[
        "tgn:2225218",
        "tgn:1002716",
        "tgn:1000001",
        "tgn:7012149",
        "tgn:7007711",
        "tgn:7029392"
    ],
    "tgn:id":2225218,
    "tgn:name":"Castle Hill",
    "tgn:placetype":[
        "aat:300008850"
    ]
},
  "bbox": [],
  "geometry": {"coordinates":[-71.35,41.45],"type":"Point"}
}