<<<<<<< HEAD
{
  "id": 7471555,
  "type": "Feature",
  "properties": {
    "tgn:hierarchy":[
        "tgn:7471555",
        "tgn:1000004",
        "tgn:1000454",
        "tgn:1000141",
        "tgn:7029392"
    ],
    "tgn:id":7471555,
    "tgn:name":"Zhuangzinei",
    "tgn:placetype":[
        "aat:300008347"
    ]
},
  "bbox": [],
  "geometry": {"coordinates":[121.46484,25.174669],"type":"Point"}
}
=======
{"geometry":{"type":"Point","coordinates":[121.464840,25.174669]},"type":"Feature","properties":{"hierarchy":["tgn:7471555","tgn:1000004","tgn:1000454","tgn:1000141","tgn:7029392"],"placetype":["aat:300008347"],"id":7471555,"name:xx":"Zhuangzinei"}}
>>>>>>> 03f74aca74312dbeaf24d7e61306dd6a786dc3d0
