{
  "id": 7061950,
  "type": "Feature",
  "properties": {
    "tgn:hierarchy":[
        "tgn:7061950",
        "tgn:7003692",
        "tgn:1000003",
        "tgn:7000084",
        "tgn:7029392"
    ],
    "tgn:id":7061950,
    "tgn:name":"Bachhofen",
    "tgn:placetype":[
        "aat:300000206"
    ]
},
  "bbox": [],
  "geometry": {"coordinates":[9.783333,47.65],"type":"Point"}
}