{
  "id": 2569642,
  "type": "Feature",
  "properties": {
    "tgn:hierarchy":[
        "tgn:2569642",
        "tgn:1000001",
        "tgn:7012149",
        "tgn:2001711",
        "tgn:7007708",
        "tgn:7029392"
    ],
    "tgn:id":2569642,
    "tgn:name":"Parsnip Creek",
    "tgn:placetype":[
        "aat:300008706"
    ]
},
  "bbox": [],
  "geometry": {"coordinates":[-122.3833,42.6333],"type":"Point"}
}