<<<<<<< HEAD
{
  "id": 2255712,
  "type": "Feature",
  "properties": {
    "tgn:hierarchy":[
        "tgn:2255712",
        "tgn:1000001",
        "tgn:2001410",
        "tgn:7012149",
        "tgn:7007526",
        "tgn:7029392"
    ],
    "tgn:id":2255712,
    "tgn:name":"Copper Basin",
    "tgn:placetype":[
        "aat:300386845"
    ]
},
  "bbox": [],
  "geometry": {"coordinates":[-114.7,35.7833],"type":"Point"}
}
=======
{"geometry":{"type":"Point","coordinates":[-114.700000,35.783300]},"type":"Feature","properties":{"hierarchy":["tgn:2255712","tgn:1000001","tgn:2001410","tgn:7012149","tgn:7007526","tgn:7029392"],"placetype":["aat:300386845"],"id":2255712,"name:xx":"Copper Basin"}}
>>>>>>> 03f74aca74312dbeaf24d7e61306dd6a786dc3d0
