<<<<<<< HEAD
{
  "id": 2767538,
  "type": "Feature",
  "properties": {
    "tgn:hierarchy":[
        "tgn:2767538",
        "tgn:1000001",
        "tgn:2001331",
        "tgn:7012149",
        "tgn:7007525",
        "tgn:7029392"
    ],
    "tgn:id":2767538,
    "tgn:name":"White Valley",
    "tgn:placetype":[
        "aat:300386845"
    ]
},
  "bbox": [],
  "geometry": {"coordinates":[-102.0167,42.4667],"type":"Point"}
}
=======
{"geometry":{"type":"Point","coordinates":[-102.016700,42.466700]},"type":"Feature","properties":{"hierarchy":["tgn:2767538","tgn:1000001","tgn:2001331","tgn:7012149","tgn:7007525","tgn:7029392"],"placetype":["aat:300386845"],"id":2767538,"name:xx":"White Valley"}}
>>>>>>> 03f74aca74312dbeaf24d7e61306dd6a786dc3d0
