{
  "id": 2431728,
  "type": "Feature",
  "properties": {
    "tgn:hierarchy":[
        "tgn:2431728",
        "tgn:1000001",
        "tgn:2000462",
        "tgn:7012149",
        "tgn:7007250",
        "tgn:7029392"
    ],
    "tgn:id":2431728,
    "tgn:name":"Katka Peak",
    "tgn:placetype":[
        "aat:300008798"
    ]
},
  "bbox": [],
  "geometry": {"coordinates":[-116.15,48.6167],"type":"Point"}
}