{
  "id": 2209701,
  "type": "Feature",
  "properties": {
    "tgn:hierarchy":[
        "tgn:2209701",
        "tgn:1000001",
        "tgn:2001416",
        "tgn:7012149",
        "tgn:7007526",
        "tgn:7029392"
    ],
    "tgn:id":2209701,
    "tgn:name":"Burro Basin",
    "tgn:placetype":[
        "aat:300386845"
    ]
},
  "bbox": [],
  "geometry": {"coordinates":[-115.3333,36.8833],"type":"Point"}
}