{
  "id": 7204216,
  "type": "Feature",
  "properties": {
    "tgn:hierarchy":[
        "tgn:7204216",
        "tgn:7003669",
        "tgn:1000003",
        "tgn:7000084",
        "tgn:7029392"
    ],
    "tgn:id":7204216,
    "tgn:name":"Br\u00fccklas",
    "tgn:placetype":[
        "aat:300008347"
    ]
},
  "bbox": [],
  "geometry": {"coordinates":[11.966667,50.066667],"type":"Point"}
}