{
  "id": 2102801,
  "type": "Feature",
  "properties": {
    "tgn:hierarchy":[
        "tgn:2102801",
        "tgn:1000001",
        "tgn:7012149",
        "tgn:2002030",
        "tgn:7007826",
        "tgn:7029392"
    ],
    "tgn:id":2102801,
    "tgn:name":"Bluffton",
    "tgn:placetype":[
        "aat:300008347"
    ]
},
  "bbox": [],
  "geometry": {"coordinates":[-98.4833,30.8167],"type":"Point"}
}