{
  "id": 2411490,
  "type": "Feature",
  "properties": {
    "tgn:hierarchy":[
        "tgn:2411490",
        "tgn:1000001",
        "tgn:7012149",
        "tgn:2000471",
        "tgn:7007250",
        "tgn:7029392"
    ],
    "tgn:id":2411490,
    "tgn:name":"Indian Hole Pond",
    "tgn:placetype":[
        "aat:300008680"
    ]
},
  "bbox": [],
  "geometry": {"coordinates":[-115.3167,42.9333],"type":"Point"}
}