<<<<<<< HEAD
{
  "id": 7055981,
  "type": "Feature",
  "properties": {
    "tgn:hierarchy":[
        "tgn:7055981",
        "tgn:1001641",
        "tgn:1000003",
        "tgn:7003121",
        "tgn:1000080",
        "tgn:7029392"
    ],
    "tgn:id":7055981,
    "tgn:name":"Ollastu, Riu",
    "tgn:placetype":[
        "aat:300008699"
    ]
},
  "bbox": [],
  "geometry": {"coordinates":[9.466667,39.35],"type":"Point"}
}
=======
{"geometry":{"type":"Point","coordinates":[9.466667,39.350000]},"type":"Feature","properties":{"hierarchy":["tgn:7055981","tgn:1001641","tgn:1000003","tgn:7003121","tgn:1000080","tgn:7029392"],"placetype":["aat:300008699"],"id":7055981,"name:xx":"Ollastu, Riu"}}
>>>>>>> 03f74aca74312dbeaf24d7e61306dd6a786dc3d0
