{
  "id": 2238792,
  "type": "Feature",
  "properties": {
    "tgn:hierarchy":[
        "tgn:2238792",
        "tgn:1000001",
        "tgn:7012149",
        "tgn:2001887",
        "tgn:7007825",
        "tgn:7029392"
    ],
    "tgn:id":2238792,
    "tgn:name":"Christian Prospect Number One",
    "tgn:placetype":[
        "aat:300000390"
    ]
},
  "bbox": [],
  "geometry": {"coordinates":[-87.5333,35.4833],"type":"Point"}
}