{
  "id": 7334408,
  "type": "Feature",
  "properties": {
    "tgn:hierarchy":[
        "tgn:7334408",
        "tgn:7002805",
        "tgn:7002758",
        "tgn:1000003",
        "tgn:1000095",
        "tgn:7029392"
    ],
    "tgn:id":7334408,
    "tgn:name":"El R\u00edo Grande",
    "tgn:placetype":[
        "aat:300008347"
    ]
},
  "bbox": [],
  "geometry": {"coordinates":[-3.016667,36.816667],"type":"Point"}
}