{
  "id": 7410917,
  "type": "Feature",
  "properties": {
    "tgn:hierarchy":[
        "tgn:7410917",
        "tgn:7005587",
        "tgn:1000001",
        "tgn:7005560",
        "tgn:7029392"
    ],
    "tgn:id":7410917,
    "tgn:name:es":"Xajha",
    "tgn:placetype":[
        "aat:300008347"
    ]
},
  "bbox": [],
  "geometry": {"coordinates":[-99.483333,20.716667],"type":"Point"}
}