{
  "id": 2001635,
  "type": "Feature",
  "properties": {
    "tgn:hierarchy":[
        "tgn:2001635",
        "tgn:1000001",
        "tgn:7012149",
        "tgn:7007707",
        "tgn:7029392"
    ],
    "tgn:id":2001635,
    "tgn:name":"Cimarron",
    "tgn:placetype":[
        "aat:300387145",
        "aat:300000771"
    ]
},
  "bbox": [],
  "geometry": {"coordinates":[-102.5167,36.75],"type":"Point"}
}