{
  "id": 2273395,
  "type": "Feature",
  "properties": {
    "tgn:hierarchy":[
        "tgn:2273395",
        "tgn:1000001",
        "tgn:7012149",
        "tgn:2001928",
        "tgn:7007825",
        "tgn:7029392"
    ],
    "tgn:id":2273395,
    "tgn:name":"Cypress Creek Lake Number Twelve",
    "tgn:placetype":[
        "aat:300006191"
    ]
},
  "bbox": [],
  "geometry": {"coordinates":[-88.7167,36.3667],"type":"Point"}
}