{
  "id": 7295312,
  "type": "Feature",
  "properties": {
    "tgn:hierarchy":[
        "tgn:7295312",
        "tgn:7002849",
        "tgn:1000003",
        "tgn:7009604",
        "tgn:1000095",
        "tgn:7029392"
    ],
    "tgn:id":7295312,
    "tgn:name":"Basigo de Baguio",
    "tgn:placetype":[
        "aat:300008347"
    ]
},
  "bbox": [],
  "geometry": {"coordinates":[-2.81317,43.418309],"type":"Point"}
}