{
  "id": 7476145,
  "type": "Feature",
  "properties": {
    "tgn:hierarchy":[
        "tgn:7476145",
        "tgn:7487020",
        "tgn:1000004",
        "tgn:1000141",
        "tgn:7029392"
    ],
    "tgn:id":7476145,
    "tgn:name":"Erwan",
    "tgn:placetype":[
        "aat:300008347"
    ]
},
  "bbox": [],
  "geometry": {"coordinates":[120.964682,24.66511],"type":"Point"}
}