{
  "id": 7501775,
  "type": "Feature",
  "properties": {
    "tgn:hierarchy":[
        "tgn:7501775",
        "tgn:1000004",
        "tgn:7490934",
        "tgn:1000141",
        "tgn:7029392"
    ],
    "tgn:id":7501775,
    "tgn:name":"Xucuohu Qiao",
    "tgn:placetype":[
        "aat:300007836"
    ]
},
  "bbox": [],
  "geometry": {"coordinates":[120.348056,22.982222],"type":"Point"}
}