{
  "id": 7589871,
  "type": "Feature",
  "properties": {
    "tgn:hierarchy":[
        "tgn:7589871",
        "tgn:1000004",
        "tgn:7000198",
        "tgn:7000799",
        "tgn:7029392"
    ],
    "tgn:id":7589871,
    "tgn:name:en":"Barchoi",
    "tgn:placetype":[
        "aat:300008347"
    ]
},
  "bbox": [],
  "geometry": {"coordinates":[74.434722,33.038889],"type":"Point"}
}