{
  "id": 7236958,
  "type": "Feature",
  "properties": {
    "tgn:hierarchy":[
        "tgn:7236958",
        "tgn:7002681",
        "tgn:7001395",
        "tgn:1000003",
        "tgn:1000074",
        "tgn:7029392"
    ],
    "tgn:id":7236958,
    "tgn:name":"Elaiokh\u00f3rion",
    "tgn:placetype":[
        "aat:300008347"
    ]
},
  "bbox": [],
  "geometry": {"coordinates":[24.25,38.216667],"type":"Point"}
}