{
  "id": 2523177,
  "type": "Feature",
  "properties": {
    "tgn:hierarchy":[
        "tgn:2523177",
        "tgn:1000001",
        "tgn:7012149",
        "tgn:7007919",
        "tgn:7029392"
    ],
    "tgn:id":2523177,
    "tgn:name":"Moores Creek",
    "tgn:placetype":[
        "aat:300008706"
    ]
},
  "bbox": [],
  "geometry": {"coordinates":[-79.2333,37.9333],"type":"Point"}
}