{
  "id": 7469483,
  "type": "Feature",
  "properties": {
    "tgn:hierarchy":[
        "tgn:7469483",
        "tgn:1000004",
        "tgn:7001009",
        "tgn:1000141",
        "tgn:7029392"
    ],
    "tgn:id":7469483,
    "tgn:name":"Qingtonglin Shan",
    "tgn:placetype":[
        "aat:300008798"
    ]
},
  "bbox": [],
  "geometry": {"coordinates":[120.742054,24.040812],"type":"Point"}
}