{
  "id": 7090450,
  "type": "Feature",
  "properties": {
    "tgn:hierarchy":[
        "tgn:7090450",
        "tgn:7003669",
        "tgn:1000003",
        "tgn:7000084",
        "tgn:7029392"
    ],
    "tgn:id":7090450,
    "tgn:name":"Voglsinger",
    "tgn:placetype":[
        "aat:300000206"
    ]
},
  "bbox": [],
  "geometry": {"coordinates":[13.266667,48.55],"type":"Point"}
}