<<<<<<< HEAD
{
  "id": 2330469,
  "type": "Feature",
  "properties": {
    "tgn:hierarchy":[
        "tgn:2330469",
        "tgn:1000001",
        "tgn:7012149",
        "tgn:7029392"
    ],
    "tgn:id":2330469,
    "tgn:name":"Flat Creek",
    "tgn:placetype":[
        "aat:300008706"
    ]
},
  "bbox": [],
  "geometry": {"coordinates":[-88.3833,30.8167],"type":"Point"}
}
=======
{"geometry":{"type":"Point","coordinates":[-88.383300,30.816700]},"type":"Feature","properties":{"hierarchy":["tgn:2330469","tgn:1000001","tgn:7012149","tgn:7029392"],"placetype":["aat:300008706"],"id":2330469,"name:xx":"Flat Creek"}}
>>>>>>> 03f74aca74312dbeaf24d7e61306dd6a786dc3d0
