{
  "id": 2315301,
  "type": "Feature",
  "properties": {
    "tgn:hierarchy":[
        "tgn:2315301",
        "tgn:1000001",
        "tgn:7012149",
        "tgn:7029392"
    ],
    "tgn:id":2315301,
    "tgn:name":"Elliot Branch",
    "tgn:placetype":[
        "aat:300008699"
    ]
},
  "bbox": [],
  "geometry": {"coordinates":[-81.7333,36.6167],"type":"Point"}
}