{
  "id": 7371804,
  "type": "Feature",
  "properties": {
    "tgn:hierarchy":[
        "tgn:7371804",
        "tgn:1000001",
        "tgn:7005595",
        "tgn:7005560",
        "tgn:7029392"
    ],
    "tgn:id":7371804,
    "tgn:name":"La Huerta",
    "tgn:placetype":[
        "aat:300008347"
    ]
},
  "bbox": [],
  "geometry": {"coordinates":[-106.933333,24.216667],"type":"Point"}
}