{
  "id": 2309684,
  "type": "Feature",
  "properties": {
    "tgn:hierarchy":[
        "tgn:2309684",
        "tgn:1000001",
        "tgn:2001472",
        "tgn:7012149",
        "tgn:7007709",
        "tgn:7029392"
    ],
    "tgn:id":2309684,
    "tgn:name":"Eastend Lake",
    "tgn:placetype":[
        "aat:300008680"
    ]
},
  "bbox": [],
  "geometry": {"coordinates":[-78.0167,34.0167],"type":"Point"}
}