{
  "id": 1040135,
  "type": "Feature",
  "properties": {
    "tgn:hierarchy":[
        "tgn:1040135",
        "tgn:7003692",
        "tgn:1000003",
        "tgn:7000084",
        "tgn:7029392"
    ],
    "tgn:id":1040135,
    "tgn:name":"Linkenheim",
    "tgn:placetype":[
        "aat:300008347"
    ]
},
  "bbox": [],
  "geometry": {"coordinates":[8.4167,49.1167],"type":"Point"}
}