{
  "id": 1114439,
  "type": "Feature",
  "properties": {
    "tgn:hierarchy":[
        "tgn:1114439",
        "tgn:1000004",
        "tgn:1001390",
        "tgn:1000111",
        "tgn:7029392"
    ],
    "tgn:id":1114439,
    "tgn:name":"Dalian Wan",
    "tgn:placetype":[
        "aat:300008678"
    ]
},
  "bbox": [],
  "geometry": {"coordinates":[121.75,38.95],"type":"Point"}
}