{
  "id": 2500953,
  "type": "Feature",
  "properties": {
    "tgn:hierarchy":[
        "tgn:2500953",
        "tgn:1000001",
        "tgn:2001014",
        "tgn:7012149",
        "tgn:7007521",
        "tgn:7029392"
    ],
    "tgn:id":2500953,
    "tgn:name":"McFarland Lake",
    "tgn:placetype":[
        "aat:300008680"
    ]
},
  "bbox": [],
  "geometry": {"coordinates":[-90.0667,48.05],"type":"Point"}
}