{
  "id": 2532896,
  "type": "Feature",
  "properties": {
    "tgn:hierarchy":[
        "tgn:2532896",
        "tgn:1000001",
        "tgn:7012149",
        "tgn:2000995",
        "tgn:7007520",
        "tgn:7029392"
    ],
    "tgn:id":2532896,
    "tgn:name":"Murray Drain",
    "tgn:placetype":[
        "aat:300006075"
    ]
},
  "bbox": [],
  "geometry": {"coordinates":[-82.6833,43.35],"type":"Point"}
}