{
  "id": 7572949,
  "type": "Feature",
  "properties": {
    "tgn:hierarchy":[
        "tgn:7572949",
        "tgn:1000004",
        "tgn:7000198",
        "tgn:1001882",
        "tgn:7029392"
    ],
    "tgn:id":7572949,
    "tgn:name:en":"Hutti",
    "tgn:placetype":[
        "aat:300008347"
    ]
},
  "bbox": [],
  "geometry": {"coordinates":[76.65,16.15],"type":"Point"}
}