{
  "id": 2538223,
  "type": "Feature",
  "properties": {
    "tgn:hierarchy":[
        "tgn:2538223",
        "tgn:7006450",
        "tgn:1000001",
        "tgn:2124012",
        "tgn:7012149",
        "tgn:7029392"
    ],
    "tgn:id":2538223,
    "tgn:name":"Nelson Reef",
    "tgn:placetype":[
        "aat:300132348"
    ]
},
  "bbox": [],
  "geometry": {"coordinates":[-154.0333,56.9333],"type":"Point"}
}