{
  "id": 7535692,
  "type": "Feature",
  "properties": {
    "tgn:hierarchy":[
        "tgn:7535692",
        "tgn:7001242",
        "tgn:7016833",
        "tgn:1001142",
        "tgn:7029392"
    ],
    "tgn:id":7535692,
    "tgn:name:en":"Ibw\u012b\u0163 al Qad\u012bmah",
    "tgn:placetype":[
        "aat:300008347"
    ]
},
  "bbox": [],
  "geometry": {"coordinates":[31.133333,29.333333],"type":"Point"}
}