{
  "id": 2168839,
  "type": "Feature",
  "properties": {
    "tgn:hierarchy":[
        "tgn:2168839",
        "tgn:1000001",
        "tgn:7012149",
        "tgn:2002194",
        "tgn:7007919",
        "tgn:7029392"
    ],
    "tgn:id":2168839,
    "tgn:name":"Big Horse Cove",
    "tgn:placetype":[
        "aat:300008761"
    ]
},
  "bbox": [],
  "geometry": {"coordinates":[-82.05,36.8167],"type":"Point"}
}