{
  "id": 7194481,
  "type": "Feature",
  "properties": {
    "tgn:hierarchy":[
        "tgn:7194481",
        "tgn:1000003",
        "tgn:7003687",
        "tgn:7000084",
        "tgn:7029392"
    ],
    "tgn:id":7194481,
    "tgn:name":"Dodendorf",
    "tgn:placetype":[
        "aat:300008347"
    ]
},
  "bbox": [],
  "geometry": {"coordinates":[11.616667,52.033333],"type":"Point"}
}