{
  "id": 7500372,
  "type": "Feature",
  "properties": {
    "tgn:hierarchy":[
        "tgn:7500372",
        "tgn:1000004",
        "tgn:7001009",
        "tgn:1000141",
        "tgn:7029392"
    ],
    "tgn:id":7500372,
    "tgn:name":"Nanzi",
    "tgn:placetype":[
        "aat:300008347"
    ]
},
  "bbox": [],
  "geometry": {"coordinates":[120.528811,24.211039],"type":"Point"}
}