{
  "id": 7467642,
  "type": "Feature",
  "properties": {
    "tgn:hierarchy":[
        "tgn:7467642",
        "tgn:1000004",
        "tgn:7004300",
        "tgn:1000141",
        "tgn:7029392"
    ],
    "tgn:id":7467642,
    "tgn:name":"Xiaolie Yu",
    "tgn:placetype":[
        "aat:300008791"
    ]
},
  "bbox": [],
  "geometry": {"coordinates":[119.585,23.766944],"type":"Point"}
}