{
  "id": 2398684,
  "type": "Feature",
  "properties": {
    "tgn:hierarchy":[
        "tgn:2398684",
        "tgn:1000001",
        "tgn:7012149",
        "tgn:1002755",
        "tgn:7007523",
        "tgn:7029392"
    ],
    "tgn:id":2398684,
    "tgn:name":"Hope",
    "tgn:placetype":[
        "aat:300008347"
    ]
},
  "bbox": [],
  "geometry": {"coordinates":[-91.6667,38.5167],"type":"Point"}
}