{
  "id": 7049386,
  "type": "Feature",
  "properties": {
    "tgn:hierarchy":[
        "tgn:7049386",
        "tgn:7009084",
        "tgn:7004154",
        "tgn:1000003",
        "tgn:1000080",
        "tgn:7029392"
    ],
    "tgn:id":7049386,
    "tgn:name":"Carrito",
    "tgn:placetype":[
        "aat:300008347"
    ]
},
  "bbox": [],
  "geometry": {"coordinates":[13.716667,42.016667],"type":"Point"}
}