{
  "id": 7390120,
  "type": "Feature",
  "properties": {
    "tgn:hierarchy":[
        "tgn:7390120",
        "tgn:7005581",
        "tgn:1000001",
        "tgn:7005560",
        "tgn:7029392"
    ],
    "tgn:id":7390120,
    "tgn:name":"Rancho Ricubichic",
    "tgn:placetype":[
        "aat:300000241"
    ]
},
  "bbox": [],
  "geometry": {"coordinates":[-107.95,27.883333],"type":"Point"}
}