{
  "id": 7465307,
  "type": "Feature",
  "properties": {
    "tgn:hierarchy":[
        "tgn:7465307",
        "tgn:7002445",
        "tgn:1000003",
        "tgn:5000227",
        "tgn:7008591",
        "tgn:7029392"
    ],
    "tgn:id":7465307,
    "tgn:name:en":"Beckford",
    "tgn:placetype":[
        "aat:300008347"
    ]
},
  "bbox": [],
  "geometry": {"coordinates":[-2.033333,52.016667],"type":"Point"}
}