{
  "id": 2512633,
  "type": "Feature",
  "properties": {
    "tgn:hierarchy":[
        "tgn:2512633",
        "tgn:1000001",
        "tgn:7012149",
        "tgn:2000805",
        "tgn:7007255",
        "tgn:7029392"
    ],
    "tgn:id":2512633,
    "tgn:name":"Mill Creek",
    "tgn:placetype":[
        "aat:300008706"
    ]
},
  "bbox": [],
  "geometry": {"coordinates":[-83.0167,37.2833],"type":"Point"}
}