{
  "id": 2587894,
  "type": "Feature",
  "properties": {
    "tgn:hierarchy":[
        "tgn:2587894",
        "tgn:1000001",
        "tgn:1002695",
        "tgn:7012149",
        "tgn:7007565",
        "tgn:7029392"
    ],
    "tgn:id":2587894,
    "tgn:name":"Pleasant Valley Lake",
    "tgn:placetype":[
        "aat:300008680"
    ]
},
  "bbox": [],
  "geometry": {"coordinates":[-74.6167,40.75],"type":"Point"}
}