{
  "id": 2045298,
  "type": "Feature",
  "properties": {
    "tgn:hierarchy":[
        "tgn:2045298",
        "tgn:1000001",
        "tgn:2000925",
        "tgn:7012149",
        "tgn:7007515",
        "tgn:7029392"
    ],
    "tgn:id":2045298,
    "tgn:name":"North Whitefield",
    "tgn:placetype":[
        "aat:300008347"
    ]
},
  "bbox": [],
  "geometry": {"coordinates":[-69.5833,44.2167],"type":"Point"}
}