{
  "id": 2469411,
  "type": "Feature",
  "properties": {
    "tgn:hierarchy":[
        "tgn:2469411",
        "tgn:1000001",
        "tgn:1002267",
        "tgn:7012149",
        "tgn:7007919",
        "tgn:7029392"
    ],
    "tgn:id":2469411,
    "tgn:name":"Longwood Acres",
    "tgn:placetype":[
        "aat:300008347"
    ]
},
  "bbox": [],
  "geometry": {"coordinates":[-77.55,37.45],"type":"Point"}
}