{
  "id": 7317665,
  "type": "Feature",
  "properties": {
    "tgn:hierarchy":[
        "tgn:7317665",
        "tgn:1001699",
        "tgn:1000049",
        "tgn:1000002",
        "tgn:7029392"
    ],
    "tgn:id":7317665,
    "tgn:name":"Comau, Canal",
    "tgn:placetype":[
        "aat:300387026"
    ]
},
  "bbox": [],
  "geometry": {"coordinates":[-72.583333,-42.183333],"type":"Point"}
}