{
  "id": 2500946,
  "type": "Feature",
  "properties": {
    "tgn:hierarchy":[
        "tgn:2500946",
        "tgn:1000001",
        "tgn:7012149",
        "tgn:2001843",
        "tgn:7007825",
        "tgn:7029392"
    ],
    "tgn:id":2500946,
    "tgn:name":"McFarland Hollow",
    "tgn:placetype":[
        "aat:300008761"
    ]
},
  "bbox": [],
  "geometry": {"coordinates":[-84.0167,36.3833],"type":"Point"}
}