{
  "id": 7276545,
  "type": "Feature",
  "properties": {
    "tgn:hierarchy":[
        "tgn:7276545",
        "tgn:1001630",
        "tgn:1000049",
        "tgn:1000002",
        "tgn:7029392"
    ],
    "tgn:id":7276545,
    "tgn:name":"Alcatraz, Islote",
    "tgn:placetype":[
        "aat:300008791"
    ]
},
  "bbox": [],
  "geometry": {"coordinates":[-71.277778,-28.463333],"type":"Point"}
}