{
  "id": 7489643,
  "type": "Feature",
  "properties": {
    "tgn:hierarchy":[
        "tgn:7489643",
        "tgn:1000957",
        "tgn:1000004",
        "tgn:1000141",
        "tgn:7029392"
    ],
    "tgn:id":7489643,
    "tgn:name":"Dasha Wan",
    "tgn:placetype":[
        "aat:300266557"
    ]
},
  "bbox": [],
  "geometry": {"coordinates":[121.75,25.15],"type":"Point"}
}