<<<<<<< HEAD
{
  "id": 7489643,
  "type": "Feature",
  "properties": {
    "tgn:hierarchy":[
        "tgn:7489643",
        "tgn:1000957",
        "tgn:1000004",
        "tgn:1000141",
        "tgn:7029392"
    ],
    "tgn:id":7489643,
    "tgn:name":"Dasha Wan",
    "tgn:placetype":[
        "aat:300266557"
    ]
},
  "bbox": [],
  "geometry": {"coordinates":[121.75,25.15],"type":"Point"}
}
=======
{"geometry":{"type":"Point","coordinates":[121.750000,25.150000]},"type":"Feature","properties":{"hierarchy":["tgn:7489643","tgn:1000957","tgn:1000004","tgn:1000141","tgn:7029392"],"placetype":["aat:300266557"],"id":7489643,"name:xx":"Dasha Wan"}}
>>>>>>> 03f74aca74312dbeaf24d7e61306dd6a786dc3d0
