{
  "id": 2104383,
  "type": "Feature",
  "properties": {
    "tgn:hierarchy":[
        "tgn:2104383",
        "tgn:1000001",
        "tgn:7012149",
        "tgn:2002014",
        "tgn:7007826",
        "tgn:7029392"
    ],
    "tgn:id":2104383,
    "tgn:name":"Funston",
    "tgn:placetype":[
        "aat:300008347",
        "aat:300387210"
    ]
},
  "bbox": [],
  "geometry": {"coordinates":[-99.7833,32.75],"type":"Point"}
}