{
  "id": 7548572,
  "type": "Feature",
  "properties": {
    "tgn:hierarchy":[
        "tgn:7548572",
        "tgn:1001828",
        "tgn:1000004",
        "tgn:7000198",
        "tgn:7029392"
    ],
    "tgn:id":7548572,
    "tgn:name:en":"Chinnekuntapalle",
    "tgn:placetype":[
        "aat:300007783"
    ]
},
  "bbox": [],
  "geometry": {"coordinates":[77.866667,14.45],"type":"Point"}
}