{
  "id": 2779612,
  "type": "Feature",
  "properties": {
    "tgn:hierarchy":[
        "tgn:2779612",
        "tgn:1000001",
        "tgn:7012149",
        "tgn:2001216",
        "tgn:7007523",
        "tgn:7029392"
    ],
    "tgn:id":2779612,
    "tgn:name":"Wolf Pen Hollow",
    "tgn:placetype":[
        "aat:300008761"
    ]
},
  "bbox": [],
  "geometry": {"coordinates":[-94.35,36.5333],"type":"Point"}
}