{
  "id": 2588679,
  "type": "Feature",
  "properties": {
    "tgn:hierarchy":[
        "tgn:2588679",
        "tgn:2002101",
        "tgn:1000001",
        "tgn:7012149",
        "tgn:7007827",
        "tgn:7029392"
    ],
    "tgn:id":2588679,
    "tgn:name":"Plunge Spring",
    "tgn:placetype":[
        "aat:300008697"
    ]
},
  "bbox": [],
  "geometry": {"coordinates":[-112.8667,38.2333],"type":"Point"}
}