{
  "id": 7159591,
  "type": "Feature",
  "properties": {
    "tgn:hierarchy":[
        "tgn:7159591",
        "tgn:7003669",
        "tgn:1000003",
        "tgn:7000084",
        "tgn:7029392"
    ],
    "tgn:id":7159591,
    "tgn:name":"Hoisberg",
    "tgn:placetype":[
        "aat:300000206"
    ]
},
  "bbox": [],
  "geometry": {"coordinates":[13.033333,48.533333],"type":"Point"}
}