{
  "id": 2605690,
  "type": "Feature",
  "properties": {
    "tgn:hierarchy":[
        "tgn:2605690",
        "tgn:1000001",
        "tgn:7012149",
        "tgn:2001447",
        "tgn:7007566",
        "tgn:7029392"
    ],
    "tgn:id":2605690,
    "tgn:name":"Railsplitter Tank Number Two",
    "tgn:placetype":[
        "aat:300006191"
    ]
},
  "bbox": [],
  "geometry": {"coordinates":[-105.4333,32.75],"type":"Point"}
}