{
  "id": 2466716,
  "type": "Feature",
  "properties": {
    "tgn:hierarchy":[
        "tgn:2466716",
        "tgn:1000001",
        "tgn:7012149",
        "tgn:2001855",
        "tgn:7007825",
        "tgn:7029392"
    ],
    "tgn:id":2466716,
    "tgn:name":"Long Branch",
    "tgn:placetype":[
        "aat:300008699"
    ]
},
  "bbox": [],
  "geometry": {"coordinates":[-86.9333,36.2167],"type":"Point"}
}