{
  "id": 2315319,
  "type": "Feature",
  "properties": {
    "tgn:hierarchy":[
        "tgn:2315319",
        "tgn:7013349",
        "tgn:1000001",
        "tgn:7012149",
        "tgn:7007708",
        "tgn:7029392"
    ],
    "tgn:id":2315319,
    "tgn:name":"Elliot Ditch",
    "tgn:placetype":[
        "aat:300006075"
    ]
},
  "bbox": [],
  "geometry": {"coordinates":[-117.7667,44.4833],"type":"Point"}
}