{
  "id": 7523009,
  "type": "Feature",
  "properties": {
    "tgn:hierarchy":[
        "tgn:7523009",
        "tgn:7001242",
        "tgn:1001075",
        "tgn:7016833",
        "tgn:7029392"
    ],
    "tgn:id":7523009,
    "tgn:name:en":"Disy\u0101 al Kan\u0101'is",
    "tgn:placetype":[
        "aat:300008347"
    ]
},
  "bbox": [],
  "geometry": {"coordinates":[30.560556,31.1475],"type":"Point"}
}