{
  "id": 2699739,
  "type": "Feature",
  "properties": {
    "tgn:hierarchy":[
        "tgn:2699739",
        "tgn:1000001",
        "tgn:7012149",
        "tgn:2000230",
        "tgn:7007158",
        "tgn:7029392"
    ],
    "tgn:id":2699739,
    "tgn:name":"Stubb Creek",
    "tgn:placetype":[
        "aat:300008706"
    ]
},
  "bbox": [],
  "geometry": {"coordinates":[-107.6833,39.2167],"type":"Point"}
}