{
  "id": 7305026,
  "type": "Feature",
  "properties": {
    "tgn:hierarchy":[
        "tgn:7305026",
        "tgn:7002836",
        "tgn:7016622",
        "tgn:1000003",
        "tgn:1000095",
        "tgn:7029392"
    ],
    "tgn:id":7305026,
    "tgn:name":"Las Toscas",
    "tgn:placetype":[
        "aat:300008347"
    ]
},
  "bbox": [],
  "geometry": {"coordinates":[-18.016667,27.75],"type":"Point"}
}