{
  "id": 2497059,
  "type": "Feature",
  "properties": {
    "tgn:hierarchy":[
        "tgn:2497059",
        "tgn:1000001",
        "tgn:7012149",
        "tgn:2001497",
        "tgn:7007709",
        "tgn:7029392"
    ],
    "tgn:id":2497059,
    "tgn:name":"Mauney Branch",
    "tgn:placetype":[
        "aat:300008699"
    ]
},
  "bbox": [],
  "geometry": {"coordinates":[-83.8167,35.3167],"type":"Point"}
}