<<<<<<< HEAD
{
  "id": 7058308,
  "type": "Feature",
  "properties": {
    "tgn:hierarchy":[
        "tgn:7058308",
        "tgn:7003168",
        "tgn:1000003",
        "tgn:7009760",
        "tgn:1000080",
        "tgn:7029392"
    ],
    "tgn:id":7058308,
    "tgn:name":"Botteghino",
    "tgn:placetype":[
        "aat:300008347"
    ]
},
  "bbox": [],
  "geometry": {"coordinates":[11.3,43.266667],"type":"Point"}
}
=======
{"geometry":{"type":"Point","coordinates":[11.300000,43.266667]},"type":"Feature","properties":{"hierarchy":["tgn:7058308","tgn:7003168","tgn:1000003","tgn:7009760","tgn:1000080","tgn:7029392"],"placetype":["aat:300008347"],"id":7058308,"name:xx":"Botteghino"}}
>>>>>>> 03f74aca74312dbeaf24d7e61306dd6a786dc3d0
