{
  "id": 2518589,
  "type": "Feature",
  "properties": {
    "tgn:hierarchy":[
        "tgn:2518589",
        "tgn:1000001",
        "tgn:7012149",
        "tgn:2002250",
        "tgn:7007920",
        "tgn:7029392"
    ],
    "tgn:id":2518589,
    "tgn:name":"Mitchell Draw",
    "tgn:placetype":[
        "aat:300008761"
    ]
},
  "bbox": [],
  "geometry": {"coordinates":[-117.6667,47.9333],"type":"Point"}
}