{
  "id": 7027399,
  "type": "Feature",
  "properties": {
    "tgn:hierarchy":[
        "tgn:7027399",
        "tgn:7002445",
        "tgn:1000003",
        "tgn:7008153",
        "tgn:7008591",
        "tgn:7029392"
    ],
    "tgn:id":7027399,
    "tgn:name":"Pineham",
    "tgn:placetype":[
        "aat:300008347",
        "aat:300008372"
    ]
},
  "bbox": [],
  "geometry": {"coordinates":[1.3167,51.1667],"type":"Point"}
}