<<<<<<< HEAD
{
  "id": 7028124,
  "type": "Feature",
  "properties": {
    "tgn:hierarchy":[
        "tgn:7028124",
        "tgn:7002445",
        "tgn:1000003",
        "tgn:7008157",
        "tgn:7008591",
        "tgn:7029392"
    ],
    "tgn:id":7028124,
    "tgn:name:en":"South Thoresby",
    "tgn:placetype":[
        "aat:300008347",
        "aat:300008372"
    ]
},
  "bbox": [],
  "geometry": {"coordinates":[0.1,53.266667],"type":"Point"}
}
=======
{"geometry":{"type":"Point","coordinates":[0.100000,53.266667]},"type":"Feature","properties":{"hierarchy":["tgn:7028124","tgn:7002445","tgn:1000003","tgn:7008157","tgn:7008591","tgn:7029392"],"placetype":["aat:300008347","aat:300008372"],"name:en":"South Thoresby","id":7028124}}
>>>>>>> 03f74aca74312dbeaf24d7e61306dd6a786dc3d0
