{
  "id": 2230774,
  "type": "Feature",
  "properties": {
    "tgn:hierarchy":[
        "tgn:2230774",
        "tgn:1000001",
        "tgn:2000778",
        "tgn:7012149",
        "tgn:7007255",
        "tgn:7029392"
    ],
    "tgn:id":2230774,
    "tgn:name":"Central Creek",
    "tgn:placetype":[
        "aat:300008706"
    ]
},
  "bbox": [],
  "geometry": {"coordinates":[-89.0167,36.8333],"type":"Point"}
}