<<<<<<< HEAD
{
  "id": 7374965,
  "type": "Feature",
  "properties": {
    "tgn:hierarchy":[
        "tgn:7374965",
        "tgn:7005586",
        "tgn:1000001",
        "tgn:7005560",
        "tgn:7029392"
    ],
    "tgn:id":7374965,
    "tgn:name":"La Miseria",
    "tgn:placetype":[
        "aat:300008347"
    ]
},
  "bbox": [],
  "geometry": {"coordinates":[-103.333333,19.5],"type":"Point"}
}
=======
{"geometry":{"type":"Point","coordinates":[-103.333333,19.500000]},"type":"Feature","properties":{"hierarchy":["tgn:7374965","tgn:7005586","tgn:1000001","tgn:7005560","tgn:7029392"],"placetype":["aat:300008347"],"id":7374965,"name:xx":"La Miseria"}}
>>>>>>> 03f74aca74312dbeaf24d7e61306dd6a786dc3d0
