{
  "id": 7187744,
  "type": "Feature",
  "properties": {
    "tgn:hierarchy":[
        "tgn:7187744",
        "tgn:7000096",
        "tgn:1000003",
        "tgn:7000084",
        "tgn:7029392"
    ],
    "tgn:id":7187744,
    "tgn:name":"Eldenburg",
    "tgn:placetype":[
        "aat:300008347"
    ]
},
  "bbox": [],
  "geometry": {"coordinates":[11.433333,53.116667],"type":"Point"}
}