{
  "id": 2210274,
  "type": "Feature",
  "properties": {
    "tgn:hierarchy":[
        "tgn:2210274",
        "tgn:1000001",
        "tgn:7012149",
        "tgn:2000362",
        "tgn:7007248",
        "tgn:7029392"
    ],
    "tgn:id":2210274,
    "tgn:name":"Bush Creek",
    "tgn:placetype":[
        "aat:300008706"
    ]
},
  "bbox": [],
  "geometry": {"coordinates":[-85.1333,33.7167],"type":"Point"}
}