{
  "id": 7322073,
  "type": "Feature",
  "properties": {
    "tgn:hierarchy":[
        "tgn:7322073",
        "tgn:1001623",
        "tgn:1000049",
        "tgn:1000002",
        "tgn:7029392"
    ],
    "tgn:id":7322073,
    "tgn:name":"Atenais, Grupo",
    "tgn:placetype":[
        "aat:300008791"
    ]
},
  "bbox": [],
  "geometry": {"coordinates":[-73.583333,-45.233333],"type":"Point"}
}