{
  "id": 2290456,
  "type": "Feature",
  "properties": {
    "tgn:hierarchy":[
        "tgn:2290456",
        "tgn:1000001",
        "tgn:7012149",
        "tgn:2001699",
        "tgn:7007707",
        "tgn:7029392"
    ],
    "tgn:id":2290456,
    "tgn:name":"Doe Creek",
    "tgn:placetype":[
        "aat:300008706"
    ]
},
  "bbox": [],
  "geometry": {"coordinates":[-99.15,36.55],"type":"Point"}
}