<<<<<<< HEAD
{
  "id": 7055425,
  "type": "Feature",
  "properties": {
    "tgn:hierarchy":[
        "tgn:7055425",
        "tgn:7003162",
        "tgn:1000003",
        "tgn:7009760",
        "tgn:1000080",
        "tgn:7029392"
    ],
    "tgn:id":7055425,
    "tgn:name":"Poggiola",
    "tgn:placetype":[
        "aat:300008347"
    ]
},
  "bbox": [],
  "geometry": {"coordinates":[11.8,43.45],"type":"Point"}
}
=======
{"geometry":{"type":"Point","coordinates":[11.800000,43.450000]},"type":"Feature","properties":{"hierarchy":["tgn:7055425","tgn:7003162","tgn:1000003","tgn:7009760","tgn:1000080","tgn:7029392"],"placetype":["aat:300008347"],"id":7055425,"name:xx":"Poggiola"}}
>>>>>>> 03f74aca74312dbeaf24d7e61306dd6a786dc3d0
