{
  "id": 7546079,
  "type": "Feature",
  "properties": {
    "tgn:hierarchy":[
        "tgn:7546079",
        "tgn:7001819",
        "tgn:1000004",
        "tgn:7000198",
        "tgn:7029392"
    ],
    "tgn:id":7546079,
    "tgn:name:en":"Baisha Pass",
    "tgn:placetype":[
        "aat:300259572"
    ]
},
  "bbox": [],
  "geometry": {"coordinates":[95.334371,28.411291],"type":"Point"}
}