{
  "id": 2217603,
  "type": "Feature",
  "properties": {
    "tgn:hierarchy":[
        "tgn:2217603",
        "tgn:1000001",
        "tgn:7012149",
        "tgn:1002528",
        "tgn:7007710",
        "tgn:7029392"
    ],
    "tgn:id":2217603,
    "tgn:name":"Campbell Hollow",
    "tgn:placetype":[
        "aat:300008761"
    ]
},
  "bbox": [],
  "geometry": {"coordinates":[-77.6833,40.3333],"type":"Point"}
}