{
  "id": 2124460,
  "type": "Feature",
  "properties": {
    "tgn:hierarchy":[
        "tgn:2124460",
        "tgn:1000001",
        "tgn:2002147",
        "tgn:7012149",
        "tgn:7007919",
        "tgn:7029392"
    ],
    "tgn:id":2124460,
    "tgn:name":"Aaron Creek",
    "tgn:placetype":[
        "aat:300008706"
    ]
},
  "bbox": [],
  "geometry": {"coordinates":[-78.0167,36.8333],"type":"Point"}
}