{
  "id": 2484061,
  "type": "Feature",
  "properties": {
    "tgn:hierarchy":[
        "tgn:2484061",
        "tgn:1000001",
        "tgn:2002148",
        "tgn:7012149",
        "tgn:7007919",
        "tgn:7029392"
    ],
    "tgn:id":2484061,
    "tgn:name":"Lauders Branch",
    "tgn:placetype":[
        "aat:300008699"
    ]
},
  "bbox": [],
  "geometry": {"coordinates":[-81.8833,37.2167],"type":"Point"}
}