{
  "id": 1032987,
  "type": "Feature",
  "properties": {
    "tgn:hierarchy":[
        "tgn:1032987",
        "tgn:7002870",
        "tgn:1000003",
        "tgn:1000070",
        "tgn:7029392"
    ],
    "tgn:id":1032987,
    "tgn:name":"Drusenheim",
    "tgn:placetype":[
        "aat:300008347"
    ]
},
  "bbox": [],
  "geometry": {"coordinates":[7.95,48.7667],"type":"Point"}
}