<<<<<<< HEAD
{
  "id": 7488150,
  "type": "Feature",
  "properties": {
    "tgn:hierarchy":[
        "tgn:7488150",
        "tgn:7001004",
        "tgn:1000004",
        "tgn:1000141",
        "tgn:7029392"
    ],
    "tgn:id":7488150,
    "tgn:name":"Luodi Shan",
    "tgn:placetype":[
        "aat:300008777"
    ]
},
  "bbox": [],
  "geometry": {"coordinates":[120.25,22.766667],"type":"Point"}
}
=======
{"geometry":{"type":"Point","coordinates":[120.250000,22.766667]},"type":"Feature","properties":{"hierarchy":["tgn:7488150","tgn:7001004","tgn:1000004","tgn:1000141","tgn:7029392"],"placetype":["aat:300008777"],"id":7488150,"name:xx":"Luodi Shan"}}
>>>>>>> 03f74aca74312dbeaf24d7e61306dd6a786dc3d0
