{
  "id": 2400038,
  "type": "Feature",
  "properties": {
    "tgn:hierarchy":[
        "tgn:2400038",
        "tgn:1000001",
        "tgn:7012149",
        "tgn:2000217",
        "tgn:7007158",
        "tgn:7029392"
    ],
    "tgn:id":2400038,
    "tgn:name":"Horse Creek",
    "tgn:placetype":[
        "aat:300008706"
    ]
},
  "bbox": [],
  "geometry": {"coordinates":[-107.4167,38.8167],"type":"Point"}
}