<<<<<<< HEAD
{
  "id": 2400038,
  "type": "Feature",
  "properties": {
    "tgn:hierarchy":[
        "tgn:2400038",
        "tgn:1000001",
        "tgn:7012149",
        "tgn:2000217",
        "tgn:7007158",
        "tgn:7029392"
    ],
    "tgn:id":2400038,
    "tgn:name":"Horse Creek",
    "tgn:placetype":[
        "aat:300008706"
    ]
},
  "bbox": [],
  "geometry": {"coordinates":[-107.4167,38.8167],"type":"Point"}
}
=======
{"geometry":{"type":"Point","coordinates":[-107.416700,38.816700]},"type":"Feature","properties":{"hierarchy":["tgn:2400038","tgn:1000001","tgn:7012149","tgn:2000217","tgn:7007158","tgn:7029392"],"placetype":["aat:300008706"],"id":2400038,"name:xx":"Horse Creek"}}
>>>>>>> 03f74aca74312dbeaf24d7e61306dd6a786dc3d0
