{
  "id": 2347015,
  "type": "Feature",
  "properties": {
    "tgn:hierarchy":[
        "tgn:2347015",
        "tgn:1000001",
        "tgn:2000299",
        "tgn:7012149",
        "tgn:7007248",
        "tgn:7029392"
    ],
    "tgn:id":2347015,
    "tgn:name":"Gene Tilley Lake",
    "tgn:placetype":[
        "aat:300006191"
    ]
},
  "bbox": [],
  "geometry": {"coordinates":[-84.75,34.1833],"type":"Point"}
}