{
  "id": 2784697,
  "type": "Feature",
  "properties": {
    "tgn:hierarchy":[
        "tgn:2784697",
        "tgn:1000001",
        "tgn:7012149",
        "tgn:2001315",
        "tgn:7007524",
        "tgn:7029392"
    ],
    "tgn:id":2784697,
    "tgn:name":"Yegen Drain",
    "tgn:placetype":[
        "aat:300006075"
    ]
},
  "bbox": [],
  "geometry": {"coordinates":[-108.4833,45.7667],"type":"Point"}
}