{
  "id": 2265873,
  "type": "Feature",
  "properties": {
    "tgn:hierarchy":[
        "tgn:2265873",
        "tgn:1000001",
        "tgn:7012149",
        "tgn:2002373",
        "tgn:7007923",
        "tgn:7029392"
    ],
    "tgn:id":2265873,
    "tgn:name":"Crater Sink",
    "tgn:placetype":[
        "aat:300386845"
    ]
},
  "bbox": [],
  "geometry": {"coordinates":[-108.7333,43.7667],"type":"Point"}
}