{
  "id": 2536248,
  "type": "Feature",
  "properties": {
    "tgn:hierarchy":[
        "tgn:2536248",
        "tgn:1000001",
        "tgn:7012149",
        "tgn:2002119",
        "tgn:7007827",
        "tgn:7029392"
    ],
    "tgn:id":2536248,
    "tgn:name":"Navajo Reservation",
    "tgn:placetype":[
        "aat:300008178"
    ]
},
  "bbox": [],
  "geometry": {"coordinates":[-109.7333,35.75],"type":"Point"}
}