{
  "id": 7564261,
  "type": "Feature",
  "properties": {
    "tgn:hierarchy":[
        "tgn:7564261",
        "tgn:1000004",
        "tgn:7000198",
        "tgn:1001894",
        "tgn:7029392"
    ],
    "tgn:id":7564261,
    "tgn:name:en":"Doh",
    "tgn:placetype":[
        "aat:300008347"
    ]
},
  "bbox": [],
  "geometry": {"coordinates":[79.26368,24.825211],"type":"Point"}
}