{
  "id": 7020236,
  "type": "Feature",
  "properties": {
    "tgn:hierarchy":[
        "tgn:7020236",
        "tgn:1000001",
        "tgn:7012149",
        "tgn:7013940",
        "tgn:7007709",
        "tgn:7029392"
    ],
    "tgn:id":7020236,
    "tgn:name":"Sagamore, Lake",
    "tgn:placetype":[
        "aat:300006191"
    ]
},
  "bbox": [],
  "geometry": {"coordinates":[-78.1833,35.9333],"type":"Point"}
}