<<<<<<< HEAD
{
  "id": 7020621,
  "type": "Feature",
  "properties": {
    "tgn:hierarchy":[
        "tgn:7020621",
        "tgn:1000001",
        "tgn:7012149",
        "tgn:2001296",
        "tgn:7007524",
        "tgn:7029392"
    ],
    "tgn:id":7020621,
    "tgn:name":"A Canal",
    "tgn:placetype":[
        "aat:300006075"
    ]
},
  "bbox": [],
  "geometry": {"coordinates":[-112.2833,48.3333],"type":"Point"}
}
=======
{"geometry":{"type":"Point","coordinates":[-112.283300,48.333300]},"type":"Feature","properties":{"hierarchy":["tgn:7020621","tgn:1000001","tgn:7012149","tgn:2001296","tgn:7007524","tgn:7029392"],"placetype":["aat:300006075"],"id":7020621,"name:xx":"A Canal"}}
>>>>>>> 03f74aca74312dbeaf24d7e61306dd6a786dc3d0
