<<<<<<< HEAD
{
  "id": 7361712,
  "type": "Feature",
  "properties": {
    "tgn:hierarchy":[
        "tgn:7361712",
        "tgn:7005581",
        "tgn:1000001",
        "tgn:7005560",
        "tgn:7029392"
    ],
    "tgn:id":7361712,
    "tgn:name":"Rancho El Campamento",
    "tgn:placetype":[
        "aat:300000241"
    ]
},
  "bbox": [],
  "geometry": {"coordinates":[-105.683333,27.516667],"type":"Point"}
}
=======
{"geometry":{"type":"Point","coordinates":[-105.683333,27.516667]},"type":"Feature","properties":{"hierarchy":["tgn:7361712","tgn:7005581","tgn:1000001","tgn:7005560","tgn:7029392"],"placetype":["aat:300000241"],"id":7361712,"name:xx":"Rancho El Campamento"}}
>>>>>>> 03f74aca74312dbeaf24d7e61306dd6a786dc3d0
