{
  "id": 7307335,
  "type": "Feature",
  "properties": {
    "tgn:hierarchy":[
        "tgn:7307335",
        "tgn:7002758",
        "tgn:1001316",
        "tgn:1000003",
        "tgn:1000095",
        "tgn:7029392"
    ],
    "tgn:id":7307335,
    "tgn:name":"Marroqu\u00edn Encina Hermosa",
    "tgn:placetype":[
        "aat:300008347"
    ]
},
  "bbox": [],
  "geometry": {"coordinates":[-3.833333,37.55],"type":"Point"}
}