{
  "id": 1016164,
  "type": "Feature",
  "properties": {
    "tgn:hierarchy":[
        "tgn:1016164",
        "tgn:7005685",
        "tgn:1000001",
        "tgn:7005805",
        "tgn:7029392"
    ],
    "tgn:id":1016164,
    "tgn:name":"Whitewood",
    "tgn:placetype":[
        "aat:300008347"
    ]
},
  "bbox": [],
  "geometry": {"coordinates":[-102.2667,50.3167],"type":"Point"}
}