{
  "id": 7576775,
  "type": "Feature",
  "properties": {
    "tgn:hierarchy":[
        "tgn:7576775",
        "tgn:1000004",
        "tgn:7000198",
        "tgn:7000799",
        "tgn:7029392"
    ],
    "tgn:id":7576775,
    "tgn:name:en":"Khard\u016bng",
    "tgn:placetype":[
        "aat:300008347"
    ]
},
  "bbox": [],
  "geometry": {"coordinates":[77.669429,34.400412],"type":"Point"}
}