{
  "id": 7486689,
  "type": "Feature",
  "properties": {
    "tgn:hierarchy":[
        "tgn:7486689",
        "tgn:1000004",
        "tgn:7490934",
        "tgn:1000141",
        "tgn:7029392"
    ],
    "tgn:id":7486689,
    "tgn:name":"Bajia",
    "tgn:placetype":[
        "aat:300008347"
    ]
},
  "bbox": [],
  "geometry": {"coordinates":[120.296944,22.975833],"type":"Point"}
}