{
  "id": 7540513,
  "type": "Feature",
  "properties": {
    "tgn:hierarchy":[
        "tgn:7540513",
        "tgn:7001242",
        "tgn:7016833",
        "tgn:1001092",
        "tgn:7029392"
    ],
    "tgn:id":7540513,
    "tgn:name:en":"Minsh\u0101t Dhi'\u0101b",
    "tgn:placetype":[
        "aat:300008347"
    ]
},
  "bbox": [],
  "geometry": {"coordinates":[31.271092,30.415963],"type":"Point"}
}