{
  "id": 2180960,
  "type": "Feature",
  "properties": {
    "tgn:hierarchy":[
        "tgn:2180960",
        "tgn:1000001",
        "tgn:7012149",
        "tgn:2002111",
        "tgn:7007827",
        "tgn:7029392"
    ],
    "tgn:id":2180960,
    "tgn:name":"Blowout Pit",
    "tgn:placetype":[
        "aat:300386845"
    ]
},
  "bbox": [],
  "geometry": {"coordinates":[-113.3667,37.6167],"type":"Point"}
}