{
  "id": 7198166,
  "type": "Feature",
  "properties": {
    "tgn:hierarchy":[
        "tgn:7198166",
        "tgn:7003669",
        "tgn:1000003",
        "tgn:7000084",
        "tgn:7029392"
    ],
    "tgn:id":7198166,
    "tgn:name":"Ehemoosen",
    "tgn:placetype":[
        "aat:300000206"
    ]
},
  "bbox": [],
  "geometry": {"coordinates":[12.866667,47.916667],"type":"Point"}
}