{
  "id": 7412733,
  "type": "Feature",
  "properties": {
    "tgn:hierarchy":[
        "tgn:7412733",
        "tgn:7005587",
        "tgn:1000001",
        "tgn:7005560",
        "tgn:7029392"
    ],
    "tgn:id":7412733,
    "tgn:name:es":"Las Fuentes",
    "tgn:placetype":[
        "aat:300008347"
    ]
},
  "bbox": [],
  "geometry": {"coordinates":[-99.091667,21.108333],"type":"Point"}
}