{
  "id": 2441500,
  "type": "Feature",
  "properties": {
    "tgn:hierarchy":[
        "tgn:2441500",
        "tgn:1000001",
        "tgn:2001704",
        "tgn:7012149",
        "tgn:7007708",
        "tgn:7029392"
    ],
    "tgn:id":2441500,
    "tgn:name":"Koch Creek",
    "tgn:placetype":[
        "aat:300008706"
    ]
},
  "bbox": [],
  "geometry": {"coordinates":[-124.4167,42.8167],"type":"Point"}
}