<<<<<<< HEAD
{
  "id": 7364754,
  "type": "Feature",
  "properties": {
    "tgn:hierarchy":[
        "tgn:7364754",
        "tgn:7005581",
        "tgn:1000001",
        "tgn:7005560",
        "tgn:7029392"
    ],
    "tgn:id":7364754,
    "tgn:name":"Flor de Marzo Chica, Sierra",
    "tgn:placetype":[
        "aat:300008795"
    ]
},
  "bbox": [],
  "geometry": {"coordinates":[-107.783333,31.083333],"type":"Point"}
}
=======
{"geometry":{"type":"Point","coordinates":[-107.783333,31.083333]},"type":"Feature","properties":{"hierarchy":["tgn:7364754","tgn:7005581","tgn:1000001","tgn:7005560","tgn:7029392"],"placetype":["aat:300008795"],"id":7364754,"name:xx":"Flor de Marzo Chica, Sierra"}}
>>>>>>> 03f74aca74312dbeaf24d7e61306dd6a786dc3d0
