{
  "id": 7364754,
  "type": "Feature",
  "properties": {
    "tgn:hierarchy":[
        "tgn:7364754",
        "tgn:7005581",
        "tgn:1000001",
        "tgn:7005560",
        "tgn:7029392"
    ],
    "tgn:id":7364754,
    "tgn:name":"Flor de Marzo Chica, Sierra",
    "tgn:placetype":[
        "aat:300008795"
    ]
},
  "bbox": [],
  "geometry": {"coordinates":[-107.783333,31.083333],"type":"Point"}
}