{
  "id": 2717025,
  "type": "Feature",
  "properties": {
    "tgn:hierarchy":[
        "tgn:2717025",
        "tgn:1000001",
        "tgn:1002601",
        "tgn:7012149",
        "tgn:7007159",
        "tgn:7029392"
    ],
    "tgn:id":2717025,
    "tgn:name":"Third Bay",
    "tgn:placetype":[
        "aat:300132316"
    ]
},
  "bbox": [],
  "geometry": {"coordinates":[-73.0833,41.8833],"type":"Point"}
}