<<<<<<< HEAD
{
  "id": 7112608,
  "type": "Feature",
  "properties": {
    "tgn:hierarchy":[
        "tgn:7112608",
        "tgn:1000003",
        "tgn:7000094",
        "tgn:7000084",
        "tgn:7029392"
    ],
    "tgn:id":7112608,
    "tgn:name":"R\u00fcgischer Bodden",
    "tgn:placetype":[
        "aat:300132316"
    ]
},
  "bbox": [],
  "geometry": {"coordinates":[13.533333,54.3],"type":"Point"}
}
=======
{"geometry":{"type":"Point","coordinates":[13.533333,54.300000]},"type":"Feature","properties":{"hierarchy":["tgn:7112608","tgn:1000003","tgn:7000094","tgn:7000084","tgn:7029392"],"placetype":["aat:300132316"],"id":7112608,"name:xx":"R\u00fcgischer Bodden"}}
>>>>>>> 03f74aca74312dbeaf24d7e61306dd6a786dc3d0
