{
  "id": 1067451,
  "type": "Feature",
  "properties": {
    "tgn:hierarchy":[
        "tgn:1067451",
        "tgn:1000004",
        "tgn:1000960",
        "tgn:1000111",
        "tgn:7029392"
    ],
    "tgn:id":1067451,
    "tgn:name":"Dalubeikou",
    "tgn:placetype":[
        "aat:300008347"
    ]
},
  "bbox": [],
  "geometry": {"coordinates":[117.2333,38.95],"type":"Point"}
}