<<<<<<< HEAD
{
  "id": 2760064,
  "type": "Feature",
  "properties": {
    "tgn:hierarchy":[
        "tgn:2760064",
        "tgn:1000001",
        "tgn:7012149",
        "tgn:2001718",
        "tgn:7007708",
        "tgn:7029392"
    ],
    "tgn:id":2760064,
    "tgn:name":"West Fork Oregon Canyon Creek",
    "tgn:placetype":[
        "aat:300008706"
    ]
},
  "bbox": [],
  "geometry": {"coordinates":[-117.9833,42.1333],"type":"Point"}
}
=======
{"geometry":{"type":"Point","coordinates":[-117.983300,42.133300]},"type":"Feature","properties":{"hierarchy":["tgn:2760064","tgn:1000001","tgn:7012149","tgn:2001718","tgn:7007708","tgn:7029392"],"placetype":["aat:300008706"],"id":2760064,"name:xx":"West Fork Oregon Canyon Creek"}}
>>>>>>> 03f74aca74312dbeaf24d7e61306dd6a786dc3d0
