{
  "id": 2038936,
  "type": "Feature",
  "properties": {
    "tgn:hierarchy":[
        "tgn:2038936",
        "tgn:1000001",
        "tgn:7012149",
        "tgn:2000784",
        "tgn:7007255",
        "tgn:7029392"
    ],
    "tgn:id":2038936,
    "tgn:name":"Frances",
    "tgn:placetype":[
        "aat:300008347"
    ]
},
  "bbox": [],
  "geometry": {"coordinates":[-88.1333,37.2167],"type":"Point"}
}