{
  "id": 2561894,
  "type": "Feature",
  "properties": {
    "tgn:hierarchy":[
        "tgn:2561894",
        "tgn:1000001",
        "tgn:7012149",
        "tgn:2001504",
        "tgn:7007709",
        "tgn:7029392"
    ],
    "tgn:id":2561894,
    "tgn:name":"Ottanola",
    "tgn:placetype":[
        "aat:300008347"
    ]
},
  "bbox": [],
  "geometry": {"coordinates":[-82.2667,35.3833],"type":"Point"}
}