{
  "id": 7469549,
  "type": "Feature",
  "properties": {
    "tgn:hierarchy":[
        "tgn:7469549",
        "tgn:1000004",
        "tgn:7471332",
        "tgn:1000141",
        "tgn:7029392"
    ],
    "tgn:id":7469549,
    "tgn:name":"Zhongbeishi",
    "tgn:placetype":[
        "aat:300008347"
    ]
},
  "bbox": [],
  "geometry": {"coordinates":[121.054444,24.897222],"type":"Point"}
}