{
  "id": 2386874,
  "type": "Feature",
  "properties": {
    "tgn:hierarchy":[
        "tgn:2386874",
        "tgn:1000001",
        "tgn:7012149",
        "tgn:1002494",
        "tgn:7007710",
        "tgn:7029392"
    ],
    "tgn:id":2386874,
    "tgn:name":"Herod Run",
    "tgn:placetype":[
        "aat:300008699"
    ]
},
  "bbox": [],
  "geometry": {"coordinates":[-77.8833,40.6333],"type":"Point"}
}