<<<<<<< HEAD
{
  "id": 2333598,
  "type": "Feature",
  "properties": {
    "tgn:hierarchy":[
        "tgn:2333598",
        "tgn:7006450",
        "tgn:1000001",
        "tgn:7012149",
        "tgn:2000082",
        "tgn:7029392"
    ],
    "tgn:id":2333598,
    "tgn:name":"Fontaine Island",
    "tgn:placetype":[
        "aat:300008791"
    ]
},
  "bbox": [],
  "geometry": {"coordinates":[-133.4667,56.15],"type":"Point"}
}
=======
{"geometry":{"type":"Point","coordinates":[-133.466700,56.150000]},"type":"Feature","properties":{"hierarchy":["tgn:2333598","tgn:7006450","tgn:1000001","tgn:7012149","tgn:2000082","tgn:7029392"],"placetype":["aat:300008791"],"id":2333598,"name:xx":"Fontaine Island"}}
>>>>>>> 03f74aca74312dbeaf24d7e61306dd6a786dc3d0
