{
  "id": 2333598,
  "type": "Feature",
  "properties": {
    "tgn:hierarchy":[
        "tgn:2333598",
        "tgn:7006450",
        "tgn:1000001",
        "tgn:7012149",
        "tgn:2000082",
        "tgn:7029392"
    ],
    "tgn:id":2333598,
    "tgn:name":"Fontaine Island",
    "tgn:placetype":[
        "aat:300008791"
    ]
},
  "bbox": [],
  "geometry": {"coordinates":[-133.4667,56.15],"type":"Point"}
}