<<<<<<< HEAD
{
  "id": 7177460,
  "type": "Feature",
  "properties": {
    "tgn:hierarchy":[
        "tgn:7177460",
        "tgn:1000003",
        "tgn:7003677",
        "tgn:7000084",
        "tgn:7029392"
    ],
    "tgn:id":7177460,
    "tgn:name":"G\u00fc\u00f6rtpott",
    "tgn:placetype":[
        "aat:300008699"
    ]
},
  "bbox": [],
  "geometry": {"coordinates":[7.6,51.95],"type":"Point"}
}
=======
{"geometry":{"type":"Point","coordinates":[7.600000,51.950000]},"type":"Feature","properties":{"hierarchy":["tgn:7177460","tgn:1000003","tgn:7003677","tgn:7000084","tgn:7029392"],"placetype":["aat:300008699"],"id":7177460,"name:xx":"G\u00fc\u00f6rtpott"}}
>>>>>>> 03f74aca74312dbeaf24d7e61306dd6a786dc3d0
