{
  "id": 2543694,
  "type": "Feature",
  "properties": {
    "tgn:hierarchy":[
        "tgn:2543694",
        "tgn:1000001",
        "tgn:2001410",
        "tgn:7012149",
        "tgn:7007526",
        "tgn:7029392"
    ],
    "tgn:id":2543694,
    "tgn:name":"North Basin Light Cove",
    "tgn:placetype":[
        "aat:300132316"
    ]
},
  "bbox": [],
  "geometry": {"coordinates":[-114.6667,35.4667],"type":"Point"}
}