{
  "id": 2446629,
  "type": "Feature",
  "properties": {
    "tgn:hierarchy":[
        "tgn:2446629",
        "tgn:1000001",
        "tgn:7012149",
        "tgn:2001420",
        "tgn:7007526",
        "tgn:7029392"
    ],
    "tgn:id":2446629,
    "tgn:name":"Lewis Springs",
    "tgn:placetype":[
        "aat:300008697"
    ]
},
  "bbox": [],
  "geometry": {"coordinates":[-114.65,39.7833],"type":"Point"}
}