{
  "id": 7138225,
  "type": "Feature",
  "properties": {
    "tgn:hierarchy":[
        "tgn:7138225",
        "tgn:1000003",
        "tgn:7003677",
        "tgn:7000084",
        "tgn:7029392"
    ],
    "tgn:id":7138225,
    "tgn:name":"Lendersdorf",
    "tgn:placetype":[
        "aat:300008347"
    ]
},
  "bbox": [],
  "geometry": {"coordinates":[6.483333,50.766667],"type":"Point"}
}