{
  "id": 7166827,
  "type": "Feature",
  "properties": {
    "tgn:hierarchy":[
        "tgn:7166827",
        "tgn:1000003",
        "tgn:7003677",
        "tgn:7000084",
        "tgn:7029392"
    ],
    "tgn:id":7166827,
    "tgn:name":"Heide",
    "tgn:placetype":[
        "aat:300000206"
    ]
},
  "bbox": [],
  "geometry": {"coordinates":[7.716667,51.483333],"type":"Point"}
}