{
  "id": 2239050,
  "type": "Feature",
  "properties": {
    "tgn:hierarchy":[
        "tgn:2239050",
        "tgn:1000001",
        "tgn:7012149",
        "tgn:2001297",
        "tgn:7007524",
        "tgn:7029392"
    ],
    "tgn:id":2239050,
    "tgn:name":"Chromo Creek",
    "tgn:placetype":[
        "aat:300008706"
    ]
},
  "bbox": [],
  "geometry": {"coordinates":[-106.2167,45.4167],"type":"Point"}
}