{
  "id": 2315625,
  "type": "Feature",
  "properties": {
    "tgn:hierarchy":[
        "tgn:2315625",
        "tgn:1000001",
        "tgn:2001260",
        "tgn:7012149",
        "tgn:7007524",
        "tgn:7029392"
    ],
    "tgn:id":2315625,
    "tgn:name":"Ellis Peak",
    "tgn:placetype":[
        "aat:300008798"
    ]
},
  "bbox": [],
  "geometry": {"coordinates":[-112.9833,44.7333],"type":"Point"}
}