{
  "id": 2629962,
  "type": "Feature",
  "properties": {
    "tgn:hierarchy":[
        "tgn:2629962",
        "tgn:1000001",
        "tgn:7012149",
        "tgn:7007157",
        "tgn:7014005",
        "tgn:7029392"
    ],
    "tgn:id":2629962,
    "tgn:name":"Ross Valley",
    "tgn:placetype":[
        "aat:300008761"
    ]
},
  "bbox": [],
  "geometry": {"coordinates":[-122.5667,37.9833],"type":"Point"}
}