{
  "id": 7041726,
  "type": "Feature",
  "properties": {
    "tgn:hierarchy":[
        "tgn:7041726",
        "tgn:7003154",
        "tgn:1000003",
        "tgn:7003120",
        "tgn:1000080",
        "tgn:7029392"
    ],
    "tgn:id":7041726,
    "tgn:name":"San Gillio",
    "tgn:placetype":[
        "aat:300008347"
    ]
},
  "bbox": [],
  "geometry": {"coordinates":[7.533333,45.133333],"type":"Point"}
}