{
  "id": 2291376,
  "type": "Feature",
  "properties": {
    "tgn:hierarchy":[
        "tgn:2291376",
        "tgn:7006450",
        "tgn:1000001",
        "tgn:7012149",
        "tgn:2000089",
        "tgn:7029392"
    ],
    "tgn:id":2291376,
    "tgn:name":"Doherty Creek",
    "tgn:placetype":[
        "aat:300008706"
    ]
},
  "bbox": [],
  "geometry": {"coordinates":[-157.4333,62.3667],"type":"Point"}
}