{
  "id": 2080307,
  "type": "Feature",
  "properties": {
    "tgn:hierarchy":[
        "tgn:2080307",
        "tgn:1000001",
        "tgn:7012149",
        "tgn:1002776",
        "tgn:7007706",
        "tgn:7029392"
    ],
    "tgn:id":2080307,
    "tgn:name":"Latty",
    "tgn:placetype":[
        "aat:300008347"
    ]
},
  "bbox": [],
  "geometry": {"coordinates":[-84.5833,41.0833],"type":"Point"}
}