{
  "id": 4008511,
  "type": "Feature",
  "properties": {
    "tgn:hierarchy":[
        "tgn:4008511",
        "tgn:7002839",
        "tgn:7001158",
        "tgn:1000003",
        "tgn:1000095",
        "tgn:7029392"
    ],
    "tgn:id":4008511,
    "tgn:name":"Pedraza",
    "tgn:placetype":[
        "aat:300008347"
    ]
},
  "bbox": [],
  "geometry": {"coordinates":[-7.85,42.816667],"type":"Point"}
}