{
  "id": 2441238,
  "type": "Feature",
  "properties": {
    "tgn:hierarchy":[
        "tgn:2441238",
        "tgn:7006450",
        "tgn:1000001",
        "tgn:7012149",
        "tgn:2000086",
        "tgn:7029392"
    ],
    "tgn:id":2441238,
    "tgn:name":"Knowles Head",
    "tgn:placetype":[
        "aat:300008850"
    ]
},
  "bbox": [],
  "geometry": {"coordinates":[-146.6167,60.6667],"type":"Point"}
}