{
  "id": 7476951,
  "type": "Feature",
  "properties": {
    "tgn:hierarchy":[
        "tgn:7476951",
        "tgn:1000004",
        "tgn:1000454",
        "tgn:1000141",
        "tgn:7029392"
    ],
    "tgn:id":7476951,
    "tgn:name":"Sanbanqiao",
    "tgn:placetype":[
        "aat:300008347"
    ]
},
  "bbox": [],
  "geometry": {"coordinates":[121.897919,25.05615],"type":"Point"}
}