{
  "id": 2458401,
  "type": "Feature",
  "properties": {
    "tgn:hierarchy":[
        "tgn:2458401",
        "tgn:1000001",
        "tgn:7012149",
        "tgn:1002613",
        "tgn:7007710",
        "tgn:7029392"
    ],
    "tgn:id":2458401,
    "tgn:name":"Little Muncy Creek",
    "tgn:placetype":[
        "aat:300008706"
    ]
},
  "bbox": [],
  "geometry": {"coordinates":[-76.4667,41.2667],"type":"Point"}
}