{
  "id": 2569481,
  "type": "Feature",
  "properties": {
    "tgn:hierarchy":[
        "tgn:2569481",
        "tgn:1000001",
        "tgn:7012149",
        "tgn:2002111",
        "tgn:7007827",
        "tgn:7029392"
    ],
    "tgn:id":2569481,
    "tgn:name":"Parowan Canyon",
    "tgn:placetype":[
        "aat:300008761"
    ]
},
  "bbox": [],
  "geometry": {"coordinates":[-112.9667,38.0667],"type":"Point"}
}