{
  "id": 2488023,
  "type": "Feature",
  "properties": {
    "tgn:hierarchy":[
        "tgn:2488023",
        "tgn:1000001",
        "tgn:7012149",
        "tgn:2001294",
        "tgn:7007524",
        "tgn:7029392"
    ],
    "tgn:id":2488023,
    "tgn:name":"Maginnis Creek",
    "tgn:placetype":[
        "aat:300008706"
    ]
},
  "bbox": [],
  "geometry": {"coordinates":[-108.15,46.8667],"type":"Point"}
}