{
  "id": 7256826,
  "type": "Feature",
  "properties": {
    "tgn:hierarchy":[
        "tgn:7256826",
        "tgn:7004783",
        "tgn:7593114",
        "tgn:7593112",
        "tgn:1000001",
        "tgn:7029392"
    ],
    "tgn:id":7256826,
    "tgn:name:nl":"Crispeen",
    "tgn:placetype":[
        "aat:300387200"
    ]
},
  "bbox": [],
  "geometry": {"coordinates":[-63.233333,17.616667],"type":"Point"}
}