{
  "id": 7126341,
  "type": "Feature",
  "properties": {
    "tgn:hierarchy":[
        "tgn:7126341",
        "tgn:7003692",
        "tgn:1000003",
        "tgn:7000084",
        "tgn:7029392"
    ],
    "tgn:id":7126341,
    "tgn:name":"Oberh\u00f6fen",
    "tgn:placetype":[
        "aat:300008347"
    ]
},
  "bbox": [],
  "geometry": {"coordinates":[9.539167,49.161667],"type":"Point"}
}