<<<<<<< HEAD
{
  "id": 7021911,
  "type": "Feature",
  "properties": {
    "tgn:hierarchy":[
        "tgn:7021911",
        "tgn:1002132",
        "tgn:1000001",
        "tgn:7012149",
        "tgn:7007919",
        "tgn:7029392"
    ],
    "tgn:id":7021911,
    "tgn:name":"Finneys Creek",
    "tgn:placetype":[
        "aat:300008706"
    ]
},
  "bbox": [],
  "geometry": {"coordinates":[-75.7667,37.7],"type":"Point"}
}
=======
{"geometry":{"type":"Point","coordinates":[-75.766700,37.700000]},"type":"Feature","properties":{"hierarchy":["tgn:7021911","tgn:1002132","tgn:1000001","tgn:7012149","tgn:7007919","tgn:7029392"],"placetype":["aat:300008706"],"id":7021911,"name:xx":"Finneys Creek"}}
>>>>>>> 03f74aca74312dbeaf24d7e61306dd6a786dc3d0
