<<<<<<< HEAD
{
  "id": 7021778,
  "type": "Feature",
  "properties": {
    "tgn:hierarchy":[
        "tgn:7021778",
        "tgn:1000001",
        "tgn:7012149",
        "tgn:2001761",
        "tgn:7007712",
        "tgn:7029392"
    ],
    "tgn:id":7021778,
    "tgn:name":"Pine Mountain",
    "tgn:placetype":[
        "aat:300008798"
    ]
},
  "bbox": [],
  "geometry": {"coordinates":[-83.2833,34.6833],"type":"Point"}
}
=======
{"geometry":{"type":"Point","coordinates":[-83.283300,34.683300]},"type":"Feature","properties":{"hierarchy":["tgn:7021778","tgn:1000001","tgn:7012149","tgn:2001761","tgn:7007712","tgn:7029392"],"placetype":["aat:300008798"],"id":7021778,"name:xx":"Pine Mountain"}}
>>>>>>> 03f74aca74312dbeaf24d7e61306dd6a786dc3d0
