{
  "id": 2769042,
  "type": "Feature",
  "properties": {
    "tgn:hierarchy":[
        "tgn:2769042",
        "tgn:1000001",
        "tgn:7014423",
        "tgn:7012149",
        "tgn:7007517",
        "tgn:7029392"
    ],
    "tgn:id":2769042,
    "tgn:name":"Whittemore Point",
    "tgn:placetype":[
        "aat:300008850"
    ]
},
  "bbox": [],
  "geometry": {"coordinates":[-70.6167,41.7333],"type":"Point"}
}