<<<<<<< HEAD
{
  "id": 2769042,
  "type": "Feature",
  "properties": {
    "tgn:hierarchy":[
        "tgn:2769042",
        "tgn:1000001",
        "tgn:7014423",
        "tgn:7012149",
        "tgn:7007517",
        "tgn:7029392"
    ],
    "tgn:id":2769042,
    "tgn:name":"Whittemore Point",
    "tgn:placetype":[
        "aat:300008850"
    ]
},
  "bbox": [],
  "geometry": {"coordinates":[-70.6167,41.7333],"type":"Point"}
}
=======
{"geometry":{"type":"Point","coordinates":[-70.616700,41.733300]},"type":"Feature","properties":{"hierarchy":["tgn:2769042","tgn:1000001","tgn:7014423","tgn:7012149","tgn:7007517","tgn:7029392"],"placetype":["aat:300008850"],"id":2769042,"name:xx":"Whittemore Point"}}
>>>>>>> 03f74aca74312dbeaf24d7e61306dd6a786dc3d0
