{
  "id": 2482317,
  "type": "Feature",
  "properties": {
    "tgn:hierarchy":[
        "tgn:2482317",
        "tgn:2001726",
        "tgn:1000001",
        "tgn:7012149",
        "tgn:7007712",
        "tgn:7029392"
    ],
    "tgn:id":2482317,
    "tgn:name":"Langley Pond",
    "tgn:placetype":[
        "aat:300006191"
    ]
},
  "bbox": [],
  "geometry": {"coordinates":[-81.8333,33.5167],"type":"Point"}
}