{
  "id": 2475223,
  "type": "Feature",
  "properties": {
    "tgn:hierarchy":[
        "tgn:2475223",
        "tgn:1000001",
        "tgn:7012149",
        "tgn:2000893",
        "tgn:7007256",
        "tgn:7029392"
    ],
    "tgn:id":2475223,
    "tgn:name":"Loyd",
    "tgn:placetype":[
        "aat:300008347"
    ]
},
  "bbox": [],
  "geometry": {"coordinates":[-92.35,31.0333],"type":"Point"}
}