{
  "id": 1015306,
  "type": "Feature",
  "properties": {
    "tgn:hierarchy":[
        "tgn:1015306",
        "tgn:7005685",
        "tgn:1000001",
        "tgn:7005804",
        "tgn:7029392"
    ],
    "tgn:id":1015306,
    "tgn:name":"Bedford",
    "tgn:placetype":[
        "aat:300008347"
    ]
},
  "bbox": [],
  "geometry": {"coordinates":[-72.9833,45.1167],"type":"Point"}
}