{
  "id": 2020233,
  "type": "Feature",
  "properties": {
    "tgn:hierarchy":[
        "tgn:2020233",
        "tgn:2000258",
        "tgn:1000001",
        "tgn:7012149",
        "tgn:7007240",
        "tgn:7029392"
    ],
    "tgn:id":2020233,
    "tgn:name":"Lynn Haven",
    "tgn:placetype":[
        "aat:300008347"
    ]
},
  "bbox": [],
  "geometry": {"coordinates":[-85.6333,30.2333],"type":"Point"}
}