{
  "id": 7462778,
  "type": "Feature",
  "properties": {
    "tgn:hierarchy":[
        "tgn:7462778",
        "tgn:7002444",
        "tgn:1000003",
        "tgn:7008094",
        "tgn:7008591",
        "tgn:7029392"
    ],
    "tgn:id":7462778,
    "tgn:name:en":"Lionel",
    "tgn:placetype":[
        "aat:300008347"
    ]
},
  "bbox": [],
  "geometry": {"coordinates":[-6.25,58.466667],"type":"Point"}
}