{
  "id": 7587616,
  "type": "Feature",
  "properties": {
    "tgn:hierarchy":[
        "tgn:7587616",
        "tgn:1000004",
        "tgn:7000198",
        "tgn:7000799",
        "tgn:7029392"
    ],
    "tgn:id":7587616,
    "tgn:name:en":"Gund-i-Chand\u0101l",
    "tgn:placetype":[
        "aat:300008347"
    ]
},
  "bbox": [],
  "geometry": {"coordinates":[74.832252,34.043388],"type":"Point"}
}