{
  "id": 2306938,
  "type": "Feature",
  "properties": {
    "tgn:hierarchy":[
        "tgn:2306938",
        "tgn:1000001",
        "tgn:1002279",
        "tgn:7012149",
        "tgn:7007706",
        "tgn:7029392"
    ],
    "tgn:id":2306938,
    "tgn:name":"East Fork Lake",
    "tgn:placetype":[
        "aat:300006191"
    ]
},
  "bbox": [],
  "geometry": {"coordinates":[-84.15,39.0167],"type":"Point"}
}