{
  "id": 7428038,
  "type": "Feature",
  "properties": {
    "tgn:hierarchy":[
        "tgn:7428038",
        "tgn:1000001",
        "tgn:7005601",
        "tgn:7005560",
        "tgn:7029392"
    ],
    "tgn:id":7428038,
    "tgn:name":"Las Aguajas, Arroyo",
    "tgn:placetype":[
        "aat:300266554",
        "aat:300008699"
    ]
},
  "bbox": [],
  "geometry": {"coordinates":[-103.333333,23.833333],"type":"Point"}
}