{
  "id": 7551488,
  "type": "Feature",
  "properties": {
    "tgn:hierarchy":[
        "tgn:7551488",
        "tgn:1000004",
        "tgn:7000198",
        "tgn:7001797",
        "tgn:7029392"
    ],
    "tgn:id":7551488,
    "tgn:name:en":"Chey\u016br",
    "tgn:placetype":[
        "aat:300008347"
    ]
},
  "bbox": [],
  "geometry": {"coordinates":[80.004722,12.348056],"type":"Point"}
}