{
  "id": 2117151,
  "type": "Feature",
  "properties": {
    "tgn:hierarchy":[
        "tgn:2117151",
        "tgn:1000001",
        "tgn:7012149",
        "tgn:2002252",
        "tgn:7007920",
        "tgn:7029392"
    ],
    "tgn:id":2117151,
    "tgn:name":"Winona",
    "tgn:placetype":[
        "aat:300008347"
    ]
},
  "bbox": [],
  "geometry": {"coordinates":[-117.7833,46.9333],"type":"Point"}
}