{
  "id": 2573066,
  "type": "Feature",
  "properties": {
    "tgn:hierarchy":[
        "tgn:2573066",
        "tgn:1000001",
        "tgn:7012149",
        "tgn:2002039",
        "tgn:7007826",
        "tgn:7029392"
    ],
    "tgn:id":2573066,
    "tgn:name":"Pearson",
    "tgn:placetype":[
        "aat:300008347"
    ]
},
  "bbox": [],
  "geometry": {"coordinates":[-98.8667,29.2667],"type":"Point"}
}