{
  "id": 7276188,
  "type": "Feature",
  "properties": {
    "tgn:hierarchy":[
        "tgn:7276188",
        "tgn:1001695",
        "tgn:1000049",
        "tgn:1000002",
        "tgn:7029392"
    ],
    "tgn:id":7276188,
    "tgn:name":"Tinguiririca, Volc\u00e1n",
    "tgn:placetype":[
        "aat:300386986"
    ]
},
  "bbox": [],
  "geometry": {"coordinates":[-70.35,-34.816667],"type":"Point"}
}