{
  "id": 7594270,
  "type": "Feature",
  "properties": {
    "tgn:hierarchy":[
        "tgn:7594270",
        "tgn:1000003",
        "tgn:7003141",
        "tgn:7003236",
        "tgn:1000080",
        "tgn:7029392"
    ],
    "tgn:id":7594270,
    "tgn:name":"Grotta dei Fanciulli",
    "tgn:placetype":[
        "aat:300386972",
        "aat:300000810",
        "aat:300048808",
        "aat:300387006"
    ]
},
  "bbox": [],
  "geometry": {"coordinates":[7.535,43.783],"type":"Point"}
}