{
  "id": 7576120,
  "type": "Feature",
  "properties": {
    "tgn:hierarchy":[
        "tgn:7576120",
        "tgn:1000004",
        "tgn:7000198",
        "tgn:7016722",
        "tgn:7029392"
    ],
    "tgn:id":7576120,
    "tgn:name:en":"Korh Road",
    "tgn:placetype":[
        "aat:300007783"
    ]
},
  "bbox": [],
  "geometry": {"coordinates":[82.433333,25.283333],"type":"Point"}
}