{
  "id": 2252069,
  "type": "Feature",
  "properties": {
    "tgn:hierarchy":[
        "tgn:2252069",
        "tgn:1000001",
        "tgn:7012149",
        "tgn:2001916",
        "tgn:7007825",
        "tgn:7029392"
    ],
    "tgn:id":2252069,
    "tgn:name":"Condit Hollow",
    "tgn:placetype":[
        "aat:300008761"
    ]
},
  "bbox": [],
  "geometry": {"coordinates":[-85.85,36.2167],"type":"Point"}
}