<<<<<<< HEAD
{
  "id": 2252069,
  "type": "Feature",
  "properties": {
    "tgn:hierarchy":[
        "tgn:2252069",
        "tgn:1000001",
        "tgn:7012149",
        "tgn:2001916",
        "tgn:7007825",
        "tgn:7029392"
    ],
    "tgn:id":2252069,
    "tgn:name":"Condit Hollow",
    "tgn:placetype":[
        "aat:300008761"
    ]
},
  "bbox": [],
  "geometry": {"coordinates":[-85.85,36.2167],"type":"Point"}
}
=======
{"geometry":{"type":"Point","coordinates":[-85.850000,36.216700]},"type":"Feature","properties":{"hierarchy":["tgn:2252069","tgn:1000001","tgn:7012149","tgn:2001916","tgn:7007825","tgn:7029392"],"placetype":["aat:300008761"],"id":2252069,"name:xx":"Condit Hollow"}}
>>>>>>> 03f74aca74312dbeaf24d7e61306dd6a786dc3d0
