{
  "id": 7035325,
  "type": "Feature",
  "properties": {
    "tgn:hierarchy":[
        "tgn:7035325",
        "tgn:1003488",
        "tgn:1000003",
        "tgn:7002993",
        "tgn:1000080",
        "tgn:7029392"
    ],
    "tgn:id":7035325,
    "tgn:name":"Resettum, Monte",
    "tgn:placetype":[
        "aat:300008795"
    ]
},
  "bbox": [],
  "geometry": {"coordinates":[12.575278,46.240556],"type":"Point"}
}