{
  "id": 7497160,
  "type": "Feature",
  "properties": {
    "tgn:hierarchy":[
        "tgn:7497160",
        "tgn:1000004",
        "tgn:7001009",
        "tgn:1000141",
        "tgn:7029392"
    ],
    "tgn:id":7497160,
    "tgn:name":"Leye Guoxiao",
    "tgn:placetype":[
        "aat:300006495"
    ]
},
  "bbox": [],
  "geometry": {"coordinates":[120.6944,24.1376],"type":"Point"}
}