{
  "id": 1052001,
  "type": "Feature",
  "properties": {
    "tgn:hierarchy":[
        "tgn:1052001",
        "tgn:1000004",
        "tgn:1003363",
        "tgn:7014786",
        "tgn:7029392"
    ],
    "tgn:id":1052001,
    "tgn:name":"Akzharyk",
    "tgn:placetype":[
        "aat:300008347"
    ]
},
  "bbox": [],
  "geometry": {"coordinates":[75.4833,48.5667],"type":"Point"}
}