{
  "id": 7532789,
  "type": "Feature",
  "properties": {
    "tgn:hierarchy":[
        "tgn:7532789",
        "tgn:7001242",
        "tgn:7016833",
        "tgn:1001091",
        "tgn:7029392"
    ],
    "tgn:id":7532789,
    "tgn:name":"S\u012bnam\u0101 Awdiy\u016bn",
    "tgn:placetype":[
        "aat:300004792"
    ]
},
  "bbox": [],
  "geometry": {"coordinates":[31.238582,30.050017],"type":"Point"}
}