{
  "id": 2537838,
  "type": "Feature",
  "properties": {
    "tgn:hierarchy":[
        "tgn:2537838",
        "tgn:1000001",
        "tgn:1002477",
        "tgn:7012149",
        "tgn:7007240",
        "tgn:7029392"
    ],
    "tgn:id":2537838,
    "tgn:name":"Nellie Northwest, Lake",
    "tgn:placetype":[
        "aat:300008680"
    ]
},
  "bbox": [],
  "geometry": {"coordinates":[-81.3833,27.35],"type":"Point"}
}