{
  "id": 2516954,
  "type": "Feature",
  "properties": {
    "tgn:hierarchy":[
        "tgn:2516954",
        "tgn:1000001",
        "tgn:7012149",
        "tgn:7007710",
        "tgn:7029392"
    ],
    "tgn:id":2516954,
    "tgn:name":"Minister Creek",
    "tgn:placetype":[
        "aat:300008706"
    ]
},
  "bbox": [],
  "geometry": {"coordinates":[-75.6167,40.3167],"type":"Point"}
}