{
  "id": 7525971,
  "type": "Feature",
  "properties": {
    "tgn:hierarchy":[
        "tgn:7525971",
        "tgn:7001242",
        "tgn:7016833",
        "tgn:7000122",
        "tgn:7029392"
    ],
    "tgn:id":7525971,
    "tgn:name:en":"Man\u0101mat S\u012bd\u012b \u1e28asan",
    "tgn:placetype":[
        "aat:300005926"
    ]
},
  "bbox": [],
  "geometry": {"coordinates":[32.916667,24.533333],"type":"Point"}
}