<<<<<<< HEAD
{
  "id": 2151866,
  "type": "Feature",
  "properties": {
    "tgn:hierarchy":[
        "tgn:2151866",
        "tgn:1000001",
        "tgn:7006451",
        "tgn:7012149",
        "tgn:2000098",
        "tgn:7029392"
    ],
    "tgn:id":2151866,
    "tgn:name":"Battleship Mountain",
    "tgn:placetype":[
        "aat:300008798"
    ]
},
  "bbox": [],
  "geometry": {"coordinates":[-114.3667,35.0667],"type":"Point"}
}
=======
{"geometry":{"type":"Point","coordinates":[-114.366700,35.066700]},"type":"Feature","properties":{"hierarchy":["tgn:2151866","tgn:1000001","tgn:7006451","tgn:7012149","tgn:2000098","tgn:7029392"],"placetype":["aat:300008798"],"id":2151866,"name:xx":"Battleship Mountain"}}
>>>>>>> 03f74aca74312dbeaf24d7e61306dd6a786dc3d0
