{
  "id": 2177838,
  "type": "Feature",
  "properties": {
    "tgn:hierarchy":[
        "tgn:2177838",
        "tgn:1000001",
        "tgn:7012149",
        "tgn:1002567",
        "tgn:7007240",
        "tgn:7029392"
    ],
    "tgn:id":2177838,
    "tgn:name":"Black Water Swamp",
    "tgn:placetype":[
        "aat:300008905"
    ]
},
  "bbox": [],
  "geometry": {"coordinates":[-81.5667,28.95],"type":"Point"}
}