{
  "id": 7010591,
  "type": "Feature",
  "properties": {
    "tgn:hierarchy":[
        "tgn:7010591",
        "tgn:1000003",
        "tgn:7002890",
        "tgn:1000070",
        "tgn:7029392"
    ],
    "tgn:id":7010591,
    "tgn:name":"Saint-Riquier",
    "tgn:placetype":[
        "aat:300008347"
    ]
},
  "bbox": [],
  "geometry": {"coordinates":[1.9667,50.15],"type":"Point"}
}