{
  "id": 2709571,
  "type": "Feature",
  "properties": {
    "tgn:hierarchy":[
        "tgn:2709571",
        "tgn:1000001",
        "tgn:1002328",
        "tgn:7012149",
        "tgn:7007568",
        "tgn:7029392"
    ],
    "tgn:id":2709571,
    "tgn:name":"Tacoma",
    "tgn:placetype":[
        "aat:300008347"
    ]
},
  "bbox": [],
  "geometry": {"coordinates":[-75.2667,42.2333],"type":"Point"}
}