{
  "id": 1044433,
  "type": "Feature",
  "properties": {
    "tgn:hierarchy":[
        "tgn:1044433",
        "tgn:7002996",
        "tgn:1000003",
        "tgn:7002997",
        "tgn:1000080",
        "tgn:7029392"
    ],
    "tgn:id":1044433,
    "tgn:name":"Crocetta del Montello",
    "tgn:placetype":[
        "aat:300008347"
    ]
},
  "bbox": [],
  "geometry": {"coordinates":[12.033611,45.836667],"type":"Point"}
}