{
  "id": 2771423,
  "type": "Feature",
  "properties": {
    "tgn:hierarchy":[
        "tgn:2771423",
        "tgn:2000453",
        "tgn:1000001",
        "tgn:7012149",
        "tgn:7007250",
        "tgn:7029392"
    ],
    "tgn:id":2771423,
    "tgn:name":"Wildhorse",
    "tgn:placetype":[
        "aat:300008347"
    ]
},
  "bbox": [],
  "geometry": {"coordinates":[-116.8167,44.85],"type":"Point"}
}