{
  "id": 2308626,
  "type": "Feature",
  "properties": {
    "tgn:hierarchy":[
        "tgn:2308626",
        "tgn:1000001",
        "tgn:7012149",
        "tgn:2000230",
        "tgn:7007158",
        "tgn:7029392"
    ],
    "tgn:id":2308626,
    "tgn:name":"East Orchard Mesa",
    "tgn:placetype":[
        "aat:300008798"
    ]
},
  "bbox": [],
  "geometry": {"coordinates":[-108.35,39.0833],"type":"Point"}
}