{
  "id": 2636722,
  "type": "Feature",
  "properties": {
    "tgn:hierarchy":[
        "tgn:2636722",
        "tgn:1000001",
        "tgn:7012149",
        "tgn:2002371",
        "tgn:7007923",
        "tgn:7029392"
    ],
    "tgn:id":2636722,
    "tgn:name":"Sagebrush Draw",
    "tgn:placetype":[
        "aat:300008761"
    ]
},
  "bbox": [],
  "geometry": {"coordinates":[-107.6167,43.45],"type":"Point"}
}