{
  "id": 7472465,
  "type": "Feature",
  "properties": {
    "tgn:hierarchy":[
        "tgn:7472465",
        "tgn:1000004",
        "tgn:7467799",
        "tgn:1000141",
        "tgn:7029392"
    ],
    "tgn:id":7472465,
    "tgn:name":"Xinzhuangzi",
    "tgn:placetype":[
        "aat:300387033"
    ]
},
  "bbox": [],
  "geometry": {"coordinates":[120.491568,23.865887],"type":"Point"}
}