{
  "id": 7002487,
  "type": "Feature",
  "properties": {
    "tgn:hierarchy":[
        "tgn:7002487",
        "tgn:1001287",
        "tgn:7018452",
        "tgn:1000004",
        "tgn:1000144",
        "tgn:7029392"
    ],
    "tgn:id":7002487,
    "tgn:name":"Kamberli",
    "tgn:placetype":[
        "aat:300008347"
    ]
},
  "bbox": [],
  "geometry": {"coordinates":[36.15,36.15],"type":"Point"}
}