<<<<<<< HEAD
{
  "id": 7471965,
  "type": "Feature",
  "properties": {
    "tgn:hierarchy":[
        "tgn:7471965",
        "tgn:7001010",
        "tgn:1000004",
        "tgn:1000141",
        "tgn:7029392"
    ],
    "tgn:id":7471965,
    "tgn:name":"Lan Shan Nanfeng",
    "tgn:placetype":[
        "aat:300008798"
    ]
},
  "bbox": [],
  "geometry": {"coordinates":[121.5217,24.0391],"type":"Point"}
}
=======
{"geometry":{"type":"Point","coordinates":[121.521700,24.039100]},"type":"Feature","properties":{"hierarchy":["tgn:7471965","tgn:7001010","tgn:1000004","tgn:1000141","tgn:7029392"],"placetype":["aat:300008798"],"id":7471965,"name:xx":"Lan Shan Nanfeng"}}
>>>>>>> 03f74aca74312dbeaf24d7e61306dd6a786dc3d0
