{
  "id": 7429172,
  "type": "Feature",
  "properties": {
    "tgn:hierarchy":[
        "tgn:7429172",
        "tgn:1001853",
        "tgn:1000001",
        "tgn:7005560",
        "tgn:7029392"
    ],
    "tgn:id":7429172,
    "tgn:name":"Las Pulgas",
    "tgn:placetype":[
        "aat:300008347"
    ]
},
  "bbox": [],
  "geometry": {"coordinates":[-100.833333,25.366667],"type":"Point"}
}