{
  "id": 2680911,
  "type": "Feature",
  "properties": {
    "tgn:hierarchy":[
        "tgn:2680911",
        "tgn:1000001",
        "tgn:7012149",
        "tgn:2002359",
        "tgn:7007922",
        "tgn:7029392"
    ],
    "tgn:id":2680911,
    "tgn:name":"South Lakes Church",
    "tgn:placetype":[
        "aat:300008680"
    ]
},
  "bbox": [],
  "geometry": {"coordinates":[-89.1667,46.0167],"type":"Point"}
}