{
  "id": 1080188,
  "type": "Feature",
  "properties": {
    "tgn:hierarchy":[
        "tgn:1080188",
        "tgn:1000997",
        "tgn:1000004",
        "tgn:7000901",
        "tgn:1000120",
        "tgn:7029392"
    ],
    "tgn:id":1080188,
    "tgn:name":"Ichinomiya",
    "tgn:placetype":[
        "aat:300008347"
    ]
},
  "bbox": [],
  "geometry": {"coordinates":[131.1167,32.95],"type":"Point"}
}