{
  "id": 7519193,
  "type": "Feature",
  "properties": {
    "tgn:hierarchy":[
        "tgn:7519193",
        "tgn:1009227",
        "tgn:1000226",
        "tgn:1000006",
        "tgn:7016850",
        "tgn:7029392"
    ],
    "tgn:id":7519193,
    "tgn:name:en":"Brown, Mount",
    "tgn:placetype":[
        "aat:300008795"
    ]
},
  "bbox": [],
  "geometry": {"coordinates":[171.216667,-42.866667],"type":"Point"}
}