{
  "id": 2584767,
  "type": "Feature",
  "properties": {
    "tgn:hierarchy":[
        "tgn:2584767",
        "tgn:1000001",
        "tgn:7012149",
        "tgn:2001855",
        "tgn:7007825",
        "tgn:7029392"
    ],
    "tgn:id":2584767,
    "tgn:name":"Pinhook Hill",
    "tgn:placetype":[
        "aat:300008798"
    ]
},
  "bbox": [],
  "geometry": {"coordinates":[-86.8833,36.25],"type":"Point"}
}