{
  "id": 2743205,
  "type": "Feature",
  "properties": {
    "tgn:hierarchy":[
        "tgn:2743205",
        "tgn:1000001",
        "tgn:7012149",
        "tgn:2002293",
        "tgn:7013961",
        "tgn:7029392"
    ],
    "tgn:id":2743205,
    "tgn:name":"Vandale Fork",
    "tgn:placetype":[
        "aat:300008699"
    ]
},
  "bbox": [],
  "geometry": {"coordinates":[-81.2833,38.7333],"type":"Point"}
}