{
  "id": 2211299,
  "type": "Feature",
  "properties": {
    "tgn:hierarchy":[
        "tgn:2211299",
        "tgn:1000001",
        "tgn:7012149",
        "tgn:2000219",
        "tgn:7007158",
        "tgn:7029392"
    ],
    "tgn:id":2211299,
    "tgn:name":"Butte Ditch",
    "tgn:placetype":[
        "aat:300006075"
    ]
},
  "bbox": [],
  "geometry": {"coordinates":[-105.0333,37.4667],"type":"Point"}
}