{
  "id": 2291446,
  "type": "Feature",
  "properties": {
    "tgn:hierarchy":[
        "tgn:2291446",
        "tgn:1000001",
        "tgn:1002275",
        "tgn:7012149",
        "tgn:7007920",
        "tgn:7029392"
    ],
    "tgn:id":2291446,
    "tgn:name":"Dole",
    "tgn:placetype":[
        "aat:300008347"
    ]
},
  "bbox": [],
  "geometry": {"coordinates":[-122.3333,45.7833],"type":"Point"}
}