{
  "id": 2578740,
  "type": "Feature",
  "properties": {
    "tgn:hierarchy":[
        "tgn:2578740",
        "tgn:1000001",
        "tgn:7012149",
        "tgn:2001711",
        "tgn:7007708",
        "tgn:7029392"
    ],
    "tgn:id":2578740,
    "tgn:name":"Phillips Creek",
    "tgn:placetype":[
        "aat:300008706"
    ]
},
  "bbox": [],
  "geometry": {"coordinates":[-122.4167,42.6167],"type":"Point"}
}