{
  "id": 1071336,
  "type": "Feature",
  "properties": {
    "tgn:hierarchy":[
        "tgn:1071336",
        "tgn:1000004",
        "tgn:7002076",
        "tgn:1000111",
        "tgn:7029392"
    ],
    "tgn:id":1071336,
    "tgn:name":"Sanmen",
    "tgn:placetype":[
        "aat:300008347"
    ]
},
  "bbox": [],
  "geometry": {"coordinates":[121.3667,29.1333],"type":"Point"}
}