{
  "id": 7394906,
  "type": "Feature",
  "properties": {
    "tgn:hierarchy":[
        "tgn:7394906",
        "tgn:1001836",
        "tgn:1000001",
        "tgn:7005560",
        "tgn:7029392"
    ],
    "tgn:id":7394906,
    "tgn:name":"Estero San Cosme, Punta",
    "tgn:placetype":[
        "aat:300386846"
    ]
},
  "bbox": [],
  "geometry": {"coordinates":[-111.145833,25.565556],"type":"Point"}
}