{
  "id": 2239389,
  "type": "Feature",
  "properties": {
    "tgn:hierarchy":[
        "tgn:2239389",
        "tgn:1000001",
        "tgn:7012149",
        "tgn:7029392"
    ],
    "tgn:id":2239389,
    "tgn:name":"Church Creek",
    "tgn:placetype":[
        "aat:300008706"
    ]
},
  "bbox": [],
  "geometry": {"coordinates":[-84.8167,39.6833],"type":"Point"}
}