{
  "id": 7168604,
  "type": "Feature",
  "properties": {
    "tgn:hierarchy":[
        "tgn:7168604",
        "tgn:1000003",
        "tgn:7003676",
        "tgn:7000084",
        "tgn:7029392"
    ],
    "tgn:id":7168604,
    "tgn:name":"Heiligenbruch",
    "tgn:placetype":[
        "aat:300008347"
    ]
},
  "bbox": [],
  "geometry": {"coordinates":[8.933333,52.966667],"type":"Point"}
}