{
  "id": 7359741,
  "type": "Feature",
  "properties": {
    "tgn:hierarchy":[
        "tgn:7359741",
        "tgn:1000001",
        "tgn:7005597",
        "tgn:7005560",
        "tgn:7029392"
    ],
    "tgn:id":7359741,
    "tgn:name":"Coahuila",
    "tgn:placetype":[
        "aat:300008347"
    ]
},
  "bbox": [],
  "geometry": {"coordinates":[-99.233333,22.866667],"type":"Point"}
}