<<<<<<< HEAD
{
  "id": 7359741,
  "type": "Feature",
  "properties": {
    "tgn:hierarchy":[
        "tgn:7359741",
        "tgn:1000001",
        "tgn:7005597",
        "tgn:7005560",
        "tgn:7029392"
    ],
    "tgn:id":7359741,
    "tgn:name":"Coahuila",
    "tgn:placetype":[
        "aat:300008347"
    ]
},
  "bbox": [],
  "geometry": {"coordinates":[-99.233333,22.866667],"type":"Point"}
}
=======
{"geometry":{"type":"Point","coordinates":[-99.233333,22.866667]},"type":"Feature","properties":{"hierarchy":["tgn:7359741","tgn:1000001","tgn:7005597","tgn:7005560","tgn:7029392"],"placetype":["aat:300008347"],"id":7359741,"name:xx":"Coahuila"}}
>>>>>>> 03f74aca74312dbeaf24d7e61306dd6a786dc3d0
