{
  "id": 7589996,
  "type": "Feature",
  "properties": {
    "tgn:hierarchy":[
        "tgn:7589996",
        "tgn:1000004",
        "tgn:7000198",
        "tgn:7000799",
        "tgn:7029392"
    ],
    "tgn:id":7589996,
    "tgn:name:en":"Ker\u0101n",
    "tgn:placetype":[
        "aat:300008798"
    ]
},
  "bbox": [],
  "geometry": {"coordinates":[73.97143,34.049784],"type":"Point"}
}