{
  "id": 7504678,
  "type": "Feature",
  "properties": {
    "tgn:hierarchy":[
        "tgn:7504678",
        "tgn:7000508",
        "tgn:1008380",
        "tgn:1000226",
        "tgn:1000006",
        "tgn:7029392"
    ],
    "tgn:id":7504678,
    "tgn:name:en":"Takapuna Beach",
    "tgn:placetype":[
        "aat:300008816"
    ]
},
  "bbox": [],
  "geometry": {"coordinates":[174.780556,-36.791667],"type":"Point"}
}