{
  "id": 1126174,
  "type": "Feature",
  "properties": {
    "tgn:hierarchy":[
        "tgn:1126174",
        "tgn:1000001",
        "tgn:7012149",
        "tgn:1002468",
        "tgn:7007252",
        "tgn:7029392"
    ],
    "tgn:id":1126174,
    "tgn:name":"Little Blue",
    "tgn:placetype":[
        "aat:300008707"
    ]
},
  "bbox": [],
  "geometry": {"coordinates":[-85.2667,39.9667],"type":"Point"}
}