{
  "id": 7142897,
  "type": "Feature",
  "properties": {
    "tgn:hierarchy":[
        "tgn:7142897",
        "tgn:1000003",
        "tgn:7000094",
        "tgn:7000084",
        "tgn:7029392"
    ],
    "tgn:id":7142897,
    "tgn:name":"Magdalenenlust",
    "tgn:placetype":[
        "aat:300000206"
    ]
},
  "bbox": [],
  "geometry": {"coordinates":[12.183333,53.783333],"type":"Point"}
}