{
  "id": 1099422,
  "type": "Feature",
  "properties": {
    "tgn:hierarchy":[
        "tgn:1099422",
        "tgn:1000886",
        "tgn:7006160",
        "tgn:1000006",
        "tgn:7029392"
    ],
    "tgn:id":1099422,
    "tgn:name":"Atemble",
    "tgn:placetype":[
        "aat:300008347"
    ]
},
  "bbox": [],
  "geometry": {"coordinates":[144.7833,-5.05],"type":"Point"}
}