{
  "id": 2506693,
  "type": "Feature",
  "properties": {
    "tgn:hierarchy":[
        "tgn:2506693",
        "tgn:1000001",
        "tgn:2001430",
        "tgn:7012149",
        "tgn:7007566",
        "tgn:7029392"
    ],
    "tgn:id":2506693,
    "tgn:name":"Mesa Tank",
    "tgn:placetype":[
        "aat:300006191"
    ]
},
  "bbox": [],
  "geometry": {"coordinates":[-104.6333,33.9667],"type":"Point"}
}