{
  "id": 2061118,
  "type": "Feature",
  "properties": {
    "tgn:hierarchy":[
        "tgn:2061118",
        "tgn:1000001",
        "tgn:7012149",
        "tgn:2001276",
        "tgn:7007524",
        "tgn:7029392"
    ],
    "tgn:id":2061118,
    "tgn:name":"Brusett",
    "tgn:placetype":[
        "aat:300008347"
    ]
},
  "bbox": [],
  "geometry": {"coordinates":[-107.25,47.4167],"type":"Point"}
}