<<<<<<< HEAD
{
  "id": 2767687,
  "type": "Feature",
  "properties": {
    "tgn:hierarchy":[
        "tgn:2767687",
        "tgn:1000001",
        "tgn:7012149",
        "tgn:7007521",
        "tgn:7029392"
    ],
    "tgn:id":2767687,
    "tgn:name":"Whitefish Lake",
    "tgn:placetype":[
        "aat:300008680"
    ]
},
  "bbox": [],
  "geometry": {"coordinates":[-93.8,46.2],"type":"Point"}
}
=======
{"geometry":{"type":"Point","coordinates":[-93.800000,46.200000]},"type":"Feature","properties":{"hierarchy":["tgn:2767687","tgn:1000001","tgn:7012149","tgn:7007521","tgn:7029392"],"placetype":["aat:300008680"],"id":2767687,"name:xx":"Whitefish Lake"}}
>>>>>>> 03f74aca74312dbeaf24d7e61306dd6a786dc3d0
