{
  "id": 1113107,
  "type": "Feature",
  "properties": {
    "tgn:hierarchy":[
        "tgn:1113107",
        "tgn:7005685",
        "tgn:1000001",
        "tgn:1000296",
        "tgn:7024247",
        "tgn:7029392"
    ],
    "tgn:id":1113107,
    "tgn:name":"Hardy Bay",
    "tgn:placetype":[
        "aat:300132316"
    ]
},
  "bbox": [],
  "geometry": {"coordinates":[-115.2667,75.0333],"type":"Point"}
}