<<<<<<< HEAD
{
  "id": 7357896,
  "type": "Feature",
  "properties": {
    "tgn:hierarchy":[
        "tgn:7357896",
        "tgn:1001853",
        "tgn:1000001",
        "tgn:7005560",
        "tgn:7029392"
    ],
    "tgn:id":7357896,
    "tgn:name":"Ejido La Sicilia",
    "tgn:placetype":[
        "aat:300008347"
    ]
},
  "bbox": [],
  "geometry": {"coordinates":[-101.916667,25.566667],"type":"Point"}
}
=======
{"geometry":{"type":"Point","coordinates":[-101.916667,25.566667]},"type":"Feature","properties":{"hierarchy":["tgn:7357896","tgn:1001853","tgn:1000001","tgn:7005560","tgn:7029392"],"placetype":["aat:300008347"],"id":7357896,"name:xx":"Ejido La Sicilia"}}
>>>>>>> 03f74aca74312dbeaf24d7e61306dd6a786dc3d0
