{
  "id": 2649974,
  "type": "Feature",
  "properties": {
    "tgn:hierarchy":[
        "tgn:2649974",
        "tgn:1000001",
        "tgn:7012149",
        "tgn:1002782",
        "tgn:7007710",
        "tgn:7029392"
    ],
    "tgn:id":2649974,
    "tgn:name":"Scuylkill Rowing Basin",
    "tgn:placetype":[
        "aat:300006191"
    ]
},
  "bbox": [],
  "geometry": {"coordinates":[-75.1833,39.9667],"type":"Point"}
}