{
  "id": 1079578,
  "type": "Feature",
  "properties": {
    "tgn:hierarchy":[
        "tgn:1079578",
        "tgn:1000862",
        "tgn:1000004",
        "tgn:1000119",
        "tgn:7029392"
    ],
    "tgn:id":1079578,
    "tgn:name":"Nes \u1e94iyyona",
    "tgn:placetype":[
        "aat:300008347"
    ]
},
  "bbox": [],
  "geometry": {"coordinates":[34.7667,31.9333],"type":"Point"}
}