{
  "id": 1123271,
  "type": "Feature",
  "properties": {
    "tgn:hierarchy":[
        "tgn:1123271",
        "tgn:1000004",
        "tgn:7002078",
        "tgn:1000111",
        "tgn:7029392"
    ],
    "tgn:id":1123271,
    "tgn:name":"Dafu",
    "tgn:placetype":[
        "aat:300008707"
    ]
},
  "bbox": [],
  "geometry": {"coordinates":[113.5333,30.8667],"type":"Point"}
}