{
  "id": 7463395,
  "type": "Feature",
  "properties": {
    "tgn:hierarchy":[
        "tgn:7463395",
        "tgn:7002445",
        "tgn:1000003",
        "tgn:7008166",
        "tgn:7008591",
        "tgn:7029392"
    ],
    "tgn:id":7463395,
    "tgn:name:en":"Long Nab",
    "tgn:placetype":[
        "aat:300386846"
    ]
},
  "bbox": [],
  "geometry": {"coordinates":[-0.416667,54.333333],"type":"Point"}
}