{
  "id": 7591105,
  "type": "Feature",
  "properties": {
    "tgn:hierarchy":[
        "tgn:7591105",
        "tgn:1000004",
        "tgn:7000198",
        "tgn:7000799",
        "tgn:7029392"
    ],
    "tgn:id":7591105,
    "tgn:name:en":"Bad\u0101li",
    "tgn:placetype":[
        "aat:300008347"
    ]
},
  "bbox": [],
  "geometry": {"coordinates":[74.989455,32.560661],"type":"Point"}
}