{
  "id": 7053575,
  "type": "Feature",
  "properties": {
    "tgn:hierarchy":[
        "tgn:7053575",
        "tgn:7005611",
        "tgn:1000003",
        "tgn:7003120",
        "tgn:1000080",
        "tgn:7029392"
    ],
    "tgn:id":7053575,
    "tgn:name":"Montegrosso d'Asti",
    "tgn:placetype":[
        "aat:300008347"
    ]
},
  "bbox": [],
  "geometry": {"coordinates":[8.233333,44.816667],"type":"Point"}
}