<<<<<<< HEAD
{
  "id": 7172125,
  "type": "Feature",
  "properties": {
    "tgn:hierarchy":[
        "tgn:7172125",
        "tgn:1000003",
        "tgn:7003676",
        "tgn:7000084",
        "tgn:7029392"
    ],
    "tgn:id":7172125,
    "tgn:name":"Helmsm\u00fchle",
    "tgn:placetype":[
        "aat:300000206"
    ]
},
  "bbox": [],
  "geometry": {"coordinates":[8.533333,52.683333],"type":"Point"}
}
=======
{"geometry":{"type":"Point","coordinates":[8.533333,52.683333]},"type":"Feature","properties":{"hierarchy":["tgn:7172125","tgn:1000003","tgn:7003676","tgn:7000084","tgn:7029392"],"placetype":["aat:300000206"],"id":7172125,"name:xx":"Helmsm\u00fchle"}}
>>>>>>> 03f74aca74312dbeaf24d7e61306dd6a786dc3d0
