{
  "id": 7308660,
  "type": "Feature",
  "properties": {
    "tgn:hierarchy":[
        "tgn:7308660",
        "tgn:1001702",
        "tgn:1000049",
        "tgn:1000002",
        "tgn:7029392"
    ],
    "tgn:id":7308660,
    "tgn:name":"Low, Rocas",
    "tgn:placetype":[
        "aat:300011692"
    ]
},
  "bbox": [],
  "geometry": {"coordinates":[-73.683333,-52.616667],"type":"Point"}
}