{
  "id": 7164089,
  "type": "Feature",
  "properties": {
    "tgn:hierarchy":[
        "tgn:7164089",
        "tgn:1000003",
        "tgn:7003676",
        "tgn:7000084",
        "tgn:7029392"
    ],
    "tgn:id":7164089,
    "tgn:name":"H\u00fcnstollen",
    "tgn:placetype":[
        "aat:300008777"
    ]
},
  "bbox": [],
  "geometry": {"coordinates":[10.05,51.583333],"type":"Point"}
}