<<<<<<< HEAD
{
  "id": 2151526,
  "type": "Feature",
  "properties": {
    "tgn:hierarchy":[
        "tgn:2151526",
        "tgn:1000001",
        "tgn:7012149",
        "tgn:1002392",
        "tgn:7007157",
        "tgn:7029392"
    ],
    "tgn:id":2151526,
    "tgn:name":"Battalion Lake",
    "tgn:placetype":[
        "aat:300008680"
    ]
},
  "bbox": [],
  "geometry": {"coordinates":[-118.7333,37.05],"type":"Point"}
}
=======
{"geometry":{"type":"Point","coordinates":[-118.733300,37.050000]},"type":"Feature","properties":{"hierarchy":["tgn:2151526","tgn:1000001","tgn:7012149","tgn:1002392","tgn:7007157","tgn:7029392"],"placetype":["aat:300008680"],"id":2151526,"name:xx":"Battalion Lake"}}
>>>>>>> 03f74aca74312dbeaf24d7e61306dd6a786dc3d0
