{
  "id": 2151526,
  "type": "Feature",
  "properties": {
    "tgn:hierarchy":[
        "tgn:2151526",
        "tgn:1000001",
        "tgn:7012149",
        "tgn:1002392",
        "tgn:7007157",
        "tgn:7029392"
    ],
    "tgn:id":2151526,
    "tgn:name":"Battalion Lake",
    "tgn:placetype":[
        "aat:300008680"
    ]
},
  "bbox": [],
  "geometry": {"coordinates":[-118.7333,37.05],"type":"Point"}
}