{
  "id": 2487551,
  "type": "Feature",
  "properties": {
    "tgn:hierarchy":[
        "tgn:2487551",
        "tgn:1000001",
        "tgn:2002102",
        "tgn:7012149",
        "tgn:7007827",
        "tgn:7029392"
    ],
    "tgn:id":2487551,
    "tgn:name":"Left Fork Dutchmans Canyon",
    "tgn:placetype":[
        "aat:300008761"
    ]
},
  "bbox": [],
  "geometry": {"coordinates":[-112.1167,41.9167],"type":"Point"}
}