<<<<<<< HEAD
{
  "id": 2407322,
  "type": "Feature",
  "properties": {
    "tgn:hierarchy":[
        "tgn:2407322",
        "tgn:1000001",
        "tgn:7016104",
        "tgn:7012149",
        "tgn:7007516",
        "tgn:7029392"
    ],
    "tgn:id":2407322,
    "tgn:name":"Huntington",
    "tgn:placetype":[
        "aat:300008347"
    ]
},
  "bbox": [],
  "geometry": {"coordinates":[-77.1,38.9833],"type":"Point"}
}
=======
{"geometry":{"type":"Point","coordinates":[-77.100000,38.983300]},"type":"Feature","properties":{"hierarchy":["tgn:2407322","tgn:1000001","tgn:7016104","tgn:7012149","tgn:7007516","tgn:7029392"],"placetype":["aat:300008347"],"id":2407322,"name:xx":"Huntington"}}
>>>>>>> 03f74aca74312dbeaf24d7e61306dd6a786dc3d0
