{
  "id": 2516009,
  "type": "Feature",
  "properties": {
    "tgn:hierarchy":[
        "tgn:2516009",
        "tgn:1000001",
        "tgn:2001417",
        "tgn:7012149",
        "tgn:7007526",
        "tgn:7029392"
    ],
    "tgn:id":2516009,
    "tgn:name":"Mina Mine",
    "tgn:placetype":[
        "aat:300000390"
    ]
},
  "bbox": [],
  "geometry": {"coordinates":[-117.9333,38.3667],"type":"Point"}
}