{
  "id": 1099945,
  "type": "Feature",
  "properties": {
    "tgn:hierarchy":[
        "tgn:1099945",
        "tgn:1001015",
        "tgn:7000897",
        "tgn:1000004",
        "tgn:1000120",
        "tgn:7029392"
    ],
    "tgn:id":1099945,
    "tgn:name":"Tsukinowa-kofun",
    "tgn:placetype":[
        "aat:300008347",
        "aat:300167671"
    ]
},
  "bbox": [],
  "geometry": {"coordinates":[134.1833,34.9167],"type":"Point"}
}