{
  "id": 1136163,
  "type": "Feature",
  "properties": {
    "tgn:hierarchy":[
        "tgn:1136163",
        "tgn:1001708",
        "tgn:1000049",
        "tgn:1000002",
        "tgn:7029392"
    ],
    "tgn:id":1136163,
    "tgn:name":"El Colorado, Canal de",
    "tgn:placetype":[
        "aat:300006178"
    ]
},
  "bbox": [],
  "geometry": {"coordinates":[-70.5333,-33.5667],"type":"Point"}
}