<<<<<<< HEAD
{
  "id": 7482258,
  "type": "Feature",
  "properties": {
    "tgn:hierarchy":[
        "tgn:7482258",
        "tgn:1000004",
        "tgn:7490934",
        "tgn:1000141",
        "tgn:7029392"
    ],
    "tgn:id":7482258,
    "tgn:name":"Guangxing Gong",
    "tgn:placetype":[
        "aat:300007595"
    ]
},
  "bbox": [],
  "geometry": {"coordinates":[120.280124,23.018852],"type":"Point"}
}
=======
{"geometry":{"type":"Point","coordinates":[120.280124,23.018852]},"type":"Feature","properties":{"hierarchy":["tgn:7482258","tgn:1000004","tgn:7490934","tgn:1000141","tgn:7029392"],"placetype":["aat:300007595"],"id":7482258,"name:xx":"Guangxing Gong"}}
>>>>>>> 03f74aca74312dbeaf24d7e61306dd6a786dc3d0
