{
  "id": 7284607,
  "type": "Feature",
  "properties": {
    "tgn:hierarchy":[
        "tgn:7284607",
        "tgn:1001699",
        "tgn:1000049",
        "tgn:1000002",
        "tgn:7029392"
    ],
    "tgn:id":7284607,
    "tgn:name":"Punco, Estero",
    "tgn:placetype":[
        "aat:300008699"
    ]
},
  "bbox": [],
  "geometry": {"coordinates":[-72.716667,-39.833333],"type":"Point"}
}