{
  "id": 7565658,
  "type": "Feature",
  "properties": {
    "tgn:hierarchy":[
        "tgn:7565658",
        "tgn:1000004",
        "tgn:7000198",
        "tgn:7016722",
        "tgn:7029392"
    ],
    "tgn:id":7565658,
    "tgn:name:en":"Patipura",
    "tgn:placetype":[
        "aat:300008347"
    ]
},
  "bbox": [],
  "geometry": {"coordinates":[79.458482,26.116974],"type":"Point"}
}