{
  "id": 2364786,
  "type": "Feature",
  "properties": {
    "tgn:hierarchy":[
        "tgn:2364786",
        "tgn:1000001",
        "tgn:2000951",
        "tgn:7012149",
        "tgn:7007520",
        "tgn:7029392"
    ],
    "tgn:id":2364786,
    "tgn:name":"Greene Creek",
    "tgn:placetype":[
        "aat:300008706"
    ]
},
  "bbox": [],
  "geometry": {"coordinates":[-84.2833,45.6167],"type":"Point"}
}