{
  "id": 2161019,
  "type": "Feature",
  "properties": {
    "tgn:hierarchy":[
        "tgn:2161019",
        "tgn:1000001",
        "tgn:7012149",
        "tgn:7016021",
        "tgn:7007568",
        "tgn:7029392"
    ],
    "tgn:id":2161019,
    "tgn:name":"Bell Brook",
    "tgn:placetype":[
        "aat:300008699"
    ]
},
  "bbox": [],
  "geometry": {"coordinates":[-74.8333,44.7833],"type":"Point"}
}