{
  "id": 2023885,
  "type": "Feature",
  "properties": {
    "tgn:hierarchy":[
        "tgn:2023885",
        "tgn:1000001",
        "tgn:7012149",
        "tgn:2000405",
        "tgn:7007248",
        "tgn:7029392"
    ],
    "tgn:id":2023885,
    "tgn:name":"Pedenville",
    "tgn:placetype":[
        "aat:300008347",
        "aat:300387210"
    ]
},
  "bbox": [],
  "geometry": {"coordinates":[-84.4833,33.1167],"type":"Point"}
}