{
  "id": 7033671,
  "type": "Feature",
  "properties": {
    "tgn:hierarchy":[
        "tgn:7033671",
        "tgn:7003129",
        "tgn:1000003",
        "tgn:7008516",
        "tgn:1000080",
        "tgn:7029392"
    ],
    "tgn:id":7033671,
    "tgn:name":"San Giovanni in Compito",
    "tgn:placetype":[
        "aat:300008347"
    ]
},
  "bbox": [],
  "geometry": {"coordinates":[12.375833,44.088611],"type":"Point"}
}