{
  "id": 2597184,
  "type": "Feature",
  "properties": {
    "tgn:hierarchy":[
        "tgn:2597184",
        "tgn:1000001",
        "tgn:7012149",
        "tgn:2002035",
        "tgn:7007826",
        "tgn:7029392"
    ],
    "tgn:id":2597184,
    "tgn:name":"Pozo Tank",
    "tgn:placetype":[
        "aat:300006191"
    ]
},
  "bbox": [],
  "geometry": {"coordinates":[-98.75,28.2667],"type":"Point"}
}