<<<<<<< HEAD
{
  "id": 2259536,
  "type": "Feature",
  "properties": {
    "tgn:hierarchy":[
        "tgn:2259536",
        "tgn:1000001",
        "tgn:7006451",
        "tgn:7012149",
        "tgn:2000098",
        "tgn:7029392"
    ],
    "tgn:id":2259536,
    "tgn:name":"Cottonwood Wash",
    "tgn:placetype":[
        "aat:300008699"
    ]
},
  "bbox": [],
  "geometry": {"coordinates":[-112.8667,36.9],"type":"Point"}
}
=======
{"geometry":{"type":"Point","coordinates":[-112.866700,36.900000]},"type":"Feature","properties":{"hierarchy":["tgn:2259536","tgn:1000001","tgn:7006451","tgn:7012149","tgn:2000098","tgn:7029392"],"placetype":["aat:300008699"],"id":2259536,"name:xx":"Cottonwood Wash"}}
>>>>>>> 03f74aca74312dbeaf24d7e61306dd6a786dc3d0
