<<<<<<< HEAD
{
  "id": 7477909,
  "type": "Feature",
  "properties": {
    "tgn:hierarchy":[
        "tgn:7477909",
        "tgn:1000004",
        "tgn:7467799",
        "tgn:1000141",
        "tgn:7029392"
    ],
    "tgn:id":7477909,
    "tgn:name":"Yongjing Guoxiao",
    "tgn:placetype":[
        "aat:300006495"
    ]
},
  "bbox": [],
  "geometry": {"coordinates":[120.547746,23.920855],"type":"Point"}
}
=======
{"geometry":{"type":"Point","coordinates":[120.547746,23.920855]},"type":"Feature","properties":{"hierarchy":["tgn:7477909","tgn:1000004","tgn:7467799","tgn:1000141","tgn:7029392"],"placetype":["aat:300006495"],"id":7477909,"name:xx":"Yongjing Guoxiao"}}
>>>>>>> 03f74aca74312dbeaf24d7e61306dd6a786dc3d0
