{
  "id": 2758664,
  "type": "Feature",
  "properties": {
    "tgn:hierarchy":[
        "tgn:2758664",
        "tgn:1000001",
        "tgn:7012149",
        "tgn:7007708",
        "tgn:7029392"
    ],
    "tgn:id":2758664,
    "tgn:name":"West Creek",
    "tgn:placetype":[
        "aat:300008706"
    ]
},
  "bbox": [],
  "geometry": {"coordinates":[-123.3833,46.0833],"type":"Point"}
}