<<<<<<< HEAD
{
  "id": 7367610,
  "type": "Feature",
  "properties": {
    "tgn:hierarchy":[
        "tgn:7367610",
        "tgn:7005585",
        "tgn:1000001",
        "tgn:7005560",
        "tgn:7029392"
    ],
    "tgn:id":7367610,
    "tgn:name":"Estrella, Cerro",
    "tgn:placetype":[
        "aat:300008795"
    ]
},
  "bbox": [],
  "geometry": {"coordinates":[-100.766667,17.916667],"type":"Point"}
}
=======
{"geometry":{"type":"Point","coordinates":[-100.766667,17.916667]},"type":"Feature","properties":{"hierarchy":["tgn:7367610","tgn:7005585","tgn:1000001","tgn:7005560","tgn:7029392"],"placetype":["aat:300008795"],"id":7367610,"name:xx":"Estrella, Cerro"}}
>>>>>>> 03f74aca74312dbeaf24d7e61306dd6a786dc3d0
