{
  "id": 7432190,
  "type": "Feature",
  "properties": {
    "tgn:hierarchy":[
        "tgn:7432190",
        "tgn:1000001",
        "tgn:7005595",
        "tgn:7005560",
        "tgn:7029392"
    ],
    "tgn:id":7432190,
    "tgn:name":"Guamuchil",
    "tgn:placetype":[
        "aat:300008347"
    ]
},
  "bbox": [],
  "geometry": {"coordinates":[-106.066667,23.65],"type":"Point"}
}