<<<<<<< HEAD
{
  "id": 2258359,
  "type": "Feature",
  "properties": {
    "tgn:hierarchy":[
        "tgn:2258359",
        "tgn:1000001",
        "tgn:7012149",
        "tgn:7007252",
        "tgn:7029392"
    ],
    "tgn:id":2258359,
    "tgn:name":"Cotton Branch",
    "tgn:placetype":[
        "aat:300008699"
    ]
},
  "bbox": [],
  "geometry": {"coordinates":[-86.7167,39.6],"type":"Point"}
}
=======
{"geometry":{"type":"Point","coordinates":[-86.716700,39.600000]},"type":"Feature","properties":{"hierarchy":["tgn:2258359","tgn:1000001","tgn:7012149","tgn:7007252","tgn:7029392"],"placetype":["aat:300008699"],"id":2258359,"name:xx":"Cotton Branch"}}
>>>>>>> 03f74aca74312dbeaf24d7e61306dd6a786dc3d0
