{
  "id": 7424804,
  "type": "Feature",
  "properties": {
    "tgn:hierarchy":[
        "tgn:7424804",
        "tgn:1000001",
        "tgn:7005597",
        "tgn:7005560",
        "tgn:7029392"
    ],
    "tgn:id":7424804,
    "tgn:name":"El Alto del Chaparral",
    "tgn:placetype":[
        "aat:300008347"
    ]
},
  "bbox": [],
  "geometry": {"coordinates":[-98.716667,24.766667],"type":"Point"}
}