{
  "id": 7498478,
  "type": "Feature",
  "properties": {
    "tgn:hierarchy":[
        "tgn:7498478",
        "tgn:1000004",
        "tgn:7491221",
        "tgn:1000141",
        "tgn:7029392"
    ],
    "tgn:id":7498478,
    "tgn:name":"Shanli Yihao Qiao",
    "tgn:placetype":[
        "aat:300007836"
    ]
},
  "bbox": [],
  "geometry": {"coordinates":[121.130729,22.880249],"type":"Point"}
}