<<<<<<< HEAD
{
  "id": 2407541,
  "type": "Feature",
  "properties": {
    "tgn:hierarchy":[
        "tgn:2407541",
        "tgn:1000001",
        "tgn:7012149",
        "tgn:1002811",
        "tgn:7007706",
        "tgn:7029392"
    ],
    "tgn:id":2407541,
    "tgn:name":"Huntstown",
    "tgn:placetype":[
        "aat:300008347"
    ]
},
  "bbox": [],
  "geometry": {"coordinates":[-84.3,41.0],"type":"Point"}
}
=======
{"geometry":{"type":"Point","coordinates":[-84.300000,41.000000]},"type":"Feature","properties":{"hierarchy":["tgn:2407541","tgn:1000001","tgn:7012149","tgn:1002811","tgn:7007706","tgn:7029392"],"placetype":["aat:300008347"],"id":2407541,"name:xx":"Huntstown"}}
>>>>>>> 03f74aca74312dbeaf24d7e61306dd6a786dc3d0
