{
  "id": 7583867,
  "type": "Feature",
  "properties": {
    "tgn:hierarchy":[
        "tgn:7583867",
        "tgn:1000004",
        "tgn:7000198",
        "tgn:1001894",
        "tgn:7029392"
    ],
    "tgn:id":7583867,
    "tgn:name:en":"Keshri Protected Forest",
    "tgn:placetype":[
        "aat:300008865"
    ]
},
  "bbox": [],
  "geometry": {"coordinates":[78.761396,25.105166],"type":"Point"}
}