<<<<<<< HEAD
{
  "id": 7372447,
  "type": "Feature",
  "properties": {
    "tgn:hierarchy":[
        "tgn:7372447",
        "tgn:7005581",
        "tgn:1000001",
        "tgn:7005560",
        "tgn:7029392"
    ],
    "tgn:id":7372447,
    "tgn:name":"Rancho La Esperanza",
    "tgn:placetype":[
        "aat:300000241"
    ]
},
  "bbox": [],
  "geometry": {"coordinates":[-105.566667,29.983333],"type":"Point"}
}
=======
{"geometry":{"type":"Point","coordinates":[-105.566667,29.983333]},"type":"Feature","properties":{"hierarchy":["tgn:7372447","tgn:7005581","tgn:1000001","tgn:7005560","tgn:7029392"],"placetype":["aat:300000241"],"id":7372447,"name:xx":"Rancho La Esperanza"}}
>>>>>>> 03f74aca74312dbeaf24d7e61306dd6a786dc3d0
