<<<<<<< HEAD
{
  "id": 2331754,
  "type": "Feature",
  "properties": {
    "tgn:hierarchy":[
        "tgn:2331754",
        "tgn:1000001",
        "tgn:2001435",
        "tgn:7012149",
        "tgn:7007566",
        "tgn:7029392"
    ],
    "tgn:id":2331754,
    "tgn:name":"Fleming Tank",
    "tgn:placetype":[
        "aat:300006191"
    ]
},
  "bbox": [],
  "geometry": {"coordinates":[-106.8333,32.7],"type":"Point"}
}
=======
{"geometry":{"type":"Point","coordinates":[-106.833300,32.700000]},"type":"Feature","properties":{"hierarchy":["tgn:2331754","tgn:1000001","tgn:2001435","tgn:7012149","tgn:7007566","tgn:7029392"],"placetype":["aat:300006191"],"id":2331754,"name:xx":"Fleming Tank"}}
>>>>>>> 03f74aca74312dbeaf24d7e61306dd6a786dc3d0
