{
  "id": 7108633,
  "type": "Feature",
  "properties": {
    "tgn:hierarchy":[
        "tgn:7108633",
        "tgn:1000003",
        "tgn:7003677",
        "tgn:7000084",
        "tgn:7029392"
    ],
    "tgn:id":7108633,
    "tgn:name":"Rei\u00df-Berg",
    "tgn:placetype":[
        "aat:300008777"
    ]
},
  "bbox": [],
  "geometry": {"coordinates":[7.766667,51.233333],"type":"Point"}
}