{
  "id": 2464045,
  "type": "Feature",
  "properties": {
    "tgn:hierarchy":[
        "tgn:2464045",
        "tgn:1000001",
        "tgn:7012149",
        "tgn:2002192",
        "tgn:7007919",
        "tgn:7029392"
    ],
    "tgn:id":2464045,
    "tgn:name":"Locust Branch",
    "tgn:placetype":[
        "aat:300008699"
    ]
},
  "bbox": [],
  "geometry": {"coordinates":[-81.5167,37.0167],"type":"Point"}
}