{
  "id": 2431095,
  "type": "Feature",
  "properties": {
    "tgn:hierarchy":[
        "tgn:2431095",
        "tgn:1000001",
        "tgn:7012149",
        "tgn:7018871",
        "tgn:7007920",
        "tgn:7029392"
    ],
    "tgn:id":2431095,
    "tgn:name":"Kanim Creek",
    "tgn:placetype":[
        "aat:300008706"
    ]
},
  "bbox": [],
  "geometry": {"coordinates":[-122.05,47.5833],"type":"Point"}
}