{
  "id": 2610340,
  "type": "Feature",
  "properties": {
    "tgn:hierarchy":[
        "tgn:2610340",
        "tgn:1000001",
        "tgn:2000470",
        "tgn:7012149",
        "tgn:7007250",
        "tgn:7029392"
    ],
    "tgn:id":2610340,
    "tgn:name":"Red Butte",
    "tgn:placetype":[
        "aat:300008798"
    ]
},
  "bbox": [],
  "geometry": {"coordinates":[-114.3167,44.6333],"type":"Point"}
}