{
  "id": 2607634,
  "type": "Feature",
  "properties": {
    "tgn:hierarchy":[
        "tgn:2607634",
        "tgn:1000001",
        "tgn:7012149",
        "tgn:2002248",
        "tgn:7007920",
        "tgn:7029392"
    ],
    "tgn:id":2607634,
    "tgn:name":"Rapids Creek",
    "tgn:placetype":[
        "aat:300008706"
    ]
},
  "bbox": [],
  "geometry": {"coordinates":[-117.0667,48.5833],"type":"Point"}
}