{
  "id": 7237213,
  "type": "Feature",
  "properties": {
    "tgn:hierarchy":[
        "tgn:7237213",
        "tgn:7002715",
        "tgn:7002730",
        "tgn:1000003",
        "tgn:1000074",
        "tgn:7029392"
    ],
    "tgn:id":7237213,
    "tgn:name":"Kastano\u00fassis, Di\u00e1vasis",
    "tgn:placetype":[
        "aat:300259572"
    ]
},
  "bbox": [],
  "geometry": {"coordinates":[22.894722,41.272778],"type":"Point"}
}