{
  "id": 7272656,
  "type": "Feature",
  "properties": {
    "tgn:hierarchy":[
        "tgn:7272656",
        "tgn:1000003",
        "tgn:7003626",
        "tgn:7016845",
        "tgn:7029392"
    ],
    "tgn:id":7272656,
    "tgn:name:nl":"Voorst",
    "tgn:placetype":[
        "aat:300008347"
    ]
},
  "bbox": [],
  "geometry": {"coordinates":[6.05,52.516667],"type":"Point"}
}