{
  "id": 7291840,
  "type": "Feature",
  "properties": {
    "tgn:hierarchy":[
        "tgn:7291840",
        "tgn:7002464",
        "tgn:1000049",
        "tgn:1000002",
        "tgn:7029392"
    ],
    "tgn:id":7291840,
    "tgn:name":"Flor de Tarapac\u00e1, Cerro",
    "tgn:placetype":[
        "aat:300008795"
    ]
},
  "bbox": [],
  "geometry": {"coordinates":[-68.866667,-20.866667],"type":"Point"}
}