{
  "id": 2451926,
  "type": "Feature",
  "properties": {
    "tgn:hierarchy":[
        "tgn:2451926",
        "tgn:1000001",
        "tgn:7012149",
        "tgn:2000352",
        "tgn:7007248",
        "tgn:7029392"
    ],
    "tgn:id":2451926,
    "tgn:name":"Little Bee Mountain",
    "tgn:placetype":[
        "aat:300008798"
    ]
},
  "bbox": [],
  "geometry": {"coordinates":[-84.3667,34.75],"type":"Point"}
}