{
  "id": 7559110,
  "type": "Feature",
  "properties": {
    "tgn:hierarchy":[
        "tgn:7559110",
        "tgn:1000004",
        "tgn:1001871",
        "tgn:7000198",
        "tgn:7029392"
    ],
    "tgn:id":7559110,
    "tgn:name:en":"Ris\u0101liya Khera",
    "tgn:placetype":[
        "aat:300008347"
    ]
},
  "bbox": [],
  "geometry": {"coordinates":[74.763706,29.713436],"type":"Point"}
}