{
  "id": 1000888,
  "type": "Feature",
  "properties": {
    "tgn:hierarchy":[
        "tgn:1000888",
        "tgn:7001242",
        "tgn:1000149",
        "tgn:7029392"
    ],
    "tgn:id":1000888,
    "tgn:name":"Malanje",
    "tgn:placetype":[
        "aat:300387064",
        "aat:300000774"
    ]
},
  "bbox": [],
  "geometry": {"coordinates":[16.825,-9.675],"type":"Point"}
}