{
  "id": 2041499,
  "type": "Feature",
  "properties": {
    "tgn:hierarchy":[
        "tgn:2041499",
        "tgn:1000001",
        "tgn:7012149",
        "tgn:2000827",
        "tgn:7007255",
        "tgn:7029392"
    ],
    "tgn:id":2041499,
    "tgn:name":"Stringtown",
    "tgn:placetype":[
        "aat:300008347"
    ]
},
  "bbox": [],
  "geometry": {"coordinates":[-84.8167,37.7667],"type":"Point"}
}