{
  "id": 7270338,
  "type": "Feature",
  "properties": {
    "tgn:hierarchy":[
        "tgn:7270338",
        "tgn:7003616",
        "tgn:1000003",
        "tgn:7016845",
        "tgn:7029392"
    ],
    "tgn:id":7270338,
    "tgn:name:nl":"Nesserduinen",
    "tgn:placetype":[
        "aat:300008750"
    ]
},
  "bbox": [],
  "geometry": {"coordinates":[5.766667,53.45],"type":"Point"}
}