<<<<<<< HEAD
{
  "id": 7117925,
  "type": "Feature",
  "properties": {
    "tgn:hierarchy":[
        "tgn:7117925",
        "tgn:7003712",
        "tgn:7003670",
        "tgn:1000003",
        "tgn:7000084",
        "tgn:7029392"
    ],
    "tgn:id":7117925,
    "tgn:name":"Der Obersee",
    "tgn:placetype":[
        "aat:300008680"
    ]
},
  "bbox": [],
  "geometry": {"coordinates":[13.5,52.55],"type":"Point"}
}
=======
{"geometry":{"type":"Point","coordinates":[13.500000,52.550000]},"type":"Feature","properties":{"hierarchy":["tgn:7117925","tgn:7003712","tgn:7003670","tgn:1000003","tgn:7000084","tgn:7029392"],"placetype":["aat:300008680"],"id":7117925,"name:xx":"Der Obersee"}}
>>>>>>> 03f74aca74312dbeaf24d7e61306dd6a786dc3d0
