{
  "id": 7416717,
  "type": "Feature",
  "properties": {
    "tgn:hierarchy":[
        "tgn:7416717",
        "tgn:7005584",
        "tgn:1000001",
        "tgn:7005560",
        "tgn:7029392"
    ],
    "tgn:id":7416717,
    "tgn:name":"La Tinaja del Toro",
    "tgn:placetype":[
        "aat:300008347"
    ]
},
  "bbox": [],
  "geometry": {"coordinates":[-101.765556,20.618056],"type":"Point"}
}