{
  "id": 2767947,
  "type": "Feature",
  "properties": {
    "tgn:hierarchy":[
        "tgn:2767947",
        "tgn:1000001",
        "tgn:7012149",
        "tgn:1002611",
        "tgn:7007706",
        "tgn:7029392"
    ],
    "tgn:id":2767947,
    "tgn:name":"Whitemeir Ditch",
    "tgn:placetype":[
        "aat:300006075"
    ]
},
  "bbox": [],
  "geometry": {"coordinates":[-83.7667,41.4833],"type":"Point"}
}