<<<<<<< HEAD
{
  "id": 2767947,
  "type": "Feature",
  "properties": {
    "tgn:hierarchy":[
        "tgn:2767947",
        "tgn:1000001",
        "tgn:7012149",
        "tgn:1002611",
        "tgn:7007706",
        "tgn:7029392"
    ],
    "tgn:id":2767947,
    "tgn:name":"Whitemeir Ditch",
    "tgn:placetype":[
        "aat:300006075"
    ]
},
  "bbox": [],
  "geometry": {"coordinates":[-83.7667,41.4833],"type":"Point"}
}
=======
{"geometry":{"type":"Point","coordinates":[-83.766700,41.483300]},"type":"Feature","properties":{"hierarchy":["tgn:2767947","tgn:1000001","tgn:7012149","tgn:1002611","tgn:7007706","tgn:7029392"],"placetype":["aat:300006075"],"id":2767947,"name:xx":"Whitemeir Ditch"}}
>>>>>>> 03f74aca74312dbeaf24d7e61306dd6a786dc3d0
