{
  "id": 7507806,
  "type": "Feature",
  "properties": {
    "tgn:hierarchy":[
        "tgn:7507806",
        "tgn:1009227",
        "tgn:1000226",
        "tgn:7018437",
        "tgn:1000006",
        "tgn:7029392"
    ],
    "tgn:id":7507806,
    "tgn:name:en":"Pilot Point",
    "tgn:placetype":[
        "aat:300386846"
    ]
},
  "bbox": [],
  "geometry": {"coordinates":[170.666667,-45.766667],"type":"Point"}
}