{
  "id": 2712549,
  "type": "Feature",
  "properties": {
    "tgn:hierarchy":[
        "tgn:2712549",
        "tgn:1000001",
        "tgn:7012149",
        "tgn:2001537",
        "tgn:7007709",
        "tgn:7029392"
    ],
    "tgn:id":2712549,
    "tgn:name":"Taylor Branch",
    "tgn:placetype":[
        "aat:300008699"
    ]
},
  "bbox": [],
  "geometry": {"coordinates":[-81.75,35.45],"type":"Point"}
}