{
  "id": 7219386,
  "type": "Feature",
  "properties": {
    "tgn:hierarchy":[
        "tgn:7219386",
        "tgn:7011161",
        "tgn:7002674",
        "tgn:1000003",
        "tgn:1000074",
        "tgn:7029392"
    ],
    "tgn:id":7219386,
    "tgn:name":"X\u00fdlou, Vr\u00e1choi",
    "tgn:placetype":[
        "aat:300011692"
    ]
},
  "bbox": [],
  "geometry": {"coordinates":[25.868889,38.2375],"type":"Point"}
}