{
  "id": 1046588,
  "type": "Feature",
  "properties": {
    "tgn:hierarchy":[
        "tgn:1046588",
        "tgn:1003455",
        "tgn:1000003",
        "tgn:7010380",
        "tgn:1000080",
        "tgn:7029392"
    ],
    "tgn:id":1046588,
    "tgn:name":"San Menaio",
    "tgn:placetype":[
        "aat:300008347"
    ]
},
  "bbox": [],
  "geometry": {"coordinates":[15.9667,41.9333],"type":"Point"}
}