{
  "id": 7469449,
  "type": "Feature",
  "properties": {
    "tgn:hierarchy":[
        "tgn:7469449",
        "tgn:7488858",
        "tgn:1000004",
        "tgn:1000141",
        "tgn:7029392"
    ],
    "tgn:id":7469449,
    "tgn:name":"Xiaomao",
    "tgn:placetype":[
        "aat:300008347"
    ]
},
  "bbox": [],
  "geometry": {"coordinates":[120.794719,23.88039],"type":"Point"}
}