<<<<<<< HEAD
{
  "id": 7021768,
  "type": "Feature",
  "properties": {
    "tgn:hierarchy":[
        "tgn:7021768",
        "tgn:1000001",
        "tgn:7012149",
        "tgn:2001759",
        "tgn:7007712",
        "tgn:7029392"
    ],
    "tgn:id":7021768,
    "tgn:name":"Red Bluff Lake",
    "tgn:placetype":[
        "aat:300006191"
    ]
},
  "bbox": [],
  "geometry": {"coordinates":[-79.5,34.6],"type":"Point"}
}
=======
{"geometry":{"type":"Point","coordinates":[-79.500000,34.600000]},"type":"Feature","properties":{"hierarchy":["tgn:7021768","tgn:1000001","tgn:7012149","tgn:2001759","tgn:7007712","tgn:7029392"],"placetype":["aat:300006191"],"id":7021768,"name:xx":"Red Bluff Lake"}}
>>>>>>> 03f74aca74312dbeaf24d7e61306dd6a786dc3d0
