{
  "id": 7072651,
  "type": "Feature",
  "properties": {
    "tgn:hierarchy":[
        "tgn:7072651",
        "tgn:7003669",
        "tgn:1000003",
        "tgn:7000084",
        "tgn:7029392"
    ],
    "tgn:id":7072651,
    "tgn:name":"Tappenbach",
    "tgn:placetype":[
        "aat:300008699"
    ]
},
  "bbox": [],
  "geometry": {"coordinates":[10.983333,49.766667],"type":"Point"}
}