{
  "id": 7528946,
  "type": "Feature",
  "properties": {
    "tgn:hierarchy":[
        "tgn:7528946",
        "tgn:7001242",
        "tgn:1001059",
        "tgn:7016833",
        "tgn:7029392"
    ],
    "tgn:id":7528946,
    "tgn:name":"Tafahnah al Ashr\u0101f",
    "tgn:placetype":[
        "aat:300008347"
    ]
},
  "bbox": [],
  "geometry": {"coordinates":[31.345722,30.668263],"type":"Point"}
}