{
  "id": 1013652,
  "type": "Feature",
  "properties": {
    "tgn:hierarchy":[
        "tgn:1013652",
        "tgn:7005735",
        "tgn:7005685",
        "tgn:1000001",
        "tgn:7029392"
    ],
    "tgn:id":1013652,
    "tgn:name":"Nithi River",
    "tgn:placetype":[
        "aat:300008347"
    ]
},
  "bbox": [],
  "geometry": {"coordinates":[-124.9667,53.9833],"type":"Point"}
}