{
  "id": 1018385,
  "type": "Feature",
  "properties": {
    "tgn:hierarchy":[
        "tgn:1018385",
        "tgn:1000001",
        "tgn:7005590",
        "tgn:7005560",
        "tgn:7029392"
    ],
    "tgn:id":1018385,
    "tgn:name":"Tanhuato",
    "tgn:placetype":[
        "aat:300008347"
    ]
},
  "bbox": [],
  "geometry": {"coordinates":[-102.333333,20.283333],"type":"Point"}
}