{
  "id": 7476214,
  "type": "Feature",
  "properties": {
    "tgn:hierarchy":[
        "tgn:7476214",
        "tgn:1000004",
        "tgn:7489179",
        "tgn:1000141",
        "tgn:7029392"
    ],
    "tgn:id":7476214,
    "tgn:name":"Changlinglu",
    "tgn:placetype":[
        "aat:300008347"
    ]
},
  "bbox": [],
  "geometry": {"coordinates":[121.622507,24.684245],"type":"Point"}
}