{
  "id": 2220040,
  "type": "Feature",
  "properties": {
    "tgn:hierarchy":[
        "tgn:2220040",
        "tgn:1000001",
        "tgn:7012149",
        "tgn:2002028",
        "tgn:7007826",
        "tgn:7029392"
    ],
    "tgn:id":2220040,
    "tgn:name":"Canyon Creek",
    "tgn:placetype":[
        "aat:300008706"
    ]
},
  "bbox": [],
  "geometry": {"coordinates":[-100.15,36.0667],"type":"Point"}
}