{
  "id": 1107103,
  "type": "Feature",
  "properties": {
    "tgn:hierarchy":[
        "tgn:1107103",
        "tgn:1000001",
        "tgn:2001411",
        "tgn:7012149",
        "tgn:7007526",
        "tgn:7029392"
    ],
    "tgn:id":1107103,
    "tgn:name":"Antelope Peak",
    "tgn:placetype":[
        "aat:300008798"
    ]
},
  "bbox": [],
  "geometry": {"coordinates":[-114.9667,41.3167],"type":"Point"}
}