{
  "id": 7186924,
  "type": "Feature",
  "properties": {
    "tgn:hierarchy":[
        "tgn:7186924",
        "tgn:1000003",
        "tgn:7003685",
        "tgn:7000084",
        "tgn:7029392"
    ],
    "tgn:id":7186924,
    "tgn:name":"Gold Berg",
    "tgn:placetype":[
        "aat:300008777"
    ]
},
  "bbox": [],
  "geometry": {"coordinates":[13.366667,50.883333],"type":"Point"}
}