{
  "id": 2610986,
  "type": "Feature",
  "properties": {
    "tgn:hierarchy":[
        "tgn:2610986",
        "tgn:1000001",
        "tgn:7012149",
        "tgn:2001538",
        "tgn:7007709",
        "tgn:7029392"
    ],
    "tgn:id":2610986,
    "tgn:name":"Red Hill",
    "tgn:placetype":[
        "aat:300008347"
    ]
},
  "bbox": [],
  "geometry": {"coordinates":[-78.3833,35.1333],"type":"Point"}
}