{
  "id": 2200392,
  "type": "Feature",
  "properties": {
    "tgn:hierarchy":[
        "tgn:2200392",
        "tgn:1000001",
        "tgn:7012149",
        "tgn:1002526",
        "tgn:7007826",
        "tgn:7029392"
    ],
    "tgn:id":2200392,
    "tgn:name":"Brushy Knob",
    "tgn:placetype":[
        "aat:300008798"
    ]
},
  "bbox": [],
  "geometry": {"coordinates":[-97.4167,32.45],"type":"Point"}
}