{
  "id": 7590517,
  "type": "Feature",
  "properties": {
    "tgn:hierarchy":[
        "tgn:7590517",
        "tgn:1000004",
        "tgn:7000198",
        "tgn:7016722",
        "tgn:7029392"
    ],
    "tgn:id":7590517,
    "tgn:name:en":"J\u0101farpur",
    "tgn:placetype":[
        "aat:300008347"
    ]
},
  "bbox": [],
  "geometry": {"coordinates":[77.322299,29.631077],"type":"Point"}
}