{
  "id": 7285861,
  "type": "Feature",
  "properties": {
    "tgn:hierarchy":[
        "tgn:7285861",
        "tgn:7002464",
        "tgn:1000049",
        "tgn:1000002",
        "tgn:7029392"
    ],
    "tgn:id":7285861,
    "tgn:name":"Pichican, Cerro",
    "tgn:placetype":[
        "aat:300008795"
    ]
},
  "bbox": [],
  "geometry": {"coordinates":[-69.166667,-18.616667],"type":"Point"}
}