{
  "id": 7162410,
  "type": "Feature",
  "properties": {
    "tgn:hierarchy":[
        "tgn:7162410",
        "tgn:1000003",
        "tgn:7000094",
        "tgn:7000084",
        "tgn:7029392"
    ],
    "tgn:id":7162410,
    "tgn:name":"Innenreede",
    "tgn:placetype":[
        "aat:300008217"
    ]
},
  "bbox": [],
  "geometry": {"coordinates":[11.366667,53.966667],"type":"Point"}
}