{
  "id": 2195783,
  "type": "Feature",
  "properties": {
    "tgn:hierarchy":[
        "tgn:2195783",
        "tgn:1000001",
        "tgn:1002233",
        "tgn:7012149",
        "tgn:7007710",
        "tgn:7029392"
    ],
    "tgn:id":2195783,
    "tgn:name":"Broad Run",
    "tgn:placetype":[
        "aat:300008699"
    ]
},
  "bbox": [],
  "geometry": {"coordinates":[-75.8833,40.8833],"type":"Point"}
}