{
  "id": 2250319,
  "type": "Feature",
  "properties": {
    "tgn:hierarchy":[
        "tgn:2250319",
        "tgn:1000001",
        "tgn:7012149",
        "tgn:1002974",
        "tgn:7007251",
        "tgn:7029392"
    ],
    "tgn:id":2250319,
    "tgn:name":"Collison Branch",
    "tgn:placetype":[
        "aat:300008699"
    ]
},
  "bbox": [],
  "geometry": {"coordinates":[-87.8167,40.1833],"type":"Point"}
}