{
  "id": 7485737,
  "type": "Feature",
  "properties": {
    "tgn:hierarchy":[
        "tgn:7485737",
        "tgn:1000004",
        "tgn:7490934",
        "tgn:1000141",
        "tgn:7029392"
    ],
    "tgn:id":7485737,
    "tgn:name":"Jianye Guoxiao",
    "tgn:placetype":[
        "aat:300006495"
    ]
},
  "bbox": [],
  "geometry": {"coordinates":[120.202222,22.976389],"type":"Point"}
}