{
  "id": 2768348,
  "type": "Feature",
  "properties": {
    "tgn:hierarchy":[
        "tgn:2768348",
        "tgn:1000001",
        "tgn:2001184",
        "tgn:7012149",
        "tgn:7007523",
        "tgn:7029392"
    ],
    "tgn:id":2768348,
    "tgn:name":"Whiteside Lake",
    "tgn:placetype":[
        "aat:300008680"
    ]
},
  "bbox": [],
  "geometry": {"coordinates":[-92.95,39.3667],"type":"Point"}
}