{
  "id": 1070648,
  "type": "Feature",
  "properties": {
    "tgn:hierarchy":[
        "tgn:1070648",
        "tgn:1000004",
        "tgn:1000958",
        "tgn:1000111",
        "tgn:7029392"
    ],
    "tgn:id":1070648,
    "tgn:name":"Nansunzhai",
    "tgn:placetype":[
        "aat:300008347"
    ]
},
  "bbox": [],
  "geometry": {"coordinates":[121.45,31.35],"type":"Point"}
}