{
  "id": 2203343,
  "type": "Feature",
  "properties": {
    "tgn:hierarchy":[
        "tgn:2203343",
        "tgn:1000001",
        "tgn:7012149",
        "tgn:2000494",
        "tgn:7007250",
        "tgn:7029392"
    ],
    "tgn:id":2203343,
    "tgn:name":"Buckhorn Mountain Lake",
    "tgn:placetype":[
        "aat:300008680"
    ]
},
  "bbox": [],
  "geometry": {"coordinates":[-115.8667,44.8667],"type":"Point"}
}