{
  "id": 7520518,
  "type": "Feature",
  "properties": {
    "tgn:hierarchy":[
        "tgn:7520518",
        "tgn:7001242",
        "tgn:7001311",
        "tgn:7016833",
        "tgn:7029392"
    ],
    "tgn:id":7520518,
    "tgn:name:en":"Ab\u016b Urayk\u012b, Mars\u00e1",
    "tgn:placetype":[
        "aat:300132317"
    ]
},
  "bbox": [],
  "geometry": {"coordinates":[34.803817,25.217282],"type":"Point"}
}