{
  "id": 7294492,
  "type": "Feature",
  "properties": {
    "tgn:hierarchy":[
        "tgn:7294492",
        "tgn:7002803",
        "tgn:1001647",
        "tgn:1000003",
        "tgn:1000095",
        "tgn:7029392"
    ],
    "tgn:id":7294492,
    "tgn:name":"Ventas de Alcolea",
    "tgn:placetype":[
        "aat:300008347"
    ]
},
  "bbox": [],
  "geometry": {"coordinates":[-2.433333,39.283333],"type":"Point"}
}