<<<<<<< HEAD
{
  "id": 2404911,
  "type": "Feature",
  "properties": {
    "tgn:hierarchy":[
        "tgn:2404911",
        "tgn:1000001",
        "tgn:7016172",
        "tgn:7012149",
        "tgn:2000153",
        "tgn:7029392"
    ],
    "tgn:id":2404911,
    "tgn:name":"Huddleston",
    "tgn:placetype":[
        "aat:300008347"
    ]
},
  "bbox": [],
  "geometry": {"coordinates":[-93.8333,34.5833],"type":"Point"}
}
=======
{"geometry":{"type":"Point","coordinates":[-93.833300,34.583300]},"type":"Feature","properties":{"hierarchy":["tgn:2404911","tgn:1000001","tgn:7016172","tgn:7012149","tgn:2000153","tgn:7029392"],"placetype":["aat:300008347"],"id":2404911,"name:xx":"Huddleston"}}
>>>>>>> 03f74aca74312dbeaf24d7e61306dd6a786dc3d0
