{
  "id": 2458639,
  "type": "Feature",
  "properties": {
    "tgn:hierarchy":[
        "tgn:2458639",
        "tgn:1000001",
        "tgn:7012149",
        "tgn:1002392",
        "tgn:7007157",
        "tgn:7029392"
    ],
    "tgn:id":2458639,
    "tgn:name":"Little Oak Spring",
    "tgn:placetype":[
        "aat:300008697"
    ]
},
  "bbox": [],
  "geometry": {"coordinates":[-120.3833,36.3333],"type":"Point"}
}