{
  "id": 7133857,
  "type": "Feature",
  "properties": {
    "tgn:hierarchy":[
        "tgn:7133857",
        "tgn:1000003",
        "tgn:7003687",
        "tgn:7000084",
        "tgn:7029392"
    ],
    "tgn:id":7133857,
    "tgn:name":"M\u00fchlberg",
    "tgn:placetype":[
        "aat:300008777"
    ]
},
  "bbox": [],
  "geometry": {"coordinates":[11.433333,51.183333],"type":"Point"}
}