{
  "id": 7576555,
  "type": "Feature",
  "properties": {
    "tgn:hierarchy":[
        "tgn:7576555",
        "tgn:1001828",
        "tgn:1000004",
        "tgn:7000198",
        "tgn:7029392"
    ],
    "tgn:id":7576555,
    "tgn:name:en":"Kotepalli",
    "tgn:placetype":[
        "aat:300008347"
    ]
},
  "bbox": [],
  "geometry": {"coordinates":[77.75,17.383333],"type":"Point"}
}