{
  "id": 2271561,
  "type": "Feature",
  "properties": {
    "tgn:hierarchy":[
        "tgn:2271561",
        "tgn:1000001",
        "tgn:7012149",
        "tgn:2001722",
        "tgn:7007708",
        "tgn:7029392"
    ],
    "tgn:id":2271561,
    "tgn:name":"Cumming Gulch",
    "tgn:placetype":[
        "aat:300008761"
    ]
},
  "bbox": [],
  "geometry": {"coordinates":[-116.9833,45.35],"type":"Point"}
}