{
  "id": 2405519,
  "type": "Feature",
  "properties": {
    "tgn:hierarchy":[
        "tgn:2405519",
        "tgn:1000001",
        "tgn:7012149",
        "tgn:7007826",
        "tgn:7029392"
    ],
    "tgn:id":2405519,
    "tgn:name":"Hughes Creek",
    "tgn:placetype":[
        "aat:300008706"
    ]
},
  "bbox": [],
  "geometry": {"coordinates":[-94.65,33.0167],"type":"Point"}
}