{
  "id": 2347961,
  "type": "Feature",
  "properties": {
    "tgn:hierarchy":[
        "tgn:2347961",
        "tgn:1000001",
        "tgn:7012149",
        "tgn:2000206",
        "tgn:7007158",
        "tgn:7029392"
    ],
    "tgn:id":2347961,
    "tgn:name":"German Creek Springs",
    "tgn:placetype":[
        "aat:300008697"
    ]
},
  "bbox": [],
  "geometry": {"coordinates":[-107.5167,38.8333],"type":"Point"}
}