{
  "id": 2100999,
  "type": "Feature",
  "properties": {
    "tgn:hierarchy":[
        "tgn:2100999",
        "tgn:1000001",
        "tgn:7012149",
        "tgn:2001850",
        "tgn:7007825",
        "tgn:7029392"
    ],
    "tgn:id":2100999,
    "tgn:name":"Pine Hill",
    "tgn:placetype":[
        "aat:300008347",
        "aat:300387210"
    ]
},
  "bbox": [],
  "geometry": {"coordinates":[-85.6333,36.5667],"type":"Point"}
}