{
  "id": 7398012,
  "type": "Feature",
  "properties": {
    "tgn:hierarchy":[
        "tgn:7398012",
        "tgn:1000001",
        "tgn:1001960",
        "tgn:7005560",
        "tgn:7029392"
    ],
    "tgn:id":7398012,
    "tgn:name":"El Compartidero, Ca\u00f1ada",
    "tgn:placetype":[
        "aat:300008773"
    ]
},
  "bbox": [],
  "geometry": {"coordinates":[-111.392222,30.918889],"type":"Point"}
}