{
  "id": 2102137,
  "type": "Feature",
  "properties": {
    "tgn:hierarchy":[
        "tgn:2102137",
        "tgn:1000001",
        "tgn:7012149",
        "tgn:2001851",
        "tgn:7007825",
        "tgn:7029392"
    ],
    "tgn:id":2102137,
    "tgn:name":"Wilsonville",
    "tgn:placetype":[
        "aat:300008347",
        "aat:300387210"
    ]
},
  "bbox": [],
  "geometry": {"coordinates":[-83.2333,35.9667],"type":"Point"}
}