{
  "id": 2577536,
  "type": "Feature",
  "properties": {
    "tgn:hierarchy":[
        "tgn:2577536",
        "tgn:1000001",
        "tgn:7012149",
        "tgn:2000220",
        "tgn:7007158",
        "tgn:7029392"
    ],
    "tgn:id":2577536,
    "tgn:name":"Peterson Ditch Number 1",
    "tgn:placetype":[
        "aat:300006075"
    ]
},
  "bbox": [],
  "geometry": {"coordinates":[-106.3833,40.6167],"type":"Point"}
}