{
  "id": 2287530,
  "type": "Feature",
  "properties": {
    "tgn:hierarchy":[
        "tgn:2287530",
        "tgn:1000001",
        "tgn:2002368",
        "tgn:7012149",
        "tgn:7007923",
        "tgn:7029392"
    ],
    "tgn:id":2287530,
    "tgn:name":"Difficulty Spring",
    "tgn:placetype":[
        "aat:300008697"
    ]
},
  "bbox": [],
  "geometry": {"coordinates":[-106.4167,42.1167],"type":"Point"}
}