{
  "id": 2439706,
  "type": "Feature",
  "properties": {
    "tgn:hierarchy":[
        "tgn:2439706",
        "tgn:7030515",
        "tgn:7006450",
        "tgn:1000001",
        "tgn:7012149",
        "tgn:7029392"
    ],
    "tgn:id":2439706,
    "tgn:name":"Kitchen Anchorage",
    "tgn:placetype":[
        "aat:300132316"
    ]
},
  "bbox": [],
  "geometry": {"coordinates":[-162.1167,55.1167],"type":"Point"}
}