{
  "id": 2673948,
  "type": "Feature",
  "properties": {
    "tgn:hierarchy":[
        "tgn:2673948",
        "tgn:1000001",
        "tgn:7012149",
        "tgn:7007157",
        "tgn:1002710",
        "tgn:7029392"
    ],
    "tgn:id":2673948,
    "tgn:name":"Snow Mountain Ditch",
    "tgn:placetype":[
        "aat:300006075"
    ]
},
  "bbox": [],
  "geometry": {"coordinates":[-120.9333,39.2667],"type":"Point"}
}