{
  "id": 2257128,
  "type": "Feature",
  "properties": {
    "tgn:hierarchy":[
        "tgn:2257128",
        "tgn:1000001",
        "tgn:7012149",
        "tgn:1002742",
        "tgn:7007920",
        "tgn:7029392"
    ],
    "tgn:id":2257128,
    "tgn:name":"Corner Butte",
    "tgn:placetype":[
        "aat:300008798"
    ]
},
  "bbox": [],
  "geometry": {"coordinates":[-118.9333,48.6167],"type":"Point"}
}