{
  "id": 7562910,
  "type": "Feature",
  "properties": {
    "tgn:hierarchy":[
        "tgn:7562910",
        "tgn:1000004",
        "tgn:7000198",
        "tgn:7016722",
        "tgn:7029392"
    ],
    "tgn:id":7562910,
    "tgn:name:en":"Tarwa",
    "tgn:placetype":[
        "aat:300008347"
    ]
},
  "bbox": [],
  "geometry": {"coordinates":[79.8021,27.0262],"type":"Point"}
}