{
  "id": 7165289,
  "type": "Feature",
  "properties": {
    "tgn:hierarchy":[
        "tgn:7165289",
        "tgn:1000003",
        "tgn:7003678",
        "tgn:7000084",
        "tgn:7029392"
    ],
    "tgn:id":7165289,
    "tgn:name":"Horwieden",
    "tgn:placetype":[
        "aat:300008347"
    ]
},
  "bbox": [],
  "geometry": {"coordinates":[9.75,50.566667],"type":"Point"}
}