{
  "id": 7047380,
  "type": "Feature",
  "properties": {
    "tgn:hierarchy":[
        "tgn:7047380",
        "tgn:1003505",
        "tgn:1000003",
        "tgn:7002993",
        "tgn:1000080",
        "tgn:7029392"
    ],
    "tgn:id":7047380,
    "tgn:name":"Gropada",
    "tgn:placetype":[
        "aat:300008347"
    ]
},
  "bbox": [],
  "geometry": {"coordinates":[13.850278,45.665833],"type":"Point"}
}