{
  "id": 7483964,
  "type": "Feature",
  "properties": {
    "tgn:hierarchy":[
        "tgn:7483964",
        "tgn:7001004",
        "tgn:1000004",
        "tgn:1000141",
        "tgn:7029392"
    ],
    "tgn:id":7483964,
    "tgn:name":"Taguoyan Shan",
    "tgn:placetype":[
        "aat:300008798"
    ]
},
  "bbox": [],
  "geometry": {"coordinates":[120.724722,23.18],"type":"Point"}
}