{
  "id": 7409576,
  "type": "Feature",
  "properties": {
    "tgn:hierarchy":[
        "tgn:7409576",
        "tgn:1000001",
        "tgn:7005590",
        "tgn:7005560",
        "tgn:7029392"
    ],
    "tgn:id":7409576,
    "tgn:name":"Tirimacuaro",
    "tgn:placetype":[
        "aat:300008347"
    ]
},
  "bbox": [],
  "geometry": {"coordinates":[-101.911111,20.108333],"type":"Point"}
}