{
  "id": 7197977,
  "type": "Feature",
  "properties": {
    "tgn:hierarchy":[
        "tgn:7197977",
        "tgn:1000003",
        "tgn:7003676",
        "tgn:7000084",
        "tgn:7029392"
    ],
    "tgn:id":7197977,
    "tgn:name":"Ehlbeck",
    "tgn:placetype":[
        "aat:300008347"
    ]
},
  "bbox": [],
  "geometry": {"coordinates":[10.15,53.083333],"type":"Point"}
}