{
  "id": 2276100,
  "type": "Feature",
  "properties": {
    "tgn:hierarchy":[
        "tgn:2276100",
        "tgn:1000001",
        "tgn:7012149",
        "tgn:2000734",
        "tgn:7007254",
        "tgn:7029392"
    ],
    "tgn:id":2276100,
    "tgn:name":"Darnells Creek",
    "tgn:placetype":[
        "aat:300008706"
    ]
},
  "bbox": [],
  "geometry": {"coordinates":[-96.3167,39.4333],"type":"Point"}
}