{
  "id": 1128585,
  "type": "Feature",
  "properties": {
    "tgn:hierarchy":[
        "tgn:1128585",
        "tgn:7001242",
        "tgn:7029392"
    ],
    "tgn:id":1128585,
    "tgn:name":"Phepane",
    "tgn:placetype":[
        "aat:300008707"
    ]
},
  "bbox": [],
  "geometry": {"coordinates":[22.75,-25.8333],"type":"Point"}
}