{
  "id": 2000831,
  "type": "Feature",
  "properties": {
    "tgn:hierarchy":[
        "tgn:2000831",
        "tgn:1000001",
        "tgn:7012149",
        "tgn:7007255",
        "tgn:7029392"
    ],
    "tgn:id":2000831,
    "tgn:name":"Morgan",
    "tgn:placetype":[
        "aat:300387145",
        "aat:300000771"
    ]
},
  "bbox": [],
  "geometry": {"coordinates":[-83.2667,37.9167],"type":"Point"}
}