{
  "id": 7581573,
  "type": "Feature",
  "properties": {
    "tgn:hierarchy":[
        "tgn:7581573",
        "tgn:1000004",
        "tgn:7000198",
        "tgn:7031783",
        "tgn:7029392"
    ],
    "tgn:id":7581573,
    "tgn:name:en":"Silwai",
    "tgn:placetype":[
        "aat:300008347"
    ]
},
  "bbox": [],
  "geometry": {"coordinates":[85.446193,23.378612],"type":"Point"}
}