{
  "id": 2679005,
  "type": "Feature",
  "properties": {
    "tgn:hierarchy":[
        "tgn:2679005",
        "tgn:1000001",
        "tgn:7012149",
        "tgn:7007255",
        "tgn:7029392"
    ],
    "tgn:id":2679005,
    "tgn:name":"South Fork Honey Locust Creek",
    "tgn:placetype":[
        "aat:300008706"
    ]
},
  "bbox": [],
  "geometry": {"coordinates":[-86.6667,37.75],"type":"Point"}
}