<<<<<<< HEAD
{
  "id": 2762463,
  "type": "Feature",
  "properties": {
    "tgn:hierarchy":[
        "tgn:2762463",
        "tgn:1000001",
        "tgn:1002665",
        "tgn:7012149",
        "tgn:7007517",
        "tgn:7029392"
    ],
    "tgn:id":2762463,
    "tgn:name":"West Village",
    "tgn:placetype":[
        "aat:300008347"
    ]
},
  "bbox": [],
  "geometry": {"coordinates":[-71.1,42.5667],"type":"Point"}
}
=======
{"geometry":{"type":"Point","coordinates":[-71.100000,42.566700]},"type":"Feature","properties":{"hierarchy":["tgn:2762463","tgn:1000001","tgn:1002665","tgn:7012149","tgn:7007517","tgn:7029392"],"placetype":["aat:300008347"],"id":2762463,"name:xx":"West Village"}}
>>>>>>> 03f74aca74312dbeaf24d7e61306dd6a786dc3d0
