{
  "id": 7425246,
  "type": "Feature",
  "properties": {
    "tgn:hierarchy":[
        "tgn:7425246",
        "tgn:1000001",
        "tgn:7005597",
        "tgn:7005560",
        "tgn:7029392"
    ],
    "tgn:id":7425246,
    "tgn:name":"El Tahuachel",
    "tgn:placetype":[
        "aat:300008347"
    ]
},
  "bbox": [],
  "geometry": {"coordinates":[-97.616667,25.966667],"type":"Point"}
}