{
  "id": 7403132,
  "type": "Feature",
  "properties": {
    "tgn:hierarchy":[
        "tgn:7403132",
        "tgn:1000001",
        "tgn:7005600",
        "tgn:7005560",
        "tgn:7029392"
    ],
    "tgn:id":7403132,
    "tgn:name":"Popolnah",
    "tgn:placetype":[
        "aat:300008347"
    ]
},
  "bbox": [],
  "geometry": {"coordinates":[-87.5625,20.995833],"type":"Point"}
}