{
  "id": 2708880,
  "type": "Feature",
  "properties": {
    "tgn:hierarchy":[
        "tgn:2708880",
        "tgn:1000001",
        "tgn:7012149",
        "tgn:2002119",
        "tgn:7007827",
        "tgn:7029392"
    ],
    "tgn:id":2708880,
    "tgn:name":"Syncline Valley",
    "tgn:placetype":[
        "aat:300008761"
    ]
},
  "bbox": [],
  "geometry": {"coordinates":[-109.9167,38.45],"type":"Point"}
}