{
  "id": 2102857,
  "type": "Feature",
  "properties": {
    "tgn:hierarchy":[
        "tgn:2102857",
        "tgn:1000001",
        "tgn:7012149",
        "tgn:1003031",
        "tgn:7007826",
        "tgn:7029392"
    ],
    "tgn:id":2102857,
    "tgn:name":"Boyd",
    "tgn:placetype":[
        "aat:300008347"
    ]
},
  "bbox": [],
  "geometry": {"coordinates":[-97.55,33.0667],"type":"Point"}
}