<<<<<<< HEAD
{
  "id": 7484010,
  "type": "Feature",
  "properties": {
    "tgn:hierarchy":[
        "tgn:7484010",
        "tgn:7488858",
        "tgn:1000004",
        "tgn:1000141",
        "tgn:7029392"
    ],
    "tgn:id":7484010,
    "tgn:name":"Dakeng Yihao Qiao",
    "tgn:placetype":[
        "aat:300007836"
    ]
},
  "bbox": [],
  "geometry": {"coordinates":[120.685556,23.738333],"type":"Point"}
}
=======
{"geometry":{"type":"Point","coordinates":[120.685556,23.738333]},"type":"Feature","properties":{"hierarchy":["tgn:7484010","tgn:7488858","tgn:1000004","tgn:1000141","tgn:7029392"],"placetype":["aat:300007836"],"id":7484010,"name:xx":"Dakeng Yihao Qiao"}}
>>>>>>> 03f74aca74312dbeaf24d7e61306dd6a786dc3d0
