{
  "id": 2363084,
  "type": "Feature",
  "properties": {
    "tgn:hierarchy":[
        "tgn:2363084",
        "tgn:2002307",
        "tgn:1000001",
        "tgn:7012149",
        "tgn:7007922",
        "tgn:7029392"
    ],
    "tgn:id":2363084,
    "tgn:name":"Greeley Lake",
    "tgn:placetype":[
        "aat:300008680"
    ]
},
  "bbox": [],
  "geometry": {"coordinates":[-91.9833,45.5833],"type":"Point"}
}