{
  "id": 2635772,
  "type": "Feature",
  "properties": {
    "tgn:hierarchy":[
        "tgn:2635772",
        "tgn:1000001",
        "tgn:7012149",
        "tgn:7007522",
        "tgn:7029392"
    ],
    "tgn:id":2635772,
    "tgn:name":"Sabougla Creek",
    "tgn:placetype":[
        "aat:300008706"
    ]
},
  "bbox": [],
  "geometry": {"coordinates":[-89.25,33.65],"type":"Point"}
}