{
  "id": 2217687,
  "type": "Feature",
  "properties": {
    "tgn:hierarchy":[
        "tgn:2217687",
        "tgn:1000001",
        "tgn:2001840",
        "tgn:7012149",
        "tgn:7007825",
        "tgn:7029392"
    ],
    "tgn:id":2217687,
    "tgn:name":"Campbell Mine",
    "tgn:placetype":[
        "aat:300000390"
    ]
},
  "bbox": [],
  "geometry": {"coordinates":[-85.1833,35.65],"type":"Point"}
}