<<<<<<< HEAD
{
  "id": 7179203,
  "type": "Feature",
  "properties": {
    "tgn:hierarchy":[
        "tgn:7179203",
        "tgn:7003669",
        "tgn:1000003",
        "tgn:7000084",
        "tgn:7029392"
    ],
    "tgn:id":7179203,
    "tgn:name":"Haid",
    "tgn:placetype":[
        "aat:300008347"
    ]
},
  "bbox": [],
  "geometry": {"coordinates":[12.533333,48.7],"type":"Point"}
}
=======
{"geometry":{"type":"Point","coordinates":[12.533333,48.700000]},"type":"Feature","properties":{"hierarchy":["tgn:7179203","tgn:7003669","tgn:1000003","tgn:7000084","tgn:7029392"],"placetype":["aat:300008347"],"id":7179203,"name:xx":"Haid"}}
>>>>>>> 03f74aca74312dbeaf24d7e61306dd6a786dc3d0
