{
  "id": 2226396,
  "type": "Feature",
  "properties": {
    "tgn:hierarchy":[
        "tgn:2226396",
        "tgn:1000001",
        "tgn:7012149",
        "tgn:2002128",
        "tgn:7007827",
        "tgn:7029392"
    ],
    "tgn:id":2226396,
    "tgn:name":"Cathedral Mountain",
    "tgn:placetype":[
        "aat:300008798"
    ]
},
  "bbox": [],
  "geometry": {"coordinates":[-111.35,38.4833],"type":"Point"}
}