{
  "id": 7437251,
  "type": "Feature",
  "properties": {
    "tgn:hierarchy":[
        "tgn:7437251",
        "tgn:1000001",
        "tgn:7005591",
        "tgn:7005560",
        "tgn:7029392"
    ],
    "tgn:id":7437251,
    "tgn:name":"Santiago Huajolotitl\u00e1n",
    "tgn:placetype":[
        "aat:300008347"
    ]
},
  "bbox": [],
  "geometry": {"coordinates":[-97.733333,17.816667],"type":"Point"}
}