{
  "id": 7075572,
  "type": "Feature",
  "properties": {
    "tgn:hierarchy":[
        "tgn:7075572",
        "tgn:1000003",
        "tgn:7003676",
        "tgn:7000084",
        "tgn:7029392"
    ],
    "tgn:id":7075572,
    "tgn:name":"Holm Seppensen",
    "tgn:placetype":[
        "aat:300008347"
    ]
},
  "bbox": [],
  "geometry": {"coordinates":[9.866667,53.283333],"type":"Point"}
}