<<<<<<< HEAD
{
  "id": 2703477,
  "type": "Feature",
  "properties": {
    "tgn:hierarchy":[
        "tgn:2703477",
        "tgn:1000001",
        "tgn:2001815",
        "tgn:7012149",
        "tgn:7007713",
        "tgn:7029392"
    ],
    "tgn:id":2703477,
    "tgn:name":"Summit Lake",
    "tgn:placetype":[
        "aat:300008680"
    ]
},
  "bbox": [],
  "geometry": {"coordinates":[-97.2667,45.7667],"type":"Point"}
}
=======
{"geometry":{"type":"Point","coordinates":[-97.266700,45.766700]},"type":"Feature","properties":{"hierarchy":["tgn:2703477","tgn:1000001","tgn:2001815","tgn:7012149","tgn:7007713","tgn:7029392"],"placetype":["aat:300008680"],"id":2703477,"name:xx":"Summit Lake"}}
>>>>>>> 03f74aca74312dbeaf24d7e61306dd6a786dc3d0
