{
  "id": 7555104,
  "type": "Feature",
  "properties": {
    "tgn:hierarchy":[
        "tgn:7555104",
        "tgn:1000004",
        "tgn:7000198",
        "tgn:7001797",
        "tgn:7029392"
    ],
    "tgn:id":7555104,
    "tgn:name:en":"Nallatanni T\u012bvu",
    "tgn:placetype":[
        "aat:300008791"
    ]
},
  "bbox": [],
  "geometry": {"coordinates":[78.566667,9.116667],"type":"Point"}
}