{
  "id": 1118774,
  "type": "Feature",
  "properties": {
    "tgn:hierarchy":[
        "tgn:1118774",
        "tgn:7005685",
        "tgn:1000001",
        "tgn:7013154",
        "tgn:7029392"
    ],
    "tgn:id":1118774,
    "tgn:name":"Wye Lake",
    "tgn:placetype":[
        "aat:300008680"
    ]
},
  "bbox": [],
  "geometry": {"coordinates":[-79.8667,44.7167],"type":"Point"}
}