{
  "id": 7006491,
  "type": "Feature",
  "properties": {
    "tgn:hierarchy":[
        "tgn:7006491",
        "tgn:1000003",
        "tgn:7006541",
        "tgn:7029392"
    ],
    "tgn:id":7006491,
    "tgn:name":"Daugavpils",
    "tgn:placetype":[
        "aat:300387064",
        "aat:300387081"
    ]
},
  "bbox": [],
  "geometry": {"coordinates":[26.5333,55.8833],"type":"Point"}
}