<<<<<<< HEAD
{
  "id": 7470736,
  "type": "Feature",
  "properties": {
    "tgn:hierarchy":[
        "tgn:7470736",
        "tgn:1000004",
        "tgn:7467799",
        "tgn:1000141",
        "tgn:7029392"
    ],
    "tgn:id":7470736,
    "tgn:name":"Xiazhuzijiao",
    "tgn:placetype":[
        "aat:300008347"
    ]
},
  "bbox": [],
  "geometry": {"coordinates":[120.521057,24.078957],"type":"Point"}
}
=======
{"geometry":{"type":"Point","coordinates":[120.521057,24.078957]},"type":"Feature","properties":{"hierarchy":["tgn:7470736","tgn:1000004","tgn:7467799","tgn:1000141","tgn:7029392"],"placetype":["aat:300008347"],"id":7470736,"name:xx":"Xiazhuzijiao"}}
>>>>>>> 03f74aca74312dbeaf24d7e61306dd6a786dc3d0
