{
  "id": 1076539,
  "type": "Feature",
  "properties": {
    "tgn:hierarchy":[
        "tgn:1076539",
        "tgn:1000004",
        "tgn:7000198",
        "tgn:1001895",
        "tgn:7029392"
    ],
    "tgn:id":1076539,
    "tgn:name:en":"Pandharpur",
    "tgn:placetype":[
        "aat:300008347"
    ]
},
  "bbox": [],
  "geometry": {"coordinates":[75.330978,17.679236],"type":"Point"}
}