{
  "id": 7196766,
  "type": "Feature",
  "properties": {
    "tgn:hierarchy":[
        "tgn:7196766",
        "tgn:7003669",
        "tgn:1000003",
        "tgn:7000084",
        "tgn:7029392"
    ],
    "tgn:id":7196766,
    "tgn:name":"Dettenkofen",
    "tgn:placetype":[
        "aat:300008347"
    ]
},
  "bbox": [],
  "geometry": {"coordinates":[12.383333,48.816667],"type":"Point"}
}