{
  "id": 7296118,
  "type": "Feature",
  "properties": {
    "tgn:hierarchy":[
        "tgn:7296118",
        "tgn:7002758",
        "tgn:7002817",
        "tgn:1000003",
        "tgn:1000095",
        "tgn:7029392"
    ],
    "tgn:id":7296118,
    "tgn:name":"Yeguas, R\u00edo de las",
    "tgn:placetype":[
        "aat:300008699"
    ]
},
  "bbox": [],
  "geometry": {"coordinates":[-4.75,37.366667],"type":"Point"}
}