{
  "id": 2207049,
  "type": "Feature",
  "properties": {
    "tgn:hierarchy":[
        "tgn:2207049",
        "tgn:1000001",
        "tgn:7012149",
        "tgn:2002110",
        "tgn:7007827",
        "tgn:7029392"
    ],
    "tgn:id":2207049,
    "tgn:name":"Bunchground Canyon",
    "tgn:placetype":[
        "aat:300008761"
    ]
},
  "bbox": [],
  "geometry": {"coordinates":[-109.25,38.6167],"type":"Point"}
}