{
  "id": 2687225,
  "type": "Feature",
  "properties": {
    "tgn:hierarchy":[
        "tgn:2687225",
        "tgn:1000001",
        "tgn:7012149",
        "tgn:2002287",
        "tgn:7013961",
        "tgn:7029392"
    ],
    "tgn:id":2687225,
    "tgn:name":"Spring House Cave",
    "tgn:placetype":[
        "aat:300008746"
    ]
},
  "bbox": [],
  "geometry": {"coordinates":[-80.25,38.1333],"type":"Point"}
}