<<<<<<< HEAD
{
  "id": 2404328,
  "type": "Feature",
  "properties": {
    "tgn:hierarchy":[
        "tgn:2404328",
        "tgn:1000001",
        "tgn:7006451",
        "tgn:2000092",
        "tgn:7012149",
        "tgn:7029392"
    ],
    "tgn:id":2404328,
    "tgn:name":"Hualapai Spring",
    "tgn:placetype":[
        "aat:300008697"
    ]
},
  "bbox": [],
  "geometry": {"coordinates":[-112.5333,36.4167],"type":"Point"}
}
=======
{"geometry":{"type":"Point","coordinates":[-112.533300,36.416700]},"type":"Feature","properties":{"hierarchy":["tgn:2404328","tgn:1000001","tgn:7006451","tgn:2000092","tgn:7012149","tgn:7029392"],"placetype":["aat:300008697"],"id":2404328,"name:xx":"Hualapai Spring"}}
>>>>>>> 03f74aca74312dbeaf24d7e61306dd6a786dc3d0
