<<<<<<< HEAD
{
  "id": 7173587,
  "type": "Feature",
  "properties": {
    "tgn:hierarchy":[
        "tgn:7173587",
        "tgn:1000003",
        "tgn:7003688",
        "tgn:7000084",
        "tgn:7029392"
    ],
    "tgn:id":7173587,
    "tgn:name":"Grundlos",
    "tgn:placetype":[
        "aat:300000206"
    ]
},
  "bbox": [],
  "geometry": {"coordinates":[9.533333,54.483333],"type":"Point"}
}
=======
{"geometry":{"type":"Point","coordinates":[9.533333,54.483333]},"type":"Feature","properties":{"hierarchy":["tgn:7173587","tgn:1000003","tgn:7003688","tgn:7000084","tgn:7029392"],"placetype":["aat:300000206"],"id":7173587,"name:xx":"Grundlos"}}
>>>>>>> 03f74aca74312dbeaf24d7e61306dd6a786dc3d0
