<<<<<<< HEAD
{
  "id": 2769002,
  "type": "Feature",
  "properties": {
    "tgn:hierarchy":[
        "tgn:2769002",
        "tgn:1000001",
        "tgn:7016172",
        "tgn:7012149",
        "tgn:2000126",
        "tgn:7029392"
    ],
    "tgn:id":2769002,
    "tgn:name":"Whittaker Branch",
    "tgn:placetype":[
        "aat:300008699"
    ]
},
  "bbox": [],
  "geometry": {"coordinates":[-91.6333,33.6667],"type":"Point"}
}
=======
{"geometry":{"type":"Point","coordinates":[-91.633300,33.666700]},"type":"Feature","properties":{"hierarchy":["tgn:2769002","tgn:1000001","tgn:7016172","tgn:7012149","tgn:2000126","tgn:7029392"],"placetype":["aat:300008699"],"id":2769002,"name:xx":"Whittaker Branch"}}
>>>>>>> 03f74aca74312dbeaf24d7e61306dd6a786dc3d0
