{
  "id": 7386122,
  "type": "Feature",
  "properties": {
    "tgn:hierarchy":[
        "tgn:7386122",
        "tgn:1000001",
        "tgn:1001960",
        "tgn:7005560",
        "tgn:7029392"
    ],
    "tgn:id":7386122,
    "tgn:name":"Estaci\u00f3n Pitahaya",
    "tgn:placetype":[
        "aat:300007783"
    ]
},
  "bbox": [],
  "geometry": {"coordinates":[-110.416667,27.733333],"type":"Point"}
}