{
  "id": 2415224,
  "type": "Feature",
  "properties": {
    "tgn:hierarchy":[
        "tgn:2415224",
        "tgn:1000001",
        "tgn:7012149",
        "tgn:2001058",
        "tgn:7007521",
        "tgn:7029392"
    ],
    "tgn:id":2415224,
    "tgn:name":"Island Lake",
    "tgn:placetype":[
        "aat:300008680"
    ]
},
  "bbox": [],
  "geometry": {"coordinates":[-96.0667,47.6167],"type":"Point"}
}