{
  "id": 7495319,
  "type": "Feature",
  "properties": {
    "tgn:hierarchy":[
        "tgn:7495319",
        "tgn:1000004",
        "tgn:7492971",
        "tgn:1000141",
        "tgn:7029392"
    ],
    "tgn:id":7495319,
    "tgn:name":"Xinzhen Qiao",
    "tgn:placetype":[
        "aat:300007836"
    ]
},
  "bbox": [],
  "geometry": {"coordinates":[120.547128,22.501401],"type":"Point"}
}