{
  "id": 7428573,
  "type": "Feature",
  "properties": {
    "tgn:hierarchy":[
        "tgn:7428573",
        "tgn:7005581",
        "tgn:1000001",
        "tgn:7005560",
        "tgn:7029392"
    ],
    "tgn:id":7428573,
    "tgn:name":"Tampico Nuevo",
    "tgn:placetype":[
        "aat:300008347"
    ]
},
  "bbox": [],
  "geometry": {"coordinates":[-104.85,27.316667],"type":"Point"}
}