{
  "id": 2709481,
  "type": "Feature",
  "properties": {
    "tgn:hierarchy":[
        "tgn:2709481",
        "tgn:1000001",
        "tgn:2002134",
        "tgn:7012149",
        "tgn:7007828",
        "tgn:7029392"
    ],
    "tgn:id":2709481,
    "tgn:name":"Tabor Branch",
    "tgn:placetype":[
        "aat:300008699"
    ]
},
  "bbox": [],
  "geometry": {"coordinates":[-72.2667,44.1667],"type":"Point"}
}