{
  "id": 7443741,
  "type": "Feature",
  "properties": {
    "tgn:hierarchy":[
        "tgn:7443741",
        "tgn:7002445",
        "tgn:1000003",
        "tgn:7008118",
        "tgn:7008591",
        "tgn:7029392"
    ],
    "tgn:id":7443741,
    "tgn:name:en":"Upper Langwith",
    "tgn:placetype":[
        "aat:300008347"
    ]
},
  "bbox": [],
  "geometry": {"coordinates":[-1.233333,53.216667],"type":"Point"}
}