{
  "id": 2353288,
  "type": "Feature",
  "properties": {
    "tgn:hierarchy":[
        "tgn:2353288",
        "tgn:1000001",
        "tgn:1002340",
        "tgn:7012149",
        "tgn:7007526",
        "tgn:7029392"
    ],
    "tgn:id":2353288,
    "tgn:name":"Gold Bug Mine",
    "tgn:placetype":[
        "aat:300000390"
    ]
},
  "bbox": [],
  "geometry": {"coordinates":[-119.5167,38.8167],"type":"Point"}
}