{
  "id": 7406544,
  "type": "Feature",
  "properties": {
    "tgn:hierarchy":[
        "tgn:7406544",
        "tgn:1000001",
        "tgn:1001906",
        "tgn:7005560",
        "tgn:7029392"
    ],
    "tgn:id":7406544,
    "tgn:name":"Santa Gertrudis, Arroyo",
    "tgn:placetype":[
        "aat:300008699"
    ]
},
  "bbox": [],
  "geometry": {"coordinates":[-104.733333,22.416667],"type":"Point"}
}