<<<<<<< HEAD
{
  "id": 2765529,
  "type": "Feature",
  "properties": {
    "tgn:hierarchy":[
        "tgn:2765529",
        "tgn:1000001",
        "tgn:7012149",
        "tgn:1002298",
        "tgn:7007157",
        "tgn:7029392"
    ],
    "tgn:id":2765529,
    "tgn:name":"White Canyon",
    "tgn:placetype":[
        "aat:300008761"
    ]
},
  "bbox": [],
  "geometry": {"coordinates":[-121.95,37.8833],"type":"Point"}
}
=======
{"geometry":{"type":"Point","coordinates":[-121.950000,37.883300]},"type":"Feature","properties":{"hierarchy":["tgn:2765529","tgn:1000001","tgn:7012149","tgn:1002298","tgn:7007157","tgn:7029392"],"placetype":["aat:300008761"],"id":2765529,"name:xx":"White Canyon"}}
>>>>>>> 03f74aca74312dbeaf24d7e61306dd6a786dc3d0
