{
  "id": 1114978,
  "type": "Feature",
  "properties": {
    "tgn:hierarchy":[
        "tgn:1114978",
        "tgn:7002444",
        "tgn:1000003",
        "tgn:7008094",
        "tgn:7008591",
        "tgn:7029392"
    ],
    "tgn:id":1114978,
    "tgn:name:en":"Harris, Sound of",
    "tgn:placetype":[
        "aat:300266558"
    ]
},
  "bbox": [],
  "geometry": {"coordinates":[-7.1667,57.75],"type":"Point"}
}