{
  "id": 2231333,
  "type": "Feature",
  "properties": {
    "tgn:hierarchy":[
        "tgn:2231333",
        "tgn:1000001",
        "tgn:7012149",
        "tgn:7007922",
        "tgn:7029392"
    ],
    "tgn:id":2231333,
    "tgn:name":"Chain of Lakes",
    "tgn:placetype":[
        "aat:300008680"
    ]
},
  "bbox": [],
  "geometry": {"coordinates":[-91.1667,43.3667],"type":"Point"}
}