{
  "id": 2683734,
  "type": "Feature",
  "properties": {
    "tgn:hierarchy":[
        "tgn:2683734",
        "tgn:7030515",
        "tgn:7006450",
        "tgn:1000001",
        "tgn:7012149",
        "tgn:7029392"
    ],
    "tgn:id":2683734,
    "tgn:name":"Spectacle Island",
    "tgn:placetype":[
        "aat:300008791"
    ]
},
  "bbox": [],
  "geometry": {"coordinates":[-159.7167,31.1333],"type":"Point"}
}