{
  "id": 7263719,
  "type": "Feature",
  "properties": {
    "tgn:hierarchy":[
        "tgn:7263719",
        "tgn:1000003",
        "tgn:7003613",
        "tgn:7016845",
        "tgn:7029392"
    ],
    "tgn:id":7263719,
    "tgn:name:nl":"Leest, Polder de",
    "tgn:placetype":[
        "aat:300006163"
    ]
},
  "bbox": [],
  "geometry": {"coordinates":[6.85,53.15],"type":"Point"}
}