{
  "id": 2363459,
  "type": "Feature",
  "properties": {
    "tgn:hierarchy":[
        "tgn:2363459",
        "tgn:1000001",
        "tgn:7012149",
        "tgn:2000354",
        "tgn:7007248",
        "tgn:7029392"
    ],
    "tgn:id":2363459,
    "tgn:name":"Green Creek Swamp",
    "tgn:placetype":[
        "aat:300008905"
    ]
},
  "bbox": [],
  "geometry": {"coordinates":[-81.65,31.2333],"type":"Point"}
}