{
  "id": 7315331,
  "type": "Feature",
  "properties": {
    "tgn:hierarchy":[
        "tgn:7315331",
        "tgn:7002464",
        "tgn:1000049",
        "tgn:1000002",
        "tgn:7029392"
    ],
    "tgn:id":7315331,
    "tgn:name":"Cha\u00f1o, Quebrada",
    "tgn:placetype":[
        "aat:300008699"
    ]
},
  "bbox": [],
  "geometry": {"coordinates":[-69.166667,-18.566667],"type":"Point"}
}