{
  "id": 7507280,
  "type": "Feature",
  "properties": {
    "tgn:hierarchy":[
        "tgn:7507280",
        "tgn:1009227",
        "tgn:1000226",
        "tgn:7018437",
        "tgn:1000006",
        "tgn:7029392"
    ],
    "tgn:id":7507280,
    "tgn:name:en":"Puketawa",
    "tgn:placetype":[
        "aat:300008795"
    ]
},
  "bbox": [],
  "geometry": {"coordinates":[169.483333,-46.433333],"type":"Point"}
}