<<<<<<< HEAD
{
  "id": 2764218,
  "type": "Feature",
  "properties": {
    "tgn:hierarchy":[
        "tgn:2764218",
        "tgn:1000001",
        "tgn:7012149",
        "tgn:2002125",
        "tgn:7007827",
        "tgn:7029392"
    ],
    "tgn:id":2764218,
    "tgn:name":"Wheeler Springs",
    "tgn:placetype":[
        "aat:300008697"
    ]
},
  "bbox": [],
  "geometry": {"coordinates":[-111.5833,40.15],"type":"Point"}
}
=======
{"geometry":{"type":"Point","coordinates":[-111.583300,40.150000]},"type":"Feature","properties":{"hierarchy":["tgn:2764218","tgn:1000001","tgn:7012149","tgn:2002125","tgn:7007827","tgn:7029392"],"placetype":["aat:300008697"],"id":2764218,"name:xx":"Wheeler Springs"}}
>>>>>>> 03f74aca74312dbeaf24d7e61306dd6a786dc3d0
