{
  "id": 2764218,
  "type": "Feature",
  "properties": {
    "tgn:hierarchy":[
        "tgn:2764218",
        "tgn:1000001",
        "tgn:7012149",
        "tgn:2002125",
        "tgn:7007827",
        "tgn:7029392"
    ],
    "tgn:id":2764218,
    "tgn:name":"Wheeler Springs",
    "tgn:placetype":[
        "aat:300008697"
    ]
},
  "bbox": [],
  "geometry": {"coordinates":[-111.5833,40.15],"type":"Point"}
}