{
  "id": 2197914,
  "type": "Feature",
  "properties": {
    "tgn:hierarchy":[
        "tgn:2197914",
        "tgn:1000001",
        "tgn:7012149",
        "tgn:1002402",
        "tgn:7007523",
        "tgn:7029392"
    ],
    "tgn:id":2197914,
    "tgn:name":"Brown Shanty Lake",
    "tgn:placetype":[
        "aat:300006191"
    ]
},
  "bbox": [],
  "geometry": {"coordinates":[-91.5667,38.5333],"type":"Point"}
}