{
  "id": 2695406,
  "type": "Feature",
  "properties": {
    "tgn:hierarchy":[
        "tgn:2695406",
        "tgn:1000001",
        "tgn:7012149",
        "tgn:1002751",
        "tgn:7007568",
        "tgn:7029392"
    ],
    "tgn:id":2695406,
    "tgn:name":"Stilwell Lake",
    "tgn:placetype":[
        "aat:300006191"
    ]
},
  "bbox": [],
  "geometry": {"coordinates":[-74.0167,41.3333],"type":"Point"}
}