{
  "id": 7311917,
  "type": "Feature",
  "properties": {
    "tgn:hierarchy":[
        "tgn:7311917",
        "tgn:1001768",
        "tgn:1000049",
        "tgn:1000002",
        "tgn:7029392"
    ],
    "tgn:id":7311917,
    "tgn:name":"Las Lagunillas",
    "tgn:placetype":[
        "aat:300387200"
    ]
},
  "bbox": [],
  "geometry": {"coordinates":[-71.433333,-32.683333],"type":"Point"}
}