<<<<<<< HEAD
{
  "id": 2331551,
  "type": "Feature",
  "properties": {
    "tgn:hierarchy":[
        "tgn:2331551",
        "tgn:1002143",
        "tgn:1000001",
        "tgn:7012149",
        "tgn:7007252",
        "tgn:7029392"
    ],
    "tgn:id":2331551,
    "tgn:name":"Flaugh Ditch",
    "tgn:placetype":[
        "aat:300006075"
    ]
},
  "bbox": [],
  "geometry": {"coordinates":[-85.2167,41.0667],"type":"Point"}
}
=======
{"geometry":{"type":"Point","coordinates":[-85.216700,41.066700]},"type":"Feature","properties":{"hierarchy":["tgn:2331551","tgn:1002143","tgn:1000001","tgn:7012149","tgn:7007252","tgn:7029392"],"placetype":["aat:300006075"],"id":2331551,"name:xx":"Flaugh Ditch"}}
>>>>>>> 03f74aca74312dbeaf24d7e61306dd6a786dc3d0
