{
  "id": 2414445,
  "type": "Feature",
  "properties": {
    "tgn:hierarchy":[
        "tgn:2414445",
        "tgn:1000001",
        "tgn:7012149",
        "tgn:2001750",
        "tgn:7007712",
        "tgn:7029392"
    ],
    "tgn:id":2414445,
    "tgn:name":"Iron Springs Swamp",
    "tgn:placetype":[
        "aat:300008699"
    ]
},
  "bbox": [],
  "geometry": {"coordinates":[-78.9833,34.1667],"type":"Point"}
}