{
  "id": 2049661,
  "type": "Feature",
  "properties": {
    "tgn:hierarchy":[
        "tgn:2049661",
        "tgn:1000001",
        "tgn:7013518",
        "tgn:1002724",
        "tgn:7012149",
        "tgn:7007517",
        "tgn:7029392"
    ],
    "tgn:id":2049661,
    "tgn:name":"Endicott",
    "tgn:placetype":[
        "aat:300000745"
    ]
},
  "bbox": [],
  "geometry": {"coordinates":[-71.15,42.2167],"type":"Point"}
}