{
  "id": 2099336,
  "type": "Feature",
  "properties": {
    "tgn:hierarchy":[
        "tgn:2099336",
        "tgn:2001837",
        "tgn:1000001",
        "tgn:7012149",
        "tgn:7007825",
        "tgn:7029392"
    ],
    "tgn:id":2099336,
    "tgn:name":"Granite",
    "tgn:placetype":[
        "aat:300008347",
        "aat:300387210"
    ]
},
  "bbox": [],
  "geometry": {"coordinates":[-84.15,36.1167],"type":"Point"}
}