{
  "id": 2162200,
  "type": "Feature",
  "properties": {
    "tgn:hierarchy":[
        "tgn:2162200",
        "tgn:1000001",
        "tgn:7012149",
        "tgn:7007157",
        "tgn:2000189",
        "tgn:7029392"
    ],
    "tgn:id":2162200,
    "tgn:name":"Belnap Spring",
    "tgn:placetype":[
        "aat:300008697"
    ]
},
  "bbox": [],
  "geometry": {"coordinates":[-121.7833,41.3833],"type":"Point"}
}