{
  "id": 7217499,
  "type": "Feature",
  "properties": {
    "tgn:hierarchy":[
        "tgn:7217499",
        "tgn:7002735",
        "tgn:7017076",
        "tgn:1000003",
        "tgn:1000074",
        "tgn:7029392"
    ],
    "tgn:id":7217499,
    "tgn:name":"Ts\u00e1konas",
    "tgn:placetype":[
        "aat:300266640"
    ]
},
  "bbox": [],
  "geometry": {"coordinates":[23.066667,36.783333],"type":"Point"}
}