{
  "id": 2361970,
  "type": "Feature",
  "properties": {
    "tgn:hierarchy":[
        "tgn:2361970",
        "tgn:1000001",
        "tgn:7012149",
        "tgn:2001075",
        "tgn:7007521",
        "tgn:7029392"
    ],
    "tgn:id":2361970,
    "tgn:name":"Gray Lake",
    "tgn:placetype":[
        "aat:300008680"
    ]
},
  "bbox": [],
  "geometry": {"coordinates":[-95.0667,46.0333],"type":"Point"}
}