{
  "id": 2321742,
  "type": "Feature",
  "properties": {
    "tgn:hierarchy":[
        "tgn:2321742",
        "tgn:1000001",
        "tgn:7012149",
        "tgn:7007157",
        "tgn:7014516",
        "tgn:7029392"
    ],
    "tgn:id":2321742,
    "tgn:name":"Fairville",
    "tgn:placetype":[
        "aat:300008347"
    ]
},
  "bbox": [],
  "geometry": {"coordinates":[-122.4333,38.1667],"type":"Point"}
}