{
  "id": 2345612,
  "type": "Feature",
  "properties": {
    "tgn:hierarchy":[
        "tgn:2345612",
        "tgn:1000001",
        "tgn:2001414",
        "tgn:7012149",
        "tgn:7007526",
        "tgn:7029392"
    ],
    "tgn:id":2345612,
    "tgn:name":"Garret Spring",
    "tgn:placetype":[
        "aat:300008697"
    ]
},
  "bbox": [],
  "geometry": {"coordinates":[-117.0667,41.2333],"type":"Point"}
}