{
  "id": 7359041,
  "type": "Feature",
  "properties": {
    "tgn:hierarchy":[
        "tgn:7359041",
        "tgn:1000001",
        "tgn:7005595",
        "tgn:7005560",
        "tgn:7029392"
    ],
    "tgn:id":7359041,
    "tgn:name":"El \u00c1guila",
    "tgn:placetype":[
        "aat:300008347"
    ]
},
  "bbox": [],
  "geometry": {"coordinates":[-109.15,25.916667],"type":"Point"}
}