{
  "id": 2349130,
  "type": "Feature",
  "properties": {
    "tgn:hierarchy":[
        "tgn:2349130",
        "tgn:1000001",
        "tgn:7012149",
        "tgn:2000977",
        "tgn:7007520",
        "tgn:7029392"
    ],
    "tgn:id":2349130,
    "tgn:name":"Gilbert Creek",
    "tgn:placetype":[
        "aat:300008706"
    ]
},
  "bbox": [],
  "geometry": {"coordinates":[-85.25,43.6667],"type":"Point"}
}