{
  "id": 7557879,
  "type": "Feature",
  "properties": {
    "tgn:hierarchy":[
        "tgn:7557879",
        "tgn:1000004",
        "tgn:7000198",
        "tgn:7016788",
        "tgn:7029392"
    ],
    "tgn:id":7557879,
    "tgn:name:en":"Ranjitpura",
    "tgn:placetype":[
        "aat:300008347"
    ]
},
  "bbox": [],
  "geometry": {"coordinates":[72.124581,28.017272],"type":"Point"}
}