{
  "id": 7444510,
  "type": "Feature",
  "properties": {
    "tgn:hierarchy":[
        "tgn:7444510",
        "tgn:7002445",
        "tgn:1000003",
        "tgn:7019017",
        "tgn:7008591",
        "tgn:7029392"
    ],
    "tgn:id":7444510,
    "tgn:name:en":"Sand Point",
    "tgn:placetype":[
        "aat:300386846"
    ]
},
  "bbox": [],
  "geometry": {"coordinates":[-2.976944,51.39],"type":"Point"}
}