{
  "id": 2784098,
  "type": "Feature",
  "properties": {
    "tgn:hierarchy":[
        "tgn:2784098",
        "tgn:1000001",
        "tgn:7012149",
        "tgn:7007157",
        "tgn:1002858",
        "tgn:7029392"
    ],
    "tgn:id":2784098,
    "tgn:name":"Yaldora",
    "tgn:placetype":[
        "aat:300008347"
    ]
},
  "bbox": [],
  "geometry": {"coordinates":[-117.3833,33.2167],"type":"Point"}
}