{
  "id": 2708556,
  "type": "Feature",
  "properties": {
    "tgn:hierarchy":[
        "tgn:2708556",
        "tgn:1000001",
        "tgn:2002262",
        "tgn:7012149",
        "tgn:7013961",
        "tgn:7029392"
    ],
    "tgn:id":2708556,
    "tgn:name":"Sycamore Run",
    "tgn:placetype":[
        "aat:300008699"
    ]
},
  "bbox": [],
  "geometry": {"coordinates":[-80.8167,38.9667],"type":"Point"}
}