{
  "id": 7108544,
  "type": "Feature",
  "properties": {
    "tgn:hierarchy":[
        "tgn:7108544",
        "tgn:1000003",
        "tgn:7003685",
        "tgn:7000084",
        "tgn:7029392"
    ],
    "tgn:id":7108544,
    "tgn:name":"Rabenstein",
    "tgn:placetype":[
        "aat:300000745"
    ]
},
  "bbox": [],
  "geometry": {"coordinates":[12.833333,50.833333],"type":"Point"}
}