{
  "id": 2307049,
  "type": "Feature",
  "properties": {
    "tgn:hierarchy":[
        "tgn:2307049",
        "tgn:1000001",
        "tgn:7012149",
        "tgn:7007525",
        "tgn:7029392"
    ],
    "tgn:id":2307049,
    "tgn:name":"East Fork Maple Creek",
    "tgn:placetype":[
        "aat:300008706"
    ]
},
  "bbox": [],
  "geometry": {"coordinates":[-97.1333,41.85],"type":"Point"}
}