{
  "id": 2525549,
  "type": "Feature",
  "properties": {
    "tgn:hierarchy":[
        "tgn:2525549",
        "tgn:1000001",
        "tgn:7012149",
        "tgn:2002111",
        "tgn:7007827",
        "tgn:7029392"
    ],
    "tgn:id":2525549,
    "tgn:name":"Mortensen Canyon",
    "tgn:placetype":[
        "aat:300008761"
    ]
},
  "bbox": [],
  "geometry": {"coordinates":[-112.6167,37.8333],"type":"Point"}
}