{
  "id": 2703036,
  "type": "Feature",
  "properties": {
    "tgn:hierarchy":[
        "tgn:2703036",
        "tgn:2000090",
        "tgn:1000001",
        "tgn:7006451",
        "tgn:7012149",
        "tgn:7029392"
    ],
    "tgn:id":2703036,
    "tgn:name":"Sulzberger Tank",
    "tgn:placetype":[
        "aat:300006191"
    ]
},
  "bbox": [],
  "geometry": {"coordinates":[-109.2333,33.8667],"type":"Point"}
}