{
  "id": 7540078,
  "type": "Feature",
  "properties": {
    "tgn:hierarchy":[
        "tgn:7540078",
        "tgn:7001242",
        "tgn:7001311",
        "tgn:7016833",
        "tgn:7029392"
    ],
    "tgn:id":7540078,
    "tgn:name:en":"Migwal el- Sambi",
    "tgn:placetype":[
        "aat:300006207"
    ]
},
  "bbox": [],
  "geometry": {"coordinates":[35.15,24.35],"type":"Point"}
}