{
  "id": 7536273,
  "type": "Feature",
  "properties": {
    "tgn:hierarchy":[
        "tgn:7536273",
        "tgn:7001242",
        "tgn:7016833",
        "tgn:1001113",
        "tgn:7029392"
    ],
    "tgn:id":7536273,
    "tgn:name":"Kafr ash Shaykh M\u016bs\u00e1 'Umr\u0101n",
    "tgn:placetype":[
        "aat:300008347"
    ]
},
  "bbox": [],
  "geometry": {"coordinates":[31.628611,30.616667],"type":"Point"}
}