{
  "id": 7113594,
  "type": "Feature",
  "properties": {
    "tgn:hierarchy":[
        "tgn:7113594",
        "tgn:1000003",
        "tgn:7003678",
        "tgn:7000084",
        "tgn:7029392"
    ],
    "tgn:id":7113594,
    "tgn:name":"R\u00f6s-Berg",
    "tgn:placetype":[
        "aat:300008777"
    ]
},
  "bbox": [],
  "geometry": {"coordinates":[9.75,51.216667],"type":"Point"}
}