{
  "id": 7008606,
  "type": "Feature",
  "properties": {
    "tgn:hierarchy":[
        "tgn:7008606",
        "tgn:1000003",
        "tgn:1000070",
        "tgn:7002897",
        "tgn:7029392"
    ],
    "tgn:id":7008606,
    "tgn:name":"Abondance",
    "tgn:placetype":[
        "aat:300008347"
    ]
},
  "bbox": [],
  "geometry": {"coordinates":[6.7333,46.2833],"type":"Point"}
}