<<<<<<< HEAD
{
  "id": 2152196,
  "type": "Feature",
  "properties": {
    "tgn:hierarchy":[
        "tgn:2152196",
        "tgn:1000001",
        "tgn:7012149",
        "tgn:2000383",
        "tgn:7007248",
        "tgn:7029392"
    ],
    "tgn:id":2152196,
    "tgn:name":"Bay Branch",
    "tgn:placetype":[
        "aat:300008699"
    ]
},
  "bbox": [],
  "geometry": {"coordinates":[-83.3333,30.9333],"type":"Point"}
}
=======
{"geometry":{"type":"Point","coordinates":[-83.333300,30.933300]},"type":"Feature","properties":{"hierarchy":["tgn:2152196","tgn:1000001","tgn:7012149","tgn:2000383","tgn:7007248","tgn:7029392"],"placetype":["aat:300008699"],"id":2152196,"name:xx":"Bay Branch"}}
>>>>>>> 03f74aca74312dbeaf24d7e61306dd6a786dc3d0
