{
  "id": 7040638,
  "type": "Feature",
  "properties": {
    "tgn:hierarchy":[
        "tgn:7040638",
        "tgn:7003168",
        "tgn:1000003",
        "tgn:7009760",
        "tgn:1000080",
        "tgn:7029392"
    ],
    "tgn:id":7040638,
    "tgn:name":"San Sano",
    "tgn:placetype":[
        "aat:300008347"
    ]
},
  "bbox": [],
  "geometry": {"coordinates":[11.383333,43.416667],"type":"Point"}
}