{
  "id": 1059076,
  "type": "Feature",
  "properties": {
    "tgn:hierarchy":[
        "tgn:1059076",
        "tgn:7011551",
        "tgn:1000004",
        "tgn:7018214",
        "tgn:7002435",
        "tgn:7029392"
    ],
    "tgn:id":1059076,
    "tgn:name":"Rylovichi",
    "tgn:placetype":[
        "aat:300008347"
    ]
},
  "bbox": [],
  "geometry": {"coordinates":[32.0667,52.4833],"type":"Point"}
}