{
  "id": 7114221,
  "type": "Feature",
  "properties": {
    "tgn:hierarchy":[
        "tgn:7114221",
        "tgn:1000003",
        "tgn:7003676",
        "tgn:7000084",
        "tgn:7029392"
    ],
    "tgn:id":7114221,
    "tgn:name":"Repkebach",
    "tgn:placetype":[
        "aat:300008699"
    ]
},
  "bbox": [],
  "geometry": {"coordinates":[9.683333,51.783333],"type":"Point"}
}