<<<<<<< HEAD
{
  "id": 7114221,
  "type": "Feature",
  "properties": {
    "tgn:hierarchy":[
        "tgn:7114221",
        "tgn:1000003",
        "tgn:7003676",
        "tgn:7000084",
        "tgn:7029392"
    ],
    "tgn:id":7114221,
    "tgn:name":"Repkebach",
    "tgn:placetype":[
        "aat:300008699"
    ]
},
  "bbox": [],
  "geometry": {"coordinates":[9.683333,51.783333],"type":"Point"}
}
=======
{"geometry":{"type":"Point","coordinates":[9.683333,51.783333]},"type":"Feature","properties":{"hierarchy":["tgn:7114221","tgn:1000003","tgn:7003676","tgn:7000084","tgn:7029392"],"placetype":["aat:300008699"],"id":7114221,"name:xx":"Repkebach"}}
>>>>>>> 03f74aca74312dbeaf24d7e61306dd6a786dc3d0
