{
  "id": 7567606,
  "type": "Feature",
  "properties": {
    "tgn:hierarchy":[
        "tgn:7567606",
        "tgn:1000004",
        "tgn:7000198",
        "tgn:1001996",
        "tgn:7029392"
    ],
    "tgn:id":7567606,
    "tgn:name:en":"Baror",
    "tgn:placetype":[
        "aat:300008347"
    ]
},
  "bbox": [],
  "geometry": {"coordinates":[77.018333,31.231389],"type":"Point"}
}