{
  "id": 7158763,
  "type": "Feature",
  "properties": {
    "tgn:hierarchy":[
        "tgn:7158763",
        "tgn:1000003",
        "tgn:7003682",
        "tgn:7000084",
        "tgn:7029392"
    ],
    "tgn:id":7158763,
    "tgn:name":"Hofweiler",
    "tgn:placetype":[
        "aat:300008347"
    ]
},
  "bbox": [],
  "geometry": {"coordinates":[6.616667,49.866667],"type":"Point"}
}