{
  "id": 7593415,
  "type": "Feature",
  "properties": {
    "tgn:hierarchy":[
        "tgn:7593415",
        "tgn:7005401",
        "tgn:1000001",
        "tgn:7005388",
        "tgn:7029392"
    ],
    "tgn:id":7593415,
    "tgn:name":"El Lim\u00f3n",
    "tgn:placetype":[
        "aat:300008347"
    ]
},
  "bbox": [],
  "geometry": {"coordinates":[-71.777,18.431],"type":"Point"}
}