{
  "id": 7277352,
  "type": "Feature",
  "properties": {
    "tgn:hierarchy":[
        "tgn:7277352",
        "tgn:1001637",
        "tgn:1000049",
        "tgn:1000002",
        "tgn:7029392"
    ],
    "tgn:id":7277352,
    "tgn:name":"Puerto Yana",
    "tgn:placetype":[
        "aat:300000206"
    ]
},
  "bbox": [],
  "geometry": {"coordinates":[-73.633333,-37.383333],"type":"Point"}
}