{
  "id": 7206358,
  "type": "Feature",
  "properties": {
    "tgn:hierarchy":[
        "tgn:7206358",
        "tgn:1000003",
        "tgn:7003676",
        "tgn:7000084",
        "tgn:7029392"
    ],
    "tgn:id":7206358,
    "tgn:name":"Cappeler Altendeich",
    "tgn:placetype":[
        "aat:300387200"
    ]
},
  "bbox": [],
  "geometry": {"coordinates":[8.566667,53.75],"type":"Point"}
}