{
  "id": 2443811,
  "type": "Feature",
  "properties": {
    "tgn:hierarchy":[
        "tgn:2443811",
        "tgn:1000001",
        "tgn:7012149",
        "tgn:2001449",
        "tgn:7007566",
        "tgn:7029392"
    ],
    "tgn:id":2443811,
    "tgn:name":"La Mesa del Pedregosa",
    "tgn:placetype":[
        "aat:300008798"
    ]
},
  "bbox": [],
  "geometry": {"coordinates":[-106.4667,36.0333],"type":"Point"}
}