{
  "id": 7232958,
  "type": "Feature",
  "properties": {
    "tgn:hierarchy":[
        "tgn:7232958",
        "tgn:7002707",
        "tgn:7002705",
        "tgn:1000003",
        "tgn:1000074",
        "tgn:7029392"
    ],
    "tgn:id":7232958,
    "tgn:name":"Lo\u00fatra Kav\u00e1silon",
    "tgn:placetype":[
        "aat:300008057"
    ]
},
  "bbox": [],
  "geometry": {"coordinates":[20.709722,40.106389],"type":"Point"}
}