{
  "id": 1088587,
  "type": "Feature",
  "properties": {
    "tgn:hierarchy":[
        "tgn:1088587",
        "tgn:1008355",
        "tgn:7001242",
        "tgn:1000157",
        "tgn:7029392"
    ],
    "tgn:id":1088587,
    "tgn:name":"Demb\u00e9ni",
    "tgn:placetype":[
        "aat:300008347"
    ]
},
  "bbox": [],
  "geometry": {"coordinates":[43.4167,-11.8333],"type":"Point"}
}