{
  "id": 7029678,
  "type": "Feature",
  "properties": {
    "tgn:hierarchy":[
        "tgn:7029678",
        "tgn:1000004",
        "tgn:7024355",
        "tgn:1000111",
        "tgn:7029392"
    ],
    "tgn:id":7029678,
    "tgn:name":"Fuling Shi",
    "tgn:placetype":[
        "aat:300387198"
    ]
},
  "bbox": [],
  "geometry": {"coordinates":[107.406,29.716],"type":"Point"}
}