{
  "id": 2186390,
  "type": "Feature",
  "properties": {
    "tgn:hierarchy":[
        "tgn:2186390",
        "tgn:1000001",
        "tgn:7012149",
        "tgn:2001226",
        "tgn:7007523",
        "tgn:7029392"
    ],
    "tgn:id":2186390,
    "tgn:name":"Bond Ridge",
    "tgn:placetype":[
        "aat:300266640"
    ]
},
  "bbox": [],
  "geometry": {"coordinates":[-92.1667,36.6667],"type":"Point"}
}