{
  "id": 7256505,
  "type": "Feature",
  "properties": {
    "tgn:hierarchy":[
        "tgn:7256505",
        "tgn:7003460",
        "tgn:1000003",
        "tgn:1000063",
        "tgn:4012014",
        "tgn:7029392"
    ],
    "tgn:id":7256505,
    "tgn:name":"Wieschen",
    "tgn:placetype":[
        "aat:300008347"
    ]
},
  "bbox": [],
  "geometry": {"coordinates":[6.066667,50.333333],"type":"Point"}
}