{
  "id": 2359638,
  "type": "Feature",
  "properties": {
    "tgn:hierarchy":[
        "tgn:2359638",
        "tgn:1000001",
        "tgn:2001418",
        "tgn:7012149",
        "tgn:7007526",
        "tgn:7029392"
    ],
    "tgn:id":2359638,
    "tgn:name":"Grantsville Canyon",
    "tgn:placetype":[
        "aat:300008761"
    ]
},
  "bbox": [],
  "geometry": {"coordinates":[-117.5167,38.85],"type":"Point"}
}