{
  "id": 2430189,
  "type": "Feature",
  "properties": {
    "tgn:hierarchy":[
        "tgn:2430189",
        "tgn:1000001",
        "tgn:7012149",
        "tgn:1002682",
        "tgn:7007710",
        "tgn:7029392"
    ],
    "tgn:id":2430189,
    "tgn:name":"Kahkhout Mountain",
    "tgn:placetype":[
        "aat:300008347"
    ]
},
  "bbox": [],
  "geometry": {"coordinates":[-75.05,41.0667],"type":"Point"}
}