{
  "id": 1113074,
  "type": "Feature",
  "properties": {
    "tgn:hierarchy":[
        "tgn:1113074",
        "tgn:7015075",
        "tgn:1000001",
        "tgn:7004772",
        "tgn:7029392"
    ],
    "tgn:id":1113074,
    "tgn:name":"Rodney Bay",
    "tgn:placetype":[
        "aat:300132316"
    ]
},
  "bbox": [],
  "geometry": {"coordinates":[-60.9667,14.0833],"type":"Point"}
}