{
  "id": 7099155,
  "type": "Feature",
  "properties": {
    "tgn:hierarchy":[
        "tgn:7099155",
        "tgn:1000003",
        "tgn:7003688",
        "tgn:7000084",
        "tgn:7029392"
    ],
    "tgn:id":7099155,
    "tgn:name":"Sieverstedtfeld",
    "tgn:placetype":[
        "aat:300000206"
    ]
},
  "bbox": [],
  "geometry": {"coordinates":[9.466667,54.633333],"type":"Point"}
}