{
  "id": 2421535,
  "type": "Feature",
  "properties": {
    "tgn:hierarchy":[
        "tgn:2421535",
        "tgn:1000001",
        "tgn:7012149",
        "tgn:1002418",
        "tgn:7007920",
        "tgn:7029392"
    ],
    "tgn:id":2421535,
    "tgn:name":"Jessie Slough",
    "tgn:placetype":[
        "aat:300008699"
    ]
},
  "bbox": [],
  "geometry": {"coordinates":[-124.0333,47.05],"type":"Point"}
}