{
  "id": 2034982,
  "type": "Feature",
  "properties": {
    "tgn:hierarchy":[
        "tgn:2034982",
        "tgn:1000001",
        "tgn:2000579",
        "tgn:7012149",
        "tgn:7007253",
        "tgn:7029392"
    ],
    "tgn:id":2034982,
    "tgn:name":"Ionia",
    "tgn:placetype":[
        "aat:300008347"
    ]
},
  "bbox": [],
  "geometry": {"coordinates":[-92.45,43.0333],"type":"Point"}
}