{
  "id": 2268208,
  "type": "Feature",
  "properties": {
    "tgn:hierarchy":[
        "tgn:2268208",
        "tgn:1000001",
        "tgn:7012149",
        "tgn:1002291",
        "tgn:7007826",
        "tgn:7029392"
    ],
    "tgn:id":2268208,
    "tgn:name":"Crooked Creek Lake",
    "tgn:placetype":[
        "aat:300008680"
    ]
},
  "bbox": [],
  "geometry": {"coordinates":[-96.65,29.5167],"type":"Point"}
}