{
  "id": 7386310,
  "type": "Feature",
  "properties": {
    "tgn:hierarchy":[
        "tgn:7386310",
        "tgn:7005587",
        "tgn:1000001",
        "tgn:7005560",
        "tgn:7029392"
    ],
    "tgn:id":7386310,
    "tgn:name":"Pe\u00f1a del \u00c1guila, Cerro",
    "tgn:placetype":[
        "aat:300008795"
    ]
},
  "bbox": [],
  "geometry": {"coordinates":[-98.65,20.116667],"type":"Point"}
}