<<<<<<< HEAD
{
  "id": 2332670,
  "type": "Feature",
  "properties": {
    "tgn:hierarchy":[
        "tgn:2332670",
        "tgn:1000001",
        "tgn:7012149",
        "tgn:2000220",
        "tgn:7007158",
        "tgn:7029392"
    ],
    "tgn:id":2332670,
    "tgn:name":"Flourspar Mine",
    "tgn:placetype":[
        "aat:300000390"
    ]
},
  "bbox": [],
  "geometry": {"coordinates":[-106.2833,40.9167],"type":"Point"}
}
=======
{"geometry":{"type":"Point","coordinates":[-106.283300,40.916700]},"type":"Feature","properties":{"hierarchy":["tgn:2332670","tgn:1000001","tgn:7012149","tgn:2000220","tgn:7007158","tgn:7029392"],"placetype":["aat:300000390"],"id":2332670,"name:xx":"Flourspar Mine"}}
>>>>>>> 03f74aca74312dbeaf24d7e61306dd6a786dc3d0
