{
  "id": 2417303,
  "type": "Feature",
  "properties": {
    "tgn:hierarchy":[
        "tgn:2417303",
        "tgn:1000001",
        "tgn:7012149",
        "tgn:2002160",
        "tgn:7007919",
        "tgn:7029392"
    ],
    "tgn:id":2417303,
    "tgn:name":"Jacks Creek",
    "tgn:placetype":[
        "aat:300008706"
    ]
},
  "bbox": [],
  "geometry": {"coordinates":[-79.7167,36.9833],"type":"Point"}
}