<<<<<<< HEAD
{
  "id": 2153311,
  "type": "Feature",
  "properties": {
    "tgn:hierarchy":[
        "tgn:2153311",
        "tgn:1000001",
        "tgn:7012149",
        "tgn:1002545",
        "tgn:7007157",
        "tgn:7029392"
    ],
    "tgn:id":2153311,
    "tgn:name":"Bean Canyon",
    "tgn:placetype":[
        "aat:300008761"
    ]
},
  "bbox": [],
  "geometry": {"coordinates":[-118.4,35.0],"type":"Point"}
}
=======
{"geometry":{"type":"Point","coordinates":[-118.400000,35.000000]},"type":"Feature","properties":{"hierarchy":["tgn:2153311","tgn:1000001","tgn:7012149","tgn:1002545","tgn:7007157","tgn:7029392"],"placetype":["aat:300008761"],"id":2153311,"name:xx":"Bean Canyon"}}
>>>>>>> 03f74aca74312dbeaf24d7e61306dd6a786dc3d0
