<<<<<<< HEAD
{
  "id": 2404899,
  "type": "Feature",
  "properties": {
    "tgn:hierarchy":[
        "tgn:2404899",
        "tgn:1000001",
        "tgn:7012149",
        "tgn:2002196",
        "tgn:7007919",
        "tgn:7029392"
    ],
    "tgn:id":2404899,
    "tgn:name":"Huddle Branch",
    "tgn:placetype":[
        "aat:300008699"
    ]
},
  "bbox": [],
  "geometry": {"coordinates":[-81.3333,36.9167],"type":"Point"}
}
=======
{"geometry":{"type":"Point","coordinates":[-81.333300,36.916700]},"type":"Feature","properties":{"hierarchy":["tgn:2404899","tgn:1000001","tgn:7012149","tgn:2002196","tgn:7007919","tgn:7029392"],"placetype":["aat:300008699"],"id":2404899,"name:xx":"Huddle Branch"}}
>>>>>>> 03f74aca74312dbeaf24d7e61306dd6a786dc3d0
