{
  "id": 2404899,
  "type": "Feature",
  "properties": {
    "tgn:hierarchy":[
        "tgn:2404899",
        "tgn:1000001",
        "tgn:7012149",
        "tgn:2002196",
        "tgn:7007919",
        "tgn:7029392"
    ],
    "tgn:id":2404899,
    "tgn:name":"Huddle Branch",
    "tgn:placetype":[
        "aat:300008699"
    ]
},
  "bbox": [],
  "geometry": {"coordinates":[-81.3333,36.9167],"type":"Point"}
}