<<<<<<< HEAD
{
  "id": 7026220,
  "type": "Feature",
  "properties": {
    "tgn:hierarchy":[
        "tgn:7026220",
        "tgn:7002445",
        "tgn:1000003",
        "tgn:1003654",
        "tgn:7008591",
        "tgn:7029392"
    ],
    "tgn:id":7026220,
    "tgn:name":"North Stifford",
    "tgn:placetype":[
        "aat:300008347"
    ]
},
  "bbox": [],
  "geometry": {"coordinates":[0.3,51.5],"type":"Point"}
}
=======
{"geometry":{"type":"Point","coordinates":[0.300000,51.500000]},"type":"Feature","properties":{"hierarchy":["tgn:7026220","tgn:7002445","tgn:1000003","tgn:1003654","tgn:7008591","tgn:7029392"],"placetype":["aat:300008347"],"id":7026220,"name:xx":"North Stifford"}}
>>>>>>> 03f74aca74312dbeaf24d7e61306dd6a786dc3d0
