{
  "id": 2242076,
  "type": "Feature",
  "properties": {
    "tgn:hierarchy":[
        "tgn:2242076",
        "tgn:1000001",
        "tgn:2000315",
        "tgn:7012149",
        "tgn:7007248",
        "tgn:7029392"
    ],
    "tgn:id":2242076,
    "tgn:name":"Clay Island",
    "tgn:placetype":[
        "aat:300008791"
    ]
},
  "bbox": [],
  "geometry": {"coordinates":[-82.0833,30.9667],"type":"Point"}
}