{
  "id": 2166418,
  "type": "Feature",
  "properties": {
    "tgn:hierarchy":[
        "tgn:2166418",
        "tgn:1000001",
        "tgn:7012149",
        "tgn:7007524",
        "tgn:7029392"
    ],
    "tgn:id":2166418,
    "tgn:name":"Big Bobcat Creek",
    "tgn:placetype":[
        "aat:300008706"
    ]
},
  "bbox": [],
  "geometry": {"coordinates":[-105.5333,45.7833],"type":"Point"}
}