{
  "id": 2390564,
  "type": "Feature",
  "properties": {
    "tgn:hierarchy":[
        "tgn:2390564",
        "tgn:1000001",
        "tgn:2002106",
        "tgn:7012149",
        "tgn:7007827",
        "tgn:7029392"
    ],
    "tgn:id":2390564,
    "tgn:name":"Highlands",
    "tgn:placetype":[
        "aat:300008347"
    ]
},
  "bbox": [],
  "geometry": {"coordinates":[-111.8833,40.8333],"type":"Point"}
}