{
  "id": 2452044,
  "type": "Feature",
  "properties": {
    "tgn:hierarchy":[
        "tgn:2452044",
        "tgn:1000001",
        "tgn:7012149",
        "tgn:2000927",
        "tgn:7007515",
        "tgn:7029392"
    ],
    "tgn:id":2452044,
    "tgn:name":"Little Birch Stream",
    "tgn:placetype":[
        "aat:300008699"
    ]
},
  "bbox": [],
  "geometry": {"coordinates":[-68.5167,44.9167],"type":"Point"}
}