{
  "id": 2271974,
  "type": "Feature",
  "properties": {
    "tgn:hierarchy":[
        "tgn:2271974",
        "tgn:1000001",
        "tgn:7016172",
        "tgn:7012149",
        "tgn:2000136",
        "tgn:7029392"
    ],
    "tgn:id":2271974,
    "tgn:name":"Curia Creek Ditch",
    "tgn:placetype":[
        "aat:300006075"
    ]
},
  "bbox": [],
  "geometry": {"coordinates":[-91.25,35.8667],"type":"Point"}
}