{
  "id": 2621033,
  "type": "Feature",
  "properties": {
    "tgn:hierarchy":[
        "tgn:2621033",
        "tgn:1000001",
        "tgn:7012149",
        "tgn:2000804",
        "tgn:7007255",
        "tgn:7029392"
    ],
    "tgn:id":2621033,
    "tgn:name":"Road Fork",
    "tgn:placetype":[
        "aat:300008699"
    ]
},
  "bbox": [],
  "geometry": {"coordinates":[-82.7667,37.8333],"type":"Point"}
}