{
  "id": 7088445,
  "type": "Feature",
  "properties": {
    "tgn:hierarchy":[
        "tgn:7088445",
        "tgn:7003669",
        "tgn:1000003",
        "tgn:7000084",
        "tgn:7029392"
    ],
    "tgn:id":7088445,
    "tgn:name":"Weihers\u00f6lden",
    "tgn:placetype":[
        "aat:300000206"
    ]
},
  "bbox": [],
  "geometry": {"coordinates":[12.283333,49.083333],"type":"Point"}
}