{
  "id": 7163313,
  "type": "Feature",
  "properties": {
    "tgn:hierarchy":[
        "tgn:7163313",
        "tgn:1000003",
        "tgn:7003677",
        "tgn:7000084",
        "tgn:7029392"
    ],
    "tgn:id":7163313,
    "tgn:name":"Im Sirrenberg",
    "tgn:placetype":[
        "aat:300387200"
    ]
},
  "bbox": [],
  "geometry": {"coordinates":[7.266667,51.366667],"type":"Point"}
}