{
  "id": 2163072,
  "type": "Feature",
  "properties": {
    "tgn:hierarchy":[
        "tgn:2163072",
        "tgn:1000001",
        "tgn:7012149",
        "tgn:7007520",
        "tgn:7029392"
    ],
    "tgn:id":2163072,
    "tgn:name":"Bennett Creek",
    "tgn:placetype":[
        "aat:300008706"
    ]
},
  "bbox": [],
  "geometry": {"coordinates":[-85.5667,43.5833],"type":"Point"}
}