{
  "id": 2671185,
  "type": "Feature",
  "properties": {
    "tgn:hierarchy":[
        "tgn:2671185",
        "tgn:1000001",
        "tgn:2001471",
        "tgn:7012149",
        "tgn:7007709",
        "tgn:7029392"
    ],
    "tgn:id":2671185,
    "tgn:name":"Smith Crossroads",
    "tgn:placetype":[
        "aat:300008347"
    ]
},
  "bbox": [],
  "geometry": {"coordinates":[-78.3667,34.6833],"type":"Point"}
}