{
  "id": 7209788,
  "type": "Feature",
  "properties": {
    "tgn:hierarchy":[
        "tgn:7209788",
        "tgn:1000003",
        "tgn:7003685",
        "tgn:7000084",
        "tgn:7029392"
    ],
    "tgn:id":7209788,
    "tgn:name":"Leipzig Bayerischer Bahnhof",
    "tgn:placetype":[
        "aat:300007783"
    ]
},
  "bbox": [],
  "geometry": {"coordinates":[12.381389,51.328611],"type":"Point"}
}