<<<<<<< HEAD
{
  "id": 7117722,
  "type": "Feature",
  "properties": {
    "tgn:hierarchy":[
        "tgn:7117722",
        "tgn:1000003",
        "tgn:7003678",
        "tgn:7000084",
        "tgn:7029392"
    ],
    "tgn:id":7117722,
    "tgn:name":"Ostheim",
    "tgn:placetype":[
        "aat:300008347"
    ]
},
  "bbox": [],
  "geometry": {"coordinates":[8.666667,50.4],"type":"Point"}
}
=======
{"geometry":{"type":"Point","coordinates":[8.666667,50.400000]},"type":"Feature","properties":{"hierarchy":["tgn:7117722","tgn:1000003","tgn:7003678","tgn:7000084","tgn:7029392"],"placetype":["aat:300008347"],"id":7117722,"name:xx":"Ostheim"}}
>>>>>>> 03f74aca74312dbeaf24d7e61306dd6a786dc3d0
