{
  "id": 2450080,
  "type": "Feature",
  "properties": {
    "tgn:hierarchy":[
        "tgn:2450080",
        "tgn:1000001",
        "tgn:7012149",
        "tgn:2001846",
        "tgn:7007825",
        "tgn:7029392"
    ],
    "tgn:id":2450080,
    "tgn:name":"Lindy Camp Branch",
    "tgn:placetype":[
        "aat:300008699"
    ]
},
  "bbox": [],
  "geometry": {"coordinates":[-81.95,36.4667],"type":"Point"}
}