{
  "id": 7552785,
  "type": "Feature",
  "properties": {
    "tgn:hierarchy":[
        "tgn:7552785",
        "tgn:1000004",
        "tgn:7000198",
        "tgn:1001882",
        "tgn:7029392"
    ],
    "tgn:id":7552785,
    "tgn:name:en":"Mudb\u0101l",
    "tgn:placetype":[
        "aat:300008347"
    ]
},
  "bbox": [],
  "geometry": {"coordinates":[76.816667,16.833333],"type":"Point"}
}