{
  "id": 7229189,
  "type": "Feature",
  "properties": {
    "tgn:hierarchy":[
        "tgn:7229189",
        "tgn:7002743",
        "tgn:7017076",
        "tgn:1000003",
        "tgn:1000074",
        "tgn:7029392"
    ],
    "tgn:id":7229189,
    "tgn:name":"Kardam\u00e1s",
    "tgn:placetype":[
        "aat:300008347"
    ]
},
  "bbox": [],
  "geometry": {"coordinates":[21.333333,37.766667],"type":"Point"}
}