<<<<<<< HEAD
{
  "id": 7478880,
  "type": "Feature",
  "properties": {
    "tgn:hierarchy":[
        "tgn:7478880",
        "tgn:7487020",
        "tgn:1000004",
        "tgn:1000141",
        "tgn:7029392"
    ],
    "tgn:id":7478880,
    "tgn:name":"Xindian Er Qiao",
    "tgn:placetype":[
        "aat:300007836"
    ]
},
  "bbox": [],
  "geometry": {"coordinates":[120.924758,24.548449],"type":"Point"}
}
=======
{"geometry":{"type":"Point","coordinates":[120.924758,24.548449]},"type":"Feature","properties":{"hierarchy":["tgn:7478880","tgn:7487020","tgn:1000004","tgn:1000141","tgn:7029392"],"placetype":["aat:300007836"],"id":7478880,"name:xx":"Xindian Er Qiao"}}
>>>>>>> 03f74aca74312dbeaf24d7e61306dd6a786dc3d0
