{
  "id": 2458839,
  "type": "Feature",
  "properties": {
    "tgn:hierarchy":[
        "tgn:2458839",
        "tgn:1000001",
        "tgn:7012149",
        "tgn:1002456",
        "tgn:7007826",
        "tgn:7029392"
    ],
    "tgn:id":2458839,
    "tgn:name":"Little Pasture Cove",
    "tgn:placetype":[
        "aat:300132316"
    ]
},
  "bbox": [],
  "geometry": {"coordinates":[-94.5333,29.5167],"type":"Point"}
}