<<<<<<< HEAD
{
  "id": 2257878,
  "type": "Feature",
  "properties": {
    "tgn:hierarchy":[
        "tgn:2257878",
        "tgn:7016099",
        "tgn:1000001",
        "tgn:7012149",
        "tgn:7007516",
        "tgn:7029392"
    ],
    "tgn:id":2257878,
    "tgn:name":"Correlli Estates",
    "tgn:placetype":[
        "aat:300008347"
    ]
},
  "bbox": [],
  "geometry": {"coordinates":[-76.4333,39.4],"type":"Point"}
}
=======
{"geometry":{"type":"Point","coordinates":[-76.433300,39.400000]},"type":"Feature","properties":{"hierarchy":["tgn:2257878","tgn:7016099","tgn:1000001","tgn:7012149","tgn:7007516","tgn:7029392"],"placetype":["aat:300008347"],"id":2257878,"name:xx":"Correlli Estates"}}
>>>>>>> 03f74aca74312dbeaf24d7e61306dd6a786dc3d0
