{
  "id": 2665024,
  "type": "Feature",
  "properties": {
    "tgn:hierarchy":[
        "tgn:2665024",
        "tgn:1000001",
        "tgn:7012149",
        "tgn:2000348",
        "tgn:7007248",
        "tgn:7029392"
    ],
    "tgn:id":2665024,
    "tgn:name":"Simpson Lake",
    "tgn:placetype":[
        "aat:300006191"
    ]
},
  "bbox": [],
  "geometry": {"coordinates":[-85.3167,34.2333],"type":"Point"}
}