{
  "id": 2412087,
  "type": "Feature",
  "properties": {
    "tgn:hierarchy":[
        "tgn:2412087",
        "tgn:1000001",
        "tgn:7006451",
        "tgn:7012149",
        "tgn:2000099",
        "tgn:7029392"
    ],
    "tgn:id":2412087,
    "tgn:name":"Indian Rock Tank",
    "tgn:placetype":[
        "aat:300006191"
    ]
},
  "bbox": [],
  "geometry": {"coordinates":[-110.2833,34.5667],"type":"Point"}
}