{
  "id": 2325455,
  "type": "Feature",
  "properties": {
    "tgn:hierarchy":[
        "tgn:2325455",
        "tgn:1000001",
        "tgn:1002257",
        "tgn:7012149",
        "tgn:7007919",
        "tgn:7029392"
    ],
    "tgn:id":2325455,
    "tgn:name":"Ferry Point",
    "tgn:placetype":[
        "aat:300008850"
    ]
},
  "bbox": [],
  "geometry": {"coordinates":[-76.8667,37.25],"type":"Point"}
}