{
  "id": 7253306,
  "type": "Feature",
  "properties": {
    "tgn:hierarchy":[
        "tgn:7253306",
        "tgn:7003466",
        "tgn:1000003",
        "tgn:1000063",
        "tgn:4012014",
        "tgn:7029392"
    ],
    "tgn:id":7253306,
    "tgn:name":"Trou de Leuvre",
    "tgn:placetype":[
        "aat:300008347"
    ]
},
  "bbox": [],
  "geometry": {"coordinates":[5.258863,50.284288],"type":"Point"}
}