{
  "id": 1042767,
  "type": "Feature",
  "properties": {
    "tgn:hierarchy":[
        "tgn:1042767",
        "tgn:7001198",
        "tgn:7003483",
        "tgn:1000003",
        "tgn:1000078",
        "tgn:7029392"
    ],
    "tgn:id":1042767,
    "tgn:name":"Dromore West",
    "tgn:placetype":[
        "aat:300008347"
    ]
},
  "bbox": [],
  "geometry": {"coordinates":[-8.8833,54.25],"type":"Point"}
}