{
  "id": 2165063,
  "type": "Feature",
  "properties": {
    "tgn:hierarchy":[
        "tgn:2165063",
        "tgn:1000001",
        "tgn:7012149",
        "tgn:2000904",
        "tgn:7007256",
        "tgn:7029392"
    ],
    "tgn:id":2165063,
    "tgn:name":"Bethel Bayou",
    "tgn:placetype":[
        "aat:300008699"
    ]
},
  "bbox": [],
  "geometry": {"coordinates":[-91.3333,29.6667],"type":"Point"}
}