<<<<<<< HEAD
{
  "id": 2255379,
  "type": "Feature",
  "properties": {
    "tgn:hierarchy":[
        "tgn:2255379",
        "tgn:1000001",
        "tgn:7012149",
        "tgn:7007255",
        "tgn:7029392"
    ],
    "tgn:id":2255379,
    "tgn:name":"Coopertown Creek",
    "tgn:placetype":[
        "aat:300008706"
    ]
},
  "bbox": [],
  "geometry": {"coordinates":[-84.5667,38.6],"type":"Point"}
}
=======
{"geometry":{"type":"Point","coordinates":[-84.566700,38.600000]},"type":"Feature","properties":{"hierarchy":["tgn:2255379","tgn:1000001","tgn:7012149","tgn:7007255","tgn:7029392"],"placetype":["aat:300008706"],"id":2255379,"name:xx":"Coopertown Creek"}}
>>>>>>> 03f74aca74312dbeaf24d7e61306dd6a786dc3d0
