{
  "id": 2308773,
  "type": "Feature",
  "properties": {
    "tgn:hierarchy":[
        "tgn:2308773",
        "tgn:1000001",
        "tgn:2000922",
        "tgn:7012149",
        "tgn:7007515",
        "tgn:7029392"
    ],
    "tgn:id":2308773,
    "tgn:name":"East Point",
    "tgn:placetype":[
        "aat:300008850"
    ]
},
  "bbox": [],
  "geometry": {"coordinates":[-68.3833,44.15],"type":"Point"}
}