{
  "id": 1116294,
  "type": "Feature",
  "properties": {
    "tgn:hierarchy":[
        "tgn:1116294",
        "tgn:1000966",
        "tgn:7001242",
        "tgn:1000156",
        "tgn:7029392"
    ],
    "tgn:id":1116294,
    "tgn:name":"Fittri, Lac",
    "tgn:placetype":[
        "aat:300008680"
    ]
},
  "bbox": [],
  "geometry": {"coordinates":[17.2833,12.7167],"type":"Point"}
}