{
  "id": 7032756,
  "type": "Feature",
  "properties": {
    "tgn:hierarchy":[
        "tgn:7032756",
        "tgn:1000001",
        "tgn:1001893",
        "tgn:7005560",
        "tgn:7029392"
    ],
    "tgn:id":7032756,
    "tgn:name":"Los Melones",
    "tgn:placetype":[
        "aat:300008347",
        "aat:300000810",
        "aat:300167671"
    ]
},
  "bbox": [],
  "geometry": {"coordinates":[-109.266667,28.833333],"type":"Point"}
}