{
  "id": 2351147,
  "type": "Feature",
  "properties": {
    "tgn:hierarchy":[
        "tgn:2351147",
        "tgn:1000001",
        "tgn:7012149",
        "tgn:2000430",
        "tgn:7007248",
        "tgn:7029392"
    ],
    "tgn:id":2351147,
    "tgn:name":"Glassy Knob",
    "tgn:placetype":[
        "aat:300008798"
    ]
},
  "bbox": [],
  "geometry": {"coordinates":[-83.7667,34.8667],"type":"Point"}
}