{
  "id": 7296224,
  "type": "Feature",
  "properties": {
    "tgn:hierarchy":[
        "tgn:7296224",
        "tgn:7002832",
        "tgn:7001158",
        "tgn:1000003",
        "tgn:1000095",
        "tgn:7029392"
    ],
    "tgn:id":7296224,
    "tgn:name":"Villambr\u00e1n de Cea",
    "tgn:placetype":[
        "aat:300008347"
    ]
},
  "bbox": [],
  "geometry": {"coordinates":[-4.883333,42.433333],"type":"Point"}
}