{
  "id": 2506282,
  "type": "Feature",
  "properties": {
    "tgn:hierarchy":[
        "tgn:2506282",
        "tgn:1000001",
        "tgn:1002480",
        "tgn:7012149",
        "tgn:7007564",
        "tgn:7029392"
    ],
    "tgn:id":2506282,
    "tgn:name":"Merrill Hill",
    "tgn:placetype":[
        "aat:300008798"
    ]
},
  "bbox": [],
  "geometry": {"coordinates":[-71.3833,42.7333],"type":"Point"}
}