{
  "id": 7486400,
  "type": "Feature",
  "properties": {
    "tgn:hierarchy":[
        "tgn:7486400",
        "tgn:1000004",
        "tgn:7492971",
        "tgn:1000141",
        "tgn:7029392"
    ],
    "tgn:id":7486400,
    "tgn:name":"Xiapou Xi",
    "tgn:placetype":[
        "aat:300008699"
    ]
},
  "bbox": [],
  "geometry": {"coordinates":[120.494086,22.441748],"type":"Point"}
}