{
  "id": 2416020,
  "type": "Feature",
  "properties": {
    "tgn:hierarchy":[
        "tgn:2416020",
        "tgn:1000001",
        "tgn:1002174",
        "tgn:7012149",
        "tgn:7007826",
        "tgn:7029392"
    ],
    "tgn:id":2416020,
    "tgn:name":"Ivy Mountain",
    "tgn:placetype":[
        "aat:300008798"
    ]
},
  "bbox": [],
  "geometry": {"coordinates":[-97.85,31.0333],"type":"Point"}
}