{
  "id": 7384550,
  "type": "Feature",
  "properties": {
    "tgn:hierarchy":[
        "tgn:7384550",
        "tgn:7005587",
        "tgn:1000001",
        "tgn:7005560",
        "tgn:7029392"
    ],
    "tgn:id":7384550,
    "tgn:name":"Ocotl\u00e1n",
    "tgn:placetype":[
        "aat:300008347"
    ]
},
  "bbox": [],
  "geometry": {"coordinates":[-98.733333,20.866667],"type":"Point"}
}