{
  "id": 7096086,
  "type": "Feature",
  "properties": {
    "tgn:hierarchy":[
        "tgn:7096086",
        "tgn:7003692",
        "tgn:1000003",
        "tgn:7000084",
        "tgn:7029392"
    ],
    "tgn:id":7096086,
    "tgn:name":"Sch\u00f6nbach",
    "tgn:placetype":[
        "aat:300008699"
    ]
},
  "bbox": [],
  "geometry": {"coordinates":[8.733333,48.016667],"type":"Point"}
}