{
  "id": 7402661,
  "type": "Feature",
  "properties": {
    "tgn:hierarchy":[
        "tgn:7402661",
        "tgn:1000001",
        "tgn:1001937",
        "tgn:7005560",
        "tgn:7029392"
    ],
    "tgn:id":7402661,
    "tgn:name":"Tabasco",
    "tgn:placetype":[
        "aat:300008347"
    ]
},
  "bbox": [],
  "geometry": {"coordinates":[-88.683333,19.975],"type":"Point"}
}