{
  "id": 2702421,
  "type": "Feature",
  "properties": {
    "tgn:hierarchy":[
        "tgn:2702421",
        "tgn:1000001",
        "tgn:2001266",
        "tgn:7012149",
        "tgn:7007524",
        "tgn:7029392"
    ],
    "tgn:id":2702421,
    "tgn:name":"Sullivan Valley",
    "tgn:placetype":[
        "aat:300008761"
    ]
},
  "bbox": [],
  "geometry": {"coordinates":[-111.9667,47.2833],"type":"Point"}
}