{
  "id": 7452628,
  "type": "Feature",
  "properties": {
    "tgn:hierarchy":[
        "tgn:7452628",
        "tgn:7002444",
        "tgn:1000003",
        "tgn:7029508",
        "tgn:7008591",
        "tgn:7029392"
    ],
    "tgn:id":7452628,
    "tgn:name:en":"Fore Holm",
    "tgn:placetype":[
        "aat:300008791"
    ]
},
  "bbox": [],
  "geometry": {"coordinates":[-1.366667,60.183333],"type":"Point"}
}