<<<<<<< HEAD
{
  "id": 7478180,
  "type": "Feature",
  "properties": {
    "tgn:hierarchy":[
        "tgn:7478180",
        "tgn:1000004",
        "tgn:7467799",
        "tgn:1000141",
        "tgn:7029392"
    ],
    "tgn:id":7478180,
    "tgn:name":"Linnei Erhao Ti",
    "tgn:placetype":[
        "aat:300006156"
    ]
},
  "bbox": [],
  "geometry": {"coordinates":[120.627,23.7808],"type":"Point"}
}
=======
{"geometry":{"type":"Point","coordinates":[120.627000,23.780800]},"type":"Feature","properties":{"hierarchy":["tgn:7478180","tgn:1000004","tgn:7467799","tgn:1000141","tgn:7029392"],"placetype":["aat:300006156"],"id":7478180,"name:xx":"Linnei Erhao Ti"}}
>>>>>>> 03f74aca74312dbeaf24d7e61306dd6a786dc3d0
