<<<<<<< HEAD
{
  "id": 7370206,
  "type": "Feature",
  "properties": {
    "tgn:hierarchy":[
        "tgn:7370206",
        "tgn:7005584",
        "tgn:1000001",
        "tgn:7005560",
        "tgn:7029392"
    ],
    "tgn:id":7370206,
    "tgn:name":"Jamaica",
    "tgn:placetype":[
        "aat:300008347"
    ]
},
  "bbox": [],
  "geometry": {"coordinates":[-100.933333,20.433333],"type":"Point"}
}
=======
{"geometry":{"type":"Point","coordinates":[-100.933333,20.433333]},"type":"Feature","properties":{"hierarchy":["tgn:7370206","tgn:7005584","tgn:1000001","tgn:7005560","tgn:7029392"],"placetype":["aat:300008347"],"id":7370206,"name:xx":"Jamaica"}}
>>>>>>> 03f74aca74312dbeaf24d7e61306dd6a786dc3d0
