{
  "id": 2567509,
  "type": "Feature",
  "properties": {
    "tgn:hierarchy":[
        "tgn:2567509",
        "tgn:1000001",
        "tgn:2001941",
        "tgn:7012149",
        "tgn:7007826",
        "tgn:7029392"
    ],
    "tgn:id":2567509,
    "tgn:name":"Papke Hill",
    "tgn:placetype":[
        "aat:300008798"
    ]
},
  "bbox": [],
  "geometry": {"coordinates":[-98.55,29.6333],"type":"Point"}
}