{
  "id": 2073303,
  "type": "Feature",
  "properties": {
    "tgn:hierarchy":[
        "tgn:2073303",
        "tgn:1000001",
        "tgn:7012149",
        "tgn:1002961",
        "tgn:7007568",
        "tgn:7029392"
    ],
    "tgn:id":2073303,
    "tgn:name":"Woodland",
    "tgn:placetype":[
        "aat:300008347"
    ]
},
  "bbox": [],
  "geometry": {"coordinates":[-74.3167,42.05],"type":"Point"}
}