{
  "id": 7322023,
  "type": "Feature",
  "properties": {
    "tgn:hierarchy":[
        "tgn:7322023",
        "tgn:1001768",
        "tgn:1000049",
        "tgn:1000002",
        "tgn:7029392"
    ],
    "tgn:id":7322023,
    "tgn:name":"Bayas, Islas",
    "tgn:placetype":[
        "aat:300008791"
    ]
},
  "bbox": [],
  "geometry": {"coordinates":[-71.683333,-33.35],"type":"Point"}
}