{
  "id": 2146910,
  "type": "Feature",
  "properties": {
    "tgn:hierarchy":[
        "tgn:2146910",
        "tgn:1000001",
        "tgn:7012149",
        "tgn:7007157",
        "tgn:1002858",
        "tgn:7029392"
    ],
    "tgn:id":2146910,
    "tgn:name":"Banner Canyon",
    "tgn:placetype":[
        "aat:300008761"
    ]
},
  "bbox": [],
  "geometry": {"coordinates":[-116.5833,33.0833],"type":"Point"}
}