{
  "id": 2135830,
  "type": "Feature",
  "properties": {
    "tgn:hierarchy":[
        "tgn:2135830",
        "tgn:1000001",
        "tgn:7012149",
        "tgn:7007923",
        "tgn:7029392"
    ],
    "tgn:id":2135830,
    "tgn:name":"Apperson Creek",
    "tgn:placetype":[
        "aat:300008706"
    ]
},
  "bbox": [],
  "geometry": {"coordinates":[-110.5333,42.7167],"type":"Point"}
}