{
  "id": 1086417,
  "type": "Feature",
  "properties": {
    "tgn:hierarchy":[
        "tgn:1086417",
        "tgn:1001513",
        "tgn:1000004",
        "tgn:7018450",
        "tgn:1000144",
        "tgn:7029392"
    ],
    "tgn:id":1086417,
    "tgn:name":"Hendek",
    "tgn:placetype":[
        "aat:300008347"
    ]
},
  "bbox": [],
  "geometry": {"coordinates":[30.75,40.7833],"type":"Point"}
}