{
  "id": 7345348,
  "type": "Feature",
  "properties": {
    "tgn:hierarchy":[
        "tgn:7345348",
        "tgn:7002826",
        "tgn:7001158",
        "tgn:1000003",
        "tgn:1000095",
        "tgn:7029392"
    ],
    "tgn:id":7345348,
    "tgn:name":"Alcoba de la Ribera",
    "tgn:placetype":[
        "aat:300008347"
    ]
},
  "bbox": [],
  "geometry": {"coordinates":[-5.833333,42.55],"type":"Point"}
}