{
  "id": 2370935,
  "type": "Feature",
  "properties": {
    "tgn:hierarchy":[
        "tgn:2370935",
        "tgn:1000001",
        "tgn:7012149",
        "tgn:2000229",
        "tgn:7007158",
        "tgn:7029392"
    ],
    "tgn:id":2370935,
    "tgn:name":"Hadfield Island",
    "tgn:placetype":[
        "aat:300008791"
    ]
},
  "bbox": [],
  "geometry": {"coordinates":[-103.2167,40.5667],"type":"Point"}
}