{
  "id": 2353093,
  "type": "Feature",
  "properties": {
    "tgn:hierarchy":[
        "tgn:2353093",
        "tgn:1000001",
        "tgn:7012149",
        "tgn:2000824",
        "tgn:7007255",
        "tgn:7029392"
    ],
    "tgn:id":2353093,
    "tgn:name":"Goff Branch",
    "tgn:placetype":[
        "aat:300008699"
    ]
},
  "bbox": [],
  "geometry": {"coordinates":[-82.3333,37.7333],"type":"Point"}
}