<<<<<<< HEAD
{
  "id": 7249123,
  "type": "Feature",
  "properties": {
    "tgn:hierarchy":[
        "tgn:7249123",
        "tgn:7003457",
        "tgn:1000003",
        "tgn:1000063",
        "tgn:7018236",
        "tgn:7029392"
    ],
    "tgn:id":7249123,
    "tgn:name":"Ploeg Ter Hagen",
    "tgn:placetype":[
        "aat:300008347"
    ]
},
  "bbox": [],
  "geometry": {"coordinates":[4.116667,50.966667],"type":"Point"}
}
=======
{"geometry":{"type":"Point","coordinates":[4.116667,50.966667]},"type":"Feature","properties":{"hierarchy":["tgn:7249123","tgn:7003457","tgn:1000003","tgn:1000063","tgn:7018236","tgn:7029392"],"placetype":["aat:300008347"],"id":7249123,"name:xx":"Ploeg Ter Hagen"}}
>>>>>>> 03f74aca74312dbeaf24d7e61306dd6a786dc3d0
