{
  "id": 7092554,
  "type": "Feature",
  "properties": {
    "tgn:hierarchy":[
        "tgn:7092554",
        "tgn:1000003",
        "tgn:7003676",
        "tgn:7000084",
        "tgn:7029392"
    ],
    "tgn:id":7092554,
    "tgn:name":"Ur-Berg",
    "tgn:placetype":[
        "aat:300008777"
    ]
},
  "bbox": [],
  "geometry": {"coordinates":[8.033333,52.166667],"type":"Point"}
}