{
  "id": 7293185,
  "type": "Feature",
  "properties": {
    "tgn:hierarchy":[
        "tgn:7293185",
        "tgn:1001692",
        "tgn:1000049",
        "tgn:1000002",
        "tgn:7029392"
    ],
    "tgn:id":7293185,
    "tgn:name":"Esquilluco, Estero",
    "tgn:placetype":[
        "aat:300008699"
    ]
},
  "bbox": [],
  "geometry": {"coordinates":[-73.083333,-38.366667],"type":"Point"}
}