<<<<<<< HEAD
{
  "id": 2257030,
  "type": "Feature",
  "properties": {
    "tgn:hierarchy":[
        "tgn:2257030",
        "tgn:1000001",
        "tgn:1002294",
        "tgn:7012149",
        "tgn:7007710",
        "tgn:7029392"
    ],
    "tgn:id":2257030,
    "tgn:name":"Corn Run",
    "tgn:placetype":[
        "aat:300008699"
    ]
},
  "bbox": [],
  "geometry": {"coordinates":[-76.4167,40.9667],"type":"Point"}
}
=======
{"geometry":{"type":"Point","coordinates":[-76.416700,40.966700]},"type":"Feature","properties":{"hierarchy":["tgn:2257030","tgn:1000001","tgn:1002294","tgn:7012149","tgn:7007710","tgn:7029392"],"placetype":["aat:300008699"],"id":2257030,"name:xx":"Corn Run"}}
>>>>>>> 03f74aca74312dbeaf24d7e61306dd6a786dc3d0
