{
  "id": 7313901,
  "type": "Feature",
  "properties": {
    "tgn:hierarchy":[
        "tgn:7313901",
        "tgn:1001702",
        "tgn:1000049",
        "tgn:1000002",
        "tgn:7029392"
    ],
    "tgn:id":7313901,
    "tgn:name":"Laura, Seno",
    "tgn:placetype":[
        "aat:300132316"
    ]
},
  "bbox": [],
  "geometry": {"coordinates":[-73.233333,-54.116667],"type":"Point"}
}