{
  "id": 7328322,
  "type": "Feature",
  "properties": {
    "tgn:hierarchy":[
        "tgn:7328322",
        "tgn:7002810",
        "tgn:7001158",
        "tgn:1000003",
        "tgn:1000095",
        "tgn:7029392"
    ],
    "tgn:id":7328322,
    "tgn:name":"Quintanamanvirgo",
    "tgn:placetype":[
        "aat:300008347"
    ]
},
  "bbox": [],
  "geometry": {"coordinates":[-3.95,41.75],"type":"Point"}
}