{
  "id": 2667473,
  "type": "Feature",
  "properties": {
    "tgn:hierarchy":[
        "tgn:2667473",
        "tgn:1000001",
        "tgn:7013649",
        "tgn:7012149",
        "tgn:7007251",
        "tgn:7029392"
    ],
    "tgn:id":2667473,
    "tgn:name":"Skokie Ditch",
    "tgn:placetype":[
        "aat:300006075"
    ]
},
  "bbox": [],
  "geometry": {"coordinates":[-87.7333,42.0833],"type":"Point"}
}