{
  "id": 7278036,
  "type": "Feature",
  "properties": {
    "tgn:hierarchy":[
        "tgn:7278036",
        "tgn:1001623",
        "tgn:1000049",
        "tgn:1000002",
        "tgn:7029392"
    ],
    "tgn:id":7278036,
    "tgn:name":"Wargny, Isla",
    "tgn:placetype":[
        "aat:300008791"
    ]
},
  "bbox": [],
  "geometry": {"coordinates":[-73.135278,-44.276667],"type":"Point"}
}