{
  "id": 7557012,
  "type": "Feature",
  "properties": {
    "tgn:hierarchy":[
        "tgn:7557012",
        "tgn:1000004",
        "tgn:7000198",
        "tgn:7016788",
        "tgn:7029392"
    ],
    "tgn:id":7557012,
    "tgn:name:en":"R\u0101imalw\u0101ra",
    "tgn:placetype":[
        "aat:300008347"
    ]
},
  "bbox": [],
  "geometry": {"coordinates":[73.006195,26.892141],"type":"Point"}
}