{
  "id": 7493270,
  "type": "Feature",
  "properties": {
    "tgn:hierarchy":[
        "tgn:7493270",
        "tgn:7468018",
        "tgn:1000004",
        "tgn:1000141",
        "tgn:7029392"
    ],
    "tgn:id":7493270,
    "tgn:name":"Jianan Dazhen",
    "tgn:placetype":[
        "aat:300006075"
    ]
},
  "bbox": [],
  "geometry": {"coordinates":[120.359317,23.596248],"type":"Point"}
}