{
  "id": 2429781,
  "type": "Feature",
  "properties": {
    "tgn:hierarchy":[
        "tgn:2429781",
        "tgn:1000001",
        "tgn:1002493",
        "tgn:7012149",
        "tgn:7007565",
        "tgn:7029392"
    ],
    "tgn:id":2429781,
    "tgn:name":"Jutland Lake",
    "tgn:placetype":[
        "aat:300006191"
    ]
},
  "bbox": [],
  "geometry": {"coordinates":[-74.95,40.6167],"type":"Point"}
}