<<<<<<< HEAD
{
  "id": 7022753,
  "type": "Feature",
  "properties": {
    "tgn:hierarchy":[
        "tgn:7022753",
        "tgn:1000001",
        "tgn:7012149",
        "tgn:1002992",
        "tgn:7007252",
        "tgn:7029392"
    ],
    "tgn:id":7022753,
    "tgn:name":"Daisy Hill",
    "tgn:placetype":[
        "aat:300008347",
        "aat:300387210"
    ]
},
  "bbox": [],
  "geometry": {"coordinates":[-85.9333,38.5],"type":"Point"}
}
=======
{"geometry":{"type":"Point","coordinates":[-85.933300,38.500000]},"type":"Feature","properties":{"hierarchy":["tgn:7022753","tgn:1000001","tgn:7012149","tgn:1002992","tgn:7007252","tgn:7029392"],"placetype":["aat:300008347","aat:300387210"],"id":7022753,"name:xx":"Daisy Hill"}}
>>>>>>> 03f74aca74312dbeaf24d7e61306dd6a786dc3d0
