<<<<<<< HEAD
{
  "id": 2159403,
  "type": "Feature",
  "properties": {
    "tgn:hierarchy":[
        "tgn:2159403",
        "tgn:1000001",
        "tgn:7012149",
        "tgn:2001251",
        "tgn:7007523",
        "tgn:7029392"
    ],
    "tgn:id":2159403,
    "tgn:name":"Bee Creek",
    "tgn:placetype":[
        "aat:300008706"
    ]
},
  "bbox": [],
  "geometry": {"coordinates":[-93.2333,36.6833],"type":"Point"}
}
=======
{"geometry":{"type":"Point","coordinates":[-93.233300,36.683300]},"type":"Feature","properties":{"hierarchy":["tgn:2159403","tgn:1000001","tgn:7012149","tgn:2001251","tgn:7007523","tgn:7029392"],"placetype":["aat:300008706"],"id":2159403,"name:xx":"Bee Creek"}}
>>>>>>> 03f74aca74312dbeaf24d7e61306dd6a786dc3d0
