<<<<<<< HEAD
{
  "id": 2335146,
  "type": "Feature",
  "properties": {
    "tgn:hierarchy":[
        "tgn:2335146",
        "tgn:1000001",
        "tgn:7012149",
        "tgn:2001115",
        "tgn:7007522",
        "tgn:7029392"
    ],
    "tgn:id":2335146,
    "tgn:name":"Fort Bayou Estates",
    "tgn:placetype":[
        "aat:300008347"
    ]
},
  "bbox": [],
  "geometry": {"coordinates":[-88.7833,30.4167],"type":"Point"}
}
=======
{"geometry":{"type":"Point","coordinates":[-88.783300,30.416700]},"type":"Feature","properties":{"hierarchy":["tgn:2335146","tgn:1000001","tgn:7012149","tgn:2001115","tgn:7007522","tgn:7029392"],"placetype":["aat:300008347"],"id":2335146,"name:xx":"Fort Bayou Estates"}}
>>>>>>> 03f74aca74312dbeaf24d7e61306dd6a786dc3d0
