{
  "id": 2151357,
  "type": "Feature",
  "properties": {
    "tgn:hierarchy":[
        "tgn:2151357",
        "tgn:1000001",
        "tgn:7012149",
        "tgn:2000237",
        "tgn:7007158",
        "tgn:7029392"
    ],
    "tgn:id":2151357,
    "tgn:name":"Bates Lakes",
    "tgn:placetype":[
        "aat:300008680"
    ]
},
  "bbox": [],
  "geometry": {"coordinates":[-107.5833,38.2167],"type":"Point"}
}