{
  "id": 2680300,
  "type": "Feature",
  "properties": {
    "tgn:hierarchy":[
        "tgn:2680300",
        "tgn:7006450",
        "tgn:1000001",
        "tgn:7012149",
        "tgn:7029392"
    ],
    "tgn:id":2680300,
    "tgn:name":"South Fork Upper Carmen River",
    "tgn:placetype":[
        "aat:300008707"
    ]
},
  "bbox": [],
  "geometry": {"coordinates":[-148.65,60.8333],"type":"Point"}
}