{
  "id": 7429573,
  "type": "Feature",
  "properties": {
    "tgn:hierarchy":[
        "tgn:7429573",
        "tgn:1001853",
        "tgn:1000001",
        "tgn:7005560",
        "tgn:7029392"
    ],
    "tgn:id":7429573,
    "tgn:name":"Estaci\u00f3n Amador",
    "tgn:placetype":[
        "aat:300007783"
    ]
},
  "bbox": [],
  "geometry": {"coordinates":[-103.483333,25.266667],"type":"Point"}
}