<<<<<<< HEAD
{
  "id": 2768480,
  "type": "Feature",
  "properties": {
    "tgn:hierarchy":[
        "tgn:2768480",
        "tgn:1000001",
        "tgn:7006451",
        "tgn:7012149",
        "tgn:2000099",
        "tgn:7029392"
    ],
    "tgn:id":2768480,
    "tgn:name":"Whitewall Springs",
    "tgn:placetype":[
        "aat:300008697"
    ]
},
  "bbox": [],
  "geometry": {"coordinates":[-110.5167,35.8],"type":"Point"}
}
=======
{"geometry":{"type":"Point","coordinates":[-110.516700,35.800000]},"type":"Feature","properties":{"hierarchy":["tgn:2768480","tgn:1000001","tgn:7006451","tgn:7012149","tgn:2000099","tgn:7029392"],"placetype":["aat:300008697"],"id":2768480,"name:xx":"Whitewall Springs"}}
>>>>>>> 03f74aca74312dbeaf24d7e61306dd6a786dc3d0
