{
  "id": 2561713,
  "type": "Feature",
  "properties": {
    "tgn:hierarchy":[
        "tgn:2561713",
        "tgn:1000001",
        "tgn:7012149",
        "tgn:7007157",
        "tgn:7014004",
        "tgn:7029392"
    ],
    "tgn:id":2561713,
    "tgn:name":"Ostrander Rocks",
    "tgn:placetype":[
        "aat:300008798"
    ]
},
  "bbox": [],
  "geometry": {"coordinates":[-119.5833,37.6833],"type":"Point"}
}