{
  "id": 2244888,
  "type": "Feature",
  "properties": {
    "tgn:hierarchy":[
        "tgn:2244888",
        "tgn:1000001",
        "tgn:2000671",
        "tgn:7012149",
        "tgn:7007254",
        "tgn:7029392"
    ],
    "tgn:id":2244888,
    "tgn:name":"Clough Valley",
    "tgn:placetype":[
        "aat:300008761"
    ]
},
  "bbox": [],
  "geometry": {"coordinates":[-102.0333,39.8667],"type":"Point"}
}