{
  "id": 2522155,
  "type": "Feature",
  "properties": {
    "tgn:hierarchy":[
        "tgn:2522155",
        "tgn:1000001",
        "tgn:2001410",
        "tgn:7012149",
        "tgn:7007526",
        "tgn:7029392"
    ],
    "tgn:id":2522155,
    "tgn:name":"Moon Cove",
    "tgn:placetype":[
        "aat:300132316"
    ]
},
  "bbox": [],
  "geometry": {"coordinates":[-114.7833,36.0667],"type":"Point"}
}