{
  "id": 2120290,
  "type": "Feature",
  "properties": {
    "tgn:hierarchy":[
        "tgn:2120290",
        "tgn:1000001",
        "tgn:2002259",
        "tgn:7012149",
        "tgn:7013961",
        "tgn:7029392"
    ],
    "tgn:id":2120290,
    "tgn:name":"Valley Fork",
    "tgn:placetype":[
        "aat:300008347"
    ]
},
  "bbox": [],
  "geometry": {"coordinates":[-81.1167,38.5167],"type":"Point"}
}