{
  "id": 2735838,
  "type": "Feature",
  "properties": {
    "tgn:hierarchy":[
        "tgn:2735838",
        "tgn:1000001",
        "tgn:7012149",
        "tgn:2000181",
        "tgn:7007157",
        "tgn:7029392"
    ],
    "tgn:id":2735838,
    "tgn:name":"Twin Lakes",
    "tgn:placetype":[
        "aat:300008680"
    ]
},
  "bbox": [],
  "geometry": {"coordinates":[-123.7333,40.7167],"type":"Point"}
}