{
  "id": 1061758,
  "type": "Feature",
  "properties": {
    "tgn:hierarchy":[
        "tgn:1061758",
        "tgn:7002759",
        "tgn:7008909",
        "tgn:1000003",
        "tgn:1000095",
        "tgn:7029392"
    ],
    "tgn:id":1061758,
    "tgn:name":"Almud\u00e9bar",
    "tgn:placetype":[
        "aat:300008347"
    ]
},
  "bbox": [],
  "geometry": {"coordinates":[-0.581406,42.042549],"type":"Point"}
}