{
  "id": 2770886,
  "type": "Feature",
  "properties": {
    "tgn:hierarchy":[
        "tgn:2770886",
        "tgn:1000001",
        "tgn:7012149",
        "tgn:1003042",
        "tgn:7007920",
        "tgn:7029392"
    ],
    "tgn:id":2770886,
    "tgn:name":"Wildcat Creek",
    "tgn:placetype":[
        "aat:300008706"
    ]
},
  "bbox": [],
  "geometry": {"coordinates":[-121.25,46.6667],"type":"Point"}
}