{
  "id": 2616754,
  "type": "Feature",
  "properties": {
    "tgn:hierarchy":[
        "tgn:2616754",
        "tgn:1000001",
        "tgn:7012149",
        "tgn:2001722",
        "tgn:7007708",
        "tgn:7029392"
    ],
    "tgn:id":2616754,
    "tgn:name":"Rich Creek",
    "tgn:placetype":[
        "aat:300008706"
    ]
},
  "bbox": [],
  "geometry": {"coordinates":[-116.8833,45.2333],"type":"Point"}
}