{
  "id": 7017812,
  "type": "Feature",
  "properties": {
    "tgn:hierarchy":[
        "tgn:7017812",
        "tgn:1000001",
        "tgn:7012149",
        "tgn:1002732",
        "tgn:7007710",
        "tgn:7029392"
    ],
    "tgn:id":7017812,
    "tgn:name":"Fairview",
    "tgn:placetype":[
        "aat:300008347"
    ]
},
  "bbox": [],
  "geometry": {"coordinates":[-76.5667,40.7833],"type":"Point"}
}