<<<<<<< HEAD
{
  "id": 7020288,
  "type": "Feature",
  "properties": {
    "tgn:hierarchy":[
        "tgn:7020288",
        "tgn:1000001",
        "tgn:7012149",
        "tgn:2001508",
        "tgn:7007709",
        "tgn:7029392"
    ],
    "tgn:id":7020288,
    "tgn:name":"Doubletop Mountain",
    "tgn:placetype":[
        "aat:300008798"
    ]
},
  "bbox": [],
  "geometry": {"coordinates":[-83.0833,35.2667],"type":"Point"}
}
=======
{"geometry":{"type":"Point","coordinates":[-83.083300,35.266700]},"type":"Feature","properties":{"hierarchy":["tgn:7020288","tgn:1000001","tgn:7012149","tgn:2001508","tgn:7007709","tgn:7029392"],"placetype":["aat:300008798"],"id":7020288,"name:xx":"Doubletop Mountain"}}
>>>>>>> 03f74aca74312dbeaf24d7e61306dd6a786dc3d0
