{
  "id": 7076323,
  "type": "Feature",
  "properties": {
    "tgn:hierarchy":[
        "tgn:7076323",
        "tgn:1000003",
        "tgn:7003682",
        "tgn:7000084",
        "tgn:7029392"
    ],
    "tgn:id":7076323,
    "tgn:name":"Kirchwald",
    "tgn:placetype":[
        "aat:300008347"
    ]
},
  "bbox": [],
  "geometry": {"coordinates":[7.15,50.366667],"type":"Point"}
}