{
  "id": 2488199,
  "type": "Feature",
  "properties": {
    "tgn:hierarchy":[
        "tgn:2488199",
        "tgn:1000001",
        "tgn:7012149",
        "tgn:7029392"
    ],
    "tgn:id":2488199,
    "tgn:name":"Magnusson Hollow",
    "tgn:placetype":[
        "aat:300008761"
    ]
},
  "bbox": [],
  "geometry": {"coordinates":[-86.85,34.9667],"type":"Point"}
}