{
  "id": 1137260,
  "type": "Feature",
  "properties": {
    "tgn:hierarchy":[
        "tgn:1137260",
        "tgn:6001332",
        "tgn:1000003",
        "tgn:7006660",
        "tgn:7029392"
    ],
    "tgn:id":1137260,
    "tgn:name":"Bilozir'ya",
    "tgn:placetype":[
        "aat:300008347",
        "aat:300008375"
    ]
},
  "bbox": [],
  "geometry": {"coordinates":[31.5833,49.4833],"type":"Point"}
}