{
  "id": 7317645,
  "type": "Feature",
  "properties": {
    "tgn:hierarchy":[
        "tgn:7317645",
        "tgn:1001630",
        "tgn:1000049",
        "tgn:1000002",
        "tgn:7029392"
    ],
    "tgn:id":7317645,
    "tgn:name":"Cortina, Quebrada",
    "tgn:placetype":[
        "aat:300266554",
        "aat:300008699"
    ]
},
  "bbox": [],
  "geometry": {"coordinates":[-69.516667,-26.65],"type":"Point"}
}