{
  "id": 2188611,
  "type": "Feature",
  "properties": {
    "tgn:hierarchy":[
        "tgn:2188611",
        "tgn:1000001",
        "tgn:7012149",
        "tgn:2000220",
        "tgn:7007158",
        "tgn:7029392"
    ],
    "tgn:id":2188611,
    "tgn:name":"Bottom Draw",
    "tgn:placetype":[
        "aat:300008761"
    ]
},
  "bbox": [],
  "geometry": {"coordinates":[-106.1167,40.65],"type":"Point"}
}