{
  "id": 1056659,
  "type": "Feature",
  "properties": {
    "tgn:hierarchy":[
        "tgn:1056659",
        "tgn:1000004",
        "tgn:1003398",
        "tgn:7018214",
        "tgn:7002435",
        "tgn:7029392"
    ],
    "tgn:id":1056659,
    "tgn:name":"Yasnaya Polyana",
    "tgn:placetype":[
        "aat:300008347"
    ]
},
  "bbox": [],
  "geometry": {"coordinates":[53.0833,51.7167],"type":"Point"}
}