{
  "id": 7588626,
  "type": "Feature",
  "properties": {
    "tgn:hierarchy":[
        "tgn:7588626",
        "tgn:1000004",
        "tgn:7000198",
        "tgn:1001894",
        "tgn:7029392"
    ],
    "tgn:id":7588626,
    "tgn:name:en":"Khopa",
    "tgn:placetype":[
        "aat:300008347"
    ]
},
  "bbox": [],
  "geometry": {"coordinates":[80.251967,24.313288],"type":"Point"}
}