{
  "id": 2280092,
  "type": "Feature",
  "properties": {
    "tgn:hierarchy":[
        "tgn:2280092",
        "tgn:1000001",
        "tgn:7012149",
        "tgn:2001281",
        "tgn:7007524",
        "tgn:7029392"
    ],
    "tgn:id":2280092,
    "tgn:name":"Dearborn Creek",
    "tgn:placetype":[
        "aat:300008706"
    ]
},
  "bbox": [],
  "geometry": {"coordinates":[-112.0333,46.0167],"type":"Point"}
}