{
  "id": 2374685,
  "type": "Feature",
  "properties": {
    "tgn:hierarchy":[
        "tgn:2374685",
        "tgn:1000001",
        "tgn:7012149",
        "tgn:2001716",
        "tgn:7007708",
        "tgn:7029392"
    ],
    "tgn:id":2374685,
    "tgn:name":"Hand Lake",
    "tgn:placetype":[
        "aat:300008680"
    ]
},
  "bbox": [],
  "geometry": {"coordinates":[-121.8667,44.2167],"type":"Point"}
}