{
  "id": 7283162,
  "type": "Feature",
  "properties": {
    "tgn:hierarchy":[
        "tgn:7283162",
        "tgn:1001637",
        "tgn:1000049",
        "tgn:1000002",
        "tgn:7029392"
    ],
    "tgn:id":7283162,
    "tgn:name":"Paso Ancho, Estero",
    "tgn:placetype":[
        "aat:300008699"
    ]
},
  "bbox": [],
  "geometry": {"coordinates":[-72.783333,-37.416667],"type":"Point"}
}