{
  "id": 2692361,
  "type": "Feature",
  "properties": {
    "tgn:hierarchy":[
        "tgn:2692361",
        "tgn:1000001",
        "tgn:1002260",
        "tgn:7012149",
        "tgn:7007920",
        "tgn:7029392"
    ],
    "tgn:id":2692361,
    "tgn:name":"Stayman",
    "tgn:placetype":[
        "aat:300008347"
    ]
},
  "bbox": [],
  "geometry": {"coordinates":[-120.0833,47.75],"type":"Point"}
}