<<<<<<< HEAD
{
  "id": 7171579,
  "type": "Feature",
  "properties": {
    "tgn:hierarchy":[
        "tgn:7171579",
        "tgn:1000003",
        "tgn:7003685",
        "tgn:7000084",
        "tgn:7029392"
    ],
    "tgn:id":7171579,
    "tgn:name":"Hilligersches Vorwerk",
    "tgn:placetype":[
        "aat:300000206"
    ]
},
  "bbox": [],
  "geometry": {"coordinates":[13.366667,50.9],"type":"Point"}
}
=======
{"geometry":{"type":"Point","coordinates":[13.366667,50.900000]},"type":"Feature","properties":{"hierarchy":["tgn:7171579","tgn:1000003","tgn:7003685","tgn:7000084","tgn:7029392"],"placetype":["aat:300000206"],"id":7171579,"name:xx":"Hilligersches Vorwerk"}}
>>>>>>> 03f74aca74312dbeaf24d7e61306dd6a786dc3d0
