{
  "id": 2095630,
  "type": "Feature",
  "properties": {
    "tgn:hierarchy":[
        "tgn:2095630",
        "tgn:1000001",
        "tgn:7012149",
        "tgn:2001766",
        "tgn:7007712",
        "tgn:7029392"
    ],
    "tgn:id":2095630,
    "tgn:name":"Cross Anchor",
    "tgn:placetype":[
        "aat:300008347"
    ]
},
  "bbox": [],
  "geometry": {"coordinates":[-81.85,34.6333],"type":"Point"}
}