{
  "id": 2364473,
  "type": "Feature",
  "properties": {
    "tgn:hierarchy":[
        "tgn:2364473",
        "tgn:1000001",
        "tgn:1002410",
        "tgn:7012149",
        "tgn:7007565",
        "tgn:7029392"
    ],
    "tgn:id":2364473,
    "tgn:name":"Green Tree",
    "tgn:placetype":[
        "aat:300008347"
    ]
},
  "bbox": [],
  "geometry": {"coordinates":[-75.0667,39.75],"type":"Point"}
}