{
  "id": 7073095,
  "type": "Feature",
  "properties": {
    "tgn:hierarchy":[
        "tgn:7073095",
        "tgn:1000003",
        "tgn:7003676",
        "tgn:7000084",
        "tgn:7029392"
    ],
    "tgn:id":7073095,
    "tgn:name":"Tannenkamp",
    "tgn:placetype":[
        "aat:300008863"
    ]
},
  "bbox": [],
  "geometry": {"coordinates":[7.233333,52.85],"type":"Point"}
}