{
  "id": 2292841,
  "type": "Feature",
  "properties": {
    "tgn:hierarchy":[
        "tgn:2292841",
        "tgn:1000001",
        "tgn:7012149",
        "tgn:7007157",
        "tgn:2000186",
        "tgn:7029392"
    ],
    "tgn:id":2292841,
    "tgn:name":"Dorris Reservoir",
    "tgn:placetype":[
        "aat:300006191"
    ]
},
  "bbox": [],
  "geometry": {"coordinates":[-120.4833,41.4833],"type":"Point"}
}