{
  "id": 7501750,
  "type": "Feature",
  "properties": {
    "tgn:hierarchy":[
        "tgn:7501750",
        "tgn:7001004",
        "tgn:1000004",
        "tgn:1000141",
        "tgn:7029392"
    ],
    "tgn:id":7501750,
    "tgn:name":"Changtan Diaoqiao",
    "tgn:placetype":[
        "aat:300007836"
    ]
},
  "bbox": [],
  "geometry": {"coordinates":[120.422778,22.914444],"type":"Point"}
}