{
  "id": 2420024,
  "type": "Feature",
  "properties": {
    "tgn:hierarchy":[
        "tgn:2420024",
        "tgn:1000001",
        "tgn:7012149",
        "tgn:1002554",
        "tgn:7007920",
        "tgn:7029392"
    ],
    "tgn:id":2420024,
    "tgn:name":"Jebe Swale",
    "tgn:placetype":[
        "aat:300008699"
    ]
},
  "bbox": [],
  "geometry": {"coordinates":[-121.2667,45.9333],"type":"Point"}
}