<<<<<<< HEAD
{
  "id": 7362348,
  "type": "Feature",
  "properties": {
    "tgn:hierarchy":[
        "tgn:7362348",
        "tgn:7005578",
        "tgn:1000001",
        "tgn:7005560",
        "tgn:7029392"
    ],
    "tgn:id":7362348,
    "tgn:name":"El Paraguas",
    "tgn:placetype":[
        "aat:300008347"
    ]
},
  "bbox": [],
  "geometry": {"coordinates":[-91.116667,18.166667],"type":"Point"}
}
=======
{"geometry":{"type":"Point","coordinates":[-91.116667,18.166667]},"type":"Feature","properties":{"hierarchy":["tgn:7362348","tgn:7005578","tgn:1000001","tgn:7005560","tgn:7029392"],"placetype":["aat:300008347"],"id":7362348,"name:xx":"El Paraguas"}}
>>>>>>> 03f74aca74312dbeaf24d7e61306dd6a786dc3d0
