<<<<<<< HEAD
{
  "id": 7351353,
  "type": "Feature",
  "properties": {
    "tgn:hierarchy":[
        "tgn:7351353",
        "tgn:7005580",
        "tgn:1000001",
        "tgn:7005560",
        "tgn:7029392"
    ],
    "tgn:id":7351353,
    "tgn:name":"Cachi",
    "tgn:placetype":[
        "aat:300008347"
    ]
},
  "bbox": [],
  "geometry": {"coordinates":[-92.7,16.25],"type":"Point"}
}
=======
{"geometry":{"type":"Point","coordinates":[-92.700000,16.250000]},"type":"Feature","properties":{"hierarchy":["tgn:7351353","tgn:7005580","tgn:1000001","tgn:7005560","tgn:7029392"],"placetype":["aat:300008347"],"id":7351353,"name:xx":"Cachi"}}
>>>>>>> 03f74aca74312dbeaf24d7e61306dd6a786dc3d0
