{
  "id": 2494525,
  "type": "Feature",
  "properties": {
    "tgn:hierarchy":[
        "tgn:2494525",
        "tgn:1000001",
        "tgn:7012149",
        "tgn:1002920",
        "tgn:7007568",
        "tgn:7029392"
    ],
    "tgn:id":2494525,
    "tgn:name":"Martin Hill",
    "tgn:placetype":[
        "aat:300008798"
    ]
},
  "bbox": [],
  "geometry": {"coordinates":[-77.05,42.05],"type":"Point"}
}