{
  "id": 1066104,
  "type": "Feature",
  "properties": {
    "tgn:hierarchy":[
        "tgn:1066104",
        "tgn:1000004",
        "tgn:7002188",
        "tgn:1000108",
        "tgn:7029392"
    ],
    "tgn:id":1066104,
    "tgn:name":"Kyondo",
    "tgn:placetype":[
        "aat:300008347"
    ]
},
  "bbox": [],
  "geometry": {"coordinates":[98.05,16.5833],"type":"Point"}
}