{
  "id": 7186645,
  "type": "Feature",
  "properties": {
    "tgn:hierarchy":[
        "tgn:7186645",
        "tgn:7003692",
        "tgn:1000003",
        "tgn:7000084",
        "tgn:7029392"
    ],
    "tgn:id":7186645,
    "tgn:name":"Grabenstetten",
    "tgn:placetype":[
        "aat:300008347"
    ]
},
  "bbox": [],
  "geometry": {"coordinates":[9.466667,48.516667],"type":"Point"}
}