{
  "id": 2040809,
  "type": "Feature",
  "properties": {
    "tgn:hierarchy":[
        "tgn:2040809",
        "tgn:1000001",
        "tgn:7012149",
        "tgn:1003036",
        "tgn:7007255",
        "tgn:7029392"
    ],
    "tgn:id":2040809,
    "tgn:name":"Pisgah",
    "tgn:placetype":[
        "aat:300008347",
        "aat:300387210"
    ]
},
  "bbox": [],
  "geometry": {"coordinates":[-84.65,38.05],"type":"Point"}
}