{
  "id": 7581099,
  "type": "Feature",
  "properties": {
    "tgn:hierarchy":[
        "tgn:7581099",
        "tgn:1000004",
        "tgn:7000198",
        "tgn:7016722",
        "tgn:7029392"
    ],
    "tgn:id":7581099,
    "tgn:name:en":"S\u016brajpur",
    "tgn:placetype":[
        "aat:300008347"
    ]
},
  "bbox": [],
  "geometry": {"coordinates":[77.479139,28.511159],"type":"Point"}
}