{
  "id": 1042351,
  "type": "Feature",
  "properties": {
    "tgn:hierarchy":[
        "tgn:1042351",
        "tgn:7006350",
        "tgn:1000003",
        "tgn:7006278",
        "tgn:7029392"
    ],
    "tgn:id":1042351,
    "tgn:name":"Hegyeshalom",
    "tgn:placetype":[
        "aat:300008347"
    ]
},
  "bbox": [],
  "geometry": {"coordinates":[17.1667,47.9167],"type":"Point"}
}