{
  "id": 7002842,
  "type": "Feature",
  "properties": {
    "tgn:hierarchy":[
        "tgn:7002842",
        "tgn:7001158",
        "tgn:1000003",
        "tgn:1000095",
        "tgn:7029392"
    ],
    "tgn:id":7002842,
    "tgn:name":"Soria",
    "tgn:placetype":[
        "aat:300387145",
        "aat:300000774"
    ]
},
  "bbox": [],
  "geometry": {"coordinates":[-2.666,41.666],"type":"Point"}
}