{
  "id": 7511300,
  "type": "Feature",
  "properties": {
    "tgn:hierarchy":[
        "tgn:7511300",
        "tgn:1009227",
        "tgn:1000226",
        "tgn:7016822",
        "tgn:1000006",
        "tgn:7029392"
    ],
    "tgn:id":7511300,
    "tgn:name:en":"Tree Island",
    "tgn:placetype":[
        "aat:300008791"
    ]
},
  "bbox": [],
  "geometry": {"coordinates":[168.383333,-44.95],"type":"Point"}
}