{
  "id": 2386722,
  "type": "Feature",
  "properties": {
    "tgn:hierarchy":[
        "tgn:2386722",
        "tgn:1000001",
        "tgn:7012149",
        "tgn:2001312",
        "tgn:7007524",
        "tgn:7029392"
    ],
    "tgn:id":2386722,
    "tgn:name":"Hermans Spring",
    "tgn:placetype":[
        "aat:300008697"
    ]
},
  "bbox": [],
  "geometry": {"coordinates":[-106.4333,48.3333],"type":"Point"}
}