{
  "id": 7426771,
  "type": "Feature",
  "properties": {
    "tgn:hierarchy":[
        "tgn:7426771",
        "tgn:1000001",
        "tgn:7005594",
        "tgn:7005560",
        "tgn:7029392"
    ],
    "tgn:id":7426771,
    "tgn:name":"Los Remedios",
    "tgn:placetype":[
        "aat:300008347"
    ]
},
  "bbox": [],
  "geometry": {"coordinates":[-101.316667,22.916667],"type":"Point"}
}