<<<<<<< HEAD
{
  "id": 7115807,
  "type": "Feature",
  "properties": {
    "tgn:hierarchy":[
        "tgn:7115807",
        "tgn:1000003",
        "tgn:7003676",
        "tgn:7000084",
        "tgn:7029392"
    ],
    "tgn:id":7115807,
    "tgn:name":"Ohnhorst",
    "tgn:placetype":[
        "aat:300008347"
    ]
},
  "bbox": [],
  "geometry": {"coordinates":[10.566667,52.4],"type":"Point"}
}
=======
{"geometry":{"type":"Point","coordinates":[10.566667,52.400000]},"type":"Feature","properties":{"hierarchy":["tgn:7115807","tgn:1000003","tgn:7003676","tgn:7000084","tgn:7029392"],"placetype":["aat:300008347"],"id":7115807,"name:xx":"Ohnhorst"}}
>>>>>>> 03f74aca74312dbeaf24d7e61306dd6a786dc3d0
