{
  "id": 1049527,
  "type": "Feature",
  "properties": {
    "tgn:hierarchy":[
        "tgn:1049527",
        "tgn:1000003",
        "tgn:7024117",
        "tgn:7006366",
        "tgn:7029392"
    ],
    "tgn:id":1049527,
    "tgn:name":"Szypliszki",
    "tgn:placetype":[
        "aat:300008347"
    ]
},
  "bbox": [],
  "geometry": {"coordinates":[23.0667,54.25],"type":"Point"}
}