{
  "id": 7013290,
  "type": "Feature",
  "properties": {
    "tgn:hierarchy":[
        "tgn:7013290",
        "tgn:1000001",
        "tgn:7012149",
        "tgn:7007157",
        "tgn:1002857",
        "tgn:2010925",
        "tgn:7029392"
    ],
    "tgn:id":7013290,
    "tgn:name":"Alta Loma",
    "tgn:placetype":[
        "aat:300008347",
        "aat:300008375"
    ]
},
  "bbox": [],
  "geometry": {"coordinates":[-117.5833,34.1167],"type":"Point"}
}