{
  "id": 2185207,
  "type": "Feature",
  "properties": {
    "tgn:hierarchy":[
        "tgn:2185207",
        "tgn:1000001",
        "tgn:7012149",
        "tgn:2002378",
        "tgn:7007923",
        "tgn:7029392"
    ],
    "tgn:id":2185207,
    "tgn:name":"Boggy Creek",
    "tgn:placetype":[
        "aat:300008706"
    ]
},
  "bbox": [],
  "geometry": {"coordinates":[-104.5833,42.9333],"type":"Point"}
}