{
  "id": 1055630,
  "type": "Feature",
  "properties": {
    "tgn:hierarchy":[
        "tgn:1055630",
        "tgn:1000004",
        "tgn:1003314",
        "tgn:7018214",
        "tgn:7002435",
        "tgn:7029392"
    ],
    "tgn:id":1055630,
    "tgn:name":"Kordovo",
    "tgn:placetype":[
        "aat:300008347"
    ]
},
  "bbox": [],
  "geometry": {"coordinates":[93.2333,54.1667],"type":"Point"}
}