<<<<<<< HEAD
{
  "id": 7362875,
  "type": "Feature",
  "properties": {
    "tgn:hierarchy":[
        "tgn:7362875",
        "tgn:7005581",
        "tgn:1000001",
        "tgn:7005560",
        "tgn:7029392"
    ],
    "tgn:id":7362875,
    "tgn:name":"El Mercade\u00f1o",
    "tgn:placetype":[
        "aat:300008347"
    ]
},
  "bbox": [],
  "geometry": {"coordinates":[-104.9,27.166667],"type":"Point"}
}
=======
{"geometry":{"type":"Point","coordinates":[-104.900000,27.166667]},"type":"Feature","properties":{"hierarchy":["tgn:7362875","tgn:7005581","tgn:1000001","tgn:7005560","tgn:7029392"],"placetype":["aat:300008347"],"id":7362875,"name:xx":"El Mercade\u00f1o"}}
>>>>>>> 03f74aca74312dbeaf24d7e61306dd6a786dc3d0
