{
  "id": 2598002,
  "type": "Feature",
  "properties": {
    "tgn:hierarchy":[
        "tgn:2598002",
        "tgn:1000001",
        "tgn:1002293",
        "tgn:7012149",
        "tgn:7007708",
        "tgn:7029392"
    ],
    "tgn:id":2598002,
    "tgn:name":"Prescott Bar",
    "tgn:placetype":[
        "aat:300132348"
    ]
},
  "bbox": [],
  "geometry": {"coordinates":[-122.8833,46.05],"type":"Point"}
}