{
  "id": 2684666,
  "type": "Feature",
  "properties": {
    "tgn:hierarchy":[
        "tgn:2684666",
        "tgn:1000001",
        "tgn:1002714",
        "tgn:7012149",
        "tgn:7007159",
        "tgn:7029392"
    ],
    "tgn:id":2684666,
    "tgn:name":"Spinning Mill Brook",
    "tgn:placetype":[
        "aat:300008699"
    ]
},
  "bbox": [],
  "geometry": {"coordinates":[-72.25,41.6833],"type":"Point"}
}