{
  "id": 2663926,
  "type": "Feature",
  "properties": {
    "tgn:hierarchy":[
        "tgn:2663926",
        "tgn:1000001",
        "tgn:7019982",
        "tgn:7012149",
        "tgn:7007517",
        "tgn:7029392"
    ],
    "tgn:id":2663926,
    "tgn:name":"Silver Lake Reservoir",
    "tgn:placetype":[
        "aat:300006191"
    ]
},
  "bbox": [],
  "geometry": {"coordinates":[-72.6333,42.0667],"type":"Point"}
}