{
  "id": 7521235,
  "type": "Feature",
  "properties": {
    "tgn:hierarchy":[
        "tgn:7521235",
        "tgn:7001242",
        "tgn:7016833",
        "tgn:1001142",
        "tgn:7029392"
    ],
    "tgn:id":7521235,
    "tgn:name:en":"A\u1e29mar al Qibl\u012b, Al 'Ilw al",
    "tgn:placetype":[
        "aat:300008777"
    ]
},
  "bbox": [],
  "geometry": {"coordinates":[30.016667,28.95],"type":"Point"}
}