{
  "id": 7493138,
  "type": "Feature",
  "properties": {
    "tgn:hierarchy":[
        "tgn:7493138",
        "tgn:1000004",
        "tgn:7001014",
        "tgn:1000141",
        "tgn:7029392"
    ],
    "tgn:id":7493138,
    "tgn:name":"Shengpingliao",
    "tgn:placetype":[
        "aat:300008347"
    ]
},
  "bbox": [],
  "geometry": {"coordinates":[120.300675,23.696915],"type":"Point"}
}