{
  "id": 2600790,
  "type": "Feature",
  "properties": {
    "tgn:hierarchy":[
        "tgn:2600790",
        "tgn:1000001",
        "tgn:7012149",
        "tgn:2002380",
        "tgn:7007923",
        "tgn:7029392"
    ],
    "tgn:id":2600790,
    "tgn:name":"Pump Reservoir",
    "tgn:placetype":[
        "aat:300006191"
    ]
},
  "bbox": [],
  "geometry": {"coordinates":[-104.8167,41.9667],"type":"Point"}
}