{
  "id": 7384374,
  "type": "Feature",
  "properties": {
    "tgn:hierarchy":[
        "tgn:7384374",
        "tgn:1000001",
        "tgn:7005591",
        "tgn:7005560",
        "tgn:7029392"
    ],
    "tgn:id":7384374,
    "tgn:name":"Ocotes",
    "tgn:placetype":[
        "aat:300008347"
    ]
},
  "bbox": [],
  "geometry": {"coordinates":[-96.733333,15.933333],"type":"Point"}
}