<<<<<<< HEAD
{
  "id": 2407646,
  "type": "Feature",
  "properties": {
    "tgn:hierarchy":[
        "tgn:2407646",
        "tgn:1000001",
        "tgn:7012149",
        "tgn:2002381",
        "tgn:7007923",
        "tgn:7029392"
    ],
    "tgn:id":2407646,
    "tgn:name":"Hurlburt Creek",
    "tgn:placetype":[
        "aat:300008706"
    ]
},
  "bbox": [],
  "geometry": {"coordinates":[-107.0833,44.6],"type":"Point"}
}
=======
{"geometry":{"type":"Point","coordinates":[-107.083300,44.600000]},"type":"Feature","properties":{"hierarchy":["tgn:2407646","tgn:1000001","tgn:7012149","tgn:2002381","tgn:7007923","tgn:7029392"],"placetype":["aat:300008706"],"id":2407646,"name:xx":"Hurlburt Creek"}}
>>>>>>> 03f74aca74312dbeaf24d7e61306dd6a786dc3d0
