{
  "id": 2067871,
  "type": "Feature",
  "properties": {
    "tgn:hierarchy":[
        "tgn:2067871",
        "tgn:1000001",
        "tgn:7012149",
        "tgn:1002708",
        "tgn:7007568",
        "tgn:7029392"
    ],
    "tgn:id":2067871,
    "tgn:name":"Atlantic Beach",
    "tgn:placetype":[
        "aat:300008347"
    ]
},
  "bbox": [],
  "geometry": {"coordinates":[-73.7167,40.5833],"type":"Point"}
}