{
  "id": 2349494,
  "type": "Feature",
  "properties": {
    "tgn:hierarchy":[
        "tgn:2349494",
        "tgn:1000001",
        "tgn:1002260",
        "tgn:7012149",
        "tgn:7007920",
        "tgn:7029392"
    ],
    "tgn:id":2349494,
    "tgn:name":"Gill Creek",
    "tgn:placetype":[
        "aat:300008706"
    ]
},
  "bbox": [],
  "geometry": {"coordinates":[-120.8833,47.7333],"type":"Point"}
}