{
  "id": 7346709,
  "type": "Feature",
  "properties": {
    "tgn:hierarchy":[
        "tgn:7346709",
        "tgn:7002759",
        "tgn:7008909",
        "tgn:1000003",
        "tgn:1000095",
        "tgn:7029392"
    ],
    "tgn:id":7346709,
    "tgn:name":"Belarra",
    "tgn:placetype":[
        "aat:300008347"
    ]
},
  "bbox": [],
  "geometry": {"coordinates":[-0.362649,42.376251],"type":"Point"}
}