{
  "id": 2500385,
  "type": "Feature",
  "properties": {
    "tgn:hierarchy":[
        "tgn:2500385",
        "tgn:1000001",
        "tgn:7012149",
        "tgn:1002785",
        "tgn:7007920",
        "tgn:7029392"
    ],
    "tgn:id":2500385,
    "tgn:name":"McDermott Point",
    "tgn:placetype":[
        "aat:300008850"
    ]
},
  "bbox": [],
  "geometry": {"coordinates":[-122.7333,47.1833],"type":"Point"}
}