{
  "id": 2220511,
  "type": "Feature",
  "properties": {
    "tgn:hierarchy":[
        "tgn:2220511",
        "tgn:1002232",
        "tgn:1000001",
        "tgn:7012149",
        "tgn:7007565",
        "tgn:7029392"
    ],
    "tgn:id":2220511,
    "tgn:name":"Cape May Harbor",
    "tgn:placetype":[
        "aat:300132316"
    ]
},
  "bbox": [],
  "geometry": {"coordinates":[-74.8833,38.95],"type":"Point"}
}