{
  "id": 2532029,
  "type": "Feature",
  "properties": {
    "tgn:hierarchy":[
        "tgn:2532029",
        "tgn:1000001",
        "tgn:7012149",
        "tgn:7007158",
        "tgn:2000253",
        "tgn:7029392"
    ],
    "tgn:id":2532029,
    "tgn:name":"Mumper Corner",
    "tgn:placetype":[
        "aat:300008347"
    ]
},
  "bbox": [],
  "geometry": {"coordinates":[-104.6833,40.45],"type":"Point"}
}