{
  "id": 7085056,
  "type": "Feature",
  "properties": {
    "tgn:hierarchy":[
        "tgn:7085056",
        "tgn:1000003",
        "tgn:7003678",
        "tgn:7000084",
        "tgn:7029392"
    ],
    "tgn:id":7085056,
    "tgn:name":"Wetter-Ost, Forst",
    "tgn:placetype":[
        "aat:300008863"
    ]
},
  "bbox": [],
  "geometry": {"coordinates":[8.766667,50.933333],"type":"Point"}
}