{
  "id": 7424398,
  "type": "Feature",
  "properties": {
    "tgn:hierarchy":[
        "tgn:7424398",
        "tgn:1000001",
        "tgn:7005601",
        "tgn:7005560",
        "tgn:7029392"
    ],
    "tgn:id":7424398,
    "tgn:name":"El Seminario",
    "tgn:placetype":[
        "aat:300008347"
    ]
},
  "bbox": [],
  "geometry": {"coordinates":[-103.583333,22.283333],"type":"Point"}
}