{
  "id": 7392384,
  "type": "Feature",
  "properties": {
    "tgn:hierarchy":[
        "tgn:7392384",
        "tgn:7005581",
        "tgn:1000001",
        "tgn:7005560",
        "tgn:7029392"
    ],
    "tgn:id":7392384,
    "tgn:name":"Rancho Los Lamentos",
    "tgn:placetype":[
        "aat:300008347"
    ]
},
  "bbox": [],
  "geometry": {"coordinates":[-108.083333,31.75],"type":"Point"}
}