{
  "id": 2588272,
  "type": "Feature",
  "properties": {
    "tgn:hierarchy":[
        "tgn:2588272",
        "tgn:1000001",
        "tgn:2000593",
        "tgn:7012149",
        "tgn:7007253",
        "tgn:7029392"
    ],
    "tgn:id":2588272,
    "tgn:name":"Plum Creek",
    "tgn:placetype":[
        "aat:300008706"
    ]
},
  "bbox": [],
  "geometry": {"coordinates":[-91.6833,42.85],"type":"Point"}
}