{
  "id": 2453752,
  "type": "Feature",
  "properties": {
    "tgn:hierarchy":[
        "tgn:2453752",
        "tgn:2001559",
        "tgn:1000001",
        "tgn:7012149",
        "tgn:7007705",
        "tgn:7029392"
    ],
    "tgn:id":2453752,
    "tgn:name":"Little Coulee",
    "tgn:placetype":[
        "aat:300008761"
    ]
},
  "bbox": [],
  "geometry": {"coordinates":[-99.2167,48.1833],"type":"Point"}
}