{
  "id": 2396709,
  "type": "Feature",
  "properties": {
    "tgn:hierarchy":[
        "tgn:2396709",
        "tgn:2000999",
        "tgn:1000001",
        "tgn:7012149",
        "tgn:7007521",
        "tgn:7029392"
    ],
    "tgn:id":2396709,
    "tgn:name":"Holy Water Lake",
    "tgn:placetype":[
        "aat:300008680"
    ]
},
  "bbox": [],
  "geometry": {"coordinates":[-93.7333,47.0167],"type":"Point"}
}