{
  "id": 2689239,
  "type": "Feature",
  "properties": {
    "tgn:hierarchy":[
        "tgn:2689239",
        "tgn:1000001",
        "tgn:7006451",
        "tgn:7012149",
        "tgn:2000103",
        "tgn:7029392"
    ],
    "tgn:id":2689239,
    "tgn:name":"Squaw Creek",
    "tgn:placetype":[
        "aat:300008706"
    ]
},
  "bbox": [],
  "geometry": {"coordinates":[-111.7167,34.25],"type":"Point"}
}