{
  "id": 2343266,
  "type": "Feature",
  "properties": {
    "tgn:hierarchy":[
        "tgn:2343266",
        "tgn:1000001",
        "tgn:7012149",
        "tgn:2001711",
        "tgn:7007708",
        "tgn:7029392"
    ],
    "tgn:id":2343266,
    "tgn:name":"Gaerky Creek",
    "tgn:placetype":[
        "aat:300008706"
    ]
},
  "bbox": [],
  "geometry": {"coordinates":[-122.6167,42.2333],"type":"Point"}
}