{
  "id": 1130701,
  "type": "Feature",
  "properties": {
    "tgn:hierarchy":[
        "tgn:1130701",
        "tgn:7000895",
        "tgn:1000004",
        "tgn:1000988",
        "tgn:1000120",
        "tgn:7029392"
    ],
    "tgn:id":1130701,
    "tgn:name":"Tedori-gawa",
    "tgn:placetype":[
        "aat:300008707"
    ]
},
  "bbox": [],
  "geometry": {"coordinates":[136.4667,36.4833],"type":"Point"}
}