{
  "id": 7098990,
  "type": "Feature",
  "properties": {
    "tgn:hierarchy":[
        "tgn:7098990",
        "tgn:1000003",
        "tgn:7003688",
        "tgn:7000084",
        "tgn:7029392"
    ],
    "tgn:id":7098990,
    "tgn:name":"Selker Noor",
    "tgn:placetype":[
        "aat:300008680"
    ]
},
  "bbox": [],
  "geometry": {"coordinates":[9.583333,54.483333],"type":"Point"}
}