{
  "id": 7224596,
  "type": "Feature",
  "properties": {
    "tgn:hierarchy":[
        "tgn:7224596",
        "tgn:4003773",
        "tgn:7001395",
        "tgn:1000003",
        "tgn:1000074",
        "tgn:7029392"
    ],
    "tgn:id":7224596,
    "tgn:name":"Ner\u00e1\u00efda",
    "tgn:placetype":[
        "aat:300008347"
    ]
},
  "bbox": [],
  "geometry": {"coordinates":[21.685,39.181944],"type":"Point"}
}