{
  "id": 7399017,
  "type": "Feature",
  "properties": {
    "tgn:hierarchy":[
        "tgn:7399017",
        "tgn:1000001",
        "tgn:1001893",
        "tgn:7005560",
        "tgn:7029392"
    ],
    "tgn:id":7399017,
    "tgn:name":"San Luis Boro",
    "tgn:placetype":[
        "aat:300008347"
    ]
},
  "bbox": [],
  "geometry": {"coordinates":[-99.855,19.811944],"type":"Point"}
}