{
  "id": 2276102,
  "type": "Feature",
  "properties": {
    "tgn:hierarchy":[
        "tgn:2276102",
        "tgn:1000001",
        "tgn:7012149",
        "tgn:7016021",
        "tgn:7007568",
        "tgn:7029392"
    ],
    "tgn:id":2276102,
    "tgn:name":"Darning Needle Pond",
    "tgn:placetype":[
        "aat:300008680"
    ]
},
  "bbox": [],
  "geometry": {"coordinates":[-74.7667,44.1167],"type":"Point"}
}