{
  "id": 2585438,
  "type": "Feature",
  "properties": {
    "tgn:hierarchy":[
        "tgn:2585438",
        "tgn:1000001",
        "tgn:7012149",
        "tgn:2002371",
        "tgn:7007923",
        "tgn:7029392"
    ],
    "tgn:id":2585438,
    "tgn:name":"Pinto Park Lake",
    "tgn:placetype":[
        "aat:300008680"
    ]
},
  "bbox": [],
  "geometry": {"coordinates":[-109.05,42.7333],"type":"Point"}
}