{
  "id": 2241059,
  "type": "Feature",
  "properties": {
    "tgn:hierarchy":[
        "tgn:2241059",
        "tgn:1000001",
        "tgn:7016172",
        "tgn:7012149",
        "tgn:2000155",
        "tgn:7029392"
    ],
    "tgn:id":2241059,
    "tgn:name":"Clark Creek",
    "tgn:placetype":[
        "aat:300008706"
    ]
},
  "bbox": [],
  "geometry": {"coordinates":[-93.3833,36.0167],"type":"Point"}
}