{
  "id": 7559265,
  "type": "Feature",
  "properties": {
    "tgn:hierarchy":[
        "tgn:7559265",
        "tgn:1000004",
        "tgn:7000198",
        "tgn:7031783",
        "tgn:7029392"
    ],
    "tgn:id":7559265,
    "tgn:name:en":"Rohr\u0101b\u0101ndh",
    "tgn:placetype":[
        "aat:300008347"
    ]
},
  "bbox": [],
  "geometry": {"coordinates":[86.499692,23.664495],"type":"Point"}
}