{
  "id": 7353223,
  "type": "Feature",
  "properties": {
    "tgn:hierarchy":[
        "tgn:7353223",
        "tgn:1000001",
        "tgn:7005600",
        "tgn:7005560",
        "tgn:7029392"
    ],
    "tgn:id":7353223,
    "tgn:name":"Becanch\u00e9n",
    "tgn:placetype":[
        "aat:300008347"
    ]
},
  "bbox": [],
  "geometry": {"coordinates":[-89.366667,19.833333],"type":"Point"}
}