{
  "id": 2212700,
  "type": "Feature",
  "properties": {
    "tgn:hierarchy":[
        "tgn:2212700",
        "tgn:1000001",
        "tgn:7012149",
        "tgn:2000358",
        "tgn:7007248",
        "tgn:7029392"
    ],
    "tgn:id":2212700,
    "tgn:name":"C and S Financial Corporation Lake",
    "tgn:placetype":[
        "aat:300006191"
    ]
},
  "bbox": [],
  "geometry": {"coordinates":[-84.1167,33.8833],"type":"Point"}
}