{
  "id": 2284884,
  "type": "Feature",
  "properties": {
    "tgn:hierarchy":[
        "tgn:2284884",
        "tgn:1000001",
        "tgn:7006451",
        "tgn:2000092",
        "tgn:7012149",
        "tgn:7029392"
    ],
    "tgn:id":2284884,
    "tgn:name":"Deva Temple",
    "tgn:placetype":[
        "aat:300008798"
    ]
},
  "bbox": [],
  "geometry": {"coordinates":[-112.0167,36.15],"type":"Point"}
}