{
  "id": 2281709,
  "type": "Feature",
  "properties": {
    "tgn:hierarchy":[
        "tgn:2281709",
        "tgn:1000001",
        "tgn:7012149",
        "tgn:2001302",
        "tgn:7007524",
        "tgn:7029392"
    ],
    "tgn:id":2281709,
    "tgn:name":"Deer Creek",
    "tgn:placetype":[
        "aat:300008706"
    ]
},
  "bbox": [],
  "geometry": {"coordinates":[-104.0833,48.0667],"type":"Point"}
}