{
  "id": 2082396,
  "type": "Feature",
  "properties": {
    "tgn:hierarchy":[
        "tgn:2082396",
        "tgn:1000001",
        "tgn:7012149",
        "tgn:1002658",
        "tgn:7007706",
        "tgn:7029392"
    ],
    "tgn:id":2082396,
    "tgn:name":"Wabash",
    "tgn:placetype":[
        "aat:300008347"
    ]
},
  "bbox": [],
  "geometry": {"coordinates":[-84.75,40.5333],"type":"Point"}
}