{
  "id": 7386180,
  "type": "Feature",
  "properties": {
    "tgn:hierarchy":[
        "tgn:7386180",
        "tgn:7005586",
        "tgn:1000001",
        "tgn:7005560",
        "tgn:7029392"
    ],
    "tgn:id":7386180,
    "tgn:name":"Prieto, Cerro",
    "tgn:placetype":[
        "aat:300008795"
    ]
},
  "bbox": [],
  "geometry": {"coordinates":[-104.566667,19.283333],"type":"Point"}
}