{
  "id": 7561374,
  "type": "Feature",
  "properties": {
    "tgn:hierarchy":[
        "tgn:7561374",
        "tgn:1000004",
        "tgn:7000198",
        "tgn:7016722",
        "tgn:7029392"
    ],
    "tgn:id":7561374,
    "tgn:name:en":"R\u0101mpura",
    "tgn:placetype":[
        "aat:300008347"
    ]
},
  "bbox": [],
  "geometry": {"coordinates":[79.17419,26.887994],"type":"Point"}
}