{
  "id": 2523467,
  "type": "Feature",
  "properties": {
    "tgn:hierarchy":[
        "tgn:2523467",
        "tgn:1000001",
        "tgn:2000922",
        "tgn:7012149",
        "tgn:7007515",
        "tgn:7029392"
    ],
    "tgn:id":2523467,
    "tgn:name":"Moose Island",
    "tgn:placetype":[
        "aat:300008791"
    ]
},
  "bbox": [],
  "geometry": {"coordinates":[-68.6833,44.1333],"type":"Point"}
}