{
  "id": 1123593,
  "type": "Feature",
  "properties": {
    "tgn:hierarchy":[
        "tgn:1123593",
        "tgn:1000004",
        "tgn:7000198",
        "tgn:1001977",
        "tgn:7029392"
    ],
    "tgn:id":1123593,
    "tgn:name":"Dw\u0101rkeswar",
    "tgn:placetype":[
        "aat:300008707"
    ]
},
  "bbox": [],
  "geometry": {"coordinates":[87.3333,23.0833],"type":"Point"}
}