{
  "id": 2659119,
  "type": "Feature",
  "properties": {
    "tgn:hierarchy":[
        "tgn:2659119",
        "tgn:1000001",
        "tgn:2001705",
        "tgn:7012149",
        "tgn:7007708",
        "tgn:7029392"
    ],
    "tgn:id":2659119,
    "tgn:name":"Shevlin",
    "tgn:placetype":[
        "aat:300008347"
    ]
},
  "bbox": [],
  "geometry": {"coordinates":[-121.3833,43.7667],"type":"Point"}
}