{
  "id": 7037871,
  "type": "Feature",
  "properties": {
    "tgn:hierarchy":[
        "tgn:7037871",
        "tgn:7007850",
        "tgn:1003491",
        "tgn:1000003",
        "tgn:1000080",
        "tgn:7029392"
    ],
    "tgn:id":7037871,
    "tgn:name":"Varale, Fiumara",
    "tgn:placetype":[
        "aat:300008699"
    ]
},
  "bbox": [],
  "geometry": {"coordinates":[16.033333,38.483333],"type":"Point"}
}