{
  "id": 2477647,
  "type": "Feature",
  "properties": {
    "tgn:hierarchy":[
        "tgn:2477647",
        "tgn:1000001",
        "tgn:7012149",
        "tgn:1002876",
        "tgn:7007710",
        "tgn:7029392"
    ],
    "tgn:id":2477647,
    "tgn:name":"MWIS Site Number Six-Anthracite Reservoir",
    "tgn:placetype":[
        "aat:300006191"
    ]
},
  "bbox": [],
  "geometry": {"coordinates":[-76.9833,40.45],"type":"Point"}
}