{
  "id": 7470862,
  "type": "Feature",
  "properties": {
    "tgn:hierarchy":[
        "tgn:7470862",
        "tgn:1000004",
        "tgn:7001009",
        "tgn:1000141",
        "tgn:7029392"
    ],
    "tgn:id":7470862,
    "tgn:name":"Jiufangcuo",
    "tgn:placetype":[
        "aat:300008347"
    ]
},
  "bbox": [],
  "geometry": {"coordinates":[120.783104,24.27621],"type":"Point"}
}