{
  "id": 2297943,
  "type": "Feature",
  "properties": {
    "tgn:hierarchy":[
        "tgn:2297943",
        "tgn:1000001",
        "tgn:7012149",
        "tgn:2001665",
        "tgn:7007707",
        "tgn:7029392"
    ],
    "tgn:id":2297943,
    "tgn:name":"Dry Hollow Creek",
    "tgn:placetype":[
        "aat:300008706"
    ]
},
  "bbox": [],
  "geometry": {"coordinates":[-97.1167,33.85],"type":"Point"}
}