{
  "id": 7493462,
  "type": "Feature",
  "properties": {
    "tgn:hierarchy":[
        "tgn:7493462",
        "tgn:7468018",
        "tgn:1000004",
        "tgn:1000141",
        "tgn:7029392"
    ],
    "tgn:id":7493462,
    "tgn:name":"Tudigongqi Ding",
    "tgn:placetype":[
        "aat:300008777"
    ]
},
  "bbox": [],
  "geometry": {"coordinates":[120.511589,23.477255],"type":"Point"}
}