{
  "id": 2232204,
  "type": "Feature",
  "properties": {
    "tgn:hierarchy":[
        "tgn:2232204",
        "tgn:2001423",
        "tgn:1000001",
        "tgn:7012149",
        "tgn:7007564",
        "tgn:7029392"
    ],
    "tgn:id":2232204,
    "tgn:name":"Chandler Brook",
    "tgn:placetype":[
        "aat:300008699"
    ]
},
  "bbox": [],
  "geometry": {"coordinates":[-71.05,44.2167],"type":"Point"}
}