{
  "id": 2452857,
  "type": "Feature",
  "properties": {
    "tgn:hierarchy":[
        "tgn:2452857",
        "tgn:1000001",
        "tgn:2001430",
        "tgn:7012149",
        "tgn:7007566",
        "tgn:7029392"
    ],
    "tgn:id":2452857,
    "tgn:name":"Little Burts Tank",
    "tgn:placetype":[
        "aat:300006191"
    ]
},
  "bbox": [],
  "geometry": {"coordinates":[-104.7167,33.8667],"type":"Point"}
}