{
  "id": 2540482,
  "type": "Feature",
  "properties": {
    "tgn:hierarchy":[
        "tgn:2540482",
        "tgn:1000001",
        "tgn:7012149",
        "tgn:2000809",
        "tgn:7007255",
        "tgn:7029392"
    ],
    "tgn:id":2540482,
    "tgn:name":"Newsome Hollow",
    "tgn:placetype":[
        "aat:300008761"
    ]
},
  "bbox": [],
  "geometry": {"coordinates":[-82.7333,38.1333],"type":"Point"}
}