{
  "id": 7279857,
  "type": "Feature",
  "properties": {
    "tgn:hierarchy":[
        "tgn:7279857",
        "tgn:1001623",
        "tgn:1000049",
        "tgn:1000002",
        "tgn:7029392"
    ],
    "tgn:id":7279857,
    "tgn:name":"Ram\u00edrez",
    "tgn:placetype":[
        "aat:300004792"
    ]
},
  "bbox": [],
  "geometry": {"coordinates":[-72.833333,-47.033333],"type":"Point"}
}