{
  "id": 2629188,
  "type": "Feature",
  "properties": {
    "tgn:hierarchy":[
        "tgn:2629188",
        "tgn:1000001",
        "tgn:7016172",
        "tgn:7012149",
        "tgn:2000149",
        "tgn:7029392"
    ],
    "tgn:id":2629188,
    "tgn:name":"Rose Ridge",
    "tgn:placetype":[
        "aat:300266640"
    ]
},
  "bbox": [],
  "geometry": {"coordinates":[-92.4667,36.0833],"type":"Point"}
}