{
  "id": 1055990,
  "type": "Feature",
  "properties": {
    "tgn:hierarchy":[
        "tgn:1055990",
        "tgn:1000004",
        "tgn:7012941",
        "tgn:7018214",
        "tgn:7002435",
        "tgn:7029392"
    ],
    "tgn:id":1055990,
    "tgn:name":"Kuzhenkino",
    "tgn:placetype":[
        "aat:300008347"
    ]
},
  "bbox": [],
  "geometry": {"coordinates":[33.9833,57.7333],"type":"Point"}
}