{
  "id": 7522584,
  "type": "Feature",
  "properties": {
    "tgn:hierarchy":[
        "tgn:7522584",
        "tgn:7001242",
        "tgn:7016833",
        "tgn:1001418",
        "tgn:7029392"
    ],
    "tgn:id":7522584,
    "tgn:name:en":"Dhi'b, Dayr adh",
    "tgn:placetype":[
        "aat:300386860"
    ]
},
  "bbox": [],
  "geometry": {"coordinates":[28.819688,30.763753],"type":"Point"}
}