{
  "id": 7137703,
  "type": "Feature",
  "properties": {
    "tgn:hierarchy":[
        "tgn:7137703",
        "tgn:1000003",
        "tgn:7003676",
        "tgn:7000084",
        "tgn:7029392"
    ],
    "tgn:id":7137703,
    "tgn:name":"Liekwegen",
    "tgn:placetype":[
        "aat:300008347"
    ]
},
  "bbox": [],
  "geometry": {"coordinates":[9.166667,52.283333],"type":"Point"}
}