{
  "id": 2542261,
  "type": "Feature",
  "properties": {
    "tgn:hierarchy":[
        "tgn:2542261",
        "tgn:7030516",
        "tgn:7006450",
        "tgn:1000001",
        "tgn:7012149",
        "tgn:7029392"
    ],
    "tgn:id":2542261,
    "tgn:name":"Nizki Cove",
    "tgn:placetype":[
        "aat:300132316"
    ]
},
  "bbox": [],
  "geometry": {"coordinates":[173.9333,52.7333],"type":"Point"}
}