<<<<<<< HEAD
{
  "id": 2408044,
  "type": "Feature",
  "properties": {
    "tgn:hierarchy":[
        "tgn:2408044",
        "tgn:1000001",
        "tgn:7012149",
        "tgn:2000548",
        "tgn:7007252",
        "tgn:7029392"
    ],
    "tgn:id":2408044,
    "tgn:name":"Hurricane Hill",
    "tgn:placetype":[
        "aat:300008798"
    ]
},
  "bbox": [],
  "geometry": {"coordinates":[-86.9,39.3333],"type":"Point"}
}
=======
{"geometry":{"type":"Point","coordinates":[-86.900000,39.333300]},"type":"Feature","properties":{"hierarchy":["tgn:2408044","tgn:1000001","tgn:7012149","tgn:2000548","tgn:7007252","tgn:7029392"],"placetype":["aat:300008798"],"id":2408044,"name:xx":"Hurricane Hill"}}
>>>>>>> 03f74aca74312dbeaf24d7e61306dd6a786dc3d0
