{
  "id": 2583145,
  "type": "Feature",
  "properties": {
    "tgn:hierarchy":[
        "tgn:2583145",
        "tgn:1000001",
        "tgn:7012149",
        "tgn:2000182",
        "tgn:7007157",
        "tgn:7029392"
    ],
    "tgn:id":2583145,
    "tgn:name":"Pine Lateral",
    "tgn:placetype":[
        "aat:300006075"
    ]
},
  "bbox": [],
  "geometry": {"coordinates":[-115.35,32.85],"type":"Point"}
}