{
  "id": 2433356,
  "type": "Feature",
  "properties": {
    "tgn:hierarchy":[
        "tgn:2433356",
        "tgn:1000001",
        "tgn:7012149",
        "tgn:7007523",
        "tgn:7029392"
    ],
    "tgn:id":2433356,
    "tgn:name":"Kelley Hollow",
    "tgn:placetype":[
        "aat:300008761"
    ]
},
  "bbox": [],
  "geometry": {"coordinates":[-91.1833,37.0667],"type":"Point"}
}