{
  "id": 2500006,
  "type": "Feature",
  "properties": {
    "tgn:hierarchy":[
        "tgn:2500006",
        "tgn:1000001",
        "tgn:7012149",
        "tgn:2001888",
        "tgn:7007825",
        "tgn:7029392"
    ],
    "tgn:id":2500006,
    "tgn:name":"McCrady Hill",
    "tgn:placetype":[
        "aat:300008798"
    ]
},
  "bbox": [],
  "geometry": {"coordinates":[-86.6333,35.2833],"type":"Point"}
}