{
  "id": 7036710,
  "type": "Feature",
  "properties": {
    "tgn:hierarchy":[
        "tgn:7036710",
        "tgn:7003139",
        "tgn:1000003",
        "tgn:7003080",
        "tgn:1000080",
        "tgn:7029392"
    ],
    "tgn:id":7036710,
    "tgn:name":"Vite, Fosso della",
    "tgn:placetype":[
        "aat:300008699"
    ]
},
  "bbox": [],
  "geometry": {"coordinates":[11.75,42.166667],"type":"Point"}
}