<<<<<<< HEAD
{
  "id": 7480071,
  "type": "Feature",
  "properties": {
    "tgn:hierarchy":[
        "tgn:7480071",
        "tgn:1000004",
        "tgn:7490934",
        "tgn:1000141",
        "tgn:7029392"
    ],
    "tgn:id":7480071,
    "tgn:name":"Daxing Gong",
    "tgn:placetype":[
        "aat:300007595"
    ]
},
  "bbox": [],
  "geometry": {"coordinates":[120.187222,23.010833],"type":"Point"}
}
=======
{"geometry":{"type":"Point","coordinates":[120.187222,23.010833]},"type":"Feature","properties":{"hierarchy":["tgn:7480071","tgn:1000004","tgn:7490934","tgn:1000141","tgn:7029392"],"placetype":["aat:300007595"],"id":7480071,"name:xx":"Daxing Gong"}}
>>>>>>> 03f74aca74312dbeaf24d7e61306dd6a786dc3d0
