{
  "id": 7129140,
  "type": "Feature",
  "properties": {
    "tgn:hierarchy":[
        "tgn:7129140",
        "tgn:7003692",
        "tgn:1000003",
        "tgn:7000084",
        "tgn:7029392"
    ],
    "tgn:id":7129140,
    "tgn:name":"Nordschwaben",
    "tgn:placetype":[
        "aat:300008347"
    ]
},
  "bbox": [],
  "geometry": {"coordinates":[7.816667,47.616667],"type":"Point"}
}