{
  "id": 7508869,
  "type": "Feature",
  "properties": {
    "tgn:hierarchy":[
        "tgn:7508869",
        "tgn:1008380",
        "tgn:7520093",
        "tgn:1000226",
        "tgn:1000006",
        "tgn:7029392"
    ],
    "tgn:id":7508869,
    "tgn:name:en":"Waione",
    "tgn:placetype":[
        "aat:300008795"
    ]
},
  "bbox": [],
  "geometry": {"coordinates":[176.033333,-39.033333],"type":"Point"}
}