<<<<<<< HEAD
{
  "id": 2159548,
  "type": "Feature",
  "properties": {
    "tgn:hierarchy":[
        "tgn:2159548",
        "tgn:1000001",
        "tgn:7012149",
        "tgn:2001255",
        "tgn:7007523",
        "tgn:7029392"
    ],
    "tgn:id":2159548,
    "tgn:name":"Bee Press Ridge",
    "tgn:placetype":[
        "aat:300266640"
    ]
},
  "bbox": [],
  "geometry": {"coordinates":[-90.1667,36.9833],"type":"Point"}
}
=======
{"geometry":{"type":"Point","coordinates":[-90.166700,36.983300]},"type":"Feature","properties":{"hierarchy":["tgn:2159548","tgn:1000001","tgn:7012149","tgn:2001255","tgn:7007523","tgn:7029392"],"placetype":["aat:300266640"],"id":2159548,"name:xx":"Bee Press Ridge"}}
>>>>>>> 03f74aca74312dbeaf24d7e61306dd6a786dc3d0
