{
  "id": 2159548,
  "type": "Feature",
  "properties": {
    "tgn:hierarchy":[
        "tgn:2159548",
        "tgn:1000001",
        "tgn:7012149",
        "tgn:2001255",
        "tgn:7007523",
        "tgn:7029392"
    ],
    "tgn:id":2159548,
    "tgn:name":"Bee Press Ridge",
    "tgn:placetype":[
        "aat:300266640"
    ]
},
  "bbox": [],
  "geometry": {"coordinates":[-90.1667,36.9833],"type":"Point"}
}