{
  "id": 1018789,
  "type": "Feature",
  "properties": {
    "tgn:hierarchy":[
        "tgn:1018789",
        "tgn:1000566",
        "tgn:1000001",
        "tgn:7005562",
        "tgn:7029392"
    ],
    "tgn:id":1018789,
    "tgn:name":"Santo Tom\u00e1s del Norte",
    "tgn:placetype":[
        "aat:300008347"
    ]
},
  "bbox": [],
  "geometry": {"coordinates":[-86.9333,13.1833],"type":"Point"}
}