<<<<<<< HEAD
{
  "id": 7113963,
  "type": "Feature",
  "properties": {
    "tgn:hierarchy":[
        "tgn:7113963",
        "tgn:7003669",
        "tgn:1000003",
        "tgn:7000084",
        "tgn:7029392"
    ],
    "tgn:id":7113963,
    "tgn:name":"Riedlberg",
    "tgn:placetype":[
        "aat:300008795"
    ]
},
  "bbox": [],
  "geometry": {"coordinates":[12.166667,47.733333],"type":"Point"}
}
=======
{"geometry":{"type":"Point","coordinates":[12.166667,47.733333]},"type":"Feature","properties":{"hierarchy":["tgn:7113963","tgn:7003669","tgn:1000003","tgn:7000084","tgn:7029392"],"placetype":["aat:300008795"],"id":7113963,"name:xx":"Riedlberg"}}
>>>>>>> 03f74aca74312dbeaf24d7e61306dd6a786dc3d0
