{
  "id": 7113963,
  "type": "Feature",
  "properties": {
    "tgn:hierarchy":[
        "tgn:7113963",
        "tgn:7003669",
        "tgn:1000003",
        "tgn:7000084",
        "tgn:7029392"
    ],
    "tgn:id":7113963,
    "tgn:name":"Riedlberg",
    "tgn:placetype":[
        "aat:300008795"
    ]
},
  "bbox": [],
  "geometry": {"coordinates":[12.166667,47.733333],"type":"Point"}
}