{
  "id": 2509546,
  "type": "Feature",
  "properties": {
    "tgn:hierarchy":[
        "tgn:2509546",
        "tgn:1000001",
        "tgn:7012149",
        "tgn:2002299",
        "tgn:7013961",
        "tgn:7029392"
    ],
    "tgn:id":2509546,
    "tgn:name":"Middle Fork Wilson Creek",
    "tgn:placetype":[
        "aat:300008706"
    ]
},
  "bbox": [],
  "geometry": {"coordinates":[-82.3833,38.2167],"type":"Point"}
}