{
  "id": 2398477,
  "type": "Feature",
  "properties": {
    "tgn:hierarchy":[
        "tgn:2398477",
        "tgn:1000001",
        "tgn:7012149",
        "tgn:2002069",
        "tgn:7007826",
        "tgn:7029392"
    ],
    "tgn:id":2398477,
    "tgn:name":"Hooten Hollow",
    "tgn:placetype":[
        "aat:300008761"
    ]
},
  "bbox": [],
  "geometry": {"coordinates":[-98.9667,31.25],"type":"Point"}
}