{
  "id": 2047746,
  "type": "Feature",
  "properties": {
    "tgn:hierarchy":[
        "tgn:2047746",
        "tgn:2000934",
        "tgn:1000001",
        "tgn:7012149",
        "tgn:7007516",
        "tgn:7029392"
    ],
    "tgn:id":2047746,
    "tgn:name":"Loarville",
    "tgn:placetype":[
        "aat:300008347"
    ]
},
  "bbox": [],
  "geometry": {"coordinates":[-78.8833,39.6167],"type":"Point"}
}