<<<<<<< HEAD
{
  "id": 2153319,
  "type": "Feature",
  "properties": {
    "tgn:hierarchy":[
        "tgn:2153319",
        "tgn:1000001",
        "tgn:7012149",
        "tgn:7007157",
        "tgn:2000187",
        "tgn:7029392"
    ],
    "tgn:id":2153319,
    "tgn:name":"Bean Creek",
    "tgn:placetype":[
        "aat:300008706"
    ]
},
  "bbox": [],
  "geometry": {"coordinates":[-121.1,39.9833],"type":"Point"}
}
=======
{"geometry":{"type":"Point","coordinates":[-121.100000,39.983300]},"type":"Feature","properties":{"hierarchy":["tgn:2153319","tgn:1000001","tgn:7012149","tgn:7007157","tgn:2000187","tgn:7029392"],"placetype":["aat:300008706"],"id":2153319,"name:xx":"Bean Creek"}}
>>>>>>> 03f74aca74312dbeaf24d7e61306dd6a786dc3d0
