{
  "id": 2261808,
  "type": "Feature",
  "properties": {
    "tgn:hierarchy":[
        "tgn:2261808",
        "tgn:1000001",
        "tgn:7012149",
        "tgn:2002114",
        "tgn:7007827",
        "tgn:7029392"
    ],
    "tgn:id":2261808,
    "tgn:name":"Cove Spring",
    "tgn:placetype":[
        "aat:300008697"
    ]
},
  "bbox": [],
  "geometry": {"coordinates":[-112.85,38.65],"type":"Point"}
}