{
  "id": 7573541,
  "type": "Feature",
  "properties": {
    "tgn:hierarchy":[
        "tgn:7573541",
        "tgn:7001819",
        "tgn:1000004",
        "tgn:7000198",
        "tgn:7029392"
    ],
    "tgn:id":7573541,
    "tgn:name:en":"Irchik Dakhru",
    "tgn:placetype":[
        "aat:300259572"
    ]
},
  "bbox": [],
  "geometry": {"coordinates":[97.240361,28.010193],"type":"Point"}
}