{
  "id": 2260645,
  "type": "Feature",
  "properties": {
    "tgn:hierarchy":[
        "tgn:2260645",
        "tgn:1000001",
        "tgn:7012149",
        "tgn:2001046",
        "tgn:7007521",
        "tgn:7029392"
    ],
    "tgn:id":2260645,
    "tgn:name":"County Ditch Number Nine",
    "tgn:placetype":[
        "aat:300006075"
    ]
},
  "bbox": [],
  "geometry": {"coordinates":[-93.65,45.6833],"type":"Point"}
}