<<<<<<< HEAD
{
  "id": 7020498,
  "type": "Feature",
  "properties": {
    "tgn:hierarchy":[
        "tgn:7020498",
        "tgn:1000001",
        "tgn:7012149",
        "tgn:2001281",
        "tgn:7007524",
        "tgn:7029392"
    ],
    "tgn:id":7020498,
    "tgn:name":"Washington Mines",
    "tgn:placetype":[
        "aat:300000390"
    ]
},
  "bbox": [],
  "geometry": {"coordinates":[-112.1333,46.35],"type":"Point"}
}
=======
{"geometry":{"type":"Point","coordinates":[-112.133300,46.350000]},"type":"Feature","properties":{"hierarchy":["tgn:7020498","tgn:1000001","tgn:7012149","tgn:2001281","tgn:7007524","tgn:7029392"],"placetype":["aat:300000390"],"id":7020498,"name:xx":"Washington Mines"}}
>>>>>>> 03f74aca74312dbeaf24d7e61306dd6a786dc3d0
