{
  "id": 2574126,
  "type": "Feature",
  "properties": {
    "tgn:hierarchy":[
        "tgn:2574126",
        "tgn:1000001",
        "tgn:7012149",
        "tgn:7007157",
        "tgn:1002858",
        "tgn:7029392"
    ],
    "tgn:id":2574126,
    "tgn:name":"Peg Leg Mine",
    "tgn:placetype":[
        "aat:300000390"
    ]
},
  "bbox": [],
  "geometry": {"coordinates":[-116.85,32.7333],"type":"Point"}
}