{
  "id": 2362812,
  "type": "Feature",
  "properties": {
    "tgn:hierarchy":[
        "tgn:2362812",
        "tgn:1000001",
        "tgn:7012149",
        "tgn:2001486",
        "tgn:7007709",
        "tgn:7029392"
    ],
    "tgn:id":2362812,
    "tgn:name":"Great Neck",
    "tgn:placetype":[
        "aat:300008850"
    ]
},
  "bbox": [],
  "geometry": {"coordinates":[-76.6833,34.9167],"type":"Point"}
}