{
  "id": 7183851,
  "type": "Feature",
  "properties": {
    "tgn:hierarchy":[
        "tgn:7183851",
        "tgn:7003692",
        "tgn:1000003",
        "tgn:7000084",
        "tgn:7029392"
    ],
    "tgn:id":7183851,
    "tgn:name":"G\u00f6ggingen",
    "tgn:placetype":[
        "aat:300008347"
    ]
},
  "bbox": [],
  "geometry": {"coordinates":[9.933333,48.333333],"type":"Point"}
}