{
  "id": 1130007,
  "type": "Feature",
  "properties": {
    "tgn:hierarchy":[
        "tgn:1130007",
        "tgn:7002636",
        "tgn:1000730",
        "tgn:1000002",
        "tgn:1000055",
        "tgn:7029392"
    ],
    "tgn:id":1130007,
    "tgn:name":"Siete Puntas, R\u00edo",
    "tgn:placetype":[
        "aat:300008707"
    ]
},
  "bbox": [],
  "geometry": {"coordinates":[-57.3333,-23.5667],"type":"Point"}
}