{
  "id": 7281172,
  "type": "Feature",
  "properties": {
    "tgn:hierarchy":[
        "tgn:7281172",
        "tgn:1001768",
        "tgn:1000049",
        "tgn:1000002",
        "tgn:7029392"
    ],
    "tgn:id":7281172,
    "tgn:name":"Tabolango",
    "tgn:placetype":[
        "aat:300008347"
    ]
},
  "bbox": [],
  "geometry": {"coordinates":[-70.666667,-32.833333],"type":"Point"}
}