{
  "id": 2249739,
  "type": "Feature",
  "properties": {
    "tgn:hierarchy":[
        "tgn:2249739",
        "tgn:1000001",
        "tgn:7012149",
        "tgn:7007826",
        "tgn:7029392"
    ],
    "tgn:id":2249739,
    "tgn:name":"Collard Creek",
    "tgn:placetype":[
        "aat:300008706"
    ]
},
  "bbox": [],
  "geometry": {"coordinates":[-95.8667,30.95],"type":"Point"}
}