{
  "id": 7457241,
  "type": "Feature",
  "properties": {
    "tgn:hierarchy":[
        "tgn:7457241",
        "tgn:7002445",
        "tgn:1000003",
        "tgn:7011961",
        "tgn:7008591",
        "tgn:7029392"
    ],
    "tgn:id":7457241,
    "tgn:name:en":"Motcombe",
    "tgn:placetype":[
        "aat:300008347"
    ]
},
  "bbox": [],
  "geometry": {"coordinates":[-2.214722,51.025556],"type":"Point"}
}