{
  "id": 7238149,
  "type": "Feature",
  "properties": {
    "tgn:hierarchy":[
        "tgn:7238149",
        "tgn:7003461",
        "tgn:1000003",
        "tgn:1000063",
        "tgn:7018236",
        "tgn:7029392"
    ],
    "tgn:id":7238149,
    "tgn:name":"Hamveld",
    "tgn:placetype":[
        "aat:300008347"
    ]
},
  "bbox": [],
  "geometry": {"coordinates":[5.233333,50.833333],"type":"Point"}
}