{
  "id": 7425209,
  "type": "Feature",
  "properties": {
    "tgn:hierarchy":[
        "tgn:7425209",
        "tgn:1000001",
        "tgn:7005597",
        "tgn:7005560",
        "tgn:7029392"
    ],
    "tgn:id":7425209,
    "tgn:name":"Las Delicias",
    "tgn:placetype":[
        "aat:300008347"
    ]
},
  "bbox": [],
  "geometry": {"coordinates":[-98.666667,25.116667],"type":"Point"}
}