{
  "id": 2147535,
  "type": "Feature",
  "properties": {
    "tgn:hierarchy":[
        "tgn:2147535",
        "tgn:1000001",
        "tgn:7006451",
        "tgn:2000092",
        "tgn:7012149",
        "tgn:7029392"
    ],
    "tgn:id":2147535,
    "tgn:name":"Barbershop Spring",
    "tgn:placetype":[
        "aat:300008697"
    ]
},
  "bbox": [],
  "geometry": {"coordinates":[-111.1833,34.4333],"type":"Point"}
}