{
  "id": 7255001,
  "type": "Feature",
  "properties": {
    "tgn:hierarchy":[
        "tgn:7255001",
        "tgn:7003465",
        "tgn:1000003",
        "tgn:1000063",
        "tgn:4012014",
        "tgn:7029392"
    ],
    "tgn:id":7255001,
    "tgn:name":"Tohogne",
    "tgn:placetype":[
        "aat:300008347"
    ]
},
  "bbox": [],
  "geometry": {"coordinates":[5.480999,50.381248],"type":"Point"}
}