{
  "id": 2578909,
  "type": "Feature",
  "properties": {
    "tgn:hierarchy":[
        "tgn:2578909",
        "tgn:1000001",
        "tgn:7006451",
        "tgn:2000095",
        "tgn:7012149",
        "tgn:7029392"
    ],
    "tgn:id":2578909,
    "tgn:name":"Phillips Tank",
    "tgn:placetype":[
        "aat:300006191"
    ]
},
  "bbox": [],
  "geometry": {"coordinates":[-109.0667,33.05],"type":"Point"}
}