{
  "id": 2330546,
  "type": "Feature",
  "properties": {
    "tgn:hierarchy":[
        "tgn:2330546",
        "tgn:1000001",
        "tgn:7012149",
        "tgn:1002384",
        "tgn:7007523",
        "tgn:7029392"
    ],
    "tgn:id":2330546,
    "tgn:name":"Flat Creek",
    "tgn:placetype":[
        "aat:300008706"
    ]
},
  "bbox": [],
  "geometry": {"coordinates":[-91.0667,38.45],"type":"Point"}
}