<<<<<<< HEAD
{
  "id": 2330546,
  "type": "Feature",
  "properties": {
    "tgn:hierarchy":[
        "tgn:2330546",
        "tgn:1000001",
        "tgn:7012149",
        "tgn:1002384",
        "tgn:7007523",
        "tgn:7029392"
    ],
    "tgn:id":2330546,
    "tgn:name":"Flat Creek",
    "tgn:placetype":[
        "aat:300008706"
    ]
},
  "bbox": [],
  "geometry": {"coordinates":[-91.0667,38.45],"type":"Point"}
}
=======
{"geometry":{"type":"Point","coordinates":[-91.066700,38.450000]},"type":"Feature","properties":{"hierarchy":["tgn:2330546","tgn:1000001","tgn:7012149","tgn:1002384","tgn:7007523","tgn:7029392"],"placetype":["aat:300008706"],"id":2330546,"name:xx":"Flat Creek"}}
>>>>>>> 03f74aca74312dbeaf24d7e61306dd6a786dc3d0
