{
  "id": 2322572,
  "type": "Feature",
  "properties": {
    "tgn:hierarchy":[
        "tgn:2322572",
        "tgn:1000001",
        "tgn:2002243",
        "tgn:7012149",
        "tgn:7007920",
        "tgn:7029392"
    ],
    "tgn:id":2322572,
    "tgn:name":"Falls Creek",
    "tgn:placetype":[
        "aat:300008706"
    ]
},
  "bbox": [],
  "geometry": {"coordinates":[-118.3667,48.1667],"type":"Point"}
}