{
  "id": 2190282,
  "type": "Feature",
  "properties": {
    "tgn:hierarchy":[
        "tgn:2190282",
        "tgn:1000001",
        "tgn:7012149",
        "tgn:7007157",
        "tgn:2000189",
        "tgn:7029392"
    ],
    "tgn:id":2190282,
    "tgn:name":"Box Canyon",
    "tgn:placetype":[
        "aat:300008761"
    ]
},
  "bbox": [],
  "geometry": {"coordinates":[-121.6833,41.7667],"type":"Point"}
}