{
  "id": 2725402,
  "type": "Feature",
  "properties": {
    "tgn:hierarchy":[
        "tgn:2725402",
        "tgn:1000001",
        "tgn:2000260",
        "tgn:7012149",
        "tgn:7007240",
        "tgn:7029392"
    ],
    "tgn:id":2725402,
    "tgn:name":"Toolchest Branch",
    "tgn:placetype":[
        "aat:300008699"
    ]
},
  "bbox": [],
  "geometry": {"coordinates":[-85.1833,30.4333],"type":"Point"}
}