{
  "id": 7521330,
  "type": "Feature",
  "properties": {
    "tgn:hierarchy":[
        "tgn:7521330",
        "tgn:7001242",
        "tgn:7016833",
        "tgn:7001336",
        "tgn:7029392"
    ],
    "tgn:id":7521330,
    "tgn:name:en":"Ab\u016b Jard\u0101n, W\u0101d\u012b",
    "tgn:placetype":[
        "aat:300379998"
    ]
},
  "bbox": [],
  "geometry": {"coordinates":[34.487344,28.802996],"type":"Point"}
}