{
  "id": 2443581,
  "type": "Feature",
  "properties": {
    "tgn:hierarchy":[
        "tgn:2443581",
        "tgn:1000001",
        "tgn:7012149",
        "tgn:2001453",
        "tgn:7007566",
        "tgn:7029392"
    ],
    "tgn:id":2443581,
    "tgn:name":"La Cueva Number Two Spring",
    "tgn:placetype":[
        "aat:300008697"
    ]
},
  "bbox": [],
  "geometry": {"coordinates":[-105.5167,35.55],"type":"Point"}
}