{
  "id": 2650834,
  "type": "Feature",
  "properties": {
    "tgn:hierarchy":[
        "tgn:2650834",
        "tgn:1000001",
        "tgn:7012149",
        "tgn:7007825",
        "tgn:7029392"
    ],
    "tgn:id":2650834,
    "tgn:name":"Second Creek",
    "tgn:placetype":[
        "aat:300008706"
    ]
},
  "bbox": [],
  "geometry": {"coordinates":[-85.7167,36.0833],"type":"Point"}
}