{
  "id": 7454220,
  "type": "Feature",
  "properties": {
    "tgn:hierarchy":[
        "tgn:7454220",
        "tgn:7002445",
        "tgn:1000003",
        "tgn:7008157",
        "tgn:7008591",
        "tgn:7029392"
    ],
    "tgn:id":7454220,
    "tgn:name:en":"Chequer Shoal",
    "tgn:placetype":[
        "aat:300387036"
    ]
},
  "bbox": [],
  "geometry": {"coordinates":[0.166667,53.566667],"type":"Point"}
}