{
  "id": 7535451,
  "type": "Feature",
  "properties": {
    "tgn:hierarchy":[
        "tgn:7535451",
        "tgn:7001242",
        "tgn:7016833",
        "tgn:1001418",
        "tgn:7029392"
    ],
    "tgn:id":7535451,
    "tgn:name:en":"Qabr Gadalla",
    "tgn:placetype":[
        "aat:300005926"
    ]
},
  "bbox": [],
  "geometry": {"coordinates":[27.325601,30.958967],"type":"Point"}
}