{
  "id": 4009770,
  "type": "Feature",
  "properties": {
    "tgn:hierarchy":[
        "tgn:4009770",
        "tgn:1000003",
        "tgn:7002885",
        "tgn:1000070",
        "tgn:7029392"
    ],
    "tgn:id":4009770,
    "tgn:name":"Saint-Papoul",
    "tgn:placetype":[
        "aat:300008347"
    ]
},
  "bbox": [],
  "geometry": {"coordinates":[2.0333,43.3333],"type":"Point"}
}