{
  "id": 7194094,
  "type": "Feature",
  "properties": {
    "tgn:hierarchy":[
        "tgn:7194094",
        "tgn:7000096",
        "tgn:1000003",
        "tgn:7000084",
        "tgn:7029392"
    ],
    "tgn:id":7194094,
    "tgn:name":"Felchowsee",
    "tgn:placetype":[
        "aat:300008680"
    ]
},
  "bbox": [],
  "geometry": {"coordinates":[14.133333,53.05],"type":"Point"}
}