{
  "id": 2241000,
  "type": "Feature",
  "properties": {
    "tgn:hierarchy":[
        "tgn:2241000",
        "tgn:1000001",
        "tgn:7013686",
        "tgn:7012149",
        "tgn:7007517",
        "tgn:7029392"
    ],
    "tgn:id":2241000,
    "tgn:name":"Clark Brook",
    "tgn:placetype":[
        "aat:300008699"
    ]
},
  "bbox": [],
  "geometry": {"coordinates":[-72.7167,42.3667],"type":"Point"}
}