{
  "id": 2508471,
  "type": "Feature",
  "properties": {
    "tgn:hierarchy":[
        "tgn:2508471",
        "tgn:1000001",
        "tgn:7012149",
        "tgn:2000508",
        "tgn:7007251",
        "tgn:7029392"
    ],
    "tgn:id":2508471,
    "tgn:name":"Middle Creek",
    "tgn:placetype":[
        "aat:300008706"
    ]
},
  "bbox": [],
  "geometry": {"coordinates":[-88.65,38.1167],"type":"Point"}
}