{
  "id": 2182248,
  "type": "Feature",
  "properties": {
    "tgn:hierarchy":[
        "tgn:2182248",
        "tgn:1000001",
        "tgn:7012149",
        "tgn:2000493",
        "tgn:7007250",
        "tgn:7029392"
    ],
    "tgn:id":2182248,
    "tgn:name":"Blue Mud Spring",
    "tgn:placetype":[
        "aat:300008697"
    ]
},
  "bbox": [],
  "geometry": {"coordinates":[-114.35,42.1833],"type":"Point"}
}