{
  "id": 2682209,
  "type": "Feature",
  "properties": {
    "tgn:hierarchy":[
        "tgn:2682209",
        "tgn:1000001",
        "tgn:7012149",
        "tgn:2000208",
        "tgn:7007158",
        "tgn:7029392"
    ],
    "tgn:id":2682209,
    "tgn:name":"South Twin Creek",
    "tgn:placetype":[
        "aat:300008706"
    ]
},
  "bbox": [],
  "geometry": {"coordinates":[-107.8667,37.75],"type":"Point"}
}