{
  "id": 7439269,
  "type": "Feature",
  "properties": {
    "tgn:hierarchy":[
        "tgn:7439269",
        "tgn:1000001",
        "tgn:7005588",
        "tgn:7005560",
        "tgn:7029392"
    ],
    "tgn:id":7439269,
    "tgn:name":"Tetlama",
    "tgn:placetype":[
        "aat:300008347"
    ]
},
  "bbox": [],
  "geometry": {"coordinates":[-99.283333,18.816667],"type":"Point"}
}