{
  "id": 7511251,
  "type": "Feature",
  "properties": {
    "tgn:hierarchy":[
        "tgn:7511251",
        "tgn:1009227",
        "tgn:1000226",
        "tgn:7018437",
        "tgn:1000006",
        "tgn:7029392"
    ],
    "tgn:id":7511251,
    "tgn:name:en":"Tuapeka River",
    "tgn:placetype":[
        "aat:300008699"
    ]
},
  "bbox": [],
  "geometry": {"coordinates":[169.516667,-46.016667],"type":"Point"}
}