<<<<<<< HEAD
{
  "id": 2764400,
  "type": "Feature",
  "properties": {
    "tgn:hierarchy":[
        "tgn:2764400",
        "tgn:1000001",
        "tgn:2001476",
        "tgn:7012149",
        "tgn:7007709",
        "tgn:7029392"
    ],
    "tgn:id":2764400,
    "tgn:name":"Whetstone Mountain",
    "tgn:placetype":[
        "aat:300008798"
    ]
},
  "bbox": [],
  "geometry": {"coordinates":[-81.5833,36.0167],"type":"Point"}
}
=======
{"geometry":{"type":"Point","coordinates":[-81.583300,36.016700]},"type":"Feature","properties":{"hierarchy":["tgn:2764400","tgn:1000001","tgn:2001476","tgn:7012149","tgn:7007709","tgn:7029392"],"placetype":["aat:300008798"],"id":2764400,"name:xx":"Whetstone Mountain"}}
>>>>>>> 03f74aca74312dbeaf24d7e61306dd6a786dc3d0
