{
  "id": 7423143,
  "type": "Feature",
  "properties": {
    "tgn:hierarchy":[
        "tgn:7423143",
        "tgn:1000001",
        "tgn:1001960",
        "tgn:7005560",
        "tgn:7029392"
    ],
    "tgn:id":7423143,
    "tgn:name":"Agua Nueva",
    "tgn:placetype":[
        "aat:300008347"
    ]
},
  "bbox": [],
  "geometry": {"coordinates":[-111.566667,28.466667],"type":"Point"}
}