{
  "id": 1081650,
  "type": "Feature",
  "properties": {
    "tgn:hierarchy":[
        "tgn:1081650",
        "tgn:7004299",
        "tgn:1007508",
        "tgn:1010395",
        "tgn:7004290",
        "tgn:1000004",
        "tgn:1001016",
        "tgn:1000120",
        "tgn:7029392"
    ],
    "tgn:id":1081650,
    "tgn:name":"Ueharu",
    "tgn:placetype":[
        "aat:300008347"
    ]
},
  "bbox": [],
  "geometry": {"coordinates":[123.7667,24.4167],"type":"Point"}
}