{
  "id": 2197335,
  "type": "Feature",
  "properties": {
    "tgn:hierarchy":[
        "tgn:2197335",
        "tgn:2000090",
        "tgn:1000001",
        "tgn:7006451",
        "tgn:7012149",
        "tgn:7029392"
    ],
    "tgn:id":2197335,
    "tgn:name":"Brown Butte",
    "tgn:placetype":[
        "aat:300008798"
    ]
},
  "bbox": [],
  "geometry": {"coordinates":[-109.6333,34.0833],"type":"Point"}
}