<<<<<<< HEAD
{
  "id": 7488443,
  "type": "Feature",
  "properties": {
    "tgn:hierarchy":[
        "tgn:7488443",
        "tgn:1000004",
        "tgn:1000454",
        "tgn:1000141",
        "tgn:7029392"
    ],
    "tgn:id":7488443,
    "tgn:name":"Huodancun",
    "tgn:placetype":[
        "aat:300387200"
    ]
},
  "bbox": [],
  "geometry": {"coordinates":[121.85,25.05],"type":"Point"}
}
=======
{"geometry":{"type":"Point","coordinates":[121.850000,25.050000]},"type":"Feature","properties":{"hierarchy":["tgn:7488443","tgn:1000004","tgn:1000454","tgn:1000141","tgn:7029392"],"placetype":["aat:300387200"],"id":7488443,"name:xx":"Huodancun"}}
>>>>>>> 03f74aca74312dbeaf24d7e61306dd6a786dc3d0
