{
  "id": 2187368,
  "type": "Feature",
  "properties": {
    "tgn:hierarchy":[
        "tgn:2187368",
        "tgn:1000001",
        "tgn:7012149",
        "tgn:1003019",
        "tgn:7007826",
        "tgn:7029392"
    ],
    "tgn:id":2187368,
    "tgn:name":"Boone Branch",
    "tgn:placetype":[
        "aat:300008699"
    ]
},
  "bbox": [],
  "geometry": {"coordinates":[-96.0167,29.4167],"type":"Point"}
}