{
  "id": 2307329,
  "type": "Feature",
  "properties": {
    "tgn:hierarchy":[
        "tgn:2307329",
        "tgn:1000001",
        "tgn:7012149",
        "tgn:7007157",
        "tgn:2000189",
        "tgn:7029392"
    ],
    "tgn:id":2307329,
    "tgn:name":"East Fork Rattlesnake Creek",
    "tgn:placetype":[
        "aat:300008706"
    ]
},
  "bbox": [],
  "geometry": {"coordinates":[-122.8833,41.6833],"type":"Point"}
}