{
  "id": 2199611,
  "type": "Feature",
  "properties": {
    "tgn:hierarchy":[
        "tgn:2199611",
        "tgn:1000001",
        "tgn:7012149",
        "tgn:1002591",
        "tgn:7007255",
        "tgn:7029392"
    ],
    "tgn:id":2199611,
    "tgn:name":"Brush Creek Island",
    "tgn:placetype":[
        "aat:300008791"
    ]
},
  "bbox": [],
  "geometry": {"coordinates":[-83.45,38.6667],"type":"Point"}
}