{
  "id": 7529599,
  "type": "Feature",
  "properties": {
    "tgn:hierarchy":[
        "tgn:7529599",
        "tgn:7001242",
        "tgn:7016833",
        "tgn:7000123",
        "tgn:7029392"
    ],
    "tgn:id":7529599,
    "tgn:name:en":"S\u012bd\u012b Dahmash",
    "tgn:placetype":[
        "aat:300005926"
    ]
},
  "bbox": [],
  "geometry": {"coordinates":[32.75,25.85],"type":"Point"}
}