{
  "id": 7344166,
  "type": "Feature",
  "properties": {
    "tgn:hierarchy":[
        "tgn:7344166",
        "tgn:7002803",
        "tgn:1001647",
        "tgn:1000003",
        "tgn:1000095",
        "tgn:7029392"
    ],
    "tgn:id":7344166,
    "tgn:name":"Casa de Jaime",
    "tgn:placetype":[
        "aat:300008347"
    ]
},
  "bbox": [],
  "geometry": {"coordinates":[-1.316667,38.716667],"type":"Point"}
}