{
  "id": 7502095,
  "type": "Feature",
  "properties": {
    "tgn:hierarchy":[
        "tgn:7502095",
        "tgn:1000004",
        "tgn:7001009",
        "tgn:1000141",
        "tgn:7029392"
    ],
    "tgn:id":7502095,
    "tgn:name":"Xiangjiaoshi",
    "tgn:placetype":[
        "aat:300008347"
    ]
},
  "bbox": [],
  "geometry": {"coordinates":[120.886858,24.089937],"type":"Point"}
}