{
  "id": 7214546,
  "type": "Feature",
  "properties": {
    "tgn:hierarchy":[
        "tgn:7214546",
        "tgn:1000003",
        "tgn:7003676",
        "tgn:7000084",
        "tgn:7029392"
    ],
    "tgn:id":7214546,
    "tgn:name":"B\u00f6hrn",
    "tgn:placetype":[
        "aat:300008863"
    ]
},
  "bbox": [],
  "geometry": {"coordinates":[7.916667,53.216667],"type":"Point"}
}