{
  "id": 2781085,
  "type": "Feature",
  "properties": {
    "tgn:hierarchy":[
        "tgn:2781085",
        "tgn:1000001",
        "tgn:7012149",
        "tgn:1002971",
        "tgn:7007710",
        "tgn:7029392"
    ],
    "tgn:id":2781085,
    "tgn:name":"Woodcock Run",
    "tgn:placetype":[
        "aat:300008699"
    ]
},
  "bbox": [],
  "geometry": {"coordinates":[-79.5167,41.5833],"type":"Point"}
}