{
  "id": 2203552,
  "type": "Feature",
  "properties": {
    "tgn:hierarchy":[
        "tgn:2203552",
        "tgn:1000001",
        "tgn:7012149",
        "tgn:2000964",
        "tgn:7007520",
        "tgn:7029392"
    ],
    "tgn:id":2203552,
    "tgn:name":"Buckley Creek",
    "tgn:placetype":[
        "aat:300008706"
    ]
},
  "bbox": [],
  "geometry": {"coordinates":[-82.6833,43.7667],"type":"Point"}
}