{
  "id": 7462138,
  "type": "Feature",
  "properties": {
    "tgn:hierarchy":[
        "tgn:7462138",
        "tgn:7002445",
        "tgn:7008116",
        "tgn:1000003",
        "tgn:7008591",
        "tgn:7029392"
    ],
    "tgn:id":7462138,
    "tgn:name:en":"Kit Hill",
    "tgn:placetype":[
        "aat:300008795"
    ]
},
  "bbox": [],
  "geometry": {"coordinates":[-4.283333,50.533333],"type":"Point"}
}