{
  "id": 2670565,
  "type": "Feature",
  "properties": {
    "tgn:hierarchy":[
        "tgn:2670565",
        "tgn:1000001",
        "tgn:7012149",
        "tgn:2001192",
        "tgn:7007523",
        "tgn:7029392"
    ],
    "tgn:id":2670565,
    "tgn:name":"Smelter Hollow",
    "tgn:placetype":[
        "aat:300008761"
    ]
},
  "bbox": [],
  "geometry": {"coordinates":[-92.95,37.75],"type":"Point"}
}