<<<<<<< HEAD
{
  "id": 7028515,
  "type": "Feature",
  "properties": {
    "tgn:hierarchy":[
        "tgn:7028515",
        "tgn:7002445",
        "tgn:1000003",
        "tgn:7008160",
        "tgn:7008591",
        "tgn:7029392"
    ],
    "tgn:id":7028515,
    "tgn:name:en":"North Lopham",
    "tgn:placetype":[
        "aat:300008347",
        "aat:300008372"
    ]
},
  "bbox": [],
  "geometry": {"coordinates":[1.0,52.4],"type":"Point"}
}
=======
{"geometry":{"type":"Point","coordinates":[1.000000,52.400000]},"type":"Feature","properties":{"hierarchy":["tgn:7028515","tgn:7002445","tgn:1000003","tgn:7008160","tgn:7008591","tgn:7029392"],"placetype":["aat:300008347","aat:300008372"],"name:en":"North Lopham","id":7028515}}
>>>>>>> 03f74aca74312dbeaf24d7e61306dd6a786dc3d0
