{
  "id": 7488919,
  "type": "Feature",
  "properties": {
    "tgn:hierarchy":[
        "tgn:7488919",
        "tgn:1000004",
        "tgn:7492971",
        "tgn:1000141",
        "tgn:7029392"
    ],
    "tgn:id":7488919,
    "tgn:name":"Dinghutoushan",
    "tgn:placetype":[
        "aat:300008347"
    ]
},
  "bbox": [],
  "geometry": {"coordinates":[120.741111,22.040278],"type":"Point"}
}