{
  "id": 7559795,
  "type": "Feature",
  "properties": {
    "tgn:hierarchy":[
        "tgn:7559795",
        "tgn:1000004",
        "tgn:7000198",
        "tgn:7016722",
        "tgn:7029392"
    ],
    "tgn:id":7559795,
    "tgn:name:en":"Afati\u0101pur",
    "tgn:placetype":[
        "aat:300008347"
    ]
},
  "bbox": [],
  "geometry": {"coordinates":[79.725982,27.714142],"type":"Point"}
}