{
  "id": 2048770,
  "type": "Feature",
  "properties": {
    "tgn:hierarchy":[
        "tgn:2048770",
        "tgn:1000001",
        "tgn:7016106",
        "tgn:7012149",
        "tgn:7007516",
        "tgn:7029392"
    ],
    "tgn:id":2048770,
    "tgn:name":"Smithsburg",
    "tgn:placetype":[
        "aat:300008347"
    ]
},
  "bbox": [],
  "geometry": {"coordinates":[-77.5667,39.65],"type":"Point"}
}