{
  "id": 2514368,
  "type": "Feature",
  "properties": {
    "tgn:hierarchy":[
        "tgn:2514368",
        "tgn:1000001",
        "tgn:7012149",
        "tgn:1002636",
        "tgn:7007708",
        "tgn:7029392"
    ],
    "tgn:id":2514368,
    "tgn:name":"Miller Creek",
    "tgn:placetype":[
        "aat:300008706"
    ]
},
  "bbox": [],
  "geometry": {"coordinates":[-123.0333,44.8167],"type":"Point"}
}