{
  "id": 7222676,
  "type": "Feature",
  "properties": {
    "tgn:hierarchy":[
        "tgn:7222676",
        "tgn:7002743",
        "tgn:7017076",
        "tgn:1000003",
        "tgn:1000074",
        "tgn:7029392"
    ],
    "tgn:id":7222676,
    "tgn:name":"Ploutokh\u00f3rion",
    "tgn:placetype":[
        "aat:300008347"
    ]
},
  "bbox": [],
  "geometry": {"coordinates":[21.716667,37.616667],"type":"Point"}
}