{
  "id": 1120596,
  "type": "Feature",
  "properties": {
    "tgn:hierarchy":[
        "tgn:1120596",
        "tgn:7000490",
        "tgn:1000006",
        "tgn:7006238",
        "tgn:7029392"
    ],
    "tgn:id":1120596,
    "tgn:name":"Tullaroop Reservoir",
    "tgn:placetype":[
        "aat:300006191"
    ]
},
  "bbox": [],
  "geometry": {"coordinates":[143.8667,-37.1167],"type":"Point"}
}