{
  "id": 7227503,
  "type": "Feature",
  "properties": {
    "tgn:hierarchy":[
        "tgn:7227503",
        "tgn:1042193",
        "tgn:7002705",
        "tgn:1000003",
        "tgn:1000074",
        "tgn:7029392"
    ],
    "tgn:id":7227503,
    "tgn:name":"Lygi\u00e1",
    "tgn:placetype":[
        "aat:300008347"
    ]
},
  "bbox": [],
  "geometry": {"coordinates":[20.579722,39.153889],"type":"Point"}
}