<<<<<<< HEAD
{
  "id": 2254917,
  "type": "Feature",
  "properties": {
    "tgn:hierarchy":[
        "tgn:2254917",
        "tgn:1000001",
        "tgn:7012149",
        "tgn:2001449",
        "tgn:7007566",
        "tgn:7029392"
    ],
    "tgn:id":2254917,
    "tgn:name":"Cooper Arroyo",
    "tgn:placetype":[
        "aat:300008699"
    ]
},
  "bbox": [],
  "geometry": {"coordinates":[-106.75,36.5667],"type":"Point"}
}
=======
{"geometry":{"type":"Point","coordinates":[-106.750000,36.566700]},"type":"Feature","properties":{"hierarchy":["tgn:2254917","tgn:1000001","tgn:7012149","tgn:2001449","tgn:7007566","tgn:7029392"],"placetype":["aat:300008699"],"id":2254917,"name:xx":"Cooper Arroyo"}}
>>>>>>> 03f74aca74312dbeaf24d7e61306dd6a786dc3d0
