{
  "id": 2181450,
  "type": "Feature",
  "properties": {
    "tgn:hierarchy":[
        "tgn:2181450",
        "tgn:1000001",
        "tgn:7012149",
        "tgn:2000833",
        "tgn:7007255",
        "tgn:7029392"
    ],
    "tgn:id":2181450,
    "tgn:name":"Blue Gap",
    "tgn:placetype":[
        "aat:300008347"
    ]
},
  "bbox": [],
  "geometry": {"coordinates":[-85.55,37.6833],"type":"Point"}
}