{
  "id": 2025341,
  "type": "Feature",
  "properties": {
    "tgn:hierarchy":[
        "tgn:2025341",
        "tgn:1000001",
        "tgn:7012149",
        "tgn:2000490",
        "tgn:7007250",
        "tgn:7029392"
    ],
    "tgn:id":2025341,
    "tgn:name":"Arbon",
    "tgn:placetype":[
        "aat:300008347"
    ]
},
  "bbox": [],
  "geometry": {"coordinates":[-112.5667,42.45],"type":"Point"}
}