{
  "id": 4005875,
  "type": "Feature",
  "properties": {
    "tgn:hierarchy":[
        "tgn:4005875",
        "tgn:1000003",
        "tgn:7024122",
        "tgn:7006366",
        "tgn:7029392"
    ],
    "tgn:id":4005875,
    "tgn:name":"Krze\u015blin",
    "tgn:placetype":[
        "aat:300008347"
    ]
},
  "bbox": [],
  "geometry": {"coordinates":[22.35,52.25],"type":"Point"}
}