{
  "id": 7158271,
  "type": "Feature",
  "properties": {
    "tgn:hierarchy":[
        "tgn:7158271",
        "tgn:1000003",
        "tgn:7003689",
        "tgn:7000084",
        "tgn:7029392"
    ],
    "tgn:id":7158271,
    "tgn:name":"Keulrod",
    "tgn:placetype":[
        "aat:300008347"
    ]
},
  "bbox": [],
  "geometry": {"coordinates":[10.683333,50.55],"type":"Point"}
}