{
  "id": 1092532,
  "type": "Feature",
  "properties": {
    "tgn:hierarchy":[
        "tgn:1092532",
        "tgn:7001242",
        "tgn:1001757",
        "tgn:1000189",
        "tgn:7029392"
    ],
    "tgn:id":1092532,
    "tgn:name":"Mekh\u00e9",
    "tgn:placetype":[
        "aat:300008347"
    ]
},
  "bbox": [],
  "geometry": {"coordinates":[-16.6667,15.0333],"type":"Point"}
}