{
  "id": 2474598,
  "type": "Feature",
  "properties": {
    "tgn:hierarchy":[
        "tgn:2474598",
        "tgn:1000001",
        "tgn:7012149",
        "tgn:2001719",
        "tgn:7007708",
        "tgn:7029392"
    ],
    "tgn:id":2474598,
    "tgn:name":"Lower Sand Spring",
    "tgn:placetype":[
        "aat:300008697"
    ]
},
  "bbox": [],
  "geometry": {"coordinates":[-119.5333,45.85],"type":"Point"}
}