{
  "id": 2139281,
  "type": "Feature",
  "properties": {
    "tgn:hierarchy":[
        "tgn:2139281",
        "tgn:1000001",
        "tgn:7012149",
        "tgn:7007159",
        "tgn:7029392"
    ],
    "tgn:id":2139281,
    "tgn:name":"Asmun Brook",
    "tgn:placetype":[
        "aat:300008699"
    ]
},
  "bbox": [],
  "geometry": {"coordinates":[-72.7333,41.4833],"type":"Point"}
}