{
  "id": 2476317,
  "type": "Feature",
  "properties": {
    "tgn:hierarchy":[
        "tgn:2476317",
        "tgn:1000001",
        "tgn:7012149",
        "tgn:1002742",
        "tgn:7007920",
        "tgn:7029392"
    ],
    "tgn:id":2476317,
    "tgn:name":"Lunch Creek",
    "tgn:placetype":[
        "aat:300008706"
    ]
},
  "bbox": [],
  "geometry": {"coordinates":[-120.5833,48.8667],"type":"Point"}
}