{
  "id": 2306784,
  "type": "Feature",
  "properties": {
    "tgn:hierarchy":[
        "tgn:2306784",
        "tgn:7002659",
        "tgn:1000001",
        "tgn:2000013",
        "tgn:7012149",
        "tgn:7029392"
    ],
    "tgn:id":2306784,
    "tgn:name":"East Fork Hatchet Creek",
    "tgn:placetype":[
        "aat:300008706"
    ]
},
  "bbox": [],
  "geometry": {"coordinates":[-85.9833,33.2833],"type":"Point"}
}