{
  "id": 2180081,
  "type": "Feature",
  "properties": {
    "tgn:hierarchy":[
        "tgn:2180081",
        "tgn:7030516",
        "tgn:7006450",
        "tgn:1000001",
        "tgn:7012149",
        "tgn:7029392"
    ],
    "tgn:id":2180081,
    "tgn:name":"Blind Point",
    "tgn:placetype":[
        "aat:300008850"
    ]
},
  "bbox": [],
  "geometry": {"coordinates":[-176.4333,51.8333],"type":"Point"}
}