{
  "id": 2515767,
  "type": "Feature",
  "properties": {
    "tgn:hierarchy":[
        "tgn:2515767",
        "tgn:1000001",
        "tgn:7012149",
        "tgn:2001706",
        "tgn:7007708",
        "tgn:7029392"
    ],
    "tgn:id":2515767,
    "tgn:name":"Millwood",
    "tgn:placetype":[
        "aat:300008347"
    ]
},
  "bbox": [],
  "geometry": {"coordinates":[-123.5333,43.3833],"type":"Point"}
}