{
  "id": 7555427,
  "type": "Feature",
  "properties": {
    "tgn:hierarchy":[
        "tgn:7555427",
        "tgn:1000004",
        "tgn:7000198",
        "tgn:7016788",
        "tgn:7029392"
    ],
    "tgn:id":7555427,
    "tgn:name:en":"Padampura",
    "tgn:placetype":[
        "aat:300008347"
    ]
},
  "bbox": [],
  "geometry": {"coordinates":[75.066667,25.15],"type":"Point"}
}