{
  "id": 7479268,
  "type": "Feature",
  "properties": {
    "tgn:hierarchy":[
        "tgn:7479268",
        "tgn:1000004",
        "tgn:7491221",
        "tgn:1000141",
        "tgn:7029392"
    ],
    "tgn:id":7479268,
    "tgn:name":"Zhulinshe",
    "tgn:placetype":[
        "aat:300387033"
    ]
},
  "bbox": [],
  "geometry": {"coordinates":[121.078333,22.742778],"type":"Point"}
}