{
  "id": 7338460,
  "type": "Feature",
  "properties": {
    "tgn:hierarchy":[
        "tgn:7338460",
        "tgn:7002758",
        "tgn:7002841",
        "tgn:1000003",
        "tgn:1000095",
        "tgn:7029392"
    ],
    "tgn:id":7338460,
    "tgn:name":"Castilleja de Guzm\u00e1n",
    "tgn:placetype":[
        "aat:300008347"
    ]
},
  "bbox": [],
  "geometry": {"coordinates":[-6.05,37.416667],"type":"Point"}
}