<<<<<<< HEAD
{
  "id": 2330878,
  "type": "Feature",
  "properties": {
    "tgn:hierarchy":[
        "tgn:2330878",
        "tgn:1000001",
        "tgn:7012149",
        "tgn:2002287",
        "tgn:7013961",
        "tgn:7029392"
    ],
    "tgn:id":2330878,
    "tgn:name":"Flat Ridge",
    "tgn:placetype":[
        "aat:300266640"
    ]
},
  "bbox": [],
  "geometry": {"coordinates":[-80.1333,38.3833],"type":"Point"}
}
=======
{"geometry":{"type":"Point","coordinates":[-80.133300,38.383300]},"type":"Feature","properties":{"hierarchy":["tgn:2330878","tgn:1000001","tgn:7012149","tgn:2002287","tgn:7013961","tgn:7029392"],"placetype":["aat:300266640"],"id":2330878,"name:xx":"Flat Ridge"}}
>>>>>>> 03f74aca74312dbeaf24d7e61306dd6a786dc3d0
