<<<<<<< HEAD
{
  "id": 7171545,
  "type": "Feature",
  "properties": {
    "tgn:hierarchy":[
        "tgn:7171545",
        "tgn:7003669",
        "tgn:1000003",
        "tgn:7000084",
        "tgn:7029392"
    ],
    "tgn:id":7171545,
    "tgn:name":"Hirsch-Berg",
    "tgn:placetype":[
        "aat:300008777"
    ]
},
  "bbox": [],
  "geometry": {"coordinates":[12.283333,49.333333],"type":"Point"}
}
=======
{"geometry":{"type":"Point","coordinates":[12.283333,49.333333]},"type":"Feature","properties":{"hierarchy":["tgn:7171545","tgn:7003669","tgn:1000003","tgn:7000084","tgn:7029392"],"placetype":["aat:300008777"],"id":7171545,"name:xx":"Hirsch-Berg"}}
>>>>>>> 03f74aca74312dbeaf24d7e61306dd6a786dc3d0
