{
  "id": 7410264,
  "type": "Feature",
  "properties": {
    "tgn:hierarchy":[
        "tgn:7410264",
        "tgn:1000001",
        "tgn:7005592",
        "tgn:7005560",
        "tgn:7029392"
    ],
    "tgn:id":7410264,
    "tgn:name":"Xalcomulco",
    "tgn:placetype":[
        "aat:300008347"
    ]
},
  "bbox": [],
  "geometry": {"coordinates":[-97.766667,19.593056],"type":"Point"}
}