{
  "id": 7125598,
  "type": "Feature",
  "properties": {
    "tgn:hierarchy":[
        "tgn:7125598",
        "tgn:1000003",
        "tgn:7003677",
        "tgn:7000084",
        "tgn:7029392"
    ],
    "tgn:id":7125598,
    "tgn:name":"Niedersch\u00f6nhagen",
    "tgn:placetype":[
        "aat:300008347"
    ]
},
  "bbox": [],
  "geometry": {"coordinates":[8.966667,51.95],"type":"Point"}
}