{
  "id": 7519466,
  "type": "Feature",
  "properties": {
    "tgn:hierarchy":[
        "tgn:7519466",
        "tgn:1009227",
        "tgn:7001866",
        "tgn:1000226",
        "tgn:1000006",
        "tgn:7029392"
    ],
    "tgn:id":7519466,
    "tgn:name:en":"Boundary Creek",
    "tgn:placetype":[
        "aat:300008699"
    ]
},
  "bbox": [],
  "geometry": {"coordinates":[170.133333,-44.05],"type":"Point"}
}