{
  "id": 2680267,
  "type": "Feature",
  "properties": {
    "tgn:hierarchy":[
        "tgn:2680267",
        "tgn:1000001",
        "tgn:7012149",
        "tgn:2001306",
        "tgn:7007524",
        "tgn:7029392"
    ],
    "tgn:id":2680267,
    "tgn:name":"South Fork Tucker Creek",
    "tgn:placetype":[
        "aat:300008706"
    ]
},
  "bbox": [],
  "geometry": {"coordinates":[-112.6167,45.7833],"type":"Point"}
}