{
  "id": 2223990,
  "type": "Feature",
  "properties": {
    "tgn:hierarchy":[
        "tgn:2223990",
        "tgn:1000001",
        "tgn:7012149",
        "tgn:7007255",
        "tgn:7029392"
    ],
    "tgn:id":2223990,
    "tgn:name":"Cartwright Creek",
    "tgn:placetype":[
        "aat:300008706"
    ]
},
  "bbox": [],
  "geometry": {"coordinates":[-85.1667,37.5833],"type":"Point"}
}