{
  "id": 2281764,
  "type": "Feature",
  "properties": {
    "tgn:hierarchy":[
        "tgn:2281764",
        "tgn:1000001",
        "tgn:2001704",
        "tgn:7012149",
        "tgn:7007708",
        "tgn:7029392"
    ],
    "tgn:id":2281764,
    "tgn:name":"Deer Creek",
    "tgn:placetype":[
        "aat:300008706"
    ]
},
  "bbox": [],
  "geometry": {"coordinates":[-124.1167,42.0333],"type":"Point"}
}