{
  "id": 2232936,
  "type": "Feature",
  "properties": {
    "tgn:hierarchy":[
        "tgn:2232936",
        "tgn:1000001",
        "tgn:7012149",
        "tgn:2000183",
        "tgn:7007157",
        "tgn:7029392"
    ],
    "tgn:id":2232936,
    "tgn:name":"Chappo Spring",
    "tgn:placetype":[
        "aat:300008697"
    ]
},
  "bbox": [],
  "geometry": {"coordinates":[-116.1833,35.9333],"type":"Point"}
}