{
  "id": 2667273,
  "type": "Feature",
  "properties": {
    "tgn:hierarchy":[
        "tgn:2667273",
        "tgn:1000001",
        "tgn:7012149",
        "tgn:2000544",
        "tgn:7007252",
        "tgn:7029392"
    ],
    "tgn:id":2667273,
    "tgn:name":"Skinner Branch",
    "tgn:placetype":[
        "aat:300008699"
    ]
},
  "bbox": [],
  "geometry": {"coordinates":[-86.8833,39.0667],"type":"Point"}
}