{
  "id": 1132752,
  "type": "Feature",
  "properties": {
    "tgn:hierarchy":[
        "tgn:1132752",
        "tgn:1000001",
        "tgn:7012149",
        "tgn:7007826",
        "tgn:7029392"
    ],
    "tgn:id":1132752,
    "tgn:name":"Cedar Creek",
    "tgn:placetype":[
        "aat:300008706"
    ]
},
  "bbox": [],
  "geometry": {"coordinates":[-100.3333,31.6667],"type":"Point"}
}