{
  "id": 1021683,
  "type": "Feature",
  "properties": {
    "tgn:hierarchy":[
        "tgn:1021683",
        "tgn:7012827",
        "tgn:7002454",
        "tgn:1000047",
        "tgn:1000002",
        "tgn:7029392"
    ],
    "tgn:id":1021683,
    "tgn:name":"Itabera\u00ed",
    "tgn:placetype":[
        "aat:300008347"
    ]
},
  "bbox": [],
  "geometry": {"coordinates":[-49.7167,-16.05],"type":"Point"}
}