{
  "id": 2211206,
  "type": "Feature",
  "properties": {
    "tgn:hierarchy":[
        "tgn:2211206",
        "tgn:1000001",
        "tgn:7012149",
        "tgn:2002162",
        "tgn:7007919",
        "tgn:7029392"
    ],
    "tgn:id":2211206,
    "tgn:name":"Butt Mountain",
    "tgn:placetype":[
        "aat:300008798"
    ]
},
  "bbox": [],
  "geometry": {"coordinates":[-80.6167,37.3667],"type":"Point"}
}