<<<<<<< HEAD
{
  "id": 7052566,
  "type": "Feature",
  "properties": {
    "tgn:hierarchy":[
        "tgn:7052566",
        "tgn:7003013",
        "tgn:7003005",
        "tgn:1000003",
        "tgn:1000080",
        "tgn:7029392"
    ],
    "tgn:id":7052566,
    "tgn:name":"Canale d' Ischia",
    "tgn:placetype":[
        "aat:300006075"
    ]
},
  "bbox": [],
  "geometry": {"coordinates":[13.983333,40.733333],"type":"Point"}
}
=======
{"geometry":{"type":"Point","coordinates":[13.983333,40.733333]},"type":"Feature","properties":{"hierarchy":["tgn:7052566","tgn:7003013","tgn:7003005","tgn:1000003","tgn:1000080","tgn:7029392"],"placetype":["aat:300006075"],"id":7052566,"name:xx":"Canale d' Ischia"}}
>>>>>>> 03f74aca74312dbeaf24d7e61306dd6a786dc3d0
