{
  "id": 7514747,
  "type": "Feature",
  "properties": {
    "tgn:hierarchy":[
        "tgn:7514747",
        "tgn:1009227",
        "tgn:1000226",
        "tgn:1000006",
        "tgn:7016850",
        "tgn:7029392"
    ],
    "tgn:id":7514747,
    "tgn:name:en":"Deadmans Creek",
    "tgn:placetype":[
        "aat:300008699"
    ]
},
  "bbox": [],
  "geometry": {"coordinates":[171.666667,-41.733333],"type":"Point"}
}