<<<<<<< HEAD
{
  "id": 7481506,
  "type": "Feature",
  "properties": {
    "tgn:hierarchy":[
        "tgn:7481506",
        "tgn:7487020",
        "tgn:1000004",
        "tgn:1000141",
        "tgn:7029392"
    ],
    "tgn:id":7481506,
    "tgn:name":"Xiaobajian Shan",
    "tgn:placetype":[
        "aat:300008798"
    ]
},
  "bbox": [],
  "geometry": {"coordinates":[121.251944,24.455556],"type":"Point"}
}
=======
{"geometry":{"type":"Point","coordinates":[121.251944,24.455556]},"type":"Feature","properties":{"hierarchy":["tgn:7481506","tgn:7487020","tgn:1000004","tgn:1000141","tgn:7029392"],"placetype":["aat:300008798"],"id":7481506,"name:xx":"Xiaobajian Shan"}}
>>>>>>> 03f74aca74312dbeaf24d7e61306dd6a786dc3d0
