{
  "id": 2656105,
  "type": "Feature",
  "properties": {
    "tgn:hierarchy":[
        "tgn:2656105",
        "tgn:1000001",
        "tgn:1002934",
        "tgn:7012149",
        "tgn:7007565",
        "tgn:7029392"
    ],
    "tgn:id":2656105,
    "tgn:name":"Shawanni, Lake",
    "tgn:placetype":[
        "aat:300006191"
    ]
},
  "bbox": [],
  "geometry": {"coordinates":[-74.8333,41.1667],"type":"Point"}
}