{
  "id": 2476807,
  "type": "Feature",
  "properties": {
    "tgn:hierarchy":[
        "tgn:2476807",
        "tgn:1000001",
        "tgn:7012149",
        "tgn:7007922",
        "tgn:7029392"
    ],
    "tgn:id":2476807,
    "tgn:name":"Lyga Valley",
    "tgn:placetype":[
        "aat:300008761"
    ]
},
  "bbox": [],
  "geometry": {"coordinates":[-91.5667,44.3667],"type":"Point"}
}