<<<<<<< HEAD
{
  "id": 2406636,
  "type": "Feature",
  "properties": {
    "tgn:hierarchy":[
        "tgn:2406636",
        "tgn:1000001",
        "tgn:7012149",
        "tgn:2002110",
        "tgn:7007827",
        "tgn:7029392"
    ],
    "tgn:id":2406636,
    "tgn:name":"Hunt Canyon",
    "tgn:placetype":[
        "aat:300008761"
    ]
},
  "bbox": [],
  "geometry": {"coordinates":[-109.4667,39.2833],"type":"Point"}
}
=======
{"geometry":{"type":"Point","coordinates":[-109.466700,39.283300]},"type":"Feature","properties":{"hierarchy":["tgn:2406636","tgn:1000001","tgn:7012149","tgn:2002110","tgn:7007827","tgn:7029392"],"placetype":["aat:300008761"],"id":2406636,"name:xx":"Hunt Canyon"}}
>>>>>>> 03f74aca74312dbeaf24d7e61306dd6a786dc3d0
