{
  "id": 2406636,
  "type": "Feature",
  "properties": {
    "tgn:hierarchy":[
        "tgn:2406636",
        "tgn:1000001",
        "tgn:7012149",
        "tgn:2002110",
        "tgn:7007827",
        "tgn:7029392"
    ],
    "tgn:id":2406636,
    "tgn:name":"Hunt Canyon",
    "tgn:placetype":[
        "aat:300008761"
    ]
},
  "bbox": [],
  "geometry": {"coordinates":[-109.4667,39.2833],"type":"Point"}
}