{
  "id": 2641859,
  "type": "Feature",
  "properties": {
    "tgn:hierarchy":[
        "tgn:2641859",
        "tgn:1000001",
        "tgn:2000275",
        "tgn:7012149",
        "tgn:7007240",
        "tgn:7029392"
    ],
    "tgn:id":2641859,
    "tgn:name":"Sand Lake",
    "tgn:placetype":[
        "aat:300008680"
    ]
},
  "bbox": [],
  "geometry": {"coordinates":[-83.2667,30.0667],"type":"Point"}
}