{
  "id": 2041007,
  "type": "Feature",
  "properties": {
    "tgn:hierarchy":[
        "tgn:2041007",
        "tgn:1000001",
        "tgn:7012149",
        "tgn:2000798",
        "tgn:7007255",
        "tgn:7029392"
    ],
    "tgn:id":2041007,
    "tgn:name":"Rex",
    "tgn:placetype":[
        "aat:300008347",
        "aat:300387210"
    ]
},
  "bbox": [],
  "geometry": {"coordinates":[-85.7833,37.2167],"type":"Point"}
}