{
  "id": 2677980,
  "type": "Feature",
  "properties": {
    "tgn:hierarchy":[
        "tgn:2677980",
        "tgn:2002142",
        "tgn:1000001",
        "tgn:7012149",
        "tgn:7007919",
        "tgn:7029392"
    ],
    "tgn:id":2677980,
    "tgn:name":"South Fork Back Creek",
    "tgn:placetype":[
        "aat:300008706"
    ]
},
  "bbox": [],
  "geometry": {"coordinates":[-79.0167,37.8833],"type":"Point"}
}