{
  "id": 2265889,
  "type": "Feature",
  "properties": {
    "tgn:hierarchy":[
        "tgn:2265889",
        "tgn:1000001",
        "tgn:2001412",
        "tgn:7012149",
        "tgn:7007526",
        "tgn:7029392"
    ],
    "tgn:id":2265889,
    "tgn:name":"Crater, The",
    "tgn:placetype":[
        "aat:300008798"
    ]
},
  "bbox": [],
  "geometry": {"coordinates":[-117.6333,37.8167],"type":"Point"}
}