{
  "id": 7331432,
  "type": "Feature",
  "properties": {
    "tgn:hierarchy":[
        "tgn:7331432",
        "tgn:7002758",
        "tgn:7002821",
        "tgn:1000003",
        "tgn:1000095",
        "tgn:7029392"
    ],
    "tgn:id":7331432,
    "tgn:name":"Jayena",
    "tgn:placetype":[
        "aat:300008347"
    ]
},
  "bbox": [],
  "geometry": {"coordinates":[-3.816667,36.95],"type":"Point"}
}