<<<<<<< HEAD
{
  "id": 7488819,
  "type": "Feature",
  "properties": {
    "tgn:hierarchy":[
        "tgn:7488819",
        "tgn:1000004",
        "tgn:7001009",
        "tgn:1000141",
        "tgn:7029392"
    ],
    "tgn:id":7488819,
    "tgn:name":"Nancun Li",
    "tgn:placetype":[
        "aat:300387173"
    ]
},
  "bbox": [],
  "geometry": {"coordinates":[120.736667,24.257222],"type":"Point"}
}
=======
{"geometry":{"type":"Point","coordinates":[120.736667,24.257222]},"type":"Feature","properties":{"hierarchy":["tgn:7488819","tgn:1000004","tgn:7001009","tgn:1000141","tgn:7029392"],"placetype":["aat:300387173"],"id":7488819,"name:xx":"Nancun Li"}}
>>>>>>> 03f74aca74312dbeaf24d7e61306dd6a786dc3d0
