{
  "id": 2292626,
  "type": "Feature",
  "properties": {
    "tgn:hierarchy":[
        "tgn:2292626",
        "tgn:1000001",
        "tgn:7012149",
        "tgn:1002611",
        "tgn:7007706",
        "tgn:7029392"
    ],
    "tgn:id":2292626,
    "tgn:name":"Doran Ditch",
    "tgn:placetype":[
        "aat:300006075"
    ]
},
  "bbox": [],
  "geometry": {"coordinates":[-83.8333,41.4833],"type":"Point"}
}