<<<<<<< HEAD
{
  "id": 2252560,
  "type": "Feature",
  "properties": {
    "tgn:hierarchy":[
        "tgn:2252560",
        "tgn:1000001",
        "tgn:2001100",
        "tgn:7012149",
        "tgn:7007522",
        "tgn:7029392"
    ],
    "tgn:id":2252560,
    "tgn:name":"Conn",
    "tgn:placetype":[
        "aat:300008347"
    ]
},
  "bbox": [],
  "geometry": {"coordinates":[-90.7,31.8833],"type":"Point"}
}
=======
{"geometry":{"type":"Point","coordinates":[-90.700000,31.883300]},"type":"Feature","properties":{"hierarchy":["tgn:2252560","tgn:1000001","tgn:2001100","tgn:7012149","tgn:7007522","tgn:7029392"],"placetype":["aat:300008347"],"id":2252560,"name:xx":"Conn"}}
>>>>>>> 03f74aca74312dbeaf24d7e61306dd6a786dc3d0
