{
  "id": 1102786,
  "type": "Feature",
  "properties": {
    "tgn:hierarchy":[
        "tgn:1102786",
        "tgn:1000003",
        "tgn:1000070",
        "tgn:7002895",
        "tgn:7029392"
    ],
    "tgn:id":1102786,
    "tgn:name":"Dominal, Parc",
    "tgn:placetype":[
        "aat:300008187"
    ]
},
  "bbox": [],
  "geometry": {"coordinates":[6.5333,44.8667],"type":"Point"}
}