{
  "id": 2043931,
  "type": "Feature",
  "properties": {
    "tgn:hierarchy":[
        "tgn:2043931",
        "tgn:1000001",
        "tgn:2000873",
        "tgn:7012149",
        "tgn:7007256",
        "tgn:7029392"
    ],
    "tgn:id":2043931,
    "tgn:name":"Saint Landry",
    "tgn:placetype":[
        "aat:300008347"
    ]
},
  "bbox": [],
  "geometry": {"coordinates":[-92.25,30.8333],"type":"Point"}
}