<<<<<<< HEAD
{
  "id": 2408759,
  "type": "Feature",
  "properties": {
    "tgn:hierarchy":[
        "tgn:2408759",
        "tgn:7002659",
        "tgn:1000001",
        "tgn:2000016",
        "tgn:7012149",
        "tgn:7029392"
    ],
    "tgn:id":2408759,
    "tgn:name":"Hyde Lake",
    "tgn:placetype":[
        "aat:300006191"
    ]
},
  "bbox": [],
  "geometry": {"coordinates":[-87.6667,34.5667],"type":"Point"}
}
=======
{"geometry":{"type":"Point","coordinates":[-87.666700,34.566700]},"type":"Feature","properties":{"hierarchy":["tgn:2408759","tgn:7002659","tgn:1000001","tgn:2000016","tgn:7012149","tgn:7029392"],"placetype":["aat:300006191"],"id":2408759,"name:xx":"Hyde Lake"}}
>>>>>>> 03f74aca74312dbeaf24d7e61306dd6a786dc3d0
