{
  "id": 2408759,
  "type": "Feature",
  "properties": {
    "tgn:hierarchy":[
        "tgn:2408759",
        "tgn:7002659",
        "tgn:1000001",
        "tgn:2000016",
        "tgn:7012149",
        "tgn:7029392"
    ],
    "tgn:id":2408759,
    "tgn:name":"Hyde Lake",
    "tgn:placetype":[
        "aat:300006191"
    ]
},
  "bbox": [],
  "geometry": {"coordinates":[-87.6667,34.5667],"type":"Point"}
}