<<<<<<< HEAD
{
  "id": 2155270,
  "type": "Feature",
  "properties": {
    "tgn:hierarchy":[
        "tgn:2155270",
        "tgn:1000001",
        "tgn:7012149",
        "tgn:2001453",
        "tgn:7007566",
        "tgn:7029392"
    ],
    "tgn:id":2155270,
    "tgn:name":"Bear Mountain",
    "tgn:placetype":[
        "aat:300008798"
    ]
},
  "bbox": [],
  "geometry": {"coordinates":[-105.4833,35.6667],"type":"Point"}
}
=======
{"geometry":{"type":"Point","coordinates":[-105.483300,35.666700]},"type":"Feature","properties":{"hierarchy":["tgn:2155270","tgn:1000001","tgn:7012149","tgn:2001453","tgn:7007566","tgn:7029392"],"placetype":["aat:300008798"],"id":2155270,"name:xx":"Bear Mountain"}}
>>>>>>> 03f74aca74312dbeaf24d7e61306dd6a786dc3d0
