{
  "id": 2029621,
  "type": "Feature",
  "properties": {
    "tgn:hierarchy":[
        "tgn:2029621",
        "tgn:1000001",
        "tgn:7017520",
        "tgn:7012149",
        "tgn:2000521",
        "tgn:7007251",
        "tgn:7029392"
    ],
    "tgn:id":2029621,
    "tgn:name":"Golden Acres",
    "tgn:placetype":[
        "aat:300000745"
    ]
},
  "bbox": [],
  "geometry": {"coordinates":[-89.6167,40.7333],"type":"Point"}
}