{
  "id": 2257756,
  "type": "Feature",
  "properties": {
    "tgn:hierarchy":[
        "tgn:2257756",
        "tgn:1000001",
        "tgn:2001705",
        "tgn:7012149",
        "tgn:7007708",
        "tgn:7029392"
    ],
    "tgn:id":2257756,
    "tgn:name":"Corral Lake",
    "tgn:placetype":[
        "aat:300008680"
    ]
},
  "bbox": [],
  "geometry": {"coordinates":[-121.7167,44.05],"type":"Point"}
}