<<<<<<< HEAD
{
  "id": 2257756,
  "type": "Feature",
  "properties": {
    "tgn:hierarchy":[
        "tgn:2257756",
        "tgn:1000001",
        "tgn:2001705",
        "tgn:7012149",
        "tgn:7007708",
        "tgn:7029392"
    ],
    "tgn:id":2257756,
    "tgn:name":"Corral Lake",
    "tgn:placetype":[
        "aat:300008680"
    ]
},
  "bbox": [],
  "geometry": {"coordinates":[-121.7167,44.05],"type":"Point"}
}
=======
{"geometry":{"type":"Point","coordinates":[-121.716700,44.050000]},"type":"Feature","properties":{"hierarchy":["tgn:2257756","tgn:1000001","tgn:2001705","tgn:7012149","tgn:7007708","tgn:7029392"],"placetype":["aat:300008680"],"id":2257756,"name:xx":"Corral Lake"}}
>>>>>>> 03f74aca74312dbeaf24d7e61306dd6a786dc3d0
