{
  "id": 7352635,
  "type": "Feature",
  "properties": {
    "tgn:hierarchy":[
        "tgn:7352635",
        "tgn:7005586",
        "tgn:1000001",
        "tgn:7005560",
        "tgn:7029392"
    ],
    "tgn:id":7352635,
    "tgn:name":"Atenquique",
    "tgn:placetype":[
        "aat:300000241"
    ]
},
  "bbox": [],
  "geometry": {"coordinates":[-103.516667,19.55],"type":"Point"}
}