<<<<<<< HEAD
{
  "id": 7352635,
  "type": "Feature",
  "properties": {
    "tgn:hierarchy":[
        "tgn:7352635",
        "tgn:7005586",
        "tgn:1000001",
        "tgn:7005560",
        "tgn:7029392"
    ],
    "tgn:id":7352635,
    "tgn:name":"Atenquique",
    "tgn:placetype":[
        "aat:300000241"
    ]
},
  "bbox": [],
  "geometry": {"coordinates":[-103.516667,19.55],"type":"Point"}
}
=======
{"geometry":{"type":"Point","coordinates":[-103.516667,19.550000]},"type":"Feature","properties":{"hierarchy":["tgn:7352635","tgn:7005586","tgn:1000001","tgn:7005560","tgn:7029392"],"placetype":["aat:300000241"],"id":7352635,"name:xx":"Atenquique"}}
>>>>>>> 03f74aca74312dbeaf24d7e61306dd6a786dc3d0
