{
  "id": 7480635,
  "type": "Feature",
  "properties": {
    "tgn:hierarchy":[
        "tgn:7480635",
        "tgn:7468018",
        "tgn:1000004",
        "tgn:1000141",
        "tgn:7029392"
    ],
    "tgn:id":7480635,
    "tgn:name":"Pitou Qiao",
    "tgn:placetype":[
        "aat:300007836"
    ]
},
  "bbox": [],
  "geometry": {"coordinates":[120.228233,23.354244],"type":"Point"}
}