{
  "id": 1084466,
  "type": "Feature",
  "properties": {
    "tgn:hierarchy":[
        "tgn:1084466",
        "tgn:1000004",
        "tgn:1001185",
        "tgn:1000135",
        "tgn:7029392"
    ],
    "tgn:id":1084466,
    "tgn:name":"Moalboal",
    "tgn:placetype":[
        "aat:300008347"
    ]
},
  "bbox": [],
  "geometry": {"coordinates":[123.3833,9.9333],"type":"Point"}
}