{
  "id": 2071515,
  "type": "Feature",
  "properties": {
    "tgn:hierarchy":[
        "tgn:2071515",
        "tgn:1000001",
        "tgn:7012149",
        "tgn:1002746",
        "tgn:7007568",
        "tgn:7029392"
    ],
    "tgn:id":2071515,
    "tgn:name":"Otisco Valley",
    "tgn:placetype":[
        "aat:300008347"
    ]
},
  "bbox": [],
  "geometry": {"coordinates":[-76.2167,42.8167],"type":"Point"}
}