{
  "id": 2669810,
  "type": "Feature",
  "properties": {
    "tgn:hierarchy":[
        "tgn:2669810",
        "tgn:1000001",
        "tgn:7012149",
        "tgn:7007157",
        "tgn:1002608",
        "tgn:7029392"
    ],
    "tgn:id":2669810,
    "tgn:name":"Slip Number One",
    "tgn:placetype":[
        "aat:300008678"
    ]
},
  "bbox": [],
  "geometry": {"coordinates":[-118.25,33.75],"type":"Point"}
}