{
  "id": 7067840,
  "type": "Feature",
  "properties": {
    "tgn:hierarchy":[
        "tgn:7067840",
        "tgn:1000003",
        "tgn:7003677",
        "tgn:7000084",
        "tgn:7029392"
    ],
    "tgn:id":7067840,
    "tgn:name":"F\u00f6rsterei Torfbruch",
    "tgn:placetype":[
        "aat:300004792"
    ]
},
  "bbox": [],
  "geometry": {"coordinates":[8.95,51.616667],"type":"Point"}
}