{
  "id": 7592209,
  "type": "Feature",
  "properties": {
    "tgn:hierarchy":[
        "tgn:7592209",
        "tgn:1000004",
        "tgn:7000198",
        "tgn:7000799",
        "tgn:7029392"
    ],
    "tgn:id":7592209,
    "tgn:name:en":"Kangar",
    "tgn:placetype":[
        "aat:300008347"
    ]
},
  "bbox": [],
  "geometry": {"coordinates":[74.629167,32.893056],"type":"Point"}
}