{
  "id": 2161049,
  "type": "Feature",
  "properties": {
    "tgn:hierarchy":[
        "tgn:2161049",
        "tgn:1000001",
        "tgn:2001411",
        "tgn:7012149",
        "tgn:7007526",
        "tgn:7029392"
    ],
    "tgn:id":2161049,
    "tgn:name":"Bell Canyon",
    "tgn:placetype":[
        "aat:300008761"
    ]
},
  "bbox": [],
  "geometry": {"coordinates":[-114.6167,41.6333],"type":"Point"}
}