{
  "id": 7216844,
  "type": "Feature",
  "properties": {
    "tgn:hierarchy":[
        "tgn:7216844",
        "tgn:1000003",
        "tgn:7003677",
        "tgn:7000084",
        "tgn:7029392"
    ],
    "tgn:id":7216844,
    "tgn:name":"Aaperh\u00f6fe",
    "tgn:placetype":[
        "aat:300000206"
    ]
},
  "bbox": [],
  "geometry": {"coordinates":[6.65,51.65],"type":"Point"}
}