{
  "id": 2651079,
  "type": "Feature",
  "properties": {
    "tgn:hierarchy":[
        "tgn:2651079",
        "tgn:1000001",
        "tgn:7012149",
        "tgn:2000214",
        "tgn:7007158",
        "tgn:7029392"
    ],
    "tgn:id":2651079,
    "tgn:name":"Second Water Spring",
    "tgn:placetype":[
        "aat:300008697"
    ]
},
  "bbox": [],
  "geometry": {"coordinates":[-108.5167,39.5333],"type":"Point"}
}