{
  "id": 2594645,
  "type": "Feature",
  "properties": {
    "tgn:hierarchy":[
        "tgn:2594645",
        "tgn:1000001",
        "tgn:7012149",
        "tgn:2001694",
        "tgn:7007707",
        "tgn:7029392"
    ],
    "tgn:id":2594645,
    "tgn:name":"Posey Creek",
    "tgn:placetype":[
        "aat:300008706"
    ]
},
  "bbox": [],
  "geometry": {"coordinates":[-95.9667,35.95],"type":"Point"}
}