{
  "id": 7476452,
  "type": "Feature",
  "properties": {
    "tgn:hierarchy":[
        "tgn:7476452",
        "tgn:7487020",
        "tgn:1000004",
        "tgn:1000141",
        "tgn:7029392"
    ],
    "tgn:id":7476452,
    "tgn:name":"Kengkou",
    "tgn:placetype":[
        "aat:300008347"
    ]
},
  "bbox": [],
  "geometry": {"coordinates":[120.990454,24.665891],"type":"Point"}
}