{
  "id": 2664467,
  "type": "Feature",
  "properties": {
    "tgn:hierarchy":[
        "tgn:2664467",
        "tgn:1000001",
        "tgn:7012149",
        "tgn:2001441",
        "tgn:7007566",
        "tgn:7029392"
    ],
    "tgn:id":2664467,
    "tgn:name":"Simanola Valley",
    "tgn:placetype":[
        "aat:300008761"
    ]
},
  "bbox": [],
  "geometry": {"coordinates":[-103.4167,33.35],"type":"Point"}
}