{
  "id": 7066476,
  "type": "Feature",
  "properties": {
    "tgn:hierarchy":[
        "tgn:7066476",
        "tgn:7003669",
        "tgn:1000003",
        "tgn:7000084",
        "tgn:7029392"
    ],
    "tgn:id":7066476,
    "tgn:name":"\u00dchleinshof",
    "tgn:placetype":[
        "aat:300008347"
    ]
},
  "bbox": [],
  "geometry": {"coordinates":[11.266667,49.733333],"type":"Point"}
}