{
  "id": 2163642,
  "type": "Feature",
  "properties": {
    "tgn:hierarchy":[
        "tgn:2163642",
        "tgn:1000001",
        "tgn:7012149",
        "tgn:2000349",
        "tgn:7007248",
        "tgn:7029392"
    ],
    "tgn:id":2163642,
    "tgn:name":"Bentley Creek",
    "tgn:placetype":[
        "aat:300008706"
    ]
},
  "bbox": [],
  "geometry": {"coordinates":[-84.2167,34.1833],"type":"Point"}
}