{
  "id": 1013464,
  "type": "Feature",
  "properties": {
    "tgn:hierarchy":[
        "tgn:1013464",
        "tgn:7005735",
        "tgn:7005685",
        "tgn:1000001",
        "tgn:7029392"
    ],
    "tgn:id":1013464,
    "tgn:name":"Criss Creek",
    "tgn:placetype":[
        "aat:300008347"
    ]
},
  "bbox": [],
  "geometry": {"coordinates":[-120.7333,51.0333],"type":"Point"}
}