{
  "id": 2549334,
  "type": "Feature",
  "properties": {
    "tgn:hierarchy":[
        "tgn:2549334",
        "tgn:1000001",
        "tgn:2001634",
        "tgn:7012149",
        "tgn:7007707",
        "tgn:7029392"
    ],
    "tgn:id":2549334,
    "tgn:name":"North Sandy Branch",
    "tgn:placetype":[
        "aat:300008699"
    ]
},
  "bbox": [],
  "geometry": {"coordinates":[-95.3833,33.95],"type":"Point"}
}