{
  "id": 2269439,
  "type": "Feature",
  "properties": {
    "tgn:hierarchy":[
        "tgn:2269439",
        "tgn:1000001",
        "tgn:7014423",
        "tgn:7012149",
        "tgn:7007517",
        "tgn:7029392"
    ],
    "tgn:id":2269439,
    "tgn:name":"Crow Point",
    "tgn:placetype":[
        "aat:300008850"
    ]
},
  "bbox": [],
  "geometry": {"coordinates":[-70.8833,42.25],"type":"Point"}
}