{
  "id": 7141469,
  "type": "Feature",
  "properties": {
    "tgn:hierarchy":[
        "tgn:7141469",
        "tgn:7003692",
        "tgn:1000003",
        "tgn:7000084",
        "tgn:7029392"
    ],
    "tgn:id":7141469,
    "tgn:name":"Linsenhof",
    "tgn:placetype":[
        "aat:300008347"
    ]
},
  "bbox": [],
  "geometry": {"coordinates":[9.783333,48.916667],"type":"Point"}
}