{
  "id": 1081531,
  "type": "Feature",
  "properties": {
    "tgn:hierarchy":[
        "tgn:1081531",
        "tgn:1000004",
        "tgn:1001012",
        "tgn:7000896",
        "tgn:1000120",
        "tgn:7029392"
    ],
    "tgn:id":1081531,
    "tgn:name":"Tenri",
    "tgn:placetype":[
        "aat:300008347"
    ]
},
  "bbox": [],
  "geometry": {"coordinates":[135.8333,34.5833],"type":"Point"}
}