{
  "id": 2453863,
  "type": "Feature",
  "properties": {
    "tgn:hierarchy":[
        "tgn:2453863",
        "tgn:1000001",
        "tgn:7012149",
        "tgn:2001075",
        "tgn:7007521",
        "tgn:7029392"
    ],
    "tgn:id":2453863,
    "tgn:name":"Little Cranberry Lake",
    "tgn:placetype":[
        "aat:300008680"
    ]
},
  "bbox": [],
  "geometry": {"coordinates":[-94.6667,46.1833],"type":"Point"}
}