{
  "id": 1128391,
  "type": "Feature",
  "properties": {
    "tgn:hierarchy":[
        "tgn:1128391",
        "tgn:1000002",
        "tgn:7029392"
    ],
    "tgn:id":1128391,
    "tgn:name":"Paran\u00e1",
    "tgn:placetype":[
        "aat:300008707"
    ]
},
  "bbox": [],
  "geometry": {"coordinates":[-52.4167,-22.5833],"type":"Point"}
}