{
  "id": 2749447,
  "type": "Feature",
  "properties": {
    "tgn:hierarchy":[
        "tgn:2749447",
        "tgn:1000001",
        "tgn:7012149",
        "tgn:2001243",
        "tgn:7007523",
        "tgn:7029392"
    ],
    "tgn:id":2749447,
    "tgn:name":"Wallys Lake",
    "tgn:placetype":[
        "aat:300006191"
    ]
},
  "bbox": [],
  "geometry": {"coordinates":[-93.1667,39.1333],"type":"Point"}
}