{
  "id": 2785294,
  "type": "Feature",
  "properties": {
    "tgn:hierarchy":[
        "tgn:2785294",
        "tgn:1000001",
        "tgn:2000507",
        "tgn:7012149",
        "tgn:7007251",
        "tgn:7029392"
    ],
    "tgn:id":2785294,
    "tgn:name":"Yellowbank Slough",
    "tgn:placetype":[
        "aat:300008905"
    ]
},
  "bbox": [],
  "geometry": {"coordinates":[-88.1167,37.8333],"type":"Point"}
}