{
  "id": 1107630,
  "type": "Feature",
  "properties": {
    "tgn:hierarchy":[
        "tgn:1107630",
        "tgn:1000001",
        "tgn:2001418",
        "tgn:7012149",
        "tgn:7007526",
        "tgn:7029392"
    ],
    "tgn:id":1107630,
    "tgn:name":"Wheelbarrow Peak",
    "tgn:placetype":[
        "aat:300008798"
    ]
},
  "bbox": [],
  "geometry": {"coordinates":[-116.0667,37.45],"type":"Point"}
}