{
  "id": 2025973,
  "type": "Feature",
  "properties": {
    "tgn:hierarchy":[
        "tgn:2025973",
        "tgn:2000455",
        "tgn:1000001",
        "tgn:7012149",
        "tgn:7007250",
        "tgn:7029392"
    ],
    "tgn:id":2025973,
    "tgn:name":"Ovid",
    "tgn:placetype":[
        "aat:300008347"
    ]
},
  "bbox": [],
  "geometry": {"coordinates":[-111.3833,42.2833],"type":"Point"}
}