{
  "id": 2140383,
  "type": "Feature",
  "properties": {
    "tgn:hierarchy":[
        "tgn:2140383",
        "tgn:1000001",
        "tgn:7012149",
        "tgn:2001868",
        "tgn:7007825",
        "tgn:7029392"
    ],
    "tgn:id":2140383,
    "tgn:name":"Aunt Jane Hollow",
    "tgn:placetype":[
        "aat:300008761"
    ]
},
  "bbox": [],
  "geometry": {"coordinates":[-83.3167,36.15],"type":"Point"}
}