{
  "id": 2622138,
  "type": "Feature",
  "properties": {
    "tgn:hierarchy":[
        "tgn:2622138",
        "tgn:1000001",
        "tgn:7012149",
        "tgn:1002447",
        "tgn:7007252",
        "tgn:7029392"
    ],
    "tgn:id":2622138,
    "tgn:name":"Roberts Lake",
    "tgn:placetype":[
        "aat:300008680"
    ]
},
  "bbox": [],
  "geometry": {"coordinates":[-85.75,39.7833],"type":"Point"}
}