{
  "id": 2744343,
  "type": "Feature",
  "properties": {
    "tgn:hierarchy":[
        "tgn:2744343",
        "tgn:1000001",
        "tgn:2000459",
        "tgn:7012149",
        "tgn:7007250",
        "tgn:7029392"
    ],
    "tgn:id":2744343,
    "tgn:name":"Vernon Lake",
    "tgn:placetype":[
        "aat:300008680"
    ]
},
  "bbox": [],
  "geometry": {"coordinates":[-114.9833,43.95],"type":"Point"}
}