{
  "id": 2346245,
  "type": "Feature",
  "properties": {
    "tgn:hierarchy":[
        "tgn:2346245",
        "tgn:1000001",
        "tgn:2156155",
        "tgn:7012149",
        "tgn:7007248",
        "tgn:7029392"
    ],
    "tgn:id":2346245,
    "tgn:name":"Gates Lake",
    "tgn:placetype":[
        "aat:300006191"
    ]
},
  "bbox": [],
  "geometry": {"coordinates":[-84.7833,32.55],"type":"Point"}
}