{
  "id": 2071252,
  "type": "Feature",
  "properties": {
    "tgn:hierarchy":[
        "tgn:2071252",
        "tgn:1000001",
        "tgn:7012149",
        "tgn:7014287",
        "tgn:7007568",
        "tgn:7029392"
    ],
    "tgn:id":2071252,
    "tgn:name":"North Bay",
    "tgn:placetype":[
        "aat:300008347"
    ]
},
  "bbox": [],
  "geometry": {"coordinates":[-75.7333,43.2167],"type":"Point"}
}