{
  "id": 7557108,
  "type": "Feature",
  "properties": {
    "tgn:hierarchy":[
        "tgn:7557108",
        "tgn:1000004",
        "tgn:7000198",
        "tgn:1001977",
        "tgn:7029392"
    ],
    "tgn:id":7557108,
    "tgn:name:en":"Pippli Sand",
    "tgn:placetype":[
        "aat:300386970"
    ]
},
  "bbox": [],
  "geometry": {"coordinates":[88.35,21.533333],"type":"Point"}
}