{
  "id": 2042835,
  "type": "Feature",
  "properties": {
    "tgn:hierarchy":[
        "tgn:2042835",
        "tgn:1000001",
        "tgn:7012149",
        "tgn:2000887",
        "tgn:7007256",
        "tgn:7029392"
    ],
    "tgn:id":2042835,
    "tgn:name":"Galion",
    "tgn:placetype":[
        "aat:300008347",
        "aat:300387210"
    ]
},
  "bbox": [],
  "geometry": {"coordinates":[-91.75,32.85],"type":"Point"}
}