<<<<<<< HEAD
{
  "id": 2152091,
  "type": "Feature",
  "properties": {
    "tgn:hierarchy":[
        "tgn:2152091",
        "tgn:1000001",
        "tgn:7012149",
        "tgn:1002678",
        "tgn:7007252",
        "tgn:7029392"
    ],
    "tgn:id":2152091,
    "tgn:name":"Baxter Branch",
    "tgn:placetype":[
        "aat:300008699"
    ]
},
  "bbox": [],
  "geometry": {"coordinates":[-86.4333,39.1167],"type":"Point"}
}
=======
{"geometry":{"type":"Point","coordinates":[-86.433300,39.116700]},"type":"Feature","properties":{"hierarchy":["tgn:2152091","tgn:1000001","tgn:7012149","tgn:1002678","tgn:7007252","tgn:7029392"],"placetype":["aat:300008699"],"id":2152091,"name:xx":"Baxter Branch"}}
>>>>>>> 03f74aca74312dbeaf24d7e61306dd6a786dc3d0
