<<<<<<< HEAD
{
  "id": 2255759,
  "type": "Feature",
  "properties": {
    "tgn:hierarchy":[
        "tgn:2255759",
        "tgn:1000001",
        "tgn:7006451",
        "tgn:7012149",
        "tgn:2000101",
        "tgn:7029392"
    ],
    "tgn:id":2255759,
    "tgn:name":"Copper Butte Mine",
    "tgn:placetype":[
        "aat:300000390"
    ]
},
  "bbox": [],
  "geometry": {"coordinates":[-111.05,33.1333],"type":"Point"}
}
=======
{"geometry":{"type":"Point","coordinates":[-111.050000,33.133300]},"type":"Feature","properties":{"hierarchy":["tgn:2255759","tgn:1000001","tgn:7006451","tgn:7012149","tgn:2000101","tgn:7029392"],"placetype":["aat:300000390"],"id":2255759,"name:xx":"Copper Butte Mine"}}
>>>>>>> 03f74aca74312dbeaf24d7e61306dd6a786dc3d0
