{
  "id": 7319344,
  "type": "Feature",
  "properties": {
    "tgn:hierarchy":[
        "tgn:7319344",
        "tgn:1001623",
        "tgn:1000049",
        "tgn:1000002",
        "tgn:7029392"
    ],
    "tgn:id":7319344,
    "tgn:name":"Americano, Puerto",
    "tgn:placetype":[
        "aat:300008678"
    ]
},
  "bbox": [],
  "geometry": {"coordinates":[-73.716667,-45.033333],"type":"Point"}
}