{
  "id": 2729783,
  "type": "Feature",
  "properties": {
    "tgn:hierarchy":[
        "tgn:2729783",
        "tgn:1000001",
        "tgn:7012149",
        "tgn:2002374",
        "tgn:7007923",
        "tgn:7029392"
    ],
    "tgn:id":2729783,
    "tgn:name":"Trough Spring",
    "tgn:placetype":[
        "aat:300008697"
    ]
},
  "bbox": [],
  "geometry": {"coordinates":[-106.9333,43.8167],"type":"Point"}
}