<<<<<<< HEAD
{
  "id": 7023755,
  "type": "Feature",
  "properties": {
    "tgn:hierarchy":[
        "tgn:7023755",
        "tgn:1000001",
        "tgn:7012149",
        "tgn:7007251",
        "tgn:7029392"
    ],
    "tgn:id":7023755,
    "tgn:name":"Tiber Creek",
    "tgn:placetype":[
        "aat:300008706"
    ]
},
  "bbox": [],
  "geometry": {"coordinates":[-89.95,40.6667],"type":"Point"}
}
=======
{"geometry":{"type":"Point","coordinates":[-89.950000,40.666700]},"type":"Feature","properties":{"hierarchy":["tgn:7023755","tgn:1000001","tgn:7012149","tgn:7007251","tgn:7029392"],"placetype":["aat:300008706"],"id":7023755,"name:xx":"Tiber Creek"}}
>>>>>>> 03f74aca74312dbeaf24d7e61306dd6a786dc3d0
