{
  "id": 7529261,
  "type": "Feature",
  "properties": {
    "tgn:hierarchy":[
        "tgn:7529261",
        "tgn:7001242",
        "tgn:7001105",
        "tgn:7016833",
        "tgn:7029392"
    ],
    "tgn:id":7529261,
    "tgn:name:en":"Man\u0101mat S\u012bd\u012b al Mur\u0101bi\u0163",
    "tgn:placetype":[
        "aat:300005926"
    ]
},
  "bbox": [],
  "geometry": {"coordinates":[30.75,29.283333],"type":"Point"}
}