{
  "id": 2674565,
  "type": "Feature",
  "properties": {
    "tgn:hierarchy":[
        "tgn:2674565",
        "tgn:1000001",
        "tgn:7012149",
        "tgn:2002377",
        "tgn:7007923",
        "tgn:7029392"
    ],
    "tgn:id":2674565,
    "tgn:name":"Snyder Reservoir",
    "tgn:placetype":[
        "aat:300006191"
    ]
},
  "bbox": [],
  "geometry": {"coordinates":[-106.3167,43.35],"type":"Point"}
}