{
  "id": 7275681,
  "type": "Feature",
  "properties": {
    "tgn:hierarchy":[
        "tgn:7275681",
        "tgn:1001702",
        "tgn:1000049",
        "tgn:1000002",
        "tgn:7029392"
    ],
    "tgn:id":7275681,
    "tgn:name":"Treble, Isla",
    "tgn:placetype":[
        "aat:300008791"
    ]
},
  "bbox": [],
  "geometry": {"coordinates":[-71.016667,-55.083333],"type":"Point"}
}