{
  "id": 2765726,
  "type": "Feature",
  "properties": {
    "tgn:hierarchy":[
        "tgn:2765726",
        "tgn:1000001",
        "tgn:7012149",
        "tgn:2002121",
        "tgn:7007827",
        "tgn:7029392"
    ],
    "tgn:id":2765726,
    "tgn:name":"White Creek",
    "tgn:placetype":[
        "aat:300008706"
    ]
},
  "bbox": [],
  "geometry": {"coordinates":[-111.65,38.6833],"type":"Point"}
}