{
  "id": 2352770,
  "type": "Feature",
  "properties": {
    "tgn:hierarchy":[
        "tgn:2352770",
        "tgn:1000001",
        "tgn:7012149",
        "tgn:2001684",
        "tgn:7007707",
        "tgn:7029392"
    ],
    "tgn:id":2352770,
    "tgn:name":"Gobbler Knob",
    "tgn:placetype":[
        "aat:300008798"
    ]
},
  "bbox": [],
  "geometry": {"coordinates":[-96.55,34.5333],"type":"Point"}
}