{
  "id": 2110234,
  "type": "Feature",
  "properties": {
    "tgn:hierarchy":[
        "tgn:2110234",
        "tgn:1000001",
        "tgn:7012149",
        "tgn:2002175",
        "tgn:7007919",
        "tgn:7029392"
    ],
    "tgn:id":2110234,
    "tgn:name":"Adial",
    "tgn:placetype":[
        "aat:300008347",
        "aat:300387210"
    ]
},
  "bbox": [],
  "geometry": {"coordinates":[-78.8167,37.85],"type":"Point"}
}