{
  "id": 7088610,
  "type": "Feature",
  "properties": {
    "tgn:hierarchy":[
        "tgn:7088610",
        "tgn:1000003",
        "tgn:7003687",
        "tgn:7000084",
        "tgn:7029392"
    ],
    "tgn:id":7088610,
    "tgn:name":"Wahlsdorf",
    "tgn:placetype":[
        "aat:300008347"
    ]
},
  "bbox": [],
  "geometry": {"coordinates":[12.516667,51.95],"type":"Point"}
}