{
  "id": 2121524,
  "type": "Feature",
  "properties": {
    "tgn:hierarchy":[
        "tgn:2121524",
        "tgn:1000001",
        "tgn:2002325",
        "tgn:7012149",
        "tgn:7007922",
        "tgn:7029392"
    ],
    "tgn:id":2121524,
    "tgn:name":"Kingston",
    "tgn:placetype":[
        "aat:300008347"
    ]
},
  "bbox": [],
  "geometry": {"coordinates":[-89.1167,43.6833],"type":"Point"}
}