{
  "id": 7580780,
  "type": "Feature",
  "properties": {
    "tgn:hierarchy":[
        "tgn:7580780",
        "tgn:1000004",
        "tgn:1001842",
        "tgn:7000198",
        "tgn:7029392"
    ],
    "tgn:id":7580780,
    "tgn:name:en":"Sh\u0101hpur Patori",
    "tgn:placetype":[
        "aat:300008347"
    ]
},
  "bbox": [],
  "geometry": {"coordinates":[85.582279,25.637341],"type":"Point"}
}