{
  "id": 2437868,
  "type": "Feature",
  "properties": {
    "tgn:hierarchy":[
        "tgn:2437868",
        "tgn:1000001",
        "tgn:7012149",
        "tgn:7015666",
        "tgn:7007825",
        "tgn:7029392"
    ],
    "tgn:id":2437868,
    "tgn:name":"King Hollow",
    "tgn:placetype":[
        "aat:300008761"
    ]
},
  "bbox": [],
  "geometry": {"coordinates":[-87.6667,35.6833],"type":"Point"}
}