{
  "id": 7514228,
  "type": "Feature",
  "properties": {
    "tgn:hierarchy":[
        "tgn:7514228",
        "tgn:1009227",
        "tgn:1000226",
        "tgn:7016822",
        "tgn:1000006",
        "tgn:7029392"
    ],
    "tgn:id":7514228,
    "tgn:name:en":"Eastmere",
    "tgn:placetype":[
        "aat:300008680"
    ]
},
  "bbox": [],
  "geometry": {"coordinates":[167.616667,-45.483333],"type":"Point"}
}