{
  "id": 7027850,
  "type": "Feature",
  "properties": {
    "tgn:hierarchy":[
        "tgn:7027850",
        "tgn:7002445",
        "tgn:1000003",
        "tgn:7008157",
        "tgn:7008591",
        "tgn:7029392"
    ],
    "tgn:id":7027850,
    "tgn:name":"Easton",
    "tgn:placetype":[
        "aat:300008347",
        "aat:300008372"
    ]
},
  "bbox": [],
  "geometry": {"coordinates":[-0.6333,52.8333],"type":"Point"}
}