{
  "id": 7565495,
  "type": "Feature",
  "properties": {
    "tgn:hierarchy":[
        "tgn:7565495",
        "tgn:1000004",
        "tgn:7000198",
        "tgn:7016722",
        "tgn:7029392"
    ],
    "tgn:id":7565495,
    "tgn:name:en":"Nab\u012bpur",
    "tgn:placetype":[
        "aat:300008347"
    ]
},
  "bbox": [],
  "geometry": {"coordinates":[79.317439,26.238243],"type":"Point"}
}