{
  "id": 2478398,
  "type": "Feature",
  "properties": {
    "tgn:hierarchy":[
        "tgn:2478398",
        "tgn:1008293",
        "tgn:1000001",
        "tgn:1002705",
        "tgn:7012149",
        "tgn:7007517",
        "tgn:7029392"
    ],
    "tgn:id":2478398,
    "tgn:name":"Macys Hill",
    "tgn:placetype":[
        "aat:300008777"
    ]
},
  "bbox": [],
  "geometry": {"coordinates":[-70.0167,41.2667],"type":"Point"}
}