{
  "id": 2719468,
  "type": "Feature",
  "properties": {
    "tgn:hierarchy":[
        "tgn:2719468",
        "tgn:7006450",
        "tgn:1000001",
        "tgn:7012149",
        "tgn:2124002",
        "tgn:7029392"
    ],
    "tgn:id":2719468,
    "tgn:name":"Three Entrance Bay",
    "tgn:placetype":[
        "aat:300132316"
    ]
},
  "bbox": [],
  "geometry": {"coordinates":[-135.3667,56.9667],"type":"Point"}
}