{
  "id": 7348943,
  "type": "Feature",
  "properties": {
    "tgn:hierarchy":[
        "tgn:7348943",
        "tgn:7005581",
        "tgn:1000001",
        "tgn:7005560",
        "tgn:7029392"
    ],
    "tgn:id":7348943,
    "tgn:name":"Agua Caliente",
    "tgn:placetype":[
        "aat:300008347"
    ]
},
  "bbox": [],
  "geometry": {"coordinates":[-108.466667,27.583333],"type":"Point"}
}