{
  "id": 2565383,
  "type": "Feature",
  "properties": {
    "tgn:hierarchy":[
        "tgn:2565383",
        "tgn:1000001",
        "tgn:7012149",
        "tgn:1002612",
        "tgn:7007710",
        "tgn:7029392"
    ],
    "tgn:id":2565383,
    "tgn:name":"Paint Spring Run",
    "tgn:placetype":[
        "aat:300008699"
    ]
},
  "bbox": [],
  "geometry": {"coordinates":[-76.0833,41.35],"type":"Point"}
}