{
  "id": 2219719,
  "type": "Feature",
  "properties": {
    "tgn:hierarchy":[
        "tgn:2219719",
        "tgn:1000001",
        "tgn:7012149",
        "tgn:2000203",
        "tgn:7007158",
        "tgn:7029392"
    ],
    "tgn:id":2219719,
    "tgn:name":"Canova Canyon",
    "tgn:placetype":[
        "aat:300008761"
    ]
},
  "bbox": [],
  "geometry": {"coordinates":[-105.15,37.2167],"type":"Point"}
}