{
  "id": 2565560,
  "type": "Feature",
  "properties": {
    "tgn:hierarchy":[
        "tgn:2565560",
        "tgn:1000001",
        "tgn:1002330",
        "tgn:7012149",
        "tgn:7007710",
        "tgn:7029392"
    ],
    "tgn:id":2565560,
    "tgn:name":"Painters Crossroads",
    "tgn:placetype":[
        "aat:300008347"
    ]
},
  "bbox": [],
  "geometry": {"coordinates":[-75.5333,39.8667],"type":"Point"}
}