{
  "id": 7292063,
  "type": "Feature",
  "properties": {
    "tgn:hierarchy":[
        "tgn:7292063",
        "tgn:1001630",
        "tgn:1000049",
        "tgn:1000002",
        "tgn:7029392"
    ],
    "tgn:id":7292063,
    "tgn:name":"Finca Agua Dulce",
    "tgn:placetype":[
        "aat:300008347"
    ]
},
  "bbox": [],
  "geometry": {"coordinates":[-69.516667,-26.433333],"type":"Point"}
}