{
  "id": 2764514,
  "type": "Feature",
  "properties": {
    "tgn:hierarchy":[
        "tgn:2764514",
        "tgn:1000001",
        "tgn:7012149",
        "tgn:1002993",
        "tgn:7007568",
        "tgn:7029392"
    ],
    "tgn:id":2764514,
    "tgn:name":"Whipple Brook",
    "tgn:placetype":[
        "aat:300008699"
    ]
},
  "bbox": [],
  "geometry": {"coordinates":[-73.4167,42.9833],"type":"Point"}
}