<<<<<<< HEAD
{
  "id": 2150041,
  "type": "Feature",
  "properties": {
    "tgn:hierarchy":[
        "tgn:2150041",
        "tgn:7002659",
        "tgn:1000001",
        "tgn:7012149",
        "tgn:2000063",
        "tgn:7029392"
    ],
    "tgn:id":2150041,
    "tgn:name":"Barton Creek",
    "tgn:placetype":[
        "aat:300008706"
    ]
},
  "bbox": [],
  "geometry": {"coordinates":[-87.1833,33.7],"type":"Point"}
}
=======
{"geometry":{"type":"Point","coordinates":[-87.183300,33.700000]},"type":"Feature","properties":{"hierarchy":["tgn:2150041","tgn:7002659","tgn:1000001","tgn:7012149","tgn:2000063","tgn:7029392"],"placetype":["aat:300008706"],"id":2150041,"name:xx":"Barton Creek"}}
>>>>>>> 03f74aca74312dbeaf24d7e61306dd6a786dc3d0
