<<<<<<< HEAD
{
  "id": 7352767,
  "type": "Feature",
  "properties": {
    "tgn:hierarchy":[
        "tgn:7352767",
        "tgn:1000001",
        "tgn:7005599",
        "tgn:7005560",
        "tgn:7029392"
    ],
    "tgn:id":7352767,
    "tgn:name":"Buenavista",
    "tgn:placetype":[
        "aat:300008347"
    ]
},
  "bbox": [],
  "geometry": {"coordinates":[-95.75,18.05],"type":"Point"}
}
=======
{"geometry":{"type":"Point","coordinates":[-95.750000,18.050000]},"type":"Feature","properties":{"hierarchy":["tgn:7352767","tgn:1000001","tgn:7005599","tgn:7005560","tgn:7029392"],"placetype":["aat:300008347"],"id":7352767,"name:xx":"Buenavista"}}
>>>>>>> 03f74aca74312dbeaf24d7e61306dd6a786dc3d0
