{
  "id": 7352767,
  "type": "Feature",
  "properties": {
    "tgn:hierarchy":[
        "tgn:7352767",
        "tgn:1000001",
        "tgn:7005599",
        "tgn:7005560",
        "tgn:7029392"
    ],
    "tgn:id":7352767,
    "tgn:name":"Buenavista",
    "tgn:placetype":[
        "aat:300008347"
    ]
},
  "bbox": [],
  "geometry": {"coordinates":[-95.75,18.05],"type":"Point"}
}