{
  "id": 2011056,
  "type": "Feature",
  "properties": {
    "tgn:hierarchy":[
        "tgn:2011056",
        "tgn:1000001",
        "tgn:7012149",
        "tgn:7007157",
        "tgn:1002858",
        "tgn:7029392"
    ],
    "tgn:id":2011056,
    "tgn:name":"Division",
    "tgn:placetype":[
        "aat:300387016"
    ]
},
  "bbox": [],
  "geometry": {"coordinates":[-116.5333,32.5833],"type":"Point"}
}