<<<<<<< HEAD
{
  "id": 7023335,
  "type": "Feature",
  "properties": {
    "tgn:hierarchy":[
        "tgn:7023335",
        "tgn:1000001",
        "tgn:7012149",
        "tgn:7029392"
    ],
    "tgn:id":7023335,
    "tgn:name":"South Branch Naaman Creek",
    "tgn:placetype":[
        "aat:300008706"
    ]
},
  "bbox": [],
  "geometry": {"coordinates":[-75.5,39.8333],"type":"Point"}
}
=======
{"geometry":{"type":"Point","coordinates":[-75.500000,39.833300]},"type":"Feature","properties":{"hierarchy":["tgn:7023335","tgn:1000001","tgn:7012149","tgn:7029392"],"placetype":["aat:300008706"],"id":7023335,"name:xx":"South Branch Naaman Creek"}}
>>>>>>> 03f74aca74312dbeaf24d7e61306dd6a786dc3d0
