{
  "id": 7277744,
  "type": "Feature",
  "properties": {
    "tgn:hierarchy":[
        "tgn:7277744",
        "tgn:1001768",
        "tgn:1000049",
        "tgn:1000002",
        "tgn:7029392"
    ],
    "tgn:id":7277744,
    "tgn:name":"Muelle Sopesa",
    "tgn:placetype":[
        "aat:300120779"
    ]
},
  "bbox": [],
  "geometry": {"coordinates":[-71.618611,-33.591667],"type":"Point"}
}