{
  "id": 7561313,
  "type": "Feature",
  "properties": {
    "tgn:hierarchy":[
        "tgn:7561313",
        "tgn:1000004",
        "tgn:7000198",
        "tgn:7016722",
        "tgn:7029392"
    ],
    "tgn:id":7561313,
    "tgn:name:en":"Behta L\u0101khi",
    "tgn:placetype":[
        "aat:300008347"
    ]
},
  "bbox": [],
  "geometry": {"coordinates":[79.786,27.2361],"type":"Point"}
}