<<<<<<< HEAD
{
  "id": 7471970,
  "type": "Feature",
  "properties": {
    "tgn:hierarchy":[
        "tgn:7471970",
        "tgn:7001010",
        "tgn:1000004",
        "tgn:1000141",
        "tgn:7029392"
    ],
    "tgn:id":7471970,
    "tgn:name":"Xiulin Guoxiao",
    "tgn:placetype":[
        "aat:300006495"
    ]
},
  "bbox": [],
  "geometry": {"coordinates":[121.624438,24.117546],"type":"Point"}
}
=======
{"geometry":{"type":"Point","coordinates":[121.624438,24.117546]},"type":"Feature","properties":{"hierarchy":["tgn:7471970","tgn:7001010","tgn:1000004","tgn:1000141","tgn:7029392"],"placetype":["aat:300006495"],"id":7471970,"name:xx":"Xiulin Guoxiao"}}
>>>>>>> 03f74aca74312dbeaf24d7e61306dd6a786dc3d0
