{
  "id": 1124417,
  "type": "Feature",
  "properties": {
    "tgn:hierarchy":[
        "tgn:1124417",
        "tgn:1000001",
        "tgn:7012149",
        "tgn:7007157",
        "tgn:7014475",
        "tgn:7029392"
    ],
    "tgn:id":1124417,
    "tgn:name":"Guadalupe",
    "tgn:placetype":[
        "aat:300008707"
    ]
},
  "bbox": [],
  "geometry": {"coordinates":[-121.8667,37.2333],"type":"Point"}
}