<<<<<<< HEAD
{
  "id": 2257455,
  "type": "Feature",
  "properties": {
    "tgn:hierarchy":[
        "tgn:2257455",
        "tgn:7002659",
        "tgn:1000001",
        "tgn:7012149",
        "tgn:2000063",
        "tgn:7029392"
    ],
    "tgn:id":2257455,
    "tgn:name":"Corona Number 20 Mine",
    "tgn:placetype":[
        "aat:300000390"
    ]
},
  "bbox": [],
  "geometry": {"coordinates":[-87.5,33.7],"type":"Point"}
}
=======
{"geometry":{"type":"Point","coordinates":[-87.500000,33.700000]},"type":"Feature","properties":{"hierarchy":["tgn:2257455","tgn:7002659","tgn:1000001","tgn:7012149","tgn:2000063","tgn:7029392"],"placetype":["aat:300000390"],"id":2257455,"name:xx":"Corona Number 20 Mine"}}
>>>>>>> 03f74aca74312dbeaf24d7e61306dd6a786dc3d0
