{
  "id": 7581817,
  "type": "Feature",
  "properties": {
    "tgn:hierarchy":[
        "tgn:7581817",
        "tgn:1000004",
        "tgn:1001869",
        "tgn:7000198",
        "tgn:7029392"
    ],
    "tgn:id":7581817,
    "tgn:name:en":"Singwada River",
    "tgn:placetype":[
        "aat:300008699"
    ]
},
  "bbox": [],
  "geometry": {"coordinates":[70.671667,20.756944],"type":"Point"}
}