{
  "id": 7232959,
  "type": "Feature",
  "properties": {
    "tgn:hierarchy":[
        "tgn:7232959",
        "tgn:7002748",
        "tgn:7001399",
        "tgn:1000003",
        "tgn:1000074",
        "tgn:7029392"
    ],
    "tgn:id":7232959,
    "tgn:name":"Loutr\u00e1 Ka\u1e2ftsis",
    "tgn:placetype":[
        "aat:300008347"
    ]
},
  "bbox": [],
  "geometry": {"coordinates":[22.15,39.133333],"type":"Point"}
}