{
  "id": 7178510,
  "type": "Feature",
  "properties": {
    "tgn:hierarchy":[
        "tgn:7178510",
        "tgn:7003669",
        "tgn:1000003",
        "tgn:7000084",
        "tgn:7029392"
    ],
    "tgn:id":7178510,
    "tgn:name":"Haimelkofen",
    "tgn:placetype":[
        "aat:300008347"
    ]
},
  "bbox": [],
  "geometry": {"coordinates":[12.316667,48.75],"type":"Point"}
}