{
  "id": 2302324,
  "type": "Feature",
  "properties": {
    "tgn:hierarchy":[
        "tgn:2302324",
        "tgn:2000453",
        "tgn:1000001",
        "tgn:7012149",
        "tgn:7007250",
        "tgn:7029392"
    ],
    "tgn:id":2302324,
    "tgn:name":"Dutch Oven Gulch",
    "tgn:placetype":[
        "aat:300008761"
    ]
},
  "bbox": [],
  "geometry": {"coordinates":[-116.35,44.65],"type":"Point"}
}