{
  "id": 1019809,
  "type": "Feature",
  "properties": {
    "tgn:hierarchy":[
        "tgn:1019809",
        "tgn:1001160",
        "tgn:7006477",
        "tgn:1000002",
        "tgn:7029392"
    ],
    "tgn:id":1019809,
    "tgn:name":"Olavarr\u00eda",
    "tgn:placetype":[
        "aat:300008347",
        "aat:300008375"
    ]
},
  "bbox": [],
  "geometry": {"coordinates":[-60.3333,-36.95],"type":"Point"}
}