<<<<<<< HEAD
{
  "id": 7055822,
  "type": "Feature",
  "properties": {
    "tgn:hierarchy":[
        "tgn:7055822",
        "tgn:1001730",
        "tgn:1000003",
        "tgn:7003121",
        "tgn:1000080",
        "tgn:7029392"
    ],
    "tgn:id":7055822,
    "tgn:name":"Planu, Riu",
    "tgn:placetype":[
        "aat:300008699"
    ]
},
  "bbox": [],
  "geometry": {"coordinates":[8.783333,40.0],"type":"Point"}
}
=======
{"geometry":{"type":"Point","coordinates":[8.783333,40.000000]},"type":"Feature","properties":{"hierarchy":["tgn:7055822","tgn:1001730","tgn:1000003","tgn:7003121","tgn:1000080","tgn:7029392"],"placetype":["aat:300008699"],"id":7055822,"name:xx":"Planu, Riu"}}
>>>>>>> 03f74aca74312dbeaf24d7e61306dd6a786dc3d0
