{
  "id": 2372151,
  "type": "Feature",
  "properties": {
    "tgn:hierarchy":[
        "tgn:2372151",
        "tgn:1000001",
        "tgn:1002479",
        "tgn:7012149",
        "tgn:7007240",
        "tgn:7029392"
    ],
    "tgn:id":2372151,
    "tgn:name":"Halfmoon Lake",
    "tgn:placetype":[
        "aat:300008680"
    ]
},
  "bbox": [],
  "geometry": {"coordinates":[-82.5333,28.0833],"type":"Point"}
}