{
  "id": 2181061,
  "type": "Feature",
  "properties": {
    "tgn:hierarchy":[
        "tgn:2181061",
        "tgn:1000001",
        "tgn:7006451",
        "tgn:7012149",
        "tgn:2000103",
        "tgn:7029392"
    ],
    "tgn:id":2181061,
    "tgn:name":"Blue Bell Tank Number Two",
    "tgn:placetype":[
        "aat:300006191"
    ]
},
  "bbox": [],
  "geometry": {"coordinates":[-112.2167,34.3333],"type":"Point"}
}