{
  "id": 2524498,
  "type": "Feature",
  "properties": {
    "tgn:hierarchy":[
        "tgn:2524498",
        "tgn:1000001",
        "tgn:1002278",
        "tgn:7012149",
        "tgn:7007710",
        "tgn:7029392"
    ],
    "tgn:id":2524498,
    "tgn:name":"Morgans Land",
    "tgn:placetype":[
        "aat:300008347"
    ]
},
  "bbox": [],
  "geometry": {"coordinates":[-78.5333,40.8167],"type":"Point"}
}