<<<<<<< HEAD
{
  "id": 2761022,
  "type": "Feature",
  "properties": {
    "tgn:hierarchy":[
        "tgn:2761022",
        "tgn:1000001",
        "tgn:7012149",
        "tgn:2002375",
        "tgn:7007923",
        "tgn:7029392"
    ],
    "tgn:id":2761022,
    "tgn:name":"West Kellehan Creek",
    "tgn:placetype":[
        "aat:300008706"
    ]
},
  "bbox": [],
  "geometry": {"coordinates":[-104.2,41.45],"type":"Point"}
}
=======
{"geometry":{"type":"Point","coordinates":[-104.200000,41.450000]},"type":"Feature","properties":{"hierarchy":["tgn:2761022","tgn:1000001","tgn:7012149","tgn:2002375","tgn:7007923","tgn:7029392"],"placetype":["aat:300008706"],"id":2761022,"name:xx":"West Kellehan Creek"}}
>>>>>>> 03f74aca74312dbeaf24d7e61306dd6a786dc3d0
