{
  "id": 2505041,
  "type": "Feature",
  "properties": {
    "tgn:hierarchy":[
        "tgn:2505041",
        "tgn:1000001",
        "tgn:7012149",
        "tgn:1002961",
        "tgn:7007568",
        "tgn:7029392"
    ],
    "tgn:id":2505041,
    "tgn:name":"Meenahga, Mount",
    "tgn:placetype":[
        "aat:300008798"
    ]
},
  "bbox": [],
  "geometry": {"coordinates":[-74.3667,41.6833],"type":"Point"}
}