{
  "id": 1128920,
  "type": "Feature",
  "properties": {
    "tgn:hierarchy":[
        "tgn:1128920",
        "tgn:7002641",
        "tgn:1000002",
        "tgn:1000058",
        "tgn:7029392"
    ],
    "tgn:id":1128920,
    "tgn:name":"R\u00edo Queguay Grande",
    "tgn:placetype":[
        "aat:300008707"
    ]
},
  "bbox": [],
  "geometry": {"coordinates":[-58.15,-32.15],"type":"Point"}
}