<<<<<<< HEAD
{
  "id": 7240668,
  "type": "Feature",
  "properties": {
    "tgn:hierarchy":[
        "tgn:7240668",
        "tgn:7003460",
        "tgn:1000003",
        "tgn:1000063",
        "tgn:4012014",
        "tgn:7029392"
    ],
    "tgn:id":7240668,
    "tgn:name":"Fays",
    "tgn:placetype":[
        "aat:300008347"
    ]
},
  "bbox": [],
  "geometry": {"coordinates":[5.866667,50.55],"type":"Point"}
}
=======
{"geometry":{"type":"Point","coordinates":[5.866667,50.550000]},"type":"Feature","properties":{"hierarchy":["tgn:7240668","tgn:7003460","tgn:1000003","tgn:1000063","tgn:4012014","tgn:7029392"],"placetype":["aat:300008347"],"id":7240668,"name:xx":"Fays"}}
>>>>>>> 03f74aca74312dbeaf24d7e61306dd6a786dc3d0
