{
  "id": 7523502,
  "type": "Feature",
  "properties": {
    "tgn:hierarchy":[
        "tgn:7523502",
        "tgn:7001242",
        "tgn:1001075",
        "tgn:7016833",
        "tgn:7029392"
    ],
    "tgn:id":7523502,
    "tgn:name:en":"Bas\u0163arah",
    "tgn:placetype":[
        "aat:300008347"
    ]
},
  "bbox": [],
  "geometry": {"coordinates":[30.424232,31.076711],"type":"Point"}
}