{
  "id": 2023788,
  "type": "Feature",
  "properties": {
    "tgn:hierarchy":[
        "tgn:2023788",
        "tgn:1000001",
        "tgn:7012149",
        "tgn:2000432",
        "tgn:7007248",
        "tgn:7029392"
    ],
    "tgn:id":2023788,
    "tgn:name":"Oak Grove",
    "tgn:placetype":[
        "aat:300008347",
        "aat:300387210"
    ]
},
  "bbox": [],
  "geometry": {"coordinates":[-84.8667,32.8833],"type":"Point"}
}