{
  "id": 7277120,
  "type": "Feature",
  "properties": {
    "tgn:hierarchy":[
        "tgn:7277120",
        "tgn:1001699",
        "tgn:1000049",
        "tgn:1000002",
        "tgn:7029392"
    ],
    "tgn:id":7277120,
    "tgn:name":"Yeli, R\u00edo",
    "tgn:placetype":[
        "aat:300008699"
    ]
},
  "bbox": [],
  "geometry": {"coordinates":[-73.044722,-43.517778],"type":"Point"}
}