{
  "id": 7502734,
  "type": "Feature",
  "properties": {
    "tgn:hierarchy":[
        "tgn:7502734",
        "tgn:1000004",
        "tgn:7471332",
        "tgn:1000141",
        "tgn:7029392"
    ],
    "tgn:id":7502734,
    "tgn:name":"Wufeng Guozhong",
    "tgn:placetype":[
        "aat:300006495"
    ]
},
  "bbox": [],
  "geometry": {"coordinates":[121.117778,24.6325],"type":"Point"}
}