{
  "id": 7486750,
  "type": "Feature",
  "properties": {
    "tgn:hierarchy":[
        "tgn:7486750",
        "tgn:1000004",
        "tgn:7489179",
        "tgn:1000141",
        "tgn:7029392"
    ],
    "tgn:id":7486750,
    "tgn:name":"Gangziqian",
    "tgn:placetype":[
        "aat:300008347"
    ]
},
  "bbox": [],
  "geometry": {"coordinates":[121.803889,24.833611],"type":"Point"}
}