{
  "id": 2338881,
  "type": "Feature",
  "properties": {
    "tgn:hierarchy":[
        "tgn:2338881",
        "tgn:1000001",
        "tgn:7012149",
        "tgn:7007157",
        "tgn:1002857",
        "tgn:7029392"
    ],
    "tgn:id":2338881,
    "tgn:name":"Frankish Canyon",
    "tgn:placetype":[
        "aat:300008761"
    ]
},
  "bbox": [],
  "geometry": {"coordinates":[-117.65,34.1667],"type":"Point"}
}