{
  "id": 2622563,
  "type": "Feature",
  "properties": {
    "tgn:hierarchy":[
        "tgn:2622563",
        "tgn:2002138",
        "tgn:1000001",
        "tgn:7012149",
        "tgn:7007919",
        "tgn:7029392"
    ],
    "tgn:id":2622563,
    "tgn:name":"Robinson Branch",
    "tgn:placetype":[
        "aat:300008699"
    ]
},
  "bbox": [],
  "geometry": {"coordinates":[-80.1667,37.65],"type":"Point"}
}