<<<<<<< HEAD
{
  "id": 2156086,
  "type": "Feature",
  "properties": {
    "tgn:hierarchy":[
        "tgn:2156086",
        "tgn:1000001",
        "tgn:7012149",
        "tgn:2002287",
        "tgn:7013961",
        "tgn:7029392"
    ],
    "tgn:id":2156086,
    "tgn:name":"Beard",
    "tgn:placetype":[
        "aat:300008347"
    ]
},
  "bbox": [],
  "geometry": {"coordinates":[-80.2167,38.0667],"type":"Point"}
}
=======
{"geometry":{"type":"Point","coordinates":[-80.216700,38.066700]},"type":"Feature","properties":{"hierarchy":["tgn:2156086","tgn:1000001","tgn:7012149","tgn:2002287","tgn:7013961","tgn:7029392"],"placetype":["aat:300008347"],"id":2156086,"name:xx":"Beard"}}
>>>>>>> 03f74aca74312dbeaf24d7e61306dd6a786dc3d0
