{
  "id": 7556600,
  "type": "Feature",
  "properties": {
    "tgn:hierarchy":[
        "tgn:7556600",
        "tgn:1000004",
        "tgn:7000198",
        "tgn:7016883",
        "tgn:7029392"
    ],
    "tgn:id":7556600,
    "tgn:name:en":"Sekhw\u0101n",
    "tgn:placetype":[
        "aat:300008347"
    ]
},
  "bbox": [],
  "geometry": {"coordinates":[75.319693,31.85135],"type":"Point"}
}