<<<<<<< HEAD
{
  "id": 7366590,
  "type": "Feature",
  "properties": {
    "tgn:hierarchy":[
        "tgn:7366590",
        "tgn:7005581",
        "tgn:1000001",
        "tgn:7005560",
        "tgn:7029392"
    ],
    "tgn:id":7366590,
    "tgn:name":"El Ri\u00edto, Arroyo",
    "tgn:placetype":[
        "aat:300008699"
    ]
},
  "bbox": [],
  "geometry": {"coordinates":[-106.65,26.4],"type":"Point"}
}
=======
{"geometry":{"type":"Point","coordinates":[-106.650000,26.400000]},"type":"Feature","properties":{"hierarchy":["tgn:7366590","tgn:7005581","tgn:1000001","tgn:7005560","tgn:7029392"],"placetype":["aat:300008699"],"id":7366590,"name:xx":"El Ri\u00edto, Arroyo"}}
>>>>>>> 03f74aca74312dbeaf24d7e61306dd6a786dc3d0
