{
  "id": 7252610,
  "type": "Feature",
  "properties": {
    "tgn:hierarchy":[
        "tgn:7252610",
        "tgn:7003457",
        "tgn:1000003",
        "tgn:1000063",
        "tgn:7018236",
        "tgn:7029392"
    ],
    "tgn:id":7252610,
    "tgn:name":"Sint-Goriks-Oudenhove",
    "tgn:placetype":[
        "aat:300008347"
    ]
},
  "bbox": [],
  "geometry": {"coordinates":[3.786118,50.852785],"type":"Point"}
}