{
  "id": 7558656,
  "type": "Feature",
  "properties": {
    "tgn:hierarchy":[
        "tgn:7558656",
        "tgn:1000004",
        "tgn:7000198",
        "tgn:1001895",
        "tgn:7029392"
    ],
    "tgn:id":7558656,
    "tgn:name:en":"S\u0101oli",
    "tgn:placetype":[
        "aat:300008347"
    ]
},
  "bbox": [],
  "geometry": {"coordinates":[79.783333,20.083333],"type":"Point"}
}