{
  "id": 7569845,
  "type": "Feature",
  "properties": {
    "tgn:hierarchy":[
        "tgn:7569845",
        "tgn:1000004",
        "tgn:7000198",
        "tgn:1001895",
        "tgn:7029392"
    ],
    "tgn:id":7569845,
    "tgn:name:en":"V\u0101ghrankh\u0101r",
    "tgn:placetype":[
        "aat:300008347"
    ]
},
  "bbox": [],
  "geometry": {"coordinates":[72.951389,18.73],"type":"Point"}
}