<<<<<<< HEAD
{
  "id": 7367534,
  "type": "Feature",
  "properties": {
    "tgn:hierarchy":[
        "tgn:7367534",
        "tgn:1000001",
        "tgn:7005597",
        "tgn:7005560",
        "tgn:7029392"
    ],
    "tgn:id":7367534,
    "tgn:name":"El Valle de los Ebanos",
    "tgn:placetype":[
        "aat:300008347"
    ]
},
  "bbox": [],
  "geometry": {"coordinates":[-98.283333,23.633333],"type":"Point"}
}
=======
{"geometry":{"type":"Point","coordinates":[-98.283333,23.633333]},"type":"Feature","properties":{"hierarchy":["tgn:7367534","tgn:1000001","tgn:7005597","tgn:7005560","tgn:7029392"],"placetype":["aat:300008347"],"id":7367534,"name:xx":"El Valle de los Ebanos"}}
>>>>>>> 03f74aca74312dbeaf24d7e61306dd6a786dc3d0
