{
  "id": 7372146,
  "type": "Feature",
  "properties": {
    "tgn:hierarchy":[
        "tgn:7372146",
        "tgn:1000001",
        "tgn:7005597",
        "tgn:7005560",
        "tgn:7029392"
    ],
    "tgn:id":7372146,
    "tgn:name":"La Esperanza",
    "tgn:placetype":[
        "aat:300008347"
    ]
},
  "bbox": [],
  "geometry": {"coordinates":[-99.316667,23.95],"type":"Point"}
}