{
  "id": 2313694,
  "type": "Feature",
  "properties": {
    "tgn:hierarchy":[
        "tgn:2313694",
        "tgn:1000001",
        "tgn:7012149",
        "tgn:2000237",
        "tgn:7007158",
        "tgn:7029392"
    ],
    "tgn:id":2313694,
    "tgn:name":"Elephant Reservoir",
    "tgn:placetype":[
        "aat:300006191"
    ]
},
  "bbox": [],
  "geometry": {"coordinates":[-107.8167,38.1833],"type":"Point"}
}