{
  "id": 7248886,
  "type": "Feature",
  "properties": {
    "tgn:hierarchy":[
        "tgn:7248886",
        "tgn:7007877",
        "tgn:1000003",
        "tgn:1000063",
        "tgn:4012014",
        "tgn:7029392"
    ],
    "tgn:id":7248886,
    "tgn:name":"Bois-de-Lessines",
    "tgn:placetype":[
        "aat:300008347"
    ]
},
  "bbox": [],
  "geometry": {"coordinates":[3.896133,50.696621],"type":"Point"}
}