<<<<<<< HEAD
{
  "id": 7365314,
  "type": "Feature",
  "properties": {
    "tgn:hierarchy":[
        "tgn:7365314",
        "tgn:7005578",
        "tgn:1000001",
        "tgn:7005560",
        "tgn:7029392"
    ],
    "tgn:id":7365314,
    "tgn:name":"El S\u00fachil",
    "tgn:placetype":[
        "aat:300008347"
    ]
},
  "bbox": [],
  "geometry": {"coordinates":[-91.033333,18.333333],"type":"Point"}
}
=======
{"geometry":{"type":"Point","coordinates":[-91.033333,18.333333]},"type":"Feature","properties":{"hierarchy":["tgn:7365314","tgn:7005578","tgn:1000001","tgn:7005560","tgn:7029392"],"placetype":["aat:300008347"],"id":7365314,"name:xx":"El S\u00fachil"}}
>>>>>>> 03f74aca74312dbeaf24d7e61306dd6a786dc3d0
