<<<<<<< HEAD
{
  "id": 7051405,
  "type": "Feature",
  "properties": {
    "tgn:hierarchy":[
        "tgn:7051405",
        "tgn:1003478",
        "tgn:1000003",
        "tgn:7003120",
        "tgn:1000080",
        "tgn:7029392"
    ],
    "tgn:id":7051405,
    "tgn:name":"La Colla",
    "tgn:placetype":[
        "aat:300008347"
    ]
},
  "bbox": [],
  "geometry": {"coordinates":[8.5,46.166667],"type":"Point"}
}
=======
{"geometry":{"type":"Point","coordinates":[8.500000,46.166667]},"type":"Feature","properties":{"hierarchy":["tgn:7051405","tgn:1003478","tgn:1000003","tgn:7003120","tgn:1000080","tgn:7029392"],"placetype":["aat:300008347"],"id":7051405,"name:xx":"La Colla"}}
>>>>>>> 03f74aca74312dbeaf24d7e61306dd6a786dc3d0
