{
  "id": 7314489,
  "type": "Feature",
  "properties": {
    "tgn:hierarchy":[
        "tgn:7314489",
        "tgn:1001692",
        "tgn:1000049",
        "tgn:1000002",
        "tgn:7029392"
    ],
    "tgn:id":7314489,
    "tgn:name":"Li\u00f1eco, Cerro",
    "tgn:placetype":[
        "aat:300008795"
    ]
},
  "bbox": [],
  "geometry": {"coordinates":[-73.033333,-38.133333],"type":"Point"}
}