{
  "id": 7495497,
  "type": "Feature",
  "properties": {
    "tgn:hierarchy":[
        "tgn:7495497",
        "tgn:7487020",
        "tgn:1000004",
        "tgn:1000141",
        "tgn:7029392"
    ],
    "tgn:id":7495497,
    "tgn:name":"Wenlin Guozhong Fenxiao",
    "tgn:placetype":[
        "aat:300006495"
    ]
},
  "bbox": [],
  "geometry": {"coordinates":[120.809514,24.429976],"type":"Point"}
}