{
  "id": 2538284,
  "type": "Feature",
  "properties": {
    "tgn:hierarchy":[
        "tgn:2538284",
        "tgn:1000001",
        "tgn:7012149",
        "tgn:2000355",
        "tgn:7007248",
        "tgn:7029392"
    ],
    "tgn:id":2538284,
    "tgn:name":"Nelson lake",
    "tgn:placetype":[
        "aat:300006191"
    ]
},
  "bbox": [],
  "geometry": {"coordinates":[-84.9667,34.45],"type":"Point"}
}