{
  "id": 1065497,
  "type": "Feature",
  "properties": {
    "tgn:hierarchy":[
        "tgn:1065497",
        "tgn:7016612",
        "tgn:1000004",
        "tgn:1001249",
        "tgn:7029392"
    ],
    "tgn:id":1065497,
    "tgn:name":"Do Qaleh",
    "tgn:placetype":[
        "aat:300008347"
    ]
},
  "bbox": [],
  "geometry": {"coordinates":[61.4333,32.1333],"type":"Point"}
}