{
  "id": 7221146,
  "type": "Feature",
  "properties": {
    "tgn:hierarchy":[
        "tgn:7221146",
        "tgn:7002715",
        "tgn:7002731",
        "tgn:1000003",
        "tgn:1000074",
        "tgn:7029392"
    ],
    "tgn:id":7221146,
    "tgn:name":"Sk\u00e1la Ne\u00f3n Epivat\u00f3n",
    "tgn:placetype":[
        "aat:300007928"
    ]
},
  "bbox": [],
  "geometry": {"coordinates":[22.907157,40.505235],"type":"Point"}
}