{
  "id": 2231523,
  "type": "Feature",
  "properties": {
    "tgn:hierarchy":[
        "tgn:2231523",
        "tgn:1000001",
        "tgn:7012149",
        "tgn:2001927",
        "tgn:7007825",
        "tgn:7029392"
    ],
    "tgn:id":2231523,
    "tgn:name":"Chalk Hollow",
    "tgn:placetype":[
        "aat:300008761"
    ]
},
  "bbox": [],
  "geometry": {"coordinates":[-87.85,35.3667],"type":"Point"}
}