<<<<<<< HEAD
{
  "id": 2400182,
  "type": "Feature",
  "properties": {
    "tgn:hierarchy":[
        "tgn:2400182",
        "tgn:1000001",
        "tgn:7012149",
        "tgn:1002263",
        "tgn:7007826",
        "tgn:7029392"
    ],
    "tgn:id":2400182,
    "tgn:name":"Horse Creek",
    "tgn:placetype":[
        "aat:300008706"
    ]
},
  "bbox": [],
  "geometry": {"coordinates":[-95.1167,31.8],"type":"Point"}
}
=======
{"geometry":{"type":"Point","coordinates":[-95.116700,31.800000]},"type":"Feature","properties":{"hierarchy":["tgn:2400182","tgn:1000001","tgn:7012149","tgn:1002263","tgn:7007826","tgn:7029392"],"placetype":["aat:300008706"],"id":2400182,"name:xx":"Horse Creek"}}
>>>>>>> 03f74aca74312dbeaf24d7e61306dd6a786dc3d0
