{
  "id": 2722488,
  "type": "Feature",
  "properties": {
    "tgn:hierarchy":[
        "tgn:2722488",
        "tgn:1000001",
        "tgn:7012149",
        "tgn:2000481",
        "tgn:7007250",
        "tgn:7029392"
    ],
    "tgn:id":2722488,
    "tgn:name":"Tincan Spring",
    "tgn:placetype":[
        "aat:300008697"
    ]
},
  "bbox": [],
  "geometry": {"coordinates":[-114.1333,45.55],"type":"Point"}
}