{
  "id": 7475584,
  "type": "Feature",
  "properties": {
    "tgn:hierarchy":[
        "tgn:7475584",
        "tgn:1000004",
        "tgn:7489179",
        "tgn:1000141",
        "tgn:7029392"
    ],
    "tgn:id":7475584,
    "tgn:name":"Yongchun Xinzhan",
    "tgn:placetype":[
        "aat:300007783"
    ]
},
  "bbox": [],
  "geometry": {"coordinates":[121.845375,24.574387],"type":"Point"}
}