{
  "id": 2681394,
  "type": "Feature",
  "properties": {
    "tgn:hierarchy":[
        "tgn:2681394",
        "tgn:1000001",
        "tgn:7012149",
        "tgn:2002371",
        "tgn:7007923",
        "tgn:7029392"
    ],
    "tgn:id":2681394,
    "tgn:name":"South Pocket",
    "tgn:placetype":[
        "aat:300008761"
    ]
},
  "bbox": [],
  "geometry": {"coordinates":[-109.7167,43.7667],"type":"Point"}
}