{
  "id": 2694569,
  "type": "Feature",
  "properties": {
    "tgn:hierarchy":[
        "tgn:2694569",
        "tgn:1000001",
        "tgn:7012149",
        "tgn:2001279",
        "tgn:7007524",
        "tgn:7029392"
    ],
    "tgn:id":2694569,
    "tgn:name":"Stewart Gulch",
    "tgn:placetype":[
        "aat:300008761"
    ]
},
  "bbox": [],
  "geometry": {"coordinates":[-113.2333,46.3333],"type":"Point"}
}