{
  "id": 2666407,
  "type": "Feature",
  "properties": {
    "tgn:hierarchy":[
        "tgn:2666407",
        "tgn:1000001",
        "tgn:7012149",
        "tgn:7020792",
        "tgn:7007524",
        "tgn:7029392"
    ],
    "tgn:id":2666407,
    "tgn:name":"Sixmile Creek",
    "tgn:placetype":[
        "aat:300008706"
    ]
},
  "bbox": [],
  "geometry": {"coordinates":[-113.0333,46.0333],"type":"Point"}
}