{
  "id": 1119282,
  "type": "Feature",
  "properties": {
    "tgn:hierarchy":[
        "tgn:1119282",
        "tgn:1002165",
        "tgn:1000001",
        "tgn:7012149",
        "tgn:7007517",
        "tgn:7029392"
    ],
    "tgn:id":1119282,
    "tgn:name":"Long Pond",
    "tgn:placetype":[
        "aat:300008688"
    ]
},
  "bbox": [],
  "geometry": {"coordinates":[-70.0667,41.7167],"type":"Point"}
}