{
  "id": 7064138,
  "type": "Feature",
  "properties": {
    "tgn:hierarchy":[
        "tgn:7064138",
        "tgn:7003669",
        "tgn:1000003",
        "tgn:7000084",
        "tgn:7029392"
    ],
    "tgn:id":7064138,
    "tgn:name":"Unterer Pielenhofener Wald",
    "tgn:placetype":[
        "aat:300008863"
    ]
},
  "bbox": [],
  "geometry": {"coordinates":[11.95,49.05],"type":"Point"}
}