{
  "id": 2440189,
  "type": "Feature",
  "properties": {
    "tgn:hierarchy":[
        "tgn:2440189",
        "tgn:1000001",
        "tgn:7012149",
        "tgn:1002599",
        "tgn:7007708",
        "tgn:7029392"
    ],
    "tgn:id":2440189,
    "tgn:name":"Klickitat Lake",
    "tgn:placetype":[
        "aat:300008680"
    ]
},
  "bbox": [],
  "geometry": {"coordinates":[-123.65,44.4667],"type":"Point"}
}