{
  "id": 2615176,
  "type": "Feature",
  "properties": {
    "tgn:hierarchy":[
        "tgn:2615176",
        "tgn:1000001",
        "tgn:7012149",
        "tgn:2000350",
        "tgn:7007248",
        "tgn:7029392"
    ],
    "tgn:id":2615176,
    "tgn:name":"Reservoir 33",
    "tgn:placetype":[
        "aat:300006191"
    ]
},
  "bbox": [],
  "geometry": {"coordinates":[-83.1833,34.4333],"type":"Point"}
}