{
  "id": 2188247,
  "type": "Feature",
  "properties": {
    "tgn:hierarchy":[
        "tgn:2188247",
        "tgn:1000001",
        "tgn:7012149",
        "tgn:2000215",
        "tgn:7007158",
        "tgn:7029392"
    ],
    "tgn:id":2188247,
    "tgn:name":"Boss Mine",
    "tgn:placetype":[
        "aat:300000390"
    ]
},
  "bbox": [],
  "geometry": {"coordinates":[-105.5167,39.8167],"type":"Point"}
}