{
  "id": 7221482,
  "type": "Feature",
  "properties": {
    "tgn:hierarchy":[
        "tgn:7221482",
        "tgn:7011164",
        "tgn:7002674",
        "tgn:1000003",
        "tgn:1000074",
        "tgn:7029392"
    ],
    "tgn:id":7221482,
    "tgn:name":"Vourli\u00f3ti R\u00e9ma",
    "tgn:placetype":[
        "aat:300008699"
    ]
},
  "bbox": [],
  "geometry": {"coordinates":[26.708056,37.708333],"type":"Point"}
}