{
  "id": 2728903,
  "type": "Feature",
  "properties": {
    "tgn:hierarchy":[
        "tgn:2728903",
        "tgn:1000001",
        "tgn:7006451",
        "tgn:2000095",
        "tgn:7012149",
        "tgn:7029392"
    ],
    "tgn:id":2728903,
    "tgn:name":"Triangle Seeps",
    "tgn:placetype":[
        "aat:300008697"
    ]
},
  "bbox": [],
  "geometry": {"coordinates":[-109.2833,33.65],"type":"Point"}
}