{
  "id": 2721784,
  "type": "Feature",
  "properties": {
    "tgn:hierarchy":[
        "tgn:2721784",
        "tgn:1000001",
        "tgn:7012149",
        "tgn:2001313",
        "tgn:7007524",
        "tgn:7029392"
    ],
    "tgn:id":2721784,
    "tgn:name":"Timber Creek",
    "tgn:placetype":[
        "aat:300008706"
    ]
},
  "bbox": [],
  "geometry": {"coordinates":[-109.7167,46.3167],"type":"Point"}
}