{
  "id": 7498537,
  "type": "Feature",
  "properties": {
    "tgn:hierarchy":[
        "tgn:7498537",
        "tgn:1000004",
        "tgn:7467799",
        "tgn:1000141",
        "tgn:7029392"
    ],
    "tgn:id":7498537,
    "tgn:name":"Zhongwei Qiao",
    "tgn:placetype":[
        "aat:300007836"
    ]
},
  "bbox": [],
  "geometry": {"coordinates":[120.529001,24.109193],"type":"Point"}
}