<<<<<<< HEAD
{
  "id": 2334671,
  "type": "Feature",
  "properties": {
    "tgn:hierarchy":[
        "tgn:2334671",
        "tgn:1000001",
        "tgn:7012149",
        "tgn:7007157",
        "tgn:1002956",
        "tgn:7029392"
    ],
    "tgn:id":2334671,
    "tgn:name":"Forgotten Canyon",
    "tgn:placetype":[
        "aat:300008761"
    ]
},
  "bbox": [],
  "geometry": {"coordinates":[-118.3333,36.45],"type":"Point"}
}
=======
{"geometry":{"type":"Point","coordinates":[-118.333300,36.450000]},"type":"Feature","properties":{"hierarchy":["tgn:2334671","tgn:1000001","tgn:7012149","tgn:7007157","tgn:1002956","tgn:7029392"],"placetype":["aat:300008761"],"id":2334671,"name:xx":"Forgotten Canyon"}}
>>>>>>> 03f74aca74312dbeaf24d7e61306dd6a786dc3d0
