{
  "id": 1088771,
  "type": "Feature",
  "properties": {
    "tgn:hierarchy":[
        "tgn:1088771",
        "tgn:1001143",
        "tgn:7001242",
        "tgn:1000159",
        "tgn:7029392"
    ],
    "tgn:id":1088771,
    "tgn:name":"Bagata",
    "tgn:placetype":[
        "aat:300008347"
    ]
},
  "bbox": [],
  "geometry": {"coordinates":[17.95,-3.7833],"type":"Point"}
}