{
  "id": 2646364,
  "type": "Feature",
  "properties": {
    "tgn:hierarchy":[
        "tgn:2646364",
        "tgn:1000001",
        "tgn:7012149",
        "tgn:1003026",
        "tgn:7007826",
        "tgn:7029392"
    ],
    "tgn:id":2646364,
    "tgn:name":"Sawyer Hollow",
    "tgn:placetype":[
        "aat:300008761"
    ]
},
  "bbox": [],
  "geometry": {"coordinates":[-97.7833,30.65],"type":"Point"}
}