{
  "id": 7369086,
  "type": "Feature",
  "properties": {
    "tgn:hierarchy":[
        "tgn:7369086",
        "tgn:1000001",
        "tgn:7005591",
        "tgn:7005560",
        "tgn:7029392"
    ],
    "tgn:id":7369086,
    "tgn:name:es":"Ixhuat\u00e1n",
    "tgn:placetype":[
        "aat:300008347"
    ]
},
  "bbox": [],
  "geometry": {"coordinates":[-94.4825,16.356944],"type":"Point"}
}