<<<<<<< HEAD
{
  "id": 7369086,
  "type": "Feature",
  "properties": {
    "tgn:hierarchy":[
        "tgn:7369086",
        "tgn:1000001",
        "tgn:7005591",
        "tgn:7005560",
        "tgn:7029392"
    ],
    "tgn:id":7369086,
    "tgn:name:es":"Ixhuat\u00e1n",
    "tgn:placetype":[
        "aat:300008347"
    ]
},
  "bbox": [],
  "geometry": {"coordinates":[-94.4825,16.356944],"type":"Point"}
}
=======
{"geometry":{"type":"Point","coordinates":[-94.482500,16.356944]},"type":"Feature","properties":{"hierarchy":["tgn:7369086","tgn:1000001","tgn:7005591","tgn:7005560","tgn:7029392"],"placetype":["aat:300008347"],"id":7369086,"name:es":"Ixhuat\u00e1n"}}
>>>>>>> 03f74aca74312dbeaf24d7e61306dd6a786dc3d0
