{
  "id": 7578698,
  "type": "Feature",
  "properties": {
    "tgn:hierarchy":[
        "tgn:7578698",
        "tgn:1000004",
        "tgn:1001869",
        "tgn:7000198",
        "tgn:7029392"
    ],
    "tgn:id":7578698,
    "tgn:name:en":"Wagh\u0101i",
    "tgn:placetype":[
        "aat:300008347"
    ]
},
  "bbox": [],
  "geometry": {"coordinates":[73.483333,20.766667],"type":"Point"}
}