{
  "id": 1135757,
  "type": "Feature",
  "properties": {
    "tgn:hierarchy":[
        "tgn:1135757",
        "tgn:7001242",
        "tgn:1001943",
        "tgn:1000182",
        "tgn:7029392"
    ],
    "tgn:id":1135757,
    "tgn:name":"Bonny",
    "tgn:placetype":[
        "aat:300387055"
    ]
},
  "bbox": [],
  "geometry": {"coordinates":[7.1667,4.3333],"type":"Point"}
}