{
  "id": 2410335,
  "type": "Feature",
  "properties": {
    "tgn:hierarchy":[
        "tgn:2410335",
        "tgn:1000001",
        "tgn:2000499",
        "tgn:7012149",
        "tgn:7007251",
        "tgn:7029392"
    ],
    "tgn:id":2410335,
    "tgn:name":"Indian Branch",
    "tgn:placetype":[
        "aat:300008699"
    ]
},
  "bbox": [],
  "geometry": {"coordinates":[-87.7333,39.2833],"type":"Point"}
}