{
  "id": 2005149,
  "type": "Feature",
  "properties": {
    "tgn:hierarchy":[
        "tgn:2005149",
        "tgn:7002659",
        "tgn:1000001",
        "tgn:7012149",
        "tgn:2000065",
        "tgn:7029392"
    ],
    "tgn:id":2005149,
    "tgn:name":"Rosebud",
    "tgn:placetype":[
        "aat:300008347"
    ]
},
  "bbox": [],
  "geometry": {"coordinates":[-87.1333,31.9333],"type":"Point"}
}