{
  "id": 2243822,
  "type": "Feature",
  "properties": {
    "tgn:hierarchy":[
        "tgn:2243822",
        "tgn:1000001",
        "tgn:2001792",
        "tgn:7012149",
        "tgn:7007713",
        "tgn:7029392"
    ],
    "tgn:id":2243822,
    "tgn:name":"Cleveland Dam",
    "tgn:placetype":[
        "aat:300006191"
    ]
},
  "bbox": [],
  "geometry": {"coordinates":[-99.15,45.3667],"type":"Point"}
}