{
  "id": 2600090,
  "type": "Feature",
  "properties": {
    "tgn:hierarchy":[
        "tgn:2600090",
        "tgn:1000001",
        "tgn:7012149",
        "tgn:2001843",
        "tgn:7007825",
        "tgn:7029392"
    ],
    "tgn:id":2600090,
    "tgn:name":"Pryor Meredith Branch",
    "tgn:placetype":[
        "aat:300008699"
    ]
},
  "bbox": [],
  "geometry": {"coordinates":[-84.2333,36.45],"type":"Point"}
}