{
  "id": 1086827,
  "type": "Feature",
  "properties": {
    "tgn:hierarchy":[
        "tgn:1086827",
        "tgn:1001586",
        "tgn:1000004",
        "tgn:7018456",
        "tgn:1000144",
        "tgn:7029392"
    ],
    "tgn:id":1086827,
    "tgn:name":"Siverek",
    "tgn:placetype":[
        "aat:300008347"
    ]
},
  "bbox": [],
  "geometry": {"coordinates":[39.3167,37.75],"type":"Point"}
}