<<<<<<< HEAD
{
  "id": 2339696,
  "type": "Feature",
  "properties": {
    "tgn:hierarchy":[
        "tgn:2339696",
        "tgn:1000001",
        "tgn:7012149",
        "tgn:1003004",
        "tgn:7007252",
        "tgn:7029392"
    ],
    "tgn:id":2339696,
    "tgn:name":"Free Run",
    "tgn:placetype":[
        "aat:300008699"
    ]
},
  "bbox": [],
  "geometry": {"coordinates":[-85.0167,39.8333],"type":"Point"}
}
=======
{"geometry":{"type":"Point","coordinates":[-85.016700,39.833300]},"type":"Feature","properties":{"hierarchy":["tgn:2339696","tgn:1000001","tgn:7012149","tgn:1003004","tgn:7007252","tgn:7029392"],"placetype":["aat:300008699"],"id":2339696,"name:xx":"Free Run"}}
>>>>>>> 03f74aca74312dbeaf24d7e61306dd6a786dc3d0
