{
  "id": 2149509,
  "type": "Feature",
  "properties": {
    "tgn:hierarchy":[
        "tgn:2149509",
        "tgn:1000001",
        "tgn:7012149",
        "tgn:2001073",
        "tgn:7007521",
        "tgn:7029392"
    ],
    "tgn:id":2149509,
    "tgn:name":"Barrett Lake",
    "tgn:placetype":[
        "aat:300008680"
    ]
},
  "bbox": [],
  "geometry": {"coordinates":[-96.0667,45.7333],"type":"Point"}
}