<<<<<<< HEAD
{
  "id": 7026625,
  "type": "Feature",
  "properties": {
    "tgn:hierarchy":[
        "tgn:7026625",
        "tgn:7002445",
        "tgn:1000003",
        "tgn:7008132",
        "tgn:7008591",
        "tgn:7029392"
    ],
    "tgn:id":7026625,
    "tgn:name":"Elmstone Hardwicke",
    "tgn:placetype":[
        "aat:300008347",
        "aat:300008372"
    ]
},
  "bbox": [],
  "geometry": {"coordinates":[-2.1167,51.9333],"type":"Point"}
}
=======
{"geometry":{"type":"Point","coordinates":[-2.116700,51.933300]},"type":"Feature","properties":{"hierarchy":["tgn:7026625","tgn:7002445","tgn:1000003","tgn:7008132","tgn:7008591","tgn:7029392"],"placetype":["aat:300008347","aat:300008372"],"id":7026625,"name:xx":"Elmstone Hardwicke"}}
>>>>>>> 03f74aca74312dbeaf24d7e61306dd6a786dc3d0
