{
  "id": 2554986,
  "type": "Feature",
  "properties": {
    "tgn:hierarchy":[
        "tgn:2554986",
        "tgn:1000001",
        "tgn:7012149",
        "tgn:1002920",
        "tgn:7007568",
        "tgn:7029392"
    ],
    "tgn:id":2554986,
    "tgn:name":"Obes Glen",
    "tgn:placetype":[
        "aat:300008761"
    ]
},
  "bbox": [],
  "geometry": {"coordinates":[-77.5667,42.2833],"type":"Point"}
}