{
  "id": 2133154,
  "type": "Feature",
  "properties": {
    "tgn:hierarchy":[
        "tgn:2133154",
        "tgn:1000001",
        "tgn:7012149",
        "tgn:7016022",
        "tgn:7007251",
        "tgn:7029392"
    ],
    "tgn:id":2133154,
    "tgn:name":"Anderson Lake",
    "tgn:placetype":[
        "aat:300006191"
    ]
},
  "bbox": [],
  "geometry": {"coordinates":[-89.9333,38.5333],"type":"Point"}
}