{
  "id": 7202102,
  "type": "Feature",
  "properties": {
    "tgn:hierarchy":[
        "tgn:7202102",
        "tgn:1000003",
        "tgn:7003677",
        "tgn:7000084",
        "tgn:7029392"
    ],
    "tgn:id":7202102,
    "tgn:name":"Bramsche Bach",
    "tgn:placetype":[
        "aat:300008699"
    ]
},
  "bbox": [],
  "geometry": {"coordinates":[8.666667,52.166667],"type":"Point"}
}