{
  "id": 7158648,
  "type": "Feature",
  "properties": {
    "tgn:hierarchy":[
        "tgn:7158648",
        "tgn:7003692",
        "tgn:1000003",
        "tgn:7000084",
        "tgn:7029392"
    ],
    "tgn:id":7158648,
    "tgn:name":"H\u00f6llenhof",
    "tgn:placetype":[
        "aat:300000206"
    ]
},
  "bbox": [],
  "geometry": {"coordinates":[8.066667,48.433333],"type":"Point"}
}