<<<<<<< HEAD
{
  "id": 7367098,
  "type": "Feature",
  "properties": {
    "tgn:hierarchy":[
        "tgn:7367098",
        "tgn:1000001",
        "tgn:7005599",
        "tgn:7005560",
        "tgn:7029392"
    ],
    "tgn:id":7367098,
    "tgn:name":"El Triste",
    "tgn:placetype":[
        "aat:300008347"
    ]
},
  "bbox": [],
  "geometry": {"coordinates":[-97.6,20.3],"type":"Point"}
}
=======
{"geometry":{"type":"Point","coordinates":[-97.600000,20.300000]},"type":"Feature","properties":{"hierarchy":["tgn:7367098","tgn:1000001","tgn:7005599","tgn:7005560","tgn:7029392"],"placetype":["aat:300008347"],"id":7367098,"name:xx":"El Triste"}}
>>>>>>> 03f74aca74312dbeaf24d7e61306dd6a786dc3d0
