{
  "id": 7083530,
  "type": "Feature",
  "properties": {
    "tgn:hierarchy":[
        "tgn:7083530",
        "tgn:1000003",
        "tgn:7003677",
        "tgn:7000084",
        "tgn:7029392"
    ],
    "tgn:id":7083530,
    "tgn:name":"Wellringrade",
    "tgn:placetype":[
        "aat:300000206"
    ]
},
  "bbox": [],
  "geometry": {"coordinates":[7.366667,51.216667],"type":"Point"}
}