{
  "id": 7261435,
  "type": "Feature",
  "properties": {
    "tgn:hierarchy":[
        "tgn:7261435",
        "tgn:7003616",
        "tgn:1000003",
        "tgn:7016845",
        "tgn:7029392"
    ],
    "tgn:id":7261435,
    "tgn:name:nl":"Gaasterland",
    "tgn:placetype":[
        "aat:300055621"
    ]
},
  "bbox": [],
  "geometry": {"coordinates":[5.45,52.866667],"type":"Point"}
}