{
  "id": 2609095,
  "type": "Feature",
  "properties": {
    "tgn:hierarchy":[
        "tgn:2609095",
        "tgn:1000001",
        "tgn:2001415",
        "tgn:7012149",
        "tgn:7007526",
        "tgn:7029392"
    ],
    "tgn:id":2609095,
    "tgn:name":"Ravenswood",
    "tgn:placetype":[
        "aat:300008347",
        "aat:300167671",
        "aat:300387305"
    ]
},
  "bbox": [],
  "geometry": {"coordinates":[-117.25,39.7667],"type":"Point"}
}