{
  "id": 7588976,
  "type": "Feature",
  "properties": {
    "tgn:hierarchy":[
        "tgn:7588976",
        "tgn:1000004",
        "tgn:7000198",
        "tgn:1001998",
        "tgn:7029392"
    ],
    "tgn:id":7588976,
    "tgn:name:en":"Tachhip",
    "tgn:placetype":[
        "aat:300008347"
    ]
},
  "bbox": [],
  "geometry": {"coordinates":[92.720618,23.582835],"type":"Point"}
}