{
  "id": 7477448,
  "type": "Feature",
  "properties": {
    "tgn:hierarchy":[
        "tgn:7477448",
        "tgn:7488858",
        "tgn:1000004",
        "tgn:1000141",
        "tgn:7029392"
    ],
    "tgn:id":7477448,
    "tgn:name":"Daping",
    "tgn:placetype":[
        "aat:300008347"
    ]
},
  "bbox": [],
  "geometry": {"coordinates":[120.918151,23.903327],"type":"Point"}
}