{
  "id": 2617326,
  "type": "Feature",
  "properties": {
    "tgn:hierarchy":[
        "tgn:2617326",
        "tgn:1000001",
        "tgn:7012149",
        "tgn:2000814",
        "tgn:7007255",
        "tgn:7029392"
    ],
    "tgn:id":2617326,
    "tgn:name":"Richland Creek",
    "tgn:placetype":[
        "aat:300008706"
    ]
},
  "bbox": [],
  "geometry": {"coordinates":[-88.25,37.0833],"type":"Point"}
}