{
  "id": 2482134,
  "type": "Feature",
  "properties": {
    "tgn:hierarchy":[
        "tgn:2482134",
        "tgn:1000001",
        "tgn:7012149",
        "tgn:2001440",
        "tgn:7007566",
        "tgn:7029392"
    ],
    "tgn:id":2482134,
    "tgn:name":"Lang Canyon",
    "tgn:placetype":[
        "aat:300008761"
    ]
},
  "bbox": [],
  "geometry": {"coordinates":[-108.75,31.3167],"type":"Point"}
}