<<<<<<< HEAD
{
  "id": 7483322,
  "type": "Feature",
  "properties": {
    "tgn:hierarchy":[
        "tgn:7483322",
        "tgn:7487020",
        "tgn:1000004",
        "tgn:1000141",
        "tgn:7029392"
    ],
    "tgn:id":7483322,
    "tgn:name":"Zhenmin Qiao",
    "tgn:placetype":[
        "aat:300007836"
    ]
},
  "bbox": [],
  "geometry": {"coordinates":[120.683056,24.368056],"type":"Point"}
}
=======
{"geometry":{"type":"Point","coordinates":[120.683056,24.368056]},"type":"Feature","properties":{"hierarchy":["tgn:7483322","tgn:7487020","tgn:1000004","tgn:1000141","tgn:7029392"],"placetype":["aat:300007836"],"id":7483322,"name:xx":"Zhenmin Qiao"}}
>>>>>>> 03f74aca74312dbeaf24d7e61306dd6a786dc3d0
