{
  "id": 1129447,
  "type": "Feature",
  "properties": {
    "tgn:hierarchy":[
        "tgn:1129447",
        "tgn:1000001",
        "tgn:7029392"
    ],
    "tgn:id":1129447,
    "tgn:name":"Salinas",
    "tgn:placetype":[
        "aat:300008707"
    ]
},
  "bbox": [],
  "geometry": {"coordinates":[-90.55,16.4667],"type":"Point"}
}