<<<<<<< HEAD
{
  "id": 7365830,
  "type": "Feature",
  "properties": {
    "tgn:hierarchy":[
        "tgn:7365830",
        "tgn:1000001",
        "tgn:7005596",
        "tgn:7005560",
        "tgn:7029392"
    ],
    "tgn:id":7365830,
    "tgn:name":"Ensenada Grande, Laguna",
    "tgn:placetype":[
        "aat:300008680"
    ]
},
  "bbox": [],
  "geometry": {"coordinates":[-91.083333,17.4],"type":"Point"}
}
=======
{"geometry":{"type":"Point","coordinates":[-91.083333,17.400000]},"type":"Feature","properties":{"hierarchy":["tgn:7365830","tgn:1000001","tgn:7005596","tgn:7005560","tgn:7029392"],"placetype":["aat:300008680"],"id":7365830,"name:xx":"Ensenada Grande, Laguna"}}
>>>>>>> 03f74aca74312dbeaf24d7e61306dd6a786dc3d0
