{
  "id": 2427114,
  "type": "Feature",
  "properties": {
    "tgn:hierarchy":[
        "tgn:2427114",
        "tgn:2001089",
        "tgn:1000001",
        "tgn:7012149",
        "tgn:7007522",
        "tgn:7029392"
    ],
    "tgn:id":2427114,
    "tgn:name":"Joplin",
    "tgn:placetype":[
        "aat:300008347"
    ]
},
  "bbox": [],
  "geometry": {"coordinates":[-89.45,33.0167],"type":"Point"}
}