{
  "id": 1116491,
  "type": "Feature",
  "properties": {
    "tgn:hierarchy":[
        "tgn:1116491",
        "tgn:1000001",
        "tgn:7012149",
        "tgn:1002982",
        "tgn:7007922",
        "tgn:7029392"
    ],
    "tgn:id":1116491,
    "tgn:name":"Green Lake",
    "tgn:placetype":[
        "aat:300008680"
    ]
},
  "bbox": [],
  "geometry": {"coordinates":[-88.5667,42.7667],"type":"Point"}
}