{
  "id": 7318826,
  "type": "Feature",
  "properties": {
    "tgn:hierarchy":[
        "tgn:7318826",
        "tgn:1001702",
        "tgn:1000049",
        "tgn:1000002",
        "tgn:7029392"
    ],
    "tgn:id":7318826,
    "tgn:name":"Barrie, Roca",
    "tgn:placetype":[
        "aat:300011692"
    ]
},
  "bbox": [],
  "geometry": {"coordinates":[-73.65,-52.35],"type":"Point"}
}