<<<<<<< HEAD
{
  "id": 7487964,
  "type": "Feature",
  "properties": {
    "tgn:hierarchy":[
        "tgn:7487964",
        "tgn:7487020",
        "tgn:1000004",
        "tgn:1000141",
        "tgn:7029392"
    ],
    "tgn:id":7487964,
    "tgn:name":"Nanzhuang Xiang",
    "tgn:placetype":[
        "aat:300387173"
    ]
},
  "bbox": [],
  "geometry": {"coordinates":[121.016667,24.566667],"type":"Point"}
}
=======
{"geometry":{"type":"Point","coordinates":[121.016667,24.566667]},"type":"Feature","properties":{"hierarchy":["tgn:7487964","tgn:7487020","tgn:1000004","tgn:1000141","tgn:7029392"],"placetype":["aat:300387173"],"id":7487964,"name:xx":"Nanzhuang Xiang"}}
>>>>>>> 03f74aca74312dbeaf24d7e61306dd6a786dc3d0
