{
  "id": 7366964,
  "type": "Feature",
  "properties": {
    "tgn:hierarchy":[
        "tgn:7366964",
        "tgn:1000001",
        "tgn:7005595",
        "tgn:7005560",
        "tgn:7029392"
    ],
    "tgn:id":7366964,
    "tgn:name":"El Perihuete",
    "tgn:placetype":[
        "aat:300008347"
    ]
},
  "bbox": [],
  "geometry": {"coordinates":[-108.133333,25.766667],"type":"Point"}
}