{
  "id": 2268008,
  "type": "Feature",
  "properties": {
    "tgn:hierarchy":[
        "tgn:2268008",
        "tgn:1000001",
        "tgn:7012149",
        "tgn:2000730",
        "tgn:7007254",
        "tgn:7029392"
    ],
    "tgn:id":2268008,
    "tgn:name":"Crooked Creek",
    "tgn:placetype":[
        "aat:300008706"
    ]
},
  "bbox": [],
  "geometry": {"coordinates":[-99.0167,39.5333],"type":"Point"}
}