{
  "id": 2021084,
  "type": "Feature",
  "properties": {
    "tgn:hierarchy":[
        "tgn:2021084",
        "tgn:1000001",
        "tgn:7012149",
        "tgn:1002631",
        "tgn:7007240",
        "tgn:7029392"
    ],
    "tgn:id":2021084,
    "tgn:name":"Rolling Ranches",
    "tgn:placetype":[
        "aat:300008347"
    ]
},
  "bbox": [],
  "geometry": {"coordinates":[-82.3333,29.05],"type":"Point"}
}