{
  "id": 2507713,
  "type": "Feature",
  "properties": {
    "tgn:hierarchy":[
        "tgn:2507713",
        "tgn:1000001",
        "tgn:7012149",
        "tgn:2001615",
        "tgn:7007706",
        "tgn:7029392"
    ],
    "tgn:id":2507713,
    "tgn:name":"Michaels Run",
    "tgn:placetype":[
        "aat:300008699"
    ]
},
  "bbox": [],
  "geometry": {"coordinates":[-82.3167,38.4833],"type":"Point"}
}