{
  "id": 2554249,
  "type": "Feature",
  "properties": {
    "tgn:hierarchy":[
        "tgn:2554249",
        "tgn:1000001",
        "tgn:7012149",
        "tgn:2001452",
        "tgn:7007566",
        "tgn:7029392"
    ],
    "tgn:id":2554249,
    "tgn:name":"Oak Springs Canyon",
    "tgn:placetype":[
        "aat:300008761"
    ]
},
  "bbox": [],
  "geometry": {"coordinates":[-108.2667,36.95],"type":"Point"}
}