<<<<<<< HEAD
{
  "id": 7170116,
  "type": "Feature",
  "properties": {
    "tgn:hierarchy":[
        "tgn:7170116",
        "tgn:7003669",
        "tgn:1000003",
        "tgn:7000084",
        "tgn:7029392"
    ],
    "tgn:id":7170116,
    "tgn:name":"Hoch-Berg",
    "tgn:placetype":[
        "aat:300008777"
    ]
},
  "bbox": [],
  "geometry": {"coordinates":[12.65,47.85],"type":"Point"}
}
=======
{"geometry":{"type":"Point","coordinates":[12.650000,47.850000]},"type":"Feature","properties":{"hierarchy":["tgn:7170116","tgn:7003669","tgn:1000003","tgn:7000084","tgn:7029392"],"placetype":["aat:300008777"],"id":7170116,"name:xx":"Hoch-Berg"}}
>>>>>>> 03f74aca74312dbeaf24d7e61306dd6a786dc3d0
