<<<<<<< HEAD
{
  "id": 2760156,
  "type": "Feature",
  "properties": {
    "tgn:hierarchy":[
        "tgn:2760156",
        "tgn:1000001",
        "tgn:7012149",
        "tgn:2002092",
        "tgn:7007826",
        "tgn:7029392"
    ],
    "tgn:id":2760156,
    "tgn:name":"West Fork Pond Creek",
    "tgn:placetype":[
        "aat:300008706"
    ]
},
  "bbox": [],
  "geometry": {"coordinates":[-98.6667,34.0],"type":"Point"}
}
=======
{"geometry":{"type":"Point","coordinates":[-98.666700,34.000000]},"type":"Feature","properties":{"hierarchy":["tgn:2760156","tgn:1000001","tgn:7012149","tgn:2002092","tgn:7007826","tgn:7029392"],"placetype":["aat:300008706"],"id":2760156,"name:xx":"West Fork Pond Creek"}}
>>>>>>> 03f74aca74312dbeaf24d7e61306dd6a786dc3d0
