{
  "id": 7241674,
  "type": "Feature",
  "properties": {
    "tgn:hierarchy":[
        "tgn:7241674",
        "tgn:7003466",
        "tgn:1000003",
        "tgn:1000063",
        "tgn:4012014",
        "tgn:7029392"
    ],
    "tgn:id":7241674,
    "tgn:name":"Le Frechisse",
    "tgn:placetype":[
        "aat:300008347"
    ]
},
  "bbox": [],
  "geometry": {"coordinates":[5.084101,50.315984],"type":"Point"}
}