{
  "id": 2245269,
  "type": "Feature",
  "properties": {
    "tgn:hierarchy":[
        "tgn:2245269",
        "tgn:1000001",
        "tgn:7012149",
        "tgn:1002535",
        "tgn:7007826",
        "tgn:7029392"
    ],
    "tgn:id":2245269,
    "tgn:name":"Club Lake",
    "tgn:placetype":[
        "aat:300006191"
    ]
},
  "bbox": [],
  "geometry": {"coordinates":[-96.25,32.6167],"type":"Point"}
}