{
  "id": 7052959,
  "type": "Feature",
  "properties": {
    "tgn:hierarchy":[
        "tgn:7052959",
        "tgn:7003131",
        "tgn:1000003",
        "tgn:7008516",
        "tgn:1000080",
        "tgn:7029392"
    ],
    "tgn:id":7052959,
    "tgn:name":"Iggio",
    "tgn:placetype":[
        "aat:300008347"
    ]
},
  "bbox": [],
  "geometry": {"coordinates":[9.866667,44.766667],"type":"Point"}
}