{
  "id": 7323774,
  "type": "Feature",
  "properties": {
    "tgn:hierarchy":[
        "tgn:7323774",
        "tgn:7002829",
        "tgn:1000003",
        "tgn:7002786",
        "tgn:1000095",
        "tgn:7029392"
    ],
    "tgn:id":7323774,
    "tgn:name":"Ribeira, Arroyo de",
    "tgn:placetype":[
        "aat:300008699"
    ]
},
  "bbox": [],
  "geometry": {"coordinates":[-7.766667,43.333333],"type":"Point"}
}