{
  "id": 2122152,
  "type": "Feature",
  "properties": {
    "tgn:hierarchy":[
        "tgn:2122152",
        "tgn:1000001",
        "tgn:2002323",
        "tgn:7012149",
        "tgn:7007922",
        "tgn:7029392"
    ],
    "tgn:id":2122152,
    "tgn:name":"Popple River",
    "tgn:placetype":[
        "aat:300008347"
    ]
},
  "bbox": [],
  "geometry": {"coordinates":[-88.6833,45.7833],"type":"Point"}
}