{
  "id": 7139151,
  "type": "Feature",
  "properties": {
    "tgn:hierarchy":[
        "tgn:7139151",
        "tgn:1000003",
        "tgn:7003685",
        "tgn:7000084",
        "tgn:7029392"
    ],
    "tgn:id":7139151,
    "tgn:name":"Bahnhof Leipzig-Knauthain",
    "tgn:placetype":[
        "aat:300007783"
    ]
},
  "bbox": [],
  "geometry": {"coordinates":[12.308333,51.278333],"type":"Point"}
}