{
  "id": 7160309,
  "type": "Feature",
  "properties": {
    "tgn:hierarchy":[
        "tgn:7160309",
        "tgn:7000096",
        "tgn:1000003",
        "tgn:7000084",
        "tgn:7029392"
    ],
    "tgn:id":7160309,
    "tgn:name":"Hohenelse",
    "tgn:placetype":[
        "aat:300008347"
    ]
},
  "bbox": [],
  "geometry": {"coordinates":[12.883333,53.133333],"type":"Point"}
}