{
  "id": 7451659,
  "type": "Feature",
  "properties": {
    "tgn:hierarchy":[
        "tgn:7451659",
        "tgn:7002445",
        "tgn:1000003",
        "tgn:7008166",
        "tgn:7008591",
        "tgn:7029392"
    ],
    "tgn:id":7451659,
    "tgn:name:en":"Great Haw",
    "tgn:placetype":[
        "aat:300008795"
    ]
},
  "bbox": [],
  "geometry": {"coordinates":[-1.866667,54.216667],"type":"Point"}
}