<<<<<<< HEAD
{
  "id": 2333288,
  "type": "Feature",
  "properties": {
    "tgn:hierarchy":[
        "tgn:2333288",
        "tgn:1000001",
        "tgn:7013638",
        "tgn:7012149",
        "tgn:7007568",
        "tgn:7029392"
    ],
    "tgn:id":2333288,
    "tgn:name":"Fog Hill",
    "tgn:placetype":[
        "aat:300008798"
    ]
},
  "bbox": [],
  "geometry": {"coordinates":[-73.45,42.3333],"type":"Point"}
}
=======
{"geometry":{"type":"Point","coordinates":[-73.450000,42.333300]},"type":"Feature","properties":{"hierarchy":["tgn:2333288","tgn:1000001","tgn:7013638","tgn:7012149","tgn:7007568","tgn:7029392"],"placetype":["aat:300008798"],"id":2333288,"name:xx":"Fog Hill"}}
>>>>>>> 03f74aca74312dbeaf24d7e61306dd6a786dc3d0
