{
  "id": 7404602,
  "type": "Feature",
  "properties": {
    "tgn:hierarchy":[
        "tgn:7404602",
        "tgn:7005585",
        "tgn:1000001",
        "tgn:7005560",
        "tgn:7029392"
    ],
    "tgn:id":7404602,
    "tgn:name":"El Cayaco",
    "tgn:placetype":[
        "aat:300008347"
    ]
},
  "bbox": [],
  "geometry": {"coordinates":[-99.808333,16.858333],"type":"Point"}
}