{
  "id": 7166850,
  "type": "Feature",
  "properties": {
    "tgn:hierarchy":[
        "tgn:7166850",
        "tgn:1000003",
        "tgn:7003676",
        "tgn:7000084",
        "tgn:7029392"
    ],
    "tgn:id":7166850,
    "tgn:name":"Heidbrink",
    "tgn:placetype":[
        "aat:300008777"
    ]
},
  "bbox": [],
  "geometry": {"coordinates":[9.566667,51.85],"type":"Point"}
}