{
  "id": 7225576,
  "type": "Feature",
  "properties": {
    "tgn:hierarchy":[
        "tgn:7225576",
        "tgn:7002711",
        "tgn:7001338",
        "tgn:1000003",
        "tgn:1000074",
        "tgn:7029392"
    ],
    "tgn:id":7225576,
    "tgn:name":"Per\u00edtheia",
    "tgn:placetype":[
        "aat:300008347"
    ]
},
  "bbox": [],
  "geometry": {"coordinates":[19.872222,39.7625],"type":"Point"}
}