{
  "id": 2381656,
  "type": "Feature",
  "properties": {
    "tgn:hierarchy":[
        "tgn:2381656",
        "tgn:1000001",
        "tgn:7012149",
        "tgn:7007516",
        "tgn:7029392"
    ],
    "tgn:id":2381656,
    "tgn:name":"Hay Meadow Branch",
    "tgn:placetype":[
        "aat:300008699"
    ]
},
  "bbox": [],
  "geometry": {"coordinates":[-77.1167,39.3333],"type":"Point"}
}