{
  "id": 1023036,
  "type": "Feature",
  "properties": {
    "tgn:hierarchy":[
        "tgn:1023036",
        "tgn:7006237",
        "tgn:1000047",
        "tgn:7002457",
        "tgn:1000002",
        "tgn:7029392"
    ],
    "tgn:id":1023036,
    "tgn:name":"Sapuca\u00ed-Mirim",
    "tgn:placetype":[
        "aat:300008347"
    ]
},
  "bbox": [],
  "geometry": {"coordinates":[-45.75,-22.7333],"type":"Point"}
}