{
  "id": 2244891,
  "type": "Feature",
  "properties": {
    "tgn:hierarchy":[
        "tgn:2244891",
        "tgn:1000001",
        "tgn:7012149",
        "tgn:2000439",
        "tgn:7007248",
        "tgn:7029392"
    ],
    "tgn:id":2244891,
    "tgn:name":"Cloughs Bay",
    "tgn:placetype":[
        "aat:300008905"
    ]
},
  "bbox": [],
  "geometry": {"coordinates":[-82.45,31.1667],"type":"Point"}
}