{
  "id": 7411048,
  "type": "Feature",
  "properties": {
    "tgn:hierarchy":[
        "tgn:7411048",
        "tgn:7005580",
        "tgn:1000001",
        "tgn:7005560",
        "tgn:7029392"
    ],
    "tgn:id":7411048,
    "tgn:name":"Paso Chinal",
    "tgn:placetype":[
        "aat:300008347"
    ]
},
  "bbox": [],
  "geometry": {"coordinates":[-92.505556,17.494444],"type":"Point"}
}