{
  "id": 7032026,
  "type": "Feature",
  "properties": {
    "tgn:hierarchy":[
        "tgn:7032026",
        "tgn:1000001",
        "tgn:7029392"
    ],
    "tgn:id":7032026,
    "tgn:name:en":"Bermuda",
    "tgn:name:fr":"Bermudes",
    "tgn:placetype":[
        "aat:300387054",
        "aat:300235115",
        "aat:300386853",
        "aat:300387176"
    ]
},
  "bbox": [],
  "geometry": {"coordinates":[-64.75,32.3333],"type":"Point"}
}