{
  "id": 2430593,
  "type": "Feature",
  "properties": {
    "tgn:hierarchy":[
        "tgn:2430593",
        "tgn:1002648",
        "tgn:1000001",
        "tgn:7019158",
        "tgn:7012149",
        "tgn:7007249",
        "tgn:7029392"
    ],
    "tgn:id":2430593,
    "tgn:name":"Kalena Stream",
    "tgn:placetype":[
        "aat:300008699"
    ]
},
  "bbox": [],
  "geometry": {"coordinates":[-156.0667,20.6667],"type":"Point"}
}