{
  "id": 2245115,
  "type": "Feature",
  "properties": {
    "tgn:hierarchy":[
        "tgn:2245115",
        "tgn:1000001",
        "tgn:7012149",
        "tgn:1002505",
        "tgn:7007920",
        "tgn:7029392"
    ],
    "tgn:id":2245115,
    "tgn:name":"Clover Valley",
    "tgn:placetype":[
        "aat:300008761"
    ]
},
  "bbox": [],
  "geometry": {"coordinates":[-122.6333,48.3333],"type":"Point"}
}