{
  "id": 7063421,
  "type": "Feature",
  "properties": {
    "tgn:hierarchy":[
        "tgn:7063421",
        "tgn:1000003",
        "tgn:7003689",
        "tgn:7000084",
        "tgn:7029392"
    ],
    "tgn:id":7063421,
    "tgn:name":"Apfelbach",
    "tgn:placetype":[
        "aat:300008347"
    ]
},
  "bbox": [],
  "geometry": {"coordinates":[9.95,50.65],"type":"Point"}
}