{
  "id": 7051619,
  "type": "Feature",
  "properties": {
    "tgn:hierarchy":[
        "tgn:7051619",
        "tgn:7003136",
        "tgn:1000003",
        "tgn:7003080",
        "tgn:1000080",
        "tgn:7029392"
    ],
    "tgn:id":7051619,
    "tgn:name":"Mulino, Punta",
    "tgn:placetype":[
        "aat:300386846"
    ]
},
  "bbox": [],
  "geometry": {"coordinates":[13.566667,41.216667],"type":"Point"}
}