{
  "id": 2386046,
  "type": "Feature",
  "properties": {
    "tgn:hierarchy":[
        "tgn:2386046",
        "tgn:1000001",
        "tgn:7012149",
        "tgn:2001718",
        "tgn:7007708",
        "tgn:7029392"
    ],
    "tgn:id":2386046,
    "tgn:name":"Henry Gulch Spring",
    "tgn:placetype":[
        "aat:300008697"
    ]
},
  "bbox": [],
  "geometry": {"coordinates":[-117.15,44.0667],"type":"Point"}
}