{
  "id": 7364026,
  "type": "Feature",
  "properties": {
    "tgn:hierarchy":[
        "tgn:7364026",
        "tgn:1000001",
        "tgn:7005589",
        "tgn:7005560",
        "tgn:7029392"
    ],
    "tgn:id":7364026,
    "tgn:name":"Rancho El Barrial",
    "tgn:placetype":[
        "aat:300000241"
    ]
},
  "bbox": [],
  "geometry": {"coordinates":[-99.414167,24.746944],"type":"Point"}
}