{
  "id": 2341056,
  "type": "Feature",
  "properties": {
    "tgn:hierarchy":[
        "tgn:2341056",
        "tgn:1000001",
        "tgn:7012149",
        "tgn:1002612",
        "tgn:7007710",
        "tgn:7029392"
    ],
    "tgn:id":2341056,
    "tgn:name":"Friendship Hill",
    "tgn:placetype":[
        "aat:300008798"
    ]
},
  "bbox": [],
  "geometry": {"coordinates":[-75.9667,41.3167],"type":"Point"}
}