{
  "id": 2628332,
  "type": "Feature",
  "properties": {
    "tgn:hierarchy":[
        "tgn:2628332",
        "tgn:1000001",
        "tgn:7012149",
        "tgn:2001190",
        "tgn:7007523",
        "tgn:7029392"
    ],
    "tgn:id":2628332,
    "tgn:name":"Romine Lead Mine",
    "tgn:placetype":[
        "aat:300000390"
    ]
},
  "bbox": [],
  "geometry": {"coordinates":[-91.15,38.15],"type":"Point"}
}