{
  "id": 7489898,
  "type": "Feature",
  "properties": {
    "tgn:hierarchy":[
        "tgn:7489898",
        "tgn:1000004",
        "tgn:7001014",
        "tgn:1000141",
        "tgn:7029392"
    ],
    "tgn:id":7489898,
    "tgn:name":"Sushuiwei",
    "tgn:placetype":[
        "aat:300008347"
    ]
},
  "bbox": [],
  "geometry": {"coordinates":[120.206667,23.581944],"type":"Point"}
}