{
  "id": 7523131,
  "type": "Feature",
  "properties": {
    "tgn:hierarchy":[
        "tgn:7523131",
        "tgn:7001242",
        "tgn:7016833",
        "tgn:1001142",
        "tgn:7029392"
    ],
    "tgn:id":7523131,
    "tgn:name:en":"Ash Shun\u0163\u016br",
    "tgn:placetype":[
        "aat:300008347"
    ]
},
  "bbox": [],
  "geometry": {"coordinates":[30.855679,28.953552],"type":"Point"}
}