{
  "id": 1045745,
  "type": "Feature",
  "properties": {
    "tgn:hierarchy":[
        "tgn:1045745",
        "tgn:1001724",
        "tgn:1000003",
        "tgn:7003121",
        "tgn:1000080",
        "tgn:7029392"
    ],
    "tgn:id":1045745,
    "tgn:name":"Olzai",
    "tgn:placetype":[
        "aat:300008347"
    ]
},
  "bbox": [],
  "geometry": {"coordinates":[9.15,40.183333],"type":"Point"}
}