{
  "id": 1058565,
  "type": "Feature",
  "properties": {
    "tgn:hierarchy":[
        "tgn:1058565",
        "tgn:1000004",
        "tgn:7012930",
        "tgn:7014786",
        "tgn:7029392"
    ],
    "tgn:id":1058565,
    "tgn:name":"Poludino",
    "tgn:placetype":[
        "aat:300008347"
    ]
},
  "bbox": [],
  "geometry": {"coordinates":[69.8833,54.85],"type":"Point"}
}