{
  "id": 1054769,
  "type": "Feature",
  "properties": {
    "tgn:hierarchy":[
        "tgn:1054769",
        "tgn:1000004",
        "tgn:1003418",
        "tgn:7018214",
        "tgn:7002435",
        "tgn:7029392"
    ],
    "tgn:id":1054769,
    "tgn:name":"Yudino",
    "tgn:placetype":[
        "aat:300008347"
    ]
},
  "bbox": [],
  "geometry": {"coordinates":[38.3167,54.15],"type":"Point"}
}