{
  "id": 2751393,
  "type": "Feature",
  "properties": {
    "tgn:hierarchy":[
        "tgn:2751393",
        "tgn:1000001",
        "tgn:7012149",
        "tgn:2001437",
        "tgn:7007566",
        "tgn:7029392"
    ],
    "tgn:id":2751393,
    "tgn:name":"Warm Springs",
    "tgn:placetype":[
        "aat:300008697"
    ]
},
  "bbox": [],
  "geometry": {"coordinates":[-108.0167,32.55],"type":"Point"}
}