{
  "id": 7232778,
  "type": "Feature",
  "properties": {
    "tgn:hierarchy":[
        "tgn:7232778",
        "tgn:7002743",
        "tgn:7017076",
        "tgn:1000003",
        "tgn:1000074",
        "tgn:7029392"
    ],
    "tgn:id":7232778,
    "tgn:name":"Katsar\u00f3s",
    "tgn:placetype":[
        "aat:300008347"
    ]
},
  "bbox": [],
  "geometry": {"coordinates":[21.416667,37.716667],"type":"Point"}
}