{
  "id": 7391382,
  "type": "Feature",
  "properties": {
    "tgn:hierarchy":[
        "tgn:7391382",
        "tgn:1000001",
        "tgn:1001960",
        "tgn:7005560",
        "tgn:7029392"
    ],
    "tgn:id":7391382,
    "tgn:name":"Rancho Santa Mar\u00eda Buaraje",
    "tgn:placetype":[
        "aat:300008347"
    ]
},
  "bbox": [],
  "geometry": {"coordinates":[-109.883333,27.133333],"type":"Point"}
}