{
  "id": 1052987,
  "type": "Feature",
  "properties": {
    "tgn:hierarchy":[
        "tgn:1052987",
        "tgn:1000004",
        "tgn:7013207",
        "tgn:7018214",
        "tgn:7002435",
        "tgn:7029392"
    ],
    "tgn:id":1052987,
    "tgn:name":"Bol'shoye Sudach'ye",
    "tgn:placetype":[
        "aat:300008347"
    ]
},
  "bbox": [],
  "geometry": {"coordinates":[44.0833,50.8167],"type":"Point"}
}