{
  "id": 7590127,
  "type": "Feature",
  "properties": {
    "tgn:hierarchy":[
        "tgn:7590127",
        "tgn:1000004",
        "tgn:7000198",
        "tgn:7000799",
        "tgn:7029392"
    ],
    "tgn:id":7590127,
    "tgn:name:en":"Garang Forest",
    "tgn:placetype":[
        "aat:300008863"
    ]
},
  "bbox": [],
  "geometry": {"coordinates":[74.283333,33.841667],"type":"Point"}
}