<<<<<<< HEAD
{
  "id": 2255771,
  "type": "Feature",
  "properties": {
    "tgn:hierarchy":[
        "tgn:2255771",
        "tgn:1000001",
        "tgn:7006451",
        "tgn:7012149",
        "tgn:2000103",
        "tgn:7029392"
    ],
    "tgn:id":2255771,
    "tgn:name":"Copper Canyon",
    "tgn:placetype":[
        "aat:300008761"
    ]
},
  "bbox": [],
  "geometry": {"coordinates":[-111.95,34.5167],"type":"Point"}
}
=======
{"geometry":{"type":"Point","coordinates":[-111.950000,34.516700]},"type":"Feature","properties":{"hierarchy":["tgn:2255771","tgn:1000001","tgn:7006451","tgn:7012149","tgn:2000103","tgn:7029392"],"placetype":["aat:300008761"],"id":2255771,"name:xx":"Copper Canyon"}}
>>>>>>> 03f74aca74312dbeaf24d7e61306dd6a786dc3d0
