{
  "id": 7286678,
  "type": "Feature",
  "properties": {
    "tgn:hierarchy":[
        "tgn:7286678",
        "tgn:1001623",
        "tgn:1000049",
        "tgn:1000002",
        "tgn:7029392"
    ],
    "tgn:id":7286678,
    "tgn:name":"Guatelaguen, Punta",
    "tgn:placetype":[
        "aat:300386846"
    ]
},
  "bbox": [],
  "geometry": {"coordinates":[-75.116667,-47.666667],"type":"Point"}
}