<<<<<<< HEAD
{
  "id": 2156148,
  "type": "Feature",
  "properties": {
    "tgn:hierarchy":[
        "tgn:2156148",
        "tgn:1000001",
        "tgn:7019982",
        "tgn:7012149",
        "tgn:7007517",
        "tgn:7029392"
    ],
    "tgn:id":2156148,
    "tgn:name":"Bearden Brook",
    "tgn:placetype":[
        "aat:300008699"
    ]
},
  "bbox": [],
  "geometry": {"coordinates":[-72.8333,42.2167],"type":"Point"}
}
=======
{"geometry":{"type":"Point","coordinates":[-72.833300,42.216700]},"type":"Feature","properties":{"hierarchy":["tgn:2156148","tgn:1000001","tgn:7019982","tgn:7012149","tgn:7007517","tgn:7029392"],"placetype":["aat:300008699"],"id":2156148,"name:xx":"Bearden Brook"}}
>>>>>>> 03f74aca74312dbeaf24d7e61306dd6a786dc3d0
