{
  "id": 2653017,
  "type": "Feature",
  "properties": {
    "tgn:hierarchy":[
        "tgn:2653017",
        "tgn:1000001",
        "tgn:7012149",
        "tgn:7007158",
        "tgn:2000253",
        "tgn:7029392"
    ],
    "tgn:id":2653017,
    "tgn:name":"Seven Cross Hill",
    "tgn:placetype":[
        "aat:300008798"
    ]
},
  "bbox": [],
  "geometry": {"coordinates":[-104.2667,40.6667],"type":"Point"}
}