{
  "id": 7506964,
  "type": "Feature",
  "properties": {
    "tgn:hierarchy":[
        "tgn:7506964",
        "tgn:1008380",
        "tgn:7520093",
        "tgn:1000226",
        "tgn:1000006",
        "tgn:7029392"
    ],
    "tgn:id":7506964,
    "tgn:name:en":"Rangiatea",
    "tgn:placetype":[
        "aat:300008795"
    ]
},
  "bbox": [],
  "geometry": {"coordinates":[175.366667,-38.933333],"type":"Point"}
}