{
  "id": 2199781,
  "type": "Feature",
  "properties": {
    "tgn:hierarchy":[
        "tgn:2199781",
        "tgn:1000001",
        "tgn:7012149",
        "tgn:2002120",
        "tgn:7007827",
        "tgn:7029392"
    ],
    "tgn:id":2199781,
    "tgn:name":"Brush Reservoir",
    "tgn:placetype":[
        "aat:300006191"
    ]
},
  "bbox": [],
  "geometry": {"coordinates":[-111.4333,39.0667],"type":"Point"}
}