{
  "id": 2769101,
  "type": "Feature",
  "properties": {
    "tgn:hierarchy":[
        "tgn:2769101",
        "tgn:1000001",
        "tgn:1002359",
        "tgn:7012149",
        "tgn:7007517",
        "tgn:7029392"
    ],
    "tgn:id":2769101,
    "tgn:name":"Whittiers Cove",
    "tgn:placetype":[
        "aat:300132316"
    ]
},
  "bbox": [],
  "geometry": {"coordinates":[-70.7667,42.5667],"type":"Point"}
}