<<<<<<< HEAD
{
  "id": 2769101,
  "type": "Feature",
  "properties": {
    "tgn:hierarchy":[
        "tgn:2769101",
        "tgn:1000001",
        "tgn:1002359",
        "tgn:7012149",
        "tgn:7007517",
        "tgn:7029392"
    ],
    "tgn:id":2769101,
    "tgn:name":"Whittiers Cove",
    "tgn:placetype":[
        "aat:300132316"
    ]
},
  "bbox": [],
  "geometry": {"coordinates":[-70.7667,42.5667],"type":"Point"}
}
=======
{"geometry":{"type":"Point","coordinates":[-70.766700,42.566700]},"type":"Feature","properties":{"hierarchy":["tgn:2769101","tgn:1000001","tgn:1002359","tgn:7012149","tgn:7007517","tgn:7029392"],"placetype":["aat:300132316"],"id":2769101,"name:xx":"Whittiers Cove"}}
>>>>>>> 03f74aca74312dbeaf24d7e61306dd6a786dc3d0
