{
  "id": 7381373,
  "type": "Feature",
  "properties": {
    "tgn:hierarchy":[
        "tgn:7381373",
        "tgn:7005583",
        "tgn:1000001",
        "tgn:7005560",
        "tgn:7029392"
    ],
    "tgn:id":7381373,
    "tgn:name":"Los Alisos",
    "tgn:placetype":[
        "aat:300008347"
    ]
},
  "bbox": [],
  "geometry": {"coordinates":[-106.061944,24.771389],"type":"Point"}
}