{
  "id": 7540466,
  "type": "Feature",
  "properties": {
    "tgn:hierarchy":[
        "tgn:7540466",
        "tgn:7001242",
        "tgn:7016833",
        "tgn:7000123",
        "tgn:7029392"
    ],
    "tgn:id":7540466,
    "tgn:name:en":"Naj' as Sam\u0101sir\u012byah",
    "tgn:placetype":[
        "aat:300008347"
    ]
},
  "bbox": [],
  "geometry": {"coordinates":[32.366667,26.033333],"type":"Point"}
}