{
  "id": 2168523,
  "type": "Feature",
  "properties": {
    "tgn:hierarchy":[
        "tgn:2168523",
        "tgn:1000001",
        "tgn:7012149",
        "tgn:7007157",
        "tgn:1002791",
        "tgn:7029392"
    ],
    "tgn:id":2168523,
    "tgn:name":"Big Hill",
    "tgn:placetype":[
        "aat:300008798"
    ]
},
  "bbox": [],
  "geometry": {"coordinates":[-121.15,38.9833],"type":"Point"}
}