{
  "id": 1078495,
  "type": "Feature",
  "properties": {
    "tgn:hierarchy":[
        "tgn:1078495",
        "tgn:1000004",
        "tgn:7003970",
        "tgn:1000116",
        "tgn:7029392"
    ],
    "tgn:id":1078495,
    "tgn:name":"Sarmi",
    "tgn:placetype":[
        "aat:300008347"
    ]
},
  "bbox": [],
  "geometry": {"coordinates":[138.75,-1.85],"type":"Point"}
}