{
  "id": 7200985,
  "type": "Feature",
  "properties": {
    "tgn:hierarchy":[
        "tgn:7200985",
        "tgn:1000003",
        "tgn:7003676",
        "tgn:7000084",
        "tgn:7029392"
    ],
    "tgn:id":7200985,
    "tgn:name":"Dorumer Wasserl\u00f6se",
    "tgn:placetype":[
        "aat:300008699"
    ]
},
  "bbox": [],
  "geometry": {"coordinates":[8.516667,53.733333],"type":"Point"}
}