<<<<<<< HEAD
{
  "id": 2158138,
  "type": "Feature",
  "properties": {
    "tgn:hierarchy":[
        "tgn:2158138",
        "tgn:1000001",
        "tgn:2002321",
        "tgn:7012149",
        "tgn:7007922",
        "tgn:7029392"
    ],
    "tgn:id":2158138,
    "tgn:name":"Beaver Pond",
    "tgn:placetype":[
        "aat:300008680"
    ]
},
  "bbox": [],
  "geometry": {"coordinates":[-88.65,45.8167],"type":"Point"}
}
=======
{"geometry":{"type":"Point","coordinates":[-88.650000,45.816700]},"type":"Feature","properties":{"hierarchy":["tgn:2158138","tgn:1000001","tgn:2002321","tgn:7012149","tgn:7007922","tgn:7029392"],"placetype":["aat:300008680"],"id":2158138,"name:xx":"Beaver Pond"}}
>>>>>>> 03f74aca74312dbeaf24d7e61306dd6a786dc3d0
