{
  "id": 7008574,
  "type": "Feature",
  "properties": {
    "tgn:hierarchy":[
        "tgn:7008574",
        "tgn:7002443",
        "tgn:7026970",
        "tgn:1000003",
        "tgn:7008591",
        "tgn:7029392"
    ],
    "tgn:id":7008574,
    "tgn:name:en":"Abergele",
    "tgn:placetype":[
        "aat:300008347"
    ]
},
  "bbox": [],
  "geometry": {"coordinates":[-3.583333,53.283333],"type":"Point"}
}