{
  "id": 7055540,
  "type": "Feature",
  "properties": {
    "tgn:hierarchy":[
        "tgn:7055540",
        "tgn:7003164",
        "tgn:1000003",
        "tgn:7009760",
        "tgn:1000080",
        "tgn:7029392"
    ],
    "tgn:id":7055540,
    "tgn:name":"Ortano, Isolotto d'",
    "tgn:placetype":[
        "aat:300008791"
    ]
},
  "bbox": [],
  "geometry": {"coordinates":[10.433333,42.783333],"type":"Point"}
}