{
  "id": 7576960,
  "type": "Feature",
  "properties": {
    "tgn:hierarchy":[
        "tgn:7576960",
        "tgn:1000004",
        "tgn:7000198",
        "tgn:1001894",
        "tgn:7029392"
    ],
    "tgn:id":7576960,
    "tgn:name:en":"Karhi",
    "tgn:placetype":[
        "aat:300008347"
    ]
},
  "bbox": [],
  "geometry": {"coordinates":[74.482153,22.565668],"type":"Point"}
}