{
  "id": 7562536,
  "type": "Feature",
  "properties": {
    "tgn:hierarchy":[
        "tgn:7562536",
        "tgn:1000004",
        "tgn:7000198",
        "tgn:1001894",
        "tgn:7029392"
    ],
    "tgn:id":7562536,
    "tgn:name:en":"Deoju ka Pura",
    "tgn:placetype":[
        "aat:300008347"
    ]
},
  "bbox": [],
  "geometry": {"coordinates":[79.07674,26.321541],"type":"Point"}
}