{
  "id": 7304326,
  "type": "Feature",
  "properties": {
    "tgn:hierarchy":[
        "tgn:7304326",
        "tgn:7001122",
        "tgn:1000003",
        "tgn:7002765",
        "tgn:1000095",
        "tgn:7029392"
    ],
    "tgn:id":7304326,
    "tgn:name":"Llamp, Cabo del",
    "tgn:placetype":[
        "aat:300008850"
    ]
},
  "bbox": [],
  "geometry": {"coordinates":[2.383333,39.516667],"type":"Point"}
}