<<<<<<< HEAD
{
  "id": 2333135,
  "type": "Feature",
  "properties": {
    "tgn:hierarchy":[
        "tgn:2333135",
        "tgn:1000001",
        "tgn:1002712",
        "tgn:7012149",
        "tgn:7007159",
        "tgn:7029392"
    ],
    "tgn:id":2333135,
    "tgn:name":"Flying Point",
    "tgn:placetype":[
        "aat:300008850"
    ]
},
  "bbox": [],
  "geometry": {"coordinates":[-72.75,41.25],"type":"Point"}
}
=======
{"geometry":{"type":"Point","coordinates":[-72.750000,41.250000]},"type":"Feature","properties":{"hierarchy":["tgn:2333135","tgn:1000001","tgn:1002712","tgn:7012149","tgn:7007159","tgn:7029392"],"placetype":["aat:300008850"],"id":2333135,"name:xx":"Flying Point"}}
>>>>>>> 03f74aca74312dbeaf24d7e61306dd6a786dc3d0
