{
  "id": 7379422,
  "type": "Feature",
  "properties": {
    "tgn:hierarchy":[
        "tgn:7379422",
        "tgn:1000001",
        "tgn:7005592",
        "tgn:7005560",
        "tgn:7029392"
    ],
    "tgn:id":7379422,
    "tgn:name":"Michac",
    "tgn:placetype":[
        "aat:300008347"
    ]
},
  "bbox": [],
  "geometry": {"coordinates":[-98.05,19.85],"type":"Point"}
}