{
  "id": 7586325,
  "type": "Feature",
  "properties": {
    "tgn:hierarchy":[
        "tgn:7586325",
        "tgn:1000004",
        "tgn:7000198",
        "tgn:7000799",
        "tgn:7029392"
    ],
    "tgn:id":7586325,
    "tgn:name:en":"Imbarzalw\u0101ri",
    "tgn:placetype":[
        "aat:300008699"
    ]
},
  "bbox": [],
  "geometry": {"coordinates":[74.441866,34.386172],"type":"Point"}
}