<<<<<<< HEAD
{
  "id": 2337413,
  "type": "Feature",
  "properties": {
    "tgn:hierarchy":[
        "tgn:2337413",
        "tgn:1000001",
        "tgn:2001425",
        "tgn:7012149",
        "tgn:7007564",
        "tgn:7029392"
    ],
    "tgn:id":2337413,
    "tgn:name":"Fowler Brook",
    "tgn:placetype":[
        "aat:300008699"
    ]
},
  "bbox": [],
  "geometry": {"coordinates":[-71.4167,43.2],"type":"Point"}
}
=======
{"geometry":{"type":"Point","coordinates":[-71.416700,43.200000]},"type":"Feature","properties":{"hierarchy":["tgn:2337413","tgn:1000001","tgn:2001425","tgn:7012149","tgn:7007564","tgn:7029392"],"placetype":["aat:300008699"],"id":2337413,"name:xx":"Fowler Brook"}}
>>>>>>> 03f74aca74312dbeaf24d7e61306dd6a786dc3d0
