{
  "id": 2463744,
  "type": "Feature",
  "properties": {
    "tgn:hierarchy":[
        "tgn:2463744",
        "tgn:1000001",
        "tgn:7012149",
        "tgn:2001858",
        "tgn:7007825",
        "tgn:7029392"
    ],
    "tgn:id":2463744,
    "tgn:name":"Locke Hollow",
    "tgn:placetype":[
        "aat:300008761"
    ]
},
  "bbox": [],
  "geometry": {"coordinates":[-87.4667,36.0333],"type":"Point"}
}