{
  "id": 7020158,
  "type": "Feature",
  "properties": {
    "tgn:hierarchy":[
        "tgn:7020158",
        "tgn:1000001",
        "tgn:2001473",
        "tgn:7012149",
        "tgn:7007709",
        "tgn:7029392"
    ],
    "tgn:id":7020158,
    "tgn:name":"High Hickory Knob",
    "tgn:placetype":[
        "aat:300008798"
    ]
},
  "bbox": [],
  "geometry": {"coordinates":[-82.3833,35.5667],"type":"Point"}
}