{
  "id": 2174956,
  "type": "Feature",
  "properties": {
    "tgn:hierarchy":[
        "tgn:2174956",
        "tgn:1000001",
        "tgn:7012149",
        "tgn:7013867",
        "tgn:7007710",
        "tgn:7029392"
    ],
    "tgn:id":2174956,
    "tgn:name":"Black Baron",
    "tgn:placetype":[
        "aat:300008347"
    ]
},
  "bbox": [],
  "geometry": {"coordinates":[-76.1833,39.7333],"type":"Point"}
}