{
  "id": 2548231,
  "type": "Feature",
  "properties": {
    "tgn:hierarchy":[
        "tgn:2548231",
        "tgn:1000001",
        "tgn:7012149",
        "tgn:2000348",
        "tgn:7007248",
        "tgn:7029392"
    ],
    "tgn:id":2548231,
    "tgn:name":"North Jones Lake",
    "tgn:placetype":[
        "aat:300006191"
    ]
},
  "bbox": [],
  "geometry": {"coordinates":[-85.25,34.1667],"type":"Point"}
}