{
  "id": 7452593,
  "type": "Feature",
  "properties": {
    "tgn:hierarchy":[
        "tgn:7452593",
        "tgn:7002445",
        "tgn:1000003",
        "tgn:7008153",
        "tgn:7008591",
        "tgn:7029392"
    ],
    "tgn:id":7452593,
    "tgn:name:en":"Goodwin Sands",
    "tgn:placetype":[
        "aat:300387036"
    ]
},
  "bbox": [],
  "geometry": {"coordinates":[1.583333,51.233333],"type":"Point"}
}