{
  "id": 7460478,
  "type": "Feature",
  "properties": {
    "tgn:hierarchy":[
        "tgn:7460478",
        "tgn:7002443",
        "tgn:1000003",
        "tgn:7018966",
        "tgn:7008591",
        "tgn:7029392"
    ],
    "tgn:id":7460478,
    "tgn:name:en":"Llysworney",
    "tgn:placetype":[
        "aat:300008347"
    ]
},
  "bbox": [],
  "geometry": {"coordinates":[-3.493333,51.456944],"type":"Point"}
}