{
  "id": 2753725,
  "type": "Feature",
  "properties": {
    "tgn:hierarchy":[
        "tgn:2753725",
        "tgn:1000001",
        "tgn:1002239",
        "tgn:7012149",
        "tgn:7007706",
        "tgn:7029392"
    ],
    "tgn:id":2753725,
    "tgn:name":"Watheys",
    "tgn:placetype":[
        "aat:300008347"
    ]
},
  "bbox": [],
  "geometry": {"coordinates":[-81.0167,40.65],"type":"Point"}
}