<<<<<<< HEAD
{
  "id": 7363738,
  "type": "Feature",
  "properties": {
    "tgn:hierarchy":[
        "tgn:7363738",
        "tgn:1000001",
        "tgn:1001960",
        "tgn:7005560",
        "tgn:7029392"
    ],
    "tgn:id":7363738,
    "tgn:name":"El Chinal",
    "tgn:placetype":[
        "aat:300008347"
    ]
},
  "bbox": [],
  "geometry": {"coordinates":[-108.7025,26.681667],"type":"Point"}
}
=======
{"geometry":{"type":"Point","coordinates":[-108.702500,26.681667]},"type":"Feature","properties":{"hierarchy":["tgn:7363738","tgn:1000001","tgn:1001960","tgn:7005560","tgn:7029392"],"placetype":["aat:300008347"],"id":7363738,"name:xx":"El Chinal"}}
>>>>>>> 03f74aca74312dbeaf24d7e61306dd6a786dc3d0
