<<<<<<< HEAD
{
  "id": 7486685,
  "type": "Feature",
  "properties": {
    "tgn:hierarchy":[
        "tgn:7486685",
        "tgn:7487020",
        "tgn:1000004",
        "tgn:1000141",
        "tgn:7029392"
    ],
    "tgn:id":7486685,
    "tgn:name":"Bajiaokeng",
    "tgn:placetype":[
        "aat:300008347"
    ]
},
  "bbox": [],
  "geometry": {"coordinates":[120.894215,24.479573],"type":"Point"}
}
=======
{"geometry":{"type":"Point","coordinates":[120.894215,24.479573]},"type":"Feature","properties":{"hierarchy":["tgn:7486685","tgn:7487020","tgn:1000004","tgn:1000141","tgn:7029392"],"placetype":["aat:300008347"],"id":7486685,"name:xx":"Bajiaokeng"}}
>>>>>>> 03f74aca74312dbeaf24d7e61306dd6a786dc3d0
