{
  "id": 7486685,
  "type": "Feature",
  "properties": {
    "tgn:hierarchy":[
        "tgn:7486685",
        "tgn:7487020",
        "tgn:1000004",
        "tgn:1000141",
        "tgn:7029392"
    ],
    "tgn:id":7486685,
    "tgn:name":"Bajiaokeng",
    "tgn:placetype":[
        "aat:300008347"
    ]
},
  "bbox": [],
  "geometry": {"coordinates":[120.894215,24.479573],"type":"Point"}
}