{
  "id": 7013994,
  "type": "Feature",
  "properties": {
    "tgn:hierarchy":[
        "tgn:7013994",
        "tgn:1000001",
        "tgn:7012149",
        "tgn:2002335",
        "tgn:7007922",
        "tgn:7029392"
    ],
    "tgn:id":7013994,
    "tgn:name":"Manitowoc",
    "tgn:placetype":[
        "aat:300008347",
        "aat:300008416",
        "aat:300008389",
        "aat:300264742",
        "aat:300387302",
        "aat:300120599"
    ]
},
  "bbox": [],
  "geometry": {"coordinates":[-87.65,44.0833],"type":"Point"}
}