{
  "id": 7515466,
  "type": "Feature",
  "properties": {
    "tgn:hierarchy":[
        "tgn:7515466",
        "tgn:1009227",
        "tgn:1000226",
        "tgn:7016822",
        "tgn:1000006",
        "tgn:7029392"
    ],
    "tgn:id":7515466,
    "tgn:name:en":"Only Islands",
    "tgn:placetype":[
        "aat:300008791"
    ]
},
  "bbox": [],
  "geometry": {"coordinates":[166.883333,-45.966667],"type":"Point"}
}