<<<<<<< HEAD
{
  "id": 7057391,
  "type": "Feature",
  "properties": {
    "tgn:hierarchy":[
        "tgn:7057391",
        "tgn:7009084",
        "tgn:7003000",
        "tgn:1000003",
        "tgn:1000080",
        "tgn:7029392"
    ],
    "tgn:id":7057391,
    "tgn:name":"Avello, Fiume",
    "tgn:placetype":[
        "aat:300008699"
    ]
},
  "bbox": [],
  "geometry": {"coordinates":[14.266667,42.116667],"type":"Point"}
}
=======
{"geometry":{"type":"Point","coordinates":[14.266667,42.116667]},"type":"Feature","properties":{"hierarchy":["tgn:7057391","tgn:7009084","tgn:7003000","tgn:1000003","tgn:1000080","tgn:7029392"],"placetype":["aat:300008699"],"id":7057391,"name:xx":"Avello, Fiume"}}
>>>>>>> 03f74aca74312dbeaf24d7e61306dd6a786dc3d0
