{
  "id": 2578674,
  "type": "Feature",
  "properties": {
    "tgn:hierarchy":[
        "tgn:2578674",
        "tgn:1000001",
        "tgn:7012149",
        "tgn:1003038",
        "tgn:7007517",
        "tgn:7029392"
    ],
    "tgn:id":2578674,
    "tgn:name":"Phillips Brook",
    "tgn:placetype":[
        "aat:300008699"
    ]
},
  "bbox": [],
  "geometry": {"coordinates":[-71.8333,42.5667],"type":"Point"}
}