{
  "id": 7110501,
  "type": "Feature",
  "properties": {
    "tgn:hierarchy":[
        "tgn:7110501",
        "tgn:7003692",
        "tgn:1000003",
        "tgn:7000084",
        "tgn:7029392"
    ],
    "tgn:id":7110501,
    "tgn:name":"Reichertshofen",
    "tgn:placetype":[
        "aat:300008347"
    ]
},
  "bbox": [],
  "geometry": {"coordinates":[9.95,48.916667],"type":"Point"}
}