<<<<<<< HEAD
{
  "id": 7020724,
  "type": "Feature",
  "properties": {
    "tgn:hierarchy":[
        "tgn:7020724",
        "tgn:1000001",
        "tgn:7016172",
        "tgn:7012149",
        "tgn:2000161",
        "tgn:7029392"
    ],
    "tgn:id":7020724,
    "tgn:name":"Hillcrest Lake",
    "tgn:placetype":[
        "aat:300008680",
        "aat:300006191"
    ]
},
  "bbox": [],
  "geometry": {"coordinates":[-94.2,34.6],"type":"Point"}
}
=======
{"geometry":{"type":"Point","coordinates":[-94.200000,34.600000]},"type":"Feature","properties":{"hierarchy":["tgn:7020724","tgn:1000001","tgn:7016172","tgn:7012149","tgn:2000161","tgn:7029392"],"placetype":["aat:300008680","aat:300006191"],"id":7020724,"name:xx":"Hillcrest Lake"}}
>>>>>>> 03f74aca74312dbeaf24d7e61306dd6a786dc3d0
