{
  "id": 2353696,
  "type": "Feature",
  "properties": {
    "tgn:hierarchy":[
        "tgn:2353696",
        "tgn:1000001",
        "tgn:7012149",
        "tgn:7007523",
        "tgn:7029392"
    ],
    "tgn:id":2353696,
    "tgn:name":"Gold Mine Hollow",
    "tgn:placetype":[
        "aat:300008761"
    ]
},
  "bbox": [],
  "geometry": {"coordinates":[-91.2167,36.85],"type":"Point"}
}