{
  "id": 1092980,
  "type": "Feature",
  "properties": {
    "tgn:hierarchy":[
        "tgn:1092980",
        "tgn:7001242",
        "tgn:7017583",
        "tgn:1000193",
        "tgn:7029392"
    ],
    "tgn:id":1092980,
    "tgn:name":"Cradock",
    "tgn:placetype":[
        "aat:300008347"
    ]
},
  "bbox": [],
  "geometry": {"coordinates":[25.6167,-32.1667],"type":"Point"}
}