{
  "id": 7083508,
  "type": "Feature",
  "properties": {
    "tgn:hierarchy":[
        "tgn:7083508",
        "tgn:1000003",
        "tgn:7003685",
        "tgn:7000084",
        "tgn:7029392"
    ],
    "tgn:id":7083508,
    "tgn:name":"Welsau",
    "tgn:placetype":[
        "aat:300008347"
    ]
},
  "bbox": [],
  "geometry": {"coordinates":[12.966667,51.583333],"type":"Point"}
}