{
  "id": 7534364,
  "type": "Feature",
  "properties": {
    "tgn:hierarchy":[
        "tgn:7534364",
        "tgn:7001242",
        "tgn:7001311",
        "tgn:7016833",
        "tgn:7029392"
    ],
    "tgn:id":7534364,
    "tgn:name:en":"J\u016bb\u0101l a\u015f \u015eagh\u012brah, Jaz\u012brat",
    "tgn:placetype":[
        "aat:300008791"
    ]
},
  "bbox": [],
  "geometry": {"coordinates":[33.795499,27.676067],"type":"Point"}
}