{
  "id": 2143792,
  "type": "Feature",
  "properties": {
    "tgn:hierarchy":[
        "tgn:2143792",
        "tgn:1000001",
        "tgn:7012149",
        "tgn:2001750",
        "tgn:7007712",
        "tgn:7029392"
    ],
    "tgn:id":2143792,
    "tgn:name":"Baker Bay",
    "tgn:placetype":[
        "aat:300008905"
    ]
},
  "bbox": [],
  "geometry": {"coordinates":[-78.65,33.8833],"type":"Point"}
}