{
  "id": 7549523,
  "type": "Feature",
  "properties": {
    "tgn:hierarchy":[
        "tgn:7549523",
        "tgn:1000004",
        "tgn:7000198",
        "tgn:7001797",
        "tgn:7029392"
    ],
    "tgn:id":7549523,
    "tgn:name:en":"Elavanas\u016br",
    "tgn:placetype":[
        "aat:300008347"
    ]
},
  "bbox": [],
  "geometry": {"coordinates":[79.183333,11.716667],"type":"Point"}
}