{
  "id": 2000151,
  "type": "Feature",
  "properties": {
    "tgn:hierarchy":[
        "tgn:2000151",
        "tgn:1000001",
        "tgn:7016172",
        "tgn:7012149",
        "tgn:7029392"
    ],
    "tgn:id":2000151,
    "tgn:name":"Mississippi",
    "tgn:placetype":[
        "aat:300387145",
        "aat:300000771"
    ]
},
  "bbox": [],
  "geometry": {"coordinates":[-90.05,35.7667],"type":"Point"}
}