{
  "id": 7040149,
  "type": "Feature",
  "properties": {
    "tgn:hierarchy":[
        "tgn:7040149",
        "tgn:1003460",
        "tgn:1000003",
        "tgn:7009760",
        "tgn:1000080",
        "tgn:7029392"
    ],
    "tgn:id":7040149,
    "tgn:name":"Scabbia, Torrente",
    "tgn:placetype":[
        "aat:300008699"
    ]
},
  "bbox": [],
  "geometry": {"coordinates":[11.583333,42.816667],"type":"Point"}
}