{
  "id": 2705316,
  "type": "Feature",
  "properties": {
    "tgn:hierarchy":[
        "tgn:2705316",
        "tgn:1000001",
        "tgn:2001419",
        "tgn:7012149",
        "tgn:7007526",
        "tgn:7029392"
    ],
    "tgn:id":2705316,
    "tgn:name":"Sure Thing Mine",
    "tgn:placetype":[
        "aat:300000390"
    ]
},
  "bbox": [],
  "geometry": {"coordinates":[-118.7833,40.45],"type":"Point"}
}