{
  "id": 2212849,
  "type": "Feature",
  "properties": {
    "tgn:hierarchy":[
        "tgn:2212849",
        "tgn:1000001",
        "tgn:7012149",
        "tgn:2001281",
        "tgn:7007524",
        "tgn:7029392"
    ],
    "tgn:id":2212849,
    "tgn:name":"C and D Mine",
    "tgn:placetype":[
        "aat:300000390"
    ]
},
  "bbox": [],
  "geometry": {"coordinates":[-111.9333,46.2833],"type":"Point"}
}