{
  "id": 2697472,
  "type": "Feature",
  "properties": {
    "tgn:hierarchy":[
        "tgn:2697472",
        "tgn:1000001",
        "tgn:2000955",
        "tgn:7012149",
        "tgn:7007520",
        "tgn:7029392"
    ],
    "tgn:id":2697472,
    "tgn:name":"Stony Point",
    "tgn:placetype":[
        "aat:300008850"
    ]
},
  "bbox": [],
  "geometry": {"coordinates":[-86.6333,45.8333],"type":"Point"}
}