<<<<<<< HEAD
{
  "id": 7170977,
  "type": "Feature",
  "properties": {
    "tgn:hierarchy":[
        "tgn:7170977",
        "tgn:1000003",
        "tgn:7003677",
        "tgn:7000084",
        "tgn:7029392"
    ],
    "tgn:id":7170977,
    "tgn:name":"Henken Teich",
    "tgn:placetype":[
        "aat:300008688"
    ]
},
  "bbox": [],
  "geometry": {"coordinates":[8.6,51.833333],"type":"Point"}
}
=======
{"geometry":{"type":"Point","coordinates":[8.600000,51.833333]},"type":"Feature","properties":{"hierarchy":["tgn:7170977","tgn:1000003","tgn:7003677","tgn:7000084","tgn:7029392"],"placetype":["aat:300008688"],"id":7170977,"name:xx":"Henken Teich"}}
>>>>>>> 03f74aca74312dbeaf24d7e61306dd6a786dc3d0
