{
  "id": 2626285,
  "type": "Feature",
  "properties": {
    "tgn:hierarchy":[
        "tgn:2626285",
        "tgn:1000001",
        "tgn:7012149",
        "tgn:7029392"
    ],
    "tgn:id":2626285,
    "tgn:name":"Rocky Face Mountain",
    "tgn:placetype":[
        "aat:300008798"
    ]
},
  "bbox": [],
  "geometry": {"coordinates":[-83.1833,35.7333],"type":"Point"}
}