{
  "id": 2345999,
  "type": "Feature",
  "properties": {
    "tgn:hierarchy":[
        "tgn:2345999",
        "tgn:1000001",
        "tgn:7012149",
        "tgn:2002112",
        "tgn:7007827",
        "tgn:7029392"
    ],
    "tgn:id":2345999,
    "tgn:name":"Gash Canyon",
    "tgn:placetype":[
        "aat:300008761"
    ]
},
  "bbox": [],
  "geometry": {"coordinates":[-113.9667,39.7833],"type":"Point"}
}