{
  "id": 2322138,
  "type": "Feature",
  "properties": {
    "tgn:hierarchy":[
        "tgn:2322138",
        "tgn:1000001",
        "tgn:7012149",
        "tgn:7007920",
        "tgn:7029392"
    ],
    "tgn:id":2322138,
    "tgn:name":"Fall Creek",
    "tgn:placetype":[
        "aat:300008706"
    ]
},
  "bbox": [],
  "geometry": {"coordinates":[-122.6333,46.75],"type":"Point"}
}