{
  "id": 7061799,
  "type": "Feature",
  "properties": {
    "tgn:hierarchy":[
        "tgn:7061799",
        "tgn:1000003",
        "tgn:7003682",
        "tgn:7000084",
        "tgn:7029392"
    ],
    "tgn:id":7061799,
    "tgn:name":"Arzheim",
    "tgn:placetype":[
        "aat:300008347"
    ]
},
  "bbox": [],
  "geometry": {"coordinates":[7.633333,50.35],"type":"Point"}
}