<<<<<<< HEAD
{
  "id": 2336595,
  "type": "Feature",
  "properties": {
    "tgn:hierarchy":[
        "tgn:2336595",
        "tgn:1000001",
        "tgn:7012149",
        "tgn:2001898",
        "tgn:7007825",
        "tgn:7029392"
    ],
    "tgn:id":2336595,
    "tgn:name":"Four Mile Creek Shoals",
    "tgn:placetype":[
        "aat:300132348"
    ]
},
  "bbox": [],
  "geometry": {"coordinates":[-84.1,35.55],"type":"Point"}
}
=======
{"geometry":{"type":"Point","coordinates":[-84.100000,35.550000]},"type":"Feature","properties":{"hierarchy":["tgn:2336595","tgn:1000001","tgn:7012149","tgn:2001898","tgn:7007825","tgn:7029392"],"placetype":["aat:300132348"],"id":2336595,"name:xx":"Four Mile Creek Shoals"}}
>>>>>>> 03f74aca74312dbeaf24d7e61306dd6a786dc3d0
