{
  "id": 2484242,
  "type": "Feature",
  "properties": {
    "tgn:hierarchy":[
        "tgn:2484242",
        "tgn:1000001",
        "tgn:7012149",
        "tgn:2000787",
        "tgn:7007255",
        "tgn:7029392"
    ],
    "tgn:id":2484242,
    "tgn:name":"Laurel Branch",
    "tgn:placetype":[
        "aat:300008699"
    ]
},
  "bbox": [],
  "geometry": {"coordinates":[-86.2333,37.1667],"type":"Point"}
}