{
  "id": 2414490,
  "type": "Feature",
  "properties": {
    "tgn:hierarchy":[
        "tgn:2414490",
        "tgn:1000001",
        "tgn:7012149",
        "tgn:1002314",
        "tgn:7007240",
        "tgn:7029392"
    ],
    "tgn:id":2414490,
    "tgn:name":"Irongrape Hammock",
    "tgn:placetype":[
        "aat:300008791"
    ]
},
  "bbox": [],
  "geometry": {"coordinates":[-80.65,25.6333],"type":"Point"}
}