{
  "id": 7484675,
  "type": "Feature",
  "properties": {
    "tgn:hierarchy":[
        "tgn:7484675",
        "tgn:7001004",
        "tgn:1000004",
        "tgn:1000141",
        "tgn:7029392"
    ],
    "tgn:id":7484675,
    "tgn:name":"Yuexian",
    "tgn:placetype":[
        "aat:300008347"
    ]
},
  "bbox": [],
  "geometry": {"coordinates":[120.696667,23.040833],"type":"Point"}
}