<<<<<<< HEAD
{
  "id": 2259546,
  "type": "Feature",
  "properties": {
    "tgn:hierarchy":[
        "tgn:2259546",
        "tgn:1000001",
        "tgn:7012149",
        "tgn:2000233",
        "tgn:7007158",
        "tgn:7029392"
    ],
    "tgn:id":2259546,
    "tgn:name":"Cottonwood Wash",
    "tgn:placetype":[
        "aat:300008761"
    ]
},
  "bbox": [],
  "geometry": {"coordinates":[-108.7833,37.2667],"type":"Point"}
}
=======
{"geometry":{"type":"Point","coordinates":[-108.783300,37.266700]},"type":"Feature","properties":{"hierarchy":["tgn:2259546","tgn:1000001","tgn:7012149","tgn:2000233","tgn:7007158","tgn:7029392"],"placetype":["aat:300008761"],"id":2259546,"name:xx":"Cottonwood Wash"}}
>>>>>>> 03f74aca74312dbeaf24d7e61306dd6a786dc3d0
