{
  "id": 2259546,
  "type": "Feature",
  "properties": {
    "tgn:hierarchy":[
        "tgn:2259546",
        "tgn:1000001",
        "tgn:7012149",
        "tgn:2000233",
        "tgn:7007158",
        "tgn:7029392"
    ],
    "tgn:id":2259546,
    "tgn:name":"Cottonwood Wash",
    "tgn:placetype":[
        "aat:300008761"
    ]
},
  "bbox": [],
  "geometry": {"coordinates":[-108.7833,37.2667],"type":"Point"}
}