<<<<<<< HEAD
{
  "id": 7247955,
  "type": "Feature",
  "properties": {
    "tgn:hierarchy":[
        "tgn:7247955",
        "tgn:7018239",
        "tgn:1000003",
        "tgn:1000063",
        "tgn:7018236",
        "tgn:7029392"
    ],
    "tgn:id":7247955,
    "tgn:name":"Ecluse, Ruisseau de L'",
    "tgn:placetype":[
        "aat:300008699"
    ]
},
  "bbox": [],
  "geometry": {"coordinates":[4.85,50.766667],"type":"Point"}
}
=======
{"geometry":{"type":"Point","coordinates":[4.850000,50.766667]},"type":"Feature","properties":{"hierarchy":["tgn:7247955","tgn:7018239","tgn:1000003","tgn:1000063","tgn:7018236","tgn:7029392"],"placetype":["aat:300008699"],"id":7247955,"name:xx":"Ecluse, Ruisseau de L'"}}
>>>>>>> 03f74aca74312dbeaf24d7e61306dd6a786dc3d0
