{
  "id": 2775676,
  "type": "Feature",
  "properties": {
    "tgn:hierarchy":[
        "tgn:2775676",
        "tgn:2000452",
        "tgn:1000001",
        "tgn:7012149",
        "tgn:7007250",
        "tgn:7029392"
    ],
    "tgn:id":2775676,
    "tgn:name":"Wilson Fruit Lateral",
    "tgn:placetype":[
        "aat:300006075"
    ]
},
  "bbox": [],
  "geometry": {"coordinates":[-116.3167,43.5833],"type":"Point"}
}