{
  "id": 2488621,
  "type": "Feature",
  "properties": {
    "tgn:hierarchy":[
        "tgn:2488621",
        "tgn:1000001",
        "tgn:2001025",
        "tgn:7012149",
        "tgn:7007521",
        "tgn:7029392"
    ],
    "tgn:id":2488621,
    "tgn:name":"Mahpiyata Island",
    "tgn:placetype":[
        "aat:300008791"
    ]
},
  "bbox": [],
  "geometry": {"coordinates":[-93.5667,44.9167],"type":"Point"}
}