{
  "id": 2426205,
  "type": "Feature",
  "properties": {
    "tgn:hierarchy":[
        "tgn:2426205",
        "tgn:1000001",
        "tgn:2002109",
        "tgn:7012149",
        "tgn:7007827",
        "tgn:7029392"
    ],
    "tgn:id":2426205,
    "tgn:name":"Jones Corral Spring",
    "tgn:placetype":[
        "aat:300008697"
    ]
},
  "bbox": [],
  "geometry": {"coordinates":[-112.1667,38.0667],"type":"Point"}
}