{
  "id": 2180947,
  "type": "Feature",
  "properties": {
    "tgn:hierarchy":[
        "tgn:2180947",
        "tgn:1000001",
        "tgn:7012149",
        "tgn:2001686",
        "tgn:7007707",
        "tgn:7029392"
    ],
    "tgn:id":2180947,
    "tgn:name":"Blowout Hollow",
    "tgn:placetype":[
        "aat:300008761"
    ]
},
  "bbox": [],
  "geometry": {"coordinates":[-95.5167,34.45],"type":"Point"}
}