<<<<<<< HEAD
{
  "id": 2765750,
  "type": "Feature",
  "properties": {
    "tgn:hierarchy":[
        "tgn:2765750",
        "tgn:1000001",
        "tgn:7012149",
        "tgn:2000342",
        "tgn:7007248",
        "tgn:7029392"
    ],
    "tgn:id":2765750,
    "tgn:name":"White Deer Branch",
    "tgn:placetype":[
        "aat:300008699"
    ]
},
  "bbox": [],
  "geometry": {"coordinates":[-81.3333,32.3333],"type":"Point"}
}
=======
{"geometry":{"type":"Point","coordinates":[-81.333300,32.333300]},"type":"Feature","properties":{"hierarchy":["tgn:2765750","tgn:1000001","tgn:7012149","tgn:2000342","tgn:7007248","tgn:7029392"],"placetype":["aat:300008699"],"id":2765750,"name:xx":"White Deer Branch"}}
>>>>>>> 03f74aca74312dbeaf24d7e61306dd6a786dc3d0
