{
  "id": 2040607,
  "type": "Feature",
  "properties": {
    "tgn:hierarchy":[
        "tgn:2040607",
        "tgn:1000001",
        "tgn:7012149",
        "tgn:1002887",
        "tgn:7007255",
        "tgn:7029392"
    ],
    "tgn:id":2040607,
    "tgn:name":"Olive Branch",
    "tgn:placetype":[
        "aat:300008347",
        "aat:300387210"
    ]
},
  "bbox": [],
  "geometry": {"coordinates":[-85.25,38.1167],"type":"Point"}
}