{
  "id": 2365659,
  "type": "Feature",
  "properties": {
    "tgn:hierarchy":[
        "tgn:2365659",
        "tgn:1000001",
        "tgn:1002480",
        "tgn:7012149",
        "tgn:7007564",
        "tgn:7029392"
    ],
    "tgn:id":2365659,
    "tgn:name":"Gregg Lake",
    "tgn:placetype":[
        "aat:300008680"
    ]
},
  "bbox": [],
  "geometry": {"coordinates":[-71.9833,43.0333],"type":"Point"}
}