<<<<<<< HEAD
{
  "id": 2255315,
  "type": "Feature",
  "properties": {
    "tgn:hierarchy":[
        "tgn:2255315",
        "tgn:1000001",
        "tgn:7012149",
        "tgn:2002160",
        "tgn:7007919",
        "tgn:7029392"
    ],
    "tgn:id":2255315,
    "tgn:name":"Coopers Cove",
    "tgn:placetype":[
        "aat:300008347"
    ]
},
  "bbox": [],
  "geometry": {"coordinates":[-79.85,37.2],"type":"Point"}
}
=======
{"geometry":{"type":"Point","coordinates":[-79.850000,37.200000]},"type":"Feature","properties":{"hierarchy":["tgn:2255315","tgn:1000001","tgn:7012149","tgn:2002160","tgn:7007919","tgn:7029392"],"placetype":["aat:300008347"],"id":2255315,"name:xx":"Coopers Cove"}}
>>>>>>> 03f74aca74312dbeaf24d7e61306dd6a786dc3d0
