{
  "id": 2229107,
  "type": "Feature",
  "properties": {
    "tgn:hierarchy":[
        "tgn:2229107",
        "tgn:1000001",
        "tgn:7012149",
        "tgn:2002125",
        "tgn:7007827",
        "tgn:7029392"
    ],
    "tgn:id":2229107,
    "tgn:name":"Cedar Knoll",
    "tgn:placetype":[
        "aat:300008798"
    ]
},
  "bbox": [],
  "geometry": {"coordinates":[-111.4667,39.8667],"type":"Point"}
}