{
  "id": 2583323,
  "type": "Feature",
  "properties": {
    "tgn:hierarchy":[
        "tgn:2583323",
        "tgn:1000001",
        "tgn:7012149",
        "tgn:2002127",
        "tgn:7007827",
        "tgn:7029392"
    ],
    "tgn:id":2583323,
    "tgn:name":"Pine Mountain",
    "tgn:placetype":[
        "aat:300008798"
    ]
},
  "bbox": [],
  "geometry": {"coordinates":[-114.0333,37.5833],"type":"Point"}
}