{
  "id": 7421136,
  "type": "Feature",
  "properties": {
    "tgn:hierarchy":[
        "tgn:7421136",
        "tgn:7005579",
        "tgn:1000001",
        "tgn:7005560",
        "tgn:7029392"
    ],
    "tgn:id":7421136,
    "tgn:name":"Puerta de Coyote",
    "tgn:placetype":[
        "aat:300008347"
    ]
},
  "bbox": [],
  "geometry": {"coordinates":[-102.608333,21.795833],"type":"Point"}
}