{
  "id": 7328987,
  "type": "Feature",
  "properties": {
    "tgn:hierarchy":[
        "tgn:7328987",
        "tgn:7002820",
        "tgn:7030216",
        "tgn:1000003",
        "tgn:1000095",
        "tgn:7029392"
    ],
    "tgn:id":7328987,
    "tgn:name":"Purtal\u00f3, Isla",
    "tgn:placetype":[
        "aat:300008791"
    ]
},
  "bbox": [],
  "geometry": {"coordinates":[3.28576,42.332762],"type":"Point"}
}