{
  "id": 7365567,
  "type": "Feature",
  "properties": {
    "tgn:hierarchy":[
        "tgn:7365567",
        "tgn:7005581",
        "tgn:1000001",
        "tgn:7005560",
        "tgn:7029392"
    ],
    "tgn:id":7365567,
    "tgn:name":"Encino, Arroyo del",
    "tgn:placetype":[
        "aat:300266554",
        "aat:300008699"
    ]
},
  "bbox": [],
  "geometry": {"coordinates":[-107.95,30.683333],"type":"Point"}
}