{
  "id": 1050534,
  "type": "Feature",
  "properties": {
    "tgn:hierarchy":[
        "tgn:1050534",
        "tgn:7002444",
        "tgn:1000003",
        "tgn:7008082",
        "tgn:7008591",
        "tgn:7029392"
    ],
    "tgn:id":1050534,
    "tgn:name":"Coldbackie",
    "tgn:placetype":[
        "aat:300008347"
    ]
},
  "bbox": [],
  "geometry": {"coordinates":[-4.3833,58.4833],"type":"Point"}
}