{
  "id": 2242585,
  "type": "Feature",
  "properties": {
    "tgn:hierarchy":[
        "tgn:2242585",
        "tgn:1000001",
        "tgn:7012149",
        "tgn:7007158",
        "tgn:2000247",
        "tgn:7029392"
    ],
    "tgn:id":2242585,
    "tgn:name":"Clear Creek",
    "tgn:placetype":[
        "aat:300008706"
    ]
},
  "bbox": [],
  "geometry": {"coordinates":[-107.7667,37.8167],"type":"Point"}
}