{
  "id": 7456112,
  "type": "Feature",
  "properties": {
    "tgn:hierarchy":[
        "tgn:7456112",
        "tgn:7002448",
        "tgn:7008700",
        "tgn:1000003",
        "tgn:7008591",
        "tgn:7029392"
    ],
    "tgn:id":7456112,
    "tgn:name:en":"Dromore Castle",
    "tgn:placetype":[
        "aat:300387502"
    ]
},
  "bbox": [],
  "geometry": {"coordinates":[-9.716667,51.866667],"type":"Point"}
}