{
  "id": 2443274,
  "type": "Feature",
  "properties": {
    "tgn:hierarchy":[
        "tgn:2443274",
        "tgn:1000001",
        "tgn:7012149",
        "tgn:2001919",
        "tgn:7007825",
        "tgn:7029392"
    ],
    "tgn:id":2443274,
    "tgn:name":"L A Green Lake",
    "tgn:placetype":[
        "aat:300006191"
    ]
},
  "bbox": [],
  "geometry": {"coordinates":[-86.4833,36.35],"type":"Point"}
}