{
  "id": 2248505,
  "type": "Feature",
  "properties": {
    "tgn:hierarchy":[
        "tgn:2248505",
        "tgn:1002996",
        "tgn:1000001",
        "tgn:7012149",
        "tgn:7007711",
        "tgn:7029392"
    ],
    "tgn:id":2248505,
    "tgn:name":"Cold Spring Beach",
    "tgn:placetype":[
        "aat:300008347"
    ]
},
  "bbox": [],
  "geometry": {"coordinates":[-71.4333,41.55],"type":"Point"}
}