{
  "id": 7157378,
  "type": "Feature",
  "properties": {
    "tgn:hierarchy":[
        "tgn:7157378",
        "tgn:7003669",
        "tgn:1000003",
        "tgn:7000084",
        "tgn:7029392"
    ],
    "tgn:id":7157378,
    "tgn:name":"Kay",
    "tgn:placetype":[
        "aat:300008347"
    ]
},
  "bbox": [],
  "geometry": {"coordinates":[12.75,48.05],"type":"Point"}
}