{
  "id": 2436290,
  "type": "Feature",
  "properties": {
    "tgn:hierarchy":[
        "tgn:2436290",
        "tgn:7006450",
        "tgn:1000001",
        "tgn:7012149",
        "tgn:7030574",
        "tgn:7029392"
    ],
    "tgn:id":2436290,
    "tgn:name":"Khantaak Island",
    "tgn:placetype":[
        "aat:300008791"
    ]
},
  "bbox": [],
  "geometry": {"coordinates":[-139.75,59.5833],"type":"Point"}
}