{
  "id": 2485082,
  "type": "Feature",
  "properties": {
    "tgn:hierarchy":[
        "tgn:2485082",
        "tgn:1000001",
        "tgn:2001410",
        "tgn:7012149",
        "tgn:7007526",
        "tgn:7029392"
    ],
    "tgn:id":2485082,
    "tgn:name":"Lavina Mine",
    "tgn:placetype":[
        "aat:300000390"
    ]
},
  "bbox": [],
  "geometry": {"coordinates":[-115.4667,35.8333],"type":"Point"}
}