<<<<<<< HEAD
{
  "id": 2403392,
  "type": "Feature",
  "properties": {
    "tgn:hierarchy":[
        "tgn:2403392",
        "tgn:1000001",
        "tgn:7012149",
        "tgn:2001524",
        "tgn:7007709",
        "tgn:7029392"
    ],
    "tgn:id":2403392,
    "tgn:name":"Houston Heights",
    "tgn:placetype":[
        "aat:300008347"
    ]
},
  "bbox": [],
  "geometry": {"coordinates":[-77.4167,34.7667],"type":"Point"}
}
=======
{"geometry":{"type":"Point","coordinates":[-77.416700,34.766700]},"type":"Feature","properties":{"hierarchy":["tgn:2403392","tgn:1000001","tgn:7012149","tgn:2001524","tgn:7007709","tgn:7029392"],"placetype":["aat:300008347"],"id":2403392,"name:xx":"Houston Heights"}}
>>>>>>> 03f74aca74312dbeaf24d7e61306dd6a786dc3d0
