{
  "id": 2501102,
  "type": "Feature",
  "properties": {
    "tgn:hierarchy":[
        "tgn:2501102",
        "tgn:1000001",
        "tgn:7012149",
        "tgn:7007709",
        "tgn:7029392"
    ],
    "tgn:id":2501102,
    "tgn:name":"McGee Creek",
    "tgn:placetype":[
        "aat:300008706"
    ]
},
  "bbox": [],
  "geometry": {"coordinates":[-78.4833,36.1167],"type":"Point"}
}