{
  "id": 1029210,
  "type": "Feature",
  "properties": {
    "tgn:hierarchy":[
        "tgn:1029210",
        "tgn:7002445",
        "tgn:1000003",
        "tgn:7008160",
        "tgn:7008591",
        "tgn:7029392"
    ],
    "tgn:id":1029210,
    "tgn:name":"Fakenham",
    "tgn:placetype":[
        "aat:300008347",
        "aat:300008375"
    ]
},
  "bbox": [],
  "geometry": {"coordinates":[0.833333,52.833333],"type":"Point"}
}