{
  "id": 1090355,
  "type": "Feature",
  "properties": {
    "tgn:hierarchy":[
        "tgn:1090355",
        "tgn:7001242",
        "tgn:1000613",
        "tgn:1000168",
        "tgn:7029392"
    ],
    "tgn:id":1090355,
    "tgn:name":"Guib\u00e9roua",
    "tgn:placetype":[
        "aat:300008347"
    ]
},
  "bbox": [],
  "geometry": {"coordinates":[-6.1667,6.2333],"type":"Point"}
}