<<<<<<< HEAD
{
  "id": 7245390,
  "type": "Feature",
  "properties": {
    "tgn:hierarchy":[
        "tgn:7245390",
        "tgn:7003460",
        "tgn:1000003",
        "tgn:1000063",
        "tgn:4012014",
        "tgn:7029392"
    ],
    "tgn:id":7245390,
    "tgn:name":"Al Hesse",
    "tgn:placetype":[
        "aat:300008347"
    ]
},
  "bbox": [],
  "geometry": {"coordinates":[5.85,50.283333],"type":"Point"}
}
=======
{"geometry":{"type":"Point","coordinates":[5.850000,50.283333]},"type":"Feature","properties":{"hierarchy":["tgn:7245390","tgn:7003460","tgn:1000003","tgn:1000063","tgn:4012014","tgn:7029392"],"placetype":["aat:300008347"],"id":7245390,"name:xx":"Al Hesse"}}
>>>>>>> 03f74aca74312dbeaf24d7e61306dd6a786dc3d0
