{
  "id": 7046235,
  "type": "Feature",
  "properties": {
    "tgn:hierarchy":[
        "tgn:7046235",
        "tgn:7003170",
        "tgn:1000003",
        "tgn:7003125",
        "tgn:1000080",
        "tgn:7029392"
    ],
    "tgn:id":7046235,
    "tgn:name":"Fionchi, Monte",
    "tgn:placetype":[
        "aat:300008795"
    ]
},
  "bbox": [],
  "geometry": {"coordinates":[12.766667,42.666667],"type":"Point"}
}