{
  "id": 1077719,
  "type": "Feature",
  "properties": {
    "tgn:hierarchy":[
        "tgn:1077719",
        "tgn:1009872",
        "tgn:1009718",
        "tgn:1000004",
        "tgn:1001409",
        "tgn:1000116",
        "tgn:7029392"
    ],
    "tgn:id":1077719,
    "tgn:name":"Ilwaki",
    "tgn:placetype":[
        "aat:300008347"
    ]
},
  "bbox": [],
  "geometry": {"coordinates":[126.4333,-7.9333],"type":"Point"}
}