{
  "id": 2451278,
  "type": "Feature",
  "properties": {
    "tgn:hierarchy":[
        "tgn:2451278",
        "tgn:1000001",
        "tgn:7012149",
        "tgn:2000217",
        "tgn:7007158",
        "tgn:7029392"
    ],
    "tgn:id":2451278,
    "tgn:name":"Little Baldy",
    "tgn:placetype":[
        "aat:300008798"
    ]
},
  "bbox": [],
  "geometry": {"coordinates":[-106.4667,38.5667],"type":"Point"}
}