{
  "id": 2116157,
  "type": "Feature",
  "properties": {
    "tgn:hierarchy":[
        "tgn:2116157",
        "tgn:1000001",
        "tgn:7012149",
        "tgn:2002248",
        "tgn:7007920",
        "tgn:7029392"
    ],
    "tgn:id":2116157,
    "tgn:name":"Locke",
    "tgn:placetype":[
        "aat:300008347",
        "aat:300387210"
    ]
},
  "bbox": [],
  "geometry": {"coordinates":[-117.3167,48.4167],"type":"Point"}
}