<<<<<<< HEAD
{
  "id": 7480815,
  "type": "Feature",
  "properties": {
    "tgn:hierarchy":[
        "tgn:7480815",
        "tgn:1000004",
        "tgn:1000454",
        "tgn:1000141",
        "tgn:7029392"
    ],
    "tgn:id":7480815,
    "tgn:name":"Jueming Si",
    "tgn:placetype":[
        "aat:300007595"
    ]
},
  "bbox": [],
  "geometry": {"coordinates":[121.447355,25.032386],"type":"Point"}
}
=======
{"geometry":{"type":"Point","coordinates":[121.447355,25.032386]},"type":"Feature","properties":{"hierarchy":["tgn:7480815","tgn:1000004","tgn:1000454","tgn:1000141","tgn:7029392"],"placetype":["aat:300007595"],"id":7480815,"name:xx":"Jueming Si"}}
>>>>>>> 03f74aca74312dbeaf24d7e61306dd6a786dc3d0
