{
  "id": 7480815,
  "type": "Feature",
  "properties": {
    "tgn:hierarchy":[
        "tgn:7480815",
        "tgn:1000004",
        "tgn:1000454",
        "tgn:1000141",
        "tgn:7029392"
    ],
    "tgn:id":7480815,
    "tgn:name":"Jueming Si",
    "tgn:placetype":[
        "aat:300007595"
    ]
},
  "bbox": [],
  "geometry": {"coordinates":[121.447355,25.032386],"type":"Point"}
}