{
  "id": 7452647,
  "type": "Feature",
  "properties": {
    "tgn:hierarchy":[
        "tgn:7452647",
        "tgn:7002444",
        "tgn:1000003",
        "tgn:7029508",
        "tgn:7008591",
        "tgn:7029392"
    ],
    "tgn:id":7452647,
    "tgn:name:en":"Fora Ness",
    "tgn:placetype":[
        "aat:300008804"
    ]
},
  "bbox": [],
  "geometry": {"coordinates":[-1.366667,60.183333],"type":"Point"}
}