{
  "id": 7239587,
  "type": "Feature",
  "properties": {
    "tgn:hierarchy":[
        "tgn:7239587",
        "tgn:7003456",
        "tgn:1000003",
        "tgn:1000063",
        "tgn:7018236",
        "tgn:7029392"
    ],
    "tgn:id":7239587,
    "tgn:name":"Heidelo",
    "tgn:placetype":[
        "aat:300008347"
    ]
},
  "bbox": [],
  "geometry": {"coordinates":[4.732757,51.056741],"type":"Point"}
}