{
  "id": 2564676,
  "type": "Feature",
  "properties": {
    "tgn:hierarchy":[
        "tgn:2564676",
        "tgn:1000001",
        "tgn:7006451",
        "tgn:2000094",
        "tgn:7012149",
        "tgn:7029392"
    ],
    "tgn:id":2564676,
    "tgn:name":"Packwood Canyon",
    "tgn:placetype":[
        "aat:300008761"
    ]
},
  "bbox": [],
  "geometry": {"coordinates":[-110.3167,33.0333],"type":"Point"}
}