{
  "id": 7394277,
  "type": "Feature",
  "properties": {
    "tgn:hierarchy":[
        "tgn:7394277",
        "tgn:7005580",
        "tgn:1000001",
        "tgn:7005560",
        "tgn:7029392"
    ],
    "tgn:id":7394277,
    "tgn:name":"San Caralampio de las Palmas",
    "tgn:placetype":[
        "aat:300008347"
    ]
},
  "bbox": [],
  "geometry": {"coordinates":[-92.033333,15.933333],"type":"Point"}
}