{
  "id": 7075150,
  "type": "Feature",
  "properties": {
    "tgn:hierarchy":[
        "tgn:7075150",
        "tgn:7003669",
        "tgn:1000003",
        "tgn:7000084",
        "tgn:7029392"
    ],
    "tgn:id":7075150,
    "tgn:name":"Daxenthal",
    "tgn:placetype":[
        "aat:300008347"
    ]
},
  "bbox": [],
  "geometry": {"coordinates":[12.85,48.233333],"type":"Point"}
}