{
  "id": 7535108,
  "type": "Feature",
  "properties": {
    "tgn:hierarchy":[
        "tgn:7535108",
        "tgn:7001242",
        "tgn:7016833",
        "tgn:7000124",
        "tgn:7029392"
    ],
    "tgn:id":7535108,
    "tgn:name:en":"Kawm Badd\u0101r",
    "tgn:placetype":[
        "aat:300008347"
    ]
},
  "bbox": [],
  "geometry": {"coordinates":[31.732282,26.45438],"type":"Point"}
}