{
  "id": 1102174,
  "type": "Feature",
  "properties": {
    "tgn:hierarchy":[
        "tgn:1102174",
        "tgn:1000001",
        "tgn:1002189",
        "tgn:7012149",
        "tgn:7007255",
        "tgn:7029392"
    ],
    "tgn:id":1102174,
    "tgn:name":"Big Bone Lick State Park",
    "tgn:placetype":[
        "aat:300008192"
    ]
},
  "bbox": [],
  "geometry": {"coordinates":[-84.75,38.8833],"type":"Point"}
}