{
  "id": 2444807,
  "type": "Feature",
  "properties": {
    "tgn:hierarchy":[
        "tgn:2444807",
        "tgn:1000001",
        "tgn:2000470",
        "tgn:7012149",
        "tgn:7007250",
        "tgn:7029392"
    ],
    "tgn:id":2444807,
    "tgn:name":"Lehman Basin",
    "tgn:placetype":[
        "aat:300386845"
    ]
},
  "bbox": [],
  "geometry": {"coordinates":[-113.85,43.9333],"type":"Point"}
}