{
  "id": 1084391,
  "type": "Feature",
  "properties": {
    "tgn:hierarchy":[
        "tgn:1084391",
        "tgn:1001064",
        "tgn:1000004",
        "tgn:1000135",
        "tgn:7029392"
    ],
    "tgn:id":1084391,
    "tgn:name":"Magsaysay",
    "tgn:placetype":[
        "aat:300008347"
    ]
},
  "bbox": [],
  "geometry": {"coordinates":[125.1667,9.0167],"type":"Point"}
}