{
  "id": 7067833,
  "type": "Feature",
  "properties": {
    "tgn:hierarchy":[
        "tgn:7067833",
        "tgn:7003692",
        "tgn:1000003",
        "tgn:7000084",
        "tgn:7029392"
    ],
    "tgn:id":7067833,
    "tgn:name":"Torpenbach",
    "tgn:placetype":[
        "aat:300008699"
    ]
},
  "bbox": [],
  "geometry": {"coordinates":[9.25,47.733333],"type":"Point"}
}