{
  "id": 2073048,
  "type": "Feature",
  "properties": {
    "tgn:hierarchy":[
        "tgn:2073048",
        "tgn:1000001",
        "tgn:7012149",
        "tgn:1002926",
        "tgn:7007568",
        "tgn:7029392"
    ],
    "tgn:id":2073048,
    "tgn:name":"Westbrookville",
    "tgn:placetype":[
        "aat:300008347"
    ]
},
  "bbox": [],
  "geometry": {"coordinates":[-74.55,41.4833],"type":"Point"}
}