{
  "id": 2512131,
  "type": "Feature",
  "properties": {
    "tgn:hierarchy":[
        "tgn:2512131",
        "tgn:1000001",
        "tgn:7012149",
        "tgn:2001549",
        "tgn:7007709",
        "tgn:7029392"
    ],
    "tgn:id":2512131,
    "tgn:name":"Mill Branch",
    "tgn:placetype":[
        "aat:300008699"
    ]
},
  "bbox": [],
  "geometry": {"coordinates":[-78.0833,36.35],"type":"Point"}
}