{
  "id": 2157689,
  "type": "Feature",
  "properties": {
    "tgn:hierarchy":[
        "tgn:2157689",
        "tgn:1000001",
        "tgn:7012149",
        "tgn:2002120",
        "tgn:7007827",
        "tgn:7029392"
    ],
    "tgn:id":2157689,
    "tgn:name":"Beaver Dam Reservoir",
    "tgn:placetype":[
        "aat:300006191"
    ]
},
  "bbox": [],
  "geometry": {"coordinates":[-111.2833,39.65],"type":"Point"}
}