{
  "id": 2416450,
  "type": "Feature",
  "properties": {
    "tgn:hierarchy":[
        "tgn:2416450",
        "tgn:1000001",
        "tgn:7012149",
        "tgn:1002314",
        "tgn:7007240",
        "tgn:7029392"
    ],
    "tgn:id":2416450,
    "tgn:name":"Jack Clay Hammock",
    "tgn:placetype":[
        "aat:300008791"
    ]
},
  "bbox": [],
  "geometry": {"coordinates":[-80.8167,25.85],"type":"Point"}
}