{
  "id": 7287070,
  "type": "Feature",
  "properties": {
    "tgn:hierarchy":[
        "tgn:7287070",
        "tgn:1001702",
        "tgn:1000049",
        "tgn:1000002",
        "tgn:7029392"
    ],
    "tgn:id":7287070,
    "tgn:name":"Graves, Cabo",
    "tgn:placetype":[
        "aat:300386846"
    ]
},
  "bbox": [],
  "geometry": {"coordinates":[-71.966667,-52.566667],"type":"Point"}
}