<<<<<<< HEAD
{
  "id": 2339377,
  "type": "Feature",
  "properties": {
    "tgn:hierarchy":[
        "tgn:2339377",
        "tgn:1000001",
        "tgn:7012149",
        "tgn:7007157",
        "tgn:1002972",
        "tgn:7029392"
    ],
    "tgn:id":2339377,
    "tgn:name":"Frazier Creek",
    "tgn:placetype":[
        "aat:300008706"
    ]
},
  "bbox": [],
  "geometry": {"coordinates":[-118.9333,34.65],"type":"Point"}
}
=======
{"geometry":{"type":"Point","coordinates":[-118.933300,34.650000]},"type":"Feature","properties":{"hierarchy":["tgn:2339377","tgn:1000001","tgn:7012149","tgn:7007157","tgn:1002972","tgn:7029392"],"placetype":["aat:300008706"],"id":2339377,"name:xx":"Frazier Creek"}}
>>>>>>> 03f74aca74312dbeaf24d7e61306dd6a786dc3d0
