{
  "id": 2339377,
  "type": "Feature",
  "properties": {
    "tgn:hierarchy":[
        "tgn:2339377",
        "tgn:1000001",
        "tgn:7012149",
        "tgn:7007157",
        "tgn:1002972",
        "tgn:7029392"
    ],
    "tgn:id":2339377,
    "tgn:name":"Frazier Creek",
    "tgn:placetype":[
        "aat:300008706"
    ]
},
  "bbox": [],
  "geometry": {"coordinates":[-118.9333,34.65],"type":"Point"}
}