<<<<<<< HEAD
{
  "id": 7054262,
  "type": "Feature",
  "properties": {
    "tgn:hierarchy":[
        "tgn:7054262",
        "tgn:7003134",
        "tgn:1000003",
        "tgn:7008516",
        "tgn:1000080",
        "tgn:7029392"
    ],
    "tgn:id":7054262,
    "tgn:name":"Ponte Vettigano",
    "tgn:placetype":[
        "aat:300008347"
    ]
},
  "bbox": [],
  "geometry": {"coordinates":[10.8,44.833333],"type":"Point"}
}
=======
{"geometry":{"type":"Point","coordinates":[10.800000,44.833333]},"type":"Feature","properties":{"hierarchy":["tgn:7054262","tgn:7003134","tgn:1000003","tgn:7008516","tgn:1000080","tgn:7029392"],"placetype":["aat:300008347"],"id":7054262,"name:xx":"Ponte Vettigano"}}
>>>>>>> 03f74aca74312dbeaf24d7e61306dd6a786dc3d0
