{
  "id": 2491101,
  "type": "Feature",
  "properties": {
    "tgn:hierarchy":[
        "tgn:2491101",
        "tgn:1000001",
        "tgn:7012149",
        "tgn:2000226",
        "tgn:7007158",
        "tgn:7029392"
    ],
    "tgn:id":2491101,
    "tgn:name":"Many Thunders Mountain",
    "tgn:placetype":[
        "aat:300008798"
    ]
},
  "bbox": [],
  "geometry": {"coordinates":[-105.55,40.8333],"type":"Point"}
}