{
  "id": 2069287,
  "type": "Feature",
  "properties": {
    "tgn:hierarchy":[
        "tgn:2069287",
        "tgn:1000001",
        "tgn:7012149",
        "tgn:1002423",
        "tgn:7007568",
        "tgn:7029392"
    ],
    "tgn:id":2069287,
    "tgn:name":"Freehold",
    "tgn:placetype":[
        "aat:300008347"
    ]
},
  "bbox": [],
  "geometry": {"coordinates":[-74.05,42.35],"type":"Point"}
}