{
  "id": 1091463,
  "type": "Feature",
  "properties": {
    "tgn:hierarchy":[
        "tgn:1091463",
        "tgn:7001242",
        "tgn:1000179",
        "tgn:7593686",
        "tgn:7029392"
    ],
    "tgn:id":1091463,
    "tgn:name":"Tinerhir",
    "tgn:placetype":[
        "aat:300008347"
    ]
},
  "bbox": [],
  "geometry": {"coordinates":[-5.5333,31.5167],"type":"Point"}
}