{
  "id": 2538413,
  "type": "Feature",
  "properties": {
    "tgn:hierarchy":[
        "tgn:2538413",
        "tgn:1000001",
        "tgn:2000264",
        "tgn:7012149",
        "tgn:7007240",
        "tgn:7029392"
    ],
    "tgn:id":2538413,
    "tgn:name":"Neptune, Lake",
    "tgn:placetype":[
        "aat:300008680"
    ]
},
  "bbox": [],
  "geometry": {"coordinates":[-81.3833,30.3167],"type":"Point"}
}