<<<<<<< HEAD
{
  "id": 2255482,
  "type": "Feature",
  "properties": {
    "tgn:hierarchy":[
        "tgn:2255482",
        "tgn:1000001",
        "tgn:7012149",
        "tgn:2001508",
        "tgn:7007709",
        "tgn:7029392"
    ],
    "tgn:id":2255482,
    "tgn:name":"Cope Creek",
    "tgn:placetype":[
        "aat:300008706"
    ]
},
  "bbox": [],
  "geometry": {"coordinates":[-83.15,35.3667],"type":"Point"}
}
=======
{"geometry":{"type":"Point","coordinates":[-83.150000,35.366700]},"type":"Feature","properties":{"hierarchy":["tgn:2255482","tgn:1000001","tgn:7012149","tgn:2001508","tgn:7007709","tgn:7029392"],"placetype":["aat:300008706"],"id":2255482,"name:xx":"Cope Creek"}}
>>>>>>> 03f74aca74312dbeaf24d7e61306dd6a786dc3d0
