{
  "id": 7365822,
  "type": "Feature",
  "properties": {
    "tgn:hierarchy":[
        "tgn:7365822",
        "tgn:1000001",
        "tgn:7005601",
        "tgn:7005560",
        "tgn:7029392"
    ],
    "tgn:id":7365822,
    "tgn:name":"Epazote",
    "tgn:placetype":[
        "aat:300008347"
    ]
},
  "bbox": [],
  "geometry": {"coordinates":[-101.883333,22.05],"type":"Point"}
}