<<<<<<< HEAD
{
  "id": 7365822,
  "type": "Feature",
  "properties": {
    "tgn:hierarchy":[
        "tgn:7365822",
        "tgn:1000001",
        "tgn:7005601",
        "tgn:7005560",
        "tgn:7029392"
    ],
    "tgn:id":7365822,
    "tgn:name":"Epazote",
    "tgn:placetype":[
        "aat:300008347"
    ]
},
  "bbox": [],
  "geometry": {"coordinates":[-101.883333,22.05],"type":"Point"}
}
=======
{"geometry":{"type":"Point","coordinates":[-101.883333,22.050000]},"type":"Feature","properties":{"hierarchy":["tgn:7365822","tgn:1000001","tgn:7005601","tgn:7005560","tgn:7029392"],"placetype":["aat:300008347"],"id":7365822,"name:xx":"Epazote"}}
>>>>>>> 03f74aca74312dbeaf24d7e61306dd6a786dc3d0
