{
  "id": 7229856,
  "type": "Feature",
  "properties": {
    "tgn:hierarchy":[
        "tgn:7229856",
        "tgn:7002725",
        "tgn:7002715",
        "tgn:1000003",
        "tgn:1000074",
        "tgn:7029392"
    ],
    "tgn:id":7229856,
    "tgn:name":"Er\u00edpia Kapnot\u00f3pou",
    "tgn:placetype":[
        "aat:300008057"
    ]
},
  "bbox": [],
  "geometry": {"coordinates":[23.383333,41.383333],"type":"Point"}
}