{
  "id": 2388114,
  "type": "Feature",
  "properties": {
    "tgn:hierarchy":[
        "tgn:2388114",
        "tgn:1000001",
        "tgn:2000504",
        "tgn:7012149",
        "tgn:7007251",
        "tgn:7029392"
    ],
    "tgn:id":2388114,
    "tgn:name":"Hickory Grove Creek",
    "tgn:placetype":[
        "aat:300008706"
    ]
},
  "bbox": [],
  "geometry": {"coordinates":[-87.8833,39.5333],"type":"Point"}
}