{
  "id": 2305005,
  "type": "Feature",
  "properties": {
    "tgn:hierarchy":[
        "tgn:2305005",
        "tgn:1000001",
        "tgn:7012149",
        "tgn:7007706",
        "tgn:7029392"
    ],
    "tgn:id":2305005,
    "tgn:name":"East Branch Huron River",
    "tgn:placetype":[
        "aat:300008707"
    ]
},
  "bbox": [],
  "geometry": {"coordinates":[-82.5333,41.0667],"type":"Point"}
}