{
  "id": 7502089,
  "type": "Feature",
  "properties": {
    "tgn:hierarchy":[
        "tgn:7502089",
        "tgn:1000004",
        "tgn:7001009",
        "tgn:1000141",
        "tgn:7029392"
    ],
    "tgn:id":7502089,
    "tgn:name":"Ludukeng",
    "tgn:placetype":[
        "aat:300008347"
    ]
},
  "bbox": [],
  "geometry": {"coordinates":[120.820088,24.095269],"type":"Point"}
}