{
  "id": 2025925,
  "type": "Feature",
  "properties": {
    "tgn:hierarchy":[
        "tgn:2025925",
        "tgn:1000001",
        "tgn:7012149",
        "tgn:2000486",
        "tgn:7007250",
        "tgn:7029392"
    ],
    "tgn:id":2025925,
    "tgn:name":"Myrtle",
    "tgn:placetype":[
        "aat:300008347"
    ]
},
  "bbox": [],
  "geometry": {"coordinates":[-116.7167,46.4833],"type":"Point"}
}