{
  "id": 2254109,
  "type": "Feature",
  "properties": {
    "tgn:hierarchy":[
        "tgn:2254109",
        "tgn:1000001",
        "tgn:7012149",
        "tgn:2000822",
        "tgn:7007255",
        "tgn:7029392"
    ],
    "tgn:id":2254109,
    "tgn:name":"Cooley Knob",
    "tgn:placetype":[
        "aat:300008798"
    ]
},
  "bbox": [],
  "geometry": {"coordinates":[-85.0333,37.5167],"type":"Point"}
}