{
  "id": 2180561,
  "type": "Feature",
  "properties": {
    "tgn:hierarchy":[
        "tgn:2180561",
        "tgn:1000001",
        "tgn:2124025",
        "tgn:7012149",
        "tgn:7007516",
        "tgn:7029392"
    ],
    "tgn:id":2180561,
    "tgn:name":"Bloody Point Creek",
    "tgn:placetype":[
        "aat:300132316"
    ]
},
  "bbox": [],
  "geometry": {"coordinates":[-76.3667,38.8333],"type":"Point"}
}