{
  "id": 7512179,
  "type": "Feature",
  "properties": {
    "tgn:hierarchy":[
        "tgn:7512179",
        "tgn:1009227",
        "tgn:1000226",
        "tgn:7018437",
        "tgn:1000006",
        "tgn:7029392"
    ],
    "tgn:id":7512179,
    "tgn:name:en":"Jacksons Creek",
    "tgn:placetype":[
        "aat:300008699"
    ]
},
  "bbox": [],
  "geometry": {"coordinates":[169.316667,-45.133333],"type":"Point"}
}