{
  "id": 7007107,
  "type": "Feature",
  "properties": {
    "tgn:hierarchy":[
        "tgn:7007107",
        "tgn:7002759",
        "tgn:7002845",
        "tgn:1000003",
        "tgn:1000095",
        "tgn:7029392"
    ],
    "tgn:id":7007107,
    "tgn:name":"Alag\u00f3n",
    "tgn:placetype":[
        "aat:300008347"
    ]
},
  "bbox": [],
  "geometry": {"coordinates":[-1.116667,41.766667],"type":"Point"}
}