{
  "id": 2356923,
  "type": "Feature",
  "properties": {
    "tgn:hierarchy":[
        "tgn:2356923",
        "tgn:1002933",
        "tgn:1000001",
        "tgn:7012149",
        "tgn:7007239",
        "tgn:7029392"
    ],
    "tgn:id":2356923,
    "tgn:name":"Goslee Mill Pond",
    "tgn:placetype":[
        "aat:300006191"
    ]
},
  "bbox": [],
  "geometry": {"coordinates":[-75.1833,38.7167],"type":"Point"}
}