{
  "id": 1074614,
  "type": "Feature",
  "properties": {
    "tgn:hierarchy":[
        "tgn:1074614",
        "tgn:1000004",
        "tgn:1001842",
        "tgn:7000198",
        "tgn:7029392"
    ],
    "tgn:id":1074614,
    "tgn:name:en":"Bakhtiy\u0101rpur",
    "tgn:placetype":[
        "aat:300008347"
    ]
},
  "bbox": [],
  "geometry": {"coordinates":[85.533009,25.459312],"type":"Point"}
}