{
  "id": 2172020,
  "type": "Feature",
  "properties": {
    "tgn:hierarchy":[
        "tgn:2172020",
        "tgn:1000001",
        "tgn:7012149",
        "tgn:2001872",
        "tgn:7007825",
        "tgn:7029392"
    ],
    "tgn:id":2172020,
    "tgn:name":"Bigbee Branch",
    "tgn:placetype":[
        "aat:300008699"
    ]
},
  "bbox": [],
  "geometry": {"coordinates":[-88.0333,35.25],"type":"Point"}
}