<<<<<<< HEAD
{
  "id": 7480058,
  "type": "Feature",
  "properties": {
    "tgn:hierarchy":[
        "tgn:7480058",
        "tgn:1000004",
        "tgn:7490934",
        "tgn:1000141",
        "tgn:7029392"
    ],
    "tgn:id":7480058,
    "tgn:name":"Jinjiangjun Miao",
    "tgn:placetype":[
        "aat:300007595"
    ]
},
  "bbox": [],
  "geometry": {"coordinates":[120.245278,23.025278],"type":"Point"}
}
=======
{"geometry":{"type":"Point","coordinates":[120.245278,23.025278]},"type":"Feature","properties":{"hierarchy":["tgn:7480058","tgn:1000004","tgn:7490934","tgn:1000141","tgn:7029392"],"placetype":["aat:300007595"],"id":7480058,"name:xx":"Jinjiangjun Miao"}}
>>>>>>> 03f74aca74312dbeaf24d7e61306dd6a786dc3d0
