{
  "id": 7480058,
  "type": "Feature",
  "properties": {
    "tgn:hierarchy":[
        "tgn:7480058",
        "tgn:1000004",
        "tgn:7490934",
        "tgn:1000141",
        "tgn:7029392"
    ],
    "tgn:id":7480058,
    "tgn:name":"Jinjiangjun Miao",
    "tgn:placetype":[
        "aat:300007595"
    ]
},
  "bbox": [],
  "geometry": {"coordinates":[120.245278,23.025278],"type":"Point"}
}