<<<<<<< HEAD
{
  "id": 2259314,
  "type": "Feature",
  "properties": {
    "tgn:hierarchy":[
        "tgn:2259314",
        "tgn:1000001",
        "tgn:7012149",
        "tgn:2000237",
        "tgn:7007158",
        "tgn:7029392"
    ],
    "tgn:id":2259314,
    "tgn:name":"Cottonwood Reservoir",
    "tgn:placetype":[
        "aat:300006191"
    ]
},
  "bbox": [],
  "geometry": {"coordinates":[-107.8833,38.2333],"type":"Point"}
}
=======
{"geometry":{"type":"Point","coordinates":[-107.883300,38.233300]},"type":"Feature","properties":{"hierarchy":["tgn:2259314","tgn:1000001","tgn:7012149","tgn:2000237","tgn:7007158","tgn:7029392"],"placetype":["aat:300006191"],"id":2259314,"name:xx":"Cottonwood Reservoir"}}
>>>>>>> 03f74aca74312dbeaf24d7e61306dd6a786dc3d0
