{
  "id": 7538010,
  "type": "Feature",
  "properties": {
    "tgn:hierarchy":[
        "tgn:7538010",
        "tgn:7001242",
        "tgn:7016833",
        "tgn:1001083",
        "tgn:7029392"
    ],
    "tgn:id":7538010,
    "tgn:name:en":"Nazlat al Ba\u0163r\u0101n",
    "tgn:placetype":[
        "aat:300008347"
    ]
},
  "bbox": [],
  "geometry": {"coordinates":[31.159045,29.97189],"type":"Point"}
}