{
  "id": 7560269,
  "type": "Feature",
  "properties": {
    "tgn:hierarchy":[
        "tgn:7560269",
        "tgn:1000004",
        "tgn:7000198",
        "tgn:7016722",
        "tgn:7029392"
    ],
    "tgn:id":7560269,
    "tgn:name:en":"Dharampur",
    "tgn:placetype":[
        "aat:300008347"
    ]
},
  "bbox": [],
  "geometry": {"coordinates":[79.695539,27.607008],"type":"Point"}
}