{
  "id": 7323101,
  "type": "Feature",
  "properties": {
    "tgn:hierarchy":[
        "tgn:7323101",
        "tgn:7008912",
        "tgn:7030216",
        "tgn:1000003",
        "tgn:1000095",
        "tgn:7029392"
    ],
    "tgn:id":7323101,
    "tgn:name":"Ruhos, Cap de",
    "tgn:placetype":[
        "aat:300008798"
    ]
},
  "bbox": [],
  "geometry": {"coordinates":[1.229228,42.728055],"type":"Point"}
}