{
  "id": 2432900,
  "type": "Feature",
  "properties": {
    "tgn:hierarchy":[
        "tgn:2432900",
        "tgn:1000001",
        "tgn:1002289",
        "tgn:7012149",
        "tgn:7007240",
        "tgn:7029392"
    ],
    "tgn:id":2432900,
    "tgn:name":"Keewaydin Island",
    "tgn:placetype":[
        "aat:300008791"
    ]
},
  "bbox": [],
  "geometry": {"coordinates":[-81.7667,26.0333],"type":"Point"}
}