{
  "id": 2739288,
  "type": "Feature",
  "properties": {
    "tgn:hierarchy":[
        "tgn:2739288",
        "tgn:1000001",
        "tgn:2000684",
        "tgn:7012149",
        "tgn:7007254",
        "tgn:7029392"
    ],
    "tgn:id":2739288,
    "tgn:name":"Upola",
    "tgn:placetype":[
        "aat:300008347"
    ]
},
  "bbox": [],
  "geometry": {"coordinates":[-95.9833,37.4167],"type":"Point"}
}