{
  "id": 2524234,
  "type": "Feature",
  "properties": {
    "tgn:hierarchy":[
        "tgn:2524234",
        "tgn:1000001",
        "tgn:7012149",
        "tgn:2001281",
        "tgn:7007524",
        "tgn:7029392"
    ],
    "tgn:id":2524234,
    "tgn:name":"Morgan Gulch",
    "tgn:placetype":[
        "aat:300008761"
    ]
},
  "bbox": [],
  "geometry": {"coordinates":[-112.1333,46.3833],"type":"Point"}
}