{
  "id": 2313904,
  "type": "Feature",
  "properties": {
    "tgn:hierarchy":[
        "tgn:2313904",
        "tgn:1000001",
        "tgn:7012149",
        "tgn:2002303",
        "tgn:7013961",
        "tgn:7029392"
    ],
    "tgn:id":2313904,
    "tgn:name":"Elijah Run",
    "tgn:placetype":[
        "aat:300008699"
    ]
},
  "bbox": [],
  "geometry": {"coordinates":[-81.6333,39.1833],"type":"Point"}
}