{
  "id": 2396814,
  "type": "Feature",
  "properties": {
    "tgn:hierarchy":[
        "tgn:2396814",
        "tgn:1000001",
        "tgn:2001738",
        "tgn:7012149",
        "tgn:7007712",
        "tgn:7029392"
    ],
    "tgn:id":2396814,
    "tgn:name":"Home Lake",
    "tgn:placetype":[
        "aat:300008680"
    ]
},
  "bbox": [],
  "geometry": {"coordinates":[-80.0333,33.7167],"type":"Point"}
}