{
  "id": 7224170,
  "type": "Feature",
  "properties": {
    "tgn:hierarchy":[
        "tgn:7224170",
        "tgn:7002728",
        "tgn:7002715",
        "tgn:1000003",
        "tgn:1000074",
        "tgn:7029392"
    ],
    "tgn:id":7224170,
    "tgn:name":"N\u00f3tia",
    "tgn:placetype":[
        "aat:300008347"
    ]
},
  "bbox": [],
  "geometry": {"coordinates":[22.2025,41.104167],"type":"Point"}
}