{
  "id": 2654535,
  "type": "Feature",
  "properties": {
    "tgn:hierarchy":[
        "tgn:2654535",
        "tgn:1000001",
        "tgn:7012149",
        "tgn:2002057",
        "tgn:7007826",
        "tgn:7029392"
    ],
    "tgn:id":2654535,
    "tgn:name":"Shafter Mine",
    "tgn:placetype":[
        "aat:300000390"
    ]
},
  "bbox": [],
  "geometry": {"coordinates":[-104.3167,29.8167],"type":"Point"}
}