{
  "id": 2411386,
  "type": "Feature",
  "properties": {
    "tgn:hierarchy":[
        "tgn:2411386",
        "tgn:1000001",
        "tgn:7012149",
        "tgn:2000476",
        "tgn:7007250",
        "tgn:7029392"
    ],
    "tgn:id":2411386,
    "tgn:name":"Indian Hill",
    "tgn:placetype":[
        "aat:300008798"
    ]
},
  "bbox": [],
  "geometry": {"coordinates":[-115.2333,45.9833],"type":"Point"}
}