{
  "id": 7295373,
  "type": "Feature",
  "properties": {
    "tgn:hierarchy":[
        "tgn:7295373",
        "tgn:7002839",
        "tgn:7001158",
        "tgn:1000003",
        "tgn:1000095",
        "tgn:7029392"
    ],
    "tgn:id":7295373,
    "tgn:name":"Zarzuela del Monte",
    "tgn:placetype":[
        "aat:300008347"
    ]
},
  "bbox": [],
  "geometry": {"coordinates":[-4.333333,40.816667],"type":"Point"}
}