{
  "id": 2510710,
  "type": "Feature",
  "properties": {
    "tgn:hierarchy":[
        "tgn:2510710",
        "tgn:1000001",
        "tgn:7012149",
        "tgn:7007157",
        "tgn:2000191",
        "tgn:7029392"
    ],
    "tgn:id":2510710,
    "tgn:name":"Middleton Gulch",
    "tgn:placetype":[
        "aat:300008761"
    ]
},
  "bbox": [],
  "geometry": {"coordinates":[-122.9667,40.55],"type":"Point"}
}