{
  "id": 7456305,
  "type": "Feature",
  "properties": {
    "tgn:hierarchy":[
        "tgn:7456305",
        "tgn:7002444",
        "tgn:1000003",
        "tgn:7008072",
        "tgn:7008591",
        "tgn:7029392"
    ],
    "tgn:id":7456305,
    "tgn:name:en":"Carlops",
    "tgn:placetype":[
        "aat:300008347"
    ]
},
  "bbox": [],
  "geometry": {"coordinates":[-3.333333,55.783333],"type":"Point"}
}