{
  "id": 7192778,
  "type": "Feature",
  "properties": {
    "tgn:hierarchy":[
        "tgn:7192778",
        "tgn:7003669",
        "tgn:1000003",
        "tgn:7000084",
        "tgn:7029392"
    ],
    "tgn:id":7192778,
    "tgn:name":"Failnbach",
    "tgn:placetype":[
        "aat:300008347"
    ]
},
  "bbox": [],
  "geometry": {"coordinates":[12.616667,48.533333],"type":"Point"}
}