{
  "id": 2502427,
  "type": "Feature",
  "properties": {
    "tgn:hierarchy":[
        "tgn:2502427",
        "tgn:7002659",
        "tgn:1000001",
        "tgn:7012149",
        "tgn:2000029",
        "tgn:7029392"
    ],
    "tgn:id":2502427,
    "tgn:name":"McKnight Branch",
    "tgn:placetype":[
        "aat:300008699"
    ]
},
  "bbox": [],
  "geometry": {"coordinates":[-87.85,34.4833],"type":"Point"}
}