{
  "id": 2694186,
  "type": "Feature",
  "properties": {
    "tgn:hierarchy":[
        "tgn:2694186",
        "tgn:1000001",
        "tgn:2000955",
        "tgn:7012149",
        "tgn:7007520",
        "tgn:7029392"
    ],
    "tgn:id":2694186,
    "tgn:name":"Stevens Lake",
    "tgn:placetype":[
        "aat:300008680"
    ]
},
  "bbox": [],
  "geometry": {"coordinates":[-86.5667,46.0667],"type":"Point"}
}