{
  "id": 2154227,
  "type": "Feature",
  "properties": {
    "tgn:hierarchy":[
        "tgn:2154227",
        "tgn:1000001",
        "tgn:2001260",
        "tgn:7012149",
        "tgn:7007524",
        "tgn:7029392"
    ],
    "tgn:id":2154227,
    "tgn:name":"Bear Creek",
    "tgn:placetype":[
        "aat:300008706"
    ]
},
  "bbox": [],
  "geometry": {"coordinates":[-112.9667,44.4333],"type":"Point"}
}