{
  "id": 7580666,
  "type": "Feature",
  "properties": {
    "tgn:hierarchy":[
        "tgn:7580666",
        "tgn:1000004",
        "tgn:7000198",
        "tgn:1001894",
        "tgn:7029392"
    ],
    "tgn:id":7580666,
    "tgn:name:en":"Sult\u0101npur",
    "tgn:placetype":[
        "aat:300008347"
    ]
},
  "bbox": [],
  "geometry": {"coordinates":[77.934755,23.136643],"type":"Point"}
}