{
  "id": 7151152,
  "type": "Feature",
  "properties": {
    "tgn:hierarchy":[
        "tgn:7151152",
        "tgn:1000003",
        "tgn:7003688",
        "tgn:7000084",
        "tgn:7029392"
    ],
    "tgn:id":7151152,
    "tgn:name":"Kanzlei",
    "tgn:placetype":[
        "aat:300387200"
    ]
},
  "bbox": [],
  "geometry": {"coordinates":[9.033333,54.133333],"type":"Point"}
}