{
  "id": 7155318,
  "type": "Feature",
  "properties": {
    "tgn:hierarchy":[
        "tgn:7155318",
        "tgn:1000003",
        "tgn:7003676",
        "tgn:7000084",
        "tgn:7029392"
    ],
    "tgn:id":7155318,
    "tgn:name":"Ker\u00dfenbrock",
    "tgn:placetype":[
        "aat:300008347"
    ]
},
  "bbox": [],
  "geometry": {"coordinates":[8.316667,52.133333],"type":"Point"}
}