{
  "id": 2326491,
  "type": "Feature",
  "properties": {
    "tgn:hierarchy":[
        "tgn:2326491",
        "tgn:1000001",
        "tgn:7012149",
        "tgn:1002550",
        "tgn:7007157",
        "tgn:7029392"
    ],
    "tgn:id":2326491,
    "tgn:name":"Finito, Arroyo",
    "tgn:placetype":[
        "aat:300008699"
    ]
},
  "bbox": [],
  "geometry": {"coordinates":[-120.0333,36.0167],"type":"Point"}
}