<<<<<<< HEAD
{
  "id": 7023205,
  "type": "Feature",
  "properties": {
    "tgn:hierarchy":[
        "tgn:7023205",
        "tgn:1000001",
        "tgn:7012149",
        "tgn:7029392"
    ],
    "tgn:id":7023205,
    "tgn:name":"Slavens Branch",
    "tgn:placetype":[
        "aat:300008699"
    ]
},
  "bbox": [],
  "geometry": {"coordinates":[-84.65,36.55],"type":"Point"}
}
=======
{"geometry":{"type":"Point","coordinates":[-84.650000,36.550000]},"type":"Feature","properties":{"hierarchy":["tgn:7023205","tgn:1000001","tgn:7012149","tgn:7029392"],"placetype":["aat:300008699"],"id":7023205,"name:xx":"Slavens Branch"}}
>>>>>>> 03f74aca74312dbeaf24d7e61306dd6a786dc3d0
