{
  "id": 7023205,
  "type": "Feature",
  "properties": {
    "tgn:hierarchy":[
        "tgn:7023205",
        "tgn:1000001",
        "tgn:7012149",
        "tgn:7029392"
    ],
    "tgn:id":7023205,
    "tgn:name":"Slavens Branch",
    "tgn:placetype":[
        "aat:300008699"
    ]
},
  "bbox": [],
  "geometry": {"coordinates":[-84.65,36.55],"type":"Point"}
}