{
  "id": 2009533,
  "type": "Feature",
  "properties": {
    "tgn:hierarchy":[
        "tgn:2009533",
        "tgn:1000001",
        "tgn:7016172",
        "tgn:2000119",
        "tgn:7012149",
        "tgn:7029392"
    ],
    "tgn:id":2009533,
    "tgn:name":"Solgohachia",
    "tgn:placetype":[
        "aat:300008347"
    ]
},
  "bbox": [],
  "geometry": {"coordinates":[-92.6667,35.25],"type":"Point"}
}