{
  "id": 7420284,
  "type": "Feature",
  "properties": {
    "tgn:hierarchy":[
        "tgn:7420284",
        "tgn:1000001",
        "tgn:7005589",
        "tgn:7005560",
        "tgn:7029392"
    ],
    "tgn:id":7420284,
    "tgn:name:es":"Los Fresnos",
    "tgn:placetype":[
        "aat:300008347"
    ]
},
  "bbox": [],
  "geometry": {"coordinates":[-99.531111,26.171111],"type":"Point"}
}