{
  "id": 2470107,
  "type": "Feature",
  "properties": {
    "tgn:hierarchy":[
        "tgn:2470107",
        "tgn:1000001",
        "tgn:7006451",
        "tgn:2000095",
        "tgn:7012149",
        "tgn:7029392"
    ],
    "tgn:id":2470107,
    "tgn:name":"Loop Tank",
    "tgn:placetype":[
        "aat:300006191"
    ]
},
  "bbox": [],
  "geometry": {"coordinates":[-109.3833,33.6833],"type":"Point"}
}