{
  "id": 2561521,
  "type": "Feature",
  "properties": {
    "tgn:hierarchy":[
        "tgn:2561521",
        "tgn:1002300",
        "tgn:1000001",
        "tgn:7012149",
        "tgn:7007564",
        "tgn:7029392"
    ],
    "tgn:id":2561521,
    "tgn:name":"Osgood Ridge",
    "tgn:placetype":[
        "aat:300266640"
    ]
},
  "bbox": [],
  "geometry": {"coordinates":[-71.25,44.3167],"type":"Point"}
}