<<<<<<< HEAD
{
  "id": 2334253,
  "type": "Feature",
  "properties": {
    "tgn:hierarchy":[
        "tgn:2334253",
        "tgn:1000001",
        "tgn:2001703",
        "tgn:7012149",
        "tgn:7007708",
        "tgn:7029392"
    ],
    "tgn:id":2334253,
    "tgn:name":"Forest Crossing",
    "tgn:placetype":[
        "aat:300008347"
    ]
},
  "bbox": [],
  "geometry": {"coordinates":[-121.0667,44.3333],"type":"Point"}
}
=======
{"geometry":{"type":"Point","coordinates":[-121.066700,44.333300]},"type":"Feature","properties":{"hierarchy":["tgn:2334253","tgn:1000001","tgn:2001703","tgn:7012149","tgn:7007708","tgn:7029392"],"placetype":["aat:300008347"],"id":2334253,"name:xx":"Forest Crossing"}}
>>>>>>> 03f74aca74312dbeaf24d7e61306dd6a786dc3d0
