{
  "id": 2586121,
  "type": "Feature",
  "properties": {
    "tgn:hierarchy":[
        "tgn:2586121",
        "tgn:1000001",
        "tgn:2000921",
        "tgn:7012149",
        "tgn:7007515",
        "tgn:7029392"
    ],
    "tgn:id":2586121,
    "tgn:name":"Pisgah, Mount",
    "tgn:placetype":[
        "aat:300008798"
    ]
},
  "bbox": [],
  "geometry": {"coordinates":[-70.65,45.3667],"type":"Point"}
}