{
  "id": 2084344,
  "type": "Feature",
  "properties": {
    "tgn:hierarchy":[
        "tgn:2084344",
        "tgn:1000001",
        "tgn:7012149",
        "tgn:2001716",
        "tgn:7007708",
        "tgn:7029392"
    ],
    "tgn:id":2084344,
    "tgn:name":"Alvadore",
    "tgn:placetype":[
        "aat:300008347"
    ]
},
  "bbox": [],
  "geometry": {"coordinates":[-123.25,44.1167],"type":"Point"}
}