{
  "id": 1125599,
  "type": "Feature",
  "properties": {
    "tgn:hierarchy":[
        "tgn:1125599",
        "tgn:1000004",
        "tgn:7029392"
    ],
    "tgn:id":1125599,
    "tgn:name":"Kishen Ganga",
    "tgn:placetype":[
        "aat:300008707"
    ]
},
  "bbox": [],
  "geometry": {"coordinates":[73.5833,34.3333],"type":"Point"}
}