{
  "id": 2308868,
  "type": "Feature",
  "properties": {
    "tgn:hierarchy":[
        "tgn:2308868",
        "tgn:1000001",
        "tgn:7012149",
        "tgn:2001718",
        "tgn:7007708",
        "tgn:7029392"
    ],
    "tgn:id":2308868,
    "tgn:name":"East Prong Dry Creek",
    "tgn:placetype":[
        "aat:300008706"
    ]
},
  "bbox": [],
  "geometry": {"coordinates":[-117.65,44.15],"type":"Point"}
}