{
  "id": 2744771,
  "type": "Feature",
  "properties": {
    "tgn:hierarchy":[
        "tgn:2744771",
        "tgn:1000001",
        "tgn:2000317",
        "tgn:7012149",
        "tgn:7007248",
        "tgn:7029392"
    ],
    "tgn:id":2744771,
    "tgn:name":"Victoria Pond",
    "tgn:placetype":[
        "aat:300006191"
    ]
},
  "bbox": [],
  "geometry": {"coordinates":[-84.8167,32.35],"type":"Point"}
}