{
  "id": 7484962,
  "type": "Feature",
  "properties": {
    "tgn:hierarchy":[
        "tgn:7484962",
        "tgn:7001004",
        "tgn:1000004",
        "tgn:1000141",
        "tgn:7029392"
    ],
    "tgn:id":7484962,
    "tgn:name":"Baizikeng Xi",
    "tgn:placetype":[
        "aat:300008699"
    ]
},
  "bbox": [],
  "geometry": {"coordinates":[120.521389,23.012778],"type":"Point"}
}