<<<<<<< HEAD
{
  "id": 7484962,
  "type": "Feature",
  "properties": {
    "tgn:hierarchy":[
        "tgn:7484962",
        "tgn:7001004",
        "tgn:1000004",
        "tgn:1000141",
        "tgn:7029392"
    ],
    "tgn:id":7484962,
    "tgn:name":"Baizikeng Xi",
    "tgn:placetype":[
        "aat:300008699"
    ]
},
  "bbox": [],
  "geometry": {"coordinates":[120.521389,23.012778],"type":"Point"}
}
=======
{"geometry":{"type":"Point","coordinates":[120.521389,23.012778]},"type":"Feature","properties":{"hierarchy":["tgn:7484962","tgn:7001004","tgn:1000004","tgn:1000141","tgn:7029392"],"placetype":["aat:300008699"],"id":7484962,"name:xx":"Baizikeng Xi"}}
>>>>>>> 03f74aca74312dbeaf24d7e61306dd6a786dc3d0
