{
  "id": 2429028,
  "type": "Feature",
  "properties": {
    "tgn:hierarchy":[
        "tgn:2429028",
        "tgn:1000001",
        "tgn:7012149",
        "tgn:7007920",
        "tgn:7029392"
    ],
    "tgn:id":2429028,
    "tgn:name":"Jumpoff Ridge",
    "tgn:placetype":[
        "aat:300266640"
    ]
},
  "bbox": [],
  "geometry": {"coordinates":[-120.2167,47.3167],"type":"Point"}
}