{
  "id": 2175879,
  "type": "Feature",
  "properties": {
    "tgn:hierarchy":[
        "tgn:2175879",
        "tgn:7006450",
        "tgn:1000001",
        "tgn:7012149",
        "tgn:2000085",
        "tgn:7029392"
    ],
    "tgn:id":2175879,
    "tgn:name":"Black Diamond Creek",
    "tgn:placetype":[
        "aat:300008706"
    ]
},
  "bbox": [],
  "geometry": {"coordinates":[-141.6333,64.65],"type":"Point"}
}