{
  "id": 2180447,
  "type": "Feature",
  "properties": {
    "tgn:hierarchy":[
        "tgn:2180447",
        "tgn:1000001",
        "tgn:7012149",
        "tgn:1002591",
        "tgn:7007255",
        "tgn:7029392"
    ],
    "tgn:id":2180447,
    "tgn:name":"Blood Lick",
    "tgn:placetype":[
        "aat:300008699"
    ]
},
  "bbox": [],
  "geometry": {"coordinates":[-83.3667,38.6167],"type":"Point"}
}