<<<<<<< HEAD
{
  "id": 7246769,
  "type": "Feature",
  "properties": {
    "tgn:hierarchy":[
        "tgn:7246769",
        "tgn:7003456",
        "tgn:1000003",
        "tgn:1000063",
        "tgn:7018236",
        "tgn:7029392"
    ],
    "tgn:id":7246769,
    "tgn:name":"Calvenne",
    "tgn:placetype":[
        "aat:300008347"
    ]
},
  "bbox": [],
  "geometry": {"coordinates":[4.716667,51.0],"type":"Point"}
}
=======
{"geometry":{"type":"Point","coordinates":[4.716667,51.000000]},"type":"Feature","properties":{"hierarchy":["tgn:7246769","tgn:7003456","tgn:1000003","tgn:1000063","tgn:7018236","tgn:7029392"],"placetype":["aat:300008347"],"id":7246769,"name:xx":"Calvenne"}}
>>>>>>> 03f74aca74312dbeaf24d7e61306dd6a786dc3d0
