{
  "id": 7238161,
  "type": "Feature",
  "properties": {
    "tgn:hierarchy":[
        "tgn:7238161",
        "tgn:7007877",
        "tgn:1000003",
        "tgn:1000063",
        "tgn:4012014",
        "tgn:7029392"
    ],
    "tgn:id":7238161,
    "tgn:name":"Grand Hameau",
    "tgn:placetype":[
        "aat:300008347"
    ]
},
  "bbox": [],
  "geometry": {"coordinates":[3.876164,50.551229],"type":"Point"}
}