{
  "id": 7022693,
  "type": "Feature",
  "properties": {
    "tgn:hierarchy":[
        "tgn:7022693",
        "tgn:1000001",
        "tgn:7012149",
        "tgn:7029392"
    ],
    "tgn:id":7022693,
    "tgn:name":"West Dog Canyon",
    "tgn:placetype":[
        "aat:300008761"
    ]
},
  "bbox": [],
  "geometry": {"coordinates":[-104.85,31.95],"type":"Point"}
}