{
  "id": 1041100,
  "type": "Feature",
  "properties": {
    "tgn:hierarchy":[
        "tgn:1041100",
        "tgn:7003669",
        "tgn:1000003",
        "tgn:7000084",
        "tgn:7029392"
    ],
    "tgn:id":1041100,
    "tgn:name":"Schirnding",
    "tgn:placetype":[
        "aat:300008347"
    ]
},
  "bbox": [],
  "geometry": {"coordinates":[12.233333,50.083333],"type":"Point"}
}