{
  "id": 7389561,
  "type": "Feature",
  "properties": {
    "tgn:hierarchy":[
        "tgn:7389561",
        "tgn:1000001",
        "tgn:1001960",
        "tgn:7005560",
        "tgn:7029392"
    ],
    "tgn:id":7389561,
    "tgn:name":"Rancho El Rosario",
    "tgn:placetype":[
        "aat:300008347"
    ]
},
  "bbox": [],
  "geometry": {"coordinates":[-112.341389,30.6325],"type":"Point"}
}