{
  "id": 7387580,
  "type": "Feature",
  "properties": {
    "tgn:hierarchy":[
        "tgn:7387580",
        "tgn:1000001",
        "tgn:1001906",
        "tgn:7005560",
        "tgn:7029392"
    ],
    "tgn:id":7387580,
    "tgn:name":"Paranal",
    "tgn:placetype":[
        "aat:300008347"
    ]
},
  "bbox": [],
  "geometry": {"coordinates":[-105.083333,21.266667],"type":"Point"}
}