{
  "id": 2672264,
  "type": "Feature",
  "properties": {
    "tgn:hierarchy":[
        "tgn:2672264",
        "tgn:1000001",
        "tgn:7012149",
        "tgn:2000548",
        "tgn:7007252",
        "tgn:7029392"
    ],
    "tgn:id":2672264,
    "tgn:name":"Smithville",
    "tgn:placetype":[
        "aat:300008347"
    ]
},
  "bbox": [],
  "geometry": {"coordinates":[-87.0167,39.3167],"type":"Point"}
}