{
  "id": 7453555,
  "type": "Feature",
  "properties": {
    "tgn:hierarchy":[
        "tgn:7453555",
        "tgn:7002445",
        "tgn:1000003",
        "tgn:7008117",
        "tgn:7008591",
        "tgn:7029392"
    ],
    "tgn:id":7453555,
    "tgn:name:en":"Caldbeck",
    "tgn:placetype":[
        "aat:300008347"
    ]
},
  "bbox": [],
  "geometry": {"coordinates":[-3.05,54.733333],"type":"Point"}
}