{
  "id": 2514648,
  "type": "Feature",
  "properties": {
    "tgn:hierarchy":[
        "tgn:2514648",
        "tgn:1000001",
        "tgn:7012149",
        "tgn:1002514",
        "tgn:7007251",
        "tgn:7029392"
    ],
    "tgn:id":2514648,
    "tgn:name":"Miller Lake",
    "tgn:placetype":[
        "aat:300006191"
    ]
},
  "bbox": [],
  "geometry": {"coordinates":[-88.8833,38.3833],"type":"Point"}
}