<<<<<<< HEAD
{
  "id": 2336458,
  "type": "Feature",
  "properties": {
    "tgn:hierarchy":[
        "tgn:2336458",
        "tgn:1000001",
        "tgn:7012149",
        "tgn:2001708",
        "tgn:7007708",
        "tgn:7029392"
    ],
    "tgn:id":2336458,
    "tgn:name":"Four Bar Spring",
    "tgn:placetype":[
        "aat:300008697"
    ]
},
  "bbox": [],
  "geometry": {"coordinates":[-119.3167,43.9667],"type":"Point"}
}
=======
{"geometry":{"type":"Point","coordinates":[-119.316700,43.966700]},"type":"Feature","properties":{"hierarchy":["tgn:2336458","tgn:1000001","tgn:7012149","tgn:2001708","tgn:7007708","tgn:7029392"],"placetype":["aat:300008697"],"id":2336458,"name:xx":"Four Bar Spring"}}
>>>>>>> 03f74aca74312dbeaf24d7e61306dd6a786dc3d0
