{
  "id": 2246297,
  "type": "Feature",
  "properties": {
    "tgn:hierarchy":[
        "tgn:2246297",
        "tgn:7006450",
        "tgn:1000001",
        "tgn:7012149",
        "tgn:2124014",
        "tgn:7029392"
    ],
    "tgn:id":2246297,
    "tgn:name":"Coarse Gold Creek",
    "tgn:placetype":[
        "aat:300008706"
    ]
},
  "bbox": [],
  "geometry": {"coordinates":[-162.1833,65.75],"type":"Point"}
}