{
  "id": 2195230,
  "type": "Feature",
  "properties": {
    "tgn:hierarchy":[
        "tgn:2195230",
        "tgn:1000001",
        "tgn:7012149",
        "tgn:1002402",
        "tgn:7007523",
        "tgn:7029392"
    ],
    "tgn:id":2195230,
    "tgn:name":"Brinkman Creek",
    "tgn:placetype":[
        "aat:300008706"
    ]
},
  "bbox": [],
  "geometry": {"coordinates":[-91.55,38.45],"type":"Point"}
}