{
  "id": 7217589,
  "type": "Feature",
  "properties": {
    "tgn:hierarchy":[
        "tgn:7217589",
        "tgn:7011161",
        "tgn:7002674",
        "tgn:1000003",
        "tgn:1000074",
        "tgn:7029392"
    ],
    "tgn:id":7217589,
    "tgn:name":"Tsoump\u00e1res",
    "tgn:placetype":[
        "aat:300266640"
    ]
},
  "bbox": [],
  "geometry": {"coordinates":[26.077778,38.4675],"type":"Point"}
}