{
  "id": 7057831,
  "type": "Feature",
  "properties": {
    "tgn:hierarchy":[
        "tgn:7057831",
        "tgn:1001724",
        "tgn:1000003",
        "tgn:7003121",
        "tgn:1000080",
        "tgn:7029392"
    ],
    "tgn:id":7057831,
    "tgn:name":"Argiola, Riu s'",
    "tgn:placetype":[
        "aat:300008699"
    ]
},
  "bbox": [],
  "geometry": {"coordinates":[9.383333,40.016667],"type":"Point"}
}