{
  "id": 2768683,
  "type": "Feature",
  "properties": {
    "tgn:hierarchy":[
        "tgn:2768683",
        "tgn:1000001",
        "tgn:7012149",
        "tgn:2001921",
        "tgn:7007825",
        "tgn:7029392"
    ],
    "tgn:id":2768683,
    "tgn:name":"Whitleys Island",
    "tgn:placetype":[
        "aat:300008791"
    ]
},
  "bbox": [],
  "geometry": {"coordinates":[-86.2167,36.3667],"type":"Point"}
}