{
  "id": 2040636,
  "type": "Feature",
  "properties": {
    "tgn:hierarchy":[
        "tgn:2040636",
        "tgn:1000001",
        "tgn:7012149",
        "tgn:2000829",
        "tgn:7007255",
        "tgn:7029392"
    ],
    "tgn:id":2040636,
    "tgn:name":"Otia",
    "tgn:placetype":[
        "aat:300008347",
        "aat:300387210"
    ]
},
  "bbox": [],
  "geometry": {"coordinates":[-85.5667,36.6833],"type":"Point"}
}