{
  "id": 7590112,
  "type": "Feature",
  "properties": {
    "tgn:hierarchy":[
        "tgn:7590112",
        "tgn:1000004",
        "tgn:1001871",
        "tgn:7000198",
        "tgn:7029392"
    ],
    "tgn:id":7590112,
    "tgn:name:en":"Kurh\u0101mi",
    "tgn:placetype":[
        "aat:300008347"
    ]
},
  "bbox": [],
  "geometry": {"coordinates":[76.961193,29.955662],"type":"Point"}
}