{
  "id": 2480258,
  "type": "Feature",
  "properties": {
    "tgn:hierarchy":[
        "tgn:2480258",
        "tgn:1000001",
        "tgn:7012149",
        "tgn:1002599",
        "tgn:7007708",
        "tgn:7029392"
    ],
    "tgn:id":2480258,
    "tgn:name":"Lake Point",
    "tgn:placetype":[
        "aat:300008850"
    ]
},
  "bbox": [],
  "geometry": {"coordinates":[-123.9833,44.9833],"type":"Point"}
}