{
  "id": 7381530,
  "type": "Feature",
  "properties": {
    "tgn:hierarchy":[
        "tgn:7381530",
        "tgn:1000001",
        "tgn:7005595",
        "tgn:7005560",
        "tgn:7029392"
    ],
    "tgn:id":7381530,
    "tgn:name":"Los Amoles",
    "tgn:placetype":[
        "aat:300008347"
    ]
},
  "bbox": [],
  "geometry": {"coordinates":[-107.233333,25.466667],"type":"Point"}
}