{
  "id": 7279045,
  "type": "Feature",
  "properties": {
    "tgn:hierarchy":[
        "tgn:7279045",
        "tgn:1001692",
        "tgn:1000049",
        "tgn:1000002",
        "tgn:7029392"
    ],
    "tgn:id":7279045,
    "tgn:name":"Rumi\u00f1ano",
    "tgn:placetype":[
        "aat:300008347"
    ]
},
  "bbox": [],
  "geometry": {"coordinates":[-71.55,-38.933333],"type":"Point"}
}