{
  "id": 2489403,
  "type": "Feature",
  "properties": {
    "tgn:hierarchy":[
        "tgn:2489403",
        "tgn:1000001",
        "tgn:7012149",
        "tgn:2002373",
        "tgn:7007923",
        "tgn:7029392"
    ],
    "tgn:id":2489403,
    "tgn:name":"Malcolm Spring",
    "tgn:placetype":[
        "aat:300008697"
    ]
},
  "bbox": [],
  "geometry": {"coordinates":[-107.9167,43.6333],"type":"Point"}
}