{
  "id": 2513646,
  "type": "Feature",
  "properties": {
    "tgn:hierarchy":[
        "tgn:2513646",
        "tgn:1000001",
        "tgn:7012149",
        "tgn:2001949",
        "tgn:7007826",
        "tgn:7029392"
    ],
    "tgn:id":2513646,
    "tgn:name":"Mill Pond",
    "tgn:placetype":[
        "aat:300008680"
    ]
},
  "bbox": [],
  "geometry": {"coordinates":[-98.2333,30.6333],"type":"Point"}
}