{
  "id": 2073818,
  "type": "Feature",
  "properties": {
    "tgn:hierarchy":[
        "tgn:2073818",
        "tgn:1000001",
        "tgn:7012149",
        "tgn:2001511",
        "tgn:7007709",
        "tgn:7029392"
    ],
    "tgn:id":2073818,
    "tgn:name":"Broadway",
    "tgn:placetype":[
        "aat:300008347"
    ]
},
  "bbox": [],
  "geometry": {"coordinates":[-79.05,35.45],"type":"Point"}
}