{
  "id": 2233409,
  "type": "Feature",
  "properties": {
    "tgn:hierarchy":[
        "tgn:2233409",
        "tgn:2002239",
        "tgn:1000001",
        "tgn:7012149",
        "tgn:7007920",
        "tgn:7029392"
    ],
    "tgn:id":2233409,
    "tgn:name":"Charlie Knight Gulch",
    "tgn:placetype":[
        "aat:300008761"
    ]
},
  "bbox": [],
  "geometry": {"coordinates":[-117.3167,46.15],"type":"Point"}
}