{
  "id": 7552088,
  "type": "Feature",
  "properties": {
    "tgn:hierarchy":[
        "tgn:7552088",
        "tgn:1000004",
        "tgn:7000198",
        "tgn:1001894",
        "tgn:7029392"
    ],
    "tgn:id":7552088,
    "tgn:name:en":"Denw\u0101 River",
    "tgn:placetype":[
        "aat:300008699"
    ]
},
  "bbox": [],
  "geometry": {"coordinates":[78.161305,22.564734],"type":"Point"}
}