<<<<<<< HEAD
{
  "id": 2400514,
  "type": "Feature",
  "properties": {
    "tgn:hierarchy":[
        "tgn:2400514",
        "tgn:1000001",
        "tgn:7012149",
        "tgn:2001516",
        "tgn:7007709",
        "tgn:7029392"
    ],
    "tgn:id":2400514,
    "tgn:name":"Horse Knob",
    "tgn:placetype":[
        "aat:300008798"
    ]
},
  "bbox": [],
  "geometry": {"coordinates":[-82.7667,35.8167],"type":"Point"}
}
=======
{"geometry":{"type":"Point","coordinates":[-82.766700,35.816700]},"type":"Feature","properties":{"hierarchy":["tgn:2400514","tgn:1000001","tgn:7012149","tgn:2001516","tgn:7007709","tgn:7029392"],"placetype":["aat:300008798"],"id":2400514,"name:xx":"Horse Knob"}}
>>>>>>> 03f74aca74312dbeaf24d7e61306dd6a786dc3d0
