{
  "id": 2400514,
  "type": "Feature",
  "properties": {
    "tgn:hierarchy":[
        "tgn:2400514",
        "tgn:1000001",
        "tgn:7012149",
        "tgn:2001516",
        "tgn:7007709",
        "tgn:7029392"
    ],
    "tgn:id":2400514,
    "tgn:name":"Horse Knob",
    "tgn:placetype":[
        "aat:300008798"
    ]
},
  "bbox": [],
  "geometry": {"coordinates":[-82.7667,35.8167],"type":"Point"}
}