{
  "id": 2120289,
  "type": "Feature",
  "properties": {
    "tgn:hierarchy":[
        "tgn:2120289",
        "tgn:1000001",
        "tgn:7012149",
        "tgn:2002275",
        "tgn:7013961",
        "tgn:7029392"
    ],
    "tgn:id":2120289,
    "tgn:name":"Valley Falls",
    "tgn:placetype":[
        "aat:300008347",
        "aat:300387210"
    ]
},
  "bbox": [],
  "geometry": {"coordinates":[-80.0833,39.3833],"type":"Point"}
}