<<<<<<< HEAD
{
  "id": 2333388,
  "type": "Feature",
  "properties": {
    "tgn:hierarchy":[
        "tgn:2333388",
        "tgn:1000001",
        "tgn:2001784",
        "tgn:7012149",
        "tgn:7007713",
        "tgn:7029392"
    ],
    "tgn:id":2333388,
    "tgn:name":"Foley",
    "tgn:placetype":[
        "aat:300008347"
    ]
},
  "bbox": [],
  "geometry": {"coordinates":[-97.1333,44.8333],"type":"Point"}
}
=======
{"geometry":{"type":"Point","coordinates":[-97.133300,44.833300]},"type":"Feature","properties":{"hierarchy":["tgn:2333388","tgn:1000001","tgn:2001784","tgn:7012149","tgn:7007713","tgn:7029392"],"placetype":["aat:300008347"],"id":2333388,"name:xx":"Foley"}}
>>>>>>> 03f74aca74312dbeaf24d7e61306dd6a786dc3d0
