{
  "id": 1024409,
  "type": "Feature",
  "properties": {
    "tgn:hierarchy":[
        "tgn:1024409",
        "tgn:1000518",
        "tgn:1000002",
        "tgn:1000056",
        "tgn:7029392"
    ],
    "tgn:id":1024409,
    "tgn:name":"Cangallo",
    "tgn:placetype":[
        "aat:300008347"
    ]
},
  "bbox": [],
  "geometry": {"coordinates":[-74.1333,-13.6167],"type":"Point"}
}