{
  "id": 2576523,
  "type": "Feature",
  "properties": {
    "tgn:hierarchy":[
        "tgn:2576523",
        "tgn:1000001",
        "tgn:7012149",
        "tgn:1002779",
        "tgn:7007710",
        "tgn:7029392"
    ],
    "tgn:id":2576523,
    "tgn:name":"Perry Valley",
    "tgn:placetype":[
        "aat:300008761"
    ]
},
  "bbox": [],
  "geometry": {"coordinates":[-77.0667,40.55],"type":"Point"}
}