{
  "id": 2528641,
  "type": "Feature",
  "properties": {
    "tgn:hierarchy":[
        "tgn:2528641",
        "tgn:1000001",
        "tgn:7012149",
        "tgn:2000891",
        "tgn:7007256",
        "tgn:7029392"
    ],
    "tgn:id":2528641,
    "tgn:name":"Mud Bay",
    "tgn:placetype":[
        "aat:300008680"
    ]
},
  "bbox": [],
  "geometry": {"coordinates":[-89.65,29.4833],"type":"Point"}
}