{
  "id": 2238477,
  "type": "Feature",
  "properties": {
    "tgn:hierarchy":[
        "tgn:2238477",
        "tgn:7006450",
        "tgn:1000001",
        "tgn:7012149",
        "tgn:2000089",
        "tgn:7029392"
    ],
    "tgn:id":2238477,
    "tgn:name":"Chokoyik Island",
    "tgn:placetype":[
        "aat:300008791"
    ]
},
  "bbox": [],
  "geometry": {"coordinates":[-153.9167,65.05],"type":"Point"}
}