{
  "id": 2381847,
  "type": "Feature",
  "properties": {
    "tgn:hierarchy":[
        "tgn:2381847",
        "tgn:1000001",
        "tgn:2000950",
        "tgn:7012149",
        "tgn:7007520",
        "tgn:7029392"
    ],
    "tgn:id":2381847,
    "tgn:name":"Hayden Point",
    "tgn:placetype":[
        "aat:300008850"
    ]
},
  "bbox": [],
  "geometry": {"coordinates":[-85.0833,45.2333],"type":"Point"}
}