{
  "id": 7194370,
  "type": "Feature",
  "properties": {
    "tgn:hierarchy":[
        "tgn:7194370",
        "tgn:1000003",
        "tgn:7003678",
        "tgn:7000084",
        "tgn:7029392"
    ],
    "tgn:id":7194370,
    "tgn:name":"Densberg",
    "tgn:placetype":[
        "aat:300008347"
    ]
},
  "bbox": [],
  "geometry": {"coordinates":[9.083333,50.983333],"type":"Point"}
}