{
  "id": 2093339,
  "type": "Feature",
  "properties": {
    "tgn:hierarchy":[
        "tgn:2093339",
        "tgn:1000001",
        "tgn:1002185",
        "tgn:7012149",
        "tgn:7007710",
        "tgn:7029392"
    ],
    "tgn:id":2093339,
    "tgn:name":"Sproul",
    "tgn:placetype":[
        "aat:300008347"
    ]
},
  "bbox": [],
  "geometry": {"coordinates":[-78.45,40.2667],"type":"Point"}
}