{
  "id": 2401387,
  "type": "Feature",
  "properties": {
    "tgn:hierarchy":[
        "tgn:2401387",
        "tgn:1000001",
        "tgn:7012149",
        "tgn:2000891",
        "tgn:7007256",
        "tgn:7029392"
    ],
    "tgn:id":2401387,
    "tgn:name":"Horsepower Canal",
    "tgn:placetype":[
        "aat:300006075"
    ]
},
  "bbox": [],
  "geometry": {"coordinates":[-89.8833,29.65],"type":"Point"}
}