<<<<<<< HEAD
{
  "id": 2401729,
  "type": "Feature",
  "properties": {
    "tgn:hierarchy":[
        "tgn:2401729",
        "tgn:1000001",
        "tgn:7012149",
        "tgn:2000985",
        "tgn:7007520",
        "tgn:7029392"
    ],
    "tgn:id":2401729,
    "tgn:name":"Horseshoe Lake",
    "tgn:placetype":[
        "aat:300008680"
    ]
},
  "bbox": [],
  "geometry": {"coordinates":[-84.2667,44.4167],"type":"Point"}
}
=======
{"geometry":{"type":"Point","coordinates":[-84.266700,44.416700]},"type":"Feature","properties":{"hierarchy":["tgn:2401729","tgn:1000001","tgn:7012149","tgn:2000985","tgn:7007520","tgn:7029392"],"placetype":["aat:300008680"],"id":2401729,"name:xx":"Horseshoe Lake"}}
>>>>>>> 03f74aca74312dbeaf24d7e61306dd6a786dc3d0
