{
  "id": 1116126,
  "type": "Feature",
  "properties": {
    "tgn:hierarchy":[
        "tgn:1116126",
        "tgn:1000003",
        "tgn:1003396",
        "tgn:7006660",
        "tgn:7029392"
    ],
    "tgn:id":1116126,
    "tgn:name":"Dnestrovskiy liman",
    "tgn:placetype":[
        "aat:300008680"
    ]
},
  "bbox": [],
  "geometry": {"coordinates":[30.2833,46.25],"type":"Point"}
}