{
  "id": 2741297,
  "type": "Feature",
  "properties": {
    "tgn:hierarchy":[
        "tgn:2741297",
        "tgn:1000001",
        "tgn:2001016",
        "tgn:7012149",
        "tgn:7007521",
        "tgn:7029392"
    ],
    "tgn:id":2741297,
    "tgn:name":"Upper Whipple Lake",
    "tgn:placetype":[
        "aat:300008680"
    ]
},
  "bbox": [],
  "geometry": {"coordinates":[-94.3167,46.35],"type":"Point"}
}