{
  "id": 2452660,
  "type": "Feature",
  "properties": {
    "tgn:hierarchy":[
        "tgn:2452660",
        "tgn:1000001",
        "tgn:7012149",
        "tgn:1002897",
        "tgn:7007920",
        "tgn:7029392"
    ],
    "tgn:id":2452660,
    "tgn:name":"Little Buck Creek",
    "tgn:placetype":[
        "aat:300008706"
    ]
},
  "bbox": [],
  "geometry": {"coordinates":[-121.5833,45.7833],"type":"Point"}
}