{
  "id": 2273121,
  "type": "Feature",
  "properties": {
    "tgn:hierarchy":[
        "tgn:2273121",
        "tgn:1000001",
        "tgn:2002109",
        "tgn:7012149",
        "tgn:7007827",
        "tgn:7029392"
    ],
    "tgn:id":2273121,
    "tgn:name":"Cyclone Lake",
    "tgn:placetype":[
        "aat:300008680"
    ]
},
  "bbox": [],
  "geometry": {"coordinates":[-111.7167,37.9833],"type":"Point"}
}