<<<<<<< HEAD
{
  "id": 2768905,
  "type": "Feature",
  "properties": {
    "tgn:hierarchy":[
        "tgn:2768905",
        "tgn:1000001",
        "tgn:7012149",
        "tgn:2001045",
        "tgn:7007521",
        "tgn:7029392"
    ],
    "tgn:id":2768905,
    "tgn:name":"Whitney Lake",
    "tgn:placetype":[
        "aat:300008680"
    ]
},
  "bbox": [],
  "geometry": {"coordinates":[-94.7,45.25],"type":"Point"}
}
=======
{"geometry":{"type":"Point","coordinates":[-94.700000,45.250000]},"type":"Feature","properties":{"hierarchy":["tgn:2768905","tgn:1000001","tgn:7012149","tgn:2001045","tgn:7007521","tgn:7029392"],"placetype":["aat:300008680"],"id":2768905,"name:xx":"Whitney Lake"}}
>>>>>>> 03f74aca74312dbeaf24d7e61306dd6a786dc3d0
