<<<<<<< HEAD
{
  "id": 2403140,
  "type": "Feature",
  "properties": {
    "tgn:hierarchy":[
        "tgn:2403140",
        "tgn:1000001",
        "tgn:7012149",
        "tgn:7007707",
        "tgn:7029392"
    ],
    "tgn:id":2403140,
    "tgn:name":"House Creek",
    "tgn:placetype":[
        "aat:300008706"
    ]
},
  "bbox": [],
  "geometry": {"coordinates":[-96.5667,36.1833],"type":"Point"}
}
=======
{"geometry":{"type":"Point","coordinates":[-96.566700,36.183300]},"type":"Feature","properties":{"hierarchy":["tgn:2403140","tgn:1000001","tgn:7012149","tgn:7007707","tgn:7029392"],"placetype":["aat:300008706"],"id":2403140,"name:xx":"House Creek"}}
>>>>>>> 03f74aca74312dbeaf24d7e61306dd6a786dc3d0
