{
  "id": 7156071,
  "type": "Feature",
  "properties": {
    "tgn:hierarchy":[
        "tgn:7156071",
        "tgn:1000003",
        "tgn:7003676",
        "tgn:7000084",
        "tgn:7029392"
    ],
    "tgn:id":7156071,
    "tgn:name":"Klein Garsiens",
    "tgn:placetype":[
        "aat:300000206"
    ]
},
  "bbox": [],
  "geometry": {"coordinates":[7.966667,53.633333],"type":"Point"}
}