{
  "id": 2136930,
  "type": "Feature",
  "properties": {
    "tgn:hierarchy":[
        "tgn:2136930",
        "tgn:1000001",
        "tgn:7012149",
        "tgn:1003008",
        "tgn:7007710",
        "tgn:7029392"
    ],
    "tgn:id":2136930,
    "tgn:name":"Ariel, Lake",
    "tgn:placetype":[
        "aat:300008680"
    ]
},
  "bbox": [],
  "geometry": {"coordinates":[-75.3667,41.4333],"type":"Point"}
}