{
  "id": 1113564,
  "type": "Feature",
  "properties": {
    "tgn:hierarchy":[
        "tgn:1113564",
        "tgn:1000001",
        "tgn:7004641",
        "tgn:7029392"
    ],
    "tgn:id":1113564,
    "tgn:name":"Pagua Bay",
    "tgn:placetype":[
        "aat:300132316"
    ]
},
  "bbox": [],
  "geometry": {"coordinates":[-61.2667,15.5167],"type":"Point"}
}