{
  "id": 7416618,
  "type": "Feature",
  "properties": {
    "tgn:hierarchy":[
        "tgn:7416618",
        "tgn:1000001",
        "tgn:7005591",
        "tgn:7005560",
        "tgn:7029392"
    ],
    "tgn:id":7416618,
    "tgn:name:es":"Nejapa",
    "tgn:placetype":[
        "aat:300008347"
    ]
},
  "bbox": [],
  "geometry": {"coordinates":[-96.109722,17.109167],"type":"Point"}
}