{
  "id": 7293041,
  "type": "Feature",
  "properties": {
    "tgn:hierarchy":[
        "tgn:7293041",
        "tgn:1001630",
        "tgn:1000049",
        "tgn:1000002",
        "tgn:7029392"
    ],
    "tgn:id":7293041,
    "tgn:name":"El Salto, Quebrada",
    "tgn:placetype":[
        "aat:300266554",
        "aat:300008699"
    ]
},
  "bbox": [],
  "geometry": {"coordinates":[-70.35,-27.85],"type":"Point"}
}