{
  "id": 1008693,
  "type": "Feature",
  "properties": {
    "tgn:hierarchy":[
        "tgn:1008693",
        "tgn:7032089",
        "tgn:1000001",
        "tgn:7004773",
        "tgn:7029392"
    ],
    "tgn:id":1008693,
    "tgn:name":"Quatre, Isle \u00e0",
    "tgn:placetype":[
        "aat:300008791"
    ]
},
  "bbox": [],
  "geometry": {"coordinates":[-61.25,12.95],"type":"Point"}
}