{
  "id": 7381097,
  "type": "Feature",
  "properties": {
    "tgn:hierarchy":[
        "tgn:7381097",
        "tgn:1000001",
        "tgn:7005601",
        "tgn:7005560",
        "tgn:7029392"
    ],
    "tgn:id":7381097,
    "tgn:name":"Melchor Ocampo",
    "tgn:placetype":[
        "aat:300008347"
    ]
},
  "bbox": [],
  "geometry": {"coordinates":[-101.633333,24.833333],"type":"Point"}
}