{
  "id": 2687614,
  "type": "Feature",
  "properties": {
    "tgn:hierarchy":[
        "tgn:2687614",
        "tgn:1000001",
        "tgn:1002359",
        "tgn:7012149",
        "tgn:7007517",
        "tgn:7029392"
    ],
    "tgn:id":2687614,
    "tgn:name":"Spring Pond",
    "tgn:placetype":[
        "aat:300008680"
    ]
},
  "bbox": [],
  "geometry": {"coordinates":[-71.05,42.4667],"type":"Point"}
}