{
  "id": 7309496,
  "type": "Feature",
  "properties": {
    "tgn:hierarchy":[
        "tgn:7309496",
        "tgn:1001695",
        "tgn:1000049",
        "tgn:1000002",
        "tgn:7029392"
    ],
    "tgn:id":7309496,
    "tgn:name":"Nuevo Reino, Cerro",
    "tgn:placetype":[
        "aat:300008777"
    ]
},
  "bbox": [],
  "geometry": {"coordinates":[-71.983333,-34.416667],"type":"Point"}
}