{
  "id": 7380001,
  "type": "Feature",
  "properties": {
    "tgn:hierarchy":[
        "tgn:7380001",
        "tgn:7005581",
        "tgn:1000001",
        "tgn:7005560",
        "tgn:7029392"
    ],
    "tgn:id":7380001,
    "tgn:name":"Rancho Lucero",
    "tgn:placetype":[
        "aat:300000241"
    ]
},
  "bbox": [],
  "geometry": {"coordinates":[-106.25,30.95],"type":"Point"}
}