{
  "id": 7267878,
  "type": "Feature",
  "properties": {
    "tgn:hierarchy":[
        "tgn:7267878",
        "tgn:1000003",
        "tgn:7003627",
        "tgn:7016845",
        "tgn:7029392"
    ],
    "tgn:id":7267878,
    "tgn:name:nl":"Rijnouwen",
    "tgn:placetype":[
        "aat:300006909"
    ]
},
  "bbox": [],
  "geometry": {"coordinates":[5.183333,52.083333],"type":"Point"}
}