{
  "id": 2588744,
  "type": "Feature",
  "properties": {
    "tgn:hierarchy":[
        "tgn:2588744",
        "tgn:1000001",
        "tgn:1002601",
        "tgn:7012149",
        "tgn:7007159",
        "tgn:7029392"
    ],
    "tgn:id":2588744,
    "tgn:name":"Plymouth Lake",
    "tgn:placetype":[
        "aat:300006191"
    ]
},
  "bbox": [],
  "geometry": {"coordinates":[-73.0333,41.65],"type":"Point"}
}