{
  "id": 1079951,
  "type": "Feature",
  "properties": {
    "tgn:hierarchy":[
        "tgn:1079951",
        "tgn:1000975",
        "tgn:1000004",
        "tgn:7000901",
        "tgn:1000120",
        "tgn:7029392"
    ],
    "tgn:id":1079951,
    "tgn:name":"Fukuma",
    "tgn:placetype":[
        "aat:300008347"
    ]
},
  "bbox": [],
  "geometry": {"coordinates":[130.45,33.7833],"type":"Point"}
}