{
  "id": 2193821,
  "type": "Feature",
  "properties": {
    "tgn:hierarchy":[
        "tgn:2193821",
        "tgn:1000001",
        "tgn:7012149",
        "tgn:1003031",
        "tgn:7007826",
        "tgn:7029392"
    ],
    "tgn:id":2193821,
    "tgn:name":"Briar Branch",
    "tgn:placetype":[
        "aat:300008699"
    ]
},
  "bbox": [],
  "geometry": {"coordinates":[-97.6333,33.3667],"type":"Point"}
}