{
  "id": 7024689,
  "type": "Feature",
  "properties": {
    "tgn:hierarchy":[
        "tgn:7024689",
        "tgn:7002811",
        "tgn:1000003",
        "tgn:7003837",
        "tgn:1000095",
        "tgn:7029392"
    ],
    "tgn:id":7024689,
    "tgn:name":"Almaraz",
    "tgn:placetype":[
        "aat:300008347"
    ]
},
  "bbox": [],
  "geometry": {"coordinates":[-5.683333,39.816667],"type":"Point"}
}