{
  "id": 7261356,
  "type": "Feature",
  "properties": {
    "tgn:concordances":{
        "gn:id":"2756467"
    },
    "tgn:hierarchy":[
        "tgn:7261356",
        "tgn:1000003",
        "tgn:7003627",
        "tgn:7016845",
        "tgn:7029392"
    ],
    "tgn:id":7261356,
    "tgn:name:nl":"Dwarsdijk",
    "tgn:placetype":[
        "aat:300008347"
    ]
},
  "bbox": [],
  "geometry": {"coordinates":[5.283333,51.983333],"type":"Point"}
}