{
  "id": 2016569,
  "type": "Feature",
  "properties": {
    "tgn:hierarchy":[
        "tgn:2016569",
        "tgn:1000001",
        "tgn:1002461",
        "tgn:7012149",
        "tgn:7007159",
        "tgn:7029392"
    ],
    "tgn:id":2016569,
    "tgn:name":"Addison",
    "tgn:placetype":[
        "aat:300008347"
    ]
},
  "bbox": [],
  "geometry": {"coordinates":[-72.5667,41.7167],"type":"Point"}
}