{
  "id": 1049658,
  "type": "Feature",
  "properties": {
    "tgn:hierarchy":[
        "tgn:1049658",
        "tgn:1000882",
        "tgn:1000003",
        "tgn:1000090",
        "tgn:7029392"
    ],
    "tgn:id":1049658,
    "tgn:name":"Abrunheira",
    "tgn:placetype":[
        "aat:300008347"
    ]
},
  "bbox": [],
  "geometry": {"coordinates":[-9.356,38.773],"type":"Point"}
}