{
  "id": 1116481,
  "type": "Feature",
  "properties": {
    "tgn:hierarchy":[
        "tgn:1116481",
        "tgn:7005685",
        "tgn:7005807",
        "tgn:1000001",
        "tgn:7005801",
        "tgn:7029392"
    ],
    "tgn:id":1116481,
    "tgn:name":"Great Burnt Lake",
    "tgn:placetype":[
        "aat:300008680"
    ]
},
  "bbox": [],
  "geometry": {"coordinates":[-56.25,48.3333],"type":"Point"}
}