{
  "id": 7158159,
  "type": "Feature",
  "properties": {
    "tgn:hierarchy":[
        "tgn:7158159",
        "tgn:1000003",
        "tgn:7003677",
        "tgn:7000084",
        "tgn:7029392"
    ],
    "tgn:id":7158159,
    "tgn:name":"Kleiner Aa-Bach",
    "tgn:placetype":[
        "aat:300008699"
    ]
},
  "bbox": [],
  "geometry": {"coordinates":[8.733333,51.483333],"type":"Point"}
}