{
  "id": 7483802,
  "type": "Feature",
  "properties": {
    "tgn:hierarchy":[
        "tgn:7483802",
        "tgn:7001004",
        "tgn:1000004",
        "tgn:1000141",
        "tgn:7029392"
    ],
    "tgn:id":7483802,
    "tgn:name":"Shuanglianku",
    "tgn:placetype":[
        "aat:300008347"
    ]
},
  "bbox": [],
  "geometry": {"coordinates":[120.6475,23.216111],"type":"Point"}
}