{
  "id": 7522980,
  "type": "Feature",
  "properties": {
    "tgn:hierarchy":[
        "tgn:7522980",
        "tgn:7001242",
        "tgn:7016833",
        "tgn:1001083",
        "tgn:7029392"
    ],
    "tgn:id":7522980,
    "tgn:name:en":"Ash Shawbak al Gharb\u012b",
    "tgn:placetype":[
        "aat:300008347"
    ]
},
  "bbox": [],
  "geometry": {"coordinates":[31.283333,29.783333],"type":"Point"}
}