<<<<<<< HEAD
{
  "id": 2331386,
  "type": "Feature",
  "properties": {
    "tgn:hierarchy":[
        "tgn:2331386",
        "tgn:1000001",
        "tgn:7012149",
        "tgn:2001886",
        "tgn:7007825",
        "tgn:7029392"
    ],
    "tgn:id":2331386,
    "tgn:name":"Flatrock Branch",
    "tgn:placetype":[
        "aat:300008699"
    ]
},
  "bbox": [],
  "geometry": {"coordinates":[-87.3,35.05],"type":"Point"}
}
=======
{"geometry":{"type":"Point","coordinates":[-87.300000,35.050000]},"type":"Feature","properties":{"hierarchy":["tgn:2331386","tgn:1000001","tgn:7012149","tgn:2001886","tgn:7007825","tgn:7029392"],"placetype":["aat:300008699"],"id":2331386,"name:xx":"Flatrock Branch"}}
>>>>>>> 03f74aca74312dbeaf24d7e61306dd6a786dc3d0
