{
  "id": 2220161,
  "type": "Feature",
  "properties": {
    "tgn:hierarchy":[
        "tgn:2220161",
        "tgn:1000001",
        "tgn:7006451",
        "tgn:7012149",
        "tgn:2000098",
        "tgn:7029392"
    ],
    "tgn:id":2220161,
    "tgn:name":"Canyon Ridge",
    "tgn:placetype":[
        "aat:300266640"
    ]
},
  "bbox": [],
  "geometry": {"coordinates":[-114.6167,36.0833],"type":"Point"}
}