{
  "id": 2290650,
  "type": "Feature",
  "properties": {
    "tgn:hierarchy":[
        "tgn:2290650",
        "tgn:7006450",
        "tgn:1000001",
        "tgn:7012149",
        "tgn:2000082",
        "tgn:7029392"
    ],
    "tgn:id":2290650,
    "tgn:name":"Dog Bay",
    "tgn:placetype":[
        "aat:300132316"
    ]
},
  "bbox": [],
  "geometry": {"coordinates":[-131.3333,54.9667],"type":"Point"}
}