{
  "id": 1039993,
  "type": "Feature",
  "properties": {
    "tgn:hierarchy":[
        "tgn:1039993",
        "tgn:1000003",
        "tgn:7003676",
        "tgn:7000084",
        "tgn:7029392"
    ],
    "tgn:id":1039993,
    "tgn:name":"Lachendorf",
    "tgn:placetype":[
        "aat:300008347"
    ]
},
  "bbox": [],
  "geometry": {"coordinates":[10.25,52.616667],"type":"Point"}
}