{
  "id": 7276847,
  "type": "Feature",
  "properties": {
    "tgn:hierarchy":[
        "tgn:7276847",
        "tgn:1001699",
        "tgn:1000049",
        "tgn:1000002",
        "tgn:7029392"
    ],
    "tgn:id":7276847,
    "tgn:name":"Garzas, Islote",
    "tgn:placetype":[
        "aat:300008791"
    ]
},
  "bbox": [],
  "geometry": {"coordinates":[-72.65,-42.05],"type":"Point"}
}