{
  "id": 7249919,
  "type": "Feature",
  "properties": {
    "tgn:hierarchy":[
        "tgn:7249919",
        "tgn:7003466",
        "tgn:1000003",
        "tgn:1000063",
        "tgn:4012014",
        "tgn:7029392"
    ],
    "tgn:id":7249919,
    "tgn:name":"Prahy",
    "tgn:placetype":[
        "aat:300008347"
    ]
},
  "bbox": [],
  "geometry": {"coordinates":[4.633333,50.466667],"type":"Point"}
}