{
  "id": 7472330,
  "type": "Feature",
  "properties": {
    "tgn:hierarchy":[
        "tgn:7472330",
        "tgn:1000004",
        "tgn:7492971",
        "tgn:1000141",
        "tgn:7029392"
    ],
    "tgn:id":7472330,
    "tgn:name":"Wukui",
    "tgn:placetype":[
        "aat:300008347"
    ]
},
  "bbox": [],
  "geometry": {"coordinates":[120.532603,22.561988],"type":"Point"}
}