{
  "id": 1091755,
  "type": "Feature",
  "properties": {
    "tgn:hierarchy":[
        "tgn:1091755",
        "tgn:7001242",
        "tgn:7032820",
        "tgn:1000181",
        "tgn:7029392"
    ],
    "tgn:id":1091755,
    "tgn:name":"Filingu\u00e9",
    "tgn:placetype":[
        "aat:300008347"
    ]
},
  "bbox": [],
  "geometry": {"coordinates":[3.3667,14.35],"type":"Point"}
}