{
  "id": 7418161,
  "type": "Feature",
  "properties": {
    "tgn:hierarchy":[
        "tgn:7418161",
        "tgn:1001835",
        "tgn:1000001",
        "tgn:7005560",
        "tgn:7029392"
    ],
    "tgn:id":7418161,
    "tgn:name":"Ayalo",
    "tgn:placetype":[
        "aat:300008347"
    ]
},
  "bbox": [],
  "geometry": {"coordinates":[-115.004167,32.128611],"type":"Point"}
}