{
  "id": 7299996,
  "type": "Feature",
  "properties": {
    "tgn:hierarchy":[
        "tgn:7299996",
        "tgn:7002839",
        "tgn:7001158",
        "tgn:1000003",
        "tgn:1000095",
        "tgn:7029392"
    ],
    "tgn:id":7299996,
    "tgn:name":"Torreguti\u00e9rrez",
    "tgn:placetype":[
        "aat:300008347"
    ]
},
  "bbox": [],
  "geometry": {"coordinates":[-4.35,41.416667],"type":"Point"}
}