{
  "id": 2206045,
  "type": "Feature",
  "properties": {
    "tgn:hierarchy":[
        "tgn:2206045",
        "tgn:1000001",
        "tgn:7012149",
        "tgn:2001708",
        "tgn:7007708",
        "tgn:7029392"
    ],
    "tgn:id":2206045,
    "tgn:name":"Bull Run Reservoir",
    "tgn:placetype":[
        "aat:300006191"
    ]
},
  "bbox": [],
  "geometry": {"coordinates":[-118.9333,44.1667],"type":"Point"}
}