{
  "id": 2132328,
  "type": "Feature",
  "properties": {
    "tgn:hierarchy":[
        "tgn:2132328",
        "tgn:1000001",
        "tgn:7012149",
        "tgn:2001507",
        "tgn:7007709",
        "tgn:7029392"
    ],
    "tgn:id":2132328,
    "tgn:name":"Amity Hill",
    "tgn:placetype":[
        "aat:300008347"
    ]
},
  "bbox": [],
  "geometry": {"coordinates":[-80.7667,35.6833],"type":"Point"}
}