{
  "id": 7486998,
  "type": "Feature",
  "properties": {
    "tgn:hierarchy":[
        "tgn:7486998",
        "tgn:1000004",
        "tgn:7492971",
        "tgn:1000141",
        "tgn:7029392"
    ],
    "tgn:id":7486998,
    "tgn:name":"Lilu",
    "tgn:placetype":[
        "aat:300008347"
    ]
},
  "bbox": [],
  "geometry": {"coordinates":[120.766667,22.75],"type":"Point"}
}