{
  "id": 7593006,
  "type": "Feature",
  "properties": {
    "tgn:hierarchy":[
        "tgn:7593006",
        "tgn:1000004",
        "tgn:7000198",
        "tgn:7000799",
        "tgn:7029392"
    ],
    "tgn:id":7593006,
    "tgn:name:en":"Gon Kargil",
    "tgn:placetype":[
        "aat:300008347"
    ]
},
  "bbox": [],
  "geometry": {"coordinates":[76.119444,34.569444],"type":"Point"}
}