<<<<<<< HEAD
{
  "id": 7358517,
  "type": "Feature",
  "properties": {
    "tgn:hierarchy":[
        "tgn:7358517",
        "tgn:1000001",
        "tgn:7005597",
        "tgn:7005560",
        "tgn:7029392"
    ],
    "tgn:id":7358517,
    "tgn:name":"Dependencia",
    "tgn:placetype":[
        "aat:300008347"
    ]
},
  "bbox": [],
  "geometry": {"coordinates":[-99.666667,27.483333],"type":"Point"}
}
=======
{"geometry":{"type":"Point","coordinates":[-99.666667,27.483333]},"type":"Feature","properties":{"hierarchy":["tgn:7358517","tgn:1000001","tgn:7005597","tgn:7005560","tgn:7029392"],"placetype":["aat:300008347"],"id":7358517,"name:xx":"Dependencia"}}
>>>>>>> 03f74aca74312dbeaf24d7e61306dd6a786dc3d0
