{
  "id": 7072434,
  "type": "Feature",
  "properties": {
    "tgn:hierarchy":[
        "tgn:7072434",
        "tgn:7003669",
        "tgn:1000003",
        "tgn:7000084",
        "tgn:7029392"
    ],
    "tgn:id":7072434,
    "tgn:name":"Taschnerhof",
    "tgn:placetype":[
        "aat:300000206"
    ]
},
  "bbox": [],
  "geometry": {"coordinates":[12.783333,48.383333],"type":"Point"}
}