{
  "id": 2317406,
  "type": "Feature",
  "properties": {
    "tgn:hierarchy":[
        "tgn:2317406",
        "tgn:1000001",
        "tgn:7012149",
        "tgn:1002296",
        "tgn:7007157",
        "tgn:7029392"
    ],
    "tgn:id":2317406,
    "tgn:name":"Empire Mine",
    "tgn:placetype":[
        "aat:300000390"
    ]
},
  "bbox": [],
  "geometry": {"coordinates":[-122.4167,39.0333],"type":"Point"}
}