{
  "id": 2264964,
  "type": "Feature",
  "properties": {
    "tgn:hierarchy":[
        "tgn:2264964",
        "tgn:1000001",
        "tgn:7012149",
        "tgn:1003042",
        "tgn:7007920",
        "tgn:7029392"
    ],
    "tgn:id":2264964,
    "tgn:name":"Cramer Mountain",
    "tgn:placetype":[
        "aat:300008798"
    ]
},
  "bbox": [],
  "geometry": {"coordinates":[-121.3667,46.6833],"type":"Point"}
}