{
  "id": 7242018,
  "type": "Feature",
  "properties": {
    "tgn:hierarchy":[
        "tgn:7242018",
        "tgn:7003458",
        "tgn:1000003",
        "tgn:1000063",
        "tgn:7018236",
        "tgn:7029392"
    ],
    "tgn:id":7242018,
    "tgn:name":"Kleitgat",
    "tgn:placetype":[
        "aat:300008347"
    ]
},
  "bbox": [],
  "geometry": {"coordinates":[3.260493,50.776837],"type":"Point"}
}