{
  "id": 7232659,
  "type": "Feature",
  "properties": {
    "tgn:hierarchy":[
        "tgn:7232659",
        "tgn:7002711",
        "tgn:7001338",
        "tgn:1000003",
        "tgn:1000074",
        "tgn:7029392"
    ],
    "tgn:id":7232659,
    "tgn:name":"Kothon\u00edkion",
    "tgn:placetype":[
        "aat:300008347"
    ]
},
  "bbox": [],
  "geometry": {"coordinates":[19.868889,39.583889],"type":"Point"}
}