<<<<<<< HEAD
{
  "id": 7367368,
  "type": "Feature",
  "properties": {
    "tgn:hierarchy":[
        "tgn:7367368",
        "tgn:1000001",
        "tgn:7005595",
        "tgn:7005560",
        "tgn:7029392"
    ],
    "tgn:id":7367368,
    "tgn:name":"El Tule Alto",
    "tgn:placetype":[
        "aat:300008347"
    ]
},
  "bbox": [],
  "geometry": {"coordinates":[-107.866667,25.65],"type":"Point"}
}
=======
{"geometry":{"type":"Point","coordinates":[-107.866667,25.650000]},"type":"Feature","properties":{"hierarchy":["tgn:7367368","tgn:1000001","tgn:7005595","tgn:7005560","tgn:7029392"],"placetype":["aat:300008347"],"id":7367368,"name:xx":"El Tule Alto"}}
>>>>>>> 03f74aca74312dbeaf24d7e61306dd6a786dc3d0
