{
  "id": 2681990,
  "type": "Feature",
  "properties": {
    "tgn:hierarchy":[
        "tgn:2681990",
        "tgn:1000001",
        "tgn:2001430",
        "tgn:7012149",
        "tgn:7007566",
        "tgn:7029392"
    ],
    "tgn:id":2681990,
    "tgn:name":"South Spring Acres",
    "tgn:placetype":[
        "aat:300008347"
    ]
},
  "bbox": [],
  "geometry": {"coordinates":[-104.4833,33.3333],"type":"Point"}
}