{
  "id": 2305169,
  "type": "Feature",
  "properties": {
    "tgn:hierarchy":[
        "tgn:2305169",
        "tgn:1000001",
        "tgn:7012149",
        "tgn:2000987",
        "tgn:7007520",
        "tgn:7029392"
    ],
    "tgn:id":2305169,
    "tgn:name":"East Branch Pine River",
    "tgn:placetype":[
        "aat:300008707"
    ]
},
  "bbox": [],
  "geometry": {"coordinates":[-85.4333,44.15],"type":"Point"}
}