{
  "id": 7387139,
  "type": "Feature",
  "properties": {
    "tgn:hierarchy":[
        "tgn:7387139",
        "tgn:1001853",
        "tgn:1000001",
        "tgn:7005560",
        "tgn:7029392"
    ],
    "tgn:id":7387139,
    "tgn:name":"Rancho Balconcitos",
    "tgn:placetype":[
        "aat:300008347"
    ]
},
  "bbox": [],
  "geometry": {"coordinates":[-101.25,27.483333],"type":"Point"}
}