{
  "id": 7221246,
  "type": "Feature",
  "properties": {
    "tgn:hierarchy":[
        "tgn:7221246",
        "tgn:7011164",
        "tgn:7002674",
        "tgn:1000003",
        "tgn:1000074",
        "tgn:7029392"
    ],
    "tgn:id":7221246,
    "tgn:name":"Prof\u00edtis Il\u00edas",
    "tgn:placetype":[
        "aat:300007466"
    ]
},
  "bbox": [],
  "geometry": {"coordinates":[26.745,37.7275],"type":"Point"}
}