{
  "id": 7278427,
  "type": "Feature",
  "properties": {
    "tgn:hierarchy":[
        "tgn:7278427",
        "tgn:1001768",
        "tgn:1000049",
        "tgn:1000002",
        "tgn:7029392"
    ],
    "tgn:id":7278427,
    "tgn:name":"Pulhu\u00e9, Cerro",
    "tgn:placetype":[
        "aat:300008795"
    ]
},
  "bbox": [],
  "geometry": {"coordinates":[-71.239722,-32.396389],"type":"Point"}
}