<<<<<<< HEAD
{
  "id": 7481402,
  "type": "Feature",
  "properties": {
    "tgn:hierarchy":[
        "tgn:7481402",
        "tgn:1000004",
        "tgn:1000454",
        "tgn:1000141",
        "tgn:7029392"
    ],
    "tgn:id":7481402,
    "tgn:name":"Pengjia Yu Dengta",
    "tgn:placetype":[
        "aat:300007741"
    ]
},
  "bbox": [],
  "geometry": {"coordinates":[122.080278,25.630833],"type":"Point"}
}
=======
{"geometry":{"type":"Point","coordinates":[122.080278,25.630833]},"type":"Feature","properties":{"hierarchy":["tgn:7481402","tgn:1000004","tgn:1000454","tgn:1000141","tgn:7029392"],"placetype":["aat:300007741"],"id":7481402,"name:xx":"Pengjia Yu Dengta"}}
>>>>>>> 03f74aca74312dbeaf24d7e61306dd6a786dc3d0
