{
  "id": 7425532,
  "type": "Feature",
  "properties": {
    "tgn:hierarchy":[
        "tgn:7425532",
        "tgn:7005581",
        "tgn:1000001",
        "tgn:7005560",
        "tgn:7029392"
    ],
    "tgn:id":7425532,
    "tgn:name":"San Antonio del Zoquete",
    "tgn:placetype":[
        "aat:300008347"
    ]
},
  "bbox": [],
  "geometry": {"coordinates":[-104.583333,26.866667],"type":"Point"}
}