{
  "id": 2659465,
  "type": "Feature",
  "properties": {
    "tgn:hierarchy":[
        "tgn:2659465",
        "tgn:1000001",
        "tgn:7012149",
        "tgn:7013941",
        "tgn:7007568",
        "tgn:7029392"
    ],
    "tgn:id":2659465,
    "tgn:name":"Shingle Bay",
    "tgn:placetype":[
        "aat:300132316"
    ]
},
  "bbox": [],
  "geometry": {"coordinates":[-74.1833,44.3167],"type":"Point"}
}