{
  "id": 2239796,
  "type": "Feature",
  "properties": {
    "tgn:hierarchy":[
        "tgn:2239796",
        "tgn:1000001",
        "tgn:7012149",
        "tgn:2002057",
        "tgn:7007826",
        "tgn:7029392"
    ],
    "tgn:id":2239796,
    "tgn:name":"Cienega Creek",
    "tgn:placetype":[
        "aat:300008706"
    ]
},
  "bbox": [],
  "geometry": {"coordinates":[-104.2667,30.0167],"type":"Point"}
}