<<<<<<< HEAD
{
  "id": 2766332,
  "type": "Feature",
  "properties": {
    "tgn:hierarchy":[
        "tgn:2766332",
        "tgn:1000001",
        "tgn:7012149",
        "tgn:2001449",
        "tgn:7007566",
        "tgn:7029392"
    ],
    "tgn:id":2766332,
    "tgn:name":"White Mine",
    "tgn:placetype":[
        "aat:300000390"
    ]
},
  "bbox": [],
  "geometry": {"coordinates":[-106.0333,36.45],"type":"Point"}
}
=======
{"geometry":{"type":"Point","coordinates":[-106.033300,36.450000]},"type":"Feature","properties":{"hierarchy":["tgn:2766332","tgn:1000001","tgn:7012149","tgn:2001449","tgn:7007566","tgn:7029392"],"placetype":["aat:300000390"],"id":2766332,"name:xx":"White Mine"}}
>>>>>>> 03f74aca74312dbeaf24d7e61306dd6a786dc3d0
