{
  "id": 2374027,
  "type": "Feature",
  "properties": {
    "tgn:hierarchy":[
        "tgn:2374027",
        "tgn:1000001",
        "tgn:2001735",
        "tgn:7012149",
        "tgn:7007712",
        "tgn:7029392"
    ],
    "tgn:id":2374027,
    "tgn:name":"Hammett Lake",
    "tgn:placetype":[
        "aat:300006191"
    ]
},
  "bbox": [],
  "geometry": {"coordinates":[-81.7167,34.9667],"type":"Point"}
}