{
  "id": 7233927,
  "type": "Feature",
  "properties": {
    "tgn:hierarchy":[
        "tgn:7233927",
        "tgn:7002741",
        "tgn:7017076",
        "tgn:1000003",
        "tgn:1000074",
        "tgn:7029392"
    ],
    "tgn:id":7233927,
    "tgn:name":"Dhesf\u00edna",
    "tgn:placetype":[
        "aat:300008347"
    ]
},
  "bbox": [],
  "geometry": {"coordinates":[22.533333,38.416667],"type":"Point"}
}