{
  "id": 2749483,
  "type": "Feature",
  "properties": {
    "tgn:hierarchy":[
        "tgn:2749483",
        "tgn:1000001",
        "tgn:7012149",
        "tgn:2001536",
        "tgn:7007709",
        "tgn:7029392"
    ],
    "tgn:id":2749483,
    "tgn:name":"Walnut Branch",
    "tgn:placetype":[
        "aat:300008699"
    ]
},
  "bbox": [],
  "geometry": {"coordinates":[-80.55,35.6833],"type":"Point"}
}