{
  "id": 2530183,
  "type": "Feature",
  "properties": {
    "tgn:hierarchy":[
        "tgn:2530183",
        "tgn:1000001",
        "tgn:7006451",
        "tgn:2000092",
        "tgn:7012149",
        "tgn:7029392"
    ],
    "tgn:id":2530183,
    "tgn:name":"Mud Springs",
    "tgn:placetype":[
        "aat:300008697"
    ]
},
  "bbox": [],
  "geometry": {"coordinates":[-112.1833,35.1167],"type":"Point"}
}