{
  "id": 7012222,
  "type": "Feature",
  "properties": {
    "tgn:hierarchy":[
        "tgn:7012222",
        "tgn:1000004",
        "tgn:7029392"
    ],
    "tgn:id":7012222,
    "tgn:name:en":"Tejen",
    "tgn:placetype":[
        "aat:300008707"
    ]
},
  "bbox": [],
  "geometry": {"coordinates":[60.6667,37.4167],"type":"Point"}
}