{
  "id": 7265741,
  "type": "Feature",
  "properties": {
    "tgn:concordances":{
        "gn:id":"2753346"
    },
    "tgn:hierarchy":[
        "tgn:7265741",
        "tgn:1000003",
        "tgn:7003622",
        "tgn:7016845",
        "tgn:7029392"
    ],
    "tgn:id":7265741,
    "tgn:name:nl":"IJzeren",
    "tgn:placetype":[
        "aat:300008347"
    ]
},
  "bbox": [],
  "geometry": {"coordinates":[5.833333,50.833333],"type":"Point"}
}