{
  "id": 2594365,
  "type": "Feature",
  "properties": {
    "tgn:hierarchy":[
        "tgn:2594365",
        "tgn:1000001",
        "tgn:7012149",
        "tgn:1002358",
        "tgn:7007710",
        "tgn:7029392"
    ],
    "tgn:id":2594365,
    "tgn:name":"Porter Run",
    "tgn:placetype":[
        "aat:300008699"
    ]
},
  "bbox": [],
  "geometry": {"coordinates":[-80.1667,41.9333],"type":"Point"}
}