{
  "id": 2534680,
  "type": "Feature",
  "properties": {
    "tgn:hierarchy":[
        "tgn:2534680",
        "tgn:1000001",
        "tgn:7020680",
        "tgn:7012149",
        "tgn:7007256",
        "tgn:7029392"
    ],
    "tgn:id":2534680,
    "tgn:name":"Nabors Pond",
    "tgn:placetype":[
        "aat:300006191"
    ]
},
  "bbox": [],
  "geometry": {"coordinates":[-93.7167,32.0333],"type":"Point"}
}