<<<<<<< HEAD
{
  "id": 2158598,
  "type": "Feature",
  "properties": {
    "tgn:hierarchy":[
        "tgn:2158598",
        "tgn:1000001",
        "tgn:7012149",
        "tgn:7013961",
        "tgn:7029392"
    ],
    "tgn:id":2158598,
    "tgn:name":"Beaverdam Run",
    "tgn:placetype":[
        "aat:300008699"
    ]
},
  "bbox": [],
  "geometry": {"coordinates":[-81.3,38.9],"type":"Point"}
}
=======
{"geometry":{"type":"Point","coordinates":[-81.300000,38.900000]},"type":"Feature","properties":{"hierarchy":["tgn:2158598","tgn:1000001","tgn:7012149","tgn:7013961","tgn:7029392"],"placetype":["aat:300008699"],"id":2158598,"name:xx":"Beaverdam Run"}}
>>>>>>> 03f74aca74312dbeaf24d7e61306dd6a786dc3d0
