{
  "id": 7125758,
  "type": "Feature",
  "properties": {
    "tgn:hierarchy":[
        "tgn:7125758",
        "tgn:1000003",
        "tgn:7003688",
        "tgn:7000084",
        "tgn:7029392"
    ],
    "tgn:id":7125758,
    "tgn:name":"Norderwurth",
    "tgn:placetype":[
        "aat:300000206"
    ]
},
  "bbox": [],
  "geometry": {"coordinates":[9.116667,54.166667],"type":"Point"}
}