{
  "id": 2505058,
  "type": "Feature",
  "properties": {
    "tgn:hierarchy":[
        "tgn:2505058",
        "tgn:7002659",
        "tgn:1000001",
        "tgn:7012149",
        "tgn:2000031",
        "tgn:7029392"
    ],
    "tgn:id":2505058,
    "tgn:name":"Meeting House Branch",
    "tgn:placetype":[
        "aat:300008699"
    ]
},
  "bbox": [],
  "geometry": {"coordinates":[-88.0333,32.75],"type":"Point"}
}