{
  "id": 1116097,
  "type": "Feature",
  "properties": {
    "tgn:hierarchy":[
        "tgn:1116097",
        "tgn:7005685",
        "tgn:1000001",
        "tgn:7029392"
    ],
    "tgn:id":1116097,
    "tgn:name":"Desch\u00eanes, Lac",
    "tgn:placetype":[
        "aat:300008680"
    ]
},
  "bbox": [],
  "geometry": {"coordinates":[-75.85,45.3667],"type":"Point"}
}