{
  "id": 1031531,
  "type": "Feature",
  "properties": {
    "tgn:hierarchy":[
        "tgn:1031531",
        "tgn:1001385",
        "tgn:1000003",
        "tgn:1000069",
        "tgn:7029392"
    ],
    "tgn:id":1031531,
    "tgn:name":"Ranua",
    "tgn:placetype":[
        "aat:300008347"
    ]
},
  "bbox": [],
  "geometry": {"coordinates":[26.5667,65.9167],"type":"Point"}
}