{
  "id": 7346488,
  "type": "Feature",
  "properties": {
    "tgn:hierarchy":[
        "tgn:7346488",
        "tgn:7002844",
        "tgn:7030216",
        "tgn:1000003",
        "tgn:1000095",
        "tgn:7029392"
    ],
    "tgn:id":7346488,
    "tgn:name":"Belltal",
    "tgn:placetype":[
        "aat:300008347"
    ]
},
  "bbox": [],
  "geometry": {"coordinates":[1.186076,41.504921],"type":"Point"}
}