{
  "id": 7277080,
  "type": "Feature",
  "properties": {
    "tgn:hierarchy":[
        "tgn:7277080",
        "tgn:7002464",
        "tgn:1000049",
        "tgn:1000002",
        "tgn:7029392"
    ],
    "tgn:id":7277080,
    "tgn:name":"Picutane, Cerro",
    "tgn:placetype":[
        "aat:300008795"
    ]
},
  "bbox": [],
  "geometry": {"coordinates":[-69.913056,-17.553056],"type":"Point"}
}