{
  "id": 7558435,
  "type": "Feature",
  "properties": {
    "tgn:hierarchy":[
        "tgn:7558435",
        "tgn:1000004",
        "tgn:7000198",
        "tgn:7016883",
        "tgn:7029392"
    ],
    "tgn:id":7558435,
    "tgn:name:en":"Pati\u0101lew\u0101li Nad\u012b",
    "tgn:placetype":[
        "aat:300008699"
    ]
},
  "bbox": [],
  "geometry": {"coordinates":[76.243749,30.079119],"type":"Point"}
}