{
  "id": 2626735,
  "type": "Feature",
  "properties": {
    "tgn:hierarchy":[
        "tgn:2626735",
        "tgn:1000001",
        "tgn:7012149",
        "tgn:1002913",
        "tgn:7007919",
        "tgn:7029392"
    ],
    "tgn:id":2626735,
    "tgn:name":"Rocky Pen Run",
    "tgn:placetype":[
        "aat:300008699"
    ]
},
  "bbox": [],
  "geometry": {"coordinates":[-77.5167,38.3667],"type":"Point"}
}