{
  "id": 7564754,
  "type": "Feature",
  "properties": {
    "tgn:hierarchy":[
        "tgn:7564754",
        "tgn:1000004",
        "tgn:7000198",
        "tgn:1001894",
        "tgn:7029392"
    ],
    "tgn:id":7564754,
    "tgn:name:en":"Ph\u016blpur",
    "tgn:placetype":[
        "aat:300008347"
    ]
},
  "bbox": [],
  "geometry": {"coordinates":[79.100519,24.94619],"type":"Point"}
}