{
  "id": 2148301,
  "type": "Feature",
  "properties": {
    "tgn:hierarchy":[
        "tgn:2148301",
        "tgn:1000001",
        "tgn:7012149",
        "tgn:2001718",
        "tgn:7007708",
        "tgn:7029392"
    ],
    "tgn:id":2148301,
    "tgn:name":"Barlow Reservoir",
    "tgn:placetype":[
        "aat:300006191"
    ]
},
  "bbox": [],
  "geometry": {"coordinates":[-117.0833,43.0667],"type":"Point"}
}