<<<<<<< HEAD
{
  "id": 7488883,
  "type": "Feature",
  "properties": {
    "tgn:hierarchy":[
        "tgn:7488883",
        "tgn:1000004",
        "tgn:7001014",
        "tgn:1000141",
        "tgn:7029392"
    ],
    "tgn:id":7488883,
    "tgn:name":"Huwei Zhen",
    "tgn:placetype":[
        "aat:300387173"
    ]
},
  "bbox": [],
  "geometry": {"coordinates":[120.433333,23.716667],"type":"Point"}
}
=======
{"geometry":{"type":"Point","coordinates":[120.433333,23.716667]},"type":"Feature","properties":{"hierarchy":["tgn:7488883","tgn:1000004","tgn:7001014","tgn:1000141","tgn:7029392"],"placetype":["aat:300387173"],"id":7488883,"name:xx":"Huwei Zhen"}}
>>>>>>> 03f74aca74312dbeaf24d7e61306dd6a786dc3d0
