{
  "id": 2648652,
  "type": "Feature",
  "properties": {
    "tgn:hierarchy":[
        "tgn:2648652",
        "tgn:1000001",
        "tgn:7012149",
        "tgn:2002127",
        "tgn:7007827",
        "tgn:7029392"
    ],
    "tgn:id":2648652,
    "tgn:name":"Scoggins Wash",
    "tgn:placetype":[
        "aat:300008761"
    ]
},
  "bbox": [],
  "geometry": {"coordinates":[-113.0167,37.2167],"type":"Point"}
}