{
  "id": 7314093,
  "type": "Feature",
  "properties": {
    "tgn:hierarchy":[
        "tgn:7314093",
        "tgn:1001705",
        "tgn:1000049",
        "tgn:1000002",
        "tgn:7029392"
    ],
    "tgn:id":7314093,
    "tgn:name":"La Tutela, Puntilla",
    "tgn:placetype":[
        "aat:300386846"
    ]
},
  "bbox": [],
  "geometry": {"coordinates":[-72.183333,-34.883333],"type":"Point"}
}