{
  "id": 2412154,
  "type": "Feature",
  "properties": {
    "tgn:hierarchy":[
        "tgn:2412154",
        "tgn:1000001",
        "tgn:7012149",
        "tgn:2002189",
        "tgn:7007919",
        "tgn:7029392"
    ],
    "tgn:id":2412154,
    "tgn:name":"Indian Skull Cave",
    "tgn:placetype":[
        "aat:300008746"
    ]
},
  "bbox": [],
  "geometry": {"coordinates":[-82.8833,36.6333],"type":"Point"}
}