{
  "id": 7229952,
  "type": "Feature",
  "properties": {
    "tgn:hierarchy":[
        "tgn:7229952",
        "tgn:7002707",
        "tgn:7002705",
        "tgn:1000003",
        "tgn:1000074",
        "tgn:7029392"
    ],
    "tgn:id":7229952,
    "tgn:name":"Meg\u00e1li G\u00f3tista",
    "tgn:placetype":[
        "aat:300008347"
    ]
},
  "bbox": [],
  "geometry": {"coordinates":[21.0425,39.684444],"type":"Point"}
}