{
  "id": 7329929,
  "type": "Feature",
  "properties": {
    "tgn:hierarchy":[
        "tgn:7329929",
        "tgn:7002758",
        "tgn:7002821",
        "tgn:1000003",
        "tgn:1000095",
        "tgn:7029392"
    ],
    "tgn:id":7329929,
    "tgn:name":"Hu\u00e9tor Vega",
    "tgn:placetype":[
        "aat:300008347"
    ]
},
  "bbox": [],
  "geometry": {"coordinates":[-3.566667,37.15],"type":"Point"}
}