{
  "id": 2258531,
  "type": "Feature",
  "properties": {
    "tgn:hierarchy":[
        "tgn:2258531",
        "tgn:1000001",
        "tgn:7012149",
        "tgn:2002379",
        "tgn:7007923",
        "tgn:7029392"
    ],
    "tgn:id":2258531,
    "tgn:name":"Cottongrass Creek",
    "tgn:placetype":[
        "aat:300008706"
    ]
},
  "bbox": [],
  "geometry": {"coordinates":[-110.3833,44.6333],"type":"Point"}
}