{
  "id": 7039525,
  "type": "Feature",
  "properties": {
    "tgn:hierarchy":[
        "tgn:7039525",
        "tgn:1003440",
        "tgn:1000003",
        "tgn:7003124",
        "tgn:1000080",
        "tgn:7029392"
    ],
    "tgn:id":7039525,
    "tgn:name":"San Vito",
    "tgn:placetype":[
        "aat:300008347"
    ]
},
  "bbox": [],
  "geometry": {"coordinates":[12.102222,46.714167],"type":"Point"}
}