{
  "id": 2394136,
  "type": "Feature",
  "properties": {
    "tgn:hierarchy":[
        "tgn:2394136",
        "tgn:1000001",
        "tgn:7012149",
        "tgn:2001917",
        "tgn:7007825",
        "tgn:7029392"
    ],
    "tgn:id":2394136,
    "tgn:name":"Hogan Hollow",
    "tgn:placetype":[
        "aat:300008761"
    ]
},
  "bbox": [],
  "geometry": {"coordinates":[-87.8333,36.4333],"type":"Point"}
}