<<<<<<< HEAD
{
  "id": 7115615,
  "type": "Feature",
  "properties": {
    "tgn:hierarchy":[
        "tgn:7115615",
        "tgn:1000003",
        "tgn:7003684",
        "tgn:7000084",
        "tgn:7029392"
    ],
    "tgn:id":7115615,
    "tgn:name":"Oberw\u00fcrzbach",
    "tgn:placetype":[
        "aat:300008347"
    ]
},
  "bbox": [],
  "geometry": {"coordinates":[7.15,49.25],"type":"Point"}
}
=======
{"geometry":{"type":"Point","coordinates":[7.150000,49.250000]},"type":"Feature","properties":{"hierarchy":["tgn:7115615","tgn:1000003","tgn:7003684","tgn:7000084","tgn:7029392"],"placetype":["aat:300008347"],"id":7115615,"name:xx":"Oberw\u00fcrzbach"}}
>>>>>>> 03f74aca74312dbeaf24d7e61306dd6a786dc3d0
