{
  "id": 2592136,
  "type": "Feature",
  "properties": {
    "tgn:hierarchy":[
        "tgn:2592136",
        "tgn:1002300",
        "tgn:1000001",
        "tgn:7012149",
        "tgn:7007564",
        "tgn:7029392"
    ],
    "tgn:id":2592136,
    "tgn:name":"Pontook Reservoir",
    "tgn:placetype":[
        "aat:300006191"
    ]
},
  "bbox": [],
  "geometry": {"coordinates":[-71.2333,44.6333],"type":"Point"}
}