{
  "id": 7227359,
  "type": "Feature",
  "properties": {
    "tgn:hierarchy":[
        "tgn:7227359",
        "tgn:7002739",
        "tgn:7017076",
        "tgn:1000003",
        "tgn:1000074",
        "tgn:7029392"
    ],
    "tgn:id":7227359,
    "tgn:name":"K\u00e1to Dholian\u00e1",
    "tgn:placetype":[
        "aat:300008347"
    ]
},
  "bbox": [],
  "geometry": {"coordinates":[22.683333,37.433333],"type":"Point"}
}