{
  "id": 2478616,
  "type": "Feature",
  "properties": {
    "tgn:hierarchy":[
        "tgn:2478616",
        "tgn:1000001",
        "tgn:7012149",
        "tgn:1002459",
        "tgn:7007706",
        "tgn:7029392"
    ],
    "tgn:id":2478616,
    "tgn:name":"Mader Pond",
    "tgn:placetype":[
        "aat:300006191"
    ]
},
  "bbox": [],
  "geometry": {"coordinates":[-80.8667,40.3667],"type":"Point"}
}