{
  "id": 2451621,
  "type": "Feature",
  "properties": {
    "tgn:hierarchy":[
        "tgn:2451621",
        "tgn:1000001",
        "tgn:7012149",
        "tgn:2001279",
        "tgn:7007524",
        "tgn:7029392"
    ],
    "tgn:id":2451621,
    "tgn:name":"Little Bear Creek",
    "tgn:placetype":[
        "aat:300008706"
    ]
},
  "bbox": [],
  "geometry": {"coordinates":[-113.3833,46.7167],"type":"Point"}
}