<<<<<<< HEAD
{
  "id": 7475777,
  "type": "Feature",
  "properties": {
    "tgn:hierarchy":[
        "tgn:7475777",
        "tgn:1000004",
        "tgn:7489179",
        "tgn:1000141",
        "tgn:7029392"
    ],
    "tgn:id":7475777,
    "tgn:name":"Zhongli Zhan",
    "tgn:placetype":[
        "aat:300007783"
    ]
},
  "bbox": [],
  "geometry": {"coordinates":[121.774951,24.69423],"type":"Point"}
}
=======
{"geometry":{"type":"Point","coordinates":[121.774951,24.694230]},"type":"Feature","properties":{"hierarchy":["tgn:7475777","tgn:1000004","tgn:7489179","tgn:1000141","tgn:7029392"],"placetype":["aat:300007783"],"id":7475777,"name:xx":"Zhongli Zhan"}}
>>>>>>> 03f74aca74312dbeaf24d7e61306dd6a786dc3d0
