{
  "id": 7470063,
  "type": "Feature",
  "properties": {
    "tgn:hierarchy":[
        "tgn:7470063",
        "tgn:1000004",
        "tgn:1000454",
        "tgn:1000141",
        "tgn:7029392"
    ],
    "tgn:id":7470063,
    "tgn:name":"Hengke",
    "tgn:placetype":[
        "aat:300008347"
    ]
},
  "bbox": [],
  "geometry": {"coordinates":[121.617317,25.049268],"type":"Point"}
}