{
  "id": 2543646,
  "type": "Feature",
  "properties": {
    "tgn:hierarchy":[
        "tgn:2543646",
        "tgn:1000001",
        "tgn:2000923",
        "tgn:7012149",
        "tgn:7007515",
        "tgn:7029392"
    ],
    "tgn:id":2543646,
    "tgn:name":"North Augusta",
    "tgn:placetype":[
        "aat:300008347"
    ]
},
  "bbox": [],
  "geometry": {"coordinates":[-69.7833,44.3667],"type":"Point"}
}