{
  "id": 1084836,
  "type": "Feature",
  "properties": {
    "tgn:hierarchy":[
        "tgn:1084836",
        "tgn:7000674",
        "tgn:1000004",
        "tgn:7003877",
        "tgn:1000137",
        "tgn:7029392"
    ],
    "tgn:id":1084836,
    "tgn:name":"Al-Q\u0101rah",
    "tgn:placetype":[
        "aat:300008347"
    ]
},
  "bbox": [],
  "geometry": {"coordinates":[49.6667,25.4167],"type":"Point"}
}