{
  "id": 7424756,
  "type": "Feature",
  "properties": {
    "tgn:hierarchy":[
        "tgn:7424756",
        "tgn:1000001",
        "tgn:7005597",
        "tgn:7005560",
        "tgn:7029392"
    ],
    "tgn:id":7424756,
    "tgn:name":"Bordo La Escondida",
    "tgn:placetype":[
        "aat:300006191"
    ]
},
  "bbox": [],
  "geometry": {"coordinates":[-99.35,24.216667],"type":"Point"}
}