{
  "id": 2315812,
  "type": "Feature",
  "properties": {
    "tgn:hierarchy":[
        "tgn:2315812",
        "tgn:1000001",
        "tgn:7006451",
        "tgn:2000092",
        "tgn:7012149",
        "tgn:7029392"
    ],
    "tgn:id":2315812,
    "tgn:name":"Ellsworth Trick Tank",
    "tgn:placetype":[
        "aat:300006191"
    ]
},
  "bbox": [],
  "geometry": {"coordinates":[-110.9333,34.5833],"type":"Point"}
}