{
  "id": 7370207,
  "type": "Feature",
  "properties": {
    "tgn:hierarchy":[
        "tgn:7370207",
        "tgn:7005580",
        "tgn:1000001",
        "tgn:7005560",
        "tgn:7029392"
    ],
    "tgn:id":7370207,
    "tgn:name":"Jamaica",
    "tgn:placetype":[
        "aat:300008347"
    ]
},
  "bbox": [],
  "geometry": {"coordinates":[-92.516667,15.333333],"type":"Point"}
}