{
  "id": 2350537,
  "type": "Feature",
  "properties": {
    "tgn:hierarchy":[
        "tgn:2350537",
        "tgn:1000001",
        "tgn:7012149",
        "tgn:2000622",
        "tgn:7007253",
        "tgn:7029392"
    ],
    "tgn:id":2350537,
    "tgn:name":"Givin",
    "tgn:placetype":[
        "aat:300008347"
    ]
},
  "bbox": [],
  "geometry": {"coordinates":[-92.65,41.2167],"type":"Point"}
}