{
  "id": 2265500,
  "type": "Feature",
  "properties": {
    "tgn:hierarchy":[
        "tgn:2265500",
        "tgn:1000001",
        "tgn:7012149",
        "tgn:1002924",
        "tgn:7007568",
        "tgn:7029392"
    ],
    "tgn:id":2265500,
    "tgn:name":"Crane Neck",
    "tgn:placetype":[
        "aat:300008850"
    ]
},
  "bbox": [],
  "geometry": {"coordinates":[-73.1333,40.95],"type":"Point"}
}