{
  "id": 7083790,
  "type": "Feature",
  "properties": {
    "tgn:hierarchy":[
        "tgn:7083790",
        "tgn:1000003",
        "tgn:7003685",
        "tgn:7000084",
        "tgn:7029392"
    ],
    "tgn:id":7083790,
    "tgn:name":"Wilhelmsh\u00f6he",
    "tgn:placetype":[
        "aat:300008777"
    ]
},
  "bbox": [],
  "geometry": {"coordinates":[12.316667,50.566667],"type":"Point"}
}