<<<<<<< HEAD
{
  "id": 7481828,
  "type": "Feature",
  "properties": {
    "tgn:hierarchy":[
        "tgn:7481828",
        "tgn:7468018",
        "tgn:1000004",
        "tgn:1000141",
        "tgn:7029392"
    ],
    "tgn:id":7481828,
    "tgn:name":"Haomeili Yugang",
    "tgn:placetype":[
        "aat:300008678"
    ]
},
  "bbox": [],
  "geometry": {"coordinates":[120.125726,23.341174],"type":"Point"}
}
=======
{"geometry":{"type":"Point","coordinates":[120.125726,23.341174]},"type":"Feature","properties":{"hierarchy":["tgn:7481828","tgn:7468018","tgn:1000004","tgn:1000141","tgn:7029392"],"placetype":["aat:300008678"],"id":7481828,"name:xx":"Haomeili Yugang"}}
>>>>>>> 03f74aca74312dbeaf24d7e61306dd6a786dc3d0
