{
  "id": 7481828,
  "type": "Feature",
  "properties": {
    "tgn:hierarchy":[
        "tgn:7481828",
        "tgn:7468018",
        "tgn:1000004",
        "tgn:1000141",
        "tgn:7029392"
    ],
    "tgn:id":7481828,
    "tgn:name":"Haomeili Yugang",
    "tgn:placetype":[
        "aat:300008678"
    ]
},
  "bbox": [],
  "geometry": {"coordinates":[120.125726,23.341174],"type":"Point"}
}