{
  "id": 7129210,
  "type": "Feature",
  "properties": {
    "tgn:hierarchy":[
        "tgn:7129210",
        "tgn:7000096",
        "tgn:1000003",
        "tgn:7000084",
        "tgn:7029392"
    ],
    "tgn:id":7129210,
    "tgn:name":"Mattendorf",
    "tgn:placetype":[
        "aat:300008347"
    ]
},
  "bbox": [],
  "geometry": {"coordinates":[14.55,51.666667],"type":"Point"}
}