<<<<<<< HEAD
{
  "id": 2250302,
  "type": "Feature",
  "properties": {
    "tgn:hierarchy":[
        "tgn:2250302",
        "tgn:1000001",
        "tgn:7012149",
        "tgn:7029392"
    ],
    "tgn:id":2250302,
    "tgn:name":"Collins, Mount",
    "tgn:placetype":[
        "aat:300008798"
    ]
},
  "bbox": [],
  "geometry": {"coordinates":[-83.4667,35.5833],"type":"Point"}
}
=======
{"geometry":{"type":"Point","coordinates":[-83.466700,35.583300]},"type":"Feature","properties":{"hierarchy":["tgn:2250302","tgn:1000001","tgn:7012149","tgn:7029392"],"placetype":["aat:300008798"],"id":2250302,"name:xx":"Collins, Mount"}}
>>>>>>> 03f74aca74312dbeaf24d7e61306dd6a786dc3d0
