{
  "id": 1037654,
  "type": "Feature",
  "properties": {
    "tgn:hierarchy":[
        "tgn:1037654",
        "tgn:7000096",
        "tgn:1000003",
        "tgn:7000084",
        "tgn:7029392"
    ],
    "tgn:id":1037654,
    "tgn:name":"Sch\u00f6nefeld",
    "tgn:placetype":[
        "aat:300008347"
    ]
},
  "bbox": [],
  "geometry": {"coordinates":[13.516667,52.383333],"type":"Point"}
}