{
  "id": 7431274,
  "type": "Feature",
  "properties": {
    "tgn:hierarchy":[
        "tgn:7431274",
        "tgn:7005581",
        "tgn:1000001",
        "tgn:7005560",
        "tgn:7029392"
    ],
    "tgn:id":7431274,
    "tgn:name":"Arroyo de F\u00e9lix",
    "tgn:placetype":[
        "aat:300008347"
    ]
},
  "bbox": [],
  "geometry": {"coordinates":[-106.516667,28.583333],"type":"Point"}
}