{
  "id": 7278575,
  "type": "Feature",
  "properties": {
    "tgn:hierarchy":[
        "tgn:7278575",
        "tgn:1001768",
        "tgn:1000049",
        "tgn:1000002",
        "tgn:7029392"
    ],
    "tgn:id":7278575,
    "tgn:name":"Valle Alegre",
    "tgn:placetype":[
        "aat:300008347"
    ]
},
  "bbox": [],
  "geometry": {"coordinates":[-70.633333,-32.816667],"type":"Point"}
}