{
  "id": 2563434,
  "type": "Feature",
  "properties": {
    "tgn:hierarchy":[
        "tgn:2563434",
        "tgn:1000001",
        "tgn:7012149",
        "tgn:1002515",
        "tgn:7007252",
        "tgn:7029392"
    ],
    "tgn:id":2563434,
    "tgn:name":"Owl Hollow",
    "tgn:placetype":[
        "aat:300008761"
    ]
},
  "bbox": [],
  "geometry": {"coordinates":[-85.2833,38.85],"type":"Point"}
}