{
  "id": 7306955,
  "type": "Feature",
  "properties": {
    "tgn:hierarchy":[
        "tgn:7306955",
        "tgn:7002826",
        "tgn:7001158",
        "tgn:1000003",
        "tgn:1000095",
        "tgn:7029392"
    ],
    "tgn:id":7306955,
    "tgn:name":"Magaz de Cepeda",
    "tgn:placetype":[
        "aat:300008347"
    ]
},
  "bbox": [],
  "geometry": {"coordinates":[-6.066667,42.533333],"type":"Point"}
}