{
  "id": 2637578,
  "type": "Feature",
  "properties": {
    "tgn:hierarchy":[
        "tgn:2637578",
        "tgn:1000001",
        "tgn:7012149",
        "tgn:7029392"
    ],
    "tgn:id":2637578,
    "tgn:name":"Saint Marys Branch",
    "tgn:placetype":[
        "aat:300008699"
    ]
},
  "bbox": [],
  "geometry": {"coordinates":[-90.85,30.9667],"type":"Point"}
}