{
  "id": 2622818,
  "type": "Feature",
  "properties": {
    "tgn:hierarchy":[
        "tgn:2622818",
        "tgn:1000001",
        "tgn:2001587",
        "tgn:7012149",
        "tgn:7007705",
        "tgn:7029392"
    ],
    "tgn:id":2622818,
    "tgn:name":"Robinson Lake",
    "tgn:placetype":[
        "aat:300008680"
    ]
},
  "bbox": [],
  "geometry": {"coordinates":[-102.6167,48.1333],"type":"Point"}
}