{
  "id": 7559278,
  "type": "Feature",
  "properties": {
    "tgn:hierarchy":[
        "tgn:7559278",
        "tgn:1000004",
        "tgn:7000198",
        "tgn:7016788",
        "tgn:7029392"
    ],
    "tgn:id":7559278,
    "tgn:name:en":"Rohat",
    "tgn:placetype":[
        "aat:300007783"
    ]
},
  "bbox": [],
  "geometry": {"coordinates":[73.095871,25.921986],"type":"Point"}
}