{
  "id": 7588155,
  "type": "Feature",
  "properties": {
    "tgn:hierarchy":[
        "tgn:7588155",
        "tgn:1000004",
        "tgn:7000198",
        "tgn:7000799",
        "tgn:7029392"
    ],
    "tgn:id":7588155,
    "tgn:name:en":"Kunyibal",
    "tgn:placetype":[
        "aat:300008347"
    ]
},
  "bbox": [],
  "geometry": {"coordinates":[74.94925,34.011749],"type":"Point"}
}