{
  "id": 2197347,
  "type": "Feature",
  "properties": {
    "tgn:hierarchy":[
        "tgn:2197347",
        "tgn:1000001",
        "tgn:7006451",
        "tgn:2000091",
        "tgn:7012149",
        "tgn:7029392"
    ],
    "tgn:id":2197347,
    "tgn:name":"Brown Canyon",
    "tgn:placetype":[
        "aat:300008761"
    ]
},
  "bbox": [],
  "geometry": {"coordinates":[-110.3167,31.4333],"type":"Point"}
}