{
  "id": 7156196,
  "type": "Feature",
  "properties": {
    "tgn:hierarchy":[
        "tgn:7156196",
        "tgn:1000003",
        "tgn:7003678",
        "tgn:7000084",
        "tgn:7029392"
    ],
    "tgn:id":7156196,
    "tgn:name":"Kemmete",
    "tgn:placetype":[
        "aat:300008699"
    ]
},
  "bbox": [],
  "geometry": {"coordinates":[9.616667,50.45],"type":"Point"}
}