{
  "id": 2174461,
  "type": "Feature",
  "properties": {
    "tgn:hierarchy":[
        "tgn:2174461",
        "tgn:1000001",
        "tgn:7012149",
        "tgn:2002300",
        "tgn:7013961",
        "tgn:7029392"
    ],
    "tgn:id":2174461,
    "tgn:name":"Bishop Knob",
    "tgn:placetype":[
        "aat:300008798"
    ]
},
  "bbox": [],
  "geometry": {"coordinates":[-80.4833,38.3333],"type":"Point"}
}