{
  "id": 2119294,
  "type": "Feature",
  "properties": {
    "tgn:hierarchy":[
        "tgn:2119294",
        "tgn:1000001",
        "tgn:7012149",
        "tgn:2002268",
        "tgn:7013961",
        "tgn:7029392"
    ],
    "tgn:id":2119294,
    "tgn:name":"Mount Alto",
    "tgn:placetype":[
        "aat:300008347"
    ]
},
  "bbox": [],
  "geometry": {"coordinates":[-81.8667,38.85],"type":"Point"}
}