{
  "id": 1101136,
  "type": "Feature",
  "properties": {
    "tgn:hierarchy":[
        "tgn:1101136",
        "tgn:7001242",
        "tgn:1001075",
        "tgn:7016833",
        "tgn:7029392"
    ],
    "tgn:id":1101136,
    "tgn:name":"Sadd Idf\u012bn\u0101",
    "tgn:placetype":[
        "aat:300006084"
    ]
},
  "bbox": [],
  "geometry": {"coordinates":[30.5167,31.2833],"type":"Point"}
}