{
  "id": 2211897,
  "type": "Feature",
  "properties": {
    "tgn:hierarchy":[
        "tgn:2211897",
        "tgn:1000001",
        "tgn:7012149",
        "tgn:2001442",
        "tgn:7007566",
        "tgn:7029392"
    ],
    "tgn:id":2211897,
    "tgn:name":"Butts Pit",
    "tgn:placetype":[
        "aat:300000390"
    ]
},
  "bbox": [],
  "geometry": {"coordinates":[-105.1833,33.3667],"type":"Point"}
}