{
  "id": 2281578,
  "type": "Feature",
  "properties": {
    "tgn:hierarchy":[
        "tgn:2281578",
        "tgn:1000001",
        "tgn:7012149",
        "tgn:7007158",
        "tgn:2000250",
        "tgn:7029392"
    ],
    "tgn:id":2281578,
    "tgn:name":"Deer Creek",
    "tgn:placetype":[
        "aat:300008706"
    ]
},
  "bbox": [],
  "geometry": {"coordinates":[-105.8667,39.5167],"type":"Point"}
}