{
  "id": 2182741,
  "type": "Feature",
  "properties": {
    "tgn:hierarchy":[
        "tgn:2182741",
        "tgn:1000001",
        "tgn:7012149",
        "tgn:2001856",
        "tgn:7007825",
        "tgn:7029392"
    ],
    "tgn:id":2182741,
    "tgn:name":"Blue Spring Hollow",
    "tgn:placetype":[
        "aat:300008761"
    ]
},
  "bbox": [],
  "geometry": {"coordinates":[-88.0667,35.5167],"type":"Point"}
}