{
  "id": 7359274,
  "type": "Feature",
  "properties": {
    "tgn:hierarchy":[
        "tgn:7359274",
        "tgn:1001853",
        "tgn:1000001",
        "tgn:7005560",
        "tgn:7029392"
    ],
    "tgn:id":7359274,
    "tgn:name":"Comanche",
    "tgn:placetype":[
        "aat:300008347"
    ]
},
  "bbox": [],
  "geometry": {"coordinates":[-103.733333,27.166667],"type":"Point"}
}