{
  "id": 7001450,
  "type": "Feature",
  "properties": {
    "tgn:hierarchy":[
        "tgn:7001450",
        "tgn:7001242",
        "tgn:7016833",
        "tgn:1001113",
        "tgn:7029392"
    ],
    "tgn:id":7001450,
    "tgn:name":"\u015e\u0101n al \u1e28ajar al Qibl\u012byah",
    "tgn:placetype":[
        "aat:300008347",
        "aat:300008375"
    ]
},
  "bbox": [],
  "geometry": {"coordinates":[31.872307,30.97478],"type":"Point"}
}