{
  "id": 7537047,
  "type": "Feature",
  "properties": {
    "tgn:hierarchy":[
        "tgn:7537047",
        "tgn:7001242",
        "tgn:7001311",
        "tgn:7016833",
        "tgn:7029392"
    ],
    "tgn:id":7537047,
    "tgn:name:en":"Lawi, W\u00e2di",
    "tgn:placetype":[
        "aat:300379998"
    ]
},
  "bbox": [],
  "geometry": {"coordinates":[34.816667,24.783333],"type":"Point"}
}