{
  "id": 2666069,
  "type": "Feature",
  "properties": {
    "tgn:hierarchy":[
        "tgn:2666069",
        "tgn:7006450",
        "tgn:1000001",
        "tgn:7012149",
        "tgn:2000079",
        "tgn:7029392"
    ],
    "tgn:id":2666069,
    "tgn:name":"Siteeluk Bay",
    "tgn:placetype":[
        "aat:300132316"
    ]
},
  "bbox": [],
  "geometry": {"coordinates":[-171.6667,63.35],"type":"Point"}
}