{
  "id": 7301876,
  "type": "Feature",
  "properties": {
    "tgn:hierarchy":[
        "tgn:7301876",
        "tgn:7002835",
        "tgn:7001158",
        "tgn:1000003",
        "tgn:1000095",
        "tgn:7029392"
    ],
    "tgn:id":7301876,
    "tgn:name":"Miguel Mu\u00f1oz",
    "tgn:placetype":[
        "aat:300008347"
    ]
},
  "bbox": [],
  "geometry": {"coordinates":[-5.716667,40.75],"type":"Point"}
}