{
  "id": 7008027,
  "type": "Feature",
  "properties": {
    "tgn:hierarchy":[
        "tgn:7008027",
        "tgn:1000003",
        "tgn:7002883",
        "tgn:1000070",
        "tgn:7029392"
    ],
    "tgn:id":7008027,
    "tgn:name":"Chars",
    "tgn:placetype":[
        "aat:300008347"
    ]
},
  "bbox": [],
  "geometry": {"coordinates":[1.9833,49.15],"type":"Point"}
}