{
  "id": 7551429,
  "type": "Feature",
  "properties": {
    "tgn:hierarchy":[
        "tgn:7551429",
        "tgn:1000004",
        "tgn:7000198",
        "tgn:1001998",
        "tgn:7029392"
    ],
    "tgn:id":7551429,
    "tgn:name:en":"Boinu River",
    "tgn:placetype":[
        "aat:300387032"
    ]
},
  "bbox": [],
  "geometry": {"coordinates":[92.966667,22.933333],"type":"Point"}
}