{
  "id": 2183379,
  "type": "Feature",
  "properties": {
    "tgn:hierarchy":[
        "tgn:2183379",
        "tgn:1000001",
        "tgn:7012149",
        "tgn:1002795",
        "tgn:7007826",
        "tgn:7029392"
    ],
    "tgn:id":2183379,
    "tgn:name":"Bluff Creek",
    "tgn:placetype":[
        "aat:300008706"
    ]
},
  "bbox": [],
  "geometry": {"coordinates":[-94.7833,30.7333],"type":"Point"}
}