{
  "id": 2242338,
  "type": "Feature",
  "properties": {
    "tgn:hierarchy":[
        "tgn:2242338",
        "tgn:2000919",
        "tgn:1000001",
        "tgn:7012149",
        "tgn:7007515",
        "tgn:7029392"
    ],
    "tgn:id":2242338,
    "tgn:name":"Clayton Brook",
    "tgn:placetype":[
        "aat:300008699"
    ]
},
  "bbox": [],
  "geometry": {"coordinates":[-68.3833,46.6333],"type":"Point"}
}