{
  "id": 2613549,
  "type": "Feature",
  "properties": {
    "tgn:hierarchy":[
        "tgn:2613549",
        "tgn:1000001",
        "tgn:1002190",
        "tgn:7012149",
        "tgn:7007523",
        "tgn:7029392"
    ],
    "tgn:id":2613549,
    "tgn:name":"Reeder Creek",
    "tgn:placetype":[
        "aat:300008706"
    ]
},
  "bbox": [],
  "geometry": {"coordinates":[-92.35,39.15],"type":"Point"}
}