{
  "id": 7554384,
  "type": "Feature",
  "properties": {
    "tgn:hierarchy":[
        "tgn:7554384",
        "tgn:1000004",
        "tgn:7000198",
        "tgn:7001797",
        "tgn:7029392"
    ],
    "tgn:id":7554384,
    "tgn:name:en":"Malatt\u0101r River",
    "tgn:placetype":[
        "aat:300008699"
    ]
},
  "bbox": [],
  "geometry": {"coordinates":[79.816667,11.833333],"type":"Point"}
}