{
  "id": 2457551,
  "type": "Feature",
  "properties": {
    "tgn:hierarchy":[
        "tgn:2457551",
        "tgn:1000001",
        "tgn:7012149",
        "tgn:2001447",
        "tgn:7007566",
        "tgn:7029392"
    ],
    "tgn:id":2457551,
    "tgn:name":"Little Mack Tank",
    "tgn:placetype":[
        "aat:300006191"
    ]
},
  "bbox": [],
  "geometry": {"coordinates":[-105.9333,32.2833],"type":"Point"}
}