{
  "id": 2424523,
  "type": "Feature",
  "properties": {
    "tgn:hierarchy":[
        "tgn:2424523",
        "tgn:1000001",
        "tgn:7012149",
        "tgn:7007157",
        "tgn:2000191",
        "tgn:7029392"
    ],
    "tgn:id":2424523,
    "tgn:name":"Johnson Creek",
    "tgn:placetype":[
        "aat:300008706"
    ]
},
  "bbox": [],
  "geometry": {"coordinates":[-123.2833,40.2667],"type":"Point"}
}