{
  "id": 2327539,
  "type": "Feature",
  "properties": {
    "tgn:hierarchy":[
        "tgn:2327539",
        "tgn:1002158",
        "tgn:1000001",
        "tgn:7012149",
        "tgn:7007523",
        "tgn:7029392"
    ],
    "tgn:id":2327539,
    "tgn:name":"Fish Branch",
    "tgn:placetype":[
        "aat:300008699"
    ]
},
  "bbox": [],
  "geometry": {"coordinates":[-92.0333,39.25],"type":"Point"}
}