{
  "id": 2699380,
  "type": "Feature",
  "properties": {
    "tgn:hierarchy":[
        "tgn:2699380",
        "tgn:1000001",
        "tgn:2001410",
        "tgn:7012149",
        "tgn:7007526",
        "tgn:7029392"
    ],
    "tgn:id":2699380,
    "tgn:name":"Striper Bay",
    "tgn:placetype":[
        "aat:300132316"
    ]
},
  "bbox": [],
  "geometry": {"coordinates":[-114.25,36.0333],"type":"Point"}
}