{
  "id": 7576752,
  "type": "Feature",
  "properties": {
    "tgn:hierarchy":[
        "tgn:7576752",
        "tgn:1000004",
        "tgn:7000198",
        "tgn:7016788",
        "tgn:7029392"
    ],
    "tgn:id":7576752,
    "tgn:name:en":"Kh\u0101ria Tala",
    "tgn:placetype":[
        "aat:300006207"
    ]
},
  "bbox": [],
  "geometry": {"coordinates":[70.134182,27.126499],"type":"Point"}
}