{
  "id": 2348185,
  "type": "Feature",
  "properties": {
    "tgn:hierarchy":[
        "tgn:2348185",
        "tgn:1000001",
        "tgn:7012149",
        "tgn:7007158",
        "tgn:2000248",
        "tgn:7029392"
    ],
    "tgn:id":2348185,
    "tgn:name":"Gertrude Mine",
    "tgn:placetype":[
        "aat:300000390"
    ]
},
  "bbox": [],
  "geometry": {"coordinates":[-107.8167,37.85],"type":"Point"}
}