{
  "id": 2295416,
  "type": "Feature",
  "properties": {
    "tgn:hierarchy":[
        "tgn:2295416",
        "tgn:1000001",
        "tgn:2000924",
        "tgn:7012149",
        "tgn:7007515",
        "tgn:7029392"
    ],
    "tgn:id":2295416,
    "tgn:name":"Drinking Cove",
    "tgn:placetype":[
        "aat:300132316"
    ]
},
  "bbox": [],
  "geometry": {"coordinates":[-69.2167,43.9167],"type":"Point"}
}