{
  "id": 2275895,
  "type": "Feature",
  "properties": {
    "tgn:hierarchy":[
        "tgn:2275895",
        "tgn:1000001",
        "tgn:1002461",
        "tgn:7012149",
        "tgn:7007159",
        "tgn:7029392"
    ],
    "tgn:id":2275895,
    "tgn:name":"Dark Hollow Brook",
    "tgn:placetype":[
        "aat:300008699"
    ]
},
  "bbox": [],
  "geometry": {"coordinates":[-72.4833,41.6833],"type":"Point"}
}