{
  "id": 2552139,
  "type": "Feature",
  "properties": {
    "tgn:hierarchy":[
        "tgn:2552139",
        "tgn:1000001",
        "tgn:2001091",
        "tgn:7012149",
        "tgn:7007522",
        "tgn:7029392"
    ],
    "tgn:id":2552139,
    "tgn:name":"Number One, Ditch",
    "tgn:placetype":[
        "aat:300006075"
    ]
},
  "bbox": [],
  "geometry": {"coordinates":[-90.7833,33.85],"type":"Point"}
}