{
  "id": 2198618,
  "type": "Feature",
  "properties": {
    "tgn:hierarchy":[
        "tgn:2198618",
        "tgn:1000001",
        "tgn:2000783",
        "tgn:7012149",
        "tgn:7007255",
        "tgn:7029392"
    ],
    "tgn:id":2198618,
    "tgn:name":"Browns Pond",
    "tgn:placetype":[
        "aat:300008680"
    ]
},
  "bbox": [],
  "geometry": {"coordinates":[-85.1667,36.7333],"type":"Point"}
}