{
  "id": 7374865,
  "type": "Feature",
  "properties": {
    "tgn:hierarchy":[
        "tgn:7374865",
        "tgn:1001835",
        "tgn:1000001",
        "tgn:7005560",
        "tgn:7029392"
    ],
    "tgn:id":7374865,
    "tgn:name":"La Milla, Cerro",
    "tgn:placetype":[
        "aat:300008795"
    ]
},
  "bbox": [],
  "geometry": {"coordinates":[-115.914722,32.273333],"type":"Point"}
}