{
  "id": 7501003,
  "type": "Feature",
  "properties": {
    "tgn:hierarchy":[
        "tgn:7501003",
        "tgn:1000004",
        "tgn:7467799",
        "tgn:1000141",
        "tgn:7029392"
    ],
    "tgn:id":7501003,
    "tgn:name":"Jinjiaoyi",
    "tgn:placetype":[
        "aat:300008347"
    ]
},
  "bbox": [],
  "geometry": {"coordinates":[120.6127,24.0396],"type":"Point"}
}