{
  "id": 1032124,
  "type": "Feature",
  "properties": {
    "tgn:hierarchy":[
        "tgn:1032124",
        "tgn:1000003",
        "tgn:7001097",
        "tgn:1000070",
        "tgn:7029392"
    ],
    "tgn:id":1032124,
    "tgn:name":"Bertry",
    "tgn:placetype":[
        "aat:300008347"
    ]
},
  "bbox": [],
  "geometry": {"coordinates":[3.45,50.0833],"type":"Point"}
}