<<<<<<< HEAD
{
  "id": 2766599,
  "type": "Feature",
  "properties": {
    "tgn:hierarchy":[
        "tgn:2766599",
        "tgn:1000001",
        "tgn:7012149",
        "tgn:1002263",
        "tgn:7007826",
        "tgn:7029392"
    ],
    "tgn:id":2766599,
    "tgn:name":"White Oak Creek",
    "tgn:placetype":[
        "aat:300008706"
    ]
},
  "bbox": [],
  "geometry": {"coordinates":[-95.15,31.6833],"type":"Point"}
}
=======
{"geometry":{"type":"Point","coordinates":[-95.150000,31.683300]},"type":"Feature","properties":{"hierarchy":["tgn:2766599","tgn:1000001","tgn:7012149","tgn:1002263","tgn:7007826","tgn:7029392"],"placetype":["aat:300008706"],"id":2766599,"name:xx":"White Oak Creek"}}
>>>>>>> 03f74aca74312dbeaf24d7e61306dd6a786dc3d0
