{
  "id": 2345248,
  "type": "Feature",
  "properties": {
    "tgn:hierarchy":[
        "tgn:2345248",
        "tgn:1000001",
        "tgn:7012149",
        "tgn:7007250",
        "tgn:7029392"
    ],
    "tgn:id":2345248,
    "tgn:name":"Garfield Ucon Canal",
    "tgn:placetype":[
        "aat:300006075"
    ]
},
  "bbox": [],
  "geometry": {"coordinates":[-111.9333,43.6167],"type":"Point"}
}