{
  "id": 7285437,
  "type": "Feature",
  "properties": {
    "tgn:hierarchy":[
        "tgn:7285437",
        "tgn:1001623",
        "tgn:1000049",
        "tgn:1000002",
        "tgn:7029392"
    ],
    "tgn:id":7285437,
    "tgn:name":"Pichirupa, Canal",
    "tgn:placetype":[
        "aat:300387026"
    ]
},
  "bbox": [],
  "geometry": {"coordinates":[-74.183333,-45.283333],"type":"Point"}
}