{
  "id": 1009720,
  "type": "Feature",
  "properties": {
    "tgn:hierarchy":[
        "tgn:1009720",
        "tgn:1000001",
        "tgn:7012149",
        "tgn:7007157",
        "tgn:1002901",
        "tgn:7029392"
    ],
    "tgn:id":1009720,
    "tgn:name":"Wheeler Island",
    "tgn:placetype":[
        "aat:300008791"
    ]
},
  "bbox": [],
  "geometry": {"coordinates":[-121.9333,38.0833],"type":"Point"}
}