{
  "id": 7336875,
  "type": "Feature",
  "properties": {
    "tgn:hierarchy":[
        "tgn:7336875",
        "tgn:7001155",
        "tgn:1000003",
        "tgn:7002790",
        "tgn:1000095",
        "tgn:7029392"
    ],
    "tgn:id":7336875,
    "tgn:name":"Gasti\u00e1in",
    "tgn:placetype":[
        "aat:300008347"
    ]
},
  "bbox": [],
  "geometry": {"coordinates":[-2.283156,42.720918],"type":"Point"}
}