{
  "id": 2476582,
  "type": "Feature",
  "properties": {
    "tgn:hierarchy":[
        "tgn:2476582",
        "tgn:1000001",
        "tgn:7012149",
        "tgn:2000550",
        "tgn:7007252",
        "tgn:7029392"
    ],
    "tgn:id":2476582,
    "tgn:name":"Lutgring Hill",
    "tgn:placetype":[
        "aat:300008798"
    ]
},
  "bbox": [],
  "geometry": {"coordinates":[-86.65,37.95],"type":"Point"}
}