{
  "id": 2312508,
  "type": "Feature",
  "properties": {
    "tgn:hierarchy":[
        "tgn:2312508",
        "tgn:1000001",
        "tgn:7006451",
        "tgn:7012149",
        "tgn:2000098",
        "tgn:7029392"
    ],
    "tgn:id":2312508,
    "tgn:name":"Eileen Spring",
    "tgn:placetype":[
        "aat:300008697"
    ]
},
  "bbox": [],
  "geometry": {"coordinates":[-114.2667,35.75],"type":"Point"}
}