<<<<<<< HEAD
{
  "id": 2702950,
  "type": "Feature",
  "properties": {
    "tgn:hierarchy":[
        "tgn:2702950",
        "tgn:1000001",
        "tgn:7012149",
        "tgn:2001709",
        "tgn:7007708",
        "tgn:7029392"
    ],
    "tgn:id":2702950,
    "tgn:name":"Sulphur Springs",
    "tgn:placetype":[
        "aat:300008697"
    ]
},
  "bbox": [],
  "geometry": {"coordinates":[-118.3333,42.8167],"type":"Point"}
}
=======
{"geometry":{"type":"Point","coordinates":[-118.333300,42.816700]},"type":"Feature","properties":{"hierarchy":["tgn:2702950","tgn:1000001","tgn:7012149","tgn:2001709","tgn:7007708","tgn:7029392"],"placetype":["aat:300008697"],"id":2702950,"name:xx":"Sulphur Springs"}}
>>>>>>> 03f74aca74312dbeaf24d7e61306dd6a786dc3d0
