{
  "id": 2469805,
  "type": "Feature",
  "properties": {
    "tgn:hierarchy":[
        "tgn:2469805",
        "tgn:1000001",
        "tgn:7012149",
        "tgn:2002125",
        "tgn:7007827",
        "tgn:7029392"
    ],
    "tgn:id":2469805,
    "tgn:name":"Lookout Spring",
    "tgn:placetype":[
        "aat:300008697"
    ]
},
  "bbox": [],
  "geometry": {"coordinates":[-111.4167,39.9667],"type":"Point"}
}