{
  "id": 7466764,
  "type": "Feature",
  "properties": {
    "tgn:hierarchy":[
        "tgn:7466764",
        "tgn:7002445",
        "tgn:1000003",
        "tgn:7008180",
        "tgn:7008591",
        "tgn:7029392"
    ],
    "tgn:id":7466764,
    "tgn:name:en":"Bishopstrow",
    "tgn:placetype":[
        "aat:300008347"
    ]
},
  "bbox": [],
  "geometry": {"coordinates":[-2.155278,51.193056],"type":"Point"}
}