{
  "id": 2120198,
  "type": "Feature",
  "properties": {
    "tgn:hierarchy":[
        "tgn:2120198",
        "tgn:1000001",
        "tgn:7012149",
        "tgn:2002295",
        "tgn:7013961",
        "tgn:7029392"
    ],
    "tgn:id":2120198,
    "tgn:name":"Thornton",
    "tgn:placetype":[
        "aat:300008347"
    ]
},
  "bbox": [],
  "geometry": {"coordinates":[-79.9333,39.3333],"type":"Point"}
}