{
  "id": 2082460,
  "type": "Feature",
  "properties": {
    "tgn:hierarchy":[
        "tgn:2082460",
        "tgn:1000001",
        "tgn:7012149",
        "tgn:1002917",
        "tgn:7007706",
        "tgn:7029392"
    ],
    "tgn:id":2082460,
    "tgn:name":"Waynesburg",
    "tgn:placetype":[
        "aat:300008347"
    ]
},
  "bbox": [],
  "geometry": {"coordinates":[-81.25,40.6667],"type":"Point"}
}