{
  "id": 1063351,
  "type": "Feature",
  "properties": {
    "tgn:hierarchy":[
        "tgn:1063351",
        "tgn:1000003",
        "tgn:7003777",
        "tgn:1000097",
        "tgn:7029392"
    ],
    "tgn:id":1063351,
    "tgn:name":"M\u00f6lnbo",
    "tgn:placetype":[
        "aat:300008347"
    ]
},
  "bbox": [],
  "geometry": {"coordinates":[17.4167,59.05],"type":"Point"}
}