{
  "id": 7561121,
  "type": "Feature",
  "properties": {
    "tgn:hierarchy":[
        "tgn:7561121",
        "tgn:1000004",
        "tgn:7000198",
        "tgn:7016722",
        "tgn:7029392"
    ],
    "tgn:id":7561121,
    "tgn:name:en":"Sam\u0101dhi",
    "tgn:placetype":[
        "aat:300008347"
    ]
},
  "bbox": [],
  "geometry": {"coordinates":[79.718304,27.53573],"type":"Point"}
}