{
  "id": 2541905,
  "type": "Feature",
  "properties": {
    "tgn:hierarchy":[
        "tgn:2541905",
        "tgn:1000001",
        "tgn:7012149",
        "tgn:2001667",
        "tgn:7007707",
        "tgn:7029392"
    ],
    "tgn:id":2541905,
    "tgn:name":"Nineteen hundred and Eight Cut-off Lake",
    "tgn:placetype":[
        "aat:300008680"
    ]
},
  "bbox": [],
  "geometry": {"coordinates":[-94.6333,33.6833],"type":"Point"}
}