{
  "id": 2632368,
  "type": "Feature",
  "properties": {
    "tgn:hierarchy":[
        "tgn:2632368",
        "tgn:1000001",
        "tgn:7012149",
        "tgn:1002314",
        "tgn:7007240",
        "tgn:7029392"
    ],
    "tgn:id":2632368,
    "tgn:name":"Royal Galdes Canal",
    "tgn:placetype":[
        "aat:300006075"
    ]
},
  "bbox": [],
  "geometry": {"coordinates":[-80.1667,25.9167],"type":"Point"}
}