{
  "id": 2149939,
  "type": "Feature",
  "properties": {
    "tgn:hierarchy":[
        "tgn:2149939",
        "tgn:1000001",
        "tgn:7012149",
        "tgn:7007157",
        "tgn:1002957",
        "tgn:7029392"
    ],
    "tgn:id":2149939,
    "tgn:name":"Bartlett Peak",
    "tgn:placetype":[
        "aat:300008798"
    ]
},
  "bbox": [],
  "geometry": {"coordinates":[-119.7667,38.0833],"type":"Point"}
}