{
  "id": 2614873,
  "type": "Feature",
  "properties": {
    "tgn:hierarchy":[
        "tgn:2614873",
        "tgn:1000001",
        "tgn:7012149",
        "tgn:1002288",
        "tgn:7007523",
        "tgn:7029392"
    ],
    "tgn:id":2614873,
    "tgn:name":"Renns Lake",
    "tgn:placetype":[
        "aat:300006191"
    ]
},
  "bbox": [],
  "geometry": {"coordinates":[-92.2167,38.5333],"type":"Point"}
}