{
  "id": 2411333,
  "type": "Feature",
  "properties": {
    "tgn:hierarchy":[
        "tgn:2411333",
        "tgn:1000001",
        "tgn:7014423",
        "tgn:7012149",
        "tgn:7007517",
        "tgn:7029392"
    ],
    "tgn:id":2411333,
    "tgn:name":"Indian Head Brook",
    "tgn:placetype":[
        "aat:300008699"
    ]
},
  "bbox": [],
  "geometry": {"coordinates":[-70.85,42.0333],"type":"Point"}
}