{
  "id": 2626404,
  "type": "Feature",
  "properties": {
    "tgn:hierarchy":[
        "tgn:2626404",
        "tgn:1000001",
        "tgn:2002318",
        "tgn:7012149",
        "tgn:7007922",
        "tgn:7029392"
    ],
    "tgn:id":2626404,
    "tgn:name":"Rocky Gorge",
    "tgn:placetype":[
        "aat:300008761"
    ]
},
  "bbox": [],
  "geometry": {"coordinates":[-92.1167,46.5333],"type":"Point"}
}