{
  "id": 2671773,
  "type": "Feature",
  "properties": {
    "tgn:hierarchy":[
        "tgn:2671773",
        "tgn:2000258",
        "tgn:1000001",
        "tgn:7012149",
        "tgn:7007240",
        "tgn:7029392"
    ],
    "tgn:id":2671773,
    "tgn:name":"Smith Point",
    "tgn:placetype":[
        "aat:300008850"
    ]
},
  "bbox": [],
  "geometry": {"coordinates":[-85.55,30.1167],"type":"Point"}
}