{
  "id": 2134448,
  "type": "Feature",
  "properties": {
    "tgn:hierarchy":[
        "tgn:2134448",
        "tgn:1000001",
        "tgn:7012149",
        "tgn:2002110",
        "tgn:7007827",
        "tgn:7029392"
    ],
    "tgn:id":2134448,
    "tgn:name":"Anniversary Arch",
    "tgn:placetype":[
        "aat:300386837"
    ]
},
  "bbox": [],
  "geometry": {"coordinates":[-109.6667,38.7833],"type":"Point"}
}