{
  "id": 1066453,
  "type": "Feature",
  "properties": {
    "tgn:hierarchy":[
        "tgn:1066453",
        "tgn:1000004",
        "tgn:7000408",
        "tgn:1000110",
        "tgn:7029392"
    ],
    "tgn:id":1066453,
    "tgn:name":"Dehiwala-Mount Lavinia",
    "tgn:placetype":[
        "aat:300008347",
        "aat:300000547",
        "aat:300379515"
    ]
},
  "bbox": [],
  "geometry": {"coordinates":[79.8667,6.8667],"type":"Point"}
}