{
  "id": 7377378,
  "type": "Feature",
  "properties": {
    "tgn:hierarchy":[
        "tgn:7377378",
        "tgn:1000001",
        "tgn:7005595",
        "tgn:7005560",
        "tgn:7029392"
    ],
    "tgn:id":7377378,
    "tgn:name":"La Pila",
    "tgn:placetype":[
        "aat:300008347"
    ]
},
  "bbox": [],
  "geometry": {"coordinates":[-107.633333,25.316667],"type":"Point"}
}