{
  "id": 7152901,
  "type": "Feature",
  "properties": {
    "tgn:hierarchy":[
        "tgn:7152901",
        "tgn:1000003",
        "tgn:7003685",
        "tgn:7000084",
        "tgn:7029392"
    ],
    "tgn:id":7152901,
    "tgn:name":"J\u00e4gerhof",
    "tgn:placetype":[
        "aat:300000206"
    ]
},
  "bbox": [],
  "geometry": {"coordinates":[12.366667,50.633333],"type":"Point"}
}