{
  "id": 2031905,
  "type": "Feature",
  "properties": {
    "tgn:hierarchy":[
        "tgn:2031905",
        "tgn:1000001",
        "tgn:7012149",
        "tgn:1002465",
        "tgn:7007252",
        "tgn:7029392"
    ],
    "tgn:id":2031905,
    "tgn:name":"Friendswood",
    "tgn:placetype":[
        "aat:300008347"
    ]
},
  "bbox": [],
  "geometry": {"coordinates":[-86.3167,39.6333],"type":"Point"}
}