{
  "id": 1081502,
  "type": "Feature",
  "properties": {
    "tgn:hierarchy":[
        "tgn:1081502",
        "tgn:7016696",
        "tgn:1000004",
        "tgn:7000894",
        "tgn:1000120",
        "tgn:7029392"
    ],
    "tgn:id":1081502,
    "tgn:name":"Tamura",
    "tgn:placetype":[
        "aat:300008347"
    ]
},
  "bbox": [],
  "geometry": {"coordinates":[139.3667,35.3667],"type":"Point"}
}