{
  "id": 2525127,
  "type": "Feature",
  "properties": {
    "tgn:hierarchy":[
        "tgn:2525127",
        "tgn:1000001",
        "tgn:2001428",
        "tgn:7012149",
        "tgn:7007566",
        "tgn:7029392"
    ],
    "tgn:id":2525127,
    "tgn:name":"Morris Pit",
    "tgn:placetype":[
        "aat:300000390"
    ]
},
  "bbox": [],
  "geometry": {"coordinates":[-106.5833,35.1667],"type":"Point"}
}