{
  "id": 2115401,
  "type": "Feature",
  "properties": {
    "tgn:hierarchy":[
        "tgn:2115401",
        "tgn:2002238",
        "tgn:1000001",
        "tgn:7012149",
        "tgn:7007920",
        "tgn:7029392"
    ],
    "tgn:id":2115401,
    "tgn:name":"Bruce",
    "tgn:placetype":[
        "aat:300387016"
    ]
},
  "bbox": [],
  "geometry": {"coordinates":[-119.05,46.8333],"type":"Point"}
}