{
  "id": 1010160,
  "type": "Feature",
  "properties": {
    "tgn:hierarchy":[
        "tgn:1010160",
        "tgn:1000004",
        "tgn:7000894",
        "tgn:1001032",
        "tgn:7006216",
        "tgn:1000120",
        "tgn:7029392"
    ],
    "tgn:id":1010160,
    "tgn:name":"Mukoshima-rett\u014d",
    "tgn:placetype":[
        "aat:300008791"
    ]
},
  "bbox": [],
  "geometry": {"coordinates":[142.1667,27.6167],"type":"Point"}
}