<<<<<<< HEAD
{
  "id": 7475073,
  "type": "Feature",
  "properties": {
    "tgn:hierarchy":[
        "tgn:7475073",
        "tgn:1000004",
        "tgn:7001014",
        "tgn:1000141",
        "tgn:7029392"
    ],
    "tgn:id":7475073,
    "tgn:name":"Dayi Dapai Erhao Qiao",
    "tgn:placetype":[
        "aat:300007836"
    ]
},
  "bbox": [],
  "geometry": {"coordinates":[120.410148,23.78653],"type":"Point"}
}
=======
{"geometry":{"type":"Point","coordinates":[120.410148,23.786530]},"type":"Feature","properties":{"hierarchy":["tgn:7475073","tgn:1000004","tgn:7001014","tgn:1000141","tgn:7029392"],"placetype":["aat:300007836"],"id":7475073,"name:xx":"Dayi Dapai Erhao Qiao"}}
>>>>>>> 03f74aca74312dbeaf24d7e61306dd6a786dc3d0
