{
  "id": 7475073,
  "type": "Feature",
  "properties": {
    "tgn:hierarchy":[
        "tgn:7475073",
        "tgn:1000004",
        "tgn:7001014",
        "tgn:1000141",
        "tgn:7029392"
    ],
    "tgn:id":7475073,
    "tgn:name":"Dayi Dapai Erhao Qiao",
    "tgn:placetype":[
        "aat:300007836"
    ]
},
  "bbox": [],
  "geometry": {"coordinates":[120.410148,23.78653],"type":"Point"}
}