<<<<<<< HEAD
{
  "id": 2401280,
  "type": "Feature",
  "properties": {
    "tgn:hierarchy":[
        "tgn:2401280",
        "tgn:1000001",
        "tgn:1002753",
        "tgn:7012149",
        "tgn:7007828",
        "tgn:7029392"
    ],
    "tgn:id":2401280,
    "tgn:name":"Horseneck Island",
    "tgn:placetype":[
        "aat:300008791"
    ]
},
  "bbox": [],
  "geometry": {"coordinates":[-72.2,44.95],"type":"Point"}
}
=======
{"geometry":{"type":"Point","coordinates":[-72.200000,44.950000]},"type":"Feature","properties":{"hierarchy":["tgn:2401280","tgn:1000001","tgn:1002753","tgn:7012149","tgn:7007828","tgn:7029392"],"placetype":["aat:300008791"],"id":2401280,"name:xx":"Horseneck Island"}}
>>>>>>> 03f74aca74312dbeaf24d7e61306dd6a786dc3d0
