{
  "id": 2613344,
  "type": "Feature",
  "properties": {
    "tgn:hierarchy":[
        "tgn:2613344",
        "tgn:1000001",
        "tgn:7012149",
        "tgn:2002167",
        "tgn:7007919",
        "tgn:7029392"
    ],
    "tgn:id":2613344,
    "tgn:name":"Reed Creek Village",
    "tgn:placetype":[
        "aat:300008347"
    ]
},
  "bbox": [],
  "geometry": {"coordinates":[-79.9167,36.7667],"type":"Point"}
}