{
  "id": 2551264,
  "type": "Feature",
  "properties": {
    "tgn:hierarchy":[
        "tgn:2551264",
        "tgn:1000001",
        "tgn:7012149",
        "tgn:2000215",
        "tgn:7007158",
        "tgn:7029392"
    ],
    "tgn:id":2551264,
    "tgn:name":"Nugget",
    "tgn:placetype":[
        "aat:300008347"
    ]
},
  "bbox": [],
  "geometry": {"coordinates":[-105.5833,39.85],"type":"Point"}
}