{
  "id": 7504037,
  "type": "Feature",
  "properties": {
    "tgn:hierarchy":[
        "tgn:7504037",
        "tgn:1008380",
        "tgn:7000507",
        "tgn:1000226",
        "tgn:1000006",
        "tgn:7029392"
    ],
    "tgn:id":7504037,
    "tgn:name:en":"West Anchorage",
    "tgn:placetype":[
        "aat:300386968"
    ]
},
  "bbox": [],
  "geometry": {"coordinates":[-177.95,-29.266667],"type":"Point"}
}