{
  "id": 2481237,
  "type": "Feature",
  "properties": {
    "tgn:hierarchy":[
        "tgn:2481237",
        "tgn:1000001",
        "tgn:2001841",
        "tgn:7012149",
        "tgn:7007825",
        "tgn:7029392"
    ],
    "tgn:id":2481237,
    "tgn:name":"Lambert Lake",
    "tgn:placetype":[
        "aat:300006191"
    ]
},
  "bbox": [],
  "geometry": {"coordinates":[-83.95,35.65],"type":"Point"}
}