{
  "id": 7534991,
  "type": "Feature",
  "properties": {
    "tgn:hierarchy":[
        "tgn:7534991",
        "tgn:7001242",
        "tgn:7016833",
        "tgn:7000122",
        "tgn:7029392"
    ],
    "tgn:id":7534991,
    "tgn:name:en":"Temple of Horus",
    "tgn:placetype":[
        "aat:300387007"
    ]
},
  "bbox": [],
  "geometry": {"coordinates":[32.866667,24.983333],"type":"Point"}
}