{
  "id": 7294127,
  "type": "Feature",
  "properties": {
    "tgn:hierarchy":[
        "tgn:7294127",
        "tgn:7002760",
        "tgn:1000003",
        "tgn:1000095",
        "tgn:7029392"
    ],
    "tgn:id":7294127,
    "tgn:name":"Via\u00f1a",
    "tgn:placetype":[
        "aat:300008347"
    ]
},
  "bbox": [],
  "geometry": {"coordinates":[-4.266667,43.183333],"type":"Point"}
}