{
  "id": 7214675,
  "type": "Feature",
  "properties": {
    "tgn:hierarchy":[
        "tgn:7214675",
        "tgn:1000003",
        "tgn:7003682",
        "tgn:7000084",
        "tgn:7029392"
    ],
    "tgn:id":7214675,
    "tgn:name":"Beulerhof",
    "tgn:placetype":[
        "aat:300000206"
    ]
},
  "bbox": [],
  "geometry": {"coordinates":[7.216667,50.516667],"type":"Point"}
}