{
  "id": 7256358,
  "type": "Feature",
  "properties": {
    "tgn:hierarchy":[
        "tgn:7256358",
        "tgn:7003614",
        "tgn:1000003",
        "tgn:7016845",
        "tgn:7029392"
    ],
    "tgn:id":7256358,
    "tgn:name:nl":"Annerveensche Mond",
    "tgn:placetype":[
        "aat:300006075"
    ]
},
  "bbox": [],
  "geometry": {"coordinates":[6.75,53.05],"type":"Point"}
}