{
  "id": 7339905,
  "type": "Feature",
  "properties": {
    "tgn:hierarchy":[
        "tgn:7339905",
        "tgn:7002805",
        "tgn:7002758",
        "tgn:1000003",
        "tgn:1000095",
        "tgn:7029392"
    ],
    "tgn:id":7339905,
    "tgn:name":"El Arroyo Aceituno",
    "tgn:placetype":[
        "aat:300008347"
    ]
},
  "bbox": [],
  "geometry": {"coordinates":[-2.066667,37.35],"type":"Point"}
}