<<<<<<< HEAD
{
  "id": 7480626,
  "type": "Feature",
  "properties": {
    "tgn:hierarchy":[
        "tgn:7480626",
        "tgn:1000004",
        "tgn:7490934",
        "tgn:1000141",
        "tgn:7029392"
    ],
    "tgn:id":7480626,
    "tgn:name":"Zheng'an Qiao",
    "tgn:placetype":[
        "aat:300007836"
    ]
},
  "bbox": [],
  "geometry": {"coordinates":[120.148481,23.28939],"type":"Point"}
}
=======
{"geometry":{"type":"Point","coordinates":[120.148481,23.289390]},"type":"Feature","properties":{"hierarchy":["tgn:7480626","tgn:1000004","tgn:7490934","tgn:1000141","tgn:7029392"],"placetype":["aat:300007836"],"id":7480626,"name:xx":"Zheng'an Qiao"}}
>>>>>>> 03f74aca74312dbeaf24d7e61306dd6a786dc3d0
