{
  "id": 2453267,
  "type": "Feature",
  "properties": {
    "tgn:hierarchy":[
        "tgn:2453267",
        "tgn:1000001",
        "tgn:2001473",
        "tgn:7012149",
        "tgn:7007709",
        "tgn:7029392"
    ],
    "tgn:id":2453267,
    "tgn:name":"Little Cedar Mountain",
    "tgn:placetype":[
        "aat:300008798"
    ]
},
  "bbox": [],
  "geometry": {"coordinates":[-82.45,35.55],"type":"Point"}
}