{
  "id": 2460071,
  "type": "Feature",
  "properties": {
    "tgn:hierarchy":[
        "tgn:2460071",
        "tgn:1000001",
        "tgn:7012149",
        "tgn:2001507",
        "tgn:7007709",
        "tgn:7029392"
    ],
    "tgn:id":2460071,
    "tgn:name":"Little Rocky Creek",
    "tgn:placetype":[
        "aat:300008706"
    ]
},
  "bbox": [],
  "geometry": {"coordinates":[-80.95,35.9333],"type":"Point"}
}