{
  "id": 1069985,
  "type": "Feature",
  "properties": {
    "tgn:hierarchy":[
        "tgn:1069985",
        "tgn:1000004",
        "tgn:1000958",
        "tgn:1000111",
        "tgn:7029392"
    ],
    "tgn:id":1069985,
    "tgn:name":"Liujiazhai",
    "tgn:placetype":[
        "aat:300008347"
    ]
},
  "bbox": [],
  "geometry": {"coordinates":[121.45,31.35],"type":"Point"}
}