{
  "id": 7393001,
  "type": "Feature",
  "properties": {
    "tgn:hierarchy":[
        "tgn:7393001",
        "tgn:7005586",
        "tgn:1000001",
        "tgn:7005560",
        "tgn:7029392"
    ],
    "tgn:id":7393001,
    "tgn:name":"San Francisco",
    "tgn:placetype":[
        "aat:300008347"
    ]
},
  "bbox": [],
  "geometry": {"coordinates":[-104.666667,19.183333],"type":"Point"}
}