{
  "id": 7270992,
  "type": "Feature",
  "properties": {
    "tgn:hierarchy":[
        "tgn:7270992",
        "tgn:7003616",
        "tgn:1000003",
        "tgn:7016845",
        "tgn:7029392"
    ],
    "tgn:id":7270992,
    "tgn:name:nl":"Spannumeropvaart",
    "tgn:placetype":[
        "aat:300006075"
    ]
},
  "bbox": [],
  "geometry": {"coordinates":[5.633333,53.116667],"type":"Point"}
}