{
  "id": 2082677,
  "type": "Feature",
  "properties": {
    "tgn:hierarchy":[
        "tgn:2082677",
        "tgn:1000001",
        "tgn:7012149",
        "tgn:1003033",
        "tgn:7007706",
        "tgn:7029392"
    ],
    "tgn:id":2082677,
    "tgn:name":"Woodville Gardens",
    "tgn:placetype":[
        "aat:300008347"
    ]
},
  "bbox": [],
  "geometry": {"coordinates":[-83.45,41.5833],"type":"Point"}
}