{
  "id": 2606100,
  "type": "Feature",
  "properties": {
    "tgn:hierarchy":[
        "tgn:2606100",
        "tgn:1000001",
        "tgn:7012149",
        "tgn:1002594",
        "tgn:7007920",
        "tgn:7029392"
    ],
    "tgn:id":2606100,
    "tgn:name":"Rainey Valley",
    "tgn:placetype":[
        "aat:300008761"
    ]
},
  "bbox": [],
  "geometry": {"coordinates":[-122.0833,46.5333],"type":"Point"}
}