{
  "id": 7213631,
  "type": "Feature",
  "properties": {
    "tgn:hierarchy":[
        "tgn:7213631",
        "tgn:1000003",
        "tgn:7003676",
        "tgn:7000084",
        "tgn:7029392"
    ],
    "tgn:id":7213631,
    "tgn:name":"Bollingerf\u00e4hr",
    "tgn:placetype":[
        "aat:300000206"
    ]
},
  "bbox": [],
  "geometry": {"coordinates":[7.283333,52.966667],"type":"Point"}
}