{
  "id": 2648792,
  "type": "Feature",
  "properties": {
    "tgn:hierarchy":[
        "tgn:2648792",
        "tgn:1000001",
        "tgn:7012149",
        "tgn:2001279",
        "tgn:7007524",
        "tgn:7029392"
    ],
    "tgn:id":2648792,
    "tgn:name":"Scotchman Gulch",
    "tgn:placetype":[
        "aat:300008761"
    ]
},
  "bbox": [],
  "geometry": {"coordinates":[-113.5833,46.4167],"type":"Point"}
}