{
  "id": 2217544,
  "type": "Feature",
  "properties": {
    "tgn:hierarchy":[
        "tgn:2217544",
        "tgn:1000001",
        "tgn:7012149",
        "tgn:7007158",
        "tgn:2000245",
        "tgn:7029392"
    ],
    "tgn:id":2217544,
    "tgn:name":"Campbell Ditch",
    "tgn:placetype":[
        "aat:300006075"
    ]
},
  "bbox": [],
  "geometry": {"coordinates":[-106.95,40.65],"type":"Point"}
}