{
  "id": 1051144,
  "type": "Feature",
  "properties": {
    "tgn:hierarchy":[
        "tgn:1051144",
        "tgn:7002444",
        "tgn:1000003",
        "tgn:7019091",
        "tgn:7008591",
        "tgn:7029392"
    ],
    "tgn:id":1051144,
    "tgn:name:en":"West Kilbride",
    "tgn:placetype":[
        "aat:300008347"
    ]
},
  "bbox": [],
  "geometry": {"coordinates":[-4.85,55.683333],"type":"Point"}
}