{
  "id": 7282175,
  "type": "Feature",
  "properties": {
    "tgn:hierarchy":[
        "tgn:7282175",
        "tgn:1001702",
        "tgn:1000049",
        "tgn:1000002",
        "tgn:7029392"
    ],
    "tgn:id":7282175,
    "tgn:name":"Sarita, Islote",
    "tgn:placetype":[
        "aat:300008791"
    ]
},
  "bbox": [],
  "geometry": {"coordinates":[-73.616667,-52.35],"type":"Point"}
}