<<<<<<< HEAD
{
  "id": 7481071,
  "type": "Feature",
  "properties": {
    "tgn:hierarchy":[
        "tgn:7481071",
        "tgn:7468018",
        "tgn:1000004",
        "tgn:1000141",
        "tgn:7029392"
    ],
    "tgn:id":7481071,
    "tgn:name":"Wangliao Gang",
    "tgn:placetype":[
        "aat:300008678"
    ]
},
  "bbox": [],
  "geometry": {"coordinates":[120.146909,23.437794],"type":"Point"}
}
=======
{"geometry":{"type":"Point","coordinates":[120.146909,23.437794]},"type":"Feature","properties":{"hierarchy":["tgn:7481071","tgn:7468018","tgn:1000004","tgn:1000141","tgn:7029392"],"placetype":["aat:300008678"],"id":7481071,"name:xx":"Wangliao Gang"}}
>>>>>>> 03f74aca74312dbeaf24d7e61306dd6a786dc3d0
