{
  "id": 7481071,
  "type": "Feature",
  "properties": {
    "tgn:hierarchy":[
        "tgn:7481071",
        "tgn:7468018",
        "tgn:1000004",
        "tgn:1000141",
        "tgn:7029392"
    ],
    "tgn:id":7481071,
    "tgn:name":"Wangliao Gang",
    "tgn:placetype":[
        "aat:300008678"
    ]
},
  "bbox": [],
  "geometry": {"coordinates":[120.146909,23.437794],"type":"Point"}
}