{
  "id": 1043994,
  "type": "Feature",
  "properties": {
    "tgn:hierarchy":[
        "tgn:1043994",
        "tgn:7005880",
        "tgn:1000003",
        "tgn:7003237",
        "tgn:1000080",
        "tgn:7029392"
    ],
    "tgn:id":1043994,
    "tgn:name":"Castel d'Ario",
    "tgn:placetype":[
        "aat:300008347"
    ]
},
  "bbox": [],
  "geometry": {"coordinates":[10.966667,45.183333],"type":"Point"}
}