{
  "id": 1090306,
  "type": "Feature",
  "properties": {
    "tgn:hierarchy":[
        "tgn:1090306",
        "tgn:7001242",
        "tgn:7018265",
        "tgn:1000168",
        "tgn:7029392"
    ],
    "tgn:id":1090306,
    "tgn:name":"Agnibil\u00e9krou",
    "tgn:placetype":[
        "aat:300008347"
    ]
},
  "bbox": [],
  "geometry": {"coordinates":[-3.1833,7.1667],"type":"Point"}
}