{
  "id": 7047594,
  "type": "Feature",
  "properties": {
    "tgn:hierarchy":[
        "tgn:7047594",
        "tgn:7003162",
        "tgn:1000003",
        "tgn:7009760",
        "tgn:1000080",
        "tgn:7029392"
    ],
    "tgn:id":7047594,
    "tgn:name":"Civitella, Monte",
    "tgn:placetype":[
        "aat:300008795"
    ]
},
  "bbox": [],
  "geometry": {"coordinates":[12.083333,43.433333],"type":"Point"}
}