{
  "id": 7018826,
  "type": "Feature",
  "properties": {
    "tgn:hierarchy":[
        "tgn:7018826",
        "tgn:7000677",
        "tgn:1000004",
        "tgn:7003877",
        "tgn:1000137",
        "tgn:7029392"
    ],
    "tgn:id":7018826,
    "tgn:name":"Al-Bid\u02bb",
    "tgn:placetype":[
        "aat:300008347"
    ]
},
  "bbox": [],
  "geometry": {"coordinates":[35.0167,28.4667],"type":"Point"}
}