{
  "id": 7277142,
  "type": "Feature",
  "properties": {
    "tgn:hierarchy":[
        "tgn:7277142",
        "tgn:1001630",
        "tgn:1000049",
        "tgn:1000002",
        "tgn:7029392"
    ],
    "tgn:id":7277142,
    "tgn:name":"Yegua, Quebrada",
    "tgn:placetype":[
        "aat:300008699"
    ]
},
  "bbox": [],
  "geometry": {"coordinates":[-69.466667,-27.683333],"type":"Point"}
}