{
  "id": 7066637,
  "type": "Feature",
  "properties": {
    "tgn:hierarchy":[
        "tgn:7066637",
        "tgn:7003669",
        "tgn:1000003",
        "tgn:7000084",
        "tgn:7029392"
    ],
    "tgn:id":7066637,
    "tgn:name":"Stockham",
    "tgn:placetype":[
        "aat:300000206"
    ]
},
  "bbox": [],
  "geometry": {"coordinates":[12.85,47.816667],"type":"Point"}
}