{
  "id": 7433059,
  "type": "Feature",
  "properties": {
    "tgn:hierarchy":[
        "tgn:7433059",
        "tgn:7005583",
        "tgn:1000001",
        "tgn:7005560",
        "tgn:7029392"
    ],
    "tgn:id":7433059,
    "tgn:name":"Toboso, Cerro",
    "tgn:placetype":[
        "aat:300008795"
    ]
},
  "bbox": [],
  "geometry": {"coordinates":[-102.633333,24.75],"type":"Point"}
}