{
  "id": 2751895,
  "type": "Feature",
  "properties": {
    "tgn:hierarchy":[
        "tgn:2751895",
        "tgn:1000001",
        "tgn:7012149",
        "tgn:2000560",
        "tgn:7007252",
        "tgn:7029392"
    ],
    "tgn:id":2751895,
    "tgn:name":"Warrens Lake",
    "tgn:placetype":[
        "aat:300008680"
    ]
},
  "bbox": [],
  "geometry": {"coordinates":[-87.4333,38.1333],"type":"Point"}
}