{
  "id": 7498356,
  "type": "Feature",
  "properties": {
    "tgn:hierarchy":[
        "tgn:7498356",
        "tgn:7001004",
        "tgn:1000004",
        "tgn:1000141",
        "tgn:7029392"
    ],
    "tgn:id":7498356,
    "tgn:name":"Tianchi",
    "tgn:placetype":[
        "aat:300008347"
    ]
},
  "bbox": [],
  "geometry": {"coordinates":[120.915235,23.279656],"type":"Point"}
}