{
  "id": 7008053,
  "type": "Feature",
  "properties": {
    "tgn:hierarchy":[
        "tgn:7008053",
        "tgn:7002443",
        "tgn:1000003",
        "tgn:7008591",
        "tgn:7029392"
    ],
    "tgn:id":7008053,
    "tgn:name:en":"West Glamorgan",
    "tgn:placetype":[
        "aat:300387179",
        "aat:300387064",
        "aat:300387305",
        "aat:300000771",
        "aat:300387302"
    ]
},
  "bbox": [],
  "geometry": {"coordinates":[-3.5833,51.5833],"type":"Point"}
}