{
  "id": 2669792,
  "type": "Feature",
  "properties": {
    "tgn:hierarchy":[
        "tgn:2669792",
        "tgn:1000001",
        "tgn:7006451",
        "tgn:2000093",
        "tgn:7012149",
        "tgn:7029392"
    ],
    "tgn:id":2669792,
    "tgn:name":"Slinkard Spring",
    "tgn:placetype":[
        "aat:300008697"
    ]
},
  "bbox": [],
  "geometry": {"coordinates":[-110.7333,33.5167],"type":"Point"}
}