{
  "id": 2267154,
  "type": "Feature",
  "properties": {
    "tgn:hierarchy":[
        "tgn:2267154",
        "tgn:7002659",
        "tgn:1000001",
        "tgn:7012149",
        "tgn:2000055",
        "tgn:7029392"
    ],
    "tgn:id":2267154,
    "tgn:name":"Crews Mine",
    "tgn:placetype":[
        "aat:300000390"
    ]
},
  "bbox": [],
  "geometry": {"coordinates":[-85.55,33.45],"type":"Point"}
}