<<<<<<< HEAD
{
  "id": 7170520,
  "type": "Feature",
  "properties": {
    "tgn:hierarchy":[
        "tgn:7170520",
        "tgn:7003669",
        "tgn:1000003",
        "tgn:7000084",
        "tgn:7029392"
    ],
    "tgn:id":7170520,
    "tgn:name":"Henthalhof",
    "tgn:placetype":[
        "aat:300008347"
    ]
},
  "bbox": [],
  "geometry": {"coordinates":[10.783333,48.9],"type":"Point"}
}
=======
{"geometry":{"type":"Point","coordinates":[10.783333,48.900000]},"type":"Feature","properties":{"hierarchy":["tgn:7170520","tgn:7003669","tgn:1000003","tgn:7000084","tgn:7029392"],"placetype":["aat:300008347"],"id":7170520,"name:xx":"Henthalhof"}}
>>>>>>> 03f74aca74312dbeaf24d7e61306dd6a786dc3d0
