{
  "id": 7377994,
  "type": "Feature",
  "properties": {
    "tgn:hierarchy":[
        "tgn:7377994",
        "tgn:7005583",
        "tgn:1000001",
        "tgn:7005560",
        "tgn:7029392"
    ],
    "tgn:id":7377994,
    "tgn:name":"Rancho La Posta de Jiguites",
    "tgn:placetype":[
        "aat:300000241"
    ]
},
  "bbox": [],
  "geometry": {"coordinates":[-105.583333,25.733333],"type":"Point"}
}