{
  "id": 2729088,
  "type": "Feature",
  "properties": {
    "tgn:hierarchy":[
        "tgn:2729088",
        "tgn:1000001",
        "tgn:7012149",
        "tgn:2000488",
        "tgn:7007250",
        "tgn:7029392"
    ],
    "tgn:id":2729088,
    "tgn:name":"Triguero Lake",
    "tgn:placetype":[
        "aat:300008680"
    ]
},
  "bbox": [],
  "geometry": {"coordinates":[-115.6667,42.15],"type":"Point"}
}