{
  "id": 1019464,
  "type": "Feature",
  "properties": {
    "tgn:hierarchy":[
        "tgn:1019464",
        "tgn:7006477",
        "tgn:1001253",
        "tgn:1000002",
        "tgn:7029392"
    ],
    "tgn:id":1019464,
    "tgn:name":"Formosa",
    "tgn:placetype":[
        "aat:300008347",
        "aat:300008389",
        "aat:300387223",
        "aat:300120599"
    ]
},
  "bbox": [],
  "geometry": {"coordinates":[-58.2333,-26.1167],"type":"Point"}
}