{
  "id": 7296450,
  "type": "Feature",
  "properties": {
    "tgn:hierarchy":[
        "tgn:7296450",
        "tgn:7010420",
        "tgn:1000003",
        "tgn:7002795",
        "tgn:1000095",
        "tgn:7029392"
    ],
    "tgn:id":7296450,
    "tgn:name":"Villamanrique de Tajo",
    "tgn:placetype":[
        "aat:300008347"
    ]
},
  "bbox": [],
  "geometry": {"coordinates":[-3.233333,40.066667],"type":"Point"}
}