{
  "id": 2211841,
  "type": "Feature",
  "properties": {
    "tgn:hierarchy":[
        "tgn:2211841",
        "tgn:7002659",
        "tgn:1000001",
        "tgn:2000011",
        "tgn:7012149",
        "tgn:7029392"
    ],
    "tgn:id":2211841,
    "tgn:name":"Buttonwood Branch",
    "tgn:placetype":[
        "aat:300008699"
    ]
},
  "bbox": [],
  "geometry": {"coordinates":[-88.1167,31.9833],"type":"Point"}
}