{
  "id": 2340720,
  "type": "Feature",
  "properties": {
    "tgn:hierarchy":[
        "tgn:2340720",
        "tgn:1000001",
        "tgn:7012149",
        "tgn:1002755",
        "tgn:7007523",
        "tgn:7029392"
    ],
    "tgn:id":2340720,
    "tgn:name":"Fresh Water Hollow",
    "tgn:placetype":[
        "aat:300008761"
    ]
},
  "bbox": [],
  "geometry": {"coordinates":[-91.8333,38.35],"type":"Point"}
}