{
  "id": 2418746,
  "type": "Feature",
  "properties": {
    "tgn:hierarchy":[
        "tgn:2418746",
        "tgn:1000001",
        "tgn:7012149",
        "tgn:2001722",
        "tgn:7007708",
        "tgn:7029392"
    ],
    "tgn:id":2418746,
    "tgn:name":"Jakey Ridge",
    "tgn:placetype":[
        "aat:300266640"
    ]
},
  "bbox": [],
  "geometry": {"coordinates":[-116.65,45.5667],"type":"Point"}
}