{
  "id": 2178541,
  "type": "Feature",
  "properties": {
    "tgn:hierarchy":[
        "tgn:2178541",
        "tgn:1000001",
        "tgn:7012149",
        "tgn:2000843",
        "tgn:7007255",
        "tgn:7029392"
    ],
    "tgn:id":2178541,
    "tgn:name":"Blacks Hill",
    "tgn:placetype":[
        "aat:300008798"
    ]
},
  "bbox": [],
  "geometry": {"coordinates":[-85.3333,38.0167],"type":"Point"}
}