{
  "id": 2726049,
  "type": "Feature",
  "properties": {
    "tgn:hierarchy":[
        "tgn:2726049",
        "tgn:1000001",
        "tgn:7012149",
        "tgn:2000479",
        "tgn:7007250",
        "tgn:7029392"
    ],
    "tgn:id":2726049,
    "tgn:name":"Tottens Pond",
    "tgn:placetype":[
        "aat:300008905"
    ]
},
  "bbox": [],
  "geometry": {"coordinates":[-116.75,47.7333],"type":"Point"}
}