{
  "id": 7217315,
  "type": "Feature",
  "properties": {
    "tgn:hierarchy":[
        "tgn:7217315",
        "tgn:7011164",
        "tgn:7002674",
        "tgn:1000003",
        "tgn:1000074",
        "tgn:7029392"
    ],
    "tgn:id":7217315,
    "tgn:name":"V\u00edgla",
    "tgn:placetype":[
        "aat:300008798"
    ]
},
  "bbox": [],
  "geometry": {"coordinates":[26.621111,37.725],"type":"Point"}
}