{
  "id": 7047421,
  "type": "Feature",
  "properties": {
    "tgn:hierarchy":[
        "tgn:7047421",
        "tgn:1003505",
        "tgn:1000003",
        "tgn:7002993",
        "tgn:1000080",
        "tgn:7029392"
    ],
    "tgn:id":7047421,
    "tgn:name":"Gretta",
    "tgn:placetype":[
        "aat:300000745"
    ]
},
  "bbox": [],
  "geometry": {"coordinates":[13.75,45.666667],"type":"Point"}
}