{
  "id": 7230368,
  "type": "Feature",
  "properties": {
    "tgn:hierarchy":[
        "tgn:7230368",
        "tgn:7011170",
        "tgn:7002715",
        "tgn:1000003",
        "tgn:1000074",
        "tgn:7029392"
    ],
    "tgn:id":7230368,
    "tgn:name":"Mavrol\u00edthion",
    "tgn:placetype":[
        "aat:300008057"
    ]
},
  "bbox": [],
  "geometry": {"coordinates":[24.216667,41.25],"type":"Point"}
}