{
  "id": 1140116,
  "type": "Feature",
  "properties": {
    "tgn:hierarchy":[
        "tgn:1140116",
        "tgn:1000004",
        "tgn:7000198",
        "tgn:1001977",
        "tgn:7029392"
    ],
    "tgn:id":1140116,
    "tgn:name:en":"Bara",
    "tgn:placetype":[
        "aat:300008347"
    ]
},
  "bbox": [],
  "geometry": {"coordinates":[88.267455,22.763322],"type":"Point"}
}