{
  "id": 1020080,
  "type": "Feature",
  "properties": {
    "tgn:hierarchy":[
        "tgn:1020080",
        "tgn:7006477",
        "tgn:1001376",
        "tgn:1000002",
        "tgn:7029392"
    ],
    "tgn:id":1020080,
    "tgn:name":"Tama",
    "tgn:placetype":[
        "aat:300008347"
    ]
},
  "bbox": [],
  "geometry": {"coordinates":[-66.5333,-30.5167],"type":"Point"}
}