{
  "id": 7286590,
  "type": "Feature",
  "properties": {
    "tgn:hierarchy":[
        "tgn:7286590",
        "tgn:1001702",
        "tgn:1000049",
        "tgn:1000002",
        "tgn:7029392"
    ],
    "tgn:id":7286590,
    "tgn:name":"Gusano, Pen\u00ednsula",
    "tgn:placetype":[
        "aat:300008804"
    ]
},
  "bbox": [],
  "geometry": {"coordinates":[-67.616667,-54.916667],"type":"Point"}
}