{
  "id": 2635157,
  "type": "Feature",
  "properties": {
    "tgn:hierarchy":[
        "tgn:2635157",
        "tgn:1000001",
        "tgn:7012149",
        "tgn:1002515",
        "tgn:7007252",
        "tgn:7029392"
    ],
    "tgn:id":2635157,
    "tgn:name":"Rykers Ridge",
    "tgn:placetype":[
        "aat:300266640"
    ]
},
  "bbox": [],
  "geometry": {"coordinates":[-85.3167,38.7667],"type":"Point"}
}