<<<<<<< HEAD
{
  "id": 7179462,
  "type": "Feature",
  "properties": {
    "tgn:hierarchy":[
        "tgn:7179462",
        "tgn:7003669",
        "tgn:1000003",
        "tgn:7000084",
        "tgn:7029392"
    ],
    "tgn:id":7179462,
    "tgn:name":"Habach",
    "tgn:placetype":[
        "aat:300008347"
    ]
},
  "bbox": [],
  "geometry": {"coordinates":[12.7,48.366667],"type":"Point"}
}
=======
{"geometry":{"type":"Point","coordinates":[12.700000,48.366667]},"type":"Feature","properties":{"hierarchy":["tgn:7179462","tgn:7003669","tgn:1000003","tgn:7000084","tgn:7029392"],"placetype":["aat:300008347"],"id":7179462,"name:xx":"Habach"}}
>>>>>>> 03f74aca74312dbeaf24d7e61306dd6a786dc3d0
