{
  "id": 7458547,
  "type": "Feature",
  "properties": {
    "tgn:hierarchy":[
        "tgn:7458547",
        "tgn:7002443",
        "tgn:7017242",
        "tgn:1000003",
        "tgn:7008591",
        "tgn:7029392"
    ],
    "tgn:id":7458547,
    "tgn:name:en":"New Quay Bay",
    "tgn:placetype":[
        "aat:300132316"
    ]
},
  "bbox": [],
  "geometry": {"coordinates":[-4.35,52.216667],"type":"Point"}
}