{
  "id": 2181099,
  "type": "Feature",
  "properties": {
    "tgn:hierarchy":[
        "tgn:2181099",
        "tgn:7002659",
        "tgn:1000001",
        "tgn:7012149",
        "tgn:2000029",
        "tgn:7029392"
    ],
    "tgn:id":2181099,
    "tgn:name":"Blue Branch",
    "tgn:placetype":[
        "aat:300008699"
    ]
},
  "bbox": [],
  "geometry": {"coordinates":[-88.0167,34.5167],"type":"Point"}
}