{
  "id": 2120772,
  "type": "Feature",
  "properties": {
    "tgn:hierarchy":[
        "tgn:2120772",
        "tgn:1000001",
        "tgn:7012149",
        "tgn:2002352",
        "tgn:7007922",
        "tgn:7029392"
    ],
    "tgn:id":2120772,
    "tgn:name":"Bluffview",
    "tgn:placetype":[
        "aat:300008347"
    ]
},
  "bbox": [],
  "geometry": {"coordinates":[-89.7667,43.3667],"type":"Point"}
}