{
  "id": 7415082,
  "type": "Feature",
  "properties": {
    "tgn:hierarchy":[
        "tgn:7415082",
        "tgn:1000001",
        "tgn:7005591",
        "tgn:7005560",
        "tgn:7029392"
    ],
    "tgn:id":7415082,
    "tgn:name:es":"R\u00edo Florido",
    "tgn:placetype":[
        "aat:300008347"
    ]
},
  "bbox": [],
  "geometry": {"coordinates":[-97.063889,17.3675],"type":"Point"}
}