{
  "id": 7240224,
  "type": "Feature",
  "properties": {
    "tgn:hierarchy":[
        "tgn:7240224",
        "tgn:7003461",
        "tgn:1000003",
        "tgn:1000063",
        "tgn:7018236",
        "tgn:7029392"
    ],
    "tgn:id":7240224,
    "tgn:name":"Eikelbos",
    "tgn:placetype":[
        "aat:300008347"
    ]
},
  "bbox": [],
  "geometry": {"coordinates":[5.416667,51.166667],"type":"Point"}
}