<<<<<<< HEAD
{
  "id": 7240224,
  "type": "Feature",
  "properties": {
    "tgn:hierarchy":[
        "tgn:7240224",
        "tgn:7003461",
        "tgn:1000003",
        "tgn:1000063",
        "tgn:7018236",
        "tgn:7029392"
    ],
    "tgn:id":7240224,
    "tgn:name":"Eikelbos",
    "tgn:placetype":[
        "aat:300008347"
    ]
},
  "bbox": [],
  "geometry": {"coordinates":[5.416667,51.166667],"type":"Point"}
}
=======
{"geometry":{"type":"Point","coordinates":[5.416667,51.166667]},"type":"Feature","properties":{"hierarchy":["tgn:7240224","tgn:7003461","tgn:1000003","tgn:1000063","tgn:7018236","tgn:7029392"],"placetype":["aat:300008347"],"id":7240224,"name:xx":"Eikelbos"}}
>>>>>>> 03f74aca74312dbeaf24d7e61306dd6a786dc3d0
