{
  "id": 7108446,
  "type": "Feature",
  "properties": {
    "tgn:hierarchy":[
        "tgn:7108446",
        "tgn:1000003",
        "tgn:7003682",
        "tgn:7000084",
        "tgn:7029392"
    ],
    "tgn:id":7108446,
    "tgn:name":"Rehborn",
    "tgn:placetype":[
        "aat:300008347"
    ]
},
  "bbox": [],
  "geometry": {"coordinates":[7.683333,49.733333],"type":"Point"}
}