<<<<<<< HEAD
{
  "id": 2159881,
  "type": "Feature",
  "properties": {
    "tgn:hierarchy":[
        "tgn:2159881",
        "tgn:1000001",
        "tgn:7012149",
        "tgn:7029392"
    ],
    "tgn:id":2159881,
    "tgn:name":"Beech Fork",
    "tgn:placetype":[
        "aat:300008699"
    ]
},
  "bbox": [],
  "geometry": {"coordinates":[-81.6833,37.1667],"type":"Point"}
}
=======
{"geometry":{"type":"Point","coordinates":[-81.683300,37.166700]},"type":"Feature","properties":{"hierarchy":["tgn:2159881","tgn:1000001","tgn:7012149","tgn:7029392"],"placetype":["aat:300008699"],"id":2159881,"name:xx":"Beech Fork"}}
>>>>>>> 03f74aca74312dbeaf24d7e61306dd6a786dc3d0
