<<<<<<< HEAD
{
  "id": 7026614,
  "type": "Feature",
  "properties": {
    "tgn:hierarchy":[
        "tgn:7026614",
        "tgn:7002445",
        "tgn:1000003",
        "tgn:7019020",
        "tgn:7008591",
        "tgn:7029392"
    ],
    "tgn:id":7026614,
    "tgn:name:en":"Doynton",
    "tgn:placetype":[
        "aat:300008347",
        "aat:300008372"
    ]
},
  "bbox": [],
  "geometry": {"coordinates":[-2.404444,51.463333],"type":"Point"}
}
=======
{"geometry":{"type":"Point","coordinates":[-2.404444,51.463333]},"type":"Feature","properties":{"hierarchy":["tgn:7026614","tgn:7002445","tgn:1000003","tgn:7019020","tgn:7008591","tgn:7029392"],"placetype":["aat:300008347","aat:300008372"],"name:en":"Doynton","id":7026614}}
>>>>>>> 03f74aca74312dbeaf24d7e61306dd6a786dc3d0
