{
  "id": 2451289,
  "type": "Feature",
  "properties": {
    "tgn:hierarchy":[
        "tgn:2451289",
        "tgn:1000001",
        "tgn:7012149",
        "tgn:2002125",
        "tgn:7007827",
        "tgn:7029392"
    ],
    "tgn:id":2451289,
    "tgn:name":"Little Baldy",
    "tgn:placetype":[
        "aat:300008798"
    ]
},
  "bbox": [],
  "geometry": {"coordinates":[-111.65,40.35],"type":"Point"}
}