<<<<<<< HEAD
{
  "id": 7175442,
  "type": "Feature",
  "properties": {
    "tgn:hierarchy":[
        "tgn:7175442",
        "tgn:1000003",
        "tgn:7000094",
        "tgn:7000084",
        "tgn:7029392"
    ],
    "tgn:id":7175442,
    "tgn:name":"Gro\u00dfe Stubbenkammer",
    "tgn:placetype":[
        "aat:300008749"
    ]
},
  "bbox": [],
  "geometry": {"coordinates":[13.666667,54.583333],"type":"Point"}
}
=======
{"geometry":{"type":"Point","coordinates":[13.666667,54.583333]},"type":"Feature","properties":{"hierarchy":["tgn:7175442","tgn:1000003","tgn:7000094","tgn:7000084","tgn:7029392"],"placetype":["aat:300008749"],"id":7175442,"name:xx":"Gro\u00dfe Stubbenkammer"}}
>>>>>>> 03f74aca74312dbeaf24d7e61306dd6a786dc3d0
