{
  "id": 7221480,
  "type": "Feature",
  "properties": {
    "tgn:hierarchy":[
        "tgn:7221480",
        "tgn:7011164",
        "tgn:7002674",
        "tgn:1000003",
        "tgn:1000074",
        "tgn:7029392"
    ],
    "tgn:id":7221480,
    "tgn:name":"\u00c1gioi P\u00e1ntes",
    "tgn:placetype":[
        "aat:300007466"
    ]
},
  "bbox": [],
  "geometry": {"coordinates":[26.695833,37.735],"type":"Point"}
}