{
  "id": 7227235,
  "type": "Feature",
  "properties": {
    "tgn:hierarchy":[
        "tgn:7227235",
        "tgn:7002751",
        "tgn:7001399",
        "tgn:1000003",
        "tgn:1000074",
        "tgn:7029392"
    ],
    "tgn:id":7227235,
    "tgn:name":"Ski\u00e1thou, Sten\u00f3",
    "tgn:placetype":[
        "aat:300387026"
    ]
},
  "bbox": [],
  "geometry": {"coordinates":[23.366667,39.166667],"type":"Point"}
}