{
  "id": 7314106,
  "type": "Feature",
  "properties": {
    "tgn:hierarchy":[
        "tgn:7314106",
        "tgn:1001695",
        "tgn:1000049",
        "tgn:1000002",
        "tgn:7029392"
    ],
    "tgn:id":7314106,
    "tgn:name":"La Tuna",
    "tgn:placetype":[
        "aat:300008347"
    ]
},
  "bbox": [],
  "geometry": {"coordinates":[-71.083333,-34.633333],"type":"Point"}
}