{
  "id": 2368583,
  "type": "Feature",
  "properties": {
    "tgn:hierarchy":[
        "tgn:2368583",
        "tgn:1000001",
        "tgn:7012149",
        "tgn:7007248",
        "tgn:7029392"
    ],
    "tgn:id":2368583,
    "tgn:name":"Gulf Creek",
    "tgn:placetype":[
        "aat:300008706"
    ]
},
  "bbox": [],
  "geometry": {"coordinates":[-85.4333,34.7833],"type":"Point"}
}