{
  "id": 7082759,
  "type": "Feature",
  "properties": {
    "tgn:hierarchy":[
        "tgn:7082759",
        "tgn:1000003",
        "tgn:7003676",
        "tgn:7000084",
        "tgn:7029392"
    ],
    "tgn:id":7082759,
    "tgn:name":"Westerlutten",
    "tgn:placetype":[
        "aat:300008347"
    ]
},
  "bbox": [],
  "geometry": {"coordinates":[8.316667,52.766667],"type":"Point"}
}