<<<<<<< HEAD
{
  "id": 2337406,
  "type": "Feature",
  "properties": {
    "tgn:hierarchy":[
        "tgn:2337406",
        "tgn:1000001",
        "tgn:7012149",
        "tgn:2001883",
        "tgn:7007825",
        "tgn:7029392"
    ],
    "tgn:id":2337406,
    "tgn:name":"Fowler Branch",
    "tgn:placetype":[
        "aat:300008699"
    ]
},
  "bbox": [],
  "geometry": {"coordinates":[-84.0667,36.0667],"type":"Point"}
}
=======
{"geometry":{"type":"Point","coordinates":[-84.066700,36.066700]},"type":"Feature","properties":{"hierarchy":["tgn:2337406","tgn:1000001","tgn:7012149","tgn:2001883","tgn:7007825","tgn:7029392"],"placetype":["aat:300008699"],"id":2337406,"name:xx":"Fowler Branch"}}
>>>>>>> 03f74aca74312dbeaf24d7e61306dd6a786dc3d0
