{
  "id": 7561356,
  "type": "Feature",
  "properties": {
    "tgn:hierarchy":[
        "tgn:7561356",
        "tgn:1000004",
        "tgn:7000198",
        "tgn:7016722",
        "tgn:7029392"
    ],
    "tgn:id":7561356,
    "tgn:name:en":"Kush\u0101lpur",
    "tgn:placetype":[
        "aat:300008347"
    ]
},
  "bbox": [],
  "geometry": {"coordinates":[79.402699,27.124992],"type":"Point"}
}