{
  "id": 2679980,
  "type": "Feature",
  "properties": {
    "tgn:hierarchy":[
        "tgn:2679980",
        "tgn:1000001",
        "tgn:2001429",
        "tgn:7012149",
        "tgn:7007566",
        "tgn:7029392"
    ],
    "tgn:id":2679980,
    "tgn:name":"South Fork Silver Creek",
    "tgn:placetype":[
        "aat:300008706"
    ]
},
  "bbox": [],
  "geometry": {"coordinates":[-108.7667,33.3667],"type":"Point"}
}