<<<<<<< HEAD
{
  "id": 7371027,
  "type": "Feature",
  "properties": {
    "tgn:hierarchy":[
        "tgn:7371027",
        "tgn:1000001",
        "tgn:7005591",
        "tgn:7005560",
        "tgn:7029392"
    ],
    "tgn:id":7371027,
    "tgn:name":"Guviche",
    "tgn:placetype":[
        "aat:300008347"
    ]
},
  "bbox": [],
  "geometry": {"coordinates":[-95.233333,16.633333],"type":"Point"}
}
=======
{"geometry":{"type":"Point","coordinates":[-95.233333,16.633333]},"type":"Feature","properties":{"hierarchy":["tgn:7371027","tgn:1000001","tgn:7005591","tgn:7005560","tgn:7029392"],"placetype":["aat:300008347"],"id":7371027,"name:xx":"Guviche"}}
>>>>>>> 03f74aca74312dbeaf24d7e61306dd6a786dc3d0
