{
  "id": 2041302,
  "type": "Feature",
  "properties": {
    "tgn:hierarchy":[
        "tgn:2041302",
        "tgn:1000001",
        "tgn:7012149",
        "tgn:2000820",
        "tgn:7007255",
        "tgn:7029392"
    ],
    "tgn:id":2041302,
    "tgn:name":"Silver Creek",
    "tgn:placetype":[
        "aat:300008347",
        "aat:300387210"
    ]
},
  "bbox": [],
  "geometry": {"coordinates":[-84.35,37.65],"type":"Point"}
}