{
  "id": 1002643,
  "type": "Feature",
  "properties": {
    "tgn:hierarchy":[
        "tgn:1002643",
        "tgn:1000001",
        "tgn:7012149",
        "tgn:7007251",
        "tgn:7029392"
    ],
    "tgn:id":1002643,
    "tgn:name":"Mason",
    "tgn:placetype":[
        "aat:300387145",
        "aat:300000771"
    ]
},
  "bbox": [],
  "geometry": {"coordinates":[-89.8833,40.25],"type":"Point"}
}