{
  "id": 2407068,
  "type": "Feature",
  "properties": {
    "tgn:hierarchy":[
        "tgn:2407068",
        "tgn:1000001",
        "tgn:7012149",
        "tgn:1002678",
        "tgn:7007252",
        "tgn:7029392"
    ],
    "tgn:id":2407068,
    "tgn:name":"Hunter Switch",
    "tgn:placetype":[
        "aat:300008347"
    ]
},
  "bbox": [],
  "geometry": {"coordinates":[-86.5667,39.1667],"type":"Point"}
}