{
  "id": 7585062,
  "type": "Feature",
  "properties": {
    "tgn:hierarchy":[
        "tgn:7585062",
        "tgn:1000004",
        "tgn:7000198",
        "tgn:7016788",
        "tgn:7029392"
    ],
    "tgn:id":7585062,
    "tgn:name:en":"M\u012blan ki Dh\u0101ni",
    "tgn:placetype":[
        "aat:300008347"
    ]
},
  "bbox": [],
  "geometry": {"coordinates":[75.435179,28.064383],"type":"Point"}
}