{
  "id": 2462267,
  "type": "Feature",
  "properties": {
    "tgn:hierarchy":[
        "tgn:2462267",
        "tgn:1000001",
        "tgn:7012149",
        "tgn:2002341",
        "tgn:7007922",
        "tgn:7029392"
    ],
    "tgn:id":2462267,
    "tgn:name":"Little Wapato Lake",
    "tgn:placetype":[
        "aat:300008680"
    ]
},
  "bbox": [],
  "geometry": {"coordinates":[-88.65,45.2833],"type":"Point"}
}