<<<<<<< HEAD
{
  "id": 2766677,
  "type": "Feature",
  "properties": {
    "tgn:hierarchy":[
        "tgn:2766677",
        "tgn:1000001",
        "tgn:7012149",
        "tgn:2001534",
        "tgn:7007709",
        "tgn:7029392"
    ],
    "tgn:id":2766677,
    "tgn:name":"White Oak Lake",
    "tgn:placetype":[
        "aat:300006191"
    ]
},
  "bbox": [],
  "geometry": {"coordinates":[-78.8667,34.6667],"type":"Point"}
}
=======
{"geometry":{"type":"Point","coordinates":[-78.866700,34.666700]},"type":"Feature","properties":{"hierarchy":["tgn:2766677","tgn:1000001","tgn:7012149","tgn:2001534","tgn:7007709","tgn:7029392"],"placetype":["aat:300006191"],"id":2766677,"name:xx":"White Oak Lake"}}
>>>>>>> 03f74aca74312dbeaf24d7e61306dd6a786dc3d0
