{
  "id": 2766677,
  "type": "Feature",
  "properties": {
    "tgn:hierarchy":[
        "tgn:2766677",
        "tgn:1000001",
        "tgn:7012149",
        "tgn:2001534",
        "tgn:7007709",
        "tgn:7029392"
    ],
    "tgn:id":2766677,
    "tgn:name":"White Oak Lake",
    "tgn:placetype":[
        "aat:300006191"
    ]
},
  "bbox": [],
  "geometry": {"coordinates":[-78.8667,34.6667],"type":"Point"}
}