{
  "id": 2470544,
  "type": "Feature",
  "properties": {
    "tgn:hierarchy":[
        "tgn:2470544",
        "tgn:1000001",
        "tgn:7012149",
        "tgn:2001451",
        "tgn:7007566",
        "tgn:7029392"
    ],
    "tgn:id":2470544,
    "tgn:name":"Los Jaramillos, Ojo de",
    "tgn:placetype":[
        "aat:300008697"
    ]
},
  "bbox": [],
  "geometry": {"coordinates":[-107.15,35.5667],"type":"Point"}
}