{
  "id": 7198547,
  "type": "Feature",
  "properties": {
    "tgn:hierarchy":[
        "tgn:7198547",
        "tgn:7000096",
        "tgn:1000003",
        "tgn:7000084",
        "tgn:7029392"
    ],
    "tgn:id":7198547,
    "tgn:name":"Dr\u00f6gen",
    "tgn:placetype":[
        "aat:300008347"
    ]
},
  "bbox": [],
  "geometry": {"coordinates":[13.166667,53.133333],"type":"Point"}
}