{
  "id": 2545413,
  "type": "Feature",
  "properties": {
    "tgn:hierarchy":[
        "tgn:2545413",
        "tgn:7006450",
        "tgn:1000001",
        "tgn:7012149",
        "tgn:7029392"
    ],
    "tgn:id":2545413,
    "tgn:name":"North Fork Big River",
    "tgn:placetype":[
        "aat:300008707"
    ]
},
  "bbox": [],
  "geometry": {"coordinates":[-154.1667,62.0167],"type":"Point"}
}