{
  "id": 7219900,
  "type": "Feature",
  "properties": {
    "tgn:hierarchy":[
        "tgn:7219900",
        "tgn:7011330",
        "tgn:7002674",
        "tgn:1000003",
        "tgn:1000074",
        "tgn:7029392"
    ],
    "tgn:id":7219900,
    "tgn:name":"\u00c1gios Ge\u00f3rgios",
    "tgn:placetype":[
        "aat:300008347"
    ]
},
  "bbox": [],
  "geometry": {"coordinates":[27.165,36.849444],"type":"Point"}
}