{
  "id": 7558980,
  "type": "Feature",
  "properties": {
    "tgn:hierarchy":[
        "tgn:7558980",
        "tgn:1000004",
        "tgn:7000198",
        "tgn:7000799",
        "tgn:7029392"
    ],
    "tgn:id":7558980,
    "tgn:name:en":"Pattan",
    "tgn:placetype":[
        "aat:300008347"
    ]
},
  "bbox": [],
  "geometry": {"coordinates":[74.555535,34.161114],"type":"Point"}
}