{
  "id": 2644567,
  "type": "Feature",
  "properties": {
    "tgn:hierarchy":[
        "tgn:2644567",
        "tgn:1000001",
        "tgn:7012149",
        "tgn:2002129",
        "tgn:7007827",
        "tgn:7029392"
    ],
    "tgn:id":2644567,
    "tgn:name":"Sardine Canyon",
    "tgn:placetype":[
        "aat:300008761"
    ]
},
  "bbox": [],
  "geometry": {"coordinates":[-111.8667,41.2333],"type":"Point"}
}