<<<<<<< HEAD
{
  "id": 7115530,
  "type": "Feature",
  "properties": {
    "tgn:hierarchy":[
        "tgn:7115530",
        "tgn:1000003",
        "tgn:7003677",
        "tgn:7000084",
        "tgn:7029392"
    ],
    "tgn:id":7115530,
    "tgn:name":"\u00d6lbach",
    "tgn:placetype":[
        "aat:300008699"
    ]
},
  "bbox": [],
  "geometry": {"coordinates":[8.35,51.883333],"type":"Point"}
}
=======
{"geometry":{"type":"Point","coordinates":[8.350000,51.883333]},"type":"Feature","properties":{"hierarchy":["tgn:7115530","tgn:1000003","tgn:7003677","tgn:7000084","tgn:7029392"],"placetype":["aat:300008699"],"id":7115530,"name:xx":"\u00d6lbach"}}
>>>>>>> 03f74aca74312dbeaf24d7e61306dd6a786dc3d0
