{
  "id": 1040191,
  "type": "Feature",
  "properties": {
    "tgn:hierarchy":[
        "tgn:1040191",
        "tgn:7003669",
        "tgn:1000003",
        "tgn:7000084",
        "tgn:7029392"
    ],
    "tgn:id":1040191,
    "tgn:name":"M\u00f6ttingen",
    "tgn:placetype":[
        "aat:300008347"
    ]
},
  "bbox": [],
  "geometry": {"coordinates":[10.583333,48.816667],"type":"Point"}
}