{
  "id": 2434923,
  "type": "Feature",
  "properties": {
    "tgn:hierarchy":[
        "tgn:2434923",
        "tgn:1000001",
        "tgn:7012149",
        "tgn:7021516",
        "tgn:7007706",
        "tgn:7029392"
    ],
    "tgn:id":2434923,
    "tgn:name":"Kenston Lake",
    "tgn:placetype":[
        "aat:300006191"
    ]
},
  "bbox": [],
  "geometry": {"coordinates":[-81.3333,41.3667],"type":"Point"}
}