{
  "id": 2577656,
  "type": "Feature",
  "properties": {
    "tgn:hierarchy":[
        "tgn:2577656",
        "tgn:1000001",
        "tgn:2001703",
        "tgn:7012149",
        "tgn:7007708",
        "tgn:7029392"
    ],
    "tgn:id":2577656,
    "tgn:name":"Peterson Reservoir",
    "tgn:placetype":[
        "aat:300006191"
    ]
},
  "bbox": [],
  "geometry": {"coordinates":[-120.2833,44.0833],"type":"Point"}
}