{
  "id": 7374483,
  "type": "Feature",
  "properties": {
    "tgn:hierarchy":[
        "tgn:7374483",
        "tgn:1001853",
        "tgn:1000001",
        "tgn:7005560",
        "tgn:7029392"
    ],
    "tgn:id":7374483,
    "tgn:name":"La Bohemia",
    "tgn:placetype":[
        "aat:300008347"
    ]
},
  "bbox": [],
  "geometry": {"coordinates":[-103.266667,25.766667],"type":"Point"}
}