{
  "id": 2079870,
  "type": "Feature",
  "properties": {
    "tgn:hierarchy":[
        "tgn:2079870",
        "tgn:1000001",
        "tgn:1002279",
        "tgn:7012149",
        "tgn:7007706",
        "tgn:7029392"
    ],
    "tgn:id":2079870,
    "tgn:name":"Hamlet",
    "tgn:placetype":[
        "aat:300008347"
    ]
},
  "bbox": [],
  "geometry": {"coordinates":[-84.1833,39.0167],"type":"Point"}
}