{
  "id": 7558731,
  "type": "Feature",
  "properties": {
    "tgn:hierarchy":[
        "tgn:7558731",
        "tgn:1000004",
        "tgn:7000198",
        "tgn:1001894",
        "tgn:7029392"
    ],
    "tgn:id":7558731,
    "tgn:name:en":"Par\u0101si",
    "tgn:placetype":[
        "aat:300008347"
    ]
},
  "bbox": [],
  "geometry": {"coordinates":[82.015578,23.065786],"type":"Point"}
}