{
  "id": 7366436,
  "type": "Feature",
  "properties": {
    "tgn:hierarchy":[
        "tgn:7366436",
        "tgn:7005578",
        "tgn:1000001",
        "tgn:7005560",
        "tgn:7029392"
    ],
    "tgn:id":7366436,
    "tgn:name":"Esperanza",
    "tgn:placetype":[
        "aat:300008347"
    ]
},
  "bbox": [],
  "geometry": {"coordinates":[-90.333333,19.983333],"type":"Point"}
}