{
  "id": 7316970,
  "type": "Feature",
  "properties": {
    "tgn:hierarchy":[
        "tgn:7316970",
        "tgn:1001702",
        "tgn:1000049",
        "tgn:1000002",
        "tgn:7029392"
    ],
    "tgn:id":7316970,
    "tgn:name":"Conejos, Islote",
    "tgn:placetype":[
        "aat:300008791"
    ]
},
  "bbox": [],
  "geometry": {"coordinates":[-68.166667,-55.033333],"type":"Point"}
}