{
  "id": 7243513,
  "type": "Feature",
  "properties": {
    "tgn:hierarchy":[
        "tgn:7243513",
        "tgn:7003465",
        "tgn:1000003",
        "tgn:1000063",
        "tgn:4012014",
        "tgn:7029392"
    ],
    "tgn:id":7243513,
    "tgn:name":"Les Quatre Chemins",
    "tgn:placetype":[
        "aat:300008347"
    ]
},
  "bbox": [],
  "geometry": {"coordinates":[5.166667,49.766667],"type":"Point"}
}