<<<<<<< HEAD
{
  "id": 2768864,
  "type": "Feature",
  "properties": {
    "tgn:hierarchy":[
        "tgn:2768864",
        "tgn:1000001",
        "tgn:7012149",
        "tgn:2001053",
        "tgn:7007521",
        "tgn:7029392"
    ],
    "tgn:id":2768864,
    "tgn:name":"Whitney Creek",
    "tgn:placetype":[
        "aat:300008706"
    ]
},
  "bbox": [],
  "geometry": {"coordinates":[-92.4167,43.9],"type":"Point"}
}
=======
{"geometry":{"type":"Point","coordinates":[-92.416700,43.900000]},"type":"Feature","properties":{"hierarchy":["tgn:2768864","tgn:1000001","tgn:7012149","tgn:2001053","tgn:7007521","tgn:7029392"],"placetype":["aat:300008706"],"id":2768864,"name:xx":"Whitney Creek"}}
>>>>>>> 03f74aca74312dbeaf24d7e61306dd6a786dc3d0
