{
  "id": 2677014,
  "type": "Feature",
  "properties": {
    "tgn:hierarchy":[
        "tgn:2677014",
        "tgn:1000001",
        "tgn:7012149",
        "tgn:7007565",
        "tgn:7029392"
    ],
    "tgn:id":2677014,
    "tgn:name":"South Branch Mount Misery Brook",
    "tgn:placetype":[
        "aat:300008699"
    ]
},
  "bbox": [],
  "geometry": {"coordinates":[-74.3833,39.85],"type":"Point"}
}