{
  "id": 2640211,
  "type": "Feature",
  "properties": {
    "tgn:hierarchy":[
        "tgn:2640211",
        "tgn:1000001",
        "tgn:7012149",
        "tgn:2001456",
        "tgn:7007566",
        "tgn:7029392"
    ],
    "tgn:id":2640211,
    "tgn:name":"San Antonio Ditch",
    "tgn:placetype":[
        "aat:300006075"
    ]
},
  "bbox": [],
  "geometry": {"coordinates":[-106.85,33.9667],"type":"Point"}
}