<<<<<<< HEAD
{
  "id": 2762421,
  "type": "Feature",
  "properties": {
    "tgn:hierarchy":[
        "tgn:2762421",
        "tgn:1000001",
        "tgn:7006451",
        "tgn:7012149",
        "tgn:2000102",
        "tgn:7029392"
    ],
    "tgn:id":2762421,
    "tgn:name":"West Two Tank",
    "tgn:placetype":[
        "aat:300006191"
    ]
},
  "bbox": [],
  "geometry": {"coordinates":[-110.65,31.3667],"type":"Point"}
}
=======
{"geometry":{"type":"Point","coordinates":[-110.650000,31.366700]},"type":"Feature","properties":{"hierarchy":["tgn:2762421","tgn:1000001","tgn:7006451","tgn:7012149","tgn:2000102","tgn:7029392"],"placetype":["aat:300006191"],"id":2762421,"name:xx":"West Two Tank"}}
>>>>>>> 03f74aca74312dbeaf24d7e61306dd6a786dc3d0
