{
  "id": 2035698,
  "type": "Feature",
  "properties": {
    "tgn:hierarchy":[
        "tgn:2035698",
        "tgn:1000001",
        "tgn:2000600",
        "tgn:7012149",
        "tgn:7007253",
        "tgn:7029392"
    ],
    "tgn:id":2035698,
    "tgn:name":"Stanhope",
    "tgn:placetype":[
        "aat:300008347"
    ]
},
  "bbox": [],
  "geometry": {"coordinates":[-93.7833,42.2833],"type":"Point"}
}