<<<<<<< HEAD
{
  "id": 2409721,
  "type": "Feature",
  "properties": {
    "tgn:hierarchy":[
        "tgn:2409721",
        "tgn:7006450",
        "tgn:1000001",
        "tgn:2124012",
        "tgn:7012149",
        "tgn:7029392"
    ],
    "tgn:id":2409721,
    "tgn:name":"Ikpik Hill",
    "tgn:placetype":[
        "aat:300008798"
    ]
},
  "bbox": [],
  "geometry": {"coordinates":[-154.5,57.0333],"type":"Point"}
}
=======
{"geometry":{"type":"Point","coordinates":[-154.500000,57.033300]},"type":"Feature","properties":{"hierarchy":["tgn:2409721","tgn:7006450","tgn:1000001","tgn:2124012","tgn:7012149","tgn:7029392"],"placetype":["aat:300008798"],"id":2409721,"name:xx":"Ikpik Hill"}}
>>>>>>> 03f74aca74312dbeaf24d7e61306dd6a786dc3d0
