{
  "id": 2478282,
  "type": "Feature",
  "properties": {
    "tgn:hierarchy":[
        "tgn:2478282",
        "tgn:1000001",
        "tgn:7006451",
        "tgn:2000092",
        "tgn:7012149",
        "tgn:7029392"
    ],
    "tgn:id":2478282,
    "tgn:name":"Macks Crossing",
    "tgn:placetype":[
        "aat:300008347"
    ]
},
  "bbox": [],
  "geometry": {"coordinates":[-111.0833,34.6167],"type":"Point"}
}