{
  "id": 2517753,
  "type": "Feature",
  "properties": {
    "tgn:hierarchy":[
        "tgn:2517753",
        "tgn:1000001",
        "tgn:7012149",
        "tgn:1002314",
        "tgn:7007240",
        "tgn:7029392"
    ],
    "tgn:id":2517753,
    "tgn:name":"Mirror Lake",
    "tgn:placetype":[
        "aat:300008680"
    ]
},
  "bbox": [],
  "geometry": {"coordinates":[-80.1833,25.8667],"type":"Point"}
}