<<<<<<< HEAD
{
  "id": 7370057,
  "type": "Feature",
  "properties": {
    "tgn:hierarchy":[
        "tgn:7370057",
        "tgn:1000001",
        "tgn:7005594",
        "tgn:7005560",
        "tgn:7029392"
    ],
    "tgn:id":7370057,
    "tgn:name":"Guardarraya",
    "tgn:placetype":[
        "aat:300008347"
    ]
},
  "bbox": [],
  "geometry": {"coordinates":[-100.85,22.733333],"type":"Point"}
}
=======
{"geometry":{"type":"Point","coordinates":[-100.850000,22.733333]},"type":"Feature","properties":{"hierarchy":["tgn:7370057","tgn:1000001","tgn:7005594","tgn:7005560","tgn:7029392"],"placetype":["aat:300008347"],"id":7370057,"name:xx":"Guardarraya"}}
>>>>>>> 03f74aca74312dbeaf24d7e61306dd6a786dc3d0
