{
  "id": 2195061,
  "type": "Feature",
  "properties": {
    "tgn:hierarchy":[
        "tgn:2195061",
        "tgn:1000001",
        "tgn:7012149",
        "tgn:1002945",
        "tgn:7007710",
        "tgn:7029392"
    ],
    "tgn:id":2195061,
    "tgn:name":"Brill Hollow",
    "tgn:placetype":[
        "aat:300008761"
    ]
},
  "bbox": [],
  "geometry": {"coordinates":[-77.35,41.55],"type":"Point"}
}