<<<<<<< HEAD
{
  "id": 7059314,
  "type": "Feature",
  "properties": {
    "tgn:hierarchy":[
        "tgn:7059314",
        "tgn:7003692",
        "tgn:1000003",
        "tgn:7000084",
        "tgn:7029392"
    ],
    "tgn:id":7059314,
    "tgn:name":"Alter Boll",
    "tgn:placetype":[
        "aat:300008863"
    ]
},
  "bbox": [],
  "geometry": {"coordinates":[8.983333,47.766667],"type":"Point"}
}
=======
{"geometry":{"type":"Point","coordinates":[8.983333,47.766667]},"type":"Feature","properties":{"hierarchy":["tgn:7059314","tgn:7003692","tgn:1000003","tgn:7000084","tgn:7029392"],"placetype":["aat:300008863"],"id":7059314,"name:xx":"Alter Boll"}}
>>>>>>> 03f74aca74312dbeaf24d7e61306dd6a786dc3d0
