{
  "id": 7487692,
  "type": "Feature",
  "properties": {
    "tgn:hierarchy":[
        "tgn:7487692",
        "tgn:1000004",
        "tgn:7471332",
        "tgn:1000141",
        "tgn:7029392"
    ],
    "tgn:id":7487692,
    "tgn:name":"Liugu",
    "tgn:placetype":[
        "aat:300008347"
    ]
},
  "bbox": [],
  "geometry": {"coordinates":[121.103056,24.818056],"type":"Point"}
}