<<<<<<< HEAD
{
  "id": 7487692,
  "type": "Feature",
  "properties": {
    "tgn:hierarchy":[
        "tgn:7487692",
        "tgn:1000004",
        "tgn:7471332",
        "tgn:1000141",
        "tgn:7029392"
    ],
    "tgn:id":7487692,
    "tgn:name":"Liugu",
    "tgn:placetype":[
        "aat:300008347"
    ]
},
  "bbox": [],
  "geometry": {"coordinates":[121.103056,24.818056],"type":"Point"}
}
=======
{"geometry":{"type":"Point","coordinates":[121.103056,24.818056]},"type":"Feature","properties":{"hierarchy":["tgn:7487692","tgn:1000004","tgn:7471332","tgn:1000141","tgn:7029392"],"placetype":["aat:300008347"],"id":7487692,"name:xx":"Liugu"}}
>>>>>>> 03f74aca74312dbeaf24d7e61306dd6a786dc3d0
