{
  "id": 7570873,
  "type": "Feature",
  "properties": {
    "tgn:hierarchy":[
        "tgn:7570873",
        "tgn:1000004",
        "tgn:7000198",
        "tgn:1001882",
        "tgn:7029392"
    ],
    "tgn:id":7570873,
    "tgn:name:en":"Ghataparti",
    "tgn:placetype":[
        "aat:300008347"
    ]
},
  "bbox": [],
  "geometry": {"coordinates":[76.766667,14.483333],"type":"Point"}
}