{
  "id": 7441908,
  "type": "Feature",
  "properties": {
    "tgn:hierarchy":[
        "tgn:7441908",
        "tgn:7002444",
        "tgn:1000003",
        "tgn:7008082",
        "tgn:7008591",
        "tgn:7029392"
    ],
    "tgn:id":7441908,
    "tgn:name:en":"Toscaig, Loch",
    "tgn:placetype":[
        "aat:300132316"
    ]
},
  "bbox": [],
  "geometry": {"coordinates":[-5.866667,57.366667],"type":"Point"}
}