{
  "id": 1127572,
  "type": "Feature",
  "properties": {
    "tgn:hierarchy":[
        "tgn:1127572",
        "tgn:1000001",
        "tgn:7012149",
        "tgn:7007922",
        "tgn:7029392"
    ],
    "tgn:id":1127572,
    "tgn:name":"Namekagon",
    "tgn:placetype":[
        "aat:300008707"
    ]
},
  "bbox": [],
  "geometry": {"coordinates":[-91.1167,46.2167],"type":"Point"}
}