{
  "id": 7229277,
  "type": "Feature",
  "properties": {
    "tgn:hierarchy":[
        "tgn:7229277",
        "tgn:4003773",
        "tgn:7001395",
        "tgn:1000003",
        "tgn:1000074",
        "tgn:7029392"
    ],
    "tgn:id":7229277,
    "tgn:name":"Fri\u00e1s",
    "tgn:placetype":[
        "aat:300008798"
    ]
},
  "bbox": [],
  "geometry": {"coordinates":[21.566667,38.85],"type":"Point"}
}