{
  "id": 2008648,
  "type": "Feature",
  "properties": {
    "tgn:hierarchy":[
        "tgn:2008648",
        "tgn:1000001",
        "tgn:7016172",
        "tgn:7012149",
        "tgn:2000158",
        "tgn:7029392"
    ],
    "tgn:id":2008648,
    "tgn:name":"Kindall",
    "tgn:placetype":[
        "aat:300008347",
        "aat:300387210"
    ]
},
  "bbox": [],
  "geometry": {"coordinates":[-90.8167,34.55],"type":"Point"}
}