{
  "id": 2034380,
  "type": "Feature",
  "properties": {
    "tgn:hierarchy":[
        "tgn:2034380",
        "tgn:1000001",
        "tgn:7012149",
        "tgn:2000605",
        "tgn:7007253",
        "tgn:7029392"
    ],
    "tgn:id":2034380,
    "tgn:name":"Bonair",
    "tgn:placetype":[
        "aat:300008347",
        "aat:300387210"
    ]
},
  "bbox": [],
  "geometry": {"coordinates":[-92.1833,43.4167],"type":"Point"}
}