{
  "id": 7260737,
  "type": "Feature",
  "properties": {
    "tgn:hierarchy":[
        "tgn:7260737",
        "tgn:1000003",
        "tgn:7003626",
        "tgn:7016845",
        "tgn:7029392"
    ],
    "tgn:id":7260737,
    "tgn:name:nl":"Driebelterveld",
    "tgn:placetype":[
        "aat:300008187"
    ]
},
  "bbox": [],
  "geometry": {"coordinates":[6.533333,52.233333],"type":"Point"}
}