{
  "id": 7421605,
  "type": "Feature",
  "properties": {
    "tgn:hierarchy":[
        "tgn:7421605",
        "tgn:7005584",
        "tgn:1000001",
        "tgn:7005560",
        "tgn:7029392"
    ],
    "tgn:id":7421605,
    "tgn:name":"San Juan de Otates, Arroyo",
    "tgn:placetype":[
        "aat:300266554",
        "aat:300008699"
    ]
},
  "bbox": [],
  "geometry": {"coordinates":[-101.554444,21.109167],"type":"Point"}
}