{
  "id": 2568259,
  "type": "Feature",
  "properties": {
    "tgn:hierarchy":[
        "tgn:2568259",
        "tgn:1000001",
        "tgn:2000868",
        "tgn:7012149",
        "tgn:7007256",
        "tgn:7029392"
    ],
    "tgn:id":2568259,
    "tgn:name":"Parish Lake",
    "tgn:placetype":[
        "aat:300008680"
    ]
},
  "bbox": [],
  "geometry": {"coordinates":[-91.6833,31.5333],"type":"Point"}
}