{
  "id": 7308409,
  "type": "Feature",
  "properties": {
    "tgn:hierarchy":[
        "tgn:7308409",
        "tgn:1001692",
        "tgn:1000049",
        "tgn:1000002",
        "tgn:7029392"
    ],
    "tgn:id":7308409,
    "tgn:name":"Mar\u00eda Jes\u00fas, Laguna",
    "tgn:placetype":[
        "aat:300008680"
    ]
},
  "bbox": [],
  "geometry": {"coordinates":[-71.35,-38.266667],"type":"Point"}
}