<<<<<<< HEAD
{
  "id": 2408349,
  "type": "Feature",
  "properties": {
    "tgn:hierarchy":[
        "tgn:2408349",
        "tgn:1000001",
        "tgn:7012149",
        "tgn:1002926",
        "tgn:7007568",
        "tgn:7029392"
    ],
    "tgn:id":2408349,
    "tgn:name":"Hust Pond",
    "tgn:placetype":[
        "aat:300006191"
    ]
},
  "bbox": [],
  "geometry": {"coordinates":[-74.9333,41.7167],"type":"Point"}
}
=======
{"geometry":{"type":"Point","coordinates":[-74.933300,41.716700]},"type":"Feature","properties":{"hierarchy":["tgn:2408349","tgn:1000001","tgn:7012149","tgn:1002926","tgn:7007568","tgn:7029392"],"placetype":["aat:300006191"],"id":2408349,"name:xx":"Hust Pond"}}
>>>>>>> 03f74aca74312dbeaf24d7e61306dd6a786dc3d0
