{
  "id": 2043843,
  "type": "Feature",
  "properties": {
    "tgn:hierarchy":[
        "tgn:2043843",
        "tgn:2000855",
        "tgn:1000001",
        "tgn:7012149",
        "tgn:7007256",
        "tgn:7029392"
    ],
    "tgn:id":2043843,
    "tgn:name":"Reids",
    "tgn:placetype":[
        "aat:300008347",
        "aat:300387210"
    ]
},
  "bbox": [],
  "geometry": {"coordinates":[-92.8833,30.85],"type":"Point"}
}