{
  "id": 7070833,
  "type": "Feature",
  "properties": {
    "tgn:hierarchy":[
        "tgn:7070833",
        "tgn:1000003",
        "tgn:7003682",
        "tgn:7000084",
        "tgn:7029392"
    ],
    "tgn:id":7070833,
    "tgn:name":"Steinbergs Kopf",
    "tgn:placetype":[
        "aat:300008777"
    ]
},
  "bbox": [],
  "geometry": {"coordinates":[7.283333,50.483333],"type":"Point"}
}