{
  "id": 1015725,
  "type": "Feature",
  "properties": {
    "tgn:hierarchy":[
        "tgn:1015725",
        "tgn:7005685",
        "tgn:1000001",
        "tgn:7005804",
        "tgn:7029392"
    ],
    "tgn:id":1015725,
    "tgn:name":"Saint-Timoth\u00e9e",
    "tgn:placetype":[
        "aat:300008347"
    ]
},
  "bbox": [],
  "geometry": {"coordinates":[-74.05,45.2833],"type":"Point"}
}