{
  "id": 7283385,
  "type": "Feature",
  "properties": {
    "tgn:hierarchy":[
        "tgn:7283385",
        "tgn:1001657",
        "tgn:1000049",
        "tgn:1000002",
        "tgn:7029392"
    ],
    "tgn:id":7283385,
    "tgn:name":"Estaci\u00f3n Palestina",
    "tgn:placetype":[
        "aat:300007783"
    ]
},
  "bbox": [],
  "geometry": {"coordinates":[-69.733333,-23.866667],"type":"Point"}
}