{
  "id": 2307197,
  "type": "Feature",
  "properties": {
    "tgn:hierarchy":[
        "tgn:2307197",
        "tgn:1000001",
        "tgn:7012149",
        "tgn:2001718",
        "tgn:7007708",
        "tgn:7029392"
    ],
    "tgn:id":2307197,
    "tgn:name":"East Fork Oregon Canyon Creek",
    "tgn:placetype":[
        "aat:300008706"
    ]
},
  "bbox": [],
  "geometry": {"coordinates":[-117.9167,42.1167],"type":"Point"}
}