{
  "id": 2194383,
  "type": "Feature",
  "properties": {
    "tgn:hierarchy":[
        "tgn:2194383",
        "tgn:1000001",
        "tgn:7012149",
        "tgn:2001709",
        "tgn:7007708",
        "tgn:7029392"
    ],
    "tgn:id":2194383,
    "tgn:name":"Bridge Creek Canal",
    "tgn:placetype":[
        "aat:300006075"
    ]
},
  "bbox": [],
  "geometry": {"coordinates":[-118.8667,42.85],"type":"Point"}
}