{
  "id": 7124691,
  "type": "Feature",
  "properties": {
    "tgn:hierarchy":[
        "tgn:7124691",
        "tgn:7003669",
        "tgn:1000003",
        "tgn:7000084",
        "tgn:7029392"
    ],
    "tgn:id":7124691,
    "tgn:name":"Neub\u00e4uer Forst",
    "tgn:placetype":[
        "aat:300008863"
    ]
},
  "bbox": [],
  "geometry": {"coordinates":[12.416667,49.25],"type":"Point"}
}