{
  "id": 7013570,
  "type": "Feature",
  "properties": {
    "tgn:hierarchy":[
        "tgn:7013570",
        "tgn:1000004",
        "tgn:7029392"
    ],
    "tgn:id":7013570,
    "tgn:name":"Irtysh",
    "tgn:placetype":[
        "aat:300008707"
    ]
},
  "bbox": [],
  "geometry": {"coordinates":[-68.8333,61.0833],"type":"Point"}
}