{
  "id": 2722660,
  "type": "Feature",
  "properties": {
    "tgn:hierarchy":[
        "tgn:2722660",
        "tgn:1000001",
        "tgn:1002840",
        "tgn:7012149",
        "tgn:7007828",
        "tgn:7029392"
    ],
    "tgn:id":2722660,
    "tgn:name":"Tinmouth Mountain",
    "tgn:placetype":[
        "aat:300008798"
    ]
},
  "bbox": [],
  "geometry": {"coordinates":[-73.0667,43.4167],"type":"Point"}
}