{
  "id": 2647633,
  "type": "Feature",
  "properties": {
    "tgn:hierarchy":[
        "tgn:2647633",
        "tgn:1002146",
        "tgn:1000001",
        "tgn:7012149",
        "tgn:7007157",
        "tgn:7029392"
    ],
    "tgn:id":2647633,
    "tgn:name":"School Ditch",
    "tgn:placetype":[
        "aat:300006075"
    ]
},
  "bbox": [],
  "geometry": {"coordinates":[-120.8167,38.3833],"type":"Point"}
}