{
  "id": 7356064,
  "type": "Feature",
  "properties": {
    "tgn:hierarchy":[
        "tgn:7356064",
        "tgn:1001853",
        "tgn:1000001",
        "tgn:7005560",
        "tgn:7029392"
    ],
    "tgn:id":7356064,
    "tgn:name":"Chifl\u00f3n",
    "tgn:placetype":[
        "aat:300008347"
    ]
},
  "bbox": [],
  "geometry": {"coordinates":[-100.883333,27.633333],"type":"Point"}
}