{
  "id": 7220760,
  "type": "Feature",
  "properties": {
    "tgn:hierarchy":[
        "tgn:7220760",
        "tgn:7011170",
        "tgn:7002715",
        "tgn:1000003",
        "tgn:1000074",
        "tgn:7029392"
    ],
    "tgn:id":7220760,
    "tgn:name":"Elefther\u00f3n, Lim\u00e9nas",
    "tgn:placetype":[
        "aat:300008678"
    ]
},
  "bbox": [],
  "geometry": {"coordinates":[24.316111,40.849167],"type":"Point"}
}