{
  "id": 7329355,
  "type": "Feature",
  "properties": {
    "tgn:hierarchy":[
        "tgn:7329355",
        "tgn:7002804",
        "tgn:1000003",
        "tgn:7002793",
        "tgn:1000095",
        "tgn:7029392"
    ],
    "tgn:id":7329355,
    "tgn:name":"Pinet,Salinas del",
    "tgn:placetype":[
        "aat:300386883"
    ]
},
  "bbox": [],
  "geometry": {"coordinates":[-0.616667,38.166667],"type":"Point"}
}