{
  "id": 7241259,
  "type": "Feature",
  "properties": {
    "tgn:hierarchy":[
        "tgn:7241259",
        "tgn:7003457",
        "tgn:1000003",
        "tgn:1000063",
        "tgn:7018236",
        "tgn:7029392"
    ],
    "tgn:id":7241259,
    "tgn:name":"Lebeke",
    "tgn:placetype":[
        "aat:300008347"
    ]
},
  "bbox": [],
  "geometry": {"coordinates":[3.992539,50.862754],"type":"Point"}
}