{
  "id": 7283319,
  "type": "Feature",
  "properties": {
    "tgn:hierarchy":[
        "tgn:7283319",
        "tgn:1001699",
        "tgn:1000049",
        "tgn:1000002",
        "tgn:7029392"
    ],
    "tgn:id":7283319,
    "tgn:name":"Pangua, Estero",
    "tgn:placetype":[
        "aat:300008699"
    ]
},
  "bbox": [],
  "geometry": {"coordinates":[-73.766667,-40.716667],"type":"Point"}
}