{
  "id": 2441548,
  "type": "Feature",
  "properties": {
    "tgn:hierarchy":[
        "tgn:2441548",
        "tgn:1000001",
        "tgn:7012149",
        "tgn:2002350",
        "tgn:7007922",
        "tgn:7029392"
    ],
    "tgn:id":2441548,
    "tgn:name":"Koehler Lake",
    "tgn:placetype":[
        "aat:300008680"
    ]
},
  "bbox": [],
  "geometry": {"coordinates":[-91.5167,45.3333],"type":"Point"}
}