<<<<<<< HEAD
{
  "id": 2402052,
  "type": "Feature",
  "properties": {
    "tgn:hierarchy":[
        "tgn:2402052",
        "tgn:1000001",
        "tgn:2002366",
        "tgn:7012149",
        "tgn:7007923",
        "tgn:7029392"
    ],
    "tgn:id":2402052,
    "tgn:name":"Horseshoe Reservoir",
    "tgn:placetype":[
        "aat:300006191"
    ]
},
  "bbox": [],
  "geometry": {"coordinates":[-108.25,44.8667],"type":"Point"}
}
=======
{"geometry":{"type":"Point","coordinates":[-108.250000,44.866700]},"type":"Feature","properties":{"hierarchy":["tgn:2402052","tgn:1000001","tgn:2002366","tgn:7012149","tgn:7007923","tgn:7029392"],"placetype":["aat:300006191"],"id":2402052,"name:xx":"Horseshoe Reservoir"}}
>>>>>>> 03f74aca74312dbeaf24d7e61306dd6a786dc3d0
