<<<<<<< HEAD
{
  "id": 7373892,
  "type": "Feature",
  "properties": {
    "tgn:hierarchy":[
        "tgn:7373892",
        "tgn:1001853",
        "tgn:1000001",
        "tgn:7005560",
        "tgn:7029392"
    ],
    "tgn:id":7373892,
    "tgn:name":"La Bandera, Picacho",
    "tgn:placetype":[
        "aat:300008798"
    ]
},
  "bbox": [],
  "geometry": {"coordinates":[-101.2,25.333333],"type":"Point"}
}
=======
{"geometry":{"type":"Point","coordinates":[-101.200000,25.333333]},"type":"Feature","properties":{"hierarchy":["tgn:7373892","tgn:1001853","tgn:1000001","tgn:7005560","tgn:7029392"],"placetype":["aat:300008798"],"id":7373892,"name:xx":"La Bandera, Picacho"}}
>>>>>>> 03f74aca74312dbeaf24d7e61306dd6a786dc3d0
