{
  "id": 7097406,
  "type": "Feature",
  "properties": {
    "tgn:hierarchy":[
        "tgn:7097406",
        "tgn:1000003",
        "tgn:7003677",
        "tgn:7000084",
        "tgn:7029392"
    ],
    "tgn:id":7097406,
    "tgn:name":"Sp\u00fcrklen-Berg",
    "tgn:placetype":[
        "aat:300008777"
    ]
},
  "bbox": [],
  "geometry": {"coordinates":[6.983333,51.116667],"type":"Point"}
}