{
  "id": 1012373,
  "type": "Feature",
  "properties": {
    "tgn:hierarchy":[
        "tgn:1012373",
        "tgn:1000001",
        "tgn:1001906",
        "tgn:7005560",
        "tgn:7029392"
    ],
    "tgn:id":1012373,
    "tgn:name":"Raza, Punta",
    "tgn:placetype":[
        "aat:300386846"
    ]
},
  "bbox": [],
  "geometry": {"coordinates":[-105.333333,21.033333],"type":"Point"}
}