{
  "id": 7486192,
  "type": "Feature",
  "properties": {
    "tgn:hierarchy":[
        "tgn:7486192",
        "tgn:7001010",
        "tgn:1000004",
        "tgn:1000141",
        "tgn:7029392"
    ],
    "tgn:id":7486192,
    "tgn:name":"Rongxing Qiao",
    "tgn:placetype":[
        "aat:300007836"
    ]
},
  "bbox": [],
  "geometry": {"coordinates":[121.280867,23.217071],"type":"Point"}
}