{
  "id": 2620883,
  "type": "Feature",
  "properties": {
    "tgn:hierarchy":[
        "tgn:2620883",
        "tgn:1000001",
        "tgn:1002200",
        "tgn:7012149",
        "tgn:7007240",
        "tgn:7029392"
    ],
    "tgn:id":2620883,
    "tgn:name":"Roach Hole",
    "tgn:placetype":[
        "aat:300008680"
    ]
},
  "bbox": [],
  "geometry": {"coordinates":[-80.7667,28.6333],"type":"Point"}
}