<<<<<<< HEAD
{
  "id": 7375067,
  "type": "Feature",
  "properties": {
    "tgn:hierarchy":[
        "tgn:7375067",
        "tgn:1000001",
        "tgn:7005595",
        "tgn:7005560",
        "tgn:7029392"
    ],
    "tgn:id":7375067,
    "tgn:name":"Lechuguilla, Estero de la",
    "tgn:placetype":[
        "aat:300266559"
    ]
},
  "bbox": [],
  "geometry": {"coordinates":[-109.383333,25.6],"type":"Point"}
}
=======
{"geometry":{"type":"Point","coordinates":[-109.383333,25.600000]},"type":"Feature","properties":{"hierarchy":["tgn:7375067","tgn:1000001","tgn:7005595","tgn:7005560","tgn:7029392"],"placetype":["aat:300266559"],"id":7375067,"name:xx":"Lechuguilla, Estero de la"}}
>>>>>>> 03f74aca74312dbeaf24d7e61306dd6a786dc3d0
