{
  "id": 2617265,
  "type": "Feature",
  "properties": {
    "tgn:hierarchy":[
        "tgn:2617265",
        "tgn:1000001",
        "tgn:2000772",
        "tgn:7012149",
        "tgn:7007255",
        "tgn:7029392"
    ],
    "tgn:id":2617265,
    "tgn:name":"Richie Branch",
    "tgn:placetype":[
        "aat:300008699"
    ]
},
  "bbox": [],
  "geometry": {"coordinates":[-83.1833,37.6333],"type":"Point"}
}