{
  "id": 2160791,
  "type": "Feature",
  "properties": {
    "tgn:hierarchy":[
        "tgn:2160791",
        "tgn:1000001",
        "tgn:7012149",
        "tgn:2002055",
        "tgn:7007826",
        "tgn:7029392"
    ],
    "tgn:id":2160791,
    "tgn:name":"Belding Draw",
    "tgn:placetype":[
        "aat:300008761"
    ]
},
  "bbox": [],
  "geometry": {"coordinates":[-103.0333,30.4167],"type":"Point"}
}