{
  "id": 7578547,
  "type": "Feature",
  "properties": {
    "tgn:hierarchy":[
        "tgn:7578547",
        "tgn:1000004",
        "tgn:7000198",
        "tgn:1003539",
        "tgn:7029392"
    ],
    "tgn:id":7578547,
    "tgn:name:en":"Tura Range",
    "tgn:placetype":[
        "aat:300008795"
    ]
},
  "bbox": [],
  "geometry": {"coordinates":[90.454727,25.45675],"type":"Point"}
}