{
  "id": 1021004,
  "type": "Feature",
  "properties": {
    "tgn:hierarchy":[
        "tgn:1021004",
        "tgn:7006237",
        "tgn:1000047",
        "tgn:7002457",
        "tgn:1000002",
        "tgn:7029392"
    ],
    "tgn:id":1021004,
    "tgn:name":"Cambuquira",
    "tgn:placetype":[
        "aat:300008347"
    ]
},
  "bbox": [],
  "geometry": {"coordinates":[-45.3167,-21.8667],"type":"Point"}
}