{
  "id": 7509053,
  "type": "Feature",
  "properties": {
    "tgn:hierarchy":[
        "tgn:7509053",
        "tgn:1009227",
        "tgn:7001866",
        "tgn:1000226",
        "tgn:1000006",
        "tgn:7029392"
    ],
    "tgn:id":7509053,
    "tgn:name:en":"Takamatua Bay",
    "tgn:placetype":[
        "aat:300008347"
    ]
},
  "bbox": [],
  "geometry": {"coordinates":[172.966667,-43.783333],"type":"Point"}
}