{
  "id": 1031582,
  "type": "Feature",
  "properties": {
    "tgn:hierarchy":[
        "tgn:1031582",
        "tgn:7024077",
        "tgn:1000003",
        "tgn:1000069",
        "tgn:7029392"
    ],
    "tgn:id":1031582,
    "tgn:name":"Toholampi",
    "tgn:placetype":[
        "aat:300008347"
    ]
},
  "bbox": [],
  "geometry": {"coordinates":[24.25,63.7667],"type":"Point"}
}