<<<<<<< HEAD
{
  "id": 2150924,
  "type": "Feature",
  "properties": {
    "tgn:hierarchy":[
        "tgn:2150924",
        "tgn:1000001",
        "tgn:7012149",
        "tgn:1002794",
        "tgn:7007708",
        "tgn:7029392"
    ],
    "tgn:id":2150924,
    "tgn:name":"Bass Reservoir",
    "tgn:placetype":[
        "aat:300006191"
    ]
},
  "bbox": [],
  "geometry": {"coordinates":[-123.35,44.85],"type":"Point"}
}
=======
{"geometry":{"type":"Point","coordinates":[-123.350000,44.850000]},"type":"Feature","properties":{"hierarchy":["tgn:2150924","tgn:1000001","tgn:7012149","tgn:1002794","tgn:7007708","tgn:7029392"],"placetype":["aat:300006191"],"id":2150924,"name:xx":"Bass Reservoir"}}
>>>>>>> 03f74aca74312dbeaf24d7e61306dd6a786dc3d0
