{
  "id": 2150924,
  "type": "Feature",
  "properties": {
    "tgn:hierarchy":[
        "tgn:2150924",
        "tgn:1000001",
        "tgn:7012149",
        "tgn:1002794",
        "tgn:7007708",
        "tgn:7029392"
    ],
    "tgn:id":2150924,
    "tgn:name":"Bass Reservoir",
    "tgn:placetype":[
        "aat:300006191"
    ]
},
  "bbox": [],
  "geometry": {"coordinates":[-123.35,44.85],"type":"Point"}
}