{
  "id": 7418331,
  "type": "Feature",
  "properties": {
    "tgn:hierarchy":[
        "tgn:7418331",
        "tgn:7005579",
        "tgn:1000001",
        "tgn:7005560",
        "tgn:7029392"
    ],
    "tgn:id":7418331,
    "tgn:name":"Roto, Tanque",
    "tgn:placetype":[
        "aat:300008688"
    ]
},
  "bbox": [],
  "geometry": {"coordinates":[-102.170833,21.916667],"type":"Point"}
}