{
  "id": 2229139,
  "type": "Feature",
  "properties": {
    "tgn:hierarchy":[
        "tgn:2229139",
        "tgn:1000001",
        "tgn:7012149",
        "tgn:1002919",
        "tgn:7007252",
        "tgn:7029392"
    ],
    "tgn:id":2229139,
    "tgn:name":"Cedar Lake",
    "tgn:placetype":[
        "aat:300008905"
    ]
},
  "bbox": [],
  "geometry": {"coordinates":[-84.8833,41.7333],"type":"Point"}
}