{
  "id": 2715336,
  "type": "Feature",
  "properties": {
    "tgn:hierarchy":[
        "tgn:2715336",
        "tgn:1000001",
        "tgn:7012149",
        "tgn:1002628",
        "tgn:7007240",
        "tgn:7029392"
    ],
    "tgn:id":2715336,
    "tgn:name":"Terra Ceia Point",
    "tgn:placetype":[
        "aat:300008850"
    ]
},
  "bbox": [],
  "geometry": {"coordinates":[-82.6167,27.5333],"type":"Point"}
}