<<<<<<< HEAD
{
  "id": 7360649,
  "type": "Feature",
  "properties": {
    "tgn:hierarchy":[
        "tgn:7360649",
        "tgn:1001835",
        "tgn:1000001",
        "tgn:7005560",
        "tgn:7029392"
    ],
    "tgn:id":7360649,
    "tgn:name":"Cord\u00f3n",
    "tgn:placetype":[
        "aat:300008795"
    ]
},
  "bbox": [],
  "geometry": {"coordinates":[-115.6,32.533333],"type":"Point"}
}
=======
{"geometry":{"type":"Point","coordinates":[-115.600000,32.533333]},"type":"Feature","properties":{"hierarchy":["tgn:7360649","tgn:1001835","tgn:1000001","tgn:7005560","tgn:7029392"],"placetype":["aat:300008795"],"id":7360649,"name:xx":"Cord\u00f3n"}}
>>>>>>> 03f74aca74312dbeaf24d7e61306dd6a786dc3d0
