{
  "id": 7054463,
  "type": "Feature",
  "properties": {
    "tgn:hierarchy":[
        "tgn:7054463",
        "tgn:7005611",
        "tgn:1000003",
        "tgn:7003120",
        "tgn:1000080",
        "tgn:7029392"
    ],
    "tgn:id":7054463,
    "tgn:name":"Mongardino",
    "tgn:placetype":[
        "aat:300008347"
    ]
},
  "bbox": [],
  "geometry": {"coordinates":[8.216667,44.85],"type":"Point"}
}