<<<<<<< HEAD
{
  "id": 2332109,
  "type": "Feature",
  "properties": {
    "tgn:hierarchy":[
        "tgn:2332109",
        "tgn:1000001",
        "tgn:7012149",
        "tgn:7014398",
        "tgn:7013961",
        "tgn:7029392"
    ],
    "tgn:id":2332109,
    "tgn:name":"Flint Knob",
    "tgn:placetype":[
        "aat:300008798"
    ]
},
  "bbox": [],
  "geometry": {"coordinates":[-79.3333,38.5833],"type":"Point"}
}
=======
{"geometry":{"type":"Point","coordinates":[-79.333300,38.583300]},"type":"Feature","properties":{"hierarchy":["tgn:2332109","tgn:1000001","tgn:7012149","tgn:7014398","tgn:7013961","tgn:7029392"],"placetype":["aat:300008798"],"id":2332109,"name:xx":"Flint Knob"}}
>>>>>>> 03f74aca74312dbeaf24d7e61306dd6a786dc3d0
