{
  "id": 2563131,
  "type": "Feature",
  "properties": {
    "tgn:hierarchy":[
        "tgn:2563131",
        "tgn:1000001",
        "tgn:7016172",
        "tgn:7012149",
        "tgn:2000168",
        "tgn:7029392"
    ],
    "tgn:id":2563131,
    "tgn:name":"Owens Hollow",
    "tgn:placetype":[
        "aat:300008761"
    ]
},
  "bbox": [],
  "geometry": {"coordinates":[-93.8667,34.8667],"type":"Point"}
}