{
  "id": 2694662,
  "type": "Feature",
  "properties": {
    "tgn:hierarchy":[
        "tgn:2694662",
        "tgn:1000001",
        "tgn:7012149",
        "tgn:2001461",
        "tgn:7007568",
        "tgn:7029392"
    ],
    "tgn:id":2694662,
    "tgn:name":"Stewart Mountain",
    "tgn:placetype":[
        "aat:300008798"
    ]
},
  "bbox": [],
  "geometry": {"coordinates":[-73.85,44.3167],"type":"Point"}
}