{
  "id": 7381082,
  "type": "Feature",
  "properties": {
    "tgn:hierarchy":[
        "tgn:7381082",
        "tgn:7005581",
        "tgn:1000001",
        "tgn:7005560",
        "tgn:7029392"
    ],
    "tgn:id":7381082,
    "tgn:name":"Loma Prieta",
    "tgn:placetype":[
        "aat:300008347"
    ]
},
  "bbox": [],
  "geometry": {"coordinates":[-105.483333,28.533333],"type":"Point"}
}