{
  "id": 7312148,
  "type": "Feature",
  "properties": {
    "tgn:hierarchy":[
        "tgn:7312148",
        "tgn:1001630",
        "tgn:1000049",
        "tgn:1000002",
        "tgn:7029392"
    ],
    "tgn:id":7312148,
    "tgn:name":"Las Carmelitas",
    "tgn:placetype":[
        "aat:300387200"
    ]
},
  "bbox": [],
  "geometry": {"coordinates":[-70.033333,-27.616667],"type":"Point"}
}