{
  "id": 7283274,
  "type": "Feature",
  "properties": {
    "tgn:hierarchy":[
        "tgn:7283274",
        "tgn:1001702",
        "tgn:1000049",
        "tgn:1000002",
        "tgn:7029392"
    ],
    "tgn:id":7283274,
    "tgn:name":"Parker, Isla",
    "tgn:placetype":[
        "aat:300008791"
    ]
},
  "bbox": [],
  "geometry": {"coordinates":[-74.133333,-52.683333],"type":"Point"}
}