{
  "id": 2745419,
  "type": "Feature",
  "properties": {
    "tgn:hierarchy":[
        "tgn:2745419",
        "tgn:1000001",
        "tgn:2001483",
        "tgn:7012149",
        "tgn:7007709",
        "tgn:7029392"
    ],
    "tgn:id":2745419,
    "tgn:name":"Vineyard Mountain",
    "tgn:placetype":[
        "aat:300008798"
    ]
},
  "bbox": [],
  "geometry": {"coordinates":[-83.6667,35.05],"type":"Point"}
}