{
  "id": 7102937,
  "type": "Feature",
  "properties": {
    "tgn:hierarchy":[
        "tgn:7102937",
        "tgn:1000003",
        "tgn:7003676",
        "tgn:7000084",
        "tgn:7029392"
    ],
    "tgn:id":7102937,
    "tgn:name":"Rotes L\u00e4ppchen",
    "tgn:placetype":[
        "aat:300387200"
    ]
},
  "bbox": [],
  "geometry": {"coordinates":[7.233333,52.816667],"type":"Point"}
}