{
  "id": 7231552,
  "type": "Feature",
  "properties": {
    "tgn:hierarchy":[
        "tgn:7231552",
        "tgn:4003773",
        "tgn:7001395",
        "tgn:1000003",
        "tgn:1000074",
        "tgn:7029392"
    ],
    "tgn:id":7231552,
    "tgn:name":"Koust\u00e9sa",
    "tgn:placetype":[
        "aat:300008347"
    ]
},
  "bbox": [],
  "geometry": {"coordinates":[21.63,39.2275],"type":"Point"}
}