{
  "id": 2178800,
  "type": "Feature",
  "properties": {
    "tgn:hierarchy":[
        "tgn:2178800",
        "tgn:1000001",
        "tgn:7012149",
        "tgn:2001607",
        "tgn:7007705",
        "tgn:7029392"
    ],
    "tgn:id":2178800,
    "tgn:name":"Blackwater Coulee",
    "tgn:placetype":[
        "aat:300008761"
    ]
},
  "bbox": [],
  "geometry": {"coordinates":[-101.2833,48.0167],"type":"Point"}
}