{
  "id": 7005141,
  "type": "Feature",
  "properties": {
    "tgn:hierarchy":[
        "tgn:7005141",
        "tgn:7003171",
        "tgn:1000003",
        "tgn:7003125",
        "tgn:1000080",
        "tgn:7029392"
    ],
    "tgn:id":7005141,
    "tgn:name":"Otricoli",
    "tgn:placetype":[
        "aat:300008347"
    ]
},
  "bbox": [],
  "geometry": {"coordinates":[12.483333,42.416667],"type":"Point"}
}