{
  "id": 7167234,
  "type": "Feature",
  "properties": {
    "tgn:hierarchy":[
        "tgn:7167234",
        "tgn:7003692",
        "tgn:1000003",
        "tgn:7000084",
        "tgn:7029392"
    ],
    "tgn:id":7167234,
    "tgn:name":"Heinkenbusch",
    "tgn:placetype":[
        "aat:300008347"
    ]
},
  "bbox": [],
  "geometry": {"coordinates":[9.983333,49.15],"type":"Point"}
}