{
  "id": 1127886,
  "type": "Feature",
  "properties": {
    "tgn:hierarchy":[
        "tgn:1127886",
        "tgn:1000001",
        "tgn:7012149",
        "tgn:7007826",
        "tgn:7029392"
    ],
    "tgn:id":1127886,
    "tgn:name":"North Llano",
    "tgn:placetype":[
        "aat:300008707"
    ]
},
  "bbox": [],
  "geometry": {"coordinates":[-100.4333,30.6167],"type":"Point"}
}