{
  "id": 2415756,
  "type": "Feature",
  "properties": {
    "tgn:hierarchy":[
        "tgn:2415756",
        "tgn:1000001",
        "tgn:7012149",
        "tgn:2000289",
        "tgn:7007240",
        "tgn:7029392"
    ],
    "tgn:id":2415756,
    "tgn:name":"Ivan",
    "tgn:placetype":[
        "aat:300008347"
    ]
},
  "bbox": [],
  "geometry": {"coordinates":[-84.35,30.2167],"type":"Point"}
}