<<<<<<< HEAD
{
  "id": 2768045,
  "type": "Feature",
  "properties": {
    "tgn:hierarchy":[
        "tgn:2768045",
        "tgn:1000001",
        "tgn:7012149",
        "tgn:2001854",
        "tgn:7007825",
        "tgn:7029392"
    ],
    "tgn:id":2768045,
    "tgn:name":"Whitepine Branch",
    "tgn:placetype":[
        "aat:300008699"
    ]
},
  "bbox": [],
  "geometry": {"coordinates":[-84.9667,36.0167],"type":"Point"}
}
=======
{"geometry":{"type":"Point","coordinates":[-84.966700,36.016700]},"type":"Feature","properties":{"hierarchy":["tgn:2768045","tgn:1000001","tgn:7012149","tgn:2001854","tgn:7007825","tgn:7029392"],"placetype":["aat:300008699"],"id":2768045,"name:xx":"Whitepine Branch"}}
>>>>>>> 03f74aca74312dbeaf24d7e61306dd6a786dc3d0
