{
  "id": 7523232,
  "type": "Feature",
  "properties": {
    "tgn:hierarchy":[
        "tgn:7523232",
        "tgn:7001242",
        "tgn:7016833",
        "tgn:1001225",
        "tgn:7029392"
    ],
    "tgn:id":7523232,
    "tgn:name:en":"Barr, Ra's al",
    "tgn:placetype":[
        "aat:300008850"
    ]
},
  "bbox": [],
  "geometry": {"coordinates":[31.840556,31.525],"type":"Point"}
}