{
  "id": 7444492,
  "type": "Feature",
  "properties": {
    "tgn:hierarchy":[
        "tgn:7444492",
        "tgn:7002445",
        "tgn:1000003",
        "tgn:7012032",
        "tgn:7008591",
        "tgn:7029392"
    ],
    "tgn:id":7444492,
    "tgn:name:en":"Lamyatt",
    "tgn:placetype":[
        "aat:300008347"
    ]
},
  "bbox": [],
  "geometry": {"coordinates":[-2.495,51.121667],"type":"Point"}
}