{
  "id": 2688574,
  "type": "Feature",
  "properties": {
    "tgn:hierarchy":[
        "tgn:2688574",
        "tgn:1000001",
        "tgn:7012149",
        "tgn:2000836",
        "tgn:7007255",
        "tgn:7029392"
    ],
    "tgn:id":2688574,
    "tgn:name":"Spruce Pine Fork",
    "tgn:placetype":[
        "aat:300008699"
    ]
},
  "bbox": [],
  "geometry": {"coordinates":[-83.5167,37.3333],"type":"Point"}
}