{
  "id": 7435236,
  "type": "Feature",
  "properties": {
    "tgn:hierarchy":[
        "tgn:7435236",
        "tgn:1000001",
        "tgn:1001960",
        "tgn:7005560",
        "tgn:7029392"
    ],
    "tgn:id":7435236,
    "tgn:name":"Valle",
    "tgn:placetype":[
        "aat:300008347"
    ]
},
  "bbox": [],
  "geometry": {"coordinates":[-111.116667,30.566667],"type":"Point"}
}