{
  "id": 2200675,
  "type": "Feature",
  "properties": {
    "tgn:hierarchy":[
        "tgn:2200675",
        "tgn:1000001",
        "tgn:7012149",
        "tgn:2001444",
        "tgn:7007566",
        "tgn:7029392"
    ],
    "tgn:id":2200675,
    "tgn:name":"Brushy Tank",
    "tgn:placetype":[
        "aat:300006191"
    ]
},
  "bbox": [],
  "geometry": {"coordinates":[-107.4333,32.0833],"type":"Point"}
}