{
  "id": 2703541,
  "type": "Feature",
  "properties": {
    "tgn:hierarchy":[
        "tgn:2703541",
        "tgn:1000001",
        "tgn:7012149",
        "tgn:7007157",
        "tgn:7029392"
    ],
    "tgn:id":2703541,
    "tgn:name":"Summit Range",
    "tgn:placetype":[
        "aat:300386831"
    ]
},
  "bbox": [],
  "geometry": {"coordinates":[-117.5667,35.45],"type":"Point"}
}