{
  "id": 1088511,
  "type": "Feature",
  "properties": {
    "tgn:hierarchy":[
        "tgn:1088511",
        "tgn:7001242",
        "tgn:7016848",
        "tgn:1000156",
        "tgn:7029392"
    ],
    "tgn:id":1088511,
    "tgn:name":"Goz-Be\u00efda",
    "tgn:placetype":[
        "aat:300008347"
    ]
},
  "bbox": [],
  "geometry": {"coordinates":[21.3333,12.1667],"type":"Point"}
}