{
  "id": 7450566,
  "type": "Feature",
  "properties": {
    "tgn:hierarchy":[
        "tgn:7450566",
        "tgn:7002443",
        "tgn:7018962",
        "tgn:1000003",
        "tgn:7008591",
        "tgn:7029392"
    ],
    "tgn:id":7450566,
    "tgn:name:en":"General Station",
    "tgn:placetype":[
        "aat:300007783"
    ]
},
  "bbox": [],
  "geometry": {"coordinates":[-3.166667,51.483333],"type":"Point"}
}