{
  "id": 2037629,
  "type": "Feature",
  "properties": {
    "tgn:hierarchy":[
        "tgn:2037629",
        "tgn:1000001",
        "tgn:7012149",
        "tgn:1002375",
        "tgn:7007255",
        "tgn:7029392"
    ],
    "tgn:id":2037629,
    "tgn:name":"Battle Run",
    "tgn:placetype":[
        "aat:300008347",
        "aat:300387210"
    ]
},
  "bbox": [],
  "geometry": {"coordinates":[-83.8333,38.3333],"type":"Point"}
}