{
  "id": 2656806,
  "type": "Feature",
  "properties": {
    "tgn:hierarchy":[
        "tgn:2656806",
        "tgn:1000001",
        "tgn:7012149",
        "tgn:7029392"
    ],
    "tgn:id":2656806,
    "tgn:name":"Sheep Dip Hollow",
    "tgn:placetype":[
        "aat:300008761"
    ]
},
  "bbox": [],
  "geometry": {"coordinates":[-112.15,41.9833],"type":"Point"}
}