{
  "id": 2152455,
  "type": "Feature",
  "properties": {
    "tgn:hierarchy":[
        "tgn:2152455",
        "tgn:1000001",
        "tgn:2000270",
        "tgn:7012149",
        "tgn:7007240",
        "tgn:7029392"
    ],
    "tgn:id":2152455,
    "tgn:name":"Bay San Blas",
    "tgn:placetype":[
        "aat:300132316"
    ]
},
  "bbox": [],
  "geometry": {"coordinates":[-85.2833,29.6667],"type":"Point"}
}