<<<<<<< HEAD
{
  "id": 7112534,
  "type": "Feature",
  "properties": {
    "tgn:hierarchy":[
        "tgn:7112534",
        "tgn:7003669",
        "tgn:1000003",
        "tgn:7000084",
        "tgn:7029392"
    ],
    "tgn:id":7112534,
    "tgn:name":"Rindel Berg",
    "tgn:placetype":[
        "aat:300008795"
    ]
},
  "bbox": [],
  "geometry": {"coordinates":[13.5,48.9],"type":"Point"}
}
=======
{"geometry":{"type":"Point","coordinates":[13.500000,48.900000]},"type":"Feature","properties":{"hierarchy":["tgn:7112534","tgn:7003669","tgn:1000003","tgn:7000084","tgn:7029392"],"placetype":["aat:300008795"],"id":7112534,"name:xx":"Rindel Berg"}}
>>>>>>> 03f74aca74312dbeaf24d7e61306dd6a786dc3d0
