<<<<<<< HEAD
{
  "id": 2331468,
  "type": "Feature",
  "properties": {
    "tgn:hierarchy":[
        "tgn:2331468",
        "tgn:1000001",
        "tgn:7006451",
        "tgn:7012149",
        "tgn:2000098",
        "tgn:7029392"
    ],
    "tgn:id":2331468,
    "tgn:name":"Flattop Draw",
    "tgn:placetype":[
        "aat:300008761"
    ]
},
  "bbox": [],
  "geometry": {"coordinates":[-113.0,36.7833],"type":"Point"}
}
=======
{"geometry":{"type":"Point","coordinates":[-113.000000,36.783300]},"type":"Feature","properties":{"hierarchy":["tgn:2331468","tgn:1000001","tgn:7006451","tgn:7012149","tgn:2000098","tgn:7029392"],"placetype":["aat:300008761"],"id":2331468,"name:xx":"Flattop Draw"}}
>>>>>>> 03f74aca74312dbeaf24d7e61306dd6a786dc3d0
