{
  "id": 7509601,
  "type": "Feature",
  "properties": {
    "tgn:hierarchy":[
        "tgn:7509601",
        "tgn:1008380",
        "tgn:1000226",
        "tgn:7000512",
        "tgn:1000006",
        "tgn:7029392"
    ],
    "tgn:id":7509601,
    "tgn:name:en":"Te Whanga",
    "tgn:placetype":[
        "aat:300008795"
    ]
},
  "bbox": [],
  "geometry": {"coordinates":[175.733333,-41.033333],"type":"Point"}
}