{
  "id": 2306956,
  "type": "Feature",
  "properties": {
    "tgn:hierarchy":[
        "tgn:2306956",
        "tgn:1000001",
        "tgn:7012149",
        "tgn:2001277",
        "tgn:7007524",
        "tgn:7029392"
    ],
    "tgn:id":2306956,
    "tgn:name":"East Fork Lee Creek",
    "tgn:placetype":[
        "aat:300008706"
    ]
},
  "bbox": [],
  "geometry": {"coordinates":[-113.5833,48.9333],"type":"Point"}
}