{
  "id": 7096875,
  "type": "Feature",
  "properties": {
    "tgn:hierarchy":[
        "tgn:7096875",
        "tgn:7003669",
        "tgn:1000003",
        "tgn:7000084",
        "tgn:7029392"
    ],
    "tgn:id":7096875,
    "tgn:name":"Ruine Sodenburg",
    "tgn:placetype":[
        "aat:300008057"
    ]
},
  "bbox": [],
  "geometry": {"coordinates":[9.216667,49.916667],"type":"Point"}
}