{
  "id": 7256625,
  "type": "Feature",
  "properties": {
    "tgn:concordances":{
        "gn:id":"2759667"
    },
    "tgn:hierarchy":[
        "tgn:7256625",
        "tgn:7003619",
        "tgn:1000003",
        "tgn:7016845",
        "tgn:7029392"
    ],
    "tgn:id":7256625,
    "tgn:name:nl":"Armhoede",
    "tgn:placetype":[
        "aat:300008347"
    ]
},
  "bbox": [],
  "geometry": {"coordinates":[6.45,52.166667],"type":"Point"}
}