{
  "id": 2516085,
  "type": "Feature",
  "properties": {
    "tgn:hierarchy":[
        "tgn:2516085",
        "tgn:1000001",
        "tgn:1002724",
        "tgn:7012149",
        "tgn:7007517",
        "tgn:7029392"
    ],
    "tgn:id":2516085,
    "tgn:name":"Mine Brook",
    "tgn:placetype":[
        "aat:300008699"
    ]
},
  "bbox": [],
  "geometry": {"coordinates":[-71.2667,42.1833],"type":"Point"}
}