{
  "id": 2463231,
  "type": "Feature",
  "properties": {
    "tgn:hierarchy":[
        "tgn:2463231",
        "tgn:1000001",
        "tgn:7012149",
        "tgn:7007158",
        "tgn:7029392"
    ],
    "tgn:id":2463231,
    "tgn:name":"Lizard Head",
    "tgn:placetype":[
        "aat:300008798"
    ]
},
  "bbox": [],
  "geometry": {"coordinates":[-107.95,37.8333],"type":"Point"}
}