{
  "id": 2190907,
  "type": "Feature",
  "properties": {
    "tgn:hierarchy":[
        "tgn:2190907",
        "tgn:1000001",
        "tgn:7012149",
        "tgn:2001927",
        "tgn:7007825",
        "tgn:7029392"
    ],
    "tgn:id":2190907,
    "tgn:name":"Boyd Hollow",
    "tgn:placetype":[
        "aat:300008761"
    ]
},
  "bbox": [],
  "geometry": {"coordinates":[-87.8333,35.3167],"type":"Point"}
}