<<<<<<< HEAD
{
  "id": 7028298,
  "type": "Feature",
  "properties": {
    "tgn:hierarchy":[
        "tgn:7028298",
        "tgn:7002445",
        "tgn:1000003",
        "tgn:7008160",
        "tgn:7008591",
        "tgn:7029392"
    ],
    "tgn:id":7028298,
    "tgn:name":"East Bradenham",
    "tgn:placetype":[
        "aat:300008347",
        "aat:300008372"
    ]
},
  "bbox": [],
  "geometry": {"coordinates":[0.85,52.633333],"type":"Point"}
}
=======
{"geometry":{"type":"Point","coordinates":[0.850000,52.633333]},"type":"Feature","properties":{"hierarchy":["tgn:7028298","tgn:7002445","tgn:1000003","tgn:7008160","tgn:7008591","tgn:7029392"],"placetype":["aat:300008347","aat:300008372"],"id":7028298,"name:xx":"East Bradenham"}}
>>>>>>> 03f74aca74312dbeaf24d7e61306dd6a786dc3d0
