{
  "id": 2706088,
  "type": "Feature",
  "properties": {
    "tgn:hierarchy":[
        "tgn:2706088",
        "tgn:1000001",
        "tgn:2000922",
        "tgn:7012149",
        "tgn:7007515",
        "tgn:7029392"
    ],
    "tgn:id":2706088,
    "tgn:name":"Swains Ledge",
    "tgn:placetype":[
        "aat:300132348"
    ]
},
  "bbox": [],
  "geometry": {"coordinates":[-68.7333,44.2833],"type":"Point"}
}