{
  "id": 2143203,
  "type": "Feature",
  "properties": {
    "tgn:hierarchy":[
        "tgn:2143203",
        "tgn:1000001",
        "tgn:7012149",
        "tgn:2001851",
        "tgn:7007825",
        "tgn:7029392"
    ],
    "tgn:id":2143203,
    "tgn:name":"Bailey Branch",
    "tgn:placetype":[
        "aat:300008699"
    ]
},
  "bbox": [],
  "geometry": {"coordinates":[-83.2667,35.85],"type":"Point"}
}