{
  "id": 7391027,
  "type": "Feature",
  "properties": {
    "tgn:hierarchy":[
        "tgn:7391027",
        "tgn:7005580",
        "tgn:1000001",
        "tgn:7005560",
        "tgn:7029392"
    ],
    "tgn:id":7391027,
    "tgn:name":"R\u00edo Grande",
    "tgn:placetype":[
        "aat:300008347"
    ]
},
  "bbox": [],
  "geometry": {"coordinates":[-93.883333,16.233333],"type":"Point"}
}