{
  "id": 7506374,
  "type": "Feature",
  "properties": {
    "tgn:hierarchy":[
        "tgn:7506374",
        "tgn:1009227",
        "tgn:7001866",
        "tgn:1000226",
        "tgn:1000006",
        "tgn:7029392"
    ],
    "tgn:id":7506374,
    "tgn:name:en":"Row, Mount",
    "tgn:placetype":[
        "aat:300008795"
    ]
},
  "bbox": [],
  "geometry": {"coordinates":[171.95,-42.816667],"type":"Point"}
}