{
  "id": 2506933,
  "type": "Feature",
  "properties": {
    "tgn:hierarchy":[
        "tgn:2506933",
        "tgn:1000001",
        "tgn:7006451",
        "tgn:7012149",
        "tgn:2000097",
        "tgn:7029392"
    ],
    "tgn:id":2506933,
    "tgn:name":"Mesquite Tank Wash",
    "tgn:placetype":[
        "aat:300008701"
    ]
},
  "bbox": [],
  "geometry": {"coordinates":[-112.0167,33.7667],"type":"Point"}
}