{
  "id": 2387671,
  "type": "Feature",
  "properties": {
    "tgn:hierarchy":[
        "tgn:2387671",
        "tgn:1000001",
        "tgn:7012149",
        "tgn:1002950",
        "tgn:7007568",
        "tgn:7029392"
    ],
    "tgn:id":2387671,
    "tgn:name":"Hibbards Corner",
    "tgn:placetype":[
        "aat:300008347"
    ]
},
  "bbox": [],
  "geometry": {"coordinates":[-76.4167,42.4167],"type":"Point"}
}