{
  "id": 2008787,
  "type": "Feature",
  "properties": {
    "tgn:hierarchy":[
        "tgn:2008787",
        "tgn:1000001",
        "tgn:7016172",
        "tgn:2000111",
        "tgn:7012149",
        "tgn:7029392"
    ],
    "tgn:id":2008787,
    "tgn:name":"Locust Bayou",
    "tgn:placetype":[
        "aat:300008347"
    ]
},
  "bbox": [],
  "geometry": {"coordinates":[-92.6667,33.55],"type":"Point"}
}