{
  "id": 2125293,
  "type": "Feature",
  "properties": {
    "tgn:hierarchy":[
        "tgn:2125293",
        "tgn:1000001",
        "tgn:7012149",
        "tgn:1003021",
        "tgn:7007252",
        "tgn:7029392"
    ],
    "tgn:id":2125293,
    "tgn:name":"Ackerman Ditch",
    "tgn:placetype":[
        "aat:300006075"
    ]
},
  "bbox": [],
  "geometry": {"coordinates":[-86.6333,40.8667],"type":"Point"}
}