{
  "id": 7200916,
  "type": "Feature",
  "properties": {
    "tgn:hierarchy":[
        "tgn:7200916",
        "tgn:7000096",
        "tgn:1000003",
        "tgn:7000084",
        "tgn:7029392"
    ],
    "tgn:id":7200916,
    "tgn:name":"D\u00fcppel-Berg",
    "tgn:placetype":[
        "aat:300008777"
    ]
},
  "bbox": [],
  "geometry": {"coordinates":[12.433333,52.35],"type":"Point"}
}