{
  "id": 7296067,
  "type": "Feature",
  "properties": {
    "tgn:hierarchy":[
        "tgn:7296067",
        "tgn:7007780",
        "tgn:1000003",
        "tgn:7009604",
        "tgn:1000095",
        "tgn:7029392"
    ],
    "tgn:id":7296067,
    "tgn:name":"Yurre",
    "tgn:placetype":[
        "aat:300008347"
    ]
},
  "bbox": [],
  "geometry": {"coordinates":[-2.217714,43.037329],"type":"Point"}
}