{
  "id": 2722334,
  "type": "Feature",
  "properties": {
    "tgn:hierarchy":[
        "tgn:2722334",
        "tgn:1000001",
        "tgn:2002368",
        "tgn:7012149",
        "tgn:7007923",
        "tgn:7029392"
    ],
    "tgn:id":2722334,
    "tgn:name":"Tin Can Draw",
    "tgn:placetype":[
        "aat:300008761"
    ]
},
  "bbox": [],
  "geometry": {"coordinates":[-106.7333,42.2167],"type":"Point"}
}