{
  "id": 2222552,
  "type": "Feature",
  "properties": {
    "tgn:hierarchy":[
        "tgn:2222552",
        "tgn:1000001",
        "tgn:7012149",
        "tgn:1002746",
        "tgn:7007568",
        "tgn:7029392"
    ],
    "tgn:id":2222552,
    "tgn:name":"Carpenter Pond",
    "tgn:placetype":[
        "aat:300008680"
    ]
},
  "bbox": [],
  "geometry": {"coordinates":[-75.9667,42.8667],"type":"Point"}
}