{
  "id": 7143495,
  "type": "Feature",
  "properties": {
    "tgn:hierarchy":[
        "tgn:7143495",
        "tgn:1000003",
        "tgn:7003676",
        "tgn:7000084",
        "tgn:7029392"
    ],
    "tgn:id":7143495,
    "tgn:name":"Lockhausen",
    "tgn:placetype":[
        "aat:300008347"
    ]
},
  "bbox": [],
  "geometry": {"coordinates":[8.366667,52.333333],"type":"Point"}
}