{
  "id": 7039327,
  "type": "Feature",
  "properties": {
    "tgn:hierarchy":[
        "tgn:7039327",
        "tgn:7015163",
        "tgn:1000003",
        "tgn:7003121",
        "tgn:1000080",
        "tgn:7029392"
    ],
    "tgn:id":7039327,
    "tgn:name":"Surrau, Rio",
    "tgn:placetype":[
        "aat:300008699"
    ]
},
  "bbox": [],
  "geometry": {"coordinates":[9.033333,41.183333],"type":"Point"}
}