{
  "id": 2455828,
  "type": "Feature",
  "properties": {
    "tgn:hierarchy":[
        "tgn:2455828",
        "tgn:1000001",
        "tgn:7012149",
        "tgn:1002518",
        "tgn:7007568",
        "tgn:7029392"
    ],
    "tgn:id":2455828,
    "tgn:name":"Little Grenadier Island",
    "tgn:placetype":[
        "aat:300008791"
    ]
},
  "bbox": [],
  "geometry": {"coordinates":[-76.3333,44.0333],"type":"Point"}
}