{
  "id": 2743378,
  "type": "Feature",
  "properties": {
    "tgn:hierarchy":[
        "tgn:2743378",
        "tgn:1000001",
        "tgn:7012149",
        "tgn:7007158",
        "tgn:2000244",
        "tgn:7029392"
    ],
    "tgn:id":2743378,
    "tgn:name":"Vano Ditch",
    "tgn:placetype":[
        "aat:300006075"
    ]
},
  "bbox": [],
  "geometry": {"coordinates":[-106.0833,37.65],"type":"Point"}
}