{
  "id": 2480631,
  "type": "Feature",
  "properties": {
    "tgn:hierarchy":[
        "tgn:2480631",
        "tgn:1000001",
        "tgn:7012149",
        "tgn:2002357",
        "tgn:7007922",
        "tgn:7029392"
    ],
    "tgn:id":2480631,
    "tgn:name":"Lakes Coulee",
    "tgn:placetype":[
        "aat:300008761"
    ]
},
  "bbox": [],
  "geometry": {"coordinates":[-91.35,44.25],"type":"Point"}
}