{
  "id": 7463998,
  "type": "Feature",
  "properties": {
    "tgn:hierarchy":[
        "tgn:7463998",
        "tgn:7002445",
        "tgn:1003664",
        "tgn:1000003",
        "tgn:7026570",
        "tgn:7008591",
        "tgn:7029392"
    ],
    "tgn:id":7463998,
    "tgn:name:en":"Bickershaw",
    "tgn:placetype":[
        "aat:300008347"
    ]
},
  "bbox": [],
  "geometry": {"coordinates":[-2.566667,53.516667],"type":"Point"}
}