{
  "id": 2440989,
  "type": "Feature",
  "properties": {
    "tgn:hierarchy":[
        "tgn:2440989",
        "tgn:1000001",
        "tgn:7012149",
        "tgn:7029392"
    ],
    "tgn:id":2440989,
    "tgn:name":"Knob Run",
    "tgn:placetype":[
        "aat:300008699"
    ]
},
  "bbox": [],
  "geometry": {"coordinates":[-80.4667,39.7167],"type":"Point"}
}