<<<<<<< HEAD
{
  "id": 7352942,
  "type": "Feature",
  "properties": {
    "tgn:hierarchy":[
        "tgn:7352942",
        "tgn:1000001",
        "tgn:7005595",
        "tgn:7005560",
        "tgn:7029392"
    ],
    "tgn:id":7352942,
    "tgn:name":"Batopito",
    "tgn:placetype":[
        "aat:300008347"
    ]
},
  "bbox": [],
  "geometry": {"coordinates":[-107.516667,25.3],"type":"Point"}
}
=======
{"geometry":{"type":"Point","coordinates":[-107.516667,25.300000]},"type":"Feature","properties":{"hierarchy":["tgn:7352942","tgn:1000001","tgn:7005595","tgn:7005560","tgn:7029392"],"placetype":["aat:300008347"],"id":7352942,"name:xx":"Batopito"}}
>>>>>>> 03f74aca74312dbeaf24d7e61306dd6a786dc3d0
