{
  "id": 2113504,
  "type": "Feature",
  "properties": {
    "tgn:hierarchy":[
        "tgn:2113504",
        "tgn:1000001",
        "tgn:7012149",
        "tgn:1002647",
        "tgn:7007919",
        "tgn:7029392"
    ],
    "tgn:id":2113504,
    "tgn:name":"Onemo",
    "tgn:placetype":[
        "aat:300008347"
    ]
},
  "bbox": [],
  "geometry": {"coordinates":[-76.2667,37.3833],"type":"Point"}
}