{
  "id": 2689550,
  "type": "Feature",
  "properties": {
    "tgn:hierarchy":[
        "tgn:2689550",
        "tgn:1000001",
        "tgn:7012149",
        "tgn:2002341",
        "tgn:7007922",
        "tgn:7029392"
    ],
    "tgn:id":2689550,
    "tgn:name":"Squaw Lake",
    "tgn:placetype":[
        "aat:300008680"
    ]
},
  "bbox": [],
  "geometry": {"coordinates":[-88.2333,45.05],"type":"Point"}
}