{
  "id": 2164072,
  "type": "Feature",
  "properties": {
    "tgn:hierarchy":[
        "tgn:2164072",
        "tgn:1000001",
        "tgn:7012149",
        "tgn:2001854",
        "tgn:7007825",
        "tgn:7029392"
    ],
    "tgn:id":2164072,
    "tgn:name":"Berks Creek",
    "tgn:placetype":[
        "aat:300008706"
    ]
},
  "bbox": [],
  "geometry": {"coordinates":[-84.85,35.8833],"type":"Point"}
}