{
  "id": 7005751,
  "type": "Feature",
  "properties": {
    "tgn:hierarchy":[
        "tgn:7005751",
        "tgn:1000003",
        "tgn:7594248",
        "tgn:7005729",
        "tgn:7029392"
    ],
    "tgn:id":7005751,
    "tgn:name":"\u017burrieq",
    "tgn:placetype":[
        "aat:300008347"
    ]
},
  "bbox": [],
  "geometry": {"coordinates":[14.4833,35.8333],"type":"Point"}
}