{
  "id": 7442889,
  "type": "Feature",
  "properties": {
    "tgn:hierarchy":[
        "tgn:7442889",
        "tgn:7002445",
        "tgn:1000003",
        "tgn:7008166",
        "tgn:7008591",
        "tgn:7029392"
    ],
    "tgn:id":7442889,
    "tgn:name:en":"Whitleybridge",
    "tgn:placetype":[
        "aat:300008347"
    ]
},
  "bbox": [],
  "geometry": {"coordinates":[-1.15,53.683333],"type":"Point"}
}