{
  "id": 2782204,
  "type": "Feature",
  "properties": {
    "tgn:hierarchy":[
        "tgn:2782204",
        "tgn:1000001",
        "tgn:1002665",
        "tgn:7012149",
        "tgn:7007517",
        "tgn:7029392"
    ],
    "tgn:id":2782204,
    "tgn:name":"Woodsville",
    "tgn:placetype":[
        "aat:300008347"
    ]
},
  "bbox": [],
  "geometry": {"coordinates":[-71.6167,42.5667],"type":"Point"}
}