{
  "id": 1024631,
  "type": "Feature",
  "properties": {
    "tgn:hierarchy":[
        "tgn:1024631",
        "tgn:1000700",
        "tgn:1000002",
        "tgn:1000056",
        "tgn:7029392"
    ],
    "tgn:id":1024631,
    "tgn:name":"Moquegua",
    "tgn:placetype":[
        "aat:300008347",
        "aat:300387220",
        "aat:300008375"
    ]
},
  "bbox": [],
  "geometry": {"coordinates":[-70.9333,-17.1833],"type":"Point"}
}