{
  "id": 7388207,
  "type": "Feature",
  "properties": {
    "tgn:hierarchy":[
        "tgn:7388207",
        "tgn:1000001",
        "tgn:1001937",
        "tgn:7005560",
        "tgn:7029392"
    ],
    "tgn:id":7388207,
    "tgn:name":"Puerto Madero",
    "tgn:placetype":[
        "aat:300008347"
    ]
},
  "bbox": [],
  "geometry": {"coordinates":[-87.466667,19.283333],"type":"Point"}
}