{
  "id": 7239736,
  "type": "Feature",
  "properties": {
    "tgn:hierarchy":[
        "tgn:7239736",
        "tgn:7003456",
        "tgn:1000003",
        "tgn:1000063",
        "tgn:7018236",
        "tgn:7029392"
    ],
    "tgn:id":7239736,
    "tgn:name":"Gijmelberg",
    "tgn:placetype":[
        "aat:300008347"
    ]
},
  "bbox": [],
  "geometry": {"coordinates":[4.843556,51.003592],"type":"Point"}
}