{
  "id": 2470848,
  "type": "Feature",
  "properties": {
    "tgn:hierarchy":[
        "tgn:2470848",
        "tgn:1000001",
        "tgn:2001410",
        "tgn:7012149",
        "tgn:7007526",
        "tgn:7029392"
    ],
    "tgn:id":2470848,
    "tgn:name":"Lost Cove",
    "tgn:placetype":[
        "aat:300132316"
    ]
},
  "bbox": [],
  "geometry": {"coordinates":[-114.6333,35.3833],"type":"Point"}
}