{
  "id": 1138974,
  "type": "Feature",
  "properties": {
    "tgn:hierarchy":[
        "tgn:1138974",
        "tgn:1000004",
        "tgn:7002077",
        "tgn:1000111",
        "tgn:7029392"
    ],
    "tgn:id":1138974,
    "tgn:name":"Funing",
    "tgn:placetype":[
        "aat:300008347"
    ]
},
  "bbox": [],
  "geometry": {"coordinates":[119.25,39.8667],"type":"Point"}
}