{
  "id": 2087972,
  "type": "Feature",
  "properties": {
    "tgn:hierarchy":[
        "tgn:2087972",
        "tgn:1000001",
        "tgn:7012149",
        "tgn:1002564",
        "tgn:7007710",
        "tgn:7029392"
    ],
    "tgn:id":2087972,
    "tgn:name":"East Benton",
    "tgn:placetype":[
        "aat:300008347"
    ]
},
  "bbox": [],
  "geometry": {"coordinates":[-75.65,41.5667],"type":"Point"}
}