<<<<<<< HEAD
{
  "id": 2338339,
  "type": "Feature",
  "properties": {
    "tgn:hierarchy":[
        "tgn:2338339",
        "tgn:1000001",
        "tgn:7012149",
        "tgn:2001489",
        "tgn:7007709",
        "tgn:7029392"
    ],
    "tgn:id":2338339,
    "tgn:name":"Foxcroff",
    "tgn:placetype":[
        "aat:300008347"
    ]
},
  "bbox": [],
  "geometry": {"coordinates":[-80.2833,35.7333],"type":"Point"}
}
=======
{"geometry":{"type":"Point","coordinates":[-80.283300,35.733300]},"type":"Feature","properties":{"hierarchy":["tgn:2338339","tgn:1000001","tgn:7012149","tgn:2001489","tgn:7007709","tgn:7029392"],"placetype":["aat:300008347"],"id":2338339,"name:xx":"Foxcroff"}}
>>>>>>> 03f74aca74312dbeaf24d7e61306dd6a786dc3d0
