{
  "id": 2338339,
  "type": "Feature",
  "properties": {
    "tgn:hierarchy":[
        "tgn:2338339",
        "tgn:1000001",
        "tgn:7012149",
        "tgn:2001489",
        "tgn:7007709",
        "tgn:7029392"
    ],
    "tgn:id":2338339,
    "tgn:name":"Foxcroff",
    "tgn:placetype":[
        "aat:300008347"
    ]
},
  "bbox": [],
  "geometry": {"coordinates":[-80.2833,35.7333],"type":"Point"}
}