<<<<<<< HEAD
{
  "id": 2159352,
  "type": "Feature",
  "properties": {
    "tgn:hierarchy":[
        "tgn:2159352",
        "tgn:1000001",
        "tgn:7006451",
        "tgn:2000092",
        "tgn:7012149",
        "tgn:7029392"
    ],
    "tgn:id":2159352,
    "tgn:name":"Bee Canyon",
    "tgn:placetype":[
        "aat:300008761"
    ]
},
  "bbox": [],
  "geometry": {"coordinates":[-111.7167,34.9167],"type":"Point"}
}
=======
{"geometry":{"type":"Point","coordinates":[-111.716700,34.916700]},"type":"Feature","properties":{"hierarchy":["tgn:2159352","tgn:1000001","tgn:7006451","tgn:2000092","tgn:7012149","tgn:7029392"],"placetype":["aat:300008761"],"id":2159352,"name:xx":"Bee Canyon"}}
>>>>>>> 03f74aca74312dbeaf24d7e61306dd6a786dc3d0
