{
  "id": 7276705,
  "type": "Feature",
  "properties": {
    "tgn:hierarchy":[
        "tgn:7276705",
        "tgn:1001699",
        "tgn:1000049",
        "tgn:1000002",
        "tgn:7029392"
    ],
    "tgn:id":7276705,
    "tgn:name":"Villar, Monte",
    "tgn:placetype":[
        "aat:300008795"
    ]
},
  "bbox": [],
  "geometry": {"coordinates":[-72.283333,-41.45],"type":"Point"}
}