{
  "id": 1088344,
  "type": "Feature",
  "properties": {
    "tgn:hierarchy":[
        "tgn:1088344",
        "tgn:7001242",
        "tgn:1001020",
        "tgn:1000155",
        "tgn:7029392"
    ],
    "tgn:id":1088344,
    "tgn:name":"Bossangoa",
    "tgn:placetype":[
        "aat:300008347",
        "aat:300387220"
    ]
},
  "bbox": [],
  "geometry": {"coordinates":[17.35,6.45],"type":"Point"}
}