{
  "id": 2106150,
  "type": "Feature",
  "properties": {
    "tgn:hierarchy":[
        "tgn:2106150",
        "tgn:1000001",
        "tgn:7012149",
        "tgn:1002303",
        "tgn:7007826",
        "tgn:7029392"
    ],
    "tgn:id":2106150,
    "tgn:name":"Mound",
    "tgn:placetype":[
        "aat:300008347"
    ]
},
  "bbox": [],
  "geometry": {"coordinates":[-97.6333,31.35],"type":"Point"}
}