{
  "id": 2008305,
  "type": "Feature",
  "properties": {
    "tgn:hierarchy":[
        "tgn:2008305",
        "tgn:1000001",
        "tgn:7016172",
        "tgn:7012149",
        "tgn:2000136",
        "tgn:7029392"
    ],
    "tgn:id":2008305,
    "tgn:name":"Gainsboro",
    "tgn:placetype":[
        "aat:300008347",
        "aat:300387210"
    ]
},
  "bbox": [],
  "geometry": {"coordinates":[-91.5167,35.7833],"type":"Point"}
}