{
  "id": 1071662,
  "type": "Feature",
  "properties": {
    "tgn:hierarchy":[
        "tgn:1071662",
        "tgn:1000004",
        "tgn:7001838",
        "tgn:1000111",
        "tgn:7029392"
    ],
    "tgn:id":1071662,
    "tgn:name":"Shiguaigou",
    "tgn:placetype":[
        "aat:300008347"
    ]
},
  "bbox": [],
  "geometry": {"coordinates":[110.2333,40.8667],"type":"Point"}
}