{
  "id": 2671017,
  "type": "Feature",
  "properties": {
    "tgn:hierarchy":[
        "tgn:2671017",
        "tgn:1000001",
        "tgn:7012149",
        "tgn:2000812",
        "tgn:7007255",
        "tgn:7029392"
    ],
    "tgn:id":2671017,
    "tgn:name":"Smith Creek",
    "tgn:placetype":[
        "aat:300008706"
    ]
},
  "bbox": [],
  "geometry": {"coordinates":[-82.75,37.0167],"type":"Point"}
}