{
  "id": 7545456,
  "type": "Feature",
  "properties": {
    "tgn:hierarchy":[
        "tgn:7545456",
        "tgn:1000004",
        "tgn:7000198",
        "tgn:7016788",
        "tgn:7029392"
    ],
    "tgn:id":7545456,
    "tgn:name:en":"Barliya",
    "tgn:placetype":[
        "aat:300008347"
    ]
},
  "bbox": [],
  "geometry": {"coordinates":[72.834174,26.066741],"type":"Point"}
}