{
  "id": 7584751,
  "type": "Feature",
  "properties": {
    "tgn:hierarchy":[
        "tgn:7584751",
        "tgn:1000004",
        "tgn:7000198",
        "tgn:1001894",
        "tgn:7029392"
    ],
    "tgn:id":7584751,
    "tgn:name:en":"R\u016bsiya",
    "tgn:placetype":[
        "aat:300008347"
    ]
},
  "bbox": [],
  "geometry": {"coordinates":[78.016689,24.093131],"type":"Point"}
}