{
  "id": 7237206,
  "type": "Feature",
  "properties": {
    "tgn:hierarchy":[
        "tgn:7237206",
        "tgn:7002750",
        "tgn:7001399",
        "tgn:1000003",
        "tgn:1000074",
        "tgn:7029392"
    ],
    "tgn:id":7237206,
    "tgn:name":"Dri\u00e1novon",
    "tgn:placetype":[
        "aat:300008347"
    ]
},
  "bbox": [],
  "geometry": {"coordinates":[22.15,39.916667],"type":"Point"}
}