{
  "id": 4009160,
  "type": "Feature",
  "properties": {
    "tgn:hierarchy":[
        "tgn:4009160",
        "tgn:7002445",
        "tgn:1000003",
        "tgn:7008157",
        "tgn:7008591",
        "tgn:7029392"
    ],
    "tgn:id":4009160,
    "tgn:name:en":"Reedham",
    "tgn:placetype":[
        "aat:300008347"
    ]
},
  "bbox": [],
  "geometry": {"coordinates":[1.566667,52.55],"type":"Point"}
}