{
  "id": 2360045,
  "type": "Feature",
  "properties": {
    "tgn:hierarchy":[
        "tgn:2360045",
        "tgn:7013313",
        "tgn:1000001",
        "tgn:7012149",
        "tgn:7007826",
        "tgn:7029392"
    ],
    "tgn:id":2360045,
    "tgn:name":"Grass Island",
    "tgn:placetype":[
        "aat:300008791"
    ]
},
  "bbox": [],
  "geometry": {"coordinates":[-97.15,28.05],"type":"Point"}
}