{
  "id": 7559092,
  "type": "Feature",
  "properties": {
    "tgn:hierarchy":[
        "tgn:7559092",
        "tgn:1000004",
        "tgn:7000198",
        "tgn:7000799",
        "tgn:7029392"
    ],
    "tgn:id":7559092,
    "tgn:name:en":"Roang",
    "tgn:placetype":[
        "aat:300008347"
    ]
},
  "bbox": [],
  "geometry": {"coordinates":[78.140806,33.637226],"type":"Point"}
}