{
  "id": 2771952,
  "type": "Feature",
  "properties": {
    "tgn:hierarchy":[
        "tgn:2771952",
        "tgn:2001089",
        "tgn:1000001",
        "tgn:7012149",
        "tgn:7007522",
        "tgn:7029392"
    ],
    "tgn:id":2771952,
    "tgn:name":"Wilkins Branch",
    "tgn:placetype":[
        "aat:300008699"
    ]
},
  "bbox": [],
  "geometry": {"coordinates":[-89.35,32.95],"type":"Point"}
}