{
  "id": 1020292,
  "type": "Feature",
  "properties": {
    "tgn:hierarchy":[
        "tgn:1020292",
        "tgn:1000662",
        "tgn:1000046",
        "tgn:1000002",
        "tgn:7029392"
    ],
    "tgn:id":1020292,
    "tgn:name":"Coripata",
    "tgn:placetype":[
        "aat:300008347"
    ]
},
  "bbox": [],
  "geometry": {"coordinates":[-67.5333,-16.2333],"type":"Point"}
}