{
  "id": 2179295,
  "type": "Feature",
  "properties": {
    "tgn:hierarchy":[
        "tgn:2179295",
        "tgn:1000001",
        "tgn:7012149",
        "tgn:1002862",
        "tgn:7007920",
        "tgn:7029392"
    ],
    "tgn:id":2179295,
    "tgn:name":"Blakely Peak",
    "tgn:placetype":[
        "aat:300008798"
    ]
},
  "bbox": [],
  "geometry": {"coordinates":[-122.7833,48.5667],"type":"Point"}
}