{
  "id": 7530249,
  "type": "Feature",
  "properties": {
    "tgn:hierarchy":[
        "tgn:7530249",
        "tgn:7001242",
        "tgn:7016833",
        "tgn:1001083",
        "tgn:7029392"
    ],
    "tgn:id":7530249,
    "tgn:name":"Mustashf\u00e1 al \u1e28ikmah at Takha\u015f\u015fu\u015f\u012b",
    "tgn:placetype":[
        "aat:300006676"
    ]
},
  "bbox": [],
  "geometry": {"coordinates":[31.217009,30.099607],"type":"Point"}
}