{
  "id": 7547245,
  "type": "Feature",
  "properties": {
    "tgn:hierarchy":[
        "tgn:7547245",
        "tgn:1000004",
        "tgn:7000198",
        "tgn:7016788",
        "tgn:7029392"
    ],
    "tgn:id":7547245,
    "tgn:name:en":"Arthuna",
    "tgn:placetype":[
        "aat:300008347"
    ]
},
  "bbox": [],
  "geometry": {"coordinates":[74.095808,23.498258],"type":"Point"}
}