<<<<<<< HEAD
{
  "id": 7173249,
  "type": "Feature",
  "properties": {
    "tgn:hierarchy":[
        "tgn:7173249",
        "tgn:1000003",
        "tgn:7003687",
        "tgn:7000084",
        "tgn:7029392"
    ],
    "tgn:id":7173249,
    "tgn:name":"Gro\u00dfer Stemm-Berg",
    "tgn:placetype":[
        "aat:300008777"
    ]
},
  "bbox": [],
  "geometry": {"coordinates":[10.9,51.716667],"type":"Point"}
}
=======
{"geometry":{"type":"Point","coordinates":[10.900000,51.716667]},"type":"Feature","properties":{"hierarchy":["tgn:7173249","tgn:1000003","tgn:7003687","tgn:7000084","tgn:7029392"],"placetype":["aat:300008777"],"id":7173249,"name:xx":"Gro\u00dfer Stemm-Berg"}}
>>>>>>> 03f74aca74312dbeaf24d7e61306dd6a786dc3d0
