{
  "id": 7309798,
  "type": "Feature",
  "properties": {
    "tgn:hierarchy":[
        "tgn:7309798",
        "tgn:1001695",
        "tgn:1000049",
        "tgn:1000002",
        "tgn:7029392"
    ],
    "tgn:id":7309798,
    "tgn:name":"Mogote, Cerro",
    "tgn:placetype":[
        "aat:300008795"
    ]
},
  "bbox": [],
  "geometry": {"coordinates":[-71.766667,-34.466667],"type":"Point"}
}