{
  "id": 7067451,
  "type": "Feature",
  "properties": {
    "tgn:hierarchy":[
        "tgn:7067451",
        "tgn:1000003",
        "tgn:7003678",
        "tgn:7000084",
        "tgn:7029392"
    ],
    "tgn:id":7067451,
    "tgn:name":"Treisbach",
    "tgn:placetype":[
        "aat:300000206"
    ]
},
  "bbox": [],
  "geometry": {"coordinates":[8.833333,51.116667],"type":"Point"}
}