<<<<<<< HEAD
{
  "id": 2159750,
  "type": "Feature",
  "properties": {
    "tgn:hierarchy":[
        "tgn:2159750",
        "tgn:1000001",
        "tgn:2002261",
        "tgn:7012149",
        "tgn:7013961",
        "tgn:7029392"
    ],
    "tgn:id":2159750,
    "tgn:name":"Beech Bottom Branch",
    "tgn:placetype":[
        "aat:300008699"
    ]
},
  "bbox": [],
  "geometry": {"coordinates":[-81.1833,37.95],"type":"Point"}
}
=======
{"geometry":{"type":"Point","coordinates":[-81.183300,37.950000]},"type":"Feature","properties":{"hierarchy":["tgn:2159750","tgn:1000001","tgn:2002261","tgn:7012149","tgn:7013961","tgn:7029392"],"placetype":["aat:300008699"],"id":2159750,"name:xx":"Beech Bottom Branch"}}
>>>>>>> 03f74aca74312dbeaf24d7e61306dd6a786dc3d0
