<<<<<<< HEAD
{
  "id": 2252914,
  "type": "Feature",
  "properties": {
    "tgn:hierarchy":[
        "tgn:2252914",
        "tgn:1000001",
        "tgn:7012149",
        "tgn:1003042",
        "tgn:7007920",
        "tgn:7029392"
    ],
    "tgn:id":2252914,
    "tgn:name":"Conrad Glacier",
    "tgn:placetype":[
        "aat:300008835"
    ]
},
  "bbox": [],
  "geometry": {"coordinates":[-121.4,46.4833],"type":"Point"}
}
=======
{"geometry":{"type":"Point","coordinates":[-121.400000,46.483300]},"type":"Feature","properties":{"hierarchy":["tgn:2252914","tgn:1000001","tgn:7012149","tgn:1003042","tgn:7007920","tgn:7029392"],"placetype":["aat:300008835"],"id":2252914,"name:xx":"Conrad Glacier"}}
>>>>>>> 03f74aca74312dbeaf24d7e61306dd6a786dc3d0
