<<<<<<< HEAD
{
  "id": 2258132,
  "type": "Feature",
  "properties": {
    "tgn:hierarchy":[
        "tgn:2258132",
        "tgn:7006450",
        "tgn:1000001",
        "tgn:7012149",
        "tgn:2000089",
        "tgn:7029392"
    ],
    "tgn:id":2258132,
    "tgn:name":"Costa Fork",
    "tgn:placetype":[
        "aat:300008699"
    ]
},
  "bbox": [],
  "geometry": {"coordinates":[-146.1333,65.45],"type":"Point"}
}
=======
{"geometry":{"type":"Point","coordinates":[-146.133300,65.450000]},"type":"Feature","properties":{"hierarchy":["tgn:2258132","tgn:7006450","tgn:1000001","tgn:7012149","tgn:2000089","tgn:7029392"],"placetype":["aat:300008699"],"id":2258132,"name:xx":"Costa Fork"}}
>>>>>>> 03f74aca74312dbeaf24d7e61306dd6a786dc3d0
