<<<<<<< HEAD
{
  "id": 2767608,
  "type": "Feature",
  "properties": {
    "tgn:hierarchy":[
        "tgn:2767608",
        "tgn:1000001",
        "tgn:7006451",
        "tgn:2000093",
        "tgn:7012149",
        "tgn:7029392"
    ],
    "tgn:id":2767608,
    "tgn:name":"Whitebank Spring",
    "tgn:placetype":[
        "aat:300008697"
    ]
},
  "bbox": [],
  "geometry": {"coordinates":[-110.9,33.4667],"type":"Point"}
}
=======
{"geometry":{"type":"Point","coordinates":[-110.900000,33.466700]},"type":"Feature","properties":{"hierarchy":["tgn:2767608","tgn:1000001","tgn:7006451","tgn:2000093","tgn:7012149","tgn:7029392"],"placetype":["aat:300008697"],"id":2767608,"name:xx":"Whitebank Spring"}}
>>>>>>> 03f74aca74312dbeaf24d7e61306dd6a786dc3d0
