{
  "id": 2423322,
  "type": "Feature",
  "properties": {
    "tgn:hierarchy":[
        "tgn:2423322",
        "tgn:1000001",
        "tgn:7012149",
        "tgn:2001949",
        "tgn:7007826",
        "tgn:7029392"
    ],
    "tgn:id":2423322,
    "tgn:name":"Johhny Branch",
    "tgn:placetype":[
        "aat:300008699"
    ]
},
  "bbox": [],
  "geometry": {"coordinates":[-98.2667,30.8167],"type":"Point"}
}