{
  "id": 2369530,
  "type": "Feature",
  "properties": {
    "tgn:hierarchy":[
        "tgn:2369530",
        "tgn:1000001",
        "tgn:1002260",
        "tgn:7012149",
        "tgn:7007920",
        "tgn:7029392"
    ],
    "tgn:id":2369530,
    "tgn:name":"Gunn Ditch",
    "tgn:placetype":[
        "aat:300006075"
    ]
},
  "bbox": [],
  "geometry": {"coordinates":[-120.3833,47.4667],"type":"Point"}
}