<<<<<<< HEAD
{
  "id": 2337998,
  "type": "Feature",
  "properties": {
    "tgn:hierarchy":[
        "tgn:2337998",
        "tgn:7006450",
        "tgn:1000001",
        "tgn:7012149",
        "tgn:2000086",
        "tgn:7029392"
    ],
    "tgn:id":2337998,
    "tgn:name":"Fox Island",
    "tgn:placetype":[
        "aat:300008791"
    ]
},
  "bbox": [],
  "geometry": {"coordinates":[-144.6,60.1667],"type":"Point"}
}
=======
{"geometry":{"type":"Point","coordinates":[-144.600000,60.166700]},"type":"Feature","properties":{"hierarchy":["tgn:2337998","tgn:7006450","tgn:1000001","tgn:7012149","tgn:2000086","tgn:7029392"],"placetype":["aat:300008791"],"id":2337998,"name:xx":"Fox Island"}}
>>>>>>> 03f74aca74312dbeaf24d7e61306dd6a786dc3d0
