{
  "id": 7226852,
  "type": "Feature",
  "properties": {
    "tgn:hierarchy":[
        "tgn:7226852",
        "tgn:7002711",
        "tgn:7001338",
        "tgn:1000003",
        "tgn:1000074",
        "tgn:7029392"
    ],
    "tgn:id":7226852,
    "tgn:name":"Skotein\u00ed, \u00c1kra",
    "tgn:placetype":[
        "aat:300008850"
    ]
},
  "bbox": [],
  "geometry": {"coordinates":[19.577222,39.899444],"type":"Point"}
}