{
  "id": 7160472,
  "type": "Feature",
  "properties": {
    "tgn:hierarchy":[
        "tgn:7160472",
        "tgn:7003669",
        "tgn:1000003",
        "tgn:7000084",
        "tgn:7029392"
    ],
    "tgn:id":7160472,
    "tgn:name":"Hohlach",
    "tgn:placetype":[
        "aat:300008347"
    ]
},
  "bbox": [],
  "geometry": {"coordinates":[10.15,49.516667],"type":"Point"}
}