{
  "id": 7389956,
  "type": "Feature",
  "properties": {
    "tgn:hierarchy":[
        "tgn:7389956",
        "tgn:1000001",
        "tgn:7005589",
        "tgn:7005560",
        "tgn:7029392"
    ],
    "tgn:id":7389956,
    "tgn:name":"Rancho Retamitas",
    "tgn:placetype":[
        "aat:300000241"
    ]
},
  "bbox": [],
  "geometry": {"coordinates":[-99.083333,25.25],"type":"Point"}
}