{
  "id": 7483646,
  "type": "Feature",
  "properties": {
    "tgn:hierarchy":[
        "tgn:7483646",
        "tgn:1000004",
        "tgn:7489179",
        "tgn:1000141",
        "tgn:7029392"
    ],
    "tgn:id":7483646,
    "tgn:name":"Gang'ao Xikou",
    "tgn:placetype":[
        "aat:300387057"
    ]
},
  "bbox": [],
  "geometry": {"coordinates":[121.8425,24.876389],"type":"Point"}
}