<<<<<<< HEAD
{
  "id": 7483646,
  "type": "Feature",
  "properties": {
    "tgn:hierarchy":[
        "tgn:7483646",
        "tgn:1000004",
        "tgn:7489179",
        "tgn:1000141",
        "tgn:7029392"
    ],
    "tgn:id":7483646,
    "tgn:name":"Gang'ao Xikou",
    "tgn:placetype":[
        "aat:300387057"
    ]
},
  "bbox": [],
  "geometry": {"coordinates":[121.8425,24.876389],"type":"Point"}
}
=======
{"geometry":{"type":"Point","coordinates":[121.842500,24.876389]},"type":"Feature","properties":{"hierarchy":["tgn:7483646","tgn:1000004","tgn:7489179","tgn:1000141","tgn:7029392"],"placetype":["aat:300387057"],"id":7483646,"name:xx":"Gang'ao Xikou"}}
>>>>>>> 03f74aca74312dbeaf24d7e61306dd6a786dc3d0
