{
  "id": 1075322,
  "type": "Feature",
  "properties": {
    "tgn:hierarchy":[
        "tgn:1075322",
        "tgn:1000004",
        "tgn:7000198",
        "tgn:1001894",
        "tgn:7029392"
    ],
    "tgn:id":1075322,
    "tgn:name:en":"Gaurela",
    "tgn:placetype":[
        "aat:300008347"
    ]
},
  "bbox": [],
  "geometry": {"coordinates":[81.901605,22.756318],"type":"Point"}
}