<<<<<<< HEAD
{
  "id": 2334967,
  "type": "Feature",
  "properties": {
    "tgn:hierarchy":[
        "tgn:2334967",
        "tgn:1000001",
        "tgn:7012149",
        "tgn:2001843",
        "tgn:7007825",
        "tgn:7029392"
    ],
    "tgn:id":2334967,
    "tgn:name":"Forkvale",
    "tgn:placetype":[
        "aat:300008347"
    ]
},
  "bbox": [],
  "geometry": {"coordinates":[-83.9667,36.3],"type":"Point"}
}
=======
{"geometry":{"type":"Point","coordinates":[-83.966700,36.300000]},"type":"Feature","properties":{"hierarchy":["tgn:2334967","tgn:1000001","tgn:7012149","tgn:2001843","tgn:7007825","tgn:7029392"],"placetype":["aat:300008347"],"id":2334967,"name:xx":"Forkvale"}}
>>>>>>> 03f74aca74312dbeaf24d7e61306dd6a786dc3d0
