{
  "id": 2768790,
  "type": "Feature",
  "properties": {
    "tgn:hierarchy":[
        "tgn:2768790",
        "tgn:1000001",
        "tgn:7012149",
        "tgn:1002865",
        "tgn:7007706",
        "tgn:7029392"
    ],
    "tgn:id":2768790,
    "tgn:name":"Whitmore",
    "tgn:placetype":[
        "aat:300008347"
    ]
},
  "bbox": [],
  "geometry": {"coordinates":[-82.8833,41.3833],"type":"Point"}
}