{
  "id": 2173198,
  "type": "Feature",
  "properties": {
    "tgn:hierarchy":[
        "tgn:2173198",
        "tgn:1000001",
        "tgn:7012149",
        "tgn:1002569",
        "tgn:7007252",
        "tgn:7029392"
    ],
    "tgn:id":2173198,
    "tgn:name":"Bingo Lake",
    "tgn:placetype":[
        "aat:300008680"
    ]
},
  "bbox": [],
  "geometry": {"coordinates":[-87.4667,41.45],"type":"Point"}
}