{
  "id": 2173039,
  "type": "Feature",
  "properties": {
    "tgn:hierarchy":[
        "tgn:2173039",
        "tgn:1000001",
        "tgn:7012149",
        "tgn:2000975",
        "tgn:7007520",
        "tgn:7029392"
    ],
    "tgn:id":2173039,
    "tgn:name":"Bilsky Lake",
    "tgn:placetype":[
        "aat:300008680"
    ]
},
  "bbox": [],
  "geometry": {"coordinates":[-87.4667,46.2333],"type":"Point"}
}