{
  "id": 2146248,
  "type": "Feature",
  "properties": {
    "tgn:hierarchy":[
        "tgn:2146248",
        "tgn:1000001",
        "tgn:7012149",
        "tgn:1002899",
        "tgn:7007920",
        "tgn:7029392"
    ],
    "tgn:id":2146248,
    "tgn:name":"Ballinger, Lake",
    "tgn:placetype":[
        "aat:300006191"
    ]
},
  "bbox": [],
  "geometry": {"coordinates":[-122.3167,47.7667],"type":"Point"}
}