<<<<<<< HEAD
{
  "id": 2401356,
  "type": "Feature",
  "properties": {
    "tgn:hierarchy":[
        "tgn:2401356",
        "tgn:1000001",
        "tgn:7012149",
        "tgn:2002156",
        "tgn:7007919",
        "tgn:7029392"
    ],
    "tgn:id":2401356,
    "tgn:name":"Horsepen Creek",
    "tgn:placetype":[
        "aat:300008706"
    ]
},
  "bbox": [],
  "geometry": {"coordinates":[-78.3,37.3833],"type":"Point"}
}
=======
{"geometry":{"type":"Point","coordinates":[-78.300000,37.383300]},"type":"Feature","properties":{"hierarchy":["tgn:2401356","tgn:1000001","tgn:7012149","tgn:2002156","tgn:7007919","tgn:7029392"],"placetype":["aat:300008706"],"id":2401356,"name:xx":"Horsepen Creek"}}
>>>>>>> 03f74aca74312dbeaf24d7e61306dd6a786dc3d0
