{
  "id": 7374676,
  "type": "Feature",
  "properties": {
    "tgn:hierarchy":[
        "tgn:7374676",
        "tgn:1000001",
        "tgn:7005589",
        "tgn:7005560",
        "tgn:7029392"
    ],
    "tgn:id":7374676,
    "tgn:name":"La Mesa de los Chivos",
    "tgn:placetype":[
        "aat:300008811"
    ]
},
  "bbox": [],
  "geometry": {"coordinates":[-100.916667,26.216667],"type":"Point"}
}