<<<<<<< HEAD
{
  "id": 7374676,
  "type": "Feature",
  "properties": {
    "tgn:hierarchy":[
        "tgn:7374676",
        "tgn:1000001",
        "tgn:7005589",
        "tgn:7005560",
        "tgn:7029392"
    ],
    "tgn:id":7374676,
    "tgn:name":"La Mesa de los Chivos",
    "tgn:placetype":[
        "aat:300008811"
    ]
},
  "bbox": [],
  "geometry": {"coordinates":[-100.916667,26.216667],"type":"Point"}
}
=======
{"geometry":{"type":"Point","coordinates":[-100.916667,26.216667]},"type":"Feature","properties":{"hierarchy":["tgn:7374676","tgn:1000001","tgn:7005589","tgn:7005560","tgn:7029392"],"placetype":["aat:300008811"],"id":7374676,"name:xx":"La Mesa de los Chivos"}}
>>>>>>> 03f74aca74312dbeaf24d7e61306dd6a786dc3d0
