{
  "id": 2077093,
  "type": "Feature",
  "properties": {
    "tgn:hierarchy":[
        "tgn:2077093",
        "tgn:1000001",
        "tgn:7012149",
        "tgn:2001491",
        "tgn:7007709",
        "tgn:7029392"
    ],
    "tgn:id":2077093,
    "tgn:name":"Warsaw",
    "tgn:placetype":[
        "aat:300008347"
    ]
},
  "bbox": [],
  "geometry": {"coordinates":[-78.0833,34.9833],"type":"Point"}
}