{
  "id": 7473905,
  "type": "Feature",
  "properties": {
    "tgn:hierarchy":[
        "tgn:7473905",
        "tgn:1000004",
        "tgn:1000454",
        "tgn:1000141",
        "tgn:7029392"
    ],
    "tgn:id":7473905,
    "tgn:name":"Diqi Gongmu",
    "tgn:placetype":[
        "aat:300266755"
    ]
},
  "bbox": [],
  "geometry": {"coordinates":[121.538247,24.928308],"type":"Point"}
}