<<<<<<< HEAD
{
  "id": 7473905,
  "type": "Feature",
  "properties": {
    "tgn:hierarchy":[
        "tgn:7473905",
        "tgn:1000004",
        "tgn:1000454",
        "tgn:1000141",
        "tgn:7029392"
    ],
    "tgn:id":7473905,
    "tgn:name":"Diqi Gongmu",
    "tgn:placetype":[
        "aat:300266755"
    ]
},
  "bbox": [],
  "geometry": {"coordinates":[121.538247,24.928308],"type":"Point"}
}
=======
{"geometry":{"type":"Point","coordinates":[121.538247,24.928308]},"type":"Feature","properties":{"hierarchy":["tgn:7473905","tgn:1000004","tgn:1000454","tgn:1000141","tgn:7029392"],"placetype":["aat:300266755"],"id":7473905,"name:xx":"Diqi Gongmu"}}
>>>>>>> 03f74aca74312dbeaf24d7e61306dd6a786dc3d0
