{
  "id": 2663186,
  "type": "Feature",
  "properties": {
    "tgn:hierarchy":[
        "tgn:2663186",
        "tgn:1000001",
        "tgn:7012149",
        "tgn:2000281",
        "tgn:7007240",
        "tgn:7029392"
    ],
    "tgn:id":2663186,
    "tgn:name":"Silver Creek",
    "tgn:placetype":[
        "aat:300008706"
    ]
},
  "bbox": [],
  "geometry": {"coordinates":[-86.5167,30.65],"type":"Point"}
}