{
  "id": 2373768,
  "type": "Feature",
  "properties": {
    "tgn:hierarchy":[
        "tgn:2373768",
        "tgn:1000001",
        "tgn:7012149",
        "tgn:7007157",
        "tgn:2000184",
        "tgn:7029392"
    ],
    "tgn:id":2373768,
    "tgn:name":"Hamilton Mountain",
    "tgn:placetype":[
        "aat:300008798"
    ]
},
  "bbox": [],
  "geometry": {"coordinates":[-120.85,40.3167],"type":"Point"}
}