{
  "id": 7521797,
  "type": "Feature",
  "properties": {
    "tgn:hierarchy":[
        "tgn:7521797",
        "tgn:7001242",
        "tgn:7016833",
        "tgn:7000122",
        "tgn:7029392"
    ],
    "tgn:id":7521797,
    "tgn:name:en":"Al Ba\u015fal\u012byah Ba\u1e29r\u012b",
    "tgn:placetype":[
        "aat:300008347"
    ]
},
  "bbox": [],
  "geometry": {"coordinates":[32.716667,25.15],"type":"Point"}
}