<<<<<<< HEAD
{
  "id": 7379578,
  "type": "Feature",
  "properties": {
    "tgn:hierarchy":[
        "tgn:7379578",
        "tgn:1000001",
        "tgn:7005589",
        "tgn:7005560",
        "tgn:7029392"
    ],
    "tgn:id":7379578,
    "tgn:name":"Milpa",
    "tgn:placetype":[
        "aat:300008347"
    ]
},
  "bbox": [],
  "geometry": {"coordinates":[-99.833333,25.683333],"type":"Point"}
}
=======
{"geometry":{"type":"Point","coordinates":[-99.833333,25.683333]},"type":"Feature","properties":{"hierarchy":["tgn:7379578","tgn:1000001","tgn:7005589","tgn:7005560","tgn:7029392"],"placetype":["aat:300008347"],"id":7379578,"name:xx":"Milpa"}}
>>>>>>> 03f74aca74312dbeaf24d7e61306dd6a786dc3d0
