{
  "id": 7168890,
  "type": "Feature",
  "properties": {
    "tgn:hierarchy":[
        "tgn:7168890",
        "tgn:1000003",
        "tgn:7003677",
        "tgn:7000084",
        "tgn:7029392"
    ],
    "tgn:id":7168890,
    "tgn:name":"Heidschott",
    "tgn:placetype":[
        "aat:300000206"
    ]
},
  "bbox": [],
  "geometry": {"coordinates":[8.05,51.066667],"type":"Point"}
}