{
  "id": 7304351,
  "type": "Feature",
  "properties": {
    "tgn:hierarchy":[
        "tgn:7304351",
        "tgn:7002820",
        "tgn:7030216",
        "tgn:1000003",
        "tgn:1000095",
        "tgn:7029392"
    ],
    "tgn:id":7304351,
    "tgn:name":"Lladra, Roca",
    "tgn:placetype":[
        "aat:300008798"
    ]
},
  "bbox": [],
  "geometry": {"coordinates":[2.498572,42.136474],"type":"Point"}
}