{
  "id": 7071360,
  "type": "Feature",
  "properties": {
    "tgn:hierarchy":[
        "tgn:7071360",
        "tgn:1000003",
        "tgn:7003688",
        "tgn:7000084",
        "tgn:7029392"
    ],
    "tgn:id":7071360,
    "tgn:name":"Sush\u00f6rn",
    "tgn:placetype":[
        "aat:300000206"
    ]
},
  "bbox": [],
  "geometry": {"coordinates":[9.466667,53.766667],"type":"Point"}
}