{
  "id": 2338017,
  "type": "Feature",
  "properties": {
    "tgn:hierarchy":[
        "tgn:2338017",
        "tgn:1002996",
        "tgn:1000001",
        "tgn:7012149",
        "tgn:7007711",
        "tgn:7029392"
    ],
    "tgn:id":2338017,
    "tgn:name":"Fox Island",
    "tgn:placetype":[
        "aat:300008791"
    ]
},
  "bbox": [],
  "geometry": {"coordinates":[-71.4167,41.55],"type":"Point"}
}