<<<<<<< HEAD
{
  "id": 2338017,
  "type": "Feature",
  "properties": {
    "tgn:hierarchy":[
        "tgn:2338017",
        "tgn:1002996",
        "tgn:1000001",
        "tgn:7012149",
        "tgn:7007711",
        "tgn:7029392"
    ],
    "tgn:id":2338017,
    "tgn:name":"Fox Island",
    "tgn:placetype":[
        "aat:300008791"
    ]
},
  "bbox": [],
  "geometry": {"coordinates":[-71.4167,41.55],"type":"Point"}
}
=======
{"geometry":{"type":"Point","coordinates":[-71.416700,41.550000]},"type":"Feature","properties":{"hierarchy":["tgn:2338017","tgn:1002996","tgn:1000001","tgn:7012149","tgn:7007711","tgn:7029392"],"placetype":["aat:300008791"],"id":2338017,"name:xx":"Fox Island"}}
>>>>>>> 03f74aca74312dbeaf24d7e61306dd6a786dc3d0
