{
  "id": 2275867,
  "type": "Feature",
  "properties": {
    "tgn:hierarchy":[
        "tgn:2275867",
        "tgn:1000001",
        "tgn:7012149",
        "tgn:2002195",
        "tgn:7007919",
        "tgn:7029392"
    ],
    "tgn:id":2275867,
    "tgn:name":"Dark Hollow",
    "tgn:placetype":[
        "aat:300008761"
    ]
},
  "bbox": [],
  "geometry": {"coordinates":[-82.75,36.8833],"type":"Point"}
}