{
  "id": 2358776,
  "type": "Feature",
  "properties": {
    "tgn:hierarchy":[
        "tgn:2358776",
        "tgn:1000001",
        "tgn:7012149",
        "tgn:2001516",
        "tgn:7007709",
        "tgn:7029392"
    ],
    "tgn:id":2358776,
    "tgn:name":"Granger Mountain",
    "tgn:placetype":[
        "aat:300008798"
    ]
},
  "bbox": [],
  "geometry": {"coordinates":[-82.85,35.75],"type":"Point"}
}