{
  "id": 1087463,
  "type": "Feature",
  "properties": {
    "tgn:hierarchy":[
        "tgn:1087463",
        "tgn:7001242",
        "tgn:7016752",
        "tgn:7000350",
        "tgn:7029392"
    ],
    "tgn:id":1087463,
    "tgn:name":"Grarem",
    "tgn:placetype":[
        "aat:300008347"
    ]
},
  "bbox": [],
  "geometry": {"coordinates":[6.3167,36.5167],"type":"Point"}
}