{
  "id": 7574854,
  "type": "Feature",
  "properties": {
    "tgn:hierarchy":[
        "tgn:7574854",
        "tgn:1000004",
        "tgn:1001869",
        "tgn:7000198",
        "tgn:7029392"
    ],
    "tgn:id":7574854,
    "tgn:name:en":"Kau",
    "tgn:placetype":[
        "aat:300008347"
    ]
},
  "bbox": [],
  "geometry": {"coordinates":[73.318861,23.383086],"type":"Point"}
}