{
  "id": 1030384,
  "type": "Feature",
  "properties": {
    "tgn:hierarchy":[
        "tgn:1030384",
        "tgn:7002445",
        "tgn:1000003",
        "tgn:7008153",
        "tgn:1009131",
        "tgn:7008591",
        "tgn:7029392"
    ],
    "tgn:id":1030384,
    "tgn:name:en":"Queenborough",
    "tgn:placetype":[
        "aat:300008347"
    ]
},
  "bbox": [],
  "geometry": {"coordinates":[0.766667,51.416667],"type":"Point"}
}