{
  "id": 2314189,
  "type": "Feature",
  "properties": {
    "tgn:hierarchy":[
        "tgn:2314189",
        "tgn:1000001",
        "tgn:7012149",
        "tgn:1002763",
        "tgn:7007255",
        "tgn:7029392"
    ],
    "tgn:id":2314189,
    "tgn:name":"Elk Creek",
    "tgn:placetype":[
        "aat:300008706"
    ]
},
  "bbox": [],
  "geometry": {"coordinates":[-84.7667,38.45],"type":"Point"}
}