{
  "id": 2285162,
  "type": "Feature",
  "properties": {
    "tgn:hierarchy":[
        "tgn:2285162",
        "tgn:1000001",
        "tgn:2001817",
        "tgn:7012149",
        "tgn:7007713",
        "tgn:7029392"
    ],
    "tgn:id":2285162,
    "tgn:name":"Devils Backbone, The",
    "tgn:placetype":[
        "aat:300266640"
    ]
},
  "bbox": [],
  "geometry": {"coordinates":[-101.1167,43.5333],"type":"Point"}
}