{
  "id": 7093195,
  "type": "Feature",
  "properties": {
    "tgn:hierarchy":[
        "tgn:7093195",
        "tgn:1000003",
        "tgn:7003689",
        "tgn:7000084",
        "tgn:7029392"
    ],
    "tgn:id":7093195,
    "tgn:name":"Schweinitz",
    "tgn:placetype":[
        "aat:300008347"
    ]
},
  "bbox": [],
  "geometry": {"coordinates":[11.616667,50.716667],"type":"Point"}
}