{
  "id": 2535502,
  "type": "Feature",
  "properties": {
    "tgn:hierarchy":[
        "tgn:2535502",
        "tgn:2319304",
        "tgn:1000001",
        "tgn:1002705",
        "tgn:7012149",
        "tgn:7007517",
        "tgn:7029392"
    ],
    "tgn:id":2535502,
    "tgn:name":"Narrow Creek Pond",
    "tgn:placetype":[
        "aat:300008680",
        "aat:300185707"
    ]
},
  "bbox": [],
  "geometry": {"coordinates":[-70.2167,41.2667],"type":"Point"}
}