{
  "id": 2184774,
  "type": "Feature",
  "properties": {
    "tgn:hierarchy":[
        "tgn:2184774",
        "tgn:2000919",
        "tgn:1000001",
        "tgn:7012149",
        "tgn:7007515",
        "tgn:7029392"
    ],
    "tgn:id":2184774,
    "tgn:name":"Bog Brook",
    "tgn:placetype":[
        "aat:300008699"
    ]
},
  "bbox": [],
  "geometry": {"coordinates":[-68.3667,46.0667],"type":"Point"}
}