{
  "id": 2063163,
  "type": "Feature",
  "properties": {
    "tgn:hierarchy":[
        "tgn:2063163",
        "tgn:1000001",
        "tgn:2001419",
        "tgn:7012149",
        "tgn:7007526",
        "tgn:7029392"
    ],
    "tgn:id":2063163,
    "tgn:name":"Toy",
    "tgn:placetype":[
        "aat:300387016"
    ]
},
  "bbox": [],
  "geometry": {"coordinates":[-118.6667,40.0167],"type":"Point"}
}