{
  "id": 2033845,
  "type": "Feature",
  "properties": {
    "tgn:hierarchy":[
        "tgn:2033845",
        "tgn:1000001",
        "tgn:7012149",
        "tgn:2000549",
        "tgn:7007252",
        "tgn:7029392"
    ],
    "tgn:id":2033845,
    "tgn:name":"Sylvania",
    "tgn:placetype":[
        "aat:300008347"
    ]
},
  "bbox": [],
  "geometry": {"coordinates":[-87.2833,39.9167],"type":"Point"}
}