{
  "id": 7193220,
  "type": "Feature",
  "properties": {
    "tgn:hierarchy":[
        "tgn:7193220",
        "tgn:1000003",
        "tgn:7003676",
        "tgn:7000084",
        "tgn:7029392"
    ],
    "tgn:id":7193220,
    "tgn:name":"Fahnstermoor",
    "tgn:placetype":[
        "aat:300008347"
    ]
},
  "bbox": [],
  "geometry": {"coordinates":[7.433333,53.433333],"type":"Point"}
}