{
  "id": 2745821,
  "type": "Feature",
  "properties": {
    "tgn:hierarchy":[
        "tgn:2745821",
        "tgn:1000001",
        "tgn:7012149",
        "tgn:7007157",
        "tgn:1002859",
        "tgn:7029392"
    ],
    "tgn:id":2745821,
    "tgn:name":"Vista Del Monte",
    "tgn:placetype":[
        "aat:300008347"
    ]
},
  "bbox": [],
  "geometry": {"coordinates":[-122.4333,37.7333],"type":"Point"}
}