<<<<<<< HEAD
{
  "id": 7173184,
  "type": "Feature",
  "properties": {
    "tgn:hierarchy":[
        "tgn:7173184",
        "tgn:1000003",
        "tgn:7003685",
        "tgn:7000084",
        "tgn:7029392"
    ],
    "tgn:id":7173184,
    "tgn:name":"Gro\u00dfr\u00fcckerswalde, Forst",
    "tgn:placetype":[
        "aat:300008863"
    ]
},
  "bbox": [],
  "geometry": {"coordinates":[13.15,50.583333],"type":"Point"}
}
=======
{"geometry":{"type":"Point","coordinates":[13.150000,50.583333]},"type":"Feature","properties":{"hierarchy":["tgn:7173184","tgn:1000003","tgn:7003685","tgn:7000084","tgn:7029392"],"placetype":["aat:300008863"],"id":7173184,"name:xx":"Gro\u00dfr\u00fcckerswalde, Forst"}}
>>>>>>> 03f74aca74312dbeaf24d7e61306dd6a786dc3d0
