{
  "id": 7098812,
  "type": "Feature",
  "properties": {
    "tgn:hierarchy":[
        "tgn:7098812",
        "tgn:7003669",
        "tgn:1000003",
        "tgn:7000084",
        "tgn:7029392"
    ],
    "tgn:id":7098812,
    "tgn:name":"Spitzberg",
    "tgn:placetype":[
        "aat:300008777"
    ]
},
  "bbox": [],
  "geometry": {"coordinates":[11.316667,50.333333],"type":"Point"}
}