{
  "id": 2478207,
  "type": "Feature",
  "properties": {
    "tgn:hierarchy":[
        "tgn:2478207",
        "tgn:1000001",
        "tgn:7016172",
        "tgn:2000109",
        "tgn:7012149",
        "tgn:7029392"
    ],
    "tgn:id":2478207,
    "tgn:name":"Mackey Hollow",
    "tgn:placetype":[
        "aat:300008761"
    ]
},
  "bbox": [],
  "geometry": {"coordinates":[-92.9167,36.3167],"type":"Point"}
}