{
  "id": 2466701,
  "type": "Feature",
  "properties": {
    "tgn:hierarchy":[
        "tgn:2466701",
        "tgn:1000001",
        "tgn:7012149",
        "tgn:2001906",
        "tgn:7007825",
        "tgn:7029392"
    ],
    "tgn:id":2466701,
    "tgn:name":"Long Branch",
    "tgn:placetype":[
        "aat:300008699"
    ]
},
  "bbox": [],
  "geometry": {"coordinates":[-84.5333,35.15],"type":"Point"}
}