{
  "id": 2286617,
  "type": "Feature",
  "properties": {
    "tgn:hierarchy":[
        "tgn:2286617",
        "tgn:1000001",
        "tgn:7012149",
        "tgn:2001274",
        "tgn:7007524",
        "tgn:7029392"
    ],
    "tgn:id":2286617,
    "tgn:name":"Diamond Lake",
    "tgn:placetype":[
        "aat:300008680"
    ]
},
  "bbox": [],
  "geometry": {"coordinates":[-113.15,47.6167],"type":"Point"}
}