{
  "id": 2352774,
  "type": "Feature",
  "properties": {
    "tgn:hierarchy":[
        "tgn:2352774",
        "tgn:1000001",
        "tgn:7012149",
        "tgn:2001843",
        "tgn:7007825",
        "tgn:7029392"
    ],
    "tgn:id":2352774,
    "tgn:name":"Gobbler Knob",
    "tgn:placetype":[
        "aat:300008798"
    ]
},
  "bbox": [],
  "geometry": {"coordinates":[-84.3167,36.4333],"type":"Point"}
}