{
  "id": 7521210,
  "type": "Feature",
  "properties": {
    "tgn:hierarchy":[
        "tgn:7521210",
        "tgn:7001242",
        "tgn:7016833",
        "tgn:7001336",
        "tgn:7029392"
    ],
    "tgn:id":7521210,
    "tgn:name:en":"Abudli, Gebel",
    "tgn:placetype":[
        "aat:300008795"
    ]
},
  "bbox": [],
  "geometry": {"coordinates":[34.019753,28.683546],"type":"Point"}
}