{
  "id": 2362768,
  "type": "Feature",
  "properties": {
    "tgn:hierarchy":[
        "tgn:2362768",
        "tgn:2000946",
        "tgn:1000001",
        "tgn:7012149",
        "tgn:7007520",
        "tgn:7029392"
    ],
    "tgn:id":2362768,
    "tgn:name":"Great Lakes Marina",
    "tgn:placetype":[
        "aat:300008678"
    ]
},
  "bbox": [],
  "geometry": {"coordinates":[-83.8667,43.95],"type":"Point"}
}