{
  "id": 7056049,
  "type": "Feature",
  "properties": {
    "tgn:hierarchy":[
        "tgn:7056049",
        "tgn:1003444",
        "tgn:1000003",
        "tgn:7003241",
        "tgn:1000080",
        "tgn:7029392"
    ],
    "tgn:id":7056049,
    "tgn:name":"Micheluccio, Colle",
    "tgn:placetype":[
        "aat:300008795"
    ]
},
  "bbox": [],
  "geometry": {"coordinates":[14.633333,41.816667],"type":"Point"}
}