<<<<<<< HEAD
{
  "id": 7374889,
  "type": "Feature",
  "properties": {
    "tgn:hierarchy":[
        "tgn:7374889",
        "tgn:1000001",
        "tgn:7005601",
        "tgn:7005560",
        "tgn:7029392"
    ],
    "tgn:id":7374889,
    "tgn:name":"La Herradura",
    "tgn:placetype":[
        "aat:300008347"
    ]
},
  "bbox": [],
  "geometry": {"coordinates":[-102.3,24.683333],"type":"Point"}
}
=======
{"geometry":{"type":"Point","coordinates":[-102.300000,24.683333]},"type":"Feature","properties":{"hierarchy":["tgn:7374889","tgn:1000001","tgn:7005601","tgn:7005560","tgn:7029392"],"placetype":["aat:300008347"],"id":7374889,"name:xx":"La Herradura"}}
>>>>>>> 03f74aca74312dbeaf24d7e61306dd6a786dc3d0
