{
  "id": 2435956,
  "type": "Feature",
  "properties": {
    "tgn:hierarchy":[
        "tgn:2435956",
        "tgn:7013313",
        "tgn:1000001",
        "tgn:7012149",
        "tgn:7007826",
        "tgn:7029392"
    ],
    "tgn:id":2435956,
    "tgn:name":"Key Allegro",
    "tgn:placetype":[
        "aat:300008791"
    ]
},
  "bbox": [],
  "geometry": {"coordinates":[-97.0167,28.0333],"type":"Point"}
}