{
  "id": 2501658,
  "type": "Feature",
  "properties": {
    "tgn:hierarchy":[
        "tgn:2501658",
        "tgn:1000001",
        "tgn:7012149",
        "tgn:1002617",
        "tgn:7007520",
        "tgn:7029392"
    ],
    "tgn:id":2501658,
    "tgn:name":"McInerney Drain",
    "tgn:placetype":[
        "aat:300008699"
    ]
},
  "bbox": [],
  "geometry": {"coordinates":[-82.9833,42.55],"type":"Point"}
}