{
  "id": 7585981,
  "type": "Feature",
  "properties": {
    "tgn:hierarchy":[
        "tgn:7585981",
        "tgn:1000004",
        "tgn:7000198",
        "tgn:7000799",
        "tgn:7029392"
    ],
    "tgn:id":7585981,
    "tgn:name:en":"Bihinpur",
    "tgn:placetype":[
        "aat:300008347"
    ]
},
  "bbox": [],
  "geometry": {"coordinates":[74.142771,34.408833],"type":"Point"}
}