{
  "id": 1009679,
  "type": "Feature",
  "properties": {
    "tgn:hierarchy":[
        "tgn:1009679",
        "tgn:1000003",
        "tgn:7003635",
        "tgn:7016845",
        "tgn:7029392"
    ],
    "tgn:id":1009679,
    "tgn:name":"Walcheren",
    "tgn:placetype":[
        "aat:300008791"
    ]
},
  "bbox": [],
  "geometry": {"coordinates":[3.5833,51.55],"type":"Point"}
}