{
  "id": 2124569,
  "type": "Feature",
  "properties": {
    "tgn:hierarchy":[
        "tgn:2124569",
        "tgn:1000001",
        "tgn:7012149",
        "tgn:1002999",
        "tgn:7007526",
        "tgn:7029392"
    ],
    "tgn:id":2124569,
    "tgn:name":"Abbie, Mount",
    "tgn:placetype":[
        "aat:300008798"
    ]
},
  "bbox": [],
  "geometry": {"coordinates":[-119.6667,39.3167],"type":"Point"}
}