<<<<<<< HEAD
{
  "id": 7473227,
  "type": "Feature",
  "properties": {
    "tgn:hierarchy":[
        "tgn:7473227",
        "tgn:7001010",
        "tgn:1000004",
        "tgn:1000141",
        "tgn:7029392"
    ],
    "tgn:id":7473227,
    "tgn:name":"Yangming Suidao",
    "tgn:placetype":[
        "aat:300007899"
    ]
},
  "bbox": [],
  "geometry": {"coordinates":[121.416944,24.193889],"type":"Point"}
}
=======
{"geometry":{"type":"Point","coordinates":[121.416944,24.193889]},"type":"Feature","properties":{"hierarchy":["tgn:7473227","tgn:7001010","tgn:1000004","tgn:1000141","tgn:7029392"],"placetype":["aat:300007899"],"id":7473227,"name:xx":"Yangming Suidao"}}
>>>>>>> 03f74aca74312dbeaf24d7e61306dd6a786dc3d0
