{
  "id": 7489533,
  "type": "Feature",
  "properties": {
    "tgn:hierarchy":[
        "tgn:7489533",
        "tgn:1000004",
        "tgn:7490934",
        "tgn:1000141",
        "tgn:7029392"
    ],
    "tgn:id":7489533,
    "tgn:name":"Yancheng",
    "tgn:placetype":[
        "aat:300000745"
    ]
},
  "bbox": [],
  "geometry": {"coordinates":[120.193056,22.973056],"type":"Point"}
}