<<<<<<< HEAD
{
  "id": 7489533,
  "type": "Feature",
  "properties": {
    "tgn:hierarchy":[
        "tgn:7489533",
        "tgn:1000004",
        "tgn:7490934",
        "tgn:1000141",
        "tgn:7029392"
    ],
    "tgn:id":7489533,
    "tgn:name":"Yancheng",
    "tgn:placetype":[
        "aat:300000745"
    ]
},
  "bbox": [],
  "geometry": {"coordinates":[120.193056,22.973056],"type":"Point"}
}
=======
{"geometry":{"type":"Point","coordinates":[120.193056,22.973056]},"type":"Feature","properties":{"hierarchy":["tgn:7489533","tgn:1000004","tgn:7490934","tgn:1000141","tgn:7029392"],"placetype":["aat:300000745"],"id":7489533,"name:xx":"Yancheng"}}
>>>>>>> 03f74aca74312dbeaf24d7e61306dd6a786dc3d0
