{
  "id": 7546363,
  "type": "Feature",
  "properties": {
    "tgn:hierarchy":[
        "tgn:7546363",
        "tgn:1001828",
        "tgn:1000004",
        "tgn:7000198",
        "tgn:7029392"
    ],
    "tgn:id":7546363,
    "tgn:name:en":"B\u0101vanap\u0101du",
    "tgn:placetype":[
        "aat:300008347"
    ]
},
  "bbox": [],
  "geometry": {"coordinates":[84.35,18.566667],"type":"Point"}
}