{
  "id": 2360675,
  "type": "Feature",
  "properties": {
    "tgn:hierarchy":[
        "tgn:2360675",
        "tgn:7006450",
        "tgn:1000001",
        "tgn:7012149",
        "tgn:2000088",
        "tgn:7029392"
    ],
    "tgn:id":2360675,
    "tgn:name":"Grassy Island",
    "tgn:placetype":[
        "aat:300008791"
    ]
},
  "bbox": [],
  "geometry": {"coordinates":[-132.55,56.6833],"type":"Point"}
}