<<<<<<< HEAD
{
  "id": 2407442,
  "type": "Feature",
  "properties": {
    "tgn:hierarchy":[
        "tgn:2407442",
        "tgn:1000001",
        "tgn:7012149",
        "tgn:7014318",
        "tgn:7007568",
        "tgn:7029392"
    ],
    "tgn:id":2407442,
    "tgn:name":"Huntly Corners",
    "tgn:placetype":[
        "aat:300008347"
    ]
},
  "bbox": [],
  "geometry": {"coordinates":[-75.1333,42.8167],"type":"Point"}
}
=======
{"geometry":{"type":"Point","coordinates":[-75.133300,42.816700]},"type":"Feature","properties":{"hierarchy":["tgn:2407442","tgn:1000001","tgn:7012149","tgn:7014318","tgn:7007568","tgn:7029392"],"placetype":["aat:300008347"],"id":2407442,"name:xx":"Huntly Corners"}}
>>>>>>> 03f74aca74312dbeaf24d7e61306dd6a786dc3d0
