{
  "id": 2755373,
  "type": "Feature",
  "properties": {
    "tgn:hierarchy":[
        "tgn:2755373",
        "tgn:1000001",
        "tgn:7012149",
        "tgn:1002358",
        "tgn:7007710",
        "tgn:7029392"
    ],
    "tgn:id":2755373,
    "tgn:name":"Weber Hills",
    "tgn:placetype":[
        "aat:300008347"
    ]
},
  "bbox": [],
  "geometry": {"coordinates":[-80.05,42.0667],"type":"Point"}
}