{
  "id": 7085671,
  "type": "Feature",
  "properties": {
    "tgn:hierarchy":[
        "tgn:7085671",
        "tgn:1000003",
        "tgn:7003676",
        "tgn:7000084",
        "tgn:7029392"
    ],
    "tgn:id":7085671,
    "tgn:name":"Waddensersiel",
    "tgn:placetype":[
        "aat:300008347"
    ]
},
  "bbox": [],
  "geometry": {"coordinates":[8.45,53.566667],"type":"Point"}
}