{
  "id": 2693175,
  "type": "Feature",
  "properties": {
    "tgn:hierarchy":[
        "tgn:2693175",
        "tgn:1000001",
        "tgn:2001429",
        "tgn:7012149",
        "tgn:7007566",
        "tgn:7029392"
    ],
    "tgn:id":2693175,
    "tgn:name":"Steeple U Tank",
    "tgn:placetype":[
        "aat:300006191"
    ]
},
  "bbox": [],
  "geometry": {"coordinates":[-108.0667,33.3667],"type":"Point"}
}