{
  "id": 7541191,
  "type": "Feature",
  "properties": {
    "tgn:hierarchy":[
        "tgn:7541191",
        "tgn:7001242",
        "tgn:7016833",
        "tgn:7001336",
        "tgn:7029392"
    ],
    "tgn:id":7541191,
    "tgn:name:en":"Marwa, W\u0101d\u012b",
    "tgn:placetype":[
        "aat:300379998"
    ]
},
  "bbox": [],
  "geometry": {"coordinates":[34.120929,28.290259],"type":"Point"}
}