{
  "id": 7098811,
  "type": "Feature",
  "properties": {
    "tgn:hierarchy":[
        "tgn:7098811",
        "tgn:7003669",
        "tgn:1000003",
        "tgn:7000084",
        "tgn:7029392"
    ],
    "tgn:id":7098811,
    "tgn:name":"Spitz-Berg",
    "tgn:placetype":[
        "aat:300008777"
    ]
},
  "bbox": [],
  "geometry": {"coordinates":[11.65,50.333333],"type":"Point"}
}