{
  "id": 7584066,
  "type": "Feature",
  "properties": {
    "tgn:hierarchy":[
        "tgn:7584066",
        "tgn:1000004",
        "tgn:7000198",
        "tgn:7016883",
        "tgn:7029392"
    ],
    "tgn:id":7584066,
    "tgn:name:en":"T\u0101jalpur",
    "tgn:placetype":[
        "aat:300008347"
    ]
},
  "bbox": [],
  "geometry": {"coordinates":[76.596711,30.226233],"type":"Point"}
}