{
  "id": 7501899,
  "type": "Feature",
  "properties": {
    "tgn:hierarchy":[
        "tgn:7501899",
        "tgn:7488858",
        "tgn:1000004",
        "tgn:1000141",
        "tgn:7029392"
    ],
    "tgn:id":7501899,
    "tgn:name":"Xinfeng Qiao",
    "tgn:placetype":[
        "aat:300007836"
    ]
},
  "bbox": [],
  "geometry": {"coordinates":[120.933696,24.061824],"type":"Point"}
}