{
  "id": 1072331,
  "type": "Feature",
  "properties": {
    "tgn:hierarchy":[
        "tgn:1072331",
        "tgn:1000004",
        "tgn:7002087",
        "tgn:1000111",
        "tgn:7029392"
    ],
    "tgn:id":1072331,
    "tgn:name":"Tongxing",
    "tgn:placetype":[
        "aat:300008347"
    ]
},
  "bbox": [],
  "geometry": {"coordinates":[106.1333,30.6667],"type":"Point"}
}