{
  "id": 2264129,
  "type": "Feature",
  "properties": {
    "tgn:hierarchy":[
        "tgn:2264129",
        "tgn:1000001",
        "tgn:7012149",
        "tgn:2002114",
        "tgn:7007827",
        "tgn:7029392"
    ],
    "tgn:id":2264129,
    "tgn:name":"Coyote Spring",
    "tgn:placetype":[
        "aat:300008697"
    ]
},
  "bbox": [],
  "geometry": {"coordinates":[-112.8667,38.7667],"type":"Point"}
}