{
  "id": 2250107,
  "type": "Feature",
  "properties": {
    "tgn:hierarchy":[
        "tgn:2250107",
        "tgn:1000001",
        "tgn:7012149",
        "tgn:2001706",
        "tgn:7007708",
        "tgn:7029392"
    ],
    "tgn:id":2250107,
    "tgn:name":"Collins Creek",
    "tgn:placetype":[
        "aat:300008706"
    ]
},
  "bbox": [],
  "geometry": {"coordinates":[-122.8667,42.9833],"type":"Point"}
}