{
  "id": 1061954,
  "type": "Feature",
  "properties": {
    "tgn:hierarchy":[
        "tgn:1061954",
        "tgn:1001439",
        "tgn:1000003",
        "tgn:7002797",
        "tgn:1000095",
        "tgn:7029392"
    ],
    "tgn:id":1061954,
    "tgn:name":"Cieza",
    "tgn:placetype":[
        "aat:300008347"
    ]
},
  "bbox": [],
  "geometry": {"coordinates":[-1.416667,38.233333],"type":"Point"}
}