{
  "id": 7173997,
  "type": "Feature",
  "properties": {
    "tgn:hierarchy":[
        "tgn:7173997",
        "tgn:7003669",
        "tgn:1000003",
        "tgn:7000084",
        "tgn:7029392"
    ],
    "tgn:id":7173997,
    "tgn:name":"Grossaign",
    "tgn:placetype":[
        "aat:300000206"
    ]
},
  "bbox": [],
  "geometry": {"coordinates":[12.133333,48.416667],"type":"Point"}
}