{
  "id": 2386473,
  "type": "Feature",
  "properties": {
    "tgn:hierarchy":[
        "tgn:2386473",
        "tgn:7013349",
        "tgn:1000001",
        "tgn:7012149",
        "tgn:7007708",
        "tgn:7029392"
    ],
    "tgn:id":2386473,
    "tgn:name":"Herculean Mine",
    "tgn:placetype":[
        "aat:300000390"
    ]
},
  "bbox": [],
  "geometry": {"coordinates":[-118.2667,44.85],"type":"Point"}
}