{
  "id": 2762466,
  "type": "Feature",
  "properties": {
    "tgn:hierarchy":[
        "tgn:2762466",
        "tgn:1000001",
        "tgn:7012149",
        "tgn:2001761",
        "tgn:7007712",
        "tgn:7029392"
    ],
    "tgn:id":2762466,
    "tgn:name":"West Village Creek",
    "tgn:placetype":[
        "aat:300008706"
    ]
},
  "bbox": [],
  "geometry": {"coordinates":[-83.1833,34.8667],"type":"Point"}
}