<<<<<<< HEAD
{
  "id": 2762466,
  "type": "Feature",
  "properties": {
    "tgn:hierarchy":[
        "tgn:2762466",
        "tgn:1000001",
        "tgn:7012149",
        "tgn:2001761",
        "tgn:7007712",
        "tgn:7029392"
    ],
    "tgn:id":2762466,
    "tgn:name":"West Village Creek",
    "tgn:placetype":[
        "aat:300008706"
    ]
},
  "bbox": [],
  "geometry": {"coordinates":[-83.1833,34.8667],"type":"Point"}
}
=======
{"geometry":{"type":"Point","coordinates":[-83.183300,34.866700]},"type":"Feature","properties":{"hierarchy":["tgn:2762466","tgn:1000001","tgn:7012149","tgn:2001761","tgn:7007712","tgn:7029392"],"placetype":["aat:300008706"],"id":2762466,"name:xx":"West Village Creek"}}
>>>>>>> 03f74aca74312dbeaf24d7e61306dd6a786dc3d0
