{
  "id": 7453487,
  "type": "Feature",
  "properties": {
    "tgn:hierarchy":[
        "tgn:7453487",
        "tgn:7002445",
        "tgn:1000003",
        "tgn:7008132",
        "tgn:7008591",
        "tgn:7029392"
    ],
    "tgn:id":7453487,
    "tgn:name:en":"Church End",
    "tgn:placetype":[
        "aat:300008347"
    ]
},
  "bbox": [],
  "geometry": {"coordinates":[-2.15,52.016667],"type":"Point"}
}