<<<<<<< HEAD
{
  "id": 2330939,
  "type": "Feature",
  "properties": {
    "tgn:hierarchy":[
        "tgn:2330939",
        "tgn:1000001",
        "tgn:7013677",
        "tgn:7012149",
        "tgn:7007712",
        "tgn:7029392"
    ],
    "tgn:id":2330939,
    "tgn:name":"Flat Rock Branch",
    "tgn:placetype":[
        "aat:300008699"
    ]
},
  "bbox": [],
  "geometry": {"coordinates":[-81.7667,33.8167],"type":"Point"}
}
=======
{"geometry":{"type":"Point","coordinates":[-81.766700,33.816700]},"type":"Feature","properties":{"hierarchy":["tgn:2330939","tgn:1000001","tgn:7013677","tgn:7012149","tgn:7007712","tgn:7029392"],"placetype":["aat:300008699"],"id":2330939,"name:xx":"Flat Rock Branch"}}
>>>>>>> 03f74aca74312dbeaf24d7e61306dd6a786dc3d0
