{
  "id": 2208909,
  "type": "Feature",
  "properties": {
    "tgn:hierarchy":[
        "tgn:2208909",
        "tgn:1000001",
        "tgn:7012149",
        "tgn:2002250",
        "tgn:7007920",
        "tgn:7029392"
    ],
    "tgn:id":2208909,
    "tgn:name":"Burnt Canyon",
    "tgn:placetype":[
        "aat:300008761"
    ]
},
  "bbox": [],
  "geometry": {"coordinates":[-118.0167,48.3167],"type":"Point"}
}