{
  "id": 1064867,
  "type": "Feature",
  "properties": {
    "tgn:hierarchy":[
        "tgn:1064867",
        "tgn:7017298",
        "tgn:1000003",
        "tgn:7006663",
        "tgn:7029392"
    ],
    "tgn:id":1064867,
    "tgn:name":"\u010cazma",
    "tgn:placetype":[
        "aat:300008347"
    ]
},
  "bbox": [],
  "geometry": {"coordinates":[16.6667,45.75],"type":"Point"}
}