{
  "id": 2417378,
  "type": "Feature",
  "properties": {
    "tgn:hierarchy":[
        "tgn:2417378",
        "tgn:1000001",
        "tgn:7012149",
        "tgn:7007710",
        "tgn:7029392"
    ],
    "tgn:id":2417378,
    "tgn:name":"Jacks Mountain",
    "tgn:placetype":[
        "aat:300386831"
    ]
},
  "bbox": [],
  "geometry": {"coordinates":[-77.6167,40.6167],"type":"Point"}
}