{
  "id": 2215031,
  "type": "Feature",
  "properties": {
    "tgn:hierarchy":[
        "tgn:2215031",
        "tgn:1000001",
        "tgn:7012149",
        "tgn:7007157",
        "tgn:1002621",
        "tgn:7029392"
    ],
    "tgn:id":2215031,
    "tgn:name":"California Creek",
    "tgn:placetype":[
        "aat:300008706"
    ]
},
  "bbox": [],
  "geometry": {"coordinates":[-119.5667,37.4333],"type":"Point"}
}