{
  "id": 2560753,
  "type": "Feature",
  "properties": {
    "tgn:hierarchy":[
        "tgn:2560753",
        "tgn:1000001",
        "tgn:7012149",
        "tgn:1002924",
        "tgn:7007568",
        "tgn:7029392"
    ],
    "tgn:id":2560753,
    "tgn:name":"Orient Shoal",
    "tgn:placetype":[
        "aat:300132348"
    ]
},
  "bbox": [],
  "geometry": {"coordinates":[-72.3167,41.1333],"type":"Point"}
}