{
  "id": 2555318,
  "type": "Feature",
  "properties": {
    "tgn:hierarchy":[
        "tgn:2555318",
        "tgn:1002247",
        "tgn:1000001",
        "tgn:7012149",
        "tgn:7007516",
        "tgn:7029392"
    ],
    "tgn:id":2555318,
    "tgn:name":"Oddessy",
    "tgn:placetype":[
        "aat:300008347"
    ]
},
  "bbox": [],
  "geometry": {"coordinates":[-75.8167,39.5667],"type":"Point"}
}