{
  "id": 2724960,
  "type": "Feature",
  "properties": {
    "tgn:hierarchy":[
        "tgn:2724960",
        "tgn:7002659",
        "tgn:1000001",
        "tgn:7012149",
        "tgn:2000046",
        "tgn:7029392"
    ],
    "tgn:id":2724960,
    "tgn:name":"Toms Den Branch",
    "tgn:placetype":[
        "aat:300008699"
    ]
},
  "bbox": [],
  "geometry": {"coordinates":[-87.8833,34.1667],"type":"Point"}
}