{
  "id": 1018111,
  "type": "Feature",
  "properties": {
    "tgn:hierarchy":[
        "tgn:1018111",
        "tgn:1000001",
        "tgn:7005597",
        "tgn:7005560",
        "tgn:7029392"
    ],
    "tgn:id":1018111,
    "tgn:name":"Reynosa",
    "tgn:placetype":[
        "aat:300387277",
        "aat:300008347",
        "aat:300008389",
        "aat:300387270",
        "aat:300387302",
        "aat:300120599"
    ]
},
  "bbox": [],
  "geometry": {"coordinates":[-98.283333,26.083333],"type":"Point"}
}