<<<<<<< HEAD
{
  "id": 2250881,
  "type": "Feature",
  "properties": {
    "tgn:hierarchy":[
        "tgn:2250881",
        "tgn:1000001",
        "tgn:2000108",
        "tgn:7016172",
        "tgn:7012149",
        "tgn:7029392"
    ],
    "tgn:id":2250881,
    "tgn:name":"Columbia Hollow Creek",
    "tgn:placetype":[
        "aat:300008706"
    ]
},
  "bbox": [],
  "geometry": {"coordinates":[-94.4667,36.3167],"type":"Point"}
}
=======
{"geometry":{"type":"Point","coordinates":[-94.466700,36.316700]},"type":"Feature","properties":{"hierarchy":["tgn:2250881","tgn:1000001","tgn:2000108","tgn:7016172","tgn:7012149","tgn:7029392"],"placetype":["aat:300008706"],"id":2250881,"name:xx":"Columbia Hollow Creek"}}
>>>>>>> 03f74aca74312dbeaf24d7e61306dd6a786dc3d0
