{
  "id": 7448562,
  "type": "Feature",
  "properties": {
    "tgn:hierarchy":[
        "tgn:7448562",
        "tgn:7002444",
        "tgn:7008074",
        "tgn:1000003",
        "tgn:7008591",
        "tgn:7029392"
    ],
    "tgn:id":7448562,
    "tgn:name:en":"Talnotry",
    "tgn:placetype":[
        "aat:300008347"
    ]
},
  "bbox": [],
  "geometry": {"coordinates":[-4.366667,55.016667],"type":"Point"}
}