{
  "id": 2406004,
  "type": "Feature",
  "properties": {
    "tgn:hierarchy":[
        "tgn:2406004",
        "tgn:1000001",
        "tgn:7012149",
        "tgn:2000205",
        "tgn:7007158",
        "tgn:7029392"
    ],
    "tgn:id":2406004,
    "tgn:name":"Humboldt Peak",
    "tgn:placetype":[
        "aat:300008798"
    ]
},
  "bbox": [],
  "geometry": {"coordinates":[-105.55,37.9667],"type":"Point"}
}