{
  "id": 7428917,
  "type": "Feature",
  "properties": {
    "tgn:hierarchy":[
        "tgn:7428917",
        "tgn:7005586",
        "tgn:1000001",
        "tgn:7005560",
        "tgn:7029392"
    ],
    "tgn:id":7428917,
    "tgn:name":"Baj\u00edo de los Amoles",
    "tgn:placetype":[
        "aat:300008347"
    ]
},
  "bbox": [],
  "geometry": {"coordinates":[-103.933333,22.05],"type":"Point"}
}