{
  "id": 2747372,
  "type": "Feature",
  "properties": {
    "tgn:hierarchy":[
        "tgn:2747372",
        "tgn:1000001",
        "tgn:7012149",
        "tgn:7007919",
        "tgn:7029392"
    ],
    "tgn:id":2747372,
    "tgn:name":"Wahrani Swamp",
    "tgn:placetype":[
        "aat:300008699"
    ]
},
  "bbox": [],
  "geometry": {"coordinates":[-76.85,37.4833],"type":"Point"}
}