{
  "id": 7315539,
  "type": "Feature",
  "properties": {
    "tgn:hierarchy":[
        "tgn:7315539",
        "tgn:1001699",
        "tgn:1000049",
        "tgn:1000002",
        "tgn:7029392"
    ],
    "tgn:id":7315539,
    "tgn:name":"Chahuico, Estero",
    "tgn:placetype":[
        "aat:300008699"
    ]
},
  "bbox": [],
  "geometry": {"coordinates":[-73.216667,-40.733333],"type":"Point"}
}