<<<<<<< HEAD
{
  "id": 7368534,
  "type": "Feature",
  "properties": {
    "tgn:hierarchy":[
        "tgn:7368534",
        "tgn:7005583",
        "tgn:1000001",
        "tgn:7005560",
        "tgn:7029392"
    ],
    "tgn:id":7368534,
    "tgn:name":"Juan",
    "tgn:placetype":[
        "aat:300008347"
    ]
},
  "bbox": [],
  "geometry": {"coordinates":[-103.5,25.283333],"type":"Point"}
}
=======
{"geometry":{"type":"Point","coordinates":[-103.500000,25.283333]},"type":"Feature","properties":{"hierarchy":["tgn:7368534","tgn:7005583","tgn:1000001","tgn:7005560","tgn:7029392"],"placetype":["aat:300008347"],"id":7368534,"name:xx":"Juan"}}
>>>>>>> 03f74aca74312dbeaf24d7e61306dd6a786dc3d0
