{
  "id": 2774454,
  "type": "Feature",
  "properties": {
    "tgn:hierarchy":[
        "tgn:2774454",
        "tgn:1000001",
        "tgn:7012149",
        "tgn:1002646",
        "tgn:7007826",
        "tgn:7029392"
    ],
    "tgn:id":2774454,
    "tgn:name":"Willow Lake",
    "tgn:placetype":[
        "aat:300008680"
    ]
},
  "bbox": [],
  "geometry": {"coordinates":[-95.95,28.7667],"type":"Point"}
}