{
  "id": 2034502,
  "type": "Feature",
  "properties": {
    "tgn:hierarchy":[
        "tgn:2034502",
        "tgn:1000001",
        "tgn:2000578",
        "tgn:7012149",
        "tgn:7007253",
        "tgn:7029392"
    ],
    "tgn:id":2034502,
    "tgn:name":"Cherokee",
    "tgn:placetype":[
        "aat:300008347"
    ]
},
  "bbox": [],
  "geometry": {"coordinates":[-95.55,42.7333],"type":"Point"}
}