{
  "id": 1115915,
  "type": "Feature",
  "properties": {
    "tgn:hierarchy":[
        "tgn:1115915",
        "tgn:7005735",
        "tgn:7005685",
        "tgn:1000001",
        "tgn:7029392"
    ],
    "tgn:id":1115915,
    "tgn:name":"Christina Lake",
    "tgn:placetype":[
        "aat:300008680"
    ]
},
  "bbox": [],
  "geometry": {"coordinates":[-118.2667,49.1167],"type":"Point"}
}