{
  "id": 7274293,
  "type": "Feature",
  "properties": {
    "tgn:concordances":{
        "gn:id":"2743718"
    },
    "tgn:hierarchy":[
        "tgn:7274293",
        "tgn:1000003",
        "tgn:7006951",
        "tgn:7016845",
        "tgn:7029392"
    ],
    "tgn:id":7274293,
    "tgn:name:nl":"Zuiderwoude",
    "tgn:placetype":[
        "aat:300008347"
    ]
},
  "bbox": [],
  "geometry": {"coordinates":[5.033333,52.433333],"type":"Point"}
}