{
  "id": 7397745,
  "type": "Feature",
  "properties": {
    "tgn:hierarchy":[
        "tgn:7397745",
        "tgn:1000001",
        "tgn:1001893",
        "tgn:7005560",
        "tgn:7029392"
    ],
    "tgn:id":7397745,
    "tgn:name":"San Francisco Chimalpa",
    "tgn:placetype":[
        "aat:300008347"
    ]
},
  "bbox": [],
  "geometry": {"coordinates":[-99.3475,19.444167],"type":"Point"}
}