{
  "id": 7013573,
  "type": "Feature",
  "properties": {
    "tgn:hierarchy":[
        "tgn:7013573",
        "tgn:1000001",
        "tgn:2000688",
        "tgn:7012149",
        "tgn:7007254",
        "tgn:7029392"
    ],
    "tgn:id":7013573,
    "tgn:name":"Dodge City",
    "tgn:placetype":[
        "aat:300008347",
        "aat:300387233",
        "aat:300008375"
    ]
},
  "bbox": [],
  "geometry": {"coordinates":[-100.0167,37.75],"type":"Point"}
}