{
  "id": 2538077,
  "type": "Feature",
  "properties": {
    "tgn:hierarchy":[
        "tgn:2538077",
        "tgn:1000001",
        "tgn:7012149",
        "tgn:2002374",
        "tgn:7007923",
        "tgn:7029392"
    ],
    "tgn:id":2538077,
    "tgn:name":"Nelson Draw",
    "tgn:placetype":[
        "aat:300008761"
    ]
},
  "bbox": [],
  "geometry": {"coordinates":[-106.7667,44.55],"type":"Point"}
}