<<<<<<< HEAD
{
  "id": 7378693,
  "type": "Feature",
  "properties": {
    "tgn:hierarchy":[
        "tgn:7378693",
        "tgn:1000001",
        "tgn:7005590",
        "tgn:7005560",
        "tgn:7029392"
    ],
    "tgn:id":7378693,
    "tgn:name":"Los Camichines",
    "tgn:placetype":[
        "aat:300008347"
    ]
},
  "bbox": [],
  "geometry": {"coordinates":[-103.083333,18.8],"type":"Point"}
}
=======
{"geometry":{"type":"Point","coordinates":[-103.083333,18.800000]},"type":"Feature","properties":{"hierarchy":["tgn:7378693","tgn:1000001","tgn:7005590","tgn:7005560","tgn:7029392"],"placetype":["aat:300008347"],"id":7378693,"name:xx":"Los Camichines"}}
>>>>>>> 03f74aca74312dbeaf24d7e61306dd6a786dc3d0
