{
  "id": 1057428,
  "type": "Feature",
  "properties": {
    "tgn:hierarchy":[
        "tgn:1057428",
        "tgn:1003351",
        "tgn:1000004",
        "tgn:7018214",
        "tgn:7002435",
        "tgn:7029392"
    ],
    "tgn:id":1057428,
    "tgn:name":"Nizhnyaya Shaktama",
    "tgn:placetype":[
        "aat:300008347"
    ]
},
  "bbox": [],
  "geometry": {"coordinates":[117.75,51.4333],"type":"Point"}
}