{
  "id": 2490437,
  "type": "Feature",
  "properties": {
    "tgn:hierarchy":[
        "tgn:2490437",
        "tgn:1002648",
        "tgn:1000001",
        "tgn:7019158",
        "tgn:7012149",
        "tgn:7007249",
        "tgn:7029392"
    ],
    "tgn:id":2490437,
    "tgn:name":"Manienie Gulch",
    "tgn:placetype":[
        "aat:300008761"
    ]
},
  "bbox": [],
  "geometry": {"coordinates":[-156.5833,20.9833],"type":"Point"}
}