{
  "id": 2686809,
  "type": "Feature",
  "properties": {
    "tgn:hierarchy":[
        "tgn:2686809",
        "tgn:1000001",
        "tgn:7012149",
        "tgn:2001848",
        "tgn:7007825",
        "tgn:7029392"
    ],
    "tgn:id":2686809,
    "tgn:name":"Spring Creek Lake",
    "tgn:placetype":[
        "aat:300006191"
    ]
},
  "bbox": [],
  "geometry": {"coordinates":[-88.4833,35.4333],"type":"Point"}
}