{
  "id": 7228923,
  "type": "Feature",
  "properties": {
    "tgn:hierarchy":[
        "tgn:7228923",
        "tgn:7011170",
        "tgn:7002715",
        "tgn:1000003",
        "tgn:1000074",
        "tgn:7029392"
    ],
    "tgn:id":7228923,
    "tgn:name":"L\u00e9vki",
    "tgn:placetype":[
        "aat:300008347"
    ]
},
  "bbox": [],
  "geometry": {"coordinates":[24.866667,41.083333],"type":"Point"}
}