{
  "id": 7251623,
  "type": "Feature",
  "properties": {
    "tgn:hierarchy":[
        "tgn:7251623",
        "tgn:7003465",
        "tgn:1000003",
        "tgn:1000063",
        "tgn:4012014",
        "tgn:7029392"
    ],
    "tgn:id":7251623,
    "tgn:name":"Marcourt",
    "tgn:placetype":[
        "aat:300008347"
    ]
},
  "bbox": [],
  "geometry": {"coordinates":[5.524792,50.215329],"type":"Point"}
}