{
  "id": 7471451,
  "type": "Feature",
  "properties": {
    "tgn:hierarchy":[
        "tgn:7471451",
        "tgn:1000004",
        "tgn:7490934",
        "tgn:1000141",
        "tgn:7029392"
    ],
    "tgn:id":7471451,
    "tgn:name":"Houdongjiao",
    "tgn:placetype":[
        "aat:300008347"
    ]
},
  "bbox": [],
  "geometry": {"coordinates":[120.422371,23.215814],"type":"Point"}
}