<<<<<<< HEAD
{
  "id": 2259279,
  "type": "Feature",
  "properties": {
    "tgn:hierarchy":[
        "tgn:2259279",
        "tgn:1000001",
        "tgn:2001413",
        "tgn:7012149",
        "tgn:7007526",
        "tgn:7029392"
    ],
    "tgn:id":2259279,
    "tgn:name":"Cottonwood Number Two Spring",
    "tgn:placetype":[
        "aat:300008697"
    ]
},
  "bbox": [],
  "geometry": {"coordinates":[-116.55,39.7833],"type":"Point"}
}
=======
{"geometry":{"type":"Point","coordinates":[-116.550000,39.783300]},"type":"Feature","properties":{"hierarchy":["tgn:2259279","tgn:1000001","tgn:2001413","tgn:7012149","tgn:7007526","tgn:7029392"],"placetype":["aat:300008697"],"id":2259279,"name:xx":"Cottonwood Number Two Spring"}}
>>>>>>> 03f74aca74312dbeaf24d7e61306dd6a786dc3d0
