{
  "id": 2630560,
  "type": "Feature",
  "properties": {
    "tgn:hierarchy":[
        "tgn:2630560",
        "tgn:1002201",
        "tgn:1000001",
        "tgn:7012149",
        "tgn:7007517",
        "tgn:7029392"
    ],
    "tgn:id":2630560,
    "tgn:name":"Round Hill",
    "tgn:placetype":[
        "aat:300008798"
    ]
},
  "bbox": [],
  "geometry": {"coordinates":[-70.9167,41.5333],"type":"Point"}
}