{
  "id": 2503229,
  "type": "Feature",
  "properties": {
    "tgn:hierarchy":[
        "tgn:2503229",
        "tgn:1000001",
        "tgn:7012149",
        "tgn:1002553",
        "tgn:7007920",
        "tgn:7029392"
    ],
    "tgn:id":2503229,
    "tgn:name":"McPherson Canyon",
    "tgn:placetype":[
        "aat:300008761"
    ]
},
  "bbox": [],
  "geometry": {"coordinates":[-120.4333,46.8667],"type":"Point"}
}