{
  "id": 7045447,
  "type": "Feature",
  "properties": {
    "tgn:hierarchy":[
        "tgn:7045447",
        "tgn:7009084",
        "tgn:7004154",
        "tgn:1000003",
        "tgn:1000080",
        "tgn:7029392"
    ],
    "tgn:id":7045447,
    "tgn:name":"Fondillo, Torrente",
    "tgn:placetype":[
        "aat:300008699"
    ]
},
  "bbox": [],
  "geometry": {"coordinates":[13.85,41.783333],"type":"Point"}
}