{
  "id": 7383141,
  "type": "Feature",
  "properties": {
    "tgn:hierarchy":[
        "tgn:7383141",
        "tgn:1000001",
        "tgn:1001960",
        "tgn:7005560",
        "tgn:7029392"
    ],
    "tgn:id":7383141,
    "tgn:name":"Muerto, R\u00edo",
    "tgn:placetype":[
        "aat:300008699"
    ]
},
  "bbox": [],
  "geometry": {"coordinates":[-110.133333,27.533333],"type":"Point"}
}