{
  "id": 7437831,
  "type": "Feature",
  "properties": {
    "tgn:hierarchy":[
        "tgn:7437831",
        "tgn:1001853",
        "tgn:1000001",
        "tgn:7005560",
        "tgn:7029392"
    ],
    "tgn:id":7437831,
    "tgn:name":"Segu\u00edn",
    "tgn:placetype":[
        "aat:300007783"
    ]
},
  "bbox": [],
  "geometry": {"coordinates":[-101.716667,25.45],"type":"Point"}
}