{
  "id": 2247753,
  "type": "Feature",
  "properties": {
    "tgn:hierarchy":[
        "tgn:2247753",
        "tgn:1000001",
        "tgn:7012149",
        "tgn:7007157",
        "tgn:2000187",
        "tgn:7029392"
    ],
    "tgn:id":2247753,
    "tgn:name":"Cogswell Ravine",
    "tgn:placetype":[
        "aat:300008761"
    ]
},
  "bbox": [],
  "geometry": {"coordinates":[-120.6333,39.85],"type":"Point"}
}