{
  "id": 7406221,
  "type": "Feature",
  "properties": {
    "tgn:hierarchy":[
        "tgn:7406221",
        "tgn:7005585",
        "tgn:1000001",
        "tgn:7005560",
        "tgn:7029392"
    ],
    "tgn:id":7406221,
    "tgn:name":"El Llor\u00f3n, Isla",
    "tgn:placetype":[
        "aat:300008791"
    ]
},
  "bbox": [],
  "geometry": {"coordinates":[-101.766667,18.579167],"type":"Point"}
}