{
  "id": 7141893,
  "type": "Feature",
  "properties": {
    "tgn:hierarchy":[
        "tgn:7141893",
        "tgn:1000003",
        "tgn:7003677",
        "tgn:7000084",
        "tgn:7029392"
    ],
    "tgn:id":7141893,
    "tgn:name":"Lingese",
    "tgn:placetype":[
        "aat:300000206"
    ]
},
  "bbox": [],
  "geometry": {"coordinates":[7.566667,51.116667],"type":"Point"}
}