{
  "id": 2431168,
  "type": "Feature",
  "properties": {
    "tgn:hierarchy":[
        "tgn:2431168",
        "tgn:1000001",
        "tgn:7012149",
        "tgn:2001504",
        "tgn:7007709",
        "tgn:7029392"
    ],
    "tgn:id":2431168,
    "tgn:name":"Kanuga Ridge",
    "tgn:placetype":[
        "aat:300008347"
    ]
},
  "bbox": [],
  "geometry": {"coordinates":[-82.5167,35.2667],"type":"Point"}
}