{
  "id": 1042005,
  "type": "Feature",
  "properties": {
    "tgn:hierarchy":[
        "tgn:1042005",
        "tgn:7002715",
        "tgn:7002731",
        "tgn:1000003",
        "tgn:1000074",
        "tgn:7029392"
    ],
    "tgn:id":1042005,
    "tgn:name":"Epanom\u00ed",
    "tgn:placetype":[
        "aat:300008347"
    ]
},
  "bbox": [],
  "geometry": {"coordinates":[22.928624,40.426381],"type":"Point"}
}