{
  "id": 7321143,
  "type": "Feature",
  "properties": {
    "tgn:hierarchy":[
        "tgn:7321143",
        "tgn:1001657",
        "tgn:1000049",
        "tgn:1000002",
        "tgn:7029392"
    ],
    "tgn:id":7321143,
    "tgn:name":"Balada",
    "tgn:placetype":[
        "aat:300008347"
    ]
},
  "bbox": [],
  "geometry": {"coordinates":[-70.216667,-29.916667],"type":"Point"}
}