{
  "id": 7324550,
  "type": "Feature",
  "properties": {
    "tgn:hierarchy":[
        "tgn:7324550",
        "tgn:7007780",
        "tgn:1000003",
        "tgn:7009604",
        "tgn:1000095",
        "tgn:7029392"
    ],
    "tgn:id":7324550,
    "tgn:name":"San Pedro",
    "tgn:placetype":[
        "aat:300008347"
    ]
},
  "bbox": [],
  "geometry": {"coordinates":[-2.433333,43.033333],"type":"Point"}
}