<<<<<<< HEAD
{
  "id": 7483815,
  "type": "Feature",
  "properties": {
    "tgn:hierarchy":[
        "tgn:7483815",
        "tgn:1000004",
        "tgn:7490934",
        "tgn:1000141",
        "tgn:7029392"
    ],
    "tgn:id":7483815,
    "tgn:name":"Zhuziliaokeng",
    "tgn:placetype":[
        "aat:300008347"
    ]
},
  "bbox": [],
  "geometry": {"coordinates":[120.61,23.212778],"type":"Point"}
}
=======
{"geometry":{"type":"Point","coordinates":[120.610000,23.212778]},"type":"Feature","properties":{"hierarchy":["tgn:7483815","tgn:1000004","tgn:7490934","tgn:1000141","tgn:7029392"],"placetype":["aat:300008347"],"id":7483815,"name:xx":"Zhuziliaokeng"}}
>>>>>>> 03f74aca74312dbeaf24d7e61306dd6a786dc3d0
