<<<<<<< HEAD
{
  "id": 2339014,
  "type": "Feature",
  "properties": {
    "tgn:hierarchy":[
        "tgn:2339014",
        "tgn:1000001",
        "tgn:7012149",
        "tgn:1002454",
        "tgn:7007826",
        "tgn:7029392"
    ],
    "tgn:id":2339014,
    "tgn:name":"Franklin Lake",
    "tgn:placetype":[
        "aat:300008680"
    ]
},
  "bbox": [],
  "geometry": {"coordinates":[-94.1,30.4667],"type":"Point"}
}
=======
{"geometry":{"type":"Point","coordinates":[-94.100000,30.466700]},"type":"Feature","properties":{"hierarchy":["tgn:2339014","tgn:1000001","tgn:7012149","tgn:1002454","tgn:7007826","tgn:7029392"],"placetype":["aat:300008680"],"id":2339014,"name:xx":"Franklin Lake"}}
>>>>>>> 03f74aca74312dbeaf24d7e61306dd6a786dc3d0
