{
  "id": 2301292,
  "type": "Feature",
  "properties": {
    "tgn:hierarchy":[
        "tgn:2301292",
        "tgn:1000001",
        "tgn:7012149",
        "tgn:1002540",
        "tgn:7007520",
        "tgn:7029392"
    ],
    "tgn:id":2301292,
    "tgn:name":"Dunlop Lake",
    "tgn:placetype":[
        "aat:300008680"
    ]
},
  "bbox": [],
  "geometry": {"coordinates":[-85.5667,43.0333],"type":"Point"}
}