{
  "id": 7455049,
  "type": "Feature",
  "properties": {
    "tgn:hierarchy":[
        "tgn:7455049",
        "tgn:7002445",
        "tgn:1000003",
        "tgn:7008174",
        "tgn:7008591",
        "tgn:7029392"
    ],
    "tgn:id":7455049,
    "tgn:name:en":"Colwich",
    "tgn:placetype":[
        "aat:300008347"
    ]
},
  "bbox": [],
  "geometry": {"coordinates":[-1.983333,52.783333],"type":"Point"}
}