<<<<<<< HEAD
{
  "id": 7471790,
  "type": "Feature",
  "properties": {
    "tgn:hierarchy":[
        "tgn:7471790",
        "tgn:1000004",
        "tgn:7471332",
        "tgn:1000141",
        "tgn:7029392"
    ],
    "tgn:id":7471790,
    "tgn:name":"Fenjiwo",
    "tgn:placetype":[
        "aat:300008347"
    ]
},
  "bbox": [],
  "geometry": {"coordinates":[121.054444,24.871667],"type":"Point"}
}
=======
{"geometry":{"type":"Point","coordinates":[121.054444,24.871667]},"type":"Feature","properties":{"hierarchy":["tgn:7471790","tgn:1000004","tgn:7471332","tgn:1000141","tgn:7029392"],"placetype":["aat:300008347"],"id":7471790,"name:xx":"Fenjiwo"}}
>>>>>>> 03f74aca74312dbeaf24d7e61306dd6a786dc3d0
