{
  "id": 2131439,
  "type": "Feature",
  "properties": {
    "tgn:hierarchy":[
        "tgn:2131439",
        "tgn:1000001",
        "tgn:2000955",
        "tgn:7012149",
        "tgn:7007520",
        "tgn:7029392"
    ],
    "tgn:id":2131439,
    "tgn:name":"Alton",
    "tgn:placetype":[
        "aat:300008347"
    ]
},
  "bbox": [],
  "geometry": {"coordinates":[-86.8833,45.8667],"type":"Point"}
}