{
  "id": 2503214,
  "type": "Feature",
  "properties": {
    "tgn:hierarchy":[
        "tgn:2503214",
        "tgn:1000001",
        "tgn:7012149",
        "tgn:7007253",
        "tgn:7029392"
    ],
    "tgn:id":2503214,
    "tgn:name":"McPherron Creek",
    "tgn:placetype":[
        "aat:300008706"
    ]
},
  "bbox": [],
  "geometry": {"coordinates":[-95.6667,40.9167],"type":"Point"}
}