{
  "id": 2763305,
  "type": "Feature",
  "properties": {
    "tgn:hierarchy":[
        "tgn:2763305",
        "tgn:1000001",
        "tgn:7012149",
        "tgn:2001716",
        "tgn:7007708",
        "tgn:7029392"
    ],
    "tgn:id":2763305,
    "tgn:name":"Wet Gulch",
    "tgn:placetype":[
        "aat:300008761"
    ]
},
  "bbox": [],
  "geometry": {"coordinates":[-122.4167,44.1333],"type":"Point"}
}