{
  "id": 1087902,
  "type": "Feature",
  "properties": {
    "tgn:hierarchy":[
        "tgn:1087902",
        "tgn:7001242",
        "tgn:1000149",
        "tgn:1000884",
        "tgn:7029392"
    ],
    "tgn:id":1087902,
    "tgn:name":"Mu\u00e1 Ximica",
    "tgn:placetype":[
        "aat:300008347"
    ]
},
  "bbox": [],
  "geometry": {"coordinates":[18.7667,-9.8167],"type":"Point"}
}