{
  "id": 7143379,
  "type": "Feature",
  "properties": {
    "tgn:hierarchy":[
        "tgn:7143379",
        "tgn:1000003",
        "tgn:7003676",
        "tgn:7000084",
        "tgn:7029392"
    ],
    "tgn:id":7143379,
    "tgn:name":"Maade",
    "tgn:placetype":[
        "aat:300008699"
    ]
},
  "bbox": [],
  "geometry": {"coordinates":[8.133333,53.55],"type":"Point"}
}