{
  "id": 7546247,
  "type": "Feature",
  "properties": {
    "tgn:hierarchy":[
        "tgn:7546247",
        "tgn:1001828",
        "tgn:1000004",
        "tgn:7000198",
        "tgn:7029392"
    ],
    "tgn:id":7546247,
    "tgn:name:en":"Anantar\u0101jupeta",
    "tgn:placetype":[
        "aat:300007783"
    ]
},
  "bbox": [],
  "geometry": {"coordinates":[79.316667,13.983333],"type":"Point"}
}