{
  "id": 7043573,
  "type": "Feature",
  "properties": {
    "tgn:hierarchy":[
        "tgn:7043573",
        "tgn:1003444",
        "tgn:1000003",
        "tgn:7003241",
        "tgn:1000080",
        "tgn:7029392"
    ],
    "tgn:id":7043573,
    "tgn:name":"Cece, Monte",
    "tgn:placetype":[
        "aat:300008795"
    ]
},
  "bbox": [],
  "geometry": {"coordinates":[14.833333,41.783333],"type":"Point"}
}