{
  "id": 2045936,
  "type": "Feature",
  "properties": {
    "tgn:hierarchy":[
        "tgn:2045936",
        "tgn:1000001",
        "tgn:7012149",
        "tgn:2000931",
        "tgn:7007515",
        "tgn:7029392"
    ],
    "tgn:id":2045936,
    "tgn:name":"Youngtown",
    "tgn:placetype":[
        "aat:300008347",
        "aat:300387210"
    ]
},
  "bbox": [],
  "geometry": {"coordinates":[-69.0833,44.2667],"type":"Point"}
}