{
  "id": 2158527,
  "type": "Feature",
  "properties": {
    "tgn:hierarchy":[
        "tgn:2158527",
        "tgn:1000001",
        "tgn:2002370",
        "tgn:7012149",
        "tgn:7007923",
        "tgn:7029392"
    ],
    "tgn:id":2158527,
    "tgn:name":"Beaverdam Creek",
    "tgn:placetype":[
        "aat:300008706"
    ]
},
  "bbox": [],
  "geometry": {"coordinates":[-104.3667,44.6833],"type":"Point"}
}