{
  "id": 7280677,
  "type": "Feature",
  "properties": {
    "tgn:hierarchy":[
        "tgn:7280677",
        "tgn:7002464",
        "tgn:1000049",
        "tgn:1000002",
        "tgn:7029392"
    ],
    "tgn:id":7280677,
    "tgn:name":"San Jos\u00e9, R\u00edo",
    "tgn:placetype":[
        "aat:300266554",
        "aat:300008699"
    ]
},
  "bbox": [],
  "geometry": {"coordinates":[-70.316667,-18.466667],"type":"Point"}
}