{
  "id": 2035834,
  "type": "Feature",
  "properties": {
    "tgn:hierarchy":[
        "tgn:2035834",
        "tgn:2000566",
        "tgn:1000001",
        "tgn:7012149",
        "tgn:7007253",
        "tgn:7029392"
    ],
    "tgn:id":2035834,
    "tgn:name":"Walford",
    "tgn:placetype":[
        "aat:300008347"
    ]
},
  "bbox": [],
  "geometry": {"coordinates":[-91.8333,41.8667],"type":"Point"}
}