<<<<<<< HEAD
{
  "id": 7173705,
  "type": "Feature",
  "properties": {
    "tgn:hierarchy":[
        "tgn:7173705",
        "tgn:1000003",
        "tgn:7003682",
        "tgn:7000084",
        "tgn:7029392"
    ],
    "tgn:id":7173705,
    "tgn:name":"Gro\u00dfer Rhein Berg",
    "tgn:placetype":[
        "aat:300132356"
    ]
},
  "bbox": [],
  "geometry": {"coordinates":[7.85,49.983333],"type":"Point"}
}
=======
{"geometry":{"type":"Point","coordinates":[7.850000,49.983333]},"type":"Feature","properties":{"hierarchy":["tgn:7173705","tgn:1000003","tgn:7003682","tgn:7000084","tgn:7029392"],"placetype":["aat:300132356"],"id":7173705,"name:xx":"Gro\u00dfer Rhein Berg"}}
>>>>>>> 03f74aca74312dbeaf24d7e61306dd6a786dc3d0
