{
  "id": 7484667,
  "type": "Feature",
  "properties": {
    "tgn:hierarchy":[
        "tgn:7484667",
        "tgn:7468018",
        "tgn:1000004",
        "tgn:1000141",
        "tgn:7029392"
    ],
    "tgn:id":7484667,
    "tgn:name":"Zhongxinlunkeng",
    "tgn:placetype":[
        "aat:300008699"
    ]
},
  "bbox": [],
  "geometry": {"coordinates":[120.565833,23.238889],"type":"Point"}
}