{
  "id": 2193049,
  "type": "Feature",
  "properties": {
    "tgn:hierarchy":[
        "tgn:2193049",
        "tgn:1000001",
        "tgn:7012149",
        "tgn:2001879",
        "tgn:7007825",
        "tgn:7029392"
    ],
    "tgn:id":2193049,
    "tgn:name":"Breadens Spring",
    "tgn:placetype":[
        "aat:300008697"
    ]
},
  "bbox": [],
  "geometry": {"coordinates":[-87.6833,36.0167],"type":"Point"}
}