{
  "id": 2485280,
  "type": "Feature",
  "properties": {
    "tgn:hierarchy":[
        "tgn:2485280",
        "tgn:1000001",
        "tgn:7016172",
        "tgn:7012149",
        "tgn:2000172",
        "tgn:7029392"
    ],
    "tgn:id":2485280,
    "tgn:name":"Lawrence Hollow",
    "tgn:placetype":[
        "aat:300008761"
    ]
},
  "bbox": [],
  "geometry": {"coordinates":[-91.45,36.2333],"type":"Point"}
}