{
  "id": 7566726,
  "type": "Feature",
  "properties": {
    "tgn:hierarchy":[
        "tgn:7566726",
        "tgn:1000004",
        "tgn:7000198",
        "tgn:7016722",
        "tgn:7029392"
    ],
    "tgn:id":7566726,
    "tgn:name:en":"Mau Minor",
    "tgn:placetype":[
        "aat:300006075"
    ]
},
  "bbox": [],
  "geometry": {"coordinates":[79.877722,26.673848],"type":"Point"}
}