{
  "id": 2665077,
  "type": "Feature",
  "properties": {
    "tgn:hierarchy":[
        "tgn:2665077",
        "tgn:1000001",
        "tgn:7012149",
        "tgn:1002596",
        "tgn:7007706",
        "tgn:7029392"
    ],
    "tgn:id":2665077,
    "tgn:name":"Simpson Run",
    "tgn:placetype":[
        "aat:300008699"
    ]
},
  "bbox": [],
  "geometry": {"coordinates":[-82.6667,40.05],"type":"Point"}
}