{
  "id": 1113079,
  "type": "Feature",
  "properties": {
    "tgn:hierarchy":[
        "tgn:1113079",
        "tgn:1001942",
        "tgn:1000047",
        "tgn:7002457",
        "tgn:1000002",
        "tgn:7029392"
    ],
    "tgn:id":1113079,
    "tgn:name":"Guanabara, Ba\u00eda de",
    "tgn:placetype":[
        "aat:300132316"
    ]
},
  "bbox": [],
  "geometry": {"coordinates":[-43.1667,-22.8333],"type":"Point"}
}