<<<<<<< HEAD
{
  "id": 2760289,
  "type": "Feature",
  "properties": {
    "tgn:hierarchy":[
        "tgn:2760289",
        "tgn:1000001",
        "tgn:7012149",
        "tgn:2002119",
        "tgn:7007827",
        "tgn:7029392"
    ],
    "tgn:id":2760289,
    "tgn:name":"West Fork Salt Creek",
    "tgn:placetype":[
        "aat:300008706"
    ]
},
  "bbox": [],
  "geometry": {"coordinates":[-109.8,37.9667],"type":"Point"}
}
=======
{"geometry":{"type":"Point","coordinates":[-109.800000,37.966700]},"type":"Feature","properties":{"hierarchy":["tgn:2760289","tgn:1000001","tgn:7012149","tgn:2002119","tgn:7007827","tgn:7029392"],"placetype":["aat:300008706"],"id":2760289,"name:xx":"West Fork Salt Creek"}}
>>>>>>> 03f74aca74312dbeaf24d7e61306dd6a786dc3d0
