<<<<<<< HEAD
{
  "id": 7353650,
  "type": "Feature",
  "properties": {
    "tgn:hierarchy":[
        "tgn:7353650",
        "tgn:7005581",
        "tgn:1000001",
        "tgn:7005560",
        "tgn:7029392"
    ],
    "tgn:id":7353650,
    "tgn:name":"Benito Ju\u00e1rez",
    "tgn:placetype":[
        "aat:300008347"
    ]
},
  "bbox": [],
  "geometry": {"coordinates":[-107.933333,29.75],"type":"Point"}
}
=======
{"geometry":{"type":"Point","coordinates":[-107.933333,29.750000]},"type":"Feature","properties":{"hierarchy":["tgn:7353650","tgn:7005581","tgn:1000001","tgn:7005560","tgn:7029392"],"placetype":["aat:300008347"],"id":7353650,"name:xx":"Benito Ju\u00e1rez"}}
>>>>>>> 03f74aca74312dbeaf24d7e61306dd6a786dc3d0
