{
  "id": 7421585,
  "type": "Feature",
  "properties": {
    "tgn:hierarchy":[
        "tgn:7421585",
        "tgn:1000001",
        "tgn:1001960",
        "tgn:7005560",
        "tgn:7029392"
    ],
    "tgn:id":7421585,
    "tgn:name":"Las Hojalitas, Picacho",
    "tgn:placetype":[
        "aat:300008798"
    ]
},
  "bbox": [],
  "geometry": {"coordinates":[-112.484722,31.155556],"type":"Point"}
}