{
  "id": 7517694,
  "type": "Feature",
  "properties": {
    "tgn:hierarchy":[
        "tgn:7517694",
        "tgn:7000509",
        "tgn:1008380",
        "tgn:1000226",
        "tgn:1000006",
        "tgn:7029392"
    ],
    "tgn:id":7517694,
    "tgn:name:en":"Kiwinui",
    "tgn:placetype":[
        "aat:300008777"
    ]
},
  "bbox": [],
  "geometry": {"coordinates":[176.933333,-38.016667],"type":"Point"}
}