{
  "id": 2475236,
  "type": "Feature",
  "properties": {
    "tgn:hierarchy":[
        "tgn:2475236",
        "tgn:1000001",
        "tgn:7012149",
        "tgn:2001449",
        "tgn:7007566",
        "tgn:7029392"
    ],
    "tgn:id":2475236,
    "tgn:name":"Loyd Tank",
    "tgn:placetype":[
        "aat:300006191"
    ]
},
  "bbox": [],
  "geometry": {"coordinates":[-106.1667,36.7167],"type":"Point"}
}