{
  "id": 7347611,
  "type": "Feature",
  "properties": {
    "tgn:hierarchy":[
        "tgn:7347611",
        "tgn:7002839",
        "tgn:7001158",
        "tgn:1000003",
        "tgn:1000095",
        "tgn:7029392"
    ],
    "tgn:id":7347611,
    "tgn:name":"Basardilla",
    "tgn:placetype":[
        "aat:300008347"
    ]
},
  "bbox": [],
  "geometry": {"coordinates":[-4.016667,41.016667],"type":"Point"}
}