{
  "id": 7523288,
  "type": "Feature",
  "properties": {
    "tgn:hierarchy":[
        "tgn:7523288",
        "tgn:7001242",
        "tgn:7016833",
        "tgn:7001336",
        "tgn:7029392"
    ],
    "tgn:id":7523288,
    "tgn:name:en":"Duqayyia, Sha'ab ad",
    "tgn:placetype":[
        "aat:300008808"
    ]
},
  "bbox": [],
  "geometry": {"coordinates":[33.833333,27.866667],"type":"Point"}
}