<<<<<<< HEAD
{
  "id": 7363326,
  "type": "Feature",
  "properties": {
    "tgn:hierarchy":[
        "tgn:7363326",
        "tgn:1000001",
        "tgn:7005597",
        "tgn:7005560",
        "tgn:7029392"
    ],
    "tgn:id":7363326,
    "tgn:name":"El Mimbral",
    "tgn:placetype":[
        "aat:300266554",
        "aat:300008699"
    ]
},
  "bbox": [],
  "geometry": {"coordinates":[-99.733333,23.3],"type":"Point"}
}
=======
{"geometry":{"type":"Point","coordinates":[-99.733333,23.300000]},"type":"Feature","properties":{"hierarchy":["tgn:7363326","tgn:1000001","tgn:7005597","tgn:7005560","tgn:7029392"],"placetype":["aat:300266554","aat:300008699"],"id":7363326,"name:xx":"El Mimbral"}}
>>>>>>> 03f74aca74312dbeaf24d7e61306dd6a786dc3d0
