{
  "id": 7404222,
  "type": "Feature",
  "properties": {
    "tgn:hierarchy":[
        "tgn:7404222",
        "tgn:7005578",
        "tgn:1000001",
        "tgn:7005560",
        "tgn:7029392"
    ],
    "tgn:id":7404222,
    "tgn:name":"Yapur, Laguna",
    "tgn:placetype":[
        "aat:300008680"
    ]
},
  "bbox": [],
  "geometry": {"coordinates":[-90.116667,18.783333],"type":"Point"}
}