{
  "id": 2127602,
  "type": "Feature",
  "properties": {
    "tgn:hierarchy":[
        "tgn:2127602",
        "tgn:1000001",
        "tgn:7012149",
        "tgn:2002005",
        "tgn:7007826",
        "tgn:7029392"
    ],
    "tgn:id":2127602,
    "tgn:name":"Alacran Mountain",
    "tgn:placetype":[
        "aat:300008798"
    ]
},
  "bbox": [],
  "geometry": {"coordinates":[-105.9667,31.8667],"type":"Point"}
}