{
  "id": 7592225,
  "type": "Feature",
  "properties": {
    "tgn:hierarchy":[
        "tgn:7592225",
        "tgn:1000004",
        "tgn:7000198",
        "tgn:7000799",
        "tgn:7029392"
    ],
    "tgn:id":7592225,
    "tgn:name:en":"Loh\u0101r\u0101n Laihr",
    "tgn:placetype":[
        "aat:300008347"
    ]
},
  "bbox": [],
  "geometry": {"coordinates":[74.997222,32.883333],"type":"Point"}
}