{
  "id": 7513363,
  "type": "Feature",
  "properties": {
    "tgn:hierarchy":[
        "tgn:7513363",
        "tgn:1009227",
        "tgn:1000226",
        "tgn:7018437",
        "tgn:1000006",
        "tgn:7029392"
    ],
    "tgn:id":7513363,
    "tgn:name:en":"Gordons Rock",
    "tgn:placetype":[
        "aat:300011692"
    ]
},
  "bbox": [],
  "geometry": {"coordinates":[169.166667,-44.916667],"type":"Point"}
}