{
  "id": 2262036,
  "type": "Feature",
  "properties": {
    "tgn:hierarchy":[
        "tgn:2262036",
        "tgn:1000001",
        "tgn:7012149",
        "tgn:2001752",
        "tgn:7007712",
        "tgn:7029392"
    ],
    "tgn:id":2262036,
    "tgn:name":"Cow Branch",
    "tgn:placetype":[
        "aat:300008699"
    ]
},
  "bbox": [],
  "geometry": {"coordinates":[-80.5333,34.45],"type":"Point"}
}