{
  "id": 7492686,
  "type": "Feature",
  "properties": {
    "tgn:hierarchy":[
        "tgn:7492686",
        "tgn:1000004",
        "tgn:7001013",
        "tgn:1000141",
        "tgn:7029392"
    ],
    "tgn:id":7492686,
    "tgn:name":"Shanziding",
    "tgn:placetype":[
        "aat:300008347"
    ]
},
  "bbox": [],
  "geometry": {"coordinates":[121.155791,25.015088],"type":"Point"}
}