{
  "id": 2723540,
  "type": "Feature",
  "properties": {
    "tgn:hierarchy":[
        "tgn:2723540",
        "tgn:1000001",
        "tgn:2001429",
        "tgn:7012149",
        "tgn:7007566",
        "tgn:7029392"
    ],
    "tgn:id":2723540,
    "tgn:name":"Todd Cienega Tank",
    "tgn:placetype":[
        "aat:300006191"
    ]
},
  "bbox": [],
  "geometry": {"coordinates":[-108.4667,33.8167],"type":"Point"}
}