{
  "id": 2247951,
  "type": "Feature",
  "properties": {
    "tgn:hierarchy":[
        "tgn:2247951",
        "tgn:7002659",
        "tgn:1000001",
        "tgn:2000016",
        "tgn:7012149",
        "tgn:7029392"
    ],
    "tgn:id":2247951,
    "tgn:name":"Colbert Shoals Canal",
    "tgn:placetype":[
        "aat:300387088",
        "aat:300006075"
    ]
},
  "bbox": [],
  "geometry": {"coordinates":[-88.0167,34.8833],"type":"Point"}
}