{
  "id": 7474286,
  "type": "Feature",
  "properties": {
    "tgn:hierarchy":[
        "tgn:7474286",
        "tgn:1000004",
        "tgn:1000454",
        "tgn:1000141",
        "tgn:7029392"
    ],
    "tgn:id":7474286,
    "tgn:name":"Yuetaoliao",
    "tgn:placetype":[
        "aat:300008347"
    ]
},
  "bbox": [],
  "geometry": {"coordinates":[121.78114,25.059334],"type":"Point"}
}