{
  "id": 2356416,
  "type": "Feature",
  "properties": {
    "tgn:hierarchy":[
        "tgn:2356416",
        "tgn:1000001",
        "tgn:7012149",
        "tgn:2000219",
        "tgn:7007158",
        "tgn:7029392"
    ],
    "tgn:id":2356416,
    "tgn:name":"Gordon Arroyo",
    "tgn:placetype":[
        "aat:300008699"
    ]
},
  "bbox": [],
  "geometry": {"coordinates":[-104.95,37.6333],"type":"Point"}
}