{
  "id": 2620253,
  "type": "Feature",
  "properties": {
    "tgn:hierarchy":[
        "tgn:2620253",
        "tgn:1000001",
        "tgn:7012149",
        "tgn:2000227",
        "tgn:7007158",
        "tgn:7029392"
    ],
    "tgn:id":2620253,
    "tgn:name":"Rivale Spring",
    "tgn:placetype":[
        "aat:300008697"
    ]
},
  "bbox": [],
  "geometry": {"coordinates":[-104.2333,37.0167],"type":"Point"}
}