{
  "id": 7033769,
  "type": "Feature",
  "properties": {
    "tgn:hierarchy":[
        "tgn:7033769",
        "tgn:1003459",
        "tgn:1000003",
        "tgn:7002993",
        "tgn:1000080",
        "tgn:7029392"
    ],
    "tgn:id":7033769,
    "tgn:name":"Rupa",
    "tgn:placetype":[
        "aat:300008347"
    ]
},
  "bbox": [],
  "geometry": {"coordinates":[13.589722,45.891389],"type":"Point"}
}