{
  "id": 7481124,
  "type": "Feature",
  "properties": {
    "tgn:hierarchy":[
        "tgn:7481124",
        "tgn:1000004",
        "tgn:7490934",
        "tgn:1000141",
        "tgn:7029392"
    ],
    "tgn:id":7481124,
    "tgn:name":"Shagouku",
    "tgn:placetype":[
        "aat:300008347"
    ]
},
  "bbox": [],
  "geometry": {"coordinates":[120.25514,23.347102],"type":"Point"}
}