{
  "id": 7134559,
  "type": "Feature",
  "properties": {
    "tgn:hierarchy":[
        "tgn:7134559",
        "tgn:7003669",
        "tgn:1000003",
        "tgn:7000084",
        "tgn:7029392"
    ],
    "tgn:id":7134559,
    "tgn:name":"M\u00fchlbach",
    "tgn:placetype":[
        "aat:300008699"
    ]
},
  "bbox": [],
  "geometry": {"coordinates":[12.416667,47.716667],"type":"Point"}
}