{
  "id": 2543359,
  "type": "Feature",
  "properties": {
    "tgn:hierarchy":[
        "tgn:2543359",
        "tgn:2001566",
        "tgn:1000001",
        "tgn:7012149",
        "tgn:7007705",
        "tgn:7029392"
    ],
    "tgn:id":2543359,
    "tgn:name":"Norman Otto Hill",
    "tgn:placetype":[
        "aat:300008798"
    ]
},
  "bbox": [],
  "geometry": {"coordinates":[-98.0667,48.9167],"type":"Point"}
}