{
  "id": 7499628,
  "type": "Feature",
  "properties": {
    "tgn:hierarchy":[
        "tgn:7499628",
        "tgn:7001004",
        "tgn:1000004",
        "tgn:1000141",
        "tgn:7029392"
    ],
    "tgn:id":7499628,
    "tgn:name":"Jiuqu Guoxiao",
    "tgn:placetype":[
        "aat:300006495"
    ]
},
  "bbox": [],
  "geometry": {"coordinates":[120.424319,22.655733],"type":"Point"}
}