{
  "id": 2442985,
  "type": "Feature",
  "properties": {
    "tgn:hierarchy":[
        "tgn:2442985",
        "tgn:7006450",
        "tgn:1000001",
        "tgn:7012149",
        "tgn:2000089",
        "tgn:7029392"
    ],
    "tgn:id":2442985,
    "tgn:name":"Kupuk Creek",
    "tgn:placetype":[
        "aat:300008706"
    ]
},
  "bbox": [],
  "geometry": {"coordinates":[-150.0167,67.8167],"type":"Point"}
}