{
  "id": 1017745,
  "type": "Feature",
  "properties": {
    "tgn:hierarchy":[
        "tgn:1017745",
        "tgn:1000001",
        "tgn:7005590",
        "tgn:7005560",
        "tgn:7029392"
    ],
    "tgn:id":1017745,
    "tgn:name":"Las Cruces",
    "tgn:placetype":[
        "aat:300008347"
    ]
},
  "bbox": [],
  "geometry": {"coordinates":[-102.266667,18.75],"type":"Point"}
}