{
  "id": 7510122,
  "type": "Feature",
  "properties": {
    "tgn:hierarchy":[
        "tgn:7510122",
        "tgn:1009227",
        "tgn:1000226",
        "tgn:7016822",
        "tgn:1000006",
        "tgn:7029392"
    ],
    "tgn:id":7510122,
    "tgn:name:en":"Steeple Burn",
    "tgn:placetype":[
        "aat:300008699"
    ]
},
  "bbox": [],
  "geometry": {"coordinates":[168.883333,-45.683333],"type":"Point"}
}