{
  "id": 7270090,
  "type": "Feature",
  "properties": {
    "tgn:hierarchy":[
        "tgn:7270090",
        "tgn:1000003",
        "tgn:7006951",
        "tgn:7016845",
        "tgn:7029392"
    ],
    "tgn:id":7270090,
    "tgn:name:nl":"Molenplas",
    "tgn:placetype":[
        "aat:300008688"
    ]
},
  "bbox": [],
  "geometry": {"coordinates":[4.65,52.35],"type":"Point"}
}