{
  "id": 2346186,
  "type": "Feature",
  "properties": {
    "tgn:hierarchy":[
        "tgn:2346186",
        "tgn:1000001",
        "tgn:7012149",
        "tgn:1002871",
        "tgn:7007568",
        "tgn:7029392"
    ],
    "tgn:id":2346186,
    "tgn:name":"Gates",
    "tgn:placetype":[
        "aat:300008347"
    ]
},
  "bbox": [],
  "geometry": {"coordinates":[-73.6333,43.0833],"type":"Point"}
}