{
  "id": 2265282,
  "type": "Feature",
  "properties": {
    "tgn:hierarchy":[
        "tgn:2265282",
        "tgn:1000001",
        "tgn:7012149",
        "tgn:1002758",
        "tgn:7007568",
        "tgn:7029392"
    ],
    "tgn:id":2265282,
    "tgn:name":"Crandell Creek",
    "tgn:placetype":[
        "aat:300008706"
    ]
},
  "bbox": [],
  "geometry": {"coordinates":[-75.8833,43.25],"type":"Point"}
}