{
  "id": 2569433,
  "type": "Feature",
  "properties": {
    "tgn:hierarchy":[
        "tgn:2569433",
        "tgn:1000001",
        "tgn:7012149",
        "tgn:2000238",
        "tgn:7007158",
        "tgn:7029392"
    ],
    "tgn:id":2569433,
    "tgn:name":"Parmalee and Shoemaker Ditch Number 3",
    "tgn:placetype":[
        "aat:300006075"
    ]
},
  "bbox": [],
  "geometry": {"coordinates":[-105.95,39.0167],"type":"Point"}
}