{
  "id": 2085615,
  "type": "Feature",
  "properties": {
    "tgn:hierarchy":[
        "tgn:2085615",
        "tgn:1000001",
        "tgn:7012149",
        "tgn:2001717",
        "tgn:7007708",
        "tgn:7029392"
    ],
    "tgn:id":2085615,
    "tgn:name":"Tallman",
    "tgn:placetype":[
        "aat:300008347",
        "aat:300387210"
    ]
},
  "bbox": [],
  "geometry": {"coordinates":[-122.9667,44.55],"type":"Point"}
}