{
  "id": 7127451,
  "type": "Feature",
  "properties": {
    "tgn:hierarchy":[
        "tgn:7127451",
        "tgn:7003669",
        "tgn:1000003",
        "tgn:7000084",
        "tgn:7029392"
    ],
    "tgn:id":7127451,
    "tgn:name":"Oberndorf",
    "tgn:placetype":[
        "aat:300008347"
    ]
},
  "bbox": [],
  "geometry": {"coordinates":[13.016667,48.616667],"type":"Point"}
}