{
  "id": 2648691,
  "type": "Feature",
  "properties": {
    "tgn:hierarchy":[
        "tgn:2648691",
        "tgn:1000001",
        "tgn:7012149",
        "tgn:2000180",
        "tgn:7007157",
        "tgn:7029392"
    ],
    "tgn:id":2648691,
    "tgn:name":"Scorpion Creek",
    "tgn:placetype":[
        "aat:300008706"
    ]
},
  "bbox": [],
  "geometry": {"coordinates":[-123.6667,41.4667],"type":"Point"}
}