{
  "id": 2384261,
  "type": "Feature",
  "properties": {
    "tgn:hierarchy":[
        "tgn:2384261",
        "tgn:1000001",
        "tgn:7012149",
        "tgn:7007524",
        "tgn:7029392"
    ],
    "tgn:id":2384261,
    "tgn:name":"Heist Creek",
    "tgn:placetype":[
        "aat:300008706"
    ]
},
  "bbox": [],
  "geometry": {"coordinates":[-107.1333,46.9333],"type":"Point"}
}