{
  "id": 2691547,
  "type": "Feature",
  "properties": {
    "tgn:hierarchy":[
        "tgn:2691547",
        "tgn:1000001",
        "tgn:7012149",
        "tgn:2001244",
        "tgn:7007523",
        "tgn:7029392"
    ],
    "tgn:id":2691547,
    "tgn:name":"Starbuck Lake",
    "tgn:placetype":[
        "aat:300006191"
    ]
},
  "bbox": [],
  "geometry": {"coordinates":[-92.4667,40.3833],"type":"Point"}
}