{
  "id": 7438460,
  "type": "Feature",
  "properties": {
    "tgn:hierarchy":[
        "tgn:7438460",
        "tgn:1000001",
        "tgn:7005595",
        "tgn:7005560",
        "tgn:7029392"
    ],
    "tgn:id":7438460,
    "tgn:name":"Tahuilana",
    "tgn:placetype":[
        "aat:300008347"
    ]
},
  "bbox": [],
  "geometry": {"coordinates":[-108.35,25.65],"type":"Point"}
}