<<<<<<< HEAD
{
  "id": 2768808,
  "type": "Feature",
  "properties": {
    "tgn:hierarchy":[
        "tgn:2768808",
        "tgn:1000001",
        "tgn:2001416",
        "tgn:7012149",
        "tgn:7007526",
        "tgn:7029392"
    ],
    "tgn:id":2768808,
    "tgn:name":"Whitmore Mine",
    "tgn:placetype":[
        "aat:300000390"
    ]
},
  "bbox": [],
  "geometry": {"coordinates":[-114.45,36.9167],"type":"Point"}
}
=======
{"geometry":{"type":"Point","coordinates":[-114.450000,36.916700]},"type":"Feature","properties":{"hierarchy":["tgn:2768808","tgn:1000001","tgn:2001416","tgn:7012149","tgn:7007526","tgn:7029392"],"placetype":["aat:300000390"],"id":2768808,"name:xx":"Whitmore Mine"}}
>>>>>>> 03f74aca74312dbeaf24d7e61306dd6a786dc3d0
