{
  "id": 2500575,
  "type": "Feature",
  "properties": {
    "tgn:hierarchy":[
        "tgn:2500575",
        "tgn:1000001",
        "tgn:7012149",
        "tgn:7007157",
        "tgn:1002972",
        "tgn:7029392"
    ],
    "tgn:id":2500575,
    "tgn:name":"McDonald Peak",
    "tgn:placetype":[
        "aat:300008798"
    ]
},
  "bbox": [],
  "geometry": {"coordinates":[-118.9333,34.6333],"type":"Point"}
}