{
  "id": 2773690,
  "type": "Feature",
  "properties": {
    "tgn:hierarchy":[
        "tgn:2773690",
        "tgn:1000001",
        "tgn:7020676",
        "tgn:7012149",
        "tgn:7007256",
        "tgn:7029392"
    ],
    "tgn:id":2773690,
    "tgn:name":"Willow Bayou",
    "tgn:placetype":[
        "aat:300008699"
    ]
},
  "bbox": [],
  "geometry": {"coordinates":[-93.7333,29.8667],"type":"Point"}
}