<<<<<<< HEAD
{
  "id": 2152810,
  "type": "Feature",
  "properties": {
    "tgn:hierarchy":[
        "tgn:2152810",
        "tgn:1000001",
        "tgn:7012149",
        "tgn:7007255",
        "tgn:7029392"
    ],
    "tgn:id":2152810,
    "tgn:name":"Bays Fork",
    "tgn:placetype":[
        "aat:300008699"
    ]
},
  "bbox": [],
  "geometry": {"coordinates":[-86.1333,36.7],"type":"Point"}
}
=======
{"geometry":{"type":"Point","coordinates":[-86.133300,36.700000]},"type":"Feature","properties":{"hierarchy":["tgn:2152810","tgn:1000001","tgn:7012149","tgn:7007255","tgn:7029392"],"placetype":["aat:300008699"],"id":2152810,"name:xx":"Bays Fork"}}
>>>>>>> 03f74aca74312dbeaf24d7e61306dd6a786dc3d0
