{
  "id": 2038043,
  "type": "Feature",
  "properties": {
    "tgn:hierarchy":[
        "tgn:2038043",
        "tgn:1000001",
        "tgn:7012149",
        "tgn:2000823",
        "tgn:7007255",
        "tgn:7029392"
    ],
    "tgn:id":2038043,
    "tgn:name":"Calvert City",
    "tgn:placetype":[
        "aat:300008347"
    ]
},
  "bbox": [],
  "geometry": {"coordinates":[-88.35,37.0333],"type":"Point"}
}