{
  "id": 7265349,
  "type": "Feature",
  "properties": {
    "tgn:concordances":{
        "gn:id":"2751406"
    },
    "tgn:hierarchy":[
        "tgn:7265349",
        "tgn:7003614",
        "tgn:1000003",
        "tgn:7016845",
        "tgn:7029392"
    ],
    "tgn:id":7265349,
    "tgn:name:nl":"Lubbinge",
    "tgn:placetype":[
        "aat:300008347"
    ]
},
  "bbox": [],
  "geometry": {"coordinates":[6.433333,52.683333],"type":"Point"}
}