{
  "id": 7338000,
  "type": "Feature",
  "properties": {
    "tgn:hierarchy":[
        "tgn:7338000",
        "tgn:7002760",
        "tgn:1000003",
        "tgn:1000095",
        "tgn:7029392"
    ],
    "tgn:id":7338000,
    "tgn:name":"Cerrazo",
    "tgn:placetype":[
        "aat:300008347"
    ]
},
  "bbox": [],
  "geometry": {"coordinates":[-4.116667,43.366667],"type":"Point"}
}