{
  "id": 2770276,
  "type": "Feature",
  "properties": {
    "tgn:hierarchy":[
        "tgn:2770276",
        "tgn:7002659",
        "tgn:1000001",
        "tgn:7012149",
        "tgn:2000044",
        "tgn:7029392"
    ],
    "tgn:id":2770276,
    "tgn:name":"Wild Hog Swamp",
    "tgn:placetype":[
        "aat:300008905"
    ]
},
  "bbox": [],
  "geometry": {"coordinates":[-86.7667,34.6667],"type":"Point"}
}