{
  "id": 2554962,
  "type": "Feature",
  "properties": {
    "tgn:hierarchy":[
        "tgn:2554962",
        "tgn:1000001",
        "tgn:2001629",
        "tgn:7012149",
        "tgn:7007707",
        "tgn:7029392"
    ],
    "tgn:id":2554962,
    "tgn:name":"Oberlin Lake",
    "tgn:placetype":[
        "aat:300008680"
    ]
},
  "bbox": [],
  "geometry": {"coordinates":[-95.85,33.85],"type":"Point"}
}