{
  "id": 7209418,
  "type": "Feature",
  "properties": {
    "tgn:hierarchy":[
        "tgn:7209418",
        "tgn:1000003",
        "tgn:7000094",
        "tgn:7000084",
        "tgn:7029392"
    ],
    "tgn:id":7209418,
    "tgn:name":"Bargensdorf",
    "tgn:placetype":[
        "aat:300008347"
    ]
},
  "bbox": [],
  "geometry": {"coordinates":[13.283333,53.516667],"type":"Point"}
}