{
  "id": 7264457,
  "type": "Feature",
  "properties": {
    "tgn:hierarchy":[
        "tgn:7264457",
        "tgn:7003619",
        "tgn:1000003",
        "tgn:7016845",
        "tgn:7029392"
    ],
    "tgn:id":7264457,
    "tgn:name:nl":"Liesberg",
    "tgn:placetype":[
        "aat:300008777"
    ]
},
  "bbox": [],
  "geometry": {"coordinates":[5.766667,52.316667],"type":"Point"}
}