{
  "id": 2329835,
  "type": "Feature",
  "properties": {
    "tgn:hierarchy":[
        "tgn:2329835",
        "tgn:1000001",
        "tgn:7012149",
        "tgn:1002898",
        "tgn:7007826",
        "tgn:7029392"
    ],
    "tgn:id":2329835,
    "tgn:name":"Flag Bay",
    "tgn:placetype":[
        "aat:300132316"
    ]
},
  "bbox": [],
  "geometry": {"coordinates":[-95.45,32.1833],"type":"Point"}
}