{
  "id": 2109440,
  "type": "Feature",
  "properties": {
    "tgn:hierarchy":[
        "tgn:2109440",
        "tgn:1000001",
        "tgn:2002133",
        "tgn:7012149",
        "tgn:7007828",
        "tgn:7029392"
    ],
    "tgn:id":2109440,
    "tgn:name":"Belvidere Center",
    "tgn:placetype":[
        "aat:300008347"
    ]
},
  "bbox": [],
  "geometry": {"coordinates":[-72.6833,44.75],"type":"Point"}
}