{
  "id": 7458545,
  "type": "Feature",
  "properties": {
    "tgn:hierarchy":[
        "tgn:7458545",
        "tgn:7002443",
        "tgn:1000003",
        "tgn:7008050",
        "tgn:7008591",
        "tgn:7029392"
    ],
    "tgn:id":7458545,
    "tgn:name:en":"New Radnor",
    "tgn:placetype":[
        "aat:300008347"
    ]
},
  "bbox": [],
  "geometry": {"coordinates":[-3.133333,52.25],"type":"Point"}
}