{
  "id": 7463672,
  "type": "Feature",
  "properties": {
    "tgn:hierarchy":[
        "tgn:7463672",
        "tgn:7002444",
        "tgn:1000003",
        "tgn:7019152",
        "tgn:7008591",
        "tgn:7029392"
    ],
    "tgn:id":7463672,
    "tgn:name:en":"Logierait",
    "tgn:placetype":[
        "aat:300008347"
    ]
},
  "bbox": [],
  "geometry": {"coordinates":[-3.683333,56.633333],"type":"Point"}
}