{
  "id": 7346532,
  "type": "Feature",
  "properties": {
    "tgn:hierarchy":[
        "tgn:7346532",
        "tgn:7002826",
        "tgn:7001158",
        "tgn:1000003",
        "tgn:1000095",
        "tgn:7029392"
    ],
    "tgn:id":7346532,
    "tgn:name":"B\u00e1rcena de la Abad\u00eda",
    "tgn:placetype":[
        "aat:300008347"
    ]
},
  "bbox": [],
  "geometry": {"coordinates":[-6.633333,42.783333],"type":"Point"}
}