{
  "id": 1084489,
  "type": "Feature",
  "properties": {
    "tgn:hierarchy":[
        "tgn:1084489",
        "tgn:1000004",
        "tgn:7000373",
        "tgn:1000135",
        "tgn:7029392"
    ],
    "tgn:id":1084489,
    "tgn:name":"Navotas",
    "tgn:placetype":[
        "aat:300008347",
        "aat:300265612",
        "aat:300008375",
        "aat:300387249"
    ]
},
  "bbox": [],
  "geometry": {"coordinates":[120.95,14.65],"type":"Point"}
}