<<<<<<< HEAD
{
  "id": 7377905,
  "type": "Feature",
  "properties": {
    "tgn:hierarchy":[
        "tgn:7377905",
        "tgn:7005586",
        "tgn:1000001",
        "tgn:7005560",
        "tgn:7029392"
    ],
    "tgn:id":7377905,
    "tgn:name":"Las Cebollas",
    "tgn:placetype":[
        "aat:300008347"
    ]
},
  "bbox": [],
  "geometry": {"coordinates":[-103.166667,20.083333],"type":"Point"}
}
=======
{"geometry":{"type":"Point","coordinates":[-103.166667,20.083333]},"type":"Feature","properties":{"hierarchy":["tgn:7377905","tgn:7005586","tgn:1000001","tgn:7005560","tgn:7029392"],"placetype":["aat:300008347"],"id":7377905,"name:xx":"Las Cebollas"}}
>>>>>>> 03f74aca74312dbeaf24d7e61306dd6a786dc3d0
