{
  "id": 2749803,
  "type": "Feature",
  "properties": {
    "tgn:hierarchy":[
        "tgn:2749803",
        "tgn:1000001",
        "tgn:7012149",
        "tgn:2002264",
        "tgn:7013961",
        "tgn:7029392"
    ],
    "tgn:id":2749803,
    "tgn:name":"Walnut Knob",
    "tgn:placetype":[
        "aat:300008798"
    ]
},
  "bbox": [],
  "geometry": {"coordinates":[-80.75,38.0333],"type":"Point"}
}