{
  "id": 7133787,
  "type": "Feature",
  "properties": {
    "tgn:hierarchy":[
        "tgn:7133787",
        "tgn:1000003",
        "tgn:7000094",
        "tgn:7000084",
        "tgn:7029392"
    ],
    "tgn:id":7133787,
    "tgn:name":"Bahnhof Neddemin",
    "tgn:placetype":[
        "aat:300007783"
    ]
},
  "bbox": [],
  "geometry": {"coordinates":[13.263333,53.634167],"type":"Point"}
}