{
  "id": 2593729,
  "type": "Feature",
  "properties": {
    "tgn:hierarchy":[
        "tgn:2593729",
        "tgn:1000001",
        "tgn:7012149",
        "tgn:2000481",
        "tgn:7007250",
        "tgn:7029392"
    ],
    "tgn:id":2593729,
    "tgn:name":"Porphyry Creek",
    "tgn:placetype":[
        "aat:300008706"
    ]
},
  "bbox": [],
  "geometry": {"coordinates":[-114.4333,45.0667],"type":"Point"}
}