{
  "id": 7293248,
  "type": "Feature",
  "properties": {
    "tgn:hierarchy":[
        "tgn:7293248",
        "tgn:7002758",
        "tgn:7002823",
        "tgn:1000003",
        "tgn:1000095",
        "tgn:7029392"
    ],
    "tgn:id":7293248,
    "tgn:name":"Casa de Cabezarrasa",
    "tgn:placetype":[
        "aat:300005433"
    ]
},
  "bbox": [],
  "geometry": {"coordinates":[-6.400556,37.207222],"type":"Point"}
}