{
  "id": 7446289,
  "type": "Feature",
  "properties": {
    "tgn:hierarchy":[
        "tgn:7446289",
        "tgn:7002444",
        "tgn:1000003",
        "tgn:7009907",
        "tgn:7008591",
        "tgn:7029392"
    ],
    "tgn:id":7446289,
    "tgn:name:en":"Stromness Taing",
    "tgn:placetype":[
        "aat:300386846"
    ]
},
  "bbox": [],
  "geometry": {"coordinates":[-2.966667,59.116667],"type":"Point"}
}