<<<<<<< HEAD
{
  "id": 2404840,
  "type": "Feature",
  "properties": {
    "tgn:hierarchy":[
        "tgn:2404840",
        "tgn:1000001",
        "tgn:7012149",
        "tgn:2000818",
        "tgn:7007255",
        "tgn:7029392"
    ],
    "tgn:id":2404840,
    "tgn:name":"Huckleberry Ridge",
    "tgn:placetype":[
        "aat:300266640"
    ]
},
  "bbox": [],
  "geometry": {"coordinates":[-84.6833,36.6833],"type":"Point"}
}
=======
{"geometry":{"type":"Point","coordinates":[-84.683300,36.683300]},"type":"Feature","properties":{"hierarchy":["tgn:2404840","tgn:1000001","tgn:7012149","tgn:2000818","tgn:7007255","tgn:7029392"],"placetype":["aat:300266640"],"id":2404840,"name:xx":"Huckleberry Ridge"}}
>>>>>>> 03f74aca74312dbeaf24d7e61306dd6a786dc3d0
