{
  "id": 7146198,
  "type": "Feature",
  "properties": {
    "tgn:hierarchy":[
        "tgn:7146198",
        "tgn:1000003",
        "tgn:7003682",
        "tgn:7000084",
        "tgn:7029392"
    ],
    "tgn:id":7146198,
    "tgn:name":"F\u00f6rsterei Kolbenstein",
    "tgn:placetype":[
        "aat:300004792"
    ]
},
  "bbox": [],
  "geometry": {"coordinates":[7.583333,50.183333],"type":"Point"}
}