<<<<<<< HEAD
{
  "id": 2761776,
  "type": "Feature",
  "properties": {
    "tgn:hierarchy":[
        "tgn:2761776",
        "tgn:1000001",
        "tgn:7012149",
        "tgn:2001284",
        "tgn:7007524",
        "tgn:7029392"
    ],
    "tgn:id":2761776,
    "tgn:name":"West Prong Dearborn River",
    "tgn:placetype":[
        "aat:300008707"
    ]
},
  "bbox": [],
  "geometry": {"coordinates":[-112.35,47.0667],"type":"Point"}
}
=======
{"geometry":{"type":"Point","coordinates":[-112.350000,47.066700]},"type":"Feature","properties":{"hierarchy":["tgn:2761776","tgn:1000001","tgn:7012149","tgn:2001284","tgn:7007524","tgn:7029392"],"placetype":["aat:300008707"],"id":2761776,"name:xx":"West Prong Dearborn River"}}
>>>>>>> 03f74aca74312dbeaf24d7e61306dd6a786dc3d0
