{
  "id": 2761776,
  "type": "Feature",
  "properties": {
    "tgn:hierarchy":[
        "tgn:2761776",
        "tgn:1000001",
        "tgn:7012149",
        "tgn:2001284",
        "tgn:7007524",
        "tgn:7029392"
    ],
    "tgn:id":2761776,
    "tgn:name":"West Prong Dearborn River",
    "tgn:placetype":[
        "aat:300008707"
    ]
},
  "bbox": [],
  "geometry": {"coordinates":[-112.35,47.0667],"type":"Point"}
}