{
  "id": 2175005,
  "type": "Feature",
  "properties": {
    "tgn:hierarchy":[
        "tgn:2175005",
        "tgn:1000001",
        "tgn:7020676",
        "tgn:7012149",
        "tgn:7007256",
        "tgn:7029392"
    ],
    "tgn:id":2175005,
    "tgn:name":"Black Bayou Cutoff",
    "tgn:placetype":[
        "aat:300006075"
    ]
},
  "bbox": [],
  "geometry": {"coordinates":[-93.6167,30.0333],"type":"Point"}
}