{
  "id": 2199753,
  "type": "Feature",
  "properties": {
    "tgn:hierarchy":[
        "tgn:2199753",
        "tgn:1000001",
        "tgn:7012149",
        "tgn:2001898",
        "tgn:7007825",
        "tgn:7029392"
    ],
    "tgn:id":2199753,
    "tgn:name":"Brush Mountain",
    "tgn:placetype":[
        "aat:300266640"
    ]
},
  "bbox": [],
  "geometry": {"coordinates":[-84.0333,35.3667],"type":"Point"}
}