{
  "id": 2394414,
  "type": "Feature",
  "properties": {
    "tgn:hierarchy":[
        "tgn:2394414",
        "tgn:1000001",
        "tgn:7012149",
        "tgn:2001683",
        "tgn:7007707",
        "tgn:7029392"
    ],
    "tgn:id":2394414,
    "tgn:name":"Hogeye Hollow",
    "tgn:placetype":[
        "aat:300008761"
    ]
},
  "bbox": [],
  "geometry": {"coordinates":[-95.6667,34.65],"type":"Point"}
}