{
  "id": 2284754,
  "type": "Feature",
  "properties": {
    "tgn:hierarchy":[
        "tgn:2284754",
        "tgn:1000001",
        "tgn:7012149",
        "tgn:1002871",
        "tgn:7007568",
        "tgn:7029392"
    ],
    "tgn:id":2284754,
    "tgn:name":"Desolation, Lake",
    "tgn:placetype":[
        "aat:300008680"
    ]
},
  "bbox": [],
  "geometry": {"coordinates":[-73.9667,43.1333],"type":"Point"}
}