{
  "id": 2209303,
  "type": "Feature",
  "properties": {
    "tgn:hierarchy":[
        "tgn:2209303",
        "tgn:1000001",
        "tgn:7012149",
        "tgn:7007157",
        "tgn:1002608",
        "tgn:7029392"
    ],
    "tgn:id":2209303,
    "tgn:name":"Burnt Peak Canyon",
    "tgn:placetype":[
        "aat:300008761"
    ]
},
  "bbox": [],
  "geometry": {"coordinates":[-118.5333,34.6667],"type":"Point"}
}