{
  "id": 2151490,
  "type": "Feature",
  "properties": {
    "tgn:hierarchy":[
        "tgn:2151490",
        "tgn:1000001",
        "tgn:7012149",
        "tgn:2002290",
        "tgn:7013961",
        "tgn:7029392"
    ],
    "tgn:id":2151490,
    "tgn:name":"Batoff Mountain",
    "tgn:placetype":[
        "aat:300008798"
    ]
},
  "bbox": [],
  "geometry": {"coordinates":[-81.15,37.8333],"type":"Point"}
}