{
  "id": 7513000,
  "type": "Feature",
  "properties": {
    "tgn:hierarchy":[
        "tgn:7513000",
        "tgn:1008380",
        "tgn:1000226",
        "tgn:7018426",
        "tgn:1000006",
        "tgn:7029392"
    ],
    "tgn:id":7513000,
    "tgn:name:en":"Harihari Beach",
    "tgn:placetype":[
        "aat:300008816"
    ]
},
  "bbox": [],
  "geometry": {"coordinates":[174.716667,-38.216667],"type":"Point"}
}