{
  "id": 7311491,
  "type": "Feature",
  "properties": {
    "tgn:hierarchy":[
        "tgn:7311491",
        "tgn:1001637",
        "tgn:1000049",
        "tgn:1000002",
        "tgn:7029392"
    ],
    "tgn:id":7311491,
    "tgn:name":"Locobe",
    "tgn:placetype":[
        "aat:300000206"
    ]
},
  "bbox": [],
  "geometry": {"coordinates":[-73.55,-37.383333],"type":"Point"}
}