{
  "id": 2328427,
  "type": "Feature",
  "properties": {
    "tgn:hierarchy":[
        "tgn:2328427",
        "tgn:1000001",
        "tgn:7012149",
        "tgn:1002747",
        "tgn:7007568",
        "tgn:7029392"
    ],
    "tgn:id":2328427,
    "tgn:name":"Fisher Gully",
    "tgn:placetype":[
        "aat:300008761"
    ]
},
  "bbox": [],
  "geometry": {"coordinates":[-77.2833,42.75],"type":"Point"}
}