{
  "id": 1079086,
  "type": "Feature",
  "properties": {
    "tgn:hierarchy":[
        "tgn:1079086",
        "tgn:1000004",
        "tgn:7001282",
        "tgn:7000231",
        "tgn:7029392"
    ],
    "tgn:id":1079086,
    "tgn:name":"Fas\u0101",
    "tgn:placetype":[
        "aat:300008347"
    ]
},
  "bbox": [],
  "geometry": {"coordinates":[53.9833,28.9167],"type":"Point"}
}