{
  "id": 7417316,
  "type": "Feature",
  "properties": {
    "tgn:hierarchy":[
        "tgn:7417316",
        "tgn:1000001",
        "tgn:7005591",
        "tgn:7005560",
        "tgn:7029392"
    ],
    "tgn:id":7417316,
    "tgn:name:es":"Piedra de Amolar",
    "tgn:placetype":[
        "aat:300008347"
    ]
},
  "bbox": [],
  "geometry": {"coordinates":[-96.454167,18.125],"type":"Point"}
}