{
  "id": 1074540,
  "type": "Feature",
  "properties": {
    "tgn:hierarchy":[
        "tgn:1074540",
        "tgn:1000004",
        "tgn:7000198",
        "tgn:7016788",
        "tgn:7029392"
    ],
    "tgn:id":1074540,
    "tgn:name:en":"B\u0101nsw\u0101ra",
    "tgn:placetype":[
        "aat:300008347"
    ]
},
  "bbox": [],
  "geometry": {"coordinates":[74.446063,23.549915],"type":"Point"}
}