{
  "id": 2024528,
  "type": "Feature",
  "properties": {
    "tgn:hierarchy":[
        "tgn:2024528",
        "tgn:1000001",
        "tgn:2000315",
        "tgn:7012149",
        "tgn:7007248",
        "tgn:7029392"
    ],
    "tgn:id":2024528,
    "tgn:name":"Toledo",
    "tgn:placetype":[
        "aat:300008347",
        "aat:300387210"
    ]
},
  "bbox": [],
  "geometry": {"coordinates":[-82.05,30.6333],"type":"Point"}
}