{
  "id": 1098894,
  "type": "Feature",
  "properties": {
    "tgn:hierarchy":[
        "tgn:1098894",
        "tgn:1009227",
        "tgn:1000226",
        "tgn:7520095",
        "tgn:1000006",
        "tgn:7029392"
    ],
    "tgn:id":1098894,
    "tgn:name:en":"Collingwood",
    "tgn:placetype":[
        "aat:300008347"
    ]
},
  "bbox": [],
  "geometry": {"coordinates":[172.683333,-40.666667],"type":"Point"}
}