{
  "id": 2281877,
  "type": "Feature",
  "properties": {
    "tgn:hierarchy":[
        "tgn:2281877",
        "tgn:1000001",
        "tgn:7012149",
        "tgn:7007157",
        "tgn:1002710",
        "tgn:7029392"
    ],
    "tgn:id":2281877,
    "tgn:name":"Deer Creek Ditch",
    "tgn:placetype":[
        "aat:300006075"
    ]
},
  "bbox": [],
  "geometry": {"coordinates":[-121.05,39.25],"type":"Point"}
}