<<<<<<< HEAD
{
  "id": 2405354,
  "type": "Feature",
  "properties": {
    "tgn:hierarchy":[
        "tgn:2405354",
        "tgn:1000001",
        "tgn:7012149",
        "tgn:2002088",
        "tgn:7007826",
        "tgn:7029392"
    ],
    "tgn:id":2405354,
    "tgn:name":"Huffstudler Canyon",
    "tgn:placetype":[
        "aat:300008761"
    ]
},
  "bbox": [],
  "geometry": {"coordinates":[-101.1167,29.9833],"type":"Point"}
}
=======
{"geometry":{"type":"Point","coordinates":[-101.116700,29.983300]},"type":"Feature","properties":{"hierarchy":["tgn:2405354","tgn:1000001","tgn:7012149","tgn:2002088","tgn:7007826","tgn:7029392"],"placetype":["aat:300008761"],"id":2405354,"name:xx":"Huffstudler Canyon"}}
>>>>>>> 03f74aca74312dbeaf24d7e61306dd6a786dc3d0
