{
  "id": 2320565,
  "type": "Feature",
  "properties": {
    "tgn:hierarchy":[
        "tgn:2320565",
        "tgn:1000001",
        "tgn:2001429",
        "tgn:7012149",
        "tgn:7007566",
        "tgn:7029392"
    ],
    "tgn:id":2320565,
    "tgn:name":"Ewe Canyon Tank",
    "tgn:placetype":[
        "aat:300006191"
    ]
},
  "bbox": [],
  "geometry": {"coordinates":[-108.5167,33.4833],"type":"Point"}
}