{
  "id": 7087422,
  "type": "Feature",
  "properties": {
    "tgn:hierarchy":[
        "tgn:7087422",
        "tgn:1000003",
        "tgn:7003687",
        "tgn:7000084",
        "tgn:7029392"
    ],
    "tgn:id":7087422,
    "tgn:name":"Wanneweh",
    "tgn:placetype":[
        "aat:300008699"
    ]
},
  "bbox": [],
  "geometry": {"coordinates":[11.316667,52.383333],"type":"Point"}
}