{
  "id": 7226496,
  "type": "Feature",
  "properties": {
    "tgn:hierarchy":[
        "tgn:7226496",
        "tgn:7011167",
        "tgn:7001338",
        "tgn:1000003",
        "tgn:1000074",
        "tgn:7029392"
    ],
    "tgn:id":7226496,
    "tgn:name":"Sof\u00eda, Nis\u00edda",
    "tgn:placetype":[
        "aat:300008791"
    ]
},
  "bbox": [],
  "geometry": {"coordinates":[21.0025,38.480833],"type":"Point"}
}