{
  "id": 2706247,
  "type": "Feature",
  "properties": {
    "tgn:hierarchy":[
        "tgn:2706247",
        "tgn:1000001",
        "tgn:7012149",
        "tgn:2001876",
        "tgn:7007825",
        "tgn:7029392"
    ],
    "tgn:id":2706247,
    "tgn:name":"Swamp Creek",
    "tgn:placetype":[
        "aat:300008706"
    ]
},
  "bbox": [],
  "geometry": {"coordinates":[-88.1667,36.3667],"type":"Point"}
}