{
  "id": 2651284,
  "type": "Feature",
  "properties": {
    "tgn:hierarchy":[
        "tgn:2651284",
        "tgn:1000001",
        "tgn:7016172",
        "tgn:7012149",
        "tgn:2000175",
        "tgn:7029392"
    ],
    "tgn:id":2651284,
    "tgn:name":"Section Hollow",
    "tgn:placetype":[
        "aat:300008761"
    ]
},
  "bbox": [],
  "geometry": {"coordinates":[-92.6167,35.7667],"type":"Point"}
}