{
  "id": 1133008,
  "type": "Feature",
  "properties": {
    "tgn:hierarchy":[
        "tgn:1133008",
        "tgn:1000001",
        "tgn:7012149",
        "tgn:7007826",
        "tgn:7029392"
    ],
    "tgn:id":1133008,
    "tgn:name":"Davidson Creek",
    "tgn:placetype":[
        "aat:300008706"
    ]
},
  "bbox": [],
  "geometry": {"coordinates":[-96.8833,30.65],"type":"Point"}
}