{
  "id": 7495697,
  "type": "Feature",
  "properties": {
    "tgn:hierarchy":[
        "tgn:7495697",
        "tgn:1000004",
        "tgn:7491221",
        "tgn:1000141",
        "tgn:7029392"
    ],
    "tgn:id":7495697,
    "tgn:name":"Baxiandong",
    "tgn:placetype":[
        "aat:300008347"
    ]
},
  "bbox": [],
  "geometry": {"coordinates":[121.478412,23.397317],"type":"Point"}
}