{
  "id": 2448117,
  "type": "Feature",
  "properties": {
    "tgn:hierarchy":[
        "tgn:2448117",
        "tgn:1000001",
        "tgn:7012149",
        "tgn:2000491",
        "tgn:7007250",
        "tgn:7029392"
    ],
    "tgn:id":2448117,
    "tgn:name":"Lightner Draw",
    "tgn:placetype":[
        "aat:300008761"
    ]
},
  "bbox": [],
  "geometry": {"coordinates":[-116.2333,47.6333],"type":"Point"}
}