{
  "id": 7591546,
  "type": "Feature",
  "properties": {
    "tgn:hierarchy":[
        "tgn:7591546",
        "tgn:1000004",
        "tgn:7000198",
        "tgn:7000799",
        "tgn:7029392"
    ],
    "tgn:id":7591546,
    "tgn:name:en":"N\u0101dir",
    "tgn:placetype":[
        "aat:300008347"
    ]
},
  "bbox": [],
  "geometry": {"coordinates":[75.013889,34.527778],"type":"Point"}
}