{
  "id": 7414348,
  "type": "Feature",
  "properties": {
    "tgn:hierarchy":[
        "tgn:7414348",
        "tgn:1000001",
        "tgn:7005596",
        "tgn:7005560",
        "tgn:7029392"
    ],
    "tgn:id":7414348,
    "tgn:name:es":"San Felipe",
    "tgn:placetype":[
        "aat:300008347"
    ]
},
  "bbox": [],
  "geometry": {"coordinates":[-91.716667,17.8625],"type":"Point"}
}