{
  "id": 2454732,
  "type": "Feature",
  "properties": {
    "tgn:hierarchy":[
        "tgn:2454732",
        "tgn:1000001",
        "tgn:2000315",
        "tgn:7012149",
        "tgn:7007248",
        "tgn:7029392"
    ],
    "tgn:id":2454732,
    "tgn:name":"Little Double Lakes",
    "tgn:placetype":[
        "aat:300008680"
    ]
},
  "bbox": [],
  "geometry": {"coordinates":[-82.15,30.8667],"type":"Point"}
}