<<<<<<< HEAD
{
  "id": 2403988,
  "type": "Feature",
  "properties": {
    "tgn:hierarchy":[
        "tgn:2403988",
        "tgn:1000001",
        "tgn:7012149",
        "tgn:1002889",
        "tgn:7007706",
        "tgn:7029392"
    ],
    "tgn:id":2403988,
    "tgn:name":"Howell Ditch",
    "tgn:placetype":[
        "aat:300006075"
    ]
},
  "bbox": [],
  "geometry": {"coordinates":[-84.05,40.3833],"type":"Point"}
}
=======
{"geometry":{"type":"Point","coordinates":[-84.050000,40.383300]},"type":"Feature","properties":{"hierarchy":["tgn:2403988","tgn:1000001","tgn:7012149","tgn:1002889","tgn:7007706","tgn:7029392"],"placetype":["aat:300006075"],"id":2403988,"name:xx":"Howell Ditch"}}
>>>>>>> 03f74aca74312dbeaf24d7e61306dd6a786dc3d0
