{
  "id": 7536045,
  "type": "Feature",
  "properties": {
    "tgn:hierarchy":[
        "tgn:7536045",
        "tgn:7001242",
        "tgn:7016833",
        "tgn:1001335",
        "tgn:7029392"
    ],
    "tgn:id":7536045,
    "tgn:name:en":"Al Mansh\u012byah",
    "tgn:placetype":[
        "aat:300008347"
    ]
},
  "bbox": [],
  "geometry": {"coordinates":[30.908321,31.05306],"type":"Point"}
}