{
  "id": 7550939,
  "type": "Feature",
  "properties": {
    "tgn:hierarchy":[
        "tgn:7550939",
        "tgn:1000004",
        "tgn:7000198",
        "tgn:1001894",
        "tgn:7029392"
    ],
    "tgn:id":7550939,
    "tgn:name:en":"Chau Mahla",
    "tgn:placetype":[
        "aat:300007783"
    ]
},
  "bbox": [],
  "geometry": {"coordinates":[75.60085,23.948567],"type":"Point"}
}