{
  "id": 7254958,
  "type": "Feature",
  "properties": {
    "tgn:hierarchy":[
        "tgn:7254958",
        "tgn:1000003",
        "tgn:1000063",
        "tgn:7029392"
    ],
    "tgn:id":7254958,
    "tgn:name":"Steenvoordebeek",
    "tgn:placetype":[
        "aat:300008699"
    ]
},
  "bbox": [],
  "geometry": {"coordinates":[2.613634,50.858138],"type":"Point"}
}