{
  "id": 7323228,
  "type": "Feature",
  "properties": {
    "tgn:hierarchy":[
        "tgn:7323228",
        "tgn:7002760",
        "tgn:1000003",
        "tgn:1000095",
        "tgn:7029392"
    ],
    "tgn:id":7323228,
    "tgn:name":"R\u00edolastras",
    "tgn:placetype":[
        "aat:300008347"
    ]
},
  "bbox": [],
  "geometry": {"coordinates":[-3.55,43.383333],"type":"Point"}
}