{
  "id": 2486656,
  "type": "Feature",
  "properties": {
    "tgn:hierarchy":[
        "tgn:2486656",
        "tgn:7006450",
        "tgn:1000001",
        "tgn:7012149",
        "tgn:2000088",
        "tgn:7029392"
    ],
    "tgn:id":2486656,
    "tgn:name":"Ledge Lake",
    "tgn:placetype":[
        "aat:300008680"
    ]
},
  "bbox": [],
  "geometry": {"coordinates":[-134.2667,56.8833],"type":"Point"}
}