{
  "id": 2710888,
  "type": "Feature",
  "properties": {
    "tgn:hierarchy":[
        "tgn:2710888",
        "tgn:1000001",
        "tgn:2000198",
        "tgn:7012149",
        "tgn:7007158",
        "tgn:7029392"
    ],
    "tgn:id":2710888,
    "tgn:name":"Tanima Peak",
    "tgn:placetype":[
        "aat:300008798"
    ]
},
  "bbox": [],
  "geometry": {"coordinates":[-105.65,40.2167],"type":"Point"}
}