{
  "id": 7497439,
  "type": "Feature",
  "properties": {
    "tgn:hierarchy":[
        "tgn:7497439",
        "tgn:1000004",
        "tgn:7001009",
        "tgn:1000141",
        "tgn:7029392"
    ],
    "tgn:id":7497439,
    "tgn:name":"Baoxiang Qiao",
    "tgn:placetype":[
        "aat:300007836"
    ]
},
  "bbox": [],
  "geometry": {"coordinates":[120.680835,24.207792],"type":"Point"}
}