{
  "id": 1121942,
  "type": "Feature",
  "properties": {
    "tgn:hierarchy":[
        "tgn:1121942",
        "tgn:7001242",
        "tgn:7029392"
    ],
    "tgn:id":1121942,
    "tgn:name":"Bissigh, Lach",
    "tgn:placetype":[
        "aat:300008707"
    ]
},
  "bbox": [],
  "geometry": {"coordinates":[41.55,0.75],"type":"Point"}
}