{
  "id": 7514267,
  "type": "Feature",
  "properties": {
    "tgn:hierarchy":[
        "tgn:7514267",
        "tgn:1009227",
        "tgn:1000226",
        "tgn:7016729",
        "tgn:1000006",
        "tgn:7029392"
    ],
    "tgn:id":7514267,
    "tgn:name:en":"East Bay",
    "tgn:placetype":[
        "aat:300132316"
    ]
},
  "bbox": [],
  "geometry": {"coordinates":[174.133333,-41.233333],"type":"Point"}
}