{
  "id": 7492996,
  "type": "Feature",
  "properties": {
    "tgn:hierarchy":[
        "tgn:7492996",
        "tgn:1000004",
        "tgn:7491221",
        "tgn:1000141",
        "tgn:7029392"
    ],
    "tgn:id":7492996,
    "tgn:name":"Dapo Chi",
    "tgn:placetype":[
        "aat:300008680"
    ]
},
  "bbox": [],
  "geometry": {"coordinates":[121.225,23.118611],"type":"Point"}
}