{
  "id": 2378092,
  "type": "Feature",
  "properties": {
    "tgn:hierarchy":[
        "tgn:2378092",
        "tgn:1000001",
        "tgn:7012149",
        "tgn:1002357",
        "tgn:7007706",
        "tgn:7029392"
    ],
    "tgn:id":2378092,
    "tgn:name":"Harris Ditch",
    "tgn:placetype":[
        "aat:300006075"
    ]
},
  "bbox": [],
  "geometry": {"coordinates":[-82.6167,41.35],"type":"Point"}
}