{
  "id": 2595890,
  "type": "Feature",
  "properties": {
    "tgn:hierarchy":[
        "tgn:2595890",
        "tgn:1000001",
        "tgn:7012149",
        "tgn:1002760",
        "tgn:7007520",
        "tgn:7029392"
    ],
    "tgn:id":2595890,
    "tgn:name":"Pottawattomie Bayou",
    "tgn:placetype":[
        "aat:300132316"
    ]
},
  "bbox": [],
  "geometry": {"coordinates":[-86.1667,43.0167],"type":"Point"}
}