{
  "id": 2079853,
  "type": "Feature",
  "properties": {
    "tgn:hierarchy":[
        "tgn:2079853",
        "tgn:1000001",
        "tgn:7012149",
        "tgn:1003025",
        "tgn:7007706",
        "tgn:7029392"
    ],
    "tgn:id":2079853,
    "tgn:name":"Hallock",
    "tgn:placetype":[
        "aat:300008347"
    ]
},
  "bbox": [],
  "geometry": {"coordinates":[-84.55,41.5167],"type":"Point"}
}