{
  "id": 7367585,
  "type": "Feature",
  "properties": {
    "tgn:hierarchy":[
        "tgn:7367585",
        "tgn:7005580",
        "tgn:1000001",
        "tgn:7005560",
        "tgn:7029392"
    ],
    "tgn:id":7367585,
    "tgn:name":"Eureka",
    "tgn:placetype":[
        "aat:300008347"
    ]
},
  "bbox": [],
  "geometry": {"coordinates":[-92.116667,15.05],"type":"Point"}
}