<<<<<<< HEAD
{
  "id": 7177822,
  "type": "Feature",
  "properties": {
    "tgn:hierarchy":[
        "tgn:7177822",
        "tgn:7003692",
        "tgn:1000003",
        "tgn:7000084",
        "tgn:7029392"
    ],
    "tgn:id":7177822,
    "tgn:name":"Hainsterbach",
    "tgn:placetype":[
        "aat:300008699"
    ]
},
  "bbox": [],
  "geometry": {"coordinates":[9.316667,49.533333],"type":"Point"}
}
=======
{"geometry":{"type":"Point","coordinates":[9.316667,49.533333]},"type":"Feature","properties":{"hierarchy":["tgn:7177822","tgn:7003692","tgn:1000003","tgn:7000084","tgn:7029392"],"placetype":["aat:300008699"],"id":7177822,"name:xx":"Hainsterbach"}}
>>>>>>> 03f74aca74312dbeaf24d7e61306dd6a786dc3d0
