{
  "id": 2753741,
  "type": "Feature",
  "properties": {
    "tgn:hierarchy":[
        "tgn:2753741",
        "tgn:1000001",
        "tgn:7016172",
        "tgn:7012149",
        "tgn:2000177",
        "tgn:7029392"
    ],
    "tgn:id":2753741,
    "tgn:name":"Watkins Brake",
    "tgn:placetype":[
        "aat:300008905"
    ]
},
  "bbox": [],
  "geometry": {"coordinates":[-91.55,35.0833],"type":"Point"}
}