{
  "id": 2147106,
  "type": "Feature",
  "properties": {
    "tgn:hierarchy":[
        "tgn:2147106",
        "tgn:1000001",
        "tgn:7012149",
        "tgn:7007248",
        "tgn:7029392"
    ],
    "tgn:id":2147106,
    "tgn:name":"Baptist Creek",
    "tgn:placetype":[
        "aat:300008706"
    ]
},
  "bbox": [],
  "geometry": {"coordinates":[-83.8833,32.4167],"type":"Point"}
}