{
  "id": 7594088,
  "type": "Feature",
  "properties": {
    "tgn:hierarchy":[
        "tgn:7594088",
        "tgn:1003500",
        "tgn:1000003",
        "tgn:7010380",
        "tgn:1000080",
        "tgn:7029392"
    ],
    "tgn:id":7594088,
    "tgn:name":"San Pietro in Bevagna",
    "tgn:placetype":[
        "aat:300008347"
    ]
},
  "bbox": [],
  "geometry": {"coordinates":[17.672497,40.306561],"type":"Point"}
}