{
  "id": 1138456,
  "type": "Feature",
  "properties": {
    "tgn:hierarchy":[
        "tgn:1138456",
        "tgn:1000004",
        "tgn:7011589",
        "tgn:7018214",
        "tgn:7002435",
        "tgn:7029392"
    ],
    "tgn:id":1138456,
    "tgn:name":"Stud'onoje",
    "tgn:placetype":[
        "aat:300008347"
    ]
},
  "bbox": [],
  "geometry": {"coordinates":[77.5167,53.6167],"type":"Point"}
}