{
  "id": 7021101,
  "type": "Feature",
  "properties": {
    "tgn:hierarchy":[
        "tgn:7021101",
        "tgn:1000001",
        "tgn:2001013",
        "tgn:7012149",
        "tgn:7007521",
        "tgn:7029392"
    ],
    "tgn:id":7021101,
    "tgn:name":"Waptus Lake",
    "tgn:placetype":[
        "aat:300008680"
    ]
},
  "bbox": [],
  "geometry": {"coordinates":[-95.4333,47.25],"type":"Point"}
}