{
  "id": 7183094,
  "type": "Feature",
  "properties": {
    "tgn:hierarchy":[
        "tgn:7183094",
        "tgn:1000003",
        "tgn:7003682",
        "tgn:7000084",
        "tgn:7029392"
    ],
    "tgn:id":7183094,
    "tgn:name":"F\u00fcllenbacherhof",
    "tgn:placetype":[
        "aat:300000206"
    ]
},
  "bbox": [],
  "geometry": {"coordinates":[7.75,49.95],"type":"Point"}
}