{
  "id": 7493230,
  "type": "Feature",
  "properties": {
    "tgn:hierarchy":[
        "tgn:7493230",
        "tgn:1000004",
        "tgn:7492971",
        "tgn:1000141",
        "tgn:7029392"
    ],
    "tgn:id":7493230,
    "tgn:name":"Xinnanshi Tifang",
    "tgn:placetype":[
        "aat:300006156"
    ]
},
  "bbox": [],
  "geometry": {"coordinates":[120.572057,22.776696],"type":"Point"}
}