{
  "id": 7563447,
  "type": "Feature",
  "properties": {
    "tgn:hierarchy":[
        "tgn:7563447",
        "tgn:1000004",
        "tgn:7000198",
        "tgn:7016788",
        "tgn:7029392"
    ],
    "tgn:id":7563447,
    "tgn:name:en":"Binj\u0101sar",
    "tgn:placetype":[
        "aat:300008347"
    ]
},
  "bbox": [],
  "geometry": {"coordinates":[74.268594,28.808547],"type":"Point"}
}