{
  "id": 2604429,
  "type": "Feature",
  "properties": {
    "tgn:hierarchy":[
        "tgn:2604429",
        "tgn:1000001",
        "tgn:2001638",
        "tgn:7012149",
        "tgn:7007707",
        "tgn:7029392"
    ],
    "tgn:id":2604429,
    "tgn:name":"Rabbit Hill",
    "tgn:placetype":[
        "aat:300008798"
    ]
},
  "bbox": [],
  "geometry": {"coordinates":[-98.45,34.7167],"type":"Point"}
}