{
  "id": 7297122,
  "type": "Feature",
  "properties": {
    "tgn:hierarchy":[
        "tgn:7297122",
        "tgn:7002811",
        "tgn:1000003",
        "tgn:7003837",
        "tgn:1000095",
        "tgn:7029392"
    ],
    "tgn:id":7297122,
    "tgn:name":"Tartamu\u00f1a, Puerto de",
    "tgn:placetype":[
        "aat:300259572"
    ]
},
  "bbox": [],
  "geometry": {"coordinates":[-6.383333,40.233333],"type":"Point"}
}