<<<<<<< HEAD
{
  "id": 2766906,
  "type": "Feature",
  "properties": {
    "tgn:hierarchy":[
        "tgn:2766906",
        "tgn:1000001",
        "tgn:2001737",
        "tgn:7012149",
        "tgn:7007712",
        "tgn:7029392"
    ],
    "tgn:id":2766906,
    "tgn:name":"White Plains",
    "tgn:placetype":[
        "aat:300008347"
    ]
},
  "bbox": [],
  "geometry": {"coordinates":[-80.4167,34.7],"type":"Point"}
}
=======
{"geometry":{"type":"Point","coordinates":[-80.416700,34.700000]},"type":"Feature","properties":{"hierarchy":["tgn:2766906","tgn:1000001","tgn:2001737","tgn:7012149","tgn:7007712","tgn:7029392"],"placetype":["aat:300008347"],"id":2766906,"name:xx":"White Plains"}}
>>>>>>> 03f74aca74312dbeaf24d7e61306dd6a786dc3d0
