{
  "id": 2664505,
  "type": "Feature",
  "properties": {
    "tgn:hierarchy":[
        "tgn:2664505",
        "tgn:1000001",
        "tgn:7012149",
        "tgn:7014510",
        "tgn:7007920",
        "tgn:7029392"
    ],
    "tgn:id":2664505,
    "tgn:name":"Similk Bay",
    "tgn:placetype":[
        "aat:300132316"
    ]
},
  "bbox": [],
  "geometry": {"coordinates":[-122.55,48.4333],"type":"Point"}
}