{
  "id": 2172998,
  "type": "Feature",
  "properties": {
    "tgn:hierarchy":[
        "tgn:2172998",
        "tgn:1000001",
        "tgn:7012149",
        "tgn:7029392"
    ],
    "tgn:id":2172998,
    "tgn:name":"Billys Branch",
    "tgn:placetype":[
        "aat:300008699"
    ]
},
  "bbox": [],
  "geometry": {"coordinates":[-86.45,30.9667],"type":"Point"}
}