<<<<<<< HEAD
{
  "id": 7373614,
  "type": "Feature",
  "properties": {
    "tgn:hierarchy":[
        "tgn:7373614",
        "tgn:7005586",
        "tgn:1000001",
        "tgn:7005560",
        "tgn:7029392"
    ],
    "tgn:id":7373614,
    "tgn:name":"La Atalaya",
    "tgn:placetype":[
        "aat:300008347"
    ]
},
  "bbox": [],
  "geometry": {"coordinates":[-104.7,19.883333],"type":"Point"}
}
=======
{"geometry":{"type":"Point","coordinates":[-104.700000,19.883333]},"type":"Feature","properties":{"hierarchy":["tgn:7373614","tgn:7005586","tgn:1000001","tgn:7005560","tgn:7029392"],"placetype":["aat:300008347"],"id":7373614,"name:xx":"La Atalaya"}}
>>>>>>> 03f74aca74312dbeaf24d7e61306dd6a786dc3d0
