<<<<<<< HEAD
{
  "id": 7051103,
  "type": "Feature",
  "properties": {
    "tgn:hierarchy":[
        "tgn:7051103",
        "tgn:1003460",
        "tgn:1000003",
        "tgn:7009760",
        "tgn:1000080",
        "tgn:7029392"
    ],
    "tgn:id":7051103,
    "tgn:name":"Pian d'Alma",
    "tgn:placetype":[
        "aat:300008347"
    ]
},
  "bbox": [],
  "geometry": {"coordinates":[10.816667,42.833333],"type":"Point"}
}
=======
{"geometry":{"type":"Point","coordinates":[10.816667,42.833333]},"type":"Feature","properties":{"hierarchy":["tgn:7051103","tgn:1003460","tgn:1000003","tgn:7009760","tgn:1000080","tgn:7029392"],"placetype":["aat:300008347"],"id":7051103,"name:xx":"Pian d'Alma"}}
>>>>>>> 03f74aca74312dbeaf24d7e61306dd6a786dc3d0
