{
  "id": 2186523,
  "type": "Feature",
  "properties": {
    "tgn:hierarchy":[
        "tgn:2186523",
        "tgn:1000001",
        "tgn:7012149",
        "tgn:2002043",
        "tgn:7007826",
        "tgn:7029392"
    ],
    "tgn:id":2186523,
    "tgn:name":"Bone Hollow",
    "tgn:placetype":[
        "aat:300008761"
    ]
},
  "bbox": [],
  "geometry": {"coordinates":[-100.85,32.45],"type":"Point"}
}