{
  "id": 7103818,
  "type": "Feature",
  "properties": {
    "tgn:hierarchy":[
        "tgn:7103818",
        "tgn:7003669",
        "tgn:1000003",
        "tgn:7000084",
        "tgn:7029392"
    ],
    "tgn:id":7103818,
    "tgn:name":"Schmalg\u00fctl",
    "tgn:placetype":[
        "aat:300000206"
    ]
},
  "bbox": [],
  "geometry": {"coordinates":[12.633333,48.233333],"type":"Point"}
}