{
  "id": 7055645,
  "type": "Feature",
  "properties": {
    "tgn:hierarchy":[
        "tgn:7055645",
        "tgn:7003128",
        "tgn:1000003",
        "tgn:7008516",
        "tgn:1000080",
        "tgn:7029392"
    ],
    "tgn:id":7055645,
    "tgn:name":"Mirabello",
    "tgn:placetype":[
        "aat:300008347"
    ]
},
  "bbox": [],
  "geometry": {"coordinates":[11.466667,44.833333],"type":"Point"}
}