{
  "id": 2421863,
  "type": "Feature",
  "properties": {
    "tgn:hierarchy":[
        "tgn:2421863",
        "tgn:1000001",
        "tgn:7012149",
        "tgn:2000917",
        "tgn:7007256",
        "tgn:7029392"
    ],
    "tgn:id":2421863,
    "tgn:name":"Jilks Branch",
    "tgn:placetype":[
        "aat:300008699"
    ]
},
  "bbox": [],
  "geometry": {"coordinates":[-92.8333,32.0167],"type":"Point"}
}