{
  "id": 2629321,
  "type": "Feature",
  "properties": {
    "tgn:hierarchy":[
        "tgn:2629321",
        "tgn:1000001",
        "tgn:7012149",
        "tgn:2002121",
        "tgn:7007827",
        "tgn:7029392"
    ],
    "tgn:id":2629321,
    "tgn:name":"Rosebud Creek",
    "tgn:placetype":[
        "aat:300008706"
    ]
},
  "bbox": [],
  "geometry": {"coordinates":[-112.4167,38.5167],"type":"Point"}
}