{
  "id": 7426840,
  "type": "Feature",
  "properties": {
    "tgn:hierarchy":[
        "tgn:7426840",
        "tgn:7005581",
        "tgn:1000001",
        "tgn:7005560",
        "tgn:7029392"
    ],
    "tgn:id":7426840,
    "tgn:name":"Los Cuajes",
    "tgn:placetype":[
        "aat:300008347"
    ]
},
  "bbox": [],
  "geometry": {"coordinates":[-105.016667,30.316667],"type":"Point"}
}