{
  "id": 2320612,
  "type": "Feature",
  "properties": {
    "tgn:hierarchy":[
        "tgn:2320612",
        "tgn:1000001",
        "tgn:1002223",
        "tgn:7012149",
        "tgn:7007523",
        "tgn:7029392"
    ],
    "tgn:id":2320612,
    "tgn:name":"Ewing Creek",
    "tgn:placetype":[
        "aat:300008706"
    ]
},
  "bbox": [],
  "geometry": {"coordinates":[-91.8833,38.7167],"type":"Point"}
}