<<<<<<< HEAD
{
  "id": 7174696,
  "type": "Feature",
  "properties": {
    "tgn:hierarchy":[
        "tgn:7174696",
        "tgn:7003669",
        "tgn:1000003",
        "tgn:7000084",
        "tgn:7029392"
    ],
    "tgn:id":7174696,
    "tgn:name":"Gruber H\u00f6rndl",
    "tgn:placetype":[
        "aat:300008798"
    ]
},
  "bbox": [],
  "geometry": {"coordinates":[12.783333,47.75],"type":"Point"}
}
=======
{"geometry":{"type":"Point","coordinates":[12.783333,47.750000]},"type":"Feature","properties":{"hierarchy":["tgn:7174696","tgn:7003669","tgn:1000003","tgn:7000084","tgn:7029392"],"placetype":["aat:300008798"],"id":7174696,"name:xx":"Gruber H\u00f6rndl"}}
>>>>>>> 03f74aca74312dbeaf24d7e61306dd6a786dc3d0
