{
  "id": 7174696,
  "type": "Feature",
  "properties": {
    "tgn:hierarchy":[
        "tgn:7174696",
        "tgn:7003669",
        "tgn:1000003",
        "tgn:7000084",
        "tgn:7029392"
    ],
    "tgn:id":7174696,
    "tgn:name":"Gruber H\u00f6rndl",
    "tgn:placetype":[
        "aat:300008798"
    ]
},
  "bbox": [],
  "geometry": {"coordinates":[12.783333,47.75],"type":"Point"}
}