{
  "id": 1077290,
  "type": "Feature",
  "properties": {
    "tgn:hierarchy":[
        "tgn:1077290",
        "tgn:1000004",
        "tgn:7000198",
        "tgn:7001797",
        "tgn:7029392"
    ],
    "tgn:id":1077290,
    "tgn:name:en":"Villupuram",
    "tgn:placetype":[
        "aat:300008347"
    ]
},
  "bbox": [],
  "geometry": {"coordinates":[79.483333,11.933333],"type":"Point"}
}