{
  "id": 1091328,
  "type": "Feature",
  "properties": {
    "tgn:hierarchy":[
        "tgn:1091328",
        "tgn:7006226",
        "tgn:7001242",
        "tgn:7001669",
        "tgn:7029392"
    ],
    "tgn:id":1091328,
    "tgn:name":"Bandeli",
    "tgn:placetype":[
        "aat:300008347"
    ]
},
  "bbox": [],
  "geometry": {"coordinates":[45.2167,-12.9167],"type":"Point"}
}