{
  "id": 7588740,
  "type": "Feature",
  "properties": {
    "tgn:hierarchy":[
        "tgn:7588740",
        "tgn:1000004",
        "tgn:7000198",
        "tgn:7000799",
        "tgn:7029392"
    ],
    "tgn:id":7588740,
    "tgn:name:en":"Sh\u016bl\u012bpur",
    "tgn:placetype":[
        "aat:300008347"
    ]
},
  "bbox": [],
  "geometry": {"coordinates":[74.675107,34.007413],"type":"Point"}
}