<<<<<<< HEAD
{
  "id": 2154022,
  "type": "Feature",
  "properties": {
    "tgn:hierarchy":[
        "tgn:2154022",
        "tgn:1000001",
        "tgn:7012149",
        "tgn:7007157",
        "tgn:2000189",
        "tgn:7029392"
    ],
    "tgn:id":2154022,
    "tgn:name":"Bear Creek",
    "tgn:placetype":[
        "aat:300008706"
    ]
},
  "bbox": [],
  "geometry": {"coordinates":[-122.3,41.2167],"type":"Point"}
}
=======
{"geometry":{"type":"Point","coordinates":[-122.300000,41.216700]},"type":"Feature","properties":{"hierarchy":["tgn:2154022","tgn:1000001","tgn:7012149","tgn:7007157","tgn:2000189","tgn:7029392"],"placetype":["aat:300008706"],"id":2154022,"name:xx":"Bear Creek"}}
>>>>>>> 03f74aca74312dbeaf24d7e61306dd6a786dc3d0
