<<<<<<< HEAD
{
  "id": 2154374,
  "type": "Feature",
  "properties": {
    "tgn:hierarchy":[
        "tgn:2154374",
        "tgn:1000001",
        "tgn:7012149",
        "tgn:1002454",
        "tgn:7007826",
        "tgn:7029392"
    ],
    "tgn:id":2154374,
    "tgn:name":"Bear Creek",
    "tgn:placetype":[
        "aat:300008706"
    ]
},
  "bbox": [],
  "geometry": {"coordinates":[-94.2833,30.2333],"type":"Point"}
}
=======
{"geometry":{"type":"Point","coordinates":[-94.283300,30.233300]},"type":"Feature","properties":{"hierarchy":["tgn:2154374","tgn:1000001","tgn:7012149","tgn:1002454","tgn:7007826","tgn:7029392"],"placetype":["aat:300008706"],"id":2154374,"name:xx":"Bear Creek"}}
>>>>>>> 03f74aca74312dbeaf24d7e61306dd6a786dc3d0
