{
  "id": 2435415,
  "type": "Feature",
  "properties": {
    "tgn:hierarchy":[
        "tgn:2435415",
        "tgn:1000001",
        "tgn:7012149",
        "tgn:1002545",
        "tgn:7007157",
        "tgn:7029392"
    ],
    "tgn:id":2435415,
    "tgn:name":"Kern Lake",
    "tgn:placetype":[
        "aat:300008347"
    ]
},
  "bbox": [],
  "geometry": {"coordinates":[-119.0667,35.1333],"type":"Point"}
}