<<<<<<< HEAD
{
  "id": 7350368,
  "type": "Feature",
  "properties": {
    "tgn:hierarchy":[
        "tgn:7350368",
        "tgn:7005581",
        "tgn:1000001",
        "tgn:7005560",
        "tgn:7029392"
    ],
    "tgn:id":7350368,
    "tgn:name":"Burro, Ca\u00f1\u00f3n del",
    "tgn:placetype":[
        "aat:300008763"
    ]
},
  "bbox": [],
  "geometry": {"coordinates":[-106.3,28.6],"type":"Point"}
}
=======
{"geometry":{"type":"Point","coordinates":[-106.300000,28.600000]},"type":"Feature","properties":{"hierarchy":["tgn:7350368","tgn:7005581","tgn:1000001","tgn:7005560","tgn:7029392"],"placetype":["aat:300008763"],"id":7350368,"name:xx":"Burro, Ca\u00f1\u00f3n del"}}
>>>>>>> 03f74aca74312dbeaf24d7e61306dd6a786dc3d0
