{
  "id": 7360543,
  "type": "Feature",
  "properties": {
    "tgn:hierarchy":[
        "tgn:7360543",
        "tgn:1000001",
        "tgn:1001893",
        "tgn:7005560",
        "tgn:7029392"
    ],
    "tgn:id":7360543,
    "tgn:name":"Ecatzingo de Hidalgo",
    "tgn:placetype":[
        "aat:300008347"
    ]
},
  "bbox": [],
  "geometry": {"coordinates":[-98.75,18.933333],"type":"Point"}
}