{
  "id": 7555312,
  "type": "Feature",
  "properties": {
    "tgn:hierarchy":[
        "tgn:7555312",
        "tgn:1000004",
        "tgn:7000198",
        "tgn:7000799",
        "tgn:7029392"
    ],
    "tgn:id":7555312,
    "tgn:name:en":"Mitpal Tso",
    "tgn:placetype":[
        "aat:300008680"
    ]
},
  "bbox": [],
  "geometry": {"coordinates":[78.61174,33.465153],"type":"Point"}
}