{
  "id": 2303932,
  "type": "Feature",
  "properties": {
    "tgn:hierarchy":[
        "tgn:2303932",
        "tgn:7006450",
        "tgn:1000001",
        "tgn:2124089",
        "tgn:7012149",
        "tgn:7029392"
    ],
    "tgn:id":2303932,
    "tgn:name":"Eagle River",
    "tgn:placetype":[
        "aat:300008707"
    ]
},
  "bbox": [],
  "geometry": {"coordinates":[-134.7167,58.5833],"type":"Point"}
}