{
  "id": 2419436,
  "type": "Feature",
  "properties": {
    "tgn:hierarchy":[
        "tgn:2419436",
        "tgn:1000001",
        "tgn:2001411",
        "tgn:7012149",
        "tgn:7007526",
        "tgn:7029392"
    ],
    "tgn:id":2419436,
    "tgn:name":"Jarbidge Lake",
    "tgn:placetype":[
        "aat:300008680"
    ]
},
  "bbox": [],
  "geometry": {"coordinates":[-115.3667,41.7667],"type":"Point"}
}