{
  "id": 1084478,
  "type": "Feature",
  "properties": {
    "tgn:hierarchy":[
        "tgn:1084478",
        "tgn:1000004",
        "tgn:1001541",
        "tgn:1000135",
        "tgn:7029392"
    ],
    "tgn:id":1084478,
    "tgn:name":"Naci",
    "tgn:placetype":[
        "aat:300008347"
    ]
},
  "bbox": [],
  "geometry": {"coordinates":[124.7667,6.3167],"type":"Point"}
}