<<<<<<< HEAD
{
  "id": 2259965,
  "type": "Feature",
  "properties": {
    "tgn:hierarchy":[
        "tgn:2259965",
        "tgn:1000001",
        "tgn:1002714",
        "tgn:7012149",
        "tgn:7007159",
        "tgn:7029392"
    ],
    "tgn:id":2259965,
    "tgn:name":"Coults Hole",
    "tgn:placetype":[
        "aat:300132316"
    ]
},
  "bbox": [],
  "geometry": {"coordinates":[-72.35,41.35],"type":"Point"}
}
=======
{"geometry":{"type":"Point","coordinates":[-72.350000,41.350000]},"type":"Feature","properties":{"hierarchy":["tgn:2259965","tgn:1000001","tgn:1002714","tgn:7012149","tgn:7007159","tgn:7029392"],"placetype":["aat:300132316"],"id":2259965,"name:xx":"Coults Hole"}}
>>>>>>> 03f74aca74312dbeaf24d7e61306dd6a786dc3d0
