{
  "id": 7211799,
  "type": "Feature",
  "properties": {
    "tgn:hierarchy":[
        "tgn:7211799",
        "tgn:7003692",
        "tgn:1000003",
        "tgn:7000084",
        "tgn:7029392"
    ],
    "tgn:id":7211799,
    "tgn:name":"Bilsenhof",
    "tgn:placetype":[
        "aat:300000206"
    ]
},
  "bbox": [],
  "geometry": {"coordinates":[9.866667,48.75],"type":"Point"}
}