{
  "id": 7583292,
  "type": "Feature",
  "properties": {
    "tgn:hierarchy":[
        "tgn:7583292",
        "tgn:1000004",
        "tgn:7000198",
        "tgn:1001882",
        "tgn:7029392"
    ],
    "tgn:id":7583292,
    "tgn:name:en":"Yen\u016br",
    "tgn:placetype":[
        "aat:300008347"
    ]
},
  "bbox": [],
  "geometry": {"coordinates":[75.133333,13.016667],"type":"Point"}
}