{
  "id": 2063141,
  "type": "Feature",
  "properties": {
    "tgn:hierarchy":[
        "tgn:2063141",
        "tgn:1000001",
        "tgn:2001411",
        "tgn:7012149",
        "tgn:7007526",
        "tgn:7029392"
    ],
    "tgn:id":2063141,
    "tgn:name":"Spruce",
    "tgn:placetype":[
        "aat:300387016"
    ]
},
  "bbox": [],
  "geometry": {"coordinates":[-114.65,40.7833],"type":"Point"}
}