{
  "id": 7388054,
  "type": "Feature",
  "properties": {
    "tgn:hierarchy":[
        "tgn:7388054",
        "tgn:1000001",
        "tgn:7005600",
        "tgn:7005560",
        "tgn:7029392"
    ],
    "tgn:id":7388054,
    "tgn:name":"Piedra, Punta de",
    "tgn:placetype":[
        "aat:300386846"
    ]
},
  "bbox": [],
  "geometry": {"coordinates":[-90.116667,21.15],"type":"Point"}
}