<<<<<<< HEAD
{
  "id": 2400285,
  "type": "Feature",
  "properties": {
    "tgn:hierarchy":[
        "tgn:2400285",
        "tgn:7002659",
        "tgn:1000001",
        "tgn:7012149",
        "tgn:7029392"
    ],
    "tgn:id":2400285,
    "tgn:name":"Horse Creek Valley",
    "tgn:placetype":[
        "aat:300008761"
    ]
},
  "bbox": [],
  "geometry": {"coordinates":[-85.9,33.4333],"type":"Point"}
}
=======
{"geometry":{"type":"Point","coordinates":[-85.900000,33.433300]},"type":"Feature","properties":{"hierarchy":["tgn:2400285","tgn:7002659","tgn:1000001","tgn:7012149","tgn:7029392"],"placetype":["aat:300008761"],"id":2400285,"name:xx":"Horse Creek Valley"}}
>>>>>>> 03f74aca74312dbeaf24d7e61306dd6a786dc3d0
