{
  "id": 2181834,
  "type": "Feature",
  "properties": {
    "tgn:hierarchy":[
        "tgn:2181834",
        "tgn:1000001",
        "tgn:7012149",
        "tgn:2002111",
        "tgn:7007827",
        "tgn:7029392"
    ],
    "tgn:id":2181834,
    "tgn:name":"Blue Knoll",
    "tgn:placetype":[
        "aat:300008798"
    ]
},
  "bbox": [],
  "geometry": {"coordinates":[-113.25,38.0833],"type":"Point"}
}