{
  "id": 2704247,
  "type": "Feature",
  "properties": {
    "tgn:hierarchy":[
        "tgn:2704247",
        "tgn:1000001",
        "tgn:7012149",
        "tgn:2001254",
        "tgn:7007523",
        "tgn:7029392"
    ],
    "tgn:id":2704247,
    "tgn:name":"Sunnen Lake",
    "tgn:placetype":[
        "aat:300006191"
    ]
},
  "bbox": [],
  "geometry": {"coordinates":[-90.9167,37.95],"type":"Point"}
}