{
  "id": 2760137,
  "type": "Feature",
  "properties": {
    "tgn:hierarchy":[
        "tgn:2760137",
        "tgn:1000001",
        "tgn:7016172",
        "tgn:2000119",
        "tgn:7012149",
        "tgn:7029392"
    ],
    "tgn:id":2760137,
    "tgn:name":"West Fork Point Remove Creek Site 15 Reservoir",
    "tgn:placetype":[
        "aat:300006191"
    ]
},
  "bbox": [],
  "geometry": {"coordinates":[-92.7667,35.3167],"type":"Point"}
}