{
  "id": 2210199,
  "type": "Feature",
  "properties": {
    "tgn:hierarchy":[
        "tgn:2210199",
        "tgn:1000001",
        "tgn:2001261",
        "tgn:7012149",
        "tgn:7007524",
        "tgn:7029392"
    ],
    "tgn:id":2210199,
    "tgn:name":"Busby Creek",
    "tgn:placetype":[
        "aat:300008706"
    ]
},
  "bbox": [],
  "geometry": {"coordinates":[-106.9167,45.4833],"type":"Point"}
}