<<<<<<< HEAD
{
  "id": 2406022,
  "type": "Feature",
  "properties": {
    "tgn:hierarchy":[
        "tgn:2406022",
        "tgn:1000001",
        "tgn:7012149",
        "tgn:2001281",
        "tgn:7007524",
        "tgn:7029392"
    ],
    "tgn:id":2406022,
    "tgn:name":"Humbolt Mine",
    "tgn:placetype":[
        "aat:300000390"
    ]
},
  "bbox": [],
  "geometry": {"coordinates":[-112.35,45.9333],"type":"Point"}
}
=======
{"geometry":{"type":"Point","coordinates":[-112.350000,45.933300]},"type":"Feature","properties":{"hierarchy":["tgn:2406022","tgn:1000001","tgn:7012149","tgn:2001281","tgn:7007524","tgn:7029392"],"placetype":["aat:300000390"],"id":2406022,"name:xx":"Humbolt Mine"}}
>>>>>>> 03f74aca74312dbeaf24d7e61306dd6a786dc3d0
