{
  "id": 2780902,
  "type": "Feature",
  "properties": {
    "tgn:hierarchy":[
        "tgn:2780902",
        "tgn:1000001",
        "tgn:7012149",
        "tgn:2000182",
        "tgn:7007157",
        "tgn:7029392"
    ],
    "tgn:id":2780902,
    "tgn:name":"Woodbine Lateral Seven",
    "tgn:placetype":[
        "aat:300006075"
    ]
},
  "bbox": [],
  "geometry": {"coordinates":[-115.65,32.6667],"type":"Point"}
}