{
  "id": 2697439,
  "type": "Feature",
  "properties": {
    "tgn:hierarchy":[
        "tgn:2697439",
        "tgn:1000001",
        "tgn:7012149",
        "tgn:2001868",
        "tgn:7007825",
        "tgn:7029392"
    ],
    "tgn:id":2697439,
    "tgn:name":"Stony Mountain",
    "tgn:placetype":[
        "aat:300008798"
    ]
},
  "bbox": [],
  "geometry": {"coordinates":[-83.1667,36.3333],"type":"Point"}
}