{
  "id": 2142368,
  "type": "Feature",
  "properties": {
    "tgn:hierarchy":[
        "tgn:2142368",
        "tgn:1000001",
        "tgn:7012149",
        "tgn:1002988",
        "tgn:7007710",
        "tgn:7029392"
    ],
    "tgn:id":2142368,
    "tgn:name":"Backup Corners",
    "tgn:placetype":[
        "aat:300008347"
    ]
},
  "bbox": [],
  "geometry": {"coordinates":[-79.15,41.9167],"type":"Point"}
}