<<<<<<< HEAD
{
  "id": 2406435,
  "type": "Feature",
  "properties": {
    "tgn:hierarchy":[
        "tgn:2406435",
        "tgn:1000001",
        "tgn:7012149",
        "tgn:2002248",
        "tgn:7007920",
        "tgn:7029392"
    ],
    "tgn:id":2406435,
    "tgn:name":"Hungry Creek",
    "tgn:placetype":[
        "aat:300008706"
    ]
},
  "bbox": [],
  "geometry": {"coordinates":[-117.1333,48.5833],"type":"Point"}
}
=======
{"geometry":{"type":"Point","coordinates":[-117.133300,48.583300]},"type":"Feature","properties":{"hierarchy":["tgn:2406435","tgn:1000001","tgn:7012149","tgn:2002248","tgn:7007920","tgn:7029392"],"placetype":["aat:300008706"],"id":2406435,"name:xx":"Hungry Creek"}}
>>>>>>> 03f74aca74312dbeaf24d7e61306dd6a786dc3d0
