{
  "id": 2008714,
  "type": "Feature",
  "properties": {
    "tgn:hierarchy":[
        "tgn:2008714",
        "tgn:1000001",
        "tgn:7016172",
        "tgn:7012149",
        "tgn:2000169",
        "tgn:7029392"
    ],
    "tgn:id":2008714,
    "tgn:name":"Leslie",
    "tgn:placetype":[
        "aat:300008347"
    ]
},
  "bbox": [],
  "geometry": {"coordinates":[-92.55,35.8167],"type":"Point"}
}