{
  "id": 2711153,
  "type": "Feature",
  "properties": {
    "tgn:hierarchy":[
        "tgn:2711153",
        "tgn:2000858",
        "tgn:1000001",
        "tgn:7012149",
        "tgn:7007256",
        "tgn:7029392"
    ],
    "tgn:id":2711153,
    "tgn:name":"Tanner Lake",
    "tgn:placetype":[
        "aat:300008680"
    ]
},
  "bbox": [],
  "geometry": {"coordinates":[-92.15,30.9333],"type":"Point"}
}