{
  "id": 2423974,
  "type": "Feature",
  "properties": {
    "tgn:hierarchy":[
        "tgn:2423974",
        "tgn:1000001",
        "tgn:7012149",
        "tgn:1002384",
        "tgn:7007523",
        "tgn:7029392"
    ],
    "tgn:id":2423974,
    "tgn:name":"Johns Branch",
    "tgn:placetype":[
        "aat:300008699"
    ]
},
  "bbox": [],
  "geometry": {"coordinates":[-91.3167,38.35],"type":"Point"}
}