{
  "id": 2474898,
  "type": "Feature",
  "properties": {
    "tgn:hierarchy":[
        "tgn:2474898",
        "tgn:1000001",
        "tgn:7012149",
        "tgn:2001046",
        "tgn:7007521",
        "tgn:7029392"
    ],
    "tgn:id":2474898,
    "tgn:name":"Lower Twin Island",
    "tgn:placetype":[
        "aat:300008791"
    ]
},
  "bbox": [],
  "geometry": {"coordinates":[-93.5167,46.1333],"type":"Point"}
}