{
  "id": 1003893,
  "type": "Feature",
  "properties": {
    "tgn:hierarchy":[
        "tgn:1003893",
        "tgn:1003530",
        "tgn:1000003",
        "tgn:1001780",
        "tgn:7029392"
    ],
    "tgn:id":1003893,
    "tgn:name":"\u010cakovice",
    "tgn:placetype":[
        "aat:300000745"
    ]
},
  "bbox": [],
  "geometry": {"coordinates":[14.5167,50.15],"type":"Point"}
}