{
  "id": 2059801,
  "type": "Feature",
  "properties": {
    "tgn:hierarchy":[
        "tgn:2059801",
        "tgn:1000001",
        "tgn:7012149",
        "tgn:2001204",
        "tgn:7007523",
        "tgn:7029392"
    ],
    "tgn:id":2059801,
    "tgn:name":"Mound City",
    "tgn:placetype":[
        "aat:300008347"
    ]
},
  "bbox": [],
  "geometry": {"coordinates":[-95.2167,40.1167],"type":"Point"}
}