{
  "id": 2073853,
  "type": "Feature",
  "properties": {
    "tgn:hierarchy":[
        "tgn:2073853",
        "tgn:1000001",
        "tgn:7012149",
        "tgn:7014128",
        "tgn:7007709",
        "tgn:7029392"
    ],
    "tgn:id":2073853,
    "tgn:name":"Bullock",
    "tgn:placetype":[
        "aat:300008347"
    ]
},
  "bbox": [],
  "geometry": {"coordinates":[-78.5333,36.4833],"type":"Point"}
}