{
  "id": 2311188,
  "type": "Feature",
  "properties": {
    "tgn:hierarchy":[
        "tgn:2311188",
        "tgn:1000001",
        "tgn:7012149",
        "tgn:2002125",
        "tgn:7007827",
        "tgn:7029392"
    ],
    "tgn:id":2311188,
    "tgn:name":"Edgemont",
    "tgn:placetype":[
        "aat:300008347"
    ]
},
  "bbox": [],
  "geometry": {"coordinates":[-111.65,40.2833],"type":"Point"}
}