{
  "id": 7557415,
  "type": "Feature",
  "properties": {
    "tgn:hierarchy":[
        "tgn:7557415",
        "tgn:1000004",
        "tgn:7000198",
        "tgn:1001882",
        "tgn:7029392"
    ],
    "tgn:id":7557415,
    "tgn:name:en":"S\u0101ligr\u0101ma",
    "tgn:placetype":[
        "aat:300008347"
    ]
},
  "bbox": [],
  "geometry": {"coordinates":[76.261944,12.561944],"type":"Point"}
}