{
  "id": 2467318,
  "type": "Feature",
  "properties": {
    "tgn:hierarchy":[
        "tgn:2467318",
        "tgn:1000001",
        "tgn:7012149",
        "tgn:1002877",
        "tgn:7007706",
        "tgn:7029392"
    ],
    "tgn:id":2467318,
    "tgn:name":"Long Fork Bear Creek",
    "tgn:placetype":[
        "aat:300008706"
    ]
},
  "bbox": [],
  "geometry": {"coordinates":[-83.2167,38.7833],"type":"Point"}
}