{
  "id": 2464764,
  "type": "Feature",
  "properties": {
    "tgn:hierarchy":[
        "tgn:2464764",
        "tgn:1000001",
        "tgn:1002340",
        "tgn:7012149",
        "tgn:7007526",
        "tgn:7029392"
    ],
    "tgn:id":2464764,
    "tgn:name":"Logan Creek Estates",
    "tgn:placetype":[
        "aat:300008347"
    ]
},
  "bbox": [],
  "geometry": {"coordinates":[-119.9333,39.05],"type":"Point"}
}