{
  "id": 2008528,
  "type": "Feature",
  "properties": {
    "tgn:hierarchy":[
        "tgn:2008528",
        "tgn:1000001",
        "tgn:7016172",
        "tgn:2000116",
        "tgn:7012149",
        "tgn:7029392"
    ],
    "tgn:id":2008528,
    "tgn:name":"Hopewell",
    "tgn:placetype":[
        "aat:300008347",
        "aat:300387210"
    ]
},
  "bbox": [],
  "geometry": {"coordinates":[-92.05,35.3833],"type":"Point"}
}