{
  "id": 1106811,
  "type": "Feature",
  "properties": {
    "tgn:hierarchy":[
        "tgn:1106811",
        "tgn:7002448",
        "tgn:7019157",
        "tgn:1000003",
        "tgn:7008591",
        "tgn:7029392"
    ],
    "tgn:id":1106811,
    "tgn:name:en":"Trostan",
    "tgn:placetype":[
        "aat:300008795"
    ]
},
  "bbox": [],
  "geometry": {"coordinates":[-6.166667,55.05],"type":"Point"}
}