{
  "id": 7044867,
  "type": "Feature",
  "properties": {
    "tgn:hierarchy":[
        "tgn:7044867",
        "tgn:7003132",
        "tgn:1000003",
        "tgn:7008516",
        "tgn:1000080",
        "tgn:7029392"
    ],
    "tgn:id":7044867,
    "tgn:name":"Canedo",
    "tgn:placetype":[
        "aat:300008347"
    ]
},
  "bbox": [],
  "geometry": {"coordinates":[9.316667,44.816667],"type":"Point"}
}