{
  "id": 2572500,
  "type": "Feature",
  "properties": {
    "tgn:hierarchy":[
        "tgn:2572500",
        "tgn:1000001",
        "tgn:7012149",
        "tgn:2000389",
        "tgn:7007248",
        "tgn:7029392"
    ],
    "tgn:id":2572500,
    "tgn:name":"Peachtree Branch",
    "tgn:placetype":[
        "aat:300008699"
    ]
},
  "bbox": [],
  "geometry": {"coordinates":[-84.6333,32.4667],"type":"Point"}
}