{
  "id": 2549227,
  "type": "Feature",
  "properties": {
    "tgn:hierarchy":[
        "tgn:2549227",
        "tgn:1000001",
        "tgn:7012149",
        "tgn:1002418",
        "tgn:7007920",
        "tgn:7029392"
    ],
    "tgn:id":2549227,
    "tgn:name":"North River Divide",
    "tgn:placetype":[
        "aat:300266640"
    ]
},
  "bbox": [],
  "geometry": {"coordinates":[-123.85,46.8333],"type":"Point"}
}