{
  "id": 7332496,
  "type": "Feature",
  "properties": {
    "tgn:hierarchy":[
        "tgn:7332496",
        "tgn:7002825",
        "tgn:7016622",
        "tgn:1000003",
        "tgn:1000095",
        "tgn:7029392"
    ],
    "tgn:id":7332496,
    "tgn:name":"La Baja",
    "tgn:placetype":[
        "aat:300011692"
    ]
},
  "bbox": [],
  "geometry": {"coordinates":[-13.333333,29.266667],"type":"Point"}
}