{
  "id": 7553565,
  "type": "Feature",
  "properties": {
    "tgn:hierarchy":[
        "tgn:7553565",
        "tgn:1000004",
        "tgn:7000198",
        "tgn:1001882",
        "tgn:7029392"
    ],
    "tgn:id":7553565,
    "tgn:name:en":"Maski",
    "tgn:placetype":[
        "aat:300008347"
    ]
},
  "bbox": [],
  "geometry": {"coordinates":[76.666667,15.966667],"type":"Point"}
}