{
  "id": 2093980,
  "type": "Feature",
  "properties": {
    "tgn:hierarchy":[
        "tgn:2093980",
        "tgn:1000001",
        "tgn:7012149",
        "tgn:2093962",
        "tgn:1002690",
        "tgn:7007710",
        "tgn:7029392"
    ],
    "tgn:id":2093980,
    "tgn:name":"Rebel Hill",
    "tgn:placetype":[
        "aat:300387200"
    ]
},
  "bbox": [],
  "geometry": {"coordinates":[-75.3333,40.05],"type":"Point"}
}