{
  "id": 2354392,
  "type": "Feature",
  "properties": {
    "tgn:hierarchy":[
        "tgn:2354392",
        "tgn:1000001",
        "tgn:7012149",
        "tgn:7018871",
        "tgn:7007920",
        "tgn:7029392"
    ],
    "tgn:id":2354392,
    "tgn:name":"Goldmyer Hot Springs",
    "tgn:placetype":[
        "aat:300008697"
    ]
},
  "bbox": [],
  "geometry": {"coordinates":[-121.3833,47.4833],"type":"Point"}
}