{
  "id": 1085214,
  "type": "Feature",
  "properties": {
    "tgn:hierarchy":[
        "tgn:1085214",
        "tgn:1002074",
        "tgn:1000004",
        "tgn:1000140",
        "tgn:7029392"
    ],
    "tgn:id":1085214,
    "tgn:name":"Naw\u00e1",
    "tgn:placetype":[
        "aat:300008347"
    ]
},
  "bbox": [],
  "geometry": {"coordinates":[36.05,32.8833],"type":"Point"}
}