{
  "id": 7406004,
  "type": "Feature",
  "properties": {
    "tgn:hierarchy":[
        "tgn:7406004",
        "tgn:7005585",
        "tgn:1000001",
        "tgn:7005560",
        "tgn:7029392"
    ],
    "tgn:id":7406004,
    "tgn:name":"Las \u00c1guilas, Cerros",
    "tgn:placetype":[
        "aat:300008795"
    ]
},
  "bbox": [],
  "geometry": {"coordinates":[-101.833333,18.183333],"type":"Point"}
}