{
  "id": 7498142,
  "type": "Feature",
  "properties": {
    "tgn:hierarchy":[
        "tgn:7498142",
        "tgn:1000004",
        "tgn:7491221",
        "tgn:1000141",
        "tgn:7029392"
    ],
    "tgn:id":7498142,
    "tgn:name":"Dabaliujiu Jiubuluo",
    "tgn:placetype":[
        "aat:300387323"
    ]
},
  "bbox": [],
  "geometry": {"coordinates":[121.06202,22.806418],"type":"Point"}
}