{
  "id": 7481214,
  "type": "Feature",
  "properties": {
    "tgn:hierarchy":[
        "tgn:7481214",
        "tgn:1000004",
        "tgn:7491221",
        "tgn:1000141",
        "tgn:7029392"
    ],
    "tgn:id":7481214,
    "tgn:name":"Muji Yan",
    "tgn:placetype":[
        "aat:300011692"
    ]
},
  "bbox": [],
  "geometry": {"coordinates":[121.557778,22.082222],"type":"Point"}
}