{
  "id": 2382489,
  "type": "Feature",
  "properties": {
    "tgn:hierarchy":[
        "tgn:2382489",
        "tgn:2000195",
        "tgn:1000001",
        "tgn:7012149",
        "tgn:7007158",
        "tgn:7029392"
    ],
    "tgn:id":2382489,
    "tgn:name":"Haystack Mountain",
    "tgn:placetype":[
        "aat:300008798"
    ]
},
  "bbox": [],
  "geometry": {"coordinates":[-107.2333,37.2167],"type":"Point"}
}