<<<<<<< HEAD
{
  "id": 2405774,
  "type": "Feature",
  "properties": {
    "tgn:hierarchy":[
        "tgn:2405774",
        "tgn:1000001",
        "tgn:7012149",
        "tgn:2001721",
        "tgn:7007708",
        "tgn:7029392"
    ],
    "tgn:id":2405774,
    "tgn:name":"Hulick Branch",
    "tgn:placetype":[
        "aat:300008699"
    ]
},
  "bbox": [],
  "geometry": {"coordinates":[-117.7833,45.2833],"type":"Point"}
}
=======
{"geometry":{"type":"Point","coordinates":[-117.783300,45.283300]},"type":"Feature","properties":{"hierarchy":["tgn:2405774","tgn:1000001","tgn:7012149","tgn:2001721","tgn:7007708","tgn:7029392"],"placetype":["aat:300008699"],"id":2405774,"name:xx":"Hulick Branch"}}
>>>>>>> 03f74aca74312dbeaf24d7e61306dd6a786dc3d0
