{
  "id": 7037538,
  "type": "Feature",
  "properties": {
    "tgn:hierarchy":[
        "tgn:7037538",
        "tgn:1001724",
        "tgn:1000003",
        "tgn:7003121",
        "tgn:1000080",
        "tgn:7029392"
    ],
    "tgn:id":7037538,
    "tgn:name":"Triei",
    "tgn:placetype":[
        "aat:300008347"
    ]
},
  "bbox": [],
  "geometry": {"coordinates":[9.633333,40.033333],"type":"Point"}
}