{
  "id": 7364605,
  "type": "Feature",
  "properties": {
    "tgn:hierarchy":[
        "tgn:7364605",
        "tgn:7005586",
        "tgn:1000001",
        "tgn:7005560",
        "tgn:7029392"
    ],
    "tgn:id":7364605,
    "tgn:name":"El Saucillo de Maldonado",
    "tgn:placetype":[
        "aat:300008347"
    ]
},
  "bbox": [],
  "geometry": {"coordinates":[-102.916667,20.55],"type":"Point"}
}