{
  "id": 7018564,
  "type": "Feature",
  "properties": {
    "tgn:hierarchy":[
        "tgn:7018564",
        "tgn:7018541",
        "tgn:7005557",
        "tgn:1000001",
        "tgn:7005556",
        "tgn:7029392"
    ],
    "tgn:id":7018564,
    "tgn:name":"Cascade",
    "tgn:placetype":[
        "aat:300008347",
        "aat:300008375"
    ]
},
  "bbox": [],
  "geometry": {"coordinates":[-78.103,18.397],"type":"Point"}
}