<<<<<<< HEAD
{
  "id": 2769593,
  "type": "Feature",
  "properties": {
    "tgn:hierarchy":[
        "tgn:2769593",
        "tgn:1000001",
        "tgn:2001264",
        "tgn:7012149",
        "tgn:7007524",
        "tgn:7029392"
    ],
    "tgn:id":2769593,
    "tgn:name":"Widowed Lake",
    "tgn:placetype":[
        "aat:300008680"
    ]
},
  "bbox": [],
  "geometry": {"coordinates":[-109.7,45.05],"type":"Point"}
}
=======
{"geometry":{"type":"Point","coordinates":[-109.700000,45.050000]},"type":"Feature","properties":{"hierarchy":["tgn:2769593","tgn:1000001","tgn:2001264","tgn:7012149","tgn:7007524","tgn:7029392"],"placetype":["aat:300008680"],"id":2769593,"name:xx":"Widowed Lake"}}
>>>>>>> 03f74aca74312dbeaf24d7e61306dd6a786dc3d0
