{
  "id": 2077863,
  "type": "Feature",
  "properties": {
    "tgn:hierarchy":[
        "tgn:2077863",
        "tgn:1000001",
        "tgn:2001595",
        "tgn:7012149",
        "tgn:7007705",
        "tgn:7029392"
    ],
    "tgn:id":2077863,
    "tgn:name":"Moselle",
    "tgn:placetype":[
        "aat:300387016"
    ]
},
  "bbox": [],
  "geometry": {"coordinates":[-97.0667,46.2167],"type":"Point"}
}