{
  "id": 2520669,
  "type": "Feature",
  "properties": {
    "tgn:hierarchy":[
        "tgn:2520669",
        "tgn:1000001",
        "tgn:7012149",
        "tgn:1002794",
        "tgn:7007708",
        "tgn:7029392"
    ],
    "tgn:id":2520669,
    "tgn:name":"Monmouth Reservoir",
    "tgn:placetype":[
        "aat:300006191"
    ]
},
  "bbox": [],
  "geometry": {"coordinates":[-123.2333,44.8333],"type":"Point"}
}