{
  "id": 2437625,
  "type": "Feature",
  "properties": {
    "tgn:hierarchy":[
        "tgn:2437625",
        "tgn:1000001",
        "tgn:2001749",
        "tgn:7012149",
        "tgn:7007712",
        "tgn:7029392"
    ],
    "tgn:id":2437625,
    "tgn:name":"King Branch",
    "tgn:placetype":[
        "aat:300008699"
    ]
},
  "bbox": [],
  "geometry": {"coordinates":[-81.2667,32.65],"type":"Point"}
}