{
  "id": 2588891,
  "type": "Feature",
  "properties": {
    "tgn:hierarchy":[
        "tgn:2588891",
        "tgn:1000001",
        "tgn:7012149",
        "tgn:7007252",
        "tgn:7029392"
    ],
    "tgn:id":2588891,
    "tgn:name":"Pocket Hollow",
    "tgn:placetype":[
        "aat:300008761"
    ]
},
  "bbox": [],
  "geometry": {"coordinates":[-86.5333,39.3333],"type":"Point"}
}