{
  "id": 2221004,
  "type": "Feature",
  "properties": {
    "tgn:hierarchy":[
        "tgn:2221004",
        "tgn:7006450",
        "tgn:1000001",
        "tgn:7012149",
        "tgn:2000082",
        "tgn:7029392"
    ],
    "tgn:id":2221004,
    "tgn:name":"Caracol Island",
    "tgn:placetype":[
        "aat:300008791"
    ]
},
  "bbox": [],
  "geometry": {"coordinates":[-133.4333,55.5167],"type":"Point"}
}