{
  "id": 7530219,
  "type": "Feature",
  "properties": {
    "tgn:hierarchy":[
        "tgn:7530219",
        "tgn:7001242",
        "tgn:7016833",
        "tgn:7001335",
        "tgn:7029392"
    ],
    "tgn:id":7530219,
    "tgn:name":"Ghurrah, Jabal al",
    "tgn:placetype":[
        "aat:300008795"
    ]
},
  "bbox": [],
  "geometry": {"coordinates":[34.410917,30.625493],"type":"Point"}
}