{
  "id": 7379774,
  "type": "Feature",
  "properties": {
    "tgn:hierarchy":[
        "tgn:7379774",
        "tgn:7005586",
        "tgn:1000001",
        "tgn:7005560",
        "tgn:7029392"
    ],
    "tgn:id":7379774,
    "tgn:name":"Milpillas",
    "tgn:placetype":[
        "aat:300008347"
    ]
},
  "bbox": [],
  "geometry": {"coordinates":[-103.066667,19.933333],"type":"Point"}
}