<<<<<<< HEAD
{
  "id": 2338388,
  "type": "Feature",
  "properties": {
    "tgn:hierarchy":[
        "tgn:2338388",
        "tgn:1000001",
        "tgn:7012149",
        "tgn:2000960",
        "tgn:7007520",
        "tgn:7029392"
    ],
    "tgn:id":2338388,
    "tgn:name":"Foxpaw Lake",
    "tgn:placetype":[
        "aat:300008680"
    ]
},
  "bbox": [],
  "geometry": {"coordinates":[-89.8,46.3],"type":"Point"}
}
=======
{"geometry":{"type":"Point","coordinates":[-89.800000,46.300000]},"type":"Feature","properties":{"hierarchy":["tgn:2338388","tgn:1000001","tgn:7012149","tgn:2000960","tgn:7007520","tgn:7029392"],"placetype":["aat:300008680"],"id":2338388,"name:xx":"Foxpaw Lake"}}
>>>>>>> 03f74aca74312dbeaf24d7e61306dd6a786dc3d0
