{
  "id": 7011844,
  "type": "Feature",
  "properties": {
    "tgn:hierarchy":[
        "tgn:7011844",
        "tgn:7002445",
        "tgn:1000003",
        "tgn:7008131",
        "tgn:7008591",
        "tgn:7029392"
    ],
    "tgn:id":7011844,
    "tgn:name:en":"Waltham Abbey",
    "tgn:placetype":[
        "aat:300008347"
    ]
},
  "bbox": [],
  "geometry": {"coordinates":[0.016667,51.683333],"type":"Point"}
}