{
  "id": 7452549,
  "type": "Feature",
  "properties": {
    "tgn:hierarchy":[
        "tgn:7452549",
        "tgn:7002445",
        "tgn:1000003",
        "tgn:7008131",
        "tgn:7008591",
        "tgn:7029392"
    ],
    "tgn:id":7452549,
    "tgn:name:en":"Gosfield",
    "tgn:placetype":[
        "aat:300008347"
    ]
},
  "bbox": [],
  "geometry": {"coordinates":[0.583333,51.933333],"type":"Point"}
}