{
  "id": 7495865,
  "type": "Feature",
  "properties": {
    "tgn:hierarchy":[
        "tgn:7495865",
        "tgn:7487020",
        "tgn:1000004",
        "tgn:1000141",
        "tgn:7029392"
    ],
    "tgn:id":7495865,
    "tgn:name":"Tangwo Shan",
    "tgn:placetype":[
        "aat:300387033"
    ]
},
  "bbox": [],
  "geometry": {"coordinates":[120.7282,24.5012],"type":"Point"}
}