{
  "id": 7244533,
  "type": "Feature",
  "properties": {
    "tgn:hierarchy":[
        "tgn:7244533",
        "tgn:7003457",
        "tgn:1000003",
        "tgn:1000063",
        "tgn:7018236",
        "tgn:7029392"
    ],
    "tgn:id":7244533,
    "tgn:name":"Kuil",
    "tgn:placetype":[
        "aat:300008347"
    ]
},
  "bbox": [],
  "geometry": {"coordinates":[4.115971,51.135035],"type":"Point"}
}