<<<<<<< HEAD
{
  "id": 7246364,
  "type": "Feature",
  "properties": {
    "tgn:hierarchy":[
        "tgn:7246364",
        "tgn:7007877",
        "tgn:1000003",
        "tgn:1000063",
        "tgn:4012014",
        "tgn:7029392"
    ],
    "tgn:id":7246364,
    "tgn:name":"Coucou",
    "tgn:placetype":[
        "aat:300008347"
    ]
},
  "bbox": [],
  "geometry": {"coordinates":[3.692538,50.654558],"type":"Point"}
}
=======
{"geometry":{"type":"Point","coordinates":[3.692538,50.654558]},"type":"Feature","properties":{"hierarchy":["tgn:7246364","tgn:7007877","tgn:1000003","tgn:1000063","tgn:4012014","tgn:7029392"],"placetype":["aat:300008347"],"id":7246364,"name:xx":"Coucou"}}
>>>>>>> 03f74aca74312dbeaf24d7e61306dd6a786dc3d0
