{
  "id": 7246364,
  "type": "Feature",
  "properties": {
    "tgn:hierarchy":[
        "tgn:7246364",
        "tgn:7007877",
        "tgn:1000003",
        "tgn:1000063",
        "tgn:4012014",
        "tgn:7029392"
    ],
    "tgn:id":7246364,
    "tgn:name":"Coucou",
    "tgn:placetype":[
        "aat:300008347"
    ]
},
  "bbox": [],
  "geometry": {"coordinates":[3.692538,50.654558],"type":"Point"}
}