{
  "id": 2357676,
  "type": "Feature",
  "properties": {
    "tgn:hierarchy":[
        "tgn:2357676",
        "tgn:1000001",
        "tgn:7012149",
        "tgn:2000330",
        "tgn:7007248",
        "tgn:7029392"
    ],
    "tgn:id":2357676,
    "tgn:name":"Grace Branch",
    "tgn:placetype":[
        "aat:300008699"
    ]
},
  "bbox": [],
  "geometry": {"coordinates":[-84.0667,32.7333],"type":"Point"}
}