{
  "id": 7251249,
  "type": "Feature",
  "properties": {
    "tgn:hierarchy":[
        "tgn:7251249",
        "tgn:7003458",
        "tgn:1000003",
        "tgn:1000063",
        "tgn:7018236",
        "tgn:7029392"
    ],
    "tgn:id":7251249,
    "tgn:name":"Oostrozebeke",
    "tgn:placetype":[
        "aat:300008347"
    ]
},
  "bbox": [],
  "geometry": {"coordinates":[3.337988,50.920926],"type":"Point"}
}