{
  "id": 7235529,
  "type": "Feature",
  "properties": {
    "tgn:hierarchy":[
        "tgn:7235529",
        "tgn:7002743",
        "tgn:7017076",
        "tgn:1000003",
        "tgn:1000074",
        "tgn:7029392"
    ],
    "tgn:id":7235529,
    "tgn:name":"Filippaka\u00edika",
    "tgn:placetype":[
        "aat:300008347"
    ]
},
  "bbox": [],
  "geometry": {"coordinates":[21.35,37.966667],"type":"Point"}
}