{
  "id": 2360276,
  "type": "Feature",
  "properties": {
    "tgn:hierarchy":[
        "tgn:2360276",
        "tgn:1002138",
        "tgn:1000001",
        "tgn:7012149",
        "tgn:7007157",
        "tgn:7029392"
    ],
    "tgn:id":2360276,
    "tgn:name":"Grass Valley",
    "tgn:placetype":[
        "aat:300008761"
    ]
},
  "bbox": [],
  "geometry": {"coordinates":[-122.1333,37.7833],"type":"Point"}
}