{
  "id": 2234382,
  "type": "Feature",
  "properties": {
    "tgn:hierarchy":[
        "tgn:2234382",
        "tgn:1000001",
        "tgn:7012149",
        "tgn:2002124",
        "tgn:7007827",
        "tgn:7029392"
    ],
    "tgn:id":2234382,
    "tgn:name":"Cheney Ranch",
    "tgn:placetype":[
        "aat:300132451"
    ]
},
  "bbox": [],
  "geometry": {"coordinates":[-109.4833,40.0667],"type":"Point"}
}