{
  "id": 1055597,
  "type": "Feature",
  "properties": {
    "tgn:hierarchy":[
        "tgn:1055597",
        "tgn:1000004",
        "tgn:7011457",
        "tgn:7014786",
        "tgn:7029392"
    ],
    "tgn:id":1055597,
    "tgn:name":"Konyrat",
    "tgn:placetype":[
        "aat:300008347"
    ]
},
  "bbox": [],
  "geometry": {"coordinates":[47.0167,49.5833],"type":"Point"}
}