<<<<<<< HEAD
{
  "id": 7484156,
  "type": "Feature",
  "properties": {
    "tgn:hierarchy":[
        "tgn:7484156",
        "tgn:1000004",
        "tgn:7490934",
        "tgn:1000141",
        "tgn:7029392"
    ],
    "tgn:id":7484156,
    "tgn:name":"Changrong Luqiao",
    "tgn:placetype":[
        "aat:300007836"
    ]
},
  "bbox": [],
  "geometry": {"coordinates":[120.331389,23.319722],"type":"Point"}
}
=======
{"geometry":{"type":"Point","coordinates":[120.331389,23.319722]},"type":"Feature","properties":{"hierarchy":["tgn:7484156","tgn:1000004","tgn:7490934","tgn:1000141","tgn:7029392"],"placetype":["aat:300007836"],"id":7484156,"name:xx":"Changrong Luqiao"}}
>>>>>>> 03f74aca74312dbeaf24d7e61306dd6a786dc3d0
