{
  "id": 7484156,
  "type": "Feature",
  "properties": {
    "tgn:hierarchy":[
        "tgn:7484156",
        "tgn:1000004",
        "tgn:7490934",
        "tgn:1000141",
        "tgn:7029392"
    ],
    "tgn:id":7484156,
    "tgn:name":"Changrong Luqiao",
    "tgn:placetype":[
        "aat:300007836"
    ]
},
  "bbox": [],
  "geometry": {"coordinates":[120.331389,23.319722],"type":"Point"}
}