{
  "id": 2508359,
  "type": "Feature",
  "properties": {
    "tgn:hierarchy":[
        "tgn:2508359",
        "tgn:1000001",
        "tgn:2001429",
        "tgn:7012149",
        "tgn:7007566",
        "tgn:7029392"
    ],
    "tgn:id":2508359,
    "tgn:name":"Middle Canyon Creek Tank",
    "tgn:placetype":[
        "aat:300006191"
    ]
},
  "bbox": [],
  "geometry": {"coordinates":[-108.35,33.4667],"type":"Point"}
}