{
  "id": 2119970,
  "type": "Feature",
  "properties": {
    "tgn:hierarchy":[
        "tgn:2119970",
        "tgn:1000001",
        "tgn:7012149",
        "tgn:2002291",
        "tgn:7013961",
        "tgn:7029392"
    ],
    "tgn:id":2119970,
    "tgn:name":"Silica",
    "tgn:placetype":[
        "aat:300387016"
    ]
},
  "bbox": [],
  "geometry": {"coordinates":[-80.2333,38.6833],"type":"Point"}
}