{
  "id": 2691469,
  "type": "Feature",
  "properties": {
    "tgn:hierarchy":[
        "tgn:2691469",
        "tgn:1000001",
        "tgn:7012149",
        "tgn:2002010",
        "tgn:7007826",
        "tgn:7029392"
    ],
    "tgn:id":2691469,
    "tgn:name":"Star Mountain",
    "tgn:placetype":[
        "aat:300008798"
    ]
},
  "bbox": [],
  "geometry": {"coordinates":[-103.7833,30.7667],"type":"Point"}
}