{
  "id": 2025598,
  "type": "Feature",
  "properties": {
    "tgn:hierarchy":[
        "tgn:2025598",
        "tgn:1000001",
        "tgn:7012149",
        "tgn:2000491",
        "tgn:7007250",
        "tgn:7029392"
    ],
    "tgn:id":2025598,
    "tgn:name":"Enaville",
    "tgn:placetype":[
        "aat:300008347",
        "aat:300387210"
    ]
},
  "bbox": [],
  "geometry": {"coordinates":[-116.2333,47.55],"type":"Point"}
}