<<<<<<< HEAD
{
  "id": 7351901,
  "type": "Feature",
  "properties": {
    "tgn:hierarchy":[
        "tgn:7351901",
        "tgn:7005581",
        "tgn:1000001",
        "tgn:7005560",
        "tgn:7029392"
    ],
    "tgn:id":7351901,
    "tgn:name":"Borjas",
    "tgn:placetype":[
        "aat:300007783"
    ]
},
  "bbox": [],
  "geometry": {"coordinates":[-105.666667,26.783333],"type":"Point"}
}
=======
{"geometry":{"type":"Point","coordinates":[-105.666667,26.783333]},"type":"Feature","properties":{"hierarchy":["tgn:7351901","tgn:7005581","tgn:1000001","tgn:7005560","tgn:7029392"],"placetype":["aat:300007783"],"id":7351901,"name:xx":"Borjas"}}
>>>>>>> 03f74aca74312dbeaf24d7e61306dd6a786dc3d0
