<<<<<<< HEAD
{
  "id": 2332551,
  "type": "Feature",
  "properties": {
    "tgn:hierarchy":[
        "tgn:2332551",
        "tgn:1000001",
        "tgn:7012149",
        "tgn:1003041",
        "tgn:7007710",
        "tgn:7029392"
    ],
    "tgn:id":2332551,
    "tgn:name":"Florey Knob",
    "tgn:placetype":[
        "aat:300008798"
    ]
},
  "bbox": [],
  "geometry": {"coordinates":[-76.0,41.5833],"type":"Point"}
}
=======
{"geometry":{"type":"Point","coordinates":[-76.000000,41.583300]},"type":"Feature","properties":{"hierarchy":["tgn:2332551","tgn:1000001","tgn:7012149","tgn:1003041","tgn:7007710","tgn:7029392"],"placetype":["aat:300008798"],"id":2332551,"name:xx":"Florey Knob"}}
>>>>>>> 03f74aca74312dbeaf24d7e61306dd6a786dc3d0
