{
  "id": 2445180,
  "type": "Feature",
  "properties": {
    "tgn:hierarchy":[
        "tgn:2445180",
        "tgn:1000001",
        "tgn:7012149",
        "tgn:2001706",
        "tgn:7007708",
        "tgn:7029392"
    ],
    "tgn:id":2445180,
    "tgn:name":"Lemolo Lake",
    "tgn:placetype":[
        "aat:300006191"
    ]
},
  "bbox": [],
  "geometry": {"coordinates":[-122.1833,43.3167],"type":"Point"}
}