{
  "id": 7553893,
  "type": "Feature",
  "properties": {
    "tgn:hierarchy":[
        "tgn:7553893",
        "tgn:1000004",
        "tgn:7000198",
        "tgn:7016722",
        "tgn:7029392"
    ],
    "tgn:id":7553893,
    "tgn:name:en":"Mustaf\u0101b\u0101d",
    "tgn:placetype":[
        "aat:300008347"
    ]
},
  "bbox": [],
  "geometry": {"coordinates":[78.576224,27.307955],"type":"Point"}
}