{
  "id": 2655384,
  "type": "Feature",
  "properties": {
    "tgn:hierarchy":[
        "tgn:2655384",
        "tgn:1000001",
        "tgn:7012149",
        "tgn:2000476",
        "tgn:7007250",
        "tgn:7029392"
    ],
    "tgn:id":2655384,
    "tgn:name":"Sharman Creek",
    "tgn:placetype":[
        "aat:300008706"
    ]
},
  "bbox": [],
  "geometry": {"coordinates":[-115.4167,45.7167],"type":"Point"}
}