{
  "id": 2124443,
  "type": "Feature",
  "properties": {
    "tgn:hierarchy":[
        "tgn:2124443",
        "tgn:1000001",
        "tgn:7012149",
        "tgn:1002636",
        "tgn:7007708",
        "tgn:7029392"
    ],
    "tgn:id":2124443,
    "tgn:name":"Aarhus Reservoir",
    "tgn:placetype":[
        "aat:300006191"
    ]
},
  "bbox": [],
  "geometry": {"coordinates":[-122.8167,45.0333],"type":"Point"}
}