{
  "id": 1047113,
  "type": "Feature",
  "properties": {
    "tgn:hierarchy":[
        "tgn:1047113",
        "tgn:1003489",
        "tgn:7004610",
        "tgn:1000003",
        "tgn:1000080",
        "tgn:7029392"
    ],
    "tgn:id":1047113,
    "tgn:name":"Tito",
    "tgn:placetype":[
        "aat:300008347"
    ]
},
  "bbox": [],
  "geometry": {"coordinates":[15.666667,40.583333],"type":"Point"}
}