{
  "id": 7576975,
  "type": "Feature",
  "properties": {
    "tgn:hierarchy":[
        "tgn:7576975",
        "tgn:1000004",
        "tgn:7000198",
        "tgn:1001894",
        "tgn:7029392"
    ],
    "tgn:id":7576975,
    "tgn:name:en":"Kareri",
    "tgn:placetype":[
        "aat:300008347"
    ]
},
  "bbox": [],
  "geometry": {"coordinates":[76.199381,23.445656],"type":"Point"}
}