{
  "id": 7473857,
  "type": "Feature",
  "properties": {
    "tgn:hierarchy":[
        "tgn:7473857",
        "tgn:1000004",
        "tgn:7467799",
        "tgn:1000141",
        "tgn:7029392"
    ],
    "tgn:id":7473857,
    "tgn:name":"Yuanquan",
    "tgn:placetype":[
        "aat:300008347"
    ]
},
  "bbox": [],
  "geometry": {"coordinates":[120.642357,23.798793],"type":"Point"}
}