{
  "id": 2565907,
  "type": "Feature",
  "properties": {
    "tgn:hierarchy":[
        "tgn:2565907",
        "tgn:1000001",
        "tgn:7012149",
        "tgn:2000378",
        "tgn:7007248",
        "tgn:7029392"
    ],
    "tgn:id":2565907,
    "tgn:name":"Palm Lake",
    "tgn:placetype":[
        "aat:300006191"
    ]
},
  "bbox": [],
  "geometry": {"coordinates":[-82.7167,32.3667],"type":"Point"}
}