{
  "id": 2654731,
  "type": "Feature",
  "properties": {
    "tgn:hierarchy":[
        "tgn:2654731",
        "tgn:1000001",
        "tgn:2002109",
        "tgn:7012149",
        "tgn:7007827",
        "tgn:7029392"
    ],
    "tgn:id":2654731,
    "tgn:name":"Shakespeare Mine",
    "tgn:placetype":[
        "aat:300000390"
    ]
},
  "bbox": [],
  "geometry": {"coordinates":[-111.9667,37.65],"type":"Point"}
}