{
  "id": 2328567,
  "type": "Feature",
  "properties": {
    "tgn:hierarchy":[
        "tgn:2328567",
        "tgn:1000001",
        "tgn:2002256",
        "tgn:7012149",
        "tgn:7013961",
        "tgn:7029392"
    ],
    "tgn:id":2328567,
    "tgn:name":"Fisher Run",
    "tgn:placetype":[
        "aat:300008699"
    ]
},
  "bbox": [],
  "geometry": {"coordinates":[-80.6667,38.5833],"type":"Point"}
}