{
  "id": 7515247,
  "type": "Feature",
  "properties": {
    "tgn:hierarchy":[
        "tgn:7515247",
        "tgn:1009227",
        "tgn:1000226",
        "tgn:1000006",
        "tgn:7016850",
        "tgn:7029392"
    ],
    "tgn:id":7515247,
    "tgn:name:en":"Coal Creek",
    "tgn:placetype":[
        "aat:300008699"
    ]
},
  "bbox": [],
  "geometry": {"coordinates":[171.233333,-42.433333],"type":"Point"}
}