{
  "id": 2573836,
  "type": "Feature",
  "properties": {
    "tgn:hierarchy":[
        "tgn:2573836",
        "tgn:1000001",
        "tgn:2002367",
        "tgn:7012149",
        "tgn:7007923",
        "tgn:7029392"
    ],
    "tgn:id":2573836,
    "tgn:name":"Pedersen Reservoir",
    "tgn:placetype":[
        "aat:300006191"
    ]
},
  "bbox": [],
  "geometry": {"coordinates":[-105.6333,44.0833],"type":"Point"}
}