{
  "id": 7586058,
  "type": "Feature",
  "properties": {
    "tgn:hierarchy":[
        "tgn:7586058",
        "tgn:1000004",
        "tgn:7000198",
        "tgn:7000799",
        "tgn:7029392"
    ],
    "tgn:id":7586058,
    "tgn:name:en":"Nahom",
    "tgn:placetype":[
        "aat:300008347"
    ]
},
  "bbox": [],
  "geometry": {"coordinates":[74.336111,34.355556],"type":"Point"}
}