{
  "id": 2060962,
  "type": "Feature",
  "properties": {
    "tgn:hierarchy":[
        "tgn:2060962",
        "tgn:1000001",
        "tgn:7012149",
        "tgn:1002619",
        "tgn:7007523",
        "tgn:7029392"
    ],
    "tgn:id":2060962,
    "tgn:name":"Woodville",
    "tgn:placetype":[
        "aat:300008347",
        "aat:300387210"
    ]
},
  "bbox": [],
  "geometry": {"coordinates":[-92.3333,39.6167],"type":"Point"}
}