{
  "id": 2647179,
  "type": "Feature",
  "properties": {
    "tgn:hierarchy":[
        "tgn:2647179",
        "tgn:1000001",
        "tgn:7012149",
        "tgn:2001950",
        "tgn:7007826",
        "tgn:7029392"
    ],
    "tgn:id":2647179,
    "tgn:name":"Schicke Point",
    "tgn:placetype":[
        "aat:300008850"
    ]
},
  "bbox": [],
  "geometry": {"coordinates":[-96.35,28.6167],"type":"Point"}
}