{
  "id": 2199666,
  "type": "Feature",
  "properties": {
    "tgn:hierarchy":[
        "tgn:2199666",
        "tgn:1000001",
        "tgn:7012149",
        "tgn:7007708",
        "tgn:7029392"
    ],
    "tgn:id":2199666,
    "tgn:name":"Brush Hollow",
    "tgn:placetype":[
        "aat:300008761"
    ]
},
  "bbox": [],
  "geometry": {"coordinates":[-120.3833,45.0833],"type":"Point"}
}