<<<<<<< HEAD
{
  "id": 2767642,
  "type": "Feature",
  "properties": {
    "tgn:hierarchy":[
        "tgn:2767642",
        "tgn:7002659",
        "tgn:1000001",
        "tgn:2000004",
        "tgn:7012149",
        "tgn:7029392"
    ],
    "tgn:id":2767642,
    "tgn:name":"Whited Lake",
    "tgn:placetype":[
        "aat:300006191"
    ]
},
  "bbox": [],
  "geometry": {"coordinates":[-86.4833,33.9667],"type":"Point"}
}
=======
{"geometry":{"type":"Point","coordinates":[-86.483300,33.966700]},"type":"Feature","properties":{"hierarchy":["tgn:2767642","tgn:7002659","tgn:1000001","tgn:2000004","tgn:7012149","tgn:7029392"],"placetype":["aat:300006191"],"id":2767642,"name:xx":"Whited Lake"}}
>>>>>>> 03f74aca74312dbeaf24d7e61306dd6a786dc3d0
