{
  "id": 2767642,
  "type": "Feature",
  "properties": {
    "tgn:hierarchy":[
        "tgn:2767642",
        "tgn:7002659",
        "tgn:1000001",
        "tgn:2000004",
        "tgn:7012149",
        "tgn:7029392"
    ],
    "tgn:id":2767642,
    "tgn:name":"Whited Lake",
    "tgn:placetype":[
        "aat:300006191"
    ]
},
  "bbox": [],
  "geometry": {"coordinates":[-86.4833,33.9667],"type":"Point"}
}