<<<<<<< HEAD
{
  "id": 7022931,
  "type": "Feature",
  "properties": {
    "tgn:hierarchy":[
        "tgn:7022931",
        "tgn:1000001",
        "tgn:7012149",
        "tgn:7029392"
    ],
    "tgn:id":7022931,
    "tgn:name":"East Fork Illinois River",
    "tgn:placetype":[
        "aat:300008707"
    ]
},
  "bbox": [],
  "geometry": {"coordinates":[-123.6,41.8667],"type":"Point"}
}
=======
{"geometry":{"type":"Point","coordinates":[-123.600000,41.866700]},"type":"Feature","properties":{"hierarchy":["tgn:7022931","tgn:1000001","tgn:7012149","tgn:7029392"],"placetype":["aat:300008707"],"id":7022931,"name:xx":"East Fork Illinois River"}}
>>>>>>> 03f74aca74312dbeaf24d7e61306dd6a786dc3d0
