{
  "id": 2287078,
  "type": "Feature",
  "properties": {
    "tgn:hierarchy":[
        "tgn:2287078",
        "tgn:1000001",
        "tgn:7012149",
        "tgn:1002636",
        "tgn:7007708",
        "tgn:7029392"
    ],
    "tgn:id":2287078,
    "tgn:name":"Dicker Reservoir",
    "tgn:placetype":[
        "aat:300006191"
    ]
},
  "bbox": [],
  "geometry": {"coordinates":[-123.1333,44.85],"type":"Point"}
}