<<<<<<< HEAD
{
  "id": 7363776,
  "type": "Feature",
  "properties": {
    "tgn:hierarchy":[
        "tgn:7363776",
        "tgn:7005581",
        "tgn:1000001",
        "tgn:7005560",
        "tgn:7029392"
    ],
    "tgn:id":7363776,
    "tgn:name":"El Morado, Cerro",
    "tgn:placetype":[
        "aat:300008795"
    ]
},
  "bbox": [],
  "geometry": {"coordinates":[-107.083333,30.15],"type":"Point"}
}
=======
{"geometry":{"type":"Point","coordinates":[-107.083333,30.150000]},"type":"Feature","properties":{"hierarchy":["tgn:7363776","tgn:7005581","tgn:1000001","tgn:7005560","tgn:7029392"],"placetype":["aat:300008795"],"id":7363776,"name:xx":"El Morado, Cerro"}}
>>>>>>> 03f74aca74312dbeaf24d7e61306dd6a786dc3d0
