{
  "id": 2381454,
  "type": "Feature",
  "properties": {
    "tgn:hierarchy":[
        "tgn:2381454",
        "tgn:1000001",
        "tgn:7012149",
        "tgn:2001067",
        "tgn:7007521",
        "tgn:7029392"
    ],
    "tgn:id":2381454,
    "tgn:name":"Hay Creek",
    "tgn:placetype":[
        "aat:300008706"
    ]
},
  "bbox": [],
  "geometry": {"coordinates":[-92.4167,47.4167],"type":"Point"}
}