{
  "id": 2476975,
  "type": "Feature",
  "properties": {
    "tgn:hierarchy":[
        "tgn:2476975",
        "tgn:1000001",
        "tgn:7012149",
        "tgn:2001276",
        "tgn:7007524",
        "tgn:7029392"
    ],
    "tgn:id":2476975,
    "tgn:name":"Lynch Coulee",
    "tgn:placetype":[
        "aat:300008761"
    ]
},
  "bbox": [],
  "geometry": {"coordinates":[-107.25,47.0833],"type":"Point"}
}