{
  "id": 7268531,
  "type": "Feature",
  "properties": {
    "tgn:concordances":{
        "gn:id":"2748616"
    },
    "tgn:hierarchy":[
        "tgn:7268531",
        "tgn:7003614",
        "tgn:1000003",
        "tgn:7016845",
        "tgn:7029392"
    ],
    "tgn:id":7268531,
    "tgn:name:nl":"Pieperij",
    "tgn:placetype":[
        "aat:300008347"
    ]
},
  "bbox": [],
  "geometry": {"coordinates":[6.366667,52.633333],"type":"Point"}
}