{
  "id": 2207438,
  "type": "Feature",
  "properties": {
    "tgn:hierarchy":[
        "tgn:2207438",
        "tgn:1000001",
        "tgn:1002361",
        "tgn:7012149",
        "tgn:7007828",
        "tgn:7029392"
    ],
    "tgn:id":2207438,
    "tgn:name":"Bunnell Brook",
    "tgn:placetype":[
        "aat:300008699"
    ]
},
  "bbox": [],
  "geometry": {"coordinates":[-71.5667,44.9833],"type":"Point"}
}