{
  "id": 2523816,
  "type": "Feature",
  "properties": {
    "tgn:hierarchy":[
        "tgn:2523816",
        "tgn:1000001",
        "tgn:7012149",
        "tgn:2002072",
        "tgn:7007826",
        "tgn:7029392"
    ],
    "tgn:id":2523816,
    "tgn:name":"Moran Lake",
    "tgn:placetype":[
        "aat:300006191"
    ]
},
  "bbox": [],
  "geometry": {"coordinates":[-99.1667,32.5333],"type":"Point"}
}