{
  "id": 1076293,
  "type": "Feature",
  "properties": {
    "tgn:hierarchy":[
        "tgn:1076293",
        "tgn:1000004",
        "tgn:7000198",
        "tgn:7031786",
        "tgn:7029392"
    ],
    "tgn:id":1076293,
    "tgn:name:en":"Mussoorie",
    "tgn:placetype":[
        "aat:300008347"
    ]
},
  "bbox": [],
  "geometry": {"coordinates":[78.054976,30.457103],"type":"Point"}
}