{
  "id": 2484258,
  "type": "Feature",
  "properties": {
    "tgn:hierarchy":[
        "tgn:2484258",
        "tgn:1000001",
        "tgn:7012149",
        "tgn:2001556",
        "tgn:7007709",
        "tgn:7029392"
    ],
    "tgn:id":2484258,
    "tgn:name":"Laurel Branch",
    "tgn:placetype":[
        "aat:300008699"
    ]
},
  "bbox": [],
  "geometry": {"coordinates":[-82.2167,35.75],"type":"Point"}
}