{
  "id": 2391694,
  "type": "Feature",
  "properties": {
    "tgn:hierarchy":[
        "tgn:2391694",
        "tgn:1000001",
        "tgn:7012149",
        "tgn:2001756",
        "tgn:7007712",
        "tgn:7029392"
    ],
    "tgn:id":2391694,
    "tgn:name":"Hillside",
    "tgn:placetype":[
        "aat:300008347"
    ]
},
  "bbox": [],
  "geometry": {"coordinates":[-81.1667,33.95],"type":"Point"}
}