<<<<<<< HEAD
{
  "id": 7356379,
  "type": "Feature",
  "properties": {
    "tgn:hierarchy":[
        "tgn:7356379",
        "tgn:7005578",
        "tgn:1000001",
        "tgn:7005560",
        "tgn:7029392"
    ],
    "tgn:id":7356379,
    "tgn:name":"California, Laguna",
    "tgn:placetype":[
        "aat:300008680"
    ]
},
  "bbox": [],
  "geometry": {"coordinates":[-90.916667,17.9],"type":"Point"}
}
=======
{"geometry":{"type":"Point","coordinates":[-90.916667,17.900000]},"type":"Feature","properties":{"hierarchy":["tgn:7356379","tgn:7005578","tgn:1000001","tgn:7005560","tgn:7029392"],"placetype":["aat:300008680"],"id":7356379,"name:xx":"California, Laguna"}}
>>>>>>> 03f74aca74312dbeaf24d7e61306dd6a786dc3d0
