{
  "id": 7286807,
  "type": "Feature",
  "properties": {
    "tgn:hierarchy":[
        "tgn:7286807",
        "tgn:1001768",
        "tgn:1000049",
        "tgn:1000002",
        "tgn:7029392"
    ],
    "tgn:id":7286807,
    "tgn:name":"Golpe de Agua, Paso",
    "tgn:placetype":[
        "aat:300259572"
    ]
},
  "bbox": [],
  "geometry": {"coordinates":[-70.316667,-32.183333],"type":"Point"}
}