{
  "id": 2201242,
  "type": "Feature",
  "properties": {
    "tgn:hierarchy":[
        "tgn:2201242",
        "tgn:7030516",
        "tgn:7006450",
        "tgn:1000001",
        "tgn:7012149",
        "tgn:7029392"
    ],
    "tgn:id":2201242,
    "tgn:name":"Buchanan Point",
    "tgn:placetype":[
        "aat:300008850"
    ]
},
  "bbox": [],
  "geometry": {"coordinates":[173.4167,52.8333],"type":"Point"}
}