{
  "id": 1098569,
  "type": "Feature",
  "properties": {
    "tgn:hierarchy":[
        "tgn:1098569",
        "tgn:7000490",
        "tgn:1000006",
        "tgn:7001830",
        "tgn:7029392"
    ],
    "tgn:id":1098569,
    "tgn:name":"Wondai",
    "tgn:placetype":[
        "aat:300008347"
    ]
},
  "bbox": [],
  "geometry": {"coordinates":[151.85,-26.3167],"type":"Point"}
}