{
  "id": 2728112,
  "type": "Feature",
  "properties": {
    "tgn:hierarchy":[
        "tgn:2728112",
        "tgn:2002308",
        "tgn:1000001",
        "tgn:7012149",
        "tgn:7007922",
        "tgn:7029392"
    ],
    "tgn:id":2728112,
    "tgn:name":"Trapper Lake",
    "tgn:placetype":[
        "aat:300008680"
    ]
},
  "bbox": [],
  "geometry": {"coordinates":[-91.0833,46.25],"type":"Point"}
}