{
  "id": 2413868,
  "type": "Feature",
  "properties": {
    "tgn:hierarchy":[
        "tgn:2413868",
        "tgn:1000001",
        "tgn:2000470",
        "tgn:7012149",
        "tgn:7007250",
        "tgn:7029392"
    ],
    "tgn:id":2413868,
    "tgn:name":"Iron Bog Creek",
    "tgn:placetype":[
        "aat:300008706"
    ]
},
  "bbox": [],
  "geometry": {"coordinates":[-113.75,43.6333],"type":"Point"}
}