{
  "id": 2677452,
  "type": "Feature",
  "properties": {
    "tgn:hierarchy":[
        "tgn:2677452",
        "tgn:1000001",
        "tgn:2001265",
        "tgn:7012149",
        "tgn:7007524",
        "tgn:7029392"
    ],
    "tgn:id":2677452,
    "tgn:name":"South Carter Spring",
    "tgn:placetype":[
        "aat:300008697"
    ]
},
  "bbox": [],
  "geometry": {"coordinates":[-104.15,45.6333],"type":"Point"}
}