{
  "id": 2230358,
  "type": "Feature",
  "properties": {
    "tgn:hierarchy":[
        "tgn:2230358",
        "tgn:2002365",
        "tgn:1000001",
        "tgn:7012149",
        "tgn:7007923",
        "tgn:7029392"
    ],
    "tgn:id":2230358,
    "tgn:name":"Centennial Ridge",
    "tgn:placetype":[
        "aat:300266640"
    ]
},
  "bbox": [],
  "geometry": {"coordinates":[-106.1667,41.2667],"type":"Point"}
}