{
  "id": 7130104,
  "type": "Feature",
  "properties": {
    "tgn:hierarchy":[
        "tgn:7130104",
        "tgn:1000003",
        "tgn:7003676",
        "tgn:7000084",
        "tgn:7029392"
    ],
    "tgn:id":7130104,
    "tgn:name":"Meinersand",
    "tgn:placetype":[
        "aat:300008347"
    ]
},
  "bbox": [],
  "geometry": {"coordinates":[10.533333,52.383333],"type":"Point"}
}