{
  "id": 2656539,
  "type": "Feature",
  "properties": {
    "tgn:hierarchy":[
        "tgn:2656539",
        "tgn:1000001",
        "tgn:7006451",
        "tgn:7012149",
        "tgn:2000103",
        "tgn:7029392"
    ],
    "tgn:id":2656539,
    "tgn:name":"Sheep Camp Tank",
    "tgn:placetype":[
        "aat:300006191"
    ]
},
  "bbox": [],
  "geometry": {"coordinates":[-112.1833,34.7667],"type":"Point"}
}