{
  "id": 7519235,
  "type": "Feature",
  "properties": {
    "tgn:hierarchy":[
        "tgn:7519235",
        "tgn:1009227",
        "tgn:1000226",
        "tgn:7016822",
        "tgn:1000006",
        "tgn:7029392"
    ],
    "tgn:id":7519235,
    "tgn:name:en":"Broad Head",
    "tgn:placetype":[
        "aat:300008850"
    ]
},
  "bbox": [],
  "geometry": {"coordinates":[167.65,-47.266667],"type":"Point"}
}