{
  "id": 7432058,
  "type": "Feature",
  "properties": {
    "tgn:hierarchy":[
        "tgn:7432058",
        "tgn:1001853",
        "tgn:1000001",
        "tgn:7005560",
        "tgn:7029392"
    ],
    "tgn:id":7432058,
    "tgn:name":"Pe\u00f1a Blanca",
    "tgn:placetype":[
        "aat:300008347"
    ]
},
  "bbox": [],
  "geometry": {"coordinates":[-103.433333,28.566667],"type":"Point"}
}