{
  "id": 2480255,
  "type": "Feature",
  "properties": {
    "tgn:hierarchy":[
        "tgn:2480255",
        "tgn:1000001",
        "tgn:7016172",
        "tgn:7012149",
        "tgn:2000139",
        "tgn:7029392"
    ],
    "tgn:id":2480255,
    "tgn:name":"Lake Point",
    "tgn:placetype":[
        "aat:300008850"
    ]
},
  "bbox": [],
  "geometry": {"coordinates":[-91.5167,34.0833],"type":"Point"}
}