{
  "id": 2249610,
  "type": "Feature",
  "properties": {
    "tgn:hierarchy":[
        "tgn:2249610",
        "tgn:1000001",
        "tgn:7012149",
        "tgn:2000910",
        "tgn:7007256",
        "tgn:7029392"
    ],
    "tgn:id":2249610,
    "tgn:name":"Coles Island",
    "tgn:placetype":[
        "aat:300055621"
    ]
},
  "bbox": [],
  "geometry": {"coordinates":[-92.35,30.0333],"type":"Point"}
}