{
  "id": 2512290,
  "type": "Feature",
  "properties": {
    "tgn:hierarchy":[
        "tgn:2512290",
        "tgn:1000001",
        "tgn:7012149",
        "tgn:2001494",
        "tgn:7007709",
        "tgn:7029392"
    ],
    "tgn:id":2512290,
    "tgn:name":"Mill Brook",
    "tgn:placetype":[
        "aat:300008347"
    ]
},
  "bbox": [],
  "geometry": {"coordinates":[-80.3667,36.15],"type":"Point"}
}