{
  "id": 7397874,
  "type": "Feature",
  "properties": {
    "tgn:hierarchy":[
        "tgn:7397874",
        "tgn:1000001",
        "tgn:1001893",
        "tgn:7005560",
        "tgn:7029392"
    ],
    "tgn:id":7397874,
    "tgn:name":"Zempoala, Lagunas de",
    "tgn:placetype":[
        "aat:300266561"
    ]
},
  "bbox": [],
  "geometry": {"coordinates":[-99.3175,19.049444],"type":"Point"}
}