{
  "id": 7278201,
  "type": "Feature",
  "properties": {
    "tgn:hierarchy":[
        "tgn:7278201",
        "tgn:1001702",
        "tgn:1000049",
        "tgn:1000002",
        "tgn:7029392"
    ],
    "tgn:id":7278201,
    "tgn:name":"Ripita, Islotes",
    "tgn:placetype":[
        "aat:300008791"
    ]
},
  "bbox": [],
  "geometry": {"coordinates":[-70.183333,-55.316667],"type":"Point"}
}