{
  "id": 7550411,
  "type": "Feature",
  "properties": {
    "tgn:hierarchy":[
        "tgn:7550411",
        "tgn:1000004",
        "tgn:7000198",
        "tgn:7016788",
        "tgn:7029392"
    ],
    "tgn:id":7550411,
    "tgn:name:en":"Dh\u012brw\u0101s",
    "tgn:placetype":[
        "aat:300008347"
    ]
},
  "bbox": [],
  "geometry": {"coordinates":[74.916506,28.844491],"type":"Point"}
}