{
  "id": 2293219,
  "type": "Feature",
  "properties": {
    "tgn:hierarchy":[
        "tgn:2293219",
        "tgn:1000001",
        "tgn:7012149",
        "tgn:7007919",
        "tgn:7029392"
    ],
    "tgn:id":2293219,
    "tgn:name":"Double Branch",
    "tgn:placetype":[
        "aat:300008699"
    ]
},
  "bbox": [],
  "geometry": {"coordinates":[-78.85,37.1167],"type":"Point"}
}