{
  "id": 2653522,
  "type": "Feature",
  "properties": {
    "tgn:hierarchy":[
        "tgn:2653522",
        "tgn:1000001",
        "tgn:7012149",
        "tgn:2001312",
        "tgn:7007524",
        "tgn:7029392"
    ],
    "tgn:id":2653522,
    "tgn:name":"Seventh Coulee",
    "tgn:placetype":[
        "aat:300008761"
    ]
},
  "bbox": [],
  "geometry": {"coordinates":[-106.8167,47.8667],"type":"Point"}
}