{
  "id": 7508366,
  "type": "Feature",
  "properties": {
    "tgn:hierarchy":[
        "tgn:7508366",
        "tgn:7000509",
        "tgn:1008380",
        "tgn:1000226",
        "tgn:1000006",
        "tgn:7029392"
    ],
    "tgn:id":7508366,
    "tgn:name:en":"Orakei",
    "tgn:placetype":[
        "aat:300008795"
    ]
},
  "bbox": [],
  "geometry": {"coordinates":[176.266667,-38.55],"type":"Point"}
}