{
  "id": 7438961,
  "type": "Feature",
  "properties": {
    "tgn:hierarchy":[
        "tgn:7438961",
        "tgn:1000001",
        "tgn:7005591",
        "tgn:7005560",
        "tgn:7029392"
    ],
    "tgn:id":7438961,
    "tgn:name":"Sartenejas, Cerro",
    "tgn:placetype":[
        "aat:300008795"
    ]
},
  "bbox": [],
  "geometry": {"coordinates":[-97.916667,17.316667],"type":"Point"}
}