<<<<<<< HEAD
{
  "id": 2403980,
  "type": "Feature",
  "properties": {
    "tgn:hierarchy":[
        "tgn:2403980",
        "tgn:1000001",
        "tgn:7012149",
        "tgn:2001860",
        "tgn:7007825",
        "tgn:7029392"
    ],
    "tgn:id":2403980,
    "tgn:name":"Howell Creek",
    "tgn:placetype":[
        "aat:300008706"
    ]
},
  "bbox": [],
  "geometry": {"coordinates":[-89.2833,35.1833],"type":"Point"}
}
=======
{"geometry":{"type":"Point","coordinates":[-89.283300,35.183300]},"type":"Feature","properties":{"hierarchy":["tgn:2403980","tgn:1000001","tgn:7012149","tgn:2001860","tgn:7007825","tgn:7029392"],"placetype":["aat:300008706"],"id":2403980,"name:xx":"Howell Creek"}}
>>>>>>> 03f74aca74312dbeaf24d7e61306dd6a786dc3d0
