{
  "id": 7502405,
  "type": "Feature",
  "properties": {
    "tgn:hierarchy":[
        "tgn:7502405",
        "tgn:7001010",
        "tgn:1000004",
        "tgn:1000141",
        "tgn:7029392"
    ],
    "tgn:id":7502405,
    "tgn:name":"Dongxing",
    "tgn:placetype":[
        "aat:300008347"
    ]
},
  "bbox": [],
  "geometry": {"coordinates":[121.530833,23.635],"type":"Point"}
}