{
  "id": 2746075,
  "type": "Feature",
  "properties": {
    "tgn:hierarchy":[
        "tgn:2746075",
        "tgn:1000001",
        "tgn:7012149",
        "tgn:2002360",
        "tgn:7007922",
        "tgn:7029392"
    ],
    "tgn:id":2746075,
    "tgn:name":"Vollmers Lake",
    "tgn:placetype":[
        "aat:300008680"
    ]
},
  "bbox": [],
  "geometry": {"coordinates":[-91.5667,45.7333],"type":"Point"}
}