{
  "id": 2198656,
  "type": "Feature",
  "properties": {
    "tgn:hierarchy":[
        "tgn:2198656",
        "tgn:1000001",
        "tgn:7012149",
        "tgn:7007828",
        "tgn:7029392"
    ],
    "tgn:id":2198656,
    "tgn:name":"Browns River",
    "tgn:placetype":[
        "aat:300008707"
    ]
},
  "bbox": [],
  "geometry": {"coordinates":[-72.8167,44.5333],"type":"Point"}
}