{
  "id": 2754360,
  "type": "Feature",
  "properties": {
    "tgn:hierarchy":[
        "tgn:2754360",
        "tgn:1000001",
        "tgn:2001260",
        "tgn:7012149",
        "tgn:7007524",
        "tgn:7029392"
    ],
    "tgn:id":2754360,
    "tgn:name":"Waukena Lake",
    "tgn:placetype":[
        "aat:300006191"
    ]
},
  "bbox": [],
  "geometry": {"coordinates":[-112.95,45.55],"type":"Point"}
}