{
  "id": 2377306,
  "type": "Feature",
  "properties": {
    "tgn:hierarchy":[
        "tgn:2377306",
        "tgn:1000001",
        "tgn:7012149",
        "tgn:1002897",
        "tgn:7007920",
        "tgn:7029392"
    ],
    "tgn:id":2377306,
    "tgn:name":"Harmony Falls Landing",
    "tgn:placetype":[
        "aat:300008347"
    ]
},
  "bbox": [],
  "geometry": {"coordinates":[-122.1333,46.25],"type":"Point"}
}