{
  "id": 1107922,
  "type": "Feature",
  "properties": {
    "tgn:hierarchy":[
        "tgn:1107922",
        "tgn:1006287",
        "tgn:1000001",
        "tgn:7012149",
        "tgn:7007157",
        "tgn:7014005",
        "tgn:7029392"
    ],
    "tgn:id":1107922,
    "tgn:name":"Caroline Livermore, Mount",
    "tgn:placetype":[
        "aat:300008777"
    ]
},
  "bbox": [],
  "geometry": {"coordinates":[-122.4167,37.85],"type":"Point"}
}