{
  "id": 7449592,
  "type": "Feature",
  "properties": {
    "tgn:hierarchy":[
        "tgn:7449592",
        "tgn:7002445",
        "tgn:1000003",
        "tgn:7008175",
        "tgn:7008591",
        "tgn:7029392"
    ],
    "tgn:id":7449592,
    "tgn:name:en":"Hambledon",
    "tgn:placetype":[
        "aat:300008347"
    ]
},
  "bbox": [],
  "geometry": {"coordinates":[-0.616667,51.116667],"type":"Point"}
}