{
  "id": 7466891,
  "type": "Feature",
  "properties": {
    "tgn:hierarchy":[
        "tgn:7466891",
        "tgn:7002444",
        "tgn:1000003",
        "tgn:7008082",
        "tgn:7008591",
        "tgn:7029392"
    ],
    "tgn:id":7466891,
    "tgn:name:en":"Am Fiar Loch",
    "tgn:placetype":[
        "aat:300008680"
    ]
},
  "bbox": [],
  "geometry": {"coordinates":[-4.916667,57.466667],"type":"Point"}
}