{
  "id": 7561667,
  "type": "Feature",
  "properties": {
    "tgn:hierarchy":[
        "tgn:7561667",
        "tgn:1000004",
        "tgn:7000198",
        "tgn:7016722",
        "tgn:7029392"
    ],
    "tgn:id":7561667,
    "tgn:name:en":"Part\u0101pura",
    "tgn:placetype":[
        "aat:300008347"
    ]
},
  "bbox": [],
  "geometry": {"coordinates":[79.13569,26.851881],"type":"Point"}
}