{
  "id": 7384409,
  "type": "Feature",
  "properties": {
    "tgn:hierarchy":[
        "tgn:7384409",
        "tgn:1000001",
        "tgn:1001906",
        "tgn:7005560",
        "tgn:7029392"
    ],
    "tgn:id":7384409,
    "tgn:name":"Moderna",
    "tgn:placetype":[
        "aat:300008347"
    ]
},
  "bbox": [],
  "geometry": {"coordinates":[-104.65,21.45],"type":"Point"}
}