{
  "id": 7045356,
  "type": "Feature",
  "properties": {
    "tgn:hierarchy":[
        "tgn:7045356",
        "tgn:1003483",
        "tgn:1000003",
        "tgn:7003240",
        "tgn:1000080",
        "tgn:7029392"
    ],
    "tgn:id":7045356,
    "tgn:name":"Calibano",
    "tgn:placetype":[
        "aat:300008347"
    ]
},
  "bbox": [],
  "geometry": {"coordinates":[12.866667,43.883333],"type":"Point"}
}