{
  "id": 1002429,
  "type": "Feature",
  "properties": {
    "tgn:hierarchy":[
        "tgn:1002429",
        "tgn:1000001",
        "tgn:7012149",
        "tgn:7007826",
        "tgn:7029392"
    ],
    "tgn:id":1002429,
    "tgn:name":"Grimes",
    "tgn:placetype":[
        "aat:300387145",
        "aat:300000771"
    ]
},
  "bbox": [],
  "geometry": {"coordinates":[-95.9667,30.5333],"type":"Point"}
}