{
  "id": 2105685,
  "type": "Feature",
  "properties": {
    "tgn:hierarchy":[
        "tgn:2105685",
        "tgn:1000001",
        "tgn:7012149",
        "tgn:1002220",
        "tgn:7007826",
        "tgn:7029392"
    ],
    "tgn:id":2105685,
    "tgn:name":"Lockhart",
    "tgn:placetype":[
        "aat:300008347"
    ]
},
  "bbox": [],
  "geometry": {"coordinates":[-97.6667,29.8833],"type":"Point"}
}