<<<<<<< HEAD
{
  "id": 7050939,
  "type": "Feature",
  "properties": {
    "tgn:hierarchy":[
        "tgn:7050939",
        "tgn:7005126",
        "tgn:1000003",
        "tgn:7003120",
        "tgn:1000080",
        "tgn:7029392"
    ],
    "tgn:id":7050939,
    "tgn:name":"La Miniera",
    "tgn:placetype":[
        "aat:300008347"
    ]
},
  "bbox": [],
  "geometry": {"coordinates":[7.266667,44.366667],"type":"Point"}
}
=======
{"geometry":{"type":"Point","coordinates":[7.266667,44.366667]},"type":"Feature","properties":{"hierarchy":["tgn:7050939","tgn:7005126","tgn:1000003","tgn:7003120","tgn:1000080","tgn:7029392"],"placetype":["aat:300008347"],"id":7050939,"name:xx":"La Miniera"}}
>>>>>>> 03f74aca74312dbeaf24d7e61306dd6a786dc3d0
