{
  "id": 7217595,
  "type": "Feature",
  "properties": {
    "tgn:hierarchy":[
        "tgn:7217595",
        "tgn:7011161",
        "tgn:7002674",
        "tgn:1000003",
        "tgn:1000074",
        "tgn:7029392"
    ],
    "tgn:id":7217595,
    "tgn:name":"Plak\u00f3n Lagk\u00e1di",
    "tgn:placetype":[
        "aat:300008699"
    ]
},
  "bbox": [],
  "geometry": {"coordinates":[26.143611,38.458333],"type":"Point"}
}