{
  "id": 7446895,
  "type": "Feature",
  "properties": {
    "tgn:hierarchy":[
        "tgn:7446895",
        "tgn:7002445",
        "tgn:1000003",
        "tgn:7019065",
        "tgn:7008591",
        "tgn:7029392"
    ],
    "tgn:id":7446895,
    "tgn:name:en":"Salt Scars, The",
    "tgn:placetype":[
        "aat:300011692"
    ]
},
  "bbox": [],
  "geometry": {"coordinates":[-1.060833,54.625556],"type":"Point"}
}