{
  "id": 7469051,
  "type": "Feature",
  "properties": {
    "tgn:hierarchy":[
        "tgn:7469051",
        "tgn:1000004",
        "tgn:1000454",
        "tgn:1000141",
        "tgn:7029392"
    ],
    "tgn:id":7469051,
    "tgn:name":"Xinwen",
    "tgn:placetype":[
        "aat:300008347"
    ]
},
  "bbox": [],
  "geometry": {"coordinates":[121.45,25.066667],"type":"Point"}
}