{
  "id": 7052142,
  "type": "Feature",
  "properties": {
    "tgn:hierarchy":[
        "tgn:7052142",
        "tgn:7003133",
        "tgn:1000003",
        "tgn:7008516",
        "tgn:1000080",
        "tgn:7029392"
    ],
    "tgn:id":7052142,
    "tgn:name":"La Cascina",
    "tgn:placetype":[
        "aat:300008347"
    ]
},
  "bbox": [],
  "geometry": {"coordinates":[12.246667,44.566944],"type":"Point"}
}