{
  "id": 2724257,
  "type": "Feature",
  "properties": {
    "tgn:hierarchy":[
        "tgn:2724257",
        "tgn:1000001",
        "tgn:7012149",
        "tgn:7007826",
        "tgn:7029392"
    ],
    "tgn:id":2724257,
    "tgn:name":"Tom Dean Creek",
    "tgn:placetype":[
        "aat:300008706"
    ]
},
  "bbox": [],
  "geometry": {"coordinates":[-99.2167,31.4167],"type":"Point"}
}