{
  "id": 1008186,
  "type": "Feature",
  "properties": {
    "tgn:hierarchy":[
        "tgn:1008186",
        "tgn:7001242",
        "tgn:1000201",
        "tgn:1001097",
        "tgn:7029392"
    ],
    "tgn:id":1008186,
    "tgn:name":"Mograt Island",
    "tgn:placetype":[
        "aat:300008791"
    ]
},
  "bbox": [],
  "geometry": {"coordinates":[33.2667,19.4667],"type":"Point"}
}