{
  "id": 2574208,
  "type": "Feature",
  "properties": {
    "tgn:hierarchy":[
        "tgn:2574208",
        "tgn:7006450",
        "tgn:1000001",
        "tgn:7012149",
        "tgn:2000085",
        "tgn:7029392"
    ],
    "tgn:id":2574208,
    "tgn:name":"Pegmatite Creek",
    "tgn:placetype":[
        "aat:300008706"
    ]
},
  "bbox": [],
  "geometry": {"coordinates":[-145.0333,63.5667],"type":"Point"}
}