{
  "id": 2315363,
  "type": "Feature",
  "properties": {
    "tgn:hierarchy":[
        "tgn:2315363",
        "tgn:1000001",
        "tgn:7012149",
        "tgn:1003042",
        "tgn:7007920",
        "tgn:7029392"
    ],
    "tgn:id":2315363,
    "tgn:name":"Elliott Ave",
    "tgn:placetype":[
        "aat:300008347"
    ]
},
  "bbox": [],
  "geometry": {"coordinates":[-120.65,46.5833],"type":"Point"}
}