{
  "id": 2665527,
  "type": "Feature",
  "properties": {
    "tgn:hierarchy":[
        "tgn:2665527",
        "tgn:1000001",
        "tgn:7012149",
        "tgn:2001190",
        "tgn:7007523",
        "tgn:7029392"
    ],
    "tgn:id":2665527,
    "tgn:name":"Sinkhole Hollow",
    "tgn:placetype":[
        "aat:300008761"
    ]
},
  "bbox": [],
  "geometry": {"coordinates":[-91.15,37.8333],"type":"Point"}
}