<<<<<<< HEAD
{
  "id": 7355276,
  "type": "Feature",
  "properties": {
    "tgn:hierarchy":[
        "tgn:7355276",
        "tgn:1000001",
        "tgn:7005601",
        "tgn:7005560",
        "tgn:7029392"
    ],
    "tgn:id":7355276,
    "tgn:name":"Cedro",
    "tgn:placetype":[
        "aat:300007783"
    ]
},
  "bbox": [],
  "geometry": {"coordinates":[-102.6,23.683333],"type":"Point"}
}
=======
{"geometry":{"type":"Point","coordinates":[-102.600000,23.683333]},"type":"Feature","properties":{"hierarchy":["tgn:7355276","tgn:1000001","tgn:7005601","tgn:7005560","tgn:7029392"],"placetype":["aat:300007783"],"id":7355276,"name:xx":"Cedro"}}
>>>>>>> 03f74aca74312dbeaf24d7e61306dd6a786dc3d0
