{
  "id": 7413693,
  "type": "Feature",
  "properties": {
    "tgn:hierarchy":[
        "tgn:7413693",
        "tgn:7005580",
        "tgn:1000001",
        "tgn:7005560",
        "tgn:7029392"
    ],
    "tgn:id":7413693,
    "tgn:name":"Benito Ju\u00e1rez",
    "tgn:placetype":[
        "aat:300008347"
    ]
},
  "bbox": [],
  "geometry": {"coordinates":[-93.183333,16.883333],"type":"Point"}
}