{
  "id": 7158601,
  "type": "Feature",
  "properties": {
    "tgn:hierarchy":[
        "tgn:7158601",
        "tgn:7003692",
        "tgn:1000003",
        "tgn:7000084",
        "tgn:7029392"
    ],
    "tgn:id":7158601,
    "tgn:name":"Hochgescheid",
    "tgn:placetype":[
        "aat:300008795"
    ]
},
  "bbox": [],
  "geometry": {"coordinates":[7.933333,47.783333],"type":"Point"}
}