{
  "id": 7316062,
  "type": "Feature",
  "properties": {
    "tgn:hierarchy":[
        "tgn:7316062",
        "tgn:1001637",
        "tgn:1000049",
        "tgn:1000002",
        "tgn:7029392"
    ],
    "tgn:id":7316062,
    "tgn:name":"Casas Viejas",
    "tgn:placetype":[
        "aat:300008347"
    ]
},
  "bbox": [],
  "geometry": {"coordinates":[-72.183333,-37.883333],"type":"Point"}
}