{
  "id": 7284652,
  "type": "Feature",
  "properties": {
    "tgn:hierarchy":[
        "tgn:7284652",
        "tgn:1001702",
        "tgn:1000049",
        "tgn:1000002",
        "tgn:7029392"
    ],
    "tgn:id":7284652,
    "tgn:name":"Porter, Cerro",
    "tgn:placetype":[
        "aat:300008795"
    ]
},
  "bbox": [],
  "geometry": {"coordinates":[-72.333333,-52.866667],"type":"Point"}
}