<<<<<<< HEAD
{
  "id": 2766165,
  "type": "Feature",
  "properties": {
    "tgn:hierarchy":[
        "tgn:2766165",
        "tgn:1000001",
        "tgn:1002269",
        "tgn:7012149",
        "tgn:7007240",
        "tgn:7029392"
    ],
    "tgn:id":2766165,
    "tgn:name":"White Lake",
    "tgn:placetype":[
        "aat:300008680"
    ]
},
  "bbox": [],
  "geometry": {"coordinates":[-82.35,28.85],"type":"Point"}
}
=======
{"geometry":{"type":"Point","coordinates":[-82.350000,28.850000]},"type":"Feature","properties":{"hierarchy":["tgn:2766165","tgn:1000001","tgn:1002269","tgn:7012149","tgn:7007240","tgn:7029392"],"placetype":["aat:300008680"],"id":2766165,"name:xx":"White Lake"}}
>>>>>>> 03f74aca74312dbeaf24d7e61306dd6a786dc3d0
