{
  "id": 2782224,
  "type": "Feature",
  "properties": {
    "tgn:hierarchy":[
        "tgn:2782224",
        "tgn:1000001",
        "tgn:1002267",
        "tgn:7012149",
        "tgn:7007919",
        "tgn:7029392"
    ],
    "tgn:id":2782224,
    "tgn:name":"Woodvale",
    "tgn:placetype":[
        "aat:300008347"
    ]
},
  "bbox": [],
  "geometry": {"coordinates":[-77.3333,37.35],"type":"Point"}
}