{
  "id": 7010289,
  "type": "Feature",
  "properties": {
    "tgn:hierarchy":[
        "tgn:7010289",
        "tgn:1000004",
        "tgn:1003314",
        "tgn:7018214",
        "tgn:7002435",
        "tgn:7029392"
    ],
    "tgn:id":7010289,
    "tgn:name":"Solomennikova",
    "tgn:placetype":[
        "aat:300008347"
    ]
},
  "bbox": [],
  "geometry": {"coordinates":[88.85,58.2833],"type":"Point"}
}