<<<<<<< HEAD
{
  "id": 2400724,
  "type": "Feature",
  "properties": {
    "tgn:hierarchy":[
        "tgn:2400724",
        "tgn:1000001",
        "tgn:7006451",
        "tgn:7012149",
        "tgn:2000102",
        "tgn:7029392"
    ],
    "tgn:id":2400724,
    "tgn:name":"Horse Pasture Spring",
    "tgn:placetype":[
        "aat:300008697"
    ]
},
  "bbox": [],
  "geometry": {"coordinates":[-111.1833,31.4],"type":"Point"}
}
=======
{"geometry":{"type":"Point","coordinates":[-111.183300,31.400000]},"type":"Feature","properties":{"hierarchy":["tgn:2400724","tgn:1000001","tgn:7006451","tgn:7012149","tgn:2000102","tgn:7029392"],"placetype":["aat:300008697"],"id":2400724,"name:xx":"Horse Pasture Spring"}}
>>>>>>> 03f74aca74312dbeaf24d7e61306dd6a786dc3d0
