{
  "id": 2289179,
  "type": "Feature",
  "properties": {
    "tgn:hierarchy":[
        "tgn:2289179",
        "tgn:1000001",
        "tgn:7006451",
        "tgn:2000093",
        "tgn:7012149",
        "tgn:7029392"
    ],
    "tgn:id":2289179,
    "tgn:name":"Divided Water Spring",
    "tgn:placetype":[
        "aat:300008697"
    ]
},
  "bbox": [],
  "geometry": {"coordinates":[-110.8667,34.0667],"type":"Point"}
}