{
  "id": 1063674,
  "type": "Feature",
  "properties": {
    "tgn:hierarchy":[
        "tgn:1063674",
        "tgn:1000003",
        "tgn:7003780",
        "tgn:1000097",
        "tgn:7029392"
    ],
    "tgn:id":1063674,
    "tgn:name":"Str\u00f6msholm",
    "tgn:placetype":[
        "aat:300008347"
    ]
},
  "bbox": [],
  "geometry": {"coordinates":[16.25,59.5333],"type":"Point"}
}