{
  "id": 7498332,
  "type": "Feature",
  "properties": {
    "tgn:hierarchy":[
        "tgn:7498332",
        "tgn:1000004",
        "tgn:7492971",
        "tgn:1000141",
        "tgn:7029392"
    ],
    "tgn:id":7498332,
    "tgn:name":"Zhuguang Qiao",
    "tgn:placetype":[
        "aat:300007836"
    ]
},
  "bbox": [],
  "geometry": {"coordinates":[120.578678,22.865998],"type":"Point"}
}