{
  "id": 1083071,
  "type": "Feature",
  "properties": {
    "tgn:hierarchy":[
        "tgn:1083071",
        "tgn:1002065",
        "tgn:1000004",
        "tgn:7029379",
        "tgn:7029392"
    ],
    "tgn:id":1083071,
    "tgn:name":"Bugat",
    "tgn:placetype":[
        "aat:300008347"
    ]
},
  "bbox": [],
  "geometry": {"coordinates":[101.2667,47.9167],"type":"Point"}
}