{
  "id": 2466542,
  "type": "Feature",
  "properties": {
    "tgn:hierarchy":[
        "tgn:2466542",
        "tgn:1000001",
        "tgn:2000859",
        "tgn:7012149",
        "tgn:7007256",
        "tgn:7029392"
    ],
    "tgn:id":2466542,
    "tgn:name":"Long Branch",
    "tgn:placetype":[
        "aat:300008699"
    ]
},
  "bbox": [],
  "geometry": {"coordinates":[-93.2167,30.7333],"type":"Point"}
}