{
  "id": 7416981,
  "type": "Feature",
  "properties": {
    "tgn:hierarchy":[
        "tgn:7416981",
        "tgn:7005584",
        "tgn:1000001",
        "tgn:7005560",
        "tgn:7029392"
    ],
    "tgn:id":7416981,
    "tgn:name":"Arandas, Cerro",
    "tgn:placetype":[
        "aat:300008795"
    ]
},
  "bbox": [],
  "geometry": {"coordinates":[-101.396111,20.703056],"type":"Point"}
}