<<<<<<< HEAD
{
  "id": 7051154,
  "type": "Feature",
  "properties": {
    "tgn:hierarchy":[
        "tgn:7051154",
        "tgn:7003013",
        "tgn:7003005",
        "tgn:1000003",
        "tgn:1000080",
        "tgn:7029392"
    ],
    "tgn:id":7051154,
    "tgn:name":"Negro, Capo",
    "tgn:placetype":[
        "aat:300008850"
    ]
},
  "bbox": [],
  "geometry": {"coordinates":[13.866667,40.7],"type":"Point"}
}
=======
{"geometry":{"type":"Point","coordinates":[13.866667,40.700000]},"type":"Feature","properties":{"hierarchy":["tgn:7051154","tgn:7003013","tgn:7003005","tgn:1000003","tgn:1000080","tgn:7029392"],"placetype":["aat:300008850"],"id":7051154,"name:xx":"Negro, Capo"}}
>>>>>>> 03f74aca74312dbeaf24d7e61306dd6a786dc3d0
