{
  "id": 2193631,
  "type": "Feature",
  "properties": {
    "tgn:hierarchy":[
        "tgn:2193631",
        "tgn:1000001",
        "tgn:7012149",
        "tgn:2001284",
        "tgn:7007524",
        "tgn:7029392"
    ],
    "tgn:id":2193631,
    "tgn:name":"Brewer Hill",
    "tgn:placetype":[
        "aat:300008798"
    ]
},
  "bbox": [],
  "geometry": {"coordinates":[-111.9667,47.0667],"type":"Point"}
}