{
  "id": 7087199,
  "type": "Feature",
  "properties": {
    "tgn:hierarchy":[
        "tgn:7087199",
        "tgn:7000096",
        "tgn:1000003",
        "tgn:7000084",
        "tgn:7029392"
    ],
    "tgn:id":7087199,
    "tgn:name":"Waldfrieden",
    "tgn:placetype":[
        "aat:300000206"
    ]
},
  "bbox": [],
  "geometry": {"coordinates":[13.216667,52.65],"type":"Point"}
}