{
  "id": 7305244,
  "type": "Feature",
  "properties": {
    "tgn:hierarchy":[
        "tgn:7305244",
        "tgn:7002803",
        "tgn:1001647",
        "tgn:1000003",
        "tgn:1000095",
        "tgn:7029392"
    ],
    "tgn:id":7305244,
    "tgn:name":"Las Anorias",
    "tgn:placetype":[
        "aat:300008347"
    ]
},
  "bbox": [],
  "geometry": {"coordinates":[-1.533333,38.75],"type":"Point"}
}