{
  "id": 2253346,
  "type": "Feature",
  "properties": {
    "tgn:hierarchy":[
        "tgn:2253346",
        "tgn:1000001",
        "tgn:7012149",
        "tgn:2001750",
        "tgn:7007712",
        "tgn:7029392"
    ],
    "tgn:id":2253346,
    "tgn:name":"Conway Oxidation Pond Number One",
    "tgn:placetype":[
        "aat:300006191"
    ]
},
  "bbox": [],
  "geometry": {"coordinates":[-79.0667,33.8167],"type":"Point"}
}