<<<<<<< HEAD
{
  "id": 2253346,
  "type": "Feature",
  "properties": {
    "tgn:hierarchy":[
        "tgn:2253346",
        "tgn:1000001",
        "tgn:7012149",
        "tgn:2001750",
        "tgn:7007712",
        "tgn:7029392"
    ],
    "tgn:id":2253346,
    "tgn:name":"Conway Oxidation Pond Number One",
    "tgn:placetype":[
        "aat:300006191"
    ]
},
  "bbox": [],
  "geometry": {"coordinates":[-79.0667,33.8167],"type":"Point"}
}
=======
{"geometry":{"type":"Point","coordinates":[-79.066700,33.816700]},"type":"Feature","properties":{"hierarchy":["tgn:2253346","tgn:1000001","tgn:7012149","tgn:2001750","tgn:7007712","tgn:7029392"],"placetype":["aat:300006191"],"id":2253346,"name:xx":"Conway Oxidation Pond Number One"}}
>>>>>>> 03f74aca74312dbeaf24d7e61306dd6a786dc3d0
