<<<<<<< HEAD
{
  "id": 7057295,
  "type": "Feature",
  "properties": {
    "tgn:hierarchy":[
        "tgn:7057295",
        "tgn:7015163",
        "tgn:1000003",
        "tgn:7003121",
        "tgn:1000080",
        "tgn:7029392"
    ],
    "tgn:id":7057295,
    "tgn:name":"Badu Crabolu, Riu",
    "tgn:placetype":[
        "aat:300008699"
    ]
},
  "bbox": [],
  "geometry": {"coordinates":[8.533333,40.383333],"type":"Point"}
}
=======
{"geometry":{"type":"Point","coordinates":[8.533333,40.383333]},"type":"Feature","properties":{"hierarchy":["tgn:7057295","tgn:7015163","tgn:1000003","tgn:7003121","tgn:1000080","tgn:7029392"],"placetype":["aat:300008699"],"id":7057295,"name:xx":"Badu Crabolu, Riu"}}
>>>>>>> 03f74aca74312dbeaf24d7e61306dd6a786dc3d0
