{
  "id": 7047852,
  "type": "Feature",
  "properties": {
    "tgn:hierarchy":[
        "tgn:7047852",
        "tgn:1003468",
        "tgn:1000003",
        "tgn:7010380",
        "tgn:1000080",
        "tgn:7029392"
    ],
    "tgn:id":7047852,
    "tgn:name":"Grande, Isola",
    "tgn:placetype":[
        "aat:300008791"
    ]
},
  "bbox": [],
  "geometry": {"coordinates":[17.883333,40.25],"type":"Point"}
}