{
  "id": 7289226,
  "type": "Feature",
  "properties": {
    "tgn:hierarchy":[
        "tgn:7289226",
        "tgn:7016598",
        "tgn:1000049",
        "tgn:1000002",
        "tgn:7029392"
    ],
    "tgn:id":7289226,
    "tgn:name":"La Avestruz, Pampa",
    "tgn:placetype":[
        "aat:300008805"
    ]
},
  "bbox": [],
  "geometry": {"coordinates":[-68.583333,-21.85],"type":"Point"}
}