{
  "id": 7407514,
  "type": "Feature",
  "properties": {
    "tgn:hierarchy":[
        "tgn:7407514",
        "tgn:1000001",
        "tgn:7005590",
        "tgn:7005560",
        "tgn:7029392"
    ],
    "tgn:id":7407514,
    "tgn:name":"Llanos de los Puercos",
    "tgn:placetype":[
        "aat:300008347"
    ]
},
  "bbox": [],
  "geometry": {"coordinates":[-100.683333,19.366667],"type":"Point"}
}