{
  "id": 2703898,
  "type": "Feature",
  "properties": {
    "tgn:hierarchy":[
        "tgn:2703898",
        "tgn:1000001",
        "tgn:2000275",
        "tgn:7012149",
        "tgn:7007240",
        "tgn:7029392"
    ],
    "tgn:id":2703898,
    "tgn:name":"Sunday Bay",
    "tgn:placetype":[
        "aat:300132316"
    ]
},
  "bbox": [],
  "geometry": {"coordinates":[-81.2667,25.7833],"type":"Point"}
}