{
  "id": 1095263,
  "type": "Feature",
  "properties": {
    "tgn:hierarchy":[
        "tgn:1095263",
        "tgn:7001242",
        "tgn:7016833",
        "tgn:1001418",
        "tgn:7029392"
    ],
    "tgn:id":1095263,
    "tgn:name:en":"Ma\u1e29a\u0163\u0163at al Haww\u0101r\u012byah",
    "tgn:placetype":[
        "aat:300007783"
    ]
},
  "bbox": [],
  "geometry": {"coordinates":[29.6833,30.9667],"type":"Point"}
}