{
  "id": 7432181,
  "type": "Feature",
  "properties": {
    "tgn:hierarchy":[
        "tgn:7432181",
        "tgn:1000001",
        "tgn:7005595",
        "tgn:7005560",
        "tgn:7029392"
    ],
    "tgn:id":7432181,
    "tgn:name":"Tesquino, R\u00edo",
    "tgn:placetype":[
        "aat:300008699"
    ]
},
  "bbox": [],
  "geometry": {"coordinates":[-105.866667,23.633333],"type":"Point"}
}