{
  "id": 7186490,
  "type": "Feature",
  "properties": {
    "tgn:hierarchy":[
        "tgn:7186490",
        "tgn:1000003",
        "tgn:7003685",
        "tgn:7000084",
        "tgn:7029392"
    ],
    "tgn:id":7186490,
    "tgn:name":"Gold-H\u00fcbel",
    "tgn:placetype":[
        "aat:300008777"
    ]
},
  "bbox": [],
  "geometry": {"coordinates":[13.483333,50.683333],"type":"Point"}
}