{
  "id": 7488027,
  "type": "Feature",
  "properties": {
    "tgn:hierarchy":[
        "tgn:7488027",
        "tgn:7488858",
        "tgn:1000004",
        "tgn:1000141",
        "tgn:7029392"
    ],
    "tgn:id":7488027,
    "tgn:name":"Xiufeng",
    "tgn:placetype":[
        "aat:300008347"
    ]
},
  "bbox": [],
  "geometry": {"coordinates":[120.776455,23.780067],"type":"Point"}
}