{
  "id": 2598322,
  "type": "Feature",
  "properties": {
    "tgn:hierarchy":[
        "tgn:2598322",
        "tgn:1000001",
        "tgn:7012149",
        "tgn:2002304",
        "tgn:7013961",
        "tgn:7029392"
    ],
    "tgn:id":2598322,
    "tgn:name":"Pretty Ridge",
    "tgn:placetype":[
        "aat:300266640"
    ]
},
  "bbox": [],
  "geometry": {"coordinates":[-81.4833,37.6333],"type":"Point"}
}