{
  "id": 2348390,
  "type": "Feature",
  "properties": {
    "tgn:hierarchy":[
        "tgn:2348390",
        "tgn:1000001",
        "tgn:2002109",
        "tgn:7012149",
        "tgn:7007827",
        "tgn:7029392"
    ],
    "tgn:id":2348390,
    "tgn:name":"Ghost Ridge",
    "tgn:placetype":[
        "aat:300266640"
    ]
},
  "bbox": [],
  "geometry": {"coordinates":[-110.65,37.85],"type":"Point"}
}