{
  "id": 7235228,
  "type": "Feature",
  "properties": {
    "tgn:hierarchy":[
        "tgn:7235228",
        "tgn:7002743",
        "tgn:7017076",
        "tgn:1000003",
        "tgn:1000074",
        "tgn:7029392"
    ],
    "tgn:id":7235228,
    "tgn:name":"Fol\u00f3\u00ef",
    "tgn:placetype":[
        "aat:300008347"
    ]
},
  "bbox": [],
  "geometry": {"coordinates":[21.716667,37.783333],"type":"Point"}
}