{
  "id": 2688641,
  "type": "Feature",
  "properties": {
    "tgn:hierarchy":[
        "tgn:2688641",
        "tgn:1000001",
        "tgn:7012149",
        "tgn:1002789",
        "tgn:7007710",
        "tgn:7029392"
    ],
    "tgn:id":2688641,
    "tgn:name":"Spruce Run",
    "tgn:placetype":[
        "aat:300008699"
    ]
},
  "bbox": [],
  "geometry": {"coordinates":[-75.1167,41.1833],"type":"Point"}
}