{
  "id": 7102730,
  "type": "Feature",
  "properties": {
    "tgn:hierarchy":[
        "tgn:7102730",
        "tgn:1000003",
        "tgn:7003688",
        "tgn:7000084",
        "tgn:7029392"
    ],
    "tgn:id":7102730,
    "tgn:name":"Sankt Lorenz S\u00fcd",
    "tgn:placetype":[
        "aat:300000745"
    ]
},
  "bbox": [],
  "geometry": {"coordinates":[10.65,53.866667],"type":"Point"}
}