{
  "id": 7445960,
  "type": "Feature",
  "properties": {
    "tgn:hierarchy":[
        "tgn:7445960",
        "tgn:7002444",
        "tgn:1000003",
        "tgn:7029508",
        "tgn:7008591",
        "tgn:7029392"
    ],
    "tgn:id":7445960,
    "tgn:name:en":"Scatsta, Voe of",
    "tgn:placetype":[
        "aat:300132316"
    ]
},
  "bbox": [],
  "geometry": {"coordinates":[-1.283333,60.45],"type":"Point"}
}