{
  "id": 2218104,
  "type": "Feature",
  "properties": {
    "tgn:hierarchy":[
        "tgn:2218104",
        "tgn:1000001",
        "tgn:1002245",
        "tgn:7012149",
        "tgn:7007568",
        "tgn:7029392"
    ],
    "tgn:id":2218104,
    "tgn:name":"Canada Hill",
    "tgn:placetype":[
        "aat:300008798"
    ]
},
  "bbox": [],
  "geometry": {"coordinates":[-78.5833,42.35],"type":"Point"}
}