{
  "id": 7567267,
  "type": "Feature",
  "properties": {
    "tgn:hierarchy":[
        "tgn:7567267",
        "tgn:1000004",
        "tgn:7000198",
        "tgn:7001797",
        "tgn:7029392"
    ],
    "tgn:id":7567267,
    "tgn:name:en":"Uttandi",
    "tgn:placetype":[
        "aat:300008347"
    ]
},
  "bbox": [],
  "geometry": {"coordinates":[80.242222,12.869167],"type":"Point"}
}