{
  "id": 1129534,
  "type": "Feature",
  "properties": {
    "tgn:hierarchy":[
        "tgn:1129534",
        "tgn:1001201",
        "tgn:1000001",
        "tgn:7005565",
        "tgn:7029392"
    ],
    "tgn:id":1129534,
    "tgn:name":"San F\u00e9lix, R\u00edo",
    "tgn:placetype":[
        "aat:300008707"
    ]
},
  "bbox": [],
  "geometry": {"coordinates":[-81.85,8.1667],"type":"Point"}
}