{
  "id": 2102101,
  "type": "Feature",
  "properties": {
    "tgn:hierarchy":[
        "tgn:2102101",
        "tgn:1000001",
        "tgn:7012149",
        "tgn:2001894",
        "tgn:7007825",
        "tgn:7029392"
    ],
    "tgn:id":2102101,
    "tgn:name":"Whiteside",
    "tgn:placetype":[
        "aat:300008347"
    ]
},
  "bbox": [],
  "geometry": {"coordinates":[-85.4833,34.9833],"type":"Point"}
}