{
  "id": 7022654,
  "type": "Feature",
  "properties": {
    "tgn:hierarchy":[
        "tgn:7022654",
        "tgn:7005685",
        "tgn:1000001",
        "tgn:7029392"
    ],
    "tgn:id":7022654,
    "tgn:name":"Cypress Hills Provincial Park",
    "tgn:placetype":[
        "aat:300008195"
    ]
},
  "bbox": [],
  "geometry": {"coordinates":[-110.1667,49.65],"type":"Point"}
}