{
  "id": 2534035,
  "type": "Feature",
  "properties": {
    "tgn:hierarchy":[
        "tgn:2534035",
        "tgn:2000943",
        "tgn:1000001",
        "tgn:7012149",
        "tgn:7007520",
        "tgn:7029392"
    ],
    "tgn:id":2534035,
    "tgn:name":"Myren",
    "tgn:placetype":[
        "aat:300008347"
    ]
},
  "bbox": [],
  "geometry": {"coordinates":[-86.4167,46.4167],"type":"Point"}
}