{
  "id": 2339321,
  "type": "Feature",
  "properties": {
    "tgn:hierarchy":[
        "tgn:2339321",
        "tgn:1000001",
        "tgn:7012149",
        "tgn:2000533",
        "tgn:7007251",
        "tgn:7029392"
    ],
    "tgn:id":2339321,
    "tgn:name":"Fravet",
    "tgn:placetype":[
        "aat:300008347"
    ]
},
  "bbox": [],
  "geometry": {"coordinates":[-89.3667,40.4333],"type":"Point"}
}