<<<<<<< HEAD
{
  "id": 2154472,
  "type": "Feature",
  "properties": {
    "tgn:hierarchy":[
        "tgn:2154472",
        "tgn:1000001",
        "tgn:7012149",
        "tgn:2002381",
        "tgn:7007923",
        "tgn:7029392"
    ],
    "tgn:id":2154472,
    "tgn:name":"Bear Creek",
    "tgn:placetype":[
        "aat:300008706"
    ]
},
  "bbox": [],
  "geometry": {"coordinates":[-107.3167,44.7333],"type":"Point"}
}
=======
{"geometry":{"type":"Point","coordinates":[-107.316700,44.733300]},"type":"Feature","properties":{"hierarchy":["tgn:2154472","tgn:1000001","tgn:7012149","tgn:2002381","tgn:7007923","tgn:7029392"],"placetype":["aat:300008706"],"id":2154472,"name:xx":"Bear Creek"}}
>>>>>>> 03f74aca74312dbeaf24d7e61306dd6a786dc3d0
