{
  "id": 2495765,
  "type": "Feature",
  "properties": {
    "tgn:hierarchy":[
        "tgn:2495765",
        "tgn:1000001",
        "tgn:2000599",
        "tgn:7012149",
        "tgn:7007253",
        "tgn:7029392"
    ],
    "tgn:id":2495765,
    "tgn:name":"Mason Creek",
    "tgn:placetype":[
        "aat:300008706"
    ]
},
  "bbox": [],
  "geometry": {"coordinates":[-94.6333,41.6167],"type":"Point"}
}