{
  "id": 2225841,
  "type": "Feature",
  "properties": {
    "tgn:hierarchy":[
        "tgn:2225841",
        "tgn:1000001",
        "tgn:2001477",
        "tgn:7012149",
        "tgn:7007709",
        "tgn:7029392"
    ],
    "tgn:id":2225841,
    "tgn:name":"Cat Island",
    "tgn:placetype":[
        "aat:300008791"
    ]
},
  "bbox": [],
  "geometry": {"coordinates":[-76.9667,34.6833],"type":"Point"}
}