{
  "id": 2324049,
  "type": "Feature",
  "properties": {
    "tgn:hierarchy":[
        "tgn:2324049",
        "tgn:1000001",
        "tgn:7012149",
        "tgn:7007157",
        "tgn:1002857",
        "tgn:7029392"
    ],
    "tgn:id":2324049,
    "tgn:name":"Fawnskin Valley",
    "tgn:placetype":[
        "aat:300386845"
    ]
},
  "bbox": [],
  "geometry": {"coordinates":[-116.95,34.2833],"type":"Point"}
}