{
  "id": 1075527,
  "type": "Feature",
  "properties": {
    "tgn:hierarchy":[
        "tgn:1075527",
        "tgn:1000004",
        "tgn:7000198",
        "tgn:1001894",
        "tgn:7029392"
    ],
    "tgn:id":1075527,
    "tgn:name:en":"It\u0101rsi",
    "tgn:placetype":[
        "aat:300008347"
    ]
},
  "bbox": [],
  "geometry": {"coordinates":[77.762217,22.614772],"type":"Point"}
}