{
  "id": 2499694,
  "type": "Feature",
  "properties": {
    "tgn:hierarchy":[
        "tgn:2499694",
        "tgn:1000001",
        "tgn:1002237",
        "tgn:7012149",
        "tgn:7007255",
        "tgn:7029392"
    ],
    "tgn:id":2499694,
    "tgn:name":"McCools Creek",
    "tgn:placetype":[
        "aat:300008706"
    ]
},
  "bbox": [],
  "geometry": {"coordinates":[-85.0167,38.6667],"type":"Point"}
}