{
  "id": 2412609,
  "type": "Feature",
  "properties": {
    "tgn:hierarchy":[
        "tgn:2412609",
        "tgn:1000001",
        "tgn:7012149",
        "tgn:7007706",
        "tgn:7029392"
    ],
    "tgn:id":2412609,
    "tgn:name":"Indigo Creek",
    "tgn:placetype":[
        "aat:300008706"
    ]
},
  "bbox": [],
  "geometry": {"coordinates":[-82.8167,40.3667],"type":"Point"}
}