{
  "id": 2704513,
  "type": "Feature",
  "properties": {
    "tgn:hierarchy":[
        "tgn:2704513",
        "tgn:7006450",
        "tgn:1000001",
        "tgn:7019698",
        "tgn:7012149",
        "tgn:7029392"
    ],
    "tgn:id":2704513,
    "tgn:name":"Sunrise Creek",
    "tgn:placetype":[
        "aat:300008706"
    ]
},
  "bbox": [],
  "geometry": {"coordinates":[-149.4667,60.8667],"type":"Point"}
}