{
  "id": 2421970,
  "type": "Feature",
  "properties": {
    "tgn:hierarchy":[
        "tgn:2421970",
        "tgn:1000001",
        "tgn:7012149",
        "tgn:7007158",
        "tgn:2000253",
        "tgn:7029392"
    ],
    "tgn:id":2421970,
    "tgn:name":"Jim Creek",
    "tgn:placetype":[
        "aat:300008706"
    ]
},
  "bbox": [],
  "geometry": {"coordinates":[-104.5333,40.0333],"type":"Point"}
}