{
  "id": 2581082,
  "type": "Feature",
  "properties": {
    "tgn:hierarchy":[
        "tgn:2581082",
        "tgn:1000001",
        "tgn:7012149",
        "tgn:1002612",
        "tgn:7007710",
        "tgn:7029392"
    ],
    "tgn:id":2581082,
    "tgn:name":"Pikes Creek Reservoir",
    "tgn:placetype":[
        "aat:300006191"
    ]
},
  "bbox": [],
  "geometry": {"coordinates":[-76.0333,41.25],"type":"Point"}
}