{
  "id": 1065182,
  "type": "Feature",
  "properties": {
    "tgn:hierarchy":[
        "tgn:1065182",
        "tgn:7017295",
        "tgn:1000003",
        "tgn:7006663",
        "tgn:7029392"
    ],
    "tgn:id":1065182,
    "tgn:name":"Pla\u0161ki",
    "tgn:placetype":[
        "aat:300008347"
    ]
},
  "bbox": [],
  "geometry": {"coordinates":[15.3667,45.0667],"type":"Point"}
}