{
  "id": 2450913,
  "type": "Feature",
  "properties": {
    "tgn:hierarchy":[
        "tgn:2450913",
        "tgn:2001467",
        "tgn:1000001",
        "tgn:7012149",
        "tgn:7007709",
        "tgn:7029392"
    ],
    "tgn:id":2450913,
    "tgn:name":"Listening Rock",
    "tgn:placetype":[
        "aat:300008347"
    ]
},
  "bbox": [],
  "geometry": {"coordinates":[-81.6333,36.55],"type":"Point"}
}