{
  "id": 7568667,
  "type": "Feature",
  "properties": {
    "tgn:hierarchy":[
        "tgn:7568667",
        "tgn:1000004",
        "tgn:7000198",
        "tgn:7016722",
        "tgn:7029392"
    ],
    "tgn:id":7568667,
    "tgn:name:en":"Purm\u0101fi",
    "tgn:placetype":[
        "aat:300008347"
    ]
},
  "bbox": [],
  "geometry": {"coordinates":[77.270355,29.543293],"type":"Point"}
}