{
  "id": 7368759,
  "type": "Feature",
  "properties": {
    "tgn:hierarchy":[
        "tgn:7368759",
        "tgn:1000001",
        "tgn:7005597",
        "tgn:7005560",
        "tgn:7029392"
    ],
    "tgn:id":7368759,
    "tgn:name":"Guadalupe",
    "tgn:placetype":[
        "aat:300008347"
    ]
},
  "bbox": [],
  "geometry": {"coordinates":[-98.766667,23.383333],"type":"Point"}
}