{
  "id": 7544853,
  "type": "Feature",
  "properties": {
    "tgn:hierarchy":[
        "tgn:7544853",
        "tgn:1000004",
        "tgn:1001871",
        "tgn:7000198",
        "tgn:7029392"
    ],
    "tgn:id":7544853,
    "tgn:name:en":"Babarpur Railroad Station",
    "tgn:placetype":[
        "aat:300007783"
    ]
},
  "bbox": [],
  "geometry": {"coordinates":[76.966499,29.44994],"type":"Point"}
}