{
  "id": 1105896,
  "type": "Feature",
  "properties": {
    "tgn:hierarchy":[
        "tgn:1105896",
        "tgn:7003029",
        "tgn:1000003",
        "tgn:1000062",
        "tgn:7029392"
    ],
    "tgn:id":1105896,
    "tgn:name":"Olperer",
    "tgn:placetype":[
        "aat:300008795"
    ]
},
  "bbox": [],
  "geometry": {"coordinates":[11.6667,47.05],"type":"Point"}
}