{
  "id": 7582662,
  "type": "Feature",
  "properties": {
    "tgn:hierarchy":[
        "tgn:7582662",
        "tgn:1000004",
        "tgn:7000198",
        "tgn:7016788",
        "tgn:7029392"
    ],
    "tgn:id":7582662,
    "tgn:name:en":"Ghand\u0101wa",
    "tgn:placetype":[
        "aat:300008347"
    ]
},
  "bbox": [],
  "geometry": {"coordinates":[75.671245,28.284847],"type":"Point"}
}