{
  "id": 2126630,
  "type": "Feature",
  "properties": {
    "tgn:hierarchy":[
        "tgn:2126630",
        "tgn:1000001",
        "tgn:7012149",
        "tgn:7007158",
        "tgn:2000245",
        "tgn:7029392"
    ],
    "tgn:id":2126630,
    "tgn:name":"Agate Creek",
    "tgn:placetype":[
        "aat:300008706"
    ]
},
  "bbox": [],
  "geometry": {"coordinates":[-106.85,40.45],"type":"Point"}
}