{
  "id": 2564027,
  "type": "Feature",
  "properties": {
    "tgn:hierarchy":[
        "tgn:2564027",
        "tgn:1000001",
        "tgn:1002712",
        "tgn:7012149",
        "tgn:7007159",
        "tgn:7029392"
    ],
    "tgn:id":2564027,
    "tgn:name":"Oyster River Point",
    "tgn:placetype":[
        "aat:300008850"
    ]
},
  "bbox": [],
  "geometry": {"coordinates":[-72.9667,41.2333],"type":"Point"}
}