{
  "id": 7479618,
  "type": "Feature",
  "properties": {
    "tgn:hierarchy":[
        "tgn:7479618",
        "tgn:1000004",
        "tgn:7490934",
        "tgn:1000141",
        "tgn:7029392"
    ],
    "tgn:id":7479618,
    "tgn:name":"Zheng'an Gong",
    "tgn:placetype":[
        "aat:300007595"
    ]
},
  "bbox": [],
  "geometry": {"coordinates":[120.245833,23.165],"type":"Point"}
}