{
  "id": 7184607,
  "type": "Feature",
  "properties": {
    "tgn:hierarchy":[
        "tgn:7184607",
        "tgn:1000003",
        "tgn:7003677",
        "tgn:7000084",
        "tgn:7029392"
    ],
    "tgn:id":7184607,
    "tgn:name":"Gickels-Berg",
    "tgn:placetype":[
        "aat:300008777"
    ]
},
  "bbox": [],
  "geometry": {"coordinates":[8.25,50.966667],"type":"Point"}
}