{
  "id": 1070761,
  "type": "Feature",
  "properties": {
    "tgn:hierarchy":[
        "tgn:1070761",
        "tgn:1000004",
        "tgn:7002087",
        "tgn:1000111",
        "tgn:7029392"
    ],
    "tgn:id":1070761,
    "tgn:name":"Niupichang",
    "tgn:placetype":[
        "aat:300008347"
    ]
},
  "bbox": [],
  "geometry": {"coordinates":[103.6667,30.5833],"type":"Point"}
}