{
  "id": 1053890,
  "type": "Feature",
  "properties": {
    "tgn:hierarchy":[
        "tgn:1053890",
        "tgn:7012221",
        "tgn:1000004",
        "tgn:7006659",
        "tgn:7029392"
    ],
    "tgn:id":1053890,
    "tgn:name":"Firyuza",
    "tgn:placetype":[
        "aat:300008347"
    ]
},
  "bbox": [],
  "geometry": {"coordinates":[58.05,37.9167],"type":"Point"}
}