{
  "id": 2485422,
  "type": "Feature",
  "properties": {
    "tgn:hierarchy":[
        "tgn:2485422",
        "tgn:1000001",
        "tgn:7012149",
        "tgn:1002506",
        "tgn:7007919",
        "tgn:7029392"
    ],
    "tgn:id":2485422,
    "tgn:name":"Lawson Creek",
    "tgn:placetype":[
        "aat:300008706"
    ]
},
  "bbox": [],
  "geometry": {"coordinates":[-76.6333,37.0167],"type":"Point"}
}