{
  "id": 7272332,
  "type": "Feature",
  "properties": {
    "tgn:hierarchy":[
        "tgn:7272332",
        "tgn:1000003",
        "tgn:7003613",
        "tgn:7016845",
        "tgn:7029392"
    ],
    "tgn:id":7272332,
    "tgn:name:nl":"Verenigdkanaal",
    "tgn:placetype":[
        "aat:300006075"
    ]
},
  "bbox": [],
  "geometry": {"coordinates":[7.183333,53.166667],"type":"Point"}
}