<<<<<<< HEAD
{
  "id": 7052116,
  "type": "Feature",
  "properties": {
    "tgn:hierarchy":[
        "tgn:7052116",
        "tgn:1001730",
        "tgn:1000003",
        "tgn:7003121",
        "tgn:1000080",
        "tgn:7029392"
    ],
    "tgn:id":7052116,
    "tgn:name":"Mannu, Riu",
    "tgn:placetype":[
        "aat:300008699"
    ]
},
  "bbox": [],
  "geometry": {"coordinates":[8.45,40.166667],"type":"Point"}
}
=======
{"geometry":{"type":"Point","coordinates":[8.450000,40.166667]},"type":"Feature","properties":{"hierarchy":["tgn:7052116","tgn:1001730","tgn:1000003","tgn:7003121","tgn:1000080","tgn:7029392"],"placetype":["aat:300008699"],"id":7052116,"name:xx":"Mannu, Riu"}}
>>>>>>> 03f74aca74312dbeaf24d7e61306dd6a786dc3d0
