{
  "id": 2120655,
  "type": "Feature",
  "properties": {
    "tgn:hierarchy":[
        "tgn:2120655",
        "tgn:1000001",
        "tgn:2002323",
        "tgn:7012149",
        "tgn:7007922",
        "tgn:7029392"
    ],
    "tgn:id":2120655,
    "tgn:name":"Atkins",
    "tgn:placetype":[
        "aat:300387016"
    ]
},
  "bbox": [],
  "geometry": {"coordinates":[-89.0167,45.65],"type":"Point"}
}