{
  "id": 7495082,
  "type": "Feature",
  "properties": {
    "tgn:hierarchy":[
        "tgn:7495082",
        "tgn:7468018",
        "tgn:1000004",
        "tgn:1000141",
        "tgn:7029392"
    ],
    "tgn:id":7495082,
    "tgn:name":"Shizhuo",
    "tgn:placetype":[
        "aat:300008347"
    ]
},
  "bbox": [],
  "geometry": {"coordinates":[120.700964,23.476428],"type":"Point"}
}