{
  "id": 1135892,
  "type": "Feature",
  "properties": {
    "tgn:hierarchy":[
        "tgn:1135892",
        "tgn:1000001",
        "tgn:7012149",
        "tgn:7029392"
    ],
    "tgn:id":1135892,
    "tgn:name":"Dismal Swamp Canal",
    "tgn:placetype":[
        "aat:300006075"
    ]
},
  "bbox": [],
  "geometry": {"coordinates":[-76.3333,36.4667],"type":"Point"}
}