{
  "id": 2361570,
  "type": "Feature",
  "properties": {
    "tgn:hierarchy":[
        "tgn:2361570",
        "tgn:7006450",
        "tgn:1000001",
        "tgn:7012149",
        "tgn:7019760",
        "tgn:7029392"
    ],
    "tgn:id":2361570,
    "tgn:name":"Graves Rocks",
    "tgn:placetype":[
        "aat:300055621"
    ]
},
  "bbox": [],
  "geometry": {"coordinates":[-136.75,58.2333],"type":"Point"}
}