{
  "id": 2569826,
  "type": "Feature",
  "properties": {
    "tgn:hierarchy":[
        "tgn:2569826",
        "tgn:7002659",
        "tgn:1000001",
        "tgn:7012149",
        "tgn:2000062",
        "tgn:7029392"
    ],
    "tgn:id":2569826,
    "tgn:name":"Partlow Lake Lower",
    "tgn:placetype":[
        "aat:300006191"
    ]
},
  "bbox": [],
  "geometry": {"coordinates":[-87.6333,33.2333],"type":"Point"}
}