{
  "id": 7516924,
  "type": "Feature",
  "properties": {
    "tgn:hierarchy":[
        "tgn:7516924",
        "tgn:1009227",
        "tgn:1000226",
        "tgn:7520095",
        "tgn:1000006",
        "tgn:7029392"
    ],
    "tgn:id":7516924,
    "tgn:name:en":"North-West Nelson State Forest Park",
    "tgn:placetype":[
        "aat:300008187"
    ]
},
  "bbox": [],
  "geometry": {"coordinates":[172.333333,-41.166667],"type":"Point"}
}