{
  "id": 2168321,
  "type": "Feature",
  "properties": {
    "tgn:hierarchy":[
        "tgn:2168321",
        "tgn:1000001",
        "tgn:7012149",
        "tgn:2002017",
        "tgn:7007826",
        "tgn:7029392"
    ],
    "tgn:id":2168321,
    "tgn:name":"Big Gobbler",
    "tgn:placetype":[
        "aat:300008761"
    ]
},
  "bbox": [],
  "geometry": {"coordinates":[-100.7333,32.9667],"type":"Point"}
}