<<<<<<< HEAD
{
  "id": 2156471,
  "type": "Feature",
  "properties": {
    "tgn:hierarchy":[
        "tgn:2156471",
        "tgn:7030515",
        "tgn:7006450",
        "tgn:1000001",
        "tgn:7012149",
        "tgn:7029392"
    ],
    "tgn:id":2156471,
    "tgn:name":"Beartrack Creek",
    "tgn:placetype":[
        "aat:300008706"
    ]
},
  "bbox": [],
  "geometry": {"coordinates":[-164.75,54.5333],"type":"Point"}
}
=======
{"geometry":{"type":"Point","coordinates":[-164.750000,54.533300]},"type":"Feature","properties":{"hierarchy":["tgn:2156471","tgn:7030515","tgn:7006450","tgn:1000001","tgn:7012149","tgn:7029392"],"placetype":["aat:300008706"],"id":2156471,"name:xx":"Beartrack Creek"}}
>>>>>>> 03f74aca74312dbeaf24d7e61306dd6a786dc3d0
