{
  "id": 2299070,
  "type": "Feature",
  "properties": {
    "tgn:hierarchy":[
        "tgn:2299070",
        "tgn:1000001",
        "tgn:7012149",
        "tgn:2000229",
        "tgn:7007158",
        "tgn:7029392"
    ],
    "tgn:id":2299070,
    "tgn:name":"Duck Creek",
    "tgn:placetype":[
        "aat:300008706"
    ]
},
  "bbox": [],
  "geometry": {"coordinates":[-102.7833,40.9167],"type":"Point"}
}