{
  "id": 2155624,
  "type": "Feature",
  "properties": {
    "tgn:hierarchy":[
        "tgn:2155624",
        "tgn:1000001",
        "tgn:7006451",
        "tgn:7012149",
        "tgn:2000099",
        "tgn:7029392"
    ],
    "tgn:id":2155624,
    "tgn:name":"Bear Spring",
    "tgn:placetype":[
        "aat:300008697"
    ]
},
  "bbox": [],
  "geometry": {"coordinates":[-109.9833,33.8667],"type":"Point"}
}