{
  "id": 2107454,
  "type": "Feature",
  "properties": {
    "tgn:hierarchy":[
        "tgn:2107454",
        "tgn:1000001",
        "tgn:2001942",
        "tgn:7012149",
        "tgn:7007826",
        "tgn:7029392"
    ],
    "tgn:id":2107454,
    "tgn:name":"Sandy",
    "tgn:placetype":[
        "aat:300008347"
    ]
},
  "bbox": [],
  "geometry": {"coordinates":[-98.4667,30.35],"type":"Point"}
}