{
  "id": 2335163,
  "type": "Feature",
  "properties": {
    "tgn:hierarchy":[
        "tgn:2335163",
        "tgn:1000001",
        "tgn:2000779",
        "tgn:7012149",
        "tgn:7007255",
        "tgn:7029392"
    ],
    "tgn:id":2335163,
    "tgn:name":"Fort Branch",
    "tgn:placetype":[
        "aat:300008699"
    ]
},
  "bbox": [],
  "geometry": {"coordinates":[-85.0167,37.4167],"type":"Point"}
}