<<<<<<< HEAD
{
  "id": 2335163,
  "type": "Feature",
  "properties": {
    "tgn:hierarchy":[
        "tgn:2335163",
        "tgn:1000001",
        "tgn:2000779",
        "tgn:7012149",
        "tgn:7007255",
        "tgn:7029392"
    ],
    "tgn:id":2335163,
    "tgn:name":"Fort Branch",
    "tgn:placetype":[
        "aat:300008699"
    ]
},
  "bbox": [],
  "geometry": {"coordinates":[-85.0167,37.4167],"type":"Point"}
}
=======
{"geometry":{"type":"Point","coordinates":[-85.016700,37.416700]},"type":"Feature","properties":{"hierarchy":["tgn:2335163","tgn:1000001","tgn:2000779","tgn:7012149","tgn:7007255","tgn:7029392"],"placetype":["aat:300008699"],"id":2335163,"name:xx":"Fort Branch"}}
>>>>>>> 03f74aca74312dbeaf24d7e61306dd6a786dc3d0
