{
  "id": 1065340,
  "type": "Feature",
  "properties": {
    "tgn:hierarchy":[
        "tgn:1065340",
        "tgn:1000003",
        "tgn:4011927",
        "tgn:7006669",
        "tgn:7029392"
    ],
    "tgn:id":1065340,
    "tgn:name":"Vrbas",
    "tgn:placetype":[
        "aat:300008347"
    ]
},
  "bbox": [],
  "geometry": {"coordinates":[19.6333,45.5667],"type":"Point"}
}