{
  "id": 7534799,
  "type": "Feature",
  "properties": {
    "tgn:hierarchy":[
        "tgn:7534799",
        "tgn:7001242",
        "tgn:7016833",
        "tgn:1001087",
        "tgn:7029392"
    ],
    "tgn:id":7534799,
    "tgn:name:en":"\u1e28i\u015f\u015fat Mil\u012bj",
    "tgn:placetype":[
        "aat:300008347"
    ]
},
  "bbox": [],
  "geometry": {"coordinates":[31.045114,30.599677],"type":"Point"}
}