{
  "id": 2487073,
  "type": "Feature",
  "properties": {
    "tgn:hierarchy":[
        "tgn:2487073",
        "tgn:1000001",
        "tgn:7012149",
        "tgn:2001554",
        "tgn:7007709",
        "tgn:7029392"
    ],
    "tgn:id":2487073,
    "tgn:name":"Lee Swamp",
    "tgn:placetype":[
        "aat:300008699"
    ]
},
  "bbox": [],
  "geometry": {"coordinates":[-78.0833,35.65],"type":"Point"}
}