{
  "id": 2301090,
  "type": "Feature",
  "properties": {
    "tgn:hierarchy":[
        "tgn:2301090",
        "tgn:1000001",
        "tgn:1002271",
        "tgn:7012149",
        "tgn:7007920",
        "tgn:7029392"
    ],
    "tgn:id":2301090,
    "tgn:name":"Dunham Creek",
    "tgn:placetype":[
        "aat:300008706"
    ]
},
  "bbox": [],
  "geometry": {"coordinates":[-124.5333,48.1333],"type":"Point"}
}