<<<<<<< HEAD
{
  "id": 2763018,
  "type": "Feature",
  "properties": {
    "tgn:hierarchy":[
        "tgn:2763018",
        "tgn:1000001",
        "tgn:7012149",
        "tgn:2000930",
        "tgn:7007515",
        "tgn:7029392"
    ],
    "tgn:id":2763018,
    "tgn:name":"Weston Island",
    "tgn:placetype":[
        "aat:300008791"
    ]
},
  "bbox": [],
  "geometry": {"coordinates":[-69.85,44.8167],"type":"Point"}
}
=======
{"geometry":{"type":"Point","coordinates":[-69.850000,44.816700]},"type":"Feature","properties":{"hierarchy":["tgn:2763018","tgn:1000001","tgn:7012149","tgn:2000930","tgn:7007515","tgn:7029392"],"placetype":["aat:300008791"],"id":2763018,"name:xx":"Weston Island"}}
>>>>>>> 03f74aca74312dbeaf24d7e61306dd6a786dc3d0
