{
  "id": 2488486,
  "type": "Feature",
  "properties": {
    "tgn:hierarchy":[
        "tgn:2488486",
        "tgn:1000001",
        "tgn:7012149",
        "tgn:2001718",
        "tgn:7007708",
        "tgn:7029392"
    ],
    "tgn:id":2488486,
    "tgn:name":"Mahogany Long Draw Reservoir",
    "tgn:placetype":[
        "aat:300006191"
    ]
},
  "bbox": [],
  "geometry": {"coordinates":[-117.1833,43.6167],"type":"Point"}
}