{
  "id": 7476438,
  "type": "Feature",
  "properties": {
    "tgn:hierarchy":[
        "tgn:7476438",
        "tgn:7487020",
        "tgn:1000004",
        "tgn:1000141",
        "tgn:7029392"
    ],
    "tgn:id":7476438,
    "tgn:name":"Fengluque",
    "tgn:placetype":[
        "aat:300008347"
    ]
},
  "bbox": [],
  "geometry": {"coordinates":[120.783821,24.553901],"type":"Point"}
}