<<<<<<< HEAD
{
  "id": 7025361,
  "type": "Feature",
  "properties": {
    "tgn:hierarchy":[
        "tgn:7025361",
        "tgn:7002445",
        "tgn:1000003",
        "tgn:7012077",
        "tgn:7008591",
        "tgn:7029392"
    ],
    "tgn:id":7025361,
    "tgn:name":"Aller",
    "tgn:placetype":[
        "aat:300008347"
    ]
},
  "bbox": [],
  "geometry": {"coordinates":[-3.5833,50.5],"type":"Point"}
}
=======
{"geometry":{"type":"Point","coordinates":[-3.583300,50.500000]},"type":"Feature","properties":{"hierarchy":["tgn:7025361","tgn:7002445","tgn:1000003","tgn:7012077","tgn:7008591","tgn:7029392"],"placetype":["aat:300008347"],"id":7025361,"name:xx":"Aller"}}
>>>>>>> 03f74aca74312dbeaf24d7e61306dd6a786dc3d0
