{
  "id": 7017205,
  "type": "Feature",
  "properties": {
    "tgn:hierarchy":[
        "tgn:7017205",
        "tgn:1000003",
        "tgn:7015085",
        "tgn:7006670",
        "tgn:7029392"
    ],
    "tgn:id":7017205,
    "tgn:name":"Most na So\u010di",
    "tgn:placetype":[
        "aat:300008347"
    ]
},
  "bbox": [],
  "geometry": {"coordinates":[13.75,46.15],"type":"Point"}
}