{
  "id": 7126948,
  "type": "Feature",
  "properties": {
    "tgn:hierarchy":[
        "tgn:7126948",
        "tgn:7003692",
        "tgn:1000003",
        "tgn:7000084",
        "tgn:7029392"
    ],
    "tgn:id":7126948,
    "tgn:name":"Oberohrn",
    "tgn:placetype":[
        "aat:300008347"
    ]
},
  "bbox": [],
  "geometry": {"coordinates":[9.530556,49.178056],"type":"Point"}
}