{
  "id": 2273834,
  "type": "Feature",
  "properties": {
    "tgn:hierarchy":[
        "tgn:2273834",
        "tgn:1000001",
        "tgn:7012149",
        "tgn:2001679",
        "tgn:7007707",
        "tgn:7029392"
    ],
    "tgn:id":2273834,
    "tgn:name":"Dad Creek",
    "tgn:placetype":[
        "aat:300008706"
    ]
},
  "bbox": [],
  "geometry": {"coordinates":[-96.1333,36.3167],"type":"Point"}
}