<<<<<<< HEAD
{
  "id": 7473886,
  "type": "Feature",
  "properties": {
    "tgn:hierarchy":[
        "tgn:7473886",
        "tgn:1000004",
        "tgn:7489179",
        "tgn:1000141",
        "tgn:7029392"
    ],
    "tgn:id":7473886,
    "tgn:name":"Dongyue Cun",
    "tgn:placetype":[
        "aat:300387173"
    ]
},
  "bbox": [],
  "geometry": {"coordinates":[121.8234,24.5272],"type":"Point"}
}
=======
{"geometry":{"type":"Point","coordinates":[121.823400,24.527200]},"type":"Feature","properties":{"hierarchy":["tgn:7473886","tgn:1000004","tgn:7489179","tgn:1000141","tgn:7029392"],"placetype":["aat:300387173"],"id":7473886,"name:xx":"Dongyue Cun"}}
>>>>>>> 03f74aca74312dbeaf24d7e61306dd6a786dc3d0
