{
  "id": 7216637,
  "type": "Feature",
  "properties": {
    "tgn:hierarchy":[
        "tgn:7216637",
        "tgn:1000003",
        "tgn:7003676",
        "tgn:7000084",
        "tgn:7029392"
    ],
    "tgn:id":7216637,
    "tgn:name":"Abbenstein",
    "tgn:placetype":[
        "aat:300008795"
    ]
},
  "bbox": [],
  "geometry": {"coordinates":[10.566667,51.816667],"type":"Point"}
}