{
  "id": 2109501,
  "type": "Feature",
  "properties": {
    "tgn:hierarchy":[
        "tgn:2109501",
        "tgn:1000001",
        "tgn:1002840",
        "tgn:7012149",
        "tgn:7007828",
        "tgn:7029392"
    ],
    "tgn:id":2109501,
    "tgn:name":"Burnham Hollow",
    "tgn:placetype":[
        "aat:300008347",
        "aat:300387210"
    ]
},
  "bbox": [],
  "geometry": {"coordinates":[-73.1333,43.4833],"type":"Point"}
}