{
  "id": 1001211,
  "type": "Feature",
  "properties": {
    "tgn:hierarchy":[
        "tgn:1001211",
        "tgn:7002561",
        "tgn:1000051",
        "tgn:1000002",
        "tgn:7029392"
    ],
    "tgn:id":1001211,
    "tgn:name":"Cotopaxi",
    "tgn:placetype":[
        "aat:300387064",
        "aat:300000774"
    ]
},
  "bbox": [],
  "geometry": {"coordinates":[-78.796,-0.747],"type":"Point"}
}