{
  "id": 2520556,
  "type": "Feature",
  "properties": {
    "tgn:hierarchy":[
        "tgn:2520556",
        "tgn:7002659",
        "tgn:1000001",
        "tgn:2000018",
        "tgn:7012149",
        "tgn:7029392"
    ],
    "tgn:id":2520556,
    "tgn:name":"Monk Creek",
    "tgn:placetype":[
        "aat:300008706"
    ]
},
  "bbox": [],
  "geometry": {"coordinates":[-86.3167,33.0833],"type":"Point"}
}