{
  "id": 2298034,
  "type": "Feature",
  "properties": {
    "tgn:hierarchy":[
        "tgn:2298034",
        "tgn:1000001",
        "tgn:7012149",
        "tgn:2000966",
        "tgn:7007520",
        "tgn:7029392"
    ],
    "tgn:id":2298034,
    "tgn:name":"Dry Lake",
    "tgn:placetype":[
        "aat:300008680"
    ]
},
  "bbox": [],
  "geometry": {"coordinates":[-88.2167,46.0333],"type":"Point"}
}