{
  "id": 7439635,
  "type": "Feature",
  "properties": {
    "tgn:hierarchy":[
        "tgn:7439635",
        "tgn:1000001",
        "tgn:7005591",
        "tgn:7005560",
        "tgn:7029392"
    ],
    "tgn:id":7439635,
    "tgn:name":"San Pedro Totomachapan",
    "tgn:placetype":[
        "aat:300008347"
    ]
},
  "bbox": [],
  "geometry": {"coordinates":[-97.133333,16.833333],"type":"Point"}
}