{
  "id": 2508692,
  "type": "Feature",
  "properties": {
    "tgn:hierarchy":[
        "tgn:2508692",
        "tgn:1000001",
        "tgn:7012149",
        "tgn:2000821",
        "tgn:7007255",
        "tgn:7029392"
    ],
    "tgn:id":2508692,
    "tgn:name":"Middle Fork",
    "tgn:placetype":[
        "aat:300008699"
    ]
},
  "bbox": [],
  "geometry": {"coordinates":[-83.0167,37.5833],"type":"Point"}
}