{
  "id": 7470793,
  "type": "Feature",
  "properties": {
    "tgn:hierarchy":[
        "tgn:7470793",
        "tgn:7487020",
        "tgn:1000004",
        "tgn:1000141",
        "tgn:7029392"
    ],
    "tgn:id":7470793,
    "tgn:name":"Xikeng",
    "tgn:placetype":[
        "aat:300008347"
    ]
},
  "bbox": [],
  "geometry": {"coordinates":[120.7927,24.3991],"type":"Point"}
}