{
  "id": 7161171,
  "type": "Feature",
  "properties": {
    "tgn:hierarchy":[
        "tgn:7161171",
        "tgn:1000003",
        "tgn:7003677",
        "tgn:7000084",
        "tgn:7029392"
    ],
    "tgn:id":7161171,
    "tgn:name":"Hoher Sto\u00df",
    "tgn:placetype":[
        "aat:300008777"
    ]
},
  "bbox": [],
  "geometry": {"coordinates":[8.133333,51.483333],"type":"Point"}
}