{
  "id": 7395512,
  "type": "Feature",
  "properties": {
    "tgn:hierarchy":[
        "tgn:7395512",
        "tgn:7005586",
        "tgn:1000001",
        "tgn:7005560",
        "tgn:7029392"
    ],
    "tgn:id":7395512,
    "tgn:name":"San Antonio",
    "tgn:placetype":[
        "aat:300008347"
    ]
},
  "bbox": [],
  "geometry": {"coordinates":[-103.783333,21.833333],"type":"Point"}
}