{
  "id": 2677805,
  "type": "Feature",
  "properties": {
    "tgn:hierarchy":[
        "tgn:2677805",
        "tgn:1000001",
        "tgn:7012149",
        "tgn:7007827",
        "tgn:7029392"
    ],
    "tgn:id":2677805,
    "tgn:name":"South Draw",
    "tgn:placetype":[
        "aat:300008761"
    ]
},
  "bbox": [],
  "geometry": {"coordinates":[-111.1667,38.1167],"type":"Point"}
}