{
  "id": 2304265,
  "type": "Feature",
  "properties": {
    "tgn:hierarchy":[
        "tgn:2304265",
        "tgn:1000001",
        "tgn:7006451",
        "tgn:7012149",
        "tgn:2000103",
        "tgn:7029392"
    ],
    "tgn:id":2304265,
    "tgn:name":"Earis Tank",
    "tgn:placetype":[
        "aat:300006191"
    ]
},
  "bbox": [],
  "geometry": {"coordinates":[-112.75,34.15],"type":"Point"}
}