{
  "id": 1040114,
  "type": "Feature",
  "properties": {
    "tgn:hierarchy":[
        "tgn:1040114",
        "tgn:7003669",
        "tgn:1000003",
        "tgn:7000084",
        "tgn:7029392"
    ],
    "tgn:id":1040114,
    "tgn:name":"Lichtenberg",
    "tgn:placetype":[
        "aat:300008347"
    ]
},
  "bbox": [],
  "geometry": {"coordinates":[11.666667,50.383333],"type":"Point"}
}