{
  "id": 1068646,
  "type": "Feature",
  "properties": {
    "tgn:hierarchy":[
        "tgn:1068646",
        "tgn:1000004",
        "tgn:7002086",
        "tgn:1000111",
        "tgn:7029392"
    ],
    "tgn:id":1068646,
    "tgn:name":"Heilongguan",
    "tgn:placetype":[
        "aat:300008347"
    ]
},
  "bbox": [],
  "geometry": {"coordinates":[111.25,36.2833],"type":"Point"}
}