{
  "id": 7165852,
  "type": "Feature",
  "properties": {
    "tgn:hierarchy":[
        "tgn:7165852",
        "tgn:1000003",
        "tgn:7003678",
        "tgn:7000084",
        "tgn:7029392"
    ],
    "tgn:id":7165852,
    "tgn:name":"Hardtk\u00fcppel",
    "tgn:placetype":[
        "aat:300008777"
    ]
},
  "bbox": [],
  "geometry": {"coordinates":[8.466667,50.383333],"type":"Point"}
}