<<<<<<< HEAD
{
  "id": 2336120,
  "type": "Feature",
  "properties": {
    "tgn:hierarchy":[
        "tgn:2336120",
        "tgn:1000001",
        "tgn:7012149",
        "tgn:2000850",
        "tgn:7007255",
        "tgn:7029392"
    ],
    "tgn:id":2336120,
    "tgn:name":"Foster Hollow",
    "tgn:placetype":[
        "aat:300008761"
    ]
},
  "bbox": [],
  "geometry": {"coordinates":[-84.75,36.8],"type":"Point"}
}
=======
{"geometry":{"type":"Point","coordinates":[-84.750000,36.800000]},"type":"Feature","properties":{"hierarchy":["tgn:2336120","tgn:1000001","tgn:7012149","tgn:2000850","tgn:7007255","tgn:7029392"],"placetype":["aat:300008761"],"id":2336120,"name:xx":"Foster Hollow"}}
>>>>>>> 03f74aca74312dbeaf24d7e61306dd6a786dc3d0
