{
  "id": 7504201,
  "type": "Feature",
  "properties": {
    "tgn:hierarchy":[
        "tgn:7504201",
        "tgn:1008380",
        "tgn:1000226",
        "tgn:7000512",
        "tgn:1000006",
        "tgn:7029392"
    ],
    "tgn:id":7504201,
    "tgn:name:en":"Wangaehu River",
    "tgn:placetype":[
        "aat:300008699"
    ]
},
  "bbox": [],
  "geometry": {"coordinates":[175.683333,-40.983333],"type":"Point"}
}