{
  "id": 2738263,
  "type": "Feature",
  "properties": {
    "tgn:hierarchy":[
        "tgn:2738263",
        "tgn:1000001",
        "tgn:7012149",
        "tgn:7007157",
        "tgn:2000189",
        "tgn:7029392"
    ],
    "tgn:id":2738263,
    "tgn:name":"Uminoffer Gulch",
    "tgn:placetype":[
        "aat:300008761"
    ]
},
  "bbox": [],
  "geometry": {"coordinates":[-122.6833,41.65],"type":"Point"}
}