{
  "id": 2752723,
  "type": "Feature",
  "properties": {
    "tgn:hierarchy":[
        "tgn:2752723",
        "tgn:1000001",
        "tgn:7012149",
        "tgn:2000412",
        "tgn:7007248",
        "tgn:7029392"
    ],
    "tgn:id":2752723,
    "tgn:name":"Wastewater Treatment Pond Number Two",
    "tgn:placetype":[
        "aat:300006191"
    ]
},
  "bbox": [],
  "geometry": {"coordinates":[-81.9333,33.3167],"type":"Point"}
}