{
  "id": 7261978,
  "type": "Feature",
  "properties": {
    "tgn:concordances":{
        "gn:id":"2756313"
    },
    "tgn:hierarchy":[
        "tgn:7261978",
        "tgn:7003614",
        "tgn:1000003",
        "tgn:7016845",
        "tgn:7029392"
    ],
    "tgn:id":7261978,
    "tgn:name:nl":"Eexterveenschekanaal",
    "tgn:placetype":[
        "aat:300008347"
    ]
},
  "bbox": [],
  "geometry": {"coordinates":[6.833333,53.05],"type":"Point"}
}