{
  "id": 2668596,
  "type": "Feature",
  "properties": {
    "tgn:hierarchy":[
        "tgn:2668596",
        "tgn:1002169",
        "tgn:1000001",
        "tgn:7012149",
        "tgn:7007255",
        "tgn:7029392"
    ],
    "tgn:id":2668596,
    "tgn:name":"Slate Lick Branch",
    "tgn:placetype":[
        "aat:300008699"
    ]
},
  "bbox": [],
  "geometry": {"coordinates":[-83.6333,38.0667],"type":"Point"}
}