{
  "id": 2130510,
  "type": "Feature",
  "properties": {
    "tgn:hierarchy":[
        "tgn:2130510",
        "tgn:1000001",
        "tgn:7012149",
        "tgn:2002011",
        "tgn:7007826",
        "tgn:7029392"
    ],
    "tgn:id":2130510,
    "tgn:name":"Alligator Bayou",
    "tgn:placetype":[
        "aat:300008699"
    ]
},
  "bbox": [],
  "geometry": {"coordinates":[-93.9667,29.85],"type":"Point"}
}