{
  "id": 2004739,
  "type": "Feature",
  "properties": {
    "tgn:hierarchy":[
        "tgn:2004739",
        "tgn:7002659",
        "tgn:1000001",
        "tgn:7012149",
        "tgn:2000036",
        "tgn:7029392"
    ],
    "tgn:id":2004739,
    "tgn:name":"Oak Grove",
    "tgn:placetype":[
        "aat:300008347"
    ]
},
  "bbox": [],
  "geometry": {"coordinates":[-87.15,33.45],"type":"Point"}
}