{
  "id": 2560535,
  "type": "Feature",
  "properties": {
    "tgn:hierarchy":[
        "tgn:2560535",
        "tgn:1000001",
        "tgn:7012149",
        "tgn:2000481",
        "tgn:7007250",
        "tgn:7029392"
    ],
    "tgn:id":2560535,
    "tgn:name":"Oreana Spring",
    "tgn:placetype":[
        "aat:300008697"
    ]
},
  "bbox": [],
  "geometry": {"coordinates":[-114.4833,45.45],"type":"Point"}
}