{
  "id": 2407930,
  "type": "Feature",
  "properties": {
    "tgn:hierarchy":[
        "tgn:2407930",
        "tgn:1000001",
        "tgn:7012149",
        "tgn:2000784",
        "tgn:7007255",
        "tgn:7029392"
    ],
    "tgn:id":2407930,
    "tgn:name":"Hurricane Creek",
    "tgn:placetype":[
        "aat:300008706"
    ]
},
  "bbox": [],
  "geometry": {"coordinates":[-88.1667,37.3333],"type":"Point"}
}