{
  "id": 2717592,
  "type": "Feature",
  "properties": {
    "tgn:hierarchy":[
        "tgn:2717592",
        "tgn:1000001",
        "tgn:7016172",
        "tgn:7012149",
        "tgn:2000134",
        "tgn:7029392"
    ],
    "tgn:id":2717592,
    "tgn:name":"Thomas Creek",
    "tgn:placetype":[
        "aat:300008706"
    ]
},
  "bbox": [],
  "geometry": {"coordinates":[-92.7333,34.25],"type":"Point"}
}