<<<<<<< HEAD
{
  "id": 2700286,
  "type": "Feature",
  "properties": {
    "tgn:hierarchy":[
        "tgn:2700286",
        "tgn:1000001",
        "tgn:2001816",
        "tgn:7012149",
        "tgn:7007713",
        "tgn:7029392"
    ],
    "tgn:id":2700286,
    "tgn:name":"Sturgis Sandstone Quarry",
    "tgn:placetype":[
        "aat:300000390"
    ]
},
  "bbox": [],
  "geometry": {"coordinates":[-103.5333,44.3833],"type":"Point"}
}
=======
{"geometry":{"type":"Point","coordinates":[-103.533300,44.383300]},"type":"Feature","properties":{"hierarchy":["tgn:2700286","tgn:1000001","tgn:2001816","tgn:7012149","tgn:7007713","tgn:7029392"],"placetype":["aat:300000390"],"id":2700286,"name:xx":"Sturgis Sandstone Quarry"}}
>>>>>>> 03f74aca74312dbeaf24d7e61306dd6a786dc3d0
