<<<<<<< HEAD
{
  "id": 7025702,
  "type": "Feature",
  "properties": {
    "tgn:hierarchy":[
        "tgn:7025702",
        "tgn:7002445",
        "tgn:1000003",
        "tgn:7012077",
        "tgn:7008591",
        "tgn:7029392"
    ],
    "tgn:id":7025702,
    "tgn:name":"Raleigh",
    "tgn:placetype":[
        "aat:300008347"
    ]
},
  "bbox": [],
  "geometry": {"coordinates":[-4.05,51.0833],"type":"Point"}
}
=======
{"geometry":{"type":"Point","coordinates":[-4.050000,51.083300]},"type":"Feature","properties":{"hierarchy":["tgn:7025702","tgn:7002445","tgn:1000003","tgn:7012077","tgn:7008591","tgn:7029392"],"placetype":["aat:300008347"],"id":7025702,"name:xx":"Raleigh"}}
>>>>>>> 03f74aca74312dbeaf24d7e61306dd6a786dc3d0
