{
  "id": 2696418,
  "type": "Feature",
  "properties": {
    "tgn:hierarchy":[
        "tgn:2696418",
        "tgn:1000001",
        "tgn:7012149",
        "tgn:7007523",
        "tgn:7029392"
    ],
    "tgn:id":2696418,
    "tgn:name":"Stone Hill Branch",
    "tgn:placetype":[
        "aat:300008699"
    ]
},
  "bbox": [],
  "geometry": {"coordinates":[-91.2833,37.5667],"type":"Point"}
}