<<<<<<< HEAD
{
  "id": 2255763,
  "type": "Feature",
  "properties": {
    "tgn:hierarchy":[
        "tgn:2255763",
        "tgn:1000001",
        "tgn:7006451",
        "tgn:7012149",
        "tgn:2000097",
        "tgn:7029392"
    ],
    "tgn:id":2255763,
    "tgn:name":"Copper Camp Creek",
    "tgn:placetype":[
        "aat:300008706"
    ]
},
  "bbox": [],
  "geometry": {"coordinates":[-111.5333,33.9667],"type":"Point"}
}
=======
{"geometry":{"type":"Point","coordinates":[-111.533300,33.966700]},"type":"Feature","properties":{"hierarchy":["tgn:2255763","tgn:1000001","tgn:7006451","tgn:7012149","tgn:2000097","tgn:7029392"],"placetype":["aat:300008706"],"id":2255763,"name:xx":"Copper Camp Creek"}}
>>>>>>> 03f74aca74312dbeaf24d7e61306dd6a786dc3d0
