{
  "id": 2712886,
  "type": "Feature",
  "properties": {
    "tgn:hierarchy":[
        "tgn:2712886",
        "tgn:1000001",
        "tgn:7012149",
        "tgn:2000213",
        "tgn:7007158",
        "tgn:7029392"
    ],
    "tgn:id":2712886,
    "tgn:name":"Taylor Gulch",
    "tgn:placetype":[
        "aat:300008761"
    ]
},
  "bbox": [],
  "geometry": {"coordinates":[-105.9167,38.4333],"type":"Point"}
}