{
  "id": 2541507,
  "type": "Feature",
  "properties": {
    "tgn:hierarchy":[
        "tgn:2541507",
        "tgn:1000001",
        "tgn:7012149",
        "tgn:1002611",
        "tgn:7007706",
        "tgn:7029392"
    ],
    "tgn:id":2541507,
    "tgn:name":"Niles Beach",
    "tgn:placetype":[
        "aat:300008347"
    ]
},
  "bbox": [],
  "geometry": {"coordinates":[-83.3667,41.6833],"type":"Point"}
}