{
  "id": 2510372,
  "type": "Feature",
  "properties": {
    "tgn:hierarchy":[
        "tgn:2510372",
        "tgn:1000001",
        "tgn:7012149",
        "tgn:7014160",
        "tgn:7007919",
        "tgn:7029392"
    ],
    "tgn:id":2510372,
    "tgn:name":"Middle Run",
    "tgn:placetype":[
        "aat:300008699"
    ]
},
  "bbox": [],
  "geometry": {"coordinates":[-77.25,38.75],"type":"Point"}
}