{
  "id": 7585812,
  "type": "Feature",
  "properties": {
    "tgn:hierarchy":[
        "tgn:7585812",
        "tgn:1000004",
        "tgn:7000198",
        "tgn:7000799",
        "tgn:7029392"
    ],
    "tgn:id":7585812,
    "tgn:name:en":"Surhalu Forest",
    "tgn:placetype":[
        "aat:300008863"
    ]
},
  "bbox": [],
  "geometry": {"coordinates":[74.183333,34.366667],"type":"Point"}
}