{
  "id": 7333768,
  "type": "Feature",
  "properties": {
    "tgn:hierarchy":[
        "tgn:7333768",
        "tgn:7002759",
        "tgn:7008909",
        "tgn:1000003",
        "tgn:1000095",
        "tgn:7029392"
    ],
    "tgn:id":7333768,
    "tgn:name":"Escalona",
    "tgn:placetype":[
        "aat:300008347"
    ]
},
  "bbox": [],
  "geometry": {"coordinates":[0.142898,42.49845],"type":"Point"}
}