{
  "id": 7552010,
  "type": "Feature",
  "properties": {
    "tgn:hierarchy":[
        "tgn:7552010",
        "tgn:1000004",
        "tgn:7000198",
        "tgn:1001895",
        "tgn:7029392"
    ],
    "tgn:id":7552010,
    "tgn:name:en":"Chikhali",
    "tgn:placetype":[
        "aat:300008347"
    ]
},
  "bbox": [],
  "geometry": {"coordinates":[74.333333,16.45],"type":"Point"}
}