{
  "id": 2620481,
  "type": "Feature",
  "properties": {
    "tgn:hierarchy":[
        "tgn:2620481",
        "tgn:1000001",
        "tgn:7012149",
        "tgn:2002043",
        "tgn:7007826",
        "tgn:7029392"
    ],
    "tgn:id":2620481,
    "tgn:name":"River Tank",
    "tgn:placetype":[
        "aat:300006191"
    ]
},
  "bbox": [],
  "geometry": {"coordinates":[-100.8833,32.2667],"type":"Point"}
}