{
  "id": 2534364,
  "type": "Feature",
  "properties": {
    "tgn:hierarchy":[
        "tgn:2534364",
        "tgn:1000001",
        "tgn:7012149",
        "tgn:2001288",
        "tgn:7007524",
        "tgn:7029392"
    ],
    "tgn:id":2534364,
    "tgn:name":"NE NE Section 28 Mine",
    "tgn:placetype":[
        "aat:300000390"
    ]
},
  "bbox": [],
  "geometry": {"coordinates":[-112.5833,45.6333],"type":"Point"}
}