{
  "id": 2302141,
  "type": "Feature",
  "properties": {
    "tgn:hierarchy":[
        "tgn:2302141",
        "tgn:1000001",
        "tgn:2002313",
        "tgn:7012149",
        "tgn:7007922",
        "tgn:7029392"
    ],
    "tgn:id":2302141,
    "tgn:name":"Dutch Creek",
    "tgn:placetype":[
        "aat:300008706"
    ]
},
  "bbox": [],
  "geometry": {"coordinates":[-91.1667,44.9667],"type":"Point"}
}