{
  "id": 2289201,
  "type": "Feature",
  "properties": {
    "tgn:hierarchy":[
        "tgn:2289201",
        "tgn:7002659",
        "tgn:1000001",
        "tgn:7012149",
        "tgn:2000058",
        "tgn:7029392"
    ],
    "tgn:id":2289201,
    "tgn:name":"Dividing Ridge",
    "tgn:placetype":[
        "aat:300266640"
    ]
},
  "bbox": [],
  "geometry": {"coordinates":[-86.8167,33.3167],"type":"Point"}
}