{
  "id": 1009598,
  "type": "Feature",
  "properties": {
    "tgn:hierarchy":[
        "tgn:1009598",
        "tgn:1001601",
        "tgn:1000233",
        "tgn:1000006",
        "tgn:7029392"
    ],
    "tgn:id":1009598,
    "tgn:name":"Vaghena Island",
    "tgn:placetype":[
        "aat:300008791"
    ]
},
  "bbox": [],
  "geometry": {"coordinates":[157.7667,-7.4333],"type":"Point"}
}