{
  "id": 2384553,
  "type": "Feature",
  "properties": {
    "tgn:hierarchy":[
        "tgn:2384553",
        "tgn:2002306",
        "tgn:1000001",
        "tgn:7012149",
        "tgn:7007922",
        "tgn:7029392"
    ],
    "tgn:id":2384553,
    "tgn:name":"Hell Hole Creek",
    "tgn:placetype":[
        "aat:300008706"
    ]
},
  "bbox": [],
  "geometry": {"coordinates":[-90.8667,46.2833],"type":"Point"}
}