{
  "id": 2264292,
  "type": "Feature",
  "properties": {
    "tgn:hierarchy":[
        "tgn:2264292",
        "tgn:2000001",
        "tgn:7002659",
        "tgn:1000001",
        "tgn:7012149",
        "tgn:7029392"
    ],
    "tgn:id":2264292,
    "tgn:name":"Crab Creek",
    "tgn:placetype":[
        "aat:300008706"
    ]
},
  "bbox": [],
  "geometry": {"coordinates":[-87.95,30.7667],"type":"Point"}
}