<<<<<<< HEAD
{
  "id": 2252381,
  "type": "Feature",
  "properties": {
    "tgn:hierarchy":[
        "tgn:2252381",
        "tgn:7006450",
        "tgn:1000001",
        "tgn:7012149",
        "tgn:2000089",
        "tgn:7029392"
    ],
    "tgn:id":2252381,
    "tgn:name":"Conglomerate Creek",
    "tgn:placetype":[
        "aat:300008706"
    ]
},
  "bbox": [],
  "geometry": {"coordinates":[-150.7333,67.5833],"type":"Point"}
}
=======
{"geometry":{"type":"Point","coordinates":[-150.733300,67.583300]},"type":"Feature","properties":{"hierarchy":["tgn:2252381","tgn:7006450","tgn:1000001","tgn:7012149","tgn:2000089","tgn:7029392"],"placetype":["aat:300008706"],"id":2252381,"name:xx":"Conglomerate Creek"}}
>>>>>>> 03f74aca74312dbeaf24d7e61306dd6a786dc3d0
