<<<<<<< HEAD
{
  "id": 7369592,
  "type": "Feature",
  "properties": {
    "tgn:hierarchy":[
        "tgn:7369592",
        "tgn:7005581",
        "tgn:1000001",
        "tgn:7005560",
        "tgn:7029392"
    ],
    "tgn:id":7369592,
    "tgn:name":"Jacalitos",
    "tgn:placetype":[
        "aat:300387007"
    ]
},
  "bbox": [],
  "geometry": {"coordinates":[-105.266667,27.05],"type":"Point"}
}
=======
{"geometry":{"type":"Point","coordinates":[-105.266667,27.050000]},"type":"Feature","properties":{"hierarchy":["tgn:7369592","tgn:7005581","tgn:1000001","tgn:7005560","tgn:7029392"],"placetype":["aat:300387007"],"id":7369592,"name:xx":"Jacalitos"}}
>>>>>>> 03f74aca74312dbeaf24d7e61306dd6a786dc3d0
