{
  "id": 2056375,
  "type": "Feature",
  "properties": {
    "tgn:hierarchy":[
        "tgn:2056375",
        "tgn:1000001",
        "tgn:7012149",
        "tgn:2001120",
        "tgn:7007522",
        "tgn:7029392"
    ],
    "tgn:id":2056375,
    "tgn:name":"Enondale",
    "tgn:placetype":[
        "aat:300008347"
    ]
},
  "bbox": [],
  "geometry": {"coordinates":[-88.4667,32.6333],"type":"Point"}
}