{
  "id": 2518301,
  "type": "Feature",
  "properties": {
    "tgn:hierarchy":[
        "tgn:2518301",
        "tgn:1000001",
        "tgn:7012149",
        "tgn:2000215",
        "tgn:7007158",
        "tgn:7029392"
    ],
    "tgn:id":2518301,
    "tgn:name":"Missouri Lake",
    "tgn:placetype":[
        "aat:300008680"
    ]
},
  "bbox": [],
  "geometry": {"coordinates":[-105.5167,39.8167],"type":"Point"}
}