{
  "id": 2716993,
  "type": "Feature",
  "properties": {
    "tgn:hierarchy":[
        "tgn:2716993",
        "tgn:1000001",
        "tgn:7012149",
        "tgn:2001029",
        "tgn:7007521",
        "tgn:7029392"
    ],
    "tgn:id":2716993,
    "tgn:name":"Thimble Lake",
    "tgn:placetype":[
        "aat:300008680"
    ]
},
  "bbox": [],
  "geometry": {"coordinates":[-93.4667,47.8667],"type":"Point"}
}