{
  "id": 2719456,
  "type": "Feature",
  "properties": {
    "tgn:hierarchy":[
        "tgn:2719456",
        "tgn:1000001",
        "tgn:7012149",
        "tgn:7007920",
        "tgn:7029392"
    ],
    "tgn:id":2719456,
    "tgn:name":"Three Devils",
    "tgn:placetype":[
        "aat:300008761"
    ]
},
  "bbox": [],
  "geometry": {"coordinates":[-119.7667,47.4333],"type":"Point"}
}