{
  "id": 7200710,
  "type": "Feature",
  "properties": {
    "tgn:hierarchy":[
        "tgn:7200710",
        "tgn:1000003",
        "tgn:7003677",
        "tgn:7000084",
        "tgn:7029392"
    ],
    "tgn:id":7200710,
    "tgn:name":"D\u00fcrholt",
    "tgn:placetype":[
        "aat:300000206"
    ]
},
  "bbox": [],
  "geometry": {"coordinates":[7.316667,51.266667],"type":"Point"}
}