{
  "id": 7408914,
  "type": "Feature",
  "properties": {
    "tgn:hierarchy":[
        "tgn:7408914",
        "tgn:7005580",
        "tgn:1000001",
        "tgn:7005560",
        "tgn:7029392"
    ],
    "tgn:id":7408914,
    "tgn:name":"Pamal\u00e1",
    "tgn:placetype":[
        "aat:300008347"
    ]
},
  "bbox": [],
  "geometry": {"coordinates":[-91.916667,16.883333],"type":"Point"}
}