{
  "id": 1042119,
  "type": "Feature",
  "properties": {
    "tgn:hierarchy":[
        "tgn:1042119",
        "tgn:7011270",
        "tgn:7002674",
        "tgn:1000003",
        "tgn:1000074",
        "tgn:7010922",
        "tgn:7029392"
    ],
    "tgn:id":1042119,
    "tgn:name:en":"M\u00edlos",
    "tgn:placetype":[
        "aat:300008347"
    ]
},
  "bbox": [],
  "geometry": {"coordinates":[24.433333,36.75],"type":"Point"}
}