{
  "id": 7491497,
  "type": "Feature",
  "properties": {
    "tgn:hierarchy":[
        "tgn:7491497",
        "tgn:1000004",
        "tgn:7490934",
        "tgn:1000141",
        "tgn:7029392"
    ],
    "tgn:id":7491497,
    "tgn:name":"Dakengwei",
    "tgn:placetype":[
        "aat:300008347"
    ]
},
  "bbox": [],
  "geometry": {"coordinates":[120.3862,23.0114],"type":"Point"}
}