{
  "id": 2589285,
  "type": "Feature",
  "properties": {
    "tgn:hierarchy":[
        "tgn:2589285",
        "tgn:1000001",
        "tgn:2001417",
        "tgn:7012149",
        "tgn:7007526",
        "tgn:7029392"
    ],
    "tgn:id":2589285,
    "tgn:name":"Poinsettia Spring",
    "tgn:placetype":[
        "aat:300008697"
    ]
},
  "bbox": [],
  "geometry": {"coordinates":[-118.25,38.7667],"type":"Point"}
}