<<<<<<< HEAD
{
  "id": 7172599,
  "type": "Feature",
  "properties": {
    "tgn:hierarchy":[
        "tgn:7172599",
        "tgn:7003669",
        "tgn:1000003",
        "tgn:7000084",
        "tgn:7029392"
    ],
    "tgn:id":7172599,
    "tgn:name":"Hellersberg",
    "tgn:placetype":[
        "aat:300008347"
    ]
},
  "bbox": [],
  "geometry": {"coordinates":[13.4,48.6],"type":"Point"}
}
=======
{"geometry":{"type":"Point","coordinates":[13.400000,48.600000]},"type":"Feature","properties":{"hierarchy":["tgn:7172599","tgn:7003669","tgn:1000003","tgn:7000084","tgn:7029392"],"placetype":["aat:300008347"],"id":7172599,"name:xx":"Hellersberg"}}
>>>>>>> 03f74aca74312dbeaf24d7e61306dd6a786dc3d0
