{
  "id": 2462421,
  "type": "Feature",
  "properties": {
    "tgn:hierarchy":[
        "tgn:2462421",
        "tgn:7002659",
        "tgn:1000001",
        "tgn:7012149",
        "tgn:7021514",
        "tgn:7029392"
    ],
    "tgn:id":2462421,
    "tgn:name":"Little Whippoorwill Creek",
    "tgn:placetype":[
        "aat:300008706"
    ]
},
  "bbox": [],
  "geometry": {"coordinates":[-86.0667,34.35],"type":"Point"}
}