{
  "id": 2351848,
  "type": "Feature",
  "properties": {
    "tgn:hierarchy":[
        "tgn:2351848",
        "tgn:1000001",
        "tgn:7012149",
        "tgn:2001920",
        "tgn:7007825",
        "tgn:7029392"
    ],
    "tgn:id":2351848,
    "tgn:name":"Glenview Lake",
    "tgn:placetype":[
        "aat:300006191"
    ]
},
  "bbox": [],
  "geometry": {"coordinates":[-89.8333,35.4667],"type":"Point"}
}