{
  "id": 2343953,
  "type": "Feature",
  "properties": {
    "tgn:hierarchy":[
        "tgn:2343953",
        "tgn:1000001",
        "tgn:7019560",
        "tgn:7012149",
        "tgn:7007566",
        "tgn:7029392"
    ],
    "tgn:id":2343953,
    "tgn:name":"Galloway Tank",
    "tgn:placetype":[
        "aat:300006191"
    ]
},
  "bbox": [],
  "geometry": {"coordinates":[-104.45,34.05],"type":"Point"}
}