{
  "id": 7589880,
  "type": "Feature",
  "properties": {
    "tgn:hierarchy":[
        "tgn:7589880",
        "tgn:1000004",
        "tgn:7000198",
        "tgn:7000799",
        "tgn:7029392"
    ],
    "tgn:id":7589880,
    "tgn:name:en":"Thandan\u0101ni",
    "tgn:placetype":[
        "aat:300008347"
    ]
},
  "bbox": [],
  "geometry": {"coordinates":[74.481489,33.062904],"type":"Point"}
}