{
  "id": 7037562,
  "type": "Feature",
  "properties": {
    "tgn:hierarchy":[
        "tgn:7037562",
        "tgn:7003007",
        "tgn:1000003",
        "tgn:7002997",
        "tgn:1000080",
        "tgn:7029392"
    ],
    "tgn:id":7037562,
    "tgn:name":"Trevenzuolo",
    "tgn:placetype":[
        "aat:300008347"
    ]
},
  "bbox": [],
  "geometry": {"coordinates":[10.933333,45.266667],"type":"Point"}
}