{
  "id": 2065209,
  "type": "Feature",
  "properties": {
    "tgn:hierarchy":[
        "tgn:2065209",
        "tgn:1000001",
        "tgn:1002410",
        "tgn:7012149",
        "tgn:7007565",
        "tgn:7029392"
    ],
    "tgn:id":2065209,
    "tgn:name":"Lincoln",
    "tgn:placetype":[
        "aat:300008347",
        "aat:300387210"
    ]
},
  "bbox": [],
  "geometry": {"coordinates":[-75.2333,39.6667],"type":"Point"}
}