{
  "id": 7420074,
  "type": "Feature",
  "properties": {
    "tgn:hierarchy":[
        "tgn:7420074",
        "tgn:1000001",
        "tgn:7005589",
        "tgn:7005560",
        "tgn:7029392"
    ],
    "tgn:id":7420074,
    "tgn:name:es":"El Quemado",
    "tgn:placetype":[
        "aat:300008347"
    ]
},
  "bbox": [],
  "geometry": {"coordinates":[-100.668889,26.296667],"type":"Point"}
}