{
  "id": 7348148,
  "type": "Feature",
  "properties": {
    "tgn:hierarchy":[
        "tgn:7348148",
        "tgn:7007780",
        "tgn:1000003",
        "tgn:7009604",
        "tgn:1000095",
        "tgn:7029392"
    ],
    "tgn:id":7348148,
    "tgn:name":"Aizpe-goicoechea",
    "tgn:placetype":[
        "aat:300008347"
    ]
},
  "bbox": [],
  "geometry": {"coordinates":[-2.302284,43.021235],"type":"Point"}
}