{
  "id": 2061846,
  "type": "Feature",
  "properties": {
    "tgn:hierarchy":[
        "tgn:2061846",
        "tgn:1000001",
        "tgn:7012149",
        "tgn:2001272",
        "tgn:7007524",
        "tgn:7029392"
    ],
    "tgn:id":2061846,
    "tgn:name":"Willard",
    "tgn:placetype":[
        "aat:300008347"
    ]
},
  "bbox": [],
  "geometry": {"coordinates":[-104.3667,46.1833],"type":"Point"}
}