{
  "id": 1035510,
  "type": "Feature",
  "properties": {
    "tgn:hierarchy":[
        "tgn:1035510",
        "tgn:1000003",
        "tgn:7002880",
        "tgn:1000070",
        "tgn:7029392"
    ],
    "tgn:id":1035510,
    "tgn:name":"Saint-R\u00e9my-en-Bouzemont-Saint-Genest-et-Isson",
    "tgn:placetype":[
        "aat:300008347"
    ]
},
  "bbox": [],
  "geometry": {"coordinates":[4.6333,48.6333],"type":"Point"}
}