{
  "id": 7397734,
  "type": "Feature",
  "properties": {
    "tgn:hierarchy":[
        "tgn:7397734",
        "tgn:1000001",
        "tgn:1001893",
        "tgn:7005560",
        "tgn:7029392"
    ],
    "tgn:id":7397734,
    "tgn:name":"Las Mesas",
    "tgn:placetype":[
        "aat:300008347"
    ]
},
  "bbox": [],
  "geometry": {"coordinates":[-99.497778,19.561111],"type":"Point"}
}