{
  "id": 2149306,
  "type": "Feature",
  "properties": {
    "tgn:hierarchy":[
        "tgn:2149306",
        "tgn:1000001",
        "tgn:7012149",
        "tgn:1002999",
        "tgn:7007526",
        "tgn:7029392"
    ],
    "tgn:id":2149306,
    "tgn:name":"Barrel Springs",
    "tgn:placetype":[
        "aat:300008697"
    ]
},
  "bbox": [],
  "geometry": {"coordinates":[-119.9667,41.8833],"type":"Point"}
}