{
  "id": 1054642,
  "type": "Feature",
  "properties": {
    "tgn:hierarchy":[
        "tgn:1054642",
        "tgn:1000004",
        "tgn:7011531",
        "tgn:7018214",
        "tgn:7002435",
        "tgn:7029392"
    ],
    "tgn:id":1054642,
    "tgn:name":"Yeysk",
    "tgn:placetype":[
        "aat:300008347"
    ]
},
  "bbox": [],
  "geometry": {"coordinates":[38.2833,46.7167],"type":"Point"}
}