{
  "id": 2337393,
  "type": "Feature",
  "properties": {
    "tgn:hierarchy":[
        "tgn:2337393",
        "tgn:1000001",
        "tgn:7012149",
        "tgn:2001503",
        "tgn:7007709",
        "tgn:7029392"
    ],
    "tgn:id":2337393,
    "tgn:name":"Fowler Balsam Mountain",
    "tgn:placetype":[
        "aat:300008798"
    ]
},
  "bbox": [],
  "geometry": {"coordinates":[-83.0667,35.4667],"type":"Point"}
}