{
  "id": 2050355,
  "type": "Feature",
  "properties": {
    "tgn:hierarchy":[
        "tgn:2050355",
        "tgn:1000001",
        "tgn:7012149",
        "tgn:1003038",
        "tgn:7007517",
        "tgn:7029392"
    ],
    "tgn:id":2050355,
    "tgn:name":"Furnace",
    "tgn:placetype":[
        "aat:300008347",
        "aat:300387210"
    ]
},
  "bbox": [],
  "geometry": {"coordinates":[-72.15,42.3333],"type":"Point"}
}