{
  "id": 7179569,
  "type": "Feature",
  "properties": {
    "tgn:hierarchy":[
        "tgn:7179569",
        "tgn:1000003",
        "tgn:7003688",
        "tgn:7000084",
        "tgn:7029392"
    ],
    "tgn:id":7179569,
    "tgn:name":"Hamdorf",
    "tgn:placetype":[
        "aat:300008347"
    ]
},
  "bbox": [],
  "geometry": {"coordinates":[9.533333,54.233333],"type":"Point"}
}