{
  "id": 1070366,
  "type": "Feature",
  "properties": {
    "tgn:hierarchy":[
        "tgn:1070366",
        "tgn:1000004",
        "tgn:7001319",
        "tgn:1000111",
        "tgn:7029392"
    ],
    "tgn:id":1070366,
    "tgn:name":"Mara",
    "tgn:placetype":[
        "aat:300008347"
    ]
},
  "bbox": [],
  "geometry": {"coordinates":[94.1333,28.1833],"type":"Point"}
}