{
  "id": 2721072,
  "type": "Feature",
  "properties": {
    "tgn:hierarchy":[
        "tgn:2721072",
        "tgn:1000001",
        "tgn:7012149",
        "tgn:2000181",
        "tgn:7007157",
        "tgn:7029392"
    ],
    "tgn:id":2721072,
    "tgn:name":"Tierney Peak",
    "tgn:placetype":[
        "aat:300008798"
    ]
},
  "bbox": [],
  "geometry": {"coordinates":[-123.55,40.4333],"type":"Point"}
}