{
  "id": 2036510,
  "type": "Feature",
  "properties": {
    "tgn:hierarchy":[
        "tgn:2036510",
        "tgn:1000001",
        "tgn:7012149",
        "tgn:2000716",
        "tgn:7007254",
        "tgn:7029392"
    ],
    "tgn:id":2036510,
    "tgn:name":"Hilton",
    "tgn:placetype":[
        "aat:300387016"
    ]
},
  "bbox": [],
  "geometry": {"coordinates":[-97.6667,38.4333],"type":"Point"}
}