{
  "id": 2237989,
  "type": "Feature",
  "properties": {
    "tgn:hierarchy":[
        "tgn:2237989",
        "tgn:7006450",
        "tgn:1000001",
        "tgn:7012149",
        "tgn:2000089",
        "tgn:7029392"
    ],
    "tgn:id":2237989,
    "tgn:name":"Chips Island",
    "tgn:placetype":[
        "aat:300008791"
    ]
},
  "bbox": [],
  "geometry": {"coordinates":[-157.65,65.1333],"type":"Point"}
}