{
  "id": 2173609,
  "type": "Feature",
  "properties": {
    "tgn:hierarchy":[
        "tgn:2173609",
        "tgn:1000001",
        "tgn:7012149",
        "tgn:1003017",
        "tgn:7007710",
        "tgn:7029392"
    ],
    "tgn:id":2173609,
    "tgn:name":"Birch Rock Hill",
    "tgn:placetype":[
        "aat:300008798"
    ]
},
  "bbox": [],
  "geometry": {"coordinates":[-79.3167,40.0333],"type":"Point"}
}