{
  "id": 2378823,
  "type": "Feature",
  "properties": {
    "tgn:hierarchy":[
        "tgn:2378823",
        "tgn:1000001",
        "tgn:7012149",
        "tgn:1003042",
        "tgn:7007920",
        "tgn:7029392"
    ],
    "tgn:id":2378823,
    "tgn:name":"Hart Creek",
    "tgn:placetype":[
        "aat:300008706"
    ]
},
  "bbox": [],
  "geometry": {"coordinates":[-121.1833,46.65],"type":"Point"}
}