{
  "id": 2106530,
  "type": "Feature",
  "properties": {
    "tgn:hierarchy":[
        "tgn:2106530",
        "tgn:1000001",
        "tgn:2001940",
        "tgn:7012149",
        "tgn:7007826",
        "tgn:7029392"
    ],
    "tgn:id":2106530,
    "tgn:name":"Orangedale",
    "tgn:placetype":[
        "aat:300008347",
        "aat:300387210"
    ]
},
  "bbox": [],
  "geometry": {"coordinates":[-97.8167,28.4333],"type":"Point"}
}