{
  "id": 7109600,
  "type": "Feature",
  "properties": {
    "tgn:hierarchy":[
        "tgn:7109600",
        "tgn:7003692",
        "tgn:1000003",
        "tgn:7000084",
        "tgn:7029392"
    ],
    "tgn:id":7109600,
    "tgn:name":"Reckenberg",
    "tgn:placetype":[
        "aat:300008347"
    ]
},
  "bbox": [],
  "geometry": {"coordinates":[7.983333,47.983333],"type":"Point"}
}