{
  "id": 2497349,
  "type": "Feature",
  "properties": {
    "tgn:hierarchy":[
        "tgn:2497349",
        "tgn:1000001",
        "tgn:7012149",
        "tgn:1002694",
        "tgn:7007252",
        "tgn:7029392"
    ],
    "tgn:id":2497349,
    "tgn:name":"Maxine, Lake",
    "tgn:placetype":[
        "aat:300006191"
    ]
},
  "bbox": [],
  "geometry": {"coordinates":[-86.6167,39.4833],"type":"Point"}
}