{
  "id": 7282224,
  "type": "Feature",
  "properties": {
    "tgn:hierarchy":[
        "tgn:7282224",
        "tgn:1001708",
        "tgn:1000049",
        "tgn:1000002",
        "tgn:7029392"
    ],
    "tgn:id":7282224,
    "tgn:name":"San Nicol\u00e1s, Estero",
    "tgn:placetype":[
        "aat:300008699"
    ]
},
  "bbox": [],
  "geometry": {"coordinates":[-70.183333,-33.766667],"type":"Point"}
}