{
  "id": 1079230,
  "type": "Feature",
  "properties": {
    "tgn:hierarchy":[
        "tgn:1079230",
        "tgn:1000004",
        "tgn:7002004",
        "tgn:7000231",
        "tgn:7029392"
    ],
    "tgn:id":1079230,
    "tgn:name":"Ozgol",
    "tgn:placetype":[
        "aat:300008347"
    ]
},
  "bbox": [],
  "geometry": {"coordinates":[51.4833,35.7833],"type":"Point"}
}