{
  "id": 2080496,
  "type": "Feature",
  "properties": {
    "tgn:hierarchy":[
        "tgn:2080496",
        "tgn:1000001",
        "tgn:7012149",
        "tgn:1003007",
        "tgn:7007706",
        "tgn:7029392"
    ],
    "tgn:id":2080496,
    "tgn:name":"McCance",
    "tgn:placetype":[
        "aat:300008347",
        "aat:300387210"
    ]
},
  "bbox": [],
  "geometry": {"coordinates":[-81.8833,40.6833],"type":"Point"}
}