{
  "id": 2513546,
  "type": "Feature",
  "properties": {
    "tgn:hierarchy":[
        "tgn:2513546",
        "tgn:1000001",
        "tgn:1002714",
        "tgn:7012149",
        "tgn:7007159",
        "tgn:7029392"
    ],
    "tgn:id":2513546,
    "tgn:name":"Mill Pond",
    "tgn:placetype":[
        "aat:300008680"
    ]
},
  "bbox": [],
  "geometry": {"coordinates":[-72.2333,41.45],"type":"Point"}
}