{
  "id": 7589215,
  "type": "Feature",
  "properties": {
    "tgn:hierarchy":[
        "tgn:7589215",
        "tgn:1000004",
        "tgn:7000198",
        "tgn:1001977",
        "tgn:7029392"
    ],
    "tgn:id":7589215,
    "tgn:name:en":"Jagadal G\u0101ng",
    "tgn:placetype":[
        "aat:300387055"
    ]
},
  "bbox": [],
  "geometry": {"coordinates":[88.435622,21.620051],"type":"Point"}
}