{
  "id": 1081333,
  "type": "Feature",
  "properties": {
    "tgn:hierarchy":[
        "tgn:1081333",
        "tgn:1001015",
        "tgn:7000897",
        "tgn:1000004",
        "tgn:1000120",
        "tgn:7029392"
    ],
    "tgn:id":1081333,
    "tgn:name":"Shingo",
    "tgn:placetype":[
        "aat:300008347"
    ]
},
  "bbox": [],
  "geometry": {"coordinates":[133.3833,34.9833],"type":"Point"}
}