{
  "id": 7517145,
  "type": "Feature",
  "properties": {
    "tgn:hierarchy":[
        "tgn:7517145",
        "tgn:7016670",
        "tgn:1008380",
        "tgn:1000226",
        "tgn:1000006",
        "tgn:7029392"
    ],
    "tgn:id":7517145,
    "tgn:name:en":"Mangahina Stream",
    "tgn:placetype":[
        "aat:300008699"
    ]
},
  "bbox": [],
  "geometry": {"coordinates":[176.716667,-39.383333],"type":"Point"}
}