{
  "id": 2540457,
  "type": "Feature",
  "properties": {
    "tgn:hierarchy":[
        "tgn:2540457",
        "tgn:1000001",
        "tgn:7012149",
        "tgn:1002418",
        "tgn:7007920",
        "tgn:7029392"
    ],
    "tgn:id":2540457,
    "tgn:name":"Newskah Creek",
    "tgn:placetype":[
        "aat:300008706"
    ]
},
  "bbox": [],
  "geometry": {"coordinates":[-123.7833,46.8667],"type":"Point"}
}