{
  "id": 7315873,
  "type": "Feature",
  "properties": {
    "tgn:hierarchy":[
        "tgn:7315873",
        "tgn:1001657",
        "tgn:1000049",
        "tgn:1000002",
        "tgn:7029392"
    ],
    "tgn:id":7315873,
    "tgn:name":"Cenicero, Cerro",
    "tgn:placetype":[
        "aat:300008795"
    ]
},
  "bbox": [],
  "geometry": {"coordinates":[-70.75,-31.35],"type":"Point"}
}