{
  "id": 2352600,
  "type": "Feature",
  "properties": {
    "tgn:hierarchy":[
        "tgn:2352600",
        "tgn:1000001",
        "tgn:7012149",
        "tgn:7007708",
        "tgn:7029392"
    ],
    "tgn:id":2352600,
    "tgn:name":"Goat Peak",
    "tgn:placetype":[
        "aat:300008798"
    ]
},
  "bbox": [],
  "geometry": {"coordinates":[-121.7833,44.6333],"type":"Point"}
}