{
  "id": 7252050,
  "type": "Feature",
  "properties": {
    "tgn:hierarchy":[
        "tgn:7252050",
        "tgn:7003457",
        "tgn:1000003",
        "tgn:1000063",
        "tgn:7018236",
        "tgn:7029392"
    ],
    "tgn:id":7252050,
    "tgn:name":"Melselestraat",
    "tgn:placetype":[
        "aat:300008347"
    ]
},
  "bbox": [],
  "geometry": {"coordinates":[4.25,51.183333],"type":"Point"}
}