{
  "id": 2661694,
  "type": "Feature",
  "properties": {
    "tgn:hierarchy":[
        "tgn:2661694",
        "tgn:1000001",
        "tgn:2001702",
        "tgn:7012149",
        "tgn:7007708",
        "tgn:7029392"
    ],
    "tgn:id":2661694,
    "tgn:name":"Shuck Mountain",
    "tgn:placetype":[
        "aat:300008798"
    ]
},
  "bbox": [],
  "geometry": {"coordinates":[-124.1333,43.1167],"type":"Point"}
}