{
  "id": 2773965,
  "type": "Feature",
  "properties": {
    "tgn:hierarchy":[
        "tgn:2773965",
        "tgn:1000001",
        "tgn:7012149",
        "tgn:2000816",
        "tgn:7007255",
        "tgn:7029392"
    ],
    "tgn:id":2773965,
    "tgn:name":"Willow Creek",
    "tgn:placetype":[
        "aat:300008706"
    ]
},
  "bbox": [],
  "geometry": {"coordinates":[-88.1333,36.95],"type":"Point"}
}