{
  "id": 7287623,
  "type": "Feature",
  "properties": {
    "tgn:hierarchy":[
        "tgn:7287623",
        "tgn:1001630",
        "tgn:1000049",
        "tgn:1000002",
        "tgn:7029392"
    ],
    "tgn:id":7287623,
    "tgn:name":"La Diuca, Cerro",
    "tgn:placetype":[
        "aat:300008777"
    ]
},
  "bbox": [],
  "geometry": {"coordinates":[-70.85,-27.783333],"type":"Point"}
}