{
  "id": 2082279,
  "type": "Feature",
  "properties": {
    "tgn:hierarchy":[
        "tgn:2082279",
        "tgn:1000001",
        "tgn:1002304",
        "tgn:7012149",
        "tgn:7007706",
        "tgn:7029392"
    ],
    "tgn:id":2082279,
    "tgn:name":"Tunnel Hill",
    "tgn:placetype":[
        "aat:300008347",
        "aat:300387210"
    ]
},
  "bbox": [],
  "geometry": {"coordinates":[-82.0333,40.25],"type":"Point"}
}