{
  "id": 7553348,
  "type": "Feature",
  "properties": {
    "tgn:hierarchy":[
        "tgn:7553348",
        "tgn:1000004",
        "tgn:7000198",
        "tgn:1001895",
        "tgn:7029392"
    ],
    "tgn:id":7553348,
    "tgn:name:en":"Pande",
    "tgn:placetype":[
        "aat:300008347"
    ]
},
  "bbox": [],
  "geometry": {"coordinates":[75.231665,18.375642],"type":"Point"}
}