{
  "id": 2743974,
  "type": "Feature",
  "properties": {
    "tgn:hierarchy":[
        "tgn:2743974",
        "tgn:7006450",
        "tgn:1000001",
        "tgn:7012149",
        "tgn:2000089",
        "tgn:7029392"
    ],
    "tgn:id":2743974,
    "tgn:name":"Venetie Lake",
    "tgn:placetype":[
        "aat:300008680"
    ]
},
  "bbox": [],
  "geometry": {"coordinates":[-146.35,67.05],"type":"Point"}
}