{
  "id": 2690244,
  "type": "Feature",
  "properties": {
    "tgn:hierarchy":[
        "tgn:2690244",
        "tgn:1000001",
        "tgn:7012149",
        "tgn:2000225",
        "tgn:7007158",
        "tgn:7029392"
    ],
    "tgn:id":2690244,
    "tgn:name":"Stag Canyon",
    "tgn:placetype":[
        "aat:300008761"
    ]
},
  "bbox": [],
  "geometry": {"coordinates":[-108.0167,37.0833],"type":"Point"}
}