{
  "id": 7501561,
  "type": "Feature",
  "properties": {
    "tgn:hierarchy":[
        "tgn:7501561",
        "tgn:1000004",
        "tgn:7492971",
        "tgn:1000141",
        "tgn:7029392"
    ],
    "tgn:id":7501561,
    "tgn:name":"Luliao",
    "tgn:placetype":[
        "aat:300008347"
    ]
},
  "bbox": [],
  "geometry": {"coordinates":[120.8925,22.047778],"type":"Point"}
}