{
  "id": 7140257,
  "type": "Feature",
  "properties": {
    "tgn:hierarchy":[
        "tgn:7140257",
        "tgn:1000003",
        "tgn:7003688",
        "tgn:7000084",
        "tgn:7029392"
    ],
    "tgn:id":7140257,
    "tgn:name":"Louisenberg",
    "tgn:placetype":[
        "aat:300008347"
    ]
},
  "bbox": [],
  "geometry": {"coordinates":[9.866667,54.483333],"type":"Point"}
}