{
  "id": 2166648,
  "type": "Feature",
  "properties": {
    "tgn:hierarchy":[
        "tgn:2166648",
        "tgn:1000001",
        "tgn:7012149",
        "tgn:2001544",
        "tgn:7007709",
        "tgn:7029392"
    ],
    "tgn:id":2166648,
    "tgn:name":"Big Branch",
    "tgn:placetype":[
        "aat:300008699"
    ]
},
  "bbox": [],
  "geometry": {"coordinates":[-82.7167,35.1167],"type":"Point"}
}