{
  "id": 2586514,
  "type": "Feature",
  "properties": {
    "tgn:hierarchy":[
        "tgn:2586514",
        "tgn:1000001",
        "tgn:7012149",
        "tgn:2002250",
        "tgn:7007920",
        "tgn:7029392"
    ],
    "tgn:id":2586514,
    "tgn:name":"Pittman Lake",
    "tgn:placetype":[
        "aat:300008680"
    ]
},
  "bbox": [],
  "geometry": {"coordinates":[-118.1333,48.8833],"type":"Point"}
}