<<<<<<< HEAD
{
  "id": 7022381,
  "type": "Feature",
  "properties": {
    "tgn:hierarchy":[
        "tgn:7022381",
        "tgn:1000001",
        "tgn:7012149",
        "tgn:2001125",
        "tgn:7007522",
        "tgn:7029392"
    ],
    "tgn:id":7022381,
    "tgn:name":"Bertice",
    "tgn:placetype":[
        "aat:300008347",
        "aat:300387210"
    ]
},
  "bbox": [],
  "geometry": {"coordinates":[-89.6667,32.6167],"type":"Point"}
}
=======
{"geometry":{"type":"Point","coordinates":[-89.666700,32.616700]},"type":"Feature","properties":{"hierarchy":["tgn:7022381","tgn:1000001","tgn:7012149","tgn:2001125","tgn:7007522","tgn:7029392"],"placetype":["aat:300008347","aat:300387210"],"id":7022381,"name:xx":"Bertice"}}
>>>>>>> 03f74aca74312dbeaf24d7e61306dd6a786dc3d0
