{
  "id": 2554257,
  "type": "Feature",
  "properties": {
    "tgn:hierarchy":[
        "tgn:2554257",
        "tgn:1000001",
        "tgn:2000304",
        "tgn:7012149",
        "tgn:7007248",
        "tgn:7029392"
    ],
    "tgn:id":2554257,
    "tgn:name":"Oak Suck",
    "tgn:placetype":[
        "aat:300008905"
    ]
},
  "bbox": [],
  "geometry": {"coordinates":[-82.0167,31.2667],"type":"Point"}
}