{
  "id": 7418203,
  "type": "Feature",
  "properties": {
    "tgn:hierarchy":[
        "tgn:7418203",
        "tgn:7005584",
        "tgn:1000001",
        "tgn:7005560",
        "tgn:7029392"
    ],
    "tgn:id":7418203,
    "tgn:name":"Ca\u00f1ada El Sauz",
    "tgn:placetype":[
        "aat:300008347"
    ]
},
  "bbox": [],
  "geometry": {"coordinates":[-101.120833,21.033611],"type":"Point"}
}