<<<<<<< HEAD
{
  "id": 7375192,
  "type": "Feature",
  "properties": {
    "tgn:hierarchy":[
        "tgn:7375192",
        "tgn:7005581",
        "tgn:1000001",
        "tgn:7005560",
        "tgn:7029392"
    ],
    "tgn:id":7375192,
    "tgn:name":"Rancho Las Delicias",
    "tgn:placetype":[
        "aat:300000241"
    ]
},
  "bbox": [],
  "geometry": {"coordinates":[-105.7,26.75],"type":"Point"}
}
=======
{"geometry":{"type":"Point","coordinates":[-105.700000,26.750000]},"type":"Feature","properties":{"hierarchy":["tgn:7375192","tgn:7005581","tgn:1000001","tgn:7005560","tgn:7029392"],"placetype":["aat:300000241"],"id":7375192,"name:xx":"Rancho Las Delicias"}}
>>>>>>> 03f74aca74312dbeaf24d7e61306dd6a786dc3d0
