{
  "id": 7272838,
  "type": "Feature",
  "properties": {
    "tgn:hierarchy":[
        "tgn:7272838",
        "tgn:1000003",
        "tgn:7003622",
        "tgn:7016845",
        "tgn:7029392"
    ],
    "tgn:id":7272838,
    "tgn:name:nl":"Vossenheuvel",
    "tgn:placetype":[
        "aat:300008777"
    ]
},
  "bbox": [],
  "geometry": {"coordinates":[5.916667,51.433333],"type":"Point"}
}