{
  "id": 2382748,
  "type": "Feature",
  "properties": {
    "tgn:hierarchy":[
        "tgn:2382748",
        "tgn:1002158",
        "tgn:1000001",
        "tgn:7012149",
        "tgn:7007523",
        "tgn:7029392"
    ],
    "tgn:id":2382748,
    "tgn:name":"Hazel Creek",
    "tgn:placetype":[
        "aat:300008706"
    ]
},
  "bbox": [],
  "geometry": {"coordinates":[-91.8167,39.2167],"type":"Point"}
}