{
  "id": 7478358,
  "type": "Feature",
  "properties": {
    "tgn:hierarchy":[
        "tgn:7478358",
        "tgn:1000004",
        "tgn:7467799",
        "tgn:1000141",
        "tgn:7029392"
    ],
    "tgn:id":7478358,
    "tgn:name":"Dapeng Shan",
    "tgn:placetype":[
        "aat:300008777"
    ]
},
  "bbox": [],
  "geometry": {"coordinates":[120.6138,23.832],"type":"Point"}
}