<<<<<<< HEAD
{
  "id": 7478358,
  "type": "Feature",
  "properties": {
    "tgn:hierarchy":[
        "tgn:7478358",
        "tgn:1000004",
        "tgn:7467799",
        "tgn:1000141",
        "tgn:7029392"
    ],
    "tgn:id":7478358,
    "tgn:name":"Dapeng Shan",
    "tgn:placetype":[
        "aat:300008777"
    ]
},
  "bbox": [],
  "geometry": {"coordinates":[120.6138,23.832],"type":"Point"}
}
=======
{"geometry":{"type":"Point","coordinates":[120.613800,23.832000]},"type":"Feature","properties":{"hierarchy":["tgn:7478358","tgn:1000004","tgn:7467799","tgn:1000141","tgn:7029392"],"placetype":["aat:300008777"],"id":7478358,"name:xx":"Dapeng Shan"}}
>>>>>>> 03f74aca74312dbeaf24d7e61306dd6a786dc3d0
