{
  "id": 7217072,
  "type": "Feature",
  "properties": {
    "tgn:hierarchy":[
        "tgn:7217072",
        "tgn:7002725",
        "tgn:7002715",
        "tgn:1000003",
        "tgn:1000074",
        "tgn:7029392"
    ],
    "tgn:id":7217072,
    "tgn:name":"Zevgolati\u00f3n",
    "tgn:placetype":[
        "aat:300008347"
    ]
},
  "bbox": [],
  "geometry": {"coordinates":[23.283333,41.083333],"type":"Point"}
}