{
  "id": 7136788,
  "type": "Feature",
  "properties": {
    "tgn:hierarchy":[
        "tgn:7136788",
        "tgn:1000003",
        "tgn:7003682",
        "tgn:7000084",
        "tgn:7029392"
    ],
    "tgn:id":7136788,
    "tgn:name":"Langenbach",
    "tgn:placetype":[
        "aat:300008347"
    ]
},
  "bbox": [],
  "geometry": {"coordinates":[7.733333,50.75],"type":"Point"}
}