{
  "id": 7535944,
  "type": "Feature",
  "properties": {
    "tgn:hierarchy":[
        "tgn:7535944",
        "tgn:7001242",
        "tgn:7016833",
        "tgn:7001336",
        "tgn:7029392"
    ],
    "tgn:id":7535944,
    "tgn:name:en":"Imlay\u1e29, Jabal",
    "tgn:placetype":[
        "aat:300008795"
    ]
},
  "bbox": [],
  "geometry": {"coordinates":[33.704955,28.893087],"type":"Point"}
}