{
  "id": 2309017,
  "type": "Feature",
  "properties": {
    "tgn:hierarchy":[
        "tgn:2309017",
        "tgn:1000001",
        "tgn:7012149",
        "tgn:2000354",
        "tgn:7007248",
        "tgn:7029392"
    ],
    "tgn:id":2309017,
    "tgn:name":"East River",
    "tgn:placetype":[
        "aat:300008707"
    ]
},
  "bbox": [],
  "geometry": {"coordinates":[-81.5167,31.15],"type":"Point"}
}