<<<<<<< HEAD
{
  "id": 2333450,
  "type": "Feature",
  "properties": {
    "tgn:hierarchy":[
        "tgn:2333450",
        "tgn:1000001",
        "tgn:2000310",
        "tgn:7012149",
        "tgn:7007248",
        "tgn:7029392"
    ],
    "tgn:id":2333450,
    "tgn:name":"Folks",
    "tgn:placetype":[
        "aat:300008347"
    ]
},
  "bbox": [],
  "geometry": {"coordinates":[-84.6,31.6167],"type":"Point"}
}
=======
{"geometry":{"type":"Point","coordinates":[-84.600000,31.616700]},"type":"Feature","properties":{"hierarchy":["tgn:2333450","tgn:1000001","tgn:2000310","tgn:7012149","tgn:7007248","tgn:7029392"],"placetype":["aat:300008347"],"id":2333450,"name:xx":"Folks"}}
>>>>>>> 03f74aca74312dbeaf24d7e61306dd6a786dc3d0
