{
  "id": 7534638,
  "type": "Feature",
  "properties": {
    "tgn:hierarchy":[
        "tgn:7534638",
        "tgn:7001242",
        "tgn:7001311",
        "tgn:7016833",
        "tgn:7029392"
    ],
    "tgn:id":7534638,
    "tgn:name:en":"Jund\u012b, W\u0101d\u012b al",
    "tgn:placetype":[
        "aat:300379998"
    ]
},
  "bbox": [],
  "geometry": {"coordinates":[33.873962,25.313711],"type":"Point"}
}