{
  "id": 2324583,
  "type": "Feature",
  "properties": {
    "tgn:hierarchy":[
        "tgn:2324583",
        "tgn:1000001",
        "tgn:7012149",
        "tgn:7007157",
        "tgn:1002957",
        "tgn:7029392"
    ],
    "tgn:id":2324583,
    "tgn:name":"Femmons",
    "tgn:placetype":[
        "aat:300008347"
    ]
},
  "bbox": [],
  "geometry": {"coordinates":[-120.0167,37.9333],"type":"Point"}
}