{
  "id": 7218860,
  "type": "Feature",
  "properties": {
    "tgn:hierarchy":[
        "tgn:7218860",
        "tgn:7011330",
        "tgn:7002674",
        "tgn:1000003",
        "tgn:1000074",
        "tgn:7029392"
    ],
    "tgn:id":7218860,
    "tgn:name":"M\u00e9sos Adelf\u00f3s, Vrachonis\u00edda",
    "tgn:placetype":[
        "aat:300008791"
    ]
},
  "bbox": [],
  "geometry": {"coordinates":[26.597778,36.418611],"type":"Point"}
}