{
  "id": 7511681,
  "type": "Feature",
  "properties": {
    "tgn:hierarchy":[
        "tgn:7511681",
        "tgn:1009227",
        "tgn:1000226",
        "tgn:7016822",
        "tgn:1000006",
        "tgn:7029392"
    ],
    "tgn:id":7511681,
    "tgn:name:en":"Loch Burn",
    "tgn:placetype":[
        "aat:300008699"
    ]
},
  "bbox": [],
  "geometry": {"coordinates":[167.633333,-45.15],"type":"Point"}
}