{
  "id": 7453824,
  "type": "Feature",
  "properties": {
    "tgn:hierarchy":[
        "tgn:7453824",
        "tgn:7002444",
        "tgn:1000003",
        "tgn:7008082",
        "tgn:7008591",
        "tgn:7029392"
    ],
    "tgn:id":7453824,
    "tgn:name:en":"Bynac, Ben",
    "tgn:placetype":[
        "aat:300008795"
    ]
},
  "bbox": [],
  "geometry": {"coordinates":[-3.583333,57.133333],"type":"Point"}
}