{
  "id": 2037659,
  "type": "Feature",
  "properties": {
    "tgn:hierarchy":[
        "tgn:2037659",
        "tgn:1000001",
        "tgn:2000772",
        "tgn:7012149",
        "tgn:7007255",
        "tgn:7029392"
    ],
    "tgn:id":2037659,
    "tgn:name":"Beech",
    "tgn:placetype":[
        "aat:300008347",
        "aat:300387210"
    ]
},
  "bbox": [],
  "geometry": {"coordinates":[-83.4167,37.3667],"type":"Point"}
}