{
  "id": 2720369,
  "type": "Feature",
  "properties": {
    "tgn:hierarchy":[
        "tgn:2720369",
        "tgn:1000001",
        "tgn:7012149",
        "tgn:1003020",
        "tgn:7007920",
        "tgn:7029392"
    ],
    "tgn:id":2720369,
    "tgn:name":"Thunder Arm",
    "tgn:placetype":[
        "aat:300132316"
    ]
},
  "bbox": [],
  "geometry": {"coordinates":[-121.0833,48.6833],"type":"Point"}
}