<<<<<<< HEAD
{
  "id": 2257373,
  "type": "Feature",
  "properties": {
    "tgn:hierarchy":[
        "tgn:2257373",
        "tgn:7013349",
        "tgn:1000001",
        "tgn:7012149",
        "tgn:7007708",
        "tgn:7029392"
    ],
    "tgn:id":2257373,
    "tgn:name":"Cornucopia Mines",
    "tgn:placetype":[
        "aat:300000390"
    ]
},
  "bbox": [],
  "geometry": {"coordinates":[-117.2,45.0],"type":"Point"}
}
=======
{"geometry":{"type":"Point","coordinates":[-117.200000,45.000000]},"type":"Feature","properties":{"hierarchy":["tgn:2257373","tgn:7013349","tgn:1000001","tgn:7012149","tgn:7007708","tgn:7029392"],"placetype":["aat:300000390"],"id":2257373,"name:xx":"Cornucopia Mines"}}
>>>>>>> 03f74aca74312dbeaf24d7e61306dd6a786dc3d0
