{
  "id": 2344437,
  "type": "Feature",
  "properties": {
    "tgn:hierarchy":[
        "tgn:2344437",
        "tgn:1000001",
        "tgn:2001747",
        "tgn:7012149",
        "tgn:7007712",
        "tgn:7029392"
    ],
    "tgn:id":2344437,
    "tgn:name":"Gap Creek",
    "tgn:placetype":[
        "aat:300008706"
    ]
},
  "bbox": [],
  "geometry": {"coordinates":[-82.45,35.1667],"type":"Point"}
}