{
  "id": 2462895,
  "type": "Feature",
  "properties": {
    "tgn:hierarchy":[
        "tgn:2462895",
        "tgn:1000001",
        "tgn:7012149",
        "tgn:7007517",
        "tgn:7029392"
    ],
    "tgn:id":2462895,
    "tgn:name":"Littleville Lake",
    "tgn:placetype":[
        "aat:300006191"
    ]
},
  "bbox": [],
  "geometry": {"coordinates":[-72.8667,42.25],"type":"Point"}
}