{
  "id": 7086157,
  "type": "Feature",
  "properties": {
    "tgn:hierarchy":[
        "tgn:7086157",
        "tgn:7003669",
        "tgn:1000003",
        "tgn:7000084",
        "tgn:7029392"
    ],
    "tgn:id":7086157,
    "tgn:name":"Weidenhart",
    "tgn:placetype":[
        "aat:300008863"
    ]
},
  "bbox": [],
  "geometry": {"coordinates":[10.783333,48.316667],"type":"Point"}
}