{
  "id": 7005325,
  "type": "Feature",
  "properties": {
    "tgn:hierarchy":[
        "tgn:7005325",
        "tgn:1010367",
        "tgn:1000001",
        "tgn:7004630",
        "tgn:7029392"
    ],
    "tgn:id":7005325,
    "tgn:name":"Grand Turk",
    "tgn:placetype":[
        "aat:300008791"
    ]
},
  "bbox": [],
  "geometry": {"coordinates":[-71.1167,21.4833],"type":"Point"}
}