{
  "id": 7507475,
  "type": "Feature",
  "properties": {
    "tgn:hierarchy":[
        "tgn:7507475",
        "tgn:1009227",
        "tgn:1000226",
        "tgn:7018437",
        "tgn:1000006",
        "tgn:7029392"
    ],
    "tgn:id":7507475,
    "tgn:name:en":"Pudding Hill",
    "tgn:placetype":[
        "aat:300008795"
    ]
},
  "bbox": [],
  "geometry": {"coordinates":[170.833333,-44.75],"type":"Point"}
}