{
  "id": 7184294,
  "type": "Feature",
  "properties": {
    "tgn:hierarchy":[
        "tgn:7184294",
        "tgn:1000003",
        "tgn:7003685",
        "tgn:7000084",
        "tgn:7029392"
    ],
    "tgn:id":7184294,
    "tgn:name":"G\u00f6bschelwitz",
    "tgn:placetype":[
        "aat:300008347"
    ]
},
  "bbox": [],
  "geometry": {"coordinates":[12.416667,51.416667],"type":"Point"}
}