{
  "id": 7146603,
  "type": "Feature",
  "properties": {
    "tgn:hierarchy":[
        "tgn:7146603",
        "tgn:7003692",
        "tgn:1000003",
        "tgn:7000084",
        "tgn:7029392"
    ],
    "tgn:id":7146603,
    "tgn:name":"Kopfenhof",
    "tgn:placetype":[
        "aat:300000206"
    ]
},
  "bbox": [],
  "geometry": {"coordinates":[8.733333,48.25],"type":"Point"}
}