{
  "id": 7004533,
  "type": "Feature",
  "properties": {
    "tgn:hierarchy":[
        "tgn:7004533",
        "tgn:7003013",
        "tgn:7003005",
        "tgn:1000003",
        "tgn:7004474",
        "tgn:1000080",
        "tgn:7029392"
    ],
    "tgn:id":7004533,
    "tgn:name":"Ponticelli",
    "tgn:placetype":[
        "aat:300008347",
        "aat:300387336"
    ]
},
  "bbox": [],
  "geometry": {"coordinates":[14.3333,40.85],"type":"Point"}
}