{
  "id": 2084199,
  "type": "Feature",
  "properties": {
    "tgn:hierarchy":[
        "tgn:2084199",
        "tgn:1000001",
        "tgn:7012149",
        "tgn:2001677",
        "tgn:7007707",
        "tgn:7029392"
    ],
    "tgn:id":2084199,
    "tgn:name":"The Village",
    "tgn:placetype":[
        "aat:300008347"
    ]
},
  "bbox": [],
  "geometry": {"coordinates":[-97.55,35.55],"type":"Point"}
}