{
  "id": 2664998,
  "type": "Feature",
  "properties": {
    "tgn:hierarchy":[
        "tgn:2664998",
        "tgn:1000001",
        "tgn:2002369",
        "tgn:7012149",
        "tgn:7007923",
        "tgn:7029392"
    ],
    "tgn:id":2664998,
    "tgn:name":"Simpson Draw",
    "tgn:placetype":[
        "aat:300008761"
    ]
},
  "bbox": [],
  "geometry": {"coordinates":[-105.2333,42.85],"type":"Point"}
}