{
  "id": 7465495,
  "type": "Feature",
  "properties": {
    "tgn:hierarchy":[
        "tgn:7465495",
        "tgn:7002443",
        "tgn:1000003",
        "tgn:7029493",
        "tgn:7008591",
        "tgn:7029392"
    ],
    "tgn:id":7465495,
    "tgn:name:en":"Bont Newydd",
    "tgn:placetype":[
        "aat:300007783"
    ]
},
  "bbox": [],
  "geometry": {"coordinates":[-3.833333,52.75],"type":"Point"}
}