{
  "id": 1128785,
  "type": "Feature",
  "properties": {
    "tgn:hierarchy":[
        "tgn:1128785",
        "tgn:1000001",
        "tgn:7012149",
        "tgn:7029392"
    ],
    "tgn:id":1128785,
    "tgn:name":"Poteau",
    "tgn:placetype":[
        "aat:300008707"
    ]
},
  "bbox": [],
  "geometry": {"coordinates":[-94.4333,35.3833],"type":"Point"}
}