<<<<<<< HEAD
{
  "id": 7361181,
  "type": "Feature",
  "properties": {
    "tgn:hierarchy":[
        "tgn:7361181",
        "tgn:7005580",
        "tgn:1000001",
        "tgn:7005560",
        "tgn:7029392"
    ],
    "tgn:id":7361181,
    "tgn:name":"El Ocote",
    "tgn:placetype":[
        "aat:300008347"
    ]
},
  "bbox": [],
  "geometry": {"coordinates":[-93.35,16.883333],"type":"Point"}
}
=======
{"geometry":{"type":"Point","coordinates":[-93.350000,16.883333]},"type":"Feature","properties":{"hierarchy":["tgn:7361181","tgn:7005580","tgn:1000001","tgn:7005560","tgn:7029392"],"placetype":["aat:300008347"],"id":7361181,"name:xx":"El Ocote"}}
>>>>>>> 03f74aca74312dbeaf24d7e61306dd6a786dc3d0
