{
  "id": 2621566,
  "type": "Feature",
  "properties": {
    "tgn:hierarchy":[
        "tgn:2621566",
        "tgn:1000001",
        "tgn:7012149",
        "tgn:1002384",
        "tgn:7007523",
        "tgn:7029392"
    ],
    "tgn:id":2621566,
    "tgn:name":"Roaring Spring",
    "tgn:placetype":[
        "aat:300008697"
    ]
},
  "bbox": [],
  "geometry": {"coordinates":[-91.0667,38.2667],"type":"Point"}
}