{
  "id": 7466922,
  "type": "Feature",
  "properties": {
    "tgn:hierarchy":[
        "tgn:7466922",
        "tgn:7008695",
        "tgn:7002448",
        "tgn:1000003",
        "tgn:7008591",
        "tgn:7029392"
    ],
    "tgn:id":7466922,
    "tgn:name:en":"British",
    "tgn:placetype":[
        "aat:300008347"
    ]
},
  "bbox": [],
  "geometry": {"coordinates":[-6.216667,54.65],"type":"Point"}
}