<<<<<<< HEAD
{
  "id": 2252158,
  "type": "Feature",
  "properties": {
    "tgn:hierarchy":[
        "tgn:2252158",
        "tgn:7006450",
        "tgn:1000001",
        "tgn:7012149",
        "tgn:2000082",
        "tgn:7029392"
    ],
    "tgn:id":2252158,
    "tgn:name":"Cone Peak",
    "tgn:placetype":[
        "aat:300008798"
    ]
},
  "bbox": [],
  "geometry": {"coordinates":[-133.6333,55.7833],"type":"Point"}
}
=======
{"geometry":{"type":"Point","coordinates":[-133.633300,55.783300]},"type":"Feature","properties":{"hierarchy":["tgn:2252158","tgn:7006450","tgn:1000001","tgn:7012149","tgn:2000082","tgn:7029392"],"placetype":["aat:300008798"],"id":2252158,"name:xx":"Cone Peak"}}
>>>>>>> 03f74aca74312dbeaf24d7e61306dd6a786dc3d0
