{
  "id": 1108649,
  "type": "Feature",
  "properties": {
    "tgn:hierarchy":[
        "tgn:1108649",
        "tgn:7001242",
        "tgn:7001311",
        "tgn:7016833",
        "tgn:7029392"
    ],
    "tgn:id":1108649,
    "tgn:name":"Jabal 'At\u0101qah",
    "tgn:placetype":[
        "aat:300008795"
    ]
},
  "bbox": [],
  "geometry": {"coordinates":[32.369444,29.972222],"type":"Point"}
}