{
  "id": 2687200,
  "type": "Feature",
  "properties": {
    "tgn:hierarchy":[
        "tgn:2687200",
        "tgn:1000001",
        "tgn:7012149",
        "tgn:2002120",
        "tgn:7007827",
        "tgn:7029392"
    ],
    "tgn:id":2687200,
    "tgn:name":"Spring Hollow",
    "tgn:placetype":[
        "aat:300008761"
    ]
},
  "bbox": [],
  "geometry": {"coordinates":[-111.5167,39.5833],"type":"Point"}
}