{
  "id": 2785152,
  "type": "Feature",
  "properties": {
    "tgn:hierarchy":[
        "tgn:2785152",
        "tgn:1000001",
        "tgn:7012149",
        "tgn:1002789",
        "tgn:7007710",
        "tgn:7029392"
    ],
    "tgn:id":2785152,
    "tgn:name":"Yellow Pine Ridge",
    "tgn:placetype":[
        "aat:300266640"
    ]
},
  "bbox": [],
  "geometry": {"coordinates":[-74.9167,41.3167],"type":"Point"}
}