{
  "id": 7103545,
  "type": "Feature",
  "properties": {
    "tgn:hierarchy":[
        "tgn:7103545",
        "tgn:7003669",
        "tgn:1000003",
        "tgn:7000084",
        "tgn:7029392"
    ],
    "tgn:id":7103545,
    "tgn:name":"Ruckasing",
    "tgn:placetype":[
        "aat:300008347"
    ]
},
  "bbox": [],
  "geometry": {"coordinates":[13.033333,48.716667],"type":"Point"}
}