{
  "id": 7568459,
  "type": "Feature",
  "properties": {
    "tgn:hierarchy":[
        "tgn:7568459",
        "tgn:1000004",
        "tgn:7000198",
        "tgn:7016788",
        "tgn:7029392"
    ],
    "tgn:id":7568459,
    "tgn:name:en":"Baladesar",
    "tgn:placetype":[
        "aat:300008347"
    ]
},
  "bbox": [],
  "geometry": {"coordinates":[73.764759,28.827159],"type":"Point"}
}