{
  "id": 2578796,
  "type": "Feature",
  "properties": {
    "tgn:hierarchy":[
        "tgn:2578796",
        "tgn:1000001",
        "tgn:7012149",
        "tgn:2000826",
        "tgn:7007255",
        "tgn:7029392"
    ],
    "tgn:id":2578796,
    "tgn:name":"Phillips Hollow",
    "tgn:placetype":[
        "aat:300008761"
    ]
},
  "bbox": [],
  "geometry": {"coordinates":[-83.7333,37.95],"type":"Point"}
}