{
  "id": 7340170,
  "type": "Feature",
  "properties": {
    "tgn:hierarchy":[
        "tgn:7340170",
        "tgn:7002811",
        "tgn:1000003",
        "tgn:7003837",
        "tgn:1000095",
        "tgn:7029392"
    ],
    "tgn:id":7340170,
    "tgn:name":"Culebra, Portillo del",
    "tgn:placetype":[
        "aat:300259572"
    ]
},
  "bbox": [],
  "geometry": {"coordinates":[-6.166667,40.316667],"type":"Point"}
}