<<<<<<< HEAD
{
  "id": 2762511,
  "type": "Feature",
  "properties": {
    "tgn:hierarchy":[
        "tgn:2762511",
        "tgn:1000001",
        "tgn:7012149",
        "tgn:2002010",
        "tgn:7007826",
        "tgn:7029392"
    ],
    "tgn:id":2762511,
    "tgn:name":"West Well Canyon",
    "tgn:placetype":[
        "aat:300008761"
    ]
},
  "bbox": [],
  "geometry": {"coordinates":[-104.7,30.6],"type":"Point"}
}
=======
{"geometry":{"type":"Point","coordinates":[-104.700000,30.600000]},"type":"Feature","properties":{"hierarchy":["tgn:2762511","tgn:1000001","tgn:7012149","tgn:2002010","tgn:7007826","tgn:7029392"],"placetype":["aat:300008761"],"id":2762511,"name:xx":"West Well Canyon"}}
>>>>>>> 03f74aca74312dbeaf24d7e61306dd6a786dc3d0
