<<<<<<< HEAD
{
  "id": 2333922,
  "type": "Feature",
  "properties": {
    "tgn:hierarchy":[
        "tgn:2333922",
        "tgn:1000001",
        "tgn:7012149",
        "tgn:2001850",
        "tgn:7007825",
        "tgn:7029392"
    ],
    "tgn:id":2333922,
    "tgn:name":"Ford Cave",
    "tgn:placetype":[
        "aat:300008746"
    ]
},
  "bbox": [],
  "geometry": {"coordinates":[-85.3,36.55],"type":"Point"}
}
=======
{"geometry":{"type":"Point","coordinates":[-85.300000,36.550000]},"type":"Feature","properties":{"hierarchy":["tgn:2333922","tgn:1000001","tgn:7012149","tgn:2001850","tgn:7007825","tgn:7029392"],"placetype":["aat:300008746"],"id":2333922,"name:xx":"Ford Cave"}}
>>>>>>> 03f74aca74312dbeaf24d7e61306dd6a786dc3d0
