{
  "id": 7374203,
  "type": "Feature",
  "properties": {
    "tgn:hierarchy":[
        "tgn:7374203",
        "tgn:1001835",
        "tgn:1000001",
        "tgn:7005560",
        "tgn:7029392"
    ],
    "tgn:id":7374203,
    "tgn:name":"Estaci\u00f3n Laguna",
    "tgn:placetype":[
        "aat:300007783"
    ]
},
  "bbox": [],
  "geometry": {"coordinates":[-115.233333,32.416667],"type":"Point"}
}