{
  "id": 2756890,
  "type": "Feature",
  "properties": {
    "tgn:hierarchy":[
        "tgn:2756890",
        "tgn:1000001",
        "tgn:2001426",
        "tgn:7012149",
        "tgn:7007564",
        "tgn:7029392"
    ],
    "tgn:id":2756890,
    "tgn:name":"Welshs Corner",
    "tgn:placetype":[
        "aat:300008347"
    ]
},
  "bbox": [],
  "geometry": {"coordinates":[-71.1167,43.3333],"type":"Point"}
}