{
  "id": 2539275,
  "type": "Feature",
  "properties": {
    "tgn:hierarchy":[
        "tgn:2539275",
        "tgn:2001732",
        "tgn:1000001",
        "tgn:7012149",
        "tgn:7007712",
        "tgn:7029392"
    ],
    "tgn:id":2539275,
    "tgn:name":"New Hope",
    "tgn:placetype":[
        "aat:300008347"
    ]
},
  "bbox": [],
  "geometry": {"coordinates":[-79.8167,33.0833],"type":"Point"}
}