<<<<<<< HEAD
{
  "id": 7477481,
  "type": "Feature",
  "properties": {
    "tgn:hierarchy":[
        "tgn:7477481",
        "tgn:7488858",
        "tgn:1000004",
        "tgn:1000141",
        "tgn:7029392"
    ],
    "tgn:id":7477481,
    "tgn:name":"Riyuetan Suidao",
    "tgn:placetype":[
        "aat:300007899"
    ]
},
  "bbox": [],
  "geometry": {"coordinates":[120.902324,23.844231],"type":"Point"}
}
=======
{"geometry":{"type":"Point","coordinates":[120.902324,23.844231]},"type":"Feature","properties":{"hierarchy":["tgn:7477481","tgn:7488858","tgn:1000004","tgn:1000141","tgn:7029392"],"placetype":["aat:300007899"],"id":7477481,"name:xx":"Riyuetan Suidao"}}
>>>>>>> 03f74aca74312dbeaf24d7e61306dd6a786dc3d0
