{
  "id": 2308636,
  "type": "Feature",
  "properties": {
    "tgn:hierarchy":[
        "tgn:2308636",
        "tgn:1000001",
        "tgn:7012149",
        "tgn:2002383",
        "tgn:7007923",
        "tgn:7029392"
    ],
    "tgn:id":2308636,
    "tgn:name":"East Otterson Wash",
    "tgn:placetype":[
        "aat:300008761"
    ]
},
  "bbox": [],
  "geometry": {"coordinates":[-109.5833,41.8167],"type":"Point"}
}