{
  "id": 2325267,
  "type": "Feature",
  "properties": {
    "tgn:hierarchy":[
        "tgn:2325267",
        "tgn:7013388",
        "tgn:1000001",
        "tgn:7012149",
        "tgn:7007517",
        "tgn:7029392"
    ],
    "tgn:id":2325267,
    "tgn:name":"Fernwood Reservoir",
    "tgn:placetype":[
        "aat:300006191"
    ]
},
  "bbox": [],
  "geometry": {"coordinates":[-73.1333,42.4333],"type":"Point"}
}