{
  "id": 7115957,
  "type": "Feature",
  "properties": {
    "tgn:hierarchy":[
        "tgn:7115957",
        "tgn:1000003",
        "tgn:7003677",
        "tgn:7000084",
        "tgn:7029392"
    ],
    "tgn:id":7115957,
    "tgn:name":"Ostendorf",
    "tgn:placetype":[
        "aat:300000206"
    ]
},
  "bbox": [],
  "geometry": {"coordinates":[6.983333,51.983333],"type":"Point"}
}