{
  "id": 2477701,
  "type": "Feature",
  "properties": {
    "tgn:hierarchy":[
        "tgn:2477701",
        "tgn:1000001",
        "tgn:7012149",
        "tgn:1002423",
        "tgn:7007568",
        "tgn:7029392"
    ],
    "tgn:id":2477701,
    "tgn:name":"Maben Hill",
    "tgn:placetype":[
        "aat:300008798"
    ]
},
  "bbox": [],
  "geometry": {"coordinates":[-74.3833,42.2667],"type":"Point"}
}