{
  "id": 1114516,
  "type": "Feature",
  "properties": {
    "tgn:hierarchy":[
        "tgn:1114516",
        "tgn:1000004",
        "tgn:1000138",
        "tgn:7000381",
        "tgn:7029392"
    ],
    "tgn:id":1114516,
    "tgn:name":"Serangoon Harbour",
    "tgn:placetype":[
        "aat:300008678"
    ]
},
  "bbox": [],
  "geometry": {"coordinates":[103.95,1.3833],"type":"Point"}
}