{
  "id": 7417396,
  "type": "Feature",
  "properties": {
    "tgn:hierarchy":[
        "tgn:7417396",
        "tgn:7005584",
        "tgn:1000001",
        "tgn:7005560",
        "tgn:7029392"
    ],
    "tgn:id":7417396,
    "tgn:name":"El Chayotal",
    "tgn:placetype":[
        "aat:300008347"
    ]
},
  "bbox": [],
  "geometry": {"coordinates":[-101.0625,20.666944],"type":"Point"}
}