{
  "id": 1032281,
  "type": "Feature",
  "properties": {
    "tgn:hierarchy":[
        "tgn:1032281",
        "tgn:1000003",
        "tgn:7002890",
        "tgn:1000070",
        "tgn:7029392"
    ],
    "tgn:id":1032281,
    "tgn:name":"Bouttencourt",
    "tgn:placetype":[
        "aat:300008347"
    ]
},
  "bbox": [],
  "geometry": {"coordinates":[1.6333,49.9333],"type":"Point"}
}