{
  "id": 2165660,
  "type": "Feature",
  "properties": {
    "tgn:hierarchy":[
        "tgn:2165660",
        "tgn:1000001",
        "tgn:1002270",
        "tgn:7012149",
        "tgn:7007708",
        "tgn:7029392"
    ],
    "tgn:id":2165660,
    "tgn:name":"Beyers Lake",
    "tgn:placetype":[
        "aat:300008680"
    ]
},
  "bbox": [],
  "geometry": {"coordinates":[-122.55,45.0333],"type":"Point"}
}