{
  "id": 7358628,
  "type": "Feature",
  "properties": {
    "tgn:hierarchy":[
        "tgn:7358628",
        "tgn:7005585",
        "tgn:1000001",
        "tgn:7005560",
        "tgn:7029392"
    ],
    "tgn:id":7358628,
    "tgn:name":"Coyuxtlahuac",
    "tgn:placetype":[
        "aat:300008347"
    ]
},
  "bbox": [],
  "geometry": {"coordinates":[-98.45,17.116667],"type":"Point"}
}