{
  "id": 1012499,
  "type": "Feature",
  "properties": {
    "tgn:hierarchy":[
        "tgn:1012499",
        "tgn:7005332",
        "tgn:7593498",
        "tgn:1000001",
        "tgn:7029392"
    ],
    "tgn:id":1012499,
    "tgn:name":"South Point",
    "tgn:placetype":[
        "aat:300386846"
    ]
},
  "bbox": [],
  "geometry": {"coordinates":[-74.8833,22.85],"type":"Point"}
}