{
  "id": 2247793,
  "type": "Feature",
  "properties": {
    "tgn:hierarchy":[
        "tgn:2247793",
        "tgn:7002659",
        "tgn:1000001",
        "tgn:7012149",
        "tgn:7029392"
    ],
    "tgn:id":2247793,
    "tgn:name":"Cohobadiah Creek",
    "tgn:placetype":[
        "aat:300008706"
    ]
},
  "bbox": [],
  "geometry": {"coordinates":[-85.4833,33.4833],"type":"Point"}
}