{
  "id": 7459486,
  "type": "Feature",
  "properties": {
    "tgn:hierarchy":[
        "tgn:7459486",
        "tgn:7002445",
        "tgn:1000003",
        "tgn:7011430",
        "tgn:7008591",
        "tgn:7029392"
    ],
    "tgn:id":7459486,
    "tgn:name:en":"Needles Point",
    "tgn:placetype":[
        "aat:300386846"
    ]
},
  "bbox": [],
  "geometry": {"coordinates":[-1.583333,50.666667],"type":"Point"}
}