{
  "id": 1017291,
  "type": "Feature",
  "properties": {
    "tgn:hierarchy":[
        "tgn:1017291",
        "tgn:1000001",
        "tgn:7005595",
        "tgn:7005560",
        "tgn:7029392"
    ],
    "tgn:id":1017291,
    "tgn:name":"Corerepe",
    "tgn:placetype":[
        "aat:300008347"
    ]
},
  "bbox": [],
  "geometry": {"coordinates":[-108.716667,25.633333],"type":"Point"}
}