{
  "id": 1027976,
  "type": "Feature",
  "properties": {
    "tgn:hierarchy":[
        "tgn:1027976",
        "tgn:7594008",
        "tgn:1000003",
        "tgn:1000066",
        "tgn:7029392"
    ],
    "tgn:id":1027976,
    "tgn:name":"Kragen\u00e6s",
    "tgn:placetype":[
        "aat:300008347"
    ]
},
  "bbox": [],
  "geometry": {"coordinates":[11.3667,54.9167],"type":"Point"}
}