{
  "id": 7112260,
  "type": "Feature",
  "properties": {
    "tgn:hierarchy":[
        "tgn:7112260",
        "tgn:7003692",
        "tgn:1000003",
        "tgn:7000084",
        "tgn:7029392"
    ],
    "tgn:id":7112260,
    "tgn:name":"Rohrbach",
    "tgn:placetype":[
        "aat:300000206"
    ]
},
  "bbox": [],
  "geometry": {"coordinates":[8.033333,48.516667],"type":"Point"}
}