{
  "id": 2049228,
  "type": "Feature",
  "properties": {
    "tgn:hierarchy":[
        "tgn:2049228",
        "tgn:1000001",
        "tgn:1003023",
        "tgn:7012149",
        "tgn:7007516",
        "tgn:7029392"
    ],
    "tgn:id":2049228,
    "tgn:name":"Willards",
    "tgn:placetype":[
        "aat:300008347"
    ]
},
  "bbox": [],
  "geometry": {"coordinates":[-75.3333,38.3833],"type":"Point"}
}