{
  "id": 7152625,
  "type": "Feature",
  "properties": {
    "tgn:hierarchy":[
        "tgn:7152625",
        "tgn:1000003",
        "tgn:7003685",
        "tgn:7000084",
        "tgn:7029392"
    ],
    "tgn:id":7152625,
    "tgn:name":"Jahna",
    "tgn:placetype":[
        "aat:300008347"
    ]
},
  "bbox": [],
  "geometry": {"coordinates":[13.183333,51.216667],"type":"Point"}
}