{
  "id": 7481683,
  "type": "Feature",
  "properties": {
    "tgn:hierarchy":[
        "tgn:7481683",
        "tgn:1000004",
        "tgn:7489179",
        "tgn:1000141",
        "tgn:7029392"
    ],
    "tgn:id":7481683,
    "tgn:name":"Siji Guoxiao Fenxiao",
    "tgn:placetype":[
        "aat:300006495"
    ]
},
  "bbox": [],
  "geometry": {"coordinates":[121.451389,24.532778],"type":"Point"}
}