{
  "id": 2034044,
  "type": "Feature",
  "properties": {
    "tgn:hierarchy":[
        "tgn:2034044",
        "tgn:1000001",
        "tgn:7012149",
        "tgn:1002557",
        "tgn:7007252",
        "tgn:7029392"
    ],
    "tgn:id":2034044,
    "tgn:name":"Warsaw",
    "tgn:placetype":[
        "aat:300008347"
    ]
},
  "bbox": [],
  "geometry": {"coordinates":[-85.85,41.2333],"type":"Point"}
}