{
  "id": 2599603,
  "type": "Feature",
  "properties": {
    "tgn:hierarchy":[
        "tgn:2599603",
        "tgn:1000001",
        "tgn:7012149",
        "tgn:2001844",
        "tgn:7007825",
        "tgn:7029392"
    ],
    "tgn:id":2599603,
    "tgn:name":"Prospect Hill Cave",
    "tgn:placetype":[
        "aat:300008746"
    ]
},
  "bbox": [],
  "geometry": {"coordinates":[-86.0333,35.7833],"type":"Point"}
}