{
  "id": 2430072,
  "type": "Feature",
  "properties": {
    "tgn:hierarchy":[
        "tgn:2430072",
        "tgn:7006450",
        "tgn:1000001",
        "tgn:7012149",
        "tgn:2124005",
        "tgn:7029392"
    ],
    "tgn:id":2430072,
    "tgn:name":"Kagiluak Bight",
    "tgn:placetype":[
        "aat:300132316"
    ]
},
  "bbox": [],
  "geometry": {"coordinates":[-141.25,69.6167],"type":"Point"}
}