{
  "id": 7175408,
  "type": "Feature",
  "properties": {
    "tgn:hierarchy":[
        "tgn:7175408",
        "tgn:1000003",
        "tgn:7003676",
        "tgn:7000084",
        "tgn:7029392"
    ],
    "tgn:id":7175408,
    "tgn:name":"Gro\u00df Feldhus",
    "tgn:placetype":[
        "aat:300000206"
    ]
},
  "bbox": [],
  "geometry": {"coordinates":[8.216667,53.216667],"type":"Point"}
}