{
  "id": 2641233,
  "type": "Feature",
  "properties": {
    "tgn:hierarchy":[
        "tgn:2641233",
        "tgn:1000001",
        "tgn:7012149",
        "tgn:7007157",
        "tgn:1002857",
        "tgn:7029392"
    ],
    "tgn:id":2641233,
    "tgn:name":"Sand Creek",
    "tgn:placetype":[
        "aat:300008706"
    ]
},
  "bbox": [],
  "geometry": {"coordinates":[-116.9333,34.1833],"type":"Point"}
}