{
  "id": 2744903,
  "type": "Feature",
  "properties": {
    "tgn:hierarchy":[
        "tgn:2744903",
        "tgn:1000001",
        "tgn:7012149",
        "tgn:2000888",
        "tgn:7007256",
        "tgn:7029392"
    ],
    "tgn:id":2744903,
    "tgn:name":"Vienna Bend",
    "tgn:placetype":[
        "aat:300008347"
    ]
},
  "bbox": [],
  "geometry": {"coordinates":[-93.0333,31.7167],"type":"Point"}
}