<<<<<<< HEAD
{
  "id": 7172556,
  "type": "Feature",
  "properties": {
    "tgn:hierarchy":[
        "tgn:7172556",
        "tgn:7003692",
        "tgn:1000003",
        "tgn:7000084",
        "tgn:7029392"
    ],
    "tgn:id":7172556,
    "tgn:name":"Herrenberg",
    "tgn:placetype":[
        "aat:300000206"
    ]
},
  "bbox": [],
  "geometry": {"coordinates":[10.1,47.733333],"type":"Point"}
}
=======
{"geometry":{"type":"Point","coordinates":[10.100000,47.733333]},"type":"Feature","properties":{"hierarchy":["tgn:7172556","tgn:7003692","tgn:1000003","tgn:7000084","tgn:7029392"],"placetype":["aat:300000206"],"id":7172556,"name:xx":"Herrenberg"}}
>>>>>>> 03f74aca74312dbeaf24d7e61306dd6a786dc3d0
