{
  "id": 7253220,
  "type": "Feature",
  "properties": {
    "tgn:hierarchy":[
        "tgn:7253220",
        "tgn:7018239",
        "tgn:1000003",
        "tgn:1000063",
        "tgn:7018236",
        "tgn:7029392"
    ],
    "tgn:id":7253220,
    "tgn:name":"Tafelbos",
    "tgn:placetype":[
        "aat:300008863"
    ]
},
  "bbox": [],
  "geometry": {"coordinates":[4.883333,50.883333],"type":"Point"}
}