<<<<<<< HEAD
{
  "id": 7374044,
  "type": "Feature",
  "properties": {
    "tgn:hierarchy":[
        "tgn:7374044",
        "tgn:1000001",
        "tgn:7005597",
        "tgn:7005560",
        "tgn:7029392"
    ],
    "tgn:id":7374044,
    "tgn:name":"La Amistad",
    "tgn:placetype":[
        "aat:300008347"
    ]
},
  "bbox": [],
  "geometry": {"coordinates":[-99.116667,26.5],"type":"Point"}
}
=======
{"geometry":{"type":"Point","coordinates":[-99.116667,26.500000]},"type":"Feature","properties":{"hierarchy":["tgn:7374044","tgn:1000001","tgn:7005597","tgn:7005560","tgn:7029392"],"placetype":["aat:300008347"],"id":7374044,"name:xx":"La Amistad"}}
>>>>>>> 03f74aca74312dbeaf24d7e61306dd6a786dc3d0
