{
  "id": 2734032,
  "type": "Feature",
  "properties": {
    "tgn:hierarchy":[
        "tgn:2734032",
        "tgn:1000001",
        "tgn:7012149",
        "tgn:2001755",
        "tgn:7007712",
        "tgn:7029392"
    ],
    "tgn:id":2734032,
    "tgn:name":"Turners Pond",
    "tgn:placetype":[
        "aat:300006191"
    ]
},
  "bbox": [],
  "geometry": {"coordinates":[-80.1833,34.0167],"type":"Point"}
}