{
  "id": 7073826,
  "type": "Feature",
  "properties": {
    "tgn:hierarchy":[
        "tgn:7073826",
        "tgn:7003692",
        "tgn:1000003",
        "tgn:7000084",
        "tgn:7029392"
    ],
    "tgn:id":7073826,
    "tgn:name":"Haltepunkt Talheim-Vellberg",
    "tgn:placetype":[
        "aat:300007783"
    ]
},
  "bbox": [],
  "geometry": {"coordinates":[9.88,49.100278],"type":"Point"}
}