{
  "id": 7571557,
  "type": "Feature",
  "properties": {
    "tgn:hierarchy":[
        "tgn:7571557",
        "tgn:1000004",
        "tgn:7000198",
        "tgn:7016694",
        "tgn:7029392"
    ],
    "tgn:id":7571557,
    "tgn:name:en":"Go\u0101ldei",
    "tgn:placetype":[
        "aat:300008795"
    ]
},
  "bbox": [],
  "geometry": {"coordinates":[84.833333,20.516667],"type":"Point"}
}