{
  "id": 7339134,
  "type": "Feature",
  "properties": {
    "tgn:hierarchy":[
        "tgn:7339134",
        "tgn:7002824",
        "tgn:1000003",
        "tgn:7002786",
        "tgn:1000095",
        "tgn:7029392"
    ],
    "tgn:id":7339134,
    "tgn:name":"Corcoesto",
    "tgn:placetype":[
        "aat:300008347"
    ]
},
  "bbox": [],
  "geometry": {"coordinates":[-8.833333,43.233333],"type":"Point"}
}