{
  "id": 2692650,
  "type": "Feature",
  "properties": {
    "tgn:hierarchy":[
        "tgn:2692650",
        "tgn:1000001",
        "tgn:7012149",
        "tgn:2001312",
        "tgn:7007524",
        "tgn:7029392"
    ],
    "tgn:id":2692650,
    "tgn:name":"Stebley Reservoir",
    "tgn:placetype":[
        "aat:300006191"
    ]
},
  "bbox": [],
  "geometry": {"coordinates":[-106.7833,47.8167],"type":"Point"}
}