{
  "id": 2683395,
  "type": "Feature",
  "properties": {
    "tgn:hierarchy":[
        "tgn:2683395",
        "tgn:1000001",
        "tgn:7012149",
        "tgn:7016022",
        "tgn:7007251",
        "tgn:7029392"
    ],
    "tgn:id":2683395,
    "tgn:name":"Sparrow Creek",
    "tgn:placetype":[
        "aat:300008706"
    ]
},
  "bbox": [],
  "geometry": {"coordinates":[-90.15,38.4833],"type":"Point"}
}