{
  "id": 7375870,
  "type": "Feature",
  "properties": {
    "tgn:hierarchy":[
        "tgn:7375870",
        "tgn:7005580",
        "tgn:1000001",
        "tgn:7005560",
        "tgn:7029392"
    ],
    "tgn:id":7375870,
    "tgn:name":"La Reforma",
    "tgn:placetype":[
        "aat:300008347"
    ]
},
  "bbox": [],
  "geometry": {"coordinates":[-92.65,15.916667],"type":"Point"}
}