{
  "id": 1101617,
  "type": "Feature",
  "properties": {
    "tgn:hierarchy":[
        "tgn:1101617",
        "tgn:1001187",
        "tgn:7001242",
        "tgn:1000209",
        "tgn:7029392"
    ],
    "tgn:id":1101617,
    "tgn:name":"Kasanka National Park",
    "tgn:placetype":[
        "aat:300008189"
    ]
},
  "bbox": [],
  "geometry": {"coordinates":[30.25,-12.5833],"type":"Point"}
}