{
  "id": 2267270,
  "type": "Feature",
  "properties": {
    "tgn:hierarchy":[
        "tgn:2267270",
        "tgn:1000001",
        "tgn:7012149",
        "tgn:2002282",
        "tgn:7013961",
        "tgn:7029392"
    ],
    "tgn:id":2267270,
    "tgn:name":"Crimson Springs",
    "tgn:placetype":[
        "aat:300008347"
    ]
},
  "bbox": [],
  "geometry": {"coordinates":[-80.4667,37.5167],"type":"Point"}
}