{
  "id": 2263245,
  "type": "Feature",
  "properties": {
    "tgn:hierarchy":[
        "tgn:2263245",
        "tgn:1000001",
        "tgn:7012149",
        "tgn:2002189",
        "tgn:7007919",
        "tgn:7029392"
    ],
    "tgn:id":2263245,
    "tgn:name":"Cox Burial Cave",
    "tgn:placetype":[
        "aat:300008746"
    ]
},
  "bbox": [],
  "geometry": {"coordinates":[-82.5833,36.75],"type":"Point"}
}