{
  "id": 7174184,
  "type": "Feature",
  "properties": {
    "tgn:hierarchy":[
        "tgn:7174184",
        "tgn:7003669",
        "tgn:1000003",
        "tgn:7000084",
        "tgn:7029392"
    ],
    "tgn:id":7174184,
    "tgn:name":"Groppenhof",
    "tgn:placetype":[
        "aat:300008347"
    ]
},
  "bbox": [],
  "geometry": {"coordinates":[11.083333,48.85],"type":"Point"}
}