{
  "id": 7001767,
  "type": "Feature",
  "properties": {
    "tgn:hierarchy":[
        "tgn:7001767",
        "tgn:1008380",
        "tgn:1000226",
        "tgn:7018426",
        "tgn:1000006",
        "tgn:7029392"
    ],
    "tgn:id":7001767,
    "tgn:name:en":"Thames",
    "tgn:placetype":[
        "aat:300008347"
    ]
},
  "bbox": [],
  "geometry": {"coordinates":[175.533333,-37.133333],"type":"Point"}
}