{
  "id": 7591707,
  "type": "Feature",
  "properties": {
    "tgn:hierarchy":[
        "tgn:7591707",
        "tgn:1000004",
        "tgn:7000198",
        "tgn:7000799",
        "tgn:7029392"
    ],
    "tgn:id":7591707,
    "tgn:name:en":"Nor",
    "tgn:placetype":[
        "aat:300008347"
    ]
},
  "bbox": [],
  "geometry": {"coordinates":[74.796356,32.985208],"type":"Point"}
}