{
  "id": 7571715,
  "type": "Feature",
  "properties": {
    "tgn:hierarchy":[
        "tgn:7571715",
        "tgn:1000004",
        "tgn:7000198",
        "tgn:1001882",
        "tgn:7029392"
    ],
    "tgn:id":7571715,
    "tgn:name:en":"Hebri",
    "tgn:placetype":[
        "aat:300008347"
    ]
},
  "bbox": [],
  "geometry": {"coordinates":[74.983333,13.466667],"type":"Point"}
}