{
  "id": 7201822,
  "type": "Feature",
  "properties": {
    "tgn:hierarchy":[
        "tgn:7201822",
        "tgn:1000003",
        "tgn:7003685",
        "tgn:7000084",
        "tgn:7029392"
    ],
    "tgn:id":7201822,
    "tgn:name":"Breite Berg",
    "tgn:placetype":[
        "aat:300008777"
    ]
},
  "bbox": [],
  "geometry": {"coordinates":[13.733333,50.85],"type":"Point"}
}