{
  "id": 2370477,
  "type": "Feature",
  "properties": {
    "tgn:hierarchy":[
        "tgn:2370477",
        "tgn:1000001",
        "tgn:7012149",
        "tgn:1002564",
        "tgn:7007710",
        "tgn:7029392"
    ],
    "tgn:id":2370477,
    "tgn:name":"Haas Pond",
    "tgn:placetype":[
        "aat:300006191"
    ]
},
  "bbox": [],
  "geometry": {"coordinates":[-75.45,41.35],"type":"Point"}
}