{
  "id": 7568330,
  "type": "Feature",
  "properties": {
    "tgn:hierarchy":[
        "tgn:7568330",
        "tgn:1000004",
        "tgn:7000198",
        "tgn:1001996",
        "tgn:7029392"
    ],
    "tgn:id":7568330,
    "tgn:name:en":"Purohi Chariy\u0101n Protected Forest",
    "tgn:placetype":[
        "aat:300008863"
    ]
},
  "bbox": [],
  "geometry": {"coordinates":[77.019444,31.178611],"type":"Point"}
}