{
  "id": 2169581,
  "type": "Feature",
  "properties": {
    "tgn:hierarchy":[
        "tgn:2169581",
        "tgn:1000001",
        "tgn:7012149",
        "tgn:7007157",
        "tgn:2000191",
        "tgn:7029392"
    ],
    "tgn:id":2169581,
    "tgn:name":"Big Meadow Creek",
    "tgn:placetype":[
        "aat:300008706"
    ]
},
  "bbox": [],
  "geometry": {"coordinates":[-123.4667,40.25],"type":"Point"}
}