{
  "id": 7458661,
  "type": "Feature",
  "properties": {
    "tgn:hierarchy":[
        "tgn:7458661",
        "tgn:7002445",
        "tgn:1000003",
        "tgn:7012034",
        "tgn:7008591",
        "tgn:7029392"
    ],
    "tgn:id":7458661,
    "tgn:name:en":"Lydbury North",
    "tgn:placetype":[
        "aat:300008347"
    ]
},
  "bbox": [],
  "geometry": {"coordinates":[-2.95,52.466667],"type":"Point"}
}