{
  "id": 1096434,
  "type": "Feature",
  "properties": {
    "tgn:hierarchy":[
        "tgn:1096434",
        "tgn:7000490",
        "tgn:1000006",
        "tgn:7001830",
        "tgn:7029392"
    ],
    "tgn:id":1096434,
    "tgn:name":"Burpengary",
    "tgn:placetype":[
        "aat:300008347"
    ]
},
  "bbox": [],
  "geometry": {"coordinates":[152.95,-27.1667],"type":"Point"}
}