{
  "id": 2308095,
  "type": "Feature",
  "properties": {
    "tgn:hierarchy":[
        "tgn:2308095",
        "tgn:1000001",
        "tgn:7012149",
        "tgn:1002636",
        "tgn:7007708",
        "tgn:7029392"
    ],
    "tgn:id":2308095,
    "tgn:name":"East Humbug Creek",
    "tgn:placetype":[
        "aat:300008706"
    ]
},
  "bbox": [],
  "geometry": {"coordinates":[-122.0167,44.8333],"type":"Point"}
}