{
  "id": 2604869,
  "type": "Feature",
  "properties": {
    "tgn:hierarchy":[
        "tgn:2604869",
        "tgn:1000001",
        "tgn:7012149",
        "tgn:1002897",
        "tgn:7007920",
        "tgn:7029392"
    ],
    "tgn:id":2604869,
    "tgn:name":"Race Track Lakes",
    "tgn:placetype":[
        "aat:300008680"
    ]
},
  "bbox": [],
  "geometry": {"coordinates":[-121.8167,45.9333],"type":"Point"}
}