{
  "id": 2156624,
  "type": "Feature",
  "properties": {
    "tgn:hierarchy":[
        "tgn:2156624",
        "tgn:1000001",
        "tgn:7012149",
        "tgn:2001721",
        "tgn:7007708",
        "tgn:7029392"
    ],
    "tgn:id":2156624,
    "tgn:name":"Bearwallow Spring",
    "tgn:placetype":[
        "aat:300008697"
    ]
},
  "bbox": [],
  "geometry": {"coordinates":[-117.6333,45.1667],"type":"Point"}
}