{
  "id": 1115349,
  "type": "Feature",
  "properties": {
    "tgn:hierarchy":[
        "tgn:1115349",
        "tgn:1001826",
        "tgn:1000047",
        "tgn:7002456",
        "tgn:1000002",
        "tgn:7029392"
    ],
    "tgn:id":1115349,
    "tgn:name":"Acar\u00e1, Lago",
    "tgn:placetype":[
        "aat:300008680"
    ]
},
  "bbox": [],
  "geometry": {"coordinates":[-62.6333,-3.6167],"type":"Point"}
}