{
  "id": 2505630,
  "type": "Feature",
  "properties": {
    "tgn:hierarchy":[
        "tgn:2505630",
        "tgn:1000001",
        "tgn:7012149",
        "tgn:1002924",
        "tgn:7007568",
        "tgn:7029392"
    ],
    "tgn:id":2505630,
    "tgn:name":"Menantic Creek",
    "tgn:placetype":[
        "aat:300132316"
    ]
},
  "bbox": [],
  "geometry": {"coordinates":[-72.3333,41.05],"type":"Point"}
}