{
  "id": 2014887,
  "type": "Feature",
  "properties": {
    "tgn:hierarchy":[
        "tgn:2014887",
        "tgn:1000001",
        "tgn:7012149",
        "tgn:7007157",
        "tgn:2000184",
        "tgn:7029392"
    ],
    "tgn:id":2014887,
    "tgn:name":"Wendel",
    "tgn:placetype":[
        "aat:300008347"
    ]
},
  "bbox": [],
  "geometry": {"coordinates":[-120.2167,40.3333],"type":"Point"}
}