{
  "id": 2180766,
  "type": "Feature",
  "properties": {
    "tgn:hierarchy":[
        "tgn:2180766",
        "tgn:1000001",
        "tgn:7012149",
        "tgn:1002790",
        "tgn:7007240",
        "tgn:7029392"
    ],
    "tgn:id":2180766,
    "tgn:name":"Blossom Lake",
    "tgn:placetype":[
        "aat:300008680"
    ]
},
  "bbox": [],
  "geometry": {"coordinates":[-82.7833,27.8167],"type":"Point"}
}