{
  "id": 2677004,
  "type": "Feature",
  "properties": {
    "tgn:hierarchy":[
        "tgn:2677004",
        "tgn:1000001",
        "tgn:7019982",
        "tgn:7012149",
        "tgn:7007517",
        "tgn:7029392"
    ],
    "tgn:id":2677004,
    "tgn:name":"South Branch Mill River",
    "tgn:placetype":[
        "aat:300008707"
    ]
},
  "bbox": [],
  "geometry": {"coordinates":[-72.4167,42.0667],"type":"Point"}
}