{
  "id": 7556888,
  "type": "Feature",
  "properties": {
    "tgn:hierarchy":[
        "tgn:7556888",
        "tgn:1000004",
        "tgn:7000198",
        "tgn:1001894",
        "tgn:7029392"
    ],
    "tgn:id":7556888,
    "tgn:name:en":"Sendal",
    "tgn:placetype":[
        "aat:300008347"
    ]
},
  "bbox": [],
  "geometry": {"coordinates":[76.01704,22.480125],"type":"Point"}
}