{
  "id": 2193133,
  "type": "Feature",
  "properties": {
    "tgn:hierarchy":[
        "tgn:2193133",
        "tgn:1000001",
        "tgn:7012149",
        "tgn:2000740",
        "tgn:7007254",
        "tgn:7029392"
    ],
    "tgn:id":2193133,
    "tgn:name":"Breakneck Lake",
    "tgn:placetype":[
        "aat:300006191"
    ]
},
  "bbox": [],
  "geometry": {"coordinates":[-96.8333,39.0833],"type":"Point"}
}