{
  "id": 2534296,
  "type": "Feature",
  "properties": {
    "tgn:hierarchy":[
        "tgn:2534296",
        "tgn:1000001",
        "tgn:7012149",
        "tgn:2001296",
        "tgn:7007524",
        "tgn:7029392"
    ],
    "tgn:id":2534296,
    "tgn:name":"N Canal",
    "tgn:placetype":[
        "aat:300006075"
    ]
},
  "bbox": [],
  "geometry": {"coordinates":[-112.3667,48.45],"type":"Point"}
}