{
  "id": 2136338,
  "type": "Feature",
  "properties": {
    "tgn:hierarchy":[
        "tgn:2136338",
        "tgn:1000001",
        "tgn:7012149",
        "tgn:2000822",
        "tgn:7007255",
        "tgn:7029392"
    ],
    "tgn:id":2136338,
    "tgn:name":"Arbuckle Creek",
    "tgn:placetype":[
        "aat:300008706"
    ]
},
  "bbox": [],
  "geometry": {"coordinates":[-85.1833,37.4333],"type":"Point"}
}