{
  "id": 2695561,
  "type": "Feature",
  "properties": {
    "tgn:hierarchy":[
        "tgn:2695561",
        "tgn:1000001",
        "tgn:7012149",
        "tgn:2001270",
        "tgn:7007524",
        "tgn:7029392"
    ],
    "tgn:id":2695561,
    "tgn:name":"Stinking Coulee",
    "tgn:placetype":[
        "aat:300008761"
    ]
},
  "bbox": [],
  "geometry": {"coordinates":[-104.9833,47.3333],"type":"Point"}
}