{
  "id": 2035311,
  "type": "Feature",
  "properties": {
    "tgn:hierarchy":[
        "tgn:2035311",
        "tgn:1000001",
        "tgn:7019178",
        "tgn:7012149",
        "tgn:7007253",
        "tgn:7029392"
    ],
    "tgn:id":2035311,
    "tgn:name":"Murray",
    "tgn:placetype":[
        "aat:300008347"
    ]
},
  "bbox": [],
  "geometry": {"coordinates":[-93.9333,41.0333],"type":"Point"}
}