{
  "id": 1123001,
  "type": "Feature",
  "properties": {
    "tgn:hierarchy":[
        "tgn:1123001",
        "tgn:7006450",
        "tgn:1000001",
        "tgn:7012149",
        "tgn:2124005",
        "tgn:7029392"
    ],
    "tgn:id":1123001,
    "tgn:name":"Colville",
    "tgn:placetype":[
        "aat:300008707"
    ]
},
  "bbox": [],
  "geometry": {"coordinates":[-160.35,68.8167],"type":"Point"}
}