{
  "id": 2698115,
  "type": "Feature",
  "properties": {
    "tgn:hierarchy":[
        "tgn:2698115",
        "tgn:1000001",
        "tgn:7006451",
        "tgn:2000094",
        "tgn:7012149",
        "tgn:7029392"
    ],
    "tgn:id":2698115,
    "tgn:name":"Stove Spring",
    "tgn:placetype":[
        "aat:300008697"
    ]
},
  "bbox": [],
  "geometry": {"coordinates":[-109.8333,33.45],"type":"Point"}
}