{
  "id": 7277711,
  "type": "Feature",
  "properties": {
    "tgn:hierarchy":[
        "tgn:7277711",
        "tgn:1001699",
        "tgn:1000049",
        "tgn:1000002",
        "tgn:7029392"
    ],
    "tgn:id":7277711,
    "tgn:name":"Los Angeles",
    "tgn:placetype":[
        "aat:300008347"
    ]
},
  "bbox": [],
  "geometry": {"coordinates":[-73.489167,-42.600833],"type":"Point"}
}