{
  "id": 2606859,
  "type": "Feature",
  "properties": {
    "tgn:hierarchy":[
        "tgn:2606859",
        "tgn:1000001",
        "tgn:7012149",
        "tgn:1002613",
        "tgn:7007710",
        "tgn:7029392"
    ],
    "tgn:id":2606859,
    "tgn:name":"Ramsey Run",
    "tgn:placetype":[
        "aat:300008699"
    ]
},
  "bbox": [],
  "geometry": {"coordinates":[-77.3167,41.3167],"type":"Point"}
}