{
  "id": 2486511,
  "type": "Feature",
  "properties": {
    "tgn:hierarchy":[
        "tgn:2486511",
        "tgn:1000001",
        "tgn:7012149",
        "tgn:7007710",
        "tgn:7029392"
    ],
    "tgn:id":2486511,
    "tgn:name":"Lebo Branch",
    "tgn:placetype":[
        "aat:300008699"
    ]
},
  "bbox": [],
  "geometry": {"coordinates":[-77.9833,41.3667],"type":"Point"}
}