<<<<<<< HEAD
{
  "id": 2157197,
  "type": "Feature",
  "properties": {
    "tgn:hierarchy":[
        "tgn:2157197",
        "tgn:1000001",
        "tgn:7016172",
        "tgn:7012149",
        "tgn:2000169",
        "tgn:7029392"
    ],
    "tgn:id":2157197,
    "tgn:name":"Beaver Creek",
    "tgn:placetype":[
        "aat:300008706"
    ]
},
  "bbox": [],
  "geometry": {"coordinates":[-92.5833,35.9167],"type":"Point"}
}
=======
{"geometry":{"type":"Point","coordinates":[-92.583300,35.916700]},"type":"Feature","properties":{"hierarchy":["tgn:2157197","tgn:1000001","tgn:7016172","tgn:7012149","tgn:2000169","tgn:7029392"],"placetype":["aat:300008706"],"id":2157197,"name:xx":"Beaver Creek"}}
>>>>>>> 03f74aca74312dbeaf24d7e61306dd6a786dc3d0
