{
  "id": 2157197,
  "type": "Feature",
  "properties": {
    "tgn:hierarchy":[
        "tgn:2157197",
        "tgn:1000001",
        "tgn:7016172",
        "tgn:7012149",
        "tgn:2000169",
        "tgn:7029392"
    ],
    "tgn:id":2157197,
    "tgn:name":"Beaver Creek",
    "tgn:placetype":[
        "aat:300008706"
    ]
},
  "bbox": [],
  "geometry": {"coordinates":[-92.5833,35.9167],"type":"Point"}
}