{
  "id": 7539501,
  "type": "Feature",
  "properties": {
    "tgn:hierarchy":[
        "tgn:7539501",
        "tgn:7001242",
        "tgn:7016833",
        "tgn:7029392"
    ],
    "tgn:id":7539501,
    "tgn:name:en":"Qal\u012bt, 'Ayn al",
    "tgn:placetype":[
        "aat:300008697"
    ]
},
  "bbox": [],
  "geometry": {"coordinates":[29.105738,28.314434],"type":"Point"}
}