{
  "id": 7362775,
  "type": "Feature",
  "properties": {
    "tgn:hierarchy":[
        "tgn:7362775",
        "tgn:1000001",
        "tgn:7005595",
        "tgn:7005560",
        "tgn:7029392"
    ],
    "tgn:id":7362775,
    "tgn:name":"El Carrizo",
    "tgn:placetype":[
        "aat:300008347"
    ]
},
  "bbox": [],
  "geometry": {"coordinates":[-105.583333,23.066667],"type":"Point"}
}