{
  "id": 2689449,
  "type": "Feature",
  "properties": {
    "tgn:hierarchy":[
        "tgn:2689449",
        "tgn:1000001",
        "tgn:7012149",
        "tgn:2001284",
        "tgn:7007524",
        "tgn:7029392"
    ],
    "tgn:id":2689449,
    "tgn:name":"Squaw Gulch",
    "tgn:placetype":[
        "aat:300008761"
    ]
},
  "bbox": [],
  "geometry": {"coordinates":[-112.0833,46.55],"type":"Point"}
}