{
  "id": 2505591,
  "type": "Feature",
  "properties": {
    "tgn:hierarchy":[
        "tgn:2505591",
        "tgn:1002309",
        "tgn:1000001",
        "tgn:7012149",
        "tgn:7007565",
        "tgn:7029392"
    ],
    "tgn:id":2505591,
    "tgn:name":"Memorial Park Pond",
    "tgn:placetype":[
        "aat:300006191"
    ]
},
  "bbox": [],
  "geometry": {"coordinates":[-74.95,39.4667],"type":"Point"}
}