{
  "id": 2534859,
  "type": "Feature",
  "properties": {
    "tgn:hierarchy":[
        "tgn:2534859",
        "tgn:1000001",
        "tgn:7012149",
        "tgn:7022544",
        "tgn:7007825",
        "tgn:7029392"
    ],
    "tgn:id":2534859,
    "tgn:name":"Nail Creek",
    "tgn:placetype":[
        "aat:300008706"
    ]
},
  "bbox": [],
  "geometry": {"coordinates":[-88.6667,35.15],"type":"Point"}
}