{
  "id": 2583198,
  "type": "Feature",
  "properties": {
    "tgn:hierarchy":[
        "tgn:2583198",
        "tgn:1000001",
        "tgn:1002318",
        "tgn:7012149",
        "tgn:7007710",
        "tgn:7029392"
    ],
    "tgn:id":2583198,
    "tgn:name":"Pine Manor",
    "tgn:placetype":[
        "aat:300008347"
    ]
},
  "bbox": [],
  "geometry": {"coordinates":[-76.65,40.1667],"type":"Point"}
}