{
  "id": 2377470,
  "type": "Feature",
  "properties": {
    "tgn:hierarchy":[
        "tgn:2377470",
        "tgn:1000001",
        "tgn:7012149",
        "tgn:2000437",
        "tgn:7007248",
        "tgn:7029392"
    ],
    "tgn:id":2377470,
    "tgn:name":"Harper Branch",
    "tgn:placetype":[
        "aat:300008699"
    ]
},
  "bbox": [],
  "geometry": {"coordinates":[-85.45,34.65],"type":"Point"}
}