{
  "id": 2209311,
  "type": "Feature",
  "properties": {
    "tgn:hierarchy":[
        "tgn:2209311",
        "tgn:7006450",
        "tgn:1000001",
        "tgn:7012149",
        "tgn:7019760",
        "tgn:7029392"
    ],
    "tgn:id":2209311,
    "tgn:name":"Burnt Point",
    "tgn:placetype":[
        "aat:300008850"
    ]
},
  "bbox": [],
  "geometry": {"coordinates":[-135.55,58.0333],"type":"Point"}
}