{
  "id": 7420655,
  "type": "Feature",
  "properties": {
    "tgn:hierarchy":[
        "tgn:7420655",
        "tgn:7005579",
        "tgn:1000001",
        "tgn:7005560",
        "tgn:7029392"
    ],
    "tgn:id":7420655,
    "tgn:name":"Estancia de Mosqueira",
    "tgn:placetype":[
        "aat:300008347"
    ]
},
  "bbox": [],
  "geometry": {"coordinates":[-102.35,22.141667],"type":"Point"}
}