{
  "id": 2135118,
  "type": "Feature",
  "properties": {
    "tgn:hierarchy":[
        "tgn:2135118",
        "tgn:1000001",
        "tgn:7012149",
        "tgn:1002613",
        "tgn:7007710",
        "tgn:7029392"
    ],
    "tgn:id":2135118,
    "tgn:name":"Antes Creek",
    "tgn:placetype":[
        "aat:300008706"
    ]
},
  "bbox": [],
  "geometry": {"coordinates":[-77.2167,41.15],"type":"Point"}
}