{
  "id": 2138014,
  "type": "Feature",
  "properties": {
    "tgn:hierarchy":[
        "tgn:2138014",
        "tgn:1000001",
        "tgn:7006451",
        "tgn:7012149",
        "tgn:2000097",
        "tgn:7029392"
    ],
    "tgn:id":2138014,
    "tgn:name":"Arrowhead Ranch",
    "tgn:placetype":[
        "aat:300008347"
    ]
},
  "bbox": [],
  "geometry": {"coordinates":[-112.1833,33.6667],"type":"Point"}
}