{
  "id": 1127288,
  "type": "Feature",
  "properties": {
    "tgn:hierarchy":[
        "tgn:1127288",
        "tgn:1000003",
        "tgn:7029392"
    ],
    "tgn:id":1127288,
    "tgn:name":"Mokryy Yelanchik",
    "tgn:placetype":[
        "aat:300008707"
    ]
},
  "bbox": [],
  "geometry": {"coordinates":[38.3333,47.1333],"type":"Point"}
}