<<<<<<< HEAD
{
  "id": 7364534,
  "type": "Feature",
  "properties": {
    "tgn:hierarchy":[
        "tgn:7364534",
        "tgn:7005581",
        "tgn:1000001",
        "tgn:7005560",
        "tgn:7029392"
    ],
    "tgn:id":7364534,
    "tgn:name":"Rancho El Pres\u00f3n",
    "tgn:placetype":[
        "aat:300000241"
    ]
},
  "bbox": [],
  "geometry": {"coordinates":[-107.483333,29.966667],"type":"Point"}
}
=======
{"geometry":{"type":"Point","coordinates":[-107.483333,29.966667]},"type":"Feature","properties":{"hierarchy":["tgn:7364534","tgn:7005581","tgn:1000001","tgn:7005560","tgn:7029392"],"placetype":["aat:300000241"],"id":7364534,"name:xx":"Rancho El Pres\u00f3n"}}
>>>>>>> 03f74aca74312dbeaf24d7e61306dd6a786dc3d0
