{
  "id": 7083359,
  "type": "Feature",
  "properties": {
    "tgn:hierarchy":[
        "tgn:7083359",
        "tgn:1000003",
        "tgn:7003688",
        "tgn:7000084",
        "tgn:7029392"
    ],
    "tgn:id":7083359,
    "tgn:name":"Willenbrook",
    "tgn:placetype":[
        "aat:300000206"
    ]
},
  "bbox": [],
  "geometry": {"coordinates":[9.866667,54.016667],"type":"Point"}
}