{
  "id": 2237303,
  "type": "Feature",
  "properties": {
    "tgn:hierarchy":[
        "tgn:2237303",
        "tgn:1000001",
        "tgn:7012149",
        "tgn:2000838",
        "tgn:7007255",
        "tgn:7029392"
    ],
    "tgn:id":2237303,
    "tgn:name":"Chimney Rocks",
    "tgn:placetype":[
        "aat:300008798"
    ]
},
  "bbox": [],
  "geometry": {"coordinates":[-83.7667,37.8833],"type":"Point"}
}