{
  "id": 7241381,
  "type": "Feature",
  "properties": {
    "tgn:hierarchy":[
        "tgn:7241381",
        "tgn:7003456",
        "tgn:1000003",
        "tgn:1000063",
        "tgn:7018236",
        "tgn:7029392"
    ],
    "tgn:id":7241381,
    "tgn:name":"Klaverbeek",
    "tgn:placetype":[
        "aat:300008699"
    ]
},
  "bbox": [],
  "geometry": {"coordinates":[4.254028,51.056546],"type":"Point"}
}