{
  "id": 7132821,
  "type": "Feature",
  "properties": {
    "tgn:hierarchy":[
        "tgn:7132821",
        "tgn:7003669",
        "tgn:1000003",
        "tgn:7000084",
        "tgn:7029392"
    ],
    "tgn:id":7132821,
    "tgn:name":"Moggenbrunn",
    "tgn:placetype":[
        "aat:300008347"
    ]
},
  "bbox": [],
  "geometry": {"coordinates":[10.95,50.316667],"type":"Point"}
}