{
  "id": 7519159,
  "type": "Feature",
  "properties": {
    "tgn:hierarchy":[
        "tgn:7519159",
        "tgn:1009227",
        "tgn:7001866",
        "tgn:1000226",
        "tgn:1000006",
        "tgn:7029392"
    ],
    "tgn:id":7519159,
    "tgn:name:en":"Andrews Creek",
    "tgn:placetype":[
        "aat:300008699"
    ]
},
  "bbox": [],
  "geometry": {"coordinates":[171.183333,-43.916667],"type":"Point"}
}