{
  "id": 7566916,
  "type": "Feature",
  "properties": {
    "tgn:hierarchy":[
        "tgn:7566916",
        "tgn:1000004",
        "tgn:7000198",
        "tgn:7001797",
        "tgn:7029392"
    ],
    "tgn:id":7566916,
    "tgn:name:en":"Doctor Vijayaraghavulu Nagar",
    "tgn:placetype":[
        "aat:300000745"
    ]
},
  "bbox": [],
  "geometry": {"coordinates":[80.279167,13.110278],"type":"Point"}
}