<<<<<<< HEAD
{
  "id": 2405807,
  "type": "Feature",
  "properties": {
    "tgn:hierarchy":[
        "tgn:2405807",
        "tgn:1000001",
        "tgn:2001701",
        "tgn:7012149",
        "tgn:7007708",
        "tgn:7029392"
    ],
    "tgn:id":2405807,
    "tgn:name":"Hull Creek",
    "tgn:placetype":[
        "aat:300008706"
    ]
},
  "bbox": [],
  "geometry": {"coordinates":[-123.3333,44.4],"type":"Point"}
}
=======
{"geometry":{"type":"Point","coordinates":[-123.333300,44.400000]},"type":"Feature","properties":{"hierarchy":["tgn:2405807","tgn:1000001","tgn:2001701","tgn:7012149","tgn:7007708","tgn:7029392"],"placetype":["aat:300008706"],"id":2405807,"name:xx":"Hull Creek"}}
>>>>>>> 03f74aca74312dbeaf24d7e61306dd6a786dc3d0
