{
  "id": 7068929,
  "type": "Feature",
  "properties": {
    "tgn:hierarchy":[
        "tgn:7068929",
        "tgn:7003669",
        "tgn:1000003",
        "tgn:7000084",
        "tgn:7029392"
    ],
    "tgn:id":7068929,
    "tgn:name":"Steiben Bach",
    "tgn:placetype":[
        "aat:300008699"
    ]
},
  "bbox": [],
  "geometry": {"coordinates":[10.266667,47.466667],"type":"Point"}
}