<<<<<<< HEAD
{
  "id": 2257276,
  "type": "Feature",
  "properties": {
    "tgn:hierarchy":[
        "tgn:2257276",
        "tgn:1000001",
        "tgn:7012149",
        "tgn:2001714",
        "tgn:7007708",
        "tgn:7029392"
    ],
    "tgn:id":2257276,
    "tgn:name":"Cornett Lake",
    "tgn:placetype":[
        "aat:300008680"
    ]
},
  "bbox": [],
  "geometry": {"coordinates":[-122.0833,43.4667],"type":"Point"}
}
=======
{"geometry":{"type":"Point","coordinates":[-122.083300,43.466700]},"type":"Feature","properties":{"hierarchy":["tgn:2257276","tgn:1000001","tgn:7012149","tgn:2001714","tgn:7007708","tgn:7029392"],"placetype":["aat:300008680"],"id":2257276,"name:xx":"Cornett Lake"}}
>>>>>>> 03f74aca74312dbeaf24d7e61306dd6a786dc3d0
