<<<<<<< HEAD
{
  "id": 2332674,
  "type": "Feature",
  "properties": {
    "tgn:hierarchy":[
        "tgn:2332674",
        "tgn:1000001",
        "tgn:7012149",
        "tgn:2000985",
        "tgn:7007520",
        "tgn:7029392"
    ],
    "tgn:id":2332674,
    "tgn:name":"Flowage Lake",
    "tgn:placetype":[
        "aat:300008680"
    ]
},
  "bbox": [],
  "geometry": {"coordinates":[-84.2,44.25],"type":"Point"}
}
=======
{"geometry":{"type":"Point","coordinates":[-84.200000,44.250000]},"type":"Feature","properties":{"hierarchy":["tgn:2332674","tgn:1000001","tgn:7012149","tgn:2000985","tgn:7007520","tgn:7029392"],"placetype":["aat:300008680"],"id":2332674,"name:xx":"Flowage Lake"}}
>>>>>>> 03f74aca74312dbeaf24d7e61306dd6a786dc3d0
