{
  "id": 7272339,
  "type": "Feature",
  "properties": {
    "tgn:hierarchy":[
        "tgn:7272339",
        "tgn:7003619",
        "tgn:1000003",
        "tgn:7016845",
        "tgn:7029392"
    ],
    "tgn:id":7272339,
    "tgn:name:nl":"Verbindingskanaal",
    "tgn:placetype":[
        "aat:300006075"
    ]
},
  "bbox": [],
  "geometry": {"coordinates":[6.033333,52.25],"type":"Point"}
}