{
  "id": 7307706,
  "type": "Feature",
  "properties": {
    "tgn:hierarchy":[
        "tgn:7307706",
        "tgn:7002836",
        "tgn:7016622",
        "tgn:1000003",
        "tgn:1000095",
        "tgn:7029392"
    ],
    "tgn:id":7307706,
    "tgn:name":"Los Cristianos",
    "tgn:placetype":[
        "aat:300008347"
    ]
},
  "bbox": [],
  "geometry": {"coordinates":[-16.716667,28.05],"type":"Point"}
}