{
  "id": 2212508,
  "type": "Feature",
  "properties": {
    "tgn:hierarchy":[
        "tgn:2212508",
        "tgn:1000001",
        "tgn:2001633",
        "tgn:7012149",
        "tgn:7007707",
        "tgn:7029392"
    ],
    "tgn:id":2212508,
    "tgn:name":"Bynum Ridge",
    "tgn:placetype":[
        "aat:300266640"
    ]
},
  "bbox": [],
  "geometry": {"coordinates":[-95.0667,35.9667],"type":"Point"}
}