{
  "id": 7277179,
  "type": "Feature",
  "properties": {
    "tgn:hierarchy":[
        "tgn:7277179",
        "tgn:1001702",
        "tgn:1000049",
        "tgn:1000002",
        "tgn:7029392"
    ],
    "tgn:id":7277179,
    "tgn:name":"Vicu\u00f1a Mackenna, Pen\u00ednsula",
    "tgn:placetype":[
        "aat:300008804"
    ]
},
  "bbox": [],
  "geometry": {"coordinates":[-73.083333,-52.166667],"type":"Point"}
}