{
  "id": 2415953,
  "type": "Feature",
  "properties": {
    "tgn:hierarchy":[
        "tgn:2415953",
        "tgn:1000001",
        "tgn:7012149",
        "tgn:7013961",
        "tgn:7029392"
    ],
    "tgn:id":2415953,
    "tgn:name":"Ivy Branch",
    "tgn:placetype":[
        "aat:300008699"
    ]
},
  "bbox": [],
  "geometry": {"coordinates":[-82.1833,37.9667],"type":"Point"}
}