<<<<<<< HEAD
{
  "id": 7369512,
  "type": "Feature",
  "properties": {
    "tgn:hierarchy":[
        "tgn:7369512",
        "tgn:1000001",
        "tgn:7005589",
        "tgn:7005560",
        "tgn:7029392"
    ],
    "tgn:id":7369512,
    "tgn:name":"Jabali, Ca\u00f1\u00f3n de",
    "tgn:placetype":[
        "aat:300008763"
    ]
},
  "bbox": [],
  "geometry": {"coordinates":[-100.166667,24.466667],"type":"Point"}
}
=======
{"geometry":{"type":"Point","coordinates":[-100.166667,24.466667]},"type":"Feature","properties":{"hierarchy":["tgn:7369512","tgn:1000001","tgn:7005589","tgn:7005560","tgn:7029392"],"placetype":["aat:300008763"],"id":7369512,"name:xx":"Jabali, Ca\u00f1\u00f3n de"}}
>>>>>>> 03f74aca74312dbeaf24d7e61306dd6a786dc3d0
