{
  "id": 2127577,
  "type": "Feature",
  "properties": {
    "tgn:hierarchy":[
        "tgn:2127577",
        "tgn:1000001",
        "tgn:2000316",
        "tgn:7012149",
        "tgn:7007248",
        "tgn:7029392"
    ],
    "tgn:id":2127577,
    "tgn:name":"Alabama Junction",
    "tgn:placetype":[
        "aat:300008347"
    ]
},
  "bbox": [],
  "geometry": {"coordinates":[-81.1333,32.0667],"type":"Point"}
}