{
  "id": 7228686,
  "type": "Feature",
  "properties": {
    "tgn:hierarchy":[
        "tgn:7228686",
        "tgn:7011171",
        "tgn:7001395",
        "tgn:1000003",
        "tgn:1000074",
        "tgn:7029392"
    ],
    "tgn:id":7228686,
    "tgn:name":"Ko\u00edli, Nis\u00eds",
    "tgn:placetype":[
        "aat:300008791"
    ]
},
  "bbox": [],
  "geometry": {"coordinates":[24.133333,38.666667],"type":"Point"}
}