<<<<<<< HEAD
{
  "id": 7356464,
  "type": "Feature",
  "properties": {
    "tgn:hierarchy":[
        "tgn:7356464",
        "tgn:7005581",
        "tgn:1000001",
        "tgn:7005560",
        "tgn:7029392"
    ],
    "tgn:id":7356464,
    "tgn:name":"Carneros, Cerro de los",
    "tgn:placetype":[
        "aat:300008795"
    ]
},
  "bbox": [],
  "geometry": {"coordinates":[-105.4,29.316667],"type":"Point"}
}
=======
{"geometry":{"type":"Point","coordinates":[-105.400000,29.316667]},"type":"Feature","properties":{"hierarchy":["tgn:7356464","tgn:7005581","tgn:1000001","tgn:7005560","tgn:7029392"],"placetype":["aat:300008795"],"id":7356464,"name:xx":"Carneros, Cerro de los"}}
>>>>>>> 03f74aca74312dbeaf24d7e61306dd6a786dc3d0
