{
  "id": 7504551,
  "type": "Feature",
  "properties": {
    "tgn:hierarchy":[
        "tgn:7504551",
        "tgn:1008380",
        "tgn:7000507",
        "tgn:1000226",
        "tgn:1000006",
        "tgn:7029392"
    ],
    "tgn:id":7504551,
    "tgn:name:en":"Stevens Point",
    "tgn:placetype":[
        "aat:300386846"
    ]
},
  "bbox": [],
  "geometry": {"coordinates":[174.372778,-35.768056],"type":"Point"}
}