{
  "id": 2583527,
  "type": "Feature",
  "properties": {
    "tgn:hierarchy":[
        "tgn:2583527",
        "tgn:1000001",
        "tgn:2001841",
        "tgn:7012149",
        "tgn:7007825",
        "tgn:7029392"
    ],
    "tgn:id":2583527,
    "tgn:name":"Pine Ridge",
    "tgn:placetype":[
        "aat:300266640"
    ]
},
  "bbox": [],
  "geometry": {"coordinates":[-83.85,35.5333],"type":"Point"}
}