{
  "id": 2386508,
  "type": "Feature",
  "properties": {
    "tgn:hierarchy":[
        "tgn:2386508",
        "tgn:1000001",
        "tgn:7012149",
        "tgn:7007157",
        "tgn:2000189",
        "tgn:7029392"
    ],
    "tgn:id":2386508,
    "tgn:name":"Herd Peak",
    "tgn:placetype":[
        "aat:300008798"
    ]
},
  "bbox": [],
  "geometry": {"coordinates":[-122.2167,41.6167],"type":"Point"}
}