{
  "id": 2499455,
  "type": "Feature",
  "properties": {
    "tgn:hierarchy":[
        "tgn:2499455",
        "tgn:1000001",
        "tgn:7012149",
        "tgn:2001503",
        "tgn:7007709",
        "tgn:7029392"
    ],
    "tgn:id":2499455,
    "tgn:name":"McClure Cove",
    "tgn:placetype":[
        "aat:300008761"
    ]
},
  "bbox": [],
  "geometry": {"coordinates":[-82.9167,35.55],"type":"Point"}
}