<<<<<<< HEAD
{
  "id": 7243469,
  "type": "Feature",
  "properties": {
    "tgn:hierarchy":[
        "tgn:7243469",
        "tgn:7003466",
        "tgn:1000003",
        "tgn:1000063",
        "tgn:4012014",
        "tgn:7029392"
    ],
    "tgn:id":7243469,
    "tgn:name":"Les Trieux",
    "tgn:placetype":[
        "aat:300008347"
    ]
},
  "bbox": [],
  "geometry": {"coordinates":[4.45,50.033333],"type":"Point"}
}
=======
{"geometry":{"type":"Point","coordinates":[4.450000,50.033333]},"type":"Feature","properties":{"hierarchy":["tgn:7243469","tgn:7003466","tgn:1000003","tgn:1000063","tgn:4012014","tgn:7029392"],"placetype":["aat:300008347"],"id":7243469,"name:xx":"Les Trieux"}}
>>>>>>> 03f74aca74312dbeaf24d7e61306dd6a786dc3d0
