{
  "id": 7420387,
  "type": "Feature",
  "properties": {
    "tgn:hierarchy":[
        "tgn:7420387",
        "tgn:1001836",
        "tgn:1000001",
        "tgn:7005560",
        "tgn:7029392"
    ],
    "tgn:id":7420387,
    "tgn:name":"El Obisbo, R\u00edo",
    "tgn:placetype":[
        "aat:300008699"
    ]
},
  "bbox": [],
  "geometry": {"coordinates":[-111.3125,24.655278],"type":"Point"}
}