{
  "id": 7338432,
  "type": "Feature",
  "properties": {
    "tgn:hierarchy":[
        "tgn:7338432",
        "tgn:7002824",
        "tgn:1000003",
        "tgn:7002786",
        "tgn:1000095",
        "tgn:7029392"
    ],
    "tgn:id":7338432,
    "tgn:name":"Castillo",
    "tgn:placetype":[
        "aat:300008347"
    ]
},
  "bbox": [],
  "geometry": {"coordinates":[-8.216667,43.15],"type":"Point"}
}