{
  "id": 2690618,
  "type": "Feature",
  "properties": {
    "tgn:hierarchy":[
        "tgn:2690618",
        "tgn:1000001",
        "tgn:7012149",
        "tgn:7007707",
        "tgn:7029392"
    ],
    "tgn:id":2690618,
    "tgn:name":"Stamp Dance Creek",
    "tgn:placetype":[
        "aat:300008706"
    ]
},
  "bbox": [],
  "geometry": {"coordinates":[-96.8167,35.4667],"type":"Point"}
}