{
  "id": 7377917,
  "type": "Feature",
  "properties": {
    "tgn:hierarchy":[
        "tgn:7377917",
        "tgn:7005586",
        "tgn:1000001",
        "tgn:7005560",
        "tgn:7029392"
    ],
    "tgn:id":7377917,
    "tgn:name":"La Villita",
    "tgn:placetype":[
        "aat:300266554",
        "aat:300008699"
    ]
},
  "bbox": [],
  "geometry": {"coordinates":[-103.65,20.483333],"type":"Point"}
}