{
  "id": 7577887,
  "type": "Feature",
  "properties": {
    "tgn:hierarchy":[
        "tgn:7577887",
        "tgn:1000004",
        "tgn:7000198",
        "tgn:7016788",
        "tgn:7029392"
    ],
    "tgn:id":7577887,
    "tgn:name:en":"Khud\u0101ni",
    "tgn:placetype":[
        "aat:300008347"
    ]
},
  "bbox": [],
  "geometry": {"coordinates":[70.703102,25.869044],"type":"Point"}
}