{
  "id": 7305258,
  "type": "Feature",
  "properties": {
    "tgn:hierarchy":[
        "tgn:7305258",
        "tgn:7002813",
        "tgn:7002758",
        "tgn:1000003",
        "tgn:1000095",
        "tgn:7029392"
    ],
    "tgn:id":7305258,
    "tgn:name":"Salemara, Piedra la",
    "tgn:placetype":[
        "aat:300011692"
    ]
},
  "bbox": [],
  "geometry": {"coordinates":[-5.383333,36.166667],"type":"Point"}
}