<<<<<<< HEAD
{
  "id": 7025469,
  "type": "Feature",
  "properties": {
    "tgn:hierarchy":[
        "tgn:7025469",
        "tgn:7002445",
        "tgn:1000003",
        "tgn:7012077",
        "tgn:7008591",
        "tgn:7029392"
    ],
    "tgn:id":7025469,
    "tgn:name":"East Charleton",
    "tgn:placetype":[
        "aat:300008347"
    ]
},
  "bbox": [],
  "geometry": {"coordinates":[-3.7333,50.2667],"type":"Point"}
}
=======
{"geometry":{"type":"Point","coordinates":[-3.733300,50.266700]},"type":"Feature","properties":{"hierarchy":["tgn:7025469","tgn:7002445","tgn:1000003","tgn:7012077","tgn:7008591","tgn:7029392"],"placetype":["aat:300008347"],"id":7025469,"name:xx":"East Charleton"}}
>>>>>>> 03f74aca74312dbeaf24d7e61306dd6a786dc3d0
