<<<<<<< HEAD
{
  "id": 2764834,
  "type": "Feature",
  "properties": {
    "tgn:hierarchy":[
        "tgn:2764834",
        "tgn:1000001",
        "tgn:7012149",
        "tgn:1002788",
        "tgn:7007706",
        "tgn:7029392"
    ],
    "tgn:id":2764834,
    "tgn:name":"Whiskey Hollow",
    "tgn:placetype":[
        "aat:300008761"
    ]
},
  "bbox": [],
  "geometry": {"coordinates":[-83.2667,39.1833],"type":"Point"}
}
=======
{"geometry":{"type":"Point","coordinates":[-83.266700,39.183300]},"type":"Feature","properties":{"hierarchy":["tgn:2764834","tgn:1000001","tgn:7012149","tgn:1002788","tgn:7007706","tgn:7029392"],"placetype":["aat:300008761"],"id":2764834,"name:xx":"Whiskey Hollow"}}
>>>>>>> 03f74aca74312dbeaf24d7e61306dd6a786dc3d0
