{
  "id": 1019096,
  "type": "Feature",
  "properties": {
    "tgn:hierarchy":[
        "tgn:1019096",
        "tgn:7593613",
        "tgn:1000001",
        "tgn:7004787",
        "tgn:7029392"
    ],
    "tgn:id":1019096,
    "tgn:name":"Siparia",
    "tgn:placetype":[
        "aat:300008347"
    ]
},
  "bbox": [],
  "geometry": {"coordinates":[-61.5167,10.1333],"type":"Point"}
}