{
  "id": 2638004,
  "type": "Feature",
  "properties": {
    "tgn:hierarchy":[
        "tgn:2638004",
        "tgn:1000001",
        "tgn:7012149",
        "tgn:2001110",
        "tgn:7007522",
        "tgn:7029392"
    ],
    "tgn:id":2638004,
    "tgn:name":"Salem",
    "tgn:placetype":[
        "aat:300008347"
    ]
},
  "bbox": [],
  "geometry": {"coordinates":[-90.5333,32.1667],"type":"Point"}
}