{
  "id": 1118771,
  "type": "Feature",
  "properties": {
    "tgn:hierarchy":[
        "tgn:1118771",
        "tgn:1000004",
        "tgn:7000198",
        "tgn:7000799",
        "tgn:7029392"
    ],
    "tgn:id":1118771,
    "tgn:name:en":"Wular Lake",
    "tgn:placetype":[
        "aat:300008680"
    ]
},
  "bbox": [],
  "geometry": {"coordinates":[74.549086,34.364459],"type":"Point"}
}