{
  "id": 1015683,
  "type": "Feature",
  "properties": {
    "tgn:hierarchy":[
        "tgn:1015683",
        "tgn:7005685",
        "tgn:1000001",
        "tgn:7005804",
        "tgn:1008205",
        "tgn:7029392"
    ],
    "tgn:id":1015683,
    "tgn:name":"Saint-L\u00e9onard",
    "tgn:placetype":[
        "aat:300008347"
    ]
},
  "bbox": [],
  "geometry": {"coordinates":[-73.65,45.5833],"type":"Point"}
}