{
  "id": 1035560,
  "type": "Feature",
  "properties": {
    "tgn:hierarchy":[
        "tgn:1035560",
        "tgn:1000003",
        "tgn:7002882",
        "tgn:1000070",
        "tgn:7029392"
    ],
    "tgn:id":1035560,
    "tgn:name":"Sainte-Adresse",
    "tgn:placetype":[
        "aat:300008347"
    ]
},
  "bbox": [],
  "geometry": {"coordinates":[0.0833,49.5167],"type":"Point"}
}