{
  "id": 2341944,
  "type": "Feature",
  "properties": {
    "tgn:hierarchy":[
        "tgn:2341944",
        "tgn:1002141",
        "tgn:1000001",
        "tgn:7012149",
        "tgn:7007568",
        "tgn:7029392"
    ],
    "tgn:id":2341944,
    "tgn:name":"Fry Creek",
    "tgn:placetype":[
        "aat:300008706"
    ]
},
  "bbox": [],
  "geometry": {"coordinates":[-77.9167,42.4667],"type":"Point"}
}