<<<<<<< HEAD
{
  "id": 2157695,
  "type": "Feature",
  "properties": {
    "tgn:hierarchy":[
        "tgn:2157695",
        "tgn:1000001",
        "tgn:7012149",
        "tgn:2001709",
        "tgn:7007708",
        "tgn:7029392"
    ],
    "tgn:id":2157695,
    "tgn:name":"Beaver Dam Spring",
    "tgn:placetype":[
        "aat:300008697"
    ]
},
  "bbox": [],
  "geometry": {"coordinates":[-119.5,43.8],"type":"Point"}
}
=======
{"geometry":{"type":"Point","coordinates":[-119.500000,43.800000]},"type":"Feature","properties":{"hierarchy":["tgn:2157695","tgn:1000001","tgn:7012149","tgn:2001709","tgn:7007708","tgn:7029392"],"placetype":["aat:300008697"],"id":2157695,"name:xx":"Beaver Dam Spring"}}
>>>>>>> 03f74aca74312dbeaf24d7e61306dd6a786dc3d0
