{
  "id": 2786331,
  "type": "Feature",
  "properties": {
    "tgn:hierarchy":[
        "tgn:2786331",
        "tgn:1000001",
        "tgn:2000861",
        "tgn:7012149",
        "tgn:7007256",
        "tgn:7029392"
    ],
    "tgn:id":2786331,
    "tgn:name":"Youngs Point Landing",
    "tgn:placetype":[
        "aat:300008850"
    ]
},
  "bbox": [],
  "geometry": {"coordinates":[-93.5667,32.3167],"type":"Point"}
}