{
  "id": 2536568,
  "type": "Feature",
  "properties": {
    "tgn:hierarchy":[
        "tgn:2536568",
        "tgn:1000001",
        "tgn:1002724",
        "tgn:7012149",
        "tgn:7007517",
        "tgn:7029392"
    ],
    "tgn:id":2536568,
    "tgn:name":"Neary Mountain",
    "tgn:placetype":[
        "aat:300008798"
    ]
},
  "bbox": [],
  "geometry": {"coordinates":[-71.05,42.15],"type":"Point"}
}