{
  "id": 1051886,
  "type": "Feature",
  "properties": {
    "tgn:hierarchy":[
        "tgn:1051886",
        "tgn:1000004",
        "tgn:7012947",
        "tgn:7014786",
        "tgn:7029392"
    ],
    "tgn:id":1051886,
    "tgn:name":"Achisay",
    "tgn:placetype":[
        "aat:300008347"
    ]
},
  "bbox": [],
  "geometry": {"coordinates":[68.8833,43.5833],"type":"Point"}
}