{
  "id": 2039309,
  "type": "Feature",
  "properties": {
    "tgn:hierarchy":[
        "tgn:2039309",
        "tgn:1000001",
        "tgn:7012149",
        "tgn:2000799",
        "tgn:7007255",
        "tgn:7029392"
    ],
    "tgn:id":2039309,
    "tgn:name":"Hebbardsville",
    "tgn:placetype":[
        "aat:300008347"
    ]
},
  "bbox": [],
  "geometry": {"coordinates":[-87.3667,37.7667],"type":"Point"}
}