{
  "id": 2704843,
  "type": "Feature",
  "properties": {
    "tgn:hierarchy":[
        "tgn:2704843",
        "tgn:1000001",
        "tgn:7012149",
        "tgn:1002519",
        "tgn:7007706",
        "tgn:7029392"
    ],
    "tgn:id":2704843,
    "tgn:name":"Sunset Lake",
    "tgn:placetype":[
        "aat:300008680"
    ]
},
  "bbox": [],
  "geometry": {"coordinates":[-80.7333,40.4167],"type":"Point"}
}