<<<<<<< HEAD
{
  "id": 2408541,
  "type": "Feature",
  "properties": {
    "tgn:hierarchy":[
        "tgn:2408541",
        "tgn:1000001",
        "tgn:7012149",
        "tgn:2001105",
        "tgn:7007522",
        "tgn:7029392"
    ],
    "tgn:id":2408541,
    "tgn:name":"Hutson Lake",
    "tgn:placetype":[
        "aat:300008680"
    ]
},
  "bbox": [],
  "geometry": {"coordinates":[-88.75,30.8667],"type":"Point"}
}
=======
{"geometry":{"type":"Point","coordinates":[-88.750000,30.866700]},"type":"Feature","properties":{"hierarchy":["tgn:2408541","tgn:1000001","tgn:7012149","tgn:2001105","tgn:7007522","tgn:7029392"],"placetype":["aat:300008680"],"id":2408541,"name:xx":"Hutson Lake"}}
>>>>>>> 03f74aca74312dbeaf24d7e61306dd6a786dc3d0
