{
  "id": 7064553,
  "type": "Feature",
  "properties": {
    "tgn:hierarchy":[
        "tgn:7064553",
        "tgn:7003669",
        "tgn:1000003",
        "tgn:7000084",
        "tgn:7029392"
    ],
    "tgn:id":7064553,
    "tgn:name":"Unteralmsham",
    "tgn:placetype":[
        "aat:300000206"
    ]
},
  "bbox": [],
  "geometry": {"coordinates":[12.366667,48.266667],"type":"Point"}
}