{
  "id": 2773682,
  "type": "Feature",
  "properties": {
    "tgn:hierarchy":[
        "tgn:2773682",
        "tgn:7006450",
        "tgn:1000001",
        "tgn:7012149",
        "tgn:2124014",
        "tgn:7029392"
    ],
    "tgn:id":2773682,
    "tgn:name":"Willow Bay",
    "tgn:placetype":[
        "aat:300132316"
    ]
},
  "bbox": [],
  "geometry": {"coordinates":[-162.35,66.0333],"type":"Point"}
}