{
  "id": 2210003,
  "type": "Feature",
  "properties": {
    "tgn:hierarchy":[
        "tgn:2210003",
        "tgn:1000001",
        "tgn:7012149",
        "tgn:2000839",
        "tgn:7007255",
        "tgn:7029392"
    ],
    "tgn:id":2210003,
    "tgn:name":"Burton Branch",
    "tgn:placetype":[
        "aat:300008699"
    ]
},
  "bbox": [],
  "geometry": {"coordinates":[-84.7333,37.0333],"type":"Point"}
}