{
  "id": 1096263,
  "type": "Feature",
  "properties": {
    "tgn:hierarchy":[
        "tgn:1096263",
        "tgn:7000490",
        "tgn:1000006",
        "tgn:7006238",
        "tgn:7029392"
    ],
    "tgn:id":1096263,
    "tgn:name":"Beulah",
    "tgn:placetype":[
        "aat:300008347"
    ]
},
  "bbox": [],
  "geometry": {"coordinates":[142.4333,-35.9833],"type":"Point"}
}