{
  "id": 2381559,
  "type": "Feature",
  "properties": {
    "tgn:hierarchy":[
        "tgn:2381559",
        "tgn:1000001",
        "tgn:7012149",
        "tgn:7007923",
        "tgn:7029392"
    ],
    "tgn:id":2381559,
    "tgn:name":"Hay Draw",
    "tgn:placetype":[
        "aat:300008761"
    ]
},
  "bbox": [],
  "geometry": {"coordinates":[-106.3667,43.4167],"type":"Point"}
}