{
  "id": 7372399,
  "type": "Feature",
  "properties": {
    "tgn:hierarchy":[
        "tgn:7372399",
        "tgn:1000001",
        "tgn:1001960",
        "tgn:7005560",
        "tgn:7029392"
    ],
    "tgn:id":7372399,
    "tgn:name":"Rancho La Judicial",
    "tgn:placetype":[
        "aat:300000241"
    ]
},
  "bbox": [],
  "geometry": {"coordinates":[-111.833333,28.916667],"type":"Point"}
}