{
  "id": 1093837,
  "type": "Feature",
  "properties": {
    "tgn:hierarchy":[
        "tgn:1093837",
        "tgn:7001242",
        "tgn:7017584",
        "tgn:1000193",
        "tgn:7029392"
    ],
    "tgn:id":1093837,
    "tgn:name":"Zaaimansdal",
    "tgn:placetype":[
        "aat:300008347"
    ]
},
  "bbox": [],
  "geometry": {"coordinates":[23.35,-33.5833],"type":"Point"}
}