{
  "id": 7180005,
  "type": "Feature",
  "properties": {
    "tgn:hierarchy":[
        "tgn:7180005",
        "tgn:1000003",
        "tgn:7003685",
        "tgn:7000084",
        "tgn:7029392"
    ],
    "tgn:id":7180005,
    "tgn:name":"Talsperre des Friedens",
    "tgn:placetype":[
        "aat:300006191"
    ]
},
  "bbox": [],
  "geometry": {"coordinates":[12.633333,50.483333],"type":"Point"}
}