{
  "id": 7265875,
  "type": "Feature",
  "properties": {
    "tgn:hierarchy":[
        "tgn:7265875",
        "tgn:7003616",
        "tgn:1000003",
        "tgn:7016845",
        "tgn:7029392"
    ],
    "tgn:id":7265875,
    "tgn:name:nl":"Langakkerpolder",
    "tgn:placetype":[
        "aat:300006163"
    ]
},
  "bbox": [],
  "geometry": {"coordinates":[5.416667,52.883333],"type":"Point"}
}