{
  "id": 2356379,
  "type": "Feature",
  "properties": {
    "tgn:hierarchy":[
        "tgn:2356379",
        "tgn:1000001",
        "tgn:7012149",
        "tgn:2001447",
        "tgn:7007566",
        "tgn:7029392"
    ],
    "tgn:id":2356379,
    "tgn:name":"Gopher Tank",
    "tgn:placetype":[
        "aat:300006191"
    ]
},
  "bbox": [],
  "geometry": {"coordinates":[-105.4167,32.0833],"type":"Point"}
}