{
  "id": 2293217,
  "type": "Feature",
  "properties": {
    "tgn:hierarchy":[
        "tgn:2293217",
        "tgn:1000001",
        "tgn:7012149",
        "tgn:2002154",
        "tgn:7007919",
        "tgn:7029392"
    ],
    "tgn:id":2293217,
    "tgn:name":"Double Branch",
    "tgn:placetype":[
        "aat:300008699"
    ]
},
  "bbox": [],
  "geometry": {"coordinates":[-80.35,37.4833],"type":"Point"}
}