{
  "id": 7168884,
  "type": "Feature",
  "properties": {
    "tgn:hierarchy":[
        "tgn:7168884",
        "tgn:1000003",
        "tgn:7003678",
        "tgn:7000084",
        "tgn:7029392"
    ],
    "tgn:id":7168884,
    "tgn:name":"Heydstadt",
    "tgn:placetype":[
        "aat:300000206"
    ]
},
  "bbox": [],
  "geometry": {"coordinates":[9.433333,51.216667],"type":"Point"}
}