{
  "id": 7588677,
  "type": "Feature",
  "properties": {
    "tgn:hierarchy":[
        "tgn:7588677",
        "tgn:1000004",
        "tgn:7000198",
        "tgn:7000799",
        "tgn:7029392"
    ],
    "tgn:id":7588677,
    "tgn:name:en":"Khati Dharms\u0101l",
    "tgn:placetype":[
        "aat:300008347"
    ]
},
  "bbox": [],
  "geometry": {"coordinates":[74.05,33.763889],"type":"Point"}
}