{
  "id": 7177916,
  "type": "Feature",
  "properties": {
    "tgn:hierarchy":[
        "tgn:7177916",
        "tgn:1000003",
        "tgn:7003678",
        "tgn:7000084",
        "tgn:7029392"
    ],
    "tgn:id":7177916,
    "tgn:name":"G\u00fcnsterode",
    "tgn:placetype":[
        "aat:300008347"
    ]
},
  "bbox": [],
  "geometry": {"coordinates":[9.65,51.166667],"type":"Point"}
}