{
  "id": 2734883,
  "type": "Feature",
  "properties": {
    "tgn:hierarchy":[
        "tgn:2734883",
        "tgn:1000001",
        "tgn:7012149",
        "tgn:2000481",
        "tgn:7007250",
        "tgn:7029392"
    ],
    "tgn:id":2734883,
    "tgn:name":"Twelvemile Creek",
    "tgn:placetype":[
        "aat:300008706"
    ]
},
  "bbox": [],
  "geometry": {"coordinates":[-113.85,44.9167],"type":"Point"}
}