{
  "id": 2087664,
  "type": "Feature",
  "properties": {
    "tgn:hierarchy":[
        "tgn:2087664",
        "tgn:1000001",
        "tgn:7012149",
        "tgn:1002995",
        "tgn:7007710",
        "tgn:7029392"
    ],
    "tgn:id":2087664,
    "tgn:name":"Daisytown",
    "tgn:placetype":[
        "aat:300008347"
    ]
},
  "bbox": [],
  "geometry": {"coordinates":[-79.9167,40.05],"type":"Point"}
}