{
  "id": 2468072,
  "type": "Feature",
  "properties": {
    "tgn:hierarchy":[
        "tgn:2468072",
        "tgn:1000001",
        "tgn:7012149",
        "tgn:1002391",
        "tgn:7007826",
        "tgn:7029392"
    ],
    "tgn:id":2468072,
    "tgn:name":"Long Lake",
    "tgn:placetype":[
        "aat:300008680"
    ]
},
  "bbox": [],
  "geometry": {"coordinates":[-96.05,31.9167],"type":"Point"}
}