{
  "id": 2566778,
  "type": "Feature",
  "properties": {
    "tgn:hierarchy":[
        "tgn:2566778",
        "tgn:1000001",
        "tgn:7012149",
        "tgn:2001128",
        "tgn:7007522",
        "tgn:7029392"
    ],
    "tgn:id":2566778,
    "tgn:name":"Panter Creek",
    "tgn:placetype":[
        "aat:300008706"
    ]
},
  "bbox": [],
  "geometry": {"coordinates":[-90.5833,31.4833],"type":"Point"}
}