{
  "id": 7518407,
  "type": "Feature",
  "properties": {
    "tgn:hierarchy":[
        "tgn:7518407",
        "tgn:1008380",
        "tgn:7520093",
        "tgn:1000226",
        "tgn:1000006",
        "tgn:7029392"
    ],
    "tgn:id":7518407,
    "tgn:name:en":"Matarua",
    "tgn:placetype":[
        "aat:300008795"
    ]
},
  "bbox": [],
  "geometry": {"coordinates":[175.766667,-40.45],"type":"Point"}
}