{
  "id": 2578609,
  "type": "Feature",
  "properties": {
    "tgn:hierarchy":[
        "tgn:2578609",
        "tgn:1000001",
        "tgn:7012149",
        "tgn:2001919",
        "tgn:7007825",
        "tgn:7029392"
    ],
    "tgn:id":2578609,
    "tgn:name":"Phillip Bradshaw Lake",
    "tgn:placetype":[
        "aat:300006191"
    ]
},
  "bbox": [],
  "geometry": {"coordinates":[-86.55,36.5333],"type":"Point"}
}