{
  "id": 7368083,
  "type": "Feature",
  "properties": {
    "tgn:hierarchy":[
        "tgn:7368083",
        "tgn:7005585",
        "tgn:1000001",
        "tgn:7005560",
        "tgn:7029392"
    ],
    "tgn:id":7368083,
    "tgn:name":"Joluchuca, Boca de",
    "tgn:placetype":[
        "aat:300387057"
    ]
},
  "bbox": [],
  "geometry": {"coordinates":[-101.233333,17.416667],"type":"Point"}
}