{
  "id": 7305144,
  "type": "Feature",
  "properties": {
    "tgn:hierarchy":[
        "tgn:7305144",
        "tgn:7002758",
        "tgn:7002821",
        "tgn:1000003",
        "tgn:1000095",
        "tgn:7029392"
    ],
    "tgn:id":7305144,
    "tgn:name":"Las Puertas",
    "tgn:placetype":[
        "aat:300008347"
    ]
},
  "bbox": [],
  "geometry": {"coordinates":[-3.733333,36.416667],"type":"Point"}
}