{
  "id": 7143332,
  "type": "Feature",
  "properties": {
    "tgn:hierarchy":[
        "tgn:7143332",
        "tgn:7000096",
        "tgn:1000003",
        "tgn:7000084",
        "tgn:7029392"
    ],
    "tgn:id":7143332,
    "tgn:name":"Machnower See",
    "tgn:placetype":[
        "aat:300008680"
    ]
},
  "bbox": [],
  "geometry": {"coordinates":[13.45,52.283333],"type":"Point"}
}