<<<<<<< HEAD
{
  "id": 7489040,
  "type": "Feature",
  "properties": {
    "tgn:hierarchy":[
        "tgn:7489040",
        "tgn:1000004",
        "tgn:7001014",
        "tgn:1000141",
        "tgn:7029392"
    ],
    "tgn:id":7489040,
    "tgn:name":"Lunbei Cun",
    "tgn:placetype":[
        "aat:300387173"
    ]
},
  "bbox": [],
  "geometry": {"coordinates":[120.163333,23.656389],"type":"Point"}
}
=======
{"geometry":{"type":"Point","coordinates":[120.163333,23.656389]},"type":"Feature","properties":{"hierarchy":["tgn:7489040","tgn:1000004","tgn:7001014","tgn:1000141","tgn:7029392"],"placetype":["aat:300387173"],"id":7489040,"name:xx":"Lunbei Cun"}}
>>>>>>> 03f74aca74312dbeaf24d7e61306dd6a786dc3d0
