{
  "id": 7489040,
  "type": "Feature",
  "properties": {
    "tgn:hierarchy":[
        "tgn:7489040",
        "tgn:1000004",
        "tgn:7001014",
        "tgn:1000141",
        "tgn:7029392"
    ],
    "tgn:id":7489040,
    "tgn:name":"Lunbei Cun",
    "tgn:placetype":[
        "aat:300387173"
    ]
},
  "bbox": [],
  "geometry": {"coordinates":[120.163333,23.656389],"type":"Point"}
}