{
  "id": 2298010,
  "type": "Feature",
  "properties": {
    "tgn:hierarchy":[
        "tgn:2298010",
        "tgn:1000001",
        "tgn:7012149",
        "tgn:2000208",
        "tgn:7007158",
        "tgn:7029392"
    ],
    "tgn:id":2298010,
    "tgn:name":"Dry Lake",
    "tgn:placetype":[
        "aat:300008680"
    ]
},
  "bbox": [],
  "geometry": {"coordinates":[-108.6333,37.7833],"type":"Point"}
}