{
  "id": 2184850,
  "type": "Feature",
  "properties": {
    "tgn:hierarchy":[
        "tgn:2184850",
        "tgn:1000001",
        "tgn:7012149",
        "tgn:2001667",
        "tgn:7007707",
        "tgn:7029392"
    ],
    "tgn:id":2184850,
    "tgn:name":"Bog Mountain",
    "tgn:placetype":[
        "aat:300008798"
    ]
},
  "bbox": [],
  "geometry": {"coordinates":[-94.5167,34.2167],"type":"Point"}
}