<<<<<<< HEAD
{
  "id": 7112201,
  "type": "Feature",
  "properties": {
    "tgn:hierarchy":[
        "tgn:7112201",
        "tgn:7003669",
        "tgn:1000003",
        "tgn:7000084",
        "tgn:7029392"
    ],
    "tgn:id":7112201,
    "tgn:name":"Rossberg",
    "tgn:placetype":[
        "aat:300008777"
    ]
},
  "bbox": [],
  "geometry": {"coordinates":[10.6,50.066667],"type":"Point"}
}
=======
{"geometry":{"type":"Point","coordinates":[10.600000,50.066667]},"type":"Feature","properties":{"hierarchy":["tgn:7112201","tgn:7003669","tgn:1000003","tgn:7000084","tgn:7029392"],"placetype":["aat:300008777"],"id":7112201,"name:xx":"Rossberg"}}
>>>>>>> 03f74aca74312dbeaf24d7e61306dd6a786dc3d0
