{
  "id": 7482921,
  "type": "Feature",
  "properties": {
    "tgn:hierarchy":[
        "tgn:7482921",
        "tgn:7468018",
        "tgn:1000004",
        "tgn:1000141",
        "tgn:7029392"
    ],
    "tgn:id":7482921,
    "tgn:name":"Yaorenkeng",
    "tgn:placetype":[
        "aat:300008347"
    ]
},
  "bbox": [],
  "geometry": {"coordinates":[120.536667,23.550278],"type":"Point"}
}