{
  "id": 2082118,
  "type": "Feature",
  "properties": {
    "tgn:hierarchy":[
        "tgn:2082118",
        "tgn:1000001",
        "tgn:1002295",
        "tgn:7012149",
        "tgn:7007706",
        "tgn:7029392"
    ],
    "tgn:id":2082118,
    "tgn:name":"Summitville",
    "tgn:placetype":[
        "aat:300008347"
    ]
},
  "bbox": [],
  "geometry": {"coordinates":[-80.8833,40.6667],"type":"Point"}
}