{
  "id": 7384645,
  "type": "Feature",
  "properties": {
    "tgn:hierarchy":[
        "tgn:7384645",
        "tgn:7005586",
        "tgn:1000001",
        "tgn:7005560",
        "tgn:7029392"
    ],
    "tgn:id":7384645,
    "tgn:name":"Mistemeque",
    "tgn:placetype":[
        "aat:300000241"
    ]
},
  "bbox": [],
  "geometry": {"coordinates":[-103.716667,20.983333],"type":"Point"}
}