{
  "id": 2669166,
  "type": "Feature",
  "properties": {
    "tgn:hierarchy":[
        "tgn:2669166",
        "tgn:1000001",
        "tgn:7012149",
        "tgn:7029392"
    ],
    "tgn:id":2669166,
    "tgn:name":"Sleepy Creek Mountain",
    "tgn:placetype":[
        "aat:300008798"
    ]
},
  "bbox": [],
  "geometry": {"coordinates":[-78.1833,39.45],"type":"Point"}
}