{
  "id": 2528014,
  "type": "Feature",
  "properties": {
    "tgn:hierarchy":[
        "tgn:2528014",
        "tgn:1000001",
        "tgn:7012149",
        "tgn:7016167",
        "tgn:7007523",
        "tgn:7029392"
    ],
    "tgn:id":2528014,
    "tgn:name":"Mountain Ridge",
    "tgn:placetype":[
        "aat:300008347"
    ]
},
  "bbox": [],
  "geometry": {"coordinates":[-90.5333,38.55],"type":"Point"}
}