{
  "id": 2202057,
  "type": "Feature",
  "properties": {
    "tgn:hierarchy":[
        "tgn:2202057",
        "tgn:1000001",
        "tgn:7012149",
        "tgn:2000435",
        "tgn:7007248",
        "tgn:7029392"
    ],
    "tgn:id":2202057,
    "tgn:name":"Buck Knob",
    "tgn:placetype":[
        "aat:300008798"
    ]
},
  "bbox": [],
  "geometry": {"coordinates":[-84.0167,34.7833],"type":"Point"}
}