{
  "id": 2379147,
  "type": "Feature",
  "properties": {
    "tgn:hierarchy":[
        "tgn:2379147",
        "tgn:1000001",
        "tgn:7012149",
        "tgn:2000353",
        "tgn:7007248",
        "tgn:7029392"
    ],
    "tgn:id":2379147,
    "tgn:name":"Harts",
    "tgn:placetype":[
        "aat:300008347"
    ]
},
  "bbox": [],
  "geometry": {"coordinates":[-82.55,33.3167],"type":"Point"}
}