{
  "id": 2005790,
  "type": "Feature",
  "properties": {
    "tgn:hierarchy":[
        "tgn:2005790",
        "tgn:7002659",
        "tgn:1000001",
        "tgn:7012149",
        "tgn:2000058",
        "tgn:7029392"
    ],
    "tgn:id":2005790,
    "tgn:name":"Wilton",
    "tgn:placetype":[
        "aat:300008347"
    ]
},
  "bbox": [],
  "geometry": {"coordinates":[-86.8667,33.0667],"type":"Point"}
}