{
  "id": 2023095,
  "type": "Feature",
  "properties": {
    "tgn:hierarchy":[
        "tgn:2023095",
        "tgn:1000001",
        "tgn:7012149",
        "tgn:2000366",
        "tgn:7007248",
        "tgn:7029392"
    ],
    "tgn:id":2023095,
    "tgn:name":"Hampton",
    "tgn:placetype":[
        "aat:300008347"
    ]
},
  "bbox": [],
  "geometry": {"coordinates":[-84.2667,33.3833],"type":"Point"}
}