{
  "id": 7310174,
  "type": "Feature",
  "properties": {
    "tgn:hierarchy":[
        "tgn:7310174",
        "tgn:1001692",
        "tgn:1000049",
        "tgn:1000002",
        "tgn:7029392"
    ],
    "tgn:id":7310174,
    "tgn:name":"\u00d1irca, Estero",
    "tgn:placetype":[
        "aat:300008699"
    ]
},
  "bbox": [],
  "geometry": {"coordinates":[-72.433333,-38.55],"type":"Point"}
}