{
  "id": 7236266,
  "type": "Feature",
  "properties": {
    "tgn:hierarchy":[
        "tgn:7236266",
        "tgn:7002728",
        "tgn:7002715",
        "tgn:1000003",
        "tgn:1000074",
        "tgn:7029392"
    ],
    "tgn:id":7236266,
    "tgn:name":"\u00c1no Rodoni\u00e1",
    "tgn:placetype":[
        "aat:300008347"
    ]
},
  "bbox": [],
  "geometry": {"coordinates":[22.025,40.963333],"type":"Point"}
}