{
  "id": 1089097,
  "type": "Feature",
  "properties": {
    "tgn:hierarchy":[
        "tgn:1089097",
        "tgn:7001242",
        "tgn:7016707",
        "tgn:1000159",
        "tgn:7029392"
    ],
    "tgn:id":1089097,
    "tgn:name":"Katanda",
    "tgn:placetype":[
        "aat:300008347"
    ]
},
  "bbox": [],
  "geometry": {"coordinates":[29.35,-0.85],"type":"Point"}
}