<<<<<<< HEAD
{
  "id": 2400516,
  "type": "Feature",
  "properties": {
    "tgn:hierarchy":[
        "tgn:2400516",
        "tgn:1000001",
        "tgn:7012149",
        "tgn:2001895",
        "tgn:7007825",
        "tgn:7029392"
    ],
    "tgn:id":2400516,
    "tgn:name":"Horse Knob",
    "tgn:placetype":[
        "aat:300008798"
    ]
},
  "bbox": [],
  "geometry": {"coordinates":[-86.8,35.2667],"type":"Point"}
}
=======
{"geometry":{"type":"Point","coordinates":[-86.800000,35.266700]},"type":"Feature","properties":{"hierarchy":["tgn:2400516","tgn:1000001","tgn:7012149","tgn:2001895","tgn:7007825","tgn:7029392"],"placetype":["aat:300008798"],"id":2400516,"name:xx":"Horse Knob"}}
>>>>>>> 03f74aca74312dbeaf24d7e61306dd6a786dc3d0
