{
  "id": 7374621,
  "type": "Feature",
  "properties": {
    "tgn:hierarchy":[
        "tgn:7374621",
        "tgn:1000001",
        "tgn:7005594",
        "tgn:7005560",
        "tgn:7029392"
    ],
    "tgn:id":7374621,
    "tgn:name":"Lagunillas",
    "tgn:placetype":[
        "aat:300008347"
    ]
},
  "bbox": [],
  "geometry": {"coordinates":[-100.483333,22.433333],"type":"Point"}
}