<<<<<<< HEAD
{
  "id": 7374359,
  "type": "Feature",
  "properties": {
    "tgn:hierarchy":[
        "tgn:7374359",
        "tgn:1000001",
        "tgn:1001960",
        "tgn:7005560",
        "tgn:7029392"
    ],
    "tgn:id":7374359,
    "tgn:name":"Laguna Larga, Arroyo",
    "tgn:placetype":[
        "aat:300266554",
        "aat:300008699"
    ]
},
  "bbox": [],
  "geometry": {"coordinates":[-110.133333,28.05],"type":"Point"}
}
=======
{"geometry":{"type":"Point","coordinates":[-110.133333,28.050000]},"type":"Feature","properties":{"hierarchy":["tgn:7374359","tgn:1000001","tgn:1001960","tgn:7005560","tgn:7029392"],"placetype":["aat:300266554","aat:300008699"],"id":7374359,"name:xx":"Laguna Larga, Arroyo"}}
>>>>>>> 03f74aca74312dbeaf24d7e61306dd6a786dc3d0
