{
  "id": 1083901,
  "type": "Feature",
  "properties": {
    "tgn:hierarchy":[
        "tgn:1083901",
        "tgn:1000004",
        "tgn:7001390",
        "tgn:1000119",
        "tgn:7029392"
    ],
    "tgn:id":1083901,
    "tgn:name":"Jab\u0101liy\u0101",
    "tgn:placetype":[
        "aat:300008347"
    ]
},
  "bbox": [],
  "geometry": {"coordinates":[34.4833,31.5333],"type":"Point"}
}