{
  "id": 2536516,
  "type": "Feature",
  "properties": {
    "tgn:hierarchy":[
        "tgn:2536516",
        "tgn:2002139",
        "tgn:1000001",
        "tgn:7012149",
        "tgn:7007919",
        "tgn:7029392"
    ],
    "tgn:id":2536516,
    "tgn:name":"Neals Creek",
    "tgn:placetype":[
        "aat:300008706"
    ]
},
  "bbox": [],
  "geometry": {"coordinates":[-78.15,37.3667],"type":"Point"}
}