{
  "id": 7442729,
  "type": "Feature",
  "properties": {
    "tgn:hierarchy":[
        "tgn:7442729",
        "tgn:7002445",
        "tgn:7008114",
        "tgn:1000003",
        "tgn:7008591",
        "tgn:7029392"
    ],
    "tgn:id":7442729,
    "tgn:name:en":"Wallerscote",
    "tgn:placetype":[
        "aat:300008347"
    ]
},
  "bbox": [],
  "geometry": {"coordinates":[-2.533333,53.25],"type":"Point"}
}