{
  "id": 2205761,
  "type": "Feature",
  "properties": {
    "tgn:hierarchy":[
        "tgn:2205761",
        "tgn:1000001",
        "tgn:7012149",
        "tgn:7007158",
        "tgn:2000248",
        "tgn:7029392"
    ],
    "tgn:id":2205761,
    "tgn:name":"Bull Lake",
    "tgn:placetype":[
        "aat:300008680"
    ]
},
  "bbox": [],
  "geometry": {"coordinates":[-108.3833,37.8833],"type":"Point"}
}