{
  "id": 2417808,
  "type": "Feature",
  "properties": {
    "tgn:hierarchy":[
        "tgn:2417808",
        "tgn:1000001",
        "tgn:7012149",
        "tgn:2002384",
        "tgn:7007923",
        "tgn:7029392"
    ],
    "tgn:id":2417808,
    "tgn:name":"Jackson Hole",
    "tgn:placetype":[
        "aat:300386845"
    ]
},
  "bbox": [],
  "geometry": {"coordinates":[-110.6833,43.6833],"type":"Point"}
}