{
  "id": 1026737,
  "type": "Feature",
  "properties": {
    "tgn:hierarchy":[
        "tgn:1026737",
        "tgn:7018239",
        "tgn:1000003",
        "tgn:1000063",
        "tgn:7018236",
        "tgn:7029392"
    ],
    "tgn:id":1026737,
    "tgn:name":"Sint-Pieters-Leeuw",
    "tgn:placetype":[
        "aat:300008347"
    ]
},
  "bbox": [],
  "geometry": {"coordinates":[4.243548,50.779262],"type":"Point"}
}