{
  "id": 7204981,
  "type": "Feature",
  "properties": {
    "tgn:hierarchy":[
        "tgn:7204981",
        "tgn:7003669",
        "tgn:1000003",
        "tgn:7000084",
        "tgn:7029392"
    ],
    "tgn:id":7204981,
    "tgn:name":"Buchberg",
    "tgn:placetype":[
        "aat:300008347"
    ]
},
  "bbox": [],
  "geometry": {"coordinates":[11.95,47.733333],"type":"Point"}
}