{
  "id": 2040008,
  "type": "Feature",
  "properties": {
    "tgn:hierarchy":[
        "tgn:2040008",
        "tgn:1000001",
        "tgn:2000781",
        "tgn:7012149",
        "tgn:7007255",
        "tgn:7029392"
    ],
    "tgn:id":2040008,
    "tgn:name":"Log Lick",
    "tgn:placetype":[
        "aat:300008347",
        "aat:300387210"
    ]
},
  "bbox": [],
  "geometry": {"coordinates":[-84.0167,37.85],"type":"Point"}
}