{
  "id": 1096155,
  "type": "Feature",
  "properties": {
    "tgn:hierarchy":[
        "tgn:1096155",
        "tgn:7000490",
        "tgn:1000006",
        "tgn:7001830",
        "tgn:7029392"
    ],
    "tgn:id":1096155,
    "tgn:name":"Bajool",
    "tgn:placetype":[
        "aat:300008347"
    ]
},
  "bbox": [],
  "geometry": {"coordinates":[150.6667,-23.6167],"type":"Point"}
}