{
  "id": 2262956,
  "type": "Feature",
  "properties": {
    "tgn:hierarchy":[
        "tgn:2262956",
        "tgn:1000001",
        "tgn:2001840",
        "tgn:7012149",
        "tgn:7007825",
        "tgn:7029392"
    ],
    "tgn:id":2262956,
    "tgn:name":"Cowen Branch",
    "tgn:placetype":[
        "aat:300008699"
    ]
},
  "bbox": [],
  "geometry": {"coordinates":[-85.15,35.7333],"type":"Point"}
}