{
  "id": 7157888,
  "type": "Feature",
  "properties": {
    "tgn:hierarchy":[
        "tgn:7157888",
        "tgn:7000096",
        "tgn:1000003",
        "tgn:7000084",
        "tgn:7029392"
    ],
    "tgn:id":7157888,
    "tgn:name":"Kleiner Glietzensee",
    "tgn:placetype":[
        "aat:300008680"
    ]
},
  "bbox": [],
  "geometry": {"coordinates":[13.066667,53.183333],"type":"Point"}
}