{
  "id": 7584765,
  "type": "Feature",
  "properties": {
    "tgn:hierarchy":[
        "tgn:7584765",
        "tgn:1000004",
        "tgn:7000198",
        "tgn:1001894",
        "tgn:7029392"
    ],
    "tgn:id":7584765,
    "tgn:name:en":"Kajrai",
    "tgn:placetype":[
        "aat:300008347"
    ]
},
  "bbox": [],
  "geometry": {"coordinates":[78.150859,24.102183],"type":"Point"}
}