{
  "id": 2783867,
  "type": "Feature",
  "properties": {
    "tgn:hierarchy":[
        "tgn:2783867",
        "tgn:1000001",
        "tgn:7012149",
        "tgn:1002974",
        "tgn:7007251",
        "tgn:7029392"
    ],
    "tgn:id":2783867,
    "tgn:name":"Wyton",
    "tgn:placetype":[
        "aat:300008347"
    ]
},
  "bbox": [],
  "geometry": {"coordinates":[-87.6333,40.1167],"type":"Point"}
}