{
  "id": 2399214,
  "type": "Feature",
  "properties": {
    "tgn:hierarchy":[
        "tgn:2399214",
        "tgn:1000001",
        "tgn:7012149",
        "tgn:2001139",
        "tgn:7007522",
        "tgn:7029392"
    ],
    "tgn:id":2399214,
    "tgn:name":"Horatio",
    "tgn:placetype":[
        "aat:300008347"
    ]
},
  "bbox": [],
  "geometry": {"coordinates":[-90.05,34.4333],"type":"Point"}
}