{
  "id": 2542520,
  "type": "Feature",
  "properties": {
    "tgn:hierarchy":[
        "tgn:2542520",
        "tgn:1000001",
        "tgn:7012149",
        "tgn:2001764",
        "tgn:7007712",
        "tgn:7029392"
    ],
    "tgn:id":2542520,
    "tgn:name":"Noahs Marsh",
    "tgn:placetype":[
        "aat:300008905"
    ]
},
  "bbox": [],
  "geometry": {"coordinates":[-80.75,34.0167],"type":"Point"}
}