{
  "id": 2552511,
  "type": "Feature",
  "properties": {
    "tgn:hierarchy":[
        "tgn:2552511",
        "tgn:7006450",
        "tgn:2000069",
        "tgn:1000001",
        "tgn:7012149",
        "tgn:7029392"
    ],
    "tgn:id":2552511,
    "tgn:name":"Nunavakanukakslak Lake",
    "tgn:placetype":[
        "aat:300008680"
    ]
},
  "bbox": [],
  "geometry": {"coordinates":[-162.35,60.9333],"type":"Point"}
}