{
  "id": 7224192,
  "type": "Feature",
  "properties": {
    "tgn:hierarchy":[
        "tgn:7224192",
        "tgn:7002681",
        "tgn:7001395",
        "tgn:1000003",
        "tgn:1000074",
        "tgn:7029392"
    ],
    "tgn:id":7224192,
    "tgn:name":"\u00c1kra Nis\u00edda",
    "tgn:placetype":[
        "aat:300008850"
    ]
},
  "bbox": [],
  "geometry": {"coordinates":[23.243551,37.586595],"type":"Point"}
}