{
  "id": 7286521,
  "type": "Feature",
  "properties": {
    "tgn:hierarchy":[
        "tgn:7286521",
        "tgn:1001702",
        "tgn:1000049",
        "tgn:1000002",
        "tgn:7029392"
    ],
    "tgn:id":7286521,
    "tgn:name":"Harriet, Bah\u00eda",
    "tgn:placetype":[
        "aat:300132316"
    ]
},
  "bbox": [],
  "geometry": {"coordinates":[-73.766667,-51.766667],"type":"Point"}
}