<<<<<<< HEAD
{
  "id": 2405693,
  "type": "Feature",
  "properties": {
    "tgn:hierarchy":[
        "tgn:2405693",
        "tgn:1000001",
        "tgn:7012149",
        "tgn:2001821",
        "tgn:7007713",
        "tgn:7029392"
    ],
    "tgn:id":2405693,
    "tgn:name":"Hugo Mine",
    "tgn:placetype":[
        "aat:300000390"
    ]
},
  "bbox": [],
  "geometry": {"coordinates":[-103.4167,43.8667],"type":"Point"}
}
=======
{"geometry":{"type":"Point","coordinates":[-103.416700,43.866700]},"type":"Feature","properties":{"hierarchy":["tgn:2405693","tgn:1000001","tgn:7012149","tgn:2001821","tgn:7007713","tgn:7029392"],"placetype":["aat:300000390"],"id":2405693,"name:xx":"Hugo Mine"}}
>>>>>>> 03f74aca74312dbeaf24d7e61306dd6a786dc3d0
