{
  "id": 7476355,
  "type": "Feature",
  "properties": {
    "tgn:hierarchy":[
        "tgn:7476355",
        "tgn:7488858",
        "tgn:1000004",
        "tgn:1000141",
        "tgn:7029392"
    ],
    "tgn:id":7476355,
    "tgn:name":"L\u00fcmei Qiao",
    "tgn:placetype":[
        "aat:300007836"
    ]
},
  "bbox": [],
  "geometry": {"coordinates":[120.694453,23.914534],"type":"Point"}
}