{
  "id": 7566656,
  "type": "Feature",
  "properties": {
    "tgn:hierarchy":[
        "tgn:7566656",
        "tgn:1000004",
        "tgn:7000198",
        "tgn:7016722",
        "tgn:7029392"
    ],
    "tgn:id":7566656,
    "tgn:name:en":"Turka Lahch\u016bra",
    "tgn:placetype":[
        "aat:300167671"
    ]
},
  "bbox": [],
  "geometry": {"coordinates":[79.23032,25.516407],"type":"Point"}
}