{
  "id": 1016903,
  "type": "Feature",
  "properties": {
    "tgn:hierarchy":[
        "tgn:1016903",
        "tgn:7015035",
        "tgn:1000001",
        "tgn:7005870",
        "tgn:7029392"
    ],
    "tgn:id":1016903,
    "tgn:name":"Le Diamant",
    "tgn:placetype":[
        "aat:300008347"
    ]
},
  "bbox": [],
  "geometry": {"coordinates":[-61.0333,14.4833],"type":"Point"}
}