{
  "id": 7007634,
  "type": "Feature",
  "properties": {
    "tgn:hierarchy":[
        "tgn:7007634",
        "tgn:7002444",
        "tgn:1000003",
        "tgn:5000460",
        "tgn:7008591",
        "tgn:7029392"
    ],
    "tgn:id":7007634,
    "tgn:name":"Brig o' Turk",
    "tgn:placetype":[
        "aat:300008347"
    ]
},
  "bbox": [],
  "geometry": {"coordinates":[-4.3667,56.2167],"type":"Point"}
}