{
  "id": 7522271,
  "type": "Feature",
  "properties": {
    "tgn:hierarchy":[
        "tgn:7522271",
        "tgn:7001242",
        "tgn:7001311",
        "tgn:7016833",
        "tgn:7029392"
    ],
    "tgn:id":7522271,
    "tgn:name:en":"Al \u1e28amm\u0101m\u012byah",
    "tgn:placetype":[
        "aat:300008347"
    ]
},
  "bbox": [],
  "geometry": {"coordinates":[31.488167,26.930453],"type":"Point"}
}