{
  "id": 7553354,
  "type": "Feature",
  "properties": {
    "tgn:hierarchy":[
        "tgn:7553354",
        "tgn:1000004",
        "tgn:7000198",
        "tgn:1001882",
        "tgn:7029392"
    ],
    "tgn:id":7553354,
    "tgn:name:en":"New Mangalore",
    "tgn:placetype":[
        "aat:300120599"
    ]
},
  "bbox": [],
  "geometry": {"coordinates":[74.820833,12.927778],"type":"Point"}
}