{
  "id": 7417275,
  "type": "Feature",
  "properties": {
    "tgn:hierarchy":[
        "tgn:7417275",
        "tgn:1000001",
        "tgn:7005591",
        "tgn:7005560",
        "tgn:7029392"
    ],
    "tgn:id":7417275,
    "tgn:name:es":"Cerro Tepexcuintle",
    "tgn:placetype":[
        "aat:300008347"
    ]
},
  "bbox": [],
  "geometry": {"coordinates":[-96.333611,18.156111],"type":"Point"}
}