{
  "id": 2532764,
  "type": "Feature",
  "properties": {
    "tgn:hierarchy":[
        "tgn:2532764",
        "tgn:1000001",
        "tgn:2001331",
        "tgn:7012149",
        "tgn:7007525",
        "tgn:7029392"
    ],
    "tgn:id":2532764,
    "tgn:name":"Murphy Swamp",
    "tgn:placetype":[
        "aat:300008905"
    ]
},
  "bbox": [],
  "geometry": {"coordinates":[-100.8667,42.2833],"type":"Point"}
}