{
  "id": 2726973,
  "type": "Feature",
  "properties": {
    "tgn:hierarchy":[
        "tgn:2726973",
        "tgn:1000001",
        "tgn:7012149",
        "tgn:2000182",
        "tgn:7007157",
        "tgn:7029392"
    ],
    "tgn:id":2726973,
    "tgn:name":"Township Drain",
    "tgn:placetype":[
        "aat:300006075"
    ]
},
  "bbox": [],
  "geometry": {"coordinates":[-115.3167,32.8833],"type":"Point"}
}