{
  "id": 7287387,
  "type": "Feature",
  "properties": {
    "tgn:hierarchy":[
        "tgn:7287387",
        "tgn:7016598",
        "tgn:1000049",
        "tgn:1000002",
        "tgn:7029392"
    ],
    "tgn:id":7287387,
    "tgn:name":"Guacate, Cerros de",
    "tgn:placetype":[
        "aat:300008795"
    ]
},
  "bbox": [],
  "geometry": {"coordinates":[-69.183333,-22.583333],"type":"Point"}
}