{
  "id": 7221605,
  "type": "Feature",
  "properties": {
    "tgn:hierarchy":[
        "tgn:7221605",
        "tgn:7002690",
        "tgn:7012056",
        "tgn:1000003",
        "tgn:1000074",
        "tgn:7029392"
    ],
    "tgn:id":7221605,
    "tgn:name":"Zimvro\u00fa",
    "tgn:placetype":[
        "aat:300008347"
    ]
},
  "bbox": [],
  "geometry": {"coordinates":[23.766667,35.283333],"type":"Point"}
}