{
  "id": 2393958,
  "type": "Feature",
  "properties": {
    "tgn:hierarchy":[
        "tgn:2393958",
        "tgn:1002165",
        "tgn:1000001",
        "tgn:7012149",
        "tgn:7007517",
        "tgn:7029392"
    ],
    "tgn:id":2393958,
    "tgn:name":"Hog Ponds",
    "tgn:placetype":[
        "aat:300008680"
    ]
},
  "bbox": [],
  "geometry": {"coordinates":[-70.45,41.6833],"type":"Point"}
}