{
  "id": 2057322,
  "type": "Feature",
  "properties": {
    "tgn:hierarchy":[
        "tgn:2057322",
        "tgn:1000001",
        "tgn:7012149",
        "tgn:2001132",
        "tgn:7007522",
        "tgn:7029392"
    ],
    "tgn:id":2057322,
    "tgn:name":"Red Banks",
    "tgn:placetype":[
        "aat:300008347"
    ]
},
  "bbox": [],
  "geometry": {"coordinates":[-89.55,34.8167],"type":"Point"}
}