{
  "id": 7188369,
  "type": "Feature",
  "properties": {
    "tgn:hierarchy":[
        "tgn:7188369",
        "tgn:1000003",
        "tgn:7003676",
        "tgn:7000084",
        "tgn:7029392"
    ],
    "tgn:id":7188369,
    "tgn:name":"Emmerthal",
    "tgn:placetype":[
        "aat:300387173"
    ]
},
  "bbox": [],
  "geometry": {"coordinates":[9.383333,52.05],"type":"Point"}
}