<<<<<<< HEAD
{
  "id": 2404730,
  "type": "Feature",
  "properties": {
    "tgn:hierarchy":[
        "tgn:2404730",
        "tgn:1000001",
        "tgn:7012149",
        "tgn:2002250",
        "tgn:7007920",
        "tgn:7029392"
    ],
    "tgn:id":2404730,
    "tgn:name":"Huckleberry Creek",
    "tgn:placetype":[
        "aat:300008706"
    ]
},
  "bbox": [],
  "geometry": {"coordinates":[-117.9167,48.2167],"type":"Point"}
}
=======
{"geometry":{"type":"Point","coordinates":[-117.916700,48.216700]},"type":"Feature","properties":{"hierarchy":["tgn:2404730","tgn:1000001","tgn:7012149","tgn:2002250","tgn:7007920","tgn:7029392"],"placetype":["aat:300008706"],"id":2404730,"name:xx":"Huckleberry Creek"}}
>>>>>>> 03f74aca74312dbeaf24d7e61306dd6a786dc3d0
