{
  "id": 2126611,
  "type": "Feature",
  "properties": {
    "tgn:hierarchy":[
        "tgn:2126611",
        "tgn:7006450",
        "tgn:1000001",
        "tgn:7012149",
        "tgn:2000082",
        "tgn:7029392"
    ],
    "tgn:id":2126611,
    "tgn:name":"Agassiz Mountain",
    "tgn:placetype":[
        "aat:300008798"
    ]
},
  "bbox": [],
  "geometry": {"coordinates":[-131.4833,55.0667],"type":"Point"}
}