{
  "id": 7521360,
  "type": "Feature",
  "properties": {
    "tgn:hierarchy":[
        "tgn:7521360",
        "tgn:7001242",
        "tgn:1001059",
        "tgn:7016833",
        "tgn:7029392"
    ],
    "tgn:id":7521360,
    "tgn:name:en":"Al A\u1e29mad\u012byah",
    "tgn:placetype":[
        "aat:300008347"
    ]
},
  "bbox": [],
  "geometry": {"coordinates":[31.974533,31.19024],"type":"Point"}
}