{
  "id": 2715668,
  "type": "Feature",
  "properties": {
    "tgn:hierarchy":[
        "tgn:2715668",
        "tgn:1000001",
        "tgn:2000198",
        "tgn:7012149",
        "tgn:7007158",
        "tgn:7029392"
    ],
    "tgn:id":2715668,
    "tgn:name":"Terry Lateral",
    "tgn:placetype":[
        "aat:300006075"
    ]
},
  "bbox": [],
  "geometry": {"coordinates":[-105.1167,40.2333],"type":"Point"}
}