{
  "id": 7500109,
  "type": "Feature",
  "properties": {
    "tgn:hierarchy":[
        "tgn:7500109",
        "tgn:7001004",
        "tgn:1000004",
        "tgn:1000141",
        "tgn:7029392"
    ],
    "tgn:id":7500109,
    "tgn:name":"Zhongshan Gaozhong",
    "tgn:placetype":[
        "aat:300006495"
    ]
},
  "bbox": [],
  "geometry": {"coordinates":[120.2941,22.7278],"type":"Point"}
}