{
  "id": 2125170,
  "type": "Feature",
  "properties": {
    "tgn:hierarchy":[
        "tgn:2125170",
        "tgn:1000001",
        "tgn:7012149",
        "tgn:2001821",
        "tgn:7007713",
        "tgn:7029392"
    ],
    "tgn:id":2125170,
    "tgn:name":"Accidental Mine",
    "tgn:placetype":[
        "aat:300000390"
    ]
},
  "bbox": [],
  "geometry": {"coordinates":[-103.7667,43.9667],"type":"Point"}
}