{
  "id": 7352560,
  "type": "Feature",
  "properties": {
    "tgn:hierarchy":[
        "tgn:7352560",
        "tgn:1000001",
        "tgn:7005599",
        "tgn:7005560",
        "tgn:7029392"
    ],
    "tgn:id":7352560,
    "tgn:name":"Amate",
    "tgn:placetype":[
        "aat:300008347"
    ]
},
  "bbox": [],
  "geometry": {"coordinates":[-95.683333,17.966667],"type":"Point"}
}