{
  "id": 2717561,
  "type": "Feature",
  "properties": {
    "tgn:hierarchy":[
        "tgn:2717561",
        "tgn:1000001",
        "tgn:7006451",
        "tgn:7012149",
        "tgn:2000100",
        "tgn:7029392"
    ],
    "tgn:id":2717561,
    "tgn:name":"Thomas Canyon",
    "tgn:placetype":[
        "aat:300008761"
    ]
},
  "bbox": [],
  "geometry": {"coordinates":[-111.5833,31.7667],"type":"Point"}
}