{
  "id": 2206779,
  "type": "Feature",
  "properties": {
    "tgn:hierarchy":[
        "tgn:2206779",
        "tgn:1000001",
        "tgn:7012149",
        "tgn:2001709",
        "tgn:7007708",
        "tgn:7029392"
    ],
    "tgn:id":2206779,
    "tgn:name":"Bullseye Spring",
    "tgn:placetype":[
        "aat:300008697"
    ]
},
  "bbox": [],
  "geometry": {"coordinates":[-119.55,43.8667],"type":"Point"}
}