<<<<<<< HEAD
{
  "id": 2405931,
  "type": "Feature",
  "properties": {
    "tgn:hierarchy":[
        "tgn:2405931",
        "tgn:1000001",
        "tgn:7012149",
        "tgn:2002381",
        "tgn:7007923",
        "tgn:7029392"
    ],
    "tgn:id":2405931,
    "tgn:name":"Hultz Draw",
    "tgn:placetype":[
        "aat:300008761"
    ]
},
  "bbox": [],
  "geometry": {"coordinates":[-107.0833,44.8167],"type":"Point"}
}
=======
{"geometry":{"type":"Point","coordinates":[-107.083300,44.816700]},"type":"Feature","properties":{"hierarchy":["tgn:2405931","tgn:1000001","tgn:7012149","tgn:2002381","tgn:7007923","tgn:7029392"],"placetype":["aat:300008761"],"id":2405931,"name:xx":"Hultz Draw"}}
>>>>>>> 03f74aca74312dbeaf24d7e61306dd6a786dc3d0
