{
  "id": 7557865,
  "type": "Feature",
  "properties": {
    "tgn:hierarchy":[
        "tgn:7557865",
        "tgn:1000004",
        "tgn:7000198",
        "tgn:7016788",
        "tgn:7029392"
    ],
    "tgn:id":7557865,
    "tgn:name:en":"Ranthambhor",
    "tgn:placetype":[
        "aat:300006909"
    ]
},
  "bbox": [],
  "geometry": {"coordinates":[76.454178,26.019031],"type":"Point"}
}