{
  "id": 2033579,
  "type": "Feature",
  "properties": {
    "tgn:hierarchy":[
        "tgn:2033579",
        "tgn:1000001",
        "tgn:7012149",
        "tgn:2000559",
        "tgn:7007252",
        "tgn:7029392"
    ],
    "tgn:id":2033579,
    "tgn:name":"Sandcut",
    "tgn:placetype":[
        "aat:300008347"
    ]
},
  "bbox": [],
  "geometry": {"coordinates":[-87.3167,39.55],"type":"Point"}
}