{
  "id": 7432790,
  "type": "Feature",
  "properties": {
    "tgn:hierarchy":[
        "tgn:7432790",
        "tgn:1000001",
        "tgn:7005599",
        "tgn:7005560",
        "tgn:7029392"
    ],
    "tgn:id":7432790,
    "tgn:name":"Tzicatl\u00e1n",
    "tgn:placetype":[
        "aat:300008347"
    ]
},
  "bbox": [],
  "geometry": {"coordinates":[-98.216667,20.683333],"type":"Point"}
}