{
  "id": 1041958,
  "type": "Feature",
  "properties": {
    "tgn:hierarchy":[
        "tgn:1041958",
        "tgn:7002753",
        "tgn:7002756",
        "tgn:1000003",
        "tgn:1000074",
        "tgn:7029392"
    ],
    "tgn:id":1041958,
    "tgn:name":"Alexandro\u00fapolis",
    "tgn:placetype":[
        "aat:300008347",
        "aat:300008389",
        "aat:300387220",
        "aat:300120599"
    ]
},
  "bbox": [],
  "geometry": {"coordinates":[25.874444,40.8475],"type":"Point"}
}