{
  "id": 2733925,
  "type": "Feature",
  "properties": {
    "tgn:hierarchy":[
        "tgn:2733925",
        "tgn:1000001",
        "tgn:7012149",
        "tgn:2000479",
        "tgn:7007250",
        "tgn:7029392"
    ],
    "tgn:id":2733925,
    "tgn:name":"Turner Peak",
    "tgn:placetype":[
        "aat:300008798"
    ]
},
  "bbox": [],
  "geometry": {"coordinates":[-116.7167,47.55],"type":"Point"}
}