{
  "id": 2688243,
  "type": "Feature",
  "properties": {
    "tgn:hierarchy":[
        "tgn:2688243",
        "tgn:1002538",
        "tgn:1000001",
        "tgn:7012149",
        "tgn:7007239",
        "tgn:7029392"
    ],
    "tgn:id":2688243,
    "tgn:name":"Spruance City",
    "tgn:placetype":[
        "aat:300008347"
    ]
},
  "bbox": [],
  "geometry": {"coordinates":[-75.6167,39.2833],"type":"Point"}
}