{
  "id": 2261764,
  "type": "Feature",
  "properties": {
    "tgn:hierarchy":[
        "tgn:2261764",
        "tgn:1000001",
        "tgn:7012149",
        "tgn:7007919",
        "tgn:7029392"
    ],
    "tgn:id":2261764,
    "tgn:name":"Cove Ridge",
    "tgn:placetype":[
        "aat:300266640"
    ]
},
  "bbox": [],
  "geometry": {"coordinates":[-82.3333,36.65],"type":"Point"}
}