{
  "id": 7357869,
  "type": "Feature",
  "properties": {
    "tgn:hierarchy":[
        "tgn:7357869",
        "tgn:1000001",
        "tgn:7005595",
        "tgn:7005560",
        "tgn:7029392"
    ],
    "tgn:id":7357869,
    "tgn:name":"Las Brisas",
    "tgn:placetype":[
        "aat:300008347"
    ]
},
  "bbox": [],
  "geometry": {"coordinates":[-109.05,25.783333],"type":"Point"}
}