{
  "id": 1042191,
  "type": "Feature",
  "properties": {
    "tgn:hierarchy":[
        "tgn:1042191",
        "tgn:7002716",
        "tgn:7002715",
        "tgn:1000003",
        "tgn:1000074",
        "tgn:7029392"
    ],
    "tgn:id":1042191,
    "tgn:name":"Pol\u00edyiros",
    "tgn:placetype":[
        "aat:300008347",
        "aat:300387220"
    ]
},
  "bbox": [],
  "geometry": {"coordinates":[23.438333,40.374444],"type":"Point"}
}