{
  "id": 1099036,
  "type": "Feature",
  "properties": {
    "tgn:hierarchy":[
        "tgn:1099036",
        "tgn:7000509",
        "tgn:1008380",
        "tgn:1000226",
        "tgn:1000006",
        "tgn:7029392"
    ],
    "tgn:id":1099036,
    "tgn:name:en":"Maketu",
    "tgn:placetype":[
        "aat:300008347"
    ]
},
  "bbox": [],
  "geometry": {"coordinates":[176.45,-37.766667],"type":"Point"}
}