{
  "id": 7267963,
  "type": "Feature",
  "properties": {
    "tgn:concordances":{
        "gn:id":"2750119"
    },
    "tgn:hierarchy":[
        "tgn:7267963",
        "tgn:1000003",
        "tgn:7003635",
        "tgn:7016845",
        "tgn:7029392"
    ],
    "tgn:id":7267963,
    "tgn:name:nl":"Nieuwvliet-Bad",
    "tgn:placetype":[
        "aat:300008347"
    ]
},
  "bbox": [],
  "geometry": {"coordinates":[3.45,51.383333],"type":"Point"}
}