{
  "id": 7342815,
  "type": "Feature",
  "properties": {
    "tgn:hierarchy":[
        "tgn:7342815",
        "tgn:7002815",
        "tgn:1000003",
        "tgn:7002793",
        "tgn:1000095",
        "tgn:7029392"
    ],
    "tgn:id":7342815,
    "tgn:name":"Cargador, Punta del",
    "tgn:placetype":[
        "aat:300386846"
    ]
},
  "bbox": [],
  "geometry": {"coordinates":[0.266667,40.233333],"type":"Point"}
}