{
  "id": 7488942,
  "type": "Feature",
  "properties": {
    "tgn:hierarchy":[
        "tgn:7488942",
        "tgn:1000004",
        "tgn:7491221",
        "tgn:1000141",
        "tgn:7029392"
    ],
    "tgn:id":7488942,
    "tgn:name":"Longtian Cun",
    "tgn:placetype":[
        "aat:300387173"
    ]
},
  "bbox": [],
  "geometry": {"coordinates":[121.15,22.95],"type":"Point"}
}