<<<<<<< HEAD
{
  "id": 7488942,
  "type": "Feature",
  "properties": {
    "tgn:hierarchy":[
        "tgn:7488942",
        "tgn:1000004",
        "tgn:7491221",
        "tgn:1000141",
        "tgn:7029392"
    ],
    "tgn:id":7488942,
    "tgn:name":"Longtian Cun",
    "tgn:placetype":[
        "aat:300387173"
    ]
},
  "bbox": [],
  "geometry": {"coordinates":[121.15,22.95],"type":"Point"}
}
=======
{"geometry":{"type":"Point","coordinates":[121.150000,22.950000]},"type":"Feature","properties":{"hierarchy":["tgn:7488942","tgn:1000004","tgn:7491221","tgn:1000141","tgn:7029392"],"placetype":["aat:300387173"],"id":7488942,"name:xx":"Longtian Cun"}}
>>>>>>> 03f74aca74312dbeaf24d7e61306dd6a786dc3d0
