{
  "id": 7512777,
  "type": "Feature",
  "properties": {
    "tgn:hierarchy":[
        "tgn:7512777",
        "tgn:7520092",
        "tgn:1008380",
        "tgn:1000226",
        "tgn:1000006",
        "tgn:7029392"
    ],
    "tgn:id":7512777,
    "tgn:name:en":"Hereheretanga",
    "tgn:placetype":[
        "aat:300008795"
    ]
},
  "bbox": [],
  "geometry": {"coordinates":[177.816667,-37.733333],"type":"Point"}
}