{
  "id": 2652392,
  "type": "Feature",
  "properties": {
    "tgn:hierarchy":[
        "tgn:2652392",
        "tgn:1000001",
        "tgn:2002150",
        "tgn:7012149",
        "tgn:7007919",
        "tgn:7029392"
    ],
    "tgn:id":2652392,
    "tgn:name":"Seneca Creek",
    "tgn:placetype":[
        "aat:300008706"
    ]
},
  "bbox": [],
  "geometry": {"coordinates":[-79.15,37.2667],"type":"Point"}
}