{
  "id": 2333696,
  "type": "Feature",
  "properties": {
    "tgn:hierarchy":[
        "tgn:2333696",
        "tgn:1000001",
        "tgn:7012149",
        "tgn:2001067",
        "tgn:7007521",
        "tgn:7029392"
    ],
    "tgn:id":2333696,
    "tgn:name":"Foolsgold Lake",
    "tgn:placetype":[
        "aat:300008680"
    ]
},
  "bbox": [],
  "geometry": {"coordinates":[-92.3167,48.0667],"type":"Point"}
}