<<<<<<< HEAD
{
  "id": 2251988,
  "type": "Feature",
  "properties": {
    "tgn:hierarchy":[
        "tgn:2251988",
        "tgn:1000001",
        "tgn:7012149",
        "tgn:2000437",
        "tgn:7007248",
        "tgn:7029392"
    ],
    "tgn:id":2251988,
    "tgn:name":"Concord Creek",
    "tgn:placetype":[
        "aat:300008706"
    ]
},
  "bbox": [],
  "geometry": {"coordinates":[-85.1333,34.7],"type":"Point"}
}
=======
{"geometry":{"type":"Point","coordinates":[-85.133300,34.700000]},"type":"Feature","properties":{"hierarchy":["tgn:2251988","tgn:1000001","tgn:7012149","tgn:2000437","tgn:7007248","tgn:7029392"],"placetype":["aat:300008706"],"id":2251988,"name:xx":"Concord Creek"}}
>>>>>>> 03f74aca74312dbeaf24d7e61306dd6a786dc3d0
