{
  "id": 1051189,
  "type": "Feature",
  "properties": {
    "tgn:hierarchy":[
        "tgn:1051189",
        "tgn:1000003",
        "tgn:7011670",
        "tgn:7006660",
        "tgn:7029392"
    ],
    "tgn:id":1051189,
    "tgn:name":"Chapayevka",
    "tgn:placetype":[
        "aat:300008347"
    ]
},
  "bbox": [],
  "geometry": {"coordinates":[36.3333,47.4833],"type":"Point"}
}