{
  "id": 2279677,
  "type": "Feature",
  "properties": {
    "tgn:hierarchy":[
        "tgn:2279677",
        "tgn:1000001",
        "tgn:7012149",
        "tgn:7029392"
    ],
    "tgn:id":2279677,
    "tgn:name":"Deadmans Hollow",
    "tgn:placetype":[
        "aat:300008761"
    ]
},
  "bbox": [],
  "geometry": {"coordinates":[-87.55,39.9667],"type":"Point"}
}