{
  "id": 1071829,
  "type": "Feature",
  "properties": {
    "tgn:hierarchy":[
        "tgn:1071829",
        "tgn:1000004",
        "tgn:7002077",
        "tgn:1000111",
        "tgn:7029392"
    ],
    "tgn:id":1071829,
    "tgn:name":"Shuangtuozhen",
    "tgn:placetype":[
        "aat:300008347"
    ]
},
  "bbox": [],
  "geometry": {"coordinates":[118.3833,39.4833],"type":"Point"}
}