{
  "id": 2715352,
  "type": "Feature",
  "properties": {
    "tgn:hierarchy":[
        "tgn:2715352",
        "tgn:1000001",
        "tgn:7012149",
        "tgn:2001993",
        "tgn:7007826",
        "tgn:7029392"
    ],
    "tgn:id":2715352,
    "tgn:name":"Terrace",
    "tgn:placetype":[
        "aat:300008347"
    ]
},
  "bbox": [],
  "geometry": {"coordinates":[-96.45,33.6667],"type":"Point"}
}