{
  "id": 2659193,
  "type": "Feature",
  "properties": {
    "tgn:hierarchy":[
        "tgn:2659193",
        "tgn:1000001",
        "tgn:2000199",
        "tgn:7012149",
        "tgn:7007158",
        "tgn:7029392"
    ],
    "tgn:id":2659193,
    "tgn:name":"Shields Gulch",
    "tgn:placetype":[
        "aat:300008761"
    ]
},
  "bbox": [],
  "geometry": {"coordinates":[-106.0333,38.85],"type":"Point"}
}