<<<<<<< HEAD
{
  "id": 2333114,
  "type": "Feature",
  "properties": {
    "tgn:hierarchy":[
        "tgn:2333114",
        "tgn:1000001",
        "tgn:7012149",
        "tgn:2002123",
        "tgn:7007827",
        "tgn:7029392"
    ],
    "tgn:id":2333114,
    "tgn:name":"Flying Dutchman Mine",
    "tgn:placetype":[
        "aat:300000390"
    ]
},
  "bbox": [],
  "geometry": {"coordinates":[-112.5167,39.9167],"type":"Point"}
}
=======
{"geometry":{"type":"Point","coordinates":[-112.516700,39.916700]},"type":"Feature","properties":{"hierarchy":["tgn:2333114","tgn:1000001","tgn:7012149","tgn:2002123","tgn:7007827","tgn:7029392"],"placetype":["aat:300000390"],"id":2333114,"name:xx":"Flying Dutchman Mine"}}
>>>>>>> 03f74aca74312dbeaf24d7e61306dd6a786dc3d0
