{
  "id": 2738488,
  "type": "Feature",
  "properties": {
    "tgn:hierarchy":[
        "tgn:2738488",
        "tgn:1000001",
        "tgn:7012149",
        "tgn:2001141",
        "tgn:7007522",
        "tgn:7029392"
    ],
    "tgn:id":2738488,
    "tgn:name":"Underwood Branch",
    "tgn:placetype":[
        "aat:300008699"
    ]
},
  "bbox": [],
  "geometry": {"coordinates":[-89.05,31.3167],"type":"Point"}
}