{
  "id": 7227673,
  "type": "Feature",
  "properties": {
    "tgn:hierarchy":[
        "tgn:7227673",
        "tgn:7011330",
        "tgn:7002674",
        "tgn:1000003",
        "tgn:1000074",
        "tgn:7029392"
    ],
    "tgn:id":7227673,
    "tgn:name":"Katerg\u00e1ris, Vrachonis\u00edda",
    "tgn:placetype":[
        "aat:300008791"
    ]
},
  "bbox": [],
  "geometry": {"coordinates":[26.257222,36.577778],"type":"Point"}
}