{
  "id": 2305004,
  "type": "Feature",
  "properties": {
    "tgn:hierarchy":[
        "tgn:2305004",
        "tgn:1000001",
        "tgn:7012149",
        "tgn:7007520",
        "tgn:7029392"
    ],
    "tgn:id":2305004,
    "tgn:name":"East Branch Huron River",
    "tgn:placetype":[
        "aat:300008707"
    ]
},
  "bbox": [],
  "geometry": {"coordinates":[-88.0167,46.7333],"type":"Point"}
}