{
  "id": 7218191,
  "type": "Feature",
  "properties": {
    "tgn:hierarchy":[
        "tgn:7218191",
        "tgn:7011161",
        "tgn:7002674",
        "tgn:1000003",
        "tgn:1000074",
        "tgn:7029392"
    ],
    "tgn:id":7218191,
    "tgn:name":"Trach\u00f3nia",
    "tgn:placetype":[
        "aat:300008777"
    ]
},
  "bbox": [],
  "geometry": {"coordinates":[25.945,38.288889],"type":"Point"}
}