{
  "id": 2485136,
  "type": "Feature",
  "properties": {
    "tgn:hierarchy":[
        "tgn:2485136",
        "tgn:1000001",
        "tgn:7012149",
        "tgn:2002292",
        "tgn:7013961",
        "tgn:7029392"
    ],
    "tgn:id":2485136,
    "tgn:name":"Lawford",
    "tgn:placetype":[
        "aat:300008347"
    ]
},
  "bbox": [],
  "geometry": {"coordinates":[-80.9333,39.0667],"type":"Point"}
}