{
  "id": 1030935,
  "type": "Feature",
  "properties": {
    "tgn:hierarchy":[
        "tgn:1030935",
        "tgn:7002445",
        "tgn:1000003",
        "tgn:7008167",
        "tgn:7008591",
        "tgn:7029392"
    ],
    "tgn:id":1030935,
    "tgn:name:en":"Tuxford",
    "tgn:placetype":[
        "aat:300008347",
        "aat:300008375"
    ]
},
  "bbox": [],
  "geometry": {"coordinates":[-0.883333,53.216667],"type":"Point"}
}