{
  "id": 2251368,
  "type": "Feature",
  "properties": {
    "tgn:hierarchy":[
        "tgn:2251368",
        "tgn:1000001",
        "tgn:7012149",
        "tgn:2001305",
        "tgn:7007524",
        "tgn:7029392"
    ],
    "tgn:id":2251368,
    "tgn:name":"Comers Lake",
    "tgn:placetype":[
        "aat:300008680"
    ]
},
  "bbox": [],
  "geometry": {"coordinates":[-104.25,48.8833],"type":"Point"}
}