<<<<<<< HEAD
{
  "id": 2251368,
  "type": "Feature",
  "properties": {
    "tgn:hierarchy":[
        "tgn:2251368",
        "tgn:1000001",
        "tgn:7012149",
        "tgn:2001305",
        "tgn:7007524",
        "tgn:7029392"
    ],
    "tgn:id":2251368,
    "tgn:name":"Comers Lake",
    "tgn:placetype":[
        "aat:300008680"
    ]
},
  "bbox": [],
  "geometry": {"coordinates":[-104.25,48.8833],"type":"Point"}
}
=======
{"geometry":{"type":"Point","coordinates":[-104.250000,48.883300]},"type":"Feature","properties":{"hierarchy":["tgn:2251368","tgn:1000001","tgn:7012149","tgn:2001305","tgn:7007524","tgn:7029392"],"placetype":["aat:300008680"],"id":2251368,"name:xx":"Comers Lake"}}
>>>>>>> 03f74aca74312dbeaf24d7e61306dd6a786dc3d0
