{
  "id": 2669536,
  "type": "Feature",
  "properties": {
    "tgn:hierarchy":[
        "tgn:2669536",
        "tgn:1000001",
        "tgn:7012149",
        "tgn:1002965",
        "tgn:7007710",
        "tgn:7029392"
    ],
    "tgn:id":2669536,
    "tgn:name":"Slide Hollow",
    "tgn:placetype":[
        "aat:300008761"
    ]
},
  "bbox": [],
  "geometry": {"coordinates":[-77.15,40.9667],"type":"Point"}
}