{
  "id": 7042896,
  "type": "Feature",
  "properties": {
    "tgn:hierarchy":[
        "tgn:7042896",
        "tgn:1003450",
        "tgn:7007850",
        "tgn:1000003",
        "tgn:1000080",
        "tgn:7029392"
    ],
    "tgn:id":7042896,
    "tgn:name":"Rimendello, Torrente",
    "tgn:placetype":[
        "aat:300008699"
    ]
},
  "bbox": [],
  "geometry": {"coordinates":[15.883333,40.183333],"type":"Point"}
}