{
  "id": 7049257,
  "type": "Feature",
  "properties": {
    "tgn:hierarchy":[
        "tgn:7049257",
        "tgn:7009084",
        "tgn:7003001",
        "tgn:1000003",
        "tgn:1000080",
        "tgn:7029392"
    ],
    "tgn:id":7049257,
    "tgn:name":"Cesacastina",
    "tgn:placetype":[
        "aat:300008347"
    ]
},
  "bbox": [],
  "geometry": {"coordinates":[13.45,42.583333],"type":"Point"}
}