{
  "id": 2279042,
  "type": "Feature",
  "properties": {
    "tgn:hierarchy":[
        "tgn:2279042",
        "tgn:1000001",
        "tgn:7012149",
        "tgn:2001067",
        "tgn:7007521",
        "tgn:7029392"
    ],
    "tgn:id":2279042,
    "tgn:name":"Dead River",
    "tgn:placetype":[
        "aat:300008707"
    ]
},
  "bbox": [],
  "geometry": {"coordinates":[-91.9333,47.95],"type":"Point"}
}