{
  "id": 2468131,
  "type": "Feature",
  "properties": {
    "tgn:hierarchy":[
        "tgn:2468131",
        "tgn:1000001",
        "tgn:2002368",
        "tgn:7012149",
        "tgn:7007923",
        "tgn:7029392"
    ],
    "tgn:id":2468131,
    "tgn:name":"Long Lake",
    "tgn:placetype":[
        "aat:300008680"
    ]
},
  "bbox": [],
  "geometry": {"coordinates":[-106.4667,41.05],"type":"Point"}
}