{
  "id": 1027032,
  "type": "Feature",
  "properties": {
    "tgn:hierarchy":[
        "tgn:1027032",
        "tgn:7027129",
        "tgn:1000003",
        "tgn:7011765",
        "tgn:7029392"
    ],
    "tgn:id":1027032,
    "tgn:name":"\u0160ala",
    "tgn:placetype":[
        "aat:300008347"
    ]
},
  "bbox": [],
  "geometry": {"coordinates":[17.8333,48.1667],"type":"Point"}
}