{
  "id": 2249004,
  "type": "Feature",
  "properties": {
    "tgn:hierarchy":[
        "tgn:2249004",
        "tgn:1000001",
        "tgn:7012149",
        "tgn:1002416",
        "tgn:7007252",
        "tgn:7029392"
    ],
    "tgn:id":2249004,
    "tgn:name":"Cole",
    "tgn:placetype":[
        "aat:300008347"
    ]
},
  "bbox": [],
  "geometry": {"coordinates":[-85.7833,40.4667],"type":"Point"}
}