{
  "id": 2121079,
  "type": "Feature",
  "properties": {
    "tgn:hierarchy":[
        "tgn:2121079",
        "tgn:1000001",
        "tgn:7012149",
        "tgn:2002334",
        "tgn:7007922",
        "tgn:7029392"
    ],
    "tgn:id":2121079,
    "tgn:name":"Dudley",
    "tgn:placetype":[
        "aat:300008347"
    ]
},
  "bbox": [],
  "geometry": {"coordinates":[-89.45,45.3333],"type":"Point"}
}