{
  "id": 2627229,
  "type": "Feature",
  "properties": {
    "tgn:hierarchy":[
        "tgn:2627229",
        "tgn:1000001",
        "tgn:7012149",
        "tgn:2001718",
        "tgn:7007708",
        "tgn:7029392"
    ],
    "tgn:id":2627229,
    "tgn:name":"Rodeo Spring",
    "tgn:placetype":[
        "aat:300008697"
    ]
},
  "bbox": [],
  "geometry": {"coordinates":[-118.05,43.8833],"type":"Point"}
}