{
  "id": 2482407,
  "type": "Feature",
  "properties": {
    "tgn:hierarchy":[
        "tgn:2482407",
        "tgn:1000001",
        "tgn:2001841",
        "tgn:7012149",
        "tgn:7007825",
        "tgn:7029392"
    ],
    "tgn:id":2482407,
    "tgn:name":"Lanier Lake",
    "tgn:placetype":[
        "aat:300006191"
    ]
},
  "bbox": [],
  "geometry": {"coordinates":[-83.9667,35.6333],"type":"Point"}
}