{
  "id": 1073870,
  "type": "Feature",
  "properties": {
    "tgn:hierarchy":[
        "tgn:1073870",
        "tgn:1000004",
        "tgn:7002085",
        "tgn:1000111",
        "tgn:7029392"
    ],
    "tgn:id":1073870,
    "tgn:name":"Zhanglu",
    "tgn:placetype":[
        "aat:300008347"
    ]
},
  "bbox": [],
  "geometry": {"coordinates":[115.5333,36.25],"type":"Point"}
}