{
  "id": 2117045,
  "type": "Feature",
  "properties": {
    "tgn:hierarchy":[
        "tgn:2117045",
        "tgn:1000001",
        "tgn:1002275",
        "tgn:7012149",
        "tgn:7007920",
        "tgn:7029392"
    ],
    "tgn:id":2117045,
    "tgn:name":"Venersborg",
    "tgn:placetype":[
        "aat:300008347",
        "aat:300387210"
    ]
},
  "bbox": [],
  "geometry": {"coordinates":[-122.4167,45.7667],"type":"Point"}
}