{
  "id": 7056026,
  "type": "Feature",
  "properties": {
    "tgn:hierarchy":[
        "tgn:7056026",
        "tgn:7003167",
        "tgn:1000003",
        "tgn:7009760",
        "tgn:1000080",
        "tgn:7029392"
    ],
    "tgn:id":7056026,
    "tgn:name":"Migliorini",
    "tgn:placetype":[
        "aat:300008347"
    ]
},
  "bbox": [],
  "geometry": {"coordinates":[10.766667,44.033333],"type":"Point"}
}