{
  "id": 7294317,
  "type": "Feature",
  "properties": {
    "tgn:hierarchy":[
        "tgn:7294317",
        "tgn:7002829",
        "tgn:1000003",
        "tgn:7002786",
        "tgn:1000095",
        "tgn:7029392"
    ],
    "tgn:id":7294317,
    "tgn:name":"Ver",
    "tgn:placetype":[
        "aat:300008347"
    ]
},
  "bbox": [],
  "geometry": {"coordinates":[-7.316667,42.833333],"type":"Point"}
}