{
  "id": 7593899,
  "type": "Feature",
  "properties": {
    "tgn:hierarchy":[
        "tgn:7593899",
        "tgn:1000004",
        "tgn:1000118",
        "tgn:7029392"
    ],
    "tgn:id":7593899,
    "tgn:name":"Babylonia",
    "tgn:placetype":[
        "aat:300387356"
    ]
},
  "bbox": [],
  "geometry": {"coordinates":[44.42,32.536],"type":"Point"}
}