{
  "id": 2518219,
  "type": "Feature",
  "properties": {
    "tgn:hierarchy":[
        "tgn:2518219",
        "tgn:1000001",
        "tgn:7012149",
        "tgn:7007256",
        "tgn:7029392"
    ],
    "tgn:id":2518219,
    "tgn:name":"Mississippi River Delta",
    "tgn:placetype":[
        "aat:300055621"
    ]
},
  "bbox": [],
  "geometry": {"coordinates":[-89.25,29.1667],"type":"Point"}
}