{
  "id": 7127790,
  "type": "Feature",
  "properties": {
    "tgn:hierarchy":[
        "tgn:7127790",
        "tgn:1000003",
        "tgn:7003688",
        "tgn:7000084",
        "tgn:7029392"
    ],
    "tgn:id":7127790,
    "tgn:name":"N\u00fctschau",
    "tgn:placetype":[
        "aat:300008347"
    ]
},
  "bbox": [],
  "geometry": {"coordinates":[10.333333,53.833333],"type":"Point"}
}