<<<<<<< HEAD
{
  "id": 2404723,
  "type": "Feature",
  "properties": {
    "tgn:hierarchy":[
        "tgn:2404723",
        "tgn:1000001",
        "tgn:7012149",
        "tgn:2001852",
        "tgn:7007825",
        "tgn:7029392"
    ],
    "tgn:id":2404723,
    "tgn:name":"Huckleberry Creek",
    "tgn:placetype":[
        "aat:300008706"
    ]
},
  "bbox": [],
  "geometry": {"coordinates":[-86.05,35.4167],"type":"Point"}
}
=======
{"geometry":{"type":"Point","coordinates":[-86.050000,35.416700]},"type":"Feature","properties":{"hierarchy":["tgn:2404723","tgn:1000001","tgn:7012149","tgn:2001852","tgn:7007825","tgn:7029392"],"placetype":["aat:300008706"],"id":2404723,"name:xx":"Huckleberry Creek"}}
>>>>>>> 03f74aca74312dbeaf24d7e61306dd6a786dc3d0
