{
  "id": 1076225,
  "type": "Feature",
  "properties": {
    "tgn:hierarchy":[
        "tgn:1076225",
        "tgn:1000004",
        "tgn:7000198",
        "tgn:1001977",
        "tgn:7029392"
    ],
    "tgn:id":1076225,
    "tgn:name":"Memari",
    "tgn:placetype":[
        "aat:300008347"
    ]
},
  "bbox": [],
  "geometry": {"coordinates":[88.097486,23.176473],"type":"Point"}
}