<<<<<<< HEAD
{
  "id": 2335567,
  "type": "Feature",
  "properties": {
    "tgn:hierarchy":[
        "tgn:2335567",
        "tgn:1000001",
        "tgn:7006451",
        "tgn:2000092",
        "tgn:7012149",
        "tgn:7029392"
    ],
    "tgn:id":2335567,
    "tgn:name":"Fort Valley Experimental Forest",
    "tgn:placetype":[
        "aat:300008863"
    ]
},
  "bbox": [],
  "geometry": {"coordinates":[-111.7,35.2667],"type":"Point"}
}
=======
{"geometry":{"type":"Point","coordinates":[-111.700000,35.266700]},"type":"Feature","properties":{"hierarchy":["tgn:2335567","tgn:1000001","tgn:7006451","tgn:2000092","tgn:7012149","tgn:7029392"],"placetype":["aat:300008863"],"id":2335567,"name:xx":"Fort Valley Experimental Forest"}}
>>>>>>> 03f74aca74312dbeaf24d7e61306dd6a786dc3d0
