<<<<<<< HEAD
{
  "id": 7375155,
  "type": "Feature",
  "properties": {
    "tgn:hierarchy":[
        "tgn:7375155",
        "tgn:1000001",
        "tgn:7005599",
        "tgn:7005560",
        "tgn:7029392"
    ],
    "tgn:id":7375155,
    "tgn:name":"La Puente",
    "tgn:placetype":[
        "aat:300008347"
    ]
},
  "bbox": [],
  "geometry": {"coordinates":[-95.6,18.533333],"type":"Point"}
}
=======
{"geometry":{"type":"Point","coordinates":[-95.600000,18.533333]},"type":"Feature","properties":{"hierarchy":["tgn:7375155","tgn:1000001","tgn:7005599","tgn:7005560","tgn:7029392"],"placetype":["aat:300008347"],"id":7375155,"name:xx":"La Puente"}}
>>>>>>> 03f74aca74312dbeaf24d7e61306dd6a786dc3d0
