{
  "id": 7385863,
  "type": "Feature",
  "properties": {
    "tgn:hierarchy":[
        "tgn:7385863",
        "tgn:7005583",
        "tgn:1000001",
        "tgn:7005560",
        "tgn:7029392"
    ],
    "tgn:id":7385863,
    "tgn:name":"Pedro V\u00e9lez",
    "tgn:placetype":[
        "aat:300008347"
    ]
},
  "bbox": [],
  "geometry": {"coordinates":[-103.806111,24.241111],"type":"Point"}
}