{
  "id": 7067733,
  "type": "Feature",
  "properties": {
    "tgn:hierarchy":[
        "tgn:7067733",
        "tgn:7003669",
        "tgn:1000003",
        "tgn:7000084",
        "tgn:7029392"
    ],
    "tgn:id":7067733,
    "tgn:name":"Trag",
    "tgn:placetype":[
        "aat:300008347"
    ]
},
  "bbox": [],
  "geometry": {"coordinates":[11.866667,49.75],"type":"Point"}
}