{
  "id": 2160808,
  "type": "Feature",
  "properties": {
    "tgn:hierarchy":[
        "tgn:2160808",
        "tgn:1000001",
        "tgn:7012149",
        "tgn:2001886",
        "tgn:7007825",
        "tgn:7029392"
    ],
    "tgn:id":2160808,
    "tgn:name":"Belew Springs",
    "tgn:placetype":[
        "aat:300008697"
    ]
},
  "bbox": [],
  "geometry": {"coordinates":[-87.4333,35.0333],"type":"Point"}
}