{
  "id": 7273563,
  "type": "Feature",
  "properties": {
    "tgn:hierarchy":[
        "tgn:7273563",
        "tgn:7003615",
        "tgn:1000003",
        "tgn:7016845",
        "tgn:7029392"
    ],
    "tgn:id":7273563,
    "tgn:name:nl":"Hoeve Willemijn",
    "tgn:placetype":[
        "aat:300000206"
    ]
},
  "bbox": [],
  "geometry": {"coordinates":[5.766667,52.816667],"type":"Point"}
}