{
  "id": 7553382,
  "type": "Feature",
  "properties": {
    "tgn:hierarchy":[
        "tgn:7553382",
        "tgn:1000004",
        "tgn:7000198",
        "tgn:1003539",
        "tgn:7029392"
    ],
    "tgn:id":7553382,
    "tgn:name:en":"Maryngksih",
    "tgn:placetype":[
        "aat:300008795"
    ]
},
  "bbox": [],
  "geometry": {"coordinates":[92.647983,25.247807],"type":"Point"}
}