{
  "id": 7348348,
  "type": "Feature",
  "properties": {
    "tgn:hierarchy":[
        "tgn:7348348",
        "tgn:7001155",
        "tgn:1000003",
        "tgn:7002790",
        "tgn:1000095",
        "tgn:7029392"
    ],
    "tgn:id":7348348,
    "tgn:name":"Agua Salada, Barranco de",
    "tgn:placetype":[
        "aat:300266554",
        "aat:300008699"
    ]
},
  "bbox": [],
  "geometry": {"coordinates":[-1.666667,42.266667],"type":"Point"}
}