{
  "id": 2226762,
  "type": "Feature",
  "properties": {
    "tgn:hierarchy":[
        "tgn:2226762",
        "tgn:1000001",
        "tgn:7012149",
        "tgn:2001452",
        "tgn:7007566",
        "tgn:7029392"
    ],
    "tgn:id":2226762,
    "tgn:name":"Cattail Spring",
    "tgn:placetype":[
        "aat:300008697"
    ]
},
  "bbox": [],
  "geometry": {"coordinates":[-107.8167,36.9833],"type":"Point"}
}