{
  "id": 1065128,
  "type": "Feature",
  "properties": {
    "tgn:hierarchy":[
        "tgn:1065128",
        "tgn:1000003",
        "tgn:7015085",
        "tgn:7006670",
        "tgn:7029392"
    ],
    "tgn:id":1065128,
    "tgn:name":"Mojstrana",
    "tgn:placetype":[
        "aat:300008347"
    ]
},
  "bbox": [],
  "geometry": {"coordinates":[13.9333,46.45],"type":"Point"}
}