{
  "id": 2120703,
  "type": "Feature",
  "properties": {
    "tgn:hierarchy":[
        "tgn:2120703",
        "tgn:1000001",
        "tgn:7012149",
        "tgn:2002343",
        "tgn:7007922",
        "tgn:7029392"
    ],
    "tgn:id":2120703,
    "tgn:name":"Bear Creek",
    "tgn:placetype":[
        "aat:300008347"
    ]
},
  "bbox": [],
  "geometry": {"coordinates":[-88.7167,44.5167],"type":"Point"}
}