{
  "id": 2617537,
  "type": "Feature",
  "properties": {
    "tgn:hierarchy":[
        "tgn:2617537",
        "tgn:1000001",
        "tgn:7012149",
        "tgn:7007568",
        "tgn:7029392"
    ],
    "tgn:id":2617537,
    "tgn:name":"Richtmyer Peak",
    "tgn:placetype":[
        "aat:300008798"
    ]
},
  "bbox": [],
  "geometry": {"coordinates":[-74.25,42.3667],"type":"Point"}
}