{
  "id": 7035185,
  "type": "Feature",
  "properties": {
    "tgn:hierarchy":[
        "tgn:7035185",
        "tgn:1003506",
        "tgn:1000003",
        "tgn:7002993",
        "tgn:1000080",
        "tgn:7029392"
    ],
    "tgn:id":7035185,
    "tgn:name":"Zaiaur, Monte",
    "tgn:placetype":[
        "aat:300008795"
    ]
},
  "bbox": [],
  "geometry": {"coordinates":[13.3375,46.310833],"type":"Point"}
}