{
  "id": 2128192,
  "type": "Feature",
  "properties": {
    "tgn:hierarchy":[
        "tgn:2128192",
        "tgn:1000001",
        "tgn:7012149",
        "tgn:1003017",
        "tgn:7007710",
        "tgn:7029392"
    ],
    "tgn:id":2128192,
    "tgn:name":"Albrights Lake",
    "tgn:placetype":[
        "aat:300006191"
    ]
},
  "bbox": [],
  "geometry": {"coordinates":[-79.5333,40.2333],"type":"Point"}
}