{
  "id": 2248133,
  "type": "Feature",
  "properties": {
    "tgn:hierarchy":[
        "tgn:2248133",
        "tgn:1000001",
        "tgn:1002461",
        "tgn:7012149",
        "tgn:7007159",
        "tgn:7029392"
    ],
    "tgn:id":2248133,
    "tgn:name":"Cold Brook Reservoir",
    "tgn:placetype":[
        "aat:300006191"
    ]
},
  "bbox": [],
  "geometry": {"coordinates":[-72.5333,41.6667],"type":"Point"}
}