{
  "id": 2507266,
  "type": "Feature",
  "properties": {
    "tgn:hierarchy":[
        "tgn:2507266",
        "tgn:1000001",
        "tgn:7012149",
        "tgn:1002513",
        "tgn:7007252",
        "tgn:7029392"
    ],
    "tgn:id":2507266,
    "tgn:name":"Metzner Ditch",
    "tgn:placetype":[
        "aat:300006075"
    ]
},
  "bbox": [],
  "geometry": {"coordinates":[-84.9333,40.5167],"type":"Point"}
}