{
  "id": 1122148,
  "type": "Feature",
  "properties": {
    "tgn:hierarchy":[
        "tgn:1122148",
        "tgn:7001242",
        "tgn:1000524",
        "tgn:7016752",
        "tgn:7029392"
    ],
    "tgn:id":1122148,
    "tgn:name":"Bou Sellam, Oued",
    "tgn:placetype":[
        "aat:300008707"
    ]
},
  "bbox": [],
  "geometry": {"coordinates":[4.5667,36.4333],"type":"Point"}
}