<<<<<<< HEAD
{
  "id": 7176697,
  "type": "Feature",
  "properties": {
    "tgn:hierarchy":[
        "tgn:7176697",
        "tgn:7003669",
        "tgn:1000003",
        "tgn:7000084",
        "tgn:7029392"
    ],
    "tgn:id":7176697,
    "tgn:name":"Hallershof",
    "tgn:placetype":[
        "aat:300008347"
    ]
},
  "bbox": [],
  "geometry": {"coordinates":[11.4,49.466667],"type":"Point"}
}
=======
{"geometry":{"type":"Point","coordinates":[11.400000,49.466667]},"type":"Feature","properties":{"hierarchy":["tgn:7176697","tgn:7003669","tgn:1000003","tgn:7000084","tgn:7029392"],"placetype":["aat:300008347"],"id":7176697,"name:xx":"Hallershof"}}
>>>>>>> 03f74aca74312dbeaf24d7e61306dd6a786dc3d0
