{
  "id": 7374353,
  "type": "Feature",
  "properties": {
    "tgn:hierarchy":[
        "tgn:7374353",
        "tgn:7005581",
        "tgn:1000001",
        "tgn:7005560",
        "tgn:7029392"
    ],
    "tgn:id":7374353,
    "tgn:name":"Laguna Prieta, Puerto",
    "tgn:placetype":[
        "aat:300259572"
    ]
},
  "bbox": [],
  "geometry": {"coordinates":[-107.733333,30.366667],"type":"Point"}
}