<<<<<<< HEAD
{
  "id": 7374353,
  "type": "Feature",
  "properties": {
    "tgn:hierarchy":[
        "tgn:7374353",
        "tgn:7005581",
        "tgn:1000001",
        "tgn:7005560",
        "tgn:7029392"
    ],
    "tgn:id":7374353,
    "tgn:name":"Laguna Prieta, Puerto",
    "tgn:placetype":[
        "aat:300259572"
    ]
},
  "bbox": [],
  "geometry": {"coordinates":[-107.733333,30.366667],"type":"Point"}
}
=======
{"geometry":{"type":"Point","coordinates":[-107.733333,30.366667]},"type":"Feature","properties":{"hierarchy":["tgn:7374353","tgn:7005581","tgn:1000001","tgn:7005560","tgn:7029392"],"placetype":["aat:300259572"],"id":7374353,"name:xx":"Laguna Prieta, Puerto"}}
>>>>>>> 03f74aca74312dbeaf24d7e61306dd6a786dc3d0
