{
  "id": 2781665,
  "type": "Feature",
  "properties": {
    "tgn:hierarchy":[
        "tgn:2781665",
        "tgn:1000001",
        "tgn:2001098",
        "tgn:7012149",
        "tgn:7007522",
        "tgn:7029392"
    ],
    "tgn:id":2781665,
    "tgn:name":"Woodruff Creek",
    "tgn:placetype":[
        "aat:300008706"
    ]
},
  "bbox": [],
  "geometry": {"coordinates":[-88.85,33.7167],"type":"Point"}
}