{
  "id": 2677440,
  "type": "Feature",
  "properties": {
    "tgn:hierarchy":[
        "tgn:2677440",
        "tgn:1000001",
        "tgn:7012149",
        "tgn:7007157",
        "tgn:2000184",
        "tgn:7029392"
    ],
    "tgn:id":2677440,
    "tgn:name":"South Caribou",
    "tgn:placetype":[
        "aat:300008798"
    ]
},
  "bbox": [],
  "geometry": {"coordinates":[-121.1667,40.45],"type":"Point"}
}