{
  "id": 2003181,
  "type": "Feature",
  "properties": {
    "tgn:hierarchy":[
        "tgn:2003181",
        "tgn:7002659",
        "tgn:1000001",
        "tgn:7012149",
        "tgn:2000063",
        "tgn:7029392"
    ],
    "tgn:id":2003181,
    "tgn:name":"Cordova",
    "tgn:placetype":[
        "aat:300008347"
    ]
},
  "bbox": [],
  "geometry": {"coordinates":[-87.1833,33.75],"type":"Point"}
}