{
  "id": 2241229,
  "type": "Feature",
  "properties": {
    "tgn:hierarchy":[
        "tgn:2241229",
        "tgn:1000001",
        "tgn:7012149",
        "tgn:2002125",
        "tgn:7007827",
        "tgn:7029392"
    ],
    "tgn:id":2241229,
    "tgn:name":"Clark Hollow",
    "tgn:placetype":[
        "aat:300008761"
    ]
},
  "bbox": [],
  "geometry": {"coordinates":[-111.3667,40.2333],"type":"Point"}
}