{
  "id": 7590304,
  "type": "Feature",
  "properties": {
    "tgn:hierarchy":[
        "tgn:7590304",
        "tgn:1000004",
        "tgn:7000198",
        "tgn:7000799",
        "tgn:7029392"
    ],
    "tgn:id":7590304,
    "tgn:name:en":"Uparla B\u0101n",
    "tgn:placetype":[
        "aat:300008347"
    ]
},
  "bbox": [],
  "geometry": {"coordinates":[74.322997,33.790782],"type":"Point"}
}