{
  "id": 2195024,
  "type": "Feature",
  "properties": {
    "tgn:hierarchy":[
        "tgn:2195024",
        "tgn:1000001",
        "tgn:7012149",
        "tgn:7022217",
        "tgn:7007919",
        "tgn:7029392"
    ],
    "tgn:id":2195024,
    "tgn:name":"Brights Lake",
    "tgn:placetype":[
        "aat:300006191"
    ]
},
  "bbox": [],
  "geometry": {"coordinates":[-76.5333,36.7667],"type":"Point"}
}