{
  "id": 1084118,
  "type": "Feature",
  "properties": {
    "tgn:hierarchy":[
        "tgn:1084118",
        "tgn:1000004",
        "tgn:1001565",
        "tgn:1000135",
        "tgn:7029392"
    ],
    "tgn:id":1084118,
    "tgn:name":"Capas",
    "tgn:placetype":[
        "aat:300008347"
    ]
},
  "bbox": [],
  "geometry": {"coordinates":[120.5833,15.3333],"type":"Point"}
}