{
  "id": 7065701,
  "type": "Feature",
  "properties": {
    "tgn:hierarchy":[
        "tgn:7065701",
        "tgn:1000003",
        "tgn:7003688",
        "tgn:7000084",
        "tgn:7029392"
    ],
    "tgn:id":7065701,
    "tgn:name":"Stellbrokmoor",
    "tgn:placetype":[
        "aat:300386886"
    ]
},
  "bbox": [],
  "geometry": {"coordinates":[10.033333,53.95],"type":"Point"}
}