{
  "id": 7231311,
  "type": "Feature",
  "properties": {
    "tgn:hierarchy":[
        "tgn:7231311",
        "tgn:7002690",
        "tgn:7012056",
        "tgn:1000003",
        "tgn:1000074",
        "tgn:7029392"
    ],
    "tgn:id":7231311,
    "tgn:name":"Khalaso\u00fa",
    "tgn:placetype":[
        "aat:300008347"
    ]
},
  "bbox": [],
  "geometry": {"coordinates":[25.216667,35.116667],"type":"Point"}
}