{
  "id": 7494458,
  "type": "Feature",
  "properties": {
    "tgn:hierarchy":[
        "tgn:7494458",
        "tgn:1000004",
        "tgn:7001014",
        "tgn:1000141",
        "tgn:7029392"
    ],
    "tgn:id":7494458,
    "tgn:name":"Tiantou Qiao",
    "tgn:placetype":[
        "aat:300007836"
    ]
},
  "bbox": [],
  "geometry": {"coordinates":[120.484464,23.702092],"type":"Point"}
}