{
  "id": 7102648,
  "type": "Feature",
  "properties": {
    "tgn:hierarchy":[
        "tgn:7102648",
        "tgn:1000003",
        "tgn:7000094",
        "tgn:7000084",
        "tgn:7029392"
    ],
    "tgn:id":7102648,
    "tgn:name":"Rugensee",
    "tgn:placetype":[
        "aat:300008680"
    ]
},
  "bbox": [],
  "geometry": {"coordinates":[11.383333,53.716667],"type":"Point"}
}