{
  "id": 2158468,
  "type": "Feature",
  "properties": {
    "tgn:hierarchy":[
        "tgn:2158468",
        "tgn:1000001",
        "tgn:7012149",
        "tgn:2001555",
        "tgn:7007709",
        "tgn:7029392"
    ],
    "tgn:id":2158468,
    "tgn:name":"Beaverdam Creek",
    "tgn:placetype":[
        "aat:300008706"
    ]
},
  "bbox": [],
  "geometry": {"coordinates":[-80.85,36.1833],"type":"Point"}
}