{
  "id": 2531331,
  "type": "Feature",
  "properties": {
    "tgn:hierarchy":[
        "tgn:2531331",
        "tgn:2000090",
        "tgn:1000001",
        "tgn:7006451",
        "tgn:7012149",
        "tgn:7029392"
    ],
    "tgn:id":2531331,
    "tgn:name":"Mule Corral Canyon",
    "tgn:placetype":[
        "aat:300008761"
    ]
},
  "bbox": [],
  "geometry": {"coordinates":[-109.7833,33.55],"type":"Point"}
}