{
  "id": 7504897,
  "type": "Feature",
  "properties": {
    "tgn:hierarchy":[
        "tgn:7504897",
        "tgn:1009227",
        "tgn:1000226",
        "tgn:7016822",
        "tgn:1000006",
        "tgn:7029392"
    ],
    "tgn:id":7504897,
    "tgn:name:en":"Forgotten Peak",
    "tgn:placetype":[
        "aat:300008798"
    ]
},
  "bbox": [],
  "geometry": {"coordinates":[166.866667,-46.05],"type":"Point"}
}