{
  "id": 7158711,
  "type": "Feature",
  "properties": {
    "tgn:hierarchy":[
        "tgn:7158711",
        "tgn:7003692",
        "tgn:1000003",
        "tgn:7000084",
        "tgn:7029392"
    ],
    "tgn:id":7158711,
    "tgn:name":"Hohenstra\u00dfen",
    "tgn:placetype":[
        "aat:300008347"
    ]
},
  "bbox": [],
  "geometry": {"coordinates":[9.533333,49.083333],"type":"Point"}
}