<<<<<<< HEAD
{
  "id": 7028986,
  "type": "Feature",
  "properties": {
    "tgn:hierarchy":[
        "tgn:7028986",
        "tgn:7002445",
        "tgn:1000003",
        "tgn:7019064",
        "tgn:7008591",
        "tgn:7029392"
    ],
    "tgn:id":7028986,
    "tgn:name":"Woodthorpe",
    "tgn:placetype":[
        "aat:300008347",
        "aat:300000874"
    ]
},
  "bbox": [],
  "geometry": {"coordinates":[-1.118,53.934],"type":"Point"}
}
=======
{"geometry":{"type":"Point","coordinates":[-1.118000,53.934000]},"type":"Feature","properties":{"hierarchy":["tgn:7028986","tgn:7002445","tgn:1000003","tgn:7019064","tgn:7008591","tgn:7029392"],"placetype":["aat:300008347","aat:300000874"],"id":7028986,"name:xx":"Woodthorpe"}}
>>>>>>> 03f74aca74312dbeaf24d7e61306dd6a786dc3d0
