{
  "id": 2355866,
  "type": "Feature",
  "properties": {
    "tgn:hierarchy":[
        "tgn:2355866",
        "tgn:1000001",
        "tgn:7012149",
        "tgn:7007705",
        "tgn:7029392"
    ],
    "tgn:id":2355866,
    "tgn:name":"Goose Lake",
    "tgn:placetype":[
        "aat:300008680"
    ]
},
  "bbox": [],
  "geometry": {"coordinates":[-97.85,47.2167],"type":"Point"}
}