{
  "id": 7589364,
  "type": "Feature",
  "properties": {
    "tgn:hierarchy":[
        "tgn:7589364",
        "tgn:1000004",
        "tgn:7000198",
        "tgn:7000799",
        "tgn:7029392"
    ],
    "tgn:id":7589364,
    "tgn:name:en":"Khajurla",
    "tgn:placetype":[
        "aat:300008347"
    ]
},
  "bbox": [],
  "geometry": {"coordinates":[74.201611,33.352077],"type":"Point"}
}