{
  "id": 7590569,
  "type": "Feature",
  "properties": {
    "tgn:hierarchy":[
        "tgn:7590569",
        "tgn:1000004",
        "tgn:7000198",
        "tgn:7000799",
        "tgn:7029392"
    ],
    "tgn:id":7590569,
    "tgn:name:en":"Kh\u0101ra ki Gali",
    "tgn:placetype":[
        "aat:300259572"
    ]
},
  "bbox": [],
  "geometry": {"coordinates":[74.411019,33.852611],"type":"Point"}
}