{
  "id": 2436303,
  "type": "Feature",
  "properties": {
    "tgn:hierarchy":[
        "tgn:2436303",
        "tgn:2001837",
        "tgn:1000001",
        "tgn:7012149",
        "tgn:7007825",
        "tgn:7029392"
    ],
    "tgn:id":2436303,
    "tgn:name":"Khotan",
    "tgn:placetype":[
        "aat:300008347"
    ]
},
  "bbox": [],
  "geometry": {"coordinates":[-84.3333,36.0667],"type":"Point"}
}