{
  "id": 2443902,
  "type": "Feature",
  "properties": {
    "tgn:hierarchy":[
        "tgn:2443902",
        "tgn:1000001",
        "tgn:7012149",
        "tgn:2001439",
        "tgn:7007566",
        "tgn:7029392"
    ],
    "tgn:id":2443902,
    "tgn:name":"La Pompa Draw",
    "tgn:placetype":[
        "aat:300008761"
    ]
},
  "bbox": [],
  "geometry": {"coordinates":[-104.1167,35.9167],"type":"Point"}
}