{
  "id": 2699480,
  "type": "Feature",
  "properties": {
    "tgn:hierarchy":[
        "tgn:2699480",
        "tgn:1000001",
        "tgn:2001430",
        "tgn:7012149",
        "tgn:7007566",
        "tgn:7029392"
    ],
    "tgn:id":2699480,
    "tgn:name":"Strong Tank",
    "tgn:placetype":[
        "aat:300006191"
    ]
},
  "bbox": [],
  "geometry": {"coordinates":[-105.3167,32.5167],"type":"Point"}
}