{
  "id": 2555467,
  "type": "Feature",
  "properties": {
    "tgn:hierarchy":[
        "tgn:2555467",
        "tgn:1000001",
        "tgn:7012149",
        "tgn:2000433",
        "tgn:7007248",
        "tgn:7029392"
    ],
    "tgn:id":2555467,
    "tgn:name":"Odum Lake",
    "tgn:placetype":[
        "aat:300006191"
    ]
},
  "bbox": [],
  "geometry": {"coordinates":[-83.5167,31.6167],"type":"Point"}
}