{
  "id": 2422142,
  "type": "Feature",
  "properties": {
    "tgn:hierarchy":[
        "tgn:2422142",
        "tgn:1000001",
        "tgn:7012149",
        "tgn:2001750",
        "tgn:7007712",
        "tgn:7029392"
    ],
    "tgn:id":2422142,
    "tgn:name":"Jim Lewis Bay",
    "tgn:placetype":[
        "aat:300008905"
    ]
},
  "bbox": [],
  "geometry": {"coordinates":[-79.1167,34.1667],"type":"Point"}
}