{
  "id": 7318965,
  "type": "Feature",
  "properties": {
    "tgn:hierarchy":[
        "tgn:7318965",
        "tgn:7016598",
        "tgn:1000049",
        "tgn:1000002",
        "tgn:7029392"
    ],
    "tgn:id":7318965,
    "tgn:name":"Arenoso, Cerro",
    "tgn:placetype":[
        "aat:300008795"
    ]
},
  "bbox": [],
  "geometry": {"coordinates":[-67.483333,-23.383333],"type":"Point"}
}