{
  "id": 7464079,
  "type": "Feature",
  "properties": {
    "tgn:hierarchy":[
        "tgn:7464079",
        "tgn:7002443",
        "tgn:1000003",
        "tgn:7018993",
        "tgn:7008591",
        "tgn:7029392"
    ],
    "tgn:id":7464079,
    "tgn:name:en":"Bais Bank",
    "tgn:placetype":[
        "aat:300386970"
    ]
},
  "bbox": [],
  "geometry": {"coordinates":[-5.416667,51.95],"type":"Point"}
}