{
  "id": 1067984,
  "type": "Feature",
  "properties": {
    "tgn:hierarchy":[
        "tgn:1067984",
        "tgn:1000004",
        "tgn:7018118",
        "tgn:1000111",
        "tgn:7029392"
    ],
    "tgn:id":1067984,
    "tgn:name":"Fangniu",
    "tgn:placetype":[
        "aat:300008347"
    ]
},
  "bbox": [],
  "geometry": {"coordinates":[100.4167,27.6667],"type":"Point"}
}