{
  "id": 7049016,
  "type": "Feature",
  "properties": {
    "tgn:hierarchy":[
        "tgn:7049016",
        "tgn:7003013",
        "tgn:7003005",
        "tgn:1000003",
        "tgn:1000080",
        "tgn:7029392"
    ],
    "tgn:id":7049016,
    "tgn:name":"Casa Balzano",
    "tgn:placetype":[
        "aat:300008347"
    ]
},
  "bbox": [],
  "geometry": {"coordinates":[14.433333,40.783333],"type":"Point"}
}