{
  "id": 7566143,
  "type": "Feature",
  "properties": {
    "tgn:hierarchy":[
        "tgn:7566143",
        "tgn:1000004",
        "tgn:7000198",
        "tgn:1001977",
        "tgn:7029392"
    ],
    "tgn:id":7566143,
    "tgn:name:en":"Idalghutu",
    "tgn:placetype":[
        "aat:300008347"
    ]
},
  "bbox": [],
  "geometry": {"coordinates":[89.865908,26.40534],"type":"Point"}
}