{
  "id": 7407734,
  "type": "Feature",
  "properties": {
    "tgn:hierarchy":[
        "tgn:7407734",
        "tgn:1000001",
        "tgn:7005590",
        "tgn:7005560",
        "tgn:7029392"
    ],
    "tgn:id":7407734,
    "tgn:name":"Fronteras",
    "tgn:placetype":[
        "aat:300008347"
    ]
},
  "bbox": [],
  "geometry": {"coordinates":[-101.158333,19.166667],"type":"Point"}
}