{
  "id": 2315071,
  "type": "Feature",
  "properties": {
    "tgn:hierarchy":[
        "tgn:2315071",
        "tgn:1000001",
        "tgn:1002665",
        "tgn:7012149",
        "tgn:7007517",
        "tgn:7029392"
    ],
    "tgn:id":2315071,
    "tgn:name":"Ell Pond",
    "tgn:placetype":[
        "aat:300008680"
    ]
},
  "bbox": [],
  "geometry": {"coordinates":[-71.0667,42.45],"type":"Point"}
}