<<<<<<< HEAD
{
  "id": 7022811,
  "type": "Feature",
  "properties": {
    "tgn:hierarchy":[
        "tgn:7022811",
        "tgn:1000001",
        "tgn:7012149",
        "tgn:7007157",
        "tgn:7029392"
    ],
    "tgn:id":7022811,
    "tgn:name":"Diamond Ravine",
    "tgn:placetype":[
        "aat:300008761"
    ]
},
  "bbox": [],
  "geometry": {"coordinates":[-121.05,39.6167],"type":"Point"}
}
=======
{"geometry":{"type":"Point","coordinates":[-121.050000,39.616700]},"type":"Feature","properties":{"hierarchy":["tgn:7022811","tgn:1000001","tgn:7012149","tgn:7007157","tgn:7029392"],"placetype":["aat:300008761"],"id":7022811,"name:xx":"Diamond Ravine"}}
>>>>>>> 03f74aca74312dbeaf24d7e61306dd6a786dc3d0
