{
  "id": 7209840,
  "type": "Feature",
  "properties": {
    "tgn:hierarchy":[
        "tgn:7209840",
        "tgn:7003669",
        "tgn:1000003",
        "tgn:7000084",
        "tgn:7029392"
    ],
    "tgn:id":7209840,
    "tgn:name":"B\u00e4renhaupt",
    "tgn:placetype":[
        "aat:300008795"
    ]
},
  "bbox": [],
  "geometry": {"coordinates":[11.433333,47.633333],"type":"Point"}
}