{
  "id": 2768268,
  "type": "Feature",
  "properties": {
    "tgn:hierarchy":[
        "tgn:2768268",
        "tgn:1000001",
        "tgn:7012149",
        "tgn:2002068",
        "tgn:7007826",
        "tgn:7029392"
    ],
    "tgn:id":2768268,
    "tgn:name":"Whites Point",
    "tgn:placetype":[
        "aat:300008850"
    ]
},
  "bbox": [],
  "geometry": {"coordinates":[-97.4667,27.85],"type":"Point"}
}