<<<<<<< HEAD
{
  "id": 2768268,
  "type": "Feature",
  "properties": {
    "tgn:hierarchy":[
        "tgn:2768268",
        "tgn:1000001",
        "tgn:7012149",
        "tgn:2002068",
        "tgn:7007826",
        "tgn:7029392"
    ],
    "tgn:id":2768268,
    "tgn:name":"Whites Point",
    "tgn:placetype":[
        "aat:300008850"
    ]
},
  "bbox": [],
  "geometry": {"coordinates":[-97.4667,27.85],"type":"Point"}
}
=======
{"geometry":{"type":"Point","coordinates":[-97.466700,27.850000]},"type":"Feature","properties":{"hierarchy":["tgn:2768268","tgn:1000001","tgn:7012149","tgn:2002068","tgn:7007826","tgn:7029392"],"placetype":["aat:300008850"],"id":2768268,"name:xx":"Whites Point"}}
>>>>>>> 03f74aca74312dbeaf24d7e61306dd6a786dc3d0
