{
  "id": 7219137,
  "type": "Feature",
  "properties": {
    "tgn:hierarchy":[
        "tgn:7219137",
        "tgn:7011163",
        "tgn:7002674",
        "tgn:1000003",
        "tgn:1000074",
        "tgn:7029392"
    ],
    "tgn:id":7219137,
    "tgn:name":"Megalon\u00edsi Gavath\u00e1, Vrachonis\u00edda",
    "tgn:placetype":[
        "aat:300008791"
    ]
},
  "bbox": [],
  "geometry": {"coordinates":[25.982778,39.286389],"type":"Point"}
}