{
  "id": 7590144,
  "type": "Feature",
  "properties": {
    "tgn:hierarchy":[
        "tgn:7590144",
        "tgn:1000004",
        "tgn:7000198",
        "tgn:7000799",
        "tgn:7029392"
    ],
    "tgn:id":7590144,
    "tgn:name:en":"Molsar",
    "tgn:placetype":[
        "aat:300008347"
    ]
},
  "bbox": [],
  "geometry": {"coordinates":[74.316667,33.875],"type":"Point"}
}