<<<<<<< HEAD
{
  "id": 2764830,
  "type": "Feature",
  "properties": {
    "tgn:hierarchy":[
        "tgn:2764830",
        "tgn:1000001",
        "tgn:7012149",
        "tgn:1002938",
        "tgn:7007252",
        "tgn:7029392"
    ],
    "tgn:id":2764830,
    "tgn:name":"Whiskey Hollow",
    "tgn:placetype":[
        "aat:300008761"
    ]
},
  "bbox": [],
  "geometry": {"coordinates":[-85.1167,38.7167],"type":"Point"}
}
=======
{"geometry":{"type":"Point","coordinates":[-85.116700,38.716700]},"type":"Feature","properties":{"hierarchy":["tgn:2764830","tgn:1000001","tgn:7012149","tgn:1002938","tgn:7007252","tgn:7029392"],"placetype":["aat:300008761"],"id":2764830,"name:xx":"Whiskey Hollow"}}
>>>>>>> 03f74aca74312dbeaf24d7e61306dd6a786dc3d0
