{
  "id": 1080703,
  "type": "Feature",
  "properties": {
    "tgn:hierarchy":[
        "tgn:1080703",
        "tgn:1000004",
        "tgn:7000894",
        "tgn:1001032",
        "tgn:1000120",
        "tgn:7029392"
    ],
    "tgn:id":1080703,
    "tgn:name":"Machida-shi",
    "tgn:placetype":[
        "aat:300008347"
    ]
},
  "bbox": [],
  "geometry": {"coordinates":[139.4167,35.5667],"type":"Point"}
}