{
  "id": 2309679,
  "type": "Feature",
  "properties": {
    "tgn:hierarchy":[
        "tgn:2309679",
        "tgn:1000001",
        "tgn:7012149",
        "tgn:2000203",
        "tgn:7007158",
        "tgn:7029392"
    ],
    "tgn:id":2309679,
    "tgn:name":"Eastdale Canal Number 2",
    "tgn:placetype":[
        "aat:300006075"
    ]
},
  "bbox": [],
  "geometry": {"coordinates":[-105.5333,37.0333],"type":"Point"}
}