{
  "id": 7228211,
  "type": "Feature",
  "properties": {
    "tgn:hierarchy":[
        "tgn:7228211",
        "tgn:7002681",
        "tgn:7001395",
        "tgn:1000003",
        "tgn:1000074",
        "tgn:7029392"
    ],
    "tgn:id":7228211,
    "tgn:name":"Limni\u00f3niza, \u00d3rmos",
    "tgn:placetype":[
        "aat:300132316"
    ]
},
  "bbox": [],
  "geometry": {"coordinates":[23.511094,37.33835],"type":"Point"}
}