{
  "id": 2500316,
  "type": "Feature",
  "properties": {
    "tgn:hierarchy":[
        "tgn:2500316",
        "tgn:1000001",
        "tgn:7012149",
        "tgn:2001895",
        "tgn:7007825",
        "tgn:7029392"
    ],
    "tgn:id":2500316,
    "tgn:name":"McDaniel Hollow",
    "tgn:placetype":[
        "aat:300008761"
    ]
},
  "bbox": [],
  "geometry": {"coordinates":[-86.85,35.3833],"type":"Point"}
}