{
  "id": 2479454,
  "type": "Feature",
  "properties": {
    "tgn:hierarchy":[
        "tgn:2479454",
        "tgn:1000001",
        "tgn:7012149",
        "tgn:2000963",
        "tgn:7007520",
        "tgn:7029392"
    ],
    "tgn:id":2479454,
    "tgn:name":"Lahti Creek",
    "tgn:placetype":[
        "aat:300008706"
    ]
},
  "bbox": [],
  "geometry": {"coordinates":[-88.4167,47.05],"type":"Point"}
}