{
  "id": 2572277,
  "type": "Feature",
  "properties": {
    "tgn:hierarchy":[
        "tgn:2572277",
        "tgn:1000001",
        "tgn:7012149",
        "tgn:2001206",
        "tgn:7007523",
        "tgn:7029392"
    ],
    "tgn:id":2572277,
    "tgn:name":"Peace Valley Draft",
    "tgn:placetype":[
        "aat:300008761"
    ]
},
  "bbox": [],
  "geometry": {"coordinates":[-91.7667,36.8167],"type":"Point"}
}