{
  "id": 2347615,
  "type": "Feature",
  "properties": {
    "tgn:hierarchy":[
        "tgn:2347615",
        "tgn:1000001",
        "tgn:2000922",
        "tgn:7012149",
        "tgn:7007515",
        "tgn:7029392"
    ],
    "tgn:id":2347615,
    "tgn:name":"Georges Brook",
    "tgn:placetype":[
        "aat:300008699"
    ]
},
  "bbox": [],
  "geometry": {"coordinates":[-68.25,44.6167],"type":"Point"}
}