<<<<<<< HEAD
{
  "id": 7119193,
  "type": "Feature",
  "properties": {
    "tgn:hierarchy":[
        "tgn:7119193",
        "tgn:7003669",
        "tgn:1000003",
        "tgn:7000084",
        "tgn:7029392"
    ],
    "tgn:id":7119193,
    "tgn:name":"Perfall",
    "tgn:placetype":[
        "aat:300000206"
    ]
},
  "bbox": [],
  "geometry": {"coordinates":[12.25,48.016667],"type":"Point"}
}
=======
{"geometry":{"type":"Point","coordinates":[12.250000,48.016667]},"type":"Feature","properties":{"hierarchy":["tgn:7119193","tgn:7003669","tgn:1000003","tgn:7000084","tgn:7029392"],"placetype":["aat:300000206"],"id":7119193,"name:xx":"Perfall"}}
>>>>>>> 03f74aca74312dbeaf24d7e61306dd6a786dc3d0
