{
  "id": 2275855,
  "type": "Feature",
  "properties": {
    "tgn:hierarchy":[
        "tgn:2275855",
        "tgn:1000001",
        "tgn:7012149",
        "tgn:2001923",
        "tgn:7007825",
        "tgn:7029392"
    ],
    "tgn:id":2275855,
    "tgn:name":"Dark Hollow",
    "tgn:placetype":[
        "aat:300008761"
    ]
},
  "bbox": [],
  "geometry": {"coordinates":[-83.9167,36.25],"type":"Point"}
}