{
  "id": 2160487,
  "type": "Feature",
  "properties": {
    "tgn:hierarchy":[
        "tgn:2160487",
        "tgn:1000001",
        "tgn:1002934",
        "tgn:7012149",
        "tgn:7007565",
        "tgn:7029392"
    ],
    "tgn:id":2160487,
    "tgn:name":"Beerskill",
    "tgn:placetype":[
        "aat:300008699"
    ]
},
  "bbox": [],
  "geometry": {"coordinates":[-74.75,41.2667],"type":"Point"}
}