<<<<<<< HEAD
{
  "id": 2763734,
  "type": "Feature",
  "properties": {
    "tgn:hierarchy":[
        "tgn:2763734",
        "tgn:1000001",
        "tgn:7012149",
        "tgn:7029392"
    ],
    "tgn:id":2763734,
    "tgn:name":"Whartenby Creek",
    "tgn:placetype":[
        "aat:300008706"
    ]
},
  "bbox": [],
  "geometry": {"coordinates":[-96.5667,36.9833],"type":"Point"}
}
=======
{"geometry":{"type":"Point","coordinates":[-96.566700,36.983300]},"type":"Feature","properties":{"hierarchy":["tgn:2763734","tgn:1000001","tgn:7012149","tgn:7029392"],"placetype":["aat:300008706"],"id":2763734,"name:xx":"Whartenby Creek"}}
>>>>>>> 03f74aca74312dbeaf24d7e61306dd6a786dc3d0
