{
  "id": 7563681,
  "type": "Feature",
  "properties": {
    "tgn:hierarchy":[
        "tgn:7563681",
        "tgn:1000004",
        "tgn:7000198",
        "tgn:7016722",
        "tgn:7029392"
    ],
    "tgn:id":7563681,
    "tgn:name:en":"Baghr\u0101jan",
    "tgn:placetype":[
        "aat:300167671"
    ]
},
  "bbox": [],
  "geometry": {"coordinates":[79.466413,25.251692],"type":"Point"}
}