<<<<<<< HEAD
{
  "id": 2154758,
  "type": "Feature",
  "properties": {
    "tgn:hierarchy":[
        "tgn:2154758",
        "tgn:1000001",
        "tgn:7012149",
        "tgn:1002873",
        "tgn:7007568",
        "tgn:7029392"
    ],
    "tgn:id":2154758,
    "tgn:name":"Bear Gulch Pond",
    "tgn:placetype":[
        "aat:300006191"
    ]
},
  "bbox": [],
  "geometry": {"coordinates":[-74.5833,42.5833],"type":"Point"}
}
=======
{"geometry":{"type":"Point","coordinates":[-74.583300,42.583300]},"type":"Feature","properties":{"hierarchy":["tgn:2154758","tgn:1000001","tgn:7012149","tgn:1002873","tgn:7007568","tgn:7029392"],"placetype":["aat:300006191"],"id":2154758,"name:xx":"Bear Gulch Pond"}}
>>>>>>> 03f74aca74312dbeaf24d7e61306dd6a786dc3d0
