{
  "id": 7393891,
  "type": "Feature",
  "properties": {
    "tgn:hierarchy":[
        "tgn:7393891",
        "tgn:1000001",
        "tgn:7005595",
        "tgn:7005560",
        "tgn:7029392"
    ],
    "tgn:id":7393891,
    "tgn:name":"San Jos\u00e9",
    "tgn:placetype":[
        "aat:300008347"
    ]
},
  "bbox": [],
  "geometry": {"coordinates":[-108.439722,26.5475],"type":"Point"}
}