{
  "id": 1101215,
  "type": "Feature",
  "properties": {
    "tgn:hierarchy":[
        "tgn:1101215",
        "tgn:1000001",
        "tgn:7012149",
        "tgn:7007157",
        "tgn:1002828",
        "tgn:7029392"
    ],
    "tgn:id":1101215,
    "tgn:name":"Prado Dam",
    "tgn:placetype":[
        "aat:300006084"
    ]
},
  "bbox": [],
  "geometry": {"coordinates":[-117.6333,33.8833],"type":"Point"}
}