{
  "id": 2785435,
  "type": "Feature",
  "properties": {
    "tgn:hierarchy":[
        "tgn:2785435",
        "tgn:1000001",
        "tgn:7012149",
        "tgn:2001537",
        "tgn:7007709",
        "tgn:7029392"
    ],
    "tgn:id":2785435,
    "tgn:name":"Yellowtop Mountain",
    "tgn:placetype":[
        "aat:300008798"
    ]
},
  "bbox": [],
  "geometry": {"coordinates":[-81.8167,35.4833],"type":"Point"}
}