{
  "id": 7178644,
  "type": "Feature",
  "properties": {
    "tgn:hierarchy":[
        "tgn:7178644",
        "tgn:7003669",
        "tgn:1000003",
        "tgn:7000084",
        "tgn:7029392"
    ],
    "tgn:id":7178644,
    "tgn:name":"Hamm\u00fchle",
    "tgn:placetype":[
        "aat:300000206"
    ]
},
  "bbox": [],
  "geometry": {"coordinates":[12.416667,49.166667],"type":"Point"}
}