{
  "id": 7298841,
  "type": "Feature",
  "properties": {
    "tgn:hierarchy":[
        "tgn:7298841",
        "tgn:7002822",
        "tgn:1001647",
        "tgn:1000003",
        "tgn:1000095",
        "tgn:7029392"
    ],
    "tgn:id":7298841,
    "tgn:name":"Tordesilos",
    "tgn:placetype":[
        "aat:300008347"
    ]
},
  "bbox": [],
  "geometry": {"coordinates":[-1.583333,40.666667],"type":"Point"}
}