{
  "id": 2182691,
  "type": "Feature",
  "properties": {
    "tgn:hierarchy":[
        "tgn:2182691",
        "tgn:2001837",
        "tgn:1000001",
        "tgn:7012149",
        "tgn:7007825",
        "tgn:7029392"
    ],
    "tgn:id":2182691,
    "tgn:name":"Blue Spring Branch",
    "tgn:placetype":[
        "aat:300008699"
    ]
},
  "bbox": [],
  "geometry": {"coordinates":[-84.2667,36.0667],"type":"Point"}
}