{
  "id": 2340675,
  "type": "Feature",
  "properties": {
    "tgn:hierarchy":[
        "tgn:2340675",
        "tgn:1000001",
        "tgn:2000952",
        "tgn:7012149",
        "tgn:7007520",
        "tgn:7029392"
    ],
    "tgn:id":2340675,
    "tgn:name":"Frenes, Point aux",
    "tgn:placetype":[
        "aat:300008850"
    ]
},
  "bbox": [],
  "geometry": {"coordinates":[-84.0167,46.1167],"type":"Point"}
}