{
  "id": 2605026,
  "type": "Feature",
  "properties": {
    "tgn:hierarchy":[
        "tgn:2605026",
        "tgn:1000001",
        "tgn:1002359",
        "tgn:7012149",
        "tgn:7007517",
        "tgn:7029392"
    ],
    "tgn:id":2605026,
    "tgn:name":"Raddin Station",
    "tgn:placetype":[
        "aat:300008347"
    ]
},
  "bbox": [],
  "geometry": {"coordinates":[-70.9667,42.45],"type":"Point"}
}