{
  "id": 2488798,
  "type": "Feature",
  "properties": {
    "tgn:hierarchy":[
        "tgn:2488798",
        "tgn:1000001",
        "tgn:7012149",
        "tgn:2001226",
        "tgn:7007523",
        "tgn:7029392"
    ],
    "tgn:id":2488798,
    "tgn:name":"Mailroute Hollow",
    "tgn:placetype":[
        "aat:300008761"
    ]
},
  "bbox": [],
  "geometry": {"coordinates":[-92.45,36.7167],"type":"Point"}
}