{
  "id": 7042972,
  "type": "Feature",
  "properties": {
    "tgn:hierarchy":[
        "tgn:7042972",
        "tgn:1003428",
        "tgn:1000003",
        "tgn:7003120",
        "tgn:1000080",
        "tgn:7029392"
    ],
    "tgn:id":7042972,
    "tgn:name":"Ricaldone",
    "tgn:placetype":[
        "aat:300387198",
        "aat:300265612"
    ]
},
  "bbox": [],
  "geometry": {"coordinates":[8.466667,44.733333],"type":"Point"}
}