{
  "id": 7389883,
  "type": "Feature",
  "properties": {
    "tgn:hierarchy":[
        "tgn:7389883",
        "tgn:1000001",
        "tgn:1001960",
        "tgn:7005560",
        "tgn:7029392"
    ],
    "tgn:id":7389883,
    "tgn:name":"Rancho Pitahayitas",
    "tgn:placetype":[
        "aat:300008347"
    ]
},
  "bbox": [],
  "geometry": {"coordinates":[-109.133333,27.133333],"type":"Point"}
}