{
  "id": 7340961,
  "type": "Feature",
  "properties": {
    "tgn:hierarchy":[
        "tgn:7340961",
        "tgn:7002759",
        "tgn:7008909",
        "tgn:1000003",
        "tgn:1000095",
        "tgn:7029392"
    ],
    "tgn:id":7340961,
    "tgn:name":"Burgas\u00e9",
    "tgn:placetype":[
        "aat:300008347"
    ]
},
  "bbox": [],
  "geometry": {"coordinates":[-0.025788,42.523283],"type":"Point"}
}