<<<<<<< HEAD
{
  "id": 7020750,
  "type": "Feature",
  "properties": {
    "tgn:hierarchy":[
        "tgn:7020750",
        "tgn:1000001",
        "tgn:7012149",
        "tgn:2001310",
        "tgn:7007524",
        "tgn:7029392"
    ],
    "tgn:id":7020750,
    "tgn:name":"Childers Reservoir",
    "tgn:placetype":[
        "aat:300006191"
    ]
},
  "bbox": [],
  "geometry": {"coordinates":[-111.3333,48.5667],"type":"Point"}
}
=======
{"geometry":{"type":"Point","coordinates":[-111.333300,48.566700]},"type":"Feature","properties":{"hierarchy":["tgn:7020750","tgn:1000001","tgn:7012149","tgn:2001310","tgn:7007524","tgn:7029392"],"placetype":["aat:300006191"],"id":7020750,"name:xx":"Childers Reservoir"}}
>>>>>>> 03f74aca74312dbeaf24d7e61306dd6a786dc3d0
