{
  "id": 7530780,
  "type": "Feature",
  "properties": {
    "tgn:hierarchy":[
        "tgn:7530780",
        "tgn:7001242",
        "tgn:7016833",
        "tgn:1001083",
        "tgn:7029392"
    ],
    "tgn:id":7530780,
    "tgn:name":"Fay\u015fal",
    "tgn:placetype":[
        "aat:300007780"
    ]
},
  "bbox": [],
  "geometry": {"coordinates":[31.203959,30.017273],"type":"Point"}
}