{
  "id": 7539887,
  "type": "Feature",
  "properties": {
    "tgn:hierarchy":[
        "tgn:7539887",
        "tgn:7001242",
        "tgn:7016833",
        "tgn:7001312",
        "tgn:7029392"
    ],
    "tgn:id":7539887,
    "tgn:name:en":"S\u00e2m\u00fbl",
    "tgn:placetype":[
        "aat:300008347"
    ]
},
  "bbox": [],
  "geometry": {"coordinates":[31.136417,31.053886],"type":"Point"}
}