<<<<<<< HEAD
{
  "id": 2256158,
  "type": "Feature",
  "properties": {
    "tgn:hierarchy":[
        "tgn:2256158",
        "tgn:1000001",
        "tgn:7012149",
        "tgn:7007919",
        "tgn:7029392"
    ],
    "tgn:id":2256158,
    "tgn:name":"Copper Ridge",
    "tgn:placetype":[
        "aat:300266640"
    ]
},
  "bbox": [],
  "geometry": {"coordinates":[-82.8,36.6167],"type":"Point"}
}
=======
{"geometry":{"type":"Point","coordinates":[-82.800000,36.616700]},"type":"Feature","properties":{"hierarchy":["tgn:2256158","tgn:1000001","tgn:7012149","tgn:7007919","tgn:7029392"],"placetype":["aat:300266640"],"id":2256158,"name:xx":"Copper Ridge"}}
>>>>>>> 03f74aca74312dbeaf24d7e61306dd6a786dc3d0
