{
  "id": 2722220,
  "type": "Feature",
  "properties": {
    "tgn:hierarchy":[
        "tgn:2722220",
        "tgn:1000001",
        "tgn:7012149",
        "tgn:2000226",
        "tgn:7007158",
        "tgn:7029392"
    ],
    "tgn:id":2722220,
    "tgn:name":"Timnath Reservoir",
    "tgn:placetype":[
        "aat:300006191"
    ]
},
  "bbox": [],
  "geometry": {"coordinates":[-104.95,40.7167],"type":"Point"}
}