{
  "id": 7179521,
  "type": "Feature",
  "properties": {
    "tgn:hierarchy":[
        "tgn:7179521",
        "tgn:1000003",
        "tgn:7003676",
        "tgn:7000084",
        "tgn:7029392"
    ],
    "tgn:id":7179521,
    "tgn:name":"Gru\u00dfendorf",
    "tgn:placetype":[
        "aat:300008347"
    ]
},
  "bbox": [],
  "geometry": {"coordinates":[10.716667,52.533333],"type":"Point"}
}