{
  "id": 2351071,
  "type": "Feature",
  "properties": {
    "tgn:hierarchy":[
        "tgn:2351071",
        "tgn:1000001",
        "tgn:1003023",
        "tgn:7012149",
        "tgn:7007516",
        "tgn:7029392"
    ],
    "tgn:id":2351071,
    "tgn:name":"Glass Hill",
    "tgn:placetype":[
        "aat:300008347"
    ]
},
  "bbox": [],
  "geometry": {"coordinates":[-75.4333,38.3833],"type":"Point"}
}