{
  "id": 2581993,
  "type": "Feature",
  "properties": {
    "tgn:hierarchy":[
        "tgn:2581993",
        "tgn:1000001",
        "tgn:7012149",
        "tgn:2000233",
        "tgn:7007158",
        "tgn:7029392"
    ],
    "tgn:id":2581993,
    "tgn:name":"Pine Canyon",
    "tgn:placetype":[
        "aat:300008761"
    ]
},
  "bbox": [],
  "geometry": {"coordinates":[-108.4333,37.1333],"type":"Point"}
}