{
  "id": 7560881,
  "type": "Feature",
  "properties": {
    "tgn:hierarchy":[
        "tgn:7560881",
        "tgn:1000004",
        "tgn:7000198",
        "tgn:7016722",
        "tgn:7029392"
    ],
    "tgn:id":7560881,
    "tgn:name:en":"Muhammadpur Kh\u0101s",
    "tgn:placetype":[
        "aat:300008347"
    ]
},
  "bbox": [],
  "geometry": {"coordinates":[79.467957,27.132547],"type":"Point"}
}