{
  "id": 7388684,
  "type": "Feature",
  "properties": {
    "tgn:hierarchy":[
        "tgn:7388684",
        "tgn:1001836",
        "tgn:1000001",
        "tgn:7005560",
        "tgn:7029392"
    ],
    "tgn:id":7388684,
    "tgn:name":"Punta Cayuco",
    "tgn:placetype":[
        "aat:300008347"
    ]
},
  "bbox": [],
  "geometry": {"coordinates":[-111.666667,24.566667],"type":"Point"}
}