<<<<<<< HEAD
{
  "id": 2765795,
  "type": "Feature",
  "properties": {
    "tgn:hierarchy":[
        "tgn:2765795",
        "tgn:1000001",
        "tgn:7012149",
        "tgn:2002088",
        "tgn:7007826",
        "tgn:7029392"
    ],
    "tgn:id":2765795,
    "tgn:name":"White Draw",
    "tgn:placetype":[
        "aat:300008761"
    ]
},
  "bbox": [],
  "geometry": {"coordinates":[-100.8667,30.1167],"type":"Point"}
}
=======
{"geometry":{"type":"Point","coordinates":[-100.866700,30.116700]},"type":"Feature","properties":{"hierarchy":["tgn:2765795","tgn:1000001","tgn:7012149","tgn:2002088","tgn:7007826","tgn:7029392"],"placetype":["aat:300008761"],"id":2765795,"name:xx":"White Draw"}}
>>>>>>> 03f74aca74312dbeaf24d7e61306dd6a786dc3d0
