{
  "id": 2231684,
  "type": "Feature",
  "properties": {
    "tgn:hierarchy":[
        "tgn:2231684",
        "tgn:7002659",
        "tgn:1000001",
        "tgn:7012149",
        "tgn:2000039",
        "tgn:7029392"
    ],
    "tgn:id":2231684,
    "tgn:name":"Chalybeate Spring",
    "tgn:placetype":[
        "aat:300008697"
    ]
},
  "bbox": [],
  "geometry": {"coordinates":[-87.2333,34.5333],"type":"Point"}
}