<<<<<<< HEAD
{
  "id": 2763188,
  "type": "Feature",
  "properties": {
    "tgn:hierarchy":[
        "tgn:2763188",
        "tgn:1000001",
        "tgn:7012149",
        "tgn:2000879",
        "tgn:7007256",
        "tgn:7029392"
    ],
    "tgn:id":2763188,
    "tgn:name":"Westwego Swamp",
    "tgn:placetype":[
        "aat:300008905"
    ]
},
  "bbox": [],
  "geometry": {"coordinates":[-90.15,29.9],"type":"Point"}
}
=======
{"geometry":{"type":"Point","coordinates":[-90.150000,29.900000]},"type":"Feature","properties":{"hierarchy":["tgn:2763188","tgn:1000001","tgn:7012149","tgn:2000879","tgn:7007256","tgn:7029392"],"placetype":["aat:300008905"],"id":2763188,"name:xx":"Westwego Swamp"}}
>>>>>>> 03f74aca74312dbeaf24d7e61306dd6a786dc3d0
