{
  "id": 7590174,
  "type": "Feature",
  "properties": {
    "tgn:hierarchy":[
        "tgn:7590174",
        "tgn:1000004",
        "tgn:7000198",
        "tgn:7000799",
        "tgn:7029392"
    ],
    "tgn:id":7590174,
    "tgn:name:en":"Khetar Danna",
    "tgn:placetype":[
        "aat:300008347"
    ]
},
  "bbox": [],
  "geometry": {"coordinates":[73.916667,34.080556],"type":"Point"}
}