{
  "id": 2443681,
  "type": "Feature",
  "properties": {
    "tgn:hierarchy":[
        "tgn:2443681",
        "tgn:1000001",
        "tgn:7012149",
        "tgn:2001281",
        "tgn:7007524",
        "tgn:7029392"
    ],
    "tgn:id":2443681,
    "tgn:name":"La Hood Park",
    "tgn:placetype":[
        "aat:300008347"
    ]
},
  "bbox": [],
  "geometry": {"coordinates":[-111.9167,45.85],"type":"Point"}
}