{
  "id": 2568079,
  "type": "Feature",
  "properties": {
    "tgn:hierarchy":[
        "tgn:2568079",
        "tgn:1000001",
        "tgn:7012149",
        "tgn:7007157",
        "tgn:1002858",
        "tgn:7029392"
    ],
    "tgn:id":2568079,
    "tgn:name":"Parayne Hill",
    "tgn:placetype":[
        "aat:300008798"
    ]
},
  "bbox": [],
  "geometry": {"coordinates":[-116.7667,33.2667],"type":"Point"}
}