{
  "id": 2549296,
  "type": "Feature",
  "properties": {
    "tgn:hierarchy":[
        "tgn:2549296",
        "tgn:1000001",
        "tgn:7012149",
        "tgn:7007157",
        "tgn:2000189",
        "tgn:7029392"
    ],
    "tgn:id":2549296,
    "tgn:name":"North Russian Creek",
    "tgn:placetype":[
        "aat:300008706"
    ]
},
  "bbox": [],
  "geometry": {"coordinates":[-123.0167,41.3833],"type":"Point"}
}