{
  "id": 7553167,
  "type": "Feature",
  "properties": {
    "tgn:hierarchy":[
        "tgn:7553167",
        "tgn:1000004",
        "tgn:7000198",
        "tgn:7016694",
        "tgn:7029392"
    ],
    "tgn:id":7553167,
    "tgn:name:en":"P\u0101nchp\u0101ra Nad\u012b",
    "tgn:placetype":[
        "aat:300008699"
    ]
},
  "bbox": [],
  "geometry": {"coordinates":[87.123326,21.514234],"type":"Point"}
}