{
  "id": 7056097,
  "type": "Feature",
  "properties": {
    "tgn:hierarchy":[
        "tgn:7056097",
        "tgn:1000003",
        "tgn:7003151",
        "tgn:7003237",
        "tgn:1000080",
        "tgn:7029392"
    ],
    "tgn:id":7056097,
    "tgn:name":"Mezzana Rabattone",
    "tgn:placetype":[
        "aat:300008347"
    ]
},
  "bbox": [],
  "geometry": {"coordinates":[9.033333,45.083333],"type":"Point"}
}