{
  "id": 7222558,
  "type": "Feature",
  "properties": {
    "tgn:hierarchy":[
        "tgn:7222558",
        "tgn:4003773",
        "tgn:7001395",
        "tgn:1000003",
        "tgn:1000074",
        "tgn:7029392"
    ],
    "tgn:id":7222558,
    "tgn:name":"S\u00edmos",
    "tgn:placetype":[
        "aat:300008347"
    ]
},
  "bbox": [],
  "geometry": {"coordinates":[21.816667,38.533333],"type":"Point"}
}