{
  "id": 1044181,
  "type": "Feature",
  "properties": {
    "tgn:hierarchy":[
        "tgn:1044181",
        "tgn:1000003",
        "tgn:7003141",
        "tgn:7003236",
        "tgn:1000080",
        "tgn:7029392"
    ],
    "tgn:id":1044181,
    "tgn:name":"Cervo",
    "tgn:placetype":[
        "aat:300008347"
    ]
},
  "bbox": [],
  "geometry": {"coordinates":[8.116667,43.916667],"type":"Point"}
}