{
  "id": 2737107,
  "type": "Feature",
  "properties": {
    "tgn:hierarchy":[
        "tgn:2737107",
        "tgn:1000001",
        "tgn:7012149",
        "tgn:2000226",
        "tgn:7007158",
        "tgn:7029392"
    ],
    "tgn:id":2737107,
    "tgn:name":"Two Rivers Lake",
    "tgn:placetype":[
        "aat:300008680"
    ]
},
  "bbox": [],
  "geometry": {"coordinates":[-105.6667,40.3167],"type":"Point"}
}