{
  "id": 7560282,
  "type": "Feature",
  "properties": {
    "tgn:hierarchy":[
        "tgn:7560282",
        "tgn:1000004",
        "tgn:7000198",
        "tgn:7016788",
        "tgn:7029392"
    ],
    "tgn:id":7560282,
    "tgn:name:en":"Ganatpura",
    "tgn:placetype":[
        "aat:300008347"
    ]
},
  "bbox": [],
  "geometry": {"coordinates":[75.731011,26.851037],"type":"Point"}
}