{
  "id": 2723231,
  "type": "Feature",
  "properties": {
    "tgn:hierarchy":[
        "tgn:2723231",
        "tgn:1000001",
        "tgn:7012149",
        "tgn:7007710",
        "tgn:7029392"
    ],
    "tgn:id":2723231,
    "tgn:name":"Toad Creek",
    "tgn:placetype":[
        "aat:300008706"
    ]
},
  "bbox": [],
  "geometry": {"coordinates":[-75.6833,40.4667],"type":"Point"}
}