{
  "id": 2482644,
  "type": "Feature",
  "properties": {
    "tgn:hierarchy":[
        "tgn:2482644",
        "tgn:1000001",
        "tgn:7012149",
        "tgn:2000226",
        "tgn:7007158",
        "tgn:7029392"
    ],
    "tgn:id":2482644,
    "tgn:name":"Laramie Lake",
    "tgn:placetype":[
        "aat:300008680"
    ]
},
  "bbox": [],
  "geometry": {"coordinates":[-105.8333,40.6167],"type":"Point"}
}