{
  "id": 7223764,
  "type": "Feature",
  "properties": {
    "tgn:hierarchy":[
        "tgn:7223764",
        "tgn:7002715",
        "tgn:7002731",
        "tgn:1000003",
        "tgn:1000074",
        "tgn:7029392"
    ],
    "tgn:id":7223764,
    "tgn:name":"P\u00edsona",
    "tgn:placetype":[
        "aat:300008347"
    ]
},
  "bbox": [],
  "geometry": {"coordinates":[23.133333,40.483333],"type":"Point"}
}