{
  "id": 2694084,
  "type": "Feature",
  "properties": {
    "tgn:hierarchy":[
        "tgn:2694084",
        "tgn:1000001",
        "tgn:2000506",
        "tgn:7012149",
        "tgn:7007251",
        "tgn:7029392"
    ],
    "tgn:id":2694084,
    "tgn:name":"Stevens Creek",
    "tgn:placetype":[
        "aat:300008706"
    ]
},
  "bbox": [],
  "geometry": {"coordinates":[-88.7667,37.85],"type":"Point"}
}