{
  "id": 7514685,
  "type": "Feature",
  "properties": {
    "tgn:hierarchy":[
        "tgn:7514685",
        "tgn:1009227",
        "tgn:1000226",
        "tgn:7016822",
        "tgn:1000006",
        "tgn:7029392"
    ],
    "tgn:id":7514685,
    "tgn:name:en":"Chatton",
    "tgn:placetype":[
        "aat:300008347"
    ]
},
  "bbox": [],
  "geometry": {"coordinates":[168.916667,-45.983333],"type":"Point"}
}