{
  "id": 7479979,
  "type": "Feature",
  "properties": {
    "tgn:hierarchy":[
        "tgn:7479979",
        "tgn:1000004",
        "tgn:7490934",
        "tgn:1000141",
        "tgn:7029392"
    ],
    "tgn:id":7479979,
    "tgn:name":"Yangziliao Shan",
    "tgn:placetype":[
        "aat:300387033"
    ]
},
  "bbox": [],
  "geometry": {"coordinates":[120.355509,23.056683],"type":"Point"}
}