{
  "id": 2745445,
  "type": "Feature",
  "properties": {
    "tgn:hierarchy":[
        "tgn:2745445",
        "tgn:1000001",
        "tgn:7016172",
        "tgn:7012149",
        "tgn:2000177",
        "tgn:7029392"
    ],
    "tgn:id":2745445,
    "tgn:name":"Vinity Corner",
    "tgn:placetype":[
        "aat:300008347"
    ]
},
  "bbox": [],
  "geometry": {"coordinates":[-91.7333,35.0667],"type":"Point"}
}