<<<<<<< HEAD
{
  "id": 7488498,
  "type": "Feature",
  "properties": {
    "tgn:hierarchy":[
        "tgn:7488498",
        "tgn:7488858",
        "tgn:1000004",
        "tgn:1000141",
        "tgn:7029392"
    ],
    "tgn:id":7488498,
    "tgn:name":"Luliao Shan",
    "tgn:placetype":[
        "aat:300008798"
    ]
},
  "bbox": [],
  "geometry": {"coordinates":[120.739722,23.676111],"type":"Point"}
}
=======
{"geometry":{"type":"Point","coordinates":[120.739722,23.676111]},"type":"Feature","properties":{"hierarchy":["tgn:7488498","tgn:7488858","tgn:1000004","tgn:1000141","tgn:7029392"],"placetype":["aat:300008798"],"id":7488498,"name:xx":"Luliao Shan"}}
>>>>>>> 03f74aca74312dbeaf24d7e61306dd6a786dc3d0
