{
  "id": 7488498,
  "type": "Feature",
  "properties": {
    "tgn:hierarchy":[
        "tgn:7488498",
        "tgn:7488858",
        "tgn:1000004",
        "tgn:1000141",
        "tgn:7029392"
    ],
    "tgn:id":7488498,
    "tgn:name":"Luliao Shan",
    "tgn:placetype":[
        "aat:300008798"
    ]
},
  "bbox": [],
  "geometry": {"coordinates":[120.739722,23.676111],"type":"Point"}
}