{
  "id": 2785210,
  "type": "Feature",
  "properties": {
    "tgn:hierarchy":[
        "tgn:2785210",
        "tgn:1000001",
        "tgn:2002108",
        "tgn:7012149",
        "tgn:7007827",
        "tgn:7029392"
    ],
    "tgn:id":2785210,
    "tgn:name":"Yellow Seep",
    "tgn:placetype":[
        "aat:300008697"
    ]
},
  "bbox": [],
  "geometry": {"coordinates":[-110.8833,39.0167],"type":"Point"}
}