{
  "id": 7076880,
  "type": "Feature",
  "properties": {
    "tgn:hierarchy":[
        "tgn:7076880",
        "tgn:1000003",
        "tgn:7000094",
        "tgn:7000084",
        "tgn:7029392"
    ],
    "tgn:id":7076880,
    "tgn:name":"Zierzow",
    "tgn:placetype":[
        "aat:300008347"
    ]
},
  "bbox": [],
  "geometry": {"coordinates":[11.683333,53.283333],"type":"Point"}
}