{
  "id": 2338646,
  "type": "Feature",
  "properties": {
    "tgn:hierarchy":[
        "tgn:2338646",
        "tgn:1000001",
        "tgn:7012149",
        "tgn:2001864",
        "tgn:7007825",
        "tgn:7029392"
    ],
    "tgn:id":2338646,
    "tgn:name":"Francis Hollow",
    "tgn:placetype":[
        "aat:300008761"
    ]
},
  "bbox": [],
  "geometry": {"coordinates":[-87.1333,35.4167],"type":"Point"}
}