{
  "id": 2771544,
  "type": "Feature",
  "properties": {
    "tgn:hierarchy":[
        "tgn:2771544",
        "tgn:1000001",
        "tgn:7012149",
        "tgn:2002005",
        "tgn:7007826",
        "tgn:7029392"
    ],
    "tgn:id":2771544,
    "tgn:name":"Wildhorse Tank",
    "tgn:placetype":[
        "aat:300006191"
    ]
},
  "bbox": [],
  "geometry": {"coordinates":[-105.8667,31.65],"type":"Point"}
}