{
  "id": 2786752,
  "type": "Feature",
  "properties": {
    "tgn:hierarchy":[
        "tgn:2786752",
        "tgn:1000001",
        "tgn:7012149",
        "tgn:2002359",
        "tgn:7007922",
        "tgn:7029392"
    ],
    "tgn:id":2786752,
    "tgn:name":"Zee Lake",
    "tgn:placetype":[
        "aat:300008680"
    ]
},
  "bbox": [],
  "geometry": {"coordinates":[-89.85,46.05],"type":"Point"}
}