{
  "id": 2154931,
  "type": "Feature",
  "properties": {
    "tgn:hierarchy":[
        "tgn:2154931",
        "tgn:7006450",
        "tgn:1000001",
        "tgn:7012149",
        "tgn:7030574",
        "tgn:7029392"
    ],
    "tgn:id":2154931,
    "tgn:name":"Bear Island",
    "tgn:placetype":[
        "aat:300008791"
    ]
},
  "bbox": [],
  "geometry": {"coordinates":[-138.4333,59.15],"type":"Point"}
}