{
  "id": 2224974,
  "type": "Feature",
  "properties": {
    "tgn:hierarchy":[
        "tgn:2224974",
        "tgn:7006450",
        "tgn:1000001",
        "tgn:7012149",
        "tgn:2000079",
        "tgn:7029392"
    ],
    "tgn:id":2224974,
    "tgn:name":"Cassiope Cone",
    "tgn:placetype":[
        "aat:300008798"
    ]
},
  "bbox": [],
  "geometry": {"coordinates":[-163.4333,65.55],"type":"Point"}
}