{
  "id": 2207513,
  "type": "Feature",
  "properties": {
    "tgn:hierarchy":[
        "tgn:2207513",
        "tgn:1000001",
        "tgn:7012149",
        "tgn:2001291",
        "tgn:7007524",
        "tgn:7029392"
    ],
    "tgn:id":2207513,
    "tgn:name":"Bunyan Lake",
    "tgn:placetype":[
        "aat:300008680"
    ]
},
  "bbox": [],
  "geometry": {"coordinates":[-113.75,47.35],"type":"Point"}
}