{
  "id": 2685058,
  "type": "Feature",
  "properties": {
    "tgn:hierarchy":[
        "tgn:2685058",
        "tgn:1000001",
        "tgn:7006451",
        "tgn:7012149",
        "tgn:2000099",
        "tgn:7029392"
    ],
    "tgn:id":2685058,
    "tgn:name":"Sponseller",
    "tgn:placetype":[
        "aat:300008347"
    ]
},
  "bbox": [],
  "geometry": {"coordinates":[-109.8833,34.1833],"type":"Point"}
}