{
  "id": 2035297,
  "type": "Feature",
  "properties": {
    "tgn:hierarchy":[
        "tgn:2035297",
        "tgn:7019177",
        "tgn:1000001",
        "tgn:7012149",
        "tgn:7007253",
        "tgn:7029392"
    ],
    "tgn:id":2035297,
    "tgn:name":"Moulton",
    "tgn:placetype":[
        "aat:300008347"
    ]
},
  "bbox": [],
  "geometry": {"coordinates":[-92.6667,40.6833],"type":"Point"}
}