{
  "id": 2509356,
  "type": "Feature",
  "properties": {
    "tgn:hierarchy":[
        "tgn:2509356",
        "tgn:1000001",
        "tgn:7012149",
        "tgn:7007250",
        "tgn:7029392"
    ],
    "tgn:id":2509356,
    "tgn:name":"Middle Fork Saint Maries River",
    "tgn:placetype":[
        "aat:300008707"
    ]
},
  "bbox": [],
  "geometry": {"coordinates":[-116.15,46.9167],"type":"Point"}
}