{
  "id": 7289548,
  "type": "Feature",
  "properties": {
    "tgn:hierarchy":[
        "tgn:7289548",
        "tgn:1001630",
        "tgn:1000049",
        "tgn:1000002",
        "tgn:7029392"
    ],
    "tgn:id":7289548,
    "tgn:name":"Indio Muerto, Cerro",
    "tgn:placetype":[
        "aat:300008795"
    ]
},
  "bbox": [],
  "geometry": {"coordinates":[-69.616667,-26.266667],"type":"Point"}
}