{
  "id": 2709215,
  "type": "Feature",
  "properties": {
    "tgn:hierarchy":[
        "tgn:2709215",
        "tgn:1000001",
        "tgn:7012149",
        "tgn:7007157",
        "tgn:1002956",
        "tgn:7029392"
    ],
    "tgn:id":2709215,
    "tgn:name":"Table Meadow Creek",
    "tgn:placetype":[
        "aat:300008706"
    ]
},
  "bbox": [],
  "geometry": {"coordinates":[-118.4667,36.2667],"type":"Point"}
}