{
  "id": 7287496,
  "type": "Feature",
  "properties": {
    "tgn:hierarchy":[
        "tgn:7287496",
        "tgn:1001630",
        "tgn:1000049",
        "tgn:1000002",
        "tgn:7029392"
    ],
    "tgn:id":7287496,
    "tgn:name":"Gallina, Portezuelo de la",
    "tgn:placetype":[
        "aat:300259572"
    ]
},
  "bbox": [],
  "geometry": {"coordinates":[-69.166667,-27.666667],"type":"Point"}
}