{
  "id": 1016364,
  "type": "Feature",
  "properties": {
    "tgn:hierarchy":[
        "tgn:1016364",
        "tgn:1001521",
        "tgn:1000001",
        "tgn:7004624",
        "tgn:7029392"
    ],
    "tgn:id":1016364,
    "tgn:name":"Jatibonico",
    "tgn:placetype":[
        "aat:300008347"
    ]
},
  "bbox": [],
  "geometry": {"coordinates":[-79.1833,21.9333],"type":"Point"}
}