{
  "id": 7280520,
  "type": "Feature",
  "properties": {
    "tgn:hierarchy":[
        "tgn:7280520",
        "tgn:1001702",
        "tgn:1000049",
        "tgn:1000002",
        "tgn:7029392"
    ],
    "tgn:id":7280520,
    "tgn:name":"Tamar, Isla",
    "tgn:placetype":[
        "aat:300008791"
    ]
},
  "bbox": [],
  "geometry": {"coordinates":[-73.816667,-52.883333],"type":"Point"}
}