{
  "id": 7592411,
  "type": "Feature",
  "properties": {
    "tgn:hierarchy":[
        "tgn:7592411",
        "tgn:1000004",
        "tgn:7000198",
        "tgn:7000799",
        "tgn:7029392"
    ],
    "tgn:id":7592411,
    "tgn:name:en":"N\u0101rka",
    "tgn:placetype":[
        "aat:300008347"
    ]
},
  "bbox": [],
  "geometry": {"coordinates":[74.931984,32.855975],"type":"Point"}
}