{
  "id": 2763919,
  "type": "Feature",
  "properties": {
    "tgn:hierarchy":[
        "tgn:2763919",
        "tgn:1000001",
        "tgn:7012149",
        "tgn:2002381",
        "tgn:7007923",
        "tgn:7029392"
    ],
    "tgn:id":2763919,
    "tgn:name":"Whedon Number 1 Reservoir",
    "tgn:placetype":[
        "aat:300006191"
    ]
},
  "bbox": [],
  "geometry": {"coordinates":[-106.2833,44.8333],"type":"Point"}
}