{
  "id": 2771156,
  "type": "Feature",
  "properties": {
    "tgn:hierarchy":[
        "tgn:2771156",
        "tgn:1000001",
        "tgn:7012149",
        "tgn:7007157",
        "tgn:2000191",
        "tgn:7029392"
    ],
    "tgn:id":2771156,
    "tgn:name":"Wildcat Peak",
    "tgn:placetype":[
        "aat:300008798"
    ]
},
  "bbox": [],
  "geometry": {"coordinates":[-122.5667,41.0333],"type":"Point"}
}