<<<<<<< HEAD
{
  "id": 2332719,
  "type": "Feature",
  "properties": {
    "tgn:hierarchy":[
        "tgn:2332719",
        "tgn:1000001",
        "tgn:7006451",
        "tgn:7012149",
        "tgn:2000103",
        "tgn:7029392"
    ],
    "tgn:id":2332719,
    "tgn:name":"Flower Pot",
    "tgn:placetype":[
        "aat:300008347"
    ]
},
  "bbox": [],
  "geometry": {"coordinates":[-111.9667,34.5],"type":"Point"}
}
=======
{"geometry":{"type":"Point","coordinates":[-111.966700,34.500000]},"type":"Feature","properties":{"hierarchy":["tgn:2332719","tgn:1000001","tgn:7006451","tgn:7012149","tgn:2000103","tgn:7029392"],"placetype":["aat:300008347"],"id":2332719,"name:xx":"Flower Pot"}}
>>>>>>> 03f74aca74312dbeaf24d7e61306dd6a786dc3d0
