{
  "id": 2611159,
  "type": "Feature",
  "properties": {
    "tgn:hierarchy":[
        "tgn:2611159",
        "tgn:1000001",
        "tgn:2002369",
        "tgn:7012149",
        "tgn:7007923",
        "tgn:7029392"
    ],
    "tgn:id":2611159,
    "tgn:name":"Red Hills",
    "tgn:placetype":[
        "aat:300386831"
    ]
},
  "bbox": [],
  "geometry": {"coordinates":[-105.25,43.4667],"type":"Point"}
}