{
  "id": 2542861,
  "type": "Feature",
  "properties": {
    "tgn:hierarchy":[
        "tgn:2542861",
        "tgn:1000001",
        "tgn:7012149",
        "tgn:2001884",
        "tgn:7007825",
        "tgn:7029392"
    ],
    "tgn:id":2542861,
    "tgn:name":"Nolan Bar",
    "tgn:placetype":[
        "aat:300132348"
    ]
},
  "bbox": [],
  "geometry": {"coordinates":[-89.5167,36.45],"type":"Point"}
}