{
  "id": 2609133,
  "type": "Feature",
  "properties": {
    "tgn:hierarchy":[
        "tgn:2609133",
        "tgn:1000001",
        "tgn:7012149",
        "tgn:2000226",
        "tgn:7007158",
        "tgn:7029392"
    ],
    "tgn:id":2609133,
    "tgn:name":"Rawah Creek",
    "tgn:placetype":[
        "aat:300008706"
    ]
},
  "bbox": [],
  "geometry": {"coordinates":[-105.95,40.6667],"type":"Point"}
}