{
  "id": 7397700,
  "type": "Feature",
  "properties": {
    "tgn:hierarchy":[
        "tgn:7397700",
        "tgn:1001836",
        "tgn:1000001",
        "tgn:7005560",
        "tgn:7029392"
    ],
    "tgn:id":7397700,
    "tgn:name":"San Nicol\u00e1s, Bah\u00eda",
    "tgn:placetype":[
        "aat:300132316"
    ]
},
  "bbox": [],
  "geometry": {"coordinates":[-111.533333,26.566667],"type":"Point"}
}