{
  "id": 7261638,
  "type": "Feature",
  "properties": {
    "tgn:concordances":{
        "gn:id":"2756405"
    },
    "tgn:hierarchy":[
        "tgn:7261638",
        "tgn:7003614",
        "tgn:1000003",
        "tgn:7016845",
        "tgn:7029392"
    ],
    "tgn:id":7261638,
    "tgn:name:nl":"Eelderwolde",
    "tgn:placetype":[
        "aat:300008347"
    ]
},
  "bbox": [],
  "geometry": {"coordinates":[6.55,53.183333],"type":"Point"}
}