{
  "id": 2664135,
  "type": "Feature",
  "properties": {
    "tgn:hierarchy":[
        "tgn:2664135",
        "tgn:7002659",
        "tgn:1000001",
        "tgn:7012149",
        "tgn:2000060",
        "tgn:7029392"
    ],
    "tgn:id":2664135,
    "tgn:name":"Silver Run Creek",
    "tgn:placetype":[
        "aat:300008706"
    ]
},
  "bbox": [],
  "geometry": {"coordinates":[-85.8833,33.5333],"type":"Point"}
}