{
  "id": 7048943,
  "type": "Feature",
  "properties": {
    "tgn:hierarchy":[
        "tgn:7048943",
        "tgn:1000003",
        "tgn:7003122",
        "tgn:1001737",
        "tgn:1000080",
        "tgn:7029392"
    ],
    "tgn:id":7048943,
    "tgn:name":"Casa Criscione",
    "tgn:placetype":[
        "aat:300008347"
    ]
},
  "bbox": [],
  "geometry": {"coordinates":[14.533333,36.983333],"type":"Point"}
}