{
  "id": 2687503,
  "type": "Feature",
  "properties": {
    "tgn:hierarchy":[
        "tgn:2687503",
        "tgn:1000001",
        "tgn:7012149",
        "tgn:2001274",
        "tgn:7007524",
        "tgn:7029392"
    ],
    "tgn:id":2687503,
    "tgn:name":"Spring Lakes",
    "tgn:placetype":[
        "aat:300008680"
    ]
},
  "bbox": [],
  "geometry": {"coordinates":[-114.6833,48.65],"type":"Point"}
}