{
  "id": 7453915,
  "type": "Feature",
  "properties": {
    "tgn:hierarchy":[
        "tgn:7453915",
        "tgn:7019094",
        "tgn:7002444",
        "tgn:1000003",
        "tgn:7008591",
        "tgn:7029392"
    ],
    "tgn:id":7453915,
    "tgn:name:en":"Coulport",
    "tgn:placetype":[
        "aat:300008347"
    ]
},
  "bbox": [],
  "geometry": {"coordinates":[-4.883333,56.05],"type":"Point"}
}