{
  "id": 2451029,
  "type": "Feature",
  "properties": {
    "tgn:hierarchy":[
        "tgn:2451029",
        "tgn:1000001",
        "tgn:7012149",
        "tgn:2001543",
        "tgn:7007709",
        "tgn:7029392"
    ],
    "tgn:id":2451029,
    "tgn:name":"Little Alarka Creek",
    "tgn:placetype":[
        "aat:300008706"
    ]
},
  "bbox": [],
  "geometry": {"coordinates":[-83.4333,35.3833],"type":"Point"}
}