{
  "id": 2489948,
  "type": "Feature",
  "properties": {
    "tgn:hierarchy":[
        "tgn:2489948",
        "tgn:1000001",
        "tgn:2000465",
        "tgn:7012149",
        "tgn:7007250",
        "tgn:7029392"
    ],
    "tgn:id":2489948,
    "tgn:name":"Mammen Gulch",
    "tgn:placetype":[
        "aat:300008761"
    ]
},
  "bbox": [],
  "geometry": {"coordinates":[-116.8833,43.6833],"type":"Point"}
}