{
  "id": 2490096,
  "type": "Feature",
  "properties": {
    "tgn:hierarchy":[
        "tgn:2490096",
        "tgn:1000001",
        "tgn:7012149",
        "tgn:2002037",
        "tgn:7007826",
        "tgn:7029392"
    ],
    "tgn:id":2490096,
    "tgn:name":"Man Mountain",
    "tgn:placetype":[
        "aat:300008798"
    ]
},
  "bbox": [],
  "geometry": {"coordinates":[-99.0667,30.8167],"type":"Point"}
}