{
  "id": 7410769,
  "type": "Feature",
  "properties": {
    "tgn:hierarchy":[
        "tgn:7410769",
        "tgn:1000001",
        "tgn:1001893",
        "tgn:7005560",
        "tgn:7029392"
    ],
    "tgn:id":7410769,
    "tgn:name":"Plan Cutzamala",
    "tgn:placetype":[
        "aat:300008347"
    ]
},
  "bbox": [],
  "geometry": {"coordinates":[-100.075,19.391667],"type":"Point"}
}