{
  "id": 7327183,
  "type": "Feature",
  "properties": {
    "tgn:hierarchy":[
        "tgn:7327183",
        "tgn:7002758",
        "tgn:7002823",
        "tgn:1000003",
        "tgn:1000095",
        "tgn:7029392"
    ],
    "tgn:id":7327183,
    "tgn:name":"Pasada de los Bayos",
    "tgn:placetype":[
        "aat:300008347"
    ]
},
  "bbox": [],
  "geometry": {"coordinates":[-7.116667,37.316667],"type":"Point"}
}