{
  "id": 7482359,
  "type": "Feature",
  "properties": {
    "tgn:hierarchy":[
        "tgn:7482359",
        "tgn:7468018",
        "tgn:1000004",
        "tgn:1000141",
        "tgn:7029392"
    ],
    "tgn:id":7482359,
    "tgn:name":"Wanneng Gongshang",
    "tgn:placetype":[
        "aat:300006495"
    ]
},
  "bbox": [],
  "geometry": {"coordinates":[120.390278,23.430278],"type":"Point"}
}