{
  "id": 7505064,
  "type": "Feature",
  "properties": {
    "tgn:hierarchy":[
        "tgn:7505064",
        "tgn:1009227",
        "tgn:1000226",
        "tgn:7016729",
        "tgn:1000006",
        "tgn:7029392"
    ],
    "tgn:id":7505064,
    "tgn:name:en":"Awash Rocks",
    "tgn:placetype":[
        "aat:300011692"
    ]
},
  "bbox": [],
  "geometry": {"coordinates":[174.416667,-41.158333],"type":"Point"}
}