{
  "id": 7146242,
  "type": "Feature",
  "properties": {
    "tgn:hierarchy":[
        "tgn:7146242",
        "tgn:1000003",
        "tgn:7003677",
        "tgn:7000084",
        "tgn:7029392"
    ],
    "tgn:id":7146242,
    "tgn:name":"Klusen-Berg",
    "tgn:placetype":[
        "aat:300008777"
    ]
},
  "bbox": [],
  "geometry": {"coordinates":[8.983333,51.716667],"type":"Point"}
}