{
  "id": 1096974,
  "type": "Feature",
  "properties": {
    "tgn:hierarchy":[
        "tgn:1096974",
        "tgn:7000490",
        "tgn:1000006",
        "tgn:7001831",
        "tgn:7029392"
    ],
    "tgn:id":1096974,
    "tgn:name":"Glencoe",
    "tgn:placetype":[
        "aat:300008347"
    ]
},
  "bbox": [],
  "geometry": {"coordinates":[140.0833,-37.6833],"type":"Point"}
}