{
  "id": 7393867,
  "type": "Feature",
  "properties": {
    "tgn:hierarchy":[
        "tgn:7393867",
        "tgn:1001836",
        "tgn:1000001",
        "tgn:7005560",
        "tgn:7029392"
    ],
    "tgn:id":7393867,
    "tgn:name":"San Venancio",
    "tgn:placetype":[
        "aat:300008347"
    ]
},
  "bbox": [],
  "geometry": {"coordinates":[-111.897778,25.858889],"type":"Point"}
}