{
  "id": 7075003,
  "type": "Feature",
  "properties": {
    "tgn:hierarchy":[
        "tgn:7075003",
        "tgn:7003669",
        "tgn:1000003",
        "tgn:7000084",
        "tgn:7029392"
    ],
    "tgn:id":7075003,
    "tgn:name":"Z\u00f6tzelhofen",
    "tgn:placetype":[
        "aat:300008347"
    ]
},
  "bbox": [],
  "geometry": {"coordinates":[11.266667,48.25],"type":"Point"}
}