{
  "id": 1022883,
  "type": "Feature",
  "properties": {
    "tgn:hierarchy":[
        "tgn:1022883",
        "tgn:1001941",
        "tgn:1000047",
        "tgn:7002458",
        "tgn:1000002",
        "tgn:7029392"
    ],
    "tgn:id":1022883,
    "tgn:name":"S\u00e3o Pedro do Sul",
    "tgn:placetype":[
        "aat:300008347"
    ]
},
  "bbox": [],
  "geometry": {"coordinates":[-54.1667,-29.5833],"type":"Point"}
}