{
  "id": 7561001,
  "type": "Feature",
  "properties": {
    "tgn:hierarchy":[
        "tgn:7561001",
        "tgn:1000004",
        "tgn:7000198",
        "tgn:7016722",
        "tgn:7029392"
    ],
    "tgn:id":7561001,
    "tgn:name:en":"Deokali Kham",
    "tgn:placetype":[
        "aat:300008347"
    ]
},
  "bbox": [],
  "geometry": {"coordinates":[79.156996,27.812895],"type":"Point"}
}