{
  "id": 7127510,
  "type": "Feature",
  "properties": {
    "tgn:hierarchy":[
        "tgn:7127510",
        "tgn:7003669",
        "tgn:1000003",
        "tgn:7000084",
        "tgn:7029392"
    ],
    "tgn:id":7127510,
    "tgn:name":"Oberaign",
    "tgn:placetype":[
        "aat:300000206"
    ]
},
  "bbox": [],
  "geometry": {"coordinates":[12.45,49.116667],"type":"Point"}
}