{
  "id": 7584482,
  "type": "Feature",
  "properties": {
    "tgn:hierarchy":[
        "tgn:7584482",
        "tgn:1000004",
        "tgn:7000198",
        "tgn:1001894",
        "tgn:7029392"
    ],
    "tgn:id":7584482,
    "tgn:name:en":"Sil\u0101r Nadi",
    "tgn:placetype":[
        "aat:300008699"
    ]
},
  "bbox": [],
  "geometry": {"coordinates":[78.079512,24.161401],"type":"Point"}
}