{
  "id": 7534343,
  "type": "Feature",
  "properties": {
    "tgn:hierarchy":[
        "tgn:7534343",
        "tgn:7001242",
        "tgn:7016833",
        "tgn:1001110",
        "tgn:7029392"
    ],
    "tgn:id":7534343,
    "tgn:name:en":"Jafr\u0101, Jabal al",
    "tgn:placetype":[
        "aat:300008795"
    ]
},
  "bbox": [],
  "geometry": {"coordinates":[31.909637,30.152625],"type":"Point"}
}