<<<<<<< HEAD
{
  "id": 2259692,
  "type": "Feature",
  "properties": {
    "tgn:hierarchy":[
        "tgn:2259692",
        "tgn:1000001",
        "tgn:7012149",
        "tgn:2001290",
        "tgn:7007524",
        "tgn:7029392"
    ],
    "tgn:id":2259692,
    "tgn:name":"Cougar Creek",
    "tgn:placetype":[
        "aat:300008706"
    ]
},
  "bbox": [],
  "geometry": {"coordinates":[-114.85,47.0833],"type":"Point"}
}
=======
{"geometry":{"type":"Point","coordinates":[-114.850000,47.083300]},"type":"Feature","properties":{"hierarchy":["tgn:2259692","tgn:1000001","tgn:7012149","tgn:2001290","tgn:7007524","tgn:7029392"],"placetype":["aat:300008706"],"id":2259692,"name:xx":"Cougar Creek"}}
>>>>>>> 03f74aca74312dbeaf24d7e61306dd6a786dc3d0
