{
  "id": 2663061,
  "type": "Feature",
  "properties": {
    "tgn:hierarchy":[
        "tgn:2663061",
        "tgn:1000001",
        "tgn:7012149",
        "tgn:7016021",
        "tgn:7007568",
        "tgn:7029392"
    ],
    "tgn:id":2663061,
    "tgn:name":"Silver Brook",
    "tgn:placetype":[
        "aat:300008699"
    ]
},
  "bbox": [],
  "geometry": {"coordinates":[-74.7167,44.2167],"type":"Point"}
}