{
  "id": 7472508,
  "type": "Feature",
  "properties": {
    "tgn:hierarchy":[
        "tgn:7472508",
        "tgn:7001010",
        "tgn:1000004",
        "tgn:1000141",
        "tgn:7029392"
    ],
    "tgn:id":7472508,
    "tgn:name":"Wuling Shan",
    "tgn:placetype":[
        "aat:300008798"
    ]
},
  "bbox": [],
  "geometry": {"coordinates":[121.345885,23.973578],"type":"Point"}
}