<<<<<<< HEAD
{
  "id": 7472508,
  "type": "Feature",
  "properties": {
    "tgn:hierarchy":[
        "tgn:7472508",
        "tgn:7001010",
        "tgn:1000004",
        "tgn:1000141",
        "tgn:7029392"
    ],
    "tgn:id":7472508,
    "tgn:name":"Wuling Shan",
    "tgn:placetype":[
        "aat:300008798"
    ]
},
  "bbox": [],
  "geometry": {"coordinates":[121.345885,23.973578],"type":"Point"}
}
=======
{"geometry":{"type":"Point","coordinates":[121.345885,23.973578]},"type":"Feature","properties":{"hierarchy":["tgn:7472508","tgn:7001010","tgn:1000004","tgn:1000141","tgn:7029392"],"placetype":["aat:300008798"],"id":7472508,"name:xx":"Wuling Shan"}}
>>>>>>> 03f74aca74312dbeaf24d7e61306dd6a786dc3d0
