<<<<<<< HEAD
{
  "id": 2764934,
  "type": "Feature",
  "properties": {
    "tgn:hierarchy":[
        "tgn:2764934",
        "tgn:1000001",
        "tgn:7012149",
        "tgn:7007157",
        "tgn:1002857",
        "tgn:7029392"
    ],
    "tgn:id":2764934,
    "tgn:name":"Whiskey Springs",
    "tgn:placetype":[
        "aat:300008697"
    ]
},
  "bbox": [],
  "geometry": {"coordinates":[-116.8167,34.3333],"type":"Point"}
}
=======
{"geometry":{"type":"Point","coordinates":[-116.816700,34.333300]},"type":"Feature","properties":{"hierarchy":["tgn:2764934","tgn:1000001","tgn:7012149","tgn:7007157","tgn:1002857","tgn:7029392"],"placetype":["aat:300008697"],"id":2764934,"name:xx":"Whiskey Springs"}}
>>>>>>> 03f74aca74312dbeaf24d7e61306dd6a786dc3d0
