{
  "id": 2352699,
  "type": "Feature",
  "properties": {
    "tgn:hierarchy":[
        "tgn:2352699",
        "tgn:1000001",
        "tgn:7006451",
        "tgn:2000092",
        "tgn:7012149",
        "tgn:7029392"
    ],
    "tgn:id":2352699,
    "tgn:name":"Goat Tank",
    "tgn:placetype":[
        "aat:300006191"
    ]
},
  "bbox": [],
  "geometry": {"coordinates":[-111.6333,35.4833],"type":"Point"}
}