{
  "id": 2429140,
  "type": "Feature",
  "properties": {
    "tgn:hierarchy":[
        "tgn:2429140",
        "tgn:1000001",
        "tgn:7012149",
        "tgn:2001720",
        "tgn:7007708",
        "tgn:7029392"
    ],
    "tgn:id":2429140,
    "tgn:name":"Junction Spring",
    "tgn:placetype":[
        "aat:300008697"
    ]
},
  "bbox": [],
  "geometry": {"coordinates":[-118.25,45.55],"type":"Point"}
}