{
  "id": 7526631,
  "type": "Feature",
  "properties": {
    "tgn:hierarchy":[
        "tgn:7526631",
        "tgn:7001242",
        "tgn:7016833",
        "tgn:1001091",
        "tgn:7029392"
    ],
    "tgn:id":7526631,
    "tgn:name":"Shirkat Mamfis lil Adwiyah",
    "tgn:placetype":[
        "aat:300004792"
    ]
},
  "bbox": [],
  "geometry": {"coordinates":[31.294108,30.106495],"type":"Point"}
}