{
  "id": 7134041,
  "type": "Feature",
  "properties": {
    "tgn:hierarchy":[
        "tgn:7134041",
        "tgn:1000003",
        "tgn:7003689",
        "tgn:7000084",
        "tgn:7029392"
    ],
    "tgn:id":7134041,
    "tgn:name":"M\u00fcnchenroda",
    "tgn:placetype":[
        "aat:300008347"
    ]
},
  "bbox": [],
  "geometry": {"coordinates":[11.516667,50.933333],"type":"Point"}
}