{
  "id": 2781368,
  "type": "Feature",
  "properties": {
    "tgn:hierarchy":[
        "tgn:2781368",
        "tgn:1000001",
        "tgn:1002695",
        "tgn:7012149",
        "tgn:7007565",
        "tgn:7029392"
    ],
    "tgn:id":2781368,
    "tgn:name":"Woodland Lake",
    "tgn:placetype":[
        "aat:300006191"
    ]
},
  "bbox": [],
  "geometry": {"coordinates":[-74.2833,40.95],"type":"Point"}
}