{
  "id": 7507895,
  "type": "Feature",
  "properties": {
    "tgn:hierarchy":[
        "tgn:7507895",
        "tgn:1009227",
        "tgn:7001866",
        "tgn:1000226",
        "tgn:1000006",
        "tgn:7029392"
    ],
    "tgn:id":7507895,
    "tgn:name:en":"Perth River",
    "tgn:placetype":[
        "aat:300008699"
    ]
},
  "bbox": [],
  "geometry": {"coordinates":[170.45,-43.333333],"type":"Point"}
}