{
  "id": 7384346,
  "type": "Feature",
  "properties": {
    "tgn:hierarchy":[
        "tgn:7384346",
        "tgn:1001853",
        "tgn:1000001",
        "tgn:7005560",
        "tgn:7029392"
    ],
    "tgn:id":7384346,
    "tgn:name":"Paila, Barrial de la",
    "tgn:placetype":[
        "aat:300008905"
    ]
},
  "bbox": [],
  "geometry": {"coordinates":[-101.916667,25.75],"type":"Point"}
}