{
  "id": 1058645,
  "type": "Feature",
  "properties": {
    "tgn:hierarchy":[
        "tgn:1058645",
        "tgn:7006504",
        "tgn:1000003",
        "tgn:7006541",
        "tgn:7029392"
    ],
    "tgn:id":1058645,
    "tgn:name":"Prei\u013ci",
    "tgn:placetype":[
        "aat:300008347",
        "aat:300008389",
        "aat:300387222"
    ]
},
  "bbox": [],
  "geometry": {"coordinates":[26.8333,56.2667],"type":"Point"}
}