{
  "id": 7466349,
  "type": "Feature",
  "properties": {
    "tgn:hierarchy":[
        "tgn:7466349",
        "tgn:7002445",
        "tgn:1000003",
        "tgn:7008185",
        "tgn:7008591",
        "tgn:7029392"
    ],
    "tgn:id":7466349,
    "tgn:name:en":"Bardwell",
    "tgn:placetype":[
        "aat:300008347"
    ]
},
  "bbox": [],
  "geometry": {"coordinates":[0.85,52.316667],"type":"Point"}
}