{
  "id": 2221920,
  "type": "Feature",
  "properties": {
    "tgn:hierarchy":[
        "tgn:2221920",
        "tgn:1000001",
        "tgn:1002281",
        "tgn:7012149",
        "tgn:7007251",
        "tgn:7029392"
    ],
    "tgn:id":2221920,
    "tgn:name":"Carlyle Reservoir",
    "tgn:placetype":[
        "aat:300006191"
    ]
},
  "bbox": [],
  "geometry": {"coordinates":[-89.35,38.6167],"type":"Point"}
}