{
  "id": 7099203,
  "type": "Feature",
  "properties": {
    "tgn:hierarchy":[
        "tgn:7099203",
        "tgn:7000096",
        "tgn:1000003",
        "tgn:7000084",
        "tgn:7029392"
    ],
    "tgn:id":7099203,
    "tgn:name":"Bahnhof Selchow",
    "tgn:placetype":[
        "aat:300007783"
    ]
},
  "bbox": [],
  "geometry": {"coordinates":[13.483333,52.35],"type":"Point"}
}