{
  "id": 2127278,
  "type": "Feature",
  "properties": {
    "tgn:hierarchy":[
        "tgn:2127278",
        "tgn:1000001",
        "tgn:7006451",
        "tgn:7012149",
        "tgn:2000098",
        "tgn:7029392"
    ],
    "tgn:id":2127278,
    "tgn:name":"Airport Cove",
    "tgn:placetype":[
        "aat:300132316"
    ]
},
  "bbox": [],
  "geometry": {"coordinates":[-114.65,35.4667],"type":"Point"}
}