<<<<<<< HEAD
{
  "id": 2402367,
  "type": "Feature",
  "properties": {
    "tgn:hierarchy":[
        "tgn:2402367",
        "tgn:2000105",
        "tgn:1000001",
        "tgn:7016172",
        "tgn:7012149",
        "tgn:7029392"
    ],
    "tgn:id":2402367,
    "tgn:name":"Horton Lake",
    "tgn:placetype":[
        "aat:300006191"
    ]
},
  "bbox": [],
  "geometry": {"coordinates":[-91.1167,34.2833],"type":"Point"}
}
=======
{"geometry":{"type":"Point","coordinates":[-91.116700,34.283300]},"type":"Feature","properties":{"hierarchy":["tgn:2402367","tgn:2000105","tgn:1000001","tgn:7016172","tgn:7012149","tgn:7029392"],"placetype":["aat:300006191"],"id":2402367,"name:xx":"Horton Lake"}}
>>>>>>> 03f74aca74312dbeaf24d7e61306dd6a786dc3d0
