{
  "id": 7067348,
  "type": "Feature",
  "properties": {
    "tgn:hierarchy":[
        "tgn:7067348",
        "tgn:7003669",
        "tgn:1000003",
        "tgn:7000084",
        "tgn:7029392"
    ],
    "tgn:id":7067348,
    "tgn:name":"Stoffels",
    "tgn:placetype":[
        "aat:300000206"
    ]
},
  "bbox": [],
  "geometry": {"coordinates":[10.266667,47.716667],"type":"Point"}
}