<<<<<<< HEAD
{
  "id": 2332263,
  "type": "Feature",
  "properties": {
    "tgn:hierarchy":[
        "tgn:2332263",
        "tgn:1000001",
        "tgn:7012149",
        "tgn:2000208",
        "tgn:7007158",
        "tgn:7029392"
    ],
    "tgn:id":2332263,
    "tgn:name":"Floating Reservoir",
    "tgn:placetype":[
        "aat:300006191"
    ]
},
  "bbox": [],
  "geometry": {"coordinates":[-108.7,37.7],"type":"Point"}
}
=======
{"geometry":{"type":"Point","coordinates":[-108.700000,37.700000]},"type":"Feature","properties":{"hierarchy":["tgn:2332263","tgn:1000001","tgn:7012149","tgn:2000208","tgn:7007158","tgn:7029392"],"placetype":["aat:300006191"],"id":2332263,"name:xx":"Floating Reservoir"}}
>>>>>>> 03f74aca74312dbeaf24d7e61306dd6a786dc3d0
