{
  "id": 2618701,
  "type": "Feature",
  "properties": {
    "tgn:hierarchy":[
        "tgn:2618701",
        "tgn:1000001",
        "tgn:7012149",
        "tgn:2000811",
        "tgn:7007255",
        "tgn:7029392"
    ],
    "tgn:id":2618701,
    "tgn:name":"Right Fork Peters Branch",
    "tgn:placetype":[
        "aat:300008699"
    ]
},
  "bbox": [],
  "geometry": {"coordinates":[-83.3667,36.95],"type":"Point"}
}