{
  "id": 2658746,
  "type": "Feature",
  "properties": {
    "tgn:hierarchy":[
        "tgn:2658746",
        "tgn:1000001",
        "tgn:7012149",
        "tgn:7007157",
        "tgn:1002956",
        "tgn:7029392"
    ],
    "tgn:id":2658746,
    "tgn:name":"Sherman Creek",
    "tgn:placetype":[
        "aat:300008706"
    ]
},
  "bbox": [],
  "geometry": {"coordinates":[-118.7333,36.5833],"type":"Point"}
}