{
  "id": 2602825,
  "type": "Feature",
  "properties": {
    "tgn:hierarchy":[
        "tgn:2602825",
        "tgn:1000001",
        "tgn:1002539",
        "tgn:7012149",
        "tgn:7007516",
        "tgn:7029392"
    ],
    "tgn:id":2602825,
    "tgn:name":"Quaker Neck Landing",
    "tgn:placetype":[
        "aat:300008347"
    ]
},
  "bbox": [],
  "geometry": {"coordinates":[-76.0833,39.1167],"type":"Point"}
}