<<<<<<< HEAD
{
  "id": 7027276,
  "type": "Feature",
  "properties": {
    "tgn:hierarchy":[
        "tgn:7027276",
        "tgn:7002445",
        "tgn:7011980",
        "tgn:1000003",
        "tgn:7008591",
        "tgn:7029392"
    ],
    "tgn:id":7027276,
    "tgn:name":"Colne",
    "tgn:name:ang":"Colne",
    "tgn:placetype":[
        "aat:300008347",
        "aat:300008372"
    ]
},
  "bbox": [],
  "geometry": {"coordinates":[0.016667,52.366667],"type":"Point"}
}
=======
{"geometry":{"type":"Point","coordinates":[0.016667,52.366667]},"type":"Feature","properties":{"hierarchy":["tgn:7027276","tgn:7002445","tgn:7011980","tgn:1000003","tgn:7008591","tgn:7029392"],"placetype":["aat:300008347","aat:300008372"],"id":7027276,"name:xx":"Colne","name:ang":"Colne"}}
>>>>>>> 03f74aca74312dbeaf24d7e61306dd6a786dc3d0
