{
  "id": 7468185,
  "type": "Feature",
  "properties": {
    "tgn:hierarchy":[
        "tgn:7468185",
        "tgn:1000004",
        "tgn:1000959",
        "tgn:1000141",
        "tgn:7029392"
    ],
    "tgn:id":7468185,
    "tgn:name":"Jiangling Li",
    "tgn:placetype":[
        "aat:300387173"
    ]
},
  "bbox": [],
  "geometry": {"coordinates":[121.5368,24.9845],"type":"Point"}
}