<<<<<<< HEAD
{
  "id": 7352525,
  "type": "Feature",
  "properties": {
    "tgn:hierarchy":[
        "tgn:7352525",
        "tgn:7005581",
        "tgn:1000001",
        "tgn:7005560",
        "tgn:7029392"
    ],
    "tgn:id":7352525,
    "tgn:name":"Rancho Barzon",
    "tgn:placetype":[
        "aat:300000241"
    ]
},
  "bbox": [],
  "geometry": {"coordinates":[-106.05,31.066667],"type":"Point"}
}
=======
{"geometry":{"type":"Point","coordinates":[-106.050000,31.066667]},"type":"Feature","properties":{"hierarchy":["tgn:7352525","tgn:7005581","tgn:1000001","tgn:7005560","tgn:7029392"],"placetype":["aat:300000241"],"id":7352525,"name:xx":"Rancho Barzon"}}
>>>>>>> 03f74aca74312dbeaf24d7e61306dd6a786dc3d0
