{
  "id": 7564615,
  "type": "Feature",
  "properties": {
    "tgn:hierarchy":[
        "tgn:7564615",
        "tgn:1000004",
        "tgn:7000198",
        "tgn:7016722",
        "tgn:7029392"
    ],
    "tgn:id":7564615,
    "tgn:name:en":"\u0100lampur",
    "tgn:placetype":[
        "aat:300008347"
    ]
},
  "bbox": [],
  "geometry": {"coordinates":[79.323348,26.366951],"type":"Point"}
}