{
  "id": 1129256,
  "type": "Feature",
  "properties": {
    "tgn:hierarchy":[
        "tgn:1129256",
        "tgn:7005735",
        "tgn:7005685",
        "tgn:1000001",
        "tgn:7029392"
    ],
    "tgn:id":1129256,
    "tgn:name":"Ryan",
    "tgn:placetype":[
        "aat:300008707"
    ]
},
  "bbox": [],
  "geometry": {"coordinates":[-122.7167,50.4167],"type":"Point"}
}