<<<<<<< HEAD
{
  "id": 7473172,
  "type": "Feature",
  "properties": {
    "tgn:hierarchy":[
        "tgn:7473172",
        "tgn:1000004",
        "tgn:7492971",
        "tgn:1000141",
        "tgn:7029392"
    ],
    "tgn:id":7473172,
    "tgn:name":"Donggang Zhan",
    "tgn:placetype":[
        "aat:300007783"
    ]
},
  "bbox": [],
  "geometry": {"coordinates":[120.458862,22.464245],"type":"Point"}
}
=======
{"geometry":{"type":"Point","coordinates":[120.458862,22.464245]},"type":"Feature","properties":{"hierarchy":["tgn:7473172","tgn:1000004","tgn:7492971","tgn:1000141","tgn:7029392"],"placetype":["aat:300007783"],"id":7473172,"name:xx":"Donggang Zhan"}}
>>>>>>> 03f74aca74312dbeaf24d7e61306dd6a786dc3d0
