{
  "id": 2721518,
  "type": "Feature",
  "properties": {
    "tgn:hierarchy":[
        "tgn:2721518",
        "tgn:1000001",
        "tgn:7012149",
        "tgn:7007522",
        "tgn:7029392"
    ],
    "tgn:id":2721518,
    "tgn:name":"Tillatoba Creek",
    "tgn:placetype":[
        "aat:300008706"
    ]
},
  "bbox": [],
  "geometry": {"coordinates":[-89.7667,34.0167],"type":"Point"}
}