{
  "id": 7252562,
  "type": "Feature",
  "properties": {
    "tgn:hierarchy":[
        "tgn:7252562",
        "tgn:7003466",
        "tgn:1000003",
        "tgn:1000063",
        "tgn:4012014",
        "tgn:7029392"
    ],
    "tgn:id":7252562,
    "tgn:name":"Ostemer\u00e9e",
    "tgn:placetype":[
        "aat:300008347"
    ]
},
  "bbox": [],
  "geometry": {"coordinates":[4.766912,50.249142],"type":"Point"}
}