{
  "id": 2368813,
  "type": "Feature",
  "properties": {
    "tgn:hierarchy":[
        "tgn:2368813",
        "tgn:1000001",
        "tgn:7012149",
        "tgn:1002472",
        "tgn:7007568",
        "tgn:7029392"
    ],
    "tgn:id":2368813,
    "tgn:name":"Gull Rock Point",
    "tgn:placetype":[
        "aat:300008850"
    ]
},
  "bbox": [],
  "geometry": {"coordinates":[-74.8333,43.75],"type":"Point"}
}