{
  "id": 1058618,
  "type": "Feature",
  "properties": {
    "tgn:hierarchy":[
        "tgn:1058618",
        "tgn:1000004",
        "tgn:7011539",
        "tgn:7018214",
        "tgn:7002435",
        "tgn:7029392"
    ],
    "tgn:id":1058618,
    "tgn:name":"Posyet",
    "tgn:placetype":[
        "aat:300008347"
    ]
},
  "bbox": [],
  "geometry": {"coordinates":[130.7833,42.65],"type":"Point"}
}