<<<<<<< HEAD
{
  "id": 7025597,
  "type": "Feature",
  "properties": {
    "tgn:hierarchy":[
        "tgn:7025597",
        "tgn:7002445",
        "tgn:1000003",
        "tgn:7012077",
        "tgn:7008591",
        "tgn:7029392"
    ],
    "tgn:id":7025597,
    "tgn:name":"Huish",
    "tgn:placetype":[
        "aat:300008347"
    ]
},
  "bbox": [],
  "geometry": {"coordinates":[-4.8333,50.8833],"type":"Point"}
}
=======
{"geometry":{"type":"Point","coordinates":[-4.833300,50.883300]},"type":"Feature","properties":{"hierarchy":["tgn:7025597","tgn:7002445","tgn:1000003","tgn:7012077","tgn:7008591","tgn:7029392"],"placetype":["aat:300008347"],"id":7025597,"name:xx":"Huish"}}
>>>>>>> 03f74aca74312dbeaf24d7e61306dd6a786dc3d0
