{
  "id": 7025597,
  "type": "Feature",
  "properties": {
    "tgn:hierarchy":[
        "tgn:7025597",
        "tgn:7002445",
        "tgn:1000003",
        "tgn:7012077",
        "tgn:7008591",
        "tgn:7029392"
    ],
    "tgn:id":7025597,
    "tgn:name":"Huish",
    "tgn:placetype":[
        "aat:300008347"
    ]
},
  "bbox": [],
  "geometry": {"coordinates":[-4.8333,50.8833],"type":"Point"}
}