{
  "id": 2389928,
  "type": "Feature",
  "properties": {
    "tgn:hierarchy":[
        "tgn:2389928",
        "tgn:1000001",
        "tgn:7012149",
        "tgn:7007157",
        "tgn:1002706",
        "tgn:7029392"
    ],
    "tgn:id":2389928,
    "tgn:name":"High Point",
    "tgn:placetype":[
        "aat:300008798"
    ]
},
  "bbox": [],
  "geometry": {"coordinates":[-122.5167,38.6167],"type":"Point"}
}