{
  "id": 2634295,
  "type": "Feature",
  "properties": {
    "tgn:hierarchy":[
        "tgn:2634295",
        "tgn:7002659",
        "tgn:1000001",
        "tgn:7012149",
        "tgn:2000054",
        "tgn:7029392"
    ],
    "tgn:id":2634295,
    "tgn:name":"Russell Pond",
    "tgn:placetype":[
        "aat:300006191"
    ]
},
  "bbox": [],
  "geometry": {"coordinates":[-86.1167,31.95],"type":"Point"}
}