{
  "id": 7508464,
  "type": "Feature",
  "properties": {
    "tgn:hierarchy":[
        "tgn:7508464",
        "tgn:1009227",
        "tgn:1000226",
        "tgn:7016822",
        "tgn:1000006",
        "tgn:7029392"
    ],
    "tgn:id":7508464,
    "tgn:name:en":"Paget Point",
    "tgn:placetype":[
        "aat:300386846"
    ]
},
  "bbox": [],
  "geometry": {"coordinates":[167.116667,-45.083333],"type":"Point"}
}