{
  "id": 7281980,
  "type": "Feature",
  "properties": {
    "tgn:hierarchy":[
        "tgn:7281980",
        "tgn:7016598",
        "tgn:1000049",
        "tgn:1000002",
        "tgn:7029392"
    ],
    "tgn:id":7281980,
    "tgn:name":"San Pedro, R\u00edo",
    "tgn:placetype":[
        "aat:300266554",
        "aat:300008699"
    ]
},
  "bbox": [],
  "geometry": {"coordinates":[-68.25,-22.983333],"type":"Point"}
}