{
  "id": 2051273,
  "type": "Feature",
  "properties": {
    "tgn:hierarchy":[
        "tgn:2051273",
        "tgn:1000001",
        "tgn:7012149",
        "tgn:1002503",
        "tgn:7007520",
        "tgn:7029392"
    ],
    "tgn:id":2051273,
    "tgn:name":"Belding",
    "tgn:placetype":[
        "aat:300008347"
    ]
},
  "bbox": [],
  "geometry": {"coordinates":[-85.2167,43.0833],"type":"Point"}
}