{
  "id": 2101173,
  "type": "Feature",
  "properties": {
    "tgn:hierarchy":[
        "tgn:2101173",
        "tgn:1000001",
        "tgn:7012149",
        "tgn:2001883",
        "tgn:7007825",
        "tgn:7029392"
    ],
    "tgn:id":2101173,
    "tgn:name":"Ramsey",
    "tgn:placetype":[
        "aat:300008347"
    ]
},
  "bbox": [],
  "geometry": {"coordinates":[-83.8333,35.9667],"type":"Point"}
}