{
  "id": 7009051,
  "type": "Feature",
  "properties": {
    "tgn:hierarchy":[
        "tgn:7009051",
        "tgn:1000003",
        "tgn:7012216",
        "tgn:1000070",
        "tgn:7029392"
    ],
    "tgn:id":7009051,
    "tgn:name":"Concarneau",
    "tgn:placetype":[
        "aat:300008347"
    ]
},
  "bbox": [],
  "geometry": {"coordinates":[-3.9167,47.8833],"type":"Point"}
}