<<<<<<< HEAD
{
  "id": 2406971,
  "type": "Feature",
  "properties": {
    "tgn:hierarchy":[
        "tgn:2406971",
        "tgn:1000001",
        "tgn:7012149",
        "tgn:1002353",
        "tgn:7007252",
        "tgn:7029392"
    ],
    "tgn:id":2406971,
    "tgn:name":"Hunter Lake",
    "tgn:placetype":[
        "aat:300008680"
    ]
},
  "bbox": [],
  "geometry": {"coordinates":[-85.6667,41.7167],"type":"Point"}
}
=======
{"geometry":{"type":"Point","coordinates":[-85.666700,41.716700]},"type":"Feature","properties":{"hierarchy":["tgn:2406971","tgn:1000001","tgn:7012149","tgn:1002353","tgn:7007252","tgn:7029392"],"placetype":["aat:300008680"],"id":2406971,"name:xx":"Hunter Lake"}}
>>>>>>> 03f74aca74312dbeaf24d7e61306dd6a786dc3d0
