{
  "id": 2357644,
  "type": "Feature",
  "properties": {
    "tgn:hierarchy":[
        "tgn:2357644",
        "tgn:1000001",
        "tgn:7012149",
        "tgn:1002997",
        "tgn:7007826",
        "tgn:7029392"
    ],
    "tgn:id":2357644,
    "tgn:name":"Graball",
    "tgn:placetype":[
        "aat:300008347"
    ]
},
  "bbox": [],
  "geometry": {"coordinates":[-96.1333,30.25],"type":"Point"}
}