{
  "id": 7440322,
  "type": "Feature",
  "properties": {
    "tgn:hierarchy":[
        "tgn:7440322",
        "tgn:7005581",
        "tgn:1000001",
        "tgn:7005560",
        "tgn:7029392"
    ],
    "tgn:id":7440322,
    "tgn:name":"San Pedro",
    "tgn:placetype":[
        "aat:300008347"
    ]
},
  "bbox": [],
  "geometry": {"coordinates":[-104.933333,29.333333],"type":"Point"}
}