{
  "id": 7264377,
  "type": "Feature",
  "properties": {
    "tgn:hierarchy":[
        "tgn:7264377",
        "tgn:7003616",
        "tgn:1000003",
        "tgn:7016845",
        "tgn:7029392"
    ],
    "tgn:id":7264377,
    "tgn:name:nl":"Koudumervaart",
    "tgn:placetype":[
        "aat:300006075"
    ]
},
  "bbox": [],
  "geometry": {"coordinates":[5.466667,52.933333],"type":"Point"}
}