{
  "id": 2433344,
  "type": "Feature",
  "properties": {
    "tgn:hierarchy":[
        "tgn:2433344",
        "tgn:1000001",
        "tgn:7012149",
        "tgn:2002376",
        "tgn:7007923",
        "tgn:7029392"
    ],
    "tgn:id":2433344,
    "tgn:name":"Kelley Creek",
    "tgn:placetype":[
        "aat:300008706"
    ]
},
  "bbox": [],
  "geometry": {"coordinates":[-110.7833,42.2833],"type":"Point"}
}