{
  "id": 2729876,
  "type": "Feature",
  "properties": {
    "tgn:hierarchy":[
        "tgn:2729876",
        "tgn:1000001",
        "tgn:7012149",
        "tgn:1002800",
        "tgn:7007710",
        "tgn:7029392"
    ],
    "tgn:id":2729876,
    "tgn:name":"Trout Brook",
    "tgn:placetype":[
        "aat:300008699"
    ]
},
  "bbox": [],
  "geometry": {"coordinates":[-78.0833,41.7833],"type":"Point"}
}