<<<<<<< HEAD
{
  "id": 2258322,
  "type": "Feature",
  "properties": {
    "tgn:hierarchy":[
        "tgn:2258322",
        "tgn:1000001",
        "tgn:7012149",
        "tgn:2001461",
        "tgn:7007568",
        "tgn:7029392"
    ],
    "tgn:id":2258322,
    "tgn:name":"Cotters Pond",
    "tgn:placetype":[
        "aat:300008680"
    ]
},
  "bbox": [],
  "geometry": {"coordinates":[-73.65,43.8667],"type":"Point"}
}
=======
{"geometry":{"type":"Point","coordinates":[-73.650000,43.866700]},"type":"Feature","properties":{"hierarchy":["tgn:2258322","tgn:1000001","tgn:7012149","tgn:2001461","tgn:7007568","tgn:7029392"],"placetype":["aat:300008680"],"id":2258322,"name:xx":"Cotters Pond"}}
>>>>>>> 03f74aca74312dbeaf24d7e61306dd6a786dc3d0
