{
  "id": 1114995,
  "type": "Feature",
  "properties": {
    "tgn:hierarchy":[
        "tgn:1114995",
        "tgn:7005735",
        "tgn:7005685",
        "tgn:1000001",
        "tgn:7029392"
    ],
    "tgn:id":1114995,
    "tgn:name":"Laredo Sound",
    "tgn:placetype":[
        "aat:300266558"
    ]
},
  "bbox": [],
  "geometry": {"coordinates":[-128.9167,52.4167],"type":"Point"}
}