{
  "id": 7353199,
  "type": "Feature",
  "properties": {
    "tgn:hierarchy":[
        "tgn:7353199",
        "tgn:1000001",
        "tgn:7005589",
        "tgn:7005560",
        "tgn:7029392"
    ],
    "tgn:id":7353199,
    "tgn:name":"Rancho Belceb\u00fa",
    "tgn:placetype":[
        "aat:300000241"
    ]
},
  "bbox": [],
  "geometry": {"coordinates":[-99.783333,26.616667],"type":"Point"}
}