{
  "id": 2378931,
  "type": "Feature",
  "properties": {
    "tgn:hierarchy":[
        "tgn:2378931",
        "tgn:7013349",
        "tgn:1000001",
        "tgn:7012149",
        "tgn:7007708",
        "tgn:7029392"
    ],
    "tgn:id":2378931,
    "tgn:name":"Hart Spring",
    "tgn:placetype":[
        "aat:300008697"
    ]
},
  "bbox": [],
  "geometry": {"coordinates":[-118.05,44.9667],"type":"Point"}
}