{
  "id": 2307059,
  "type": "Feature",
  "properties": {
    "tgn:hierarchy":[
        "tgn:2307059",
        "tgn:1000001",
        "tgn:7012149",
        "tgn:7007158",
        "tgn:7029392"
    ],
    "tgn:id":2307059,
    "tgn:name":"East Fork Mc Kenzie Creek",
    "tgn:placetype":[
        "aat:300008706"
    ]
},
  "bbox": [],
  "geometry": {"coordinates":[-107.9667,38.15],"type":"Point"}
}