{
  "id": 7341088,
  "type": "Feature",
  "properties": {
    "tgn:hierarchy":[
        "tgn:7341088",
        "tgn:7002807",
        "tgn:1000003",
        "tgn:7003837",
        "tgn:1000095",
        "tgn:7029392"
    ],
    "tgn:id":7341088,
    "tgn:name":"Buenavista",
    "tgn:placetype":[
        "aat:300000745"
    ]
},
  "bbox": [],
  "geometry": {"coordinates":[-6.783333,38.516667],"type":"Point"}
}