{
  "id": 7543704,
  "type": "Feature",
  "properties": {
    "tgn:hierarchy":[
        "tgn:7543704",
        "tgn:7001242",
        "tgn:7016833",
        "tgn:7001335",
        "tgn:7029392"
    ],
    "tgn:id":7543704,
    "tgn:name:en":"Tasa Junction",
    "tgn:placetype":[
        "aat:300008347"
    ]
},
  "bbox": [],
  "geometry": {"coordinates":[32.623291,30.55746],"type":"Point"}
}