{
  "id": 1016601,
  "type": "Feature",
  "properties": {
    "tgn:hierarchy":[
        "tgn:1016601",
        "tgn:1007776",
        "tgn:7018313",
        "tgn:1000001",
        "tgn:7004545",
        "tgn:7029392"
    ],
    "tgn:id":1016601,
    "tgn:name":"Grande Anse",
    "tgn:placetype":[
        "aat:300008347"
    ]
},
  "bbox": [],
  "geometry": {"coordinates":[-61.0667,16.2833],"type":"Point"}
}