{
  "id": 2674771,
  "type": "Feature",
  "properties": {
    "tgn:hierarchy":[
        "tgn:2674771",
        "tgn:1000001",
        "tgn:7012149",
        "tgn:1002350",
        "tgn:7007157",
        "tgn:7029392"
    ],
    "tgn:id":2674771,
    "tgn:name":"Soapweed Creek",
    "tgn:placetype":[
        "aat:300008706"
    ]
},
  "bbox": [],
  "geometry": {"coordinates":[-120.65,38.85],"type":"Point"}
}