{
  "id": 7319370,
  "type": "Feature",
  "properties": {
    "tgn:hierarchy":[
        "tgn:7319370",
        "tgn:7016598",
        "tgn:1000049",
        "tgn:1000002",
        "tgn:7029392"
    ],
    "tgn:id":7319370,
    "tgn:name":"Amarillo, Cerro",
    "tgn:placetype":[
        "aat:300008795"
    ]
},
  "bbox": [],
  "geometry": {"coordinates":[-69.766667,-22.466667],"type":"Point"}
}