{
  "id": 7328875,
  "type": "Feature",
  "properties": {
    "tgn:hierarchy":[
        "tgn:7328875",
        "tgn:7002836",
        "tgn:7016622",
        "tgn:1000003",
        "tgn:1000095",
        "tgn:7029392"
    ],
    "tgn:id":7328875,
    "tgn:name":"Ermita del Pita",
    "tgn:placetype":[
        "aat:300000640"
    ]
},
  "bbox": [],
  "geometry": {"coordinates":[-16.333333,28.433333],"type":"Point"}
}