{
  "id": 2321617,
  "type": "Feature",
  "properties": {
    "tgn:hierarchy":[
        "tgn:2321617",
        "tgn:1000001",
        "tgn:2000952",
        "tgn:7012149",
        "tgn:7007520",
        "tgn:7029392"
    ],
    "tgn:id":2321617,
    "tgn:name":"Fairview Cove",
    "tgn:placetype":[
        "aat:300132316"
    ]
},
  "bbox": [],
  "geometry": {"coordinates":[-83.8333,45.95],"type":"Point"}
}