{
  "id": 2540749,
  "type": "Feature",
  "properties": {
    "tgn:hierarchy":[
        "tgn:2540749",
        "tgn:1000001",
        "tgn:7012149",
        "tgn:7007708",
        "tgn:7029392"
    ],
    "tgn:id":2540749,
    "tgn:name":"Niagara Creek",
    "tgn:placetype":[
        "aat:300008706"
    ]
},
  "bbox": [],
  "geometry": {"coordinates":[-123.6667,45.1833],"type":"Point"}
}