{
  "id": 7151336,
  "type": "Feature",
  "properties": {
    "tgn:hierarchy":[
        "tgn:7151336",
        "tgn:1000003",
        "tgn:7003676",
        "tgn:7000084",
        "tgn:7029392"
    ],
    "tgn:id":7151336,
    "tgn:name":"Insenhausen",
    "tgn:placetype":[
        "aat:300000206"
    ]
},
  "bbox": [],
  "geometry": {"coordinates":[7.683333,53.65],"type":"Point"}
}