{
  "id": 7516493,
  "type": "Feature",
  "properties": {
    "tgn:hierarchy":[
        "tgn:7516493",
        "tgn:1009227",
        "tgn:1000226",
        "tgn:7016822",
        "tgn:1000006",
        "tgn:7029392"
    ],
    "tgn:id":7516493,
    "tgn:name:en":"Mokotua",
    "tgn:placetype":[
        "aat:300008347"
    ]
},
  "bbox": [],
  "geometry": {"coordinates":[168.583333,-46.45],"type":"Point"}
}