{
  "id": 1087371,
  "type": "Feature",
  "properties": {
    "tgn:hierarchy":[
        "tgn:1087371",
        "tgn:7001242",
        "tgn:1000519",
        "tgn:7016752",
        "tgn:7029392"
    ],
    "tgn:id":1087371,
    "tgn:name":"B\u00e9char",
    "tgn:placetype":[
        "aat:300008347",
        "aat:300387225",
        "aat:300008375",
        "aat:300387286"
    ]
},
  "bbox": [],
  "geometry": {"coordinates":[-2.2833,31.5833],"type":"Point"}
}