{
  "id": 2621258,
  "type": "Feature",
  "properties": {
    "tgn:hierarchy":[
        "tgn:2621258",
        "tgn:1000001",
        "tgn:7012149",
        "tgn:2001845",
        "tgn:7007825",
        "tgn:7029392"
    ],
    "tgn:id":2621258,
    "tgn:name":"Roan Creek",
    "tgn:placetype":[
        "aat:300008706"
    ]
},
  "bbox": [],
  "geometry": {"coordinates":[-88.4333,35.8667],"type":"Point"}
}