<<<<<<< HEAD
{
  "id": 7365984,
  "type": "Feature",
  "properties": {
    "tgn:hierarchy":[
        "tgn:7365984",
        "tgn:1000001",
        "tgn:7005589",
        "tgn:7005560",
        "tgn:7029392"
    ],
    "tgn:id":7365984,
    "tgn:name:es":"El Refugio",
    "tgn:placetype":[
        "aat:300008347"
    ]
},
  "bbox": [],
  "geometry": {"coordinates":[-100.015278,25.471389],"type":"Point"}
}
=======
{"geometry":{"type":"Point","coordinates":[-100.015278,25.471389]},"type":"Feature","properties":{"hierarchy":["tgn:7365984","tgn:1000001","tgn:7005589","tgn:7005560","tgn:7029392"],"placetype":["aat:300008347"],"id":7365984,"name:es":"El Refugio"}}
>>>>>>> 03f74aca74312dbeaf24d7e61306dd6a786dc3d0
