{
  "id": 7301460,
  "type": "Feature",
  "properties": {
    "tgn:hierarchy":[
        "tgn:7301460",
        "tgn:7002824",
        "tgn:1000003",
        "tgn:7002786",
        "tgn:1000095",
        "tgn:7029392"
    ],
    "tgn:id":7301460,
    "tgn:name":"Molinos",
    "tgn:placetype":[
        "aat:300008347"
    ]
},
  "bbox": [],
  "geometry": {"coordinates":[-9.183333,43.083333],"type":"Point"}
}