{
  "id": 7222425,
  "type": "Feature",
  "properties": {
    "tgn:hierarchy":[
        "tgn:7222425",
        "tgn:7002735",
        "tgn:7017076",
        "tgn:1000003",
        "tgn:1000074",
        "tgn:7029392"
    ],
    "tgn:id":7222425,
    "tgn:name":"Palaiopanay\u00eda",
    "tgn:placetype":[
        "aat:300008347"
    ]
},
  "bbox": [],
  "geometry": {"coordinates":[22.433333,36.983333],"type":"Point"}
}