{
  "id": 7243984,
  "type": "Feature",
  "properties": {
    "tgn:hierarchy":[
        "tgn:7243984",
        "tgn:7003465",
        "tgn:1000003",
        "tgn:1000063",
        "tgn:4012014",
        "tgn:7029392"
    ],
    "tgn:id":7243984,
    "tgn:name":"Jemeppe",
    "tgn:placetype":[
        "aat:300008347"
    ]
},
  "bbox": [],
  "geometry": {"coordinates":[5.316667,50.183333],"type":"Point"}
}