{
  "id": 2343581,
  "type": "Feature",
  "properties": {
    "tgn:hierarchy":[
        "tgn:2343581",
        "tgn:2001170",
        "tgn:1000001",
        "tgn:7012149",
        "tgn:7007523",
        "tgn:7029392"
    ],
    "tgn:id":2343581,
    "tgn:name":"Galena Hollow",
    "tgn:placetype":[
        "aat:300008761"
    ]
},
  "bbox": [],
  "geometry": {"coordinates":[-93.7667,36.6833],"type":"Point"}
}