{
  "id": 7453583,
  "type": "Feature",
  "properties": {
    "tgn:hierarchy":[
        "tgn:7453583",
        "tgn:7002444",
        "tgn:7008074",
        "tgn:1000003",
        "tgn:7008591",
        "tgn:7029392"
    ],
    "tgn:id":7453583,
    "tgn:name:en":"Cairn Head",
    "tgn:placetype":[
        "aat:300386846"
    ]
},
  "bbox": [],
  "geometry": {"coordinates":[-4.35,54.716667],"type":"Point"}
}