{
  "id": 2470733,
  "type": "Feature",
  "properties": {
    "tgn:hierarchy":[
        "tgn:2470733",
        "tgn:1000001",
        "tgn:7012149",
        "tgn:2001914",
        "tgn:7007825",
        "tgn:7029392"
    ],
    "tgn:id":2470733,
    "tgn:name":"Lost Branch",
    "tgn:placetype":[
        "aat:300008699"
    ]
},
  "bbox": [],
  "geometry": {"coordinates":[-83.6167,35.6167],"type":"Point"}
}