{
  "id": 7238304,
  "type": "Feature",
  "properties": {
    "tgn:hierarchy":[
        "tgn:7238304",
        "tgn:7003456",
        "tgn:1000003",
        "tgn:1000063",
        "tgn:7018236",
        "tgn:7029392"
    ],
    "tgn:id":7238304,
    "tgn:name":"Het Zand",
    "tgn:placetype":[
        "aat:300008347"
    ]
},
  "bbox": [],
  "geometry": {"coordinates":[4.505539,51.295828],"type":"Point"}
}