{
  "id": 2348284,
  "type": "Feature",
  "properties": {
    "tgn:hierarchy":[
        "tgn:2348284",
        "tgn:1000001",
        "tgn:2000462",
        "tgn:7012149",
        "tgn:7007250",
        "tgn:7029392"
    ],
    "tgn:id":2348284,
    "tgn:name":"Geyselman Lake",
    "tgn:placetype":[
        "aat:300008680"
    ]
},
  "bbox": [],
  "geometry": {"coordinates":[-116.1667,48.95],"type":"Point"}
}