{
  "id": 7528094,
  "type": "Feature",
  "properties": {
    "tgn:hierarchy":[
        "tgn:7528094",
        "tgn:7001242",
        "tgn:7016833",
        "tgn:1001335",
        "tgn:7029392"
    ],
    "tgn:id":7528094,
    "tgn:name:en":"Sinj\u0101r, Jaz\u012brat",
    "tgn:placetype":[
        "aat:300008791"
    ]
},
  "bbox": [],
  "geometry": {"coordinates":[30.938229,31.511293],"type":"Point"}
}