{
  "id": 2224276,
  "type": "Feature",
  "properties": {
    "tgn:hierarchy":[
        "tgn:2224276",
        "tgn:1000001",
        "tgn:7012149",
        "tgn:2001309",
        "tgn:7007524",
        "tgn:7029392"
    ],
    "tgn:id":2224276,
    "tgn:name":"Cascade Canal",
    "tgn:placetype":[
        "aat:300006075"
    ]
},
  "bbox": [],
  "geometry": {"coordinates":[-112.1167,47.7333],"type":"Point"}
}