{
  "id": 7030914,
  "type": "Feature",
  "properties": {
    "tgn:hierarchy":[
        "tgn:7030914",
        "tgn:7002445",
        "tgn:1000003",
        "tgn:7026520",
        "tgn:7008591",
        "tgn:7029392"
    ],
    "tgn:id":7030914,
    "tgn:name":"Pilsgate",
    "tgn:placetype":[
        "aat:300008347"
    ]
},
  "bbox": [],
  "geometry": {"coordinates":[-0.423,52.633],"type":"Point"}
}