<<<<<<< HEAD
{
  "id": 7020940,
  "type": "Feature",
  "properties": {
    "tgn:hierarchy":[
        "tgn:7020940",
        "tgn:1000001",
        "tgn:7012149",
        "tgn:2000476",
        "tgn:7007250",
        "tgn:7029392"
    ],
    "tgn:id":7020940,
    "tgn:name":"Handy Creek",
    "tgn:placetype":[
        "aat:300008706"
    ]
},
  "bbox": [],
  "geometry": {"coordinates":[-115.5,46.1667],"type":"Point"}
}
=======
{"geometry":{"type":"Point","coordinates":[-115.500000,46.166700]},"type":"Feature","properties":{"hierarchy":["tgn:7020940","tgn:1000001","tgn:7012149","tgn:2000476","tgn:7007250","tgn:7029392"],"placetype":["aat:300008706"],"id":7020940,"name:xx":"Handy Creek"}}
>>>>>>> 03f74aca74312dbeaf24d7e61306dd6a786dc3d0
