{
  "id": 2614643,
  "type": "Feature",
  "properties": {
    "tgn:hierarchy":[
        "tgn:2614643",
        "tgn:1000001",
        "tgn:2002241",
        "tgn:7012149",
        "tgn:7007920",
        "tgn:7029392"
    ],
    "tgn:id":2614643,
    "tgn:name":"Relief",
    "tgn:placetype":[
        "aat:300008347"
    ]
},
  "bbox": [],
  "geometry": {"coordinates":[-118.0833,46.45],"type":"Point"}
}