{
  "id": 7156975,
  "type": "Feature",
  "properties": {
    "tgn:hierarchy":[
        "tgn:7156975",
        "tgn:7000096",
        "tgn:1000003",
        "tgn:7000084",
        "tgn:7029392"
    ],
    "tgn:id":7156975,
    "tgn:name":"Kleiner See",
    "tgn:placetype":[
        "aat:300008680"
    ]
},
  "bbox": [],
  "geometry": {"coordinates":[14.366667,52.033333],"type":"Point"}
}