{
  "id": 7497066,
  "type": "Feature",
  "properties": {
    "tgn:hierarchy":[
        "tgn:7497066",
        "tgn:1000004",
        "tgn:1000454",
        "tgn:1000141",
        "tgn:7029392"
    ],
    "tgn:id":7497066,
    "tgn:name":"Hongshulin Zhan",
    "tgn:placetype":[
        "aat:300007783"
    ]
},
  "bbox": [],
  "geometry": {"coordinates":[121.459113,25.153231],"type":"Point"}
}