{
  "id": 2540643,
  "type": "Feature",
  "properties": {
    "tgn:hierarchy":[
        "tgn:2540643",
        "tgn:1000001",
        "tgn:7012149",
        "tgn:2001854",
        "tgn:7007825",
        "tgn:7029392"
    ],
    "tgn:id":2540643,
    "tgn:name":"Newton Spring",
    "tgn:placetype":[
        "aat:300008697"
    ]
},
  "bbox": [],
  "geometry": {"coordinates":[-84.9167,35.8333],"type":"Point"}
}