{
  "id": 2661630,
  "type": "Feature",
  "properties": {
    "tgn:hierarchy":[
        "tgn:2661630",
        "tgn:1000001",
        "tgn:7012149",
        "tgn:7014398",
        "tgn:7013961",
        "tgn:7029392"
    ],
    "tgn:id":2661630,
    "tgn:name":"Shriner Knob",
    "tgn:placetype":[
        "aat:300008798"
    ]
},
  "bbox": [],
  "geometry": {"coordinates":[-79.2333,38.5333],"type":"Point"}
}