{
  "id": 2491493,
  "type": "Feature",
  "properties": {
    "tgn:hierarchy":[
        "tgn:2491493",
        "tgn:1000001",
        "tgn:2001019",
        "tgn:7012149",
        "tgn:7007521",
        "tgn:7029392"
    ],
    "tgn:id":2491493,
    "tgn:name":"Maple Lake",
    "tgn:placetype":[
        "aat:300008680"
    ]
},
  "bbox": [],
  "geometry": {"coordinates":[-95.3667,45.7667],"type":"Point"}
}