{
  "id": 7203454,
  "type": "Feature",
  "properties": {
    "tgn:hierarchy":[
        "tgn:7203454",
        "tgn:1000003",
        "tgn:7003677",
        "tgn:7000084",
        "tgn:7029392"
    ],
    "tgn:id":7203454,
    "tgn:name":"B\u00f6swipper",
    "tgn:placetype":[
        "aat:300387200"
    ]
},
  "bbox": [],
  "geometry": {"coordinates":[7.45,51.116667],"type":"Point"}
}