{
  "id": 7013929,
  "type": "Feature",
  "properties": {
    "tgn:hierarchy":[
        "tgn:7013929",
        "tgn:1000001",
        "tgn:7006451",
        "tgn:7012149",
        "tgn:2000097",
        "tgn:7029392"
    ],
    "tgn:id":7013929,
    "tgn:name":"Phoenix",
    "tgn:placetype":[
        "aat:300387277",
        "aat:300008347",
        "aat:300008416",
        "aat:300387218",
        "aat:300008389",
        "aat:300387308",
        "aat:300005135",
        "aat:300264742",
        "aat:300387305",
        "aat:300387221",
        "aat:300387270",
        "aat:300387292",
        "aat:300387280",
        "aat:300387291",
        "aat:300387286"
    ]
},
  "bbox": [],
  "geometry": {"coordinates":[-112.0667,33.4333],"type":"Point"}
}