{
  "id": 2160531,
  "type": "Feature",
  "properties": {
    "tgn:hierarchy":[
        "tgn:2160531",
        "tgn:7016099",
        "tgn:1000001",
        "tgn:7012149",
        "tgn:7007516",
        "tgn:7029392"
    ],
    "tgn:id":2160531,
    "tgn:name":"Beetree",
    "tgn:placetype":[
        "aat:300008347"
    ]
},
  "bbox": [],
  "geometry": {"coordinates":[-76.6667,39.6833],"type":"Point"}
}