{
  "id": 1047429,
  "type": "Feature",
  "properties": {
    "tgn:hierarchy":[
        "tgn:1047429",
        "tgn:7007850",
        "tgn:1003491",
        "tgn:1000003",
        "tgn:1000080",
        "tgn:7029392"
    ],
    "tgn:id":1047429,
    "tgn:name":"Villa San Giovanni",
    "tgn:placetype":[
        "aat:300008347"
    ]
},
  "bbox": [],
  "geometry": {"coordinates":[15.633333,38.216667],"type":"Point"}
}