{
  "id": 7412256,
  "type": "Feature",
  "properties": {
    "tgn:hierarchy":[
        "tgn:7412256",
        "tgn:7005587",
        "tgn:1000001",
        "tgn:7005560",
        "tgn:7029392"
    ],
    "tgn:id":7412256,
    "tgn:name:es":"Estaci\u00f3n Empresa Divisi\u00f3n Oro",
    "tgn:placetype":[
        "aat:300007783"
    ]
},
  "bbox": [],
  "geometry": {"coordinates":[-98.769444,20.130556],"type":"Point"}
}