{
  "id": 7078284,
  "type": "Feature",
  "properties": {
    "tgn:hierarchy":[
        "tgn:7078284",
        "tgn:1000003",
        "tgn:7003682",
        "tgn:7000084",
        "tgn:7029392"
    ],
    "tgn:id":7078284,
    "tgn:name":"Gut Zur Nette",
    "tgn:placetype":[
        "aat:300000206"
    ]
},
  "bbox": [],
  "geometry": {"coordinates":[7.45,50.416667],"type":"Point"}
}