{
  "id": 2184067,
  "type": "Feature",
  "properties": {
    "tgn:hierarchy":[
        "tgn:2184067",
        "tgn:2000001",
        "tgn:7002659",
        "tgn:1000001",
        "tgn:7012149",
        "tgn:7029392"
    ],
    "tgn:id":2184067,
    "tgn:name":"Boatyard Lake",
    "tgn:placetype":[
        "aat:300008680"
    ]
},
  "bbox": [],
  "geometry": {"coordinates":[-87.8333,31.1667],"type":"Point"}
}