{
  "id": 2587703,
  "type": "Feature",
  "properties": {
    "tgn:hierarchy":[
        "tgn:2587703",
        "tgn:1002143",
        "tgn:1000001",
        "tgn:7012149",
        "tgn:7007252",
        "tgn:7029392"
    ],
    "tgn:id":2587703,
    "tgn:name":"Pleasant Run Ditch",
    "tgn:placetype":[
        "aat:300006075"
    ]
},
  "bbox": [],
  "geometry": {"coordinates":[-85.2833,40.9333],"type":"Point"}
}