{
  "id": 2545545,
  "type": "Feature",
  "properties": {
    "tgn:hierarchy":[
        "tgn:2545545",
        "tgn:1000001",
        "tgn:7012149",
        "tgn:2001293",
        "tgn:7007524",
        "tgn:7029392"
    ],
    "tgn:id":2545545,
    "tgn:name":"North Fork Bull Creek",
    "tgn:placetype":[
        "aat:300008706"
    ]
},
  "bbox": [],
  "geometry": {"coordinates":[-110.1833,45.1333],"type":"Point"}
}