{
  "id": 2625810,
  "type": "Feature",
  "properties": {
    "tgn:hierarchy":[
        "tgn:2625810",
        "tgn:1000001",
        "tgn:7012149",
        "tgn:7007522",
        "tgn:7029392"
    ],
    "tgn:id":2625810,
    "tgn:name":"Rocky Branch",
    "tgn:placetype":[
        "aat:300008699"
    ]
},
  "bbox": [],
  "geometry": {"coordinates":[-89.65,31.3167],"type":"Point"}
}