{
  "id": 7279372,
  "type": "Feature",
  "properties": {
    "tgn:hierarchy":[
        "tgn:7279372",
        "tgn:1001623",
        "tgn:1000049",
        "tgn:1000002",
        "tgn:7029392"
    ],
    "tgn:id":7279372,
    "tgn:name":"Riveros, Punta",
    "tgn:placetype":[
        "aat:300386846"
    ]
},
  "bbox": [],
  "geometry": {"coordinates":[-74.633333,-46.833333],"type":"Point"}
}