{
  "id": 1010044,
  "type": "Feature",
  "properties": {
    "tgn:hierarchy":[
        "tgn:1010044",
        "tgn:7006219",
        "tgn:1000006",
        "tgn:7029392"
    ],
    "tgn:id":1010044,
    "tgn:name":"Horn, \u00celes De",
    "tgn:placetype":[
        "aat:300235114",
        "aat:300386853"
    ]
},
  "bbox": [],
  "geometry": {"coordinates":[-178.0833,-14.3167],"type":"Point"}
}