{
  "id": 7335906,
  "type": "Feature",
  "properties": {
    "tgn:hierarchy":[
        "tgn:7335906",
        "tgn:7008911",
        "tgn:1000003",
        "tgn:7002763",
        "tgn:1000095",
        "tgn:7029392"
    ],
    "tgn:id":7335906,
    "tgn:name":"Faya",
    "tgn:placetype":[
        "aat:300008347"
    ]
},
  "bbox": [],
  "geometry": {"coordinates":[-5.566667,43.383333],"type":"Point"}
}