{
  "id": 7448269,
  "type": "Feature",
  "properties": {
    "tgn:hierarchy":[
        "tgn:7448269",
        "tgn:7002445",
        "tgn:1000003",
        "tgn:7008166",
        "tgn:7008591",
        "tgn:7029392"
    ],
    "tgn:id":7448269,
    "tgn:name:en":"Runswick Bay",
    "tgn:placetype":[
        "aat:300132316"
    ]
},
  "bbox": [],
  "geometry": {"coordinates":[-0.7375,54.536944],"type":"Point"}
}