{
  "id": 2647812,
  "type": "Feature",
  "properties": {
    "tgn:hierarchy":[
        "tgn:2647812",
        "tgn:1000001",
        "tgn:7012149",
        "tgn:1002932",
        "tgn:7007710",
        "tgn:7029392"
    ],
    "tgn:id":2647812,
    "tgn:name":"Schooley Pond",
    "tgn:placetype":[
        "aat:300006191"
    ]
},
  "bbox": [],
  "geometry": {"coordinates":[-75.85,41.6833],"type":"Point"}
}