{
  "id": 2547683,
  "type": "Feature",
  "properties": {
    "tgn:hierarchy":[
        "tgn:2547683",
        "tgn:1000001",
        "tgn:2001787",
        "tgn:7012149",
        "tgn:7007713",
        "tgn:7029392"
    ],
    "tgn:id":2547683,
    "tgn:name":"North Fork Twelvemile Creek",
    "tgn:placetype":[
        "aat:300008706"
    ]
},
  "bbox": [],
  "geometry": {"coordinates":[-98.2333,43.5667],"type":"Point"}
}