{
  "id": 1074622,
  "type": "Feature",
  "properties": {
    "tgn:hierarchy":[
        "tgn:1074622",
        "tgn:1000004",
        "tgn:7000198",
        "tgn:7016694",
        "tgn:7029392"
    ],
    "tgn:id":1074622,
    "tgn:name":"Baleshwar",
    "tgn:placetype":[
        "aat:300008347"
    ]
},
  "bbox": [],
  "geometry": {"coordinates":[86.933477,21.492658],"type":"Point"}
}