{
  "id": 7085716,
  "type": "Feature",
  "properties": {
    "tgn:hierarchy":[
        "tgn:7085716",
        "tgn:1000003",
        "tgn:7003682",
        "tgn:7000084",
        "tgn:7029392"
    ],
    "tgn:id":7085716,
    "tgn:name":"Weidsteinh\u00f6he",
    "tgn:placetype":[
        "aat:300008777"
    ]
},
  "bbox": [],
  "geometry": {"coordinates":[7.55,49.233333],"type":"Point"}
}