{
  "id": 7400995,
  "type": "Feature",
  "properties": {
    "tgn:hierarchy":[
        "tgn:7400995",
        "tgn:1000001",
        "tgn:7005599",
        "tgn:7005560",
        "tgn:7029392"
    ],
    "tgn:id":7400995,
    "tgn:name":"Macuiltepec",
    "tgn:placetype":[
        "aat:300008347"
    ]
},
  "bbox": [],
  "geometry": {"coordinates":[-97.425,20.830556],"type":"Point"}
}