{
  "id": 2363621,
  "type": "Feature",
  "properties": {
    "tgn:hierarchy":[
        "tgn:2363621",
        "tgn:1002996",
        "tgn:1000001",
        "tgn:7012149",
        "tgn:7007711",
        "tgn:7029392"
    ],
    "tgn:id":2363621,
    "tgn:name":"Green Hill Cove",
    "tgn:placetype":[
        "aat:300132316"
    ]
},
  "bbox": [],
  "geometry": {"coordinates":[-71.5333,41.15],"type":"Point"}
}