{
  "id": 1021948,
  "type": "Feature",
  "properties": {
    "tgn:hierarchy":[
        "tgn:1021948",
        "tgn:7006064",
        "tgn:1000047",
        "tgn:7002455",
        "tgn:1000002",
        "tgn:7029392"
    ],
    "tgn:id":1021948,
    "tgn:name":"Lavras da Mangabeira",
    "tgn:placetype":[
        "aat:300008347"
    ]
},
  "bbox": [],
  "geometry": {"coordinates":[-38.9167,-6.6833],"type":"Point"}
}