{
  "id": 7112406,
  "type": "Feature",
  "properties": {
    "tgn:hierarchy":[
        "tgn:7112406",
        "tgn:1000003",
        "tgn:7000094",
        "tgn:7000084",
        "tgn:7029392"
    ],
    "tgn:id":7112406,
    "tgn:name":"Rhede Ort",
    "tgn:placetype":[
        "aat:300386846"
    ]
},
  "bbox": [],
  "geometry": {"coordinates":[12.55,54.383333],"type":"Point"}
}