{
  "id": 7342487,
  "type": "Feature",
  "properties": {
    "tgn:hierarchy":[
        "tgn:7342487",
        "tgn:7010420",
        "tgn:1000003",
        "tgn:7002795",
        "tgn:1000095",
        "tgn:7029392"
    ],
    "tgn:id":7342487,
    "tgn:name":"Calvache, R\u00edo",
    "tgn:placetype":[
        "aat:300008699"
    ]
},
  "bbox": [],
  "geometry": {"coordinates":[-3.066667,40.15],"type":"Point"}
}