{
  "id": 7292342,
  "type": "Feature",
  "properties": {
    "tgn:hierarchy":[
        "tgn:7292342",
        "tgn:1001699",
        "tgn:1000049",
        "tgn:1000002",
        "tgn:7029392"
    ],
    "tgn:id":7292342,
    "tgn:name":"El Trap\u00e9n",
    "tgn:placetype":[
        "aat:300000206"
    ]
},
  "bbox": [],
  "geometry": {"coordinates":[-73.166667,-41.533333],"type":"Point"}
}