{
  "id": 7504771,
  "type": "Feature",
  "properties": {
    "tgn:hierarchy":[
        "tgn:7504771",
        "tgn:7000508",
        "tgn:1008380",
        "tgn:1000226",
        "tgn:1000006",
        "tgn:7029392"
    ],
    "tgn:id":7504771,
    "tgn:name:en":"Hautapu Rocks",
    "tgn:placetype":[
        "aat:300011692"
    ]
},
  "bbox": [],
  "geometry": {"coordinates":[175.421111,-36.735556],"type":"Point"}
}