{
  "id": 7315094,
  "type": "Feature",
  "properties": {
    "tgn:hierarchy":[
        "tgn:7315094",
        "tgn:1001705",
        "tgn:1000049",
        "tgn:1000002",
        "tgn:7029392"
    ],
    "tgn:id":7315094,
    "tgn:name":"Los Culenes",
    "tgn:placetype":[
        "aat:300387200"
    ]
},
  "bbox": [],
  "geometry": {"coordinates":[-72.133333,-35.233333],"type":"Point"}
}