{
  "id": 7574981,
  "type": "Feature",
  "properties": {
    "tgn:hierarchy":[
        "tgn:7574981",
        "tgn:1000004",
        "tgn:1001842",
        "tgn:7000198",
        "tgn:7029392"
    ],
    "tgn:id":7574981,
    "tgn:name:en":"Kurtha",
    "tgn:placetype":[
        "aat:300008347"
    ]
},
  "bbox": [],
  "geometry": {"coordinates":[84.811044,25.124299],"type":"Point"}
}