{
  "id": 7562638,
  "type": "Feature",
  "properties": {
    "tgn:hierarchy":[
        "tgn:7562638",
        "tgn:1000004",
        "tgn:7000198",
        "tgn:7016722",
        "tgn:7029392"
    ],
    "tgn:id":7562638,
    "tgn:name:en":"Purwa D\u0101nda",
    "tgn:placetype":[
        "aat:300008347"
    ]
},
  "bbox": [],
  "geometry": {"coordinates":[79.151757,26.483768],"type":"Point"}
}