{
  "id": 2574466,
  "type": "Feature",
  "properties": {
    "tgn:hierarchy":[
        "tgn:2574466",
        "tgn:1000001",
        "tgn:2001470",
        "tgn:7012149",
        "tgn:7007709",
        "tgn:7029392"
    ],
    "tgn:id":2574466,
    "tgn:name":"Pell Mell Pocosin",
    "tgn:placetype":[
        "aat:300008905"
    ]
},
  "bbox": [],
  "geometry": {"coordinates":[-76.9167,36.0833],"type":"Point"}
}