{
  "id": 7310925,
  "type": "Feature",
  "properties": {
    "tgn:hierarchy":[
        "tgn:7310925",
        "tgn:1001630",
        "tgn:1000049",
        "tgn:1000002",
        "tgn:7029392"
    ],
    "tgn:id":7310925,
    "tgn:name":"Morado, Quebrada del",
    "tgn:placetype":[
        "aat:300266554",
        "aat:300008699"
    ]
},
  "bbox": [],
  "geometry": {"coordinates":[-70.75,-26.75],"type":"Point"}
}