{
  "id": 2635765,
  "type": "Feature",
  "properties": {
    "tgn:hierarchy":[
        "tgn:2635765",
        "tgn:1000001",
        "tgn:7012149",
        "tgn:7007157",
        "tgn:1002857",
        "tgn:7029392"
    ],
    "tgn:id":2635765,
    "tgn:name":"Sablon",
    "tgn:placetype":[
        "aat:300008347"
    ]
},
  "bbox": [],
  "geometry": {"coordinates":[-114.9833,34.1667],"type":"Point"}
}