<<<<<<< HEAD
{
  "id": 7110647,
  "type": "Feature",
  "properties": {
    "tgn:hierarchy":[
        "tgn:7110647",
        "tgn:1000003",
        "tgn:7003688",
        "tgn:7000084",
        "tgn:7029392"
    ],
    "tgn:id":7110647,
    "tgn:name":"Puls",
    "tgn:placetype":[
        "aat:300008347"
    ]
},
  "bbox": [],
  "geometry": {"coordinates":[9.516667,54.083333],"type":"Point"}
}
=======
{"geometry":{"type":"Point","coordinates":[9.516667,54.083333]},"type":"Feature","properties":{"hierarchy":["tgn:7110647","tgn:1000003","tgn:7003688","tgn:7000084","tgn:7029392"],"placetype":["aat:300008347"],"id":7110647,"name:xx":"Puls"}}
>>>>>>> 03f74aca74312dbeaf24d7e61306dd6a786dc3d0
