{
  "id": 7137496,
  "type": "Feature",
  "properties": {
    "tgn:hierarchy":[
        "tgn:7137496",
        "tgn:7000096",
        "tgn:1000003",
        "tgn:7000084",
        "tgn:7029392"
    ],
    "tgn:id":7137496,
    "tgn:name":"F\u00f6rsterei Liepe",
    "tgn:placetype":[
        "aat:300004792"
    ]
},
  "bbox": [],
  "geometry": {"coordinates":[13.95,52.883333],"type":"Point"}
}