{
  "id": 2131016,
  "type": "Feature",
  "properties": {
    "tgn:hierarchy":[
        "tgn:2131016",
        "tgn:1000001",
        "tgn:1002493",
        "tgn:7012149",
        "tgn:7007565",
        "tgn:7029392"
    ],
    "tgn:id":2131016,
    "tgn:name":"Alpaugh Brook",
    "tgn:placetype":[
        "aat:300008699"
    ]
},
  "bbox": [],
  "geometry": {"coordinates":[-74.95,40.6833],"type":"Point"}
}