<<<<<<< HEAD
{
  "id": 2332780,
  "type": "Feature",
  "properties": {
    "tgn:hierarchy":[
        "tgn:2332780",
        "tgn:1000001",
        "tgn:7016172",
        "tgn:7012149",
        "tgn:2000135",
        "tgn:7029392"
    ],
    "tgn:id":2332780,
    "tgn:name":"Flowers Spring Creek",
    "tgn:placetype":[
        "aat:300008706"
    ]
},
  "bbox": [],
  "geometry": {"coordinates":[-94.0,34.1833],"type":"Point"}
}
=======
{"geometry":{"type":"Point","coordinates":[-94.000000,34.183300]},"type":"Feature","properties":{"hierarchy":["tgn:2332780","tgn:1000001","tgn:7016172","tgn:7012149","tgn:2000135","tgn:7029392"],"placetype":["aat:300008706"],"id":2332780,"name:xx":"Flowers Spring Creek"}}
>>>>>>> 03f74aca74312dbeaf24d7e61306dd6a786dc3d0
