<<<<<<< HEAD
{
  "id": 7372156,
  "type": "Feature",
  "properties": {
    "tgn:hierarchy":[
        "tgn:7372156",
        "tgn:7005586",
        "tgn:1000001",
        "tgn:7005560",
        "tgn:7029392"
    ],
    "tgn:id":7372156,
    "tgn:name":"La Esperanza",
    "tgn:placetype":[
        "aat:300008347"
    ]
},
  "bbox": [],
  "geometry": {"coordinates":[-104.9,20.116667],"type":"Point"}
}
=======
{"geometry":{"type":"Point","coordinates":[-104.900000,20.116667]},"type":"Feature","properties":{"hierarchy":["tgn:7372156","tgn:7005586","tgn:1000001","tgn:7005560","tgn:7029392"],"placetype":["aat:300008347"],"id":7372156,"name:xx":"La Esperanza"}}
>>>>>>> 03f74aca74312dbeaf24d7e61306dd6a786dc3d0
