{
  "id": 7498346,
  "type": "Feature",
  "properties": {
    "tgn:hierarchy":[
        "tgn:7498346",
        "tgn:1000004",
        "tgn:7001009",
        "tgn:1000141",
        "tgn:7029392"
    ],
    "tgn:id":7498346,
    "tgn:name":"Wenhua Daqiao",
    "tgn:placetype":[
        "aat:300007836"
    ]
},
  "bbox": [],
  "geometry": {"coordinates":[120.5279,24.2444],"type":"Point"}
}