{
  "id": 7526612,
  "type": "Feature",
  "properties": {
    "tgn:hierarchy":[
        "tgn:7526612",
        "tgn:7001242",
        "tgn:7016833",
        "tgn:1001091",
        "tgn:7029392"
    ],
    "tgn:id":7526612,
    "tgn:name":"Maq\u0101bir 'Arab al \u1e28i\u015fn",
    "tgn:placetype":[
        "aat:300266755"
    ]
},
  "bbox": [],
  "geometry": {"coordinates":[31.302676,30.131902],"type":"Point"}
}