{
  "id": 7424258,
  "type": "Feature",
  "properties": {
    "tgn:hierarchy":[
        "tgn:7424258",
        "tgn:1000001",
        "tgn:1001960",
        "tgn:7005560",
        "tgn:7029392"
    ],
    "tgn:id":7424258,
    "tgn:name":"Potrero de Novillos",
    "tgn:placetype":[
        "aat:300008347"
    ]
},
  "bbox": [],
  "geometry": {"coordinates":[-110.483333,29.483333],"type":"Point"}
}