{
  "id": 2130641,
  "type": "Feature",
  "properties": {
    "tgn:hierarchy":[
        "tgn:2130641",
        "tgn:1000001",
        "tgn:7012149",
        "tgn:2002047",
        "tgn:7007826",
        "tgn:7029392"
    ],
    "tgn:id":2130641,
    "tgn:name":"Alligator Lake",
    "tgn:placetype":[
        "aat:300008680"
    ]
},
  "bbox": [],
  "geometry": {"coordinates":[-93.55,30.8167],"type":"Point"}
}