{
  "id": 7301516,
  "type": "Feature",
  "properties": {
    "tgn:hierarchy":[
        "tgn:7301516",
        "tgn:7002758",
        "tgn:7002841",
        "tgn:1000003",
        "tgn:1000095",
        "tgn:7029392"
    ],
    "tgn:id":7301516,
    "tgn:name":"Miraflores, Arroyo de",
    "tgn:placetype":[
        "aat:300266554",
        "aat:300008699"
    ]
},
  "bbox": [],
  "geometry": {"coordinates":[-5.95,37.383333],"type":"Point"}
}