{
  "id": 2477169,
  "type": "Feature",
  "properties": {
    "tgn:hierarchy":[
        "tgn:2477169",
        "tgn:1000001",
        "tgn:7012149",
        "tgn:2002008",
        "tgn:7007826",
        "tgn:7029392"
    ],
    "tgn:id":2477169,
    "tgn:name":"Lynn Creek",
    "tgn:placetype":[
        "aat:300008706"
    ]
},
  "bbox": [],
  "geometry": {"coordinates":[-98.35,33.2667],"type":"Point"}
}