{
  "id": 7558574,
  "type": "Feature",
  "properties": {
    "tgn:hierarchy":[
        "tgn:7558574",
        "tgn:1009838",
        "tgn:7000204",
        "tgn:1000004",
        "tgn:7000198",
        "tgn:7029392"
    ],
    "tgn:id":7558574,
    "tgn:name:en":"Red Skin Island",
    "tgn:placetype":[
        "aat:300008791"
    ]
},
  "bbox": [],
  "geometry": {"coordinates":[92.583333,11.55],"type":"Point"}
}