{
  "id": 2758380,
  "type": "Feature",
  "properties": {
    "tgn:hierarchy":[
        "tgn:2758380",
        "tgn:1000001",
        "tgn:7012149",
        "tgn:1002993",
        "tgn:7007568",
        "tgn:7029392"
    ],
    "tgn:id":2758380,
    "tgn:name":"West Cambridge",
    "tgn:placetype":[
        "aat:300008347"
    ]
},
  "bbox": [],
  "geometry": {"coordinates":[-73.4667,42.9833],"type":"Point"}
}