{
  "id": 2466583,
  "type": "Feature",
  "properties": {
    "tgn:hierarchy":[
        "tgn:2466583",
        "tgn:1000001",
        "tgn:7012149",
        "tgn:2001220",
        "tgn:7007523",
        "tgn:7029392"
    ],
    "tgn:id":2466583,
    "tgn:name":"Long Branch",
    "tgn:placetype":[
        "aat:300008699"
    ]
},
  "bbox": [],
  "geometry": {"coordinates":[-92.6833,38.65],"type":"Point"}
}