{
  "id": 7425553,
  "type": "Feature",
  "properties": {
    "tgn:hierarchy":[
        "tgn:7425553",
        "tgn:7005581",
        "tgn:1000001",
        "tgn:7005560",
        "tgn:7029392"
    ],
    "tgn:id":7425553,
    "tgn:name":"El T\u00e1scate",
    "tgn:placetype":[
        "aat:300008347"
    ]
},
  "bbox": [],
  "geometry": {"coordinates":[-106.916667,28.116667],"type":"Point"}
}