{
  "id": 7545664,
  "type": "Feature",
  "properties": {
    "tgn:hierarchy":[
        "tgn:7545664",
        "tgn:1000004",
        "tgn:7031781",
        "tgn:7000198",
        "tgn:7029392"
    ],
    "tgn:id":7545664,
    "tgn:name:en":"B\u0101godori",
    "tgn:placetype":[
        "aat:300008347"
    ]
},
  "bbox": [],
  "geometry": {"coordinates":[82.366667,18.983333],"type":"Point"}
}