<<<<<<< HEAD
{
  "id": 2761533,
  "type": "Feature",
  "properties": {
    "tgn:hierarchy":[
        "tgn:2761533",
        "tgn:1000001",
        "tgn:7012149",
        "tgn:2000933",
        "tgn:7007515",
        "tgn:7029392"
    ],
    "tgn:id":2761533,
    "tgn:name":"West Outlet",
    "tgn:placetype":[
        "aat:300008699"
    ]
},
  "bbox": [],
  "geometry": {"coordinates":[-70.65,43.5],"type":"Point"}
}
=======
{"geometry":{"type":"Point","coordinates":[-70.650000,43.500000]},"type":"Feature","properties":{"hierarchy":["tgn:2761533","tgn:1000001","tgn:7012149","tgn:2000933","tgn:7007515","tgn:7029392"],"placetype":["aat:300008699"],"id":2761533,"name:xx":"West Outlet"}}
>>>>>>> 03f74aca74312dbeaf24d7e61306dd6a786dc3d0
