{
  "id": 1135395,
  "type": "Feature",
  "properties": {
    "tgn:hierarchy":[
        "tgn:1135395",
        "tgn:1000001",
        "tgn:1002665",
        "tgn:7012149",
        "tgn:7007517",
        "tgn:7029392"
    ],
    "tgn:id":1135395,
    "tgn:name":"Spencer Brook",
    "tgn:placetype":[
        "aat:300008703"
    ]
},
  "bbox": [],
  "geometry": {"coordinates":[-71.35,42.5167],"type":"Point"}
}