<<<<<<< HEAD
{
  "id": 2331824,
  "type": "Feature",
  "properties": {
    "tgn:hierarchy":[
        "tgn:2331824",
        "tgn:1000001",
        "tgn:7012149",
        "tgn:1002517",
        "tgn:7007523",
        "tgn:7029392"
    ],
    "tgn:id":2331824,
    "tgn:name":"Fletcher Branch",
    "tgn:placetype":[
        "aat:300008699"
    ]
},
  "bbox": [],
  "geometry": {"coordinates":[-90.5167,38.0167],"type":"Point"}
}
=======
{"geometry":{"type":"Point","coordinates":[-90.516700,38.016700]},"type":"Feature","properties":{"hierarchy":["tgn:2331824","tgn:1000001","tgn:7012149","tgn:1002517","tgn:7007523","tgn:7029392"],"placetype":["aat:300008699"],"id":2331824,"name:xx":"Fletcher Branch"}}
>>>>>>> 03f74aca74312dbeaf24d7e61306dd6a786dc3d0
