{
  "id": 2331824,
  "type": "Feature",
  "properties": {
    "tgn:hierarchy":[
        "tgn:2331824",
        "tgn:1000001",
        "tgn:7012149",
        "tgn:1002517",
        "tgn:7007523",
        "tgn:7029392"
    ],
    "tgn:id":2331824,
    "tgn:name":"Fletcher Branch",
    "tgn:placetype":[
        "aat:300008699"
    ]
},
  "bbox": [],
  "geometry": {"coordinates":[-90.5167,38.0167],"type":"Point"}
}