{
  "id": 7233016,
  "type": "Feature",
  "properties": {
    "tgn:hierarchy":[
        "tgn:7233016",
        "tgn:7002711",
        "tgn:7001338",
        "tgn:1000003",
        "tgn:1000074",
        "tgn:7029392"
    ],
    "tgn:id":7233016,
    "tgn:name":"Long\u00f3s",
    "tgn:placetype":[
        "aat:300008347"
    ]
},
  "bbox": [],
  "geometry": {"coordinates":[20.160833,39.225556],"type":"Point"}
}