{
  "id": 2372372,
  "type": "Feature",
  "properties": {
    "tgn:hierarchy":[
        "tgn:2372372",
        "tgn:1000001",
        "tgn:7012149",
        "tgn:1002312",
        "tgn:7007709",
        "tgn:7029392"
    ],
    "tgn:id":2372372,
    "tgn:name":"Halfway Point",
    "tgn:placetype":[
        "aat:300008850"
    ]
},
  "bbox": [],
  "geometry": {"coordinates":[-75.9667,36.4833],"type":"Point"}
}