{
  "id": 7219896,
  "type": "Feature",
  "properties": {
    "tgn:hierarchy":[
        "tgn:7219896",
        "tgn:7011330",
        "tgn:7002674",
        "tgn:1000003",
        "tgn:1000074",
        "tgn:7029392"
    ],
    "tgn:id":7219896,
    "tgn:name":"Katso\u00fandria",
    "tgn:placetype":[
        "aat:300387200"
    ]
},
  "bbox": [],
  "geometry": {"coordinates":[27.193333,36.861667],"type":"Point"}
}