{
  "id": 2202318,
  "type": "Feature",
  "properties": {
    "tgn:hierarchy":[
        "tgn:2202318",
        "tgn:1000001",
        "tgn:7012149",
        "tgn:1002862",
        "tgn:7007920",
        "tgn:7029392"
    ],
    "tgn:id":2202318,
    "tgn:name":"Buck Mountain",
    "tgn:placetype":[
        "aat:300008798"
    ]
},
  "bbox": [],
  "geometry": {"coordinates":[-122.85,48.6833],"type":"Point"}
}