{
  "id": 7073589,
  "type": "Feature",
  "properties": {
    "tgn:hierarchy":[
        "tgn:7073589",
        "tgn:7000096",
        "tgn:1000003",
        "tgn:7000084",
        "tgn:7029392"
    ],
    "tgn:id":7073589,
    "tgn:name":"Tangersdorfer See",
    "tgn:placetype":[
        "aat:300008680"
    ]
},
  "bbox": [],
  "geometry": {"coordinates":[13.333333,53.166667],"type":"Point"}
}