{
  "id": 2006869,
  "type": "Feature",
  "properties": {
    "tgn:hierarchy":[
        "tgn:2006869",
        "tgn:1000001",
        "tgn:7006451",
        "tgn:7012149",
        "tgn:2000097",
        "tgn:7029392"
    ],
    "tgn:id":2006869,
    "tgn:name":"Hassayampa",
    "tgn:placetype":[
        "aat:300008347",
        "aat:300387210"
    ]
},
  "bbox": [],
  "geometry": {"coordinates":[-112.7167,33.3333],"type":"Point"}
}