{
  "id": 2355977,
  "type": "Feature",
  "properties": {
    "tgn:hierarchy":[
        "tgn:2355977",
        "tgn:7002659",
        "tgn:1000001",
        "tgn:7012149",
        "tgn:2000041",
        "tgn:7029392"
    ],
    "tgn:id":2355977,
    "tgn:name":"Goose Pond",
    "tgn:placetype":[
        "aat:300008680"
    ]
},
  "bbox": [],
  "geometry": {"coordinates":[-86.8333,34.55],"type":"Point"}
}