{
  "id": 7156384,
  "type": "Feature",
  "properties": {
    "tgn:hierarchy":[
        "tgn:7156384",
        "tgn:7003669",
        "tgn:1000003",
        "tgn:7000084",
        "tgn:7029392"
    ],
    "tgn:id":7156384,
    "tgn:name":"Kirchbach",
    "tgn:placetype":[
        "aat:300008347"
    ]
},
  "bbox": [],
  "geometry": {"coordinates":[12.083333,47.733333],"type":"Point"}
}