{
  "id": 1018002,
  "type": "Feature",
  "properties": {
    "tgn:hierarchy":[
        "tgn:1018002",
        "tgn:1000001",
        "tgn:7005599",
        "tgn:7005560",
        "tgn:7029392"
    ],
    "tgn:id":1018002,
    "tgn:name":"Para\u00edso Novillero",
    "tgn:placetype":[
        "aat:300008347"
    ]
},
  "bbox": [],
  "geometry": {"coordinates":[-95.9833,18.2667],"type":"Point"}
}