{
  "id": 7280067,
  "type": "Feature",
  "properties": {
    "tgn:hierarchy":[
        "tgn:7280067",
        "tgn:1001702",
        "tgn:1000049",
        "tgn:1000002",
        "tgn:7029392"
    ],
    "tgn:id":7280067,
    "tgn:name":"Quod, Cabo",
    "tgn:placetype":[
        "aat:300386846"
    ]
},
  "bbox": [],
  "geometry": {"coordinates":[-72.55,-53.55],"type":"Point"}
}