<<<<<<< HEAD
{
  "id": 2255760,
  "type": "Feature",
  "properties": {
    "tgn:hierarchy":[
        "tgn:2255760",
        "tgn:7013349",
        "tgn:1000001",
        "tgn:7012149",
        "tgn:7007708",
        "tgn:7029392"
    ],
    "tgn:id":2255760,
    "tgn:name":"Copper Buttes",
    "tgn:placetype":[
        "aat:300008798"
    ]
},
  "bbox": [],
  "geometry": {"coordinates":[-117.5167,44.9333],"type":"Point"}
}
=======
{"geometry":{"type":"Point","coordinates":[-117.516700,44.933300]},"type":"Feature","properties":{"hierarchy":["tgn:2255760","tgn:7013349","tgn:1000001","tgn:7012149","tgn:7007708","tgn:7029392"],"placetype":["aat:300008798"],"id":2255760,"name:xx":"Copper Buttes"}}
>>>>>>> 03f74aca74312dbeaf24d7e61306dd6a786dc3d0
