{
  "id": 7292198,
  "type": "Feature",
  "properties": {
    "tgn:hierarchy":[
        "tgn:7292198",
        "tgn:1001623",
        "tgn:1000049",
        "tgn:1000002",
        "tgn:7029392"
    ],
    "tgn:id":7292198,
    "tgn:name":"El Fr\u00edo",
    "tgn:placetype":[
        "aat:300008347"
    ]
},
  "bbox": [],
  "geometry": {"coordinates":[-71.283333,-44.45],"type":"Point"}
}