{
  "id": 2301029,
  "type": "Feature",
  "properties": {
    "tgn:hierarchy":[
        "tgn:2301029",
        "tgn:1000001",
        "tgn:2001412",
        "tgn:7012149",
        "tgn:7007526",
        "tgn:7029392"
    ],
    "tgn:id":2301029,
    "tgn:name":"Dunfee, Mount",
    "tgn:placetype":[
        "aat:300008798"
    ]
},
  "bbox": [],
  "geometry": {"coordinates":[-117.3167,37.3333],"type":"Point"}
}