{
  "id": 1089771,
  "type": "Feature",
  "properties": {
    "tgn:hierarchy":[
        "tgn:1089771",
        "tgn:7001242",
        "tgn:1001266",
        "tgn:7000489",
        "tgn:7029392"
    ],
    "tgn:id":1089771,
    "tgn:name":"Debre May",
    "tgn:placetype":[
        "aat:300008347"
    ]
},
  "bbox": [],
  "geometry": {"coordinates":[37.4167,11.3333],"type":"Point"}
}