{
  "id": 2492015,
  "type": "Feature",
  "properties": {
    "tgn:hierarchy":[
        "tgn:2492015",
        "tgn:1000001",
        "tgn:7012149",
        "tgn:7007157",
        "tgn:1002857",
        "tgn:7029392"
    ],
    "tgn:id":2492015,
    "tgn:name":"Marbolite Mine",
    "tgn:placetype":[
        "aat:300000390"
    ]
},
  "bbox": [],
  "geometry": {"coordinates":[-115.8833,34.0667],"type":"Point"}
}