{
  "id": 7048068,
  "type": "Feature",
  "properties": {
    "tgn:hierarchy":[
        "tgn:7048068",
        "tgn:7003168",
        "tgn:1000003",
        "tgn:7009760",
        "tgn:1000080",
        "tgn:7029392"
    ],
    "tgn:id":7048068,
    "tgn:name":"Ciciano",
    "tgn:placetype":[
        "aat:300008347"
    ]
},
  "bbox": [],
  "geometry": {"coordinates":[11.066667,43.15],"type":"Point"}
}