{
  "id": 2556782,
  "type": "Feature",
  "properties": {
    "tgn:hierarchy":[
        "tgn:2556782",
        "tgn:1000001",
        "tgn:7012149",
        "tgn:2001722",
        "tgn:7007708",
        "tgn:7029392"
    ],
    "tgn:id":2556782,
    "tgn:name":"Old Cold Spring",
    "tgn:placetype":[
        "aat:300008697"
    ]
},
  "bbox": [],
  "geometry": {"coordinates":[-116.95,45.8833],"type":"Point"}
}