{
  "id": 2772831,
  "type": "Feature",
  "properties": {
    "tgn:hierarchy":[
        "tgn:2772831",
        "tgn:1000001",
        "tgn:2002260",
        "tgn:7012149",
        "tgn:7013961",
        "tgn:7029392"
    ],
    "tgn:id":2772831,
    "tgn:name":"Williams Hollow",
    "tgn:placetype":[
        "aat:300008761"
    ]
},
  "bbox": [],
  "geometry": {"coordinates":[-80.75,39.15],"type":"Point"}
}