{
  "id": 7021474,
  "type": "Feature",
  "properties": {
    "tgn:hierarchy":[
        "tgn:7021474",
        "tgn:1000001",
        "tgn:7012149",
        "tgn:2002300",
        "tgn:7013961",
        "tgn:7029392"
    ],
    "tgn:id":7021474,
    "tgn:name":"Mill Branch",
    "tgn:placetype":[
        "aat:300008699"
    ]
},
  "bbox": [],
  "geometry": {"coordinates":[-80.4167,38.3333],"type":"Point"}
}