{
  "id": 2265431,
  "type": "Feature",
  "properties": {
    "tgn:hierarchy":[
        "tgn:2265431",
        "tgn:1000001",
        "tgn:7012149",
        "tgn:1002862",
        "tgn:7007920",
        "tgn:7029392"
    ],
    "tgn:id":2265431,
    "tgn:name":"Crane Island",
    "tgn:placetype":[
        "aat:300008791"
    ]
},
  "bbox": [],
  "geometry": {"coordinates":[-122.9833,48.5833],"type":"Point"}
}