{
  "id": 2043674,
  "type": "Feature",
  "properties": {
    "tgn:hierarchy":[
        "tgn:2043674",
        "tgn:1000001",
        "tgn:2000862",
        "tgn:7012149",
        "tgn:7007256",
        "tgn:7029392"
    ],
    "tgn:id":2043674,
    "tgn:name":"Oil City",
    "tgn:placetype":[
        "aat:300008347"
    ]
},
  "bbox": [],
  "geometry": {"coordinates":[-93.9667,32.7333],"type":"Point"}
}