{
  "id": 2134806,
  "type": "Feature",
  "properties": {
    "tgn:hierarchy":[
        "tgn:2134806",
        "tgn:1000001",
        "tgn:7012149",
        "tgn:2000213",
        "tgn:7007158",
        "tgn:7029392"
    ],
    "tgn:id":2134806,
    "tgn:name":"Antelope Gulch",
    "tgn:placetype":[
        "aat:300008761"
    ]
},
  "bbox": [],
  "geometry": {"coordinates":[-105.85,38.6667],"type":"Point"}
}