{
  "id": 7315769,
  "type": "Feature",
  "properties": {
    "tgn:hierarchy":[
        "tgn:7315769",
        "tgn:1001768",
        "tgn:1000049",
        "tgn:1000002",
        "tgn:7029392"
    ],
    "tgn:id":7315769,
    "tgn:name":"Cepo, Quebrada del",
    "tgn:placetype":[
        "aat:300008699"
    ]
},
  "bbox": [],
  "geometry": {"coordinates":[-70.733333,-32.133333],"type":"Point"}
}