{
  "id": 7398193,
  "type": "Feature",
  "properties": {
    "tgn:hierarchy":[
        "tgn:7398193",
        "tgn:1000001",
        "tgn:1001960",
        "tgn:7005560",
        "tgn:7029392"
    ],
    "tgn:id":7398193,
    "tgn:name":"La Escondida",
    "tgn:placetype":[
        "aat:300008347"
    ]
},
  "bbox": [],
  "geometry": {"coordinates":[-111.128611,30.779444],"type":"Point"}
}