{
  "id": 7478337,
  "type": "Feature",
  "properties": {
    "tgn:hierarchy":[
        "tgn:7478337",
        "tgn:1000004",
        "tgn:7467799",
        "tgn:1000141",
        "tgn:7029392"
    ],
    "tgn:id":7478337,
    "tgn:name":"Guogou Qiao",
    "tgn:placetype":[
        "aat:300007836"
    ]
},
  "bbox": [],
  "geometry": {"coordinates":[120.556959,24.002382],"type":"Point"}
}