<<<<<<< HEAD
{
  "id": 7478337,
  "type": "Feature",
  "properties": {
    "tgn:hierarchy":[
        "tgn:7478337",
        "tgn:1000004",
        "tgn:7467799",
        "tgn:1000141",
        "tgn:7029392"
    ],
    "tgn:id":7478337,
    "tgn:name":"Guogou Qiao",
    "tgn:placetype":[
        "aat:300007836"
    ]
},
  "bbox": [],
  "geometry": {"coordinates":[120.556959,24.002382],"type":"Point"}
}
=======
{"geometry":{"type":"Point","coordinates":[120.556959,24.002382]},"type":"Feature","properties":{"hierarchy":["tgn:7478337","tgn:1000004","tgn:7467799","tgn:1000141","tgn:7029392"],"placetype":["aat:300007836"],"id":7478337,"name:xx":"Guogou Qiao"}}
>>>>>>> 03f74aca74312dbeaf24d7e61306dd6a786dc3d0
