{
  "id": 7557699,
  "type": "Feature",
  "properties": {
    "tgn:hierarchy":[
        "tgn:7557699",
        "tgn:1000004",
        "tgn:1001871",
        "tgn:7000198",
        "tgn:7029392"
    ],
    "tgn:id":7557699,
    "tgn:name:en":"Sam\u0101na",
    "tgn:placetype":[
        "aat:300008347"
    ]
},
  "bbox": [],
  "geometry": {"coordinates":[76.911355,29.903386],"type":"Point"}
}