{
  "id": 7548056,
  "type": "Feature",
  "properties": {
    "tgn:hierarchy":[
        "tgn:7548056",
        "tgn:1000004",
        "tgn:7000198",
        "tgn:7016694",
        "tgn:7029392"
    ],
    "tgn:id":7548056,
    "tgn:name:en":"Aul",
    "tgn:placetype":[
        "aat:300008347"
    ]
},
  "bbox": [],
  "geometry": {"coordinates":[86.648071,20.686592],"type":"Point"}
}