{
  "id": 7013770,
  "type": "Feature",
  "properties": {
    "tgn:hierarchy":[
        "tgn:7013770",
        "tgn:7003669",
        "tgn:1000003",
        "tgn:7000084",
        "tgn:7029392"
    ],
    "tgn:id":7013770,
    "tgn:name":"K\u00f6nigssee",
    "tgn:placetype":[
        "aat:300008680"
    ]
},
  "bbox": [],
  "geometry": {"coordinates":[12.966667,47.55],"type":"Point"}
}