{
  "id": 7002712,
  "type": "Feature",
  "properties": {
    "tgn:hierarchy":[
        "tgn:7002712",
        "tgn:7011168",
        "tgn:7001338",
        "tgn:1000003",
        "tgn:1000074",
        "tgn:7029392"
    ],
    "tgn:id":7002712,
    "tgn:name":"Lefk\u00e1s, N\u00edsos",
    "tgn:placetype":[
        "aat:300008791"
    ]
},
  "bbox": [],
  "geometry": {"coordinates":[20.633333,38.716667],"type":"Point"}
}