{
  "id": 2745497,
  "type": "Feature",
  "properties": {
    "tgn:hierarchy":[
        "tgn:2745497",
        "tgn:1000001",
        "tgn:2000863",
        "tgn:7012149",
        "tgn:7007256",
        "tgn:7029392"
    ],
    "tgn:id":2745497,
    "tgn:name":"Vinton Drainage Canal",
    "tgn:placetype":[
        "aat:300006075"
    ]
},
  "bbox": [],
  "geometry": {"coordinates":[-93.5667,30.1167],"type":"Point"}
}