{
  "id": 7553536,
  "type": "Feature",
  "properties": {
    "tgn:hierarchy":[
        "tgn:7553536",
        "tgn:1000004",
        "tgn:7000198",
        "tgn:7016722",
        "tgn:7029392"
    ],
    "tgn:id":7553536,
    "tgn:name:en":"Nibua Raiganj",
    "tgn:placetype":[
        "aat:300008347"
    ]
},
  "bbox": [],
  "geometry": {"coordinates":[83.893867,27.072001],"type":"Point"}
}