{
  "id": 2598733,
  "type": "Feature",
  "properties": {
    "tgn:hierarchy":[
        "tgn:2598733",
        "tgn:1000001",
        "tgn:2001816",
        "tgn:7012149",
        "tgn:7007713",
        "tgn:7029392"
    ],
    "tgn:id":2598733,
    "tgn:name":"Priest Canyon",
    "tgn:placetype":[
        "aat:300008761"
    ]
},
  "bbox": [],
  "geometry": {"coordinates":[-103.4167,44.2167],"type":"Point"}
}