{
  "id": 2694189,
  "type": "Feature",
  "properties": {
    "tgn:hierarchy":[
        "tgn:2694189",
        "tgn:1000001",
        "tgn:2001019",
        "tgn:7012149",
        "tgn:7007521",
        "tgn:7029392"
    ],
    "tgn:id":2694189,
    "tgn:name":"Stevens Lake",
    "tgn:placetype":[
        "aat:300008680"
    ]
},
  "bbox": [],
  "geometry": {"coordinates":[-95.1333,45.85],"type":"Point"}
}