{
  "id": 7432642,
  "type": "Feature",
  "properties": {
    "tgn:hierarchy":[
        "tgn:7432642",
        "tgn:7005586",
        "tgn:1000001",
        "tgn:7005560",
        "tgn:7029392"
    ],
    "tgn:id":7432642,
    "tgn:name":"Tomasillo, Cerro",
    "tgn:placetype":[
        "aat:300008795"
    ]
},
  "bbox": [],
  "geometry": {"coordinates":[-103.766667,20.733333],"type":"Point"}
}