{
  "id": 2127500,
  "type": "Feature",
  "properties": {
    "tgn:hierarchy":[
        "tgn:2127500",
        "tgn:1000001",
        "tgn:7012149",
        "tgn:1003040",
        "tgn:7007568",
        "tgn:7029392"
    ],
    "tgn:id":2127500,
    "tgn:name":"Akron Reservoir",
    "tgn:placetype":[
        "aat:300006191"
    ]
},
  "bbox": [],
  "geometry": {"coordinates":[-78.35,42.8667],"type":"Point"}
}