{
  "id": 1012532,
  "type": "Feature",
  "properties": {
    "tgn:hierarchy":[
        "tgn:1012532",
        "tgn:1000004",
        "tgn:1001433",
        "tgn:1000135",
        "tgn:7029392"
    ],
    "tgn:id":1012532,
    "tgn:name":"Sulauan Point",
    "tgn:placetype":[
        "aat:300386846"
    ]
},
  "bbox": [],
  "geometry": {"coordinates":[124.4833,8.6167],"type":"Point"}
}