<<<<<<< HEAD
{
  "id": 7368090,
  "type": "Feature",
  "properties": {
    "tgn:hierarchy":[
        "tgn:7368090",
        "tgn:1000001",
        "tgn:1001960",
        "tgn:7005560",
        "tgn:7029392"
    ],
    "tgn:id":7368090,
    "tgn:name":"Rancho Herford",
    "tgn:placetype":[
        "aat:300000241"
    ]
},
  "bbox": [],
  "geometry": {"coordinates":[-111.25,29.95],"type":"Point"}
}
=======
{"geometry":{"type":"Point","coordinates":[-111.250000,29.950000]},"type":"Feature","properties":{"hierarchy":["tgn:7368090","tgn:1000001","tgn:1001960","tgn:7005560","tgn:7029392"],"placetype":["aat:300000241"],"id":7368090,"name:xx":"Rancho Herford"}}
>>>>>>> 03f74aca74312dbeaf24d7e61306dd6a786dc3d0
