{
  "id": 2314974,
  "type": "Feature",
  "properties": {
    "tgn:hierarchy":[
        "tgn:2314974",
        "tgn:1000001",
        "tgn:7012149",
        "tgn:7007157",
        "tgn:2000185",
        "tgn:7029392"
    ],
    "tgn:id":2314974,
    "tgn:name":"Elkins Creek",
    "tgn:placetype":[
        "aat:300008706"
    ]
},
  "bbox": [],
  "geometry": {"coordinates":[-123.2833,38.9333],"type":"Point"}
}