{
  "id": 2453075,
  "type": "Feature",
  "properties": {
    "tgn:hierarchy":[
        "tgn:2453075",
        "tgn:1000001",
        "tgn:7012149",
        "tgn:7019676",
        "tgn:7007566",
        "tgn:7029392"
    ],
    "tgn:id":2453075,
    "tgn:name":"Little Canyon",
    "tgn:placetype":[
        "aat:300008761"
    ]
},
  "bbox": [],
  "geometry": {"coordinates":[-108.8833,35.2833],"type":"Point"}
}