{
  "id": 2549018,
  "type": "Feature",
  "properties": {
    "tgn:hierarchy":[
        "tgn:2549018",
        "tgn:1000001",
        "tgn:7016172",
        "tgn:7012149",
        "tgn:7029392"
    ],
    "tgn:id":2549018,
    "tgn:name":"North Prong Brushy Fork",
    "tgn:placetype":[
        "aat:300008699"
    ]
},
  "bbox": [],
  "geometry": {"coordinates":[-92.8167,35.5667],"type":"Point"}
}