{
  "id": 7508540,
  "type": "Feature",
  "properties": {
    "tgn:hierarchy":[
        "tgn:7508540",
        "tgn:1009227",
        "tgn:1000226",
        "tgn:7016729",
        "tgn:1000006",
        "tgn:7029392"
    ],
    "tgn:id":7508540,
    "tgn:name:en":"Otarawao",
    "tgn:placetype":[
        "aat:300008347"
    ]
},
  "bbox": [],
  "geometry": {"coordinates":[173.683333,-41.05],"type":"Point"}
}