{
  "id": 2716365,
  "type": "Feature",
  "properties": {
    "tgn:hierarchy":[
        "tgn:2716365",
        "tgn:1000001",
        "tgn:7012149",
        "tgn:2000183",
        "tgn:7007157",
        "tgn:7029392"
    ],
    "tgn:id":2716365,
    "tgn:name":"The Dunes",
    "tgn:placetype":[
        "aat:300008798"
    ]
},
  "bbox": [],
  "geometry": {"coordinates":[-117.85,36.75],"type":"Point"}
}