{
  "id": 2221307,
  "type": "Feature",
  "properties": {
    "tgn:hierarchy":[
        "tgn:2221307",
        "tgn:1000001",
        "tgn:7012149",
        "tgn:7014318",
        "tgn:7007568",
        "tgn:7029392"
    ],
    "tgn:id":2221307,
    "tgn:name":"Cardtown",
    "tgn:placetype":[
        "aat:300008347"
    ]
},
  "bbox": [],
  "geometry": {"coordinates":[-75.2333,42.6333],"type":"Point"}
}