{
  "id": 2003801,
  "type": "Feature",
  "properties": {
    "tgn:hierarchy":[
        "tgn:2003801",
        "tgn:7002659",
        "tgn:1000001",
        "tgn:7012149",
        "tgn:2000056",
        "tgn:7029392"
    ],
    "tgn:id":2003801,
    "tgn:name":"Hatchechubbee",
    "tgn:placetype":[
        "aat:300008347"
    ]
},
  "bbox": [],
  "geometry": {"coordinates":[-85.2667,32.2667],"type":"Point"}
}