{
  "id": 2703863,
  "type": "Feature",
  "properties": {
    "tgn:hierarchy":[
        "tgn:2703863",
        "tgn:1000001",
        "tgn:7012149",
        "tgn:2000282",
        "tgn:7007240",
        "tgn:7029392"
    ],
    "tgn:id":2703863,
    "tgn:name":"Suncoast Keys, The",
    "tgn:placetype":[
        "aat:300008791"
    ]
},
  "bbox": [],
  "geometry": {"coordinates":[-82.7167,28.8167],"type":"Point"}
}