{
  "id": 7402867,
  "type": "Feature",
  "properties": {
    "tgn:hierarchy":[
        "tgn:7402867",
        "tgn:1000001",
        "tgn:1001906",
        "tgn:7005560",
        "tgn:7029392"
    ],
    "tgn:id":7402867,
    "tgn:name":"El Berrinche",
    "tgn:placetype":[
        "aat:300008347"
    ]
},
  "bbox": [],
  "geometry": {"coordinates":[-104.725,21.633333],"type":"Point"}
}