<<<<<<< HEAD
{
  "id": 2333022,
  "type": "Feature",
  "properties": {
    "tgn:hierarchy":[
        "tgn:2333022",
        "tgn:1000001",
        "tgn:7012149",
        "tgn:7007158",
        "tgn:2000245",
        "tgn:7029392"
    ],
    "tgn:id":2333022,
    "tgn:name":"Fly Creek",
    "tgn:placetype":[
        "aat:300008706"
    ]
},
  "bbox": [],
  "geometry": {"coordinates":[-107.2167,40.9167],"type":"Point"}
}
=======
{"geometry":{"type":"Point","coordinates":[-107.216700,40.916700]},"type":"Feature","properties":{"hierarchy":["tgn:2333022","tgn:1000001","tgn:7012149","tgn:7007158","tgn:2000245","tgn:7029392"],"placetype":["aat:300008706"],"id":2333022,"name:xx":"Fly Creek"}}
>>>>>>> 03f74aca74312dbeaf24d7e61306dd6a786dc3d0
