{
  "id": 7428107,
  "type": "Feature",
  "properties": {
    "tgn:hierarchy":[
        "tgn:7428107",
        "tgn:1000001",
        "tgn:7005594",
        "tgn:7005560",
        "tgn:7029392"
    ],
    "tgn:id":7428107,
    "tgn:name":"Ojo de Agua",
    "tgn:placetype":[
        "aat:300008347"
    ]
},
  "bbox": [],
  "geometry": {"coordinates":[-99.183333,22.316667],"type":"Point"}
}