{
  "id": 7323676,
  "type": "Feature",
  "properties": {
    "tgn:hierarchy":[
        "tgn:7323676",
        "tgn:7002807",
        "tgn:1000003",
        "tgn:7003837",
        "tgn:1000095",
        "tgn:7029392"
    ],
    "tgn:id":7323676,
    "tgn:name":"Rivillas, Arroyo de",
    "tgn:placetype":[
        "aat:300266554",
        "aat:300008699"
    ]
},
  "bbox": [],
  "geometry": {"coordinates":[-6.966667,38.866667],"type":"Point"}
}