{
  "id": 2605332,
  "type": "Feature",
  "properties": {
    "tgn:hierarchy":[
        "tgn:2605332",
        "tgn:1000001",
        "tgn:7012149",
        "tgn:2002172",
        "tgn:7007919",
        "tgn:7029392"
    ],
    "tgn:id":2605332,
    "tgn:name":"Ragged Run",
    "tgn:placetype":[
        "aat:300008699"
    ]
},
  "bbox": [],
  "geometry": {"coordinates":[-78.3167,38.5333],"type":"Point"}
}