{
  "id": 7555338,
  "type": "Feature",
  "properties": {
    "tgn:hierarchy":[
        "tgn:7555338",
        "tgn:1000004",
        "tgn:7000198",
        "tgn:7016788",
        "tgn:7029392"
    ],
    "tgn:id":7555338,
    "tgn:name:en":"Mand\u0101vara",
    "tgn:placetype":[
        "aat:300008347"
    ]
},
  "bbox": [],
  "geometry": {"coordinates":[74.837941,27.049746],"type":"Point"}
}