<<<<<<< HEAD
{
  "id": 2709550,
  "type": "Feature",
  "properties": {
    "tgn:hierarchy":[
        "tgn:2709550",
        "tgn:1000001",
        "tgn:7012149",
        "tgn:2000826",
        "tgn:7007255",
        "tgn:7029392"
    ],
    "tgn:id":2709550,
    "tgn:name":"Tackett Hollow",
    "tgn:placetype":[
        "aat:300008761"
    ]
},
  "bbox": [],
  "geometry": {"coordinates":[-83.6833,37.9667],"type":"Point"}
}
=======
{"geometry":{"type":"Point","coordinates":[-83.683300,37.966700]},"type":"Feature","properties":{"hierarchy":["tgn:2709550","tgn:1000001","tgn:7012149","tgn:2000826","tgn:7007255","tgn:7029392"],"placetype":["aat:300008761"],"id":2709550,"name:xx":"Tackett Hollow"}}
>>>>>>> 03f74aca74312dbeaf24d7e61306dd6a786dc3d0
