{
  "id": 2680357,
  "type": "Feature",
  "properties": {
    "tgn:hierarchy":[
        "tgn:2680357",
        "tgn:1000001",
        "tgn:7012149",
        "tgn:7016020",
        "tgn:7007710",
        "tgn:7029392"
    ],
    "tgn:id":2680357,
    "tgn:name":"South Fork West Branch Potato Creek",
    "tgn:placetype":[
        "aat:300008706"
    ]
},
  "bbox": [],
  "geometry": {"coordinates":[-78.4333,41.6167],"type":"Point"}
}