{
  "id": 7552751,
  "type": "Feature",
  "properties": {
    "tgn:hierarchy":[
        "tgn:7552751",
        "tgn:1000004",
        "tgn:7000198",
        "tgn:7031786",
        "tgn:7029392"
    ],
    "tgn:id":7552751,
    "tgn:name:en":"Mug\u0101ra",
    "tgn:placetype":[
        "aat:300008347"
    ]
},
  "bbox": [],
  "geometry": {"coordinates":[80.257365,30.087912],"type":"Point"}
}