{
  "id": 2372333,
  "type": "Feature",
  "properties": {
    "tgn:hierarchy":[
        "tgn:2372333",
        "tgn:1000001",
        "tgn:7012149",
        "tgn:2002124",
        "tgn:7007827",
        "tgn:7029392"
    ],
    "tgn:id":2372333,
    "tgn:name":"Halfway Hollow",
    "tgn:placetype":[
        "aat:300008761"
    ]
},
  "bbox": [],
  "geometry": {"coordinates":[-109.7167,40.4833],"type":"Point"}
}