{
  "id": 2488535,
  "type": "Feature",
  "properties": {
    "tgn:hierarchy":[
        "tgn:2488535",
        "tgn:1000001",
        "tgn:7012149",
        "tgn:2002126",
        "tgn:7007827",
        "tgn:7029392"
    ],
    "tgn:id":2488535,
    "tgn:name":"Mahogany Spring",
    "tgn:placetype":[
        "aat:300008697"
    ]
},
  "bbox": [],
  "geometry": {"coordinates":[-111.4833,40.5333],"type":"Point"}
}