{
  "id": 7292017,
  "type": "Feature",
  "properties": {
    "tgn:hierarchy":[
        "tgn:7292017",
        "tgn:1001708",
        "tgn:1000049",
        "tgn:1000002",
        "tgn:7029392"
    ],
    "tgn:id":7292017,
    "tgn:name":"El Gallito, Cerro",
    "tgn:placetype":[
        "aat:300008795"
    ]
},
  "bbox": [],
  "geometry": {"coordinates":[-71.033333,-33.933333],"type":"Point"}
}