<<<<<<< HEAD
{
  "id": 2333541,
  "type": "Feature",
  "properties": {
    "tgn:hierarchy":[
        "tgn:2333541",
        "tgn:1000001",
        "tgn:7012149",
        "tgn:2002252",
        "tgn:7007920",
        "tgn:7029392"
    ],
    "tgn:id":2333541,
    "tgn:name":"Folsom Lake",
    "tgn:placetype":[
        "aat:300008680"
    ]
},
  "bbox": [],
  "geometry": {"coordinates":[-117.8833,47.2167],"type":"Point"}
}
=======
{"geometry":{"type":"Point","coordinates":[-117.883300,47.216700]},"type":"Feature","properties":{"hierarchy":["tgn:2333541","tgn:1000001","tgn:7012149","tgn:2002252","tgn:7007920","tgn:7029392"],"placetype":["aat:300008680"],"id":2333541,"name:xx":"Folsom Lake"}}
>>>>>>> 03f74aca74312dbeaf24d7e61306dd6a786dc3d0
