{
  "id": 1107623,
  "type": "Feature",
  "properties": {
    "tgn:hierarchy":[
        "tgn:1107623",
        "tgn:1007657",
        "tgn:1002534",
        "tgn:1000001",
        "tgn:7012149",
        "tgn:7007249",
        "tgn:7029392"
    ],
    "tgn:id":1107623,
    "tgn:name":"Waialeale",
    "tgn:placetype":[
        "aat:300055621"
    ]
},
  "bbox": [],
  "geometry": {"coordinates":[-159.4833,22.0667],"type":"Point"}
}