{
  "id": 7095967,
  "type": "Feature",
  "properties": {
    "tgn:hierarchy":[
        "tgn:7095967",
        "tgn:1000003",
        "tgn:7003678",
        "tgn:7000084",
        "tgn:7029392"
    ],
    "tgn:id":7095967,
    "tgn:name":"Schwarz",
    "tgn:placetype":[
        "aat:300008347"
    ]
},
  "bbox": [],
  "geometry": {"coordinates":[9.416667,50.716667],"type":"Point"}
}