{
  "id": 1098570,
  "type": "Feature",
  "properties": {
    "tgn:hierarchy":[
        "tgn:1098570",
        "tgn:7000490",
        "tgn:1000006",
        "tgn:7001834",
        "tgn:7029392"
    ],
    "tgn:id":1098570,
    "tgn:name":"Wondinong",
    "tgn:placetype":[
        "aat:300008347"
    ]
},
  "bbox": [],
  "geometry": {"coordinates":[118.4167,-27.8667],"type":"Point"}
}