{
  "id": 2003548,
  "type": "Feature",
  "properties": {
    "tgn:hierarchy":[
        "tgn:2003548",
        "tgn:2000000",
        "tgn:7002659",
        "tgn:1000001",
        "tgn:7012149",
        "tgn:7029392"
    ],
    "tgn:id":2003548,
    "tgn:name":"Forester",
    "tgn:placetype":[
        "aat:300008347"
    ]
},
  "bbox": [],
  "geometry": {"coordinates":[-86.5833,32.4333],"type":"Point"}
}