{
  "id": 7125175,
  "type": "Feature",
  "properties": {
    "tgn:hierarchy":[
        "tgn:7125175",
        "tgn:1000003",
        "tgn:7003676",
        "tgn:7000084",
        "tgn:7029392"
    ],
    "tgn:id":7125175,
    "tgn:name":"Nette",
    "tgn:placetype":[
        "aat:300008699"
    ]
},
  "bbox": [],
  "geometry": {"coordinates":[8.033333,52.283333],"type":"Point"}
}