{
  "id": 7368607,
  "type": "Feature",
  "properties": {
    "tgn:hierarchy":[
        "tgn:7368607",
        "tgn:7005578",
        "tgn:1000001",
        "tgn:7005560",
        "tgn:7029392"
    ],
    "tgn:id":7368607,
    "tgn:name":"Isla de Aguada",
    "tgn:placetype":[
        "aat:300008347"
    ]
},
  "bbox": [],
  "geometry": {"coordinates":[-91.466667,18.783333],"type":"Point"}
}