{
  "id": 7420090,
  "type": "Feature",
  "properties": {
    "tgn:hierarchy":[
        "tgn:7420090",
        "tgn:1000001",
        "tgn:7005589",
        "tgn:7005560",
        "tgn:7029392"
    ],
    "tgn:id":7420090,
    "tgn:name:es":"El Aguajito",
    "tgn:placetype":[
        "aat:300008347"
    ]
},
  "bbox": [],
  "geometry": {"coordinates":[-100.359167,26.249444],"type":"Point"}
}