{
  "id": 7561623,
  "type": "Feature",
  "properties": {
    "tgn:hierarchy":[
        "tgn:7561623",
        "tgn:1000004",
        "tgn:7000198",
        "tgn:7016722",
        "tgn:7029392"
    ],
    "tgn:id":7561623,
    "tgn:name:en":"Sabsinghpur",
    "tgn:placetype":[
        "aat:300008347"
    ]
},
  "bbox": [],
  "geometry": {"coordinates":[79.334798,27.127539],"type":"Point"}
}