{
  "id": 7377381,
  "type": "Feature",
  "properties": {
    "tgn:hierarchy":[
        "tgn:7377381",
        "tgn:7005586",
        "tgn:1000001",
        "tgn:7005560",
        "tgn:7029392"
    ],
    "tgn:id":7377381,
    "tgn:name":"La Pila",
    "tgn:placetype":[
        "aat:300008688"
    ]
},
  "bbox": [],
  "geometry": {"coordinates":[-104.016667,20.183333],"type":"Point"}
}