{
  "id": 7514839,
  "type": "Feature",
  "properties": {
    "tgn:hierarchy":[
        "tgn:7514839",
        "tgn:1009227",
        "tgn:1000226",
        "tgn:7520095",
        "tgn:1000006",
        "tgn:7029392"
    ],
    "tgn:id":7514839,
    "tgn:name:en":"Cupola, Mount",
    "tgn:placetype":[
        "aat:300008795"
    ]
},
  "bbox": [],
  "geometry": {"coordinates":[172.733333,-41.983333],"type":"Point"}
}