{
  "id": 2417234,
  "type": "Feature",
  "properties": {
    "tgn:hierarchy":[
        "tgn:2417234",
        "tgn:1000001",
        "tgn:7019982",
        "tgn:7012149",
        "tgn:7007517",
        "tgn:7029392"
    ],
    "tgn:id":2417234,
    "tgn:name":"Jacks Brook",
    "tgn:placetype":[
        "aat:300008699"
    ]
},
  "bbox": [],
  "geometry": {"coordinates":[-72.7833,42.0833],"type":"Point"}
}