{
  "id": 2227775,
  "type": "Feature",
  "properties": {
    "tgn:hierarchy":[
        "tgn:2227775",
        "tgn:1000001",
        "tgn:7012149",
        "tgn:2001057",
        "tgn:7007521",
        "tgn:7029392"
    ],
    "tgn:id":2227775,
    "tgn:name":"Cazenovia",
    "tgn:placetype":[
        "aat:300008347"
    ]
},
  "bbox": [],
  "geometry": {"coordinates":[-96.3667,44.0667],"type":"Point"}
}