{
  "id": 7570186,
  "type": "Feature",
  "properties": {
    "tgn:hierarchy":[
        "tgn:7570186",
        "tgn:1000004",
        "tgn:7000198",
        "tgn:7016788",
        "tgn:7029392"
    ],
    "tgn:id":7570186,
    "tgn:name:en":"Jyotipura",
    "tgn:placetype":[
        "aat:300008347"
    ]
},
  "bbox": [],
  "geometry": {"coordinates":[75.65338,25.846315],"type":"Point"}
}