{
  "id": 2416519,
  "type": "Feature",
  "properties": {
    "tgn:hierarchy":[
        "tgn:2416519",
        "tgn:1000001",
        "tgn:7012149",
        "tgn:2001672",
        "tgn:7007707",
        "tgn:7029392"
    ],
    "tgn:id":2416519,
    "tgn:name":"Jack Creek",
    "tgn:placetype":[
        "aat:300008706"
    ]
},
  "bbox": [],
  "geometry": {"coordinates":[-96.9833,34.3667],"type":"Point"}
}