{
  "id": 7581961,
  "type": "Feature",
  "properties": {
    "tgn:hierarchy":[
        "tgn:7581961",
        "tgn:1000004",
        "tgn:7000198",
        "tgn:7000799",
        "tgn:7029392"
    ],
    "tgn:id":7581961,
    "tgn:name:en":"Trahag\u0101m",
    "tgn:placetype":[
        "aat:300008347"
    ]
},
  "bbox": [],
  "geometry": {"coordinates":[74.172238,34.514209],"type":"Point"}
}