{
  "id": 7277620,
  "type": "Feature",
  "properties": {
    "tgn:hierarchy":[
        "tgn:7277620",
        "tgn:1001702",
        "tgn:1000049",
        "tgn:1000002",
        "tgn:7029392"
    ],
    "tgn:id":7277620,
    "tgn:name":"Wilcke, Seno",
    "tgn:placetype":[
        "aat:300008676"
    ]
},
  "bbox": [],
  "geometry": {"coordinates":[-75.15,-49.133333],"type":"Point"}
}