{
  "id": 1022650,
  "type": "Feature",
  "properties": {
    "tgn:hierarchy":[
        "tgn:1022650",
        "tgn:7006064",
        "tgn:1000047",
        "tgn:7002455",
        "tgn:1000002",
        "tgn:7029392"
    ],
    "tgn:id":1022650,
    "tgn:name":"Reriutaba",
    "tgn:placetype":[
        "aat:300008347"
    ]
},
  "bbox": [],
  "geometry": {"coordinates":[-40.5833,-4.1333],"type":"Point"}
}