{
  "id": 2663298,
  "type": "Feature",
  "properties": {
    "tgn:hierarchy":[
        "tgn:2663298",
        "tgn:1000001",
        "tgn:7012149",
        "tgn:1002882",
        "tgn:7007568",
        "tgn:7029392"
    ],
    "tgn:id":2663298,
    "tgn:name":"Silver Creek",
    "tgn:placetype":[
        "aat:300008706"
    ]
},
  "bbox": [],
  "geometry": {"coordinates":[-76.8333,42.8167],"type":"Point"}
}