<<<<<<< HEAD
{
  "id": 7489974,
  "type": "Feature",
  "properties": {
    "tgn:hierarchy":[
        "tgn:7489974",
        "tgn:1000004",
        "tgn:7001009",
        "tgn:1000141",
        "tgn:7029392"
    ],
    "tgn:id":7489974,
    "tgn:name":"Shifen",
    "tgn:placetype":[
        "aat:300008347"
    ]
},
  "bbox": [],
  "geometry": {"coordinates":[120.7869,24.2511],"type":"Point"}
}
=======
{"geometry":{"type":"Point","coordinates":[120.786900,24.251100]},"type":"Feature","properties":{"hierarchy":["tgn:7489974","tgn:1000004","tgn:7001009","tgn:1000141","tgn:7029392"],"placetype":["aat:300008347"],"id":7489974,"name:xx":"Shifen"}}
>>>>>>> 03f74aca74312dbeaf24d7e61306dd6a786dc3d0
