{
  "id": 7290691,
  "type": "Feature",
  "properties": {
    "tgn:hierarchy":[
        "tgn:7290691",
        "tgn:7016598",
        "tgn:1000049",
        "tgn:1000002",
        "tgn:7029392"
    ],
    "tgn:id":7290691,
    "tgn:name":"Cumuri",
    "tgn:placetype":[
        "aat:300387200"
    ]
},
  "bbox": [],
  "geometry": {"coordinates":[-68.583333,-21.633333],"type":"Point"}
}