{
  "id": 7253073,
  "type": "Feature",
  "properties": {
    "tgn:hierarchy":[
        "tgn:7253073",
        "tgn:7007877",
        "tgn:1000003",
        "tgn:1000063",
        "tgn:4012014",
        "tgn:7029392"
    ],
    "tgn:id":7253073,
    "tgn:name":"Sart les Moines",
    "tgn:placetype":[
        "aat:300008347"
    ]
},
  "bbox": [],
  "geometry": {"coordinates":[4.416667,50.45],"type":"Point"}
}