{
  "id": 2288825,
  "type": "Feature",
  "properties": {
    "tgn:hierarchy":[
        "tgn:2288825",
        "tgn:1000001",
        "tgn:7012149",
        "tgn:2001222",
        "tgn:7007523",
        "tgn:7029392"
    ],
    "tgn:id":2288825,
    "tgn:name":"Ditch Number 40",
    "tgn:placetype":[
        "aat:300006075"
    ]
},
  "bbox": [],
  "geometry": {"coordinates":[-89.7333,36.5833],"type":"Point"}
}