{
  "id": 7531925,
  "type": "Feature",
  "properties": {
    "tgn:hierarchy":[
        "tgn:7531925",
        "tgn:7001242",
        "tgn:7016833",
        "tgn:1001091",
        "tgn:7029392"
    ],
    "tgn:id":7531925,
    "tgn:name":"Mustashf\u00e1 ar R\u0101'\u012b a\u015f \u015e\u0101li\u1e29",
    "tgn:placetype":[
        "aat:300006676"
    ]
},
  "bbox": [],
  "geometry": {"coordinates":[31.245694,30.076589],"type":"Point"}
}