{
  "id": 2473627,
  "type": "Feature",
  "properties": {
    "tgn:hierarchy":[
        "tgn:2473627",
        "tgn:1000001",
        "tgn:7012149",
        "tgn:2001291",
        "tgn:7007524",
        "tgn:7029392"
    ],
    "tgn:id":2473627,
    "tgn:name":"Lower Dick Creek Mine",
    "tgn:placetype":[
        "aat:300000390"
    ]
},
  "bbox": [],
  "geometry": {"coordinates":[-114.35,46.6833],"type":"Point"}
}