<<<<<<< HEAD
{
  "id": 2157643,
  "type": "Feature",
  "properties": {
    "tgn:hierarchy":[
        "tgn:2157643",
        "tgn:1000001",
        "tgn:7012149",
        "tgn:2002125",
        "tgn:7007827",
        "tgn:7029392"
    ],
    "tgn:id":2157643,
    "tgn:name":"Beaver Dam Creek",
    "tgn:placetype":[
        "aat:300008706"
    ]
},
  "bbox": [],
  "geometry": {"coordinates":[-111.6333,39.9],"type":"Point"}
}
=======
{"geometry":{"type":"Point","coordinates":[-111.633300,39.900000]},"type":"Feature","properties":{"hierarchy":["tgn:2157643","tgn:1000001","tgn:7012149","tgn:2002125","tgn:7007827","tgn:7029392"],"placetype":["aat:300008706"],"id":2157643,"name:xx":"Beaver Dam Creek"}}
>>>>>>> 03f74aca74312dbeaf24d7e61306dd6a786dc3d0
