{
  "id": 2254655,
  "type": "Feature",
  "properties": {
    "tgn:hierarchy":[
        "tgn:2254655",
        "tgn:1000001",
        "tgn:7012149",
        "tgn:7007157",
        "tgn:1003046",
        "tgn:7029392"
    ],
    "tgn:id":2254655,
    "tgn:name":"Coon Lake",
    "tgn:placetype":[
        "aat:300008680"
    ]
},
  "bbox": [],
  "geometry": {"coordinates":[-121.6667,38.75],"type":"Point"}
}