{
  "id": 1005749,
  "type": "Feature",
  "properties": {
    "tgn:hierarchy":[
        "tgn:1005749",
        "tgn:1000003",
        "tgn:7003122",
        "tgn:7003157",
        "tgn:1000080",
        "tgn:7029392"
    ],
    "tgn:id":1005749,
    "tgn:name":"Torre Faro",
    "tgn:placetype":[
        "aat:300008347"
    ]
},
  "bbox": [],
  "geometry": {"coordinates":[15.583333,38.266667],"type":"Point"}
}