{
  "id": 7490496,
  "type": "Feature",
  "properties": {
    "tgn:hierarchy":[
        "tgn:7490496",
        "tgn:1000004",
        "tgn:7490934",
        "tgn:1000141",
        "tgn:7029392"
    ],
    "tgn:id":7490496,
    "tgn:name":"Daxi",
    "tgn:placetype":[
        "aat:300008347"
    ]
},
  "bbox": [],
  "geometry": {"coordinates":[120.229444,23.142222],"type":"Point"}
}