{
  "id": 2615106,
  "type": "Feature",
  "properties": {
    "tgn:hierarchy":[
        "tgn:2615106",
        "tgn:1000001",
        "tgn:7012149",
        "tgn:2002379",
        "tgn:7007923",
        "tgn:7029392"
    ],
    "tgn:id":2615106,
    "tgn:name":"Reservation Peak",
    "tgn:placetype":[
        "aat:300008798"
    ]
},
  "bbox": [],
  "geometry": {"coordinates":[-110.0167,44.4167],"type":"Point"}
}