{
  "id": 1113015,
  "type": "Feature",
  "properties": {
    "tgn:hierarchy":[
        "tgn:1113015",
        "tgn:7013022",
        "tgn:7005685",
        "tgn:1000001",
        "tgn:7005802",
        "tgn:7029392"
    ],
    "tgn:id":1113015,
    "tgn:name":"Gabarus Bay",
    "tgn:placetype":[
        "aat:300132316"
    ]
},
  "bbox": [],
  "geometry": {"coordinates":[-60.1167,45.85],"type":"Point"}
}