{
  "id": 7342439,
  "type": "Feature",
  "properties": {
    "tgn:hierarchy":[
        "tgn:7342439",
        "tgn:7002826",
        "tgn:7001158",
        "tgn:1000003",
        "tgn:1000095",
        "tgn:7029392"
    ],
    "tgn:id":7342439,
    "tgn:name":"Cand\u00edn",
    "tgn:placetype":[
        "aat:300008347"
    ]
},
  "bbox": [],
  "geometry": {"coordinates":[-6.733333,42.816667],"type":"Point"}
}