{
  "id": 7492353,
  "type": "Feature",
  "properties": {
    "tgn:hierarchy":[
        "tgn:7492353",
        "tgn:1000004",
        "tgn:1000454",
        "tgn:1000141",
        "tgn:7029392"
    ],
    "tgn:id":7492353,
    "tgn:name":"Pengcailiao",
    "tgn:placetype":[
        "aat:300008347"
    ]
},
  "bbox": [],
  "geometry": {"coordinates":[121.650889,24.974136],"type":"Point"}
}