{
  "id": 2301107,
  "type": "Feature",
  "properties": {
    "tgn:hierarchy":[
        "tgn:2301107",
        "tgn:1000001",
        "tgn:7012149",
        "tgn:1002440",
        "tgn:7007568",
        "tgn:7029392"
    ],
    "tgn:id":2301107,
    "tgn:name":"Dunham Mountain",
    "tgn:placetype":[
        "aat:300008798"
    ]
},
  "bbox": [],
  "geometry": {"coordinates":[-74.3833,43.45],"type":"Point"}
}