{
  "id": 2188508,
  "type": "Feature",
  "properties": {
    "tgn:hierarchy":[
        "tgn:2188508",
        "tgn:1000001",
        "tgn:7019982",
        "tgn:7012149",
        "tgn:7007517",
        "tgn:7029392"
    ],
    "tgn:id":2188508,
    "tgn:name":"Bottle Brook",
    "tgn:placetype":[
        "aat:300008699"
    ]
},
  "bbox": [],
  "geometry": {"coordinates":[-72.2333,42.1333],"type":"Point"}
}