{
  "id": 2570879,
  "type": "Feature",
  "properties": {
    "tgn:hierarchy":[
        "tgn:2570879",
        "tgn:7006450",
        "tgn:1000001",
        "tgn:7012149",
        "tgn:2124014",
        "tgn:7029392"
    ],
    "tgn:id":2570879,
    "tgn:name":"Patterson Creek",
    "tgn:placetype":[
        "aat:300008706"
    ]
},
  "bbox": [],
  "geometry": {"coordinates":[-162.15,65.8333],"type":"Point"}
}