{
  "id": 2661865,
  "type": "Feature",
  "properties": {
    "tgn:hierarchy":[
        "tgn:2661865",
        "tgn:1000001",
        "tgn:7012149",
        "tgn:2002127",
        "tgn:7007827",
        "tgn:7029392"
    ],
    "tgn:id":2661865,
    "tgn:name":"Shunesburg",
    "tgn:placetype":[
        "aat:300008347"
    ]
},
  "bbox": [],
  "geometry": {"coordinates":[-112.9667,37.15],"type":"Point"}
}