<<<<<<< HEAD
{
  "id": 7024829,
  "type": "Feature",
  "properties": {
    "tgn:hierarchy":[
        "tgn:7024829",
        "tgn:7002445",
        "tgn:7008114",
        "tgn:1000003",
        "tgn:7008591",
        "tgn:7029392"
    ],
    "tgn:id":7024829,
    "tgn:name:ang":"Lautune",
    "tgn:placetype":[
        "aat:300008347"
    ]
},
  "bbox": [],
  "geometry": {"coordinates":[-2.2833,53.1],"type":"Point"}
}
=======
{"geometry":{"type":"Point","coordinates":[-2.283300,53.100000]},"type":"Feature","properties":{"hierarchy":["tgn:7024829","tgn:7002445","tgn:7008114","tgn:1000003","tgn:7008591","tgn:7029392"],"placetype":["aat:300008347"],"id":7024829,"name:ang":"Lautune"}}
>>>>>>> 03f74aca74312dbeaf24d7e61306dd6a786dc3d0
