{
  "id": 1068552,
  "type": "Feature",
  "properties": {
    "tgn:hierarchy":[
        "tgn:1068552",
        "tgn:1000004",
        "tgn:7002088",
        "tgn:1000111",
        "tgn:7029392"
    ],
    "tgn:id":1068552,
    "tgn:name":"Haitun",
    "tgn:placetype":[
        "aat:300008347"
    ]
},
  "bbox": [],
  "geometry": {"coordinates":[96.6833,38.8333],"type":"Point"}
}