{
  "id": 7389690,
  "type": "Feature",
  "properties": {
    "tgn:hierarchy":[
        "tgn:7389690",
        "tgn:1000001",
        "tgn:7005599",
        "tgn:7005560",
        "tgn:7029392"
    ],
    "tgn:id":7389690,
    "tgn:name":"Remolino",
    "tgn:placetype":[
        "aat:300008347"
    ]
},
  "bbox": [],
  "geometry": {"coordinates":[-97.216667,20.433333],"type":"Point"}
}