<<<<<<< HEAD
{
  "id": 2760356,
  "type": "Feature",
  "properties": {
    "tgn:hierarchy":[
        "tgn:2760356",
        "tgn:1000001",
        "tgn:7012149",
        "tgn:2001516",
        "tgn:7007709",
        "tgn:7029392"
    ],
    "tgn:id":2760356,
    "tgn:name":"West Fork Shut-In Creek",
    "tgn:placetype":[
        "aat:300008706"
    ]
},
  "bbox": [],
  "geometry": {"coordinates":[-82.9,35.8333],"type":"Point"}
}
=======
{"geometry":{"type":"Point","coordinates":[-82.900000,35.833300]},"type":"Feature","properties":{"hierarchy":["tgn:2760356","tgn:1000001","tgn:7012149","tgn:2001516","tgn:7007709","tgn:7029392"],"placetype":["aat:300008706"],"id":2760356,"name:xx":"West Fork Shut-In Creek"}}
>>>>>>> 03f74aca74312dbeaf24d7e61306dd6a786dc3d0
