{
  "id": 7349727,
  "type": "Feature",
  "properties": {
    "tgn:hierarchy":[
        "tgn:7349727",
        "tgn:1000001",
        "tgn:7005591",
        "tgn:7005560",
        "tgn:7029392"
    ],
    "tgn:id":7349727,
    "tgn:name":"Aguas Pocas",
    "tgn:placetype":[
        "aat:300008347"
    ]
},
  "bbox": [],
  "geometry": {"coordinates":[-94.866667,16.15],"type":"Point"}
}