{
  "id": 7465110,
  "type": "Feature",
  "properties": {
    "tgn:hierarchy":[
        "tgn:7465110",
        "tgn:7002445",
        "tgn:1000003",
        "tgn:7008129",
        "tgn:7008591",
        "tgn:7029392"
    ],
    "tgn:id":7465110,
    "tgn:name:en":"Boulder Banks",
    "tgn:placetype":[
        "aat:300387036"
    ]
},
  "bbox": [],
  "geometry": {"coordinates":[0.733333,50.866667],"type":"Point"}
}