{
  "id": 1127952,
  "type": "Feature",
  "properties": {
    "tgn:hierarchy":[
        "tgn:1127952",
        "tgn:1000004",
        "tgn:7001838",
        "tgn:1000111",
        "tgn:7029392"
    ],
    "tgn:id":1127952,
    "tgn:name":"Nuomin He",
    "tgn:placetype":[
        "aat:300008707"
    ]
},
  "bbox": [],
  "geometry": {"coordinates":[124.4167,48.0833],"type":"Point"}
}