{
  "id": 2243462,
  "type": "Feature",
  "properties": {
    "tgn:hierarchy":[
        "tgn:2243462",
        "tgn:1000001",
        "tgn:7012149",
        "tgn:7007523",
        "tgn:7029392"
    ],
    "tgn:id":2243462,
    "tgn:name":"Clearwater Lake",
    "tgn:placetype":[
        "aat:300006191"
    ]
},
  "bbox": [],
  "geometry": {"coordinates":[-90.7667,37.1333],"type":"Point"}
}