{
  "id": 2676270,
  "type": "Feature",
  "properties": {
    "tgn:hierarchy":[
        "tgn:2676270",
        "tgn:1000001",
        "tgn:7006451",
        "tgn:2000092",
        "tgn:7012149",
        "tgn:7029392"
    ],
    "tgn:id":2676270,
    "tgn:name":"Sour Water Spring",
    "tgn:placetype":[
        "aat:300008697"
    ]
},
  "bbox": [],
  "geometry": {"coordinates":[-110.9333,36.5333],"type":"Point"}
}