{
  "id": 7551279,
  "type": "Feature",
  "properties": {
    "tgn:hierarchy":[
        "tgn:7551279",
        "tgn:1000004",
        "tgn:7000198",
        "tgn:1001882",
        "tgn:7029392"
    ],
    "tgn:id":7551279,
    "tgn:name:en":"Daroji Kere",
    "tgn:placetype":[
        "aat:300008680"
    ]
},
  "bbox": [],
  "geometry": {"coordinates":[76.666667,15.233333],"type":"Point"}
}