{
  "id": 2644518,
  "type": "Feature",
  "properties": {
    "tgn:hierarchy":[
        "tgn:2644518",
        "tgn:1000001",
        "tgn:2002368",
        "tgn:7012149",
        "tgn:7007923",
        "tgn:7029392"
    ],
    "tgn:id":2644518,
    "tgn:name":"Saratoga Lake",
    "tgn:placetype":[
        "aat:300008680"
    ]
},
  "bbox": [],
  "geometry": {"coordinates":[-106.7667,41.4667],"type":"Point"}
}