<<<<<<< HEAD
{
  "id": 2337426,
  "type": "Feature",
  "properties": {
    "tgn:hierarchy":[
        "tgn:2337426",
        "tgn:1000001",
        "tgn:7012149",
        "tgn:7007157",
        "tgn:7014475",
        "tgn:7029392"
    ],
    "tgn:id":2337426,
    "tgn:name":"Fowler Creek",
    "tgn:placetype":[
        "aat:300008706"
    ]
},
  "bbox": [],
  "geometry": {"coordinates":[-121.7167,37.3167],"type":"Point"}
}
=======
{"geometry":{"type":"Point","coordinates":[-121.716700,37.316700]},"type":"Feature","properties":{"hierarchy":["tgn:2337426","tgn:1000001","tgn:7012149","tgn:7007157","tgn:7014475","tgn:7029392"],"placetype":["aat:300008706"],"id":2337426,"name:xx":"Fowler Creek"}}
>>>>>>> 03f74aca74312dbeaf24d7e61306dd6a786dc3d0
