{
  "id": 7070321,
  "type": "Feature",
  "properties": {
    "tgn:hierarchy":[
        "tgn:7070321",
        "tgn:1000003",
        "tgn:7003685",
        "tgn:7000084",
        "tgn:7029392"
    ],
    "tgn:id":7070321,
    "tgn:name":"Steinbach",
    "tgn:placetype":[
        "aat:300008699"
    ]
},
  "bbox": [],
  "geometry": {"coordinates":[13.966667,51.116667],"type":"Point"}
}