{
  "id": 2264205,
  "type": "Feature",
  "properties": {
    "tgn:hierarchy":[
        "tgn:2264205",
        "tgn:1000001",
        "tgn:7006451",
        "tgn:7012149",
        "tgn:2000100",
        "tgn:7029392"
    ],
    "tgn:id":2264205,
    "tgn:name":"Coyote Wash",
    "tgn:placetype":[
        "aat:300008699"
    ]
},
  "bbox": [],
  "geometry": {"coordinates":[-110.6167,32.0833],"type":"Point"}
}