{
  "id": 2615107,
  "type": "Feature",
  "properties": {
    "tgn:hierarchy":[
        "tgn:2615107",
        "tgn:1000001",
        "tgn:7012149",
        "tgn:7007157",
        "tgn:1002608",
        "tgn:7029392"
    ],
    "tgn:id":2615107,
    "tgn:name":"Reservation Point",
    "tgn:placetype":[
        "aat:300008850"
    ]
},
  "bbox": [],
  "geometry": {"coordinates":[-118.25,33.7167],"type":"Point"}
}