{
  "id": 2250209,
  "type": "Feature",
  "properties": {
    "tgn:hierarchy":[
        "tgn:2250209",
        "tgn:1000001",
        "tgn:7012149",
        "tgn:2000204",
        "tgn:7007158",
        "tgn:7029392"
    ],
    "tgn:id":2250209,
    "tgn:name":"Collins Lateral",
    "tgn:placetype":[
        "aat:300006075"
    ]
},
  "bbox": [],
  "geometry": {"coordinates":[-103.85,38.2167],"type":"Point"}
}