{
  "id": 2628339,
  "type": "Feature",
  "properties": {
    "tgn:hierarchy":[
        "tgn:2628339",
        "tgn:1000001",
        "tgn:7012149",
        "tgn:2001300",
        "tgn:7007524",
        "tgn:7029392"
    ],
    "tgn:id":2628339,
    "tgn:name":"Romney Ridge",
    "tgn:placetype":[
        "aat:300266640"
    ]
},
  "bbox": [],
  "geometry": {"coordinates":[-114.2333,46.25],"type":"Point"}
}