{
  "id": 7069596,
  "type": "Feature",
  "properties": {
    "tgn:hierarchy":[
        "tgn:7069596",
        "tgn:1000003",
        "tgn:7003687",
        "tgn:7000084",
        "tgn:7029392"
    ],
    "tgn:id":7069596,
    "tgn:name":"Thie\u00dfen",
    "tgn:placetype":[
        "aat:300008347"
    ]
},
  "bbox": [],
  "geometry": {"coordinates":[12.683333,51.916667],"type":"Point"}
}