{
  "id": 2519360,
  "type": "Feature",
  "properties": {
    "tgn:hierarchy":[
        "tgn:2519360",
        "tgn:1000001",
        "tgn:2001410",
        "tgn:7012149",
        "tgn:7007526",
        "tgn:7029392"
    ],
    "tgn:id":2519360,
    "tgn:name":"Mockingbird Spring",
    "tgn:placetype":[
        "aat:300008697"
    ]
},
  "bbox": [],
  "geometry": {"coordinates":[-114.2833,36.25],"type":"Point"}
}