{
  "id": 1055448,
  "type": "Feature",
  "properties": {
    "tgn:hierarchy":[
        "tgn:1055448",
        "tgn:1000004",
        "tgn:7011572",
        "tgn:7018214",
        "tgn:7002435",
        "tgn:7029392"
    ],
    "tgn:id":1055448,
    "tgn:name":"Kobona",
    "tgn:placetype":[
        "aat:300008347"
    ]
},
  "bbox": [],
  "geometry": {"coordinates":[31.55,60.0167],"type":"Point"}
}