<<<<<<< HEAD
{
  "id": 2158666,
  "type": "Feature",
  "properties": {
    "tgn:hierarchy":[
        "tgn:2158666",
        "tgn:1000001",
        "tgn:7012149",
        "tgn:2001300",
        "tgn:7007524",
        "tgn:7029392"
    ],
    "tgn:id":2158666,
    "tgn:name":"Beavertail Creek",
    "tgn:placetype":[
        "aat:300008706"
    ]
},
  "bbox": [],
  "geometry": {"coordinates":[-114.1833,45.7833],"type":"Point"}
}
=======
{"geometry":{"type":"Point","coordinates":[-114.183300,45.783300]},"type":"Feature","properties":{"hierarchy":["tgn:2158666","tgn:1000001","tgn:7012149","tgn:2001300","tgn:7007524","tgn:7029392"],"placetype":["aat:300008706"],"id":2158666,"name:xx":"Beavertail Creek"}}
>>>>>>> 03f74aca74312dbeaf24d7e61306dd6a786dc3d0
