<<<<<<< HEAD
{
  "id": 7355287,
  "type": "Feature",
  "properties": {
    "tgn:hierarchy":[
        "tgn:7355287",
        "tgn:1001853",
        "tgn:1000001",
        "tgn:7005560",
        "tgn:7029392"
    ],
    "tgn:id":7355287,
    "tgn:name":"Cedral",
    "tgn:placetype":[
        "aat:300007783"
    ]
},
  "bbox": [],
  "geometry": {"coordinates":[-101.4,27.833333],"type":"Point"}
}
=======
{"geometry":{"type":"Point","coordinates":[-101.400000,27.833333]},"type":"Feature","properties":{"hierarchy":["tgn:7355287","tgn:1001853","tgn:1000001","tgn:7005560","tgn:7029392"],"placetype":["aat:300007783"],"id":7355287,"name:xx":"Cedral"}}
>>>>>>> 03f74aca74312dbeaf24d7e61306dd6a786dc3d0
