{
  "id": 2176406,
  "type": "Feature",
  "properties": {
    "tgn:hierarchy":[
        "tgn:2176406",
        "tgn:1000001",
        "tgn:2001432",
        "tgn:7012149",
        "tgn:7007566",
        "tgn:7029392"
    ],
    "tgn:id":2176406,
    "tgn:name":"Black Jacks Hideout",
    "tgn:placetype":[
        "aat:300000390"
    ]
},
  "bbox": [],
  "geometry": {"coordinates":[-105.0333,36.5667],"type":"Point"}
}