{
  "id": 7378912,
  "type": "Feature",
  "properties": {
    "tgn:hierarchy":[
        "tgn:7378912",
        "tgn:1000001",
        "tgn:1001960",
        "tgn:7005560",
        "tgn:7029392"
    ],
    "tgn:id":7378912,
    "tgn:name":"Maquibito",
    "tgn:placetype":[
        "aat:300008347"
    ]
},
  "bbox": [],
  "geometry": {"coordinates":[-108.716111,26.741389],"type":"Point"}
}