{
  "id": 2640391,
  "type": "Feature",
  "properties": {
    "tgn:hierarchy":[
        "tgn:2640391",
        "tgn:1000001",
        "tgn:7012149",
        "tgn:2001456",
        "tgn:7007566",
        "tgn:7029392"
    ],
    "tgn:id":2640391,
    "tgn:name":"San Francisco Lateral",
    "tgn:placetype":[
        "aat:300006075"
    ]
},
  "bbox": [],
  "geometry": {"coordinates":[-106.8167,34.4333],"type":"Point"}
}