{
  "id": 7342188,
  "type": "Feature",
  "properties": {
    "tgn:hierarchy":[
        "tgn:7342188",
        "tgn:7002758",
        "tgn:7002830",
        "tgn:1000003",
        "tgn:1000095",
        "tgn:7029392"
    ],
    "tgn:id":7342188,
    "tgn:name":"Canillas de Aceituno",
    "tgn:placetype":[
        "aat:300008347"
    ]
},
  "bbox": [],
  "geometry": {"coordinates":[-4.066667,36.866667],"type":"Point"}
}