{
  "id": 2591701,
  "type": "Feature",
  "properties": {
    "tgn:hierarchy":[
        "tgn:2591701",
        "tgn:1000001",
        "tgn:7012149",
        "tgn:2001199",
        "tgn:7007523",
        "tgn:7029392"
    ],
    "tgn:id":2591701,
    "tgn:name":"Pond Creek",
    "tgn:placetype":[
        "aat:300008706"
    ]
},
  "bbox": [],
  "geometry": {"coordinates":[-93.4333,37.1333],"type":"Point"}
}