{
  "id": 1122625,
  "type": "Feature",
  "properties": {
    "tgn:hierarchy":[
        "tgn:1122625",
        "tgn:1001204",
        "tgn:1000001",
        "tgn:7004624",
        "tgn:7029392"
    ],
    "tgn:id":1122625,
    "tgn:name":"Ceiba, R\u00edo",
    "tgn:placetype":[
        "aat:300008707"
    ]
},
  "bbox": [],
  "geometry": {"coordinates":[-78.85,21.6333],"type":"Point"}
}