{
  "id": 1092383,
  "type": "Feature",
  "properties": {
    "tgn:hierarchy":[
        "tgn:1092383",
        "tgn:7001242",
        "tgn:7594001",
        "tgn:1000185",
        "tgn:7029392"
    ],
    "tgn:id":1092383,
    "tgn:name":"Glencova",
    "tgn:placetype":[
        "aat:300008347"
    ]
},
  "bbox": [],
  "geometry": {"coordinates":[31.4333,-19.9667],"type":"Point"}
}