{
  "id": 1134536,
  "type": "Feature",
  "properties": {
    "tgn:hierarchy":[
        "tgn:1134536",
        "tgn:1000574",
        "tgn:1000002",
        "tgn:1000058",
        "tgn:7029392"
    ],
    "tgn:id":1134536,
    "tgn:name":"Sauce, Arroyo",
    "tgn:placetype":[
        "aat:300008706"
    ]
},
  "bbox": [],
  "geometry": {"coordinates":[-57.4667,-34.4333],"type":"Point"}
}