{
  "id": 2281638,
  "type": "Feature",
  "properties": {
    "tgn:hierarchy":[
        "tgn:2281638",
        "tgn:1000001",
        "tgn:7012149",
        "tgn:1002416",
        "tgn:7007252",
        "tgn:7029392"
    ],
    "tgn:id":2281638,
    "tgn:name":"Deer Creek",
    "tgn:placetype":[
        "aat:300008706"
    ]
},
  "bbox": [],
  "geometry": {"coordinates":[-25.6667,40.3667],"type":"Point"}
}