<<<<<<< HEAD
{
  "id": 2765875,
  "type": "Feature",
  "properties": {
    "tgn:hierarchy":[
        "tgn:2765875",
        "tgn:1000001",
        "tgn:7012149",
        "tgn:7016020",
        "tgn:7007710",
        "tgn:7029392"
    ],
    "tgn:id":2765875,
    "tgn:name":"White Gravel Creek",
    "tgn:placetype":[
        "aat:300008706"
    ]
},
  "bbox": [],
  "geometry": {"coordinates":[-78.7833,41.8167],"type":"Point"}
}
=======
{"geometry":{"type":"Point","coordinates":[-78.783300,41.816700]},"type":"Feature","properties":{"hierarchy":["tgn:2765875","tgn:1000001","tgn:7012149","tgn:7016020","tgn:7007710","tgn:7029392"],"placetype":["aat:300008706"],"id":2765875,"name:xx":"White Gravel Creek"}}
>>>>>>> 03f74aca74312dbeaf24d7e61306dd6a786dc3d0
