{
  "id": 1133067,
  "type": "Feature",
  "properties": {
    "tgn:hierarchy":[
        "tgn:1133067",
        "tgn:1000001",
        "tgn:7012149",
        "tgn:7007919",
        "tgn:7029392"
    ],
    "tgn:id":1133067,
    "tgn:name":"Dragon Swamp",
    "tgn:placetype":[
        "aat:300008706"
    ]
},
  "bbox": [],
  "geometry": {"coordinates":[-76.9333,37.7667],"type":"Point"}
}