{
  "id": 2306895,
  "type": "Feature",
  "properties": {
    "tgn:hierarchy":[
        "tgn:2306895",
        "tgn:1000001",
        "tgn:7012149",
        "tgn:2002373",
        "tgn:7007923",
        "tgn:7029392"
    ],
    "tgn:id":2306895,
    "tgn:name":"East Fork Jones Creek",
    "tgn:placetype":[
        "aat:300008706"
    ]
},
  "bbox": [],
  "geometry": {"coordinates":[-107.9833,43.4667],"type":"Point"}
}