{
  "id": 2353086,
  "type": "Feature",
  "properties": {
    "tgn:hierarchy":[
        "tgn:2353086",
        "tgn:1000001",
        "tgn:7012149",
        "tgn:2002247",
        "tgn:7007920",
        "tgn:7029392"
    ],
    "tgn:id":2353086,
    "tgn:name":"Goetz Lake",
    "tgn:placetype":[
        "aat:300008680"
    ]
},
  "bbox": [],
  "geometry": {"coordinates":[-118.7833,47.45],"type":"Point"}
}