<<<<<<< HEAD
{
  "id": 7171166,
  "type": "Feature",
  "properties": {
    "tgn:hierarchy":[
        "tgn:7171166",
        "tgn:7003692",
        "tgn:1000003",
        "tgn:7000084",
        "tgn:7029392"
    ],
    "tgn:id":7171166,
    "tgn:name":"Herzenklingen",
    "tgn:placetype":[
        "aat:300000206"
    ]
},
  "bbox": [],
  "geometry": {"coordinates":[9.8,48.766667],"type":"Point"}
}
=======
{"geometry":{"type":"Point","coordinates":[9.800000,48.766667]},"type":"Feature","properties":{"hierarchy":["tgn:7171166","tgn:7003692","tgn:1000003","tgn:7000084","tgn:7029392"],"placetype":["aat:300000206"],"id":7171166,"name:xx":"Herzenklingen"}}
>>>>>>> 03f74aca74312dbeaf24d7e61306dd6a786dc3d0
