{
  "id": 7017816,
  "type": "Feature",
  "properties": {
    "tgn:hierarchy":[
        "tgn:7017816",
        "tgn:1000001",
        "tgn:1002217",
        "tgn:7012149",
        "tgn:7007710",
        "tgn:7029392"
    ],
    "tgn:id":7017816,
    "tgn:name":"Homeacre",
    "tgn:placetype":[
        "aat:300008347"
    ]
},
  "bbox": [],
  "geometry": {"coordinates":[-79.9333,40.85],"type":"Point"}
}