{
  "id": 7009634,
  "type": "Feature",
  "properties": {
    "tgn:hierarchy":[
        "tgn:7009634",
        "tgn:1000003",
        "tgn:7002892",
        "tgn:1000070",
        "tgn:7029392"
    ],
    "tgn:id":7009634,
    "tgn:name":"Saint Jean-d'Ang\u00e9ly",
    "tgn:placetype":[
        "aat:300008347"
    ]
},
  "bbox": [],
  "geometry": {"coordinates":[-0.5167,45.95],"type":"Point"}
}