{
  "id": 7540924,
  "type": "Feature",
  "properties": {
    "tgn:hierarchy":[
        "tgn:7540924",
        "tgn:7001242",
        "tgn:7016833",
        "tgn:7001336",
        "tgn:7029392"
    ],
    "tgn:id":7540924,
    "tgn:name:en":"Shellal, W\u0101d\u012b",
    "tgn:placetype":[
        "aat:300379998"
    ]
},
  "bbox": [],
  "geometry": {"coordinates":[34.291111,28.533333],"type":"Point"}
}