{
  "id": 2580963,
  "type": "Feature",
  "properties": {
    "tgn:hierarchy":[
        "tgn:2580963",
        "tgn:1000001",
        "tgn:2002260",
        "tgn:7012149",
        "tgn:7013961",
        "tgn:7029392"
    ],
    "tgn:id":2580963,
    "tgn:name":"Pike Fork",
    "tgn:placetype":[
        "aat:300008699"
    ]
},
  "bbox": [],
  "geometry": {"coordinates":[-80.5333,39.3833],"type":"Point"}
}