{
  "id": 2701950,
  "type": "Feature",
  "properties": {
    "tgn:hierarchy":[
        "tgn:2701950",
        "tgn:1000001",
        "tgn:7012149",
        "tgn:2002114",
        "tgn:7007827",
        "tgn:7029392"
    ],
    "tgn:id":2701950,
    "tgn:name":"Sugarloaf Mountain",
    "tgn:placetype":[
        "aat:300008798"
    ]
},
  "bbox": [],
  "geometry": {"coordinates":[-112.1667,38.9167],"type":"Point"}
}