<<<<<<< HEAD
{
  "id": 7376218,
  "type": "Feature",
  "properties": {
    "tgn:hierarchy":[
        "tgn:7376218",
        "tgn:7005586",
        "tgn:1000001",
        "tgn:7005560",
        "tgn:7029392"
    ],
    "tgn:id":7376218,
    "tgn:name":"Lo Arado",
    "tgn:placetype":[
        "aat:300008347"
    ]
},
  "bbox": [],
  "geometry": {"coordinates":[-104.583333,19.616667],"type":"Point"}
}
=======
{"geometry":{"type":"Point","coordinates":[-104.583333,19.616667]},"type":"Feature","properties":{"hierarchy":["tgn:7376218","tgn:7005586","tgn:1000001","tgn:7005560","tgn:7029392"],"placetype":["aat:300008347"],"id":7376218,"name:xx":"Lo Arado"}}
>>>>>>> 03f74aca74312dbeaf24d7e61306dd6a786dc3d0
