{
  "id": 1054865,
  "type": "Feature",
  "properties": {
    "tgn:hierarchy":[
        "tgn:1054865",
        "tgn:1000003",
        "tgn:7011661",
        "tgn:7006660",
        "tgn:7029392"
    ],
    "tgn:id":1054865,
    "tgn:name":"Kagarlyk",
    "tgn:placetype":[
        "aat:300008347"
    ]
},
  "bbox": [],
  "geometry": {"coordinates":[30.8333,49.8333],"type":"Point"}
}