{
  "id": 2736499,
  "type": "Feature",
  "properties": {
    "tgn:hierarchy":[
        "tgn:2736499",
        "tgn:1000001",
        "tgn:2001429",
        "tgn:7012149",
        "tgn:7007566",
        "tgn:7029392"
    ],
    "tgn:id":2736499,
    "tgn:name":"Twin Sister Tank Number One",
    "tgn:placetype":[
        "aat:300006191"
    ]
},
  "bbox": [],
  "geometry": {"coordinates":[-108.9833,33.4333],"type":"Point"}
}