{
  "id": 7238203,
  "type": "Feature",
  "properties": {
    "tgn:hierarchy":[
        "tgn:7238203",
        "tgn:7007877",
        "tgn:1000003",
        "tgn:1000063",
        "tgn:4012014",
        "tgn:7029392"
    ],
    "tgn:id":7238203,
    "tgn:name":"Grande Cense",
    "tgn:placetype":[
        "aat:300000206"
    ]
},
  "bbox": [],
  "geometry": {"coordinates":[4.216667,50.683333],"type":"Point"}
}