{
  "id": 7071301,
  "type": "Feature",
  "properties": {
    "tgn:hierarchy":[
        "tgn:7071301",
        "tgn:7003669",
        "tgn:1000003",
        "tgn:7000084",
        "tgn:7029392"
    ],
    "tgn:id":7071301,
    "tgn:name":"Tegernbach",
    "tgn:placetype":[
        "aat:300008347"
    ]
},
  "bbox": [],
  "geometry": {"coordinates":[12.083333,48.316667],"type":"Point"}
}