{
  "id": 7514478,
  "type": "Feature",
  "properties": {
    "tgn:hierarchy":[
        "tgn:7514478",
        "tgn:1009227",
        "tgn:1000226",
        "tgn:7016822",
        "tgn:1000006",
        "tgn:7029392"
    ],
    "tgn:id":7514478,
    "tgn:name:en":"Divide Head",
    "tgn:placetype":[
        "aat:300008850"
    ]
},
  "bbox": [],
  "geometry": {"coordinates":[166.65,-45.95],"type":"Point"}
}