{
  "id": 7098595,
  "type": "Feature",
  "properties": {
    "tgn:hierarchy":[
        "tgn:7098595",
        "tgn:7003669",
        "tgn:1000003",
        "tgn:7000084",
        "tgn:7029392"
    ],
    "tgn:id":7098595,
    "tgn:name":"Spitz Berg",
    "tgn:placetype":[
        "aat:300008795"
    ]
},
  "bbox": [],
  "geometry": {"coordinates":[12.35,47.716667],"type":"Point"}
}