{
  "id": 2550052,
  "type": "Feature",
  "properties": {
    "tgn:hierarchy":[
        "tgn:2550052",
        "tgn:1002132",
        "tgn:1000001",
        "tgn:7012149",
        "tgn:7007919",
        "tgn:7029392"
    ],
    "tgn:id":2550052,
    "tgn:name":"Northam Creek",
    "tgn:placetype":[
        "aat:300008706"
    ]
},
  "bbox": [],
  "geometry": {"coordinates":[-75.55,37.8167],"type":"Point"}
}