{
  "id": 7527394,
  "type": "Feature",
  "properties": {
    "tgn:hierarchy":[
        "tgn:7527394",
        "tgn:7001242",
        "tgn:7016833",
        "tgn:7000122",
        "tgn:7029392"
    ],
    "tgn:id":7527394,
    "tgn:name:en":"S\u012bd\u012b S\u0101lim",
    "tgn:placetype":[
        "aat:300005926"
    ]
},
  "bbox": [],
  "geometry": {"coordinates":[32.883333,24.933333],"type":"Point"}
}