{
  "id": 7515559,
  "type": "Feature",
  "properties": {
    "tgn:hierarchy":[
        "tgn:7515559",
        "tgn:1008380",
        "tgn:7520093",
        "tgn:1000226",
        "tgn:1000006",
        "tgn:7029392"
    ],
    "tgn:id":7515559,
    "tgn:name:en":"Mount Lake",
    "tgn:placetype":[
        "aat:300008680"
    ]
},
  "bbox": [],
  "geometry": {"coordinates":[175.25,-40.116667],"type":"Point"}
}