{
  "id": 2214814,
  "type": "Feature",
  "properties": {
    "tgn:hierarchy":[
        "tgn:2214814",
        "tgn:1000001",
        "tgn:7006451",
        "tgn:2000094",
        "tgn:7012149",
        "tgn:7029392"
    ],
    "tgn:id":2214814,
    "tgn:name":"Calf Spring",
    "tgn:placetype":[
        "aat:300008697"
    ]
},
  "bbox": [],
  "geometry": {"coordinates":[-110.2333,32.95],"type":"Point"}
}