<<<<<<< HEAD
{
  "id": 2766351,
  "type": "Feature",
  "properties": {
    "tgn:hierarchy":[
        "tgn:2766351",
        "tgn:1000001",
        "tgn:7012149",
        "tgn:7007157",
        "tgn:1002972",
        "tgn:7029392"
    ],
    "tgn:id":2766351,
    "tgn:name":"White Mountain",
    "tgn:placetype":[
        "aat:300008798"
    ]
},
  "bbox": [],
  "geometry": {"coordinates":[-118.8333,34.6167],"type":"Point"}
}
=======
{"geometry":{"type":"Point","coordinates":[-118.833300,34.616700]},"type":"Feature","properties":{"hierarchy":["tgn:2766351","tgn:1000001","tgn:7012149","tgn:7007157","tgn:1002972","tgn:7029392"],"placetype":["aat:300008798"],"id":2766351,"name:xx":"White Mountain"}}
>>>>>>> 03f74aca74312dbeaf24d7e61306dd6a786dc3d0
