{
  "id": 2766351,
  "type": "Feature",
  "properties": {
    "tgn:hierarchy":[
        "tgn:2766351",
        "tgn:1000001",
        "tgn:7012149",
        "tgn:7007157",
        "tgn:1002972",
        "tgn:7029392"
    ],
    "tgn:id":2766351,
    "tgn:name":"White Mountain",
    "tgn:placetype":[
        "aat:300008798"
    ]
},
  "bbox": [],
  "geometry": {"coordinates":[-118.8333,34.6167],"type":"Point"}
}