<<<<<<< HEAD
{
  "id": 7350952,
  "type": "Feature",
  "properties": {
    "tgn:hierarchy":[
        "tgn:7350952",
        "tgn:7005581",
        "tgn:1000001",
        "tgn:7005560",
        "tgn:7029392"
    ],
    "tgn:id":7350952,
    "tgn:name":"Baj\u00edo de las Liebres",
    "tgn:placetype":[
        "aat:300008347"
    ]
},
  "bbox": [],
  "geometry": {"coordinates":[-104.7,28.5],"type":"Point"}
}
=======
{"geometry":{"type":"Point","coordinates":[-104.700000,28.500000]},"type":"Feature","properties":{"hierarchy":["tgn:7350952","tgn:7005581","tgn:1000001","tgn:7005560","tgn:7029392"],"placetype":["aat:300008347"],"id":7350952,"name:xx":"Baj\u00edo de las Liebres"}}
>>>>>>> 03f74aca74312dbeaf24d7e61306dd6a786dc3d0
