{
  "id": 2432902,
  "type": "Feature",
  "properties": {
    "tgn:hierarchy":[
        "tgn:2432902",
        "tgn:1000001",
        "tgn:7012149",
        "tgn:1002518",
        "tgn:7007568",
        "tgn:7029392"
    ],
    "tgn:id":2432902,
    "tgn:name":"Keewaydin Point",
    "tgn:placetype":[
        "aat:300008850"
    ]
},
  "bbox": [],
  "geometry": {"coordinates":[-75.9333,44.3167],"type":"Point"}
}