{
  "id": 7009924,
  "type": "Feature",
  "properties": {
    "tgn:hierarchy":[
        "tgn:7009924",
        "tgn:7019094",
        "tgn:7002444",
        "tgn:1000003",
        "tgn:7008591",
        "tgn:7009075",
        "tgn:7029392"
    ],
    "tgn:id":7009924,
    "tgn:name:en":"Lochdonhead",
    "tgn:placetype":[
        "aat:300008347"
    ]
},
  "bbox": [],
  "geometry": {"coordinates":[-5.683333,56.433333],"type":"Point"}
}