{
  "id": 2297301,
  "type": "Feature",
  "properties": {
    "tgn:hierarchy":[
        "tgn:2297301",
        "tgn:1000001",
        "tgn:7012149",
        "tgn:2002326",
        "tgn:7007922",
        "tgn:7029392"
    ],
    "tgn:id":2297301,
    "tgn:name":"Dry Dog Ridge",
    "tgn:placetype":[
        "aat:300266640"
    ]
},
  "bbox": [],
  "geometry": {"coordinates":[-90.3667,43.1333],"type":"Point"}
}