{
  "id": 2274326,
  "type": "Feature",
  "properties": {
    "tgn:hierarchy":[
        "tgn:2274326",
        "tgn:1000001",
        "tgn:7012149",
        "tgn:2002387",
        "tgn:7007923",
        "tgn:7029392"
    ],
    "tgn:id":2274326,
    "tgn:name":"Dakoming",
    "tgn:placetype":[
        "aat:300008347"
    ]
},
  "bbox": [],
  "geometry": {"coordinates":[-104.0667,43.5833],"type":"Point"}
}