{
  "id": 2421759,
  "type": "Feature",
  "properties": {
    "tgn:hierarchy":[
        "tgn:2421759",
        "tgn:2000919",
        "tgn:1000001",
        "tgn:7012149",
        "tgn:7007515",
        "tgn:7029392"
    ],
    "tgn:id":2421759,
    "tgn:name":"Jewells Corner",
    "tgn:placetype":[
        "aat:300008347"
    ]
},
  "bbox": [],
  "geometry": {"coordinates":[-67.8333,46.3333],"type":"Point"}
}