{
  "id": 2624517,
  "type": "Feature",
  "properties": {
    "tgn:hierarchy":[
        "tgn:2624517",
        "tgn:1000001",
        "tgn:7012149",
        "tgn:2000278",
        "tgn:7007240",
        "tgn:7029392"
    ],
    "tgn:id":2624517,
    "tgn:name":"Rock Pond",
    "tgn:placetype":[
        "aat:300008680"
    ]
},
  "bbox": [],
  "geometry": {"coordinates":[-84.95,30.1833],"type":"Point"}
}