{
  "id": 7079880,
  "type": "Feature",
  "properties": {
    "tgn:hierarchy":[
        "tgn:7079880",
        "tgn:7003669",
        "tgn:1000003",
        "tgn:7000084",
        "tgn:7029392"
    ],
    "tgn:id":7079880,
    "tgn:name":"W\u00f6lfle Bach",
    "tgn:placetype":[
        "aat:300008699"
    ]
},
  "bbox": [],
  "geometry": {"coordinates":[10.483333,47.716667],"type":"Point"}
}