{
  "id": 2740815,
  "type": "Feature",
  "properties": {
    "tgn:hierarchy":[
        "tgn:2740815",
        "tgn:1000001",
        "tgn:7012149",
        "tgn:2002371",
        "tgn:7007923",
        "tgn:7029392"
    ],
    "tgn:id":2740815,
    "tgn:name":"Upper Rock Creek Reservoir",
    "tgn:placetype":[
        "aat:300006191"
    ]
},
  "bbox": [],
  "geometry": {"coordinates":[-108.7667,42.5333],"type":"Point"}
}