{
  "id": 7184856,
  "type": "Feature",
  "properties": {
    "tgn:hierarchy":[
        "tgn:7184856",
        "tgn:7003669",
        "tgn:1000003",
        "tgn:7000084",
        "tgn:7029392"
    ],
    "tgn:id":7184856,
    "tgn:name":"Grasleiten-Stein",
    "tgn:placetype":[
        "aat:300008777"
    ]
},
  "bbox": [],
  "geometry": {"coordinates":[11.616667,47.65],"type":"Point"}
}