{
  "id": 7228931,
  "type": "Feature",
  "properties": {
    "tgn:hierarchy":[
        "tgn:7228931",
        "tgn:7011270",
        "tgn:7002674",
        "tgn:1000003",
        "tgn:1000074",
        "tgn:7029392"
    ],
    "tgn:id":7228931,
    "tgn:name":"Lefk\u00e1das, \u00d3rmos",
    "tgn:placetype":[
        "aat:300132316"
    ]
},
  "bbox": [],
  "geometry": {"coordinates":[24.45,37.366667],"type":"Point"}
}