{
  "id": 7467621,
  "type": "Feature",
  "properties": {
    "tgn:hierarchy":[
        "tgn:7467621",
        "tgn:1000004",
        "tgn:7467799",
        "tgn:1000141",
        "tgn:7029392"
    ],
    "tgn:id":7467621,
    "tgn:name":"Andongliao",
    "tgn:placetype":[
        "aat:300008347"
    ]
},
  "bbox": [],
  "geometry": {"coordinates":[120.331144,23.855576],"type":"Point"}
}