{
  "id": 2440534,
  "type": "Feature",
  "properties": {
    "tgn:hierarchy":[
        "tgn:2440534",
        "tgn:1000001",
        "tgn:1002359",
        "tgn:7012149",
        "tgn:7007517",
        "tgn:7029392"
    ],
    "tgn:id":2440534,
    "tgn:name":"Knapp Rock",
    "tgn:placetype":[
        "aat:300011692"
    ]
},
  "bbox": [],
  "geometry": {"coordinates":[-70.85,41.5167],"type":"Point"}
}