{
  "id": 2364330,
  "type": "Feature",
  "properties": {
    "tgn:hierarchy":[
        "tgn:2364330",
        "tgn:1000001",
        "tgn:2001842",
        "tgn:7012149",
        "tgn:7007825",
        "tgn:7029392"
    ],
    "tgn:id":2364330,
    "tgn:name":"Green Shadow Lake",
    "tgn:placetype":[
        "aat:300006191"
    ]
},
  "bbox": [],
  "geometry": {"coordinates":[-84.7833,35.0333],"type":"Point"}
}