{
  "id": 7009513,
  "type": "Feature",
  "properties": {
    "tgn:hierarchy":[
        "tgn:7009513",
        "tgn:7002872",
        "tgn:1000003",
        "tgn:1000070",
        "tgn:7029392"
    ],
    "tgn:id":7009513,
    "tgn:name":"Trun",
    "tgn:placetype":[
        "aat:300008347"
    ]
},
  "bbox": [],
  "geometry": {"coordinates":[0.0333,48.8333],"type":"Point"}
}