{
  "id": 1085896,
  "type": "Feature",
  "properties": {
    "tgn:hierarchy":[
        "tgn:1085896",
        "tgn:1001135",
        "tgn:1000004",
        "tgn:7018450",
        "tgn:1000144",
        "tgn:7029392"
    ],
    "tgn:id":1085896,
    "tgn:name":"\u0130vrindi",
    "tgn:placetype":[
        "aat:300008347"
    ]
},
  "bbox": [],
  "geometry": {"coordinates":[27.45,39.55],"type":"Point"}
}