<<<<<<< HEAD
{
  "id": 7379171,
  "type": "Feature",
  "properties": {
    "tgn:hierarchy":[
        "tgn:7379171",
        "tgn:1000001",
        "tgn:7005595",
        "tgn:7005560",
        "tgn:7029392"
    ],
    "tgn:id":7379171,
    "tgn:name":"Mezcales, Arroyo de los",
    "tgn:placetype":[
        "aat:300266554",
        "aat:300008699"
    ]
},
  "bbox": [],
  "geometry": {"coordinates":[-107.733333,25.133333],"type":"Point"}
}
=======
{"geometry":{"type":"Point","coordinates":[-107.733333,25.133333]},"type":"Feature","properties":{"hierarchy":["tgn:7379171","tgn:1000001","tgn:7005595","tgn:7005560","tgn:7029392"],"placetype":["aat:300266554","aat:300008699"],"id":7379171,"name:xx":"Mezcales, Arroyo de los"}}
>>>>>>> 03f74aca74312dbeaf24d7e61306dd6a786dc3d0
