{
  "id": 7016176,
  "type": "Feature",
  "properties": {
    "tgn:hierarchy":[
        "tgn:7016176",
        "tgn:1000001",
        "tgn:1002284",
        "tgn:7012149",
        "tgn:7007568",
        "tgn:7029392"
    ],
    "tgn:id":7016176,
    "tgn:name":"Plattsburgh",
    "tgn:placetype":[
        "aat:300008347",
        "aat:300008389"
    ]
},
  "bbox": [],
  "geometry": {"coordinates":[-73.45,44.6833],"type":"Point"}
}