{
  "id": 7352092,
  "type": "Feature",
  "properties": {
    "tgn:hierarchy":[
        "tgn:7352092",
        "tgn:1001853",
        "tgn:1000001",
        "tgn:7005560",
        "tgn:7029392"
    ],
    "tgn:id":7352092,
    "tgn:name":"Barrancas",
    "tgn:placetype":[
        "aat:300008347"
    ]
},
  "bbox": [],
  "geometry": {"coordinates":[-101.133333,25.466667],"type":"Point"}
}