{
  "id": 2741942,
  "type": "Feature",
  "properties": {
    "tgn:hierarchy":[
        "tgn:2741942",
        "tgn:1000001",
        "tgn:2001435",
        "tgn:7012149",
        "tgn:7007566",
        "tgn:7029392"
    ],
    "tgn:id":2741942,
    "tgn:name":"Vado Quarry Number One",
    "tgn:placetype":[
        "aat:300000390"
    ]
},
  "bbox": [],
  "geometry": {"coordinates":[-106.6333,32.1333],"type":"Point"}
}