{
  "id": 1069981,
  "type": "Feature",
  "properties": {
    "tgn:hierarchy":[
        "tgn:1069981",
        "tgn:1000004",
        "tgn:7002077",
        "tgn:1000111",
        "tgn:7029392"
    ],
    "tgn:id":1069981,
    "tgn:name":"Liujiang",
    "tgn:placetype":[
        "aat:300008347"
    ]
},
  "bbox": [],
  "geometry": {"coordinates":[119.6167,40.0833],"type":"Point"}
}