{
  "id": 2580882,
  "type": "Feature",
  "properties": {
    "tgn:hierarchy":[
        "tgn:2580882",
        "tgn:1000001",
        "tgn:7012149",
        "tgn:2001060",
        "tgn:7007521",
        "tgn:7029392"
    ],
    "tgn:id":2580882,
    "tgn:name":"Pigs Eye Island Number Two",
    "tgn:placetype":[
        "aat:300008791"
    ]
},
  "bbox": [],
  "geometry": {"coordinates":[-93.0167,44.8833],"type":"Point"}
}