{
  "id": 2683791,
  "type": "Feature",
  "properties": {
    "tgn:hierarchy":[
        "tgn:2683791",
        "tgn:1000001",
        "tgn:7012149",
        "tgn:2000928",
        "tgn:7007515",
        "tgn:7029392"
    ],
    "tgn:id":2683791,
    "tgn:name":"Spectacle Ponds",
    "tgn:placetype":[
        "aat:300008680"
    ]
},
  "bbox": [],
  "geometry": {"coordinates":[-69.5333,45.3333],"type":"Point"}
}