<<<<<<< HEAD
{
  "id": 2331173,
  "type": "Feature",
  "properties": {
    "tgn:hierarchy":[
        "tgn:2331173",
        "tgn:2001560",
        "tgn:1000001",
        "tgn:7012149",
        "tgn:7007705",
        "tgn:7029392"
    ],
    "tgn:id":2331173,
    "tgn:name":"Flat Top Butte",
    "tgn:placetype":[
        "aat:300008798"
    ]
},
  "bbox": [],
  "geometry": {"coordinates":[-103.3167,46.7],"type":"Point"}
}
=======
{"geometry":{"type":"Point","coordinates":[-103.316700,46.700000]},"type":"Feature","properties":{"hierarchy":["tgn:2331173","tgn:2001560","tgn:1000001","tgn:7012149","tgn:7007705","tgn:7029392"],"placetype":["aat:300008798"],"id":2331173,"name:xx":"Flat Top Butte"}}
>>>>>>> 03f74aca74312dbeaf24d7e61306dd6a786dc3d0
