{
  "id": 2424444,
  "type": "Feature",
  "properties": {
    "tgn:hierarchy":[
        "tgn:2424444",
        "tgn:1000001",
        "tgn:7012149",
        "tgn:1003042",
        "tgn:7007920",
        "tgn:7029392"
    ],
    "tgn:id":2424444,
    "tgn:name":"Johnson Canyon",
    "tgn:placetype":[
        "aat:300008761"
    ]
},
  "bbox": [],
  "geometry": {"coordinates":[-120.9833,46.85],"type":"Point"}
}