{
  "id": 2394436,
  "type": "Feature",
  "properties": {
    "tgn:hierarchy":[
        "tgn:2394436",
        "tgn:1000001",
        "tgn:7012149",
        "tgn:2000432",
        "tgn:7007248",
        "tgn:7029392"
    ],
    "tgn:id":2394436,
    "tgn:name":"Hogg Mountain",
    "tgn:placetype":[
        "aat:300008798"
    ]
},
  "bbox": [],
  "geometry": {"coordinates":[-85.0667,32.95],"type":"Point"}
}