{
  "id": 7350932,
  "type": "Feature",
  "properties": {
    "tgn:hierarchy":[
        "tgn:7350932",
        "tgn:1001835",
        "tgn:1000001",
        "tgn:7005560",
        "tgn:7029392"
    ],
    "tgn:id":7350932,
    "tgn:name":"Rancho Bajio Largo",
    "tgn:placetype":[
        "aat:300000241"
    ]
},
  "bbox": [],
  "geometry": {"coordinates":[-116.283333,32.25],"type":"Point"}
}