{
  "id": 1045887,
  "type": "Feature",
  "properties": {
    "tgn:hierarchy":[
        "tgn:1045887",
        "tgn:7003137",
        "tgn:1000003",
        "tgn:7003080",
        "tgn:1000080",
        "tgn:7029392"
    ],
    "tgn:id":1045887,
    "tgn:name":"Passo Corese",
    "tgn:placetype":[
        "aat:300008347"
    ]
},
  "bbox": [],
  "geometry": {"coordinates":[12.65,42.15],"type":"Point"}
}