{
  "id": 2460088,
  "type": "Feature",
  "properties": {
    "tgn:hierarchy":[
        "tgn:2460088",
        "tgn:1000001",
        "tgn:2000922",
        "tgn:7012149",
        "tgn:7007515",
        "tgn:7029392"
    ],
    "tgn:id":2460088,
    "tgn:name":"Little Rocky Pond",
    "tgn:placetype":[
        "aat:300008680"
    ]
},
  "bbox": [],
  "geometry": {"coordinates":[-68.5333,44.6333],"type":"Point"}
}