{
  "id": 1055333,
  "type": "Feature",
  "properties": {
    "tgn:hierarchy":[
        "tgn:1055333",
        "tgn:1000004",
        "tgn:7011589",
        "tgn:7018214",
        "tgn:7002435",
        "tgn:7029392"
    ],
    "tgn:id":1055333,
    "tgn:name":"Kirza",
    "tgn:placetype":[
        "aat:300008347"
    ]
},
  "bbox": [],
  "geometry": {"coordinates":[81.7167,54.2333],"type":"Point"}
}