{
  "id": 7575927,
  "type": "Feature",
  "properties": {
    "tgn:hierarchy":[
        "tgn:7575927",
        "tgn:1000004",
        "tgn:7000198",
        "tgn:7016883",
        "tgn:7029392"
    ],
    "tgn:id":7575927,
    "tgn:name:en":"Lakkhoke Bahr\u0101m",
    "tgn:placetype":[
        "aat:300008347"
    ]
},
  "bbox": [],
  "geometry": {"coordinates":[74.448699,30.825235],"type":"Point"}
}