{
  "id": 7112499,
  "type": "Feature",
  "properties": {
    "tgn:hierarchy":[
        "tgn:7112499",
        "tgn:7003692",
        "tgn:1000003",
        "tgn:7000084",
        "tgn:7029392"
    ],
    "tgn:id":7112499,
    "tgn:name":"R\u00f6hlingen",
    "tgn:placetype":[
        "aat:300008347"
    ]
},
  "bbox": [],
  "geometry": {"coordinates":[10.216667,48.95],"type":"Point"}
}