{
  "id": 1113540,
  "type": "Feature",
  "properties": {
    "tgn:hierarchy":[
        "tgn:1113540",
        "tgn:1000001",
        "tgn:7029392"
    ],
    "tgn:id":1113540,
    "tgn:name":"Omoa, Bah\u00eda de",
    "tgn:placetype":[
        "aat:300132316"
    ]
},
  "bbox": [],
  "geometry": {"coordinates":[-88.1667,15.75],"type":"Point"}
}