{
  "id": 2306154,
  "type": "Feature",
  "properties": {
    "tgn:hierarchy":[
        "tgn:2306154",
        "tgn:1000001",
        "tgn:7012149",
        "tgn:2001290",
        "tgn:7007524",
        "tgn:7029392"
    ],
    "tgn:id":2306154,
    "tgn:name":"East Fork Big Creek",
    "tgn:placetype":[
        "aat:300008706"
    ]
},
  "bbox": [],
  "geometry": {"coordinates":[-115.45,47.2667],"type":"Point"}
}