{
  "id": 2182902,
  "type": "Feature",
  "properties": {
    "tgn:hierarchy":[
        "tgn:2182902",
        "tgn:1000001",
        "tgn:7012149",
        "tgn:2002021",
        "tgn:7007826",
        "tgn:7029392"
    ],
    "tgn:id":2182902,
    "tgn:name":"Blue Waterhole",
    "tgn:placetype":[
        "aat:300008680"
    ]
},
  "bbox": [],
  "geometry": {"coordinates":[-100.2667,29.55],"type":"Point"}
}