{
  "id": 7084441,
  "type": "Feature",
  "properties": {
    "tgn:hierarchy":[
        "tgn:7084441",
        "tgn:1000003",
        "tgn:7000094",
        "tgn:7000084",
        "tgn:7029392"
    ],
    "tgn:id":7084441,
    "tgn:name":"Weitenfeld",
    "tgn:placetype":[
        "aat:300008347"
    ]
},
  "bbox": [],
  "geometry": {"coordinates":[10.783333,53.333333],"type":"Point"}
}