{
  "id": 2499255,
  "type": "Feature",
  "properties": {
    "tgn:hierarchy":[
        "tgn:2499255",
        "tgn:1000001",
        "tgn:7012149",
        "tgn:2001906",
        "tgn:7007825",
        "tgn:7029392"
    ],
    "tgn:id":2499255,
    "tgn:name":"McClary Islands",
    "tgn:placetype":[
        "aat:300386853"
    ]
},
  "bbox": [],
  "geometry": {"coordinates":[-84.6333,35.2167],"type":"Point"}
}