{
  "id": 1075355,
  "type": "Feature",
  "properties": {
    "tgn:hierarchy":[
        "tgn:1075355",
        "tgn:1000004",
        "tgn:7000198",
        "tgn:1001977",
        "tgn:7029392"
    ],
    "tgn:id":1075355,
    "tgn:name:en":"Go\u0101ltor",
    "tgn:placetype":[
        "aat:300008347"
    ]
},
  "bbox": [],
  "geometry": {"coordinates":[87.169644,22.709431],"type":"Point"}
}