{
  "id": 2421021,
  "type": "Feature",
  "properties": {
    "tgn:hierarchy":[
        "tgn:2421021",
        "tgn:1000001",
        "tgn:1002257",
        "tgn:7012149",
        "tgn:7007919",
        "tgn:7029392"
    ],
    "tgn:id":2421021,
    "tgn:name":"Jerdones Big Woods",
    "tgn:placetype":[
        "aat:300132451"
    ]
},
  "bbox": [],
  "geometry": {"coordinates":[-77.0333,37.3833],"type":"Point"}
}