{
  "id": 7036459,
  "type": "Feature",
  "properties": {
    "tgn:hierarchy":[
        "tgn:7036459",
        "tgn:1003506",
        "tgn:1000003",
        "tgn:7002993",
        "tgn:1000080",
        "tgn:7029392"
    ],
    "tgn:id":7036459,
    "tgn:name":"Venzonazza, Torrente",
    "tgn:placetype":[
        "aat:300008699"
    ]
},
  "bbox": [],
  "geometry": {"coordinates":[13.138889,46.336944],"type":"Point"}
}