{
  "id": 2487005,
  "type": "Feature",
  "properties": {
    "tgn:hierarchy":[
        "tgn:2487005",
        "tgn:1000001",
        "tgn:7012149",
        "tgn:2001503",
        "tgn:7007709",
        "tgn:7029392"
    ],
    "tgn:id":2487005,
    "tgn:name":"Lee Mountain",
    "tgn:placetype":[
        "aat:300008798"
    ]
},
  "bbox": [],
  "geometry": {"coordinates":[-82.8667,35.6167],"type":"Point"}
}