<<<<<<< HEAD
{
  "id": 7241357,
  "type": "Feature",
  "properties": {
    "tgn:hierarchy":[
        "tgn:7241357",
        "tgn:7003465",
        "tgn:1000003",
        "tgn:1000063",
        "tgn:4012014",
        "tgn:7029392"
    ],
    "tgn:id":7241357,
    "tgn:name":"La Belle au Bois",
    "tgn:placetype":[
        "aat:300008347"
    ]
},
  "bbox": [],
  "geometry": {"coordinates":[5.5,49.916667],"type":"Point"}
}
=======
{"geometry":{"type":"Point","coordinates":[5.500000,49.916667]},"type":"Feature","properties":{"hierarchy":["tgn:7241357","tgn:7003465","tgn:1000003","tgn:1000063","tgn:4012014","tgn:7029392"],"placetype":["aat:300008347"],"id":7241357,"name:xx":"La Belle au Bois"}}
>>>>>>> 03f74aca74312dbeaf24d7e61306dd6a786dc3d0
