{
  "id": 7530138,
  "type": "Feature",
  "properties": {
    "tgn:hierarchy":[
        "tgn:7530138",
        "tgn:7001242",
        "tgn:7016833",
        "tgn:1001113",
        "tgn:7029392"
    ],
    "tgn:id":7530138,
    "tgn:name":"Tur'at Shinb\u0101rah",
    "tgn:placetype":[
        "aat:300006075"
    ]
},
  "bbox": [],
  "geometry": {"coordinates":[31.657525,30.50502],"type":"Point"}
}