{
  "id": 7380342,
  "type": "Feature",
  "properties": {
    "tgn:hierarchy":[
        "tgn:7380342",
        "tgn:7005581",
        "tgn:1000001",
        "tgn:7005560",
        "tgn:7029392"
    ],
    "tgn:id":7380342,
    "tgn:name":"Macho Grullo",
    "tgn:placetype":[
        "aat:300008347"
    ]
},
  "bbox": [],
  "geometry": {"coordinates":[-106.283333,26.733333],"type":"Point"}
}