{
  "id": 7589743,
  "type": "Feature",
  "properties": {
    "tgn:hierarchy":[
        "tgn:7589743",
        "tgn:1000004",
        "tgn:7000198",
        "tgn:7000799",
        "tgn:7029392"
    ],
    "tgn:id":7589743,
    "tgn:name:en":"Yogm\u0101th\u0101ng",
    "tgn:placetype":[
        "aat:300008347"
    ]
},
  "bbox": [],
  "geometry": {"coordinates":[76.343056,34.658333],"type":"Point"}
}