{
  "id": 2763558,
  "type": "Feature",
  "properties": {
    "tgn:hierarchy":[
        "tgn:2763558",
        "tgn:1000001",
        "tgn:7012149",
        "tgn:1002628",
        "tgn:7007240",
        "tgn:7029392"
    ],
    "tgn:id":2763558,
    "tgn:name":"Whale Key",
    "tgn:placetype":[
        "aat:300008791"
    ]
},
  "bbox": [],
  "geometry": {"coordinates":[-82.6167,27.3833],"type":"Point"}
}