{
  "id": 7509169,
  "type": "Feature",
  "properties": {
    "tgn:hierarchy":[
        "tgn:7509169",
        "tgn:1009227",
        "tgn:1000226",
        "tgn:7016822",
        "tgn:1000006",
        "tgn:7029392"
    ],
    "tgn:id":7509169,
    "tgn:name:en":"Waimea Stream",
    "tgn:placetype":[
        "aat:300008699"
    ]
},
  "bbox": [],
  "geometry": {"coordinates":[168.816667,-45.983333],"type":"Point"}
}