{
  "id": 1071841,
  "type": "Feature",
  "properties": {
    "tgn:hierarchy":[
        "tgn:1071841",
        "tgn:1000004",
        "tgn:7002080",
        "tgn:1000111",
        "tgn:7029392"
    ],
    "tgn:id":1071841,
    "tgn:name":"Shuibatang",
    "tgn:placetype":[
        "aat:300008347"
    ]
},
  "bbox": [],
  "geometry": {"coordinates":[107.0833,28.7167],"type":"Point"}
}