{
  "id": 2022860,
  "type": "Feature",
  "properties": {
    "tgn:hierarchy":[
        "tgn:2022860",
        "tgn:1000001",
        "tgn:2000323",
        "tgn:7012149",
        "tgn:7007248",
        "tgn:7029392"
    ],
    "tgn:id":2022860,
    "tgn:name":"Fargo",
    "tgn:placetype":[
        "aat:300008347"
    ]
},
  "bbox": [],
  "geometry": {"coordinates":[-82.55,30.6833],"type":"Point"}
}