{
  "id": 2419531,
  "type": "Feature",
  "properties": {
    "tgn:hierarchy":[
        "tgn:2419531",
        "tgn:1000001",
        "tgn:7012149",
        "tgn:2000789",
        "tgn:7007255",
        "tgn:7029392"
    ],
    "tgn:id":2419531,
    "tgn:name":"Jarrell Fork",
    "tgn:placetype":[
        "aat:300008699"
    ]
},
  "bbox": [],
  "geometry": {"coordinates":[-82.7667,37.5833],"type":"Point"}
}