{
  "id": 7052354,
  "type": "Feature",
  "properties": {
    "tgn:hierarchy":[
        "tgn:7052354",
        "tgn:7003170",
        "tgn:1000003",
        "tgn:7003125",
        "tgn:1000080",
        "tgn:7029392"
    ],
    "tgn:id":7052354,
    "tgn:name":"Morleschio",
    "tgn:placetype":[
        "aat:300008347"
    ]
},
  "bbox": [],
  "geometry": {"coordinates":[12.466667,43.216667],"type":"Point"}
}