{
  "id": 2545296,
  "type": "Feature",
  "properties": {
    "tgn:hierarchy":[
        "tgn:2545296",
        "tgn:1000001",
        "tgn:7012149",
        "tgn:2001715",
        "tgn:7007708",
        "tgn:7029392"
    ],
    "tgn:id":2545296,
    "tgn:name":"North Fork Augur Creek",
    "tgn:placetype":[
        "aat:300008706"
    ]
},
  "bbox": [],
  "geometry": {"coordinates":[-120.7167,42.5333],"type":"Point"}
}