{
  "id": 7589325,
  "type": "Feature",
  "properties": {
    "tgn:hierarchy":[
        "tgn:7589325",
        "tgn:1000004",
        "tgn:7000198",
        "tgn:1001977",
        "tgn:7029392"
    ],
    "tgn:id":7589325,
    "tgn:name:en":"Bichania",
    "tgn:placetype":[
        "aat:300008347"
    ]
},
  "bbox": [],
  "geometry": {"coordinates":[87.806922,21.727705],"type":"Point"}
}