{
  "id": 1104045,
  "type": "Feature",
  "properties": {
    "tgn:hierarchy":[
        "tgn:1104045",
        "tgn:1000001",
        "tgn:1002601",
        "tgn:7012149",
        "tgn:7007159",
        "tgn:7029392"
    ],
    "tgn:id":1104045,
    "tgn:name":"Bradford Mountain",
    "tgn:placetype":[
        "aat:300008795"
    ]
},
  "bbox": [],
  "geometry": {"coordinates":[-73.2833,41.9833],"type":"Point"}
}