{
  "id": 2554961,
  "type": "Feature",
  "properties": {
    "tgn:hierarchy":[
        "tgn:2554961",
        "tgn:1000001",
        "tgn:7012149",
        "tgn:2000546",
        "tgn:7007252",
        "tgn:7029392"
    ],
    "tgn:id":2554961,
    "tgn:name":"Oberlin Lake",
    "tgn:placetype":[
        "aat:300006191"
    ]
},
  "bbox": [],
  "geometry": {"coordinates":[-86.8667,38.8833],"type":"Point"}
}