{
  "id": 2110572,
  "type": "Feature",
  "properties": {
    "tgn:hierarchy":[
        "tgn:2110572",
        "tgn:1000001",
        "tgn:7012149",
        "tgn:1002362",
        "tgn:7007919",
        "tgn:7029392"
    ],
    "tgn:id":2110572,
    "tgn:name":"Beazley",
    "tgn:placetype":[
        "aat:300008347",
        "aat:300387210"
    ]
},
  "bbox": [],
  "geometry": {"coordinates":[-77.0667,37.95],"type":"Point"}
}