{
  "id": 7077031,
  "type": "Feature",
  "properties": {
    "tgn:hierarchy":[
        "tgn:7077031",
        "tgn:1000003",
        "tgn:7003682",
        "tgn:7000084",
        "tgn:7029392"
    ],
    "tgn:id":7077031,
    "tgn:name":"Sickinger H\u00f6he",
    "tgn:placetype":[
        "aat:300008777"
    ]
},
  "bbox": [],
  "geometry": {"coordinates":[7.516667,49.35],"type":"Point"}
}