{
  "id": 1010860,
  "type": "Feature",
  "properties": {
    "tgn:hierarchy":[
        "tgn:1010860",
        "tgn:7001242",
        "tgn:7030583",
        "tgn:1000198",
        "tgn:7029392"
    ],
    "tgn:id":1010860,
    "tgn:name":"Cross, Cape",
    "tgn:placetype":[
        "aat:300008850"
    ]
},
  "bbox": [],
  "geometry": {"coordinates":[13.9667,-21.7833],"type":"Point"}
}