{
  "id": 2604374,
  "type": "Feature",
  "properties": {
    "tgn:hierarchy":[
        "tgn:2604374",
        "tgn:1000001",
        "tgn:7012149",
        "tgn:2001714",
        "tgn:7007708",
        "tgn:7029392"
    ],
    "tgn:id":2604374,
    "tgn:name":"Rabbit Creek",
    "tgn:placetype":[
        "aat:300008706"
    ]
},
  "bbox": [],
  "geometry": {"coordinates":[-121.9333,43.3333],"type":"Point"}
}