{
  "id": 7093856,
  "type": "Feature",
  "properties": {
    "tgn:hierarchy":[
        "tgn:7093856",
        "tgn:1000003",
        "tgn:7000094",
        "tgn:7000084",
        "tgn:7029392"
    ],
    "tgn:id":7093856,
    "tgn:name":"Seehof",
    "tgn:placetype":[
        "aat:300008347"
    ]
},
  "bbox": [],
  "geometry": {"coordinates":[13.15,54.55],"type":"Point"}
}