{
  "id": 2765303,
  "type": "Feature",
  "properties": {
    "tgn:hierarchy":[
        "tgn:2765303",
        "tgn:1000001",
        "tgn:7012149",
        "tgn:1002790",
        "tgn:7007240",
        "tgn:7029392"
    ],
    "tgn:id":2765303,
    "tgn:name":"Whitcomb Bayou",
    "tgn:placetype":[
        "aat:300132316"
    ]
},
  "bbox": [],
  "geometry": {"coordinates":[-82.75,28.1333],"type":"Point"}
}