{
  "id": 7324167,
  "type": "Feature",
  "properties": {
    "tgn:hierarchy":[
        "tgn:7324167",
        "tgn:7002825",
        "tgn:7016622",
        "tgn:1000003",
        "tgn:1000095",
        "tgn:7029392"
    ],
    "tgn:id":7324167,
    "tgn:name":"San Isidro",
    "tgn:placetype":[
        "aat:300008347"
    ]
},
  "bbox": [],
  "geometry": {"coordinates":[-15.666667,28.133333],"type":"Point"}
}