{
  "id": 2217473,
  "type": "Feature",
  "properties": {
    "tgn:hierarchy":[
        "tgn:2217473",
        "tgn:1000001",
        "tgn:7012149",
        "tgn:2000395",
        "tgn:7007248",
        "tgn:7029392"
    ],
    "tgn:id":2217473,
    "tgn:name":"Campbell Creek",
    "tgn:placetype":[
        "aat:300008706"
    ]
},
  "bbox": [],
  "geometry": {"coordinates":[-83.6167,33.5833],"type":"Point"}
}