{
  "id": 7568091,
  "type": "Feature",
  "properties": {
    "tgn:hierarchy":[
        "tgn:7568091",
        "tgn:1000004",
        "tgn:7000198",
        "tgn:7031786",
        "tgn:7029392"
    ],
    "tgn:id":7568091,
    "tgn:name:en":"Sukoli Talli",
    "tgn:placetype":[
        "aat:300008347"
    ]
},
  "bbox": [],
  "geometry": {"coordinates":[78.746389,29.763611],"type":"Point"}
}