{
  "id": 7129357,
  "type": "Feature",
  "properties": {
    "tgn:hierarchy":[
        "tgn:7129357",
        "tgn:1000003",
        "tgn:7000094",
        "tgn:7000084",
        "tgn:7029392"
    ],
    "tgn:id":7129357,
    "tgn:name":"Melzerm\u00fchle",
    "tgn:placetype":[
        "aat:300000206"
    ]
},
  "bbox": [],
  "geometry": {"coordinates":[12.616667,53.333333],"type":"Point"}
}