{
  "id": 7543619,
  "type": "Feature",
  "properties": {
    "tgn:hierarchy":[
        "tgn:7543619",
        "tgn:7001242",
        "tgn:7016833",
        "tgn:1001079",
        "tgn:7029392"
    ],
    "tgn:id":7543619,
    "tgn:name:en":"Al Taft\u012bsh al Awwal",
    "tgn:placetype":[
        "aat:300008347"
    ]
},
  "bbox": [],
  "geometry": {"coordinates":[29.9628,30.816744],"type":"Point"}
}