{
  "id": 7489034,
  "type": "Feature",
  "properties": {
    "tgn:hierarchy":[
        "tgn:7489034",
        "tgn:7001010",
        "tgn:1000004",
        "tgn:1000141",
        "tgn:7029392"
    ],
    "tgn:id":7489034,
    "tgn:name":"Gucun Shan",
    "tgn:placetype":[
        "aat:300008798"
    ]
},
  "bbox": [],
  "geometry": {"coordinates":[121.325969,23.44372],"type":"Point"}
}