{
  "id": 7578294,
  "type": "Feature",
  "properties": {
    "tgn:hierarchy":[
        "tgn:7578294",
        "tgn:1000004",
        "tgn:7000198",
        "tgn:1001895",
        "tgn:7029392"
    ],
    "tgn:id":7578294,
    "tgn:name:en":"Talni",
    "tgn:placetype":[
        "aat:300008347"
    ]
},
  "bbox": [],
  "geometry": {"coordinates":[77.616667,18.783333],"type":"Point"}
}