{
  "id": 7320898,
  "type": "Feature",
  "properties": {
    "tgn:hierarchy":[
        "tgn:7320898",
        "tgn:1001623",
        "tgn:1000049",
        "tgn:1000002",
        "tgn:7029392"
    ],
    "tgn:id":7320898,
    "tgn:name":"Bandera, Cerro",
    "tgn:placetype":[
        "aat:300008795"
    ]
},
  "bbox": [],
  "geometry": {"coordinates":[-71.866667,-46.016667],"type":"Point"}
}