{
  "id": 2441225,
  "type": "Feature",
  "properties": {
    "tgn:hierarchy":[
        "tgn:2441225",
        "tgn:1000001",
        "tgn:7012149",
        "tgn:2000230",
        "tgn:7007158",
        "tgn:7029392"
    ],
    "tgn:id":2441225,
    "tgn:name":"Knowles Canyon",
    "tgn:placetype":[
        "aat:300008761"
    ]
},
  "bbox": [],
  "geometry": {"coordinates":[-108.8667,39.0667],"type":"Point"}
}