{
  "id": 2243674,
  "type": "Feature",
  "properties": {
    "tgn:hierarchy":[
        "tgn:2243674",
        "tgn:1000001",
        "tgn:7016172",
        "tgn:2000117",
        "tgn:7012149",
        "tgn:7029392"
    ],
    "tgn:id":2243674,
    "tgn:name":"Clements Pond",
    "tgn:placetype":[
        "aat:300006191"
    ]
},
  "bbox": [],
  "geometry": {"coordinates":[-92.3167,33.9333],"type":"Point"}
}