{
  "id": 2362463,
  "type": "Feature",
  "properties": {
    "tgn:hierarchy":[
        "tgn:2362463",
        "tgn:1000001",
        "tgn:7012149",
        "tgn:1002508",
        "tgn:7007252",
        "tgn:7029392"
    ],
    "tgn:id":2362463,
    "tgn:name":"Greasy Creek",
    "tgn:placetype":[
        "aat:300008706"
    ]
},
  "bbox": [],
  "geometry": {"coordinates":[-86.2167,38.8167],"type":"Point"}
}