<<<<<<< HEAD
{
  "id": 2256844,
  "type": "Feature",
  "properties": {
    "tgn:hierarchy":[
        "tgn:2256844",
        "tgn:1000001",
        "tgn:7012149",
        "tgn:2001715",
        "tgn:7007708",
        "tgn:7029392"
    ],
    "tgn:id":2256844,
    "tgn:name":"Cork Reservoir Number Seven",
    "tgn:placetype":[
        "aat:300006191"
    ]
},
  "bbox": [],
  "geometry": {"coordinates":[-119.9333,42.05],"type":"Point"}
}
=======
{"geometry":{"type":"Point","coordinates":[-119.933300,42.050000]},"type":"Feature","properties":{"hierarchy":["tgn:2256844","tgn:1000001","tgn:7012149","tgn:2001715","tgn:7007708","tgn:7029392"],"placetype":["aat:300006191"],"id":2256844,"name:xx":"Cork Reservoir Number Seven"}}
>>>>>>> 03f74aca74312dbeaf24d7e61306dd6a786dc3d0
