{
  "id": 2037813,
  "type": "Feature",
  "properties": {
    "tgn:hierarchy":[
        "tgn:2037813",
        "tgn:1000001",
        "tgn:7012149",
        "tgn:1002516",
        "tgn:7007255",
        "tgn:7029392"
    ],
    "tgn:id":2037813,
    "tgn:name":"Blue Ridge Manor",
    "tgn:placetype":[
        "aat:300008347"
    ]
},
  "bbox": [],
  "geometry": {"coordinates":[-85.55,38.2333],"type":"Point"}
}