{
  "id": 2495617,
  "type": "Feature",
  "properties": {
    "tgn:hierarchy":[
        "tgn:2495617",
        "tgn:1000001",
        "tgn:7006451",
        "tgn:2000094",
        "tgn:7012149",
        "tgn:7029392"
    ],
    "tgn:id":2495617,
    "tgn:name":"Mash Barrel Spring",
    "tgn:placetype":[
        "aat:300008697"
    ]
},
  "bbox": [],
  "geometry": {"coordinates":[-109.8333,32.5167],"type":"Point"}
}