{
  "id": 2127728,
  "type": "Feature",
  "properties": {
    "tgn:hierarchy":[
        "tgn:2127728",
        "tgn:1000001",
        "tgn:7012149",
        "tgn:7007157",
        "tgn:1002901",
        "tgn:7029392"
    ],
    "tgn:id":2127728,
    "tgn:name":"Alamo Creek",
    "tgn:placetype":[
        "aat:300008706"
    ]
},
  "bbox": [],
  "geometry": {"coordinates":[-122.0833,38.3833],"type":"Point"}
}