{
  "id": 2698784,
  "type": "Feature",
  "properties": {
    "tgn:hierarchy":[
        "tgn:2698784",
        "tgn:1000001",
        "tgn:7012149",
        "tgn:2001715",
        "tgn:7007708",
        "tgn:7029392"
    ],
    "tgn:id":2698784,
    "tgn:name":"Strawberry Butte",
    "tgn:placetype":[
        "aat:300008798"
    ]
},
  "bbox": [],
  "geometry": {"coordinates":[-120.8667,42.0833],"type":"Point"}
}