{
  "id": 2640758,
  "type": "Feature",
  "properties": {
    "tgn:hierarchy":[
        "tgn:2640758",
        "tgn:1000001",
        "tgn:7012149",
        "tgn:7007157",
        "tgn:7014005",
        "tgn:7029392"
    ],
    "tgn:id":2640758,
    "tgn:name":"San Pedro Hill",
    "tgn:placetype":[
        "aat:300008798"
    ]
},
  "bbox": [],
  "geometry": {"coordinates":[-122.45,37.9833],"type":"Point"}
}