<<<<<<< HEAD
{
  "id": 7059464,
  "type": "Feature",
  "properties": {
    "tgn:hierarchy":[
        "tgn:7059464",
        "tgn:1000003",
        "tgn:7003688",
        "tgn:7000084",
        "tgn:7029392"
    ],
    "tgn:id":7059464,
    "tgn:name":"Altenweide",
    "tgn:placetype":[
        "aat:300000206"
    ]
},
  "bbox": [],
  "geometry": {"coordinates":[10.433333,53.866667],"type":"Point"}
}
=======
{"geometry":{"type":"Point","coordinates":[10.433333,53.866667]},"type":"Feature","properties":{"hierarchy":["tgn:7059464","tgn:1000003","tgn:7003688","tgn:7000084","tgn:7029392"],"placetype":["aat:300000206"],"id":7059464,"name:xx":"Altenweide"}}
>>>>>>> 03f74aca74312dbeaf24d7e61306dd6a786dc3d0
