{
  "id": 2152059,
  "type": "Feature",
  "properties": {
    "tgn:hierarchy":[
        "tgn:2152059",
        "tgn:1000001",
        "tgn:7012149",
        "tgn:2001869",
        "tgn:7007825",
        "tgn:7029392"
    ],
    "tgn:id":2152059,
    "tgn:name":"Bauxite Ridge",
    "tgn:placetype":[
        "aat:300266640"
    ]
},
  "bbox": [],
  "geometry": {"coordinates":[-85.0333,35.0167],"type":"Point"}
}