{
  "id": 2405903,
  "type": "Feature",
  "properties": {
    "tgn:hierarchy":[
        "tgn:2405903",
        "tgn:1000001",
        "tgn:7012149",
        "tgn:2001254",
        "tgn:7007523",
        "tgn:7029392"
    ],
    "tgn:id":2405903,
    "tgn:name":"Hulsey",
    "tgn:placetype":[
        "aat:300008347"
    ]
},
  "bbox": [],
  "geometry": {"coordinates":[-91.0333,38.1667],"type":"Point"}
}