{
  "id": 2573876,
  "type": "Feature",
  "properties": {
    "tgn:hierarchy":[
        "tgn:2573876",
        "tgn:7013349",
        "tgn:1000001",
        "tgn:7012149",
        "tgn:7007708",
        "tgn:7029392"
    ],
    "tgn:id":2573876,
    "tgn:name":"Pedro",
    "tgn:placetype":[
        "aat:300008347"
    ]
},
  "bbox": [],
  "geometry": {"coordinates":[-117.5167,44.4667],"type":"Point"}
}