<<<<<<< HEAD
{
  "id": 2337937,
  "type": "Feature",
  "properties": {
    "tgn:hierarchy":[
        "tgn:2337937",
        "tgn:1000001",
        "tgn:7012149",
        "tgn:1002837",
        "tgn:7007255",
        "tgn:7029392"
    ],
    "tgn:id":2337937,
    "tgn:name":"Fox Hollow",
    "tgn:placetype":[
        "aat:300008761"
    ]
},
  "bbox": [],
  "geometry": {"coordinates":[-83.55,38.2167],"type":"Point"}
}
=======
{"geometry":{"type":"Point","coordinates":[-83.550000,38.216700]},"type":"Feature","properties":{"hierarchy":["tgn:2337937","tgn:1000001","tgn:7012149","tgn:1002837","tgn:7007255","tgn:7029392"],"placetype":["aat:300008761"],"id":2337937,"name:xx":"Fox Hollow"}}
>>>>>>> 03f74aca74312dbeaf24d7e61306dd6a786dc3d0
