{
  "id": 7437663,
  "type": "Feature",
  "properties": {
    "tgn:hierarchy":[
        "tgn:7437663",
        "tgn:1000001",
        "tgn:1001960",
        "tgn:7005560",
        "tgn:7029392"
    ],
    "tgn:id":7437663,
    "tgn:name":"T\u00edo Ram\u00f3n, Isla",
    "tgn:placetype":[
        "aat:300008791"
    ]
},
  "bbox": [],
  "geometry": {"coordinates":[-110.866667,27.933333],"type":"Point"}
}