{
  "id": 2671427,
  "type": "Feature",
  "properties": {
    "tgn:hierarchy":[
        "tgn:2671427",
        "tgn:1000001",
        "tgn:2002241",
        "tgn:7012149",
        "tgn:7007920",
        "tgn:7029392"
    ],
    "tgn:id":2671427,
    "tgn:name":"Smith Hollow",
    "tgn:placetype":[
        "aat:300008761"
    ]
},
  "bbox": [],
  "geometry": {"coordinates":[-117.95,46.3833],"type":"Point"}
}