<<<<<<< HEAD
{
  "id": 2155678,
  "type": "Feature",
  "properties": {
    "tgn:hierarchy":[
        "tgn:2155678",
        "tgn:1000001",
        "tgn:7012149",
        "tgn:2002039",
        "tgn:7007826",
        "tgn:7029392"
    ],
    "tgn:id":2155678,
    "tgn:name":"Bear Spring Creek",
    "tgn:placetype":[
        "aat:300008706"
    ]
},
  "bbox": [],
  "geometry": {"coordinates":[-99.3167,29.5833],"type":"Point"}
}
=======
{"geometry":{"type":"Point","coordinates":[-99.316700,29.583300]},"type":"Feature","properties":{"hierarchy":["tgn:2155678","tgn:1000001","tgn:7012149","tgn:2002039","tgn:7007826","tgn:7029392"],"placetype":["aat:300008706"],"id":2155678,"name:xx":"Bear Spring Creek"}}
>>>>>>> 03f74aca74312dbeaf24d7e61306dd6a786dc3d0
