{
  "id": 7291935,
  "type": "Feature",
  "properties": {
    "tgn:hierarchy":[
        "tgn:7291935",
        "tgn:1001768",
        "tgn:1000049",
        "tgn:1000002",
        "tgn:7029392"
    ],
    "tgn:id":7291935,
    "tgn:name":"El Peumo",
    "tgn:placetype":[
        "aat:300387200"
    ]
},
  "bbox": [],
  "geometry": {"coordinates":[-71.116667,-32.583333],"type":"Point"}
}