<<<<<<< HEAD
{
  "id": 7482392,
  "type": "Feature",
  "properties": {
    "tgn:hierarchy":[
        "tgn:7482392",
        "tgn:1000004",
        "tgn:7471332",
        "tgn:1000141",
        "tgn:7029392"
    ],
    "tgn:id":7482392,
    "tgn:name":"Nanmayang Shan",
    "tgn:placetype":[
        "aat:300008798"
    ]
},
  "bbox": [],
  "geometry": {"coordinates":[121.278889,24.494722],"type":"Point"}
}
=======
{"geometry":{"type":"Point","coordinates":[121.278889,24.494722]},"type":"Feature","properties":{"hierarchy":["tgn:7482392","tgn:1000004","tgn:7471332","tgn:1000141","tgn:7029392"],"placetype":["aat:300008798"],"id":7482392,"name:xx":"Nanmayang Shan"}}
>>>>>>> 03f74aca74312dbeaf24d7e61306dd6a786dc3d0
