{
  "id": 7482392,
  "type": "Feature",
  "properties": {
    "tgn:hierarchy":[
        "tgn:7482392",
        "tgn:1000004",
        "tgn:7471332",
        "tgn:1000141",
        "tgn:7029392"
    ],
    "tgn:id":7482392,
    "tgn:name":"Nanmayang Shan",
    "tgn:placetype":[
        "aat:300008798"
    ]
},
  "bbox": [],
  "geometry": {"coordinates":[121.278889,24.494722],"type":"Point"}
}