{
  "id": 2542176,
  "type": "Feature",
  "properties": {
    "tgn:hierarchy":[
        "tgn:2542176",
        "tgn:1000001",
        "tgn:2000772",
        "tgn:7012149",
        "tgn:7007255",
        "tgn:7029392"
    ],
    "tgn:id":2542176,
    "tgn:name":"Nix Branch",
    "tgn:placetype":[
        "aat:300008699"
    ]
},
  "bbox": [],
  "geometry": {"coordinates":[-83.2167,37.4833],"type":"Point"}
}