{
  "id": 7579825,
  "type": "Feature",
  "properties": {
    "tgn:hierarchy":[
        "tgn:7579825",
        "tgn:1000004",
        "tgn:1001869",
        "tgn:7000198",
        "tgn:7029392"
    ],
    "tgn:id":7579825,
    "tgn:name:en":"Shinaya",
    "tgn:placetype":[
        "aat:300008347"
    ]
},
  "bbox": [],
  "geometry": {"coordinates":[70.066667,23.05],"type":"Point"}
}