{
  "id": 2335314,
  "type": "Feature",
  "properties": {
    "tgn:hierarchy":[
        "tgn:2335314",
        "tgn:1000001",
        "tgn:7012149",
        "tgn:1002794",
        "tgn:7007708",
        "tgn:7029392"
    ],
    "tgn:id":2335314,
    "tgn:name":"Fort Hill",
    "tgn:placetype":[
        "aat:300008798"
    ]
},
  "bbox": [],
  "geometry": {"coordinates":[-123.55,45.05],"type":"Point"}
}