{
  "id": 1086769,
  "type": "Feature",
  "properties": {
    "tgn:hierarchy":[
        "tgn:1086769",
        "tgn:7016655",
        "tgn:1000004",
        "tgn:7018455",
        "tgn:1000144",
        "tgn:7029392"
    ],
    "tgn:id":1086769,
    "tgn:name":"Pasinler",
    "tgn:placetype":[
        "aat:300008347"
    ]
},
  "bbox": [],
  "geometry": {"coordinates":[41.6833,39.9833],"type":"Point"}
}