{
  "id": 7350183,
  "type": "Feature",
  "properties": {
    "tgn:hierarchy":[
        "tgn:7350183",
        "tgn:7005586",
        "tgn:1000001",
        "tgn:7005560",
        "tgn:7029392"
    ],
    "tgn:id":7350183,
    "tgn:name":"Ahuatl\u00e1n",
    "tgn:placetype":[
        "aat:300008347"
    ]
},
  "bbox": [],
  "geometry": {"coordinates":[-102.866667,20.416667],"type":"Point"}
}