{
  "id": 2410947,
  "type": "Feature",
  "properties": {
    "tgn:hierarchy":[
        "tgn:2410947",
        "tgn:1000001",
        "tgn:7012149",
        "tgn:1002782",
        "tgn:7007710",
        "tgn:7029392"
    ],
    "tgn:id":2410947,
    "tgn:name":"Indian Creek",
    "tgn:placetype":[
        "aat:300008706"
    ]
},
  "bbox": [],
  "geometry": {"coordinates":[-75.25,39.9667],"type":"Point"}
}