{
  "id": 1054581,
  "type": "Feature",
  "properties": {
    "tgn:hierarchy":[
        "tgn:1054581",
        "tgn:1000004",
        "tgn:1003314",
        "tgn:7018214",
        "tgn:7002435",
        "tgn:7029392"
    ],
    "tgn:id":1054581,
    "tgn:name":"Yarkino",
    "tgn:placetype":[
        "aat:300008347"
    ]
},
  "bbox": [],
  "geometry": {"coordinates":[99.45,59.1833],"type":"Point"}
}