{
  "id": 1073740,
  "type": "Feature",
  "properties": {
    "tgn:hierarchy":[
        "tgn:1073740",
        "tgn:1000004",
        "tgn:7001838",
        "tgn:1000111",
        "tgn:7029392"
    ],
    "tgn:id":1073740,
    "tgn:name":"Yuliangpu",
    "tgn:placetype":[
        "aat:300008347"
    ]
},
  "bbox": [],
  "geometry": {"coordinates":[121.9833,43.4167],"type":"Point"}
}