{
  "id": 1104053,
  "type": "Feature",
  "properties": {
    "tgn:hierarchy":[
        "tgn:1104053",
        "tgn:7005694",
        "tgn:7005685",
        "tgn:1000001",
        "tgn:7029392"
    ],
    "tgn:id":1104053,
    "tgn:name":"Brazeau, Mount",
    "tgn:placetype":[
        "aat:300008795"
    ]
},
  "bbox": [],
  "geometry": {"coordinates":[-117.3667,52.5667],"type":"Point"}
}