{
  "id": 2214131,
  "type": "Feature",
  "properties": {
    "tgn:hierarchy":[
        "tgn:2214131",
        "tgn:1000001",
        "tgn:7012149",
        "tgn:7007157",
        "tgn:1002684",
        "tgn:7029392"
    ],
    "tgn:id":2214131,
    "tgn:name":"Cahoon Spring",
    "tgn:placetype":[
        "aat:300008697"
    ]
},
  "bbox": [],
  "geometry": {"coordinates":[-121.55,36.3167],"type":"Point"}
}