<<<<<<< HEAD
{
  "id": 7052579,
  "type": "Feature",
  "properties": {
    "tgn:hierarchy":[
        "tgn:7052579",
        "tgn:1003489",
        "tgn:7004610",
        "tgn:1000003",
        "tgn:1000080",
        "tgn:7029392"
    ],
    "tgn:id":7052579,
    "tgn:name":"Irsi, Monte",
    "tgn:placetype":[
        "aat:300008777"
    ]
},
  "bbox": [],
  "geometry": {"coordinates":[16.316667,40.716667],"type":"Point"}
}
=======
{"geometry":{"type":"Point","coordinates":[16.316667,40.716667]},"type":"Feature","properties":{"hierarchy":["tgn:7052579","tgn:1003489","tgn:7004610","tgn:1000003","tgn:1000080","tgn:7029392"],"placetype":["aat:300008777"],"id":7052579,"name:xx":"Irsi, Monte"}}
>>>>>>> 03f74aca74312dbeaf24d7e61306dd6a786dc3d0
