{
  "id": 2178922,
  "type": "Feature",
  "properties": {
    "tgn:hierarchy":[
        "tgn:2178922",
        "tgn:1000001",
        "tgn:7012149",
        "tgn:1002733",
        "tgn:7007919",
        "tgn:7029392"
    ],
    "tgn:id":2178922,
    "tgn:name":"Blackwells Creek",
    "tgn:placetype":[
        "aat:300008706"
    ]
},
  "bbox": [],
  "geometry": {"coordinates":[-76.3667,37.8833],"type":"Point"}
}