{
  "id": 1074380,
  "type": "Feature",
  "properties": {
    "tgn:hierarchy":[
        "tgn:1074380",
        "tgn:1000004",
        "tgn:7000198",
        "tgn:1001895",
        "tgn:7029392"
    ],
    "tgn:id":1074380,
    "tgn:name":"Akurli",
    "tgn:placetype":[
        "aat:300008347"
    ]
},
  "bbox": [],
  "geometry": {"coordinates":[73.1333,19.0167],"type":"Point"}
}