{
  "id": 7550047,
  "type": "Feature",
  "properties": {
    "tgn:hierarchy":[
        "tgn:7550047",
        "tgn:1000004",
        "tgn:1001869",
        "tgn:7000198",
        "tgn:7029392"
    ],
    "tgn:id":7550047,
    "tgn:name:en":"Dabka",
    "tgn:placetype":[
        "aat:300008347"
    ]
},
  "bbox": [],
  "geometry": {"coordinates":[72.95,22.25],"type":"Point"}
}