{
  "id": 7569637,
  "type": "Feature",
  "properties": {
    "tgn:hierarchy":[
        "tgn:7569637",
        "tgn:1000004",
        "tgn:7000198",
        "tgn:7016788",
        "tgn:7029392"
    ],
    "tgn:id":7569637,
    "tgn:name:en":"M\u016bndghasa",
    "tgn:placetype":[
        "aat:300008347"
    ]
},
  "bbox": [],
  "geometry": {"coordinates":[75.622421,25.558913],"type":"Point"}
}