{
  "id": 7382217,
  "type": "Feature",
  "properties": {
    "tgn:hierarchy":[
        "tgn:7382217",
        "tgn:1000001",
        "tgn:7005597",
        "tgn:7005560",
        "tgn:7029392"
    ],
    "tgn:id":7382217,
    "tgn:name":"Palo Blanco, Arroyo",
    "tgn:placetype":[
        "aat:300008699"
    ]
},
  "bbox": [],
  "geometry": {"coordinates":[-98.716667,24.983333],"type":"Point"}
}