{
  "id": 7035558,
  "type": "Feature",
  "properties": {
    "tgn:hierarchy":[
        "tgn:7035558",
        "tgn:7002991",
        "tgn:1000003",
        "tgn:7002997",
        "tgn:1000080",
        "tgn:7029392"
    ],
    "tgn:id":7035558,
    "tgn:name":"Sparlonga, Col della",
    "tgn:placetype":[
        "aat:300008795"
    ]
},
  "bbox": [],
  "geometry": {"coordinates":[12.233611,46.253611],"type":"Point"}
}