{
  "id": 2709923,
  "type": "Feature",
  "properties": {
    "tgn:hierarchy":[
        "tgn:2709923",
        "tgn:7006450",
        "tgn:1000001",
        "tgn:7012149",
        "tgn:7019760",
        "tgn:7029392"
    ],
    "tgn:id":2709923,
    "tgn:name":"Takanis Peninsula",
    "tgn:placetype":[
        "aat:300008850"
    ]
},
  "bbox": [],
  "geometry": {"coordinates":[-136.5333,57.9167],"type":"Point"}
}