{
  "id": 2370366,
  "type": "Feature",
  "properties": {
    "tgn:hierarchy":[
        "tgn:2370366",
        "tgn:1000001",
        "tgn:7012149",
        "tgn:2001288",
        "tgn:7007524",
        "tgn:7029392"
    ],
    "tgn:id":2370366,
    "tgn:name":"H Lazy Ditch",
    "tgn:placetype":[
        "aat:300006075"
    ]
},
  "bbox": [],
  "geometry": {"coordinates":[-111.6167,45.35],"type":"Point"}
}