<<<<<<< HEAD
{
  "id": 2159622,
  "type": "Feature",
  "properties": {
    "tgn:hierarchy":[
        "tgn:2159622",
        "tgn:1000001",
        "tgn:7012149",
        "tgn:2001918",
        "tgn:7007825",
        "tgn:7029392"
    ],
    "tgn:id":2159622,
    "tgn:name":"Bee Suck Branch",
    "tgn:placetype":[
        "aat:300008699"
    ]
},
  "bbox": [],
  "geometry": {"coordinates":[-81.9667,36.5833],"type":"Point"}
}
=======
{"geometry":{"type":"Point","coordinates":[-81.966700,36.583300]},"type":"Feature","properties":{"hierarchy":["tgn:2159622","tgn:1000001","tgn:7012149","tgn:2001918","tgn:7007825","tgn:7029392"],"placetype":["aat:300008699"],"id":2159622,"name:xx":"Bee Suck Branch"}}
>>>>>>> 03f74aca74312dbeaf24d7e61306dd6a786dc3d0
