{
  "id": 7176016,
  "type": "Feature",
  "properties": {
    "tgn:hierarchy":[
        "tgn:7176016",
        "tgn:7003669",
        "tgn:1000003",
        "tgn:7000084",
        "tgn:7029392"
    ],
    "tgn:id":7176016,
    "tgn:name":"Greuth",
    "tgn:placetype":[
        "aat:300000206"
    ]
},
  "bbox": [],
  "geometry": {"coordinates":[10.35,47.65],"type":"Point"}
}