{
  "id": 1090208,
  "type": "Feature",
  "properties": {
    "tgn:hierarchy":[
        "tgn:1090208",
        "tgn:7001242",
        "tgn:1001722",
        "tgn:1000166",
        "tgn:7029392"
    ],
    "tgn:id":1090208,
    "tgn:name":"Yapei",
    "tgn:placetype":[
        "aat:300008347"
    ]
},
  "bbox": [],
  "geometry": {"coordinates":[-1.1667,9.1667],"type":"Point"}
}