{
  "id": 2719661,
  "type": "Feature",
  "properties": {
    "tgn:hierarchy":[
        "tgn:2719661",
        "tgn:1000001",
        "tgn:7012149",
        "tgn:2002337",
        "tgn:7007922",
        "tgn:7029392"
    ],
    "tgn:id":2719661,
    "tgn:name":"Three Little Lakes",
    "tgn:placetype":[
        "aat:300008680"
    ]
},
  "bbox": [],
  "geometry": {"coordinates":[-88.35,45.3833],"type":"Point"}
}