{
  "id": 2545217,
  "type": "Feature",
  "properties": {
    "tgn:hierarchy":[
        "tgn:2545217",
        "tgn:1000001",
        "tgn:2002368",
        "tgn:7012149",
        "tgn:7007923",
        "tgn:7029392"
    ],
    "tgn:id":2545217,
    "tgn:name":"North Flat Top",
    "tgn:placetype":[
        "aat:300008798"
    ]
},
  "bbox": [],
  "geometry": {"coordinates":[-107.8333,41.2167],"type":"Point"}
}