{
  "id": 7504701,
  "type": "Feature",
  "properties": {
    "tgn:hierarchy":[
        "tgn:7504701",
        "tgn:7000508",
        "tgn:1008380",
        "tgn:1000226",
        "tgn:1000006",
        "tgn:7029392"
    ],
    "tgn:id":7504701,
    "tgn:name:en":"East Bastion Reef",
    "tgn:placetype":[
        "aat:300008808"
    ]
},
  "bbox": [],
  "geometry": {"coordinates":[174.852222,-36.841111],"type":"Point"}
}