{
  "id": 2154342,
  "type": "Feature",
  "properties": {
    "tgn:hierarchy":[
        "tgn:2154342",
        "tgn:1000001",
        "tgn:7012149",
        "tgn:1002378",
        "tgn:7007710",
        "tgn:7029392"
    ],
    "tgn:id":2154342,
    "tgn:name":"Bear Creek",
    "tgn:placetype":[
        "aat:300008706"
    ]
},
  "bbox": [],
  "geometry": {"coordinates":[-79.2333,41.4833],"type":"Point"}
}