<<<<<<< HEAD
{
  "id": 2154342,
  "type": "Feature",
  "properties": {
    "tgn:hierarchy":[
        "tgn:2154342",
        "tgn:1000001",
        "tgn:7012149",
        "tgn:1002378",
        "tgn:7007710",
        "tgn:7029392"
    ],
    "tgn:id":2154342,
    "tgn:name":"Bear Creek",
    "tgn:placetype":[
        "aat:300008706"
    ]
},
  "bbox": [],
  "geometry": {"coordinates":[-79.2333,41.4833],"type":"Point"}
}
=======
{"geometry":{"type":"Point","coordinates":[-79.233300,41.483300]},"type":"Feature","properties":{"hierarchy":["tgn:2154342","tgn:1000001","tgn:7012149","tgn:1002378","tgn:7007710","tgn:7029392"],"placetype":["aat:300008706"],"id":2154342,"name:xx":"Bear Creek"}}
>>>>>>> 03f74aca74312dbeaf24d7e61306dd6a786dc3d0
