{
  "id": 7415362,
  "type": "Feature",
  "properties": {
    "tgn:hierarchy":[
        "tgn:7415362",
        "tgn:7005584",
        "tgn:1000001",
        "tgn:7005560",
        "tgn:7029392"
    ],
    "tgn:id":7415362,
    "tgn:name":"La Silla",
    "tgn:placetype":[
        "aat:300008347"
    ]
},
  "bbox": [],
  "geometry": {"coordinates":[-100.137222,21.023333],"type":"Point"}
}