{
  "id": 2372841,
  "type": "Feature",
  "properties": {
    "tgn:hierarchy":[
        "tgn:2372841",
        "tgn:1000001",
        "tgn:7012149",
        "tgn:7014510",
        "tgn:7007920",
        "tgn:7029392"
    ],
    "tgn:id":2372841,
    "tgn:name":"Hall Slough",
    "tgn:placetype":[
        "aat:300008699"
    ]
},
  "bbox": [],
  "geometry": {"coordinates":[-122.4167,48.3333],"type":"Point"}
}