{
  "id": 2675742,
  "type": "Feature",
  "properties": {
    "tgn:hierarchy":[
        "tgn:2675742",
        "tgn:1000001",
        "tgn:7012149",
        "tgn:1002547",
        "tgn:7007919",
        "tgn:7029392"
    ],
    "tgn:id":2675742,
    "tgn:name":"Somerset Beach",
    "tgn:placetype":[
        "aat:300008347"
    ]
},
  "bbox": [],
  "geometry": {"coordinates":[-77.1833,38.3333],"type":"Point"}
}