<<<<<<< HEAD
{
  "id": 7021614,
  "type": "Feature",
  "properties": {
    "tgn:hierarchy":[
        "tgn:7021614",
        "tgn:1000001",
        "tgn:7012149",
        "tgn:2001977",
        "tgn:7007826",
        "tgn:7029392"
    ],
    "tgn:id":7021614,
    "tgn:name":"Concepcion",
    "tgn:placetype":[
        "aat:300008347"
    ]
},
  "bbox": [],
  "geometry": {"coordinates":[-98.35,27.3833],"type":"Point"}
}
=======
{"geometry":{"type":"Point","coordinates":[-98.350000,27.383300]},"type":"Feature","properties":{"hierarchy":["tgn:7021614","tgn:1000001","tgn:7012149","tgn:2001977","tgn:7007826","tgn:7029392"],"placetype":["aat:300008347"],"id":7021614,"name:xx":"Concepcion"}}
>>>>>>> 03f74aca74312dbeaf24d7e61306dd6a786dc3d0
