{
  "id": 1074890,
  "type": "Feature",
  "properties": {
    "tgn:hierarchy":[
        "tgn:1074890",
        "tgn:1000004",
        "tgn:7000198",
        "tgn:1001977",
        "tgn:7029392"
    ],
    "tgn:id":1074890,
    "tgn:name:en":"Barddham\u0101n",
    "tgn:placetype":[
        "aat:300008347"
    ]
},
  "bbox": [],
  "geometry": {"coordinates":[87.856906,23.255716],"type":"Point"}
}