{
  "id": 7287597,
  "type": "Feature",
  "properties": {
    "tgn:hierarchy":[
        "tgn:7287597",
        "tgn:1001657",
        "tgn:1000049",
        "tgn:1000002",
        "tgn:7029392"
    ],
    "tgn:id":7287597,
    "tgn:name":"La Engorda",
    "tgn:placetype":[
        "aat:300387200"
    ]
},
  "bbox": [],
  "geometry": {"coordinates":[-71.033333,-30.433333],"type":"Point"}
}