{
  "id": 7229921,
  "type": "Feature",
  "properties": {
    "tgn:hierarchy":[
        "tgn:7229921",
        "tgn:7002715",
        "tgn:7002731",
        "tgn:1000003",
        "tgn:1000074",
        "tgn:7029392"
    ],
    "tgn:id":7229921,
    "tgn:name":"Meg\u00e1lo \u00c9mvolo, \u00c1kra",
    "tgn:placetype":[
        "aat:300008850"
    ]
},
  "bbox": [],
  "geometry": {"coordinates":[22.816475,40.501828],"type":"Point"}
}