{
  "id": 2725325,
  "type": "Feature",
  "properties": {
    "tgn:hierarchy":[
        "tgn:2725325",
        "tgn:1000001",
        "tgn:2001331",
        "tgn:7012149",
        "tgn:7007525",
        "tgn:7029392"
    ],
    "tgn:id":2725325,
    "tgn:name":"Tony Lake",
    "tgn:placetype":[
        "aat:300008680"
    ]
},
  "bbox": [],
  "geometry": {"coordinates":[-101.9333,42.25],"type":"Point"}
}