<<<<<<< HEAD
{
  "id": 7375174,
  "type": "Feature",
  "properties": {
    "tgn:hierarchy":[
        "tgn:7375174",
        "tgn:1001835",
        "tgn:1000001",
        "tgn:7005560",
        "tgn:7029392"
    ],
    "tgn:id":7375174,
    "tgn:name":"Las Pinitas, Cerro",
    "tgn:placetype":[
        "aat:300008795"
    ]
},
  "bbox": [],
  "geometry": {"coordinates":[-116.3,31.266667],"type":"Point"}
}
=======
{"geometry":{"type":"Point","coordinates":[-116.300000,31.266667]},"type":"Feature","properties":{"hierarchy":["tgn:7375174","tgn:1001835","tgn:1000001","tgn:7005560","tgn:7029392"],"placetype":["aat:300008795"],"id":7375174,"name:xx":"Las Pinitas, Cerro"}}
>>>>>>> 03f74aca74312dbeaf24d7e61306dd6a786dc3d0
