{
  "id": 7255248,
  "type": "Feature",
  "properties": {
    "tgn:hierarchy":[
        "tgn:7255248",
        "tgn:7003460",
        "tgn:1000003",
        "tgn:1000063",
        "tgn:4012014",
        "tgn:7029392"
    ],
    "tgn:id":7255248,
    "tgn:name":"Reuland, Bois de",
    "tgn:placetype":[
        "aat:300008863"
    ]
},
  "bbox": [],
  "geometry": {"coordinates":[5.994444,50.333056],"type":"Point"}
}