{
  "id": 2260047,
  "type": "Feature",
  "properties": {
    "tgn:hierarchy":[
        "tgn:2260047",
        "tgn:1000001",
        "tgn:7012149",
        "tgn:2000401",
        "tgn:7007248",
        "tgn:7029392"
    ],
    "tgn:id":2260047,
    "tgn:name":"Country Acres",
    "tgn:placetype":[
        "aat:300008347"
    ]
},
  "bbox": [],
  "geometry": {"coordinates":[-84.7833,33.95],"type":"Point"}
}