{
  "id": 2190832,
  "type": "Feature",
  "properties": {
    "tgn:hierarchy":[
        "tgn:2190832",
        "tgn:1000001",
        "tgn:7012149",
        "tgn:2001516",
        "tgn:7007709",
        "tgn:7029392"
    ],
    "tgn:id":2190832,
    "tgn:name":"Boyd Branch",
    "tgn:placetype":[
        "aat:300008699"
    ]
},
  "bbox": [],
  "geometry": {"coordinates":[-82.7333,35.7333],"type":"Point"}
}