{
  "id": 2399437,
  "type": "Feature",
  "properties": {
    "tgn:hierarchy":[
        "tgn:2399437",
        "tgn:1000001",
        "tgn:2002135",
        "tgn:7012149",
        "tgn:7007828",
        "tgn:7029392"
    ],
    "tgn:id":2399437,
    "tgn:name":"Horn of the Moon Pond",
    "tgn:placetype":[
        "aat:300008680"
    ]
},
  "bbox": [],
  "geometry": {"coordinates":[-72.5333,44.3167],"type":"Point"}
}