{
  "id": 7559897,
  "type": "Feature",
  "properties": {
    "tgn:hierarchy":[
        "tgn:7559897",
        "tgn:1000004",
        "tgn:7000198",
        "tgn:7016722",
        "tgn:7029392"
    ],
    "tgn:id":7559897,
    "tgn:name:en":"Karhori ka Nagla",
    "tgn:placetype":[
        "aat:300008347"
    ]
},
  "bbox": [],
  "geometry": {"coordinates":[79.126815,26.983268],"type":"Point"}
}