{
  "id": 7436190,
  "type": "Feature",
  "properties": {
    "tgn:hierarchy":[
        "tgn:7436190",
        "tgn:7005581",
        "tgn:1000001",
        "tgn:7005560",
        "tgn:7029392"
    ],
    "tgn:id":7436190,
    "tgn:name":"Terrero",
    "tgn:placetype":[
        "aat:300008347"
    ]
},
  "bbox": [],
  "geometry": {"coordinates":[-107.433333,28.25],"type":"Point"}
}