{
  "id": 2163257,
  "type": "Feature",
  "properties": {
    "tgn:hierarchy":[
        "tgn:2163257",
        "tgn:1000001",
        "tgn:7012149",
        "tgn:1002920",
        "tgn:7007568",
        "tgn:7029392"
    ],
    "tgn:id":2163257,
    "tgn:name":"Bennetts",
    "tgn:placetype":[
        "aat:300008347"
    ]
},
  "bbox": [],
  "geometry": {"coordinates":[-77.6167,42.1833],"type":"Point"}
}