{
  "id": 1033005,
  "type": "Feature",
  "properties": {
    "tgn:hierarchy":[
        "tgn:1033005",
        "tgn:1000003",
        "tgn:7002888",
        "tgn:1000070",
        "tgn:7029392"
    ],
    "tgn:id":1033005,
    "tgn:name":"Einville",
    "tgn:placetype":[
        "aat:300008347"
    ]
},
  "bbox": [],
  "geometry": {"coordinates":[6.4833,48.6667],"type":"Point"}
}