{
  "id": 7449912,
  "type": "Feature",
  "properties": {
    "tgn:hierarchy":[
        "tgn:7449912",
        "tgn:7002444",
        "tgn:1000003",
        "tgn:7019097",
        "tgn:7008591",
        "tgn:7029392"
    ],
    "tgn:id":7449912,
    "tgn:name:en":"Finnieston",
    "tgn:placetype":[
        "aat:300000745"
    ]
},
  "bbox": [],
  "geometry": {"coordinates":[-4.283333,55.85],"type":"Point"}
}