{
  "id": 2158687,
  "type": "Feature",
  "properties": {
    "tgn:hierarchy":[
        "tgn:2158687",
        "tgn:1000001",
        "tgn:1003028",
        "tgn:7012149",
        "tgn:7007159",
        "tgn:7029392"
    ],
    "tgn:id":2158687,
    "tgn:name":"Bebbington Brook",
    "tgn:placetype":[
        "aat:300008699"
    ]
},
  "bbox": [],
  "geometry": {"coordinates":[-72.1167,41.85],"type":"Point"}
}