{
  "id": 2260248,
  "type": "Feature",
  "properties": {
    "tgn:hierarchy":[
        "tgn:2260248",
        "tgn:1000001",
        "tgn:7012149",
        "tgn:2002118",
        "tgn:7007827",
        "tgn:7029392"
    ],
    "tgn:id":2260248,
    "tgn:name":"Country Squire Estates",
    "tgn:placetype":[
        "aat:300008347"
    ]
},
  "bbox": [],
  "geometry": {"coordinates":[-111.95,40.6667],"type":"Point"}
}