{
  "id": 7519054,
  "type": "Feature",
  "properties": {
    "tgn:hierarchy":[
        "tgn:7519054",
        "tgn:7000508",
        "tgn:1008380",
        "tgn:1000226",
        "tgn:1000006",
        "tgn:7029392"
    ],
    "tgn:id":7519054,
    "tgn:name:en":"Browns Bay",
    "tgn:placetype":[
        "aat:300008347"
    ]
},
  "bbox": [],
  "geometry": {"coordinates":[174.75,-36.716667],"type":"Point"}
}