{
  "id": 2459472,
  "type": "Feature",
  "properties": {
    "tgn:hierarchy":[
        "tgn:2459472",
        "tgn:7002659",
        "tgn:1000001",
        "tgn:7012149",
        "tgn:2000052",
        "tgn:7029392"
    ],
    "tgn:id":2459472,
    "tgn:name":"Little Pryor Creek",
    "tgn:placetype":[
        "aat:300008706"
    ]
},
  "bbox": [],
  "geometry": {"coordinates":[-87.0333,32.7333],"type":"Point"}
}