{
  "id": 2629588,
  "type": "Feature",
  "properties": {
    "tgn:hierarchy":[
        "tgn:2629588",
        "tgn:1000001",
        "tgn:2002107",
        "tgn:7012149",
        "tgn:7007827",
        "tgn:7029392"
    ],
    "tgn:id":2629588,
    "tgn:name":"Rosie Hollow",
    "tgn:placetype":[
        "aat:300008761"
    ]
},
  "bbox": [],
  "geometry": {"coordinates":[-110.65,40.0167],"type":"Point"}
}