<<<<<<< HEAD
{
  "id": 2764078,
  "type": "Feature",
  "properties": {
    "tgn:hierarchy":[
        "tgn:2764078",
        "tgn:1000001",
        "tgn:7012149",
        "tgn:7007157",
        "tgn:7014004",
        "tgn:7029392"
    ],
    "tgn:id":2764078,
    "tgn:name":"Wheeler Gulch",
    "tgn:placetype":[
        "aat:300008761"
    ]
},
  "bbox": [],
  "geometry": {"coordinates":[-120.2333,37.7167],"type":"Point"}
}
=======
{"geometry":{"type":"Point","coordinates":[-120.233300,37.716700]},"type":"Feature","properties":{"hierarchy":["tgn:2764078","tgn:1000001","tgn:7012149","tgn:7007157","tgn:7014004","tgn:7029392"],"placetype":["aat:300008761"],"id":2764078,"name:xx":"Wheeler Gulch"}}
>>>>>>> 03f74aca74312dbeaf24d7e61306dd6a786dc3d0
