{
  "id": 2764078,
  "type": "Feature",
  "properties": {
    "tgn:hierarchy":[
        "tgn:2764078",
        "tgn:1000001",
        "tgn:7012149",
        "tgn:7007157",
        "tgn:7014004",
        "tgn:7029392"
    ],
    "tgn:id":2764078,
    "tgn:name":"Wheeler Gulch",
    "tgn:placetype":[
        "aat:300008761"
    ]
},
  "bbox": [],
  "geometry": {"coordinates":[-120.2333,37.7167],"type":"Point"}
}