{
  "id": 7015491,
  "type": "Feature",
  "properties": {
    "tgn:hierarchy":[
        "tgn:7015491",
        "tgn:1000003",
        "tgn:4011927",
        "tgn:7006669",
        "tgn:7029392"
    ],
    "tgn:id":7015491,
    "tgn:name":"Sremska Mitrovica",
    "tgn:placetype":[
        "aat:300008347",
        "aat:300008389",
        "aat:300387512",
        "aat:300387316",
        "aat:300387235",
        "aat:300008375",
        "aat:300120599"
    ]
},
  "bbox": [],
  "geometry": {"coordinates":[19.65,44.9833],"type":"Point"}
}