{
  "id": 7477643,
  "type": "Feature",
  "properties": {
    "tgn:hierarchy":[
        "tgn:7477643",
        "tgn:7488858",
        "tgn:1000004",
        "tgn:1000141",
        "tgn:7029392"
    ],
    "tgn:id":7477643,
    "tgn:name":"Zhongming Qiao",
    "tgn:placetype":[
        "aat:300007836"
    ]
},
  "bbox": [],
  "geometry": {"coordinates":[120.922474,23.884827],"type":"Point"}
}