{
  "id": 7048138,
  "type": "Feature",
  "properties": {
    "tgn:hierarchy":[
        "tgn:7048138",
        "tgn:7005869",
        "tgn:1000003",
        "tgn:7003237",
        "tgn:1000080",
        "tgn:7029392"
    ],
    "tgn:id":7048138,
    "tgn:name":"Casalsigone",
    "tgn:placetype":[
        "aat:300008347"
    ]
},
  "bbox": [],
  "geometry": {"coordinates":[10.016667,45.216667],"type":"Point"}
}