{
  "id": 7130027,
  "type": "Feature",
  "properties": {
    "tgn:hierarchy":[
        "tgn:7130027",
        "tgn:1000003",
        "tgn:7003678",
        "tgn:7000084",
        "tgn:7029392"
    ],
    "tgn:id":7130027,
    "tgn:name":"Michelbach",
    "tgn:placetype":[
        "aat:300008347"
    ]
},
  "bbox": [],
  "geometry": {"coordinates":[8.85,49.733333],"type":"Point"}
}