{
  "id": 2218147,
  "type": "Feature",
  "properties": {
    "tgn:hierarchy":[
        "tgn:2218147",
        "tgn:1000001",
        "tgn:7012149",
        "tgn:2001684",
        "tgn:7007707",
        "tgn:7029392"
    ],
    "tgn:id":2218147,
    "tgn:name":"Canadian Sandy Creek",
    "tgn:placetype":[
        "aat:300008706"
    ]
},
  "bbox": [],
  "geometry": {"coordinates":[-96.8167,34.65],"type":"Point"}
}