{
  "id": 2554205,
  "type": "Feature",
  "properties": {
    "tgn:hierarchy":[
        "tgn:2554205",
        "tgn:1000001",
        "tgn:2002109",
        "tgn:7012149",
        "tgn:7007827",
        "tgn:7029392"
    ],
    "tgn:id":2554205,
    "tgn:name":"Oak Spring",
    "tgn:placetype":[
        "aat:300008697"
    ]
},
  "bbox": [],
  "geometry": {"coordinates":[-111.6167,37.6667],"type":"Point"}
}