{
  "id": 2036638,
  "type": "Feature",
  "properties": {
    "tgn:hierarchy":[
        "tgn:2036638",
        "tgn:1000001",
        "tgn:7012149",
        "tgn:2000727",
        "tgn:7007254",
        "tgn:7029392"
    ],
    "tgn:id":2036638,
    "tgn:name":"Laird",
    "tgn:placetype":[
        "aat:300387016"
    ]
},
  "bbox": [],
  "geometry": {"coordinates":[-100.05,38.4333],"type":"Point"}
}