{
  "id": 7270593,
  "type": "Feature",
  "properties": {
    "tgn:concordances":{
        "gn:id":"2748325"
    },
    "tgn:hierarchy":[
        "tgn:7270593",
        "tgn:1000003",
        "tgn:7003626",
        "tgn:7016845",
        "tgn:7029392"
    ],
    "tgn:id":7270593,
    "tgn:name:nl":"Ranserveen",
    "tgn:placetype":[
        "aat:300008347"
    ]
},
  "bbox": [],
  "geometry": {"coordinates":[6.283333,52.566667],"type":"Point"}
}