<<<<<<< HEAD
{
  "id": 2333068,
  "type": "Feature",
  "properties": {
    "tgn:hierarchy":[
        "tgn:2333068",
        "tgn:1000001",
        "tgn:7012149",
        "tgn:2001293",
        "tgn:7007524",
        "tgn:7029392"
    ],
    "tgn:id":2333068,
    "tgn:name":"Fly Lake",
    "tgn:placetype":[
        "aat:300008680"
    ]
},
  "bbox": [],
  "geometry": {"coordinates":[-109.9667,45.1167],"type":"Point"}
}
=======
{"geometry":{"type":"Point","coordinates":[-109.966700,45.116700]},"type":"Feature","properties":{"hierarchy":["tgn:2333068","tgn:1000001","tgn:7012149","tgn:2001293","tgn:7007524","tgn:7029392"],"placetype":["aat:300008680"],"id":2333068,"name:xx":"Fly Lake"}}
>>>>>>> 03f74aca74312dbeaf24d7e61306dd6a786dc3d0
