{
  "id": 2771560,
  "type": "Feature",
  "properties": {
    "tgn:hierarchy":[
        "tgn:2771560",
        "tgn:1000001",
        "tgn:7012149",
        "tgn:2001295",
        "tgn:7007524",
        "tgn:7029392"
    ],
    "tgn:id":2771560,
    "tgn:name":"Wildlife Reservoir",
    "tgn:placetype":[
        "aat:300006191"
    ]
},
  "bbox": [],
  "geometry": {"coordinates":[-108.1667,47.6333],"type":"Point"}
}