{
  "id": 2369012,
  "type": "Feature",
  "properties": {
    "tgn:hierarchy":[
        "tgn:2369012",
        "tgn:1000001",
        "tgn:7012149",
        "tgn:7007826",
        "tgn:7029392"
    ],
    "tgn:id":2369012,
    "tgn:name":"Gum Branch",
    "tgn:placetype":[
        "aat:300008699"
    ]
},
  "bbox": [],
  "geometry": {"coordinates":[-95.5167,30.55],"type":"Point"}
}