{
  "id": 1078589,
  "type": "Feature",
  "properties": {
    "tgn:hierarchy":[
        "tgn:1078589",
        "tgn:1000004",
        "tgn:1001336",
        "tgn:1000116",
        "tgn:7029392"
    ],
    "tgn:id":1078589,
    "tgn:name":"Singkawang",
    "tgn:placetype":[
        "aat:300008347"
    ]
},
  "bbox": [],
  "geometry": {"coordinates":[108.95,0.95],"type":"Point"}
}