{
  "id": 2262908,
  "type": "Feature",
  "properties": {
    "tgn:hierarchy":[
        "tgn:2262908",
        "tgn:1000001",
        "tgn:2000458",
        "tgn:7012149",
        "tgn:7007250",
        "tgn:7029392"
    ],
    "tgn:id":2262908,
    "tgn:name":"Cowcatcher Ridge",
    "tgn:placetype":[
        "aat:300266640"
    ]
},
  "bbox": [],
  "geometry": {"coordinates":[-114.25,43.4667],"type":"Point"}
}