{
  "id": 2552228,
  "type": "Feature",
  "properties": {
    "tgn:hierarchy":[
        "tgn:2552228",
        "tgn:1000001",
        "tgn:7012149",
        "tgn:2001885",
        "tgn:7007825",
        "tgn:7029392"
    ],
    "tgn:id":2552228,
    "tgn:name":"Number Six, Island",
    "tgn:placetype":[
        "aat:300008791"
    ]
},
  "bbox": [],
  "geometry": {"coordinates":[-89.3333,35.8667],"type":"Point"}
}