<<<<<<< HEAD
{
  "id": 2159027,
  "type": "Feature",
  "properties": {
    "tgn:hierarchy":[
        "tgn:2159027",
        "tgn:1000001",
        "tgn:7012149",
        "tgn:2000930",
        "tgn:7007515",
        "tgn:7029392"
    ],
    "tgn:id":2159027,
    "tgn:name":"Becky Inlet",
    "tgn:placetype":[
        "aat:300008699"
    ]
},
  "bbox": [],
  "geometry": {"coordinates":[-70.3667,45.2667],"type":"Point"}
}
=======
{"geometry":{"type":"Point","coordinates":[-70.366700,45.266700]},"type":"Feature","properties":{"hierarchy":["tgn:2159027","tgn:1000001","tgn:7012149","tgn:2000930","tgn:7007515","tgn:7029392"],"placetype":["aat:300008699"],"id":2159027,"name:xx":"Becky Inlet"}}
>>>>>>> 03f74aca74312dbeaf24d7e61306dd6a786dc3d0
