{
  "id": 2352649,
  "type": "Feature",
  "properties": {
    "tgn:hierarchy":[
        "tgn:2352649",
        "tgn:1000001",
        "tgn:7012149",
        "tgn:7007157",
        "tgn:1002710",
        "tgn:7029392"
    ],
    "tgn:id":2352649,
    "tgn:name":"Goat Rock",
    "tgn:placetype":[
        "aat:300008798"
    ]
},
  "bbox": [],
  "geometry": {"coordinates":[-120.9833,39.1333],"type":"Point"}
}