{
  "id": 2083717,
  "type": "Feature",
  "properties": {
    "tgn:hierarchy":[
        "tgn:2083717",
        "tgn:1000001",
        "tgn:2001632",
        "tgn:7012149",
        "tgn:7007707",
        "tgn:7029392"
    ],
    "tgn:id":2083717,
    "tgn:name":"Oil City",
    "tgn:placetype":[
        "aat:300008347",
        "aat:300387210"
    ]
},
  "bbox": [],
  "geometry": {"coordinates":[-97.4167,34.2667],"type":"Point"}
}