{
  "id": 7333114,
  "type": "Feature",
  "properties": {
    "tgn:hierarchy":[
        "tgn:7333114",
        "tgn:7002844",
        "tgn:7030216",
        "tgn:1000003",
        "tgn:1000095",
        "tgn:7029392"
    ],
    "tgn:id":7333114,
    "tgn:name":"La Mas\u00f3",
    "tgn:placetype":[
        "aat:300008347"
    ]
},
  "bbox": [],
  "geometry": {"coordinates":[1.216667,41.233333],"type":"Point"}
}