{
  "id": 2746835,
  "type": "Feature",
  "properties": {
    "tgn:hierarchy":[
        "tgn:2746835",
        "tgn:2000192",
        "tgn:1000001",
        "tgn:7012149",
        "tgn:7007158",
        "tgn:7029392"
    ],
    "tgn:id":2746835,
    "tgn:name":"Wadley Reservoir Number 2",
    "tgn:placetype":[
        "aat:300006191"
    ]
},
  "bbox": [],
  "geometry": {"coordinates":[-104.95,39.95],"type":"Point"}
}