{
  "id": 2173753,
  "type": "Feature",
  "properties": {
    "tgn:hierarchy":[
        "tgn:2173753",
        "tgn:1000001",
        "tgn:2001842",
        "tgn:7012149",
        "tgn:7007825",
        "tgn:7029392"
    ],
    "tgn:id":2173753,
    "tgn:name":"Bird Branch",
    "tgn:placetype":[
        "aat:300008699"
    ]
},
  "bbox": [],
  "geometry": {"coordinates":[-84.7667,35.0667],"type":"Point"}
}