<<<<<<< HEAD
{
  "id": 2336727,
  "type": "Feature",
  "properties": {
    "tgn:hierarchy":[
        "tgn:2336727",
        "tgn:1000001",
        "tgn:7016172",
        "tgn:7012149",
        "tgn:7029392"
    ],
    "tgn:id":2336727,
    "tgn:name":"Fourche Lafave River",
    "tgn:placetype":[
        "aat:300008707"
    ]
},
  "bbox": [],
  "geometry": {"coordinates":[-94.15,34.7667],"type":"Point"}
}
=======
{"geometry":{"type":"Point","coordinates":[-94.150000,34.766700]},"type":"Feature","properties":{"hierarchy":["tgn:2336727","tgn:1000001","tgn:7016172","tgn:7012149","tgn:7029392"],"placetype":["aat:300008707"],"id":2336727,"name:xx":"Fourche Lafave River"}}
>>>>>>> 03f74aca74312dbeaf24d7e61306dd6a786dc3d0
