{
  "id": 2483503,
  "type": "Feature",
  "properties": {
    "tgn:hierarchy":[
        "tgn:2483503",
        "tgn:1000001",
        "tgn:7012149",
        "tgn:2000233",
        "tgn:7007158",
        "tgn:7029392"
    ],
    "tgn:id":2483503,
    "tgn:name":"Last Chance Reservoir",
    "tgn:placetype":[
        "aat:300006191"
    ]
},
  "bbox": [],
  "geometry": {"coordinates":[-108.0833,37.5833],"type":"Point"}
}