{
  "id": 2239194,
  "type": "Feature",
  "properties": {
    "tgn:hierarchy":[
        "tgn:2239194",
        "tgn:1000001",
        "tgn:2001418",
        "tgn:7012149",
        "tgn:7007526",
        "tgn:7029392"
    ],
    "tgn:id":2239194,
    "tgn:name":"Chuckwalla Canyon",
    "tgn:placetype":[
        "aat:300008761"
    ]
},
  "bbox": [],
  "geometry": {"coordinates":[-116.6667,36.8333],"type":"Point"}
}