{
  "id": 2662795,
  "type": "Feature",
  "properties": {
    "tgn:hierarchy":[
        "tgn:2662795",
        "tgn:1000001",
        "tgn:7012149",
        "tgn:2001714",
        "tgn:7007708",
        "tgn:7029392"
    ],
    "tgn:id":2662795,
    "tgn:name":"Silent Creek",
    "tgn:placetype":[
        "aat:300008706"
    ]
},
  "bbox": [],
  "geometry": {"coordinates":[-121.9833,42.9833],"type":"Point"}
}