{
  "id": 2271816,
  "type": "Feature",
  "properties": {
    "tgn:hierarchy":[
        "tgn:2271816",
        "tgn:1000001",
        "tgn:2001178",
        "tgn:7012149",
        "tgn:7007523",
        "tgn:7029392"
    ],
    "tgn:id":2271816,
    "tgn:name":"Cunningham Hollow",
    "tgn:placetype":[
        "aat:300008761"
    ]
},
  "bbox": [],
  "geometry": {"coordinates":[-92.85,38.0833],"type":"Point"}
}