{
  "id": 7568172,
  "type": "Feature",
  "properties": {
    "tgn:hierarchy":[
        "tgn:7568172",
        "tgn:1001828",
        "tgn:1000004",
        "tgn:7000198",
        "tgn:7029392"
    ],
    "tgn:id":7568172,
    "tgn:name:en":"Gundla Pochampalli",
    "tgn:placetype":[
        "aat:300008347"
    ]
},
  "bbox": [],
  "geometry": {"coordinates":[78.479444,17.568333],"type":"Point"}
}