{
  "id": 2195175,
  "type": "Feature",
  "properties": {
    "tgn:hierarchy":[
        "tgn:2195175",
        "tgn:7002659",
        "tgn:1000001",
        "tgn:7012149",
        "tgn:2000051",
        "tgn:7029392"
    ],
    "tgn:id":2195175,
    "tgn:name":"Brindley Hollow Spring",
    "tgn:placetype":[
        "aat:300008697"
    ]
},
  "bbox": [],
  "geometry": {"coordinates":[-86.7833,34.4167],"type":"Point"}
}