{
  "id": 7348996,
  "type": "Feature",
  "properties": {
    "tgn:hierarchy":[
        "tgn:7348996",
        "tgn:7005581",
        "tgn:1000001",
        "tgn:7005560",
        "tgn:7029392"
    ],
    "tgn:id":7348996,
    "tgn:name":"Alascaderos",
    "tgn:placetype":[
        "aat:300008347"
    ]
},
  "bbox": [],
  "geometry": {"coordinates":[-106.916667,25.916667],"type":"Point"}
}