<<<<<<< HEAD
{
  "id": 7171298,
  "type": "Feature",
  "properties": {
    "tgn:hierarchy":[
        "tgn:7171298",
        "tgn:7003692",
        "tgn:1000003",
        "tgn:7000084",
        "tgn:7029392"
    ],
    "tgn:id":7171298,
    "tgn:name":"Hirschb\u00fchl",
    "tgn:placetype":[
        "aat:300000206"
    ]
},
  "bbox": [],
  "geometry": {"coordinates":[8.433333,48.2],"type":"Point"}
}
=======
{"geometry":{"type":"Point","coordinates":[8.433333,48.200000]},"type":"Feature","properties":{"hierarchy":["tgn:7171298","tgn:7003692","tgn:1000003","tgn:7000084","tgn:7029392"],"placetype":["aat:300000206"],"id":7171298,"name:xx":"Hirschb\u00fchl"}}
>>>>>>> 03f74aca74312dbeaf24d7e61306dd6a786dc3d0
