{
  "id": 2775386,
  "type": "Feature",
  "properties": {
    "tgn:hierarchy":[
        "tgn:2775386",
        "tgn:1000001",
        "tgn:7012149",
        "tgn:7007157",
        "tgn:1002608",
        "tgn:7029392"
    ],
    "tgn:id":2775386,
    "tgn:name":"Wilson Canyon",
    "tgn:placetype":[
        "aat:300008761"
    ]
},
  "bbox": [],
  "geometry": {"coordinates":[-118.4333,34.35],"type":"Point"}
}