{
  "id": 7509915,
  "type": "Feature",
  "properties": {
    "tgn:hierarchy":[
        "tgn:7509915",
        "tgn:1008380",
        "tgn:7000507",
        "tgn:1000226",
        "tgn:1000006",
        "tgn:7029392"
    ],
    "tgn:id":7509915,
    "tgn:name:en":"Waihaha",
    "tgn:placetype":[
        "aat:300008347"
    ]
},
  "bbox": [],
  "geometry": {"coordinates":[174.233333,-35.333333],"type":"Point"}
}