<<<<<<< HEAD
{
  "id": 7477198,
  "type": "Feature",
  "properties": {
    "tgn:hierarchy":[
        "tgn:7477198",
        "tgn:7488858",
        "tgn:1000004",
        "tgn:1000141",
        "tgn:7029392"
    ],
    "tgn:id":7477198,
    "tgn:name":"Dashanjiao",
    "tgn:placetype":[
        "aat:300008347"
    ]
},
  "bbox": [],
  "geometry": {"coordinates":[120.82435,23.83329],"type":"Point"}
}
=======
{"geometry":{"type":"Point","coordinates":[120.824350,23.833290]},"type":"Feature","properties":{"hierarchy":["tgn:7477198","tgn:7488858","tgn:1000004","tgn:1000141","tgn:7029392"],"placetype":["aat:300008347"],"id":7477198,"name:xx":"Dashanjiao"}}
>>>>>>> 03f74aca74312dbeaf24d7e61306dd6a786dc3d0
