{
  "id": 7343616,
  "type": "Feature",
  "properties": {
    "tgn:hierarchy":[
        "tgn:7343616",
        "tgn:7002831",
        "tgn:1000003",
        "tgn:7002786",
        "tgn:1000095",
        "tgn:7029392"
    ],
    "tgn:id":7343616,
    "tgn:name":"Cadabal, Monte",
    "tgn:placetype":[
        "aat:300266640"
    ]
},
  "bbox": [],
  "geometry": {"coordinates":[-7.05,42.366667],"type":"Point"}
}