{
  "id": 1015251,
  "type": "Feature",
  "properties": {
    "tgn:hierarchy":[
        "tgn:1015251",
        "tgn:7005685",
        "tgn:1000001",
        "tgn:7005803",
        "tgn:7029392"
    ],
    "tgn:id":1015251,
    "tgn:name":"Mount Stewart",
    "tgn:placetype":[
        "aat:300008347"
    ]
},
  "bbox": [],
  "geometry": {"coordinates":[-62.8667,46.3667],"type":"Point"}
}