{
  "id": 2469263,
  "type": "Feature",
  "properties": {
    "tgn:hierarchy":[
        "tgn:2469263",
        "tgn:1000001",
        "tgn:7012149",
        "tgn:2000928",
        "tgn:7007515",
        "tgn:7029392"
    ],
    "tgn:id":2469263,
    "tgn:name":"Longley Stream",
    "tgn:placetype":[
        "aat:300008699"
    ]
},
  "bbox": [],
  "geometry": {"coordinates":[-69.4167,46.15],"type":"Point"}
}