{
  "id": 2164633,
  "type": "Feature",
  "properties": {
    "tgn:hierarchy":[
        "tgn:2164633",
        "tgn:1000001",
        "tgn:7012149",
        "tgn:2002297",
        "tgn:7013961",
        "tgn:7029392"
    ],
    "tgn:id":2164633,
    "tgn:name":"Bert",
    "tgn:placetype":[
        "aat:300008347"
    ]
},
  "bbox": [],
  "geometry": {"coordinates":[-80.95,39.45],"type":"Point"}
}