<<<<<<< HEAD
{
  "id": 7470599,
  "type": "Feature",
  "properties": {
    "tgn:hierarchy":[
        "tgn:7470599",
        "tgn:7001004",
        "tgn:1000004",
        "tgn:1000141",
        "tgn:7029392"
    ],
    "tgn:id":7470599,
    "tgn:name":"Xixi",
    "tgn:placetype":[
        "aat:300008347"
    ]
},
  "bbox": [],
  "geometry": {"coordinates":[120.3915,22.488398],"type":"Point"}
}
=======
{"geometry":{"type":"Point","coordinates":[120.391500,22.488398]},"type":"Feature","properties":{"hierarchy":["tgn:7470599","tgn:7001004","tgn:1000004","tgn:1000141","tgn:7029392"],"placetype":["aat:300008347"],"id":7470599,"name:xx":"Xixi"}}
>>>>>>> 03f74aca74312dbeaf24d7e61306dd6a786dc3d0
