{
  "id": 7529556,
  "type": "Feature",
  "properties": {
    "tgn:hierarchy":[
        "tgn:7529556",
        "tgn:7001242",
        "tgn:7016833",
        "tgn:1001110",
        "tgn:7029392"
    ],
    "tgn:id":7529556,
    "tgn:name:en":"Umm Zaytah, W\u0101d\u012b",
    "tgn:placetype":[
        "aat:300379998"
    ]
},
  "bbox": [],
  "geometry": {"coordinates":[32.263227,29.826182],"type":"Point"}
}