{
  "id": 1090731,
  "type": "Feature",
  "properties": {
    "tgn:hierarchy":[
        "tgn:1090731",
        "tgn:7001242",
        "tgn:7000611",
        "tgn:1000172",
        "tgn:7029392"
    ],
    "tgn:id":1090731,
    "tgn:name":"Zal\u1e6dan",
    "tgn:placetype":[
        "aat:300008347"
    ]
},
  "bbox": [],
  "geometry": {"coordinates":[11.85,32.95],"type":"Point"}
}