{
  "id": 2628660,
  "type": "Feature",
  "properties": {
    "tgn:hierarchy":[
        "tgn:2628660",
        "tgn:1000001",
        "tgn:2001419",
        "tgn:7012149",
        "tgn:7007526",
        "tgn:7029392"
    ],
    "tgn:id":2628660,
    "tgn:name":"Root Spring",
    "tgn:placetype":[
        "aat:300008697"
    ]
},
  "bbox": [],
  "geometry": {"coordinates":[-117.85,40.2333],"type":"Point"}
}