<<<<<<< HEAD
{
  "id": 2157743,
  "type": "Feature",
  "properties": {
    "tgn:hierarchy":[
        "tgn:2157743",
        "tgn:1000001",
        "tgn:7012149",
        "tgn:7014612",
        "tgn:7007568",
        "tgn:7029392"
    ],
    "tgn:id":2157743,
    "tgn:name":"Beaver Hill",
    "tgn:placetype":[
        "aat:300008798"
    ]
},
  "bbox": [],
  "geometry": {"coordinates":[-73.8167,41.0667],"type":"Point"}
}
=======
{"geometry":{"type":"Point","coordinates":[-73.816700,41.066700]},"type":"Feature","properties":{"hierarchy":["tgn:2157743","tgn:1000001","tgn:7012149","tgn:7014612","tgn:7007568","tgn:7029392"],"placetype":["aat:300008798"],"id":2157743,"name:xx":"Beaver Hill"}}
>>>>>>> 03f74aca74312dbeaf24d7e61306dd6a786dc3d0
