<<<<<<< HEAD
{
  "id": 2401907,
  "type": "Feature",
  "properties": {
    "tgn:hierarchy":[
        "tgn:2401907",
        "tgn:1000001",
        "tgn:7012149",
        "tgn:2002332",
        "tgn:7007922",
        "tgn:7029392"
    ],
    "tgn:id":2401907,
    "tgn:name":"Horseshoe Lake",
    "tgn:placetype":[
        "aat:300008680"
    ]
},
  "bbox": [],
  "geometry": {"coordinates":[-89.8667,42.5667],"type":"Point"}
}
=======
{"geometry":{"type":"Point","coordinates":[-89.866700,42.566700]},"type":"Feature","properties":{"hierarchy":["tgn:2401907","tgn:1000001","tgn:7012149","tgn:2002332","tgn:7007922","tgn:7029392"],"placetype":["aat:300008680"],"id":2401907,"name:xx":"Horseshoe Lake"}}
>>>>>>> 03f74aca74312dbeaf24d7e61306dd6a786dc3d0
