<<<<<<< HEAD
{
  "id": 7178596,
  "type": "Feature",
  "properties": {
    "tgn:hierarchy":[
        "tgn:7178596",
        "tgn:1000003",
        "tgn:7003678",
        "tgn:7000084",
        "tgn:7029392"
    ],
    "tgn:id":7178596,
    "tgn:name":"Guls-Berg",
    "tgn:placetype":[
        "aat:300008777"
    ]
},
  "bbox": [],
  "geometry": {"coordinates":[9.783333,51.216667],"type":"Point"}
}
=======
{"geometry":{"type":"Point","coordinates":[9.783333,51.216667]},"type":"Feature","properties":{"hierarchy":["tgn:7178596","tgn:1000003","tgn:7003678","tgn:7000084","tgn:7029392"],"placetype":["aat:300008777"],"id":7178596,"name:xx":"Guls-Berg"}}
>>>>>>> 03f74aca74312dbeaf24d7e61306dd6a786dc3d0
