{
  "id": 7178596,
  "type": "Feature",
  "properties": {
    "tgn:hierarchy":[
        "tgn:7178596",
        "tgn:1000003",
        "tgn:7003678",
        "tgn:7000084",
        "tgn:7029392"
    ],
    "tgn:id":7178596,
    "tgn:name":"Guls-Berg",
    "tgn:placetype":[
        "aat:300008777"
    ]
},
  "bbox": [],
  "geometry": {"coordinates":[9.783333,51.216667],"type":"Point"}
}