{
  "id": 2714405,
  "type": "Feature",
  "properties": {
    "tgn:hierarchy":[
        "tgn:2714405",
        "tgn:1000001",
        "tgn:2001264",
        "tgn:7012149",
        "tgn:7007524",
        "tgn:7029392"
    ],
    "tgn:id":2714405,
    "tgn:name":"Tempest Mountain",
    "tgn:placetype":[
        "aat:300008798"
    ]
},
  "bbox": [],
  "geometry": {"coordinates":[-109.7833,45.1667],"type":"Point"}
}