{
  "id": 1082339,
  "type": "Feature",
  "properties": {
    "tgn:hierarchy":[
        "tgn:1082339",
        "tgn:7001322",
        "tgn:1000004",
        "tgn:7000299",
        "tgn:7029392"
    ],
    "tgn:id":1082339,
    "tgn:name":"Pup'y\u014fng",
    "tgn:placetype":[
        "aat:300008347"
    ]
},
  "bbox": [],
  "geometry": {"coordinates":[126.7167,37.5333],"type":"Point"}
}