{
  "id": 2286656,
  "type": "Feature",
  "properties": {
    "tgn:hierarchy":[
        "tgn:2286656",
        "tgn:1000001",
        "tgn:7012149",
        "tgn:2000851",
        "tgn:7007255",
        "tgn:7029392"
    ],
    "tgn:id":2286656,
    "tgn:name":"Diamond Mines",
    "tgn:placetype":[
        "aat:300000390"
    ]
},
  "bbox": [],
  "geometry": {"coordinates":[-87.7833,37.4167],"type":"Point"}
}