<<<<<<< HEAD
{
  "id": 7117830,
  "type": "Feature",
  "properties": {
    "tgn:hierarchy":[
        "tgn:7117830",
        "tgn:7003669",
        "tgn:1000003",
        "tgn:7000084",
        "tgn:7029392"
    ],
    "tgn:id":7117830,
    "tgn:name":"Oderer",
    "tgn:placetype":[
        "aat:300000206"
    ]
},
  "bbox": [],
  "geometry": {"coordinates":[13.333333,48.516667],"type":"Point"}
}
=======
{"geometry":{"type":"Point","coordinates":[13.333333,48.516667]},"type":"Feature","properties":{"hierarchy":["tgn:7117830","tgn:7003669","tgn:1000003","tgn:7000084","tgn:7029392"],"placetype":["aat:300000206"],"id":7117830,"name:xx":"Oderer"}}
>>>>>>> 03f74aca74312dbeaf24d7e61306dd6a786dc3d0
