{
  "id": 7410874,
  "type": "Feature",
  "properties": {
    "tgn:hierarchy":[
        "tgn:7410874",
        "tgn:1000001",
        "tgn:7005590",
        "tgn:7005560",
        "tgn:7029392"
    ],
    "tgn:id":7410874,
    "tgn:name":"Huarichi",
    "tgn:placetype":[
        "aat:300008347"
    ]
},
  "bbox": [],
  "geometry": {"coordinates":[-100.688889,18.440278],"type":"Point"}
}