{
  "id": 2269243,
  "type": "Feature",
  "properties": {
    "tgn:hierarchy":[
        "tgn:2269243",
        "tgn:1000001",
        "tgn:7012149",
        "tgn:2000653",
        "tgn:7007253",
        "tgn:7029392"
    ],
    "tgn:id":2269243,
    "tgn:name":"Crow Creek",
    "tgn:placetype":[
        "aat:300008706"
    ]
},
  "bbox": [],
  "geometry": {"coordinates":[-93.1667,40.8333],"type":"Point"}
}