{
  "id": 7284054,
  "type": "Feature",
  "properties": {
    "tgn:hierarchy":[
        "tgn:7284054",
        "tgn:1001692",
        "tgn:1000049",
        "tgn:1000002",
        "tgn:7029392"
    ],
    "tgn:id":7284054,
    "tgn:name":"Quino",
    "tgn:placetype":[
        "aat:300000206"
    ]
},
  "bbox": [],
  "geometry": {"coordinates":[-72.516667,-38.333333],"type":"Point"}
}