{
  "id": 2539701,
  "type": "Feature",
  "properties": {
    "tgn:hierarchy":[
        "tgn:2539701",
        "tgn:1000001",
        "tgn:7012149",
        "tgn:2000283",
        "tgn:7007240",
        "tgn:7029392"
    ],
    "tgn:id":2539701,
    "tgn:name":"New Switzerland Point",
    "tgn:placetype":[
        "aat:300008850"
    ]
},
  "bbox": [],
  "geometry": {"coordinates":[-81.6667,30.05],"type":"Point"}
}