{
  "id": 2565893,
  "type": "Feature",
  "properties": {
    "tgn:hierarchy":[
        "tgn:2565893",
        "tgn:1000001",
        "tgn:1002473",
        "tgn:7012149",
        "tgn:7007240",
        "tgn:7029392"
    ],
    "tgn:id":2565893,
    "tgn:name":"Palm Grove Colony",
    "tgn:placetype":[
        "aat:300008347"
    ]
},
  "bbox": [],
  "geometry": {"coordinates":[-82.6167,28.55],"type":"Point"}
}