{
  "id": 7562049,
  "type": "Feature",
  "properties": {
    "tgn:hierarchy":[
        "tgn:7562049",
        "tgn:1000004",
        "tgn:7000198",
        "tgn:7016722",
        "tgn:7029392"
    ],
    "tgn:id":7562049,
    "tgn:name:en":"Nagaria",
    "tgn:placetype":[
        "aat:300008347"
    ]
},
  "bbox": [],
  "geometry": {"coordinates":[79.306796,27.064467],"type":"Point"}
}