{
  "id": 7090625,
  "type": "Feature",
  "properties": {
    "tgn:hierarchy":[
        "tgn:7090625",
        "tgn:1000003",
        "tgn:7003687",
        "tgn:7000084",
        "tgn:7029392"
    ],
    "tgn:id":7090625,
    "tgn:name":"Voss-Berg",
    "tgn:placetype":[
        "aat:300008777"
    ]
},
  "bbox": [],
  "geometry": {"coordinates":[11.683333,52.383333],"type":"Point"}
}