{
  "id": 2148239,
  "type": "Feature",
  "properties": {
    "tgn:hierarchy":[
        "tgn:2148239",
        "tgn:7006450",
        "tgn:1000001",
        "tgn:2124012",
        "tgn:7012149",
        "tgn:7029392"
    ],
    "tgn:id":2148239,
    "tgn:name":"Barling Bay",
    "tgn:placetype":[
        "aat:300132316"
    ]
},
  "bbox": [],
  "geometry": {"coordinates":[-153.35,57.1833],"type":"Point"}
}