{
  "id": 2686619,
  "type": "Feature",
  "properties": {
    "tgn:hierarchy":[
        "tgn:2686619",
        "tgn:1000001",
        "tgn:2001783",
        "tgn:7012149",
        "tgn:7007713",
        "tgn:7029392"
    ],
    "tgn:id":2686619,
    "tgn:name":"Spring Creek",
    "tgn:placetype":[
        "aat:300008706"
    ]
},
  "bbox": [],
  "geometry": {"coordinates":[-97.0833,42.9667],"type":"Point"}
}