{
  "id": 2593256,
  "type": "Feature",
  "properties": {
    "tgn:hierarchy":[
        "tgn:2593256",
        "tgn:7002659",
        "tgn:1000001",
        "tgn:7012149",
        "tgn:2000035",
        "tgn:7029392"
    ],
    "tgn:id":2593256,
    "tgn:name":"Poplar Spring Creek",
    "tgn:placetype":[
        "aat:300008706"
    ]
},
  "bbox": [],
  "geometry": {"coordinates":[-86.1167,34.8667],"type":"Point"}
}