{
  "id": 2396207,
  "type": "Feature",
  "properties": {
    "tgn:hierarchy":[
        "tgn:2396207",
        "tgn:7013349",
        "tgn:1000001",
        "tgn:7012149",
        "tgn:7007708",
        "tgn:7029392"
    ],
    "tgn:id":2396207,
    "tgn:name":"Holman Creek",
    "tgn:placetype":[
        "aat:300008706"
    ]
},
  "bbox": [],
  "geometry": {"coordinates":[-117.5333,44.6833],"type":"Point"}
}