{
  "id": 7224733,
  "type": "Feature",
  "properties": {
    "tgn:hierarchy":[
        "tgn:7224733",
        "tgn:7002692",
        "tgn:7012056",
        "tgn:1000003",
        "tgn:1000074",
        "tgn:7029392"
    ],
    "tgn:id":7224733,
    "tgn:name":"Riz\u00f3viglo",
    "tgn:placetype":[
        "aat:300008347"
    ]
},
  "bbox": [],
  "geometry": {"coordinates":[26.266667,35.216667],"type":"Point"}
}