{
  "id": 7567582,
  "type": "Feature",
  "properties": {
    "tgn:hierarchy":[
        "tgn:7567582",
        "tgn:1000004",
        "tgn:7000198",
        "tgn:1001996",
        "tgn:7029392"
    ],
    "tgn:id":7567582,
    "tgn:name:en":"Pal\u0101hata",
    "tgn:placetype":[
        "aat:300008347"
    ]
},
  "bbox": [],
  "geometry": {"coordinates":[77.005556,31.2125],"type":"Point"}
}