{
  "id": 7163181,
  "type": "Feature",
  "properties": {
    "tgn:hierarchy":[
        "tgn:7163181",
        "tgn:1000003",
        "tgn:7003676",
        "tgn:7000084",
        "tgn:7029392"
    ],
    "tgn:id":7163181,
    "tgn:name":"Huth-Berg",
    "tgn:placetype":[
        "aat:300008795"
    ]
},
  "bbox": [],
  "geometry": {"coordinates":[10.483333,51.866667],"type":"Point"}
}