{
  "id": 7163353,
  "type": "Feature",
  "properties": {
    "tgn:hierarchy":[
        "tgn:7163353",
        "tgn:1000003",
        "tgn:7003676",
        "tgn:7000084",
        "tgn:7029392"
    ],
    "tgn:id":7163353,
    "tgn:name":"Im Panzenberge",
    "tgn:placetype":[
        "aat:300386990"
    ]
},
  "bbox": [],
  "geometry": {"coordinates":[8.466667,53.533333],"type":"Point"}
}