{
  "id": 2776718,
  "type": "Feature",
  "properties": {
    "tgn:hierarchy":[
        "tgn:2776718",
        "tgn:1000001",
        "tgn:7012149",
        "tgn:7007157",
        "tgn:2000189",
        "tgn:7029392"
    ],
    "tgn:id":2776718,
    "tgn:name":"Windmill Point",
    "tgn:placetype":[
        "aat:300008798"
    ]
},
  "bbox": [],
  "geometry": {"coordinates":[-122.35,41.8833],"type":"Point"}
}