{
  "id": 2760351,
  "type": "Feature",
  "properties": {
    "tgn:hierarchy":[
        "tgn:2760351",
        "tgn:1000001",
        "tgn:7012149",
        "tgn:2001147",
        "tgn:7007522",
        "tgn:7029392"
    ],
    "tgn:id":2760351,
    "tgn:name":"West Fork Shockaloo Creek",
    "tgn:placetype":[
        "aat:300008706"
    ]
},
  "bbox": [],
  "geometry": {"coordinates":[-89.5667,32.3833],"type":"Point"}
}