<<<<<<< HEAD
{
  "id": 2331918,
  "type": "Feature",
  "properties": {
    "tgn:hierarchy":[
        "tgn:2331918",
        "tgn:1000001",
        "tgn:2002368",
        "tgn:7012149",
        "tgn:7007923",
        "tgn:7029392"
    ],
    "tgn:id":2331918,
    "tgn:name":"Fletcher Peak",
    "tgn:placetype":[
        "aat:300008798"
    ]
},
  "bbox": [],
  "geometry": {"coordinates":[-107.0833,41.0667],"type":"Point"}
}
=======
{"geometry":{"type":"Point","coordinates":[-107.083300,41.066700]},"type":"Feature","properties":{"hierarchy":["tgn:2331918","tgn:1000001","tgn:2002368","tgn:7012149","tgn:7007923","tgn:7029392"],"placetype":["aat:300008798"],"id":2331918,"name:xx":"Fletcher Peak"}}
>>>>>>> 03f74aca74312dbeaf24d7e61306dd6a786dc3d0
