{
  "id": 2502859,
  "type": "Feature",
  "properties": {
    "tgn:hierarchy":[
        "tgn:2502859",
        "tgn:1000001",
        "tgn:7012149",
        "tgn:2002372",
        "tgn:7007923",
        "tgn:7029392"
    ],
    "tgn:id":2502859,
    "tgn:name":"McMillen Number 2 Reservoir",
    "tgn:placetype":[
        "aat:300006191"
    ]
},
  "bbox": [],
  "geometry": {"coordinates":[-104.1667,41.7667],"type":"Point"}
}