{
  "id": 2556299,
  "type": "Feature",
  "properties": {
    "tgn:hierarchy":[
        "tgn:2556299",
        "tgn:7006450",
        "tgn:1000001",
        "tgn:7012149",
        "tgn:2124005",
        "tgn:7029392"
    ],
    "tgn:id":2556299,
    "tgn:name":"Okerokovik River",
    "tgn:placetype":[
        "aat:300008707"
    ]
},
  "bbox": [],
  "geometry": {"coordinates":[-143.2833,69.3833],"type":"Point"}
}