{
  "id": 7545905,
  "type": "Feature",
  "properties": {
    "tgn:hierarchy":[
        "tgn:7545905",
        "tgn:1000004",
        "tgn:1001871",
        "tgn:7000198",
        "tgn:7029392"
    ],
    "tgn:id":7545905,
    "tgn:name:en":"Barw\u0101la",
    "tgn:placetype":[
        "aat:300008347"
    ]
},
  "bbox": [],
  "geometry": {"coordinates":[75.906689,29.366597],"type":"Point"}
}