{
  "id": 2419372,
  "type": "Feature",
  "properties": {
    "tgn:hierarchy":[
        "tgn:2419372",
        "tgn:1000001",
        "tgn:7012149",
        "tgn:2001525",
        "tgn:7007709",
        "tgn:7029392"
    ],
    "tgn:id":2419372,
    "tgn:name":"Jappa Oaks",
    "tgn:placetype":[
        "aat:300008347"
    ]
},
  "bbox": [],
  "geometry": {"coordinates":[-79.0667,36.0333],"type":"Point"}
}