{
  "id": 7398519,
  "type": "Feature",
  "properties": {
    "tgn:hierarchy":[
        "tgn:7398519",
        "tgn:7005587",
        "tgn:1000001",
        "tgn:7005560",
        "tgn:7029392"
    ],
    "tgn:id":7398519,
    "tgn:name":"Santa Mar\u00eda Magdalena",
    "tgn:placetype":[
        "aat:300008347"
    ]
},
  "bbox": [],
  "geometry": {"coordinates":[-99.378056,19.975278],"type":"Point"}
}