{
  "id": 7329704,
  "type": "Feature",
  "properties": {
    "tgn:hierarchy":[
        "tgn:7329704",
        "tgn:7002831",
        "tgn:1000003",
        "tgn:7002786",
        "tgn:1000095",
        "tgn:7029392"
    ],
    "tgn:id":7329704,
    "tgn:name":"Lamalonga",
    "tgn:placetype":[
        "aat:300008347"
    ]
},
  "bbox": [],
  "geometry": {"coordinates":[-6.966667,42.283333],"type":"Point"}
}