{
  "id": 2523765,
  "type": "Feature",
  "properties": {
    "tgn:hierarchy":[
        "tgn:2523765",
        "tgn:7006450",
        "tgn:1000001",
        "tgn:7012149",
        "tgn:2000086",
        "tgn:7029392"
    ],
    "tgn:id":2523765,
    "tgn:name":"Moraine Reef",
    "tgn:placetype":[
        "aat:300132348"
    ]
},
  "bbox": [],
  "geometry": {"coordinates":[-141.4167,59.9167],"type":"Point"}
}