{
  "id": 2015999,
  "type": "Feature",
  "properties": {
    "tgn:hierarchy":[
        "tgn:2015999",
        "tgn:1000001",
        "tgn:7012149",
        "tgn:7007158",
        "tgn:2000244",
        "tgn:7029392"
    ],
    "tgn:id":2015999,
    "tgn:name":"Monte Vista",
    "tgn:placetype":[
        "aat:300008347"
    ]
},
  "bbox": [],
  "geometry": {"coordinates":[-106.1333,37.5667],"type":"Point"}
}