<<<<<<< HEAD
{
  "id": 2252546,
  "type": "Feature",
  "properties": {
    "tgn:hierarchy":[
        "tgn:2252546",
        "tgn:1000001",
        "tgn:7006451",
        "tgn:7012149",
        "tgn:2000101",
        "tgn:7029392"
    ],
    "tgn:id":2252546,
    "tgn:name":"Conley Spring Wash",
    "tgn:placetype":[
        "aat:300008699"
    ]
},
  "bbox": [],
  "geometry": {"coordinates":[-111.0833,33.3167],"type":"Point"}
}
=======
{"geometry":{"type":"Point","coordinates":[-111.083300,33.316700]},"type":"Feature","properties":{"hierarchy":["tgn:2252546","tgn:1000001","tgn:7006451","tgn:7012149","tgn:2000101","tgn:7029392"],"placetype":["aat:300008699"],"id":2252546,"name:xx":"Conley Spring Wash"}}
>>>>>>> 03f74aca74312dbeaf24d7e61306dd6a786dc3d0
