{
  "id": 7284461,
  "type": "Feature",
  "properties": {
    "tgn:hierarchy":[
        "tgn:7284461",
        "tgn:7016598",
        "tgn:1000049",
        "tgn:1000002",
        "tgn:7029392"
    ],
    "tgn:id":7284461,
    "tgn:name":"Campamento Pinchal",
    "tgn:placetype":[
        "aat:300008057"
    ]
},
  "bbox": [],
  "geometry": {"coordinates":[-68.883333,-21.45],"type":"Point"}
}