{
  "id": 2246894,
  "type": "Feature",
  "properties": {
    "tgn:hierarchy":[
        "tgn:2246894",
        "tgn:1000001",
        "tgn:7012149",
        "tgn:2000784",
        "tgn:7007255",
        "tgn:7029392"
    ],
    "tgn:id":2246894,
    "tgn:name":"Cochran Hill",
    "tgn:placetype":[
        "aat:300008798"
    ]
},
  "bbox": [],
  "geometry": {"coordinates":[-88.0667,37.2667],"type":"Point"}
}