{
  "id": 2160439,
  "type": "Feature",
  "properties": {
    "tgn:hierarchy":[
        "tgn:2160439",
        "tgn:1000001",
        "tgn:7012149",
        "tgn:2000276",
        "tgn:7007240",
        "tgn:7029392"
    ],
    "tgn:id":2160439,
    "tgn:name":"Beer Can Pond",
    "tgn:placetype":[
        "aat:300008680"
    ]
},
  "bbox": [],
  "geometry": {"coordinates":[-84.0167,30.5833],"type":"Point"}
}