{
  "id": 7212752,
  "type": "Feature",
  "properties": {
    "tgn:hierarchy":[
        "tgn:7212752",
        "tgn:1000003",
        "tgn:7003688",
        "tgn:7000084",
        "tgn:7029392"
    ],
    "tgn:id":7212752,
    "tgn:name":"Bonsberg",
    "tgn:placetype":[
        "aat:300000206"
    ]
},
  "bbox": [],
  "geometry": {"coordinates":[9.866667,54.75],"type":"Point"}
}