<<<<<<< HEAD
{
  "id": 7118752,
  "type": "Feature",
  "properties": {
    "tgn:hierarchy":[
        "tgn:7118752",
        "tgn:1000003",
        "tgn:7000094",
        "tgn:7000084",
        "tgn:7029392"
    ],
    "tgn:id":7118752,
    "tgn:name":"Probst Jesar",
    "tgn:placetype":[
        "aat:300008347"
    ]
},
  "bbox": [],
  "geometry": {"coordinates":[11.116667,53.3],"type":"Point"}
}
=======
{"geometry":{"type":"Point","coordinates":[11.116667,53.300000]},"type":"Feature","properties":{"hierarchy":["tgn:7118752","tgn:1000003","tgn:7000094","tgn:7000084","tgn:7029392"],"placetype":["aat:300008347"],"id":7118752,"name:xx":"Probst Jesar"}}
>>>>>>> 03f74aca74312dbeaf24d7e61306dd6a786dc3d0
