{
  "id": 1118034,
  "type": "Feature",
  "properties": {
    "tgn:hierarchy":[
        "tgn:1118034",
        "tgn:7002991",
        "tgn:1000003",
        "tgn:7002997",
        "tgn:1000080",
        "tgn:7029392"
    ],
    "tgn:id":1118034,
    "tgn:name":"Santa Croce, Lago di",
    "tgn:placetype":[
        "aat:300008680"
    ]
},
  "bbox": [],
  "geometry": {"coordinates":[12.340278,46.112222],"type":"Point"}
}