<<<<<<< HEAD
{
  "id": 2257877,
  "type": "Feature",
  "properties": {
    "tgn:hierarchy":[
        "tgn:2257877",
        "tgn:1000001",
        "tgn:7012149",
        "tgn:2001897",
        "tgn:7007825",
        "tgn:7029392"
    ],
    "tgn:id":2257877,
    "tgn:name":"Correll Ridge",
    "tgn:placetype":[
        "aat:300266640"
    ]
},
  "bbox": [],
  "geometry": {"coordinates":[-84.8167,35.5167],"type":"Point"}
}
=======
{"geometry":{"type":"Point","coordinates":[-84.816700,35.516700]},"type":"Feature","properties":{"hierarchy":["tgn:2257877","tgn:1000001","tgn:7012149","tgn:2001897","tgn:7007825","tgn:7029392"],"placetype":["aat:300266640"],"id":2257877,"name:xx":"Correll Ridge"}}
>>>>>>> 03f74aca74312dbeaf24d7e61306dd6a786dc3d0
