{
  "id": 7563962,
  "type": "Feature",
  "properties": {
    "tgn:hierarchy":[
        "tgn:7563962",
        "tgn:1000004",
        "tgn:7000198",
        "tgn:7016722",
        "tgn:7029392"
    ],
    "tgn:id":7563962,
    "tgn:name:en":"Farrukh\u0101b\u0101d Protected Forest",
    "tgn:placetype":[
        "aat:300008865"
    ]
},
  "bbox": [],
  "geometry": {"coordinates":[79.529681,26.928753],"type":"Point"}
}