{
  "id": 7590840,
  "type": "Feature",
  "properties": {
    "tgn:hierarchy":[
        "tgn:7590840",
        "tgn:1000004",
        "tgn:7000198",
        "tgn:7000799",
        "tgn:7029392"
    ],
    "tgn:id":7590840,
    "tgn:name:en":"Gurw\u0101n Sar",
    "tgn:placetype":[
        "aat:300008680"
    ]
},
  "bbox": [],
  "geometry": {"coordinates":[74.463889,33.802778],"type":"Point"}
}