{
  "id": 2082511,
  "type": "Feature",
  "properties": {
    "tgn:hierarchy":[
        "tgn:2082511",
        "tgn:1000001",
        "tgn:7012149",
        "tgn:1002625",
        "tgn:7007706",
        "tgn:7029392"
    ],
    "tgn:id":2082511,
    "tgn:name":"West Jefferson",
    "tgn:placetype":[
        "aat:300008347"
    ]
},
  "bbox": [],
  "geometry": {"coordinates":[-83.2667,39.9333],"type":"Point"}
}