{
  "id": 2181628,
  "type": "Feature",
  "properties": {
    "tgn:hierarchy":[
        "tgn:2181628",
        "tgn:1000001",
        "tgn:1002200",
        "tgn:7012149",
        "tgn:7007240",
        "tgn:7029392"
    ],
    "tgn:id":2181628,
    "tgn:name":"Blue Hole",
    "tgn:placetype":[
        "aat:300386845"
    ]
},
  "bbox": [],
  "geometry": {"coordinates":[-80.8167,28.55],"type":"Point"}
}