{
  "id": 2632234,
  "type": "Feature",
  "properties": {
    "tgn:hierarchy":[
        "tgn:2632234",
        "tgn:1000001",
        "tgn:7012149",
        "tgn:2001529",
        "tgn:7007709",
        "tgn:7029392"
    ],
    "tgn:id":2632234,
    "tgn:name":"Roxboro Country Club Lake",
    "tgn:placetype":[
        "aat:300006191"
    ]
},
  "bbox": [],
  "geometry": {"coordinates":[-78.9833,36.45],"type":"Point"}
}