{
  "id": 7277688,
  "type": "Feature",
  "properties": {
    "tgn:hierarchy":[
        "tgn:7277688",
        "tgn:1001699",
        "tgn:1000049",
        "tgn:1000002",
        "tgn:7029392"
    ],
    "tgn:id":7277688,
    "tgn:name":"Caleta Ayacara",
    "tgn:placetype":[
        "aat:300132317"
    ]
},
  "bbox": [],
  "geometry": {"coordinates":[-72.800833,-42.405],"type":"Point"}
}