{
  "id": 7243125,
  "type": "Feature",
  "properties": {
    "tgn:hierarchy":[
        "tgn:7243125",
        "tgn:7018238",
        "tgn:1000003",
        "tgn:1000063",
        "tgn:4012014",
        "tgn:7029392"
    ],
    "tgn:id":7243125,
    "tgn:name":"Lumay",
    "tgn:placetype":[
        "aat:300008347"
    ]
},
  "bbox": [],
  "geometry": {"coordinates":[4.885843,50.757644],"type":"Point"}
}