{
  "id": 7560503,
  "type": "Feature",
  "properties": {
    "tgn:hierarchy":[
        "tgn:7560503",
        "tgn:1000004",
        "tgn:7000198",
        "tgn:7016722",
        "tgn:7029392"
    ],
    "tgn:id":7560503,
    "tgn:name:en":"Nagla Mah\u0101singh",
    "tgn:placetype":[
        "aat:300008347"
    ]
},
  "bbox": [],
  "geometry": {"coordinates":[79.233591,26.865474],"type":"Point"}
}