{
  "id": 2396201,
  "type": "Feature",
  "properties": {
    "tgn:hierarchy":[
        "tgn:2396201",
        "tgn:1000001",
        "tgn:7012149",
        "tgn:2001029",
        "tgn:7007521",
        "tgn:7029392"
    ],
    "tgn:id":2396201,
    "tgn:name":"Holman Cliffs Mine",
    "tgn:placetype":[
        "aat:300000390"
    ]
},
  "bbox": [],
  "geometry": {"coordinates":[-93.3833,47.3167],"type":"Point"}
}