<<<<<<< HEAD
{
  "id": 7362989,
  "type": "Feature",
  "properties": {
    "tgn:hierarchy":[
        "tgn:7362989",
        "tgn:7005581",
        "tgn:1000001",
        "tgn:7005560",
        "tgn:7029392"
    ],
    "tgn:id":7362989,
    "tgn:name":"Rancho El Meste\u00f1o",
    "tgn:placetype":[
        "aat:300000241"
    ]
},
  "bbox": [],
  "geometry": {"coordinates":[-107.1,28.5],"type":"Point"}
}
=======
{"geometry":{"type":"Point","coordinates":[-107.100000,28.500000]},"type":"Feature","properties":{"hierarchy":["tgn:7362989","tgn:7005581","tgn:1000001","tgn:7005560","tgn:7029392"],"placetype":["aat:300000241"],"id":7362989,"name:xx":"Rancho El Meste\u00f1o"}}
>>>>>>> 03f74aca74312dbeaf24d7e61306dd6a786dc3d0
