{
  "id": 2153898,
  "type": "Feature",
  "properties": {
    "tgn:hierarchy":[
        "tgn:2153898",
        "tgn:1000001",
        "tgn:7006451",
        "tgn:2000094",
        "tgn:7012149",
        "tgn:7029392"
    ],
    "tgn:id":2153898,
    "tgn:name":"Bear Canyon Tank",
    "tgn:placetype":[
        "aat:300006191"
    ]
},
  "bbox": [],
  "geometry": {"coordinates":[-109.6833,33.0333],"type":"Point"}
}