<<<<<<< HEAD
{
  "id": 2153898,
  "type": "Feature",
  "properties": {
    "tgn:hierarchy":[
        "tgn:2153898",
        "tgn:1000001",
        "tgn:7006451",
        "tgn:2000094",
        "tgn:7012149",
        "tgn:7029392"
    ],
    "tgn:id":2153898,
    "tgn:name":"Bear Canyon Tank",
    "tgn:placetype":[
        "aat:300006191"
    ]
},
  "bbox": [],
  "geometry": {"coordinates":[-109.6833,33.0333],"type":"Point"}
}
=======
{"geometry":{"type":"Point","coordinates":[-109.683300,33.033300]},"type":"Feature","properties":{"hierarchy":["tgn:2153898","tgn:1000001","tgn:7006451","tgn:2000094","tgn:7012149","tgn:7029392"],"placetype":["aat:300006191"],"id":2153898,"name:xx":"Bear Canyon Tank"}}
>>>>>>> 03f74aca74312dbeaf24d7e61306dd6a786dc3d0
