{
  "id": 2205846,
  "type": "Feature",
  "properties": {
    "tgn:hierarchy":[
        "tgn:2205846",
        "tgn:1000001",
        "tgn:7006451",
        "tgn:7012149",
        "tgn:2000103",
        "tgn:7029392"
    ],
    "tgn:id":2205846,
    "tgn:name":"Bull Pasture Tank",
    "tgn:placetype":[
        "aat:300006191"
    ]
},
  "bbox": [],
  "geometry": {"coordinates":[-113.1167,35.0333],"type":"Point"}
}