{
  "id": 2552604,
  "type": "Feature",
  "properties": {
    "tgn:hierarchy":[
        "tgn:2552604",
        "tgn:1000001",
        "tgn:7012149",
        "tgn:2000476",
        "tgn:7007250",
        "tgn:7029392"
    ],
    "tgn:id":2552604,
    "tgn:name":"Nut Basin",
    "tgn:placetype":[
        "aat:300386845"
    ]
},
  "bbox": [],
  "geometry": {"coordinates":[-116.1667,45.5167],"type":"Point"}
}