{
  "id": 2069445,
  "type": "Feature",
  "properties": {
    "tgn:hierarchy":[
        "tgn:2069445",
        "tgn:1000001",
        "tgn:7012149",
        "tgn:1002833",
        "tgn:7007568",
        "tgn:7029392"
    ],
    "tgn:id":2069445,
    "tgn:name":"Grand View-on-Hudson",
    "tgn:placetype":[
        "aat:300008347"
    ]
},
  "bbox": [],
  "geometry": {"coordinates":[-73.9167,41.05],"type":"Point"}
}