{
  "id": 7204065,
  "type": "Feature",
  "properties": {
    "tgn:hierarchy":[
        "tgn:7204065",
        "tgn:1000003",
        "tgn:7003678",
        "tgn:7000084",
        "tgn:7029392"
    ],
    "tgn:id":7204065,
    "tgn:name":"Braunfels, Forst",
    "tgn:placetype":[
        "aat:300008863"
    ]
},
  "bbox": [],
  "geometry": {"coordinates":[8.366667,50.533333],"type":"Point"}
}