{
  "id": 7353422,
  "type": "Feature",
  "properties": {
    "tgn:hierarchy":[
        "tgn:7353422",
        "tgn:1000001",
        "tgn:7005588",
        "tgn:7005560",
        "tgn:7029392"
    ],
    "tgn:id":7353422,
    "tgn:name":"Ayala",
    "tgn:placetype":[
        "aat:300008347"
    ]
},
  "bbox": [],
  "geometry": {"coordinates":[-98.983333,18.75],"type":"Point"}
}