{
  "id": 2473638,
  "type": "Feature",
  "properties": {
    "tgn:hierarchy":[
        "tgn:2473638",
        "tgn:1000001",
        "tgn:7012149",
        "tgn:1002749",
        "tgn:7007240",
        "tgn:7029392"
    ],
    "tgn:id":2473638,
    "tgn:name":"Lower Doe Lake",
    "tgn:placetype":[
        "aat:300008680"
    ]
},
  "bbox": [],
  "geometry": {"coordinates":[-81.5333,28.6667],"type":"Point"}
}