{
  "id": 2353662,
  "type": "Feature",
  "properties": {
    "tgn:hierarchy":[
        "tgn:2353662",
        "tgn:1000001",
        "tgn:7012149",
        "tgn:2001279",
        "tgn:7007524",
        "tgn:7029392"
    ],
    "tgn:id":2353662,
    "tgn:name":"Gold Leaf Mine",
    "tgn:placetype":[
        "aat:300000390"
    ]
},
  "bbox": [],
  "geometry": {"coordinates":[-113.5667,46.5833],"type":"Point"}
}