{
  "id": 2744253,
  "type": "Feature",
  "properties": {
    "tgn:hierarchy":[
        "tgn:2744253",
        "tgn:1000001",
        "tgn:7012149",
        "tgn:7007520",
        "tgn:7029392"
    ],
    "tgn:id":2744253,
    "tgn:name":"Vermilion Creek",
    "tgn:placetype":[
        "aat:300008706"
    ]
},
  "bbox": [],
  "geometry": {"coordinates":[-84.2333,42.7333],"type":"Point"}
}