{
  "id": 2454713,
  "type": "Feature",
  "properties": {
    "tgn:hierarchy":[
        "tgn:2454713",
        "tgn:1000001",
        "tgn:7012149",
        "tgn:2001293",
        "tgn:7007524",
        "tgn:7029392"
    ],
    "tgn:id":2454713,
    "tgn:name":"Little Donahue Creek",
    "tgn:placetype":[
        "aat:300008706"
    ]
},
  "bbox": [],
  "geometry": {"coordinates":[-110.9167,45.2667],"type":"Point"}
}