<<<<<<< HEAD
{
  "id": 2155500,
  "type": "Feature",
  "properties": {
    "tgn:hierarchy":[
        "tgn:2155500",
        "tgn:1000001",
        "tgn:7012149",
        "tgn:7007520",
        "tgn:7029392"
    ],
    "tgn:id":2155500,
    "tgn:name":"Bear River",
    "tgn:placetype":[
        "aat:300008707"
    ]
},
  "bbox": [],
  "geometry": {"coordinates":[-84.9333,45.25],"type":"Point"}
}
=======
{"geometry":{"type":"Point","coordinates":[-84.933300,45.250000]},"type":"Feature","properties":{"hierarchy":["tgn:2155500","tgn:1000001","tgn:7012149","tgn:7007520","tgn:7029392"],"placetype":["aat:300008707"],"id":2155500,"name:xx":"Bear River"}}
>>>>>>> 03f74aca74312dbeaf24d7e61306dd6a786dc3d0
