{
  "id": 7287644,
  "type": "Feature",
  "properties": {
    "tgn:hierarchy":[
        "tgn:7287644",
        "tgn:1001702",
        "tgn:1000049",
        "tgn:1000002",
        "tgn:7029392"
    ],
    "tgn:id":7287644,
    "tgn:name":"La C\u00fapula, Islote",
    "tgn:placetype":[
        "aat:300008791"
    ]
},
  "bbox": [],
  "geometry": {"coordinates":[-74.65,-52.55],"type":"Point"}
}