{
  "id": 2053466,
  "type": "Feature",
  "properties": {
    "tgn:hierarchy":[
        "tgn:2053466",
        "tgn:1000001",
        "tgn:7012149",
        "tgn:1002760",
        "tgn:7007520",
        "tgn:7029392"
    ],
    "tgn:id":2053466,
    "tgn:name":"Tallmadge",
    "tgn:placetype":[
        "aat:300008347"
    ]
},
  "bbox": [],
  "geometry": {"coordinates":[-85.8333,42.9833],"type":"Point"}
}