{
  "id": 7472072,
  "type": "Feature",
  "properties": {
    "tgn:hierarchy":[
        "tgn:7472072",
        "tgn:1000004",
        "tgn:7004300",
        "tgn:1000141",
        "tgn:7029392"
    ],
    "tgn:id":7472072,
    "tgn:name":"Cetian Dao",
    "tgn:placetype":[
        "aat:300386881"
    ]
},
  "bbox": [],
  "geometry": {"coordinates":[119.566018,23.55399],"type":"Point"}
}