<<<<<<< HEAD
{
  "id": 2706658,
  "type": "Feature",
  "properties": {
    "tgn:hierarchy":[
        "tgn:2706658",
        "tgn:1000001",
        "tgn:7012149",
        "tgn:2001284",
        "tgn:7007524",
        "tgn:7029392"
    ],
    "tgn:id":2706658,
    "tgn:name":"Swan Mine",
    "tgn:placetype":[
        "aat:300000390"
    ]
},
  "bbox": [],
  "geometry": {"coordinates":[-112.0667,46.6667],"type":"Point"}
}
=======
{"geometry":{"type":"Point","coordinates":[-112.066700,46.666700]},"type":"Feature","properties":{"hierarchy":["tgn:2706658","tgn:1000001","tgn:7012149","tgn:2001284","tgn:7007524","tgn:7029392"],"placetype":["aat:300000390"],"id":2706658,"name:xx":"Swan Mine"}}
>>>>>>> 03f74aca74312dbeaf24d7e61306dd6a786dc3d0
