{
  "id": 7323909,
  "type": "Feature",
  "properties": {
    "tgn:hierarchy":[
        "tgn:7323909",
        "tgn:7002820",
        "tgn:7030216",
        "tgn:1000003",
        "tgn:1000095",
        "tgn:7029392"
    ],
    "tgn:id":7323909,
    "tgn:name":"Ribas de Fresser",
    "tgn:placetype":[
        "aat:300008347"
    ]
},
  "bbox": [],
  "geometry": {"coordinates":[2.171093,42.309423],"type":"Point"}
}