{
  "id": 7165145,
  "type": "Feature",
  "properties": {
    "tgn:hierarchy":[
        "tgn:7165145",
        "tgn:1000003",
        "tgn:7003676",
        "tgn:7000084",
        "tgn:7029392"
    ],
    "tgn:id":7165145,
    "tgn:name":"Hombert",
    "tgn:placetype":[
        "aat:300000206"
    ]
},
  "bbox": [],
  "geometry": {"coordinates":[6.883333,52.65],"type":"Point"}
}