{
  "id": 1122091,
  "type": "Feature",
  "properties": {
    "tgn:hierarchy":[
        "tgn:1122091",
        "tgn:1000004",
        "tgn:1003408",
        "tgn:7018214",
        "tgn:7002435",
        "tgn:7029392"
    ],
    "tgn:id":1122091,
    "tgn:name":"Bol'\u0161oj Karaman",
    "tgn:placetype":[
        "aat:300008707"
    ]
},
  "bbox": [],
  "geometry": {"coordinates":[46.6333,51.6667],"type":"Point"}
}