{
  "id": 2204487,
  "type": "Feature",
  "properties": {
    "tgn:hierarchy":[
        "tgn:2204487",
        "tgn:1000001",
        "tgn:7012149",
        "tgn:2002028",
        "tgn:7007826",
        "tgn:7029392"
    ],
    "tgn:id":2204487,
    "tgn:name":"Buffalo Creek",
    "tgn:placetype":[
        "aat:300008706"
    ]
},
  "bbox": [],
  "geometry": {"coordinates":[-100.5167,36.1167],"type":"Point"}
}