{
  "id": 7081118,
  "type": "Feature",
  "properties": {
    "tgn:hierarchy":[
        "tgn:7081118",
        "tgn:1000003",
        "tgn:7003677",
        "tgn:7000084",
        "tgn:7029392"
    ],
    "tgn:id":7081118,
    "tgn:name":"Winkel",
    "tgn:placetype":[
        "aat:300000206"
    ]
},
  "bbox": [],
  "geometry": {"coordinates":[6.066667,51.116667],"type":"Point"}
}