{
  "id": 7217747,
  "type": "Feature",
  "properties": {
    "tgn:hierarchy":[
        "tgn:7217747",
        "tgn:7002715",
        "tgn:7002731",
        "tgn:1000003",
        "tgn:1000074",
        "tgn:7029392"
    ],
    "tgn:id":7217747,
    "tgn:name":"Sk\u00e1la Yerakin\u00eds",
    "tgn:placetype":[
        "aat:300007928"
    ]
},
  "bbox": [],
  "geometry": {"coordinates":[23.433333,40.266667],"type":"Point"}
}