{
  "id": 1084843,
  "type": "Feature",
  "properties": {
    "tgn:hierarchy":[
        "tgn:1084843",
        "tgn:7000680",
        "tgn:1000004",
        "tgn:7003879",
        "tgn:1000137",
        "tgn:7029392"
    ],
    "tgn:id":1084843,
    "tgn:name":"Al-Quway\u02bb\u012byah",
    "tgn:placetype":[
        "aat:300008347"
    ]
},
  "bbox": [],
  "geometry": {"coordinates":[45.2667,24.05],"type":"Point"}
}