{
  "id": 7233852,
  "type": "Feature",
  "properties": {
    "tgn:hierarchy":[
        "tgn:7233852",
        "tgn:7011170",
        "tgn:7002715",
        "tgn:1000003",
        "tgn:1000074",
        "tgn:7029392"
    ],
    "tgn:id":7233852,
    "tgn:name":"Dh\u00edkaia",
    "tgn:placetype":[
        "aat:300008057"
    ]
},
  "bbox": [],
  "geometry": {"coordinates":[25.166667,40.966667],"type":"Point"}
}