<<<<<<< HEAD
{
  "id": 7173735,
  "type": "Feature",
  "properties": {
    "tgn:hierarchy":[
        "tgn:7173735",
        "tgn:7000096",
        "tgn:1000003",
        "tgn:7000084",
        "tgn:7029392"
    ],
    "tgn:id":7173735,
    "tgn:name":"Gro\u00dfbeuthen",
    "tgn:placetype":[
        "aat:300008347"
    ]
},
  "bbox": [],
  "geometry": {"coordinates":[13.216667,52.25],"type":"Point"}
}
=======
{"geometry":{"type":"Point","coordinates":[13.216667,52.250000]},"type":"Feature","properties":{"hierarchy":["tgn:7173735","tgn:7000096","tgn:1000003","tgn:7000084","tgn:7029392"],"placetype":["aat:300008347"],"id":7173735,"name:xx":"Gro\u00dfbeuthen"}}
>>>>>>> 03f74aca74312dbeaf24d7e61306dd6a786dc3d0
