{
  "id": 7545827,
  "type": "Feature",
  "properties": {
    "tgn:hierarchy":[
        "tgn:7545827",
        "tgn:1000004",
        "tgn:7000198",
        "tgn:7016694",
        "tgn:7029392"
    ],
    "tgn:id":7545827,
    "tgn:name:en":"Bahald\u0101",
    "tgn:placetype":[
        "aat:300008347"
    ]
},
  "bbox": [],
  "geometry": {"coordinates":[86.081488,22.383387],"type":"Point"}
}