{
  "id": 7467694,
  "type": "Feature",
  "properties": {
    "tgn:hierarchy":[
        "tgn:7467694",
        "tgn:7469009",
        "tgn:1000004",
        "tgn:1000141",
        "tgn:7029392"
    ],
    "tgn:id":7467694,
    "tgn:name":"Qilin Shan",
    "tgn:placetype":[
        "aat:300008777"
    ]
},
  "bbox": [],
  "geometry": {"coordinates":[118.251111,24.4425],"type":"Point"}
}