{
  "id": 2016884,
  "type": "Feature",
  "properties": {
    "tgn:hierarchy":[
        "tgn:2016884",
        "tgn:1000001",
        "tgn:1002601",
        "tgn:7012149",
        "tgn:7007159",
        "tgn:7029392"
    ],
    "tgn:id":2016884,
    "tgn:name":"Flanders",
    "tgn:placetype":[
        "aat:300008347"
    ]
},
  "bbox": [],
  "geometry": {"coordinates":[-73.45,41.7333],"type":"Point"}
}