{
  "id": 7019994,
  "type": "Feature",
  "properties": {
    "tgn:hierarchy":[
        "tgn:7019994",
        "tgn:1000001",
        "tgn:7012149",
        "tgn:7029392"
    ],
    "tgn:id":7019994,
    "tgn:name":"Costilla Creek",
    "tgn:placetype":[
        "aat:300008706"
    ]
},
  "bbox": [],
  "geometry": {"coordinates":[-105.7167,36.9667],"type":"Point"}
}