{
  "id": 7293879,
  "type": "Feature",
  "properties": {
    "tgn:hierarchy":[
        "tgn:7293879",
        "tgn:7002824",
        "tgn:1000003",
        "tgn:7002786",
        "tgn:1000095",
        "tgn:7029392"
    ],
    "tgn:id":7293879,
    "tgn:name":"Viladonelle",
    "tgn:placetype":[
        "aat:300008347"
    ]
},
  "bbox": [],
  "geometry": {"coordinates":[-8.116667,43.483333],"type":"Point"}
}