{
  "id": 7495074,
  "type": "Feature",
  "properties": {
    "tgn:hierarchy":[
        "tgn:7495074",
        "tgn:7468018",
        "tgn:1000004",
        "tgn:1000141",
        "tgn:7029392"
    ],
    "tgn:id":7495074,
    "tgn:name":"Qianbayayi",
    "tgn:placetype":[
        "aat:300008347"
    ]
},
  "bbox": [],
  "geometry": {"coordinates":[120.675171,23.364645],"type":"Point"}
}