{
  "id": 2042364,
  "type": "Feature",
  "properties": {
    "tgn:hierarchy":[
        "tgn:2042364",
        "tgn:1000001",
        "tgn:7012149",
        "tgn:2000902",
        "tgn:7007256",
        "tgn:7029392"
    ],
    "tgn:id":2042364,
    "tgn:name":"Boscoville",
    "tgn:placetype":[
        "aat:300008347",
        "aat:300387210"
    ]
},
  "bbox": [],
  "geometry": {"coordinates":[-92.0167,30.5167],"type":"Point"}
}