{
  "id": 7083393,
  "type": "Feature",
  "properties": {
    "tgn:hierarchy":[
        "tgn:7083393",
        "tgn:1000003",
        "tgn:7003678",
        "tgn:7000084",
        "tgn:7029392"
    ],
    "tgn:id":7083393,
    "tgn:name":"Wiehof",
    "tgn:placetype":[
        "aat:300008699"
    ]
},
  "bbox": [],
  "geometry": {"coordinates":[9.266667,51.216667],"type":"Point"}
}