{
  "id": 2270085,
  "type": "Feature",
  "properties": {
    "tgn:hierarchy":[
        "tgn:2270085",
        "tgn:1000001",
        "tgn:7012149",
        "tgn:1003041",
        "tgn:7007710",
        "tgn:7029392"
    ],
    "tgn:id":2270085,
    "tgn:name":"Cruver Pond",
    "tgn:placetype":[
        "aat:300008680"
    ]
},
  "bbox": [],
  "geometry": {"coordinates":[-75.95,41.55],"type":"Point"}
}