{
  "id": 2592866,
  "type": "Feature",
  "properties": {
    "tgn:hierarchy":[
        "tgn:2592866",
        "tgn:1002149",
        "tgn:1000001",
        "tgn:7012149",
        "tgn:7007826",
        "tgn:7029392"
    ],
    "tgn:id":2592866,
    "tgn:name":"Pophers Creek",
    "tgn:placetype":[
        "aat:300008706"
    ]
},
  "bbox": [],
  "geometry": {"coordinates":[-94.4667,31.2167],"type":"Point"}
}