<<<<<<< HEAD
{
  "id": 2330564,
  "type": "Feature",
  "properties": {
    "tgn:hierarchy":[
        "tgn:2330564",
        "tgn:1000001",
        "tgn:7012149",
        "tgn:1002472",
        "tgn:7007568",
        "tgn:7029392"
    ],
    "tgn:id":2330564,
    "tgn:name":"Flat Creek",
    "tgn:placetype":[
        "aat:300008706"
    ]
},
  "bbox": [],
  "geometry": {"coordinates":[-74.9667,42.9167],"type":"Point"}
}
=======
{"geometry":{"type":"Point","coordinates":[-74.966700,42.916700]},"type":"Feature","properties":{"hierarchy":["tgn:2330564","tgn:1000001","tgn:7012149","tgn:1002472","tgn:7007568","tgn:7029392"],"placetype":["aat:300008706"],"id":2330564,"name:xx":"Flat Creek"}}
>>>>>>> 03f74aca74312dbeaf24d7e61306dd6a786dc3d0
