{
  "id": 7440686,
  "type": "Feature",
  "properties": {
    "tgn:hierarchy":[
        "tgn:7440686",
        "tgn:7005585",
        "tgn:1000001",
        "tgn:7005560",
        "tgn:7029392"
    ],
    "tgn:id":7440686,
    "tgn:name":"Santa Mar\u00eda",
    "tgn:placetype":[
        "aat:300008347"
    ]
},
  "bbox": [],
  "geometry": {"coordinates":[-98.433333,16.833333],"type":"Point"}
}