{
  "id": 2537160,
  "type": "Feature",
  "properties": {
    "tgn:hierarchy":[
        "tgn:2537160",
        "tgn:1000001",
        "tgn:7012149",
        "tgn:2000896",
        "tgn:7007256",
        "tgn:7029392"
    ],
    "tgn:id":2537160,
    "tgn:name":"Negreet, Bayou",
    "tgn:placetype":[
        "aat:300008699"
    ]
},
  "bbox": [],
  "geometry": {"coordinates":[-93.5833,31.45],"type":"Point"}
}