{
  "id": 2491108,
  "type": "Feature",
  "properties": {
    "tgn:hierarchy":[
        "tgn:2491108",
        "tgn:1000001",
        "tgn:7012149",
        "tgn:2000219",
        "tgn:7007158",
        "tgn:7029392"
    ],
    "tgn:id":2491108,
    "tgn:name":"Manzanares Creek",
    "tgn:placetype":[
        "aat:300008706"
    ]
},
  "bbox": [],
  "geometry": {"coordinates":[-105.35,37.6333],"type":"Point"}
}