{
  "id": 1057493,
  "type": "Feature",
  "properties": {
    "tgn:hierarchy":[
        "tgn:1057493",
        "tgn:7011651",
        "tgn:1000003",
        "tgn:7006660",
        "tgn:7029392"
    ],
    "tgn:id":1057493,
    "tgn:name":"Nyzhniy Rohachyk",
    "tgn:placetype":[
        "aat:300008347"
    ]
},
  "bbox": [],
  "geometry": {"coordinates":[34.0333,47.35],"type":"Point"}
}