{
  "id": 2068916,
  "type": "Feature",
  "properties": {
    "tgn:hierarchy":[
        "tgn:2068916",
        "tgn:1000001",
        "tgn:7012149",
        "tgn:1002423",
        "tgn:7007568",
        "tgn:7029392"
    ],
    "tgn:id":2068916,
    "tgn:name":"East Durham",
    "tgn:placetype":[
        "aat:300008347"
    ]
},
  "bbox": [],
  "geometry": {"coordinates":[-74.0833,42.3667],"type":"Point"}
}