{
  "id": 2507255,
  "type": "Feature",
  "properties": {
    "tgn:hierarchy":[
        "tgn:2507255",
        "tgn:1000001",
        "tgn:7012149",
        "tgn:1002969",
        "tgn:7007826",
        "tgn:7029392"
    ],
    "tgn:id":2507255,
    "tgn:name":"Metzger Lake",
    "tgn:placetype":[
        "aat:300006191"
    ]
},
  "bbox": [],
  "geometry": {"coordinates":[-95.7333,32.55],"type":"Point"}
}