{
  "id": 7441677,
  "type": "Feature",
  "properties": {
    "tgn:hierarchy":[
        "tgn:7441677",
        "tgn:7002443",
        "tgn:1000003",
        "tgn:7018993",
        "tgn:7008591",
        "tgn:7029392"
    ],
    "tgn:id":7441677,
    "tgn:name:en":"Deullyn, Ynys",
    "tgn:placetype":[
        "aat:300386846"
    ]
},
  "bbox": [],
  "geometry": {"coordinates":[-5.145278,51.961111],"type":"Point"}
}