{
  "id": 2317182,
  "type": "Feature",
  "properties": {
    "tgn:hierarchy":[
        "tgn:2317182",
        "tgn:1000001",
        "tgn:7012149",
        "tgn:2000208",
        "tgn:7007158",
        "tgn:7029392"
    ],
    "tgn:id":2317182,
    "tgn:name":"Emma Mine",
    "tgn:placetype":[
        "aat:300000390"
    ]
},
  "bbox": [],
  "geometry": {"coordinates":[-108.0833,37.7667],"type":"Point"}
}