{
  "id": 2447904,
  "type": "Feature",
  "properties": {
    "tgn:hierarchy":[
        "tgn:2447904",
        "tgn:1000001",
        "tgn:7012149",
        "tgn:7007710",
        "tgn:7029392"
    ],
    "tgn:id":2447904,
    "tgn:name":"Lieb Run",
    "tgn:placetype":[
        "aat:300008699"
    ]
},
  "bbox": [],
  "geometry": {"coordinates":[-77.7833,41.4667],"type":"Point"}
}