{
  "id": 1015587,
  "type": "Feature",
  "properties": {
    "tgn:hierarchy":[
        "tgn:1015587",
        "tgn:7005685",
        "tgn:1000001",
        "tgn:7005804",
        "tgn:7029392"
    ],
    "tgn:id":1015587,
    "tgn:name":"Rivi\u00e8re-Bleue",
    "tgn:placetype":[
        "aat:300008347"
    ]
},
  "bbox": [],
  "geometry": {"coordinates":[-69.0333,47.4333],"type":"Point"}
}