{
  "id": 1072464,
  "type": "Feature",
  "properties": {
    "tgn:hierarchy":[
        "tgn:1072464",
        "tgn:1000004",
        "tgn:7002077",
        "tgn:1000111",
        "tgn:7029392"
    ],
    "tgn:id":1072464,
    "tgn:name":"Wanglanzhuang",
    "tgn:placetype":[
        "aat:300008347"
    ]
},
  "bbox": [],
  "geometry": {"coordinates":[118.0167,39.4333],"type":"Point"}
}