{
  "id": 2419643,
  "type": "Feature",
  "properties": {
    "tgn:hierarchy":[
        "tgn:2419643",
        "tgn:1000001",
        "tgn:7012149",
        "tgn:2001454",
        "tgn:7007566",
        "tgn:7029392"
    ],
    "tgn:id":2419643,
    "tgn:name":"Jaspe, Arroyo",
    "tgn:placetype":[
        "aat:300008761"
    ]
},
  "bbox": [],
  "geometry": {"coordinates":[-105.75,35.2833],"type":"Point"}
}