{
  "id": 7588916,
  "type": "Feature",
  "properties": {
    "tgn:hierarchy":[
        "tgn:7588916",
        "tgn:1000004",
        "tgn:7000198",
        "tgn:7000799",
        "tgn:7029392"
    ],
    "tgn:id":7588916,
    "tgn:name:en":"Las\u0101na",
    "tgn:placetype":[
        "aat:300008347"
    ]
},
  "bbox": [],
  "geometry": {"coordinates":[74.218787,33.702297],"type":"Point"}
}