{
  "id": 7137920,
  "type": "Feature",
  "properties": {
    "tgn:hierarchy":[
        "tgn:7137920",
        "tgn:7003692",
        "tgn:1000003",
        "tgn:7000084",
        "tgn:7029392"
    ],
    "tgn:id":7137920,
    "tgn:name":"Liebradsberg",
    "tgn:placetype":[
        "aat:300000206"
    ]
},
  "bbox": [],
  "geometry": {"coordinates":[7.966667,48.233333],"type":"Point"}
}