{
  "id": 7339216,
  "type": "Feature",
  "properties": {
    "tgn:hierarchy":[
        "tgn:7339216",
        "tgn:7002818",
        "tgn:1001647",
        "tgn:1000003",
        "tgn:1000095",
        "tgn:7029392"
    ],
    "tgn:id":7339216,
    "tgn:name":"El Ca\u00f1izo",
    "tgn:placetype":[
        "aat:300387200"
    ]
},
  "bbox": [],
  "geometry": {"coordinates":[-2.183333,39.683333],"type":"Point"}
}