{
  "id": 7491896,
  "type": "Feature",
  "properties": {
    "tgn:hierarchy":[
        "tgn:7491896",
        "tgn:1000004",
        "tgn:7492971",
        "tgn:1000141",
        "tgn:7029392"
    ],
    "tgn:id":7491896,
    "tgn:name":"Baoheyi Shan",
    "tgn:placetype":[
        "aat:300008798"
    ]
},
  "bbox": [],
  "geometry": {"coordinates":[120.648889,22.452778],"type":"Point"}
}