{
  "id": 2548483,
  "type": "Feature",
  "properties": {
    "tgn:hierarchy":[
        "tgn:2548483",
        "tgn:1000001",
        "tgn:7006451",
        "tgn:7012149",
        "tgn:2000101",
        "tgn:7029392"
    ],
    "tgn:id":2548483,
    "tgn:name":"North Mammoth",
    "tgn:placetype":[
        "aat:300008347"
    ]
},
  "bbox": [],
  "geometry": {"coordinates":[-110.6333,32.7333],"type":"Point"}
}