{
  "id": 7414358,
  "type": "Feature",
  "properties": {
    "tgn:hierarchy":[
        "tgn:7414358",
        "tgn:1000001",
        "tgn:7005596",
        "tgn:7005560",
        "tgn:7029392"
    ],
    "tgn:id":7414358,
    "tgn:name:es":"Dos Lomitos",
    "tgn:placetype":[
        "aat:300008347"
    ]
},
  "bbox": [],
  "geometry": {"coordinates":[-91.641667,17.908333],"type":"Point"}
}