{
  "id": 2193380,
  "type": "Feature",
  "properties": {
    "tgn:hierarchy":[
        "tgn:2193380",
        "tgn:1000001",
        "tgn:7012149",
        "tgn:2001054",
        "tgn:7007521",
        "tgn:7029392"
    ],
    "tgn:id":2193380,
    "tgn:name":"Brekke Lake",
    "tgn:placetype":[
        "aat:300008680"
    ]
},
  "bbox": [],
  "geometry": {"coordinates":[-95.95,46.3333],"type":"Point"}
}