{
  "id": 2696644,
  "type": "Feature",
  "properties": {
    "tgn:hierarchy":[
        "tgn:2696644",
        "tgn:1000001",
        "tgn:1002359",
        "tgn:7012149",
        "tgn:7007517",
        "tgn:7029392"
    ],
    "tgn:id":2696644,
    "tgn:name":"Stone Rock",
    "tgn:placetype":[
        "aat:300011692"
    ]
},
  "bbox": [],
  "geometry": {"coordinates":[-70.85,42.5167],"type":"Point"}
}