{
  "id": 7007014,
  "type": "Feature",
  "properties": {
    "tgn:hierarchy":[
        "tgn:7007014",
        "tgn:7003138",
        "tgn:1000003",
        "tgn:7003080",
        "tgn:1000080",
        "tgn:7029392"
    ],
    "tgn:id":7007014,
    "tgn:name":"Grottaferrata",
    "tgn:placetype":[
        "aat:300008347"
    ]
},
  "bbox": [],
  "geometry": {"coordinates":[12.666667,41.783333],"type":"Point"}
}