{
  "id": 2785133,
  "type": "Feature",
  "properties": {
    "tgn:hierarchy":[
        "tgn:2785133",
        "tgn:1000001",
        "tgn:7012149",
        "tgn:2002379",
        "tgn:7007923",
        "tgn:7029392"
    ],
    "tgn:id":2785133,
    "tgn:name":"Yellow Mountain",
    "tgn:placetype":[
        "aat:300008798"
    ]
},
  "bbox": [],
  "geometry": {"coordinates":[-109.7833,44.0167],"type":"Point"}
}