{
  "id": 2627484,
  "type": "Feature",
  "properties": {
    "tgn:hierarchy":[
        "tgn:2627484",
        "tgn:1000001",
        "tgn:1002840",
        "tgn:7012149",
        "tgn:7007828",
        "tgn:7029392"
    ],
    "tgn:id":2627484,
    "tgn:name":"Roger Hill",
    "tgn:placetype":[
        "aat:300008798"
    ]
},
  "bbox": [],
  "geometry": {"coordinates":[-72.85,43.45],"type":"Point"}
}