{
  "id": 2319427,
  "type": "Feature",
  "properties": {
    "tgn:hierarchy":[
        "tgn:2319427",
        "tgn:1000001",
        "tgn:7012149",
        "tgn:2002371",
        "tgn:7007923",
        "tgn:7029392"
    ],
    "tgn:id":2319427,
    "tgn:name":"Ethete Saint Michael Mission",
    "tgn:placetype":[
        "aat:300008347"
    ]
},
  "bbox": [],
  "geometry": {"coordinates":[-108.7667,43.0167],"type":"Point"}
}