{
  "id": 2531696,
  "type": "Feature",
  "properties": {
    "tgn:hierarchy":[
        "tgn:2531696",
        "tgn:1000001",
        "tgn:2001093",
        "tgn:7012149",
        "tgn:7007522",
        "tgn:7029392"
    ],
    "tgn:id":2531696,
    "tgn:name":"Mullen Branch",
    "tgn:placetype":[
        "aat:300008699"
    ]
},
  "bbox": [],
  "geometry": {"coordinates":[-89.85,33.5333],"type":"Point"}
}