{
  "id": 1063610,
  "type": "Feature",
  "properties": {
    "tgn:hierarchy":[
        "tgn:1063610",
        "tgn:1000003",
        "tgn:1000405",
        "tgn:1000097",
        "tgn:7029392"
    ],
    "tgn:id":1063610,
    "tgn:name":"Skruv",
    "tgn:placetype":[
        "aat:300008347"
    ]
},
  "bbox": [],
  "geometry": {"coordinates":[15.3667,56.6833],"type":"Point"}
}