{
  "id": 7040875,
  "type": "Feature",
  "properties": {
    "tgn:hierarchy":[
        "tgn:7040875",
        "tgn:7002991",
        "tgn:1000003",
        "tgn:7002997",
        "tgn:1000080",
        "tgn:7029392"
    ],
    "tgn:id":7040875,
    "tgn:name":"San Tominaso",
    "tgn:placetype":[
        "aat:300008347"
    ]
},
  "bbox": [],
  "geometry": {"coordinates":[11.966667,46.383333],"type":"Point"}
}