{
  "id": 2314138,
  "type": "Feature",
  "properties": {
    "tgn:hierarchy":[
        "tgn:2314138",
        "tgn:1000001",
        "tgn:7012149",
        "tgn:7007157",
        "tgn:2000185",
        "tgn:7029392"
    ],
    "tgn:id":2314138,
    "tgn:name":"Elk Creek",
    "tgn:placetype":[
        "aat:300008706"
    ]
},
  "bbox": [],
  "geometry": {"coordinates":[-123.3167,39.4833],"type":"Point"}
}