{
  "id": 2652621,
  "type": "Feature",
  "properties": {
    "tgn:hierarchy":[
        "tgn:2652621",
        "tgn:1000001",
        "tgn:7012149",
        "tgn:1002594",
        "tgn:7007920",
        "tgn:7029392"
    ],
    "tgn:id":2652621,
    "tgn:name":"Sep Creek",
    "tgn:placetype":[
        "aat:300008706"
    ]
},
  "bbox": [],
  "geometry": {"coordinates":[-123.1167,46.4333],"type":"Point"}
}