{
  "id": 2203137,
  "type": "Feature",
  "properties": {
    "tgn:hierarchy":[
        "tgn:2203137",
        "tgn:1000001",
        "tgn:2001471",
        "tgn:7012149",
        "tgn:7007709",
        "tgn:7029392"
    ],
    "tgn:id":2203137,
    "tgn:name":"Buckhorn Branch",
    "tgn:placetype":[
        "aat:300008699"
    ]
},
  "bbox": [],
  "geometry": {"coordinates":[-78.8167,34.5667],"type":"Point"}
}