{
  "id": 7394452,
  "type": "Feature",
  "properties": {
    "tgn:hierarchy":[
        "tgn:7394452",
        "tgn:1000001",
        "tgn:1001960",
        "tgn:7005560",
        "tgn:7029392"
    ],
    "tgn:id":7394452,
    "tgn:name":"San Carlos",
    "tgn:placetype":[
        "aat:300008347"
    ]
},
  "bbox": [],
  "geometry": {"coordinates":[-111.416667,28.883333],"type":"Point"}
}