{
  "id": 7181676,
  "type": "Feature",
  "properties": {
    "tgn:hierarchy":[
        "tgn:7181676",
        "tgn:1000003",
        "tgn:7003677",
        "tgn:7000084",
        "tgn:7029392"
    ],
    "tgn:id":7181676,
    "tgn:name":"Bahnhof Garbeck",
    "tgn:placetype":[
        "aat:300007783"
    ]
},
  "bbox": [],
  "geometry": {"coordinates":[7.839444,51.321944],"type":"Point"}
}