{
  "id": 2552692,
  "type": "Feature",
  "properties": {
    "tgn:hierarchy":[
        "tgn:2552692",
        "tgn:1000001",
        "tgn:7012149",
        "tgn:2002267",
        "tgn:7013961",
        "tgn:7029392"
    ],
    "tgn:id":2552692,
    "tgn:name":"Nutter Run",
    "tgn:placetype":[
        "aat:300008699"
    ]
},
  "bbox": [],
  "geometry": {"coordinates":[-80.3333,39.2333],"type":"Point"}
}