{
  "id": 2108748,
  "type": "Feature",
  "properties": {
    "tgn:hierarchy":[
        "tgn:2108748",
        "tgn:1000001",
        "tgn:2002109",
        "tgn:7012149",
        "tgn:7007827",
        "tgn:7029392"
    ],
    "tgn:id":2108748,
    "tgn:name":"Cannonville",
    "tgn:placetype":[
        "aat:300008347"
    ]
},
  "bbox": [],
  "geometry": {"coordinates":[-112.05,37.5667],"type":"Point"}
}