{
  "id": 7432094,
  "type": "Feature",
  "properties": {
    "tgn:hierarchy":[
        "tgn:7432094",
        "tgn:1001835",
        "tgn:1000001",
        "tgn:7005560",
        "tgn:7029392"
    ],
    "tgn:id":7432094,
    "tgn:name":"San Jos\u00e9, Ensenada",
    "tgn:placetype":[
        "aat:300132316"
    ]
},
  "bbox": [],
  "geometry": {"coordinates":[-112.833333,28.333333],"type":"Point"}
}