{
  "id": 7423901,
  "type": "Feature",
  "properties": {
    "tgn:hierarchy":[
        "tgn:7423901",
        "tgn:1000001",
        "tgn:7005601",
        "tgn:7005560",
        "tgn:7029392"
    ],
    "tgn:id":7423901,
    "tgn:name":"La Noria Vieja",
    "tgn:placetype":[
        "aat:300008347"
    ]
},
  "bbox": [],
  "geometry": {"coordinates":[-101.516667,22.533333],"type":"Point"}
}