<<<<<<< HEAD
{
  "id": 2157058,
  "type": "Feature",
  "properties": {
    "tgn:hierarchy":[
        "tgn:2157058",
        "tgn:1000001",
        "tgn:7012149",
        "tgn:2001216",
        "tgn:7007523",
        "tgn:7029392"
    ],
    "tgn:id":2157058,
    "tgn:name":"Beaver Branch",
    "tgn:placetype":[
        "aat:300008699"
    ]
},
  "bbox": [],
  "geometry": {"coordinates":[-94.4,36.7333],"type":"Point"}
}
=======
{"geometry":{"type":"Point","coordinates":[-94.400000,36.733300]},"type":"Feature","properties":{"hierarchy":["tgn:2157058","tgn:1000001","tgn:7012149","tgn:2001216","tgn:7007523","tgn:7029392"],"placetype":["aat:300008699"],"id":2157058,"name:xx":"Beaver Branch"}}
>>>>>>> 03f74aca74312dbeaf24d7e61306dd6a786dc3d0
