{
  "id": 2080666,
  "type": "Feature",
  "properties": {
    "tgn:hierarchy":[
        "tgn:2080666",
        "tgn:1000001",
        "tgn:7012149",
        "tgn:1003007",
        "tgn:7007706",
        "tgn:7029392"
    ],
    "tgn:id":2080666,
    "tgn:name":"Maysville",
    "tgn:placetype":[
        "aat:300008347"
    ]
},
  "bbox": [],
  "geometry": {"coordinates":[-81.7833,40.6833],"type":"Point"}
}