{
  "id": 7558026,
  "type": "Feature",
  "properties": {
    "tgn:hierarchy":[
        "tgn:7558026",
        "tgn:1000004",
        "tgn:1001832",
        "tgn:7000198",
        "tgn:7029392"
    ],
    "tgn:id":7558026,
    "tgn:name:en":"P\u0101niputa",
    "tgn:placetype":[
        "aat:300008347"
    ]
},
  "bbox": [],
  "geometry": {"coordinates":[92.775476,26.835766],"type":"Point"}
}