{
  "id": 2213791,
  "type": "Feature",
  "properties": {
    "tgn:hierarchy":[
        "tgn:2213791",
        "tgn:7006450",
        "tgn:1000001",
        "tgn:2124076",
        "tgn:7012149",
        "tgn:7029392"
    ],
    "tgn:id":2213791,
    "tgn:name":"Cactus Point",
    "tgn:placetype":[
        "aat:300008850"
    ]
},
  "bbox": [],
  "geometry": {"coordinates":[-130.9333,55.55],"type":"Point"}
}