{
  "id": 7543523,
  "type": "Feature",
  "properties": {
    "tgn:hierarchy":[
        "tgn:7543523",
        "tgn:7001242",
        "tgn:7016833",
        "tgn:7001335",
        "tgn:7029392"
    ],
    "tgn:id":7543523,
    "tgn:name:en":"El Fitat",
    "tgn:placetype":[
        "aat:300008347"
    ]
},
  "bbox": [],
  "geometry": {"coordinates":[34.090569,31.112508],"type":"Point"}
}