{
  "id": 2749846,
  "type": "Feature",
  "properties": {
    "tgn:hierarchy":[
        "tgn:2749846",
        "tgn:2001170",
        "tgn:1000001",
        "tgn:7012149",
        "tgn:7007523",
        "tgn:7029392"
    ],
    "tgn:id":2749846,
    "tgn:name":"Walnut Ridge",
    "tgn:placetype":[
        "aat:300266640"
    ]
},
  "bbox": [],
  "geometry": {"coordinates":[-93.7667,36.5667],"type":"Point"}
}