{
  "id": 1090772,
  "type": "Feature",
  "properties": {
    "tgn:hierarchy":[
        "tgn:1090772",
        "tgn:7001242",
        "tgn:7000556",
        "tgn:1000173",
        "tgn:7029392"
    ],
    "tgn:id":1090772,
    "tgn:name":"Ambohimahamasina",
    "tgn:placetype":[
        "aat:300008347"
    ]
},
  "bbox": [],
  "geometry": {"coordinates":[47.1833,-21.9333],"type":"Point"}
}