{
  "id": 2172057,
  "type": "Feature",
  "properties": {
    "tgn:hierarchy":[
        "tgn:2172057",
        "tgn:1000001",
        "tgn:7012149",
        "tgn:2002326",
        "tgn:7007922",
        "tgn:7029392"
    ],
    "tgn:id":2172057,
    "tgn:name":"Bigelow Hill",
    "tgn:placetype":[
        "aat:300008798"
    ]
},
  "bbox": [],
  "geometry": {"coordinates":[-90.2333,43.15],"type":"Point"}
}