{
  "id": 7286943,
  "type": "Feature",
  "properties": {
    "tgn:hierarchy":[
        "tgn:7286943",
        "tgn:1001657",
        "tgn:1000049",
        "tgn:1000002",
        "tgn:7029392"
    ],
    "tgn:id":7286943,
    "tgn:name":"Cencerro, Paso del",
    "tgn:placetype":[
        "aat:300259572"
    ]
},
  "bbox": [],
  "geometry": {"coordinates":[-70.25,-31.983333],"type":"Point"}
}