<<<<<<< HEAD
{
  "id": 7373364,
  "type": "Feature",
  "properties": {
    "tgn:hierarchy":[
        "tgn:7373364",
        "tgn:7005580",
        "tgn:1000001",
        "tgn:7005560",
        "tgn:7029392"
    ],
    "tgn:id":7373364,
    "tgn:name":"La Libertad",
    "tgn:placetype":[
        "aat:300008347"
    ]
},
  "bbox": [],
  "geometry": {"coordinates":[-92.193611,14.591111],"type":"Point"}
}
=======
{"geometry":{"type":"Point","coordinates":[-92.193611,14.591111]},"type":"Feature","properties":{"hierarchy":["tgn:7373364","tgn:7005580","tgn:1000001","tgn:7005560","tgn:7029392"],"placetype":["aat:300008347"],"id":7373364,"name:xx":"La Libertad"}}
>>>>>>> 03f74aca74312dbeaf24d7e61306dd6a786dc3d0
