{
  "id": 2443885,
  "type": "Feature",
  "properties": {
    "tgn:hierarchy":[
        "tgn:2443885",
        "tgn:1000001",
        "tgn:7012149",
        "tgn:2001452",
        "tgn:7007566",
        "tgn:7029392"
    ],
    "tgn:id":2443885,
    "tgn:name":"La Plata Mine",
    "tgn:placetype":[
        "aat:300000390"
    ]
},
  "bbox": [],
  "geometry": {"coordinates":[-108.1833,36.9833],"type":"Point"}
}