{
  "id": 2614405,
  "type": "Feature",
  "properties": {
    "tgn:hierarchy":[
        "tgn:2614405",
        "tgn:1000001",
        "tgn:7012149",
        "tgn:2001930",
        "tgn:7007825",
        "tgn:7029392"
    ],
    "tgn:id":2614405,
    "tgn:name":"Reid Hill Branch",
    "tgn:placetype":[
        "aat:300008699"
    ]
},
  "bbox": [],
  "geometry": {"coordinates":[-86.8833,35.9167],"type":"Point"}
}