{
  "id": 7041587,
  "type": "Feature",
  "properties": {
    "tgn:hierarchy":[
        "tgn:7041587",
        "tgn:1003440",
        "tgn:1000003",
        "tgn:7003124",
        "tgn:1000080",
        "tgn:7029392"
    ],
    "tgn:id":7041587,
    "tgn:name":"San Giuseppe in Anterselva",
    "tgn:placetype":[
        "aat:300008347"
    ]
},
  "bbox": [],
  "geometry": {"coordinates":[12.130833,46.877222],"type":"Point"}
}