{
  "id": 5003394,
  "type": "Feature",
  "properties": {
    "tgn:hierarchy":[
        "tgn:5003394",
        "tgn:7002810",
        "tgn:7001158",
        "tgn:1000003",
        "tgn:1000095",
        "tgn:7029392"
    ],
    "tgn:id":5003394,
    "tgn:name":"Rebolledo de la Torre",
    "tgn:placetype":[
        "aat:300008347"
    ]
},
  "bbox": [],
  "geometry": {"coordinates":[-4.216667,42.683333],"type":"Point"}
}