<<<<<<< HEAD
{
  "id": 2334037,
  "type": "Feature",
  "properties": {
    "tgn:hierarchy":[
        "tgn:2334037",
        "tgn:1000001",
        "tgn:7012149",
        "tgn:2000834",
        "tgn:7007255",
        "tgn:7029392"
    ],
    "tgn:id":2334037,
    "tgn:name":"Ford Run",
    "tgn:placetype":[
        "aat:300008699"
    ]
},
  "bbox": [],
  "geometry": {"coordinates":[-86.6833,37.4],"type":"Point"}
}
=======
{"geometry":{"type":"Point","coordinates":[-86.683300,37.400000]},"type":"Feature","properties":{"hierarchy":["tgn:2334037","tgn:1000001","tgn:7012149","tgn:2000834","tgn:7007255","tgn:7029392"],"placetype":["aat:300008699"],"id":2334037,"name:xx":"Ford Run"}}
>>>>>>> 03f74aca74312dbeaf24d7e61306dd6a786dc3d0
