{
  "id": 7471022,
  "type": "Feature",
  "properties": {
    "tgn:hierarchy":[
        "tgn:7471022",
        "tgn:1000004",
        "tgn:7490934",
        "tgn:1000141",
        "tgn:7029392"
    ],
    "tgn:id":7471022,
    "tgn:name":"Jiugu",
    "tgn:placetype":[
        "aat:300008347"
    ]
},
  "bbox": [],
  "geometry": {"coordinates":[120.106667,23.103889],"type":"Point"}
}