{
  "id": 2566874,
  "type": "Feature",
  "properties": {
    "tgn:hierarchy":[
        "tgn:2566874",
        "tgn:1000001",
        "tgn:2001419",
        "tgn:7012149",
        "tgn:7007526",
        "tgn:7029392"
    ],
    "tgn:id":2566874,
    "tgn:name":"Panther Canyon",
    "tgn:placetype":[
        "aat:300008761"
    ]
},
  "bbox": [],
  "geometry": {"coordinates":[-118.1833,40.4333],"type":"Point"}
}