{
  "id": 2351463,
  "type": "Feature",
  "properties": {
    "tgn:hierarchy":[
        "tgn:2351463",
        "tgn:1000001",
        "tgn:2002313",
        "tgn:7012149",
        "tgn:7007922",
        "tgn:7029392"
    ],
    "tgn:id":2351463,
    "tgn:name":"Glen Lock Lake",
    "tgn:placetype":[
        "aat:300006191"
    ]
},
  "bbox": [],
  "geometry": {"coordinates":[-91.3833,44.95],"type":"Point"}
}