{
  "id": 1137557,
  "type": "Feature",
  "properties": {
    "tgn:hierarchy":[
        "tgn:1137557",
        "tgn:1000004",
        "tgn:7011459",
        "tgn:7014786",
        "tgn:7029392"
    ],
    "tgn:id":1137557,
    "tgn:name":"Yuzhnyy",
    "tgn:placetype":[
        "aat:300008347"
    ]
},
  "bbox": [],
  "geometry": {"coordinates":[72.95,49.3833],"type":"Point"}
}