<<<<<<< HEAD
{
  "id": 2259655,
  "type": "Feature",
  "properties": {
    "tgn:hierarchy":[
        "tgn:2259655",
        "tgn:1000001",
        "tgn:7012149",
        "tgn:2000488",
        "tgn:7007250",
        "tgn:7029392"
    ],
    "tgn:id":2259655,
    "tgn:name":"Cougar Canyon",
    "tgn:placetype":[
        "aat:300008761"
    ]
},
  "bbox": [],
  "geometry": {"coordinates":[-116.65,42.55],"type":"Point"}
}
=======
{"geometry":{"type":"Point","coordinates":[-116.650000,42.550000]},"type":"Feature","properties":{"hierarchy":["tgn:2259655","tgn:1000001","tgn:7012149","tgn:2000488","tgn:7007250","tgn:7029392"],"placetype":["aat:300008761"],"id":2259655,"name:xx":"Cougar Canyon"}}
>>>>>>> 03f74aca74312dbeaf24d7e61306dd6a786dc3d0
