{
  "id": 1107797,
  "type": "Feature",
  "properties": {
    "tgn:hierarchy":[
        "tgn:1107797",
        "tgn:1000001",
        "tgn:7012149",
        "tgn:2001714",
        "tgn:7007708",
        "tgn:7029392"
    ],
    "tgn:id":1107797,
    "tgn:name":"Yainax Butte",
    "tgn:placetype":[
        "aat:300008744"
    ]
},
  "bbox": [],
  "geometry": {"coordinates":[-121.2667,42.3167],"type":"Point"}
}