{
  "id": 7382471,
  "type": "Feature",
  "properties": {
    "tgn:hierarchy":[
        "tgn:7382471",
        "tgn:1000001",
        "tgn:7005594",
        "tgn:7005560",
        "tgn:7029392"
    ],
    "tgn:id":7382471,
    "tgn:name":"Palomas",
    "tgn:placetype":[
        "aat:300008347"
    ]
},
  "bbox": [],
  "geometry": {"coordinates":[-99.916667,22.466667],"type":"Point"}
}