{
  "id": 2410586,
  "type": "Feature",
  "properties": {
    "tgn:hierarchy":[
        "tgn:2410586",
        "tgn:1000001",
        "tgn:7012149",
        "tgn:2000488",
        "tgn:7007250",
        "tgn:7029392"
    ],
    "tgn:id":2410586,
    "tgn:name":"Indian Cove",
    "tgn:placetype":[
        "aat:300008761"
    ]
},
  "bbox": [],
  "geometry": {"coordinates":[-115.5333,42.8833],"type":"Point"}
}