{
  "id": 1111162,
  "type": "Feature",
  "properties": {
    "tgn:hierarchy":[
        "tgn:1111162",
        "tgn:1000004",
        "tgn:1000118",
        "tgn:7029392"
    ],
    "tgn:id":1111162,
    "tgn:name":"Ghud\u0101d, W\u0101d\u012b al-",
    "tgn:placetype":[
        "aat:300387091"
    ]
},
  "bbox": [],
  "geometry": {"coordinates":[47.1667,30.8333],"type":"Point"}
}