{
  "id": 2700011,
  "type": "Feature",
  "properties": {
    "tgn:hierarchy":[
        "tgn:2700011",
        "tgn:1000001",
        "tgn:2000952",
        "tgn:7012149",
        "tgn:7007520",
        "tgn:7029392"
    ],
    "tgn:id":2700011,
    "tgn:name":"Stump Lake",
    "tgn:placetype":[
        "aat:300008680"
    ]
},
  "bbox": [],
  "geometry": {"coordinates":[-84.8667,46.35],"type":"Point"}
}