{
  "id": 1051203,
  "type": "Feature",
  "properties": {
    "tgn:hierarchy":[
        "tgn:1051203",
        "tgn:7011683",
        "tgn:1000004",
        "tgn:7006661",
        "tgn:7029392"
    ],
    "tgn:id":1051203,
    "tgn:name":"Charkesar",
    "tgn:placetype":[
        "aat:300008347"
    ]
},
  "bbox": [],
  "geometry": {"coordinates":[70.8667,41.0333],"type":"Point"}
}