{
  "id": 2219913,
  "type": "Feature",
  "properties": {
    "tgn:hierarchy":[
        "tgn:2219913",
        "tgn:1000001",
        "tgn:1002275",
        "tgn:7012149",
        "tgn:7007920",
        "tgn:7029392"
    ],
    "tgn:id":2219913,
    "tgn:name":"Canvasback Lake",
    "tgn:placetype":[
        "aat:300008680"
    ]
},
  "bbox": [],
  "geometry": {"coordinates":[-122.7667,45.8167],"type":"Point"}
}