{
  "id": 1066277,
  "type": "Feature",
  "properties": {
    "tgn:hierarchy":[
        "tgn:1066277",
        "tgn:1000004",
        "tgn:1002093",
        "tgn:1000108",
        "tgn:7029392"
    ],
    "tgn:id":1066277,
    "tgn:name":"Sinbaungwe",
    "tgn:placetype":[
        "aat:300008347"
    ]
},
  "bbox": [],
  "geometry": {"coordinates":[95.1667,19.7333],"type":"Point"}
}