{
  "id": 7569976,
  "type": "Feature",
  "properties": {
    "tgn:hierarchy":[
        "tgn:7569976",
        "tgn:1000004",
        "tgn:7000198",
        "tgn:7031786",
        "tgn:7029392"
    ],
    "tgn:id":7569976,
    "tgn:name:en":"Dev\u012bkhet",
    "tgn:placetype":[
        "aat:300008347"
    ]
},
  "bbox": [],
  "geometry": {"coordinates":[78.555833,29.91],"type":"Point"}
}