{
  "id": 2485676,
  "type": "Feature",
  "properties": {
    "tgn:hierarchy":[
        "tgn:2485676",
        "tgn:1002338",
        "tgn:1000001",
        "tgn:7012149",
        "tgn:7007516",
        "tgn:7029392"
    ],
    "tgn:id":2485676,
    "tgn:name":"Laytons Ditch",
    "tgn:placetype":[
        "aat:300006075"
    ]
},
  "bbox": [],
  "geometry": {"coordinates":[-75.7667,38.5167],"type":"Point"}
}