{
  "id": 2354476,
  "type": "Feature",
  "properties": {
    "tgn:hierarchy":[
        "tgn:2354476",
        "tgn:1000001",
        "tgn:7012149",
        "tgn:1002513",
        "tgn:7007252",
        "tgn:7029392"
    ],
    "tgn:id":2354476,
    "tgn:name":"Golf Brook",
    "tgn:placetype":[
        "aat:300008699"
    ]
},
  "bbox": [],
  "geometry": {"coordinates":[-84.9833,40.3667],"type":"Point"}
}