{
  "id": 2662790,
  "type": "Feature",
  "properties": {
    "tgn:hierarchy":[
        "tgn:2662790",
        "tgn:1000001",
        "tgn:7006451",
        "tgn:7012149",
        "tgn:2000103",
        "tgn:7029392"
    ],
    "tgn:id":2662790,
    "tgn:name":"Silent Basin",
    "tgn:placetype":[
        "aat:300386845"
    ]
},
  "bbox": [],
  "geometry": {"coordinates":[-113.05,34.65],"type":"Point"}
}