{
  "id": 7157205,
  "type": "Feature",
  "properties": {
    "tgn:hierarchy":[
        "tgn:7157205",
        "tgn:7000096",
        "tgn:1000003",
        "tgn:7000084",
        "tgn:7029392"
    ],
    "tgn:id":7157205,
    "tgn:name":"Klein Pinnowsee",
    "tgn:placetype":[
        "aat:300008680"
    ]
},
  "bbox": [],
  "geometry": {"coordinates":[13.583333,52.933333],"type":"Point"}
}