{
  "id": 2653367,
  "type": "Feature",
  "properties": {
    "tgn:hierarchy":[
        "tgn:2653367",
        "tgn:1000001",
        "tgn:2002109",
        "tgn:7012149",
        "tgn:7007827",
        "tgn:7029392"
    ],
    "tgn:id":2653367,
    "tgn:name":"Sevenmile Creek",
    "tgn:placetype":[
        "aat:300008706"
    ]
},
  "bbox": [],
  "geometry": {"coordinates":[-110.5833,37.6667],"type":"Point"}
}