{
  "id": 7459882,
  "type": "Feature",
  "properties": {
    "tgn:hierarchy":[
        "tgn:7459882",
        "tgn:7002444",
        "tgn:1000003",
        "tgn:7008094",
        "tgn:7008591",
        "tgn:7029392"
    ],
    "tgn:id":7459882,
    "tgn:name:en":"Old Rocks",
    "tgn:placetype":[
        "aat:300011692"
    ]
},
  "bbox": [],
  "geometry": {"coordinates":[-7.15,57.966667],"type":"Point"}
}