{
  "id": 1091615,
  "type": "Feature",
  "properties": {
    "tgn:hierarchy":[
        "tgn:1091615",
        "tgn:7001242",
        "tgn:1000902",
        "tgn:1000180",
        "tgn:7029392"
    ],
    "tgn:id":1091615,
    "tgn:name":"Mogincual",
    "tgn:placetype":[
        "aat:300008347"
    ]
},
  "bbox": [],
  "geometry": {"coordinates":[40.4833,-15.55],"type":"Point"}
}