<<<<<<< HEAD
{
  "id": 7111299,
  "type": "Feature",
  "properties": {
    "tgn:hierarchy":[
        "tgn:7111299",
        "tgn:1000003",
        "tgn:7003687",
        "tgn:7000084",
        "tgn:7029392"
    ],
    "tgn:id":7111299,
    "tgn:name":"Remkersleben",
    "tgn:placetype":[
        "aat:300008347"
    ]
},
  "bbox": [],
  "geometry": {"coordinates":[11.35,52.083333],"type":"Point"}
}
=======
{"geometry":{"type":"Point","coordinates":[11.350000,52.083333]},"type":"Feature","properties":{"hierarchy":["tgn:7111299","tgn:1000003","tgn:7003687","tgn:7000084","tgn:7029392"],"placetype":["aat:300008347"],"id":7111299,"name:xx":"Remkersleben"}}
>>>>>>> 03f74aca74312dbeaf24d7e61306dd6a786dc3d0
