{
  "id": 7482229,
  "type": "Feature",
  "properties": {
    "tgn:hierarchy":[
        "tgn:7482229",
        "tgn:1000004",
        "tgn:7492971",
        "tgn:1000141",
        "tgn:7029392"
    ],
    "tgn:id":7482229,
    "tgn:name":"Shepi",
    "tgn:placetype":[
        "aat:300008347"
    ]
},
  "bbox": [],
  "geometry": {"coordinates":[120.533612,22.509057],"type":"Point"}
}