{
  "id": 2122565,
  "type": "Feature",
  "properties": {
    "tgn:hierarchy":[
        "tgn:2122565",
        "tgn:1000001",
        "tgn:2002320",
        "tgn:7012149",
        "tgn:7007922",
        "tgn:7029392"
    ],
    "tgn:id":2122565,
    "tgn:name":"Truax",
    "tgn:placetype":[
        "aat:300387016"
    ]
},
  "bbox": [],
  "geometry": {"coordinates":[-91.5667,44.8333],"type":"Point"}
}