{
  "id": 2689910,
  "type": "Feature",
  "properties": {
    "tgn:hierarchy":[
        "tgn:2689910",
        "tgn:1000001",
        "tgn:7012149",
        "tgn:7007157",
        "tgn:2000187",
        "tgn:7029392"
    ],
    "tgn:id":2689910,
    "tgn:name":"Squirrel Creek Mine",
    "tgn:placetype":[
        "aat:300000390"
    ]
},
  "bbox": [],
  "geometry": {"coordinates":[-120.7167,39.7833],"type":"Point"}
}