{
  "id": 7032250,
  "type": "Feature",
  "properties": {
    "tgn:hierarchy":[
        "tgn:7032250",
        "tgn:7001680",
        "tgn:7001242",
        "tgn:1000184",
        "tgn:7029392"
    ],
    "tgn:id":7032250,
    "tgn:name:fr":"Saint-Fran\u00e7ois, Mornes de",
    "tgn:placetype":[
        "aat:300008798"
    ]
},
  "bbox": [],
  "geometry": {"coordinates":[55.65,-21.1166],"type":"Point"}
}