{
  "id": 2490834,
  "type": "Feature",
  "properties": {
    "tgn:hierarchy":[
        "tgn:2490834",
        "tgn:7023902",
        "tgn:1000001",
        "tgn:7012149",
        "tgn:7007249",
        "tgn:7029392"
    ],
    "tgn:id":2490834,
    "tgn:name":"Manowaialee Forest Reserve",
    "tgn:placetype":[
        "aat:300008863"
    ]
},
  "bbox": [],
  "geometry": {"coordinates":[-155.3167,19.9667],"type":"Point"}
}