<<<<<<< HEAD
{
  "id": 2256824,
  "type": "Feature",
  "properties": {
    "tgn:hierarchy":[
        "tgn:2256824",
        "tgn:1000001",
        "tgn:7012149",
        "tgn:7007157",
        "tgn:7014005",
        "tgn:7029392"
    ],
    "tgn:id":2256824,
    "tgn:name":"Corinthian Island",
    "tgn:placetype":[
        "aat:300008791"
    ]
},
  "bbox": [],
  "geometry": {"coordinates":[-122.45,37.8667],"type":"Point"}
}
=======
{"geometry":{"type":"Point","coordinates":[-122.450000,37.866700]},"type":"Feature","properties":{"hierarchy":["tgn:2256824","tgn:1000001","tgn:7012149","tgn:7007157","tgn:7014005","tgn:7029392"],"placetype":["aat:300008791"],"id":2256824,"name:xx":"Corinthian Island"}}
>>>>>>> 03f74aca74312dbeaf24d7e61306dd6a786dc3d0
