{
  "id": 2287966,
  "type": "Feature",
  "properties": {
    "tgn:hierarchy":[
        "tgn:2287966",
        "tgn:1000001",
        "tgn:7012149",
        "tgn:1002626",
        "tgn:7007826",
        "tgn:7029392"
    ],
    "tgn:id":2287966,
    "tgn:name":"Dingerville",
    "tgn:placetype":[
        "aat:300008347"
    ]
},
  "bbox": [],
  "geometry": {"coordinates":[-95.8333,31.0667],"type":"Point"}
}