{
  "id": 7007719,
  "type": "Feature",
  "properties": {
    "tgn:hierarchy":[
        "tgn:7007719",
        "tgn:1000003",
        "tgn:7024127",
        "tgn:7006366",
        "tgn:7029392"
    ],
    "tgn:id":7007719,
    "tgn:name":"Gorlice",
    "tgn:placetype":[
        "aat:300008347",
        "aat:300000835",
        "aat:300008375",
        "aat:300387302"
    ]
},
  "bbox": [],
  "geometry": {"coordinates":[21.1667,49.6667],"type":"Point"}
}