<<<<<<< HEAD
{
  "id": 7473737,
  "type": "Feature",
  "properties": {
    "tgn:hierarchy":[
        "tgn:7473737",
        "tgn:1000004",
        "tgn:1000959",
        "tgn:1000141",
        "tgn:7029392"
    ],
    "tgn:id":7473737,
    "tgn:name":"Zhong'an Daqiao",
    "tgn:placetype":[
        "aat:300007836"
    ]
},
  "bbox": [],
  "geometry": {"coordinates":[121.5275,24.971],"type":"Point"}
}
=======
{"geometry":{"type":"Point","coordinates":[121.527500,24.971000]},"type":"Feature","properties":{"hierarchy":["tgn:7473737","tgn:1000004","tgn:1000959","tgn:1000141","tgn:7029392"],"placetype":["aat:300007836"],"id":7473737,"name:xx":"Zhong'an Daqiao"}}
>>>>>>> 03f74aca74312dbeaf24d7e61306dd6a786dc3d0
