{
  "id": 7473737,
  "type": "Feature",
  "properties": {
    "tgn:hierarchy":[
        "tgn:7473737",
        "tgn:1000004",
        "tgn:1000959",
        "tgn:1000141",
        "tgn:7029392"
    ],
    "tgn:id":7473737,
    "tgn:name":"Zhong'an Daqiao",
    "tgn:placetype":[
        "aat:300007836"
    ]
},
  "bbox": [],
  "geometry": {"coordinates":[121.5275,24.971],"type":"Point"}
}