{
  "id": 2473731,
  "type": "Feature",
  "properties": {
    "tgn:hierarchy":[
        "tgn:2473731",
        "tgn:1000001",
        "tgn:7012149",
        "tgn:2000837",
        "tgn:7007255",
        "tgn:7029392"
    ],
    "tgn:id":2473731,
    "tgn:name":"Lower Field Branch",
    "tgn:placetype":[
        "aat:300008699"
    ]
},
  "bbox": [],
  "geometry": {"coordinates":[-82.45,37.2667],"type":"Point"}
}