{
  "id": 2632517,
  "type": "Feature",
  "properties": {
    "tgn:hierarchy":[
        "tgn:2632517",
        "tgn:1000001",
        "tgn:7012149",
        "tgn:7007825",
        "tgn:7029392"
    ],
    "tgn:id":2632517,
    "tgn:name":"Royster Creek",
    "tgn:placetype":[
        "aat:300008706"
    ]
},
  "bbox": [],
  "geometry": {"coordinates":[-89.9167,35.4167],"type":"Point"}
}