{
  "id": 1036813,
  "type": "Feature",
  "properties": {
    "tgn:hierarchy":[
        "tgn:1036813",
        "tgn:7000096",
        "tgn:1000003",
        "tgn:7000084",
        "tgn:7029392"
    ],
    "tgn:id":1036813,
    "tgn:name":"Gr\u00f6ben",
    "tgn:placetype":[
        "aat:300008347"
    ]
},
  "bbox": [],
  "geometry": {"coordinates":[13.166667,52.283333],"type":"Point"}
}