{
  "id": 7134640,
  "type": "Feature",
  "properties": {
    "tgn:hierarchy":[
        "tgn:7134640",
        "tgn:1000003",
        "tgn:7003688",
        "tgn:7000084",
        "tgn:7029392"
    ],
    "tgn:id":7134640,
    "tgn:name":"M\u00f6nkloh",
    "tgn:placetype":[
        "aat:300008347"
    ]
},
  "bbox": [],
  "geometry": {"coordinates":[9.783333,53.883333],"type":"Point"}
}