{
  "id": 2627500,
  "type": "Feature",
  "properties": {
    "tgn:hierarchy":[
        "tgn:2627500",
        "tgn:1000001",
        "tgn:7012149",
        "tgn:7029392"
    ],
    "tgn:id":2627500,
    "tgn:name":"Roger Smith Reservoir",
    "tgn:placetype":[
        "aat:300006191"
    ]
},
  "bbox": [],
  "geometry": {"coordinates":[-116.3333,41.9833],"type":"Point"}
}