{
  "id": 2430927,
  "type": "Feature",
  "properties": {
    "tgn:hierarchy":[
        "tgn:2430927",
        "tgn:7023902",
        "tgn:1000001",
        "tgn:7012149",
        "tgn:7007249",
        "tgn:7029392"
    ],
    "tgn:id":2430927,
    "tgn:name":"Kananaka",
    "tgn:placetype":[
        "aat:300055621"
    ]
},
  "bbox": [],
  "geometry": {"coordinates":[-155.6833,18.9167],"type":"Point"}
}