<<<<<<< HEAD
{
  "id": 7114863,
  "type": "Feature",
  "properties": {
    "tgn:hierarchy":[
        "tgn:7114863",
        "tgn:1000003",
        "tgn:7003688",
        "tgn:7000084",
        "tgn:7029392"
    ],
    "tgn:id":7114863,
    "tgn:name":"Olfhusum",
    "tgn:placetype":[
        "aat:300008347"
    ]
},
  "bbox": [],
  "geometry": {"coordinates":[8.666667,54.833333],"type":"Point"}
}
=======
{"geometry":{"type":"Point","coordinates":[8.666667,54.833333]},"type":"Feature","properties":{"hierarchy":["tgn:7114863","tgn:1000003","tgn:7003688","tgn:7000084","tgn:7029392"],"placetype":["aat:300008347"],"id":7114863,"name:xx":"Olfhusum"}}
>>>>>>> 03f74aca74312dbeaf24d7e61306dd6a786dc3d0
