{
  "id": 1090958,
  "type": "Feature",
  "properties": {
    "tgn:hierarchy":[
        "tgn:1090958",
        "tgn:7001242",
        "tgn:1001575",
        "tgn:1000173",
        "tgn:7029392"
    ],
    "tgn:id":1090958,
    "tgn:name":"Manja",
    "tgn:placetype":[
        "aat:300008347"
    ]
},
  "bbox": [],
  "geometry": {"coordinates":[44.3333,-21.4333],"type":"Point"}
}