{
  "id": 7419372,
  "type": "Feature",
  "properties": {
    "tgn:hierarchy":[
        "tgn:7419372",
        "tgn:1000001",
        "tgn:7005589",
        "tgn:7005560",
        "tgn:7029392"
    ],
    "tgn:id":7419372,
    "tgn:name:es":"Ca\u00f1ada Honda",
    "tgn:placetype":[
        "aat:300008347"
    ]
},
  "bbox": [],
  "geometry": {"coordinates":[-100.605556,27.195833],"type":"Point"}
}