<<<<<<< HEAD
{
  "id": 2404965,
  "type": "Feature",
  "properties": {
    "tgn:hierarchy":[
        "tgn:2404965",
        "tgn:1000001",
        "tgn:7012149",
        "tgn:2001277",
        "tgn:7007524",
        "tgn:7029392"
    ],
    "tgn:id":2404965,
    "tgn:name":"Hudson Bay Creek",
    "tgn:placetype":[
        "aat:300008706"
    ]
},
  "bbox": [],
  "geometry": {"coordinates":[-113.5333,48.5667],"type":"Point"}
}
=======
{"geometry":{"type":"Point","coordinates":[-113.533300,48.566700]},"type":"Feature","properties":{"hierarchy":["tgn:2404965","tgn:1000001","tgn:7012149","tgn:2001277","tgn:7007524","tgn:7029392"],"placetype":["aat:300008706"],"id":2404965,"name:xx":"Hudson Bay Creek"}}
>>>>>>> 03f74aca74312dbeaf24d7e61306dd6a786dc3d0
