{
  "id": 2690988,
  "type": "Feature",
  "properties": {
    "tgn:hierarchy":[
        "tgn:2690988",
        "tgn:1000001",
        "tgn:7012149",
        "tgn:2000219",
        "tgn:7007158",
        "tgn:7029392"
    ],
    "tgn:id":2690988,
    "tgn:name":"Stanley Creek",
    "tgn:placetype":[
        "aat:300008706"
    ]
},
  "bbox": [],
  "geometry": {"coordinates":[-105.35,37.65],"type":"Point"}
}