{
  "id": 2514457,
  "type": "Feature",
  "properties": {
    "tgn:hierarchy":[
        "tgn:2514457",
        "tgn:1000001",
        "tgn:2001260",
        "tgn:7012149",
        "tgn:7007524",
        "tgn:7029392"
    ],
    "tgn:id":2514457,
    "tgn:name":"Miller Ditch",
    "tgn:placetype":[
        "aat:300006075"
    ]
},
  "bbox": [],
  "geometry": {"coordinates":[-113.4667,45.4833],"type":"Point"}
}