{
  "id": 7432014,
  "type": "Feature",
  "properties": {
    "tgn:hierarchy":[
        "tgn:7432014",
        "tgn:7005586",
        "tgn:1000001",
        "tgn:7005560",
        "tgn:7029392"
    ],
    "tgn:id":7432014,
    "tgn:name":"El Gavil\u00e1n de Abajo",
    "tgn:placetype":[
        "aat:300008347"
    ]
},
  "bbox": [],
  "geometry": {"coordinates":[-102.45,21.616667],"type":"Point"}
}