{
  "id": 2562791,
  "type": "Feature",
  "properties": {
    "tgn:hierarchy":[
        "tgn:2562791",
        "tgn:1000001",
        "tgn:7012149",
        "tgn:1002451",
        "tgn:7007919",
        "tgn:7029392"
    ],
    "tgn:id":2562791,
    "tgn:name":"Overhill Lake",
    "tgn:placetype":[
        "aat:300006191"
    ]
},
  "bbox": [],
  "geometry": {"coordinates":[-77.55,37.6833],"type":"Point"}
}