{
  "id": 2692725,
  "type": "Feature",
  "properties": {
    "tgn:hierarchy":[
        "tgn:2692725",
        "tgn:1000001",
        "tgn:7012149",
        "tgn:1002778",
        "tgn:7007255",
        "tgn:7029392"
    ],
    "tgn:id":2692725,
    "tgn:name":"Steel Creek",
    "tgn:placetype":[
        "aat:300008706"
    ]
},
  "bbox": [],
  "geometry": {"coordinates":[-84.3167,38.75],"type":"Point"}
}