{
  "id": 2675844,
  "type": "Feature",
  "properties": {
    "tgn:hierarchy":[
        "tgn:2675844",
        "tgn:1000001",
        "tgn:7012149",
        "tgn:2001289",
        "tgn:7007524",
        "tgn:7029392"
    ],
    "tgn:id":2675844,
    "tgn:name":"Songster Butte Mine",
    "tgn:placetype":[
        "aat:300000390"
    ]
},
  "bbox": [],
  "geometry": {"coordinates":[-111.1833,46.8333],"type":"Point"}
}