{
  "id": 1053157,
  "type": "Feature",
  "properties": {
    "tgn:hierarchy":[
        "tgn:1053157",
        "tgn:7011626",
        "tgn:1000004",
        "tgn:7014835",
        "tgn:7029392"
    ],
    "tgn:id":1053157,
    "tgn:name":"Bunay",
    "tgn:placetype":[
        "aat:300008347"
    ]
},
  "bbox": [],
  "geometry": {"coordinates":[71.5333,38.4333],"type":"Point"}
}