{
  "id": 2311007,
  "type": "Feature",
  "properties": {
    "tgn:hierarchy":[
        "tgn:2311007",
        "tgn:1000001",
        "tgn:7016172",
        "tgn:7012149",
        "tgn:2000155",
        "tgn:7029392"
    ],
    "tgn:id":2311007,
    "tgn:name":"Eden Falls Cave",
    "tgn:placetype":[
        "aat:300008746"
    ]
},
  "bbox": [],
  "geometry": {"coordinates":[-93.3833,36.0167],"type":"Point"}
}