<<<<<<< HEAD
{
  "id": 7364119,
  "type": "Feature",
  "properties": {
    "tgn:hierarchy":[
        "tgn:7364119",
        "tgn:1000001",
        "tgn:7005593",
        "tgn:7005560",
        "tgn:7029392"
    ],
    "tgn:id":7364119,
    "tgn:name":"El Bat\u00e1n",
    "tgn:placetype":[
        "aat:300008347"
    ]
},
  "bbox": [],
  "geometry": {"coordinates":[-100.416667,20.5],"type":"Point"}
}
=======
{"geometry":{"type":"Point","coordinates":[-100.416667,20.500000]},"type":"Feature","properties":{"hierarchy":["tgn:7364119","tgn:1000001","tgn:7005593","tgn:7005560","tgn:7029392"],"placetype":["aat:300008347"],"id":7364119,"name:xx":"El Bat\u00e1n"}}
>>>>>>> 03f74aca74312dbeaf24d7e61306dd6a786dc3d0
