{
  "id": 2526173,
  "type": "Feature",
  "properties": {
    "tgn:hierarchy":[
        "tgn:2526173",
        "tgn:1000001",
        "tgn:7012149",
        "tgn:2001718",
        "tgn:7007708",
        "tgn:7029392"
    ],
    "tgn:id":2526173,
    "tgn:name":"Mosquito Mountain",
    "tgn:placetype":[
        "aat:300008798"
    ]
},
  "bbox": [],
  "geometry": {"coordinates":[-118.0333,43.5833],"type":"Point"}
}