<<<<<<< HEAD
{
  "id": 2409309,
  "type": "Feature",
  "properties": {
    "tgn:hierarchy":[
        "tgn:2409309",
        "tgn:7006450",
        "tgn:1000001",
        "tgn:7012149",
        "tgn:7019760",
        "tgn:7029392"
    ],
    "tgn:id":2409309,
    "tgn:name":"Icy Point",
    "tgn:placetype":[
        "aat:300008850"
    ]
},
  "bbox": [],
  "geometry": {"coordinates":[-137.0833,58.3833],"type":"Point"}
}
=======
{"geometry":{"type":"Point","coordinates":[-137.083300,58.383300]},"type":"Feature","properties":{"hierarchy":["tgn:2409309","tgn:7006450","tgn:1000001","tgn:7012149","tgn:7019760","tgn:7029392"],"placetype":["aat:300008850"],"id":2409309,"name:xx":"Icy Point"}}
>>>>>>> 03f74aca74312dbeaf24d7e61306dd6a786dc3d0
