{
  "id": 7219761,
  "type": "Feature",
  "properties": {
    "tgn:hierarchy":[
        "tgn:7219761",
        "tgn:7011170",
        "tgn:7002715",
        "tgn:1000003",
        "tgn:1000074",
        "tgn:7029392"
    ],
    "tgn:id":7219761,
    "tgn:name":"Viston\u00eds, L\u00edmni",
    "tgn:placetype":[
        "aat:300008680"
    ]
},
  "bbox": [],
  "geometry": {"coordinates":[25.116667,41.05],"type":"Point"}
}