{
  "id": 7549220,
  "type": "Feature",
  "properties": {
    "tgn:hierarchy":[
        "tgn:7549220",
        "tgn:1000004",
        "tgn:7000198",
        "tgn:7001797",
        "tgn:7029392"
    ],
    "tgn:id":7549220,
    "tgn:name:en":"Egmore",
    "tgn:placetype":[
        "aat:300000745"
    ]
},
  "bbox": [],
  "geometry": {"coordinates":[80.255556,13.071667],"type":"Point"}
}