{
  "id": 2747521,
  "type": "Feature",
  "properties": {
    "tgn:hierarchy":[
        "tgn:2747521",
        "tgn:1002648",
        "tgn:1000001",
        "tgn:7019158",
        "tgn:7012149",
        "tgn:7007249",
        "tgn:7029392"
    ],
    "tgn:id":2747521,
    "tgn:name":"Waihee Ditch",
    "tgn:placetype":[
        "aat:300006075"
    ]
},
  "bbox": [],
  "geometry": {"coordinates":[-156.4833,20.8333],"type":"Point"}
}