{
  "id": 2693408,
  "type": "Feature",
  "properties": {
    "tgn:hierarchy":[
        "tgn:2693408",
        "tgn:1000001",
        "tgn:7012149",
        "tgn:2001711",
        "tgn:7007708",
        "tgn:7029392"
    ],
    "tgn:id":2693408,
    "tgn:name":"Steinman Creek",
    "tgn:placetype":[
        "aat:300008706"
    ]
},
  "bbox": [],
  "geometry": {"coordinates":[-122.5833,42.0833],"type":"Point"}
}