{
  "id": 7447603,
  "type": "Feature",
  "properties": {
    "tgn:hierarchy":[
        "tgn:7447603",
        "tgn:7002443",
        "tgn:1000003",
        "tgn:7018966",
        "tgn:7008591",
        "tgn:7029392"
    ],
    "tgn:id":7447603,
    "tgn:name:en":"Saint Donats",
    "tgn:placetype":[
        "aat:300008347"
    ]
},
  "bbox": [],
  "geometry": {"coordinates":[-3.528056,51.404444],"type":"Point"}
}