{
  "id": 2644170,
  "type": "Feature",
  "properties": {
    "tgn:hierarchy":[
        "tgn:2644170",
        "tgn:1000001",
        "tgn:7012149",
        "tgn:7007157",
        "tgn:1002608",
        "tgn:7029392"
    ],
    "tgn:id":2644170,
    "tgn:name":"Santa Ynez Lake",
    "tgn:placetype":[
        "aat:300008680"
    ]
},
  "bbox": [],
  "geometry": {"coordinates":[-118.55,34.0333],"type":"Point"}
}