{
  "id": 7380206,
  "type": "Feature",
  "properties": {
    "tgn:hierarchy":[
        "tgn:7380206",
        "tgn:1000001",
        "tgn:7005589",
        "tgn:7005560",
        "tgn:7029392"
    ],
    "tgn:id":7380206,
    "tgn:name":"Minas Viejas, Sierra de",
    "tgn:placetype":[
        "aat:300008795"
    ]
},
  "bbox": [],
  "geometry": {"coordinates":[-100.466667,26.083333],"type":"Point"}
}