{
  "id": 7336553,
  "type": "Feature",
  "properties": {
    "tgn:hierarchy":[
        "tgn:7336553",
        "tgn:7002804",
        "tgn:1000003",
        "tgn:7002793",
        "tgn:1000095",
        "tgn:7029392"
    ],
    "tgn:id":7336553,
    "tgn:name":"Fontilles",
    "tgn:placetype":[
        "aat:300008347"
    ]
},
  "bbox": [],
  "geometry": {"coordinates":[-0.083333,38.783333],"type":"Point"}
}