{
  "id": 7570769,
  "type": "Feature",
  "properties": {
    "tgn:hierarchy":[
        "tgn:7570769",
        "tgn:1000004",
        "tgn:1001869",
        "tgn:7000198",
        "tgn:7029392"
    ],
    "tgn:id":7570769,
    "tgn:name:en":"Hansthal Creek",
    "tgn:placetype":[
        "aat:300266571"
    ]
},
  "bbox": [],
  "geometry": {"coordinates":[70.366667,22.916667],"type":"Point"}
}