{
  "id": 2656434,
  "type": "Feature",
  "properties": {
    "tgn:hierarchy":[
        "tgn:2656434",
        "tgn:1000001",
        "tgn:7012149",
        "tgn:2001288",
        "tgn:7007524",
        "tgn:7029392"
    ],
    "tgn:id":2656434,
    "tgn:name":"Shedhorn Mountain",
    "tgn:placetype":[
        "aat:300008798"
    ]
},
  "bbox": [],
  "geometry": {"coordinates":[-111.4167,45.0833],"type":"Point"}
}