{
  "id": 2679767,
  "type": "Feature",
  "properties": {
    "tgn:hierarchy":[
        "tgn:2679767",
        "tgn:1000001",
        "tgn:7012149",
        "tgn:2001299",
        "tgn:7007524",
        "tgn:7029392"
    ],
    "tgn:id":2679767,
    "tgn:name":"South Fork Reservoir",
    "tgn:placetype":[
        "aat:300006191"
    ]
},
  "bbox": [],
  "geometry": {"coordinates":[-105.6667,46.8667],"type":"Point"}
}