{
  "id": 1032027,
  "type": "Feature",
  "properties": {
    "tgn:hierarchy":[
        "tgn:1032027",
        "tgn:7002870",
        "tgn:1000003",
        "tgn:1000070",
        "tgn:7029392"
    ],
    "tgn:id":1032027,
    "tgn:name":"Bartenheim",
    "tgn:placetype":[
        "aat:300008347"
    ]
},
  "bbox": [],
  "geometry": {"coordinates":[7.4833,47.6333],"type":"Point"}
}