{
  "id": 7056266,
  "type": "Feature",
  "properties": {
    "tgn:hierarchy":[
        "tgn:7056266",
        "tgn:1003510",
        "tgn:1000003",
        "tgn:7003120",
        "tgn:1000080",
        "tgn:7029392"
    ],
    "tgn:id":7056266,
    "tgn:name":"Piode",
    "tgn:placetype":[
        "aat:300008347"
    ]
},
  "bbox": [],
  "geometry": {"coordinates":[8.05,45.766667],"type":"Point"}
}