<<<<<<< HEAD
{
  "id": 2763398,
  "type": "Feature",
  "properties": {
    "tgn:hierarchy":[
        "tgn:2763398",
        "tgn:1000001",
        "tgn:7012149",
        "tgn:2000233",
        "tgn:7007158",
        "tgn:7029392"
    ],
    "tgn:id":2763398,
    "tgn:name":"Wetherill Mesa",
    "tgn:placetype":[
        "aat:300008798"
    ]
},
  "bbox": [],
  "geometry": {"coordinates":[-108.5333,37.2],"type":"Point"}
}
=======
{"geometry":{"type":"Point","coordinates":[-108.533300,37.200000]},"type":"Feature","properties":{"hierarchy":["tgn:2763398","tgn:1000001","tgn:7012149","tgn:2000233","tgn:7007158","tgn:7029392"],"placetype":["aat:300008798"],"id":2763398,"name:xx":"Wetherill Mesa"}}
>>>>>>> 03f74aca74312dbeaf24d7e61306dd6a786dc3d0
