{
  "id": 7263584,
  "type": "Feature",
  "properties": {
    "tgn:hierarchy":[
        "tgn:7263584",
        "tgn:7003615",
        "tgn:1000003",
        "tgn:7016845",
        "tgn:7029392"
    ],
    "tgn:id":7263584,
    "tgn:name:nl":"Johannes Posttocht",
    "tgn:placetype":[
        "aat:300006075"
    ]
},
  "bbox": [],
  "geometry": {"coordinates":[5.733333,52.65],"type":"Point"}
}