{
  "id": 7122961,
  "type": "Feature",
  "properties": {
    "tgn:hierarchy":[
        "tgn:7122961",
        "tgn:1000003",
        "tgn:7000094",
        "tgn:7000084",
        "tgn:7029392"
    ],
    "tgn:id":7122961,
    "tgn:name":"Neu Stuer",
    "tgn:placetype":[
        "aat:300008347"
    ]
},
  "bbox": [],
  "geometry": {"coordinates":[12.316667,53.366667],"type":"Point"}
}