{
  "id": 7095882,
  "type": "Feature",
  "properties": {
    "tgn:hierarchy":[
        "tgn:7095882",
        "tgn:1000003",
        "tgn:7003678",
        "tgn:7000084",
        "tgn:7029392"
    ],
    "tgn:id":7095882,
    "tgn:name":"Sch\u00f6nberg",
    "tgn:placetype":[
        "aat:300008777"
    ]
},
  "bbox": [],
  "geometry": {"coordinates":[9.466667,50.583333],"type":"Point"}
}