{
  "id": 2613289,
  "type": "Feature",
  "properties": {
    "tgn:hierarchy":[
        "tgn:2613289",
        "tgn:1000001",
        "tgn:7012149",
        "tgn:2001503",
        "tgn:7007709",
        "tgn:7029392"
    ],
    "tgn:id":2613289,
    "tgn:name":"Reed Cove",
    "tgn:placetype":[
        "aat:300008761"
    ]
},
  "bbox": [],
  "geometry": {"coordinates":[-82.7667,35.4333],"type":"Point"}
}