{
  "id": 2346626,
  "type": "Feature",
  "properties": {
    "tgn:hierarchy":[
        "tgn:2346626",
        "tgn:1000001",
        "tgn:7012149",
        "tgn:2002377",
        "tgn:7007923",
        "tgn:7029392"
    ],
    "tgn:id":2346626,
    "tgn:name":"Gaylord Reservoir",
    "tgn:placetype":[
        "aat:300006191"
    ]
},
  "bbox": [],
  "geometry": {"coordinates":[-107.0833,42.9333],"type":"Point"}
}