{
  "id": 2515594,
  "type": "Feature",
  "properties": {
    "tgn:hierarchy":[
        "tgn:2515594",
        "tgn:1002933",
        "tgn:1000001",
        "tgn:7012149",
        "tgn:7007239",
        "tgn:7029392"
    ],
    "tgn:id":2515594,
    "tgn:name":"Millsboro Pond",
    "tgn:placetype":[
        "aat:300006191"
    ]
},
  "bbox": [],
  "geometry": {"coordinates":[-75.2833,38.5833],"type":"Point"}
}