<<<<<<< HEAD
{
  "id": 2259390,
  "type": "Feature",
  "properties": {
    "tgn:hierarchy":[
        "tgn:2259390",
        "tgn:1000001",
        "tgn:7012149",
        "tgn:2000488",
        "tgn:7007250",
        "tgn:7029392"
    ],
    "tgn:id":2259390,
    "tgn:name":"Cottonwood Spring",
    "tgn:placetype":[
        "aat:300008697"
    ]
},
  "bbox": [],
  "geometry": {"coordinates":[-116.9,42.4167],"type":"Point"}
}
=======
{"geometry":{"type":"Point","coordinates":[-116.900000,42.416700]},"type":"Feature","properties":{"hierarchy":["tgn:2259390","tgn:1000001","tgn:7012149","tgn:2000488","tgn:7007250","tgn:7029392"],"placetype":["aat:300008697"],"id":2259390,"name:xx":"Cottonwood Spring"}}
>>>>>>> 03f74aca74312dbeaf24d7e61306dd6a786dc3d0
