{
  "id": 7059212,
  "type": "Feature",
  "properties": {
    "tgn:hierarchy":[
        "tgn:7059212",
        "tgn:1000001",
        "tgn:7004786",
        "tgn:7029392"
    ],
    "tgn:id":7059212,
    "tgn:name":"Belham River",
    "tgn:placetype":[
        "aat:300008699"
    ]
},
  "bbox": [],
  "geometry": {"coordinates":[-62.233,16.733],"type":"Point"}
}