<<<<<<< HEAD
{
  "id": 7059212,
  "type": "Feature",
  "properties": {
    "tgn:hierarchy":[
        "tgn:7059212",
        "tgn:1000001",
        "tgn:7004786",
        "tgn:7029392"
    ],
    "tgn:id":7059212,
    "tgn:name":"Belham River",
    "tgn:placetype":[
        "aat:300008699"
    ]
},
  "bbox": [],
  "geometry": {"coordinates":[-62.233,16.733],"type":"Point"}
}
=======
{"geometry":{"type":"Point","coordinates":[-62.233000,16.733000]},"type":"Feature","properties":{"hierarchy":["tgn:7059212","tgn:1000001","tgn:7004786","tgn:7029392"],"placetype":["aat:300008699"],"id":7059212,"name:xx":"Belham River"}}
>>>>>>> 03f74aca74312dbeaf24d7e61306dd6a786dc3d0
