{
  "id": 2262486,
  "type": "Feature",
  "properties": {
    "tgn:hierarchy":[
        "tgn:2262486",
        "tgn:1000001",
        "tgn:2000925",
        "tgn:7012149",
        "tgn:7007515",
        "tgn:7029392"
    ],
    "tgn:id":2262486,
    "tgn:name":"Cow Island",
    "tgn:placetype":[
        "aat:300008791"
    ]
},
  "bbox": [],
  "geometry": {"coordinates":[-69.3833,43.95],"type":"Point"}
}