<<<<<<< HEAD
{
  "id": 2159633,
  "type": "Feature",
  "properties": {
    "tgn:hierarchy":[
        "tgn:2159633",
        "tgn:1000001",
        "tgn:7012149",
        "tgn:7007157",
        "tgn:1002894",
        "tgn:7029392"
    ],
    "tgn:id":2159633,
    "tgn:name":"Bee Tree Borrow Pit",
    "tgn:placetype":[
        "aat:300000390"
    ]
},
  "bbox": [],
  "geometry": {"coordinates":[-120.8833,39.6167],"type":"Point"}
}
=======
{"geometry":{"type":"Point","coordinates":[-120.883300,39.616700]},"type":"Feature","properties":{"hierarchy":["tgn:2159633","tgn:1000001","tgn:7012149","tgn:7007157","tgn:1002894","tgn:7029392"],"placetype":["aat:300000390"],"id":2159633,"name:xx":"Bee Tree Borrow Pit"}}
>>>>>>> 03f74aca74312dbeaf24d7e61306dd6a786dc3d0
