{
  "id": 2655278,
  "type": "Feature",
  "properties": {
    "tgn:hierarchy":[
        "tgn:2655278",
        "tgn:1000001",
        "tgn:7012149",
        "tgn:7007252",
        "tgn:7029392"
    ],
    "tgn:id":2655278,
    "tgn:name":"Shanty Creek",
    "tgn:placetype":[
        "aat:300008706"
    ]
},
  "bbox": [],
  "geometry": {"coordinates":[-86.1833,40.35],"type":"Point"}
}