{
  "id": 2590443,
  "type": "Feature",
  "properties": {
    "tgn:hierarchy":[
        "tgn:2590443",
        "tgn:1000001",
        "tgn:1002664",
        "tgn:7012149",
        "tgn:7007159",
        "tgn:7029392"
    ],
    "tgn:id":2590443,
    "tgn:name":"Pole Bridge Brook",
    "tgn:placetype":[
        "aat:300008699"
    ]
},
  "bbox": [],
  "geometry": {"coordinates":[-72.5333,41.4667],"type":"Point"}
}