{
  "id": 2118024,
  "type": "Feature",
  "properties": {
    "tgn:hierarchy":[
        "tgn:2118024",
        "tgn:1000001",
        "tgn:7012149",
        "tgn:2002273",
        "tgn:7013961",
        "tgn:7029392"
    ],
    "tgn:id":2118024,
    "tgn:name":"Dobra",
    "tgn:placetype":[
        "aat:300008347"
    ]
},
  "bbox": [],
  "geometry": {"coordinates":[-81.8167,37.9333],"type":"Point"}
}