<<<<<<< HEAD
{
  "id": 7370710,
  "type": "Feature",
  "properties": {
    "tgn:hierarchy":[
        "tgn:7370710",
        "tgn:7005586",
        "tgn:1000001",
        "tgn:7005560",
        "tgn:7029392"
    ],
    "tgn:id":7370710,
    "tgn:name":"Gloria, Cerro la",
    "tgn:placetype":[
        "aat:300008795"
    ]
},
  "bbox": [],
  "geometry": {"coordinates":[-105.183333,20.466667],"type":"Point"}
}
=======
{"geometry":{"type":"Point","coordinates":[-105.183333,20.466667]},"type":"Feature","properties":{"hierarchy":["tgn:7370710","tgn:7005586","tgn:1000001","tgn:7005560","tgn:7029392"],"placetype":["aat:300008795"],"id":7370710,"name:xx":"Gloria, Cerro la"}}
>>>>>>> 03f74aca74312dbeaf24d7e61306dd6a786dc3d0
