<<<<<<< HEAD
{
  "id": 7357556,
  "type": "Feature",
  "properties": {
    "tgn:hierarchy":[
        "tgn:7357556",
        "tgn:7005581",
        "tgn:1000001",
        "tgn:7005560",
        "tgn:7029392"
    ],
    "tgn:id":7357556,
    "tgn:name":"Corralitos",
    "tgn:placetype":[
        "aat:300008347"
    ]
},
  "bbox": [],
  "geometry": {"coordinates":[-104.1,29.016667],"type":"Point"}
}
=======
{"geometry":{"type":"Point","coordinates":[-104.100000,29.016667]},"type":"Feature","properties":{"hierarchy":["tgn:7357556","tgn:7005581","tgn:1000001","tgn:7005560","tgn:7029392"],"placetype":["aat:300008347"],"id":7357556,"name:xx":"Corralitos"}}
>>>>>>> 03f74aca74312dbeaf24d7e61306dd6a786dc3d0
