{
  "id": 2045388,
  "type": "Feature",
  "properties": {
    "tgn:hierarchy":[
        "tgn:2045388",
        "tgn:1000001",
        "tgn:7012149",
        "tgn:2000930",
        "tgn:7007515",
        "tgn:7029392"
    ],
    "tgn:id":2045388,
    "tgn:name":"Pittsfield",
    "tgn:placetype":[
        "aat:300008347"
    ]
},
  "bbox": [],
  "geometry": {"coordinates":[-69.3833,44.7667],"type":"Point"}
}