<<<<<<< HEAD
{
  "id": 2706775,
  "type": "Feature",
  "properties": {
    "tgn:hierarchy":[
        "tgn:2706775",
        "tgn:1000001",
        "tgn:7012149",
        "tgn:2002053",
        "tgn:7007826",
        "tgn:7029392"
    ],
    "tgn:id":2706775,
    "tgn:name":"Swank Mountain",
    "tgn:placetype":[
        "aat:300008798"
    ]
},
  "bbox": [],
  "geometry": {"coordinates":[-98.3667,32.55],"type":"Point"}
}
=======
{"geometry":{"type":"Point","coordinates":[-98.366700,32.550000]},"type":"Feature","properties":{"hierarchy":["tgn:2706775","tgn:1000001","tgn:7012149","tgn:2002053","tgn:7007826","tgn:7029392"],"placetype":["aat:300008798"],"id":2706775,"name:xx":"Swank Mountain"}}
>>>>>>> 03f74aca74312dbeaf24d7e61306dd6a786dc3d0
