<<<<<<< HEAD
{
  "id": 2404910,
  "type": "Feature",
  "properties": {
    "tgn:hierarchy":[
        "tgn:2404910",
        "tgn:1000001",
        "tgn:7012149",
        "tgn:7007825",
        "tgn:7029392"
    ],
    "tgn:id":2404910,
    "tgn:name":"Huddleson Hollow",
    "tgn:placetype":[
        "aat:300008761"
    ]
},
  "bbox": [],
  "geometry": {"coordinates":[-85.7667,36.0833],"type":"Point"}
}
=======
{"geometry":{"type":"Point","coordinates":[-85.766700,36.083300]},"type":"Feature","properties":{"hierarchy":["tgn:2404910","tgn:1000001","tgn:7012149","tgn:7007825","tgn:7029392"],"placetype":["aat:300008761"],"id":2404910,"name:xx":"Huddleson Hollow"}}
>>>>>>> 03f74aca74312dbeaf24d7e61306dd6a786dc3d0
