{
  "id": 2132733,
  "type": "Feature",
  "properties": {
    "tgn:hierarchy":[
        "tgn:2132733",
        "tgn:7006450",
        "tgn:1000001",
        "tgn:2000071",
        "tgn:7012149",
        "tgn:7029392"
    ],
    "tgn:id":2132733,
    "tgn:name":"Anchor Point",
    "tgn:placetype":[
        "aat:300008850"
    ]
},
  "bbox": [],
  "geometry": {"coordinates":[-160.3167,58.9333],"type":"Point"}
}