{
  "id": 1082538,
  "type": "Feature",
  "properties": {
    "tgn:hierarchy":[
        "tgn:1082538",
        "tgn:1000004",
        "tgn:7000848",
        "tgn:1000125",
        "tgn:7029392"
    ],
    "tgn:id":1082538,
    "tgn:name":"Muang Yo",
    "tgn:placetype":[
        "aat:300008347"
    ]
},
  "bbox": [],
  "geometry": {"coordinates":[101.85,21.5167],"type":"Point"}
}