{
  "id": 2524529,
  "type": "Feature",
  "properties": {
    "tgn:hierarchy":[
        "tgn:2524529",
        "tgn:1000001",
        "tgn:7012149",
        "tgn:2001618",
        "tgn:7007706",
        "tgn:7029392"
    ],
    "tgn:id":2524529,
    "tgn:name":"Morganville",
    "tgn:placetype":[
        "aat:300008347"
    ]
},
  "bbox": [],
  "geometry": {"coordinates":[-81.95,39.6167],"type":"Point"}
}