{
  "id": 1048475,
  "type": "Feature",
  "properties": {
    "tgn:hierarchy":[
        "tgn:1048475",
        "tgn:7003644",
        "tgn:1000003",
        "tgn:1000088",
        "tgn:7029392"
    ],
    "tgn:id":1048475,
    "tgn:name":"Ballangen",
    "tgn:placetype":[
        "aat:300008347"
    ]
},
  "bbox": [],
  "geometry": {"coordinates":[16.8333,68.35],"type":"Point"}
}