{
  "id": 2603457,
  "type": "Feature",
  "properties": {
    "tgn:hierarchy":[
        "tgn:2603457",
        "tgn:1000001",
        "tgn:7016172",
        "tgn:7012149",
        "tgn:2000161",
        "tgn:7029392"
    ],
    "tgn:id":2603457,
    "tgn:name":"Queen Creek",
    "tgn:placetype":[
        "aat:300008706"
    ]
},
  "bbox": [],
  "geometry": {"coordinates":[-94.3667,34.65],"type":"Point"}
}