{
  "id": 2028889,
  "type": "Feature",
  "properties": {
    "tgn:hierarchy":[
        "tgn:2028889",
        "tgn:1000001",
        "tgn:2000504",
        "tgn:7012149",
        "tgn:7007251",
        "tgn:7029392"
    ],
    "tgn:id":2028889,
    "tgn:name":"Mabel",
    "tgn:placetype":[
        "aat:300387016"
    ]
},
  "bbox": [],
  "geometry": {"coordinates":[-87.6833,39.8667],"type":"Point"}
}