{
  "id": 2453183,
  "type": "Feature",
  "properties": {
    "tgn:hierarchy":[
        "tgn:2453183",
        "tgn:1000001",
        "tgn:2001472",
        "tgn:7012149",
        "tgn:7007709",
        "tgn:7029392"
    ],
    "tgn:id":2453183,
    "tgn:name":"Little Cawcaw Swamp",
    "tgn:placetype":[
        "aat:300008699"
    ]
},
  "bbox": [],
  "geometry": {"coordinates":[-78.5333,33.9167],"type":"Point"}
}