{
  "id": 7560231,
  "type": "Feature",
  "properties": {
    "tgn:hierarchy":[
        "tgn:7560231",
        "tgn:1000004",
        "tgn:7000198",
        "tgn:7016722",
        "tgn:7029392"
    ],
    "tgn:id":7560231,
    "tgn:name:en":"H\u012br\u0101nagar",
    "tgn:placetype":[
        "aat:300008347"
    ]
},
  "bbox": [],
  "geometry": {"coordinates":[79.587189,27.653161],"type":"Point"}
}