{
  "id": 2300274,
  "type": "Feature",
  "properties": {
    "tgn:hierarchy":[
        "tgn:2300274",
        "tgn:1000001",
        "tgn:7012149",
        "tgn:2002160",
        "tgn:7007919",
        "tgn:7029392"
    ],
    "tgn:id":2300274,
    "tgn:name":"Dugwell",
    "tgn:placetype":[
        "aat:300008347"
    ]
},
  "bbox": [],
  "geometry": {"coordinates":[-79.95,37.0333],"type":"Point"}
}