<<<<<<< HEAD
{
  "id": 2405356,
  "type": "Feature",
  "properties": {
    "tgn:hierarchy":[
        "tgn:2405356",
        "tgn:1000001",
        "tgn:7012149",
        "tgn:7007826",
        "tgn:7029392"
    ],
    "tgn:id":2405356,
    "tgn:name":"Huffstuttle Creek",
    "tgn:placetype":[
        "aat:300008706"
    ]
},
  "bbox": [],
  "geometry": {"coordinates":[-98.9,33.0],"type":"Point"}
}
=======
{"geometry":{"type":"Point","coordinates":[-98.900000,33.000000]},"type":"Feature","properties":{"hierarchy":["tgn:2405356","tgn:1000001","tgn:7012149","tgn:7007826","tgn:7029392"],"placetype":["aat:300008706"],"id":2405356,"name:xx":"Huffstuttle Creek"}}
>>>>>>> 03f74aca74312dbeaf24d7e61306dd6a786dc3d0
