{
  "id": 7139178,
  "type": "Feature",
  "properties": {
    "tgn:hierarchy":[
        "tgn:7139178",
        "tgn:7003692",
        "tgn:1000003",
        "tgn:7000084",
        "tgn:7029392"
    ],
    "tgn:id":7139178,
    "tgn:name":"Lautenb\u00e4chle",
    "tgn:placetype":[
        "aat:300387200"
    ]
},
  "bbox": [],
  "geometry": {"coordinates":[8.15,48.633333],"type":"Point"}
}