{
  "id": 1016036,
  "type": "Feature",
  "properties": {
    "tgn:hierarchy":[
        "tgn:1016036",
        "tgn:7005685",
        "tgn:1000001",
        "tgn:7005805",
        "tgn:7029392"
    ],
    "tgn:id":1016036,
    "tgn:name":"Montreal Lake",
    "tgn:placetype":[
        "aat:300008347"
    ]
},
  "bbox": [],
  "geometry": {"coordinates":[-105.8167,54.05],"type":"Point"}
}