{
  "id": 2306902,
  "type": "Feature",
  "properties": {
    "tgn:hierarchy":[
        "tgn:2306902",
        "tgn:1000001",
        "tgn:7012149",
        "tgn:1002521",
        "tgn:7007920",
        "tgn:7029392"
    ],
    "tgn:id":2306902,
    "tgn:name":"East Fork Kalaloch Creek",
    "tgn:placetype":[
        "aat:300008706"
    ]
},
  "bbox": [],
  "geometry": {"coordinates":[-124.2833,47.65],"type":"Point"}
}