{
  "id": 7225167,
  "type": "Feature",
  "properties": {
    "tgn:hierarchy":[
        "tgn:7225167",
        "tgn:7002690",
        "tgn:7012056",
        "tgn:1000003",
        "tgn:1000074",
        "tgn:7029392"
    ],
    "tgn:id":7225167,
    "tgn:name":"Petrok\u00e9falon",
    "tgn:placetype":[
        "aat:300008347"
    ]
},
  "bbox": [],
  "geometry": {"coordinates":[25.033333,35.25],"type":"Point"}
}