{
  "id": 2158091,
  "type": "Feature",
  "properties": {
    "tgn:hierarchy":[
        "tgn:2158091",
        "tgn:1000001",
        "tgn:7012149",
        "tgn:2001160",
        "tgn:7007522",
        "tgn:7029392"
    ],
    "tgn:id":2158091,
    "tgn:name":"Beaver Pond",
    "tgn:placetype":[
        "aat:300008680"
    ]
},
  "bbox": [],
  "geometry": {"coordinates":[-90.8333,32.1333],"type":"Point"}
}