<<<<<<< HEAD
{
  "id": 2158091,
  "type": "Feature",
  "properties": {
    "tgn:hierarchy":[
        "tgn:2158091",
        "tgn:1000001",
        "tgn:7012149",
        "tgn:2001160",
        "tgn:7007522",
        "tgn:7029392"
    ],
    "tgn:id":2158091,
    "tgn:name":"Beaver Pond",
    "tgn:placetype":[
        "aat:300008680"
    ]
},
  "bbox": [],
  "geometry": {"coordinates":[-90.8333,32.1333],"type":"Point"}
}
=======
{"geometry":{"type":"Point","coordinates":[-90.833300,32.133300]},"type":"Feature","properties":{"hierarchy":["tgn:2158091","tgn:1000001","tgn:7012149","tgn:2001160","tgn:7007522","tgn:7029392"],"placetype":["aat:300008680"],"id":2158091,"name:xx":"Beaver Pond"}}
>>>>>>> 03f74aca74312dbeaf24d7e61306dd6a786dc3d0
