{
  "id": 2010298,
  "type": "Feature",
  "properties": {
    "tgn:hierarchy":[
        "tgn:2010298",
        "tgn:1000001",
        "tgn:7012149",
        "tgn:7007157",
        "tgn:1002710",
        "tgn:7029392"
    ],
    "tgn:id":2010298,
    "tgn:name":"Boca",
    "tgn:placetype":[
        "aat:300387016"
    ]
},
  "bbox": [],
  "geometry": {"coordinates":[-120.0833,39.3833],"type":"Point"}
}