{
  "id": 7103673,
  "type": "Feature",
  "properties": {
    "tgn:hierarchy":[
        "tgn:7103673",
        "tgn:1000003",
        "tgn:7003676",
        "tgn:7000084",
        "tgn:7029392"
    ],
    "tgn:id":7103673,
    "tgn:name":"Sand-Kopf",
    "tgn:placetype":[
        "aat:300008777"
    ]
},
  "bbox": [],
  "geometry": {"coordinates":[10.316667,51.533333],"type":"Point"}
}