{
  "id": 2283211,
  "type": "Feature",
  "properties": {
    "tgn:hierarchy":[
        "tgn:2283211",
        "tgn:1000001",
        "tgn:7012149",
        "tgn:7007710",
        "tgn:7029392"
    ],
    "tgn:id":2283211,
    "tgn:name":"Delaware River Gorge",
    "tgn:placetype":[
        "aat:300008761"
    ]
},
  "bbox": [],
  "geometry": {"coordinates":[-75.35,41.9833],"type":"Point"}
}