{
  "id": 2434253,
  "type": "Feature",
  "properties": {
    "tgn:hierarchy":[
        "tgn:2434253",
        "tgn:1000001",
        "tgn:7012149",
        "tgn:1002677",
        "tgn:7007251",
        "tgn:7029392"
    ],
    "tgn:id":2434253,
    "tgn:name":"Kemper Landing",
    "tgn:placetype":[
        "aat:300008347"
    ]
},
  "bbox": [],
  "geometry": {"coordinates":[-90.2667,38.15],"type":"Point"}
}