{
  "id": 7503559,
  "type": "Feature",
  "properties": {
    "tgn:hierarchy":[
        "tgn:7503559",
        "tgn:1000004",
        "tgn:7491221",
        "tgn:1000141",
        "tgn:7029392"
    ],
    "tgn:id":7503559,
    "tgn:name":"Fengming Shan",
    "tgn:placetype":[
        "aat:300008798"
    ]
},
  "bbox": [],
  "geometry": {"coordinates":[121.253333,23.083611],"type":"Point"}
}