{
  "id": 2548801,
  "type": "Feature",
  "properties": {
    "tgn:hierarchy":[
        "tgn:2548801",
        "tgn:1000001",
        "tgn:7006451",
        "tgn:7012149",
        "tgn:2000103",
        "tgn:7029392"
    ],
    "tgn:id":2548801,
    "tgn:name":"North Pine Creek",
    "tgn:placetype":[
        "aat:300008706"
    ]
},
  "bbox": [],
  "geometry": {"coordinates":[-112.3667,34.2333],"type":"Point"}
}