{
  "id": 7142330,
  "type": "Feature",
  "properties": {
    "tgn:hierarchy":[
        "tgn:7142330",
        "tgn:1000003",
        "tgn:7003676",
        "tgn:7000084",
        "tgn:7029392"
    ],
    "tgn:id":7142330,
    "tgn:name":"Lohl-Berg",
    "tgn:placetype":[
        "aat:300008777"
    ]
},
  "bbox": [],
  "geometry": {"coordinates":[10.883333,52.083333],"type":"Point"}
}