{
  "id": 2189991,
  "type": "Feature",
  "properties": {
    "tgn:hierarchy":[
        "tgn:2189991",
        "tgn:1000001",
        "tgn:2000772",
        "tgn:7012149",
        "tgn:7007255",
        "tgn:7029392"
    ],
    "tgn:id":2189991,
    "tgn:name":"Bowling Creek",
    "tgn:placetype":[
        "aat:300008706"
    ]
},
  "bbox": [],
  "geometry": {"coordinates":[-83.4167,37.35],"type":"Point"}
}