<<<<<<< HEAD
{
  "id": 7470319,
  "type": "Feature",
  "properties": {
    "tgn:hierarchy":[
        "tgn:7470319",
        "tgn:1000004",
        "tgn:7467799",
        "tgn:1000141",
        "tgn:7029392"
    ],
    "tgn:id":7470319,
    "tgn:name":"Xizhuangzi",
    "tgn:placetype":[
        "aat:300008347"
    ]
},
  "bbox": [],
  "geometry": {"coordinates":[120.4442,23.8893],"type":"Point"}
}
=======
{"geometry":{"type":"Point","coordinates":[120.444200,23.889300]},"type":"Feature","properties":{"hierarchy":["tgn:7470319","tgn:1000004","tgn:7467799","tgn:1000141","tgn:7029392"],"placetype":["aat:300008347"],"id":7470319,"name:xx":"Xizhuangzi"}}
>>>>>>> 03f74aca74312dbeaf24d7e61306dd6a786dc3d0
