{
  "id": 7470319,
  "type": "Feature",
  "properties": {
    "tgn:hierarchy":[
        "tgn:7470319",
        "tgn:1000004",
        "tgn:7467799",
        "tgn:1000141",
        "tgn:7029392"
    ],
    "tgn:id":7470319,
    "tgn:name":"Xizhuangzi",
    "tgn:placetype":[
        "aat:300008347"
    ]
},
  "bbox": [],
  "geometry": {"coordinates":[120.4442,23.8893],"type":"Point"}
}