{
  "id": 2444194,
  "type": "Feature",
  "properties": {
    "tgn:hierarchy":[
        "tgn:2444194",
        "tgn:1000001",
        "tgn:2001810",
        "tgn:7012149",
        "tgn:7007713",
        "tgn:7029392"
    ],
    "tgn:id":2444194,
    "tgn:name":"Labrador Gulch",
    "tgn:placetype":[
        "aat:300008761"
    ]
},
  "bbox": [],
  "geometry": {"coordinates":[-103.85,44.35],"type":"Point"}
}