{
  "id": 2154257,
  "type": "Feature",
  "properties": {
    "tgn:hierarchy":[
        "tgn:2154257",
        "tgn:1000001",
        "tgn:2001432",
        "tgn:7012149",
        "tgn:7007566",
        "tgn:7029392"
    ],
    "tgn:id":2154257,
    "tgn:name":"Bear Creek",
    "tgn:placetype":[
        "aat:300008706"
    ]
},
  "bbox": [],
  "geometry": {"coordinates":[-105.0667,36.45],"type":"Point"}
}