{
  "id": 2436357,
  "type": "Feature",
  "properties": {
    "tgn:hierarchy":[
        "tgn:2436357",
        "tgn:1000001",
        "tgn:7012149",
        "tgn:7007157",
        "tgn:2000185",
        "tgn:7029392"
    ],
    "tgn:id":2436357,
    "tgn:name":"Kibbey Peak",
    "tgn:placetype":[
        "aat:300008798"
    ]
},
  "bbox": [],
  "geometry": {"coordinates":[-123.0333,39.3167],"type":"Point"}
}