{
  "id": 7093197,
  "type": "Feature",
  "properties": {
    "tgn:hierarchy":[
        "tgn:7093197",
        "tgn:7003669",
        "tgn:1000003",
        "tgn:7000084",
        "tgn:7029392"
    ],
    "tgn:id":7093197,
    "tgn:name":"Schweinhof",
    "tgn:placetype":[
        "aat:300008347"
    ]
},
  "bbox": [],
  "geometry": {"coordinates":[10.183333,50.35],"type":"Point"}
}