{
  "id": 7178311,
  "type": "Feature",
  "properties": {
    "tgn:hierarchy":[
        "tgn:7178311",
        "tgn:1000003",
        "tgn:7003676",
        "tgn:7000084",
        "tgn:7029392"
    ],
    "tgn:id":7178311,
    "tgn:name":"Haendorf",
    "tgn:placetype":[
        "aat:300008347"
    ]
},
  "bbox": [],
  "geometry": {"coordinates":[9.033333,52.783333],"type":"Point"}
}