{
  "id": 2026228,
  "type": "Feature",
  "properties": {
    "tgn:hierarchy":[
        "tgn:2026228",
        "tgn:1000001",
        "tgn:7012149",
        "tgn:2000489",
        "tgn:7007250",
        "tgn:7029392"
    ],
    "tgn:id":2026228,
    "tgn:name":"Washoe",
    "tgn:placetype":[
        "aat:300008347",
        "aat:300387210"
    ]
},
  "bbox": [],
  "geometry": {"coordinates":[-116.9333,44.05],"type":"Point"}
}