{
  "id": 2534849,
  "type": "Feature",
  "properties": {
    "tgn:hierarchy":[
        "tgn:2534849",
        "tgn:1000001",
        "tgn:7012149",
        "tgn:2001437",
        "tgn:7007566",
        "tgn:7029392"
    ],
    "tgn:id":2534849,
    "tgn:name":"Naiad Queen Mine",
    "tgn:placetype":[
        "aat:300000390"
    ]
},
  "bbox": [],
  "geometry": {"coordinates":[-108.0167,32.8333],"type":"Point"}
}