{
  "id": 2499114,
  "type": "Feature",
  "properties": {
    "tgn:hierarchy":[
        "tgn:2499114",
        "tgn:1000001",
        "tgn:7012149",
        "tgn:2001721",
        "tgn:7007708",
        "tgn:7029392"
    ],
    "tgn:id":2499114,
    "tgn:name":"McCarty Spring",
    "tgn:placetype":[
        "aat:300008697"
    ]
},
  "bbox": [],
  "geometry": {"coordinates":[-118.45,45.1833],"type":"Point"}
}