{
  "id": 1136402,
  "type": "Feature",
  "properties": {
    "tgn:hierarchy":[
        "tgn:1136402",
        "tgn:7005586",
        "tgn:1000001",
        "tgn:7005560",
        "tgn:7029392"
    ],
    "tgn:id":1136402,
    "tgn:name":"Venustiano Carranza",
    "tgn:placetype":[
        "aat:300008347"
    ]
},
  "bbox": [],
  "geometry": {"coordinates":[-103.783333,19.733333],"type":"Point"}
}