{
  "id": 2483585,
  "type": "Feature",
  "properties": {
    "tgn:hierarchy":[
        "tgn:2483585",
        "tgn:1000001",
        "tgn:7020676",
        "tgn:7012149",
        "tgn:7007256",
        "tgn:7029392"
    ],
    "tgn:id":2483585,
    "tgn:name":"Latania Bayou",
    "tgn:placetype":[
        "aat:300008699"
    ]
},
  "bbox": [],
  "geometry": {"coordinates":[-92.8333,29.9167],"type":"Point"}
}