{
  "id": 1090244,
  "type": "Feature",
  "properties": {
    "tgn:hierarchy":[
        "tgn:1090244",
        "tgn:7001242",
        "tgn:7000795",
        "tgn:1000167",
        "tgn:7029392"
    ],
    "tgn:id":1090244,
    "tgn:name":"Iri\u00e9",
    "tgn:placetype":[
        "aat:300008347"
    ]
},
  "bbox": [],
  "geometry": {"coordinates":[-9.1667,8.2667],"type":"Point"}
}