{
  "id": 7567610,
  "type": "Feature",
  "properties": {
    "tgn:hierarchy":[
        "tgn:7567610",
        "tgn:1000004",
        "tgn:7000198",
        "tgn:1001996",
        "tgn:7029392"
    ],
    "tgn:id":7567610,
    "tgn:name:en":"Dharer",
    "tgn:placetype":[
        "aat:300008347"
    ]
},
  "bbox": [],
  "geometry": {"coordinates":[77.012778,31.234444],"type":"Point"}
}