<<<<<<< HEAD
{
  "id": 2151580,
  "type": "Feature",
  "properties": {
    "tgn:hierarchy":[
        "tgn:2151580",
        "tgn:7006450",
        "tgn:1000001",
        "tgn:2124077",
        "tgn:7012149",
        "tgn:7029392"
    ],
    "tgn:id":2151580,
    "tgn:name":"Battery Point",
    "tgn:placetype":[
        "aat:300008850"
    ]
},
  "bbox": [],
  "geometry": {"coordinates":[-135.35,59.2],"type":"Point"}
}
=======
{"geometry":{"type":"Point","coordinates":[-135.350000,59.200000]},"type":"Feature","properties":{"hierarchy":["tgn:2151580","tgn:7006450","tgn:1000001","tgn:2124077","tgn:7012149","tgn:7029392"],"placetype":["aat:300008850"],"id":2151580,"name:xx":"Battery Point"}}
>>>>>>> 03f74aca74312dbeaf24d7e61306dd6a786dc3d0
