{
  "id": 2565497,
  "type": "Feature",
  "properties": {
    "tgn:hierarchy":[
        "tgn:2565497",
        "tgn:1000001",
        "tgn:7012149",
        "tgn:2000181",
        "tgn:7007157",
        "tgn:7029392"
    ],
    "tgn:id":2565497,
    "tgn:name":"Painter Gulch",
    "tgn:placetype":[
        "aat:300008761"
    ]
},
  "bbox": [],
  "geometry": {"coordinates":[-123.9333,40.7167],"type":"Point"}
}