<<<<<<< HEAD
{
  "id": 2152111,
  "type": "Feature",
  "properties": {
    "tgn:hierarchy":[
        "tgn:2152111",
        "tgn:1000001",
        "tgn:7012149",
        "tgn:1002599",
        "tgn:7007708",
        "tgn:7029392"
    ],
    "tgn:id":2152111,
    "tgn:name":"Baxter Creek",
    "tgn:placetype":[
        "aat:300008706"
    ]
},
  "bbox": [],
  "geometry": {"coordinates":[-123.95,45.0],"type":"Point"}
}
=======
{"geometry":{"type":"Point","coordinates":[-123.950000,45.000000]},"type":"Feature","properties":{"hierarchy":["tgn:2152111","tgn:1000001","tgn:7012149","tgn:1002599","tgn:7007708","tgn:7029392"],"placetype":["aat:300008706"],"id":2152111,"name:xx":"Baxter Creek"}}
>>>>>>> 03f74aca74312dbeaf24d7e61306dd6a786dc3d0
