{
  "id": 1013963,
  "type": "Feature",
  "properties": {
    "tgn:hierarchy":[
        "tgn:1013963",
        "tgn:7005685",
        "tgn:1000001",
        "tgn:7005734",
        "tgn:7029392"
    ],
    "tgn:id":1013963,
    "tgn:name":"Ninga",
    "tgn:placetype":[
        "aat:300008347"
    ]
},
  "bbox": [],
  "geometry": {"coordinates":[-99.8833,49.2167],"type":"Point"}
}