{
  "id": 7331109,
  "type": "Feature",
  "properties": {
    "tgn:hierarchy":[
        "tgn:7331109",
        "tgn:7008912",
        "tgn:7030216",
        "tgn:1000003",
        "tgn:1000095",
        "tgn:7029392"
    ],
    "tgn:id":7331109,
    "tgn:name":"Gualter",
    "tgn:placetype":[
        "aat:300008347"
    ]
},
  "bbox": [],
  "geometry": {"coordinates":[1.196232,41.932476],"type":"Point"}
}