{
  "id": 7146688,
  "type": "Feature",
  "properties": {
    "tgn:hierarchy":[
        "tgn:7146688",
        "tgn:7003669",
        "tgn:1000003",
        "tgn:7000084",
        "tgn:7029392"
    ],
    "tgn:id":7146688,
    "tgn:name":"Klosterstein",
    "tgn:placetype":[
        "aat:300008798"
    ]
},
  "bbox": [],
  "geometry": {"coordinates":[12.95,48.933333],"type":"Point"}
}