{
  "id": 7547035,
  "type": "Feature",
  "properties": {
    "tgn:hierarchy":[
        "tgn:7547035",
        "tgn:1000004",
        "tgn:7000198",
        "tgn:7016788",
        "tgn:7029392"
    ],
    "tgn:id":7547035,
    "tgn:name:en":"Arjansar",
    "tgn:placetype":[
        "aat:300007783"
    ]
},
  "bbox": [],
  "geometry": {"coordinates":[73.871478,28.930838],"type":"Point"}
}