{
  "id": 1106941,
  "type": "Feature",
  "properties": {
    "tgn:hierarchy":[
        "tgn:1106941",
        "tgn:7002445",
        "tgn:1000003",
        "tgn:7008154",
        "tgn:7008591",
        "tgn:7029392"
    ],
    "tgn:id":1106941,
    "tgn:name":"Ward's Stone",
    "tgn:placetype":[
        "aat:300006960",
        "aat:300008795"
    ]
},
  "bbox": [],
  "geometry": {"coordinates":[-2.633333,54.016667],"type":"Point"}
}