{
  "id": 2355560,
  "type": "Feature",
  "properties": {
    "tgn:hierarchy":[
        "tgn:2355560",
        "tgn:1000001",
        "tgn:7012149",
        "tgn:7007705",
        "tgn:7029392"
    ],
    "tgn:id":2355560,
    "tgn:name":"Goose Creek",
    "tgn:placetype":[
        "aat:300008706"
    ]
},
  "bbox": [],
  "geometry": {"coordinates":[-98.0833,47.9167],"type":"Point"}
}