{
  "id": 7420495,
  "type": "Feature",
  "properties": {
    "tgn:hierarchy":[
        "tgn:7420495",
        "tgn:7005584",
        "tgn:1000001",
        "tgn:7005560",
        "tgn:7029392"
    ],
    "tgn:id":7420495,
    "tgn:name":"La Quinta",
    "tgn:placetype":[
        "aat:300008347"
    ]
},
  "bbox": [],
  "geometry": {"coordinates":[-100.579167,21.398333],"type":"Point"}
}