{
  "id": 7562250,
  "type": "Feature",
  "properties": {
    "tgn:hierarchy":[
        "tgn:7562250",
        "tgn:1000004",
        "tgn:7000198",
        "tgn:7016722",
        "tgn:7029392"
    ],
    "tgn:id":7562250,
    "tgn:name:en":"Dhura",
    "tgn:placetype":[
        "aat:300008347"
    ]
},
  "bbox": [],
  "geometry": {"coordinates":[79.317243,27.048867],"type":"Point"}
}