{
  "id": 2101811,
  "type": "Feature",
  "properties": {
    "tgn:hierarchy":[
        "tgn:2101811",
        "tgn:1000001",
        "tgn:7012149",
        "tgn:2001886",
        "tgn:7007825",
        "tgn:7029392"
    ],
    "tgn:id":2101811,
    "tgn:name":"Three Oaks",
    "tgn:placetype":[
        "aat:300008347"
    ]
},
  "bbox": [],
  "geometry": {"coordinates":[-87.2667,35.35],"type":"Point"}
}