{
  "id": 7033269,
  "type": "Feature",
  "properties": {
    "tgn:hierarchy":[
        "tgn:7033269",
        "tgn:1003506",
        "tgn:1000003",
        "tgn:7002993",
        "tgn:1000080",
        "tgn:7029392"
    ],
    "tgn:id":7033269,
    "tgn:name":"Nogaredo",
    "tgn:placetype":[
        "aat:300008347"
    ]
},
  "bbox": [],
  "geometry": {"coordinates":[13.377778,45.913889],"type":"Point"}
}