{
  "id": 2179988,
  "type": "Feature",
  "properties": {
    "tgn:hierarchy":[
        "tgn:2179988",
        "tgn:1000001",
        "tgn:7012149",
        "tgn:2000481",
        "tgn:7007250",
        "tgn:7029392"
    ],
    "tgn:id":2179988,
    "tgn:name":"Blind Canyon",
    "tgn:placetype":[
        "aat:300008761"
    ]
},
  "bbox": [],
  "geometry": {"coordinates":[-112.8667,44.3333],"type":"Point"}
}