{
  "id": 7388214,
  "type": "Feature",
  "properties": {
    "tgn:hierarchy":[
        "tgn:7388214",
        "tgn:7005586",
        "tgn:1000001",
        "tgn:7005560",
        "tgn:7029392"
    ],
    "tgn:id":7388214,
    "tgn:name":"Puerto Grande, Cerro el",
    "tgn:placetype":[
        "aat:300008795"
    ]
},
  "bbox": [],
  "geometry": {"coordinates":[-104.966667,20.083333],"type":"Point"}
}