{
  "id": 7573167,
  "type": "Feature",
  "properties": {
    "tgn:hierarchy":[
        "tgn:7573167",
        "tgn:1000004",
        "tgn:7000198",
        "tgn:7016722",
        "tgn:7029392"
    ],
    "tgn:id":7573167,
    "tgn:name:en":"Jumna Bridge",
    "tgn:placetype":[
        "aat:300007783"
    ]
},
  "bbox": [],
  "geometry": {"coordinates":[78.045714,27.194782],"type":"Point"}
}