{
  "id": 2647850,
  "type": "Feature",
  "properties": {
    "tgn:hierarchy":[
        "tgn:2647850",
        "tgn:1000001",
        "tgn:7012149",
        "tgn:1002953",
        "tgn:7007255",
        "tgn:7029392"
    ],
    "tgn:id":2647850,
    "tgn:name":"Schoolhouse Branch",
    "tgn:placetype":[
        "aat:300008699"
    ]
},
  "bbox": [],
  "geometry": {"coordinates":[-85.3667,38.5667],"type":"Point"}
}