{
  "id": 7423989,
  "type": "Feature",
  "properties": {
    "tgn:hierarchy":[
        "tgn:7423989",
        "tgn:1000001",
        "tgn:7005588",
        "tgn:7005560",
        "tgn:7029392"
    ],
    "tgn:id":7423989,
    "tgn:name":"Los Pretiles",
    "tgn:placetype":[
        "aat:300008699"
    ]
},
  "bbox": [],
  "geometry": {"coordinates":[-105.008611,22.695],"type":"Point"}
}