{
  "id": 2363908,
  "type": "Feature",
  "properties": {
    "tgn:hierarchy":[
        "tgn:2363908",
        "tgn:1000001",
        "tgn:2001096",
        "tgn:7012149",
        "tgn:7007522",
        "tgn:7029392"
    ],
    "tgn:id":2363908,
    "tgn:name":"Green Meadow",
    "tgn:placetype":[
        "aat:300008347"
    ]
},
  "bbox": [],
  "geometry": {"coordinates":[-90.9667,31.95],"type":"Point"}
}