{
  "id": 2710234,
  "type": "Feature",
  "properties": {
    "tgn:hierarchy":[
        "tgn:2710234",
        "tgn:1000001",
        "tgn:7012149",
        "tgn:1002595",
        "tgn:7007826",
        "tgn:7029392"
    ],
    "tgn:id":2710234,
    "tgn:name":"Talley Lake",
    "tgn:placetype":[
        "aat:300008680"
    ]
},
  "bbox": [],
  "geometry": {"coordinates":[-94.8167,29.9333],"type":"Point"}
}