<<<<<<< HEAD
{
  "id": 2157213,
  "type": "Feature",
  "properties": {
    "tgn:hierarchy":[
        "tgn:2157213",
        "tgn:1000001",
        "tgn:7012149",
        "tgn:2000230",
        "tgn:7007158",
        "tgn:7029392"
    ],
    "tgn:id":2157213,
    "tgn:name":"Beaver Creek",
    "tgn:placetype":[
        "aat:300008706"
    ]
},
  "bbox": [],
  "geometry": {"coordinates":[-107.7,39.1833],"type":"Point"}
}
=======
{"geometry":{"type":"Point","coordinates":[-107.700000,39.183300]},"type":"Feature","properties":{"hierarchy":["tgn:2157213","tgn:1000001","tgn:7012149","tgn:2000230","tgn:7007158","tgn:7029392"],"placetype":["aat:300008706"],"id":2157213,"name:xx":"Beaver Creek"}}
>>>>>>> 03f74aca74312dbeaf24d7e61306dd6a786dc3d0
