{
  "id": 2530963,
  "type": "Feature",
  "properties": {
    "tgn:hierarchy":[
        "tgn:2530963",
        "tgn:7006450",
        "tgn:1000001",
        "tgn:7012149",
        "tgn:2000079",
        "tgn:7029392"
    ],
    "tgn:id":2530963,
    "tgn:name":"Mudyutok River",
    "tgn:placetype":[
        "aat:300008707"
    ]
},
  "bbox": [],
  "geometry": {"coordinates":[-163.3833,64.6667],"type":"Point"}
}