{
  "id": 7114588,
  "type": "Feature",
  "properties": {
    "tgn:hierarchy":[
        "tgn:7114588",
        "tgn:7003692",
        "tgn:1000003",
        "tgn:7000084",
        "tgn:7029392"
    ],
    "tgn:id":7114588,
    "tgn:name":"Ritzenweiler",
    "tgn:placetype":[
        "aat:300008347"
    ]
},
  "bbox": [],
  "geometry": {"coordinates":[9.816667,47.983333],"type":"Point"}
}