{
  "id": 2222701,
  "type": "Feature",
  "properties": {
    "tgn:hierarchy":[
        "tgn:2222701",
        "tgn:1000001",
        "tgn:7012149",
        "tgn:7016167",
        "tgn:7007523",
        "tgn:7029392"
    ],
    "tgn:id":2222701,
    "tgn:name":"Carr Creek",
    "tgn:placetype":[
        "aat:300008706"
    ]
},
  "bbox": [],
  "geometry": {"coordinates":[-90.6667,38.5167],"type":"Point"}
}