{
  "id": 2160011,
  "type": "Feature",
  "properties": {
    "tgn:hierarchy":[
        "tgn:2160011",
        "tgn:1000001",
        "tgn:7012149",
        "tgn:1002986",
        "tgn:7007568",
        "tgn:7029392"
    ],
    "tgn:id":2160011,
    "tgn:name":"Beech Mountain",
    "tgn:placetype":[
        "aat:300008798"
    ]
},
  "bbox": [],
  "geometry": {"coordinates":[-73.7667,43.35],"type":"Point"}
}