{
  "id": 2016966,
  "type": "Feature",
  "properties": {
    "tgn:hierarchy":[
        "tgn:2016966",
        "tgn:1000001",
        "tgn:1002714",
        "tgn:7012149",
        "tgn:7007159",
        "tgn:7029392"
    ],
    "tgn:id":2016966,
    "tgn:name":"Hamburg",
    "tgn:placetype":[
        "aat:300008347"
    ]
},
  "bbox": [],
  "geometry": {"coordinates":[-72.35,41.3833],"type":"Point"}
}