{
  "id": 2392427,
  "type": "Feature",
  "properties": {
    "tgn:hierarchy":[
        "tgn:2392427",
        "tgn:1000001",
        "tgn:7012149",
        "tgn:2001067",
        "tgn:7007521",
        "tgn:7029392"
    ],
    "tgn:id":2392427,
    "tgn:name":"Hitchcock Island",
    "tgn:placetype":[
        "aat:300008791"
    ]
},
  "bbox": [],
  "geometry": {"coordinates":[-92.8833,48.5333],"type":"Point"}
}