<<<<<<< HEAD
{
  "id": 7365884,
  "type": "Feature",
  "properties": {
    "tgn:hierarchy":[
        "tgn:7365884",
        "tgn:1000001",
        "tgn:7005601",
        "tgn:7005560",
        "tgn:7029392"
    ],
    "tgn:id":7365884,
    "tgn:name":"El Refugio",
    "tgn:placetype":[
        "aat:300008347"
    ]
},
  "bbox": [],
  "geometry": {"coordinates":[-103.3,23.15],"type":"Point"}
}
=======
{"geometry":{"type":"Point","coordinates":[-103.300000,23.150000]},"type":"Feature","properties":{"hierarchy":["tgn:7365884","tgn:1000001","tgn:7005601","tgn:7005560","tgn:7029392"],"placetype":["aat:300008347"],"id":7365884,"name:xx":"El Refugio"}}
>>>>>>> 03f74aca74312dbeaf24d7e61306dd6a786dc3d0
