{
  "id": 7535888,
  "type": "Feature",
  "properties": {
    "tgn:hierarchy":[
        "tgn:7535888",
        "tgn:7001242",
        "tgn:7016833",
        "tgn:7001336",
        "tgn:7029392"
    ],
    "tgn:id":7535888,
    "tgn:name:en":"Fayr\u0101n, W\u0101\u1e29at",
    "tgn:placetype":[
        "aat:300008686"
    ]
},
  "bbox": [],
  "geometry": {"coordinates":[33.620187,28.718672],"type":"Point"}
}