{
  "id": 7555082,
  "type": "Feature",
  "properties": {
    "tgn:hierarchy":[
        "tgn:7555082",
        "tgn:1000004",
        "tgn:1001871",
        "tgn:7000198",
        "tgn:7029392"
    ],
    "tgn:id":7555082,
    "tgn:name:en":"Manethi",
    "tgn:placetype":[
        "aat:300008347"
    ]
},
  "bbox": [],
  "geometry": {"coordinates":[76.387692,28.157944],"type":"Point"}
}