{
  "id": 2463876,
  "type": "Feature",
  "properties": {
    "tgn:hierarchy":[
        "tgn:2463876",
        "tgn:1000001",
        "tgn:7012149",
        "tgn:2000285",
        "tgn:7007240",
        "tgn:7029392"
    ],
    "tgn:id":2463876,
    "tgn:name":"Locklin Lake",
    "tgn:placetype":[
        "aat:300008680"
    ]
},
  "bbox": [],
  "geometry": {"coordinates":[-87.0333,30.6167],"type":"Point"}
}