{
  "id": 1092495,
  "type": "Feature",
  "properties": {
    "tgn:hierarchy":[
        "tgn:1092495",
        "tgn:7001242",
        "tgn:1001742",
        "tgn:1000189",
        "tgn:7029392"
    ],
    "tgn:id":1092495,
    "tgn:name":"Dialakoto",
    "tgn:placetype":[
        "aat:300008347"
    ]
},
  "bbox": [],
  "geometry": {"coordinates":[-13.3167,13.35],"type":"Point"}
}