{
  "id": 1049176,
  "type": "Feature",
  "properties": {
    "tgn:hierarchy":[
        "tgn:1049176",
        "tgn:1000003",
        "tgn:7024124",
        "tgn:7006366",
        "tgn:7029392"
    ],
    "tgn:id":1049176,
    "tgn:name":"Krapkowice",
    "tgn:placetype":[
        "aat:300008347"
    ]
},
  "bbox": [],
  "geometry": {"coordinates":[17.9333,50.4833],"type":"Point"}
}