{
  "id": 7349459,
  "type": "Feature",
  "properties": {
    "tgn:hierarchy":[
        "tgn:7349459",
        "tgn:1000001",
        "tgn:7005591",
        "tgn:7005560",
        "tgn:7029392"
    ],
    "tgn:id":7349459,
    "tgn:name":"Almoloya",
    "tgn:placetype":[
        "aat:300007783"
    ]
},
  "bbox": [],
  "geometry": {"coordinates":[-95.05,16.75],"type":"Point"}
}