{
  "id": 2703495,
  "type": "Feature",
  "properties": {
    "tgn:hierarchy":[
        "tgn:2703495",
        "tgn:1000001",
        "tgn:7012149",
        "tgn:1002468",
        "tgn:7007252",
        "tgn:7029392"
    ],
    "tgn:id":2703495,
    "tgn:name":"Summit Lake Reservoir",
    "tgn:placetype":[
        "aat:300006191"
    ]
},
  "bbox": [],
  "geometry": {"coordinates":[-85.3167,40.0167],"type":"Point"}
}