{
  "id": 2700946,
  "type": "Feature",
  "properties": {
    "tgn:hierarchy":[
        "tgn:2700946",
        "tgn:1000001",
        "tgn:2000459",
        "tgn:7012149",
        "tgn:7007250",
        "tgn:7029392"
    ],
    "tgn:id":2700946,
    "tgn:name":"Sugar Creek",
    "tgn:placetype":[
        "aat:300008706"
    ]
},
  "bbox": [],
  "geometry": {"coordinates":[-115.9167,43.85],"type":"Point"}
}