{
  "id": 1052021,
  "type": "Feature",
  "properties": {
    "tgn:hierarchy":[
        "tgn:1052021",
        "tgn:1003351",
        "tgn:1000004",
        "tgn:7018214",
        "tgn:7002435",
        "tgn:7029392"
    ],
    "tgn:id":1052021,
    "tgn:name":"Aksenovo-Zilovskoye",
    "tgn:placetype":[
        "aat:300008347"
    ]
},
  "bbox": [],
  "geometry": {"coordinates":[117.5833,53.0833],"type":"Point"}
}