{
  "id": 1016538,
  "type": "Feature",
  "properties": {
    "tgn:hierarchy":[
        "tgn:1016538",
        "tgn:7005465",
        "tgn:1000001",
        "tgn:7005441",
        "tgn:7029392"
    ],
    "tgn:id":1016538,
    "tgn:name":"Metap\u00e1n",
    "tgn:placetype":[
        "aat:300008347"
    ]
},
  "bbox": [],
  "geometry": {"coordinates":[-89.4667,14.3333],"type":"Point"}
}