{
  "id": 2154718,
  "type": "Feature",
  "properties": {
    "tgn:hierarchy":[
        "tgn:2154718",
        "tgn:1000001",
        "tgn:7012149",
        "tgn:2001285",
        "tgn:7007524",
        "tgn:7029392"
    ],
    "tgn:id":2154718,
    "tgn:name":"Bear Gulch",
    "tgn:placetype":[
        "aat:300008761"
    ]
},
  "bbox": [],
  "geometry": {"coordinates":[-111.1333,48.8667],"type":"Point"}
}