{
  "id": 2754273,
  "type": "Feature",
  "properties": {
    "tgn:hierarchy":[
        "tgn:2754273",
        "tgn:1000001",
        "tgn:7012149",
        "tgn:2000818",
        "tgn:7007255",
        "tgn:7029392"
    ],
    "tgn:id":2754273,
    "tgn:name":"Watts Mountain",
    "tgn:placetype":[
        "aat:300008798"
    ]
},
  "bbox": [],
  "geometry": {"coordinates":[-84.65,36.6333],"type":"Point"}
}