{
  "id": 2708421,
  "type": "Feature",
  "properties": {
    "tgn:hierarchy":[
        "tgn:2708421",
        "tgn:1000001",
        "tgn:7012149",
        "tgn:2000804",
        "tgn:7007255",
        "tgn:7029392"
    ],
    "tgn:id":2708421,
    "tgn:name":"Sycamore Creek",
    "tgn:placetype":[
        "aat:300008706"
    ]
},
  "bbox": [],
  "geometry": {"coordinates":[-82.65,37.7167],"type":"Point"}
}