{
  "id": 7290346,
  "type": "Feature",
  "properties": {
    "tgn:hierarchy":[
        "tgn:7290346",
        "tgn:1001702",
        "tgn:1000049",
        "tgn:1000002",
        "tgn:7029392"
    ],
    "tgn:id":7290346,
    "tgn:name":"Dolores, Arrecife",
    "tgn:placetype":[
        "aat:300008808"
    ]
},
  "bbox": [],
  "geometry": {"coordinates":[-74.433333,-49.366667],"type":"Point"}
}