{
  "id": 2243284,
  "type": "Feature",
  "properties": {
    "tgn:hierarchy":[
        "tgn:2243284",
        "tgn:1000001",
        "tgn:7012149",
        "tgn:1002904",
        "tgn:7007710",
        "tgn:7029392"
    ],
    "tgn:id":2243284,
    "tgn:name":"Clear Shade Wild Area",
    "tgn:placetype":[
        "aat:300055621"
    ]
},
  "bbox": [],
  "geometry": {"coordinates":[-78.75,40.1833],"type":"Point"}
}