{
  "id": 2654734,
  "type": "Feature",
  "properties": {
    "tgn:hierarchy":[
        "tgn:2654734",
        "tgn:1000001",
        "tgn:7012149",
        "tgn:2002005",
        "tgn:7007826",
        "tgn:7029392"
    ],
    "tgn:id":2654734,
    "tgn:name":"Shakespeare Tanks",
    "tgn:placetype":[
        "aat:300006191"
    ]
},
  "bbox": [],
  "geometry": {"coordinates":[-105.75,31.65],"type":"Point"}
}