{
  "id": 2594571,
  "type": "Feature",
  "properties": {
    "tgn:hierarchy":[
        "tgn:2594571",
        "tgn:1000001",
        "tgn:2001016",
        "tgn:7012149",
        "tgn:7007521",
        "tgn:7029392"
    ],
    "tgn:id":2594571,
    "tgn:name":"Portsmouth Mine",
    "tgn:placetype":[
        "aat:300000390"
    ]
},
  "bbox": [],
  "geometry": {"coordinates":[-93.95,46.4833],"type":"Point"}
}