{
  "id": 7258642,
  "type": "Feature",
  "properties": {
    "tgn:hierarchy":[
        "tgn:7258642",
        "tgn:7018239",
        "tgn:1000003",
        "tgn:1000063",
        "tgn:7018236",
        "tgn:7029392"
    ],
    "tgn:id":7258642,
    "tgn:name":"Zibbeek",
    "tgn:placetype":[
        "aat:300008699"
    ]
},
  "bbox": [],
  "geometry": {"coordinates":[4.216667,50.85],"type":"Point"}
}