{
  "id": 2780588,
  "type": "Feature",
  "properties": {
    "tgn:hierarchy":[
        "tgn:2780588",
        "tgn:1000001",
        "tgn:2001425",
        "tgn:7012149",
        "tgn:7007564",
        "tgn:7029392"
    ],
    "tgn:id":2780588,
    "tgn:name":"Wood Hill",
    "tgn:placetype":[
        "aat:300008798"
    ]
},
  "bbox": [],
  "geometry": {"coordinates":[-71.55,43.1167],"type":"Point"}
}