<<<<<<< HEAD
{
  "id": 2338264,
  "type": "Feature",
  "properties": {
    "tgn:hierarchy":[
        "tgn:2338264",
        "tgn:1000001",
        "tgn:7012149",
        "tgn:1002659",
        "tgn:7007710",
        "tgn:7029392"
    ],
    "tgn:id":2338264,
    "tgn:name":"Fox Run",
    "tgn:placetype":[
        "aat:300008699"
    ]
},
  "bbox": [],
  "geometry": {"coordinates":[-80.0667,41.3],"type":"Point"}
}
=======
{"geometry":{"type":"Point","coordinates":[-80.066700,41.300000]},"type":"Feature","properties":{"hierarchy":["tgn:2338264","tgn:1000001","tgn:7012149","tgn:1002659","tgn:7007710","tgn:7029392"],"placetype":["aat:300008699"],"id":2338264,"name:xx":"Fox Run"}}
>>>>>>> 03f74aca74312dbeaf24d7e61306dd6a786dc3d0
