{
  "id": 7424639,
  "type": "Feature",
  "properties": {
    "tgn:hierarchy":[
        "tgn:7424639",
        "tgn:1000001",
        "tgn:7005601",
        "tgn:7005560",
        "tgn:7029392"
    ],
    "tgn:id":7424639,
    "tgn:name":"Manatial de la Honda",
    "tgn:placetype":[
        "aat:300008347"
    ]
},
  "bbox": [],
  "geometry": {"coordinates":[-103.577222,24.116667],"type":"Point"}
}