{
  "id": 2230151,
  "type": "Feature",
  "properties": {
    "tgn:hierarchy":[
        "tgn:2230151",
        "tgn:1000001",
        "tgn:7012149",
        "tgn:2000523",
        "tgn:7007251",
        "tgn:7029392"
    ],
    "tgn:id":2230151,
    "tgn:name":"Cement Hollow",
    "tgn:placetype":[
        "aat:300008761"
    ]
},
  "bbox": [],
  "geometry": {"coordinates":[-88.55,37.3333],"type":"Point"}
}