<<<<<<< HEAD
{
  "id": 2337763,
  "type": "Feature",
  "properties": {
    "tgn:hierarchy":[
        "tgn:2337763",
        "tgn:1000001",
        "tgn:7012149",
        "tgn:2001381",
        "tgn:7007525",
        "tgn:7029392"
    ],
    "tgn:id":2337763,
    "tgn:name":"Fox Creek",
    "tgn:placetype":[
        "aat:300008706"
    ]
},
  "bbox": [],
  "geometry": {"coordinates":[-95.9333,40.6167],"type":"Point"}
}
=======
{"geometry":{"type":"Point","coordinates":[-95.933300,40.616700]},"type":"Feature","properties":{"hierarchy":["tgn:2337763","tgn:1000001","tgn:7012149","tgn:2001381","tgn:7007525","tgn:7029392"],"placetype":["aat:300008706"],"id":2337763,"name:xx":"Fox Creek"}}
>>>>>>> 03f74aca74312dbeaf24d7e61306dd6a786dc3d0
