{
  "id": 1067957,
  "type": "Feature",
  "properties": {
    "tgn:hierarchy":[
        "tgn:1067957",
        "tgn:1000004",
        "tgn:7002077",
        "tgn:1000111",
        "tgn:7029392"
    ],
    "tgn:id":1067957,
    "tgn:name":"Erpuzi",
    "tgn:placetype":[
        "aat:300008347"
    ]
},
  "bbox": [],
  "geometry": {"coordinates":[115.55,40.4833],"type":"Point"}
}