{
  "id": 7034492,
  "type": "Feature",
  "properties": {
    "tgn:hierarchy":[
        "tgn:7034492",
        "tgn:1003500",
        "tgn:1000003",
        "tgn:7010380",
        "tgn:1000080",
        "tgn:7029392"
    ],
    "tgn:id":7034492,
    "tgn:name":"Masseria Acquagnor\u00e1",
    "tgn:placetype":[
        "aat:300000206"
    ]
},
  "bbox": [],
  "geometry": {"coordinates":[17.046111,40.615278],"type":"Point"}
}