{
  "id": 1062201,
  "type": "Feature",
  "properties": {
    "tgn:hierarchy":[
        "tgn:1062201",
        "tgn:7010420",
        "tgn:1000003",
        "tgn:7002795",
        "tgn:1000095",
        "tgn:7029392"
    ],
    "tgn:id":1062201,
    "tgn:name":"Majadahonda",
    "tgn:placetype":[
        "aat:300008347"
    ]
},
  "bbox": [],
  "geometry": {"coordinates":[-3.866667,40.466667],"type":"Point"}
}