{
  "id": 7235695,
  "type": "Feature",
  "properties": {
    "tgn:hierarchy":[
        "tgn:7235695",
        "tgn:7002715",
        "tgn:7002731",
        "tgn:1000003",
        "tgn:1000074",
        "tgn:7029392"
    ],
    "tgn:id":7235695,
    "tgn:name":"Ar\u00e9thousa",
    "tgn:placetype":[
        "aat:300008347"
    ]
},
  "bbox": [],
  "geometry": {"coordinates":[23.583333,40.75],"type":"Point"}
}