{
  "id": 7474919,
  "type": "Feature",
  "properties": {
    "tgn:hierarchy":[
        "tgn:7474919",
        "tgn:1000004",
        "tgn:7467799",
        "tgn:1000141",
        "tgn:7029392"
    ],
    "tgn:id":7474919,
    "tgn:name":"Xinbao Guoxiao",
    "tgn:placetype":[
        "aat:300006495"
    ]
},
  "bbox": [],
  "geometry": {"coordinates":[120.345447,23.979095],"type":"Point"}
}