{
  "id": 7274994,
  "type": "Feature",
  "properties": {
    "tgn:hierarchy":[
        "tgn:7274994",
        "tgn:1001702",
        "tgn:1000049",
        "tgn:1000002",
        "tgn:7029392"
    ],
    "tgn:id":7274994,
    "tgn:name":"Mono, Punta",
    "tgn:placetype":[
        "aat:300386846"
    ]
},
  "bbox": [],
  "geometry": {"coordinates":[-71.833333,-54.716667],"type":"Point"}
}