{
  "id": 7219147,
  "type": "Feature",
  "properties": {
    "tgn:hierarchy":[
        "tgn:7219147",
        "tgn:7011163",
        "tgn:7002674",
        "tgn:1000003",
        "tgn:1000074",
        "tgn:7029392"
    ],
    "tgn:id":7219147,
    "tgn:name":"Skordon\u00edsi, Vrachonis\u00edda",
    "tgn:placetype":[
        "aat:300008791"
    ]
},
  "bbox": [],
  "geometry": {"coordinates":[25.845556,39.198889],"type":"Point"}
}