{
  "id": 2522445,
  "type": "Feature",
  "properties": {
    "tgn:hierarchy":[
        "tgn:2522445",
        "tgn:1000001",
        "tgn:7012149",
        "tgn:2001221",
        "tgn:7007523",
        "tgn:7029392"
    ],
    "tgn:id":2522445,
    "tgn:name":"Moonlight Bay",
    "tgn:placetype":[
        "aat:300132316"
    ]
},
  "bbox": [],
  "geometry": {"coordinates":[-92.7667,38.1833],"type":"Point"}
}