{
  "id": 7580117,
  "type": "Feature",
  "properties": {
    "tgn:hierarchy":[
        "tgn:7580117",
        "tgn:1001828",
        "tgn:1000004",
        "tgn:7000198",
        "tgn:7029392"
    ],
    "tgn:id":7580117,
    "tgn:name:en":"Utsap\u0101lem",
    "tgn:placetype":[
        "aat:300008347"
    ]
},
  "bbox": [],
  "geometry": {"coordinates":[79.666667,14.366667],"type":"Point"}
}