{
  "id": 2707182,
  "type": "Feature",
  "properties": {
    "tgn:hierarchy":[
        "tgn:2707182",
        "tgn:1000001",
        "tgn:7012149",
        "tgn:2001286",
        "tgn:7007524",
        "tgn:7029392"
    ],
    "tgn:id":2707182,
    "tgn:name":"Swede Mountain",
    "tgn:placetype":[
        "aat:300008798"
    ]
},
  "bbox": [],
  "geometry": {"coordinates":[-115.45,48.3667],"type":"Point"}
}