{
  "id": 2477756,
  "type": "Feature",
  "properties": {
    "tgn:hierarchy":[
        "tgn:2477756",
        "tgn:1000001",
        "tgn:7012149",
        "tgn:7007920",
        "tgn:7029392"
    ],
    "tgn:id":2477756,
    "tgn:name":"Mac Peak",
    "tgn:placetype":[
        "aat:300008798"
    ]
},
  "bbox": [],
  "geometry": {"coordinates":[-121.1167,47.6167],"type":"Point"}
}