{
  "id": 2172303,
  "type": "Feature",
  "properties": {
    "tgn:hierarchy":[
        "tgn:2172303",
        "tgn:1000001",
        "tgn:7012149",
        "tgn:7007157",
        "tgn:2000184",
        "tgn:7029392"
    ],
    "tgn:id":2172303,
    "tgn:name":"Bill Allen Spring",
    "tgn:placetype":[
        "aat:300008697"
    ]
},
  "bbox": [],
  "geometry": {"coordinates":[-120.55,41.05],"type":"Point"}
}