{
  "id": 7321174,
  "type": "Feature",
  "properties": {
    "tgn:hierarchy":[
        "tgn:7321174",
        "tgn:1001702",
        "tgn:1000049",
        "tgn:1000002",
        "tgn:7029392"
    ],
    "tgn:id":7321174,
    "tgn:name":"Baja, Punta",
    "tgn:placetype":[
        "aat:300386846"
    ]
},
  "bbox": [],
  "geometry": {"coordinates":[-74.65,-52.85],"type":"Point"}
}