{
  "id": 1084569,
  "type": "Feature",
  "properties": {
    "tgn:hierarchy":[
        "tgn:1084569",
        "tgn:1001094",
        "tgn:1000004",
        "tgn:1000135",
        "tgn:7029392"
    ],
    "tgn:id":1084569,
    "tgn:name":"Polangui",
    "tgn:placetype":[
        "aat:300008347"
    ]
},
  "bbox": [],
  "geometry": {"coordinates":[123.4833,13.2833],"type":"Point"}
}