{
  "id": 2745149,
  "type": "Feature",
  "properties": {
    "tgn:hierarchy":[
        "tgn:2745149",
        "tgn:1000001",
        "tgn:7012149",
        "tgn:7007157",
        "tgn:1002857",
        "tgn:7029392"
    ],
    "tgn:id":2745149,
    "tgn:name":"Village Point",
    "tgn:placetype":[
        "aat:300008850"
    ]
},
  "bbox": [],
  "geometry": {"coordinates":[-117.1833,34.25],"type":"Point"}
}