{
  "id": 2350573,
  "type": "Feature",
  "properties": {
    "tgn:hierarchy":[
        "tgn:2350573",
        "tgn:7006450",
        "tgn:1000001",
        "tgn:7030517",
        "tgn:7012149",
        "tgn:7029392"
    ],
    "tgn:id":2350573,
    "tgn:name":"Glacier Creek",
    "tgn:placetype":[
        "aat:300008706"
    ]
},
  "bbox": [],
  "geometry": {"coordinates":[-156.4667,57.1667],"type":"Point"}
}