{
  "id": 7562013,
  "type": "Feature",
  "properties": {
    "tgn:hierarchy":[
        "tgn:7562013",
        "tgn:1000004",
        "tgn:7000198",
        "tgn:7016722",
        "tgn:7029392"
    ],
    "tgn:id":7562013,
    "tgn:name:en":"Chiranji Purwa",
    "tgn:placetype":[
        "aat:300008347"
    ]
},
  "bbox": [],
  "geometry": {"coordinates":[79.9892,27.0893],"type":"Point"}
}