{
  "id": 2026273,
  "type": "Feature",
  "properties": {
    "tgn:hierarchy":[
        "tgn:2026273",
        "tgn:1000001",
        "tgn:2000500",
        "tgn:7012149",
        "tgn:7007251",
        "tgn:7029392"
    ],
    "tgn:id":2026273,
    "tgn:name":"Etna",
    "tgn:placetype":[
        "aat:300008347",
        "aat:300387210"
    ]
},
  "bbox": [],
  "geometry": {"coordinates":[-88.4167,39.3833],"type":"Point"}
}