<<<<<<< HEAD
{
  "id": 7050744,
  "type": "Feature",
  "properties": {
    "tgn:hierarchy":[
        "tgn:7050744",
        "tgn:7003167",
        "tgn:1000003",
        "tgn:7009760",
        "tgn:1000080",
        "tgn:7029392"
    ],
    "tgn:id":7050744,
    "tgn:name":"Nievole, Fiume",
    "tgn:placetype":[
        "aat:300008699"
    ]
},
  "bbox": [],
  "geometry": {"coordinates":[10.816667,43.816667],"type":"Point"}
}
=======
{"geometry":{"type":"Point","coordinates":[10.816667,43.816667]},"type":"Feature","properties":{"hierarchy":["tgn:7050744","tgn:7003167","tgn:1000003","tgn:7009760","tgn:1000080","tgn:7029392"],"placetype":["aat:300008699"],"id":7050744,"name:xx":"Nievole, Fiume"}}
>>>>>>> 03f74aca74312dbeaf24d7e61306dd6a786dc3d0
