{
  "id": 7569458,
  "type": "Feature",
  "properties": {
    "tgn:hierarchy":[
        "tgn:7569458",
        "tgn:1000004",
        "tgn:7000198",
        "tgn:7031786",
        "tgn:7029392"
    ],
    "tgn:id":7569458,
    "tgn:name:en":"Dhaura",
    "tgn:placetype":[
        "aat:300008347"
    ]
},
  "bbox": [],
  "geometry": {"coordinates":[78.708978,29.984284],"type":"Point"}
}