{
  "id": 7140006,
  "type": "Feature",
  "properties": {
    "tgn:hierarchy":[
        "tgn:7140006",
        "tgn:7003669",
        "tgn:1000003",
        "tgn:7000084",
        "tgn:7029392"
    ],
    "tgn:id":7140006,
    "tgn:name":"Lettner Berg",
    "tgn:placetype":[
        "aat:300008795"
    ]
},
  "bbox": [],
  "geometry": {"coordinates":[11.533333,47.616667],"type":"Point"}
}