{
  "id": 2661638,
  "type": "Feature",
  "properties": {
    "tgn:hierarchy":[
        "tgn:2661638",
        "tgn:1000001",
        "tgn:7012149",
        "tgn:2000381",
        "tgn:7007248",
        "tgn:7029392"
    ],
    "tgn:id":2661638,
    "tgn:name":"Shriver Creek",
    "tgn:placetype":[
        "aat:300008706"
    ]
},
  "bbox": [],
  "geometry": {"coordinates":[-82.35,33.7667],"type":"Point"}
}