{
  "id": 2409452,
  "type": "Feature",
  "properties": {
    "tgn:hierarchy":[
        "tgn:2409452",
        "tgn:1000001",
        "tgn:7012149",
        "tgn:1002501",
        "tgn:7007710",
        "tgn:7029392"
    ],
    "tgn:id":2409452,
    "tgn:name":"Ideal",
    "tgn:placetype":[
        "aat:300008347"
    ]
},
  "bbox": [],
  "geometry": {"coordinates":[-79.0667,40.6167],"type":"Point"}
}