{
  "id": 2638997,
  "type": "Feature",
  "properties": {
    "tgn:hierarchy":[
        "tgn:2638997",
        "tgn:1000001",
        "tgn:7012149",
        "tgn:7029392"
    ],
    "tgn:id":2638997,
    "tgn:name":"Salt Fork Arkansas River",
    "tgn:placetype":[
        "aat:300008707"
    ]
},
  "bbox": [],
  "geometry": {"coordinates":[-99.35,37.1667],"type":"Point"}
}