{
  "id": 2456231,
  "type": "Feature",
  "properties": {
    "tgn:hierarchy":[
        "tgn:2456231",
        "tgn:1000001",
        "tgn:7012149",
        "tgn:2000905",
        "tgn:7007256",
        "tgn:7029392"
    ],
    "tgn:id":2456231,
    "tgn:name":"Little Holmes Bayou",
    "tgn:placetype":[
        "aat:300008699"
    ]
},
  "bbox": [],
  "geometry": {"coordinates":[-89.75,30.4833],"type":"Point"}
}