{
  "id": 7509379,
  "type": "Feature",
  "properties": {
    "tgn:hierarchy":[
        "tgn:7509379",
        "tgn:7016670",
        "tgn:1008380",
        "tgn:1000226",
        "tgn:1000006",
        "tgn:7029392"
    ],
    "tgn:id":7509379,
    "tgn:name:en":"Tahaenui River",
    "tgn:placetype":[
        "aat:300008699"
    ]
},
  "bbox": [],
  "geometry": {"coordinates":[177.666667,-39.05],"type":"Point"}
}