{
  "id": 2770579,
  "type": "Feature",
  "properties": {
    "tgn:hierarchy":[
        "tgn:2770579",
        "tgn:1000001",
        "tgn:7012149",
        "tgn:2001447",
        "tgn:7007566",
        "tgn:7029392"
    ],
    "tgn:id":2770579,
    "tgn:name":"Wildboy Spring",
    "tgn:placetype":[
        "aat:300008697"
    ]
},
  "bbox": [],
  "geometry": {"coordinates":[-105.7833,32.65],"type":"Point"}
}