{
  "id": 7463814,
  "type": "Feature",
  "properties": {
    "tgn:hierarchy":[
        "tgn:7463814",
        "tgn:7002445",
        "tgn:1000003",
        "tgn:7008165",
        "tgn:7008591",
        "tgn:7029392"
    ],
    "tgn:id":7463814,
    "tgn:name:en":"Housesteads",
    "tgn:placetype":[
        "aat:300387007"
    ]
},
  "bbox": [],
  "geometry": {"coordinates":[-2.333333,55.016667],"type":"Point"}
}