<<<<<<< HEAD
{
  "id": 2708732,
  "type": "Feature",
  "properties": {
    "tgn:hierarchy":[
        "tgn:2708732",
        "tgn:1000001",
        "tgn:2001024",
        "tgn:7012149",
        "tgn:7007521",
        "tgn:7029392"
    ],
    "tgn:id":2708732,
    "tgn:name":"Sylvan Lake",
    "tgn:placetype":[
        "aat:300008680"
    ]
},
  "bbox": [],
  "geometry": {"coordinates":[-95.7667,45.9167],"type":"Point"}
}
=======
{"geometry":{"type":"Point","coordinates":[-95.766700,45.916700]},"type":"Feature","properties":{"hierarchy":["tgn:2708732","tgn:1000001","tgn:2001024","tgn:7012149","tgn:7007521","tgn:7029392"],"placetype":["aat:300008680"],"id":2708732,"name:xx":"Sylvan Lake"}}
>>>>>>> 03f74aca74312dbeaf24d7e61306dd6a786dc3d0
