{
  "id": 7425417,
  "type": "Feature",
  "properties": {
    "tgn:hierarchy":[
        "tgn:7425417",
        "tgn:1000001",
        "tgn:7005601",
        "tgn:7005560",
        "tgn:7029392"
    ],
    "tgn:id":7425417,
    "tgn:name":"La Pila, Arroyo",
    "tgn:placetype":[
        "aat:300266554",
        "aat:300008699"
    ]
},
  "bbox": [],
  "geometry": {"coordinates":[-103.333333,24.45],"type":"Point"}
}