{
  "id": 2635475,
  "type": "Feature",
  "properties": {
    "tgn:hierarchy":[
        "tgn:2635475",
        "tgn:1000001",
        "tgn:7012149",
        "tgn:2001311",
        "tgn:7007524",
        "tgn:7029392"
    ],
    "tgn:id":2635475,
    "tgn:name":"SE Starved/Death-14 Mine",
    "tgn:placetype":[
        "aat:300000390"
    ]
},
  "bbox": [],
  "geometry": {"coordinates":[-107.05,46.35],"type":"Point"}
}