{
  "id": 7206522,
  "type": "Feature",
  "properties": {
    "tgn:hierarchy":[
        "tgn:7206522",
        "tgn:7003669",
        "tgn:1000003",
        "tgn:7000084",
        "tgn:7029392"
    ],
    "tgn:id":7206522,
    "tgn:name":"Buchsee",
    "tgn:placetype":[
        "aat:300000206"
    ]
},
  "bbox": [],
  "geometry": {"coordinates":[11.383333,47.916667],"type":"Point"}
}