<<<<<<< HEAD
{
  "id": 2403780,
  "type": "Feature",
  "properties": {
    "tgn:hierarchy":[
        "tgn:2403780",
        "tgn:1000001",
        "tgn:7012149",
        "tgn:2001898",
        "tgn:7007825",
        "tgn:7029392"
    ],
    "tgn:id":2403780,
    "tgn:name":"Howard Spring",
    "tgn:placetype":[
        "aat:300008697"
    ]
},
  "bbox": [],
  "geometry": {"coordinates":[-84.4167,35.5667],"type":"Point"}
}
=======
{"geometry":{"type":"Point","coordinates":[-84.416700,35.566700]},"type":"Feature","properties":{"hierarchy":["tgn:2403780","tgn:1000001","tgn:7012149","tgn:2001898","tgn:7007825","tgn:7029392"],"placetype":["aat:300008697"],"id":2403780,"name:xx":"Howard Spring"}}
>>>>>>> 03f74aca74312dbeaf24d7e61306dd6a786dc3d0
