{
  "id": 7172462,
  "type": "Feature",
  "properties": {
    "tgn:hierarchy":[
        "tgn:7172462",
        "tgn:7003669",
        "tgn:1000003",
        "tgn:7000084",
        "tgn:7029392"
    ],
    "tgn:id":7172462,
    "tgn:name":"Hinterschmelz",
    "tgn:placetype":[
        "aat:300000206"
    ]
},
  "bbox": [],
  "geometry": {"coordinates":[13.05,49.216667],"type":"Point"}
}