{
  "id": 7421643,
  "type": "Feature",
  "properties": {
    "tgn:hierarchy":[
        "tgn:7421643",
        "tgn:7005584",
        "tgn:1000001",
        "tgn:7005560",
        "tgn:7029392"
    ],
    "tgn:id":7421643,
    "tgn:name":"Rinc\u00f3n de Ortega",
    "tgn:placetype":[
        "aat:300008347"
    ]
},
  "bbox": [],
  "geometry": {"coordinates":[-101.281111,21.245833],"type":"Point"}
}