{
  "id": 2519779,
  "type": "Feature",
  "properties": {
    "tgn:hierarchy":[
        "tgn:2519779",
        "tgn:1000001",
        "tgn:7012149",
        "tgn:7007157",
        "tgn:7014516",
        "tgn:7029392"
    ],
    "tgn:id":2519779,
    "tgn:name":"Mohrhardt Ridge",
    "tgn:placetype":[
        "aat:300266640"
    ]
},
  "bbox": [],
  "geometry": {"coordinates":[-123.15,38.5667],"type":"Point"}
}