{
  "id": 1053828,
  "type": "Feature",
  "properties": {
    "tgn:hierarchy":[
        "tgn:1053828",
        "tgn:1000004",
        "tgn:7011573",
        "tgn:7018214",
        "tgn:7002435",
        "tgn:7029392"
    ],
    "tgn:id":1053828,
    "tgn:name":"Elektrougli",
    "tgn:placetype":[
        "aat:300008347"
    ]
},
  "bbox": [],
  "geometry": {"coordinates":[38.2333,55.6833],"type":"Point"}
}