{
  "id": 2224080,
  "type": "Feature",
  "properties": {
    "tgn:hierarchy":[
        "tgn:2224080",
        "tgn:1000001",
        "tgn:1002207",
        "tgn:7012149",
        "tgn:7007240",
        "tgn:7029392"
    ],
    "tgn:id":2224080,
    "tgn:name":"Carver Ranches",
    "tgn:placetype":[
        "aat:300008347"
    ]
},
  "bbox": [],
  "geometry": {"coordinates":[-80.1833,25.9833],"type":"Point"}
}