{
  "id": 7565747,
  "type": "Feature",
  "properties": {
    "tgn:hierarchy":[
        "tgn:7565747",
        "tgn:1000004",
        "tgn:7000198",
        "tgn:7016722",
        "tgn:7029392"
    ],
    "tgn:id":7565747,
    "tgn:name:en":"Purwa Bhadauria Bela",
    "tgn:placetype":[
        "aat:300008347"
    ]
},
  "bbox": [],
  "geometry": {"coordinates":[79.586771,26.81969],"type":"Point"}
}