{
  "id": 2345287,
  "type": "Feature",
  "properties": {
    "tgn:hierarchy":[
        "tgn:2345287",
        "tgn:1000001",
        "tgn:2000952",
        "tgn:7012149",
        "tgn:7007520",
        "tgn:7029392"
    ],
    "tgn:id":2345287,
    "tgn:name":"Garkinghouse Lake",
    "tgn:placetype":[
        "aat:300008680"
    ]
},
  "bbox": [],
  "geometry": {"coordinates":[-84.55,46.2833],"type":"Point"}
}