{
  "id": 2164590,
  "type": "Feature",
  "properties": {
    "tgn:hierarchy":[
        "tgn:2164590",
        "tgn:1000001",
        "tgn:7012149",
        "tgn:2001207",
        "tgn:7007523",
        "tgn:7029392"
    ],
    "tgn:id":2164590,
    "tgn:name":"Berryman",
    "tgn:placetype":[
        "aat:300008347"
    ]
},
  "bbox": [],
  "geometry": {"coordinates":[-90.6833,37.4667],"type":"Point"}
}