{
  "id": 2061334,
  "type": "Feature",
  "properties": {
    "tgn:hierarchy":[
        "tgn:2061334",
        "tgn:1000001",
        "tgn:7012149",
        "tgn:2001278",
        "tgn:7007524",
        "tgn:7029392"
    ],
    "tgn:id":2061334,
    "tgn:name":"Franklin",
    "tgn:placetype":[
        "aat:300387016"
    ]
},
  "bbox": [],
  "geometry": {"coordinates":[-109.2667,46.3667],"type":"Point"}
}