{
  "id": 7068642,
  "type": "Feature",
  "properties": {
    "tgn:hierarchy":[
        "tgn:7068642",
        "tgn:1000003",
        "tgn:7003682",
        "tgn:7000084",
        "tgn:7029392"
    ],
    "tgn:id":7068642,
    "tgn:name":"Stahleck",
    "tgn:placetype":[
        "aat:300008777"
    ]
},
  "bbox": [],
  "geometry": {"coordinates":[7.816667,50.133333],"type":"Point"}
}