{
  "id": 1097041,
  "type": "Feature",
  "properties": {
    "tgn:hierarchy":[
        "tgn:1097041",
        "tgn:7000490",
        "tgn:1000006",
        "tgn:7001828",
        "tgn:7029392"
    ],
    "tgn:id":1097041,
    "tgn:name":"Gulgong",
    "tgn:placetype":[
        "aat:300008347"
    ]
},
  "bbox": [],
  "geometry": {"coordinates":[149.8167,-32.3333],"type":"Point"}
}