{
  "id": 1127840,
  "type": "Feature",
  "properties": {
    "tgn:hierarchy":[
        "tgn:1127840",
        "tgn:7003158",
        "tgn:1000003",
        "tgn:7003124",
        "tgn:1000080",
        "tgn:7029392"
    ],
    "tgn:id":1127840,
    "tgn:name":"Noce",
    "tgn:placetype":[
        "aat:300008707",
        "aat:300008699"
    ]
},
  "bbox": [],
  "geometry": {"coordinates":[11.066667,46.15],"type":"Point"}
}