{
  "id": 2325982,
  "type": "Feature",
  "properties": {
    "tgn:hierarchy":[
        "tgn:2325982",
        "tgn:1000001",
        "tgn:7012149",
        "tgn:7007157",
        "tgn:1002857",
        "tgn:7029392"
    ],
    "tgn:id":2325982,
    "tgn:name":"Fifteenmile Point",
    "tgn:placetype":[
        "aat:300008850"
    ]
},
  "bbox": [],
  "geometry": {"coordinates":[-117.05,34.45],"type":"Point"}
}