{
  "id": 7325684,
  "type": "Feature",
  "properties": {
    "tgn:hierarchy":[
        "tgn:7325684",
        "tgn:7001158",
        "tgn:7002850",
        "tgn:1000003",
        "tgn:1000095",
        "tgn:7029392"
    ],
    "tgn:id":7325684,
    "tgn:name":"San Mamed, R\u00edo de",
    "tgn:placetype":[
        "aat:300008699"
    ]
},
  "bbox": [],
  "geometry": {"coordinates":[-6.533333,41.683333],"type":"Point"}
}