{
  "id": 7353886,
  "type": "Feature",
  "properties": {
    "tgn:hierarchy":[
        "tgn:7353886",
        "tgn:7005581",
        "tgn:1000001",
        "tgn:7005560",
        "tgn:7029392"
    ],
    "tgn:id":7353886,
    "tgn:name":"Campo 3 A",
    "tgn:placetype":[
        "aat:300008347"
    ]
},
  "bbox": [],
  "geometry": {"coordinates":[-106.933333,28.483333],"type":"Point"}
}