{
  "id": 7320593,
  "type": "Feature",
  "properties": {
    "tgn:hierarchy":[
        "tgn:7320593",
        "tgn:1001630",
        "tgn:1000049",
        "tgn:1000002",
        "tgn:7029392"
    ],
    "tgn:id":7320593,
    "tgn:name":"Caballo Muerto, Quebrada",
    "tgn:placetype":[
        "aat:300266554",
        "aat:300008699"
    ]
},
  "bbox": [],
  "geometry": {"coordinates":[-69.35,-26.866667],"type":"Point"}
}