{
  "id": 2169419,
  "type": "Feature",
  "properties": {
    "tgn:hierarchy":[
        "tgn:2169419",
        "tgn:1000001",
        "tgn:7012149",
        "tgn:2001854",
        "tgn:7007825",
        "tgn:7029392"
    ],
    "tgn:id":2169419,
    "tgn:name":"Big Level",
    "tgn:placetype":[
        "aat:300008798"
    ]
},
  "bbox": [],
  "geometry": {"coordinates":[-85.1833,35.8333],"type":"Point"}
}