{
  "id": 7095583,
  "type": "Feature",
  "properties": {
    "tgn:hierarchy":[
        "tgn:7095583",
        "tgn:1000003",
        "tgn:7003689",
        "tgn:7000084",
        "tgn:7029392"
    ],
    "tgn:id":7095583,
    "tgn:name":"Schulen-Berg",
    "tgn:placetype":[
        "aat:300008777"
    ]
},
  "bbox": [],
  "geometry": {"coordinates":[10.416667,51.566667],"type":"Point"}
}