{
  "id": 2370170,
  "type": "Feature",
  "properties": {
    "tgn:hierarchy":[
        "tgn:2370170",
        "tgn:1000001",
        "tgn:7012149",
        "tgn:2000975",
        "tgn:7007520",
        "tgn:7029392"
    ],
    "tgn:id":2370170,
    "tgn:name":"Gwinn Mine",
    "tgn:placetype":[
        "aat:300000390"
    ]
},
  "bbox": [],
  "geometry": {"coordinates":[-87.4333,46.2667],"type":"Point"}
}