{
  "id": 7591730,
  "type": "Feature",
  "properties": {
    "tgn:hierarchy":[
        "tgn:7591730",
        "tgn:1000004",
        "tgn:7000198",
        "tgn:7000799",
        "tgn:7029392"
    ],
    "tgn:id":7591730,
    "tgn:name:en":"Baru\u0101b N\u0101la",
    "tgn:placetype":[
        "aat:300008699"
    ]
},
  "bbox": [],
  "geometry": {"coordinates":[75.197222,34.566667],"type":"Point"}
}