{
  "id": 1116486,
  "type": "Feature",
  "properties": {
    "tgn:hierarchy":[
        "tgn:1116486",
        "tgn:1000001",
        "tgn:7012149",
        "tgn:7007568",
        "tgn:7029392"
    ],
    "tgn:id":1116486,
    "tgn:name":"Great Sacandaga Lake",
    "tgn:placetype":[
        "aat:300008680"
    ]
},
  "bbox": [],
  "geometry": {"coordinates":[-73.9167,43.3167],"type":"Point"}
}