{
  "id": 2552526,
  "type": "Feature",
  "properties": {
    "tgn:hierarchy":[
        "tgn:2552526",
        "tgn:1000001",
        "tgn:7013686",
        "tgn:7012149",
        "tgn:7007517",
        "tgn:7029392"
    ],
    "tgn:id":2552526,
    "tgn:name":"Nungee Swamp",
    "tgn:placetype":[
        "aat:300008905"
    ]
},
  "bbox": [],
  "geometry": {"coordinates":[-72.6833,42.3833],"type":"Point"}
}