{
  "id": 2439458,
  "type": "Feature",
  "properties": {
    "tgn:hierarchy":[
        "tgn:2439458",
        "tgn:1000001",
        "tgn:7012149",
        "tgn:1002838",
        "tgn:7007252",
        "tgn:7029392"
    ],
    "tgn:id":2439458,
    "tgn:name":"Kirkpatrick Ditch",
    "tgn:placetype":[
        "aat:300006075"
    ]
},
  "bbox": [],
  "geometry": {"coordinates":[-85.3167,39.6833],"type":"Point"}
}