{
  "id": 7116254,
  "type": "Feature",
  "properties": {
    "tgn:hierarchy":[
        "tgn:7116254",
        "tgn:1000003",
        "tgn:7003688",
        "tgn:7000084",
        "tgn:7029392"
    ],
    "tgn:id":7116254,
    "tgn:name":"Ohe",
    "tgn:placetype":[
        "aat:300008347"
    ]
},
  "bbox": [],
  "geometry": {"coordinates":[9.766667,54.283333],"type":"Point"}
}