<<<<<<< HEAD
{
  "id": 2337758,
  "type": "Feature",
  "properties": {
    "tgn:hierarchy":[
        "tgn:2337758",
        "tgn:1000001",
        "tgn:7012149",
        "tgn:2001277",
        "tgn:7007524",
        "tgn:7029392"
    ],
    "tgn:id":2337758,
    "tgn:name":"Fox Creek",
    "tgn:placetype":[
        "aat:300008706"
    ]
},
  "bbox": [],
  "geometry": {"coordinates":[-113.3833,48.7],"type":"Point"}
}
=======
{"geometry":{"type":"Point","coordinates":[-113.383300,48.700000]},"type":"Feature","properties":{"hierarchy":["tgn:2337758","tgn:1000001","tgn:7012149","tgn:2001277","tgn:7007524","tgn:7029392"],"placetype":["aat:300008706"],"id":2337758,"name:xx":"Fox Creek"}}
>>>>>>> 03f74aca74312dbeaf24d7e61306dd6a786dc3d0
