{
  "id": 7280605,
  "type": "Feature",
  "properties": {
    "tgn:hierarchy":[
        "tgn:7280605",
        "tgn:1001695",
        "tgn:1000049",
        "tgn:1000002",
        "tgn:7029392"
    ],
    "tgn:id":7280605,
    "tgn:name":"Santa Rosa",
    "tgn:placetype":[
        "aat:300008777"
    ]
},
  "bbox": [],
  "geometry": {"coordinates":[-71.916667,-34.366667],"type":"Point"}
}