{
  "id": 2659323,
  "type": "Feature",
  "properties": {
    "tgn:hierarchy":[
        "tgn:2659323",
        "tgn:1000001",
        "tgn:7012149",
        "tgn:7021746",
        "tgn:7007826",
        "tgn:7029392"
    ],
    "tgn:id":2659323,
    "tgn:name":"Shiloh Creek",
    "tgn:placetype":[
        "aat:300008706"
    ]
},
  "bbox": [],
  "geometry": {"coordinates":[-97.4333,29.05],"type":"Point"}
}