{
  "id": 1008226,
  "type": "Feature",
  "properties": {
    "tgn:hierarchy":[
        "tgn:1008226",
        "tgn:7000509",
        "tgn:1008380",
        "tgn:1000226",
        "tgn:1000006",
        "tgn:7029392"
    ],
    "tgn:id":1008226,
    "tgn:name:en":"Motiti Island",
    "tgn:placetype":[
        "aat:300008791"
    ]
},
  "bbox": [],
  "geometry": {"coordinates":[176.4333,-37.633],"type":"Point"}
}