<<<<<<< HEAD
{
  "id": 7249207,
  "type": "Feature",
  "properties": {
    "tgn:hierarchy":[
        "tgn:7249207",
        "tgn:7003465",
        "tgn:1000003",
        "tgn:1000063",
        "tgn:4012014",
        "tgn:7029392"
    ],
    "tgn:id":7249207,
    "tgn:name":"Monaville",
    "tgn:placetype":[
        "aat:300008347"
    ]
},
  "bbox": [],
  "geometry": {"coordinates":[5.7,50.05],"type":"Point"}
}
=======
{"geometry":{"type":"Point","coordinates":[5.700000,50.050000]},"type":"Feature","properties":{"hierarchy":["tgn:7249207","tgn:7003465","tgn:1000003","tgn:1000063","tgn:4012014","tgn:7029392"],"placetype":["aat:300008347"],"id":7249207,"name:xx":"Monaville"}}
>>>>>>> 03f74aca74312dbeaf24d7e61306dd6a786dc3d0
