{
  "id": 7382704,
  "type": "Feature",
  "properties": {
    "tgn:hierarchy":[
        "tgn:7382704",
        "tgn:7005581",
        "tgn:1000001",
        "tgn:7005560",
        "tgn:7029392"
    ],
    "tgn:id":7382704,
    "tgn:name":"Morita",
    "tgn:placetype":[
        "aat:300008347"
    ]
},
  "bbox": [],
  "geometry": {"coordinates":[-105.45,27.05],"type":"Point"}
}