{
  "id": 2763590,
  "type": "Feature",
  "properties": {
    "tgn:hierarchy":[
        "tgn:2763590",
        "tgn:1000001",
        "tgn:2001410",
        "tgn:7012149",
        "tgn:7007526",
        "tgn:7029392"
    ],
    "tgn:id":2763590,
    "tgn:name":"Whale Rock",
    "tgn:placetype":[
        "aat:300008791",
        "aat:300008850"
    ]
},
  "bbox": [],
  "geometry": {"coordinates":[-114.3667,36.3333],"type":"Point"}
}