<<<<<<< HEAD
{
  "id": 2763590,
  "type": "Feature",
  "properties": {
    "tgn:hierarchy":[
        "tgn:2763590",
        "tgn:1000001",
        "tgn:2001410",
        "tgn:7012149",
        "tgn:7007526",
        "tgn:7029392"
    ],
    "tgn:id":2763590,
    "tgn:name":"Whale Rock",
    "tgn:placetype":[
        "aat:300008791",
        "aat:300008850"
    ]
},
  "bbox": [],
  "geometry": {"coordinates":[-114.3667,36.3333],"type":"Point"}
}
=======
{"geometry":{"type":"Point","coordinates":[-114.366700,36.333300]},"type":"Feature","properties":{"hierarchy":["tgn:2763590","tgn:1000001","tgn:2001410","tgn:7012149","tgn:7007526","tgn:7029392"],"placetype":["aat:300008791","aat:300008850"],"id":2763590,"name:xx":"Whale Rock"}}
>>>>>>> 03f74aca74312dbeaf24d7e61306dd6a786dc3d0
