{
  "id": 7287460,
  "type": "Feature",
  "properties": {
    "tgn:hierarchy":[
        "tgn:7287460",
        "tgn:1001702",
        "tgn:1000049",
        "tgn:1000002",
        "tgn:7029392"
    ],
    "tgn:id":7287460,
    "tgn:name":"Goodwin, Monte",
    "tgn:placetype":[
        "aat:300008795"
    ]
},
  "bbox": [],
  "geometry": {"coordinates":[-70.783333,-54.333333],"type":"Point"}
}