<<<<<<< HEAD
{
  "id": 2332171,
  "type": "Feature",
  "properties": {
    "tgn:hierarchy":[
        "tgn:2332171",
        "tgn:1000001",
        "tgn:7012149",
        "tgn:2001420",
        "tgn:7007526",
        "tgn:7029392"
    ],
    "tgn:id":2332171,
    "tgn:name":"Flint Spring Canyon",
    "tgn:placetype":[
        "aat:300008761"
    ]
},
  "bbox": [],
  "geometry": {"coordinates":[-114.9167,39.95],"type":"Point"}
}
=======
{"geometry":{"type":"Point","coordinates":[-114.916700,39.950000]},"type":"Feature","properties":{"hierarchy":["tgn:2332171","tgn:1000001","tgn:7012149","tgn:2001420","tgn:7007526","tgn:7029392"],"placetype":["aat:300008761"],"id":2332171,"name:xx":"Flint Spring Canyon"}}
>>>>>>> 03f74aca74312dbeaf24d7e61306dd6a786dc3d0
