{
  "id": 2437123,
  "type": "Feature",
  "properties": {
    "tgn:hierarchy":[
        "tgn:2437123",
        "tgn:1000001",
        "tgn:2002370",
        "tgn:7012149",
        "tgn:7007923",
        "tgn:7029392"
    ],
    "tgn:id":2437123,
    "tgn:name":"Kilpatrick Reservoir",
    "tgn:placetype":[
        "aat:300006191"
    ]
},
  "bbox": [],
  "geometry": {"coordinates":[-104.15,44.7833],"type":"Point"}
}