{
  "id": 7408179,
  "type": "Feature",
  "properties": {
    "tgn:hierarchy":[
        "tgn:7408179",
        "tgn:1000001",
        "tgn:7005590",
        "tgn:7005560",
        "tgn:7029392"
    ],
    "tgn:id":7408179,
    "tgn:name":"El Mirador",
    "tgn:placetype":[
        "aat:300008347"
    ]
},
  "bbox": [],
  "geometry": {"coordinates":[-101.866667,19.191667],"type":"Point"}
}