<<<<<<< HEAD
{
  "id": 7372661,
  "type": "Feature",
  "properties": {
    "tgn:hierarchy":[
        "tgn:7372661",
        "tgn:7005581",
        "tgn:1000001",
        "tgn:7005560",
        "tgn:7029392"
    ],
    "tgn:id":7372661,
    "tgn:name":"Rancho La Laborcita",
    "tgn:placetype":[
        "aat:300000241"
    ]
},
  "bbox": [],
  "geometry": {"coordinates":[-105.966667,28.316667],"type":"Point"}
}
=======
{"geometry":{"type":"Point","coordinates":[-105.966667,28.316667]},"type":"Feature","properties":{"hierarchy":["tgn:7372661","tgn:7005581","tgn:1000001","tgn:7005560","tgn:7029392"],"placetype":["aat:300000241"],"id":7372661,"name:xx":"Rancho La Laborcita"}}
>>>>>>> 03f74aca74312dbeaf24d7e61306dd6a786dc3d0
