{
  "id": 7260589,
  "type": "Feature",
  "properties": {
    "tgn:hierarchy":[
        "tgn:7260589",
        "tgn:1000003",
        "tgn:7003635",
        "tgn:7016845",
        "tgn:7029392"
    ],
    "tgn:id":7260589,
    "tgn:name:nl":"Groene Duin",
    "tgn:placetype":[
        "aat:300008750"
    ]
},
  "bbox": [],
  "geometry": {"coordinates":[3.716667,51.683333],"type":"Point"}
}