{
  "id": 2604164,
  "type": "Feature",
  "properties": {
    "tgn:hierarchy":[
        "tgn:2604164",
        "tgn:1000001",
        "tgn:7012149",
        "tgn:1002472",
        "tgn:7007568",
        "tgn:7029392"
    ],
    "tgn:id":2604164,
    "tgn:name":"Quiver Pond",
    "tgn:placetype":[
        "aat:300008680"
    ]
},
  "bbox": [],
  "geometry": {"coordinates":[-74.8667,43.7333],"type":"Point"}
}