{
  "id": 2271375,
  "type": "Feature",
  "properties": {
    "tgn:hierarchy":[
        "tgn:2271375",
        "tgn:1000001",
        "tgn:7012149",
        "tgn:2002381",
        "tgn:7007923",
        "tgn:7029392"
    ],
    "tgn:id":2271375,
    "tgn:name":"Cultra Reservoir",
    "tgn:placetype":[
        "aat:300006191"
    ]
},
  "bbox": [],
  "geometry": {"coordinates":[-106.1667,44.75],"type":"Point"}
}