{
  "id": 7297755,
  "type": "Feature",
  "properties": {
    "tgn:hierarchy":[
        "tgn:7297755",
        "tgn:7001122",
        "tgn:1000003",
        "tgn:7002765",
        "tgn:1000095",
        "tgn:7029392"
    ],
    "tgn:id":7297755,
    "tgn:name":"Son Veri",
    "tgn:placetype":[
        "aat:300008347"
    ]
},
  "bbox": [],
  "geometry": {"coordinates":[2.75,39.483333],"type":"Point"}
}