{
  "id": 7287171,
  "type": "Feature",
  "properties": {
    "tgn:hierarchy":[
        "tgn:7287171",
        "tgn:1001623",
        "tgn:1000049",
        "tgn:1000002",
        "tgn:7029392"
    ],
    "tgn:id":7287171,
    "tgn:name":"Gatica, Isla",
    "tgn:placetype":[
        "aat:300008791"
    ]
},
  "bbox": [],
  "geometry": {"coordinates":[-73.583333,-45.133333],"type":"Point"}
}