{
  "id": 7406241,
  "type": "Feature",
  "properties": {
    "tgn:hierarchy":[
        "tgn:7406241",
        "tgn:7005578",
        "tgn:1000001",
        "tgn:7005560",
        "tgn:7029392"
    ],
    "tgn:id":7406241,
    "tgn:name":"El Tesoro",
    "tgn:placetype":[
        "aat:300008347"
    ]
},
  "bbox": [],
  "geometry": {"coordinates":[-89.166667,18.15],"type":"Point"}
}