{
  "id": 2665580,
  "type": "Feature",
  "properties": {
    "tgn:hierarchy":[
        "tgn:2665580",
        "tgn:1000001",
        "tgn:7012149",
        "tgn:2001911",
        "tgn:7007825",
        "tgn:7029392"
    ],
    "tgn:id":2665580,
    "tgn:name":"Sinking Creek",
    "tgn:placetype":[
        "aat:300008706"
    ]
},
  "bbox": [],
  "geometry": {"coordinates":[-86.5333,36.0167],"type":"Point"}
}