{
  "id": 7504099,
  "type": "Feature",
  "properties": {
    "tgn:hierarchy":[
        "tgn:7504099",
        "tgn:1009227",
        "tgn:1000226",
        "tgn:7520095",
        "tgn:1000006",
        "tgn:7029392"
    ],
    "tgn:id":7504099,
    "tgn:name:en":"Webb Stream",
    "tgn:placetype":[
        "aat:300008699"
    ]
},
  "bbox": [],
  "geometry": {"coordinates":[172.366667,-40.716667],"type":"Point"}
}