{
  "id": 2628545,
  "type": "Feature",
  "properties": {
    "tgn:hierarchy":[
        "tgn:2628545",
        "tgn:1000001",
        "tgn:2002107",
        "tgn:7012149",
        "tgn:7007827",
        "tgn:7029392"
    ],
    "tgn:id":2628545,
    "tgn:name":"Roosevelt Lateral",
    "tgn:placetype":[
        "aat:300006075"
    ]
},
  "bbox": [],
  "geometry": {"coordinates":[-110.0167,40.35],"type":"Point"}
}