{
  "id": 7189788,
  "type": "Feature",
  "properties": {
    "tgn:hierarchy":[
        "tgn:7189788",
        "tgn:1000003",
        "tgn:7000094",
        "tgn:7000084",
        "tgn:7029392"
    ],
    "tgn:id":7189788,
    "tgn:name":"Einhusen",
    "tgn:placetype":[
        "aat:300008347"
    ]
},
  "bbox": [],
  "geometry": {"coordinates":[11.85,54.033333],"type":"Point"}
}