{
  "id": 1018193,
  "type": "Feature",
  "properties": {
    "tgn:hierarchy":[
        "tgn:1018193",
        "tgn:1000001",
        "tgn:7005601",
        "tgn:7005560",
        "tgn:7029392"
    ],
    "tgn:id":1018193,
    "tgn:name":"San Jos\u00e9 de Llanetes",
    "tgn:placetype":[
        "aat:300008347"
    ]
},
  "bbox": [],
  "geometry": {"coordinates":[-103.266667,22.916667],"type":"Point"}
}