{
  "id": 2557844,
  "type": "Feature",
  "properties": {
    "tgn:hierarchy":[
        "tgn:2557844",
        "tgn:1000001",
        "tgn:7012149",
        "tgn:1002742",
        "tgn:7007920",
        "tgn:7029392"
    ],
    "tgn:id":2557844,
    "tgn:name":"Old Sheridan Mine",
    "tgn:placetype":[
        "aat:300000390"
    ]
},
  "bbox": [],
  "geometry": {"coordinates":[-118.85,48.7667],"type":"Point"}
}