{
  "id": 2778657,
  "type": "Feature",
  "properties": {
    "tgn:hierarchy":[
        "tgn:2778657",
        "tgn:1000001",
        "tgn:1002222",
        "tgn:7012149",
        "tgn:7007520",
        "tgn:7029392"
    ],
    "tgn:id":2778657,
    "tgn:name":"Wolcott Lake",
    "tgn:placetype":[
        "aat:300008680"
    ]
},
  "bbox": [],
  "geometry": {"coordinates":[-84.7833,42.2833],"type":"Point"}
}