{
  "id": 7488985,
  "type": "Feature",
  "properties": {
    "tgn:hierarchy":[
        "tgn:7488985",
        "tgn:7001004",
        "tgn:1000004",
        "tgn:1000141",
        "tgn:7029392"
    ],
    "tgn:id":7488985,
    "tgn:name":"Kulinghu",
    "tgn:placetype":[
        "aat:300008347"
    ]
},
  "bbox": [],
  "geometry": {"coordinates":[120.416944,22.943056],"type":"Point"}
}