<<<<<<< HEAD
{
  "id": 2338797,
  "type": "Feature",
  "properties": {
    "tgn:hierarchy":[
        "tgn:2338797",
        "tgn:1000001",
        "tgn:7012149",
        "tgn:2000972",
        "tgn:7007520",
        "tgn:7029392"
    ],
    "tgn:id":2338797,
    "tgn:name":"Frank Lake",
    "tgn:placetype":[
        "aat:300008680"
    ]
},
  "bbox": [],
  "geometry": {"coordinates":[-85.8333,46.4833],"type":"Point"}
}
=======
{"geometry":{"type":"Point","coordinates":[-85.833300,46.483300]},"type":"Feature","properties":{"hierarchy":["tgn:2338797","tgn:1000001","tgn:7012149","tgn:2000972","tgn:7007520","tgn:7029392"],"placetype":["aat:300008680"],"id":2338797,"name:xx":"Frank Lake"}}
>>>>>>> 03f74aca74312dbeaf24d7e61306dd6a786dc3d0
