{
  "id": 2629347,
  "type": "Feature",
  "properties": {
    "tgn:hierarchy":[
        "tgn:2629347",
        "tgn:1000001",
        "tgn:2001416",
        "tgn:7012149",
        "tgn:7007526",
        "tgn:7029392"
    ],
    "tgn:id":2629347,
    "tgn:name":"Rosebud Spring",
    "tgn:placetype":[
        "aat:300008697"
    ]
},
  "bbox": [],
  "geometry": {"coordinates":[-114.7167,38.5167],"type":"Point"}
}