{
  "id": 2331229,
  "type": "Feature",
  "properties": {
    "tgn:hierarchy":[
        "tgn:2331229",
        "tgn:1000001",
        "tgn:2002144",
        "tgn:7012149",
        "tgn:7007919",
        "tgn:7029392"
    ],
    "tgn:id":2331229,
    "tgn:name":"Flat Top Mountain",
    "tgn:placetype":[
        "aat:300008798"
    ]
},
  "bbox": [],
  "geometry": {"coordinates":[-79.5667,37.45],"type":"Point"}
}