{
  "id": 7498681,
  "type": "Feature",
  "properties": {
    "tgn:hierarchy":[
        "tgn:7498681",
        "tgn:1000004",
        "tgn:7001009",
        "tgn:1000141",
        "tgn:7029392"
    ],
    "tgn:id":7498681,
    "tgn:name":"Lincuo Yihao Qiao",
    "tgn:placetype":[
        "aat:300007836"
    ]
},
  "bbox": [],
  "geometry": {"coordinates":[120.6142,24.2009],"type":"Point"}
}