{
  "id": 7141572,
  "type": "Feature",
  "properties": {
    "tgn:hierarchy":[
        "tgn:7141572",
        "tgn:1000003",
        "tgn:7003688",
        "tgn:7000084",
        "tgn:7029392"
    ],
    "tgn:id":7141572,
    "tgn:name":"Lundenberger Sand",
    "tgn:placetype":[
        "aat:300386970"
    ]
},
  "bbox": [],
  "geometry": {"coordinates":[8.966667,54.466667],"type":"Point"}
}