{
  "id": 2697481,
  "type": "Feature",
  "properties": {
    "tgn:hierarchy":[
        "tgn:2697481",
        "tgn:1000001",
        "tgn:7012149",
        "tgn:2001029",
        "tgn:7007521",
        "tgn:7029392"
    ],
    "tgn:id":2697481,
    "tgn:name":"Stony Point",
    "tgn:placetype":[
        "aat:300008850"
    ]
},
  "bbox": [],
  "geometry": {"coordinates":[-93.5667,47.1667],"type":"Point"}
}