{
  "id": 7415806,
  "type": "Feature",
  "properties": {
    "tgn:hierarchy":[
        "tgn:7415806",
        "tgn:7005584",
        "tgn:1000001",
        "tgn:7005560",
        "tgn:7029392"
    ],
    "tgn:id":7415806,
    "tgn:name":"Lobera, Arroyo",
    "tgn:placetype":[
        "aat:300266554",
        "aat:300008699"
    ]
},
  "bbox": [],
  "geometry": {"coordinates":[-101.206944,20.828056],"type":"Point"}
}