{
  "id": 7002952,
  "type": "Feature",
  "properties": {
    "tgn:hierarchy":[
        "tgn:7002952",
        "tgn:1000003",
        "tgn:7012216",
        "tgn:1000070",
        "tgn:7029392"
    ],
    "tgn:id":7002952,
    "tgn:name":"Ille-et-Vilaine",
    "tgn:placetype":[
        "aat:300387145",
        "aat:300000772"
    ]
},
  "bbox": [],
  "geometry": {"coordinates":[-1.5833,48.1667],"type":"Point"}
}