{
  "id": 7423522,
  "type": "Feature",
  "properties": {
    "tgn:hierarchy":[
        "tgn:7423522",
        "tgn:1000001",
        "tgn:7005590",
        "tgn:7005560",
        "tgn:7029392"
    ],
    "tgn:id":7423522,
    "tgn:name":"Puerta el Naranjo",
    "tgn:placetype":[
        "aat:300008347"
    ]
},
  "bbox": [],
  "geometry": {"coordinates":[-101.383056,19.018889],"type":"Point"}
}