{
  "id": 2679114,
  "type": "Feature",
  "properties": {
    "tgn:hierarchy":[
        "tgn:2679114",
        "tgn:1000001",
        "tgn:2002102",
        "tgn:7012149",
        "tgn:7007827",
        "tgn:7029392"
    ],
    "tgn:id":2679114,
    "tgn:name":"South Fork Junction Creek",
    "tgn:placetype":[
        "aat:300008706"
    ]
},
  "bbox": [],
  "geometry": {"coordinates":[-113.7167,41.75],"type":"Point"}
}