{
  "id": 7220981,
  "type": "Feature",
  "properties": {
    "tgn:hierarchy":[
        "tgn:7220981",
        "tgn:7011164",
        "tgn:7002674",
        "tgn:1000003",
        "tgn:1000074",
        "tgn:7029392"
    ],
    "tgn:id":7220981,
    "tgn:name":"Valeont\u00e1des",
    "tgn:placetype":[
        "aat:300008347"
    ]
},
  "bbox": [],
  "geometry": {"coordinates":[26.828889,37.792222],"type":"Point"}
}