{
  "id": 7249625,
  "type": "Feature",
  "properties": {
    "tgn:hierarchy":[
        "tgn:7249625",
        "tgn:7003461",
        "tgn:1000003",
        "tgn:1000063",
        "tgn:7018236",
        "tgn:7029392"
    ],
    "tgn:id":7249625,
    "tgn:name":"Nieuwstraat",
    "tgn:placetype":[
        "aat:300008347"
    ]
},
  "bbox": [],
  "geometry": {"coordinates":[5.316667,51.016667],"type":"Point"}
}