{
  "id": 7396567,
  "type": "Feature",
  "properties": {
    "tgn:hierarchy":[
        "tgn:7396567",
        "tgn:7005583",
        "tgn:1000001",
        "tgn:7005560",
        "tgn:7029392"
    ],
    "tgn:id":7396567,
    "tgn:name":"San Miguel",
    "tgn:placetype":[
        "aat:300008347"
    ]
},
  "bbox": [],
  "geometry": {"coordinates":[-103.633333,26.316667],"type":"Point"}
}