{
  "id": 2453006,
  "type": "Feature",
  "properties": {
    "tgn:hierarchy":[
        "tgn:2453006",
        "tgn:7002659",
        "tgn:1000001",
        "tgn:2000003",
        "tgn:7012149",
        "tgn:7029392"
    ],
    "tgn:id":2453006,
    "tgn:name":"Little Cane Creek",
    "tgn:placetype":[
        "aat:300008706"
    ]
},
  "bbox": [],
  "geometry": {"coordinates":[-87.0833,33.1667],"type":"Point"}
}