{
  "id": 2707497,
  "type": "Feature",
  "properties": {
    "tgn:hierarchy":[
        "tgn:2707497",
        "tgn:1000001",
        "tgn:7012149",
        "tgn:1002917",
        "tgn:7007706",
        "tgn:7029392"
    ],
    "tgn:id":2707497,
    "tgn:name":"Sweetbriar",
    "tgn:placetype":[
        "aat:300008347"
    ]
},
  "bbox": [],
  "geometry": {"coordinates":[-81.4167,40.8333],"type":"Point"}
}