{
  "id": 2647639,
  "type": "Feature",
  "properties": {
    "tgn:hierarchy":[
        "tgn:2647639",
        "tgn:1000001",
        "tgn:7012149",
        "tgn:2001040",
        "tgn:7007521",
        "tgn:7029392"
    ],
    "tgn:id":2647639,
    "tgn:name":"School Grove Lake",
    "tgn:placetype":[
        "aat:300008680"
    ]
},
  "bbox": [],
  "geometry": {"coordinates":[-95.6167,44.55],"type":"Point"}
}