{
  "id": 2623744,
  "type": "Feature",
  "properties": {
    "tgn:hierarchy":[
        "tgn:2623744",
        "tgn:1000001",
        "tgn:7012149",
        "tgn:2001867",
        "tgn:7007825",
        "tgn:7029392"
    ],
    "tgn:id":2623744,
    "tgn:name":"Rock Creek",
    "tgn:placetype":[
        "aat:300008706"
    ]
},
  "bbox": [],
  "geometry": {"coordinates":[-85.8667,35.4167],"type":"Point"}
}