{
  "id": 2626553,
  "type": "Feature",
  "properties": {
    "tgn:hierarchy":[
        "tgn:2626553",
        "tgn:1000001",
        "tgn:7012149",
        "tgn:2001846",
        "tgn:7007825",
        "tgn:7029392"
    ],
    "tgn:id":2626553,
    "tgn:name":"Rocky Hollow Branch",
    "tgn:placetype":[
        "aat:300008699"
    ]
},
  "bbox": [],
  "geometry": {"coordinates":[-81.9833,36.4333],"type":"Point"}
}