{
  "id": 7561742,
  "type": "Feature",
  "properties": {
    "tgn:hierarchy":[
        "tgn:7561742",
        "tgn:1000004",
        "tgn:7000198",
        "tgn:7016722",
        "tgn:7029392"
    ],
    "tgn:id":7561742,
    "tgn:name:en":"Ahl\u0101dpur",
    "tgn:placetype":[
        "aat:300008347"
    ]
},
  "bbox": [],
  "geometry": {"coordinates":[79.041357,26.821604],"type":"Point"}
}