{
  "id": 7229396,
  "type": "Feature",
  "properties": {
    "tgn:hierarchy":[
        "tgn:7229396",
        "tgn:7002681",
        "tgn:7001395",
        "tgn:1000003",
        "tgn:1000074",
        "tgn:7029392"
    ],
    "tgn:id":7229396,
    "tgn:name":"Kir Ann\u00edtsa, \u00c1kra",
    "tgn:placetype":[
        "aat:300008850"
    ]
},
  "bbox": [],
  "geometry": {"coordinates":[23.55,37.733333],"type":"Point"}
}