{
  "id": 7592870,
  "type": "Feature",
  "properties": {
    "tgn:hierarchy":[
        "tgn:7592870",
        "tgn:1000004",
        "tgn:7000198",
        "tgn:7000799",
        "tgn:7029392"
    ],
    "tgn:id":7592870,
    "tgn:name:en":"D\u0101ndak",
    "tgn:placetype":[
        "aat:300008347"
    ]
},
  "bbox": [],
  "geometry": {"coordinates":[74.352778,33.075],"type":"Point"}
}