{
  "id": 7478159,
  "type": "Feature",
  "properties": {
    "tgn:hierarchy":[
        "tgn:7478159",
        "tgn:7487020",
        "tgn:1000004",
        "tgn:1000141",
        "tgn:7029392"
    ],
    "tgn:id":7478159,
    "tgn:name":"Jiadong Shan",
    "tgn:placetype":[
        "aat:300008777"
    ]
},
  "bbox": [],
  "geometry": {"coordinates":[120.856521,24.623708],"type":"Point"}
}