{
  "id": 1012630,
  "type": "Feature",
  "properties": {
    "tgn:hierarchy":[
        "tgn:1012630",
        "tgn:7005685",
        "tgn:1000001",
        "tgn:7013154",
        "tgn:7029392"
    ],
    "tgn:id":1012630,
    "tgn:name":"Windmill Point",
    "tgn:placetype":[
        "aat:300386846"
    ]
},
  "bbox": [],
  "geometry": {"coordinates":[-79.0167,42.8667],"type":"Point"}
}