{
  "id": 7199154,
  "type": "Feature",
  "properties": {
    "tgn:hierarchy":[
        "tgn:7199154",
        "tgn:1000003",
        "tgn:7003677",
        "tgn:7000084",
        "tgn:7029392"
    ],
    "tgn:id":7199154,
    "tgn:name":"Ebbinghausen",
    "tgn:placetype":[
        "aat:300008347"
    ]
},
  "bbox": [],
  "geometry": {"coordinates":[8.833333,51.616667],"type":"Point"}
}