<<<<<<< HEAD
{
  "id": 2337237,
  "type": "Feature",
  "properties": {
    "tgn:hierarchy":[
        "tgn:2337237",
        "tgn:1000001",
        "tgn:7012149",
        "tgn:2001067",
        "tgn:7007521",
        "tgn:7029392"
    ],
    "tgn:id":2337237,
    "tgn:name":"Fourth Lake",
    "tgn:placetype":[
        "aat:300008680"
    ]
},
  "bbox": [],
  "geometry": {"coordinates":[-92.35,47.4667],"type":"Point"}
}
=======
{"geometry":{"type":"Point","coordinates":[-92.350000,47.466700]},"type":"Feature","properties":{"hierarchy":["tgn:2337237","tgn:1000001","tgn:7012149","tgn:2001067","tgn:7007521","tgn:7029392"],"placetype":["aat:300008680"],"id":2337237,"name:xx":"Fourth Lake"}}
>>>>>>> 03f74aca74312dbeaf24d7e61306dd6a786dc3d0
