{
  "id": 1072584,
  "type": "Feature",
  "properties": {
    "tgn:hierarchy":[
        "tgn:1072584",
        "tgn:1000004",
        "tgn:1001390",
        "tgn:1000111",
        "tgn:7029392"
    ],
    "tgn:id":1072584,
    "tgn:name":"Wenquansi",
    "tgn:placetype":[
        "aat:300008347"
    ]
},
  "bbox": [],
  "geometry": {"coordinates":[124.0333,41.35],"type":"Point"}
}