<<<<<<< HEAD
{
  "id": 7175809,
  "type": "Feature",
  "properties": {
    "tgn:hierarchy":[
        "tgn:7175809",
        "tgn:1000003",
        "tgn:7000094",
        "tgn:7000084",
        "tgn:7029392"
    ],
    "tgn:id":7175809,
    "tgn:name":"Gro\u00df Welzin",
    "tgn:placetype":[
        "aat:300008347"
    ]
},
  "bbox": [],
  "geometry": {"coordinates":[11.2,53.6],"type":"Point"}
}
=======
{"geometry":{"type":"Point","coordinates":[11.200000,53.600000]},"type":"Feature","properties":{"hierarchy":["tgn:7175809","tgn:1000003","tgn:7000094","tgn:7000084","tgn:7029392"],"placetype":["aat:300008347"],"id":7175809,"name:xx":"Gro\u00df Welzin"}}
>>>>>>> 03f74aca74312dbeaf24d7e61306dd6a786dc3d0
