{
  "id": 7161705,
  "type": "Feature",
  "properties": {
    "tgn:hierarchy":[
        "tgn:7161705",
        "tgn:1000003",
        "tgn:7003677",
        "tgn:7000084",
        "tgn:7029392"
    ],
    "tgn:id":7161705,
    "tgn:name":"Hohe-Bracke",
    "tgn:placetype":[
        "aat:300008777"
    ]
},
  "bbox": [],
  "geometry": {"coordinates":[8.216667,51.433333],"type":"Point"}
}