{
  "id": 2441003,
  "type": "Feature",
  "properties": {
    "tgn:hierarchy":[
        "tgn:2441003",
        "tgn:1002165",
        "tgn:1000001",
        "tgn:7012149",
        "tgn:7007517",
        "tgn:7029392"
    ],
    "tgn:id":2441003,
    "tgn:name":"Knob, The",
    "tgn:placetype":[
        "aat:300008798"
    ]
},
  "bbox": [],
  "geometry": {"coordinates":[-70.65,41.5333],"type":"Point"}
}