{
  "id": 1069596,
  "type": "Feature",
  "properties": {
    "tgn:hierarchy":[
        "tgn:1069596",
        "tgn:1000004",
        "tgn:7005232",
        "tgn:1000111",
        "tgn:7029392"
    ],
    "tgn:id":1069596,
    "tgn:name":"L\u00fctian",
    "tgn:placetype":[
        "aat:300008347"
    ]
},
  "bbox": [],
  "geometry": {"coordinates":[113.9333,23.7667],"type":"Point"}
}