{
  "id": 7251859,
  "type": "Feature",
  "properties": {
    "tgn:hierarchy":[
        "tgn:7251859",
        "tgn:7007877",
        "tgn:1000003",
        "tgn:1000063",
        "tgn:4012014",
        "tgn:7029392"
    ],
    "tgn:id":7251859,
    "tgn:name":"Ferme Mayeux",
    "tgn:placetype":[
        "aat:300000206"
    ]
},
  "bbox": [],
  "geometry": {"coordinates":[4.35,50.633333],"type":"Point"}
}