{
  "id": 7431949,
  "type": "Feature",
  "properties": {
    "tgn:hierarchy":[
        "tgn:7431949",
        "tgn:1000001",
        "tgn:7005595",
        "tgn:7005560",
        "tgn:7029392"
    ],
    "tgn:id":7431949,
    "tgn:name":"Dieciocho",
    "tgn:placetype":[
        "aat:300008347"
    ]
},
  "bbox": [],
  "geometry": {"coordinates":[-106.883333,23.116667],"type":"Point"}
}