{
  "id": 2180293,
  "type": "Feature",
  "properties": {
    "tgn:hierarchy":[
        "tgn:2180293",
        "tgn:1000001",
        "tgn:7012149",
        "tgn:1002900",
        "tgn:7007710",
        "tgn:7029392"
    ],
    "tgn:id":2180293,
    "tgn:name":"Block Ore Ridge",
    "tgn:placetype":[
        "aat:300266640"
    ]
},
  "bbox": [],
  "geometry": {"coordinates":[-77.05,40.75],"type":"Point"}
}