<<<<<<< HEAD
{
  "id": 7479169,
  "type": "Feature",
  "properties": {
    "tgn:hierarchy":[
        "tgn:7479169",
        "tgn:1000004",
        "tgn:7490934",
        "tgn:1000141",
        "tgn:7029392"
    ],
    "tgn:id":7479169,
    "tgn:name":"Diqiucun Leyuan",
    "tgn:placetype":[
        "aat:300008187"
    ]
},
  "bbox": [],
  "geometry": {"coordinates":[120.167222,23.071111],"type":"Point"}
}
=======
{"geometry":{"type":"Point","coordinates":[120.167222,23.071111]},"type":"Feature","properties":{"hierarchy":["tgn:7479169","tgn:1000004","tgn:7490934","tgn:1000141","tgn:7029392"],"placetype":["aat:300008187"],"id":7479169,"name:xx":"Diqiucun Leyuan"}}
>>>>>>> 03f74aca74312dbeaf24d7e61306dd6a786dc3d0
