{
  "id": 7479169,
  "type": "Feature",
  "properties": {
    "tgn:hierarchy":[
        "tgn:7479169",
        "tgn:1000004",
        "tgn:7490934",
        "tgn:1000141",
        "tgn:7029392"
    ],
    "tgn:id":7479169,
    "tgn:name":"Diqiucun Leyuan",
    "tgn:placetype":[
        "aat:300008187"
    ]
},
  "bbox": [],
  "geometry": {"coordinates":[120.167222,23.071111],"type":"Point"}
}