{
  "id": 2736317,
  "type": "Feature",
  "properties": {
    "tgn:hierarchy":[
        "tgn:2736317",
        "tgn:1000001",
        "tgn:7012149",
        "tgn:2000488",
        "tgn:7007250",
        "tgn:7029392"
    ],
    "tgn:id":2736317,
    "tgn:name":"Twin Peaks",
    "tgn:placetype":[
        "aat:300008798"
    ]
},
  "bbox": [],
  "geometry": {"coordinates":[-116.85,43.0833],"type":"Point"}
}