{
  "id": 2595781,
  "type": "Feature",
  "properties": {
    "tgn:hierarchy":[
        "tgn:2595781",
        "tgn:1000001",
        "tgn:7012149",
        "tgn:7007522",
        "tgn:7029392"
    ],
    "tgn:id":2595781,
    "tgn:name":"Potlockney Creek",
    "tgn:placetype":[
        "aat:300008706"
    ]
},
  "bbox": [],
  "geometry": {"coordinates":[-89.3167,34.15],"type":"Point"}
}