{
  "id": 7534869,
  "type": "Feature",
  "properties": {
    "tgn:hierarchy":[
        "tgn:7534869",
        "tgn:7001242",
        "tgn:7016833",
        "tgn:1001418",
        "tgn:7029392"
    ],
    "tgn:id":7534869,
    "tgn:name:en":"Kafr Abu Habhab",
    "tgn:placetype":[
        "aat:300008347"
    ]
},
  "bbox": [],
  "geometry": {"coordinates":[26.85,31.433333],"type":"Point"}
}