{
  "id": 7099643,
  "type": "Feature",
  "properties": {
    "tgn:hierarchy":[
        "tgn:7099643",
        "tgn:7003669",
        "tgn:1000003",
        "tgn:7000084",
        "tgn:7029392"
    ],
    "tgn:id":7099643,
    "tgn:name":"Siegst\u00e4tt",
    "tgn:placetype":[
        "aat:300000206"
    ]
},
  "bbox": [],
  "geometry": {"coordinates":[11.933333,48.166667],"type":"Point"}
}