{
  "id": 2149531,
  "type": "Feature",
  "properties": {
    "tgn:hierarchy":[
        "tgn:2149531",
        "tgn:1000001",
        "tgn:7012149",
        "tgn:2001868",
        "tgn:7007825",
        "tgn:7029392"
    ],
    "tgn:id":2149531,
    "tgn:name":"Barrett Pond",
    "tgn:placetype":[
        "aat:300008680"
    ]
},
  "bbox": [],
  "geometry": {"coordinates":[-83.3333,36.1833],"type":"Point"}
}