{
  "id": 7046367,
  "type": "Feature",
  "properties": {
    "tgn:hierarchy":[
        "tgn:7046367",
        "tgn:1001641",
        "tgn:1000003",
        "tgn:7003121",
        "tgn:1000080",
        "tgn:7029392"
    ],
    "tgn:id":7046367,
    "tgn:name":"Collinas",
    "tgn:placetype":[
        "aat:300008347"
    ]
},
  "bbox": [],
  "geometry": {"coordinates":[8.841389,39.642778],"type":"Point"}
}