{
  "id": 2507294,
  "type": "Feature",
  "properties": {
    "tgn:hierarchy":[
        "tgn:2507294",
        "tgn:1000001",
        "tgn:7006451",
        "tgn:2000094",
        "tgn:7012149",
        "tgn:7029392"
    ],
    "tgn:id":2507294,
    "tgn:name":"Mexican Canyon",
    "tgn:placetype":[
        "aat:300008761"
    ]
},
  "bbox": [],
  "geometry": {"coordinates":[-110.0167,32.7833],"type":"Point"}
}