{
  "id": 2296203,
  "type": "Feature",
  "properties": {
    "tgn:hierarchy":[
        "tgn:2296203",
        "tgn:1000001",
        "tgn:7012149",
        "tgn:2001254",
        "tgn:7007523",
        "tgn:7029392"
    ],
    "tgn:id":2296203,
    "tgn:name":"Dry Branch",
    "tgn:placetype":[
        "aat:300008699"
    ]
},
  "bbox": [],
  "geometry": {"coordinates":[-90.8833,38.1167],"type":"Point"}
}