{
  "id": 7275428,
  "type": "Feature",
  "properties": {
    "tgn:hierarchy":[
        "tgn:7275428",
        "tgn:1001637",
        "tgn:1000049",
        "tgn:1000002",
        "tgn:7029392"
    ],
    "tgn:id":7275428,
    "tgn:name":"Trup\u00e1n, Meseta",
    "tgn:placetype":[
        "aat:300132339"
    ]
},
  "bbox": [],
  "geometry": {"coordinates":[-71.75,-37.266667],"type":"Point"}
}