{
  "id": 2170229,
  "type": "Feature",
  "properties": {
    "tgn:hierarchy":[
        "tgn:2170229",
        "tgn:1000001",
        "tgn:7006451",
        "tgn:7012149",
        "tgn:2000103",
        "tgn:7029392"
    ],
    "tgn:id":2170229,
    "tgn:name":"Big Reef Mill",
    "tgn:placetype":[
        "aat:300008347"
    ]
},
  "bbox": [],
  "geometry": {"coordinates":[-112.4833,33.95],"type":"Point"}
}