{
  "id": 7348115,
  "type": "Feature",
  "properties": {
    "tgn:hierarchy":[
        "tgn:7348115",
        "tgn:7008911",
        "tgn:1000003",
        "tgn:7002763",
        "tgn:1000095",
        "tgn:7029392"
    ],
    "tgn:id":7348115,
    "tgn:name":"Aballe",
    "tgn:placetype":[
        "aat:300008347"
    ]
},
  "bbox": [],
  "geometry": {"coordinates":[-5.133333,43.333333],"type":"Point"}
}