{
  "id": 7368273,
  "type": "Feature",
  "properties": {
    "tgn:hierarchy":[
        "tgn:7368273",
        "tgn:1001853",
        "tgn:1000001",
        "tgn:7005560",
        "tgn:7029392"
    ],
    "tgn:id":7368273,
    "tgn:name":"Jorobado",
    "tgn:placetype":[
        "aat:300008347"
    ]
},
  "bbox": [],
  "geometry": {"coordinates":[-101.916667,26.45],"type":"Point"}
}