{
  "id": 7194457,
  "type": "Feature",
  "properties": {
    "tgn:hierarchy":[
        "tgn:7194457",
        "tgn:1000003",
        "tgn:7003689",
        "tgn:7000084",
        "tgn:7029392"
    ],
    "tgn:id":7194457,
    "tgn:name":"D\u00f6hlau",
    "tgn:placetype":[
        "aat:300008347"
    ]
},
  "bbox": [],
  "geometry": {"coordinates":[11.05,50.366667],"type":"Point"}
}