{
  "id": 5003517,
  "type": "Feature",
  "properties": {
    "tgn:hierarchy":[
        "tgn:5003517",
        "tgn:7008911",
        "tgn:1000003",
        "tgn:7002763",
        "tgn:1000095",
        "tgn:7029392"
    ],
    "tgn:id":5003517,
    "tgn:name":"Priesca",
    "tgn:placetype":[
        "aat:300008347"
    ]
},
  "bbox": [],
  "geometry": {"coordinates":[-5.35,43.483333],"type":"Point"}
}