{
  "id": 2104862,
  "type": "Feature",
  "properties": {
    "tgn:hierarchy":[
        "tgn:2104862",
        "tgn:1000001",
        "tgn:7012149",
        "tgn:1002214",
        "tgn:7007826",
        "tgn:7029392"
    ],
    "tgn:id":2104862,
    "tgn:name":"Hogg",
    "tgn:placetype":[
        "aat:300008347",
        "aat:300387210"
    ]
},
  "bbox": [],
  "geometry": {"coordinates":[-96.7833,30.4333],"type":"Point"}
}