{
  "id": 7297496,
  "type": "Feature",
  "properties": {
    "tgn:hierarchy":[
        "tgn:7297496",
        "tgn:7002844",
        "tgn:7030216",
        "tgn:1000003",
        "tgn:1000095",
        "tgn:7029392"
    ],
    "tgn:id":7297496,
    "tgn:name":"Sur\u00f3",
    "tgn:placetype":[
        "aat:300008795"
    ]
},
  "bbox": [],
  "geometry": {"coordinates":[1.308797,41.572824],"type":"Point"}
}