{
  "id": 2688867,
  "type": "Feature",
  "properties": {
    "tgn:hierarchy":[
        "tgn:2688867",
        "tgn:1000001",
        "tgn:7012149",
        "tgn:7007826",
        "tgn:7029392"
    ],
    "tgn:id":2688867,
    "tgn:name":"Spurler Creek",
    "tgn:placetype":[
        "aat:300008706"
    ]
},
  "bbox": [],
  "geometry": {"coordinates":[-100.1167,28.7833],"type":"Point"}
}