{
  "id": 7530607,
  "type": "Feature",
  "properties": {
    "tgn:hierarchy":[
        "tgn:7530607",
        "tgn:7001242",
        "tgn:7016833",
        "tgn:1001083",
        "tgn:7029392"
    ],
    "tgn:id":7530607,
    "tgn:name":"Masjid ash Shaykh Mu\u1e29ammad Bin \u1e28amad \u0100l Th\u0101n",
    "tgn:placetype":[
        "aat:300007544"
    ]
},
  "bbox": [],
  "geometry": {"coordinates":[31.198155,30.013751],"type":"Point"}
}