{
  "id": 7506106,
  "type": "Feature",
  "properties": {
    "tgn:hierarchy":[
        "tgn:7506106",
        "tgn:1009227",
        "tgn:1000226",
        "tgn:7018437",
        "tgn:1000006",
        "tgn:7029392"
    ],
    "tgn:id":7506106,
    "tgn:name:en":"Scroggs Hill",
    "tgn:placetype":[
        "aat:300008795"
    ]
},
  "bbox": [],
  "geometry": {"coordinates":[170.316667,-45.916667],"type":"Point"}
}