{
  "id": 7076073,
  "type": "Feature",
  "properties": {
    "tgn:hierarchy":[
        "tgn:7076073",
        "tgn:1000003",
        "tgn:7003688",
        "tgn:7000084",
        "tgn:7029392"
    ],
    "tgn:id":7076073,
    "tgn:name":"Osbekgrund",
    "tgn:placetype":[
        "aat:300387036"
    ]
},
  "bbox": [],
  "geometry": {"coordinates":[9.445833,54.814722],"type":"Point"}
}