{
  "id": 2184394,
  "type": "Feature",
  "properties": {
    "tgn:hierarchy":[
        "tgn:2184394",
        "tgn:1000001",
        "tgn:7006451",
        "tgn:2000093",
        "tgn:7012149",
        "tgn:7029392"
    ],
    "tgn:id":2184394,
    "tgn:name":"Bobcat Tank Number Two",
    "tgn:placetype":[
        "aat:300006191"
    ]
},
  "bbox": [],
  "geometry": {"coordinates":[-111.0167,33.5833],"type":"Point"}
}