{
  "id": 7368203,
  "type": "Feature",
  "properties": {
    "tgn:hierarchy":[
        "tgn:7368203",
        "tgn:7005586",
        "tgn:1000001",
        "tgn:7005560",
        "tgn:7029392"
    ],
    "tgn:id":7368203,
    "tgn:name":"Iglesias, Isla",
    "tgn:placetype":[
        "aat:300008791"
    ]
},
  "bbox": [],
  "geometry": {"coordinates":[-104.816667,19.216667],"type":"Point"}
}