{
  "id": 7436243,
  "type": "Feature",
  "properties": {
    "tgn:hierarchy":[
        "tgn:7436243",
        "tgn:1000001",
        "tgn:7005595",
        "tgn:7005560",
        "tgn:7029392"
    ],
    "tgn:id":7436243,
    "tgn:name":"Canal Taxtes",
    "tgn:placetype":[
        "aat:300006075"
    ]
},
  "bbox": [],
  "geometry": {"coordinates":[-109.083333,25.733333],"type":"Point"}
}