{
  "id": 2723055,
  "type": "Feature",
  "properties": {
    "tgn:hierarchy":[
        "tgn:2723055",
        "tgn:1000001",
        "tgn:7006451",
        "tgn:2000092",
        "tgn:7012149",
        "tgn:7029392"
    ],
    "tgn:id":2723055,
    "tgn:name":"Tishepi Spring",
    "tgn:placetype":[
        "aat:300008697"
    ]
},
  "bbox": [],
  "geometry": {"coordinates":[-110.95,35.6833],"type":"Point"}
}