<<<<<<< HEAD
{
  "id": 7020233,
  "type": "Feature",
  "properties": {
    "tgn:hierarchy":[
        "tgn:7020233",
        "tgn:1000001",
        "tgn:7012149",
        "tgn:2001494",
        "tgn:7007709",
        "tgn:7029392"
    ],
    "tgn:id":7020233,
    "tgn:name":"Myers Lake",
    "tgn:placetype":[
        "aat:300006191"
    ]
},
  "bbox": [],
  "geometry": {"coordinates":[-80.2667,36.05],"type":"Point"}
}
=======
{"geometry":{"type":"Point","coordinates":[-80.266700,36.050000]},"type":"Feature","properties":{"hierarchy":["tgn:7020233","tgn:1000001","tgn:7012149","tgn:2001494","tgn:7007709","tgn:7029392"],"placetype":["aat:300006191"],"id":7020233,"name:xx":"Myers Lake"}}
>>>>>>> 03f74aca74312dbeaf24d7e61306dd6a786dc3d0
