{
  "id": 7020233,
  "type": "Feature",
  "properties": {
    "tgn:hierarchy":[
        "tgn:7020233",
        "tgn:1000001",
        "tgn:7012149",
        "tgn:2001494",
        "tgn:7007709",
        "tgn:7029392"
    ],
    "tgn:id":7020233,
    "tgn:name":"Myers Lake",
    "tgn:placetype":[
        "aat:300006191"
    ]
},
  "bbox": [],
  "geometry": {"coordinates":[-80.2667,36.05],"type":"Point"}
}