{
  "id": 1124225,
  "type": "Feature",
  "properties": {
    "tgn:hierarchy":[
        "tgn:1124225",
        "tgn:1000004",
        "tgn:7000198",
        "tgn:7029392"
    ],
    "tgn:id":1124225,
    "tgn:name":"Gobai",
    "tgn:placetype":[
        "aat:300008707"
    ]
},
  "bbox": [],
  "geometry": {"coordinates":[86.4667,23.6167],"type":"Point"}
}