{
  "id": 7567756,
  "type": "Feature",
  "properties": {
    "tgn:hierarchy":[
        "tgn:7567756",
        "tgn:1001828",
        "tgn:1000004",
        "tgn:7000198",
        "tgn:7029392"
    ],
    "tgn:id":7567756,
    "tgn:name:en":"Potraddipalli",
    "tgn:placetype":[
        "aat:300008347"
    ]
},
  "bbox": [],
  "geometry": {"coordinates":[78.921667,17.881111],"type":"Point"}
}