{
  "id": 2015429,
  "type": "Feature",
  "properties": {
    "tgn:hierarchy":[
        "tgn:2015429",
        "tgn:1000001",
        "tgn:7012149",
        "tgn:7007158",
        "tgn:2000251",
        "tgn:7029392"
    ],
    "tgn:id":2015429,
    "tgn:name":"Cripple Creek",
    "tgn:placetype":[
        "aat:300008347"
    ]
},
  "bbox": [],
  "geometry": {"coordinates":[-105.1667,38.7333],"type":"Point"}
}