{
  "id": 7117817,
  "type": "Feature",
  "properties": {
    "tgn:hierarchy":[
        "tgn:7117817",
        "tgn:1000003",
        "tgn:7003682",
        "tgn:7000084",
        "tgn:7029392"
    ],
    "tgn:id":7117817,
    "tgn:name":"Olzheimer Wald",
    "tgn:placetype":[
        "aat:300008863"
    ]
},
  "bbox": [],
  "geometry": {"coordinates":[6.416667,50.283333],"type":"Point"}
}