{
  "id": 7582335,
  "type": "Feature",
  "properties": {
    "tgn:hierarchy":[
        "tgn:7582335",
        "tgn:1000004",
        "tgn:7000198",
        "tgn:7016722",
        "tgn:7029392"
    ],
    "tgn:id":7582335,
    "tgn:name:en":"Jairw\u0101ra",
    "tgn:placetype":[
        "aat:300008347"
    ]
},
  "bbox": [],
  "geometry": {"coordinates":[78.34219,24.782378],"type":"Point"}
}