<<<<<<< HEAD
{
  "id": 2254341,
  "type": "Feature",
  "properties": {
    "tgn:hierarchy":[
        "tgn:2254341",
        "tgn:1000001",
        "tgn:7012149",
        "tgn:2000650",
        "tgn:7007253",
        "tgn:7029392"
    ],
    "tgn:id":2254341,
    "tgn:name":"Coon Creek",
    "tgn:placetype":[
        "aat:300008706"
    ]
},
  "bbox": [],
  "geometry": {"coordinates":[-92.3,41.0167],"type":"Point"}
}
=======
{"geometry":{"type":"Point","coordinates":[-92.300000,41.016700]},"type":"Feature","properties":{"hierarchy":["tgn:2254341","tgn:1000001","tgn:7012149","tgn:2000650","tgn:7007253","tgn:7029392"],"placetype":["aat:300008706"],"id":2254341,"name:xx":"Coon Creek"}}
>>>>>>> 03f74aca74312dbeaf24d7e61306dd6a786dc3d0
