{
  "id": 7290733,
  "type": "Feature",
  "properties": {
    "tgn:hierarchy":[
        "tgn:7290733",
        "tgn:1001699",
        "tgn:1000049",
        "tgn:1000002",
        "tgn:7029392"
    ],
    "tgn:id":7290733,
    "tgn:name":"Punta Detif",
    "tgn:placetype":[
        "aat:300386846"
    ]
},
  "bbox": [],
  "geometry": {"coordinates":[-73.577222,-42.695],"type":"Point"}
}