<<<<<<< HEAD
{
  "id": 7114885,
  "type": "Feature",
  "properties": {
    "tgn:hierarchy":[
        "tgn:7114885",
        "tgn:1000003",
        "tgn:7003676",
        "tgn:7000084",
        "tgn:7029392"
    ],
    "tgn:id":7114885,
    "tgn:name":"Oldorf",
    "tgn:placetype":[
        "aat:300008347"
    ]
},
  "bbox": [],
  "geometry": {"coordinates":[8.15,53.4],"type":"Point"}
}
=======
{"geometry":{"type":"Point","coordinates":[8.150000,53.400000]},"type":"Feature","properties":{"hierarchy":["tgn:7114885","tgn:1000003","tgn:7003676","tgn:7000084","tgn:7029392"],"placetype":["aat:300008347"],"id":7114885,"name:xx":"Oldorf"}}
>>>>>>> 03f74aca74312dbeaf24d7e61306dd6a786dc3d0
