{
  "id": 7199435,
  "type": "Feature",
  "properties": {
    "tgn:hierarchy":[
        "tgn:7199435",
        "tgn:1000003",
        "tgn:7003682",
        "tgn:7000084",
        "tgn:7029392"
    ],
    "tgn:id":7199435,
    "tgn:name":"Dreim\u00fcllerhof",
    "tgn:placetype":[
        "aat:300000206"
    ]
},
  "bbox": [],
  "geometry": {"coordinates":[6.866667,50.366667],"type":"Point"}
}