{
  "id": 1055753,
  "type": "Feature",
  "properties": {
    "tgn:hierarchy":[
        "tgn:1055753",
        "tgn:1000004",
        "tgn:1003405",
        "tgn:7018214",
        "tgn:7002435",
        "tgn:7029392"
    ],
    "tgn:id":1055753,
    "tgn:name":"Kryukovo",
    "tgn:placetype":[
        "aat:300008347"
    ]
},
  "bbox": [],
  "geometry": {"coordinates":[39.2167,47.65],"type":"Point"}
}