{
  "id": 2102970,
  "type": "Feature",
  "properties": {
    "tgn:hierarchy":[
        "tgn:2102970",
        "tgn:1000001",
        "tgn:7012149",
        "tgn:2001989",
        "tgn:7007826",
        "tgn:7029392"
    ],
    "tgn:id":2102970,
    "tgn:name":"Buenos",
    "tgn:placetype":[
        "aat:300387016"
    ]
},
  "bbox": [],
  "geometry": {"coordinates":[-101.4833,33.2833],"type":"Point"}
}