{
  "id": 2270029,
  "type": "Feature",
  "properties": {
    "tgn:hierarchy":[
        "tgn:2270029",
        "tgn:1000001",
        "tgn:7012149",
        "tgn:2000840",
        "tgn:7007255",
        "tgn:7029392"
    ],
    "tgn:id":2270029,
    "tgn:name":"Cruse Ridge",
    "tgn:placetype":[
        "aat:300266640"
    ]
},
  "bbox": [],
  "geometry": {"coordinates":[-84.2167,37.4833],"type":"Point"}
}