{
  "id": 7396504,
  "type": "Feature",
  "properties": {
    "tgn:hierarchy":[
        "tgn:7396504",
        "tgn:7005581",
        "tgn:1000001",
        "tgn:7005560",
        "tgn:7029392"
    ],
    "tgn:id":7396504,
    "tgn:name":"Santa Rita",
    "tgn:placetype":[
        "aat:300008347"
    ]
},
  "bbox": [],
  "geometry": {"coordinates":[-106.266667,27.383333],"type":"Point"}
}