{
  "id": 7349626,
  "type": "Feature",
  "properties": {
    "tgn:hierarchy":[
        "tgn:7349626",
        "tgn:1001835",
        "tgn:1000001",
        "tgn:7005560",
        "tgn:7029392"
    ],
    "tgn:id":7349626,
    "tgn:name":"Agua Mat\u00edas",
    "tgn:placetype":[
        "aat:300008347"
    ]
},
  "bbox": [],
  "geometry": {"coordinates":[-115.933333,32.383333],"type":"Point"}
}