{
  "id": 2517131,
  "type": "Feature",
  "properties": {
    "tgn:hierarchy":[
        "tgn:2517131",
        "tgn:2001610",
        "tgn:1000001",
        "tgn:7012149",
        "tgn:7007706",
        "tgn:7029392"
    ],
    "tgn:id":2517131,
    "tgn:name":"Minkers Run",
    "tgn:placetype":[
        "aat:300008699"
    ]
},
  "bbox": [],
  "geometry": {"coordinates":[-82.2667,39.45],"type":"Point"}
}