{
  "id": 7046784,
  "type": "Feature",
  "properties": {
    "tgn:hierarchy":[
        "tgn:7046784",
        "tgn:7003135",
        "tgn:1000003",
        "tgn:7003080",
        "tgn:1000080",
        "tgn:7029392"
    ],
    "tgn:id":7046784,
    "tgn:name":"Colleberardi",
    "tgn:placetype":[
        "aat:300008347"
    ]
},
  "bbox": [],
  "geometry": {"coordinates":[13.45,41.683333],"type":"Point"}
}