{
  "id": 2105117,
  "type": "Feature",
  "properties": {
    "tgn:hierarchy":[
        "tgn:2105117",
        "tgn:1000001",
        "tgn:7012149",
        "tgn:2002032",
        "tgn:7007826",
        "tgn:7029392"
    ],
    "tgn:id":2105117,
    "tgn:name":"Hurlwood",
    "tgn:placetype":[
        "aat:300008347"
    ]
},
  "bbox": [],
  "geometry": {"coordinates":[-102.0333,33.5667],"type":"Point"}
}