<<<<<<< HEAD
{
  "id": 2403217,
  "type": "Feature",
  "properties": {
    "tgn:hierarchy":[
        "tgn:2403217",
        "tgn:1000001",
        "tgn:2001435",
        "tgn:7012149",
        "tgn:7007566",
        "tgn:7029392"
    ],
    "tgn:id":2403217,
    "tgn:name":"House Pasture Tank",
    "tgn:placetype":[
        "aat:300006191"
    ]
},
  "bbox": [],
  "geometry": {"coordinates":[-106.8,32.8],"type":"Point"}
}
=======
{"geometry":{"type":"Point","coordinates":[-106.800000,32.800000]},"type":"Feature","properties":{"hierarchy":["tgn:2403217","tgn:1000001","tgn:2001435","tgn:7012149","tgn:7007566","tgn:7029392"],"placetype":["aat:300006191"],"id":2403217,"name:xx":"House Pasture Tank"}}
>>>>>>> 03f74aca74312dbeaf24d7e61306dd6a786dc3d0
