{
  "id": 1056489,
  "type": "Feature",
  "properties": {
    "tgn:hierarchy":[
        "tgn:1056489",
        "tgn:1000004",
        "tgn:1003424",
        "tgn:7018214",
        "tgn:7002435",
        "tgn:7029392"
    ],
    "tgn:id":1056489,
    "tgn:name":"Lizinovka",
    "tgn:placetype":[
        "aat:300008347"
    ]
},
  "bbox": [],
  "geometry": {"coordinates":[39.4667,50.1167],"type":"Point"}
}