<<<<<<< HEAD
{
  "id": 2405073,
  "type": "Feature",
  "properties": {
    "tgn:hierarchy":[
        "tgn:2405073",
        "tgn:7002659",
        "tgn:1000001",
        "tgn:2000013",
        "tgn:7012149",
        "tgn:7029392"
    ],
    "tgn:id":2405073,
    "tgn:name":"Hudson Mine",
    "tgn:placetype":[
        "aat:300000390"
    ]
},
  "bbox": [],
  "geometry": {"coordinates":[-85.8833,33.3333],"type":"Point"}
}
=======
{"geometry":{"type":"Point","coordinates":[-85.883300,33.333300]},"type":"Feature","properties":{"hierarchy":["tgn:2405073","tgn:7002659","tgn:1000001","tgn:2000013","tgn:7012149","tgn:7029392"],"placetype":["aat:300000390"],"id":2405073,"name:xx":"Hudson Mine"}}
>>>>>>> 03f74aca74312dbeaf24d7e61306dd6a786dc3d0
