{
  "id": 7169636,
  "type": "Feature",
  "properties": {
    "tgn:hierarchy":[
        "tgn:7169636",
        "tgn:1000003",
        "tgn:7003677",
        "tgn:7000084",
        "tgn:7029392"
    ],
    "tgn:id":7169636,
    "tgn:name":"Herhagen",
    "tgn:placetype":[
        "aat:300008347"
    ]
},
  "bbox": [],
  "geometry": {"coordinates":[8.266667,51.266667],"type":"Point"}
}