<<<<<<< HEAD
{
  "id": 2407631,
  "type": "Feature",
  "properties": {
    "tgn:hierarchy":[
        "tgn:2407631",
        "tgn:1000001",
        "tgn:1002949",
        "tgn:7012149",
        "tgn:7007159",
        "tgn:7029392"
    ],
    "tgn:id":2407631,
    "tgn:name":"Hurds Lake",
    "tgn:placetype":[
        "aat:300006191"
    ]
},
  "bbox": [],
  "geometry": {"coordinates":[-72.4,42.0167],"type":"Point"}
}
=======
{"geometry":{"type":"Point","coordinates":[-72.400000,42.016700]},"type":"Feature","properties":{"hierarchy":["tgn:2407631","tgn:1000001","tgn:1002949","tgn:7012149","tgn:7007159","tgn:7029392"],"placetype":["aat:300006191"],"id":2407631,"name:xx":"Hurds Lake"}}
>>>>>>> 03f74aca74312dbeaf24d7e61306dd6a786dc3d0
