{
  "id": 7157390,
  "type": "Feature",
  "properties": {
    "tgn:hierarchy":[
        "tgn:7157390",
        "tgn:7000096",
        "tgn:1000003",
        "tgn:7000084",
        "tgn:7029392"
    ],
    "tgn:id":7157390,
    "tgn:name":"Kavel-Berg",
    "tgn:placetype":[
        "aat:300008777"
    ]
},
  "bbox": [],
  "geometry": {"coordinates":[13.566667,52.866667],"type":"Point"}
}