{
  "id": 2745097,
  "type": "Feature",
  "properties": {
    "tgn:hierarchy":[
        "tgn:2745097",
        "tgn:1000001",
        "tgn:7012149",
        "tgn:7007253",
        "tgn:7029392"
    ],
    "tgn:id":2745097,
    "tgn:name":"Village Creek",
    "tgn:placetype":[
        "aat:300008706"
    ]
},
  "bbox": [],
  "geometry": {"coordinates":[-92.5833,40.95],"type":"Point"}
}