{
  "id": 1099393,
  "type": "Feature",
  "properties": {
    "tgn:hierarchy":[
        "tgn:1099393",
        "tgn:1007161",
        "tgn:7018511",
        "tgn:1000220",
        "tgn:1009774",
        "tgn:1000006",
        "tgn:7029392"
    ],
    "tgn:id":1099393,
    "tgn:name":"Meqruur",
    "tgn:placetype":[
        "aat:300008347"
    ]
},
  "bbox": [],
  "geometry": {"coordinates":[138.15,9.5167],"type":"Point"}
}