{
  "id": 2756434,
  "type": "Feature",
  "properties": {
    "tgn:hierarchy":[
        "tgn:2756434",
        "tgn:1000001",
        "tgn:2001430",
        "tgn:7012149",
        "tgn:7007566",
        "tgn:7029392"
    ],
    "tgn:id":2756434,
    "tgn:name":"Well Drilled Canyon",
    "tgn:placetype":[
        "aat:300008761"
    ]
},
  "bbox": [],
  "geometry": {"coordinates":[-105.2333,32.95],"type":"Point"}
}