{
  "id": 1024661,
  "type": "Feature",
  "properties": {
    "tgn:hierarchy":[
        "tgn:1024661",
        "tgn:1000670",
        "tgn:1000002",
        "tgn:1000056",
        "tgn:7029392"
    ],
    "tgn:id":1024661,
    "tgn:name":"Pacaraos",
    "tgn:placetype":[
        "aat:300008347"
    ]
},
  "bbox": [],
  "geometry": {"coordinates":[-76.6333,-11.1833],"type":"Point"}
}