{
  "id": 7009548,
  "type": "Feature",
  "properties": {
    "tgn:hierarchy":[
        "tgn:7009548",
        "tgn:7002444",
        "tgn:1000003",
        "tgn:7019123",
        "tgn:7008591",
        "tgn:7029392"
    ],
    "tgn:id":7009548,
    "tgn:name:en":"Penicuik",
    "tgn:placetype":[
        "aat:300008347"
    ]
},
  "bbox": [],
  "geometry": {"coordinates":[-3.233333,55.816667],"type":"Point"}
}