<<<<<<< HEAD
{
  "id": 2250976,
  "type": "Feature",
  "properties": {
    "tgn:hierarchy":[
        "tgn:2250976",
        "tgn:1000001",
        "tgn:2000199",
        "tgn:7012149",
        "tgn:7007158",
        "tgn:7029392"
    ],
    "tgn:id":2250976,
    "tgn:name":"Columbine Gulch",
    "tgn:placetype":[
        "aat:300008761"
    ]
},
  "bbox": [],
  "geometry": {"coordinates":[-105.9667,38.7667],"type":"Point"}
}
=======
{"geometry":{"type":"Point","coordinates":[-105.966700,38.766700]},"type":"Feature","properties":{"hierarchy":["tgn:2250976","tgn:1000001","tgn:2000199","tgn:7012149","tgn:7007158","tgn:7029392"],"placetype":["aat:300008761"],"id":2250976,"name:xx":"Columbine Gulch"}}
>>>>>>> 03f74aca74312dbeaf24d7e61306dd6a786dc3d0
