{
  "id": 7377366,
  "type": "Feature",
  "properties": {
    "tgn:hierarchy":[
        "tgn:7377366",
        "tgn:7005586",
        "tgn:1000001",
        "tgn:7005560",
        "tgn:7029392"
    ],
    "tgn:id":7377366,
    "tgn:name":"La Sauceda",
    "tgn:placetype":[
        "aat:300008347"
    ]
},
  "bbox": [],
  "geometry": {"coordinates":[-101.816667,21.333333],"type":"Point"}
}