{
  "id": 7134620,
  "type": "Feature",
  "properties": {
    "tgn:hierarchy":[
        "tgn:7134620",
        "tgn:7003669",
        "tgn:1000003",
        "tgn:7000084",
        "tgn:7029392"
    ],
    "tgn:id":7134620,
    "tgn:name":"M\u00f6nschberg",
    "tgn:placetype":[
        "aat:300000206"
    ]
},
  "bbox": [],
  "geometry": {"coordinates":[11.866667,48.533333],"type":"Point"}
}