{
  "id": 2080040,
  "type": "Feature",
  "properties": {
    "tgn:hierarchy":[
        "tgn:2080040",
        "tgn:1000001",
        "tgn:7012149",
        "tgn:1003033",
        "tgn:7007706",
        "tgn:7029392"
    ],
    "tgn:id":2080040,
    "tgn:name":"Hoytville",
    "tgn:placetype":[
        "aat:300008347"
    ]
},
  "bbox": [],
  "geometry": {"coordinates":[-83.7833,41.1833],"type":"Point"}
}