{
  "id": 7294930,
  "type": "Feature",
  "properties": {
    "tgn:hierarchy":[
        "tgn:7294930",
        "tgn:7002758",
        "tgn:7002817",
        "tgn:1000003",
        "tgn:1000095",
        "tgn:7029392"
    ],
    "tgn:id":7294930,
    "tgn:name":"Z\u00fajar",
    "tgn:placetype":[
        "aat:300008347"
    ]
},
  "bbox": [],
  "geometry": {"coordinates":[-5.316667,38.566667],"type":"Point"}
}