{
  "id": 2441319,
  "type": "Feature",
  "properties": {
    "tgn:hierarchy":[
        "tgn:2441319",
        "tgn:7002659",
        "tgn:1000001",
        "tgn:7012149",
        "tgn:7029392"
    ],
    "tgn:id":2441319,
    "tgn:name":"Knox Creek",
    "tgn:placetype":[
        "aat:300008706"
    ]
},
  "bbox": [],
  "geometry": {"coordinates":[-86.75,34.7833],"type":"Point"}
}