{
  "id": 2110136,
  "type": "Feature",
  "properties": {
    "tgn:hierarchy":[
        "tgn:2110136",
        "tgn:1000001",
        "tgn:2002136",
        "tgn:7012149",
        "tgn:7007828",
        "tgn:7029392"
    ],
    "tgn:id":2110136,
    "tgn:name":"Weathersfield Center",
    "tgn:placetype":[
        "aat:300008347"
    ]
},
  "bbox": [],
  "geometry": {"coordinates":[-72.4667,43.3667],"type":"Point"}
}