{
  "id": 7119308,
  "type": "Feature",
  "properties": {
    "tgn:hierarchy":[
        "tgn:7119308",
        "tgn:1000003",
        "tgn:7003688",
        "tgn:7000084",
        "tgn:7029392"
    ],
    "tgn:id":7119308,
    "tgn:name":"Poggenpohl",
    "tgn:placetype":[
        "aat:300008347"
    ]
},
  "bbox": [],
  "geometry": {"coordinates":[10.616667,53.85],"type":"Point"}
}