{
  "id": 7095721,
  "type": "Feature",
  "properties": {
    "tgn:hierarchy":[
        "tgn:7095721",
        "tgn:1000003",
        "tgn:7003685",
        "tgn:7000084",
        "tgn:7029392"
    ],
    "tgn:id":7095721,
    "tgn:name":"Schweta",
    "tgn:placetype":[
        "aat:300008347"
    ]
},
  "bbox": [],
  "geometry": {"coordinates":[13.083333,51.25],"type":"Point"}
}