{
  "id": 2006359,
  "type": "Feature",
  "properties": {
    "tgn:hierarchy":[
        "tgn:2006359",
        "tgn:7006450",
        "tgn:1000001",
        "tgn:7012149",
        "tgn:2000079",
        "tgn:7019621",
        "tgn:7029392"
    ],
    "tgn:id":2006359,
    "tgn:name":"Savoonga",
    "tgn:placetype":[
        "aat:300008347"
    ]
},
  "bbox": [],
  "geometry": {"coordinates":[-170.4667,63.6833],"type":"Point"}
}