{
  "id": 2436033,
  "type": "Feature",
  "properties": {
    "tgn:hierarchy":[
        "tgn:2436033",
        "tgn:1000001",
        "tgn:7012149",
        "tgn:2001723",
        "tgn:7007708",
        "tgn:7029392"
    ],
    "tgn:id":2436033,
    "tgn:name":"Keyes Mountain",
    "tgn:placetype":[
        "aat:300008798"
    ]
},
  "bbox": [],
  "geometry": {"coordinates":[-120.0333,44.5833],"type":"Point"}
}