{
  "id": 2367645,
  "type": "Feature",
  "properties": {
    "tgn:hierarchy":[
        "tgn:2367645",
        "tgn:1000001",
        "tgn:2000470",
        "tgn:7012149",
        "tgn:7007250",
        "tgn:7029392"
    ],
    "tgn:id":2367645,
    "tgn:name":"Grouse Peak",
    "tgn:placetype":[
        "aat:300008798"
    ]
},
  "bbox": [],
  "geometry": {"coordinates":[-114.0833,44.55],"type":"Point"}
}