{
  "id": 2293357,
  "type": "Feature",
  "properties": {
    "tgn:hierarchy":[
        "tgn:2293357",
        "tgn:1000001",
        "tgn:7012149",
        "tgn:1002550",
        "tgn:7007157",
        "tgn:7029392"
    ],
    "tgn:id":2293357,
    "tgn:name":"Double Hill",
    "tgn:placetype":[
        "aat:300266640"
    ]
},
  "bbox": [],
  "geometry": {"coordinates":[-120.0833,36.0333],"type":"Point"}
}