{
  "id": 7535906,
  "type": "Feature",
  "properties": {
    "tgn:hierarchy":[
        "tgn:7535906",
        "tgn:7001242",
        "tgn:7016833",
        "tgn:7001336",
        "tgn:7029392"
    ],
    "tgn:id":7535906,
    "tgn:name:en":"Fawq\u012byah, 'Ayn al",
    "tgn:placetype":[
        "aat:300008697"
    ]
},
  "bbox": [],
  "geometry": {"coordinates":[33.186389,29.594444],"type":"Point"}
}