{
  "id": 7336766,
  "type": "Feature",
  "properties": {
    "tgn:hierarchy":[
        "tgn:7336766",
        "tgn:7001158",
        "tgn:7002850",
        "tgn:1000003",
        "tgn:1000095",
        "tgn:7029392"
    ],
    "tgn:id":7336766,
    "tgn:name":"Fontanillas de Castro",
    "tgn:placetype":[
        "aat:300008347"
    ]
},
  "bbox": [],
  "geometry": {"coordinates":[-5.783333,41.733333],"type":"Point"}
}