{
  "id": 7505891,
  "type": "Feature",
  "properties": {
    "tgn:hierarchy":[
        "tgn:7505891",
        "tgn:1008380",
        "tgn:7000507",
        "tgn:1000226",
        "tgn:1000006",
        "tgn:7029392"
    ],
    "tgn:id":7505891,
    "tgn:name:en":"Taraere Bay",
    "tgn:placetype":[
        "aat:300132316"
    ]
},
  "bbox": [],
  "geometry": {"coordinates":[172.966667,-34.583333],"type":"Point"}
}