{
  "id": 2174010,
  "type": "Feature",
  "properties": {
    "tgn:hierarchy":[
        "tgn:2174010",
        "tgn:1000001",
        "tgn:7012149",
        "tgn:1002263",
        "tgn:7007826",
        "tgn:7029392"
    ],
    "tgn:id":2174010,
    "tgn:name":"Bird Pond",
    "tgn:placetype":[
        "aat:300008680"
    ]
},
  "bbox": [],
  "geometry": {"coordinates":[-95.1167,31.9333],"type":"Point"}
}