{
  "id": 7142304,
  "type": "Feature",
  "properties": {
    "tgn:hierarchy":[
        "tgn:7142304",
        "tgn:1000003",
        "tgn:7003689",
        "tgn:7000084",
        "tgn:7029392"
    ],
    "tgn:id":7142304,
    "tgn:name":"Lohmen",
    "tgn:placetype":[
        "aat:300008777"
    ]
},
  "bbox": [],
  "geometry": {"coordinates":[11.783333,50.566667],"type":"Point"}
}