{
  "id": 2402201,
  "type": "Feature",
  "properties": {
    "tgn:hierarchy":[
        "tgn:2402201",
        "tgn:1000001",
        "tgn:7012149",
        "tgn:1002392",
        "tgn:7007157",
        "tgn:7029392"
    ],
    "tgn:id":2402201,
    "tgn:name":"Horsethief Creek",
    "tgn:placetype":[
        "aat:300008706"
    ]
},
  "bbox": [],
  "geometry": {"coordinates":[-119.2667,37.2833],"type":"Point"}
}