<<<<<<< HEAD
{
  "id": 2402201,
  "type": "Feature",
  "properties": {
    "tgn:hierarchy":[
        "tgn:2402201",
        "tgn:1000001",
        "tgn:7012149",
        "tgn:1002392",
        "tgn:7007157",
        "tgn:7029392"
    ],
    "tgn:id":2402201,
    "tgn:name":"Horsethief Creek",
    "tgn:placetype":[
        "aat:300008706"
    ]
},
  "bbox": [],
  "geometry": {"coordinates":[-119.2667,37.2833],"type":"Point"}
}
=======
{"geometry":{"type":"Point","coordinates":[-119.266700,37.283300]},"type":"Feature","properties":{"hierarchy":["tgn:2402201","tgn:1000001","tgn:7012149","tgn:1002392","tgn:7007157","tgn:7029392"],"placetype":["aat:300008706"],"id":2402201,"name:xx":"Horsethief Creek"}}
>>>>>>> 03f74aca74312dbeaf24d7e61306dd6a786dc3d0
