{
  "id": 7137302,
  "type": "Feature",
  "properties": {
    "tgn:hierarchy":[
        "tgn:7137302",
        "tgn:1000003",
        "tgn:7003684",
        "tgn:7000084",
        "tgn:7029392"
    ],
    "tgn:id":7137302,
    "tgn:name":"Leopoldsthal",
    "tgn:placetype":[
        "aat:300008347"
    ]
},
  "bbox": [],
  "geometry": {"coordinates":[7.116667,49.366667],"type":"Point"}
}