{
  "id": 7341853,
  "type": "Feature",
  "properties": {
    "tgn:hierarchy":[
        "tgn:7341853",
        "tgn:7002824",
        "tgn:1000003",
        "tgn:7002786",
        "tgn:1000095",
        "tgn:7029392"
    ],
    "tgn:id":7341853,
    "tgn:name":"Boente, R\u00edo",
    "tgn:placetype":[
        "aat:300008699"
    ]
},
  "bbox": [],
  "geometry": {"coordinates":[-8.133333,42.866667],"type":"Point"}
}