{
  "id": 7398817,
  "type": "Feature",
  "properties": {
    "tgn:hierarchy":[
        "tgn:7398817",
        "tgn:1000001",
        "tgn:1001893",
        "tgn:7005560",
        "tgn:7029392"
    ],
    "tgn:id":7398817,
    "tgn:name":"Santa Mar\u00eda Tetitla",
    "tgn:placetype":[
        "aat:300008347"
    ]
},
  "bbox": [],
  "geometry": {"coordinates":[-99.554444,19.423056],"type":"Point"}
}