{
  "id": 7184874,
  "type": "Feature",
  "properties": {
    "tgn:hierarchy":[
        "tgn:7184874",
        "tgn:7003669",
        "tgn:1000003",
        "tgn:7000084",
        "tgn:7029392"
    ],
    "tgn:id":7184874,
    "tgn:name":"Grasheim",
    "tgn:placetype":[
        "aat:300008347"
    ]
},
  "bbox": [],
  "geometry": {"coordinates":[11.266667,48.683333],"type":"Point"}
}