{
  "id": 2476762,
  "type": "Feature",
  "properties": {
    "tgn:hierarchy":[
        "tgn:2476762",
        "tgn:1000001",
        "tgn:7012149",
        "tgn:1002758",
        "tgn:7007568",
        "tgn:7029392"
    ],
    "tgn:id":2476762,
    "tgn:name":"Lydiatt Creek",
    "tgn:placetype":[
        "aat:300008706"
    ]
},
  "bbox": [],
  "geometry": {"coordinates":[-75.9333,43.25],"type":"Point"}
}