{
  "id": 7556057,
  "type": "Feature",
  "properties": {
    "tgn:hierarchy":[
        "tgn:7556057",
        "tgn:1000004",
        "tgn:7000198",
        "tgn:7001797",
        "tgn:7029392"
    ],
    "tgn:id":7556057,
    "tgn:name:en":"R\u0101j\u0101singamangalam",
    "tgn:placetype":[
        "aat:300008347"
    ]
},
  "bbox": [],
  "geometry": {"coordinates":[78.85,9.666667],"type":"Point"}
}