{
  "id": 7347190,
  "type": "Feature",
  "properties": {
    "tgn:hierarchy":[
        "tgn:7347190",
        "tgn:7002835",
        "tgn:7001158",
        "tgn:1000003",
        "tgn:1000095",
        "tgn:7029392"
    ],
    "tgn:id":7347190,
    "tgn:name":"Ba\u00f1uelos, Arroyo de",
    "tgn:placetype":[
        "aat:300266554",
        "aat:300008699"
    ]
},
  "bbox": [],
  "geometry": {"coordinates":[-5.25,41.033333],"type":"Point"}
}