{
  "id": 2268761,
  "type": "Feature",
  "properties": {
    "tgn:hierarchy":[
        "tgn:2268761",
        "tgn:1000001",
        "tgn:7013638",
        "tgn:7012149",
        "tgn:7007568",
        "tgn:7029392"
    ],
    "tgn:id":2268761,
    "tgn:name":"Cross Hill",
    "tgn:placetype":[
        "aat:300008798"
    ]
},
  "bbox": [],
  "geometry": {"coordinates":[-73.8833,42.0833],"type":"Point"}
}