{
  "id": 7236573,
  "type": "Feature",
  "properties": {
    "tgn:hierarchy":[
        "tgn:7236573",
        "tgn:7011170",
        "tgn:7002715",
        "tgn:1000003",
        "tgn:1000074",
        "tgn:7029392"
    ],
    "tgn:id":7236573,
    "tgn:name":"Ano Ionik\u00f3n",
    "tgn:placetype":[
        "aat:300000745"
    ]
},
  "bbox": [],
  "geometry": {"coordinates":[24.633333,41.25],"type":"Point"}
}