{
  "id": 7228443,
  "type": "Feature",
  "properties": {
    "tgn:hierarchy":[
        "tgn:7228443",
        "tgn:7002715",
        "tgn:7002731",
        "tgn:1000003",
        "tgn:1000074",
        "tgn:7029392"
    ],
    "tgn:id":7228443,
    "tgn:name":"Kass\u00e1ndras, \u00c1kra",
    "tgn:placetype":[
        "aat:300008850"
    ]
},
  "bbox": [],
  "geometry": {"coordinates":[23.35,39.95],"type":"Point"}
}