{
  "id": 2507620,
  "type": "Feature",
  "properties": {
    "tgn:hierarchy":[
        "tgn:2507620",
        "tgn:1000001",
        "tgn:7012149",
        "tgn:2001543",
        "tgn:7007709",
        "tgn:7029392"
    ],
    "tgn:id":2507620,
    "tgn:name":"Mica Knob",
    "tgn:placetype":[
        "aat:300008798"
    ]
},
  "bbox": [],
  "geometry": {"coordinates":[-83.45,35.3167],"type":"Point"}
}