{
  "id": 2766038,
  "type": "Feature",
  "properties": {
    "tgn:hierarchy":[
        "tgn:2766038",
        "tgn:1000001",
        "tgn:7012149",
        "tgn:2000488",
        "tgn:7007250",
        "tgn:7029392"
    ],
    "tgn:id":2766038,
    "tgn:name":"White Horse Creek",
    "tgn:placetype":[
        "aat:300008706"
    ]
},
  "bbox": [],
  "geometry": {"coordinates":[-116.5167,42.8333],"type":"Point"}
}