{
  "id": 7211800,
  "type": "Feature",
  "properties": {
    "tgn:hierarchy":[
        "tgn:7211800",
        "tgn:1000003",
        "tgn:7003688",
        "tgn:7000084",
        "tgn:7029392"
    ],
    "tgn:id":7211800,
    "tgn:name":"Bilsener Wohld",
    "tgn:placetype":[
        "aat:300008863"
    ]
},
  "bbox": [],
  "geometry": {"coordinates":[9.883333,53.75],"type":"Point"}
}