<<<<<<< HEAD
{
  "id": 2258355,
  "type": "Feature",
  "properties": {
    "tgn:hierarchy":[
        "tgn:2258355",
        "tgn:1000001",
        "tgn:7012149",
        "tgn:7007256",
        "tgn:7029392"
    ],
    "tgn:id":2258355,
    "tgn:name":"Cotton Bayou",
    "tgn:placetype":[
        "aat:300008699"
    ]
},
  "bbox": [],
  "geometry": {"coordinates":[-90.95,30.3167],"type":"Point"}
}
=======
{"geometry":{"type":"Point","coordinates":[-90.950000,30.316700]},"type":"Feature","properties":{"hierarchy":["tgn:2258355","tgn:1000001","tgn:7012149","tgn:7007256","tgn:7029392"],"placetype":["aat:300008699"],"id":2258355,"name:xx":"Cotton Bayou"}}
>>>>>>> 03f74aca74312dbeaf24d7e61306dd6a786dc3d0
