{
  "id": 1024459,
  "type": "Feature",
  "properties": {
    "tgn:hierarchy":[
        "tgn:1024459",
        "tgn:1000665",
        "tgn:1000002",
        "tgn:1000056",
        "tgn:7029392"
    ],
    "tgn:id":1024459,
    "tgn:name":"Chongoyape",
    "tgn:placetype":[
        "aat:300008347"
    ]
},
  "bbox": [],
  "geometry": {"coordinates":[-79.3833,-6.6333],"type":"Point"}
}