{
  "id": 1077366,
  "type": "Feature",
  "properties": {
    "tgn:hierarchy":[
        "tgn:1077366",
        "tgn:1000004",
        "tgn:1001409",
        "tgn:1009102",
        "tgn:1000116",
        "tgn:7029392"
    ],
    "tgn:id":1077366,
    "tgn:name":"Angar",
    "tgn:placetype":[
        "aat:300008347"
    ]
},
  "bbox": [],
  "geometry": {"coordinates":[130.8333,-3.65],"type":"Point"}
}