<<<<<<< HEAD
{
  "id": 7024077,
  "type": "Feature",
  "properties": {
    "tgn:hierarchy":[
        "tgn:7024077",
        "tgn:1000003",
        "tgn:1000069",
        "tgn:7029392"
    ],
    "tgn:id":7024077,
    "tgn:name":"L\u00e4nsi-Suomen L\u00e4\u00e4ni",
    "tgn:placetype":[
        "aat:300387064",
        "aat:300000774"
    ]
},
  "bbox": [],
  "geometry": {"coordinates":[24.0,62.0],"type":"Point"}
}
=======
{"geometry":{"type":"Point","coordinates":[24.000000,62.000000]},"type":"Feature","properties":{"hierarchy":["tgn:7024077","tgn:1000003","tgn:1000069","tgn:7029392"],"placetype":["aat:300387064","aat:300000774"],"id":7024077,"name:xx":"L\u00e4nsi-Suomen L\u00e4\u00e4ni"}}
>>>>>>> 03f74aca74312dbeaf24d7e61306dd6a786dc3d0
