{
  "id": 7433665,
  "type": "Feature",
  "properties": {
    "tgn:hierarchy":[
        "tgn:7433665",
        "tgn:7005580",
        "tgn:1000001",
        "tgn:7005560",
        "tgn:7029392"
    ],
    "tgn:id":7433665,
    "tgn:name":"Verde, Cerro",
    "tgn:placetype":[
        "aat:300008795"
    ]
},
  "bbox": [],
  "geometry": {"coordinates":[-92.516667,15.35],"type":"Point"}
}