{
  "id": 7584202,
  "type": "Feature",
  "properties": {
    "tgn:hierarchy":[
        "tgn:7584202",
        "tgn:1000004",
        "tgn:7000198",
        "tgn:1001894",
        "tgn:7029392"
    ],
    "tgn:id":7584202,
    "tgn:name:en":"Bilg\u0101yan Protected Forest",
    "tgn:placetype":[
        "aat:300008865"
    ]
},
  "bbox": [],
  "geometry": {"coordinates":[78.871541,24.879454],"type":"Point"}
}