{
  "id": 1112533,
  "type": "Feature",
  "properties": {
    "tgn:hierarchy":[
        "tgn:1112533",
        "tgn:7001242",
        "tgn:7016833",
        "tgn:1001418",
        "tgn:7029392"
    ],
    "tgn:id":1112533,
    "tgn:name":"\u02bbArab, Khal\u012bj al",
    "tgn:placetype":[
        "aat:300132316",
        "aat:300132315"
    ]
},
  "bbox": [],
  "geometry": {"coordinates":[29.086043,30.916011],"type":"Point"}
}