{
  "id": 2340055,
  "type": "Feature",
  "properties": {
    "tgn:hierarchy":[
        "tgn:2340055",
        "tgn:1000001",
        "tgn:7012149",
        "tgn:2001687",
        "tgn:7007707",
        "tgn:7029392"
    ],
    "tgn:id":2340055,
    "tgn:name":"Freezeout Creek",
    "tgn:placetype":[
        "aat:300008706"
    ]
},
  "bbox": [],
  "geometry": {"coordinates":[-99.9333,35.4833],"type":"Point"}
}