{
  "id": 2084525,
  "type": "Feature",
  "properties": {
    "tgn:hierarchy":[
        "tgn:2084525",
        "tgn:1000001",
        "tgn:2001702",
        "tgn:7012149",
        "tgn:7007708",
        "tgn:7029392"
    ],
    "tgn:id":2084525,
    "tgn:name":"Charleston",
    "tgn:placetype":[
        "aat:300008347"
    ]
},
  "bbox": [],
  "geometry": {"coordinates":[-124.3167,43.3333],"type":"Point"}
}