{
  "id": 7173379,
  "type": "Feature",
  "properties": {
    "tgn:hierarchy":[
        "tgn:7173379",
        "tgn:7003692",
        "tgn:1000003",
        "tgn:7000084",
        "tgn:7029392"
    ],
    "tgn:id":7173379,
    "tgn:name":"Gro\u00dfrinderfeld",
    "tgn:placetype":[
        "aat:300008347"
    ]
},
  "bbox": [],
  "geometry": {"coordinates":[9.75,49.65],"type":"Point"}
}