{
  "id": 7497543,
  "type": "Feature",
  "properties": {
    "tgn:hierarchy":[
        "tgn:7497543",
        "tgn:1000004",
        "tgn:1000454",
        "tgn:1000141",
        "tgn:7029392"
    ],
    "tgn:id":7497543,
    "tgn:name":"Huanggang Yugang",
    "tgn:placetype":[
        "aat:300008678"
    ]
},
  "bbox": [],
  "geometry": {"coordinates":[121.647628,25.23061],"type":"Point"}
}