{
  "id": 2551831,
  "type": "Feature",
  "properties": {
    "tgn:hierarchy":[
        "tgn:2551831",
        "tgn:1000001",
        "tgn:7016172",
        "tgn:7012149",
        "tgn:2000151",
        "tgn:7029392"
    ],
    "tgn:id":2551831,
    "tgn:name":"Number 7a, Ditch",
    "tgn:placetype":[
        "aat:300006075"
    ]
},
  "bbox": [],
  "geometry": {"coordinates":[-89.8333,35.9167],"type":"Point"}
}