{
  "id": 2370817,
  "type": "Feature",
  "properties": {
    "tgn:hierarchy":[
        "tgn:2370817",
        "tgn:1000001",
        "tgn:7012149",
        "tgn:1002403",
        "tgn:7007709",
        "tgn:7029392"
    ],
    "tgn:id":2370817,
    "tgn:name":"Hackley Swamp",
    "tgn:placetype":[
        "aat:300008699"
    ]
},
  "bbox": [],
  "geometry": {"coordinates":[-76.7667,36.5167],"type":"Point"}
}