{
  "id": 2012951,
  "type": "Feature",
  "properties": {
    "tgn:hierarchy":[
        "tgn:2012951",
        "tgn:1000001",
        "tgn:7012149",
        "tgn:2000182",
        "tgn:7007157",
        "tgn:7029392"
    ],
    "tgn:id":2012951,
    "tgn:name":"Niland",
    "tgn:placetype":[
        "aat:300008347"
    ]
},
  "bbox": [],
  "geometry": {"coordinates":[-115.5167,33.2333],"type":"Point"}
}