{
  "id": 7140768,
  "type": "Feature",
  "properties": {
    "tgn:hierarchy":[
        "tgn:7140768",
        "tgn:1000003",
        "tgn:7003676",
        "tgn:7000084",
        "tgn:7029392"
    ],
    "tgn:id":7140768,
    "tgn:name":"Litteler Fuhrenkamp",
    "tgn:placetype":[
        "aat:300055621"
    ]
},
  "bbox": [],
  "geometry": {"coordinates":[8.133333,53.033333],"type":"Point"}
}