<<<<<<< HEAD
{
  "id": 2159580,
  "type": "Feature",
  "properties": {
    "tgn:hierarchy":[
        "tgn:2159580",
        "tgn:1000001",
        "tgn:1002193",
        "tgn:7012149",
        "tgn:7007255",
        "tgn:7029392"
    ],
    "tgn:id":2159580,
    "tgn:name":"Bee Run",
    "tgn:placetype":[
        "aat:300008699"
    ]
},
  "bbox": [],
  "geometry": {"coordinates":[-83.9333,38.75],"type":"Point"}
}
=======
{"geometry":{"type":"Point","coordinates":[-83.933300,38.750000]},"type":"Feature","properties":{"hierarchy":["tgn:2159580","tgn:1000001","tgn:1002193","tgn:7012149","tgn:7007255","tgn:7029392"],"placetype":["aat:300008699"],"id":2159580,"name:xx":"Bee Run"}}
>>>>>>> 03f74aca74312dbeaf24d7e61306dd6a786dc3d0
