{
  "id": 2159580,
  "type": "Feature",
  "properties": {
    "tgn:hierarchy":[
        "tgn:2159580",
        "tgn:1000001",
        "tgn:1002193",
        "tgn:7012149",
        "tgn:7007255",
        "tgn:7029392"
    ],
    "tgn:id":2159580,
    "tgn:name":"Bee Run",
    "tgn:placetype":[
        "aat:300008699"
    ]
},
  "bbox": [],
  "geometry": {"coordinates":[-83.9333,38.75],"type":"Point"}
}