{
  "id": 1065952,
  "type": "Feature",
  "properties": {
    "tgn:hierarchy":[
        "tgn:1065952",
        "tgn:1000004",
        "tgn:7000191",
        "tgn:1000105",
        "tgn:7029392"
    ],
    "tgn:id":1065952,
    "tgn:name":"Suj\u0101nagar",
    "tgn:placetype":[
        "aat:300008347"
    ]
},
  "bbox": [],
  "geometry": {"coordinates":[89.4167,23.95],"type":"Point"}
}