{
  "id": 2595992,
  "type": "Feature",
  "properties": {
    "tgn:hierarchy":[
        "tgn:2595992",
        "tgn:2002239",
        "tgn:1000001",
        "tgn:7012149",
        "tgn:7007920",
        "tgn:7029392"
    ],
    "tgn:id":2595992,
    "tgn:name":"Potter Hill",
    "tgn:placetype":[
        "aat:300008798"
    ]
},
  "bbox": [],
  "geometry": {"coordinates":[-117.35,46.3167],"type":"Point"}
}