{
  "id": 7421377,
  "type": "Feature",
  "properties": {
    "tgn:hierarchy":[
        "tgn:7421377",
        "tgn:7005584",
        "tgn:1000001",
        "tgn:7005560",
        "tgn:7029392"
    ],
    "tgn:id":7421377,
    "tgn:name":"Las Golondrinas",
    "tgn:placetype":[
        "aat:300008347"
    ]
},
  "bbox": [],
  "geometry": {"coordinates":[-101.542222,21.4525],"type":"Point"}
}