<<<<<<< HEAD
{
  "id": 7480810,
  "type": "Feature",
  "properties": {
    "tgn:hierarchy":[
        "tgn:7480810",
        "tgn:7001010",
        "tgn:1000004",
        "tgn:1000141",
        "tgn:7029392"
    ],
    "tgn:id":7480810,
    "tgn:name":"Hai'an Shanmai",
    "tgn:placetype":[
        "aat:300008795"
    ]
},
  "bbox": [],
  "geometry": {"coordinates":[121.569722,23.828889],"type":"Point"}
}
=======
{"geometry":{"type":"Point","coordinates":[121.569722,23.828889]},"type":"Feature","properties":{"hierarchy":["tgn:7480810","tgn:7001010","tgn:1000004","tgn:1000141","tgn:7029392"],"placetype":["aat:300008795"],"id":7480810,"name:xx":"Hai'an Shanmai"}}
>>>>>>> 03f74aca74312dbeaf24d7e61306dd6a786dc3d0
