{
  "id": 2416953,
  "type": "Feature",
  "properties": {
    "tgn:hierarchy":[
        "tgn:2416953",
        "tgn:1000001",
        "tgn:7012149",
        "tgn:2001709",
        "tgn:7007708",
        "tgn:7029392"
    ],
    "tgn:id":2416953,
    "tgn:name":"Jackass Creek",
    "tgn:placetype":[
        "aat:300008706"
    ]
},
  "bbox": [],
  "geometry": {"coordinates":[-119.15,43.0167],"type":"Point"}
}