{
  "id": 2411944,
  "type": "Feature",
  "properties": {
    "tgn:hierarchy":[
        "tgn:2411944",
        "tgn:1000001",
        "tgn:2002325",
        "tgn:7012149",
        "tgn:7007922",
        "tgn:7029392"
    ],
    "tgn:id":2411944,
    "tgn:name":"Indian Point",
    "tgn:placetype":[
        "aat:300008850"
    ]
},
  "bbox": [],
  "geometry": {"coordinates":[-88.9167,43.8167],"type":"Point"}
}