{
  "id": 2458077,
  "type": "Feature",
  "properties": {
    "tgn:hierarchy":[
        "tgn:2458077",
        "tgn:1000001",
        "tgn:7012149",
        "tgn:2001075",
        "tgn:7007521",
        "tgn:7029392"
    ],
    "tgn:id":2458077,
    "tgn:name":"Little Mound Lake",
    "tgn:placetype":[
        "aat:300008680"
    ]
},
  "bbox": [],
  "geometry": {"coordinates":[-94.6667,45.8333],"type":"Point"}
}