{
  "id": 7224673,
  "type": "Feature",
  "properties": {
    "tgn:hierarchy":[
        "tgn:7224673",
        "tgn:7011270",
        "tgn:7002674",
        "tgn:1000003",
        "tgn:1000074",
        "tgn:7029392"
    ],
    "tgn:id":7224673,
    "tgn:name":"Strongyl\u00f3, Nis\u00edda",
    "tgn:placetype":[
        "aat:300008791"
    ]
},
  "bbox": [],
  "geometry": {"coordinates":[24.960833,36.948056],"type":"Point"}
}