{
  "id": 7007942,
  "type": "Feature",
  "properties": {
    "tgn:hierarchy":[
        "tgn:7007942",
        "tgn:7002758",
        "tgn:7002830",
        "tgn:1000003",
        "tgn:1000095",
        "tgn:7029392"
    ],
    "tgn:id":7007942,
    "tgn:name":"M\u00e1laga",
    "tgn:placetype":[
        "aat:300008347",
        "aat:300008389",
        "aat:300387223",
        "aat:300387302",
        "aat:300120599"
    ]
},
  "bbox": [],
  "geometry": {"coordinates":[-4.416667,36.716667],"type":"Point"}
}