{
  "id": 7545152,
  "type": "Feature",
  "properties": {
    "tgn:hierarchy":[
        "tgn:7545152",
        "tgn:1000004",
        "tgn:7000198",
        "tgn:7016788",
        "tgn:7029392"
    ],
    "tgn:id":7545152,
    "tgn:name:en":"Bad\u0101bara Railroad Station",
    "tgn:placetype":[
        "aat:300007783"
    ]
},
  "bbox": [],
  "geometry": {"coordinates":[74.357465,27.156018],"type":"Point"}
}