{
  "id": 2727475,
  "type": "Feature",
  "properties": {
    "tgn:hierarchy":[
        "tgn:2727475",
        "tgn:1000001",
        "tgn:2000469",
        "tgn:7012149",
        "tgn:7007250",
        "tgn:7029392"
    ],
    "tgn:id":2727475,
    "tgn:name":"Trail Creek",
    "tgn:placetype":[
        "aat:300008706"
    ]
},
  "bbox": [],
  "geometry": {"coordinates":[-115.7833,46.5833],"type":"Point"}
}