<<<<<<< HEAD
{
  "id": 2334076,
  "type": "Feature",
  "properties": {
    "tgn:hierarchy":[
        "tgn:2334076",
        "tgn:1000001",
        "tgn:2000860",
        "tgn:7012149",
        "tgn:7007256",
        "tgn:7029392"
    ],
    "tgn:id":2334076,
    "tgn:name":"Fords",
    "tgn:placetype":[
        "aat:300008347"
    ]
},
  "bbox": [],
  "geometry": {"coordinates":[-92.9833,32.5333],"type":"Point"}
}
=======
{"geometry":{"type":"Point","coordinates":[-92.983300,32.533300]},"type":"Feature","properties":{"hierarchy":["tgn:2334076","tgn:1000001","tgn:2000860","tgn:7012149","tgn:7007256","tgn:7029392"],"placetype":["aat:300008347"],"id":2334076,"name:xx":"Fords"}}
>>>>>>> 03f74aca74312dbeaf24d7e61306dd6a786dc3d0
