{
  "id": 1107844,
  "type": "Feature",
  "properties": {
    "tgn:hierarchy":[
        "tgn:1107844",
        "tgn:7016675",
        "tgn:1000004",
        "tgn:7000896",
        "tgn:1000120",
        "tgn:7029392"
    ],
    "tgn:id":1107844,
    "tgn:name":"Arima-fuji",
    "tgn:placetype":[
        "aat:300008777"
    ]
},
  "bbox": [],
  "geometry": {"coordinates":[135.2333,34.9167],"type":"Point"}
}