{
  "id": 7292128,
  "type": "Feature",
  "properties": {
    "tgn:hierarchy":[
        "tgn:7292128",
        "tgn:1001702",
        "tgn:1000049",
        "tgn:1000002",
        "tgn:7029392"
    ],
    "tgn:id":7292128,
    "tgn:name":"El Vapor, Chorrillo",
    "tgn:placetype":[
        "aat:300008699"
    ]
},
  "bbox": [],
  "geometry": {"coordinates":[-71.45,-52.633333],"type":"Point"}
}