{
  "id": 7592932,
  "type": "Feature",
  "properties": {
    "tgn:hierarchy":[
        "tgn:7592932",
        "tgn:1000004",
        "tgn:7000198",
        "tgn:7000799",
        "tgn:7029392"
    ],
    "tgn:id":7592932,
    "tgn:name:en":"J\u0101n\u012bpura",
    "tgn:placetype":[
        "aat:300008347"
    ]
},
  "bbox": [],
  "geometry": {"coordinates":[74.851085,32.754772],"type":"Point"}
}