{
  "id": 1060624,
  "type": "Feature",
  "properties": {
    "tgn:hierarchy":[
        "tgn:1060624",
        "tgn:4000818",
        "tgn:1000004",
        "tgn:7018214",
        "tgn:7002435",
        "tgn:7029392"
    ],
    "tgn:id":1060624,
    "tgn:name":"Uyemskiy",
    "tgn:placetype":[
        "aat:300008347"
    ]
},
  "bbox": [],
  "geometry": {"coordinates":[40.8333,64.65],"type":"Point"}
}