<<<<<<< HEAD
{
  "id": 7470021,
  "type": "Feature",
  "properties": {
    "tgn:hierarchy":[
        "tgn:7470021",
        "tgn:7001010",
        "tgn:1000004",
        "tgn:1000141",
        "tgn:7029392"
    ],
    "tgn:id":7470021,
    "tgn:name":"Zhongyuan",
    "tgn:placetype":[
        "aat:300008347"
    ]
},
  "bbox": [],
  "geometry": {"coordinates":[121.459487,23.736545],"type":"Point"}
}
=======
{"geometry":{"type":"Point","coordinates":[121.459487,23.736545]},"type":"Feature","properties":{"hierarchy":["tgn:7470021","tgn:7001010","tgn:1000004","tgn:1000141","tgn:7029392"],"placetype":["aat:300008347"],"id":7470021,"name:xx":"Zhongyuan"}}
>>>>>>> 03f74aca74312dbeaf24d7e61306dd6a786dc3d0
