{
  "id": 2618282,
  "type": "Feature",
  "properties": {
    "tgn:hierarchy":[
        "tgn:2618282",
        "tgn:1000001",
        "tgn:7012149",
        "tgn:2000837",
        "tgn:7007255",
        "tgn:7029392"
    ],
    "tgn:id":2618282,
    "tgn:name":"Riggs Creek",
    "tgn:placetype":[
        "aat:300008706"
    ]
},
  "bbox": [],
  "geometry": {"coordinates":[-82.3833,37.3833],"type":"Point"}
}