<<<<<<< HEAD
{
  "id": 2257383,
  "type": "Feature",
  "properties": {
    "tgn:hierarchy":[
        "tgn:2257383",
        "tgn:1000001",
        "tgn:7012149",
        "tgn:2001447",
        "tgn:7007566",
        "tgn:7029392"
    ],
    "tgn:id":2257383,
    "tgn:name":"Cornudas Tank",
    "tgn:placetype":[
        "aat:300006191"
    ]
},
  "bbox": [],
  "geometry": {"coordinates":[-105.5167,32.0833],"type":"Point"}
}
=======
{"geometry":{"type":"Point","coordinates":[-105.516700,32.083300]},"type":"Feature","properties":{"hierarchy":["tgn:2257383","tgn:1000001","tgn:7012149","tgn:2001447","tgn:7007566","tgn:7029392"],"placetype":["aat:300006191"],"id":2257383,"name:xx":"Cornudas Tank"}}
>>>>>>> 03f74aca74312dbeaf24d7e61306dd6a786dc3d0
