{
  "id": 7480870,
  "type": "Feature",
  "properties": {
    "tgn:hierarchy":[
        "tgn:7480870",
        "tgn:1000004",
        "tgn:7471332",
        "tgn:1000141",
        "tgn:7029392"
    ],
    "tgn:id":7480870,
    "tgn:name":"Liuquwo",
    "tgn:placetype":[
        "aat:300008347"
    ]
},
  "bbox": [],
  "geometry": {"coordinates":[121.244167,24.762222],"type":"Point"}
}