{
  "id": 7114241,
  "type": "Feature",
  "properties": {
    "tgn:hierarchy":[
        "tgn:7114241",
        "tgn:1000003",
        "tgn:7003676",
        "tgn:7000084",
        "tgn:7029392"
    ],
    "tgn:id":7114241,
    "tgn:name":"Renzel",
    "tgn:placetype":[
        "aat:300008347"
    ]
},
  "bbox": [],
  "geometry": {"coordinates":[8.733333,52.583333],"type":"Point"}
}