{
  "id": 7094217,
  "type": "Feature",
  "properties": {
    "tgn:hierarchy":[
        "tgn:7094217",
        "tgn:7003669",
        "tgn:1000003",
        "tgn:7000084",
        "tgn:7029392"
    ],
    "tgn:id":7094217,
    "tgn:name":"Sch\u00fcrpfeneck Berg",
    "tgn:placetype":[
        "aat:300008795"
    ]
},
  "bbox": [],
  "geometry": {"coordinates":[11.433333,47.566667],"type":"Point"}
}