<<<<<<< HEAD
{
  "id": 7472306,
  "type": "Feature",
  "properties": {
    "tgn:hierarchy":[
        "tgn:7472306",
        "tgn:1000004",
        "tgn:7001013",
        "tgn:1000141",
        "tgn:7029392"
    ],
    "tgn:id":7472306,
    "tgn:name":"Wulai Shan",
    "tgn:placetype":[
        "aat:300008798"
    ]
},
  "bbox": [],
  "geometry": {"coordinates":[121.31,24.6675],"type":"Point"}
}
=======
{"geometry":{"type":"Point","coordinates":[121.310000,24.667500]},"type":"Feature","properties":{"hierarchy":["tgn:7472306","tgn:1000004","tgn:7001013","tgn:1000141","tgn:7029392"],"placetype":["aat:300008798"],"id":7472306,"name:xx":"Wulai Shan"}}
>>>>>>> 03f74aca74312dbeaf24d7e61306dd6a786dc3d0
