{
  "id": 7397916,
  "type": "Feature",
  "properties": {
    "tgn:hierarchy":[
        "tgn:7397916",
        "tgn:1000001",
        "tgn:1001960",
        "tgn:7005560",
        "tgn:7029392"
    ],
    "tgn:id":7397916,
    "tgn:name":"San Mart\u00edn",
    "tgn:placetype":[
        "aat:300006191"
    ]
},
  "bbox": [],
  "geometry": {"coordinates":[-111.551389,30.904444],"type":"Point"}
}