{
  "id": 7200656,
  "type": "Feature",
  "properties": {
    "tgn:hierarchy":[
        "tgn:7200656",
        "tgn:7003669",
        "tgn:1000003",
        "tgn:7000084",
        "tgn:7029392"
    ],
    "tgn:id":7200656,
    "tgn:name":"Eckhof",
    "tgn:placetype":[
        "aat:300000206"
    ]
},
  "bbox": [],
  "geometry": {"coordinates":[13.633333,48.65],"type":"Point"}
}