{
  "id": 7297573,
  "type": "Feature",
  "properties": {
    "tgn:hierarchy":[
        "tgn:7297573",
        "tgn:7002829",
        "tgn:1000003",
        "tgn:7002786",
        "tgn:1000095",
        "tgn:7029392"
    ],
    "tgn:id":7297573,
    "tgn:name":"Souto",
    "tgn:placetype":[
        "aat:300008347"
    ]
},
  "bbox": [],
  "geometry": {"coordinates":[-7.116667,42.933333],"type":"Point"}
}