{
  "id": 7593569,
  "type": "Feature",
  "properties": {
    "tgn:hierarchy":[
        "tgn:7593569",
        "tgn:7005509",
        "tgn:1000001",
        "tgn:7005502",
        "tgn:7029392"
    ],
    "tgn:id":7593569,
    "tgn:name":"Gona\u00efves, Baie des",
    "tgn:placetype":[
        "aat:300132316"
    ]
},
  "bbox": [],
  "geometry": {"coordinates":[-72.74,19.431],"type":"Point"}
}