{
  "id": 1034366,
  "type": "Feature",
  "properties": {
    "tgn:hierarchy":[
        "tgn:1034366",
        "tgn:1000003",
        "tgn:7002877",
        "tgn:1000070",
        "tgn:7029392"
    ],
    "tgn:id":1034366,
    "tgn:name":"Mettray",
    "tgn:placetype":[
        "aat:300008347"
    ]
},
  "bbox": [],
  "geometry": {"coordinates":[0.65,47.45],"type":"Point"}
}