{
  "id": 2499464,
  "type": "Feature",
  "properties": {
    "tgn:hierarchy":[
        "tgn:2499464",
        "tgn:1000001",
        "tgn:7012149",
        "tgn:2001661",
        "tgn:7007707",
        "tgn:7029392"
    ],
    "tgn:id":2499464,
    "tgn:name":"McClure Creek",
    "tgn:placetype":[
        "aat:300008706"
    ]
},
  "bbox": [],
  "geometry": {"coordinates":[-95.0167,35.0333],"type":"Point"}
}