{
  "id": 2245256,
  "type": "Feature",
  "properties": {
    "tgn:hierarchy":[
        "tgn:2245256",
        "tgn:1000001",
        "tgn:7012149",
        "tgn:2000966",
        "tgn:7007520",
        "tgn:7029392"
    ],
    "tgn:id":2245256,
    "tgn:name":"Club Lake",
    "tgn:placetype":[
        "aat:300008680"
    ]
},
  "bbox": [],
  "geometry": {"coordinates":[-88.9333,46.3167],"type":"Point"}
}