{
  "id": 2561159,
  "type": "Feature",
  "properties": {
    "tgn:hierarchy":[
        "tgn:2561159",
        "tgn:1000001",
        "tgn:7012149",
        "tgn:2001442",
        "tgn:7007566",
        "tgn:7029392"
    ],
    "tgn:id":2561159,
    "tgn:name":"Ortiz Tank",
    "tgn:placetype":[
        "aat:300006191"
    ]
},
  "bbox": [],
  "geometry": {"coordinates":[-106.0167,33.8167],"type":"Point"}
}