{
  "id": 2586203,
  "type": "Feature",
  "properties": {
    "tgn:hierarchy":[
        "tgn:2586203",
        "tgn:1000001",
        "tgn:1002271",
        "tgn:7012149",
        "tgn:7007920",
        "tgn:7029392"
    ],
    "tgn:id":2586203,
    "tgn:name":"Pistol Creek",
    "tgn:placetype":[
        "aat:300008706"
    ]
},
  "bbox": [],
  "geometry": {"coordinates":[-124.0833,47.9667],"type":"Point"}
}