{
  "id": 2374232,
  "type": "Feature",
  "properties": {
    "tgn:hierarchy":[
        "tgn:2374232",
        "tgn:1000001",
        "tgn:1002310",
        "tgn:7012149",
        "tgn:7007710",
        "tgn:7029392"
    ],
    "tgn:id":2374232,
    "tgn:name":"Hammonds Rocks",
    "tgn:placetype":[
        "aat:300008798"
    ]
},
  "bbox": [],
  "geometry": {"coordinates":[-77.2333,40.0667],"type":"Point"}
}