{
  "id": 7030154,
  "type": "Feature",
  "properties": {
    "tgn:hierarchy":[
        "tgn:7030154",
        "tgn:7019048",
        "tgn:7002445",
        "tgn:1000003",
        "tgn:7029505",
        "tgn:7008591",
        "tgn:7029392"
    ],
    "tgn:id":7030154,
    "tgn:name":"Oxspring",
    "tgn:placetype":[
        "aat:300008347",
        "aat:300008372"
    ]
},
  "bbox": [],
  "geometry": {"coordinates":[-1.61,53.516],"type":"Point"}
}