{
  "id": 7572679,
  "type": "Feature",
  "properties": {
    "tgn:hierarchy":[
        "tgn:7572679",
        "tgn:1000004",
        "tgn:1001832",
        "tgn:7000198",
        "tgn:7029392"
    ],
    "tgn:id":7572679,
    "tgn:name:en":"Hudukh\u0101ta",
    "tgn:placetype":[
        "aat:300008347"
    ]
},
  "bbox": [],
  "geometry": {"coordinates":[91.103126,26.610347],"type":"Point"}
}