{
  "id": 1027242,
  "type": "Feature",
  "properties": {
    "tgn:hierarchy":[
        "tgn:1027242",
        "tgn:7593917",
        "tgn:1000003",
        "tgn:1001780",
        "tgn:7029392"
    ],
    "tgn:id":1027242,
    "tgn:name":"Jesen\u00edk",
    "tgn:placetype":[
        "aat:300008347"
    ]
},
  "bbox": [],
  "geometry": {"coordinates":[17.203,50.23],"type":"Point"}
}