{
  "id": 7127084,
  "type": "Feature",
  "properties": {
    "tgn:hierarchy":[
        "tgn:7127084",
        "tgn:1000003",
        "tgn:7003677",
        "tgn:7000084",
        "tgn:7029392"
    ],
    "tgn:id":7127084,
    "tgn:name":"Oberauel",
    "tgn:placetype":[
        "aat:300008347"
    ]
},
  "bbox": [],
  "geometry": {"coordinates":[7.216667,50.95],"type":"Point"}
}