{
  "id": 7398021,
  "type": "Feature",
  "properties": {
    "tgn:hierarchy":[
        "tgn:7398021",
        "tgn:1000001",
        "tgn:1001960",
        "tgn:7005560",
        "tgn:7029392"
    ],
    "tgn:id":7398021,
    "tgn:name":"El Padre",
    "tgn:placetype":[
        "aat:300006191"
    ]
},
  "bbox": [],
  "geometry": {"coordinates":[-111.733056,30.909444],"type":"Point"}
}