{
  "id": 2752799,
  "type": "Feature",
  "properties": {
    "tgn:hierarchy":[
        "tgn:2752799",
        "tgn:1002996",
        "tgn:1000001",
        "tgn:7012149",
        "tgn:7007711",
        "tgn:7029392"
    ],
    "tgn:id":2752799,
    "tgn:name":"Watchaug Pond",
    "tgn:placetype":[
        "aat:300008680"
    ]
},
  "bbox": [],
  "geometry": {"coordinates":[-71.6833,41.3833],"type":"Point"}
}