{
  "id": 2346683,
  "type": "Feature",
  "properties": {
    "tgn:hierarchy":[
        "tgn:2346683",
        "tgn:1000001",
        "tgn:7012149",
        "tgn:2000230",
        "tgn:7007158",
        "tgn:7029392"
    ],
    "tgn:id":2346683,
    "tgn:name":"Gearhart Mine",
    "tgn:placetype":[
        "aat:300000390"
    ]
},
  "bbox": [],
  "geometry": {"coordinates":[-108.3833,39.1167],"type":"Point"}
}