{
  "id": 2504399,
  "type": "Feature",
  "properties": {
    "tgn:hierarchy":[
        "tgn:2504399",
        "tgn:1000001",
        "tgn:7012149",
        "tgn:2002272",
        "tgn:7013961",
        "tgn:7029392"
    ],
    "tgn:id":2504399,
    "tgn:name":"Meadows Hollow",
    "tgn:placetype":[
        "aat:300008761"
    ]
},
  "bbox": [],
  "geometry": {"coordinates":[-81.9333,38.15],"type":"Point"}
}