<<<<<<< HEAD
{
  "id": 2259978,
  "type": "Feature",
  "properties": {
    "tgn:hierarchy":[
        "tgn:2259978",
        "tgn:1000001",
        "tgn:7012149",
        "tgn:2001714",
        "tgn:7007708",
        "tgn:7029392"
    ],
    "tgn:id":2259978,
    "tgn:name":"Council Butte",
    "tgn:placetype":[
        "aat:300008798"
    ]
},
  "bbox": [],
  "geometry": {"coordinates":[-121.4,42.45],"type":"Point"}
}
=======
{"geometry":{"type":"Point","coordinates":[-121.400000,42.450000]},"type":"Feature","properties":{"hierarchy":["tgn:2259978","tgn:1000001","tgn:7012149","tgn:2001714","tgn:7007708","tgn:7029392"],"placetype":["aat:300008798"],"id":2259978,"name:xx":"Council Butte"}}
>>>>>>> 03f74aca74312dbeaf24d7e61306dd6a786dc3d0
