{
  "id": 7277305,
  "type": "Feature",
  "properties": {
    "tgn:hierarchy":[
        "tgn:7277305",
        "tgn:7002464",
        "tgn:1000049",
        "tgn:1000002",
        "tgn:7029392"
    ],
    "tgn:id":7277305,
    "tgn:name":"Otaviata, Cerro",
    "tgn:placetype":[
        "aat:300008795"
    ]
},
  "bbox": [],
  "geometry": {"coordinates":[-69.744722,-17.971111],"type":"Point"}
}