{
  "id": 2449842,
  "type": "Feature",
  "properties": {
    "tgn:hierarchy":[
        "tgn:2449842",
        "tgn:1000001",
        "tgn:1002218",
        "tgn:7012149",
        "tgn:7007157",
        "tgn:7029392"
    ],
    "tgn:id":2449842,
    "tgn:name":"Linden Spring",
    "tgn:placetype":[
        "aat:300008697"
    ]
},
  "bbox": [],
  "geometry": {"coordinates":[-121.4333,39.6333],"type":"Point"}
}