{
  "id": 7477826,
  "type": "Feature",
  "properties": {
    "tgn:hierarchy":[
        "tgn:7477826",
        "tgn:1000004",
        "tgn:1000454",
        "tgn:1000141",
        "tgn:7029392"
    ],
    "tgn:id":7477826,
    "tgn:name":"Changtanli Yugang",
    "tgn:placetype":[
        "aat:300008678"
    ]
},
  "bbox": [],
  "geometry": {"coordinates":[121.803329,25.140523],"type":"Point"}
}