{
  "id": 7128237,
  "type": "Feature",
  "properties": {
    "tgn:hierarchy":[
        "tgn:7128237",
        "tgn:1000003",
        "tgn:7003676",
        "tgn:7000084",
        "tgn:7029392"
    ],
    "tgn:id":7128237,
    "tgn:name":"N\u00fcnningen",
    "tgn:placetype":[
        "aat:300008347"
    ]
},
  "bbox": [],
  "geometry": {"coordinates":[9.533333,52.883333],"type":"Point"}
}