{
  "id": 7506434,
  "type": "Feature",
  "properties": {
    "tgn:hierarchy":[
        "tgn:7506434",
        "tgn:1009227",
        "tgn:1000226",
        "tgn:7016729",
        "tgn:1000006",
        "tgn:7029392"
    ],
    "tgn:id":7506434,
    "tgn:name:en":"Rotorua, Lake",
    "tgn:placetype":[
        "aat:300008680"
    ]
},
  "bbox": [],
  "geometry": {"coordinates":[173.583333,-42.416667],"type":"Point"}
}