{
  "id": 7386096,
  "type": "Feature",
  "properties": {
    "tgn:hierarchy":[
        "tgn:7386096",
        "tgn:1000001",
        "tgn:1001960",
        "tgn:7005560",
        "tgn:7029392"
    ],
    "tgn:id":7386096,
    "tgn:name":"Estaci\u00f3n Pititquit",
    "tgn:placetype":[
        "aat:300007783"
    ]
},
  "bbox": [],
  "geometry": {"coordinates":[-112.016667,30.683333],"type":"Point"}
}