{
  "id": 2559700,
  "type": "Feature",
  "properties": {
    "tgn:hierarchy":[
        "tgn:2559700",
        "tgn:1000001",
        "tgn:7016172",
        "tgn:7012149",
        "tgn:2000174",
        "tgn:7029392"
    ],
    "tgn:id":2559700,
    "tgn:name":"Open Brake",
    "tgn:placetype":[
        "aat:300008680"
    ]
},
  "bbox": [],
  "geometry": {"coordinates":[-92.1333,33.1167],"type":"Point"}
}