<<<<<<< HEAD
{
  "id": 2157502,
  "type": "Feature",
  "properties": {
    "tgn:hierarchy":[
        "tgn:2157502",
        "tgn:1000001",
        "tgn:7012149",
        "tgn:1002552",
        "tgn:7007920",
        "tgn:7029392"
    ],
    "tgn:id":2157502,
    "tgn:name":"Beaver Creek",
    "tgn:placetype":[
        "aat:300008706"
    ]
},
  "bbox": [],
  "geometry": {"coordinates":[-122.55,47.5333],"type":"Point"}
}
=======
{"geometry":{"type":"Point","coordinates":[-122.550000,47.533300]},"type":"Feature","properties":{"hierarchy":["tgn:2157502","tgn:1000001","tgn:7012149","tgn:1002552","tgn:7007920","tgn:7029392"],"placetype":["aat:300008706"],"id":2157502,"name:xx":"Beaver Creek"}}
>>>>>>> 03f74aca74312dbeaf24d7e61306dd6a786dc3d0
