{
  "id": 7218573,
  "type": "Feature",
  "properties": {
    "tgn:hierarchy":[
        "tgn:7218573",
        "tgn:7011330",
        "tgn:7002674",
        "tgn:1000003",
        "tgn:1000074",
        "tgn:7029392"
    ],
    "tgn:id":7218573,
    "tgn:name":"Meg\u00e1los N\u00edftis, \u00c1kra",
    "tgn:placetype":[
        "aat:300386846"
    ]
},
  "bbox": [],
  "geometry": {"coordinates":[29.604722,36.147222],"type":"Point"}
}