{
  "id": 2530468,
  "type": "Feature",
  "properties": {
    "tgn:hierarchy":[
        "tgn:2530468",
        "tgn:1000001",
        "tgn:7012149",
        "tgn:1002535",
        "tgn:7007826",
        "tgn:7029392"
    ],
    "tgn:id":2530468,
    "tgn:name":"Muddy Cedar Creek",
    "tgn:placetype":[
        "aat:300008706"
    ]
},
  "bbox": [],
  "geometry": {"coordinates":[-96.1667,32.7833],"type":"Point"}
}