{
  "id": 1121502,
  "type": "Feature",
  "properties": {
    "tgn:hierarchy":[
        "tgn:1121502",
        "tgn:7001242",
        "tgn:7029392"
    ],
    "tgn:id":1121502,
    "tgn:name":"Auob",
    "tgn:placetype":[
        "aat:300008707"
    ]
},
  "bbox": [],
  "geometry": {"coordinates":[20.6167,-26.9333],"type":"Point"}
}