{
  "id": 2341774,
  "type": "Feature",
  "properties": {
    "tgn:hierarchy":[
        "tgn:2341774",
        "tgn:7006450",
        "tgn:1000001",
        "tgn:7012149",
        "tgn:2000088",
        "tgn:7029392"
    ],
    "tgn:id":2341774,
    "tgn:name":"Frosty Bay",
    "tgn:placetype":[
        "aat:300132316"
    ]
},
  "bbox": [],
  "geometry": {"coordinates":[-131.9667,56.05],"type":"Point"}
}