<<<<<<< HEAD
{
  "id": 2765997,
  "type": "Feature",
  "properties": {
    "tgn:hierarchy":[
        "tgn:2765997",
        "tgn:1000001",
        "tgn:7012149",
        "tgn:7016020",
        "tgn:7007710",
        "tgn:7029392"
    ],
    "tgn:id":2765997,
    "tgn:name":"White Hollow",
    "tgn:placetype":[
        "aat:300008761"
    ]
},
  "bbox": [],
  "geometry": {"coordinates":[-78.3333,41.7667],"type":"Point"}
}
=======
{"geometry":{"type":"Point","coordinates":[-78.333300,41.766700]},"type":"Feature","properties":{"hierarchy":["tgn:2765997","tgn:1000001","tgn:7012149","tgn:7016020","tgn:7007710","tgn:7029392"],"placetype":["aat:300008761"],"id":2765997,"name:xx":"White Hollow"}}
>>>>>>> 03f74aca74312dbeaf24d7e61306dd6a786dc3d0
