{
  "id": 2607108,
  "type": "Feature",
  "properties": {
    "tgn:hierarchy":[
        "tgn:2607108",
        "tgn:1000001",
        "tgn:7012149",
        "tgn:7014589",
        "tgn:7007515",
        "tgn:7029392"
    ],
    "tgn:id":2607108,
    "tgn:name":"Rand Lake",
    "tgn:placetype":[
        "aat:300008680"
    ]
},
  "bbox": [],
  "geometry": {"coordinates":[-67.1833,45.0833],"type":"Point"}
}