{
  "id": 7577875,
  "type": "Feature",
  "properties": {
    "tgn:hierarchy":[
        "tgn:7577875",
        "tgn:1000004",
        "tgn:1001869",
        "tgn:7000198",
        "tgn:7029392"
    ],
    "tgn:id":7577875,
    "tgn:name:en":"Lotpur",
    "tgn:placetype":[
        "aat:300008347"
    ]
},
  "bbox": [],
  "geometry": {"coordinates":[71.433333,20.966667],"type":"Point"}
}