<<<<<<< HEAD
{
  "id": 7489304,
  "type": "Feature",
  "properties": {
    "tgn:hierarchy":[
        "tgn:7489304",
        "tgn:7468018",
        "tgn:1000004",
        "tgn:1000141",
        "tgn:7029392"
    ],
    "tgn:id":7489304,
    "tgn:name":"Neigou",
    "tgn:placetype":[
        "aat:300387036"
    ]
},
  "bbox": [],
  "geometry": {"coordinates":[120.083333,23.4],"type":"Point"}
}
=======
{"geometry":{"type":"Point","coordinates":[120.083333,23.400000]},"type":"Feature","properties":{"hierarchy":["tgn:7489304","tgn:7468018","tgn:1000004","tgn:1000141","tgn:7029392"],"placetype":["aat:300387036"],"id":7489304,"name:xx":"Neigou"}}
>>>>>>> 03f74aca74312dbeaf24d7e61306dd6a786dc3d0
