{
  "id": 2185610,
  "type": "Feature",
  "properties": {
    "tgn:hierarchy":[
        "tgn:2185610",
        "tgn:1000001",
        "tgn:7012149",
        "tgn:2002190",
        "tgn:7007919",
        "tgn:7029392"
    ],
    "tgn:id":2185610,
    "tgn:name":"Boiling Spring",
    "tgn:placetype":[
        "aat:300008697"
    ]
},
  "bbox": [],
  "geometry": {"coordinates":[-78.6833,38.6833],"type":"Point"}
}