{
  "id": 7321232,
  "type": "Feature",
  "properties": {
    "tgn:hierarchy":[
        "tgn:7321232",
        "tgn:1001623",
        "tgn:1000049",
        "tgn:1000002",
        "tgn:7029392"
    ],
    "tgn:id":7321232,
    "tgn:name":"Camello, Punta",
    "tgn:placetype":[
        "aat:300386846"
    ]
},
  "bbox": [],
  "geometry": {"coordinates":[-72.983333,-45.433333],"type":"Point"}
}