{
  "id": 7349984,
  "type": "Feature",
  "properties": {
    "tgn:hierarchy":[
        "tgn:7349984",
        "tgn:1000001",
        "tgn:7005592",
        "tgn:7005560",
        "tgn:7029392"
    ],
    "tgn:id":7349984,
    "tgn:name":"Acoyotitla",
    "tgn:placetype":[
        "aat:300008347"
    ]
},
  "bbox": [],
  "geometry": {"coordinates":[-97.983333,20.466667],"type":"Point"}
}