{
  "id": 2220529,
  "type": "Feature",
  "properties": {
    "tgn:hierarchy":[
        "tgn:2220529",
        "tgn:1000001",
        "tgn:7012149",
        "tgn:2000933",
        "tgn:7007515",
        "tgn:7029392"
    ],
    "tgn:id":2220529,
    "tgn:name":"Cape Neddick River",
    "tgn:placetype":[
        "aat:300008707"
    ]
},
  "bbox": [],
  "geometry": {"coordinates":[-70.6333,43.1667],"type":"Point"}
}