<<<<<<< HEAD
{
  "id": 2400524,
  "type": "Feature",
  "properties": {
    "tgn:hierarchy":[
        "tgn:2400524",
        "tgn:1000001",
        "tgn:7012149",
        "tgn:7007157",
        "tgn:1002894",
        "tgn:7029392"
    ],
    "tgn:id":2400524,
    "tgn:name":"Horse Lake",
    "tgn:placetype":[
        "aat:300008680"
    ]
},
  "bbox": [],
  "geometry": {"coordinates":[-120.65,39.65],"type":"Point"}
}
=======
{"geometry":{"type":"Point","coordinates":[-120.650000,39.650000]},"type":"Feature","properties":{"hierarchy":["tgn:2400524","tgn:1000001","tgn:7012149","tgn:7007157","tgn:1002894","tgn:7029392"],"placetype":["aat:300008680"],"id":2400524,"name:xx":"Horse Lake"}}
>>>>>>> 03f74aca74312dbeaf24d7e61306dd6a786dc3d0
