{
  "id": 2262485,
  "type": "Feature",
  "properties": {
    "tgn:hierarchy":[
        "tgn:2262485",
        "tgn:1000001",
        "tgn:7012149",
        "tgn:2000929",
        "tgn:7007515",
        "tgn:7029392"
    ],
    "tgn:id":2262485,
    "tgn:name":"Cow Island",
    "tgn:placetype":[
        "aat:300008791"
    ]
},
  "bbox": [],
  "geometry": {"coordinates":[-69.9333,43.9167],"type":"Point"}
}