{
  "id": 2572927,
  "type": "Feature",
  "properties": {
    "tgn:hierarchy":[
        "tgn:2572927",
        "tgn:1000001",
        "tgn:2000470",
        "tgn:7012149",
        "tgn:7007250",
        "tgn:7029392"
    ],
    "tgn:id":2572927,
    "tgn:name":"Pearl Creek",
    "tgn:placetype":[
        "aat:300008706"
    ]
},
  "bbox": [],
  "geometry": {"coordinates":[-115.0833,44.5833],"type":"Point"}
}