{
  "id": 7151179,
  "type": "Feature",
  "properties": {
    "tgn:hierarchy":[
        "tgn:7151179",
        "tgn:7003692",
        "tgn:1000003",
        "tgn:7000084",
        "tgn:7029392"
    ],
    "tgn:id":7151179,
    "tgn:name":"Kaisersbach",
    "tgn:placetype":[
        "aat:300008347"
    ]
},
  "bbox": [],
  "geometry": {"coordinates":[9.3775,49.067778],"type":"Point"}
}