{
  "id": 2353587,
  "type": "Feature",
  "properties": {
    "tgn:hierarchy":[
        "tgn:2353587",
        "tgn:1000001",
        "tgn:7012149",
        "tgn:7007157",
        "tgn:1002857",
        "tgn:7029392"
    ],
    "tgn:id":2353587,
    "tgn:name":"Gold Hill Mine",
    "tgn:placetype":[
        "aat:300000390"
    ]
},
  "bbox": [],
  "geometry": {"coordinates":[-116.7833,34.25],"type":"Point"}
}