{
  "id": 7586989,
  "type": "Feature",
  "properties": {
    "tgn:hierarchy":[
        "tgn:7586989",
        "tgn:1000004",
        "tgn:7000198",
        "tgn:7000799",
        "tgn:7029392"
    ],
    "tgn:id":7586989,
    "tgn:name:en":"Chigul Namgole",
    "tgn:placetype":[
        "aat:300008347"
    ]
},
  "bbox": [],
  "geometry": {"coordinates":[78.952425,32.609298],"type":"Point"}
}