{
  "id": 7110858,
  "type": "Feature",
  "properties": {
    "tgn:hierarchy":[
        "tgn:7110858",
        "tgn:1000003",
        "tgn:7003677",
        "tgn:7000084",
        "tgn:7029392"
    ],
    "tgn:id":7110858,
    "tgn:name":"Puderburg",
    "tgn:placetype":[
        "aat:300008795"
    ]
},
  "bbox": [],
  "geometry": {"coordinates":[8.45,50.95],"type":"Point"}
}