{
  "id": 7478079,
  "type": "Feature",
  "properties": {
    "tgn:hierarchy":[
        "tgn:7478079",
        "tgn:7488858",
        "tgn:1000004",
        "tgn:1000141",
        "tgn:7029392"
    ],
    "tgn:id":7478079,
    "tgn:name":"Bagua Shan Shanmo",
    "tgn:placetype":[
        "aat:300008795"
    ]
},
  "bbox": [],
  "geometry": {"coordinates":[120.625754,23.931688],"type":"Point"}
}