<<<<<<< HEAD
{
  "id": 7478079,
  "type": "Feature",
  "properties": {
    "tgn:hierarchy":[
        "tgn:7478079",
        "tgn:7488858",
        "tgn:1000004",
        "tgn:1000141",
        "tgn:7029392"
    ],
    "tgn:id":7478079,
    "tgn:name":"Bagua Shan Shanmo",
    "tgn:placetype":[
        "aat:300008795"
    ]
},
  "bbox": [],
  "geometry": {"coordinates":[120.625754,23.931688],"type":"Point"}
}
=======
{"geometry":{"type":"Point","coordinates":[120.625754,23.931688]},"type":"Feature","properties":{"hierarchy":["tgn:7478079","tgn:7488858","tgn:1000004","tgn:1000141","tgn:7029392"],"placetype":["aat:300008795"],"id":7478079,"name:xx":"Bagua Shan Shanmo"}}
>>>>>>> 03f74aca74312dbeaf24d7e61306dd6a786dc3d0
