{
  "id": 7086929,
  "type": "Feature",
  "properties": {
    "tgn:hierarchy":[
        "tgn:7086929",
        "tgn:1000003",
        "tgn:7000094",
        "tgn:7000084",
        "tgn:7029392"
    ],
    "tgn:id":7086929,
    "tgn:name":"Warnekow",
    "tgn:placetype":[
        "aat:300008347"
    ]
},
  "bbox": [],
  "geometry": {"coordinates":[13.766667,53.95],"type":"Point"}
}