{
  "id": 2184657,
  "type": "Feature",
  "properties": {
    "tgn:hierarchy":[
        "tgn:2184657",
        "tgn:7002659",
        "tgn:1000001",
        "tgn:2000020",
        "tgn:7012149",
        "tgn:7029392"
    ],
    "tgn:id":2184657,
    "tgn:name":"Bodifords Lake",
    "tgn:placetype":[
        "aat:300006191"
    ]
},
  "bbox": [],
  "geometry": {"coordinates":[-86.2667,31.85],"type":"Point"}
}