{
  "id": 2684262,
  "type": "Feature",
  "properties": {
    "tgn:hierarchy":[
        "tgn:2684262",
        "tgn:1000001",
        "tgn:7012149",
        "tgn:2002382",
        "tgn:7007923",
        "tgn:7029392"
    ],
    "tgn:id":2684262,
    "tgn:name":"Sphaeralcea Reservoir",
    "tgn:placetype":[
        "aat:300006191"
    ]
},
  "bbox": [],
  "geometry": {"coordinates":[-110.3667,42.5333],"type":"Point"}
}