{
  "id": 2145980,
  "type": "Feature",
  "properties": {
    "tgn:hierarchy":[
        "tgn:2145980",
        "tgn:1000001",
        "tgn:2002136",
        "tgn:7012149",
        "tgn:7007828",
        "tgn:7029392"
    ],
    "tgn:id":2145980,
    "tgn:name":"Ball Hill",
    "tgn:placetype":[
        "aat:300008798"
    ]
},
  "bbox": [],
  "geometry": {"coordinates":[-72.6167,43.35],"type":"Point"}
}