{
  "id": 2531870,
  "type": "Feature",
  "properties": {
    "tgn:hierarchy":[
        "tgn:2531870",
        "tgn:1000001",
        "tgn:1002217",
        "tgn:7012149",
        "tgn:7007710",
        "tgn:7029392"
    ],
    "tgn:id":2531870,
    "tgn:name":"Mulligan Run",
    "tgn:placetype":[
        "aat:300008699"
    ]
},
  "bbox": [],
  "geometry": {"coordinates":[-79.9833,40.9167],"type":"Point"}
}