<<<<<<< HEAD
{
  "id": 7020834,
  "type": "Feature",
  "properties": {
    "tgn:hierarchy":[
        "tgn:7020834",
        "tgn:2000453",
        "tgn:1000001",
        "tgn:7012149",
        "tgn:7007250",
        "tgn:7029392"
    ],
    "tgn:id":7020834,
    "tgn:name":"West Fork Weiser River",
    "tgn:placetype":[
        "aat:300008707"
    ]
},
  "bbox": [],
  "geometry": {"coordinates":[-116.5,45.0],"type":"Point"}
}
=======
{"geometry":{"type":"Point","coordinates":[-116.500000,45.000000]},"type":"Feature","properties":{"hierarchy":["tgn:7020834","tgn:2000453","tgn:1000001","tgn:7012149","tgn:7007250","tgn:7029392"],"placetype":["aat:300008707"],"id":7020834,"name:xx":"West Fork Weiser River"}}
>>>>>>> 03f74aca74312dbeaf24d7e61306dd6a786dc3d0
