{
  "id": 1016678,
  "type": "Feature",
  "properties": {
    "tgn:hierarchy":[
        "tgn:1016678",
        "tgn:1000601",
        "tgn:1000001",
        "tgn:7005493",
        "tgn:7029392"
    ],
    "tgn:id":1016678,
    "tgn:name":"Moraz\u00e1n",
    "tgn:placetype":[
        "aat:300008347"
    ]
},
  "bbox": [],
  "geometry": {"coordinates":[-90.15,14.9333],"type":"Point"}
}