{
  "id": 2325415,
  "type": "Feature",
  "properties": {
    "tgn:hierarchy":[
        "tgn:2325415",
        "tgn:1000001",
        "tgn:7012149",
        "tgn:7015666",
        "tgn:7007825",
        "tgn:7029392"
    ],
    "tgn:id":2325415,
    "tgn:name":"Ferry Hill Hollow",
    "tgn:placetype":[
        "aat:300008761"
    ]
},
  "bbox": [],
  "geometry": {"coordinates":[-87.25,35.7333],"type":"Point"}
}