{
  "id": 2183969,
  "type": "Feature",
  "properties": {
    "tgn:hierarchy":[
        "tgn:2183969",
        "tgn:1000001",
        "tgn:7012149",
        "tgn:7014510",
        "tgn:7007920",
        "tgn:7029392"
    ],
    "tgn:id":2183969,
    "tgn:name":"Boat Harbor",
    "tgn:placetype":[
        "aat:300132316"
    ]
},
  "bbox": [],
  "geometry": {"coordinates":[-122.5667,48.5333],"type":"Point"}
}