{
  "id": 2352371,
  "type": "Feature",
  "properties": {
    "tgn:hierarchy":[
        "tgn:2352371",
        "tgn:1000001",
        "tgn:7012149",
        "tgn:1002392",
        "tgn:7007157",
        "tgn:7029392"
    ],
    "tgn:id":2352371,
    "tgn:name":"Goat Crest",
    "tgn:placetype":[
        "aat:300266640"
    ]
},
  "bbox": [],
  "geometry": {"coordinates":[-118.5833,36.8833],"type":"Point"}
}