{
  "id": 7062426,
  "type": "Feature",
  "properties": {
    "tgn:hierarchy":[
        "tgn:7062426",
        "tgn:1000003",
        "tgn:7003689",
        "tgn:7000084",
        "tgn:7029392"
    ],
    "tgn:id":7062426,
    "tgn:name":"Auen-Berg",
    "tgn:placetype":[
        "aat:300008777"
    ]
},
  "bbox": [],
  "geometry": {"coordinates":[11.716667,50.766667],"type":"Point"}
}