{
  "id": 7273965,
  "type": "Feature",
  "properties": {
    "tgn:concordances":{
        "gn:id":"2744032"
    },
    "tgn:hierarchy":[
        "tgn:7273965",
        "tgn:1000003",
        "tgn:7006951",
        "tgn:7016845",
        "tgn:7029392"
    ],
    "tgn:id":7273965,
    "tgn:name:nl":"Zanegeest",
    "tgn:placetype":[
        "aat:300008347"
    ]
},
  "bbox": [],
  "geometry": {"coordinates":[4.716667,52.683333],"type":"Point"}
}