{
  "id": 1057635,
  "type": "Feature",
  "properties": {
    "tgn:hierarchy":[
        "tgn:1057635",
        "tgn:1000004",
        "tgn:1003424",
        "tgn:7018214",
        "tgn:7002435",
        "tgn:7029392"
    ],
    "tgn:id":1057635,
    "tgn:name":"Novobelaya",
    "tgn:placetype":[
        "aat:300008347"
    ]
},
  "bbox": [],
  "geometry": {"coordinates":[39.3333,49.8333],"type":"Point"}
}