{
  "id": 2698285,
  "type": "Feature",
  "properties": {
    "tgn:hierarchy":[
        "tgn:2698285",
        "tgn:2000768",
        "tgn:1000001",
        "tgn:7012149",
        "tgn:7007255",
        "tgn:7029392"
    ],
    "tgn:id":2698285,
    "tgn:name":"Strader Branch",
    "tgn:placetype":[
        "aat:300008699"
    ]
},
  "bbox": [],
  "geometry": {"coordinates":[-85.75,37.05],"type":"Point"}
}