{
  "id": 2705270,
  "type": "Feature",
  "properties": {
    "tgn:hierarchy":[
        "tgn:2705270",
        "tgn:1000001",
        "tgn:7012149",
        "tgn:2001708",
        "tgn:7007708",
        "tgn:7029392"
    ],
    "tgn:id":2705270,
    "tgn:name":"Suplee Spring",
    "tgn:placetype":[
        "aat:300008697"
    ]
},
  "bbox": [],
  "geometry": {"coordinates":[-119.6167,44.1333],"type":"Point"}
}