{
  "id": 7500293,
  "type": "Feature",
  "properties": {
    "tgn:hierarchy":[
        "tgn:7500293",
        "tgn:7001010",
        "tgn:1000004",
        "tgn:1000141",
        "tgn:7029392"
    ],
    "tgn:id":7500293,
    "tgn:name":"Balanshake Shan",
    "tgn:placetype":[
        "aat:300008798"
    ]
},
  "bbox": [],
  "geometry": {"coordinates":[121.116389,23.290278],"type":"Point"}
}