{
  "id": 7562350,
  "type": "Feature",
  "properties": {
    "tgn:hierarchy":[
        "tgn:7562350",
        "tgn:1000004",
        "tgn:7000198",
        "tgn:1001894",
        "tgn:7029392"
    ],
    "tgn:id":7562350,
    "tgn:name:en":"Bagi\u0101pura",
    "tgn:placetype":[
        "aat:300008347"
    ]
},
  "bbox": [],
  "geometry": {"coordinates":[79.07631,26.34457],"type":"Point"}
}