{
  "id": 7425095,
  "type": "Feature",
  "properties": {
    "tgn:hierarchy":[
        "tgn:7425095",
        "tgn:7005581",
        "tgn:1000001",
        "tgn:7005560",
        "tgn:7029392"
    ],
    "tgn:id":7425095,
    "tgn:name":"Verde, Laguna",
    "tgn:placetype":[
        "aat:300008680"
    ]
},
  "bbox": [],
  "geometry": {"coordinates":[-104.533333,28.066667],"type":"Point"}
}