{
  "id": 7365287,
  "type": "Feature",
  "properties": {
    "tgn:hierarchy":[
        "tgn:7365287",
        "tgn:1000001",
        "tgn:7005597",
        "tgn:7005560",
        "tgn:7029392"
    ],
    "tgn:id":7365287,
    "tgn:name":"Francisco Villa",
    "tgn:placetype":[
        "aat:300008347"
    ]
},
  "bbox": [],
  "geometry": {"coordinates":[-99.733333,23.166667],"type":"Point"}
}