<<<<<<< HEAD
{
  "id": 2765216,
  "type": "Feature",
  "properties": {
    "tgn:hierarchy":[
        "tgn:2765216",
        "tgn:1000001",
        "tgn:7012149",
        "tgn:2001556",
        "tgn:7007709",
        "tgn:7029392"
    ],
    "tgn:id":2765216,
    "tgn:name":"Whistling Gap Branch",
    "tgn:placetype":[
        "aat:300008699"
    ]
},
  "bbox": [],
  "geometry": {"coordinates":[-82.4167,36.0167],"type":"Point"}
}
=======
{"geometry":{"type":"Point","coordinates":[-82.416700,36.016700]},"type":"Feature","properties":{"hierarchy":["tgn:2765216","tgn:1000001","tgn:7012149","tgn:2001556","tgn:7007709","tgn:7029392"],"placetype":["aat:300008699"],"id":2765216,"name:xx":"Whistling Gap Branch"}}
>>>>>>> 03f74aca74312dbeaf24d7e61306dd6a786dc3d0
