{
  "id": 7546512,
  "type": "Feature",
  "properties": {
    "tgn:hierarchy":[
        "tgn:7546512",
        "tgn:1000004",
        "tgn:7000198",
        "tgn:1001895",
        "tgn:7029392"
    ],
    "tgn:id":7546512,
    "tgn:name:en":"Angar",
    "tgn:placetype":[
        "aat:300008347"
    ]
},
  "bbox": [],
  "geometry": {"coordinates":[75.575167,17.898208],"type":"Point"}
}