{
  "id": 1135004,
  "type": "Feature",
  "properties": {
    "tgn:hierarchy":[
        "tgn:1135004",
        "tgn:1000001",
        "tgn:7012149",
        "tgn:1003042",
        "tgn:7007920",
        "tgn:7029392"
    ],
    "tgn:id":1135004,
    "tgn:name":"Wenas Creek",
    "tgn:placetype":[
        "aat:300008706"
    ]
},
  "bbox": [],
  "geometry": {"coordinates":[-120.7833,46.8667],"type":"Point"}
}