<<<<<<< HEAD
{
  "id": 2763634,
  "type": "Feature",
  "properties": {
    "tgn:hierarchy":[
        "tgn:2763634",
        "tgn:1000001",
        "tgn:7012149",
        "tgn:1002594",
        "tgn:7007920",
        "tgn:7029392"
    ],
    "tgn:id":2763634,
    "tgn:name":"Whalehead Ridge",
    "tgn:placetype":[
        "aat:300266640"
    ]
},
  "bbox": [],
  "geometry": {"coordinates":[-121.8667,46.5833],"type":"Point"}
}
=======
{"geometry":{"type":"Point","coordinates":[-121.866700,46.583300]},"type":"Feature","properties":{"hierarchy":["tgn:2763634","tgn:1000001","tgn:7012149","tgn:1002594","tgn:7007920","tgn:7029392"],"placetype":["aat:300266640"],"id":2763634,"name:xx":"Whalehead Ridge"}}
>>>>>>> 03f74aca74312dbeaf24d7e61306dd6a786dc3d0
