{
  "id": 2397531,
  "type": "Feature",
  "properties": {
    "tgn:hierarchy":[
        "tgn:2397531",
        "tgn:1000001",
        "tgn:7012149",
        "tgn:2000798",
        "tgn:7007255",
        "tgn:7029392"
    ],
    "tgn:id":2397531,
    "tgn:name":"Honey Run",
    "tgn:placetype":[
        "aat:300008699"
    ]
},
  "bbox": [],
  "geometry": {"coordinates":[-85.7833,37.35],"type":"Point"}
}