<<<<<<< HEAD
{
  "id": 7170425,
  "type": "Feature",
  "properties": {
    "tgn:hierarchy":[
        "tgn:7170425",
        "tgn:1000003",
        "tgn:7003676",
        "tgn:7000084",
        "tgn:7029392"
    ],
    "tgn:id":7170425,
    "tgn:name":"Hinteln",
    "tgn:placetype":[
        "aat:300008347"
    ]
},
  "bbox": [],
  "geometry": {"coordinates":[9.9,53.383333],"type":"Point"}
}
=======
{"geometry":{"type":"Point","coordinates":[9.900000,53.383333]},"type":"Feature","properties":{"hierarchy":["tgn:7170425","tgn:1000003","tgn:7003676","tgn:7000084","tgn:7029392"],"placetype":["aat:300008347"],"id":7170425,"name:xx":"Hinteln"}}
>>>>>>> 03f74aca74312dbeaf24d7e61306dd6a786dc3d0
