<<<<<<< HEAD
{
  "id": 7374949,
  "type": "Feature",
  "properties": {
    "tgn:hierarchy":[
        "tgn:7374949",
        "tgn:1000001",
        "tgn:7005599",
        "tgn:7005560",
        "tgn:7029392"
    ],
    "tgn:id":7374949,
    "tgn:name":"La Mojarra",
    "tgn:placetype":[
        "aat:300008347"
    ]
},
  "bbox": [],
  "geometry": {"coordinates":[-95.8,18.6],"type":"Point"}
}
=======
{"geometry":{"type":"Point","coordinates":[-95.800000,18.600000]},"type":"Feature","properties":{"hierarchy":["tgn:7374949","tgn:1000001","tgn:7005599","tgn:7005560","tgn:7029392"],"placetype":["aat:300008347"],"id":7374949,"name:xx":"La Mojarra"}}
>>>>>>> 03f74aca74312dbeaf24d7e61306dd6a786dc3d0
