{
  "id": 2774868,
  "type": "Feature",
  "properties": {
    "tgn:hierarchy":[
        "tgn:2774868",
        "tgn:1000001",
        "tgn:7012149",
        "tgn:7007157",
        "tgn:7029392"
    ],
    "tgn:id":2774868,
    "tgn:name":"Willow Springs Canyon",
    "tgn:placetype":[
        "aat:300008761"
    ]
},
  "bbox": [],
  "geometry": {"coordinates":[-120.4333,35.8333],"type":"Point"}
}