{
  "id": 2312799,
  "type": "Feature",
  "properties": {
    "tgn:hierarchy":[
        "tgn:2312799",
        "tgn:1000001",
        "tgn:7012149",
        "tgn:2001457",
        "tgn:7007566",
        "tgn:7029392"
    ],
    "tgn:id":2312799,
    "tgn:name":"El Padro",
    "tgn:placetype":[
        "aat:300008347"
    ]
},
  "bbox": [],
  "geometry": {"coordinates":[-105.5667,36.4167],"type":"Point"}
}