{
  "id": 7319270,
  "type": "Feature",
  "properties": {
    "tgn:hierarchy":[
        "tgn:7319270",
        "tgn:7002464",
        "tgn:1000049",
        "tgn:1000002",
        "tgn:7029392"
    ],
    "tgn:id":7319270,
    "tgn:name":"Ancoma, R\u00edo",
    "tgn:placetype":[
        "aat:300008699"
    ]
},
  "bbox": [],
  "geometry": {"coordinates":[-69.55,-18.183333],"type":"Point"}
}