{
  "id": 7516623,
  "type": "Feature",
  "properties": {
    "tgn:hierarchy":[
        "tgn:7516623",
        "tgn:1008380",
        "tgn:7520093",
        "tgn:1000226",
        "tgn:1000006",
        "tgn:7029392"
    ],
    "tgn:id":7516623,
    "tgn:name:en":"Mangapipi Stream",
    "tgn:placetype":[
        "aat:300008699"
    ]
},
  "bbox": [],
  "geometry": {"coordinates":[175.633333,-39.966667],"type":"Point"}
}