{
  "id": 7167845,
  "type": "Feature",
  "properties": {
    "tgn:hierarchy":[
        "tgn:7167845",
        "tgn:1000003",
        "tgn:7003676",
        "tgn:7000084",
        "tgn:7029392"
    ],
    "tgn:id":7167845,
    "tgn:name":"Hattorf",
    "tgn:placetype":[
        "aat:300008347"
    ]
},
  "bbox": [],
  "geometry": {"coordinates":[10.75,52.35],"type":"Point"}
}