<<<<<<< HEAD
{
  "id": 7118710,
  "type": "Feature",
  "properties": {
    "tgn:hierarchy":[
        "tgn:7118710",
        "tgn:7003669",
        "tgn:1000003",
        "tgn:7000084",
        "tgn:7029392"
    ],
    "tgn:id":7118710,
    "tgn:name":"Petersberg",
    "tgn:placetype":[
        "aat:300008777"
    ]
},
  "bbox": [],
  "geometry": {"coordinates":[10.383333,49.433333],"type":"Point"}
}
=======
{"geometry":{"type":"Point","coordinates":[10.383333,49.433333]},"type":"Feature","properties":{"hierarchy":["tgn:7118710","tgn:7003669","tgn:1000003","tgn:7000084","tgn:7029392"],"placetype":["aat:300008777"],"id":7118710,"name:xx":"Petersberg"}}
>>>>>>> 03f74aca74312dbeaf24d7e61306dd6a786dc3d0
