{
  "id": 7445335,
  "type": "Feature",
  "properties": {
    "tgn:hierarchy":[
        "tgn:7445335",
        "tgn:7002444",
        "tgn:1000003",
        "tgn:7019109",
        "tgn:7008591",
        "tgn:7029392"
    ],
    "tgn:id":7445335,
    "tgn:name:en":"Waverley Station",
    "tgn:placetype":[
        "aat:300007783"
    ]
},
  "bbox": [],
  "geometry": {"coordinates":[-3.183333,55.95],"type":"Point"}
}