{
  "id": 7359750,
  "type": "Feature",
  "properties": {
    "tgn:hierarchy":[
        "tgn:7359750",
        "tgn:7005586",
        "tgn:1000001",
        "tgn:7005560",
        "tgn:7029392"
    ],
    "tgn:id":7359750,
    "tgn:name":"Coacoyul",
    "tgn:placetype":[
        "aat:300008347"
    ]
},
  "bbox": [],
  "geometry": {"coordinates":[-104.533333,19.583333],"type":"Point"}
}