{
  "id": 1140242,
  "type": "Feature",
  "properties": {
    "tgn:hierarchy":[
        "tgn:1140242",
        "tgn:1000004",
        "tgn:1001338",
        "tgn:1000116",
        "tgn:7029392"
    ],
    "tgn:id":1140242,
    "tgn:name":"Kumai",
    "tgn:placetype":[
        "aat:300008347"
    ]
},
  "bbox": [],
  "geometry": {"coordinates":[112.55,-3.3833],"type":"Point"}
}