{
  "id": 2123122,
  "type": "Feature",
  "properties": {
    "tgn:hierarchy":[
        "tgn:2123122",
        "tgn:1000001",
        "tgn:7012149",
        "tgn:2002383",
        "tgn:7007923",
        "tgn:7029392"
    ],
    "tgn:id":2123122,
    "tgn:name":"Quealy",
    "tgn:placetype":[
        "aat:300008347"
    ]
},
  "bbox": [],
  "geometry": {"coordinates":[-109.2167,41.5333],"type":"Point"}
}