{
  "id": 2215090,
  "type": "Feature",
  "properties": {
    "tgn:hierarchy":[
        "tgn:2215090",
        "tgn:1002141",
        "tgn:1000001",
        "tgn:7012149",
        "tgn:7007568",
        "tgn:7029392"
    ],
    "tgn:id":2215090,
    "tgn:name":"California Hollow",
    "tgn:placetype":[
        "aat:300008761"
    ]
},
  "bbox": [],
  "geometry": {"coordinates":[-78.0667,42.05],"type":"Point"}
}