{
  "id": 2343701,
  "type": "Feature",
  "properties": {
    "tgn:hierarchy":[
        "tgn:2343701",
        "tgn:1000001",
        "tgn:7012149",
        "tgn:1002990",
        "tgn:7007708",
        "tgn:7029392"
    ],
    "tgn:id":2343701,
    "tgn:name":"Gallagher Canyon",
    "tgn:placetype":[
        "aat:300008761"
    ]
},
  "bbox": [],
  "geometry": {"coordinates":[-120.6167,44.8333],"type":"Point"}
}