{
  "id": 2302075,
  "type": "Feature",
  "properties": {
    "tgn:hierarchy":[
        "tgn:2302075",
        "tgn:1000001",
        "tgn:7012149",
        "tgn:2002379",
        "tgn:7007923",
        "tgn:7029392"
    ],
    "tgn:id":2302075,
    "tgn:name":"Dutch Charlie Creek",
    "tgn:placetype":[
        "aat:300008706"
    ]
},
  "bbox": [],
  "geometry": {"coordinates":[-109.4167,44.85],"type":"Point"}
}