{
  "id": 2212962,
  "type": "Feature",
  "properties": {
    "tgn:hierarchy":[
        "tgn:2212962",
        "tgn:1000001",
        "tgn:2001430",
        "tgn:7012149",
        "tgn:7007566",
        "tgn:7029392"
    ],
    "tgn:id":2212962,
    "tgn:name":"CCC Tank",
    "tgn:placetype":[
        "aat:300006191"
    ]
},
  "bbox": [],
  "geometry": {"coordinates":[-104.6167,33.6333],"type":"Point"}
}