{
  "id": 7226630,
  "type": "Feature",
  "properties": {
    "tgn:hierarchy":[
        "tgn:7226630",
        "tgn:7002681",
        "tgn:7001395",
        "tgn:1000003",
        "tgn:1000074",
        "tgn:7029392"
    ],
    "tgn:id":7226630,
    "tgn:name":"Pat\u00edsia",
    "tgn:placetype":[
        "aat:300000745"
    ]
},
  "bbox": [],
  "geometry": {"coordinates":[23.733333,38.033333],"type":"Point"}
}