{
  "id": 2260951,
  "type": "Feature",
  "properties": {
    "tgn:hierarchy":[
        "tgn:2260951",
        "tgn:1000001",
        "tgn:7012149",
        "tgn:2001063",
        "tgn:7007521",
        "tgn:7029392"
    ],
    "tgn:id":2260951,
    "tgn:name":"County Ditch Number Thirtyfive A",
    "tgn:placetype":[
        "aat:300006075"
    ]
},
  "bbox": [],
  "geometry": {"coordinates":[-95.1333,44.75],"type":"Point"}
}