{
  "id": 1015408,
  "type": "Feature",
  "properties": {
    "tgn:hierarchy":[
        "tgn:1015408",
        "tgn:7005685",
        "tgn:1000001",
        "tgn:7005804",
        "tgn:7029392"
    ],
    "tgn:id":1015408,
    "tgn:name":"Ham-Nord",
    "tgn:placetype":[
        "aat:300008347"
    ]
},
  "bbox": [],
  "geometry": {"coordinates":[-71.6167,45.8833],"type":"Point"}
}