{
  "id": 7579696,
  "type": "Feature",
  "properties": {
    "tgn:hierarchy":[
        "tgn:7579696",
        "tgn:1000004",
        "tgn:7000198",
        "tgn:1001894",
        "tgn:7029392"
    ],
    "tgn:id":7579696,
    "tgn:name:en":"Teloli",
    "tgn:placetype":[
        "aat:300008347"
    ]
},
  "bbox": [],
  "geometry": {"coordinates":[81.678894,23.552642],"type":"Point"}
}