{
  "id": 7457123,
  "type": "Feature",
  "properties": {
    "tgn:hierarchy":[
        "tgn:7457123",
        "tgn:7002445",
        "tgn:1000003",
        "tgn:7008129",
        "tgn:7008591",
        "tgn:7029392"
    ],
    "tgn:id":7457123,
    "tgn:name:en":"Pevensey Shoal",
    "tgn:placetype":[
        "aat:300387036"
    ]
},
  "bbox": [],
  "geometry": {"coordinates":[0.433333,50.783333],"type":"Point"}
}