{
  "id": 7299649,
  "type": "Feature",
  "properties": {
    "tgn:hierarchy":[
        "tgn:7299649",
        "tgn:7002820",
        "tgn:7030216",
        "tgn:1000003",
        "tgn:1000095",
        "tgn:7029392"
    ],
    "tgn:id":7299649,
    "tgn:name":"Ultramort",
    "tgn:placetype":[
        "aat:300008347"
    ]
},
  "bbox": [],
  "geometry": {"coordinates":[3.034546,42.036402],"type":"Point"}
}