{
  "id": 7513948,
  "type": "Feature",
  "properties": {
    "tgn:hierarchy":[
        "tgn:7513948",
        "tgn:1009227",
        "tgn:1000226",
        "tgn:7016822",
        "tgn:1000006",
        "tgn:7029392"
    ],
    "tgn:id":7513948,
    "tgn:name:en":"Fannin Bay",
    "tgn:placetype":[
        "aat:300132316"
    ]
},
  "bbox": [],
  "geometry": {"coordinates":[166.466667,-45.816667],"type":"Point"}
}