{
  "id": 7478125,
  "type": "Feature",
  "properties": {
    "tgn:hierarchy":[
        "tgn:7478125",
        "tgn:7487020",
        "tgn:1000004",
        "tgn:1000141",
        "tgn:7029392"
    ],
    "tgn:id":7478125,
    "tgn:name":"Niuhudong",
    "tgn:placetype":[
        "aat:300008777"
    ]
},
  "bbox": [],
  "geometry": {"coordinates":[120.909684,24.659223],"type":"Point"}
}