{
  "id": 2314648,
  "type": "Feature",
  "properties": {
    "tgn:hierarchy":[
        "tgn:2314648",
        "tgn:1000001",
        "tgn:2000602",
        "tgn:7012149",
        "tgn:7007253",
        "tgn:7029392"
    ],
    "tgn:id":2314648,
    "tgn:name":"Elk Run",
    "tgn:placetype":[
        "aat:300008699"
    ]
},
  "bbox": [],
  "geometry": {"coordinates":[-93.3333,42.55],"type":"Point"}
}