{
  "id": 2753013,
  "type": "Feature",
  "properties": {
    "tgn:hierarchy":[
        "tgn:2753013",
        "tgn:1000001",
        "tgn:7006451",
        "tgn:2000092",
        "tgn:7012149",
        "tgn:7029392"
    ],
    "tgn:id":2753013,
    "tgn:name":"Water Haul Tank",
    "tgn:placetype":[
        "aat:300006191"
    ]
},
  "bbox": [],
  "geometry": {"coordinates":[-111.7833,35.3333],"type":"Point"}
}