{
  "id": 7440938,
  "type": "Feature",
  "properties": {
    "tgn:hierarchy":[
        "tgn:7440938",
        "tgn:7005581",
        "tgn:1000001",
        "tgn:7005560",
        "tgn:7029392"
    ],
    "tgn:id":7440938,
    "tgn:name":"Santa Anita",
    "tgn:placetype":[
        "aat:300008347"
    ]
},
  "bbox": [],
  "geometry": {"coordinates":[-107.216667,25.983333],"type":"Point"}
}