{
  "id": 2301623,
  "type": "Feature",
  "properties": {
    "tgn:hierarchy":[
        "tgn:2301623",
        "tgn:1000001",
        "tgn:2001416",
        "tgn:7012149",
        "tgn:7007526",
        "tgn:7029392"
    ],
    "tgn:id":2301623,
    "tgn:name":"Dupont Spring",
    "tgn:placetype":[
        "aat:300008697"
    ]
},
  "bbox": [],
  "geometry": {"coordinates":[-114.6833,38.65],"type":"Point"}
}