{
  "id": 7125696,
  "type": "Feature",
  "properties": {
    "tgn:hierarchy":[
        "tgn:7125696",
        "tgn:7003669",
        "tgn:1000003",
        "tgn:7000084",
        "tgn:7029392"
    ],
    "tgn:id":7125696,
    "tgn:name":"Obere Filze",
    "tgn:placetype":[
        "aat:300386886"
    ]
},
  "bbox": [],
  "geometry": {"coordinates":[12.083333,47.866667],"type":"Point"}
}