{
  "id": 2352201,
  "type": "Feature",
  "properties": {
    "tgn:hierarchy":[
        "tgn:2352201",
        "tgn:1000001",
        "tgn:7012149",
        "tgn:2000354",
        "tgn:7007248",
        "tgn:7029392"
    ],
    "tgn:id":2352201,
    "tgn:name":"Glynn, Marshes of",
    "tgn:placetype":[
        "aat:300008905"
    ]
},
  "bbox": [],
  "geometry": {"coordinates":[-81.45,31.1333],"type":"Point"}
}