{
  "id": 7228412,
  "type": "Feature",
  "properties": {
    "tgn:hierarchy":[
        "tgn:7228412",
        "tgn:7002752",
        "tgn:7001399",
        "tgn:1000003",
        "tgn:1000074",
        "tgn:7029392"
    ],
    "tgn:id":7228412,
    "tgn:name":"Kastani\u00e1",
    "tgn:placetype":[
        "aat:300266640"
    ]
},
  "bbox": [],
  "geometry": {"coordinates":[21.562222,39.484444],"type":"Point"}
}