{
  "id": 2465600,
  "type": "Feature",
  "properties": {
    "tgn:hierarchy":[
        "tgn:2465600",
        "tgn:1000001",
        "tgn:2000873",
        "tgn:7012149",
        "tgn:7007256",
        "tgn:7029392"
    ],
    "tgn:id":2465600,
    "tgn:name":"Lone Pine",
    "tgn:placetype":[
        "aat:300008347"
    ]
},
  "bbox": [],
  "geometry": {"coordinates":[-92.3167,30.95],"type":"Point"}
}