{
  "id": 7349279,
  "type": "Feature",
  "properties": {
    "tgn:hierarchy":[
        "tgn:7349279",
        "tgn:7005581",
        "tgn:1000001",
        "tgn:7005560",
        "tgn:7029392"
    ],
    "tgn:id":7349279,
    "tgn:name":"Almirez, Sierra",
    "tgn:placetype":[
        "aat:300266640"
    ]
},
  "bbox": [],
  "geometry": {"coordinates":[-106.783333,30.866667],"type":"Point"}
}