{
  "id": 2381935,
  "type": "Feature",
  "properties": {
    "tgn:hierarchy":[
        "tgn:2381935",
        "tgn:1000001",
        "tgn:7012149",
        "tgn:7007157",
        "tgn:7014475",
        "tgn:7029392"
    ],
    "tgn:id":2381935,
    "tgn:name":"Hayes Creek",
    "tgn:placetype":[
        "aat:300008706"
    ]
},
  "bbox": [],
  "geometry": {"coordinates":[-121.65,37.0667],"type":"Point"}
}