{
  "id": 2432542,
  "type": "Feature",
  "properties": {
    "tgn:hierarchy":[
        "tgn:2432542",
        "tgn:1000001",
        "tgn:7012149",
        "tgn:2001926",
        "tgn:7007825",
        "tgn:7029392"
    ],
    "tgn:id":2432542,
    "tgn:name":"Keebler Crossroads",
    "tgn:placetype":[
        "aat:300008347"
    ]
},
  "bbox": [],
  "geometry": {"coordinates":[-82.4667,36.35],"type":"Point"}
}