{
  "id": 2301525,
  "type": "Feature",
  "properties": {
    "tgn:hierarchy":[
        "tgn:2301525",
        "tgn:1000001",
        "tgn:7012149",
        "tgn:7013855",
        "tgn:7007251",
        "tgn:7029392"
    ],
    "tgn:id":2301525,
    "tgn:name":"Dunns Lake",
    "tgn:placetype":[
        "aat:300008680"
    ]
},
  "bbox": [],
  "geometry": {"coordinates":[-88.1833,42.4167],"type":"Point"}
}