{
  "id": 7404293,
  "type": "Feature",
  "properties": {
    "tgn:hierarchy":[
        "tgn:7404293",
        "tgn:7016644",
        "tgn:1000001",
        "tgn:7005560",
        "tgn:7029392"
    ],
    "tgn:id":7404293,
    "tgn:name":"Cofrad\u00eda de Morelos",
    "tgn:placetype":[
        "aat:300008347"
    ]
},
  "bbox": [],
  "geometry": {"coordinates":[-103.8375,18.869444],"type":"Point"}
}