{
  "id": 1030583,
  "type": "Feature",
  "properties": {
    "tgn:hierarchy":[
        "tgn:1030583",
        "tgn:7002445",
        "tgn:7008103",
        "tgn:1000003",
        "tgn:7008591",
        "tgn:7029392"
    ],
    "tgn:id":1030583,
    "tgn:name":"Sharnbrook",
    "tgn:placetype":[
        "aat:300008347"
    ]
},
  "bbox": [],
  "geometry": {"coordinates":[-0.533333,52.216667],"type":"Point"}
}