<<<<<<< HEAD
{
  "id": 2253438,
  "type": "Feature",
  "properties": {
    "tgn:hierarchy":[
        "tgn:2253438",
        "tgn:2000919",
        "tgn:1000001",
        "tgn:7012149",
        "tgn:7007515",
        "tgn:7029392"
    ],
    "tgn:id":2253438,
    "tgn:name":"Cook Brook",
    "tgn:placetype":[
        "aat:300008699"
    ]
},
  "bbox": [],
  "geometry": {"coordinates":[-67.8167,46.1333],"type":"Point"}
}
=======
{"geometry":{"type":"Point","coordinates":[-67.816700,46.133300]},"type":"Feature","properties":{"hierarchy":["tgn:2253438","tgn:2000919","tgn:1000001","tgn:7012149","tgn:7007515","tgn:7029392"],"placetype":["aat:300008699"],"id":2253438,"name:xx":"Cook Brook"}}
>>>>>>> 03f74aca74312dbeaf24d7e61306dd6a786dc3d0
