{
  "id": 2582891,
  "type": "Feature",
  "properties": {
    "tgn:hierarchy":[
        "tgn:2582891",
        "tgn:1000001",
        "tgn:1002480",
        "tgn:7012149",
        "tgn:7007564",
        "tgn:7029392"
    ],
    "tgn:id":2582891,
    "tgn:name":"Pine Island Pond",
    "tgn:placetype":[
        "aat:300006191"
    ]
},
  "bbox": [],
  "geometry": {"coordinates":[-71.45,42.9167],"type":"Point"}
}