{
  "id": 7592098,
  "type": "Feature",
  "properties": {
    "tgn:hierarchy":[
        "tgn:7592098",
        "tgn:1000004",
        "tgn:7000198",
        "tgn:7031786",
        "tgn:7029392"
    ],
    "tgn:id":7592098,
    "tgn:name:en":"K\u0101l\u016bw\u0101la Reserved Forest",
    "tgn:placetype":[
        "aat:300008863"
    ]
},
  "bbox": [],
  "geometry": {"coordinates":[77.861165,30.241391],"type":"Point"}
}