{
  "id": 2056008,
  "type": "Feature",
  "properties": {
    "tgn:hierarchy":[
        "tgn:2056008",
        "tgn:1000001",
        "tgn:7012149",
        "tgn:2001144",
        "tgn:7007522",
        "tgn:7029392"
    ],
    "tgn:id":2056008,
    "tgn:name":"Booneville",
    "tgn:placetype":[
        "aat:300008347",
        "aat:300008416"
    ]
},
  "bbox": [],
  "geometry": {"coordinates":[-88.5667,34.65],"type":"Point"}
}