{
  "id": 2334370,
  "type": "Feature",
  "properties": {
    "tgn:hierarchy":[
        "tgn:2334370",
        "tgn:1000001",
        "tgn:2001418",
        "tgn:7012149",
        "tgn:7007526",
        "tgn:7029392"
    ],
    "tgn:id":2334370,
    "tgn:name":"Forest Home Reservoir Number 5",
    "tgn:placetype":[
        "aat:300006191"
    ]
},
  "bbox": [],
  "geometry": {"coordinates":[-115.2667,38.3667],"type":"Point"}
}