<<<<<<< HEAD
{
  "id": 2334370,
  "type": "Feature",
  "properties": {
    "tgn:hierarchy":[
        "tgn:2334370",
        "tgn:1000001",
        "tgn:2001418",
        "tgn:7012149",
        "tgn:7007526",
        "tgn:7029392"
    ],
    "tgn:id":2334370,
    "tgn:name":"Forest Home Reservoir Number 5",
    "tgn:placetype":[
        "aat:300006191"
    ]
},
  "bbox": [],
  "geometry": {"coordinates":[-115.2667,38.3667],"type":"Point"}
}
=======
{"geometry":{"type":"Point","coordinates":[-115.266700,38.366700]},"type":"Feature","properties":{"hierarchy":["tgn:2334370","tgn:1000001","tgn:2001418","tgn:7012149","tgn:7007526","tgn:7029392"],"placetype":["aat:300006191"],"id":2334370,"name:xx":"Forest Home Reservoir Number 5"}}
>>>>>>> 03f74aca74312dbeaf24d7e61306dd6a786dc3d0
