{
  "id": 1122422,
  "type": "Feature",
  "properties": {
    "tgn:hierarchy":[
        "tgn:1122422",
        "tgn:7003005",
        "tgn:7003014",
        "tgn:1000003",
        "tgn:1000080",
        "tgn:7029392"
    ],
    "tgn:id":1122422,
    "tgn:name":"Calore",
    "tgn:placetype":[
        "aat:300008707",
        "aat:300008699"
    ]
},
  "bbox": [],
  "geometry": {"coordinates":[15.016667,40.516667],"type":"Point"}
}