{
  "id": 1005145,
  "type": "Feature",
  "properties": {
    "tgn:hierarchy":[
        "tgn:1005145",
        "tgn:1001052",
        "tgn:1000004",
        "tgn:7002664",
        "tgn:7018450",
        "tgn:1000144",
        "tgn:7029392"
    ],
    "tgn:id":1005145,
    "tgn:name":"Nizam",
    "tgn:placetype":[
        "aat:300000745"
    ]
},
  "bbox": [],
  "geometry": {"coordinates":[29.1167,40.8667],"type":"Point"}
}