{
  "id": 7504817,
  "type": "Feature",
  "properties": {
    "tgn:hierarchy":[
        "tgn:7504817",
        "tgn:1009227",
        "tgn:1000226",
        "tgn:7016729",
        "tgn:1000006",
        "tgn:7029392"
    ],
    "tgn:id":7504817,
    "tgn:name:en":"Maori Pa Beach",
    "tgn:placetype":[
        "aat:300008816"
    ]
},
  "bbox": [],
  "geometry": {"coordinates":[173.447222,-41.162222],"type":"Point"}
}