{
  "id": 2554970,
  "type": "Feature",
  "properties": {
    "tgn:hierarchy":[
        "tgn:2554970",
        "tgn:1000001",
        "tgn:7012149",
        "tgn:2001714",
        "tgn:7007708",
        "tgn:7029392"
    ],
    "tgn:id":2554970,
    "tgn:name":"Oberman Reservoir",
    "tgn:placetype":[
        "aat:300006191"
    ]
},
  "bbox": [],
  "geometry": {"coordinates":[-121.6333,42.35],"type":"Point"}
}