{
  "id": 7389993,
  "type": "Feature",
  "properties": {
    "tgn:hierarchy":[
        "tgn:7389993",
        "tgn:1000001",
        "tgn:1001960",
        "tgn:7005560",
        "tgn:7029392"
    ],
    "tgn:id":7389993,
    "tgn:name":"Rancho Flores Mu\u00f1oz",
    "tgn:placetype":[
        "aat:300008347"
    ]
},
  "bbox": [],
  "geometry": {"coordinates":[-111.666667,28.633333],"type":"Point"}
}