{
  "id": 7049162,
  "type": "Feature",
  "properties": {
    "tgn:hierarchy":[
        "tgn:7049162",
        "tgn:1003450",
        "tgn:7007850",
        "tgn:1000003",
        "tgn:1000080",
        "tgn:7029392"
    ],
    "tgn:id":7049162,
    "tgn:name":"Dipignano",
    "tgn:placetype":[
        "aat:300387198"
    ]
},
  "bbox": [],
  "geometry": {"coordinates":[16.25,39.25],"type":"Point"}
}