{
  "id": 2211805,
  "type": "Feature",
  "properties": {
    "tgn:hierarchy":[
        "tgn:2211805",
        "tgn:1000001",
        "tgn:7012149",
        "tgn:1002999",
        "tgn:7007526",
        "tgn:7029392"
    ],
    "tgn:id":2211805,
    "tgn:name":"Button Mountain",
    "tgn:placetype":[
        "aat:300008798"
    ]
},
  "bbox": [],
  "geometry": {"coordinates":[-119.65,40.75],"type":"Point"}
}