{
  "id": 7171534,
  "type": "Feature",
  "properties": {
    "tgn:hierarchy":[
        "tgn:7171534",
        "tgn:7003669",
        "tgn:1000003",
        "tgn:7000084",
        "tgn:7029392"
    ],
    "tgn:id":7171534,
    "tgn:name":"Hirschberg",
    "tgn:placetype":[
        "aat:300008777"
    ]
},
  "bbox": [],
  "geometry": {"coordinates":[9.483333,49.983333],"type":"Point"}
}