{
  "id": 2276862,
  "type": "Feature",
  "properties": {
    "tgn:hierarchy":[
        "tgn:2276862",
        "tgn:1000001",
        "tgn:7012149",
        "tgn:2001235",
        "tgn:7007523",
        "tgn:7029392"
    ],
    "tgn:id":2276862,
    "tgn:name":"Davis Branch",
    "tgn:placetype":[
        "aat:300008699"
    ]
},
  "bbox": [],
  "geometry": {"coordinates":[-94.05,39.4833],"type":"Point"}
}