{
  "id": 7124132,
  "type": "Feature",
  "properties": {
    "tgn:hierarchy":[
        "tgn:7124132",
        "tgn:7003669",
        "tgn:1000003",
        "tgn:7000084",
        "tgn:7029392"
    ],
    "tgn:id":7124132,
    "tgn:name":"Neuricht",
    "tgn:placetype":[
        "aat:300008347"
    ]
},
  "bbox": [],
  "geometry": {"coordinates":[11.366667,49.25],"type":"Point"}
}