{
  "id": 1092902,
  "type": "Feature",
  "properties": {
    "tgn:hierarchy":[
        "tgn:1092902",
        "tgn:7001242",
        "tgn:7017582",
        "tgn:1000193",
        "tgn:7029392"
    ],
    "tgn:id":1092902,
    "tgn:name":"Boomrivier",
    "tgn:placetype":[
        "aat:300008347"
    ]
},
  "bbox": [],
  "geometry": {"coordinates":[20.45,-29.55],"type":"Point"}
}