{
  "id": 2726817,
  "type": "Feature",
  "properties": {
    "tgn:hierarchy":[
        "tgn:2726817",
        "tgn:1000001",
        "tgn:2001173",
        "tgn:7012149",
        "tgn:7007523",
        "tgn:7029392"
    ],
    "tgn:id":2726817,
    "tgn:name":"Townes Hollow",
    "tgn:placetype":[
        "aat:300008761"
    ]
},
  "bbox": [],
  "geometry": {"coordinates":[-93.2833,38.25],"type":"Point"}
}