{
  "id": 7229171,
  "type": "Feature",
  "properties": {
    "tgn:hierarchy":[
        "tgn:7229171",
        "tgn:7002748",
        "tgn:7001399",
        "tgn:1000003",
        "tgn:1000074",
        "tgn:7029392"
    ],
    "tgn:id":7229171,
    "tgn:name":"Karditsomago\u00fala",
    "tgn:placetype":[
        "aat:300008347"
    ]
},
  "bbox": [],
  "geometry": {"coordinates":[21.924167,39.391944],"type":"Point"}
}