{
  "id": 2160554,
  "type": "Feature",
  "properties": {
    "tgn:hierarchy":[
        "tgn:2160554",
        "tgn:1000001",
        "tgn:7012149",
        "tgn:2001851",
        "tgn:7007825",
        "tgn:7029392"
    ],
    "tgn:id":2160554,
    "tgn:name":"Beetree Hollow",
    "tgn:placetype":[
        "aat:300008761"
    ]
},
  "bbox": [],
  "geometry": {"coordinates":[-82.95,35.9333],"type":"Point"}
}