{
  "id": 7468842,
  "type": "Feature",
  "properties": {
    "tgn:hierarchy":[
        "tgn:7468842",
        "tgn:1000004",
        "tgn:7467799",
        "tgn:1000141",
        "tgn:7029392"
    ],
    "tgn:id":7468842,
    "tgn:name":"Xialiao",
    "tgn:placetype":[
        "aat:300008347"
    ]
},
  "bbox": [],
  "geometry": {"coordinates":[120.5515,23.821547],"type":"Point"}
}