{
  "id": 7585455,
  "type": "Feature",
  "properties": {
    "tgn:hierarchy":[
        "tgn:7585455",
        "tgn:1000004",
        "tgn:7000198",
        "tgn:7016722",
        "tgn:7029392"
    ],
    "tgn:id":7585455,
    "tgn:name:en":"Majhgaw\u0101n",
    "tgn:placetype":[
        "aat:300008347"
    ]
},
  "bbox": [],
  "geometry": {"coordinates":[78.448911,24.89557],"type":"Point"}
}