{
  "id": 7285573,
  "type": "Feature",
  "properties": {
    "tgn:hierarchy":[
        "tgn:7285573",
        "tgn:1001702",
        "tgn:1000049",
        "tgn:1000002",
        "tgn:7029392"
    ],
    "tgn:id":7285573,
    "tgn:name":"Playa Parda, Caleta",
    "tgn:placetype":[
        "aat:300132317"
    ]
},
  "bbox": [],
  "geometry": {"coordinates":[-73.033333,-53.316667],"type":"Point"}
}