{
  "id": 2351545,
  "type": "Feature",
  "properties": {
    "tgn:hierarchy":[
        "tgn:2351545",
        "tgn:1000001",
        "tgn:7012149",
        "tgn:2002303",
        "tgn:7013961",
        "tgn:7029392"
    ],
    "tgn:id":2351545,
    "tgn:name":"Glenbrook",
    "tgn:placetype":[
        "aat:300008347"
    ]
},
  "bbox": [],
  "geometry": {"coordinates":[-81.5167,39.3333],"type":"Point"}
}