<<<<<<< HEAD
{
  "id": 2767613,
  "type": "Feature",
  "properties": {
    "tgn:hierarchy":[
        "tgn:2767613",
        "tgn:1000001",
        "tgn:7012149",
        "tgn:2001307",
        "tgn:7007524",
        "tgn:7029392"
    ],
    "tgn:id":2767613,
    "tgn:name":"Whitebird Ditch",
    "tgn:placetype":[
        "aat:300006075"
    ]
},
  "bbox": [],
  "geometry": {"coordinates":[-109.3333,45.55],"type":"Point"}
}
=======
{"geometry":{"type":"Point","coordinates":[-109.333300,45.550000]},"type":"Feature","properties":{"hierarchy":["tgn:2767613","tgn:1000001","tgn:7012149","tgn:2001307","tgn:7007524","tgn:7029392"],"placetype":["aat:300006075"],"id":2767613,"name:xx":"Whitebird Ditch"}}
>>>>>>> 03f74aca74312dbeaf24d7e61306dd6a786dc3d0
