<<<<<<< HEAD
{
  "id": 7050148,
  "type": "Feature",
  "properties": {
    "tgn:hierarchy":[
        "tgn:7050148",
        "tgn:1003444",
        "tgn:1000003",
        "tgn:7003241",
        "tgn:1000080",
        "tgn:7029392"
    ],
    "tgn:id":7050148,
    "tgn:name":"Lauri, Valle",
    "tgn:placetype":[
        "aat:300008761"
    ]
},
  "bbox": [],
  "geometry": {"coordinates":[14.85,41.5],"type":"Point"}
}
=======
{"geometry":{"type":"Point","coordinates":[14.850000,41.500000]},"type":"Feature","properties":{"hierarchy":["tgn:7050148","tgn:1003444","tgn:1000003","tgn:7003241","tgn:1000080","tgn:7029392"],"placetype":["aat:300008761"],"id":7050148,"name:xx":"Lauri, Valle"}}
>>>>>>> 03f74aca74312dbeaf24d7e61306dd6a786dc3d0
