{
  "id": 7223912,
  "type": "Feature",
  "properties": {
    "tgn:hierarchy":[
        "tgn:7223912",
        "tgn:7002681",
        "tgn:7001395",
        "tgn:1000003",
        "tgn:1000074",
        "tgn:7029392"
    ],
    "tgn:id":7223912,
    "tgn:name":"Thermis\u00eda, L\u00edmni",
    "tgn:placetype":[
        "aat:300008679"
    ]
},
  "bbox": [],
  "geometry": {"coordinates":[23.30688,37.406071],"type":"Point"}
}