{
  "id": 7175038,
  "type": "Feature",
  "properties": {
    "tgn:hierarchy":[
        "tgn:7175038",
        "tgn:1000003",
        "tgn:7003687",
        "tgn:7000084",
        "tgn:7029392"
    ],
    "tgn:id":7175038,
    "tgn:name":"Gro\u00dfer Fallstein",
    "tgn:placetype":[
        "aat:300008777"
    ]
},
  "bbox": [],
  "geometry": {"coordinates":[10.716667,52.016667],"type":"Point"}
}