{
  "id": 2458557,
  "type": "Feature",
  "properties": {
    "tgn:hierarchy":[
        "tgn:2458557",
        "tgn:1000001",
        "tgn:7012149",
        "tgn:2002374",
        "tgn:7007923",
        "tgn:7029392"
    ],
    "tgn:id":2458557,
    "tgn:name":"Little North Fork",
    "tgn:placetype":[
        "aat:300008699"
    ]
},
  "bbox": [],
  "geometry": {"coordinates":[-106.85,44.4667],"type":"Point"}
}