{
  "id": 7421914,
  "type": "Feature",
  "properties": {
    "tgn:hierarchy":[
        "tgn:7421914",
        "tgn:1000001",
        "tgn:7005597",
        "tgn:7005560",
        "tgn:7029392"
    ],
    "tgn:id":7421914,
    "tgn:name":"Bordo Presa Grande",
    "tgn:placetype":[
        "aat:300006191"
    ]
},
  "bbox": [],
  "geometry": {"coordinates":[-99.733333,26.933333],"type":"Point"}
}