{
  "id": 2534418,
  "type": "Feature",
  "properties": {
    "tgn:hierarchy":[
        "tgn:2534418",
        "tgn:1000001",
        "tgn:7012149",
        "tgn:2001281",
        "tgn:7007524",
        "tgn:7029392"
    ],
    "tgn:id":2534418,
    "tgn:name":"NE SE Section 13 Mine",
    "tgn:placetype":[
        "aat:300000390"
    ]
},
  "bbox": [],
  "geometry": {"coordinates":[-112.2833,46.8333],"type":"Point"}
}