{
  "id": 2288737,
  "type": "Feature",
  "properties": {
    "tgn:hierarchy":[
        "tgn:2288737",
        "tgn:1000001",
        "tgn:2000592",
        "tgn:7012149",
        "tgn:7007253",
        "tgn:7029392"
    ],
    "tgn:id":2288737,
    "tgn:name":"Ditch Number 151",
    "tgn:placetype":[
        "aat:300006075"
    ]
},
  "bbox": [],
  "geometry": {"coordinates":[-94.8167,43.3333],"type":"Point"}
}