{
  "id": 2170537,
  "type": "Feature",
  "properties": {
    "tgn:hierarchy":[
        "tgn:2170537",
        "tgn:1000001",
        "tgn:7012149",
        "tgn:1002701",
        "tgn:7007706",
        "tgn:7029392"
    ],
    "tgn:id":2170537,
    "tgn:name":"Big Run",
    "tgn:placetype":[
        "aat:300008699"
    ]
},
  "bbox": [],
  "geometry": {"coordinates":[-82.0333,40.1167],"type":"Point"}
}