{
  "id": 7008072,
  "type": "Feature",
  "properties": {
    "tgn:hierarchy":[
        "tgn:7008072",
        "tgn:7002444",
        "tgn:1000003",
        "tgn:7008591",
        "tgn:7029392"
    ],
    "tgn:id":7008072,
    "tgn:name":"Scottish Borders",
    "tgn:placetype":[
        "aat:300008631",
        "aat:300387064",
        "aat:300387145",
        "aat:300236112",
        "aat:300387071"
    ]
},
  "bbox": [],
  "geometry": {"coordinates":[-3.25,55.5833],"type":"Point"}
}