{
  "id": 2654356,
  "type": "Feature",
  "properties": {
    "tgn:hierarchy":[
        "tgn:2654356",
        "tgn:1000001",
        "tgn:7012149",
        "tgn:2000787",
        "tgn:7007255",
        "tgn:7029392"
    ],
    "tgn:id":2654356,
    "tgn:name":"Shady Lake",
    "tgn:placetype":[
        "aat:300008680"
    ]
},
  "bbox": [],
  "geometry": {"coordinates":[-86.2667,37.2667],"type":"Point"}
}