<<<<<<< HEAD
{
  "id": 2159930,
  "type": "Feature",
  "properties": {
    "tgn:hierarchy":[
        "tgn:2159930",
        "tgn:1000001",
        "tgn:1002359",
        "tgn:7012149",
        "tgn:7007517",
        "tgn:7029392"
    ],
    "tgn:id":2159930,
    "tgn:name":"Beech Hill",
    "tgn:placetype":[
        "aat:300008798"
    ]
},
  "bbox": [],
  "geometry": {"coordinates":[-70.9167,42.8667],"type":"Point"}
}
=======
{"geometry":{"type":"Point","coordinates":[-70.916700,42.866700]},"type":"Feature","properties":{"hierarchy":["tgn:2159930","tgn:1000001","tgn:1002359","tgn:7012149","tgn:7007517","tgn:7029392"],"placetype":["aat:300008798"],"id":2159930,"name:xx":"Beech Hill"}}
>>>>>>> 03f74aca74312dbeaf24d7e61306dd6a786dc3d0
