<<<<<<< HEAD
{
  "id": 7248480,
  "type": "Feature",
  "properties": {
    "tgn:hierarchy":[
        "tgn:7248480",
        "tgn:7018239",
        "tgn:1000003",
        "tgn:1000063",
        "tgn:7018236",
        "tgn:7029392"
    ],
    "tgn:id":7248480,
    "tgn:name":"Beversluis",
    "tgn:placetype":[
        "aat:300008347"
    ]
},
  "bbox": [],
  "geometry": {"coordinates":[4.733333,50.95],"type":"Point"}
}
=======
{"geometry":{"type":"Point","coordinates":[4.733333,50.950000]},"type":"Feature","properties":{"hierarchy":["tgn:7248480","tgn:7018239","tgn:1000003","tgn:1000063","tgn:7018236","tgn:7029392"],"placetype":["aat:300008347"],"id":7248480,"name:xx":"Beversluis"}}
>>>>>>> 03f74aca74312dbeaf24d7e61306dd6a786dc3d0
