{
  "id": 7197111,
  "type": "Feature",
  "properties": {
    "tgn:hierarchy":[
        "tgn:7197111",
        "tgn:1000003",
        "tgn:7003678",
        "tgn:7000084",
        "tgn:7029392"
    ],
    "tgn:id":7197111,
    "tgn:name":"Dommel",
    "tgn:placetype":[
        "aat:300008795"
    ]
},
  "bbox": [],
  "geometry": {"coordinates":[8.683333,51.333333],"type":"Point"}
}