{
  "id": 7259389,
  "type": "Feature",
  "properties": {
    "tgn:hierarchy":[
        "tgn:7259389",
        "tgn:7003458",
        "tgn:1000003",
        "tgn:1000063",
        "tgn:7018236",
        "tgn:7029392"
    ],
    "tgn:id":7259389,
    "tgn:name":"Vuilpan",
    "tgn:placetype":[
        "aat:300008347"
    ]
},
  "bbox": [],
  "geometry": {"coordinates":[2.994835,50.991997],"type":"Point"}
}