{
  "id": 1092447,
  "type": "Feature",
  "properties": {
    "tgn:hierarchy":[
        "tgn:1092447",
        "tgn:7001242",
        "tgn:1001412",
        "tgn:1000185",
        "tgn:7029392"
    ],
    "tgn:id":1092447,
    "tgn:name":"Sakubva",
    "tgn:placetype":[
        "aat:300008347"
    ]
},
  "bbox": [],
  "geometry": {"coordinates":[32.6167,-18.9833],"type":"Point"}
}