{
  "id": 7125928,
  "type": "Feature",
  "properties": {
    "tgn:hierarchy":[
        "tgn:7125928",
        "tgn:7003692",
        "tgn:1000003",
        "tgn:7000084",
        "tgn:7029392"
    ],
    "tgn:id":7125928,
    "tgn:name":"Oberdorf",
    "tgn:placetype":[
        "aat:300008347"
    ]
},
  "bbox": [],
  "geometry": {"coordinates":[10.35,48.866667],"type":"Point"}
}