{
  "id": 7112598,
  "type": "Feature",
  "properties": {
    "tgn:hierarchy":[
        "tgn:7112598",
        "tgn:7003669",
        "tgn:1000003",
        "tgn:7000084",
        "tgn:7029392"
    ],
    "tgn:id":7112598,
    "tgn:name":"Rhaner Berg",
    "tgn:placetype":[
        "aat:300266640"
    ]
},
  "bbox": [],
  "geometry": {"coordinates":[12.616667,49.316667],"type":"Point"}
}