{
  "id": 7322518,
  "type": "Feature",
  "properties": {
    "tgn:hierarchy":[
        "tgn:7322518",
        "tgn:7002759",
        "tgn:7002845",
        "tgn:1000003",
        "tgn:1000095",
        "tgn:7029392"
    ],
    "tgn:id":7322518,
    "tgn:name":"San Juan de Mozarrifar",
    "tgn:placetype":[
        "aat:300008347"
    ]
},
  "bbox": [],
  "geometry": {"coordinates":[-0.833333,41.716667],"type":"Point"}
}