{
  "id": 7547450,
  "type": "Feature",
  "properties": {
    "tgn:hierarchy":[
        "tgn:7547450",
        "tgn:1000004",
        "tgn:7000198",
        "tgn:7016722",
        "tgn:7029392"
    ],
    "tgn:id":7547450,
    "tgn:name:en":"Agra Canal",
    "tgn:placetype":[
        "aat:300006075"
    ]
},
  "bbox": [],
  "geometry": {"coordinates":[77.364016,28.136966],"type":"Point"}
}