{
  "id": 7483438,
  "type": "Feature",
  "properties": {
    "tgn:hierarchy":[
        "tgn:7483438",
        "tgn:1000004",
        "tgn:7471332",
        "tgn:1000141",
        "tgn:7029392"
    ],
    "tgn:id":7483438,
    "tgn:name":"Niugu Ling",
    "tgn:placetype":[
        "aat:300387033"
    ]
},
  "bbox": [],
  "geometry": {"coordinates":[120.976667,24.869167],"type":"Point"}
}