<<<<<<< HEAD
{
  "id": 7483438,
  "type": "Feature",
  "properties": {
    "tgn:hierarchy":[
        "tgn:7483438",
        "tgn:1000004",
        "tgn:7471332",
        "tgn:1000141",
        "tgn:7029392"
    ],
    "tgn:id":7483438,
    "tgn:name":"Niugu Ling",
    "tgn:placetype":[
        "aat:300387033"
    ]
},
  "bbox": [],
  "geometry": {"coordinates":[120.976667,24.869167],"type":"Point"}
}
=======
{"geometry":{"type":"Point","coordinates":[120.976667,24.869167]},"type":"Feature","properties":{"hierarchy":["tgn:7483438","tgn:1000004","tgn:7471332","tgn:1000141","tgn:7029392"],"placetype":["aat:300387033"],"id":7483438,"name:xx":"Niugu Ling"}}
>>>>>>> 03f74aca74312dbeaf24d7e61306dd6a786dc3d0
