{
  "id": 7158028,
  "type": "Feature",
  "properties": {
    "tgn:hierarchy":[
        "tgn:7158028",
        "tgn:1000003",
        "tgn:7003689",
        "tgn:7000084",
        "tgn:7029392"
    ],
    "tgn:id":7158028,
    "tgn:name":"Kiefen-Berg",
    "tgn:placetype":[
        "aat:300008777"
    ]
},
  "bbox": [],
  "geometry": {"coordinates":[11.816667,51.033333],"type":"Point"}
}