{
  "id": 7428382,
  "type": "Feature",
  "properties": {
    "tgn:hierarchy":[
        "tgn:7428382",
        "tgn:7005581",
        "tgn:1000001",
        "tgn:7005560",
        "tgn:7029392"
    ],
    "tgn:id":7428382,
    "tgn:name":"Trinidad",
    "tgn:placetype":[
        "aat:300008347"
    ]
},
  "bbox": [],
  "geometry": {"coordinates":[-105.166667,27.183333],"type":"Point"}
}