{
  "id": 7288645,
  "type": "Feature",
  "properties": {
    "tgn:hierarchy":[
        "tgn:7288645",
        "tgn:1001699",
        "tgn:1000049",
        "tgn:1000002",
        "tgn:7029392"
    ],
    "tgn:id":7288645,
    "tgn:name":"Huidif",
    "tgn:placetype":[
        "aat:300004792"
    ]
},
  "bbox": [],
  "geometry": {"coordinates":[-72.516667,-39.833333],"type":"Point"}
}