{
  "id": 2686835,
  "type": "Feature",
  "properties": {
    "tgn:hierarchy":[
        "tgn:2686835",
        "tgn:2000195",
        "tgn:1000001",
        "tgn:7012149",
        "tgn:7007158",
        "tgn:7029392"
    ],
    "tgn:id":2686835,
    "tgn:name":"Spring Creek Reservoir",
    "tgn:placetype":[
        "aat:300006191"
    ]
},
  "bbox": [],
  "geometry": {"coordinates":[-107.1167,37.3833],"type":"Point"}
}