{
  "id": 7486944,
  "type": "Feature",
  "properties": {
    "tgn:hierarchy":[
        "tgn:7486944",
        "tgn:1000004",
        "tgn:7004300",
        "tgn:1000141",
        "tgn:7029392"
    ],
    "tgn:id":7486944,
    "tgn:name":"Baisha Xiang",
    "tgn:placetype":[
        "aat:300387173"
    ]
},
  "bbox": [],
  "geometry": {"coordinates":[119.583333,23.666667],"type":"Point"}
}