<<<<<<< HEAD
{
  "id": 7486944,
  "type": "Feature",
  "properties": {
    "tgn:hierarchy":[
        "tgn:7486944",
        "tgn:1000004",
        "tgn:7004300",
        "tgn:1000141",
        "tgn:7029392"
    ],
    "tgn:id":7486944,
    "tgn:name":"Baisha Xiang",
    "tgn:placetype":[
        "aat:300387173"
    ]
},
  "bbox": [],
  "geometry": {"coordinates":[119.583333,23.666667],"type":"Point"}
}
=======
{"geometry":{"type":"Point","coordinates":[119.583333,23.666667]},"type":"Feature","properties":{"hierarchy":["tgn:7486944","tgn:1000004","tgn:7004300","tgn:1000141","tgn:7029392"],"placetype":["aat:300387173"],"id":7486944,"name:xx":"Baisha Xiang"}}
>>>>>>> 03f74aca74312dbeaf24d7e61306dd6a786dc3d0
