{
  "id": 2526522,
  "type": "Feature",
  "properties": {
    "tgn:hierarchy":[
        "tgn:2526522",
        "tgn:2000942",
        "tgn:1000001",
        "tgn:7012149",
        "tgn:7007520",
        "tgn:7029392"
    ],
    "tgn:id":2526522,
    "tgn:name":"Mossy Bog",
    "tgn:placetype":[
        "aat:300008905"
    ]
},
  "bbox": [],
  "geometry": {"coordinates":[-83.6667,44.6333],"type":"Point"}
}