{
  "id": 2487896,
  "type": "Feature",
  "properties": {
    "tgn:hierarchy":[
        "tgn:2487896",
        "tgn:1000001",
        "tgn:2000782",
        "tgn:7012149",
        "tgn:7007255",
        "tgn:7029392"
    ],
    "tgn:id":2487896,
    "tgn:name":"Left Fork Upper Bear Creek",
    "tgn:placetype":[
        "aat:300008706"
    ]
},
  "bbox": [],
  "geometry": {"coordinates":[-83.5833,36.9833],"type":"Point"}
}