{
  "id": 1024559,
  "type": "Feature",
  "properties": {
    "tgn:hierarchy":[
        "tgn:1024559",
        "tgn:1000675",
        "tgn:1000002",
        "tgn:1000056",
        "tgn:7029392"
    ],
    "tgn:id":1024559,
    "tgn:name":"Jeberos",
    "tgn:placetype":[
        "aat:300008347"
    ]
},
  "bbox": [],
  "geometry": {"coordinates":[-76.2833,-5.2833],"type":"Point"}
}