{
  "id": 7295720,
  "type": "Feature",
  "properties": {
    "tgn:hierarchy":[
        "tgn:7295720",
        "tgn:7002806",
        "tgn:7001158",
        "tgn:1000003",
        "tgn:1000095",
        "tgn:7029392"
    ],
    "tgn:id":7295720,
    "tgn:name":"Villanueva del Aceral",
    "tgn:placetype":[
        "aat:300008347"
    ]
},
  "bbox": [],
  "geometry": {"coordinates":[-4.85,41.033333],"type":"Point"}
}