{
  "id": 2532421,
  "type": "Feature",
  "properties": {
    "tgn:hierarchy":[
        "tgn:2532421",
        "tgn:1000001",
        "tgn:7012149",
        "tgn:1002392",
        "tgn:7007157",
        "tgn:7029392"
    ],
    "tgn:id":2532421,
    "tgn:name":"Murietta Farm",
    "tgn:placetype":[
        "aat:300008347"
    ]
},
  "bbox": [],
  "geometry": {"coordinates":[-120.45,36.65],"type":"Point"}
}