<<<<<<< HEAD
{
  "id": 2153077,
  "type": "Feature",
  "properties": {
    "tgn:hierarchy":[
        "tgn:2153077",
        "tgn:1000001",
        "tgn:7012149",
        "tgn:2001856",
        "tgn:7007825",
        "tgn:7029392"
    ],
    "tgn:id":2153077,
    "tgn:name":"Beacon Junction",
    "tgn:placetype":[
        "aat:300008347"
    ]
},
  "bbox": [],
  "geometry": {"coordinates":[-88.1667,35.6333],"type":"Point"}
}
=======
{"geometry":{"type":"Point","coordinates":[-88.166700,35.633300]},"type":"Feature","properties":{"hierarchy":["tgn:2153077","tgn:1000001","tgn:7012149","tgn:2001856","tgn:7007825","tgn:7029392"],"placetype":["aat:300008347"],"id":2153077,"name:xx":"Beacon Junction"}}
>>>>>>> 03f74aca74312dbeaf24d7e61306dd6a786dc3d0
