{
  "id": 2153077,
  "type": "Feature",
  "properties": {
    "tgn:hierarchy":[
        "tgn:2153077",
        "tgn:1000001",
        "tgn:7012149",
        "tgn:2001856",
        "tgn:7007825",
        "tgn:7029392"
    ],
    "tgn:id":2153077,
    "tgn:name":"Beacon Junction",
    "tgn:placetype":[
        "aat:300008347"
    ]
},
  "bbox": [],
  "geometry": {"coordinates":[-88.1667,35.6333],"type":"Point"}
}