<<<<<<< HEAD
{
  "id": 2331018,
  "type": "Feature",
  "properties": {
    "tgn:hierarchy":[
        "tgn:2331018",
        "tgn:1000001",
        "tgn:7012149",
        "tgn:2002124",
        "tgn:7007827",
        "tgn:7029392"
    ],
    "tgn:id":2331018,
    "tgn:name":"Flat Rock Spring",
    "tgn:placetype":[
        "aat:300008697"
    ]
},
  "bbox": [],
  "geometry": {"coordinates":[-109.6667,39.5167],"type":"Point"}
}
=======
{"geometry":{"type":"Point","coordinates":[-109.666700,39.516700]},"type":"Feature","properties":{"hierarchy":["tgn:2331018","tgn:1000001","tgn:7012149","tgn:2002124","tgn:7007827","tgn:7029392"],"placetype":["aat:300008697"],"id":2331018,"name:xx":"Flat Rock Spring"}}
>>>>>>> 03f74aca74312dbeaf24d7e61306dd6a786dc3d0
