{
  "id": 2569685,
  "type": "Feature",
  "properties": {
    "tgn:hierarchy":[
        "tgn:2569685",
        "tgn:1000001",
        "tgn:7012149",
        "tgn:1002593",
        "tgn:7007568",
        "tgn:7029392"
    ],
    "tgn:id":2569685,
    "tgn:name":"Parson Mill",
    "tgn:placetype":[
        "aat:300008347"
    ]
},
  "bbox": [],
  "geometry": {"coordinates":[-75.5667,43.4333],"type":"Point"}
}