<<<<<<< HEAD
{
  "id": 2768520,
  "type": "Feature",
  "properties": {
    "tgn:hierarchy":[
        "tgn:2768520",
        "tgn:1000001",
        "tgn:7012149",
        "tgn:2001284",
        "tgn:7007524",
        "tgn:7029392"
    ],
    "tgn:id":2768520,
    "tgn:name":"Whitewater Creek",
    "tgn:placetype":[
        "aat:300008706"
    ]
},
  "bbox": [],
  "geometry": {"coordinates":[-112.75,47.3833],"type":"Point"}
}
=======
{"geometry":{"type":"Point","coordinates":[-112.750000,47.383300]},"type":"Feature","properties":{"hierarchy":["tgn:2768520","tgn:1000001","tgn:7012149","tgn:2001284","tgn:7007524","tgn:7029392"],"placetype":["aat:300008706"],"id":2768520,"name:xx":"Whitewater Creek"}}
>>>>>>> 03f74aca74312dbeaf24d7e61306dd6a786dc3d0
