{
  "id": 7577640,
  "type": "Feature",
  "properties": {
    "tgn:hierarchy":[
        "tgn:7577640",
        "tgn:1000004",
        "tgn:7000198",
        "tgn:1001882",
        "tgn:7029392"
    ],
    "tgn:id":7577640,
    "tgn:name:en":"K\u0101rw\u0101r Bay",
    "tgn:placetype":[
        "aat:300132316"
    ]
},
  "bbox": [],
  "geometry": {"coordinates":[74.111944,14.82],"type":"Point"}
}