{
  "id": 7516113,
  "type": "Feature",
  "properties": {
    "tgn:hierarchy":[
        "tgn:7516113",
        "tgn:1009227",
        "tgn:1000226",
        "tgn:7016822",
        "tgn:1000006",
        "tgn:7029392"
    ],
    "tgn:id":7516113,
    "tgn:name:en":"Monowai River",
    "tgn:placetype":[
        "aat:300008699"
    ]
},
  "bbox": [],
  "geometry": {"coordinates":[167.616667,-45.783333],"type":"Point"}
}