{
  "id": 2398802,
  "type": "Feature",
  "properties": {
    "tgn:hierarchy":[
        "tgn:2398802",
        "tgn:1000001",
        "tgn:1002949",
        "tgn:7012149",
        "tgn:7007159",
        "tgn:7029392"
    ],
    "tgn:id":2398802,
    "tgn:name":"Hope Valley",
    "tgn:placetype":[
        "aat:300008347"
    ]
},
  "bbox": [],
  "geometry": {"coordinates":[-72.3667,41.6333],"type":"Point"}
}