<<<<<<< HEAD
{
  "id": 7484669,
  "type": "Feature",
  "properties": {
    "tgn:hierarchy":[
        "tgn:7484669",
        "tgn:7001004",
        "tgn:1000004",
        "tgn:1000141",
        "tgn:7029392"
    ],
    "tgn:id":7484669,
    "tgn:name":"Bulao Xi",
    "tgn:placetype":[
        "aat:300008699"
    ]
},
  "bbox": [],
  "geometry": {"coordinates":[120.681389,23.065],"type":"Point"}
}
=======
{"geometry":{"type":"Point","coordinates":[120.681389,23.065000]},"type":"Feature","properties":{"hierarchy":["tgn:7484669","tgn:7001004","tgn:1000004","tgn:1000141","tgn:7029392"],"placetype":["aat:300008699"],"id":7484669,"name:xx":"Bulao Xi"}}
>>>>>>> 03f74aca74312dbeaf24d7e61306dd6a786dc3d0
