{
  "id": 2595670,
  "type": "Feature",
  "properties": {
    "tgn:hierarchy":[
        "tgn:2595670",
        "tgn:1000001",
        "tgn:7012149",
        "tgn:7007709",
        "tgn:7029392"
    ],
    "tgn:id":2595670,
    "tgn:name":"Potecasi Creek",
    "tgn:placetype":[
        "aat:300008706"
    ]
},
  "bbox": [],
  "geometry": {"coordinates":[-77.3333,36.3833],"type":"Point"}
}