{
  "id": 7188484,
  "type": "Feature",
  "properties": {
    "tgn:hierarchy":[
        "tgn:7188484",
        "tgn:1000003",
        "tgn:7003677",
        "tgn:7000084",
        "tgn:7029392"
    ],
    "tgn:id":7188484,
    "tgn:name":"Bahnhof Essen-H\u00fcgel",
    "tgn:placetype":[
        "aat:300007783"
    ]
},
  "bbox": [],
  "geometry": {"coordinates":[7.0075,51.404444],"type":"Point"}
}