{
  "id": 2742562,
  "type": "Feature",
  "properties": {
    "tgn:hierarchy":[
        "tgn:2742562",
        "tgn:1000001",
        "tgn:1002330",
        "tgn:7012149",
        "tgn:7007710",
        "tgn:7029392"
    ],
    "tgn:id":2742562,
    "tgn:name":"Valley View",
    "tgn:placetype":[
        "aat:300008347"
    ]
},
  "bbox": [],
  "geometry": {"coordinates":[-75.3833,39.9667],"type":"Point"}
}