{
  "id": 2581322,
  "type": "Feature",
  "properties": {
    "tgn:hierarchy":[
        "tgn:2581322",
        "tgn:1000001",
        "tgn:7012149",
        "tgn:2000369",
        "tgn:7007248",
        "tgn:7029392"
    ],
    "tgn:id":2581322,
    "tgn:name":"Pills Ponds",
    "tgn:placetype":[
        "aat:300006191"
    ]
},
  "bbox": [],
  "geometry": {"coordinates":[-82.5667,32.6333],"type":"Point"}
}