<<<<<<< HEAD
{
  "id": 2400529,
  "type": "Feature",
  "properties": {
    "tgn:hierarchy":[
        "tgn:2400529",
        "tgn:1000001",
        "tgn:1002479",
        "tgn:7012149",
        "tgn:7007240",
        "tgn:7029392"
    ],
    "tgn:id":2400529,
    "tgn:name":"Horse Lake",
    "tgn:placetype":[
        "aat:300008680"
    ]
},
  "bbox": [],
  "geometry": {"coordinates":[-82.5667,28.1],"type":"Point"}
}
=======
{"geometry":{"type":"Point","coordinates":[-82.566700,28.100000]},"type":"Feature","properties":{"hierarchy":["tgn:2400529","tgn:1000001","tgn:1002479","tgn:7012149","tgn:7007240","tgn:7029392"],"placetype":["aat:300008680"],"id":2400529,"name:xx":"Horse Lake"}}
>>>>>>> 03f74aca74312dbeaf24d7e61306dd6a786dc3d0
