{
  "id": 2621630,
  "type": "Feature",
  "properties": {
    "tgn:hierarchy":[
        "tgn:2621630",
        "tgn:1000001",
        "tgn:2001009",
        "tgn:7012149",
        "tgn:7007521",
        "tgn:7029392"
    ],
    "tgn:id":2621630,
    "tgn:name":"Rob Lake",
    "tgn:placetype":[
        "aat:300008680"
    ]
},
  "bbox": [],
  "geometry": {"coordinates":[-94.5833,46.6167],"type":"Point"}
}