{
  "id": 7508815,
  "type": "Feature",
  "properties": {
    "tgn:hierarchy":[
        "tgn:7508815",
        "tgn:1009227",
        "tgn:1000226",
        "tgn:7016822",
        "tgn:1000006",
        "tgn:7029392"
    ],
    "tgn:id":7508815,
    "tgn:name:en":"Waipapa Point",
    "tgn:placetype":[
        "aat:300386846"
    ]
},
  "bbox": [],
  "geometry": {"coordinates":[168.85,-46.65],"type":"Point"}
}