{
  "id": 7038310,
  "type": "Feature",
  "properties": {
    "tgn:hierarchy":[
        "tgn:7038310",
        "tgn:1003450",
        "tgn:7007850",
        "tgn:1000003",
        "tgn:1000080",
        "tgn:7029392"
    ],
    "tgn:id":7038310,
    "tgn:name":"Stazione di Torre Cerchiara",
    "tgn:placetype":[
        "aat:300007783"
    ]
},
  "bbox": [],
  "geometry": {"coordinates":[16.483333,39.783333],"type":"Point"}
}