{
  "id": 1140943,
  "type": "Feature",
  "properties": {
    "tgn:hierarchy":[
        "tgn:1140943",
        "tgn:7001242",
        "tgn:7016833",
        "tgn:1001083",
        "tgn:7029392"
    ],
    "tgn:id":1140943,
    "tgn:name:en":"Al Miny\u0101",
    "tgn:placetype":[
        "aat:300008347"
    ]
},
  "bbox": [],
  "geometry": {"coordinates":[31.299167,29.744458],"type":"Point"}
}