<<<<<<< HEAD
{
  "id": 2335678,
  "type": "Feature",
  "properties": {
    "tgn:hierarchy":[
        "tgn:2335678",
        "tgn:1000001",
        "tgn:2001410",
        "tgn:7012149",
        "tgn:7007526",
        "tgn:7029392"
    ],
    "tgn:id":2335678,
    "tgn:name":"Fortune Cove",
    "tgn:placetype":[
        "aat:300132316"
    ]
},
  "bbox": [],
  "geometry": {"coordinates":[-114.7,35.7167],"type":"Point"}
}
=======
{"geometry":{"type":"Point","coordinates":[-114.700000,35.716700]},"type":"Feature","properties":{"hierarchy":["tgn:2335678","tgn:1000001","tgn:2001410","tgn:7012149","tgn:7007526","tgn:7029392"],"placetype":["aat:300132316"],"id":2335678,"name:xx":"Fortune Cove"}}
>>>>>>> 03f74aca74312dbeaf24d7e61306dd6a786dc3d0
