<<<<<<< HEAD
{
  "id": 2763853,
  "type": "Feature",
  "properties": {
    "tgn:hierarchy":[
        "tgn:2763853",
        "tgn:1000001",
        "tgn:7013942",
        "tgn:7012149",
        "tgn:7007517",
        "tgn:7029392"
    ],
    "tgn:id":2763853,
    "tgn:name":"Wheatherby Brook",
    "tgn:placetype":[
        "aat:300008699"
    ]
},
  "bbox": [],
  "geometry": {"coordinates":[-72.85,42.6],"type":"Point"}
}
=======
{"geometry":{"type":"Point","coordinates":[-72.850000,42.600000]},"type":"Feature","properties":{"hierarchy":["tgn:2763853","tgn:1000001","tgn:7013942","tgn:7012149","tgn:7007517","tgn:7029392"],"placetype":["aat:300008699"],"id":2763853,"name:xx":"Wheatherby Brook"}}
>>>>>>> 03f74aca74312dbeaf24d7e61306dd6a786dc3d0
