{
  "id": 2568666,
  "type": "Feature",
  "properties": {
    "tgn:hierarchy":[
        "tgn:2568666",
        "tgn:2000258",
        "tgn:1000001",
        "tgn:7012149",
        "tgn:7007240",
        "tgn:7029392"
    ],
    "tgn:id":2568666,
    "tgn:name":"Parker Branch",
    "tgn:placetype":[
        "aat:300008699"
    ]
},
  "bbox": [],
  "geometry": {"coordinates":[-85.5167,30.15],"type":"Point"}
}