{
  "id": 1114037,
  "type": "Feature",
  "properties": {
    "tgn:hierarchy":[
        "tgn:1114037",
        "tgn:7001242",
        "tgn:1000169",
        "tgn:7029392"
    ],
    "tgn:id":1114037,
    "tgn:name":"Winam Gulf",
    "tgn:placetype":[
        "aat:300132316",
        "aat:300132315"
    ]
},
  "bbox": [],
  "geometry": {"coordinates":[34.601,-0.25],"type":"Point"}
}