{
  "id": 2288139,
  "type": "Feature",
  "properties": {
    "tgn:hierarchy":[
        "tgn:2288139",
        "tgn:1000001",
        "tgn:7012149",
        "tgn:2002270",
        "tgn:7013961",
        "tgn:7029392"
    ],
    "tgn:id":2288139,
    "tgn:name":"Dinty Moore, Lake",
    "tgn:placetype":[
        "aat:300006191"
    ]
},
  "bbox": [],
  "geometry": {"coordinates":[-81.4833,38.3667],"type":"Point"}
}