{
  "id": 7179130,
  "type": "Feature",
  "properties": {
    "tgn:hierarchy":[
        "tgn:7179130",
        "tgn:7000096",
        "tgn:1000003",
        "tgn:7000084",
        "tgn:7029392"
    ],
    "tgn:id":7179130,
    "tgn:name":"Hammer",
    "tgn:placetype":[
        "aat:300000206"
    ]
},
  "bbox": [],
  "geometry": {"coordinates":[14.65,51.966667],"type":"Point"}
}