{
  "id": 7058770,
  "type": "Feature",
  "properties": {
    "tgn:hierarchy":[
        "tgn:7058770",
        "tgn:7005880",
        "tgn:1000003",
        "tgn:7003237",
        "tgn:1000080",
        "tgn:7029392"
    ],
    "tgn:id":7058770,
    "tgn:name":"Bondeno",
    "tgn:placetype":[
        "aat:300008347"
    ]
},
  "bbox": [],
  "geometry": {"coordinates":[10.866667,44.95],"type":"Point"}
}