{
  "id": 2557066,
  "type": "Feature",
  "properties": {
    "tgn:hierarchy":[
        "tgn:2557066",
        "tgn:1000001",
        "tgn:2001637",
        "tgn:7012149",
        "tgn:7007707",
        "tgn:7029392"
    ],
    "tgn:id":2557066,
    "tgn:name":"Old Grassy Lake",
    "tgn:placetype":[
        "aat:300008680"
    ]
},
  "bbox": [],
  "geometry": {"coordinates":[-96.3333,34.45],"type":"Point"}
}