{
  "id": 2472966,
  "type": "Feature",
  "properties": {
    "tgn:hierarchy":[
        "tgn:2472966",
        "tgn:1000001",
        "tgn:2001180",
        "tgn:7012149",
        "tgn:7007523",
        "tgn:7029392"
    ],
    "tgn:id":2472966,
    "tgn:name":"Low Gap Valley",
    "tgn:placetype":[
        "aat:300008761"
    ]
},
  "bbox": [],
  "geometry": {"coordinates":[-93.6833,39.55],"type":"Point"}
}