{
  "id": 2385940,
  "type": "Feature",
  "properties": {
    "tgn:hierarchy":[
        "tgn:2385940",
        "tgn:1002143",
        "tgn:1000001",
        "tgn:7012149",
        "tgn:7007252",
        "tgn:7029392"
    ],
    "tgn:id":2385940,
    "tgn:name":"Henry Bandelier Ditch",
    "tgn:placetype":[
        "aat:300006075"
    ]
},
  "bbox": [],
  "geometry": {"coordinates":[-84.9833,41.0667],"type":"Point"}
}