{
  "id": 2347576,
  "type": "Feature",
  "properties": {
    "tgn:hierarchy":[
        "tgn:2347576",
        "tgn:1000001",
        "tgn:2001572",
        "tgn:7012149",
        "tgn:7007705",
        "tgn:7029392"
    ],
    "tgn:id":2347576,
    "tgn:name":"George, Lake",
    "tgn:placetype":[
        "aat:300008680"
    ]
},
  "bbox": [],
  "geometry": {"coordinates":[-98.95,47.3833],"type":"Point"}
}