{
  "id": 1055859,
  "type": "Feature",
  "properties": {
    "tgn:hierarchy":[
        "tgn:1055859",
        "tgn:1003351",
        "tgn:1000004",
        "tgn:7018214",
        "tgn:7002435",
        "tgn:7029392"
    ],
    "tgn:id":1055859,
    "tgn:name":"Krasnyy Chikoy",
    "tgn:placetype":[
        "aat:300008347"
    ]
},
  "bbox": [],
  "geometry": {"coordinates":[108.75,50.4167],"type":"Point"}
}