{
  "id": 2202829,
  "type": "Feature",
  "properties": {
    "tgn:hierarchy":[
        "tgn:2202829",
        "tgn:1000001",
        "tgn:7012149",
        "tgn:7007919",
        "tgn:7029392"
    ],
    "tgn:id":2202829,
    "tgn:name":"Buckeye Branch",
    "tgn:placetype":[
        "aat:300008699"
    ]
},
  "bbox": [],
  "geometry": {"coordinates":[-81.6167,36.5833],"type":"Point"}
}