{
  "id": 2684214,
  "type": "Feature",
  "properties": {
    "tgn:hierarchy":[
        "tgn:2684214",
        "tgn:1000001",
        "tgn:7006451",
        "tgn:7012149",
        "tgn:2000104",
        "tgn:7029392"
    ],
    "tgn:id":2684214,
    "tgn:name":"Spenser Wash",
    "tgn:placetype":[
        "aat:300008699"
    ]
},
  "bbox": [],
  "geometry": {"coordinates":[-113.5667,34.1667],"type":"Point"}
}