{
  "id": 7315214,
  "type": "Feature",
  "properties": {
    "tgn:hierarchy":[
        "tgn:7315214",
        "tgn:7002464",
        "tgn:1000049",
        "tgn:1000002",
        "tgn:7029392"
    ],
    "tgn:id":7315214,
    "tgn:name":"Colchane",
    "tgn:placetype":[
        "aat:300008347"
    ]
},
  "bbox": [],
  "geometry": {"coordinates":[-68.633333,-19.283333],"type":"Point"}
}