{
  "id": 2419104,
  "type": "Feature",
  "properties": {
    "tgn:hierarchy":[
        "tgn:2419104",
        "tgn:1000001",
        "tgn:2002324",
        "tgn:7012149",
        "tgn:7007922",
        "tgn:7029392"
    ],
    "tgn:id":2419104,
    "tgn:name":"Jamestown",
    "tgn:placetype":[
        "aat:300008347"
    ]
},
  "bbox": [],
  "geometry": {"coordinates":[-90.5333,42.5833],"type":"Point"}
}