{
  "id": 2568962,
  "type": "Feature",
  "properties": {
    "tgn:hierarchy":[
        "tgn:2568962",
        "tgn:1000001",
        "tgn:2001426",
        "tgn:7012149",
        "tgn:7007564",
        "tgn:7029392"
    ],
    "tgn:id":2568962,
    "tgn:name":"Parker Mountain",
    "tgn:placetype":[
        "aat:300008798"
    ]
},
  "bbox": [],
  "geometry": {"coordinates":[-71.1667,43.2667],"type":"Point"}
}