{
  "id": 2478635,
  "type": "Feature",
  "properties": {
    "tgn:hierarchy":[
        "tgn:2478635",
        "tgn:1000001",
        "tgn:7012149",
        "tgn:7007157",
        "tgn:1002621",
        "tgn:7029392"
    ],
    "tgn:id":2478635,
    "tgn:name":"Madera Quarry",
    "tgn:placetype":[
        "aat:300000390"
    ]
},
  "bbox": [],
  "geometry": {"coordinates":[-119.7833,37.1333],"type":"Point"}
}