{
  "id": 2525431,
  "type": "Feature",
  "properties": {
    "tgn:hierarchy":[
        "tgn:2525431",
        "tgn:1000001",
        "tgn:7012149",
        "tgn:1002464",
        "tgn:7007826",
        "tgn:7029392"
    ],
    "tgn:id":2525431,
    "tgn:name":"Morrow Lake",
    "tgn:placetype":[
        "aat:300008680"
    ]
},
  "bbox": [],
  "geometry": {"coordinates":[-95.85,32.1333],"type":"Point"}
}