<<<<<<< HEAD
{
  "id": 2150154,
  "type": "Feature",
  "properties": {
    "tgn:hierarchy":[
        "tgn:2150154",
        "tgn:1000001",
        "tgn:2002109",
        "tgn:7012149",
        "tgn:7007827",
        "tgn:7029392"
    ],
    "tgn:id":2150154,
    "tgn:name":"Bartons Peak",
    "tgn:placetype":[
        "aat:300008798"
    ]
},
  "bbox": [],
  "geometry": {"coordinates":[-110.7667,38.0667],"type":"Point"}
}
=======
{"geometry":{"type":"Point","coordinates":[-110.766700,38.066700]},"type":"Feature","properties":{"hierarchy":["tgn:2150154","tgn:1000001","tgn:2002109","tgn:7012149","tgn:7007827","tgn:7029392"],"placetype":["aat:300008798"],"id":2150154,"name:xx":"Bartons Peak"}}
>>>>>>> 03f74aca74312dbeaf24d7e61306dd6a786dc3d0
