{
  "id": 7053793,
  "type": "Feature",
  "properties": {
    "tgn:hierarchy":[
        "tgn:7053793",
        "tgn:7003136",
        "tgn:1000003",
        "tgn:7003080",
        "tgn:1000080",
        "tgn:7029392"
    ],
    "tgn:id":7053793,
    "tgn:name":"Porto Salvo",
    "tgn:placetype":[
        "aat:300008347"
    ]
},
  "bbox": [],
  "geometry": {"coordinates":[13.566667,41.216667],"type":"Point"}
}