{
  "id": 2362199,
  "type": "Feature",
  "properties": {
    "tgn:hierarchy":[
        "tgn:2362199",
        "tgn:1000001",
        "tgn:7012149",
        "tgn:2000996",
        "tgn:7007520",
        "tgn:7029392"
    ],
    "tgn:id":2362199,
    "tgn:name":"Grays Creek",
    "tgn:placetype":[
        "aat:300008706"
    ]
},
  "bbox": [],
  "geometry": {"coordinates":[-85.9333,46.2667],"type":"Point"}
}