{
  "id": 2769186,
  "type": "Feature",
  "properties": {
    "tgn:hierarchy":[
        "tgn:2769186",
        "tgn:1000001",
        "tgn:7012149",
        "tgn:2000835",
        "tgn:7007255",
        "tgn:7029392"
    ],
    "tgn:id":2769186,
    "tgn:name":"Whoopflarea",
    "tgn:placetype":[
        "aat:300008347"
    ]
},
  "bbox": [],
  "geometry": {"coordinates":[-83.5667,37.2833],"type":"Point"}
}