{
  "id": 1104105,
  "type": "Feature",
  "properties": {
    "tgn:hierarchy":[
        "tgn:1104105",
        "tgn:7006450",
        "tgn:1000001",
        "tgn:7012149",
        "tgn:2000089",
        "tgn:7029392"
    ],
    "tgn:id":1104105,
    "tgn:name":"Cache Mountain",
    "tgn:placetype":[
        "aat:300008795"
    ]
},
  "bbox": [],
  "geometry": {"coordinates":[-147.3167,65.5167],"type":"Point"}
}