<<<<<<< HEAD
{
  "id": 7487440,
  "type": "Feature",
  "properties": {
    "tgn:hierarchy":[
        "tgn:7487440",
        "tgn:1000004",
        "tgn:7492971",
        "tgn:1000141",
        "tgn:7029392"
    ],
    "tgn:id":7487440,
    "tgn:name":"Linzitou",
    "tgn:placetype":[
        "aat:300008347"
    ]
},
  "bbox": [],
  "geometry": {"coordinates":[120.524814,22.828043],"type":"Point"}
}
=======
{"geometry":{"type":"Point","coordinates":[120.524814,22.828043]},"type":"Feature","properties":{"hierarchy":["tgn:7487440","tgn:1000004","tgn:7492971","tgn:1000141","tgn:7029392"],"placetype":["aat:300008347"],"id":7487440,"name:xx":"Linzitou"}}
>>>>>>> 03f74aca74312dbeaf24d7e61306dd6a786dc3d0
