{
  "id": 7233755,
  "type": "Feature",
  "properties": {
    "tgn:hierarchy":[
        "tgn:7233755",
        "tgn:7011270",
        "tgn:7002674",
        "tgn:1000003",
        "tgn:1000074",
        "tgn:7029392"
    ],
    "tgn:id":7233755,
    "tgn:name":"Ag\u00eda Eir\u00edni, \u00c1kra",
    "tgn:placetype":[
        "aat:300008850"
    ]
},
  "bbox": [],
  "geometry": {"coordinates":[25.343389,36.459061],"type":"Point"}
}