{
  "id": 7273898,
  "type": "Feature",
  "properties": {
    "tgn:hierarchy":[
        "tgn:7273898",
        "tgn:1000003",
        "tgn:7006951",
        "tgn:7016845",
        "tgn:7029392"
    ],
    "tgn:id":7273898,
    "tgn:name:nl":"Waver",
    "tgn:placetype":[
        "aat:300387055"
    ]
},
  "bbox": [],
  "geometry": {"coordinates":[4.933333,52.283333],"type":"Point"}
}