{
  "id": 2285340,
  "type": "Feature",
  "properties": {
    "tgn:hierarchy":[
        "tgn:2285340",
        "tgn:1000001",
        "tgn:7012149",
        "tgn:7013940",
        "tgn:7007709",
        "tgn:7029392"
    ],
    "tgn:id":2285340,
    "tgn:name":"Devils Cradle Creek",
    "tgn:placetype":[
        "aat:300008706"
    ]
},
  "bbox": [],
  "geometry": {"coordinates":[-78.3167,36.2333],"type":"Point"}
}