{
  "id": 1051239,
  "type": "Feature",
  "properties": {
    "tgn:hierarchy":[
        "tgn:1051239",
        "tgn:6001445",
        "tgn:1000004",
        "tgn:7018214",
        "tgn:7002435",
        "tgn:7029392"
    ],
    "tgn:id":1051239,
    "tgn:name":"Chegytun",
    "tgn:placetype":[
        "aat:300008347"
    ]
},
  "bbox": [],
  "geometry": {"coordinates":[-171.1667,66.5833],"type":"Point"}
}