{
  "id": 7166233,
  "type": "Feature",
  "properties": {
    "tgn:hierarchy":[
        "tgn:7166233",
        "tgn:7003669",
        "tgn:1000003",
        "tgn:7000084",
        "tgn:7029392"
    ],
    "tgn:id":7166233,
    "tgn:name":"H\u00e4userhof",
    "tgn:placetype":[
        "aat:300008347"
    ]
},
  "bbox": [],
  "geometry": {"coordinates":[10.483333,48.316667],"type":"Point"}
}