{
  "id": 7282026,
  "type": "Feature",
  "properties": {
    "tgn:hierarchy":[
        "tgn:7282026",
        "tgn:1001695",
        "tgn:1000049",
        "tgn:1000002",
        "tgn:7029392"
    ],
    "tgn:id":7282026,
    "tgn:name":"San Pedro",
    "tgn:placetype":[
        "aat:300008777"
    ]
},
  "bbox": [],
  "geometry": {"coordinates":[-70.966667,-34.416667],"type":"Point"}
}