{
  "id": 7009211,
  "type": "Feature",
  "properties": {
    "tgn:hierarchy":[
        "tgn:7009211",
        "tgn:1000003",
        "tgn:1000070",
        "tgn:7002897",
        "tgn:7029392"
    ],
    "tgn:id":7009211,
    "tgn:name":"Givors",
    "tgn:placetype":[
        "aat:300008347"
    ]
},
  "bbox": [],
  "geometry": {"coordinates":[4.7833,45.5833],"type":"Point"}
}