{
  "id": 2161696,
  "type": "Feature",
  "properties": {
    "tgn:hierarchy":[
        "tgn:2161696",
        "tgn:1000001",
        "tgn:7012149",
        "tgn:2000810",
        "tgn:7007255",
        "tgn:7029392"
    ],
    "tgn:id":2161696,
    "tgn:name":"Belle Point",
    "tgn:placetype":[
        "aat:300008347"
    ]
},
  "bbox": [],
  "geometry": {"coordinates":[-83.7333,37.55],"type":"Point"}
}