{
  "id": 1060159,
  "type": "Feature",
  "properties": {
    "tgn:hierarchy":[
        "tgn:1060159",
        "tgn:1000004",
        "tgn:7013571",
        "tgn:7018214",
        "tgn:7002435",
        "tgn:7029392"
    ],
    "tgn:id":1060159,
    "tgn:name":"Tarko-Sale",
    "tgn:placetype":[
        "aat:300008347"
    ]
},
  "bbox": [],
  "geometry": {"coordinates":[77.8333,64.9167],"type":"Point"}
}