{
  "id": 7125328,
  "type": "Feature",
  "properties": {
    "tgn:hierarchy":[
        "tgn:7125328",
        "tgn:7000096",
        "tgn:1000003",
        "tgn:7000084",
        "tgn:7029392"
    ],
    "tgn:id":7125328,
    "tgn:name":"Neuer See",
    "tgn:placetype":[
        "aat:300008680"
    ]
},
  "bbox": [],
  "geometry": {"coordinates":[14.05,52.633333],"type":"Point"}
}