{
  "id": 1063619,
  "type": "Feature",
  "properties": {
    "tgn:hierarchy":[
        "tgn:1063619",
        "tgn:1000003",
        "tgn:7024620",
        "tgn:1000097",
        "tgn:7029392"
    ],
    "tgn:id":1063619,
    "tgn:name":"Sm\u00f6gen",
    "tgn:placetype":[
        "aat:300008347"
    ]
},
  "bbox": [],
  "geometry": {"coordinates":[11.2167,58.35],"type":"Point"}
}