{
  "id": 7536998,
  "type": "Feature",
  "properties": {
    "tgn:hierarchy":[
        "tgn:7536998",
        "tgn:7001242",
        "tgn:7016833",
        "tgn:7001312",
        "tgn:7029392"
    ],
    "tgn:id":7536998,
    "tgn:name:en":"Kafr Dimitnu",
    "tgn:placetype":[
        "aat:300008347"
    ]
},
  "bbox": [],
  "geometry": {"coordinates":[31.092454,31.056792],"type":"Point"}
}