<<<<<<< HEAD
{
  "id": 7476265,
  "type": "Feature",
  "properties": {
    "tgn:hierarchy":[
        "tgn:7476265",
        "tgn:7487020",
        "tgn:1000004",
        "tgn:1000141",
        "tgn:7029392"
    ],
    "tgn:id":7476265,
    "tgn:name":"Bashichiqiao",
    "tgn:placetype":[
        "aat:300008347"
    ]
},
  "bbox": [],
  "geometry": {"coordinates":[120.8367,24.6126],"type":"Point"}
}
=======
{"geometry":{"type":"Point","coordinates":[120.836700,24.612600]},"type":"Feature","properties":{"hierarchy":["tgn:7476265","tgn:7487020","tgn:1000004","tgn:1000141","tgn:7029392"],"placetype":["aat:300008347"],"id":7476265,"name:xx":"Bashichiqiao"}}
>>>>>>> 03f74aca74312dbeaf24d7e61306dd6a786dc3d0
