{
  "id": 2748313,
  "type": "Feature",
  "properties": {
    "tgn:hierarchy":[
        "tgn:2748313",
        "tgn:1000001",
        "tgn:7012149",
        "tgn:2000289",
        "tgn:7007240",
        "tgn:7029392"
    ],
    "tgn:id":2748313,
    "tgn:name":"Walker Creek",
    "tgn:placetype":[
        "aat:300008706"
    ]
},
  "bbox": [],
  "geometry": {"coordinates":[-84.2833,30.0833],"type":"Point"}
}