{
  "id": 2306670,
  "type": "Feature",
  "properties": {
    "tgn:hierarchy":[
        "tgn:2306670",
        "tgn:1000001",
        "tgn:7012149",
        "tgn:2000548",
        "tgn:7007252",
        "tgn:7029392"
    ],
    "tgn:id":2306670,
    "tgn:name":"East Fork Fish Creek",
    "tgn:placetype":[
        "aat:300008706"
    ]
},
  "bbox": [],
  "geometry": {"coordinates":[-86.85,39.3667],"type":"Point"}
}