{
  "id": 7540254,
  "type": "Feature",
  "properties": {
    "tgn:hierarchy":[
        "tgn:7540254",
        "tgn:7001242",
        "tgn:7016833",
        "tgn:1001418",
        "tgn:7029392"
    ],
    "tgn:id":7540254,
    "tgn:name:en":"Mil\u1e29, 'Ayn al",
    "tgn:placetype":[
        "aat:300008697"
    ]
},
  "bbox": [],
  "geometry": {"coordinates":[25.333333,29.216667],"type":"Point"}
}