<<<<<<< HEAD
{
  "id": 2256705,
  "type": "Feature",
  "properties": {
    "tgn:hierarchy":[
        "tgn:2256705",
        "tgn:1000001",
        "tgn:7006451",
        "tgn:7012149",
        "tgn:7029392"
    ],
    "tgn:id":2256705,
    "tgn:name":"Corduroy Creek",
    "tgn:placetype":[
        "aat:300008706"
    ]
},
  "bbox": [],
  "geometry": {"coordinates":[-109.8333,34.1],"type":"Point"}
}
=======
{"geometry":{"type":"Point","coordinates":[-109.833300,34.100000]},"type":"Feature","properties":{"hierarchy":["tgn:2256705","tgn:1000001","tgn:7006451","tgn:7012149","tgn:7029392"],"placetype":["aat:300008706"],"id":2256705,"name:xx":"Corduroy Creek"}}
>>>>>>> 03f74aca74312dbeaf24d7e61306dd6a786dc3d0
