{
  "id": 7285485,
  "type": "Feature",
  "properties": {
    "tgn:hierarchy":[
        "tgn:7285485",
        "tgn:1001692",
        "tgn:1000049",
        "tgn:1000002",
        "tgn:7029392"
    ],
    "tgn:id":7285485,
    "tgn:name":"Quema, Estero",
    "tgn:placetype":[
        "aat:300008699"
    ]
},
  "bbox": [],
  "geometry": {"coordinates":[-72.466667,-39.133333],"type":"Point"}
}