{
  "id": 7511270,
  "type": "Feature",
  "properties": {
    "tgn:hierarchy":[
        "tgn:7511270",
        "tgn:1008380",
        "tgn:1000226",
        "tgn:7016827",
        "tgn:1000006",
        "tgn:7029392"
    ],
    "tgn:id":7511270,
    "tgn:name:en":"Tuaahukuku",
    "tgn:placetype":[
        "aat:300008795"
    ]
},
  "bbox": [],
  "geometry": {"coordinates":[174.75,-39.566667],"type":"Point"}
}