{
  "id": 2324595,
  "type": "Feature",
  "properties": {
    "tgn:hierarchy":[
        "tgn:2324595",
        "tgn:1000001",
        "tgn:7012149",
        "tgn:2001455",
        "tgn:7007566",
        "tgn:7029392"
    ],
    "tgn:id":2324595,
    "tgn:name":"Fence Canyon",
    "tgn:placetype":[
        "aat:300008761"
    ]
},
  "bbox": [],
  "geometry": {"coordinates":[-106.75,33.2667],"type":"Point"}
}