{
  "id": 2333887,
  "type": "Feature",
  "properties": {
    "tgn:hierarchy":[
        "tgn:2333887",
        "tgn:1000001",
        "tgn:7012149",
        "tgn:2000651",
        "tgn:7007253",
        "tgn:7029392"
    ],
    "tgn:id":2333887,
    "tgn:name":"Ford",
    "tgn:placetype":[
        "aat:300008347"
    ]
},
  "bbox": [],
  "geometry": {"coordinates":[-93.3833,41.4833],"type":"Point"}
}