<<<<<<< HEAD
{
  "id": 2333887,
  "type": "Feature",
  "properties": {
    "tgn:hierarchy":[
        "tgn:2333887",
        "tgn:1000001",
        "tgn:7012149",
        "tgn:2000651",
        "tgn:7007253",
        "tgn:7029392"
    ],
    "tgn:id":2333887,
    "tgn:name":"Ford",
    "tgn:placetype":[
        "aat:300008347"
    ]
},
  "bbox": [],
  "geometry": {"coordinates":[-93.3833,41.4833],"type":"Point"}
}
=======
{"geometry":{"type":"Point","coordinates":[-93.383300,41.483300]},"type":"Feature","properties":{"hierarchy":["tgn:2333887","tgn:1000001","tgn:7012149","tgn:2000651","tgn:7007253","tgn:7029392"],"placetype":["aat:300008347"],"id":2333887,"name:xx":"Ford"}}
>>>>>>> 03f74aca74312dbeaf24d7e61306dd6a786dc3d0
