{
  "id": 2048345,
  "type": "Feature",
  "properties": {
    "tgn:hierarchy":[
        "tgn:2048345",
        "tgn:1000001",
        "tgn:1002488",
        "tgn:7012149",
        "tgn:7007516",
        "tgn:7029392"
    ],
    "tgn:id":2048345,
    "tgn:name":"Poplar Springs",
    "tgn:placetype":[
        "aat:300008347"
    ]
},
  "bbox": [],
  "geometry": {"coordinates":[-77.0833,39.3333],"type":"Point"}
}