{
  "id": 2555557,
  "type": "Feature",
  "properties": {
    "tgn:hierarchy":[
        "tgn:2555557",
        "tgn:7030516",
        "tgn:7006450",
        "tgn:1000001",
        "tgn:7012149",
        "tgn:7029392"
    ],
    "tgn:id":2555557,
    "tgn:name":"Ogangen Island",
    "tgn:placetype":[
        "aat:300008791"
    ]
},
  "bbox": [],
  "geometry": {"coordinates":[-166.8667,53.4333],"type":"Point"}
}