{
  "id": 2743079,
  "type": "Feature",
  "properties": {
    "tgn:hierarchy":[
        "tgn:2743079",
        "tgn:1000001",
        "tgn:7012149",
        "tgn:7007523",
        "tgn:7029392"
    ],
    "tgn:id":2743079,
    "tgn:name":"Van Zant Creek",
    "tgn:placetype":[
        "aat:300008706"
    ]
},
  "bbox": [],
  "geometry": {"coordinates":[-92.1833,37.1667],"type":"Point"}
}