<<<<<<< HEAD
{
  "id": 7485021,
  "type": "Feature",
  "properties": {
    "tgn:hierarchy":[
        "tgn:7485021",
        "tgn:1000004",
        "tgn:7491221",
        "tgn:1000141",
        "tgn:7029392"
    ],
    "tgn:id":7485021,
    "tgn:name":"Dazhu Sanhao Suidao",
    "tgn:placetype":[
        "aat:300007899"
    ]
},
  "bbox": [],
  "geometry": {"coordinates":[120.946389,22.468056],"type":"Point"}
}
=======
{"geometry":{"type":"Point","coordinates":[120.946389,22.468056]},"type":"Feature","properties":{"hierarchy":["tgn:7485021","tgn:1000004","tgn:7491221","tgn:1000141","tgn:7029392"],"placetype":["aat:300007899"],"id":7485021,"name:xx":"Dazhu Sanhao Suidao"}}
>>>>>>> 03f74aca74312dbeaf24d7e61306dd6a786dc3d0
