{
  "id": 7485021,
  "type": "Feature",
  "properties": {
    "tgn:hierarchy":[
        "tgn:7485021",
        "tgn:1000004",
        "tgn:7491221",
        "tgn:1000141",
        "tgn:7029392"
    ],
    "tgn:id":7485021,
    "tgn:name":"Dazhu Sanhao Suidao",
    "tgn:placetype":[
        "aat:300007899"
    ]
},
  "bbox": [],
  "geometry": {"coordinates":[120.946389,22.468056],"type":"Point"}
}