{
  "id": 1106270,
  "type": "Feature",
  "properties": {
    "tgn:hierarchy":[
        "tgn:1106270",
        "tgn:1009495",
        "tgn:7004677",
        "tgn:1000001",
        "tgn:7029392"
    ],
    "tgn:id":1106270,
    "tgn:name":"Sage, Mount",
    "tgn:placetype":[
        "aat:300008795"
    ]
},
  "bbox": [],
  "geometry": {"coordinates":[-64.65,18.4167],"type":"Point"}
}