{
  "id": 1063605,
  "type": "Feature",
  "properties": {
    "tgn:hierarchy":[
        "tgn:1063605",
        "tgn:1000003",
        "tgn:1000462",
        "tgn:1000097",
        "tgn:7029392"
    ],
    "tgn:id":1063605,
    "tgn:name":"Skoby",
    "tgn:placetype":[
        "aat:300008347"
    ]
},
  "bbox": [],
  "geometry": {"coordinates":[18.0167,60.0333],"type":"Point"}
}