<<<<<<< HEAD
{
  "id": 7356201,
  "type": "Feature",
  "properties": {
    "tgn:hierarchy":[
        "tgn:7356201",
        "tgn:7005578",
        "tgn:1000001",
        "tgn:7005560",
        "tgn:7029392"
    ],
    "tgn:id":7356201,
    "tgn:name":"Caribe, Arroyo",
    "tgn:placetype":[
        "aat:300008699"
    ]
},
  "bbox": [],
  "geometry": {"coordinates":[-90.783333,18.116667],"type":"Point"}
}
=======
{"geometry":{"type":"Point","coordinates":[-90.783333,18.116667]},"type":"Feature","properties":{"hierarchy":["tgn:7356201","tgn:7005578","tgn:1000001","tgn:7005560","tgn:7029392"],"placetype":["aat:300008699"],"id":7356201,"name:xx":"Caribe, Arroyo"}}
>>>>>>> 03f74aca74312dbeaf24d7e61306dd6a786dc3d0
