{
  "id": 2734337,
  "type": "Feature",
  "properties": {
    "tgn:hierarchy":[
        "tgn:2734337",
        "tgn:1000001",
        "tgn:7012149",
        "tgn:2002327",
        "tgn:7007922",
        "tgn:7029392"
    ],
    "tgn:id":2734337,
    "tgn:name":"Turtle Flambeau Flowage",
    "tgn:placetype":[
        "aat:300006191"
    ]
},
  "bbox": [],
  "geometry": {"coordinates":[-90.2167,46.0667],"type":"Point"}
}