{
  "id": 1135577,
  "type": "Feature",
  "properties": {
    "tgn:hierarchy":[
        "tgn:1135577",
        "tgn:7001242",
        "tgn:7016833",
        "tgn:1001225",
        "tgn:7029392"
    ],
    "tgn:id":1135577,
    "tgn:name":"Dumy\u0101\u1e6d, Ma\u1e63abb",
    "tgn:placetype":[
        "aat:300387057"
    ]
},
  "bbox": [],
  "geometry": {"coordinates":[31.844693,31.527034],"type":"Point"}
}