{
  "id": 2542896,
  "type": "Feature",
  "properties": {
    "tgn:hierarchy":[
        "tgn:2542896",
        "tgn:2000000",
        "tgn:7002659",
        "tgn:1000001",
        "tgn:7012149",
        "tgn:7029392"
    ],
    "tgn:id":2542896,
    "tgn:name":"Noland Creek",
    "tgn:placetype":[
        "aat:300008706"
    ]
},
  "bbox": [],
  "geometry": {"coordinates":[-86.5333,32.4667],"type":"Point"}
}