{
  "id": 7031218,
  "type": "Feature",
  "properties": {
    "tgn:hierarchy":[
        "tgn:7031218",
        "tgn:7002445",
        "tgn:1000003",
        "tgn:7008168",
        "tgn:7008591",
        "tgn:7029392"
    ],
    "tgn:id":7031218,
    "tgn:name":"Balscote",
    "tgn:placetype":[
        "aat:300008347",
        "aat:300008372"
    ]
},
  "bbox": [],
  "geometry": {"coordinates":[-1.423,52.067],"type":"Point"}
}