{
  "id": 7510454,
  "type": "Feature",
  "properties": {
    "tgn:hierarchy":[
        "tgn:7510454",
        "tgn:1008380",
        "tgn:7000507",
        "tgn:1000226",
        "tgn:1000006",
        "tgn:7029392"
    ],
    "tgn:id":7510454,
    "tgn:name:en":"Spirits Bay",
    "tgn:placetype":[
        "aat:300132316"
    ]
},
  "bbox": [],
  "geometry": {"coordinates":[172.783333,-34.416667],"type":"Point"}
}