{
  "id": 1127489,
  "type": "Feature",
  "properties": {
    "tgn:hierarchy":[
        "tgn:1127489",
        "tgn:7001242",
        "tgn:7029392"
    ],
    "tgn:id":1127489,
    "tgn:name":"Musengezi",
    "tgn:placetype":[
        "aat:300008707"
    ]
},
  "bbox": [],
  "geometry": {"coordinates":[31.2333,-15.7167],"type":"Point"}
}