{
  "id": 7157766,
  "type": "Feature",
  "properties": {
    "tgn:hierarchy":[
        "tgn:7157766",
        "tgn:1000003",
        "tgn:7000094",
        "tgn:7000084",
        "tgn:7029392"
    ],
    "tgn:id":7157766,
    "tgn:name":"Kieler Ort",
    "tgn:placetype":[
        "aat:300008804"
    ]
},
  "bbox": [],
  "geometry": {"coordinates":[11.516667,54.066667],"type":"Point"}
}