{
  "id": 7476947,
  "type": "Feature",
  "properties": {
    "tgn:hierarchy":[
        "tgn:7476947",
        "tgn:1000004",
        "tgn:1000454",
        "tgn:1000141",
        "tgn:7029392"
    ],
    "tgn:id":7476947,
    "tgn:name":"Dakuaicuo",
    "tgn:placetype":[
        "aat:300008347"
    ]
},
  "bbox": [],
  "geometry": {"coordinates":[121.848472,25.059102],"type":"Point"}
}