{
  "id": 7448099,
  "type": "Feature",
  "properties": {
    "tgn:hierarchy":[
        "tgn:7448099",
        "tgn:7002444",
        "tgn:1000003",
        "tgn:7008094",
        "tgn:7008591",
        "tgn:7029392"
    ],
    "tgn:id":7448099,
    "tgn:name:en":"Tavay More",
    "tgn:placetype":[
        "aat:300008791"
    ]
},
  "bbox": [],
  "geometry": {"coordinates":[-6.383333,58.116667],"type":"Point"}
}