{
  "id": 2359242,
  "type": "Feature",
  "properties": {
    "tgn:hierarchy":[
        "tgn:2359242",
        "tgn:1000001",
        "tgn:7006451",
        "tgn:7012149",
        "tgn:2000096",
        "tgn:7029392"
    ],
    "tgn:id":2359242,
    "tgn:name":"Granite Wash",
    "tgn:placetype":[
        "aat:300008701"
    ]
},
  "bbox": [],
  "geometry": {"coordinates":[-113.65,33.7167],"type":"Point"}
}