<<<<<<< HEAD
{
  "id": 7484588,
  "type": "Feature",
  "properties": {
    "tgn:hierarchy":[
        "tgn:7484588",
        "tgn:1000004",
        "tgn:7001014",
        "tgn:1000141",
        "tgn:7029392"
    ],
    "tgn:id":7484588,
    "tgn:name":"Xingchang Guoxiao",
    "tgn:placetype":[
        "aat:300006495"
    ]
},
  "bbox": [],
  "geometry": {"coordinates":[120.537222,23.611944],"type":"Point"}
}
=======
{"geometry":{"type":"Point","coordinates":[120.537222,23.611944]},"type":"Feature","properties":{"hierarchy":["tgn:7484588","tgn:1000004","tgn:7001014","tgn:1000141","tgn:7029392"],"placetype":["aat:300006495"],"id":7484588,"name:xx":"Xingchang Guoxiao"}}
>>>>>>> 03f74aca74312dbeaf24d7e61306dd6a786dc3d0
