{
  "id": 7324974,
  "type": "Feature",
  "properties": {
    "tgn:hierarchy":[
        "tgn:7324974",
        "tgn:7002759",
        "tgn:7008909",
        "tgn:1000003",
        "tgn:1000095",
        "tgn:7029392"
    ],
    "tgn:id":7324974,
    "tgn:name":"Santa Eulalia la Mayor",
    "tgn:placetype":[
        "aat:300008347"
    ]
},
  "bbox": [],
  "geometry": {"coordinates":[-0.296436,42.211305],"type":"Point"}
}