{
  "id": 7249268,
  "type": "Feature",
  "properties": {
    "tgn:hierarchy":[
        "tgn:7249268",
        "tgn:7003456",
        "tgn:1000003",
        "tgn:1000063",
        "tgn:7018236",
        "tgn:7029392"
    ],
    "tgn:id":7249268,
    "tgn:name":"Niemandshoek",
    "tgn:placetype":[
        "aat:300008347"
    ]
},
  "bbox": [],
  "geometry": {"coordinates":[4.722164,51.128122],"type":"Point"}
}