<<<<<<< HEAD
{
  "id": 7248010,
  "type": "Feature",
  "properties": {
    "tgn:hierarchy":[
        "tgn:7248010",
        "tgn:7003460",
        "tgn:1000003",
        "tgn:1000063",
        "tgn:4012014",
        "tgn:7029392"
    ],
    "tgn:id":7248010,
    "tgn:name":"B\u00e9emont",
    "tgn:placetype":[
        "aat:300008347"
    ]
},
  "bbox": [],
  "geometry": {"coordinates":[5.403323,50.4468],"type":"Point"}
}
=======
{"geometry":{"type":"Point","coordinates":[5.403323,50.446800]},"type":"Feature","properties":{"hierarchy":["tgn:7248010","tgn:7003460","tgn:1000003","tgn:1000063","tgn:4012014","tgn:7029392"],"placetype":["aat:300008347"],"id":7248010,"name:xx":"B\u00e9emont"}}
>>>>>>> 03f74aca74312dbeaf24d7e61306dd6a786dc3d0
