{
  "id": 7472727,
  "type": "Feature",
  "properties": {
    "tgn:hierarchy":[
        "tgn:7472727",
        "tgn:7468018",
        "tgn:1000004",
        "tgn:1000141",
        "tgn:7029392"
    ],
    "tgn:id":7472727,
    "tgn:name":"Duli Shan",
    "tgn:placetype":[
        "aat:300008798"
    ]
},
  "bbox": [],
  "geometry": {"coordinates":[120.6075,23.536667],"type":"Point"}
}