{
  "id": 2412193,
  "type": "Feature",
  "properties": {
    "tgn:hierarchy":[
        "tgn:2412193",
        "tgn:1000001",
        "tgn:7012149",
        "tgn:2000493",
        "tgn:7007250",
        "tgn:7029392"
    ],
    "tgn:id":2412193,
    "tgn:name":"Indian Spring",
    "tgn:placetype":[
        "aat:300008697"
    ]
},
  "bbox": [],
  "geometry": {"coordinates":[-114.35,42.2667],"type":"Point"}
}