<<<<<<< HEAD
{
  "id": 2330789,
  "type": "Feature",
  "properties": {
    "tgn:hierarchy":[
        "tgn:2330789",
        "tgn:1000001",
        "tgn:7012149",
        "tgn:2000802",
        "tgn:7007255",
        "tgn:7029392"
    ],
    "tgn:id":2330789,
    "tgn:name":"Flat Lick Creek",
    "tgn:placetype":[
        "aat:300008706"
    ]
},
  "bbox": [],
  "geometry": {"coordinates":[-83.9,37.3667],"type":"Point"}
}
=======
{"geometry":{"type":"Point","coordinates":[-83.900000,37.366700]},"type":"Feature","properties":{"hierarchy":["tgn:2330789","tgn:1000001","tgn:7012149","tgn:2000802","tgn:7007255","tgn:7029392"],"placetype":["aat:300008706"],"id":2330789,"name:xx":"Flat Lick Creek"}}
>>>>>>> 03f74aca74312dbeaf24d7e61306dd6a786dc3d0
