{
  "id": 7399058,
  "type": "Feature",
  "properties": {
    "tgn:hierarchy":[
        "tgn:7399058",
        "tgn:1000001",
        "tgn:1001893",
        "tgn:7005560",
        "tgn:7029392"
    ],
    "tgn:id":7399058,
    "tgn:name":"El Tunal Nenaxi",
    "tgn:placetype":[
        "aat:300008347"
    ]
},
  "bbox": [],
  "geometry": {"coordinates":[-99.907778,19.745556],"type":"Point"}
}