{
  "id": 2588782,
  "type": "Feature",
  "properties": {
    "tgn:hierarchy":[
        "tgn:2588782",
        "tgn:1000001",
        "tgn:7006451",
        "tgn:7012149",
        "tgn:2000098",
        "tgn:7029392"
    ],
    "tgn:id":2588782,
    "tgn:name":"Poachie Range",
    "tgn:placetype":[
        "aat:300386831"
    ]
},
  "bbox": [],
  "geometry": {"coordinates":[-113.4833,34.4667],"type":"Point"}
}