{
  "id": 7570503,
  "type": "Feature",
  "properties": {
    "tgn:hierarchy":[
        "tgn:7570503",
        "tgn:1001828",
        "tgn:1000004",
        "tgn:7000198",
        "tgn:7029392"
    ],
    "tgn:id":7570503,
    "tgn:name:en":"Daul\u0101pur",
    "tgn:placetype":[
        "aat:300008347"
    ]
},
  "bbox": [],
  "geometry": {"coordinates":[78.838333,17.771944],"type":"Point"}
}