{
  "id": 2518247,
  "type": "Feature",
  "properties": {
    "tgn:hierarchy":[
        "tgn:2518247",
        "tgn:1000001",
        "tgn:7012149",
        "tgn:2000837",
        "tgn:7007255",
        "tgn:7029392"
    ],
    "tgn:id":2518247,
    "tgn:name":"Missouri Branch",
    "tgn:placetype":[
        "aat:300008699"
    ]
},
  "bbox": [],
  "geometry": {"coordinates":[-82.5833,37.6333],"type":"Point"}
}