{
  "id": 2505343,
  "type": "Feature",
  "properties": {
    "tgn:hierarchy":[
        "tgn:2505343",
        "tgn:2000943",
        "tgn:1000001",
        "tgn:7012149",
        "tgn:7007520",
        "tgn:7029392"
    ],
    "tgn:id":2505343,
    "tgn:name":"Mellen Lake",
    "tgn:placetype":[
        "aat:300008680"
    ]
},
  "bbox": [],
  "geometry": {"coordinates":[-85.9667,46.5167],"type":"Point"}
}