<<<<<<< HEAD
{
  "id": 7359301,
  "type": "Feature",
  "properties": {
    "tgn:hierarchy":[
        "tgn:7359301",
        "tgn:1000001",
        "tgn:7005597",
        "tgn:7005560",
        "tgn:7029392"
    ],
    "tgn:id":7359301,
    "tgn:name":"Cinco de Mayo",
    "tgn:placetype":[
        "aat:300008347"
    ]
},
  "bbox": [],
  "geometry": {"coordinates":[-98.133333,23.45],"type":"Point"}
}
=======
{"geometry":{"type":"Point","coordinates":[-98.133333,23.450000]},"type":"Feature","properties":{"hierarchy":["tgn:7359301","tgn:1000001","tgn:7005597","tgn:7005560","tgn:7029392"],"placetype":["aat:300008347"],"id":7359301,"name:xx":"Cinco de Mayo"}}
>>>>>>> 03f74aca74312dbeaf24d7e61306dd6a786dc3d0
