{
  "id": 7521220,
  "type": "Feature",
  "properties": {
    "tgn:hierarchy":[
        "tgn:7521220",
        "tgn:7001242",
        "tgn:7016833",
        "tgn:1001083",
        "tgn:7029392"
    ],
    "tgn:id":7521220,
    "tgn:name:en":"Ab\u016b Dibb\u0101n, 'Ajrat",
    "tgn:placetype":[
        "aat:300008777"
    ]
},
  "bbox": [],
  "geometry": {"coordinates":[31.38,29.505833],"type":"Point"}
}