{
  "id": 2647050,
  "type": "Feature",
  "properties": {
    "tgn:hierarchy":[
        "tgn:2647050",
        "tgn:7002659",
        "tgn:1000001",
        "tgn:7012149",
        "tgn:2000029",
        "tgn:7029392"
    ],
    "tgn:id":2647050,
    "tgn:name":"Scharnagle Branch",
    "tgn:placetype":[
        "aat:300008699"
    ]
},
  "bbox": [],
  "geometry": {"coordinates":[-87.7333,34.3833],"type":"Point"}
}