{
  "id": 2720585,
  "type": "Feature",
  "properties": {
    "tgn:hierarchy":[
        "tgn:2720585",
        "tgn:1000001",
        "tgn:7006451",
        "tgn:2000093",
        "tgn:7012149",
        "tgn:7029392"
    ],
    "tgn:id":2720585,
    "tgn:name":"Thurlo Tank",
    "tgn:placetype":[
        "aat:300006191"
    ]
},
  "bbox": [],
  "geometry": {"coordinates":[-111.0167,34.1167],"type":"Point"}
}