{
  "id": 7490322,
  "type": "Feature",
  "properties": {
    "tgn:hierarchy":[
        "tgn:7490322",
        "tgn:1000004",
        "tgn:1000454",
        "tgn:1000141",
        "tgn:7029392"
    ],
    "tgn:id":7490322,
    "tgn:name":"Dazhulin Shan",
    "tgn:placetype":[
        "aat:300008795"
    ]
},
  "bbox": [],
  "geometry": {"coordinates":[121.849385,25.045313],"type":"Point"}
}