<<<<<<< HEAD
{
  "id": 2402961,
  "type": "Feature",
  "properties": {
    "tgn:hierarchy":[
        "tgn:2402961",
        "tgn:1000001",
        "tgn:1002249",
        "tgn:7012149",
        "tgn:7007710",
        "tgn:7029392"
    ],
    "tgn:id":2402961,
    "tgn:name":"Hough Mountain",
    "tgn:placetype":[
        "aat:300008798"
    ]
},
  "bbox": [],
  "geometry": {"coordinates":[-77.2667,40.9667],"type":"Point"}
}
=======
{"geometry":{"type":"Point","coordinates":[-77.266700,40.966700]},"type":"Feature","properties":{"hierarchy":["tgn:2402961","tgn:1000001","tgn:1002249","tgn:7012149","tgn:7007710","tgn:7029392"],"placetype":["aat:300008798"],"id":2402961,"name:xx":"Hough Mountain"}}
>>>>>>> 03f74aca74312dbeaf24d7e61306dd6a786dc3d0
