<<<<<<< HEAD
{
  "id": 2330306,
  "type": "Feature",
  "properties": {
    "tgn:hierarchy":[
        "tgn:2330306",
        "tgn:1000001",
        "tgn:7012149",
        "tgn:2001543",
        "tgn:7007709",
        "tgn:7029392"
    ],
    "tgn:id":2330306,
    "tgn:name":"Flat Bald Branch",
    "tgn:placetype":[
        "aat:300008699"
    ]
},
  "bbox": [],
  "geometry": {"coordinates":[-83.2,35.5167],"type":"Point"}
}
=======
{"geometry":{"type":"Point","coordinates":[-83.200000,35.516700]},"type":"Feature","properties":{"hierarchy":["tgn:2330306","tgn:1000001","tgn:7012149","tgn:2001543","tgn:7007709","tgn:7029392"],"placetype":["aat:300008699"],"id":2330306,"name:xx":"Flat Bald Branch"}}
>>>>>>> 03f74aca74312dbeaf24d7e61306dd6a786dc3d0
