<<<<<<< HEAD
{
  "id": 2760950,
  "type": "Feature",
  "properties": {
    "tgn:hierarchy":[
        "tgn:2760950",
        "tgn:1000001",
        "tgn:2000920",
        "tgn:7012149",
        "tgn:7007515",
        "tgn:7029392"
    ],
    "tgn:id":2760950,
    "tgn:name":"West Hue and Cry",
    "tgn:placetype":[
        "aat:300132348"
    ]
},
  "bbox": [],
  "geometry": {"coordinates":[-70.15,43.5167],"type":"Point"}
}
=======
{"geometry":{"type":"Point","coordinates":[-70.150000,43.516700]},"type":"Feature","properties":{"hierarchy":["tgn:2760950","tgn:1000001","tgn:2000920","tgn:7012149","tgn:7007515","tgn:7029392"],"placetype":["aat:300132348"],"id":2760950,"name:xx":"West Hue and Cry"}}
>>>>>>> 03f74aca74312dbeaf24d7e61306dd6a786dc3d0
