{
  "id": 2760950,
  "type": "Feature",
  "properties": {
    "tgn:hierarchy":[
        "tgn:2760950",
        "tgn:1000001",
        "tgn:2000920",
        "tgn:7012149",
        "tgn:7007515",
        "tgn:7029392"
    ],
    "tgn:id":2760950,
    "tgn:name":"West Hue and Cry",
    "tgn:placetype":[
        "aat:300132348"
    ]
},
  "bbox": [],
  "geometry": {"coordinates":[-70.15,43.5167],"type":"Point"}
}