{
  "id": 7436132,
  "type": "Feature",
  "properties": {
    "tgn:hierarchy":[
        "tgn:7436132",
        "tgn:1000001",
        "tgn:7005591",
        "tgn:7005560",
        "tgn:7029392"
    ],
    "tgn:id":7436132,
    "tgn:name":"Santos",
    "tgn:placetype":[
        "aat:300008347"
    ]
},
  "bbox": [],
  "geometry": {"coordinates":[-96.45,15.966667],"type":"Point"}
}