{
  "id": 7406754,
  "type": "Feature",
  "properties": {
    "tgn:hierarchy":[
        "tgn:7406754",
        "tgn:1000001",
        "tgn:1001906",
        "tgn:7005560",
        "tgn:7029392"
    ],
    "tgn:id":7406754,
    "tgn:name":"Laguna El Tule",
    "tgn:placetype":[
        "aat:300008347"
    ]
},
  "bbox": [],
  "geometry": {"coordinates":[-105.366667,22.316667],"type":"Point"}
}