{
  "id": 5002048,
  "type": "Feature",
  "properties": {
    "tgn:hierarchy":[
        "tgn:5002048",
        "tgn:7009084",
        "tgn:7003000",
        "tgn:1000003",
        "tgn:1000080",
        "tgn:7029392"
    ],
    "tgn:id":5002048,
    "tgn:name":"Villamagna",
    "tgn:placetype":[
        "aat:300008347"
    ]
},
  "bbox": [],
  "geometry": {"coordinates":[11.383333,43.766667],"type":"Point"}
}