{
  "id": 2564642,
  "type": "Feature",
  "properties": {
    "tgn:hierarchy":[
        "tgn:2564642",
        "tgn:1000001",
        "tgn:7012149",
        "tgn:2002034",
        "tgn:7007826",
        "tgn:7029392"
    ],
    "tgn:id":2564642,
    "tgn:name":"Packsaddle Hill",
    "tgn:placetype":[
        "aat:300008798"
    ]
},
  "bbox": [],
  "geometry": {"coordinates":[-99.1333,31.3333],"type":"Point"}
}