<<<<<<< HEAD
{
  "id": 2335871,
  "type": "Feature",
  "properties": {
    "tgn:hierarchy":[
        "tgn:2335871",
        "tgn:1000001",
        "tgn:2001024",
        "tgn:7012149",
        "tgn:7007521",
        "tgn:7029392"
    ],
    "tgn:id":2335871,
    "tgn:name":"Foss Lake",
    "tgn:placetype":[
        "aat:300008680"
    ]
},
  "bbox": [],
  "geometry": {"coordinates":[-96.05,46.0667],"type":"Point"}
}
=======
{"geometry":{"type":"Point","coordinates":[-96.050000,46.066700]},"type":"Feature","properties":{"hierarchy":["tgn:2335871","tgn:1000001","tgn:2001024","tgn:7012149","tgn:7007521","tgn:7029392"],"placetype":["aat:300008680"],"id":2335871,"name:xx":"Foss Lake"}}
>>>>>>> 03f74aca74312dbeaf24d7e61306dd6a786dc3d0
