{
  "id": 2497988,
  "type": "Feature",
  "properties": {
    "tgn:hierarchy":[
        "tgn:2497988",
        "tgn:1000001",
        "tgn:7012149",
        "tgn:2000393",
        "tgn:7007248",
        "tgn:7029392"
    ],
    "tgn:id":2497988,
    "tgn:name":"Maynard Lake",
    "tgn:placetype":[
        "aat:300006191"
    ]
},
  "bbox": [],
  "geometry": {"coordinates":[-83.8833,32.8833],"type":"Point"}
}