{
  "id": 7397559,
  "type": "Feature",
  "properties": {
    "tgn:hierarchy":[
        "tgn:7397559",
        "tgn:1000001",
        "tgn:7005599",
        "tgn:7005560",
        "tgn:7029392"
    ],
    "tgn:id":7397559,
    "tgn:name":"San Nicol\u00e1s",
    "tgn:placetype":[
        "aat:300008347"
    ]
},
  "bbox": [],
  "geometry": {"coordinates":[-95.533333,18.25],"type":"Point"}
}