{
  "id": 1071519,
  "type": "Feature",
  "properties": {
    "tgn:hierarchy":[
        "tgn:1071519",
        "tgn:1000004",
        "tgn:7002077",
        "tgn:1000111",
        "tgn:7029392"
    ],
    "tgn:id":1071519,
    "tgn:name":"Shanjiazhuang",
    "tgn:placetype":[
        "aat:300008347"
    ]
},
  "bbox": [],
  "geometry": {"coordinates":[115.75,38.8667],"type":"Point"}
}