<<<<<<< HEAD
{
  "id": 2256953,
  "type": "Feature",
  "properties": {
    "tgn:hierarchy":[
        "tgn:2256953",
        "tgn:1000001",
        "tgn:7012149",
        "tgn:2000852",
        "tgn:7007255",
        "tgn:7029392"
    ],
    "tgn:id":2256953,
    "tgn:name":"Corn Bread Branch",
    "tgn:placetype":[
        "aat:300008699"
    ]
},
  "bbox": [],
  "geometry": {"coordinates":[-84.2333,36.7],"type":"Point"}
}
=======
{"geometry":{"type":"Point","coordinates":[-84.233300,36.700000]},"type":"Feature","properties":{"hierarchy":["tgn:2256953","tgn:1000001","tgn:7012149","tgn:2000852","tgn:7007255","tgn:7029392"],"placetype":["aat:300008699"],"id":2256953,"name:xx":"Corn Bread Branch"}}
>>>>>>> 03f74aca74312dbeaf24d7e61306dd6a786dc3d0
