{
  "id": 7371989,
  "type": "Feature",
  "properties": {
    "tgn:hierarchy":[
        "tgn:7371989",
        "tgn:1001835",
        "tgn:1000001",
        "tgn:7005560",
        "tgn:7029392"
    ],
    "tgn:id":7371989,
    "tgn:name":"La Escondida",
    "tgn:placetype":[
        "aat:300008347"
    ]
},
  "bbox": [],
  "geometry": {"coordinates":[-114.883333,31.183333],"type":"Point"}
}