{
  "id": 2062391,
  "type": "Feature",
  "properties": {
    "tgn:hierarchy":[
        "tgn:2062391",
        "tgn:1000001",
        "tgn:7012149",
        "tgn:2001375",
        "tgn:7007525",
        "tgn:7029392"
    ],
    "tgn:id":2062391,
    "tgn:name":"Meadow Grove",
    "tgn:placetype":[
        "aat:300008347"
    ]
},
  "bbox": [],
  "geometry": {"coordinates":[-97.7333,42.0167],"type":"Point"}
}