{
  "id": 2753421,
  "type": "Feature",
  "properties": {
    "tgn:hierarchy":[
        "tgn:2753421",
        "tgn:1000001",
        "tgn:7012149",
        "tgn:1002758",
        "tgn:7007568",
        "tgn:7029392"
    ],
    "tgn:id":2753421,
    "tgn:name":"Waterhouse Creek",
    "tgn:placetype":[
        "aat:300008706"
    ]
},
  "bbox": [],
  "geometry": {"coordinates":[-76.35,43.2833],"type":"Point"}
}