{
  "id": 2384956,
  "type": "Feature",
  "properties": {
    "tgn:hierarchy":[
        "tgn:2384956",
        "tgn:1000001",
        "tgn:7012149",
        "tgn:2000972",
        "tgn:7007520",
        "tgn:7029392"
    ],
    "tgn:id":2384956,
    "tgn:name":"Helmer Creek",
    "tgn:placetype":[
        "aat:300008706"
    ]
},
  "bbox": [],
  "geometry": {"coordinates":[-85.7167,46.2667],"type":"Point"}
}