{
  "id": 7372017,
  "type": "Feature",
  "properties": {
    "tgn:hierarchy":[
        "tgn:7372017",
        "tgn:7005586",
        "tgn:1000001",
        "tgn:7005560",
        "tgn:7029392"
    ],
    "tgn:id":7372017,
    "tgn:name":"La Navidad",
    "tgn:placetype":[
        "aat:300008347"
    ]
},
  "bbox": [],
  "geometry": {"coordinates":[-103.366667,19.133333],"type":"Point"}
}