<<<<<<< HEAD
{
  "id": 2156337,
  "type": "Feature",
  "properties": {
    "tgn:hierarchy":[
        "tgn:2156337",
        "tgn:1000001",
        "tgn:7012149",
        "tgn:2002287",
        "tgn:7013961",
        "tgn:7029392"
    ],
    "tgn:id":2156337,
    "tgn:name":"Bearpen Hollow",
    "tgn:placetype":[
        "aat:300008761"
    ]
},
  "bbox": [],
  "geometry": {"coordinates":[-79.7333,38.4],"type":"Point"}
}
=======
{"geometry":{"type":"Point","coordinates":[-79.733300,38.400000]},"type":"Feature","properties":{"hierarchy":["tgn:2156337","tgn:1000001","tgn:7012149","tgn:2002287","tgn:7013961","tgn:7029392"],"placetype":["aat:300008761"],"id":2156337,"name:xx":"Bearpen Hollow"}}
>>>>>>> 03f74aca74312dbeaf24d7e61306dd6a786dc3d0
