<<<<<<< HEAD
{
  "id": 7051969,
  "type": "Feature",
  "properties": {
    "tgn:hierarchy":[
        "tgn:7051969",
        "tgn:7003007",
        "tgn:1000003",
        "tgn:7002997",
        "tgn:1000080",
        "tgn:7029392"
    ],
    "tgn:id":7051969,
    "tgn:name":"Mozzecane",
    "tgn:placetype":[
        "aat:300008347"
    ]
},
  "bbox": [],
  "geometry": {"coordinates":[10.816667,45.3],"type":"Point"}
}
=======
{"geometry":{"type":"Point","coordinates":[10.816667,45.300000]},"type":"Feature","properties":{"hierarchy":["tgn:7051969","tgn:7003007","tgn:1000003","tgn:7002997","tgn:1000080","tgn:7029392"],"placetype":["aat:300008347"],"id":7051969,"name:xx":"Mozzecane"}}
>>>>>>> 03f74aca74312dbeaf24d7e61306dd6a786dc3d0
