{
  "id": 7533316,
  "type": "Feature",
  "properties": {
    "tgn:hierarchy":[
        "tgn:7533316",
        "tgn:7001242",
        "tgn:7016833",
        "tgn:1001123",
        "tgn:7029392"
    ],
    "tgn:id":7533316,
    "tgn:name":"\u1e28alq al Kirsah, Jaz\u012brat",
    "tgn:placetype":[
        "aat:300008791"
    ]
},
  "bbox": [],
  "geometry": {"coordinates":[32.040828,31.279826],"type":"Point"}
}