{
  "id": 2663841,
  "type": "Feature",
  "properties": {
    "tgn:hierarchy":[
        "tgn:2663841",
        "tgn:1000001",
        "tgn:2001818",
        "tgn:7012149",
        "tgn:7007713",
        "tgn:7029392"
    ],
    "tgn:id":2663841,
    "tgn:name":"Silver Lake",
    "tgn:placetype":[
        "aat:300008680"
    ]
},
  "bbox": [],
  "geometry": {"coordinates":[-97.3833,44.0333],"type":"Point"}
}