{
  "id": 2218403,
  "type": "Feature",
  "properties": {
    "tgn:hierarchy":[
        "tgn:2218403",
        "tgn:1000001",
        "tgn:7012149",
        "tgn:2001284",
        "tgn:7007524",
        "tgn:7029392"
    ],
    "tgn:id":2218403,
    "tgn:name":"Candle Mountain",
    "tgn:placetype":[
        "aat:300008798"
    ]
},
  "bbox": [],
  "geometry": {"coordinates":[-111.7667,46.8833],"type":"Point"}
}