{
  "id": 2302653,
  "type": "Feature",
  "properties": {
    "tgn:hierarchy":[
        "tgn:2302653",
        "tgn:1000001",
        "tgn:7012149",
        "tgn:7007157",
        "tgn:1002706",
        "tgn:7029392"
    ],
    "tgn:id":2302653,
    "tgn:name":"Duvall Lake",
    "tgn:placetype":[
        "aat:300006191"
    ]
},
  "bbox": [],
  "geometry": {"coordinates":[-122.4667,38.6333],"type":"Point"}
}