{
  "id": 7302429,
  "type": "Feature",
  "properties": {
    "tgn:hierarchy":[
        "tgn:7302429",
        "tgn:7008911",
        "tgn:1000003",
        "tgn:7002763",
        "tgn:1000095",
        "tgn:7029392"
    ],
    "tgn:id":7302429,
    "tgn:name":"Orcado de Cuevas, Islote",
    "tgn:placetype":[
        "aat:300008791"
    ]
},
  "bbox": [],
  "geometry": {"coordinates":[-4.95,43.45],"type":"Point"}
}