{
  "id": 2022195,
  "type": "Feature",
  "properties": {
    "tgn:hierarchy":[
        "tgn:2022195",
        "tgn:1000001",
        "tgn:7012149",
        "tgn:2000435",
        "tgn:7007248",
        "tgn:7029392"
    ],
    "tgn:id":2022195,
    "tgn:name":"Blairsville",
    "tgn:placetype":[
        "aat:300008347"
    ]
},
  "bbox": [],
  "geometry": {"coordinates":[-83.95,34.8667],"type":"Point"}
}