{
  "id": 7218003,
  "type": "Feature",
  "properties": {
    "tgn:hierarchy":[
        "tgn:7218003",
        "tgn:7002752",
        "tgn:7001399",
        "tgn:1000003",
        "tgn:1000074",
        "tgn:7029392"
    ],
    "tgn:id":7218003,
    "tgn:name":"Gen\u00e9sion",
    "tgn:placetype":[
        "aat:300008347"
    ]
},
  "bbox": [],
  "geometry": {"coordinates":[21.585278,39.578611],"type":"Point"}
}