{
  "id": 7177451,
  "type": "Feature",
  "properties": {
    "tgn:hierarchy":[
        "tgn:7177451",
        "tgn:1000003",
        "tgn:7000094",
        "tgn:7000084",
        "tgn:7029392"
    ],
    "tgn:id":7177451,
    "tgn:name":"G\u00fcritz",
    "tgn:placetype":[
        "aat:300008347"
    ]
},
  "bbox": [],
  "geometry": {"coordinates":[11.483333,53.266667],"type":"Point"}
}