<<<<<<< HEAD
{
  "id": 2403702,
  "type": "Feature",
  "properties": {
    "tgn:hierarchy":[
        "tgn:2403702",
        "tgn:1000001",
        "tgn:7012149",
        "tgn:2002382",
        "tgn:7007923",
        "tgn:7029392"
    ],
    "tgn:id":2403702,
    "tgn:name":"Howard Lake",
    "tgn:placetype":[
        "aat:300008680"
    ]
},
  "bbox": [],
  "geometry": {"coordinates":[-109.45,42.9],"type":"Point"}
}
=======
{"geometry":{"type":"Point","coordinates":[-109.450000,42.900000]},"type":"Feature","properties":{"hierarchy":["tgn:2403702","tgn:1000001","tgn:7012149","tgn:2002382","tgn:7007923","tgn:7029392"],"placetype":["aat:300008680"],"id":2403702,"name:xx":"Howard Lake"}}
>>>>>>> 03f74aca74312dbeaf24d7e61306dd6a786dc3d0
