<<<<<<< HEAD
{
  "id": 2151456,
  "type": "Feature",
  "properties": {
    "tgn:hierarchy":[
        "tgn:2151456",
        "tgn:1000001",
        "tgn:7012149",
        "tgn:1002392",
        "tgn:7007157",
        "tgn:7029392"
    ],
    "tgn:id":2151456,
    "tgn:name":"Bathtub Lake",
    "tgn:placetype":[
        "aat:300008680"
    ]
},
  "bbox": [],
  "geometry": {"coordinates":[-119.0333,37.45],"type":"Point"}
}
=======
{"geometry":{"type":"Point","coordinates":[-119.033300,37.450000]},"type":"Feature","properties":{"hierarchy":["tgn:2151456","tgn:1000001","tgn:7012149","tgn:1002392","tgn:7007157","tgn:7029392"],"placetype":["aat:300008680"],"id":2151456,"name:xx":"Bathtub Lake"}}
>>>>>>> 03f74aca74312dbeaf24d7e61306dd6a786dc3d0
