{
  "id": 2452956,
  "type": "Feature",
  "properties": {
    "tgn:hierarchy":[
        "tgn:2452956",
        "tgn:1000001",
        "tgn:7012149",
        "tgn:7018871",
        "tgn:7007920",
        "tgn:7029392"
    ],
    "tgn:id":2452956,
    "tgn:name":"Little Calligan Lake",
    "tgn:placetype":[
        "aat:300008680"
    ]
},
  "bbox": [],
  "geometry": {"coordinates":[-121.6333,47.5667],"type":"Point"}
}