{
  "id": 2446001,
  "type": "Feature",
  "properties": {
    "tgn:hierarchy":[
        "tgn:2446001",
        "tgn:1000001",
        "tgn:1002452",
        "tgn:7012149",
        "tgn:7007240",
        "tgn:7029392"
    ],
    "tgn:id":2446001,
    "tgn:name":"Lettis Creek",
    "tgn:placetype":[
        "aat:300008706"
    ]
},
  "bbox": [],
  "geometry": {"coordinates":[-81.9333,27.55],"type":"Point"}
}