{
  "id": 7472723,
  "type": "Feature",
  "properties": {
    "tgn:hierarchy":[
        "tgn:7472723",
        "tgn:7001004",
        "tgn:1000004",
        "tgn:1000141",
        "tgn:7029392"
    ],
    "tgn:id":7472723,
    "tgn:name":"Zhongzhuang",
    "tgn:placetype":[
        "aat:300008347"
    ]
},
  "bbox": [],
  "geometry": {"coordinates":[120.504444,22.941111],"type":"Point"}
}