{
  "id": 7074056,
  "type": "Feature",
  "properties": {
    "tgn:hierarchy":[
        "tgn:7074056",
        "tgn:7003669",
        "tgn:1000003",
        "tgn:7000084",
        "tgn:7029392"
    ],
    "tgn:id":7074056,
    "tgn:name":"Taigscheid",
    "tgn:placetype":[
        "aat:300008347"
    ]
},
  "bbox": [],
  "geometry": {"coordinates":[12.116667,47.766667],"type":"Point"}
}