{
  "id": 2242540,
  "type": "Feature",
  "properties": {
    "tgn:hierarchy":[
        "tgn:2242540",
        "tgn:7006450",
        "tgn:1000001",
        "tgn:2124053",
        "tgn:7012149",
        "tgn:7029392"
    ],
    "tgn:id":2242540,
    "tgn:name":"Clear Creek",
    "tgn:placetype":[
        "aat:300008706"
    ]
},
  "bbox": [],
  "geometry": {"coordinates":[-148.1833,62.2167],"type":"Point"}
}