<<<<<<< HEAD
{
  "id": 2158198,
  "type": "Feature",
  "properties": {
    "tgn:hierarchy":[
        "tgn:2158198",
        "tgn:1000001",
        "tgn:7012149",
        "tgn:2001708",
        "tgn:7007708",
        "tgn:7029392"
    ],
    "tgn:id":2158198,
    "tgn:name":"Beaver Reservoir",
    "tgn:placetype":[
        "aat:300006191"
    ]
},
  "bbox": [],
  "geometry": {"coordinates":[-119.55,43.9833],"type":"Point"}
}
=======
{"geometry":{"type":"Point","coordinates":[-119.550000,43.983300]},"type":"Feature","properties":{"hierarchy":["tgn:2158198","tgn:1000001","tgn:7012149","tgn:2001708","tgn:7007708","tgn:7029392"],"placetype":["aat:300006191"],"id":2158198,"name:xx":"Beaver Reservoir"}}
>>>>>>> 03f74aca74312dbeaf24d7e61306dd6a786dc3d0
