{
  "id": 2229739,
  "type": "Feature",
  "properties": {
    "tgn:hierarchy":[
        "tgn:2229739",
        "tgn:1000001",
        "tgn:1002286",
        "tgn:7012149",
        "tgn:7007710",
        "tgn:7029392"
    ],
    "tgn:id":2229739,
    "tgn:name":"Cedar Spring",
    "tgn:placetype":[
        "aat:300008697"
    ]
},
  "bbox": [],
  "geometry": {"coordinates":[-77.5167,41.0333],"type":"Point"}
}