{
  "id": 7286389,
  "type": "Feature",
  "properties": {
    "tgn:hierarchy":[
        "tgn:7286389",
        "tgn:1001657",
        "tgn:1000049",
        "tgn:1000002",
        "tgn:7029392"
    ],
    "tgn:id":7286389,
    "tgn:name":"Higuera, Quebrada",
    "tgn:placetype":[
        "aat:300008699"
    ]
},
  "bbox": [],
  "geometry": {"coordinates":[-71.366667,-31.833333],"type":"Point"}
}