{
  "id": 2265329,
  "type": "Feature",
  "properties": {
    "tgn:hierarchy":[
        "tgn:2265329",
        "tgn:1000001",
        "tgn:7012149",
        "tgn:7007157",
        "tgn:1002957",
        "tgn:7029392"
    ],
    "tgn:id":2265329,
    "tgn:name":"Crane Creek",
    "tgn:placetype":[
        "aat:300008706"
    ]
},
  "bbox": [],
  "geometry": {"coordinates":[-119.9333,37.9833],"type":"Point"}
}