{
  "id": 2241415,
  "type": "Feature",
  "properties": {
    "tgn:hierarchy":[
        "tgn:2241415",
        "tgn:1000001",
        "tgn:7012149",
        "tgn:2000226",
        "tgn:7007158",
        "tgn:7029392"
    ],
    "tgn:id":2241415,
    "tgn:name":"Clark Reservoir",
    "tgn:placetype":[
        "aat:300006191"
    ]
},
  "bbox": [],
  "geometry": {"coordinates":[-104.9667,40.7333],"type":"Point"}
}