{
  "id": 1051707,
  "type": "Feature",
  "properties": {
    "tgn:hierarchy":[
        "tgn:1051707",
        "tgn:7011438",
        "tgn:1000004",
        "tgn:7006646",
        "tgn:7029392"
    ],
    "tgn:id":1051707,
    "tgn:name":"Shollar",
    "tgn:placetype":[
        "aat:300008347"
    ]
},
  "bbox": [],
  "geometry": {"coordinates":[48.6667,41.6333],"type":"Point"}
}