{
  "id": 7570333,
  "type": "Feature",
  "properties": {
    "tgn:hierarchy":[
        "tgn:7570333",
        "tgn:1000004",
        "tgn:1001871",
        "tgn:7000198",
        "tgn:7029392"
    ],
    "tgn:id":7570333,
    "tgn:name:en":"Ghous Ali S\u0101hib",
    "tgn:placetype":[
        "aat:300008347"
    ]
},
  "bbox": [],
  "geometry": {"coordinates":[76.9751,29.378923],"type":"Point"}
}