{
  "id": 7515828,
  "type": "Feature",
  "properties": {
    "tgn:hierarchy":[
        "tgn:7515828",
        "tgn:1009227",
        "tgn:1000226",
        "tgn:7018437",
        "tgn:1000006",
        "tgn:7029392"
    ],
    "tgn:id":7515828,
    "tgn:name:en":"Little Cattle Gully",
    "tgn:placetype":[
        "aat:300008767"
    ]
},
  "bbox": [],
  "geometry": {"coordinates":[169.933333,-44.516667],"type":"Point"}
}