{
  "id": 7311351,
  "type": "Feature",
  "properties": {
    "tgn:hierarchy":[
        "tgn:7311351",
        "tgn:1001768",
        "tgn:1000049",
        "tgn:1000002",
        "tgn:7029392"
    ],
    "tgn:id":7311351,
    "tgn:name":"Negra, Quebrada",
    "tgn:placetype":[
        "aat:300008699"
    ]
},
  "bbox": [],
  "geometry": {"coordinates":[-80.733333,-33.716667],"type":"Point"}
}