{
  "id": 2461140,
  "type": "Feature",
  "properties": {
    "tgn:hierarchy":[
        "tgn:2461140",
        "tgn:7002659",
        "tgn:1000001",
        "tgn:7012149",
        "tgn:7029392"
    ],
    "tgn:id":2461140,
    "tgn:name":"Little Spring Creek",
    "tgn:placetype":[
        "aat:300008706"
    ]
},
  "bbox": [],
  "geometry": {"coordinates":[-87.2667,33.9833],"type":"Point"}
}