{
  "id": 2054191,
  "type": "Feature",
  "properties": {
    "tgn:hierarchy":[
        "tgn:2054191",
        "tgn:2001004",
        "tgn:1000001",
        "tgn:7012149",
        "tgn:7007521",
        "tgn:7029392"
    ],
    "tgn:id":2054191,
    "tgn:name":"Correll",
    "tgn:placetype":[
        "aat:300008347"
    ]
},
  "bbox": [],
  "geometry": {"coordinates":[-96.15,45.2167],"type":"Point"}
}