{
  "id": 7282109,
  "type": "Feature",
  "properties": {
    "tgn:hierarchy":[
        "tgn:7282109",
        "tgn:1001657",
        "tgn:1000049",
        "tgn:1000002",
        "tgn:7029392"
    ],
    "tgn:id":7282109,
    "tgn:name":"Soruco, Quebrada",
    "tgn:placetype":[
        "aat:300008699"
    ]
},
  "bbox": [],
  "geometry": {"coordinates":[-71.083333,-31.083333],"type":"Point"}
}