{
  "id": 1088385,
  "type": "Feature",
  "properties": {
    "tgn:hierarchy":[
        "tgn:1088385",
        "tgn:7001242",
        "tgn:1000981",
        "tgn:1000155",
        "tgn:7029392"
    ],
    "tgn:id":1088385,
    "tgn:name":"Kitessa",
    "tgn:placetype":[
        "aat:300008347"
    ]
},
  "bbox": [],
  "geometry": {"coordinates":[25.3667,5.3667],"type":"Point"}
}