{
  "id": 7383681,
  "type": "Feature",
  "properties": {
    "tgn:hierarchy":[
        "tgn:7383681",
        "tgn:1000001",
        "tgn:7005596",
        "tgn:7005560",
        "tgn:7029392"
    ],
    "tgn:id":7383681,
    "tgn:name":"Nuevo Esperanza",
    "tgn:placetype":[
        "aat:300008347"
    ]
},
  "bbox": [],
  "geometry": {"coordinates":[-91.066667,17.333333],"type":"Point"}
}