{
  "id": 7208100,
  "type": "Feature",
  "properties": {
    "tgn:hierarchy":[
        "tgn:7208100",
        "tgn:1000003",
        "tgn:7000094",
        "tgn:7000084",
        "tgn:7029392"
    ],
    "tgn:id":7208100,
    "tgn:name":"Consrade",
    "tgn:placetype":[
        "aat:300008347"
    ]
},
  "bbox": [],
  "geometry": {"coordinates":[11.466667,53.566667],"type":"Point"}
}