{
  "id": 7307887,
  "type": "Feature",
  "properties": {
    "tgn:hierarchy":[
        "tgn:7307887",
        "tgn:1001630",
        "tgn:1000049",
        "tgn:1000002",
        "tgn:7029392"
    ],
    "tgn:id":7307887,
    "tgn:name":"Negra, Punta",
    "tgn:placetype":[
        "aat:300386846"
    ]
},
  "bbox": [],
  "geometry": {"coordinates":[-71.216667,-28.416667],"type":"Point"}
}