{
  "id": 2426012,
  "type": "Feature",
  "properties": {
    "tgn:hierarchy":[
        "tgn:2426012",
        "tgn:1000001",
        "tgn:2000864",
        "tgn:7012149",
        "tgn:7007256",
        "tgn:7029392"
    ],
    "tgn:id":2426012,
    "tgn:name":"Jones Brake",
    "tgn:placetype":[
        "aat:300008905"
    ]
},
  "bbox": [],
  "geometry": {"coordinates":[-91.9667,32.0333],"type":"Point"}
}