{
  "id": 7404094,
  "type": "Feature",
  "properties": {
    "tgn:hierarchy":[
        "tgn:7404094",
        "tgn:7016644",
        "tgn:1000001",
        "tgn:7005560",
        "tgn:7029392"
    ],
    "tgn:id":7404094,
    "tgn:name":"El Tecu\u00e1n, Estero",
    "tgn:placetype":[
        "aat:300185707"
    ]
},
  "bbox": [],
  "geometry": {"coordinates":[-103.8875,18.808333],"type":"Point"}
}