<<<<<<< HEAD
{
  "id": 7470902,
  "type": "Feature",
  "properties": {
    "tgn:hierarchy":[
        "tgn:7470902",
        "tgn:7487020",
        "tgn:1000004",
        "tgn:1000141",
        "tgn:7029392"
    ],
    "tgn:id":7470902,
    "tgn:name":"Ergangping",
    "tgn:placetype":[
        "aat:300008347"
    ]
},
  "bbox": [],
  "geometry": {"coordinates":[120.8456,24.5668],"type":"Point"}
}
=======
{"geometry":{"type":"Point","coordinates":[120.845600,24.566800]},"type":"Feature","properties":{"hierarchy":["tgn:7470902","tgn:7487020","tgn:1000004","tgn:1000141","tgn:7029392"],"placetype":["aat:300008347"],"id":7470902,"name:xx":"Ergangping"}}
>>>>>>> 03f74aca74312dbeaf24d7e61306dd6a786dc3d0
