{
  "id": 7470902,
  "type": "Feature",
  "properties": {
    "tgn:hierarchy":[
        "tgn:7470902",
        "tgn:7487020",
        "tgn:1000004",
        "tgn:1000141",
        "tgn:7029392"
    ],
    "tgn:id":7470902,
    "tgn:name":"Ergangping",
    "tgn:placetype":[
        "aat:300008347"
    ]
},
  "bbox": [],
  "geometry": {"coordinates":[120.8456,24.5668],"type":"Point"}
}