<<<<<<< HEAD
{
  "id": 2764963,
  "type": "Feature",
  "properties": {
    "tgn:hierarchy":[
        "tgn:2764963",
        "tgn:1000001",
        "tgn:7012149",
        "tgn:1002742",
        "tgn:7007920",
        "tgn:7029392"
    ],
    "tgn:id":2764963,
    "tgn:name":"Whisky Cache Creek",
    "tgn:placetype":[
        "aat:300008706"
    ]
},
  "bbox": [],
  "geometry": {"coordinates":[-119.35,48.8167],"type":"Point"}
}
=======
{"geometry":{"type":"Point","coordinates":[-119.350000,48.816700]},"type":"Feature","properties":{"hierarchy":["tgn:2764963","tgn:1000001","tgn:7012149","tgn:1002742","tgn:7007920","tgn:7029392"],"placetype":["aat:300008706"],"id":2764963,"name:xx":"Whisky Cache Creek"}}
>>>>>>> 03f74aca74312dbeaf24d7e61306dd6a786dc3d0
