{
  "id": 7230926,
  "type": "Feature",
  "properties": {
    "tgn:hierarchy":[
        "tgn:7230926",
        "tgn:7002739",
        "tgn:7017076",
        "tgn:1000003",
        "tgn:1000074",
        "tgn:7029392"
    ],
    "tgn:id":7230926,
    "tgn:name":"Kharam\u00f3s",
    "tgn:placetype":[
        "aat:300008347"
    ]
},
  "bbox": [],
  "geometry": {"coordinates":[22.983333,37.55],"type":"Point"}
}