{
  "id": 2500613,
  "type": "Feature",
  "properties": {
    "tgn:hierarchy":[
        "tgn:2500613",
        "tgn:2000090",
        "tgn:1000001",
        "tgn:7006451",
        "tgn:7012149",
        "tgn:7029392"
    ],
    "tgn:id":2500613,
    "tgn:name":"McDonald Tank",
    "tgn:placetype":[
        "aat:300006191"
    ]
},
  "bbox": [],
  "geometry": {"coordinates":[-109.55,33.6333],"type":"Point"}
}