{
  "id": 2735904,
  "type": "Feature",
  "properties": {
    "tgn:hierarchy":[
        "tgn:2735904",
        "tgn:1000001",
        "tgn:7012149",
        "tgn:1002565",
        "tgn:7007252",
        "tgn:7029392"
    ],
    "tgn:id":2735904,
    "tgn:name":"Twin Lakes",
    "tgn:placetype":[
        "aat:300008680"
    ]
},
  "bbox": [],
  "geometry": {"coordinates":[-85.45,41.7167],"type":"Point"}
}