{
  "id": 2401061,
  "type": "Feature",
  "properties": {
    "tgn:hierarchy":[
        "tgn:2401061",
        "tgn:1000001",
        "tgn:7012149",
        "tgn:7007157",
        "tgn:2000190",
        "tgn:7029392"
    ],
    "tgn:id":2401061,
    "tgn:name":"Horse Trough Creek",
    "tgn:placetype":[
        "aat:300008706"
    ]
},
  "bbox": [],
  "geometry": {"coordinates":[-122.75,39.8167],"type":"Point"}
}