{
  "id": 7227635,
  "type": "Feature",
  "properties": {
    "tgn:hierarchy":[
        "tgn:7227635",
        "tgn:7011164",
        "tgn:7002674",
        "tgn:1000003",
        "tgn:1000074",
        "tgn:7029392"
    ],
    "tgn:id":7227635,
    "tgn:name":"Kont\u00e1ki, \u00c1kra",
    "tgn:placetype":[
        "aat:300008850"
    ]
},
  "bbox": [],
  "geometry": {"coordinates":[26.740833,37.811944],"type":"Point"}
}