{
  "id": 7458371,
  "type": "Feature",
  "properties": {
    "tgn:hierarchy":[
        "tgn:7458371",
        "tgn:7002445",
        "tgn:1000003",
        "tgn:7008174",
        "tgn:7008591",
        "tgn:7029392"
    ],
    "tgn:id":7458371,
    "tgn:name:en":"Moddershall",
    "tgn:placetype":[
        "aat:300008347"
    ]
},
  "bbox": [],
  "geometry": {"coordinates":[-2.116667,52.933333],"type":"Point"}
}