{
  "id": 2139294,
  "type": "Feature",
  "properties": {
    "tgn:hierarchy":[
        "tgn:2139294",
        "tgn:1000001",
        "tgn:7012149",
        "tgn:1003018",
        "tgn:7007919",
        "tgn:7029392"
    ],
    "tgn:id":2139294,
    "tgn:name":"Asparagus Point",
    "tgn:placetype":[
        "aat:300008850"
    ]
},
  "bbox": [],
  "geometry": {"coordinates":[-76.75,38.1333],"type":"Point"}
}