{
  "id": 7184649,
  "type": "Feature",
  "properties": {
    "tgn:hierarchy":[
        "tgn:7184649",
        "tgn:7003669",
        "tgn:1000003",
        "tgn:7000084",
        "tgn:7029392"
    ],
    "tgn:id":7184649,
    "tgn:name":"Grattstadt",
    "tgn:placetype":[
        "aat:300008347"
    ]
},
  "bbox": [],
  "geometry": {"coordinates":[10.833333,50.383333],"type":"Point"}
}