{
  "id": 2284770,
  "type": "Feature",
  "properties": {
    "tgn:hierarchy":[
        "tgn:2284770",
        "tgn:1000001",
        "tgn:7012149",
        "tgn:1003020",
        "tgn:7007920",
        "tgn:7029392"
    ],
    "tgn:id":2284770,
    "tgn:name":"Despair, Mount",
    "tgn:placetype":[
        "aat:300008798"
    ]
},
  "bbox": [],
  "geometry": {"coordinates":[-121.3667,48.7333],"type":"Point"}
}