<<<<<<< HEAD
{
  "id": 2153084,
  "type": "Feature",
  "properties": {
    "tgn:hierarchy":[
        "tgn:2153084",
        "tgn:1000001",
        "tgn:7012149",
        "tgn:2001288",
        "tgn:7007524",
        "tgn:7029392"
    ],
    "tgn:id":2153084,
    "tgn:name":"Beacon Light Mine",
    "tgn:placetype":[
        "aat:300000390"
    ]
},
  "bbox": [],
  "geometry": {"coordinates":[-112.5,45.6],"type":"Point"}
}
=======
{"geometry":{"type":"Point","coordinates":[-112.500000,45.600000]},"type":"Feature","properties":{"hierarchy":["tgn:2153084","tgn:1000001","tgn:7012149","tgn:2001288","tgn:7007524","tgn:7029392"],"placetype":["aat:300000390"],"id":2153084,"name:xx":"Beacon Light Mine"}}
>>>>>>> 03f74aca74312dbeaf24d7e61306dd6a786dc3d0
