{
  "id": 7429127,
  "type": "Feature",
  "properties": {
    "tgn:hierarchy":[
        "tgn:7429127",
        "tgn:1001853",
        "tgn:1000001",
        "tgn:7005560",
        "tgn:7029392"
    ],
    "tgn:id":7429127,
    "tgn:name":"Colorado, Cerro",
    "tgn:placetype":[
        "aat:300008795"
    ]
},
  "bbox": [],
  "geometry": {"coordinates":[-102.183333,29.233333],"type":"Point"}
}