{
  "id": 2564973,
  "type": "Feature",
  "properties": {
    "tgn:hierarchy":[
        "tgn:2564973",
        "tgn:1000001",
        "tgn:7012149",
        "tgn:1002553",
        "tgn:7007920",
        "tgn:7029392"
    ],
    "tgn:id":2564973,
    "tgn:name":"Page Canyon",
    "tgn:placetype":[
        "aat:300008761"
    ]
},
  "bbox": [],
  "geometry": {"coordinates":[-120.75,47.0167],"type":"Point"}
}