{
  "id": 7278783,
  "type": "Feature",
  "properties": {
    "tgn:hierarchy":[
        "tgn:7278783",
        "tgn:1001699",
        "tgn:1000049",
        "tgn:1000002",
        "tgn:7029392"
    ],
    "tgn:id":7278783,
    "tgn:name":"Santo Domingo, Sierra",
    "tgn:placetype":[
        "aat:300008795"
    ]
},
  "bbox": [],
  "geometry": {"coordinates":[-72.416667,-41.166667],"type":"Point"}
}