{
  "id": 7324377,
  "type": "Feature",
  "properties": {
    "tgn:hierarchy":[
        "tgn:7324377",
        "tgn:7002831",
        "tgn:1000003",
        "tgn:7002786",
        "tgn:1000095",
        "tgn:7029392"
    ],
    "tgn:id":7324377,
    "tgn:name":"San Gil, R\u00edo de",
    "tgn:placetype":[
        "aat:300008699"
    ]
},
  "bbox": [],
  "geometry": {"coordinates":[-6.816667,42.333333],"type":"Point"}
}