{
  "id": 7491160,
  "type": "Feature",
  "properties": {
    "tgn:hierarchy":[
        "tgn:7491160",
        "tgn:1000004",
        "tgn:7491221",
        "tgn:1000141",
        "tgn:7029392"
    ],
    "tgn:id":7491160,
    "tgn:name":"Shizishi Shan",
    "tgn:placetype":[
        "aat:300008798"
    ]
},
  "bbox": [],
  "geometry": {"coordinates":[120.906111,22.403611],"type":"Point"}
}