<<<<<<< HEAD
{
  "id": 7377407,
  "type": "Feature",
  "properties": {
    "tgn:hierarchy":[
        "tgn:7377407",
        "tgn:7005580",
        "tgn:1000001",
        "tgn:7005560",
        "tgn:7029392"
    ],
    "tgn:id":7377407,
    "tgn:name":"La Soledad",
    "tgn:placetype":[
        "aat:300008347"
    ]
},
  "bbox": [],
  "geometry": {"coordinates":[-93.333333,17.983333],"type":"Point"}
}
=======
{"geometry":{"type":"Point","coordinates":[-93.333333,17.983333]},"type":"Feature","properties":{"hierarchy":["tgn:7377407","tgn:7005580","tgn:1000001","tgn:7005560","tgn:7029392"],"placetype":["aat:300008347"],"id":7377407,"name:xx":"La Soledad"}}
>>>>>>> 03f74aca74312dbeaf24d7e61306dd6a786dc3d0
