{
  "id": 7074398,
  "type": "Feature",
  "properties": {
    "tgn:hierarchy":[
        "tgn:7074398",
        "tgn:7003669",
        "tgn:1000003",
        "tgn:7000084",
        "tgn:7029392"
    ],
    "tgn:id":7074398,
    "tgn:name":"Strass",
    "tgn:placetype":[
        "aat:300000206"
    ]
},
  "bbox": [],
  "geometry": {"coordinates":[12.75,48.516667],"type":"Point"}
}