{
  "id": 7224132,
  "type": "Feature",
  "properties": {
    "tgn:hierarchy":[
        "tgn:7224132",
        "tgn:7002680",
        "tgn:7001395",
        "tgn:1000003",
        "tgn:1000074",
        "tgn:7029392"
    ],
    "tgn:id":7224132,
    "tgn:name":"Pirg\u00e1kion",
    "tgn:placetype":[
        "aat:300008347"
    ]
},
  "bbox": [],
  "geometry": {"coordinates":[22.066667,38.166667],"type":"Point"}
}