{
  "id": 7572221,
  "type": "Feature",
  "properties": {
    "tgn:hierarchy":[
        "tgn:7572221",
        "tgn:1000004",
        "tgn:7000198",
        "tgn:7016788",
        "tgn:7029392"
    ],
    "tgn:id":7572221,
    "tgn:name:en":"Jh\u0101l\u0101mand",
    "tgn:placetype":[
        "aat:300008347"
    ]
},
  "bbox": [],
  "geometry": {"coordinates":[73.065959,26.207198],"type":"Point"}
}