{
  "id": 7201811,
  "type": "Feature",
  "properties": {
    "tgn:hierarchy":[
        "tgn:7201811",
        "tgn:7003669",
        "tgn:1000003",
        "tgn:7000084",
        "tgn:7029392"
    ],
    "tgn:id":7201811,
    "tgn:name":"Breiter Filz",
    "tgn:placetype":[
        "aat:300055621"
    ]
},
  "bbox": [],
  "geometry": {"coordinates":[11.016667,47.683333],"type":"Point"}
}