{
  "id": 2098420,
  "type": "Feature",
  "properties": {
    "tgn:hierarchy":[
        "tgn:2098420",
        "tgn:1000001",
        "tgn:7017496",
        "tgn:7012149",
        "tgn:2001869",
        "tgn:7007825",
        "tgn:7029392"
    ],
    "tgn:id":2098420,
    "tgn:name":"Rollingwood",
    "tgn:placetype":[
        "aat:300000745"
    ]
},
  "bbox": [],
  "geometry": {"coordinates":[-85.2167,35.05],"type":"Point"}
}