{
  "id": 7555684,
  "type": "Feature",
  "properties": {
    "tgn:hierarchy":[
        "tgn:7555684",
        "tgn:1000004",
        "tgn:7000198",
        "tgn:7016788",
        "tgn:7029392"
    ],
    "tgn:id":7555684,
    "tgn:name:en":"Mandor",
    "tgn:placetype":[
        "aat:300008347"
    ]
},
  "bbox": [],
  "geometry": {"coordinates":[73.04408,26.348625],"type":"Point"}
}