{
  "id": 2319979,
  "type": "Feature",
  "properties": {
    "tgn:hierarchy":[
        "tgn:2319979",
        "tgn:1000001",
        "tgn:7012149",
        "tgn:7029392"
    ],
    "tgn:id":2319979,
    "tgn:name":"Evans Creek",
    "tgn:placetype":[
        "aat:300008706"
    ]
},
  "bbox": [],
  "geometry": {"coordinates":[-84.8167,39.8667],"type":"Point"}
}