{
  "id": 2462672,
  "type": "Feature",
  "properties": {
    "tgn:hierarchy":[
        "tgn:2462672",
        "tgn:1000001",
        "tgn:7012149",
        "tgn:2001302",
        "tgn:7007524",
        "tgn:7029392"
    ],
    "tgn:id":2462672,
    "tgn:name":"Little Wolf Creek",
    "tgn:placetype":[
        "aat:300008706"
    ]
},
  "bbox": [],
  "geometry": {"coordinates":[-105.6667,48.2333],"type":"Point"}
}