{
  "id": 2401359,
  "type": "Feature",
  "properties": {
    "tgn:hierarchy":[
        "tgn:2401359",
        "tgn:1000001",
        "tgn:7012149",
        "tgn:2002176",
        "tgn:7007919",
        "tgn:7029392"
    ],
    "tgn:id":2401359,
    "tgn:name":"Horsepen Creek",
    "tgn:placetype":[
        "aat:300008706"
    ]
},
  "bbox": [],
  "geometry": {"coordinates":[-78.1167,37.0667],"type":"Point"}
}