{
  "id": 7589534,
  "type": "Feature",
  "properties": {
    "tgn:hierarchy":[
        "tgn:7589534",
        "tgn:1000004",
        "tgn:1001871",
        "tgn:7000198",
        "tgn:7029392"
    ],
    "tgn:id":7589534,
    "tgn:name:en":"Kalra",
    "tgn:placetype":[
        "aat:300008347"
    ]
},
  "bbox": [],
  "geometry": {"coordinates":[77.134727,29.963428],"type":"Point"}
}