{
  "id": 2247397,
  "type": "Feature",
  "properties": {
    "tgn:hierarchy":[
        "tgn:2247397",
        "tgn:1000001",
        "tgn:2001702",
        "tgn:7012149",
        "tgn:7007708",
        "tgn:7029392"
    ],
    "tgn:id":2247397,
    "tgn:name":"Coffee Creek",
    "tgn:placetype":[
        "aat:300008706"
    ]
},
  "bbox": [],
  "geometry": {"coordinates":[-124.1167,43.1833],"type":"Point"}
}