<<<<<<< HEAD
{
  "id": 7024995,
  "type": "Feature",
  "properties": {
    "tgn:hierarchy":[
        "tgn:7024995",
        "tgn:7002445",
        "tgn:7008103",
        "tgn:1000003",
        "tgn:7008591",
        "tgn:7029392"
    ],
    "tgn:id":7024995,
    "tgn:name":"Thurleigh",
    "tgn:name:ang":"Lalega",
    "tgn:placetype":[
        "aat:300008347"
    ]
},
  "bbox": [],
  "geometry": {"coordinates":[-0.45,52.2],"type":"Point"}
}
=======
{"geometry":{"type":"Point","coordinates":[-0.450000,52.200000]},"type":"Feature","properties":{"hierarchy":["tgn:7024995","tgn:7002445","tgn:7008103","tgn:1000003","tgn:7008591","tgn:7029392"],"placetype":["aat:300008347"],"id":7024995,"name:xx":"Thurleigh","name:ang":"Lalega"}}
>>>>>>> 03f74aca74312dbeaf24d7e61306dd6a786dc3d0
