{
  "id": 2671175,
  "type": "Feature",
  "properties": {
    "tgn:hierarchy":[
        "tgn:2671175",
        "tgn:7014651",
        "tgn:1000001",
        "tgn:7012149",
        "tgn:7007516",
        "tgn:7029392"
    ],
    "tgn:id":2671175,
    "tgn:name":"Smith Creek Marsh",
    "tgn:placetype":[
        "aat:300008905"
    ]
},
  "bbox": [],
  "geometry": {"coordinates":[-76.55,38.8333],"type":"Point"}
}