{
  "id": 2623039,
  "type": "Feature",
  "properties": {
    "tgn:hierarchy":[
        "tgn:2623039",
        "tgn:1000001",
        "tgn:7012149",
        "tgn:2001420",
        "tgn:7007526",
        "tgn:7029392"
    ],
    "tgn:id":2623039,
    "tgn:name":"Robison Reservoir",
    "tgn:placetype":[
        "aat:300006191"
    ]
},
  "bbox": [],
  "geometry": {"coordinates":[-114.2667,39.9833],"type":"Point"}
}