<<<<<<< HEAD
{
  "id": 7119128,
  "type": "Feature",
  "properties": {
    "tgn:hierarchy":[
        "tgn:7119128",
        "tgn:7003669",
        "tgn:1000003",
        "tgn:7000084",
        "tgn:7029392"
    ],
    "tgn:id":7119128,
    "tgn:name":"Pichler",
    "tgn:placetype":[
        "aat:300000206"
    ]
},
  "bbox": [],
  "geometry": {"coordinates":[13.083333,48.3],"type":"Point"}
}
=======
{"geometry":{"type":"Point","coordinates":[13.083333,48.300000]},"type":"Feature","properties":{"hierarchy":["tgn:7119128","tgn:7003669","tgn:1000003","tgn:7000084","tgn:7029392"],"placetype":["aat:300000206"],"id":7119128,"name:xx":"Pichler"}}
>>>>>>> 03f74aca74312dbeaf24d7e61306dd6a786dc3d0
