{
  "id": 7459072,
  "type": "Feature",
  "properties": {
    "tgn:hierarchy":[
        "tgn:7459072",
        "tgn:7002445",
        "tgn:1000003",
        "tgn:7008139",
        "tgn:7008591",
        "tgn:7029392"
    ],
    "tgn:id":7459072,
    "tgn:name:en":"Middle Wallop",
    "tgn:placetype":[
        "aat:300008347"
    ]
},
  "bbox": [],
  "geometry": {"coordinates":[-1.583333,51.133333],"type":"Point"}
}