{
  "id": 1080706,
  "type": "Feature",
  "properties": {
    "tgn:hierarchy":[
        "tgn:1080706",
        "tgn:7016675",
        "tgn:1000004",
        "tgn:7000896",
        "tgn:1000120",
        "tgn:7029392"
    ],
    "tgn:id":1080706,
    "tgn:name":"Maeda",
    "tgn:placetype":[
        "aat:300008347"
    ]
},
  "bbox": [],
  "geometry": {"coordinates":[135.1333,34.9167],"type":"Point"}
}