<<<<<<< HEAD
{
  "id": 7484402,
  "type": "Feature",
  "properties": {
    "tgn:hierarchy":[
        "tgn:7484402",
        "tgn:7001004",
        "tgn:1000004",
        "tgn:1000141",
        "tgn:7029392"
    ],
    "tgn:id":7484402,
    "tgn:name":"Linguanchu Huguansuo",
    "tgn:placetype":[
        "aat:300387503"
    ]
},
  "bbox": [],
  "geometry": {"coordinates":[120.593611,23.063333],"type":"Point"}
}
=======
{"geometry":{"type":"Point","coordinates":[120.593611,23.063333]},"type":"Feature","properties":{"hierarchy":["tgn:7484402","tgn:7001004","tgn:1000004","tgn:1000141","tgn:7029392"],"placetype":["aat:300387503"],"id":7484402,"name:xx":"Linguanchu Huguansuo"}}
>>>>>>> 03f74aca74312dbeaf24d7e61306dd6a786dc3d0
