{
  "id": 7484402,
  "type": "Feature",
  "properties": {
    "tgn:hierarchy":[
        "tgn:7484402",
        "tgn:7001004",
        "tgn:1000004",
        "tgn:1000141",
        "tgn:7029392"
    ],
    "tgn:id":7484402,
    "tgn:name":"Linguanchu Huguansuo",
    "tgn:placetype":[
        "aat:300387503"
    ]
},
  "bbox": [],
  "geometry": {"coordinates":[120.593611,23.063333],"type":"Point"}
}