<<<<<<< HEAD
{
  "id": 2766651,
  "type": "Feature",
  "properties": {
    "tgn:hierarchy":[
        "tgn:2766651",
        "tgn:2000934",
        "tgn:1000001",
        "tgn:7012149",
        "tgn:7007516",
        "tgn:7029392"
    ],
    "tgn:id":2766651,
    "tgn:name":"White Oak Hollow",
    "tgn:placetype":[
        "aat:300008761"
    ]
},
  "bbox": [],
  "geometry": {"coordinates":[-78.4833,39.7],"type":"Point"}
}
=======
{"geometry":{"type":"Point","coordinates":[-78.483300,39.700000]},"type":"Feature","properties":{"hierarchy":["tgn:2766651","tgn:2000934","tgn:1000001","tgn:7012149","tgn:7007516","tgn:7029392"],"placetype":["aat:300008761"],"id":2766651,"name:xx":"White Oak Hollow"}}
>>>>>>> 03f74aca74312dbeaf24d7e61306dd6a786dc3d0
