{
  "id": 2635918,
  "type": "Feature",
  "properties": {
    "tgn:hierarchy":[
        "tgn:2635918",
        "tgn:1000001",
        "tgn:7012149",
        "tgn:2000238",
        "tgn:7007158",
        "tgn:7029392"
    ],
    "tgn:id":2635918,
    "tgn:name":"Sacramento Creek",
    "tgn:placetype":[
        "aat:300008706"
    ]
},
  "bbox": [],
  "geometry": {"coordinates":[-106.1667,39.2333],"type":"Point"}
}