{
  "id": 7263081,
  "type": "Feature",
  "properties": {
    "tgn:concordances":{
        "gn:id":"2757733"
    },
    "tgn:hierarchy":[
        "tgn:7263081",
        "tgn:1000003",
        "tgn:7003613",
        "tgn:7016845",
        "tgn:7029392"
    ],
    "tgn:id":7263081,
    "tgn:name:nl":"De Bruil",
    "tgn:placetype":[
        "aat:300008347"
    ]
},
  "bbox": [],
  "geometry": {"coordinates":[7.116667,52.866667],"type":"Point"}
}