{
  "id": 2364295,
  "type": "Feature",
  "properties": {
    "tgn:hierarchy":[
        "tgn:2364295",
        "tgn:1000001",
        "tgn:2002133",
        "tgn:7012149",
        "tgn:7007828",
        "tgn:7029392"
    ],
    "tgn:id":2364295,
    "tgn:name":"Green River Reservoir",
    "tgn:placetype":[
        "aat:300006191"
    ]
},
  "bbox": [],
  "geometry": {"coordinates":[-72.5333,44.6167],"type":"Point"}
}