{
  "id": 7057838,
  "type": "Feature",
  "properties": {
    "tgn:hierarchy":[
        "tgn:7057838",
        "tgn:7003170",
        "tgn:1000003",
        "tgn:7003125",
        "tgn:1000080",
        "tgn:7029392"
    ],
    "tgn:id":7057838,
    "tgn:name":"Argento, Torrente",
    "tgn:placetype":[
        "aat:300008699"
    ]
},
  "bbox": [],
  "geometry": {"coordinates":[12.05,42.866667],"type":"Point"}
}