<<<<<<< HEAD
{
  "id": 2255476,
  "type": "Feature",
  "properties": {
    "tgn:hierarchy":[
        "tgn:2255476",
        "tgn:1000001",
        "tgn:7012149",
        "tgn:2001707",
        "tgn:7007708",
        "tgn:7029392"
    ],
    "tgn:id":2255476,
    "tgn:name":"Cope Canyon",
    "tgn:placetype":[
        "aat:300008761"
    ]
},
  "bbox": [],
  "geometry": {"coordinates":[-120.35,45.1333],"type":"Point"}
}
=======
{"geometry":{"type":"Point","coordinates":[-120.350000,45.133300]},"type":"Feature","properties":{"hierarchy":["tgn:2255476","tgn:1000001","tgn:7012149","tgn:2001707","tgn:7007708","tgn:7029392"],"placetype":["aat:300008761"],"id":2255476,"name:xx":"Cope Canyon"}}
>>>>>>> 03f74aca74312dbeaf24d7e61306dd6a786dc3d0
