{
  "id": 7380636,
  "type": "Feature",
  "properties": {
    "tgn:hierarchy":[
        "tgn:7380636",
        "tgn:1000001",
        "tgn:7005597",
        "tgn:7005560",
        "tgn:7029392"
    ],
    "tgn:id":7380636,
    "tgn:name":"Loreto",
    "tgn:placetype":[
        "aat:300008347"
    ]
},
  "bbox": [],
  "geometry": {"coordinates":[-97.95,24.333333],"type":"Point"}
}