{
  "id": 2127570,
  "type": "Feature",
  "properties": {
    "tgn:hierarchy":[
        "tgn:2127570",
        "tgn:7002659",
        "tgn:1000001",
        "tgn:2000013",
        "tgn:7012149",
        "tgn:7029392"
    ],
    "tgn:id":2127570,
    "tgn:name":"Alabama Gold and Mica Mine",
    "tgn:placetype":[
        "aat:300000390"
    ]
},
  "bbox": [],
  "geometry": {"coordinates":[-85.8667,33.3167],"type":"Point"}
}