{
  "id": 2440107,
  "type": "Feature",
  "properties": {
    "tgn:hierarchy":[
        "tgn:2440107",
        "tgn:1000001",
        "tgn:2001705",
        "tgn:7012149",
        "tgn:7007708",
        "tgn:7029392"
    ],
    "tgn:id":2440107,
    "tgn:name":"Klawhop Butte",
    "tgn:placetype":[
        "aat:300008798"
    ]
},
  "bbox": [],
  "geometry": {"coordinates":[-121.2833,44.85],"type":"Point"}
}