{
  "id": 2565773,
  "type": "Feature",
  "properties": {
    "tgn:hierarchy":[
        "tgn:2565773",
        "tgn:1000001",
        "tgn:7012149",
        "tgn:1002447",
        "tgn:7007252",
        "tgn:7029392"
    ],
    "tgn:id":2565773,
    "tgn:name":"Palestine Branch",
    "tgn:placetype":[
        "aat:300008699"
    ]
},
  "bbox": [],
  "geometry": {"coordinates":[-85.8833,39.7333],"type":"Point"}
}