{
  "id": 2431947,
  "type": "Feature",
  "properties": {
    "tgn:hierarchy":[
        "tgn:2431947",
        "tgn:7023902",
        "tgn:1000001",
        "tgn:7012149",
        "tgn:7007249",
        "tgn:7029392"
    ],
    "tgn:id":2431947,
    "tgn:name":"Kaumuki",
    "tgn:placetype":[
        "aat:300008798"
    ]
},
  "bbox": [],
  "geometry": {"coordinates":[-154.9833,19.4333],"type":"Point"}
}