{
  "id": 7524383,
  "type": "Feature",
  "properties": {
    "tgn:hierarchy":[
        "tgn:7524383",
        "tgn:7001242",
        "tgn:7016833",
        "tgn:1001418",
        "tgn:7029392"
    ],
    "tgn:id":7524383,
    "tgn:name:en":"Birsim, Qaret el",
    "tgn:placetype":[
        "aat:300008777"
    ]
},
  "bbox": [],
  "geometry": {"coordinates":[27.962209,30.535169],"type":"Point"}
}