{
  "id": 2699502,
  "type": "Feature",
  "properties": {
    "tgn:hierarchy":[
        "tgn:2699502",
        "tgn:1000001",
        "tgn:7012149",
        "tgn:1002497",
        "tgn:7007706",
        "tgn:7029392"
    ],
    "tgn:id":2699502,
    "tgn:name":"Strongs Ridge",
    "tgn:placetype":[
        "aat:300266640"
    ]
},
  "bbox": [],
  "geometry": {"coordinates":[-82.7833,41.2833],"type":"Point"}
}