{
  "id": 7182131,
  "type": "Feature",
  "properties": {
    "tgn:hierarchy":[
        "tgn:7182131",
        "tgn:1000003",
        "tgn:7003677",
        "tgn:7000084",
        "tgn:7029392"
    ],
    "tgn:id":7182131,
    "tgn:name":"Gangfurth",
    "tgn:placetype":[
        "aat:300008347"
    ]
},
  "bbox": [],
  "geometry": {"coordinates":[6.483333,50.533333],"type":"Point"}
}