{
  "id": 2471169,
  "type": "Feature",
  "properties": {
    "tgn:hierarchy":[
        "tgn:2471169",
        "tgn:1000001",
        "tgn:7006451",
        "tgn:2000092",
        "tgn:7012149",
        "tgn:7029392"
    ],
    "tgn:id":2471169,
    "tgn:name":"Lost Eden Tank",
    "tgn:placetype":[
        "aat:300006191"
    ]
},
  "bbox": [],
  "geometry": {"coordinates":[-111.2667,34.6167],"type":"Point"}
}