{
  "id": 7504717,
  "type": "Feature",
  "properties": {
    "tgn:hierarchy":[
        "tgn:7504717",
        "tgn:7000508",
        "tgn:1008380",
        "tgn:1000226",
        "tgn:1000006",
        "tgn:7029392"
    ],
    "tgn:id":7504717,
    "tgn:name:en":"Westhaven Boat Harbor",
    "tgn:placetype":[
        "aat:300120824"
    ]
},
  "bbox": [],
  "geometry": {"coordinates":[174.749444,-36.838056],"type":"Point"}
}