{
  "id": 7524364,
  "type": "Feature",
  "properties": {
    "tgn:hierarchy":[
        "tgn:7524364",
        "tgn:7001242",
        "tgn:1001075",
        "tgn:7016833",
        "tgn:7029392"
    ],
    "tgn:id":7524364,
    "tgn:name:en":"Bisint\u0101w\u0101y",
    "tgn:placetype":[
        "aat:300008347"
    ]
},
  "bbox": [],
  "geometry": {"coordinates":[30.376032,31.120883],"type":"Point"}
}