{
  "id": 1003914,
  "type": "Feature",
  "properties": {
    "tgn:hierarchy":[
        "tgn:1003914",
        "tgn:7002445",
        "tgn:7018913",
        "tgn:1000003",
        "tgn:7008136",
        "tgn:7008591",
        "tgn:7029392"
    ],
    "tgn:id":1003914,
    "tgn:name:en":"Acton",
    "tgn:placetype":[
        "aat:300008347",
        "aat:300000745"
    ]
},
  "bbox": [],
  "geometry": {"coordinates":[-0.2833,51.5167],"type":"Point"}
}