{
  "id": 2086484,
  "type": "Feature",
  "properties": {
    "tgn:hierarchy":[
        "tgn:2086484",
        "tgn:1000001",
        "tgn:7012149",
        "tgn:1002494",
        "tgn:7007710",
        "tgn:7029392"
    ],
    "tgn:id":2086484,
    "tgn:name":"Blairs Mills",
    "tgn:placetype":[
        "aat:300008347"
    ]
},
  "bbox": [],
  "geometry": {"coordinates":[-77.7167,40.2833],"type":"Point"}
}