{
  "id": 2427993,
  "type": "Feature",
  "properties": {
    "tgn:hierarchy":[
        "tgn:2427993",
        "tgn:1000001",
        "tgn:7012149",
        "tgn:7007157",
        "tgn:1002684",
        "tgn:7029392"
    ],
    "tgn:id":2427993,
    "tgn:name":"Juan Hiquera Creek",
    "tgn:placetype":[
        "aat:300008706"
    ]
},
  "bbox": [],
  "geometry": {"coordinates":[-121.7667,36.2667],"type":"Point"}
}