{
  "id": 2515111,
  "type": "Feature",
  "properties": {
    "tgn:hierarchy":[
        "tgn:2515111",
        "tgn:1000001",
        "tgn:2000317",
        "tgn:7012149",
        "tgn:7007248",
        "tgn:7029392"
    ],
    "tgn:id":2515111,
    "tgn:name":"Millers Lake",
    "tgn:placetype":[
        "aat:300006191"
    ]
},
  "bbox": [],
  "geometry": {"coordinates":[-84.75,32.2833],"type":"Point"}
}