<<<<<<< HEAD
{
  "id": 2400973,
  "type": "Feature",
  "properties": {
    "tgn:hierarchy":[
        "tgn:2400973",
        "tgn:1000001",
        "tgn:2002109",
        "tgn:7012149",
        "tgn:7007827",
        "tgn:7029392"
    ],
    "tgn:id":2400973,
    "tgn:name":"Horse Spring Canyon",
    "tgn:placetype":[
        "aat:300008761"
    ]
},
  "bbox": [],
  "geometry": {"coordinates":[-111.7833,37.6],"type":"Point"}
}
=======
{"geometry":{"type":"Point","coordinates":[-111.783300,37.600000]},"type":"Feature","properties":{"hierarchy":["tgn:2400973","tgn:1000001","tgn:2002109","tgn:7012149","tgn:7007827","tgn:7029392"],"placetype":["aat:300008761"],"id":2400973,"name:xx":"Horse Spring Canyon"}}
>>>>>>> 03f74aca74312dbeaf24d7e61306dd6a786dc3d0
