{
  "id": 7120927,
  "type": "Feature",
  "properties": {
    "tgn:hierarchy":[
        "tgn:7120927",
        "tgn:7003669",
        "tgn:1000003",
        "tgn:7000084",
        "tgn:7029392"
    ],
    "tgn:id":7120927,
    "tgn:name":"Plantage",
    "tgn:placetype":[
        "aat:300008347"
    ]
},
  "bbox": [],
  "geometry": {"coordinates":[11.583333,49.916667],"type":"Point"}
}