{
  "id": 2622179,
  "type": "Feature",
  "properties": {
    "tgn:hierarchy":[
        "tgn:2622179",
        "tgn:1000001",
        "tgn:2001413",
        "tgn:7012149",
        "tgn:7007526",
        "tgn:7029392"
    ],
    "tgn:id":2622179,
    "tgn:name":"Roberts Mountains",
    "tgn:placetype":[
        "aat:300386831"
    ]
},
  "bbox": [],
  "geometry": {"coordinates":[-116.3333,39.8333],"type":"Point"}
}