{
  "id": 7507029,
  "type": "Feature",
  "properties": {
    "tgn:hierarchy":[
        "tgn:7507029",
        "tgn:1009227",
        "tgn:1000226",
        "tgn:7016729",
        "tgn:1000006",
        "tgn:7029392"
    ],
    "tgn:id":7507029,
    "tgn:name:en":"Rakaunui Stream",
    "tgn:placetype":[
        "aat:300008699"
    ]
},
  "bbox": [],
  "geometry": {"coordinates":[173.583333,-42.433333],"type":"Point"}
}