<<<<<<< HEAD
{
  "id": 7176954,
  "type": "Feature",
  "properties": {
    "tgn:hierarchy":[
        "tgn:7176954",
        "tgn:1000003",
        "tgn:7003676",
        "tgn:7000084",
        "tgn:7029392"
    ],
    "tgn:id":7176954,
    "tgn:name":"Hager Tief",
    "tgn:placetype":[
        "aat:300008699"
    ]
},
  "bbox": [],
  "geometry": {"coordinates":[7.233333,53.616667],"type":"Point"}
}
=======
{"geometry":{"type":"Point","coordinates":[7.233333,53.616667]},"type":"Feature","properties":{"hierarchy":["tgn:7176954","tgn:1000003","tgn:7003676","tgn:7000084","tgn:7029392"],"placetype":["aat:300008699"],"id":7176954,"name:xx":"Hager Tief"}}
>>>>>>> 03f74aca74312dbeaf24d7e61306dd6a786dc3d0
