{
  "id": 7322504,
  "type": "Feature",
  "properties": {
    "tgn:hierarchy":[
        "tgn:7322504",
        "tgn:7002826",
        "tgn:7001158",
        "tgn:1000003",
        "tgn:1000095",
        "tgn:7029392"
    ],
    "tgn:id":7322504,
    "tgn:name":"San Rom\u00e1n de Bembibre",
    "tgn:placetype":[
        "aat:300008347"
    ]
},
  "bbox": [],
  "geometry": {"coordinates":[-6.433333,42.616667],"type":"Point"}
}