{
  "id": 7467645,
  "type": "Feature",
  "properties": {
    "tgn:hierarchy":[
        "tgn:7467645",
        "tgn:7469009",
        "tgn:1000004",
        "tgn:1000141",
        "tgn:7029392"
    ],
    "tgn:id":7467645,
    "tgn:name":"Zhai Shan",
    "tgn:placetype":[
        "aat:300008777"
    ]
},
  "bbox": [],
  "geometry": {"coordinates":[118.317222,24.386111],"type":"Point"}
}