{
  "id": 7517312,
  "type": "Feature",
  "properties": {
    "tgn:hierarchy":[
        "tgn:7517312",
        "tgn:1009227",
        "tgn:1000226",
        "tgn:7016822",
        "tgn:1000006",
        "tgn:7029392"
    ],
    "tgn:id":7517312,
    "tgn:name:en":"North Harbour",
    "tgn:placetype":[
        "aat:300132316"
    ]
},
  "bbox": [],
  "geometry": {"coordinates":[166.183333,-50.516667],"type":"Point"}
}