{
  "id": 1065667,
  "type": "Feature",
  "properties": {
    "tgn:hierarchy":[
        "tgn:1065667",
        "tgn:1000004",
        "tgn:7000190",
        "tgn:1000105",
        "tgn:7029392"
    ],
    "tgn:id":1065667,
    "tgn:name":"D\u012bghalia",
    "tgn:placetype":[
        "aat:300008347"
    ]
},
  "bbox": [],
  "geometry": {"coordinates":[89.65,23.1167],"type":"Point"}
}