{
  "id": 7003423,
  "type": "Feature",
  "properties": {
    "tgn:hierarchy":[
        "tgn:7003423",
        "tgn:1000003",
        "tgn:7594009",
        "tgn:1000066",
        "tgn:7029392"
    ],
    "tgn:id":7003423,
    "tgn:name:da":"\u00c5benr\u00e5",
    "tgn:name:de":"Apenrade",
    "tgn:name:en":"\u00c5benr\u00e5",
    "tgn:placetype":[
        "aat:300008347",
        "aat:300008416",
        "aat:300008375"
    ]
},
  "bbox": [],
  "geometry": {"coordinates":[9.4333,55.05],"type":"Point"}
}