{
  "id": 7030385,
  "type": "Feature",
  "properties": {
    "tgn:hierarchy":[
        "tgn:7030385",
        "tgn:7002691",
        "tgn:7012056",
        "tgn:1000003",
        "tgn:1000074",
        "tgn:7029392"
    ],
    "tgn:id":7030385,
    "tgn:name":"Eleutherna",
    "tgn:placetype":[
        "aat:300008347",
        "aat:300000810",
        "aat:300167671",
        "aat:300008375",
        "aat:300386024"
    ]
},
  "bbox": [],
  "geometry": {"coordinates":[24.664,35.32],"type":"Point"}
}