{
  "id": 7256357,
  "type": "Feature",
  "properties": {
    "tgn:concordances":{
        "gn:id":"2759721"
    },
    "tgn:hierarchy":[
        "tgn:7256357",
        "tgn:1000003",
        "tgn:7003624",
        "tgn:7016845",
        "tgn:7029392"
    ],
    "tgn:id":7256357,
    "tgn:name:nl":"Anneville",
    "tgn:placetype":[
        "aat:300008347"
    ]
},
  "bbox": [],
  "geometry": {"coordinates":[4.833333,51.55],"type":"Point"}
}