{
  "id": 2698309,
  "type": "Feature",
  "properties": {
    "tgn:hierarchy":[
        "tgn:2698309",
        "tgn:1000001",
        "tgn:7012149",
        "tgn:2000877",
        "tgn:7007256",
        "tgn:7029392"
    ],
    "tgn:id":2698309,
    "tgn:name":"Straight Bayou",
    "tgn:placetype":[
        "aat:300008699"
    ]
},
  "bbox": [],
  "geometry": {"coordinates":[-91.5667,30.2833],"type":"Point"}
}