{
  "id": 7483003,
  "type": "Feature",
  "properties": {
    "tgn:hierarchy":[
        "tgn:7483003",
        "tgn:1000004",
        "tgn:7001014",
        "tgn:1000141",
        "tgn:7029392"
    ],
    "tgn:id":7483003,
    "tgn:name":"Guizi Shan",
    "tgn:placetype":[
        "aat:300387033"
    ]
},
  "bbox": [],
  "geometry": {"coordinates":[120.177222,23.608889],"type":"Point"}
}