<<<<<<< HEAD
{
  "id": 7483003,
  "type": "Feature",
  "properties": {
    "tgn:hierarchy":[
        "tgn:7483003",
        "tgn:1000004",
        "tgn:7001014",
        "tgn:1000141",
        "tgn:7029392"
    ],
    "tgn:id":7483003,
    "tgn:name":"Guizi Shan",
    "tgn:placetype":[
        "aat:300387033"
    ]
},
  "bbox": [],
  "geometry": {"coordinates":[120.177222,23.608889],"type":"Point"}
}
=======
{"geometry":{"type":"Point","coordinates":[120.177222,23.608889]},"type":"Feature","properties":{"hierarchy":["tgn:7483003","tgn:1000004","tgn:7001014","tgn:1000141","tgn:7029392"],"placetype":["aat:300387033"],"id":7483003,"name:xx":"Guizi Shan"}}
>>>>>>> 03f74aca74312dbeaf24d7e61306dd6a786dc3d0
