{
  "id": 2438177,
  "type": "Feature",
  "properties": {
    "tgn:hierarchy":[
        "tgn:2438177",
        "tgn:1000001",
        "tgn:7012149",
        "tgn:2001247",
        "tgn:7007523",
        "tgn:7029392"
    ],
    "tgn:id":2438177,
    "tgn:name":"Kingfisher Hollow",
    "tgn:placetype":[
        "aat:300008761"
    ]
},
  "bbox": [],
  "geometry": {"coordinates":[-91.5167,37.1667],"type":"Point"}
}