{
  "id": 7250663,
  "type": "Feature",
  "properties": {
    "tgn:hierarchy":[
        "tgn:7250663",
        "tgn:7007877",
        "tgn:1000003",
        "tgn:1000063",
        "tgn:4012014",
        "tgn:7029392"
    ],
    "tgn:id":7250663,
    "tgn:name":"Quartes",
    "tgn:placetype":[
        "aat:300008347"
    ]
},
  "bbox": [],
  "geometry": {"coordinates":[3.511529,50.650536],"type":"Point"}
}