{
  "id": 7546487,
  "type": "Feature",
  "properties": {
    "tgn:hierarchy":[
        "tgn:7546487",
        "tgn:1000004",
        "tgn:7000198",
        "tgn:1001895",
        "tgn:7029392"
    ],
    "tgn:id":7546487,
    "tgn:name:en":"Anjani River",
    "tgn:placetype":[
        "aat:300008699"
    ]
},
  "bbox": [],
  "geometry": {"coordinates":[75.318114,21.128176],"type":"Point"}
}