{
  "id": 1086974,
  "type": "Feature",
  "properties": {
    "tgn:hierarchy":[
        "tgn:1086974",
        "tgn:1001586",
        "tgn:1000004",
        "tgn:7018456",
        "tgn:1000144",
        "tgn:7029392"
    ],
    "tgn:id":1086974,
    "tgn:name":"Viran\u015fehir",
    "tgn:placetype":[
        "aat:300008347"
    ]
},
  "bbox": [],
  "geometry": {"coordinates":[39.75,37.2167],"type":"Point"}
}