<<<<<<< HEAD
{
  "id": 2258811,
  "type": "Feature",
  "properties": {
    "tgn:hierarchy":[
        "tgn:2258811",
        "tgn:1000001",
        "tgn:7012149",
        "tgn:7007158",
        "tgn:2000243",
        "tgn:7029392"
    ],
    "tgn:id":2258811,
    "tgn:name":"Cottonwood Creek",
    "tgn:placetype":[
        "aat:300008706"
    ]
},
  "bbox": [],
  "geometry": {"coordinates":[-108.95,39.8667],"type":"Point"}
}
=======
{"geometry":{"type":"Point","coordinates":[-108.950000,39.866700]},"type":"Feature","properties":{"hierarchy":["tgn:2258811","tgn:1000001","tgn:7012149","tgn:7007158","tgn:2000243","tgn:7029392"],"placetype":["aat:300008706"],"id":2258811,"name:xx":"Cottonwood Creek"}}
>>>>>>> 03f74aca74312dbeaf24d7e61306dd6a786dc3d0
