{
  "id": 1063226,
  "type": "Feature",
  "properties": {
    "tgn:hierarchy":[
        "tgn:1063226",
        "tgn:1000003",
        "tgn:7003779",
        "tgn:1000097",
        "tgn:7029392"
    ],
    "tgn:id":1063226,
    "tgn:name":"Klimpfj\u00e4ll",
    "tgn:placetype":[
        "aat:300008347"
    ]
},
  "bbox": [],
  "geometry": {"coordinates":[14.8333,65.0833],"type":"Point"}
}