<<<<<<< HEAD
{
  "id": 7054366,
  "type": "Feature",
  "properties": {
    "tgn:hierarchy":[
        "tgn:7054366",
        "tgn:7015163",
        "tgn:1000003",
        "tgn:7003121",
        "tgn:1000080",
        "tgn:7029392"
    ],
    "tgn:id":7054366,
    "tgn:name":"Paimaroni, Punta de",
    "tgn:placetype":[
        "aat:300008777"
    ]
},
  "bbox": [],
  "geometry": {"coordinates":[8.283333,40.75],"type":"Point"}
}
=======
{"geometry":{"type":"Point","coordinates":[8.283333,40.750000]},"type":"Feature","properties":{"hierarchy":["tgn:7054366","tgn:7015163","tgn:1000003","tgn:7003121","tgn:1000080","tgn:7029392"],"placetype":["aat:300008777"],"id":7054366,"name:xx":"Paimaroni, Punta de"}}
>>>>>>> 03f74aca74312dbeaf24d7e61306dd6a786dc3d0
