{
  "id": 1011341,
  "type": "Feature",
  "properties": {
    "tgn:hierarchy":[
        "tgn:1011341",
        "tgn:1009046",
        "tgn:1000239",
        "tgn:1000006",
        "tgn:7029392"
    ],
    "tgn:id":1011341,
    "tgn:name":"Tuasivi, Cape",
    "tgn:placetype":[
        "aat:300008850"
    ]
},
  "bbox": [],
  "geometry": {"coordinates":[-172.1167,-13.6667],"type":"Point"}
}