{
  "id": 7216716,
  "type": "Feature",
  "properties": {
    "tgn:hierarchy":[
        "tgn:7216716",
        "tgn:1000003",
        "tgn:7003678",
        "tgn:7000084",
        "tgn:7029392"
    ],
    "tgn:id":7216716,
    "tgn:name":"Alsberg",
    "tgn:placetype":[
        "aat:300008347"
    ]
},
  "bbox": [],
  "geometry": {"coordinates":[9.416667,50.266667],"type":"Point"}
}