{
  "id": 7529661,
  "type": "Feature",
  "properties": {
    "tgn:hierarchy":[
        "tgn:7529661",
        "tgn:7001242",
        "tgn:7016833",
        "tgn:7001336",
        "tgn:7029392"
    ],
    "tgn:id":7529661,
    "tgn:name:en":"Shayqah, W\u0101d\u012b ash",
    "tgn:placetype":[
        "aat:300379998"
    ]
},
  "bbox": [],
  "geometry": {"coordinates":[33.789479,28.922217],"type":"Point"}
}