{
  "id": 7320709,
  "type": "Feature",
  "properties": {
    "tgn:hierarchy":[
        "tgn:7320709",
        "tgn:1001702",
        "tgn:1000049",
        "tgn:1000002",
        "tgn:7029392"
    ],
    "tgn:id":7320709,
    "tgn:name":"Bandurria, R\u00edo",
    "tgn:placetype":[
        "aat:300008699"
    ]
},
  "bbox": [],
  "geometry": {"coordinates":[-72.416667,-50.733333],"type":"Point"}
}