{
  "id": 2198069,
  "type": "Feature",
  "properties": {
    "tgn:hierarchy":[
        "tgn:2198069",
        "tgn:1000001",
        "tgn:7012149",
        "tgn:2001716",
        "tgn:7007708",
        "tgn:7029392"
    ],
    "tgn:id":2198069,
    "tgn:name":"Brownie Creek",
    "tgn:placetype":[
        "aat:300008706"
    ]
},
  "bbox": [],
  "geometry": {"coordinates":[-122.8667,43.5667],"type":"Point"}
}