<<<<<<< HEAD
{
  "id": 7113494,
  "type": "Feature",
  "properties": {
    "tgn:hierarchy":[
        "tgn:7113494",
        "tgn:1000003",
        "tgn:7003676",
        "tgn:7000084",
        "tgn:7029392"
    ],
    "tgn:id":7113494,
    "tgn:name":"Riensheide",
    "tgn:placetype":[
        "aat:300008863"
    ]
},
  "bbox": [],
  "geometry": {"coordinates":[9.716667,53.0],"type":"Point"}
}
=======
{"geometry":{"type":"Point","coordinates":[9.716667,53.000000]},"type":"Feature","properties":{"hierarchy":["tgn:7113494","tgn:1000003","tgn:7003676","tgn:7000084","tgn:7029392"],"placetype":["aat:300008863"],"id":7113494,"name:xx":"Riensheide"}}
>>>>>>> 03f74aca74312dbeaf24d7e61306dd6a786dc3d0
