{
  "id": 2626170,
  "type": "Feature",
  "properties": {
    "tgn:hierarchy":[
        "tgn:2626170",
        "tgn:1000001",
        "tgn:7012149",
        "tgn:2001711",
        "tgn:7007708",
        "tgn:7029392"
    ],
    "tgn:id":2626170,
    "tgn:name":"Rocky Creek",
    "tgn:placetype":[
        "aat:300008706"
    ]
},
  "bbox": [],
  "geometry": {"coordinates":[-123.0833,42.4667],"type":"Point"}
}