{
  "id": 2772434,
  "type": "Feature",
  "properties": {
    "tgn:hierarchy":[
        "tgn:2772434",
        "tgn:1000001",
        "tgn:7016172",
        "tgn:2000114",
        "tgn:7012149",
        "tgn:7029392"
    ],
    "tgn:id":2772434,
    "tgn:name":"Williams Branch",
    "tgn:placetype":[
        "aat:300008699"
    ]
},
  "bbox": [],
  "geometry": {"coordinates":[-92.9167,34.1333],"type":"Point"}
}