{
  "id": 7589161,
  "type": "Feature",
  "properties": {
    "tgn:hierarchy":[
        "tgn:7589161",
        "tgn:1000004",
        "tgn:7000198",
        "tgn:7000799",
        "tgn:7029392"
    ],
    "tgn:id":7589161,
    "tgn:name:en":"Potus",
    "tgn:placetype":[
        "aat:300008347"
    ]
},
  "bbox": [],
  "geometry": {"coordinates":[74.311698,34.275243],"type":"Point"}
}