{
  "id": 7128423,
  "type": "Feature",
  "properties": {
    "tgn:hierarchy":[
        "tgn:7128423",
        "tgn:7003669",
        "tgn:1000003",
        "tgn:7000084",
        "tgn:7029392"
    ],
    "tgn:id":7128423,
    "tgn:name":"Obere Saugr\u00e4ben",
    "tgn:placetype":[
        "aat:300008863"
    ]
},
  "bbox": [],
  "geometry": {"coordinates":[11.85,49.65],"type":"Point"}
}