{
  "id": 2593017,
  "type": "Feature",
  "properties": {
    "tgn:hierarchy":[
        "tgn:2593017",
        "tgn:1000001",
        "tgn:7012149",
        "tgn:7007157",
        "tgn:1002956",
        "tgn:7029392"
    ],
    "tgn:id":2593017,
    "tgn:name":"Poplar Ditch",
    "tgn:placetype":[
        "aat:300006075"
    ]
},
  "bbox": [],
  "geometry": {"coordinates":[-119.05,36.0333],"type":"Point"}
}