{
  "id": 2592111,
  "type": "Feature",
  "properties": {
    "tgn:hierarchy":[
        "tgn:2592111",
        "tgn:1000001",
        "tgn:7006451",
        "tgn:7012149",
        "tgn:2000100",
        "tgn:7029392"
    ],
    "tgn:id":2592111,
    "tgn:name":"Pontatoc Mine",
    "tgn:placetype":[
        "aat:300000390"
    ]
},
  "bbox": [],
  "geometry": {"coordinates":[-110.8833,32.3167],"type":"Point"}
}