<<<<<<< HEAD
{
  "id": 2339689,
  "type": "Feature",
  "properties": {
    "tgn:hierarchy":[
        "tgn:2339689",
        "tgn:1000001",
        "tgn:7012149",
        "tgn:2001161",
        "tgn:7007522",
        "tgn:7029392"
    ],
    "tgn:id":2339689,
    "tgn:name":"Free Negro Bayou",
    "tgn:placetype":[
        "aat:300008699"
    ]
},
  "bbox": [],
  "geometry": {"coordinates":[-90.7,33.1167],"type":"Point"}
}
=======
{"geometry":{"type":"Point","coordinates":[-90.700000,33.116700]},"type":"Feature","properties":{"hierarchy":["tgn:2339689","tgn:1000001","tgn:7012149","tgn:2001161","tgn:7007522","tgn:7029392"],"placetype":["aat:300008699"],"id":2339689,"name:xx":"Free Negro Bayou"}}
>>>>>>> 03f74aca74312dbeaf24d7e61306dd6a786dc3d0
