{
  "id": 2370086,
  "type": "Feature",
  "properties": {
    "tgn:hierarchy":[
        "tgn:2370086",
        "tgn:1000001",
        "tgn:7012149",
        "tgn:2001288",
        "tgn:7007524",
        "tgn:7029392"
    ],
    "tgn:id":2370086,
    "tgn:name":"Guymon Spring",
    "tgn:placetype":[
        "aat:300008697"
    ]
},
  "bbox": [],
  "geometry": {"coordinates":[-112.0167,45.75],"type":"Point"}
}