{
  "id": 7060006,
  "type": "Feature",
  "properties": {
    "tgn:hierarchy":[
        "tgn:7060006",
        "tgn:7003669",
        "tgn:1000003",
        "tgn:7000084",
        "tgn:7029392"
    ],
    "tgn:id":7060006,
    "tgn:name":"Alkoven",
    "tgn:placetype":[
        "aat:300008347"
    ]
},
  "bbox": [],
  "geometry": {"coordinates":[13.133333,48.633333],"type":"Point"}
}