{
  "id": 1067002,
  "type": "Feature",
  "properties": {
    "tgn:hierarchy":[
        "tgn:1067002",
        "tgn:1000004",
        "tgn:7002085",
        "tgn:1000111",
        "tgn:7029392"
    ],
    "tgn:id":1067002,
    "tgn:name":"Caomaji",
    "tgn:placetype":[
        "aat:300008347"
    ]
},
  "bbox": [],
  "geometry": {"coordinates":[116.2833,34.85],"type":"Point"}
}