{
  "id": 2586565,
  "type": "Feature",
  "properties": {
    "tgn:hierarchy":[
        "tgn:2586565",
        "tgn:1000001",
        "tgn:2000774",
        "tgn:7012149",
        "tgn:7007255",
        "tgn:7029392"
    ],
    "tgn:id":2586565,
    "tgn:name":"Pitts Point",
    "tgn:placetype":[
        "aat:300008347"
    ]
},
  "bbox": [],
  "geometry": {"coordinates":[-85.8167,37.9167],"type":"Point"}
}