<<<<<<< HEAD
{
  "id": 7481460,
  "type": "Feature",
  "properties": {
    "tgn:hierarchy":[
        "tgn:7481460",
        "tgn:1000004",
        "tgn:7471332",
        "tgn:1000141",
        "tgn:7029392"
    ],
    "tgn:id":7481460,
    "tgn:name":"Wangyekeng",
    "tgn:placetype":[
        "aat:300008347"
    ]
},
  "bbox": [],
  "geometry": {"coordinates":[121.121944,24.755833],"type":"Point"}
}
=======
{"geometry":{"type":"Point","coordinates":[121.121944,24.755833]},"type":"Feature","properties":{"hierarchy":["tgn:7481460","tgn:1000004","tgn:7471332","tgn:1000141","tgn:7029392"],"placetype":["aat:300008347"],"id":7481460,"name:xx":"Wangyekeng"}}
>>>>>>> 03f74aca74312dbeaf24d7e61306dd6a786dc3d0
