{
  "id": 7481460,
  "type": "Feature",
  "properties": {
    "tgn:hierarchy":[
        "tgn:7481460",
        "tgn:1000004",
        "tgn:7471332",
        "tgn:1000141",
        "tgn:7029392"
    ],
    "tgn:id":7481460,
    "tgn:name":"Wangyekeng",
    "tgn:placetype":[
        "aat:300008347"
    ]
},
  "bbox": [],
  "geometry": {"coordinates":[121.121944,24.755833],"type":"Point"}
}