{
  "id": 7049820,
  "type": "Feature",
  "properties": {
    "tgn:hierarchy":[
        "tgn:7049820",
        "tgn:1003473",
        "tgn:1000003",
        "tgn:7009760",
        "tgn:1000080",
        "tgn:7029392"
    ],
    "tgn:id":7049820,
    "tgn:name":"Cargalla",
    "tgn:placetype":[
        "aat:300008347"
    ]
},
  "bbox": [],
  "geometry": {"coordinates":[9.916667,44.416667],"type":"Point"}
}