{
  "id": 2658743,
  "type": "Feature",
  "properties": {
    "tgn:hierarchy":[
        "tgn:2658743",
        "tgn:7006450",
        "tgn:1000001",
        "tgn:2124089",
        "tgn:7012149",
        "tgn:7029392"
    ],
    "tgn:id":2658743,
    "tgn:name":"Sherman Creek",
    "tgn:placetype":[
        "aat:300008706"
    ]
},
  "bbox": [],
  "geometry": {"coordinates":[-135.0667,58.8333],"type":"Point"}
}