{
  "id": 2373665,
  "type": "Feature",
  "properties": {
    "tgn:hierarchy":[
        "tgn:2373665",
        "tgn:1000001",
        "tgn:7012149",
        "tgn:2000544",
        "tgn:7007252",
        "tgn:7029392"
    ],
    "tgn:id":2373665,
    "tgn:name":"Hamilton Ditch",
    "tgn:placetype":[
        "aat:300006075"
    ]
},
  "bbox": [],
  "geometry": {"coordinates":[-87.1667,38.9667],"type":"Point"}
}