{
  "id": 7339817,
  "type": "Feature",
  "properties": {
    "tgn:hierarchy":[
        "tgn:7339817",
        "tgn:7002820",
        "tgn:7030216",
        "tgn:1000003",
        "tgn:1000095",
        "tgn:7029392"
    ],
    "tgn:id":7339817,
    "tgn:name":"Conca, Cala de",
    "tgn:placetype":[
        "aat:300132317"
    ]
},
  "bbox": [],
  "geometry": {"coordinates":[3.062384,41.797787],"type":"Point"}
}