{
  "id": 2315168,
  "type": "Feature",
  "properties": {
    "tgn:hierarchy":[
        "tgn:2315168",
        "tgn:1000001",
        "tgn:7012149",
        "tgn:2000966",
        "tgn:7007520",
        "tgn:7029392"
    ],
    "tgn:id":2315168,
    "tgn:name":"Ellen, Lake",
    "tgn:placetype":[
        "aat:300008680"
    ]
},
  "bbox": [],
  "geometry": {"coordinates":[-88.15,46.1667],"type":"Point"}
}