{
  "id": 7325669,
  "type": "Feature",
  "properties": {
    "tgn:hierarchy":[
        "tgn:7325669",
        "tgn:7002836",
        "tgn:7016622",
        "tgn:1000003",
        "tgn:1000095",
        "tgn:7029392"
    ],
    "tgn:id":7325669,
    "tgn:name":"Santa Catalina, Baja de",
    "tgn:placetype":[
        "aat:300387036"
    ]
},
  "bbox": [],
  "geometry": {"coordinates":[-16.216667,28.566667],"type":"Point"}
}