{
  "id": 7472720,
  "type": "Feature",
  "properties": {
    "tgn:hierarchy":[
        "tgn:7472720",
        "tgn:1000004",
        "tgn:7491221",
        "tgn:1000141",
        "tgn:7029392"
    ],
    "tgn:id":7472720,
    "tgn:name":"Dulu Beishan",
    "tgn:placetype":[
        "aat:300008798"
    ]
},
  "bbox": [],
  "geometry": {"coordinates":[121.190473,22.920707],"type":"Point"}
}