{
  "id": 2348443,
  "type": "Feature",
  "properties": {
    "tgn:hierarchy":[
        "tgn:2348443",
        "tgn:1000001",
        "tgn:7012149",
        "tgn:2000226",
        "tgn:7007158",
        "tgn:7029392"
    ],
    "tgn:id":2348443,
    "tgn:name":"Gianttrack Mountain",
    "tgn:placetype":[
        "aat:300008798"
    ]
},
  "bbox": [],
  "geometry": {"coordinates":[-105.55,40.35],"type":"Point"}
}