{
  "id": 7043789,
  "type": "Feature",
  "properties": {
    "tgn:hierarchy":[
        "tgn:7043789",
        "tgn:1003506",
        "tgn:1000003",
        "tgn:7002993",
        "tgn:1000080",
        "tgn:7029392"
    ],
    "tgn:id":7043789,
    "tgn:name":"Fusine, Laghi di",
    "tgn:placetype":[
        "aat:300008680"
    ]
},
  "bbox": [],
  "geometry": {"coordinates":[13.670556,46.479722],"type":"Point"}
}