{
  "id": 1052735,
  "type": "Feature",
  "properties": {
    "tgn:hierarchy":[
        "tgn:1052735",
        "tgn:1000003",
        "tgn:7016798",
        "tgn:7006660",
        "tgn:7029392"
    ],
    "tgn:id":1052735,
    "tgn:name":"Beregovo",
    "tgn:placetype":[
        "aat:300008347"
    ]
},
  "bbox": [],
  "geometry": {"coordinates":[22.65,48.2167],"type":"Point"}
}