{
  "id": 7484491,
  "type": "Feature",
  "properties": {
    "tgn:hierarchy":[
        "tgn:7484491",
        "tgn:7487020",
        "tgn:1000004",
        "tgn:1000141",
        "tgn:7029392"
    ],
    "tgn:id":7484491,
    "tgn:name":"Hongluqi",
    "tgn:placetype":[
        "aat:300008347"
    ]
},
  "bbox": [],
  "geometry": {"coordinates":[120.740556,24.486111],"type":"Point"}
}