{
  "id": 2069381,
  "type": "Feature",
  "properties": {
    "tgn:hierarchy":[
        "tgn:2069381",
        "tgn:1000001",
        "tgn:7012149",
        "tgn:1002872",
        "tgn:7007568",
        "tgn:7029392"
    ],
    "tgn:id":2069381,
    "tgn:name":"Gifford",
    "tgn:placetype":[
        "aat:300008347",
        "aat:300387210"
    ]
},
  "bbox": [],
  "geometry": {"coordinates":[-74.0333,42.75],"type":"Point"}
}