<<<<<<< HEAD
{
  "id": 7483219,
  "type": "Feature",
  "properties": {
    "tgn:hierarchy":[
        "tgn:7483219",
        "tgn:1000004",
        "tgn:1000454",
        "tgn:1000141",
        "tgn:7029392"
    ],
    "tgn:id":7483219,
    "tgn:name":"Fangjiaokeng",
    "tgn:placetype":[
        "aat:300008347"
    ]
},
  "bbox": [],
  "geometry": {"coordinates":[121.768889,24.952222],"type":"Point"}
}
=======
{"geometry":{"type":"Point","coordinates":[121.768889,24.952222]},"type":"Feature","properties":{"hierarchy":["tgn:7483219","tgn:1000004","tgn:1000454","tgn:1000141","tgn:7029392"],"placetype":["aat:300008347"],"id":7483219,"name:xx":"Fangjiaokeng"}}
>>>>>>> 03f74aca74312dbeaf24d7e61306dd6a786dc3d0
