{
  "id": 2654877,
  "type": "Feature",
  "properties": {
    "tgn:hierarchy":[
        "tgn:2654877",
        "tgn:1000001",
        "tgn:7012149",
        "tgn:1002472",
        "tgn:7007568",
        "tgn:7029392"
    ],
    "tgn:id":2654877,
    "tgn:name":"Shallow Pond",
    "tgn:placetype":[
        "aat:300008680"
    ]
},
  "bbox": [],
  "geometry": {"coordinates":[-75.0333,43.9167],"type":"Point"}
}