{
  "id": 2436688,
  "type": "Feature",
  "properties": {
    "tgn:hierarchy":[
        "tgn:2436688",
        "tgn:1000001",
        "tgn:7012149",
        "tgn:1002947",
        "tgn:7007252",
        "tgn:7029392"
    ],
    "tgn:id":2436688,
    "tgn:name":"Kigin Ditch",
    "tgn:placetype":[
        "aat:300006075"
    ]
},
  "bbox": [],
  "geometry": {"coordinates":[-86.1667,40.25],"type":"Point"}
}