{
  "id": 2452659,
  "type": "Feature",
  "properties": {
    "tgn:hierarchy":[
        "tgn:2452659",
        "tgn:1002149",
        "tgn:1000001",
        "tgn:7012149",
        "tgn:7007826",
        "tgn:7029392"
    ],
    "tgn:id":2452659,
    "tgn:name":"Little Buck Creek",
    "tgn:placetype":[
        "aat:300008706"
    ]
},
  "bbox": [],
  "geometry": {"coordinates":[-94.55,31.2333],"type":"Point"}
}