{
  "id": 2184497,
  "type": "Feature",
  "properties": {
    "tgn:hierarchy":[
        "tgn:2184497",
        "tgn:1000001",
        "tgn:7012149",
        "tgn:2001503",
        "tgn:7007709",
        "tgn:7029392"
    ],
    "tgn:id":2184497,
    "tgn:name":"Bobs Ridge",
    "tgn:placetype":[
        "aat:300266640"
    ]
},
  "bbox": [],
  "geometry": {"coordinates":[-82.8167,35.3667],"type":"Point"}
}