{
  "id": 7176386,
  "type": "Feature",
  "properties": {
    "tgn:hierarchy":[
        "tgn:7176386",
        "tgn:7003692",
        "tgn:1000003",
        "tgn:7000084",
        "tgn:7029392"
    ],
    "tgn:id":7176386,
    "tgn:name":"Gr\u00fcningen",
    "tgn:placetype":[
        "aat:300008347"
    ]
},
  "bbox": [],
  "geometry": {"coordinates":[9.45,48.166667],"type":"Point"}
}