{
  "id": 7298047,
  "type": "Feature",
  "properties": {
    "tgn:hierarchy":[
        "tgn:7298047",
        "tgn:7008912",
        "tgn:7030216",
        "tgn:1000003",
        "tgn:1000095",
        "tgn:7029392"
    ],
    "tgn:id":7298047,
    "tgn:name":"Solanell, Arroyo de",
    "tgn:placetype":[
        "aat:300266554",
        "aat:300008699"
    ]
},
  "bbox": [],
  "geometry": {"coordinates":[1.366667,42.366667],"type":"Point"}
}