{
  "id": 7116539,
  "type": "Feature",
  "properties": {
    "tgn:hierarchy":[
        "tgn:7116539",
        "tgn:1000003",
        "tgn:7003676",
        "tgn:7000084",
        "tgn:7029392"
    ],
    "tgn:id":7116539,
    "tgn:name":"Oberwald",
    "tgn:placetype":[
        "aat:300055621"
    ]
},
  "bbox": [],
  "geometry": {"coordinates":[8.833333,52.783333],"type":"Point"}
}