<<<<<<< HEAD
{
  "id": 7489248,
  "type": "Feature",
  "properties": {
    "tgn:hierarchy":[
        "tgn:7489248",
        "tgn:1000004",
        "tgn:7001013",
        "tgn:1000141",
        "tgn:7029392"
    ],
    "tgn:id":7489248,
    "tgn:name":"Gongcuo",
    "tgn:placetype":[
        "aat:300008347"
    ]
},
  "bbox": [],
  "geometry": {"coordinates":[121.302099,25.021332],"type":"Point"}
}
=======
{"geometry":{"type":"Point","coordinates":[121.302099,25.021332]},"type":"Feature","properties":{"hierarchy":["tgn:7489248","tgn:1000004","tgn:7001013","tgn:1000141","tgn:7029392"],"placetype":["aat:300008347"],"id":7489248,"name:xx":"Gongcuo"}}
>>>>>>> 03f74aca74312dbeaf24d7e61306dd6a786dc3d0
