{
  "id": 2072867,
  "type": "Feature",
  "properties": {
    "tgn:hierarchy":[
        "tgn:2072867",
        "tgn:1000001",
        "tgn:7012149",
        "tgn:1002688",
        "tgn:7007568",
        "tgn:7029392"
    ],
    "tgn:id":2072867,
    "tgn:name":"Van Deusenville",
    "tgn:placetype":[
        "aat:300008347",
        "aat:300387210"
    ]
},
  "bbox": [],
  "geometry": {"coordinates":[-74.6833,42.8333],"type":"Point"}
}