{
  "id": 2269768,
  "type": "Feature",
  "properties": {
    "tgn:hierarchy":[
        "tgn:2269768",
        "tgn:1000001",
        "tgn:7012149",
        "tgn:1002784",
        "tgn:7007706",
        "tgn:7029392"
    ],
    "tgn:id":2269768,
    "tgn:name":"Crownover Mill",
    "tgn:placetype":[
        "aat:300008347"
    ]
},
  "bbox": [],
  "geometry": {"coordinates":[-83.2167,39.6167],"type":"Point"}
}