{
  "id": 2048783,
  "type": "Feature",
  "properties": {
    "tgn:hierarchy":[
        "tgn:2048783",
        "tgn:1000001",
        "tgn:7016104",
        "tgn:7012149",
        "tgn:7007516",
        "tgn:7029392"
    ],
    "tgn:id":2048783,
    "tgn:name":"Somerset",
    "tgn:placetype":[
        "aat:300008347"
    ]
},
  "bbox": [],
  "geometry": {"coordinates":[-77.0833,38.95],"type":"Point"}
}