{
  "id": 7590830,
  "type": "Feature",
  "properties": {
    "tgn:hierarchy":[
        "tgn:7590830",
        "tgn:1000004",
        "tgn:7000198",
        "tgn:7000799",
        "tgn:7029392"
    ],
    "tgn:id":7590830,
    "tgn:name:en":"Khare ki Gali",
    "tgn:placetype":[
        "aat:300259572"
    ]
},
  "bbox": [],
  "geometry": {"coordinates":[74.435525,33.770033],"type":"Point"}
}