{
  "id": 2385031,
  "type": "Feature",
  "properties": {
    "tgn:hierarchy":[
        "tgn:2385031",
        "tgn:1000001",
        "tgn:2001173",
        "tgn:7012149",
        "tgn:7007523",
        "tgn:7029392"
    ],
    "tgn:id":2385031,
    "tgn:name":"Helton Branch",
    "tgn:placetype":[
        "aat:300008699"
    ]
},
  "bbox": [],
  "geometry": {"coordinates":[-93.2333,38.1667],"type":"Point"}
}