<<<<<<< HEAD
{
  "id": 2766280,
  "type": "Feature",
  "properties": {
    "tgn:hierarchy":[
        "tgn:2766280",
        "tgn:1000001",
        "tgn:7012149",
        "tgn:1002350",
        "tgn:7007157",
        "tgn:7029392"
    ],
    "tgn:id":2766280,
    "tgn:name":"White Man Ravine",
    "tgn:placetype":[
        "aat:300008761"
    ]
},
  "bbox": [],
  "geometry": {"coordinates":[-120.95,38.5667],"type":"Point"}
}
=======
{"geometry":{"type":"Point","coordinates":[-120.950000,38.566700]},"type":"Feature","properties":{"hierarchy":["tgn:2766280","tgn:1000001","tgn:7012149","tgn:1002350","tgn:7007157","tgn:7029392"],"placetype":["aat:300008761"],"id":2766280,"name:xx":"White Man Ravine"}}
>>>>>>> 03f74aca74312dbeaf24d7e61306dd6a786dc3d0
