{
  "id": 7395264,
  "type": "Feature",
  "properties": {
    "tgn:hierarchy":[
        "tgn:7395264",
        "tgn:7005580",
        "tgn:1000001",
        "tgn:7005560",
        "tgn:7029392"
    ],
    "tgn:id":7395264,
    "tgn:name":"San Andr\u00e9s",
    "tgn:placetype":[
        "aat:300007783"
    ]
},
  "bbox": [],
  "geometry": {"coordinates":[-93.583333,15.866667],"type":"Point"}
}