<<<<<<< HEAD
{
  "id": 7022672,
  "type": "Feature",
  "properties": {
    "tgn:hierarchy":[
        "tgn:7022672",
        "tgn:1000001",
        "tgn:7012149",
        "tgn:7029392"
    ],
    "tgn:id":7022672,
    "tgn:name":"Wallum Lake",
    "tgn:placetype":[
        "aat:300008680"
    ]
},
  "bbox": [],
  "geometry": {"coordinates":[-71.7667,42.0],"type":"Point"}
}
=======
{"geometry":{"type":"Point","coordinates":[-71.766700,42.000000]},"type":"Feature","properties":{"hierarchy":["tgn:7022672","tgn:1000001","tgn:7012149","tgn:7029392"],"placetype":["aat:300008680"],"id":7022672,"name:xx":"Wallum Lake"}}
>>>>>>> 03f74aca74312dbeaf24d7e61306dd6a786dc3d0
