{
  "id": 2662907,
  "type": "Feature",
  "properties": {
    "tgn:hierarchy":[
        "tgn:2662907",
        "tgn:1000001",
        "tgn:7006451",
        "tgn:2000091",
        "tgn:7012149",
        "tgn:7029392"
    ],
    "tgn:id":2662907,
    "tgn:name":"Silo Tank",
    "tgn:placetype":[
        "aat:300006191"
    ]
},
  "bbox": [],
  "geometry": {"coordinates":[-109.35,31.4667],"type":"Point"}
}