{
  "id": 2644218,
  "type": "Feature",
  "properties": {
    "tgn:hierarchy":[
        "tgn:2644218",
        "tgn:1000001",
        "tgn:2001746",
        "tgn:7012149",
        "tgn:7007712",
        "tgn:7029392"
    ],
    "tgn:id":2644218,
    "tgn:name":"Santee Point",
    "tgn:placetype":[
        "aat:300008850"
    ]
},
  "bbox": [],
  "geometry": {"coordinates":[-79.2333,33.1333],"type":"Point"}
}