{
  "id": 2129247,
  "type": "Feature",
  "properties": {
    "tgn:hierarchy":[
        "tgn:2129247",
        "tgn:1000001",
        "tgn:2000201",
        "tgn:7012149",
        "tgn:7007158",
        "tgn:7029392"
    ],
    "tgn:id":2129247,
    "tgn:name":"Alice",
    "tgn:placetype":[
        "aat:300008347"
    ]
},
  "bbox": [],
  "geometry": {"coordinates":[-105.6333,39.8167],"type":"Point"}
}