{
  "id": 1130379,
  "type": "Feature",
  "properties": {
    "tgn:hierarchy":[
        "tgn:1130379",
        "tgn:1000001",
        "tgn:2001427",
        "tgn:7012149",
        "tgn:7007564",
        "tgn:7029392"
    ],
    "tgn:id":1130379,
    "tgn:name":"Sugar",
    "tgn:placetype":[
        "aat:300008707"
    ]
},
  "bbox": [],
  "geometry": {"coordinates":[-72.0667,43.3833],"type":"Point"}
}