{
  "id": 7254033,
  "type": "Feature",
  "properties": {
    "tgn:hierarchy":[
        "tgn:7254033",
        "tgn:7003457",
        "tgn:1000003",
        "tgn:1000063",
        "tgn:7018236",
        "tgn:7029392"
    ],
    "tgn:id":7254033,
    "tgn:name":"Terleyen",
    "tgn:placetype":[
        "aat:300005567"
    ]
},
  "bbox": [],
  "geometry": {"coordinates":[3.716667,51.25],"type":"Point"}
}