{
  "id": 2111718,
  "type": "Feature",
  "properties": {
    "tgn:hierarchy":[
        "tgn:2111718",
        "tgn:1000001",
        "tgn:7012149",
        "tgn:2002164",
        "tgn:7007919",
        "tgn:7029392"
    ],
    "tgn:id":2111718,
    "tgn:name":"Fairwood",
    "tgn:placetype":[
        "aat:300008347",
        "aat:300387210"
    ]
},
  "bbox": [],
  "geometry": {"coordinates":[-81.4833,36.6833],"type":"Point"}
}