{
  "id": 2450320,
  "type": "Feature",
  "properties": {
    "tgn:hierarchy":[
        "tgn:2450320",
        "tgn:1000001",
        "tgn:7012149",
        "tgn:1003002",
        "tgn:7007922",
        "tgn:7029392"
    ],
    "tgn:id":2450320,
    "tgn:name":"Linie Lac",
    "tgn:placetype":[
        "aat:300008680"
    ]
},
  "bbox": [],
  "geometry": {"coordinates":[-88.15,42.9167],"type":"Point"}
}