{
  "id": 2372819,
  "type": "Feature",
  "properties": {
    "tgn:hierarchy":[
        "tgn:2372819",
        "tgn:2001423",
        "tgn:1000001",
        "tgn:7012149",
        "tgn:7007564",
        "tgn:7029392"
    ],
    "tgn:id":2372819,
    "tgn:name":"Hall Ponds",
    "tgn:placetype":[
        "aat:300008680"
    ]
},
  "bbox": [],
  "geometry": {"coordinates":[-71.5333,43.85],"type":"Point"}
}