<<<<<<< HEAD
{
  "id": 7482677,
  "type": "Feature",
  "properties": {
    "tgn:hierarchy":[
        "tgn:7482677",
        "tgn:1000004",
        "tgn:7490934",
        "tgn:1000141",
        "tgn:7029392"
    ],
    "tgn:id":7482677,
    "tgn:name":"Anping Gongyequ",
    "tgn:placetype":[
        "aat:300387302"
    ]
},
  "bbox": [],
  "geometry": {"coordinates":[120.181389,22.977222],"type":"Point"}
}
=======
{"geometry":{"type":"Point","coordinates":[120.181389,22.977222]},"type":"Feature","properties":{"hierarchy":["tgn:7482677","tgn:1000004","tgn:7490934","tgn:1000141","tgn:7029392"],"placetype":["aat:300387302"],"id":7482677,"name:xx":"Anping Gongyequ"}}
>>>>>>> 03f74aca74312dbeaf24d7e61306dd6a786dc3d0
