{
  "id": 2266381,
  "type": "Feature",
  "properties": {
    "tgn:hierarchy":[
        "tgn:2266381",
        "tgn:1000001",
        "tgn:2000458",
        "tgn:7012149",
        "tgn:7007250",
        "tgn:7029392"
    ],
    "tgn:id":2266381,
    "tgn:name":"Cream Can Junction",
    "tgn:placetype":[
        "aat:300008347"
    ]
},
  "bbox": [],
  "geometry": {"coordinates":[-113.3833,42.9333],"type":"Point"}
}