{
  "id": 2551090,
  "type": "Feature",
  "properties": {
    "tgn:hierarchy":[
        "tgn:2551090",
        "tgn:1000001",
        "tgn:2001702",
        "tgn:7012149",
        "tgn:7007708",
        "tgn:7029392"
    ],
    "tgn:id":2551090,
    "tgn:name":"Nowlin Creek",
    "tgn:placetype":[
        "aat:300008706"
    ]
},
  "bbox": [],
  "geometry": {"coordinates":[-124.0333,43.4333],"type":"Point"}
}