{
  "id": 7398814,
  "type": "Feature",
  "properties": {
    "tgn:hierarchy":[
        "tgn:7398814",
        "tgn:1000001",
        "tgn:1001893",
        "tgn:7005560",
        "tgn:7029392"
    ],
    "tgn:id":7398814,
    "tgn:name":"Mimbres",
    "tgn:placetype":[
        "aat:300008347"
    ]
},
  "bbox": [],
  "geometry": {"coordinates":[-99.555833,19.451667],"type":"Point"}
}