{
  "id": 7556392,
  "type": "Feature",
  "properties": {
    "tgn:hierarchy":[
        "tgn:7556392",
        "tgn:1000004",
        "tgn:7000198",
        "tgn:7016788",
        "tgn:7029392"
    ],
    "tgn:id":7556392,
    "tgn:name:en":"Phusaria",
    "tgn:placetype":[
        "aat:300008347"
    ]
},
  "bbox": [],
  "geometry": {"coordinates":[75.293414,25.000806],"type":"Point"}
}