{
  "id": 2157489,
  "type": "Feature",
  "properties": {
    "tgn:hierarchy":[
        "tgn:2157489",
        "tgn:1000001",
        "tgn:7012149",
        "tgn:7007919",
        "tgn:7029392"
    ],
    "tgn:id":2157489,
    "tgn:name":"Beaver Creek",
    "tgn:placetype":[
        "aat:300008706"
    ]
},
  "bbox": [],
  "geometry": {"coordinates":[-78.05,38.1833],"type":"Point"}
}