<<<<<<< HEAD
{
  "id": 2336374,
  "type": "Feature",
  "properties": {
    "tgn:hierarchy":[
        "tgn:2336374",
        "tgn:1000001",
        "tgn:7012149",
        "tgn:2001852",
        "tgn:7007825",
        "tgn:7029392"
    ],
    "tgn:id":2336374,
    "tgn:name":"Fountain Grove",
    "tgn:placetype":[
        "aat:300008347"
    ]
},
  "bbox": [],
  "geometry": {"coordinates":[-85.9333,35.55],"type":"Point"}
}
=======
{"geometry":{"type":"Point","coordinates":[-85.933300,35.550000]},"type":"Feature","properties":{"hierarchy":["tgn:2336374","tgn:1000001","tgn:7012149","tgn:2001852","tgn:7007825","tgn:7029392"],"placetype":["aat:300008347"],"id":2336374,"name:xx":"Fountain Grove"}}
>>>>>>> 03f74aca74312dbeaf24d7e61306dd6a786dc3d0
