{
  "id": 2120999,
  "type": "Feature",
  "properties": {
    "tgn:hierarchy":[
        "tgn:2120999",
        "tgn:1000001",
        "tgn:2002313",
        "tgn:7012149",
        "tgn:7007922",
        "tgn:7029392"
    ],
    "tgn:id":2120999,
    "tgn:name":"Crescent",
    "tgn:placetype":[
        "aat:300008347",
        "aat:300387210"
    ]
},
  "bbox": [],
  "geometry": {"coordinates":[-91.1333,45.0667],"type":"Point"}
}