{
  "id": 2401977,
  "type": "Feature",
  "properties": {
    "tgn:hierarchy":[
        "tgn:2401977",
        "tgn:1000001",
        "tgn:7012149",
        "tgn:2002279",
        "tgn:7013961",
        "tgn:7029392"
    ],
    "tgn:id":2401977,
    "tgn:name":"Horseshoe Mountain",
    "tgn:placetype":[
        "aat:300008798"
    ]
},
  "bbox": [],
  "geometry": {"coordinates":[-78.8333,39.4833],"type":"Point"}
}