<<<<<<< HEAD
{
  "id": 7052717,
  "type": "Feature",
  "properties": {
    "tgn:hierarchy":[
        "tgn:7052717",
        "tgn:7003139",
        "tgn:1000003",
        "tgn:7003080",
        "tgn:1000080",
        "tgn:7029392"
    ],
    "tgn:id":7052717,
    "tgn:name":"Montione, Poggio",
    "tgn:placetype":[
        "aat:300008795"
    ]
},
  "bbox": [],
  "geometry": {"coordinates":[11.8,42.616667],"type":"Point"}
}
=======
{"geometry":{"type":"Point","coordinates":[11.800000,42.616667]},"type":"Feature","properties":{"hierarchy":["tgn:7052717","tgn:7003139","tgn:1000003","tgn:7003080","tgn:1000080","tgn:7029392"],"placetype":["aat:300008795"],"id":7052717,"name:xx":"Montione, Poggio"}}
>>>>>>> 03f74aca74312dbeaf24d7e61306dd6a786dc3d0
