{
  "id": 1022599,
  "type": "Feature",
  "properties": {
    "tgn:hierarchy":[
        "tgn:1022599",
        "tgn:1001942",
        "tgn:1000047",
        "tgn:7002457",
        "tgn:1000002",
        "tgn:1007248",
        "tgn:7029392"
    ],
    "tgn:id":1022599,
    "tgn:name":"Praia de Ara\u00e7atiba",
    "tgn:placetype":[
        "aat:300008347"
    ]
},
  "bbox": [],
  "geometry": {"coordinates":[-44.35,-23.25],"type":"Point"}
}