{
  "id": 7282755,
  "type": "Feature",
  "properties": {
    "tgn:hierarchy":[
        "tgn:7282755",
        "tgn:1001702",
        "tgn:1000049",
        "tgn:1000002",
        "tgn:7029392"
    ],
    "tgn:id":7282755,
    "tgn:name":"Pe\u00f1aloza, Punta",
    "tgn:placetype":[
        "aat:300386846"
    ]
},
  "bbox": [],
  "geometry": {"coordinates":[-74.616667,-50.833333],"type":"Point"}
}