{
  "id": 7342808,
  "type": "Feature",
  "properties": {
    "tgn:hierarchy":[
        "tgn:7342808",
        "tgn:7002824",
        "tgn:1000003",
        "tgn:7002786",
        "tgn:1000095",
        "tgn:7029392"
    ],
    "tgn:id":7342808,
    "tgn:name":"Cari\u00f1o, Playa de",
    "tgn:placetype":[
        "aat:300008816"
    ]
},
  "bbox": [],
  "geometry": {"coordinates":[-7.866667,43.733333],"type":"Point"}
}