{
  "id": 2668506,
  "type": "Feature",
  "properties": {
    "tgn:hierarchy":[
        "tgn:2668506",
        "tgn:1000001",
        "tgn:7012149",
        "tgn:2000828",
        "tgn:7007255",
        "tgn:7029392"
    ],
    "tgn:id":2668506,
    "tgn:name":"Slate Creek",
    "tgn:placetype":[
        "aat:300008706"
    ]
},
  "bbox": [],
  "geometry": {"coordinates":[-85.6167,36.8667],"type":"Point"}
}