{
  "id": 7543298,
  "type": "Feature",
  "properties": {
    "tgn:hierarchy":[
        "tgn:7543298",
        "tgn:7001242",
        "tgn:7016833",
        "tgn:1001335",
        "tgn:7029392"
    ],
    "tgn:id":7543298,
    "tgn:name:en":"Tir'at Damqash",
    "tgn:placetype":[
        "aat:300006075"
    ]
},
  "bbox": [],
  "geometry": {"coordinates":[31.104069,31.145126],"type":"Point"}
}