{
  "id": 4010913,
  "type": "Feature",
  "properties": {
    "tgn:hierarchy":[
        "tgn:4010913",
        "tgn:7003127",
        "tgn:1000003",
        "tgn:7008516",
        "tgn:1000080",
        "tgn:7029392"
    ],
    "tgn:id":4010913,
    "tgn:name":"Susano",
    "tgn:placetype":[
        "aat:300008347"
    ]
},
  "bbox": [],
  "geometry": {"coordinates":[10.666667,44.35],"type":"Point"}
}