{
  "id": 2476827,
  "type": "Feature",
  "properties": {
    "tgn:hierarchy":[
        "tgn:2476827",
        "tgn:1000001",
        "tgn:7016172",
        "tgn:7012149",
        "tgn:2000144",
        "tgn:7029392"
    ],
    "tgn:id":2476827,
    "tgn:name":"Lyle Creek",
    "tgn:placetype":[
        "aat:300008706"
    ]
},
  "bbox": [],
  "geometry": {"coordinates":[-91.8167,33.7833],"type":"Point"}
}