{
  "id": 7212902,
  "type": "Feature",
  "properties": {
    "tgn:hierarchy":[
        "tgn:7212902",
        "tgn:1000003",
        "tgn:7003689",
        "tgn:7000084",
        "tgn:7029392"
    ],
    "tgn:id":7212902,
    "tgn:name":"Biene",
    "tgn:placetype":[
        "aat:300008863"
    ]
},
  "bbox": [],
  "geometry": {"coordinates":[11.216667,50.316667],"type":"Point"}
}