{
  "id": 1002379,
  "type": "Feature",
  "properties": {
    "tgn:hierarchy":[
        "tgn:1002379",
        "tgn:1000001",
        "tgn:7012149",
        "tgn:7007826",
        "tgn:7029392"
    ],
    "tgn:id":1002379,
    "tgn:name":"Fort Bend",
    "tgn:placetype":[
        "aat:300387145",
        "aat:300000771"
    ]
},
  "bbox": [],
  "geometry": {"coordinates":[-95.7833,29.55],"type":"Point"}
}