{
  "id": 7067690,
  "type": "Feature",
  "properties": {
    "tgn:hierarchy":[
        "tgn:7067690",
        "tgn:1000003",
        "tgn:7003678",
        "tgn:7000084",
        "tgn:7029392"
    ],
    "tgn:id":7067690,
    "tgn:name":"Trais",
    "tgn:placetype":[
        "aat:300008347"
    ]
},
  "bbox": [],
  "geometry": {"coordinates":[8.783333,50.466667],"type":"Point"}
}