{
  "id": 7467297,
  "type": "Feature",
  "properties": {
    "tgn:hierarchy":[
        "tgn:7467297",
        "tgn:1000004",
        "tgn:7467799",
        "tgn:1000141",
        "tgn:7029392"
    ],
    "tgn:id":7467297,
    "tgn:name":"Jiangou",
    "tgn:placetype":[
        "aat:300008347"
    ]
},
  "bbox": [],
  "geometry": {"coordinates":[120.483333,24.15],"type":"Point"}
}