{
  "id": 1011205,
  "type": "Feature",
  "properties": {
    "tgn:hierarchy":[
        "tgn:1011205",
        "tgn:1000003",
        "tgn:7003122",
        "tgn:1001737",
        "tgn:1000080",
        "tgn:7029392"
    ],
    "tgn:id":1011205,
    "tgn:name":"Scaramia, Capo",
    "tgn:placetype":[
        "aat:300008850"
    ]
},
  "bbox": [],
  "geometry": {"coordinates":[14.483333,36.783333],"type":"Point"}
}