{
  "id": 7477931,
  "type": "Feature",
  "properties": {
    "tgn:hierarchy":[
        "tgn:7477931",
        "tgn:1000004",
        "tgn:7001013",
        "tgn:1000141",
        "tgn:7029392"
    ],
    "tgn:id":7477931,
    "tgn:name":"Datan Guoxiao",
    "tgn:placetype":[
        "aat:300006495"
    ]
},
  "bbox": [],
  "geometry": {"coordinates":[121.057974,25.020146],"type":"Point"}
}