{
  "id": 7519215,
  "type": "Feature",
  "properties": {
    "tgn:hierarchy":[
        "tgn:7519215",
        "tgn:1009227",
        "tgn:7001866",
        "tgn:1000226",
        "tgn:1000006",
        "tgn:7029392"
    ],
    "tgn:id":7519215,
    "tgn:name:en":"Broomfield",
    "tgn:placetype":[
        "aat:300000206"
    ]
},
  "bbox": [],
  "geometry": {"coordinates":[172.65,-43.133333],"type":"Point"}
}