{
  "id": 2664040,
  "type": "Feature",
  "properties": {
    "tgn:hierarchy":[
        "tgn:2664040",
        "tgn:1000001",
        "tgn:2001429",
        "tgn:7012149",
        "tgn:7007566",
        "tgn:7029392"
    ],
    "tgn:id":2664040,
    "tgn:name":"Silver Peak",
    "tgn:placetype":[
        "aat:300008798"
    ]
},
  "bbox": [],
  "geometry": {"coordinates":[-108.8167,33.4333],"type":"Point"}
}