{
  "id": 2508668,
  "type": "Feature",
  "properties": {
    "tgn:hierarchy":[
        "tgn:2508668",
        "tgn:1000001",
        "tgn:2001429",
        "tgn:7012149",
        "tgn:7007566",
        "tgn:7029392"
    ],
    "tgn:id":2508668,
    "tgn:name":"Middle Elk Tank",
    "tgn:placetype":[
        "aat:300006191"
    ]
},
  "bbox": [],
  "geometry": {"coordinates":[-108.3167,33.5167],"type":"Point"}
}