<<<<<<< HEAD
{
  "id": 2150888,
  "type": "Feature",
  "properties": {
    "tgn:hierarchy":[
        "tgn:2150888",
        "tgn:1000001",
        "tgn:2002318",
        "tgn:7012149",
        "tgn:7007922",
        "tgn:7029392"
    ],
    "tgn:id":2150888,
    "tgn:name":"Bass Lake",
    "tgn:placetype":[
        "aat:300008680"
    ]
},
  "bbox": [],
  "geometry": {"coordinates":[-91.85,46.2],"type":"Point"}
}
=======
{"geometry":{"type":"Point","coordinates":[-91.850000,46.200000]},"type":"Feature","properties":{"hierarchy":["tgn:2150888","tgn:1000001","tgn:2002318","tgn:7012149","tgn:7007922","tgn:7029392"],"placetype":["aat:300008680"],"id":2150888,"name:xx":"Bass Lake"}}
>>>>>>> 03f74aca74312dbeaf24d7e61306dd6a786dc3d0
