{
  "id": 1102017,
  "type": "Feature",
  "properties": {
    "tgn:hierarchy":[
        "tgn:1102017",
        "tgn:1000001",
        "tgn:2000108",
        "tgn:7016172",
        "tgn:7012149",
        "tgn:7029392"
    ],
    "tgn:id":1102017,
    "tgn:name":"Pea Ridge National Military Park",
    "tgn:placetype":[
        "aat:300000835",
        "aat:300386978"
    ]
},
  "bbox": [],
  "geometry": {"coordinates":[-94.05,36.4333],"type":"Point"}
}