{
  "id": 2687040,
  "type": "Feature",
  "properties": {
    "tgn:hierarchy":[
        "tgn:2687040",
        "tgn:7002659",
        "tgn:1000001",
        "tgn:7012149",
        "tgn:2000054",
        "tgn:7029392"
    ],
    "tgn:id":2687040,
    "tgn:name":"Spring Hill",
    "tgn:placetype":[
        "aat:300008347"
    ]
},
  "bbox": [],
  "geometry": {"coordinates":[-85.95,31.6833],"type":"Point"}
}