{
  "id": 2272509,
  "type": "Feature",
  "properties": {
    "tgn:hierarchy":[
        "tgn:2272509",
        "tgn:1000001",
        "tgn:7012149",
        "tgn:2001200",
        "tgn:7007523",
        "tgn:7029392"
    ],
    "tgn:id":2272509,
    "tgn:name":"Curtis Upper Lake",
    "tgn:placetype":[
        "aat:300006191"
    ]
},
  "bbox": [],
  "geometry": {"coordinates":[-93.4167,40.0667],"type":"Point"}
}