{
  "id": 7477129,
  "type": "Feature",
  "properties": {
    "tgn:hierarchy":[
        "tgn:7477129",
        "tgn:1000004",
        "tgn:1000454",
        "tgn:1000141",
        "tgn:7029392"
    ],
    "tgn:id":7477129,
    "tgn:name":"Zhikeng",
    "tgn:placetype":[
        "aat:300008347"
    ]
},
  "bbox": [],
  "geometry": {"coordinates":[121.809,25.0279],"type":"Point"}
}