{
  "id": 2242206,
  "type": "Feature",
  "properties": {
    "tgn:hierarchy":[
        "tgn:2242206",
        "tgn:1000001",
        "tgn:7012149",
        "tgn:2000974",
        "tgn:7007520",
        "tgn:7029392"
    ],
    "tgn:id":2242206,
    "tgn:name":"Claybank Creek",
    "tgn:placetype":[
        "aat:300008706"
    ]
},
  "bbox": [],
  "geometry": {"coordinates":[-86.1167,44.2333],"type":"Point"}
}