{
  "id": 7047513,
  "type": "Feature",
  "properties": {
    "tgn:hierarchy":[
        "tgn:7047513",
        "tgn:7009084",
        "tgn:7003000",
        "tgn:1000003",
        "tgn:1000080",
        "tgn:7029392"
    ],
    "tgn:id":7047513,
    "tgn:name":"Fallo",
    "tgn:placetype":[
        "aat:300008347"
    ]
},
  "bbox": [],
  "geometry": {"coordinates":[14.316667,41.933333],"type":"Point"}
}