{
  "id": 1103998,
  "type": "Feature",
  "properties": {
    "tgn:hierarchy":[
        "tgn:1103998",
        "tgn:1000001",
        "tgn:7012149",
        "tgn:7007248",
        "tgn:7029392"
    ],
    "tgn:id":1103998,
    "tgn:name":"Blood Mountain",
    "tgn:placetype":[
        "aat:300008795"
    ]
},
  "bbox": [],
  "geometry": {"coordinates":[-83.9333,34.7333],"type":"Point"}
}