<<<<<<< HEAD
{
  "id": 7178898,
  "type": "Feature",
  "properties": {
    "tgn:hierarchy":[
        "tgn:7178898",
        "tgn:7003669",
        "tgn:1000003",
        "tgn:7000084",
        "tgn:7029392"
    ],
    "tgn:id":7178898,
    "tgn:name":"Hammerholz",
    "tgn:placetype":[
        "aat:300008863"
    ]
},
  "bbox": [],
  "geometry": {"coordinates":[12.4,49.283333],"type":"Point"}
}
=======
{"geometry":{"type":"Point","coordinates":[12.400000,49.283333]},"type":"Feature","properties":{"hierarchy":["tgn:7178898","tgn:7003669","tgn:1000003","tgn:7000084","tgn:7029392"],"placetype":["aat:300008863"],"id":7178898,"name:xx":"Hammerholz"}}
>>>>>>> 03f74aca74312dbeaf24d7e61306dd6a786dc3d0
