{
  "id": 7560258,
  "type": "Feature",
  "properties": {
    "tgn:hierarchy":[
        "tgn:7560258",
        "tgn:1000004",
        "tgn:7000198",
        "tgn:7016722",
        "tgn:7029392"
    ],
    "tgn:id":7560258,
    "tgn:name:en":"Chaur\u0101si",
    "tgn:placetype":[
        "aat:300008347"
    ]
},
  "bbox": [],
  "geometry": {"coordinates":[79.673995,27.610095],"type":"Point"}
}