{
  "id": 2216690,
  "type": "Feature",
  "properties": {
    "tgn:hierarchy":[
        "tgn:2216690",
        "tgn:1000001",
        "tgn:2000459",
        "tgn:7012149",
        "tgn:7007250",
        "tgn:7029392"
    ],
    "tgn:id":2216690,
    "tgn:name":"Camp Creek Summer Home Area",
    "tgn:placetype":[
        "aat:300008347"
    ]
},
  "bbox": [],
  "geometry": {"coordinates":[-115.2167,44.1667],"type":"Point"}
}