{
  "id": 2312522,
  "type": "Feature",
  "properties": {
    "tgn:hierarchy":[
        "tgn:2312522",
        "tgn:1000001",
        "tgn:1002293",
        "tgn:7012149",
        "tgn:7007708",
        "tgn:7029392"
    ],
    "tgn:id":2312522,
    "tgn:name":"Eilertsen Creek",
    "tgn:placetype":[
        "aat:300008706"
    ]
},
  "bbox": [],
  "geometry": {"coordinates":[-123.3167,46.0833],"type":"Point"}
}