{
  "id": 1025962,
  "type": "Feature",
  "properties": {
    "tgn:hierarchy":[
        "tgn:1025962",
        "tgn:7003028",
        "tgn:1000003",
        "tgn:1000062",
        "tgn:7029392"
    ],
    "tgn:id":1025962,
    "tgn:name":"Predlitz",
    "tgn:placetype":[
        "aat:300008347"
    ]
},
  "bbox": [],
  "geometry": {"coordinates":[13.9167,47.0667],"type":"Point"}
}