{
  "id": 2224423,
  "type": "Feature",
  "properties": {
    "tgn:hierarchy":[
        "tgn:2224423",
        "tgn:1000001",
        "tgn:7012149",
        "tgn:2001710",
        "tgn:7007708",
        "tgn:7029392"
    ],
    "tgn:id":2224423,
    "tgn:name":"Cascade Spring",
    "tgn:placetype":[
        "aat:300008697"
    ]
},
  "bbox": [],
  "geometry": {"coordinates":[-121.8667,45.6667],"type":"Point"}
}