{
  "id": 7431953,
  "type": "Feature",
  "properties": {
    "tgn:hierarchy":[
        "tgn:7431953",
        "tgn:1000001",
        "tgn:7005595",
        "tgn:7005560",
        "tgn:7029392"
    ],
    "tgn:id":7431953,
    "tgn:name":"Palos Blancos",
    "tgn:placetype":[
        "aat:300008347"
    ]
},
  "bbox": [],
  "geometry": {"coordinates":[-105.916667,23.233333],"type":"Point"}
}