<<<<<<< HEAD
{
  "id": 7177068,
  "type": "Feature",
  "properties": {
    "tgn:hierarchy":[
        "tgn:7177068",
        "tgn:1000003",
        "tgn:7000094",
        "tgn:7000084",
        "tgn:7029392"
    ],
    "tgn:id":7177068,
    "tgn:name":"Hardenort",
    "tgn:placetype":[
        "aat:300008791"
    ]
},
  "bbox": [],
  "geometry": {"coordinates":[12.283333,53.6],"type":"Point"}
}
=======
{"geometry":{"type":"Point","coordinates":[12.283333,53.600000]},"type":"Feature","properties":{"hierarchy":["tgn:7177068","tgn:1000003","tgn:7000094","tgn:7000084","tgn:7029392"],"placetype":["aat:300008791"],"id":7177068,"name:xx":"Hardenort"}}
>>>>>>> 03f74aca74312dbeaf24d7e61306dd6a786dc3d0
