{
  "id": 2636180,
  "type": "Feature",
  "properties": {
    "tgn:hierarchy":[
        "tgn:2636180",
        "tgn:1000001",
        "tgn:2000464",
        "tgn:7012149",
        "tgn:7007250",
        "tgn:7029392"
    ],
    "tgn:id":2636180,
    "tgn:name":"Saddle Reservoir",
    "tgn:placetype":[
        "aat:300006191"
    ]
},
  "bbox": [],
  "geometry": {"coordinates":[-114.4667,43.2167],"type":"Point"}
}