{
  "id": 7292588,
  "type": "Feature",
  "properties": {
    "tgn:hierarchy":[
        "tgn:7292588",
        "tgn:1001630",
        "tgn:1000049",
        "tgn:1000002",
        "tgn:7029392"
    ],
    "tgn:id":7292588,
    "tgn:name":"El Ternerito",
    "tgn:placetype":[
        "aat:300008347"
    ]
},
  "bbox": [],
  "geometry": {"coordinates":[-70.108056,-29.1825],"type":"Point"}
}