<<<<<<< HEAD
{
  "id": 7115690,
  "type": "Feature",
  "properties": {
    "tgn:hierarchy":[
        "tgn:7115690",
        "tgn:1000003",
        "tgn:7003688",
        "tgn:7000084",
        "tgn:7029392"
    ],
    "tgn:id":7115690,
    "tgn:name":"Oxbek",
    "tgn:placetype":[
        "aat:300008699"
    ]
},
  "bbox": [],
  "geometry": {"coordinates":[9.683333,54.633333],"type":"Point"}
}
=======
{"geometry":{"type":"Point","coordinates":[9.683333,54.633333]},"type":"Feature","properties":{"hierarchy":["tgn:7115690","tgn:1000003","tgn:7003688","tgn:7000084","tgn:7029392"],"placetype":["aat:300008699"],"id":7115690,"name:xx":"Oxbek"}}
>>>>>>> 03f74aca74312dbeaf24d7e61306dd6a786dc3d0
