{
  "id": 2650752,
  "type": "Feature",
  "properties": {
    "tgn:hierarchy":[
        "tgn:2650752",
        "tgn:1000001",
        "tgn:7012149",
        "tgn:7014589",
        "tgn:7007515",
        "tgn:7029392"
    ],
    "tgn:id":2650752,
    "tgn:name":"Second Chain Lake",
    "tgn:placetype":[
        "aat:300008680"
    ]
},
  "bbox": [],
  "geometry": {"coordinates":[-67.7167,44.9833],"type":"Point"}
}