{
  "id": 7394621,
  "type": "Feature",
  "properties": {
    "tgn:hierarchy":[
        "tgn:7394621",
        "tgn:1000001",
        "tgn:7005597",
        "tgn:7005560",
        "tgn:7029392"
    ],
    "tgn:id":7394621,
    "tgn:name":"San Ignacio",
    "tgn:placetype":[
        "aat:300008347"
    ]
},
  "bbox": [],
  "geometry": {"coordinates":[-97.45,25.616667],"type":"Point"}
}