<<<<<<< HEAD
{
  "id": 7481158,
  "type": "Feature",
  "properties": {
    "tgn:hierarchy":[
        "tgn:7481158",
        "tgn:1000004",
        "tgn:7492971",
        "tgn:1000141",
        "tgn:7029392"
    ],
    "tgn:id":7481158,
    "tgn:name":"Majia Guozhong",
    "tgn:placetype":[
        "aat:300006495"
    ]
},
  "bbox": [],
  "geometry": {"coordinates":[120.609959,22.70221],"type":"Point"}
}
=======
{"geometry":{"type":"Point","coordinates":[120.609959,22.702210]},"type":"Feature","properties":{"hierarchy":["tgn:7481158","tgn:1000004","tgn:7492971","tgn:1000141","tgn:7029392"],"placetype":["aat:300006495"],"id":7481158,"name:xx":"Majia Guozhong"}}
>>>>>>> 03f74aca74312dbeaf24d7e61306dd6a786dc3d0
