{
  "id": 2120854,
  "type": "Feature",
  "properties": {
    "tgn:hierarchy":[
        "tgn:2120854",
        "tgn:1000001",
        "tgn:7020939",
        "tgn:7012149",
        "tgn:7007922",
        "tgn:7029392"
    ],
    "tgn:id":2120854,
    "tgn:name":"Byron",
    "tgn:placetype":[
        "aat:300008347"
    ]
},
  "bbox": [],
  "geometry": {"coordinates":[-88.45,43.65],"type":"Point"}
}