{
  "id": 2632744,
  "type": "Feature",
  "properties": {
    "tgn:hierarchy":[
        "tgn:2632744",
        "tgn:1000001",
        "tgn:7012149",
        "tgn:2000491",
        "tgn:7007250",
        "tgn:7029392"
    ],
    "tgn:id":2632744,
    "tgn:name":"Ruby Gulch",
    "tgn:placetype":[
        "aat:300008761"
    ]
},
  "bbox": [],
  "geometry": {"coordinates":[-115.8667,47.6333],"type":"Point"}
}