{
  "id": 2624662,
  "type": "Feature",
  "properties": {
    "tgn:hierarchy":[
        "tgn:2624662",
        "tgn:1000001",
        "tgn:7012149",
        "tgn:2002303",
        "tgn:7013961",
        "tgn:7029392"
    ],
    "tgn:id":2624662,
    "tgn:name":"Rock Run",
    "tgn:placetype":[
        "aat:300008699"
    ]
},
  "bbox": [],
  "geometry": {"coordinates":[-81.3833,39.2167],"type":"Point"}
}