{
  "id": 7343945,
  "type": "Feature",
  "properties": {
    "tgn:hierarchy":[
        "tgn:7343945",
        "tgn:7008911",
        "tgn:1000003",
        "tgn:7002763",
        "tgn:1000095",
        "tgn:7029392"
    ],
    "tgn:id":7343945,
    "tgn:name":"Casapap\u00edo",
    "tgn:placetype":[
        "aat:300008347"
    ]
},
  "bbox": [],
  "geometry": {"coordinates":[-5.533333,43.25],"type":"Point"}
}