{
  "id": 7298014,
  "type": "Feature",
  "properties": {
    "tgn:hierarchy":[
        "tgn:7298014",
        "tgn:7002820",
        "tgn:7030216",
        "tgn:1000003",
        "tgn:1000095",
        "tgn:7029392"
    ],
    "tgn:id":7298014,
    "tgn:name":"Seri\u00f1\u00e1",
    "tgn:placetype":[
        "aat:300008347"
    ]
},
  "bbox": [],
  "geometry": {"coordinates":[2.883333,41.866667],"type":"Point"}
}