{
  "id": 7337603,
  "type": "Feature",
  "properties": {
    "tgn:hierarchy":[
        "tgn:7337603",
        "tgn:7002822",
        "tgn:1001647",
        "tgn:1000003",
        "tgn:1000095",
        "tgn:7029392"
    ],
    "tgn:id":7337603,
    "tgn:name":"Checa",
    "tgn:placetype":[
        "aat:300008347"
    ]
},
  "bbox": [],
  "geometry": {"coordinates":[-1.783333,40.583333],"type":"Point"}
}