{
  "id": 2501725,
  "type": "Feature",
  "properties": {
    "tgn:hierarchy":[
        "tgn:2501725",
        "tgn:1000001",
        "tgn:7006451",
        "tgn:2000093",
        "tgn:7012149",
        "tgn:7029392"
    ],
    "tgn:id":2501725,
    "tgn:name":"McInturf Trick Tank",
    "tgn:placetype":[
        "aat:300006191"
    ]
},
  "bbox": [],
  "geometry": {"coordinates":[-110.9167,34.1667],"type":"Point"}
}