{
  "id": 7044158,
  "type": "Feature",
  "properties": {
    "tgn:hierarchy":[
        "tgn:7044158",
        "tgn:7003170",
        "tgn:1000003",
        "tgn:7003125",
        "tgn:1000080",
        "tgn:7029392"
    ],
    "tgn:id":7044158,
    "tgn:name":"Frosinone, F\u00efume",
    "tgn:placetype":[
        "aat:300008699"
    ]
},
  "bbox": [],
  "geometry": {"coordinates":[12.316667,42.916667],"type":"Point"}
}