{
  "id": 4004768,
  "type": "Feature",
  "properties": {
    "tgn:hierarchy":[
        "tgn:4004768",
        "tgn:7002872",
        "tgn:1000003",
        "tgn:1000070",
        "tgn:7029392"
    ],
    "tgn:id":4004768,
    "tgn:name":"Hambye",
    "tgn:placetype":[
        "aat:300008347"
    ]
},
  "bbox": [],
  "geometry": {"coordinates":[-1.2833,48.9333],"type":"Point"}
}