{
  "id": 1038162,
  "type": "Feature",
  "properties": {
    "tgn:hierarchy":[
        "tgn:1038162",
        "tgn:1000003",
        "tgn:7003677",
        "tgn:7000084",
        "tgn:7029392"
    ],
    "tgn:id":1038162,
    "tgn:name":"Alswede",
    "tgn:placetype":[
        "aat:300008347"
    ]
},
  "bbox": [],
  "geometry": {"coordinates":[8.566667,52.333333],"type":"Point"}
}