{
  "id": 2700152,
  "type": "Feature",
  "properties": {
    "tgn:hierarchy":[
        "tgn:2700152",
        "tgn:1000001",
        "tgn:2000540",
        "tgn:7012149",
        "tgn:7007252",
        "tgn:7029392"
    ],
    "tgn:id":2700152,
    "tgn:name":"Stunkard Run",
    "tgn:placetype":[
        "aat:300008699"
    ]
},
  "bbox": [],
  "geometry": {"coordinates":[-87.1167,39.5667],"type":"Point"}
}