{
  "id": 7417537,
  "type": "Feature",
  "properties": {
    "tgn:hierarchy":[
        "tgn:7417537",
        "tgn:1000001",
        "tgn:7005591",
        "tgn:7005560",
        "tgn:7029392"
    ],
    "tgn:id":7417537,
    "tgn:name:es":"Loma de San Juan",
    "tgn:placetype":[
        "aat:300008347"
    ]
},
  "bbox": [],
  "geometry": {"coordinates":[-96.543889,18.171667],"type":"Point"}
}