{
  "id": 7278692,
  "type": "Feature",
  "properties": {
    "tgn:hierarchy":[
        "tgn:7278692",
        "tgn:1001623",
        "tgn:1000049",
        "tgn:1000002",
        "tgn:7029392"
    ],
    "tgn:id":7278692,
    "tgn:name":"Sombrero, Isla",
    "tgn:placetype":[
        "aat:300008791"
    ]
},
  "bbox": [],
  "geometry": {"coordinates":[-74.716667,-47.783333],"type":"Point"}
}