{
  "id": 7504645,
  "type": "Feature",
  "properties": {
    "tgn:hierarchy":[
        "tgn:7504645",
        "tgn:1008380",
        "tgn:1000226",
        "tgn:7018426",
        "tgn:1000006",
        "tgn:7029392"
    ],
    "tgn:id":7504645,
    "tgn:name:en":"Hunters Creek",
    "tgn:placetype":[
        "aat:300008699"
    ]
},
  "bbox": [],
  "geometry": {"coordinates":[176.125,-37.630278],"type":"Point"}
}