{
  "id": 2323743,
  "type": "Feature",
  "properties": {
    "tgn:hierarchy":[
        "tgn:2323743",
        "tgn:1000001",
        "tgn:1002200",
        "tgn:7012149",
        "tgn:7007240",
        "tgn:7029392"
    ],
    "tgn:id":2323743,
    "tgn:name":"Faulk Canal",
    "tgn:placetype":[
        "aat:300006075"
    ]
},
  "bbox": [],
  "geometry": {"coordinates":[-80.7167,28.3167],"type":"Point"}
}