{
  "id": 2569343,
  "type": "Feature",
  "properties": {
    "tgn:hierarchy":[
        "tgn:2569343",
        "tgn:1000001",
        "tgn:2000870",
        "tgn:7012149",
        "tgn:7007256",
        "tgn:7029392"
    ],
    "tgn:id":2569343,
    "tgn:name":"Parkview Oaks South",
    "tgn:placetype":[
        "aat:300008347"
    ]
},
  "bbox": [],
  "geometry": {"coordinates":[-91.0333,30.3833],"type":"Point"}
}