{
  "id": 7016782,
  "type": "Feature",
  "properties": {
    "tgn:hierarchy":[
        "tgn:7016782",
        "tgn:7018566",
        "tgn:7005558",
        "tgn:1000001",
        "tgn:7005556",
        "tgn:7029392"
    ],
    "tgn:id":7016782,
    "tgn:name":"Porus",
    "tgn:placetype":[
        "aat:300008347"
    ]
},
  "bbox": [],
  "geometry": {"coordinates":[-77.411,18.035],"type":"Point"}
}