{
  "id": 7284060,
  "type": "Feature",
  "properties": {
    "tgn:hierarchy":[
        "tgn:7284060",
        "tgn:1001692",
        "tgn:1000049",
        "tgn:1000002",
        "tgn:7029392"
    ],
    "tgn:id":7284060,
    "tgn:name":"Qui\u00f1enahu\u00edn, R\u00edo",
    "tgn:placetype":[
        "aat:300008699"
    ]
},
  "bbox": [],
  "geometry": {"coordinates":[-71.416667,-39.216667],"type":"Point"}
}