{
  "id": 1051720,
  "type": "Feature",
  "properties": {
    "tgn:hierarchy":[
        "tgn:1051720",
        "tgn:6001332",
        "tgn:1000003",
        "tgn:7006660",
        "tgn:7029392"
    ],
    "tgn:id":1051720,
    "tgn:name":"Shramkivka",
    "tgn:placetype":[
        "aat:300008347"
    ]
},
  "bbox": [],
  "geometry": {"coordinates":[32.0833,50.1667],"type":"Point"}
}