<<<<<<< HEAD
{
  "id": 7115624,
  "type": "Feature",
  "properties": {
    "tgn:hierarchy":[
        "tgn:7115624",
        "tgn:7003669",
        "tgn:1000003",
        "tgn:7000084",
        "tgn:7029392"
    ],
    "tgn:id":7115624,
    "tgn:name":"Oberw\u00f6rnitz",
    "tgn:placetype":[
        "aat:300008347"
    ]
},
  "bbox": [],
  "geometry": {"coordinates":[10.25,49.266667],"type":"Point"}
}
=======
{"geometry":{"type":"Point","coordinates":[10.250000,49.266667]},"type":"Feature","properties":{"hierarchy":["tgn:7115624","tgn:7003669","tgn:1000003","tgn:7000084","tgn:7029392"],"placetype":["aat:300008347"],"id":7115624,"name:xx":"Oberw\u00f6rnitz"}}
>>>>>>> 03f74aca74312dbeaf24d7e61306dd6a786dc3d0
