{
  "id": 2164324,
  "type": "Feature",
  "properties": {
    "tgn:hierarchy":[
        "tgn:2164324",
        "tgn:1000001",
        "tgn:7012149",
        "tgn:7016021",
        "tgn:7007568",
        "tgn:7029392"
    ],
    "tgn:id":2164324,
    "tgn:name":"Berry Brook",
    "tgn:placetype":[
        "aat:300008699"
    ]
},
  "bbox": [],
  "geometry": {"coordinates":[-75.0667,44.2833],"type":"Point"}
}