{
  "id": 2196093,
  "type": "Feature",
  "properties": {
    "tgn:hierarchy":[
        "tgn:2196093",
        "tgn:1000001",
        "tgn:7012149",
        "tgn:2001713",
        "tgn:7007708",
        "tgn:7029392"
    ],
    "tgn:id":2196093,
    "tgn:name":"Brockman Gulch",
    "tgn:placetype":[
        "aat:300008761"
    ]
},
  "bbox": [],
  "geometry": {"coordinates":[-123.45,42.55],"type":"Point"}
}