{
  "id": 2103701,
  "type": "Feature",
  "properties": {
    "tgn:hierarchy":[
        "tgn:2103701",
        "tgn:1000001",
        "tgn:7012149",
        "tgn:1002816",
        "tgn:7007826",
        "tgn:7029392"
    ],
    "tgn:id":2103701,
    "tgn:name":"Dougherty",
    "tgn:placetype":[
        "aat:300008347",
        "aat:300387210"
    ]
},
  "bbox": [],
  "geometry": {"coordinates":[-95.7667,32.95],"type":"Point"}
}