{
  "id": 7288995,
  "type": "Feature",
  "properties": {
    "tgn:hierarchy":[
        "tgn:7288995",
        "tgn:1001768",
        "tgn:1000049",
        "tgn:1000002",
        "tgn:7029392"
    ],
    "tgn:id":7288995,
    "tgn:name":"La Bramadora, Loma",
    "tgn:placetype":[
        "aat:300387002"
    ]
},
  "bbox": [],
  "geometry": {"coordinates":[-70.716667,-32.316667],"type":"Point"}
}