{
  "id": 7355412,
  "type": "Feature",
  "properties": {
    "tgn:hierarchy":[
        "tgn:7355412",
        "tgn:1000001",
        "tgn:7005595",
        "tgn:7005560",
        "tgn:7029392"
    ],
    "tgn:id":7355412,
    "tgn:name":"Rancho Cieneguilla",
    "tgn:placetype":[
        "aat:300000241"
    ]
},
  "bbox": [],
  "geometry": {"coordinates":[-107.316667,26.033333],"type":"Point"}
}