{
  "id": 1140054,
  "type": "Feature",
  "properties": {
    "tgn:hierarchy":[
        "tgn:1140054",
        "tgn:1000004",
        "tgn:1001390",
        "tgn:1000111",
        "tgn:7029392"
    ],
    "tgn:id":1140054,
    "tgn:name":"Zhangwu",
    "tgn:placetype":[
        "aat:300008347"
    ]
},
  "bbox": [],
  "geometry": {"coordinates":[122.5167,42.3667],"type":"Point"}
}