{
  "id": 2748989,
  "type": "Feature",
  "properties": {
    "tgn:hierarchy":[
        "tgn:2748989",
        "tgn:7002659",
        "tgn:1000001",
        "tgn:7012149",
        "tgn:7021514",
        "tgn:7029392"
    ],
    "tgn:id":2748989,
    "tgn:name":"Wallace Branch",
    "tgn:placetype":[
        "aat:300008699"
    ]
},
  "bbox": [],
  "geometry": {"coordinates":[-85.95,34.2833],"type":"Point"}
}