{
  "id": 2504829,
  "type": "Feature",
  "properties": {
    "tgn:hierarchy":[
        "tgn:2504829",
        "tgn:1000001",
        "tgn:7012149",
        "tgn:2001453",
        "tgn:7007566",
        "tgn:7029392"
    ],
    "tgn:id":2504829,
    "tgn:name":"Medina Meadows",
    "tgn:placetype":[
        "aat:300055621"
    ]
},
  "bbox": [],
  "geometry": {"coordinates":[-105.3833,35.65],"type":"Point"}
}