{
  "id": 2764718,
  "type": "Feature",
  "properties": {
    "tgn:hierarchy":[
        "tgn:2764718",
        "tgn:1000001",
        "tgn:2001261",
        "tgn:7012149",
        "tgn:7007524",
        "tgn:7029392"
    ],
    "tgn:id":2764718,
    "tgn:name":"Whiskey Coulee Spring",
    "tgn:placetype":[
        "aat:300008697"
    ]
},
  "bbox": [],
  "geometry": {"coordinates":[-108.0167,45.1667],"type":"Point"}
}