{
  "id": 2278751,
  "type": "Feature",
  "properties": {
    "tgn:hierarchy":[
        "tgn:2278751",
        "tgn:1000001",
        "tgn:7012149",
        "tgn:2000820",
        "tgn:7007255",
        "tgn:7029392"
    ],
    "tgn:id":2278751,
    "tgn:name":"Dead Horse Knob",
    "tgn:placetype":[
        "aat:300008798"
    ]
},
  "bbox": [],
  "geometry": {"coordinates":[-84.2833,37.5833],"type":"Point"}
}