{
  "id": 7279860,
  "type": "Feature",
  "properties": {
    "tgn:hierarchy":[
        "tgn:7279860",
        "tgn:7002464",
        "tgn:1000049",
        "tgn:1000002",
        "tgn:7029392"
    ],
    "tgn:id":7279860,
    "tgn:name":"Estaci\u00f3n Ramaditas",
    "tgn:placetype":[
        "aat:300007783"
    ]
},
  "bbox": [],
  "geometry": {"coordinates":[-69.483333,-21.033333],"type":"Point"}
}