{
  "id": 2705535,
  "type": "Feature",
  "properties": {
    "tgn:hierarchy":[
        "tgn:2705535",
        "tgn:1000001",
        "tgn:7012149",
        "tgn:2001706",
        "tgn:7007708",
        "tgn:7029392"
    ],
    "tgn:id":2705535,
    "tgn:name":"Surveyor Creek",
    "tgn:placetype":[
        "aat:300008706"
    ]
},
  "bbox": [],
  "geometry": {"coordinates":[-122.7833,42.9833],"type":"Point"}
}