{
  "id": 1138951,
  "type": "Feature",
  "properties": {
    "tgn:hierarchy":[
        "tgn:1138951",
        "tgn:1000004",
        "tgn:1000958",
        "tgn:1000111",
        "tgn:7029392"
    ],
    "tgn:id":1138951,
    "tgn:name":"Fengcheng",
    "tgn:placetype":[
        "aat:300008347"
    ]
},
  "bbox": [],
  "geometry": {"coordinates":[121.65,30.9167],"type":"Point"}
}