<<<<<<< HEAD
{
  "id": 2258078,
  "type": "Feature",
  "properties": {
    "tgn:hierarchy":[
        "tgn:2258078",
        "tgn:1008293",
        "tgn:1000001",
        "tgn:1002705",
        "tgn:7012149",
        "tgn:7007517",
        "tgn:7029392"
    ],
    "tgn:id":2258078,
    "tgn:name":"Coskata Pond",
    "tgn:placetype":[
        "aat:300008680"
    ]
},
  "bbox": [],
  "geometry": {"coordinates":[-70.0,41.35],"type":"Point"}
}
=======
{"geometry":{"type":"Point","coordinates":[-70.000000,41.350000]},"type":"Feature","properties":{"hierarchy":["tgn:2258078","tgn:1008293","tgn:1000001","tgn:1002705","tgn:7012149","tgn:7007517","tgn:7029392"],"placetype":["aat:300008680"],"id":2258078,"name:xx":"Coskata Pond"}}
>>>>>>> 03f74aca74312dbeaf24d7e61306dd6a786dc3d0
