{
  "id": 7435136,
  "type": "Feature",
  "properties": {
    "tgn:hierarchy":[
        "tgn:7435136",
        "tgn:7005586",
        "tgn:1000001",
        "tgn:7005560",
        "tgn:7029392"
    ],
    "tgn:id":7435136,
    "tgn:name":"Volantin, Cerro el",
    "tgn:placetype":[
        "aat:300008795"
    ]
},
  "bbox": [],
  "geometry": {"coordinates":[-104.916667,20.233333],"type":"Point"}
}