{
  "id": 7581410,
  "type": "Feature",
  "properties": {
    "tgn:hierarchy":[
        "tgn:7581410",
        "tgn:1000004",
        "tgn:1001832",
        "tgn:7000198",
        "tgn:7029392"
    ],
    "tgn:id":7581410,
    "tgn:name:en":"Tisa Jo",
    "tgn:placetype":[
        "aat:300008699"
    ]
},
  "bbox": [],
  "geometry": {"coordinates":[95.195934,26.99346],"type":"Point"}
}