{
  "id": 2306165,
  "type": "Feature",
  "properties": {
    "tgn:hierarchy":[
        "tgn:2306165",
        "tgn:1000001",
        "tgn:7012149",
        "tgn:2000476",
        "tgn:7007250",
        "tgn:7029392"
    ],
    "tgn:id":2306165,
    "tgn:name":"East Fork Big Mallard Creek",
    "tgn:placetype":[
        "aat:300008706"
    ]
},
  "bbox": [],
  "geometry": {"coordinates":[-115.2667,45.5833],"type":"Point"}
}