{
  "id": 7416259,
  "type": "Feature",
  "properties": {
    "tgn:hierarchy":[
        "tgn:7416259",
        "tgn:7005584",
        "tgn:1000001",
        "tgn:7005560",
        "tgn:7029392"
    ],
    "tgn:id":7416259,
    "tgn:name":"Plan de Guanajuato",
    "tgn:placetype":[
        "aat:300008347"
    ]
},
  "bbox": [],
  "geometry": {"coordinates":[-101.696389,20.921667],"type":"Point"}
}