{
  "id": 7188430,
  "type": "Feature",
  "properties": {
    "tgn:hierarchy":[
        "tgn:7188430",
        "tgn:1000003",
        "tgn:7003677",
        "tgn:7000084",
        "tgn:7029392"
    ],
    "tgn:id":7188430,
    "tgn:name":"Eisser H\u00f6he",
    "tgn:placetype":[
        "aat:300008777"
    ]
},
  "bbox": [],
  "geometry": {"coordinates":[9.166667,51.583333],"type":"Point"}
}