{
  "id": 2216495,
  "type": "Feature",
  "properties": {
    "tgn:hierarchy":[
        "tgn:2216495",
        "tgn:1000001",
        "tgn:7012149",
        "tgn:2000885",
        "tgn:7007256",
        "tgn:7029392"
    ],
    "tgn:id":2216495,
    "tgn:name":"Camp Creek",
    "tgn:placetype":[
        "aat:300008706"
    ]
},
  "bbox": [],
  "geometry": {"coordinates":[-90.7667,30.3667],"type":"Point"}
}