{
  "id": 2046480,
  "type": "Feature",
  "properties": {
    "tgn:hierarchy":[
        "tgn:2046480",
        "tgn:1000001",
        "tgn:2124025",
        "tgn:7012149",
        "tgn:7007516",
        "tgn:7029392"
    ],
    "tgn:id":2046480,
    "tgn:name":"Carmichael",
    "tgn:placetype":[
        "aat:300008347",
        "aat:300387210"
    ]
},
  "bbox": [],
  "geometry": {"coordinates":[-76.1333,38.9333],"type":"Point"}
}