<<<<<<< HEAD
{
  "id": 2766051,
  "type": "Feature",
  "properties": {
    "tgn:hierarchy":[
        "tgn:2766051",
        "tgn:1000001",
        "tgn:2001747",
        "tgn:7012149",
        "tgn:7007712",
        "tgn:7029392"
    ],
    "tgn:id":2766051,
    "tgn:name":"White Horse Heights",
    "tgn:placetype":[
        "aat:300008347"
    ]
},
  "bbox": [],
  "geometry": {"coordinates":[-82.45,34.85],"type":"Point"}
}
=======
{"geometry":{"type":"Point","coordinates":[-82.450000,34.850000]},"type":"Feature","properties":{"hierarchy":["tgn:2766051","tgn:1000001","tgn:2001747","tgn:7012149","tgn:7007712","tgn:7029392"],"placetype":["aat:300008347"],"id":2766051,"name:xx":"White Horse Heights"}}
>>>>>>> 03f74aca74312dbeaf24d7e61306dd6a786dc3d0
