{
  "id": 2565585,
  "type": "Feature",
  "properties": {
    "tgn:hierarchy":[
        "tgn:2565585",
        "tgn:1000001",
        "tgn:7012149",
        "tgn:2002055",
        "tgn:7007826",
        "tgn:7029392"
    ],
    "tgn:id":2565585,
    "tgn:name":"Paisano Creek",
    "tgn:placetype":[
        "aat:300008706"
    ]
},
  "bbox": [],
  "geometry": {"coordinates":[-103.3167,30.6333],"type":"Point"}
}