{
  "id": 7285709,
  "type": "Feature",
  "properties": {
    "tgn:hierarchy":[
        "tgn:7285709",
        "tgn:1001699",
        "tgn:1000049",
        "tgn:1000002",
        "tgn:7029392"
    ],
    "tgn:id":7285709,
    "tgn:name":"Quechu\u00e9, Estero",
    "tgn:placetype":[
        "aat:300008699"
    ]
},
  "bbox": [],
  "geometry": {"coordinates":[-73.05,-39.533333],"type":"Point"}
}