{
  "id": 2363104,
  "type": "Feature",
  "properties": {
    "tgn:hierarchy":[
        "tgn:2363104",
        "tgn:1000001",
        "tgn:7012149",
        "tgn:7007157",
        "tgn:1003046",
        "tgn:7029392"
    ],
    "tgn:id":2363104,
    "tgn:name":"Green",
    "tgn:placetype":[
        "aat:300008347"
    ]
},
  "bbox": [],
  "geometry": {"coordinates":[-121.6333,38.3333],"type":"Point"}
}