<<<<<<< HEAD
{
  "id": 7357519,
  "type": "Feature",
  "properties": {
    "tgn:hierarchy":[
        "tgn:7357519",
        "tgn:1000001",
        "tgn:7005590",
        "tgn:7005560",
        "tgn:7029392"
    ],
    "tgn:id":7357519,
    "tgn:name":"Colecio",
    "tgn:placetype":[
        "aat:300008680"
    ]
},
  "bbox": [],
  "geometry": {"coordinates":[-102.266667,20.166667],"type":"Point"}
}
=======
{"geometry":{"type":"Point","coordinates":[-102.266667,20.166667]},"type":"Feature","properties":{"hierarchy":["tgn:7357519","tgn:1000001","tgn:7005590","tgn:7005560","tgn:7029392"],"placetype":["aat:300008680"],"id":7357519,"name:xx":"Colecio"}}
>>>>>>> 03f74aca74312dbeaf24d7e61306dd6a786dc3d0
