{
  "id": 2213742,
  "type": "Feature",
  "properties": {
    "tgn:hierarchy":[
        "tgn:2213742",
        "tgn:1000001",
        "tgn:7012149",
        "tgn:2002382",
        "tgn:7007923",
        "tgn:7029392"
    ],
    "tgn:id":2213742,
    "tgn:name":"Cacklin Lou Reservoir",
    "tgn:placetype":[
        "aat:300006191"
    ]
},
  "bbox": [],
  "geometry": {"coordinates":[-109.65,42.5833],"type":"Point"}
}