<<<<<<< HEAD
{
  "id": 7176373,
  "type": "Feature",
  "properties": {
    "tgn:hierarchy":[
        "tgn:7176373",
        "tgn:7003669",
        "tgn:1000003",
        "tgn:7000084",
        "tgn:7029392"
    ],
    "tgn:id":7176373,
    "tgn:name":"Gr\u00fcnlas",
    "tgn:placetype":[
        "aat:300008863"
    ]
},
  "bbox": [],
  "geometry": {"coordinates":[12.116667,49.933333],"type":"Point"}
}
=======
{"geometry":{"type":"Point","coordinates":[12.116667,49.933333]},"type":"Feature","properties":{"hierarchy":["tgn:7176373","tgn:7003669","tgn:1000003","tgn:7000084","tgn:7029392"],"placetype":["aat:300008863"],"id":7176373,"name:xx":"Gr\u00fcnlas"}}
>>>>>>> 03f74aca74312dbeaf24d7e61306dd6a786dc3d0
