{
  "id": 7584391,
  "type": "Feature",
  "properties": {
    "tgn:hierarchy":[
        "tgn:7584391",
        "tgn:1000004",
        "tgn:7000198",
        "tgn:1001894",
        "tgn:7029392"
    ],
    "tgn:id":7584391,
    "tgn:name:en":"Rampura",
    "tgn:placetype":[
        "aat:300008347"
    ]
},
  "bbox": [],
  "geometry": {"coordinates":[78.830284,24.857249],"type":"Point"}
}