{
  "id": 2526927,
  "type": "Feature",
  "properties": {
    "tgn:hierarchy":[
        "tgn:2526927",
        "tgn:1000001",
        "tgn:7012149",
        "tgn:2000285",
        "tgn:7007240",
        "tgn:7029392"
    ],
    "tgn:id":2526927,
    "tgn:name":"Mound, The",
    "tgn:placetype":[
        "aat:300008798"
    ]
},
  "bbox": [],
  "geometry": {"coordinates":[-87.2833,30.7333],"type":"Point"}
}