{
  "id": 1023040,
  "type": "Feature",
  "properties": {
    "tgn:hierarchy":[
        "tgn:1023040",
        "tgn:1001941",
        "tgn:1000047",
        "tgn:7002458",
        "tgn:1000002",
        "tgn:7029392"
    ],
    "tgn:id":1023040,
    "tgn:name":"Sarandi",
    "tgn:placetype":[
        "aat:300008347"
    ]
},
  "bbox": [],
  "geometry": {"coordinates":[-52.85,-27.95],"type":"Point"}
}