{
  "id": 1112347,
  "type": "Feature",
  "properties": {
    "tgn:hierarchy":[
        "tgn:1112347",
        "tgn:7001242",
        "tgn:1000524",
        "tgn:7016752",
        "tgn:7029392"
    ],
    "tgn:id":1112347,
    "tgn:name":"Beja\u00efa, Golfe de",
    "tgn:placetype":[
        "aat:300132315"
    ]
},
  "bbox": [],
  "geometry": {"coordinates":[5.4167,36.75],"type":"Point"}
}