{
  "id": 7192758,
  "type": "Feature",
  "properties": {
    "tgn:hierarchy":[
        "tgn:7192758",
        "tgn:7000096",
        "tgn:1000003",
        "tgn:7000084",
        "tgn:7029392"
    ],
    "tgn:id":7192758,
    "tgn:name":"Ferdinandshof",
    "tgn:placetype":[
        "aat:300000206"
    ]
},
  "bbox": [],
  "geometry": {"coordinates":[14.233333,52.783333],"type":"Point"}
}