{
  "id": 2180702,
  "type": "Feature",
  "properties": {
    "tgn:hierarchy":[
        "tgn:2180702",
        "tgn:1000001",
        "tgn:7012149",
        "tgn:1003007",
        "tgn:7007706",
        "tgn:7029392"
    ],
    "tgn:id":2180702,
    "tgn:name":"Bloomingdale",
    "tgn:placetype":[
        "aat:300008347"
    ]
},
  "bbox": [],
  "geometry": {"coordinates":[-82.5333,40.3333],"type":"Point"}
}