{
  "id": 1038244,
  "type": "Feature",
  "properties": {
    "tgn:hierarchy":[
        "tgn:1038244",
        "tgn:1000003",
        "tgn:7003676",
        "tgn:7000084",
        "tgn:7029392"
    ],
    "tgn:id":1038244,
    "tgn:name":"Aschendorf",
    "tgn:placetype":[
        "aat:300008347"
    ]
},
  "bbox": [],
  "geometry": {"coordinates":[7.333333,53.05],"type":"Point"}
}