{
  "id": 7432581,
  "type": "Feature",
  "properties": {
    "tgn:hierarchy":[
        "tgn:7432581",
        "tgn:1000001",
        "tgn:1001937",
        "tgn:7005560",
        "tgn:7029392"
    ],
    "tgn:id":7432581,
    "tgn:name":"Ucum, R\u00edo de",
    "tgn:placetype":[
        "aat:300008699"
    ]
},
  "bbox": [],
  "geometry": {"coordinates":[-88.483333,18.483333],"type":"Point"}
}