{
  "id": 2242364,
  "type": "Feature",
  "properties": {
    "tgn:hierarchy":[
        "tgn:2242364",
        "tgn:1000001",
        "tgn:7012149",
        "tgn:2001969",
        "tgn:7007826",
        "tgn:7029392"
    ],
    "tgn:id":2242364,
    "tgn:name":"Clayton Draw",
    "tgn:placetype":[
        "aat:300008761"
    ]
},
  "bbox": [],
  "geometry": {"coordinates":[-104.4833,31.3167],"type":"Point"}
}