{
  "id": 7589446,
  "type": "Feature",
  "properties": {
    "tgn:hierarchy":[
        "tgn:7589446",
        "tgn:1000004",
        "tgn:7000198",
        "tgn:7000799",
        "tgn:7029392"
    ],
    "tgn:id":7589446,
    "tgn:name:en":"Ber\u0101draman",
    "tgn:placetype":[
        "aat:300008699"
    ]
},
  "bbox": [],
  "geometry": {"coordinates":[74.35,33.152778],"type":"Point"}
}