<<<<<<< HEAD
{
  "id": 2155167,
  "type": "Feature",
  "properties": {
    "tgn:hierarchy":[
        "tgn:2155167",
        "tgn:7006450",
        "tgn:1000001",
        "tgn:7019698",
        "tgn:7012149",
        "tgn:7029392"
    ],
    "tgn:id":2155167,
    "tgn:name":"Bear Lake Glacier",
    "tgn:placetype":[
        "aat:300008835"
    ]
},
  "bbox": [],
  "geometry": {"coordinates":[-149.2333,60.1667],"type":"Point"}
}
=======
{"geometry":{"type":"Point","coordinates":[-149.233300,60.166700]},"type":"Feature","properties":{"hierarchy":["tgn:2155167","tgn:7006450","tgn:1000001","tgn:7019698","tgn:7012149","tgn:7029392"],"placetype":["aat:300008835"],"id":2155167,"name:xx":"Bear Lake Glacier"}}
>>>>>>> 03f74aca74312dbeaf24d7e61306dd6a786dc3d0
