{
  "id": 2155167,
  "type": "Feature",
  "properties": {
    "tgn:hierarchy":[
        "tgn:2155167",
        "tgn:7006450",
        "tgn:1000001",
        "tgn:7019698",
        "tgn:7012149",
        "tgn:7029392"
    ],
    "tgn:id":2155167,
    "tgn:name":"Bear Lake Glacier",
    "tgn:placetype":[
        "aat:300008835"
    ]
},
  "bbox": [],
  "geometry": {"coordinates":[-149.2333,60.1667],"type":"Point"}
}