{
  "id": 2282548,
  "type": "Feature",
  "properties": {
    "tgn:hierarchy":[
        "tgn:2282548",
        "tgn:1000001",
        "tgn:7012149",
        "tgn:1002990",
        "tgn:7007708",
        "tgn:7029392"
    ],
    "tgn:id":2282548,
    "tgn:name":"Deer Spring",
    "tgn:placetype":[
        "aat:300008697"
    ]
},
  "bbox": [],
  "geometry": {"coordinates":[-121.4333,45.0667],"type":"Point"}
}