{
  "id": 2648898,
  "type": "Feature",
  "properties": {
    "tgn:hierarchy":[
        "tgn:2648898",
        "tgn:1000001",
        "tgn:7012149",
        "tgn:2001515",
        "tgn:7007709",
        "tgn:7029392"
    ],
    "tgn:id":2648898,
    "tgn:name":"Scott Branch",
    "tgn:placetype":[
        "aat:300008699"
    ]
},
  "bbox": [],
  "geometry": {"coordinates":[-83.3167,35.1667],"type":"Point"}
}