{
  "id": 2573133,
  "type": "Feature",
  "properties": {
    "tgn:hierarchy":[
        "tgn:2573133",
        "tgn:1000001",
        "tgn:7012149",
        "tgn:7007157",
        "tgn:1002863",
        "tgn:7029392"
    ],
    "tgn:id":2573133,
    "tgn:name":"Pearson Spring",
    "tgn:placetype":[
        "aat:300008697"
    ]
},
  "bbox": [],
  "geometry": {"coordinates":[-119.8833,35.0833],"type":"Point"}
}