{
  "id": 7533088,
  "type": "Feature",
  "properties": {
    "tgn:hierarchy":[
        "tgn:7533088",
        "tgn:7001242",
        "tgn:7016833",
        "tgn:1001091",
        "tgn:7029392"
    ],
    "tgn:id":7533088,
    "tgn:name":"Mustashf\u00e1 B\u016bl\u0101q al '\u0100mm",
    "tgn:placetype":[
        "aat:300006676"
    ]
},
  "bbox": [],
  "geometry": {"coordinates":[31.228979,30.062977],"type":"Point"}
}