{
  "id": 1133135,
  "type": "Feature",
  "properties": {
    "tgn:hierarchy":[
        "tgn:1133135",
        "tgn:1001902",
        "tgn:1000002",
        "tgn:1000059",
        "tgn:7029392"
    ],
    "tgn:id":1133135,
    "tgn:name":"El Hatillo, Quebrada",
    "tgn:placetype":[
        "aat:300008706"
    ]
},
  "bbox": [],
  "geometry": {"coordinates":[-66.7833,10.45],"type":"Point"}
}