{
  "id": 7439973,
  "type": "Feature",
  "properties": {
    "tgn:hierarchy":[
        "tgn:7439973",
        "tgn:1000001",
        "tgn:1001893",
        "tgn:7005560",
        "tgn:7029392"
    ],
    "tgn:id":7439973,
    "tgn:name":"Santa Mar\u00eda Nativitas",
    "tgn:placetype":[
        "aat:300008347"
    ]
},
  "bbox": [],
  "geometry": {"coordinates":[-99.822778,19.287778],"type":"Point"}
}