{
  "id": 2132931,
  "type": "Feature",
  "properties": {
    "tgn:hierarchy":[
        "tgn:2132931",
        "tgn:7006450",
        "tgn:1000001",
        "tgn:7012149",
        "tgn:2000079",
        "tgn:7029392"
    ],
    "tgn:id":2132931,
    "tgn:name":"Anderson Creek",
    "tgn:placetype":[
        "aat:300008706"
    ]
},
  "bbox": [],
  "geometry": {"coordinates":[-167.1333,65.5167],"type":"Point"}
}