<<<<<<< HEAD
{
  "id": 7116030,
  "type": "Feature",
  "properties": {
    "tgn:hierarchy":[
        "tgn:7116030",
        "tgn:7003692",
        "tgn:1000003",
        "tgn:7000084",
        "tgn:7029392"
    ],
    "tgn:id":7116030,
    "tgn:name":"\u00d6hlershof",
    "tgn:placetype":[
        "aat:300000206"
    ]
},
  "bbox": [],
  "geometry": {"coordinates":[8.15,47.933333],"type":"Point"}
}
=======
{"geometry":{"type":"Point","coordinates":[8.150000,47.933333]},"type":"Feature","properties":{"hierarchy":["tgn:7116030","tgn:7003692","tgn:1000003","tgn:7000084","tgn:7029392"],"placetype":["aat:300000206"],"id":7116030,"name:xx":"\u00d6hlershof"}}
>>>>>>> 03f74aca74312dbeaf24d7e61306dd6a786dc3d0
