<<<<<<< HEAD
{
  "id": 7358131,
  "type": "Feature",
  "properties": {
    "tgn:hierarchy":[
        "tgn:7358131",
        "tgn:1001835",
        "tgn:1000001",
        "tgn:7005560",
        "tgn:7029392"
    ],
    "tgn:id":7358131,
    "tgn:name":"Colonia L\u00e1zaro Cardenas",
    "tgn:placetype":[
        "aat:300008347"
    ]
},
  "bbox": [],
  "geometry": {"coordinates":[-115.716667,31.383333],"type":"Point"}
}
=======
{"geometry":{"type":"Point","coordinates":[-115.716667,31.383333]},"type":"Feature","properties":{"hierarchy":["tgn:7358131","tgn:1001835","tgn:1000001","tgn:7005560","tgn:7029392"],"placetype":["aat:300008347"],"id":7358131,"name:xx":"Colonia L\u00e1zaro Cardenas"}}
>>>>>>> 03f74aca74312dbeaf24d7e61306dd6a786dc3d0
