{
  "id": 2722954,
  "type": "Feature",
  "properties": {
    "tgn:hierarchy":[
        "tgn:2722954",
        "tgn:1000001",
        "tgn:7012149",
        "tgn:2000232",
        "tgn:7007158",
        "tgn:7029392"
    ],
    "tgn:id":2722954,
    "tgn:name":"Tipton Ditch",
    "tgn:placetype":[
        "aat:300006075"
    ]
},
  "bbox": [],
  "geometry": {"coordinates":[-107.3833,40.6667],"type":"Point"}
}