{
  "id": 2460875,
  "type": "Feature",
  "properties": {
    "tgn:hierarchy":[
        "tgn:2460875",
        "tgn:1000001",
        "tgn:7012149",
        "tgn:2000969",
        "tgn:7007520",
        "tgn:7029392"
    ],
    "tgn:id":2460875,
    "tgn:name":"Little Siskiwit River",
    "tgn:placetype":[
        "aat:300008707"
    ]
},
  "bbox": [],
  "geometry": {"coordinates":[-89.0333,47.9167],"type":"Point"}
}