{
  "id": 7180436,
  "type": "Feature",
  "properties": {
    "tgn:hierarchy":[
        "tgn:7180436",
        "tgn:7000096",
        "tgn:1000003",
        "tgn:7000084",
        "tgn:7029392"
    ],
    "tgn:id":7180436,
    "tgn:name":"Fuchs-Berg",
    "tgn:placetype":[
        "aat:300008777"
    ]
},
  "bbox": [],
  "geometry": {"coordinates":[13.983333,53.366667],"type":"Point"}
}