{
  "id": 7214772,
  "type": "Feature",
  "properties": {
    "tgn:hierarchy":[
        "tgn:7214772",
        "tgn:1000003",
        "tgn:7003682",
        "tgn:7000084",
        "tgn:7029392"
    ],
    "tgn:id":7214772,
    "tgn:name":"Bohnenbach",
    "tgn:placetype":[
        "aat:300008699"
    ]
},
  "bbox": [],
  "geometry": {"coordinates":[6.366667,50.083333],"type":"Point"}
}