{
  "id": 1062561,
  "type": "Feature",
  "properties": {
    "tgn:hierarchy":[
        "tgn:1062561",
        "tgn:7010420",
        "tgn:1000003",
        "tgn:7002795",
        "tgn:1000095",
        "tgn:7029392"
    ],
    "tgn:id":1062561,
    "tgn:name":"Torrej\u00f3n de Ardoz",
    "tgn:placetype":[
        "aat:300008347"
    ]
},
  "bbox": [],
  "geometry": {"coordinates":[-3.483333,40.45],"type":"Point"}
}