<<<<<<< HEAD
{
  "id": 2766189,
  "type": "Feature",
  "properties": {
    "tgn:hierarchy":[
        "tgn:2766189",
        "tgn:1000001",
        "tgn:7012149",
        "tgn:2001300",
        "tgn:7007524",
        "tgn:7029392"
    ],
    "tgn:id":2766189,
    "tgn:name":"White Lake",
    "tgn:placetype":[
        "aat:300008680"
    ]
},
  "bbox": [],
  "geometry": {"coordinates":[-114.4,46.0833],"type":"Point"}
}
=======
{"geometry":{"type":"Point","coordinates":[-114.400000,46.083300]},"type":"Feature","properties":{"hierarchy":["tgn:2766189","tgn:1000001","tgn:7012149","tgn:2001300","tgn:7007524","tgn:7029392"],"placetype":["aat:300008680"],"id":2766189,"name:xx":"White Lake"}}
>>>>>>> 03f74aca74312dbeaf24d7e61306dd6a786dc3d0
