{
  "id": 1061622,
  "type": "Feature",
  "properties": {
    "tgn:hierarchy":[
        "tgn:1061622",
        "tgn:7012152",
        "tgn:1000003",
        "tgn:7006541",
        "tgn:7029392"
    ],
    "tgn:id":1061622,
    "tgn:name":"Zilupe",
    "tgn:placetype":[
        "aat:300008347"
    ]
},
  "bbox": [],
  "geometry": {"coordinates":[28.0667,56.4333],"type":"Point"}
}