{
  "id": 1017761,
  "type": "Feature",
  "properties": {
    "tgn:hierarchy":[
        "tgn:1017761",
        "tgn:1000001",
        "tgn:7005599",
        "tgn:7005560",
        "tgn:7029392"
    ],
    "tgn:id":1017761,
    "tgn:name":"Las Vigas",
    "tgn:placetype":[
        "aat:300008347"
    ]
},
  "bbox": [],
  "geometry": {"coordinates":[-97.083333,19.633333],"type":"Point"}
}