{
  "id": 2501892,
  "type": "Feature",
  "properties": {
    "tgn:hierarchy":[
        "tgn:2501892",
        "tgn:1000001",
        "tgn:7012149",
        "tgn:2001502",
        "tgn:7007709",
        "tgn:7029392"
    ],
    "tgn:id":2501892,
    "tgn:name":"McKay, Lake",
    "tgn:placetype":[
        "aat:300006191"
    ]
},
  "bbox": [],
  "geometry": {"coordinates":[-78.95,35.2333],"type":"Point"}
}