{
  "id": 7590811,
  "type": "Feature",
  "properties": {
    "tgn:hierarchy":[
        "tgn:7590811",
        "tgn:1000004",
        "tgn:7000198",
        "tgn:7000799",
        "tgn:7029392"
    ],
    "tgn:id":7590811,
    "tgn:name:en":"Panjgir\u0101\u012bn",
    "tgn:placetype":[
        "aat:300008347"
    ]
},
  "bbox": [],
  "geometry": {"coordinates":[74.758638,32.511697],"type":"Point"}
}