{
  "id": 7547434,
  "type": "Feature",
  "properties": {
    "tgn:hierarchy":[
        "tgn:7547434",
        "tgn:1000004",
        "tgn:7000198",
        "tgn:7016722",
        "tgn:7029392"
    ],
    "tgn:id":7547434,
    "tgn:name:en":"Aharan",
    "tgn:placetype":[
        "aat:300008347"
    ]
},
  "bbox": [],
  "geometry": {"coordinates":[78.237668,27.35765],"type":"Point"}
}