{
  "id": 2262773,
  "type": "Feature",
  "properties": {
    "tgn:hierarchy":[
        "tgn:2262773",
        "tgn:1000001",
        "tgn:7012149",
        "tgn:2002062",
        "tgn:7007826",
        "tgn:7029392"
    ],
    "tgn:id":2262773,
    "tgn:name":"Cowan Springs",
    "tgn:placetype":[
        "aat:300008697"
    ]
},
  "bbox": [],
  "geometry": {"coordinates":[-103.8333,31.05],"type":"Point"}
}