<<<<<<< HEAD
{
  "id": 2255485,
  "type": "Feature",
  "properties": {
    "tgn:hierarchy":[
        "tgn:2255485",
        "tgn:1000001",
        "tgn:2000772",
        "tgn:7012149",
        "tgn:7007255",
        "tgn:7029392"
    ],
    "tgn:id":2255485,
    "tgn:name":"Cope Fork",
    "tgn:placetype":[
        "aat:300008699"
    ]
},
  "bbox": [],
  "geometry": {"coordinates":[-83.2667,37.6167],"type":"Point"}
}
=======
{"geometry":{"type":"Point","coordinates":[-83.266700,37.616700]},"type":"Feature","properties":{"hierarchy":["tgn:2255485","tgn:1000001","tgn:2000772","tgn:7012149","tgn:7007255","tgn:7029392"],"placetype":["aat:300008699"],"id":2255485,"name:xx":"Cope Fork"}}
>>>>>>> 03f74aca74312dbeaf24d7e61306dd6a786dc3d0
