{
  "id": 2718364,
  "type": "Feature",
  "properties": {
    "tgn:hierarchy":[
        "tgn:2718364",
        "tgn:1000001",
        "tgn:7012149",
        "tgn:2000473",
        "tgn:7007250",
        "tgn:7029392"
    ],
    "tgn:id":2718364,
    "tgn:name":"Thompson Hole",
    "tgn:placetype":[
        "aat:300006191"
    ]
},
  "bbox": [],
  "geometry": {"coordinates":[-111.05,44.0833],"type":"Point"}
}