{
  "id": 2176615,
  "type": "Feature",
  "properties": {
    "tgn:hierarchy":[
        "tgn:2176615",
        "tgn:1000001",
        "tgn:7012149",
        "tgn:1002954",
        "tgn:7007826",
        "tgn:7029392"
    ],
    "tgn:id":2176615,
    "tgn:name":"Black Lake Creek",
    "tgn:placetype":[
        "aat:300008706"
    ]
},
  "bbox": [],
  "geometry": {"coordinates":[-95.0667,31.2333],"type":"Point"}
}