{
  "id": 7357062,
  "type": "Feature",
  "properties": {
    "tgn:hierarchy":[
        "tgn:7357062",
        "tgn:1000001",
        "tgn:1001960",
        "tgn:7005560",
        "tgn:7029392"
    ],
    "tgn:id":7357062,
    "tgn:name":"Carrizal, Sierra del",
    "tgn:placetype":[
        "aat:300008795"
    ]
},
  "bbox": [],
  "geometry": {"coordinates":[-111.533333,31.066667],"type":"Point"}
}