{
  "id": 2341615,
  "type": "Feature",
  "properties": {
    "tgn:hierarchy":[
        "tgn:2341615",
        "tgn:1000001",
        "tgn:7012149",
        "tgn:2001873",
        "tgn:7007825",
        "tgn:7029392"
    ],
    "tgn:id":2341615,
    "tgn:name":"Front Hollow",
    "tgn:placetype":[
        "aat:300008761"
    ]
},
  "bbox": [],
  "geometry": {"coordinates":[-82.6333,36.4833],"type":"Point"}
}