{
  "id": 2675146,
  "type": "Feature",
  "properties": {
    "tgn:hierarchy":[
        "tgn:2675146",
        "tgn:1000001",
        "tgn:2001265",
        "tgn:7012149",
        "tgn:7007524",
        "tgn:7029392"
    ],
    "tgn:id":2675146,
    "tgn:name":"Soft Water Draw",
    "tgn:placetype":[
        "aat:300008761"
    ]
},
  "bbox": [],
  "geometry": {"coordinates":[-104.45,45.65],"type":"Point"}
}