<<<<<<< HEAD
{
  "id": 2401613,
  "type": "Feature",
  "properties": {
    "tgn:hierarchy":[
        "tgn:2401613",
        "tgn:1000001",
        "tgn:2001425",
        "tgn:7012149",
        "tgn:7007564",
        "tgn:7029392"
    ],
    "tgn:id":2401613,
    "tgn:name":"Horseshoe Island",
    "tgn:placetype":[
        "aat:300008791"
    ]
},
  "bbox": [],
  "geometry": {"coordinates":[-71.5333,43.2167],"type":"Point"}
}
=======
{"geometry":{"type":"Point","coordinates":[-71.533300,43.216700]},"type":"Feature","properties":{"hierarchy":["tgn:2401613","tgn:1000001","tgn:2001425","tgn:7012149","tgn:7007564","tgn:7029392"],"placetype":["aat:300008791"],"id":2401613,"name:xx":"Horseshoe Island"}}
>>>>>>> 03f74aca74312dbeaf24d7e61306dd6a786dc3d0
