{
  "id": 1113327,
  "type": "Feature",
  "properties": {
    "tgn:hierarchy":[
        "tgn:1113327",
        "tgn:7002444",
        "tgn:1000003",
        "tgn:7008591",
        "tgn:7029392"
    ],
    "tgn:id":1113327,
    "tgn:name:en":"Linnhe, Loch",
    "tgn:placetype":[
        "aat:300132316"
    ]
},
  "bbox": [],
  "geometry": {"coordinates":[-5.35,56.65],"type":"Point"}
}