{
  "id": 7553302,
  "type": "Feature",
  "properties": {
    "tgn:hierarchy":[
        "tgn:7553302",
        "tgn:1001828",
        "tgn:1000004",
        "tgn:7000198",
        "tgn:7029392"
    ],
    "tgn:id":7553302,
    "tgn:name:en":"Mummidivaram",
    "tgn:placetype":[
        "aat:300008347"
    ]
},
  "bbox": [],
  "geometry": {"coordinates":[82.116667,16.65],"type":"Point"}
}