{
  "id": 7586161,
  "type": "Feature",
  "properties": {
    "tgn:hierarchy":[
        "tgn:7586161",
        "tgn:1000004",
        "tgn:7000198",
        "tgn:7000799",
        "tgn:7029392"
    ],
    "tgn:id":7586161,
    "tgn:name:en":"Saidpokhari Spring",
    "tgn:placetype":[
        "aat:300008697"
    ]
},
  "bbox": [],
  "geometry": {"coordinates":[74.913889,34.344444],"type":"Point"}
}