{
  "id": 2569961,
  "type": "Feature",
  "properties": {
    "tgn:hierarchy":[
        "tgn:2569961",
        "tgn:7002659",
        "tgn:1000001",
        "tgn:2000015",
        "tgn:7012149",
        "tgn:7029392"
    ],
    "tgn:id":2569961,
    "tgn:name":"Paschal Pond",
    "tgn:placetype":[
        "aat:300006191"
    ]
},
  "bbox": [],
  "geometry": {"coordinates":[-85.85,31.2667],"type":"Point"}
}