{
  "id": 7513798,
  "type": "Feature",
  "properties": {
    "tgn:hierarchy":[
        "tgn:7513798",
        "tgn:1008380",
        "tgn:7520093",
        "tgn:1000226",
        "tgn:1000006",
        "tgn:7029392"
    ],
    "tgn:id":7513798,
    "tgn:name:en":"Flat Spur",
    "tgn:placetype":[
        "aat:300008795"
    ]
},
  "bbox": [],
  "geometry": {"coordinates":[175.866667,-39.733333],"type":"Point"}
}