{
  "id": 2464434,
  "type": "Feature",
  "properties": {
    "tgn:hierarchy":[
        "tgn:2464434",
        "tgn:1000001",
        "tgn:2001703",
        "tgn:7012149",
        "tgn:7007708",
        "tgn:7029392"
    ],
    "tgn:id":2464434,
    "tgn:name":"Lofton Creek",
    "tgn:placetype":[
        "aat:300008706"
    ]
},
  "bbox": [],
  "geometry": {"coordinates":[-120.8667,44.4667],"type":"Point"}
}