{
  "id": 2214902,
  "type": "Feature",
  "properties": {
    "tgn:hierarchy":[
        "tgn:2214902",
        "tgn:1000001",
        "tgn:7012149",
        "tgn:2002246",
        "tgn:7007920",
        "tgn:7029392"
    ],
    "tgn:id":2214902,
    "tgn:name":"Caliche Lakes",
    "tgn:placetype":[
        "aat:300008680"
    ]
},
  "bbox": [],
  "geometry": {"coordinates":[-119.9167,47.0167],"type":"Point"}
}