<<<<<<< HEAD
{
  "id": 7176248,
  "type": "Feature",
  "properties": {
    "tgn:hierarchy":[
        "tgn:7176248",
        "tgn:1000003",
        "tgn:7003685",
        "tgn:7000084",
        "tgn:7029392"
    ],
    "tgn:id":7176248,
    "tgn:name":"Gro\u00df-Teich",
    "tgn:placetype":[
        "aat:300008688"
    ]
},
  "bbox": [],
  "geometry": {"coordinates":[13.583333,51.183333],"type":"Point"}
}
=======
{"geometry":{"type":"Point","coordinates":[13.583333,51.183333]},"type":"Feature","properties":{"hierarchy":["tgn:7176248","tgn:1000003","tgn:7003685","tgn:7000084","tgn:7029392"],"placetype":["aat:300008688"],"id":7176248,"name:xx":"Gro\u00df-Teich"}}
>>>>>>> 03f74aca74312dbeaf24d7e61306dd6a786dc3d0
