{
  "id": 2265699,
  "type": "Feature",
  "properties": {
    "tgn:hierarchy":[
        "tgn:2265699",
        "tgn:1000001",
        "tgn:7012149",
        "tgn:2000733",
        "tgn:7007254",
        "tgn:7029392"
    ],
    "tgn:id":2265699,
    "tgn:name":"Crappie Point",
    "tgn:placetype":[
        "aat:300008850"
    ]
},
  "bbox": [],
  "geometry": {"coordinates":[-99.1333,39.6333],"type":"Point"}
}