{
  "id": 1065413,
  "type": "Feature",
  "properties": {
    "tgn:hierarchy":[
        "tgn:1065413",
        "tgn:7016612",
        "tgn:1000004",
        "tgn:1001608",
        "tgn:7029392"
    ],
    "tgn:id":1065413,
    "tgn:name":"Darakht-e Yahya",
    "tgn:placetype":[
        "aat:300008347"
    ]
},
  "bbox": [],
  "geometry": {"coordinates":[68.1333,31.8167],"type":"Point"}
}