{
  "id": 2462113,
  "type": "Feature",
  "properties": {
    "tgn:hierarchy":[
        "tgn:2462113",
        "tgn:1000001",
        "tgn:7012149",
        "tgn:2002127",
        "tgn:7007827",
        "tgn:7029392"
    ],
    "tgn:id":2462113,
    "tgn:name":"Little Valley",
    "tgn:placetype":[
        "aat:300386845"
    ]
},
  "bbox": [],
  "geometry": {"coordinates":[-113.5333,37.05],"type":"Point"}
}