{
  "id": 2746463,
  "type": "Feature",
  "properties": {
    "tgn:hierarchy":[
        "tgn:2746463",
        "tgn:7023902",
        "tgn:1000001",
        "tgn:7012149",
        "tgn:7007249",
        "tgn:7029392"
    ],
    "tgn:id":2746463,
    "tgn:name":"Waawaa Point",
    "tgn:placetype":[
        "aat:300008850"
    ]
},
  "bbox": [],
  "geometry": {"coordinates":[-155.8667,19.9333],"type":"Point"}
}