{
  "id": 7472748,
  "type": "Feature",
  "properties": {
    "tgn:hierarchy":[
        "tgn:7472748",
        "tgn:1000004",
        "tgn:7491221",
        "tgn:1000141",
        "tgn:7029392"
    ],
    "tgn:id":7472748,
    "tgn:name":"Wutou Shan",
    "tgn:placetype":[
        "aat:300008795"
    ]
},
  "bbox": [],
  "geometry": {"coordinates":[120.786667,22.692778],"type":"Point"}
}