{
  "id": 2080459,
  "type": "Feature",
  "properties": {
    "tgn:hierarchy":[
        "tgn:2080459",
        "tgn:1000001",
        "tgn:7012149",
        "tgn:1002917",
        "tgn:7007706",
        "tgn:7029392"
    ],
    "tgn:id":2080459,
    "tgn:name":"Louisville",
    "tgn:placetype":[
        "aat:300008347"
    ]
},
  "bbox": [],
  "geometry": {"coordinates":[-81.25,40.8333],"type":"Point"}
}