{
  "id": 7083537,
  "type": "Feature",
  "properties": {
    "tgn:hierarchy":[
        "tgn:7083537",
        "tgn:7003669",
        "tgn:1000003",
        "tgn:7000084",
        "tgn:7029392"
    ],
    "tgn:id":7083537,
    "tgn:name":"Wellmersdorf",
    "tgn:placetype":[
        "aat:300008347"
    ]
},
  "bbox": [],
  "geometry": {"coordinates":[11.116667,50.283333],"type":"Point"}
}