{
  "id": 7369262,
  "type": "Feature",
  "properties": {
    "tgn:hierarchy":[
        "tgn:7369262",
        "tgn:1000001",
        "tgn:7005592",
        "tgn:7005560",
        "tgn:7029392"
    ],
    "tgn:id":7369262,
    "tgn:name":"Hornos",
    "tgn:placetype":[
        "aat:300008347"
    ]
},
  "bbox": [],
  "geometry": {"coordinates":[-97.733333,18.616667],"type":"Point"}
}