{
  "id": 2230139,
  "type": "Feature",
  "properties": {
    "tgn:hierarchy":[
        "tgn:2230139",
        "tgn:1000001",
        "tgn:7006451",
        "tgn:2000093",
        "tgn:7012149",
        "tgn:7029392"
    ],
    "tgn:id":2230139,
    "tgn:name":"Cement Dam Tank",
    "tgn:placetype":[
        "aat:300006191"
    ]
},
  "bbox": [],
  "geometry": {"coordinates":[-110.85,33.8333],"type":"Point"}
}