{
  "id": 2776203,
  "type": "Feature",
  "properties": {
    "tgn:hierarchy":[
        "tgn:2776203",
        "tgn:1000001",
        "tgn:7012149",
        "tgn:2001112",
        "tgn:7007522",
        "tgn:7029392"
    ],
    "tgn:id":2776203,
    "tgn:name":"Wilzone",
    "tgn:placetype":[
        "aat:300008347"
    ]
},
  "bbox": [],
  "geometry": {"coordinates":[-90.4833,32.9333],"type":"Point"}
}