{
  "id": 7001877,
  "type": "Feature",
  "properties": {
    "tgn:hierarchy":[
        "tgn:7001877",
        "tgn:1000004",
        "tgn:7002084",
        "tgn:1000111",
        "tgn:7029392"
    ],
    "tgn:id":7001877,
    "tgn:name":"Lintong",
    "tgn:placetype":[
        "aat:300008347",
        "aat:300008375"
    ]
},
  "bbox": [],
  "geometry": {"coordinates":[109.1667,34.4167],"type":"Point"}
}