{
  "id": 2636099,
  "type": "Feature",
  "properties": {
    "tgn:hierarchy":[
        "tgn:2636099",
        "tgn:1000001",
        "tgn:7012149",
        "tgn:1002899",
        "tgn:7007920",
        "tgn:7029392"
    ],
    "tgn:id":2636099,
    "tgn:name":"Saddle Lake",
    "tgn:placetype":[
        "aat:300008680"
    ]
},
  "bbox": [],
  "geometry": {"coordinates":[-121.75,48.1667],"type":"Point"}
}