{
  "id": 7510000,
  "type": "Feature",
  "properties": {
    "tgn:hierarchy":[
        "tgn:7510000",
        "tgn:1009227",
        "tgn:1000226",
        "tgn:1000006",
        "tgn:7016850",
        "tgn:7029392"
    ],
    "tgn:id":7510000,
    "tgn:name:en":"Temple Creek",
    "tgn:placetype":[
        "aat:300008699"
    ]
},
  "bbox": [],
  "geometry": {"coordinates":[169.85,-44.133333],"type":"Point"}
}