{
  "id": 2757557,
  "type": "Feature",
  "properties": {
    "tgn:hierarchy":[
        "tgn:2757557",
        "tgn:1000001",
        "tgn:7012149",
        "tgn:2002358",
        "tgn:7007922",
        "tgn:7029392"
    ],
    "tgn:id":2757557,
    "tgn:name":"West Branch Baraboo River",
    "tgn:placetype":[
        "aat:300008707"
    ]
},
  "bbox": [],
  "geometry": {"coordinates":[-90.4333,43.6833],"type":"Point"}
}