{
  "id": 2536620,
  "type": "Feature",
  "properties": {
    "tgn:hierarchy":[
        "tgn:2536620",
        "tgn:1000001",
        "tgn:7012149",
        "tgn:2000446",
        "tgn:7007248",
        "tgn:7029392"
    ],
    "tgn:id":2536620,
    "tgn:name":"Nebo Knob",
    "tgn:placetype":[
        "aat:300008798"
    ]
},
  "bbox": [],
  "geometry": {"coordinates":[-84.9833,34.9333],"type":"Point"}
}