{
  "id": 7539469,
  "type": "Feature",
  "properties": {
    "tgn:hierarchy":[
        "tgn:7539469",
        "tgn:7001242",
        "tgn:7016833",
        "tgn:1001335",
        "tgn:7029392"
    ],
    "tgn:id":7539469,
    "tgn:name:en":"Sakan Ibr\u00e2h\u00eem Sanad",
    "tgn:placetype":[
        "aat:300008347"
    ]
},
  "bbox": [],
  "geometry": {"coordinates":[30.916667,31.316667],"type":"Point"}
}