{
  "id": 1094859,
  "type": "Feature",
  "properties": {
    "tgn:hierarchy":[
        "tgn:1094859",
        "tgn:7001242",
        "tgn:7016572",
        "tgn:1000203",
        "tgn:7029392"
    ],
    "tgn:id":1094859,
    "tgn:name":"Usoke",
    "tgn:placetype":[
        "aat:300008347"
    ]
},
  "bbox": [],
  "geometry": {"coordinates":[32.35,-5.0833],"type":"Point"}
}