{
  "id": 7187598,
  "type": "Feature",
  "properties": {
    "tgn:hierarchy":[
        "tgn:7187598",
        "tgn:1000003",
        "tgn:7003678",
        "tgn:7000084",
        "tgn:7029392"
    ],
    "tgn:id":7187598,
    "tgn:name":"Erligshof",
    "tgn:placetype":[
        "aat:300000206"
    ]
},
  "bbox": [],
  "geometry": {"coordinates":[9.85,50.683333],"type":"Point"}
}