{
  "id": 7007790,
  "type": "Feature",
  "properties": {
    "tgn:hierarchy":[
        "tgn:7007790",
        "tgn:7024116",
        "tgn:1000003",
        "tgn:7006366",
        "tgn:7029392"
    ],
    "tgn:id":7007790,
    "tgn:name":"Rypin",
    "tgn:placetype":[
        "aat:300008347"
    ]
},
  "bbox": [],
  "geometry": {"coordinates":[19.3833,53.05],"type":"Point"}
}