{
  "id": 7582369,
  "type": "Feature",
  "properties": {
    "tgn:hierarchy":[
        "tgn:7582369",
        "tgn:1000004",
        "tgn:7000198",
        "tgn:7016788",
        "tgn:7029392"
    ],
    "tgn:id":7582369,
    "tgn:name:en":"Dul\u0101n\u012bya",
    "tgn:placetype":[
        "aat:300008347"
    ]
},
  "bbox": [],
  "geometry": {"coordinates":[75.6886,28.4053],"type":"Point"}
}