{
  "id": 2514639,
  "type": "Feature",
  "properties": {
    "tgn:hierarchy":[
        "tgn:2514639",
        "tgn:1000001",
        "tgn:7012149",
        "tgn:2000382",
        "tgn:7007248",
        "tgn:7029392"
    ],
    "tgn:id":2514639,
    "tgn:name":"Miller Lake",
    "tgn:placetype":[
        "aat:300008680"
    ]
},
  "bbox": [],
  "geometry": {"coordinates":[-81.65,31.5333],"type":"Point"}
}