{
  "id": 7034865,
  "type": "Feature",
  "properties": {
    "tgn:hierarchy":[
        "tgn:7034865",
        "tgn:1003442",
        "tgn:1000003",
        "tgn:7010380",
        "tgn:1000080",
        "tgn:7029392"
    ],
    "tgn:id":7034865,
    "tgn:name":"Masseria Torretta",
    "tgn:placetype":[
        "aat:300000206"
    ]
},
  "bbox": [],
  "geometry": {"coordinates":[17.921111,40.647778],"type":"Point"}
}