{
  "id": 7020970,
  "type": "Feature",
  "properties": {
    "tgn:hierarchy":[
        "tgn:7020970",
        "tgn:1000001",
        "tgn:7012149",
        "tgn:2000488",
        "tgn:7007250",
        "tgn:7029392"
    ],
    "tgn:id":7020970,
    "tgn:name":"Pothole Reservoir",
    "tgn:placetype":[
        "aat:300006191"
    ]
},
  "bbox": [],
  "geometry": {"coordinates":[-116.85,42.1167],"type":"Point"}
}