<<<<<<< HEAD
{
  "id": 7020970,
  "type": "Feature",
  "properties": {
    "tgn:hierarchy":[
        "tgn:7020970",
        "tgn:1000001",
        "tgn:7012149",
        "tgn:2000488",
        "tgn:7007250",
        "tgn:7029392"
    ],
    "tgn:id":7020970,
    "tgn:name":"Pothole Reservoir",
    "tgn:placetype":[
        "aat:300006191"
    ]
},
  "bbox": [],
  "geometry": {"coordinates":[-116.85,42.1167],"type":"Point"}
}
=======
{"geometry":{"type":"Point","coordinates":[-116.850000,42.116700]},"type":"Feature","properties":{"hierarchy":["tgn:7020970","tgn:1000001","tgn:7012149","tgn:2000488","tgn:7007250","tgn:7029392"],"placetype":["aat:300006191"],"id":7020970,"name:xx":"Pothole Reservoir"}}
>>>>>>> 03f74aca74312dbeaf24d7e61306dd6a786dc3d0
