{
  "id": 1079471,
  "type": "Feature",
  "properties": {
    "tgn:hierarchy":[
        "tgn:1079471",
        "tgn:7000249",
        "tgn:1000004",
        "tgn:1000119",
        "tgn:7029392"
    ],
    "tgn:id":1079471,
    "tgn:name":"Afiqim",
    "tgn:placetype":[
        "aat:300008347"
    ]
},
  "bbox": [],
  "geometry": {"coordinates":[35.5667,32.6667],"type":"Point"}
}