{
  "id": 2110241,
  "type": "Feature",
  "properties": {
    "tgn:hierarchy":[
        "tgn:2110241",
        "tgn:1000001",
        "tgn:7012149",
        "tgn:2002175",
        "tgn:7007919",
        "tgn:7029392"
    ],
    "tgn:id":2110241,
    "tgn:name":"Afton",
    "tgn:placetype":[
        "aat:300008347"
    ]
},
  "bbox": [],
  "geometry": {"coordinates":[-78.8333,38.0167],"type":"Point"}
}