{
  "id": 7327447,
  "type": "Feature",
  "properties": {
    "tgn:hierarchy":[
        "tgn:7327447",
        "tgn:7002759",
        "tgn:7002843",
        "tgn:1000003",
        "tgn:1000095",
        "tgn:7029392"
    ],
    "tgn:id":7327447,
    "tgn:name":"Palomita",
    "tgn:placetype":[
        "aat:300008347"
    ]
},
  "bbox": [],
  "geometry": {"coordinates":[-0.483333,40.616667],"type":"Point"}
}