{
  "id": 1067241,
  "type": "Feature",
  "properties": {
    "tgn:hierarchy":[
        "tgn:1067241",
        "tgn:1000004",
        "tgn:1000958",
        "tgn:1000111",
        "tgn:7029392"
    ],
    "tgn:id":1067241,
    "tgn:name":"Chongming",
    "tgn:placetype":[
        "aat:300008347"
    ]
},
  "bbox": [],
  "geometry": {"coordinates":[121.45,31.6333],"type":"Point"}
}