{
  "id": 2230184,
  "type": "Feature",
  "properties": {
    "tgn:hierarchy":[
        "tgn:2230184",
        "tgn:1000001",
        "tgn:7006451",
        "tgn:7012149",
        "tgn:2000099",
        "tgn:7029392"
    ],
    "tgn:id":2230184,
    "tgn:name":"Cement Tank",
    "tgn:placetype":[
        "aat:300006191"
    ]
},
  "bbox": [],
  "geometry": {"coordinates":[-110.3833,34.7167],"type":"Point"}
}