<<<<<<< HEAD
{
  "id": 7376832,
  "type": "Feature",
  "properties": {
    "tgn:hierarchy":[
        "tgn:7376832",
        "tgn:1000001",
        "tgn:7005589",
        "tgn:7005560",
        "tgn:7029392"
    ],
    "tgn:id":7376832,
    "tgn:name":"La Parida",
    "tgn:placetype":[
        "aat:300008347"
    ]
},
  "bbox": [],
  "geometry": {"coordinates":[-99.366667,25.05],"type":"Point"}
}
=======
{"geometry":{"type":"Point","coordinates":[-99.366667,25.050000]},"type":"Feature","properties":{"hierarchy":["tgn:7376832","tgn:1000001","tgn:7005589","tgn:7005560","tgn:7029392"],"placetype":["aat:300008347"],"id":7376832,"name:xx":"La Parida"}}
>>>>>>> 03f74aca74312dbeaf24d7e61306dd6a786dc3d0
