{
  "id": 2643582,
  "type": "Feature",
  "properties": {
    "tgn:hierarchy":[
        "tgn:2643582",
        "tgn:1000001",
        "tgn:7012149",
        "tgn:2000285",
        "tgn:7007240",
        "tgn:7029392"
    ],
    "tgn:id":2643582,
    "tgn:name":"Sandy Point Bayou",
    "tgn:placetype":[
        "aat:300008699"
    ]
},
  "bbox": [],
  "geometry": {"coordinates":[-87.05,30.5667],"type":"Point"}
}