<<<<<<< HEAD
{
  "id": 2764852,
  "type": "Feature",
  "properties": {
    "tgn:hierarchy":[
        "tgn:2764852",
        "tgn:1000001",
        "tgn:7012149",
        "tgn:2001718",
        "tgn:7007708",
        "tgn:7029392"
    ],
    "tgn:id":2764852,
    "tgn:name":"Whiskey Jack Spring",
    "tgn:placetype":[
        "aat:300008697"
    ]
},
  "bbox": [],
  "geometry": {"coordinates":[-117.9,43.4167],"type":"Point"}
}
=======
{"geometry":{"type":"Point","coordinates":[-117.900000,43.416700]},"type":"Feature","properties":{"hierarchy":["tgn:2764852","tgn:1000001","tgn:7012149","tgn:2001718","tgn:7007708","tgn:7029392"],"placetype":["aat:300008697"],"id":2764852,"name:xx":"Whiskey Jack Spring"}}
>>>>>>> 03f74aca74312dbeaf24d7e61306dd6a786dc3d0
