{
  "id": 1026401,
  "type": "Feature",
  "properties": {
    "tgn:hierarchy":[
        "tgn:1026401",
        "tgn:7003457",
        "tgn:1000003",
        "tgn:1000063",
        "tgn:7018236",
        "tgn:7029392"
    ],
    "tgn:id":1026401,
    "tgn:name":"Drongen",
    "tgn:placetype":[
        "aat:300008347"
    ]
},
  "bbox": [],
  "geometry": {"coordinates":[3.65649,51.050669],"type":"Point"}
}