{
  "id": 7374379,
  "type": "Feature",
  "properties": {
    "tgn:hierarchy":[
        "tgn:7374379",
        "tgn:1001853",
        "tgn:1000001",
        "tgn:7005560",
        "tgn:7029392"
    ],
    "tgn:id":7374379,
    "tgn:name":"La Constancia",
    "tgn:placetype":[
        "aat:300008347"
    ]
},
  "bbox": [],
  "geometry": {"coordinates":[-101.983333,25.216667],"type":"Point"}
}