{
  "id": 2190909,
  "type": "Feature",
  "properties": {
    "tgn:hierarchy":[
        "tgn:2190909",
        "tgn:1000001",
        "tgn:7012149",
        "tgn:2001907",
        "tgn:7007825",
        "tgn:7029392"
    ],
    "tgn:id":2190909,
    "tgn:name":"Boyd Hollow",
    "tgn:placetype":[
        "aat:300008761"
    ]
},
  "bbox": [],
  "geometry": {"coordinates":[-85.65,36.15],"type":"Point"}
}