<<<<<<< HEAD
{
  "id": 7485301,
  "type": "Feature",
  "properties": {
    "tgn:hierarchy":[
        "tgn:7485301",
        "tgn:1000004",
        "tgn:7467799",
        "tgn:1000141",
        "tgn:7029392"
    ],
    "tgn:id":7485301,
    "tgn:name":"Daxia Beiqiao",
    "tgn:placetype":[
        "aat:300007836"
    ]
},
  "bbox": [],
  "geometry": {"coordinates":[120.5025,24.104167],"type":"Point"}
}
=======
{"geometry":{"type":"Point","coordinates":[120.502500,24.104167]},"type":"Feature","properties":{"hierarchy":["tgn:7485301","tgn:1000004","tgn:7467799","tgn:1000141","tgn:7029392"],"placetype":["aat:300007836"],"id":7485301,"name:xx":"Daxia Beiqiao"}}
>>>>>>> 03f74aca74312dbeaf24d7e61306dd6a786dc3d0
