{
  "id": 2344092,
  "type": "Feature",
  "properties": {
    "tgn:hierarchy":[
        "tgn:2344092",
        "tgn:1000001",
        "tgn:7012149",
        "tgn:2000287",
        "tgn:7007240",
        "tgn:7029392"
    ],
    "tgn:id":2344092,
    "tgn:name":"Gamble Point",
    "tgn:placetype":[
        "aat:300008850"
    ]
},
  "bbox": [],
  "geometry": {"coordinates":[-83.9833,30.0667],"type":"Point"}
}