{
  "id": 7339295,
  "type": "Feature",
  "properties": {
    "tgn:hierarchy":[
        "tgn:7339295",
        "tgn:7002836",
        "tgn:7016622",
        "tgn:1000003",
        "tgn:1000095",
        "tgn:7029392"
    ],
    "tgn:id":7339295,
    "tgn:name":"Crucita, Monta\u00f1a de la",
    "tgn:placetype":[
        "aat:300008795"
    ]
},
  "bbox": [],
  "geometry": {"coordinates":[-16.466667,28.35],"type":"Point"}
}