{
  "id": 2578937,
  "type": "Feature",
  "properties": {
    "tgn:hierarchy":[
        "tgn:2578937",
        "tgn:1000001",
        "tgn:7006451",
        "tgn:2000092",
        "tgn:7012149",
        "tgn:7029392"
    ],
    "tgn:id":2578937,
    "tgn:name":"Philomena Spring",
    "tgn:placetype":[
        "aat:300008697"
    ]
},
  "bbox": [],
  "geometry": {"coordinates":[-111.6667,35.35],"type":"Point"}
}