{
  "id": 7265369,
  "type": "Feature",
  "properties": {
    "tgn:concordances":{
        "gn:id":"2752776"
    },
    "tgn:hierarchy":[
        "tgn:7265369",
        "tgn:1000003",
        "tgn:7003624",
        "tgn:7016845",
        "tgn:7029392"
    ],
    "tgn:id":7265369,
    "tgn:name:nl":"Klein-Dongen",
    "tgn:placetype":[
        "aat:300008347"
    ]
},
  "bbox": [],
  "geometry": {"coordinates":[4.966667,51.633333],"type":"Point"}
}