{
  "id": 1109085,
  "type": "Feature",
  "properties": {
    "tgn:hierarchy":[
        "tgn:1109085",
        "tgn:7002811",
        "tgn:1000003",
        "tgn:7003837",
        "tgn:1000095",
        "tgn:7029392"
    ],
    "tgn:id":1109085,
    "tgn:name":"Guadalupe, Sierra de",
    "tgn:placetype":[
        "aat:300386831",
        "aat:300008795"
    ]
},
  "bbox": [],
  "geometry": {"coordinates":[-5.416667,39.433333],"type":"Point"}
}