<<<<<<< HEAD
{
  "id": 7111361,
  "type": "Feature",
  "properties": {
    "tgn:hierarchy":[
        "tgn:7111361",
        "tgn:7000096",
        "tgn:1000003",
        "tgn:7000084",
        "tgn:7029392"
    ],
    "tgn:id":7111361,
    "tgn:name":"Rohr-Teich",
    "tgn:placetype":[
        "aat:300008680"
    ]
},
  "bbox": [],
  "geometry": {"coordinates":[13.433333,51.816667],"type":"Point"}
}
=======
{"geometry":{"type":"Point","coordinates":[13.433333,51.816667]},"type":"Feature","properties":{"hierarchy":["tgn:7111361","tgn:7000096","tgn:1000003","tgn:7000084","tgn:7029392"],"placetype":["aat:300008680"],"id":7111361,"name:xx":"Rohr-Teich"}}
>>>>>>> 03f74aca74312dbeaf24d7e61306dd6a786dc3d0
