{
  "id": 7119649,
  "type": "Feature",
  "properties": {
    "tgn:hierarchy":[
        "tgn:7119649",
        "tgn:1000003",
        "tgn:7003689",
        "tgn:7000084",
        "tgn:7029392"
    ],
    "tgn:id":7119649,
    "tgn:name":"Pelzkopf",
    "tgn:placetype":[
        "aat:300008777"
    ]
},
  "bbox": [],
  "geometry": {"coordinates":[10.566667,50.616667],"type":"Point"}
}