{
  "id": 7468022,
  "type": "Feature",
  "properties": {
    "tgn:hierarchy":[
        "tgn:7468022",
        "tgn:1000004",
        "tgn:7492971",
        "tgn:1000141",
        "tgn:7029392"
    ],
    "tgn:id":7468022,
    "tgn:name":"Qiehu",
    "tgn:placetype":[
        "aat:300008347"
    ]
},
  "bbox": [],
  "geometry": {"coordinates":[120.716944,22.036667],"type":"Point"}
}