{
  "id": 2723512,
  "type": "Feature",
  "properties": {
    "tgn:hierarchy":[
        "tgn:2723512",
        "tgn:1000001",
        "tgn:7012149",
        "tgn:7007157",
        "tgn:1002972",
        "tgn:7029392"
    ],
    "tgn:id":2723512,
    "tgn:name":"Todd Barranca",
    "tgn:placetype":[
        "aat:300008761"
    ]
},
  "bbox": [],
  "geometry": {"coordinates":[-119.1333,34.3333],"type":"Point"}
}