{
  "id": 2525121,
  "type": "Feature",
  "properties": {
    "tgn:hierarchy":[
        "tgn:2525121",
        "tgn:1002338",
        "tgn:1000001",
        "tgn:7012149",
        "tgn:7007516",
        "tgn:7029392"
    ],
    "tgn:id":2525121,
    "tgn:name":"Morris Neck",
    "tgn:placetype":[
        "aat:300008850"
    ]
},
  "bbox": [],
  "geometry": {"coordinates":[-76.1833,38.5667],"type":"Point"}
}