{
  "id": 7517265,
  "type": "Feature",
  "properties": {
    "tgn:hierarchy":[
        "tgn:7517265",
        "tgn:7016670",
        "tgn:1008380",
        "tgn:1000226",
        "tgn:1000006",
        "tgn:7029392"
    ],
    "tgn:id":7517265,
    "tgn:name:en":"Komataoneone",
    "tgn:placetype":[
        "aat:300008795"
    ]
},
  "bbox": [],
  "geometry": {"coordinates":[176.966667,-39.016667],"type":"Point"}
}