{
  "id": 2272552,
  "type": "Feature",
  "properties": {
    "tgn:hierarchy":[
        "tgn:2272552",
        "tgn:1000001",
        "tgn:7012149",
        "tgn:2001527",
        "tgn:7007709",
        "tgn:7029392"
    ],
    "tgn:id":2272552,
    "tgn:name":"Curve of the Railroad Bay",
    "tgn:placetype":[
        "aat:300008905"
    ]
},
  "bbox": [],
  "geometry": {"coordinates":[-78.0667,34.45],"type":"Point"}
}