{
  "id": 2467506,
  "type": "Feature",
  "properties": {
    "tgn:hierarchy":[
        "tgn:2467506",
        "tgn:1000001",
        "tgn:7012149",
        "tgn:2001519",
        "tgn:7007709",
        "tgn:7029392"
    ],
    "tgn:id":2467506,
    "tgn:name":"Long Hollow",
    "tgn:placetype":[
        "aat:300008761"
    ]
},
  "bbox": [],
  "geometry": {"coordinates":[-82.0667,36.0333],"type":"Point"}
}