{
  "id": 7163883,
  "type": "Feature",
  "properties": {
    "tgn:hierarchy":[
        "tgn:7163883",
        "tgn:7003692",
        "tgn:1000003",
        "tgn:7000084",
        "tgn:7029392"
    ],
    "tgn:id":7163883,
    "tgn:name":"H\u00fcbschenberg",
    "tgn:placetype":[
        "aat:300008347"
    ]
},
  "bbox": [],
  "geometry": {"coordinates":[9.666667,47.733333],"type":"Point"}
}