{
  "id": 2758274,
  "type": "Feature",
  "properties": {
    "tgn:hierarchy":[
        "tgn:2758274",
        "tgn:1000001",
        "tgn:7012149",
        "tgn:1002924",
        "tgn:7007568",
        "tgn:7029392"
    ],
    "tgn:id":2758274,
    "tgn:name":"West Brook",
    "tgn:placetype":[
        "aat:300008699"
    ]
},
  "bbox": [],
  "geometry": {"coordinates":[-73.1333,40.75],"type":"Point"}
}