{
  "id": 2214911,
  "type": "Feature",
  "properties": {
    "tgn:hierarchy":[
        "tgn:2214911",
        "tgn:1000001",
        "tgn:2001435",
        "tgn:7012149",
        "tgn:7007566",
        "tgn:7029392"
    ],
    "tgn:id":2214911,
    "tgn:name":"Caliche Tank",
    "tgn:placetype":[
        "aat:300006191"
    ]
},
  "bbox": [],
  "geometry": {"coordinates":[-106.8833,32.7333],"type":"Point"}
}