{
  "id": 2613552,
  "type": "Feature",
  "properties": {
    "tgn:hierarchy":[
        "tgn:2613552",
        "tgn:1000001",
        "tgn:7012149",
        "tgn:2001507",
        "tgn:7007709",
        "tgn:7029392"
    ],
    "tgn:id":2613552,
    "tgn:name":"Reeder Creek",
    "tgn:placetype":[
        "aat:300008706"
    ]
},
  "bbox": [],
  "geometry": {"coordinates":[-80.9333,35.75],"type":"Point"}
}