{
  "id": 7329637,
  "type": "Feature",
  "properties": {
    "tgn:hierarchy":[
        "tgn:7329637",
        "tgn:7001122",
        "tgn:1000003",
        "tgn:7002765",
        "tgn:1000095",
        "tgn:7029392"
    ],
    "tgn:id":7329637,
    "tgn:name":"R\u00e1pita, Arenal de la",
    "tgn:placetype":[
        "aat:300008816"
    ]
},
  "bbox": [],
  "geometry": {"coordinates":[2.966667,39.35],"type":"Point"}
}