{
  "id": 1094755,
  "type": "Feature",
  "properties": {
    "tgn:hierarchy":[
        "tgn:1094755",
        "tgn:7001242",
        "tgn:1001739",
        "tgn:1000203",
        "tgn:7029392"
    ],
    "tgn:id":1094755,
    "tgn:name":"Mpui",
    "tgn:placetype":[
        "aat:300008347"
    ]
},
  "bbox": [],
  "geometry": {"coordinates":[31.8333,-8.3333],"type":"Point"}
}