{
  "id": 7437648,
  "type": "Feature",
  "properties": {
    "tgn:hierarchy":[
        "tgn:7437648",
        "tgn:1001835",
        "tgn:1000001",
        "tgn:7005560",
        "tgn:7029392"
    ],
    "tgn:id":7437648,
    "tgn:name":"Sello, Arrecife del",
    "tgn:placetype":[
        "aat:300008808"
    ]
},
  "bbox": [],
  "geometry": {"coordinates":[-110.616667,24.833333],"type":"Point"}
}