<<<<<<< HEAD
{
  "id": 2333319,
  "type": "Feature",
  "properties": {
    "tgn:hierarchy":[
        "tgn:2333319",
        "tgn:1000001",
        "tgn:1002664",
        "tgn:7012149",
        "tgn:7007159",
        "tgn:7029392"
    ],
    "tgn:id":2333319,
    "tgn:name":"Fogelmarks Corners",
    "tgn:placetype":[
        "aat:300008347"
    ]
},
  "bbox": [],
  "geometry": {"coordinates":[-72.6,41.6],"type":"Point"}
}
=======
{"geometry":{"type":"Point","coordinates":[-72.600000,41.600000]},"type":"Feature","properties":{"hierarchy":["tgn:2333319","tgn:1000001","tgn:1002664","tgn:7012149","tgn:7007159","tgn:7029392"],"placetype":["aat:300008347"],"id":2333319,"name:xx":"Fogelmarks Corners"}}
>>>>>>> 03f74aca74312dbeaf24d7e61306dd6a786dc3d0
