{
  "id": 2087536,
  "type": "Feature",
  "properties": {
    "tgn:hierarchy":[
        "tgn:2087536",
        "tgn:1000001",
        "tgn:7012149",
        "tgn:1002779",
        "tgn:7007710",
        "tgn:7029392"
    ],
    "tgn:id":2087536,
    "tgn:name":"Cove",
    "tgn:placetype":[
        "aat:300008347"
    ]
},
  "bbox": [],
  "geometry": {"coordinates":[-76.9667,40.35],"type":"Point"}
}