{
  "id": 7211458,
  "type": "Feature",
  "properties": {
    "tgn:hierarchy":[
        "tgn:7211458",
        "tgn:7003669",
        "tgn:1000003",
        "tgn:7000084",
        "tgn:7029392"
    ],
    "tgn:id":7211458,
    "tgn:name":"Baiersdorf",
    "tgn:placetype":[
        "aat:300000206"
    ]
},
  "bbox": [],
  "geometry": {"coordinates":[12.433333,48.583333],"type":"Point"}
}