{
  "id": 2313951,
  "type": "Feature",
  "properties": {
    "tgn:hierarchy":[
        "tgn:2313951",
        "tgn:1000001",
        "tgn:7012149",
        "tgn:2001192",
        "tgn:7007523",
        "tgn:7029392"
    ],
    "tgn:id":2313951,
    "tgn:name":"Elixer",
    "tgn:placetype":[
        "aat:300008347"
    ]
},
  "bbox": [],
  "geometry": {"coordinates":[-93.1167,37.8833],"type":"Point"}
}