{
  "id": 2288119,
  "type": "Feature",
  "properties": {
    "tgn:hierarchy":[
        "tgn:2288119",
        "tgn:1000001",
        "tgn:7006451",
        "tgn:7012149",
        "tgn:2000101",
        "tgn:7029392"
    ],
    "tgn:id":2288119,
    "tgn:name":"Dinosaur Mountain",
    "tgn:placetype":[
        "aat:300008798"
    ]
},
  "bbox": [],
  "geometry": {"coordinates":[-111.4333,33.3667],"type":"Point"}
}