{
  "id": 1130699,
  "type": "Feature",
  "properties": {
    "tgn:hierarchy":[
        "tgn:1130699",
        "tgn:1000001",
        "tgn:7005560",
        "tgn:7029392"
    ],
    "tgn:id":1130699,
    "tgn:name":"Tecuantepec, R\u00edo",
    "tgn:placetype":[
        "aat:300008707",
        "aat:300008699"
    ]
},
  "bbox": [],
  "geometry": {"coordinates":[-97.45,20.266667],"type":"Point"}
}