{
  "id": 7507377,
  "type": "Feature",
  "properties": {
    "tgn:hierarchy":[
        "tgn:7507377",
        "tgn:1008380",
        "tgn:7000507",
        "tgn:1000226",
        "tgn:1000006",
        "tgn:7029392"
    ],
    "tgn:id":7507377,
    "tgn:name:en":"Pukekohe",
    "tgn:placetype":[
        "aat:300008777"
    ]
},
  "bbox": [],
  "geometry": {"coordinates":[173.383333,-35.533333],"type":"Point"}
}