{
  "id": 2458712,
  "type": "Feature",
  "properties": {
    "tgn:hierarchy":[
        "tgn:2458712",
        "tgn:1000001",
        "tgn:7012149",
        "tgn:7007706",
        "tgn:7029392"
    ],
    "tgn:id":2458712,
    "tgn:name":"Little Ottawa River",
    "tgn:placetype":[
        "aat:300008707"
    ]
},
  "bbox": [],
  "geometry": {"coordinates":[-84.0833,40.65],"type":"Point"}
}