{
  "id": 2222145,
  "type": "Feature",
  "properties": {
    "tgn:hierarchy":[
        "tgn:2222145",
        "tgn:1000001",
        "tgn:7012149",
        "tgn:2001308",
        "tgn:7007524",
        "tgn:7029392"
    ],
    "tgn:id":2222145,
    "tgn:name":"Carney",
    "tgn:placetype":[
        "aat:300008347"
    ]
},
  "bbox": [],
  "geometry": {"coordinates":[-110.1167,45.75],"type":"Point"}
}