{
  "id": 2486775,
  "type": "Feature",
  "properties": {
    "tgn:hierarchy":[
        "tgn:2486775",
        "tgn:1000001",
        "tgn:7016172",
        "tgn:7012149",
        "tgn:2000136",
        "tgn:7029392"
    ],
    "tgn:id":2486775,
    "tgn:name":"Lee Britten Lake",
    "tgn:placetype":[
        "aat:300006191"
    ]
},
  "bbox": [],
  "geometry": {"coordinates":[-91.5333,35.8333],"type":"Point"}
}