{
  "id": 2414984,
  "type": "Feature",
  "properties": {
    "tgn:hierarchy":[
        "tgn:2414984",
        "tgn:1000001",
        "tgn:7012149",
        "tgn:2000892",
        "tgn:7007256",
        "tgn:7029392"
    ],
    "tgn:id":2414984,
    "tgn:name":"Island",
    "tgn:placetype":[
        "aat:300008347"
    ]
},
  "bbox": [],
  "geometry": {"coordinates":[-91.3833,30.6667],"type":"Point"}
}