{
  "id": 2657962,
  "type": "Feature",
  "properties": {
    "tgn:hierarchy":[
        "tgn:2657962",
        "tgn:1000001",
        "tgn:7006451",
        "tgn:2000093",
        "tgn:7012149",
        "tgn:7029392"
    ],
    "tgn:id":2657962,
    "tgn:name":"Shell Spring",
    "tgn:placetype":[
        "aat:300008697"
    ]
},
  "bbox": [],
  "geometry": {"coordinates":[-111.2833,33.75],"type":"Point"}
}