{
  "id": 2573020,
  "type": "Feature",
  "properties": {
    "tgn:hierarchy":[
        "tgn:2573020",
        "tgn:1000001",
        "tgn:7012149",
        "tgn:2002265",
        "tgn:7013961",
        "tgn:7029392"
    ],
    "tgn:id":2573020,
    "tgn:name":"Pearl Ridge",
    "tgn:placetype":[
        "aat:300266640"
    ]
},
  "bbox": [],
  "geometry": {"coordinates":[-78.5833,39.2333],"type":"Point"}
}