{
  "id": 7284206,
  "type": "Feature",
  "properties": {
    "tgn:hierarchy":[
        "tgn:7284206",
        "tgn:7016598",
        "tgn:1000049",
        "tgn:1000002",
        "tgn:7029392"
    ],
    "tgn:id":7284206,
    "tgn:name":"Potrerito, Quebrada",
    "tgn:placetype":[
        "aat:300266554",
        "aat:300008699"
    ]
},
  "bbox": [],
  "geometry": {"coordinates":[-68.683333,-21.483333],"type":"Point"}
}