{
  "id": 2640994,
  "type": "Feature",
  "properties": {
    "tgn:hierarchy":[
        "tgn:2640994",
        "tgn:1000001",
        "tgn:2000952",
        "tgn:7012149",
        "tgn:7007520",
        "tgn:7029392"
    ],
    "tgn:id":2640994,
    "tgn:name":"Sand Bay",
    "tgn:placetype":[
        "aat:300132316"
    ]
},
  "bbox": [],
  "geometry": {"coordinates":[-83.5333,46.0167],"type":"Point"}
}