{
  "id": 2301158,
  "type": "Feature",
  "properties": {
    "tgn:hierarchy":[
        "tgn:2301158",
        "tgn:1000001",
        "tgn:7012149",
        "tgn:2002275",
        "tgn:7013961",
        "tgn:7029392"
    ],
    "tgn:id":2301158,
    "tgn:name":"Dunkard Mill Run",
    "tgn:placetype":[
        "aat:300008699"
    ]
},
  "bbox": [],
  "geometry": {"coordinates":[-80.2667,39.5667],"type":"Point"}
}