{
  "id": 2293647,
  "type": "Feature",
  "properties": {
    "tgn:hierarchy":[
        "tgn:2293647",
        "tgn:1000001",
        "tgn:2001471",
        "tgn:7012149",
        "tgn:7007709",
        "tgn:7029392"
    ],
    "tgn:id":2293647,
    "tgn:name":"Doubles Branch",
    "tgn:placetype":[
        "aat:300008699"
    ]
},
  "bbox": [],
  "geometry": {"coordinates":[-78.5667,34.5333],"type":"Point"}
}