{
  "id": 7125900,
  "type": "Feature",
  "properties": {
    "tgn:hierarchy":[
        "tgn:7125900",
        "tgn:7003692",
        "tgn:1000003",
        "tgn:7000084",
        "tgn:7029392"
    ],
    "tgn:id":7125900,
    "tgn:name":"Oberdrackenstein",
    "tgn:placetype":[
        "aat:300008347"
    ]
},
  "bbox": [],
  "geometry": {"coordinates":[9.683333,48.55],"type":"Point"}
}