{
  "id": 2528900,
  "type": "Feature",
  "properties": {
    "tgn:hierarchy":[
        "tgn:2528900",
        "tgn:1000001",
        "tgn:7012149",
        "tgn:2000985",
        "tgn:7007520",
        "tgn:7029392"
    ],
    "tgn:id":2528900,
    "tgn:name":"Mud Creek",
    "tgn:placetype":[
        "aat:300008706"
    ]
},
  "bbox": [],
  "geometry": {"coordinates":[-83.9833,44.1833],"type":"Point"}
}