{
  "id": 2368789,
  "type": "Feature",
  "properties": {
    "tgn:hierarchy":[
        "tgn:2368789",
        "tgn:7006450",
        "tgn:1000001",
        "tgn:7019698",
        "tgn:7012149",
        "tgn:7029392"
    ],
    "tgn:id":2368789,
    "tgn:name":"Gull Rock",
    "tgn:placetype":[
        "aat:300008850"
    ]
},
  "bbox": [],
  "geometry": {"coordinates":[-149.75,60.9667],"type":"Point"}
}