{
  "id": 7536956,
  "type": "Feature",
  "properties": {
    "tgn:hierarchy":[
        "tgn:7536956",
        "tgn:7001242",
        "tgn:7016833",
        "tgn:1001418",
        "tgn:7029392"
    ],
    "tgn:id":7536956,
    "tgn:name:en":"Laban, Tallat al",
    "tgn:placetype":[
        "aat:300008777"
    ]
},
  "bbox": [],
  "geometry": {"coordinates":[29.233333,30.616667],"type":"Point"}
}