{
  "id": 2293832,
  "type": "Feature",
  "properties": {
    "tgn:hierarchy":[
        "tgn:2293832",
        "tgn:7006450",
        "tgn:1000001",
        "tgn:7012149",
        "tgn:2000088",
        "tgn:7029392"
    ],
    "tgn:id":2293832,
    "tgn:name":"Douglas Bay",
    "tgn:placetype":[
        "aat:300132316"
    ]
},
  "bbox": [],
  "geometry": {"coordinates":[-133.2667,56.45],"type":"Point"}
}