{
  "id": 7229518,
  "type": "Feature",
  "properties": {
    "tgn:hierarchy":[
        "tgn:7229518",
        "tgn:4003773",
        "tgn:7001395",
        "tgn:1000003",
        "tgn:1000074",
        "tgn:7029392"
    ],
    "tgn:id":7229518,
    "tgn:name":"Karao\u00falia",
    "tgn:placetype":[
        "aat:300008798"
    ]
},
  "bbox": [],
  "geometry": {"coordinates":[22.066667,38.983333],"type":"Point"}
}