{
  "id": 7484510,
  "type": "Feature",
  "properties": {
    "tgn:hierarchy":[
        "tgn:7484510",
        "tgn:7001004",
        "tgn:1000004",
        "tgn:1000141",
        "tgn:7029392"
    ],
    "tgn:id":7484510,
    "tgn:name":"Beiliao",
    "tgn:placetype":[
        "aat:300008347"
    ]
},
  "bbox": [],
  "geometry": {"coordinates":[120.646111,23.113889],"type":"Point"}
}