{
  "id": 1111480,
  "type": "Feature",
  "properties": {
    "tgn:hierarchy":[
        "tgn:1111480",
        "tgn:7001242",
        "tgn:7001311",
        "tgn:7016833",
        "tgn:7029392"
    ],
    "tgn:id":1111480,
    "tgn:name:en":"Dakhal, W\u0101d\u012b ad",
    "tgn:placetype":[
        "aat:300008773",
        "aat:300379998"
    ]
},
  "bbox": [],
  "geometry": {"coordinates":[32.701,28.714],"type":"Point"}
}