{
  "id": 2587585,
  "type": "Feature",
  "properties": {
    "tgn:hierarchy":[
        "tgn:2587585",
        "tgn:1000001",
        "tgn:2002325",
        "tgn:7012149",
        "tgn:7007922",
        "tgn:7029392"
    ],
    "tgn:id":2587585,
    "tgn:name":"Pleasant Point",
    "tgn:placetype":[
        "aat:300008850"
    ]
},
  "bbox": [],
  "geometry": {"coordinates":[-88.9333,43.8333],"type":"Point"}
}