{
  "id": 2259238,
  "type": "Feature",
  "properties": {
    "tgn:hierarchy":[
        "tgn:2259238",
        "tgn:1000001",
        "tgn:7012149",
        "tgn:2002119",
        "tgn:7007827",
        "tgn:7029392"
    ],
    "tgn:id":2259238,
    "tgn:name":"Cottonwood Lake",
    "tgn:placetype":[
        "aat:300008680"
    ]
},
  "bbox": [],
  "geometry": {"coordinates":[-109.4333,37.05],"type":"Point"}
}