<<<<<<< HEAD
{
  "id": 2259238,
  "type": "Feature",
  "properties": {
    "tgn:hierarchy":[
        "tgn:2259238",
        "tgn:1000001",
        "tgn:7012149",
        "tgn:2002119",
        "tgn:7007827",
        "tgn:7029392"
    ],
    "tgn:id":2259238,
    "tgn:name":"Cottonwood Lake",
    "tgn:placetype":[
        "aat:300008680"
    ]
},
  "bbox": [],
  "geometry": {"coordinates":[-109.4333,37.05],"type":"Point"}
}
=======
{"geometry":{"type":"Point","coordinates":[-109.433300,37.050000]},"type":"Feature","properties":{"hierarchy":["tgn:2259238","tgn:1000001","tgn:7012149","tgn:2002119","tgn:7007827","tgn:7029392"],"placetype":["aat:300008680"],"id":2259238,"name:xx":"Cottonwood Lake"}}
>>>>>>> 03f74aca74312dbeaf24d7e61306dd6a786dc3d0
