{
  "id": 2591533,
  "type": "Feature",
  "properties": {
    "tgn:hierarchy":[
        "tgn:2591533",
        "tgn:1000001",
        "tgn:7016172",
        "tgn:7012149",
        "tgn:2000138",
        "tgn:7029392"
    ],
    "tgn:id":2591533,
    "tgn:name":"Pompeys Ditch",
    "tgn:placetype":[
        "aat:300006075"
    ]
},
  "bbox": [],
  "geometry": {"coordinates":[-91.2167,35.7333],"type":"Point"}
}