{
  "id": 1097897,
  "type": "Feature",
  "properties": {
    "tgn:hierarchy":[
        "tgn:1097897",
        "tgn:7000490",
        "tgn:1000006",
        "tgn:7001831",
        "tgn:7029392"
    ],
    "tgn:id":1097897,
    "tgn:name":"Palmer",
    "tgn:placetype":[
        "aat:300008347"
    ]
},
  "bbox": [],
  "geometry": {"coordinates":[139.1667,-34.85],"type":"Point"}
}