{
  "id": 7437138,
  "type": "Feature",
  "properties": {
    "tgn:hierarchy":[
        "tgn:7437138",
        "tgn:1000001",
        "tgn:7005594",
        "tgn:7005560",
        "tgn:7029392"
    ],
    "tgn:id":7437138,
    "tgn:name":"Tantate",
    "tgn:placetype":[
        "aat:300008347"
    ]
},
  "bbox": [],
  "geometry": {"coordinates":[-99.016667,21.666667],"type":"Point"}
}