{
  "id": 7381343,
  "type": "Feature",
  "properties": {
    "tgn:hierarchy":[
        "tgn:7381343",
        "tgn:1000001",
        "tgn:7005599",
        "tgn:7005560",
        "tgn:7029392"
    ],
    "tgn:id":7381343,
    "tgn:name":"Los Altos",
    "tgn:placetype":[
        "aat:300008347"
    ]
},
  "bbox": [],
  "geometry": {"coordinates":[-97.766667,21.516667],"type":"Point"}
}