{
  "id": 7275657,
  "type": "Feature",
  "properties": {
    "tgn:hierarchy":[
        "tgn:7275657",
        "tgn:1001637",
        "tgn:1000049",
        "tgn:1000002",
        "tgn:7029392"
    ],
    "tgn:id":7275657,
    "tgn:name":"Trentren",
    "tgn:placetype":[
        "aat:300000206"
    ]
},
  "bbox": [],
  "geometry": {"coordinates":[-73.45,-37.433333],"type":"Point"}
}