{
  "id": 2773412,
  "type": "Feature",
  "properties": {
    "tgn:hierarchy":[
        "tgn:2773412",
        "tgn:1000001",
        "tgn:2001435",
        "tgn:7012149",
        "tgn:7007566",
        "tgn:7029392"
    ],
    "tgn:id":2773412,
    "tgn:name":"Willis",
    "tgn:placetype":[
        "aat:300000390"
    ]
},
  "bbox": [],
  "geometry": {"coordinates":[-107.8667,32.3667],"type":"Point"}
}