{
  "id": 7531116,
  "type": "Feature",
  "properties": {
    "tgn:hierarchy":[
        "tgn:7531116",
        "tgn:7001242",
        "tgn:7016833",
        "tgn:1001113",
        "tgn:7029392"
    ],
    "tgn:id":7531116,
    "tgn:name":"Tur'at as Sa'd\u0101nah",
    "tgn:placetype":[
        "aat:300006075"
    ]
},
  "bbox": [],
  "geometry": {"coordinates":[31.527368,30.418036],"type":"Point"}
}