{
  "id": 1085868,
  "type": "Feature",
  "properties": {
    "tgn:hierarchy":[
        "tgn:1085868",
        "tgn:1001125",
        "tgn:1000004",
        "tgn:7018450",
        "tgn:1000144",
        "tgn:7029392"
    ],
    "tgn:id":1085868,
    "tgn:name":"\u0130lyasbey",
    "tgn:placetype":[
        "aat:300008347"
    ]
},
  "bbox": [],
  "geometry": {"coordinates":[29.8667,40.2333],"type":"Point"}
}