{
  "id": 7473617,
  "type": "Feature",
  "properties": {
    "tgn:hierarchy":[
        "tgn:7473617",
        "tgn:1000004",
        "tgn:7001014",
        "tgn:1000141",
        "tgn:7029392"
    ],
    "tgn:id":7473617,
    "tgn:name":"Dongshicuo",
    "tgn:placetype":[
        "aat:300008347"
    ]
},
  "bbox": [],
  "geometry": {"coordinates":[120.256389,23.676389],"type":"Point"}
}