{
  "id": 2697252,
  "type": "Feature",
  "properties": {
    "tgn:hierarchy":[
        "tgn:2697252",
        "tgn:1000001",
        "tgn:7012149",
        "tgn:7007705",
        "tgn:7029392"
    ],
    "tgn:id":2697252,
    "tgn:name":"Stony Creek",
    "tgn:placetype":[
        "aat:300008706"
    ]
},
  "bbox": [],
  "geometry": {"coordinates":[-102.2833,48.7667],"type":"Point"}
}