<<<<<<< HEAD
{
  "id": 7364295,
  "type": "Feature",
  "properties": {
    "tgn:hierarchy":[
        "tgn:7364295",
        "tgn:1000001",
        "tgn:7005599",
        "tgn:7005560",
        "tgn:7029392"
    ],
    "tgn:id":7364295,
    "tgn:name":"El Blanco",
    "tgn:placetype":[
        "aat:300008347"
    ]
},
  "bbox": [],
  "geometry": {"coordinates":[-95.283333,18.066667],"type":"Point"}
}
=======
{"geometry":{"type":"Point","coordinates":[-95.283333,18.066667]},"type":"Feature","properties":{"hierarchy":["tgn:7364295","tgn:1000001","tgn:7005599","tgn:7005560","tgn:7029392"],"placetype":["aat:300008347"],"id":7364295,"name:xx":"El Blanco"}}
>>>>>>> 03f74aca74312dbeaf24d7e61306dd6a786dc3d0
