{
  "id": 7209931,
  "type": "Feature",
  "properties": {
    "tgn:hierarchy":[
        "tgn:7209931",
        "tgn:1000003",
        "tgn:7003676",
        "tgn:7000084",
        "tgn:7029392"
    ],
    "tgn:id":7209931,
    "tgn:name":"Berkhofer Wiesen",
    "tgn:placetype":[
        "aat:300386990"
    ]
},
  "bbox": [],
  "geometry": {"coordinates":[9.783333,52.616667],"type":"Point"}
}