{
  "id": 2358021,
  "type": "Feature",
  "properties": {
    "tgn:hierarchy":[
        "tgn:2358021",
        "tgn:1000001",
        "tgn:7012149",
        "tgn:1002961",
        "tgn:7007568",
        "tgn:7029392"
    ],
    "tgn:id":2358021,
    "tgn:name":"Graham Mountain",
    "tgn:placetype":[
        "aat:300008798"
    ]
},
  "bbox": [],
  "geometry": {"coordinates":[-74.55,42.0333],"type":"Point"}
}