{
  "id": 2168445,
  "type": "Feature",
  "properties": {
    "tgn:hierarchy":[
        "tgn:2168445",
        "tgn:1000001",
        "tgn:7012149",
        "tgn:2001455",
        "tgn:7007566",
        "tgn:7029392"
    ],
    "tgn:id":2168445,
    "tgn:name":"Big Gyp",
    "tgn:placetype":[
        "aat:300008798"
    ]
},
  "bbox": [],
  "geometry": {"coordinates":[-106.6667,33.3167],"type":"Point"}
}