{
  "id": 7471729,
  "type": "Feature",
  "properties": {
    "tgn:hierarchy":[
        "tgn:7471729",
        "tgn:7001010",
        "tgn:1000004",
        "tgn:1000141",
        "tgn:7029392"
    ],
    "tgn:id":7471729,
    "tgn:name":"Zhuquan Li",
    "tgn:placetype":[
        "aat:300387200"
    ]
},
  "bbox": [],
  "geometry": {"coordinates":[121.592222,23.973056],"type":"Point"}
}