<<<<<<< HEAD
{
  "id": 7471729,
  "type": "Feature",
  "properties": {
    "tgn:hierarchy":[
        "tgn:7471729",
        "tgn:7001010",
        "tgn:1000004",
        "tgn:1000141",
        "tgn:7029392"
    ],
    "tgn:id":7471729,
    "tgn:name":"Zhuquan Li",
    "tgn:placetype":[
        "aat:300387200"
    ]
},
  "bbox": [],
  "geometry": {"coordinates":[121.592222,23.973056],"type":"Point"}
}
=======
{"geometry":{"type":"Point","coordinates":[121.592222,23.973056]},"type":"Feature","properties":{"hierarchy":["tgn:7471729","tgn:7001010","tgn:1000004","tgn:1000141","tgn:7029392"],"placetype":["aat:300387200"],"id":7471729,"name:xx":"Zhuquan Li"}}
>>>>>>> 03f74aca74312dbeaf24d7e61306dd6a786dc3d0
