{
  "id": 7526775,
  "type": "Feature",
  "properties": {
    "tgn:hierarchy":[
        "tgn:7526775",
        "tgn:7001242",
        "tgn:7016833",
        "tgn:1001091",
        "tgn:7029392"
    ],
    "tgn:id":7526775,
    "tgn:name":"Mustashf\u00e1 D\u0101r ash Shif\u0101'",
    "tgn:placetype":[
        "aat:300006676"
    ]
},
  "bbox": [],
  "geometry": {"coordinates":[31.279004,30.071334],"type":"Point"}
}