<<<<<<< HEAD
{
  "id": 2335621,
  "type": "Feature",
  "properties": {
    "tgn:hierarchy":[
        "tgn:2335621",
        "tgn:1000001",
        "tgn:7012149",
        "tgn:2002291",
        "tgn:7013961",
        "tgn:7029392"
    ],
    "tgn:id":2335621,
    "tgn:name":"Fortlick Run",
    "tgn:placetype":[
        "aat:300008699"
    ]
},
  "bbox": [],
  "geometry": {"coordinates":[-80.0833,38.6],"type":"Point"}
}
=======
{"geometry":{"type":"Point","coordinates":[-80.083300,38.600000]},"type":"Feature","properties":{"hierarchy":["tgn:2335621","tgn:1000001","tgn:7012149","tgn:2002291","tgn:7013961","tgn:7029392"],"placetype":["aat:300008699"],"id":2335621,"name:xx":"Fortlick Run"}}
>>>>>>> 03f74aca74312dbeaf24d7e61306dd6a786dc3d0
