{
  "id": 7332393,
  "type": "Feature",
  "properties": {
    "tgn:hierarchy":[
        "tgn:7332393",
        "tgn:7002758",
        "tgn:7002821",
        "tgn:1000003",
        "tgn:1000095",
        "tgn:7029392"
    ],
    "tgn:id":7332393,
    "tgn:name":"Lanjar\u00f3n",
    "tgn:placetype":[
        "aat:300008347"
    ]
},
  "bbox": [],
  "geometry": {"coordinates":[-3.483333,36.916667],"type":"Point"}
}