{
  "id": 2009475,
  "type": "Feature",
  "properties": {
    "tgn:hierarchy":[
        "tgn:2009475",
        "tgn:1000001",
        "tgn:7016172",
        "tgn:7012149",
        "tgn:2000161",
        "tgn:7029392"
    ],
    "tgn:id":2009475,
    "tgn:name":"Shady",
    "tgn:placetype":[
        "aat:300008347",
        "aat:300387210"
    ]
},
  "bbox": [],
  "geometry": {"coordinates":[-94.1167,34.4333],"type":"Point"}
}