{
  "id": 2334494,
  "type": "Feature",
  "properties": {
    "tgn:hierarchy":[
        "tgn:2334494",
        "tgn:1000001",
        "tgn:7012149",
        "tgn:2001281",
        "tgn:7007524",
        "tgn:7029392"
    ],
    "tgn:id":2334494,
    "tgn:name":"Forest Park Mine",
    "tgn:placetype":[
        "aat:300000390"
    ]
},
  "bbox": [],
  "geometry": {"coordinates":[-111.9667,46.4833],"type":"Point"}
}