<<<<<<< HEAD
{
  "id": 2337253,
  "type": "Feature",
  "properties": {
    "tgn:hierarchy":[
        "tgn:2337253",
        "tgn:1000001",
        "tgn:7012149",
        "tgn:2000479",
        "tgn:7007250",
        "tgn:7029392"
    ],
    "tgn:id":2337253,
    "tgn:name":"Fourth Of July Canyon",
    "tgn:placetype":[
        "aat:300008761"
    ]
},
  "bbox": [],
  "geometry": {"coordinates":[-116.5167,47.6167],"type":"Point"}
}
=======
{"geometry":{"type":"Point","coordinates":[-116.516700,47.616700]},"type":"Feature","properties":{"hierarchy":["tgn:2337253","tgn:1000001","tgn:7012149","tgn:2000479","tgn:7007250","tgn:7029392"],"placetype":["aat:300008761"],"id":2337253,"name:xx":"Fourth Of July Canyon"}}
>>>>>>> 03f74aca74312dbeaf24d7e61306dd6a786dc3d0
