{
  "id": 7328227,
  "type": "Feature",
  "properties": {
    "tgn:hierarchy":[
        "tgn:7328227",
        "tgn:7002760",
        "tgn:1000003",
        "tgn:1000095",
        "tgn:7029392"
    ],
    "tgn:id":7328227,
    "tgn:name":"Reoc\u00edn de los Molinos",
    "tgn:placetype":[
        "aat:300008347"
    ]
},
  "bbox": [],
  "geometry": {"coordinates":[-4.05,42.866667],"type":"Point"}
}