{
  "id": 2237425,
  "type": "Feature",
  "properties": {
    "tgn:hierarchy":[
        "tgn:2237425",
        "tgn:1000001",
        "tgn:7012149",
        "tgn:7007250",
        "tgn:7029392"
    ],
    "tgn:id":2237425,
    "tgn:name":"China Creek",
    "tgn:placetype":[
        "aat:300008706"
    ]
},
  "bbox": [],
  "geometry": {"coordinates":[-116.8333,46.0333],"type":"Point"}
}