<<<<<<< HEAD
{
  "id": 7024103,
  "type": "Feature",
  "properties": {
    "tgn:hierarchy":[
        "tgn:7024103",
        "tgn:1000001",
        "tgn:7005600",
        "tgn:7005560",
        "tgn:7029392"
    ],
    "tgn:id":7024103,
    "tgn:name":"Izamal",
    "tgn:placetype":[
        "aat:300008347",
        "aat:300000810",
        "aat:300008375"
    ]
},
  "bbox": [],
  "geometry": {"coordinates":[-89.016667,20.933333],"type":"Point"}
}
=======
{"geometry":{"type":"Point","coordinates":[-89.016667,20.933333]},"type":"Feature","properties":{"hierarchy":["tgn:7024103","tgn:1000001","tgn:7005600","tgn:7005560","tgn:7029392"],"placetype":["aat:300008347","aat:300000810","aat:300008375"],"id":7024103,"name:xx":"Izamal"}}
>>>>>>> 03f74aca74312dbeaf24d7e61306dd6a786dc3d0
