{
  "id": 2612340,
  "type": "Feature",
  "properties": {
    "tgn:hierarchy":[
        "tgn:2612340",
        "tgn:2002143",
        "tgn:1000001",
        "tgn:7012149",
        "tgn:7007919",
        "tgn:7029392"
    ],
    "tgn:id":2612340,
    "tgn:name":"Red Swamp",
    "tgn:placetype":[
        "aat:300008699"
    ]
},
  "bbox": [],
  "geometry": {"coordinates":[-79.7167,38.0667],"type":"Point"}
}