{
  "id": 2145600,
  "type": "Feature",
  "properties": {
    "tgn:hierarchy":[
        "tgn:2145600",
        "tgn:1000001",
        "tgn:7012149",
        "tgn:1002986",
        "tgn:7007568",
        "tgn:7029392"
    ],
    "tgn:id":2145600,
    "tgn:name":"Baldwin Mountain",
    "tgn:placetype":[
        "aat:300008798"
    ]
},
  "bbox": [],
  "geometry": {"coordinates":[-73.7833,43.6833],"type":"Point"}
}