{
  "id": 7332156,
  "type": "Feature",
  "properties": {
    "tgn:hierarchy":[
        "tgn:7332156",
        "tgn:7002836",
        "tgn:7016622",
        "tgn:1000003",
        "tgn:1000095",
        "tgn:7029392"
    ],
    "tgn:id":7332156,
    "tgn:name":"La Ovejera",
    "tgn:placetype":[
        "aat:300008347"
    ]
},
  "bbox": [],
  "geometry": {"coordinates":[-16.283333,28.433333],"type":"Point"}
}