{
  "id": 2171796,
  "type": "Feature",
  "properties": {
    "tgn:hierarchy":[
        "tgn:2171796",
        "tgn:1000001",
        "tgn:7012149",
        "tgn:1002636",
        "tgn:7007708",
        "tgn:7029392"
    ],
    "tgn:id":2171796,
    "tgn:name":"Big Twelve Creek",
    "tgn:placetype":[
        "aat:300008706"
    ]
},
  "bbox": [],
  "geometry": {"coordinates":[-122.3167,44.7833],"type":"Point"}
}