{
  "id": 2312683,
  "type": "Feature",
  "properties": {
    "tgn:hierarchy":[
        "tgn:2312683",
        "tgn:1000001",
        "tgn:7012149",
        "tgn:2001460",
        "tgn:7007566",
        "tgn:7029392"
    ],
    "tgn:id":2312683,
    "tgn:name":"El Cerro Ditch",
    "tgn:placetype":[
        "aat:300006075"
    ]
},
  "bbox": [],
  "geometry": {"coordinates":[-106.6667,34.7667],"type":"Point"}
}