{
  "id": 7052536,
  "type": "Feature",
  "properties": {
    "tgn:hierarchy":[
        "tgn:7052536",
        "tgn:1000003",
        "tgn:7003152",
        "tgn:7003237",
        "tgn:1000080",
        "tgn:7029392"
    ],
    "tgn:id":7052536,
    "tgn:name":"Isolaccia",
    "tgn:placetype":[
        "aat:300008347"
    ]
},
  "bbox": [],
  "geometry": {"coordinates":[10.283333,46.483333],"type":"Point"}
}