{
  "id": 2305265,
  "type": "Feature",
  "properties": {
    "tgn:hierarchy":[
        "tgn:2305265",
        "tgn:1000001",
        "tgn:7012149",
        "tgn:1002392",
        "tgn:7007157",
        "tgn:7029392"
    ],
    "tgn:id":2305265,
    "tgn:name":"East Branch Smith Ferry Canal",
    "tgn:placetype":[
        "aat:300006075"
    ]
},
  "bbox": [],
  "geometry": {"coordinates":[-119.4667,36.5833],"type":"Point"}
}