{
  "id": 7219708,
  "type": "Feature",
  "properties": {
    "tgn:hierarchy":[
        "tgn:7219708",
        "tgn:7011330",
        "tgn:7002674",
        "tgn:1000003",
        "tgn:1000074",
        "tgn:7029392"
    ],
    "tgn:id":7219708,
    "tgn:name":"Nis\u00e1ki, Vrachonis\u00eddes",
    "tgn:placetype":[
        "aat:300008791"
    ]
},
  "bbox": [],
  "geometry": {"coordinates":[27.106111,35.4225],"type":"Point"}
}