{
  "id": 2780314,
  "type": "Feature",
  "properties": {
    "tgn:hierarchy":[
        "tgn:2780314",
        "tgn:1000001",
        "tgn:7012149",
        "tgn:1002463",
        "tgn:7007826",
        "tgn:7029392"
    ],
    "tgn:id":2780314,
    "tgn:name":"Wonder Cave",
    "tgn:placetype":[
        "aat:300008746"
    ]
},
  "bbox": [],
  "geometry": {"coordinates":[-97.95,29.8667],"type":"Point"}
}