{
  "id": 2277323,
  "type": "Feature",
  "properties": {
    "tgn:hierarchy":[
        "tgn:2277323",
        "tgn:1000001",
        "tgn:7012149",
        "tgn:2000374",
        "tgn:7007248",
        "tgn:7029392"
    ],
    "tgn:id":2277323,
    "tgn:name":"Davis Lake",
    "tgn:placetype":[
        "aat:300006191"
    ]
},
  "bbox": [],
  "geometry": {"coordinates":[-82.75,32.6833],"type":"Point"}
}