{
  "id": 7133785,
  "type": "Feature",
  "properties": {
    "tgn:hierarchy":[
        "tgn:7133785",
        "tgn:1000003",
        "tgn:7003676",
        "tgn:7000084",
        "tgn:7029392"
    ],
    "tgn:id":7133785,
    "tgn:name":"Neddenriep",
    "tgn:placetype":[
        "aat:300000206"
    ]
},
  "bbox": [],
  "geometry": {"coordinates":[9.716667,52.933333],"type":"Point"}
}