{
  "id": 7468778,
  "type": "Feature",
  "properties": {
    "tgn:hierarchy":[
        "tgn:7468778",
        "tgn:1000004",
        "tgn:7001009",
        "tgn:1000141",
        "tgn:7029392"
    ],
    "tgn:id":7468778,
    "tgn:name":"Nanmei",
    "tgn:placetype":[
        "aat:300008347"
    ]
},
  "bbox": [],
  "geometry": {"coordinates":[120.74,24.322222],"type":"Point"}
}