{
  "id": 7086735,
  "type": "Feature",
  "properties": {
    "tgn:hierarchy":[
        "tgn:7086735",
        "tgn:1000003",
        "tgn:7003677",
        "tgn:7000084",
        "tgn:7029392"
    ],
    "tgn:id":7086735,
    "tgn:name":"Waldhorst",
    "tgn:placetype":[
        "aat:300000206"
    ]
},
  "bbox": [],
  "geometry": {"coordinates":[6.083333,51.766667],"type":"Point"}
}