{
  "id": 2496334,
  "type": "Feature",
  "properties": {
    "tgn:hierarchy":[
        "tgn:2496334",
        "tgn:1000001",
        "tgn:2001702",
        "tgn:7012149",
        "tgn:7007708",
        "tgn:7029392"
    ],
    "tgn:id":2496334,
    "tgn:name":"Matheny Creek",
    "tgn:placetype":[
        "aat:300008706"
    ]
},
  "bbox": [],
  "geometry": {"coordinates":[-124.1833,43.0333],"type":"Point"}
}