{
  "id": 2384690,
  "type": "Feature",
  "properties": {
    "tgn:hierarchy":[
        "tgn:2384690",
        "tgn:1000001",
        "tgn:7012149",
        "tgn:2002113",
        "tgn:7007827",
        "tgn:7029392"
    ],
    "tgn:id":2384690,
    "tgn:name":"Hellhole Canyon",
    "tgn:placetype":[
        "aat:300008761"
    ]
},
  "bbox": [],
  "geometry": {"coordinates":[-112.7167,37.35],"type":"Point"}
}