{
  "id": 7157787,
  "type": "Feature",
  "properties": {
    "tgn:hierarchy":[
        "tgn:7157787",
        "tgn:1000003",
        "tgn:7003688",
        "tgn:7000084",
        "tgn:7029392"
    ],
    "tgn:id":7157787,
    "tgn:name":"Kiekut",
    "tgn:placetype":[
        "aat:300000206"
    ]
},
  "bbox": [],
  "geometry": {"coordinates":[10.283333,53.65],"type":"Point"}
}