{
  "id": 2142432,
  "type": "Feature",
  "properties": {
    "tgn:hierarchy":[
        "tgn:2142432",
        "tgn:1000001",
        "tgn:7012149",
        "tgn:7007705",
        "tgn:7029392"
    ],
    "tgn:id":2142432,
    "tgn:name":"Bacon Creek",
    "tgn:placetype":[
        "aat:300008706"
    ]
},
  "bbox": [],
  "geometry": {"coordinates":[-103.6833,46.2667],"type":"Point"}
}