{
  "id": 7589727,
  "type": "Feature",
  "properties": {
    "tgn:hierarchy":[
        "tgn:7589727",
        "tgn:1000004",
        "tgn:7000198",
        "tgn:7000799",
        "tgn:7029392"
    ],
    "tgn:id":7589727,
    "tgn:name:en":"Barora",
    "tgn:placetype":[
        "aat:300008347"
    ]
},
  "bbox": [],
  "geometry": {"coordinates":[76.418403,34.680006],"type":"Point"}
}