<<<<<<< HEAD
{
  "id": 2153337,
  "type": "Feature",
  "properties": {
    "tgn:hierarchy":[
        "tgn:2153337",
        "tgn:1000001",
        "tgn:2001260",
        "tgn:7012149",
        "tgn:7007524",
        "tgn:7029392"
    ],
    "tgn:id":2153337,
    "tgn:name":"Bean Creek",
    "tgn:placetype":[
        "aat:300008706"
    ]
},
  "bbox": [],
  "geometry": {"coordinates":[-112.0167,44.5333],"type":"Point"}
}
=======
{"geometry":{"type":"Point","coordinates":[-112.016700,44.533300]},"type":"Feature","properties":{"hierarchy":["tgn:2153337","tgn:1000001","tgn:2001260","tgn:7012149","tgn:7007524","tgn:7029392"],"placetype":["aat:300008706"],"id":2153337,"name:xx":"Bean Creek"}}
>>>>>>> 03f74aca74312dbeaf24d7e61306dd6a786dc3d0
