{
  "id": 2166322,
  "type": "Feature",
  "properties": {
    "tgn:hierarchy":[
        "tgn:2166322",
        "tgn:1000001",
        "tgn:7012149",
        "tgn:2001872",
        "tgn:7007825",
        "tgn:7029392"
    ],
    "tgn:id":2166322,
    "tgn:name":"Big Bend Shoals",
    "tgn:placetype":[
        "aat:300132348"
    ]
},
  "bbox": [],
  "geometry": {"coordinates":[-88.2667,35.05],"type":"Point"}
}