{
  "id": 7259379,
  "type": "Feature",
  "properties": {
    "tgn:hierarchy":[
        "tgn:7259379",
        "tgn:7003456",
        "tgn:1000003",
        "tgn:1000063",
        "tgn:7018236",
        "tgn:7029392"
    ],
    "tgn:id":7259379,
    "tgn:name":"Waalberg",
    "tgn:placetype":[
        "aat:300008347"
    ]
},
  "bbox": [],
  "geometry": {"coordinates":[4.933333,50.983333],"type":"Point"}
}