{
  "id": 2631365,
  "type": "Feature",
  "properties": {
    "tgn:hierarchy":[
        "tgn:2631365",
        "tgn:1000001",
        "tgn:7012149",
        "tgn:1002954",
        "tgn:7007826",
        "tgn:7029392"
    ],
    "tgn:id":2631365,
    "tgn:name":"Round Pond",
    "tgn:placetype":[
        "aat:300008680"
    ]
},
  "bbox": [],
  "geometry": {"coordinates":[-94.8333,31.1333],"type":"Point"}
}