{
  "id": 1128299,
  "type": "Feature",
  "properties": {
    "tgn:hierarchy":[
        "tgn:1128299",
        "tgn:7003669",
        "tgn:1000003",
        "tgn:7000084",
        "tgn:7029392"
    ],
    "tgn:id":1128299,
    "tgn:name":"Paar",
    "tgn:placetype":[
        "aat:300008707",
        "aat:300008699"
    ]
},
  "bbox": [],
  "geometry": {"coordinates":[11.55,48.75],"type":"Point"}
}