{
  "id": 2143175,
  "type": "Feature",
  "properties": {
    "tgn:hierarchy":[
        "tgn:2143175",
        "tgn:1000001",
        "tgn:7012149",
        "tgn:2000420",
        "tgn:7007248",
        "tgn:7029392"
    ],
    "tgn:id":2143175,
    "tgn:name":"Bailey Branch",
    "tgn:placetype":[
        "aat:300008699"
    ]
},
  "bbox": [],
  "geometry": {"coordinates":[-84.15,32.0833],"type":"Point"}
}