<<<<<<< HEAD
{
  "id": 2255745,
  "type": "Feature",
  "properties": {
    "tgn:hierarchy":[
        "tgn:2255745",
        "tgn:1000001",
        "tgn:7012149",
        "tgn:2001867",
        "tgn:7007825",
        "tgn:7029392"
    ],
    "tgn:id":2255745,
    "tgn:name":"Copper Branch",
    "tgn:placetype":[
        "aat:300008699"
    ]
},
  "bbox": [],
  "geometry": {"coordinates":[-85.7167,35.3],"type":"Point"}
}
=======
{"geometry":{"type":"Point","coordinates":[-85.716700,35.300000]},"type":"Feature","properties":{"hierarchy":["tgn:2255745","tgn:1000001","tgn:7012149","tgn:2001867","tgn:7007825","tgn:7029392"],"placetype":["aat:300008699"],"id":2255745,"name:xx":"Copper Branch"}}
>>>>>>> 03f74aca74312dbeaf24d7e61306dd6a786dc3d0
