{
  "id": 2350245,
  "type": "Feature",
  "properties": {
    "tgn:hierarchy":[
        "tgn:2350245",
        "tgn:1000001",
        "tgn:7012149",
        "tgn:2000907",
        "tgn:7007256",
        "tgn:7029392"
    ],
    "tgn:id":2350245,
    "tgn:name":"Gin Lake",
    "tgn:placetype":[
        "aat:300008905"
    ]
},
  "bbox": [],
  "geometry": {"coordinates":[-91.35,31.9167],"type":"Point"}
}