{
  "id": 2695380,
  "type": "Feature",
  "properties": {
    "tgn:hierarchy":[
        "tgn:2695380",
        "tgn:1000001",
        "tgn:7012149",
        "tgn:7014021",
        "tgn:7007709",
        "tgn:7029392"
    ],
    "tgn:id":2695380,
    "tgn:name":"Stillwell Lake",
    "tgn:placetype":[
        "aat:300008680"
    ]
},
  "bbox": [],
  "geometry": {"coordinates":[-80.9167,35.4167],"type":"Point"}
}