{
  "id": 1006863,
  "type": "Feature",
  "properties": {
    "tgn:hierarchy":[
        "tgn:1006863",
        "tgn:7005685",
        "tgn:1000001",
        "tgn:7005804",
        "tgn:7029392"
    ],
    "tgn:id":1006863,
    "tgn:name":"Coudres, \u00cele aux",
    "tgn:placetype":[
        "aat:300008791"
    ]
},
  "bbox": [],
  "geometry": {"coordinates":[-70.4167,47.4167],"type":"Point"}
}