<<<<<<< HEAD
{
  "id": 7357073,
  "type": "Feature",
  "properties": {
    "tgn:hierarchy":[
        "tgn:7357073",
        "tgn:1000001",
        "tgn:7005595",
        "tgn:7005560",
        "tgn:7029392"
    ],
    "tgn:id":7357073,
    "tgn:name":"Carrizal, Cerro",
    "tgn:placetype":[
        "aat:300008795"
    ]
},
  "bbox": [],
  "geometry": {"coordinates":[-106.75,24.516667],"type":"Point"}
}
=======
{"geometry":{"type":"Point","coordinates":[-106.750000,24.516667]},"type":"Feature","properties":{"hierarchy":["tgn:7357073","tgn:1000001","tgn:7005595","tgn:7005560","tgn:7029392"],"placetype":["aat:300008795"],"id":7357073,"name:xx":"Carrizal, Cerro"}}
>>>>>>> 03f74aca74312dbeaf24d7e61306dd6a786dc3d0
