{
  "id": 2204684,
  "type": "Feature",
  "properties": {
    "tgn:hierarchy":[
        "tgn:2204684",
        "tgn:1000001",
        "tgn:7012149",
        "tgn:2000758",
        "tgn:7007254",
        "tgn:7029392"
    ],
    "tgn:id":2204684,
    "tgn:name":"Buffalo Mound",
    "tgn:placetype":[
        "aat:300008798"
    ]
},
  "bbox": [],
  "geometry": {"coordinates":[-96.0667,39.05],"type":"Point"}
}