{
  "id": 2204181,
  "type": "Feature",
  "properties": {
    "tgn:hierarchy":[
        "tgn:2204181",
        "tgn:1000001",
        "tgn:7012149",
        "tgn:2000815",
        "tgn:7007255",
        "tgn:7029392"
    ],
    "tgn:id":2204181,
    "tgn:name":"Buena Vista Creek",
    "tgn:placetype":[
        "aat:300008706"
    ]
},
  "bbox": [],
  "geometry": {"coordinates":[-86.9667,36.85],"type":"Point"}
}