{
  "id": 2310330,
  "type": "Feature",
  "properties": {
    "tgn:hierarchy":[
        "tgn:2310330",
        "tgn:1000001",
        "tgn:7012149",
        "tgn:1002899",
        "tgn:7007920",
        "tgn:7029392"
    ],
    "tgn:id":2310330,
    "tgn:name":"Ebey Island",
    "tgn:placetype":[
        "aat:300008791"
    ]
},
  "bbox": [],
  "geometry": {"coordinates":[-122.15,47.9667],"type":"Point"}
}