{
  "id": 7480640,
  "type": "Feature",
  "properties": {
    "tgn:hierarchy":[
        "tgn:7480640",
        "tgn:7468018",
        "tgn:1000004",
        "tgn:1000141",
        "tgn:7029392"
    ],
    "tgn:id":7480640,
    "tgn:name":"Xiangyun Miao",
    "tgn:placetype":[
        "aat:300007595"
    ]
},
  "bbox": [],
  "geometry": {"coordinates":[120.170755,23.3856],"type":"Point"}
}