<<<<<<< HEAD
{
  "id": 7480640,
  "type": "Feature",
  "properties": {
    "tgn:hierarchy":[
        "tgn:7480640",
        "tgn:7468018",
        "tgn:1000004",
        "tgn:1000141",
        "tgn:7029392"
    ],
    "tgn:id":7480640,
    "tgn:name":"Xiangyun Miao",
    "tgn:placetype":[
        "aat:300007595"
    ]
},
  "bbox": [],
  "geometry": {"coordinates":[120.170755,23.3856],"type":"Point"}
}
=======
{"geometry":{"type":"Point","coordinates":[120.170755,23.385600]},"type":"Feature","properties":{"hierarchy":["tgn:7480640","tgn:7468018","tgn:1000004","tgn:1000141","tgn:7029392"],"placetype":["aat:300007595"],"id":7480640,"name:xx":"Xiangyun Miao"}}
>>>>>>> 03f74aca74312dbeaf24d7e61306dd6a786dc3d0
