{
  "id": 2507142,
  "type": "Feature",
  "properties": {
    "tgn:hierarchy":[
        "tgn:2507142",
        "tgn:1000001",
        "tgn:7012149",
        "tgn:7007157",
        "tgn:2000186",
        "tgn:7029392"
    ],
    "tgn:id":2507142,
    "tgn:name":"Meteorite Tank",
    "tgn:placetype":[
        "aat:300006191"
    ]
},
  "bbox": [],
  "geometry": {"coordinates":[-120.5333,41.9667],"type":"Point"}
}