{
  "id": 7144481,
  "type": "Feature",
  "properties": {
    "tgn:hierarchy":[
        "tgn:7144481",
        "tgn:1000003",
        "tgn:7003688",
        "tgn:7000084",
        "tgn:7029392"
    ],
    "tgn:id":7144481,
    "tgn:name":"Kliffende",
    "tgn:placetype":[
        "aat:300000206"
    ]
},
  "bbox": [],
  "geometry": {"coordinates":[8.333333,54.966667],"type":"Point"}
}