{
  "id": 2309329,
  "type": "Feature",
  "properties": {
    "tgn:hierarchy":[
        "tgn:2309329",
        "tgn:1000001",
        "tgn:7012149",
        "tgn:2002371",
        "tgn:7007923",
        "tgn:7029392"
    ],
    "tgn:id":2309329,
    "tgn:name":"East Sweetwater River",
    "tgn:placetype":[
        "aat:300008707"
    ]
},
  "bbox": [],
  "geometry": {"coordinates":[-108.8833,42.5333],"type":"Point"}
}