{
  "id": 2462690,
  "type": "Feature",
  "properties": {
    "tgn:hierarchy":[
        "tgn:2462690",
        "tgn:1000001",
        "tgn:7012149",
        "tgn:2001029",
        "tgn:7007521",
        "tgn:7029392"
    ],
    "tgn:id":2462690,
    "tgn:name":"Little Wolf Impoundment",
    "tgn:placetype":[
        "aat:300006191"
    ]
},
  "bbox": [],
  "geometry": {"coordinates":[-93.4667,47.4667],"type":"Point"}
}