{
  "id": 7563644,
  "type": "Feature",
  "properties": {
    "tgn:hierarchy":[
        "tgn:7563644",
        "tgn:1000004",
        "tgn:7000198",
        "tgn:1001894",
        "tgn:7029392"
    ],
    "tgn:id":7563644,
    "tgn:name:en":"Maqbara",
    "tgn:placetype":[
        "aat:300008347"
    ]
},
  "bbox": [],
  "geometry": {"coordinates":[79.481621,24.999269],"type":"Point"}
}