{
  "id": 7040360,
  "type": "Feature",
  "properties": {
    "tgn:hierarchy":[
        "tgn:7040360",
        "tgn:7004595",
        "tgn:7003005",
        "tgn:1000003",
        "tgn:1000080",
        "tgn:7029392"
    ],
    "tgn:id":7040360,
    "tgn:name":"Sant'Angelo Radiginosa",
    "tgn:placetype":[
        "aat:300008347"
    ]
},
  "bbox": [],
  "geometry": {"coordinates":[14.766667,41.416667],"type":"Point"}
}