{
  "id": 1019651,
  "type": "Feature",
  "properties": {
    "tgn:hierarchy":[
        "tgn:1019651",
        "tgn:7006477",
        "tgn:1001203",
        "tgn:1000002",
        "tgn:7029392"
    ],
    "tgn:id":1019651,
    "tgn:name":"Lago Futalaufquen",
    "tgn:placetype":[
        "aat:300008347"
    ]
},
  "bbox": [],
  "geometry": {"coordinates":[-71.6167,-42.8833],"type":"Point"}
}