{
  "id": 7545559,
  "type": "Feature",
  "properties": {
    "tgn:hierarchy":[
        "tgn:7545559",
        "tgn:1000004",
        "tgn:7000198",
        "tgn:7016788",
        "tgn:7029392"
    ],
    "tgn:id":7545559,
    "tgn:name:en":"Baghera",
    "tgn:placetype":[
        "aat:300008347"
    ]
},
  "bbox": [],
  "geometry": {"coordinates":[75.317054,26.019496],"type":"Point"}
}