{
  "id": 2278153,
  "type": "Feature",
  "properties": {
    "tgn:hierarchy":[
        "tgn:2278153",
        "tgn:1000001",
        "tgn:7012149",
        "tgn:2001908",
        "tgn:7007825",
        "tgn:7029392"
    ],
    "tgn:id":2278153,
    "tgn:name":"Dayton Quarry Cave",
    "tgn:placetype":[
        "aat:300008746"
    ]
},
  "bbox": [],
  "geometry": {"coordinates":[-85.0167,35.4833],"type":"Point"}
}