{
  "id": 2586317,
  "type": "Feature",
  "properties": {
    "tgn:hierarchy":[
        "tgn:2586317",
        "tgn:1000001",
        "tgn:7012149",
        "tgn:2000181",
        "tgn:7007157",
        "tgn:7029392"
    ],
    "tgn:id":2586317,
    "tgn:name":"Pitcher Creek",
    "tgn:placetype":[
        "aat:300008706"
    ]
},
  "bbox": [],
  "geometry": {"coordinates":[-124.0167,41.1333],"type":"Point"}
}