{
  "id": 1037053,
  "type": "Feature",
  "properties": {
    "tgn:hierarchy":[
        "tgn:1037053",
        "tgn:7000096",
        "tgn:1000003",
        "tgn:7000084",
        "tgn:7029392"
    ],
    "tgn:id":1037053,
    "tgn:name":"Kehrigk",
    "tgn:placetype":[
        "aat:300008347"
    ]
},
  "bbox": [],
  "geometry": {"coordinates":[13.916667,52.15],"type":"Point"}
}