{
  "id": 2628047,
  "type": "Feature",
  "properties": {
    "tgn:hierarchy":[
        "tgn:2628047",
        "tgn:1000001",
        "tgn:7012149",
        "tgn:2001888",
        "tgn:7007825",
        "tgn:7029392"
    ],
    "tgn:id":2628047,
    "tgn:name":"Rolling Hills",
    "tgn:placetype":[
        "aat:300008347"
    ]
},
  "bbox": [],
  "geometry": {"coordinates":[-86.55,35.0667],"type":"Point"}
}