{
  "id": 2109162,
  "type": "Feature",
  "properties": {
    "tgn:hierarchy":[
        "tgn:2109162",
        "tgn:1000001",
        "tgn:7012149",
        "tgn:2002111",
        "tgn:7007827",
        "tgn:7029392"
    ],
    "tgn:id":2109162,
    "tgn:name":"Parowan",
    "tgn:placetype":[
        "aat:300008347"
    ]
},
  "bbox": [],
  "geometry": {"coordinates":[-112.8167,37.8333],"type":"Point"}
}