{
  "id": 7232332,
  "type": "Feature",
  "properties": {
    "tgn:hierarchy":[
        "tgn:7232332",
        "tgn:7002681",
        "tgn:7001395",
        "tgn:1000003",
        "tgn:1000074",
        "tgn:7029392"
    ],
    "tgn:id":7232332,
    "tgn:name":"Koudho\u00fani, Sk\u00f3pelos",
    "tgn:placetype":[
        "aat:300008808"
    ]
},
  "bbox": [],
  "geometry": {"coordinates":[23.883333,37.733333],"type":"Point"}
}