{
  "id": 7519751,
  "type": "Feature",
  "properties": {
    "tgn:hierarchy":[
        "tgn:7519751",
        "tgn:1009227",
        "tgn:1000226",
        "tgn:1000006",
        "tgn:7016850",
        "tgn:7029392"
    ],
    "tgn:id":7519751,
    "tgn:name:en":"Black Hills, The",
    "tgn:placetype":[
        "aat:300008795"
    ]
},
  "bbox": [],
  "geometry": {"coordinates":[170.016667,-44.133333],"type":"Point"}
}