{
  "id": 7419744,
  "type": "Feature",
  "properties": {
    "tgn:hierarchy":[
        "tgn:7419744",
        "tgn:7005579",
        "tgn:1000001",
        "tgn:7005560",
        "tgn:7029392"
    ],
    "tgn:id":7419744,
    "tgn:name":"Puentes",
    "tgn:placetype":[
        "aat:300008347"
    ]
},
  "bbox": [],
  "geometry": {"coordinates":[-102.05,22.233333],"type":"Point"}
}