<<<<<<< HEAD
{
  "id": 7370786,
  "type": "Feature",
  "properties": {
    "tgn:hierarchy":[
        "tgn:7370786",
        "tgn:7005581",
        "tgn:1000001",
        "tgn:7005560",
        "tgn:7029392"
    ],
    "tgn:id":7370786,
    "tgn:name":"Guenotes",
    "tgn:placetype":[
        "aat:300008347"
    ]
},
  "bbox": [],
  "geometry": {"coordinates":[-107.766667,27.0],"type":"Point"}
}
=======
{"geometry":{"type":"Point","coordinates":[-107.766667,27.000000]},"type":"Feature","properties":{"hierarchy":["tgn:7370786","tgn:7005581","tgn:1000001","tgn:7005560","tgn:7029392"],"placetype":["aat:300008347"],"id":7370786,"name:xx":"Guenotes"}}
>>>>>>> 03f74aca74312dbeaf24d7e61306dd6a786dc3d0
