{
  "id": 2230175,
  "type": "Feature",
  "properties": {
    "tgn:hierarchy":[
        "tgn:2230175",
        "tgn:1000001",
        "tgn:7012149",
        "tgn:7007157",
        "tgn:1003046",
        "tgn:7029392"
    ],
    "tgn:id":2230175,
    "tgn:name":"Cement Spring",
    "tgn:placetype":[
        "aat:300008697"
    ]
},
  "bbox": [],
  "geometry": {"coordinates":[-122.15,38.6833],"type":"Point"}
}