{
  "id": 2545172,
  "type": "Feature",
  "properties": {
    "tgn:hierarchy":[
        "tgn:2545172",
        "tgn:1000001",
        "tgn:7012149",
        "tgn:1002545",
        "tgn:7007157",
        "tgn:7029392"
    ],
    "tgn:id":2545172,
    "tgn:name":"North Entrance Rock",
    "tgn:placetype":[
        "aat:300132348"
    ]
},
  "bbox": [],
  "geometry": {"coordinates":[-121.1833,35.6333],"type":"Point"}
}