{
  "id": 2162668,
  "type": "Feature",
  "properties": {
    "tgn:hierarchy":[
        "tgn:2162668",
        "tgn:1000001",
        "tgn:7012149",
        "tgn:2000900",
        "tgn:7007256",
        "tgn:7029392"
    ],
    "tgn:id":2162668,
    "tgn:name":"Bend",
    "tgn:placetype":[
        "aat:300008347"
    ]
},
  "bbox": [],
  "geometry": {"coordinates":[-90.75,30.0167],"type":"Point"}
}