{
  "id": 7295538,
  "type": "Feature",
  "properties": {
    "tgn:hierarchy":[
        "tgn:7295538",
        "tgn:1001439",
        "tgn:1000003",
        "tgn:7002797",
        "tgn:1000095",
        "tgn:7029392"
    ],
    "tgn:id":7295538,
    "tgn:name":"Peque\u00f1o, Barranco",
    "tgn:placetype":[
        "aat:300008773"
    ]
},
  "bbox": [],
  "geometry": {"coordinates":[-0.966667,37.566667],"type":"Point"}
}