{
  "id": 2210308,
  "type": "Feature",
  "properties": {
    "tgn:hierarchy":[
        "tgn:2210308",
        "tgn:1000001",
        "tgn:7012149",
        "tgn:2001275",
        "tgn:7007524",
        "tgn:7029392"
    ],
    "tgn:id":2210308,
    "tgn:name":"Bush Etherington Ditch",
    "tgn:placetype":[
        "aat:300006075"
    ]
},
  "bbox": [],
  "geometry": {"coordinates":[-111.2167,45.5333],"type":"Point"}
}