<<<<<<< HEAD
{
  "id": 2259829,
  "type": "Feature",
  "properties": {
    "tgn:hierarchy":[
        "tgn:2259829",
        "tgn:2002101",
        "tgn:1000001",
        "tgn:7012149",
        "tgn:7007827",
        "tgn:7029392"
    ],
    "tgn:id":2259829,
    "tgn:name":"Cougar Spring",
    "tgn:placetype":[
        "aat:300008697"
    ]
},
  "bbox": [],
  "geometry": {"coordinates":[-113.9667,38.4667],"type":"Point"}
}
=======
{"geometry":{"type":"Point","coordinates":[-113.966700,38.466700]},"type":"Feature","properties":{"hierarchy":["tgn:2259829","tgn:2002101","tgn:1000001","tgn:7012149","tgn:7007827","tgn:7029392"],"placetype":["aat:300008697"],"id":2259829,"name:xx":"Cougar Spring"}}
>>>>>>> 03f74aca74312dbeaf24d7e61306dd6a786dc3d0
