{
  "id": 2259829,
  "type": "Feature",
  "properties": {
    "tgn:hierarchy":[
        "tgn:2259829",
        "tgn:2002101",
        "tgn:1000001",
        "tgn:7012149",
        "tgn:7007827",
        "tgn:7029392"
    ],
    "tgn:id":2259829,
    "tgn:name":"Cougar Spring",
    "tgn:placetype":[
        "aat:300008697"
    ]
},
  "bbox": [],
  "geometry": {"coordinates":[-113.9667,38.4667],"type":"Point"}
}