{
  "id": 2345323,
  "type": "Feature",
  "properties": {
    "tgn:hierarchy":[
        "tgn:2345323",
        "tgn:1000001",
        "tgn:7012149",
        "tgn:2002381",
        "tgn:7007923",
        "tgn:7029392"
    ],
    "tgn:id":2345323,
    "tgn:name":"Garland Gulch",
    "tgn:placetype":[
        "aat:300008761"
    ]
},
  "bbox": [],
  "geometry": {"coordinates":[-107.65,44.7833],"type":"Point"}
}