<<<<<<< HEAD
{
  "id": 2766892,
  "type": "Feature",
  "properties": {
    "tgn:hierarchy":[
        "tgn:2766892",
        "tgn:7014651",
        "tgn:1000001",
        "tgn:7012149",
        "tgn:7007516",
        "tgn:7029392"
    ],
    "tgn:id":2766892,
    "tgn:name":"White Pine Run",
    "tgn:placetype":[
        "aat:300008699"
    ]
},
  "bbox": [],
  "geometry": {"coordinates":[-76.55,38.8833],"type":"Point"}
}
=======
{"geometry":{"type":"Point","coordinates":[-76.550000,38.883300]},"type":"Feature","properties":{"hierarchy":["tgn:2766892","tgn:7014651","tgn:1000001","tgn:7012149","tgn:7007516","tgn:7029392"],"placetype":["aat:300008699"],"id":2766892,"name:xx":"White Pine Run"}}
>>>>>>> 03f74aca74312dbeaf24d7e61306dd6a786dc3d0
