{
  "id": 2433486,
  "type": "Feature",
  "properties": {
    "tgn:hierarchy":[
        "tgn:2433486",
        "tgn:1000001",
        "tgn:7012149",
        "tgn:2001296",
        "tgn:7007524",
        "tgn:7029392"
    ],
    "tgn:id":2433486,
    "tgn:name":"Kellogg Mine",
    "tgn:placetype":[
        "aat:300000390"
    ]
},
  "bbox": [],
  "geometry": {"coordinates":[-112.25,48.15],"type":"Point"}
}