{
  "id": 2649386,
  "type": "Feature",
  "properties": {
    "tgn:hierarchy":[
        "tgn:2649386",
        "tgn:1000001",
        "tgn:7012149",
        "tgn:2001258",
        "tgn:7007523",
        "tgn:7029392"
    ],
    "tgn:id":2649386,
    "tgn:name":"Scotts Branch",
    "tgn:placetype":[
        "aat:300008699"
    ]
},
  "bbox": [],
  "geometry": {"coordinates":[-92.5333,37.35],"type":"Point"}
}