{
  "id": 7076030,
  "type": "Feature",
  "properties": {
    "tgn:hierarchy":[
        "tgn:7076030",
        "tgn:1000003",
        "tgn:7003676",
        "tgn:7000084",
        "tgn:7029392"
    ],
    "tgn:id":7076030,
    "tgn:name":"Friesische Wehde",
    "tgn:placetype":[
        "aat:300055621",
        "aat:300387173"
    ]
},
  "bbox": [],
  "geometry": {"coordinates":[7.95,53.383333],"type":"Point"}
}