{
  "id": 2575086,
  "type": "Feature",
  "properties": {
    "tgn:hierarchy":[
        "tgn:2575086",
        "tgn:1000001",
        "tgn:7012149",
        "tgn:1002924",
        "tgn:7007568",
        "tgn:7029392"
    ],
    "tgn:id":2575086,
    "tgn:name":"Penniman Cove",
    "tgn:placetype":[
        "aat:300132316"
    ]
},
  "bbox": [],
  "geometry": {"coordinates":[-72.5833,40.8167],"type":"Point"}
}