<<<<<<< HEAD
{
  "id": 7476335,
  "type": "Feature",
  "properties": {
    "tgn:hierarchy":[
        "tgn:7476335",
        "tgn:7488858",
        "tgn:1000004",
        "tgn:1000141",
        "tgn:7029392"
    ],
    "tgn:id":7476335,
    "tgn:name":"Shibawan Shan",
    "tgn:placetype":[
        "aat:300008795"
    ]
},
  "bbox": [],
  "geometry": {"coordinates":[120.733234,23.941326],"type":"Point"}
}
=======
{"geometry":{"type":"Point","coordinates":[120.733234,23.941326]},"type":"Feature","properties":{"hierarchy":["tgn:7476335","tgn:7488858","tgn:1000004","tgn:1000141","tgn:7029392"],"placetype":["aat:300008795"],"id":7476335,"name:xx":"Shibawan Shan"}}
>>>>>>> 03f74aca74312dbeaf24d7e61306dd6a786dc3d0
