{
  "id": 2552717,
  "type": "Feature",
  "properties": {
    "tgn:hierarchy":[
        "tgn:2552717",
        "tgn:1002648",
        "tgn:1000001",
        "tgn:7019158",
        "tgn:7012149",
        "tgn:7007249",
        "tgn:7029392"
    ],
    "tgn:id":2552717,
    "tgn:name":"Nuu Bay",
    "tgn:placetype":[
        "aat:300132316"
    ]
},
  "bbox": [],
  "geometry": {"coordinates":[-156.1667,20.6167],"type":"Point"}
}