{
  "id": 2057480,
  "type": "Feature",
  "properties": {
    "tgn:hierarchy":[
        "tgn:2057480",
        "tgn:1000001",
        "tgn:7012149",
        "tgn:2001114",
        "tgn:7007522",
        "tgn:7029392"
    ],
    "tgn:id":2057480,
    "tgn:name":"Shiloh",
    "tgn:placetype":[
        "aat:300008347",
        "aat:300387210"
    ]
},
  "bbox": [],
  "geometry": {"coordinates":[-88.5167,34.3167],"type":"Point"}
}