<<<<<<< HEAD
{
  "id": 2253828,
  "type": "Feature",
  "properties": {
    "tgn:hierarchy":[
        "tgn:2253828",
        "tgn:1000001",
        "tgn:7012149",
        "tgn:2001503",
        "tgn:7007709",
        "tgn:7029392"
    ],
    "tgn:id":2253828,
    "tgn:name":"Cooks Knob",
    "tgn:placetype":[
        "aat:300008798"
    ]
},
  "bbox": [],
  "geometry": {"coordinates":[-83.1,35.65],"type":"Point"}
}
=======
{"geometry":{"type":"Point","coordinates":[-83.100000,35.650000]},"type":"Feature","properties":{"hierarchy":["tgn:2253828","tgn:1000001","tgn:7012149","tgn:2001503","tgn:7007709","tgn:7029392"],"placetype":["aat:300008798"],"id":2253828,"name:xx":"Cooks Knob"}}
>>>>>>> 03f74aca74312dbeaf24d7e61306dd6a786dc3d0
