{
  "id": 7421635,
  "type": "Feature",
  "properties": {
    "tgn:hierarchy":[
        "tgn:7421635",
        "tgn:7005584",
        "tgn:1000001",
        "tgn:7005560",
        "tgn:7029392"
    ],
    "tgn:id":7421635,
    "tgn:name":"San Jos\u00e9 de los Pinos",
    "tgn:placetype":[
        "aat:300008347"
    ]
},
  "bbox": [],
  "geometry": {"coordinates":[-101.390556,21.1275],"type":"Point"}
}