{
  "id": 2119216,
  "type": "Feature",
  "properties": {
    "tgn:hierarchy":[
        "tgn:2119216",
        "tgn:1000001",
        "tgn:7012149",
        "tgn:2002295",
        "tgn:7013961",
        "tgn:7029392"
    ],
    "tgn:id":2119216,
    "tgn:name":"Millertown",
    "tgn:placetype":[
        "aat:300008347",
        "aat:300387210"
    ]
},
  "bbox": [],
  "geometry": {"coordinates":[-79.95,39.2833],"type":"Point"}
}