{
  "id": 2509177,
  "type": "Feature",
  "properties": {
    "tgn:hierarchy":[
        "tgn:2509177",
        "tgn:1000001",
        "tgn:7012149",
        "tgn:7029392"
    ],
    "tgn:id":2509177,
    "tgn:name":"Middle Fork Medicine Creek",
    "tgn:placetype":[
        "aat:300008706"
    ]
},
  "bbox": [],
  "geometry": {"coordinates":[-93.3667,40.6833],"type":"Point"}
}