{
  "id": 2082284,
  "type": "Feature",
  "properties": {
    "tgn:hierarchy":[
        "tgn:2082284",
        "tgn:1000001",
        "tgn:7012149",
        "tgn:1002441",
        "tgn:7007706",
        "tgn:7029392"
    ],
    "tgn:id":2082284,
    "tgn:name":"Twightwee",
    "tgn:placetype":[
        "aat:300008347",
        "aat:300387210"
    ]
},
  "bbox": [],
  "geometry": {"coordinates":[-84.2833,39.25],"type":"Point"}
}