{
  "id": 2217827,
  "type": "Feature",
  "properties": {
    "tgn:hierarchy":[
        "tgn:2217827",
        "tgn:2001728",
        "tgn:1000001",
        "tgn:7012149",
        "tgn:7007712",
        "tgn:7029392"
    ],
    "tgn:id":2217827,
    "tgn:name":"Campbells Lake",
    "tgn:placetype":[
        "aat:300006191"
    ]
},
  "bbox": [],
  "geometry": {"coordinates":[-82.5833,34.6833],"type":"Point"}
}