{
  "id": 2786929,
  "type": "Feature",
  "properties": {
    "tgn:hierarchy":[
        "tgn:2786929",
        "tgn:1000001",
        "tgn:7012149",
        "tgn:1002540",
        "tgn:7007520",
        "tgn:7029392"
    ],
    "tgn:id":2786929,
    "tgn:name":"Ziegenfuss Lake",
    "tgn:placetype":[
        "aat:300008680"
    ]
},
  "bbox": [],
  "geometry": {"coordinates":[-85.3333,43.1667],"type":"Point"}
}