{
  "id": 2403678,
  "type": "Feature",
  "properties": {
    "tgn:hierarchy":[
        "tgn:2403678",
        "tgn:1000001",
        "tgn:7012149",
        "tgn:2000412",
        "tgn:7007248",
        "tgn:7029392"
    ],
    "tgn:id":2403678,
    "tgn:name":"Howard Lake",
    "tgn:placetype":[
        "aat:300006191"
    ]
},
  "bbox": [],
  "geometry": {"coordinates":[-82.2333,33.3667],"type":"Point"}
}