<<<<<<< HEAD
{
  "id": 2403678,
  "type": "Feature",
  "properties": {
    "tgn:hierarchy":[
        "tgn:2403678",
        "tgn:1000001",
        "tgn:7012149",
        "tgn:2000412",
        "tgn:7007248",
        "tgn:7029392"
    ],
    "tgn:id":2403678,
    "tgn:name":"Howard Lake",
    "tgn:placetype":[
        "aat:300006191"
    ]
},
  "bbox": [],
  "geometry": {"coordinates":[-82.2333,33.3667],"type":"Point"}
}
=======
{"geometry":{"type":"Point","coordinates":[-82.233300,33.366700]},"type":"Feature","properties":{"hierarchy":["tgn:2403678","tgn:1000001","tgn:7012149","tgn:2000412","tgn:7007248","tgn:7029392"],"placetype":["aat:300006191"],"id":2403678,"name:xx":"Howard Lake"}}
>>>>>>> 03f74aca74312dbeaf24d7e61306dd6a786dc3d0
