{
  "id": 7003891,
  "type": "Feature",
  "properties": {
    "tgn:hierarchy":[
        "tgn:7003891",
        "tgn:7000683",
        "tgn:7003875",
        "tgn:1000004",
        "tgn:1000137",
        "tgn:7029392"
    ],
    "tgn:id":7003891,
    "tgn:name":"Najr\u0101n",
    "tgn:placetype":[
        "aat:300008347",
        "aat:300008686",
        "aat:300387223",
        "aat:300387235",
        "aat:300008375"
    ]
},
  "bbox": [],
  "geometry": {"coordinates":[44.3167,17.5167],"type":"Point"}
}