{
  "id": 2671883,
  "type": "Feature",
  "properties": {
    "tgn:hierarchy":[
        "tgn:2671883",
        "tgn:1000001",
        "tgn:7012149",
        "tgn:2000236",
        "tgn:7007158",
        "tgn:7029392"
    ],
    "tgn:id":2671883,
    "tgn:name":"Smith Reservoir",
    "tgn:placetype":[
        "aat:300006191"
    ]
},
  "bbox": [],
  "geometry": {"coordinates":[-103.95,37.7667],"type":"Point"}
}