{
  "id": 7174966,
  "type": "Feature",
  "properties": {
    "tgn:hierarchy":[
        "tgn:7174966",
        "tgn:1000003",
        "tgn:7003678",
        "tgn:7000084",
        "tgn:7029392"
    ],
    "tgn:id":7174966,
    "tgn:name":"Grosshausen",
    "tgn:placetype":[
        "aat:300000745"
    ]
},
  "bbox": [],
  "geometry": {"coordinates":[8.55,49.683333],"type":"Point"}
}