<<<<<<< HEAD
{
  "id": 7174966,
  "type": "Feature",
  "properties": {
    "tgn:hierarchy":[
        "tgn:7174966",
        "tgn:1000003",
        "tgn:7003678",
        "tgn:7000084",
        "tgn:7029392"
    ],
    "tgn:id":7174966,
    "tgn:name":"Grosshausen",
    "tgn:placetype":[
        "aat:300000745"
    ]
},
  "bbox": [],
  "geometry": {"coordinates":[8.55,49.683333],"type":"Point"}
}
=======
{"geometry":{"type":"Point","coordinates":[8.550000,49.683333]},"type":"Feature","properties":{"hierarchy":["tgn:7174966","tgn:1000003","tgn:7003678","tgn:7000084","tgn:7029392"],"placetype":["aat:300000745"],"id":7174966,"name:xx":"Grosshausen"}}
>>>>>>> 03f74aca74312dbeaf24d7e61306dd6a786dc3d0
