{
  "id": 2766053,
  "type": "Feature",
  "properties": {
    "tgn:hierarchy":[
        "tgn:2766053",
        "tgn:1000001",
        "tgn:7012149",
        "tgn:1002945",
        "tgn:7007710",
        "tgn:7029392"
    ],
    "tgn:id":2766053,
    "tgn:name":"White Horse Hollow",
    "tgn:placetype":[
        "aat:300008761"
    ]
},
  "bbox": [],
  "geometry": {"coordinates":[-77.5167,41.6333],"type":"Point"}
}