<<<<<<< HEAD
{
  "id": 2766053,
  "type": "Feature",
  "properties": {
    "tgn:hierarchy":[
        "tgn:2766053",
        "tgn:1000001",
        "tgn:7012149",
        "tgn:1002945",
        "tgn:7007710",
        "tgn:7029392"
    ],
    "tgn:id":2766053,
    "tgn:name":"White Horse Hollow",
    "tgn:placetype":[
        "aat:300008761"
    ]
},
  "bbox": [],
  "geometry": {"coordinates":[-77.5167,41.6333],"type":"Point"}
}
=======
{"geometry":{"type":"Point","coordinates":[-77.516700,41.633300]},"type":"Feature","properties":{"hierarchy":["tgn:2766053","tgn:1000001","tgn:7012149","tgn:1002945","tgn:7007710","tgn:7029392"],"placetype":["aat:300008761"],"id":2766053,"name:xx":"White Horse Hollow"}}
>>>>>>> 03f74aca74312dbeaf24d7e61306dd6a786dc3d0
