{
  "id": 2512966,
  "type": "Feature",
  "properties": {
    "tgn:hierarchy":[
        "tgn:2512966",
        "tgn:1000001",
        "tgn:7012149",
        "tgn:2001909",
        "tgn:7007825",
        "tgn:7029392"
    ],
    "tgn:id":2512966,
    "tgn:name":"Mill Creek",
    "tgn:placetype":[
        "aat:300008706"
    ]
},
  "bbox": [],
  "geometry": {"coordinates":[-84.3667,35.8333],"type":"Point"}
}