{
  "id": 2039051,
  "type": "Feature",
  "properties": {
    "tgn:hierarchy":[
        "tgn:2039051",
        "tgn:1000001",
        "tgn:7012149",
        "tgn:1002644",
        "tgn:7007255",
        "tgn:7029392"
    ],
    "tgn:id":2039051,
    "tgn:name":"Germantown",
    "tgn:placetype":[
        "aat:300008347"
    ]
},
  "bbox": [],
  "geometry": {"coordinates":[-83.95,38.65],"type":"Point"}
}