{
  "id": 4001021,
  "type": "Feature",
  "properties": {
    "tgn:hierarchy":[
        "tgn:4001021",
        "tgn:7002445",
        "tgn:1000003",
        "tgn:7008145",
        "tgn:7008591",
        "tgn:7029392"
    ],
    "tgn:id":4001021,
    "tgn:name:en":"Ayot Saint Peter",
    "tgn:placetype":[
        "aat:300008347"
    ]
},
  "bbox": [],
  "geometry": {"coordinates":[-0.216667,51.816667],"type":"Point"}
}