<<<<<<< HEAD
{
  "id": 7173486,
  "type": "Feature",
  "properties": {
    "tgn:hierarchy":[
        "tgn:7173486",
        "tgn:1000003",
        "tgn:7003676",
        "tgn:7000084",
        "tgn:7029392"
    ],
    "tgn:id":7173486,
    "tgn:name":"Gro\u00dfer Schmeerpott",
    "tgn:placetype":[
        "aat:300000206"
    ]
},
  "bbox": [],
  "geometry": {"coordinates":[8.4,53.516667],"type":"Point"}
}
=======
{"geometry":{"type":"Point","coordinates":[8.400000,53.516667]},"type":"Feature","properties":{"hierarchy":["tgn:7173486","tgn:1000003","tgn:7003676","tgn:7000084","tgn:7029392"],"placetype":["aat:300000206"],"id":7173486,"name:xx":"Gro\u00dfer Schmeerpott"}}
>>>>>>> 03f74aca74312dbeaf24d7e61306dd6a786dc3d0
