{
  "id": 7034029,
  "type": "Feature",
  "properties": {
    "tgn:hierarchy":[
        "tgn:7034029",
        "tgn:1001641",
        "tgn:1000003",
        "tgn:7003121",
        "tgn:1000080",
        "tgn:7029392"
    ],
    "tgn:id":7034029,
    "tgn:name":"Piscadeddus, Scogli de",
    "tgn:placetype":[
        "aat:300011692"
    ]
},
  "bbox": [],
  "geometry": {"coordinates":[9.465,39.122778],"type":"Point"}
}