{
  "id": 1057503,
  "type": "Feature",
  "properties": {
    "tgn:hierarchy":[
        "tgn:1057503",
        "tgn:1000004",
        "tgn:7011600",
        "tgn:7018214",
        "tgn:7002435",
        "tgn:7029392"
    ],
    "tgn:id":1057503,
    "tgn:name":"Nizhniye Sergi",
    "tgn:placetype":[
        "aat:300008347"
    ]
},
  "bbox": [],
  "geometry": {"coordinates":[59.3167,56.6667],"type":"Point"}
}