<<<<<<< HEAD
{
  "id": 7474288,
  "type": "Feature",
  "properties": {
    "tgn:hierarchy":[
        "tgn:7474288",
        "tgn:1000004",
        "tgn:1000454",
        "tgn:1000141",
        "tgn:7029392"
    ],
    "tgn:id":7474288,
    "tgn:name":"Yueshanhu",
    "tgn:placetype":[
        "aat:300008347"
    ]
},
  "bbox": [],
  "geometry": {"coordinates":[121.660411,24.953996],"type":"Point"}
}
=======
{"geometry":{"type":"Point","coordinates":[121.660411,24.953996]},"type":"Feature","properties":{"hierarchy":["tgn:7474288","tgn:1000004","tgn:1000454","tgn:1000141","tgn:7029392"],"placetype":["aat:300008347"],"id":7474288,"name:xx":"Yueshanhu"}}
>>>>>>> 03f74aca74312dbeaf24d7e61306dd6a786dc3d0
