{
  "id": 1019201,
  "type": "Feature",
  "properties": {
    "tgn:hierarchy":[
        "tgn:1019201",
        "tgn:7006477",
        "tgn:7006348",
        "tgn:1000002",
        "tgn:7029392"
    ],
    "tgn:id":1019201,
    "tgn:name":"Barda del Medio",
    "tgn:placetype":[
        "aat:300008347"
    ]
},
  "bbox": [],
  "geometry": {"coordinates":[-68.2167,-38.7167],"type":"Point"}
}