{
  "id": 2582303,
  "type": "Feature",
  "properties": {
    "tgn:hierarchy":[
        "tgn:2582303",
        "tgn:1000001",
        "tgn:7012149",
        "tgn:2002356",
        "tgn:7007922",
        "tgn:7029392"
    ],
    "tgn:id":2582303,
    "tgn:name":"Pine Creek",
    "tgn:placetype":[
        "aat:300008706"
    ]
},
  "bbox": [],
  "geometry": {"coordinates":[-90.3333,45.0333],"type":"Point"}
}