{
  "id": 7447104,
  "type": "Feature",
  "properties": {
    "tgn:hierarchy":[
        "tgn:7447104",
        "tgn:7002444",
        "tgn:1000003",
        "tgn:7009907",
        "tgn:7008591",
        "tgn:7029392"
    ],
    "tgn:id":7447104,
    "tgn:name:en":"Skaildaquoy Point",
    "tgn:placetype":[
        "aat:300386846"
    ]
},
  "bbox": [],
  "geometry": {"coordinates":[-2.916667,58.883333],"type":"Point"}
}