{
  "id": 2444233,
  "type": "Feature",
  "properties": {
    "tgn:hierarchy":[
        "tgn:2444233",
        "tgn:1000001",
        "tgn:7020676",
        "tgn:7012149",
        "tgn:7007256",
        "tgn:7029392"
    ],
    "tgn:id":2444233,
    "tgn:name":"Lacassine Point",
    "tgn:placetype":[
        "aat:300008850"
    ]
},
  "bbox": [],
  "geometry": {"coordinates":[-92.8333,29.9333],"type":"Point"}
}