{
  "id": 2569220,
  "type": "Feature",
  "properties": {
    "tgn:hierarchy":[
        "tgn:2569220",
        "tgn:1000001",
        "tgn:7012149",
        "tgn:7007157",
        "tgn:1002828",
        "tgn:7029392"
    ],
    "tgn:id":2569220,
    "tgn:name":"Parks Canyon",
    "tgn:placetype":[
        "aat:300008761"
    ]
},
  "bbox": [],
  "geometry": {"coordinates":[-116.55,33.4333],"type":"Point"}
}