{
  "id": 2419654,
  "type": "Feature",
  "properties": {
    "tgn:hierarchy":[
        "tgn:2419654",
        "tgn:1000001",
        "tgn:2001786",
        "tgn:7012149",
        "tgn:7007713",
        "tgn:7029392"
    ],
    "tgn:id":2419654,
    "tgn:name":"Jasper Cave",
    "tgn:placetype":[
        "aat:300008746"
    ]
},
  "bbox": [],
  "geometry": {"coordinates":[-103.8667,43.7333],"type":"Point"}
}