{
  "id": 1014929,
  "type": "Feature",
  "properties": {
    "tgn:hierarchy":[
        "tgn:1014929",
        "tgn:7005685",
        "tgn:1000001",
        "tgn:7013154",
        "tgn:7029392"
    ],
    "tgn:id":1014929,
    "tgn:name":"Milverton",
    "tgn:placetype":[
        "aat:300008347"
    ]
},
  "bbox": [],
  "geometry": {"coordinates":[-80.9167,43.5667],"type":"Point"}
}