{
  "id": 7258859,
  "type": "Feature",
  "properties": {
    "tgn:hierarchy":[
        "tgn:7258859",
        "tgn:1000003",
        "tgn:7003626",
        "tgn:7016845",
        "tgn:7029392"
    ],
    "tgn:id":7258859,
    "tgn:name:nl":"Boxbergen",
    "tgn:placetype":[
        "aat:300387502"
    ]
},
  "bbox": [],
  "geometry": {"coordinates":[6.183333,52.316667],"type":"Point"}
}