{
  "id": 7534788,
  "type": "Feature",
  "properties": {
    "tgn:hierarchy":[
        "tgn:7534788",
        "tgn:7001242",
        "tgn:7016833",
        "tgn:1001225",
        "tgn:7029392"
    ],
    "tgn:id":7534788,
    "tgn:name:en":"Kadash",
    "tgn:placetype":[
        "aat:300008713"
    ]
},
  "bbox": [],
  "geometry": {"coordinates":[31.966667,31.433333],"type":"Point"}
}