<<<<<<< HEAD
{
  "id": 7376663,
  "type": "Feature",
  "properties": {
    "tgn:hierarchy":[
        "tgn:7376663",
        "tgn:1001835",
        "tgn:1000001",
        "tgn:7005560",
        "tgn:7029392"
    ],
    "tgn:id":7376663,
    "tgn:name":"Loma",
    "tgn:placetype":[
        "aat:300008347"
    ]
},
  "bbox": [],
  "geometry": {"coordinates":[-115.9,32.2],"type":"Point"}
}
=======
{"geometry":{"type":"Point","coordinates":[-115.900000,32.200000]},"type":"Feature","properties":{"hierarchy":["tgn:7376663","tgn:1001835","tgn:1000001","tgn:7005560","tgn:7029392"],"placetype":["aat:300008347"],"id":7376663,"name:xx":"Loma"}}
>>>>>>> 03f74aca74312dbeaf24d7e61306dd6a786dc3d0
