{
  "id": 2651366,
  "type": "Feature",
  "properties": {
    "tgn:hierarchy":[
        "tgn:2651366",
        "tgn:1000001",
        "tgn:7012149",
        "tgn:2001442",
        "tgn:7007566",
        "tgn:7029392"
    ],
    "tgn:id":2651366,
    "tgn:name":"Section Thirty-four Tank",
    "tgn:placetype":[
        "aat:300006191"
    ]
},
  "bbox": [],
  "geometry": {"coordinates":[-105.6667,33.65],"type":"Point"}
}