{
  "id": 2536294,
  "type": "Feature",
  "properties": {
    "tgn:hierarchy":[
        "tgn:2536294",
        "tgn:1000001",
        "tgn:7012149",
        "tgn:2001846",
        "tgn:7007825",
        "tgn:7029392"
    ],
    "tgn:id":2536294,
    "tgn:name":"Nave Branch",
    "tgn:placetype":[
        "aat:300008699"
    ]
},
  "bbox": [],
  "geometry": {"coordinates":[-82.05,36.3667],"type":"Point"}
}