{
  "id": 7375133,
  "type": "Feature",
  "properties": {
    "tgn:hierarchy":[
        "tgn:7375133",
        "tgn:1000001",
        "tgn:7005595",
        "tgn:7005560",
        "tgn:7029392"
    ],
    "tgn:id":7375133,
    "tgn:name":"La Puerta",
    "tgn:placetype":[
        "aat:300008347"
    ]
},
  "bbox": [],
  "geometry": {"coordinates":[-105.883333,22.733333],"type":"Point"}
}