{
  "id": 2068949,
  "type": "Feature",
  "properties": {
    "tgn:hierarchy":[
        "tgn:2068949",
        "tgn:1000001",
        "tgn:7012149",
        "tgn:7014612",
        "tgn:7007568",
        "tgn:7029392"
    ],
    "tgn:id":2068949,
    "tgn:name":"East Irvington",
    "tgn:placetype":[
        "aat:300008347"
    ]
},
  "bbox": [],
  "geometry": {"coordinates":[-73.8333,41.0333],"type":"Point"}
}