{
  "id": 2546837,
  "type": "Feature",
  "properties": {
    "tgn:hierarchy":[
        "tgn:2546837",
        "tgn:7013272",
        "tgn:1000001",
        "tgn:7012149",
        "tgn:7007710",
        "tgn:7029392"
    ],
    "tgn:id":2546837,
    "tgn:name":"North Fork Montour Run",
    "tgn:placetype":[
        "aat:300008699"
    ]
},
  "bbox": [],
  "geometry": {"coordinates":[-80.2667,40.4667],"type":"Point"}
}