<<<<<<< HEAD
{
  "id": 2153827,
  "type": "Feature",
  "properties": {
    "tgn:hierarchy":[
        "tgn:2153827",
        "tgn:1000001",
        "tgn:2000461",
        "tgn:7012149",
        "tgn:7007250",
        "tgn:7029392"
    ],
    "tgn:id":2153827,
    "tgn:name":"Bear Canyon",
    "tgn:placetype":[
        "aat:300008761"
    ]
},
  "bbox": [],
  "geometry": {"coordinates":[-111.1667,43.4667],"type":"Point"}
}
=======
{"geometry":{"type":"Point","coordinates":[-111.166700,43.466700]},"type":"Feature","properties":{"hierarchy":["tgn:2153827","tgn:1000001","tgn:2000461","tgn:7012149","tgn:7007250","tgn:7029392"],"placetype":["aat:300008761"],"id":2153827,"name:xx":"Bear Canyon"}}
>>>>>>> 03f74aca74312dbeaf24d7e61306dd6a786dc3d0
