{
  "id": 2468518,
  "type": "Feature",
  "properties": {
    "tgn:hierarchy":[
        "tgn:2468518",
        "tgn:1000001",
        "tgn:7012149",
        "tgn:1002676",
        "tgn:7007240",
        "tgn:7029392"
    ],
    "tgn:id":2468518,
    "tgn:name":"Long Point Key",
    "tgn:placetype":[
        "aat:300008791"
    ]
},
  "bbox": [],
  "geometry": {"coordinates":[-80.9833,24.7333],"type":"Point"}
}