{
  "id": 2088478,
  "type": "Feature",
  "properties": {
    "tgn:hierarchy":[
        "tgn:2088478",
        "tgn:1000001",
        "tgn:7012149",
        "tgn:1002501",
        "tgn:7007710",
        "tgn:7029392"
    ],
    "tgn:id":2088478,
    "tgn:name":"Five Points",
    "tgn:placetype":[
        "aat:300008347"
    ]
},
  "bbox": [],
  "geometry": {"coordinates":[-79.2167,40.7167],"type":"Point"}
}