{
  "id": 7570529,
  "type": "Feature",
  "properties": {
    "tgn:hierarchy":[
        "tgn:7570529",
        "tgn:1000004",
        "tgn:1001869",
        "tgn:7000198",
        "tgn:7029392"
    ],
    "tgn:id":7570529,
    "tgn:name:en":"Kalai",
    "tgn:placetype":[
        "aat:300008347"
    ]
},
  "bbox": [],
  "geometry": {"coordinates":[72.816667,20.35],"type":"Point"}
}