{
  "id": 7536087,
  "type": "Feature",
  "properties": {
    "tgn:hierarchy":[
        "tgn:7536087",
        "tgn:7001242",
        "tgn:7016833",
        "tgn:1001335",
        "tgn:7029392"
    ],
    "tgn:id":7536087,
    "tgn:name:en":"Khinz\u012br\u012b, Kawm al",
    "tgn:placetype":[
        "aat:300008777"
    ]
},
  "bbox": [],
  "geometry": {"coordinates":[30.928997,31.358636],"type":"Point"}
}