{
  "id": 7024404,
  "type": "Feature",
  "properties": {
    "tgn:hierarchy":[
        "tgn:7024404",
        "tgn:1000001",
        "tgn:7005592",
        "tgn:7005560",
        "tgn:7029392"
    ],
    "tgn:id":7024404,
    "tgn:name":"Tepostitl\u00e1n",
    "tgn:placetype":[
        "aat:300008347"
    ]
},
  "bbox": [],
  "geometry": {"coordinates":[-97.65,18.366667],"type":"Point"}
}