{
  "id": 7199879,
  "type": "Feature",
  "properties": {
    "tgn:hierarchy":[
        "tgn:7199879",
        "tgn:1000003",
        "tgn:7003678",
        "tgn:7000084",
        "tgn:7029392"
    ],
    "tgn:id":7199879,
    "tgn:name":"Dreibornsk\u00f6pfe",
    "tgn:placetype":[
        "aat:300008777"
    ]
},
  "bbox": [],
  "geometry": {"coordinates":[8.066667,50.083333],"type":"Point"}
}