{
  "id": 7401454,
  "type": "Feature",
  "properties": {
    "tgn:hierarchy":[
        "tgn:7401454",
        "tgn:1000001",
        "tgn:7005599",
        "tgn:7005560",
        "tgn:7029392"
    ],
    "tgn:id":7401454,
    "tgn:name":"Lomas de Tecamichapa",
    "tgn:placetype":[
        "aat:300008347"
    ]
},
  "bbox": [],
  "geometry": {"coordinates":[-94.716667,17.858333],"type":"Point"}
}