{
  "id": 7325310,
  "type": "Feature",
  "properties": {
    "tgn:hierarchy":[
        "tgn:7325310",
        "tgn:7002758",
        "tgn:7002841",
        "tgn:1000003",
        "tgn:1000095",
        "tgn:7029392"
    ],
    "tgn:id":7325310,
    "tgn:name":"Sancha, Arroyo de",
    "tgn:placetype":[
        "aat:300008699"
    ]
},
  "bbox": [],
  "geometry": {"coordinates":[-5.433333,37.766667],"type":"Point"}
}