{
  "id": 7018402,
  "type": "Feature",
  "properties": {
    "tgn:hierarchy":[
        "tgn:7018402",
        "tgn:7018396",
        "tgn:1000004",
        "tgn:1000121",
        "tgn:7029392"
    ],
    "tgn:id":7018402,
    "tgn:name":"Al Q\u0101disiyah",
    "tgn:placetype":[
        "aat:300008347"
    ]
},
  "bbox": [],
  "geometry": {"coordinates":[35.64,30.642],"type":"Point"}
}