{
  "id": 2554977,
  "type": "Feature",
  "properties": {
    "tgn:hierarchy":[
        "tgn:2554977",
        "tgn:2000293",
        "tgn:1000001",
        "tgn:7012149",
        "tgn:7007248",
        "tgn:7029392"
    ],
    "tgn:id":2554977,
    "tgn:name":"Oberry",
    "tgn:placetype":[
        "aat:300008347"
    ]
},
  "bbox": [],
  "geometry": {"coordinates":[-82.9667,31.3833],"type":"Point"}
}