{
  "id": 2341764,
  "type": "Feature",
  "properties": {
    "tgn:hierarchy":[
        "tgn:2341764",
        "tgn:1000001",
        "tgn:2001411",
        "tgn:7012149",
        "tgn:7007526",
        "tgn:7029392"
    ],
    "tgn:id":2341764,
    "tgn:name":"Frost Springs",
    "tgn:placetype":[
        "aat:300008697"
    ]
},
  "bbox": [],
  "geometry": {"coordinates":[-115.6667,40.3167],"type":"Point"}
}