{
  "id": 7491104,
  "type": "Feature",
  "properties": {
    "tgn:hierarchy":[
        "tgn:7491104",
        "tgn:7001010",
        "tgn:1000004",
        "tgn:1000141",
        "tgn:7029392"
    ],
    "tgn:id":7491104,
    "tgn:name":"Beinan Shan",
    "tgn:placetype":[
        "aat:300008798"
    ]
},
  "bbox": [],
  "geometry": {"coordinates":[121.615526,24.318702],"type":"Point"}
}