{
  "id": 2010658,
  "type": "Feature",
  "properties": {
    "tgn:hierarchy":[
        "tgn:2010658",
        "tgn:1000001",
        "tgn:7012149",
        "tgn:7007157",
        "tgn:1002608",
        "tgn:7029392"
    ],
    "tgn:id":2010658,
    "tgn:name":"Cerritos",
    "tgn:placetype":[
        "aat:300008347"
    ]
},
  "bbox": [],
  "geometry": {"coordinates":[-118.05,33.85],"type":"Point"}
}