<<<<<<< HEAD
{
  "id": 2258068,
  "type": "Feature",
  "properties": {
    "tgn:hierarchy":[
        "tgn:2258068",
        "tgn:1000001",
        "tgn:7012149",
        "tgn:1003038",
        "tgn:7007517",
        "tgn:7029392"
    ],
    "tgn:id":2258068,
    "tgn:name":"Cosgrove Aqueduct",
    "tgn:placetype":[
        "aat:300006075"
    ]
},
  "bbox": [],
  "geometry": {"coordinates":[-71.65,42.3833],"type":"Point"}
}
=======
{"geometry":{"type":"Point","coordinates":[-71.650000,42.383300]},"type":"Feature","properties":{"hierarchy":["tgn:2258068","tgn:1000001","tgn:7012149","tgn:1003038","tgn:7007517","tgn:7029392"],"placetype":["aat:300006075"],"id":2258068,"name:xx":"Cosgrove Aqueduct"}}
>>>>>>> 03f74aca74312dbeaf24d7e61306dd6a786dc3d0
