{
  "id": 7480258,
  "type": "Feature",
  "properties": {
    "tgn:hierarchy":[
        "tgn:7480258",
        "tgn:1000004",
        "tgn:7490934",
        "tgn:1000141",
        "tgn:7029392"
    ],
    "tgn:id":7480258,
    "tgn:name":"Dapingding",
    "tgn:placetype":[
        "aat:300008347"
    ]
},
  "bbox": [],
  "geometry": {"coordinates":[120.391511,23.1554],"type":"Point"}
}