{
  "id": 7539071,
  "type": "Feature",
  "properties": {
    "tgn:hierarchy":[
        "tgn:7539071",
        "tgn:7001242",
        "tgn:7016833",
        "tgn:1001418",
        "tgn:7029392"
    ],
    "tgn:id":7539071,
    "tgn:name:en":"Mus\u0101'id",
    "tgn:placetype":[
        "aat:300006909"
    ]
},
  "bbox": [],
  "geometry": {"coordinates":[25.100387,31.56699],"type":"Point"}
}