{
  "id": 2245226,
  "type": "Feature",
  "properties": {
    "tgn:hierarchy":[
        "tgn:2245226",
        "tgn:1000001",
        "tgn:7020676",
        "tgn:7012149",
        "tgn:7007256",
        "tgn:7029392"
    ],
    "tgn:id":2245226,
    "tgn:name":"Club Canal",
    "tgn:placetype":[
        "aat:300006075"
    ]
},
  "bbox": [],
  "geometry": {"coordinates":[-92.9167,29.7167],"type":"Point"}
}