{
  "id": 2449639,
  "type": "Feature",
  "properties": {
    "tgn:hierarchy":[
        "tgn:2449639",
        "tgn:1000001",
        "tgn:7012149",
        "tgn:7007828",
        "tgn:7029392"
    ],
    "tgn:id":2449639,
    "tgn:name":"Lincoln Mountain",
    "tgn:placetype":[
        "aat:300008798"
    ]
},
  "bbox": [],
  "geometry": {"coordinates":[-72.9167,44.15],"type":"Point"}
}