{
  "id": 7380941,
  "type": "Feature",
  "properties": {
    "tgn:hierarchy":[
        "tgn:7380941",
        "tgn:1000001",
        "tgn:1001960",
        "tgn:7005560",
        "tgn:7029392"
    ],
    "tgn:id":7380941,
    "tgn:name":"M\u00e9dano",
    "tgn:placetype":[
        "aat:300008347"
    ]
},
  "bbox": [],
  "geometry": {"coordinates":[-110.533333,27.616667],"type":"Point"}
}