{
  "id": 2673997,
  "type": "Feature",
  "properties": {
    "tgn:hierarchy":[
        "tgn:2673997",
        "tgn:1000001",
        "tgn:7012149",
        "tgn:7007157",
        "tgn:1002608",
        "tgn:7029392"
    ],
    "tgn:id":2673997,
    "tgn:name":"Snow Spring",
    "tgn:placetype":[
        "aat:300008697"
    ]
},
  "bbox": [],
  "geometry": {"coordinates":[-117.85,34.3333],"type":"Point"}
}