{
  "id": 7029729,
  "type": "Feature",
  "properties": {
    "tgn:hierarchy":[
        "tgn:7029729",
        "tgn:7002878",
        "tgn:1000003",
        "tgn:1000070",
        "tgn:7029392"
    ],
    "tgn:id":7029729,
    "tgn:name:fr":"Lacommande",
    "tgn:placetype":[
        "aat:300008347"
    ]
},
  "bbox": [],
  "geometry": {"coordinates":[-0.508,43.266],"type":"Point"}
}