<<<<<<< HEAD
{
  "id": 7029729,
  "type": "Feature",
  "properties": {
    "tgn:hierarchy":[
        "tgn:7029729",
        "tgn:7002878",
        "tgn:1000003",
        "tgn:1000070",
        "tgn:7029392"
    ],
    "tgn:id":7029729,
    "tgn:name:fr":"Lacommande",
    "tgn:placetype":[
        "aat:300008347"
    ]
},
  "bbox": [],
  "geometry": {"coordinates":[-0.508,43.266],"type":"Point"}
}
=======
{"geometry":{"type":"Point","coordinates":[-0.508000,43.266000]},"type":"Feature","properties":{"hierarchy":["tgn:7029729","tgn:7002878","tgn:1000003","tgn:1000070","tgn:7029392"],"placetype":["aat:300008347"],"name:fr":"Lacommande","id":7029729}}
>>>>>>> 03f74aca74312dbeaf24d7e61306dd6a786dc3d0
