{
  "id": 2641915,
  "type": "Feature",
  "properties": {
    "tgn:hierarchy":[
        "tgn:2641915",
        "tgn:1000001",
        "tgn:7012149",
        "tgn:1002699",
        "tgn:7007708",
        "tgn:7029392"
    ],
    "tgn:id":2641915,
    "tgn:name":"Sand Lake",
    "tgn:placetype":[
        "aat:300006191"
    ]
},
  "bbox": [],
  "geometry": {"coordinates":[-122.8333,45.65],"type":"Point"}
}