{
  "id": 7550777,
  "type": "Feature",
  "properties": {
    "tgn:hierarchy":[
        "tgn:7550777",
        "tgn:1000004",
        "tgn:7000198",
        "tgn:1001997",
        "tgn:7029392"
    ],
    "tgn:id":7550777,
    "tgn:name:en":"Chaton",
    "tgn:placetype":[
        "aat:300008347"
    ]
},
  "bbox": [],
  "geometry": {"coordinates":[93.728441,25.297582],"type":"Point"}
}