<<<<<<< HEAD
{
  "id": 2764216,
  "type": "Feature",
  "properties": {
    "tgn:hierarchy":[
        "tgn:2764216",
        "tgn:1000001",
        "tgn:7012149",
        "tgn:2001459",
        "tgn:7007566",
        "tgn:7029392"
    ],
    "tgn:id":2764216,
    "tgn:name":"Wheeler Springs",
    "tgn:placetype":[
        "aat:300008697"
    ]
},
  "bbox": [],
  "geometry": {"coordinates":[-103.95,36.9833],"type":"Point"}
}
=======
{"geometry":{"type":"Point","coordinates":[-103.950000,36.983300]},"type":"Feature","properties":{"hierarchy":["tgn:2764216","tgn:1000001","tgn:7012149","tgn:2001459","tgn:7007566","tgn:7029392"],"placetype":["aat:300008697"],"id":2764216,"name:xx":"Wheeler Springs"}}
>>>>>>> 03f74aca74312dbeaf24d7e61306dd6a786dc3d0
