{
  "id": 2273018,
  "type": "Feature",
  "properties": {
    "tgn:hierarchy":[
        "tgn:2273018",
        "tgn:1000001",
        "tgn:7013368",
        "tgn:7012149",
        "tgn:7007709",
        "tgn:7029392"
    ],
    "tgn:id":2273018,
    "tgn:name":"Cutting Sedge Creek",
    "tgn:placetype":[
        "aat:300008706"
    ]
},
  "bbox": [],
  "geometry": {"coordinates":[-76.5833,35.55],"type":"Point"}
}