{
  "id": 7475284,
  "type": "Feature",
  "properties": {
    "tgn:hierarchy":[
        "tgn:7475284",
        "tgn:1000004",
        "tgn:1000454",
        "tgn:1000141",
        "tgn:7029392"
    ],
    "tgn:id":7475284,
    "tgn:name":"Butoukeng Qiao",
    "tgn:placetype":[
        "aat:300007836"
    ]
},
  "bbox": [],
  "geometry": {"coordinates":[121.50859,25.254316],"type":"Point"}
}