{
  "id": 2343128,
  "type": "Feature",
  "properties": {
    "tgn:hierarchy":[
        "tgn:2343128",
        "tgn:1000001",
        "tgn:7012149",
        "tgn:2000485",
        "tgn:7007250",
        "tgn:7029392"
    ],
    "tgn:id":2343128,
    "tgn:name":"Gabettas Reservoir",
    "tgn:placetype":[
        "aat:300006191"
    ]
},
  "bbox": [],
  "geometry": {"coordinates":[-113.4167,42.9167],"type":"Point"}
}