{
  "id": 7024809,
  "type": "Feature",
  "properties": {
    "tgn:hierarchy":[
        "tgn:7024809",
        "tgn:7002445",
        "tgn:7008104",
        "tgn:1000003",
        "tgn:7008591",
        "tgn:7029392"
    ],
    "tgn:id":7024809,
    "tgn:name:ang":"Coblincote",
    "tgn:placetype":[
        "aat:300008347"
    ]
},
  "bbox": [],
  "geometry": {"coordinates":[-0.766667,51.883333],"type":"Point"}
}