{
  "id": 2163889,
  "type": "Feature",
  "properties": {
    "tgn:hierarchy":[
        "tgn:2163889",
        "tgn:7006450",
        "tgn:1000001",
        "tgn:7012149",
        "tgn:2000088",
        "tgn:7029392"
    ],
    "tgn:id":2163889,
    "tgn:name":"Berg Mountain",
    "tgn:placetype":[
        "aat:300008798"
    ]
},
  "bbox": [],
  "geometry": {"coordinates":[-131.9833,56.45],"type":"Point"}
}