{
  "id": 7341186,
  "type": "Feature",
  "properties": {
    "tgn:hierarchy":[
        "tgn:7341186",
        "tgn:7007780",
        "tgn:1000003",
        "tgn:7009604",
        "tgn:1000095",
        "tgn:7029392"
    ],
    "tgn:id":7341186,
    "tgn:name":"Br\u00edncola",
    "tgn:placetype":[
        "aat:300008347"
    ]
},
  "bbox": [],
  "geometry": {"coordinates":[-2.336282,43.022186],"type":"Point"}
}