{
  "id": 2701005,
  "type": "Feature",
  "properties": {
    "tgn:hierarchy":[
        "tgn:2701005",
        "tgn:1000001",
        "tgn:2001100",
        "tgn:7012149",
        "tgn:7007522",
        "tgn:7029392"
    ],
    "tgn:id":2701005,
    "tgn:name":"Sugar Creek",
    "tgn:placetype":[
        "aat:300008706"
    ]
},
  "bbox": [],
  "geometry": {"coordinates":[-90.55,31.95],"type":"Point"}
}