{
  "id": 2179475,
  "type": "Feature",
  "properties": {
    "tgn:hierarchy":[
        "tgn:2179475",
        "tgn:1000001",
        "tgn:7012149",
        "tgn:2001304",
        "tgn:7007524",
        "tgn:7029392"
    ],
    "tgn:id":2179475,
    "tgn:name":"Blanchards Corner",
    "tgn:placetype":[
        "aat:300008347"
    ]
},
  "bbox": [],
  "geometry": {"coordinates":[-114.8667,47.55],"type":"Point"}
}