{
  "id": 2058483,
  "type": "Feature",
  "properties": {
    "tgn:hierarchy":[
        "tgn:2058483",
        "tgn:1000001",
        "tgn:7012149",
        "tgn:2001256",
        "tgn:7007523",
        "tgn:7029392"
    ],
    "tgn:id":2058483,
    "tgn:name":"Cross Way",
    "tgn:placetype":[
        "aat:300008347",
        "aat:300387210"
    ]
},
  "bbox": [],
  "geometry": {"coordinates":[-93.05,37.3667],"type":"Point"}
}