{
  "id": 7276367,
  "type": "Feature",
  "properties": {
    "tgn:hierarchy":[
        "tgn:7276367",
        "tgn:1001657",
        "tgn:1000049",
        "tgn:1000002",
        "tgn:7029392"
    ],
    "tgn:id":7276367,
    "tgn:name":"Tilama",
    "tgn:placetype":[
        "aat:300000206"
    ]
},
  "bbox": [],
  "geometry": {"coordinates":[-71.183333,-32.083333],"type":"Point"}
}