{
  "id": 2159589,
  "type": "Feature",
  "properties": {
    "tgn:hierarchy":[
        "tgn:2159589",
        "tgn:1000001",
        "tgn:7012149",
        "tgn:2002300",
        "tgn:7013961",
        "tgn:7029392"
    ],
    "tgn:id":2159589,
    "tgn:name":"Bee Run",
    "tgn:placetype":[
        "aat:300008699"
    ]
},
  "bbox": [],
  "geometry": {"coordinates":[-80.5833,38.4333],"type":"Point"}
}