{
  "id": 1012098,
  "type": "Feature",
  "properties": {
    "tgn:hierarchy":[
        "tgn:1012098",
        "tgn:7002036",
        "tgn:7014654",
        "tgn:1000217",
        "tgn:1000006",
        "tgn:7029392"
    ],
    "tgn:id":1012098,
    "tgn:name":"Lilian Point",
    "tgn:placetype":[
        "aat:300386846"
    ]
},
  "bbox": [],
  "geometry": {"coordinates":[169.5833,-0.8833],"type":"Point"}
}