{
  "id": 7417654,
  "type": "Feature",
  "properties": {
    "tgn:hierarchy":[
        "tgn:7417654",
        "tgn:7005584",
        "tgn:1000001",
        "tgn:7005560",
        "tgn:7029392"
    ],
    "tgn:id":7417654,
    "tgn:name":"Puerta de Obrajuelo",
    "tgn:placetype":[
        "aat:300008347"
    ]
},
  "bbox": [],
  "geometry": {"coordinates":[-100.513889,20.601389],"type":"Point"}
}