{
  "id": 2467949,
  "type": "Feature",
  "properties": {
    "tgn:hierarchy":[
        "tgn:2467949",
        "tgn:1000001",
        "tgn:7012149",
        "tgn:1002967",
        "tgn:7007520",
        "tgn:7029392"
    ],
    "tgn:id":2467949,
    "tgn:name":"Long Lake",
    "tgn:placetype":[
        "aat:300008680"
    ]
},
  "bbox": [],
  "geometry": {"coordinates":[-85.7833,42.3667],"type":"Point"}
}