{
  "id": 1078880,
  "type": "Feature",
  "properties": {
    "tgn:hierarchy":[
        "tgn:1078880",
        "tgn:1000004",
        "tgn:1007331",
        "tgn:1001409",
        "tgn:1000116",
        "tgn:7029392"
    ],
    "tgn:id":1078880,
    "tgn:name":"Weda",
    "tgn:placetype":[
        "aat:300008347"
    ]
},
  "bbox": [],
  "geometry": {"coordinates":[127.8667,0.3333],"type":"Point"}
}