{
  "id": 2739814,
  "type": "Feature",
  "properties": {
    "tgn:hierarchy":[
        "tgn:2739814",
        "tgn:1000001",
        "tgn:7016172",
        "tgn:7012149",
        "tgn:2000152",
        "tgn:7029392"
    ],
    "tgn:id":2739814,
    "tgn:name":"Upper Eagle Nest Lake",
    "tgn:placetype":[
        "aat:300008680"
    ]
},
  "bbox": [],
  "geometry": {"coordinates":[-91.2167,34.5167],"type":"Point"}
}