{
  "id": 2081079,
  "type": "Feature",
  "properties": {
    "tgn:hierarchy":[
        "tgn:2081079",
        "tgn:1000001",
        "tgn:7012149",
        "tgn:1002955",
        "tgn:7007706",
        "tgn:7029392"
    ],
    "tgn:id":2081079,
    "tgn:name":"North Bloomfield",
    "tgn:placetype":[
        "aat:300008347"
    ]
},
  "bbox": [],
  "geometry": {"coordinates":[-80.8667,41.45],"type":"Point"}
}