<<<<<<< HEAD
{
  "id": 7356767,
  "type": "Feature",
  "properties": {
    "tgn:hierarchy":[
        "tgn:7356767",
        "tgn:1000001",
        "tgn:7005600",
        "tgn:7005560",
        "tgn:7029392"
    ],
    "tgn:id":7356767,
    "tgn:name":"Chinkil\u00e1",
    "tgn:placetype":[
        "aat:300008347"
    ]
},
  "bbox": [],
  "geometry": {"coordinates":[-89.4,20.683333],"type":"Point"}
}
=======
{"geometry":{"type":"Point","coordinates":[-89.400000,20.683333]},"type":"Feature","properties":{"hierarchy":["tgn:7356767","tgn:1000001","tgn:7005600","tgn:7005560","tgn:7029392"],"placetype":["aat:300008347"],"id":7356767,"name:xx":"Chinkil\u00e1"}}
>>>>>>> 03f74aca74312dbeaf24d7e61306dd6a786dc3d0
