{
  "id": 7275980,
  "type": "Feature",
  "properties": {
    "tgn:hierarchy":[
        "tgn:7275980",
        "tgn:1001630",
        "tgn:1000049",
        "tgn:1000002",
        "tgn:7029392"
    ],
    "tgn:id":7275980,
    "tgn:name":"Torrent",
    "tgn:placetype":[
        "aat:300387033"
    ]
},
  "bbox": [],
  "geometry": {"coordinates":[-69.833333,-26.166667],"type":"Point"}
}