{
  "id": 2352290,
  "type": "Feature",
  "properties": {
    "tgn:hierarchy":[
        "tgn:2352290",
        "tgn:1000001",
        "tgn:7006451",
        "tgn:7012149",
        "tgn:2000102",
        "tgn:7029392"
    ],
    "tgn:id":2352290,
    "tgn:name":"Goat Canyon",
    "tgn:placetype":[
        "aat:300008761"
    ]
},
  "bbox": [],
  "geometry": {"coordinates":[-110.7833,31.55],"type":"Point"}
}