{
  "id": 1019867,
  "type": "Feature",
  "properties": {
    "tgn:hierarchy":[
        "tgn:1019867",
        "tgn:7006477",
        "tgn:1001450",
        "tgn:1000002",
        "tgn:7029392"
    ],
    "tgn:id":1019867,
    "tgn:name":"Plottier",
    "tgn:placetype":[
        "aat:300008347"
    ]
},
  "bbox": [],
  "geometry": {"coordinates":[-68.2333,-38.9667],"type":"Point"}
}