<<<<<<< HEAD
{
  "id": 2337116,
  "type": "Feature",
  "properties": {
    "tgn:hierarchy":[
        "tgn:2337116",
        "tgn:1000001",
        "tgn:7012149",
        "tgn:2001447",
        "tgn:7007566",
        "tgn:7029392"
    ],
    "tgn:id":2337116,
    "tgn:name":"Fourmile Tank",
    "tgn:placetype":[
        "aat:300006191"
    ]
},
  "bbox": [],
  "geometry": {"coordinates":[-105.2,32.0167],"type":"Point"}
}
=======
{"geometry":{"type":"Point","coordinates":[-105.200000,32.016700]},"type":"Feature","properties":{"hierarchy":["tgn:2337116","tgn:1000001","tgn:7012149","tgn:2001447","tgn:7007566","tgn:7029392"],"placetype":["aat:300006191"],"id":2337116,"name:xx":"Fourmile Tank"}}
>>>>>>> 03f74aca74312dbeaf24d7e61306dd6a786dc3d0
