{
  "id": 7235746,
  "type": "Feature",
  "properties": {
    "tgn:hierarchy":[
        "tgn:7235746",
        "tgn:7002745",
        "tgn:7017076",
        "tgn:1000003",
        "tgn:1000074",
        "tgn:7029392"
    ],
    "tgn:id":7235746,
    "tgn:name":"Ara\u00edoi",
    "tgn:placetype":[
        "aat:300008347"
    ]
},
  "bbox": [],
  "geometry": {"coordinates":[22.95,36.25],"type":"Point"}
}