<<<<<<< HEAD
{
  "id": 7023307,
  "type": "Feature",
  "properties": {
    "tgn:hierarchy":[
        "tgn:7023307",
        "tgn:1000001",
        "tgn:7012149",
        "tgn:7029392"
    ],
    "tgn:id":7023307,
    "tgn:name":"Looney Ridge",
    "tgn:placetype":[
        "aat:300266640"
    ]
},
  "bbox": [],
  "geometry": {"coordinates":[-82.85,36.9],"type":"Point"}
}
=======
{"geometry":{"type":"Point","coordinates":[-82.850000,36.900000]},"type":"Feature","properties":{"hierarchy":["tgn:7023307","tgn:1000001","tgn:7012149","tgn:7029392"],"placetype":["aat:300266640"],"id":7023307,"name:xx":"Looney Ridge"}}
>>>>>>> 03f74aca74312dbeaf24d7e61306dd6a786dc3d0
