{
  "id": 2284398,
  "type": "Feature",
  "properties": {
    "tgn:hierarchy":[
        "tgn:2284398",
        "tgn:1000001",
        "tgn:7012149",
        "tgn:2002371",
        "tgn:7007923",
        "tgn:7029392"
    ],
    "tgn:id":2284398,
    "tgn:name":"Derby Spring",
    "tgn:placetype":[
        "aat:300008697"
    ]
},
  "bbox": [],
  "geometry": {"coordinates":[-108.6333,42.5833],"type":"Point"}
}