{
  "id": 7228906,
  "type": "Feature",
  "properties": {
    "tgn:hierarchy":[
        "tgn:7228906",
        "tgn:7002751",
        "tgn:7001399",
        "tgn:1000003",
        "tgn:1000074",
        "tgn:7029392"
    ],
    "tgn:id":7228906,
    "tgn:name":"Galats\u00f3na",
    "tgn:placetype":[
        "aat:300008347"
    ]
},
  "bbox": [],
  "geometry": {"coordinates":[23.233333,38.966667],"type":"Point"}
}