{
  "id": 2618446,
  "type": "Feature",
  "properties": {
    "tgn:hierarchy":[
        "tgn:2618446",
        "tgn:1000001",
        "tgn:7012149",
        "tgn:7007827",
        "tgn:7029392"
    ],
    "tgn:id":2618446,
    "tgn:name":"Right Fork Cedar Creek",
    "tgn:placetype":[
        "aat:300008706"
    ]
},
  "bbox": [],
  "geometry": {"coordinates":[-111.05,39.4667],"type":"Point"}
}