{
  "id": 2557640,
  "type": "Feature",
  "properties": {
    "tgn:hierarchy":[
        "tgn:2557640",
        "tgn:1000001",
        "tgn:7006451",
        "tgn:2000093",
        "tgn:7012149",
        "tgn:7029392"
    ],
    "tgn:id":2557640,
    "tgn:name":"Old R Spring",
    "tgn:placetype":[
        "aat:300008697"
    ]
},
  "bbox": [],
  "geometry": {"coordinates":[-110.25,33.8167],"type":"Point"}
}