{
  "id": 2772086,
  "type": "Feature",
  "properties": {
    "tgn:hierarchy":[
        "tgn:2772086",
        "tgn:1000001",
        "tgn:7012149",
        "tgn:7007522",
        "tgn:7029392"
    ],
    "tgn:id":2772086,
    "tgn:name":"Will M Whittington Auxiliary Channel",
    "tgn:placetype":[
        "aat:300006075"
    ]
},
  "bbox": [],
  "geometry": {"coordinates":[-90.5333,32.9167],"type":"Point"}
}