{
  "id": 2326235,
  "type": "Feature",
  "properties": {
    "tgn:hierarchy":[
        "tgn:2326235",
        "tgn:1000001",
        "tgn:2001435",
        "tgn:7012149",
        "tgn:7007566",
        "tgn:7029392"
    ],
    "tgn:id":2326235,
    "tgn:name":"Fillmore Spring",
    "tgn:placetype":[
        "aat:300008697"
    ]
},
  "bbox": [],
  "geometry": {"coordinates":[-106.5667,32.3333],"type":"Point"}
}