{
  "id": 7441363,
  "type": "Feature",
  "properties": {
    "tgn:hierarchy":[
        "tgn:7441363",
        "tgn:1000001",
        "tgn:7005598",
        "tgn:7005560",
        "tgn:7029392"
    ],
    "tgn:id":7441363,
    "tgn:name":"Santa In\u00e9s Tecuexcomac",
    "tgn:placetype":[
        "aat:300008347"
    ]
},
  "bbox": [],
  "geometry": {"coordinates":[-98.333333,19.283333],"type":"Point"}
}