{
  "id": 2523399,
  "type": "Feature",
  "properties": {
    "tgn:hierarchy":[
        "tgn:2523399",
        "tgn:1000001",
        "tgn:7012149",
        "tgn:2000657",
        "tgn:7007253",
        "tgn:7029392"
    ],
    "tgn:id":2523399,
    "tgn:name":"Moose Creek",
    "tgn:placetype":[
        "aat:300008706"
    ]
},
  "bbox": [],
  "geometry": {"coordinates":[-95.95,42.25],"type":"Point"}
}