{
  "id": 7340416,
  "type": "Feature",
  "properties": {
    "tgn:hierarchy":[
        "tgn:7340416",
        "tgn:7002826",
        "tgn:7001158",
        "tgn:1000003",
        "tgn:1000095",
        "tgn:7029392"
    ],
    "tgn:id":7340416,
    "tgn:name":"Cuevas",
    "tgn:placetype":[
        "aat:300008347"
    ]
},
  "bbox": [],
  "geometry": {"coordinates":[-6.033333,42.416667],"type":"Point"}
}