{
  "id": 2659784,
  "type": "Feature",
  "properties": {
    "tgn:hierarchy":[
        "tgn:2659784",
        "tgn:1000001",
        "tgn:7012149",
        "tgn:2000180",
        "tgn:7007157",
        "tgn:7029392"
    ],
    "tgn:id":2659784,
    "tgn:name":"Ship Mountain Lake",
    "tgn:placetype":[
        "aat:300008680"
    ]
},
  "bbox": [],
  "geometry": {"coordinates":[-123.7833,41.7333],"type":"Point"}
}