{
  "id": 2619170,
  "type": "Feature",
  "properties": {
    "tgn:hierarchy":[
        "tgn:2619170",
        "tgn:1000001",
        "tgn:7012149",
        "tgn:2002381",
        "tgn:7007923",
        "tgn:7029392"
    ],
    "tgn:id":2619170,
    "tgn:name":"Riley Draw",
    "tgn:placetype":[
        "aat:300008761"
    ]
},
  "bbox": [],
  "geometry": {"coordinates":[-106.6333,44.9333],"type":"Point"}
}