<<<<<<< HEAD
{
  "id": 2337520,
  "type": "Feature",
  "properties": {
    "tgn:hierarchy":[
        "tgn:2337520",
        "tgn:1000001",
        "tgn:7012149",
        "tgn:2002017",
        "tgn:7007826",
        "tgn:7029392"
    ],
    "tgn:id":2337520,
    "tgn:name":"Fowler Tank",
    "tgn:placetype":[
        "aat:300006191"
    ]
},
  "bbox": [],
  "geometry": {"coordinates":[-100.6833,33.2],"type":"Point"}
}
=======
{"geometry":{"type":"Point","coordinates":[-100.683300,33.200000]},"type":"Feature","properties":{"hierarchy":["tgn:2337520","tgn:1000001","tgn:7012149","tgn:2002017","tgn:7007826","tgn:7029392"],"placetype":["aat:300006191"],"id":2337520,"name:xx":"Fowler Tank"}}
>>>>>>> 03f74aca74312dbeaf24d7e61306dd6a786dc3d0
