{
  "id": 1052190,
  "type": "Feature",
  "properties": {
    "tgn:hierarchy":[
        "tgn:1052190",
        "tgn:1000004",
        "tgn:1003421",
        "tgn:7018214",
        "tgn:7002435",
        "tgn:7029392"
    ],
    "tgn:id":1052190,
    "tgn:name":"Andreyevo",
    "tgn:placetype":[
        "aat:300008347"
    ]
},
  "bbox": [],
  "geometry": {"coordinates":[41.15,55.9167],"type":"Point"}
}