{
  "id": 2518118,
  "type": "Feature",
  "properties": {
    "tgn:hierarchy":[
        "tgn:2518118",
        "tgn:1000001",
        "tgn:2000299",
        "tgn:7012149",
        "tgn:7007248",
        "tgn:7029392"
    ],
    "tgn:id":2518118,
    "tgn:name":"Mission Hills",
    "tgn:placetype":[
        "aat:300008347"
    ]
},
  "bbox": [],
  "geometry": {"coordinates":[-84.8333,34.1667],"type":"Point"}
}