{
  "id": 2558726,
  "type": "Feature",
  "properties": {
    "tgn:hierarchy":[
        "tgn:2558726",
        "tgn:1000001",
        "tgn:7012149",
        "tgn:7007157",
        "tgn:1002684",
        "tgn:7029392"
    ],
    "tgn:id":2558726,
    "tgn:name":"Olmstead, Mount",
    "tgn:placetype":[
        "aat:300008798"
    ]
},
  "bbox": [],
  "geometry": {"coordinates":[-121.6833,36.2333],"type":"Point"}
}