{
  "id": 7511056,
  "type": "Feature",
  "properties": {
    "tgn:hierarchy":[
        "tgn:7511056",
        "tgn:1009227",
        "tgn:1000226",
        "tgn:7018437",
        "tgn:1000006",
        "tgn:7029392"
    ],
    "tgn:id":7511056,
    "tgn:name:en":"Taumata",
    "tgn:placetype":[
        "aat:300008347"
    ]
},
  "bbox": [],
  "geometry": {"coordinates":[169.466667,-46.15],"type":"Point"}
}