{
  "id": 7258294,
  "type": "Feature",
  "properties": {
    "tgn:hierarchy":[
        "tgn:7258294",
        "tgn:7003456",
        "tgn:1000003",
        "tgn:1000063",
        "tgn:7018236",
        "tgn:7029392"
    ],
    "tgn:id":7258294,
    "tgn:name":"Zavelbos",
    "tgn:placetype":[
        "aat:300008863"
    ]
},
  "bbox": [],
  "geometry": {"coordinates":[4.866667,51.183333],"type":"Point"}
}