{
  "id": 7564861,
  "type": "Feature",
  "properties": {
    "tgn:hierarchy":[
        "tgn:7564861",
        "tgn:1000004",
        "tgn:7000198",
        "tgn:7016722",
        "tgn:7029392"
    ],
    "tgn:id":7564861,
    "tgn:name:en":"Kakr\u0101i",
    "tgn:placetype":[
        "aat:300008347"
    ]
},
  "bbox": [],
  "geometry": {"coordinates":[79.637549,26.889932],"type":"Point"}
}