{
  "id": 7193641,
  "type": "Feature",
  "properties": {
    "tgn:hierarchy":[
        "tgn:7193641",
        "tgn:1000003",
        "tgn:7003676",
        "tgn:7000084",
        "tgn:7029392"
    ],
    "tgn:id":7193641,
    "tgn:name":"Feldkamp",
    "tgn:placetype":[
        "aat:300008347"
    ]
},
  "bbox": [],
  "geometry": {"coordinates":[8.266667,52.366667],"type":"Point"}
}