{
  "id": 7242826,
  "type": "Feature",
  "properties": {
    "tgn:hierarchy":[
        "tgn:7242826",
        "tgn:7003457",
        "tgn:1000003",
        "tgn:1000063",
        "tgn:7018236",
        "tgn:7029392"
    ],
    "tgn:id":7242826,
    "tgn:name":"Lovendegem",
    "tgn:placetype":[
        "aat:300008347"
    ]
},
  "bbox": [],
  "geometry": {"coordinates":[3.612975,51.101684],"type":"Point"}
}