{
  "id": 7382817,
  "type": "Feature",
  "properties": {
    "tgn:hierarchy":[
        "tgn:7382817",
        "tgn:1001853",
        "tgn:1000001",
        "tgn:7005560",
        "tgn:7029392"
    ],
    "tgn:id":7382817,
    "tgn:name":"Palos Blancos, Ca\u00f1\u00f3n de",
    "tgn:placetype":[
        "aat:300008763"
    ]
},
  "bbox": [],
  "geometry": {"coordinates":[-102.266667,27.616667],"type":"Point"}
}