{
  "id": 2423357,
  "type": "Feature",
  "properties": {
    "tgn:hierarchy":[
        "tgn:2423357",
        "tgn:1000001",
        "tgn:7012149",
        "tgn:2000784",
        "tgn:7007255",
        "tgn:7029392"
    ],
    "tgn:id":2423357,
    "tgn:name":"John Belt Mines",
    "tgn:placetype":[
        "aat:300000390"
    ]
},
  "bbox": [],
  "geometry": {"coordinates":[-88.25,37.3167],"type":"Point"}
}