<<<<<<< HEAD
{
  "id": 2256170,
  "type": "Feature",
  "properties": {
    "tgn:hierarchy":[
        "tgn:2256170",
        "tgn:1000001",
        "tgn:7012149",
        "tgn:2001290",
        "tgn:7007524",
        "tgn:7029392"
    ],
    "tgn:id":2256170,
    "tgn:name":"Copper Rock Mine",
    "tgn:placetype":[
        "aat:300000390"
    ]
},
  "bbox": [],
  "geometry": {"coordinates":[-115.35,47.4333],"type":"Point"}
}
=======
{"geometry":{"type":"Point","coordinates":[-115.350000,47.433300]},"type":"Feature","properties":{"hierarchy":["tgn:2256170","tgn:1000001","tgn:7012149","tgn:2001290","tgn:7007524","tgn:7029392"],"placetype":["aat:300000390"],"id":2256170,"name:xx":"Copper Rock Mine"}}
>>>>>>> 03f74aca74312dbeaf24d7e61306dd6a786dc3d0
