<<<<<<< HEAD
{
  "id": 2157975,
  "type": "Feature",
  "properties": {
    "tgn:hierarchy":[
        "tgn:2157975",
        "tgn:1000001",
        "tgn:7012149",
        "tgn:1002593",
        "tgn:7007568",
        "tgn:7029392"
    ],
    "tgn:id":2157975,
    "tgn:name":"Beaver Meadow Creek",
    "tgn:placetype":[
        "aat:300008706"
    ]
},
  "bbox": [],
  "geometry": {"coordinates":[-75.2,43.7833],"type":"Point"}
}
=======
{"geometry":{"type":"Point","coordinates":[-75.200000,43.783300]},"type":"Feature","properties":{"hierarchy":["tgn:2157975","tgn:1000001","tgn:7012149","tgn:1002593","tgn:7007568","tgn:7029392"],"placetype":["aat:300008706"],"id":2157975,"name:xx":"Beaver Meadow Creek"}}
>>>>>>> 03f74aca74312dbeaf24d7e61306dd6a786dc3d0
