{
  "id": 1019155,
  "type": "Feature",
  "properties": {
    "tgn:hierarchy":[
        "tgn:1019155",
        "tgn:1001182",
        "tgn:7006477",
        "tgn:1000002",
        "tgn:7029392"
    ],
    "tgn:id":1019155,
    "tgn:name":"Ancasti",
    "tgn:placetype":[
        "aat:300008347"
    ]
},
  "bbox": [],
  "geometry": {"coordinates":[-65.5333,-28.7667],"type":"Point"}
}