{
  "id": 2293941,
  "type": "Feature",
  "properties": {
    "tgn:hierarchy":[
        "tgn:2293941",
        "tgn:1000001",
        "tgn:7012149",
        "tgn:1002555",
        "tgn:7007523",
        "tgn:7029392"
    ],
    "tgn:id":2293941,
    "tgn:name":"Douglas Lake",
    "tgn:placetype":[
        "aat:300006191"
    ]
},
  "bbox": [],
  "geometry": {"coordinates":[-92.15,40.0167],"type":"Point"}
}