<<<<<<< HEAD
{
  "id": 2251923,
  "type": "Feature",
  "properties": {
    "tgn:hierarchy":[
        "tgn:2251923",
        "tgn:1000001",
        "tgn:7012149",
        "tgn:2000283",
        "tgn:7007240",
        "tgn:7029392"
    ],
    "tgn:id":2251923,
    "tgn:name":"Conch Island",
    "tgn:placetype":[
        "aat:300008791"
    ]
},
  "bbox": [],
  "geometry": {"coordinates":[-81.2667,29.8833],"type":"Point"}
}
=======
{"geometry":{"type":"Point","coordinates":[-81.266700,29.883300]},"type":"Feature","properties":{"hierarchy":["tgn:2251923","tgn:1000001","tgn:7012149","tgn:2000283","tgn:7007240","tgn:7029392"],"placetype":["aat:300008791"],"id":2251923,"name:xx":"Conch Island"}}
>>>>>>> 03f74aca74312dbeaf24d7e61306dd6a786dc3d0
