{
  "id": 1022241,
  "type": "Feature",
  "properties": {
    "tgn:hierarchy":[
        "tgn:1022241",
        "tgn:7012827",
        "tgn:7002454",
        "tgn:1000047",
        "tgn:1000002",
        "tgn:7029392"
    ],
    "tgn:id":1022241,
    "tgn:name":"Nova Roma",
    "tgn:placetype":[
        "aat:300008347"
    ]
},
  "bbox": [],
  "geometry": {"coordinates":[-46.9167,-13.65],"type":"Point"}
}