{
  "id": 2455905,
  "type": "Feature",
  "properties": {
    "tgn:hierarchy":[
        "tgn:2455905",
        "tgn:1000001",
        "tgn:7012149",
        "tgn:7007254",
        "tgn:7029392"
    ],
    "tgn:id":2455905,
    "tgn:name":"Little Gus Creek",
    "tgn:placetype":[
        "aat:300008706"
    ]
},
  "bbox": [],
  "geometry": {"coordinates":[-94.1333,38.1167],"type":"Point"}
}