{
  "id": 2448994,
  "type": "Feature",
  "properties": {
    "tgn:hierarchy":[
        "tgn:2448994",
        "tgn:1000001",
        "tgn:7006451",
        "tgn:7012149",
        "tgn:2000097",
        "tgn:7029392"
    ],
    "tgn:id":2448994,
    "tgn:name":"Lime Mountain Spring",
    "tgn:placetype":[
        "aat:300008697"
    ]
},
  "bbox": [],
  "geometry": {"coordinates":[-111.1667,33.5333],"type":"Point"}
}