<<<<<<< HEAD
{
  "id": 2761046,
  "type": "Feature",
  "properties": {
    "tgn:hierarchy":[
        "tgn:2761046",
        "tgn:1000001",
        "tgn:7012149",
        "tgn:2000613",
        "tgn:7007253",
        "tgn:7029392"
    ],
    "tgn:id":2761046,
    "tgn:name":"West Kitty Creek",
    "tgn:placetype":[
        "aat:300008706"
    ]
},
  "bbox": [],
  "geometry": {"coordinates":[-91.1333,42.1333],"type":"Point"}
}
=======
{"geometry":{"type":"Point","coordinates":[-91.133300,42.133300]},"type":"Feature","properties":{"hierarchy":["tgn:2761046","tgn:1000001","tgn:7012149","tgn:2000613","tgn:7007253","tgn:7029392"],"placetype":["aat:300008706"],"id":2761046,"name:xx":"West Kitty Creek"}}
>>>>>>> 03f74aca74312dbeaf24d7e61306dd6a786dc3d0
