{
  "id": 7218005,
  "type": "Feature",
  "properties": {
    "tgn:hierarchy":[
        "tgn:7218005",
        "tgn:7011163",
        "tgn:7002674",
        "tgn:1000003",
        "tgn:1000074",
        "tgn:7029392"
    ],
    "tgn:id":7218005,
    "tgn:name":"Yemist\u00ed",
    "tgn:placetype":[
        "aat:300008347"
    ]
},
  "bbox": [],
  "geometry": {"coordinates":[26.333333,40.966667],"type":"Point"}
}