{
  "id": 2745956,
  "type": "Feature",
  "properties": {
    "tgn:hierarchy":[
        "tgn:2745956",
        "tgn:1000001",
        "tgn:7012149",
        "tgn:2000217",
        "tgn:7007158",
        "tgn:7029392"
    ],
    "tgn:id":2745956,
    "tgn:name":"Vogel Creek",
    "tgn:placetype":[
        "aat:300008706"
    ]
},
  "bbox": [],
  "geometry": {"coordinates":[-107.2667,38.8667],"type":"Point"}
}