<<<<<<< HEAD
{
  "id": 2150178,
  "type": "Feature",
  "properties": {
    "tgn:hierarchy":[
        "tgn:2150178",
        "tgn:1000001",
        "tgn:7012149",
        "tgn:1003035",
        "tgn:7007251",
        "tgn:7029392"
    ],
    "tgn:id":2150178,
    "tgn:name":"Barwell Lake",
    "tgn:placetype":[
        "aat:300006191"
    ]
},
  "bbox": [],
  "geometry": {"coordinates":[-89.1167,40.6167],"type":"Point"}
}
=======
{"geometry":{"type":"Point","coordinates":[-89.116700,40.616700]},"type":"Feature","properties":{"hierarchy":["tgn:2150178","tgn:1000001","tgn:7012149","tgn:1003035","tgn:7007251","tgn:7029392"],"placetype":["aat:300006191"],"id":2150178,"name:xx":"Barwell Lake"}}
>>>>>>> 03f74aca74312dbeaf24d7e61306dd6a786dc3d0
