{
  "id": 2150178,
  "type": "Feature",
  "properties": {
    "tgn:hierarchy":[
        "tgn:2150178",
        "tgn:1000001",
        "tgn:7012149",
        "tgn:1003035",
        "tgn:7007251",
        "tgn:7029392"
    ],
    "tgn:id":2150178,
    "tgn:name":"Barwell Lake",
    "tgn:placetype":[
        "aat:300006191"
    ]
},
  "bbox": [],
  "geometry": {"coordinates":[-89.1167,40.6167],"type":"Point"}
}