{
  "id": 2573306,
  "type": "Feature",
  "properties": {
    "tgn:hierarchy":[
        "tgn:2573306",
        "tgn:1000001",
        "tgn:7012149",
        "tgn:7007248",
        "tgn:7029392"
    ],
    "tgn:id":2573306,
    "tgn:name":"Peavine Creek",
    "tgn:placetype":[
        "aat:300008706"
    ]
},
  "bbox": [],
  "geometry": {"coordinates":[-85.2167,34.7667],"type":"Point"}
}