{
  "id": 2641395,
  "type": "Feature",
  "properties": {
    "tgn:hierarchy":[
        "tgn:2641395",
        "tgn:1000001",
        "tgn:7012149",
        "tgn:7007707",
        "tgn:7029392"
    ],
    "tgn:id":2641395,
    "tgn:name":"Sand Creek",
    "tgn:placetype":[
        "aat:300008706"
    ]
},
  "bbox": [],
  "geometry": {"coordinates":[-96.2167,36.1833],"type":"Point"}
}