<<<<<<< HEAD
{
  "id": 2764981,
  "type": "Feature",
  "properties": {
    "tgn:hierarchy":[
        "tgn:2764981",
        "tgn:1000001",
        "tgn:2000689",
        "tgn:7012149",
        "tgn:7007254",
        "tgn:7029392"
    ],
    "tgn:id":2764981,
    "tgn:name":"Whisky Creek",
    "tgn:placetype":[
        "aat:300008706"
    ]
},
  "bbox": [],
  "geometry": {"coordinates":[-95.3833,38.5333],"type":"Point"}
}
=======
{"geometry":{"type":"Point","coordinates":[-95.383300,38.533300]},"type":"Feature","properties":{"hierarchy":["tgn:2764981","tgn:1000001","tgn:2000689","tgn:7012149","tgn:7007254","tgn:7029392"],"placetype":["aat:300008706"],"id":2764981,"name:xx":"Whisky Creek"}}
>>>>>>> 03f74aca74312dbeaf24d7e61306dd6a786dc3d0
