{
  "id": 1017717,
  "type": "Feature",
  "properties": {
    "tgn:hierarchy":[
        "tgn:1017717",
        "tgn:1000001",
        "tgn:7005594",
        "tgn:7005560",
        "tgn:7029392"
    ],
    "tgn:id":1017717,
    "tgn:name":"La Paz",
    "tgn:placetype":[
        "aat:300008347"
    ]
},
  "bbox": [],
  "geometry": {"coordinates":[-100.716667,23.683333],"type":"Point"}
}