<<<<<<< HEAD
{
  "id": 2408802,
  "type": "Feature",
  "properties": {
    "tgn:hierarchy":[
        "tgn:2408802",
        "tgn:1000001",
        "tgn:7012149",
        "tgn:2002066",
        "tgn:7007826",
        "tgn:7029392"
    ],
    "tgn:id":2408802,
    "tgn:name":"Hyden Branch",
    "tgn:placetype":[
        "aat:300008699"
    ]
},
  "bbox": [],
  "geometry": {"coordinates":[-93.8333,31.1667],"type":"Point"}
}
=======
{"geometry":{"type":"Point","coordinates":[-93.833300,31.166700]},"type":"Feature","properties":{"hierarchy":["tgn:2408802","tgn:1000001","tgn:7012149","tgn:2002066","tgn:7007826","tgn:7029392"],"placetype":["aat:300008699"],"id":2408802,"name:xx":"Hyden Branch"}}
>>>>>>> 03f74aca74312dbeaf24d7e61306dd6a786dc3d0
