<<<<<<< HEAD
{
  "id": 7489580,
  "type": "Feature",
  "properties": {
    "tgn:hierarchy":[
        "tgn:7489580",
        "tgn:1000004",
        "tgn:7004300",
        "tgn:1000141",
        "tgn:7029392"
    ],
    "tgn:id":7489580,
    "tgn:name":"Guoye",
    "tgn:placetype":[
        "aat:300008347"
    ]
},
  "bbox": [],
  "geometry": {"coordinates":[119.678885,23.578365],"type":"Point"}
}
=======
{"geometry":{"type":"Point","coordinates":[119.678885,23.578365]},"type":"Feature","properties":{"hierarchy":["tgn:7489580","tgn:1000004","tgn:7004300","tgn:1000141","tgn:7029392"],"placetype":["aat:300008347"],"id":7489580,"name:xx":"Guoye"}}
>>>>>>> 03f74aca74312dbeaf24d7e61306dd6a786dc3d0
