{
  "id": 7282157,
  "type": "Feature",
  "properties": {
    "tgn:hierarchy":[
        "tgn:7282157",
        "tgn:1001702",
        "tgn:1000049",
        "tgn:1000002",
        "tgn:7029392"
    ],
    "tgn:id":7282157,
    "tgn:name":"Sat\u00e9lite, Punta",
    "tgn:placetype":[
        "aat:300386846"
    ]
},
  "bbox": [],
  "geometry": {"coordinates":[-69.666667,-52.533333],"type":"Point"}
}