<<<<<<< HEAD
{
  "id": 2256486,
  "type": "Feature",
  "properties": {
    "tgn:hierarchy":[
        "tgn:2256486",
        "tgn:1000001",
        "tgn:7012149",
        "tgn:1002800",
        "tgn:7007710",
        "tgn:7029392"
    ],
    "tgn:id":2256486,
    "tgn:name":"Corbett",
    "tgn:placetype":[
        "aat:300008347"
    ]
},
  "bbox": [],
  "geometry": {"coordinates":[-77.7667,41.6667],"type":"Point"}
}
=======
{"geometry":{"type":"Point","coordinates":[-77.766700,41.666700]},"type":"Feature","properties":{"hierarchy":["tgn:2256486","tgn:1000001","tgn:7012149","tgn:1002800","tgn:7007710","tgn:7029392"],"placetype":["aat:300008347"],"id":2256486,"name:xx":"Corbett"}}
>>>>>>> 03f74aca74312dbeaf24d7e61306dd6a786dc3d0
