{
  "id": 2567571,
  "type": "Feature",
  "properties": {
    "tgn:hierarchy":[
        "tgn:2567571",
        "tgn:1000001",
        "tgn:7012149",
        "tgn:2000225",
        "tgn:7007158",
        "tgn:7029392"
    ],
    "tgn:id":2567571,
    "tgn:name":"Papoose Lake",
    "tgn:placetype":[
        "aat:300008680"
    ]
},
  "bbox": [],
  "geometry": {"coordinates":[-107.7833,37.5833],"type":"Point"}
}