{
  "id": 1067562,
  "type": "Feature",
  "properties": {
    "tgn:hierarchy":[
        "tgn:1067562",
        "tgn:1000004",
        "tgn:7018118",
        "tgn:1000111",
        "tgn:7029392"
    ],
    "tgn:id":1067562,
    "tgn:name":"Dashutang",
    "tgn:placetype":[
        "aat:300008347"
    ]
},
  "bbox": [],
  "geometry": {"coordinates":[103.8833,22.8667],"type":"Point"}
}