{
  "id": 7493928,
  "type": "Feature",
  "properties": {
    "tgn:hierarchy":[
        "tgn:7493928",
        "tgn:1000004",
        "tgn:7001013",
        "tgn:1000141",
        "tgn:7029392"
    ],
    "tgn:id":7493928,
    "tgn:name":"Fuxing Diyihao Qiao",
    "tgn:placetype":[
        "aat:300007836"
    ]
},
  "bbox": [],
  "geometry": {"coordinates":[121.270116,24.994978],"type":"Point"}
}