{
  "id": 7239863,
  "type": "Feature",
  "properties": {
    "tgn:hierarchy":[
        "tgn:7239863",
        "tgn:7003457",
        "tgn:1000003",
        "tgn:1000063",
        "tgn:7018236",
        "tgn:7029392"
    ],
    "tgn:id":7239863,
    "tgn:name":"Heiplas",
    "tgn:placetype":[
        "aat:300008347"
    ]
},
  "bbox": [],
  "geometry": {"coordinates":[3.980445,50.980341],"type":"Point"}
}