<<<<<<< HEAD
{
  "id": 2334466,
  "type": "Feature",
  "properties": {
    "tgn:hierarchy":[
        "tgn:2334466",
        "tgn:1000001",
        "tgn:1002260",
        "tgn:7012149",
        "tgn:7007920",
        "tgn:7029392"
    ],
    "tgn:id":2334466,
    "tgn:name":"Forest Mountain",
    "tgn:placetype":[
        "aat:300008798"
    ]
},
  "bbox": [],
  "geometry": {"coordinates":[-120.2667,47.8333],"type":"Point"}
}
=======
{"geometry":{"type":"Point","coordinates":[-120.266700,47.833300]},"type":"Feature","properties":{"hierarchy":["tgn:2334466","tgn:1000001","tgn:1002260","tgn:7012149","tgn:7007920","tgn:7029392"],"placetype":["aat:300008798"],"id":2334466,"name:xx":"Forest Mountain"}}
>>>>>>> 03f74aca74312dbeaf24d7e61306dd6a786dc3d0
