{
  "id": 7090637,
  "type": "Feature",
  "properties": {
    "tgn:hierarchy":[
        "tgn:7090637",
        "tgn:1000003",
        "tgn:7003688",
        "tgn:7000084",
        "tgn:7029392"
    ],
    "tgn:id":7090637,
    "tgn:name":"Vossberg",
    "tgn:placetype":[
        "aat:300000206"
    ]
},
  "bbox": [],
  "geometry": {"coordinates":[10.783333,54.066667],"type":"Point"}
}