{
  "id": 2158663,
  "type": "Feature",
  "properties": {
    "tgn:hierarchy":[
        "tgn:2158663",
        "tgn:1000001",
        "tgn:2002368",
        "tgn:7012149",
        "tgn:7007923",
        "tgn:7029392"
    ],
    "tgn:id":2158663,
    "tgn:name":"Beavers Reservoir",
    "tgn:placetype":[
        "aat:300006191"
    ]
},
  "bbox": [],
  "geometry": {"coordinates":[-107.4667,41.1667],"type":"Point"}
}