<<<<<<< HEAD
{
  "id": 2158663,
  "type": "Feature",
  "properties": {
    "tgn:hierarchy":[
        "tgn:2158663",
        "tgn:1000001",
        "tgn:2002368",
        "tgn:7012149",
        "tgn:7007923",
        "tgn:7029392"
    ],
    "tgn:id":2158663,
    "tgn:name":"Beavers Reservoir",
    "tgn:placetype":[
        "aat:300006191"
    ]
},
  "bbox": [],
  "geometry": {"coordinates":[-107.4667,41.1667],"type":"Point"}
}
=======
{"geometry":{"type":"Point","coordinates":[-107.466700,41.166700]},"type":"Feature","properties":{"hierarchy":["tgn:2158663","tgn:1000001","tgn:2002368","tgn:7012149","tgn:7007923","tgn:7029392"],"placetype":["aat:300006191"],"id":2158663,"name:xx":"Beavers Reservoir"}}
>>>>>>> 03f74aca74312dbeaf24d7e61306dd6a786dc3d0
