{
  "id": 7559902,
  "type": "Feature",
  "properties": {
    "tgn:hierarchy":[
        "tgn:7559902",
        "tgn:1000004",
        "tgn:7000198",
        "tgn:7016722",
        "tgn:7029392"
    ],
    "tgn:id":7559902,
    "tgn:name:en":"Nagla Param",
    "tgn:placetype":[
        "aat:300008347"
    ]
},
  "bbox": [],
  "geometry": {"coordinates":[79.297961,27.239988],"type":"Point"}
}