{
  "id": 7230533,
  "type": "Feature",
  "properties": {
    "tgn:hierarchy":[
        "tgn:7230533",
        "tgn:7002725",
        "tgn:7002715",
        "tgn:1000003",
        "tgn:1000074",
        "tgn:7029392"
    ],
    "tgn:id":7230533,
    "tgn:name":"Kh\u00edmarros",
    "tgn:placetype":[
        "aat:300008347"
    ]
},
  "bbox": [],
  "geometry": {"coordinates":[23.25,41.116667],"type":"Point"}
}