{
  "id": 7328758,
  "type": "Feature",
  "properties": {
    "tgn:hierarchy":[
        "tgn:7328758",
        "tgn:7010420",
        "tgn:1000003",
        "tgn:7002795",
        "tgn:1000095",
        "tgn:7029392"
    ],
    "tgn:id":7328758,
    "tgn:name":"Quemadas, Arroyo de las",
    "tgn:placetype":[
        "aat:300266554",
        "aat:300008699"
    ]
},
  "bbox": [],
  "geometry": {"coordinates":[-3.566667,40.566667],"type":"Point"}
}