{
  "id": 7558791,
  "type": "Feature",
  "properties": {
    "tgn:hierarchy":[
        "tgn:7558791",
        "tgn:1000004",
        "tgn:7000198",
        "tgn:7016694",
        "tgn:7029392"
    ],
    "tgn:id":7558791,
    "tgn:name:en":"Purushottampur",
    "tgn:placetype":[
        "aat:300008347"
    ]
},
  "bbox": [],
  "geometry": {"coordinates":[84.883333,19.533333],"type":"Point"}
}