{
  "id": 1032717,
  "type": "Feature",
  "properties": {
    "tgn:hierarchy":[
        "tgn:1032717",
        "tgn:1000003",
        "tgn:7002883",
        "tgn:1000070",
        "tgn:7029392"
    ],
    "tgn:id":1032717,
    "tgn:name":"Colombes",
    "tgn:placetype":[
        "aat:300008347",
        "aat:300387330",
        "aat:300000874",
        "aat:300008375",
        "aat:300387302",
        "aat:300387293"
    ]
},
  "bbox": [],
  "geometry": {"coordinates":[2.2333,48.9167],"type":"Point"}
}