{
  "id": 7494224,
  "type": "Feature",
  "properties": {
    "tgn:hierarchy":[
        "tgn:7494224",
        "tgn:1000004",
        "tgn:7491221",
        "tgn:1000141",
        "tgn:7029392"
    ],
    "tgn:id":7494224,
    "tgn:name":"Xingang Xikou",
    "tgn:placetype":[
        "aat:300387057"
    ]
},
  "bbox": [],
  "geometry": {"coordinates":[121.387563,23.10399],"type":"Point"}
}