{
  "id": 2081756,
  "type": "Feature",
  "properties": {
    "tgn:hierarchy":[
        "tgn:2081756",
        "tgn:1000001",
        "tgn:7012149",
        "tgn:1002357",
        "tgn:7007706",
        "tgn:7029392"
    ],
    "tgn:id":2081756,
    "tgn:name":"Sand Hill",
    "tgn:placetype":[
        "aat:300008347",
        "aat:300387210"
    ]
},
  "bbox": [],
  "geometry": {"coordinates":[-82.75,41.35],"type":"Point"}
}