{
  "id": 2098709,
  "type": "Feature",
  "properties": {
    "tgn:hierarchy":[
        "tgn:2098709",
        "tgn:1000001",
        "tgn:7012149",
        "tgn:2001844",
        "tgn:7007825",
        "tgn:7029392"
    ],
    "tgn:id":2098709,
    "tgn:name":"Cross Roads",
    "tgn:placetype":[
        "aat:300008347",
        "aat:300387210"
    ]
},
  "bbox": [],
  "geometry": {"coordinates":[-85.9333,35.8333],"type":"Point"}
}