{
  "id": 2328199,
  "type": "Feature",
  "properties": {
    "tgn:hierarchy":[
        "tgn:2328199",
        "tgn:1000001",
        "tgn:7012149",
        "tgn:7014510",
        "tgn:7007920",
        "tgn:7029392"
    ],
    "tgn:id":2328199,
    "tgn:name":"Fish Town",
    "tgn:placetype":[
        "aat:300008347"
    ]
},
  "bbox": [],
  "geometry": {"coordinates":[-122.4667,48.35],"type":"Point"}
}