<<<<<<< HEAD
{
  "id": 2403485,
  "type": "Feature",
  "properties": {
    "tgn:hierarchy":[
        "tgn:2403485",
        "tgn:1000001",
        "tgn:7012149",
        "tgn:1003038",
        "tgn:7007517",
        "tgn:7029392"
    ],
    "tgn:id":2403485,
    "tgn:name":"Hovey Pond",
    "tgn:placetype":[
        "aat:300006191"
    ]
},
  "bbox": [],
  "geometry": {"coordinates":[-71.7,42.2167],"type":"Point"}
}
=======
{"geometry":{"type":"Point","coordinates":[-71.700000,42.216700]},"type":"Feature","properties":{"hierarchy":["tgn:2403485","tgn:1000001","tgn:7012149","tgn:1003038","tgn:7007517","tgn:7029392"],"placetype":["aat:300006191"],"id":2403485,"name:xx":"Hovey Pond"}}
>>>>>>> 03f74aca74312dbeaf24d7e61306dd6a786dc3d0
