{
  "id": 1093844,
  "type": "Feature",
  "properties": {
    "tgn:hierarchy":[
        "tgn:1093844",
        "tgn:7001242",
        "tgn:7017577",
        "tgn:1000193",
        "tgn:7029392"
    ],
    "tgn:id":1093844,
    "tgn:name":"Battlemound",
    "tgn:placetype":[
        "aat:300008347"
    ]
},
  "bbox": [],
  "geometry": {"coordinates":[23.7667,-26.95],"type":"Point"}
}