{
  "id": 2657935,
  "type": "Feature",
  "properties": {
    "tgn:hierarchy":[
        "tgn:2657935",
        "tgn:7013313",
        "tgn:1000001",
        "tgn:7012149",
        "tgn:7007826",
        "tgn:7029392"
    ],
    "tgn:id":2657935,
    "tgn:name":"Shell Ridge",
    "tgn:placetype":[
        "aat:300008347"
    ]
},
  "bbox": [],
  "geometry": {"coordinates":[-97.05,27.9833],"type":"Point"}
}