{
  "id": 2182527,
  "type": "Feature",
  "properties": {
    "tgn:hierarchy":[
        "tgn:2182527",
        "tgn:1000001",
        "tgn:7013387",
        "tgn:7012149",
        "tgn:7007710",
        "tgn:7029392"
    ],
    "tgn:id":2182527,
    "tgn:name":"Blue Rocks",
    "tgn:placetype":[
        "aat:300008798"
    ]
},
  "bbox": [],
  "geometry": {"coordinates":[-75.9167,40.5833],"type":"Point"}
}