<<<<<<< HEAD
{
  "id": 2153975,
  "type": "Feature",
  "properties": {
    "tgn:hierarchy":[
        "tgn:2153975",
        "tgn:7006450",
        "tgn:1000001",
        "tgn:7012149",
        "tgn:2000079",
        "tgn:7029392"
    ],
    "tgn:id":2153975,
    "tgn:name":"Bear Creek",
    "tgn:placetype":[
        "aat:300008706"
    ]
},
  "bbox": [],
  "geometry": {"coordinates":[-165.35,64.55],"type":"Point"}
}
=======
{"geometry":{"type":"Point","coordinates":[-165.350000,64.550000]},"type":"Feature","properties":{"hierarchy":["tgn:2153975","tgn:7006450","tgn:1000001","tgn:7012149","tgn:2000079","tgn:7029392"],"placetype":["aat:300008706"],"id":2153975,"name:xx":"Bear Creek"}}
>>>>>>> 03f74aca74312dbeaf24d7e61306dd6a786dc3d0
