{
  "id": 2153975,
  "type": "Feature",
  "properties": {
    "tgn:hierarchy":[
        "tgn:2153975",
        "tgn:7006450",
        "tgn:1000001",
        "tgn:7012149",
        "tgn:2000079",
        "tgn:7029392"
    ],
    "tgn:id":2153975,
    "tgn:name":"Bear Creek",
    "tgn:placetype":[
        "aat:300008706"
    ]
},
  "bbox": [],
  "geometry": {"coordinates":[-165.35,64.55],"type":"Point"}
}