{
  "id": 7586762,
  "type": "Feature",
  "properties": {
    "tgn:hierarchy":[
        "tgn:7586762",
        "tgn:1000004",
        "tgn:7000198",
        "tgn:7000799",
        "tgn:7029392"
    ],
    "tgn:id":7586762,
    "tgn:name:en":"Muq\u0101m Sharifd\u0101r",
    "tgn:placetype":[
        "aat:300008347"
    ]
},
  "bbox": [],
  "geometry": {"coordinates":[74.44271,34.476974],"type":"Point"}
}