{
  "id": 7473626,
  "type": "Feature",
  "properties": {
    "tgn:hierarchy":[
        "tgn:7473626",
        "tgn:7469009",
        "tgn:1000004",
        "tgn:1000141",
        "tgn:7029392"
    ],
    "tgn:id":7473626,
    "tgn:name":"Dongshawei",
    "tgn:placetype":[
        "aat:300008347"
    ]
},
  "bbox": [],
  "geometry": {"coordinates":[118.448056,24.446667],"type":"Point"}
}