<<<<<<< HEAD
{
  "id": 7473626,
  "type": "Feature",
  "properties": {
    "tgn:hierarchy":[
        "tgn:7473626",
        "tgn:7469009",
        "tgn:1000004",
        "tgn:1000141",
        "tgn:7029392"
    ],
    "tgn:id":7473626,
    "tgn:name":"Dongshawei",
    "tgn:placetype":[
        "aat:300008347"
    ]
},
  "bbox": [],
  "geometry": {"coordinates":[118.448056,24.446667],"type":"Point"}
}
=======
{"geometry":{"type":"Point","coordinates":[118.448056,24.446667]},"type":"Feature","properties":{"hierarchy":["tgn:7473626","tgn:7469009","tgn:1000004","tgn:1000141","tgn:7029392"],"placetype":["aat:300008347"],"id":7473626,"name:xx":"Dongshawei"}}
>>>>>>> 03f74aca74312dbeaf24d7e61306dd6a786dc3d0
