{
  "id": 2096880,
  "type": "Feature",
  "properties": {
    "tgn:hierarchy":[
        "tgn:2096880",
        "tgn:1000001",
        "tgn:2001748",
        "tgn:7012149",
        "tgn:7007712",
        "tgn:7029392"
    ],
    "tgn:id":2096880,
    "tgn:name":"Ware Shoals",
    "tgn:placetype":[
        "aat:300008347"
    ]
},
  "bbox": [],
  "geometry": {"coordinates":[-82.2333,34.3833],"type":"Point"}
}