{
  "id": 7334366,
  "type": "Feature",
  "properties": {
    "tgn:hierarchy":[
        "tgn:7334366",
        "tgn:7002760",
        "tgn:1000003",
        "tgn:1000095",
        "tgn:7029392"
    ],
    "tgn:id":7334366,
    "tgn:name":"El Hoyo",
    "tgn:placetype":[
        "aat:300008347"
    ]
},
  "bbox": [],
  "geometry": {"coordinates":[-3.716667,43.433333],"type":"Point"}
}