{
  "id": 1021074,
  "type": "Feature",
  "properties": {
    "tgn:hierarchy":[
        "tgn:1021074",
        "tgn:1001826",
        "tgn:1000047",
        "tgn:7002456",
        "tgn:1000002",
        "tgn:7029392"
    ],
    "tgn:id":1021074,
    "tgn:name":"Caracara\u00ed",
    "tgn:placetype":[
        "aat:300008347"
    ]
},
  "bbox": [],
  "geometry": {"coordinates":[-61.1833,1.7833],"type":"Point"}
}