<<<<<<< HEAD
{
  "id": 2151400,
  "type": "Feature",
  "properties": {
    "tgn:hierarchy":[
        "tgn:2151400",
        "tgn:1000001",
        "tgn:7012149",
        "tgn:2001904",
        "tgn:7007825",
        "tgn:7029392"
    ],
    "tgn:id":2151400,
    "tgn:name":"Bates Spring",
    "tgn:placetype":[
        "aat:300008697"
    ]
},
  "bbox": [],
  "geometry": {"coordinates":[-87.7667,35.7333],"type":"Point"}
}
=======
{"geometry":{"type":"Point","coordinates":[-87.766700,35.733300]},"type":"Feature","properties":{"hierarchy":["tgn:2151400","tgn:1000001","tgn:7012149","tgn:2001904","tgn:7007825","tgn:7029392"],"placetype":["aat:300008697"],"id":2151400,"name:xx":"Bates Spring"}}
>>>>>>> 03f74aca74312dbeaf24d7e61306dd6a786dc3d0
