{
  "id": 7376244,
  "type": "Feature",
  "properties": {
    "tgn:hierarchy":[
        "tgn:7376244",
        "tgn:1000001",
        "tgn:7005591",
        "tgn:7005560",
        "tgn:7029392"
    ],
    "tgn:id":7376244,
    "tgn:name":"Llano Perico",
    "tgn:placetype":[
        "aat:300008347"
    ]
},
  "bbox": [],
  "geometry": {"coordinates":[-97.066667,17.65],"type":"Point"}
}