{
  "id": 7267437,
  "type": "Feature",
  "properties": {
    "tgn:hierarchy":[
        "tgn:7267437",
        "tgn:1000003",
        "tgn:7003624",
        "tgn:7016845",
        "tgn:7029392"
    ],
    "tgn:id":7267437,
    "tgn:name:nl":"Resselbraken",
    "tgn:placetype":[
        "aat:300387200"
    ]
},
  "bbox": [],
  "geometry": {"coordinates":[5.133333,51.466667],"type":"Point"}
}