<<<<<<< HEAD
{
  "id": 7478808,
  "type": "Feature",
  "properties": {
    "tgn:hierarchy":[
        "tgn:7478808",
        "tgn:1000004",
        "tgn:7467799",
        "tgn:1000141",
        "tgn:7029392"
    ],
    "tgn:id":7478808,
    "tgn:name":"Nantian Gong",
    "tgn:placetype":[
        "aat:300007595"
    ]
},
  "bbox": [],
  "geometry": {"coordinates":[120.517484,23.815236],"type":"Point"}
}
=======
{"geometry":{"type":"Point","coordinates":[120.517484,23.815236]},"type":"Feature","properties":{"hierarchy":["tgn:7478808","tgn:1000004","tgn:7467799","tgn:1000141","tgn:7029392"],"placetype":["aat:300007595"],"id":7478808,"name:xx":"Nantian Gong"}}
>>>>>>> 03f74aca74312dbeaf24d7e61306dd6a786dc3d0
