{
  "id": 7478808,
  "type": "Feature",
  "properties": {
    "tgn:hierarchy":[
        "tgn:7478808",
        "tgn:1000004",
        "tgn:7467799",
        "tgn:1000141",
        "tgn:7029392"
    ],
    "tgn:id":7478808,
    "tgn:name":"Nantian Gong",
    "tgn:placetype":[
        "aat:300007595"
    ]
},
  "bbox": [],
  "geometry": {"coordinates":[120.517484,23.815236],"type":"Point"}
}