{
  "id": 1066206,
  "type": "Feature",
  "properties": {
    "tgn:hierarchy":[
        "tgn:1066206",
        "tgn:1000004",
        "tgn:1002109",
        "tgn:1000108",
        "tgn:7029392"
    ],
    "tgn:id":1066206,
    "tgn:name":"Nanantun",
    "tgn:placetype":[
        "aat:300008347"
    ]
},
  "bbox": [],
  "geometry": {"coordinates":[95.6833,24.75],"type":"Point"}
}