<<<<<<< HEAD
{
  "id": 2257932,
  "type": "Feature",
  "properties": {
    "tgn:hierarchy":[
        "tgn:2257932",
        "tgn:1000001",
        "tgn:7012149",
        "tgn:2000224",
        "tgn:7007158",
        "tgn:7029392"
    ],
    "tgn:id":2257932,
    "tgn:name":"Corske Creek",
    "tgn:placetype":[
        "aat:300008706"
    ]
},
  "bbox": [],
  "geometry": {"coordinates":[-106.3833,39.1],"type":"Point"}
}
=======
{"geometry":{"type":"Point","coordinates":[-106.383300,39.100000]},"type":"Feature","properties":{"hierarchy":["tgn:2257932","tgn:1000001","tgn:7012149","tgn:2000224","tgn:7007158","tgn:7029392"],"placetype":["aat:300008706"],"id":2257932,"name:xx":"Corske Creek"}}
>>>>>>> 03f74aca74312dbeaf24d7e61306dd6a786dc3d0
