{
  "id": 7404430,
  "type": "Feature",
  "properties": {
    "tgn:hierarchy":[
        "tgn:7404430",
        "tgn:7005585",
        "tgn:1000001",
        "tgn:7005560",
        "tgn:7029392"
    ],
    "tgn:id":7404430,
    "tgn:name":"El Arroyo",
    "tgn:placetype":[
        "aat:300008347"
    ]
},
  "bbox": [],
  "geometry": {"coordinates":[-100.683333,18.083333],"type":"Point"}
}