{
  "id": 1081563,
  "type": "Feature",
  "properties": {
    "tgn:hierarchy":[
        "tgn:1081563",
        "tgn:1000971",
        "tgn:1000004",
        "tgn:7000894",
        "tgn:1000120",
        "tgn:7029392"
    ],
    "tgn:id":1081563,
    "tgn:name":"Tomiyama",
    "tgn:placetype":[
        "aat:300008347"
    ]
},
  "bbox": [],
  "geometry": {"coordinates":[139.85,35.0833],"type":"Point"}
}