<<<<<<< HEAD
{
  "id": 7483366,
  "type": "Feature",
  "properties": {
    "tgn:hierarchy":[
        "tgn:7483366",
        "tgn:7001004",
        "tgn:1000004",
        "tgn:1000141",
        "tgn:7029392"
    ],
    "tgn:id":7483366,
    "tgn:name":"Xian Qiao",
    "tgn:placetype":[
        "aat:300007836"
    ]
},
  "bbox": [],
  "geometry": {"coordinates":[120.55,23.054167],"type":"Point"}
}
=======
{"geometry":{"type":"Point","coordinates":[120.550000,23.054167]},"type":"Feature","properties":{"hierarchy":["tgn:7483366","tgn:7001004","tgn:1000004","tgn:1000141","tgn:7029392"],"placetype":["aat:300007836"],"id":7483366,"name:xx":"Xian Qiao"}}
>>>>>>> 03f74aca74312dbeaf24d7e61306dd6a786dc3d0
