{
  "id": 2463388,
  "type": "Feature",
  "properties": {
    "tgn:hierarchy":[
        "tgn:2463388",
        "tgn:1000001",
        "tgn:7012149",
        "tgn:1002797",
        "tgn:7007706",
        "tgn:7029392"
    ],
    "tgn:id":2463388,
    "tgn:name":"Lloyd",
    "tgn:placetype":[
        "aat:300008347"
    ]
},
  "bbox": [],
  "geometry": {"coordinates":[-81.0167,41.0667],"type":"Point"}
}