{
  "id": 2718010,
  "type": "Feature",
  "properties": {
    "tgn:hierarchy":[
        "tgn:2718010",
        "tgn:7002659",
        "tgn:1000001",
        "tgn:7012149",
        "tgn:2000038",
        "tgn:7029392"
    ],
    "tgn:id":2718010,
    "tgn:name":"Thompson Branch",
    "tgn:placetype":[
        "aat:300008699"
    ]
},
  "bbox": [],
  "geometry": {"coordinates":[-87.3333,34.8833],"type":"Point"}
}