{
  "id": 7423601,
  "type": "Feature",
  "properties": {
    "tgn:hierarchy":[
        "tgn:7423601",
        "tgn:1000001",
        "tgn:1001960",
        "tgn:7005560",
        "tgn:7029392"
    ],
    "tgn:id":7423601,
    "tgn:name":"Ignacio Ram\u00edrez",
    "tgn:placetype":[
        "aat:300008347"
    ]
},
  "bbox": [],
  "geometry": {"coordinates":[-111.333333,28.733333],"type":"Point"}
}