{
  "id": 7469290,
  "type": "Feature",
  "properties": {
    "tgn:hierarchy":[
        "tgn:7469290",
        "tgn:1000004",
        "tgn:7491221",
        "tgn:1000141",
        "tgn:7029392"
    ],
    "tgn:id":7469290,
    "tgn:name":"Xiaojinlun",
    "tgn:placetype":[
        "aat:300008347"
    ]
},
  "bbox": [],
  "geometry": {"coordinates":[120.933333,22.533333],"type":"Point"}
}