{
  "id": 1069623,
  "type": "Feature",
  "properties": {
    "tgn:hierarchy":[
        "tgn:1069623",
        "tgn:1000004",
        "tgn:7002085",
        "tgn:1000111",
        "tgn:7029392"
    ],
    "tgn:id":1069623,
    "tgn:name":"Laixi",
    "tgn:placetype":[
        "aat:300008347"
    ]
},
  "bbox": [],
  "geometry": {"coordinates":[120.6667,36.8333],"type":"Point"}
}