{
  "id": 2294211,
  "type": "Feature",
  "properties": {
    "tgn:hierarchy":[
        "tgn:2294211",
        "tgn:1000001",
        "tgn:7012149",
        "tgn:1002645",
        "tgn:7007920",
        "tgn:7029392"
    ],
    "tgn:id":2294211,
    "tgn:name":"Dow Creek",
    "tgn:placetype":[
        "aat:300008706"
    ]
},
  "bbox": [],
  "geometry": {"coordinates":[-123.1667,47.4333],"type":"Point"}
}