<<<<<<< HEAD
{
  "id": 2257656,
  "type": "Feature",
  "properties": {
    "tgn:hierarchy":[
        "tgn:2257656",
        "tgn:1000001",
        "tgn:7012149",
        "tgn:2001722",
        "tgn:7007708",
        "tgn:7029392"
    ],
    "tgn:id":2257656,
    "tgn:name":"Corral Creek",
    "tgn:placetype":[
        "aat:300008706"
    ]
},
  "bbox": [],
  "geometry": {"coordinates":[-116.85,45.6833],"type":"Point"}
}
=======
{"geometry":{"type":"Point","coordinates":[-116.850000,45.683300]},"type":"Feature","properties":{"hierarchy":["tgn:2257656","tgn:1000001","tgn:7012149","tgn:2001722","tgn:7007708","tgn:7029392"],"placetype":["aat:300008706"],"id":2257656,"name:xx":"Corral Creek"}}
>>>>>>> 03f74aca74312dbeaf24d7e61306dd6a786dc3d0
