{
  "id": 7274603,
  "type": "Feature",
  "properties": {
    "tgn:hierarchy":[
        "tgn:7274603",
        "tgn:7003616",
        "tgn:1000003",
        "tgn:7016845",
        "tgn:7029392"
    ],
    "tgn:id":7274603,
    "tgn:name:nl":"Witveenstervaart",
    "tgn:placetype":[
        "aat:300006075"
    ]
},
  "bbox": [],
  "geometry": {"coordinates":[6.066667,53.15],"type":"Point"}
}