{
  "id": 2575112,
  "type": "Feature",
  "properties": {
    "tgn:hierarchy":[
        "tgn:2575112",
        "tgn:7006450",
        "tgn:1000001",
        "tgn:7012149",
        "tgn:2000085",
        "tgn:7029392"
    ],
    "tgn:id":2575112,
    "tgn:name":"Pennington Creek",
    "tgn:placetype":[
        "aat:300008706"
    ]
},
  "bbox": [],
  "geometry": {"coordinates":[-141.25,64.0333],"type":"Point"}
}