{
  "id": 2505837,
  "type": "Feature",
  "properties": {
    "tgn:hierarchy":[
        "tgn:2505837",
        "tgn:1000001",
        "tgn:7012149",
        "tgn:7007157",
        "tgn:7014004",
        "tgn:7029392"
    ],
    "tgn:id":2505837,
    "tgn:name":"Merced Grove",
    "tgn:placetype":[
        "aat:300132451"
    ]
},
  "bbox": [],
  "geometry": {"coordinates":[-119.8333,37.7333],"type":"Point"}
}