{
  "id": 2362470,
  "type": "Feature",
  "properties": {
    "tgn:hierarchy":[
        "tgn:2362470",
        "tgn:1000001",
        "tgn:7012149",
        "tgn:2000801",
        "tgn:7007255",
        "tgn:7029392"
    ],
    "tgn:id":2362470,
    "tgn:name":"Greasy Creek",
    "tgn:placetype":[
        "aat:300008706"
    ]
},
  "bbox": [],
  "geometry": {"coordinates":[-87.5167,37.3333],"type":"Point"}
}