{
  "id": 7371594,
  "type": "Feature",
  "properties": {
    "tgn:hierarchy":[
        "tgn:7371594",
        "tgn:1000001",
        "tgn:7005595",
        "tgn:7005560",
        "tgn:7029392"
    ],
    "tgn:id":7371594,
    "tgn:name":"La Mojonera",
    "tgn:placetype":[
        "aat:300008347"
    ]
},
  "bbox": [],
  "geometry": {"coordinates":[-107.333333,25.05],"type":"Point"}
}