{
  "id": 2310493,
  "type": "Feature",
  "properties": {
    "tgn:hierarchy":[
        "tgn:2310493",
        "tgn:2000947",
        "tgn:1000001",
        "tgn:7012149",
        "tgn:7007520",
        "tgn:7029392"
    ],
    "tgn:id":2310493,
    "tgn:name":"Echo Harbor",
    "tgn:placetype":[
        "aat:300132316"
    ]
},
  "bbox": [],
  "geometry": {"coordinates":[-88.2667,46.8167],"type":"Point"}
}