{
  "id": 7575633,
  "type": "Feature",
  "properties": {
    "tgn:hierarchy":[
        "tgn:7575633",
        "tgn:1000004",
        "tgn:7000198",
        "tgn:7016788",
        "tgn:7029392"
    ],
    "tgn:id":7575633,
    "tgn:name:en":"Kh\u0101bha",
    "tgn:placetype":[
        "aat:300008347"
    ]
},
  "bbox": [],
  "geometry": {"coordinates":[70.674161,26.812748],"type":"Point"}
}