{
  "id": 7289492,
  "type": "Feature",
  "properties": {
    "tgn:hierarchy":[
        "tgn:7289492",
        "tgn:7002464",
        "tgn:1000049",
        "tgn:1000002",
        "tgn:7029392"
    ],
    "tgn:id":7289492,
    "tgn:name":"Ingi\u00f1a",
    "tgn:placetype":[
        "aat:300004792"
    ]
},
  "bbox": [],
  "geometry": {"coordinates":[-68.583333,-19.866667],"type":"Point"}
}