{
  "id": 7469152,
  "type": "Feature",
  "properties": {
    "tgn:hierarchy":[
        "tgn:7469152",
        "tgn:7001010",
        "tgn:1000004",
        "tgn:1000141",
        "tgn:7029392"
    ],
    "tgn:id":7469152,
    "tgn:name":"Xibao",
    "tgn:placetype":[
        "aat:300008347"
    ]
},
  "bbox": [],
  "geometry": {"coordinates":[121.483611,24.201389],"type":"Point"}
}