{
  "id": 7563286,
  "type": "Feature",
  "properties": {
    "tgn:hierarchy":[
        "tgn:7563286",
        "tgn:1000004",
        "tgn:7000198",
        "tgn:7016722",
        "tgn:7029392"
    ],
    "tgn:id":7563286,
    "tgn:name:en":"Likkha Purwa",
    "tgn:placetype":[
        "aat:300008347"
    ]
},
  "bbox": [],
  "geometry": {"coordinates":[79.9435,27.0713],"type":"Point"}
}