{
  "id": 2405828,
  "type": "Feature",
  "properties": {
    "tgn:hierarchy":[
        "tgn:2405828",
        "tgn:1000001",
        "tgn:2000311",
        "tgn:7012149",
        "tgn:7007248",
        "tgn:7029392"
    ],
    "tgn:id":2405828,
    "tgn:name":"Hull Island",
    "tgn:placetype":[
        "aat:300008791"
    ]
},
  "bbox": [],
  "geometry": {"coordinates":[-81.6667,31.0333],"type":"Point"}
}