{
  "id": 1132870,
  "type": "Feature",
  "properties": {
    "tgn:hierarchy":[
        "tgn:1132870",
        "tgn:1000001",
        "tgn:7012149",
        "tgn:7007157",
        "tgn:1002864",
        "tgn:7029392"
    ],
    "tgn:id":1132870,
    "tgn:name":"Colma Creek",
    "tgn:placetype":[
        "aat:300008706"
    ]
},
  "bbox": [],
  "geometry": {"coordinates":[-122.45,37.6667],"type":"Point"}
}