{
  "id": 7402242,
  "type": "Feature",
  "properties": {
    "tgn:hierarchy":[
        "tgn:7402242",
        "tgn:1000001",
        "tgn:7005599",
        "tgn:7005560",
        "tgn:7029392"
    ],
    "tgn:id":7402242,
    "tgn:name":"San Juan de Villa Rica",
    "tgn:placetype":[
        "aat:300008347"
    ]
},
  "bbox": [],
  "geometry": {"coordinates":[-96.483333,19.608333],"type":"Point"}
}