{
  "id": 7068130,
  "type": "Feature",
  "properties": {
    "tgn:hierarchy":[
        "tgn:7068130",
        "tgn:7003669",
        "tgn:1000003",
        "tgn:7000084",
        "tgn:7029392"
    ],
    "tgn:id":7068130,
    "tgn:name":"Triebh\u00f6lzer",
    "tgn:placetype":[
        "aat:300008863"
    ]
},
  "bbox": [],
  "geometry": {"coordinates":[10.133333,48.35],"type":"Point"}
}