{
  "id": 7413809,
  "type": "Feature",
  "properties": {
    "tgn:hierarchy":[
        "tgn:7413809",
        "tgn:7005587",
        "tgn:1000001",
        "tgn:7005560",
        "tgn:7029392"
    ],
    "tgn:id":7413809,
    "tgn:name:es":"San Jos\u00e9 del Valle",
    "tgn:placetype":[
        "aat:300008347"
    ]
},
  "bbox": [],
  "geometry": {"coordinates":[-98.133333,20.391667],"type":"Point"}
}