{
  "id": 2304003,
  "type": "Feature",
  "properties": {
    "tgn:hierarchy":[
        "tgn:2304003",
        "tgn:1000001",
        "tgn:7012149",
        "tgn:7007158",
        "tgn:2000253",
        "tgn:7029392"
    ],
    "tgn:id":2304003,
    "tgn:name":"Eagle Rock Reservoir",
    "tgn:placetype":[
        "aat:300006191"
    ]
},
  "bbox": [],
  "geometry": {"coordinates":[-104.4833,40.9667],"type":"Point"}
}