{
  "id": 7492846,
  "type": "Feature",
  "properties": {
    "tgn:hierarchy":[
        "tgn:7492846",
        "tgn:1000004",
        "tgn:7492971",
        "tgn:1000141",
        "tgn:7029392"
    ],
    "tgn:id":7492846,
    "tgn:name":"Shekou",
    "tgn:placetype":[
        "aat:300008347"
    ]
},
  "bbox": [],
  "geometry": {"coordinates":[120.470684,22.612473],"type":"Point"}
}