{
  "id": 7457794,
  "type": "Feature",
  "properties": {
    "tgn:hierarchy":[
        "tgn:7457794",
        "tgn:7002443",
        "tgn:1000003",
        "tgn:7018993",
        "tgn:7008591",
        "tgn:7029392"
    ],
    "tgn:id":7457794,
    "tgn:name:en":"Penffordd",
    "tgn:placetype":[
        "aat:300008347"
    ]
},
  "bbox": [],
  "geometry": {"coordinates":[-4.793889,51.866667],"type":"Point"}
}