{
  "id": 7541236,
  "type": "Feature",
  "properties": {
    "tgn:hierarchy":[
        "tgn:7541236",
        "tgn:7001242",
        "tgn:7016833",
        "tgn:7029392"
    ],
    "tgn:id":7541236,
    "tgn:name":"Tur'at al Kawm al A\u1e29mar Raqam W\u0101\u1e29id",
    "tgn:placetype":[
        "aat:300006075"
    ]
},
  "bbox": [],
  "geometry": {"coordinates":[31.151711,30.09667],"type":"Point"}
}