{
  "id": 2479406,
  "type": "Feature",
  "properties": {
    "tgn:hierarchy":[
        "tgn:2479406",
        "tgn:1000001",
        "tgn:7012149",
        "tgn:7007826",
        "tgn:7029392"
    ],
    "tgn:id":2479406,
    "tgn:name":"Lagunas Negras",
    "tgn:placetype":[
        "aat:300008699"
    ]
},
  "bbox": [],
  "geometry": {"coordinates":[-98.25,27.2833],"type":"Point"}
}