{
  "id": 2391262,
  "type": "Feature",
  "properties": {
    "tgn:hierarchy":[
        "tgn:2391262",
        "tgn:1000001",
        "tgn:7012149",
        "tgn:2001715",
        "tgn:7007708",
        "tgn:7029392"
    ],
    "tgn:id":2391262,
    "tgn:name":"Hill Top Waterhole",
    "tgn:placetype":[
        "aat:300006191"
    ]
},
  "bbox": [],
  "geometry": {"coordinates":[-120.2833,43.55],"type":"Point"}
}