{
  "id": 7078116,
  "type": "Feature",
  "properties": {
    "tgn:hierarchy":[
        "tgn:7078116",
        "tgn:1000003",
        "tgn:7000094",
        "tgn:7000084",
        "tgn:7029392"
    ],
    "tgn:id":7078116,
    "tgn:name":"Ziddorf",
    "tgn:placetype":[
        "aat:300008347"
    ]
},
  "bbox": [],
  "geometry": {"coordinates":[12.55,53.683333],"type":"Point"}
}