{
  "id": 2453155,
  "type": "Feature",
  "properties": {
    "tgn:hierarchy":[
        "tgn:2453155",
        "tgn:1000001",
        "tgn:7012149",
        "tgn:7007157",
        "tgn:2000189",
        "tgn:7029392"
    ],
    "tgn:id":2453155,
    "tgn:name":"Little Castle Lake",
    "tgn:placetype":[
        "aat:300008680"
    ]
},
  "bbox": [],
  "geometry": {"coordinates":[-122.3667,41.2167],"type":"Point"}
}