{
  "id": 2344270,
  "type": "Feature",
  "properties": {
    "tgn:hierarchy":[
        "tgn:2344270",
        "tgn:1000001",
        "tgn:2000860",
        "tgn:7012149",
        "tgn:7007256",
        "tgn:7029392"
    ],
    "tgn:id":2344270,
    "tgn:name":"Gandy Bayou",
    "tgn:placetype":[
        "aat:300008699"
    ]
},
  "bbox": [],
  "geometry": {"coordinates":[-93.6833,32.2833],"type":"Point"}
}