{
  "id": 7298972,
  "type": "Feature",
  "properties": {
    "tgn:hierarchy":[
        "tgn:7298972",
        "tgn:7007780",
        "tgn:1000003",
        "tgn:7009604",
        "tgn:1000095",
        "tgn:7029392"
    ],
    "tgn:id":7298972,
    "tgn:name":"Urumea, R\u00edo",
    "tgn:placetype":[
        "aat:300008699"
    ]
},
  "bbox": [],
  "geometry": {"coordinates":[-1.966667,43.333333],"type":"Point"}
}