<<<<<<< HEAD
{
  "id": 2408368,
  "type": "Feature",
  "properties": {
    "tgn:hierarchy":[
        "tgn:2408368",
        "tgn:1000001",
        "tgn:7012149",
        "tgn:1002676",
        "tgn:7007240",
        "tgn:7029392"
    ],
    "tgn:id":2408368,
    "tgn:name":"Huston Bay",
    "tgn:placetype":[
        "aat:300132316"
    ]
},
  "bbox": [],
  "geometry": {"coordinates":[-81.25,25.75],"type":"Point"}
}
=======
{"geometry":{"type":"Point","coordinates":[-81.250000,25.750000]},"type":"Feature","properties":{"hierarchy":["tgn:2408368","tgn:1000001","tgn:7012149","tgn:1002676","tgn:7007240","tgn:7029392"],"placetype":["aat:300132316"],"id":2408368,"name:xx":"Huston Bay"}}
>>>>>>> 03f74aca74312dbeaf24d7e61306dd6a786dc3d0
