{
  "id": 2493523,
  "type": "Feature",
  "properties": {
    "tgn:hierarchy":[
        "tgn:2493523",
        "tgn:1000001",
        "tgn:7012149",
        "tgn:1003041",
        "tgn:7007710",
        "tgn:7029392"
    ],
    "tgn:id":2493523,
    "tgn:name":"Marsh Creek",
    "tgn:placetype":[
        "aat:300008706"
    ]
},
  "bbox": [],
  "geometry": {"coordinates":[-75.95,41.4167],"type":"Point"}
}