{
  "id": 7536043,
  "type": "Feature",
  "properties": {
    "tgn:hierarchy":[
        "tgn:7536043",
        "tgn:7001242",
        "tgn:7016833",
        "tgn:1001113",
        "tgn:7029392"
    ],
    "tgn:id":7536043,
    "tgn:name":"Kafr al Mashhad",
    "tgn:placetype":[
        "aat:300008347"
    ]
},
  "bbox": [],
  "geometry": {"coordinates":[31.603751,30.443831],"type":"Point"}
}