{
  "id": 7557663,
  "type": "Feature",
  "properties": {
    "tgn:hierarchy":[
        "tgn:7557663",
        "tgn:1000004",
        "tgn:1001869",
        "tgn:7000198",
        "tgn:7029392"
    ],
    "tgn:id":7557663,
    "tgn:name:en":"Sami",
    "tgn:placetype":[
        "aat:300008347"
    ]
},
  "bbox": [],
  "geometry": {"coordinates":[71.777063,23.683902],"type":"Point"}
}