{
  "id": 2718532,
  "type": "Feature",
  "properties": {
    "tgn:hierarchy":[
        "tgn:2718532",
        "tgn:1000001",
        "tgn:7012149",
        "tgn:7007157",
        "tgn:2000187",
        "tgn:7029392"
    ],
    "tgn:id":2718532,
    "tgn:name":"Thompson Peak",
    "tgn:placetype":[
        "aat:300008798"
    ]
},
  "bbox": [],
  "geometry": {"coordinates":[-120.55,40.25],"type":"Point"}
}