{
  "id": 2274398,
  "type": "Feature",
  "properties": {
    "tgn:hierarchy":[
        "tgn:2274398",
        "tgn:1000001",
        "tgn:7012149",
        "tgn:2001047",
        "tgn:7007521",
        "tgn:7029392"
    ],
    "tgn:id":2274398,
    "tgn:name":"Dale Lake",
    "tgn:placetype":[
        "aat:300008680"
    ]
},
  "bbox": [],
  "geometry": {"coordinates":[-94.4333,46.1167],"type":"Point"}
}