{
  "id": 1091913,
  "type": "Feature",
  "properties": {
    "tgn:hierarchy":[
        "tgn:1091913",
        "tgn:7001242",
        "tgn:1001841",
        "tgn:1000182",
        "tgn:7029392"
    ],
    "tgn:id":1091913,
    "tgn:name":"Boju Ega",
    "tgn:placetype":[
        "aat:300008347"
    ]
},
  "bbox": [],
  "geometry": {"coordinates":[8.05,7.35],"type":"Point"}
}