{
  "id": 7501193,
  "type": "Feature",
  "properties": {
    "tgn:hierarchy":[
        "tgn:7501193",
        "tgn:1000004",
        "tgn:7467799",
        "tgn:1000141",
        "tgn:7029392"
    ],
    "tgn:id":7501193,
    "tgn:name":"Xikoucuo",
    "tgn:placetype":[
        "aat:300008347"
    ]
},
  "bbox": [],
  "geometry": {"coordinates":[120.472778,24.146389],"type":"Point"}
}