{
  "id": 2209406,
  "type": "Feature",
  "properties": {
    "tgn:hierarchy":[
        "tgn:2209406",
        "tgn:1000001",
        "tgn:7012149",
        "tgn:2000232",
        "tgn:7007158",
        "tgn:7029392"
    ],
    "tgn:id":2209406,
    "tgn:name":"Burnt Spring",
    "tgn:placetype":[
        "aat:300008697"
    ]
},
  "bbox": [],
  "geometry": {"coordinates":[-108.7833,40.3167],"type":"Point"}
}