{
  "id": 7511577,
  "type": "Feature",
  "properties": {
    "tgn:hierarchy":[
        "tgn:7511577",
        "tgn:1009227",
        "tgn:1000226",
        "tgn:7018437",
        "tgn:1000006",
        "tgn:7029392"
    ],
    "tgn:id":7511577,
    "tgn:name:en":"Lowburn",
    "tgn:placetype":[
        "aat:300008699"
    ]
},
  "bbox": [],
  "geometry": {"coordinates":[169.55,-45.833333],"type":"Point"}
}