<<<<<<< HEAD
{
  "id": 7245323,
  "type": "Feature",
  "properties": {
    "tgn:hierarchy":[
        "tgn:7245323",
        "tgn:7007877",
        "tgn:1000003",
        "tgn:1000063",
        "tgn:4012014",
        "tgn:7029392"
    ],
    "tgn:id":7245323,
    "tgn:name":"Basse Heuval",
    "tgn:placetype":[
        "aat:300008347"
    ]
},
  "bbox": [],
  "geometry": {"coordinates":[4.55,50.583333],"type":"Point"}
}
=======
{"geometry":{"type":"Point","coordinates":[4.550000,50.583333]},"type":"Feature","properties":{"hierarchy":["tgn:7245323","tgn:7007877","tgn:1000003","tgn:1000063","tgn:4012014","tgn:7029392"],"placetype":["aat:300008347"],"id":7245323,"name:xx":"Basse Heuval"}}
>>>>>>> 03f74aca74312dbeaf24d7e61306dd6a786dc3d0
