{
  "id": 7564728,
  "type": "Feature",
  "properties": {
    "tgn:hierarchy":[
        "tgn:7564728",
        "tgn:1000004",
        "tgn:7000198",
        "tgn:7016788",
        "tgn:7029392"
    ],
    "tgn:id":7564728,
    "tgn:name:en":"Bhoj\u0101n",
    "tgn:placetype":[
        "aat:300008347"
    ]
},
  "bbox": [],
  "geometry": {"coordinates":[75.562376,28.566846],"type":"Point"}
}