{
  "id": 2588201,
  "type": "Feature",
  "properties": {
    "tgn:hierarchy":[
        "tgn:2588201",
        "tgn:1000001",
        "tgn:1002369",
        "tgn:7012149",
        "tgn:7007251",
        "tgn:7029392"
    ],
    "tgn:id":2588201,
    "tgn:name":"Plum Branch",
    "tgn:placetype":[
        "aat:300008699"
    ]
},
  "bbox": [],
  "geometry": {"coordinates":[-88.9667,38.8333],"type":"Point"}
}