{
  "id": 7545878,
  "type": "Feature",
  "properties": {
    "tgn:hierarchy":[
        "tgn:7545878",
        "tgn:1000004",
        "tgn:7000198",
        "tgn:1001894",
        "tgn:7029392"
    ],
    "tgn:id":7545878,
    "tgn:name:en":"\u0100mla",
    "tgn:placetype":[
        "aat:300008347"
    ]
},
  "bbox": [],
  "geometry": {"coordinates":[76.649683,21.518254],"type":"Point"}
}