{
  "id": 7316236,
  "type": "Feature",
  "properties": {
    "tgn:hierarchy":[
        "tgn:7316236",
        "tgn:7016598",
        "tgn:1000049",
        "tgn:1000002",
        "tgn:7029392"
    ],
    "tgn:id":7316236,
    "tgn:name":"Casa de Piedra",
    "tgn:placetype":[
        "aat:300008347"
    ]
},
  "bbox": [],
  "geometry": {"coordinates":[-68.716667,-20.95],"type":"Point"}
}