{
  "id": 7010030,
  "type": "Feature",
  "properties": {
    "tgn:hierarchy":[
        "tgn:7010030",
        "tgn:7002445",
        "tgn:1000003",
        "tgn:7008127",
        "tgn:7008591",
        "tgn:7029392"
    ],
    "tgn:id":7010030,
    "tgn:name:en":"Seaham",
    "tgn:placetype":[
        "aat:300008347"
    ]
},
  "bbox": [],
  "geometry": {"coordinates":[-1.338056,54.836667],"type":"Point"}
}