{
  "id": 2705156,
  "type": "Feature",
  "properties": {
    "tgn:hierarchy":[
        "tgn:2705156",
        "tgn:1000001",
        "tgn:7012149",
        "tgn:2001715",
        "tgn:7007708",
        "tgn:7029392"
    ],
    "tgn:id":2705156,
    "tgn:name":"Sunstone Area",
    "tgn:placetype":[
        "aat:300055621"
    ]
},
  "bbox": [],
  "geometry": {"coordinates":[-119.85,42.7167],"type":"Point"}
}