{
  "id": 7457979,
  "type": "Feature",
  "properties": {
    "tgn:hierarchy":[
        "tgn:7457979",
        "tgn:7002444",
        "tgn:1000003",
        "tgn:7008082",
        "tgn:7008591",
        "tgn:7029392"
    ],
    "tgn:id":7457979,
    "tgn:name:en":"Loyne, River",
    "tgn:placetype":[
        "aat:300008699"
    ]
},
  "bbox": [],
  "geometry": {"coordinates":[-4.95,57.15],"type":"Point"}
}