{
  "id": 2727760,
  "type": "Feature",
  "properties": {
    "tgn:hierarchy":[
        "tgn:2727760",
        "tgn:1000001",
        "tgn:7012149",
        "tgn:1002439",
        "tgn:7007252",
        "tgn:7029392"
    ],
    "tgn:id":2727760,
    "tgn:name":"Trails End",
    "tgn:placetype":[
        "aat:300008347"
    ]
},
  "bbox": [],
  "geometry": {"coordinates":[-86.05,39.95],"type":"Point"}
}