{
  "id": 2522806,
  "type": "Feature",
  "properties": {
    "tgn:hierarchy":[
        "tgn:2522806",
        "tgn:1000001",
        "tgn:2001629",
        "tgn:7012149",
        "tgn:7007707",
        "tgn:7029392"
    ],
    "tgn:id":2522806,
    "tgn:name":"Moore Creek",
    "tgn:placetype":[
        "aat:300008706"
    ]
},
  "bbox": [],
  "geometry": {"coordinates":[-96.4167,33.95],"type":"Point"}
}