{
  "id": 7206563,
  "type": "Feature",
  "properties": {
    "tgn:hierarchy":[
        "tgn:7206563",
        "tgn:7003669",
        "tgn:1000003",
        "tgn:7000084",
        "tgn:7029392"
    ],
    "tgn:id":7206563,
    "tgn:name":"Dachstadt",
    "tgn:placetype":[
        "aat:300008347"
    ]
},
  "bbox": [],
  "geometry": {"coordinates":[11.25,49.633333],"type":"Point"}
}