{
  "id": 2229230,
  "type": "Feature",
  "properties": {
    "tgn:hierarchy":[
        "tgn:2229230",
        "tgn:1000001",
        "tgn:7012149",
        "tgn:2002250",
        "tgn:7007920",
        "tgn:7029392"
    ],
    "tgn:id":2229230,
    "tgn:name":"Cedar Lake",
    "tgn:placetype":[
        "aat:300008680"
    ]
},
  "bbox": [],
  "geometry": {"coordinates":[-117.5833,48.9333],"type":"Point"}
}