{
  "id": 2481753,
  "type": "Feature",
  "properties": {
    "tgn:hierarchy":[
        "tgn:2481753",
        "tgn:1000001",
        "tgn:7012149",
        "tgn:7022218",
        "tgn:7007919",
        "tgn:7029392"
    ],
    "tgn:id":2481753,
    "tgn:name":"Landing Cove",
    "tgn:placetype":[
        "aat:300132316"
    ]
},
  "bbox": [],
  "geometry": {"coordinates":[-75.9667,36.65],"type":"Point"}
}