{
  "id": 1033820,
  "type": "Feature",
  "properties": {
    "tgn:hierarchy":[
        "tgn:1033820",
        "tgn:1000003",
        "tgn:1000070",
        "tgn:7002897",
        "tgn:7029392"
    ],
    "tgn:id":1033820,
    "tgn:name":"B\u00e9age, le",
    "tgn:placetype":[
        "aat:300008347"
    ]
},
  "bbox": [],
  "geometry": {"coordinates":[4.1333,44.8667],"type":"Point"}
}