{
  "id": 1073792,
  "type": "Feature",
  "properties": {
    "tgn:hierarchy":[
        "tgn:1073792",
        "tgn:1000004",
        "tgn:7002085",
        "tgn:1000111",
        "tgn:7029392"
    ],
    "tgn:id":1073792,
    "tgn:name":"Zanggezhuang",
    "tgn:placetype":[
        "aat:300008347"
    ]
},
  "bbox": [],
  "geometry": {"coordinates":[120.95,37.4667],"type":"Point"}
}