{
  "id": 7425997,
  "type": "Feature",
  "properties": {
    "tgn:hierarchy":[
        "tgn:7425997",
        "tgn:7005581",
        "tgn:1000001",
        "tgn:7005560",
        "tgn:7029392"
    ],
    "tgn:id":7425997,
    "tgn:name":"El Ocho",
    "tgn:placetype":[
        "aat:300008347"
    ]
},
  "bbox": [],
  "geometry": {"coordinates":[-107.85,31.416667],"type":"Point"}
}