{
  "id": 2049357,
  "type": "Feature",
  "properties": {
    "tgn:hierarchy":[
        "tgn:2049357",
        "tgn:2049349",
        "tgn:1000001",
        "tgn:7012149",
        "tgn:1003038",
        "tgn:7007517",
        "tgn:7029392"
    ],
    "tgn:id":2049357,
    "tgn:name":"Woodland Park",
    "tgn:placetype":[
        "aat:300000745"
    ]
},
  "bbox": [],
  "geometry": {"coordinates":[-71.8167,42.2167],"type":"Point"}
}