{
  "id": 2425253,
  "type": "Feature",
  "properties": {
    "tgn:hierarchy":[
        "tgn:2425253",
        "tgn:1000001",
        "tgn:7006451",
        "tgn:7012149",
        "tgn:2000103",
        "tgn:7029392"
    ],
    "tgn:id":2425253,
    "tgn:name":"Johnson Peak",
    "tgn:placetype":[
        "aat:300008798"
    ]
},
  "bbox": [],
  "geometry": {"coordinates":[-112.75,34.8167],"type":"Point"}
}