{
  "id": 7341354,
  "type": "Feature",
  "properties": {
    "tgn:hierarchy":[
        "tgn:7341354",
        "tgn:7002759",
        "tgn:7008909",
        "tgn:1000003",
        "tgn:1000095",
        "tgn:7029392"
    ],
    "tgn:id":7341354,
    "tgn:name":"Botella, R\u00edo",
    "tgn:placetype":[
        "aat:300008699"
    ]
},
  "bbox": [],
  "geometry": {"coordinates":[-0.283129,42.052546],"type":"Point"}
}