{
  "id": 2110521,
  "type": "Feature",
  "properties": {
    "tgn:hierarchy":[
        "tgn:2110521",
        "tgn:1000001",
        "tgn:7012149",
        "tgn:1002336",
        "tgn:7007919",
        "tgn:7029392"
    ],
    "tgn:id":2110521,
    "tgn:name":"Baltimore Corner",
    "tgn:placetype":[
        "aat:300008347",
        "aat:300387210"
    ]
},
  "bbox": [],
  "geometry": {"coordinates":[-77.7167,37.0833],"type":"Point"}
}