{
  "id": 2533063,
  "type": "Feature",
  "properties": {
    "tgn:hierarchy":[
        "tgn:2533063",
        "tgn:1000001",
        "tgn:7012149",
        "tgn:1002517",
        "tgn:7007523",
        "tgn:7029392"
    ],
    "tgn:id":2533063,
    "tgn:name":"Murril Branch",
    "tgn:placetype":[
        "aat:300008699"
    ]
},
  "bbox": [],
  "geometry": {"coordinates":[-90.55,38.2167],"type":"Point"}
}