{
  "id": 2731050,
  "type": "Feature",
  "properties": {
    "tgn:hierarchy":[
        "tgn:2731050",
        "tgn:7002659",
        "tgn:1000001",
        "tgn:2000003",
        "tgn:7012149",
        "tgn:7029392"
    ],
    "tgn:id":2731050,
    "tgn:name":"Tucker",
    "tgn:placetype":[
        "aat:300008347"
    ]
},
  "bbox": [],
  "geometry": {"coordinates":[-86.8833,32.8667],"type":"Point"}
}