<<<<<<< HEAD
{
  "id": 7356575,
  "type": "Feature",
  "properties": {
    "tgn:hierarchy":[
        "tgn:7356575",
        "tgn:7005586",
        "tgn:1000001",
        "tgn:7005560",
        "tgn:7029392"
    ],
    "tgn:id":7356575,
    "tgn:name":"Camichinas",
    "tgn:placetype":[
        "aat:300008347"
    ]
},
  "bbox": [],
  "geometry": {"coordinates":[-103.8,20.483333],"type":"Point"}
}
=======
{"geometry":{"type":"Point","coordinates":[-103.800000,20.483333]},"type":"Feature","properties":{"hierarchy":["tgn:7356575","tgn:7005586","tgn:1000001","tgn:7005560","tgn:7029392"],"placetype":["aat:300008347"],"id":7356575,"name:xx":"Camichinas"}}
>>>>>>> 03f74aca74312dbeaf24d7e61306dd6a786dc3d0
