{
  "id": 2767919,
  "type": "Feature",
  "properties": {
    "tgn:hierarchy":[
        "tgn:2767919",
        "tgn:1000001",
        "tgn:7012149",
        "tgn:7007252",
        "tgn:7029392"
    ],
    "tgn:id":2767919,
    "tgn:name":"Whitelock Ditch",
    "tgn:placetype":[
        "aat:300006075"
    ]
},
  "bbox": [],
  "geometry": {"coordinates":[-85.3167,40.7333],"type":"Point"}
}