<<<<<<< HEAD
{
  "id": 2767919,
  "type": "Feature",
  "properties": {
    "tgn:hierarchy":[
        "tgn:2767919",
        "tgn:1000001",
        "tgn:7012149",
        "tgn:7007252",
        "tgn:7029392"
    ],
    "tgn:id":2767919,
    "tgn:name":"Whitelock Ditch",
    "tgn:placetype":[
        "aat:300006075"
    ]
},
  "bbox": [],
  "geometry": {"coordinates":[-85.3167,40.7333],"type":"Point"}
}
=======
{"geometry":{"type":"Point","coordinates":[-85.316700,40.733300]},"type":"Feature","properties":{"hierarchy":["tgn:2767919","tgn:1000001","tgn:7012149","tgn:7007252","tgn:7029392"],"placetype":["aat:300006075"],"id":2767919,"name:xx":"Whitelock Ditch"}}
>>>>>>> 03f74aca74312dbeaf24d7e61306dd6a786dc3d0
