<<<<<<< HEAD
{
  "id": 7480029,
  "type": "Feature",
  "properties": {
    "tgn:hierarchy":[
        "tgn:7480029",
        "tgn:1000004",
        "tgn:7490934",
        "tgn:1000141",
        "tgn:7029392"
    ],
    "tgn:id":7480029,
    "tgn:name":"Guanditing",
    "tgn:placetype":[
        "aat:300387033"
    ]
},
  "bbox": [],
  "geometry": {"coordinates":[120.426944,23.402778],"type":"Point"}
}
=======
{"geometry":{"type":"Point","coordinates":[120.426944,23.402778]},"type":"Feature","properties":{"hierarchy":["tgn:7480029","tgn:1000004","tgn:7490934","tgn:1000141","tgn:7029392"],"placetype":["aat:300387033"],"id":7480029,"name:xx":"Guanditing"}}
>>>>>>> 03f74aca74312dbeaf24d7e61306dd6a786dc3d0
