{
  "id": 7567233,
  "type": "Feature",
  "properties": {
    "tgn:hierarchy":[
        "tgn:7567233",
        "tgn:1000004",
        "tgn:7000198",
        "tgn:7031786",
        "tgn:7029392"
    ],
    "tgn:id":7567233,
    "tgn:name:en":"Naugaon",
    "tgn:placetype":[
        "aat:300008347"
    ]
},
  "bbox": [],
  "geometry": {"coordinates":[78.648952,29.845288],"type":"Point"}
}