{
  "id": 7562986,
  "type": "Feature",
  "properties": {
    "tgn:hierarchy":[
        "tgn:7562986",
        "tgn:1000004",
        "tgn:7000198",
        "tgn:7016722",
        "tgn:7029392"
    ],
    "tgn:id":7562986,
    "tgn:name:en":"Sidhpura",
    "tgn:placetype":[
        "aat:300008347"
    ]
},
  "bbox": [],
  "geometry": {"coordinates":[79.126256,26.404267],"type":"Point"}
}