{
  "id": 7421450,
  "type": "Feature",
  "properties": {
    "tgn:hierarchy":[
        "tgn:7421450",
        "tgn:1000001",
        "tgn:7005589",
        "tgn:7005560",
        "tgn:7029392"
    ],
    "tgn:id":7421450,
    "tgn:name:es":"Los Cuales",
    "tgn:placetype":[
        "aat:300008347"
    ]
},
  "bbox": [],
  "geometry": {"coordinates":[-99.156111,25.281111],"type":"Point"}
}