{
  "id": 2551315,
  "type": "Feature",
  "properties": {
    "tgn:hierarchy":[
        "tgn:2551315",
        "tgn:1000001",
        "tgn:7012149",
        "tgn:2001288",
        "tgn:7007524",
        "tgn:7029392"
    ],
    "tgn:id":2551315,
    "tgn:name":"Nuggett Creek Mine",
    "tgn:placetype":[
        "aat:300000390"
    ]
},
  "bbox": [],
  "geometry": {"coordinates":[-112.1667,45.5167],"type":"Point"}
}