{
  "id": 7221337,
  "type": "Feature",
  "properties": {
    "tgn:hierarchy":[
        "tgn:7221337",
        "tgn:7002706",
        "tgn:7002705",
        "tgn:1000003",
        "tgn:1000074",
        "tgn:7029392"
    ],
    "tgn:id":7221337,
    "tgn:name":"Tzourn\u00f3kos",
    "tgn:placetype":[
        "aat:300132316"
    ]
},
  "bbox": [],
  "geometry": {"coordinates":[20.833333,38.916667],"type":"Point"}
}