{
  "id": 7194509,
  "type": "Feature",
  "properties": {
    "tgn:hierarchy":[
        "tgn:7194509",
        "tgn:1000003",
        "tgn:7003676",
        "tgn:7000084",
        "tgn:7029392"
    ],
    "tgn:id":7194509,
    "tgn:name":"Die oberen H\u00e4user",
    "tgn:placetype":[
        "aat:300000206"
    ]
},
  "bbox": [],
  "geometry": {"coordinates":[8.916667,52.716667],"type":"Point"}
}