{
  "id": 2335717,
  "type": "Feature",
  "properties": {
    "tgn:hierarchy":[
        "tgn:2335717",
        "tgn:1000001",
        "tgn:7012149",
        "tgn:2001247",
        "tgn:7007523",
        "tgn:7029392"
    ],
    "tgn:id":2335717,
    "tgn:name":"Forty Acre Sinkhole",
    "tgn:placetype":[
        "aat:300386845"
    ]
},
  "bbox": [],
  "geometry": {"coordinates":[-91.5167,37.15],"type":"Point"}
}