{
  "id": 2214628,
  "type": "Feature",
  "properties": {
    "tgn:hierarchy":[
        "tgn:2214628",
        "tgn:1000001",
        "tgn:1002601",
        "tgn:7012149",
        "tgn:7007159",
        "tgn:7029392"
    ],
    "tgn:id":2214628,
    "tgn:name":"Calebs Peak",
    "tgn:placetype":[
        "aat:300008798"
    ]
},
  "bbox": [],
  "geometry": {"coordinates":[-73.45,41.75],"type":"Point"}
}