{
  "id": 2741391,
  "type": "Feature",
  "properties": {
    "tgn:hierarchy":[
        "tgn:2741391",
        "tgn:1000001",
        "tgn:7012149",
        "tgn:2000969",
        "tgn:7007520",
        "tgn:7029392"
    ],
    "tgn:id":2741391,
    "tgn:name":"Upson, Lake",
    "tgn:placetype":[
        "aat:300008680"
    ]
},
  "bbox": [],
  "geometry": {"coordinates":[-88.0333,47.45],"type":"Point"}
}