{
  "id": 7285625,
  "type": "Feature",
  "properties": {
    "tgn:hierarchy":[
        "tgn:7285625",
        "tgn:1001705",
        "tgn:1000049",
        "tgn:1000002",
        "tgn:7029392"
    ],
    "tgn:id":7285625,
    "tgn:name":"Pichim\u00e1vida",
    "tgn:placetype":[
        "aat:300000206"
    ]
},
  "bbox": [],
  "geometry": {"coordinates":[-72.383333,-36.25],"type":"Point"}
}