{
  "id": 7587714,
  "type": "Feature",
  "properties": {
    "tgn:hierarchy":[
        "tgn:7587714",
        "tgn:1000004",
        "tgn:7000198",
        "tgn:7000799",
        "tgn:7029392"
    ],
    "tgn:id":7587714,
    "tgn:name:en":"Naupura",
    "tgn:placetype":[
        "aat:300008347"
    ]
},
  "bbox": [],
  "geometry": {"coordinates":[74.633333,34.136111],"type":"Point"}
}