<<<<<<< HEAD
{
  "id": 2251719,
  "type": "Feature",
  "properties": {
    "tgn:hierarchy":[
        "tgn:2251719",
        "tgn:1000001",
        "tgn:7012149",
        "tgn:7007157",
        "tgn:2000189",
        "tgn:7029392"
    ],
    "tgn:id":2251719,
    "tgn:name":"Compressor Gulch",
    "tgn:placetype":[
        "aat:300008761"
    ]
},
  "bbox": [],
  "geometry": {"coordinates":[-123.1,41.25],"type":"Point"}
}
=======
{"geometry":{"type":"Point","coordinates":[-123.100000,41.250000]},"type":"Feature","properties":{"hierarchy":["tgn:2251719","tgn:1000001","tgn:7012149","tgn:7007157","tgn:2000189","tgn:7029392"],"placetype":["aat:300008761"],"id":2251719,"name:xx":"Compressor Gulch"}}
>>>>>>> 03f74aca74312dbeaf24d7e61306dd6a786dc3d0
