{
  "id": 2758305,
  "type": "Feature",
  "properties": {
    "tgn:hierarchy":[
        "tgn:2758305",
        "tgn:1000001",
        "tgn:2001411",
        "tgn:7012149",
        "tgn:7007526",
        "tgn:7029392"
    ],
    "tgn:id":2758305,
    "tgn:name":"West Brush Creek",
    "tgn:placetype":[
        "aat:300008706"
    ]
},
  "bbox": [],
  "geometry": {"coordinates":[-114.7833,41.3167],"type":"Point"}
}