{
  "id": 2736909,
  "type": "Feature",
  "properties": {
    "tgn:hierarchy":[
        "tgn:2736909",
        "tgn:1000001",
        "tgn:7012149",
        "tgn:2000236",
        "tgn:7007158",
        "tgn:7029392"
    ],
    "tgn:id":2736909,
    "tgn:name":"Two Buttes Canal",
    "tgn:placetype":[
        "aat:300006075"
    ]
},
  "bbox": [],
  "geometry": {"coordinates":[-103.4167,37.65],"type":"Point"}
}