{
  "id": 2324652,
  "type": "Feature",
  "properties": {
    "tgn:hierarchy":[
        "tgn:2324652",
        "tgn:2000090",
        "tgn:1000001",
        "tgn:7006451",
        "tgn:7012149",
        "tgn:7029392"
    ],
    "tgn:id":2324652,
    "tgn:name":"Fenceline Tank",
    "tgn:placetype":[
        "aat:300006191"
    ]
},
  "bbox": [],
  "geometry": {"coordinates":[-109.6833,34.5167],"type":"Point"}
}