{
  "id": 2281193,
  "type": "Feature",
  "properties": {
    "tgn:hierarchy":[
        "tgn:2281193",
        "tgn:1000001",
        "tgn:7012149",
        "tgn:1002552",
        "tgn:7007920",
        "tgn:7029392"
    ],
    "tgn:id":2281193,
    "tgn:name":"Deep Lake",
    "tgn:placetype":[
        "aat:300008680"
    ]
},
  "bbox": [],
  "geometry": {"coordinates":[-122.6333,47.4833],"type":"Point"}
}