{
  "id": 1071245,
  "type": "Feature",
  "properties": {
    "tgn:hierarchy":[
        "tgn:1071245",
        "tgn:1000004",
        "tgn:7002076",
        "tgn:1000111",
        "tgn:7029392"
    ],
    "tgn:id":1071245,
    "tgn:name":"Rui An",
    "tgn:placetype":[
        "aat:300008347"
    ]
},
  "bbox": [],
  "geometry": {"coordinates":[120.65,27.85],"type":"Point"}
}