{
  "id": 2333014,
  "type": "Feature",
  "properties": {
    "tgn:hierarchy":[
        "tgn:2333014",
        "tgn:1000001",
        "tgn:7012149",
        "tgn:1002986",
        "tgn:7007568",
        "tgn:7029392"
    ],
    "tgn:id":2333014,
    "tgn:name":"Fly Brook",
    "tgn:placetype":[
        "aat:300008699"
    ]
},
  "bbox": [],
  "geometry": {"coordinates":[-73.5333,43.7167],"type":"Point"}
}