<<<<<<< HEAD
{
  "id": 2333014,
  "type": "Feature",
  "properties": {
    "tgn:hierarchy":[
        "tgn:2333014",
        "tgn:1000001",
        "tgn:7012149",
        "tgn:1002986",
        "tgn:7007568",
        "tgn:7029392"
    ],
    "tgn:id":2333014,
    "tgn:name":"Fly Brook",
    "tgn:placetype":[
        "aat:300008699"
    ]
},
  "bbox": [],
  "geometry": {"coordinates":[-73.5333,43.7167],"type":"Point"}
}
=======
{"geometry":{"type":"Point","coordinates":[-73.533300,43.716700]},"type":"Feature","properties":{"hierarchy":["tgn:2333014","tgn:1000001","tgn:7012149","tgn:1002986","tgn:7007568","tgn:7029392"],"placetype":["aat:300008699"],"id":2333014,"name:xx":"Fly Brook"}}
>>>>>>> 03f74aca74312dbeaf24d7e61306dd6a786dc3d0
