<<<<<<< HEAD
{
  "id": 2158824,
  "type": "Feature",
  "properties": {
    "tgn:hierarchy":[
        "tgn:2158824",
        "tgn:2000090",
        "tgn:1000001",
        "tgn:7006451",
        "tgn:7012149",
        "tgn:7029392"
    ],
    "tgn:id":2158824,
    "tgn:name":"Becker Creek",
    "tgn:placetype":[
        "aat:300008706"
    ]
},
  "bbox": [],
  "geometry": {"coordinates":[-109.5667,33.95],"type":"Point"}
}
=======
{"geometry":{"type":"Point","coordinates":[-109.566700,33.950000]},"type":"Feature","properties":{"hierarchy":["tgn:2158824","tgn:2000090","tgn:1000001","tgn:7006451","tgn:7012149","tgn:7029392"],"placetype":["aat:300008706"],"id":2158824,"name:xx":"Becker Creek"}}
>>>>>>> 03f74aca74312dbeaf24d7e61306dd6a786dc3d0
