{
  "id": 2325012,
  "type": "Feature",
  "properties": {
    "tgn:hierarchy":[
        "tgn:2325012",
        "tgn:1000001",
        "tgn:7012149",
        "tgn:2001861",
        "tgn:7007825",
        "tgn:7029392"
    ],
    "tgn:id":2325012,
    "tgn:name":"Fern Camp Cave",
    "tgn:placetype":[
        "aat:300008746"
    ]
},
  "bbox": [],
  "geometry": {"coordinates":[-84.95,36.3667],"type":"Point"}
}