{
  "id": 2531556,
  "type": "Feature",
  "properties": {
    "tgn:hierarchy":[
        "tgn:2531556",
        "tgn:1000001",
        "tgn:7012149",
        "tgn:2002013",
        "tgn:7007826",
        "tgn:7029392"
    ],
    "tgn:id":2531556,
    "tgn:name":"Mule Tank",
    "tgn:placetype":[
        "aat:300006191"
    ]
},
  "bbox": [],
  "geometry": {"coordinates":[-98.1667,27.9833],"type":"Point"}
}