{
  "id": 7536086,
  "type": "Feature",
  "properties": {
    "tgn:hierarchy":[
        "tgn:7536086",
        "tgn:7001242",
        "tgn:7016833",
        "tgn:1001335",
        "tgn:7029392"
    ],
    "tgn:id":7536086,
    "tgn:name:en":"Khinz\u012br\u012b, Sayy\u0101\u1e29 al",
    "tgn:placetype":[
        "aat:300008903"
    ]
},
  "bbox": [],
  "geometry": {"coordinates":[30.916667,31.333333],"type":"Point"}
}