{
  "id": 2616816,
  "type": "Feature",
  "properties": {
    "tgn:hierarchy":[
        "tgn:2616816",
        "tgn:1000001",
        "tgn:7012149",
        "tgn:2002162",
        "tgn:7007919",
        "tgn:7029392"
    ],
    "tgn:id":2616816,
    "tgn:name":"Rich Hill",
    "tgn:placetype":[
        "aat:300008798"
    ]
},
  "bbox": [],
  "geometry": {"coordinates":[-80.65,37.2667],"type":"Point"}
}