{
  "id": 7396157,
  "type": "Feature",
  "properties": {
    "tgn:hierarchy":[
        "tgn:7396157",
        "tgn:1001853",
        "tgn:1000001",
        "tgn:7005560",
        "tgn:7029392"
    ],
    "tgn:id":7396157,
    "tgn:name":"San Juan",
    "tgn:placetype":[
        "aat:300008347"
    ]
},
  "bbox": [],
  "geometry": {"coordinates":[-103.533333,27.233333],"type":"Point"}
}