{
  "id": 7155680,
  "type": "Feature",
  "properties": {
    "tgn:hierarchy":[
        "tgn:7155680",
        "tgn:7003692",
        "tgn:1000003",
        "tgn:7000084",
        "tgn:7029392"
    ],
    "tgn:id":7155680,
    "tgn:name":"Kirchenbauer",
    "tgn:placetype":[
        "aat:300000206"
    ]
},
  "bbox": [],
  "geometry": {"coordinates":[9.95,47.95],"type":"Point"}
}