<<<<<<< HEAD
{
  "id": 7242200,
  "type": "Feature",
  "properties": {
    "tgn:hierarchy":[
        "tgn:7242200",
        "tgn:7003465",
        "tgn:1000003",
        "tgn:1000063",
        "tgn:4012014",
        "tgn:7029392"
    ],
    "tgn:id":7242200,
    "tgn:name":"Logne, Ry de",
    "tgn:placetype":[
        "aat:300008699"
    ]
},
  "bbox": [],
  "geometry": {"coordinates":[5.532644,50.398481],"type":"Point"}
}
=======
{"geometry":{"type":"Point","coordinates":[5.532644,50.398481]},"type":"Feature","properties":{"hierarchy":["tgn:7242200","tgn:7003465","tgn:1000003","tgn:1000063","tgn:4012014","tgn:7029392"],"placetype":["aat:300008699"],"id":7242200,"name:xx":"Logne, Ry de"}}
>>>>>>> 03f74aca74312dbeaf24d7e61306dd6a786dc3d0
