{
  "id": 7072632,
  "type": "Feature",
  "properties": {
    "tgn:hierarchy":[
        "tgn:7072632",
        "tgn:1000003",
        "tgn:7000094",
        "tgn:7000084",
        "tgn:7029392"
    ],
    "tgn:id":7072632,
    "tgn:name":"Tarnow",
    "tgn:placetype":[
        "aat:300008347"
    ]
},
  "bbox": [],
  "geometry": {"coordinates":[13.016667,53.616667],"type":"Point"}
}