{
  "id": 2360966,
  "type": "Feature",
  "properties": {
    "tgn:hierarchy":[
        "tgn:2360966",
        "tgn:1000001",
        "tgn:7012149",
        "tgn:7016021",
        "tgn:7007568",
        "tgn:7029392"
    ],
    "tgn:id":2360966,
    "tgn:name":"Grassy Pond",
    "tgn:placetype":[
        "aat:300008680"
    ]
},
  "bbox": [],
  "geometry": {"coordinates":[-74.4167,44.5167],"type":"Point"}
}