{
  "id": 7208614,
  "type": "Feature",
  "properties": {
    "tgn:hierarchy":[
        "tgn:7208614",
        "tgn:7003669",
        "tgn:1000003",
        "tgn:7000084",
        "tgn:7029392"
    ],
    "tgn:id":7208614,
    "tgn:name":"Berg",
    "tgn:placetype":[
        "aat:300008347"
    ]
},
  "bbox": [],
  "geometry": {"coordinates":[12.15,49.816667],"type":"Point"}
}