{
  "id": 2177604,
  "type": "Feature",
  "properties": {
    "tgn:hierarchy":[
        "tgn:2177604",
        "tgn:1000001",
        "tgn:7012149",
        "tgn:7007826",
        "tgn:7029392"
    ],
    "tgn:id":2177604,
    "tgn:name":"Black Slough",
    "tgn:placetype":[
        "aat:300008699"
    ]
},
  "bbox": [],
  "geometry": {"coordinates":[-94.4667,32.35],"type":"Point"}
}