{
  "id": 2301930,
  "type": "Feature",
  "properties": {
    "tgn:hierarchy":[
        "tgn:2301930",
        "tgn:1000001",
        "tgn:7012149",
        "tgn:2000849",
        "tgn:7007255",
        "tgn:7029392"
    ],
    "tgn:id":2301930,
    "tgn:name":"Durr Branch",
    "tgn:placetype":[
        "aat:300008699"
    ]
},
  "bbox": [],
  "geometry": {"coordinates":[-85.0333,37.8833],"type":"Point"}
}