<<<<<<< HEAD
{
  "id": 7245212,
  "type": "Feature",
  "properties": {
    "tgn:hierarchy":[
        "tgn:7245212",
        "tgn:7003466",
        "tgn:1000003",
        "tgn:1000063",
        "tgn:4012014",
        "tgn:7029392"
    ],
    "tgn:id":7245212,
    "tgn:name":"Achet",
    "tgn:placetype":[
        "aat:300008347"
    ]
},
  "bbox": [],
  "geometry": {"coordinates":[5.174619,50.333461],"type":"Point"}
}
=======
{"geometry":{"type":"Point","coordinates":[5.174619,50.333461]},"type":"Feature","properties":{"hierarchy":["tgn:7245212","tgn:7003466","tgn:1000003","tgn:1000063","tgn:4012014","tgn:7029392"],"placetype":["aat:300008347"],"id":7245212,"name:xx":"Achet"}}
>>>>>>> 03f74aca74312dbeaf24d7e61306dd6a786dc3d0
