{
  "id": 2491781,
  "type": "Feature",
  "properties": {
    "tgn:hierarchy":[
        "tgn:2491781",
        "tgn:1000001",
        "tgn:7012149",
        "tgn:2000428",
        "tgn:7007248",
        "tgn:7029392"
    ],
    "tgn:id":2491781,
    "tgn:name":"Mar-Jan Lake",
    "tgn:placetype":[
        "aat:300006191"
    ]
},
  "bbox": [],
  "geometry": {"coordinates":[-83.5667,31.5833],"type":"Point"}
}