{
  "id": 7397741,
  "type": "Feature",
  "properties": {
    "tgn:hierarchy":[
        "tgn:7397741",
        "tgn:1000001",
        "tgn:1001893",
        "tgn:7005560",
        "tgn:7029392"
    ],
    "tgn:id":7397741,
    "tgn:name":"La Herradura",
    "tgn:placetype":[
        "aat:300008347"
    ]
},
  "bbox": [],
  "geometry": {"coordinates":[-99.251944,19.422778],"type":"Point"}
}