{
  "id": 1041288,
  "type": "Feature",
  "properties": {
    "tgn:hierarchy":[
        "tgn:1041288",
        "tgn:1000003",
        "tgn:7003677",
        "tgn:7000084",
        "tgn:7029392"
    ],
    "tgn:id":1041288,
    "tgn:name":"Stadtlohn",
    "tgn:placetype":[
        "aat:300008347"
    ]
},
  "bbox": [],
  "geometry": {"coordinates":[6.933333,51.983333],"type":"Point"}
}