{
  "id": 5002502,
  "type": "Feature",
  "properties": {
    "tgn:hierarchy":[
        "tgn:5002502",
        "tgn:1000003",
        "tgn:7003236",
        "tgn:7003144",
        "tgn:1000080",
        "tgn:7029392"
    ],
    "tgn:id":5002502,
    "tgn:name":"Bergeggi, Isola di",
    "tgn:placetype":[
        "aat:300008791"
    ]
},
  "bbox": [],
  "geometry": {"coordinates":[8.45,44.233333],"type":"Point"}
}