{
  "id": 2052639,
  "type": "Feature",
  "properties": {
    "tgn:hierarchy":[
        "tgn:2052639",
        "tgn:1000001",
        "tgn:7012149",
        "tgn:2000980",
        "tgn:7007520",
        "tgn:7029392"
    ],
    "tgn:id":2052639,
    "tgn:name":"Merritt",
    "tgn:placetype":[
        "aat:300008347"
    ]
},
  "bbox": [],
  "geometry": {"coordinates":[-84.9333,44.3167],"type":"Point"}
}