{
  "id": 2157167,
  "type": "Feature",
  "properties": {
    "tgn:hierarchy":[
        "tgn:2157167",
        "tgn:7002659",
        "tgn:1000001",
        "tgn:7012149",
        "tgn:7029392"
    ],
    "tgn:id":2157167,
    "tgn:name":"Beaver Creek",
    "tgn:placetype":[
        "aat:300008706"
    ]
},
  "bbox": [],
  "geometry": {"coordinates":[-87.75,33.0833],"type":"Point"}
}