<<<<<<< HEAD
{
  "id": 7176010,
  "type": "Feature",
  "properties": {
    "tgn:hierarchy":[
        "tgn:7176010",
        "tgn:7003692",
        "tgn:1000003",
        "tgn:7000084",
        "tgn:7029392"
    ],
    "tgn:id":7176010,
    "tgn:name":"Greuthof",
    "tgn:placetype":[
        "aat:300004792"
    ]
},
  "bbox": [],
  "geometry": {"coordinates":[10.316667,48.916667],"type":"Point"}
}
=======
{"geometry":{"type":"Point","coordinates":[10.316667,48.916667]},"type":"Feature","properties":{"hierarchy":["tgn:7176010","tgn:7003692","tgn:1000003","tgn:7000084","tgn:7029392"],"placetype":["aat:300004792"],"id":7176010,"name:xx":"Greuthof"}}
>>>>>>> 03f74aca74312dbeaf24d7e61306dd6a786dc3d0
