{
  "id": 7176010,
  "type": "Feature",
  "properties": {
    "tgn:hierarchy":[
        "tgn:7176010",
        "tgn:7003692",
        "tgn:1000003",
        "tgn:7000084",
        "tgn:7029392"
    ],
    "tgn:id":7176010,
    "tgn:name":"Greuthof",
    "tgn:placetype":[
        "aat:300004792"
    ]
},
  "bbox": [],
  "geometry": {"coordinates":[10.316667,48.916667],"type":"Point"}
}