<<<<<<< HEAD
{
  "id": 2404341,
  "type": "Feature",
  "properties": {
    "tgn:hierarchy":[
        "tgn:2404341",
        "tgn:1002648",
        "tgn:1000001",
        "tgn:1007799",
        "tgn:7012149",
        "tgn:7007249",
        "tgn:7029392"
    ],
    "tgn:id":2404341,
    "tgn:name":"Huawai Bay",
    "tgn:placetype":[
        "aat:300132316"
    ]
},
  "bbox": [],
  "geometry": {"coordinates":[-156.9167,20.7333],"type":"Point"}
}
=======
{"geometry":{"type":"Point","coordinates":[-156.916700,20.733300]},"type":"Feature","properties":{"hierarchy":["tgn:2404341","tgn:1002648","tgn:1000001","tgn:1007799","tgn:7012149","tgn:7007249","tgn:7029392"],"placetype":["aat:300132316"],"id":2404341,"name:xx":"Huawai Bay"}}
>>>>>>> 03f74aca74312dbeaf24d7e61306dd6a786dc3d0
