{
  "id": 2144778,
  "type": "Feature",
  "properties": {
    "tgn:hierarchy":[
        "tgn:2144778",
        "tgn:1000001",
        "tgn:2001477",
        "tgn:7012149",
        "tgn:7007709",
        "tgn:7029392"
    ],
    "tgn:id":2144778,
    "tgn:name":"Bald Hill",
    "tgn:placetype":[
        "aat:300008798"
    ]
},
  "bbox": [],
  "geometry": {"coordinates":[-76.5833,34.6667],"type":"Point"}
}