{
  "id": 1117643,
  "type": "Feature",
  "properties": {
    "tgn:hierarchy":[
        "tgn:1117643",
        "tgn:7005685",
        "tgn:1000001",
        "tgn:7013154",
        "tgn:7029392"
    ],
    "tgn:id":1117643,
    "tgn:name":"Oxtongue Lake",
    "tgn:placetype":[
        "aat:300008680"
    ]
},
  "bbox": [],
  "geometry": {"coordinates":[-78.9167,45.3667],"type":"Point"}
}