{
  "id": 7000539,
  "type": "Feature",
  "properties": {
    "tgn:hierarchy":[
        "tgn:7000539",
        "tgn:7016534",
        "tgn:7001242",
        "tgn:1000182",
        "tgn:7029392"
    ],
    "tgn:id":7000539,
    "tgn:name":"Yola",
    "tgn:placetype":[
        "aat:300008347",
        "aat:300387221",
        "aat:300008375"
    ]
},
  "bbox": [],
  "geometry": {"coordinates":[12.5333,9.2333],"type":"Point"}
}