{
  "id": 2556108,
  "type": "Feature",
  "properties": {
    "tgn:hierarchy":[
        "tgn:2556108",
        "tgn:1000001",
        "tgn:7012149",
        "tgn:2001451",
        "tgn:7007566",
        "tgn:7029392"
    ],
    "tgn:id":2556108,
    "tgn:name":"Ojito Spring",
    "tgn:placetype":[
        "aat:300008697"
    ]
},
  "bbox": [],
  "geometry": {"coordinates":[-106.95,35.5833],"type":"Point"}
}