{
  "id": 7070191,
  "type": "Feature",
  "properties": {
    "tgn:hierarchy":[
        "tgn:7070191",
        "tgn:7003669",
        "tgn:1000003",
        "tgn:7000084",
        "tgn:7029392"
    ],
    "tgn:id":7070191,
    "tgn:name":"Steinberg",
    "tgn:placetype":[
        "aat:300008777"
    ]
},
  "bbox": [],
  "geometry": {"coordinates":[10.716667,49.983333],"type":"Point"}
}