{
  "id": 1127660,
  "type": "Feature",
  "properties": {
    "tgn:hierarchy":[
        "tgn:1127660",
        "tgn:7005735",
        "tgn:7005685",
        "tgn:1000001",
        "tgn:7029392"
    ],
    "tgn:id":1127660,
    "tgn:name":"Nechako, River",
    "tgn:placetype":[
        "aat:300008707"
    ]
},
  "bbox": [],
  "geometry": {"coordinates":[-122.7333,53.9167],"type":"Point"}
}