<<<<<<< HEAD
{
  "id": 7242804,
  "type": "Feature",
  "properties": {
    "tgn:hierarchy":[
        "tgn:7242804",
        "tgn:7003460",
        "tgn:1000003",
        "tgn:1000063",
        "tgn:4012014",
        "tgn:7029392"
    ],
    "tgn:id":7242804,
    "tgn:name":"La Neuville",
    "tgn:placetype":[
        "aat:300008347"
    ]
},
  "bbox": [],
  "geometry": {"coordinates":[5.666667,50.666667],"type":"Point"}
}
=======
{"geometry":{"type":"Point","coordinates":[5.666667,50.666667]},"type":"Feature","properties":{"hierarchy":["tgn:7242804","tgn:7003460","tgn:1000003","tgn:1000063","tgn:4012014","tgn:7029392"],"placetype":["aat:300008347"],"id":7242804,"name:xx":"La Neuville"}}
>>>>>>> 03f74aca74312dbeaf24d7e61306dd6a786dc3d0
