{
  "id": 2061362,
  "type": "Feature",
  "properties": {
    "tgn:hierarchy":[
        "tgn:2061362",
        "tgn:1000001",
        "tgn:7012149",
        "tgn:2001309",
        "tgn:7007524",
        "tgn:7029392"
    ],
    "tgn:id":2061362,
    "tgn:name":"Golden Ridge",
    "tgn:placetype":[
        "aat:300008347",
        "aat:300387210"
    ]
},
  "bbox": [],
  "geometry": {"coordinates":[-112.2167,47.5667],"type":"Point"}
}