{
  "id": 2748830,
  "type": "Feature",
  "properties": {
    "tgn:hierarchy":[
        "tgn:2748830",
        "tgn:1000001",
        "tgn:7012149",
        "tgn:2000412",
        "tgn:7007248",
        "tgn:7029392"
    ],
    "tgn:id":2748830,
    "tgn:name":"Walkinshaw",
    "tgn:placetype":[
        "aat:300008347"
    ]
},
  "bbox": [],
  "geometry": {"coordinates":[-81.8833,33.2667],"type":"Point"}
}