{
  "id": 7236986,
  "type": "Feature",
  "properties": {
    "tgn:hierarchy":[
        "tgn:7236986",
        "tgn:7002745",
        "tgn:7017076",
        "tgn:1000003",
        "tgn:1000074",
        "tgn:7029392"
    ],
    "tgn:id":7236986,
    "tgn:name":"Elaf\u00f3nisos, Nis\u00eds",
    "tgn:placetype":[
        "aat:300008791"
    ]
},
  "bbox": [],
  "geometry": {"coordinates":[22.966667,36.483333],"type":"Point"}
}