{
  "id": 7488493,
  "type": "Feature",
  "properties": {
    "tgn:hierarchy":[
        "tgn:7488493",
        "tgn:7468018",
        "tgn:1000004",
        "tgn:1000141",
        "tgn:7029392"
    ],
    "tgn:id":7488493,
    "tgn:name":"Lulin Shan",
    "tgn:placetype":[
        "aat:300008798"
    ]
},
  "bbox": [],
  "geometry": {"coordinates":[120.87159,23.46081],"type":"Point"}
}