<<<<<<< HEAD
{
  "id": 7488493,
  "type": "Feature",
  "properties": {
    "tgn:hierarchy":[
        "tgn:7488493",
        "tgn:7468018",
        "tgn:1000004",
        "tgn:1000141",
        "tgn:7029392"
    ],
    "tgn:id":7488493,
    "tgn:name":"Lulin Shan",
    "tgn:placetype":[
        "aat:300008798"
    ]
},
  "bbox": [],
  "geometry": {"coordinates":[120.87159,23.46081],"type":"Point"}
}
=======
{"geometry":{"type":"Point","coordinates":[120.871590,23.460810]},"type":"Feature","properties":{"hierarchy":["tgn:7488493","tgn:7468018","tgn:1000004","tgn:1000141","tgn:7029392"],"placetype":["aat:300008798"],"id":7488493,"name:xx":"Lulin Shan"}}
>>>>>>> 03f74aca74312dbeaf24d7e61306dd6a786dc3d0
