{
  "id": 7570081,
  "type": "Feature",
  "properties": {
    "tgn:hierarchy":[
        "tgn:7570081",
        "tgn:1000004",
        "tgn:7000198",
        "tgn:7016788",
        "tgn:7029392"
    ],
    "tgn:id":7570081,
    "tgn:name:en":"Baneria",
    "tgn:placetype":[
        "aat:300008347"
    ]
},
  "bbox": [],
  "geometry": {"coordinates":[75.533706,25.897429],"type":"Point"}
}