{
  "id": 7096492,
  "type": "Feature",
  "properties": {
    "tgn:hierarchy":[
        "tgn:7096492",
        "tgn:1000003",
        "tgn:7003676",
        "tgn:7000084",
        "tgn:7029392"
    ],
    "tgn:id":7096492,
    "tgn:name":"Sehl-Berg",
    "tgn:placetype":[
        "aat:300008777"
    ]
},
  "bbox": [],
  "geometry": {"coordinates":[8.166667,52.216667],"type":"Point"}
}