<<<<<<< HEAD
{
  "id": 2258337,
  "type": "Feature",
  "properties": {
    "tgn:hierarchy":[
        "tgn:2258337",
        "tgn:1000001",
        "tgn:2001816",
        "tgn:7012149",
        "tgn:7007713",
        "tgn:7029392"
    ],
    "tgn:id":2258337,
    "tgn:name":"Cottle Creek",
    "tgn:placetype":[
        "aat:300008706"
    ]
},
  "bbox": [],
  "geometry": {"coordinates":[-103.4333,44.3833],"type":"Point"}
}
=======
{"geometry":{"type":"Point","coordinates":[-103.433300,44.383300]},"type":"Feature","properties":{"hierarchy":["tgn:2258337","tgn:1000001","tgn:2001816","tgn:7012149","tgn:7007713","tgn:7029392"],"placetype":["aat:300008706"],"id":2258337,"name:xx":"Cottle Creek"}}
>>>>>>> 03f74aca74312dbeaf24d7e61306dd6a786dc3d0
