{
  "id": 2258337,
  "type": "Feature",
  "properties": {
    "tgn:hierarchy":[
        "tgn:2258337",
        "tgn:1000001",
        "tgn:2001816",
        "tgn:7012149",
        "tgn:7007713",
        "tgn:7029392"
    ],
    "tgn:id":2258337,
    "tgn:name":"Cottle Creek",
    "tgn:placetype":[
        "aat:300008706"
    ]
},
  "bbox": [],
  "geometry": {"coordinates":[-103.4333,44.3833],"type":"Point"}
}