{
  "id": 7456263,
  "type": "Feature",
  "properties": {
    "tgn:hierarchy":[
        "tgn:7456263",
        "tgn:7002448",
        "tgn:7019217",
        "tgn:1000003",
        "tgn:7008591",
        "tgn:7029392"
    ],
    "tgn:id":7456263,
    "tgn:name:en":"Carnanelly",
    "tgn:placetype":[
        "aat:300008795"
    ]
},
  "bbox": [],
  "geometry": {"coordinates":[-6.916667,54.75],"type":"Point"}
}