{
  "id": 7077125,
  "type": "Feature",
  "properties": {
    "tgn:hierarchy":[
        "tgn:7077125",
        "tgn:7003669",
        "tgn:1000003",
        "tgn:7000084",
        "tgn:7029392"
    ],
    "tgn:id":7077125,
    "tgn:name":"Zieglerberg",
    "tgn:placetype":[
        "aat:300008777"
    ]
},
  "bbox": [],
  "geometry": {"coordinates":[10.216667,48.083333],"type":"Point"}
}