{
  "id": 2464384,
  "type": "Feature",
  "properties": {
    "tgn:hierarchy":[
        "tgn:2464384",
        "tgn:1000001",
        "tgn:2000950",
        "tgn:7012149",
        "tgn:7007520",
        "tgn:7029392"
    ],
    "tgn:id":2464384,
    "tgn:name":"Loeb Creek",
    "tgn:placetype":[
        "aat:300008706"
    ]
},
  "bbox": [],
  "geometry": {"coordinates":[-85.2333,45.25],"type":"Point"}
}