{
  "id": 2716063,
  "type": "Feature",
  "properties": {
    "tgn:hierarchy":[
        "tgn:2716063",
        "tgn:1000001",
        "tgn:7012149",
        "tgn:2001872",
        "tgn:7007825",
        "tgn:7029392"
    ],
    "tgn:id":2716063,
    "tgn:name":"Thacker Branch",
    "tgn:placetype":[
        "aat:300008699"
    ]
},
  "bbox": [],
  "geometry": {"coordinates":[-88.1167,35.3167],"type":"Point"}
}