{
  "id": 7374735,
  "type": "Feature",
  "properties": {
    "tgn:hierarchy":[
        "tgn:7374735",
        "tgn:1000001",
        "tgn:7005597",
        "tgn:7005560",
        "tgn:7029392"
    ],
    "tgn:id":7374735,
    "tgn:name":"La Borbolla",
    "tgn:placetype":[
        "aat:300008347"
    ]
},
  "bbox": [],
  "geometry": {"coordinates":[-98.766667,24.066667],"type":"Point"}
}