{
  "id": 2331744,
  "type": "Feature",
  "properties": {
    "tgn:hierarchy":[
        "tgn:2331744",
        "tgn:1000001",
        "tgn:7012149",
        "tgn:1003003",
        "tgn:7007251",
        "tgn:7029392"
    ],
    "tgn:id":2331744,
    "tgn:name":"Fleming Ridge",
    "tgn:placetype":[
        "aat:300266640"
    ]
},
  "bbox": [],
  "geometry": {"coordinates":[-88.5167,38.3167],"type":"Point"}
}