{
  "id": 2512193,
  "type": "Feature",
  "properties": {
    "tgn:hierarchy":[
        "tgn:2512193",
        "tgn:1000001",
        "tgn:7012149",
        "tgn:1002590",
        "tgn:7007826",
        "tgn:7029392"
    ],
    "tgn:id":2512193,
    "tgn:name":"Mill Branch",
    "tgn:placetype":[
        "aat:300008699"
    ]
},
  "bbox": [],
  "geometry": {"coordinates":[-96.25,31.1333],"type":"Point"}
}