{
  "id": 7337838,
  "type": "Feature",
  "properties": {
    "tgn:hierarchy":[
        "tgn:7337838",
        "tgn:7002815",
        "tgn:1000003",
        "tgn:7002793",
        "tgn:1000095",
        "tgn:7029392"
    ],
    "tgn:id":7337838,
    "tgn:name":"Cervera del Maestre",
    "tgn:placetype":[
        "aat:300008347"
    ]
},
  "bbox": [],
  "geometry": {"coordinates":[0.283333,40.45],"type":"Point"}
}