<<<<<<< HEAD
{
  "id": 7479196,
  "type": "Feature",
  "properties": {
    "tgn:hierarchy":[
        "tgn:7479196",
        "tgn:1000004",
        "tgn:7490934",
        "tgn:1000141",
        "tgn:7029392"
    ],
    "tgn:id":7479196,
    "tgn:name":"Nan'an Qiao",
    "tgn:placetype":[
        "aat:300007836"
    ]
},
  "bbox": [],
  "geometry": {"coordinates":[120.223889,23.096111],"type":"Point"}
}
=======
{"geometry":{"type":"Point","coordinates":[120.223889,23.096111]},"type":"Feature","properties":{"hierarchy":["tgn:7479196","tgn:1000004","tgn:7490934","tgn:1000141","tgn:7029392"],"placetype":["aat:300007836"],"id":7479196,"name:xx":"Nan'an Qiao"}}
>>>>>>> 03f74aca74312dbeaf24d7e61306dd6a786dc3d0
