{
  "id": 2519377,
  "type": "Feature",
  "properties": {
    "tgn:hierarchy":[
        "tgn:2519377",
        "tgn:2000456",
        "tgn:1000001",
        "tgn:7012149",
        "tgn:7007250",
        "tgn:7029392"
    ],
    "tgn:id":2519377,
    "tgn:name":"Moctileme Creek",
    "tgn:placetype":[
        "aat:300008706"
    ]
},
  "bbox": [],
  "geometry": {"coordinates":[-116.8333,47.2333],"type":"Point"}
}