{
  "id": 2754075,
  "type": "Feature",
  "properties": {
    "tgn:hierarchy":[
        "tgn:2754075",
        "tgn:1000001",
        "tgn:7012149",
        "tgn:2002166",
        "tgn:7007919",
        "tgn:7029392"
    ],
    "tgn:id":2754075,
    "tgn:name":"Watson Pond",
    "tgn:placetype":[
        "aat:300006191"
    ]
},
  "bbox": [],
  "geometry": {"coordinates":[-79.1667,36.6333],"type":"Point"}
}