{
  "id": 2344191,
  "type": "Feature",
  "properties": {
    "tgn:hierarchy":[
        "tgn:2344191",
        "tgn:1000001",
        "tgn:7012149",
        "tgn:1002899",
        "tgn:7007920",
        "tgn:7029392"
    ],
    "tgn:id":2344191,
    "tgn:name":"Gamma Peak",
    "tgn:placetype":[
        "aat:300008798"
    ]
},
  "bbox": [],
  "geometry": {"coordinates":[-121.0667,48.1333],"type":"Point"}
}