{
  "id": 1024219,
  "type": "Feature",
  "properties": {
    "tgn:hierarchy":[
        "tgn:1024219",
        "tgn:7002565",
        "tgn:1000054",
        "tgn:1000002",
        "tgn:7029392"
    ],
    "tgn:id":1024219,
    "tgn:name":"Mabaruma",
    "tgn:placetype":[
        "aat:300008347",
        "aat:300387220",
        "aat:300008375"
    ]
},
  "bbox": [],
  "geometry": {"coordinates":[-59.85,8.15],"type":"Point"}
}