<<<<<<< HEAD
{
  "id": 2762013,
  "type": "Feature",
  "properties": {
    "tgn:hierarchy":[
        "tgn:2762013",
        "tgn:1000001",
        "tgn:7012149",
        "tgn:2001876",
        "tgn:7007825",
        "tgn:7029392"
    ],
    "tgn:id":2762013,
    "tgn:name":"West Sandy Creek Drainage Ditch",
    "tgn:placetype":[
        "aat:300006075"
    ]
},
  "bbox": [],
  "geometry": {"coordinates":[-88.1833,36.2667],"type":"Point"}
}
=======
{"geometry":{"type":"Point","coordinates":[-88.183300,36.266700]},"type":"Feature","properties":{"hierarchy":["tgn:2762013","tgn:1000001","tgn:7012149","tgn:2001876","tgn:7007825","tgn:7029392"],"placetype":["aat:300006075"],"id":2762013,"name:xx":"West Sandy Creek Drainage Ditch"}}
>>>>>>> 03f74aca74312dbeaf24d7e61306dd6a786dc3d0
