{
  "id": 2762013,
  "type": "Feature",
  "properties": {
    "tgn:hierarchy":[
        "tgn:2762013",
        "tgn:1000001",
        "tgn:7012149",
        "tgn:2001876",
        "tgn:7007825",
        "tgn:7029392"
    ],
    "tgn:id":2762013,
    "tgn:name":"West Sandy Creek Drainage Ditch",
    "tgn:placetype":[
        "aat:300006075"
    ]
},
  "bbox": [],
  "geometry": {"coordinates":[-88.1833,36.2667],"type":"Point"}
}