{
  "id": 2718764,
  "type": "Feature",
  "properties": {
    "tgn:hierarchy":[
        "tgn:2718764",
        "tgn:1000001",
        "tgn:7012149",
        "tgn:2000491",
        "tgn:7007250",
        "tgn:7029392"
    ],
    "tgn:id":2718764,
    "tgn:name":"Thor Mountain",
    "tgn:placetype":[
        "aat:300008798"
    ]
},
  "bbox": [],
  "geometry": {"coordinates":[-115.5667,47.15],"type":"Point"}
}