{
  "id": 2086624,
  "type": "Feature",
  "properties": {
    "tgn:hierarchy":[
        "tgn:2086624",
        "tgn:1000001",
        "tgn:7012149",
        "tgn:1002932",
        "tgn:7007710",
        "tgn:7029392"
    ],
    "tgn:id":2086624,
    "tgn:name":"Brandt",
    "tgn:placetype":[
        "aat:300008347"
    ]
},
  "bbox": [],
  "geometry": {"coordinates":[-75.5333,41.95],"type":"Point"}
}