{
  "id": 1032418,
  "type": "Feature",
  "properties": {
    "tgn:hierarchy":[
        "tgn:1032418",
        "tgn:1000003",
        "tgn:7002888",
        "tgn:1000070",
        "tgn:7029392"
    ],
    "tgn:id":1032418,
    "tgn:name":"Carling",
    "tgn:placetype":[
        "aat:300008347"
    ]
},
  "bbox": [],
  "geometry": {"coordinates":[6.7167,49.1667],"type":"Point"}
}