{
  "id": 7097834,
  "type": "Feature",
  "properties": {
    "tgn:hierarchy":[
        "tgn:7097834",
        "tgn:1000003",
        "tgn:7003682",
        "tgn:7000084",
        "tgn:7029392"
    ],
    "tgn:id":7097834,
    "tgn:name":"Sessenhausen",
    "tgn:placetype":[
        "aat:300008347"
    ]
},
  "bbox": [],
  "geometry": {"coordinates":[7.716667,50.533333],"type":"Point"}
}