{
  "id": 7577621,
  "type": "Feature",
  "properties": {
    "tgn:hierarchy":[
        "tgn:7577621",
        "tgn:1000004",
        "tgn:7000198",
        "tgn:1001996",
        "tgn:7029392"
    ],
    "tgn:id":7577621,
    "tgn:name:en":"Kulag",
    "tgn:placetype":[
        "aat:300008347"
    ]
},
  "bbox": [],
  "geometry": {"coordinates":[77.557177,30.805653],"type":"Point"}
}