{
  "id": 2080249,
  "type": "Feature",
  "properties": {
    "tgn:hierarchy":[
        "tgn:2080249",
        "tgn:1000001",
        "tgn:7012149",
        "tgn:1002784",
        "tgn:7007706",
        "tgn:7029392"
    ],
    "tgn:id":2080249,
    "tgn:name":"Knollwood Village",
    "tgn:placetype":[
        "aat:300008347"
    ]
},
  "bbox": [],
  "geometry": {"coordinates":[-82.8833,39.6167],"type":"Point"}
}