{
  "id": 2292898,
  "type": "Feature",
  "properties": {
    "tgn:hierarchy":[
        "tgn:2292898",
        "tgn:7002659",
        "tgn:1000001",
        "tgn:7012149",
        "tgn:2000021",
        "tgn:7029392"
    ],
    "tgn:id":2292898,
    "tgn:name":"Dorsey Creek Valley",
    "tgn:placetype":[
        "aat:300008761"
    ]
},
  "bbox": [],
  "geometry": {"coordinates":[-86.95,33.9833],"type":"Point"}
}