{
  "id": 2592613,
  "type": "Feature",
  "properties": {
    "tgn:hierarchy":[
        "tgn:2592613",
        "tgn:7002659",
        "tgn:1000001",
        "tgn:7012149",
        "tgn:2000060",
        "tgn:7029392"
    ],
    "tgn:id":2592613,
    "tgn:name":"Poorhouse Branch",
    "tgn:placetype":[
        "aat:300008699"
    ]
},
  "bbox": [],
  "geometry": {"coordinates":[-86.1167,33.4833],"type":"Point"}
}