{
  "id": 7381953,
  "type": "Feature",
  "properties": {
    "tgn:hierarchy":[
        "tgn:7381953",
        "tgn:1000001",
        "tgn:7005593",
        "tgn:7005560",
        "tgn:7029392"
    ],
    "tgn:id":7381953,
    "tgn:name":"Mancha",
    "tgn:placetype":[
        "aat:300008347"
    ]
},
  "bbox": [],
  "geometry": {"coordinates":[-99.483333,20.916667],"type":"Point"}
}