{
  "id": 7466177,
  "type": "Feature",
  "properties": {
    "tgn:hierarchy":[
        "tgn:7466177",
        "tgn:7019094",
        "tgn:7002444",
        "tgn:1000003",
        "tgn:7008591",
        "tgn:7029392"
    ],
    "tgn:id":7466177,
    "tgn:name:en":"Ardmaddy Bay",
    "tgn:placetype":[
        "aat:300132316"
    ]
},
  "bbox": [],
  "geometry": {"coordinates":[-5.583333,56.283333],"type":"Point"}
}