{
  "id": 2198299,
  "type": "Feature",
  "properties": {
    "tgn:hierarchy":[
        "tgn:2198299",
        "tgn:1000001",
        "tgn:7016172",
        "tgn:7012149",
        "tgn:7029392"
    ],
    "tgn:id":2198299,
    "tgn:name":"Browns Creek",
    "tgn:placetype":[
        "aat:300008706"
    ]
},
  "bbox": [],
  "geometry": {"coordinates":[-91.2667,36.2833],"type":"Point"}
}