{
  "id": 1118988,
  "type": "Feature",
  "properties": {
    "tgn:hierarchy":[
        "tgn:1118988",
        "tgn:1002075",
        "tgn:1000004",
        "tgn:1000140",
        "tgn:7029392"
    ],
    "tgn:id":1118988,
    "tgn:name":"Raw\u1e0dah",
    "tgn:placetype":[
        "aat:300266556"
    ]
},
  "bbox": [],
  "geometry": {"coordinates":[41.0833,35.25],"type":"Point"}
}