{
  "id": 7296247,
  "type": "Feature",
  "properties": {
    "tgn:hierarchy":[
        "tgn:7296247",
        "tgn:7002758",
        "tgn:7002841",
        "tgn:1000003",
        "tgn:1000095",
        "tgn:7029392"
    ],
    "tgn:id":7296247,
    "tgn:name":"Colector Sur",
    "tgn:placetype":[
        "aat:300006075"
    ]
},
  "bbox": [],
  "geometry": {"coordinates":[-6.178056,36.9575],"type":"Point"}
}