{
  "id": 7222129,
  "type": "Feature",
  "properties": {
    "tgn:hierarchy":[
        "tgn:7222129",
        "tgn:7002707",
        "tgn:7002705",
        "tgn:1000003",
        "tgn:1000074",
        "tgn:7029392"
    ],
    "tgn:id":7222129,
    "tgn:name":"Mikr\u00e1 G\u00f3tista",
    "tgn:placetype":[
        "aat:300008347"
    ]
},
  "bbox": [],
  "geometry": {"coordinates":[21.038333,39.691389],"type":"Point"}
}