{
  "id": 7406040,
  "type": "Feature",
  "properties": {
    "tgn:hierarchy":[
        "tgn:7406040",
        "tgn:7005585",
        "tgn:1000001",
        "tgn:7005560",
        "tgn:7029392"
    ],
    "tgn:id":7406040,
    "tgn:name":"Los Bejucos",
    "tgn:placetype":[
        "aat:300008347"
    ]
},
  "bbox": [],
  "geometry": {"coordinates":[-101.533333,18.483333],"type":"Point"}
}