{
  "id": 7493774,
  "type": "Feature",
  "properties": {
    "tgn:hierarchy":[
        "tgn:7493774",
        "tgn:1000004",
        "tgn:7491221",
        "tgn:1000141",
        "tgn:7029392"
    ],
    "tgn:id":7493774,
    "tgn:name":"Ningbu Xi",
    "tgn:placetype":[
        "aat:300008699"
    ]
},
  "bbox": [],
  "geometry": {"coordinates":[121.417819,23.244333],"type":"Point"}
}