{
  "id": 7095272,
  "type": "Feature",
  "properties": {
    "tgn:hierarchy":[
        "tgn:7095272",
        "tgn:7003669",
        "tgn:1000003",
        "tgn:7000084",
        "tgn:7029392"
    ],
    "tgn:id":7095272,
    "tgn:name":"Schwarzenbach am Wald",
    "tgn:placetype":[
        "aat:300008347"
    ]
},
  "bbox": [],
  "geometry": {"coordinates":[11.616667,50.283333],"type":"Point"}
}