{
  "id": 2454800,
  "type": "Feature",
  "properties": {
    "tgn:hierarchy":[
        "tgn:2454800",
        "tgn:1000001",
        "tgn:7012149",
        "tgn:2002098",
        "tgn:7007826",
        "tgn:7029392"
    ],
    "tgn:id":2454800,
    "tgn:name":"Little Dry Creek",
    "tgn:placetype":[
        "aat:300008706"
    ]
},
  "bbox": [],
  "geometry": {"coordinates":[-98.5167,33.15],"type":"Point"}
}