<<<<<<< HEAD
{
  "id": 2152518,
  "type": "Feature",
  "properties": {
    "tgn:hierarchy":[
        "tgn:2152518",
        "tgn:1002933",
        "tgn:1000001",
        "tgn:7012149",
        "tgn:7007239",
        "tgn:7029392"
    ],
    "tgn:id":2152518,
    "tgn:name":"Bay View Estates",
    "tgn:placetype":[
        "aat:300008347"
    ]
},
  "bbox": [],
  "geometry": {"coordinates":[-75.1167,38.45],"type":"Point"}
}
=======
{"geometry":{"type":"Point","coordinates":[-75.116700,38.450000]},"type":"Feature","properties":{"hierarchy":["tgn:2152518","tgn:1002933","tgn:1000001","tgn:7012149","tgn:7007239","tgn:7029392"],"placetype":["aat:300008347"],"id":2152518,"name:xx":"Bay View Estates"}}
>>>>>>> 03f74aca74312dbeaf24d7e61306dd6a786dc3d0
