{
  "id": 1039107,
  "type": "Feature",
  "properties": {
    "tgn:hierarchy":[
        "tgn:1039107",
        "tgn:1000003",
        "tgn:7003677",
        "tgn:7000084",
        "tgn:7029392"
    ],
    "tgn:id":1039107,
    "tgn:name":"Fr\u00f6nsberg",
    "tgn:placetype":[
        "aat:300008347"
    ]
},
  "bbox": [],
  "geometry": {"coordinates":[7.916667,51.35],"type":"Point"}
}