{
  "id": 7461501,
  "type": "Feature",
  "properties": {
    "tgn:hierarchy":[
        "tgn:7461501",
        "tgn:7002444",
        "tgn:1000003",
        "tgn:7029508",
        "tgn:7008591",
        "tgn:7029392"
    ],
    "tgn:id":7461501,
    "tgn:name:en":"Kame, The",
    "tgn:placetype":[
        "aat:300008850"
    ]
},
  "bbox": [],
  "geometry": {"coordinates":[-1.383333,59.916667],"type":"Point"}
}