{
  "id": 2383627,
  "type": "Feature",
  "properties": {
    "tgn:hierarchy":[
        "tgn:2383627",
        "tgn:1000001",
        "tgn:7012149",
        "tgn:2001763",
        "tgn:7007712",
        "tgn:7029392"
    ],
    "tgn:id":2383627,
    "tgn:name":"Heathwood",
    "tgn:placetype":[
        "aat:300008347"
    ]
},
  "bbox": [],
  "geometry": {"coordinates":[-82.5333,34.8333],"type":"Point"}
}