{
  "id": 2295539,
  "type": "Feature",
  "properties": {
    "tgn:hierarchy":[
        "tgn:2295539",
        "tgn:1000001",
        "tgn:2001435",
        "tgn:7012149",
        "tgn:7007566",
        "tgn:7029392"
    ],
    "tgn:id":2295539,
    "tgn:name":"Dripping Spring Tank",
    "tgn:placetype":[
        "aat:300006191"
    ]
},
  "bbox": [],
  "geometry": {"coordinates":[-106.55,32.25],"type":"Point"}
}