{
  "id": 2676035,
  "type": "Feature",
  "properties": {
    "tgn:hierarchy":[
        "tgn:2676035",
        "tgn:1000001",
        "tgn:7012149",
        "tgn:2002378",
        "tgn:7007923",
        "tgn:7029392"
    ],
    "tgn:id":2676035,
    "tgn:name":"Sorem Number 1 Reservoir",
    "tgn:placetype":[
        "aat:300006191"
    ]
},
  "bbox": [],
  "geometry": {"coordinates":[-104.2667,43.1833],"type":"Point"}
}