{
  "id": 7561180,
  "type": "Feature",
  "properties": {
    "tgn:hierarchy":[
        "tgn:7561180",
        "tgn:1000004",
        "tgn:7000198",
        "tgn:7016722",
        "tgn:7029392"
    ],
    "tgn:id":7561180,
    "tgn:name:en":"Kaly\u0101npur R\u0101han",
    "tgn:placetype":[
        "aat:300008347"
    ]
},
  "bbox": [],
  "geometry": {"coordinates":[79.099468,26.914919],"type":"Point"}
}