{
  "id": 7132767,
  "type": "Feature",
  "properties": {
    "tgn:hierarchy":[
        "tgn:7132767",
        "tgn:1000003",
        "tgn:7000094",
        "tgn:7000084",
        "tgn:7029392"
    ],
    "tgn:id":7132767,
    "tgn:name":"Morgenitz",
    "tgn:placetype":[
        "aat:300008347"
    ]
},
  "bbox": [],
  "geometry": {"coordinates":[13.966667,53.933333],"type":"Point"}
}