{
  "id": 2491682,
  "type": "Feature",
  "properties": {
    "tgn:hierarchy":[
        "tgn:2491682",
        "tgn:1000001",
        "tgn:1003028",
        "tgn:7012149",
        "tgn:7007159",
        "tgn:7029392"
    ],
    "tgn:id":2491682,
    "tgn:name":"Maple Swamp",
    "tgn:placetype":[
        "aat:300008905"
    ]
},
  "bbox": [],
  "geometry": {"coordinates":[-72.0333,41.8333],"type":"Point"}
}