{
  "id": 2568487,
  "type": "Feature",
  "properties": {
    "tgn:hierarchy":[
        "tgn:2568487",
        "tgn:1000001",
        "tgn:7012149",
        "tgn:1002785",
        "tgn:7007920",
        "tgn:7029392"
    ],
    "tgn:id":2568487,
    "tgn:name":"Park Marsh",
    "tgn:placetype":[
        "aat:300008905"
    ]
},
  "bbox": [],
  "geometry": {"coordinates":[-122.5667,47.1167],"type":"Point"}
}