{
  "id": 7064911,
  "type": "Feature",
  "properties": {
    "tgn:hierarchy":[
        "tgn:7064911",
        "tgn:1000003",
        "tgn:7003682",
        "tgn:7000084",
        "tgn:7029392"
    ],
    "tgn:id":7064911,
    "tgn:name":"Steinshof",
    "tgn:placetype":[
        "aat:300000206"
    ]
},
  "bbox": [],
  "geometry": {"coordinates":[6.266667,49.983333],"type":"Point"}
}