{
  "id": 2353299,
  "type": "Feature",
  "properties": {
    "tgn:hierarchy":[
        "tgn:2353299",
        "tgn:1000001",
        "tgn:7006451",
        "tgn:7012149",
        "tgn:2000099",
        "tgn:7029392"
    ],
    "tgn:id":2353299,
    "tgn:name":"Gold Butte",
    "tgn:placetype":[
        "aat:300008798"
    ]
},
  "bbox": [],
  "geometry": {"coordinates":[-109.9333,33.8667],"type":"Point"}
}