{
  "id": 7274381,
  "type": "Feature",
  "properties": {
    "tgn:hierarchy":[
        "tgn:7274381",
        "tgn:1000003",
        "tgn:7003624",
        "tgn:7016845",
        "tgn:7029392"
    ],
    "tgn:id":7274381,
    "tgn:name:nl":"Zwarte Horst",
    "tgn:placetype":[
        "aat:300008187"
    ]
},
  "bbox": [],
  "geometry": {"coordinates":[5.266667,51.266667],"type":"Point"}
}