{
  "id": 7450528,
  "type": "Feature",
  "properties": {
    "tgn:hierarchy":[
        "tgn:7450528",
        "tgn:7002445",
        "tgn:1000003",
        "tgn:7008175",
        "tgn:7008591",
        "tgn:7029392"
    ],
    "tgn:id":7450528,
    "tgn:name:en":"Gibbet Hill",
    "tgn:placetype":[
        "aat:300008777"
    ]
},
  "bbox": [],
  "geometry": {"coordinates":[-0.716667,51.116667],"type":"Point"}
}