{
  "id": 2473556,
  "type": "Feature",
  "properties": {
    "tgn:hierarchy":[
        "tgn:2473556",
        "tgn:1000001",
        "tgn:2000470",
        "tgn:7012149",
        "tgn:7007250",
        "tgn:7029392"
    ],
    "tgn:id":2473556,
    "tgn:name":"Lower Cramer Lake",
    "tgn:placetype":[
        "aat:300008680"
    ]
},
  "bbox": [],
  "geometry": {"coordinates":[-114.9833,44.0333],"type":"Point"}
}