{
  "id": 2436067,
  "type": "Feature",
  "properties": {
    "tgn:hierarchy":[
        "tgn:2436067",
        "tgn:1000001",
        "tgn:7012149",
        "tgn:2000430",
        "tgn:7007248",
        "tgn:7029392"
    ],
    "tgn:id":2436067,
    "tgn:name":"Keys Branch",
    "tgn:placetype":[
        "aat:300008699"
    ]
},
  "bbox": [],
  "geometry": {"coordinates":[-83.8167,34.95],"type":"Point"}
}