{
  "id": 7332803,
  "type": "Feature",
  "properties": {
    "tgn:hierarchy":[
        "tgn:7332803",
        "tgn:7002836",
        "tgn:7016622",
        "tgn:1000003",
        "tgn:1000095",
        "tgn:7029392"
    ],
    "tgn:id":7332803,
    "tgn:name":"Infierno, Cueva del",
    "tgn:placetype":[
        "aat:300008746"
    ]
},
  "bbox": [],
  "geometry": {"coordinates":[-17.716667,28.75],"type":"Point"}
}