<<<<<<< HEAD
{
  "id": 7484544,
  "type": "Feature",
  "properties": {
    "tgn:hierarchy":[
        "tgn:7484544",
        "tgn:1000004",
        "tgn:7492971",
        "tgn:1000141",
        "tgn:7029392"
    ],
    "tgn:id":7484544,
    "tgn:name":"Jiadong Shifan Gongmu",
    "tgn:placetype":[
        "aat:300266755"
    ]
},
  "bbox": [],
  "geometry": {"coordinates":[120.563056,22.441389],"type":"Point"}
}
=======
{"geometry":{"type":"Point","coordinates":[120.563056,22.441389]},"type":"Feature","properties":{"hierarchy":["tgn:7484544","tgn:1000004","tgn:7492971","tgn:1000141","tgn:7029392"],"placetype":["aat:300266755"],"id":7484544,"name:xx":"Jiadong Shifan Gongmu"}}
>>>>>>> 03f74aca74312dbeaf24d7e61306dd6a786dc3d0
