{
  "id": 1114829,
  "type": "Feature",
  "properties": {
    "tgn:hierarchy":[
        "tgn:1114829",
        "tgn:7017434",
        "tgn:1000001",
        "tgn:7004643",
        "tgn:7029392"
    ],
    "tgn:id":1114829,
    "tgn:name":"San Jos\u00e9, Laguna",
    "tgn:placetype":[
        "aat:300008679"
    ]
},
  "bbox": [],
  "geometry": {"coordinates":[-66.0167,18.4167],"type":"Point"}
}