{
  "id": 2336253,
  "type": "Feature",
  "properties": {
    "tgn:hierarchy":[
        "tgn:2336253",
        "tgn:7002659",
        "tgn:1000001",
        "tgn:7012149",
        "tgn:2000062",
        "tgn:7029392"
    ],
    "tgn:id":2336253,
    "tgn:name":"Fosters Bar",
    "tgn:placetype":[
        "aat:300132348"
    ]
},
  "bbox": [],
  "geometry": {"coordinates":[-87.6167,33.0333],"type":"Point"}
}