{
  "id": 2202795,
  "type": "Feature",
  "properties": {
    "tgn:hierarchy":[
        "tgn:2202795",
        "tgn:1000001",
        "tgn:7012149",
        "tgn:7019676",
        "tgn:7007566",
        "tgn:7029392"
    ],
    "tgn:id":2202795,
    "tgn:name":"Buckey Number 1 Mine",
    "tgn:placetype":[
        "aat:300000390"
    ]
},
  "bbox": [],
  "geometry": {"coordinates":[-107.85,35.4333],"type":"Point"}
}