<<<<<<< HEAD
{
  "id": 7023655,
  "type": "Feature",
  "properties": {
    "tgn:hierarchy":[
        "tgn:7023655",
        "tgn:1000001",
        "tgn:7006451",
        "tgn:7012149",
        "tgn:7029392"
    ],
    "tgn:id":7023655,
    "tgn:name":"Penrod Tank",
    "tgn:placetype":[
        "aat:300006191"
    ]
},
  "bbox": [],
  "geometry": {"coordinates":[-109.85,34.2167],"type":"Point"}
}
=======
{"geometry":{"type":"Point","coordinates":[-109.850000,34.216700]},"type":"Feature","properties":{"hierarchy":["tgn:7023655","tgn:1000001","tgn:7006451","tgn:7012149","tgn:7029392"],"placetype":["aat:300006191"],"id":7023655,"name:xx":"Penrod Tank"}}
>>>>>>> 03f74aca74312dbeaf24d7e61306dd6a786dc3d0
