{
  "id": 7461561,
  "type": "Feature",
  "properties": {
    "tgn:hierarchy":[
        "tgn:7461561",
        "tgn:7002444",
        "tgn:1000003",
        "tgn:7008094",
        "tgn:7008591",
        "tgn:7029392"
    ],
    "tgn:id":7461561,
    "tgn:name:en":"Hen Shoal",
    "tgn:placetype":[
        "aat:300387036"
    ]
},
  "bbox": [],
  "geometry": {"coordinates":[-6.45,58.45],"type":"Point"}
}