{
  "id": 7267739,
  "type": "Feature",
  "properties": {
    "tgn:hierarchy":[
        "tgn:7267739",
        "tgn:1000003",
        "tgn:7006951",
        "tgn:7016845",
        "tgn:7029392"
    ],
    "tgn:id":7267739,
    "tgn:name:nl":"Oosterdoksdoorgang",
    "tgn:placetype":[
        "aat:300386965"
    ]
},
  "bbox": [],
  "geometry": {"coordinates":[4.916667,52.383333],"type":"Point"}
}