{
  "id": 2293642,
  "type": "Feature",
  "properties": {
    "tgn:hierarchy":[
        "tgn:2293642",
        "tgn:1000001",
        "tgn:7012149",
        "tgn:2000850",
        "tgn:7007255",
        "tgn:7029392"
    ],
    "tgn:id":2293642,
    "tgn:name":"Doublehead Ridge",
    "tgn:placetype":[
        "aat:300266640"
    ]
},
  "bbox": [],
  "geometry": {"coordinates":[-84.6667,36.8833],"type":"Point"}
}