{
  "id": 7226123,
  "type": "Feature",
  "properties": {
    "tgn:hierarchy":[
        "tgn:7226123",
        "tgn:7002743",
        "tgn:7017076",
        "tgn:1000003",
        "tgn:1000074",
        "tgn:7029392"
    ],
    "tgn:id":7226123,
    "tgn:name":"Souvaliota\u00edika",
    "tgn:placetype":[
        "aat:300008347"
    ]
},
  "bbox": [],
  "geometry": {"coordinates":[21.716667,38.066667],"type":"Point"}
}