{
  "id": 1079828,
  "type": "Feature",
  "properties": {
    "tgn:hierarchy":[
        "tgn:1079828",
        "tgn:7000895",
        "tgn:1000004",
        "tgn:1001010",
        "tgn:1000120",
        "tgn:7029392"
    ],
    "tgn:id":1079828,
    "tgn:name":"Asashina",
    "tgn:placetype":[
        "aat:300008347"
    ]
},
  "bbox": [],
  "geometry": {"coordinates":[138.4167,36.2667],"type":"Point"}
}