{
  "id": 2783560,
  "type": "Feature",
  "properties": {
    "tgn:hierarchy":[
        "tgn:2783560",
        "tgn:1000001",
        "tgn:7012149",
        "tgn:1002618",
        "tgn:7007251",
        "tgn:7029392"
    ],
    "tgn:id":2783560,
    "tgn:name":"Wyckles Corners",
    "tgn:placetype":[
        "aat:300008347"
    ]
},
  "bbox": [],
  "geometry": {"coordinates":[-89.0167,39.8333],"type":"Point"}
}