{
  "id": 7251598,
  "type": "Feature",
  "properties": {
    "tgn:hierarchy":[
        "tgn:7251598",
        "tgn:7003458",
        "tgn:1000003",
        "tgn:1000063",
        "tgn:7018236",
        "tgn:7029392"
    ],
    "tgn:id":7251598,
    "tgn:name":"Marialoop",
    "tgn:placetype":[
        "aat:300008347"
    ]
},
  "bbox": [],
  "geometry": {"coordinates":[3.325211,50.96429],"type":"Point"}
}