{
  "id": 7047130,
  "type": "Feature",
  "properties": {
    "tgn:hierarchy":[
        "tgn:7047130",
        "tgn:1003505",
        "tgn:1000003",
        "tgn:7002993",
        "tgn:1000080",
        "tgn:7029392"
    ],
    "tgn:id":7047130,
    "tgn:name":"Faro della Vittoria",
    "tgn:placetype":[
        "aat:300007741",
        "aat:300004847"
    ]
},
  "bbox": [],
  "geometry": {"coordinates":[7.716667,45.033333],"type":"Point"}
}