{
  "id": 2743861,
  "type": "Feature",
  "properties": {
    "tgn:hierarchy":[
        "tgn:2743861",
        "tgn:1000001",
        "tgn:7012149",
        "tgn:2002118",
        "tgn:7007827",
        "tgn:7029392"
    ],
    "tgn:id":2743861,
    "tgn:name":"Velasquez",
    "tgn:placetype":[
        "aat:300008347"
    ]
},
  "bbox": [],
  "geometry": {"coordinates":[-111.8833,40.6833],"type":"Point"}
}