{
  "id": 2569409,
  "type": "Feature",
  "properties": {
    "tgn:hierarchy":[
        "tgn:2569409",
        "tgn:1000001",
        "tgn:7012149",
        "tgn:7007827",
        "tgn:7029392"
    ],
    "tgn:id":2569409,
    "tgn:name":"Parleys Summit",
    "tgn:placetype":[
        "aat:300008798"
    ]
},
  "bbox": [],
  "geometry": {"coordinates":[-111.6167,40.75],"type":"Point"}
}