{
  "id": 2090293,
  "type": "Feature",
  "properties": {
    "tgn:hierarchy":[
        "tgn:2090293",
        "tgn:1000001",
        "tgn:7012149",
        "tgn:1003041",
        "tgn:7007710",
        "tgn:7029392"
    ],
    "tgn:id":2090293,
    "tgn:name":"Lovelton",
    "tgn:placetype":[
        "aat:300008347"
    ]
},
  "bbox": [],
  "geometry": {"coordinates":[-76.1833,41.5333],"type":"Point"}
}