{
  "id": 2558300,
  "type": "Feature",
  "properties": {
    "tgn:hierarchy":[
        "tgn:2558300",
        "tgn:1000001",
        "tgn:7012149",
        "tgn:2002342",
        "tgn:7007922",
        "tgn:7029392"
    ],
    "tgn:id":2558300,
    "tgn:name":"Ole Lake",
    "tgn:placetype":[
        "aat:300008680"
    ]
},
  "bbox": [],
  "geometry": {"coordinates":[-89.55,45.6833],"type":"Point"}
}