<<<<<<< HEAD
{
  "id": 7050546,
  "type": "Feature",
  "properties": {
    "tgn:hierarchy":[
        "tgn:7050546",
        "tgn:1001641",
        "tgn:1000003",
        "tgn:7003121",
        "tgn:1000080",
        "tgn:7029392"
    ],
    "tgn:id":7050546,
    "tgn:name":"La Punta",
    "tgn:placetype":[
        "aat:300386846"
    ]
},
  "bbox": [],
  "geometry": {"coordinates":[8.316667,39.183333],"type":"Point"}
}
=======
{"geometry":{"type":"Point","coordinates":[8.316667,39.183333]},"type":"Feature","properties":{"hierarchy":["tgn:7050546","tgn:1001641","tgn:1000003","tgn:7003121","tgn:1000080","tgn:7029392"],"placetype":["aat:300386846"],"id":7050546,"name:xx":"La Punta"}}
>>>>>>> 03f74aca74312dbeaf24d7e61306dd6a786dc3d0
