{
  "id": 7170538,
  "type": "Feature",
  "properties": {
    "tgn:hierarchy":[
        "tgn:7170538",
        "tgn:7003692",
        "tgn:1000003",
        "tgn:7000084",
        "tgn:7029392"
    ],
    "tgn:id":7170538,
    "tgn:name":"Henschelberg",
    "tgn:placetype":[
        "aat:300266640"
    ]
},
  "bbox": [],
  "geometry": {"coordinates":[8.983333,49.366667],"type":"Point"}
}