{
  "id": 2543347,
  "type": "Feature",
  "properties": {
    "tgn:hierarchy":[
        "tgn:2543347",
        "tgn:1000001",
        "tgn:7012149",
        "tgn:1002723",
        "tgn:7007252",
        "tgn:7029392"
    ],
    "tgn:id":2543347,
    "tgn:name":"Norman Lake",
    "tgn:placetype":[
        "aat:300008680"
    ]
},
  "bbox": [],
  "geometry": {"coordinates":[-85.4167,41.3333],"type":"Point"}
}