{
  "id": 2117767,
  "type": "Feature",
  "properties": {
    "tgn:hierarchy":[
        "tgn:2117767",
        "tgn:1000001",
        "tgn:7012149",
        "tgn:7014398",
        "tgn:7013961",
        "tgn:7029392"
    ],
    "tgn:id":2117767,
    "tgn:name":"Cherry Grove",
    "tgn:placetype":[
        "aat:300008347"
    ]
},
  "bbox": [],
  "geometry": {"coordinates":[-79.5167,38.6333],"type":"Point"}
}