{
  "id": 2669540,
  "type": "Feature",
  "properties": {
    "tgn:hierarchy":[
        "tgn:2669540",
        "tgn:1000001",
        "tgn:7012149",
        "tgn:1002800",
        "tgn:7007710",
        "tgn:7029392"
    ],
    "tgn:id":2669540,
    "tgn:name":"Slide Hollow",
    "tgn:placetype":[
        "aat:300008761"
    ]
},
  "bbox": [],
  "geometry": {"coordinates":[-77.7167,41.6833],"type":"Point"}
}