{
  "id": 2345347,
  "type": "Feature",
  "properties": {
    "tgn:hierarchy":[
        "tgn:2345347",
        "tgn:1000001",
        "tgn:7012149",
        "tgn:2001882",
        "tgn:7007825",
        "tgn:7029392"
    ],
    "tgn:id":2345347,
    "tgn:name":"Garland Ridge",
    "tgn:placetype":[
        "aat:300266640"
    ]
},
  "bbox": [],
  "geometry": {"coordinates":[-81.8167,36.5167],"type":"Point"}
}