{
  "id": 2634206,
  "type": "Feature",
  "properties": {
    "tgn:hierarchy":[
        "tgn:2634206",
        "tgn:1000001",
        "tgn:7012149",
        "tgn:1002414",
        "tgn:7007826",
        "tgn:7029392"
    ],
    "tgn:id":2634206,
    "tgn:name":"Russell Hill",
    "tgn:placetype":[
        "aat:300008798"
    ]
},
  "bbox": [],
  "geometry": {"coordinates":[-97.15,29.6333],"type":"Point"}
}