{
  "id": 7550463,
  "type": "Feature",
  "properties": {
    "tgn:hierarchy":[
        "tgn:7550463",
        "tgn:1000004",
        "tgn:7000198",
        "tgn:1001894",
        "tgn:7029392"
    ],
    "tgn:id":7550463,
    "tgn:name:en":"Bh\u016bri",
    "tgn:placetype":[
        "aat:300008347"
    ]
},
  "bbox": [],
  "geometry": {"coordinates":[79.440134,23.731013],"type":"Point"}
}