{
  "id": 2127636,
  "type": "Feature",
  "properties": {
    "tgn:hierarchy":[
        "tgn:2127636",
        "tgn:1002483",
        "tgn:7019080",
        "tgn:1000001",
        "tgn:7012149",
        "tgn:7007249",
        "tgn:7029392"
    ],
    "tgn:id":2127636,
    "tgn:name":"Alala Point",
    "tgn:placetype":[
        "aat:300008850"
    ]
},
  "bbox": [],
  "geometry": {"coordinates":[-157.7167,21.3833],"type":"Point"}
}