{
  "id": 2699602,
  "type": "Feature",
  "properties": {
    "tgn:hierarchy":[
        "tgn:2699602",
        "tgn:1000001",
        "tgn:7012149",
        "tgn:2001302",
        "tgn:7007524",
        "tgn:7029392"
    ],
    "tgn:id":2699602,
    "tgn:name":"Structure Number 139 Reservoir",
    "tgn:placetype":[
        "aat:300006191"
    ]
},
  "bbox": [],
  "geometry": {"coordinates":[-105.2167,48.2167],"type":"Point"}
}