{
  "id": 2042981,
  "type": "Feature",
  "properties": {
    "tgn:hierarchy":[
        "tgn:2042981",
        "tgn:1000001",
        "tgn:2000864",
        "tgn:7012149",
        "tgn:7007256",
        "tgn:7029392"
    ],
    "tgn:id":2042981,
    "tgn:name":"Hebert",
    "tgn:placetype":[
        "aat:300008347"
    ]
},
  "bbox": [],
  "geometry": {"coordinates":[-91.9833,32.1667],"type":"Point"}
}