<<<<<<< HEAD
{
  "id": 2409175,
  "type": "Feature",
  "properties": {
    "tgn:hierarchy":[
        "tgn:2409175",
        "tgn:1000001",
        "tgn:7006451",
        "tgn:2000092",
        "tgn:7012149",
        "tgn:7029392"
    ],
    "tgn:id":2409175,
    "tgn:name":"Ice Pond",
    "tgn:placetype":[
        "aat:300008680"
    ]
},
  "bbox": [],
  "geometry": {"coordinates":[-112.1333,35.2],"type":"Point"}
}
=======
{"geometry":{"type":"Point","coordinates":[-112.133300,35.200000]},"type":"Feature","properties":{"hierarchy":["tgn:2409175","tgn:1000001","tgn:7006451","tgn:2000092","tgn:7012149","tgn:7029392"],"placetype":["aat:300008680"],"id":2409175,"name:xx":"Ice Pond"}}
>>>>>>> 03f74aca74312dbeaf24d7e61306dd6a786dc3d0
