{
  "id": 1123394,
  "type": "Feature",
  "properties": {
    "tgn:hierarchy":[
        "tgn:1123394",
        "tgn:1000001",
        "tgn:7012149",
        "tgn:7007826",
        "tgn:7029392"
    ],
    "tgn:id":1123394,
    "tgn:name":"Devils",
    "tgn:placetype":[
        "aat:300008707"
    ]
},
  "bbox": [],
  "geometry": {"coordinates":[-100.9333,30.3167],"type":"Point"}
}