{
  "id": 7422617,
  "type": "Feature",
  "properties": {
    "tgn:hierarchy":[
        "tgn:7422617",
        "tgn:1000001",
        "tgn:7005601",
        "tgn:7005560",
        "tgn:7029392"
    ],
    "tgn:id":7422617,
    "tgn:name":"Tierra y Libertad",
    "tgn:placetype":[
        "aat:300008347"
    ]
},
  "bbox": [],
  "geometry": {"coordinates":[-102.891667,23.45],"type":"Point"}
}