{
  "id": 7109290,
  "type": "Feature",
  "properties": {
    "tgn:hierarchy":[
        "tgn:7109290",
        "tgn:7003669",
        "tgn:1000003",
        "tgn:7000084",
        "tgn:7029392"
    ],
    "tgn:id":7109290,
    "tgn:name":"Reipertsgesee",
    "tgn:placetype":[
        "aat:300008347"
    ]
},
  "bbox": [],
  "geometry": {"coordinates":[11.383333,49.666667],"type":"Point"}
}