<<<<<<< HEAD
{
  "id": 7170053,
  "type": "Feature",
  "properties": {
    "tgn:hierarchy":[
        "tgn:7170053",
        "tgn:1000003",
        "tgn:7003678",
        "tgn:7000084",
        "tgn:7029392"
    ],
    "tgn:id":7170053,
    "tgn:name":"Herchen-Berg",
    "tgn:placetype":[
        "aat:300008777"
    ]
},
  "bbox": [],
  "geometry": {"coordinates":[9.2,50.35],"type":"Point"}
}
=======
{"geometry":{"type":"Point","coordinates":[9.200000,50.350000]},"type":"Feature","properties":{"hierarchy":["tgn:7170053","tgn:1000003","tgn:7003678","tgn:7000084","tgn:7029392"],"placetype":["aat:300008777"],"id":7170053,"name:xx":"Herchen-Berg"}}
>>>>>>> 03f74aca74312dbeaf24d7e61306dd6a786dc3d0
