<<<<<<< HEAD
{
  "id": 2156940,
  "type": "Feature",
  "properties": {
    "tgn:hierarchy":[
        "tgn:2156940",
        "tgn:1000001",
        "tgn:1002466",
        "tgn:7012149",
        "tgn:7007240",
        "tgn:7029392"
    ],
    "tgn:id":2156940,
    "tgn:name":"Beautiful Hammock",
    "tgn:placetype":[
        "aat:300008791"
    ]
},
  "bbox": [],
  "geometry": {"coordinates":[-81.2,26.75],"type":"Point"}
}
=======
{"geometry":{"type":"Point","coordinates":[-81.200000,26.750000]},"type":"Feature","properties":{"hierarchy":["tgn:2156940","tgn:1000001","tgn:1002466","tgn:7012149","tgn:7007240","tgn:7029392"],"placetype":["aat:300008791"],"id":2156940,"name:xx":"Beautiful Hammock"}}
>>>>>>> 03f74aca74312dbeaf24d7e61306dd6a786dc3d0
