{
  "id": 7531157,
  "type": "Feature",
  "properties": {
    "tgn:hierarchy":[
        "tgn:7531157",
        "tgn:7001242",
        "tgn:7016833",
        "tgn:1001091",
        "tgn:7029392"
    ],
    "tgn:id":7531157,
    "tgn:name":"Ash Shirkah al Mi\u015fr\u012byah li Tij\u0101rat al Adwiyah",
    "tgn:placetype":[
        "aat:300004792"
    ]
},
  "bbox": [],
  "geometry": {"coordinates":[31.24144,30.09763],"type":"Point"}
}