{
  "id": 2306976,
  "type": "Feature",
  "properties": {
    "tgn:hierarchy":[
        "tgn:2306976",
        "tgn:1000001",
        "tgn:7012149",
        "tgn:2001208",
        "tgn:7007523",
        "tgn:7029392"
    ],
    "tgn:id":2306976,
    "tgn:name":"East Fork Little Blue River",
    "tgn:placetype":[
        "aat:300008707"
    ]
},
  "bbox": [],
  "geometry": {"coordinates":[-94.35,38.8833],"type":"Point"}
}