{
  "id": 2016103,
  "type": "Feature",
  "properties": {
    "tgn:hierarchy":[
        "tgn:2016103",
        "tgn:1000001",
        "tgn:7012149",
        "tgn:2000238",
        "tgn:7007158",
        "tgn:7029392"
    ],
    "tgn:id":2016103,
    "tgn:name":"Park City",
    "tgn:placetype":[
        "aat:300008347"
    ]
},
  "bbox": [],
  "geometry": {"coordinates":[-106.0833,39.2667],"type":"Point"}
}