<<<<<<< HEAD
{
  "id": 2339747,
  "type": "Feature",
  "properties": {
    "tgn:hierarchy":[
        "tgn:2339747",
        "tgn:1000001",
        "tgn:7012149",
        "tgn:7007922",
        "tgn:7029392"
    ],
    "tgn:id":2339747,
    "tgn:name":"Freedom Lakes",
    "tgn:placetype":[
        "aat:300008680"
    ]
},
  "bbox": [],
  "geometry": {"coordinates":[-92.5667,45.6333],"type":"Point"}
}
=======
{"geometry":{"type":"Point","coordinates":[-92.566700,45.633300]},"type":"Feature","properties":{"hierarchy":["tgn:2339747","tgn:1000001","tgn:7012149","tgn:7007922","tgn:7029392"],"placetype":["aat:300008680"],"id":2339747,"name:xx":"Freedom Lakes"}}
>>>>>>> 03f74aca74312dbeaf24d7e61306dd6a786dc3d0
