{
  "id": 2339747,
  "type": "Feature",
  "properties": {
    "tgn:hierarchy":[
        "tgn:2339747",
        "tgn:1000001",
        "tgn:7012149",
        "tgn:7007922",
        "tgn:7029392"
    ],
    "tgn:id":2339747,
    "tgn:name":"Freedom Lakes",
    "tgn:placetype":[
        "aat:300008680"
    ]
},
  "bbox": [],
  "geometry": {"coordinates":[-92.5667,45.6333],"type":"Point"}
}