<<<<<<< HEAD
{
  "id": 2766689,
  "type": "Feature",
  "properties": {
    "tgn:hierarchy":[
        "tgn:2766689",
        "tgn:1000001",
        "tgn:7006451",
        "tgn:7012149",
        "tgn:2000102",
        "tgn:7029392"
    ],
    "tgn:id":2766689,
    "tgn:name":"White Oak Mine",
    "tgn:placetype":[
        "aat:300000390"
    ]
},
  "bbox": [],
  "geometry": {"coordinates":[-111.0833,31.3667],"type":"Point"}
}
=======
{"geometry":{"type":"Point","coordinates":[-111.083300,31.366700]},"type":"Feature","properties":{"hierarchy":["tgn:2766689","tgn:1000001","tgn:7006451","tgn:7012149","tgn:2000102","tgn:7029392"],"placetype":["aat:300000390"],"id":2766689,"name:xx":"White Oak Mine"}}
>>>>>>> 03f74aca74312dbeaf24d7e61306dd6a786dc3d0
