{
  "id": 1078175,
  "type": "Feature",
  "properties": {
    "tgn:hierarchy":[
        "tgn:1078175",
        "tgn:1000004",
        "tgn:1001339",
        "tgn:1000116",
        "tgn:7029392"
    ],
    "tgn:id":1078175,
    "tgn:name":"Muarapangean",
    "tgn:placetype":[
        "aat:300008347"
    ]
},
  "bbox": [],
  "geometry": {"coordinates":[116.6833,2.6333],"type":"Point"}
}