{
  "id": 7326107,
  "type": "Feature",
  "properties": {
    "tgn:hierarchy":[
        "tgn:7326107",
        "tgn:7002842",
        "tgn:7001158",
        "tgn:1000003",
        "tgn:1000095",
        "tgn:7029392"
    ],
    "tgn:id":7326107,
    "tgn:name":"Portelrubio",
    "tgn:placetype":[
        "aat:300008347"
    ]
},
  "bbox": [],
  "geometry": {"coordinates":[-2.433333,41.866667],"type":"Point"}
}