{
  "id": 2162388,
  "type": "Feature",
  "properties": {
    "tgn:hierarchy":[
        "tgn:2162388",
        "tgn:1000001",
        "tgn:7012149",
        "tgn:2000928",
        "tgn:7007515",
        "tgn:7029392"
    ],
    "tgn:id":2162388,
    "tgn:name":"Ben Chase Hill",
    "tgn:placetype":[
        "aat:300008798"
    ]
},
  "bbox": [],
  "geometry": {"coordinates":[-69.2333,45.2833],"type":"Point"}
}