{
  "id": 7492281,
  "type": "Feature",
  "properties": {
    "tgn:hierarchy":[
        "tgn:7492281",
        "tgn:1000004",
        "tgn:7491221",
        "tgn:1000141",
        "tgn:7029392"
    ],
    "tgn:id":7492281,
    "tgn:name":"Daniao Shan",
    "tgn:placetype":[
        "aat:300008798"
    ]
},
  "bbox": [],
  "geometry": {"coordinates":[120.877778,22.406389],"type":"Point"}
}