<<<<<<< HEAD
{
  "id": 7360190,
  "type": "Feature",
  "properties": {
    "tgn:hierarchy":[
        "tgn:7360190",
        "tgn:1000001",
        "tgn:7005599",
        "tgn:7005560",
        "tgn:7029392"
    ],
    "tgn:id":7360190,
    "tgn:name":"Coapiloloya",
    "tgn:placetype":[
        "aat:300008347"
    ]
},
  "bbox": [],
  "geometry": {"coordinates":[-94.716667,17.666667],"type":"Point"}
}
=======
{"geometry":{"type":"Point","coordinates":[-94.716667,17.666667]},"type":"Feature","properties":{"hierarchy":["tgn:7360190","tgn:1000001","tgn:7005599","tgn:7005560","tgn:7029392"],"placetype":["aat:300008347"],"id":7360190,"name:xx":"Coapiloloya"}}
>>>>>>> 03f74aca74312dbeaf24d7e61306dd6a786dc3d0
