{
  "id": 7531999,
  "type": "Feature",
  "properties": {
    "tgn:hierarchy":[
        "tgn:7531999",
        "tgn:7001242",
        "tgn:7016833",
        "tgn:1001091",
        "tgn:7029392"
    ],
    "tgn:id":7531999,
    "tgn:name":"Malik Jam'\u012byat as S\u0101mr\u012b",
    "tgn:placetype":[
        "aat:300000745"
    ]
},
  "bbox": [],
  "geometry": {"coordinates":[31.325841,30.015898],"type":"Point"}
}