{
  "id": 2529368,
  "type": "Feature",
  "properties": {
    "tgn:hierarchy":[
        "tgn:2529368",
        "tgn:1000001",
        "tgn:7012149",
        "tgn:2000967",
        "tgn:7007520",
        "tgn:7029392"
    ],
    "tgn:id":2529368,
    "tgn:name":"Mud Lake",
    "tgn:placetype":[
        "aat:300008680"
    ]
},
  "bbox": [],
  "geometry": {"coordinates":[-84.7667,43.4833],"type":"Point"}
}