{
  "id": 1106970,
  "type": "Feature",
  "properties": {
    "tgn:hierarchy":[
        "tgn:1106970",
        "tgn:7002445",
        "tgn:1000003",
        "tgn:7008117",
        "tgn:7008591",
        "tgn:7029392"
    ],
    "tgn:id":1106970,
    "tgn:name:en":"Whernside",
    "tgn:placetype":[
        "aat:300008795"
    ]
},
  "bbox": [],
  "geometry": {"coordinates":[-2.416667,54.233333],"type":"Point"}
}