{
  "id": 7184713,
  "type": "Feature",
  "properties": {
    "tgn:hierarchy":[
        "tgn:7184713",
        "tgn:1000003",
        "tgn:7003676",
        "tgn:7000084",
        "tgn:7029392"
    ],
    "tgn:id":7184713,
    "tgn:name":"G\u00f6seken Schlatt",
    "tgn:placetype":[
        "aat:300008680"
    ]
},
  "bbox": [],
  "geometry": {"coordinates":[7.95,53.033333],"type":"Point"}
}