{
  "id": 7548530,
  "type": "Feature",
  "properties": {
    "tgn:hierarchy":[
        "tgn:7548530",
        "tgn:1001828",
        "tgn:1000004",
        "tgn:7000198",
        "tgn:7029392"
    ],
    "tgn:id":7548530,
    "tgn:name:en":"Duggir\u0101la",
    "tgn:placetype":[
        "aat:300008347"
    ]
},
  "bbox": [],
  "geometry": {"coordinates":[80.633333,16.316667],"type":"Point"}
}