<<<<<<< HEAD
{
  "id": 2407151,
  "type": "Feature",
  "properties": {
    "tgn:hierarchy":[
        "tgn:2407151",
        "tgn:1000001",
        "tgn:7012149",
        "tgn:1002768",
        "tgn:7007240",
        "tgn:7029392"
    ],
    "tgn:id":2407151,
    "tgn:name":"Hunters Island",
    "tgn:placetype":[
        "aat:300008791"
    ]
},
  "bbox": [],
  "geometry": {"coordinates":[-80.0333,26.65],"type":"Point"}
}
=======
{"geometry":{"type":"Point","coordinates":[-80.033300,26.650000]},"type":"Feature","properties":{"hierarchy":["tgn:2407151","tgn:1000001","tgn:7012149","tgn:1002768","tgn:7007240","tgn:7029392"],"placetype":["aat:300008791"],"id":2407151,"name:xx":"Hunters Island"}}
>>>>>>> 03f74aca74312dbeaf24d7e61306dd6a786dc3d0
