{
  "id": 7271697,
  "type": "Feature",
  "properties": {
    "tgn:concordances":{
        "gn:id":"2746264"
    },
    "tgn:hierarchy":[
        "tgn:7271697",
        "tgn:1000003",
        "tgn:7003613",
        "tgn:7016845",
        "tgn:7029392"
    ],
    "tgn:id":7271697,
    "tgn:name:nl":"Tjuchem",
    "tgn:placetype":[
        "aat:300008347"
    ]
},
  "bbox": [],
  "geometry": {"coordinates":[6.883333,53.283333],"type":"Point"}
}