{
  "id": 2180135,
  "type": "Feature",
  "properties": {
    "tgn:hierarchy":[
        "tgn:2180135",
        "tgn:1000001",
        "tgn:7012149",
        "tgn:2002090",
        "tgn:7007826",
        "tgn:7029392"
    ],
    "tgn:id":2180135,
    "tgn:name":"Blind Trap Tank",
    "tgn:placetype":[
        "aat:300006191"
    ]
},
  "bbox": [],
  "geometry": {"coordinates":[-99.3333,27.6333],"type":"Point"}
}