{
  "id": 2540175,
  "type": "Feature",
  "properties": {
    "tgn:hierarchy":[
        "tgn:2540175",
        "tgn:1000001",
        "tgn:7012149",
        "tgn:7007157",
        "tgn:7014516",
        "tgn:7029392"
    ],
    "tgn:id":2540175,
    "tgn:name":"Newgate Ridge",
    "tgn:placetype":[
        "aat:300266640"
    ]
},
  "bbox": [],
  "geometry": {"coordinates":[-122.9333,38.55],"type":"Point"}
}