<<<<<<< HEAD
{
  "id": 7052858,
  "type": "Feature",
  "properties": {
    "tgn:hierarchy":[
        "tgn:7052858",
        "tgn:7003008",
        "tgn:1000003",
        "tgn:7002997",
        "tgn:1000080",
        "tgn:7029392"
    ],
    "tgn:id":7052858,
    "tgn:name":"Malga Campiluzzi Inferiore",
    "tgn:placetype":[
        "aat:300008347"
    ]
},
  "bbox": [],
  "geometry": {"coordinates":[11.25,45.85],"type":"Point"}
}
=======
{"geometry":{"type":"Point","coordinates":[11.250000,45.850000]},"type":"Feature","properties":{"hierarchy":["tgn:7052858","tgn:7003008","tgn:1000003","tgn:7002997","tgn:1000080","tgn:7029392"],"placetype":["aat:300008347"],"id":7052858,"name:xx":"Malga Campiluzzi Inferiore"}}
>>>>>>> 03f74aca74312dbeaf24d7e61306dd6a786dc3d0
