<<<<<<< HEAD
{
  "id": 7024592,
  "type": "Feature",
  "properties": {
    "tgn:hierarchy":[
        "tgn:7024592",
        "tgn:7593552",
        "tgn:1000001",
        "tgn:7024573",
        "tgn:7029392"
    ],
    "tgn:id":7024592,
    "tgn:name":"Udkiggen",
    "tgn:placetype":[
        "aat:300008850"
    ]
},
  "bbox": [],
  "geometry": {"coordinates":[53.5667,69.2333],"type":"Point"}
}
=======
{"geometry":{"type":"Point","coordinates":[53.566700,69.233300]},"type":"Feature","properties":{"hierarchy":["tgn:7024592","tgn:7593552","tgn:1000001","tgn:7024573","tgn:7029392"],"placetype":["aat:300008850"],"id":7024592,"name:xx":"Udkiggen"}}
>>>>>>> 03f74aca74312dbeaf24d7e61306dd6a786dc3d0
