{
  "id": 2535893,
  "type": "Feature",
  "properties": {
    "tgn:hierarchy":[
        "tgn:2535893",
        "tgn:7030516",
        "tgn:7006450",
        "tgn:1000001",
        "tgn:7012149",
        "tgn:7029392"
    ],
    "tgn:id":2535893,
    "tgn:name":"Nateekin River",
    "tgn:placetype":[
        "aat:300008707"
    ]
},
  "bbox": [],
  "geometry": {"coordinates":[-166.8333,53.85],"type":"Point"}
}