{
  "id": 7295324,
  "type": "Feature",
  "properties": {
    "tgn:hierarchy":[
        "tgn:7295324",
        "tgn:1001439",
        "tgn:1000003",
        "tgn:7002797",
        "tgn:1000095",
        "tgn:7029392"
    ],
    "tgn:id":7295324,
    "tgn:name":"Estacio, Punta del",
    "tgn:placetype":[
        "aat:300386846"
    ]
},
  "bbox": [],
  "geometry": {"coordinates":[-0.722222,37.747222],"type":"Point"}
}