{
  "id": 2729747,
  "type": "Feature",
  "properties": {
    "tgn:hierarchy":[
        "tgn:2729747",
        "tgn:1002169",
        "tgn:1000001",
        "tgn:7012149",
        "tgn:7007255",
        "tgn:7029392"
    ],
    "tgn:id":2729747,
    "tgn:name":"Trough Lick Branch",
    "tgn:placetype":[
        "aat:300008699"
    ]
},
  "bbox": [],
  "geometry": {"coordinates":[-83.5667,38.0667],"type":"Point"}
}