<<<<<<< HEAD
{
  "id": 7117902,
  "type": "Feature",
  "properties": {
    "tgn:hierarchy":[
        "tgn:7117902",
        "tgn:1000003",
        "tgn:7003682",
        "tgn:7000084",
        "tgn:7029392"
    ],
    "tgn:id":7117902,
    "tgn:name":"Obersgegen",
    "tgn:placetype":[
        "aat:300008347"
    ]
},
  "bbox": [],
  "geometry": {"coordinates":[6.283333,49.933333],"type":"Point"}
}
=======
{"geometry":{"type":"Point","coordinates":[6.283333,49.933333]},"type":"Feature","properties":{"hierarchy":["tgn:7117902","tgn:1000003","tgn:7003682","tgn:7000084","tgn:7029392"],"placetype":["aat:300008347"],"id":7117902,"name:xx":"Obersgegen"}}
>>>>>>> 03f74aca74312dbeaf24d7e61306dd6a786dc3d0
