{
  "id": 1027500,
  "type": "Feature",
  "properties": {
    "tgn:hierarchy":[
        "tgn:1027500",
        "tgn:1003530",
        "tgn:1000003",
        "tgn:1001780",
        "tgn:7029392"
    ],
    "tgn:id":1027500,
    "tgn:name":"Ro\u017emit\u00e1l",
    "tgn:placetype":[
        "aat:300008347"
    ]
},
  "bbox": [],
  "geometry": {"coordinates":[13.8667,49.6167],"type":"Point"}
}