<<<<<<< HEAD
{
  "id": 7113991,
  "type": "Feature",
  "properties": {
    "tgn:hierarchy":[
        "tgn:7113991",
        "tgn:7003692",
        "tgn:1000003",
        "tgn:7000084",
        "tgn:7029392"
    ],
    "tgn:id":7113991,
    "tgn:name":"Restlehof",
    "tgn:placetype":[
        "aat:300000206"
    ]
},
  "bbox": [],
  "geometry": {"coordinates":[9.216667,47.766667],"type":"Point"}
}
=======
{"geometry":{"type":"Point","coordinates":[9.216667,47.766667]},"type":"Feature","properties":{"hierarchy":["tgn:7113991","tgn:7003692","tgn:1000003","tgn:7000084","tgn:7029392"],"placetype":["aat:300000206"],"id":7113991,"name:xx":"Restlehof"}}
>>>>>>> 03f74aca74312dbeaf24d7e61306dd6a786dc3d0
