{
  "id": 7155829,
  "type": "Feature",
  "properties": {
    "tgn:hierarchy":[
        "tgn:7155829",
        "tgn:1000003",
        "tgn:7003677",
        "tgn:7000084",
        "tgn:7029392"
    ],
    "tgn:id":7155829,
    "tgn:name":"Klein G\u00fcnn",
    "tgn:placetype":[
        "aat:300000206"
    ]
},
  "bbox": [],
  "geometry": {"coordinates":[6.416667,51.65],"type":"Point"}
}