{
  "id": 7475930,
  "type": "Feature",
  "properties": {
    "tgn:hierarchy":[
        "tgn:7475930",
        "tgn:7488858",
        "tgn:1000004",
        "tgn:1000141",
        "tgn:7029392"
    ],
    "tgn:id":7475930,
    "tgn:name":"Shuiwei Qiao",
    "tgn:placetype":[
        "aat:300007836"
    ]
},
  "bbox": [],
  "geometry": {"coordinates":[120.75752,23.769681],"type":"Point"}
}