<<<<<<< HEAD
{
  "id": 7475930,
  "type": "Feature",
  "properties": {
    "tgn:hierarchy":[
        "tgn:7475930",
        "tgn:7488858",
        "tgn:1000004",
        "tgn:1000141",
        "tgn:7029392"
    ],
    "tgn:id":7475930,
    "tgn:name":"Shuiwei Qiao",
    "tgn:placetype":[
        "aat:300007836"
    ]
},
  "bbox": [],
  "geometry": {"coordinates":[120.75752,23.769681],"type":"Point"}
}
=======
{"geometry":{"type":"Point","coordinates":[120.757520,23.769681]},"type":"Feature","properties":{"hierarchy":["tgn:7475930","tgn:7488858","tgn:1000004","tgn:1000141","tgn:7029392"],"placetype":["aat:300007836"],"id":7475930,"name:xx":"Shuiwei Qiao"}}
>>>>>>> 03f74aca74312dbeaf24d7e61306dd6a786dc3d0
