{
  "id": 1006696,
  "type": "Feature",
  "properties": {
    "tgn:hierarchy":[
        "tgn:1006696",
        "tgn:7005735",
        "tgn:7005685",
        "tgn:1000001",
        "tgn:7029392"
    ],
    "tgn:id":1006696,
    "tgn:name":"Campania Island",
    "tgn:placetype":[
        "aat:300008791"
    ]
},
  "bbox": [],
  "geometry": {"coordinates":[-129.4167,53.0833],"type":"Point"}
}