{
  "id": 7529624,
  "type": "Feature",
  "properties": {
    "tgn:hierarchy":[
        "tgn:7529624",
        "tgn:7001242",
        "tgn:7016833",
        "tgn:1001091",
        "tgn:7029392"
    ],
    "tgn:id":7529624,
    "tgn:name":"\u1e28ad\u012bqat Bust\u0101n az Zayt\u016bn",
    "tgn:placetype":[
        "aat:300008187"
    ]
},
  "bbox": [],
  "geometry": {"coordinates":[31.317535,30.065097],"type":"Point"}
}