<<<<<<< HEAD
{
  "id": 2407800,
  "type": "Feature",
  "properties": {
    "tgn:hierarchy":[
        "tgn:2407800",
        "tgn:1000001",
        "tgn:7012149",
        "tgn:2000824",
        "tgn:7007255",
        "tgn:7029392"
    ],
    "tgn:id":2407800,
    "tgn:name":"Hurricane Branch",
    "tgn:placetype":[
        "aat:300008699"
    ]
},
  "bbox": [],
  "geometry": {"coordinates":[-82.4833,37.7833],"type":"Point"}
}
=======
{"geometry":{"type":"Point","coordinates":[-82.483300,37.783300]},"type":"Feature","properties":{"hierarchy":["tgn:2407800","tgn:1000001","tgn:7012149","tgn:2000824","tgn:7007255","tgn:7029392"],"placetype":["aat:300008699"],"id":2407800,"name:xx":"Hurricane Branch"}}
>>>>>>> 03f74aca74312dbeaf24d7e61306dd6a786dc3d0
