{
  "id": 7346561,
  "type": "Feature",
  "properties": {
    "tgn:hierarchy":[
        "tgn:7346561",
        "tgn:7002811",
        "tgn:1000003",
        "tgn:7003837",
        "tgn:1000095",
        "tgn:7029392"
    ],
    "tgn:id":7346561,
    "tgn:name":"Avellanar, R\u00edo",
    "tgn:placetype":[
        "aat:300008699"
    ]
},
  "bbox": [],
  "geometry": {"coordinates":[-6.35,40.35],"type":"Point"}
}