<<<<<<< HEAD
{
  "id": 2400003,
  "type": "Feature",
  "properties": {
    "tgn:hierarchy":[
        "tgn:2400003",
        "tgn:7002659",
        "tgn:1000001",
        "tgn:7012149",
        "tgn:2000063",
        "tgn:7029392"
    ],
    "tgn:id":2400003,
    "tgn:name":"Horse Creek",
    "tgn:placetype":[
        "aat:300008706"
    ]
},
  "bbox": [],
  "geometry": {"coordinates":[-87.4333,33.7667],"type":"Point"}
}
=======
{"geometry":{"type":"Point","coordinates":[-87.433300,33.766700]},"type":"Feature","properties":{"hierarchy":["tgn:2400003","tgn:7002659","tgn:1000001","tgn:7012149","tgn:2000063","tgn:7029392"],"placetype":["aat:300008706"],"id":2400003,"name:xx":"Horse Creek"}}
>>>>>>> 03f74aca74312dbeaf24d7e61306dd6a786dc3d0
