{
  "id": 7300732,
  "type": "Feature",
  "properties": {
    "tgn:hierarchy":[
        "tgn:7300732",
        "tgn:7001155",
        "tgn:1000003",
        "tgn:7002790",
        "tgn:1000095",
        "tgn:7029392"
    ],
    "tgn:id":7300732,
    "tgn:name":"Nagore",
    "tgn:placetype":[
        "aat:300008347"
    ]
},
  "bbox": [],
  "geometry": {"coordinates":[-1.366667,42.85],"type":"Point"}
}