{
  "id": 1051460,
  "type": "Feature",
  "properties": {
    "tgn:hierarchy":[
        "tgn:1051460",
        "tgn:1000004",
        "tgn:7011585",
        "tgn:7018214",
        "tgn:7002435",
        "tgn:7029392"
    ],
    "tgn:id":1051460,
    "tgn:name":"Chupaleyka",
    "tgn:placetype":[
        "aat:300008347"
    ]
},
  "bbox": [],
  "geometry": {"coordinates":[42.55,55.1833],"type":"Point"}
}