{
  "id": 7092397,
  "type": "Feature",
  "properties": {
    "tgn:hierarchy":[
        "tgn:7092397",
        "tgn:7003669",
        "tgn:1000003",
        "tgn:7000084",
        "tgn:7029392"
    ],
    "tgn:id":7092397,
    "tgn:name":"Unterleiterbach",
    "tgn:placetype":[
        "aat:300008347"
    ]
},
  "bbox": [],
  "geometry": {"coordinates":[10.95,50.033333],"type":"Point"}
}