{
  "id": 1085003,
  "type": "Feature",
  "properties": {
    "tgn:hierarchy":[
        "tgn:1085003",
        "tgn:1002066",
        "tgn:1000004",
        "tgn:1000140",
        "tgn:7029392"
    ],
    "tgn:id":1085003,
    "tgn:name":"\u02bb\u0100hirah",
    "tgn:placetype":[
        "aat:300008347"
    ]
},
  "bbox": [],
  "geometry": {"coordinates":[36.4667,32.8833],"type":"Point"}
}