{
  "id": 7452366,
  "type": "Feature",
  "properties": {
    "tgn:hierarchy":[
        "tgn:7452366",
        "tgn:7002445",
        "tgn:1000003",
        "tgn:7008165",
        "tgn:7008591",
        "tgn:7029392"
    ],
    "tgn:id":7452366,
    "tgn:name:en":"Goswick Bay",
    "tgn:placetype":[
        "aat:300132316"
    ]
},
  "bbox": [],
  "geometry": {"coordinates":[-1.866667,55.716667],"type":"Point"}
}