{
  "id": 7497353,
  "type": "Feature",
  "properties": {
    "tgn:hierarchy":[
        "tgn:7497353",
        "tgn:1000004",
        "tgn:7001009",
        "tgn:1000141",
        "tgn:7029392"
    ],
    "tgn:id":7497353,
    "tgn:name":"Wuguang Guoxiao",
    "tgn:placetype":[
        "aat:300006495"
    ]
},
  "bbox": [],
  "geometry": {"coordinates":[120.647562,24.094659],"type":"Point"}
}