{
  "id": 7204637,
  "type": "Feature",
  "properties": {
    "tgn:hierarchy":[
        "tgn:7204637",
        "tgn:7003669",
        "tgn:1000003",
        "tgn:7000084",
        "tgn:7029392"
    ],
    "tgn:id":7204637,
    "tgn:name":"Bruck-Berg",
    "tgn:placetype":[
        "aat:300008777"
    ]
},
  "bbox": [],
  "geometry": {"coordinates":[11.233333,47.733333],"type":"Point"}
}