{
  "id": 1008410,
  "type": "Feature",
  "properties": {
    "tgn:hierarchy":[
        "tgn:1008410",
        "tgn:7001242",
        "tgn:1000157",
        "tgn:7029392"
    ],
    "tgn:id":1008410,
    "tgn:name":"Nzwane",
    "tgn:placetype":[
        "aat:300387064",
        "aat:300008791",
        "aat:300235093"
    ]
},
  "bbox": [],
  "geometry": {"coordinates":[44.4167,-12.25],"type":"Point"}
}