{
  "id": 7336847,
  "type": "Feature",
  "properties": {
    "tgn:hierarchy":[
        "tgn:7336847",
        "tgn:7002807",
        "tgn:1000003",
        "tgn:7003837",
        "tgn:1000095",
        "tgn:7029392"
    ],
    "tgn:id":7336847,
    "tgn:name":"Esteban, Arroyo de",
    "tgn:placetype":[
        "aat:300008699"
    ]
},
  "bbox": [],
  "geometry": {"coordinates":[-5.716667,38.15],"type":"Point"}
}