{
  "id": 2744881,
  "type": "Feature",
  "properties": {
    "tgn:hierarchy":[
        "tgn:2744881",
        "tgn:1000001",
        "tgn:7012149",
        "tgn:7019676",
        "tgn:7007566",
        "tgn:7029392"
    ],
    "tgn:id":2744881,
    "tgn:name":"Vieja, Laguna",
    "tgn:placetype":[
        "aat:300008680"
    ]
},
  "bbox": [],
  "geometry": {"coordinates":[-107.3833,35.3333],"type":"Point"}
}