{
  "id": 2593832,
  "type": "Feature",
  "properties": {
    "tgn:hierarchy":[
        "tgn:2593832",
        "tgn:7006450",
        "tgn:1000001",
        "tgn:7012149",
        "tgn:2000082",
        "tgn:7029392"
    ],
    "tgn:id":2593832,
    "tgn:name":"Port Chester",
    "tgn:placetype":[
        "aat:300132316"
    ]
},
  "bbox": [],
  "geometry": {"coordinates":[-131.5667,55.1333],"type":"Point"}
}