{
  "id": 1075612,
  "type": "Feature",
  "properties": {
    "tgn:hierarchy":[
        "tgn:1075612",
        "tgn:1000004",
        "tgn:7000198",
        "tgn:1001977",
        "tgn:7029392"
    ],
    "tgn:id":1075612,
    "tgn:name:en":"Jejur",
    "tgn:placetype":[
        "aat:300008347"
    ]
},
  "bbox": [],
  "geometry": {"coordinates":[88.122799,22.881302],"type":"Point"}
}