<<<<<<< HEAD
{
  "id": 2152726,
  "type": "Feature",
  "properties": {
    "tgn:hierarchy":[
        "tgn:2152726",
        "tgn:7002659",
        "tgn:1000001",
        "tgn:7012149",
        "tgn:2000048",
        "tgn:7029392"
    ],
    "tgn:id":2152726,
    "tgn:name":"Bayou La Fourche Bay",
    "tgn:placetype":[
        "aat:300132316"
    ]
},
  "bbox": [],
  "geometry": {"coordinates":[-88.3667,30.3833],"type":"Point"}
}
=======
{"geometry":{"type":"Point","coordinates":[-88.366700,30.383300]},"type":"Feature","properties":{"hierarchy":["tgn:2152726","tgn:7002659","tgn:1000001","tgn:7012149","tgn:2000048","tgn:7029392"],"placetype":["aat:300132316"],"id":2152726,"name:xx":"Bayou La Fourche Bay"}}
>>>>>>> 03f74aca74312dbeaf24d7e61306dd6a786dc3d0
