{
  "id": 2152726,
  "type": "Feature",
  "properties": {
    "tgn:hierarchy":[
        "tgn:2152726",
        "tgn:7002659",
        "tgn:1000001",
        "tgn:7012149",
        "tgn:2000048",
        "tgn:7029392"
    ],
    "tgn:id":2152726,
    "tgn:name":"Bayou La Fourche Bay",
    "tgn:placetype":[
        "aat:300132316"
    ]
},
  "bbox": [],
  "geometry": {"coordinates":[-88.3667,30.3833],"type":"Point"}
}