<<<<<<< HEAD
{
  "id": 2252744,
  "type": "Feature",
  "properties": {
    "tgn:hierarchy":[
        "tgn:2252744",
        "tgn:1000001",
        "tgn:7014423",
        "tgn:7012149",
        "tgn:7007517",
        "tgn:7029392"
    ],
    "tgn:id":2252744,
    "tgn:name":"Connett, Point",
    "tgn:placetype":[
        "aat:300008850"
    ]
},
  "bbox": [],
  "geometry": {"coordinates":[-70.75,41.6333],"type":"Point"}
}
=======
{"geometry":{"type":"Point","coordinates":[-70.750000,41.633300]},"type":"Feature","properties":{"hierarchy":["tgn:2252744","tgn:1000001","tgn:7014423","tgn:7012149","tgn:7007517","tgn:7029392"],"placetype":["aat:300008850"],"id":2252744,"name:xx":"Connett, Point"}}
>>>>>>> 03f74aca74312dbeaf24d7e61306dd6a786dc3d0
