{
  "id": 7338889,
  "type": "Feature",
  "properties": {
    "tgn:hierarchy":[
        "tgn:7338889",
        "tgn:7002820",
        "tgn:7030216",
        "tgn:1000003",
        "tgn:1000095",
        "tgn:7029392"
    ],
    "tgn:id":7338889,
    "tgn:name":"Cornell\u00e1 de Terri",
    "tgn:placetype":[
        "aat:300008347"
    ]
},
  "bbox": [],
  "geometry": {"coordinates":[2.815882,42.090471],"type":"Point"}
}