<<<<<<< HEAD
{
  "id": 2335651,
  "type": "Feature",
  "properties": {
    "tgn:hierarchy":[
        "tgn:2335651",
        "tgn:1000001",
        "tgn:7012149",
        "tgn:1002631",
        "tgn:7007240",
        "tgn:7029392"
    ],
    "tgn:id":2335651,
    "tgn:name":"Forts Bear Hole",
    "tgn:placetype":[
        "aat:300386845"
    ]
},
  "bbox": [],
  "geometry": {"coordinates":[-81.8,29.1],"type":"Point"}
}
=======
{"geometry":{"type":"Point","coordinates":[-81.800000,29.100000]},"type":"Feature","properties":{"hierarchy":["tgn:2335651","tgn:1000001","tgn:7012149","tgn:1002631","tgn:7007240","tgn:7029392"],"placetype":["aat:300386845"],"id":2335651,"name:xx":"Forts Bear Hole"}}
>>>>>>> 03f74aca74312dbeaf24d7e61306dd6a786dc3d0
