{
  "id": 1099237,
  "type": "Feature",
  "properties": {
    "tgn:hierarchy":[
        "tgn:1099237",
        "tgn:7000508",
        "tgn:1008380",
        "tgn:1000226",
        "tgn:1000006",
        "tgn:7029392"
    ],
    "tgn:id":1099237,
    "tgn:name:en":"Takapuna",
    "tgn:placetype":[
        "aat:300008347",
        "aat:300008389"
    ]
},
  "bbox": [],
  "geometry": {"coordinates":[174.775833,-36.791667],"type":"Point"}
}