{
  "id": 7290992,
  "type": "Feature",
  "properties": {
    "tgn:hierarchy":[
        "tgn:7290992",
        "tgn:1001708",
        "tgn:1000049",
        "tgn:1000002",
        "tgn:7029392"
    ],
    "tgn:id":7290992,
    "tgn:name":"Culenar, Quebrada",
    "tgn:placetype":[
        "aat:300008699"
    ]
},
  "bbox": [],
  "geometry": {"coordinates":[-71.866667,-34.166667],"type":"Point"}
}