<<<<<<< HEAD
{
  "id": 7365065,
  "type": "Feature",
  "properties": {
    "tgn:hierarchy":[
        "tgn:7365065",
        "tgn:1000001",
        "tgn:7005589",
        "tgn:7005560",
        "tgn:7029392"
    ],
    "tgn:id":7365065,
    "tgn:name":"Rancho El Sauz",
    "tgn:placetype":[
        "aat:300000241"
    ]
},
  "bbox": [],
  "geometry": {"coordinates":[-100.05,24.35],"type":"Point"}
}
=======
{"geometry":{"type":"Point","coordinates":[-100.050000,24.350000]},"type":"Feature","properties":{"hierarchy":["tgn:7365065","tgn:1000001","tgn:7005589","tgn:7005560","tgn:7029392"],"placetype":["aat:300000241"],"id":7365065,"name:xx":"Rancho El Sauz"}}
>>>>>>> 03f74aca74312dbeaf24d7e61306dd6a786dc3d0
