{
  "id": 2003363,
  "type": "Feature",
  "properties": {
    "tgn:hierarchy":[
        "tgn:2003363",
        "tgn:2000001",
        "tgn:7002659",
        "tgn:1000001",
        "tgn:7012149",
        "tgn:7029392"
    ],
    "tgn:id":2003363,
    "tgn:name":"Dyas",
    "tgn:placetype":[
        "aat:300008347",
        "aat:300387210"
    ]
},
  "bbox": [],
  "geometry": {"coordinates":[-87.6667,30.95],"type":"Point"}
}