{
  "id": 2139427,
  "type": "Feature",
  "properties": {
    "tgn:hierarchy":[
        "tgn:2139427",
        "tgn:1000001",
        "tgn:7012149",
        "tgn:2001715",
        "tgn:7007708",
        "tgn:7029392"
    ],
    "tgn:id":2139427,
    "tgn:name":"Aspen Spring",
    "tgn:placetype":[
        "aat:300008697"
    ]
},
  "bbox": [],
  "geometry": {"coordinates":[-120.8667,42.8333],"type":"Point"}
}