{
  "id": 1119575,
  "type": "Feature",
  "properties": {
    "tgn:hierarchy":[
        "tgn:1119575",
        "tgn:1002143",
        "tgn:1000001",
        "tgn:7012149",
        "tgn:7007252",
        "tgn:7029392"
    ],
    "tgn:id":1119575,
    "tgn:name":"Cedarville Reservoir",
    "tgn:placetype":[
        "aat:300006191"
    ]
},
  "bbox": [],
  "geometry": {"coordinates":[-85.0167,41.1833],"type":"Point"}
}