{
  "id": 1006389,
  "type": "Feature",
  "properties": {
    "tgn:hierarchy":[
        "tgn:1006389",
        "tgn:1000223",
        "tgn:1000006",
        "tgn:7029392"
    ],
    "tgn:id":1006389,
    "tgn:name":"Balabio",
    "tgn:placetype":[
        "aat:300008791"
    ]
},
  "bbox": [],
  "geometry": {"coordinates":[164.1667,-20.1667],"type":"Point"}
}