{
  "id": 2122830,
  "type": "Feature",
  "properties": {
    "tgn:hierarchy":[
        "tgn:2122830",
        "tgn:1000001",
        "tgn:7012149",
        "tgn:2002383",
        "tgn:7007923",
        "tgn:7029392"
    ],
    "tgn:id":2122830,
    "tgn:name":"Bryan",
    "tgn:placetype":[
        "aat:300387016"
    ]
},
  "bbox": [],
  "geometry": {"coordinates":[-109.6667,41.5667],"type":"Point"}
}