{
  "id": 2046132,
  "type": "Feature",
  "properties": {
    "tgn:hierarchy":[
        "tgn:2046132",
        "tgn:7014651",
        "tgn:1000001",
        "tgn:7012149",
        "tgn:7007516",
        "tgn:7029392"
    ],
    "tgn:id":2046132,
    "tgn:name":"Beechwood on the Burley",
    "tgn:placetype":[
        "aat:300008347"
    ]
},
  "bbox": [],
  "geometry": {"coordinates":[-76.4333,38.9833],"type":"Point"}
}