{
  "id": 2027958,
  "type": "Feature",
  "properties": {
    "tgn:hierarchy":[
        "tgn:2027958",
        "tgn:1000001",
        "tgn:7012149",
        "tgn:2000514",
        "tgn:7007251",
        "tgn:7029392"
    ],
    "tgn:id":2027958,
    "tgn:name":"Galena Junction",
    "tgn:placetype":[
        "aat:300387016"
    ]
},
  "bbox": [],
  "geometry": {"coordinates":[-90.4333,42.3667],"type":"Point"}
}