<<<<<<< HEAD
{
  "id": 2402838,
  "type": "Feature",
  "properties": {
    "tgn:hierarchy":[
        "tgn:2402838",
        "tgn:1000001",
        "tgn:1002206",
        "tgn:7012149",
        "tgn:7007568",
        "tgn:7029392"
    ],
    "tgn:id":2402838,
    "tgn:name":"Hotchkiss Creek",
    "tgn:placetype":[
        "aat:300008706"
    ]
},
  "bbox": [],
  "geometry": {"coordinates":[-75.6,42.0833],"type":"Point"}
}
=======
{"geometry":{"type":"Point","coordinates":[-75.600000,42.083300]},"type":"Feature","properties":{"hierarchy":["tgn:2402838","tgn:1000001","tgn:1002206","tgn:7012149","tgn:7007568","tgn:7029392"],"placetype":["aat:300008706"],"id":2402838,"name:xx":"Hotchkiss Creek"}}
>>>>>>> 03f74aca74312dbeaf24d7e61306dd6a786dc3d0
