{
  "id": 2147113,
  "type": "Feature",
  "properties": {
    "tgn:hierarchy":[
        "tgn:2147113",
        "tgn:1000001",
        "tgn:7019982",
        "tgn:7012149",
        "tgn:7007517",
        "tgn:7029392"
    ],
    "tgn:id":2147113,
    "tgn:name":"Baptist Hill",
    "tgn:placetype":[
        "aat:300008798"
    ]
},
  "bbox": [],
  "geometry": {"coordinates":[-72.35,42.1667],"type":"Point"}
}