{
  "id": 2172823,
  "type": "Feature",
  "properties": {
    "tgn:hierarchy":[
        "tgn:2172823",
        "tgn:1000001",
        "tgn:7012149",
        "tgn:7007522",
        "tgn:7029392"
    ],
    "tgn:id":2172823,
    "tgn:name":"Billy Branch",
    "tgn:placetype":[
        "aat:300008699"
    ]
},
  "bbox": [],
  "geometry": {"coordinates":[-89.3167,30.95],"type":"Point"}
}