{
  "id": 2594447,
  "type": "Feature",
  "properties": {
    "tgn:hierarchy":[
        "tgn:2594447",
        "tgn:1000001",
        "tgn:7012149",
        "tgn:2002196",
        "tgn:7007919",
        "tgn:7029392"
    ],
    "tgn:id":2594447,
    "tgn:name":"Porters Crossroads",
    "tgn:placetype":[
        "aat:300008347"
    ]
},
  "bbox": [],
  "geometry": {"coordinates":[-80.9667,36.85],"type":"Point"}
}