{
  "id": 7509703,
  "type": "Feature",
  "properties": {
    "tgn:hierarchy":[
        "tgn:7509703",
        "tgn:1009227",
        "tgn:1000226",
        "tgn:1000006",
        "tgn:7016850",
        "tgn:7029392"
    ],
    "tgn:id":7509703,
    "tgn:name:en":"Sunderland Creek",
    "tgn:placetype":[
        "aat:300008699"
    ]
},
  "bbox": [],
  "geometry": {"coordinates":[171.85,-42.266667],"type":"Point"}
}