{
  "id": 2284096,
  "type": "Feature",
  "properties": {
    "tgn:hierarchy":[
        "tgn:2284096",
        "tgn:1000001",
        "tgn:2001260",
        "tgn:7012149",
        "tgn:7007524",
        "tgn:7029392"
    ],
    "tgn:id":2284096,
    "tgn:name":"Deno Creek",
    "tgn:placetype":[
        "aat:300008706"
    ]
},
  "bbox": [],
  "geometry": {"coordinates":[-113.0667,45.7333],"type":"Point"}
}