<<<<<<< HEAD
{
  "id": 7172365,
  "type": "Feature",
  "properties": {
    "tgn:hierarchy":[
        "tgn:7172365",
        "tgn:1000003",
        "tgn:7003682",
        "tgn:7000084",
        "tgn:7029392"
    ],
    "tgn:id":7172365,
    "tgn:name":"F\u00f6rsterei Helmbach",
    "tgn:placetype":[
        "aat:300004792"
    ]
},
  "bbox": [],
  "geometry": {"coordinates":[7.983333,49.333333],"type":"Point"}
}
=======
{"geometry":{"type":"Point","coordinates":[7.983333,49.333333]},"type":"Feature","properties":{"hierarchy":["tgn:7172365","tgn:1000003","tgn:7003682","tgn:7000084","tgn:7029392"],"placetype":["aat:300004792"],"id":7172365,"name:xx":"F\u00f6rsterei Helmbach"}}
>>>>>>> 03f74aca74312dbeaf24d7e61306dd6a786dc3d0
