{
  "id": 7582771,
  "type": "Feature",
  "properties": {
    "tgn:hierarchy":[
        "tgn:7582771",
        "tgn:1000004",
        "tgn:7000198",
        "tgn:1001894",
        "tgn:7029392"
    ],
    "tgn:id":7582771,
    "tgn:name:en":"Dug\u0101ha Kal\u0101n",
    "tgn:placetype":[
        "aat:300008347"
    ]
},
  "bbox": [],
  "geometry": {"coordinates":[78.424402,24.144846],"type":"Point"}
}