{
  "id": 7416928,
  "type": "Feature",
  "properties": {
    "tgn:hierarchy":[
        "tgn:7416928",
        "tgn:1000001",
        "tgn:7005591",
        "tgn:7005560",
        "tgn:7029392"
    ],
    "tgn:id":7416928,
    "tgn:name:es":"Tepehuaje",
    "tgn:placetype":[
        "aat:300008347"
    ]
},
  "bbox": [],
  "geometry": {"coordinates":[-96.618611,16.413333],"type":"Point"}
}