{
  "id": 2611225,
  "type": "Feature",
  "properties": {
    "tgn:hierarchy":[
        "tgn:2611225",
        "tgn:1000001",
        "tgn:2001411",
        "tgn:7012149",
        "tgn:7007526",
        "tgn:7029392"
    ],
    "tgn:id":2611225,
    "tgn:name":"Red House Creek",
    "tgn:placetype":[
        "aat:300008706"
    ]
},
  "bbox": [],
  "geometry": {"coordinates":[-116.0667,40.9667],"type":"Point"}
}