{
  "id": 1104055,
  "type": "Feature",
  "properties": {
    "tgn:hierarchy":[
        "tgn:1104055",
        "tgn:7002443",
        "tgn:1000003",
        "tgn:7008050",
        "tgn:7008591",
        "tgn:7029392"
    ],
    "tgn:id":1104055,
    "tgn:name:en":"Brecon Beacons",
    "tgn:placetype":[
        "aat:300008795"
    ]
},
  "bbox": [],
  "geometry": {"coordinates":[-3.433333,51.883333],"type":"Point"}
}