{
  "id": 1011838,
  "type": "Feature",
  "properties": {
    "tgn:hierarchy":[
        "tgn:1011838",
        "tgn:1000002",
        "tgn:7029392"
    ],
    "tgn:id":1011838,
    "tgn:name":"Dungeness, Punta",
    "tgn:placetype":[
        "aat:300386846"
    ]
},
  "bbox": [],
  "geometry": {"coordinates":[-68.4167,-52.4167],"type":"Point"}
}