{
  "id": 2615129,
  "type": "Feature",
  "properties": {
    "tgn:hierarchy":[
        "tgn:2615129",
        "tgn:1000001",
        "tgn:2000464",
        "tgn:7012149",
        "tgn:7007250",
        "tgn:7029392"
    ],
    "tgn:id":2615129,
    "tgn:name":"Reserve Reservoir",
    "tgn:placetype":[
        "aat:300006191"
    ]
},
  "bbox": [],
  "geometry": {"coordinates":[-114.4167,43.2333],"type":"Point"}
}