{
  "id": 2671505,
  "type": "Feature",
  "properties": {
    "tgn:hierarchy":[
        "tgn:2671505",
        "tgn:1000001",
        "tgn:7012149",
        "tgn:2000214",
        "tgn:7007158",
        "tgn:7029392"
    ],
    "tgn:id":2671505,
    "tgn:name":"Smith Lake",
    "tgn:placetype":[
        "aat:300008680"
    ]
},
  "bbox": [],
  "geometry": {"coordinates":[-107.1167,40.0333],"type":"Point"}
}