{
  "id": 2313778,
  "type": "Feature",
  "properties": {
    "tgn:hierarchy":[
        "tgn:2313778",
        "tgn:1000001",
        "tgn:2000470",
        "tgn:7012149",
        "tgn:7007250",
        "tgn:7029392"
    ],
    "tgn:id":2313778,
    "tgn:name":"Elevenmile Creek",
    "tgn:placetype":[
        "aat:300008706"
    ]
},
  "bbox": [],
  "geometry": {"coordinates":[-114.55,44.4333],"type":"Point"}
}