{
  "id": 7007869,
  "type": "Feature",
  "properties": {
    "tgn:hierarchy":[
        "tgn:7007869",
        "tgn:7007877",
        "tgn:1000003",
        "tgn:1000063",
        "tgn:4012014",
        "tgn:7029392"
    ],
    "tgn:id":7007869,
    "tgn:name:fr":"Charleroi",
    "tgn:placetype":[
        "aat:300008347",
        "aat:300008389"
    ]
},
  "bbox": [],
  "geometry": {"coordinates":[4.433333,50.416667],"type":"Point"}
}