<<<<<<< HEAD
{
  "id": 2402236,
  "type": "Feature",
  "properties": {
    "tgn:hierarchy":[
        "tgn:2402236",
        "tgn:1000001",
        "tgn:7012149",
        "tgn:2002026",
        "tgn:7007826",
        "tgn:7029392"
    ],
    "tgn:id":2402236,
    "tgn:name":"Horsetooth Gully",
    "tgn:placetype":[
        "aat:300008761"
    ]
},
  "bbox": [],
  "geometry": {"coordinates":[-98.4,31.0833],"type":"Point"}
}
=======
{"geometry":{"type":"Point","coordinates":[-98.400000,31.083300]},"type":"Feature","properties":{"hierarchy":["tgn:2402236","tgn:1000001","tgn:7012149","tgn:2002026","tgn:7007826","tgn:7029392"],"placetype":["aat:300008761"],"id":2402236,"name:xx":"Horsetooth Gully"}}
>>>>>>> 03f74aca74312dbeaf24d7e61306dd6a786dc3d0
