{
  "id": 2307611,
  "type": "Feature",
  "properties": {
    "tgn:hierarchy":[
        "tgn:2307611",
        "tgn:1000001",
        "tgn:7012149",
        "tgn:2000791",
        "tgn:7007255",
        "tgn:7029392"
    ],
    "tgn:id":2307611,
    "tgn:name":"East Fork Sugar Creek",
    "tgn:placetype":[
        "aat:300008706"
    ]
},
  "bbox": [],
  "geometry": {"coordinates":[-84.5667,37.6333],"type":"Point"}
}