{
  "id": 2062873,
  "type": "Feature",
  "properties": {
    "tgn:hierarchy":[
        "tgn:2062873",
        "tgn:1000001",
        "tgn:2001410",
        "tgn:7012149",
        "tgn:7007526",
        "tgn:7029392"
    ],
    "tgn:id":2062873,
    "tgn:name":"East Las Vegas",
    "tgn:placetype":[
        "aat:300008347"
    ]
},
  "bbox": [],
  "geometry": {"coordinates":[-115.0333,36.0833],"type":"Point"}
}