{
  "id": 7141098,
  "type": "Feature",
  "properties": {
    "tgn:hierarchy":[
        "tgn:7141098",
        "tgn:7003669",
        "tgn:1000003",
        "tgn:7000084",
        "tgn:7029392"
    ],
    "tgn:id":7141098,
    "tgn:name":"L\u00fcssberg",
    "tgn:placetype":[
        "aat:300008777"
    ]
},
  "bbox": [],
  "geometry": {"coordinates":[11.566667,49.533333],"type":"Point"}
}