{
  "id": 2211810,
  "type": "Feature",
  "properties": {
    "tgn:hierarchy":[
        "tgn:2211810",
        "tgn:1000001",
        "tgn:7012149",
        "tgn:7007158",
        "tgn:7029392"
    ],
    "tgn:id":2211810,
    "tgn:name":"Button Rock Mountain",
    "tgn:placetype":[
        "aat:300008798"
    ]
},
  "bbox": [],
  "geometry": {"coordinates":[-105.3833,40.25],"type":"Point"}
}