{
  "id": 2053405,
  "type": "Feature",
  "properties": {
    "tgn:hierarchy":[
        "tgn:2053405",
        "tgn:2000946",
        "tgn:1000001",
        "tgn:7012149",
        "tgn:7007520",
        "tgn:7029392"
    ],
    "tgn:id":2053405,
    "tgn:name":"Sterling",
    "tgn:placetype":[
        "aat:300008347"
    ]
},
  "bbox": [],
  "geometry": {"coordinates":[-84.0167,44.0333],"type":"Point"}
}