{
  "id": 2765087,
  "type": "Feature",
  "properties": {
    "tgn:hierarchy":[
        "tgn:2765087",
        "tgn:1000001",
        "tgn:7012149",
        "tgn:2002114",
        "tgn:7007827",
        "tgn:7029392"
    ],
    "tgn:id":2765087,
    "tgn:name":"Whisky Spring",
    "tgn:placetype":[
        "aat:300008697"
    ]
},
  "bbox": [],
  "geometry": {"coordinates":[-112.2833,39.2667],"type":"Point"}
}