{
  "id": 2198395,
  "type": "Feature",
  "properties": {
    "tgn:hierarchy":[
        "tgn:2198395",
        "tgn:7006450",
        "tgn:1000001",
        "tgn:7012149",
        "tgn:2000089",
        "tgn:7029392"
    ],
    "tgn:id":2198395,
    "tgn:name":"Browns Fork",
    "tgn:placetype":[
        "aat:300008699"
    ]
},
  "bbox": [],
  "geometry": {"coordinates":[-153.6833,63.8333],"type":"Point"}
}