{
  "id": 2297133,
  "type": "Feature",
  "properties": {
    "tgn:hierarchy":[
        "tgn:2297133",
        "tgn:1000001",
        "tgn:2002149",
        "tgn:7012149",
        "tgn:7007919",
        "tgn:7029392"
    ],
    "tgn:id":2297133,
    "tgn:name":"Dry Creek",
    "tgn:placetype":[
        "aat:300008706"
    ]
},
  "bbox": [],
  "geometry": {"coordinates":[-78.4667,37.6667],"type":"Point"}
}