{
  "id": 2528480,
  "type": "Feature",
  "properties": {
    "tgn:hierarchy":[
        "tgn:2528480",
        "tgn:1000001",
        "tgn:7012149",
        "tgn:2002299",
        "tgn:7013961",
        "tgn:7029392"
    ],
    "tgn:id":2528480,
    "tgn:name":"Moxley Branch",
    "tgn:placetype":[
        "aat:300008699"
    ]
},
  "bbox": [],
  "geometry": {"coordinates":[-82.35,38.2833],"type":"Point"}
}