<<<<<<< HEAD
{
  "id": 7020739,
  "type": "Feature",
  "properties": {
    "tgn:hierarchy":[
        "tgn:7020739",
        "tgn:1000001",
        "tgn:7012149",
        "tgn:2001306",
        "tgn:7007524",
        "tgn:7029392"
    ],
    "tgn:id":7020739,
    "tgn:name":"Prospector Mine",
    "tgn:placetype":[
        "aat:300000390"
    ]
},
  "bbox": [],
  "geometry": {"coordinates":[-112.5667,46.0],"type":"Point"}
}
=======
{"geometry":{"type":"Point","coordinates":[-112.566700,46.000000]},"type":"Feature","properties":{"hierarchy":["tgn:7020739","tgn:1000001","tgn:7012149","tgn:2001306","tgn:7007524","tgn:7029392"],"placetype":["aat:300000390"],"id":7020739,"name:xx":"Prospector Mine"}}
>>>>>>> 03f74aca74312dbeaf24d7e61306dd6a786dc3d0
