{
  "id": 7080302,
  "type": "Feature",
  "properties": {
    "tgn:hierarchy":[
        "tgn:7080302",
        "tgn:1000003",
        "tgn:7000094",
        "tgn:7000084",
        "tgn:7029392"
    ],
    "tgn:id":7080302,
    "tgn:name":"Wotenitzer Tannen",
    "tgn:placetype":[
        "aat:300008863"
    ]
},
  "bbox": [],
  "geometry": {"coordinates":[11.166667,53.85],"type":"Point"}
}