{
  "id": 7018765,
  "type": "Feature",
  "properties": {
    "tgn:hierarchy":[
        "tgn:7018765",
        "tgn:1000003",
        "tgn:7006413",
        "tgn:7029392"
    ],
    "tgn:id":7018765,
    "tgn:name":"Lovech",
    "tgn:placetype":[
        "aat:300387064",
        "aat:300000774",
        "aat:300236112"
    ]
},
  "bbox": [],
  "geometry": {"coordinates":[24.583,43.066],"type":"Point"}
}