{
  "id": 2135263,
  "type": "Feature",
  "properties": {
    "tgn:hierarchy":[
        "tgn:2135263",
        "tgn:7002659",
        "tgn:1000001",
        "tgn:7012149",
        "tgn:2000050",
        "tgn:7029392"
    ],
    "tgn:id":2135263,
    "tgn:name":"Antioch",
    "tgn:placetype":[
        "aat:300008347"
    ]
},
  "bbox": [],
  "geometry": {"coordinates":[-86.45,32.35],"type":"Point"}
}