<<<<<<< HEAD
{
  "id": 2403653,
  "type": "Feature",
  "properties": {
    "tgn:hierarchy":[
        "tgn:2403653",
        "tgn:1000001",
        "tgn:7012149",
        "tgn:2000797",
        "tgn:7007255",
        "tgn:7029392"
    ],
    "tgn:id":2403653,
    "tgn:name":"Howard Hollow",
    "tgn:placetype":[
        "aat:300008761"
    ]
},
  "bbox": [],
  "geometry": {"coordinates":[-83.2833,36.7333],"type":"Point"}
}
=======
{"geometry":{"type":"Point","coordinates":[-83.283300,36.733300]},"type":"Feature","properties":{"hierarchy":["tgn:2403653","tgn:1000001","tgn:7012149","tgn:2000797","tgn:7007255","tgn:7029392"],"placetype":["aat:300008761"],"id":2403653,"name:xx":"Howard Hollow"}}
>>>>>>> 03f74aca74312dbeaf24d7e61306dd6a786dc3d0
