{
  "id": 2187438,
  "type": "Feature",
  "properties": {
    "tgn:hierarchy":[
        "tgn:2187438",
        "tgn:1000001",
        "tgn:7012149",
        "tgn:2001850",
        "tgn:7007825",
        "tgn:7029392"
    ],
    "tgn:id":2187438,
    "tgn:name":"Boone Hollow",
    "tgn:placetype":[
        "aat:300008761"
    ]
},
  "bbox": [],
  "geometry": {"coordinates":[-85.4667,36.5667],"type":"Point"}
}