{
  "id": 7228657,
  "type": "Feature",
  "properties": {
    "tgn:hierarchy":[
        "tgn:7228657",
        "tgn:7002715",
        "tgn:7002731",
        "tgn:1000003",
        "tgn:1000074",
        "tgn:7029392"
    ],
    "tgn:id":7228657,
    "tgn:name":"Kokkalo\u00fa",
    "tgn:placetype":[
        "aat:300008347"
    ]
},
  "bbox": [],
  "geometry": {"coordinates":[23.483333,40.633333],"type":"Point"}
}