{
  "id": 7086393,
  "type": "Feature",
  "properties": {
    "tgn:hierarchy":[
        "tgn:7086393",
        "tgn:7003669",
        "tgn:1000003",
        "tgn:7000084",
        "tgn:7029392"
    ],
    "tgn:id":7086393,
    "tgn:name":"Weidel",
    "tgn:placetype":[
        "aat:300055621"
    ]
},
  "bbox": [],
  "geometry": {"coordinates":[13.75,48.616667],"type":"Point"}
}