<<<<<<< HEAD
{
  "id": 7356115,
  "type": "Feature",
  "properties": {
    "tgn:hierarchy":[
        "tgn:7356115",
        "tgn:1000001",
        "tgn:7005593",
        "tgn:7005560",
        "tgn:7029392"
    ],
    "tgn:id":7356115,
    "tgn:name":"Camargo",
    "tgn:placetype":[
        "aat:300008347"
    ]
},
  "bbox": [],
  "geometry": {"coordinates":[-99.766667,21.1],"type":"Point"}
}
=======
{"geometry":{"type":"Point","coordinates":[-99.766667,21.100000]},"type":"Feature","properties":{"hierarchy":["tgn:7356115","tgn:1000001","tgn:7005593","tgn:7005560","tgn:7029392"],"placetype":["aat:300008347"],"id":7356115,"name:xx":"Camargo"}}
>>>>>>> 03f74aca74312dbeaf24d7e61306dd6a786dc3d0
