<<<<<<< HEAD
{
  "id": 7473644,
  "type": "Feature",
  "properties": {
    "tgn:hierarchy":[
        "tgn:7473644",
        "tgn:1000004",
        "tgn:7001014",
        "tgn:1000141",
        "tgn:7029392"
    ],
    "tgn:id":7473644,
    "tgn:name":"Yuanchang",
    "tgn:placetype":[
        "aat:300008347"
    ]
},
  "bbox": [],
  "geometry": {"coordinates":[120.312769,23.651702],"type":"Point"}
}
=======
{"geometry":{"type":"Point","coordinates":[120.312769,23.651702]},"type":"Feature","properties":{"hierarchy":["tgn:7473644","tgn:1000004","tgn:7001014","tgn:1000141","tgn:7029392"],"placetype":["aat:300008347"],"id":7473644,"name:xx":"Yuanchang"}}
>>>>>>> 03f74aca74312dbeaf24d7e61306dd6a786dc3d0
