{
  "id": 7446606,
  "type": "Feature",
  "properties": {
    "tgn:hierarchy":[
        "tgn:7446606",
        "tgn:7002448",
        "tgn:1000003",
        "tgn:7019199",
        "tgn:7008591",
        "tgn:7029392"
    ],
    "tgn:id":7446606,
    "tgn:name:en":"Ban, Slieve",
    "tgn:placetype":[
        "aat:300008795"
    ]
},
  "bbox": [],
  "geometry": {"coordinates":[-6.166667,54.083333],"type":"Point"}
}