{
  "id": 2602028,
  "type": "Feature",
  "properties": {
    "tgn:hierarchy":[
        "tgn:2602028",
        "tgn:1002648",
        "tgn:1000001",
        "tgn:7019158",
        "tgn:7012149",
        "tgn:7007249",
        "tgn:7029392"
    ],
    "tgn:id":2602028,
    "tgn:name":"Puu Maneoneo",
    "tgn:placetype":[
        "aat:300008798"
    ]
},
  "bbox": [],
  "geometry": {"coordinates":[-156.1667,20.6167],"type":"Point"}
}