{
  "id": 2580516,
  "type": "Feature",
  "properties": {
    "tgn:hierarchy":[
        "tgn:2580516",
        "tgn:1000001",
        "tgn:2001337",
        "tgn:7012149",
        "tgn:7007525",
        "tgn:7029392"
    ],
    "tgn:id":2580516,
    "tgn:name":"Pigeon Creek Ditch",
    "tgn:placetype":[
        "aat:300006075"
    ]
},
  "bbox": [],
  "geometry": {"coordinates":[-96.45,42.3333],"type":"Point"}
}