{
  "id": 2171877,
  "type": "Feature",
  "properties": {
    "tgn:hierarchy":[
        "tgn:2171877",
        "tgn:1000001",
        "tgn:7012149",
        "tgn:7007827",
        "tgn:7029392"
    ],
    "tgn:id":2171877,
    "tgn:name":"Big Wash",
    "tgn:placetype":[
        "aat:300008761"
    ]
},
  "bbox": [],
  "geometry": {"coordinates":[-110.2167,39.8833],"type":"Point"}
}