{
  "id": 7224073,
  "type": "Feature",
  "properties": {
    "tgn:hierarchy":[
        "tgn:7224073",
        "tgn:7002748",
        "tgn:7001399",
        "tgn:1000003",
        "tgn:1000074",
        "tgn:7029392"
    ],
    "tgn:id":7224073,
    "tgn:name":"Pyrgo\u00fali",
    "tgn:placetype":[
        "aat:300008795"
    ]
},
  "bbox": [],
  "geometry": {"coordinates":[21.759444,39.220833],"type":"Point"}
}