{
  "id": 7004998,
  "type": "Feature",
  "properties": {
    "tgn:hierarchy":[
        "tgn:7004998",
        "tgn:7003133",
        "tgn:1000003",
        "tgn:7008516",
        "tgn:1000080",
        "tgn:7029392"
    ],
    "tgn:id":7004998,
    "tgn:name":"Cervia",
    "tgn:placetype":[
        "aat:300008347"
    ]
},
  "bbox": [],
  "geometry": {"coordinates":[12.358889,44.261667],"type":"Point"}
}