{
  "id": 1112411,
  "type": "Feature",
  "properties": {
    "tgn:hierarchy":[
        "tgn:1112411",
        "tgn:1000004",
        "tgn:7016720",
        "tgn:1000135",
        "tgn:7029392"
    ],
    "tgn:id":1112411,
    "tgn:name":"Lagonoy Gulf",
    "tgn:placetype":[
        "aat:300132315"
    ]
},
  "bbox": [],
  "geometry": {"coordinates":[123.75,13.5833],"type":"Point"}
}