{
  "id": 7476026,
  "type": "Feature",
  "properties": {
    "tgn:hierarchy":[
        "tgn:7476026",
        "tgn:1000004",
        "tgn:7489179",
        "tgn:1000141",
        "tgn:7029392"
    ],
    "tgn:id":7476026,
    "tgn:name":"Deshan Qiao",
    "tgn:placetype":[
        "aat:300007836"
    ]
},
  "bbox": [],
  "geometry": {"coordinates":[121.752183,24.641717],"type":"Point"}
}