<<<<<<< HEAD
{
  "id": 7476026,
  "type": "Feature",
  "properties": {
    "tgn:hierarchy":[
        "tgn:7476026",
        "tgn:1000004",
        "tgn:7489179",
        "tgn:1000141",
        "tgn:7029392"
    ],
    "tgn:id":7476026,
    "tgn:name":"Deshan Qiao",
    "tgn:placetype":[
        "aat:300007836"
    ]
},
  "bbox": [],
  "geometry": {"coordinates":[121.752183,24.641717],"type":"Point"}
}
=======
{"geometry":{"type":"Point","coordinates":[121.752183,24.641717]},"type":"Feature","properties":{"hierarchy":["tgn:7476026","tgn:1000004","tgn:7489179","tgn:1000141","tgn:7029392"],"placetype":["aat:300007836"],"id":7476026,"name:xx":"Deshan Qiao"}}
>>>>>>> 03f74aca74312dbeaf24d7e61306dd6a786dc3d0
