{
  "id": 2471390,
  "type": "Feature",
  "properties": {
    "tgn:hierarchy":[
        "tgn:2471390",
        "tgn:1000001",
        "tgn:2000957",
        "tgn:7012149",
        "tgn:7007520",
        "tgn:7029392"
    ],
    "tgn:id":2471390,
    "tgn:name":"Lost Lake",
    "tgn:placetype":[
        "aat:300008680"
    ]
},
  "bbox": [],
  "geometry": {"coordinates":[-85.0333,42.7333],"type":"Point"}
}