{
  "id": 2259246,
  "type": "Feature",
  "properties": {
    "tgn:hierarchy":[
        "tgn:2259246",
        "tgn:1000001",
        "tgn:7012149",
        "tgn:2000230",
        "tgn:7007158",
        "tgn:7029392"
    ],
    "tgn:id":2259246,
    "tgn:name":"Cottonwood Lake Number 5",
    "tgn:placetype":[
        "aat:300006191"
    ]
},
  "bbox": [],
  "geometry": {"coordinates":[-107.95,39.0833],"type":"Point"}
}