<<<<<<< HEAD
{
  "id": 2334987,
  "type": "Feature",
  "properties": {
    "tgn:hierarchy":[
        "tgn:2334987",
        "tgn:1000001",
        "tgn:7012149",
        "tgn:7007157",
        "tgn:2000187",
        "tgn:7029392"
    ],
    "tgn:id":2334987,
    "tgn:name":"Forman Ravine",
    "tgn:placetype":[
        "aat:300008761"
    ]
},
  "bbox": [],
  "geometry": {"coordinates":[-120.8,40.1],"type":"Point"}
}
=======
{"geometry":{"type":"Point","coordinates":[-120.800000,40.100000]},"type":"Feature","properties":{"hierarchy":["tgn:2334987","tgn:1000001","tgn:7012149","tgn:7007157","tgn:2000187","tgn:7029392"],"placetype":["aat:300008761"],"id":2334987,"name:xx":"Forman Ravine"}}
>>>>>>> 03f74aca74312dbeaf24d7e61306dd6a786dc3d0
