<<<<<<< HEAD
{
  "id": 7117036,
  "type": "Feature",
  "properties": {
    "tgn:hierarchy":[
        "tgn:7117036",
        "tgn:7003669",
        "tgn:1000003",
        "tgn:7000084",
        "tgn:7029392"
    ],
    "tgn:id":7117036,
    "tgn:name":"Ottending",
    "tgn:placetype":[
        "aat:300008347"
    ]
},
  "bbox": [],
  "geometry": {"coordinates":[12.4,48.683333],"type":"Point"}
}
=======
{"geometry":{"type":"Point","coordinates":[12.400000,48.683333]},"type":"Feature","properties":{"hierarchy":["tgn:7117036","tgn:7003669","tgn:1000003","tgn:7000084","tgn:7029392"],"placetype":["aat:300008347"],"id":7117036,"name:xx":"Ottending"}}
>>>>>>> 03f74aca74312dbeaf24d7e61306dd6a786dc3d0
