{
  "id": 7328617,
  "type": "Feature",
  "properties": {
    "tgn:hierarchy":[
        "tgn:7328617",
        "tgn:7002759",
        "tgn:7002845",
        "tgn:1000003",
        "tgn:1000095",
        "tgn:7029392"
    ],
    "tgn:id":7328617,
    "tgn:name":"Plenas",
    "tgn:placetype":[
        "aat:300008347"
    ]
},
  "bbox": [],
  "geometry": {"coordinates":[-0.966667,41.116667],"type":"Point"}
}