<<<<<<< HEAD
{
  "id": 2705334,
  "type": "Feature",
  "properties": {
    "tgn:hierarchy":[
        "tgn:2705334",
        "tgn:7013349",
        "tgn:1000001",
        "tgn:7012149",
        "tgn:7007708",
        "tgn:7029392"
    ],
    "tgn:id":2705334,
    "tgn:name":"Surface Spring",
    "tgn:placetype":[
        "aat:300008697"
    ]
},
  "bbox": [],
  "geometry": {"coordinates":[-117.4333,44.8333],"type":"Point"}
}
=======
{"geometry":{"type":"Point","coordinates":[-117.433300,44.833300]},"type":"Feature","properties":{"hierarchy":["tgn:2705334","tgn:7013349","tgn:1000001","tgn:7012149","tgn:7007708","tgn:7029392"],"placetype":["aat:300008697"],"id":2705334,"name:xx":"Surface Spring"}}
>>>>>>> 03f74aca74312dbeaf24d7e61306dd6a786dc3d0
