{
  "id": 2584822,
  "type": "Feature",
  "properties": {
    "tgn:hierarchy":[
        "tgn:2584822",
        "tgn:1000001",
        "tgn:1002712",
        "tgn:7012149",
        "tgn:7007159",
        "tgn:7029392"
    ],
    "tgn:id":2584822,
    "tgn:name":"Pink House Cove",
    "tgn:placetype":[
        "aat:300132316"
    ]
},
  "bbox": [],
  "geometry": {"coordinates":[-73.1167,41.3333],"type":"Point"}
}