<<<<<<< HEAD
{
  "id": 2252643,
  "type": "Feature",
  "properties": {
    "tgn:hierarchy":[
        "tgn:2252643",
        "tgn:1000001",
        "tgn:2000775",
        "tgn:7012149",
        "tgn:7007255",
        "tgn:7029392"
    ],
    "tgn:id":2252643,
    "tgn:name":"Connelly Lake",
    "tgn:placetype":[
        "aat:300008680"
    ]
},
  "bbox": [],
  "geometry": {"coordinates":[-86.8833,37.1667],"type":"Point"}
}
=======
{"geometry":{"type":"Point","coordinates":[-86.883300,37.166700]},"type":"Feature","properties":{"hierarchy":["tgn:2252643","tgn:1000001","tgn:2000775","tgn:7012149","tgn:7007255","tgn:7029392"],"placetype":["aat:300008680"],"id":2252643,"name:xx":"Connelly Lake"}}
>>>>>>> 03f74aca74312dbeaf24d7e61306dd6a786dc3d0
