{
  "id": 7353182,
  "type": "Feature",
  "properties": {
    "tgn:hierarchy":[
        "tgn:7353182",
        "tgn:7005581",
        "tgn:1000001",
        "tgn:7005560",
        "tgn:7029392"
    ],
    "tgn:id":7353182,
    "tgn:name":"Buenavista",
    "tgn:placetype":[
        "aat:300008347"
    ]
},
  "bbox": [],
  "geometry": {"coordinates":[-105.133333,26.75],"type":"Point"}
}