{
  "id": 7539916,
  "type": "Feature",
  "properties": {
    "tgn:hierarchy":[
        "tgn:7539916",
        "tgn:7001242",
        "tgn:7016833",
        "tgn:1001123",
        "tgn:7029392"
    ],
    "tgn:id":7539916,
    "tgn:name":"Sam\u0101rah al Qibl\u012byah, Jaz\u012brat as",
    "tgn:placetype":[
        "aat:300008791"
    ]
},
  "bbox": [],
  "geometry": {"coordinates":[32.055278,31.226944],"type":"Point"}
}