{
  "id": 2170205,
  "type": "Feature",
  "properties": {
    "tgn:hierarchy":[
        "tgn:2170205",
        "tgn:1000001",
        "tgn:7012149",
        "tgn:2001711",
        "tgn:7007708",
        "tgn:7029392"
    ],
    "tgn:id":2170205,
    "tgn:name":"Big Red Mountain",
    "tgn:placetype":[
        "aat:300008798"
    ]
},
  "bbox": [],
  "geometry": {"coordinates":[-122.8333,42.05],"type":"Point"}
}