{
  "id": 2659174,
  "type": "Feature",
  "properties": {
    "tgn:hierarchy":[
        "tgn:2659174",
        "tgn:1000001",
        "tgn:7014352",
        "tgn:7012149",
        "tgn:7007564",
        "tgn:7029392"
    ],
    "tgn:id":2659174,
    "tgn:name":"Shields Brook",
    "tgn:placetype":[
        "aat:300008699"
    ]
},
  "bbox": [],
  "geometry": {"coordinates":[-71.3167,42.9167],"type":"Point"}
}