<<<<<<< HEAD
{
  "id": 2158128,
  "type": "Feature",
  "properties": {
    "tgn:hierarchy":[
        "tgn:2158128",
        "tgn:1000001",
        "tgn:2001737",
        "tgn:7012149",
        "tgn:7007712",
        "tgn:7029392"
    ],
    "tgn:id":2158128,
    "tgn:name":"Beaver Pond",
    "tgn:placetype":[
        "aat:300008680"
    ]
},
  "bbox": [],
  "geometry": {"coordinates":[-80.2,34.5833],"type":"Point"}
}
=======
{"geometry":{"type":"Point","coordinates":[-80.200000,34.583300]},"type":"Feature","properties":{"hierarchy":["tgn:2158128","tgn:1000001","tgn:2001737","tgn:7012149","tgn:7007712","tgn:7029392"],"placetype":["aat:300008680"],"id":2158128,"name:xx":"Beaver Pond"}}
>>>>>>> 03f74aca74312dbeaf24d7e61306dd6a786dc3d0
