{
  "id": 2110948,
  "type": "Feature",
  "properties": {
    "tgn:hierarchy":[
        "tgn:2110948",
        "tgn:1000001",
        "tgn:7012149",
        "tgn:1002362",
        "tgn:7007919",
        "tgn:7029392"
    ],
    "tgn:id":2110948,
    "tgn:name":"Caret",
    "tgn:placetype":[
        "aat:300008347"
    ]
},
  "bbox": [],
  "geometry": {"coordinates":[-76.95,37.9667],"type":"Point"}
}