{
  "id": 7232741,
  "type": "Feature",
  "properties": {
    "tgn:hierarchy":[
        "tgn:7232741",
        "tgn:4003773",
        "tgn:7001395",
        "tgn:1000003",
        "tgn:1000074",
        "tgn:7029392"
    ],
    "tgn:id":7232741,
    "tgn:name":"Kor\u00edtsa",
    "tgn:placetype":[
        "aat:300008347"
    ]
},
  "bbox": [],
  "geometry": {"coordinates":[21.815278,39.090556],"type":"Point"}
}