{
  "id": 7502567,
  "type": "Feature",
  "properties": {
    "tgn:hierarchy":[
        "tgn:7502567",
        "tgn:1000004",
        "tgn:7471332",
        "tgn:1000141",
        "tgn:7029392"
    ],
    "tgn:id":7502567,
    "tgn:name":"Shenli Qiao",
    "tgn:placetype":[
        "aat:300007836"
    ]
},
  "bbox": [],
  "geometry": {"coordinates":[121.068333,24.649722],"type":"Point"}
}