{
  "id": 7461915,
  "type": "Feature",
  "properties": {
    "tgn:hierarchy":[
        "tgn:7461915",
        "tgn:7002445",
        "tgn:1000003",
        "tgn:7008153",
        "tgn:7008591",
        "tgn:7029392"
    ],
    "tgn:id":7461915,
    "tgn:name:en":"Knock Deep",
    "tgn:placetype":[
        "aat:300008713"
    ]
},
  "bbox": [],
  "geometry": {"coordinates":[1.55,51.633333],"type":"Point"}
}