{
  "id": 7136077,
  "type": "Feature",
  "properties": {
    "tgn:hierarchy":[
        "tgn:7136077",
        "tgn:1000003",
        "tgn:7003677",
        "tgn:7000084",
        "tgn:7029392"
    ],
    "tgn:id":7136077,
    "tgn:name":"Mutzerath",
    "tgn:placetype":[
        "aat:300008347"
    ]
},
  "bbox": [],
  "geometry": {"coordinates":[6.783333,51.016667],"type":"Point"}
}