{
  "id": 2230538,
  "type": "Feature",
  "properties": {
    "tgn:hierarchy":[
        "tgn:2230538",
        "tgn:1000001",
        "tgn:7012149",
        "tgn:7029392"
    ],
    "tgn:id":2230538,
    "tgn:name":"Center Mountain",
    "tgn:placetype":[
        "aat:300008798"
    ]
},
  "bbox": [],
  "geometry": {"coordinates":[-113.6333,45.2167],"type":"Point"}
}