{
  "id": 2590563,
  "type": "Feature",
  "properties": {
    "tgn:hierarchy":[
        "tgn:2590563",
        "tgn:1000001",
        "tgn:7012149",
        "tgn:2000471",
        "tgn:7007250",
        "tgn:7029392"
    ],
    "tgn:id":2590563,
    "tgn:name":"Pole Creek",
    "tgn:placetype":[
        "aat:300008706"
    ]
},
  "bbox": [],
  "geometry": {"coordinates":[-115.5333,43.2667],"type":"Point"}
}