{
  "id": 7413314,
  "type": "Feature",
  "properties": {
    "tgn:hierarchy":[
        "tgn:7413314",
        "tgn:1000001",
        "tgn:7005598",
        "tgn:7005560",
        "tgn:7029392"
    ],
    "tgn:id":7413314,
    "tgn:name":"Ahuatepec",
    "tgn:placetype":[
        "aat:300008347"
    ]
},
  "bbox": [],
  "geometry": {"coordinates":[-98.109722,19.466667],"type":"Point"}
}