<<<<<<< HEAD
{
  "id": 7372188,
  "type": "Feature",
  "properties": {
    "tgn:hierarchy":[
        "tgn:7372188",
        "tgn:7005583",
        "tgn:1000001",
        "tgn:7005560",
        "tgn:7029392"
    ],
    "tgn:id":7372188,
    "tgn:name":"La Ca\u00f1ada, Arroyo",
    "tgn:placetype":[
        "aat:300266554",
        "aat:300008699"
    ]
},
  "bbox": [],
  "geometry": {"coordinates":[-105.866667,26.6],"type":"Point"}
}
=======
{"geometry":{"type":"Point","coordinates":[-105.866667,26.600000]},"type":"Feature","properties":{"hierarchy":["tgn:7372188","tgn:7005583","tgn:1000001","tgn:7005560","tgn:7029392"],"placetype":["aat:300266554","aat:300008699"],"id":7372188,"name:xx":"La Ca\u00f1ada, Arroyo"}}
>>>>>>> 03f74aca74312dbeaf24d7e61306dd6a786dc3d0
