<<<<<<< HEAD
{
  "id": 7476348,
  "type": "Feature",
  "properties": {
    "tgn:hierarchy":[
        "tgn:7476348",
        "tgn:7488858",
        "tgn:1000004",
        "tgn:1000141",
        "tgn:7029392"
    ],
    "tgn:id":7476348,
    "tgn:name":"Caowei Shan",
    "tgn:placetype":[
        "aat:300387033"
    ]
},
  "bbox": [],
  "geometry": {"coordinates":[120.6489,23.9217],"type":"Point"}
}
=======
{"geometry":{"type":"Point","coordinates":[120.648900,23.921700]},"type":"Feature","properties":{"hierarchy":["tgn:7476348","tgn:7488858","tgn:1000004","tgn:1000141","tgn:7029392"],"placetype":["aat:300387033"],"id":7476348,"name:xx":"Caowei Shan"}}
>>>>>>> 03f74aca74312dbeaf24d7e61306dd6a786dc3d0
