{
  "id": 2770294,
  "type": "Feature",
  "properties": {
    "tgn:hierarchy":[
        "tgn:2770294",
        "tgn:1000001",
        "tgn:7012149",
        "tgn:2000488",
        "tgn:7007250",
        "tgn:7029392"
    ],
    "tgn:id":2770294,
    "tgn:name":"Wild Horse Butte",
    "tgn:placetype":[
        "aat:300008798"
    ]
},
  "bbox": [],
  "geometry": {"coordinates":[-116.3167,43.1167],"type":"Point"}
}