{
  "id": 2287124,
  "type": "Feature",
  "properties": {
    "tgn:hierarchy":[
        "tgn:2287124",
        "tgn:1000001",
        "tgn:7012149",
        "tgn:7014185",
        "tgn:7007710",
        "tgn:7029392"
    ],
    "tgn:id":2287124,
    "tgn:name":"Dickerson Run",
    "tgn:placetype":[
        "aat:300008699"
    ]
},
  "bbox": [],
  "geometry": {"coordinates":[-79.65,40.0167],"type":"Point"}
}