{
  "id": 7261619,
  "type": "Feature",
  "properties": {
    "tgn:hierarchy":[
        "tgn:7261619",
        "tgn:1000003",
        "tgn:7003613",
        "tgn:7016845",
        "tgn:7029392"
    ],
    "tgn:id":7261619,
    "tgn:name:nl":"Eemshoeve",
    "tgn:placetype":[
        "aat:300000206"
    ]
},
  "bbox": [],
  "geometry": {"coordinates":[6.833333,53.416667],"type":"Point"}
}