{
  "id": 7394078,
  "type": "Feature",
  "properties": {
    "tgn:hierarchy":[
        "tgn:7394078",
        "tgn:1001835",
        "tgn:1000001",
        "tgn:7005560",
        "tgn:7029392"
    ],
    "tgn:id":7394078,
    "tgn:name":"San Gabriel, Punta",
    "tgn:placetype":[
        "aat:300386846"
    ]
},
  "bbox": [],
  "geometry": {"coordinates":[-112.866667,28.433333],"type":"Point"}
}