{
  "id": 7396147,
  "type": "Feature",
  "properties": {
    "tgn:hierarchy":[
        "tgn:7396147",
        "tgn:7005581",
        "tgn:1000001",
        "tgn:7005560",
        "tgn:7029392"
    ],
    "tgn:id":7396147,
    "tgn:name":"San Juan",
    "tgn:placetype":[
        "aat:300008347"
    ]
},
  "bbox": [],
  "geometry": {"coordinates":[-107.15,28.616667],"type":"Point"}
}