{
  "id": 7377839,
  "type": "Feature",
  "properties": {
    "tgn:hierarchy":[
        "tgn:7377839",
        "tgn:1000001",
        "tgn:7005595",
        "tgn:7005560",
        "tgn:7029392"
    ],
    "tgn:id":7377839,
    "tgn:name":"La Pitahayita",
    "tgn:placetype":[
        "aat:300008347"
    ]
},
  "bbox": [],
  "geometry": {"coordinates":[-106.860556,24.090833],"type":"Point"}
}