{
  "id": 7281879,
  "type": "Feature",
  "properties": {
    "tgn:hierarchy":[
        "tgn:7281879",
        "tgn:1001623",
        "tgn:1000049",
        "tgn:1000002",
        "tgn:7029392"
    ],
    "tgn:id":7281879,
    "tgn:name":"Steele, Estero",
    "tgn:placetype":[
        "aat:300008676"
    ]
},
  "bbox": [],
  "geometry": {"coordinates":[-73.283333,-48.15],"type":"Point"}
}