{
  "id": 2384369,
  "type": "Feature",
  "properties": {
    "tgn:hierarchy":[
        "tgn:2384369",
        "tgn:1000001",
        "tgn:7012149",
        "tgn:1002785",
        "tgn:7007920",
        "tgn:7029392"
    ],
    "tgn:id":2384369,
    "tgn:name":"Helen, Lake",
    "tgn:placetype":[
        "aat:300008680"
    ]
},
  "bbox": [],
  "geometry": {"coordinates":[-121.9333,46.8167],"type":"Point"}
}