{
  "id": 2394391,
  "type": "Feature",
  "properties": {
    "tgn:hierarchy":[
        "tgn:2394391",
        "tgn:1000001",
        "tgn:7012149",
        "tgn:7007157",
        "tgn:1002710",
        "tgn:7029392"
    ],
    "tgn:id":2394391,
    "tgn:name":"Hoge Mine",
    "tgn:placetype":[
        "aat:300000390"
    ]
},
  "bbox": [],
  "geometry": {"coordinates":[-120.9667,39.2833],"type":"Point"}
}