<<<<<<< HEAD
{
  "id": 7026139,
  "type": "Feature",
  "properties": {
    "tgn:hierarchy":[
        "tgn:7026139",
        "tgn:1002057",
        "tgn:1000004",
        "tgn:1000121",
        "tgn:7029392"
    ],
    "tgn:id":7026139,
    "tgn:name":"Tall Nimr\u012bn",
    "tgn:placetype":[
        "aat:300387007",
        "aat:300000810",
        "aat:300167671",
        "aat:300008389",
        "aat:300387238"
    ]
},
  "bbox": [],
  "geometry": {"coordinates":[35.629,31.903],"type":"Point"}
}
=======
{"geometry":{"type":"Point","coordinates":[35.629000,31.903000]},"type":"Feature","properties":{"hierarchy":["tgn:7026139","tgn:1002057","tgn:1000004","tgn:1000121","tgn:7029392"],"placetype":["aat:300387007","aat:300000810","aat:300167671","aat:300008389","aat:300387238"],"id":7026139,"name:xx":"Tall Nimr\u012bn"}}
>>>>>>> 03f74aca74312dbeaf24d7e61306dd6a786dc3d0
