{
  "id": 7035817,
  "type": "Feature",
  "properties": {
    "tgn:hierarchy":[
        "tgn:7035817",
        "tgn:7002991",
        "tgn:1000003",
        "tgn:7002997",
        "tgn:1000080",
        "tgn:7029392"
    ],
    "tgn:id":7035817,
    "tgn:name":"Terza Piccola, Monte",
    "tgn:placetype":[
        "aat:300008795"
    ]
},
  "bbox": [],
  "geometry": {"coordinates":[12.627222,46.563056],"type":"Point"}
}