{
  "id": 7031528,
  "type": "Feature",
  "properties": {
    "tgn:hierarchy":[
        "tgn:7031528",
        "tgn:7002445",
        "tgn:1000003",
        "tgn:7012032",
        "tgn:7008591",
        "tgn:7029392"
    ],
    "tgn:id":7031528,
    "tgn:name:en":"Langley Marsh",
    "tgn:placetype":[
        "aat:300008347"
    ]
},
  "bbox": [],
  "geometry": {"coordinates":[-3.321111,51.053333],"type":"Point"}
}