{
  "id": 1068068,
  "type": "Feature",
  "properties": {
    "tgn:hierarchy":[
        "tgn:1068068",
        "tgn:1000004",
        "tgn:7002079",
        "tgn:1000111",
        "tgn:7029392"
    ],
    "tgn:id":1068068,
    "tgn:name":"Fengzhou",
    "tgn:placetype":[
        "aat:300008347"
    ]
},
  "bbox": [],
  "geometry": {"coordinates":[113.8667,25.6833],"type":"Point"}
}