{
  "id": 7040477,
  "type": "Feature",
  "properties": {
    "tgn:hierarchy":[
        "tgn:7040477",
        "tgn:1000003",
        "tgn:7003122",
        "tgn:7003157",
        "tgn:1000080",
        "tgn:7029392"
    ],
    "tgn:id":7040477,
    "tgn:name":"Sant'Alessio Siculo",
    "tgn:placetype":[
        "aat:300008347"
    ]
},
  "bbox": [],
  "geometry": {"coordinates":[15.35,37.916667],"type":"Point"}
}