{
  "id": 7277443,
  "type": "Feature",
  "properties": {
    "tgn:hierarchy":[
        "tgn:7277443",
        "tgn:1001657",
        "tgn:1000049",
        "tgn:1000002",
        "tgn:7029392"
    ],
    "tgn:id":7277443,
    "tgn:name":"Vergara",
    "tgn:placetype":[
        "aat:300008347"
    ]
},
  "bbox": [],
  "geometry": {"coordinates":[-71.033333,-30.183333],"type":"Point"}
}