{
  "id": 2469157,
  "type": "Feature",
  "properties": {
    "tgn:hierarchy":[
        "tgn:2469157",
        "tgn:1000001",
        "tgn:7012149",
        "tgn:7007826",
        "tgn:7029392"
    ],
    "tgn:id":2469157,
    "tgn:name":"Long Valley Hollow",
    "tgn:placetype":[
        "aat:300008761"
    ]
},
  "bbox": [],
  "geometry": {"coordinates":[-99.0833,31.0833],"type":"Point"}
}