{
  "id": 7390037,
  "type": "Feature",
  "properties": {
    "tgn:hierarchy":[
        "tgn:7390037",
        "tgn:1001853",
        "tgn:1000001",
        "tgn:7005560",
        "tgn:7029392"
    ],
    "tgn:id":7390037,
    "tgn:name":"Rancho Rechupadero",
    "tgn:placetype":[
        "aat:300008347"
    ]
},
  "bbox": [],
  "geometry": {"coordinates":[-101.616667,27.666667],"type":"Point"}
}