{
  "id": 2569990,
  "type": "Feature",
  "properties": {
    "tgn:hierarchy":[
        "tgn:2569990",
        "tgn:1002201",
        "tgn:1000001",
        "tgn:7012149",
        "tgn:7007517",
        "tgn:7029392"
    ],
    "tgn:id":2569990,
    "tgn:name":"Paskamanset River",
    "tgn:placetype":[
        "aat:300008707"
    ]
},
  "bbox": [],
  "geometry": {"coordinates":[-70.9667,41.6667],"type":"Point"}
}