{
  "id": 2428455,
  "type": "Feature",
  "properties": {
    "tgn:hierarchy":[
        "tgn:2428455",
        "tgn:1000001",
        "tgn:2002242",
        "tgn:7012149",
        "tgn:7007920",
        "tgn:7029392"
    ],
    "tgn:id":2428455,
    "tgn:name":"Judson Lake",
    "tgn:placetype":[
        "aat:300008680"
    ]
},
  "bbox": [],
  "geometry": {"coordinates":[-119.4667,48.0333],"type":"Point"}
}