{
  "id": 7180219,
  "type": "Feature",
  "properties": {
    "tgn:hierarchy":[
        "tgn:7180219",
        "tgn:7003692",
        "tgn:1000003",
        "tgn:7000084",
        "tgn:7029392"
    ],
    "tgn:id":7180219,
    "tgn:name":"Fuchseckhof",
    "tgn:placetype":[
        "aat:300000206"
    ]
},
  "bbox": [],
  "geometry": {"coordinates":[9.683333,48.65],"type":"Point"}
}