{
  "id": 7293019,
  "type": "Feature",
  "properties": {
    "tgn:hierarchy":[
        "tgn:7293019",
        "tgn:1001657",
        "tgn:1000049",
        "tgn:1000002",
        "tgn:7029392"
    ],
    "tgn:id":7293019,
    "tgn:name":"El Sauce",
    "tgn:placetype":[
        "aat:300387200"
    ]
},
  "bbox": [],
  "geometry": {"coordinates":[-71.616667,-30.516667],"type":"Point"}
}