{
  "id": 2465347,
  "type": "Feature",
  "properties": {
    "tgn:hierarchy":[
        "tgn:2465347",
        "tgn:1000001",
        "tgn:7012149",
        "tgn:1002897",
        "tgn:7007920",
        "tgn:7029392"
    ],
    "tgn:id":2465347,
    "tgn:name":"Lone Butte Quarry",
    "tgn:placetype":[
        "aat:300000390"
    ]
},
  "bbox": [],
  "geometry": {"coordinates":[-121.8333,46.05],"type":"Point"}
}