<<<<<<< HEAD
{
  "id": 7052226,
  "type": "Feature",
  "properties": {
    "tgn:hierarchy":[
        "tgn:7052226",
        "tgn:1003483",
        "tgn:1000003",
        "tgn:7003240",
        "tgn:1000080",
        "tgn:7029392"
    ],
    "tgn:id":7052226,
    "tgn:name":"Isola del Piano",
    "tgn:placetype":[
        "aat:300008347"
    ]
},
  "bbox": [],
  "geometry": {"coordinates":[12.783333,43.733333],"type":"Point"}
}
=======
{"geometry":{"type":"Point","coordinates":[12.783333,43.733333]},"type":"Feature","properties":{"hierarchy":["tgn:7052226","tgn:1003483","tgn:1000003","tgn:7003240","tgn:1000080","tgn:7029392"],"placetype":["aat:300008347"],"id":7052226,"name:xx":"Isola del Piano"}}
>>>>>>> 03f74aca74312dbeaf24d7e61306dd6a786dc3d0
