{
  "id": 7337260,
  "type": "Feature",
  "properties": {
    "tgn:hierarchy":[
        "tgn:7337260",
        "tgn:7002844",
        "tgn:7030216",
        "tgn:1000003",
        "tgn:1000095",
        "tgn:7029392"
    ],
    "tgn:id":7337260,
    "tgn:name":"Ciurana de Tarragona",
    "tgn:placetype":[
        "aat:300008347"
    ]
},
  "bbox": [],
  "geometry": {"coordinates":[0.933333,41.25],"type":"Point"}
}