<<<<<<< HEAD
{
  "id": 7363311,
  "type": "Feature",
  "properties": {
    "tgn:hierarchy":[
        "tgn:7363311",
        "tgn:1000001",
        "tgn:7005597",
        "tgn:7005560",
        "tgn:7029392"
    ],
    "tgn:id":7363311,
    "tgn:name":"El Cerrito",
    "tgn:placetype":[
        "aat:300008347"
    ]
},
  "bbox": [],
  "geometry": {"coordinates":[-99.406667,24.211389],"type":"Point"}
}
=======
{"geometry":{"type":"Point","coordinates":[-99.406667,24.211389]},"type":"Feature","properties":{"hierarchy":["tgn:7363311","tgn:1000001","tgn:7005597","tgn:7005560","tgn:7029392"],"placetype":["aat:300008347"],"id":7363311,"name:xx":"El Cerrito"}}
>>>>>>> 03f74aca74312dbeaf24d7e61306dd6a786dc3d0
