{
  "id": 7427605,
  "type": "Feature",
  "properties": {
    "tgn:hierarchy":[
        "tgn:7427605",
        "tgn:1000001",
        "tgn:7005601",
        "tgn:7005560",
        "tgn:7029392"
    ],
    "tgn:id":7427605,
    "tgn:name":"Rancho Verde",
    "tgn:placetype":[
        "aat:300008347"
    ]
},
  "bbox": [],
  "geometry": {"coordinates":[-102.166667,23.783333],"type":"Point"}
}