{
  "id": 2329743,
  "type": "Feature",
  "properties": {
    "tgn:hierarchy":[
        "tgn:2329743",
        "tgn:1000001",
        "tgn:7012149",
        "tgn:2002160",
        "tgn:7007919",
        "tgn:7029392"
    ],
    "tgn:id":2329743,
    "tgn:name":"Fivemile Mountain",
    "tgn:placetype":[
        "aat:300008798"
    ]
},
  "bbox": [],
  "geometry": {"coordinates":[-80.1167,36.9833],"type":"Point"}
}