{
  "id": 2386078,
  "type": "Feature",
  "properties": {
    "tgn:hierarchy":[
        "tgn:2386078",
        "tgn:1000001",
        "tgn:7012149",
        "tgn:1002314",
        "tgn:7007240",
        "tgn:7029392"
    ],
    "tgn:id":2386078,
    "tgn:name":"Henry Lake",
    "tgn:placetype":[
        "aat:300008680"
    ]
},
  "bbox": [],
  "geometry": {"coordinates":[-80.75,25.1833],"type":"Point"}
}