{
  "id": 2575536,
  "type": "Feature",
  "properties": {
    "tgn:hierarchy":[
        "tgn:2575536",
        "tgn:1000001",
        "tgn:7012149",
        "tgn:2001253",
        "tgn:7007523",
        "tgn:7029392"
    ],
    "tgn:id":2575536,
    "tgn:name":"Pepper Hill",
    "tgn:placetype":[
        "aat:300008798"
    ]
},
  "bbox": [],
  "geometry": {"coordinates":[-94.2167,37.9833],"type":"Point"}
}