{
  "id": 2011301,
  "type": "Feature",
  "properties": {
    "tgn:hierarchy":[
        "tgn:2011301",
        "tgn:1000001",
        "tgn:7012149",
        "tgn:1002350",
        "tgn:7007157",
        "tgn:7029392"
    ],
    "tgn:id":2011301,
    "tgn:name":"Fallen Leaf",
    "tgn:placetype":[
        "aat:300008347",
        "aat:300387247"
    ]
},
  "bbox": [],
  "geometry": {"coordinates":[-120.0667,38.8667],"type":"Point"}
}