<<<<<<< HEAD
{
  "id": 7112208,
  "type": "Feature",
  "properties": {
    "tgn:hierarchy":[
        "tgn:7112208",
        "tgn:7003692",
        "tgn:1000003",
        "tgn:7000084",
        "tgn:7029392"
    ],
    "tgn:id":7112208,
    "tgn:name":"Ro\u00dfberg",
    "tgn:placetype":[
        "aat:300008777"
    ]
},
  "bbox": [],
  "geometry": {"coordinates":[9.333333,48.5],"type":"Point"}
}
=======
{"geometry":{"type":"Point","coordinates":[9.333333,48.500000]},"type":"Feature","properties":{"hierarchy":["tgn:7112208","tgn:7003692","tgn:1000003","tgn:7000084","tgn:7029392"],"placetype":["aat:300008777"],"id":7112208,"name:xx":"Ro\u00dfberg"}}
>>>>>>> 03f74aca74312dbeaf24d7e61306dd6a786dc3d0
