<<<<<<< HEAD
{
  "id": 2158670,
  "type": "Feature",
  "properties": {
    "tgn:hierarchy":[
        "tgn:2158670",
        "tgn:1000001",
        "tgn:7012149",
        "tgn:2000230",
        "tgn:7007158",
        "tgn:7029392"
    ],
    "tgn:id":2158670,
    "tgn:name":"Beavertail Mountain",
    "tgn:placetype":[
        "aat:300008850"
    ]
},
  "bbox": [],
  "geometry": {"coordinates":[-108.2667,39.1833],"type":"Point"}
}
=======
{"geometry":{"type":"Point","coordinates":[-108.266700,39.183300]},"type":"Feature","properties":{"hierarchy":["tgn:2158670","tgn:1000001","tgn:7012149","tgn:2000230","tgn:7007158","tgn:7029392"],"placetype":["aat:300008850"],"id":2158670,"name:xx":"Beavertail Mountain"}}
>>>>>>> 03f74aca74312dbeaf24d7e61306dd6a786dc3d0
