{
  "id": 1072465,
  "type": "Feature",
  "properties": {
    "tgn:hierarchy":[
        "tgn:1072465",
        "tgn:1000004",
        "tgn:7002079",
        "tgn:1000111",
        "tgn:7029392"
    ],
    "tgn:id":1072465,
    "tgn:name":"Wangling",
    "tgn:placetype":[
        "aat:300008347"
    ]
},
  "bbox": [],
  "geometry": {"coordinates":[113.4333,27.2333],"type":"Point"}
}