{
  "id": 2569428,
  "type": "Feature",
  "properties": {
    "tgn:hierarchy":[
        "tgn:2569428",
        "tgn:2000946",
        "tgn:1000001",
        "tgn:7012149",
        "tgn:7007520",
        "tgn:7029392"
    ],
    "tgn:id":2569428,
    "tgn:name":"Parmalee Creek",
    "tgn:placetype":[
        "aat:300008706"
    ]
},
  "bbox": [],
  "geometry": {"coordinates":[-84.0333,44.05],"type":"Point"}
}