{
  "id": 2582594,
  "type": "Feature",
  "properties": {
    "tgn:hierarchy":[
        "tgn:2582594",
        "tgn:1000001",
        "tgn:1002328",
        "tgn:7012149",
        "tgn:7007568",
        "tgn:7029392"
    ],
    "tgn:id":2582594,
    "tgn:name":"Pine Hill",
    "tgn:placetype":[
        "aat:300008798"
    ]
},
  "bbox": [],
  "geometry": {"coordinates":[-75.0833,42.1833],"type":"Point"}
}