{
  "id": 7214780,
  "type": "Feature",
  "properties": {
    "tgn:hierarchy":[
        "tgn:7214780",
        "tgn:1000003",
        "tgn:7003676",
        "tgn:7000084",
        "tgn:7029392"
    ],
    "tgn:id":7214780,
    "tgn:name":"Bohmterheide",
    "tgn:placetype":[
        "aat:300386887"
    ]
},
  "bbox": [],
  "geometry": {"coordinates":[8.333333,52.383333],"type":"Point"}
}