<<<<<<< HEAD
{
  "id": 7052300,
  "type": "Feature",
  "properties": {
    "tgn:hierarchy":[
        "tgn:7052300",
        "tgn:1001730",
        "tgn:1000003",
        "tgn:7003121",
        "tgn:1000080",
        "tgn:7029392"
    ],
    "tgn:id":7052300,
    "tgn:name":"Peloso, Isolotto",
    "tgn:placetype":[
        "aat:300008791"
    ]
},
  "bbox": [],
  "geometry": {"coordinates":[8.4,40.05],"type":"Point"}
}
=======
{"geometry":{"type":"Point","coordinates":[8.400000,40.050000]},"type":"Feature","properties":{"hierarchy":["tgn:7052300","tgn:1001730","tgn:1000003","tgn:7003121","tgn:1000080","tgn:7029392"],"placetype":["aat:300008791"],"id":7052300,"name:xx":"Peloso, Isolotto"}}
>>>>>>> 03f74aca74312dbeaf24d7e61306dd6a786dc3d0
