{
  "id": 7229098,
  "type": "Feature",
  "properties": {
    "tgn:hierarchy":[
        "tgn:7229098",
        "tgn:7011170",
        "tgn:7002715",
        "tgn:1000003",
        "tgn:1000074",
        "tgn:7029392"
    ],
    "tgn:id":7229098,
    "tgn:name":"K\u00edrnos",
    "tgn:placetype":[
        "aat:300008347"
    ]
},
  "bbox": [],
  "geometry": {"coordinates":[24.783333,40.983333],"type":"Point"}
}