{
  "id": 7480466,
  "type": "Feature",
  "properties": {
    "tgn:hierarchy":[
        "tgn:7480466",
        "tgn:1000004",
        "tgn:7490934",
        "tgn:1000141",
        "tgn:7029392"
    ],
    "tgn:id":7480466,
    "tgn:name":"Yuzhong Qiao",
    "tgn:placetype":[
        "aat:300007836"
    ]
},
  "bbox": [],
  "geometry": {"coordinates":[120.390382,23.098512],"type":"Point"}
}