<<<<<<< HEAD
{
  "id": 7480466,
  "type": "Feature",
  "properties": {
    "tgn:hierarchy":[
        "tgn:7480466",
        "tgn:1000004",
        "tgn:7490934",
        "tgn:1000141",
        "tgn:7029392"
    ],
    "tgn:id":7480466,
    "tgn:name":"Yuzhong Qiao",
    "tgn:placetype":[
        "aat:300007836"
    ]
},
  "bbox": [],
  "geometry": {"coordinates":[120.390382,23.098512],"type":"Point"}
}
=======
{"geometry":{"type":"Point","coordinates":[120.390382,23.098512]},"type":"Feature","properties":{"hierarchy":["tgn:7480466","tgn:1000004","tgn:7490934","tgn:1000141","tgn:7029392"],"placetype":["aat:300007836"],"id":7480466,"name:xx":"Yuzhong Qiao"}}
>>>>>>> 03f74aca74312dbeaf24d7e61306dd6a786dc3d0
