{
  "id": 7528612,
  "type": "Feature",
  "properties": {
    "tgn:hierarchy":[
        "tgn:7528612",
        "tgn:7001242",
        "tgn:7016833",
        "tgn:1001418",
        "tgn:7029392"
    ],
    "tgn:id":7528612,
    "tgn:name:en":"Sullam, Naqb as",
    "tgn:placetype":[
        "aat:300259572"
    ]
},
  "bbox": [],
  "geometry": {"coordinates":[28.55,27.766667],"type":"Point"}
}