{
  "id": 2145512,
  "type": "Feature",
  "properties": {
    "tgn:hierarchy":[
        "tgn:2145512",
        "tgn:1000001",
        "tgn:2000682",
        "tgn:7012149",
        "tgn:7007254",
        "tgn:7029392"
    ],
    "tgn:id":2145512,
    "tgn:name":"Baldwin City Lake",
    "tgn:placetype":[
        "aat:300006191"
    ]
},
  "bbox": [],
  "geometry": {"coordinates":[-95.15,38.75],"type":"Point"}
}