{
  "id": 2476332,
  "type": "Feature",
  "properties": {
    "tgn:hierarchy":[
        "tgn:2476332",
        "tgn:1000001",
        "tgn:7012149",
        "tgn:2001706",
        "tgn:7007708",
        "tgn:7029392"
    ],
    "tgn:id":2476332,
    "tgn:name":"Lunch Ridge",
    "tgn:placetype":[
        "aat:300266640"
    ]
},
  "bbox": [],
  "geometry": {"coordinates":[-123.95,43.7167],"type":"Point"}
}