{
  "id": 2744317,
  "type": "Feature",
  "properties": {
    "tgn:hierarchy":[
        "tgn:2744317",
        "tgn:1000001",
        "tgn:7012149",
        "tgn:1002512",
        "tgn:7007252",
        "tgn:7029392"
    ],
    "tgn:id":2744317,
    "tgn:name":"Vernigor Ditch",
    "tgn:placetype":[
        "aat:300006075"
    ]
},
  "bbox": [],
  "geometry": {"coordinates":[-87.0667,41.0833],"type":"Point"}
}