{
  "id": 7576356,
  "type": "Feature",
  "properties": {
    "tgn:hierarchy":[
        "tgn:7576356",
        "tgn:1000004",
        "tgn:7000198",
        "tgn:7016883",
        "tgn:7029392"
    ],
    "tgn:id":7576356,
    "tgn:name:en":"Landhow\u0101l",
    "tgn:placetype":[
        "aat:300007783"
    ]
},
  "bbox": [],
  "geometry": {"coordinates":[75.794353,30.977576],"type":"Point"}
}