{
  "id": 7590230,
  "type": "Feature",
  "properties": {
    "tgn:hierarchy":[
        "tgn:7590230",
        "tgn:1000004",
        "tgn:1001871",
        "tgn:7000198",
        "tgn:7029392"
    ],
    "tgn:id":7590230,
    "tgn:name:en":"Bar\u0101na",
    "tgn:placetype":[
        "aat:300008347"
    ]
},
  "bbox": [],
  "geometry": {"coordinates":[76.914187,29.880319],"type":"Point"}
}