{
  "id": 7581458,
  "type": "Feature",
  "properties": {
    "tgn:hierarchy":[
        "tgn:7581458",
        "tgn:1000004",
        "tgn:7000198",
        "tgn:7001797",
        "tgn:7029392"
    ],
    "tgn:id":7581458,
    "tgn:name:en":"Tirun\u0101manall\u016br",
    "tgn:placetype":[
        "aat:300008347"
    ]
},
  "bbox": [],
  "geometry": {"coordinates":[79.416667,11.766667],"type":"Point"}
}