{
  "id": 2664705,
  "type": "Feature",
  "properties": {
    "tgn:hierarchy":[
        "tgn:2664705",
        "tgn:1000001",
        "tgn:7014090",
        "tgn:7012149",
        "tgn:7007565",
        "tgn:7029392"
    ],
    "tgn:id":2664705,
    "tgn:name":"Simmons Pond",
    "tgn:placetype":[
        "aat:300006191"
    ]
},
  "bbox": [],
  "geometry": {"coordinates":[-74.0667,40.3167],"type":"Point"}
}