{
  "id": 7526600,
  "type": "Feature",
  "properties": {
    "tgn:hierarchy":[
        "tgn:7526600",
        "tgn:7001242",
        "tgn:7016833",
        "tgn:1001091",
        "tgn:7029392"
    ],
    "tgn:id":7526600,
    "tgn:name":"Sakan Mad\u012bnat al Fut\u016b\u1e29",
    "tgn:placetype":[
        "aat:300000745"
    ]
},
  "bbox": [],
  "geometry": {"coordinates":[31.295818,30.124331],"type":"Point"}
}