{
  "id": 2341973,
  "type": "Feature",
  "properties": {
    "tgn:hierarchy":[
        "tgn:2341973",
        "tgn:1000001",
        "tgn:7006451",
        "tgn:7012149",
        "tgn:2000098",
        "tgn:7029392"
    ],
    "tgn:id":2341973,
    "tgn:name":"Fry Mine",
    "tgn:placetype":[
        "aat:300000390"
    ]
},
  "bbox": [],
  "geometry": {"coordinates":[-114.25,35.7833],"type":"Point"}
}