{
  "id": 1069260,
  "type": "Feature",
  "properties": {
    "tgn:hierarchy":[
        "tgn:1069260",
        "tgn:1000004",
        "tgn:7002087",
        "tgn:1000111",
        "tgn:7029392"
    ],
    "tgn:id":1069260,
    "tgn:name":"Jijiamiao",
    "tgn:placetype":[
        "aat:300008347"
    ]
},
  "bbox": [],
  "geometry": {"coordinates":[104.1167,29.3167],"type":"Point"}
}