{
  "id": 2382441,
  "type": "Feature",
  "properties": {
    "tgn:hierarchy":[
        "tgn:2382441",
        "tgn:1000001",
        "tgn:7012149",
        "tgn:2001281",
        "tgn:7007524",
        "tgn:7029392"
    ],
    "tgn:id":2382441,
    "tgn:name":"Haystack Creek",
    "tgn:placetype":[
        "aat:300008706"
    ]
},
  "bbox": [],
  "geometry": {"coordinates":[-111.8333,46.4833],"type":"Point"}
}