{
  "id": 1112855,
  "type": "Feature",
  "properties": {
    "tgn:hierarchy":[
        "tgn:1112855",
        "tgn:1001861",
        "tgn:1000002",
        "tgn:1000059",
        "tgn:7029392"
    ],
    "tgn:id":1112855,
    "tgn:name":"Coro, Golfete de",
    "tgn:placetype":[
        "aat:300132316"
    ]
},
  "bbox": [],
  "geometry": {"coordinates":[-69.8833,11.5667],"type":"Point"}
}