{
  "id": 2112150,
  "type": "Feature",
  "properties": {
    "tgn:hierarchy":[
        "tgn:2112150",
        "tgn:1000001",
        "tgn:7012149",
        "tgn:2002188",
        "tgn:7007919",
        "tgn:7029392"
    ],
    "tgn:id":2112150,
    "tgn:name":"Hansonville",
    "tgn:placetype":[
        "aat:300008347"
    ]
},
  "bbox": [],
  "geometry": {"coordinates":[-82.1333,36.8167],"type":"Point"}
}