{
  "id": 7402067,
  "type": "Feature",
  "properties": {
    "tgn:hierarchy":[
        "tgn:7402067",
        "tgn:1000001",
        "tgn:7005600",
        "tgn:7005560",
        "tgn:7029392"
    ],
    "tgn:id":7402067,
    "tgn:name":"Xnibacal",
    "tgn:placetype":[
        "aat:300008347"
    ]
},
  "bbox": [],
  "geometry": {"coordinates":[-89.45,20.204167],"type":"Point"}
}