{
  "id": 7565966,
  "type": "Feature",
  "properties": {
    "tgn:hierarchy":[
        "tgn:7565966",
        "tgn:1000004",
        "tgn:7000198",
        "tgn:7016722",
        "tgn:7029392"
    ],
    "tgn:id":7565966,
    "tgn:name:en":"At\u0101kua",
    "tgn:placetype":[
        "aat:300008347"
    ]
},
  "bbox": [],
  "geometry": {"coordinates":[79.39001,26.403747],"type":"Point"}
}