<<<<<<< HEAD
{
  "id": 2256610,
  "type": "Feature",
  "properties": {
    "tgn:hierarchy":[
        "tgn:2256610",
        "tgn:1000001",
        "tgn:7012149",
        "tgn:2002060",
        "tgn:7007826",
        "tgn:7029392"
    ],
    "tgn:id":2256610,
    "tgn:name":"Cord Spring Draw",
    "tgn:placetype":[
        "aat:300008761"
    ]
},
  "bbox": [],
  "geometry": {"coordinates":[-99.9,29.7667],"type":"Point"}
}
=======
{"geometry":{"type":"Point","coordinates":[-99.900000,29.766700]},"type":"Feature","properties":{"hierarchy":["tgn:2256610","tgn:1000001","tgn:7012149","tgn:2002060","tgn:7007826","tgn:7029392"],"placetype":["aat:300008761"],"id":2256610,"name:xx":"Cord Spring Draw"}}
>>>>>>> 03f74aca74312dbeaf24d7e61306dd6a786dc3d0
