{
  "id": 7501138,
  "type": "Feature",
  "properties": {
    "tgn:hierarchy":[
        "tgn:7501138",
        "tgn:7488858",
        "tgn:1000004",
        "tgn:1000141",
        "tgn:7029392"
    ],
    "tgn:id":7501138,
    "tgn:name":"Songshan Xi",
    "tgn:placetype":[
        "aat:300008699"
    ]
},
  "bbox": [],
  "geometry": {"coordinates":[120.861667,23.541111],"type":"Point"}
}