{
  "id": 1133808,
  "type": "Feature",
  "properties": {
    "tgn:hierarchy":[
        "tgn:1133808",
        "tgn:1000001",
        "tgn:2001945",
        "tgn:7012149",
        "tgn:7007826",
        "tgn:7029392"
    ],
    "tgn:id":1133808,
    "tgn:name":"Maxon Creek",
    "tgn:placetype":[
        "aat:300008706"
    ]
},
  "bbox": [],
  "geometry": {"coordinates":[-102.95,30.05],"type":"Point"}
}