{
  "id": 2369430,
  "type": "Feature",
  "properties": {
    "tgn:hierarchy":[
        "tgn:2369430",
        "tgn:1000001",
        "tgn:1002328",
        "tgn:7012149",
        "tgn:7007568",
        "tgn:7029392"
    ],
    "tgn:id":2369430,
    "tgn:name":"Gun Hollow",
    "tgn:placetype":[
        "aat:300008761"
    ]
},
  "bbox": [],
  "geometry": {"coordinates":[-74.7833,42.0667],"type":"Point"}
}