{
  "id": 7440082,
  "type": "Feature",
  "properties": {
    "tgn:hierarchy":[
        "tgn:7440082",
        "tgn:7005580",
        "tgn:1000001",
        "tgn:7005560",
        "tgn:7029392"
    ],
    "tgn:id":7440082,
    "tgn:name":"Santa Cecilia",
    "tgn:placetype":[
        "aat:300008347"
    ]
},
  "bbox": [],
  "geometry": {"coordinates":[-92.35,15.05],"type":"Point"}
}