{
  "id": 7306216,
  "type": "Feature",
  "properties": {
    "tgn:hierarchy":[
        "tgn:7306216",
        "tgn:7002822",
        "tgn:1001647",
        "tgn:1000003",
        "tgn:1000095",
        "tgn:7029392"
    ],
    "tgn:id":7306216,
    "tgn:name":"Matallana",
    "tgn:placetype":[
        "aat:300008347"
    ]
},
  "bbox": [],
  "geometry": {"coordinates":[-3.333333,41.05],"type":"Point"}
}