{
  "id": 2747973,
  "type": "Feature",
  "properties": {
    "tgn:hierarchy":[
        "tgn:2747973",
        "tgn:1000001",
        "tgn:7012149",
        "tgn:2000220",
        "tgn:7007158",
        "tgn:7029392"
    ],
    "tgn:id":2747973,
    "tgn:name":"Walden Reservoir",
    "tgn:placetype":[
        "aat:300006191"
    ]
},
  "bbox": [],
  "geometry": {"coordinates":[-106.2833,40.7167],"type":"Point"}
}