{
  "id": 2204619,
  "type": "Feature",
  "properties": {
    "tgn:hierarchy":[
        "tgn:2204619",
        "tgn:7002659",
        "tgn:1000001",
        "tgn:7012149",
        "tgn:2000044",
        "tgn:7029392"
    ],
    "tgn:id":2204619,
    "tgn:name":"Buffalo Island",
    "tgn:placetype":[
        "aat:300008791"
    ]
},
  "bbox": [],
  "geometry": {"coordinates":[-86.4333,34.65],"type":"Point"}
}