{
  "id": 2674317,
  "type": "Feature",
  "properties": {
    "tgn:hierarchy":[
        "tgn:2674317",
        "tgn:1000001",
        "tgn:7012149",
        "tgn:7007524",
        "tgn:7029392"
    ],
    "tgn:id":2674317,
    "tgn:name":"Snowslide Creek",
    "tgn:placetype":[
        "aat:300008706"
    ]
},
  "bbox": [],
  "geometry": {"coordinates":[-111.1667,44.95],"type":"Point"}
}