{
  "id": 2148610,
  "type": "Feature",
  "properties": {
    "tgn:hierarchy":[
        "tgn:2148610",
        "tgn:1000001",
        "tgn:7012149",
        "tgn:2001622",
        "tgn:7007706",
        "tgn:7029392"
    ],
    "tgn:id":2148610,
    "tgn:name":"Barnes Hollow",
    "tgn:placetype":[
        "aat:300008761"
    ]
},
  "bbox": [],
  "geometry": {"coordinates":[-81.2167,39.4833],"type":"Point"}
}