{
  "id": 1035852,
  "type": "Feature",
  "properties": {
    "tgn:hierarchy":[
        "tgn:1035852",
        "tgn:7002871",
        "tgn:1000003",
        "tgn:1000070",
        "tgn:7029392"
    ],
    "tgn:id":1035852,
    "tgn:name":"Thiers",
    "tgn:placetype":[
        "aat:300008347"
    ]
},
  "bbox": [],
  "geometry": {"coordinates":[3.55,45.85],"type":"Point"}
}