{
  "id": 7387195,
  "type": "Feature",
  "properties": {
    "tgn:hierarchy":[
        "tgn:7387195",
        "tgn:1000001",
        "tgn:7005597",
        "tgn:7005560",
        "tgn:7029392"
    ],
    "tgn:id":7387195,
    "tgn:name":"Perroso, Cerro",
    "tgn:placetype":[
        "aat:300008795"
    ]
},
  "bbox": [],
  "geometry": {"coordinates":[-99.066667,24.516667],"type":"Point"}
}