{
  "id": 7203090,
  "type": "Feature",
  "properties": {
    "tgn:hierarchy":[
        "tgn:7203090",
        "tgn:7003669",
        "tgn:1000003",
        "tgn:7000084",
        "tgn:7029392"
    ],
    "tgn:id":7203090,
    "tgn:name":"Brunnen-K\u00f6pfel",
    "tgn:placetype":[
        "aat:300008795"
    ]
},
  "bbox": [],
  "geometry": {"coordinates":[10.966667,47.55],"type":"Point"}
}