{
  "id": 2242083,
  "type": "Feature",
  "properties": {
    "tgn:hierarchy":[
        "tgn:2242083",
        "tgn:1000001",
        "tgn:2002259",
        "tgn:7012149",
        "tgn:7013961",
        "tgn:7029392"
    ],
    "tgn:id":2242083,
    "tgn:name":"Clay Junction",
    "tgn:placetype":[
        "aat:300008347"
    ]
},
  "bbox": [],
  "geometry": {"coordinates":[-81.0667,38.4667],"type":"Point"}
}