{
  "id": 2494194,
  "type": "Feature",
  "properties": {
    "tgn:hierarchy":[
        "tgn:2494194",
        "tgn:1000001",
        "tgn:2001011",
        "tgn:7012149",
        "tgn:7007521",
        "tgn:7029392"
    ],
    "tgn:id":2494194,
    "tgn:name":"Martha, Lake",
    "tgn:placetype":[
        "aat:300008680"
    ]
},
  "bbox": [],
  "geometry": {"coordinates":[-92.8833,45.3667],"type":"Point"}
}