{
  "id": 7406118,
  "type": "Feature",
  "properties": {
    "tgn:hierarchy":[
        "tgn:7406118",
        "tgn:7005585",
        "tgn:1000001",
        "tgn:7005560",
        "tgn:7029392"
    ],
    "tgn:id":7406118,
    "tgn:name":"Maldonado",
    "tgn:placetype":[
        "aat:300008347"
    ]
},
  "bbox": [],
  "geometry": {"coordinates":[-98.608333,16.483333],"type":"Point"}
}