{
  "id": 7594154,
  "type": "Feature",
  "properties": {
    "tgn:hierarchy":[
        "tgn:7594154",
        "tgn:7006444",
        "tgn:1000003",
        "tgn:7006417",
        "tgn:7029392"
    ],
    "tgn:id":7594154,
    "tgn:name":"Shurdhahit, Ishulli i",
    "tgn:placetype":[
        "aat:300008791"
    ]
},
  "bbox": [],
  "geometry": {"coordinates":[19.652781,42.070879],"type":"Point"}
}