{
  "id": 7405331,
  "type": "Feature",
  "properties": {
    "tgn:hierarchy":[
        "tgn:7405331",
        "tgn:7005585",
        "tgn:1000001",
        "tgn:7005560",
        "tgn:7029392"
    ],
    "tgn:id":7405331,
    "tgn:name":"El Papayo",
    "tgn:placetype":[
        "aat:300008347"
    ]
},
  "bbox": [],
  "geometry": {"coordinates":[-101.25,17.683333],"type":"Point"}
}