{
  "id": 7530786,
  "type": "Feature",
  "properties": {
    "tgn:hierarchy":[
        "tgn:7530786",
        "tgn:7001242",
        "tgn:7016833",
        "tgn:1001083",
        "tgn:7029392"
    ],
    "tgn:id":7530786,
    "tgn:name":"Ma\u1e29a\u0163\u0163at Qi\u0163\u0101r\u0101t al J\u012bzah",
    "tgn:placetype":[
        "aat:300007783"
    ]
},
  "bbox": [],
  "geometry": {"coordinates":[31.207555,30.009929],"type":"Point"}
}