{
  "id": 2181363,
  "type": "Feature",
  "properties": {
    "tgn:hierarchy":[
        "tgn:2181363",
        "tgn:1000001",
        "tgn:2001350",
        "tgn:7012149",
        "tgn:7007525",
        "tgn:7029392"
    ],
    "tgn:id":2181363,
    "tgn:name":"Blue Creek Ditch",
    "tgn:placetype":[
        "aat:300006075"
    ]
},
  "bbox": [],
  "geometry": {"coordinates":[-102.3833,41.6833],"type":"Point"}
}