{
  "id": 7319997,
  "type": "Feature",
  "properties": {
    "tgn:hierarchy":[
        "tgn:7319997",
        "tgn:1001623",
        "tgn:1000049",
        "tgn:1000002",
        "tgn:7029392"
    ],
    "tgn:id":7319997,
    "tgn:name":"Bah\u00eda Adventure",
    "tgn:placetype":[
        "aat:300006495"
    ]
},
  "bbox": [],
  "geometry": {"coordinates":[-74.75,-44.833333],"type":"Point"}
}