<<<<<<< HEAD
{
  "id": 2338732,
  "type": "Feature",
  "properties": {
    "tgn:hierarchy":[
        "tgn:2338732",
        "tgn:1000001",
        "tgn:2000459",
        "tgn:7012149",
        "tgn:7007250",
        "tgn:7029392"
    ],
    "tgn:id":2338732,
    "tgn:name":"Franer Canal",
    "tgn:placetype":[
        "aat:300006075"
    ]
},
  "bbox": [],
  "geometry": {"coordinates":[-115.7667,43.85],"type":"Point"}
}
=======
{"geometry":{"type":"Point","coordinates":[-115.766700,43.850000]},"type":"Feature","properties":{"hierarchy":["tgn:2338732","tgn:1000001","tgn:2000459","tgn:7012149","tgn:7007250","tgn:7029392"],"placetype":["aat:300006075"],"id":2338732,"name:xx":"Franer Canal"}}
>>>>>>> 03f74aca74312dbeaf24d7e61306dd6a786dc3d0
