{
  "id": 7435637,
  "type": "Feature",
  "properties": {
    "tgn:hierarchy":[
        "tgn:7435637",
        "tgn:7005583",
        "tgn:1000001",
        "tgn:7005560",
        "tgn:7029392"
    ],
    "tgn:id":7435637,
    "tgn:name":"Vado de Luis",
    "tgn:placetype":[
        "aat:300008347"
    ]
},
  "bbox": [],
  "geometry": {"coordinates":[-106.716667,25.35],"type":"Point"}
}