{
  "id": 1062550,
  "type": "Feature",
  "properties": {
    "tgn:hierarchy":[
        "tgn:1062550",
        "tgn:7007780",
        "tgn:1000003",
        "tgn:7009604",
        "tgn:1000095",
        "tgn:7029392"
    ],
    "tgn:id":1062550,
    "tgn:name":"Tolosa",
    "tgn:placetype":[
        "aat:300008347"
    ]
},
  "bbox": [],
  "geometry": {"coordinates":[-2.066667,43.133333],"type":"Point"}
}