{
  "id": 2671932,
  "type": "Feature",
  "properties": {
    "tgn:hierarchy":[
        "tgn:2671932",
        "tgn:1000001",
        "tgn:7012149",
        "tgn:2002297",
        "tgn:7013961",
        "tgn:7029392"
    ],
    "tgn:id":2671932,
    "tgn:name":"Smith Ridge",
    "tgn:placetype":[
        "aat:300266640"
    ]
},
  "bbox": [],
  "geometry": {"coordinates":[-80.9833,39.5333],"type":"Point"}
}