{
  "id": 2109997,
  "type": "Feature",
  "properties": {
    "tgn:hierarchy":[
        "tgn:2109997",
        "tgn:1000001",
        "tgn:2002135",
        "tgn:7012149",
        "tgn:7007828",
        "tgn:7029392"
    ],
    "tgn:id":2109997,
    "tgn:name":"Shady Rill",
    "tgn:placetype":[
        "aat:300008347",
        "aat:300387210"
    ]
},
  "bbox": [],
  "geometry": {"coordinates":[-72.5833,44.3333],"type":"Point"}
}