{
  "id": 1131895,
  "type": "Feature",
  "properties": {
    "tgn:hierarchy":[
        "tgn:1131895",
        "tgn:1000004",
        "tgn:1000111",
        "tgn:7029392"
    ],
    "tgn:id":1131895,
    "tgn:name":"Wu Shui",
    "tgn:placetype":[
        "aat:300008707"
    ]
},
  "bbox": [],
  "geometry": {"coordinates":[109.8333,26.6667],"type":"Point"}
}