{
  "id": 2403586,
  "type": "Feature",
  "properties": {
    "tgn:hierarchy":[
        "tgn:2403586",
        "tgn:1000001",
        "tgn:7012149",
        "tgn:2001109",
        "tgn:7007522",
        "tgn:7029392"
    ],
    "tgn:id":2403586,
    "tgn:name":"Howard Creek",
    "tgn:placetype":[
        "aat:300008706"
    ]
},
  "bbox": [],
  "geometry": {"coordinates":[-88.9667,30.5167],"type":"Point"}
}