{
  "id": 2333481,
  "type": "Feature",
  "properties": {
    "tgn:hierarchy":[
        "tgn:2333481",
        "tgn:1002132",
        "tgn:1000001",
        "tgn:7012149",
        "tgn:7007919",
        "tgn:7029392"
    ],
    "tgn:id":2333481,
    "tgn:name":"Folly Creek",
    "tgn:placetype":[
        "aat:300008706"
    ]
},
  "bbox": [],
  "geometry": {"coordinates":[-75.65,37.7167],"type":"Point"}
}