<<<<<<< HEAD
{
  "id": 2333481,
  "type": "Feature",
  "properties": {
    "tgn:hierarchy":[
        "tgn:2333481",
        "tgn:1002132",
        "tgn:1000001",
        "tgn:7012149",
        "tgn:7007919",
        "tgn:7029392"
    ],
    "tgn:id":2333481,
    "tgn:name":"Folly Creek",
    "tgn:placetype":[
        "aat:300008706"
    ]
},
  "bbox": [],
  "geometry": {"coordinates":[-75.65,37.7167],"type":"Point"}
}
=======
{"geometry":{"type":"Point","coordinates":[-75.650000,37.716700]},"type":"Feature","properties":{"hierarchy":["tgn:2333481","tgn:1002132","tgn:1000001","tgn:7012149","tgn:7007919","tgn:7029392"],"placetype":["aat:300008706"],"id":2333481,"name:xx":"Folly Creek"}}
>>>>>>> 03f74aca74312dbeaf24d7e61306dd6a786dc3d0
