{
  "id": 2190098,
  "type": "Feature",
  "properties": {
    "tgn:hierarchy":[
        "tgn:2190098",
        "tgn:1000001",
        "tgn:7012149",
        "tgn:2002374",
        "tgn:7007923",
        "tgn:7029392"
    ],
    "tgn:id":2190098,
    "tgn:name":"Bowman Draw",
    "tgn:placetype":[
        "aat:300008761"
    ]
},
  "bbox": [],
  "geometry": {"coordinates":[-106.1833,44.3667],"type":"Point"}
}