<<<<<<< HEAD
{
  "id": 7025524,
  "type": "Feature",
  "properties": {
    "tgn:hierarchy":[
        "tgn:7025524",
        "tgn:7002445",
        "tgn:1000003",
        "tgn:7012077",
        "tgn:7008591",
        "tgn:7029392"
    ],
    "tgn:id":7025524,
    "tgn:name:en":"Dean Prior",
    "tgn:placetype":[
        "aat:300008347"
    ]
},
  "bbox": [],
  "geometry": {"coordinates":[-3.783333,50.45],"type":"Point"}
}
=======
{"geometry":{"type":"Point","coordinates":[-3.783333,50.450000]},"type":"Feature","properties":{"hierarchy":["tgn:7025524","tgn:7002445","tgn:1000003","tgn:7012077","tgn:7008591","tgn:7029392"],"placetype":["aat:300008347"],"name:en":"Dean Prior","id":7025524}}
>>>>>>> 03f74aca74312dbeaf24d7e61306dd6a786dc3d0
