{
  "id": 7016442,
  "type": "Feature",
  "properties": {
    "tgn:hierarchy":[
        "tgn:7016442",
        "tgn:1000003",
        "tgn:7001097",
        "tgn:1000070",
        "tgn:7029392"
    ],
    "tgn:id":7016442,
    "tgn:name:en":"Azincourt",
    "tgn:name:fr":"Azincourt",
    "tgn:placetype":[
        "aat:300008347",
        "aat:300000835",
        "aat:300008375"
    ]
},
  "bbox": [],
  "geometry": {"coordinates":[2.1167,50.4667],"type":"Point"}
}