{
  "id": 7360234,
  "type": "Feature",
  "properties": {
    "tgn:hierarchy":[
        "tgn:7360234",
        "tgn:1000001",
        "tgn:7005597",
        "tgn:7005560",
        "tgn:7029392"
    ],
    "tgn:id":7360234,
    "tgn:name":"Conrado Castillo",
    "tgn:placetype":[
        "aat:300008347"
    ]
},
  "bbox": [],
  "geometry": {"coordinates":[-99.466667,23.95],"type":"Point"}
}