{
  "id": 2147920,
  "type": "Feature",
  "properties": {
    "tgn:hierarchy":[
        "tgn:2147920",
        "tgn:1000001",
        "tgn:7016172",
        "tgn:7012149",
        "tgn:2000132",
        "tgn:7029392"
    ],
    "tgn:id":2147920,
    "tgn:name":"Bark Camp Island",
    "tgn:placetype":[
        "aat:300008791"
    ]
},
  "bbox": [],
  "geometry": {"coordinates":[-90.3167,36.1167],"type":"Point"}
}