{
  "id": 2234558,
  "type": "Feature",
  "properties": {
    "tgn:hierarchy":[
        "tgn:2234558",
        "tgn:1000001",
        "tgn:7012149",
        "tgn:2000442",
        "tgn:7007248",
        "tgn:7029392"
    ],
    "tgn:id":2234558,
    "tgn:name":"Cherokee Lakes West",
    "tgn:placetype":[
        "aat:300006191"
    ]
},
  "bbox": [],
  "geometry": {"coordinates":[-81.9333,31.75],"type":"Point"}
}