{
  "id": 2553738,
  "type": "Feature",
  "properties": {
    "tgn:hierarchy":[
        "tgn:2553738",
        "tgn:1000001",
        "tgn:7012149",
        "tgn:7014589",
        "tgn:7007515",
        "tgn:7029392"
    ],
    "tgn:id":2553738,
    "tgn:name":"Oak Hill",
    "tgn:placetype":[
        "aat:300008798"
    ]
},
  "bbox": [],
  "geometry": {"coordinates":[-67.6667,44.7167],"type":"Point"}
}