{
  "id": 2163308,
  "type": "Feature",
  "properties": {
    "tgn:hierarchy":[
        "tgn:2163308",
        "tgn:1000001",
        "tgn:7012149",
        "tgn:2001309",
        "tgn:7007524",
        "tgn:7029392"
    ],
    "tgn:id":2163308,
    "tgn:name":"Bennie Creek",
    "tgn:placetype":[
        "aat:300008706"
    ]
},
  "bbox": [],
  "geometry": {"coordinates":[-112.8333,48.05],"type":"Point"}
}