{
  "id": 7555917,
  "type": "Feature",
  "properties": {
    "tgn:hierarchy":[
        "tgn:7555917",
        "tgn:1000004",
        "tgn:7000198",
        "tgn:1001886",
        "tgn:7029392"
    ],
    "tgn:id":7555917,
    "tgn:name:en":"Narakal",
    "tgn:placetype":[
        "aat:300008347"
    ]
},
  "bbox": [],
  "geometry": {"coordinates":[76.233333,10.066667],"type":"Point"}
}