{
  "id": 2376943,
  "type": "Feature",
  "properties": {
    "tgn:hierarchy":[
        "tgn:2376943",
        "tgn:1000001",
        "tgn:2001578",
        "tgn:7012149",
        "tgn:7007705",
        "tgn:7029392"
    ],
    "tgn:id":2376943,
    "tgn:name":"Harker Lake",
    "tgn:placetype":[
        "aat:300008680"
    ]
},
  "bbox": [],
  "geometry": {"coordinates":[-99.7167,46.8167],"type":"Point"}
}