<<<<<<< HEAD
{
  "id": 7171203,
  "type": "Feature",
  "properties": {
    "tgn:hierarchy":[
        "tgn:7171203",
        "tgn:1000003",
        "tgn:7003677",
        "tgn:7000084",
        "tgn:7029392"
    ],
    "tgn:id":7171203,
    "tgn:name":"Hengsen-Berg",
    "tgn:placetype":[
        "aat:300008777"
    ]
},
  "bbox": [],
  "geometry": {"coordinates":[7.933333,51.283333],"type":"Point"}
}
=======
{"geometry":{"type":"Point","coordinates":[7.933333,51.283333]},"type":"Feature","properties":{"hierarchy":["tgn:7171203","tgn:1000003","tgn:7003677","tgn:7000084","tgn:7029392"],"placetype":["aat:300008777"],"id":7171203,"name:xx":"Hengsen-Berg"}}
>>>>>>> 03f74aca74312dbeaf24d7e61306dd6a786dc3d0
