{
  "id": 7052505,
  "type": "Feature",
  "properties": {
    "tgn:hierarchy":[
        "tgn:7052505",
        "tgn:7003170",
        "tgn:1000003",
        "tgn:7003125",
        "tgn:1000080",
        "tgn:7029392"
    ],
    "tgn:id":7052505,
    "tgn:name":"Malvano, Fosso",
    "tgn:placetype":[
        "aat:300008699"
    ]
},
  "bbox": [],
  "geometry": {"coordinates":[12.466667,42.933333],"type":"Point"}
}