{
  "id": 7481339,
  "type": "Feature",
  "properties": {
    "tgn:hierarchy":[
        "tgn:7481339",
        "tgn:1000004",
        "tgn:7492971",
        "tgn:1000141",
        "tgn:7029392"
    ],
    "tgn:id":7481339,
    "tgn:name":"Silin Guoxiao",
    "tgn:placetype":[
        "aat:300006495"
    ]
},
  "bbox": [],
  "geometry": {"coordinates":[120.569664,22.544785],"type":"Point"}
}