{
  "id": 7128740,
  "type": "Feature",
  "properties": {
    "tgn:hierarchy":[
        "tgn:7128740",
        "tgn:7003692",
        "tgn:1000003",
        "tgn:7000084",
        "tgn:7029392"
    ],
    "tgn:id":7128740,
    "tgn:name":"Niederweiler",
    "tgn:placetype":[
        "aat:300008347"
    ]
},
  "bbox": [],
  "geometry": {"coordinates":[9.416667,47.866667],"type":"Point"}
}