{
  "id": 7503005,
  "type": "Feature",
  "properties": {
    "tgn:hierarchy":[
        "tgn:7503005",
        "tgn:1000004",
        "tgn:7471332",
        "tgn:1000141",
        "tgn:7029392"
    ],
    "tgn:id":7503005,
    "tgn:name":"Hengwo",
    "tgn:placetype":[
        "aat:300000745"
    ]
},
  "bbox": [],
  "geometry": {"coordinates":[121.085,24.740556],"type":"Point"}
}