{
  "id": 1087971,
  "type": "Feature",
  "properties": {
    "tgn:hierarchy":[
        "tgn:1087971",
        "tgn:7001242",
        "tgn:1000149",
        "tgn:1000954",
        "tgn:7029392"
    ],
    "tgn:id":1087971,
    "tgn:name":"Quinz\u00e1u",
    "tgn:placetype":[
        "aat:300008347"
    ]
},
  "bbox": [],
  "geometry": {"coordinates":[12.7667,-6.8667],"type":"Point"}
}