{
  "id": 1051553,
  "type": "Feature",
  "properties": {
    "tgn:hierarchy":[
        "tgn:1051553",
        "tgn:7013670",
        "tgn:1000004",
        "tgn:7018214",
        "tgn:7002435",
        "tgn:7029392"
    ],
    "tgn:id":1051553,
    "tgn:name":"Sharchino",
    "tgn:placetype":[
        "aat:300008347"
    ]
},
  "bbox": [],
  "geometry": {"coordinates":[81.8167,53.1833],"type":"Point"}
}