{
  "id": 2385749,
  "type": "Feature",
  "properties": {
    "tgn:hierarchy":[
        "tgn:2385749",
        "tgn:7002659",
        "tgn:1000001",
        "tgn:2000004",
        "tgn:7012149",
        "tgn:7029392"
    ],
    "tgn:id":2385749,
    "tgn:name":"Hendrix Mine",
    "tgn:placetype":[
        "aat:300000390"
    ]
},
  "bbox": [],
  "geometry": {"coordinates":[-86.45,34.0167],"type":"Point"}
}