{
  "id": 1090695,
  "type": "Feature",
  "properties": {
    "tgn:hierarchy":[
        "tgn:1090695",
        "tgn:7001242",
        "tgn:7000607",
        "tgn:1000172",
        "tgn:7029392"
    ],
    "tgn:id":1090695,
    "tgn:name":"Qaryat al Qadd\u0101\u1e25\u012byah",
    "tgn:placetype":[
        "aat:300008347"
    ]
},
  "bbox": [],
  "geometry": {"coordinates":[15.2333,31.3667],"type":"Point"}
}