{
  "id": 2180527,
  "type": "Feature",
  "properties": {
    "tgn:hierarchy":[
        "tgn:2180527",
        "tgn:1000001",
        "tgn:7012149",
        "tgn:7007525",
        "tgn:7029392"
    ],
    "tgn:id":2180527,
    "tgn:name":"Bloody Creek",
    "tgn:placetype":[
        "aat:300008706"
    ]
},
  "bbox": [],
  "geometry": {"coordinates":[-99.5833,42.1667],"type":"Point"}
}