{
  "id": 7381707,
  "type": "Feature",
  "properties": {
    "tgn:hierarchy":[
        "tgn:7381707",
        "tgn:1000001",
        "tgn:7005595",
        "tgn:7005560",
        "tgn:7029392"
    ],
    "tgn:id":7381707,
    "tgn:name":"Los Naranjos",
    "tgn:placetype":[
        "aat:300008347"
    ]
},
  "bbox": [],
  "geometry": {"coordinates":[-106.05,23.45],"type":"Point"}
}