{
  "id": 2390795,
  "type": "Feature",
  "properties": {
    "tgn:hierarchy":[
        "tgn:2390795",
        "tgn:1000001",
        "tgn:7012149",
        "tgn:2002062",
        "tgn:7007826",
        "tgn:7029392"
    ],
    "tgn:id":2390795,
    "tgn:name":"Highway Tank",
    "tgn:placetype":[
        "aat:300006191"
    ]
},
  "bbox": [],
  "geometry": {"coordinates":[-103.9833,31.05],"type":"Point"}
}