<<<<<<< HEAD
{
  "id": 7355441,
  "type": "Feature",
  "properties": {
    "tgn:hierarchy":[
        "tgn:7355441",
        "tgn:1000001",
        "tgn:7005591",
        "tgn:7005560",
        "tgn:7029392"
    ],
    "tgn:id":7355441,
    "tgn:name":"Cieneguilla",
    "tgn:placetype":[
        "aat:300008347"
    ]
},
  "bbox": [],
  "geometry": {"coordinates":[-96.95,17.483333],"type":"Point"}
}
=======
{"geometry":{"type":"Point","coordinates":[-96.950000,17.483333]},"type":"Feature","properties":{"hierarchy":["tgn:7355441","tgn:1000001","tgn:7005591","tgn:7005560","tgn:7029392"],"placetype":["aat:300008347"],"id":7355441,"name:xx":"Cieneguilla"}}
>>>>>>> 03f74aca74312dbeaf24d7e61306dd6a786dc3d0
