<<<<<<< HEAD
{
  "id": 2408779,
  "type": "Feature",
  "properties": {
    "tgn:hierarchy":[
        "tgn:2408779",
        "tgn:1000001",
        "tgn:7012149",
        "tgn:7007705",
        "tgn:7029392"
    ],
    "tgn:id":2408779,
    "tgn:name":"Hyde Park Coulee",
    "tgn:placetype":[
        "aat:300008761"
    ]
},
  "bbox": [],
  "geometry": {"coordinates":[-97.8167,48.9667],"type":"Point"}
}
=======
{"geometry":{"type":"Point","coordinates":[-97.816700,48.966700]},"type":"Feature","properties":{"hierarchy":["tgn:2408779","tgn:1000001","tgn:7012149","tgn:7007705","tgn:7029392"],"placetype":["aat:300008761"],"id":2408779,"name:xx":"Hyde Park Coulee"}}
>>>>>>> 03f74aca74312dbeaf24d7e61306dd6a786dc3d0
