{
  "id": 2339094,
  "type": "Feature",
  "properties": {
    "tgn:hierarchy":[
        "tgn:2339094",
        "tgn:1000001",
        "tgn:7012149",
        "tgn:2002100",
        "tgn:7007826",
        "tgn:7029392"
    ],
    "tgn:id":2339094,
    "tgn:name":"Franklin Tank",
    "tgn:placetype":[
        "aat:300006191"
    ]
},
  "bbox": [],
  "geometry": {"coordinates":[-99.75,28.8667],"type":"Point"}
}