{
  "id": 7206934,
  "type": "Feature",
  "properties": {
    "tgn:hierarchy":[
        "tgn:7206934",
        "tgn:1000003",
        "tgn:7003677",
        "tgn:7000084",
        "tgn:7029392"
    ],
    "tgn:id":7206934,
    "tgn:name":"Buchhorst",
    "tgn:placetype":[
        "aat:300008777"
    ]
},
  "bbox": [],
  "geometry": {"coordinates":[8.483333,51.35],"type":"Point"}
}