{
  "id": 2250710,
  "type": "Feature",
  "properties": {
    "tgn:hierarchy":[
        "tgn:2250710",
        "tgn:1000001",
        "tgn:2000862",
        "tgn:7012149",
        "tgn:7007256",
        "tgn:7029392"
    ],
    "tgn:id":2250710,
    "tgn:name":"Colquitt Estates",
    "tgn:placetype":[
        "aat:300008347"
    ]
},
  "bbox": [],
  "geometry": {"coordinates":[-93.8333,32.3667],"type":"Point"}
}