{
  "id": 2050347,
  "type": "Feature",
  "properties": {
    "tgn:hierarchy":[
        "tgn:2050347",
        "tgn:1000001",
        "tgn:7012149",
        "tgn:1003038",
        "tgn:7007517",
        "tgn:7029392"
    ],
    "tgn:id":2050347,
    "tgn:name":"Oakham",
    "tgn:placetype":[
        "aat:300008347"
    ]
},
  "bbox": [],
  "geometry": {"coordinates":[-72.0333,42.35],"type":"Point"}
}