{
  "id": 2657903,
  "type": "Feature",
  "properties": {
    "tgn:hierarchy":[
        "tgn:2657903",
        "tgn:1000001",
        "tgn:7012149",
        "tgn:2000897",
        "tgn:7007256",
        "tgn:7029392"
    ],
    "tgn:id":2657903,
    "tgn:name":"Shell Point",
    "tgn:placetype":[
        "aat:300008850"
    ]
},
  "bbox": [],
  "geometry": {"coordinates":[-89.3667,30.0333],"type":"Point"}
}