{
  "id": 1077933,
  "type": "Feature",
  "properties": {
    "tgn:hierarchy":[
        "tgn:1077933",
        "tgn:1000004",
        "tgn:1001322",
        "tgn:1000116",
        "tgn:7029392"
    ],
    "tgn:id":1077933,
    "tgn:name":"Kutoarjo",
    "tgn:placetype":[
        "aat:300008347"
    ]
},
  "bbox": [],
  "geometry": {"coordinates":[109.9167,-7.75],"type":"Point"}
}