{
  "id": 7066551,
  "type": "Feature",
  "properties": {
    "tgn:hierarchy":[
        "tgn:7066551",
        "tgn:1000003",
        "tgn:7000094",
        "tgn:7000084",
        "tgn:7029392"
    ],
    "tgn:id":7066551,
    "tgn:name":"Ueckerm\u00fcnder Heide",
    "tgn:placetype":[
        "aat:300387346"
    ]
},
  "bbox": [],
  "geometry": {"coordinates":[14.083333,53.716667],"type":"Point"}
}