{
  "id": 2567910,
  "type": "Feature",
  "properties": {
    "tgn:hierarchy":[
        "tgn:2567910",
        "tgn:1000001",
        "tgn:7012149",
        "tgn:2000494",
        "tgn:7007250",
        "tgn:7029392"
    ],
    "tgn:id":2567910,
    "tgn:name":"Paradise Point",
    "tgn:placetype":[
        "aat:300008850"
    ]
},
  "bbox": [],
  "geometry": {"coordinates":[-116.05,44.95],"type":"Point"}
}