{
  "id": 2427463,
  "type": "Feature",
  "properties": {
    "tgn:hierarchy":[
        "tgn:2427463",
        "tgn:1000001",
        "tgn:7012149",
        "tgn:2000491",
        "tgn:7007250",
        "tgn:7029392"
    ],
    "tgn:id":2427463,
    "tgn:name":"Jordan Spring",
    "tgn:placetype":[
        "aat:300008697"
    ]
},
  "bbox": [],
  "geometry": {"coordinates":[-116.05,47.9667],"type":"Point"}
}