{
  "id": 2521192,
  "type": "Feature",
  "properties": {
    "tgn:hierarchy":[
        "tgn:2521192",
        "tgn:1000001",
        "tgn:7012149",
        "tgn:1002779",
        "tgn:7007710",
        "tgn:7029392"
    ],
    "tgn:id":2521192,
    "tgn:name":"Montebello",
    "tgn:placetype":[
        "aat:300008347"
    ]
},
  "bbox": [],
  "geometry": {"coordinates":[-77.0667,40.4167],"type":"Point"}
}