{
  "id": 7476887,
  "type": "Feature",
  "properties": {
    "tgn:hierarchy":[
        "tgn:7476887",
        "tgn:7487020",
        "tgn:1000004",
        "tgn:1000141",
        "tgn:7029392"
    ],
    "tgn:id":7476887,
    "tgn:name":"Ankengzi",
    "tgn:placetype":[
        "aat:300008347"
    ]
},
  "bbox": [],
  "geometry": {"coordinates":[120.870336,24.530362],"type":"Point"}
}