{
  "id": 7325401,
  "type": "Feature",
  "properties": {
    "tgn:hierarchy":[
        "tgn:7325401",
        "tgn:7002759",
        "tgn:7002845",
        "tgn:1000003",
        "tgn:1000095",
        "tgn:7029392"
    ],
    "tgn:id":7325401,
    "tgn:name":"Santa Cruz de Gr\u00edo",
    "tgn:placetype":[
        "aat:300008347"
    ]
},
  "bbox": [],
  "geometry": {"coordinates":[-1.433333,41.366667],"type":"Point"}
}