{
  "id": 7498342,
  "type": "Feature",
  "properties": {
    "tgn:hierarchy":[
        "tgn:7498342",
        "tgn:1000004",
        "tgn:7001009",
        "tgn:1000141",
        "tgn:7029392"
    ],
    "tgn:id":7498342,
    "tgn:name":"Beishi Qiao",
    "tgn:placetype":[
        "aat:300007836"
    ]
},
  "bbox": [],
  "geometry": {"coordinates":[120.5563,24.221414],"type":"Point"}
}