{
  "id": 7511780,
  "type": "Feature",
  "properties": {
    "tgn:hierarchy":[
        "tgn:7511780",
        "tgn:7016670",
        "tgn:1008380",
        "tgn:1000226",
        "tgn:1000006",
        "tgn:7029392"
    ],
    "tgn:id":7511780,
    "tgn:name:en":"Karamea",
    "tgn:placetype":[
        "aat:300008791"
    ]
},
  "bbox": [],
  "geometry": {"coordinates":[176.983333,-39.866667],"type":"Point"}
}