{
  "id": 7459869,
  "type": "Feature",
  "properties": {
    "tgn:hierarchy":[
        "tgn:7459869",
        "tgn:7002444",
        "tgn:7008074",
        "tgn:1000003",
        "tgn:7008591",
        "tgn:7029392"
    ],
    "tgn:id":7459869,
    "tgn:name:en":"Old Water",
    "tgn:placetype":[
        "aat:300008699"
    ]
},
  "bbox": [],
  "geometry": {"coordinates":[-3.75,55.083333],"type":"Point"}
}