{
  "id": 7217764,
  "type": "Feature",
  "properties": {
    "tgn:hierarchy":[
        "tgn:7217764",
        "tgn:7002752",
        "tgn:7001399",
        "tgn:1000003",
        "tgn:1000074",
        "tgn:7029392"
    ],
    "tgn:id":7217764,
    "tgn:name":"Gerak\u00e1rion",
    "tgn:placetype":[
        "aat:300008347"
    ]
},
  "bbox": [],
  "geometry": {"coordinates":[21.845,39.804444],"type":"Point"}
}