<<<<<<< HEAD
{
  "id": 7352227,
  "type": "Feature",
  "properties": {
    "tgn:hierarchy":[
        "tgn:7352227",
        "tgn:7005581",
        "tgn:1000001",
        "tgn:7005560",
        "tgn:7029392"
    ],
    "tgn:id":7352227,
    "tgn:name":"Alto, Cerro",
    "tgn:placetype":[
        "aat:300008777"
    ]
},
  "bbox": [],
  "geometry": {"coordinates":[-104.566667,29.666667],"type":"Point"}
}
=======
{"geometry":{"type":"Point","coordinates":[-104.566667,29.666667]},"type":"Feature","properties":{"hierarchy":["tgn:7352227","tgn:7005581","tgn:1000001","tgn:7005560","tgn:7029392"],"placetype":["aat:300008777"],"id":7352227,"name:xx":"Alto, Cerro"}}
>>>>>>> 03f74aca74312dbeaf24d7e61306dd6a786dc3d0
