{
  "id": 2507086,
  "type": "Feature",
  "properties": {
    "tgn:hierarchy":[
        "tgn:2507086",
        "tgn:1000001",
        "tgn:1002949",
        "tgn:7012149",
        "tgn:7007159",
        "tgn:7029392"
    ],
    "tgn:id":2507086,
    "tgn:name":"Metcalf Brook",
    "tgn:placetype":[
        "aat:300008699"
    ]
},
  "bbox": [],
  "geometry": {"coordinates":[-72.3667,41.8333],"type":"Point"}
}