{
  "id": 2596801,
  "type": "Feature",
  "properties": {
    "tgn:hierarchy":[
        "tgn:2596801",
        "tgn:1000001",
        "tgn:7012149",
        "tgn:2001298",
        "tgn:7007524",
        "tgn:7029392"
    ],
    "tgn:id":2596801,
    "tgn:name":"Powell Lake",
    "tgn:placetype":[
        "aat:300008680"
    ]
},
  "bbox": [],
  "geometry": {"coordinates":[-112.8833,46.35],"type":"Point"}
}