<<<<<<< HEAD
{
  "id": 2150811,
  "type": "Feature",
  "properties": {
    "tgn:hierarchy":[
        "tgn:2150811",
        "tgn:1000001",
        "tgn:7012149",
        "tgn:2000978",
        "tgn:7007520",
        "tgn:7029392"
    ],
    "tgn:id":2150811,
    "tgn:name":"Bass Lake",
    "tgn:placetype":[
        "aat:300008680"
    ]
},
  "bbox": [],
  "geometry": {"coordinates":[-87.8,45.4],"type":"Point"}
}
=======
{"geometry":{"type":"Point","coordinates":[-87.800000,45.400000]},"type":"Feature","properties":{"hierarchy":["tgn:2150811","tgn:1000001","tgn:7012149","tgn:2000978","tgn:7007520","tgn:7029392"],"placetype":["aat:300008680"],"id":2150811,"name:xx":"Bass Lake"}}
>>>>>>> 03f74aca74312dbeaf24d7e61306dd6a786dc3d0
