{
  "id": 7534713,
  "type": "Feature",
  "properties": {
    "tgn:hierarchy":[
        "tgn:7534713",
        "tgn:7001242",
        "tgn:7016833",
        "tgn:1001091",
        "tgn:7029392"
    ],
    "tgn:id":7534713,
    "tgn:name:en":"\u1e28im\u0101rah, Raw\u1e11 al",
    "tgn:placetype":[
        "aat:300379998"
    ]
},
  "bbox": [],
  "geometry": {"coordinates":[31.45,29.933333],"type":"Point"}
}