{
  "id": 2105648,
  "type": "Feature",
  "properties": {
    "tgn:hierarchy":[
        "tgn:2105648",
        "tgn:1000001",
        "tgn:7012149",
        "tgn:1002584",
        "tgn:7007826",
        "tgn:7029392"
    ],
    "tgn:id":2105648,
    "tgn:name":"Lincoln",
    "tgn:placetype":[
        "aat:300008347"
    ]
},
  "bbox": [],
  "geometry": {"coordinates":[-96.95,30.2833],"type":"Point"}
}