{
  "id": 7585638,
  "type": "Feature",
  "properties": {
    "tgn:hierarchy":[
        "tgn:7585638",
        "tgn:1000004",
        "tgn:7000198",
        "tgn:7000799",
        "tgn:7029392"
    ],
    "tgn:id":7585638,
    "tgn:name:en":"Rair Baihk",
    "tgn:placetype":[
        "aat:300008347"
    ]
},
  "bbox": [],
  "geometry": {"coordinates":[74.853257,34.262437],"type":"Point"}
}