{
  "id": 2741098,
  "type": "Feature",
  "properties": {
    "tgn:hierarchy":[
        "tgn:2741098",
        "tgn:1000001",
        "tgn:7006451",
        "tgn:7012149",
        "tgn:2000103",
        "tgn:7029392"
    ],
    "tgn:id":2741098,
    "tgn:name":"Upper Tailholt Spring",
    "tgn:placetype":[
        "aat:300008697"
    ]
},
  "bbox": [],
  "geometry": {"coordinates":[-112.7667,34.7833],"type":"Point"}
}