{
  "id": 7101355,
  "type": "Feature",
  "properties": {
    "tgn:hierarchy":[
        "tgn:7101355",
        "tgn:7003692",
        "tgn:1000003",
        "tgn:7000084",
        "tgn:7029392"
    ],
    "tgn:id":7101355,
    "tgn:name":"Sauerbronnen",
    "tgn:placetype":[
        "aat:300000206"
    ]
},
  "bbox": [],
  "geometry": {"coordinates":[10.033333,49.133333],"type":"Point"}
}