{
  "id": 7345153,
  "type": "Feature",
  "properties": {
    "tgn:hierarchy":[
        "tgn:7345153",
        "tgn:1001439",
        "tgn:1000003",
        "tgn:7002797",
        "tgn:1000095",
        "tgn:7029392"
    ],
    "tgn:id":7345153,
    "tgn:name":"Algas, Punta de",
    "tgn:placetype":[
        "aat:300386846"
    ]
},
  "bbox": [],
  "geometry": {"coordinates":[-0.75,37.783333],"type":"Point"}
}