{
  "id": 2165433,
  "type": "Feature",
  "properties": {
    "tgn:hierarchy":[
        "tgn:2165433",
        "tgn:1000001",
        "tgn:7006451",
        "tgn:7012149",
        "tgn:2000103",
        "tgn:7029392"
    ],
    "tgn:id":2165433,
    "tgn:name":"Bettys Tank",
    "tgn:placetype":[
        "aat:300006191"
    ]
},
  "bbox": [],
  "geometry": {"coordinates":[-112.3333,34.9167],"type":"Point"}
}