{
  "id": 7570164,
  "type": "Feature",
  "properties": {
    "tgn:hierarchy":[
        "tgn:7570164",
        "tgn:1000004",
        "tgn:7000198",
        "tgn:7031786",
        "tgn:7029392"
    ],
    "tgn:id":7570164,
    "tgn:name:en":"Dhaura",
    "tgn:placetype":[
        "aat:300008347"
    ]
},
  "bbox": [],
  "geometry": {"coordinates":[78.733669,29.916531],"type":"Point"}
}