{
  "id": 7494280,
  "type": "Feature",
  "properties": {
    "tgn:hierarchy":[
        "tgn:7494280",
        "tgn:1000004",
        "tgn:7001014",
        "tgn:1000141",
        "tgn:7029392"
    ],
    "tgn:id":7494280,
    "tgn:name":"Yangzi Gaozhong",
    "tgn:placetype":[
        "aat:300006495"
    ]
},
  "bbox": [],
  "geometry": {"coordinates":[120.425097,23.697406],"type":"Point"}
}