{
  "id": 2741410,
  "type": "Feature",
  "properties": {
    "tgn:hierarchy":[
        "tgn:2741410",
        "tgn:1000001",
        "tgn:7012149",
        "tgn:7007254",
        "tgn:7029392"
    ],
    "tgn:id":2741410,
    "tgn:name":"Upton Creek",
    "tgn:placetype":[
        "aat:300008706"
    ]
},
  "bbox": [],
  "geometry": {"coordinates":[-97.4833,39.6833],"type":"Point"}
}