{
  "id": 2593910,
  "type": "Feature",
  "properties": {
    "tgn:hierarchy":[
        "tgn:2593910",
        "tgn:7006450",
        "tgn:1000001",
        "tgn:7012149",
        "tgn:2000086",
        "tgn:7029392"
    ],
    "tgn:id":2593910,
    "tgn:name":"Port Nellie Juan",
    "tgn:placetype":[
        "aat:300132316"
    ]
},
  "bbox": [],
  "geometry": {"coordinates":[-148.2333,60.55],"type":"Point"}
}