{
  "id": 7221724,
  "type": "Feature",
  "properties": {
    "tgn:hierarchy":[
        "tgn:7221724",
        "tgn:7002709",
        "tgn:7002705",
        "tgn:1000003",
        "tgn:1000074",
        "tgn:7029392"
    ],
    "tgn:id":7221724,
    "tgn:name":"M\u00fdloi",
    "tgn:placetype":[
        "aat:300008347"
    ]
},
  "bbox": [],
  "geometry": {"coordinates":[20.3475,39.471944],"type":"Point"}
}