{
  "id": 2228874,
  "type": "Feature",
  "properties": {
    "tgn:hierarchy":[
        "tgn:2228874",
        "tgn:1000001",
        "tgn:7012149",
        "tgn:2001453",
        "tgn:7007566",
        "tgn:7029392"
    ],
    "tgn:id":2228874,
    "tgn:name":"Cedar Hill",
    "tgn:placetype":[
        "aat:300008347"
    ]
},
  "bbox": [],
  "geometry": {"coordinates":[-105.2667,35.2333],"type":"Point"}
}