{
  "id": 7437319,
  "type": "Feature",
  "properties": {
    "tgn:hierarchy":[
        "tgn:7437319",
        "tgn:7005586",
        "tgn:1000001",
        "tgn:7005560",
        "tgn:7029392"
    ],
    "tgn:id":7437319,
    "tgn:name":"Tepatitl\u00e1n",
    "tgn:placetype":[
        "aat:300266554",
        "aat:300008699"
    ]
},
  "bbox": [],
  "geometry": {"coordinates":[-102.95,20.833333],"type":"Point"}
}