{
  "id": 7214007,
  "type": "Feature",
  "properties": {
    "tgn:hierarchy":[
        "tgn:7214007",
        "tgn:7003669",
        "tgn:1000003",
        "tgn:7000084",
        "tgn:7029392"
    ],
    "tgn:id":7214007,
    "tgn:name":"Biber",
    "tgn:placetype":[
        "aat:300008699"
    ]
},
  "bbox": [],
  "geometry": {"coordinates":[10.183333,48.433333],"type":"Point"}
}