{
  "id": 2088531,
  "type": "Feature",
  "properties": {
    "tgn:hierarchy":[
        "tgn:2088531",
        "tgn:1000001",
        "tgn:7012149",
        "tgn:1003041",
        "tgn:7007710",
        "tgn:7029392"
    ],
    "tgn:id":2088531,
    "tgn:name":"Forkston",
    "tgn:placetype":[
        "aat:300008347"
    ]
},
  "bbox": [],
  "geometry": {"coordinates":[-76.1167,41.5167],"type":"Point"}
}