{
  "id": 7591398,
  "type": "Feature",
  "properties": {
    "tgn:hierarchy":[
        "tgn:7591398",
        "tgn:1000004",
        "tgn:7000198",
        "tgn:7031786",
        "tgn:7029392"
    ],
    "tgn:id":7591398,
    "tgn:name:en":"J\u016blon",
    "tgn:placetype":[
        "aat:300008347"
    ]
},
  "bbox": [],
  "geometry": {"coordinates":[77.90281,30.407792],"type":"Point"}
}