{
  "id": 2364922,
  "type": "Feature",
  "properties": {
    "tgn:hierarchy":[
        "tgn:2364922",
        "tgn:1000001",
        "tgn:7012149",
        "tgn:2001881",
        "tgn:7007825",
        "tgn:7029392"
    ],
    "tgn:id":2364922,
    "tgn:name":"Greenhill",
    "tgn:placetype":[
        "aat:300008347"
    ]
},
  "bbox": [],
  "geometry": {"coordinates":[-83.4667,36.0167],"type":"Point"}
}