{
  "id": 2636003,
  "type": "Feature",
  "properties": {
    "tgn:hierarchy":[
        "tgn:2636003",
        "tgn:1000001",
        "tgn:2001801",
        "tgn:7012149",
        "tgn:7007713",
        "tgn:7029392"
    ],
    "tgn:id":2636003,
    "tgn:name":"Saddle Butte",
    "tgn:placetype":[
        "aat:300008798"
    ]
},
  "bbox": [],
  "geometry": {"coordinates":[-103.25,45.2833],"type":"Point"}
}