{
  "id": 2314814,
  "type": "Feature",
  "properties": {
    "tgn:hierarchy":[
        "tgn:2314814",
        "tgn:1000001",
        "tgn:2000568",
        "tgn:7012149",
        "tgn:7007253",
        "tgn:7029392"
    ],
    "tgn:id":2314814,
    "tgn:name":"Elkhorn Creek",
    "tgn:placetype":[
        "aat:300008706"
    ]
},
  "bbox": [],
  "geometry": {"coordinates":[-93.8833,42.1333],"type":"Point"}
}