{
  "id": 7337306,
  "type": "Feature",
  "properties": {
    "tgn:hierarchy":[
        "tgn:7337306",
        "tgn:7002842",
        "tgn:7001158",
        "tgn:1000003",
        "tgn:1000095",
        "tgn:7029392"
    ],
    "tgn:id":7337306,
    "tgn:name":"Ciria",
    "tgn:placetype":[
        "aat:300008347"
    ]
},
  "bbox": [],
  "geometry": {"coordinates":[-1.966667,41.616667],"type":"Point"}
}