{
  "id": 1113318,
  "type": "Feature",
  "properties": {
    "tgn:hierarchy":[
        "tgn:1113318",
        "tgn:1000001",
        "tgn:7012149",
        "tgn:2001950",
        "tgn:7007826",
        "tgn:7029392"
    ],
    "tgn:id":1113318,
    "tgn:name":"Lavaca Bay",
    "tgn:placetype":[
        "aat:300132316"
    ]
},
  "bbox": [],
  "geometry": {"coordinates":[-96.5833,28.65],"type":"Point"}
}