{
  "id": 7296986,
  "type": "Feature",
  "properties": {
    "tgn:hierarchy":[
        "tgn:7296986",
        "tgn:7002825",
        "tgn:7016622",
        "tgn:1000003",
        "tgn:1000095",
        "tgn:7029392"
    ],
    "tgn:id":7296986,
    "tgn:name":"Torre, Puerto de la",
    "tgn:placetype":[
        "aat:300132317"
    ]
},
  "bbox": [],
  "geometry": {"coordinates":[-13.866667,28.35],"type":"Point"}
}