{
  "id": 2389129,
  "type": "Feature",
  "properties": {
    "tgn:hierarchy":[
        "tgn:2389129",
        "tgn:1000001",
        "tgn:7006451",
        "tgn:7012149",
        "tgn:2000097",
        "tgn:7029392"
    ],
    "tgn:id":2389129,
    "tgn:name":"Hidden Valley",
    "tgn:placetype":[
        "aat:300008761"
    ]
},
  "bbox": [],
  "geometry": {"coordinates":[-112.0333,33.3333],"type":"Point"}
}