{
  "id": 7015143,
  "type": "Feature",
  "properties": {
    "tgn:hierarchy":[
        "tgn:7015143",
        "tgn:1000003",
        "tgn:7006670",
        "tgn:7029392"
    ],
    "tgn:id":7015143,
    "tgn:name":"Terbnje, Ob\u010dina",
    "tgn:placetype":[
        "aat:300387064",
        "aat:300387081"
    ]
},
  "bbox": [],
  "geometry": {"coordinates":[15.0333,45.9167],"type":"Point"}
}