{
  "id": 7233447,
  "type": "Feature",
  "properties": {
    "tgn:hierarchy":[
        "tgn:7233447",
        "tgn:7002739",
        "tgn:7017076",
        "tgn:1000003",
        "tgn:1000074",
        "tgn:7029392"
    ],
    "tgn:id":7233447,
    "tgn:name":"Ay\u00eda Sof\u00eda",
    "tgn:placetype":[
        "aat:300008347"
    ]
},
  "bbox": [],
  "geometry": {"coordinates":[22.533333,37.433333],"type":"Point"}
}