{
  "id": 2569932,
  "type": "Feature",
  "properties": {
    "tgn:hierarchy":[
        "tgn:2569932",
        "tgn:1000001",
        "tgn:7012149",
        "tgn:1002790",
        "tgn:7007240",
        "tgn:7029392"
    ],
    "tgn:id":2569932,
    "tgn:name":"Pasadena Lake",
    "tgn:placetype":[
        "aat:300008680"
    ]
},
  "bbox": [],
  "geometry": {"coordinates":[-82.7167,27.7667],"type":"Point"}
}