{
  "id": 1009922,
  "type": "Feature",
  "properties": {
    "tgn:hierarchy":[
        "tgn:1009922",
        "tgn:1008380",
        "tgn:7000507",
        "tgn:1000226",
        "tgn:1000006",
        "tgn:7029392"
    ],
    "tgn:id":1009922,
    "tgn:name:en":"Cavalli Islands",
    "tgn:placetype":[
        "aat:300008791",
        "aat:300386853"
    ]
},
  "bbox": [],
  "geometry": {"coordinates":[173.966667,-34.966667],"type":"Point"}
}