{
  "id": 2204242,
  "type": "Feature",
  "properties": {
    "tgn:hierarchy":[
        "tgn:2204242",
        "tgn:1000001",
        "tgn:7012149",
        "tgn:2000933",
        "tgn:7007515",
        "tgn:7029392"
    ],
    "tgn:id":2204242,
    "tgn:name":"Buff Brook",
    "tgn:placetype":[
        "aat:300008699"
    ]
},
  "bbox": [],
  "geometry": {"coordinates":[-70.75,43.5667],"type":"Point"}
}