{
  "id": 2722424,
  "type": "Feature",
  "properties": {
    "tgn:hierarchy":[
        "tgn:2722424",
        "tgn:1000001",
        "tgn:7012149",
        "tgn:2001420",
        "tgn:7007526",
        "tgn:7029392"
    ],
    "tgn:id":2722424,
    "tgn:name":"Tin Springs Mountain",
    "tgn:placetype":[
        "aat:300008798"
    ]
},
  "bbox": [],
  "geometry": {"coordinates":[-114.0833,39.55],"type":"Point"}
}