<<<<<<< HEAD
{
  "id": 7022456,
  "type": "Feature",
  "properties": {
    "tgn:hierarchy":[
        "tgn:7022456",
        "tgn:1000001",
        "tgn:7012149",
        "tgn:7029392"
    ],
    "tgn:id":7022456,
    "tgn:name":"Burke Summit",
    "tgn:placetype":[
        "aat:300008798"
    ]
},
  "bbox": [],
  "geometry": {"coordinates":[-115.7,47.5167],"type":"Point"}
}
=======
{"geometry":{"type":"Point","coordinates":[-115.700000,47.516700]},"type":"Feature","properties":{"hierarchy":["tgn:7022456","tgn:1000001","tgn:7012149","tgn:7029392"],"placetype":["aat:300008798"],"id":7022456,"name:xx":"Burke Summit"}}
>>>>>>> 03f74aca74312dbeaf24d7e61306dd6a786dc3d0
