{
  "id": 2597837,
  "type": "Feature",
  "properties": {
    "tgn:hierarchy":[
        "tgn:2597837",
        "tgn:1000001",
        "tgn:7012149",
        "tgn:7007250",
        "tgn:7029392"
    ],
    "tgn:id":2597837,
    "tgn:name":"Preacher Creek",
    "tgn:placetype":[
        "aat:300008706"
    ]
},
  "bbox": [],
  "geometry": {"coordinates":[-114.5667,43.1333],"type":"Point"}
}