{
  "id": 7084822,
  "type": "Feature",
  "properties": {
    "tgn:hierarchy":[
        "tgn:7084822",
        "tgn:1000003",
        "tgn:7003676",
        "tgn:7000084",
        "tgn:7029392"
    ],
    "tgn:id":7084822,
    "tgn:name":"Wetzen",
    "tgn:placetype":[
        "aat:300008347"
    ]
},
  "bbox": [],
  "geometry": {"coordinates":[10.25,53.183333],"type":"Point"}
}