{
  "id": 7048726,
  "type": "Feature",
  "properties": {
    "tgn:hierarchy":[
        "tgn:7048726",
        "tgn:1000003",
        "tgn:7003122",
        "tgn:7003157",
        "tgn:1000080",
        "tgn:7029392"
    ],
    "tgn:id":7048726,
    "tgn:name":"Drauto",
    "tgn:placetype":[
        "aat:300008347"
    ]
},
  "bbox": [],
  "geometry": {"coordinates":[15.083333,38.633333],"type":"Point"}
}