{
  "id": 2419544,
  "type": "Feature",
  "properties": {
    "tgn:hierarchy":[
        "tgn:2419544",
        "tgn:1000001",
        "tgn:7012149",
        "tgn:2001077",
        "tgn:7007521",
        "tgn:7029392"
    ],
    "tgn:id":2419544,
    "tgn:name":"Jarrett",
    "tgn:placetype":[
        "aat:300008347"
    ]
},
  "bbox": [],
  "geometry": {"coordinates":[-92.3333,44.2333],"type":"Point"}
}