{
  "id": 2759293,
  "type": "Feature",
  "properties": {
    "tgn:hierarchy":[
        "tgn:2759293",
        "tgn:1000001",
        "tgn:7012149",
        "tgn:1002634",
        "tgn:7007523",
        "tgn:7029392"
    ],
    "tgn:id":2759293,
    "tgn:name":"West Fork Clear Creek",
    "tgn:placetype":[
        "aat:300008706"
    ]
},
  "bbox": [],
  "geometry": {"coordinates":[-94.2833,37.2333],"type":"Point"}
}