{
  "id": 7190370,
  "type": "Feature",
  "properties": {
    "tgn:hierarchy":[
        "tgn:7190370",
        "tgn:1000003",
        "tgn:7003678",
        "tgn:7000084",
        "tgn:7029392"
    ],
    "tgn:id":7190370,
    "tgn:name":"Ellershausen",
    "tgn:placetype":[
        "aat:300008347"
    ]
},
  "bbox": [],
  "geometry": {"coordinates":[8.883333,51.083333],"type":"Point"}
}