<<<<<<< HEAD
{
  "id": 7486871,
  "type": "Feature",
  "properties": {
    "tgn:hierarchy":[
        "tgn:7486871",
        "tgn:1000004",
        "tgn:7001013",
        "tgn:1000141",
        "tgn:7029392"
    ],
    "tgn:id":7486871,
    "tgn:name":"Xiaoyangmei",
    "tgn:placetype":[
        "aat:300008347"
    ]
},
  "bbox": [],
  "geometry": {"coordinates":[121.146389,24.889722],"type":"Point"}
}
=======
{"geometry":{"type":"Point","coordinates":[121.146389,24.889722]},"type":"Feature","properties":{"hierarchy":["tgn:7486871","tgn:1000004","tgn:7001013","tgn:1000141","tgn:7029392"],"placetype":["aat:300008347"],"id":7486871,"name:xx":"Xiaoyangmei"}}
>>>>>>> 03f74aca74312dbeaf24d7e61306dd6a786dc3d0
