<<<<<<< HEAD
{
  "id": 7113668,
  "type": "Feature",
  "properties": {
    "tgn:hierarchy":[
        "tgn:7113668",
        "tgn:1000003",
        "tgn:7003676",
        "tgn:7000084",
        "tgn:7029392"
    ],
    "tgn:id":7113668,
    "tgn:name":"Rodebusch",
    "tgn:placetype":[
        "aat:300008863"
    ]
},
  "bbox": [],
  "geometry": {"coordinates":[9.8,51.516667],"type":"Point"}
}
=======
{"geometry":{"type":"Point","coordinates":[9.800000,51.516667]},"type":"Feature","properties":{"hierarchy":["tgn:7113668","tgn:1000003","tgn:7003676","tgn:7000084","tgn:7029392"],"placetype":["aat:300008863"],"id":7113668,"name:xx":"Rodebusch"}}
>>>>>>> 03f74aca74312dbeaf24d7e61306dd6a786dc3d0
