{
  "id": 2222342,
  "type": "Feature",
  "properties": {
    "tgn:hierarchy":[
        "tgn:2222342",
        "tgn:1000001",
        "tgn:7012149",
        "tgn:1002640",
        "tgn:7007252",
        "tgn:7029392"
    ],
    "tgn:id":2222342,
    "tgn:name":"Carothers Ditch",
    "tgn:placetype":[
        "aat:300006075"
    ]
},
  "bbox": [],
  "geometry": {"coordinates":[-86.25,41.3667],"type":"Point"}
}