{
  "id": 1072768,
  "type": "Feature",
  "properties": {
    "tgn:hierarchy":[
        "tgn:1072768",
        "tgn:1000004",
        "tgn:7002082",
        "tgn:1000111",
        "tgn:7029392"
    ],
    "tgn:id":1072768,
    "tgn:name":"Xiangfuguan",
    "tgn:placetype":[
        "aat:300008347"
    ]
},
  "bbox": [],
  "geometry": {"coordinates":[115.4333,28.4833],"type":"Point"}
}