{
  "id": 2371579,
  "type": "Feature",
  "properties": {
    "tgn:hierarchy":[
        "tgn:2371579",
        "tgn:1000001",
        "tgn:7012149",
        "tgn:2002079",
        "tgn:7007826",
        "tgn:7029392"
    ],
    "tgn:id":2371579,
    "tgn:name":"Halbert Draw",
    "tgn:placetype":[
        "aat:300008761"
    ]
},
  "bbox": [],
  "geometry": {"coordinates":[-100.7333,30.4833],"type":"Point"}
}