{
  "id": 7589641,
  "type": "Feature",
  "properties": {
    "tgn:hierarchy":[
        "tgn:7589641",
        "tgn:1000004",
        "tgn:1001871",
        "tgn:7000198",
        "tgn:7029392"
    ],
    "tgn:id":7589641,
    "tgn:name:en":"Kandraull",
    "tgn:placetype":[
        "aat:300008347"
    ]
},
  "bbox": [],
  "geometry": {"coordinates":[77.189369,29.971738],"type":"Point"}
}