{
  "id": 7513419,
  "type": "Feature",
  "properties": {
    "tgn:hierarchy":[
        "tgn:7513419",
        "tgn:1009227",
        "tgn:1000226",
        "tgn:7520095",
        "tgn:1000006",
        "tgn:7029392"
    ],
    "tgn:id":7513419,
    "tgn:name:en":"Goat Bay",
    "tgn:placetype":[
        "aat:300132316"
    ]
},
  "bbox": [],
  "geometry": {"coordinates":[173.016667,-40.833333],"type":"Point"}
}