{
  "id": 7345969,
  "type": "Feature",
  "properties": {
    "tgn:hierarchy":[
        "tgn:7345969",
        "tgn:7002822",
        "tgn:1001647",
        "tgn:1000003",
        "tgn:1000095",
        "tgn:7029392"
    ],
    "tgn:id":7345969,
    "tgn:name":"Armu\u00f1a de Taju\u00f1a",
    "tgn:placetype":[
        "aat:300008347"
    ]
},
  "bbox": [],
  "geometry": {"coordinates":[-3.033333,40.533333],"type":"Point"}
}