{
  "id": 2247613,
  "type": "Feature",
  "properties": {
    "tgn:hierarchy":[
        "tgn:2247613",
        "tgn:1000001",
        "tgn:7012149",
        "tgn:2001706",
        "tgn:7007708",
        "tgn:7029392"
    ],
    "tgn:id":2247613,
    "tgn:name":"Coffin Creek",
    "tgn:placetype":[
        "aat:300008706"
    ]
},
  "bbox": [],
  "geometry": {"coordinates":[-122.75,42.9167],"type":"Point"}
}