{
  "id": 1053590,
  "type": "Feature",
  "properties": {
    "tgn:hierarchy":[
        "tgn:1053590",
        "tgn:1003361",
        "tgn:1000003",
        "tgn:7006660",
        "tgn:7029392"
    ],
    "tgn:id":1053590,
    "tgn:name":"Dergachi",
    "tgn:placetype":[
        "aat:300008347"
    ]
},
  "bbox": [],
  "geometry": {"coordinates":[36.1833,50.15],"type":"Point"}
}