{
  "id": 7544894,
  "type": "Feature",
  "properties": {
    "tgn:hierarchy":[
        "tgn:7544894",
        "tgn:1009838",
        "tgn:7000204",
        "tgn:1000004",
        "tgn:7000198",
        "tgn:1009218",
        "tgn:7029392"
    ],
    "tgn:id":7544894,
    "tgn:name:en":"Alipur",
    "tgn:placetype":[
        "aat:300008347"
    ]
},
  "bbox": [],
  "geometry": {"coordinates":[92.683333,11.733333],"type":"Point"}
}