{
  "id": 2267230,
  "type": "Feature",
  "properties": {
    "tgn:hierarchy":[
        "tgn:2267230",
        "tgn:1000001",
        "tgn:7012149",
        "tgn:1002794",
        "tgn:7007708",
        "tgn:7029392"
    ],
    "tgn:id":2267230,
    "tgn:name":"Crider Pond",
    "tgn:placetype":[
        "aat:300008680"
    ]
},
  "bbox": [],
  "geometry": {"coordinates":[-123.3167,44.9333],"type":"Point"}
}