{
  "id": 2757981,
  "type": "Feature",
  "properties": {
    "tgn:hierarchy":[
        "tgn:2757981",
        "tgn:1000001",
        "tgn:7012149",
        "tgn:2000963",
        "tgn:7007520",
        "tgn:7029392"
    ],
    "tgn:id":2757981,
    "tgn:name":"West Branch Otter River",
    "tgn:placetype":[
        "aat:300008707"
    ]
},
  "bbox": [],
  "geometry": {"coordinates":[-88.8833,46.8333],"type":"Point"}
}