<<<<<<< HEAD
{
  "id": 2405014,
  "type": "Feature",
  "properties": {
    "tgn:hierarchy":[
        "tgn:2405014",
        "tgn:1000001",
        "tgn:7012149",
        "tgn:2000996",
        "tgn:7007520",
        "tgn:7029392"
    ],
    "tgn:id":2405014,
    "tgn:name":"Hudson Creek",
    "tgn:placetype":[
        "aat:300008706"
    ]
},
  "bbox": [],
  "geometry": {"coordinates":[-86.0167,46.4],"type":"Point"}
}
=======
{"geometry":{"type":"Point","coordinates":[-86.016700,46.400000]},"type":"Feature","properties":{"hierarchy":["tgn:2405014","tgn:1000001","tgn:7012149","tgn:2000996","tgn:7007520","tgn:7029392"],"placetype":["aat:300008706"],"id":2405014,"name:xx":"Hudson Creek"}}
>>>>>>> 03f74aca74312dbeaf24d7e61306dd6a786dc3d0
