{
  "id": 7248414,
  "type": "Feature",
  "properties": {
    "tgn:hierarchy":[
        "tgn:7248414",
        "tgn:7003465",
        "tgn:1000003",
        "tgn:1000063",
        "tgn:4012014",
        "tgn:7029392"
    ],
    "tgn:id":7248414,
    "tgn:name":"Beth",
    "tgn:placetype":[
        "aat:300008347"
    ]
},
  "bbox": [],
  "geometry": {"coordinates":[5.116667,49.95],"type":"Point"}
}