{
  "id": 7342037,
  "type": "Feature",
  "properties": {
    "tgn:hierarchy":[
        "tgn:7342037",
        "tgn:7010420",
        "tgn:1000003",
        "tgn:7002795",
        "tgn:1000095",
        "tgn:7029392"
    ],
    "tgn:id":7342037,
    "tgn:name":"Boalo",
    "tgn:placetype":[
        "aat:300008347"
    ]
},
  "bbox": [],
  "geometry": {"coordinates":[-3.916667,40.716667],"type":"Point"}
}