{
  "id": 7283073,
  "type": "Feature",
  "properties": {
    "tgn:hierarchy":[
        "tgn:7283073",
        "tgn:7002464",
        "tgn:1000049",
        "tgn:1000002",
        "tgn:7029392"
    ],
    "tgn:id":7283073,
    "tgn:name":"Patarisa, Quebrada de",
    "tgn:placetype":[
        "aat:300266554",
        "aat:300008699"
    ]
},
  "bbox": [],
  "geometry": {"coordinates":[-69.45,-19.416667],"type":"Point"}
}