{
  "id": 2090679,
  "type": "Feature",
  "properties": {
    "tgn:hierarchy":[
        "tgn:2090679",
        "tgn:1000001",
        "tgn:7012149",
        "tgn:1002659",
        "tgn:7007710",
        "tgn:7029392"
    ],
    "tgn:id":2090679,
    "tgn:name":"Mercer",
    "tgn:placetype":[
        "aat:300008347"
    ]
},
  "bbox": [],
  "geometry": {"coordinates":[-80.2333,41.2167],"type":"Point"}
}