{
  "id": 7106834,
  "type": "Feature",
  "properties": {
    "tgn:hierarchy":[
        "tgn:7106834",
        "tgn:7003692",
        "tgn:1000003",
        "tgn:7000084",
        "tgn:7029392"
    ],
    "tgn:id":7106834,
    "tgn:name":"Schlechtauberg",
    "tgn:placetype":[
        "aat:300008777"
    ]
},
  "bbox": [],
  "geometry": {"coordinates":[8.366667,48.716667],"type":"Point"}
}