{
  "id": 7496999,
  "type": "Feature",
  "properties": {
    "tgn:hierarchy":[
        "tgn:7496999",
        "tgn:1000004",
        "tgn:7001009",
        "tgn:1000141",
        "tgn:7029392"
    ],
    "tgn:id":7496999,
    "tgn:name":"Shangfeng Guoxiao",
    "tgn:placetype":[
        "aat:300006495"
    ]
},
  "bbox": [],
  "geometry": {"coordinates":[120.666322,24.235971],"type":"Point"}
}