{
  "id": 2097578,
  "type": "Feature",
  "properties": {
    "tgn:hierarchy":[
        "tgn:2097578",
        "tgn:1000001",
        "tgn:2001811",
        "tgn:7012149",
        "tgn:7007713",
        "tgn:7029392"
    ],
    "tgn:id":2097578,
    "tgn:name":"Tea",
    "tgn:placetype":[
        "aat:300008347"
    ]
},
  "bbox": [],
  "geometry": {"coordinates":[-96.8333,43.4333],"type":"Point"}
}