{
  "id": 2088686,
  "type": "Feature",
  "properties": {
    "tgn:hierarchy":[
        "tgn:2088686",
        "tgn:1000001",
        "tgn:7012149",
        "tgn:2001724",
        "tgn:7007710",
        "tgn:7029392"
    ],
    "tgn:id":2088686,
    "tgn:name":"Garrison",
    "tgn:placetype":[
        "aat:300008347"
    ]
},
  "bbox": [],
  "geometry": {"coordinates":[-80.4167,39.7167],"type":"Point"}
}