{
  "id": 2453372,
  "type": "Feature",
  "properties": {
    "tgn:hierarchy":[
        "tgn:2453372",
        "tgn:1000001",
        "tgn:7012149",
        "tgn:2001766",
        "tgn:7007712",
        "tgn:7029392"
    ],
    "tgn:id":2453372,
    "tgn:name":"Little Chicago",
    "tgn:placetype":[
        "aat:300008347"
    ]
},
  "bbox": [],
  "geometry": {"coordinates":[-82.1833,35.05],"type":"Point"}
}