{
  "id": 2471120,
  "type": "Feature",
  "properties": {
    "tgn:hierarchy":[
        "tgn:2471120",
        "tgn:1000001",
        "tgn:7006451",
        "tgn:7012149",
        "tgn:2000098",
        "tgn:7029392"
    ],
    "tgn:id":2471120,
    "tgn:name":"Lost Creek Reservoir",
    "tgn:placetype":[
        "aat:300006191"
    ]
},
  "bbox": [],
  "geometry": {"coordinates":[-113.8833,35.75],"type":"Point"}
}