<<<<<<< HEAD
{
  "id": 2765654,
  "type": "Feature",
  "properties": {
    "tgn:hierarchy":[
        "tgn:2765654",
        "tgn:1000001",
        "tgn:7012149",
        "tgn:7007157",
        "tgn:1002706",
        "tgn:7029392"
    ],
    "tgn:id":2765654,
    "tgn:name":"White Creek",
    "tgn:placetype":[
        "aat:300008706"
    ]
},
  "bbox": [],
  "geometry": {"coordinates":[-122.1833,38.3333],"type":"Point"}
}
=======
{"geometry":{"type":"Point","coordinates":[-122.183300,38.333300]},"type":"Feature","properties":{"hierarchy":["tgn:2765654","tgn:1000001","tgn:7012149","tgn:7007157","tgn:1002706","tgn:7029392"],"placetype":["aat:300008706"],"id":2765654,"name:xx":"White Creek"}}
>>>>>>> 03f74aca74312dbeaf24d7e61306dd6a786dc3d0
