{
  "id": 7400587,
  "type": "Feature",
  "properties": {
    "tgn:hierarchy":[
        "tgn:7400587",
        "tgn:1000001",
        "tgn:7005599",
        "tgn:7005560",
        "tgn:7029392"
    ],
    "tgn:id":7400587,
    "tgn:name":"Puente Caracol",
    "tgn:placetype":[
        "aat:300007836"
    ]
},
  "bbox": [],
  "geometry": {"coordinates":[-96.133333,18.133333],"type":"Point"}
}