{
  "id": 7332979,
  "type": "Feature",
  "properties": {
    "tgn:hierarchy":[
        "tgn:7332979",
        "tgn:7002825",
        "tgn:7016622",
        "tgn:1000003",
        "tgn:1000095",
        "tgn:7029392"
    ],
    "tgn:id":7332979,
    "tgn:name":"Jurado, Punta del",
    "tgn:placetype":[
        "aat:300386846"
    ]
},
  "bbox": [],
  "geometry": {"coordinates":[-13.833333,28.983333],"type":"Point"}
}