{
  "id": 2778262,
  "type": "Feature",
  "properties": {
    "tgn:hierarchy":[
        "tgn:2778262",
        "tgn:7006450",
        "tgn:1000001",
        "tgn:2124053",
        "tgn:7012149",
        "tgn:7029392"
    ],
    "tgn:id":2778262,
    "tgn:name":"Wishbone Hill",
    "tgn:placetype":[
        "aat:300008798"
    ]
},
  "bbox": [],
  "geometry": {"coordinates":[-148.95,61.7333],"type":"Point"}
}