{
  "id": 7546789,
  "type": "Feature",
  "properties": {
    "tgn:hierarchy":[
        "tgn:7546789",
        "tgn:1000004",
        "tgn:7000198",
        "tgn:7001797",
        "tgn:7029392"
    ],
    "tgn:id":7546789,
    "tgn:name:en":"Appa T\u012bvu",
    "tgn:placetype":[
        "aat:300008791"
    ]
},
  "bbox": [],
  "geometry": {"coordinates":[78.83,9.16],"type":"Point"}
}