<<<<<<< HEAD
{
  "id": 7481278,
  "type": "Feature",
  "properties": {
    "tgn:hierarchy":[
        "tgn:7481278",
        "tgn:1000004",
        "tgn:7490934",
        "tgn:1000141",
        "tgn:7029392"
    ],
    "tgn:id":7481278,
    "tgn:name":"Dafeng Qiao",
    "tgn:placetype":[
        "aat:300007836"
    ]
},
  "bbox": [],
  "geometry": {"coordinates":[120.229,23.2662],"type":"Point"}
}
=======
{"geometry":{"type":"Point","coordinates":[120.229000,23.266200]},"type":"Feature","properties":{"hierarchy":["tgn:7481278","tgn:1000004","tgn:7490934","tgn:1000141","tgn:7029392"],"placetype":["aat:300007836"],"id":7481278,"name:xx":"Dafeng Qiao"}}
>>>>>>> 03f74aca74312dbeaf24d7e61306dd6a786dc3d0
