{
  "id": 1128955,
  "type": "Feature",
  "properties": {
    "tgn:hierarchy":[
        "tgn:1128955",
        "tgn:1000004",
        "tgn:7002176",
        "tgn:7000231",
        "tgn:7029392"
    ],
    "tgn:id":1128955,
    "tgn:name":"R\u0101pch",
    "tgn:placetype":[
        "aat:300387091"
    ]
},
  "bbox": [],
  "geometry": {"coordinates":[59.35,25.4667],"type":"Point"}
}