{
  "id": 2259367,
  "type": "Feature",
  "properties": {
    "tgn:hierarchy":[
        "tgn:2259367",
        "tgn:1000001",
        "tgn:7006451",
        "tgn:7012149",
        "tgn:2000103",
        "tgn:7029392"
    ],
    "tgn:id":2259367,
    "tgn:name":"Cottonwood Spring",
    "tgn:placetype":[
        "aat:300008697"
    ]
},
  "bbox": [],
  "geometry": {"coordinates":[-112.3833,34.0167],"type":"Point"}
}