<<<<<<< HEAD
{
  "id": 2259367,
  "type": "Feature",
  "properties": {
    "tgn:hierarchy":[
        "tgn:2259367",
        "tgn:1000001",
        "tgn:7006451",
        "tgn:7012149",
        "tgn:2000103",
        "tgn:7029392"
    ],
    "tgn:id":2259367,
    "tgn:name":"Cottonwood Spring",
    "tgn:placetype":[
        "aat:300008697"
    ]
},
  "bbox": [],
  "geometry": {"coordinates":[-112.3833,34.0167],"type":"Point"}
}
=======
{"geometry":{"type":"Point","coordinates":[-112.383300,34.016700]},"type":"Feature","properties":{"hierarchy":["tgn:2259367","tgn:1000001","tgn:7006451","tgn:7012149","tgn:2000103","tgn:7029392"],"placetype":["aat:300008697"],"id":2259367,"name:xx":"Cottonwood Spring"}}
>>>>>>> 03f74aca74312dbeaf24d7e61306dd6a786dc3d0
