{
  "id": 2657791,
  "type": "Feature",
  "properties": {
    "tgn:hierarchy":[
        "tgn:2657791",
        "tgn:1000001",
        "tgn:7012149",
        "tgn:2001754",
        "tgn:7007712",
        "tgn:7029392"
    ],
    "tgn:id":2657791,
    "tgn:name":"Shell Creek",
    "tgn:placetype":[
        "aat:300008706"
    ]
},
  "bbox": [],
  "geometry": {"coordinates":[-81.8667,34.4667],"type":"Point"}
}