<<<<<<< HEAD
{
  "id": 7053913,
  "type": "Feature",
  "properties": {
    "tgn:hierarchy":[
        "tgn:7053913",
        "tgn:1001641",
        "tgn:1000003",
        "tgn:7003121",
        "tgn:1000080",
        "tgn:7029392"
    ],
    "tgn:id":7053913,
    "tgn:name":"Palmas, Riu",
    "tgn:placetype":[
        "aat:300008699"
    ]
},
  "bbox": [],
  "geometry": {"coordinates":[8.533333,39.05],"type":"Point"}
}
=======
{"geometry":{"type":"Point","coordinates":[8.533333,39.050000]},"type":"Feature","properties":{"hierarchy":["tgn:7053913","tgn:1001641","tgn:1000003","tgn:7003121","tgn:1000080","tgn:7029392"],"placetype":["aat:300008699"],"id":7053913,"name:xx":"Palmas, Riu"}}
>>>>>>> 03f74aca74312dbeaf24d7e61306dd6a786dc3d0
