{
  "id": 2344172,
  "type": "Feature",
  "properties": {
    "tgn:hierarchy":[
        "tgn:2344172",
        "tgn:1000001",
        "tgn:7012149",
        "tgn:2001715",
        "tgn:7007708",
        "tgn:7029392"
    ],
    "tgn:id":2344172,
    "tgn:name":"Game Spring",
    "tgn:placetype":[
        "aat:300008697"
    ]
},
  "bbox": [],
  "geometry": {"coordinates":[-119.75,42.0167],"type":"Point"}
}