{
  "id": 7007784,
  "type": "Feature",
  "properties": {
    "tgn:hierarchy":[
        "tgn:7007784",
        "tgn:7002758",
        "tgn:7002823",
        "tgn:1000003",
        "tgn:1000095",
        "tgn:7029392"
    ],
    "tgn:id":7007784,
    "tgn:name":"Huelva",
    "tgn:placetype":[
        "aat:300235115",
        "aat:300008347",
        "aat:300008389",
        "aat:300387223",
        "aat:300120599"
    ]
},
  "bbox": [],
  "geometry": {"coordinates":[-6.950833,37.258333],"type":"Point"}
}