{
  "id": 2634862,
  "type": "Feature",
  "properties": {
    "tgn:hierarchy":[
        "tgn:2634862",
        "tgn:1000001",
        "tgn:7012149",
        "tgn:2001716",
        "tgn:7007708",
        "tgn:7029392"
    ],
    "tgn:id":2634862,
    "tgn:name":"Ryan Creek",
    "tgn:placetype":[
        "aat:300008706"
    ]
},
  "bbox": [],
  "geometry": {"coordinates":[-123.8167,43.95],"type":"Point"}
}