{
  "id": 2649467,
  "type": "Feature",
  "properties": {
    "tgn:hierarchy":[
        "tgn:2649467",
        "tgn:1000001",
        "tgn:7012149",
        "tgn:1002511",
        "tgn:7007919",
        "tgn:7029392"
    ],
    "tgn:id":2649467,
    "tgn:name":"Scotts Pond",
    "tgn:placetype":[
        "aat:300006191"
    ]
},
  "bbox": [],
  "geometry": {"coordinates":[-76.75,37.3167],"type":"Point"}
}