{
  "id": 7555527,
  "type": "Feature",
  "properties": {
    "tgn:hierarchy":[
        "tgn:7555527",
        "tgn:1000004",
        "tgn:1001842",
        "tgn:7000198",
        "tgn:7029392"
    ],
    "tgn:id":7555527,
    "tgn:name:en":"Mand\u0101r Hill",
    "tgn:placetype":[
        "aat:300008347"
    ]
},
  "bbox": [],
  "geometry": {"coordinates":[87.024017,24.806248],"type":"Point"}
}