{
  "id": 1069057,
  "type": "Feature",
  "properties": {
    "tgn:hierarchy":[
        "tgn:1069057",
        "tgn:1000004",
        "tgn:7002081",
        "tgn:1000111",
        "tgn:7029392"
    ],
    "tgn:id":1069057,
    "tgn:name":"Huolongzhen",
    "tgn:placetype":[
        "aat:300008347"
    ]
},
  "bbox": [],
  "geometry": {"coordinates":[121.2833,32.05],"type":"Point"}
}