{
  "id": 7569128,
  "type": "Feature",
  "properties": {
    "tgn:hierarchy":[
        "tgn:7569128",
        "tgn:1000004",
        "tgn:7000198",
        "tgn:7016788",
        "tgn:7029392"
    ],
    "tgn:id":7569128,
    "tgn:name:en":"Duleri",
    "tgn:placetype":[
        "aat:300008347"
    ]
},
  "bbox": [],
  "geometry": {"coordinates":[74.979573,28.779113],"type":"Point"}
}