{
  "id": 2664642,
  "type": "Feature",
  "properties": {
    "tgn:hierarchy":[
        "tgn:2664642",
        "tgn:1000001",
        "tgn:7012149",
        "tgn:2000491",
        "tgn:7007250",
        "tgn:7029392"
    ],
    "tgn:id":2664642,
    "tgn:name":"Simmons Draw",
    "tgn:placetype":[
        "aat:300008761"
    ]
},
  "bbox": [],
  "geometry": {"coordinates":[-116.1667,47.6667],"type":"Point"}
}