{
  "id": 2708219,
  "type": "Feature",
  "properties": {
    "tgn:hierarchy":[
        "tgn:2708219",
        "tgn:1000001",
        "tgn:7012149",
        "tgn:2002124",
        "tgn:7007827",
        "tgn:7029392"
    ],
    "tgn:id":2708219,
    "tgn:name":"Switchback Spring",
    "tgn:placetype":[
        "aat:300008697"
    ]
},
  "bbox": [],
  "geometry": {"coordinates":[-109.3333,40.5833],"type":"Point"}
}