<<<<<<< HEAD
{
  "id": 7373112,
  "type": "Feature",
  "properties": {
    "tgn:hierarchy":[
        "tgn:7373112",
        "tgn:1000001",
        "tgn:7005589",
        "tgn:7005560",
        "tgn:7029392"
    ],
    "tgn:id":7373112,
    "tgn:name":"La Lagunita",
    "tgn:placetype":[
        "aat:300008347"
    ]
},
  "bbox": [],
  "geometry": {"coordinates":[-100.15,23.716667],"type":"Point"}
}
=======
{"geometry":{"type":"Point","coordinates":[-100.150000,23.716667]},"type":"Feature","properties":{"hierarchy":["tgn:7373112","tgn:1000001","tgn:7005589","tgn:7005560","tgn:7029392"],"placetype":["aat:300008347"],"id":7373112,"name:xx":"La Lagunita"}}
>>>>>>> 03f74aca74312dbeaf24d7e61306dd6a786dc3d0
