<<<<<<< HEAD
{
  "id": 2255959,
  "type": "Feature",
  "properties": {
    "tgn:hierarchy":[
        "tgn:2255959",
        "tgn:1000001",
        "tgn:2001417",
        "tgn:7012149",
        "tgn:7007526",
        "tgn:7029392"
    ],
    "tgn:id":2255959,
    "tgn:name":"Copper Head Mine",
    "tgn:placetype":[
        "aat:300000390"
    ]
},
  "bbox": [],
  "geometry": {"coordinates":[-118.05,38.5333],"type":"Point"}
}
=======
{"geometry":{"type":"Point","coordinates":[-118.050000,38.533300]},"type":"Feature","properties":{"hierarchy":["tgn:2255959","tgn:1000001","tgn:2001417","tgn:7012149","tgn:7007526","tgn:7029392"],"placetype":["aat:300000390"],"id":2255959,"name:xx":"Copper Head Mine"}}
>>>>>>> 03f74aca74312dbeaf24d7e61306dd6a786dc3d0
