{
  "id": 2235615,
  "type": "Feature",
  "properties": {
    "tgn:hierarchy":[
        "tgn:2235615",
        "tgn:1000001",
        "tgn:7013942",
        "tgn:7012149",
        "tgn:7007517",
        "tgn:7029392"
    ],
    "tgn:id":2235615,
    "tgn:name":"Chestnut Hill",
    "tgn:placetype":[
        "aat:300008798"
    ]
},
  "bbox": [],
  "geometry": {"coordinates":[-72.4833,42.5167],"type":"Point"}
}