{
  "id": 2080137,
  "type": "Feature",
  "properties": {
    "tgn:hierarchy":[
        "tgn:2080137",
        "tgn:1000001",
        "tgn:7012149",
        "tgn:2001617",
        "tgn:7007706",
        "tgn:7029392"
    ],
    "tgn:id":2080137,
    "tgn:name":"Jerusalem",
    "tgn:placetype":[
        "aat:300008347"
    ]
},
  "bbox": [],
  "geometry": {"coordinates":[-81.0833,39.85],"type":"Point"}
}