{
  "id": 2042173,
  "type": "Feature",
  "properties": {
    "tgn:hierarchy":[
        "tgn:2042173",
        "tgn:1000001",
        "tgn:2000860",
        "tgn:7012149",
        "tgn:7007256",
        "tgn:7029392"
    ],
    "tgn:id":2042173,
    "tgn:name":"Arcadia",
    "tgn:placetype":[
        "aat:300008347"
    ]
},
  "bbox": [],
  "geometry": {"coordinates":[-92.9167,32.5333],"type":"Point"}
}