{
  "id": 7245021,
  "type": "Feature",
  "properties": {
    "tgn:hierarchy":[
        "tgn:7245021",
        "tgn:7003456",
        "tgn:1000003",
        "tgn:1000063",
        "tgn:7018236",
        "tgn:7029392"
    ],
    "tgn:id":7245021,
    "tgn:name":"Baddebroek",
    "tgn:placetype":[
        "aat:300008347"
    ]
},
  "bbox": [],
  "geometry": {"coordinates":[4.416667,51.116667],"type":"Point"}
}