<<<<<<< HEAD
{
  "id": 7176159,
  "type": "Feature",
  "properties": {
    "tgn:hierarchy":[
        "tgn:7176159",
        "tgn:1000003",
        "tgn:7003676",
        "tgn:7000084",
        "tgn:7029392"
    ],
    "tgn:id":7176159,
    "tgn:name":"Gro\u00df Ellenberg",
    "tgn:placetype":[
        "aat:300008347"
    ]
},
  "bbox": [],
  "geometry": {"coordinates":[10.75,52.933333],"type":"Point"}
}
=======
{"geometry":{"type":"Point","coordinates":[10.750000,52.933333]},"type":"Feature","properties":{"hierarchy":["tgn:7176159","tgn:1000003","tgn:7003676","tgn:7000084","tgn:7029392"],"placetype":["aat:300008347"],"id":7176159,"name:xx":"Gro\u00df Ellenberg"}}
>>>>>>> 03f74aca74312dbeaf24d7e61306dd6a786dc3d0
