{
  "id": 2585952,
  "type": "Feature",
  "properties": {
    "tgn:hierarchy":[
        "tgn:2585952",
        "tgn:1000001",
        "tgn:7012149",
        "tgn:2001871",
        "tgn:7007825",
        "tgn:7029392"
    ],
    "tgn:id":2585952,
    "tgn:name":"Pipkin Lake",
    "tgn:placetype":[
        "aat:300008680"
    ]
},
  "bbox": [],
  "geometry": {"coordinates":[-89.0667,35.4167],"type":"Point"}
}