{
  "id": 7295465,
  "type": "Feature",
  "properties": {
    "tgn:hierarchy":[
        "tgn:7295465",
        "tgn:7007088",
        "tgn:1000003",
        "tgn:7009604",
        "tgn:1000095",
        "tgn:7029392"
    ],
    "tgn:id":7295465,
    "tgn:name":"Villaverde",
    "tgn:placetype":[
        "aat:300008347"
    ]
},
  "bbox": [],
  "geometry": {"coordinates":[-2.567021,42.624372],"type":"Point"}
}