{
  "id": 5003403,
  "type": "Feature",
  "properties": {
    "tgn:hierarchy":[
        "tgn:5003403",
        "tgn:7002810",
        "tgn:7001158",
        "tgn:1000003",
        "tgn:1000095",
        "tgn:7029392"
    ],
    "tgn:id":5003403,
    "tgn:name":"Tord\u00f3mar",
    "tgn:placetype":[
        "aat:300008347"
    ]
},
  "bbox": [],
  "geometry": {"coordinates":[-3.866667,42.05],"type":"Point"}
}