{
  "id": 2411055,
  "type": "Feature",
  "properties": {
    "tgn:hierarchy":[
        "tgn:2411055",
        "tgn:1000001",
        "tgn:1002305",
        "tgn:7012149",
        "tgn:7007920",
        "tgn:7029392"
    ],
    "tgn:id":2411055,
    "tgn:name":"Indian Creek",
    "tgn:placetype":[
        "aat:300008706"
    ]
},
  "bbox": [],
  "geometry": {"coordinates":[-122.7167,46.05],"type":"Point"}
}