<<<<<<< HEAD
{
  "id": 7112121,
  "type": "Feature",
  "properties": {
    "tgn:hierarchy":[
        "tgn:7112121",
        "tgn:1000003",
        "tgn:7003688",
        "tgn:7000084",
        "tgn:7029392"
    ],
    "tgn:id":7112121,
    "tgn:name":"Rhinplatte",
    "tgn:placetype":[
        "aat:300386970"
    ]
},
  "bbox": [],
  "geometry": {"coordinates":[9.4,53.783333],"type":"Point"}
}
=======
{"geometry":{"type":"Point","coordinates":[9.400000,53.783333]},"type":"Feature","properties":{"hierarchy":["tgn:7112121","tgn:1000003","tgn:7003688","tgn:7000084","tgn:7029392"],"placetype":["aat:300386970"],"id":7112121,"name:xx":"Rhinplatte"}}
>>>>>>> 03f74aca74312dbeaf24d7e61306dd6a786dc3d0
