{
  "id": 2105719,
  "type": "Feature",
  "properties": {
    "tgn:hierarchy":[
        "tgn:2105719",
        "tgn:1000001",
        "tgn:7012149",
        "tgn:1002948",
        "tgn:7007826",
        "tgn:7029392"
    ],
    "tgn:id":2105719,
    "tgn:name":"Lone Star",
    "tgn:placetype":[
        "aat:300008347",
        "aat:300387210"
    ]
},
  "bbox": [],
  "geometry": {"coordinates":[-94.8167,33.2333],"type":"Point"}
}