<<<<<<< HEAD
{
  "id": 7246927,
  "type": "Feature",
  "properties": {
    "tgn:hierarchy":[
        "tgn:7246927",
        "tgn:7003465",
        "tgn:1000003",
        "tgn:1000063",
        "tgn:4012014",
        "tgn:7029392"
    ],
    "tgn:id":7246927,
    "tgn:name":"Cedrogne, Bois de",
    "tgn:placetype":[
        "aat:300008863"
    ]
},
  "bbox": [],
  "geometry": {"coordinates":[5.783333,50.2],"type":"Point"}
}
=======
{"geometry":{"type":"Point","coordinates":[5.783333,50.200000]},"type":"Feature","properties":{"hierarchy":["tgn:7246927","tgn:7003465","tgn:1000003","tgn:1000063","tgn:4012014","tgn:7029392"],"placetype":["aat:300008863"],"id":7246927,"name:xx":"Cedrogne, Bois de"}}
>>>>>>> 03f74aca74312dbeaf24d7e61306dd6a786dc3d0
