{
  "id": 2607257,
  "type": "Feature",
  "properties": {
    "tgn:hierarchy":[
        "tgn:2607257",
        "tgn:1000001",
        "tgn:7012149",
        "tgn:2000972",
        "tgn:7007520",
        "tgn:7029392"
    ],
    "tgn:id":2607257,
    "tgn:name":"Randolph Lake",
    "tgn:placetype":[
        "aat:300008680"
    ]
},
  "bbox": [],
  "geometry": {"coordinates":[-85.8167,46.6667],"type":"Point"}
}