{
  "id": 1077095,
  "type": "Feature",
  "properties": {
    "tgn:hierarchy":[
        "tgn:1077095",
        "tgn:1000004",
        "tgn:7000198",
        "tgn:7016694",
        "tgn:7029392"
    ],
    "tgn:id":1077095,
    "tgn:name:en":"T\u0101lb\u0101ndh",
    "tgn:placetype":[
        "aat:300008347"
    ]
},
  "bbox": [],
  "geometry": {"coordinates":[86.343414,22.030467],"type":"Point"}
}