{
  "id": 7270824,
  "type": "Feature",
  "properties": {
    "tgn:hierarchy":[
        "tgn:7270824",
        "tgn:7003619",
        "tgn:1000003",
        "tgn:7016845",
        "tgn:7029392"
    ],
    "tgn:id":7270824,
    "tgn:name:nl":"Kasteel Slangenburg",
    "tgn:placetype":[
        "aat:300006891"
    ]
},
  "bbox": [],
  "geometry": {"coordinates":[6.366667,51.966667],"type":"Point"}
}