{
  "id": 2472723,
  "type": "Feature",
  "properties": {
    "tgn:hierarchy":[
        "tgn:2472723",
        "tgn:1000001",
        "tgn:1002225",
        "tgn:7012149",
        "tgn:7007710",
        "tgn:7029392"
    ],
    "tgn:id":2472723,
    "tgn:name":"Lovell Park",
    "tgn:placetype":[
        "aat:300008347"
    ]
},
  "bbox": [],
  "geometry": {"coordinates":[-78.6667,40.4667],"type":"Point"}
}