<<<<<<< HEAD
{
  "id": 2762756,
  "type": "Feature",
  "properties": {
    "tgn:hierarchy":[
        "tgn:2762756",
        "tgn:1000001",
        "tgn:1002902",
        "tgn:7012149",
        "tgn:7007516",
        "tgn:7029392"
    ],
    "tgn:id":2762756,
    "tgn:name":"Western Islands",
    "tgn:placetype":[
        "aat:300386853"
    ]
},
  "bbox": [],
  "geometry": {"coordinates":[-76.0167,38.0667],"type":"Point"}
}
=======
{"geometry":{"type":"Point","coordinates":[-76.016700,38.066700]},"type":"Feature","properties":{"hierarchy":["tgn:2762756","tgn:1000001","tgn:1002902","tgn:7012149","tgn:7007516","tgn:7029392"],"placetype":["aat:300386853"],"id":2762756,"name:xx":"Western Islands"}}
>>>>>>> 03f74aca74312dbeaf24d7e61306dd6a786dc3d0
