{
  "id": 2762756,
  "type": "Feature",
  "properties": {
    "tgn:hierarchy":[
        "tgn:2762756",
        "tgn:1000001",
        "tgn:1002902",
        "tgn:7012149",
        "tgn:7007516",
        "tgn:7029392"
    ],
    "tgn:id":2762756,
    "tgn:name":"Western Islands",
    "tgn:placetype":[
        "aat:300386853"
    ]
},
  "bbox": [],
  "geometry": {"coordinates":[-76.0167,38.0667],"type":"Point"}
}