{
  "id": 1018704,
  "type": "Feature",
  "properties": {
    "tgn:hierarchy":[
        "tgn:1018704",
        "tgn:7593359",
        "tgn:1000001",
        "tgn:7005562",
        "tgn:7029392"
    ],
    "tgn:id":1018704,
    "tgn:name":"Punta Gorda",
    "tgn:placetype":[
        "aat:300008347"
    ]
},
  "bbox": [],
  "geometry": {"coordinates":[-83.7833,11.5167],"type":"Point"}
}