{
  "id": 2516805,
  "type": "Feature",
  "properties": {
    "tgn:hierarchy":[
        "tgn:2516805",
        "tgn:1000001",
        "tgn:2001414",
        "tgn:7012149",
        "tgn:7007526",
        "tgn:7029392"
    ],
    "tgn:id":2516805,
    "tgn:name":"Minerva Peak",
    "tgn:placetype":[
        "aat:300008798"
    ]
},
  "bbox": [],
  "geometry": {"coordinates":[-117.5667,41.9833],"type":"Point"}
}