<<<<<<< HEAD
{
  "id": 7242593,
  "type": "Feature",
  "properties": {
    "tgn:hierarchy":[
        "tgn:7242593",
        "tgn:7007877",
        "tgn:1000003",
        "tgn:1000063",
        "tgn:4012014",
        "tgn:7029392"
    ],
    "tgn:id":7242593,
    "tgn:name":"Le Sacrement",
    "tgn:placetype":[
        "aat:300008347"
    ]
},
  "bbox": [],
  "geometry": {"coordinates":[4.3,50.666667],"type":"Point"}
}
=======
{"geometry":{"type":"Point","coordinates":[4.300000,50.666667]},"type":"Feature","properties":{"hierarchy":["tgn:7242593","tgn:7007877","tgn:1000003","tgn:1000063","tgn:4012014","tgn:7029392"],"placetype":["aat:300008347"],"id":7242593,"name:xx":"Le Sacrement"}}
>>>>>>> 03f74aca74312dbeaf24d7e61306dd6a786dc3d0
