{
  "id": 2312556,
  "type": "Feature",
  "properties": {
    "tgn:hierarchy":[
        "tgn:2312556",
        "tgn:1000001",
        "tgn:2000776",
        "tgn:7012149",
        "tgn:7007255",
        "tgn:7029392"
    ],
    "tgn:id":2312556,
    "tgn:name":"Eison Branch",
    "tgn:placetype":[
        "aat:300008699"
    ]
},
  "bbox": [],
  "geometry": {"coordinates":[-87.75,37.0667],"type":"Point"}
}