{
  "id": 2605193,
  "type": "Feature",
  "properties": {
    "tgn:hierarchy":[
        "tgn:2605193",
        "tgn:1000001",
        "tgn:7012149",
        "tgn:2001758",
        "tgn:7007712",
        "tgn:7029392"
    ],
    "tgn:id":2605193,
    "tgn:name":"Raft Swamp",
    "tgn:placetype":[
        "aat:300008905"
    ]
},
  "bbox": [],
  "geometry": {"coordinates":[-79.15,34.25],"type":"Point"}
}