{
  "id": 1014758,
  "type": "Feature",
  "properties": {
    "tgn:hierarchy":[
        "tgn:1014758",
        "tgn:7005685",
        "tgn:1000001",
        "tgn:7013154",
        "tgn:7029392"
    ],
    "tgn:id":1014758,
    "tgn:name":"Everett",
    "tgn:placetype":[
        "aat:300008347"
    ]
},
  "bbox": [],
  "geometry": {"coordinates":[-79.95,44.1833],"type":"Point"}
}