<<<<<<< HEAD
{
  "id": 2256110,
  "type": "Feature",
  "properties": {
    "tgn:hierarchy":[
        "tgn:2256110",
        "tgn:1000001",
        "tgn:7012149",
        "tgn:2001440",
        "tgn:7007566",
        "tgn:7029392"
    ],
    "tgn:id":2256110,
    "tgn:name":"Copper Nugget Number 3 and 4",
    "tgn:placetype":[
        "aat:300000390"
    ]
},
  "bbox": [],
  "geometry": {"coordinates":[-108.75,32.3167],"type":"Point"}
}
=======
{"geometry":{"type":"Point","coordinates":[-108.750000,32.316700]},"type":"Feature","properties":{"hierarchy":["tgn:2256110","tgn:1000001","tgn:7012149","tgn:2001440","tgn:7007566","tgn:7029392"],"placetype":["aat:300000390"],"id":2256110,"name:xx":"Copper Nugget Number 3 and 4"}}
>>>>>>> 03f74aca74312dbeaf24d7e61306dd6a786dc3d0
