{
  "id": 7371448,
  "type": "Feature",
  "properties": {
    "tgn:hierarchy":[
        "tgn:7371448",
        "tgn:1000001",
        "tgn:1001960",
        "tgn:7005560",
        "tgn:7029392"
    ],
    "tgn:id":7371448,
    "tgn:name":"Rancho La Cueva de Elias",
    "tgn:placetype":[
        "aat:300000241"
    ]
},
  "bbox": [],
  "geometry": {"coordinates":[-109.45,30.666667],"type":"Point"}
}