{
  "id": 2172291,
  "type": "Feature",
  "properties": {
    "tgn:hierarchy":[
        "tgn:2172291",
        "tgn:1000001",
        "tgn:7012149",
        "tgn:7007158",
        "tgn:2000248",
        "tgn:7029392"
    ],
    "tgn:id":2172291,
    "tgn:name":"Bilk Basin",
    "tgn:placetype":[
        "aat:300386845"
    ]
},
  "bbox": [],
  "geometry": {"coordinates":[-107.95,37.8333],"type":"Point"}
}