{
  "id": 7185022,
  "type": "Feature",
  "properties": {
    "tgn:hierarchy":[
        "tgn:7185022",
        "tgn:1000003",
        "tgn:7003677",
        "tgn:7000084",
        "tgn:7029392"
    ],
    "tgn:id":7185022,
    "tgn:name":"Haltepunkt Gevelsberg-Nirgena",
    "tgn:placetype":[
        "aat:300007783"
    ]
},
  "bbox": [],
  "geometry": {"coordinates":[7.330278,51.296111],"type":"Point"}
}