{
  "id": 2618817,
  "type": "Feature",
  "properties": {
    "tgn:hierarchy":[
        "tgn:2618817",
        "tgn:1000001",
        "tgn:7012149",
        "tgn:2000797",
        "tgn:7007255",
        "tgn:7029392"
    ],
    "tgn:id":2618817,
    "tgn:name":"Right Fork Turtle Creek",
    "tgn:placetype":[
        "aat:300008706"
    ]
},
  "bbox": [],
  "geometry": {"coordinates":[-83.2167,36.8167],"type":"Point"}
}