<<<<<<< HEAD
{
  "id": 2151632,
  "type": "Feature",
  "properties": {
    "tgn:hierarchy":[
        "tgn:2151632",
        "tgn:1000001",
        "tgn:7012149",
        "tgn:7007157",
        "tgn:2000188",
        "tgn:7029392"
    ],
    "tgn:id":2151632,
    "tgn:name":"Battle Creek",
    "tgn:placetype":[
        "aat:300008706"
    ]
},
  "bbox": [],
  "geometry": {"coordinates":[-122.1,41.1333],"type":"Point"}
}
=======
{"geometry":{"type":"Point","coordinates":[-122.100000,41.133300]},"type":"Feature","properties":{"hierarchy":["tgn:2151632","tgn:1000001","tgn:7012149","tgn:7007157","tgn:2000188","tgn:7029392"],"placetype":["aat:300008706"],"id":2151632,"name:xx":"Battle Creek"}}
>>>>>>> 03f74aca74312dbeaf24d7e61306dd6a786dc3d0
