{
  "id": 7443765,
  "type": "Feature",
  "properties": {
    "tgn:hierarchy":[
        "tgn:7443765",
        "tgn:7002445",
        "tgn:1000003",
        "tgn:7008145",
        "tgn:7008591",
        "tgn:7029392"
    ],
    "tgn:id":7443765,
    "tgn:name:en":"Tewin",
    "tgn:placetype":[
        "aat:300008347"
    ]
},
  "bbox": [],
  "geometry": {"coordinates":[-0.15,51.816667],"type":"Point"}
}