{
  "id": 7587545,
  "type": "Feature",
  "properties": {
    "tgn:hierarchy":[
        "tgn:7587545",
        "tgn:1000004",
        "tgn:7000198",
        "tgn:7000799",
        "tgn:7029392"
    ],
    "tgn:id":7587545,
    "tgn:name:en":"Gund-i-Hasibat",
    "tgn:placetype":[
        "aat:300008347"
    ]
},
  "bbox": [],
  "geometry": {"coordinates":[74.696482,34.112346],"type":"Point"}
}