{
  "id": 1014221,
  "type": "Feature",
  "properties": {
    "tgn:hierarchy":[
        "tgn:1014221",
        "tgn:7005685",
        "tgn:7005807",
        "tgn:1000001",
        "tgn:7005801",
        "tgn:7029392"
    ],
    "tgn:id":1014221,
    "tgn:name":"Hants Harbour",
    "tgn:placetype":[
        "aat:300008347"
    ]
},
  "bbox": [],
  "geometry": {"coordinates":[-53.2667,48.0167],"type":"Point"}
}