{
  "id": 7578124,
  "type": "Feature",
  "properties": {
    "tgn:hierarchy":[
        "tgn:7578124",
        "tgn:1000004",
        "tgn:7000198",
        "tgn:1001895",
        "tgn:7029392"
    ],
    "tgn:id":7578124,
    "tgn:name:en":"Trombay",
    "tgn:placetype":[
        "aat:300008347"
    ]
},
  "bbox": [],
  "geometry": {"coordinates":[72.933333,19.033333],"type":"Point"}
}