{
  "id": 7501631,
  "type": "Feature",
  "properties": {
    "tgn:hierarchy":[
        "tgn:7501631",
        "tgn:7488858",
        "tgn:1000004",
        "tgn:1000141",
        "tgn:7029392"
    ],
    "tgn:id":7501631,
    "tgn:name":"Jiudian",
    "tgn:placetype":[
        "aat:300008347"
    ]
},
  "bbox": [],
  "geometry": {"coordinates":[120.824935,24.01789],"type":"Point"}
}