{
  "id": 7496340,
  "type": "Feature",
  "properties": {
    "tgn:hierarchy":[
        "tgn:7496340",
        "tgn:1000004",
        "tgn:7001014",
        "tgn:1000141",
        "tgn:7029392"
    ],
    "tgn:id":7496340,
    "tgn:name":"Yun Qiao",
    "tgn:placetype":[
        "aat:300007836"
    ]
},
  "bbox": [],
  "geometry": {"coordinates":[120.300687,23.721999],"type":"Point"}
}