<<<<<<< HEAD
{
  "id": 2252661,
  "type": "Feature",
  "properties": {
    "tgn:hierarchy":[
        "tgn:2252661",
        "tgn:1000001",
        "tgn:7012149",
        "tgn:7007826",
        "tgn:7029392"
    ],
    "tgn:id":2252661,
    "tgn:name":"Conner Branch",
    "tgn:placetype":[
        "aat:300008699"
    ]
},
  "bbox": [],
  "geometry": {"coordinates":[-99.1167,31.4833],"type":"Point"}
}
=======
{"geometry":{"type":"Point","coordinates":[-99.116700,31.483300]},"type":"Feature","properties":{"hierarchy":["tgn:2252661","tgn:1000001","tgn:7012149","tgn:7007826","tgn:7029392"],"placetype":["aat:300008699"],"id":2252661,"name:xx":"Conner Branch"}}
>>>>>>> 03f74aca74312dbeaf24d7e61306dd6a786dc3d0
