{
  "id": 7577120,
  "type": "Feature",
  "properties": {
    "tgn:hierarchy":[
        "tgn:7577120",
        "tgn:1001828",
        "tgn:1000004",
        "tgn:7000198",
        "tgn:7029392"
    ],
    "tgn:id":7577120,
    "tgn:name:en":"Kankip\u0101du",
    "tgn:placetype":[
        "aat:300008347"
    ]
},
  "bbox": [],
  "geometry": {"coordinates":[80.783333,16.45],"type":"Point"}
}