{
  "id": 2289974,
  "type": "Feature",
  "properties": {
    "tgn:hierarchy":[
        "tgn:2289974",
        "tgn:1000001",
        "tgn:7012149",
        "tgn:7007157",
        "tgn:2000185",
        "tgn:7029392"
    ],
    "tgn:id":2289974,
    "tgn:name":"Docker Hill",
    "tgn:placetype":[
        "aat:300008798"
    ]
},
  "bbox": [],
  "geometry": {"coordinates":[-123.5667,39.2833],"type":"Point"}
}