{
  "id": 2652009,
  "type": "Feature",
  "properties": {
    "tgn:hierarchy":[
        "tgn:2652009",
        "tgn:1000001",
        "tgn:7012149",
        "tgn:2000228",
        "tgn:7007158",
        "tgn:7029392"
    ],
    "tgn:id":2652009,
    "tgn:name":"Seldom Ridge Draw",
    "tgn:placetype":[
        "aat:300008761"
    ]
},
  "bbox": [],
  "geometry": {"coordinates":[-103.8333,38.7167],"type":"Point"}
}