<<<<<<< HEAD
{
  "id": 7369160,
  "type": "Feature",
  "properties": {
    "tgn:hierarchy":[
        "tgn:7369160",
        "tgn:7005581",
        "tgn:1000001",
        "tgn:7005560",
        "tgn:7029392"
    ],
    "tgn:id":7369160,
    "tgn:name":"Ju\u00e1rez Guerrero",
    "tgn:placetype":[
        "aat:300008347"
    ]
},
  "bbox": [],
  "geometry": {"coordinates":[-107.216667,28.466667],"type":"Point"}
}
=======
{"geometry":{"type":"Point","coordinates":[-107.216667,28.466667]},"type":"Feature","properties":{"hierarchy":["tgn:7369160","tgn:7005581","tgn:1000001","tgn:7005560","tgn:7029392"],"placetype":["aat:300008347"],"id":7369160,"name:xx":"Ju\u00e1rez Guerrero"}}
>>>>>>> 03f74aca74312dbeaf24d7e61306dd6a786dc3d0
