{
  "id": 7391013,
  "type": "Feature",
  "properties": {
    "tgn:hierarchy":[
        "tgn:7391013",
        "tgn:1000001",
        "tgn:7005591",
        "tgn:7005560",
        "tgn:7029392"
    ],
    "tgn:id":7391013,
    "tgn:name":"R\u00edo Mico",
    "tgn:placetype":[
        "aat:300008347"
    ]
},
  "bbox": [],
  "geometry": {"coordinates":[-94.716667,16.616667],"type":"Point"}
}