{
  "id": 7276379,
  "type": "Feature",
  "properties": {
    "tgn:hierarchy":[
        "tgn:7276379",
        "tgn:7002464",
        "tgn:1000049",
        "tgn:1000002",
        "tgn:7029392"
    ],
    "tgn:id":7276379,
    "tgn:name":"Tignamar, Portezuelo",
    "tgn:placetype":[
        "aat:300259572"
    ]
},
  "bbox": [],
  "geometry": {"coordinates":[-69.416667,-18.533333],"type":"Point"}
}