{
  "id": 1022065,
  "type": "Feature",
  "properties": {
    "tgn:hierarchy":[
        "tgn:1022065",
        "tgn:7012827",
        "tgn:7002454",
        "tgn:1000047",
        "tgn:1000002",
        "tgn:7029392"
    ],
    "tgn:id":1022065,
    "tgn:name":"Marzag\u00e3o",
    "tgn:placetype":[
        "aat:300008347"
    ]
},
  "bbox": [],
  "geometry": {"coordinates":[-48.6833,-17.9833],"type":"Point"}
}