<<<<<<< HEAD
{
  "id": 7379829,
  "type": "Feature",
  "properties": {
    "tgn:hierarchy":[
        "tgn:7379829",
        "tgn:1000001",
        "tgn:7005599",
        "tgn:7005560",
        "tgn:7029392"
    ],
    "tgn:id":7379829,
    "tgn:name":"Los Esteros",
    "tgn:placetype":[
        "aat:300008347"
    ]
},
  "bbox": [],
  "geometry": {"coordinates":[-98.233333,21.966667],"type":"Point"}
}
=======
{"geometry":{"type":"Point","coordinates":[-98.233333,21.966667]},"type":"Feature","properties":{"hierarchy":["tgn:7379829","tgn:1000001","tgn:7005599","tgn:7005560","tgn:7029392"],"placetype":["aat:300008347"],"id":7379829,"name:xx":"Los Esteros"}}
>>>>>>> 03f74aca74312dbeaf24d7e61306dd6a786dc3d0
