{
  "id": 1128537,
  "type": "Feature",
  "properties": {
    "tgn:hierarchy":[
        "tgn:1128537",
        "tgn:1001898",
        "tgn:7002454",
        "tgn:1000047",
        "tgn:1000002",
        "tgn:7029392"
    ],
    "tgn:id":1128537,
    "tgn:name":"Pequeri",
    "tgn:placetype":[
        "aat:300008707"
    ]
},
  "bbox": [],
  "geometry": {"coordinates":[-55.15,-17.65],"type":"Point"}
}