{
  "id": 7223063,
  "type": "Feature",
  "properties": {
    "tgn:hierarchy":[
        "tgn:7223063",
        "tgn:7002715",
        "tgn:7002731",
        "tgn:1000003",
        "tgn:1000074",
        "tgn:7029392"
    ],
    "tgn:id":7223063,
    "tgn:name":"Palai\u00f3kastron",
    "tgn:placetype":[
        "aat:300008347"
    ]
},
  "bbox": [],
  "geometry": {"coordinates":[23.416667,40.433333],"type":"Point"}
}