{
  "id": 2674649,
  "type": "Feature",
  "properties": {
    "tgn:hierarchy":[
        "tgn:2674649",
        "tgn:1000001",
        "tgn:7012149",
        "tgn:2000616",
        "tgn:7007253",
        "tgn:7029392"
    ],
    "tgn:id":2674649,
    "tgn:name":"Soap Creek",
    "tgn:placetype":[
        "aat:300008706"
    ]
},
  "bbox": [],
  "geometry": {"coordinates":[-91.4167,40.4167],"type":"Point"}
}