{
  "id": 2619004,
  "type": "Feature",
  "properties": {
    "tgn:hierarchy":[
        "tgn:2619004",
        "tgn:1000001",
        "tgn:7012149",
        "tgn:2001750",
        "tgn:7007712",
        "tgn:7029392"
    ],
    "tgn:id":2619004,
    "tgn:name":"Righthand Creek",
    "tgn:placetype":[
        "aat:300008706"
    ]
},
  "bbox": [],
  "geometry": {"coordinates":[-79.0833,33.6333],"type":"Point"}
}