{
  "id": 2298637,
  "type": "Feature",
  "properties": {
    "tgn:hierarchy":[
        "tgn:2298637",
        "tgn:1000001",
        "tgn:7019560",
        "tgn:7012149",
        "tgn:7007566",
        "tgn:7029392"
    ],
    "tgn:id":2298637,
    "tgn:name":"Dry Tank",
    "tgn:placetype":[
        "aat:300006191"
    ]
},
  "bbox": [],
  "geometry": {"coordinates":[-104.05,34.2667],"type":"Point"}
}