<<<<<<< HEAD
{
  "id": 2159752,
  "type": "Feature",
  "properties": {
    "tgn:hierarchy":[
        "tgn:2159752",
        "tgn:1000001",
        "tgn:7012149",
        "tgn:2001908",
        "tgn:7007825",
        "tgn:7029392"
    ],
    "tgn:id":2159752,
    "tgn:name":"Beech Bottom Mountain",
    "tgn:placetype":[
        "aat:300008798"
    ]
},
  "bbox": [],
  "geometry": {"coordinates":[-84.7667,35.8],"type":"Point"}
}
=======
{"geometry":{"type":"Point","coordinates":[-84.766700,35.800000]},"type":"Feature","properties":{"hierarchy":["tgn:2159752","tgn:1000001","tgn:7012149","tgn:2001908","tgn:7007825","tgn:7029392"],"placetype":["aat:300008798"],"id":2159752,"name:xx":"Beech Bottom Mountain"}}
>>>>>>> 03f74aca74312dbeaf24d7e61306dd6a786dc3d0
