<<<<<<< HEAD
{
  "id": 7022630,
  "type": "Feature",
  "properties": {
    "tgn:hierarchy":[
        "tgn:7022630",
        "tgn:1000001",
        "tgn:7012149",
        "tgn:7007709",
        "tgn:7029392"
    ],
    "tgn:id":7022630,
    "tgn:name":"Cow Gallus Creek",
    "tgn:placetype":[
        "aat:300008706"
    ]
},
  "bbox": [],
  "geometry": {"coordinates":[-76.5667,35.1333],"type":"Point"}
}
=======
{"geometry":{"type":"Point","coordinates":[-76.566700,35.133300]},"type":"Feature","properties":{"hierarchy":["tgn:7022630","tgn:1000001","tgn:7012149","tgn:7007709","tgn:7029392"],"placetype":["aat:300008706"],"id":7022630,"name:xx":"Cow Gallus Creek"}}
>>>>>>> 03f74aca74312dbeaf24d7e61306dd6a786dc3d0
