{
  "id": 7506629,
  "type": "Feature",
  "properties": {
    "tgn:hierarchy":[
        "tgn:7506629",
        "tgn:7016670",
        "tgn:1008380",
        "tgn:1000226",
        "tgn:1000006",
        "tgn:7029392"
    ],
    "tgn:id":7506629,
    "tgn:name:en":"Ringdove Bay",
    "tgn:placetype":[
        "aat:300132316"
    ]
},
  "bbox": [],
  "geometry": {"coordinates":[178.786111,-49.703333],"type":"Point"}
}