{
  "id": 2338200,
  "type": "Feature",
  "properties": {
    "tgn:hierarchy":[
        "tgn:2338200",
        "tgn:1000001",
        "tgn:7012149",
        "tgn:2001720",
        "tgn:7007708",
        "tgn:7029392"
    ],
    "tgn:id":2338200,
    "tgn:name":"Fox Prairie",
    "tgn:placetype":[
        "aat:300055621"
    ]
},
  "bbox": [],
  "geometry": {"coordinates":[-118.25,45.4167],"type":"Point"}
}