{
  "id": 7518149,
  "type": "Feature",
  "properties": {
    "tgn:hierarchy":[
        "tgn:7518149",
        "tgn:1009227",
        "tgn:1000226",
        "tgn:7016822",
        "tgn:1000006",
        "tgn:7029392"
    ],
    "tgn:id":7518149,
    "tgn:name:en":"Kepler Mountains",
    "tgn:placetype":[
        "aat:300008795"
    ]
},
  "bbox": [],
  "geometry": {"coordinates":[167.483333,-46.416667],"type":"Point"}
}