{
  "id": 2291396,
  "type": "Feature",
  "properties": {
    "tgn:hierarchy":[
        "tgn:2291396",
        "tgn:1000001",
        "tgn:7012149",
        "tgn:2000234",
        "tgn:7007158",
        "tgn:7029392"
    ],
    "tgn:id":2291396,
    "tgn:name":"Doing Ditch",
    "tgn:placetype":[
        "aat:300006075"
    ]
},
  "bbox": [],
  "geometry": {"coordinates":[-108.4833,38.25],"type":"Point"}
}