{
  "id": 1134003,
  "type": "Feature",
  "properties": {
    "tgn:hierarchy":[
        "tgn:1134003",
        "tgn:1000001",
        "tgn:7012149",
        "tgn:7007524",
        "tgn:7029392"
    ],
    "tgn:id":1134003,
    "tgn:name":"North Willow Creek",
    "tgn:placetype":[
        "aat:300008706"
    ]
},
  "bbox": [],
  "geometry": {"coordinates":[-110.7167,47.4333],"type":"Point"}
}