{
  "id": 7432646,
  "type": "Feature",
  "properties": {
    "tgn:hierarchy":[
        "tgn:7432646",
        "tgn:7005581",
        "tgn:1000001",
        "tgn:7005560",
        "tgn:7029392"
    ],
    "tgn:id":7432646,
    "tgn:name":"Toma de Agua",
    "tgn:placetype":[
        "aat:300008347"
    ]
},
  "bbox": [],
  "geometry": {"coordinates":[-107.466667,28.516667],"type":"Point"}
}