{
  "id": 7492867,
  "type": "Feature",
  "properties": {
    "tgn:hierarchy":[
        "tgn:7492867",
        "tgn:1000004",
        "tgn:7467799",
        "tgn:1000141",
        "tgn:7029392"
    ],
    "tgn:id":7492867,
    "tgn:name":"Shaziyuan",
    "tgn:placetype":[
        "aat:300008347"
    ]
},
  "bbox": [],
  "geometry": {"coordinates":[120.4925,24.133333],"type":"Point"}
}