{
  "id": 7034760,
  "type": "Feature",
  "properties": {
    "tgn:hierarchy":[
        "tgn:7034760",
        "tgn:1000003",
        "tgn:7003236",
        "tgn:1000080",
        "tgn:7029392"
    ],
    "tgn:id":7034760,
    "tgn:name":"Groppo, Monte",
    "tgn:placetype":[
        "aat:300008795"
    ]
},
  "bbox": [],
  "geometry": {"coordinates":[9.281389,44.36],"type":"Point"}
}