{
  "id": 2365759,
  "type": "Feature",
  "properties": {
    "tgn:hierarchy":[
        "tgn:2365759",
        "tgn:1000001",
        "tgn:2001702",
        "tgn:7012149",
        "tgn:7007708",
        "tgn:7029392"
    ],
    "tgn:id":2365759,
    "tgn:name":"Gregory Point",
    "tgn:placetype":[
        "aat:300008850"
    ]
},
  "bbox": [],
  "geometry": {"coordinates":[-124.3667,43.3333],"type":"Point"}
}