<<<<<<< HEAD
{
  "id": 7351212,
  "type": "Feature",
  "properties": {
    "tgn:hierarchy":[
        "tgn:7351212",
        "tgn:7005581",
        "tgn:1000001",
        "tgn:7005560",
        "tgn:7029392"
    ],
    "tgn:id":7351212,
    "tgn:name":"Boca de Potrero",
    "tgn:placetype":[
        "aat:300008347"
    ]
},
  "bbox": [],
  "geometry": {"coordinates":[-106.25,26.983333],"type":"Point"}
}
=======
{"geometry":{"type":"Point","coordinates":[-106.250000,26.983333]},"type":"Feature","properties":{"hierarchy":["tgn:7351212","tgn:7005581","tgn:1000001","tgn:7005560","tgn:7029392"],"placetype":["aat:300008347"],"id":7351212,"name:xx":"Boca de Potrero"}}
>>>>>>> 03f74aca74312dbeaf24d7e61306dd6a786dc3d0
