{
  "id": 7249634,
  "type": "Feature",
  "properties": {
    "tgn:hierarchy":[
        "tgn:7249634",
        "tgn:7003457",
        "tgn:1000003",
        "tgn:1000063",
        "tgn:7018236",
        "tgn:7029392"
    ],
    "tgn:id":7249634,
    "tgn:name":"Nieuwpoort",
    "tgn:placetype":[
        "aat:300008347"
    ]
},
  "bbox": [],
  "geometry": {"coordinates":[3.78139,50.769335],"type":"Point"}
}