{
  "id": 1010453,
  "type": "Feature",
  "properties": {
    "tgn:hierarchy":[
        "tgn:1010453",
        "tgn:1007723",
        "tgn:1000004",
        "tgn:1010290",
        "tgn:7017024",
        "tgn:7018214",
        "tgn:7002435",
        "tgn:7029392"
    ],
    "tgn:id":1010453,
    "tgn:name":"Arkticheskiy, Mys",
    "tgn:placetype":[
        "aat:300008850"
    ]
},
  "bbox": [],
  "geometry": {"coordinates":[95.75,81.25],"type":"Point"}
}