{
  "id": 2327036,
  "type": "Feature",
  "properties": {
    "tgn:hierarchy":[
        "tgn:2327036",
        "tgn:1000001",
        "tgn:2001705",
        "tgn:7012149",
        "tgn:7007708",
        "tgn:7029392"
    ],
    "tgn:id":2327036,
    "tgn:name":"Firestone Basin",
    "tgn:placetype":[
        "aat:300386845"
    ]
},
  "bbox": [],
  "geometry": {"coordinates":[-120.5833,43.7167],"type":"Point"}
}