{
  "id": 7435861,
  "type": "Feature",
  "properties": {
    "tgn:hierarchy":[
        "tgn:7435861",
        "tgn:7005581",
        "tgn:1000001",
        "tgn:7005560",
        "tgn:7029392"
    ],
    "tgn:id":7435861,
    "tgn:name":"Sombreritos",
    "tgn:placetype":[
        "aat:300008347"
    ]
},
  "bbox": [],
  "geometry": {"coordinates":[-106.666667,25.883333],"type":"Point"}
}