{
  "id": 7067946,
  "type": "Feature",
  "properties": {
    "tgn:hierarchy":[
        "tgn:7067946",
        "tgn:1000003",
        "tgn:7003676",
        "tgn:7000084",
        "tgn:7029392"
    ],
    "tgn:id":7067946,
    "tgn:name":"Torfmoor",
    "tgn:placetype":[
        "aat:300386886"
    ]
},
  "bbox": [],
  "geometry": {"coordinates":[10.433333,52.583333],"type":"Point"}
}