{
  "id": 7143475,
  "type": "Feature",
  "properties": {
    "tgn:hierarchy":[
        "tgn:7143475",
        "tgn:1000003",
        "tgn:7000094",
        "tgn:7000084",
        "tgn:7029392"
    ],
    "tgn:id":7143475,
    "tgn:name":"Lockwisch-Dorf",
    "tgn:placetype":[
        "aat:300008347"
    ]
},
  "bbox": [],
  "geometry": {"coordinates":[10.85,53.85],"type":"Point"}
}