{
  "id": 7277796,
  "type": "Feature",
  "properties": {
    "tgn:hierarchy":[
        "tgn:7277796",
        "tgn:1001768",
        "tgn:1000049",
        "tgn:1000002",
        "tgn:7029392"
    ],
    "tgn:id":7277796,
    "tgn:name":"Hornillos, Caleta",
    "tgn:placetype":[
        "aat:300132317"
    ]
},
  "bbox": [],
  "geometry": {"coordinates":[-71.688889,-33.104167],"type":"Point"}
}