{
  "id": 7364597,
  "type": "Feature",
  "properties": {
    "tgn:hierarchy":[
        "tgn:7364597",
        "tgn:1000001",
        "tgn:7005589",
        "tgn:7005560",
        "tgn:7029392"
    ],
    "tgn:id":7364597,
    "tgn:name":"El Saucito",
    "tgn:placetype":[
        "aat:300008347"
    ]
},
  "bbox": [],
  "geometry": {"coordinates":[-99.85,25.066667],"type":"Point"}
}