{
  "id": 2552485,
  "type": "Feature",
  "properties": {
    "tgn:hierarchy":[
        "tgn:2552485",
        "tgn:1002232",
        "tgn:1000001",
        "tgn:7012149",
        "tgn:7007565",
        "tgn:7029392"
    ],
    "tgn:id":2552485,
    "tgn:name":"Nummy, Lake",
    "tgn:placetype":[
        "aat:300006191"
    ]
},
  "bbox": [],
  "geometry": {"coordinates":[-74.85,39.2333],"type":"Point"}
}