{
  "id": 5002439,
  "type": "Feature",
  "properties": {
    "tgn:hierarchy":[
        "tgn:5002439",
        "tgn:7003139",
        "tgn:1000003",
        "tgn:7003080",
        "tgn:1000080",
        "tgn:7029392"
    ],
    "tgn:id":5002439,
    "tgn:name":"Bassano in Teverina",
    "tgn:placetype":[
        "aat:300008347"
    ]
},
  "bbox": [],
  "geometry": {"coordinates":[12.3167,42.466],"type":"Point"}
}