{
  "id": 2238281,
  "type": "Feature",
  "properties": {
    "tgn:hierarchy":[
        "tgn:2238281",
        "tgn:2001560",
        "tgn:1000001",
        "tgn:7012149",
        "tgn:7007705",
        "tgn:7029392"
    ],
    "tgn:id":2238281,
    "tgn:name":"Chocolate Butte",
    "tgn:placetype":[
        "aat:300008798"
    ]
},
  "bbox": [],
  "geometry": {"coordinates":[-103.3333,46.6667],"type":"Point"}
}