{
  "id": 7351064,
  "type": "Feature",
  "properties": {
    "tgn:hierarchy":[
        "tgn:7351064",
        "tgn:1001853",
        "tgn:1000001",
        "tgn:7005560",
        "tgn:7029392"
    ],
    "tgn:id":7351064,
    "tgn:name":"Arcinas",
    "tgn:placetype":[
        "aat:300008347"
    ]
},
  "bbox": [],
  "geometry": {"coordinates":[-100.966667,26.866667],"type":"Point"}
}