{
  "id": 1115063,
  "type": "Feature",
  "properties": {
    "tgn:hierarchy":[
        "tgn:1115063",
        "tgn:7002444",
        "tgn:1000003",
        "tgn:7029508",
        "tgn:7008591",
        "tgn:7029392"
    ],
    "tgn:id":1115063,
    "tgn:name:en":"Yell Sound",
    "tgn:placetype":[
        "aat:300266558"
    ]
},
  "bbox": [],
  "geometry": {"coordinates":[-1.25,60.533333],"type":"Point"}
}