{
  "id": 7035373,
  "type": "Feature",
  "properties": {
    "tgn:hierarchy":[
        "tgn:7035373",
        "tgn:1003488",
        "tgn:1000003",
        "tgn:7002993",
        "tgn:1000080",
        "tgn:7029392"
    ],
    "tgn:id":7035373,
    "tgn:name":"Ponte Pinzano",
    "tgn:placetype":[
        "aat:300007836"
    ]
},
  "bbox": [],
  "geometry": {"coordinates":[12.957222,46.185833],"type":"Point"}
}