{
  "id": 7539351,
  "type": "Feature",
  "properties": {
    "tgn:hierarchy":[
        "tgn:7539351",
        "tgn:7001242",
        "tgn:7001311",
        "tgn:7016833",
        "tgn:7029392"
    ],
    "tgn:id":7539351,
    "tgn:name:en":"Mutayyah, W\u0101d\u012b",
    "tgn:placetype":[
        "aat:300379998"
    ]
},
  "bbox": [],
  "geometry": {"coordinates":[32.477306,26.206243],"type":"Point"}
}