{
  "id": 7425973,
  "type": "Feature",
  "properties": {
    "tgn:hierarchy":[
        "tgn:7425973",
        "tgn:7005581",
        "tgn:1000001",
        "tgn:7005560",
        "tgn:7029392"
    ],
    "tgn:id":7425973,
    "tgn:name":"Piedra Encimada",
    "tgn:placetype":[
        "aat:300008347"
    ]
},
  "bbox": [],
  "geometry": {"coordinates":[-106.766667,27.45],"type":"Point"}
}