<<<<<<< HEAD
{
  "id": 7478968,
  "type": "Feature",
  "properties": {
    "tgn:hierarchy":[
        "tgn:7478968",
        "tgn:1000004",
        "tgn:7001009",
        "tgn:1000141",
        "tgn:7029392"
    ],
    "tgn:id":7478968,
    "tgn:name":"Gui Shan",
    "tgn:placetype":[
        "aat:300008798"
    ]
},
  "bbox": [],
  "geometry": {"coordinates":[121.276389,24.303611],"type":"Point"}
}
=======
{"geometry":{"type":"Point","coordinates":[121.276389,24.303611]},"type":"Feature","properties":{"hierarchy":["tgn:7478968","tgn:1000004","tgn:7001009","tgn:1000141","tgn:7029392"],"placetype":["aat:300008798"],"id":7478968,"name:xx":"Gui Shan"}}
>>>>>>> 03f74aca74312dbeaf24d7e61306dd6a786dc3d0
