<<<<<<< HEAD
{
  "id": 7175822,
  "type": "Feature",
  "properties": {
    "tgn:hierarchy":[
        "tgn:7175822",
        "tgn:1000003",
        "tgn:7003687",
        "tgn:7000084",
        "tgn:7029392"
    ],
    "tgn:id":7175822,
    "tgn:name":"Gro\u00df Wegenitz",
    "tgn:placetype":[
        "aat:300000745"
    ]
},
  "bbox": [],
  "geometry": {"coordinates":[11.766667,52.916667],"type":"Point"}
}
=======
{"geometry":{"type":"Point","coordinates":[11.766667,52.916667]},"type":"Feature","properties":{"hierarchy":["tgn:7175822","tgn:1000003","tgn:7003687","tgn:7000084","tgn:7029392"],"placetype":["aat:300000745"],"id":7175822,"name:xx":"Gro\u00df Wegenitz"}}
>>>>>>> 03f74aca74312dbeaf24d7e61306dd6a786dc3d0
