{
  "id": 4010229,
  "type": "Feature",
  "properties": {
    "tgn:hierarchy":[
        "tgn:4010229",
        "tgn:1000003",
        "tgn:7003687",
        "tgn:7000084",
        "tgn:7029392"
    ],
    "tgn:id":4010229,
    "tgn:name":"Schulpforta",
    "tgn:placetype":[
        "aat:300008347"
    ]
},
  "bbox": [],
  "geometry": {"coordinates":[11.75,51.15],"type":"Point"}
}