{
  "id": 7520941,
  "type": "Feature",
  "properties": {
    "tgn:hierarchy":[
        "tgn:7520941",
        "tgn:7001242",
        "tgn:7001105",
        "tgn:7016833",
        "tgn:7029392"
    ],
    "tgn:id":7520941,
    "tgn:name:en":"Ad Daw\u0101l\u0163ah",
    "tgn:placetype":[
        "aat:300008347"
    ]
},
  "bbox": [],
  "geometry": {"coordinates":[31.047222,29.069444],"type":"Point"}
}