{
  "id": 2628585,
  "type": "Feature",
  "properties": {
    "tgn:hierarchy":[
        "tgn:2628585",
        "tgn:1000001",
        "tgn:1002260",
        "tgn:7012149",
        "tgn:7007920",
        "tgn:7029392"
    ],
    "tgn:id":2628585,
    "tgn:name":"Rooster Comb",
    "tgn:placetype":[
        "aat:300008798"
    ]
},
  "bbox": [],
  "geometry": {"coordinates":[-120.3167,47.3833],"type":"Point"}
}