{
  "id": 1062043,
  "type": "Feature",
  "properties": {
    "tgn:hierarchy":[
        "tgn:1062043",
        "tgn:7002758",
        "tgn:7002830",
        "tgn:1000003",
        "tgn:1000095",
        "tgn:7029392"
    ],
    "tgn:id":1062043,
    "tgn:name":"Gauc\u00edn",
    "tgn:placetype":[
        "aat:300008347"
    ]
},
  "bbox": [],
  "geometry": {"coordinates":[-5.316667,36.516667],"type":"Point"}
}