{
  "id": 7591806,
  "type": "Feature",
  "properties": {
    "tgn:hierarchy":[
        "tgn:7591806",
        "tgn:1000004",
        "tgn:7000198",
        "tgn:7000799",
        "tgn:7029392"
    ],
    "tgn:id":7591806,
    "tgn:name:en":"Mukhr",
    "tgn:placetype":[
        "aat:300008347"
    ]
},
  "bbox": [],
  "geometry": {"coordinates":[74.766129,32.680699],"type":"Point"}
}