{
  "id": 2120285,
  "type": "Feature",
  "properties": {
    "tgn:hierarchy":[
        "tgn:2120285",
        "tgn:1000001",
        "tgn:7012149",
        "tgn:2002264",
        "tgn:7013961",
        "tgn:7029392"
    ],
    "tgn:id":2120285,
    "tgn:name":"Vale",
    "tgn:placetype":[
        "aat:300008347",
        "aat:300387210"
    ]
},
  "bbox": [],
  "geometry": {"coordinates":[-80.7167,37.8667],"type":"Point"}
}