<<<<<<< HEAD
{
  "id": 7377168,
  "type": "Feature",
  "properties": {
    "tgn:hierarchy":[
        "tgn:7377168",
        "tgn:7005584",
        "tgn:1000001",
        "tgn:7005560",
        "tgn:7029392"
    ],
    "tgn:id":7377168,
    "tgn:name":"La Sardina",
    "tgn:placetype":[
        "aat:300008347"
    ]
},
  "bbox": [],
  "geometry": {"coordinates":[-101.633333,20.883333],"type":"Point"}
}
=======
{"geometry":{"type":"Point","coordinates":[-101.633333,20.883333]},"type":"Feature","properties":{"hierarchy":["tgn:7377168","tgn:7005584","tgn:1000001","tgn:7005560","tgn:7029392"],"placetype":["aat:300008347"],"id":7377168,"name:xx":"La Sardina"}}
>>>>>>> 03f74aca74312dbeaf24d7e61306dd6a786dc3d0
