<<<<<<< HEAD
{
  "id": 7057499,
  "type": "Feature",
  "properties": {
    "tgn:hierarchy":[
        "tgn:7057499",
        "tgn:7003158",
        "tgn:1000003",
        "tgn:7003124",
        "tgn:1000080",
        "tgn:7029392"
    ],
    "tgn:id":7057499,
    "tgn:name":"Caderzone",
    "tgn:placetype":[
        "aat:300008347"
    ]
},
  "bbox": [],
  "geometry": {"coordinates":[10.75,46.133333],"type":"Point"}
}
=======
{"geometry":{"type":"Point","coordinates":[10.750000,46.133333]},"type":"Feature","properties":{"hierarchy":["tgn:7057499","tgn:7003158","tgn:1000003","tgn:7003124","tgn:1000080","tgn:7029392"],"placetype":["aat:300008347"],"id":7057499,"name:xx":"Caderzone"}}
>>>>>>> 03f74aca74312dbeaf24d7e61306dd6a786dc3d0
