{
  "id": 2199548,
  "type": "Feature",
  "properties": {
    "tgn:hierarchy":[
        "tgn:2199548",
        "tgn:1000001",
        "tgn:7012149",
        "tgn:2001847",
        "tgn:7007825",
        "tgn:7029392"
    ],
    "tgn:id":2199548,
    "tgn:name":"Brush Creek",
    "tgn:placetype":[
        "aat:300008706"
    ]
},
  "bbox": [],
  "geometry": {"coordinates":[-87.1167,36.2167],"type":"Point"}
}