<<<<<<< HEAD
{
  "id": 2153406,
  "type": "Feature",
  "properties": {
    "tgn:hierarchy":[
        "tgn:2153406",
        "tgn:1000001",
        "tgn:7012149",
        "tgn:2002360",
        "tgn:7007922",
        "tgn:7029392"
    ],
    "tgn:id":2153406,
    "tgn:name":"Bean Lake",
    "tgn:placetype":[
        "aat:300008680"
    ]
},
  "bbox": [],
  "geometry": {"coordinates":[-91.5667,45.9333],"type":"Point"}
}
=======
{"geometry":{"type":"Point","coordinates":[-91.566700,45.933300]},"type":"Feature","properties":{"hierarchy":["tgn:2153406","tgn:1000001","tgn:7012149","tgn:2002360","tgn:7007922","tgn:7029392"],"placetype":["aat:300008680"],"id":2153406,"name:xx":"Bean Lake"}}
>>>>>>> 03f74aca74312dbeaf24d7e61306dd6a786dc3d0
