{
  "id": 2340570,
  "type": "Feature",
  "properties": {
    "tgn:hierarchy":[
        "tgn:2340570",
        "tgn:1000001",
        "tgn:7012149",
        "tgn:2001295",
        "tgn:7007524",
        "tgn:7029392"
    ],
    "tgn:id":2340570,
    "tgn:name":"Frenchman Creek",
    "tgn:placetype":[
        "aat:300008706"
    ]
},
  "bbox": [],
  "geometry": {"coordinates":[-107.25,48.5167],"type":"Point"}
}