{
  "id": 2370514,
  "type": "Feature",
  "properties": {
    "tgn:hierarchy":[
        "tgn:2370514",
        "tgn:1000001",
        "tgn:7012149",
        "tgn:2001449",
        "tgn:7007566",
        "tgn:7029392"
    ],
    "tgn:id":2370514,
    "tgn:name":"Hachita Canyon",
    "tgn:placetype":[
        "aat:300008761"
    ]
},
  "bbox": [],
  "geometry": {"coordinates":[-106.2667,36.5667],"type":"Point"}
}