{
  "id": 2260812,
  "type": "Feature",
  "properties": {
    "tgn:hierarchy":[
        "tgn:2260812",
        "tgn:1000001",
        "tgn:7012149",
        "tgn:2001050",
        "tgn:7007521",
        "tgn:7029392"
    ],
    "tgn:id":2260812,
    "tgn:name":"County Ditch Number Six",
    "tgn:placetype":[
        "aat:300006075"
    ]
},
  "bbox": [],
  "geometry": {"coordinates":[-94.0333,44.3167],"type":"Point"}
}