{
  "id": 7486525,
  "type": "Feature",
  "properties": {
    "tgn:hierarchy":[
        "tgn:7486525",
        "tgn:1000004",
        "tgn:1000454",
        "tgn:1000141",
        "tgn:7029392"
    ],
    "tgn:id":7486525,
    "tgn:name":"Lengshuikeng",
    "tgn:placetype":[
        "aat:300008347"
    ]
},
  "bbox": [],
  "geometry": {"coordinates":[121.425543,25.092054],"type":"Point"}
}