{
  "id": 2781627,
  "type": "Feature",
  "properties": {
    "tgn:hierarchy":[
        "tgn:2781627",
        "tgn:1000001",
        "tgn:7012149",
        "tgn:1002582",
        "tgn:7007240",
        "tgn:7029392"
    ],
    "tgn:id":2781627,
    "tgn:name":"Woodrings Point",
    "tgn:placetype":[
        "aat:300008850"
    ]
},
  "bbox": [],
  "geometry": {"coordinates":[-82.05,26.4667],"type":"Point"}
}