{
  "id": 2180643,
  "type": "Feature",
  "properties": {
    "tgn:hierarchy":[
        "tgn:2180643",
        "tgn:1000001",
        "tgn:7012149",
        "tgn:2000968",
        "tgn:7007520",
        "tgn:7029392"
    ],
    "tgn:id":2180643,
    "tgn:name":"Bloom Lake",
    "tgn:placetype":[
        "aat:300008680"
    ]
},
  "bbox": [],
  "geometry": {"coordinates":[-85.2667,44.55],"type":"Point"}
}