<<<<<<< HEAD
{
  "id": 7474145,
  "type": "Feature",
  "properties": {
    "tgn:hierarchy":[
        "tgn:7474145",
        "tgn:7001004",
        "tgn:1000004",
        "tgn:1000141",
        "tgn:7029392"
    ],
    "tgn:id":7474145,
    "tgn:name":"Xiyuantan",
    "tgn:placetype":[
        "aat:300008347",
        "aat:300387200"
    ]
},
  "bbox": [],
  "geometry": {"coordinates":[120.516667,22.933333],"type":"Point"}
}
=======
{"geometry":{"type":"Point","coordinates":[120.516667,22.933333]},"type":"Feature","properties":{"hierarchy":["tgn:7474145","tgn:7001004","tgn:1000004","tgn:1000141","tgn:7029392"],"placetype":["aat:300008347","aat:300387200"],"id":7474145,"name:xx":"Xiyuantan"}}
>>>>>>> 03f74aca74312dbeaf24d7e61306dd6a786dc3d0
