{
  "id": 1136135,
  "type": "Feature",
  "properties": {
    "tgn:hierarchy":[
        "tgn:1136135",
        "tgn:1000001",
        "tgn:7012149",
        "tgn:7007157",
        "tgn:1002937",
        "tgn:7029392"
    ],
    "tgn:id":1136135,
    "tgn:name":"West Side Canal",
    "tgn:placetype":[
        "aat:300006075"
    ]
},
  "bbox": [],
  "geometry": {"coordinates":[-121.7833,38.9833],"type":"Point"}
}