{
  "id": 7439909,
  "type": "Feature",
  "properties": {
    "tgn:hierarchy":[
        "tgn:7439909",
        "tgn:7005580",
        "tgn:1000001",
        "tgn:7005560",
        "tgn:7029392"
    ],
    "tgn:id":7439909,
    "tgn:name":"San Pedro Buenavista",
    "tgn:placetype":[
        "aat:300008347"
    ]
},
  "bbox": [],
  "geometry": {"coordinates":[-92.483333,15.783333],"type":"Point"}
}