{
  "id": 7512240,
  "type": "Feature",
  "properties": {
    "tgn:hierarchy":[
        "tgn:7512240",
        "tgn:1009227",
        "tgn:1000226",
        "tgn:7018437",
        "tgn:1000006",
        "tgn:7029392"
    ],
    "tgn:id":7512240,
    "tgn:name:en":"Ironstone Creek",
    "tgn:placetype":[
        "aat:300008699"
    ]
},
  "bbox": [],
  "geometry": {"coordinates":[168.733333,-44.766667],"type":"Point"}
}