{
  "id": 7035854,
  "type": "Feature",
  "properties": {
    "tgn:hierarchy":[
        "tgn:7035854",
        "tgn:7003006",
        "tgn:1000003",
        "tgn:7002997",
        "tgn:1000080",
        "tgn:7029392"
    ],
    "tgn:id":7035854,
    "tgn:name":"Deserto",
    "tgn:placetype":[
        "aat:300008347"
    ]
},
  "bbox": [],
  "geometry": {"coordinates":[12.261667,45.104444],"type":"Point"}
}