{
  "id": 7420790,
  "type": "Feature",
  "properties": {
    "tgn:hierarchy":[
        "tgn:7420790",
        "tgn:1000001",
        "tgn:7005589",
        "tgn:7005560",
        "tgn:7029392"
    ],
    "tgn:id":7420790,
    "tgn:name:es":"Pe\u00f1a Blanca",
    "tgn:placetype":[
        "aat:300008347"
    ]
},
  "bbox": [],
  "geometry": {"coordinates":[-99.000556,25.840833],"type":"Point"}
}