{
  "id": 2155357,
  "type": "Feature",
  "properties": {
    "tgn:hierarchy":[
        "tgn:2155357",
        "tgn:1000001",
        "tgn:2000198",
        "tgn:7012149",
        "tgn:7007158",
        "tgn:7029392"
    ],
    "tgn:id":2155357,
    "tgn:name":"Bear Peak",
    "tgn:placetype":[
        "aat:300008798"
    ]
},
  "bbox": [],
  "geometry": {"coordinates":[-105.2833,39.95],"type":"Point"}
}