{
  "id": 2135395,
  "type": "Feature",
  "properties": {
    "tgn:hierarchy":[
        "tgn:2135395",
        "tgn:2000856",
        "tgn:1000001",
        "tgn:7012149",
        "tgn:7007256",
        "tgn:7029392"
    ],
    "tgn:id":2135395,
    "tgn:name":"Antoine, Bayou",
    "tgn:placetype":[
        "aat:300008699"
    ]
},
  "bbox": [],
  "geometry": {"coordinates":[-90.7333,30.1667],"type":"Point"}
}