{
  "id": 2677639,
  "type": "Feature",
  "properties": {
    "tgn:hierarchy":[
        "tgn:2677639",
        "tgn:1000001",
        "tgn:7012149",
        "tgn:1002870",
        "tgn:7007240",
        "tgn:7029392"
    ],
    "tgn:id":2677639,
    "tgn:name":"South Creek",
    "tgn:placetype":[
        "aat:300008706"
    ]
},
  "bbox": [],
  "geometry": {"coordinates":[-82.45,27.25],"type":"Point"}
}