{
  "id": 2022402,
  "type": "Feature",
  "properties": {
    "tgn:hierarchy":[
        "tgn:2022402",
        "tgn:1000001",
        "tgn:7012149",
        "tgn:2124023",
        "tgn:7007248",
        "tgn:7029392"
    ],
    "tgn:id":2022402,
    "tgn:name":"Chamblee",
    "tgn:placetype":[
        "aat:300008347"
    ]
},
  "bbox": [],
  "geometry": {"coordinates":[-84.2833,33.8833],"type":"Point"}
}