{
  "id": 7161048,
  "type": "Feature",
  "properties": {
    "tgn:hierarchy":[
        "tgn:7161048",
        "tgn:7003669",
        "tgn:1000003",
        "tgn:7000084",
        "tgn:7029392"
    ],
    "tgn:id":7161048,
    "tgn:name":"Hochwies",
    "tgn:placetype":[
        "aat:300000206"
    ]
},
  "bbox": [],
  "geometry": {"coordinates":[12.783333,49.083333],"type":"Point"}
}