{
  "id": 7301531,
  "type": "Feature",
  "properties": {
    "tgn:hierarchy":[
        "tgn:7301531",
        "tgn:7002824",
        "tgn:1000003",
        "tgn:7002786",
        "tgn:1000095",
        "tgn:7029392"
    ],
    "tgn:id":7301531,
    "tgn:name":"Mira, Monte",
    "tgn:placetype":[
        "aat:300008795"
    ]
},
  "bbox": [],
  "geometry": {"coordinates":[-9.033333,42.85],"type":"Point"}
}