{
  "id": 1016419,
  "type": "Feature",
  "properties": {
    "tgn:hierarchy":[
        "tgn:1016419",
        "tgn:1001595",
        "tgn:1000001",
        "tgn:7004624",
        "tgn:7029392"
    ],
    "tgn:id":1016419,
    "tgn:name":"Ranchuelo",
    "tgn:placetype":[
        "aat:300008347"
    ]
},
  "bbox": [],
  "geometry": {"coordinates":[-80.15,22.3833],"type":"Point"}
}