{
  "id": 7268202,
  "type": "Feature",
  "properties": {
    "tgn:concordances":{
        "gn:id":"2750016"
    },
    "tgn:hierarchy":[
        "tgn:7268202",
        "tgn:1000003",
        "tgn:7006951",
        "tgn:7016845",
        "tgn:7029392"
    ],
    "tgn:id":7268202,
    "tgn:name:nl":"Nollen",
    "tgn:placetype":[
        "aat:300008347"
    ]
},
  "bbox": [],
  "geometry": {"coordinates":[4.783333,52.65],"type":"Point"}
}