{
  "id": 7032187,
  "type": "Feature",
  "properties": {
    "tgn:hierarchy":[
        "tgn:7032187",
        "tgn:1000003",
        "tgn:1000070",
        "tgn:7002895",
        "tgn:7029392"
    ],
    "tgn:id":7032187,
    "tgn:name":"Saint-Barth\u00e9lemy, Calanques de",
    "tgn:placetype":[
        "aat:300132317"
    ]
},
  "bbox": [],
  "geometry": {"coordinates":[6.915,43.45],"type":"Point"}
}