{
  "id": 2719715,
  "type": "Feature",
  "properties": {
    "tgn:hierarchy":[
        "tgn:2719715",
        "tgn:1000001",
        "tgn:7012149",
        "tgn:2002111",
        "tgn:7007827",
        "tgn:7029392"
    ],
    "tgn:id":2719715,
    "tgn:name":"Three Peaks",
    "tgn:placetype":[
        "aat:300008798"
    ]
},
  "bbox": [],
  "geometry": {"coordinates":[-113.3667,37.7667],"type":"Point"}
}