{
  "id": 2207407,
  "type": "Feature",
  "properties": {
    "tgn:hierarchy":[
        "tgn:2207407",
        "tgn:1000001",
        "tgn:7012149",
        "tgn:2001300",
        "tgn:7007524",
        "tgn:7029392"
    ],
    "tgn:id":2207407,
    "tgn:name":"Bunkhouse Creek",
    "tgn:placetype":[
        "aat:300008706"
    ]
},
  "bbox": [],
  "geometry": {"coordinates":[-114.05,46.3667],"type":"Point"}
}