{
  "id": 2148378,
  "type": "Feature",
  "properties": {
    "tgn:hierarchy":[
        "tgn:2148378",
        "tgn:1000001",
        "tgn:7012149",
        "tgn:2001917",
        "tgn:7007825",
        "tgn:7029392"
    ],
    "tgn:id":2148378,
    "tgn:name":"Barn Hollow",
    "tgn:placetype":[
        "aat:300008761"
    ]
},
  "bbox": [],
  "geometry": {"coordinates":[-87.7833,36.4667],"type":"Point"}
}