{
  "id": 7050554,
  "type": "Feature",
  "properties": {
    "tgn:hierarchy":[
        "tgn:7050554",
        "tgn:7003008",
        "tgn:1000003",
        "tgn:7002997",
        "tgn:1000080",
        "tgn:7029392"
    ],
    "tgn:id":7050554,
    "tgn:name":"Lapio",
    "tgn:placetype":[
        "aat:300008347"
    ]
},
  "bbox": [],
  "geometry": {"coordinates":[11.533333,45.466667],"type":"Point"}
}