{
  "id": 2394708,
  "type": "Feature",
  "properties": {
    "tgn:hierarchy":[
        "tgn:2394708",
        "tgn:1000001",
        "tgn:7012149",
        "tgn:2001036",
        "tgn:7007521",
        "tgn:7029392"
    ],
    "tgn:id":2394708,
    "tgn:name":"Hoist Lake",
    "tgn:placetype":[
        "aat:300008680"
    ]
},
  "bbox": [],
  "geometry": {"coordinates":[-91.1667,47.6167],"type":"Point"}
}