{
  "id": 2161125,
  "type": "Feature",
  "properties": {
    "tgn:hierarchy":[
        "tgn:2161125",
        "tgn:1000001",
        "tgn:7012149",
        "tgn:7007525",
        "tgn:7029392"
    ],
    "tgn:id":2161125,
    "tgn:name":"Bell Creek",
    "tgn:placetype":[
        "aat:300008706"
    ]
},
  "bbox": [],
  "geometry": {"coordinates":[-96.4333,41.95],"type":"Point"}
}