{
  "id": 2697865,
  "type": "Feature",
  "properties": {
    "tgn:hierarchy":[
        "tgn:2697865",
        "tgn:1000001",
        "tgn:1002260",
        "tgn:7012149",
        "tgn:7007920",
        "tgn:7029392"
    ],
    "tgn:id":2697865,
    "tgn:name":"Stormy Spring",
    "tgn:placetype":[
        "aat:300008697"
    ]
},
  "bbox": [],
  "geometry": {"coordinates":[-120.3333,47.8833],"type":"Point"}
}