{
  "id": 1122012,
  "type": "Feature",
  "properties": {
    "tgn:hierarchy":[
        "tgn:1122012",
        "tgn:7001242",
        "tgn:7016562",
        "tgn:1000193",
        "tgn:7029392"
    ],
    "tgn:id":1122012,
    "tgn:name":"Blesbokspruit",
    "tgn:placetype":[
        "aat:300008707"
    ]
},
  "bbox": [],
  "geometry": {"coordinates":[28.483,-25.233],"type":"Point"}
}