{
  "id": 1016415,
  "type": "Feature",
  "properties": {
    "tgn:hierarchy":[
        "tgn:1016415",
        "tgn:1001204",
        "tgn:1000001",
        "tgn:7004624",
        "tgn:7029392"
    ],
    "tgn:id":1016415,
    "tgn:name":"Punta Alegre",
    "tgn:placetype":[
        "aat:300008347"
    ]
},
  "bbox": [],
  "geometry": {"coordinates":[-78.8167,22.3667],"type":"Point"}
}