{
  "id": 2427923,
  "type": "Feature",
  "properties": {
    "tgn:hierarchy":[
        "tgn:2427923",
        "tgn:2001726",
        "tgn:1000001",
        "tgn:7012149",
        "tgn:7007712",
        "tgn:7029392"
    ],
    "tgn:id":2427923,
    "tgn:name":"Joyce Branch",
    "tgn:placetype":[
        "aat:300008699"
    ]
},
  "bbox": [],
  "geometry": {"coordinates":[-81.65,33.6333],"type":"Point"}
}