{
  "id": 7051480,
  "type": "Feature",
  "properties": {
    "tgn:hierarchy":[
        "tgn:7051480",
        "tgn:7003135",
        "tgn:1000003",
        "tgn:7003080",
        "tgn:1000080",
        "tgn:7029392"
    ],
    "tgn:id":7051480,
    "tgn:name":"Pezze, Monte le",
    "tgn:placetype":[
        "aat:300008795"
    ]
},
  "bbox": [],
  "geometry": {"coordinates":[13.533333,41.35],"type":"Point"}
}