{
  "id": 2440287,
  "type": "Feature",
  "properties": {
    "tgn:hierarchy":[
        "tgn:2440287",
        "tgn:1000001",
        "tgn:7012149",
        "tgn:1002592",
        "tgn:7007523",
        "tgn:7029392"
    ],
    "tgn:id":2440287,
    "tgn:name":"Klocke Lake",
    "tgn:placetype":[
        "aat:300006191"
    ]
},
  "bbox": [],
  "geometry": {"coordinates":[-91.7167,39.9833],"type":"Point"}
}