{
  "id": 2635855,
  "type": "Feature",
  "properties": {
    "tgn:hierarchy":[
        "tgn:2635855",
        "tgn:1000001",
        "tgn:7012149",
        "tgn:7014097",
        "tgn:7007158",
        "tgn:7029392"
    ],
    "tgn:id":2635855,
    "tgn:name":"Sachett Mountain",
    "tgn:placetype":[
        "aat:300008798"
    ]
},
  "bbox": [],
  "geometry": {"coordinates":[-105.0167,38.8167],"type":"Point"}
}