{
  "id": 7204121,
  "type": "Feature",
  "properties": {
    "tgn:hierarchy":[
        "tgn:7204121",
        "tgn:1000003",
        "tgn:7003677",
        "tgn:7000084",
        "tgn:7029392"
    ],
    "tgn:id":7204121,
    "tgn:name":"B\u00f6rsting",
    "tgn:placetype":[
        "aat:300000206"
    ]
},
  "bbox": [],
  "geometry": {"coordinates":[7.283333,52.066667],"type":"Point"}
}