{
  "id": 1052178,
  "type": "Feature",
  "properties": {
    "tgn:hierarchy":[
        "tgn:1052178",
        "tgn:7012935",
        "tgn:1000004",
        "tgn:7014786",
        "tgn:7029392"
    ],
    "tgn:id":1052178,
    "tgn:name":"Anar",
    "tgn:placetype":[
        "aat:300008347"
    ]
},
  "bbox": [],
  "geometry": {"coordinates":[72.45,50.6333],"type":"Point"}
}