{
  "id": 4011920,
  "type": "Feature",
  "properties": {
    "tgn:hierarchy":[
        "tgn:4011920",
        "tgn:7018239",
        "tgn:1000003",
        "tgn:1000063",
        "tgn:7018236",
        "tgn:7029392"
    ],
    "tgn:id":4011920,
    "tgn:name":"Vlierbeek",
    "tgn:placetype":[
        "aat:300008347"
    ]
},
  "bbox": [],
  "geometry": {"coordinates":[4.483333,50.766667],"type":"Point"}
}