{
  "id": 2488985,
  "type": "Feature",
  "properties": {
    "tgn:hierarchy":[
        "tgn:2488985",
        "tgn:1000001",
        "tgn:7012149",
        "tgn:7007157",
        "tgn:1002828",
        "tgn:7029392"
    ],
    "tgn:id":2488985,
    "tgn:name":"Main Street Canyon",
    "tgn:placetype":[
        "aat:300008761"
    ]
},
  "bbox": [],
  "geometry": {"coordinates":[-117.5833,33.7833],"type":"Point"}
}