{
  "id": 7441441,
  "type": "Feature",
  "properties": {
    "tgn:hierarchy":[
        "tgn:7441441",
        "tgn:7005586",
        "tgn:1000001",
        "tgn:7005560",
        "tgn:7029392"
    ],
    "tgn:id":7441441,
    "tgn:name":"San Nicol\u00e1s de los Abundis",
    "tgn:placetype":[
        "aat:300008347"
    ]
},
  "bbox": [],
  "geometry": {"coordinates":[-103.216667,20.916667],"type":"Point"}
}