{
  "id": 7567458,
  "type": "Feature",
  "properties": {
    "tgn:hierarchy":[
        "tgn:7567458",
        "tgn:1001828",
        "tgn:1000004",
        "tgn:7000198",
        "tgn:7029392"
    ],
    "tgn:id":7567458,
    "tgn:name:en":"Nallapalli",
    "tgn:placetype":[
        "aat:300008347"
    ]
},
  "bbox": [],
  "geometry": {"coordinates":[78.358889,17.720833],"type":"Point"}
}