{
  "id": 7552488,
  "type": "Feature",
  "properties": {
    "tgn:hierarchy":[
        "tgn:7552488",
        "tgn:1000004",
        "tgn:7000198",
        "tgn:1001894",
        "tgn:7029392"
    ],
    "tgn:id":7552488,
    "tgn:name:en":"Mot\u012bn\u0101la",
    "tgn:placetype":[
        "aat:300008347"
    ]
},
  "bbox": [],
  "geometry": {"coordinates":[80.898662,22.347942],"type":"Point"}
}