{
  "id": 7251583,
  "type": "Feature",
  "properties": {
    "tgn:hierarchy":[
        "tgn:7251583",
        "tgn:7003457",
        "tgn:1000003",
        "tgn:1000063",
        "tgn:7018236",
        "tgn:7029392"
    ],
    "tgn:id":7251583,
    "tgn:name":"Malekote",
    "tgn:placetype":[
        "aat:300008347"
    ]
},
  "bbox": [],
  "geometry": {"coordinates":[3.504022,51.197944],"type":"Point"}
}