{
  "id": 7574886,
  "type": "Feature",
  "properties": {
    "tgn:hierarchy":[
        "tgn:7574886",
        "tgn:1000004",
        "tgn:7000198",
        "tgn:7001797",
        "tgn:7029392"
    ],
    "tgn:id":7574886,
    "tgn:name:en":"Kodan\u0101d",
    "tgn:placetype":[
        "aat:300008347"
    ]
},
  "bbox": [],
  "geometry": {"coordinates":[76.916667,11.516667],"type":"Point"}
}