{
  "id": 7187647,
  "type": "Feature",
  "properties": {
    "tgn:hierarchy":[
        "tgn:7187647",
        "tgn:7003669",
        "tgn:1000003",
        "tgn:7000084",
        "tgn:7029392"
    ],
    "tgn:id":7187647,
    "tgn:name":"Erlenberg",
    "tgn:placetype":[
        "aat:300008347"
    ]
},
  "bbox": [],
  "geometry": {"coordinates":[10.383333,48.05],"type":"Point"}
}