{
  "id": 7419483,
  "type": "Feature",
  "properties": {
    "tgn:hierarchy":[
        "tgn:7419483",
        "tgn:7005579",
        "tgn:1000001",
        "tgn:7005560",
        "tgn:7029392"
    ],
    "tgn:id":7419483,
    "tgn:name":"Presa Natillas",
    "tgn:placetype":[
        "aat:300006191"
    ]
},
  "bbox": [],
  "geometry": {"coordinates":[-102.316667,22.366667],"type":"Point"}
}