{
  "id": 7368736,
  "type": "Feature",
  "properties": {
    "tgn:hierarchy":[
        "tgn:7368736",
        "tgn:1000001",
        "tgn:7005599",
        "tgn:7005560",
        "tgn:7029392"
    ],
    "tgn:id":7368736,
    "tgn:name":"Higueras, Arroyo",
    "tgn:placetype":[
        "aat:300008699"
    ]
},
  "bbox": [],
  "geometry": {"coordinates":[-96.533333,19.933333],"type":"Point"}
}