<<<<<<< HEAD
{
  "id": 2769870,
  "type": "Feature",
  "properties": {
    "tgn:hierarchy":[
        "tgn:2769870",
        "tgn:1000001",
        "tgn:7012149",
        "tgn:7007251",
        "tgn:7029392"
    ],
    "tgn:id":2769870,
    "tgn:name":"Wilborn Creek",
    "tgn:placetype":[
        "aat:300008706"
    ]
},
  "bbox": [],
  "geometry": {"coordinates":[-88.8833,39.6],"type":"Point"}
}
=======
{"geometry":{"type":"Point","coordinates":[-88.883300,39.600000]},"type":"Feature","properties":{"hierarchy":["tgn:2769870","tgn:1000001","tgn:7012149","tgn:7007251","tgn:7029392"],"placetype":["aat:300008706"],"id":2769870,"name:xx":"Wilborn Creek"}}
>>>>>>> 03f74aca74312dbeaf24d7e61306dd6a786dc3d0
