<<<<<<< HEAD
{
  "id": 7177519,
  "type": "Feature",
  "properties": {
    "tgn:hierarchy":[
        "tgn:7177519",
        "tgn:1000003",
        "tgn:7000094",
        "tgn:7000084",
        "tgn:7029392"
    ],
    "tgn:id":7177519,
    "tgn:name":"Hanstein-Berg",
    "tgn:placetype":[
        "aat:300008777"
    ]
},
  "bbox": [],
  "geometry": {"coordinates":[10.883333,53.45],"type":"Point"}
}
=======
{"geometry":{"type":"Point","coordinates":[10.883333,53.450000]},"type":"Feature","properties":{"hierarchy":["tgn:7177519","tgn:1000003","tgn:7000094","tgn:7000084","tgn:7029392"],"placetype":["aat:300008777"],"id":7177519,"name:xx":"Hanstein-Berg"}}
>>>>>>> 03f74aca74312dbeaf24d7e61306dd6a786dc3d0
