{
  "id": 2649659,
  "type": "Feature",
  "properties": {
    "tgn:hierarchy":[
        "tgn:2649659",
        "tgn:7006450",
        "tgn:1000001",
        "tgn:7012149",
        "tgn:2000082",
        "tgn:7029392"
    ],
    "tgn:id":2649659,
    "tgn:name":"Scow Island",
    "tgn:placetype":[
        "aat:300008791"
    ]
},
  "bbox": [],
  "geometry": {"coordinates":[-133.3333,55.95],"type":"Point"}
}