{
  "id": 7557435,
  "type": "Feature",
  "properties": {
    "tgn:hierarchy":[
        "tgn:7557435",
        "tgn:1000004",
        "tgn:7000198",
        "tgn:7000799",
        "tgn:7029392"
    ],
    "tgn:id":7557435,
    "tgn:name:en":"Ranbirpura",
    "tgn:placetype":[
        "aat:300008347"
    ]
},
  "bbox": [],
  "geometry": {"coordinates":[77.678681,34.037319],"type":"Point"}
}