{
  "id": 2433395,
  "type": "Feature",
  "properties": {
    "tgn:hierarchy":[
        "tgn:2433395",
        "tgn:1000001",
        "tgn:7012149",
        "tgn:2001894",
        "tgn:7007825",
        "tgn:7029392"
    ],
    "tgn:id":2433395,
    "tgn:name":"Kelley Ridge",
    "tgn:placetype":[
        "aat:300266640"
    ]
},
  "bbox": [],
  "geometry": {"coordinates":[-85.5667,35.25],"type":"Point"}
}