{
  "id": 2586899,
  "type": "Feature",
  "properties": {
    "tgn:hierarchy":[
        "tgn:2586899",
        "tgn:1000001",
        "tgn:7012149",
        "tgn:2001188",
        "tgn:7007523",
        "tgn:7029392"
    ],
    "tgn:id":2586899,
    "tgn:name":"Plainview",
    "tgn:placetype":[
        "aat:300008347"
    ]
},
  "bbox": [],
  "geometry": {"coordinates":[-94.2333,39.5833],"type":"Point"}
}