{
  "id": 2207860,
  "type": "Feature",
  "properties": {
    "tgn:hierarchy":[
        "tgn:2207860",
        "tgn:1000001",
        "tgn:7012149",
        "tgn:2000850",
        "tgn:7007255",
        "tgn:7029392"
    ],
    "tgn:id":2207860,
    "tgn:name":"Burgess Hollow",
    "tgn:placetype":[
        "aat:300008761"
    ]
},
  "bbox": [],
  "geometry": {"coordinates":[-84.8333,36.7667],"type":"Point"}
}