{
  "id": 2340160,
  "type": "Feature",
  "properties": {
    "tgn:hierarchy":[
        "tgn:2340160",
        "tgn:1000001",
        "tgn:7014352",
        "tgn:7012149",
        "tgn:7007564",
        "tgn:7029392"
    ],
    "tgn:id":2340160,
    "tgn:name":"Fremont Station",
    "tgn:placetype":[
        "aat:300008347"
    ]
},
  "bbox": [],
  "geometry": {"coordinates":[-71.1167,42.9667],"type":"Point"}
}