<<<<<<< HEAD
{
  "id": 2768933,
  "type": "Feature",
  "properties": {
    "tgn:hierarchy":[
        "tgn:2768933",
        "tgn:1000001",
        "tgn:7012149",
        "tgn:2000183",
        "tgn:7007157",
        "tgn:7029392"
    ],
    "tgn:id":2768933,
    "tgn:name":"Whitney Portal",
    "tgn:placetype":[
        "aat:300008347"
    ]
},
  "bbox": [],
  "geometry": {"coordinates":[-118.2167,36.5833],"type":"Point"}
}
=======
{"geometry":{"type":"Point","coordinates":[-118.216700,36.583300]},"type":"Feature","properties":{"hierarchy":["tgn:2768933","tgn:1000001","tgn:7012149","tgn:2000183","tgn:7007157","tgn:7029392"],"placetype":["aat:300008347"],"id":2768933,"name:xx":"Whitney Portal"}}
>>>>>>> 03f74aca74312dbeaf24d7e61306dd6a786dc3d0
