{
  "id": 2724181,
  "type": "Feature",
  "properties": {
    "tgn:hierarchy":[
        "tgn:2724181",
        "tgn:1000001",
        "tgn:7012149",
        "tgn:1002592",
        "tgn:7007523",
        "tgn:7029392"
    ],
    "tgn:id":2724181,
    "tgn:name":"Tom Branch",
    "tgn:placetype":[
        "aat:300008699"
    ]
},
  "bbox": [],
  "geometry": {"coordinates":[-91.7667,40.2167],"type":"Point"}
}