{
  "id": 7279621,
  "type": "Feature",
  "properties": {
    "tgn:hierarchy":[
        "tgn:7279621",
        "tgn:1001702",
        "tgn:1000049",
        "tgn:1000002",
        "tgn:7029392"
    ],
    "tgn:id":7279621,
    "tgn:name":"Reparo, Isla",
    "tgn:placetype":[
        "aat:300008791"
    ]
},
  "bbox": [],
  "geometry": {"coordinates":[-66.816667,-55.033333],"type":"Point"}
}