{
  "id": 2243276,
  "type": "Feature",
  "properties": {
    "tgn:hierarchy":[
        "tgn:2243276",
        "tgn:1000001",
        "tgn:1002278",
        "tgn:7012149",
        "tgn:7007710",
        "tgn:7029392"
    ],
    "tgn:id":2243276,
    "tgn:name":"Clear Run",
    "tgn:placetype":[
        "aat:300008699"
    ]
},
  "bbox": [],
  "geometry": {"coordinates":[-78.75,41.15],"type":"Point"}
}