{
  "id": 7082457,
  "type": "Feature",
  "properties": {
    "tgn:hierarchy":[
        "tgn:7082457",
        "tgn:7003692",
        "tgn:1000003",
        "tgn:7000084",
        "tgn:7029392"
    ],
    "tgn:id":7082457,
    "tgn:name":"Wimbach",
    "tgn:placetype":[
        "aat:300000206"
    ]
},
  "bbox": [],
  "geometry": {"coordinates":[9.85,48.933333],"type":"Point"}
}