{
  "id": 7237120,
  "type": "Feature",
  "properties": {
    "tgn:hierarchy":[
        "tgn:7237120",
        "tgn:7011170",
        "tgn:7002715",
        "tgn:1000003",
        "tgn:1000074",
        "tgn:7029392"
    ],
    "tgn:id":7237120,
    "tgn:name":"Er\u00edpia Andil\u00e1lou",
    "tgn:placetype":[
        "aat:300008057"
    ]
},
  "bbox": [],
  "geometry": {"coordinates":[24.25,41.516667],"type":"Point"}
}