{
  "id": 2547230,
  "type": "Feature",
  "properties": {
    "tgn:hierarchy":[
        "tgn:2547230",
        "tgn:1000001",
        "tgn:7012149",
        "tgn:7007826",
        "tgn:7029392"
    ],
    "tgn:id":2547230,
    "tgn:name":"North Fork Running Water Draw",
    "tgn:placetype":[
        "aat:300008761"
    ]
},
  "bbox": [],
  "geometry": {"coordinates":[-102.4833,34.4833],"type":"Point"}
}