{
  "id": 7478176,
  "type": "Feature",
  "properties": {
    "tgn:hierarchy":[
        "tgn:7478176",
        "tgn:1000004",
        "tgn:7001014",
        "tgn:1000141",
        "tgn:7029392"
    ],
    "tgn:id":7478176,
    "tgn:name":"Xingbei",
    "tgn:placetype":[
        "aat:300008347"
    ]
},
  "bbox": [],
  "geometry": {"coordinates":[120.520667,23.775636],"type":"Point"}
}