{
  "id": 2701339,
  "type": "Feature",
  "properties": {
    "tgn:hierarchy":[
        "tgn:2701339",
        "tgn:1000001",
        "tgn:7016172",
        "tgn:2000112",
        "tgn:7012149",
        "tgn:7029392"
    ],
    "tgn:id":2701339,
    "tgn:name":"Sugar Mountain",
    "tgn:placetype":[
        "aat:300008798"
    ]
},
  "bbox": [],
  "geometry": {"coordinates":[-93.7833,36.3833],"type":"Point"}
}