<<<<<<< HEAD
{
  "id": 7359235,
  "type": "Feature",
  "properties": {
    "tgn:hierarchy":[
        "tgn:7359235",
        "tgn:1000001",
        "tgn:7005590",
        "tgn:7005560",
        "tgn:7029392"
    ],
    "tgn:id":7359235,
    "tgn:name":"Divisi\u00f3n del Norte",
    "tgn:placetype":[
        "aat:300008347"
    ]
},
  "bbox": [],
  "geometry": {"coordinates":[-102.6,19.066667],"type":"Point"}
}
=======
{"geometry":{"type":"Point","coordinates":[-102.600000,19.066667]},"type":"Feature","properties":{"hierarchy":["tgn:7359235","tgn:1000001","tgn:7005590","tgn:7005560","tgn:7029392"],"placetype":["aat:300008347"],"id":7359235,"name:xx":"Divisi\u00f3n del Norte"}}
>>>>>>> 03f74aca74312dbeaf24d7e61306dd6a786dc3d0
