{
  "id": 7452499,
  "type": "Feature",
  "properties": {
    "tgn:hierarchy":[
        "tgn:7452499",
        "tgn:7002445",
        "tgn:7011980",
        "tgn:1000003",
        "tgn:7008591",
        "tgn:7029392"
    ],
    "tgn:id":7452499,
    "tgn:name:en":"Haslingfield",
    "tgn:placetype":[
        "aat:300008347"
    ]
},
  "bbox": [],
  "geometry": {"coordinates":[0.066667,52.15],"type":"Point"}
}