{
  "id": 7320587,
  "type": "Feature",
  "properties": {
    "tgn:hierarchy":[
        "tgn:7320587",
        "tgn:7002464",
        "tgn:1000049",
        "tgn:1000002",
        "tgn:7029392"
    ],
    "tgn:id":7320587,
    "tgn:name":"Caballuno",
    "tgn:placetype":[
        "aat:300008057"
    ]
},
  "bbox": [],
  "geometry": {"coordinates":[-68.85,-20.683333],"type":"Point"}
}