{
  "id": 2683070,
  "type": "Feature",
  "properties": {
    "tgn:hierarchy":[
        "tgn:2683070",
        "tgn:1000001",
        "tgn:7012149",
        "tgn:2001221",
        "tgn:7007523",
        "tgn:7029392"
    ],
    "tgn:id":2683070,
    "tgn:name":"Spangler Hollow",
    "tgn:placetype":[
        "aat:300008761"
    ]
},
  "bbox": [],
  "geometry": {"coordinates":[-92.95,38.3167],"type":"Point"}
}