{
  "id": 2738761,
  "type": "Feature",
  "properties": {
    "tgn:hierarchy":[
        "tgn:2738761",
        "tgn:1000001",
        "tgn:7012149",
        "tgn:2000476",
        "tgn:7007250",
        "tgn:7029392"
    ],
    "tgn:id":2738761,
    "tgn:name":"Union Group Mines",
    "tgn:placetype":[
        "aat:300000390"
    ]
},
  "bbox": [],
  "geometry": {"coordinates":[-115.5333,45.55],"type":"Point"}
}