<<<<<<< HEAD
{
  "id": 2152033,
  "type": "Feature",
  "properties": {
    "tgn:hierarchy":[
        "tgn:2152033",
        "tgn:1000001",
        "tgn:7012149",
        "tgn:2001456",
        "tgn:7007566",
        "tgn:7029392"
    ],
    "tgn:id":2152033,
    "tgn:name":"Baumgardner Tank",
    "tgn:placetype":[
        "aat:300006191"
    ]
},
  "bbox": [],
  "geometry": {"coordinates":[-106.4167,34.1333],"type":"Point"}
}
=======
{"geometry":{"type":"Point","coordinates":[-106.416700,34.133300]},"type":"Feature","properties":{"hierarchy":["tgn:2152033","tgn:1000001","tgn:7012149","tgn:2001456","tgn:7007566","tgn:7029392"],"placetype":["aat:300006191"],"id":2152033,"name:xx":"Baumgardner Tank"}}
>>>>>>> 03f74aca74312dbeaf24d7e61306dd6a786dc3d0
