{
  "id": 7506466,
  "type": "Feature",
  "properties": {
    "tgn:hierarchy":[
        "tgn:7506466",
        "tgn:1008380",
        "tgn:1000226",
        "tgn:7016827",
        "tgn:1000006",
        "tgn:7029392"
    ],
    "tgn:id":7506466,
    "tgn:name:en":"Rotokahu",
    "tgn:placetype":[
        "aat:300008680"
    ]
},
  "bbox": [],
  "geometry": {"coordinates":[174.783333,-39.516667],"type":"Point"}
}