{
  "id": 2216867,
  "type": "Feature",
  "properties": {
    "tgn:hierarchy":[
        "tgn:2216867",
        "tgn:1000001",
        "tgn:7012149",
        "tgn:2002187",
        "tgn:7007919",
        "tgn:7029392"
    ],
    "tgn:id":2216867,
    "tgn:name":"Camp Hollow",
    "tgn:placetype":[
        "aat:300008761"
    ]
},
  "bbox": [],
  "geometry": {"coordinates":[-78.9667,38.7167],"type":"Point"}
}