{
  "id": 1068753,
  "type": "Feature",
  "properties": {
    "tgn:hierarchy":[
        "tgn:1068753",
        "tgn:1000004",
        "tgn:7002078",
        "tgn:1000111",
        "tgn:7029392"
    ],
    "tgn:id":1068753,
    "tgn:name":"Hiaohexi",
    "tgn:placetype":[
        "aat:300008347"
    ]
},
  "bbox": [],
  "geometry": {"coordinates":[114.0333,31.35],"type":"Point"}
}