{
  "id": 7551519,
  "type": "Feature",
  "properties": {
    "tgn:hierarchy":[
        "tgn:7551519",
        "tgn:1000004",
        "tgn:7000198",
        "tgn:7016883",
        "tgn:7029392"
    ],
    "tgn:id":7551519,
    "tgn:name:en":"Dog\u0101l",
    "tgn:placetype":[
        "aat:300008347"
    ]
},
  "bbox": [],
  "geometry": {"coordinates":[76.036284,29.988217],"type":"Point"}
}