{
  "id": 7501008,
  "type": "Feature",
  "properties": {
    "tgn:hierarchy":[
        "tgn:7501008",
        "tgn:1000004",
        "tgn:7467799",
        "tgn:1000141",
        "tgn:7029392"
    ],
    "tgn:id":7501008,
    "tgn:name":"Haibu",
    "tgn:placetype":[
        "aat:300008347"
    ]
},
  "bbox": [],
  "geometry": {"coordinates":[120.444444,24.085556],"type":"Point"}
}