{
  "id": 1065401,
  "type": "Feature",
  "properties": {
    "tgn:hierarchy":[
        "tgn:1065401",
        "tgn:7016612",
        "tgn:1000004",
        "tgn:1001561",
        "tgn:7029392"
    ],
    "tgn:id":1065401,
    "tgn:name":"Chahar Bagh",
    "tgn:placetype":[
        "aat:300008347"
    ]
},
  "bbox": [],
  "geometry": {"coordinates":[69.6333,35.95],"type":"Point"}
}