<<<<<<< HEAD
{
  "id": 2760409,
  "type": "Feature",
  "properties": {
    "tgn:hierarchy":[
        "tgn:2760409",
        "tgn:1000001",
        "tgn:7012149",
        "tgn:7007923",
        "tgn:7029392"
    ],
    "tgn:id":2760409,
    "tgn:name":"West Fork South Tongue River",
    "tgn:placetype":[
        "aat:300008707"
    ]
},
  "bbox": [],
  "geometry": {"coordinates":[-107.4333,44.6],"type":"Point"}
}
=======
{"geometry":{"type":"Point","coordinates":[-107.433300,44.600000]},"type":"Feature","properties":{"hierarchy":["tgn:2760409","tgn:1000001","tgn:7012149","tgn:7007923","tgn:7029392"],"placetype":["aat:300008707"],"id":2760409,"name:xx":"West Fork South Tongue River"}}
>>>>>>> 03f74aca74312dbeaf24d7e61306dd6a786dc3d0
