{
  "id": 2543957,
  "type": "Feature",
  "properties": {
    "tgn:hierarchy":[
        "tgn:2543957",
        "tgn:1000001",
        "tgn:7012149",
        "tgn:7007520",
        "tgn:7029392"
    ],
    "tgn:id":2543957,
    "tgn:name":"North Branch Carp River",
    "tgn:placetype":[
        "aat:300008707"
    ]
},
  "bbox": [],
  "geometry": {"coordinates":[-84.8833,46.15],"type":"Point"}
}