{
  "id": 2274464,
  "type": "Feature",
  "properties": {
    "tgn:hierarchy":[
        "tgn:2274464",
        "tgn:1000001",
        "tgn:7012149",
        "tgn:7007157",
        "tgn:2000191",
        "tgn:7029392"
    ],
    "tgn:id":2274464,
    "tgn:name":"Daley Gulch",
    "tgn:placetype":[
        "aat:300008761"
    ]
},
  "bbox": [],
  "geometry": {"coordinates":[-122.8833,41.15],"type":"Point"}
}