<<<<<<< HEAD
{
  "id": 7375377,
  "type": "Feature",
  "properties": {
    "tgn:hierarchy":[
        "tgn:7375377",
        "tgn:1000001",
        "tgn:1001960",
        "tgn:7005560",
        "tgn:7029392"
    ],
    "tgn:id":7375377,
    "tgn:name":"Rancho La Sepultura",
    "tgn:placetype":[
        "aat:300000241"
    ]
},
  "bbox": [],
  "geometry": {"coordinates":[-109.966667,27.983333],"type":"Point"}
}
=======
{"geometry":{"type":"Point","coordinates":[-109.966667,27.983333]},"type":"Feature","properties":{"hierarchy":["tgn:7375377","tgn:1000001","tgn:1001960","tgn:7005560","tgn:7029392"],"placetype":["aat:300000241"],"id":7375377,"name:xx":"Rancho La Sepultura"}}
>>>>>>> 03f74aca74312dbeaf24d7e61306dd6a786dc3d0
