{
  "id": 1135958,
  "type": "Feature",
  "properties": {
    "tgn:hierarchy":[
        "tgn:1135958",
        "tgn:1000385",
        "tgn:1000003",
        "tgn:7006278",
        "tgn:7029392"
    ],
    "tgn:id":1135958,
    "tgn:name":"Keleti-f\u0151csatorna",
    "tgn:placetype":[
        "aat:300006075"
    ]
},
  "bbox": [],
  "geometry": {"coordinates":[21.3333,48.0167],"type":"Point"}
}