{
  "id": 7321214,
  "type": "Feature",
  "properties": {
    "tgn:hierarchy":[
        "tgn:7321214",
        "tgn:1001623",
        "tgn:1000049",
        "tgn:1000002",
        "tgn:7029392"
    ],
    "tgn:id":7321214,
    "tgn:name":"Campamento, Caleta",
    "tgn:placetype":[
        "aat:300132317"
    ]
},
  "bbox": [],
  "geometry": {"coordinates":[-74.216667,-45.683333],"type":"Point"}
}