{
  "id": 7529193,
  "type": "Feature",
  "properties": {
    "tgn:hierarchy":[
        "tgn:7529193",
        "tgn:7001242",
        "tgn:7016833",
        "tgn:1001113",
        "tgn:7029392"
    ],
    "tgn:id":7529193,
    "tgn:name":"Tur'at a\u0163 \u0162arr\u0101d\u012byah",
    "tgn:placetype":[
        "aat:300006075"
    ]
},
  "bbox": [],
  "geometry": {"coordinates":[31.592151,30.713984],"type":"Point"}
}