{
  "id": 2286562,
  "type": "Feature",
  "properties": {
    "tgn:hierarchy":[
        "tgn:2286562",
        "tgn:1000001",
        "tgn:7012149",
        "tgn:2001160",
        "tgn:7007522",
        "tgn:7029392"
    ],
    "tgn:id":2286562,
    "tgn:name":"Diamond Island",
    "tgn:placetype":[
        "aat:300055621"
    ]
},
  "bbox": [],
  "geometry": {"coordinates":[-91.0333,32.2333],"type":"Point"}
}