{
  "id": 2607922,
  "type": "Feature",
  "properties": {
    "tgn:hierarchy":[
        "tgn:2607922",
        "tgn:1000001",
        "tgn:7012149",
        "tgn:7007827",
        "tgn:7029392"
    ],
    "tgn:id":2607922,
    "tgn:name":"Rat Seep Hollow",
    "tgn:placetype":[
        "aat:300008761"
    ]
},
  "bbox": [],
  "geometry": {"coordinates":[-111.35,37.4833],"type":"Point"}
}