{
  "id": 2398796,
  "type": "Feature",
  "properties": {
    "tgn:hierarchy":[
        "tgn:2398796",
        "tgn:1000001",
        "tgn:7012149",
        "tgn:2001711",
        "tgn:7007708",
        "tgn:7029392"
    ],
    "tgn:id":2398796,
    "tgn:name":"Hope Spring",
    "tgn:placetype":[
        "aat:300008697"
    ]
},
  "bbox": [],
  "geometry": {"coordinates":[-122.7667,42.1667],"type":"Point"}
}