{
  "id": 2196929,
  "type": "Feature",
  "properties": {
    "tgn:hierarchy":[
        "tgn:2196929",
        "tgn:1000001",
        "tgn:2001179",
        "tgn:7012149",
        "tgn:7007523",
        "tgn:7029392"
    ],
    "tgn:id":2196929,
    "tgn:name":"Brookside",
    "tgn:placetype":[
        "aat:300008347"
    ]
},
  "bbox": [],
  "geometry": {"coordinates":[-89.6833,37.45],"type":"Point"}
}