{
  "id": 7231127,
  "type": "Feature",
  "properties": {
    "tgn:hierarchy":[
        "tgn:7231127",
        "tgn:7011330",
        "tgn:7002674",
        "tgn:1000003",
        "tgn:1000074",
        "tgn:7029392"
    ],
    "tgn:id":7231127,
    "tgn:name":"Maratho\u00fanda, \u00d3rmos",
    "tgn:placetype":[
        "aat:300132316"
    ]
},
  "bbox": [],
  "geometry": {"coordinates":[27.916667,36.566667],"type":"Point"}
}