{
  "id": 7109072,
  "type": "Feature",
  "properties": {
    "tgn:hierarchy":[
        "tgn:7109072",
        "tgn:7003669",
        "tgn:1000003",
        "tgn:7000084",
        "tgn:7029392"
    ],
    "tgn:id":7109072,
    "tgn:name":"Reisat",
    "tgn:placetype":[
        "aat:300008347"
    ]
},
  "bbox": [],
  "geometry": {"coordinates":[12.866667,48.566667],"type":"Point"}
}