{
  "id": 7264307,
  "type": "Feature",
  "properties": {
    "tgn:concordances":{
        "gn:id":"2753046"
    },
    "tgn:hierarchy":[
        "tgn:7264307",
        "tgn:1000003",
        "tgn:7003622",
        "tgn:7016845",
        "tgn:7029392"
    ],
    "tgn:id":7264307,
    "tgn:name:nl":"Kastert",
    "tgn:placetype":[
        "aat:300008347"
    ]
},
  "bbox": [],
  "geometry": {"coordinates":[5.75,51.216667],"type":"Point"}
}