{
  "id": 7221537,
  "type": "Feature",
  "properties": {
    "tgn:hierarchy":[
        "tgn:7221537",
        "tgn:7002711",
        "tgn:7001338",
        "tgn:1000003",
        "tgn:1000074",
        "tgn:7029392"
    ],
    "tgn:id":7221537,
    "tgn:name":"Orth\u00f3lithos, \u00c1kra",
    "tgn:placetype":[
        "aat:300008850"
    ]
},
  "bbox": [],
  "geometry": {"coordinates":[20.148333,39.197222],"type":"Point"}
}