{
  "id": 2283667,
  "type": "Feature",
  "properties": {
    "tgn:hierarchy":[
        "tgn:2283667",
        "tgn:1000001",
        "tgn:2000469",
        "tgn:7012149",
        "tgn:7007250",
        "tgn:7029392"
    ],
    "tgn:id":2283667,
    "tgn:name":"Democrat Mine",
    "tgn:placetype":[
        "aat:300000390"
    ]
},
  "bbox": [],
  "geometry": {"coordinates":[-115.9333,46.5667],"type":"Point"}
}