{
  "id": 7100133,
  "type": "Feature",
  "properties": {
    "tgn:hierarchy":[
        "tgn:7100133",
        "tgn:1000003",
        "tgn:7003682",
        "tgn:7000084",
        "tgn:7029392"
    ],
    "tgn:id":7100133,
    "tgn:name":"R\u00fcbenach",
    "tgn:placetype":[
        "aat:300008347"
    ]
},
  "bbox": [],
  "geometry": {"coordinates":[7.516667,50.366667],"type":"Point"}
}