{
  "id": 7191883,
  "type": "Feature",
  "properties": {
    "tgn:hierarchy":[
        "tgn:7191883",
        "tgn:1000003",
        "tgn:7003676",
        "tgn:7000084",
        "tgn:7029392"
    ],
    "tgn:id":7191883,
    "tgn:name":"Falster",
    "tgn:placetype":[
        "aat:300000206"
    ]
},
  "bbox": [],
  "geometry": {"coordinates":[7.683333,53.616667],"type":"Point"}
}