{
  "id": 7284955,
  "type": "Feature",
  "properties": {
    "tgn:hierarchy":[
        "tgn:7284955",
        "tgn:1001623",
        "tgn:1000049",
        "tgn:1000002",
        "tgn:7029392"
    ],
    "tgn:id":7284955,
    "tgn:name":"Piedras, Punta",
    "tgn:placetype":[
        "aat:300386846"
    ]
},
  "bbox": [],
  "geometry": {"coordinates":[-75.05,-44.816667],"type":"Point"}
}