{
  "id": 2644431,
  "type": "Feature",
  "properties": {
    "tgn:hierarchy":[
        "tgn:2644431",
        "tgn:1000001",
        "tgn:7012149",
        "tgn:2001456",
        "tgn:7007566",
        "tgn:7029392"
    ],
    "tgn:id":2644431,
    "tgn:name":"Saracino Lateral",
    "tgn:placetype":[
        "aat:300006075"
    ]
},
  "bbox": [],
  "geometry": {"coordinates":[-106.8833,34.1667],"type":"Point"}
}