{
  "id": 2283357,
  "type": "Feature",
  "properties": {
    "tgn:hierarchy":[
        "tgn:2283357",
        "tgn:1000001",
        "tgn:7012149",
        "tgn:2000960",
        "tgn:7007520",
        "tgn:7029392"
    ],
    "tgn:id":2283357,
    "tgn:name":"Dellies Lake",
    "tgn:placetype":[
        "aat:300008680"
    ]
},
  "bbox": [],
  "geometry": {"coordinates":[-89.1333,46.2333],"type":"Point"}
}