{
  "id": 7316438,
  "type": "Feature",
  "properties": {
    "tgn:hierarchy":[
        "tgn:7316438",
        "tgn:7016598",
        "tgn:1000049",
        "tgn:1000002",
        "tgn:7029392"
    ],
    "tgn:id":7316438,
    "tgn:name":"Carcote, Cerro",
    "tgn:placetype":[
        "aat:300008777"
    ]
},
  "bbox": [],
  "geometry": {"coordinates":[-68.383333,-21.433333],"type":"Point"}
}