{
  "id": 2366892,
  "type": "Feature",
  "properties": {
    "tgn:hierarchy":[
        "tgn:2366892",
        "tgn:1000001",
        "tgn:2000951",
        "tgn:7012149",
        "tgn:7007520",
        "tgn:7029392"
    ],
    "tgn:id":2366892,
    "tgn:name":"Griswold Mountain",
    "tgn:placetype":[
        "aat:300008798"
    ]
},
  "bbox": [],
  "geometry": {"coordinates":[-84.6167,45.4333],"type":"Point"}
}