{
  "id": 7423447,
  "type": "Feature",
  "properties": {
    "tgn:hierarchy":[
        "tgn:7423447",
        "tgn:1000001",
        "tgn:7005601",
        "tgn:7005560",
        "tgn:7029392"
    ],
    "tgn:id":7423447,
    "tgn:name":"Los Pocitos",
    "tgn:placetype":[
        "aat:300008347"
    ]
},
  "bbox": [],
  "geometry": {"coordinates":[-102.833333,22.116667],"type":"Point"}
}