{
  "id": 2518355,
  "type": "Feature",
  "properties": {
    "tgn:hierarchy":[
        "tgn:2518355",
        "tgn:1000001",
        "tgn:2001267",
        "tgn:7012149",
        "tgn:7007524",
        "tgn:7029392"
    ],
    "tgn:id":2518355,
    "tgn:name":"Mistiguenou Ridge",
    "tgn:placetype":[
        "aat:300266640"
    ]
},
  "bbox": [],
  "geometry": {"coordinates":[-109.75,48.1833],"type":"Point"}
}