{
  "id": 2753481,
  "type": "Feature",
  "properties": {
    "tgn:hierarchy":[
        "tgn:2753481",
        "tgn:1000001",
        "tgn:7012149",
        "tgn:1002525",
        "tgn:7007252",
        "tgn:7029392"
    ],
    "tgn:id":2753481,
    "tgn:name":"Waterloo Run",
    "tgn:placetype":[
        "aat:300008699"
    ]
},
  "bbox": [],
  "geometry": {"coordinates":[-86.1833,39.55],"type":"Point"}
}