{
  "id": 1038577,
  "type": "Feature",
  "properties": {
    "tgn:hierarchy":[
        "tgn:1038577",
        "tgn:1000003",
        "tgn:7003676",
        "tgn:7000084",
        "tgn:7029392"
    ],
    "tgn:id":1038577,
    "tgn:name":"Bodenteich",
    "tgn:placetype":[
        "aat:300008347"
    ]
},
  "bbox": [],
  "geometry": {"coordinates":[10.683333,52.833333],"type":"Point"}
}