{
  "id": 7468207,
  "type": "Feature",
  "properties": {
    "tgn:hierarchy":[
        "tgn:7468207",
        "tgn:1000004",
        "tgn:7492971",
        "tgn:1000141",
        "tgn:7029392"
    ],
    "tgn:id":7468207,
    "tgn:name":"Jiadong",
    "tgn:placetype":[
        "aat:300008347"
    ]
},
  "bbox": [],
  "geometry": {"coordinates":[120.549444,22.417778],"type":"Point"}
}