{
  "id": 7436619,
  "type": "Feature",
  "properties": {
    "tgn:hierarchy":[
        "tgn:7436619",
        "tgn:1000001",
        "tgn:1001906",
        "tgn:7005560",
        "tgn:7029392"
    ],
    "tgn:id":7436619,
    "tgn:name":"Tequepexpan",
    "tgn:placetype":[
        "aat:300008347"
    ]
},
  "bbox": [],
  "geometry": {"coordinates":[-104.566667,21.216667],"type":"Point"}
}