{
  "id": 7552274,
  "type": "Feature",
  "properties": {
    "tgn:hierarchy":[
        "tgn:7552274",
        "tgn:1000004",
        "tgn:7000198",
        "tgn:7016883",
        "tgn:7029392"
    ],
    "tgn:id":7552274,
    "tgn:name:en":"Manhi\u0101la",
    "tgn:placetype":[
        "aat:300008347"
    ]
},
  "bbox": [],
  "geometry": {"coordinates":[74.54423,31.528771],"type":"Point"}
}