{
  "id": 2233019,
  "type": "Feature",
  "properties": {
    "tgn:hierarchy":[
        "tgn:2233019",
        "tgn:1000001",
        "tgn:7012149",
        "tgn:2002371",
        "tgn:7007923",
        "tgn:7029392"
    ],
    "tgn:id":2233019,
    "tgn:name":"Charcoal Spring",
    "tgn:placetype":[
        "aat:300008697"
    ]
},
  "bbox": [],
  "geometry": {"coordinates":[-108.95,42.8667],"type":"Point"}
}