{
  "id": 2729598,
  "type": "Feature",
  "properties": {
    "tgn:hierarchy":[
        "tgn:2729598",
        "tgn:1000001",
        "tgn:7012149",
        "tgn:7019015",
        "tgn:7007251",
        "tgn:7029392"
    ],
    "tgn:id":2729598,
    "tgn:name":"Troster",
    "tgn:placetype":[
        "aat:300008347"
    ]
},
  "bbox": [],
  "geometry": {"coordinates":[-88.4667,40.3167],"type":"Point"}
}