{
  "id": 7042842,
  "type": "Feature",
  "properties": {
    "tgn:hierarchy":[
        "tgn:7042842",
        "tgn:1003444",
        "tgn:1000003",
        "tgn:7003241",
        "tgn:1000080",
        "tgn:7029392"
    ],
    "tgn:id":7042842,
    "tgn:name":"Ripalimosano",
    "tgn:placetype":[
        "aat:300008347"
    ]
},
  "bbox": [],
  "geometry": {"coordinates":[14.666667,41.616667],"type":"Point"}
}