{
  "id": 2458431,
  "type": "Feature",
  "properties": {
    "tgn:hierarchy":[
        "tgn:2458431",
        "tgn:1000001",
        "tgn:7012149",
        "tgn:1002540",
        "tgn:7007520",
        "tgn:7029392"
    ],
    "tgn:id":2458431,
    "tgn:name":"Little Myers Lake",
    "tgn:placetype":[
        "aat:300008680"
    ]
},
  "bbox": [],
  "geometry": {"coordinates":[-85.4833,43.1333],"type":"Point"}
}