{
  "id": 2217463,
  "type": "Feature",
  "properties": {
    "tgn:hierarchy":[
        "tgn:2217463",
        "tgn:1000001",
        "tgn:7012149",
        "tgn:7007157",
        "tgn:7029392"
    ],
    "tgn:id":2217463,
    "tgn:name":"Campbell Creek",
    "tgn:placetype":[
        "aat:300008706"
    ]
},
  "bbox": [],
  "geometry": {"coordinates":[-121.6833,40.05],"type":"Point"}
}