{
  "id": 2371683,
  "type": "Feature",
  "properties": {
    "tgn:hierarchy":[
        "tgn:2371683",
        "tgn:1000001",
        "tgn:7012149",
        "tgn:2000806",
        "tgn:7007255",
        "tgn:7029392"
    ],
    "tgn:id":2371683,
    "tgn:name":"Hale Fork",
    "tgn:placetype":[
        "aat:300008699"
    ]
},
  "bbox": [],
  "geometry": {"coordinates":[-83.7667,36.9167],"type":"Point"}
}