<<<<<<< HEAD
{
  "id": 2405763,
  "type": "Feature",
  "properties": {
    "tgn:hierarchy":[
        "tgn:2405763",
        "tgn:1000001",
        "tgn:2002148",
        "tgn:7012149",
        "tgn:7007919",
        "tgn:7029392"
    ],
    "tgn:id":2405763,
    "tgn:name":"Hulen Branch",
    "tgn:placetype":[
        "aat:300008699"
    ]
},
  "bbox": [],
  "geometry": {"coordinates":[-81.9667,37.3667],"type":"Point"}
}
=======
{"geometry":{"type":"Point","coordinates":[-81.966700,37.366700]},"type":"Feature","properties":{"hierarchy":["tgn:2405763","tgn:1000001","tgn:2002148","tgn:7012149","tgn:7007919","tgn:7029392"],"placetype":["aat:300008699"],"id":2405763,"name:xx":"Hulen Branch"}}
>>>>>>> 03f74aca74312dbeaf24d7e61306dd6a786dc3d0
