{
  "id": 7348836,
  "type": "Feature",
  "properties": {
    "tgn:hierarchy":[
        "tgn:7348836",
        "tgn:1000001",
        "tgn:7005595",
        "tgn:7005560",
        "tgn:7029392"
    ],
    "tgn:id":7348836,
    "tgn:name":"Agua Caliente",
    "tgn:placetype":[
        "aat:300008347"
    ]
},
  "bbox": [],
  "geometry": {"coordinates":[-106.758333,24.641667],"type":"Point"}
}