{
  "id": 2549088,
  "type": "Feature",
  "properties": {
    "tgn:hierarchy":[
        "tgn:2549088",
        "tgn:1000001",
        "tgn:7012149",
        "tgn:2001532",
        "tgn:7007709",
        "tgn:7029392"
    ],
    "tgn:id":2549088,
    "tgn:name":"North Prong Richland Creek",
    "tgn:placetype":[
        "aat:300008706"
    ]
},
  "bbox": [],
  "geometry": {"coordinates":[-79.8167,35.6167],"type":"Point"}
}