<<<<<<< HEAD
{
  "id": 2761779,
  "type": "Feature",
  "properties": {
    "tgn:hierarchy":[
        "tgn:2761779",
        "tgn:1000001",
        "tgn:7012149",
        "tgn:2002087",
        "tgn:7007826",
        "tgn:7029392"
    ],
    "tgn:id":2761779,
    "tgn:name":"West Prong Flush Creek",
    "tgn:placetype":[
        "aat:300008706"
    ]
},
  "bbox": [],
  "geometry": {"coordinates":[-99.7833,29.6],"type":"Point"}
}
=======
{"geometry":{"type":"Point","coordinates":[-99.783300,29.600000]},"type":"Feature","properties":{"hierarchy":["tgn:2761779","tgn:1000001","tgn:7012149","tgn:2002087","tgn:7007826","tgn:7029392"],"placetype":["aat:300008706"],"id":2761779,"name:xx":"West Prong Flush Creek"}}
>>>>>>> 03f74aca74312dbeaf24d7e61306dd6a786dc3d0
