{
  "id": 2497745,
  "type": "Feature",
  "properties": {
    "tgn:hierarchy":[
        "tgn:2497745",
        "tgn:1000001",
        "tgn:7012149",
        "tgn:2001760",
        "tgn:7007712",
        "tgn:7029392"
    ],
    "tgn:id":2497745,
    "tgn:name":"Maybinton",
    "tgn:placetype":[
        "aat:300008347"
    ]
},
  "bbox": [],
  "geometry": {"coordinates":[-81.4667,34.45],"type":"Point"}
}