{
  "id": 1069791,
  "type": "Feature",
  "properties": {
    "tgn:hierarchy":[
        "tgn:1069791",
        "tgn:1000004",
        "tgn:7002081",
        "tgn:1000111",
        "tgn:7029392"
    ],
    "tgn:id":1069791,
    "tgn:name":"Lianyungang",
    "tgn:placetype":[
        "aat:300008347"
    ]
},
  "bbox": [],
  "geometry": {"coordinates":[119.4333,34.7333],"type":"Point"}
}