{
  "id": 7570128,
  "type": "Feature",
  "properties": {
    "tgn:hierarchy":[
        "tgn:7570128",
        "tgn:1000004",
        "tgn:7000198",
        "tgn:1001895",
        "tgn:7029392"
    ],
    "tgn:id":7570128,
    "tgn:name:en":"Vel\u0101s",
    "tgn:placetype":[
        "aat:300008347"
    ]
},
  "bbox": [],
  "geometry": {"coordinates":[72.989722,18.202778],"type":"Point"}
}