{
  "id": 2730736,
  "type": "Feature",
  "properties": {
    "tgn:hierarchy":[
        "tgn:2730736",
        "tgn:1000001",
        "tgn:7006451",
        "tgn:2000092",
        "tgn:7012149",
        "tgn:7029392"
    ],
    "tgn:id":2730736,
    "tgn:name":"Tse Tonte",
    "tgn:placetype":[
        "aat:300008798"
    ]
},
  "bbox": [],
  "geometry": {"coordinates":[-111.2333,36.9167],"type":"Point"}
}