{
  "id": 7355752,
  "type": "Feature",
  "properties": {
    "tgn:hierarchy":[
        "tgn:7355752",
        "tgn:7005581",
        "tgn:1000001",
        "tgn:7005560",
        "tgn:7029392"
    ],
    "tgn:id":7355752,
    "tgn:name":"Carabajal de Abajo",
    "tgn:placetype":[
        "aat:300008347"
    ]
},
  "bbox": [],
  "geometry": {"coordinates":[-107.033333,28.283333],"type":"Point"}
}