<<<<<<< HEAD
{
  "id": 2767290,
  "type": "Feature",
  "properties": {
    "tgn:hierarchy":[
        "tgn:2767290",
        "tgn:1000001",
        "tgn:2002133",
        "tgn:7012149",
        "tgn:7007828",
        "tgn:7029392"
    ],
    "tgn:id":2767290,
    "tgn:name":"White Rocks",
    "tgn:placetype":[
        "aat:300008798"
    ]
},
  "bbox": [],
  "geometry": {"coordinates":[-72.7167,44.5667],"type":"Point"}
}
=======
{"geometry":{"type":"Point","coordinates":[-72.716700,44.566700]},"type":"Feature","properties":{"hierarchy":["tgn:2767290","tgn:1000001","tgn:2002133","tgn:7012149","tgn:7007828","tgn:7029392"],"placetype":["aat:300008798"],"id":2767290,"name:xx":"White Rocks"}}
>>>>>>> 03f74aca74312dbeaf24d7e61306dd6a786dc3d0
