{
  "id": 2347521,
  "type": "Feature",
  "properties": {
    "tgn:hierarchy":[
        "tgn:2347521",
        "tgn:1000001",
        "tgn:7012149",
        "tgn:7007521",
        "tgn:7029392"
    ],
    "tgn:id":2347521,
    "tgn:name":"George Washington State Forest",
    "tgn:placetype":[
        "aat:300008863"
    ]
},
  "bbox": [],
  "geometry": {"coordinates":[-93.1833,47.6833],"type":"Point"}
}