{
  "id": 7037338,
  "type": "Feature",
  "properties": {
    "tgn:hierarchy":[
        "tgn:7037338",
        "tgn:7003166",
        "tgn:1000003",
        "tgn:7009760",
        "tgn:1000080",
        "tgn:7029392"
    ],
    "tgn:id":7037338,
    "tgn:name":"Usigliano",
    "tgn:placetype":[
        "aat:300008347"
    ]
},
  "bbox": [],
  "geometry": {"coordinates":[10.583333,43.55],"type":"Point"}
}