{
  "id": 1029862,
  "type": "Feature",
  "properties": {
    "tgn:hierarchy":[
        "tgn:1029862",
        "tgn:7002445",
        "tgn:7008114",
        "tgn:1000003",
        "tgn:7008591",
        "tgn:7029392"
    ],
    "tgn:id":1029862,
    "tgn:name:en":"Little Sutton",
    "tgn:placetype":[
        "aat:300008347"
    ]
},
  "bbox": [],
  "geometry": {"coordinates":[-2.95,53.283333],"type":"Point"}
}