{
  "id": 7077944,
  "type": "Feature",
  "properties": {
    "tgn:hierarchy":[
        "tgn:7077944",
        "tgn:1000003",
        "tgn:7003689",
        "tgn:7000084",
        "tgn:7029392"
    ],
    "tgn:id":7077944,
    "tgn:name":"Illeben",
    "tgn:placetype":[
        "aat:300008347"
    ]
},
  "bbox": [],
  "geometry": {"coordinates":[10.666667,51.066667],"type":"Point"}
}