{
  "id": 2294181,
  "type": "Feature",
  "properties": {
    "tgn:hierarchy":[
        "tgn:2294181",
        "tgn:2002365",
        "tgn:1000001",
        "tgn:7012149",
        "tgn:7007923",
        "tgn:7029392"
    ],
    "tgn:id":2294181,
    "tgn:name":"Dover Reservoir Number 2",
    "tgn:placetype":[
        "aat:300006191"
    ]
},
  "bbox": [],
  "geometry": {"coordinates":[-105.35,41.8667],"type":"Point"}
}