{
  "id": 2614439,
  "type": "Feature",
  "properties": {
    "tgn:hierarchy":[
        "tgn:2614439",
        "tgn:1000001",
        "tgn:7012149",
        "tgn:1002779",
        "tgn:7007710",
        "tgn:7029392"
    ],
    "tgn:id":2614439,
    "tgn:name":"Reiders Run",
    "tgn:placetype":[
        "aat:300008699"
    ]
},
  "bbox": [],
  "geometry": {"coordinates":[-77.15,40.5167],"type":"Point"}
}