{
  "id": 7410720,
  "type": "Feature",
  "properties": {
    "tgn:hierarchy":[
        "tgn:7410720",
        "tgn:1000001",
        "tgn:7005592",
        "tgn:7005560",
        "tgn:7029392"
    ],
    "tgn:id":7410720,
    "tgn:name":"La Guadalupe",
    "tgn:placetype":[
        "aat:300008347"
    ]
},
  "bbox": [],
  "geometry": {"coordinates":[-97.791667,20.738889],"type":"Point"}
}