{
  "id": 7275098,
  "type": "Feature",
  "properties": {
    "tgn:hierarchy":[
        "tgn:7275098",
        "tgn:7002464",
        "tgn:1000049",
        "tgn:1000002",
        "tgn:7029392"
    ],
    "tgn:id":7275098,
    "tgn:name":"Vinco, Cerro",
    "tgn:placetype":[
        "aat:300008795"
    ]
},
  "bbox": [],
  "geometry": {"coordinates":[-69.533333,-18.516667],"type":"Point"}
}