{
  "id": 2636081,
  "type": "Feature",
  "properties": {
    "tgn:hierarchy":[
        "tgn:2636081",
        "tgn:1000001",
        "tgn:7006451",
        "tgn:2000092",
        "tgn:7012149",
        "tgn:7029392"
    ],
    "tgn:id":2636081,
    "tgn:name":"Saddle Horse Tank",
    "tgn:placetype":[
        "aat:300006191"
    ]
},
  "bbox": [],
  "geometry": {"coordinates":[-111.8333,35.1333],"type":"Point"}
}