{
  "id": 7096971,
  "type": "Feature",
  "properties": {
    "tgn:hierarchy":[
        "tgn:7096971",
        "tgn:7003669",
        "tgn:1000003",
        "tgn:7000084",
        "tgn:7029392"
    ],
    "tgn:id":7096971,
    "tgn:name":"Stadel Graben",
    "tgn:placetype":[
        "aat:300008699"
    ]
},
  "bbox": [],
  "geometry": {"coordinates":[12.783333,47.583333],"type":"Point"}
}