{
  "id": 2115819,
  "type": "Feature",
  "properties": {
    "tgn:hierarchy":[
        "tgn:2115819",
        "tgn:1000001",
        "tgn:7012149",
        "tgn:1002785",
        "tgn:7007920",
        "tgn:7029392"
    ],
    "tgn:id":2115819,
    "tgn:name":"Fort Steilacoom",
    "tgn:placetype":[
        "aat:300387016"
    ]
},
  "bbox": [],
  "geometry": {"coordinates":[-122.55,47.1667],"type":"Point"}
}