{
  "id": 2342309,
  "type": "Feature",
  "properties": {
    "tgn:hierarchy":[
        "tgn:2342309",
        "tgn:1000001",
        "tgn:7012149",
        "tgn:7007568",
        "tgn:7029392"
    ],
    "tgn:id":2342309,
    "tgn:name":"Fuller Brook",
    "tgn:placetype":[
        "aat:300008699"
    ]
},
  "bbox": [],
  "geometry": {"coordinates":[-73.8167,43.7667],"type":"Point"}
}