{
  "id": 7565945,
  "type": "Feature",
  "properties": {
    "tgn:hierarchy":[
        "tgn:7565945",
        "tgn:1000004",
        "tgn:7000198",
        "tgn:7016722",
        "tgn:7029392"
    ],
    "tgn:id":7565945,
    "tgn:name:en":"Inguri",
    "tgn:placetype":[
        "aat:300008347"
    ]
},
  "bbox": [],
  "geometry": {"coordinates":[79.395931,26.369651],"type":"Point"}
}