{
  "id": 7518797,
  "type": "Feature",
  "properties": {
    "tgn:hierarchy":[
        "tgn:7518797",
        "tgn:1009227",
        "tgn:1000226",
        "tgn:7016822",
        "tgn:1000006",
        "tgn:7029392"
    ],
    "tgn:id":7518797,
    "tgn:name:en":"Butlers Creek",
    "tgn:placetype":[
        "aat:300008699"
    ]
},
  "bbox": [],
  "geometry": {"coordinates":[168.516667,-46.15],"type":"Point"}
}