{
  "id": 7140661,
  "type": "Feature",
  "properties": {
    "tgn:hierarchy":[
        "tgn:7140661",
        "tgn:1000003",
        "tgn:7003688",
        "tgn:7000084",
        "tgn:7029392"
    ],
    "tgn:id":7140661,
    "tgn:name":"L\u00fctjenmoor",
    "tgn:placetype":[
        "aat:300387200"
    ]
},
  "bbox": [],
  "geometry": {"coordinates":[9.133333,54.316667],"type":"Point"}
}