{
  "id": 2748537,
  "type": "Feature",
  "properties": {
    "tgn:hierarchy":[
        "tgn:2748537",
        "tgn:1000001",
        "tgn:7012149",
        "tgn:2002002",
        "tgn:7007826",
        "tgn:7029392"
    ],
    "tgn:id":2748537,
    "tgn:name":"Walker Lake",
    "tgn:placetype":[
        "aat:300008680"
    ]
},
  "bbox": [],
  "geometry": {"coordinates":[-98.4667,26.2333],"type":"Point"}
}