{
  "id": 2196287,
  "type": "Feature",
  "properties": {
    "tgn:hierarchy":[
        "tgn:2196287",
        "tgn:1000001",
        "tgn:7012149",
        "tgn:2001303",
        "tgn:7007524",
        "tgn:7029392"
    ],
    "tgn:id":2196287,
    "tgn:name":"Broken Jaw Creek",
    "tgn:placetype":[
        "aat:300008706"
    ]
},
  "bbox": [],
  "geometry": {"coordinates":[-106.5667,45.5833],"type":"Point"}
}