{
  "id": 1136944,
  "type": "Feature",
  "properties": {
    "tgn:hierarchy":[
        "tgn:1136944",
        "tgn:1000003",
        "tgn:7003677",
        "tgn:7000084",
        "tgn:7029392"
    ],
    "tgn:id":1136944,
    "tgn:name":"Monheim",
    "tgn:placetype":[
        "aat:300008347"
    ]
},
  "bbox": [],
  "geometry": {"coordinates":[6.883333,51.083333],"type":"Point"}
}