{
  "id": 7450479,
  "type": "Feature",
  "properties": {
    "tgn:hierarchy":[
        "tgn:7450479",
        "tgn:7002445",
        "tgn:7008116",
        "tgn:1000003",
        "tgn:7008591",
        "tgn:7029392"
    ],
    "tgn:id":7450479,
    "tgn:name:en":"Gull Rock",
    "tgn:placetype":[
        "aat:300011692"
    ]
},
  "bbox": [],
  "geometry": {"coordinates":[-4.766667,50.65],"type":"Point"}
}