<<<<<<< HEAD
{
  "id": 7022860,
  "type": "Feature",
  "properties": {
    "tgn:hierarchy":[
        "tgn:7022860",
        "tgn:1000001",
        "tgn:7012149",
        "tgn:7007920",
        "tgn:7029392"
    ],
    "tgn:id":7022860,
    "tgn:name":"Duley Lake",
    "tgn:placetype":[
        "aat:300008680"
    ]
},
  "bbox": [],
  "geometry": {"coordinates":[-119.4833,48.15],"type":"Point"}
}
=======
{"geometry":{"type":"Point","coordinates":[-119.483300,48.150000]},"type":"Feature","properties":{"hierarchy":["tgn:7022860","tgn:1000001","tgn:7012149","tgn:7007920","tgn:7029392"],"placetype":["aat:300008680"],"id":7022860,"name:xx":"Duley Lake"}}
>>>>>>> 03f74aca74312dbeaf24d7e61306dd6a786dc3d0
