{
  "id": 2327005,
  "type": "Feature",
  "properties": {
    "tgn:hierarchy":[
        "tgn:2327005",
        "tgn:1000001",
        "tgn:7012149",
        "tgn:2002248",
        "tgn:7007920",
        "tgn:7029392"
    ],
    "tgn:id":2327005,
    "tgn:name":"Fireline Creek",
    "tgn:placetype":[
        "aat:300008706"
    ]
},
  "bbox": [],
  "geometry": {"coordinates":[-117.1167,48.8333],"type":"Point"}
}