{
  "id": 7538266,
  "type": "Feature",
  "properties": {
    "tgn:hierarchy":[
        "tgn:7538266",
        "tgn:7001242",
        "tgn:7016833",
        "tgn:7000124",
        "tgn:7029392"
    ],
    "tgn:id":7538266,
    "tgn:name:en":"Nazlat Fazz\u0101'",
    "tgn:placetype":[
        "aat:300008347"
    ]
},
  "bbox": [],
  "geometry": {"coordinates":[31.366667,26.816667],"type":"Point"}
}