{
  "id": 2445956,
  "type": "Feature",
  "properties": {
    "tgn:hierarchy":[
        "tgn:2445956",
        "tgn:1000001",
        "tgn:7012149",
        "tgn:1002860",
        "tgn:7007826",
        "tgn:7029392"
    ],
    "tgn:id":2445956,
    "tgn:name":"Letbetter Lake",
    "tgn:placetype":[
        "aat:300006191"
    ]
},
  "bbox": [],
  "geometry": {"coordinates":[-95.1667,30.4833],"type":"Point"}
}