{
  "id": 1028916,
  "type": "Feature",
  "properties": {
    "tgn:hierarchy":[
        "tgn:1028916",
        "tgn:7002445",
        "tgn:1000003",
        "tgn:7012077",
        "tgn:7008591",
        "tgn:7029392"
    ],
    "tgn:id":1028916,
    "tgn:name:ang":"Culitone",
    "tgn:placetype":[
        "aat:300008347"
    ]
},
  "bbox": [],
  "geometry": {"coordinates":[-3.083333,50.75],"type":"Point"}
}