{
  "id": 7546120,
  "type": "Feature",
  "properties": {
    "tgn:hierarchy":[
        "tgn:7546120",
        "tgn:1000004",
        "tgn:7000198",
        "tgn:1001977",
        "tgn:7029392"
    ],
    "tgn:id":7546120,
    "tgn:name:en":"Baidyapur",
    "tgn:placetype":[
        "aat:300008347"
    ]
},
  "bbox": [],
  "geometry": {"coordinates":[88.251408,23.166897],"type":"Point"}
}