{
  "id": 2266085,
  "type": "Feature",
  "properties": {
    "tgn:hierarchy":[
        "tgn:2266085",
        "tgn:1000001",
        "tgn:7012149",
        "tgn:2002352",
        "tgn:7007922",
        "tgn:7029392"
    ],
    "tgn:id":2266085,
    "tgn:name":"Crawford Crossing",
    "tgn:placetype":[
        "aat:300008347"
    ]
},
  "bbox": [],
  "geometry": {"coordinates":[-89.7167,43.45],"type":"Point"}
}