{
  "id": 2377429,
  "type": "Feature",
  "properties": {
    "tgn:hierarchy":[
        "tgn:2377429",
        "tgn:1000001",
        "tgn:7012149",
        "tgn:2001758",
        "tgn:7007712",
        "tgn:7029392"
    ],
    "tgn:id":2377429,
    "tgn:name":"Haroldson Lake",
    "tgn:placetype":[
        "aat:300008680"
    ]
},
  "bbox": [],
  "geometry": {"coordinates":[-79.2667,34.05],"type":"Point"}
}