{
  "id": 2603726,
  "type": "Feature",
  "properties": {
    "tgn:hierarchy":[
        "tgn:2603726",
        "tgn:1000001",
        "tgn:2002243",
        "tgn:7012149",
        "tgn:7007920",
        "tgn:7029392"
    ],
    "tgn:id":2603726,
    "tgn:name":"Qui Qui Creek",
    "tgn:placetype":[
        "aat:300008706"
    ]
},
  "bbox": [],
  "geometry": {"coordinates":[-118.7833,47.9833],"type":"Point"}
}