{
  "id": 7311535,
  "type": "Feature",
  "properties": {
    "tgn:hierarchy":[
        "tgn:7311535",
        "tgn:1001623",
        "tgn:1000049",
        "tgn:1000002",
        "tgn:7029392"
    ],
    "tgn:id":7311535,
    "tgn:name":"Lobos, Islote",
    "tgn:placetype":[
        "aat:300008791"
    ]
},
  "bbox": [],
  "geometry": {"coordinates":[-74.05,-45.416667],"type":"Point"}
}