<<<<<<< HEAD
{
  "id": 7359788,
  "type": "Feature",
  "properties": {
    "tgn:hierarchy":[
        "tgn:7359788",
        "tgn:7005581",
        "tgn:1000001",
        "tgn:7005560",
        "tgn:7029392"
    ],
    "tgn:id":7359788,
    "tgn:name":"Cuatro Amigos, Cerro",
    "tgn:placetype":[
        "aat:300008795"
    ]
},
  "bbox": [],
  "geometry": {"coordinates":[-107.433333,30.566667],"type":"Point"}
}
=======
{"geometry":{"type":"Point","coordinates":[-107.433333,30.566667]},"type":"Feature","properties":{"hierarchy":["tgn:7359788","tgn:7005581","tgn:1000001","tgn:7005560","tgn:7029392"],"placetype":["aat:300008795"],"id":7359788,"name:xx":"Cuatro Amigos, Cerro"}}
>>>>>>> 03f74aca74312dbeaf24d7e61306dd6a786dc3d0
