<<<<<<< HEAD
{
  "id": 7484164,
  "type": "Feature",
  "properties": {
    "tgn:hierarchy":[
        "tgn:7484164",
        "tgn:1000004",
        "tgn:7490934",
        "tgn:1000141",
        "tgn:7029392"
    ],
    "tgn:id":7484164,
    "tgn:name":"Shifan Gongmu",
    "tgn:placetype":[
        "aat:300266755"
    ]
},
  "bbox": [],
  "geometry": {"coordinates":[120.303056,23.317222],"type":"Point"}
}
=======
{"geometry":{"type":"Point","coordinates":[120.303056,23.317222]},"type":"Feature","properties":{"hierarchy":["tgn:7484164","tgn:1000004","tgn:7490934","tgn:1000141","tgn:7029392"],"placetype":["aat:300266755"],"id":7484164,"name:xx":"Shifan Gongmu"}}
>>>>>>> 03f74aca74312dbeaf24d7e61306dd6a786dc3d0
