{
  "id": 7280826,
  "type": "Feature",
  "properties": {
    "tgn:hierarchy":[
        "tgn:7280826",
        "tgn:1001702",
        "tgn:1000049",
        "tgn:1000002",
        "tgn:7029392"
    ],
    "tgn:id":7280826,
    "tgn:name":"Santa Mar\u00eda, Cerro",
    "tgn:placetype":[
        "aat:300008777"
    ]
},
  "bbox": [],
  "geometry": {"coordinates":[-70.416667,-53.366667],"type":"Point"}
}