{
  "id": 7513522,
  "type": "Feature",
  "properties": {
    "tgn:hierarchy":[
        "tgn:7513522",
        "tgn:1009227",
        "tgn:1000226",
        "tgn:7018437",
        "tgn:1000006",
        "tgn:7029392"
    ],
    "tgn:id":7513522,
    "tgn:name:en":"Gill Hill",
    "tgn:placetype":[
        "aat:300008777"
    ]
},
  "bbox": [],
  "geometry": {"coordinates":[168.833333,-43.983333],"type":"Point"}
}