{
  "id": 7312887,
  "type": "Feature",
  "properties": {
    "tgn:hierarchy":[
        "tgn:7312887",
        "tgn:1001657",
        "tgn:1000049",
        "tgn:1000002",
        "tgn:7029392"
    ],
    "tgn:id":7312887,
    "tgn:name":"La Matanza",
    "tgn:placetype":[
        "aat:300008347"
    ]
},
  "bbox": [],
  "geometry": {"coordinates":[-70.933333,-29.633333],"type":"Point"}
}