{
  "id": 2649552,
  "type": "Feature",
  "properties": {
    "tgn:hierarchy":[
        "tgn:2649552",
        "tgn:1000001",
        "tgn:2001416",
        "tgn:7012149",
        "tgn:7007526",
        "tgn:7029392"
    ],
    "tgn:id":2649552,
    "tgn:name":"Scotty Wash",
    "tgn:placetype":[
        "aat:300008699"
    ]
},
  "bbox": [],
  "geometry": {"coordinates":[-114.6667,38.1833],"type":"Point"}
}