{
  "id": 7010371,
  "type": "Feature",
  "properties": {
    "tgn:hierarchy":[
        "tgn:7010371",
        "tgn:7003006",
        "tgn:1000003",
        "tgn:7002997",
        "tgn:1000080",
        "tgn:7029392"
    ],
    "tgn:id":7010371,
    "tgn:name":"Piave",
    "tgn:placetype":[
        "aat:300008707",
        "aat:300008699"
    ]
},
  "bbox": [],
  "geometry": {"coordinates":[12.729722,45.533889],"type":"Point"}
}