{
  "id": 1017391,
  "type": "Feature",
  "properties": {
    "tgn:hierarchy":[
        "tgn:1017391",
        "tgn:1001835",
        "tgn:1000001",
        "tgn:7005560",
        "tgn:7029392"
    ],
    "tgn:id":1017391,
    "tgn:name":"El Cipr\u00e9s",
    "tgn:placetype":[
        "aat:300008347"
    ]
},
  "bbox": [],
  "geometry": {"coordinates":[-116.566667,31.816667],"type":"Point"}
}