{
  "id": 7280130,
  "type": "Feature",
  "properties": {
    "tgn:hierarchy":[
        "tgn:7280130",
        "tgn:1001695",
        "tgn:1000049",
        "tgn:1000002",
        "tgn:7029392"
    ],
    "tgn:id":7280130,
    "tgn:name":"Requ\u00ednoa",
    "tgn:placetype":[
        "aat:300008347"
    ]
},
  "bbox": [],
  "geometry": {"coordinates":[-70.833333,-34.283333],"type":"Point"}
}