{
  "id": 2145909,
  "type": "Feature",
  "properties": {
    "tgn:hierarchy":[
        "tgn:2145909",
        "tgn:1000001",
        "tgn:1002222",
        "tgn:7012149",
        "tgn:7007520",
        "tgn:7029392"
    ],
    "tgn:id":2145909,
    "tgn:name":"Ball And Patterson Drain",
    "tgn:placetype":[
        "aat:300006075"
    ]
},
  "bbox": [],
  "geometry": {"coordinates":[-84.8167,42.1833],"type":"Point"}
}