{
  "id": 1060867,
  "type": "Feature",
  "properties": {
    "tgn:hierarchy":[
        "tgn:1060867",
        "tgn:1000004",
        "tgn:1003408",
        "tgn:7018214",
        "tgn:7002435",
        "tgn:7029392"
    ],
    "tgn:id":1060867,
    "tgn:name":"Uzmorye",
    "tgn:placetype":[
        "aat:300008347"
    ]
},
  "bbox": [],
  "geometry": {"coordinates":[45.9167,51.25],"type":"Point"}
}