{
  "id": 7196009,
  "type": "Feature",
  "properties": {
    "tgn:hierarchy":[
        "tgn:7196009",
        "tgn:1000003",
        "tgn:7003687",
        "tgn:7000084",
        "tgn:7029392"
    ],
    "tgn:id":7196009,
    "tgn:name":"Dorfstelle Asmersleben",
    "tgn:placetype":[
        "aat:300055621"
    ]
},
  "bbox": [],
  "geometry": {"coordinates":[11.233333,51.75],"type":"Point"}
}