{
  "id": 7490463,
  "type": "Feature",
  "properties": {
    "tgn:hierarchy":[
        "tgn:7490463",
        "tgn:7001010",
        "tgn:1000004",
        "tgn:1000141",
        "tgn:7029392"
    ],
    "tgn:id":7490463,
    "tgn:name":"Sanzhan",
    "tgn:placetype":[
        "aat:300008347"
    ]
},
  "bbox": [],
  "geometry": {"coordinates":[121.595,24.0551],"type":"Point"}
}