{
  "id": 7308313,
  "type": "Feature",
  "properties": {
    "tgn:hierarchy":[
        "tgn:7308313",
        "tgn:7016598",
        "tgn:1000049",
        "tgn:1000002",
        "tgn:7029392"
    ],
    "tgn:id":7308313,
    "tgn:name":"Mastodonte",
    "tgn:placetype":[
        "aat:300387033"
    ]
},
  "bbox": [],
  "geometry": {"coordinates":[-69.15,-23.666667],"type":"Point"}
}