{
  "id": 7498110,
  "type": "Feature",
  "properties": {
    "tgn:hierarchy":[
        "tgn:7498110",
        "tgn:1000004",
        "tgn:7492971",
        "tgn:1000141",
        "tgn:7029392"
    ],
    "tgn:id":7498110,
    "tgn:name":"Xiyue Qiao",
    "tgn:placetype":[
        "aat:300007836"
    ]
},
  "bbox": [],
  "geometry": {"coordinates":[120.473945,22.744128],"type":"Point"}
}