{
  "id": 2385846,
  "type": "Feature",
  "properties": {
    "tgn:hierarchy":[
        "tgn:2385846",
        "tgn:1000001",
        "tgn:2001025",
        "tgn:7012149",
        "tgn:7007521",
        "tgn:7029392"
    ],
    "tgn:id":2385846,
    "tgn:name":"Hennepin Island",
    "tgn:placetype":[
        "aat:300008791"
    ]
},
  "bbox": [],
  "geometry": {"coordinates":[-93.25,44.9667],"type":"Point"}
}