{
  "id": 7417833,
  "type": "Feature",
  "properties": {
    "tgn:hierarchy":[
        "tgn:7417833",
        "tgn:1000001",
        "tgn:7005591",
        "tgn:7005560",
        "tgn:7029392"
    ],
    "tgn:id":7417833,
    "tgn:name:es":"La Blanca, Isla",
    "tgn:placetype":[
        "aat:300008791"
    ]
},
  "bbox": [],
  "geometry": {"coordinates":[-95.531111,15.945833],"type":"Point"}
}