{
  "id": 7458737,
  "type": "Feature",
  "properties": {
    "tgn:hierarchy":[
        "tgn:7458737",
        "tgn:7002444",
        "tgn:1000003",
        "tgn:7008072",
        "tgn:7008591",
        "tgn:7029392"
    ],
    "tgn:id":7458737,
    "tgn:name:en":"Oxnam",
    "tgn:placetype":[
        "aat:300008347"
    ]
},
  "bbox": [],
  "geometry": {"coordinates":[-2.483333,55.45],"type":"Point"}
}