{
  "id": 2125866,
  "type": "Feature",
  "properties": {
    "tgn:hierarchy":[
        "tgn:2125866",
        "tgn:1000001",
        "tgn:7012149",
        "tgn:1002567",
        "tgn:7007240",
        "tgn:7029392"
    ],
    "tgn:id":2125866,
    "tgn:name":"Adams Lake",
    "tgn:placetype":[
        "aat:300008680"
    ]
},
  "bbox": [],
  "geometry": {"coordinates":[-81.55,28.7833],"type":"Point"}
}