{
  "id": 7157980,
  "type": "Feature",
  "properties": {
    "tgn:hierarchy":[
        "tgn:7157980",
        "tgn:7003692",
        "tgn:1000003",
        "tgn:7000084",
        "tgn:7029392"
    ],
    "tgn:id":7157980,
    "tgn:name":"Kirrlach",
    "tgn:placetype":[
        "aat:300008347"
    ]
},
  "bbox": [],
  "geometry": {"coordinates":[8.545278,49.243611],"type":"Point"}
}