{
  "id": 7578566,
  "type": "Feature",
  "properties": {
    "tgn:hierarchy":[
        "tgn:7578566",
        "tgn:1000004",
        "tgn:7000198",
        "tgn:1001905",
        "tgn:7029392"
    ],
    "tgn:id":7578566,
    "tgn:name:en":"Tamkhung",
    "tgn:placetype":[
        "aat:300008347"
    ]
},
  "bbox": [],
  "geometry": {"coordinates":[95.006385,26.382256],"type":"Point"}
}