{
  "id": 2055265,
  "type": "Feature",
  "properties": {
    "tgn:hierarchy":[
        "tgn:2055265",
        "tgn:2001003",
        "tgn:1000001",
        "tgn:7012149",
        "tgn:7007521",
        "tgn:7029392"
    ],
    "tgn:id":2055265,
    "tgn:name":"Popple Creek",
    "tgn:placetype":[
        "aat:300008347",
        "aat:300387210"
    ]
},
  "bbox": [],
  "geometry": {"coordinates":[-94.0167,45.65],"type":"Point"}
}