{
  "id": 7561612,
  "type": "Feature",
  "properties": {
    "tgn:hierarchy":[
        "tgn:7561612",
        "tgn:1000004",
        "tgn:7000198",
        "tgn:7016722",
        "tgn:7029392"
    ],
    "tgn:id":7561612,
    "tgn:name:en":"Dhami\u0101pur",
    "tgn:placetype":[
        "aat:300008347"
    ]
},
  "bbox": [],
  "geometry": {"coordinates":[79.334311,27.095085],"type":"Point"}
}