{
  "id": 1099030,
  "type": "Feature",
  "properties": {
    "tgn:hierarchy":[
        "tgn:1099030",
        "tgn:1009227",
        "tgn:7001866",
        "tgn:1000226",
        "tgn:1000006",
        "tgn:7029392"
    ],
    "tgn:id":1099030,
    "tgn:name:en":"Little River",
    "tgn:placetype":[
        "aat:300008347"
    ]
},
  "bbox": [],
  "geometry": {"coordinates":[172.783333,-43.766667],"type":"Point"}
}