{
  "id": 7277238,
  "type": "Feature",
  "properties": {
    "tgn:hierarchy":[
        "tgn:7277238",
        "tgn:1001699",
        "tgn:1000049",
        "tgn:1000002",
        "tgn:7029392"
    ],
    "tgn:id":7277238,
    "tgn:name":"Valle Palena",
    "tgn:placetype":[
        "aat:300008761"
    ]
},
  "bbox": [],
  "geometry": {"coordinates":[-72.300278,-43.693611],"type":"Point"}
}