{
  "id": 7564085,
  "type": "Feature",
  "properties": {
    "tgn:hierarchy":[
        "tgn:7564085",
        "tgn:1000004",
        "tgn:7000198",
        "tgn:1001894",
        "tgn:7029392"
    ],
    "tgn:id":7564085,
    "tgn:name:en":"Bar\u0101r Gh\u0101t",
    "tgn:placetype":[
        "aat:300387042"
    ]
},
  "bbox": [],
  "geometry": {"coordinates":[79.319933,24.85091],"type":"Point"}
}