<<<<<<< HEAD
{
  "id": 2156029,
  "type": "Feature",
  "properties": {
    "tgn:hierarchy":[
        "tgn:2156029",
        "tgn:1000001",
        "tgn:7012149",
        "tgn:2000481",
        "tgn:7007250",
        "tgn:7029392"
    ],
    "tgn:id":2156029,
    "tgn:name":"Bear Wallow Spring",
    "tgn:placetype":[
        "aat:300008697"
    ]
},
  "bbox": [],
  "geometry": {"coordinates":[-114.1,45.5333],"type":"Point"}
}
=======
{"geometry":{"type":"Point","coordinates":[-114.100000,45.533300]},"type":"Feature","properties":{"hierarchy":["tgn:2156029","tgn:1000001","tgn:7012149","tgn:2000481","tgn:7007250","tgn:7029392"],"placetype":["aat:300008697"],"id":2156029,"name:xx":"Bear Wallow Spring"}}
>>>>>>> 03f74aca74312dbeaf24d7e61306dd6a786dc3d0
