<<<<<<< HEAD
{
  "id": 2765461,
  "type": "Feature",
  "properties": {
    "tgn:hierarchy":[
        "tgn:2765461",
        "tgn:1000001",
        "tgn:7012149",
        "tgn:2001514",
        "tgn:7007709",
        "tgn:7029392"
    ],
    "tgn:id":2765461,
    "tgn:name":"White Branch",
    "tgn:placetype":[
        "aat:300008699"
    ]
},
  "bbox": [],
  "geometry": {"coordinates":[-81.9167,35.6333],"type":"Point"}
}
=======
{"geometry":{"type":"Point","coordinates":[-81.916700,35.633300]},"type":"Feature","properties":{"hierarchy":["tgn:2765461","tgn:1000001","tgn:7012149","tgn:2001514","tgn:7007709","tgn:7029392"],"placetype":["aat:300008699"],"id":2765461,"name:xx":"White Branch"}}
>>>>>>> 03f74aca74312dbeaf24d7e61306dd6a786dc3d0
