{
  "id": 2756086,
  "type": "Feature",
  "properties": {
    "tgn:hierarchy":[
        "tgn:2756086",
        "tgn:1000001",
        "tgn:1002205",
        "tgn:7012149",
        "tgn:7013961",
        "tgn:7029392"
    ],
    "tgn:id":2756086,
    "tgn:name":"Weirton Junction",
    "tgn:placetype":[
        "aat:300008347"
    ]
},
  "bbox": [],
  "geometry": {"coordinates":[-80.5833,40.3833],"type":"Point"}
}