{
  "id": 2107243,
  "type": "Feature",
  "properties": {
    "tgn:hierarchy":[
        "tgn:2107243",
        "tgn:1000001",
        "tgn:7012149",
        "tgn:2001999",
        "tgn:7007826",
        "tgn:7029392"
    ],
    "tgn:id":2107243,
    "tgn:name":"Romero",
    "tgn:placetype":[
        "aat:300008347",
        "aat:300387210"
    ]
},
  "bbox": [],
  "geometry": {"coordinates":[-102.9167,35.7167],"type":"Point"}
}