{
  "id": 7586014,
  "type": "Feature",
  "properties": {
    "tgn:hierarchy":[
        "tgn:7586014",
        "tgn:1000004",
        "tgn:7000198",
        "tgn:7000799",
        "tgn:7029392"
    ],
    "tgn:id":7586014,
    "tgn:name:en":"Tsogul",
    "tgn:placetype":[
        "aat:300008347"
    ]
},
  "bbox": [],
  "geometry": {"coordinates":[74.313826,34.402533],"type":"Point"}
}