{
  "id": 2602174,
  "type": "Feature",
  "properties": {
    "tgn:hierarchy":[
        "tgn:2602174",
        "tgn:7023902",
        "tgn:1000001",
        "tgn:7012149",
        "tgn:7007249",
        "tgn:7029392"
    ],
    "tgn:id":2602174,
    "tgn:name":"Puu o Keokeo",
    "tgn:placetype":[
        "aat:300008798"
    ]
},
  "bbox": [],
  "geometry": {"coordinates":[-155.7333,19.2167],"type":"Point"}
}