{
  "id": 2556249,
  "type": "Feature",
  "properties": {
    "tgn:hierarchy":[
        "tgn:2556249",
        "tgn:1000001",
        "tgn:7012149",
        "tgn:7007521",
        "tgn:7029392"
    ],
    "tgn:id":2556249,
    "tgn:name":"Okabena Creek",
    "tgn:placetype":[
        "aat:300008706"
    ]
},
  "bbox": [],
  "geometry": {"coordinates":[-95.6833,43.6833],"type":"Point"}
}