{
  "id": 2217813,
  "type": "Feature",
  "properties": {
    "tgn:hierarchy":[
        "tgn:2217813",
        "tgn:1000001",
        "tgn:7016172",
        "tgn:7012149",
        "tgn:2000144",
        "tgn:7029392"
    ],
    "tgn:id":2217813,
    "tgn:name":"Campbells Brake",
    "tgn:placetype":[
        "aat:300008905"
    ]
},
  "bbox": [],
  "geometry": {"coordinates":[-91.5667,33.7833],"type":"Point"}
}