<<<<<<< HEAD
{
  "id": 7361928,
  "type": "Feature",
  "properties": {
    "tgn:hierarchy":[
        "tgn:7361928",
        "tgn:7005583",
        "tgn:1000001",
        "tgn:7005560",
        "tgn:7029392"
    ],
    "tgn:id":7361928,
    "tgn:name":"El Cuervo",
    "tgn:placetype":[
        "aat:300008347"
    ]
},
  "bbox": [],
  "geometry": {"coordinates":[-105.2,25.983333],"type":"Point"}
}
=======
{"geometry":{"type":"Point","coordinates":[-105.200000,25.983333]},"type":"Feature","properties":{"hierarchy":["tgn:7361928","tgn:7005583","tgn:1000001","tgn:7005560","tgn:7029392"],"placetype":["aat:300008347"],"id":7361928,"name:xx":"El Cuervo"}}
>>>>>>> 03f74aca74312dbeaf24d7e61306dd6a786dc3d0
