{
  "id": 7427676,
  "type": "Feature",
  "properties": {
    "tgn:hierarchy":[
        "tgn:7427676",
        "tgn:1000001",
        "tgn:7005594",
        "tgn:7005560",
        "tgn:7029392"
    ],
    "tgn:id":7427676,
    "tgn:name":"La Flor",
    "tgn:placetype":[
        "aat:300008347"
    ]
},
  "bbox": [],
  "geometry": {"coordinates":[-101.716667,23.283333],"type":"Point"}
}