{
  "id": 2119408,
  "type": "Feature",
  "properties": {
    "tgn:hierarchy":[
        "tgn:2119408",
        "tgn:1000001",
        "tgn:2002258",
        "tgn:7012149",
        "tgn:7013961",
        "tgn:7029392"
    ],
    "tgn:id":2119408,
    "tgn:name":"Nobe",
    "tgn:placetype":[
        "aat:300008347",
        "aat:300387210"
    ]
},
  "bbox": [],
  "geometry": {"coordinates":[-81.0333,38.9833],"type":"Point"}
}