{
  "id": 7139010,
  "type": "Feature",
  "properties": {
    "tgn:hierarchy":[
        "tgn:7139010",
        "tgn:7003692",
        "tgn:1000003",
        "tgn:7000084",
        "tgn:7029392"
    ],
    "tgn:id":7139010,
    "tgn:name":"Langer Bauer",
    "tgn:placetype":[
        "aat:300000206"
    ]
},
  "bbox": [],
  "geometry": {"coordinates":[9.633333,48.416667],"type":"Point"}
}