{
  "id": 7030132,
  "type": "Feature",
  "properties": {
    "tgn:hierarchy":[
        "tgn:7030132",
        "tgn:1003567",
        "tgn:7002445",
        "tgn:1000003",
        "tgn:7029507",
        "tgn:7008591",
        "tgn:7029392"
    ],
    "tgn:id":7030132,
    "tgn:name:ang":"Neuhuse",
    "tgn:placetype":[
        "aat:300008347"
    ]
},
  "bbox": [],
  "geometry": {"coordinates":[-1.965,53.85],"type":"Point"}
}