{
  "id": 2060101,
  "type": "Feature",
  "properties": {
    "tgn:hierarchy":[
        "tgn:2060101",
        "tgn:1000001",
        "tgn:7012149",
        "tgn:2001216",
        "tgn:7007523",
        "tgn:7029392"
    ],
    "tgn:id":2060101,
    "tgn:name":"Pineville",
    "tgn:placetype":[
        "aat:300008347"
    ]
},
  "bbox": [],
  "geometry": {"coordinates":[-94.3833,36.5833],"type":"Point"}
}