{
  "id": 7427096,
  "type": "Feature",
  "properties": {
    "tgn:hierarchy":[
        "tgn:7427096",
        "tgn:7005581",
        "tgn:1000001",
        "tgn:7005560",
        "tgn:7029392"
    ],
    "tgn:id":7427096,
    "tgn:name":"Las Marianas",
    "tgn:placetype":[
        "aat:300008347"
    ]
},
  "bbox": [],
  "geometry": {"coordinates":[-106.183333,30.15],"type":"Point"}
}