{
  "id": 2231271,
  "type": "Feature",
  "properties": {
    "tgn:hierarchy":[
        "tgn:2231271",
        "tgn:2002307",
        "tgn:1000001",
        "tgn:7012149",
        "tgn:7007922",
        "tgn:7029392"
    ],
    "tgn:id":2231271,
    "tgn:name":"Chain Lake",
    "tgn:placetype":[
        "aat:300008680"
    ]
},
  "bbox": [],
  "geometry": {"coordinates":[-91.9333,45.5833],"type":"Point"}
}