{
  "id": 2396851,
  "type": "Feature",
  "properties": {
    "tgn:hierarchy":[
        "tgn:2396851",
        "tgn:1000001",
        "tgn:7012149",
        "tgn:7007158",
        "tgn:7029392"
    ],
    "tgn:id":2396851,
    "tgn:name":"Home Supply Ditch",
    "tgn:placetype":[
        "aat:300006075"
    ]
},
  "bbox": [],
  "geometry": {"coordinates":[-107.0833,39.35],"type":"Point"}
}