{
  "id": 2346646,
  "type": "Feature",
  "properties": {
    "tgn:hierarchy":[
        "tgn:2346646",
        "tgn:1000001",
        "tgn:2002316",
        "tgn:7012149",
        "tgn:7007922",
        "tgn:7029392"
    ],
    "tgn:id":2346646,
    "tgn:name":"Gays Mills Ridge",
    "tgn:placetype":[
        "aat:300266640"
    ]
},
  "bbox": [],
  "geometry": {"coordinates":[-90.8667,43.3167],"type":"Point"}
}