{
  "id": 2489118,
  "type": "Feature",
  "properties": {
    "tgn:hierarchy":[
        "tgn:2489118",
        "tgn:1000001",
        "tgn:7012149",
        "tgn:2001821",
        "tgn:7007713",
        "tgn:7029392"
    ],
    "tgn:id":2489118,
    "tgn:name":"Major Lake",
    "tgn:placetype":[
        "aat:300006191"
    ]
},
  "bbox": [],
  "geometry": {"coordinates":[-103.5667,43.9333],"type":"Point"}
}