{
  "id": 1066814,
  "type": "Feature",
  "properties": {
    "tgn:hierarchy":[
        "tgn:1066814",
        "tgn:1000004",
        "tgn:7001838",
        "tgn:1000111",
        "tgn:7029392"
    ],
    "tgn:id":1066814,
    "tgn:name":"Bayanheshuomiao",
    "tgn:placetype":[
        "aat:300008347"
    ]
},
  "bbox": [],
  "geometry": {"coordinates":[119.7667,48.85],"type":"Point"}
}