{
  "id": 2312277,
  "type": "Feature",
  "properties": {
    "tgn:hierarchy":[
        "tgn:2312277",
        "tgn:1000001",
        "tgn:7012149",
        "tgn:2001437",
        "tgn:7007566",
        "tgn:7029392"
    ],
    "tgn:id":2312277,
    "tgn:name":"Eighteen Tank",
    "tgn:placetype":[
        "aat:300006191"
    ]
},
  "bbox": [],
  "geometry": {"coordinates":[-108.0167,32.8167],"type":"Point"}
}