{
  "id": 2713973,
  "type": "Feature",
  "properties": {
    "tgn:hierarchy":[
        "tgn:2713973",
        "tgn:1000001",
        "tgn:7012149",
        "tgn:7029392"
    ],
    "tgn:id":2713973,
    "tgn:name":"Teeter Creek",
    "tgn:placetype":[
        "aat:300008706"
    ]
},
  "bbox": [],
  "geometry": {"coordinates":[-103.05,45.85],"type":"Point"}
}