<<<<<<< HEAD
{
  "id": 7361275,
  "type": "Feature",
  "properties": {
    "tgn:hierarchy":[
        "tgn:7361275",
        "tgn:1000001",
        "tgn:7005597",
        "tgn:7005560",
        "tgn:7029392"
    ],
    "tgn:id":7361275,
    "tgn:name":"El Ingenio",
    "tgn:placetype":[
        "aat:300008347"
    ]
},
  "bbox": [],
  "geometry": {"coordinates":[-99.4,23.433333],"type":"Point"}
}
=======
{"geometry":{"type":"Point","coordinates":[-99.400000,23.433333]},"type":"Feature","properties":{"hierarchy":["tgn:7361275","tgn:1000001","tgn:7005597","tgn:7005560","tgn:7029392"],"placetype":["aat:300008347"],"id":7361275,"name:xx":"El Ingenio"}}
>>>>>>> 03f74aca74312dbeaf24d7e61306dd6a786dc3d0
