{
  "id": 7415465,
  "type": "Feature",
  "properties": {
    "tgn:hierarchy":[
        "tgn:7415465",
        "tgn:1000001",
        "tgn:7005591",
        "tgn:7005560",
        "tgn:7029392"
    ],
    "tgn:id":7415465,
    "tgn:name:es":"Conejo, Cerro",
    "tgn:placetype":[
        "aat:300008795"
    ]
},
  "bbox": [],
  "geometry": {"coordinates":[-95.701667,16.156111],"type":"Point"}
}