{
  "id": 7233825,
  "type": "Feature",
  "properties": {
    "tgn:hierarchy":[
        "tgn:7233825",
        "tgn:7002707",
        "tgn:7002705",
        "tgn:1000003",
        "tgn:1000074",
        "tgn:7029392"
    ],
    "tgn:id":7233825,
    "tgn:name":"Akror\u00e1khi",
    "tgn:placetype":[
        "aat:300008795"
    ]
},
  "bbox": [],
  "geometry": {"coordinates":[20.383333,39.933333],"type":"Point"}
}