{
  "id": 1070261,
  "type": "Feature",
  "properties": {
    "tgn:hierarchy":[
        "tgn:1070261",
        "tgn:1000004",
        "tgn:7001796",
        "tgn:1000111",
        "tgn:7029392"
    ],
    "tgn:id":1070261,
    "tgn:name":"Mabi",
    "tgn:placetype":[
        "aat:300008347"
    ]
},
  "bbox": [],
  "geometry": {"coordinates":[119.65,26.3833],"type":"Point"}
}