{
  "id": 2704037,
  "type": "Feature",
  "properties": {
    "tgn:hierarchy":[
        "tgn:2704037",
        "tgn:1000001",
        "tgn:1002347",
        "tgn:7012149",
        "tgn:7007568",
        "tgn:7029392"
    ],
    "tgn:id":2704037,
    "tgn:name":"Sunfish Cove",
    "tgn:placetype":[
        "aat:300132316"
    ]
},
  "bbox": [],
  "geometry": {"coordinates":[-73.9333,41.6667],"type":"Point"}
}