{
  "id": 2101752,
  "type": "Feature",
  "properties": {
    "tgn:hierarchy":[
        "tgn:2101752",
        "tgn:1000001",
        "tgn:7012149",
        "tgn:2001854",
        "tgn:7007825",
        "tgn:7029392"
    ],
    "tgn:id":2101752,
    "tgn:name":"Tabor",
    "tgn:placetype":[
        "aat:300008347",
        "aat:300387210"
    ]
},
  "bbox": [],
  "geometry": {"coordinates":[-85.0333,36.0167],"type":"Point"}
}