{
  "id": 2128145,
  "type": "Feature",
  "properties": {
    "tgn:hierarchy":[
        "tgn:2128145",
        "tgn:1000001",
        "tgn:7012149",
        "tgn:2002118",
        "tgn:7007827",
        "tgn:7029392"
    ],
    "tgn:id":2128145,
    "tgn:name":"Albion Basin",
    "tgn:placetype":[
        "aat:300008347"
    ]
},
  "bbox": [],
  "geometry": {"coordinates":[-111.6167,40.5667],"type":"Point"}
}