<<<<<<< HEAD
{
  "id": 2255571,
  "type": "Feature",
  "properties": {
    "tgn:hierarchy":[
        "tgn:2255571",
        "tgn:1000001",
        "tgn:7016172",
        "tgn:2000115",
        "tgn:7012149",
        "tgn:7029392"
    ],
    "tgn:id":2255571,
    "tgn:name":"Copeland Lake",
    "tgn:placetype":[
        "aat:300006191"
    ]
},
  "bbox": [],
  "geometry": {"coordinates":[-90.25,36.3167],"type":"Point"}
}
=======
{"geometry":{"type":"Point","coordinates":[-90.250000,36.316700]},"type":"Feature","properties":{"hierarchy":["tgn:2255571","tgn:1000001","tgn:7016172","tgn:2000115","tgn:7012149","tgn:7029392"],"placetype":["aat:300006191"],"id":2255571,"name:xx":"Copeland Lake"}}
>>>>>>> 03f74aca74312dbeaf24d7e61306dd6a786dc3d0
