{
  "id": 2606610,
  "type": "Feature",
  "properties": {
    "tgn:hierarchy":[
        "tgn:2606610",
        "tgn:1000001",
        "tgn:7006451",
        "tgn:7012149",
        "tgn:2000101",
        "tgn:7029392"
    ],
    "tgn:id":2606610,
    "tgn:name":"Ramona Mine",
    "tgn:placetype":[
        "aat:300000390"
    ]
},
  "bbox": [],
  "geometry": {"coordinates":[-111.8833,32.5833],"type":"Point"}
}