{
  "id": 2559648,
  "type": "Feature",
  "properties": {
    "tgn:hierarchy":[
        "tgn:2559648",
        "tgn:1000001",
        "tgn:7012149",
        "tgn:2001706",
        "tgn:7007708",
        "tgn:7029392"
    ],
    "tgn:id":2559648,
    "tgn:name":"Opal Lake",
    "tgn:placetype":[
        "aat:300008680"
    ]
},
  "bbox": [],
  "geometry": {"coordinates":[-122.1167,43.4167],"type":"Point"}
}