{
  "id": 7504672,
  "type": "Feature",
  "properties": {
    "tgn:hierarchy":[
        "tgn:7504672",
        "tgn:1008380",
        "tgn:7000507",
        "tgn:1000226",
        "tgn:1000006",
        "tgn:7029392"
    ],
    "tgn:id":7504672,
    "tgn:name:en":"Puke Range",
    "tgn:placetype":[
        "aat:300008795"
    ]
},
  "bbox": [],
  "geometry": {"coordinates":[175.133333,36.783333],"type":"Point"}
}