{
  "id": 2745284,
  "type": "Feature",
  "properties": {
    "tgn:hierarchy":[
        "tgn:2745284",
        "tgn:1002215",
        "tgn:1000001",
        "tgn:7012149",
        "tgn:7007565",
        "tgn:7029392"
    ],
    "tgn:id":2745284,
    "tgn:name":"Vincentown Millpond",
    "tgn:placetype":[
        "aat:300006191"
    ]
},
  "bbox": [],
  "geometry": {"coordinates":[-74.75,39.9333],"type":"Point"}
}