<<<<<<< HEAD
{
  "id": 7356234,
  "type": "Feature",
  "properties": {
    "tgn:hierarchy":[
        "tgn:7356234",
        "tgn:1000001",
        "tgn:7005593",
        "tgn:7005560",
        "tgn:7029392"
    ],
    "tgn:id":7356234,
    "tgn:name":"Cerro Prieto",
    "tgn:placetype":[
        "aat:300008347"
    ]
},
  "bbox": [],
  "geometry": {"coordinates":[-99.616667,20.7],"type":"Point"}
}
=======
{"geometry":{"type":"Point","coordinates":[-99.616667,20.700000]},"type":"Feature","properties":{"hierarchy":["tgn:7356234","tgn:1000001","tgn:7005593","tgn:7005560","tgn:7029392"],"placetype":["aat:300008347"],"id":7356234,"name:xx":"Cerro Prieto"}}
>>>>>>> 03f74aca74312dbeaf24d7e61306dd6a786dc3d0
