<<<<<<< HEAD
{
  "id": 2336571,
  "type": "Feature",
  "properties": {
    "tgn:hierarchy":[
        "tgn:2336571",
        "tgn:1000001",
        "tgn:2002107",
        "tgn:7012149",
        "tgn:7007827",
        "tgn:7029392"
    ],
    "tgn:id":2336571,
    "tgn:name":"Four Lakes Basin",
    "tgn:placetype":[
        "aat:300386845"
    ]
},
  "bbox": [],
  "geometry": {"coordinates":[-110.75,40.6667],"type":"Point"}
}
=======
{"geometry":{"type":"Point","coordinates":[-110.750000,40.666700]},"type":"Feature","properties":{"hierarchy":["tgn:2336571","tgn:1000001","tgn:2002107","tgn:7012149","tgn:7007827","tgn:7029392"],"placetype":["aat:300386845"],"id":2336571,"name:xx":"Four Lakes Basin"}}
>>>>>>> 03f74aca74312dbeaf24d7e61306dd6a786dc3d0
