{
  "id": 2336571,
  "type": "Feature",
  "properties": {
    "tgn:hierarchy":[
        "tgn:2336571",
        "tgn:1000001",
        "tgn:2002107",
        "tgn:7012149",
        "tgn:7007827",
        "tgn:7029392"
    ],
    "tgn:id":2336571,
    "tgn:name":"Four Lakes Basin",
    "tgn:placetype":[
        "aat:300386845"
    ]
},
  "bbox": [],
  "geometry": {"coordinates":[-110.75,40.6667],"type":"Point"}
}