{
  "id": 7477184,
  "type": "Feature",
  "properties": {
    "tgn:hierarchy":[
        "tgn:7477184",
        "tgn:7488858",
        "tgn:1000004",
        "tgn:1000141",
        "tgn:7029392"
    ],
    "tgn:id":7477184,
    "tgn:name":"Guizikeng",
    "tgn:placetype":[
        "aat:300008347"
    ]
},
  "bbox": [],
  "geometry": {"coordinates":[120.893991,23.83094],"type":"Point"}
}