{
  "id": 2301156,
  "type": "Feature",
  "properties": {
    "tgn:hierarchy":[
        "tgn:2301156",
        "tgn:1000001",
        "tgn:7012149",
        "tgn:7029392"
    ],
    "tgn:id":2301156,
    "tgn:name":"Dunkard Fork",
    "tgn:placetype":[
        "aat:300008699"
    ]
},
  "bbox": [],
  "geometry": {"coordinates":[-80.4667,39.8833],"type":"Point"}
}