{
  "id": 7545248,
  "type": "Feature",
  "properties": {
    "tgn:hierarchy":[
        "tgn:7545248",
        "tgn:1000004",
        "tgn:7000198",
        "tgn:7016722",
        "tgn:7029392"
    ],
    "tgn:id":7545248,
    "tgn:name:en":"Bhelw\u0101hi Jh\u012bl",
    "tgn:placetype":[
        "aat:300008680"
    ]
},
  "bbox": [],
  "geometry": {"coordinates":[80.964464,25.902374],"type":"Point"}
}