{
  "id": 2381063,
  "type": "Feature",
  "properties": {
    "tgn:hierarchy":[
        "tgn:2381063",
        "tgn:1000001",
        "tgn:2000466",
        "tgn:7012149",
        "tgn:7007250",
        "tgn:7029392"
    ],
    "tgn:id":2381063,
    "tgn:name":"Hawkins Hollow",
    "tgn:placetype":[
        "aat:300008761"
    ]
},
  "bbox": [],
  "geometry": {"coordinates":[-111.6333,42.5333],"type":"Point"}
}