{
  "id": 7116647,
  "type": "Feature",
  "properties": {
    "tgn:hierarchy":[
        "tgn:7116647",
        "tgn:1000003",
        "tgn:7003682",
        "tgn:7000084",
        "tgn:7029392"
    ],
    "tgn:id":7116647,
    "tgn:name":"Osburger Hochwald",
    "tgn:placetype":[
        "aat:300008795"
    ]
},
  "bbox": [],
  "geometry": {"coordinates":[6.833333,49.666667],"type":"Point"}
}