{
  "id": 7051474,
  "type": "Feature",
  "properties": {
    "tgn:hierarchy":[
        "tgn:7051474",
        "tgn:7007850",
        "tgn:1003491",
        "tgn:1000003",
        "tgn:1000080",
        "tgn:7029392"
    ],
    "tgn:id":7051474,
    "tgn:name":"Pezzo, Punta",
    "tgn:placetype":[
        "aat:300386846"
    ]
},
  "bbox": [],
  "geometry": {"coordinates":[15.633333,38.233333],"type":"Point"}
}