{
  "id": 2603782,
  "type": "Feature",
  "properties": {
    "tgn:hierarchy":[
        "tgn:2603782",
        "tgn:1000001",
        "tgn:7012149",
        "tgn:2001762",
        "tgn:7007712",
        "tgn:7029392"
    ],
    "tgn:id":2603782,
    "tgn:name":"Quicktown",
    "tgn:placetype":[
        "aat:300008347"
    ]
},
  "bbox": [],
  "geometry": {"coordinates":[-80.8333,33.4833],"type":"Point"}
}