{
  "id": 7100974,
  "type": "Feature",
  "properties": {
    "tgn:hierarchy":[
        "tgn:7100974",
        "tgn:7003669",
        "tgn:1000003",
        "tgn:7000084",
        "tgn:7029392"
    ],
    "tgn:id":7100974,
    "tgn:name":"Sandbach",
    "tgn:placetype":[
        "aat:300008699"
    ]
},
  "bbox": [],
  "geometry": {"coordinates":[11.366667,47.466667],"type":"Point"}
}