<<<<<<< HEAD
{
  "id": 7477107,
  "type": "Feature",
  "properties": {
    "tgn:hierarchy":[
        "tgn:7477107",
        "tgn:1000004",
        "tgn:1000454",
        "tgn:1000141",
        "tgn:7029392"
    ],
    "tgn:id":7477107,
    "tgn:name":"Guishougu",
    "tgn:placetype":[
        "aat:300008347"
    ]
},
  "bbox": [],
  "geometry": {"coordinates":[121.948728,25.007304],"type":"Point"}
}
=======
{"geometry":{"type":"Point","coordinates":[121.948728,25.007304]},"type":"Feature","properties":{"hierarchy":["tgn:7477107","tgn:1000004","tgn:1000454","tgn:1000141","tgn:7029392"],"placetype":["aat:300008347"],"id":7477107,"name:xx":"Guishougu"}}
>>>>>>> 03f74aca74312dbeaf24d7e61306dd6a786dc3d0
