{
  "id": 2655470,
  "type": "Feature",
  "properties": {
    "tgn:hierarchy":[
        "tgn:2655470",
        "tgn:1000001",
        "tgn:7012149",
        "tgn:7007157",
        "tgn:1002956",
        "tgn:7029392"
    ],
    "tgn:id":2655470,
    "tgn:name":"Sharp Ditch",
    "tgn:placetype":[
        "aat:300006075"
    ]
},
  "bbox": [],
  "geometry": {"coordinates":[-119.2833,36.45],"type":"Point"}
}