<<<<<<< HEAD
{
  "id": 2403912,
  "type": "Feature",
  "properties": {
    "tgn:hierarchy":[
        "tgn:2403912",
        "tgn:1000001",
        "tgn:2000463",
        "tgn:7012149",
        "tgn:7007250",
        "tgn:7029392"
    ],
    "tgn:id":2403912,
    "tgn:name":"Howe Peak",
    "tgn:placetype":[
        "aat:300008798"
    ]
},
  "bbox": [],
  "geometry": {"coordinates":[-113.0833,43.7],"type":"Point"}
}
=======
{"geometry":{"type":"Point","coordinates":[-113.083300,43.700000]},"type":"Feature","properties":{"hierarchy":["tgn:2403912","tgn:1000001","tgn:2000463","tgn:7012149","tgn:7007250","tgn:7029392"],"placetype":["aat:300008798"],"id":2403912,"name:xx":"Howe Peak"}}
>>>>>>> 03f74aca74312dbeaf24d7e61306dd6a786dc3d0
