{
  "id": 2704883,
  "type": "Feature",
  "properties": {
    "tgn:hierarchy":[
        "tgn:2704883",
        "tgn:1000001",
        "tgn:7006451",
        "tgn:7012149",
        "tgn:2000097",
        "tgn:7029392"
    ],
    "tgn:id":2704883,
    "tgn:name":"Sunset Mine",
    "tgn:placetype":[
        "aat:300000390"
    ]
},
  "bbox": [],
  "geometry": {"coordinates":[-112.5667,33.95],"type":"Point"}
}