{
  "id": 7454490,
  "type": "Feature",
  "properties": {
    "tgn:hierarchy":[
        "tgn:7454490",
        "tgn:7002443",
        "tgn:7026278",
        "tgn:1000003",
        "tgn:7008591",
        "tgn:7029392"
    ],
    "tgn:id":7454490,
    "tgn:name:en":"Burton",
    "tgn:placetype":[
        "aat:300008347"
    ]
},
  "bbox": [],
  "geometry": {"coordinates":[-3.033333,53.25],"type":"Point"}
}