{
  "id": 2159327,
  "type": "Feature",
  "properties": {
    "tgn:hierarchy":[
        "tgn:2159327",
        "tgn:1000001",
        "tgn:7012149",
        "tgn:1002969",
        "tgn:7007826",
        "tgn:7029392"
    ],
    "tgn:id":2159327,
    "tgn:name":"Bee Branch",
    "tgn:placetype":[
        "aat:300008699"
    ]
},
  "bbox": [],
  "geometry": {"coordinates":[-95.8833,32.75],"type":"Point"}
}