{
  "id": 2308841,
  "type": "Feature",
  "properties": {
    "tgn:hierarchy":[
        "tgn:2308841",
        "tgn:1000001",
        "tgn:7012149",
        "tgn:2002384",
        "tgn:7007923",
        "tgn:7029392"
    ],
    "tgn:id":2308841,
    "tgn:name":"East Prong",
    "tgn:placetype":[
        "aat:300008798"
    ]
},
  "bbox": [],
  "geometry": {"coordinates":[-110.7833,43.7333],"type":"Point"}
}