{
  "id": 7544439,
  "type": "Feature",
  "properties": {
    "tgn:hierarchy":[
        "tgn:7544439",
        "tgn:7001242",
        "tgn:7016833",
        "tgn:1001335",
        "tgn:7029392"
    ],
    "tgn:id":7544439,
    "tgn:name":"Ad Dam\u0101yirah",
    "tgn:placetype":[
        "aat:300008347"
    ]
},
  "bbox": [],
  "geometry": {"coordinates":[31.247098,31.327659],"type":"Point"}
}