{
  "id": 7263046,
  "type": "Feature",
  "properties": {
    "tgn:hierarchy":[
        "tgn:7263046",
        "tgn:1000003",
        "tgn:7003626",
        "tgn:7016845",
        "tgn:7029392"
    ],
    "tgn:id":7263046,
    "tgn:name:nl":"Dassehaar",
    "tgn:placetype":[
        "aat:300387502"
    ]
},
  "bbox": [],
  "geometry": {"coordinates":[6.683333,52.283333],"type":"Point"}
}