{
  "id": 2528833,
  "type": "Feature",
  "properties": {
    "tgn:hierarchy":[
        "tgn:2528833",
        "tgn:1000001",
        "tgn:7012149",
        "tgn:1003030",
        "tgn:7007251",
        "tgn:7029392"
    ],
    "tgn:id":2528833,
    "tgn:name":"Mud Creek",
    "tgn:placetype":[
        "aat:300008706"
    ]
},
  "bbox": [],
  "geometry": {"coordinates":[-89.1333,42.3667],"type":"Point"}
}