<<<<<<< HEAD
{
  "id": 2258819,
  "type": "Feature",
  "properties": {
    "tgn:hierarchy":[
        "tgn:2258819",
        "tgn:1000001",
        "tgn:7012149",
        "tgn:2000225",
        "tgn:7007158",
        "tgn:7029392"
    ],
    "tgn:id":2258819,
    "tgn:name":"Cottonwood Creek",
    "tgn:placetype":[
        "aat:300008706"
    ]
},
  "bbox": [],
  "geometry": {"coordinates":[-108.1667,37.35],"type":"Point"}
}
=======
{"geometry":{"type":"Point","coordinates":[-108.166700,37.350000]},"type":"Feature","properties":{"hierarchy":["tgn:2258819","tgn:1000001","tgn:7012149","tgn:2000225","tgn:7007158","tgn:7029392"],"placetype":["aat:300008706"],"id":2258819,"name:xx":"Cottonwood Creek"}}
>>>>>>> 03f74aca74312dbeaf24d7e61306dd6a786dc3d0
