{
  "id": 2258819,
  "type": "Feature",
  "properties": {
    "tgn:hierarchy":[
        "tgn:2258819",
        "tgn:1000001",
        "tgn:7012149",
        "tgn:2000225",
        "tgn:7007158",
        "tgn:7029392"
    ],
    "tgn:id":2258819,
    "tgn:name":"Cottonwood Creek",
    "tgn:placetype":[
        "aat:300008706"
    ]
},
  "bbox": [],
  "geometry": {"coordinates":[-108.1667,37.35],"type":"Point"}
}