{
  "id": 2262671,
  "type": "Feature",
  "properties": {
    "tgn:hierarchy":[
        "tgn:2262671",
        "tgn:1000001",
        "tgn:2001429",
        "tgn:7012149",
        "tgn:7007566",
        "tgn:7029392"
    ],
    "tgn:id":2262671,
    "tgn:name":"Cow Springs Draw",
    "tgn:placetype":[
        "aat:300008761"
    ]
},
  "bbox": [],
  "geometry": {"coordinates":[-108.8667,34.0167],"type":"Point"}
}