{
  "id": 7124041,
  "type": "Feature",
  "properties": {
    "tgn:hierarchy":[
        "tgn:7124041",
        "tgn:1000003",
        "tgn:7003685",
        "tgn:7000084",
        "tgn:7029392"
    ],
    "tgn:id":7124041,
    "tgn:name":"Neu Buchwalde",
    "tgn:placetype":[
        "aat:300008347"
    ]
},
  "bbox": [],
  "geometry": {"coordinates":[14.283333,51.366667],"type":"Point"}
}