{
  "id": 2445421,
  "type": "Feature",
  "properties": {
    "tgn:hierarchy":[
        "tgn:2445421",
        "tgn:7002659",
        "tgn:1000001",
        "tgn:7012149",
        "tgn:2000056",
        "tgn:7029392"
    ],
    "tgn:id":2445421,
    "tgn:name":"Lenora, Lake",
    "tgn:placetype":[
        "aat:300006191"
    ]
},
  "bbox": [],
  "geometry": {"coordinates":[-85.2333,32.3333],"type":"Point"}
}