{
  "id": 2401155,
  "type": "Feature",
  "properties": {
    "tgn:hierarchy":[
        "tgn:2401155",
        "tgn:1000001",
        "tgn:2001479",
        "tgn:7012149",
        "tgn:7007709",
        "tgn:7029392"
    ],
    "tgn:id":2401155,
    "tgn:name":"Horseford Creek",
    "tgn:placetype":[
        "aat:300008706"
    ]
},
  "bbox": [],
  "geometry": {"coordinates":[-81.35,35.7333],"type":"Point"}
}