<<<<<<< HEAD
{
  "id": 2401155,
  "type": "Feature",
  "properties": {
    "tgn:hierarchy":[
        "tgn:2401155",
        "tgn:1000001",
        "tgn:2001479",
        "tgn:7012149",
        "tgn:7007709",
        "tgn:7029392"
    ],
    "tgn:id":2401155,
    "tgn:name":"Horseford Creek",
    "tgn:placetype":[
        "aat:300008706"
    ]
},
  "bbox": [],
  "geometry": {"coordinates":[-81.35,35.7333],"type":"Point"}
}
=======
{"geometry":{"type":"Point","coordinates":[-81.350000,35.733300]},"type":"Feature","properties":{"hierarchy":["tgn:2401155","tgn:1000001","tgn:2001479","tgn:7012149","tgn:7007709","tgn:7029392"],"placetype":["aat:300008706"],"id":2401155,"name:xx":"Horseford Creek"}}
>>>>>>> 03f74aca74312dbeaf24d7e61306dd6a786dc3d0
