{
  "id": 2749271,
  "type": "Feature",
  "properties": {
    "tgn:hierarchy":[
        "tgn:2749271",
        "tgn:1000001",
        "tgn:7012149",
        "tgn:2000823",
        "tgn:7007255",
        "tgn:7029392"
    ],
    "tgn:id":2749271,
    "tgn:name":"Waller Hill",
    "tgn:placetype":[
        "aat:300008798"
    ]
},
  "bbox": [],
  "geometry": {"coordinates":[-88.4167,36.85],"type":"Point"}
}