{
  "id": 7559873,
  "type": "Feature",
  "properties": {
    "tgn:hierarchy":[
        "tgn:7559873",
        "tgn:1000004",
        "tgn:7000198",
        "tgn:7016722",
        "tgn:7029392"
    ],
    "tgn:id":7559873,
    "tgn:name:en":"Makundpura",
    "tgn:placetype":[
        "aat:300008347"
    ]
},
  "bbox": [],
  "geometry": {"coordinates":[79.174497,26.965133],"type":"Point"}
}