{
  "id": 2476264,
  "type": "Feature",
  "properties": {
    "tgn:hierarchy":[
        "tgn:2476264",
        "tgn:1000001",
        "tgn:7012149",
        "tgn:1002928",
        "tgn:7007706",
        "tgn:7029392"
    ],
    "tgn:id":2476264,
    "tgn:name":"Luna Lake",
    "tgn:placetype":[
        "aat:300008680"
    ]
},
  "bbox": [],
  "geometry": {"coordinates":[-81.6167,40.9167],"type":"Point"}
}