{
  "id": 7380526,
  "type": "Feature",
  "properties": {
    "tgn:hierarchy":[
        "tgn:7380526",
        "tgn:1000001",
        "tgn:1001960",
        "tgn:7005560",
        "tgn:7029392"
    ],
    "tgn:id":7380526,
    "tgn:name":"Los Janos",
    "tgn:placetype":[
        "aat:300008347"
    ]
},
  "bbox": [],
  "geometry": {"coordinates":[-110.85,30.833333],"type":"Point"}
}