{
  "id": 2637342,
  "type": "Feature",
  "properties": {
    "tgn:hierarchy":[
        "tgn:2637342",
        "tgn:1000001",
        "tgn:7012149",
        "tgn:2001969",
        "tgn:7007826",
        "tgn:7029392"
    ],
    "tgn:id":2637342,
    "tgn:name":"Saint John Tank",
    "tgn:placetype":[
        "aat:300006191"
    ]
},
  "bbox": [],
  "geometry": {"coordinates":[-104.5167,31.4333],"type":"Point"}
}