{
  "id": 7526613,
  "type": "Feature",
  "properties": {
    "tgn:hierarchy":[
        "tgn:7526613",
        "tgn:7001242",
        "tgn:7016833",
        "tgn:1001091",
        "tgn:7029392"
    ],
    "tgn:id":7526613,
    "tgn:name":"Misallat al Ma\u0163ar\u012byah",
    "tgn:placetype":[
        "aat:300006958"
    ]
},
  "bbox": [],
  "geometry": {"coordinates":[31.307502,30.129352],"type":"Point"}
}