{
  "id": 2667811,
  "type": "Feature",
  "properties": {
    "tgn:hierarchy":[
        "tgn:2667811",
        "tgn:1000001",
        "tgn:7012149",
        "tgn:2000985",
        "tgn:7007520",
        "tgn:7029392"
    ],
    "tgn:id":2667811,
    "tgn:name":"Skunk Creek",
    "tgn:placetype":[
        "aat:300008706"
    ]
},
  "bbox": [],
  "geometry": {"coordinates":[-83.9667,44.3833],"type":"Point"}
}