{
  "id": 2295025,
  "type": "Feature",
  "properties": {
    "tgn:hierarchy":[
        "tgn:2295025",
        "tgn:1000001",
        "tgn:1002194",
        "tgn:7012149",
        "tgn:7007710",
        "tgn:7029392"
    ],
    "tgn:id":2295025,
    "tgn:name":"Draper Ridge",
    "tgn:placetype":[
        "aat:300266640"
    ]
},
  "bbox": [],
  "geometry": {"coordinates":[-76.6333,41.9667],"type":"Point"}
}