{
  "id": 2770283,
  "type": "Feature",
  "properties": {
    "tgn:hierarchy":[
        "tgn:2770283",
        "tgn:1000001",
        "tgn:2001432",
        "tgn:7012149",
        "tgn:7007566",
        "tgn:7029392"
    ],
    "tgn:id":2770283,
    "tgn:name":"Wild Horse Arroyo",
    "tgn:placetype":[
        "aat:300008699"
    ]
},
  "bbox": [],
  "geometry": {"coordinates":[-104.0667,36.8833],"type":"Point"}
}