{
  "id": 2677506,
  "type": "Feature",
  "properties": {
    "tgn:hierarchy":[
        "tgn:2677506",
        "tgn:1000001",
        "tgn:7012149",
        "tgn:2001858",
        "tgn:7007825",
        "tgn:7029392"
    ],
    "tgn:id":2677506,
    "tgn:name":"South Charlotte Mine",
    "tgn:placetype":[
        "aat:300000390"
    ]
},
  "bbox": [],
  "geometry": {"coordinates":[-87.3167,36.1667],"type":"Point"}
}