{
  "id": 7566074,
  "type": "Feature",
  "properties": {
    "tgn:hierarchy":[
        "tgn:7566074",
        "tgn:1000004",
        "tgn:7000198",
        "tgn:1001894",
        "tgn:7029392"
    ],
    "tgn:id":7566074,
    "tgn:name:en":"Sarkana",
    "tgn:placetype":[
        "aat:300008347"
    ]
},
  "bbox": [],
  "geometry": {"coordinates":[79.122769,24.607682],"type":"Point"}
}