{
  "id": 7123816,
  "type": "Feature",
  "properties": {
    "tgn:hierarchy":[
        "tgn:7123816",
        "tgn:7003669",
        "tgn:1000003",
        "tgn:7000084",
        "tgn:7029392"
    ],
    "tgn:id":7123816,
    "tgn:name":"Neudeck",
    "tgn:placetype":[
        "aat:300000206"
    ]
},
  "bbox": [],
  "geometry": {"coordinates":[12.183333,48.416667],"type":"Point"}
}