{
  "id": 7410683,
  "type": "Feature",
  "properties": {
    "tgn:hierarchy":[
        "tgn:7410683",
        "tgn:7005580",
        "tgn:1000001",
        "tgn:7005560",
        "tgn:7029392"
    ],
    "tgn:id":7410683,
    "tgn:name":"Noyola",
    "tgn:placetype":[
        "aat:300008347"
    ]
},
  "bbox": [],
  "geometry": {"coordinates":[-93.75,16.041667],"type":"Point"}
}