{
  "id": 7576810,
  "type": "Feature",
  "properties": {
    "tgn:hierarchy":[
        "tgn:7576810",
        "tgn:1000004",
        "tgn:7000198",
        "tgn:7001797",
        "tgn:7029392"
    ],
    "tgn:id":7576810,
    "tgn:name:en":"Kottagudi",
    "tgn:placetype":[
        "aat:300008347"
    ]
},
  "bbox": [],
  "geometry": {"coordinates":[77.266667,10.066667],"type":"Point"}
}