<<<<<<< HEAD
{
  "id": 2154861,
  "type": "Feature",
  "properties": {
    "tgn:hierarchy":[
        "tgn:2154861",
        "tgn:1000001",
        "tgn:7012149",
        "tgn:2000837",
        "tgn:7007255",
        "tgn:7029392"
    ],
    "tgn:id":2154861,
    "tgn:name":"Bear Hollow",
    "tgn:placetype":[
        "aat:300008761"
    ]
},
  "bbox": [],
  "geometry": {"coordinates":[-82.3167,37.3333],"type":"Point"}
}
=======
{"geometry":{"type":"Point","coordinates":[-82.316700,37.333300]},"type":"Feature","properties":{"hierarchy":["tgn:2154861","tgn:1000001","tgn:7012149","tgn:2000837","tgn:7007255","tgn:7029392"],"placetype":["aat:300008761"],"id":2154861,"name:xx":"Bear Hollow"}}
>>>>>>> 03f74aca74312dbeaf24d7e61306dd6a786dc3d0
