{
  "id": 7014390,
  "type": "Feature",
  "properties": {
    "tgn:hierarchy":[
        "tgn:7014390",
        "tgn:1000001",
        "tgn:1002775",
        "tgn:7012149",
        "tgn:7007565",
        "tgn:7029392"
    ],
    "tgn:id":7014390,
    "tgn:name":"Paterson",
    "tgn:placetype":[
        "aat:300008347",
        "aat:300008416",
        "aat:300008389",
        "aat:300387308",
        "aat:300005135",
        "aat:300264742",
        "aat:300387302",
        "aat:300387312",
        "aat:300387291"
    ]
},
  "bbox": [],
  "geometry": {"coordinates":[-74.1667,40.9167],"type":"Point"}
}