{
  "id": 7362568,
  "type": "Feature",
  "properties": {
    "tgn:hierarchy":[
        "tgn:7362568",
        "tgn:7005585",
        "tgn:1000001",
        "tgn:7005560",
        "tgn:7029392"
    ],
    "tgn:id":7362568,
    "tgn:name":"El Carrizo",
    "tgn:placetype":[
        "aat:300008347"
    ]
},
  "bbox": [],
  "geometry": {"coordinates":[-101.85,18.166667],"type":"Point"}
}