{
  "id": 2355992,
  "type": "Feature",
  "properties": {
    "tgn:hierarchy":[
        "tgn:2355992",
        "tgn:1000001",
        "tgn:7012149",
        "tgn:2000285",
        "tgn:7007240",
        "tgn:7029392"
    ],
    "tgn:id":2355992,
    "tgn:name":"Goose Pond",
    "tgn:placetype":[
        "aat:300008680"
    ]
},
  "bbox": [],
  "geometry": {"coordinates":[-86.85,30.8833],"type":"Point"}
}