{
  "id": 7469968,
  "type": "Feature",
  "properties": {
    "tgn:hierarchy":[
        "tgn:7469968",
        "tgn:1000004",
        "tgn:7004300",
        "tgn:1000141",
        "tgn:7029392"
    ],
    "tgn:id":7469968,
    "tgn:name":"Qimei Xiang",
    "tgn:placetype":[
        "aat:300387173"
    ]
},
  "bbox": [],
  "geometry": {"coordinates":[119.366667,23.266667],"type":"Point"}
}