{
  "id": 7210082,
  "type": "Feature",
  "properties": {
    "tgn:hierarchy":[
        "tgn:7210082",
        "tgn:1000003",
        "tgn:7003676",
        "tgn:7000084",
        "tgn:7029392"
    ],
    "tgn:id":7210082,
    "tgn:name":"Bardenfleth",
    "tgn:placetype":[
        "aat:300008347"
    ]
},
  "bbox": [],
  "geometry": {"coordinates":[8.366667,53.233333],"type":"Point"}
}