{
  "id": 2511723,
  "type": "Feature",
  "properties": {
    "tgn:hierarchy":[
        "tgn:2511723",
        "tgn:1000001",
        "tgn:7012149",
        "tgn:1002647",
        "tgn:7007919",
        "tgn:7029392"
    ],
    "tgn:id":2511723,
    "tgn:name":"Milford Haven",
    "tgn:placetype":[
        "aat:300132316"
    ]
},
  "bbox": [],
  "geometry": {"coordinates":[-76.2667,37.4667],"type":"Point"}
}