{
  "id": 7057482,
  "type": "Feature",
  "properties": {
    "tgn:hierarchy":[
        "tgn:7057482",
        "tgn:7002996",
        "tgn:1000003",
        "tgn:7002997",
        "tgn:1000080",
        "tgn:7029392"
    ],
    "tgn:id":7057482,
    "tgn:name":"Cacnere",
    "tgn:placetype":[
        "aat:300008347"
    ]
},
  "bbox": [],
  "geometry": {"coordinates":[11.933333,45.833333],"type":"Point"}
}