{
  "id": 2001544,
  "type": "Feature",
  "properties": {
    "tgn:hierarchy":[
        "tgn:2001544",
        "tgn:1000001",
        "tgn:7012149",
        "tgn:7007709",
        "tgn:7029392"
    ],
    "tgn:id":2001544,
    "tgn:name":"Transylvania",
    "tgn:placetype":[
        "aat:300387145",
        "aat:300000771"
    ]
},
  "bbox": [],
  "geometry": {"coordinates":[-82.7833,35.2167],"type":"Point"}
}