<<<<<<< HEAD
{
  "id": 7022361,
  "type": "Feature",
  "properties": {
    "tgn:hierarchy":[
        "tgn:7022361",
        "tgn:1000001",
        "tgn:7012149",
        "tgn:7013961",
        "tgn:7029392"
    ],
    "tgn:id":7022361,
    "tgn:name":"Beech Fork Lake",
    "tgn:placetype":[
        "aat:300006191"
    ]
},
  "bbox": [],
  "geometry": {"coordinates":[-82.4167,38.3],"type":"Point"}
}
=======
{"geometry":{"type":"Point","coordinates":[-82.416700,38.300000]},"type":"Feature","properties":{"hierarchy":["tgn:7022361","tgn:1000001","tgn:7012149","tgn:7013961","tgn:7029392"],"placetype":["aat:300006191"],"id":7022361,"name:xx":"Beech Fork Lake"}}
>>>>>>> 03f74aca74312dbeaf24d7e61306dd6a786dc3d0
