{
  "id": 2215870,
  "type": "Feature",
  "properties": {
    "tgn:hierarchy":[
        "tgn:2215870",
        "tgn:1000001",
        "tgn:7006451",
        "tgn:7012149",
        "tgn:2000097",
        "tgn:7029392"
    ],
    "tgn:id":2215870,
    "tgn:name":"Camelot Luxury Homes",
    "tgn:placetype":[
        "aat:300008347"
    ]
},
  "bbox": [],
  "geometry": {"coordinates":[-111.9167,33.35],"type":"Point"}
}