{
  "id": 7055983,
  "type": "Feature",
  "properties": {
    "tgn:hierarchy":[
        "tgn:7055983",
        "tgn:1001730",
        "tgn:1000003",
        "tgn:7003121",
        "tgn:1000080",
        "tgn:7029392"
    ],
    "tgn:id":7055983,
    "tgn:name":"Ollastra Simaxis",
    "tgn:placetype":[
        "aat:300008347"
    ]
},
  "bbox": [],
  "geometry": {"coordinates":[8.734167,39.952222],"type":"Point"}
}