{
  "id": 2079692,
  "type": "Feature",
  "properties": {
    "tgn:hierarchy":[
        "tgn:2079692",
        "tgn:1000001",
        "tgn:1002274",
        "tgn:7012149",
        "tgn:7007706",
        "tgn:7029392"
    ],
    "tgn:id":2079692,
    "tgn:name":"Garden Acres",
    "tgn:placetype":[
        "aat:300008347"
    ]
},
  "bbox": [],
  "geometry": {"coordinates":[-83.7333,39.9167],"type":"Point"}
}