{
  "id": 2586819,
  "type": "Feature",
  "properties": {
    "tgn:hierarchy":[
        "tgn:2586819",
        "tgn:1000001",
        "tgn:1002184",
        "tgn:7012149",
        "tgn:7007252",
        "tgn:7029392"
    ],
    "tgn:id":2586819,
    "tgn:name":"Placid, Lake",
    "tgn:placetype":[
        "aat:300006191"
    ]
},
  "bbox": [],
  "geometry": {"coordinates":[-85.3167,40.4333],"type":"Point"}
}