{
  "id": 7485203,
  "type": "Feature",
  "properties": {
    "tgn:hierarchy":[
        "tgn:7485203",
        "tgn:1000004",
        "tgn:7491221",
        "tgn:1000141",
        "tgn:7029392"
    ],
    "tgn:id":7485203,
    "tgn:name":"Nanxing Qiao",
    "tgn:placetype":[
        "aat:300007836"
    ]
},
  "bbox": [],
  "geometry": {"coordinates":[120.888889,22.306944],"type":"Point"}
}