{
  "id": 2081931,
  "type": "Feature",
  "properties": {
    "tgn:hierarchy":[
        "tgn:2081931",
        "tgn:1000001",
        "tgn:7012149",
        "tgn:1002607",
        "tgn:7007706",
        "tgn:7029392"
    ],
    "tgn:id":2081931,
    "tgn:name":"South Amherst",
    "tgn:placetype":[
        "aat:300008347"
    ]
},
  "bbox": [],
  "geometry": {"coordinates":[-82.25,41.35],"type":"Point"}
}