{
  "id": 2460245,
  "type": "Feature",
  "properties": {
    "tgn:hierarchy":[
        "tgn:2460245",
        "tgn:1000001",
        "tgn:7012149",
        "tgn:1002709",
        "tgn:7007826",
        "tgn:7029392"
    ],
    "tgn:id":2460245,
    "tgn:name":"Little Rush Creek",
    "tgn:placetype":[
        "aat:300008706"
    ]
},
  "bbox": [],
  "geometry": {"coordinates":[-96.3833,32.1833],"type":"Point"}
}