{
  "id": 2345421,
  "type": "Feature",
  "properties": {
    "tgn:hierarchy":[
        "tgn:2345421",
        "tgn:1000001",
        "tgn:7012149",
        "tgn:7015666",
        "tgn:7007825",
        "tgn:7029392"
    ],
    "tgn:id":2345421,
    "tgn:name":"Garner Hill",
    "tgn:placetype":[
        "aat:300008798"
    ]
},
  "bbox": [],
  "geometry": {"coordinates":[-87.25,35.85],"type":"Point"}
}