{
  "id": 2755485,
  "type": "Feature",
  "properties": {
    "tgn:hierarchy":[
        "tgn:2755485",
        "tgn:1000001",
        "tgn:7012149",
        "tgn:2001508",
        "tgn:7007709",
        "tgn:7029392"
    ],
    "tgn:id":2755485,
    "tgn:name":"Webster Creek",
    "tgn:placetype":[
        "aat:300008706"
    ]
},
  "bbox": [],
  "geometry": {"coordinates":[-83.15,35.2667],"type":"Point"}
}