<<<<<<< HEAD
{
  "id": 2333560,
  "type": "Feature",
  "properties": {
    "tgn:hierarchy":[
        "tgn:2333560",
        "tgn:1000001",
        "tgn:7012149",
        "tgn:2002353",
        "tgn:7007922",
        "tgn:7029392"
    ],
    "tgn:id":2333560,
    "tgn:name":"Folson Island",
    "tgn:placetype":[
        "aat:300008791"
    ]
},
  "bbox": [],
  "geometry": {"coordinates":[-91.0333,46.0],"type":"Point"}
}
=======
{"geometry":{"type":"Point","coordinates":[-91.033300,46.000000]},"type":"Feature","properties":{"hierarchy":["tgn:2333560","tgn:1000001","tgn:7012149","tgn:2002353","tgn:7007922","tgn:7029392"],"placetype":["aat:300008791"],"id":2333560,"name:xx":"Folson Island"}}
>>>>>>> 03f74aca74312dbeaf24d7e61306dd6a786dc3d0
