<<<<<<< HEAD
{
  "id": 2155829,
  "type": "Feature",
  "properties": {
    "tgn:hierarchy":[
        "tgn:2155829",
        "tgn:1000001",
        "tgn:7012149",
        "tgn:7007157",
        "tgn:1002748",
        "tgn:7029392"
    ],
    "tgn:id":2155829,
    "tgn:name":"Bear Trap Canyon",
    "tgn:placetype":[
        "aat:300008761"
    ]
},
  "bbox": [],
  "geometry": {"coordinates":[-117.5667,33.7],"type":"Point"}
}
=======
{"geometry":{"type":"Point","coordinates":[-117.566700,33.700000]},"type":"Feature","properties":{"hierarchy":["tgn:2155829","tgn:1000001","tgn:7012149","tgn:7007157","tgn:1002748","tgn:7029392"],"placetype":["aat:300008761"],"id":2155829,"name:xx":"Bear Trap Canyon"}}
>>>>>>> 03f74aca74312dbeaf24d7e61306dd6a786dc3d0
