{
  "id": 2209633,
  "type": "Feature",
  "properties": {
    "tgn:hierarchy":[
        "tgn:2209633",
        "tgn:1000001",
        "tgn:2001483",
        "tgn:7012149",
        "tgn:7007709",
        "tgn:7029392"
    ],
    "tgn:id":2209633,
    "tgn:name":"Burrell Cove",
    "tgn:placetype":[
        "aat:300132316"
    ]
},
  "bbox": [],
  "geometry": {"coordinates":[-83.7667,34.9833],"type":"Point"}
}