{
  "id": 1076689,
  "type": "Feature",
  "properties": {
    "tgn:hierarchy":[
        "tgn:1076689",
        "tgn:1000004",
        "tgn:7000198",
        "tgn:7001797",
        "tgn:7029392"
    ],
    "tgn:id":1076689,
    "tgn:name:en":"R\u0101man\u0101thapuram",
    "tgn:placetype":[
        "aat:300008347"
    ]
},
  "bbox": [],
  "geometry": {"coordinates":[78.833333,9.383333],"type":"Point"}
}