<<<<<<< HEAD
{
  "id": 7179040,
  "type": "Feature",
  "properties": {
    "tgn:hierarchy":[
        "tgn:7179040",
        "tgn:1000003",
        "tgn:7003676",
        "tgn:7000084",
        "tgn:7029392"
    ],
    "tgn:id":7179040,
    "tgn:name":"Gudendorf",
    "tgn:placetype":[
        "aat:300008347"
    ]
},
  "bbox": [],
  "geometry": {"coordinates":[8.683333,53.8],"type":"Point"}
}
=======
{"geometry":{"type":"Point","coordinates":[8.683333,53.800000]},"type":"Feature","properties":{"hierarchy":["tgn:7179040","tgn:1000003","tgn:7003676","tgn:7000084","tgn:7029392"],"placetype":["aat:300008347"],"id":7179040,"name:xx":"Gudendorf"}}
>>>>>>> 03f74aca74312dbeaf24d7e61306dd6a786dc3d0
