{
  "id": 7521101,
  "type": "Feature",
  "properties": {
    "tgn:hierarchy":[
        "tgn:7521101",
        "tgn:7001242",
        "tgn:7016833",
        "tgn:1001080",
        "tgn:7029392"
    ],
    "tgn:id":7521101,
    "tgn:name:en":"Al Ma\u1e29samah al Qad\u012bmah",
    "tgn:placetype":[
        "aat:300008347"
    ]
},
  "bbox": [],
  "geometry": {"coordinates":[32.024418,30.546498],"type":"Point"}
}