{
  "id": 2220539,
  "type": "Feature",
  "properties": {
    "tgn:hierarchy":[
        "tgn:2220539",
        "tgn:7006450",
        "tgn:1000001",
        "tgn:2124012",
        "tgn:7012149",
        "tgn:7029392"
    ],
    "tgn:id":2220539,
    "tgn:name":"Cape Nuniliak",
    "tgn:placetype":[
        "aat:300008850"
    ]
},
  "bbox": [],
  "geometry": {"coordinates":[-153.2167,58.15],"type":"Point"}
}