{
  "id": 2703951,
  "type": "Feature",
  "properties": {
    "tgn:hierarchy":[
        "tgn:2703951",
        "tgn:1000001",
        "tgn:7012149",
        "tgn:2002287",
        "tgn:7013961",
        "tgn:7029392"
    ],
    "tgn:id":2703951,
    "tgn:name":"Sunday Lick Run",
    "tgn:placetype":[
        "aat:300008699"
    ]
},
  "bbox": [],
  "geometry": {"coordinates":[-80.05,38.1667],"type":"Point"}
}