<<<<<<< HEAD
{
  "id": 2251132,
  "type": "Feature",
  "properties": {
    "tgn:hierarchy":[
        "tgn:2251132",
        "tgn:1000001",
        "tgn:7012149",
        "tgn:1002518",
        "tgn:7007568",
        "tgn:7029392"
    ],
    "tgn:id":2251132,
    "tgn:name":"Colwell Hill",
    "tgn:placetype":[
        "aat:300008798"
    ]
},
  "bbox": [],
  "geometry": {"coordinates":[-76.1833,43.6833],"type":"Point"}
}
=======
{"geometry":{"type":"Point","coordinates":[-76.183300,43.683300]},"type":"Feature","properties":{"hierarchy":["tgn:2251132","tgn:1000001","tgn:7012149","tgn:1002518","tgn:7007568","tgn:7029392"],"placetype":["aat:300008798"],"id":2251132,"name:xx":"Colwell Hill"}}
>>>>>>> 03f74aca74312dbeaf24d7e61306dd6a786dc3d0
