{
  "id": 1080607,
  "type": "Feature",
  "properties": {
    "tgn:hierarchy":[
        "tgn:1080607",
        "tgn:1001015",
        "tgn:7000897",
        "tgn:1000004",
        "tgn:1000120",
        "tgn:7029392"
    ],
    "tgn:id":1080607,
    "tgn:name":"Konk\u014d",
    "tgn:placetype":[
        "aat:300008347"
    ]
},
  "bbox": [],
  "geometry": {"coordinates":[133.6167,34.5333],"type":"Point"}
}