<<<<<<< HEAD
{
  "id": 7484338,
  "type": "Feature",
  "properties": {
    "tgn:hierarchy":[
        "tgn:7484338",
        "tgn:7468018",
        "tgn:1000004",
        "tgn:1000141",
        "tgn:7029392"
    ],
    "tgn:id":7484338,
    "tgn:name":"Binlangzhaizi",
    "tgn:placetype":[
        "aat:300008347"
    ]
},
  "bbox": [],
  "geometry": {"coordinates":[120.479722,23.431944],"type":"Point"}
}
=======
{"geometry":{"type":"Point","coordinates":[120.479722,23.431944]},"type":"Feature","properties":{"hierarchy":["tgn:7484338","tgn:7468018","tgn:1000004","tgn:1000141","tgn:7029392"],"placetype":["aat:300008347"],"id":7484338,"name:xx":"Binlangzhaizi"}}
>>>>>>> 03f74aca74312dbeaf24d7e61306dd6a786dc3d0
