{
  "id": 7155946,
  "type": "Feature",
  "properties": {
    "tgn:hierarchy":[
        "tgn:7155946",
        "tgn:7003669",
        "tgn:1000003",
        "tgn:7000084",
        "tgn:7029392"
    ],
    "tgn:id":7155946,
    "tgn:name":"Kirch-Berg",
    "tgn:placetype":[
        "aat:300008795"
    ]
},
  "bbox": [],
  "geometry": {"coordinates":[11.633333,47.766667],"type":"Point"}
}