{
  "id": 7011024,
  "type": "Feature",
  "properties": {
    "tgn:hierarchy":[
        "tgn:7011024",
        "tgn:7011330",
        "tgn:7002674",
        "tgn:1000003",
        "tgn:1000074",
        "tgn:7029392"
    ],
    "tgn:id":7011024,
    "tgn:name:en":"Patmos",
    "tgn:placetype":[
        "aat:300008791"
    ]
},
  "bbox": [],
  "geometry": {"coordinates":[26.55,37.333333],"type":"Point"}
}