{
  "id": 7396916,
  "type": "Feature",
  "properties": {
    "tgn:hierarchy":[
        "tgn:7396916",
        "tgn:7005580",
        "tgn:1000001",
        "tgn:7005560",
        "tgn:7029392"
    ],
    "tgn:id":7396916,
    "tgn:name":"San Ram\u00f3n",
    "tgn:placetype":[
        "aat:300008347"
    ]
},
  "bbox": [],
  "geometry": {"coordinates":[-93.266667,16.25],"type":"Point"}
}