{
  "id": 1014978,
  "type": "Feature",
  "properties": {
    "tgn:hierarchy":[
        "tgn:1014978",
        "tgn:7005685",
        "tgn:1000001",
        "tgn:7013154",
        "tgn:7029392"
    ],
    "tgn:id":1014978,
    "tgn:name":"Nortonville",
    "tgn:placetype":[
        "aat:300008347"
    ]
},
  "bbox": [],
  "geometry": {"coordinates":[-79.7333,43.7167],"type":"Point"}
}