{
  "id": 7550575,
  "type": "Feature",
  "properties": {
    "tgn:hierarchy":[
        "tgn:7550575",
        "tgn:1000004",
        "tgn:7000198",
        "tgn:1001977",
        "tgn:7029392"
    ],
    "tgn:id":7550575,
    "tgn:name:en":"Dalsingp\u0101ra",
    "tgn:placetype":[
        "aat:300007783"
    ]
},
  "bbox": [],
  "geometry": {"coordinates":[89.363368,26.779938],"type":"Point"}
}