{
  "id": 2350814,
  "type": "Feature",
  "properties": {
    "tgn:hierarchy":[
        "tgn:2350814",
        "tgn:1000001",
        "tgn:7012149",
        "tgn:7007710",
        "tgn:7029392"
    ],
    "tgn:id":2350814,
    "tgn:name":"Glade Run",
    "tgn:placetype":[
        "aat:300008699"
    ]
},
  "bbox": [],
  "geometry": {"coordinates":[-79.95,40.6667],"type":"Point"}
}