{
  "id": 7387566,
  "type": "Feature",
  "properties": {
    "tgn:hierarchy":[
        "tgn:7387566",
        "tgn:7005581",
        "tgn:1000001",
        "tgn:7005560",
        "tgn:7029392"
    ],
    "tgn:id":7387566,
    "tgn:name":"Pared",
    "tgn:placetype":[
        "aat:300008347"
    ]
},
  "bbox": [],
  "geometry": {"coordinates":[-105.916667,31.283333],"type":"Point"}
}