{
  "id": 1060870,
  "type": "Feature",
  "properties": {
    "tgn:hierarchy":[
        "tgn:1060870",
        "tgn:7012256",
        "tgn:1000004",
        "tgn:7006661",
        "tgn:7029392"
    ],
    "tgn:id":1060870,
    "tgn:name":"Uzunkuduk",
    "tgn:placetype":[
        "aat:300008347"
    ]
},
  "bbox": [],
  "geometry": {"coordinates":[67.1833,40.55],"type":"Point"}
}