{
  "id": 2385993,
  "type": "Feature",
  "properties": {
    "tgn:hierarchy":[
        "tgn:2385993",
        "tgn:1000001",
        "tgn:7012149",
        "tgn:7007254",
        "tgn:7029392"
    ],
    "tgn:id":2385993,
    "tgn:name":"Henry Creek",
    "tgn:placetype":[
        "aat:300008706"
    ]
},
  "bbox": [],
  "geometry": {"coordinates":[-97.6667,39.35],"type":"Point"}
}