{
  "id": 2512284,
  "type": "Feature",
  "properties": {
    "tgn:hierarchy":[
        "tgn:2512284",
        "tgn:1000001",
        "tgn:7012149",
        "tgn:1002961",
        "tgn:7007568",
        "tgn:7029392"
    ],
    "tgn:id":2512284,
    "tgn:name":"Mill Brook",
    "tgn:placetype":[
        "aat:300008699"
    ]
},
  "bbox": [],
  "geometry": {"coordinates":[-74.2833,41.7833],"type":"Point"}
}