<<<<<<< HEAD
{
  "id": 2253203,
  "type": "Feature",
  "properties": {
    "tgn:hierarchy":[
        "tgn:2253203",
        "tgn:1000001",
        "tgn:2001260",
        "tgn:7012149",
        "tgn:7007524",
        "tgn:7029392"
    ],
    "tgn:id":2253203,
    "tgn:name":"Continental Spring",
    "tgn:placetype":[
        "aat:300008697"
    ]
},
  "bbox": [],
  "geometry": {"coordinates":[-112.75,44.5],"type":"Point"}
}
=======
{"geometry":{"type":"Point","coordinates":[-112.750000,44.500000]},"type":"Feature","properties":{"hierarchy":["tgn:2253203","tgn:1000001","tgn:2001260","tgn:7012149","tgn:7007524","tgn:7029392"],"placetype":["aat:300008697"],"id":2253203,"name:xx":"Continental Spring"}}
>>>>>>> 03f74aca74312dbeaf24d7e61306dd6a786dc3d0
