{
  "id": 2185453,
  "type": "Feature",
  "properties": {
    "tgn:hierarchy":[
        "tgn:2185453",
        "tgn:1000001",
        "tgn:7012149",
        "tgn:2000891",
        "tgn:7007256",
        "tgn:7029392"
    ],
    "tgn:id":2185453,
    "tgn:name":"Bohemian",
    "tgn:placetype":[
        "aat:300008347"
    ]
},
  "bbox": [],
  "geometry": {"coordinates":[-89.75,29.5333],"type":"Point"}
}