{
  "id": 1077644,
  "type": "Feature",
  "properties": {
    "tgn:hierarchy":[
        "tgn:1077644",
        "tgn:1009295",
        "tgn:1000004",
        "tgn:1001466",
        "tgn:1000116",
        "tgn:7029392"
    ],
    "tgn:id":1077644,
    "tgn:name":"Dorokempo",
    "tgn:placetype":[
        "aat:300008347"
    ]
},
  "bbox": [],
  "geometry": {"coordinates":[118.25,-8.55],"type":"Point"}
}