{
  "id": 2319542,
  "type": "Feature",
  "properties": {
    "tgn:hierarchy":[
        "tgn:2319542",
        "tgn:1000001",
        "tgn:7006451",
        "tgn:2000093",
        "tgn:7012149",
        "tgn:7029392"
    ],
    "tgn:id":2319542,
    "tgn:name":"Eucalyptus Cove",
    "tgn:placetype":[
        "aat:300132316"
    ]
},
  "bbox": [],
  "geometry": {"coordinates":[-111.0833,33.6667],"type":"Point"}
}