{
  "id": 7494479,
  "type": "Feature",
  "properties": {
    "tgn:hierarchy":[
        "tgn:7494479",
        "tgn:7001010",
        "tgn:1000004",
        "tgn:1000141",
        "tgn:7029392"
    ],
    "tgn:id":7494479,
    "tgn:name":"Senrong Guoxiao",
    "tgn:placetype":[
        "aat:300006495"
    ]
},
  "bbox": [],
  "geometry": {"coordinates":[121.398341,23.716551],"type":"Point"}
}