{
  "id": 7466332,
  "type": "Feature",
  "properties": {
    "tgn:hierarchy":[
        "tgn:7466332",
        "tgn:7002445",
        "tgn:1000003",
        "tgn:7026487",
        "tgn:7008591",
        "tgn:7029392"
    ],
    "tgn:id":7466332,
    "tgn:name:en":"Barkham",
    "tgn:placetype":[
        "aat:300008347"
    ]
},
  "bbox": [],
  "geometry": {"coordinates":[-0.883333,51.383333],"type":"Point"}
}