{
  "id": 2383511,
  "type": "Feature",
  "properties": {
    "tgn:hierarchy":[
        "tgn:2383511",
        "tgn:1000001",
        "tgn:7012149",
        "tgn:1002522",
        "tgn:7007922",
        "tgn:7029392"
    ],
    "tgn:id":2383511,
    "tgn:name":"Heath Mills",
    "tgn:placetype":[
        "aat:300008347"
    ]
},
  "bbox": [],
  "geometry": {"coordinates":[-88.5667,42.9833],"type":"Point"}
}