{
  "id": 7356565,
  "type": "Feature",
  "properties": {
    "tgn:hierarchy":[
        "tgn:7356565",
        "tgn:7005581",
        "tgn:1000001",
        "tgn:7005560",
        "tgn:7029392"
    ],
    "tgn:id":7356565,
    "tgn:name":"Camino, Ojo del",
    "tgn:placetype":[
        "aat:300008697"
    ]
},
  "bbox": [],
  "geometry": {"coordinates":[-107.566667,30.216667],"type":"Point"}
}