{
  "id": 7456455,
  "type": "Feature",
  "properties": {
    "tgn:hierarchy":[
        "tgn:7456455",
        "tgn:7002443",
        "tgn:1000003",
        "tgn:7018993",
        "tgn:7008591",
        "tgn:7029392"
    ],
    "tgn:id":7456455,
    "tgn:name:en":"Penclegyr",
    "tgn:placetype":[
        "aat:300386846"
    ]
},
  "bbox": [],
  "geometry": {"coordinates":[-5.193611,51.950833],"type":"Point"}
}