{
  "id": 7590460,
  "type": "Feature",
  "properties": {
    "tgn:hierarchy":[
        "tgn:7590460",
        "tgn:1000004",
        "tgn:7000198",
        "tgn:7000799",
        "tgn:7029392"
    ],
    "tgn:id":7590460,
    "tgn:name:en":"Danna Bijildh\u0101r",
    "tgn:placetype":[
        "aat:300008347"
    ]
},
  "bbox": [],
  "geometry": {"coordinates":[73.880628,34.336897],"type":"Point"}
}