{
  "id": 7212944,
  "type": "Feature",
  "properties": {
    "tgn:hierarchy":[
        "tgn:7212944",
        "tgn:1000003",
        "tgn:7003676",
        "tgn:7000084",
        "tgn:7029392"
    ],
    "tgn:id":7212944,
    "tgn:name":"Bonnhausen",
    "tgn:placetype":[
        "aat:300000206"
    ]
},
  "bbox": [],
  "geometry": {"coordinates":[7.516667,53.216667],"type":"Point"}
}