{
  "id": 7099551,
  "type": "Feature",
  "properties": {
    "tgn:hierarchy":[
        "tgn:7099551",
        "tgn:7003669",
        "tgn:1000003",
        "tgn:7000084",
        "tgn:7029392"
    ],
    "tgn:id":7099551,
    "tgn:name":"Sommerau",
    "tgn:placetype":[
        "aat:300008347"
    ]
},
  "bbox": [],
  "geometry": {"coordinates":[11.716667,49.733333],"type":"Point"}
}