{
  "id": 2753299,
  "type": "Feature",
  "properties": {
    "tgn:hierarchy":[
        "tgn:2753299",
        "tgn:1000001",
        "tgn:7012149",
        "tgn:7007157",
        "tgn:2000185",
        "tgn:7029392"
    ],
    "tgn:id":2753299,
    "tgn:name":"Waterfall Gulch",
    "tgn:placetype":[
        "aat:300008761"
    ]
},
  "bbox": [],
  "geometry": {"coordinates":[-123.8667,39.8667],"type":"Point"}
}