<<<<<<< HEAD
{
  "id": 7057167,
  "type": "Feature",
  "properties": {
    "tgn:hierarchy":[
        "tgn:7057167",
        "tgn:7003008",
        "tgn:1000003",
        "tgn:7002997",
        "tgn:1000080",
        "tgn:7029392"
    ],
    "tgn:id":7057167,
    "tgn:name":"Baldo, Monte",
    "tgn:placetype":[
        "aat:300008795"
    ]
},
  "bbox": [],
  "geometry": {"coordinates":[11.533333,45.933333],"type":"Point"}
}
=======
{"geometry":{"type":"Point","coordinates":[11.533333,45.933333]},"type":"Feature","properties":{"hierarchy":["tgn:7057167","tgn:7003008","tgn:1000003","tgn:7002997","tgn:1000080","tgn:7029392"],"placetype":["aat:300008795"],"id":7057167,"name:xx":"Baldo, Monte"}}
>>>>>>> 03f74aca74312dbeaf24d7e61306dd6a786dc3d0
