{
  "id": 7580160,
  "type": "Feature",
  "properties": {
    "tgn:hierarchy":[
        "tgn:7580160",
        "tgn:1000004",
        "tgn:7000198",
        "tgn:1001882",
        "tgn:7029392"
    ],
    "tgn:id":7580160,
    "tgn:name:en":"Sri Chamr\u0101jendra Reservoir",
    "tgn:placetype":[
        "aat:300006191"
    ]
},
  "bbox": [],
  "geometry": {"coordinates":[77.35,12.966667],"type":"Point"}
}