{
  "id": 2764182,
  "type": "Feature",
  "properties": {
    "tgn:hierarchy":[
        "tgn:2764182",
        "tgn:1000001",
        "tgn:7014352",
        "tgn:7012149",
        "tgn:7007564",
        "tgn:7029392"
    ],
    "tgn:id":2764182,
    "tgn:name":"Wheeler Pond",
    "tgn:placetype":[
        "aat:300008680"
    ]
},
  "bbox": [],
  "geometry": {"coordinates":[-71.3333,42.8667],"type":"Point"}
}