{
  "id": 1045364,
  "type": "Feature",
  "properties": {
    "tgn:hierarchy":[
        "tgn:1045364",
        "tgn:7003158",
        "tgn:1000003",
        "tgn:7003124",
        "tgn:1000080",
        "tgn:7029392"
    ],
    "tgn:id":1045364,
    "tgn:name":"Mezzano",
    "tgn:placetype":[
        "aat:300008347"
    ]
},
  "bbox": [],
  "geometry": {"coordinates":[11.1333,46.15],"type":"Point"}
}