{
  "id": 2506673,
  "type": "Feature",
  "properties": {
    "tgn:hierarchy":[
        "tgn:2506673",
        "tgn:1000001",
        "tgn:2001418",
        "tgn:7012149",
        "tgn:7007526",
        "tgn:7029392"
    ],
    "tgn:id":2506673,
    "tgn:name":"Mesa Spring",
    "tgn:placetype":[
        "aat:300008697"
    ]
},
  "bbox": [],
  "geometry": {"coordinates":[-116.1333,38.3667],"type":"Point"}
}