{
  "id": 2361332,
  "type": "Feature",
  "properties": {
    "tgn:hierarchy":[
        "tgn:2361332",
        "tgn:1000001",
        "tgn:7012149",
        "tgn:2001709",
        "tgn:7007708",
        "tgn:7029392"
    ],
    "tgn:id":2361332,
    "tgn:name":"Gravel Spring",
    "tgn:placetype":[
        "aat:300008697"
    ]
},
  "bbox": [],
  "geometry": {"coordinates":[-119.1667,43.7167],"type":"Point"}
}