{
  "id": 7231092,
  "type": "Feature",
  "properties": {
    "tgn:hierarchy":[
        "tgn:7231092",
        "tgn:7002681",
        "tgn:7001395",
        "tgn:1000003",
        "tgn:1000074",
        "tgn:7029392"
    ],
    "tgn:id":7231092,
    "tgn:name":"Mark\u00e9llou",
    "tgn:placetype":[
        "aat:300008347"
    ]
},
  "bbox": [],
  "geometry": {"coordinates":[23.916667,37.783333],"type":"Point"}
}