<<<<<<< HEAD
{
  "id": 7170528,
  "type": "Feature",
  "properties": {
    "tgn:hierarchy":[
        "tgn:7170528",
        "tgn:1000003",
        "tgn:7003677",
        "tgn:7000084",
        "tgn:7029392"
    ],
    "tgn:id":7170528,
    "tgn:name":"Henssen-Berg",
    "tgn:placetype":[
        "aat:300008777"
    ]
},
  "bbox": [],
  "geometry": {"coordinates":[8.1,51.366667],"type":"Point"}
}
=======
{"geometry":{"type":"Point","coordinates":[8.100000,51.366667]},"type":"Feature","properties":{"hierarchy":["tgn:7170528","tgn:1000003","tgn:7003677","tgn:7000084","tgn:7029392"],"placetype":["aat:300008777"],"id":7170528,"name:xx":"Henssen-Berg"}}
>>>>>>> 03f74aca74312dbeaf24d7e61306dd6a786dc3d0
