<<<<<<< HEAD
{
  "id": 2338256,
  "type": "Feature",
  "properties": {
    "tgn:hierarchy":[
        "tgn:2338256",
        "tgn:1000001",
        "tgn:7012149",
        "tgn:7007706",
        "tgn:7029392"
    ],
    "tgn:id":2338256,
    "tgn:name":"Fox Run",
    "tgn:placetype":[
        "aat:300008699"
    ]
},
  "bbox": [],
  "geometry": {"coordinates":[-81.7,40.8833],"type":"Point"}
}
=======
{"geometry":{"type":"Point","coordinates":[-81.700000,40.883300]},"type":"Feature","properties":{"hierarchy":["tgn:2338256","tgn:1000001","tgn:7012149","tgn:7007706","tgn:7029392"],"placetype":["aat:300008699"],"id":2338256,"name:xx":"Fox Run"}}
>>>>>>> 03f74aca74312dbeaf24d7e61306dd6a786dc3d0
