{
  "id": 7460678,
  "type": "Feature",
  "properties": {
    "tgn:hierarchy":[
        "tgn:7460678",
        "tgn:7002443",
        "tgn:1000003",
        "tgn:7018993",
        "tgn:7008591",
        "tgn:7029392"
    ],
    "tgn:id":7460678,
    "tgn:name:en":"Llawhaden",
    "tgn:placetype":[
        "aat:300008347"
    ]
},
  "bbox": [],
  "geometry": {"coordinates":[-4.8025,51.821389],"type":"Point"}
}