<<<<<<< HEAD
{
  "id": 2155152,
  "type": "Feature",
  "properties": {
    "tgn:hierarchy":[
        "tgn:2155152",
        "tgn:1000001",
        "tgn:7012149",
        "tgn:2002348",
        "tgn:7007922",
        "tgn:7029392"
    ],
    "tgn:id":2155152,
    "tgn:name":"Bear Lake",
    "tgn:placetype":[
        "aat:300008680"
    ]
},
  "bbox": [],
  "geometry": {"coordinates":[-90.25,45.8667],"type":"Point"}
}
=======
{"geometry":{"type":"Point","coordinates":[-90.250000,45.866700]},"type":"Feature","properties":{"hierarchy":["tgn:2155152","tgn:1000001","tgn:7012149","tgn:2002348","tgn:7007922","tgn:7029392"],"placetype":["aat:300008680"],"id":2155152,"name:xx":"Bear Lake"}}
>>>>>>> 03f74aca74312dbeaf24d7e61306dd6a786dc3d0
