{
  "id": 1126364,
  "type": "Feature",
  "properties": {
    "tgn:hierarchy":[
        "tgn:1126364",
        "tgn:7015035",
        "tgn:1000001",
        "tgn:7005870",
        "tgn:7029392"
    ],
    "tgn:id":1126364,
    "tgn:name":"Lorrain, Rivi\u00e8re du",
    "tgn:placetype":[
        "aat:300008707"
    ]
},
  "bbox": [],
  "geometry": {"coordinates":[-61.05,14.8333],"type":"Point"}
}