{
  "id": 7554952,
  "type": "Feature",
  "properties": {
    "tgn:hierarchy":[
        "tgn:7554952",
        "tgn:1000004",
        "tgn:7000198",
        "tgn:7000799",
        "tgn:7029392"
    ],
    "tgn:id":7554952,
    "tgn:name:en":"N\u0101kaw\u0101s",
    "tgn:placetype":[
        "aat:300008347"
    ]
},
  "bbox": [],
  "geometry": {"coordinates":[74.857656,33.538603],"type":"Point"}
}