{
  "id": 7151409,
  "type": "Feature",
  "properties": {
    "tgn:hierarchy":[
        "tgn:7151409",
        "tgn:7003669",
        "tgn:1000003",
        "tgn:7000084",
        "tgn:7029392"
    ],
    "tgn:id":7151409,
    "tgn:name":"Kainer",
    "tgn:placetype":[
        "aat:300000206"
    ]
},
  "bbox": [],
  "geometry": {"coordinates":[13.216667,48.35],"type":"Point"}
}