{
  "id": 2473516,
  "type": "Feature",
  "properties": {
    "tgn:hierarchy":[
        "tgn:2473516",
        "tgn:1000001",
        "tgn:7012149",
        "tgn:2000232",
        "tgn:7007158",
        "tgn:7029392"
    ],
    "tgn:id":2473516,
    "tgn:name":"Lower Cogdill Lake",
    "tgn:placetype":[
        "aat:300006191"
    ]
},
  "bbox": [],
  "geometry": {"coordinates":[-107.3167,40.9667],"type":"Point"}
}