{
  "id": 2058114,
  "type": "Feature",
  "properties": {
    "tgn:hierarchy":[
        "tgn:2058114",
        "tgn:1000001",
        "tgn:7012149",
        "tgn:2001205",
        "tgn:7007523",
        "tgn:7029392"
    ],
    "tgn:id":2058114,
    "tgn:name":"Boonesboro",
    "tgn:placetype":[
        "aat:300008347"
    ]
},
  "bbox": [],
  "geometry": {"coordinates":[-92.8333,39.0667],"type":"Point"}
}