{
  "id": 2570983,
  "type": "Feature",
  "properties": {
    "tgn:hierarchy":[
        "tgn:2570983",
        "tgn:1000001",
        "tgn:7012149",
        "tgn:1002603",
        "tgn:7007520",
        "tgn:7029392"
    ],
    "tgn:id":2570983,
    "tgn:name":"Patterson Lake",
    "tgn:placetype":[
        "aat:300008680"
    ]
},
  "bbox": [],
  "geometry": {"coordinates":[-84.0167,42.4333],"type":"Point"}
}