<<<<<<< HEAD
{
  "id": 7175696,
  "type": "Feature",
  "properties": {
    "tgn:hierarchy":[
        "tgn:7175696",
        "tgn:1000003",
        "tgn:7003688",
        "tgn:7000084",
        "tgn:7029392"
    ],
    "tgn:id":7175696,
    "tgn:name":"Bahnhof Gro\u00dfenwiehe",
    "tgn:placetype":[
        "aat:300386961",
        "aat:300007783"
    ]
},
  "bbox": [],
  "geometry": {"coordinates":[9.233333,54.7],"type":"Point"}
}
=======
{"geometry":{"type":"Point","coordinates":[9.233333,54.700000]},"type":"Feature","properties":{"hierarchy":["tgn:7175696","tgn:1000003","tgn:7003688","tgn:7000084","tgn:7029392"],"placetype":["aat:300386961","aat:300007783"],"id":7175696,"name:xx":"Bahnhof Gro\u00dfenwiehe"}}
>>>>>>> 03f74aca74312dbeaf24d7e61306dd6a786dc3d0
