<<<<<<< HEAD
{
  "id": 2703750,
  "type": "Feature",
  "properties": {
    "tgn:hierarchy":[
        "tgn:2703750",
        "tgn:2000090",
        "tgn:1000001",
        "tgn:7006451",
        "tgn:7012149",
        "tgn:7029392"
    ],
    "tgn:id":2703750,
    "tgn:name":"Sun Creek",
    "tgn:placetype":[
        "aat:300008706"
    ]
},
  "bbox": [],
  "geometry": {"coordinates":[-109.65,33.8833],"type":"Point"}
}
=======
{"geometry":{"type":"Point","coordinates":[-109.650000,33.883300]},"type":"Feature","properties":{"hierarchy":["tgn:2703750","tgn:2000090","tgn:1000001","tgn:7006451","tgn:7012149","tgn:7029392"],"placetype":["aat:300008706"],"id":2703750,"name:xx":"Sun Creek"}}
>>>>>>> 03f74aca74312dbeaf24d7e61306dd6a786dc3d0
