{
  "id": 2552666,
  "type": "Feature",
  "properties": {
    "tgn:hierarchy":[
        "tgn:2552666",
        "tgn:1000001",
        "tgn:7012149",
        "tgn:2001449",
        "tgn:7007566",
        "tgn:7029392"
    ],
    "tgn:id":2552666,
    "tgn:name":"Nutritas, Rio",
    "tgn:placetype":[
        "aat:300008699"
    ]
},
  "bbox": [],
  "geometry": {"coordinates":[-106.25,36.7833],"type":"Point"}
}