{
  "id": 2441639,
  "type": "Feature",
  "properties": {
    "tgn:hierarchy":[
        "tgn:2441639",
        "tgn:1000001",
        "tgn:7012149",
        "tgn:1002787",
        "tgn:7007523",
        "tgn:7029392"
    ],
    "tgn:id":2441639,
    "tgn:name":"Kohl Lake West",
    "tgn:placetype":[
        "aat:300006191"
    ]
},
  "bbox": [],
  "geometry": {"coordinates":[-91.4167,39.2833],"type":"Point"}
}