{
  "id": 2708865,
  "type": "Feature",
  "properties": {
    "tgn:hierarchy":[
        "tgn:2708865",
        "tgn:1000001",
        "tgn:7012149",
        "tgn:1002468",
        "tgn:7007252",
        "tgn:7029392"
    ],
    "tgn:id":2708865,
    "tgn:name":"Symons Creek",
    "tgn:placetype":[
        "aat:300008706"
    ]
},
  "bbox": [],
  "geometry": {"coordinates":[-85.2667,39.8833],"type":"Point"}
}