{
  "id": 1018293,
  "type": "Feature",
  "properties": {
    "tgn:hierarchy":[
        "tgn:1018293",
        "tgn:1000001",
        "tgn:7005591",
        "tgn:7005560",
        "tgn:7029392"
    ],
    "tgn:id":1018293,
    "tgn:name:es":"Santa Cruz Tacache Mina",
    "tgn:placetype":[
        "aat:300008347"
    ]
},
  "bbox": [],
  "geometry": {"coordinates":[-98.146111,17.843611],"type":"Point"}
}