{
  "id": 7558783,
  "type": "Feature",
  "properties": {
    "tgn:hierarchy":[
        "tgn:7558783",
        "tgn:1000004",
        "tgn:7000198",
        "tgn:1001895",
        "tgn:7029392"
    ],
    "tgn:id":7558783,
    "tgn:name:en":"Pusegaon",
    "tgn:placetype":[
        "aat:300008347"
    ]
},
  "bbox": [],
  "geometry": {"coordinates":[74.316951,17.70789],"type":"Point"}
}