{
  "id": 2375788,
  "type": "Feature",
  "properties": {
    "tgn:hierarchy":[
        "tgn:2375788",
        "tgn:1000001",
        "tgn:7012149",
        "tgn:1002688",
        "tgn:7007568",
        "tgn:7029392"
    ],
    "tgn:id":2375788,
    "tgn:name":"Happy Hollow",
    "tgn:placetype":[
        "aat:300008761"
    ]
},
  "bbox": [],
  "geometry": {"coordinates":[-74.6333,42.9167],"type":"Point"}
}