{
  "id": 7479432,
  "type": "Feature",
  "properties": {
    "tgn:hierarchy":[
        "tgn:7479432",
        "tgn:1000004",
        "tgn:7491221",
        "tgn:1000141",
        "tgn:7029392"
    ],
    "tgn:id":7479432,
    "tgn:name":"Sanhe",
    "tgn:placetype":[
        "aat:300008347"
    ]
},
  "bbox": [],
  "geometry": {"coordinates":[121.037222,22.670833],"type":"Point"}
}