{
  "id": 1047270,
  "type": "Feature",
  "properties": {
    "tgn:hierarchy":[
        "tgn:1047270",
        "tgn:7003011",
        "tgn:7003005",
        "tgn:1000003",
        "tgn:1000080",
        "tgn:7029392"
    ],
    "tgn:id":1047270,
    "tgn:name":"Vairano Scalo",
    "tgn:placetype":[
        "aat:300008347"
    ]
},
  "bbox": [],
  "geometry": {"coordinates":[14.1333,41.3333],"type":"Point"}
}