<<<<<<< HEAD
{
  "id": 2401048,
  "type": "Feature",
  "properties": {
    "tgn:hierarchy":[
        "tgn:2401048",
        "tgn:1000001",
        "tgn:2001793",
        "tgn:7012149",
        "tgn:7007713",
        "tgn:7029392"
    ],
    "tgn:id":2401048,
    "tgn:name":"Horse Trap Mountain",
    "tgn:placetype":[
        "aat:300008798"
    ]
},
  "bbox": [],
  "geometry": {"coordinates":[-103.6333,43.3667],"type":"Point"}
}
=======
{"geometry":{"type":"Point","coordinates":[-103.633300,43.366700]},"type":"Feature","properties":{"hierarchy":["tgn:2401048","tgn:1000001","tgn:2001793","tgn:7012149","tgn:7007713","tgn:7029392"],"placetype":["aat:300008798"],"id":2401048,"name:xx":"Horse Trap Mountain"}}
>>>>>>> 03f74aca74312dbeaf24d7e61306dd6a786dc3d0
