{
  "id": 2401048,
  "type": "Feature",
  "properties": {
    "tgn:hierarchy":[
        "tgn:2401048",
        "tgn:1000001",
        "tgn:2001793",
        "tgn:7012149",
        "tgn:7007713",
        "tgn:7029392"
    ],
    "tgn:id":2401048,
    "tgn:name":"Horse Trap Mountain",
    "tgn:placetype":[
        "aat:300008798"
    ]
},
  "bbox": [],
  "geometry": {"coordinates":[-103.6333,43.3667],"type":"Point"}
}