{
  "id": 7327359,
  "type": "Feature",
  "properties": {
    "tgn:hierarchy":[
        "tgn:7327359",
        "tgn:7002820",
        "tgn:7030216",
        "tgn:1000003",
        "tgn:1000095",
        "tgn:7029392"
    ],
    "tgn:id":7327359,
    "tgn:name":"Parets de Dalt",
    "tgn:placetype":[
        "aat:300008347"
    ]
},
  "bbox": [],
  "geometry": {"coordinates":[2.880406,42.169523],"type":"Point"}
}