{
  "id": 7376530,
  "type": "Feature",
  "properties": {
    "tgn:hierarchy":[
        "tgn:7376530",
        "tgn:1000001",
        "tgn:7005589",
        "tgn:7005560",
        "tgn:7029392"
    ],
    "tgn:id":7376530,
    "tgn:name":"Las Lajas",
    "tgn:placetype":[
        "aat:300008347"
    ]
},
  "bbox": [],
  "geometry": {"coordinates":[-99.216667,25.733333],"type":"Point"}
}