<<<<<<< HEAD
{
  "id": 2762524,
  "type": "Feature",
  "properties": {
    "tgn:hierarchy":[
        "tgn:2762524",
        "tgn:1000001",
        "tgn:7012149",
        "tgn:7007158",
        "tgn:7029392"
    ],
    "tgn:id":2762524,
    "tgn:name":"West Wild Horse Creek",
    "tgn:placetype":[
        "aat:300008706"
    ]
},
  "bbox": [],
  "geometry": {"coordinates":[-102.2,38.2833],"type":"Point"}
}
=======
{"geometry":{"type":"Point","coordinates":[-102.200000,38.283300]},"type":"Feature","properties":{"hierarchy":["tgn:2762524","tgn:1000001","tgn:7012149","tgn:7007158","tgn:7029392"],"placetype":["aat:300008706"],"id":2762524,"name:xx":"West Wild Horse Creek"}}
>>>>>>> 03f74aca74312dbeaf24d7e61306dd6a786dc3d0
