{
  "id": 2258446,
  "type": "Feature",
  "properties": {
    "tgn:hierarchy":[
        "tgn:2258446",
        "tgn:1000001",
        "tgn:7012149",
        "tgn:1002671",
        "tgn:7007523",
        "tgn:7029392"
    ],
    "tgn:id":2258446,
    "tgn:name":"Cotton Island",
    "tgn:placetype":[
        "aat:300008791"
    ]
},
  "bbox": [],
  "geometry": {"coordinates":[-92.55,38.2167],"type":"Point"}
}