{
  "id": 7447403,
  "type": "Feature",
  "properties": {
    "tgn:hierarchy":[
        "tgn:7447403",
        "tgn:7002444",
        "tgn:7008074",
        "tgn:1000003",
        "tgn:7008591",
        "tgn:7029392"
    ],
    "tgn:id":7447403,
    "tgn:name:en":"Raehills",
    "tgn:placetype":[
        "aat:300387502"
    ]
},
  "bbox": [],
  "geometry": {"coordinates":[-3.483333,55.233333],"type":"Point"}
}