{
  "id": 2229741,
  "type": "Feature",
  "properties": {
    "tgn:hierarchy":[
        "tgn:2229741",
        "tgn:1000001",
        "tgn:7012149",
        "tgn:2001894",
        "tgn:7007825",
        "tgn:7029392"
    ],
    "tgn:id":2229741,
    "tgn:name":"Cedar Spring",
    "tgn:placetype":[
        "aat:300008697"
    ]
},
  "bbox": [],
  "geometry": {"coordinates":[-85.4667,35.25],"type":"Point"}
}