{
  "id": 7158185,
  "type": "Feature",
  "properties": {
    "tgn:hierarchy":[
        "tgn:7158185",
        "tgn:7003692",
        "tgn:1000003",
        "tgn:7000084",
        "tgn:7029392"
    ],
    "tgn:id":7158185,
    "tgn:name":"Kirnbach",
    "tgn:placetype":[
        "aat:300008347"
    ]
},
  "bbox": [],
  "geometry": {"coordinates":[8.25,48.266667],"type":"Point"}
}