{
  "id": 7214794,
  "type": "Feature",
  "properties": {
    "tgn:hierarchy":[
        "tgn:7214794",
        "tgn:7003669",
        "tgn:1000003",
        "tgn:7000084",
        "tgn:7029392"
    ],
    "tgn:id":7214794,
    "tgn:name":"Blicken",
    "tgn:placetype":[
        "aat:300387200"
    ]
},
  "bbox": [],
  "geometry": {"coordinates":[12.633333,47.75],"type":"Point"}
}