{
  "id": 2447081,
  "type": "Feature",
  "properties": {
    "tgn:hierarchy":[
        "tgn:2447081",
        "tgn:1000001",
        "tgn:2001418",
        "tgn:7012149",
        "tgn:7007526",
        "tgn:7029392"
    ],
    "tgn:id":2447081,
    "tgn:name":"Liberty Springs",
    "tgn:placetype":[
        "aat:300008697"
    ]
},
  "bbox": [],
  "geometry": {"coordinates":[-117.2667,38.2833],"type":"Point"}
}