<<<<<<< HEAD
{
  "id": 2701293,
  "type": "Feature",
  "properties": {
    "tgn:hierarchy":[
        "tgn:2701293",
        "tgn:7006450",
        "tgn:1000001",
        "tgn:7012149",
        "tgn:2124014",
        "tgn:7029392"
    ],
    "tgn:id":2701293,
    "tgn:name":"Sugar Loaf Creek",
    "tgn:placetype":[
        "aat:300008706"
    ]
},
  "bbox": [],
  "geometry": {"coordinates":[-161.2,65.7333],"type":"Point"}
}
=======
{"geometry":{"type":"Point","coordinates":[-161.200000,65.733300]},"type":"Feature","properties":{"hierarchy":["tgn:2701293","tgn:7006450","tgn:1000001","tgn:7012149","tgn:2124014","tgn:7029392"],"placetype":["aat:300008706"],"id":2701293,"name:xx":"Sugar Loaf Creek"}}
>>>>>>> 03f74aca74312dbeaf24d7e61306dd6a786dc3d0
