{
  "id": 2223434,
  "type": "Feature",
  "properties": {
    "tgn:hierarchy":[
        "tgn:2223434",
        "tgn:1000001",
        "tgn:7016172",
        "tgn:7012149",
        "tgn:2000177",
        "tgn:7029392"
    ],
    "tgn:id":2223434,
    "tgn:name":"Carsons Slough",
    "tgn:placetype":[
        "aat:300008699"
    ]
},
  "bbox": [],
  "geometry": {"coordinates":[-91.75,35.1333],"type":"Point"}
}