{
  "id": 7553076,
  "type": "Feature",
  "properties": {
    "tgn:hierarchy":[
        "tgn:7553076",
        "tgn:1000004",
        "tgn:7000198",
        "tgn:7000799",
        "tgn:7029392"
    ],
    "tgn:id":7553076,
    "tgn:name:en":"P\u0101n\u0101mik",
    "tgn:placetype":[
        "aat:300008347"
    ]
},
  "bbox": [],
  "geometry": {"coordinates":[77.539461,34.779564],"type":"Point"}
}