{
  "id": 7505476,
  "type": "Feature",
  "properties": {
    "tgn:hierarchy":[
        "tgn:7505476",
        "tgn:1009227",
        "tgn:7001866",
        "tgn:1000226",
        "tgn:1000006",
        "tgn:7029392"
    ],
    "tgn:id":7505476,
    "tgn:name:en":"Whatno, Mount",
    "tgn:placetype":[
        "aat:300008795"
    ]
},
  "bbox": [],
  "geometry": {"coordinates":[172.266667,-42.933333],"type":"Point"}
}