{
  "id": 7430038,
  "type": "Feature",
  "properties": {
    "tgn:hierarchy":[
        "tgn:7430038",
        "tgn:1001853",
        "tgn:1000001",
        "tgn:7005560",
        "tgn:7029392"
    ],
    "tgn:id":7430038,
    "tgn:name":"Buenavista",
    "tgn:placetype":[
        "aat:300008347"
    ]
},
  "bbox": [],
  "geometry": {"coordinates":[-102.533333,26.483333],"type":"Point"}
}