{
  "id": 1093671,
  "type": "Feature",
  "properties": {
    "tgn:hierarchy":[
        "tgn:1093671",
        "tgn:7001242",
        "tgn:7017583",
        "tgn:1000193",
        "tgn:7029392"
    ],
    "tgn:id":1093671,
    "tgn:name":"Stormsrivier",
    "tgn:placetype":[
        "aat:300008347"
    ]
},
  "bbox": [],
  "geometry": {"coordinates":[23.8833,-33.9667],"type":"Point"}
}