{
  "id": 1068250,
  "type": "Feature",
  "properties": {
    "tgn:hierarchy":[
        "tgn:1068250",
        "tgn:1000004",
        "tgn:7002085",
        "tgn:1000111",
        "tgn:7029392"
    ],
    "tgn:id":1068250,
    "tgn:name":"Gaoqing",
    "tgn:placetype":[
        "aat:300008347"
    ]
},
  "bbox": [],
  "geometry": {"coordinates":[117.7833,37.1833],"type":"Point"}
}