{
  "id": 2734651,
  "type": "Feature",
  "properties": {
    "tgn:hierarchy":[
        "tgn:2734651",
        "tgn:7006450",
        "tgn:1000001",
        "tgn:7012149",
        "tgn:2000087",
        "tgn:7029392"
    ],
    "tgn:id":2734651,
    "tgn:name":"Tutakoke River",
    "tgn:placetype":[
        "aat:300008707"
    ]
},
  "bbox": [],
  "geometry": {"coordinates":[-165.4167,61.2167],"type":"Point"}
}