<<<<<<< HEAD
{
  "id": 2253465,
  "type": "Feature",
  "properties": {
    "tgn:hierarchy":[
        "tgn:2253465",
        "tgn:1000001",
        "tgn:1002259",
        "tgn:7012149",
        "tgn:7007568",
        "tgn:7029392"
    ],
    "tgn:id":2253465,
    "tgn:name":"Cook Corners",
    "tgn:placetype":[
        "aat:300008347"
    ]
},
  "bbox": [],
  "geometry": {"coordinates":[-79.25,42.4667],"type":"Point"}
}
=======
{"geometry":{"type":"Point","coordinates":[-79.250000,42.466700]},"type":"Feature","properties":{"hierarchy":["tgn:2253465","tgn:1000001","tgn:1002259","tgn:7012149","tgn:7007568","tgn:7029392"],"placetype":["aat:300008347"],"id":2253465,"name:xx":"Cook Corners"}}
>>>>>>> 03f74aca74312dbeaf24d7e61306dd6a786dc3d0
