{
  "id": 2253465,
  "type": "Feature",
  "properties": {
    "tgn:hierarchy":[
        "tgn:2253465",
        "tgn:1000001",
        "tgn:1002259",
        "tgn:7012149",
        "tgn:7007568",
        "tgn:7029392"
    ],
    "tgn:id":2253465,
    "tgn:name":"Cook Corners",
    "tgn:placetype":[
        "aat:300008347"
    ]
},
  "bbox": [],
  "geometry": {"coordinates":[-79.25,42.4667],"type":"Point"}
}