{
  "id": 7464928,
  "type": "Feature",
  "properties": {
    "tgn:hierarchy":[
        "tgn:7464928",
        "tgn:7019038",
        "tgn:7002445",
        "tgn:1000003",
        "tgn:7029507",
        "tgn:7008591",
        "tgn:7029392"
    ],
    "tgn:id":7464928,
    "tgn:name:en":"Belle Isle",
    "tgn:placetype":[
        "aat:300008347"
    ]
},
  "bbox": [],
  "geometry": {"coordinates":[-1.533333,53.766667],"type":"Point"}
}