{
  "id": 7533632,
  "type": "Feature",
  "properties": {
    "tgn:hierarchy":[
        "tgn:7533632",
        "tgn:7001242",
        "tgn:7016833",
        "tgn:1001418",
        "tgn:7029392"
    ],
    "tgn:id":7533632,
    "tgn:name:en":"Jar\u0101wilah, W\u0101d\u012b al",
    "tgn:placetype":[
        "aat:300379998"
    ]
},
  "bbox": [],
  "geometry": {"coordinates":[27.37198,31.216],"type":"Point"}
}