{
  "id": 7504256,
  "type": "Feature",
  "properties": {
    "tgn:hierarchy":[
        "tgn:7504256",
        "tgn:1008380",
        "tgn:1000226",
        "tgn:7000512",
        "tgn:1000006",
        "tgn:7029392"
    ],
    "tgn:id":7504256,
    "tgn:name:en":"Waiwhero Stream",
    "tgn:placetype":[
        "aat:300008699"
    ]
},
  "bbox": [],
  "geometry": {"coordinates":[175.216667,-41.583333],"type":"Point"}
}