{
  "id": 7132231,
  "type": "Feature",
  "properties": {
    "tgn:hierarchy":[
        "tgn:7132231",
        "tgn:7003669",
        "tgn:1000003",
        "tgn:7000084",
        "tgn:7029392"
    ],
    "tgn:id":7132231,
    "tgn:name":"Mariaberg",
    "tgn:placetype":[
        "aat:300008347"
    ]
},
  "bbox": [],
  "geometry": {"coordinates":[12.283333,48.383333],"type":"Point"}
}