{
  "id": 2354897,
  "type": "Feature",
  "properties": {
    "tgn:hierarchy":[
        "tgn:2354897",
        "tgn:1000001",
        "tgn:7012149",
        "tgn:7007522",
        "tgn:7029392"
    ],
    "tgn:id":2354897,
    "tgn:name":"Goodford Creek",
    "tgn:placetype":[
        "aat:300008706"
    ]
},
  "bbox": [],
  "geometry": {"coordinates":[-88.9167,34.1333],"type":"Point"}
}