{
  "id": 7185801,
  "type": "Feature",
  "properties": {
    "tgn:hierarchy":[
        "tgn:7185801",
        "tgn:1000003",
        "tgn:7003678",
        "tgn:7000084",
        "tgn:7029392"
    ],
    "tgn:id":7185801,
    "tgn:name":"G\u00f6nnern",
    "tgn:placetype":[
        "aat:300008347"
    ]
},
  "bbox": [],
  "geometry": {"coordinates":[8.45,50.833333],"type":"Point"}
}