{
  "id": 7465136,
  "type": "Feature",
  "properties": {
    "tgn:hierarchy":[
        "tgn:7465136",
        "tgn:7002444",
        "tgn:7019115",
        "tgn:1000003",
        "tgn:7008591",
        "tgn:7029392"
    ],
    "tgn:id":7465136,
    "tgn:name:en":"Beggar's Cap",
    "tgn:placetype":[
        "aat:300011692"
    ]
},
  "bbox": [],
  "geometry": {"coordinates":[-2.616667,56.05],"type":"Point"}
}