{
  "id": 1077996,
  "type": "Feature",
  "properties": {
    "tgn:hierarchy":[
        "tgn:1077996",
        "tgn:1009295",
        "tgn:1000004",
        "tgn:1001466",
        "tgn:1000116",
        "tgn:7029392"
    ],
    "tgn:id":1077996,
    "tgn:name":"Lenangguar",
    "tgn:placetype":[
        "aat:300008347"
    ]
},
  "bbox": [],
  "geometry": {"coordinates":[117.3333,-8.7333],"type":"Point"}
}