{
  "id": 2274550,
  "type": "Feature",
  "properties": {
    "tgn:hierarchy":[
        "tgn:2274550",
        "tgn:1000001",
        "tgn:7012149",
        "tgn:1002441",
        "tgn:7007706",
        "tgn:7029392"
    ],
    "tgn:id":2274550,
    "tgn:name":"Dallmans Corner",
    "tgn:placetype":[
        "aat:300008347"
    ]
},
  "bbox": [],
  "geometry": {"coordinates":[-84.4167,39.1667],"type":"Point"}
}