{
  "id": 2563194,
  "type": "Feature",
  "properties": {
    "tgn:hierarchy":[
        "tgn:2563194",
        "tgn:1000001",
        "tgn:2000468",
        "tgn:7012149",
        "tgn:7007250",
        "tgn:7029392"
    ],
    "tgn:id":2563194,
    "tgn:name":"Owens Spring",
    "tgn:placetype":[
        "aat:300008697"
    ]
},
  "bbox": [],
  "geometry": {"coordinates":[-112.1833,44.45],"type":"Point"}
}