<<<<<<< HEAD
{
  "id": 7116389,
  "type": "Feature",
  "properties": {
    "tgn:hierarchy":[
        "tgn:7116389",
        "tgn:7000096",
        "tgn:1000003",
        "tgn:7000084",
        "tgn:7029392"
    ],
    "tgn:id":7116389,
    "tgn:name":"Ossen-Berg",
    "tgn:placetype":[
        "aat:300008777"
    ]
},
  "bbox": [],
  "geometry": {"coordinates":[12.366667,53.166667],"type":"Point"}
}
=======
{"geometry":{"type":"Point","coordinates":[12.366667,53.166667]},"type":"Feature","properties":{"hierarchy":["tgn:7116389","tgn:7000096","tgn:1000003","tgn:7000084","tgn:7029392"],"placetype":["aat:300008777"],"id":7116389,"name:xx":"Ossen-Berg"}}
>>>>>>> 03f74aca74312dbeaf24d7e61306dd6a786dc3d0
