{
  "id": 7116389,
  "type": "Feature",
  "properties": {
    "tgn:hierarchy":[
        "tgn:7116389",
        "tgn:7000096",
        "tgn:1000003",
        "tgn:7000084",
        "tgn:7029392"
    ],
    "tgn:id":7116389,
    "tgn:name":"Ossen-Berg",
    "tgn:placetype":[
        "aat:300008777"
    ]
},
  "bbox": [],
  "geometry": {"coordinates":[12.366667,53.166667],"type":"Point"}
}