{
  "id": 7062891,
  "type": "Feature",
  "properties": {
    "tgn:hierarchy":[
        "tgn:7062891",
        "tgn:7003669",
        "tgn:1000003",
        "tgn:7000084",
        "tgn:7029392"
    ],
    "tgn:id":7062891,
    "tgn:name":"Au Bach",
    "tgn:placetype":[
        "aat:300008699"
    ]
},
  "bbox": [],
  "geometry": {"coordinates":[12.55,49.233333],"type":"Point"}
}