{
  "id": 7422869,
  "type": "Feature",
  "properties": {
    "tgn:hierarchy":[
        "tgn:7422869",
        "tgn:1000001",
        "tgn:7005601",
        "tgn:7005560",
        "tgn:7029392"
    ],
    "tgn:id":7422869,
    "tgn:name":"Baj\u00edo del Pino",
    "tgn:placetype":[
        "aat:300008347"
    ]
},
  "bbox": [],
  "geometry": {"coordinates":[-103.616667,22.983333],"type":"Point"}
}