{
  "id": 2359008,
  "type": "Feature",
  "properties": {
    "tgn:hierarchy":[
        "tgn:2359008",
        "tgn:1000001",
        "tgn:7012149",
        "tgn:7007157",
        "tgn:1002957",
        "tgn:7029392"
    ],
    "tgn:id":2359008,
    "tgn:name":"Granite Lake",
    "tgn:placetype":[
        "aat:300008680"
    ]
},
  "bbox": [],
  "geometry": {"coordinates":[-119.8167,38.1833],"type":"Point"}
}