{
  "id": 2381732,
  "type": "Feature",
  "properties": {
    "tgn:hierarchy":[
        "tgn:2381732",
        "tgn:1002137",
        "tgn:1000001",
        "tgn:7012149",
        "tgn:7007710",
        "tgn:7029392"
    ],
    "tgn:id":2381732,
    "tgn:name":"Haycock",
    "tgn:placetype":[
        "aat:300008798"
    ]
},
  "bbox": [],
  "geometry": {"coordinates":[-77.4333,39.7167],"type":"Point"}
}