{
  "id": 7505341,
  "type": "Feature",
  "properties": {
    "tgn:hierarchy":[
        "tgn:7505341",
        "tgn:1008380",
        "tgn:7520093",
        "tgn:1000226",
        "tgn:1000006",
        "tgn:7029392"
    ],
    "tgn:id":7505341,
    "tgn:name:en":"Wilson, Mount",
    "tgn:placetype":[
        "aat:300008777"
    ]
},
  "bbox": [],
  "geometry": {"coordinates":[175.15,-40.066667],"type":"Point"}
}