{
  "id": 7228372,
  "type": "Feature",
  "properties": {
    "tgn:hierarchy":[
        "tgn:7228372",
        "tgn:7002709",
        "tgn:7002705",
        "tgn:1000003",
        "tgn:1000074",
        "tgn:7029392"
    ],
    "tgn:id":7228372,
    "tgn:name":"Kokkini\u00e1",
    "tgn:placetype":[
        "aat:300008347"
    ]
},
  "bbox": [],
  "geometry": {"coordinates":[20.433611,39.601111],"type":"Point"}
}