<<<<<<< HEAD
{
  "id": 2409026,
  "type": "Feature",
  "properties": {
    "tgn:hierarchy":[
        "tgn:2409026",
        "tgn:1000001",
        "tgn:7012149",
        "tgn:7007157",
        "tgn:1002857",
        "tgn:7029392"
    ],
    "tgn:id":2409026,
    "tgn:name":"Ibex Dunes",
    "tgn:placetype":[
        "aat:300008798"
    ]
},
  "bbox": [],
  "geometry": {"coordinates":[-116.3667,35.6833],"type":"Point"}
}
=======
{"geometry":{"type":"Point","coordinates":[-116.366700,35.683300]},"type":"Feature","properties":{"hierarchy":["tgn:2409026","tgn:1000001","tgn:7012149","tgn:7007157","tgn:1002857","tgn:7029392"],"placetype":["aat:300008798"],"id":2409026,"name:xx":"Ibex Dunes"}}
>>>>>>> 03f74aca74312dbeaf24d7e61306dd6a786dc3d0
