{
  "id": 2409026,
  "type": "Feature",
  "properties": {
    "tgn:hierarchy":[
        "tgn:2409026",
        "tgn:1000001",
        "tgn:7012149",
        "tgn:7007157",
        "tgn:1002857",
        "tgn:7029392"
    ],
    "tgn:id":2409026,
    "tgn:name":"Ibex Dunes",
    "tgn:placetype":[
        "aat:300008798"
    ]
},
  "bbox": [],
  "geometry": {"coordinates":[-116.3667,35.6833],"type":"Point"}
}