<<<<<<< HEAD
{
  "id": 2256036,
  "type": "Feature",
  "properties": {
    "tgn:hierarchy":[
        "tgn:2256036",
        "tgn:1000001",
        "tgn:7012149",
        "tgn:2002379",
        "tgn:7007923",
        "tgn:7029392"
    ],
    "tgn:id":2256036,
    "tgn:name":"Copper Lakes",
    "tgn:placetype":[
        "aat:300008680"
    ]
},
  "bbox": [],
  "geometry": {"coordinates":[-109.7333,44.6333],"type":"Point"}
}
=======
{"geometry":{"type":"Point","coordinates":[-109.733300,44.633300]},"type":"Feature","properties":{"hierarchy":["tgn:2256036","tgn:1000001","tgn:7012149","tgn:2002379","tgn:7007923","tgn:7029392"],"placetype":["aat:300008680"],"id":2256036,"name:xx":"Copper Lakes"}}
>>>>>>> 03f74aca74312dbeaf24d7e61306dd6a786dc3d0
