{
  "id": 7055982,
  "type": "Feature",
  "properties": {
    "tgn:hierarchy":[
        "tgn:7055982",
        "tgn:1001730",
        "tgn:1000003",
        "tgn:7003121",
        "tgn:1000080",
        "tgn:7029392"
    ],
    "tgn:id":7055982,
    "tgn:name":"Albagiara",
    "tgn:placetype":[
        "aat:300008347"
    ]
},
  "bbox": [],
  "geometry": {"coordinates":[8.864444,39.786944],"type":"Point"}
}