{
  "id": 2336993,
  "type": "Feature",
  "properties": {
    "tgn:hierarchy":[
        "tgn:2336993",
        "tgn:1000001",
        "tgn:7012149",
        "tgn:2000205",
        "tgn:7007158",
        "tgn:7029392"
    ],
    "tgn:id":2336993,
    "tgn:name":"Fourmile Gulch",
    "tgn:placetype":[
        "aat:300008761"
    ]
},
  "bbox": [],
  "geometry": {"coordinates":[-105.3667,38.1167],"type":"Point"}
}