{
  "id": 2314539,
  "type": "Feature",
  "properties": {
    "tgn:hierarchy":[
        "tgn:2314539",
        "tgn:1000001",
        "tgn:2002369",
        "tgn:7012149",
        "tgn:7007923",
        "tgn:7029392"
    ],
    "tgn:id":2314539,
    "tgn:name":"Elk Mountain",
    "tgn:placetype":[
        "aat:300008798"
    ]
},
  "bbox": [],
  "geometry": {"coordinates":[-105.35,42.4667],"type":"Point"}
}