{
  "id": 1016735,
  "type": "Feature",
  "properties": {
    "tgn:hierarchy":[
        "tgn:1016735",
        "tgn:7005512",
        "tgn:1000001",
        "tgn:7005502",
        "tgn:7029392"
    ],
    "tgn:id":1016735,
    "tgn:name":"Cap-Ha\u00eftien",
    "tgn:placetype":[
        "aat:300008347",
        "aat:300387218",
        "aat:300387225",
        "aat:300008389",
        "aat:300120599"
    ]
},
  "bbox": [],
  "geometry": {"coordinates":[-72.198,19.759],"type":"Point"}
}