{
  "id": 2148131,
  "type": "Feature",
  "properties": {
    "tgn:hierarchy":[
        "tgn:2148131",
        "tgn:1000001",
        "tgn:7012149",
        "tgn:2002374",
        "tgn:7007923",
        "tgn:7029392"
    ],
    "tgn:id":2148131,
    "tgn:name":"Barkey Ditch",
    "tgn:placetype":[
        "aat:300006075"
    ]
},
  "bbox": [],
  "geometry": {"coordinates":[-106.7833,44.45],"type":"Point"}
}