{
  "id": 2635057,
  "type": "Feature",
  "properties": {
    "tgn:hierarchy":[
        "tgn:2635057",
        "tgn:1000001",
        "tgn:2001416",
        "tgn:7012149",
        "tgn:7007526",
        "tgn:7029392"
    ],
    "tgn:id":2635057,
    "tgn:name":"Rye Grass Spring",
    "tgn:placetype":[
        "aat:300008697"
    ]
},
  "bbox": [],
  "geometry": {"coordinates":[-115.4167,37.5833],"type":"Point"}
}