{
  "id": 2188201,
  "type": "Feature",
  "properties": {
    "tgn:hierarchy":[
        "tgn:2188201",
        "tgn:2002306",
        "tgn:1000001",
        "tgn:7012149",
        "tgn:7007922",
        "tgn:7029392"
    ],
    "tgn:id":2188201,
    "tgn:name":"Bosner Creek",
    "tgn:placetype":[
        "aat:300008706"
    ]
},
  "bbox": [],
  "geometry": {"coordinates":[-90.3833,46.0333],"type":"Point"}
}