{
  "id": 7228630,
  "type": "Feature",
  "properties": {
    "tgn:hierarchy":[
        "tgn:7228630",
        "tgn:7002724",
        "tgn:7002715",
        "tgn:1000003",
        "tgn:1000074",
        "tgn:7029392"
    ],
    "tgn:id":7228630,
    "tgn:name":"Levk\u00f3n",
    "tgn:placetype":[
        "aat:300008347"
    ]
},
  "bbox": [],
  "geometry": {"coordinates":[21.133333,40.783333],"type":"Point"}
}