<<<<<<< HEAD
{
  "id": 7022489,
  "type": "Feature",
  "properties": {
    "tgn:hierarchy":[
        "tgn:7022489",
        "tgn:1000001",
        "tgn:7012149",
        "tgn:7007248",
        "tgn:7029392"
    ],
    "tgn:id":7022489,
    "tgn:name":"York Ridge",
    "tgn:placetype":[
        "aat:300266640"
    ]
},
  "bbox": [],
  "geometry": {"coordinates":[-83.6,34.8667],"type":"Point"}
}
=======
{"geometry":{"type":"Point","coordinates":[-83.600000,34.866700]},"type":"Feature","properties":{"hierarchy":["tgn:7022489","tgn:1000001","tgn:7012149","tgn:7007248","tgn:7029392"],"placetype":["aat:300266640"],"id":7022489,"name:xx":"York Ridge"}}
>>>>>>> 03f74aca74312dbeaf24d7e61306dd6a786dc3d0
