{
  "id": 7302834,
  "type": "Feature",
  "properties": {
    "tgn:hierarchy":[
        "tgn:7302834",
        "tgn:7002826",
        "tgn:7001158",
        "tgn:1000003",
        "tgn:1000095",
        "tgn:7029392"
    ],
    "tgn:id":7302834,
    "tgn:name":"Pajares de los Oteros",
    "tgn:placetype":[
        "aat:300008347"
    ]
},
  "bbox": [],
  "geometry": {"coordinates":[-5.466667,42.333333],"type":"Point"}
}