{
  "id": 2734318,
  "type": "Feature",
  "properties": {
    "tgn:hierarchy":[
        "tgn:2734318",
        "tgn:1000001",
        "tgn:7012149",
        "tgn:1002889",
        "tgn:7007706",
        "tgn:7029392"
    ],
    "tgn:id":2734318,
    "tgn:name":"Turtle Creek",
    "tgn:placetype":[
        "aat:300008706"
    ]
},
  "bbox": [],
  "geometry": {"coordinates":[-84.25,40.25],"type":"Point"}
}