{
  "id": 7157081,
  "type": "Feature",
  "properties": {
    "tgn:hierarchy":[
        "tgn:7157081",
        "tgn:1000003",
        "tgn:7003687",
        "tgn:7000084",
        "tgn:7029392"
    ],
    "tgn:id":7157081,
    "tgn:name":"Kietzer Bach",
    "tgn:placetype":[
        "aat:300008699"
    ]
},
  "bbox": [],
  "geometry": {"coordinates":[12.216667,52.333333],"type":"Point"}
}