{
  "id": 2697786,
  "type": "Feature",
  "properties": {
    "tgn:hierarchy":[
        "tgn:2697786",
        "tgn:1000001",
        "tgn:1002271",
        "tgn:7012149",
        "tgn:7007920",
        "tgn:7029392"
    ],
    "tgn:id":2697786,
    "tgn:name":"Storm King, Mount",
    "tgn:placetype":[
        "aat:300008798"
    ]
},
  "bbox": [],
  "geometry": {"coordinates":[-123.7333,48.05],"type":"Point"}
}