<<<<<<< HEAD
{
  "id": 7479699,
  "type": "Feature",
  "properties": {
    "tgn:hierarchy":[
        "tgn:7479699",
        "tgn:1000004",
        "tgn:7001013",
        "tgn:1000141",
        "tgn:7029392"
    ],
    "tgn:id":7479699,
    "tgn:name":"Xinwu Guoxiao",
    "tgn:placetype":[
        "aat:300006495"
    ]
},
  "bbox": [],
  "geometry": {"coordinates":[121.101944,24.974167],"type":"Point"}
}
=======
{"geometry":{"type":"Point","coordinates":[121.101944,24.974167]},"type":"Feature","properties":{"hierarchy":["tgn:7479699","tgn:1000004","tgn:7001013","tgn:1000141","tgn:7029392"],"placetype":["aat:300006495"],"id":7479699,"name:xx":"Xinwu Guoxiao"}}
>>>>>>> 03f74aca74312dbeaf24d7e61306dd6a786dc3d0
