{
  "id": 7579804,
  "type": "Feature",
  "properties": {
    "tgn:hierarchy":[
        "tgn:7579804",
        "tgn:1000004",
        "tgn:7000198",
        "tgn:1001895",
        "tgn:7029392"
    ],
    "tgn:id":7579804,
    "tgn:name:en":"Shirgaon",
    "tgn:placetype":[
        "aat:300008347"
    ]
},
  "bbox": [],
  "geometry": {"coordinates":[73.583333,16.383333],"type":"Point"}
}