{
  "id": 7095613,
  "type": "Feature",
  "properties": {
    "tgn:hierarchy":[
        "tgn:7095613",
        "tgn:7003692",
        "tgn:1000003",
        "tgn:7000084",
        "tgn:7029392"
    ],
    "tgn:id":7095613,
    "tgn:name":"Sch\u00f6nbrunn",
    "tgn:placetype":[
        "aat:300000206"
    ]
},
  "bbox": [],
  "geometry": {"coordinates":[8.183333,48.65],"type":"Point"}
}