{
  "id": 2506505,
  "type": "Feature",
  "properties": {
    "tgn:hierarchy":[
        "tgn:2506505",
        "tgn:1000001",
        "tgn:1002601",
        "tgn:7012149",
        "tgn:7007159",
        "tgn:7029392"
    ],
    "tgn:id":2506505,
    "tgn:name":"Merryall Brook",
    "tgn:placetype":[
        "aat:300008699"
    ]
},
  "bbox": [],
  "geometry": {"coordinates":[-73.4167,41.6833],"type":"Point"}
}