{
  "id": 7287897,
  "type": "Feature",
  "properties": {
    "tgn:hierarchy":[
        "tgn:7287897",
        "tgn:1001657",
        "tgn:1000049",
        "tgn:1000002",
        "tgn:7029392"
    ],
    "tgn:id":7287897,
    "tgn:name":"Juan Per\u00e9z, Cerro",
    "tgn:placetype":[
        "aat:300008795"
    ]
},
  "bbox": [],
  "geometry": {"coordinates":[-71.566667,-30.933333],"type":"Point"}
}