{
  "id": 2138783,
  "type": "Feature",
  "properties": {
    "tgn:hierarchy":[
        "tgn:2138783",
        "tgn:1000001",
        "tgn:1002601",
        "tgn:7012149",
        "tgn:7007159",
        "tgn:7029392"
    ],
    "tgn:id":2138783,
    "tgn:name":"Ash Swamp",
    "tgn:placetype":[
        "aat:300008905"
    ]
},
  "bbox": [],
  "geometry": {"coordinates":[-73.1833,41.5333],"type":"Point"}
}