{
  "id": 1011505,
  "type": "Feature",
  "properties": {
    "tgn:hierarchy":[
        "tgn:1011505",
        "tgn:7017442",
        "tgn:1000001",
        "tgn:7004643",
        "tgn:7029392"
    ],
    "tgn:id":1011505,
    "tgn:name":"San Juan, Cabezas de",
    "tgn:placetype":[
        "aat:300387499"
    ]
},
  "bbox": [],
  "geometry": {"coordinates":[-65.6167,18.3833],"type":"Point"}
}