{
  "id": 7476901,
  "type": "Feature",
  "properties": {
    "tgn:hierarchy":[
        "tgn:7476901",
        "tgn:7487020",
        "tgn:1000004",
        "tgn:1000141",
        "tgn:7029392"
    ],
    "tgn:id":7476901,
    "tgn:name":"Fangkan Shan",
    "tgn:placetype":[
        "aat:300008777"
    ]
},
  "bbox": [],
  "geometry": {"coordinates":[120.842683,24.659576],"type":"Point"}
}