<<<<<<< HEAD
{
  "id": 7378882,
  "type": "Feature",
  "properties": {
    "tgn:hierarchy":[
        "tgn:7378882",
        "tgn:1000001",
        "tgn:1001906",
        "tgn:7005560",
        "tgn:7029392"
    ],
    "tgn:id":7378882,
    "tgn:name":"Mexpan",
    "tgn:placetype":[
        "aat:300008347"
    ]
},
  "bbox": [],
  "geometry": {"coordinates":[-104.416667,21.016667],"type":"Point"}
}
=======
{"geometry":{"type":"Point","coordinates":[-104.416667,21.016667]},"type":"Feature","properties":{"hierarchy":["tgn:7378882","tgn:1000001","tgn:1001906","tgn:7005560","tgn:7029392"],"placetype":["aat:300008347"],"id":7378882,"name:xx":"Mexpan"}}
>>>>>>> 03f74aca74312dbeaf24d7e61306dd6a786dc3d0
