{
  "id": 7239919,
  "type": "Feature",
  "properties": {
    "tgn:hierarchy":[
        "tgn:7239919",
        "tgn:7003458",
        "tgn:1000003",
        "tgn:1000063",
        "tgn:7018236",
        "tgn:7029392"
    ],
    "tgn:id":7239919,
    "tgn:name":"Gits",
    "tgn:placetype":[
        "aat:300008347"
    ]
},
  "bbox": [],
  "geometry": {"coordinates":[3.095635,50.996872],"type":"Point"}
}