<<<<<<< HEAD
{
  "id": 7372816,
  "type": "Feature",
  "properties": {
    "tgn:hierarchy":[
        "tgn:7372816",
        "tgn:1001853",
        "tgn:1000001",
        "tgn:7005560",
        "tgn:7029392"
    ],
    "tgn:id":7372816,
    "tgn:name":"La Carroza, Sierra de",
    "tgn:placetype":[
        "aat:300266640"
    ]
},
  "bbox": [],
  "geometry": {"coordinates":[-101.25,25.116667],"type":"Point"}
}
=======
{"geometry":{"type":"Point","coordinates":[-101.250000,25.116667]},"type":"Feature","properties":{"hierarchy":["tgn:7372816","tgn:1001853","tgn:1000001","tgn:7005560","tgn:7029392"],"placetype":["aat:300266640"],"id":7372816,"name:xx":"La Carroza, Sierra de"}}
>>>>>>> 03f74aca74312dbeaf24d7e61306dd6a786dc3d0
