<<<<<<< HEAD
{
  "id": 7364203,
  "type": "Feature",
  "properties": {
    "tgn:hierarchy":[
        "tgn:7364203",
        "tgn:1000001",
        "tgn:7005595",
        "tgn:7005560",
        "tgn:7029392"
    ],
    "tgn:id":7364203,
    "tgn:name":"Rancho El Ciriaco",
    "tgn:placetype":[
        "aat:300000241"
    ]
},
  "bbox": [],
  "geometry": {"coordinates":[-108.3,26.133333],"type":"Point"}
}
=======
{"geometry":{"type":"Point","coordinates":[-108.300000,26.133333]},"type":"Feature","properties":{"hierarchy":["tgn:7364203","tgn:1000001","tgn:7005595","tgn:7005560","tgn:7029392"],"placetype":["aat:300000241"],"id":7364203,"name:xx":"Rancho El Ciriaco"}}
>>>>>>> 03f74aca74312dbeaf24d7e61306dd6a786dc3d0
