{
  "id": 7182495,
  "type": "Feature",
  "properties": {
    "tgn:hierarchy":[
        "tgn:7182495",
        "tgn:1000003",
        "tgn:7003682",
        "tgn:7000084",
        "tgn:7029392"
    ],
    "tgn:id":7182495,
    "tgn:name":"Geierslei",
    "tgn:placetype":[
        "aat:300000206"
    ]
},
  "bbox": [],
  "geometry": {"coordinates":[6.95,49.866667],"type":"Point"}
}