{
  "id": 7434768,
  "type": "Feature",
  "properties": {
    "tgn:hierarchy":[
        "tgn:7434768",
        "tgn:7005581",
        "tgn:1000001",
        "tgn:7005560",
        "tgn:7029392"
    ],
    "tgn:id":7434768,
    "tgn:name":"Varas, Ojo de las",
    "tgn:placetype":[
        "aat:300008697"
    ]
},
  "bbox": [],
  "geometry": {"coordinates":[-106.866667,30.616667],"type":"Point"}
}