<<<<<<< HEAD
{
  "id": 7375794,
  "type": "Feature",
  "properties": {
    "tgn:hierarchy":[
        "tgn:7375794",
        "tgn:1000001",
        "tgn:1001960",
        "tgn:7005560",
        "tgn:7029392"
    ],
    "tgn:id":7375794,
    "tgn:name":"Lista Blanca, Sierra",
    "tgn:placetype":[
        "aat:300008795"
    ]
},
  "bbox": [],
  "geometry": {"coordinates":[-110.366667,28.5],"type":"Point"}
}
=======
{"geometry":{"type":"Point","coordinates":[-110.366667,28.500000]},"type":"Feature","properties":{"hierarchy":["tgn:7375794","tgn:1000001","tgn:1001960","tgn:7005560","tgn:7029392"],"placetype":["aat:300008795"],"id":7375794,"name:xx":"Lista Blanca, Sierra"}}
>>>>>>> 03f74aca74312dbeaf24d7e61306dd6a786dc3d0
