<<<<<<< HEAD
{
  "id": 7171859,
  "type": "Feature",
  "properties": {
    "tgn:hierarchy":[
        "tgn:7171859",
        "tgn:7003669",
        "tgn:1000003",
        "tgn:7000084",
        "tgn:7029392"
    ],
    "tgn:id":7171859,
    "tgn:name":"Herrnbirket",
    "tgn:placetype":[
        "aat:300000206"
    ]
},
  "bbox": [],
  "geometry": {"coordinates":[12.766667,48.95],"type":"Point"}
}
=======
{"geometry":{"type":"Point","coordinates":[12.766667,48.950000]},"type":"Feature","properties":{"hierarchy":["tgn:7171859","tgn:7003669","tgn:1000003","tgn:7000084","tgn:7029392"],"placetype":["aat:300000206"],"id":7171859,"name:xx":"Herrnbirket"}}
>>>>>>> 03f74aca74312dbeaf24d7e61306dd6a786dc3d0
