{
  "id": 2591530,
  "type": "Feature",
  "properties": {
    "tgn:hierarchy":[
        "tgn:2591530",
        "tgn:1000001",
        "tgn:7012149",
        "tgn:1002501",
        "tgn:7007710",
        "tgn:7029392"
    ],
    "tgn:id":2591530,
    "tgn:name":"Pompey Run",
    "tgn:placetype":[
        "aat:300008699"
    ]
},
  "bbox": [],
  "geometry": {"coordinates":[-78.9167,40.6833],"type":"Point"}
}