{
  "id": 2299027,
  "type": "Feature",
  "properties": {
    "tgn:hierarchy":[
        "tgn:2299027",
        "tgn:1000001",
        "tgn:7012149",
        "tgn:2000805",
        "tgn:7007255",
        "tgn:7029392"
    ],
    "tgn:id":2299027,
    "tgn:name":"Duck Branch",
    "tgn:placetype":[
        "aat:300008699"
    ]
},
  "bbox": [],
  "geometry": {"coordinates":[-83.0667,37.45],"type":"Point"}
}