{
  "id": 7161773,
  "type": "Feature",
  "properties": {
    "tgn:hierarchy":[
        "tgn:7161773",
        "tgn:7003692",
        "tgn:1000003",
        "tgn:7000084",
        "tgn:7029392"
    ],
    "tgn:id":7161773,
    "tgn:name":"Hochmunde",
    "tgn:placetype":[
        "aat:300000206"
    ]
},
  "bbox": [],
  "geometry": {"coordinates":[8.05,48.216667],"type":"Point"}
}