{
  "id": 2249935,
  "type": "Feature",
  "properties": {
    "tgn:hierarchy":[
        "tgn:2249935",
        "tgn:1000001",
        "tgn:1003023",
        "tgn:7012149",
        "tgn:7007516",
        "tgn:7029392"
    ],
    "tgn:id":2249935,
    "tgn:name":"Collier Creek",
    "tgn:placetype":[
        "aat:300008706"
    ]
},
  "bbox": [],
  "geometry": {"coordinates":[-75.8333,38.35],"type":"Point"}
}