{
  "id": 2616932,
  "type": "Feature",
  "properties": {
    "tgn:hierarchy":[
        "tgn:2616932",
        "tgn:1000001",
        "tgn:1002229",
        "tgn:7012149",
        "tgn:7007710",
        "tgn:7029392"
    ],
    "tgn:id":2616932,
    "tgn:name":"Rich Valley",
    "tgn:placetype":[
        "aat:300008761"
    ]
},
  "bbox": [],
  "geometry": {"coordinates":[-78.3333,41.5333],"type":"Point"}
}