<<<<<<< HEAD
{
  "id": 2764092,
  "type": "Feature",
  "properties": {
    "tgn:hierarchy":[
        "tgn:2764092",
        "tgn:1000001",
        "tgn:2001424",
        "tgn:7012149",
        "tgn:7007564",
        "tgn:7029392"
    ],
    "tgn:id":2764092,
    "tgn:name":"Wheeler Hill",
    "tgn:placetype":[
        "aat:300008798"
    ]
},
  "bbox": [],
  "geometry": {"coordinates":[-71.8,44.3333],"type":"Point"}
}
=======
{"geometry":{"type":"Point","coordinates":[-71.800000,44.333300]},"type":"Feature","properties":{"hierarchy":["tgn:2764092","tgn:1000001","tgn:2001424","tgn:7012149","tgn:7007564","tgn:7029392"],"placetype":["aat:300008798"],"id":2764092,"name:xx":"Wheeler Hill"}}
>>>>>>> 03f74aca74312dbeaf24d7e61306dd6a786dc3d0
