{
  "id": 2755034,
  "type": "Feature",
  "properties": {
    "tgn:hierarchy":[
        "tgn:2755034",
        "tgn:1000001",
        "tgn:7012149",
        "tgn:1003004",
        "tgn:7007252",
        "tgn:7029392"
    ],
    "tgn:id":2755034,
    "tgn:name":"Web Branch",
    "tgn:placetype":[
        "aat:300008699"
    ]
},
  "bbox": [],
  "geometry": {"coordinates":[-84.9167,39.8833],"type":"Point"}
}