{
  "id": 1058492,
  "type": "Feature",
  "properties": {
    "tgn:hierarchy":[
        "tgn:1058492",
        "tgn:1000003",
        "tgn:7011662",
        "tgn:7006660",
        "tgn:7029392"
    ],
    "tgn:id":1058492,
    "tgn:name":"Pidlisne",
    "tgn:placetype":[
        "aat:300008347"
    ]
},
  "bbox": [],
  "geometry": {"coordinates":[32.25,48.7833],"type":"Point"}
}