<<<<<<< HEAD
{
  "id": 2764108,
  "type": "Feature",
  "properties": {
    "tgn:hierarchy":[
        "tgn:2764108",
        "tgn:1000001",
        "tgn:7012149",
        "tgn:1002800",
        "tgn:7007710",
        "tgn:7029392"
    ],
    "tgn:id":2764108,
    "tgn:name":"Wheeler Hollow",
    "tgn:placetype":[
        "aat:300008761"
    ]
},
  "bbox": [],
  "geometry": {"coordinates":[-77.9833,41.4833],"type":"Point"}
}
=======
{"geometry":{"type":"Point","coordinates":[-77.983300,41.483300]},"type":"Feature","properties":{"hierarchy":["tgn:2764108","tgn:1000001","tgn:7012149","tgn:1002800","tgn:7007710","tgn:7029392"],"placetype":["aat:300008761"],"id":2764108,"name:xx":"Wheeler Hollow"}}
>>>>>>> 03f74aca74312dbeaf24d7e61306dd6a786dc3d0
