{
  "id": 7593398,
  "type": "Feature",
  "properties": {
    "tgn:hierarchy":[
        "tgn:7593398",
        "tgn:7005395",
        "tgn:1000001",
        "tgn:7005388",
        "tgn:7029392"
    ],
    "tgn:id":7593398,
    "tgn:name":"Redonda, Laguna",
    "tgn:placetype":[
        "aat:300008679"
    ]
},
  "bbox": [],
  "geometry": {"coordinates":[-8.94,19.011],"type":"Point"}
}