{
  "id": 2413549,
  "type": "Feature",
  "properties": {
    "tgn:hierarchy":[
        "tgn:2413549",
        "tgn:1000001",
        "tgn:2001472",
        "tgn:7012149",
        "tgn:7007709",
        "tgn:7029392"
    ],
    "tgn:id":2413549,
    "tgn:name":"Iredell",
    "tgn:placetype":[
        "aat:300008347"
    ]
},
  "bbox": [],
  "geometry": {"coordinates":[-78.5833,33.9167],"type":"Point"}
}