{
  "id": 7203604,
  "type": "Feature",
  "properties": {
    "tgn:hierarchy":[
        "tgn:7203604",
        "tgn:1000003",
        "tgn:7003682",
        "tgn:7000084",
        "tgn:7029392"
    ],
    "tgn:id":7203604,
    "tgn:name":"Brexbach",
    "tgn:placetype":[
        "aat:300008699"
    ]
},
  "bbox": [],
  "geometry": {"coordinates":[7.566667,50.45],"type":"Point"}
}