<<<<<<< HEAD
{
  "id": 7482205,
  "type": "Feature",
  "properties": {
    "tgn:hierarchy":[
        "tgn:7482205",
        "tgn:1000004",
        "tgn:7471332",
        "tgn:1000141",
        "tgn:7029392"
    ],
    "tgn:id":7482205,
    "tgn:name":"Yangxiwowei",
    "tgn:placetype":[
        "aat:300008347"
    ]
},
  "bbox": [],
  "geometry": {"coordinates":[121.097778,24.875],"type":"Point"}
}
=======
{"geometry":{"type":"Point","coordinates":[121.097778,24.875000]},"type":"Feature","properties":{"hierarchy":["tgn:7482205","tgn:1000004","tgn:7471332","tgn:1000141","tgn:7029392"],"placetype":["aat:300008347"],"id":7482205,"name:xx":"Yangxiwowei"}}
>>>>>>> 03f74aca74312dbeaf24d7e61306dd6a786dc3d0
