{
  "id": 2562374,
  "type": "Feature",
  "properties": {
    "tgn:hierarchy":[
        "tgn:2562374",
        "tgn:1000001",
        "tgn:7012149",
        "tgn:2001036",
        "tgn:7007521",
        "tgn:7029392"
    ],
    "tgn:id":2562374,
    "tgn:name":"Ottertrack Lake",
    "tgn:placetype":[
        "aat:300008680"
    ]
},
  "bbox": [],
  "geometry": {"coordinates":[-91.0833,48.1667],"type":"Point"}
}