{
  "id": 7047988,
  "type": "Feature",
  "properties": {
    "tgn:hierarchy":[
        "tgn:7047988",
        "tgn:7003007",
        "tgn:1000003",
        "tgn:7002997",
        "tgn:1000080",
        "tgn:7029392"
    ],
    "tgn:id":7047988,
    "tgn:name":"Erb\u00e8",
    "tgn:placetype":[
        "aat:300008347"
    ]
},
  "bbox": [],
  "geometry": {"coordinates":[10.966667,45.233333],"type":"Point"}
}