{
  "id": 7388001,
  "type": "Feature",
  "properties": {
    "tgn:hierarchy":[
        "tgn:7388001",
        "tgn:1000001",
        "tgn:7005589",
        "tgn:7005560",
        "tgn:7029392"
    ],
    "tgn:id":7388001,
    "tgn:name":"Paso de las Cabras",
    "tgn:placetype":[
        "aat:300008347"
    ]
},
  "bbox": [],
  "geometry": {"coordinates":[-99.316667,25.583333],"type":"Point"}
}