{
  "id": 2491966,
  "type": "Feature",
  "properties": {
    "tgn:hierarchy":[
        "tgn:2491966",
        "tgn:1000001",
        "tgn:7012149",
        "tgn:2000928",
        "tgn:7007515",
        "tgn:7029392"
    ],
    "tgn:id":2491966,
    "tgn:name":"Marble Pond",
    "tgn:placetype":[
        "aat:300008680"
    ]
},
  "bbox": [],
  "geometry": {"coordinates":[-69.6833,45.2333],"type":"Point"}
}