<<<<<<< HEAD
{
  "id": 7354967,
  "type": "Feature",
  "properties": {
    "tgn:hierarchy":[
        "tgn:7354967",
        "tgn:7005581",
        "tgn:1000001",
        "tgn:7005560",
        "tgn:7029392"
    ],
    "tgn:id":7354967,
    "tgn:name":"Ci\u00e9naga del Norte, Arroyo",
    "tgn:placetype":[
        "aat:300266554",
        "aat:300008699"
    ]
},
  "bbox": [],
  "geometry": {"coordinates":[-108.483333,30.133333],"type":"Point"}
}
=======
{"geometry":{"type":"Point","coordinates":[-108.483333,30.133333]},"type":"Feature","properties":{"hierarchy":["tgn:7354967","tgn:7005581","tgn:1000001","tgn:7005560","tgn:7029392"],"placetype":["aat:300266554","aat:300008699"],"id":7354967,"name:xx":"Ci\u00e9naga del Norte, Arroyo"}}
>>>>>>> 03f74aca74312dbeaf24d7e61306dd6a786dc3d0
