<<<<<<< HEAD
{
  "id": 7113060,
  "type": "Feature",
  "properties": {
    "tgn:hierarchy":[
        "tgn:7113060",
        "tgn:7003669",
        "tgn:1000003",
        "tgn:7000084",
        "tgn:7029392"
    ],
    "tgn:id":7113060,
    "tgn:name":"Reutehof",
    "tgn:placetype":[
        "aat:300000206"
    ]
},
  "bbox": [],
  "geometry": {"coordinates":[10.183333,48.033333],"type":"Point"}
}
=======
{"geometry":{"type":"Point","coordinates":[10.183333,48.033333]},"type":"Feature","properties":{"hierarchy":["tgn:7113060","tgn:7003669","tgn:1000003","tgn:7000084","tgn:7029392"],"placetype":["aat:300000206"],"id":7113060,"name:xx":"Reutehof"}}
>>>>>>> 03f74aca74312dbeaf24d7e61306dd6a786dc3d0
