{
  "id": 2745248,
  "type": "Feature",
  "properties": {
    "tgn:hierarchy":[
        "tgn:2745248",
        "tgn:1000001",
        "tgn:7012149",
        "tgn:2000911",
        "tgn:7007256",
        "tgn:7029392"
    ],
    "tgn:id":2745248,
    "tgn:name":"Vincent Creek",
    "tgn:placetype":[
        "aat:300008706"
    ]
},
  "bbox": [],
  "geometry": {"coordinates":[-92.9833,31.1333],"type":"Point"}
}