{
  "id": 2233835,
  "type": "Feature",
  "properties": {
    "tgn:hierarchy":[
        "tgn:2233835",
        "tgn:1000001",
        "tgn:7012149",
        "tgn:2001447",
        "tgn:7007566",
        "tgn:7029392"
    ],
    "tgn:id":2233835,
    "tgn:name":"Chatfield Canyon",
    "tgn:placetype":[
        "aat:300008761"
    ]
},
  "bbox": [],
  "geometry": {"coordinates":[-105.4667,32.5333],"type":"Point"}
}