{
  "id": 2356719,
  "type": "Feature",
  "properties": {
    "tgn:hierarchy":[
        "tgn:2356719",
        "tgn:2002138",
        "tgn:1000001",
        "tgn:7012149",
        "tgn:7007919",
        "tgn:7029392"
    ],
    "tgn:id":2356719,
    "tgn:name":"Gorge, The",
    "tgn:placetype":[
        "aat:300008761"
    ]
},
  "bbox": [],
  "geometry": {"coordinates":[-79.9667,37.9333],"type":"Point"}
}