{
  "id": 2210884,
  "type": "Feature",
  "properties": {
    "tgn:hierarchy":[
        "tgn:2210884",
        "tgn:1000001",
        "tgn:7012149",
        "tgn:1002590",
        "tgn:7007826",
        "tgn:7029392"
    ],
    "tgn:id":2210884,
    "tgn:name":"Butler Branch",
    "tgn:placetype":[
        "aat:300008699"
    ]
},
  "bbox": [],
  "geometry": {"coordinates":[-95.9333,31.15],"type":"Point"}
}