{
  "id": 2134438,
  "type": "Feature",
  "properties": {
    "tgn:hierarchy":[
        "tgn:2134438",
        "tgn:1000001",
        "tgn:2002134",
        "tgn:7012149",
        "tgn:7007828",
        "tgn:7029392"
    ],
    "tgn:id":2134438,
    "tgn:name":"Annis Hill",
    "tgn:placetype":[
        "aat:300008798"
    ]
},
  "bbox": [],
  "geometry": {"coordinates":[-72.5167,44.0167],"type":"Point"}
}