{
  "id": 7559858,
  "type": "Feature",
  "properties": {
    "tgn:hierarchy":[
        "tgn:7559858",
        "tgn:1000004",
        "tgn:7000198",
        "tgn:7016722",
        "tgn:7029392"
    ],
    "tgn:id":7559858,
    "tgn:name:en":"Sonua ka Nagla",
    "tgn:placetype":[
        "aat:300008347"
    ]
},
  "bbox": [],
  "geometry": {"coordinates":[79.214991,26.976464],"type":"Point"}
}