{
  "id": 7419307,
  "type": "Feature",
  "properties": {
    "tgn:hierarchy":[
        "tgn:7419307",
        "tgn:1000001",
        "tgn:1001937",
        "tgn:7005560",
        "tgn:7029392"
    ],
    "tgn:id":7419307,
    "tgn:name":"Ciega, Laguna",
    "tgn:placetype":[
        "aat:300132317",
        "aat:300008679"
    ]
},
  "bbox": [],
  "geometry": {"coordinates":[-86.866667,20.547222],"type":"Point"}
}