<<<<<<< HEAD
{
  "id": 7022453,
  "type": "Feature",
  "properties": {
    "tgn:hierarchy":[
        "tgn:7022453",
        "tgn:1000001",
        "tgn:7012149",
        "tgn:7007825",
        "tgn:7029392"
    ],
    "tgn:id":7022453,
    "tgn:name":"Burk Cave",
    "tgn:placetype":[
        "aat:300008746"
    ]
},
  "bbox": [],
  "geometry": {"coordinates":[-86.2,35.7],"type":"Point"}
}
=======
{"geometry":{"type":"Point","coordinates":[-86.200000,35.700000]},"type":"Feature","properties":{"hierarchy":["tgn:7022453","tgn:1000001","tgn:7012149","tgn:7007825","tgn:7029392"],"placetype":["aat:300008746"],"id":7022453,"name:xx":"Burk Cave"}}
>>>>>>> 03f74aca74312dbeaf24d7e61306dd6a786dc3d0
