{
  "id": 7536506,
  "type": "Feature",
  "properties": {
    "tgn:hierarchy":[
        "tgn:7536506",
        "tgn:7001242",
        "tgn:7016833",
        "tgn:7001334",
        "tgn:7029392"
    ],
    "tgn:id":7536506,
    "tgn:name:en":"Kubaysh, 'A\u0163m\u016br al",
    "tgn:placetype":[
        "aat:300008805"
    ]
},
  "bbox": [],
  "geometry": {"coordinates":[29.646565,23.276106],"type":"Point"}
}