{
  "id": 2394702,
  "type": "Feature",
  "properties": {
    "tgn:hierarchy":[
        "tgn:2394702",
        "tgn:1000001",
        "tgn:7012149",
        "tgn:1002603",
        "tgn:7007520",
        "tgn:7029392"
    ],
    "tgn:id":2394702,
    "tgn:name":"Hoisington Lake",
    "tgn:placetype":[
        "aat:300008680"
    ]
},
  "bbox": [],
  "geometry": {"coordinates":[-83.7833,42.7667],"type":"Point"}
}