{
  "id": 7019015,
  "type": "Feature",
  "properties": {
    "tgn:hierarchy":[
        "tgn:7019015",
        "tgn:1000001",
        "tgn:7012149",
        "tgn:7007251",
        "tgn:7029392"
    ],
    "tgn:id":7019015,
    "tgn:name":"McLean",
    "tgn:placetype":[
        "aat:300387145",
        "aat:300000771"
    ]
},
  "bbox": [],
  "geometry": {"coordinates":[-88.8333,40.4833],"type":"Point"}
}