{
  "id": 7398019,
  "type": "Feature",
  "properties": {
    "tgn:hierarchy":[
        "tgn:7398019",
        "tgn:1000001",
        "tgn:1001960",
        "tgn:7005560",
        "tgn:7029392"
    ],
    "tgn:id":7398019,
    "tgn:name":"El Tabaco, Cerro",
    "tgn:placetype":[
        "aat:300008795"
    ]
},
  "bbox": [],
  "geometry": {"coordinates":[-111.724722,30.8975],"type":"Point"}
}