{
  "id": 2432577,
  "type": "Feature",
  "properties": {
    "tgn:hierarchy":[
        "tgn:2432577",
        "tgn:1000001",
        "tgn:7012149",
        "tgn:7013941",
        "tgn:7007568",
        "tgn:7029392"
    ],
    "tgn:id":2432577,
    "tgn:name":"Keegan Hill",
    "tgn:placetype":[
        "aat:300008798"
    ]
},
  "bbox": [],
  "geometry": {"coordinates":[-73.9667,44.4833],"type":"Point"}
}