{
  "id": 7565974,
  "type": "Feature",
  "properties": {
    "tgn:hierarchy":[
        "tgn:7565974",
        "tgn:1000004",
        "tgn:1001832",
        "tgn:7000198",
        "tgn:7029392"
    ],
    "tgn:id":7565974,
    "tgn:name:en":"Harw\u0101phuta",
    "tgn:placetype":[
        "aat:300008347"
    ]
},
  "bbox": [],
  "geometry": {"coordinates":[89.915676,26.444934],"type":"Point"}
}