{
  "id": 7417349,
  "type": "Feature",
  "properties": {
    "tgn:hierarchy":[
        "tgn:7417349",
        "tgn:1000001",
        "tgn:7005591",
        "tgn:7005560",
        "tgn:7029392"
    ],
    "tgn:id":7417349,
    "tgn:name:es":"El Alacr\u00e1n",
    "tgn:placetype":[
        "aat:300008347"
    ]
},
  "bbox": [],
  "geometry": {"coordinates":[-98.173611,16.383889],"type":"Point"}
}