{
  "id": 2641649,
  "type": "Feature",
  "properties": {
    "tgn:hierarchy":[
        "tgn:2641649",
        "tgn:1000001",
        "tgn:7012149",
        "tgn:2001709",
        "tgn:7007708",
        "tgn:7029392"
    ],
    "tgn:id":2641649,
    "tgn:name":"Sand Hill",
    "tgn:placetype":[
        "aat:300008798"
    ]
},
  "bbox": [],
  "geometry": {"coordinates":[-118.9667,43.6167],"type":"Point"}
}