{
  "id": 2538055,
  "type": "Feature",
  "properties": {
    "tgn:hierarchy":[
        "tgn:2538055",
        "tgn:1000001",
        "tgn:7012149",
        "tgn:7007158",
        "tgn:7029392"
    ],
    "tgn:id":2538055,
    "tgn:name":"Nelson Ditch",
    "tgn:placetype":[
        "aat:300006075"
    ]
},
  "bbox": [],
  "geometry": {"coordinates":[-108.25,38.15],"type":"Point"}
}