{
  "id": 2723566,
  "type": "Feature",
  "properties": {
    "tgn:hierarchy":[
        "tgn:2723566",
        "tgn:1000001",
        "tgn:7012149",
        "tgn:2002382",
        "tgn:7007923",
        "tgn:7029392"
    ],
    "tgn:id":2723566,
    "tgn:name":"Todd Ditch",
    "tgn:placetype":[
        "aat:300006075"
    ]
},
  "bbox": [],
  "geometry": {"coordinates":[-110.0167,42.8333],"type":"Point"}
}