{
  "id": 7160062,
  "type": "Feature",
  "properties": {
    "tgn:hierarchy":[
        "tgn:7160062",
        "tgn:7003669",
        "tgn:1000003",
        "tgn:7000084",
        "tgn:7029392"
    ],
    "tgn:id":7160062,
    "tgn:name":"Hohlweiler",
    "tgn:placetype":[
        "aat:300008347"
    ]
},
  "bbox": [],
  "geometry": {"coordinates":[10.466667,49.65],"type":"Point"}
}