{
  "id": 1119893,
  "type": "Feature",
  "properties": {
    "tgn:hierarchy":[
        "tgn:1119893",
        "tgn:1000003",
        "tgn:7003677",
        "tgn:7000084",
        "tgn:7029392"
    ],
    "tgn:id":1119893,
    "tgn:name":"Heilenbecker-Stausee",
    "tgn:placetype":[
        "aat:300006191"
    ]
},
  "bbox": [],
  "geometry": {"coordinates":[7.3667,51.25],"type":"Point"}
}