{
  "id": 2242824,
  "type": "Feature",
  "properties": {
    "tgn:hierarchy":[
        "tgn:2242824",
        "tgn:1000001",
        "tgn:2002313",
        "tgn:7012149",
        "tgn:7007922",
        "tgn:7029392"
    ],
    "tgn:id":2242824,
    "tgn:name":"Clear Creek",
    "tgn:placetype":[
        "aat:300008706"
    ]
},
  "bbox": [],
  "geometry": {"coordinates":[-91.1333,44.9167],"type":"Point"}
}