<<<<<<< HEAD
{
  "id": 7020070,
  "type": "Feature",
  "properties": {
    "tgn:hierarchy":[
        "tgn:7020070",
        "tgn:1000001",
        "tgn:7012149",
        "tgn:7018871",
        "tgn:7007920",
        "tgn:7029392"
    ],
    "tgn:id":7020070,
    "tgn:name":"Bitter Lake Reservoir",
    "tgn:placetype":[
        "aat:300006191"
    ]
},
  "bbox": [],
  "geometry": {"coordinates":[-122.3333,47.7167],"type":"Point"}
}
=======
{"geometry":{"type":"Point","coordinates":[-122.333300,47.716700]},"type":"Feature","properties":{"hierarchy":["tgn:7020070","tgn:1000001","tgn:7012149","tgn:7018871","tgn:7007920","tgn:7029392"],"placetype":["aat:300006191"],"id":7020070,"name:xx":"Bitter Lake Reservoir"}}
>>>>>>> 03f74aca74312dbeaf24d7e61306dd6a786dc3d0
