{
  "id": 7592536,
  "type": "Feature",
  "properties": {
    "tgn:hierarchy":[
        "tgn:7592536",
        "tgn:1000004",
        "tgn:7000198",
        "tgn:7000799",
        "tgn:7029392"
    ],
    "tgn:id":7592536,
    "tgn:name:en":"Jan\u0101kha",
    "tgn:placetype":[
        "aat:300008347"
    ]
},
  "bbox": [],
  "geometry": {"coordinates":[74.977778,32.855556],"type":"Point"}
}