{
  "id": 7573443,
  "type": "Feature",
  "properties": {
    "tgn:hierarchy":[
        "tgn:7573443",
        "tgn:1000004",
        "tgn:7000198",
        "tgn:1001977",
        "tgn:7029392"
    ],
    "tgn:id":7573443,
    "tgn:name:en":"Kachna",
    "tgn:placetype":[
        "aat:300007783"
    ]
},
  "bbox": [],
  "geometry": {"coordinates":[88.01927,25.635824],"type":"Point"}
}