{
  "id": 7063475,
  "type": "Feature",
  "properties": {
    "tgn:hierarchy":[
        "tgn:7063475",
        "tgn:1000003",
        "tgn:7003678",
        "tgn:7000084",
        "tgn:7029392"
    ],
    "tgn:id":7063475,
    "tgn:name":"Altwiedermus",
    "tgn:placetype":[
        "aat:300008347"
    ]
},
  "bbox": [],
  "geometry": {"coordinates":[9.05,50.233333],"type":"Point"}
}