{
  "id": 7578038,
  "type": "Feature",
  "properties": {
    "tgn:hierarchy":[
        "tgn:7578038",
        "tgn:1000004",
        "tgn:7000198",
        "tgn:7001797",
        "tgn:7029392"
    ],
    "tgn:id":7578038,
    "tgn:name:en":"Kundah River",
    "tgn:placetype":[
        "aat:300008699"
    ]
},
  "bbox": [],
  "geometry": {"coordinates":[76.766667,11.233333],"type":"Point"}
}