{
  "id": 7037924,
  "type": "Feature",
  "properties": {
    "tgn:hierarchy":[
        "tgn:7037924",
        "tgn:7003011",
        "tgn:7003005",
        "tgn:1000003",
        "tgn:1000080",
        "tgn:7029392"
    ],
    "tgn:id":7037924,
    "tgn:name":"Valogno Piccolo",
    "tgn:placetype":[
        "aat:300008347"
    ]
},
  "bbox": [],
  "geometry": {"coordinates":[13.966667,41.25],"type":"Point"}
}