{
  "id": 7329513,
  "type": "Feature",
  "properties": {
    "tgn:hierarchy":[
        "tgn:7329513",
        "tgn:7002758",
        "tgn:7002821",
        "tgn:1000003",
        "tgn:1000095",
        "tgn:7029392"
    ],
    "tgn:id":7329513,
    "tgn:name":"Portugalejo",
    "tgn:placetype":[
        "aat:300008347"
    ]
},
  "bbox": [],
  "geometry": {"coordinates":[-4.133333,36.85],"type":"Point"}
}