{
  "id": 7023802,
  "type": "Feature",
  "properties": {
    "tgn:hierarchy":[
        "tgn:7023802",
        "tgn:1000001",
        "tgn:7016172",
        "tgn:7012149",
        "tgn:7029392"
    ],
    "tgn:id":7023802,
    "tgn:name":"Two Prairie, Bayou",
    "tgn:placetype":[
        "aat:300008699"
    ]
},
  "bbox": [],
  "geometry": {"coordinates":[-92.1167,34.9833],"type":"Point"}
}