{
  "id": 2600208,
  "type": "Feature",
  "properties": {
    "tgn:hierarchy":[
        "tgn:2600208",
        "tgn:1000001",
        "tgn:7012149",
        "tgn:1002584",
        "tgn:7007826",
        "tgn:7029392"
    ],
    "tgn:id":2600208,
    "tgn:name":"Pucker Springs Branch",
    "tgn:placetype":[
        "aat:300008699"
    ]
},
  "bbox": [],
  "geometry": {"coordinates":[-97.05,30.4667],"type":"Point"}
}