{
  "id": 7239855,
  "type": "Feature",
  "properties": {
    "tgn:hierarchy":[
        "tgn:7239855",
        "tgn:7003457",
        "tgn:1000003",
        "tgn:1000063",
        "tgn:7018236",
        "tgn:7029392"
    ],
    "tgn:id":7239855,
    "tgn:name":"Hondseinde",
    "tgn:placetype":[
        "aat:300008347"
    ]
},
  "bbox": [],
  "geometry": {"coordinates":[3.526968,51.271719],"type":"Point"}
}