{
  "id": 1076192,
  "type": "Feature",
  "properties": {
    "tgn:hierarchy":[
        "tgn:1076192",
        "tgn:1000004",
        "tgn:7000198",
        "tgn:1001977",
        "tgn:7029392"
    ],
    "tgn:id":1076192,
    "tgn:name:en":"Manoharpur",
    "tgn:placetype":[
        "aat:300008347"
    ]
},
  "bbox": [],
  "geometry": {"coordinates":[87.31328,21.992866],"type":"Point"}
}