{
  "id": 2472160,
  "type": "Feature",
  "properties": {
    "tgn:hierarchy":[
        "tgn:2472160",
        "tgn:1000001",
        "tgn:2001409",
        "tgn:7012149",
        "tgn:7007526",
        "tgn:7029392"
    ],
    "tgn:id":2472160,
    "tgn:name":"Louderback Mountains",
    "tgn:placetype":[
        "aat:300386831"
    ]
},
  "bbox": [],
  "geometry": {"coordinates":[-118.0833,39.4333],"type":"Point"}
}