<<<<<<< HEAD
{
  "id": 2150087,
  "type": "Feature",
  "properties": {
    "tgn:hierarchy":[
        "tgn:2150087",
        "tgn:1000001",
        "tgn:7012149",
        "tgn:7007157",
        "tgn:2000189",
        "tgn:7029392"
    ],
    "tgn:id":2150087,
    "tgn:name":"Barton Lake",
    "tgn:placetype":[
        "aat:300006191"
    ]
},
  "bbox": [],
  "geometry": {"coordinates":[-122.4333,41.6333],"type":"Point"}
}
=======
{"geometry":{"type":"Point","coordinates":[-122.433300,41.633300]},"type":"Feature","properties":{"hierarchy":["tgn:2150087","tgn:1000001","tgn:7012149","tgn:7007157","tgn:2000189","tgn:7029392"],"placetype":["aat:300006191"],"id":2150087,"name:xx":"Barton Lake"}}
>>>>>>> 03f74aca74312dbeaf24d7e61306dd6a786dc3d0
