{
  "id": 2150087,
  "type": "Feature",
  "properties": {
    "tgn:hierarchy":[
        "tgn:2150087",
        "tgn:1000001",
        "tgn:7012149",
        "tgn:7007157",
        "tgn:2000189",
        "tgn:7029392"
    ],
    "tgn:id":2150087,
    "tgn:name":"Barton Lake",
    "tgn:placetype":[
        "aat:300006191"
    ]
},
  "bbox": [],
  "geometry": {"coordinates":[-122.4333,41.6333],"type":"Point"}
}