{
  "id": 7436133,
  "type": "Feature",
  "properties": {
    "tgn:hierarchy":[
        "tgn:7436133",
        "tgn:1000001",
        "tgn:7005591",
        "tgn:7005560",
        "tgn:7029392"
    ],
    "tgn:id":7436133,
    "tgn:name":"Santos",
    "tgn:placetype":[
        "aat:300008347"
    ]
},
  "bbox": [],
  "geometry": {"coordinates":[-96.366667,15.883333],"type":"Point"}
}