{
  "id": 7228554,
  "type": "Feature",
  "properties": {
    "tgn:hierarchy":[
        "tgn:7228554",
        "tgn:7002735",
        "tgn:7017076",
        "tgn:1000003",
        "tgn:1000074",
        "tgn:7029392"
    ],
    "tgn:id":7228554,
    "tgn:name":"Likofoli\u00e1",
    "tgn:placetype":[
        "aat:300008795"
    ]
},
  "bbox": [],
  "geometry": {"coordinates":[22.633333,37.266667],"type":"Point"}
}