{
  "id": 1007147,
  "type": "Feature",
  "properties": {
    "tgn:hierarchy":[
        "tgn:1007147",
        "tgn:7005685",
        "tgn:1000001",
        "tgn:7005801",
        "tgn:7029392"
    ],
    "tgn:id":1007147,
    "tgn:name":"Funk Island",
    "tgn:placetype":[
        "aat:300008791"
    ]
},
  "bbox": [],
  "geometry": {"coordinates":[-53.1667,49.7667],"type":"Point"}
}