{
  "id": 2692923,
  "type": "Feature",
  "properties": {
    "tgn:hierarchy":[
        "tgn:2692923",
        "tgn:1000001",
        "tgn:7012149",
        "tgn:2000181",
        "tgn:7007157",
        "tgn:7029392"
    ],
    "tgn:id":2692923,
    "tgn:name":"Steelhead",
    "tgn:placetype":[
        "aat:300008347"
    ]
},
  "bbox": [],
  "geometry": {"coordinates":[-123.6333,40.1667],"type":"Point"}
}