<<<<<<< HEAD
{
  "id": 2150478,
  "type": "Feature",
  "properties": {
    "tgn:hierarchy":[
        "tgn:2150478",
        "tgn:1000001",
        "tgn:7006451",
        "tgn:7012149",
        "tgn:2000102",
        "tgn:7029392"
    ],
    "tgn:id":2150478,
    "tgn:name":"Basin Mine",
    "tgn:placetype":[
        "aat:300000390"
    ]
},
  "bbox": [],
  "geometry": {"coordinates":[-110.7,31.4667],"type":"Point"}
}
=======
{"geometry":{"type":"Point","coordinates":[-110.700000,31.466700]},"type":"Feature","properties":{"hierarchy":["tgn:2150478","tgn:1000001","tgn:7006451","tgn:7012149","tgn:2000102","tgn:7029392"],"placetype":["aat:300000390"],"id":2150478,"name:xx":"Basin Mine"}}
>>>>>>> 03f74aca74312dbeaf24d7e61306dd6a786dc3d0
