{
  "id": 2034900,
  "type": "Feature",
  "properties": {
    "tgn:hierarchy":[
        "tgn:2034900",
        "tgn:1000001",
        "tgn:7012149",
        "tgn:2000658",
        "tgn:7007253",
        "tgn:7029392"
    ],
    "tgn:id":2034900,
    "tgn:name":"Hanlontown",
    "tgn:placetype":[
        "aat:300008347"
    ]
},
  "bbox": [],
  "geometry": {"coordinates":[-93.3667,43.2667],"type":"Point"}
}