{
  "id": 2316959,
  "type": "Feature",
  "properties": {
    "tgn:hierarchy":[
        "tgn:2316959",
        "tgn:7002659",
        "tgn:1000001",
        "tgn:2000011",
        "tgn:7012149",
        "tgn:7029392"
    ],
    "tgn:id":2316959,
    "tgn:name":"Emery Creek",
    "tgn:placetype":[
        "aat:300008706"
    ]
},
  "bbox": [],
  "geometry": {"coordinates":[-88.1667,31.9833],"type":"Point"}
}