{
  "id": 2480749,
  "type": "Feature",
  "properties": {
    "tgn:hierarchy":[
        "tgn:2480749",
        "tgn:7002659",
        "tgn:1000001",
        "tgn:2000016",
        "tgn:7012149",
        "tgn:7029392"
    ],
    "tgn:id":2480749,
    "tgn:name":"Lakeview",
    "tgn:placetype":[
        "aat:300008347"
    ]
},
  "bbox": [],
  "geometry": {"coordinates":[-87.6167,34.7833],"type":"Point"}
}