{
  "id": 2040312,
  "type": "Feature",
  "properties": {
    "tgn:hierarchy":[
        "tgn:2040312",
        "tgn:1000001",
        "tgn:7012149",
        "tgn:2000812",
        "tgn:7007255",
        "tgn:7029392"
    ],
    "tgn:id":2040312,
    "tgn:name":"Millstone",
    "tgn:placetype":[
        "aat:300008347"
    ]
},
  "bbox": [],
  "geometry": {"coordinates":[-82.75,37.1667],"type":"Point"}
}