<<<<<<< HEAD
{
  "id": 7377794,
  "type": "Feature",
  "properties": {
    "tgn:hierarchy":[
        "tgn:7377794",
        "tgn:1000001",
        "tgn:7005589",
        "tgn:7005560",
        "tgn:7029392"
    ],
    "tgn:id":7377794,
    "tgn:name":"Rancho Las Carlotas",
    "tgn:placetype":[
        "aat:300000241"
    ]
},
  "bbox": [],
  "geometry": {"coordinates":[-100.516667,26.9],"type":"Point"}
}
=======
{"geometry":{"type":"Point","coordinates":[-100.516667,26.900000]},"type":"Feature","properties":{"hierarchy":["tgn:7377794","tgn:1000001","tgn:7005589","tgn:7005560","tgn:7029392"],"placetype":["aat:300000241"],"id":7377794,"name:xx":"Rancho Las Carlotas"}}
>>>>>>> 03f74aca74312dbeaf24d7e61306dd6a786dc3d0
