{
  "id": 2624672,
  "type": "Feature",
  "properties": {
    "tgn:hierarchy":[
        "tgn:2624672",
        "tgn:1000001",
        "tgn:7012149",
        "tgn:1002800",
        "tgn:7007710",
        "tgn:7029392"
    ],
    "tgn:id":2624672,
    "tgn:name":"Rock Run Vista",
    "tgn:placetype":[
        "aat:300008798"
    ]
},
  "bbox": [],
  "geometry": {"coordinates":[-77.7333,41.75],"type":"Point"}
}