{
  "id": 1013653,
  "type": "Feature",
  "properties": {
    "tgn:hierarchy":[
        "tgn:1013653",
        "tgn:7005735",
        "tgn:7005685",
        "tgn:1000001",
        "tgn:7013409",
        "tgn:7029392"
    ],
    "tgn:id":1013653,
    "tgn:name":"Nitinat",
    "tgn:placetype":[
        "aat:300008347"
    ]
},
  "bbox": [],
  "geometry": {"coordinates":[-124.4833,48.9167],"type":"Point"}
}