<<<<<<< HEAD
{
  "id": 7020598,
  "type": "Feature",
  "properties": {
    "tgn:hierarchy":[
        "tgn:7020598",
        "tgn:1000001",
        "tgn:7012149",
        "tgn:2001291",
        "tgn:7007524",
        "tgn:7029392"
    ],
    "tgn:id":7020598,
    "tgn:name":"Lawyers Combination Mine",
    "tgn:placetype":[
        "aat:300000390"
    ]
},
  "bbox": [],
  "geometry": {"coordinates":[-114.25,46.7667],"type":"Point"}
}
=======
{"geometry":{"type":"Point","coordinates":[-114.250000,46.766700]},"type":"Feature","properties":{"hierarchy":["tgn:7020598","tgn:1000001","tgn:7012149","tgn:2001291","tgn:7007524","tgn:7029392"],"placetype":["aat:300000390"],"id":7020598,"name:xx":"Lawyers Combination Mine"}}
>>>>>>> 03f74aca74312dbeaf24d7e61306dd6a786dc3d0
