{
  "id": 1115949,
  "type": "Feature",
  "properties": {
    "tgn:hierarchy":[
        "tgn:1115949",
        "tgn:7005685",
        "tgn:1000001",
        "tgn:7029392"
    ],
    "tgn:id":1115949,
    "tgn:name":"Cold Lake",
    "tgn:placetype":[
        "aat:300008680"
    ]
},
  "bbox": [],
  "geometry": {"coordinates":[-110.0833,54.55],"type":"Point"}
}