{
  "id": 4003263,
  "type": "Feature",
  "properties": {
    "tgn:hierarchy":[
        "tgn:4003263",
        "tgn:7003669",
        "tgn:1000003",
        "tgn:7000084",
        "tgn:7029392"
    ],
    "tgn:id":4003263,
    "tgn:name":"Deutenhausen",
    "tgn:placetype":[
        "aat:300008347"
    ]
},
  "bbox": [],
  "geometry": {"coordinates":[11.583333,48.316667],"type":"Point"}
}