{
  "id": 7126054,
  "type": "Feature",
  "properties": {
    "tgn:hierarchy":[
        "tgn:7126054",
        "tgn:7003669",
        "tgn:1000003",
        "tgn:7000084",
        "tgn:7029392"
    ],
    "tgn:id":7126054,
    "tgn:name":"Oberrimbach",
    "tgn:placetype":[
        "aat:300008347"
    ]
},
  "bbox": [],
  "geometry": {"coordinates":[10.533333,49.733333],"type":"Point"}
}