{
  "id": 7019804,
  "type": "Feature",
  "properties": {
    "tgn:hierarchy":[
        "tgn:7019804",
        "tgn:1000001",
        "tgn:7012149",
        "tgn:2002371",
        "tgn:7007923",
        "tgn:7029392"
    ],
    "tgn:id":7019804,
    "tgn:name":"Pipe Springs",
    "tgn:placetype":[
        "aat:300008697"
    ]
},
  "bbox": [],
  "geometry": {"coordinates":[-108.5667,42.65],"type":"Point"}
}