{
  "id": 2667063,
  "type": "Feature",
  "properties": {
    "tgn:hierarchy":[
        "tgn:2667063",
        "tgn:1000001",
        "tgn:7012149",
        "tgn:2001500",
        "tgn:7007709",
        "tgn:7029392"
    ],
    "tgn:id":2667063,
    "tgn:name":"Ski Lake",
    "tgn:placetype":[
        "aat:300006191"
    ]
},
  "bbox": [],
  "geometry": {"coordinates":[-79.8833,36.15],"type":"Point"}
}