{
  "id": 1090763,
  "type": "Feature",
  "properties": {
    "tgn:hierarchy":[
        "tgn:1090763",
        "tgn:7001242",
        "tgn:1001575",
        "tgn:1000173",
        "tgn:7029392"
    ],
    "tgn:id":1090763,
    "tgn:name":"Ambivy",
    "tgn:placetype":[
        "aat:300008347"
    ]
},
  "bbox": [],
  "geometry": {"coordinates":[44.0167,-21.5167],"type":"Point"}
}