{
  "id": 1048730,
  "type": "Feature",
  "properties": {
    "tgn:hierarchy":[
        "tgn:1048730",
        "tgn:7003652",
        "tgn:1000003",
        "tgn:1000088",
        "tgn:7029392"
    ],
    "tgn:id":1048730,
    "tgn:name":"Sand",
    "tgn:placetype":[
        "aat:300008347"
    ]
},
  "bbox": [],
  "geometry": {"coordinates":[6.25,59.4667],"type":"Point"}
}