{
  "id": 2149824,
  "type": "Feature",
  "properties": {
    "tgn:hierarchy":[
        "tgn:2149824",
        "tgn:1000001",
        "tgn:1002359",
        "tgn:7012149",
        "tgn:7007517",
        "tgn:7029392"
    ],
    "tgn:id":2149824,
    "tgn:name":"Bartholomew Hill",
    "tgn:placetype":[
        "aat:300008798"
    ]
},
  "bbox": [],
  "geometry": {"coordinates":[-70.8833,42.6667],"type":"Point"}
}