{
  "id": 1113947,
  "type": "Feature",
  "properties": {
    "tgn:hierarchy":[
        "tgn:1113947",
        "tgn:7002443",
        "tgn:1000003",
        "tgn:7029493",
        "tgn:7008591",
        "tgn:7029392"
    ],
    "tgn:id":1113947,
    "tgn:name:en":"Tremadog Bay",
    "tgn:placetype":[
        "aat:300132316"
    ]
},
  "bbox": [],
  "geometry": {"coordinates":[-4.25,52.866667],"type":"Point"}
}