{
  "id": 1091659,
  "type": "Feature",
  "properties": {
    "tgn:hierarchy":[
        "tgn:1091659",
        "tgn:7001242",
        "tgn:1000906",
        "tgn:1000180",
        "tgn:7029392"
    ],
    "tgn:id":1091659,
    "tgn:name":"Nipepe",
    "tgn:placetype":[
        "aat:300008347"
    ]
},
  "bbox": [],
  "geometry": {"coordinates":[37.85,-14.0333],"type":"Point"}
}