<<<<<<< HEAD
{
  "id": 2255304,
  "type": "Feature",
  "properties": {
    "tgn:hierarchy":[
        "tgn:2255304",
        "tgn:1000001",
        "tgn:7012149",
        "tgn:7007157",
        "tgn:2000191",
        "tgn:7029392"
    ],
    "tgn:id":2255304,
    "tgn:name":"Coopers Bar",
    "tgn:placetype":[
        "aat:300132348"
    ]
},
  "bbox": [],
  "geometry": {"coordinates":[-123.0833,40.75],"type":"Point"}
}
=======
{"geometry":{"type":"Point","coordinates":[-123.083300,40.750000]},"type":"Feature","properties":{"hierarchy":["tgn:2255304","tgn:1000001","tgn:7012149","tgn:7007157","tgn:2000191","tgn:7029392"],"placetype":["aat:300132348"],"id":2255304,"name:xx":"Coopers Bar"}}
>>>>>>> 03f74aca74312dbeaf24d7e61306dd6a786dc3d0
