{
  "id": 2485352,
  "type": "Feature",
  "properties": {
    "tgn:hierarchy":[
        "tgn:2485352",
        "tgn:1000001",
        "tgn:7012149",
        "tgn:2000358",
        "tgn:7007248",
        "tgn:7029392"
    ],
    "tgn:id":2485352,
    "tgn:name":"Lawrenceville City Dam",
    "tgn:placetype":[
        "aat:300006191"
    ]
},
  "bbox": [],
  "geometry": {"coordinates":[-83.9667,33.95],"type":"Point"}
}