{
  "id": 2575692,
  "type": "Feature",
  "properties": {
    "tgn:hierarchy":[
        "tgn:2575692",
        "tgn:1000001",
        "tgn:2000925",
        "tgn:7012149",
        "tgn:7007515",
        "tgn:7029392"
    ],
    "tgn:id":2575692,
    "tgn:name":"Perch Island",
    "tgn:placetype":[
        "aat:300008791"
    ]
},
  "bbox": [],
  "geometry": {"coordinates":[-69.5833,43.85],"type":"Point"}
}