{
  "id": 2496506,
  "type": "Feature",
  "properties": {
    "tgn:hierarchy":[
        "tgn:2496506",
        "tgn:7002659",
        "tgn:1000001",
        "tgn:7012149",
        "tgn:2000044",
        "tgn:7029392"
    ],
    "tgn:id":2496506,
    "tgn:name":"Mathis Mountain",
    "tgn:placetype":[
        "aat:300008798"
    ]
},
  "bbox": [],
  "geometry": {"coordinates":[-86.55,34.6167],"type":"Point"}
}