<<<<<<< HEAD
{
  "id": 2409865,
  "type": "Feature",
  "properties": {
    "tgn:hierarchy":[
        "tgn:2409865",
        "tgn:7006450",
        "tgn:1000001",
        "tgn:7012149",
        "tgn:2124005",
        "tgn:7029392"
    ],
    "tgn:id":2409865,
    "tgn:name":"Ilyirak Creek",
    "tgn:placetype":[
        "aat:300008706"
    ]
},
  "bbox": [],
  "geometry": {"coordinates":[-165.8667,68.3],"type":"Point"}
}
=======
{"geometry":{"type":"Point","coordinates":[-165.866700,68.300000]},"type":"Feature","properties":{"hierarchy":["tgn:2409865","tgn:7006450","tgn:1000001","tgn:7012149","tgn:2124005","tgn:7029392"],"placetype":["aat:300008706"],"id":2409865,"name:xx":"Ilyirak Creek"}}
>>>>>>> 03f74aca74312dbeaf24d7e61306dd6a786dc3d0
