{
  "id": 7306205,
  "type": "Feature",
  "properties": {
    "tgn:hierarchy":[
        "tgn:7306205",
        "tgn:7002808",
        "tgn:7030216",
        "tgn:1000003",
        "tgn:1000095",
        "tgn:7029392"
    ],
    "tgn:id":7306205,
    "tgn:name":"Matamarg\u00f3s",
    "tgn:placetype":[
        "aat:300008347"
    ]
},
  "bbox": [],
  "geometry": {"coordinates":[1.610314,41.856068],"type":"Point"}
}