{
  "id": 7375740,
  "type": "Feature",
  "properties": {
    "tgn:hierarchy":[
        "tgn:7375740",
        "tgn:7005581",
        "tgn:1000001",
        "tgn:7005560",
        "tgn:7029392"
    ],
    "tgn:id":7375740,
    "tgn:name":"Rancho Las Tierritas",
    "tgn:placetype":[
        "aat:300000241"
    ]
},
  "bbox": [],
  "geometry": {"coordinates":[-108.166667,27.316667],"type":"Point"}
}