{
  "id": 7551398,
  "type": "Feature",
  "properties": {
    "tgn:hierarchy":[
        "tgn:7551398",
        "tgn:7001819",
        "tgn:1000004",
        "tgn:7000198",
        "tgn:7029392"
    ],
    "tgn:id":7551398,
    "tgn:name:en":"Bom\u0101k",
    "tgn:placetype":[
        "aat:300008347"
    ]
},
  "bbox": [],
  "geometry": {"coordinates":[95.528166,28.241835],"type":"Point"}
}