{
  "id": 2198204,
  "type": "Feature",
  "properties": {
    "tgn:hierarchy":[
        "tgn:2198204",
        "tgn:7002659",
        "tgn:1000001",
        "tgn:2000016",
        "tgn:7012149",
        "tgn:7029392"
    ],
    "tgn:id":2198204,
    "tgn:name":"Browns Branch",
    "tgn:placetype":[
        "aat:300008699"
    ]
},
  "bbox": [],
  "geometry": {"coordinates":[-88.05,34.6333],"type":"Point"}
}