{
  "id": 2381626,
  "type": "Feature",
  "properties": {
    "tgn:hierarchy":[
        "tgn:2381626",
        "tgn:1000001",
        "tgn:7012149",
        "tgn:2000973",
        "tgn:7007520",
        "tgn:7029392"
    ],
    "tgn:id":2381626,
    "tgn:name":"Hay Lake",
    "tgn:placetype":[
        "aat:300008680"
    ]
},
  "bbox": [],
  "geometry": {"coordinates":[-84.7833,45.9333],"type":"Point"}
}