{
  "id": 1045146,
  "type": "Feature",
  "properties": {
    "tgn:hierarchy":[
        "tgn:1045146",
        "tgn:1003444",
        "tgn:1000003",
        "tgn:7003241",
        "tgn:1000080",
        "tgn:7029392"
    ],
    "tgn:id":1045146,
    "tgn:name":"Lucito",
    "tgn:placetype":[
        "aat:300008347"
    ]
},
  "bbox": [],
  "geometry": {"coordinates":[14.683333,41.733333],"type":"Point"}
}