{
  "id": 2490360,
  "type": "Feature",
  "properties": {
    "tgn:hierarchy":[
        "tgn:2490360",
        "tgn:1000001",
        "tgn:7012149",
        "tgn:2001548",
        "tgn:7007709",
        "tgn:7029392"
    ],
    "tgn:id":2490360,
    "tgn:name":"Mango Creek",
    "tgn:placetype":[
        "aat:300008706"
    ]
},
  "bbox": [],
  "geometry": {"coordinates":[-78.4667,35.7833],"type":"Point"}
}