{
  "id": 7592597,
  "type": "Feature",
  "properties": {
    "tgn:hierarchy":[
        "tgn:7592597",
        "tgn:1000004",
        "tgn:7000198",
        "tgn:7000799",
        "tgn:7029392"
    ],
    "tgn:id":7592597,
    "tgn:name:en":"Baroi",
    "tgn:placetype":[
        "aat:300008347"
    ]
},
  "bbox": [],
  "geometry": {"coordinates":[74.929742,32.599352],"type":"Point"}
}