{
  "id": 2366515,
  "type": "Feature",
  "properties": {
    "tgn:hierarchy":[
        "tgn:2366515",
        "tgn:1000001",
        "tgn:2001409",
        "tgn:7012149",
        "tgn:7007526",
        "tgn:7029392"
    ],
    "tgn:id":2366515,
    "tgn:name":"Grimes Canyon",
    "tgn:placetype":[
        "aat:300008761"
    ]
},
  "bbox": [],
  "geometry": {"coordinates":[-118.15,39.8833],"type":"Point"}
}