{
  "id": 1025891,
  "type": "Feature",
  "properties": {
    "tgn:hierarchy":[
        "tgn:1025891",
        "tgn:7003023",
        "tgn:1000003",
        "tgn:1000062",
        "tgn:7029392"
    ],
    "tgn:id":1025891,
    "tgn:name":"Nikitsch",
    "tgn:placetype":[
        "aat:300008347"
    ]
},
  "bbox": [],
  "geometry": {"coordinates":[16.6667,47.5333],"type":"Point"}
}