{
  "id": 2665687,
  "type": "Feature",
  "properties": {
    "tgn:hierarchy":[
        "tgn:2665687",
        "tgn:1000001",
        "tgn:7012149",
        "tgn:1003025",
        "tgn:7007706",
        "tgn:7029392"
    ],
    "tgn:id":2665687,
    "tgn:name":"Sinns Subdivision",
    "tgn:placetype":[
        "aat:300008347"
    ]
},
  "bbox": [],
  "geometry": {"coordinates":[-84.5167,41.45],"type":"Point"}
}