{
  "id": 7415513,
  "type": "Feature",
  "properties": {
    "tgn:hierarchy":[
        "tgn:7415513",
        "tgn:1000001",
        "tgn:7005591",
        "tgn:7005560",
        "tgn:7029392"
    ],
    "tgn:id":7415513,
    "tgn:name:es":"Ojo de Agua",
    "tgn:placetype":[
        "aat:300008347"
    ]
},
  "bbox": [],
  "geometry": {"coordinates":[-97.031111,17.163056],"type":"Point"}
}