{
  "id": 2381896,
  "type": "Feature",
  "properties": {
    "tgn:hierarchy":[
        "tgn:2381896",
        "tgn:1000001",
        "tgn:7012149",
        "tgn:7007252",
        "tgn:7029392"
    ],
    "tgn:id":2381896,
    "tgn:name":"Hayes Branch",
    "tgn:placetype":[
        "aat:300008699"
    ]
},
  "bbox": [],
  "geometry": {"coordinates":[-85.1167,39.0333],"type":"Point"}
}