{
  "id": 2177323,
  "type": "Feature",
  "properties": {
    "tgn:hierarchy":[
        "tgn:2177323",
        "tgn:1002140",
        "tgn:1000001",
        "tgn:7012149",
        "tgn:7007520",
        "tgn:7029392"
    ],
    "tgn:id":2177323,
    "tgn:name":"Black River Drain",
    "tgn:placetype":[
        "aat:300006075"
    ]
},
  "bbox": [],
  "geometry": {"coordinates":[-86.1667,42.5167],"type":"Point"}
}