<<<<<<< HEAD
{
  "id": 2333863,
  "type": "Feature",
  "properties": {
    "tgn:hierarchy":[
        "tgn:2333863",
        "tgn:1000001",
        "tgn:7012149",
        "tgn:2001298",
        "tgn:7007524",
        "tgn:7029392"
    ],
    "tgn:id":2333863,
    "tgn:name":"Forbidding Ridge",
    "tgn:placetype":[
        "aat:300266640"
    ]
},
  "bbox": [],
  "geometry": {"coordinates":[-112.4667,46.3667],"type":"Point"}
}
=======
{"geometry":{"type":"Point","coordinates":[-112.466700,46.366700]},"type":"Feature","properties":{"hierarchy":["tgn:2333863","tgn:1000001","tgn:7012149","tgn:2001298","tgn:7007524","tgn:7029392"],"placetype":["aat:300266640"],"id":2333863,"name:xx":"Forbidding Ridge"}}
>>>>>>> 03f74aca74312dbeaf24d7e61306dd6a786dc3d0
