{
  "id": 7189076,
  "type": "Feature",
  "properties": {
    "tgn:hierarchy":[
        "tgn:7189076",
        "tgn:1000003",
        "tgn:7003685",
        "tgn:7000084",
        "tgn:7029392"
    ],
    "tgn:id":7189076,
    "tgn:name":"Eisen-Berg",
    "tgn:placetype":[
        "aat:300008777"
    ]
},
  "bbox": [],
  "geometry": {"coordinates":[12.45,50.566667],"type":"Point"}
}