{
  "id": 2773095,
  "type": "Feature",
  "properties": {
    "tgn:hierarchy":[
        "tgn:2773095",
        "tgn:1000001",
        "tgn:7012149",
        "tgn:2001883",
        "tgn:7007825",
        "tgn:7029392"
    ],
    "tgn:id":2773095,
    "tgn:name":"Williams Shoals",
    "tgn:placetype":[
        "aat:300132348"
    ]
},
  "bbox": [],
  "geometry": {"coordinates":[-83.95,35.8833],"type":"Point"}
}