{
  "id": 7271207,
  "type": "Feature",
  "properties": {
    "tgn:concordances":{
        "gn:id":"2747653"
    },
    "tgn:hierarchy":[
        "tgn:7271207",
        "tgn:1000003",
        "tgn:7003622",
        "tgn:7016845",
        "tgn:7029392"
    ],
    "tgn:id":7271207,
    "tgn:name:nl":"Schei",
    "tgn:placetype":[
        "aat:300008347"
    ]
},
  "bbox": [],
  "geometry": {"coordinates":[5.833333,50.766667],"type":"Point"}
}