<<<<<<< HEAD
{
  "id": 7110388,
  "type": "Feature",
  "properties": {
    "tgn:hierarchy":[
        "tgn:7110388",
        "tgn:1000003",
        "tgn:7003687",
        "tgn:7000084",
        "tgn:7029392"
    ],
    "tgn:id":7110388,
    "tgn:name":"Purzien",
    "tgn:placetype":[
        "aat:300008347"
    ]
},
  "bbox": [],
  "geometry": {"coordinates":[13.016667,51.766667],"type":"Point"}
}
=======
{"geometry":{"type":"Point","coordinates":[13.016667,51.766667]},"type":"Feature","properties":{"hierarchy":["tgn:7110388","tgn:1000003","tgn:7003687","tgn:7000084","tgn:7029392"],"placetype":["aat:300008347"],"id":7110388,"name:xx":"Purzien"}}
>>>>>>> 03f74aca74312dbeaf24d7e61306dd6a786dc3d0
