{
  "id": 7033486,
  "type": "Feature",
  "properties": {
    "tgn:hierarchy":[
        "tgn:7033486",
        "tgn:1003460",
        "tgn:1000003",
        "tgn:7009760",
        "tgn:1000080",
        "tgn:7029392"
    ],
    "tgn:id":7033486,
    "tgn:name":"Polveriera, Poggio",
    "tgn:placetype":[
        "aat:300008777"
    ]
},
  "bbox": [],
  "geometry": {"coordinates":[11.198611,42.416667],"type":"Point"}
}