<<<<<<< HEAD
{
  "id": 7359123,
  "type": "Feature",
  "properties": {
    "tgn:hierarchy":[
        "tgn:7359123",
        "tgn:1001853",
        "tgn:1000001",
        "tgn:7005560",
        "tgn:7029392"
    ],
    "tgn:id":7359123,
    "tgn:name":"Colorado, Puerto",
    "tgn:placetype":[
        "aat:300259572"
    ]
},
  "bbox": [],
  "geometry": {"coordinates":[-102.633333,26.716667],"type":"Point"}
}
=======
{"geometry":{"type":"Point","coordinates":[-102.633333,26.716667]},"type":"Feature","properties":{"hierarchy":["tgn:7359123","tgn:1001853","tgn:1000001","tgn:7005560","tgn:7029392"],"placetype":["aat:300259572"],"id":7359123,"name:xx":"Colorado, Puerto"}}
>>>>>>> 03f74aca74312dbeaf24d7e61306dd6a786dc3d0
