{
  "id": 2482958,
  "type": "Feature",
  "properties": {
    "tgn:hierarchy":[
        "tgn:2482958",
        "tgn:1000001",
        "tgn:2001014",
        "tgn:7012149",
        "tgn:7007521",
        "tgn:7029392"
    ],
    "tgn:id":2482958,
    "tgn:name":"Larry Lake",
    "tgn:placetype":[
        "aat:300008680"
    ]
},
  "bbox": [],
  "geometry": {"coordinates":[-90.9333,48.15],"type":"Point"}
}