{
  "id": 2544722,
  "type": "Feature",
  "properties": {
    "tgn:hierarchy":[
        "tgn:2544722",
        "tgn:1000001",
        "tgn:7012149",
        "tgn:7007825",
        "tgn:7029392"
    ],
    "tgn:id":2544722,
    "tgn:name":"North Chickamauga Creek",
    "tgn:placetype":[
        "aat:300008706"
    ]
},
  "bbox": [],
  "geometry": {"coordinates":[-85.35,35.2167],"type":"Point"}
}