{
  "id": 2455739,
  "type": "Feature",
  "properties": {
    "tgn:hierarchy":[
        "tgn:2455739",
        "tgn:1000001",
        "tgn:7012149",
        "tgn:7014128",
        "tgn:7007709",
        "tgn:7029392"
    ],
    "tgn:id":2455739,
    "tgn:name":"Little Grassy Creek",
    "tgn:placetype":[
        "aat:300008706"
    ]
},
  "bbox": [],
  "geometry": {"coordinates":[-78.6167,36.3667],"type":"Point"}
}