{
  "id": 1128826,
  "type": "Feature",
  "properties": {
    "tgn:hierarchy":[
        "tgn:1128826",
        "tgn:7006246",
        "tgn:1000047",
        "tgn:7002455",
        "tgn:1000002",
        "tgn:7029392"
    ],
    "tgn:id":1128826,
    "tgn:name":"Pregui\u00e7as",
    "tgn:placetype":[
        "aat:300008707"
    ]
},
  "bbox": [],
  "geometry": {"coordinates":[-42.7333,-2.5667],"type":"Point"}
}