{
  "id": 1075261,
  "type": "Feature",
  "properties": {
    "tgn:hierarchy":[
        "tgn:1075261",
        "tgn:1000004",
        "tgn:7000198",
        "tgn:7016722",
        "tgn:7029392"
    ],
    "tgn:id":1075261,
    "tgn:name:en":"Far\u012bdnagar",
    "tgn:placetype":[
        "aat:300008347"
    ]
},
  "bbox": [],
  "geometry": {"coordinates":[77.627431,28.769733],"type":"Point"}
}