{
  "id": 7034609,
  "type": "Feature",
  "properties": {
    "tgn:hierarchy":[
        "tgn:7034609",
        "tgn:1003500",
        "tgn:1000003",
        "tgn:7010380",
        "tgn:1000080",
        "tgn:7029392"
    ],
    "tgn:id":7034609,
    "tgn:name":"Lenne, Fiume",
    "tgn:placetype":[
        "aat:300008699"
    ]
},
  "bbox": [],
  "geometry": {"coordinates":[17.014167,40.505],"type":"Point"}
}