{
  "id": 2630282,
  "type": "Feature",
  "properties": {
    "tgn:hierarchy":[
        "tgn:2630282",
        "tgn:1000001",
        "tgn:7012149",
        "tgn:7007157",
        "tgn:1002915",
        "tgn:7029392"
    ],
    "tgn:id":2630282,
    "tgn:name":"Rough Gulch",
    "tgn:placetype":[
        "aat:300008761"
    ]
},
  "bbox": [],
  "geometry": {"coordinates":[-121.1833,37.1833],"type":"Point"}
}