{
  "id": 7309991,
  "type": "Feature",
  "properties": {
    "tgn:hierarchy":[
        "tgn:7309991",
        "tgn:1001699",
        "tgn:1000049",
        "tgn:1000002",
        "tgn:7029392"
    ],
    "tgn:id":7309991,
    "tgn:name":"Mutrico, Punta",
    "tgn:placetype":[
        "aat:300386846"
    ]
},
  "bbox": [],
  "geometry": {"coordinates":[-73.833333,-41.866667],"type":"Point"}
}