{
  "id": 2480128,
  "type": "Feature",
  "properties": {
    "tgn:hierarchy":[
        "tgn:2480128",
        "tgn:1000001",
        "tgn:7012149",
        "tgn:7018871",
        "tgn:7007920",
        "tgn:7029392"
    ],
    "tgn:id":2480128,
    "tgn:name":"Lake Marcel",
    "tgn:placetype":[
        "aat:300008680",
        "aat:300006191"
    ]
},
  "bbox": [],
  "geometry": {"coordinates":[-121.9167,47.6833],"type":"Point"}
}