<<<<<<< HEAD
{
  "id": 7482742,
  "type": "Feature",
  "properties": {
    "tgn:hierarchy":[
        "tgn:7482742",
        "tgn:1000004",
        "tgn:7001014",
        "tgn:1000141",
        "tgn:7029392"
    ],
    "tgn:id":7482742,
    "tgn:name":"Wanxing Gongmu",
    "tgn:placetype":[
        "aat:300266755"
    ]
},
  "bbox": [],
  "geometry": {"coordinates":[120.238333,23.575],"type":"Point"}
}
=======
{"geometry":{"type":"Point","coordinates":[120.238333,23.575000]},"type":"Feature","properties":{"hierarchy":["tgn:7482742","tgn:1000004","tgn:7001014","tgn:1000141","tgn:7029392"],"placetype":["aat:300266755"],"id":7482742,"name:xx":"Wanxing Gongmu"}}
>>>>>>> 03f74aca74312dbeaf24d7e61306dd6a786dc3d0
