{
  "id": 7280017,
  "type": "Feature",
  "properties": {
    "tgn:hierarchy":[
        "tgn:7280017",
        "tgn:1001702",
        "tgn:1000049",
        "tgn:1000002",
        "tgn:7029392"
    ],
    "tgn:id":7280017,
    "tgn:name":"Redonda, Punta",
    "tgn:placetype":[
        "aat:300386846"
    ]
},
  "bbox": [],
  "geometry": {"coordinates":[-72.25,-53.116667],"type":"Point"}
}