{
  "id": 2543419,
  "type": "Feature",
  "properties": {
    "tgn:hierarchy":[
        "tgn:2543419",
        "tgn:1000001",
        "tgn:2001569",
        "tgn:7012149",
        "tgn:7007705",
        "tgn:7029392"
    ],
    "tgn:id":2543419,
    "tgn:name":"Norred Creek",
    "tgn:placetype":[
        "aat:300008706"
    ]
},
  "bbox": [],
  "geometry": {"coordinates":[-102.9167,47.45],"type":"Point"}
}