<<<<<<< HEAD
{
  "id": 7116251,
  "type": "Feature",
  "properties": {
    "tgn:hierarchy":[
        "tgn:7116251",
        "tgn:1000003",
        "tgn:7003676",
        "tgn:7000084",
        "tgn:7029392"
    ],
    "tgn:id":7116251,
    "tgn:name":"Ohe",
    "tgn:placetype":[
        "aat:300008699"
    ]
},
  "bbox": [],
  "geometry": {"coordinates":[7.733333,53.016667],"type":"Point"}
}
=======
{"geometry":{"type":"Point","coordinates":[7.733333,53.016667]},"type":"Feature","properties":{"hierarchy":["tgn:7116251","tgn:1000003","tgn:7003676","tgn:7000084","tgn:7029392"],"placetype":["aat:300008699"],"id":7116251,"name:xx":"Ohe"}}
>>>>>>> 03f74aca74312dbeaf24d7e61306dd6a786dc3d0
