{
  "id": 2189485,
  "type": "Feature",
  "properties": {
    "tgn:hierarchy":[
        "tgn:2189485",
        "tgn:1000001",
        "tgn:7012149",
        "tgn:7007517",
        "tgn:7029392"
    ],
    "tgn:id":2189485,
    "tgn:name":"Bow Brook",
    "tgn:placetype":[
        "aat:300008699"
    ]
},
  "bbox": [],
  "geometry": {"coordinates":[-71.6667,42.5167],"type":"Point"}
}