{
  "id": 2785811,
  "type": "Feature",
  "properties": {
    "tgn:hierarchy":[
        "tgn:2785811",
        "tgn:1000001",
        "tgn:7012149",
        "tgn:2001864",
        "tgn:7007825",
        "tgn:7029392"
    ],
    "tgn:id":2785811,
    "tgn:name":"York Hollow",
    "tgn:placetype":[
        "aat:300008761"
    ]
},
  "bbox": [],
  "geometry": {"coordinates":[-87.0833,35.15],"type":"Point"}
}