{
  "id": 2444297,
  "type": "Feature",
  "properties": {
    "tgn:hierarchy":[
        "tgn:2444297",
        "tgn:7002659",
        "tgn:1000001",
        "tgn:7012149",
        "tgn:7021514",
        "tgn:7029392"
    ],
    "tgn:id":2444297,
    "tgn:name":"Lackey Cove",
    "tgn:placetype":[
        "aat:300008761"
    ]
},
  "bbox": [],
  "geometry": {"coordinates":[-85.8167,34.2833],"type":"Point"}
}