{
  "id": 7287282,
  "type": "Feature",
  "properties": {
    "tgn:hierarchy":[
        "tgn:7287282",
        "tgn:1001702",
        "tgn:1000049",
        "tgn:1000002",
        "tgn:7029392"
    ],
    "tgn:id":7287282,
    "tgn:name":"Grande, Boca",
    "tgn:placetype":[
        "aat:300266559"
    ]
},
  "bbox": [],
  "geometry": {"coordinates":[-74.733333,-52.366667],"type":"Point"}
}