{
  "id": 1106260,
  "type": "Feature",
  "properties": {
    "tgn:hierarchy":[
        "tgn:1106260",
        "tgn:1001069",
        "tgn:7001242",
        "tgn:1000201",
        "tgn:7029392"
    ],
    "tgn:id":1106260,
    "tgn:name":"Sabidana, Jebel",
    "tgn:placetype":[
        "aat:300008795"
    ]
},
  "bbox": [],
  "geometry": {"coordinates":[36.8333,18.0667],"type":"Point"}
}