{
  "id": 2328444,
  "type": "Feature",
  "properties": {
    "tgn:hierarchy":[
        "tgn:2328444",
        "tgn:1000001",
        "tgn:7012149",
        "tgn:2001615",
        "tgn:7007706",
        "tgn:7029392"
    ],
    "tgn:id":2328444,
    "tgn:name":"Fisher Hollow",
    "tgn:placetype":[
        "aat:300008761"
    ]
},
  "bbox": [],
  "geometry": {"coordinates":[-82.6833,38.5833],"type":"Point"}
}