{
  "id": 2341283,
  "type": "Feature",
  "properties": {
    "tgn:hierarchy":[
        "tgn:2341283",
        "tgn:1000001",
        "tgn:7012149",
        "tgn:1002809",
        "tgn:7007252",
        "tgn:7029392"
    ],
    "tgn:id":2341283,
    "tgn:name":"Fritz Ditch",
    "tgn:placetype":[
        "aat:300006075"
    ]
},
  "bbox": [],
  "geometry": {"coordinates":[-86.7667,41.0167],"type":"Point"}
}