{
  "id": 7138663,
  "type": "Feature",
  "properties": {
    "tgn:hierarchy":[
        "tgn:7138663",
        "tgn:7003669",
        "tgn:1000003",
        "tgn:7000084",
        "tgn:7029392"
    ],
    "tgn:id":7138663,
    "tgn:name":"Letz-Berg",
    "tgn:placetype":[
        "aat:300008777"
    ]
},
  "bbox": [],
  "geometry": {"coordinates":[11.15,49.816667],"type":"Point"}
}