{
  "id": 2515089,
  "type": "Feature",
  "properties": {
    "tgn:hierarchy":[
        "tgn:2515089",
        "tgn:1000001",
        "tgn:7012149",
        "tgn:2000291",
        "tgn:7007240",
        "tgn:7029392"
    ],
    "tgn:id":2515089,
    "tgn:name":"Millers Ferry",
    "tgn:placetype":[
        "aat:300008347"
    ]
},
  "bbox": [],
  "geometry": {"coordinates":[-85.8333,30.5667],"type":"Point"}
}