{
  "id": 7317123,
  "type": "Feature",
  "properties": {
    "tgn:hierarchy":[
        "tgn:7317123",
        "tgn:1001768",
        "tgn:1000049",
        "tgn:1000002",
        "tgn:7029392"
    ],
    "tgn:id":7317123,
    "tgn:name":"Chinch\u00f3n, Loma",
    "tgn:placetype":[
        "aat:300008777"
    ]
},
  "bbox": [],
  "geometry": {"coordinates":[-70.566667,-32.666667],"type":"Point"}
}