<<<<<<< HEAD
{
  "id": 2153928,
  "type": "Feature",
  "properties": {
    "tgn:hierarchy":[
        "tgn:2153928",
        "tgn:2000090",
        "tgn:1000001",
        "tgn:7006451",
        "tgn:7012149",
        "tgn:7029392"
    ],
    "tgn:id":2153928,
    "tgn:name":"Bear Cienega Creek",
    "tgn:placetype":[
        "aat:300008706"
    ]
},
  "bbox": [],
  "geometry": {"coordinates":[-109.6333,33.9667],"type":"Point"}
}
=======
{"geometry":{"type":"Point","coordinates":[-109.633300,33.966700]},"type":"Feature","properties":{"hierarchy":["tgn:2153928","tgn:2000090","tgn:1000001","tgn:7006451","tgn:7012149","tgn:7029392"],"placetype":["aat:300008706"],"id":2153928,"name:xx":"Bear Cienega Creek"}}
>>>>>>> 03f74aca74312dbeaf24d7e61306dd6a786dc3d0
