{
  "id": 2725766,
  "type": "Feature",
  "properties": {
    "tgn:hierarchy":[
        "tgn:2725766",
        "tgn:1000001",
        "tgn:7012149",
        "tgn:7007157",
        "tgn:1002828",
        "tgn:7029392"
    ],
    "tgn:id":2725766,
    "tgn:name":"Toro",
    "tgn:placetype":[
        "aat:300008178"
    ]
},
  "bbox": [],
  "geometry": {"coordinates":[-116.1333,33.4167],"type":"Point"}
}