{
  "id": 7245152,
  "type": "Feature",
  "properties": {
    "tgn:hierarchy":[
        "tgn:7245152",
        "tgn:7003465",
        "tgn:1000003",
        "tgn:1000063",
        "tgn:4012014",
        "tgn:7029392"
    ],
    "tgn:id":7245152,
    "tgn:name":"Bande, Bois de",
    "tgn:placetype":[
        "aat:300008863"
    ]
},
  "bbox": [],
  "geometry": {"coordinates":[5.416667,50.133333],"type":"Point"}
}