{
  "id": 7406336,
  "type": "Feature",
  "properties": {
    "tgn:hierarchy":[
        "tgn:7406336",
        "tgn:7005585",
        "tgn:1000001",
        "tgn:7005560",
        "tgn:7029392"
    ],
    "tgn:id":7406336,
    "tgn:name":"El Molinillo, Cerro",
    "tgn:placetype":[
        "aat:300008795"
    ]
},
  "bbox": [],
  "geometry": {"coordinates":[-98.141667,16.85],"type":"Point"}
}