{
  "id": 2629296,
  "type": "Feature",
  "properties": {
    "tgn:hierarchy":[
        "tgn:2629296",
        "tgn:1000001",
        "tgn:1002361",
        "tgn:7012149",
        "tgn:7007828",
        "tgn:7029392"
    ],
    "tgn:id":2629296,
    "tgn:name":"Rosebrook Hill",
    "tgn:placetype":[
        "aat:300008798"
    ]
},
  "bbox": [],
  "geometry": {"coordinates":[-71.9167,44.7833],"type":"Point"}
}