{
  "id": 2263086,
  "type": "Feature",
  "properties": {
    "tgn:hierarchy":[
        "tgn:2263086",
        "tgn:1000001",
        "tgn:2001471",
        "tgn:7012149",
        "tgn:7007709",
        "tgn:7029392"
    ],
    "tgn:id":2263086,
    "tgn:name":"Cowpen Bay",
    "tgn:placetype":[
        "aat:300008905"
    ]
},
  "bbox": [],
  "geometry": {"coordinates":[-78.4833,34.7167],"type":"Point"}
}