{
  "id": 2283405,
  "type": "Feature",
  "properties": {
    "tgn:hierarchy":[
        "tgn:2283405",
        "tgn:1000001",
        "tgn:2001702",
        "tgn:7012149",
        "tgn:7007708",
        "tgn:7029392"
    ],
    "tgn:id":2283405,
    "tgn:name":"Delmar Creek",
    "tgn:placetype":[
        "aat:300008706"
    ]
},
  "bbox": [],
  "geometry": {"coordinates":[-124.2333,43.25],"type":"Point"}
}