{
  "id": 2750933,
  "type": "Feature",
  "properties": {
    "tgn:hierarchy":[
        "tgn:2750933",
        "tgn:1000001",
        "tgn:7012149",
        "tgn:2000221",
        "tgn:7007158",
        "tgn:7029392"
    ],
    "tgn:id":2750933,
    "tgn:name":"Ward Reservoir Number 1",
    "tgn:placetype":[
        "aat:300006191"
    ]
},
  "bbox": [],
  "geometry": {"coordinates":[-105.0667,39.6667],"type":"Point"}
}