{
  "id": 7528928,
  "type": "Feature",
  "properties": {
    "tgn:hierarchy":[
        "tgn:7528928",
        "tgn:7001242",
        "tgn:7016833",
        "tgn:1001335",
        "tgn:7029392"
    ],
    "tgn:id":7528928,
    "tgn:name":"Qaryah Raqm Ithn\u0101n",
    "tgn:placetype":[
        "aat:300008347"
    ]
},
  "bbox": [],
  "geometry": {"coordinates":[31.060126,31.315299],"type":"Point"}
}