{
  "id": 2129985,
  "type": "Feature",
  "properties": {
    "tgn:hierarchy":[
        "tgn:2129985",
        "tgn:1000001",
        "tgn:7012149",
        "tgn:2001851",
        "tgn:7007825",
        "tgn:7029392"
    ],
    "tgn:id":2129985,
    "tgn:name":"Allen Creek",
    "tgn:placetype":[
        "aat:300008706"
    ]
},
  "bbox": [],
  "geometry": {"coordinates":[-83.2167,35.9833],"type":"Point"}
}