{
  "id": 2318841,
  "type": "Feature",
  "properties": {
    "tgn:hierarchy":[
        "tgn:2318841",
        "tgn:1000001",
        "tgn:7012149",
        "tgn:2001967",
        "tgn:7007826",
        "tgn:7029392"
    ],
    "tgn:id":2318841,
    "tgn:name":"Escondido Draw",
    "tgn:placetype":[
        "aat:300008761"
    ]
},
  "bbox": [],
  "geometry": {"coordinates":[-101.5667,30.6833],"type":"Point"}
}