<<<<<<< HEAD
{
  "id": 2769016,
  "type": "Feature",
  "properties": {
    "tgn:hierarchy":[
        "tgn:2769016",
        "tgn:1000001",
        "tgn:7012149",
        "tgn:2002247",
        "tgn:7007920",
        "tgn:7029392"
    ],
    "tgn:id":2769016,
    "tgn:name":"Whittaker Lake",
    "tgn:placetype":[
        "aat:300008680"
    ]
},
  "bbox": [],
  "geometry": {"coordinates":[-118.3833,47.6],"type":"Point"}
}
=======
{"geometry":{"type":"Point","coordinates":[-118.383300,47.600000]},"type":"Feature","properties":{"hierarchy":["tgn:2769016","tgn:1000001","tgn:7012149","tgn:2002247","tgn:7007920","tgn:7029392"],"placetype":["aat:300008680"],"id":2769016,"name:xx":"Whittaker Lake"}}
>>>>>>> 03f74aca74312dbeaf24d7e61306dd6a786dc3d0
