{
  "id": 2469817,
  "type": "Feature",
  "properties": {
    "tgn:hierarchy":[
        "tgn:2469817",
        "tgn:7002659",
        "tgn:1000001",
        "tgn:2000009",
        "tgn:7012149",
        "tgn:7029392"
    ],
    "tgn:id":2469817,
    "tgn:name":"Lookout Valley Acres",
    "tgn:placetype":[
        "aat:300008347"
    ]
},
  "bbox": [],
  "geometry": {"coordinates":[-85.75,34.1833],"type":"Point"}
}