{
  "id": 7215386,
  "type": "Feature",
  "properties": {
    "tgn:hierarchy":[
        "tgn:7215386",
        "tgn:1000003",
        "tgn:7003685",
        "tgn:7000084",
        "tgn:7029392"
    ],
    "tgn:id":7215386,
    "tgn:name":"Adels-Berg",
    "tgn:placetype":[
        "aat:300008777"
    ]
},
  "bbox": [],
  "geometry": {"coordinates":[13.016667,50.816667],"type":"Point"}
}