{
  "id": 2025895,
  "type": "Feature",
  "properties": {
    "tgn:hierarchy":[
        "tgn:2025895",
        "tgn:1000001",
        "tgn:7012149",
        "tgn:2000493",
        "tgn:7007250",
        "tgn:7029392"
    ],
    "tgn:id":2025895,
    "tgn:name":"Milner",
    "tgn:placetype":[
        "aat:300387016"
    ]
},
  "bbox": [],
  "geometry": {"coordinates":[-114.0167,42.5167],"type":"Point"}
}