{
  "id": 2709756,
  "type": "Feature",
  "properties": {
    "tgn:hierarchy":[
        "tgn:2709756",
        "tgn:7006450",
        "tgn:1000001",
        "tgn:7012149",
        "tgn:2000082",
        "tgn:7029392"
    ],
    "tgn:id":2709756,
    "tgn:name":"Tah Island",
    "tgn:placetype":[
        "aat:300008791"
    ]
},
  "bbox": [],
  "geometry": {"coordinates":[-132.3167,54.8333],"type":"Point"}
}