{
  "id": 2735666,
  "type": "Feature",
  "properties": {
    "tgn:hierarchy":[
        "tgn:2735666",
        "tgn:1000001",
        "tgn:7012149",
        "tgn:2002188",
        "tgn:7007919",
        "tgn:7029392"
    ],
    "tgn:id":2735666,
    "tgn:name":"Twin Hollow",
    "tgn:placetype":[
        "aat:300008761"
    ]
},
  "bbox": [],
  "geometry": {"coordinates":[-81.8333,36.95],"type":"Point"}
}