{
  "id": 7379129,
  "type": "Feature",
  "properties": {
    "tgn:hierarchy":[
        "tgn:7379129",
        "tgn:1001853",
        "tgn:1000001",
        "tgn:7005560",
        "tgn:7029392"
    ],
    "tgn:id":7379129,
    "tgn:name":"Mezquite, Arroyo",
    "tgn:placetype":[
        "aat:300008699"
    ]
},
  "bbox": [],
  "geometry": {"coordinates":[-101.133333,27.816667],"type":"Point"}
}