{
  "id": 2136250,
  "type": "Feature",
  "properties": {
    "tgn:hierarchy":[
        "tgn:2136250",
        "tgn:1000001",
        "tgn:7012149",
        "tgn:1003008",
        "tgn:7007710",
        "tgn:7029392"
    ],
    "tgn:id":2136250,
    "tgn:name":"Ararat, Mount",
    "tgn:placetype":[
        "aat:300008798"
    ]
},
  "bbox": [],
  "geometry": {"coordinates":[-75.45,41.7833],"type":"Point"}
}