{
  "id": 7123207,
  "type": "Feature",
  "properties": {
    "tgn:hierarchy":[
        "tgn:7123207",
        "tgn:1000003",
        "tgn:7003685",
        "tgn:7000084",
        "tgn:7029392"
    ],
    "tgn:id":7123207,
    "tgn:name":"Neustadt",
    "tgn:placetype":[
        "aat:300000745"
    ]
},
  "bbox": [],
  "geometry": {"coordinates":[13.733333,51.066667],"type":"Point"}
}