{
  "id": 7554413,
  "type": "Feature",
  "properties": {
    "tgn:hierarchy":[
        "tgn:7554413",
        "tgn:1000004",
        "tgn:7000198",
        "tgn:7016788",
        "tgn:7029392"
    ],
    "tgn:id":7554413,
    "tgn:name:en":"Mewa Nagar",
    "tgn:placetype":[
        "aat:300008347"
    ]
},
  "bbox": [],
  "geometry": {"coordinates":[72.152652,25.80086],"type":"Point"}
}