{
  "id": 7262575,
  "type": "Feature",
  "properties": {
    "tgn:concordances":{
        "gn:id":"2758142"
    },
    "tgn:hierarchy":[
        "tgn:7262575",
        "tgn:1000003",
        "tgn:7006951",
        "tgn:7016845",
        "tgn:7029392"
    ],
    "tgn:id":7262575,
    "tgn:name:nl":"Buitenhuizen",
    "tgn:placetype":[
        "aat:300008347"
    ]
},
  "bbox": [],
  "geometry": {"coordinates":[4.716667,52.433333],"type":"Point"}
}