<<<<<<< HEAD
{
  "id": 2258972,
  "type": "Feature",
  "properties": {
    "tgn:hierarchy":[
        "tgn:2258972",
        "tgn:1000001",
        "tgn:7012149",
        "tgn:1002379",
        "tgn:7007826",
        "tgn:7029392"
    ],
    "tgn:id":2258972,
    "tgn:name":"Cottonwood Creek",
    "tgn:placetype":[
        "aat:300008706"
    ]
},
  "bbox": [],
  "geometry": {"coordinates":[-95.8667,29.6333],"type":"Point"}
}
=======
{"geometry":{"type":"Point","coordinates":[-95.866700,29.633300]},"type":"Feature","properties":{"hierarchy":["tgn:2258972","tgn:1000001","tgn:7012149","tgn:1002379","tgn:7007826","tgn:7029392"],"placetype":["aat:300008706"],"id":2258972,"name:xx":"Cottonwood Creek"}}
>>>>>>> 03f74aca74312dbeaf24d7e61306dd6a786dc3d0
