{
  "id": 2466470,
  "type": "Feature",
  "properties": {
    "tgn:hierarchy":[
        "tgn:2466470",
        "tgn:1000001",
        "tgn:7012149",
        "tgn:2000527",
        "tgn:7007251",
        "tgn:7029392"
    ],
    "tgn:id":2466470,
    "tgn:name":"Long Branch",
    "tgn:placetype":[
        "aat:300008699"
    ]
},
  "bbox": [],
  "geometry": {"coordinates":[-88.0333,38.8167],"type":"Point"}
}