{
  "id": 1025499,
  "type": "Feature",
  "properties": {
    "tgn:hierarchy":[
        "tgn:1025499",
        "tgn:7003026",
        "tgn:1000003",
        "tgn:1000062",
        "tgn:7029392"
    ],
    "tgn:id":1025499,
    "tgn:name":"Eggelsberg",
    "tgn:placetype":[
        "aat:300008347"
    ]
},
  "bbox": [],
  "geometry": {"coordinates":[12.9833,48.1333],"type":"Point"}
}