{
  "id": 2282976,
  "type": "Feature",
  "properties": {
    "tgn:hierarchy":[
        "tgn:2282976",
        "tgn:1000001",
        "tgn:7012149",
        "tgn:2001752",
        "tgn:7007712",
        "tgn:7029392"
    ],
    "tgn:id":2282976,
    "tgn:name":"Dekalb",
    "tgn:placetype":[
        "aat:300008347"
    ]
},
  "bbox": [],
  "geometry": {"coordinates":[-80.5833,34.3667],"type":"Point"}
}