{
  "id": 7402739,
  "type": "Feature",
  "properties": {
    "tgn:hierarchy":[
        "tgn:7402739",
        "tgn:1000001",
        "tgn:1001937",
        "tgn:7005560",
        "tgn:7029392"
    ],
    "tgn:id":7402739,
    "tgn:name":"San Lorenzo",
    "tgn:placetype":[
        "aat:300008347"
    ]
},
  "bbox": [],
  "geometry": {"coordinates":[-87.266667,20.475],"type":"Point"}
}