{
  "id": 2189299,
  "type": "Feature",
  "properties": {
    "tgn:hierarchy":[
        "tgn:2189299",
        "tgn:1000001",
        "tgn:7006451",
        "tgn:7012149",
        "tgn:2000103",
        "tgn:7029392"
    ],
    "tgn:id":2189299,
    "tgn:name":"Boundary Tank",
    "tgn:placetype":[
        "aat:300006191"
    ]
},
  "bbox": [],
  "geometry": {"coordinates":[-112.3833,34.8167],"type":"Point"}
}