{
  "id": 2169725,
  "type": "Feature",
  "properties": {
    "tgn:hierarchy":[
        "tgn:2169725",
        "tgn:1000001",
        "tgn:1002286",
        "tgn:7012149",
        "tgn:7007710",
        "tgn:7029392"
    ],
    "tgn:id":2169725,
    "tgn:name":"Big Mountain",
    "tgn:placetype":[
        "aat:300008798"
    ]
},
  "bbox": [],
  "geometry": {"coordinates":[-77.4333,41.0167],"type":"Point"}
}