<<<<<<< HEAD
{
  "id": 7057356,
  "type": "Feature",
  "properties": {
    "tgn:hierarchy":[
        "tgn:7057356",
        "tgn:1003430",
        "tgn:1000003",
        "tgn:7003126",
        "tgn:1000080",
        "tgn:7029392"
    ],
    "tgn:id":7057356,
    "tgn:name":"Aymaville",
    "tgn:placetype":[
        "aat:300008347"
    ]
},
  "bbox": [],
  "geometry": {"coordinates":[7.233333,45.7],"type":"Point"}
}
=======
{"geometry":{"type":"Point","coordinates":[7.233333,45.700000]},"type":"Feature","properties":{"hierarchy":["tgn:7057356","tgn:1003430","tgn:1000003","tgn:7003126","tgn:1000080","tgn:7029392"],"placetype":["aat:300008347"],"id":7057356,"name:xx":"Aymaville"}}
>>>>>>> 03f74aca74312dbeaf24d7e61306dd6a786dc3d0
