{
  "id": 7572191,
  "type": "Feature",
  "properties": {
    "tgn:hierarchy":[
        "tgn:7572191",
        "tgn:1000004",
        "tgn:1001832",
        "tgn:7000198",
        "tgn:7029392"
    ],
    "tgn:id":7572191,
    "tgn:name:en":"Jh\u0101nzi River",
    "tgn:placetype":[
        "aat:300008699"
    ]
},
  "bbox": [],
  "geometry": {"coordinates":[94.352096,26.897349],"type":"Point"}
}