{
  "id": 2301374,
  "type": "Feature",
  "properties": {
    "tgn:hierarchy":[
        "tgn:2301374",
        "tgn:1000001",
        "tgn:1002260",
        "tgn:7012149",
        "tgn:7007920",
        "tgn:7029392"
    ],
    "tgn:id":2301374,
    "tgn:name":"Dunn Creek",
    "tgn:placetype":[
        "aat:300008706"
    ]
},
  "bbox": [],
  "geometry": {"coordinates":[-120.95,47.5667],"type":"Point"}
}