{
  "id": 7375124,
  "type": "Feature",
  "properties": {
    "tgn:hierarchy":[
        "tgn:7375124",
        "tgn:1000001",
        "tgn:7005598",
        "tgn:7005560",
        "tgn:7029392"
    ],
    "tgn:id":7375124,
    "tgn:name":"La Puerta",
    "tgn:placetype":[
        "aat:300007783"
    ]
},
  "bbox": [],
  "geometry": {"coordinates":[-98.166667,19.666667],"type":"Point"}
}