{
  "id": 7494043,
  "type": "Feature",
  "properties": {
    "tgn:hierarchy":[
        "tgn:7494043",
        "tgn:1000004",
        "tgn:7491221",
        "tgn:1000141",
        "tgn:7029392"
    ],
    "tgn:id":7494043,
    "tgn:name":"Xiaqilin",
    "tgn:placetype":[
        "aat:300008347"
    ]
},
  "bbox": [],
  "geometry": {"coordinates":[121.355111,23.088593],"type":"Point"}
}