{
  "id": 7139071,
  "type": "Feature",
  "properties": {
    "tgn:hierarchy":[
        "tgn:7139071",
        "tgn:7000096",
        "tgn:1000003",
        "tgn:7000084",
        "tgn:7029392"
    ],
    "tgn:id":7139071,
    "tgn:name":"Libbesicke",
    "tgn:placetype":[
        "aat:300008347"
    ]
},
  "bbox": [],
  "geometry": {"coordinates":[13.666667,53.066667],"type":"Point"}
}