{
  "id": 2765710,
  "type": "Feature",
  "properties": {
    "tgn:hierarchy":[
        "tgn:2765710",
        "tgn:1000001",
        "tgn:7012149",
        "tgn:1002943",
        "tgn:7007708",
        "tgn:7029392"
    ],
    "tgn:id":2765710,
    "tgn:name":"White Creek",
    "tgn:placetype":[
        "aat:300008706"
    ]
},
  "bbox": [],
  "geometry": {"coordinates":[-123.7333,45.5167],"type":"Point"}
}