<<<<<<< HEAD
{
  "id": 2765710,
  "type": "Feature",
  "properties": {
    "tgn:hierarchy":[
        "tgn:2765710",
        "tgn:1000001",
        "tgn:7012149",
        "tgn:1002943",
        "tgn:7007708",
        "tgn:7029392"
    ],
    "tgn:id":2765710,
    "tgn:name":"White Creek",
    "tgn:placetype":[
        "aat:300008706"
    ]
},
  "bbox": [],
  "geometry": {"coordinates":[-123.7333,45.5167],"type":"Point"}
}
=======
{"geometry":{"type":"Point","coordinates":[-123.733300,45.516700]},"type":"Feature","properties":{"hierarchy":["tgn:2765710","tgn:1000001","tgn:7012149","tgn:1002943","tgn:7007708","tgn:7029392"],"placetype":["aat:300008706"],"id":2765710,"name:xx":"White Creek"}}
>>>>>>> 03f74aca74312dbeaf24d7e61306dd6a786dc3d0
