{
  "id": 1135774,
  "type": "Feature",
  "properties": {
    "tgn:hierarchy":[
        "tgn:1135774",
        "tgn:1000004",
        "tgn:7000198",
        "tgn:1001977",
        "tgn:7029392"
    ],
    "tgn:id":1135774,
    "tgn:name":"Jamira",
    "tgn:placetype":[
        "aat:300387055"
    ]
},
  "bbox": [],
  "geometry": {"coordinates":[88.466094,21.602954],"type":"Point"}
}