{
  "id": 2309819,
  "type": "Feature",
  "properties": {
    "tgn:hierarchy":[
        "tgn:2309819",
        "tgn:1000001",
        "tgn:7012149",
        "tgn:1002511",
        "tgn:7007919",
        "tgn:7029392"
    ],
    "tgn:id":2309819,
    "tgn:name":"Eastern State Hospital Reservoir",
    "tgn:placetype":[
        "aat:300006191"
    ]
},
  "bbox": [],
  "geometry": {"coordinates":[-76.75,37.2833],"type":"Point"}
}