{
  "id": 1093761,
  "type": "Feature",
  "properties": {
    "tgn:hierarchy":[
        "tgn:1093761",
        "tgn:7001242",
        "tgn:7016562",
        "tgn:1000193",
        "tgn:7029392"
    ],
    "tgn:id":1093761,
    "tgn:name":"Villiers",
    "tgn:placetype":[
        "aat:300008347"
    ]
},
  "bbox": [],
  "geometry": {"coordinates":[28.6167,-27.0333],"type":"Point"}
}