{
  "id": 2509246,
  "type": "Feature",
  "properties": {
    "tgn:hierarchy":[
        "tgn:2509246",
        "tgn:1000001",
        "tgn:7012149",
        "tgn:7022544",
        "tgn:7007825",
        "tgn:7029392"
    ],
    "tgn:id":2509246,
    "tgn:name":"Middle Fork Owl Creek",
    "tgn:placetype":[
        "aat:300008706"
    ]
},
  "bbox": [],
  "geometry": {"coordinates":[-88.4833,35.15],"type":"Point"}
}