{
  "id": 7206495,
  "type": "Feature",
  "properties": {
    "tgn:hierarchy":[
        "tgn:7206495",
        "tgn:7003669",
        "tgn:1000003",
        "tgn:7000084",
        "tgn:7029392"
    ],
    "tgn:id":7206495,
    "tgn:name":"Buch Wald",
    "tgn:placetype":[
        "aat:300008863"
    ]
},
  "bbox": [],
  "geometry": {"coordinates":[11.266667,48.316667],"type":"Point"}
}