<<<<<<< HEAD
{
  "id": 2333306,
  "type": "Feature",
  "properties": {
    "tgn:hierarchy":[
        "tgn:2333306",
        "tgn:2001732",
        "tgn:1000001",
        "tgn:7012149",
        "tgn:7007712",
        "tgn:7029392"
    ],
    "tgn:id":2333306,
    "tgn:name":"Fogarty Creek",
    "tgn:placetype":[
        "aat:300008706"
    ]
},
  "bbox": [],
  "geometry": {"coordinates":[-79.8167,32.9333],"type":"Point"}
}
=======
{"geometry":{"type":"Point","coordinates":[-79.816700,32.933300]},"type":"Feature","properties":{"hierarchy":["tgn:2333306","tgn:2001732","tgn:1000001","tgn:7012149","tgn:7007712","tgn:7029392"],"placetype":["aat:300008706"],"id":2333306,"name:xx":"Fogarty Creek"}}
>>>>>>> 03f74aca74312dbeaf24d7e61306dd6a786dc3d0
