{
  "id": 2112166,
  "type": "Feature",
  "properties": {
    "tgn:hierarchy":[
        "tgn:2112166",
        "tgn:1000001",
        "tgn:7012149",
        "tgn:2002166",
        "tgn:7007919",
        "tgn:7029392"
    ],
    "tgn:id":2112166,
    "tgn:name":"Harmony",
    "tgn:placetype":[
        "aat:300008347"
    ]
},
  "bbox": [],
  "geometry": {"coordinates":[-78.95,36.55],"type":"Point"}
}