{
  "id": 2097269,
  "type": "Feature",
  "properties": {
    "tgn:hierarchy":[
        "tgn:2097269",
        "tgn:1000001",
        "tgn:2001819",
        "tgn:7012149",
        "tgn:7007713",
        "tgn:7029392"
    ],
    "tgn:id":2097269,
    "tgn:name":"Humboldt",
    "tgn:placetype":[
        "aat:300008347"
    ]
},
  "bbox": [],
  "geometry": {"coordinates":[-97.0667,43.6333],"type":"Point"}
}