<<<<<<< HEAD
{
  "id": 7359368,
  "type": "Feature",
  "properties": {
    "tgn:hierarchy":[
        "tgn:7359368",
        "tgn:7005586",
        "tgn:1000001",
        "tgn:7005560",
        "tgn:7029392"
    ],
    "tgn:id":7359368,
    "tgn:name":"Comitl\u00e1n",
    "tgn:placetype":[
        "aat:300008347"
    ]
},
  "bbox": [],
  "geometry": {"coordinates":[-104.75,19.483333],"type":"Point"}
}
=======
{"geometry":{"type":"Point","coordinates":[-104.750000,19.483333]},"type":"Feature","properties":{"hierarchy":["tgn:7359368","tgn:7005586","tgn:1000001","tgn:7005560","tgn:7029392"],"placetype":["aat:300008347"],"id":7359368,"name:xx":"Comitl\u00e1n"}}
>>>>>>> 03f74aca74312dbeaf24d7e61306dd6a786dc3d0
