{
  "id": 7359368,
  "type": "Feature",
  "properties": {
    "tgn:hierarchy":[
        "tgn:7359368",
        "tgn:7005586",
        "tgn:1000001",
        "tgn:7005560",
        "tgn:7029392"
    ],
    "tgn:id":7359368,
    "tgn:name":"Comitl\u00e1n",
    "tgn:placetype":[
        "aat:300008347"
    ]
},
  "bbox": [],
  "geometry": {"coordinates":[-104.75,19.483333],"type":"Point"}
}