{
  "id": 2010347,
  "type": "Feature",
  "properties": {
    "tgn:hierarchy":[
        "tgn:2010347",
        "tgn:1000001",
        "tgn:7012149",
        "tgn:7007157",
        "tgn:1002857",
        "tgn:7029392"
    ],
    "tgn:id":2010347,
    "tgn:name":"Boys Republic",
    "tgn:placetype":[
        "aat:300008347"
    ]
},
  "bbox": [],
  "geometry": {"coordinates":[-117.7167,33.9833],"type":"Point"}
}