{
  "id": 7072662,
  "type": "Feature",
  "properties": {
    "tgn:hierarchy":[
        "tgn:7072662",
        "tgn:7003692",
        "tgn:1000003",
        "tgn:7000084",
        "tgn:7029392"
    ],
    "tgn:id":7072662,
    "tgn:name":"T\u00e4nzer",
    "tgn:placetype":[
        "aat:300008863"
    ]
},
  "bbox": [],
  "geometry": {"coordinates":[9.466667,49.383333],"type":"Point"}
}