{
  "id": 2057350,
  "type": "Feature",
  "properties": {
    "tgn:hierarchy":[
        "tgn:2057350",
        "tgn:1000001",
        "tgn:7012149",
        "tgn:2001146",
        "tgn:7007522",
        "tgn:7029392"
    ],
    "tgn:id":2057350,
    "tgn:name":"Richland",
    "tgn:placetype":[
        "aat:300008347"
    ]
},
  "bbox": [],
  "geometry": {"coordinates":[-90.15,32.2333],"type":"Point"}
}