{
  "id": 2076162,
  "type": "Feature",
  "properties": {
    "tgn:hierarchy":[
        "tgn:2076162",
        "tgn:1000001",
        "tgn:7012149",
        "tgn:7013940",
        "tgn:7007709",
        "tgn:7029392"
    ],
    "tgn:id":2076162,
    "tgn:name":"Pocomoke",
    "tgn:placetype":[
        "aat:300008347",
        "aat:300387210"
    ]
},
  "bbox": [],
  "geometry": {"coordinates":[-78.5333,36.0667],"type":"Point"}
}