{
  "id": 7192820,
  "type": "Feature",
  "properties": {
    "tgn:hierarchy":[
        "tgn:7192820",
        "tgn:1000003",
        "tgn:7003688",
        "tgn:7000084",
        "tgn:7029392"
    ],
    "tgn:id":7192820,
    "tgn:name":"Fahrenhorst",
    "tgn:placetype":[
        "aat:300000206"
    ]
},
  "bbox": [],
  "geometry": {"coordinates":[10.25,53.766667],"type":"Point"}
}