<<<<<<< HEAD
{
  "id": 7058839,
  "type": "Feature",
  "properties": {
    "tgn:hierarchy":[
        "tgn:7058839",
        "tgn:7015163",
        "tgn:1000003",
        "tgn:7003121",
        "tgn:1000080",
        "tgn:7029392"
    ],
    "tgn:id":7058839,
    "tgn:name":"Alidoni, Riu l'",
    "tgn:placetype":[
        "aat:300008699"
    ]
},
  "bbox": [],
  "geometry": {"coordinates":[8.316667,40.666667],"type":"Point"}
}
=======
{"geometry":{"type":"Point","coordinates":[8.316667,40.666667]},"type":"Feature","properties":{"hierarchy":["tgn:7058839","tgn:7015163","tgn:1000003","tgn:7003121","tgn:1000080","tgn:7029392"],"placetype":["aat:300008699"],"id":7058839,"name:xx":"Alidoni, Riu l'"}}
>>>>>>> 03f74aca74312dbeaf24d7e61306dd6a786dc3d0
