{
  "id": 2503315,
  "type": "Feature",
  "properties": {
    "tgn:hierarchy":[
        "tgn:2503315",
        "tgn:1000001",
        "tgn:7012149",
        "tgn:1002946",
        "tgn:7007252",
        "tgn:7029392"
    ],
    "tgn:id":2503315,
    "tgn:name":"McQuinn Estates",
    "tgn:placetype":[
        "aat:300008347"
    ]
},
  "bbox": [],
  "geometry": {"coordinates":[-86.95,40.4333],"type":"Point"}
}