{
  "id": 7329032,
  "type": "Feature",
  "properties": {
    "tgn:hierarchy":[
        "tgn:7329032",
        "tgn:7002829",
        "tgn:1000003",
        "tgn:7002786",
        "tgn:1000095",
        "tgn:7029392"
    ],
    "tgn:id":7329032,
    "tgn:name":"Pozomouro",
    "tgn:placetype":[
        "aat:300008347"
    ]
},
  "bbox": [],
  "geometry": {"coordinates":[-7.266667,43.533333],"type":"Point"}
}