{
  "id": 2586933,
  "type": "Feature",
  "properties": {
    "tgn:hierarchy":[
        "tgn:2586933",
        "tgn:1000001",
        "tgn:7012149",
        "tgn:2002099",
        "tgn:7007826",
        "tgn:7029392"
    ],
    "tgn:id":2586933,
    "tgn:name":"Plan de Barajas, Arroyo",
    "tgn:placetype":[
        "aat:300008761"
    ]
},
  "bbox": [],
  "geometry": {"coordinates":[-99.1667,26.8833],"type":"Point"}
}