{
  "id": 7349193,
  "type": "Feature",
  "properties": {
    "tgn:hierarchy":[
        "tgn:7349193",
        "tgn:1000001",
        "tgn:1001937",
        "tgn:7005560",
        "tgn:7029392"
    ],
    "tgn:id":7349193,
    "tgn:name":"Aguada Concepcion, Laguna",
    "tgn:placetype":[
        "aat:300008680"
    ]
},
  "bbox": [],
  "geometry": {"coordinates":[-89.133333,18.716667],"type":"Point"}
}