{
  "id": 7108196,
  "type": "Feature",
  "properties": {
    "tgn:hierarchy":[
        "tgn:7108196",
        "tgn:1000003",
        "tgn:7003676",
        "tgn:7000084",
        "tgn:7029392"
    ],
    "tgn:id":7108196,
    "tgn:name":"Rehkopf-Berg",
    "tgn:placetype":[
        "aat:300008777"
    ]
},
  "bbox": [],
  "geometry": {"coordinates":[10.166667,51.783333],"type":"Point"}
}