{
  "id": 7573356,
  "type": "Feature",
  "properties": {
    "tgn:hierarchy":[
        "tgn:7573356",
        "tgn:1000004",
        "tgn:7000198",
        "tgn:7000799",
        "tgn:7029392"
    ],
    "tgn:id":7573356,
    "tgn:name:en":"Inshan",
    "tgn:placetype":[
        "aat:300008347"
    ]
},
  "bbox": [],
  "geometry": {"coordinates":[75.566797,33.812606],"type":"Point"}
}