{
  "id": 1127130,
  "type": "Feature",
  "properties": {
    "tgn:hierarchy":[
        "tgn:1127130",
        "tgn:1000001",
        "tgn:7012149",
        "tgn:7007157",
        "tgn:1002861",
        "tgn:7029392"
    ],
    "tgn:id":1127130,
    "tgn:name":"Middle",
    "tgn:placetype":[
        "aat:300008707"
    ]
},
  "bbox": [],
  "geometry": {"coordinates":[-121.3667,37.8167],"type":"Point"}
}