<<<<<<< HEAD
{
  "id": 2339915,
  "type": "Feature",
  "properties": {
    "tgn:hierarchy":[
        "tgn:2339915",
        "tgn:1000001",
        "tgn:7012149",
        "tgn:2001761",
        "tgn:7007712",
        "tgn:7029392"
    ],
    "tgn:id":2339915,
    "tgn:name":"Freeman Pond",
    "tgn:placetype":[
        "aat:300006191"
    ]
},
  "bbox": [],
  "geometry": {"coordinates":[-83.1167,34.6333],"type":"Point"}
}
=======
{"geometry":{"type":"Point","coordinates":[-83.116700,34.633300]},"type":"Feature","properties":{"hierarchy":["tgn:2339915","tgn:1000001","tgn:7012149","tgn:2001761","tgn:7007712","tgn:7029392"],"placetype":["aat:300006191"],"id":2339915,"name:xx":"Freeman Pond"}}
>>>>>>> 03f74aca74312dbeaf24d7e61306dd6a786dc3d0
