{
  "id": 7307900,
  "type": "Feature",
  "properties": {
    "tgn:hierarchy":[
        "tgn:7307900",
        "tgn:7002464",
        "tgn:1000049",
        "tgn:1000002",
        "tgn:7029392"
    ],
    "tgn:id":7307900,
    "tgn:name":"Negra, Pampa",
    "tgn:placetype":[
        "aat:300008805"
    ]
},
  "bbox": [],
  "geometry": {"coordinates":[-68.683333,-20.583333],"type":"Point"}
}