{
  "id": 2602938,
  "type": "Feature",
  "properties": {
    "tgn:hierarchy":[
        "tgn:2602938",
        "tgn:1000001",
        "tgn:7012149",
        "tgn:2002189",
        "tgn:7007919",
        "tgn:7029392"
    ],
    "tgn:id":2602938,
    "tgn:name":"Qualles Cave",
    "tgn:placetype":[
        "aat:300008746"
    ]
},
  "bbox": [],
  "geometry": {"coordinates":[-82.8333,36.6333],"type":"Point"}
}