<<<<<<< HEAD
{
  "id": 2406718,
  "type": "Feature",
  "properties": {
    "tgn:hierarchy":[
        "tgn:2406718",
        "tgn:2001001",
        "tgn:1000001",
        "tgn:7012149",
        "tgn:7007521",
        "tgn:7029392"
    ],
    "tgn:id":2406718,
    "tgn:name":"Hunt Lake",
    "tgn:placetype":[
        "aat:300008680"
    ]
},
  "bbox": [],
  "geometry": {"coordinates":[-95.9667,46.75],"type":"Point"}
}
=======
{"geometry":{"type":"Point","coordinates":[-95.966700,46.750000]},"type":"Feature","properties":{"hierarchy":["tgn:2406718","tgn:2001001","tgn:1000001","tgn:7012149","tgn:7007521","tgn:7029392"],"placetype":["aat:300008680"],"id":2406718,"name:xx":"Hunt Lake"}}
>>>>>>> 03f74aca74312dbeaf24d7e61306dd6a786dc3d0
