{
  "id": 7467257,
  "type": "Feature",
  "properties": {
    "tgn:hierarchy":[
        "tgn:7467257",
        "tgn:7469009",
        "tgn:1000004",
        "tgn:1000141",
        "tgn:7029392"
    ],
    "tgn:id":7467257,
    "tgn:name":"Qianpu",
    "tgn:placetype":[
        "aat:300008347"
    ]
},
  "bbox": [],
  "geometry": {"coordinates":[118.425833,24.450556],"type":"Point"}
}