{
  "id": 2185962,
  "type": "Feature",
  "properties": {
    "tgn:hierarchy":[
        "tgn:2185962",
        "tgn:1000001",
        "tgn:7012149",
        "tgn:2002266",
        "tgn:7013961",
        "tgn:7029392"
    ],
    "tgn:id":2185962,
    "tgn:name":"Bollinger Knob",
    "tgn:placetype":[
        "aat:300008798"
    ]
},
  "bbox": [],
  "geometry": {"coordinates":[-78.6833,38.9833],"type":"Point"}
}