{
  "id": 7547800,
  "type": "Feature",
  "properties": {
    "tgn:hierarchy":[
        "tgn:7547800",
        "tgn:1000004",
        "tgn:7000198",
        "tgn:7016694",
        "tgn:7029392"
    ],
    "tgn:id":7547800,
    "tgn:name:en":"Astaranga",
    "tgn:placetype":[
        "aat:300008347"
    ]
},
  "bbox": [],
  "geometry": {"coordinates":[86.270117,19.981356],"type":"Point"}
}