{
  "id": 2601183,
  "type": "Feature",
  "properties": {
    "tgn:hierarchy":[
        "tgn:2601183",
        "tgn:1000001",
        "tgn:7012149",
        "tgn:7007709",
        "tgn:7029392"
    ],
    "tgn:id":2601183,
    "tgn:name":"Pungo River Alligator River Canal",
    "tgn:placetype":[
        "aat:300006075"
    ]
},
  "bbox": [],
  "geometry": {"coordinates":[-76.2667,35.5833],"type":"Point"}
}