{
  "id": 7443847,
  "type": "Feature",
  "properties": {
    "tgn:hierarchy":[
        "tgn:7443847",
        "tgn:7002445",
        "tgn:1000003",
        "tgn:7008165",
        "tgn:7008591",
        "tgn:7029392"
    ],
    "tgn:id":7443847,
    "tgn:name:en":"Yetlington",
    "tgn:placetype":[
        "aat:300008347"
    ]
},
  "bbox": [],
  "geometry": {"coordinates":[-1.966667,55.366667],"type":"Point"}
}