{
  "id": 2607409,
  "type": "Feature",
  "properties": {
    "tgn:hierarchy":[
        "tgn:2607409",
        "tgn:1000001",
        "tgn:7006451",
        "tgn:2000092",
        "tgn:7012149",
        "tgn:7029392"
    ],
    "tgn:id":2607409,
    "tgn:name":"Ranger Pass Trick Tank",
    "tgn:placetype":[
        "aat:300006191"
    ]
},
  "bbox": [],
  "geometry": {"coordinates":[-112.4833,36.5833],"type":"Point"}
}