{
  "id": 2413582,
  "type": "Feature",
  "properties": {
    "tgn:hierarchy":[
        "tgn:2413582",
        "tgn:1000001",
        "tgn:1002539",
        "tgn:7012149",
        "tgn:7007516",
        "tgn:7029392"
    ],
    "tgn:id":2413582,
    "tgn:name":"Irelands Corner",
    "tgn:placetype":[
        "aat:300008347"
    ]
},
  "bbox": [],
  "geometry": {"coordinates":[-75.8667,39.3167],"type":"Point"}
}