{
  "id": 7168773,
  "type": "Feature",
  "properties": {
    "tgn:hierarchy":[
        "tgn:7168773",
        "tgn:1000003",
        "tgn:7003688",
        "tgn:7000084",
        "tgn:7029392"
    ],
    "tgn:id":7168773,
    "tgn:name":"Ha\u00dfberg",
    "tgn:placetype":[
        "aat:300008347"
    ]
},
  "bbox": [],
  "geometry": {"coordinates":[10.65,54.316667],"type":"Point"}
}