{
  "id": 7279408,
  "type": "Feature",
  "properties": {
    "tgn:hierarchy":[
        "tgn:7279408",
        "tgn:1001695",
        "tgn:1000049",
        "tgn:1000002",
        "tgn:7029392"
    ],
    "tgn:id":7279408,
    "tgn:name":"Risco, Cerro",
    "tgn:placetype":[
        "aat:300008795"
    ]
},
  "bbox": [],
  "geometry": {"coordinates":[-70.816667,-34.466667],"type":"Point"}
}