{
  "id": 2213311,
  "type": "Feature",
  "properties": {
    "tgn:hierarchy":[
        "tgn:2213311",
        "tgn:1000001",
        "tgn:7012149",
        "tgn:1002897",
        "tgn:7007920",
        "tgn:7029392"
    ],
    "tgn:id":2213311,
    "tgn:name":"Cabin Creek",
    "tgn:placetype":[
        "aat:300008706"
    ]
},
  "bbox": [],
  "geometry": {"coordinates":[-121.9667,46.2833],"type":"Point"}
}