{
  "id": 2054035,
  "type": "Feature",
  "properties": {
    "tgn:hierarchy":[
        "tgn:2054035",
        "tgn:1000001",
        "tgn:7012149",
        "tgn:2001067",
        "tgn:7007521",
        "tgn:7029392"
    ],
    "tgn:id":2054035,
    "tgn:name":"Brimson",
    "tgn:placetype":[
        "aat:300008347"
    ]
},
  "bbox": [],
  "geometry": {"coordinates":[-91.8667,47.2667],"type":"Point"}
}