<<<<<<< HEAD
{
  "id": 7246946,
  "type": "Feature",
  "properties": {
    "tgn:hierarchy":[
        "tgn:7246946",
        "tgn:7003466",
        "tgn:1000003",
        "tgn:1000063",
        "tgn:4012014",
        "tgn:7029392"
    ],
    "tgn:id":7246946,
    "tgn:name":"Castagne, Bois",
    "tgn:placetype":[
        "aat:300008863"
    ]
},
  "bbox": [],
  "geometry": {"coordinates":[4.835052,50.361586],"type":"Point"}
}
=======
{"geometry":{"type":"Point","coordinates":[4.835052,50.361586]},"type":"Feature","properties":{"hierarchy":["tgn:7246946","tgn:7003466","tgn:1000003","tgn:1000063","tgn:4012014","tgn:7029392"],"placetype":["aat:300008863"],"id":7246946,"name:xx":"Castagne, Bois"}}
>>>>>>> 03f74aca74312dbeaf24d7e61306dd6a786dc3d0
