{
  "id": 2094333,
  "type": "Feature",
  "properties": {
    "tgn:hierarchy":[
        "tgn:2094333",
        "tgn:1000001",
        "tgn:1002308",
        "tgn:7012149",
        "tgn:7007710",
        "tgn:7029392"
    ],
    "tgn:id":2094333,
    "tgn:name":"Westford",
    "tgn:placetype":[
        "aat:300008347"
    ]
},
  "bbox": [],
  "geometry": {"coordinates":[-80.4667,41.55],"type":"Point"}
}