<<<<<<< HEAD
{
  "id": 2254150,
  "type": "Feature",
  "properties": {
    "tgn:hierarchy":[
        "tgn:2254150",
        "tgn:1000001",
        "tgn:1002724",
        "tgn:7012149",
        "tgn:7007517",
        "tgn:7029392"
    ],
    "tgn:id":2254150,
    "tgn:name":"Coolidge Corner",
    "tgn:placetype":[
        "aat:300008347"
    ]
},
  "bbox": [],
  "geometry": {"coordinates":[-71.1167,42.3333],"type":"Point"}
}
=======
{"geometry":{"type":"Point","coordinates":[-71.116700,42.333300]},"type":"Feature","properties":{"hierarchy":["tgn:2254150","tgn:1000001","tgn:1002724","tgn:7012149","tgn:7007517","tgn:7029392"],"placetype":["aat:300008347"],"id":2254150,"name:xx":"Coolidge Corner"}}
>>>>>>> 03f74aca74312dbeaf24d7e61306dd6a786dc3d0
