{
  "id": 2254150,
  "type": "Feature",
  "properties": {
    "tgn:hierarchy":[
        "tgn:2254150",
        "tgn:1000001",
        "tgn:1002724",
        "tgn:7012149",
        "tgn:7007517",
        "tgn:7029392"
    ],
    "tgn:id":2254150,
    "tgn:name":"Coolidge Corner",
    "tgn:placetype":[
        "aat:300008347"
    ]
},
  "bbox": [],
  "geometry": {"coordinates":[-71.1167,42.3333],"type":"Point"}
}