<<<<<<< HEAD
{
  "id": 2258652,
  "type": "Feature",
  "properties": {
    "tgn:hierarchy":[
        "tgn:2258652",
        "tgn:1000001",
        "tgn:2001411",
        "tgn:7012149",
        "tgn:7007526",
        "tgn:7029392"
    ],
    "tgn:id":2258652,
    "tgn:name":"Cottonwood Canon",
    "tgn:placetype":[
        "aat:300008761"
    ]
},
  "bbox": [],
  "geometry": {"coordinates":[-114.7167,41.6833],"type":"Point"}
}
=======
{"geometry":{"type":"Point","coordinates":[-114.716700,41.683300]},"type":"Feature","properties":{"hierarchy":["tgn:2258652","tgn:1000001","tgn:2001411","tgn:7012149","tgn:7007526","tgn:7029392"],"placetype":["aat:300008761"],"id":2258652,"name:xx":"Cottonwood Canon"}}
>>>>>>> 03f74aca74312dbeaf24d7e61306dd6a786dc3d0
