{
  "id": 7406174,
  "type": "Feature",
  "properties": {
    "tgn:hierarchy":[
        "tgn:7406174",
        "tgn:7005585",
        "tgn:1000001",
        "tgn:7005560",
        "tgn:7029392"
    ],
    "tgn:id":7406174,
    "tgn:name":"Iglesia Vieja",
    "tgn:placetype":[
        "aat:300008347"
    ]
},
  "bbox": [],
  "geometry": {"coordinates":[-99.866667,18.116667],"type":"Point"}
}