{
  "id": 1067819,
  "type": "Feature",
  "properties": {
    "tgn:hierarchy":[
        "tgn:1067819",
        "tgn:1000004",
        "tgn:7001319",
        "tgn:1000111",
        "tgn:7029392"
    ],
    "tgn:id":1067819,
    "tgn:name":"Dongshaer",
    "tgn:placetype":[
        "aat:300008347"
    ]
},
  "bbox": [],
  "geometry": {"coordinates":[89.15,28.6833],"type":"Point"}
}