{
  "id": 2535044,
  "type": "Feature",
  "properties": {
    "tgn:hierarchy":[
        "tgn:2535044",
        "tgn:1000001",
        "tgn:7012149",
        "tgn:2001717",
        "tgn:7007708",
        "tgn:7029392"
    ],
    "tgn:id":2535044,
    "tgn:name":"Nan-Scott Lake",
    "tgn:placetype":[
        "aat:300008680"
    ]
},
  "bbox": [],
  "geometry": {"coordinates":[-121.95,44.6167],"type":"Point"}
}