{
  "id": 7548015,
  "type": "Feature",
  "properties": {
    "tgn:hierarchy":[
        "tgn:7548015",
        "tgn:1000004",
        "tgn:7000198",
        "tgn:7016694",
        "tgn:7029392"
    ],
    "tgn:id":7548015,
    "tgn:name:en":"B\u0101nsjor",
    "tgn:placetype":[
        "aat:300008347"
    ]
},
  "bbox": [],
  "geometry": {"coordinates":[84.716667,22.416667],"type":"Point"}
}