{
  "id": 2282547,
  "type": "Feature",
  "properties": {
    "tgn:hierarchy":[
        "tgn:2282547",
        "tgn:1000001",
        "tgn:7012149",
        "tgn:2001708",
        "tgn:7007708",
        "tgn:7029392"
    ],
    "tgn:id":2282547,
    "tgn:name":"Deer Spring",
    "tgn:placetype":[
        "aat:300008697"
    ]
},
  "bbox": [],
  "geometry": {"coordinates":[-118.7667,44.2667],"type":"Point"}
}