{
  "id": 7206039,
  "type": "Feature",
  "properties": {
    "tgn:hierarchy":[
        "tgn:7206039",
        "tgn:1000003",
        "tgn:7003682",
        "tgn:7000084",
        "tgn:7029392"
    ],
    "tgn:id":7206039,
    "tgn:name":"Budenbach",
    "tgn:placetype":[
        "aat:300008347"
    ]
},
  "bbox": [],
  "geometry": {"coordinates":[7.566667,50.033333],"type":"Point"}
}