{
  "id": 2173357,
  "type": "Feature",
  "properties": {
    "tgn:hierarchy":[
        "tgn:2173357",
        "tgn:1000001",
        "tgn:7012149",
        "tgn:2001708",
        "tgn:7007708",
        "tgn:7029392"
    ],
    "tgn:id":2173357,
    "tgn:name":"Birch Creek",
    "tgn:placetype":[
        "aat:300008706"
    ]
},
  "bbox": [],
  "geometry": {"coordinates":[-119.3833,44.95],"type":"Point"}
}