<<<<<<< HEAD
{
  "id": 2702236,
  "type": "Feature",
  "properties": {
    "tgn:hierarchy":[
        "tgn:2702236",
        "tgn:1000001",
        "tgn:7012149",
        "tgn:1003038",
        "tgn:7007517",
        "tgn:7029392"
    ],
    "tgn:id":2702236,
    "tgn:name":"Sullivan Brook",
    "tgn:placetype":[
        "aat:300008699"
    ]
},
  "bbox": [],
  "geometry": {"coordinates":[-72.2,42.25],"type":"Point"}
}
=======
{"geometry":{"type":"Point","coordinates":[-72.200000,42.250000]},"type":"Feature","properties":{"hierarchy":["tgn:2702236","tgn:1000001","tgn:7012149","tgn:1003038","tgn:7007517","tgn:7029392"],"placetype":["aat:300008699"],"id":2702236,"name:xx":"Sullivan Brook"}}
>>>>>>> 03f74aca74312dbeaf24d7e61306dd6a786dc3d0
