{
  "id": 2695054,
  "type": "Feature",
  "properties": {
    "tgn:hierarchy":[
        "tgn:2695054",
        "tgn:1000001",
        "tgn:7012149",
        "tgn:2001714",
        "tgn:7007708",
        "tgn:7029392"
    ],
    "tgn:id":2695054,
    "tgn:name":"Still Spring",
    "tgn:placetype":[
        "aat:300008697"
    ]
},
  "bbox": [],
  "geometry": {"coordinates":[-121.35,43.05],"type":"Point"}
}