{
  "id": 2513051,
  "type": "Feature",
  "properties": {
    "tgn:hierarchy":[
        "tgn:2513051",
        "tgn:1000001",
        "tgn:7012149",
        "tgn:1002911",
        "tgn:7007919",
        "tgn:7029392"
    ],
    "tgn:id":2513051,
    "tgn:name":"Mill Creek",
    "tgn:placetype":[
        "aat:300008706"
    ]
},
  "bbox": [],
  "geometry": {"coordinates":[-77.0167,36.55],"type":"Point"}
}