{
  "id": 2748275,
  "type": "Feature",
  "properties": {
    "tgn:hierarchy":[
        "tgn:2748275",
        "tgn:1000001",
        "tgn:7012149",
        "tgn:2002046",
        "tgn:7007826",
        "tgn:7029392"
    ],
    "tgn:id":2748275,
    "tgn:name":"Walker Canyon",
    "tgn:placetype":[
        "aat:300008761"
    ]
},
  "bbox": [],
  "geometry": {"coordinates":[-100.7667,34.1333],"type":"Point"}
}