{
  "id": 2574371,
  "type": "Feature",
  "properties": {
    "tgn:hierarchy":[
        "tgn:2574371",
        "tgn:2000943",
        "tgn:1000001",
        "tgn:7012149",
        "tgn:7007520",
        "tgn:7029392"
    ],
    "tgn:id":2574371,
    "tgn:name":"Pelican Lake",
    "tgn:placetype":[
        "aat:300008680"
    ]
},
  "bbox": [],
  "geometry": {"coordinates":[-86.1333,46.55],"type":"Point"}
}