{
  "id": 2008425,
  "type": "Feature",
  "properties": {
    "tgn:hierarchy":[
        "tgn:2008425",
        "tgn:1000001",
        "tgn:7016172",
        "tgn:7012149",
        "tgn:2000147",
        "tgn:7029392"
    ],
    "tgn:id":2008425,
    "tgn:name":"Hamilton",
    "tgn:placetype":[
        "aat:300008347",
        "aat:300387210"
    ]
},
  "bbox": [],
  "geometry": {"coordinates":[-91.7167,34.6167],"type":"Point"}
}