{
  "id": 7558071,
  "type": "Feature",
  "properties": {
    "tgn:hierarchy":[
        "tgn:7558071",
        "tgn:1000004",
        "tgn:7000198",
        "tgn:1001905",
        "tgn:7029392"
    ],
    "tgn:id":7558071,
    "tgn:name:en":"Priphema",
    "tgn:placetype":[
        "aat:300008347"
    ]
},
  "bbox": [],
  "geometry": {"coordinates":[93.969589,25.744619],"type":"Point"}
}