{
  "id": 7159490,
  "type": "Feature",
  "properties": {
    "tgn:hierarchy":[
        "tgn:7159490",
        "tgn:7003669",
        "tgn:1000003",
        "tgn:7000084",
        "tgn:7029392"
    ],
    "tgn:id":7159490,
    "tgn:name":"Holzhausen",
    "tgn:placetype":[
        "aat:300008347"
    ]
},
  "bbox": [],
  "geometry": {"coordinates":[11.85,48.233333],"type":"Point"}
}