{
  "id": 7320085,
  "type": "Feature",
  "properties": {
    "tgn:hierarchy":[
        "tgn:7320085",
        "tgn:7016598",
        "tgn:1000049",
        "tgn:1000002",
        "tgn:7029392"
    ],
    "tgn:id":7320085,
    "tgn:name":"Estaci\u00f3n Aguas Blancas",
    "tgn:placetype":[
        "aat:300007783"
    ]
},
  "bbox": [],
  "geometry": {"coordinates":[-69.85,-24.183333],"type":"Point"}
}