{
  "id": 7461077,
  "type": "Feature",
  "properties": {
    "tgn:hierarchy":[
        "tgn:7461077",
        "tgn:7002445",
        "tgn:1000003",
        "tgn:5000227",
        "tgn:7008591",
        "tgn:7029392"
    ],
    "tgn:id":7461077,
    "tgn:name:en":"Holberrow Green",
    "tgn:placetype":[
        "aat:300008347"
    ]
},
  "bbox": [],
  "geometry": {"coordinates":[-1.95,52.216667],"type":"Point"}
}