{
  "id": 7572003,
  "type": "Feature",
  "properties": {
    "tgn:hierarchy":[
        "tgn:7572003",
        "tgn:1009838",
        "tgn:7000204",
        "tgn:1000004",
        "tgn:7000198",
        "tgn:7029392"
    ],
    "tgn:id":7572003,
    "tgn:name:en":"Fusilier Channel",
    "tgn:placetype":[
        "aat:300008713"
    ]
},
  "bbox": [],
  "geometry": {"coordinates":[93.05,11.866667],"type":"Point"}
}