{
  "id": 1036981,
  "type": "Feature",
  "properties": {
    "tgn:hierarchy":[
        "tgn:1036981",
        "tgn:7000096",
        "tgn:1000003",
        "tgn:7000084",
        "tgn:7029392"
    ],
    "tgn:id":1036981,
    "tgn:name":"Hosena",
    "tgn:placetype":[
        "aat:300008347"
    ]
},
  "bbox": [],
  "geometry": {"coordinates":[14.016667,51.45],"type":"Point"}
}