{
  "id": 2455101,
  "type": "Feature",
  "properties": {
    "tgn:hierarchy":[
        "tgn:2455101",
        "tgn:1000001",
        "tgn:7012149",
        "tgn:1002401",
        "tgn:7007826",
        "tgn:7029392"
    ],
    "tgn:id":2455101,
    "tgn:name":"Little Elmgrove Bayou",
    "tgn:placetype":[
        "aat:300132316"
    ]
},
  "bbox": [],
  "geometry": {"coordinates":[-94.6667,29.4667],"type":"Point"}
}