{
  "id": 1012104,
  "type": "Feature",
  "properties": {
    "tgn:hierarchy":[
        "tgn:1012104",
        "tgn:7002445",
        "tgn:7008116",
        "tgn:1000003",
        "tgn:7008591",
        "tgn:7029392"
    ],
    "tgn:id":1012104,
    "tgn:name:en":"Lizard Point",
    "tgn:placetype":[
        "aat:300386846"
    ]
},
  "bbox": [],
  "geometry": {"coordinates":[-5.216667,49.966667],"type":"Point"}
}