{
  "id": 2229108,
  "type": "Feature",
  "properties": {
    "tgn:hierarchy":[
        "tgn:2229108",
        "tgn:1000001",
        "tgn:7012149",
        "tgn:2002387",
        "tgn:7007923",
        "tgn:7029392"
    ],
    "tgn:id":2229108,
    "tgn:name":"Cedar Knoll",
    "tgn:placetype":[
        "aat:300008798"
    ]
},
  "bbox": [],
  "geometry": {"coordinates":[-104.4833,44.1333],"type":"Point"}
}