{
  "id": 2684725,
  "type": "Feature",
  "properties": {
    "tgn:hierarchy":[
        "tgn:2684725",
        "tgn:1000001",
        "tgn:7012149",
        "tgn:2000479",
        "tgn:7007250",
        "tgn:7029392"
    ],
    "tgn:id":2684725,
    "tgn:name":"Spirit Lake",
    "tgn:placetype":[
        "aat:300008680"
    ]
},
  "bbox": [],
  "geometry": {"coordinates":[-116.8833,47.9333],"type":"Point"}
}