{
  "id": 2578470,
  "type": "Feature",
  "properties": {
    "tgn:hierarchy":[
        "tgn:2578470",
        "tgn:1000001",
        "tgn:7012149",
        "tgn:2000715",
        "tgn:7007254",
        "tgn:7029392"
    ],
    "tgn:id":2578470,
    "tgn:name":"Phenis Creek",
    "tgn:placetype":[
        "aat:300008706"
    ]
},
  "bbox": [],
  "geometry": {"coordinates":[-96.2833,38.2667],"type":"Point"}
}