{
  "id": 7312002,
  "type": "Feature",
  "properties": {
    "tgn:hierarchy":[
        "tgn:7312002",
        "tgn:1001708",
        "tgn:1000049",
        "tgn:1000002",
        "tgn:7029392"
    ],
    "tgn:id":7312002,
    "tgn:name":"Las Fun\u00edones, Loma de",
    "tgn:placetype":[
        "aat:300387002"
    ]
},
  "bbox": [],
  "geometry": {"coordinates":[-70.55,-33.833333],"type":"Point"}
}