{
  "id": 7358302,
  "type": "Feature",
  "properties": {
    "tgn:hierarchy":[
        "tgn:7358302",
        "tgn:1000001",
        "tgn:7005599",
        "tgn:7005560",
        "tgn:7029392"
    ],
    "tgn:id":7358302,
    "tgn:name":"Coyol",
    "tgn:placetype":[
        "aat:300007783"
    ]
},
  "bbox": [],
  "geometry": {"coordinates":[-96.033333,18.266667],"type":"Point"}
}