<<<<<<< HEAD
{
  "id": 2151499,
  "type": "Feature",
  "properties": {
    "tgn:hierarchy":[
        "tgn:2151499",
        "tgn:1000001",
        "tgn:7012149",
        "tgn:1002391",
        "tgn:7007826",
        "tgn:7029392"
    ],
    "tgn:id":2151499,
    "tgn:name":"Batsmith Creek",
    "tgn:placetype":[
        "aat:300008706"
    ]
},
  "bbox": [],
  "geometry": {"coordinates":[-96.0333,31.7333],"type":"Point"}
}
=======
{"geometry":{"type":"Point","coordinates":[-96.033300,31.733300]},"type":"Feature","properties":{"hierarchy":["tgn:2151499","tgn:1000001","tgn:7012149","tgn:1002391","tgn:7007826","tgn:7029392"],"placetype":["aat:300008706"],"id":2151499,"name:xx":"Batsmith Creek"}}
>>>>>>> 03f74aca74312dbeaf24d7e61306dd6a786dc3d0
