{
  "id": 1070626,
  "type": "Feature",
  "properties": {
    "tgn:hierarchy":[
        "tgn:1070626",
        "tgn:1000004",
        "tgn:7002081",
        "tgn:1000111",
        "tgn:7029392"
    ],
    "tgn:id":1070626,
    "tgn:name":"Nanmatang",
    "tgn:placetype":[
        "aat:300008347"
    ]
},
  "bbox": [],
  "geometry": {"coordinates":[120.65,32.3167],"type":"Point"}
}