{
  "id": 2049067,
  "type": "Feature",
  "properties": {
    "tgn:hierarchy":[
        "tgn:2049067",
        "tgn:7016099",
        "tgn:1000001",
        "tgn:7012149",
        "tgn:7007516",
        "tgn:7029392"
    ],
    "tgn:id":2049067,
    "tgn:name":"Vernon",
    "tgn:placetype":[
        "aat:300008347",
        "aat:300387210"
    ]
},
  "bbox": [],
  "geometry": {"coordinates":[-76.5833,39.6333],"type":"Point"}
}