{
  "id": 2221800,
  "type": "Feature",
  "properties": {
    "tgn:hierarchy":[
        "tgn:2221800",
        "tgn:1000001",
        "tgn:7012149",
        "tgn:2002383",
        "tgn:7007923",
        "tgn:7029392"
    ],
    "tgn:id":2221800,
    "tgn:name":"Carlson Draw",
    "tgn:placetype":[
        "aat:300008761"
    ]
},
  "bbox": [],
  "geometry": {"coordinates":[-109.45,42.05],"type":"Point"}
}