{
  "id": 2545792,
  "type": "Feature",
  "properties": {
    "tgn:hierarchy":[
        "tgn:2545792",
        "tgn:1000001",
        "tgn:7012149",
        "tgn:7007708",
        "tgn:7029392"
    ],
    "tgn:id":2545792,
    "tgn:name":"North Fork Corral Creek",
    "tgn:placetype":[
        "aat:300008706"
    ]
},
  "bbox": [],
  "geometry": {"coordinates":[-122.85,45.3167],"type":"Point"}
}