{
  "id": 1092770,
  "type": "Feature",
  "properties": {
    "tgn:hierarchy":[
        "tgn:1092770",
        "tgn:7001242",
        "tgn:1001687",
        "tgn:1000192",
        "tgn:7029392"
    ],
    "tgn:id":1092770,
    "tgn:name":"Solola",
    "tgn:placetype":[
        "aat:300008347"
    ]
},
  "bbox": [],
  "geometry": {"coordinates":[41.5167,0.1167],"type":"Point"}
}