{
  "id": 7242235,
  "type": "Feature",
  "properties": {
    "tgn:hierarchy":[
        "tgn:7242235",
        "tgn:7003457",
        "tgn:1000003",
        "tgn:1000063",
        "tgn:7018236",
        "tgn:7029392"
    ],
    "tgn:id":7242235,
    "tgn:name":"Lobe",
    "tgn:placetype":[
        "aat:300008347"
    ]
},
  "bbox": [],
  "geometry": {"coordinates":[3.781029,50.764517],"type":"Point"}
}