<<<<<<< HEAD
{
  "id": 7242235,
  "type": "Feature",
  "properties": {
    "tgn:hierarchy":[
        "tgn:7242235",
        "tgn:7003457",
        "tgn:1000003",
        "tgn:1000063",
        "tgn:7018236",
        "tgn:7029392"
    ],
    "tgn:id":7242235,
    "tgn:name":"Lobe",
    "tgn:placetype":[
        "aat:300008347"
    ]
},
  "bbox": [],
  "geometry": {"coordinates":[3.781029,50.764517],"type":"Point"}
}
=======
{"geometry":{"type":"Point","coordinates":[3.781029,50.764517]},"type":"Feature","properties":{"hierarchy":["tgn:7242235","tgn:7003457","tgn:1000003","tgn:1000063","tgn:7018236","tgn:7029392"],"placetype":["aat:300008347"],"id":7242235,"name:xx":"Lobe"}}
>>>>>>> 03f74aca74312dbeaf24d7e61306dd6a786dc3d0
