{
  "id": 7029759,
  "type": "Feature",
  "properties": {
    "tgn:hierarchy":[
        "tgn:7029759",
        "tgn:7002878",
        "tgn:1000003",
        "tgn:1000070",
        "tgn:7029392"
    ],
    "tgn:id":7029759,
    "tgn:name:fr":"Saint-Jean-le-Vieux",
    "tgn:placetype":[
        "aat:300008347",
        "aat:300007466"
    ]
},
  "bbox": [],
  "geometry": {"coordinates":[-1.186,43.166],"type":"Point"}
}