<<<<<<< HEAD
{
  "id": 7029759,
  "type": "Feature",
  "properties": {
    "tgn:hierarchy":[
        "tgn:7029759",
        "tgn:7002878",
        "tgn:1000003",
        "tgn:1000070",
        "tgn:7029392"
    ],
    "tgn:id":7029759,
    "tgn:name:fr":"Saint-Jean-le-Vieux",
    "tgn:placetype":[
        "aat:300008347",
        "aat:300007466"
    ]
},
  "bbox": [],
  "geometry": {"coordinates":[-1.186,43.166],"type":"Point"}
}
=======
{"geometry":{"type":"Point","coordinates":[-1.186000,43.166000]},"type":"Feature","properties":{"hierarchy":["tgn:7029759","tgn:7002878","tgn:1000003","tgn:1000070","tgn:7029392"],"placetype":["aat:300008347","aat:300007466"],"name:fr":"Saint-Jean-le-Vieux","id":7029759}}
>>>>>>> 03f74aca74312dbeaf24d7e61306dd6a786dc3d0
