{
  "id": 7086306,
  "type": "Feature",
  "properties": {
    "tgn:hierarchy":[
        "tgn:7086306",
        "tgn:7003692",
        "tgn:1000003",
        "tgn:7000084",
        "tgn:7029392"
    ],
    "tgn:id":7086306,
    "tgn:name":"Waldrems",
    "tgn:placetype":[
        "aat:300008347"
    ]
},
  "bbox": [],
  "geometry": {"coordinates":[9.433333,48.916667],"type":"Point"}
}