{
  "id": 7183672,
  "type": "Feature",
  "properties": {
    "tgn:hierarchy":[
        "tgn:7183672",
        "tgn:1000003",
        "tgn:7003682",
        "tgn:7000084",
        "tgn:7029392"
    ],
    "tgn:id":7183672,
    "tgn:name":"Gillenbeuren",
    "tgn:placetype":[
        "aat:300008347"
    ]
},
  "bbox": [],
  "geometry": {"coordinates":[7.016667,50.15],"type":"Point"}
}