<<<<<<< HEAD
{
  "id": 7021708,
  "type": "Feature",
  "properties": {
    "tgn:hierarchy":[
        "tgn:7021708",
        "tgn:1000001",
        "tgn:7012149",
        "tgn:1002898",
        "tgn:7007826",
        "tgn:7029392"
    ],
    "tgn:id":7021708,
    "tgn:name":"Greenbriar Lake",
    "tgn:placetype":[
        "aat:300006191"
    ]
},
  "bbox": [],
  "geometry": {"coordinates":[-95.3667,32.3167],"type":"Point"}
}
=======
{"geometry":{"type":"Point","coordinates":[-95.366700,32.316700]},"type":"Feature","properties":{"hierarchy":["tgn:7021708","tgn:1000001","tgn:7012149","tgn:1002898","tgn:7007826","tgn:7029392"],"placetype":["aat:300006191"],"id":7021708,"name:xx":"Greenbriar Lake"}}
>>>>>>> 03f74aca74312dbeaf24d7e61306dd6a786dc3d0
