<<<<<<< HEAD
{
  "id": 2767190,
  "type": "Feature",
  "properties": {
    "tgn:hierarchy":[
        "tgn:2767190",
        "tgn:1000001",
        "tgn:2001411",
        "tgn:7012149",
        "tgn:7007526",
        "tgn:7029392"
    ],
    "tgn:id":2767190,
    "tgn:name":"White Rock Mine",
    "tgn:placetype":[
        "aat:300000390"
    ]
},
  "bbox": [],
  "geometry": {"coordinates":[-116.1167,41.7],"type":"Point"}
}
=======
{"geometry":{"type":"Point","coordinates":[-116.116700,41.700000]},"type":"Feature","properties":{"hierarchy":["tgn:2767190","tgn:1000001","tgn:2001411","tgn:7012149","tgn:7007526","tgn:7029392"],"placetype":["aat:300000390"],"id":2767190,"name:xx":"White Rock Mine"}}
>>>>>>> 03f74aca74312dbeaf24d7e61306dd6a786dc3d0
