{
  "id": 7042297,
  "type": "Feature",
  "properties": {
    "tgn:hierarchy":[
        "tgn:7042297",
        "tgn:7005765",
        "tgn:1000003",
        "tgn:7003237",
        "tgn:1000080",
        "tgn:7029392"
    ],
    "tgn:id":7042297,
    "tgn:name":"Rocca d'Anfo",
    "tgn:placetype":[
        "aat:300008347"
    ]
},
  "bbox": [],
  "geometry": {"coordinates":[10.483333,45.783333],"type":"Point"}
}