{
  "id": 7524610,
  "type": "Feature",
  "properties": {
    "tgn:hierarchy":[
        "tgn:7524610",
        "tgn:7001242",
        "tgn:7016833",
        "tgn:7001312",
        "tgn:7029392"
    ],
    "tgn:id":7524610,
    "tgn:name:en":"Tur'et Buq\u00eena",
    "tgn:placetype":[
        "aat:300006075"
    ]
},
  "bbox": [],
  "geometry": {"coordinates":[31.1025,30.932222],"type":"Point"}
}