{
  "id": 2374195,
  "type": "Feature",
  "properties": {
    "tgn:hierarchy":[
        "tgn:2374195",
        "tgn:1000001",
        "tgn:7012149",
        "tgn:2000491",
        "tgn:7007250",
        "tgn:7029392"
    ],
    "tgn:id":2374195,
    "tgn:name":"Hammond Point",
    "tgn:placetype":[
        "aat:300008798"
    ]
},
  "bbox": [],
  "geometry": {"coordinates":[-115.7667,47.3167],"type":"Point"}
}