{
  "id": 2628379,
  "type": "Feature",
  "properties": {
    "tgn:hierarchy":[
        "tgn:2628379",
        "tgn:2000858",
        "tgn:1000001",
        "tgn:7012149",
        "tgn:7007256",
        "tgn:7029392"
    ],
    "tgn:id":2628379,
    "tgn:name":"Ronde, Baie",
    "tgn:placetype":[
        "aat:300132316"
    ]
},
  "bbox": [],
  "geometry": {"coordinates":[-91.75,31.1833],"type":"Point"}
}