{
  "id": 7426741,
  "type": "Feature",
  "properties": {
    "tgn:hierarchy":[
        "tgn:7426741",
        "tgn:1000001",
        "tgn:7005594",
        "tgn:7005560",
        "tgn:7029392"
    ],
    "tgn:id":7426741,
    "tgn:name":"La Nueva Reforma",
    "tgn:placetype":[
        "aat:300008347"
    ]
},
  "bbox": [],
  "geometry": {"coordinates":[-99.466667,21.933333],"type":"Point"}
}