{
  "id": 7231522,
  "type": "Feature",
  "properties": {
    "tgn:hierarchy":[
        "tgn:7231522",
        "tgn:7011330",
        "tgn:7002674",
        "tgn:1000003",
        "tgn:1000074",
        "tgn:7029392"
    ],
    "tgn:id":7231522,
    "tgn:name":"Mandr\u00e1kion",
    "tgn:placetype":[
        "aat:300008347"
    ]
},
  "bbox": [],
  "geometry": {"coordinates":[27.133333,36.611389],"type":"Point"}
}