{
  "id": 2629074,
  "type": "Feature",
  "properties": {
    "tgn:hierarchy":[
        "tgn:2629074",
        "tgn:1000001",
        "tgn:7016172",
        "tgn:7012149",
        "tgn:2000155",
        "tgn:7029392"
    ],
    "tgn:id":2629074,
    "tgn:name":"Rose Hollow",
    "tgn:placetype":[
        "aat:300008761"
    ]
},
  "bbox": [],
  "geometry": {"coordinates":[-92.95,35.7667],"type":"Point"}
}