{
  "id": 2342974,
  "type": "Feature",
  "properties": {
    "tgn:hierarchy":[
        "tgn:2342974",
        "tgn:1000001",
        "tgn:2002242",
        "tgn:7012149",
        "tgn:7007920",
        "tgn:7029392"
    ],
    "tgn:id":2342974,
    "tgn:name":"Fye Draw",
    "tgn:placetype":[
        "aat:300008761"
    ]
},
  "bbox": [],
  "geometry": {"coordinates":[-119.7833,47.9167],"type":"Point"}
}