{
  "id": 7539797,
  "type": "Feature",
  "properties": {
    "tgn:hierarchy":[
        "tgn:7539797",
        "tgn:7001242",
        "tgn:7016833",
        "tgn:1001083",
        "tgn:7029392"
    ],
    "tgn:id":7539797,
    "tgn:name:en":"Mas\u0101rib, Dayr al",
    "tgn:placetype":[
        "aat:300386860"
    ]
},
  "bbox": [],
  "geometry": {"coordinates":[28.833333,28.616667],"type":"Point"}
}