{
  "id": 2578458,
  "type": "Feature",
  "properties": {
    "tgn:hierarchy":[
        "tgn:2578458",
        "tgn:1000001",
        "tgn:7012149",
        "tgn:1002964",
        "tgn:7007706",
        "tgn:7029392"
    ],
    "tgn:id":2578458,
    "tgn:name":"Phelps Run",
    "tgn:placetype":[
        "aat:300008699"
    ]
},
  "bbox": [],
  "geometry": {"coordinates":[-83.3167,40.2833],"type":"Point"}
}