{
  "id": 2169894,
  "type": "Feature",
  "properties": {
    "tgn:hierarchy":[
        "tgn:2169894",
        "tgn:1000001",
        "tgn:7012149",
        "tgn:2001526",
        "tgn:7007709",
        "tgn:7029392"
    ],
    "tgn:id":2169894,
    "tgn:name":"Big Oyster Creek",
    "tgn:placetype":[
        "aat:300132316"
    ]
},
  "bbox": [],
  "geometry": {"coordinates":[-76.4833,35.2333],"type":"Point"}
}