{
  "id": 1090842,
  "type": "Feature",
  "properties": {
    "tgn:hierarchy":[
        "tgn:1090842",
        "tgn:7001242",
        "tgn:1001405",
        "tgn:1000173",
        "tgn:7029392"
    ],
    "tgn:id":1090842,
    "tgn:name":"Bandabe",
    "tgn:placetype":[
        "aat:300008347"
    ]
},
  "bbox": [],
  "geometry": {"coordinates":[49.0667,-15.5167],"type":"Point"}
}