{
  "id": 2428418,
  "type": "Feature",
  "properties": {
    "tgn:hierarchy":[
        "tgn:2428418",
        "tgn:1000001",
        "tgn:7012149",
        "tgn:2001080",
        "tgn:7007521",
        "tgn:7029392"
    ],
    "tgn:id":2428418,
    "tgn:name":"Judicial Ditch Number Two",
    "tgn:placetype":[
        "aat:300006075"
    ]
},
  "bbox": [],
  "geometry": {"coordinates":[-92.9833,45.2833],"type":"Point"}
}