{
  "id": 7010851,
  "type": "Feature",
  "properties": {
    "tgn:hierarchy":[
        "tgn:7010851",
        "tgn:7002445",
        "tgn:7011980",
        "tgn:1000003",
        "tgn:7008591",
        "tgn:7029392"
    ],
    "tgn:id":7010851,
    "tgn:name":"Great Shelford",
    "tgn:placetype":[
        "aat:300008347"
    ]
},
  "bbox": [],
  "geometry": {"coordinates":[0.15,52.15],"type":"Point"}
}