{
  "id": 2605646,
  "type": "Feature",
  "properties": {
    "tgn:hierarchy":[
        "tgn:2605646",
        "tgn:1000001",
        "tgn:7012149",
        "tgn:1002545",
        "tgn:7007157",
        "tgn:7029392"
    ],
    "tgn:id":2605646,
    "tgn:name":"Railroad Spring",
    "tgn:placetype":[
        "aat:300008697"
    ]
},
  "bbox": [],
  "geometry": {"coordinates":[-118.6667,35.3167],"type":"Point"}
}