{
  "id": 1116991,
  "type": "Feature",
  "properties": {
    "tgn:hierarchy":[
        "tgn:1116991",
        "tgn:1001160",
        "tgn:7006477",
        "tgn:1000002",
        "tgn:7029392"
    ],
    "tgn:id":1116991,
    "tgn:name":"Las Tunas Grandes, Laguna",
    "tgn:placetype":[
        "aat:300008680"
    ]
},
  "bbox": [],
  "geometry": {"coordinates":[-62.4167,-35.9667],"type":"Point"}
}