{
  "id": 1130396,
  "type": "Feature",
  "properties": {
    "tgn:hierarchy":[
        "tgn:1130396",
        "tgn:7003497",
        "tgn:7001201",
        "tgn:1000003",
        "tgn:1000078",
        "tgn:7029392"
    ],
    "tgn:id":1130396,
    "tgn:name":"Sullane",
    "tgn:placetype":[
        "aat:300008707"
    ]
},
  "bbox": [],
  "geometry": {"coordinates":[-8.9333,51.8833],"type":"Point"}
}