{
  "id": 2732496,
  "type": "Feature",
  "properties": {
    "tgn:hierarchy":[
        "tgn:2732496",
        "tgn:1000001",
        "tgn:7012149",
        "tgn:2001543",
        "tgn:7007709",
        "tgn:7029392"
    ],
    "tgn:id":2732496,
    "tgn:name":"Turkey Cove",
    "tgn:placetype":[
        "aat:300386845"
    ]
},
  "bbox": [],
  "geometry": {"coordinates":[-83.8333,35.4667],"type":"Point"}
}