<<<<<<< HEAD
{
  "id": 7021739,
  "type": "Feature",
  "properties": {
    "tgn:hierarchy":[
        "tgn:7021739",
        "tgn:1000001",
        "tgn:7012149",
        "tgn:2001755",
        "tgn:7007712",
        "tgn:7029392"
    ],
    "tgn:id":7021739,
    "tgn:name":"Players Pond",
    "tgn:placetype":[
        "aat:300006191"
    ]
},
  "bbox": [],
  "geometry": {"coordinates":[-80.2167,34.1],"type":"Point"}
}
=======
{"geometry":{"type":"Point","coordinates":[-80.216700,34.100000]},"type":"Feature","properties":{"hierarchy":["tgn:7021739","tgn:1000001","tgn:7012149","tgn:2001755","tgn:7007712","tgn:7029392"],"placetype":["aat:300006191"],"id":7021739,"name:xx":"Players Pond"}}
>>>>>>> 03f74aca74312dbeaf24d7e61306dd6a786dc3d0
