{
  "id": 2443733,
  "type": "Feature",
  "properties": {
    "tgn:hierarchy":[
        "tgn:2443733",
        "tgn:1000001",
        "tgn:7012149",
        "tgn:7007826",
        "tgn:7029392"
    ],
    "tgn:id":2443733,
    "tgn:name":"La Joya Creek",
    "tgn:placetype":[
        "aat:300008706"
    ]
},
  "bbox": [],
  "geometry": {"coordinates":[-98.5833,26.5333],"type":"Point"}
}