{
  "id": 2420500,
  "type": "Feature",
  "properties": {
    "tgn:hierarchy":[
        "tgn:2420500",
        "tgn:1000001",
        "tgn:7012149",
        "tgn:7007250",
        "tgn:7029392"
    ],
    "tgn:id":2420500,
    "tgn:name":"Jenkins Hollow",
    "tgn:placetype":[
        "aat:300008761"
    ]
},
  "bbox": [],
  "geometry": {"coordinates":[-112.1333,42.05],"type":"Point"}
}