{
  "id": 2346126,
  "type": "Feature",
  "properties": {
    "tgn:hierarchy":[
        "tgn:2346126",
        "tgn:1000001",
        "tgn:7012149",
        "tgn:2001622",
        "tgn:7007706",
        "tgn:7029392"
    ],
    "tgn:id":2346126,
    "tgn:name":"Gasville",
    "tgn:placetype":[
        "aat:300008347"
    ]
},
  "bbox": [],
  "geometry": {"coordinates":[-81.3167,39.5167],"type":"Point"}
}