{
  "id": 2662204,
  "type": "Feature",
  "properties": {
    "tgn:hierarchy":[
        "tgn:2662204",
        "tgn:1000001",
        "tgn:2001413",
        "tgn:7012149",
        "tgn:7007526",
        "tgn:7029392"
    ],
    "tgn:id":2662204,
    "tgn:name":"Sidehill Blue Spring",
    "tgn:placetype":[
        "aat:300008697"
    ]
},
  "bbox": [],
  "geometry": {"coordinates":[-116.55,40.15],"type":"Point"}
}