{
  "id": 2714985,
  "type": "Feature",
  "properties": {
    "tgn:hierarchy":[
        "tgn:2714985",
        "tgn:1000001",
        "tgn:7012149",
        "tgn:2001105",
        "tgn:7007522",
        "tgn:7029392"
    ],
    "tgn:id":2714985,
    "tgn:name":"Tennessee Creek",
    "tgn:placetype":[
        "aat:300008706"
    ]
},
  "bbox": [],
  "geometry": {"coordinates":[-88.4833,30.9333],"type":"Point"}
}