{
  "id": 2010649,
  "type": "Feature",
  "properties": {
    "tgn:hierarchy":[
        "tgn:2010649",
        "tgn:1000001",
        "tgn:7012149",
        "tgn:7007157",
        "tgn:1002710",
        "tgn:7029392"
    ],
    "tgn:id":2010649,
    "tgn:name":"Cedar Ridge",
    "tgn:placetype":[
        "aat:300008347"
    ]
},
  "bbox": [],
  "geometry": {"coordinates":[-121.0167,39.1833],"type":"Point"}
}