{
  "id": 7338621,
  "type": "Feature",
  "properties": {
    "tgn:hierarchy":[
        "tgn:7338621",
        "tgn:7002810",
        "tgn:7001158",
        "tgn:1000003",
        "tgn:1000095",
        "tgn:7029392"
    ],
    "tgn:id":7338621,
    "tgn:name":"Cucho",
    "tgn:placetype":[
        "aat:300008347"
    ]
},
  "bbox": [],
  "geometry": {"coordinates":[-2.772512,42.737318],"type":"Point"}
}