<<<<<<< HEAD
{
  "id": 2336197,
  "type": "Feature",
  "properties": {
    "tgn:hierarchy":[
        "tgn:2336197",
        "tgn:1000001",
        "tgn:7012149",
        "tgn:2000931",
        "tgn:7007515",
        "tgn:7029392"
    ],
    "tgn:id":2336197,
    "tgn:name":"Foster Pond",
    "tgn:placetype":[
        "aat:300008680"
    ]
},
  "bbox": [],
  "geometry": {"coordinates":[-69.3833,44.4],"type":"Point"}
}
=======
{"geometry":{"type":"Point","coordinates":[-69.383300,44.400000]},"type":"Feature","properties":{"hierarchy":["tgn:2336197","tgn:1000001","tgn:7012149","tgn:2000931","tgn:7007515","tgn:7029392"],"placetype":["aat:300008680"],"id":2336197,"name:xx":"Foster Pond"}}
>>>>>>> 03f74aca74312dbeaf24d7e61306dd6a786dc3d0
