{
  "id": 7186672,
  "type": "Feature",
  "properties": {
    "tgn:hierarchy":[
        "tgn:7186672",
        "tgn:7003669",
        "tgn:1000003",
        "tgn:7000084",
        "tgn:7029392"
    ],
    "tgn:id":7186672,
    "tgn:name":"Grabenberg",
    "tgn:placetype":[
        "aat:300000206"
    ]
},
  "bbox": [],
  "geometry": {"coordinates":[12.333333,49.25],"type":"Point"}
}