<<<<<<< HEAD
{
  "id": 2250904,
  "type": "Feature",
  "properties": {
    "tgn:hierarchy":[
        "tgn:2250904",
        "tgn:1000001",
        "tgn:2001410",
        "tgn:7012149",
        "tgn:7007526",
        "tgn:7029392"
    ],
    "tgn:id":2250904,
    "tgn:name":"Columbia Mine",
    "tgn:placetype":[
        "aat:300000390"
    ]
},
  "bbox": [],
  "geometry": {"coordinates":[-115.4667,35.8167],"type":"Point"}
}
=======
{"geometry":{"type":"Point","coordinates":[-115.466700,35.816700]},"type":"Feature","properties":{"hierarchy":["tgn:2250904","tgn:1000001","tgn:2001410","tgn:7012149","tgn:7007526","tgn:7029392"],"placetype":["aat:300000390"],"id":2250904,"name:xx":"Columbia Mine"}}
>>>>>>> 03f74aca74312dbeaf24d7e61306dd6a786dc3d0
