<<<<<<< HEAD
{
  "id": 2154312,
  "type": "Feature",
  "properties": {
    "tgn:hierarchy":[
        "tgn:2154312",
        "tgn:1000001",
        "tgn:7012149",
        "tgn:2001716",
        "tgn:7007708",
        "tgn:7029392"
    ],
    "tgn:id":2154312,
    "tgn:name":"Bear Creek",
    "tgn:placetype":[
        "aat:300008706"
    ]
},
  "bbox": [],
  "geometry": {"coordinates":[-122.1333,43.5167],"type":"Point"}
}
=======
{"geometry":{"type":"Point","coordinates":[-122.133300,43.516700]},"type":"Feature","properties":{"hierarchy":["tgn:2154312","tgn:1000001","tgn:7012149","tgn:2001716","tgn:7007708","tgn:7029392"],"placetype":["aat:300008706"],"id":2154312,"name:xx":"Bear Creek"}}
>>>>>>> 03f74aca74312dbeaf24d7e61306dd6a786dc3d0
