<<<<<<< HEAD
{
  "id": 2337923,
  "type": "Feature",
  "properties": {
    "tgn:hierarchy":[
        "tgn:2337923",
        "tgn:1000001",
        "tgn:2000466",
        "tgn:7012149",
        "tgn:7007250",
        "tgn:7029392"
    ],
    "tgn:id":2337923,
    "tgn:name":"Fox Hills",
    "tgn:placetype":[
        "aat:300386831"
    ]
},
  "bbox": [],
  "geometry": {"coordinates":[-111.4667,42.8],"type":"Point"}
}
=======
{"geometry":{"type":"Point","coordinates":[-111.466700,42.800000]},"type":"Feature","properties":{"hierarchy":["tgn:2337923","tgn:1000001","tgn:2000466","tgn:7012149","tgn:7007250","tgn:7029392"],"placetype":["aat:300386831"],"id":2337923,"name:xx":"Fox Hills"}}
>>>>>>> 03f74aca74312dbeaf24d7e61306dd6a786dc3d0
