{
  "id": 2388957,
  "type": "Feature",
  "properties": {
    "tgn:hierarchy":[
        "tgn:2388957",
        "tgn:1000001",
        "tgn:7006451",
        "tgn:2000092",
        "tgn:7012149",
        "tgn:7029392"
    ],
    "tgn:id":2388957,
    "tgn:name":"Hidden Lake Trick Tank",
    "tgn:placetype":[
        "aat:300006191"
    ]
},
  "bbox": [],
  "geometry": {"coordinates":[-112.2667,36.7333],"type":"Point"}
}