<<<<<<< HEAD
{
  "id": 2333208,
  "type": "Feature",
  "properties": {
    "tgn:hierarchy":[
        "tgn:2333208",
        "tgn:1000001",
        "tgn:7012149",
        "tgn:2001715",
        "tgn:7007708",
        "tgn:7029392"
    ],
    "tgn:id":2333208,
    "tgn:name":"Flynn Reservoir",
    "tgn:placetype":[
        "aat:300006191"
    ]
},
  "bbox": [],
  "geometry": {"coordinates":[-120.0667,42.2667],"type":"Point"}
}
=======
{"geometry":{"type":"Point","coordinates":[-120.066700,42.266700]},"type":"Feature","properties":{"hierarchy":["tgn:2333208","tgn:1000001","tgn:7012149","tgn:2001715","tgn:7007708","tgn:7029392"],"placetype":["aat:300006191"],"id":2333208,"name:xx":"Flynn Reservoir"}}
>>>>>>> 03f74aca74312dbeaf24d7e61306dd6a786dc3d0
