{
  "id": 7131201,
  "type": "Feature",
  "properties": {
    "tgn:hierarchy":[
        "tgn:7131201",
        "tgn:1000003",
        "tgn:7003688",
        "tgn:7000084",
        "tgn:7029392"
    ],
    "tgn:id":7131201,
    "tgn:name":"M\u0113schendorf",
    "tgn:placetype":[
        "aat:300008347"
    ]
},
  "bbox": [],
  "geometry": {"coordinates":[10.983333,54.316667],"type":"Point"}
}