{
  "id": 7584180,
  "type": "Feature",
  "properties": {
    "tgn:hierarchy":[
        "tgn:7584180",
        "tgn:1000004",
        "tgn:7000198",
        "tgn:7016788",
        "tgn:7029392"
    ],
    "tgn:id":7584180,
    "tgn:name:en":"Dhannr\u0101m ka B\u0101s",
    "tgn:placetype":[
        "aat:300008347"
    ]
},
  "bbox": [],
  "geometry": {"coordinates":[75.210591,28.463894],"type":"Point"}
}