{
  "id": 2221413,
  "type": "Feature",
  "properties": {
    "tgn:hierarchy":[
        "tgn:2221413",
        "tgn:1000001",
        "tgn:7012149",
        "tgn:2001288",
        "tgn:7007524",
        "tgn:7029392"
    ],
    "tgn:id":2221413,
    "tgn:name":"Carey, Mount",
    "tgn:placetype":[
        "aat:300008798"
    ]
},
  "bbox": [],
  "geometry": {"coordinates":[-112.0667,44.8333],"type":"Point"}
}