{
  "id": 7109080,
  "type": "Feature",
  "properties": {
    "tgn:hierarchy":[
        "tgn:7109080",
        "tgn:7003669",
        "tgn:1000003",
        "tgn:7000084",
        "tgn:7029392"
    ],
    "tgn:id":7109080,
    "tgn:name":"Reisach",
    "tgn:placetype":[
        "aat:300387200"
    ]
},
  "bbox": [],
  "geometry": {"coordinates":[13.383333,48.583333],"type":"Point"}
}