{
  "id": 7234059,
  "type": "Feature",
  "properties": {
    "tgn:hierarchy":[
        "tgn:7234059",
        "tgn:7002735",
        "tgn:7017076",
        "tgn:1000003",
        "tgn:1000074",
        "tgn:7029392"
    ],
    "tgn:id":7234059,
    "tgn:name":"Akhladh\u00f3kambos",
    "tgn:placetype":[
        "aat:300008347"
    ]
},
  "bbox": [],
  "geometry": {"coordinates":[22.983333,36.883333],"type":"Point"}
}