{
  "id": 7072258,
  "type": "Feature",
  "properties": {
    "tgn:hierarchy":[
        "tgn:7072258",
        "tgn:7003692",
        "tgn:1000003",
        "tgn:7000084",
        "tgn:7029392"
    ],
    "tgn:id":7072258,
    "tgn:name":"Sulzdorf",
    "tgn:placetype":[
        "aat:300008347"
    ]
},
  "bbox": [],
  "geometry": {"coordinates":[9.839444,49.104444],"type":"Point"}
}