{
  "id": 1113588,
  "type": "Feature",
  "properties": {
    "tgn:hierarchy":[
        "tgn:1113588",
        "tgn:7030515",
        "tgn:7006450",
        "tgn:1000001",
        "tgn:7012149",
        "tgn:7029392"
    ],
    "tgn:id":1113588,
    "tgn:name":"Pavlof Bay",
    "tgn:placetype":[
        "aat:300132316"
    ]
},
  "bbox": [],
  "geometry": {"coordinates":[-161.5333,55.5333],"type":"Point"}
}