{
  "id": 7587189,
  "type": "Feature",
  "properties": {
    "tgn:hierarchy":[
        "tgn:7587189",
        "tgn:1000004",
        "tgn:7000198",
        "tgn:7000799",
        "tgn:7029392"
    ],
    "tgn:id":7587189,
    "tgn:name:en":"Gazahom",
    "tgn:placetype":[
        "aat:300008347"
    ]
},
  "bbox": [],
  "geometry": {"coordinates":[74.668817,34.20951],"type":"Point"}
}