{
  "id": 2272175,
  "type": "Feature",
  "properties": {
    "tgn:hierarchy":[
        "tgn:2272175",
        "tgn:1000001",
        "tgn:2001266",
        "tgn:7012149",
        "tgn:7007524",
        "tgn:7029392"
    ],
    "tgn:id":2272175,
    "tgn:name":"Currie Spring",
    "tgn:placetype":[
        "aat:300008697"
    ]
},
  "bbox": [],
  "geometry": {"coordinates":[-110.7833,47.1167],"type":"Point"}
}