{
  "id": 7016426,
  "type": "Feature",
  "properties": {
    "tgn:hierarchy":[
        "tgn:7016426",
        "tgn:1000003",
        "tgn:7002892",
        "tgn:1000070",
        "tgn:7029392"
    ],
    "tgn:id":7016426,
    "tgn:name":"Coubre, Pointe de la",
    "tgn:placetype":[
        "aat:300008850"
    ]
},
  "bbox": [],
  "geometry": {"coordinates":[-1.25,45.6833],"type":"Point"}
}