{
  "id": 7269585,
  "type": "Feature",
  "properties": {
    "tgn:hierarchy":[
        "tgn:7269585",
        "tgn:7003614",
        "tgn:1000003",
        "tgn:7016845",
        "tgn:7029392"
    ],
    "tgn:id":7269585,
    "tgn:name:nl":"Mensinge",
    "tgn:placetype":[
        "aat:300008178"
    ]
},
  "bbox": [],
  "geometry": {"coordinates":[6.433333,53.116667],"type":"Point"}
}