{
  "id": 7386656,
  "type": "Feature",
  "properties": {
    "tgn:hierarchy":[
        "tgn:7386656",
        "tgn:7005583",
        "tgn:1000001",
        "tgn:7005560",
        "tgn:7029392"
    ],
    "tgn:id":7386656,
    "tgn:name":"Rancho Penjamo",
    "tgn:placetype":[
        "aat:300000241"
    ]
},
  "bbox": [],
  "geometry": {"coordinates":[-103.683333,25.55],"type":"Point"}
}