<<<<<<< HEAD
{
  "id": 7475630,
  "type": "Feature",
  "properties": {
    "tgn:hierarchy":[
        "tgn:7475630",
        "tgn:7488858",
        "tgn:1000004",
        "tgn:1000141",
        "tgn:7029392"
    ],
    "tgn:id":7475630,
    "tgn:name":"Qiaoguang Guoxiao",
    "tgn:placetype":[
        "aat:300006495"
    ]
},
  "bbox": [],
  "geometry": {"coordinates":[120.6859,23.9931],"type":"Point"}
}
=======
{"geometry":{"type":"Point","coordinates":[120.685900,23.993100]},"type":"Feature","properties":{"hierarchy":["tgn:7475630","tgn:7488858","tgn:1000004","tgn:1000141","tgn:7029392"],"placetype":["aat:300006495"],"id":7475630,"name:xx":"Qiaoguang Guoxiao"}}
>>>>>>> 03f74aca74312dbeaf24d7e61306dd6a786dc3d0
