{
  "id": 7061243,
  "type": "Feature",
  "properties": {
    "tgn:hierarchy":[
        "tgn:7061243",
        "tgn:7003692",
        "tgn:1000003",
        "tgn:7000084",
        "tgn:7029392"
    ],
    "tgn:id":7061243,
    "tgn:name":"Badhof",
    "tgn:placetype":[
        "aat:300000206"
    ]
},
  "bbox": [],
  "geometry": {"coordinates":[7.733333,48.016667],"type":"Point"}
}