{
  "id": 7298079,
  "type": "Feature",
  "properties": {
    "tgn:hierarchy":[
        "tgn:7298079",
        "tgn:7007088",
        "tgn:1000003",
        "tgn:7009604",
        "tgn:1000095",
        "tgn:7029392"
    ],
    "tgn:id":7298079,
    "tgn:name":"Sojoguti",
    "tgn:placetype":[
        "aat:300008347"
    ]
},
  "bbox": [],
  "geometry": {"coordinates":[-3.127698,43.112095],"type":"Point"}
}