{
  "id": 2763619,
  "type": "Feature",
  "properties": {
    "tgn:hierarchy":[
        "tgn:2763619",
        "tgn:1000001",
        "tgn:7012149",
        "tgn:7007157",
        "tgn:2000189",
        "tgn:7029392"
    ],
    "tgn:id":2763619,
    "tgn:name":"Whaleback, The",
    "tgn:placetype":[
        "aat:300008798"
    ]
},
  "bbox": [],
  "geometry": {"coordinates":[-122.1333,41.5167],"type":"Point"}
}