{
  "id": 7590735,
  "type": "Feature",
  "properties": {
    "tgn:hierarchy":[
        "tgn:7590735",
        "tgn:1000004",
        "tgn:7000198",
        "tgn:7000799",
        "tgn:7029392"
    ],
    "tgn:id":7590735,
    "tgn:name:en":"Lowemast",
    "tgn:placetype":[
        "aat:300008347"
    ]
},
  "bbox": [],
  "geometry": {"coordinates":[73.921538,34.416455],"type":"Point"}
}