<<<<<<< HEAD
{
  "id": 7369570,
  "type": "Feature",
  "properties": {
    "tgn:hierarchy":[
        "tgn:7369570",
        "tgn:1000001",
        "tgn:7005600",
        "tgn:7005560",
        "tgn:7029392"
    ],
    "tgn:id":7369570,
    "tgn:name":"Kancab\u00e1",
    "tgn:placetype":[
        "aat:300008347"
    ]
},
  "bbox": [],
  "geometry": {"coordinates":[-88.216667,21.216667],"type":"Point"}
}
=======
{"geometry":{"type":"Point","coordinates":[-88.216667,21.216667]},"type":"Feature","properties":{"hierarchy":["tgn:7369570","tgn:1000001","tgn:7005600","tgn:7005560","tgn:7029392"],"placetype":["aat:300008347"],"id":7369570,"name:xx":"Kancab\u00e1"}}
>>>>>>> 03f74aca74312dbeaf24d7e61306dd6a786dc3d0
