{
  "id": 2303686,
  "type": "Feature",
  "properties": {
    "tgn:hierarchy":[
        "tgn:2303686",
        "tgn:1000001",
        "tgn:2001417",
        "tgn:7012149",
        "tgn:7007526",
        "tgn:7029392"
    ],
    "tgn:id":2303686,
    "tgn:name":"Eagle Mine",
    "tgn:placetype":[
        "aat:300000390"
    ]
},
  "bbox": [],
  "geometry": {"coordinates":[-118.0833,38.55],"type":"Point"}
}