{
  "id": 7427886,
  "type": "Feature",
  "properties": {
    "tgn:hierarchy":[
        "tgn:7427886",
        "tgn:1000001",
        "tgn:7005594",
        "tgn:7005560",
        "tgn:7029392"
    ],
    "tgn:id":7427886,
    "tgn:name":"Estacio\u201dn Papagayo",
    "tgn:placetype":[
        "aat:300007783"
    ]
},
  "bbox": [],
  "geometry": {"coordinates":[-99.15,22.083333],"type":"Point"}
}