{
  "id": 2276592,
  "type": "Feature",
  "properties": {
    "tgn:hierarchy":[
        "tgn:2276592",
        "tgn:1000001",
        "tgn:1002318",
        "tgn:7012149",
        "tgn:7007710",
        "tgn:7029392"
    ],
    "tgn:id":2276592,
    "tgn:name":"David Manor",
    "tgn:placetype":[
        "aat:300008347"
    ]
},
  "bbox": [],
  "geometry": {"coordinates":[-76.7833,40.2833],"type":"Point"}
}