{
  "id": 2197829,
  "type": "Feature",
  "properties": {
    "tgn:hierarchy":[
        "tgn:2197829",
        "tgn:7006450",
        "tgn:1000001",
        "tgn:7019698",
        "tgn:7012149",
        "tgn:7029392"
    ],
    "tgn:id":2197829,
    "tgn:name":"Brown Peak",
    "tgn:placetype":[
        "aat:300008798"
    ]
},
  "bbox": [],
  "geometry": {"coordinates":[-153.6667,59.5667],"type":"Point"}
}