{
  "id": 7389095,
  "type": "Feature",
  "properties": {
    "tgn:hierarchy":[
        "tgn:7389095",
        "tgn:7005581",
        "tgn:1000001",
        "tgn:7005560",
        "tgn:7029392"
    ],
    "tgn:id":7389095,
    "tgn:name":"Quelite, Arroyo del",
    "tgn:placetype":[
        "aat:300008699"
    ]
},
  "bbox": [],
  "geometry": {"coordinates":[-106.45,26.883333],"type":"Point"}
}