{
  "id": 7130873,
  "type": "Feature",
  "properties": {
    "tgn:hierarchy":[
        "tgn:7130873",
        "tgn:1000003",
        "tgn:7003688",
        "tgn:7000084",
        "tgn:7029392"
    ],
    "tgn:id":7130873,
    "tgn:name":"Mittellochs-Knob",
    "tgn:placetype":[
        "aat:300386970"
    ]
},
  "bbox": [],
  "geometry": {"coordinates":[8.416667,54.65],"type":"Point"}
}