{
  "id": 1130839,
  "type": "Feature",
  "properties": {
    "tgn:hierarchy":[
        "tgn:1130839",
        "tgn:1001945",
        "tgn:1000047",
        "tgn:7002457",
        "tgn:1000002",
        "tgn:7029392"
    ],
    "tgn:id":1130839,
    "tgn:name":"Tiet\u00ea",
    "tgn:placetype":[
        "aat:300008707"
    ]
},
  "bbox": [],
  "geometry": {"coordinates":[-51.5833,-20.6667],"type":"Point"}
}