{
  "id": 2229464,
  "type": "Feature",
  "properties": {
    "tgn:hierarchy":[
        "tgn:2229464",
        "tgn:1000001",
        "tgn:2001009",
        "tgn:7012149",
        "tgn:7007521",
        "tgn:7029392"
    ],
    "tgn:id":2229464,
    "tgn:name":"Cedar Point",
    "tgn:placetype":[
        "aat:300008850"
    ]
},
  "bbox": [],
  "geometry": {"coordinates":[-94.5667,47.1333],"type":"Point"}
}