{
  "id": 7387733,
  "type": "Feature",
  "properties": {
    "tgn:hierarchy":[
        "tgn:7387733",
        "tgn:1000001",
        "tgn:7005599",
        "tgn:7005560",
        "tgn:7029392"
    ],
    "tgn:id":7387733,
    "tgn:name":"Pascual",
    "tgn:placetype":[
        "aat:300008347"
    ]
},
  "bbox": [],
  "geometry": {"coordinates":[-93.966667,17.716667],"type":"Point"}
}