<<<<<<< HEAD
{
  "id": 7055857,
  "type": "Feature",
  "properties": {
    "tgn:hierarchy":[
        "tgn:7055857",
        "tgn:7015163",
        "tgn:1000003",
        "tgn:7003121",
        "tgn:1000080",
        "tgn:7029392"
    ],
    "tgn:id":7055857,
    "tgn:name":"Pizzinnu, Monte",
    "tgn:placetype":[
        "aat:300008795"
    ]
},
  "bbox": [],
  "geometry": {"coordinates":[8.666667,40.666667],"type":"Point"}
}
=======
{"geometry":{"type":"Point","coordinates":[8.666667,40.666667]},"type":"Feature","properties":{"hierarchy":["tgn:7055857","tgn:7015163","tgn:1000003","tgn:7003121","tgn:1000080","tgn:7029392"],"placetype":["aat:300008795"],"id":7055857,"name:xx":"Pizzinnu, Monte"}}
>>>>>>> 03f74aca74312dbeaf24d7e61306dd6a786dc3d0
