{
  "id": 2438131,
  "type": "Feature",
  "properties": {
    "tgn:hierarchy":[
        "tgn:2438131",
        "tgn:1000001",
        "tgn:7006451",
        "tgn:7012149",
        "tgn:2000104",
        "tgn:7029392"
    ],
    "tgn:id":2438131,
    "tgn:name":"King of Arizona Mine",
    "tgn:placetype":[
        "aat:300000390"
    ]
},
  "bbox": [],
  "geometry": {"coordinates":[-113.95,33.2667],"type":"Point"}
}