{
  "id": 7421254,
  "type": "Feature",
  "properties": {
    "tgn:hierarchy":[
        "tgn:7421254",
        "tgn:1001836",
        "tgn:1000001",
        "tgn:7005560",
        "tgn:7029392"
    ],
    "tgn:id":7421254,
    "tgn:name":"La Esperanza",
    "tgn:placetype":[
        "aat:300008347"
    ]
},
  "bbox": [],
  "geometry": {"coordinates":[-112.715278,27.375],"type":"Point"}
}