{
  "id": 2748753,
  "type": "Feature",
  "properties": {
    "tgn:hierarchy":[
        "tgn:2748753",
        "tgn:1000001",
        "tgn:7012149",
        "tgn:2001555",
        "tgn:7007709",
        "tgn:7029392"
    ],
    "tgn:id":2748753,
    "tgn:name":"Walkers Branch",
    "tgn:placetype":[
        "aat:300008699"
    ]
},
  "bbox": [],
  "geometry": {"coordinates":[-80.85,36.0667],"type":"Point"}
}