{
  "id": 7319905,
  "type": "Feature",
  "properties": {
    "tgn:hierarchy":[
        "tgn:7319905",
        "tgn:1001699",
        "tgn:1000049",
        "tgn:1000002",
        "tgn:7029392"
    ],
    "tgn:id":7319905,
    "tgn:name":"Alerce, Paso",
    "tgn:placetype":[
        "aat:300259572"
    ]
},
  "bbox": [],
  "geometry": {"coordinates":[-72.116667,-42.666667],"type":"Point"}
}