{
  "id": 2112858,
  "type": "Feature",
  "properties": {
    "tgn:hierarchy":[
        "tgn:2112858",
        "tgn:2002142",
        "tgn:1000001",
        "tgn:7012149",
        "tgn:7007919",
        "tgn:7029392"
    ],
    "tgn:id":2112858,
    "tgn:name":"Madrid",
    "tgn:placetype":[
        "aat:300008347",
        "aat:300387210"
    ]
},
  "bbox": [],
  "geometry": {"coordinates":[-78.8667,38.1333],"type":"Point"}
}