{
  "id": 7327429,
  "type": "Feature",
  "properties": {
    "tgn:hierarchy":[
        "tgn:7327429",
        "tgn:7002820",
        "tgn:7030216",
        "tgn:1000003",
        "tgn:1000095",
        "tgn:7029392"
    ],
    "tgn:id":7327429,
    "tgn:name":"Pan, Coll",
    "tgn:placetype":[
        "aat:300259572"
    ]
},
  "bbox": [],
  "geometry": {"coordinates":[2.108173,42.280406],"type":"Point"}
}