{
  "id": 2179296,
  "type": "Feature",
  "properties": {
    "tgn:hierarchy":[
        "tgn:2179296",
        "tgn:1000001",
        "tgn:7012149",
        "tgn:1002552",
        "tgn:7007920",
        "tgn:7029392"
    ],
    "tgn:id":2179296,
    "tgn:name":"Blakely Rock",
    "tgn:placetype":[
        "aat:300132348"
    ]
},
  "bbox": [],
  "geometry": {"coordinates":[-122.4667,47.5833],"type":"Point"}
}