{
  "id": 7551690,
  "type": "Feature",
  "properties": {
    "tgn:hierarchy":[
        "tgn:7551690",
        "tgn:1000004",
        "tgn:7000198",
        "tgn:1001894",
        "tgn:7029392"
    ],
    "tgn:id":7551690,
    "tgn:name:en":"Bordehi Kh\u0101s",
    "tgn:placetype":[
        "aat:300008347"
    ]
},
  "bbox": [],
  "geometry": {"coordinates":[78.352542,22.005274],"type":"Point"}
}