{
  "id": 2603282,
  "type": "Feature",
  "properties": {
    "tgn:hierarchy":[
        "tgn:2603282",
        "tgn:1000001",
        "tgn:2001705",
        "tgn:7012149",
        "tgn:7007708",
        "tgn:7029392"
    ],
    "tgn:id":2603282,
    "tgn:name":"Quartz Mountain",
    "tgn:placetype":[
        "aat:300008798"
    ]
},
  "bbox": [],
  "geometry": {"coordinates":[-120.8833,43.6167],"type":"Point"}
}