{
  "id": 7579282,
  "type": "Feature",
  "properties": {
    "tgn:hierarchy":[
        "tgn:7579282",
        "tgn:1000004",
        "tgn:1001869",
        "tgn:7000198",
        "tgn:7029392"
    ],
    "tgn:id":7579282,
    "tgn:name:en":"Tarasvu",
    "tgn:placetype":[
        "aat:300008347"
    ]
},
  "bbox": [],
  "geometry": {"coordinates":[73.483333,22.25],"type":"Point"}
}