<<<<<<< HEAD
{
  "id": 7111186,
  "type": "Feature",
  "properties": {
    "tgn:hierarchy":[
        "tgn:7111186",
        "tgn:1000003",
        "tgn:7000094",
        "tgn:7000084",
        "tgn:7029392"
    ],
    "tgn:id":7111186,
    "tgn:name":"Rittermannsh\u00e4ger See",
    "tgn:placetype":[
        "aat:300008680"
    ]
},
  "bbox": [],
  "geometry": {"coordinates":[12.766667,53.616667],"type":"Point"}
}
=======
{"geometry":{"type":"Point","coordinates":[12.766667,53.616667]},"type":"Feature","properties":{"hierarchy":["tgn:7111186","tgn:1000003","tgn:7000094","tgn:7000084","tgn:7029392"],"placetype":["aat:300008680"],"id":7111186,"name:xx":"Rittermannsh\u00e4ger See"}}
>>>>>>> 03f74aca74312dbeaf24d7e61306dd6a786dc3d0
