<<<<<<< HEAD
{
  "id": 7025625,
  "type": "Feature",
  "properties": {
    "tgn:hierarchy":[
        "tgn:7025625",
        "tgn:7002445",
        "tgn:1000003",
        "tgn:7012077",
        "tgn:7008591",
        "tgn:7029392"
    ],
    "tgn:id":7025625,
    "tgn:name":"Larkbeare",
    "tgn:placetype":[
        "aat:300008347"
    ]
},
  "bbox": [],
  "geometry": {"coordinates":[-3.3167,50.7667],"type":"Point"}
}
=======
{"geometry":{"type":"Point","coordinates":[-3.316700,50.766700]},"type":"Feature","properties":{"hierarchy":["tgn:7025625","tgn:7002445","tgn:1000003","tgn:7012077","tgn:7008591","tgn:7029392"],"placetype":["aat:300008347"],"id":7025625,"name:xx":"Larkbeare"}}
>>>>>>> 03f74aca74312dbeaf24d7e61306dd6a786dc3d0
