<<<<<<< HEAD
{
  "id": 7112218,
  "type": "Feature",
  "properties": {
    "tgn:hierarchy":[
        "tgn:7112218",
        "tgn:1000003",
        "tgn:7003688",
        "tgn:7000084",
        "tgn:7029392"
    ],
    "tgn:id":7112218,
    "tgn:name":"Ro\u00dfbaum",
    "tgn:placetype":[
        "aat:300000206"
    ]
},
  "bbox": [],
  "geometry": {"coordinates":[10.55,54.383333],"type":"Point"}
}
=======
{"geometry":{"type":"Point","coordinates":[10.550000,54.383333]},"type":"Feature","properties":{"hierarchy":["tgn:7112218","tgn:1000003","tgn:7003688","tgn:7000084","tgn:7029392"],"placetype":["aat:300000206"],"id":7112218,"name:xx":"Ro\u00dfbaum"}}
>>>>>>> 03f74aca74312dbeaf24d7e61306dd6a786dc3d0
