{
  "id": 7112218,
  "type": "Feature",
  "properties": {
    "tgn:hierarchy":[
        "tgn:7112218",
        "tgn:1000003",
        "tgn:7003688",
        "tgn:7000084",
        "tgn:7029392"
    ],
    "tgn:id":7112218,
    "tgn:name":"Ro\u00dfbaum",
    "tgn:placetype":[
        "aat:300000206"
    ]
},
  "bbox": [],
  "geometry": {"coordinates":[10.55,54.383333],"type":"Point"}
}