{
  "id": 7488418,
  "type": "Feature",
  "properties": {
    "tgn:hierarchy":[
        "tgn:7488418",
        "tgn:7488858",
        "tgn:1000004",
        "tgn:1000141",
        "tgn:7029392"
    ],
    "tgn:id":7488418,
    "tgn:name":"Luliao",
    "tgn:placetype":[
        "aat:300008347"
    ]
},
  "bbox": [],
  "geometry": {"coordinates":[120.735833,23.686667],"type":"Point"}
}