{
  "id": 2367648,
  "type": "Feature",
  "properties": {
    "tgn:hierarchy":[
        "tgn:2367648",
        "tgn:1000001",
        "tgn:7012149",
        "tgn:7007157",
        "tgn:2000189",
        "tgn:7029392"
    ],
    "tgn:id":2367648,
    "tgn:name":"Grouse Point",
    "tgn:placetype":[
        "aat:300008850"
    ]
},
  "bbox": [],
  "geometry": {"coordinates":[-123.0833,41.1833],"type":"Point"}
}