{
  "id": 7539502,
  "type": "Feature",
  "properties": {
    "tgn:hierarchy":[
        "tgn:7539502",
        "tgn:7001242",
        "tgn:7016833",
        "tgn:7001312",
        "tgn:7029392"
    ],
    "tgn:id":7539502,
    "tgn:name:en":"Qal\u012bb Aby\u0101r",
    "tgn:placetype":[
        "aat:300008347"
    ]
},
  "bbox": [],
  "geometry": {"coordinates":[30.827318,30.8717],"type":"Point"}
}