{
  "id": 2438192,
  "type": "Feature",
  "properties": {
    "tgn:hierarchy":[
        "tgn:2438192",
        "tgn:1000001",
        "tgn:7012149",
        "tgn:1002703",
        "tgn:7007826",
        "tgn:7029392"
    ],
    "tgn:id":2438192,
    "tgn:name":"Kingham Creek",
    "tgn:placetype":[
        "aat:300008706"
    ]
},
  "bbox": [],
  "geometry": {"coordinates":[-94.45,31.6167],"type":"Point"}
}