{
  "id": 2467671,
  "type": "Feature",
  "properties": {
    "tgn:hierarchy":[
        "tgn:2467671",
        "tgn:1000001",
        "tgn:7012149",
        "tgn:1002567",
        "tgn:7007240",
        "tgn:7029392"
    ],
    "tgn:id":2467671,
    "tgn:name":"Long Island",
    "tgn:placetype":[
        "aat:300008791"
    ]
},
  "bbox": [],
  "geometry": {"coordinates":[-81.7667,28.75],"type":"Point"}
}