{
  "id": 2089642,
  "type": "Feature",
  "properties": {
    "tgn:hierarchy":[
        "tgn:2089642",
        "tgn:1000001",
        "tgn:7012149",
        "tgn:1002501",
        "tgn:7007710",
        "tgn:7029392"
    ],
    "tgn:id":2089642,
    "tgn:name":"Johnsonburg",
    "tgn:placetype":[
        "aat:300008347"
    ]
},
  "bbox": [],
  "geometry": {"coordinates":[-78.8667,40.8833],"type":"Point"}
}