{
  "id": 7257407,
  "type": "Feature",
  "properties": {
    "tgn:hierarchy":[
        "tgn:7257407",
        "tgn:7593113",
        "tgn:7016620",
        "tgn:7593112",
        "tgn:1000001",
        "tgn:7029392"
    ],
    "tgn:id":7257407,
    "tgn:name:nl":"Sarna, Playa",
    "tgn:placetype":[
        "aat:300132317"
    ]
},
  "bbox": [],
  "geometry": {"coordinates":[-68.266667,12.15],"type":"Point"}
}