{
  "id": 7143263,
  "type": "Feature",
  "properties": {
    "tgn:hierarchy":[
        "tgn:7143263",
        "tgn:7003669",
        "tgn:1000003",
        "tgn:7000084",
        "tgn:7029392"
    ],
    "tgn:id":7143263,
    "tgn:name":"Lofering",
    "tgn:placetype":[
        "aat:300000206"
    ]
},
  "bbox": [],
  "geometry": {"coordinates":[13.15,48.783333],"type":"Point"}
}