{
  "id": 2581370,
  "type": "Feature",
  "properties": {
    "tgn:hierarchy":[
        "tgn:2581370",
        "tgn:7002659",
        "tgn:1000001",
        "tgn:7012149",
        "tgn:2000042",
        "tgn:7029392"
    ],
    "tgn:id":2581370,
    "tgn:name":"Pilot Creek",
    "tgn:placetype":[
        "aat:300008706"
    ]
},
  "bbox": [],
  "geometry": {"coordinates":[-86.7667,32.2667],"type":"Point"}
}