<<<<<<< HEAD
{
  "id": 7050955,
  "type": "Feature",
  "properties": {
    "tgn:hierarchy":[
        "tgn:7050955",
        "tgn:1000003",
        "tgn:7003236",
        "tgn:1000080",
        "tgn:7029392"
    ],
    "tgn:id":7050955,
    "tgn:name":"La Marina",
    "tgn:placetype":[
        "aat:300008347"
    ]
},
  "bbox": [],
  "geometry": {"coordinates":[9.516667,44.216667],"type":"Point"}
}
=======
{"geometry":{"type":"Point","coordinates":[9.516667,44.216667]},"type":"Feature","properties":{"hierarchy":["tgn:7050955","tgn:1000003","tgn:7003236","tgn:1000080","tgn:7029392"],"placetype":["aat:300008347"],"id":7050955,"name:xx":"La Marina"}}
>>>>>>> 03f74aca74312dbeaf24d7e61306dd6a786dc3d0
