{
  "id": 7209471,
  "type": "Feature",
  "properties": {
    "tgn:hierarchy":[
        "tgn:7209471",
        "tgn:7003669",
        "tgn:1000003",
        "tgn:7000084",
        "tgn:7029392"
    ],
    "tgn:id":7209471,
    "tgn:name":"Berndorf",
    "tgn:placetype":[
        "aat:300008347"
    ]
},
  "bbox": [],
  "geometry": {"coordinates":[11.383333,50.016667],"type":"Point"}
}