{
  "id": 7493738,
  "type": "Feature",
  "properties": {
    "tgn:hierarchy":[
        "tgn:7493738",
        "tgn:7468018",
        "tgn:1000004",
        "tgn:1000141",
        "tgn:7029392"
    ],
    "tgn:id":7493738,
    "tgn:name":"Dabu Guoxiao Fenban",
    "tgn:placetype":[
        "aat:300006495"
    ]
},
  "bbox": [],
  "geometry": {"coordinates":[120.550503,23.335772],"type":"Point"}
}