{
  "id": 2651439,
  "type": "Feature",
  "properties": {
    "tgn:hierarchy":[
        "tgn:2651439",
        "tgn:7013388",
        "tgn:1000001",
        "tgn:7012149",
        "tgn:7007517",
        "tgn:7029392"
    ],
    "tgn:id":2651439,
    "tgn:name":"Secum Brook",
    "tgn:placetype":[
        "aat:300008699"
    ]
},
  "bbox": [],
  "geometry": {"coordinates":[-73.25,42.55],"type":"Point"}
}