<<<<<<< HEAD
{
  "id": 2763791,
  "type": "Feature",
  "properties": {
    "tgn:hierarchy":[
        "tgn:2763791",
        "tgn:1000001",
        "tgn:7012149",
        "tgn:2001904",
        "tgn:7007825",
        "tgn:7029392"
    ],
    "tgn:id":2763791,
    "tgn:name":"Wheat Branch",
    "tgn:placetype":[
        "aat:300008699"
    ]
},
  "bbox": [],
  "geometry": {"coordinates":[-88.0,35.4333],"type":"Point"}
}
=======
{"geometry":{"type":"Point","coordinates":[-88.000000,35.433300]},"type":"Feature","properties":{"hierarchy":["tgn:2763791","tgn:1000001","tgn:7012149","tgn:2001904","tgn:7007825","tgn:7029392"],"placetype":["aat:300008699"],"id":2763791,"name:xx":"Wheat Branch"}}
>>>>>>> 03f74aca74312dbeaf24d7e61306dd6a786dc3d0
