{
  "id": 7487585,
  "type": "Feature",
  "properties": {
    "tgn:hierarchy":[
        "tgn:7487585",
        "tgn:1000004",
        "tgn:7001014",
        "tgn:1000141",
        "tgn:7029392"
    ],
    "tgn:id":7487585,
    "tgn:name":"Xucuoliao",
    "tgn:placetype":[
        "aat:300008347"
    ]
},
  "bbox": [],
  "geometry": {"coordinates":[120.238611,23.789722],"type":"Point"}
}