{
  "id": 2278442,
  "type": "Feature",
  "properties": {
    "tgn:hierarchy":[
        "tgn:2278442",
        "tgn:1000001",
        "tgn:2001419",
        "tgn:7012149",
        "tgn:7007526",
        "tgn:7029392"
    ],
    "tgn:id":2278442,
    "tgn:name":"DeSoto Antimony Mine",
    "tgn:placetype":[
        "aat:300000390"
    ]
},
  "bbox": [],
  "geometry": {"coordinates":[-118.4833,40.6667],"type":"Point"}
}