{
  "id": 2012201,
  "type": "Feature",
  "properties": {
    "tgn:hierarchy":[
        "tgn:2012201",
        "tgn:1000001",
        "tgn:7012149",
        "tgn:7007157",
        "tgn:1002608",
        "tgn:7029392"
    ],
    "tgn:id":2012201,
    "tgn:name":"Leona Valley",
    "tgn:placetype":[
        "aat:300008347"
    ]
},
  "bbox": [],
  "geometry": {"coordinates":[-118.2833,34.6167],"type":"Point"}
}