{
  "id": 7329422,
  "type": "Feature",
  "properties": {
    "tgn:hierarchy":[
        "tgn:7329422",
        "tgn:7002832",
        "tgn:7001158",
        "tgn:1000003",
        "tgn:1000095",
        "tgn:7029392"
    ],
    "tgn:id":7329422,
    "tgn:name":"Raya, Arroyo de La",
    "tgn:placetype":[
        "aat:300008699"
    ]
},
  "bbox": [],
  "geometry": {"coordinates":[-4.416667,41.916667],"type":"Point"}
}