{
  "id": 1128897,
  "type": "Feature",
  "properties": {
    "tgn:hierarchy":[
        "tgn:1128897",
        "tgn:1000004",
        "tgn:7000231",
        "tgn:7029392"
    ],
    "tgn:id":1128897,
    "tgn:name":"R\u016bdkh\u0101neh-ye Qezel Owzan",
    "tgn:placetype":[
        "aat:300008707"
    ]
},
  "bbox": [],
  "geometry": {"coordinates":[49.1167,36.7833],"type":"Point"}
}