{
  "id": 7069985,
  "type": "Feature",
  "properties": {
    "tgn:hierarchy":[
        "tgn:7069985",
        "tgn:1000003",
        "tgn:7003687",
        "tgn:7000084",
        "tgn:7029392"
    ],
    "tgn:id":7069985,
    "tgn:name":"Tilleda",
    "tgn:placetype":[
        "aat:300008347"
    ]
},
  "bbox": [],
  "geometry": {"coordinates":[11.15,51.416667],"type":"Point"}
}