{
  "id": 7153257,
  "type": "Feature",
  "properties": {
    "tgn:hierarchy":[
        "tgn:7153257",
        "tgn:1000003",
        "tgn:7003688",
        "tgn:7000084",
        "tgn:7029392"
    ],
    "tgn:id":7153257,
    "tgn:name":"Julssand",
    "tgn:placetype":[
        "aat:300000206"
    ]
},
  "bbox": [],
  "geometry": {"coordinates":[9.566667,53.616667],"type":"Point"}
}