{
  "id": 7356143,
  "type": "Feature",
  "properties": {
    "tgn:hierarchy":[
        "tgn:7356143",
        "tgn:1000001",
        "tgn:7005601",
        "tgn:7005560",
        "tgn:7029392"
    ],
    "tgn:id":7356143,
    "tgn:name":"Calzones, Lagunita de",
    "tgn:placetype":[
        "aat:300008688"
    ]
},
  "bbox": [],
  "geometry": {"coordinates":[-101.883333,24.316667],"type":"Point"}
}