{
  "id": 2650428,
  "type": "Feature",
  "properties": {
    "tgn:hierarchy":[
        "tgn:2650428",
        "tgn:1000001",
        "tgn:7012149",
        "tgn:2002175",
        "tgn:7007919",
        "tgn:7029392"
    ],
    "tgn:id":2650428,
    "tgn:name":"Sears Ridge",
    "tgn:placetype":[
        "aat:300266640"
    ]
},
  "bbox": [],
  "geometry": {"coordinates":[-78.8333,37.5833],"type":"Point"}
}