{
  "id": 7236457,
  "type": "Feature",
  "properties": {
    "tgn:hierarchy":[
        "tgn:7236457",
        "tgn:7002680",
        "tgn:7001395",
        "tgn:1000003",
        "tgn:1000074",
        "tgn:7029392"
    ],
    "tgn:id":7236457,
    "tgn:name":"\u00c1yios Nik\u00f3laos, Nis\u00eds",
    "tgn:placetype":[
        "aat:300008791"
    ]
},
  "bbox": [],
  "geometry": {"coordinates":[20.783333,38.75],"type":"Point"}
}