{
  "id": 7499058,
  "type": "Feature",
  "properties": {
    "tgn:hierarchy":[
        "tgn:7499058",
        "tgn:1000957",
        "tgn:1000004",
        "tgn:1000141",
        "tgn:7029392"
    ],
    "tgn:id":7499058,
    "tgn:name":"Zhixiu Gong",
    "tgn:placetype":[
        "aat:300007595"
    ]
},
  "bbox": [],
  "geometry": {"coordinates":[121.735242,25.109078],"type":"Point"}
}