{
  "id": 2121589,
  "type": "Feature",
  "properties": {
    "tgn:hierarchy":[
        "tgn:2121589",
        "tgn:1000001",
        "tgn:7012149",
        "tgn:2002333",
        "tgn:7007922",
        "tgn:7029392"
    ],
    "tgn:id":2121589,
    "tgn:name":"Langlade",
    "tgn:placetype":[
        "aat:300008347"
    ]
},
  "bbox": [],
  "geometry": {"coordinates":[-88.7167,45.1833],"type":"Point"}
}