{
  "id": 2630548,
  "type": "Feature",
  "properties": {
    "tgn:hierarchy":[
        "tgn:2630548",
        "tgn:1000001",
        "tgn:7012149",
        "tgn:7007158",
        "tgn:2000246",
        "tgn:7029392"
    ],
    "tgn:id":2630548,
    "tgn:name":"Round Hill",
    "tgn:placetype":[
        "aat:300008798"
    ]
},
  "bbox": [],
  "geometry": {"coordinates":[-106.0667,38.3833],"type":"Point"}
}