<<<<<<< HEAD
{
  "id": 2761810,
  "type": "Feature",
  "properties": {
    "tgn:hierarchy":[
        "tgn:2761810",
        "tgn:1000001",
        "tgn:7012149",
        "tgn:2001541",
        "tgn:7007709",
        "tgn:7029392"
    ],
    "tgn:id":2761810,
    "tgn:name":"West Prong Little Yadkin River",
    "tgn:placetype":[
        "aat:300008707"
    ]
},
  "bbox": [],
  "geometry": {"coordinates":[-80.4,36.4],"type":"Point"}
}
=======
{"geometry":{"type":"Point","coordinates":[-80.400000,36.400000]},"type":"Feature","properties":{"hierarchy":["tgn:2761810","tgn:1000001","tgn:7012149","tgn:2001541","tgn:7007709","tgn:7029392"],"placetype":["aat:300008707"],"id":2761810,"name:xx":"West Prong Little Yadkin River"}}
>>>>>>> 03f74aca74312dbeaf24d7e61306dd6a786dc3d0
