{
  "id": 7307499,
  "type": "Feature",
  "properties": {
    "tgn:hierarchy":[
        "tgn:7307499",
        "tgn:7002804",
        "tgn:1000003",
        "tgn:7002793",
        "tgn:1000095",
        "tgn:7029392"
    ],
    "tgn:id":7307499,
    "tgn:name":"Lleus",
    "tgn:placetype":[
        "aat:300008347"
    ]
},
  "bbox": [],
  "geometry": {"coordinates":[0.183333,38.683333],"type":"Point"}
}