{
  "id": 2691436,
  "type": "Feature",
  "properties": {
    "tgn:hierarchy":[
        "tgn:2691436",
        "tgn:1000001",
        "tgn:7012149",
        "tgn:1002565",
        "tgn:7007252",
        "tgn:7029392"
    ],
    "tgn:id":2691436,
    "tgn:name":"Star Mill",
    "tgn:placetype":[
        "aat:300008347"
    ]
},
  "bbox": [],
  "geometry": {"coordinates":[-85.4333,41.7333],"type":"Point"}
}