{
  "id": 2135068,
  "type": "Feature",
  "properties": {
    "tgn:hierarchy":[
        "tgn:2135068",
        "tgn:1000001",
        "tgn:7012149",
        "tgn:7007157",
        "tgn:1002894",
        "tgn:7029392"
    ],
    "tgn:id":2135068,
    "tgn:name":"Antelope Valley",
    "tgn:placetype":[
        "aat:300008761"
    ]
},
  "bbox": [],
  "geometry": {"coordinates":[-120.2667,39.6167],"type":"Point"}
}