{
  "id": 7327370,
  "type": "Feature",
  "properties": {
    "tgn:hierarchy":[
        "tgn:7327370",
        "tgn:7002832",
        "tgn:7001158",
        "tgn:1000003",
        "tgn:1000095",
        "tgn:7029392"
    ],
    "tgn:id":7327370,
    "tgn:name":"Paredes de Monte",
    "tgn:placetype":[
        "aat:300008347"
    ]
},
  "bbox": [],
  "geometry": {"coordinates":[-4.633333,41.95],"type":"Point"}
}