{
  "id": 7377080,
  "type": "Feature",
  "properties": {
    "tgn:hierarchy":[
        "tgn:7377080",
        "tgn:7005583",
        "tgn:1000001",
        "tgn:7005560",
        "tgn:7029392"
    ],
    "tgn:id":7377080,
    "tgn:name":"Rancho Las Milpas",
    "tgn:placetype":[
        "aat:300000241"
    ]
},
  "bbox": [],
  "geometry": {"coordinates":[-106.95,25.433333],"type":"Point"}
}