{
  "id": 1081254,
  "type": "Feature",
  "properties": {
    "tgn:hierarchy":[
        "tgn:1081254",
        "tgn:1000975",
        "tgn:1000004",
        "tgn:7000901",
        "tgn:1000120",
        "tgn:7029392"
    ],
    "tgn:id":1081254,
    "tgn:name":"Setaka",
    "tgn:placetype":[
        "aat:300008347"
    ]
},
  "bbox": [],
  "geometry": {"coordinates":[130.4667,33.15],"type":"Point"}
}