{
  "id": 7590143,
  "type": "Feature",
  "properties": {
    "tgn:hierarchy":[
        "tgn:7590143",
        "tgn:1000004",
        "tgn:7000198",
        "tgn:7000799",
        "tgn:7029392"
    ],
    "tgn:id":7590143,
    "tgn:name:en":"H\u0101patpathri Forest",
    "tgn:placetype":[
        "aat:300008863"
    ]
},
  "bbox": [],
  "geometry": {"coordinates":[74.336111,33.869444],"type":"Point"}
}