{
  "id": 7266107,
  "type": "Feature",
  "properties": {
    "tgn:hierarchy":[
        "tgn:7266107",
        "tgn:1000003",
        "tgn:7003632",
        "tgn:7016845",
        "tgn:7029392"
    ],
    "tgn:id":7266107,
    "tgn:name:nl":"Haringvliet",
    "tgn:placetype":[
        "aat:300387055"
    ]
},
  "bbox": [],
  "geometry": {"coordinates":[4.233333,51.766667],"type":"Point"}
}