{
  "id": 1074771,
  "type": "Feature",
  "properties": {
    "tgn:hierarchy":[
        "tgn:1074771",
        "tgn:1001828",
        "tgn:1000004",
        "tgn:7000198",
        "tgn:7029392"
    ],
    "tgn:id":1074771,
    "tgn:name:en":"Bhadr\u0101chalam",
    "tgn:placetype":[
        "aat:300008347"
    ]
},
  "bbox": [],
  "geometry": {"coordinates":[80.888,17.668],"type":"Point"}
}