<<<<<<< HEAD
{
  "id": 2763937,
  "type": "Feature",
  "properties": {
    "tgn:hierarchy":[
        "tgn:2763937",
        "tgn:1000001",
        "tgn:7012149",
        "tgn:2002294",
        "tgn:7013961",
        "tgn:7029392"
    ],
    "tgn:id":2763937,
    "tgn:name":"Wheel Run",
    "tgn:placetype":[
        "aat:300008699"
    ]
},
  "bbox": [],
  "geometry": {"coordinates":[-80.8333,37.5333],"type":"Point"}
}
=======
{"geometry":{"type":"Point","coordinates":[-80.833300,37.533300]},"type":"Feature","properties":{"hierarchy":["tgn:2763937","tgn:1000001","tgn:7012149","tgn:2002294","tgn:7013961","tgn:7029392"],"placetype":["aat:300008699"],"id":2763937,"name:xx":"Wheel Run"}}
>>>>>>> 03f74aca74312dbeaf24d7e61306dd6a786dc3d0
