{
  "id": 2696792,
  "type": "Feature",
  "properties": {
    "tgn:hierarchy":[
        "tgn:2696792",
        "tgn:1000001",
        "tgn:7012149",
        "tgn:2000488",
        "tgn:7007250",
        "tgn:7029392"
    ],
    "tgn:id":2696792,
    "tgn:name":"Stoneman Creek Spring",
    "tgn:placetype":[
        "aat:300008697"
    ]
},
  "bbox": [],
  "geometry": {"coordinates":[-116.75,42.55],"type":"Point"}
}