{
  "id": 2722203,
  "type": "Feature",
  "properties": {
    "tgn:hierarchy":[
        "tgn:2722203",
        "tgn:1000001",
        "tgn:2000308",
        "tgn:7012149",
        "tgn:7007248",
        "tgn:7029392"
    ],
    "tgn:id":2722203,
    "tgn:name":"Timmons Pond",
    "tgn:placetype":[
        "aat:300006191"
    ]
},
  "bbox": [],
  "geometry": {"coordinates":[-82.1833,33.1833],"type":"Point"}
}