{
  "id": 7120387,
  "type": "Feature",
  "properties": {
    "tgn:hierarchy":[
        "tgn:7120387",
        "tgn:1000003",
        "tgn:7000094",
        "tgn:7000084",
        "tgn:7029392"
    ],
    "tgn:id":7120387,
    "tgn:name":"Pragel Forst",
    "tgn:placetype":[
        "aat:300008863"
    ]
},
  "bbox": [],
  "geometry": {"coordinates":[13.65,54.016667],"type":"Point"}
}