<<<<<<< HEAD
{
  "id": 2250076,
  "type": "Feature",
  "properties": {
    "tgn:hierarchy":[
        "tgn:2250076",
        "tgn:7002659",
        "tgn:1000001",
        "tgn:7012149",
        "tgn:2000047",
        "tgn:7029392"
    ],
    "tgn:id":2250076,
    "tgn:name":"Collins Creek",
    "tgn:placetype":[
        "aat:300008706"
    ]
},
  "bbox": [],
  "geometry": {"coordinates":[-86.2833,34.2667],"type":"Point"}
}
=======
{"geometry":{"type":"Point","coordinates":[-86.283300,34.266700]},"type":"Feature","properties":{"hierarchy":["tgn:2250076","tgn:7002659","tgn:1000001","tgn:7012149","tgn:2000047","tgn:7029392"],"placetype":["aat:300008706"],"id":2250076,"name:xx":"Collins Creek"}}
>>>>>>> 03f74aca74312dbeaf24d7e61306dd6a786dc3d0
