{
  "id": 2655691,
  "type": "Feature",
  "properties": {
    "tgn:hierarchy":[
        "tgn:2655691",
        "tgn:1000001",
        "tgn:7012149",
        "tgn:7007157",
        "tgn:2000186",
        "tgn:7029392"
    ],
    "tgn:id":2655691,
    "tgn:name":"Shartell Canyon",
    "tgn:placetype":[
        "aat:300008761"
    ]
},
  "bbox": [],
  "geometry": {"coordinates":[-120.2167,41.75],"type":"Point"}
}