{
  "id": 7336314,
  "type": "Feature",
  "properties": {
    "tgn:hierarchy":[
        "tgn:7336314",
        "tgn:7001122",
        "tgn:1000003",
        "tgn:7002765",
        "tgn:1000095",
        "tgn:7029392"
    ],
    "tgn:id":7336314,
    "tgn:name":"Fornells, Puerto de",
    "tgn:placetype":[
        "aat:300132316"
    ]
},
  "bbox": [],
  "geometry": {"coordinates":[4.133333,40.066667],"type":"Point"}
}