<<<<<<< HEAD
{
  "id": 2254996,
  "type": "Feature",
  "properties": {
    "tgn:hierarchy":[
        "tgn:2254996",
        "tgn:7002659",
        "tgn:1000001",
        "tgn:7012149",
        "tgn:2000034",
        "tgn:7029392"
    ],
    "tgn:id":2254996,
    "tgn:name":"Cooper Creek",
    "tgn:placetype":[
        "aat:300008706"
    ]
},
  "bbox": [],
  "geometry": {"coordinates":[-85.3,31.1833],"type":"Point"}
}
=======
{"geometry":{"type":"Point","coordinates":[-85.300000,31.183300]},"type":"Feature","properties":{"hierarchy":["tgn:2254996","tgn:7002659","tgn:1000001","tgn:7012149","tgn:2000034","tgn:7029392"],"placetype":["aat:300008706"],"id":2254996,"name:xx":"Cooper Creek"}}
>>>>>>> 03f74aca74312dbeaf24d7e61306dd6a786dc3d0
