{
  "id": 2276987,
  "type": "Feature",
  "properties": {
    "tgn:hierarchy":[
        "tgn:2276987",
        "tgn:7002659",
        "tgn:1000001",
        "tgn:2000008",
        "tgn:7012149",
        "tgn:7029392"
    ],
    "tgn:id":2276987,
    "tgn:name":"Davis Creek",
    "tgn:placetype":[
        "aat:300008706"
    ]
},
  "bbox": [],
  "geometry": {"coordinates":[-85.3333,33.0667],"type":"Point"}
}