<<<<<<< HEAD
{
  "id": 7351460,
  "type": "Feature",
  "properties": {
    "tgn:hierarchy":[
        "tgn:7351460",
        "tgn:1000001",
        "tgn:7005595",
        "tgn:7005560",
        "tgn:7029392"
    ],
    "tgn:id":7351460,
    "tgn:name":"Bomba los Taxtes",
    "tgn:placetype":[
        "aat:300008347"
    ]
},
  "bbox": [],
  "geometry": {"coordinates":[-108.933333,25.916667],"type":"Point"}
}
=======
{"geometry":{"type":"Point","coordinates":[-108.933333,25.916667]},"type":"Feature","properties":{"hierarchy":["tgn:7351460","tgn:1000001","tgn:7005595","tgn:7005560","tgn:7029392"],"placetype":["aat:300008347"],"id":7351460,"name:xx":"Bomba los Taxtes"}}
>>>>>>> 03f74aca74312dbeaf24d7e61306dd6a786dc3d0
