{
  "id": 2339216,
  "type": "Feature",
  "properties": {
    "tgn:hierarchy":[
        "tgn:2339216",
        "tgn:1000001",
        "tgn:7012149",
        "tgn:7014097",
        "tgn:7007158",
        "tgn:7029392"
    ],
    "tgn:id":2339216,
    "tgn:name":"Franktown Parker FPE-5 Reservoir",
    "tgn:placetype":[
        "aat:300006191"
    ]
},
  "bbox": [],
  "geometry": {"coordinates":[-104.7167,39.0833],"type":"Point"}
}