<<<<<<< HEAD
{
  "id": 2337916,
  "type": "Feature",
  "properties": {
    "tgn:hierarchy":[
        "tgn:2337916",
        "tgn:1000001",
        "tgn:7012149",
        "tgn:1002998",
        "tgn:7007922",
        "tgn:7029392"
    ],
    "tgn:id":2337916,
    "tgn:name":"Fox Hill",
    "tgn:placetype":[
        "aat:300008798"
    ]
},
  "bbox": [],
  "geometry": {"coordinates":[-88.25,43.3667],"type":"Point"}
}
=======
{"geometry":{"type":"Point","coordinates":[-88.250000,43.366700]},"type":"Feature","properties":{"hierarchy":["tgn:2337916","tgn:1000001","tgn:7012149","tgn:1002998","tgn:7007922","tgn:7029392"],"placetype":["aat:300008798"],"id":2337916,"name:xx":"Fox Hill"}}
>>>>>>> 03f74aca74312dbeaf24d7e61306dd6a786dc3d0
