{
  "id": 2337916,
  "type": "Feature",
  "properties": {
    "tgn:hierarchy":[
        "tgn:2337916",
        "tgn:1000001",
        "tgn:7012149",
        "tgn:1002998",
        "tgn:7007922",
        "tgn:7029392"
    ],
    "tgn:id":2337916,
    "tgn:name":"Fox Hill",
    "tgn:placetype":[
        "aat:300008798"
    ]
},
  "bbox": [],
  "geometry": {"coordinates":[-88.25,43.3667],"type":"Point"}
}