{
  "id": 7338434,
  "type": "Feature",
  "properties": {
    "tgn:hierarchy":[
        "tgn:7338434",
        "tgn:7002811",
        "tgn:1000003",
        "tgn:7003837",
        "tgn:1000095",
        "tgn:7029392"
    ],
    "tgn:id":7338434,
    "tgn:name":"Castillo",
    "tgn:placetype":[
        "aat:300008347"
    ]
},
  "bbox": [],
  "geometry": {"coordinates":[-6.366667,40.35],"type":"Point"}
}