{
  "id": 2432474,
  "type": "Feature",
  "properties": {
    "tgn:hierarchy":[
        "tgn:2432474",
        "tgn:1002648",
        "tgn:1000001",
        "tgn:1008191",
        "tgn:7012149",
        "tgn:7007249",
        "tgn:7029392"
    ],
    "tgn:id":2432474,
    "tgn:name":"Keawanui",
    "tgn:placetype":[
        "aat:300008850"
    ]
},
  "bbox": [],
  "geometry": {"coordinates":[-156.8833,21.1667],"type":"Point"}
}