{
  "id": 7512806,
  "type": "Feature",
  "properties": {
    "tgn:hierarchy":[
        "tgn:7512806",
        "tgn:7000508",
        "tgn:1008380",
        "tgn:1000226",
        "tgn:1000006",
        "tgn:7029392"
    ],
    "tgn:id":7512806,
    "tgn:name:en":"Hendersons Creek",
    "tgn:placetype":[
        "aat:300008777"
    ]
},
  "bbox": [],
  "geometry": {"coordinates":[174.633333,-36.816667],"type":"Point"}
}