{
  "id": 7286240,
  "type": "Feature",
  "properties": {
    "tgn:hierarchy":[
        "tgn:7286240",
        "tgn:1001637",
        "tgn:1000049",
        "tgn:1000002",
        "tgn:7029392"
    ],
    "tgn:id":7286240,
    "tgn:name":"Horn, Estero",
    "tgn:placetype":[
        "aat:300008699"
    ]
},
  "bbox": [],
  "geometry": {"coordinates":[-71.216667,-36.766667],"type":"Point"}
}