{
  "id": 7585914,
  "type": "Feature",
  "properties": {
    "tgn:hierarchy":[
        "tgn:7585914",
        "tgn:1000004",
        "tgn:7000198",
        "tgn:7000799",
        "tgn:7029392"
    ],
    "tgn:id":7585914,
    "tgn:name:en":"Wusan",
    "tgn:placetype":[
        "aat:300008347"
    ]
},
  "bbox": [],
  "geometry": {"coordinates":[74.839565,34.288881],"type":"Point"}
}