<<<<<<< HEAD
{
  "id": 7056005,
  "type": "Feature",
  "properties": {
    "tgn:hierarchy":[
        "tgn:7056005",
        "tgn:7003150",
        "tgn:1000003",
        "tgn:7003237",
        "tgn:1000080",
        "tgn:7029392"
    ],
    "tgn:id":7056005,
    "tgn:name":"Stazione Milano Porta Romana",
    "tgn:placetype":[
        "aat:300007783"
    ]
},
  "bbox": [],
  "geometry": {"coordinates":[9.2,45.45],"type":"Point"}
}
=======
{"geometry":{"type":"Point","coordinates":[9.200000,45.450000]},"type":"Feature","properties":{"hierarchy":["tgn:7056005","tgn:7003150","tgn:1000003","tgn:7003237","tgn:1000080","tgn:7029392"],"placetype":["aat:300007783"],"id":7056005,"name:xx":"Stazione Milano Porta Romana"}}
>>>>>>> 03f74aca74312dbeaf24d7e61306dd6a786dc3d0
