{
  "id": 7499406,
  "type": "Feature",
  "properties": {
    "tgn:hierarchy":[
        "tgn:7499406",
        "tgn:1000004",
        "tgn:7001009",
        "tgn:1000141",
        "tgn:7029392"
    ],
    "tgn:id":7499406,
    "tgn:name":"Dabucuo",
    "tgn:placetype":[
        "aat:300008347"
    ]
},
  "bbox": [],
  "geometry": {"coordinates":[120.685719,24.225925],"type":"Point"}
}