{
  "id": 2487062,
  "type": "Feature",
  "properties": {
    "tgn:hierarchy":[
        "tgn:2487062",
        "tgn:1000001",
        "tgn:7012149",
        "tgn:2001854",
        "tgn:7007825",
        "tgn:7029392"
    ],
    "tgn:id":2487062,
    "tgn:name":"Lee Spring",
    "tgn:placetype":[
        "aat:300008697"
    ]
},
  "bbox": [],
  "geometry": {"coordinates":[-84.9833,35.7667],"type":"Point"}
}