{
  "id": 7519642,
  "type": "Feature",
  "properties": {
    "tgn:hierarchy":[
        "tgn:7519642",
        "tgn:1009227",
        "tgn:1000226",
        "tgn:1000006",
        "tgn:7016850",
        "tgn:7029392"
    ],
    "tgn:id":7519642,
    "tgn:name:en":"Bluestream",
    "tgn:placetype":[
        "aat:300008699"
    ]
},
  "bbox": [],
  "geometry": {"coordinates":[170.15,-43.716667],"type":"Point"}
}