{
  "id": 2508634,
  "type": "Feature",
  "properties": {
    "tgn:hierarchy":[
        "tgn:2508634",
        "tgn:1000001",
        "tgn:7012149",
        "tgn:2001460",
        "tgn:7007566",
        "tgn:7029392"
    ],
    "tgn:id":2508634,
    "tgn:name":"Middle Ditch",
    "tgn:placetype":[
        "aat:300006075"
    ]
},
  "bbox": [],
  "geometry": {"coordinates":[-106.6833,34.8167],"type":"Point"}
}