{
  "id": 2678099,
  "type": "Feature",
  "properties": {
    "tgn:hierarchy":[
        "tgn:2678099",
        "tgn:1000001",
        "tgn:7012149",
        "tgn:1002599",
        "tgn:7007708",
        "tgn:7029392"
    ],
    "tgn:id":2678099,
    "tgn:name":"South Fork Big Creek",
    "tgn:placetype":[
        "aat:300008706"
    ]
},
  "bbox": [],
  "geometry": {"coordinates":[-124.0333,44.3333],"type":"Point"}
}