{
  "id": 7190089,
  "type": "Feature",
  "properties": {
    "tgn:hierarchy":[
        "tgn:7190089",
        "tgn:7003692",
        "tgn:1000003",
        "tgn:7000084",
        "tgn:7029392"
    ],
    "tgn:id":7190089,
    "tgn:name":"Enkendorf",
    "tgn:placetype":[
        "aat:300008347"
    ]
},
  "bbox": [],
  "geometry": {"coordinates":[7.883333,47.616667],"type":"Point"}
}