{
  "id": 7090621,
  "type": "Feature",
  "properties": {
    "tgn:hierarchy":[
        "tgn:7090621",
        "tgn:1000003",
        "tgn:7003676",
        "tgn:7000084",
        "tgn:7029392"
    ],
    "tgn:id":7090621,
    "tgn:name":"Voss-Berg",
    "tgn:placetype":[
        "aat:300008777"
    ]
},
  "bbox": [],
  "geometry": {"coordinates":[10.783333,53.016667],"type":"Point"}
}