{
  "id": 2097778,
  "type": "Feature",
  "properties": {
    "tgn:hierarchy":[
        "tgn:2097778",
        "tgn:1000001",
        "tgn:7012149",
        "tgn:2001847",
        "tgn:7007825",
        "tgn:7029392"
    ],
    "tgn:id":2097778,
    "tgn:name":"Ashland City",
    "tgn:placetype":[
        "aat:300008347"
    ]
},
  "bbox": [],
  "geometry": {"coordinates":[-87.05,36.2667],"type":"Point"}
}