{
  "id": 7329262,
  "type": "Feature",
  "properties": {
    "tgn:hierarchy":[
        "tgn:7329262",
        "tgn:7001158",
        "tgn:7002848",
        "tgn:1000003",
        "tgn:1000095",
        "tgn:7029392"
    ],
    "tgn:id":7329262,
    "tgn:name":"Poz\u00e1ldez",
    "tgn:placetype":[
        "aat:300008347"
    ]
},
  "bbox": [],
  "geometry": {"coordinates":[-4.833333,41.366667],"type":"Point"}
}