{
  "id": 7522908,
  "type": "Feature",
  "properties": {
    "tgn:hierarchy":[
        "tgn:7522908",
        "tgn:7001242",
        "tgn:7016833",
        "tgn:1001083",
        "tgn:7029392"
    ],
    "tgn:id":7522908,
    "tgn:name:en":"A\u015ffar, A\u0163 \u0162\u016br al",
    "tgn:placetype":[
        "aat:300008777"
    ]
},
  "bbox": [],
  "geometry": {"coordinates":[31.433333,29.583333],"type":"Point"}
}