{
  "id": 1077667,
  "type": "Feature",
  "properties": {
    "tgn:hierarchy":[
        "tgn:1077667",
        "tgn:1000004",
        "tgn:1001382",
        "tgn:1000116",
        "tgn:7029392"
    ],
    "tgn:id":1077667,
    "tgn:name":"Gedongtataan",
    "tgn:placetype":[
        "aat:300008347"
    ]
},
  "bbox": [],
  "geometry": {"coordinates":[105.0833,-5.3833],"type":"Point"}
}