{
  "id": 7585635,
  "type": "Feature",
  "properties": {
    "tgn:hierarchy":[
        "tgn:7585635",
        "tgn:1000004",
        "tgn:7000198",
        "tgn:7000799",
        "tgn:7029392"
    ],
    "tgn:id":7585635,
    "tgn:name:en":"Gujarkot",
    "tgn:placetype":[
        "aat:300008347"
    ]
},
  "bbox": [],
  "geometry": {"coordinates":[74.872222,34.258333],"type":"Point"}
}