{
  "id": 2692264,
  "type": "Feature",
  "properties": {
    "tgn:hierarchy":[
        "tgn:2692264",
        "tgn:1000001",
        "tgn:7012149",
        "tgn:2000488",
        "tgn:7007250",
        "tgn:7029392"
    ],
    "tgn:id":2692264,
    "tgn:name":"Statue Hills",
    "tgn:placetype":[
        "aat:300008798"
    ]
},
  "bbox": [],
  "geometry": {"coordinates":[-116.8667,43.0833],"type":"Point"}
}