{
  "id": 2138542,
  "type": "Feature",
  "properties": {
    "tgn:hierarchy":[
        "tgn:2138542",
        "tgn:1000001",
        "tgn:7012149",
        "tgn:7029392"
    ],
    "tgn:id":2138542,
    "tgn:name":"Ash Creek",
    "tgn:placetype":[
        "aat:300008706"
    ]
},
  "bbox": [],
  "geometry": {"coordinates":[-94.4333,34.1833],"type":"Point"}
}