{
  "id": 7301012,
  "type": "Feature",
  "properties": {
    "tgn:hierarchy":[
        "tgn:7301012",
        "tgn:7002826",
        "tgn:7001158",
        "tgn:1000003",
        "tgn:1000095",
        "tgn:7029392"
    ],
    "tgn:id":7301012,
    "tgn:name":"Montes de Valdueza",
    "tgn:placetype":[
        "aat:300008347"
    ]
},
  "bbox": [],
  "geometry": {"coordinates":[-6.566667,42.45],"type":"Point"}
}