{
  "id": 7385934,
  "type": "Feature",
  "properties": {
    "tgn:hierarchy":[
        "tgn:7385934",
        "tgn:7005580",
        "tgn:1000001",
        "tgn:7005560",
        "tgn:7029392"
    ],
    "tgn:id":7385934,
    "tgn:name":"Pir\u00e1mide, Cerro la",
    "tgn:placetype":[
        "aat:300008795"
    ]
},
  "bbox": [],
  "geometry": {"coordinates":[-91.483333,16.166667],"type":"Point"}
}