{
  "id": 2610640,
  "type": "Feature",
  "properties": {
    "tgn:hierarchy":[
        "tgn:2610640",
        "tgn:1000001",
        "tgn:7012149",
        "tgn:1002681",
        "tgn:7007568",
        "tgn:7029392"
    ],
    "tgn:id":2610640,
    "tgn:name":"Red Creek",
    "tgn:placetype":[
        "aat:300008706"
    ]
},
  "bbox": [],
  "geometry": {"coordinates":[-77.6333,43.0167],"type":"Point"}
}