{
  "id": 7285453,
  "type": "Feature",
  "properties": {
    "tgn:hierarchy":[
        "tgn:7285453",
        "tgn:7002464",
        "tgn:1000049",
        "tgn:1000002",
        "tgn:7029392"
    ],
    "tgn:id":7285453,
    "tgn:name":"Que\u00f1iza",
    "tgn:placetype":[
        "aat:300008347"
    ]
},
  "bbox": [],
  "geometry": {"coordinates":[-68.916667,-19.366667],"type":"Point"}
}