{
  "id": 7333924,
  "type": "Feature",
  "properties": {
    "tgn:hierarchy":[
        "tgn:7333924",
        "tgn:7001165",
        "tgn:1000003",
        "tgn:7002793",
        "tgn:1000095",
        "tgn:7029392"
    ],
    "tgn:id":7333924,
    "tgn:name":"\u00c9nova",
    "tgn:placetype":[
        "aat:300008347"
    ]
},
  "bbox": [],
  "geometry": {"coordinates":[-0.483333,39.05],"type":"Point"}
}