{
  "id": 7233117,
  "type": "Feature",
  "properties": {
    "tgn:hierarchy":[
        "tgn:7233117",
        "tgn:7011270",
        "tgn:7002674",
        "tgn:1000003",
        "tgn:1000074",
        "tgn:7029392"
    ],
    "tgn:id":7233117,
    "tgn:name":"K\u00e1to Sangr\u00edon",
    "tgn:placetype":[
        "aat:300008347"
    ]
},
  "bbox": [],
  "geometry": {"coordinates":[25.433333,37.033333],"type":"Point"}
}