<<<<<<< HEAD
{
  "id": 2332933,
  "type": "Feature",
  "properties": {
    "tgn:hierarchy":[
        "tgn:2332933",
        "tgn:1000001",
        "tgn:7012149",
        "tgn:7007158",
        "tgn:7029392"
    ],
    "tgn:id":2332933,
    "tgn:name":"Flume Creek",
    "tgn:placetype":[
        "aat:300008706"
    ]
},
  "bbox": [],
  "geometry": {"coordinates":[-106.3333,39.0333],"type":"Point"}
}
=======
{"geometry":{"type":"Point","coordinates":[-106.333300,39.033300]},"type":"Feature","properties":{"hierarchy":["tgn:2332933","tgn:1000001","tgn:7012149","tgn:7007158","tgn:7029392"],"placetype":["aat:300008706"],"id":2332933,"name:xx":"Flume Creek"}}
>>>>>>> 03f74aca74312dbeaf24d7e61306dd6a786dc3d0
