{
  "id": 7584544,
  "type": "Feature",
  "properties": {
    "tgn:hierarchy":[
        "tgn:7584544",
        "tgn:1000004",
        "tgn:7000198",
        "tgn:1001894",
        "tgn:7029392"
    ],
    "tgn:id":7584544,
    "tgn:name:en":"Karm\u0101sin Chhoti",
    "tgn:placetype":[
        "aat:300008347"
    ]
},
  "bbox": [],
  "geometry": {"coordinates":[78.99713,24.786999],"type":"Point"}
}