{
  "id": 7017739,
  "type": "Feature",
  "properties": {
    "tgn:hierarchy":[
        "tgn:7017739",
        "tgn:1000001",
        "tgn:7012149",
        "tgn:2001720",
        "tgn:7007708",
        "tgn:7029392"
    ],
    "tgn:id":7017739,
    "tgn:name":"Umatilla",
    "tgn:placetype":[
        "aat:300008347",
        "aat:300000835"
    ]
},
  "bbox": [],
  "geometry": {"coordinates":[-119.3333,45.9167],"type":"Point"}
}