{
  "id": 2053672,
  "type": "Feature",
  "properties": {
    "tgn:hierarchy":[
        "tgn:2053672",
        "tgn:1000001",
        "tgn:7012149",
        "tgn:1002502",
        "tgn:7007520",
        "tgn:7029392"
    ],
    "tgn:id":2053672,
    "tgn:name":"Webberville",
    "tgn:placetype":[
        "aat:300008347"
    ]
},
  "bbox": [],
  "geometry": {"coordinates":[-84.1667,42.6667],"type":"Point"}
}