{
  "id": 1113556,
  "type": "Feature",
  "properties": {
    "tgn:hierarchy":[
        "tgn:1113556",
        "tgn:7006638",
        "tgn:1000003",
        "tgn:7006540",
        "tgn:7029392"
    ],
    "tgn:id":1113556,
    "tgn:name:en":"P\u00e4rnu Laht",
    "tgn:placetype":[
        "aat:300132316"
    ]
},
  "bbox": [],
  "geometry": {"coordinates":[24.372,58.288],"type":"Point"}
}