{
  "id": 2772692,
  "type": "Feature",
  "properties": {
    "tgn:hierarchy":[
        "tgn:2772692",
        "tgn:1000001",
        "tgn:7012149",
        "tgn:2002159",
        "tgn:7007919",
        "tgn:7029392"
    ],
    "tgn:id":2772692,
    "tgn:name":"Williams Creek",
    "tgn:placetype":[
        "aat:300008706"
    ]
},
  "bbox": [],
  "geometry": {"coordinates":[-78.2833,37.8167],"type":"Point"}
}