<<<<<<< HEAD
{
  "id": 7024525,
  "type": "Feature",
  "properties": {
    "tgn:hierarchy":[
        "tgn:7024525",
        "tgn:7593551",
        "tgn:1000001",
        "tgn:7024573",
        "tgn:7029392"
    ],
    "tgn:id":7024525,
    "tgn:name":"Qeqertarsuaq",
    "tgn:placetype":[
        "aat:300008791"
    ]
},
  "bbox": [],
  "geometry": {"coordinates":[-45.7333,60.5],"type":"Point"}
}
=======
{"geometry":{"type":"Point","coordinates":[-45.733300,60.500000]},"type":"Feature","properties":{"hierarchy":["tgn:7024525","tgn:7593551","tgn:1000001","tgn:7024573","tgn:7029392"],"placetype":["aat:300008791"],"id":7024525,"name:xx":"Qeqertarsuaq"}}
>>>>>>> 03f74aca74312dbeaf24d7e61306dd6a786dc3d0
