{
  "id": 2432503,
  "type": "Feature",
  "properties": {
    "tgn:hierarchy":[
        "tgn:2432503",
        "tgn:7006450",
        "tgn:1000001",
        "tgn:7012149",
        "tgn:2000085",
        "tgn:7029392"
    ],
    "tgn:id":2432503,
    "tgn:name":"Kechumstuk Creek",
    "tgn:placetype":[
        "aat:300008706"
    ]
},
  "bbox": [],
  "geometry": {"coordinates":[-143.0833,64.0333],"type":"Point"}
}