{
  "id": 2428464,
  "type": "Feature",
  "properties": {
    "tgn:hierarchy":[
        "tgn:2428464",
        "tgn:7002659",
        "tgn:1000001",
        "tgn:7012149",
        "tgn:2000062",
        "tgn:7029392"
    ],
    "tgn:id":2428464,
    "tgn:name":"Judson, Lake",
    "tgn:placetype":[
        "aat:300008680"
    ]
},
  "bbox": [],
  "geometry": {"coordinates":[-87.45,33.1167],"type":"Point"}
}