<<<<<<< HEAD
{
  "id": 2251529,
  "type": "Feature",
  "properties": {
    "tgn:hierarchy":[
        "tgn:2251529",
        "tgn:1000001",
        "tgn:2001938",
        "tgn:7012149",
        "tgn:7007826",
        "tgn:7029392"
    ],
    "tgn:id":2251529,
    "tgn:name":"Commissioners Creek",
    "tgn:placetype":[
        "aat:300008706"
    ]
},
  "bbox": [],
  "geometry": {"coordinates":[-99.2167,29.6833],"type":"Point"}
}
=======
{"geometry":{"type":"Point","coordinates":[-99.216700,29.683300]},"type":"Feature","properties":{"hierarchy":["tgn:2251529","tgn:1000001","tgn:2001938","tgn:7012149","tgn:7007826","tgn:7029392"],"placetype":["aat:300008706"],"id":2251529,"name:xx":"Commissioners Creek"}}
>>>>>>> 03f74aca74312dbeaf24d7e61306dd6a786dc3d0
