{
  "id": 2075624,
  "type": "Feature",
  "properties": {
    "tgn:hierarchy":[
        "tgn:2075624",
        "tgn:1000001",
        "tgn:7012149",
        "tgn:2001533",
        "tgn:7007709",
        "tgn:7029392"
    ],
    "tgn:id":2075624,
    "tgn:name":"Marston",
    "tgn:placetype":[
        "aat:300008347"
    ]
},
  "bbox": [],
  "geometry": {"coordinates":[-79.5667,34.9833],"type":"Point"}
}