{
  "id": 7011384,
  "type": "Feature",
  "properties": {
    "tgn:hierarchy":[
        "tgn:7011384",
        "tgn:7002681",
        "tgn:7001395",
        "tgn:1000003",
        "tgn:1000074",
        "tgn:7029392"
    ],
    "tgn:id":7011384,
    "tgn:name:en":"Piraeus",
    "tgn:placetype":[
        "aat:300008347",
        "aat:300008389",
        "aat:300120599"
    ]
},
  "bbox": [],
  "geometry": {"coordinates":[23.638889,37.961389],"type":"Point"}
}