{
  "id": 2693948,
  "type": "Feature",
  "properties": {
    "tgn:hierarchy":[
        "tgn:2693948",
        "tgn:1000001",
        "tgn:7012149",
        "tgn:2000996",
        "tgn:7007520",
        "tgn:7029392"
    ],
    "tgn:id":2693948,
    "tgn:name":"Steuben Lake",
    "tgn:placetype":[
        "aat:300008680"
    ]
},
  "bbox": [],
  "geometry": {"coordinates":[-86.4167,46.1833],"type":"Point"}
}