{
  "id": 1066499,
  "type": "Feature",
  "properties": {
    "tgn:hierarchy":[
        "tgn:1066499",
        "tgn:1000004",
        "tgn:7001745",
        "tgn:1000111",
        "tgn:7029392"
    ],
    "tgn:id":1066499,
    "tgn:name":"Aketilepa",
    "tgn:placetype":[
        "aat:300008347"
    ]
},
  "bbox": [],
  "geometry": {"coordinates":[74.05,39.95],"type":"Point"}
}