{
  "id": 7221832,
  "type": "Feature",
  "properties": {
    "tgn:hierarchy":[
        "tgn:7221832",
        "tgn:7002724",
        "tgn:7002715",
        "tgn:1000003",
        "tgn:1000074",
        "tgn:7029392"
    ],
    "tgn:id":7221832,
    "tgn:name":"Skalokh\u00f3rion",
    "tgn:placetype":[
        "aat:300008347"
    ]
},
  "bbox": [],
  "geometry": {"coordinates":[21.233333,40.366667],"type":"Point"}
}