{
  "id": 2652160,
  "type": "Feature",
  "properties": {
    "tgn:hierarchy":[
        "tgn:2652160",
        "tgn:1000001",
        "tgn:7012149",
        "tgn:2001437",
        "tgn:7007566",
        "tgn:7029392"
    ],
    "tgn:id":2652160,
    "tgn:name":"Sellers Mine",
    "tgn:placetype":[
        "aat:300000390"
    ]
},
  "bbox": [],
  "geometry": {"coordinates":[-108.3333,32.5333],"type":"Point"}
}