{
  "id": 1070432,
  "type": "Feature",
  "properties": {
    "tgn:hierarchy":[
        "tgn:1070432",
        "tgn:1000004",
        "tgn:1001390",
        "tgn:1000111",
        "tgn:7029392"
    ],
    "tgn:id":1070432,
    "tgn:name":"Mengjiawopeng",
    "tgn:placetype":[
        "aat:300008347"
    ]
},
  "bbox": [],
  "geometry": {"coordinates":[121.85,41.3667],"type":"Point"}
}