{
  "id": 2170346,
  "type": "Feature",
  "properties": {
    "tgn:hierarchy":[
        "tgn:2170346",
        "tgn:1000001",
        "tgn:2002261",
        "tgn:7012149",
        "tgn:7013961",
        "tgn:7029392"
    ],
    "tgn:id":2170346,
    "tgn:name":"Big Righthand Fork",
    "tgn:placetype":[
        "aat:300008699"
    ]
},
  "bbox": [],
  "geometry": {"coordinates":[-81.2833,38.0667],"type":"Point"}
}