{
  "id": 1084951,
  "type": "Feature",
  "properties": {
    "tgn:hierarchy":[
        "tgn:1084951",
        "tgn:1000139",
        "tgn:7004345",
        "tgn:1000004",
        "tgn:7000261",
        "tgn:7029392"
    ],
    "tgn:id":1084951,
    "tgn:name":"\u02bbIy\u0101dh",
    "tgn:placetype":[
        "aat:300008347"
    ]
},
  "bbox": [],
  "geometry": {"coordinates":[46.8333,14.9833],"type":"Point"}
}