{
  "id": 7592871,
  "type": "Feature",
  "properties": {
    "tgn:hierarchy":[
        "tgn:7592871",
        "tgn:1000004",
        "tgn:7000198",
        "tgn:7000799",
        "tgn:7029392"
    ],
    "tgn:id":7592871,
    "tgn:name:en":"Pandori",
    "tgn:placetype":[
        "aat:300008347"
    ]
},
  "bbox": [],
  "geometry": {"coordinates":[74.336111,33.079167],"type":"Point"}
}