{
  "id": 2184187,
  "type": "Feature",
  "properties": {
    "tgn:hierarchy":[
        "tgn:2184187",
        "tgn:1000001",
        "tgn:2000198",
        "tgn:7012149",
        "tgn:7007158",
        "tgn:7029392"
    ],
    "tgn:id":2184187,
    "tgn:name":"Bob Lake",
    "tgn:placetype":[
        "aat:300008680"
    ]
},
  "bbox": [],
  "geometry": {"coordinates":[-105.6833,39.95],"type":"Point"}
}