{
  "id": 7224229,
  "type": "Feature",
  "properties": {
    "tgn:hierarchy":[
        "tgn:7224229",
        "tgn:7011170",
        "tgn:7002715",
        "tgn:1000003",
        "tgn:1000074",
        "tgn:7029392"
    ],
    "tgn:id":7224229,
    "tgn:name":"Nikots\u00e1ras",
    "tgn:placetype":[
        "aat:300008347"
    ]
},
  "bbox": [],
  "geometry": {"coordinates":[24.083333,41.116667],"type":"Point"}
}