{
  "id": 2167313,
  "type": "Feature",
  "properties": {
    "tgn:hierarchy":[
        "tgn:2167313",
        "tgn:1000001",
        "tgn:2000465",
        "tgn:7012149",
        "tgn:7007250",
        "tgn:7029392"
    ],
    "tgn:id":2167313,
    "tgn:name":"Big Cottonwood Island",
    "tgn:placetype":[
        "aat:300008791"
    ]
},
  "bbox": [],
  "geometry": {"coordinates":[-117.0167,43.8167],"type":"Point"}
}