{
  "id": 7022634,
  "type": "Feature",
  "properties": {
    "tgn:hierarchy":[
        "tgn:7022634",
        "tgn:1000001",
        "tgn:7012149",
        "tgn:7007568",
        "tgn:7029392"
    ],
    "tgn:id":7022634,
    "tgn:name":"Crab Pond",
    "tgn:placetype":[
        "aat:300008680"
    ]
},
  "bbox": [],
  "geometry": {"coordinates":[-73.6333,43.8333],"type":"Point"}
}