<<<<<<< HEAD
{
  "id": 7022634,
  "type": "Feature",
  "properties": {
    "tgn:hierarchy":[
        "tgn:7022634",
        "tgn:1000001",
        "tgn:7012149",
        "tgn:7007568",
        "tgn:7029392"
    ],
    "tgn:id":7022634,
    "tgn:name":"Crab Pond",
    "tgn:placetype":[
        "aat:300008680"
    ]
},
  "bbox": [],
  "geometry": {"coordinates":[-73.6333,43.8333],"type":"Point"}
}
=======
{"geometry":{"type":"Point","coordinates":[-73.633300,43.833300]},"type":"Feature","properties":{"hierarchy":["tgn:7022634","tgn:1000001","tgn:7012149","tgn:7007568","tgn:7029392"],"placetype":["aat:300008680"],"id":7022634,"name:xx":"Crab Pond"}}
>>>>>>> 03f74aca74312dbeaf24d7e61306dd6a786dc3d0
