{
  "id": 2225482,
  "type": "Feature",
  "properties": {
    "tgn:hierarchy":[
        "tgn:2225482",
        "tgn:1000001",
        "tgn:7012149",
        "tgn:2001718",
        "tgn:7007708",
        "tgn:7029392"
    ],
    "tgn:id":2225482,
    "tgn:name":"Castle View Spring",
    "tgn:placetype":[
        "aat:300008697"
    ]
},
  "bbox": [],
  "geometry": {"coordinates":[-118.1667,44.1167],"type":"Point"}
}