<<<<<<< HEAD
{
  "id": 7119650,
  "type": "Feature",
  "properties": {
    "tgn:hierarchy":[
        "tgn:7119650",
        "tgn:7003669",
        "tgn:1000003",
        "tgn:7000084",
        "tgn:7029392"
    ],
    "tgn:id":7119650,
    "tgn:name":"Lange Mass",
    "tgn:placetype":[
        "aat:300008777"
    ]
},
  "bbox": [],
  "geometry": {"coordinates":[10.933333,50.25],"type":"Point"}
}
=======
{"geometry":{"type":"Point","coordinates":[10.933333,50.250000]},"type":"Feature","properties":{"hierarchy":["tgn:7119650","tgn:7003669","tgn:1000003","tgn:7000084","tgn:7029392"],"placetype":["aat:300008777"],"id":7119650,"name:xx":"Lange Mass"}}
>>>>>>> 03f74aca74312dbeaf24d7e61306dd6a786dc3d0
