{
  "id": 2678240,
  "type": "Feature",
  "properties": {
    "tgn:hierarchy":[
        "tgn:2678240",
        "tgn:1000001",
        "tgn:7012149",
        "tgn:7007250",
        "tgn:7029392"
    ],
    "tgn:id":2678240,
    "tgn:name":"South Fork Bull Canyon",
    "tgn:placetype":[
        "aat:300008761"
    ]
},
  "bbox": [],
  "geometry": {"coordinates":[-112.6833,42.3167],"type":"Point"}
}