{
  "id": 2518421,
  "type": "Feature",
  "properties": {
    "tgn:hierarchy":[
        "tgn:2518421",
        "tgn:7002659",
        "tgn:1000001",
        "tgn:7012149",
        "tgn:2000023",
        "tgn:7029392"
    ],
    "tgn:id":2518421,
    "tgn:name":"Mitchell Bar",
    "tgn:placetype":[
        "aat:300132348"
    ]
},
  "bbox": [],
  "geometry": {"coordinates":[-87.1333,32.25],"type":"Point"}
}