{
  "id": 7564223,
  "type": "Feature",
  "properties": {
    "tgn:hierarchy":[
        "tgn:7564223",
        "tgn:1000004",
        "tgn:7000198",
        "tgn:7016722",
        "tgn:7029392"
    ],
    "tgn:id":7564223,
    "tgn:name:en":"Kharagpur",
    "tgn:placetype":[
        "aat:300008347"
    ]
},
  "bbox": [],
  "geometry": {"coordinates":[79.588625,26.952935],"type":"Point"}
}