<<<<<<< HEAD
{
  "id": 7171669,
  "type": "Feature",
  "properties": {
    "tgn:hierarchy":[
        "tgn:7171669",
        "tgn:1000003",
        "tgn:7003676",
        "tgn:7000084",
        "tgn:7029392"
    ],
    "tgn:id":7171669,
    "tgn:name":"Hemmelsb\u00e4ker Kanal",
    "tgn:placetype":[
        "aat:300006075"
    ]
},
  "bbox": [],
  "geometry": {"coordinates":[8.333333,53.1],"type":"Point"}
}
=======
{"geometry":{"type":"Point","coordinates":[8.333333,53.100000]},"type":"Feature","properties":{"hierarchy":["tgn:7171669","tgn:1000003","tgn:7003676","tgn:7000084","tgn:7029392"],"placetype":["aat:300006075"],"id":7171669,"name:xx":"Hemmelsb\u00e4ker Kanal"}}
>>>>>>> 03f74aca74312dbeaf24d7e61306dd6a786dc3d0
