{
  "id": 7141713,
  "type": "Feature",
  "properties": {
    "tgn:hierarchy":[
        "tgn:7141713",
        "tgn:1000003",
        "tgn:7003678",
        "tgn:7000084",
        "tgn:7029392"
    ],
    "tgn:id":7141713,
    "tgn:name":"Lingsgrund",
    "tgn:placetype":[
        "aat:300000206"
    ]
},
  "bbox": [],
  "geometry": {"coordinates":[9.783333,50.533333],"type":"Point"}
}