{
  "id": 2785596,
  "type": "Feature",
  "properties": {
    "tgn:hierarchy":[
        "tgn:2785596",
        "tgn:1000001",
        "tgn:7012149",
        "tgn:2001249",
        "tgn:7007523",
        "tgn:7029392"
    ],
    "tgn:id":2785596,
    "tgn:name":"Yocum Pond",
    "tgn:placetype":[
        "aat:300008680"
    ]
},
  "bbox": [],
  "geometry": {"coordinates":[-93.3833,36.7167],"type":"Point"}
}