{
  "id": 2297959,
  "type": "Feature",
  "properties": {
    "tgn:hierarchy":[
        "tgn:2297959",
        "tgn:1000001",
        "tgn:7012149",
        "tgn:2002047",
        "tgn:7007826",
        "tgn:7029392"
    ],
    "tgn:id":2297959,
    "tgn:name":"Dry Hurricane Creek",
    "tgn:placetype":[
        "aat:300008706"
    ]
},
  "bbox": [],
  "geometry": {"coordinates":[-93.8167,31.1167],"type":"Point"}
}