{
  "id": 7283042,
  "type": "Feature",
  "properties": {
    "tgn:hierarchy":[
        "tgn:7283042",
        "tgn:1001630",
        "tgn:1000049",
        "tgn:1000002",
        "tgn:7029392"
    ],
    "tgn:id":7283042,
    "tgn:name":"Patos, Portezuelo de los",
    "tgn:placetype":[
        "aat:300259572"
    ]
},
  "bbox": [],
  "geometry": {"coordinates":[-68.866667,-27.233333],"type":"Point"}
}