{
  "id": 2547441,
  "type": "Feature",
  "properties": {
    "tgn:hierarchy":[
        "tgn:2547441",
        "tgn:1000001",
        "tgn:7012149",
        "tgn:2002119",
        "tgn:7007827",
        "tgn:7029392"
    ],
    "tgn:id":2547441,
    "tgn:name":"North Fork South Creek",
    "tgn:placetype":[
        "aat:300008706"
    ]
},
  "bbox": [],
  "geometry": {"coordinates":[-109.4333,37.8333],"type":"Point"}
}