{
  "id": 2284357,
  "type": "Feature",
  "properties": {
    "tgn:hierarchy":[
        "tgn:2284357",
        "tgn:7006450",
        "tgn:1000001",
        "tgn:2124012",
        "tgn:7012149",
        "tgn:7029392"
    ],
    "tgn:id":2284357,
    "tgn:name":"Deranof Island",
    "tgn:placetype":[
        "aat:300008791"
    ]
},
  "bbox": [],
  "geometry": {"coordinates":[-152.8833,57.9667],"type":"Point"}
}