<<<<<<< HEAD
{
  "id": 7057122,
  "type": "Feature",
  "properties": {
    "tgn:hierarchy":[
        "tgn:7057122",
        "tgn:1003500",
        "tgn:1000003",
        "tgn:7010380",
        "tgn:1000080",
        "tgn:7029392"
    ],
    "tgn:id":7057122,
    "tgn:name":"Baracca, Punta della",
    "tgn:placetype":[
        "aat:300386846"
    ]
},
  "bbox": [],
  "geometry": {"coordinates":[17.3,40.366667],"type":"Point"}
}
=======
{"geometry":{"type":"Point","coordinates":[17.300000,40.366667]},"type":"Feature","properties":{"hierarchy":["tgn:7057122","tgn:1003500","tgn:1000003","tgn:7010380","tgn:1000080","tgn:7029392"],"placetype":["aat:300386846"],"id":7057122,"name:xx":"Baracca, Punta della"}}
>>>>>>> 03f74aca74312dbeaf24d7e61306dd6a786dc3d0
