{
  "id": 2237584,
  "type": "Feature",
  "properties": {
    "tgn:hierarchy":[
        "tgn:2237584",
        "tgn:1000001",
        "tgn:7006451",
        "tgn:7012149",
        "tgn:2000101",
        "tgn:7029392"
    ],
    "tgn:id":2237584,
    "tgn:name":"China Wash",
    "tgn:placetype":[
        "aat:300008699"
    ]
},
  "bbox": [],
  "geometry": {"coordinates":[-111.25,33.05],"type":"Point"}
}