{
  "id": 2521486,
  "type": "Feature",
  "properties": {
    "tgn:hierarchy":[
        "tgn:2521486",
        "tgn:1000001",
        "tgn:7012149",
        "tgn:1002545",
        "tgn:7007157",
        "tgn:7029392"
    ],
    "tgn:id":2521486,
    "tgn:name":"Montgomery Spring",
    "tgn:placetype":[
        "aat:300008697"
    ]
},
  "bbox": [],
  "geometry": {"coordinates":[-118.5333,35.2833],"type":"Point"}
}