{
  "id": 1082352,
  "type": "Feature",
  "properties": {
    "tgn:hierarchy":[
        "tgn:1082352",
        "tgn:1000004",
        "tgn:1001371",
        "tgn:7000299",
        "tgn:7029392"
    ],
    "tgn:id":1082352,
    "tgn:name":"Samch'\u014fnp'o",
    "tgn:placetype":[
        "aat:300008347"
    ]
},
  "bbox": [],
  "geometry": {"coordinates":[128.0667,34.9167],"type":"Point"}
}