{
  "id": 7272892,
  "type": "Feature",
  "properties": {
    "tgn:concordances":{
        "gn:id":"2745147"
    },
    "tgn:hierarchy":[
        "tgn:7272892",
        "tgn:1000003",
        "tgn:7003632",
        "tgn:7016845",
        "tgn:7029392"
    ],
    "tgn:id":7272892,
    "tgn:name:nl":"Vuilendam",
    "tgn:placetype":[
        "aat:300008347"
    ]
},
  "bbox": [],
  "geometry": {"coordinates":[4.85,51.883333],"type":"Point"}
}