{
  "id": 4003978,
  "type": "Feature",
  "properties": {
    "tgn:hierarchy":[
        "tgn:4003978",
        "tgn:1000003",
        "tgn:7002875",
        "tgn:1000070",
        "tgn:7029392"
    ],
    "tgn:id":4003978,
    "tgn:name":"Fontenoy",
    "tgn:placetype":[
        "aat:300008347",
        "aat:300000835",
        "aat:300008372"
    ]
},
  "bbox": [],
  "geometry": {"coordinates":[3.2833,47.65],"type":"Point"}
}