{
  "id": 7485293,
  "type": "Feature",
  "properties": {
    "tgn:hierarchy":[
        "tgn:7485293",
        "tgn:1000004",
        "tgn:7467799",
        "tgn:1000141",
        "tgn:7029392"
    ],
    "tgn:id":7485293,
    "tgn:name":"Haiwei Erhao Qiao",
    "tgn:placetype":[
        "aat:300007836"
    ]
},
  "bbox": [],
  "geometry": {"coordinates":[120.481944,24.169167],"type":"Point"}
}