<<<<<<< HEAD
{
  "id": 7485293,
  "type": "Feature",
  "properties": {
    "tgn:hierarchy":[
        "tgn:7485293",
        "tgn:1000004",
        "tgn:7467799",
        "tgn:1000141",
        "tgn:7029392"
    ],
    "tgn:id":7485293,
    "tgn:name":"Haiwei Erhao Qiao",
    "tgn:placetype":[
        "aat:300007836"
    ]
},
  "bbox": [],
  "geometry": {"coordinates":[120.481944,24.169167],"type":"Point"}
}
=======
{"geometry":{"type":"Point","coordinates":[120.481944,24.169167]},"type":"Feature","properties":{"hierarchy":["tgn:7485293","tgn:1000004","tgn:7467799","tgn:1000141","tgn:7029392"],"placetype":["aat:300007836"],"id":7485293,"name:xx":"Haiwei Erhao Qiao"}}
>>>>>>> 03f74aca74312dbeaf24d7e61306dd6a786dc3d0
