{
  "id": 2435975,
  "type": "Feature",
  "properties": {
    "tgn:hierarchy":[
        "tgn:2435975",
        "tgn:1000001",
        "tgn:7012149",
        "tgn:2000352",
        "tgn:7007248",
        "tgn:7029392"
    ],
    "tgn:id":2435975,
    "tgn:name":"Key Creek",
    "tgn:placetype":[
        "aat:300008706"
    ]
},
  "bbox": [],
  "geometry": {"coordinates":[-84.4167,34.8333],"type":"Point"}
}