<<<<<<< HEAD
{
  "id": 2705838,
  "type": "Feature",
  "properties": {
    "tgn:hierarchy":[
        "tgn:2705838",
        "tgn:1000001",
        "tgn:7012149",
        "tgn:7007825",
        "tgn:7029392"
    ],
    "tgn:id":2705838,
    "tgn:name":"Sutton Branch",
    "tgn:placetype":[
        "aat:300008699"
    ]
},
  "bbox": [],
  "geometry": {"coordinates":[-83.4167,36.5667],"type":"Point"}
}
=======
{"geometry":{"type":"Point","coordinates":[-83.416700,36.566700]},"type":"Feature","properties":{"hierarchy":["tgn:2705838","tgn:1000001","tgn:7012149","tgn:7007825","tgn:7029392"],"placetype":["aat:300008699"],"id":2705838,"name:xx":"Sutton Branch"}}
>>>>>>> 03f74aca74312dbeaf24d7e61306dd6a786dc3d0
