{
  "id": 2706080,
  "type": "Feature",
  "properties": {
    "tgn:hierarchy":[
        "tgn:2706080",
        "tgn:7006450",
        "tgn:1000001",
        "tgn:7012149",
        "tgn:2000088",
        "tgn:7029392"
    ],
    "tgn:id":2706080,
    "tgn:name":"Swaine Point",
    "tgn:placetype":[
        "aat:300008850"
    ]
},
  "bbox": [],
  "geometry": {"coordinates":[-134.2333,56.4167],"type":"Point"}
}