{
  "id": 2095790,
  "type": "Feature",
  "properties": {
    "tgn:hierarchy":[
        "tgn:2095790",
        "tgn:1000001",
        "tgn:7012149",
        "tgn:2001763",
        "tgn:7007712",
        "tgn:7029392"
    ],
    "tgn:id":2095790,
    "tgn:name":"Five Forks",
    "tgn:placetype":[
        "aat:300008347",
        "aat:300387210"
    ]
},
  "bbox": [],
  "geometry": {"coordinates":[-82.65,34.75],"type":"Point"}
}