{
  "id": 2427975,
  "type": "Feature",
  "properties": {
    "tgn:hierarchy":[
        "tgn:2427975",
        "tgn:7006450",
        "tgn:1000001",
        "tgn:2124089",
        "tgn:7012149",
        "tgn:7029392"
    ],
    "tgn:id":2427975,
    "tgn:name":"Jualin Mine",
    "tgn:placetype":[
        "aat:300000390"
    ]
},
  "bbox": [],
  "geometry": {"coordinates":[-135.0333,58.8333],"type":"Point"}
}