{
  "id": 2636721,
  "type": "Feature",
  "properties": {
    "tgn:hierarchy":[
        "tgn:2636721",
        "tgn:1000001",
        "tgn:2001801",
        "tgn:7012149",
        "tgn:7007713",
        "tgn:7029392"
    ],
    "tgn:id":2636721,
    "tgn:name":"Sagebrush Draw",
    "tgn:placetype":[
        "aat:300008761"
    ]
},
  "bbox": [],
  "geometry": {"coordinates":[-103.9333,45.4333],"type":"Point"}
}