{
  "id": 2020765,
  "type": "Feature",
  "properties": {
    "tgn:hierarchy":[
        "tgn:2020765",
        "tgn:1000001",
        "tgn:7012149",
        "tgn:2000283",
        "tgn:7007240",
        "tgn:7029392"
    ],
    "tgn:id":2020765,
    "tgn:name":"Palm Valley",
    "tgn:placetype":[
        "aat:300008347"
    ]
},
  "bbox": [],
  "geometry": {"coordinates":[-81.3833,30.1667],"type":"Point"}
}