{
  "id": 2579644,
  "type": "Feature",
  "properties": {
    "tgn:hierarchy":[
        "tgn:2579644",
        "tgn:1000001",
        "tgn:7012149",
        "tgn:2001983",
        "tgn:7007826",
        "tgn:7029392"
    ],
    "tgn:id":2579644,
    "tgn:name":"Pickle Creek",
    "tgn:placetype":[
        "aat:300008706"
    ]
},
  "bbox": [],
  "geometry": {"coordinates":[-96.0167,33.5167],"type":"Point"}
}