<<<<<<< HEAD
{
  "id": 2332938,
  "type": "Feature",
  "properties": {
    "tgn:hierarchy":[
        "tgn:2332938",
        "tgn:1000001",
        "tgn:7012149",
        "tgn:2000491",
        "tgn:7007250",
        "tgn:7029392"
    ],
    "tgn:id":2332938,
    "tgn:name":"Flume Creek",
    "tgn:placetype":[
        "aat:300008706"
    ]
},
  "bbox": [],
  "geometry": {"coordinates":[-115.95,47.35],"type":"Point"}
}
=======
{"geometry":{"type":"Point","coordinates":[-115.950000,47.350000]},"type":"Feature","properties":{"hierarchy":["tgn:2332938","tgn:1000001","tgn:7012149","tgn:2000491","tgn:7007250","tgn:7029392"],"placetype":["aat:300008706"],"id":2332938,"name:xx":"Flume Creek"}}
>>>>>>> 03f74aca74312dbeaf24d7e61306dd6a786dc3d0
