{
  "id": 2726034,
  "type": "Feature",
  "properties": {
    "tgn:hierarchy":[
        "tgn:2726034",
        "tgn:1000001",
        "tgn:1002712",
        "tgn:7012149",
        "tgn:7007159",
        "tgn:7029392"
    ],
    "tgn:id":2726034,
    "tgn:name":"Totoket Mountain",
    "tgn:placetype":[
        "aat:300008798"
    ]
},
  "bbox": [],
  "geometry": {"coordinates":[-72.7667,41.3833],"type":"Point"}
}