<<<<<<< HEAD
{
  "id": 2251328,
  "type": "Feature",
  "properties": {
    "tgn:hierarchy":[
        "tgn:2251328",
        "tgn:1000001",
        "tgn:7012149",
        "tgn:2000790",
        "tgn:7007255",
        "tgn:7029392"
    ],
    "tgn:id":2251328,
    "tgn:name":"Combs Spring",
    "tgn:placetype":[
        "aat:300008697"
    ]
},
  "bbox": [],
  "geometry": {"coordinates":[-89.1833,36.5167],"type":"Point"}
}
=======
{"geometry":{"type":"Point","coordinates":[-89.183300,36.516700]},"type":"Feature","properties":{"hierarchy":["tgn:2251328","tgn:1000001","tgn:7012149","tgn:2000790","tgn:7007255","tgn:7029392"],"placetype":["aat:300008697"],"id":2251328,"name:xx":"Combs Spring"}}
>>>>>>> 03f74aca74312dbeaf24d7e61306dd6a786dc3d0
