<<<<<<< HEAD
{
  "id": 7368816,
  "type": "Feature",
  "properties": {
    "tgn:hierarchy":[
        "tgn:7368816",
        "tgn:1000001",
        "tgn:1001937",
        "tgn:7005560",
        "tgn:7029392"
    ],
    "tgn:id":7368816,
    "tgn:name":"Holbox, Isla",
    "tgn:placetype":[
        "aat:300008791"
    ]
},
  "bbox": [],
  "geometry": {"coordinates":[-87.25,21.55],"type":"Point"}
}
=======
{"geometry":{"type":"Point","coordinates":[-87.250000,21.550000]},"type":"Feature","properties":{"hierarchy":["tgn:7368816","tgn:1000001","tgn:1001937","tgn:7005560","tgn:7029392"],"placetype":["aat:300008791"],"id":7368816,"name:xx":"Holbox, Isla"}}
>>>>>>> 03f74aca74312dbeaf24d7e61306dd6a786dc3d0
