{
  "id": 2458755,
  "type": "Feature",
  "properties": {
    "tgn:hierarchy":[
        "tgn:2458755",
        "tgn:1000001",
        "tgn:7012149",
        "tgn:2001056",
        "tgn:7007521",
        "tgn:7029392"
    ],
    "tgn:id":2458755,
    "tgn:name":"Little Ox Creek",
    "tgn:placetype":[
        "aat:300008706"
    ]
},
  "bbox": [],
  "geometry": {"coordinates":[-92.4833,46.1667],"type":"Point"}
}