{
  "id": 2562715,
  "type": "Feature",
  "properties": {
    "tgn:hierarchy":[
        "tgn:2562715",
        "tgn:1000001",
        "tgn:7012149",
        "tgn:7007157",
        "tgn:2000190",
        "tgn:7029392"
    ],
    "tgn:id":2562715,
    "tgn:name":"Oven Lid",
    "tgn:placetype":[
        "aat:300008798"
    ]
},
  "bbox": [],
  "geometry": {"coordinates":[-122.7833,40.0167],"type":"Point"}
}