{
  "id": 2556092,
  "type": "Feature",
  "properties": {
    "tgn:hierarchy":[
        "tgn:2556092",
        "tgn:1000001",
        "tgn:2000202",
        "tgn:7012149",
        "tgn:7007158",
        "tgn:7029392"
    ],
    "tgn:id":2556092,
    "tgn:name":"Ojito Creek",
    "tgn:placetype":[
        "aat:300008706"
    ]
},
  "bbox": [],
  "geometry": {"coordinates":[-106.2833,37.3333],"type":"Point"}
}