{
  "id": 2617467,
  "type": "Feature",
  "properties": {
    "tgn:hierarchy":[
        "tgn:2617467",
        "tgn:1000001",
        "tgn:2001415",
        "tgn:7012149",
        "tgn:7007526",
        "tgn:7029392"
    ],
    "tgn:id":2617467,
    "tgn:name":"Richmond James River Company Mine",
    "tgn:placetype":[
        "aat:300000390"
    ]
},
  "bbox": [],
  "geometry": {"coordinates":[-117.0667,39.4833],"type":"Point"}
}