{
  "id": 7559913,
  "type": "Feature",
  "properties": {
    "tgn:hierarchy":[
        "tgn:7559913",
        "tgn:1000004",
        "tgn:7000198",
        "tgn:7016722",
        "tgn:7029392"
    ],
    "tgn:id":7559913,
    "tgn:name:en":"Kakaria",
    "tgn:placetype":[
        "aat:300008347"
    ]
},
  "bbox": [],
  "geometry": {"coordinates":[79.272048,27.250062],"type":"Point"}
}