{
  "id": 7178202,
  "type": "Feature",
  "properties": {
    "tgn:hierarchy":[
        "tgn:7178202",
        "tgn:1000003",
        "tgn:7003678",
        "tgn:7000084",
        "tgn:7029392"
    ],
    "tgn:id":7178202,
    "tgn:name":"Hangarstein",
    "tgn:placetype":[
        "aat:300008777"
    ]
},
  "bbox": [],
  "geometry": {"coordinates":[9.366667,51.366667],"type":"Point"}
}