{
  "id": 2643948,
  "type": "Feature",
  "properties": {
    "tgn:hierarchy":[
        "tgn:2643948",
        "tgn:1000001",
        "tgn:7012149",
        "tgn:7007157",
        "tgn:1002608",
        "tgn:7029392"
    ],
    "tgn:id":2643948,
    "tgn:name":"Santa Anita Wash",
    "tgn:placetype":[
        "aat:300008699"
    ]
},
  "bbox": [],
  "geometry": {"coordinates":[-118.05,34.2167],"type":"Point"}
}