{
  "id": 2248408,
  "type": "Feature",
  "properties": {
    "tgn:hierarchy":[
        "tgn:2248408",
        "tgn:1000001",
        "tgn:2001415",
        "tgn:7012149",
        "tgn:7007526",
        "tgn:7029392"
    ],
    "tgn:id":2248408,
    "tgn:name":"Cold Spring",
    "tgn:placetype":[
        "aat:300008697"
    ]
},
  "bbox": [],
  "geometry": {"coordinates":[-117.0333,39.5333],"type":"Point"}
}