{
  "id": 7004898,
  "type": "Feature",
  "properties": {
    "tgn:hierarchy":[
        "tgn:7004898",
        "tgn:7003163",
        "tgn:1000003",
        "tgn:7009760",
        "tgn:1000080",
        "tgn:7029392"
    ],
    "tgn:id":7004898,
    "tgn:name":"Monticelli",
    "tgn:placetype":[
        "aat:300008347"
    ]
},
  "bbox": [],
  "geometry": {"coordinates":[11.254,43.768],"type":"Point"}
}