{
  "id": 1124628,
  "type": "Feature",
  "properties": {
    "tgn:hierarchy":[
        "tgn:1124628",
        "tgn:7005685",
        "tgn:1000001",
        "tgn:7005734",
        "tgn:7029392"
    ],
    "tgn:id":1124628,
    "tgn:name":"High Hill",
    "tgn:placetype":[
        "aat:300008707"
    ]
},
  "bbox": [],
  "geometry": {"coordinates":[-94.7167,55.8667],"type":"Point"}
}