<<<<<<< HEAD
{
  "id": 2257809,
  "type": "Feature",
  "properties": {
    "tgn:hierarchy":[
        "tgn:2257809",
        "tgn:1000001",
        "tgn:7012149",
        "tgn:2000183",
        "tgn:7007157",
        "tgn:7029392"
    ],
    "tgn:id":2257809,
    "tgn:name":"Corral Springs",
    "tgn:placetype":[
        "aat:300008697"
    ]
},
  "bbox": [],
  "geometry": {"coordinates":[-118.0167,37.2667],"type":"Point"}
}
=======
{"geometry":{"type":"Point","coordinates":[-118.016700,37.266700]},"type":"Feature","properties":{"hierarchy":["tgn:2257809","tgn:1000001","tgn:7012149","tgn:2000183","tgn:7007157","tgn:7029392"],"placetype":["aat:300008697"],"id":2257809,"name:xx":"Corral Springs"}}
>>>>>>> 03f74aca74312dbeaf24d7e61306dd6a786dc3d0
