{
  "id": 2257809,
  "type": "Feature",
  "properties": {
    "tgn:hierarchy":[
        "tgn:2257809",
        "tgn:1000001",
        "tgn:7012149",
        "tgn:2000183",
        "tgn:7007157",
        "tgn:7029392"
    ],
    "tgn:id":2257809,
    "tgn:name":"Corral Springs",
    "tgn:placetype":[
        "aat:300008697"
    ]
},
  "bbox": [],
  "geometry": {"coordinates":[-118.0167,37.2667],"type":"Point"}
}