{
  "id": 7121612,
  "type": "Feature",
  "properties": {
    "tgn:hierarchy":[
        "tgn:7121612",
        "tgn:7003669",
        "tgn:1000003",
        "tgn:7000084",
        "tgn:7029392"
    ],
    "tgn:id":7121612,
    "tgn:name":"Pirka",
    "tgn:placetype":[
        "aat:300008347"
    ]
},
  "bbox": [],
  "geometry": {"coordinates":[12.683333,48.533333],"type":"Point"}
}