{
  "id": 7441503,
  "type": "Feature",
  "properties": {
    "tgn:hierarchy":[
        "tgn:7441503",
        "tgn:1000727",
        "tgn:1000001",
        "tgn:7005493",
        "tgn:7029392"
    ],
    "tgn:id":7441503,
    "tgn:name":"Ixc\u00fan, Sitio Arqueol\u00f3gico",
    "tgn:placetype":[
        "aat:300008347",
        "aat:300387007",
        "aat:300000810"
    ]
},
  "bbox": [],
  "geometry": {"coordinates":[-89.406,16.542],"type":"Point"}
}