<<<<<<< HEAD
{
  "id": 2764340,
  "type": "Feature",
  "properties": {
    "tgn:hierarchy":[
        "tgn:2764340",
        "tgn:1000001",
        "tgn:7012149",
        "tgn:2001882",
        "tgn:7007825",
        "tgn:7029392"
    ],
    "tgn:id":2764340,
    "tgn:name":"Whetstone Branch",
    "tgn:placetype":[
        "aat:300008699"
    ]
},
  "bbox": [],
  "geometry": {"coordinates":[-81.6833,36.5833],"type":"Point"}
}
=======
{"geometry":{"type":"Point","coordinates":[-81.683300,36.583300]},"type":"Feature","properties":{"hierarchy":["tgn:2764340","tgn:1000001","tgn:7012149","tgn:2001882","tgn:7007825","tgn:7029392"],"placetype":["aat:300008699"],"id":2764340,"name:xx":"Whetstone Branch"}}
>>>>>>> 03f74aca74312dbeaf24d7e61306dd6a786dc3d0
