{
  "id": 2266723,
  "type": "Feature",
  "properties": {
    "tgn:hierarchy":[
        "tgn:2266723",
        "tgn:1000001",
        "tgn:7012149",
        "tgn:2001708",
        "tgn:7007708",
        "tgn:7029392"
    ],
    "tgn:id":2266723,
    "tgn:name":"Crescent Creek",
    "tgn:placetype":[
        "aat:300008706"
    ]
},
  "bbox": [],
  "geometry": {"coordinates":[-118.55,44.2667],"type":"Point"}
}