{
  "id": 7361895,
  "type": "Feature",
  "properties": {
    "tgn:hierarchy":[
        "tgn:7361895",
        "tgn:7005583",
        "tgn:1000001",
        "tgn:7005560",
        "tgn:7029392"
    ],
    "tgn:id":7361895,
    "tgn:name":"Rancho El Palito",
    "tgn:placetype":[
        "aat:300000241"
    ]
},
  "bbox": [],
  "geometry": {"coordinates":[-104.333333,25.983333],"type":"Point"}
}