{
  "id": 7405520,
  "type": "Feature",
  "properties": {
    "tgn:hierarchy":[
        "tgn:7405520",
        "tgn:7005585",
        "tgn:1000001",
        "tgn:7005560",
        "tgn:7029392"
    ],
    "tgn:id":7405520,
    "tgn:name":"Huerta Vieja",
    "tgn:placetype":[
        "aat:300008347"
    ]
},
  "bbox": [],
  "geometry": {"coordinates":[-100.183333,17.875],"type":"Point"}
}