{
  "id": 7289183,
  "type": "Feature",
  "properties": {
    "tgn:hierarchy":[
        "tgn:7289183",
        "tgn:1001695",
        "tgn:1000049",
        "tgn:1000002",
        "tgn:7029392"
    ],
    "tgn:id":7289183,
    "tgn:name":"La Gloria",
    "tgn:placetype":[
        "aat:300004792"
    ]
},
  "bbox": [],
  "geometry": {"coordinates":[-70.833333,-34.383333],"type":"Point"}
}