{
  "id": 2486721,
  "type": "Feature",
  "properties": {
    "tgn:hierarchy":[
        "tgn:2486721",
        "tgn:1002140",
        "tgn:1000001",
        "tgn:7012149",
        "tgn:7007520",
        "tgn:7029392"
    ],
    "tgn:id":2486721,
    "tgn:name":"Lee",
    "tgn:placetype":[
        "aat:300008347"
    ]
},
  "bbox": [],
  "geometry": {"coordinates":[-86.0833,42.45],"type":"Point"}
}