{
  "id": 2713534,
  "type": "Feature",
  "properties": {
    "tgn:hierarchy":[
        "tgn:2713534",
        "tgn:7016100",
        "tgn:1000001",
        "tgn:7012149",
        "tgn:7007516",
        "tgn:7029392"
    ],
    "tgn:id":2713534,
    "tgn:name":"Teague Point",
    "tgn:placetype":[
        "aat:300008850"
    ]
},
  "bbox": [],
  "geometry": {"coordinates":[-76.6667,38.5167],"type":"Point"}
}