{
  "id": 2293741,
  "type": "Feature",
  "properties": {
    "tgn:hierarchy":[
        "tgn:2293741",
        "tgn:1000001",
        "tgn:1002225",
        "tgn:7012149",
        "tgn:7007710",
        "tgn:7029392"
    ],
    "tgn:id":2293741,
    "tgn:name":"Dougherty",
    "tgn:placetype":[
        "aat:300008347"
    ]
},
  "bbox": [],
  "geometry": {"coordinates":[-78.45,40.6167],"type":"Point"}
}