<<<<<<< HEAD
{
  "id": 2251170,
  "type": "Feature",
  "properties": {
    "tgn:hierarchy":[
        "tgn:2251170",
        "tgn:1000001",
        "tgn:7012149",
        "tgn:2001458",
        "tgn:7007566",
        "tgn:7029392"
    ],
    "tgn:id":2251170,
    "tgn:name":"Comanche Canyon",
    "tgn:placetype":[
        "aat:300008761"
    ]
},
  "bbox": [],
  "geometry": {"coordinates":[-106.4,34.7333],"type":"Point"}
}
=======
{"geometry":{"type":"Point","coordinates":[-106.400000,34.733300]},"type":"Feature","properties":{"hierarchy":["tgn:2251170","tgn:1000001","tgn:7012149","tgn:2001458","tgn:7007566","tgn:7029392"],"placetype":["aat:300008761"],"id":2251170,"name:xx":"Comanche Canyon"}}
>>>>>>> 03f74aca74312dbeaf24d7e61306dd6a786dc3d0
