{
  "id": 7162946,
  "type": "Feature",
  "properties": {
    "tgn:hierarchy":[
        "tgn:7162946",
        "tgn:1000003",
        "tgn:7003687",
        "tgn:7000084",
        "tgn:7029392"
    ],
    "tgn:id":7162946,
    "tgn:name":"H\u00fctten",
    "tgn:placetype":[
        "aat:300008347"
    ]
},
  "bbox": [],
  "geometry": {"coordinates":[11.466667,52.35],"type":"Point"}
}