{
  "id": 7237918,
  "type": "Feature",
  "properties": {
    "tgn:hierarchy":[
        "tgn:7237918",
        "tgn:7007877",
        "tgn:1000003",
        "tgn:1000063",
        "tgn:4012014",
        "tgn:7029392"
    ],
    "tgn:id":7237918,
    "tgn:name":"Gourgues",
    "tgn:placetype":[
        "aat:300008347"
    ]
},
  "bbox": [],
  "geometry": {"coordinates":[3.526767,50.51774],"type":"Point"}
}