{
  "id": 7295398,
  "type": "Feature",
  "properties": {
    "tgn:hierarchy":[
        "tgn:7295398",
        "tgn:7002835",
        "tgn:7001158",
        "tgn:1000003",
        "tgn:1000095",
        "tgn:7029392"
    ],
    "tgn:id":7295398,
    "tgn:name":"Zarza de Don Beltr\u00e1n",
    "tgn:placetype":[
        "aat:300008347"
    ]
},
  "bbox": [],
  "geometry": {"coordinates":[-6.416667,41.166667],"type":"Point"}
}