{
  "id": 7378813,
  "type": "Feature",
  "properties": {
    "tgn:hierarchy":[
        "tgn:7378813",
        "tgn:7005581",
        "tgn:1000001",
        "tgn:7005560",
        "tgn:7029392"
    ],
    "tgn:id":7378813,
    "tgn:name":"Manzano, Arroyo del",
    "tgn:placetype":[
        "aat:300008699"
    ]
},
  "bbox": [],
  "geometry": {"coordinates":[-107.516667,28.983333],"type":"Point"}
}