{
  "id": 7447088,
  "type": "Feature",
  "properties": {
    "tgn:hierarchy":[
        "tgn:7447088",
        "tgn:7002444",
        "tgn:1000003",
        "tgn:7029508",
        "tgn:7008591",
        "tgn:7029392"
    ],
    "tgn:id":7447088,
    "tgn:name:en":"Skaw R\u00f6st",
    "tgn:placetype":[
        "aat:300386114"
    ]
},
  "bbox": [],
  "geometry": {"coordinates":[-0.75,60.833333],"type":"Point"}
}