{
  "id": 7385331,
  "type": "Feature",
  "properties": {
    "tgn:hierarchy":[
        "tgn:7385331",
        "tgn:1000001",
        "tgn:1001937",
        "tgn:7005560",
        "tgn:7029392"
    ],
    "tgn:id":7385331,
    "tgn:name":"Nizuc, R\u00edo de",
    "tgn:placetype":[
        "aat:300008679"
    ]
},
  "bbox": [],
  "geometry": {"coordinates":[-86.766667,21.083333],"type":"Point"}
}