{
  "id": 7307641,
  "type": "Feature",
  "properties": {
    "tgn:hierarchy":[
        "tgn:7307641",
        "tgn:7002758",
        "tgn:7002841",
        "tgn:1000003",
        "tgn:1000095",
        "tgn:7029392"
    ],
    "tgn:id":7307641,
    "tgn:name":"Luisiana, Arroyo de la",
    "tgn:placetype":[
        "aat:300266554",
        "aat:300008699"
    ]
},
  "bbox": [],
  "geometry": {"coordinates":[-5.283333,37.516667],"type":"Point"}
}