{
  "id": 7387567,
  "type": "Feature",
  "properties": {
    "tgn:hierarchy":[
        "tgn:7387567",
        "tgn:1000001",
        "tgn:7005590",
        "tgn:7005560",
        "tgn:7029392"
    ],
    "tgn:id":7387567,
    "tgn:name":"Parco",
    "tgn:placetype":[
        "aat:300007783"
    ]
},
  "bbox": [],
  "geometry": {"coordinates":[-101.666667,19.533333],"type":"Point"}
}