{
  "id": 2211488,
  "type": "Feature",
  "properties": {
    "tgn:hierarchy":[
        "tgn:2211488",
        "tgn:1000001",
        "tgn:2001016",
        "tgn:7012149",
        "tgn:7007521",
        "tgn:7029392"
    ],
    "tgn:id":2211488,
    "tgn:name":"Butterfield Lake",
    "tgn:placetype":[
        "aat:300008680"
    ]
},
  "bbox": [],
  "geometry": {"coordinates":[-94.0167,46.75],"type":"Point"}
}