<<<<<<< HEAD
{
  "id": 7052762,
  "type": "Feature",
  "properties": {
    "tgn:hierarchy":[
        "tgn:7052762",
        "tgn:1003471",
        "tgn:1000003",
        "tgn:7003240",
        "tgn:1000080",
        "tgn:7029392"
    ],
    "tgn:id":7052762,
    "tgn:name":"Monte Vidon Combatte",
    "tgn:placetype":[
        "aat:300008347"
    ]
},
  "bbox": [],
  "geometry": {"coordinates":[13.45,43.033333],"type":"Point"}
}
=======
{"geometry":{"type":"Point","coordinates":[13.450000,43.033333]},"type":"Feature","properties":{"hierarchy":["tgn:7052762","tgn:1003471","tgn:1000003","tgn:7003240","tgn:1000080","tgn:7029392"],"placetype":["aat:300008347"],"id":7052762,"name:xx":"Monte Vidon Combatte"}}
>>>>>>> 03f74aca74312dbeaf24d7e61306dd6a786dc3d0
