{
  "id": 7052762,
  "type": "Feature",
  "properties": {
    "tgn:hierarchy":[
        "tgn:7052762",
        "tgn:1003471",
        "tgn:1000003",
        "tgn:7003240",
        "tgn:1000080",
        "tgn:7029392"
    ],
    "tgn:id":7052762,
    "tgn:name":"Monte Vidon Combatte",
    "tgn:placetype":[
        "aat:300008347"
    ]
},
  "bbox": [],
  "geometry": {"coordinates":[13.45,43.033333],"type":"Point"}
}