{
  "id": 7562396,
  "type": "Feature",
  "properties": {
    "tgn:hierarchy":[
        "tgn:7562396",
        "tgn:1000004",
        "tgn:7000198",
        "tgn:7016722",
        "tgn:7029392"
    ],
    "tgn:id":7562396,
    "tgn:name:en":"Hadera",
    "tgn:placetype":[
        "aat:300008347"
    ]
},
  "bbox": [],
  "geometry": {"coordinates":[79.365431,27.025158],"type":"Point"}
}