{
  "id": 2134343,
  "type": "Feature",
  "properties": {
    "tgn:hierarchy":[
        "tgn:2134343",
        "tgn:1000001",
        "tgn:7012149",
        "tgn:2000339",
        "tgn:7007248",
        "tgn:7029392"
    ],
    "tgn:id":2134343,
    "tgn:name":"Anneewakee Lake",
    "tgn:placetype":[
        "aat:300006191"
    ]
},
  "bbox": [],
  "geometry": {"coordinates":[-84.7333,33.6667],"type":"Point"}
}