{
  "id": 2685568,
  "type": "Feature",
  "properties": {
    "tgn:hierarchy":[
        "tgn:2685568",
        "tgn:1000001",
        "tgn:7012149",
        "tgn:2002271",
        "tgn:7013961",
        "tgn:7029392"
    ],
    "tgn:id":2685568,
    "tgn:name":"Sprigg Hollow",
    "tgn:placetype":[
        "aat:300008761"
    ]
},
  "bbox": [],
  "geometry": {"coordinates":[-80.4167,38.8167],"type":"Point"}
}