{
  "id": 2308907,
  "type": "Feature",
  "properties": {
    "tgn:hierarchy":[
        "tgn:2308907",
        "tgn:1000001",
        "tgn:7012149",
        "tgn:2001315",
        "tgn:7007524",
        "tgn:7029392"
    ],
    "tgn:id":2308907,
    "tgn:name":"East Prong Reed Creek",
    "tgn:placetype":[
        "aat:300008706"
    ]
},
  "bbox": [],
  "geometry": {"coordinates":[-107.6667,46.0167],"type":"Point"}
}