{
  "id": 1063825,
  "type": "Feature",
  "properties": {
    "tgn:hierarchy":[
        "tgn:1063825",
        "tgn:1000003",
        "tgn:7024620",
        "tgn:1000097",
        "tgn:7029392"
    ],
    "tgn:id":1063825,
    "tgn:name":"Varg\u00f6n",
    "tgn:placetype":[
        "aat:300008347"
    ]
},
  "bbox": [],
  "geometry": {"coordinates":[12.3667,58.3667],"type":"Point"}
}