{
  "id": 2237707,
  "type": "Feature",
  "properties": {
    "tgn:hierarchy":[
        "tgn:2237707",
        "tgn:1000001",
        "tgn:7012149",
        "tgn:7014334",
        "tgn:7007919",
        "tgn:7029392"
    ],
    "tgn:id":2237707,
    "tgn:name":"Chinns Millpond",
    "tgn:placetype":[
        "aat:300006191"
    ]
},
  "bbox": [],
  "geometry": {"coordinates":[-76.5667,37.8167],"type":"Point"}
}