{
  "id": 2479023,
  "type": "Feature",
  "properties": {
    "tgn:hierarchy":[
        "tgn:2479023",
        "tgn:1000001",
        "tgn:7012149",
        "tgn:1002350",
        "tgn:7007157",
        "tgn:7029392"
    ],
    "tgn:id":2479023,
    "tgn:name":"Ladies Canyon",
    "tgn:placetype":[
        "aat:300008761"
    ]
},
  "bbox": [],
  "geometry": {"coordinates":[-120.8167,38.7667],"type":"Point"}
}