{
  "id": 7009978,
  "type": "Feature",
  "properties": {
    "tgn:hierarchy":[
        "tgn:7009978",
        "tgn:7010420",
        "tgn:1000003",
        "tgn:7002795",
        "tgn:1000095",
        "tgn:7029392"
    ],
    "tgn:id":7009978,
    "tgn:name":"Pozuelo de Alarc\u00f3n",
    "tgn:placetype":[
        "aat:300008347"
    ]
},
  "bbox": [],
  "geometry": {"coordinates":[-3.816667,40.433333],"type":"Point"}
}