{
  "id": 2192391,
  "type": "Feature",
  "properties": {
    "tgn:hierarchy":[
        "tgn:2192391",
        "tgn:1000001",
        "tgn:7012149",
        "tgn:2001709",
        "tgn:7007708",
        "tgn:7029392"
    ],
    "tgn:id":2192391,
    "tgn:name":"Brandon Spring",
    "tgn:placetype":[
        "aat:300008697"
    ]
},
  "bbox": [],
  "geometry": {"coordinates":[-118.8333,43.8833],"type":"Point"}
}