{
  "id": 2496789,
  "type": "Feature",
  "properties": {
    "tgn:hierarchy":[
        "tgn:2496789",
        "tgn:1000001",
        "tgn:7012149",
        "tgn:1003018",
        "tgn:7007919",
        "tgn:7029392"
    ],
    "tgn:id":2496789,
    "tgn:name":"Matthews Point",
    "tgn:placetype":[
        "aat:300008850"
    ]
},
  "bbox": [],
  "geometry": {"coordinates":[-76.7167,38.1167],"type":"Point"}
}