{
  "id": 7243962,
  "type": "Feature",
  "properties": {
    "tgn:hierarchy":[
        "tgn:7243962",
        "tgn:7007877",
        "tgn:1000003",
        "tgn:1000063",
        "tgn:4012014",
        "tgn:7029392"
    ],
    "tgn:id":7243962,
    "tgn:name":"Irchonwelz",
    "tgn:placetype":[
        "aat:300008347"
    ]
},
  "bbox": [],
  "geometry": {"coordinates":[3.757988,50.618408],"type":"Point"}
}