{
  "id": 2395674,
  "type": "Feature",
  "properties": {
    "tgn:hierarchy":[
        "tgn:2395674",
        "tgn:7006450",
        "tgn:1000001",
        "tgn:7012149",
        "tgn:2000082",
        "tgn:7029392"
    ],
    "tgn:id":2395674,
    "tgn:name":"Hollis Anchorage",
    "tgn:placetype":[
        "aat:300132316"
    ]
},
  "bbox": [],
  "geometry": {"coordinates":[-132.65,55.4667],"type":"Point"}
}