{
  "id": 7259912,
  "type": "Feature",
  "properties": {
    "tgn:hierarchy":[
        "tgn:7259912",
        "tgn:7003457",
        "tgn:1000003",
        "tgn:1000063",
        "tgn:7018236",
        "tgn:7029392"
    ],
    "tgn:id":7259912,
    "tgn:name":"Zwaanaarde",
    "tgn:placetype":[
        "aat:300008347"
    ]
},
  "bbox": [],
  "geometry": {"coordinates":[4.00924,51.156292],"type":"Point"}
}