{
  "id": 7468666,
  "type": "Feature",
  "properties": {
    "tgn:hierarchy":[
        "tgn:7468666",
        "tgn:1000004",
        "tgn:7467799",
        "tgn:1000141",
        "tgn:7029392"
    ],
    "tgn:id":7468666,
    "tgn:name":"Tanqian",
    "tgn:placetype":[
        "aat:300008347"
    ]
},
  "bbox": [],
  "geometry": {"coordinates":[120.500278,24.121389],"type":"Point"}
}