<<<<<<< HEAD
{
  "id": 2761416,
  "type": "Feature",
  "properties": {
    "tgn:hierarchy":[
        "tgn:2761416",
        "tgn:1000001",
        "tgn:7012149",
        "tgn:2001721",
        "tgn:7007708",
        "tgn:7029392"
    ],
    "tgn:id":2761416,
    "tgn:name":"West Mountain",
    "tgn:placetype":[
        "aat:300008798"
    ]
},
  "bbox": [],
  "geometry": {"coordinates":[-117.9667,45.5833],"type":"Point"}
}
=======
{"geometry":{"type":"Point","coordinates":[-117.966700,45.583300]},"type":"Feature","properties":{"hierarchy":["tgn:2761416","tgn:1000001","tgn:7012149","tgn:2001721","tgn:7007708","tgn:7029392"],"placetype":["aat:300008798"],"id":2761416,"name:xx":"West Mountain"}}
>>>>>>> 03f74aca74312dbeaf24d7e61306dd6a786dc3d0
