{
  "id": 2031722,
  "type": "Feature",
  "properties": {
    "tgn:hierarchy":[
        "tgn:2031722",
        "tgn:1000001",
        "tgn:7012149",
        "tgn:2000544",
        "tgn:7007252",
        "tgn:7029392"
    ],
    "tgn:id":2031722,
    "tgn:name":"Elliston",
    "tgn:placetype":[
        "aat:300008347",
        "aat:300387210"
    ]
},
  "bbox": [],
  "geometry": {"coordinates":[-86.9667,39.0167],"type":"Point"}
}