{
  "id": 2678322,
  "type": "Feature",
  "properties": {
    "tgn:hierarchy":[
        "tgn:2678322",
        "tgn:1000001",
        "tgn:7012149",
        "tgn:7007157",
        "tgn:2000188",
        "tgn:7029392"
    ],
    "tgn:id":2678322,
    "tgn:name":"South Fork Castle Creek",
    "tgn:placetype":[
        "aat:300008706"
    ]
},
  "bbox": [],
  "geometry": {"coordinates":[-122.4167,41.1167],"type":"Point"}
}