{
  "id": 7176362,
  "type": "Feature",
  "properties": {
    "tgn:hierarchy":[
        "tgn:7176362",
        "tgn:7000096",
        "tgn:1000003",
        "tgn:7000084",
        "tgn:7029392"
    ],
    "tgn:id":7176362,
    "tgn:name":"Gr\u00fcnow",
    "tgn:placetype":[
        "aat:300008347"
    ]
},
  "bbox": [],
  "geometry": {"coordinates":[14.066667,53.133333],"type":"Point"}
}