{
  "id": 2434146,
  "type": "Feature",
  "properties": {
    "tgn:hierarchy":[
        "tgn:2434146",
        "tgn:1000001",
        "tgn:7012149",
        "tgn:2001455",
        "tgn:7007566",
        "tgn:7029392"
    ],
    "tgn:id":2434146,
    "tgn:name":"Kelso Place",
    "tgn:placetype":[
        "aat:300008347"
    ]
},
  "bbox": [],
  "geometry": {"coordinates":[-107.75,33.05],"type":"Point"}
}