<<<<<<< HEAD
{
  "id": 7475901,
  "type": "Feature",
  "properties": {
    "tgn:hierarchy":[
        "tgn:7475901",
        "tgn:7488858",
        "tgn:1000004",
        "tgn:1000141",
        "tgn:7029392"
    ],
    "tgn:id":7475901,
    "tgn:name":"Sheliao Guozhong",
    "tgn:placetype":[
        "aat:300006495"
    ]
},
  "bbox": [],
  "geometry": {"coordinates":[120.720365,23.808565],"type":"Point"}
}
=======
{"geometry":{"type":"Point","coordinates":[120.720365,23.808565]},"type":"Feature","properties":{"hierarchy":["tgn:7475901","tgn:7488858","tgn:1000004","tgn:1000141","tgn:7029392"],"placetype":["aat:300006495"],"id":7475901,"name:xx":"Sheliao Guozhong"}}
>>>>>>> 03f74aca74312dbeaf24d7e61306dd6a786dc3d0
