{
  "id": 1114000,
  "type": "Feature",
  "properties": {
    "tgn:hierarchy":[
        "tgn:1114000",
        "tgn:1000004",
        "tgn:7011572",
        "tgn:7018214",
        "tgn:7002435",
        "tgn:7029392"
    ],
    "tgn:id":1114000,
    "tgn:name":"Vyborgskiy Zaliv",
    "tgn:placetype":[
        "aat:300132316"
    ]
},
  "bbox": [],
  "geometry": {"coordinates":[28.4167,60.5833],"type":"Point"}
}