{
  "id": 7245125,
  "type": "Feature",
  "properties": {
    "tgn:hierarchy":[
        "tgn:7245125",
        "tgn:7007877",
        "tgn:1000003",
        "tgn:1000063",
        "tgn:4012014",
        "tgn:7029392"
    ],
    "tgn:id":7245125,
    "tgn:name":"Barberie",
    "tgn:placetype":[
        "aat:300008347"
    ]
},
  "bbox": [],
  "geometry": {"coordinates":[3.556435,50.647408],"type":"Point"}
}