{
  "id": 7301182,
  "type": "Feature",
  "properties": {
    "tgn:hierarchy":[
        "tgn:7301182",
        "tgn:7002810",
        "tgn:7001158",
        "tgn:1000003",
        "tgn:1000095",
        "tgn:7029392"
    ],
    "tgn:id":7301182,
    "tgn:name":"Monta\u00f1ana",
    "tgn:placetype":[
        "aat:300008347"
    ]
},
  "bbox": [],
  "geometry": {"coordinates":[-3.017863,42.726634],"type":"Point"}
}