{
  "id": 1016284,
  "type": "Feature",
  "properties": {
    "tgn:hierarchy":[
        "tgn:1016284",
        "tgn:1001518",
        "tgn:1000001",
        "tgn:7005364",
        "tgn:7029392"
    ],
    "tgn:id":1016284,
    "tgn:name":"Santiago",
    "tgn:placetype":[
        "aat:300008347"
    ]
},
  "bbox": [],
  "geometry": {"coordinates":[-84.3167,9.85],"type":"Point"}
}