{
  "id": 7474046,
  "type": "Feature",
  "properties": {
    "tgn:hierarchy":[
        "tgn:7474046",
        "tgn:7487020",
        "tgn:1000004",
        "tgn:1000141",
        "tgn:7029392"
    ],
    "tgn:id":7474046,
    "tgn:name":"Cigaobei Shan",
    "tgn:placetype":[
        "aat:300008795"
    ]
},
  "bbox": [],
  "geometry": {"coordinates":[121.233333,24.416667],"type":"Point"}
}