{
  "id": 2321061,
  "type": "Feature",
  "properties": {
    "tgn:hierarchy":[
        "tgn:2321061",
        "tgn:1000001",
        "tgn:7012149",
        "tgn:2000369",
        "tgn:7007248",
        "tgn:7029392"
    ],
    "tgn:id":2321061,
    "tgn:name":"Factory Pond",
    "tgn:placetype":[
        "aat:300006191"
    ]
},
  "bbox": [],
  "geometry": {"coordinates":[-83.65,34.15],"type":"Point"}
}