{
  "id": 1064982,
  "type": "Feature",
  "properties": {
    "tgn:hierarchy":[
        "tgn:1064982",
        "tgn:7017306",
        "tgn:1000003",
        "tgn:7006663",
        "tgn:7029392"
    ],
    "tgn:id":1064982,
    "tgn:name":"Drni\u0161",
    "tgn:placetype":[
        "aat:300008347"
    ]
},
  "bbox": [],
  "geometry": {"coordinates":[16.1667,43.85],"type":"Point"}
}