{
  "id": 2119531,
  "type": "Feature",
  "properties": {
    "tgn:hierarchy":[
        "tgn:2119531",
        "tgn:1000001",
        "tgn:7012149",
        "tgn:2002274",
        "tgn:7013961",
        "tgn:7029392"
    ],
    "tgn:id":2119531,
    "tgn:name":"Paynesville",
    "tgn:placetype":[
        "aat:300008347"
    ]
},
  "bbox": [],
  "geometry": {"coordinates":[-81.8833,37.3167],"type":"Point"}
}