<<<<<<< HEAD
{
  "id": 2760892,
  "type": "Feature",
  "properties": {
    "tgn:hierarchy":[
        "tgn:2760892",
        "tgn:1000001",
        "tgn:7012149",
        "tgn:2001493",
        "tgn:7007709",
        "tgn:7029392"
    ],
    "tgn:id":2760892,
    "tgn:name":"West Hills",
    "tgn:placetype":[
        "aat:300008347"
    ]
},
  "bbox": [],
  "geometry": {"coordinates":[-77.55,35.8833],"type":"Point"}
}
=======
{"geometry":{"type":"Point","coordinates":[-77.550000,35.883300]},"type":"Feature","properties":{"hierarchy":["tgn:2760892","tgn:1000001","tgn:7012149","tgn:2001493","tgn:7007709","tgn:7029392"],"placetype":["aat:300008347"],"id":2760892,"name:xx":"West Hills"}}
>>>>>>> 03f74aca74312dbeaf24d7e61306dd6a786dc3d0
