{
  "id": 7034423,
  "type": "Feature",
  "properties": {
    "tgn:hierarchy":[
        "tgn:7034423",
        "tgn:1001641",
        "tgn:1000003",
        "tgn:7003121",
        "tgn:1000080",
        "tgn:7029392"
    ],
    "tgn:id":7034423,
    "tgn:name":"Marturedda, Punta",
    "tgn:placetype":[
        "aat:300008798"
    ]
},
  "bbox": [],
  "geometry": {"coordinates":[9.030833,39.051111],"type":"Point"}
}