{
  "id": 2519068,
  "type": "Feature",
  "properties": {
    "tgn:hierarchy":[
        "tgn:2519068",
        "tgn:7002659",
        "tgn:1000001",
        "tgn:7012149",
        "tgn:2000051",
        "tgn:7029392"
    ],
    "tgn:id":2519068,
    "tgn:name":"Moats Spring",
    "tgn:placetype":[
        "aat:300008697"
    ]
},
  "bbox": [],
  "geometry": {"coordinates":[-86.7667,34.3833],"type":"Point"}
}