{
  "id": 1106772,
  "type": "Feature",
  "properties": {
    "tgn:hierarchy":[
        "tgn:1106772",
        "tgn:7001242",
        "tgn:1000168",
        "tgn:7029392"
    ],
    "tgn:id":1106772,
    "tgn:name":"Tonkoui, Mont",
    "tgn:placetype":[
        "aat:300008795"
    ]
},
  "bbox": [],
  "geometry": {"coordinates":[-7.65,7.45],"type":"Point"}
}