<<<<<<< HEAD
{
  "id": 7488704,
  "type": "Feature",
  "properties": {
    "tgn:hierarchy":[
        "tgn:7488704",
        "tgn:7488858",
        "tgn:1000004",
        "tgn:1000141",
        "tgn:7029392"
    ],
    "tgn:id":7488704,
    "tgn:name":"Kuai Shan",
    "tgn:placetype":[
        "aat:300008798"
    ]
},
  "bbox": [],
  "geometry": {"coordinates":[121.071389,24.15],"type":"Point"}
}
=======
{"geometry":{"type":"Point","coordinates":[121.071389,24.150000]},"type":"Feature","properties":{"hierarchy":["tgn:7488704","tgn:7488858","tgn:1000004","tgn:1000141","tgn:7029392"],"placetype":["aat:300008798"],"id":7488704,"name:xx":"Kuai Shan"}}
>>>>>>> 03f74aca74312dbeaf24d7e61306dd6a786dc3d0
