{
  "id": 1096171,
  "type": "Feature",
  "properties": {
    "tgn:hierarchy":[
        "tgn:1096171",
        "tgn:7000490",
        "tgn:1000006",
        "tgn:7001828",
        "tgn:7001923",
        "tgn:7029392"
    ],
    "tgn:id":1096171,
    "tgn:name":"Balmain",
    "tgn:placetype":[
        "aat:300008347"
    ]
},
  "bbox": [],
  "geometry": {"coordinates":[151.1833,-33.8667],"type":"Point"}
}