{
  "id": 2323847,
  "type": "Feature",
  "properties": {
    "tgn:hierarchy":[
        "tgn:2323847",
        "tgn:1000001",
        "tgn:7012149",
        "tgn:7007256",
        "tgn:7029392"
    ],
    "tgn:id":2323847,
    "tgn:name":"Fausse Pointe, Lake",
    "tgn:placetype":[
        "aat:300008680"
    ]
},
  "bbox": [],
  "geometry": {"coordinates":[-91.5833,29.9667],"type":"Point"}
}