{
  "id": 2555629,
  "type": "Feature",
  "properties": {
    "tgn:hierarchy":[
        "tgn:2555629",
        "tgn:1000001",
        "tgn:7012149",
        "tgn:2000985",
        "tgn:7007520",
        "tgn:7029392"
    ],
    "tgn:id":2555629,
    "tgn:name":"Ogemaw, Lake",
    "tgn:placetype":[
        "aat:300006191"
    ]
},
  "bbox": [],
  "geometry": {"coordinates":[-84.05,44.2333],"type":"Point"}
}