{
  "id": 7189932,
  "type": "Feature",
  "properties": {
    "tgn:hierarchy":[
        "tgn:7189932",
        "tgn:7003669",
        "tgn:1000003",
        "tgn:7000084",
        "tgn:7029392"
    ],
    "tgn:id":7189932,
    "tgn:name":"Schlo\u00df Elmau",
    "tgn:placetype":[
        "aat:300006891"
    ]
},
  "bbox": [],
  "geometry": {"coordinates":[11.183333,47.466667],"type":"Point"}
}