{
  "id": 1090889,
  "type": "Feature",
  "properties": {
    "tgn:hierarchy":[
        "tgn:1090889",
        "tgn:1001103",
        "tgn:7001242",
        "tgn:1000173",
        "tgn:7029392"
    ],
    "tgn:id":1090889,
    "tgn:name":"Fenoarivo",
    "tgn:placetype":[
        "aat:300008347"
    ]
},
  "bbox": [],
  "geometry": {"coordinates":[46.5333,-18.4167],"type":"Point"}
}