<<<<<<< HEAD
{
  "id": 2767574,
  "type": "Feature",
  "properties": {
    "tgn:hierarchy":[
        "tgn:2767574",
        "tgn:1000001",
        "tgn:7012149",
        "tgn:2001821",
        "tgn:7007713",
        "tgn:7029392"
    ],
    "tgn:id":2767574,
    "tgn:name":"White Whale Mine",
    "tgn:placetype":[
        "aat:300000390"
    ]
},
  "bbox": [],
  "geometry": {"coordinates":[-103.55,43.9167],"type":"Point"}
}
=======
{"geometry":{"type":"Point","coordinates":[-103.550000,43.916700]},"type":"Feature","properties":{"hierarchy":["tgn:2767574","tgn:1000001","tgn:7012149","tgn:2001821","tgn:7007713","tgn:7029392"],"placetype":["aat:300000390"],"id":2767574,"name:xx":"White Whale Mine"}}
>>>>>>> 03f74aca74312dbeaf24d7e61306dd6a786dc3d0
