{
  "id": 7556193,
  "type": "Feature",
  "properties": {
    "tgn:hierarchy":[
        "tgn:7556193",
        "tgn:1000004",
        "tgn:7000198",
        "tgn:1001894",
        "tgn:7029392"
    ],
    "tgn:id":7556193,
    "tgn:name:en":"R\u0101jnagar",
    "tgn:placetype":[
        "aat:300008347"
    ]
},
  "bbox": [],
  "geometry": {"coordinates":[79.912822,24.890374],"type":"Point"}
}