{
  "id": 7002205,
  "type": "Feature",
  "properties": {
    "tgn:hierarchy":[
        "tgn:7002205",
        "tgn:1000004",
        "tgn:7001282",
        "tgn:7000231",
        "tgn:7029392"
    ],
    "tgn:id":7002205,
    "tgn:name":"Takht-e Jamsh\u012bd",
    "tgn:placetype":[
        "aat:300008347",
        "aat:300000810",
        "aat:300167671",
        "aat:300387218",
        "aat:300343603",
        "aat:300263063"
    ]
},
  "bbox": [],
  "geometry": {"coordinates":[52.8833,29.9333],"type":"Point"}
}