{
  "id": 2075183,
  "type": "Feature",
  "properties": {
    "tgn:hierarchy":[
        "tgn:2075183",
        "tgn:1000001",
        "tgn:7012149",
        "tgn:2001524",
        "tgn:7007709",
        "tgn:7029392"
    ],
    "tgn:id":2075183,
    "tgn:name":"Huffmantown",
    "tgn:placetype":[
        "aat:300008347",
        "aat:300387210"
    ]
},
  "bbox": [],
  "geometry": {"coordinates":[-77.55,34.95],"type":"Point"}
}