{
  "id": 2678074,
  "type": "Feature",
  "properties": {
    "tgn:hierarchy":[
        "tgn:2678074",
        "tgn:1000001",
        "tgn:7012149",
        "tgn:2002186",
        "tgn:7007919",
        "tgn:7029392"
    ],
    "tgn:id":2678074,
    "tgn:name":"South Fork Bennetts Run",
    "tgn:placetype":[
        "aat:300008699"
    ]
},
  "bbox": [],
  "geometry": {"coordinates":[-79.35,37.65],"type":"Point"}
}