{
  "id": 2167244,
  "type": "Feature",
  "properties": {
    "tgn:hierarchy":[
        "tgn:2167244",
        "tgn:1000001",
        "tgn:7016172",
        "tgn:7012149",
        "tgn:2000177",
        "tgn:7029392"
    ],
    "tgn:id":2167244,
    "tgn:name":"Big Clear Lake",
    "tgn:placetype":[
        "aat:300008680"
    ]
},
  "bbox": [],
  "geometry": {"coordinates":[-91.45,35.2667],"type":"Point"}
}