<<<<<<< HEAD
{
  "id": 2153067,
  "type": "Feature",
  "properties": {
    "tgn:hierarchy":[
        "tgn:2153067",
        "tgn:1000001",
        "tgn:7012149",
        "tgn:7018871",
        "tgn:7007920",
        "tgn:7029392"
    ],
    "tgn:id":2153067,
    "tgn:name":"Beacon Hill Reservoir",
    "tgn:placetype":[
        "aat:300006191"
    ]
},
  "bbox": [],
  "geometry": {"coordinates":[-122.3,47.5667],"type":"Point"}
}
=======
{"geometry":{"type":"Point","coordinates":[-122.300000,47.566700]},"type":"Feature","properties":{"hierarchy":["tgn:2153067","tgn:1000001","tgn:7012149","tgn:7018871","tgn:7007920","tgn:7029392"],"placetype":["aat:300006191"],"id":2153067,"name:xx":"Beacon Hill Reservoir"}}
>>>>>>> 03f74aca74312dbeaf24d7e61306dd6a786dc3d0
