{
  "id": 7287474,
  "type": "Feature",
  "properties": {
    "tgn:hierarchy":[
        "tgn:7287474",
        "tgn:1001768",
        "tgn:1000049",
        "tgn:1000002",
        "tgn:7029392"
    ],
    "tgn:id":7287474,
    "tgn:name":"G\u00e1lvez, Cord\u00f3n de",
    "tgn:placetype":[
        "aat:300266640"
    ]
},
  "bbox": [],
  "geometry": {"coordinates":[-70.766667,-32.283333],"type":"Point"}
}