{
  "id": 2543311,
  "type": "Feature",
  "properties": {
    "tgn:hierarchy":[
        "tgn:2543311",
        "tgn:1000001",
        "tgn:1002714",
        "tgn:7012149",
        "tgn:7007159",
        "tgn:7029392"
    ],
    "tgn:id":2543311,
    "tgn:name":"Norman Brook",
    "tgn:placetype":[
        "aat:300008699"
    ]
},
  "bbox": [],
  "geometry": {"coordinates":[-71.95,41.5833],"type":"Point"}
}