{
  "id": 2361228,
  "type": "Feature",
  "properties": {
    "tgn:hierarchy":[
        "tgn:2361228",
        "tgn:1000001",
        "tgn:7012149",
        "tgn:7007157",
        "tgn:1002857",
        "tgn:7029392"
    ],
    "tgn:id":2361228,
    "tgn:name":"Gravel Hills",
    "tgn:placetype":[
        "aat:300386831"
    ]
},
  "bbox": [],
  "geometry": {"coordinates":[-117.3333,35.1833],"type":"Point"}
}