{
  "id": 1014570,
  "type": "Feature",
  "properties": {
    "tgn:hierarchy":[
        "tgn:1014570",
        "tgn:7005685",
        "tgn:1000001",
        "tgn:7013154",
        "tgn:7029392"
    ],
    "tgn:id":1014570,
    "tgn:name":"Ayton",
    "tgn:placetype":[
        "aat:300008347"
    ]
},
  "bbox": [],
  "geometry": {"coordinates":[-80.9333,44.05],"type":"Point"}
}