{
  "id": 2069214,
  "type": "Feature",
  "properties": {
    "tgn:hierarchy":[
        "tgn:2069214",
        "tgn:1000001",
        "tgn:7012149",
        "tgn:1002944",
        "tgn:7007568",
        "tgn:7029392"
    ],
    "tgn:id":2069214,
    "tgn:name":"Flemingville",
    "tgn:placetype":[
        "aat:300008347",
        "aat:300387210"
    ]
},
  "bbox": [],
  "geometry": {"coordinates":[-76.2333,42.15],"type":"Point"}
}