<<<<<<< HEAD
{
  "id": 7172133,
  "type": "Feature",
  "properties": {
    "tgn:hierarchy":[
        "tgn:7172133",
        "tgn:1000003",
        "tgn:7003676",
        "tgn:7000084",
        "tgn:7029392"
    ],
    "tgn:id":7172133,
    "tgn:name":"Helmser Busch",
    "tgn:placetype":[
        "aat:300008863"
    ]
},
  "bbox": [],
  "geometry": {"coordinates":[9.5,52.883333],"type":"Point"}
}
=======
{"geometry":{"type":"Point","coordinates":[9.500000,52.883333]},"type":"Feature","properties":{"hierarchy":["tgn:7172133","tgn:1000003","tgn:7003676","tgn:7000084","tgn:7029392"],"placetype":["aat:300008863"],"id":7172133,"name:xx":"Helmser Busch"}}
>>>>>>> 03f74aca74312dbeaf24d7e61306dd6a786dc3d0
