{
  "id": 2263928,
  "type": "Feature",
  "properties": {
    "tgn:hierarchy":[
        "tgn:2263928",
        "tgn:1000001",
        "tgn:7012149",
        "tgn:2001715",
        "tgn:7007708",
        "tgn:7029392"
    ],
    "tgn:id":2263928,
    "tgn:name":"Coyote Hole Reservoir",
    "tgn:placetype":[
        "aat:300006191"
    ]
},
  "bbox": [],
  "geometry": {"coordinates":[-120.65,43.4833],"type":"Point"}
}