{
  "id": 7308683,
  "type": "Feature",
  "properties": {
    "tgn:hierarchy":[
        "tgn:7308683",
        "tgn:1001768",
        "tgn:1000049",
        "tgn:1000002",
        "tgn:7029392"
    ],
    "tgn:id":7308683,
    "tgn:name":"Lo Valdivia",
    "tgn:placetype":[
        "aat:300387200"
    ]
},
  "bbox": [],
  "geometry": {"coordinates":[-70.716667,-32.85],"type":"Point"}
}