{
  "id": 2662838,
  "type": "Feature",
  "properties": {
    "tgn:hierarchy":[
        "tgn:2662838",
        "tgn:1000001",
        "tgn:2001410",
        "tgn:7012149",
        "tgn:7007526",
        "tgn:7029392"
    ],
    "tgn:id":2662838,
    "tgn:name":"Silica Dome",
    "tgn:placetype":[
        "aat:300008798"
    ]
},
  "bbox": [],
  "geometry": {"coordinates":[-114.4833,36.45],"type":"Point"}
}