{
  "id": 7486810,
  "type": "Feature",
  "properties": {
    "tgn:hierarchy":[
        "tgn:7486810",
        "tgn:7488858",
        "tgn:1000004",
        "tgn:1000141",
        "tgn:7029392"
    ],
    "tgn:id":7486810,
    "tgn:name":"Lianshengkeng",
    "tgn:placetype":[
        "aat:300008347"
    ]
},
  "bbox": [],
  "geometry": {"coordinates":[120.863881,23.920218],"type":"Point"}
}