{
  "id": 7493736,
  "type": "Feature",
  "properties": {
    "tgn:hierarchy":[
        "tgn:7493736",
        "tgn:7468018",
        "tgn:1000004",
        "tgn:1000141",
        "tgn:7029392"
    ],
    "tgn:id":7493736,
    "tgn:name":"Yindou",
    "tgn:placetype":[
        "aat:300008791"
    ]
},
  "bbox": [],
  "geometry": {"coordinates":[120.557565,23.260206],"type":"Point"}
}