<<<<<<< HEAD
{
  "id": 2155644,
  "type": "Feature",
  "properties": {
    "tgn:hierarchy":[
        "tgn:2155644",
        "tgn:1000001",
        "tgn:7012149",
        "tgn:2001714",
        "tgn:7007708",
        "tgn:7029392"
    ],
    "tgn:id":2155644,
    "tgn:name":"Bear Spring",
    "tgn:placetype":[
        "aat:300008697"
    ]
},
  "bbox": [],
  "geometry": {"coordinates":[-121.3667,43.0833],"type":"Point"}
}
=======
{"geometry":{"type":"Point","coordinates":[-121.366700,43.083300]},"type":"Feature","properties":{"hierarchy":["tgn:2155644","tgn:1000001","tgn:7012149","tgn:2001714","tgn:7007708","tgn:7029392"],"placetype":["aat:300008697"],"id":2155644,"name:xx":"Bear Spring"}}
>>>>>>> 03f74aca74312dbeaf24d7e61306dd6a786dc3d0
