{
  "id": 7390452,
  "type": "Feature",
  "properties": {
    "tgn:hierarchy":[
        "tgn:7390452",
        "tgn:1001853",
        "tgn:1000001",
        "tgn:7005560",
        "tgn:7029392"
    ],
    "tgn:id":7390452,
    "tgn:name":"Rancho La Asunci\u00f3n",
    "tgn:placetype":[
        "aat:300008347"
    ]
},
  "bbox": [],
  "geometry": {"coordinates":[-100.783333,28.733333],"type":"Point"}
}