{
  "id": 2494684,
  "type": "Feature",
  "properties": {
    "tgn:hierarchy":[
        "tgn:2494684",
        "tgn:1000001",
        "tgn:2000950",
        "tgn:7012149",
        "tgn:7007520",
        "tgn:7029392"
    ],
    "tgn:id":2494684,
    "tgn:name":"Martin Point",
    "tgn:placetype":[
        "aat:300008850"
    ]
},
  "bbox": [],
  "geometry": {"coordinates":[-85.4833,45.6167],"type":"Point"}
}