{
  "id": 7035272,
  "type": "Feature",
  "properties": {
    "tgn:hierarchy":[
        "tgn:7035272",
        "tgn:1003506",
        "tgn:1000003",
        "tgn:7002993",
        "tgn:1000080",
        "tgn:7029392"
    ],
    "tgn:id":7035272,
    "tgn:name":"Zeglianutto",
    "tgn:placetype":[
        "aat:300008347"
    ]
},
  "bbox": [],
  "geometry": {"coordinates":[13.156667,46.199444],"type":"Point"}
}