<<<<<<< HEAD
{
  "id": 7050786,
  "type": "Feature",
  "properties": {
    "tgn:hierarchy":[
        "tgn:7050786",
        "tgn:1003510",
        "tgn:1000003",
        "tgn:7003120",
        "tgn:1000080",
        "tgn:7029392"
    ],
    "tgn:id":7050786,
    "tgn:name":"Masserano",
    "tgn:placetype":[
        "aat:300008347"
    ]
},
  "bbox": [],
  "geometry": {"coordinates":[8.2,45.583333],"type":"Point"}
}
=======
{"geometry":{"type":"Point","coordinates":[8.200000,45.583333]},"type":"Feature","properties":{"hierarchy":["tgn:7050786","tgn:1003510","tgn:1000003","tgn:7003120","tgn:1000080","tgn:7029392"],"placetype":["aat:300008347"],"id":7050786,"name:xx":"Masserano"}}
>>>>>>> 03f74aca74312dbeaf24d7e61306dd6a786dc3d0
