{
  "id": 7332242,
  "type": "Feature",
  "properties": {
    "tgn:hierarchy":[
        "tgn:7332242",
        "tgn:7002808",
        "tgn:7030216",
        "tgn:1000003",
        "tgn:1000095",
        "tgn:7029392"
    ],
    "tgn:id":7332242,
    "tgn:name":"La Granada",
    "tgn:placetype":[
        "aat:300008347"
    ]
},
  "bbox": [],
  "geometry": {"coordinates":[1.719023,41.37816],"type":"Point"}
}