{
  "id": 2099722,
  "type": "Feature",
  "properties": {
    "tgn:hierarchy":[
        "tgn:2099722",
        "tgn:1000001",
        "tgn:7012149",
        "tgn:2001906",
        "tgn:7007825",
        "tgn:7029392"
    ],
    "tgn:id":2099722,
    "tgn:name":"Isabella",
    "tgn:placetype":[
        "aat:300008347"
    ]
},
  "bbox": [],
  "geometry": {"coordinates":[-84.35,35.0167],"type":"Point"}
}