{
  "id": 2569946,
  "type": "Feature",
  "properties": {
    "tgn:hierarchy":[
        "tgn:2569946",
        "tgn:1000001",
        "tgn:7012149",
        "tgn:1002742",
        "tgn:7007920",
        "tgn:7029392"
    ],
    "tgn:id":2569946,
    "tgn:name":"Pasayten Wilderness",
    "tgn:placetype":[
        "aat:300055621"
    ]
},
  "bbox": [],
  "geometry": {"coordinates":[-120.4333,48.7167],"type":"Point"}
}