{
  "id": 2278354,
  "type": "Feature",
  "properties": {
    "tgn:hierarchy":[
        "tgn:2278354",
        "tgn:1000001",
        "tgn:7012149",
        "tgn:2001255",
        "tgn:7007523",
        "tgn:7029392"
    ],
    "tgn:id":2278354,
    "tgn:name":"DeCelis Branch",
    "tgn:placetype":[
        "aat:300008699"
    ]
},
  "bbox": [],
  "geometry": {"coordinates":[-90.2167,37.0667],"type":"Point"}
}