{
  "id": 7077449,
  "type": "Feature",
  "properties": {
    "tgn:hierarchy":[
        "tgn:7077449",
        "tgn:1000003",
        "tgn:7003688",
        "tgn:7000084",
        "tgn:7029392"
    ],
    "tgn:id":7077449,
    "tgn:name":"Schulensee",
    "tgn:placetype":[
        "aat:300008347"
    ]
},
  "bbox": [],
  "geometry": {"coordinates":[10.066667,54.283333],"type":"Point"}
}