{
  "id": 2150803,
  "type": "Feature",
  "properties": {
    "tgn:hierarchy":[
        "tgn:2150803",
        "tgn:1000001",
        "tgn:7012149",
        "tgn:2000965",
        "tgn:7007520",
        "tgn:7029392"
    ],
    "tgn:id":2150803,
    "tgn:name":"Bass Lake",
    "tgn:placetype":[
        "aat:300008680"
    ]
},
  "bbox": [],
  "geometry": {"coordinates":[-83.65,44.3333],"type":"Point"}
}