{
  "id": 7166184,
  "type": "Feature",
  "properties": {
    "tgn:hierarchy":[
        "tgn:7166184",
        "tgn:1000003",
        "tgn:7000094",
        "tgn:7000084",
        "tgn:7029392"
    ],
    "tgn:id":7166184,
    "tgn:name":"Heidekrug",
    "tgn:placetype":[
        "aat:300008347"
    ]
},
  "bbox": [],
  "geometry": {"coordinates":[10.65,53.433333],"type":"Point"}
}