{
  "id": 2224407,
  "type": "Feature",
  "properties": {
    "tgn:hierarchy":[
        "tgn:2224407",
        "tgn:1000001",
        "tgn:7012149",
        "tgn:7014510",
        "tgn:7007920",
        "tgn:7029392"
    ],
    "tgn:id":2224407,
    "tgn:name":"Cascade Peak",
    "tgn:placetype":[
        "aat:300008798"
    ]
},
  "bbox": [],
  "geometry": {"coordinates":[-121.0667,48.45],"type":"Point"}
}