{
  "id": 2399397,
  "type": "Feature",
  "properties": {
    "tgn:hierarchy":[
        "tgn:2399397",
        "tgn:7013388",
        "tgn:1000001",
        "tgn:7012149",
        "tgn:7007517",
        "tgn:7029392"
    ],
    "tgn:id":2399397,
    "tgn:name":"Horn Pond",
    "tgn:placetype":[
        "aat:300008680"
    ]
},
  "bbox": [],
  "geometry": {"coordinates":[-73.0167,42.2833],"type":"Point"}
}