<<<<<<< HEAD
{
  "id": 2155827,
  "type": "Feature",
  "properties": {
    "tgn:hierarchy":[
        "tgn:2155827",
        "tgn:1000001",
        "tgn:1002219",
        "tgn:7012149",
        "tgn:7007157",
        "tgn:7029392"
    ],
    "tgn:id":2155827,
    "tgn:name":"Bear Trap Basin",
    "tgn:placetype":[
        "aat:300386845"
    ]
},
  "bbox": [],
  "geometry": {"coordinates":[-120.0833,38.4667],"type":"Point"}
}
=======
{"geometry":{"type":"Point","coordinates":[-120.083300,38.466700]},"type":"Feature","properties":{"hierarchy":["tgn:2155827","tgn:1000001","tgn:1002219","tgn:7012149","tgn:7007157","tgn:7029392"],"placetype":["aat:300386845"],"id":2155827,"name:xx":"Bear Trap Basin"}}
>>>>>>> 03f74aca74312dbeaf24d7e61306dd6a786dc3d0
