<<<<<<< HEAD
{
  "id": 2407525,
  "type": "Feature",
  "properties": {
    "tgn:hierarchy":[
        "tgn:2407525",
        "tgn:1000001",
        "tgn:7012149",
        "tgn:2001274",
        "tgn:7007524",
        "tgn:7029392"
    ],
    "tgn:id":2407525,
    "tgn:name":"Huntsberger Lake",
    "tgn:placetype":[
        "aat:300008680"
    ]
},
  "bbox": [],
  "geometry": {"coordinates":[-114.6667,48.8],"type":"Point"}
}
=======
{"geometry":{"type":"Point","coordinates":[-114.666700,48.800000]},"type":"Feature","properties":{"hierarchy":["tgn:2407525","tgn:1000001","tgn:7012149","tgn:2001274","tgn:7007524","tgn:7029392"],"placetype":["aat:300008680"],"id":2407525,"name:xx":"Huntsberger Lake"}}
>>>>>>> 03f74aca74312dbeaf24d7e61306dd6a786dc3d0
