{
  "id": 2188205,
  "type": "Feature",
  "properties": {
    "tgn:hierarchy":[
        "tgn:2188205",
        "tgn:1000001",
        "tgn:7012149",
        "tgn:2001455",
        "tgn:7007566",
        "tgn:7029392"
    ],
    "tgn:id":2188205,
    "tgn:name":"Bosque Canyon",
    "tgn:placetype":[
        "aat:300008761"
    ]
},
  "bbox": [],
  "geometry": {"coordinates":[-106.6833,23.1333],"type":"Point"}
}