{
  "id": 1078943,
  "type": "Feature",
  "properties": {
    "tgn:hierarchy":[
        "tgn:1078943",
        "tgn:1000004",
        "tgn:1001134",
        "tgn:7000231",
        "tgn:7029392"
    ],
    "tgn:id":1078943,
    "tgn:name":"\u1e62a\u1e25neh",
    "tgn:placetype":[
        "aat:300008347"
    ]
},
  "bbox": [],
  "geometry": {"coordinates":[47.6667,34.4833],"type":"Point"}
}