{
  "id": 7305755,
  "type": "Feature",
  "properties": {
    "tgn:hierarchy":[
        "tgn:7305755",
        "tgn:7002820",
        "tgn:7030216",
        "tgn:1000003",
        "tgn:1000095",
        "tgn:7029392"
    ],
    "tgn:id":7305755,
    "tgn:name":"Mayor, R\u00edo",
    "tgn:placetype":[
        "aat:300008699"
    ]
},
  "bbox": [],
  "geometry": {"coordinates":[2.421809,41.967069],"type":"Point"}
}