{
  "id": 4011785,
  "type": "Feature",
  "properties": {
    "tgn:hierarchy":[
        "tgn:4011785",
        "tgn:7002871",
        "tgn:1000003",
        "tgn:1000070",
        "tgn:7029392"
    ],
    "tgn:id":4011785,
    "tgn:name":"Vieille Brioude",
    "tgn:placetype":[
        "aat:300008347"
    ]
},
  "bbox": [],
  "geometry": {"coordinates":[3.3833,45.2667],"type":"Point"}
}