{
  "id": 2714965,
  "type": "Feature",
  "properties": {
    "tgn:hierarchy":[
        "tgn:2714965",
        "tgn:1000001",
        "tgn:1002666",
        "tgn:7012149",
        "tgn:7007565",
        "tgn:7029392"
    ],
    "tgn:id":2714965,
    "tgn:name":"Tennent Brook",
    "tgn:placetype":[
        "aat:300008699"
    ]
},
  "bbox": [],
  "geometry": {"coordinates":[-74.2667,40.4167],"type":"Point"}
}