{
  "id": 2424766,
  "type": "Feature",
  "properties": {
    "tgn:hierarchy":[
        "tgn:2424766",
        "tgn:1000001",
        "tgn:7012149",
        "tgn:2000959",
        "tgn:7007520",
        "tgn:7029392"
    ],
    "tgn:id":2424766,
    "tgn:name":"Johnson Drain",
    "tgn:placetype":[
        "aat:300006075"
    ]
},
  "bbox": [],
  "geometry": {"coordinates":[-84.3667,43.9833],"type":"Point"}
}