{
  "id": 7311873,
  "type": "Feature",
  "properties": {
    "tgn:hierarchy":[
        "tgn:7311873",
        "tgn:1001768",
        "tgn:1000049",
        "tgn:1000002",
        "tgn:7029392"
    ],
    "tgn:id":7311873,
    "tgn:name":"Las Lomas",
    "tgn:placetype":[
        "aat:300387200"
    ]
},
  "bbox": [],
  "geometry": {"coordinates":[-71.433333,-33.466667],"type":"Point"}
}