{
  "id": 7580245,
  "type": "Feature",
  "properties": {
    "tgn:hierarchy":[
        "tgn:7580245",
        "tgn:1000004",
        "tgn:7000198",
        "tgn:7000799",
        "tgn:7029392"
    ],
    "tgn:id":7580245,
    "tgn:name:en":"Stakna",
    "tgn:placetype":[
        "aat:300008347"
    ]
},
  "bbox": [],
  "geometry": {"coordinates":[77.692615,34.006095],"type":"Point"}
}