{
  "id": 2327869,
  "type": "Feature",
  "properties": {
    "tgn:hierarchy":[
        "tgn:2327869",
        "tgn:1000001",
        "tgn:7012149",
        "tgn:7014589",
        "tgn:7007515",
        "tgn:7029392"
    ],
    "tgn:id":2327869,
    "tgn:name":"Fish Island",
    "tgn:placetype":[
        "aat:300008791"
    ]
},
  "bbox": [],
  "geometry": {"coordinates":[-67.9167,44.4667],"type":"Point"}
}