{
  "id": 2306934,
  "type": "Feature",
  "properties": {
    "tgn:hierarchy":[
        "tgn:2306934",
        "tgn:1000001",
        "tgn:7012149",
        "tgn:7007251",
        "tgn:7029392"
    ],
    "tgn:id":2306934,
    "tgn:name":"East Fork La Moine River",
    "tgn:placetype":[
        "aat:300008707"
    ]
},
  "bbox": [],
  "geometry": {"coordinates":[-90.7333,40.6333],"type":"Point"}
}