{
  "id": 7471732,
  "type": "Feature",
  "properties": {
    "tgn:hierarchy":[
        "tgn:7471732",
        "tgn:1000004",
        "tgn:1000454",
        "tgn:1000141",
        "tgn:7029392"
    ],
    "tgn:id":7471732,
    "tgn:name":"Quchi Shan",
    "tgn:placetype":[
        "aat:300008777"
    ]
},
  "bbox": [],
  "geometry": {"coordinates":[121.539196,24.927974],"type":"Point"}
}