{
  "id": 2281852,
  "type": "Feature",
  "properties": {
    "tgn:hierarchy":[
        "tgn:2281852",
        "tgn:1000001",
        "tgn:7012149",
        "tgn:2002333",
        "tgn:7007922",
        "tgn:7029392"
    ],
    "tgn:id":2281852,
    "tgn:name":"Deer Creek",
    "tgn:placetype":[
        "aat:300008706"
    ]
},
  "bbox": [],
  "geometry": {"coordinates":[-88.9667,45.1667],"type":"Point"}
}