{
  "id": 7417870,
  "type": "Feature",
  "properties": {
    "tgn:hierarchy":[
        "tgn:7417870",
        "tgn:7005584",
        "tgn:1000001",
        "tgn:7005560",
        "tgn:7029392"
    ],
    "tgn:id":7417870,
    "tgn:name":"Luisiana",
    "tgn:placetype":[
        "aat:300008347"
    ]
},
  "bbox": [],
  "geometry": {"coordinates":[-100.593611,20.428889],"type":"Point"}
}