{
  "id": 2191014,
  "type": "Feature",
  "properties": {
    "tgn:hierarchy":[
        "tgn:2191014",
        "tgn:1000001",
        "tgn:7012149",
        "tgn:2001247",
        "tgn:7007523",
        "tgn:7029392"
    ],
    "tgn:id":2191014,
    "tgn:name":"Boyds Creek",
    "tgn:placetype":[
        "aat:300008706"
    ]
},
  "bbox": [],
  "geometry": {"coordinates":[-91.5333,37.2833],"type":"Point"}
}