{
  "id": 2317168,
  "type": "Feature",
  "properties": {
    "tgn:hierarchy":[
        "tgn:2317168",
        "tgn:7006450",
        "tgn:1000001",
        "tgn:2124076",
        "tgn:7012149",
        "tgn:7029392"
    ],
    "tgn:id":2317168,
    "tgn:name":"Emma Lake",
    "tgn:placetype":[
        "aat:300008680"
    ]
},
  "bbox": [],
  "geometry": {"coordinates":[-131.5333,55.6167],"type":"Point"}
}