{
  "id": 2637318,
  "type": "Feature",
  "properties": {
    "tgn:hierarchy":[
        "tgn:2637318",
        "tgn:7002659",
        "tgn:1000001",
        "tgn:7012149",
        "tgn:2000065",
        "tgn:7029392"
    ],
    "tgn:id":2637318,
    "tgn:name":"Saint John Bar",
    "tgn:placetype":[
        "aat:300132348"
    ]
},
  "bbox": [],
  "geometry": {"coordinates":[-87.2333,32.0667],"type":"Point"}
}