{
  "id": 2313674,
  "type": "Feature",
  "properties": {
    "tgn:hierarchy":[
        "tgn:2313674",
        "tgn:1000001",
        "tgn:7012149",
        "tgn:7007157",
        "tgn:1002684",
        "tgn:7029392"
    ],
    "tgn:id":2313674,
    "tgn:name":"Elephant Mountain",
    "tgn:placetype":[
        "aat:300008798"
    ]
},
  "bbox": [],
  "geometry": {"coordinates":[-121.6833,36.3333],"type":"Point"}
}