{
  "id": 1081671,
  "type": "Feature",
  "properties": {
    "tgn:hierarchy":[
        "tgn:1081671",
        "tgn:1000985",
        "tgn:7016529",
        "tgn:7016531",
        "tgn:1000004",
        "tgn:1000120",
        "tgn:7029392"
    ],
    "tgn:id":1081671,
    "tgn:name":"Urakawa",
    "tgn:placetype":[
        "aat:300008347"
    ]
},
  "bbox": [],
  "geometry": {"coordinates":[142.7667,42.1667],"type":"Point"}
}