{
  "id": 1063264,
  "type": "Feature",
  "properties": {
    "tgn:hierarchy":[
        "tgn:1063264",
        "tgn:1000003",
        "tgn:1000331",
        "tgn:1000097",
        "tgn:7029392"
    ],
    "tgn:id":1063264,
    "tgn:name":"Kvarntorp",
    "tgn:placetype":[
        "aat:300008347"
    ]
},
  "bbox": [],
  "geometry": {"coordinates":[15.25,59.1333],"type":"Point"}
}