{
  "id": 1073640,
  "type": "Feature",
  "properties": {
    "tgn:hierarchy":[
        "tgn:1073640",
        "tgn:1000004",
        "tgn:7002078",
        "tgn:1000111",
        "tgn:7029392"
    ],
    "tgn:id":1073640,
    "tgn:name":"Yonglonghe",
    "tgn:placetype":[
        "aat:300008347"
    ]
},
  "bbox": [],
  "geometry": {"coordinates":[112.7833,30.7667],"type":"Point"}
}