{
  "id": 7137724,
  "type": "Feature",
  "properties": {
    "tgn:hierarchy":[
        "tgn:7137724",
        "tgn:1000003",
        "tgn:7003673",
        "tgn:7000084",
        "tgn:7029392"
    ],
    "tgn:id":7137724,
    "tgn:name":"Liedenkummer im S\u00fcden",
    "tgn:placetype":[
        "aat:300008347"
    ]
},
  "bbox": [],
  "geometry": {"coordinates":[9.783333,53.516667],"type":"Point"}
}