{
  "id": 7374438,
  "type": "Feature",
  "properties": {
    "tgn:hierarchy":[
        "tgn:7374438",
        "tgn:7005587",
        "tgn:1000001",
        "tgn:7005560",
        "tgn:7029392"
    ],
    "tgn:id":7374438,
    "tgn:name":"Lagunilla",
    "tgn:placetype":[
        "aat:300008347"
    ]
},
  "bbox": [],
  "geometry": {"coordinates":[-99.033333,20.35],"type":"Point"}
}