{
  "id": 7083950,
  "type": "Feature",
  "properties": {
    "tgn:hierarchy":[
        "tgn:7083950",
        "tgn:1000003",
        "tgn:7003676",
        "tgn:7000084",
        "tgn:7029392"
    ],
    "tgn:id":7083950,
    "tgn:name":"Wessenstedt",
    "tgn:placetype":[
        "aat:300008347"
    ]
},
  "bbox": [],
  "geometry": {"coordinates":[10.45,53.066667],"type":"Point"}
}