{
  "id": 2226916,
  "type": "Feature",
  "properties": {
    "tgn:hierarchy":[
        "tgn:2226916",
        "tgn:7002659",
        "tgn:1000001",
        "tgn:7012149",
        "tgn:2000050",
        "tgn:7029392"
    ],
    "tgn:id":2226916,
    "tgn:name":"Cauthen Lake Number Two",
    "tgn:placetype":[
        "aat:300006191"
    ]
},
  "bbox": [],
  "geometry": {"coordinates":[-86.2833,32.0833],"type":"Point"}
}