<<<<<<< HEAD
{
  "id": 2766722,
  "type": "Feature",
  "properties": {
    "tgn:hierarchy":[
        "tgn:2766722",
        "tgn:1000001",
        "tgn:7012149",
        "tgn:1003008",
        "tgn:7007710",
        "tgn:7029392"
    ],
    "tgn:id":2766722,
    "tgn:name":"White Oak Pond",
    "tgn:placetype":[
        "aat:300006191"
    ]
},
  "bbox": [],
  "geometry": {"coordinates":[-75.3667,41.6333],"type":"Point"}
}
=======
{"geometry":{"type":"Point","coordinates":[-75.366700,41.633300]},"type":"Feature","properties":{"hierarchy":["tgn:2766722","tgn:1000001","tgn:7012149","tgn:1003008","tgn:7007710","tgn:7029392"],"placetype":["aat:300006191"],"id":2766722,"name:xx":"White Oak Pond"}}
>>>>>>> 03f74aca74312dbeaf24d7e61306dd6a786dc3d0
