{
  "id": 1056734,
  "type": "Feature",
  "properties": {
    "tgn:hierarchy":[
        "tgn:1056734",
        "tgn:1000004",
        "tgn:1003404",
        "tgn:7018214",
        "tgn:7002435",
        "tgn:7029392"
    ],
    "tgn:id":1056734,
    "tgn:name":"Malinki",
    "tgn:placetype":[
        "aat:300008347"
    ]
},
  "bbox": [],
  "geometry": {"coordinates":[38.9833,54.0833],"type":"Point"}
}