{
  "id": 2344166,
  "type": "Feature",
  "properties": {
    "tgn:hierarchy":[
        "tgn:2344166",
        "tgn:1000001",
        "tgn:7012149",
        "tgn:2002333",
        "tgn:7007922",
        "tgn:7029392"
    ],
    "tgn:id":2344166,
    "tgn:name":"Game Lake",
    "tgn:placetype":[
        "aat:300008680"
    ]
},
  "bbox": [],
  "geometry": {"coordinates":[-89.0833,45.3167],"type":"Point"}
}