{
  "id": 7325349,
  "type": "Feature",
  "properties": {
    "tgn:hierarchy":[
        "tgn:7325349",
        "tgn:7001158",
        "tgn:7002850",
        "tgn:1000003",
        "tgn:1000095",
        "tgn:7029392"
    ],
    "tgn:id":7325349,
    "tgn:name":"Santovenia",
    "tgn:placetype":[
        "aat:300008347"
    ]
},
  "bbox": [],
  "geometry": {"coordinates":[-5.716667,41.883333],"type":"Point"}
}