{
  "id": 7077500,
  "type": "Feature",
  "properties": {
    "tgn:hierarchy":[
        "tgn:7077500",
        "tgn:1000003",
        "tgn:7003677",
        "tgn:7000084",
        "tgn:7029392"
    ],
    "tgn:id":7077500,
    "tgn:name":"Enkhausen",
    "tgn:placetype":[
        "aat:300008347"
    ]
},
  "bbox": [],
  "geometry": {"coordinates":[8.55,51.683333],"type":"Point"}
}