{
  "id": 2131769,
  "type": "Feature",
  "properties": {
    "tgn:hierarchy":[
        "tgn:2131769",
        "tgn:1000001",
        "tgn:2001418",
        "tgn:7012149",
        "tgn:7007526",
        "tgn:7029392"
    ],
    "tgn:id":2131769,
    "tgn:name":"Amargosa",
    "tgn:placetype":[
        "aat:300007783",
        "aat:300386984"
    ]
},
  "bbox": [],
  "geometry": {"coordinates":[-116.15,36.5667],"type":"Point"}
}