{
  "id": 2638628,
  "type": "Feature",
  "properties": {
    "tgn:hierarchy":[
        "tgn:2638628",
        "tgn:1000001",
        "tgn:7006451",
        "tgn:2000093",
        "tgn:7012149",
        "tgn:7029392"
    ],
    "tgn:id":2638628,
    "tgn:name":"Salome Creek",
    "tgn:placetype":[
        "aat:300008706"
    ]
},
  "bbox": [],
  "geometry": {"coordinates":[-110.9833,33.9333],"type":"Point"}
}