{
  "id": 7555119,
  "type": "Feature",
  "properties": {
    "tgn:hierarchy":[
        "tgn:7555119",
        "tgn:1000004",
        "tgn:7000198",
        "tgn:1001996",
        "tgn:7029392"
    ],
    "tgn:id":7555119,
    "tgn:name:en":"Nalgan Pass",
    "tgn:placetype":[
        "aat:300259572"
    ]
},
  "bbox": [],
  "geometry": {"coordinates":[78.217984,31.322753],"type":"Point"}
}