{
  "id": 7042115,
  "type": "Feature",
  "properties": {
    "tgn:hierarchy":[
        "tgn:7042115",
        "tgn:7005126",
        "tgn:1000003",
        "tgn:7003120",
        "tgn:1000080",
        "tgn:7029392"
    ],
    "tgn:id":7042115,
    "tgn:name":"Roncaglia",
    "tgn:placetype":[
        "aat:300008347"
    ]
},
  "bbox": [],
  "geometry": {"coordinates":[7.55,44.783333],"type":"Point"}
}