{
  "id": 7496893,
  "type": "Feature",
  "properties": {
    "tgn:hierarchy":[
        "tgn:7496893",
        "tgn:1000004",
        "tgn:7001009",
        "tgn:1000141",
        "tgn:7029392"
    ],
    "tgn:id":7496893,
    "tgn:name":"Yijiang Qiao",
    "tgn:placetype":[
        "aat:300007836"
    ]
},
  "bbox": [],
  "geometry": {"coordinates":[120.737,24.1325],"type":"Point"}
}