{
  "id": 1074372,
  "type": "Feature",
  "properties": {
    "tgn:hierarchy":[
        "tgn:1074372",
        "tgn:1000004",
        "tgn:7000198",
        "tgn:7016883",
        "tgn:7029392"
    ],
    "tgn:id":1074372,
    "tgn:name:en":"Ajn\u0101la",
    "tgn:placetype":[
        "aat:300008347"
    ]
},
  "bbox": [],
  "geometry": {"coordinates":[74.761662,31.843914],"type":"Point"}
}