{
  "id": 2303291,
  "type": "Feature",
  "properties": {
    "tgn:hierarchy":[
        "tgn:2303291",
        "tgn:1000001",
        "tgn:2000602",
        "tgn:7012149",
        "tgn:7007253",
        "tgn:7029392"
    ],
    "tgn:id":2303291,
    "tgn:name":"Eagle City",
    "tgn:placetype":[
        "aat:300008347"
    ]
},
  "bbox": [],
  "geometry": {"coordinates":[-93.1333,42.4667],"type":"Point"}
}