{
  "id": 2625050,
  "type": "Feature",
  "properties": {
    "tgn:hierarchy":[
        "tgn:2625050",
        "tgn:1000001",
        "tgn:7012149",
        "tgn:2001929",
        "tgn:7007825",
        "tgn:7029392"
    ],
    "tgn:id":2625050,
    "tgn:name":"Rock Woman Cave",
    "tgn:placetype":[
        "aat:300008746"
    ]
},
  "bbox": [],
  "geometry": {"coordinates":[-85.4333,35.9167],"type":"Point"}
}