<<<<<<< HEAD
{
  "id": 7377993,
  "type": "Feature",
  "properties": {
    "tgn:hierarchy":[
        "tgn:7377993",
        "tgn:7005583",
        "tgn:1000001",
        "tgn:7005560",
        "tgn:7029392"
    ],
    "tgn:id":7377993,
    "tgn:name":"Rancho La Posta del Vergel",
    "tgn:placetype":[
        "aat:300000241"
    ]
},
  "bbox": [],
  "geometry": {"coordinates":[-105.5,25.783333],"type":"Point"}
}
=======
{"geometry":{"type":"Point","coordinates":[-105.500000,25.783333]},"type":"Feature","properties":{"hierarchy":["tgn:7377993","tgn:7005583","tgn:1000001","tgn:7005560","tgn:7029392"],"placetype":["aat:300000241"],"id":7377993,"name:xx":"Rancho La Posta del Vergel"}}
>>>>>>> 03f74aca74312dbeaf24d7e61306dd6a786dc3d0
