{
  "id": 7279520,
  "type": "Feature",
  "properties": {
    "tgn:hierarchy":[
        "tgn:7279520",
        "tgn:1001705",
        "tgn:1000049",
        "tgn:1000002",
        "tgn:7029392"
    ],
    "tgn:id":7279520,
    "tgn:name":"Rar\u00edn, Quebrada",
    "tgn:placetype":[
        "aat:300266554",
        "aat:300008699"
    ]
},
  "bbox": [],
  "geometry": {"coordinates":[-71.966667,-34.766667],"type":"Point"}
}