{
  "id": 2671468,
  "type": "Feature",
  "properties": {
    "tgn:hierarchy":[
        "tgn:2671468",
        "tgn:1000001",
        "tgn:7012149",
        "tgn:1002899",
        "tgn:7007920",
        "tgn:7029392"
    ],
    "tgn:id":2671468,
    "tgn:name":"Smith Island",
    "tgn:placetype":[
        "aat:300008791"
    ]
},
  "bbox": [],
  "geometry": {"coordinates":[-122.1833,48.0167],"type":"Point"}
}