{
  "id": 2571963,
  "type": "Feature",
  "properties": {
    "tgn:hierarchy":[
        "tgn:2571963",
        "tgn:1000001",
        "tgn:7012149",
        "tgn:1002595",
        "tgn:7007826",
        "tgn:7029392"
    ],
    "tgn:id":2571963,
    "tgn:name":"Payne Lake",
    "tgn:placetype":[
        "aat:300008680"
    ]
},
  "bbox": [],
  "geometry": {"coordinates":[-94.8333,30.1667],"type":"Point"}
}