<<<<<<< HEAD
{
  "id": 7484063,
  "type": "Feature",
  "properties": {
    "tgn:hierarchy":[
        "tgn:7484063",
        "tgn:1000004",
        "tgn:7490934",
        "tgn:1000141",
        "tgn:7029392"
    ],
    "tgn:id":7484063,
    "tgn:name":"Nanping",
    "tgn:placetype":[
        "aat:300008347"
    ]
},
  "bbox": [],
  "geometry": {"coordinates":[120.52,23.073889],"type":"Point"}
}
=======
{"geometry":{"type":"Point","coordinates":[120.520000,23.073889]},"type":"Feature","properties":{"hierarchy":["tgn:7484063","tgn:1000004","tgn:7490934","tgn:1000141","tgn:7029392"],"placetype":["aat:300008347"],"id":7484063,"name:xx":"Nanping"}}
>>>>>>> 03f74aca74312dbeaf24d7e61306dd6a786dc3d0
