{
  "id": 7279795,
  "type": "Feature",
  "properties": {
    "tgn:hierarchy":[
        "tgn:7279795",
        "tgn:1001699",
        "tgn:1000049",
        "tgn:1000002",
        "tgn:7029392"
    ],
    "tgn:id":7279795,
    "tgn:name":"Remehue, R\u00edo",
    "tgn:placetype":[
        "aat:300008699"
    ]
},
  "bbox": [],
  "geometry": {"coordinates":[-72.566667,-39.883333],"type":"Point"}
}