{
  "id": 2072514,
  "type": "Feature",
  "properties": {
    "tgn:hierarchy":[
        "tgn:2072514",
        "tgn:1000001",
        "tgn:7012149",
        "tgn:1002688",
        "tgn:7007568",
        "tgn:7029392"
    ],
    "tgn:id":2072514,
    "tgn:name":"Sprout Brook",
    "tgn:placetype":[
        "aat:300008347",
        "aat:300387210"
    ]
},
  "bbox": [],
  "geometry": {"coordinates":[-74.6833,42.85],"type":"Point"}
}