{
  "id": 7032297,
  "type": "Feature",
  "properties": {
    "tgn:hierarchy":[
        "tgn:7032297",
        "tgn:7001680",
        "tgn:7001242",
        "tgn:1000184",
        "tgn:7029392"
    ],
    "tgn:id":7032297,
    "tgn:name:fr":"Galets, Rivi\u00e8re des",
    "tgn:placetype":[
        "aat:300008699"
    ]
},
  "bbox": [],
  "geometry": {"coordinates":[55.2833,-20.95],"type":"Point"}
}