{
  "id": 7204255,
  "type": "Feature",
  "properties": {
    "tgn:hierarchy":[
        "tgn:7204255",
        "tgn:1000003",
        "tgn:7003677",
        "tgn:7000084",
        "tgn:7029392"
    ],
    "tgn:id":7204255,
    "tgn:name":"Brenge",
    "tgn:placetype":[
        "aat:300000206"
    ]
},
  "bbox": [],
  "geometry": {"coordinates":[7.733333,51.233333],"type":"Point"}
}