{
  "id": 7133524,
  "type": "Feature",
  "properties": {
    "tgn:hierarchy":[
        "tgn:7133524",
        "tgn:1000003",
        "tgn:7003677",
        "tgn:7000084",
        "tgn:7029392"
    ],
    "tgn:id":7133524,
    "tgn:name":"Bahnhof Neheim-H\u00fcsten",
    "tgn:placetype":[
        "aat:300007783"
    ]
},
  "bbox": [],
  "geometry": {"coordinates":[7.970556,51.436389],"type":"Point"}
}