{
  "id": 2222420,
  "type": "Feature",
  "properties": {
    "tgn:hierarchy":[
        "tgn:2222420",
        "tgn:1000001",
        "tgn:7012149",
        "tgn:2001453",
        "tgn:7007566",
        "tgn:7029392"
    ],
    "tgn:id":2222420,
    "tgn:name":"Carpenter Canyon",
    "tgn:placetype":[
        "aat:300008761"
    ]
},
  "bbox": [],
  "geometry": {"coordinates":[-104.0833,35.75],"type":"Point"}
}