{
  "id": 7559323,
  "type": "Feature",
  "properties": {
    "tgn:hierarchy":[
        "tgn:7559323",
        "tgn:1000004",
        "tgn:7000198",
        "tgn:7016722",
        "tgn:7029392"
    ],
    "tgn:id":7559323,
    "tgn:name:en":"Sar\u016brpur",
    "tgn:placetype":[
        "aat:300008347"
    ]
},
  "bbox": [],
  "geometry": {"coordinates":[77.232455,29.030548],"type":"Point"}
}