{
  "id": 7591808,
  "type": "Feature",
  "properties": {
    "tgn:hierarchy":[
        "tgn:7591808",
        "tgn:1000004",
        "tgn:7000198",
        "tgn:7000799",
        "tgn:7029392"
    ],
    "tgn:id":7591808,
    "tgn:name:en":"Kotli Pandit\u0101n",
    "tgn:placetype":[
        "aat:300008347"
    ]
},
  "bbox": [],
  "geometry": {"coordinates":[74.785377,32.928494],"type":"Point"}
}