{
  "id": 2096140,
  "type": "Feature",
  "properties": {
    "tgn:hierarchy":[
        "tgn:2096140",
        "tgn:1000001",
        "tgn:7012149",
        "tgn:2001763",
        "tgn:7007712",
        "tgn:7029392"
    ],
    "tgn:id":2096140,
    "tgn:name":"Liberty",
    "tgn:placetype":[
        "aat:300008347"
    ]
},
  "bbox": [],
  "geometry": {"coordinates":[-82.6833,34.7833],"type":"Point"}
}