{
  "id": 7290720,
  "type": "Feature",
  "properties": {
    "tgn:hierarchy":[
        "tgn:7290720",
        "tgn:7002464",
        "tgn:1000049",
        "tgn:1000002",
        "tgn:7029392"
    ],
    "tgn:id":7290720,
    "tgn:name":"Diablo, Boca del",
    "tgn:placetype":[
        "aat:300387057"
    ]
},
  "bbox": [],
  "geometry": {"coordinates":[-70.116667,-21.183333],"type":"Point"}
}