{
  "id": 1092526,
  "type": "Feature",
  "properties": {
    "tgn:hierarchy":[
        "tgn:1092526",
        "tgn:7001242",
        "tgn:1001742",
        "tgn:1000189",
        "tgn:7029392"
    ],
    "tgn:id":1092526,
    "tgn:name":"Mako",
    "tgn:placetype":[
        "aat:300008347"
    ]
},
  "bbox": [],
  "geometry": {"coordinates":[-12.35,12.8667],"type":"Point"}
}