{
  "id": 2184006,
  "type": "Feature",
  "properties": {
    "tgn:hierarchy":[
        "tgn:2184006",
        "tgn:1000001",
        "tgn:7016172",
        "tgn:7012149",
        "tgn:2000175",
        "tgn:7029392"
    ],
    "tgn:id":2184006,
    "tgn:name":"Boat Ridge Island",
    "tgn:placetype":[
        "aat:300008791"
    ]
},
  "bbox": [],
  "geometry": {"coordinates":[-92.3167,35.55],"type":"Point"}
}