{
  "id": 2498108,
  "type": "Feature",
  "properties": {
    "tgn:hierarchy":[
        "tgn:2498108",
        "tgn:1000001",
        "tgn:7012149",
        "tgn:7007706",
        "tgn:7029392"
    ],
    "tgn:id":2498108,
    "tgn:name":"Mays Fork",
    "tgn:placetype":[
        "aat:300008699"
    ]
},
  "bbox": [],
  "geometry": {"coordinates":[-81.7333,39.8667],"type":"Point"}
}