{
  "id": 1000382,
  "type": "Feature",
  "properties": {
    "tgn:hierarchy":[
        "tgn:1000382",
        "tgn:7001242",
        "tgn:1000171",
        "tgn:7029392"
    ],
    "tgn:id":1000382,
    "tgn:name":"Grand Cape Mount",
    "tgn:placetype":[
        "aat:300387064",
        "aat:300000771"
    ]
},
  "bbox": [],
  "geometry": {"coordinates":[-10.8333,7.0833],"type":"Point"}
}