{
  "id": 7354821,
  "type": "Feature",
  "properties": {
    "tgn:hierarchy":[
        "tgn:7354821",
        "tgn:1000001",
        "tgn:7005600",
        "tgn:7005560",
        "tgn:7029392"
    ],
    "tgn:id":7354821,
    "tgn:name":"Caucel",
    "tgn:placetype":[
        "aat:300008347"
    ]
},
  "bbox": [],
  "geometry": {"coordinates":[-89.716667,21.016667],"type":"Point"}
}