{
  "id": 2250150,
  "type": "Feature",
  "properties": {
    "tgn:hierarchy":[
        "tgn:2250150",
        "tgn:1000001",
        "tgn:7012149",
        "tgn:2002118",
        "tgn:7007827",
        "tgn:7029392"
    ],
    "tgn:id":2250150,
    "tgn:name":"Collins Gulch",
    "tgn:placetype":[
        "aat:300008761"
    ]
},
  "bbox": [],
  "geometry": {"coordinates":[-111.6333,40.5667],"type":"Point"}
}