{
  "id": 7219975,
  "type": "Feature",
  "properties": {
    "tgn:hierarchy":[
        "tgn:7219975",
        "tgn:7011163",
        "tgn:7002674",
        "tgn:1000003",
        "tgn:1000074",
        "tgn:7029392"
    ],
    "tgn:id":7219975,
    "tgn:name":"Asprop\u00f3tamos",
    "tgn:placetype":[
        "aat:300008347"
    ]
},
  "bbox": [],
  "geometry": {"coordinates":[26.376667,39.275],"type":"Point"}
}