{
  "id": 2183404,
  "type": "Feature",
  "properties": {
    "tgn:hierarchy":[
        "tgn:2183404",
        "tgn:1000001",
        "tgn:7012149",
        "tgn:2000491",
        "tgn:7007250",
        "tgn:7029392"
    ],
    "tgn:id":2183404,
    "tgn:name":"Bluff Divide",
    "tgn:placetype":[
        "aat:300266640"
    ]
},
  "bbox": [],
  "geometry": {"coordinates":[-115.55,47.1167],"type":"Point"}
}