{
  "id": 1140956,
  "type": "Feature",
  "properties": {
    "tgn:hierarchy":[
        "tgn:1140956",
        "tgn:7000490",
        "tgn:1000006",
        "tgn:7006238",
        "tgn:7029392"
    ],
    "tgn:id":1140956,
    "tgn:name":"Blackwood",
    "tgn:placetype":[
        "aat:300008347"
    ]
},
  "bbox": [],
  "geometry": {"coordinates":[144.3167,-37.4833],"type":"Point"}
}