{
  "id": 7138054,
  "type": "Feature",
  "properties": {
    "tgn:hierarchy":[
        "tgn:7138054",
        "tgn:7003669",
        "tgn:1000003",
        "tgn:7000084",
        "tgn:7029392"
    ],
    "tgn:id":7138054,
    "tgn:name":"Leeder",
    "tgn:placetype":[
        "aat:300008347"
    ]
},
  "bbox": [],
  "geometry": {"coordinates":[10.833333,47.933333],"type":"Point"}
}