{
  "id": 2511911,
  "type": "Feature",
  "properties": {
    "tgn:hierarchy":[
        "tgn:2511911",
        "tgn:1000001",
        "tgn:7012149",
        "tgn:2000382",
        "tgn:7007248",
        "tgn:7029392"
    ],
    "tgn:id":2511911,
    "tgn:name":"Milkhouse Bay",
    "tgn:placetype":[
        "aat:300008905"
    ]
},
  "bbox": [],
  "geometry": {"coordinates":[-81.6333,31.75],"type":"Point"}
}