<<<<<<< HEAD
{
  "id": 7350567,
  "type": "Feature",
  "properties": {
    "tgn:hierarchy":[
        "tgn:7350567",
        "tgn:1001853",
        "tgn:1000001",
        "tgn:7005560",
        "tgn:7029392"
    ],
    "tgn:id":7350567,
    "tgn:name":"Blanco, Arroyo",
    "tgn:placetype":[
        "aat:300266554",
        "aat:300008699"
    ]
},
  "bbox": [],
  "geometry": {"coordinates":[-100.633333,28.8],"type":"Point"}
}
=======
{"geometry":{"type":"Point","coordinates":[-100.633333,28.800000]},"type":"Feature","properties":{"hierarchy":["tgn:7350567","tgn:1001853","tgn:1000001","tgn:7005560","tgn:7029392"],"placetype":["aat:300266554","aat:300008699"],"id":7350567,"name:xx":"Blanco, Arroyo"}}
>>>>>>> 03f74aca74312dbeaf24d7e61306dd6a786dc3d0
