{
  "id": 2541854,
  "type": "Feature",
  "properties": {
    "tgn:hierarchy":[
        "tgn:2541854",
        "tgn:1000001",
        "tgn:7012149",
        "tgn:2001278",
        "tgn:7007524",
        "tgn:7029392"
    ],
    "tgn:id":2541854,
    "tgn:name":"Ninemile Spring",
    "tgn:placetype":[
        "aat:300008697"
    ]
},
  "bbox": [],
  "geometry": {"coordinates":[-109.0833,46.3667],"type":"Point"}
}