{
  "id": 2364634,
  "type": "Feature",
  "properties": {
    "tgn:hierarchy":[
        "tgn:2364634",
        "tgn:1000001",
        "tgn:7012149",
        "tgn:2001762",
        "tgn:7007712",
        "tgn:7029392"
    ],
    "tgn:id":2364634,
    "tgn:name":"Greenbriar",
    "tgn:placetype":[
        "aat:300008347"
    ]
},
  "bbox": [],
  "geometry": {"coordinates":[-80.85,33.5333],"type":"Point"}
}