<<<<<<< HEAD
{
  "id": 7485271,
  "type": "Feature",
  "properties": {
    "tgn:hierarchy":[
        "tgn:7485271",
        "tgn:1000004",
        "tgn:7492971",
        "tgn:1000141",
        "tgn:7029392"
    ],
    "tgn:id":7485271,
    "tgn:name":"Zhongxinshelun",
    "tgn:placetype":[
        "aat:300008798"
    ]
},
  "bbox": [],
  "geometry": {"coordinates":[120.727778,22.239167],"type":"Point"}
}
=======
{"geometry":{"type":"Point","coordinates":[120.727778,22.239167]},"type":"Feature","properties":{"hierarchy":["tgn:7485271","tgn:1000004","tgn:7492971","tgn:1000141","tgn:7029392"],"placetype":["aat:300008798"],"id":7485271,"name:xx":"Zhongxinshelun"}}
>>>>>>> 03f74aca74312dbeaf24d7e61306dd6a786dc3d0
