{
  "id": 7480089,
  "type": "Feature",
  "properties": {
    "tgn:hierarchy":[
        "tgn:7480089",
        "tgn:1000004",
        "tgn:7490934",
        "tgn:1000141",
        "tgn:7029392"
    ],
    "tgn:id":7480089,
    "tgn:name":"Haidong Guoxiao",
    "tgn:placetype":[
        "aat:300006495"
    ]
},
  "bbox": [],
  "geometry": {"coordinates":[120.174444,23.046944],"type":"Point"}
}