{
  "id": 2703728,
  "type": "Feature",
  "properties": {
    "tgn:hierarchy":[
        "tgn:2703728",
        "tgn:1000001",
        "tgn:7012149",
        "tgn:2001103",
        "tgn:7007522",
        "tgn:7029392"
    ],
    "tgn:id":2703728,
    "tgn:name":"Sumrall Lake",
    "tgn:placetype":[
        "aat:300006191"
    ]
},
  "bbox": [],
  "geometry": {"coordinates":[-89.25,31.2167],"type":"Point"}
}