{
  "id": 7210902,
  "type": "Feature",
  "properties": {
    "tgn:hierarchy":[
        "tgn:7210902",
        "tgn:7003669",
        "tgn:1000003",
        "tgn:7000084",
        "tgn:7029392"
    ],
    "tgn:id":7210902,
    "tgn:name":"Beim Wei\u00dfen Stein",
    "tgn:placetype":[
        "aat:300008863"
    ]
},
  "bbox": [],
  "geometry": {"coordinates":[12.016667,49.65],"type":"Point"}
}