{
  "id": 2501189,
  "type": "Feature",
  "properties": {
    "tgn:hierarchy":[
        "tgn:2501189",
        "tgn:1000001",
        "tgn:7012149",
        "tgn:2001303",
        "tgn:7007524",
        "tgn:7029392"
    ],
    "tgn:id":2501189,
    "tgn:name":"McGhee Gulch",
    "tgn:placetype":[
        "aat:300008761"
    ]
},
  "bbox": [],
  "geometry": {"coordinates":[-106.5167,45.25],"type":"Point"}
}