{
  "id": 2367461,
  "type": "Feature",
  "properties": {
    "tgn:hierarchy":[
        "tgn:2367461",
        "tgn:1000001",
        "tgn:7012149",
        "tgn:2000471",
        "tgn:7007250",
        "tgn:7029392"
    ],
    "tgn:id":2367461,
    "tgn:name":"Grouse Butte",
    "tgn:placetype":[
        "aat:300008798"
    ]
},
  "bbox": [],
  "geometry": {"coordinates":[-115.15,43.55],"type":"Point"}
}