{
  "id": 7096332,
  "type": "Feature",
  "properties": {
    "tgn:hierarchy":[
        "tgn:7096332",
        "tgn:7003669",
        "tgn:1000003",
        "tgn:7000084",
        "tgn:7029392"
    ],
    "tgn:id":7096332,
    "tgn:name":"Sch\u00f6naich",
    "tgn:placetype":[
        "aat:300008347"
    ]
},
  "bbox": [],
  "geometry": {"coordinates":[10.433333,49.816667],"type":"Point"}
}