{
  "id": 7581652,
  "type": "Feature",
  "properties": {
    "tgn:hierarchy":[
        "tgn:7581652",
        "tgn:1000004",
        "tgn:7000198",
        "tgn:1001882",
        "tgn:7029392"
    ],
    "tgn:id":7581652,
    "tgn:name:en":"Tadasa",
    "tgn:placetype":[
        "aat:300007783"
    ]
},
  "bbox": [],
  "geometry": {"coordinates":[75.583333,13.65],"type":"Point"}
}