{
  "id": 7467401,
  "type": "Feature",
  "properties": {
    "tgn:hierarchy":[
        "tgn:7467401",
        "tgn:1000004",
        "tgn:1000959",
        "tgn:1000141",
        "tgn:7029392"
    ],
    "tgn:id":7467401,
    "tgn:name":"Jiantou",
    "tgn:placetype":[
        "aat:300000745"
    ]
},
  "bbox": [],
  "geometry": {"coordinates":[121.592532,25.086108],"type":"Point"}
}