{
  "id": 2142626,
  "type": "Feature",
  "properties": {
    "tgn:hierarchy":[
        "tgn:2142626",
        "tgn:1000001",
        "tgn:7012149",
        "tgn:2000876",
        "tgn:7007256",
        "tgn:7029392"
    ],
    "tgn:id":2142626,
    "tgn:name":"Badeaux Coulee",
    "tgn:placetype":[
        "aat:300008699"
    ]
},
  "bbox": [],
  "geometry": {"coordinates":[-91.8833,29.9667],"type":"Point"}
}