<<<<<<< HEAD
{
  "id": 7176696,
  "type": "Feature",
  "properties": {
    "tgn:hierarchy":[
        "tgn:7176696",
        "tgn:1000003",
        "tgn:7003677",
        "tgn:7000084",
        "tgn:7029392"
    ],
    "tgn:id":7176696,
    "tgn:name":"Hallerstein",
    "tgn:placetype":[
        "aat:300008777"
    ]
},
  "bbox": [],
  "geometry": {"coordinates":[8.616667,51.433333],"type":"Point"}
}
=======
{"geometry":{"type":"Point","coordinates":[8.616667,51.433333]},"type":"Feature","properties":{"hierarchy":["tgn:7176696","tgn:1000003","tgn:7003677","tgn:7000084","tgn:7029392"],"placetype":["aat:300008777"],"id":7176696,"name:xx":"Hallerstein"}}
>>>>>>> 03f74aca74312dbeaf24d7e61306dd6a786dc3d0
