{
  "id": 7110342,
  "type": "Feature",
  "properties": {
    "tgn:hierarchy":[
        "tgn:7110342",
        "tgn:1000003",
        "tgn:7003677",
        "tgn:7000084",
        "tgn:7029392"
    ],
    "tgn:id":7110342,
    "tgn:name":"Ram-Berg",
    "tgn:placetype":[
        "aat:300008777"
    ]
},
  "bbox": [],
  "geometry": {"coordinates":[8.083333,51.283333],"type":"Point"}
}