<<<<<<< HEAD
{
  "id": 7110342,
  "type": "Feature",
  "properties": {
    "tgn:hierarchy":[
        "tgn:7110342",
        "tgn:1000003",
        "tgn:7003677",
        "tgn:7000084",
        "tgn:7029392"
    ],
    "tgn:id":7110342,
    "tgn:name":"Ram-Berg",
    "tgn:placetype":[
        "aat:300008777"
    ]
},
  "bbox": [],
  "geometry": {"coordinates":[8.083333,51.283333],"type":"Point"}
}
=======
{"geometry":{"type":"Point","coordinates":[8.083333,51.283333]},"type":"Feature","properties":{"hierarchy":["tgn:7110342","tgn:1000003","tgn:7003677","tgn:7000084","tgn:7029392"],"placetype":["aat:300008777"],"id":7110342,"name:xx":"Ram-Berg"}}
>>>>>>> 03f74aca74312dbeaf24d7e61306dd6a786dc3d0
