{
  "id": 7236354,
  "type": "Feature",
  "properties": {
    "tgn:hierarchy":[
        "tgn:7236354",
        "tgn:7011330",
        "tgn:7002674",
        "tgn:1000003",
        "tgn:1000074",
        "tgn:7029392"
    ],
    "tgn:id":7236354,
    "tgn:name":"\u00c9ristos, Orm\u00edskos",
    "tgn:placetype":[
        "aat:300132316"
    ]
},
  "bbox": [],
  "geometry": {"coordinates":[27.3475,36.4275],"type":"Point"}
}