{
  "id": 7590804,
  "type": "Feature",
  "properties": {
    "tgn:hierarchy":[
        "tgn:7590804",
        "tgn:1000004",
        "tgn:7000198",
        "tgn:7000799",
        "tgn:7029392"
    ],
    "tgn:id":7590804,
    "tgn:name:en":"Sobka T\u0101la",
    "tgn:placetype":[
        "aat:300008347"
    ]
},
  "bbox": [],
  "geometry": {"coordinates":[74.748611,32.880556],"type":"Point"}
}