<<<<<<< HEAD
{
  "id": 2336162,
  "type": "Feature",
  "properties": {
    "tgn:hierarchy":[
        "tgn:2336162",
        "tgn:1000001",
        "tgn:7012149",
        "tgn:1002244",
        "tgn:7007826",
        "tgn:7029392"
    ],
    "tgn:id":2336162,
    "tgn:name":"Foster Lake",
    "tgn:placetype":[
        "aat:300006191"
    ]
},
  "bbox": [],
  "geometry": {"coordinates":[-94.4333,33.0],"type":"Point"}
}
=======
{"geometry":{"type":"Point","coordinates":[-94.433300,33.000000]},"type":"Feature","properties":{"hierarchy":["tgn:2336162","tgn:1000001","tgn:7012149","tgn:1002244","tgn:7007826","tgn:7029392"],"placetype":["aat:300006191"],"id":2336162,"name:xx":"Foster Lake"}}
>>>>>>> 03f74aca74312dbeaf24d7e61306dd6a786dc3d0
