{
  "id": 7348712,
  "type": "Feature",
  "properties": {
    "tgn:hierarchy":[
        "tgn:7348712",
        "tgn:7005581",
        "tgn:1000001",
        "tgn:7005560",
        "tgn:7029392"
    ],
    "tgn:id":7348712,
    "tgn:name":"Alamito de los Fresnos, Cerro",
    "tgn:placetype":[
        "aat:300008795"
    ]
},
  "bbox": [],
  "geometry": {"coordinates":[-107.133333,29.65],"type":"Point"}
}