{
  "id": 2438189,
  "type": "Feature",
  "properties": {
    "tgn:hierarchy":[
        "tgn:2438189",
        "tgn:1000001",
        "tgn:7012149",
        "tgn:7007157",
        "tgn:1002956",
        "tgn:7029392"
    ],
    "tgn:id":2438189,
    "tgn:name":"Kingfisher Stringer",
    "tgn:placetype":[
        "aat:300008699"
    ]
},
  "bbox": [],
  "geometry": {"coordinates":[-118.2167,36.2333],"type":"Point"}
}