{
  "id": 7404870,
  "type": "Feature",
  "properties": {
    "tgn:hierarchy":[
        "tgn:7404870",
        "tgn:7005585",
        "tgn:1000001",
        "tgn:7005560",
        "tgn:7029392"
    ],
    "tgn:id":7404870,
    "tgn:name":"Chacamerito",
    "tgn:placetype":[
        "aat:300008347"
    ]
},
  "bbox": [],
  "geometry": {"coordinates":[-100.583333,18.316667],"type":"Point"}
}