{
  "id": 2183297,
  "type": "Feature",
  "properties": {
    "tgn:hierarchy":[
        "tgn:2183297",
        "tgn:7002659",
        "tgn:1000001",
        "tgn:7012149",
        "tgn:2000041",
        "tgn:7029392"
    ],
    "tgn:id":2183297,
    "tgn:name":"Bluff Cave",
    "tgn:placetype":[
        "aat:300008746"
    ]
},
  "bbox": [],
  "geometry": {"coordinates":[-87.1167,34.8667],"type":"Point"}
}