{
  "id": 2099830,
  "type": "Feature",
  "properties": {
    "tgn:hierarchy":[
        "tgn:2099830",
        "tgn:1000001",
        "tgn:7012149",
        "tgn:2001894",
        "tgn:7007825",
        "tgn:7029392"
    ],
    "tgn:id":2099830,
    "tgn:name":"Kimball",
    "tgn:placetype":[
        "aat:300008347"
    ]
},
  "bbox": [],
  "geometry": {"coordinates":[-85.6667,35.0333],"type":"Point"}
}