{
  "id": 2056107,
  "type": "Feature",
  "properties": {
    "tgn:hierarchy":[
        "tgn:2056107",
        "tgn:1000001",
        "tgn:7012149",
        "tgn:2001128",
        "tgn:7007522",
        "tgn:7029392"
    ],
    "tgn:id":2056107,
    "tgn:name":"Carlos",
    "tgn:placetype":[
        "aat:300008347",
        "aat:300387210"
    ]
},
  "bbox": [],
  "geometry": {"coordinates":[-90.3667,31.6167],"type":"Point"}
}