{
  "id": 2638153,
  "type": "Feature",
  "properties": {
    "tgn:hierarchy":[
        "tgn:2638153",
        "tgn:7006450",
        "tgn:1000001",
        "tgn:7012149",
        "tgn:2124005",
        "tgn:7029392"
    ],
    "tgn:id":2638153,
    "tgn:name":"Saligvik Creek",
    "tgn:placetype":[
        "aat:300008706"
    ]
},
  "bbox": [],
  "geometry": {"coordinates":[-165.7333,68.1833],"type":"Point"}
}