{
  "id": 2771405,
  "type": "Feature",
  "properties": {
    "tgn:hierarchy":[
        "tgn:2771405",
        "tgn:1000001",
        "tgn:7012149",
        "tgn:2002119",
        "tgn:7007827",
        "tgn:7029392"
    ],
    "tgn:id":2771405,
    "tgn:name":"Wilderness, The",
    "tgn:placetype":[
        "aat:300055621"
    ]
},
  "bbox": [],
  "geometry": {"coordinates":[-109.6333,37.85],"type":"Point"}
}