<<<<<<< HEAD
{
  "id": 7476284,
  "type": "Feature",
  "properties": {
    "tgn:hierarchy":[
        "tgn:7476284",
        "tgn:7488858",
        "tgn:1000004",
        "tgn:1000141",
        "tgn:7029392"
    ],
    "tgn:id":7476284,
    "tgn:name":"Minhe Guoxiao",
    "tgn:placetype":[
        "aat:300006495"
    ]
},
  "bbox": [],
  "geometry": {"coordinates":[120.933059,23.79466],"type":"Point"}
}
=======
{"geometry":{"type":"Point","coordinates":[120.933059,23.794660]},"type":"Feature","properties":{"hierarchy":["tgn:7476284","tgn:7488858","tgn:1000004","tgn:1000141","tgn:7029392"],"placetype":["aat:300006495"],"id":7476284,"name:xx":"Minhe Guoxiao"}}
>>>>>>> 03f74aca74312dbeaf24d7e61306dd6a786dc3d0
