{
  "id": 2078432,
  "type": "Feature",
  "properties": {
    "tgn:hierarchy":[
        "tgn:2078432",
        "tgn:1000001",
        "tgn:7012149",
        "tgn:2001622",
        "tgn:7007706",
        "tgn:7029392"
    ],
    "tgn:id":2078432,
    "tgn:name":"Belpre",
    "tgn:placetype":[
        "aat:300008347"
    ]
},
  "bbox": [],
  "geometry": {"coordinates":[-81.5667,39.2667],"type":"Point"}
}