{
  "id": 1049933,
  "type": "Feature",
  "properties": {
    "tgn:hierarchy":[
        "tgn:1049933",
        "tgn:1000003",
        "tgn:1000929",
        "tgn:1000090",
        "tgn:7029392"
    ],
    "tgn:id":1049933,
    "tgn:name":"Seixal",
    "tgn:placetype":[
        "aat:300008347",
        "aat:300387218"
    ]
},
  "bbox": [],
  "geometry": {"coordinates":[-9.101,38.64],"type":"Point"}
}