{
  "id": 2253128,
  "type": "Feature",
  "properties": {
    "tgn:hierarchy":[
        "tgn:2253128",
        "tgn:1000001",
        "tgn:7006451",
        "tgn:2000093",
        "tgn:7012149",
        "tgn:7029392"
    ],
    "tgn:id":2253128,
    "tgn:name":"Contact Trick Tank",
    "tgn:placetype":[
        "aat:300006191"
    ]
},
  "bbox": [],
  "geometry": {"coordinates":[-111.4167,34.2667],"type":"Point"}
}