{
  "id": 7398163,
  "type": "Feature",
  "properties": {
    "tgn:hierarchy":[
        "tgn:7398163",
        "tgn:1000001",
        "tgn:1001960",
        "tgn:7005560",
        "tgn:7029392"
    ],
    "tgn:id":7398163,
    "tgn:name":"Las Canoas",
    "tgn:placetype":[
        "aat:300266554",
        "aat:300008699"
    ]
},
  "bbox": [],
  "geometry": {"coordinates":[-110.711944,30.801667],"type":"Point"}
}