<<<<<<< HEAD
{
  "id": 2407707,
  "type": "Feature",
  "properties": {
    "tgn:hierarchy":[
        "tgn:2407707",
        "tgn:1000001",
        "tgn:2001782",
        "tgn:7012149",
        "tgn:7007713",
        "tgn:7029392"
    ],
    "tgn:id":2407707,
    "tgn:name":"Huron Colony",
    "tgn:placetype":[
        "aat:300008347"
    ]
},
  "bbox": [],
  "geometry": {"coordinates":[-97.9,44.7667],"type":"Point"}
}
=======
{"geometry":{"type":"Point","coordinates":[-97.900000,44.766700]},"type":"Feature","properties":{"hierarchy":["tgn:2407707","tgn:1000001","tgn:2001782","tgn:7012149","tgn:7007713","tgn:7029392"],"placetype":["aat:300008347"],"id":2407707,"name:xx":"Huron Colony"}}
>>>>>>> 03f74aca74312dbeaf24d7e61306dd6a786dc3d0
