{
  "id": 2612346,
  "type": "Feature",
  "properties": {
    "tgn:hierarchy":[
        "tgn:2612346",
        "tgn:1000001",
        "tgn:7006451",
        "tgn:2000091",
        "tgn:7012149",
        "tgn:7029392"
    ],
    "tgn:id":2612346,
    "tgn:name":"Red Tank",
    "tgn:placetype":[
        "aat:300006191"
    ]
},
  "bbox": [],
  "geometry": {"coordinates":[-109.45,32.1833],"type":"Point"}
}