{
  "id": 2562579,
  "type": "Feature",
  "properties": {
    "tgn:hierarchy":[
        "tgn:2562579",
        "tgn:1000001",
        "tgn:7012149",
        "tgn:2001437",
        "tgn:7007566",
        "tgn:7029392"
    ],
    "tgn:id":2562579,
    "tgn:name":"Outlaw Canyon",
    "tgn:placetype":[
        "aat:300008761"
    ]
},
  "bbox": [],
  "geometry": {"coordinates":[-107.7333,32.75],"type":"Point"}
}