{
  "id": 7430178,
  "type": "Feature",
  "properties": {
    "tgn:hierarchy":[
        "tgn:7430178",
        "tgn:1001835",
        "tgn:1000001",
        "tgn:7005560",
        "tgn:7029392"
    ],
    "tgn:id":7430178,
    "tgn:name":"Jos\u00e9 Mar\u00eda Pino Su\u00e1rez",
    "tgn:placetype":[
        "aat:300008347"
    ]
},
  "bbox": [],
  "geometry": {"coordinates":[-116.083333,32.383333],"type":"Point"}
}