<<<<<<< HEAD
{
  "id": 2768543,
  "type": "Feature",
  "properties": {
    "tgn:hierarchy":[
        "tgn:2768543",
        "tgn:1000001",
        "tgn:7012149",
        "tgn:2000387",
        "tgn:7007248",
        "tgn:7029392"
    ],
    "tgn:id":2768543,
    "tgn:name":"Whitewater Pond",
    "tgn:placetype":[
        "aat:300006191"
    ]
},
  "bbox": [],
  "geometry": {"coordinates":[-84.0667,32.3333],"type":"Point"}
}
=======
{"geometry":{"type":"Point","coordinates":[-84.066700,32.333300]},"type":"Feature","properties":{"hierarchy":["tgn:2768543","tgn:1000001","tgn:7012149","tgn:2000387","tgn:7007248","tgn:7029392"],"placetype":["aat:300006191"],"id":2768543,"name:xx":"Whitewater Pond"}}
>>>>>>> 03f74aca74312dbeaf24d7e61306dd6a786dc3d0
