{
  "id": 2768543,
  "type": "Feature",
  "properties": {
    "tgn:hierarchy":[
        "tgn:2768543",
        "tgn:1000001",
        "tgn:7012149",
        "tgn:2000387",
        "tgn:7007248",
        "tgn:7029392"
    ],
    "tgn:id":2768543,
    "tgn:name":"Whitewater Pond",
    "tgn:placetype":[
        "aat:300006191"
    ]
},
  "bbox": [],
  "geometry": {"coordinates":[-84.0667,32.3333],"type":"Point"}
}