<<<<<<< HEAD
{
  "id": 2153436,
  "type": "Feature",
  "properties": {
    "tgn:hierarchy":[
        "tgn:2153436",
        "tgn:1000001",
        "tgn:7012149",
        "tgn:2001306",
        "tgn:7007524",
        "tgn:7029392"
    ],
    "tgn:id":2153436,
    "tgn:name":"Bean Ridge",
    "tgn:placetype":[
        "aat:300266640"
    ]
},
  "bbox": [],
  "geometry": {"coordinates":[-112.9,45.85],"type":"Point"}
}
=======
{"geometry":{"type":"Point","coordinates":[-112.900000,45.850000]},"type":"Feature","properties":{"hierarchy":["tgn:2153436","tgn:1000001","tgn:7012149","tgn:2001306","tgn:7007524","tgn:7029392"],"placetype":["aat:300266640"],"id":2153436,"name:xx":"Bean Ridge"}}
>>>>>>> 03f74aca74312dbeaf24d7e61306dd6a786dc3d0
