{
  "id": 7426817,
  "type": "Feature",
  "properties": {
    "tgn:hierarchy":[
        "tgn:7426817",
        "tgn:1000001",
        "tgn:7005594",
        "tgn:7005560",
        "tgn:7029392"
    ],
    "tgn:id":7426817,
    "tgn:name":"San Jos\u00e9 de los Potreros",
    "tgn:placetype":[
        "aat:300008347"
    ]
},
  "bbox": [],
  "geometry": {"coordinates":[-101.783333,22.75],"type":"Point"}
}