{
  "id": 2586997,
  "type": "Feature",
  "properties": {
    "tgn:hierarchy":[
        "tgn:2586997",
        "tgn:1000001",
        "tgn:7012149",
        "tgn:2001879",
        "tgn:7007825",
        "tgn:7029392"
    ],
    "tgn:id":2586997,
    "tgn:name":"Plant Island",
    "tgn:placetype":[
        "aat:300386851",
        "aat:300008791"
    ]
},
  "bbox": [],
  "geometry": {"coordinates":[-87.8667,36.0167],"type":"Point"}
}