{
  "id": 2274419,
  "type": "Feature",
  "properties": {
    "tgn:hierarchy":[
        "tgn:2274419",
        "tgn:1000001",
        "tgn:7012149",
        "tgn:2001449",
        "tgn:7007566",
        "tgn:7029392"
    ],
    "tgn:id":2274419,
    "tgn:name":"Dale Tank",
    "tgn:placetype":[
        "aat:300006191"
    ]
},
  "bbox": [],
  "geometry": {"coordinates":[-106.1667,36.95],"type":"Point"}
}