{
  "id": 7463879,
  "type": "Feature",
  "properties": {
    "tgn:hierarchy":[
        "tgn:7463879",
        "tgn:7002444",
        "tgn:1000003",
        "tgn:7019152",
        "tgn:7008591",
        "tgn:7029392"
    ],
    "tgn:id":7463879,
    "tgn:name:en":"Almond, Glen",
    "tgn:placetype":[
        "aat:300008761"
    ]
},
  "bbox": [],
  "geometry": {"coordinates":[-3.883333,56.466667],"type":"Point"}
}