{
  "id": 2164752,
  "type": "Feature",
  "properties": {
    "tgn:hierarchy":[
        "tgn:2164752",
        "tgn:1000001",
        "tgn:2002324",
        "tgn:7012149",
        "tgn:7007922",
        "tgn:7029392"
    ],
    "tgn:id":2164752,
    "tgn:name":"Bertom Lake",
    "tgn:placetype":[
        "aat:300008680"
    ]
},
  "bbox": [],
  "geometry": {"coordinates":[-90.9167,42.6833],"type":"Point"}
}