{
  "id": 2143230,
  "type": "Feature",
  "properties": {
    "tgn:hierarchy":[
        "tgn:2143230",
        "tgn:1000001",
        "tgn:7012149",
        "tgn:1002358",
        "tgn:7007710",
        "tgn:7029392"
    ],
    "tgn:id":2143230,
    "tgn:name":"Bailey Brook",
    "tgn:placetype":[
        "aat:300008699"
    ]
},
  "bbox": [],
  "geometry": {"coordinates":[-79.7667,42.05],"type":"Point"}
}