{
  "id": 2234651,
  "type": "Feature",
  "properties": {
    "tgn:hierarchy":[
        "tgn:2234651",
        "tgn:1000001",
        "tgn:7012149",
        "tgn:2001854",
        "tgn:7007825",
        "tgn:7029392"
    ],
    "tgn:id":2234651,
    "tgn:name":"Cherry Branch",
    "tgn:placetype":[
        "aat:300008347"
    ]
},
  "bbox": [],
  "geometry": {"coordinates":[-84.95,35.9833],"type":"Point"}
}