{
  "id": 2216161,
  "type": "Feature",
  "properties": {
    "tgn:hierarchy":[
        "tgn:2216161",
        "tgn:7002659",
        "tgn:1000001",
        "tgn:7012149",
        "tgn:2000052",
        "tgn:7029392"
    ],
    "tgn:id":2216161,
    "tgn:name":"Camp Branch",
    "tgn:placetype":[
        "aat:300008699"
    ]
},
  "bbox": [],
  "geometry": {"coordinates":[-87.1833,32.75],"type":"Point"}
}