{
  "id": 2264071,
  "type": "Feature",
  "properties": {
    "tgn:hierarchy":[
        "tgn:2264071",
        "tgn:2000090",
        "tgn:1000001",
        "tgn:7006451",
        "tgn:7012149",
        "tgn:7029392"
    ],
    "tgn:id":2264071,
    "tgn:name":"Coyote Spring",
    "tgn:placetype":[
        "aat:300008697"
    ]
},
  "bbox": [],
  "geometry": {"coordinates":[-109.15,34.1667],"type":"Point"}
}