<<<<<<< HEAD
{
  "id": 7170358,
  "type": "Feature",
  "properties": {
    "tgn:hierarchy":[
        "tgn:7170358",
        "tgn:7003669",
        "tgn:1000003",
        "tgn:7000084",
        "tgn:7029392"
    ],
    "tgn:id":7170358,
    "tgn:name":"Hitzing",
    "tgn:placetype":[
        "aat:300008347"
    ]
},
  "bbox": [],
  "geometry": {"coordinates":[13.283333,48.633333],"type":"Point"}
}
=======
{"geometry":{"type":"Point","coordinates":[13.283333,48.633333]},"type":"Feature","properties":{"hierarchy":["tgn:7170358","tgn:7003669","tgn:1000003","tgn:7000084","tgn:7029392"],"placetype":["aat:300008347"],"id":7170358,"name:xx":"Hitzing"}}
>>>>>>> 03f74aca74312dbeaf24d7e61306dd6a786dc3d0
