{
  "id": 7492793,
  "type": "Feature",
  "properties": {
    "tgn:hierarchy":[
        "tgn:7492793",
        "tgn:1000004",
        "tgn:7471332",
        "tgn:1000141",
        "tgn:7029392"
    ],
    "tgn:id":7492793,
    "tgn:name":"Pinglin",
    "tgn:placetype":[
        "aat:300008347"
    ]
},
  "bbox": [],
  "geometry": {"coordinates":[121.14,24.801667],"type":"Point"}
}