{
  "id": 7310186,
  "type": "Feature",
  "properties": {
    "tgn:hierarchy":[
        "tgn:7310186",
        "tgn:1001692",
        "tgn:1000049",
        "tgn:1000002",
        "tgn:7029392"
    ],
    "tgn:id":7310186,
    "tgn:name":"\u00d1ipaco, Estero",
    "tgn:placetype":[
        "aat:300008699"
    ]
},
  "bbox": [],
  "geometry": {"coordinates":[-72.666667,-37.766667],"type":"Point"}
}