<<<<<<< HEAD
{
  "id": 2333533,
  "type": "Feature",
  "properties": {
    "tgn:hierarchy":[
        "tgn:2333533",
        "tgn:1000001",
        "tgn:2000668",
        "tgn:7012149",
        "tgn:7007254",
        "tgn:7029392"
    ],
    "tgn:id":2333533,
    "tgn:name":"Folsom Creek",
    "tgn:placetype":[
        "aat:300008706"
    ]
},
  "bbox": [],
  "geometry": {"coordinates":[-96.6667,38.2667],"type":"Point"}
}
=======
{"geometry":{"type":"Point","coordinates":[-96.666700,38.266700]},"type":"Feature","properties":{"hierarchy":["tgn:2333533","tgn:1000001","tgn:2000668","tgn:7012149","tgn:7007254","tgn:7029392"],"placetype":["aat:300008706"],"id":2333533,"name:xx":"Folsom Creek"}}
>>>>>>> 03f74aca74312dbeaf24d7e61306dd6a786dc3d0
