{
  "id": 2514528,
  "type": "Feature",
  "properties": {
    "tgn:hierarchy":[
        "tgn:2514528",
        "tgn:1000001",
        "tgn:7012149",
        "tgn:2001713",
        "tgn:7007708",
        "tgn:7029392"
    ],
    "tgn:id":2514528,
    "tgn:name":"Miller Gulch",
    "tgn:placetype":[
        "aat:300008761"
    ]
},
  "bbox": [],
  "geometry": {"coordinates":[-123.3333,42.65],"type":"Point"}
}