{
  "id": 7442916,
  "type": "Feature",
  "properties": {
    "tgn:hierarchy":[
        "tgn:7442916",
        "tgn:7002445",
        "tgn:7019069",
        "tgn:1000003",
        "tgn:7012033",
        "tgn:7008591",
        "tgn:7029392"
    ],
    "tgn:id":7442916,
    "tgn:name:en":"White Stones",
    "tgn:placetype":[
        "aat:300008808"
    ]
},
  "bbox": [],
  "geometry": {"coordinates":[-1.329444,54.893611],"type":"Point"}
}