{
  "id": 7417994,
  "type": "Feature",
  "properties": {
    "tgn:hierarchy":[
        "tgn:7417994",
        "tgn:1000001",
        "tgn:7005591",
        "tgn:7005560",
        "tgn:7029392"
    ],
    "tgn:id":7417994,
    "tgn:name:es":"Saucitl\u00e1n",
    "tgn:placetype":[
        "aat:300008347"
    ]
},
  "bbox": [],
  "geometry": {"coordinates":[-97.826667,17.781111],"type":"Point"}
}