{
  "id": 2012576,
  "type": "Feature",
  "properties": {
    "tgn:hierarchy":[
        "tgn:2012576",
        "tgn:1000001",
        "tgn:7012149",
        "tgn:7007157",
        "tgn:1002608",
        "tgn:7013987",
        "tgn:7029392"
    ],
    "tgn:id":2012576,
    "tgn:name":"Topanga Beach",
    "tgn:placetype":[
        "aat:300008347"
    ]
},
  "bbox": [],
  "geometry": {"coordinates":[-118.5667,34.0333],"type":"Point"}
}