{
  "id": 7495711,
  "type": "Feature",
  "properties": {
    "tgn:hierarchy":[
        "tgn:7495711",
        "tgn:7468018",
        "tgn:1000004",
        "tgn:1000141",
        "tgn:7029392"
    ],
    "tgn:id":7495711,
    "tgn:name":"Zhonglun Sanhao Qiao",
    "tgn:placetype":[
        "aat:300007836"
    ]
},
  "bbox": [],
  "geometry": {"coordinates":[120.561906,23.375026],"type":"Point"}
}