{
  "id": 2358434,
  "type": "Feature",
  "properties": {
    "tgn:hierarchy":[
        "tgn:2358434",
        "tgn:2000943",
        "tgn:1000001",
        "tgn:7012149",
        "tgn:7007520",
        "tgn:7029392"
    ],
    "tgn:id":2358434,
    "tgn:name":"Grand Sable Dunes",
    "tgn:placetype":[
        "aat:300008798"
    ]
},
  "bbox": [],
  "geometry": {"coordinates":[-86.05,46.65],"type":"Point"}
}