{
  "id": 2090168,
  "type": "Feature",
  "properties": {
    "tgn:hierarchy":[
        "tgn:2090168",
        "tgn:1000001",
        "tgn:1002213",
        "tgn:7012149",
        "tgn:7007710",
        "tgn:7029392"
    ],
    "tgn:id":2090168,
    "tgn:name":"Lincoln Plaza",
    "tgn:placetype":[
        "aat:300247594"
    ]
},
  "bbox": [],
  "geometry": {"coordinates":[-74.8667,40.1667],"type":"Point"}
}