{
  "id": 2474060,
  "type": "Feature",
  "properties": {
    "tgn:hierarchy":[
        "tgn:2474060",
        "tgn:1002166",
        "tgn:1000001",
        "tgn:7012149",
        "tgn:7007520",
        "tgn:7029392"
    ],
    "tgn:id":2474060,
    "tgn:name":"Lower Lake",
    "tgn:placetype":[
        "aat:300008680"
    ]
},
  "bbox": [],
  "geometry": {"coordinates":[-85.2333,42.6833],"type":"Point"}
}