{
  "id": 2717186,
  "type": "Feature",
  "properties": {
    "tgn:hierarchy":[
        "tgn:2717186",
        "tgn:1000001",
        "tgn:7012149",
        "tgn:2001998",
        "tgn:7007826",
        "tgn:7029392"
    ],
    "tgn:id":2717186,
    "tgn:name":"Third Mound",
    "tgn:placetype":[
        "aat:300008798"
    ]
},
  "bbox": [],
  "geometry": {"coordinates":[-99.6167,34.1833],"type":"Point"}
}