{
  "id": 7151891,
  "type": "Feature",
  "properties": {
    "tgn:hierarchy":[
        "tgn:7151891",
        "tgn:1000003",
        "tgn:7003684",
        "tgn:7000084",
        "tgn:7029392"
    ],
    "tgn:id":7151891,
    "tgn:name":"Kahlenberg",
    "tgn:placetype":[
        "aat:300008777"
    ]
},
  "bbox": [],
  "geometry": {"coordinates":[7.15,49.266667],"type":"Point"}
}