{
  "id": 1057384,
  "type": "Feature",
  "properties": {
    "tgn:hierarchy":[
        "tgn:1057384",
        "tgn:7011551",
        "tgn:1000004",
        "tgn:7018214",
        "tgn:7002435",
        "tgn:7029392"
    ],
    "tgn:id":1057384,
    "tgn:name":"Nemeri\u010di",
    "tgn:placetype":[
        "aat:300008347"
    ]
},
  "bbox": [],
  "geometry": {"coordinates":[33.9833,53.85],"type":"Point"}
}