{
  "id": 7234553,
  "type": "Feature",
  "properties": {
    "tgn:hierarchy":[
        "tgn:7234553",
        "tgn:7002725",
        "tgn:7002715",
        "tgn:1000003",
        "tgn:1000074",
        "tgn:7029392"
    ],
    "tgn:id":7234553,
    "tgn:name":"Sidirodromik\u00f3s Stathm\u00f3s \u00c1sprou",
    "tgn:placetype":[
        "aat:300007783"
    ]
},
  "bbox": [],
  "geometry": {"coordinates":[22.649444,40.887778],"type":"Point"}
}