{
  "id": 1116370,
  "type": "Feature",
  "properties": {
    "tgn:hierarchy":[
        "tgn:1116370",
        "tgn:7001198",
        "tgn:7003482",
        "tgn:1000003",
        "tgn:1000078",
        "tgn:7029392"
    ],
    "tgn:id":1116370,
    "tgn:name":"Gara, Lough",
    "tgn:placetype":[
        "aat:300008680"
    ]
},
  "bbox": [],
  "geometry": {"coordinates":[-8.4167,53.9167],"type":"Point"}
}