{
  "id": 7554825,
  "type": "Feature",
  "properties": {
    "tgn:hierarchy":[
        "tgn:7554825",
        "tgn:1000004",
        "tgn:7000198",
        "tgn:7016694",
        "tgn:7029392"
    ],
    "tgn:id":7554825,
    "tgn:name:en":"Maipura Nad\u012b",
    "tgn:placetype":[
        "aat:300008699"
    ]
},
  "bbox": [],
  "geometry": {"coordinates":[86.99832,20.705695],"type":"Point"}
}