<<<<<<< HEAD
{
  "id": 7243062,
  "type": "Feature",
  "properties": {
    "tgn:hierarchy":[
        "tgn:7243062",
        "tgn:7003466",
        "tgn:1000003",
        "tgn:1000063",
        "tgn:4012014",
        "tgn:7029392"
    ],
    "tgn:id":7243062,
    "tgn:name":"Les Cul\u00e9es",
    "tgn:placetype":[
        "aat:300008347"
    ]
},
  "bbox": [],
  "geometry": {"coordinates":[5.15,50.266667],"type":"Point"}
}
=======
{"geometry":{"type":"Point","coordinates":[5.150000,50.266667]},"type":"Feature","properties":{"hierarchy":["tgn:7243062","tgn:7003466","tgn:1000003","tgn:1000063","tgn:4012014","tgn:7029392"],"placetype":["aat:300008347"],"id":7243062,"name:xx":"Les Cul\u00e9es"}}
>>>>>>> 03f74aca74312dbeaf24d7e61306dd6a786dc3d0
