{
  "id": 2412452,
  "type": "Feature",
  "properties": {
    "tgn:hierarchy":[
        "tgn:2412452",
        "tgn:1000001",
        "tgn:7012149",
        "tgn:7007158",
        "tgn:7029392"
    ],
    "tgn:id":2412452,
    "tgn:name":"Indian Trail Ridge",
    "tgn:placetype":[
        "aat:300266640"
    ]
},
  "bbox": [],
  "geometry": {"coordinates":[-108.0333,37.4833],"type":"Point"}
}