{
  "id": 7122294,
  "type": "Feature",
  "properties": {
    "tgn:hierarchy":[
        "tgn:7122294",
        "tgn:1000003",
        "tgn:7003688",
        "tgn:7000084",
        "tgn:7029392"
    ],
    "tgn:id":7122294,
    "tgn:name":"Neuwerk",
    "tgn:placetype":[
        "aat:300000206"
    ]
},
  "bbox": [],
  "geometry": {"coordinates":[8.766667,54.783333],"type":"Point"}
}