{
  "id": 2390490,
  "type": "Feature",
  "properties": {
    "tgn:hierarchy":[
        "tgn:2390490",
        "tgn:1000001",
        "tgn:2001480",
        "tgn:7012149",
        "tgn:7007709",
        "tgn:7029392"
    ],
    "tgn:id":2390490,
    "tgn:name":"Highland Pond",
    "tgn:placetype":[
        "aat:300008680"
    ]
},
  "bbox": [],
  "geometry": {"coordinates":[-79.05,35.8333],"type":"Point"}
}