{
  "id": 7592275,
  "type": "Feature",
  "properties": {
    "tgn:hierarchy":[
        "tgn:7592275",
        "tgn:1000004",
        "tgn:7000198",
        "tgn:7000799",
        "tgn:7029392"
    ],
    "tgn:id":7592275,
    "tgn:name:en":"Latori",
    "tgn:placetype":[
        "aat:300008347"
    ]
},
  "bbox": [],
  "geometry": {"coordinates":[74.919979,32.968245],"type":"Point"}
}