{
  "id": 2463969,
  "type": "Feature",
  "properties": {
    "tgn:hierarchy":[
        "tgn:2463969",
        "tgn:1000001",
        "tgn:7012149",
        "tgn:1002986",
        "tgn:7007568",
        "tgn:7029392"
    ],
    "tgn:id":2463969,
    "tgn:name":"Lockwood Swamp",
    "tgn:placetype":[
        "aat:300008905"
    ]
},
  "bbox": [],
  "geometry": {"coordinates":[-73.8167,43.4333],"type":"Point"}
}