<<<<<<< HEAD
{
  "id": 2335985,
  "type": "Feature",
  "properties": {
    "tgn:hierarchy":[
        "tgn:2335985",
        "tgn:1000001",
        "tgn:7012149",
        "tgn:1002623",
        "tgn:7007252",
        "tgn:7029392"
    ],
    "tgn:id":2335985,
    "tgn:name":"Foster Branch",
    "tgn:placetype":[
        "aat:300008699"
    ]
},
  "bbox": [],
  "geometry": {"coordinates":[-85.7333,40.05],"type":"Point"}
}
=======
{"geometry":{"type":"Point","coordinates":[-85.733300,40.050000]},"type":"Feature","properties":{"hierarchy":["tgn:2335985","tgn:1000001","tgn:7012149","tgn:1002623","tgn:7007252","tgn:7029392"],"placetype":["aat:300008699"],"id":2335985,"name:xx":"Foster Branch"}}
>>>>>>> 03f74aca74312dbeaf24d7e61306dd6a786dc3d0
