{
  "id": 2198030,
  "type": "Feature",
  "properties": {
    "tgn:hierarchy":[
        "tgn:2198030",
        "tgn:1000001",
        "tgn:2000464",
        "tgn:7012149",
        "tgn:7007250",
        "tgn:7029392"
    ],
    "tgn:id":2198030,
    "tgn:name":"Brownell Spring",
    "tgn:placetype":[
        "aat:300008697"
    ]
},
  "bbox": [],
  "geometry": {"coordinates":[-114.9333,43.2667],"type":"Point"}
}