{
  "id": 7519093,
  "type": "Feature",
  "properties": {
    "tgn:hierarchy":[
        "tgn:7519093",
        "tgn:1008380",
        "tgn:7520093",
        "tgn:1000226",
        "tgn:1000006",
        "tgn:7029392"
    ],
    "tgn:id":7519093,
    "tgn:name:en":"Aramahoe",
    "tgn:placetype":[
        "aat:300008795"
    ]
},
  "bbox": [],
  "geometry": {"coordinates":[175.216667,-38.85],"type":"Point"}
}