{
  "id": 2085700,
  "type": "Feature",
  "properties": {
    "tgn:hierarchy":[
        "tgn:2085700",
        "tgn:1000001",
        "tgn:1002293",
        "tgn:7012149",
        "tgn:7007708",
        "tgn:7029392"
    ],
    "tgn:id":2085700,
    "tgn:name":"Vernonia",
    "tgn:placetype":[
        "aat:300008347"
    ]
},
  "bbox": [],
  "geometry": {"coordinates":[-123.1833,45.85],"type":"Point"}
}