{
  "id": 1011782,
  "type": "Feature",
  "properties": {
    "tgn:hierarchy":[
        "tgn:1011782",
        "tgn:1000003",
        "tgn:7002893",
        "tgn:1000070",
        "tgn:7029392"
    ],
    "tgn:id":1011782,
    "tgn:name":"Croisic, Pointe du",
    "tgn:placetype":[
        "aat:300386846"
    ]
},
  "bbox": [],
  "geometry": {"coordinates":[-2.55,47.2833],"type":"Point"}
}