{
  "id": 2262478,
  "type": "Feature",
  "properties": {
    "tgn:hierarchy":[
        "tgn:2262478",
        "tgn:1000001",
        "tgn:7012149",
        "tgn:1002881",
        "tgn:7007240",
        "tgn:7029392"
    ],
    "tgn:id":2262478,
    "tgn:name":"Cow Island",
    "tgn:placetype":[
        "aat:300008791"
    ]
},
  "bbox": [],
  "geometry": {"coordinates":[-81.0333,28.7167],"type":"Point"}
}