{
  "id": 7443030,
  "type": "Feature",
  "properties": {
    "tgn:hierarchy":[
        "tgn:7443030",
        "tgn:7002445",
        "tgn:1000003",
        "tgn:7019054",
        "tgn:7008591",
        "tgn:7029392"
    ],
    "tgn:id":7443030,
    "tgn:name:en":"Thornton Abbey",
    "tgn:placetype":[
        "aat:300007783"
    ]
},
  "bbox": [],
  "geometry": {"coordinates":[-0.316667,53.65],"type":"Point"}
}