{
  "id": 2580064,
  "type": "Feature",
  "properties": {
    "tgn:hierarchy":[
        "tgn:2580064",
        "tgn:1000001",
        "tgn:7012149",
        "tgn:7007157",
        "tgn:1002566",
        "tgn:7029392"
    ],
    "tgn:id":2580064,
    "tgn:name":"Pierce Canyon",
    "tgn:placetype":[
        "aat:300008761"
    ]
},
  "bbox": [],
  "geometry": {"coordinates":[-122.7333,39.0667],"type":"Point"}
}