{
  "id": 7379406,
  "type": "Feature",
  "properties": {
    "tgn:hierarchy":[
        "tgn:7379406",
        "tgn:1000001",
        "tgn:7005594",
        "tgn:7005560",
        "tgn:7029392"
    ],
    "tgn:id":7379406,
    "tgn:name":"Micos",
    "tgn:placetype":[
        "aat:300008347"
    ]
},
  "bbox": [],
  "geometry": {"coordinates":[-99.25,22.183333],"type":"Point"}
}