{
  "id": 7379108,
  "type": "Feature",
  "properties": {
    "tgn:hierarchy":[
        "tgn:7379108",
        "tgn:1000001",
        "tgn:1001960",
        "tgn:7005560",
        "tgn:7029392"
    ],
    "tgn:id":7379108,
    "tgn:name":"Los Chirriones",
    "tgn:placetype":[
        "aat:300008347"
    ]
},
  "bbox": [],
  "geometry": {"coordinates":[-111.416667,31.016667],"type":"Point"}
}