{
  "id": 2739358,
  "type": "Feature",
  "properties": {
    "tgn:hierarchy":[
        "tgn:2739358",
        "tgn:1000001",
        "tgn:7006451",
        "tgn:2000092",
        "tgn:7012149",
        "tgn:7029392"
    ],
    "tgn:id":2739358,
    "tgn:name":"Upper Basin",
    "tgn:placetype":[
        "aat:300386845"
    ]
},
  "bbox": [],
  "geometry": {"coordinates":[-111.8167,35.9333],"type":"Point"}
}