{
  "id": 1105859,
  "type": "Feature",
  "properties": {
    "tgn:hierarchy":[
        "tgn:1105859",
        "tgn:1000004",
        "tgn:7029392"
    ],
    "tgn:id":1105859,
    "tgn:name":"Nowsh\u0101k",
    "tgn:placetype":[
        "aat:300008795"
    ]
},
  "bbox": [],
  "geometry": {"coordinates":[71.8333,36.4333],"type":"Point"}
}