{
  "id": 7464726,
  "type": "Feature",
  "properties": {
    "tgn:hierarchy":[
        "tgn:7464726",
        "tgn:7002445",
        "tgn:1000003",
        "tgn:7008139",
        "tgn:7008591",
        "tgn:7029392"
    ],
    "tgn:id":7464726,
    "tgn:name:en":"Avon, River",
    "tgn:placetype":[
        "aat:300008699"
    ]
},
  "bbox": [],
  "geometry": {"coordinates":[-1.766667,50.733333],"type":"Point"}
}