{
  "id": 7447214,
  "type": "Feature",
  "properties": {
    "tgn:hierarchy":[
        "tgn:7447214",
        "tgn:7002444",
        "tgn:1000003",
        "tgn:7008082",
        "tgn:7008591",
        "tgn:7029392"
    ],
    "tgn:id":7447214,
    "tgn:name:en":"Raplaich, Sithean na",
    "tgn:placetype":[
        "aat:300008795"
    ]
},
  "bbox": [],
  "geometry": {"coordinates":[-5.85,56.583333],"type":"Point"}
}