{
  "id": 7505569,
  "type": "Feature",
  "properties": {
    "tgn:hierarchy":[
        "tgn:7505569",
        "tgn:1008380",
        "tgn:7000507",
        "tgn:1000226",
        "tgn:1000006",
        "tgn:7029392"
    ],
    "tgn:id":7505569,
    "tgn:name:en":"Whangaruru South",
    "tgn:placetype":[
        "aat:300008347"
    ]
},
  "bbox": [],
  "geometry": {"coordinates":[174.35,-35.383333],"type":"Point"}
}