{
  "id": 2707197,
  "type": "Feature",
  "properties": {
    "tgn:hierarchy":[
        "tgn:2707197",
        "tgn:1000001",
        "tgn:7012149",
        "tgn:1002520",
        "tgn:7007710",
        "tgn:7029392"
    ],
    "tgn:id":2707197,
    "tgn:name":"Swede Run",
    "tgn:placetype":[
        "aat:300008699"
    ]
},
  "bbox": [],
  "geometry": {"coordinates":[-78.8833,41.2833],"type":"Point"}
}