{
  "id": 7257834,
  "type": "Feature",
  "properties": {
    "tgn:concordances":{
        "gn:id":"2760119"
    },
    "tgn:hierarchy":[
        "tgn:7257834",
        "tgn:7003619",
        "tgn:1000003",
        "tgn:7016845",
        "tgn:7029392"
    ],
    "tgn:id":7257834,
    "tgn:name:nl":"Aam",
    "tgn:placetype":[
        "aat:300008347"
    ]
},
  "bbox": [],
  "geometry": {"coordinates":[5.866667,51.916667],"type":"Point"}
}