{
  "id": 2750282,
  "type": "Feature",
  "properties": {
    "tgn:hierarchy":[
        "tgn:2750282",
        "tgn:1000001",
        "tgn:2001416",
        "tgn:7012149",
        "tgn:7007526",
        "tgn:7029392"
    ],
    "tgn:id":2750282,
    "tgn:name":"Wambolt Creek",
    "tgn:placetype":[
        "aat:300008706"
    ]
},
  "bbox": [],
  "geometry": {"coordinates":[-114.7167,38.65],"type":"Point"}
}