{
  "id": 7185662,
  "type": "Feature",
  "properties": {
    "tgn:hierarchy":[
        "tgn:7185662",
        "tgn:1000003",
        "tgn:7003689",
        "tgn:7000084",
        "tgn:7029392"
    ],
    "tgn:id":7185662,
    "tgn:name":"Gleina",
    "tgn:placetype":[
        "aat:300008347"
    ]
},
  "bbox": [],
  "geometry": {"coordinates":[11.983333,50.933333],"type":"Point"}
}