{
  "id": 2441624,
  "type": "Feature",
  "properties": {
    "tgn:hierarchy":[
        "tgn:2441624",
        "tgn:1000001",
        "tgn:7006451",
        "tgn:7012149",
        "tgn:2000101",
        "tgn:7029392"
    ],
    "tgn:id":2441624,
    "tgn:name":"Kohatk Valley",
    "tgn:placetype":[
        "aat:300008761"
    ]
},
  "bbox": [],
  "geometry": {"coordinates":[-112.1833,32.5833],"type":"Point"}
}