{
  "id": 7343425,
  "type": "Feature",
  "properties": {
    "tgn:hierarchy":[
        "tgn:7343425",
        "tgn:7008912",
        "tgn:7030216",
        "tgn:1000003",
        "tgn:1000095",
        "tgn:7029392"
    ],
    "tgn:id":7343425,
    "tgn:name":"Cad\u00ed, Sierra del",
    "tgn:placetype":[
        "aat:300008795"
    ]
},
  "bbox": [],
  "geometry": {"coordinates":[1.727054,42.283547],"type":"Point"}
}