{
  "id": 7533308,
  "type": "Feature",
  "properties": {
    "tgn:hierarchy":[
        "tgn:7533308",
        "tgn:7001242",
        "tgn:7001311",
        "tgn:7016833",
        "tgn:7029392"
    ],
    "tgn:id":7533308,
    "tgn:name:en":"\u1e28amad\u0101t, Jabal",
    "tgn:placetype":[
        "aat:300008795"
    ]
},
  "bbox": [],
  "geometry": {"coordinates":[34.16329,25.983241],"type":"Point"}
}