{
  "id": 2172122,
  "type": "Feature",
  "properties": {
    "tgn:hierarchy":[
        "tgn:2172122",
        "tgn:1000001",
        "tgn:2002146",
        "tgn:7012149",
        "tgn:7007919",
        "tgn:7029392"
    ],
    "tgn:id":2172122,
    "tgn:name":"Biggs Run",
    "tgn:placetype":[
        "aat:300008699"
    ]
},
  "bbox": [],
  "geometry": {"coordinates":[-79.9667,37.65],"type":"Point"}
}