{
  "id": 2514077,
  "type": "Feature",
  "properties": {
    "tgn:hierarchy":[
        "tgn:2514077",
        "tgn:1000001",
        "tgn:7012149",
        "tgn:1002557",
        "tgn:7007252",
        "tgn:7029392"
    ],
    "tgn:id":2514077,
    "tgn:name":"Miller Arm",
    "tgn:placetype":[
        "aat:300006075"
    ]
},
  "bbox": [],
  "geometry": {"coordinates":[-85.9667,41.2833],"type":"Point"}
}