{
  "id": 7318077,
  "type": "Feature",
  "properties": {
    "tgn:hierarchy":[
        "tgn:7318077",
        "tgn:1001630",
        "tgn:1000049",
        "tgn:1000002",
        "tgn:7029392"
    ],
    "tgn:id":7318077,
    "tgn:name":"Corrales, Caleta",
    "tgn:placetype":[
        "aat:300132317"
    ]
},
  "bbox": [],
  "geometry": {"coordinates":[-71.15,-27.983333],"type":"Point"}
}