{
  "id": 2256914,
  "type": "Feature",
  "properties": {
    "tgn:hierarchy":[
        "tgn:2256914",
        "tgn:1000001",
        "tgn:7012149",
        "tgn:2001461",
        "tgn:7007568",
        "tgn:7029392"
    ],
    "tgn:id":2256914,
    "tgn:name":"Corliss Mountain",
    "tgn:placetype":[
        "aat:300008798"
    ]
},
  "bbox": [],
  "geometry": {"coordinates":[-73.75,44.25],"type":"Point"}
}