{
  "id": 2084746,
  "type": "Feature",
  "properties": {
    "tgn:hierarchy":[
        "tgn:2084746",
        "tgn:1000001",
        "tgn:7012149",
        "tgn:1002699",
        "tgn:7007708",
        "tgn:7029392"
    ],
    "tgn:id":2084746,
    "tgn:name":"Fir",
    "tgn:placetype":[
        "aat:300387016"
    ]
},
  "bbox": [],
  "geometry": {"coordinates":[-122.5833,45.55],"type":"Point"}
}