{
  "id": 7510581,
  "type": "Feature",
  "properties": {
    "tgn:hierarchy":[
        "tgn:7510581",
        "tgn:1008380",
        "tgn:1000226",
        "tgn:7016827",
        "tgn:1000006",
        "tgn:7029392"
    ],
    "tgn:id":7510581,
    "tgn:name:en":"Uia",
    "tgn:placetype":[
        "aat:300008347"
    ]
},
  "bbox": [],
  "geometry": {"coordinates":[174.233333,-39.283333],"type":"Point"}
}