<<<<<<< HEAD
{
  "id": 2760100,
  "type": "Feature",
  "properties": {
    "tgn:hierarchy":[
        "tgn:2760100",
        "tgn:1000001",
        "tgn:7012149",
        "tgn:2000481",
        "tgn:7007250",
        "tgn:7029392"
    ],
    "tgn:id":2760100,
    "tgn:name":"West Fork Perreau Creek",
    "tgn:placetype":[
        "aat:300008706"
    ]
},
  "bbox": [],
  "geometry": {"coordinates":[-114.05,45.1167],"type":"Point"}
}
=======
{"geometry":{"type":"Point","coordinates":[-114.050000,45.116700]},"type":"Feature","properties":{"hierarchy":["tgn:2760100","tgn:1000001","tgn:7012149","tgn:2000481","tgn:7007250","tgn:7029392"],"placetype":["aat:300008706"],"id":2760100,"name:xx":"West Fork Perreau Creek"}}
>>>>>>> 03f74aca74312dbeaf24d7e61306dd6a786dc3d0
