{
  "id": 7173395,
  "type": "Feature",
  "properties": {
    "tgn:hierarchy":[
        "tgn:7173395",
        "tgn:1000003",
        "tgn:7000094",
        "tgn:7000084",
        "tgn:7029392"
    ],
    "tgn:id":7173395,
    "tgn:name":"Gro\u00df Rederank",
    "tgn:placetype":[
        "aat:300008680"
    ]
},
  "bbox": [],
  "geometry": {"coordinates":[12.316667,53.566667],"type":"Point"}
}