{
  "id": 7555871,
  "type": "Feature",
  "properties": {
    "tgn:hierarchy":[
        "tgn:7555871",
        "tgn:7016678",
        "tgn:7000204",
        "tgn:1000004",
        "tgn:7000198",
        "tgn:7029392"
    ],
    "tgn:id":7555871,
    "tgn:name:en":"Perseus Reef",
    "tgn:placetype":[
        "aat:300008808"
    ]
},
  "bbox": [],
  "geometry": {"coordinates":[93.416667,8.183333],"type":"Point"}
}