{
  "id": 7303250,
  "type": "Feature",
  "properties": {
    "tgn:hierarchy":[
        "tgn:7303250",
        "tgn:7002825",
        "tgn:7016622",
        "tgn:1000003",
        "tgn:1000095",
        "tgn:7029392"
    ],
    "tgn:id":7303250,
    "tgn:name":"Mozos, Playa de los",
    "tgn:placetype":[
        "aat:300008816"
    ]
},
  "bbox": [],
  "geometry": {"coordinates":[-14.083333,28.483333],"type":"Point"}
}