{
  "id": 7570107,
  "type": "Feature",
  "properties": {
    "tgn:hierarchy":[
        "tgn:7570107",
        "tgn:1000004",
        "tgn:7000198",
        "tgn:7016788",
        "tgn:7029392"
    ],
    "tgn:id":7570107,
    "tgn:name:en":"Jaithal",
    "tgn:placetype":[
        "aat:300008347"
    ]
},
  "bbox": [],
  "geometry": {"coordinates":[75.604591,25.990593],"type":"Point"}
}