{
  "id": 7510132,
  "type": "Feature",
  "properties": {
    "tgn:hierarchy":[
        "tgn:7510132",
        "tgn:1009227",
        "tgn:1000226",
        "tgn:7018437",
        "tgn:1000006",
        "tgn:7029392"
    ],
    "tgn:id":7510132,
    "tgn:name:en":"Station Creek",
    "tgn:placetype":[
        "aat:300008699"
    ]
},
  "bbox": [],
  "geometry": {"coordinates":[169.516667,-44.65],"type":"Point"}
}