{
  "id": 7464123,
  "type": "Feature",
  "properties": {
    "tgn:hierarchy":[
        "tgn:7464123",
        "tgn:7002445",
        "tgn:1000003",
        "tgn:7008185",
        "tgn:7008591",
        "tgn:7029392"
    ],
    "tgn:id":7464123,
    "tgn:name:en":"Aldringham",
    "tgn:placetype":[
        "aat:300008347"
    ]
},
  "bbox": [],
  "geometry": {"coordinates":[1.583333,52.183333],"type":"Point"}
}