{
  "id": 2295429,
  "type": "Feature",
  "properties": {
    "tgn:hierarchy":[
        "tgn:2295429",
        "tgn:1000001",
        "tgn:7012149",
        "tgn:2000550",
        "tgn:7007252",
        "tgn:7029392"
    ],
    "tgn:id":2295429,
    "tgn:name":"Drinkwater Hill",
    "tgn:placetype":[
        "aat:300008798"
    ]
},
  "bbox": [],
  "geometry": {"coordinates":[-86.6167,37.8667],"type":"Point"}
}