{
  "id": 2363944,
  "type": "Feature",
  "properties": {
    "tgn:hierarchy":[
        "tgn:2363944",
        "tgn:1000001",
        "tgn:2001185",
        "tgn:7012149",
        "tgn:7007523",
        "tgn:7029392"
    ],
    "tgn:id":2363944,
    "tgn:name":"Green Mound Ridge",
    "tgn:placetype":[
        "aat:300266640"
    ]
},
  "bbox": [],
  "geometry": {"coordinates":[-93.2333,36.8833],"type":"Point"}
}