{
  "id": 2569347,
  "type": "Feature",
  "properties": {
    "tgn:hierarchy":[
        "tgn:2569347",
        "tgn:1000001",
        "tgn:7012149",
        "tgn:7007158",
        "tgn:2000250",
        "tgn:7029392"
    ],
    "tgn:id":2569347,
    "tgn:name":"Parkville",
    "tgn:placetype":[
        "aat:300008347"
    ]
},
  "bbox": [],
  "geometry": {"coordinates":[-106.9333,39.4833],"type":"Point"}
}