{
  "id": 7551680,
  "type": "Feature",
  "properties": {
    "tgn:hierarchy":[
        "tgn:7551680",
        "tgn:1000004",
        "tgn:1001869",
        "tgn:7000198",
        "tgn:7029392"
    ],
    "tgn:id":7551680,
    "tgn:name:en":"Bore Rocks",
    "tgn:placetype":[
        "aat:300011692"
    ]
},
  "bbox": [],
  "geometry": {"coordinates":[72.416667,22.183333],"type":"Point"}
}