{
  "id": 1017657,
  "type": "Feature",
  "properties": {
    "tgn:hierarchy":[
        "tgn:1017657",
        "tgn:1000001",
        "tgn:7005601",
        "tgn:7005560",
        "tgn:7029392"
    ],
    "tgn:id":1017657,
    "tgn:name":"Juan Aldama",
    "tgn:placetype":[
        "aat:300008347"
    ]
},
  "bbox": [],
  "geometry": {"coordinates":[-103.394444,24.290833],"type":"Point"}
}