{
  "id": 7002475,
  "type": "Feature",
  "properties": {
    "tgn:hierarchy":[
        "tgn:7002475",
        "tgn:1001052",
        "tgn:1000004",
        "tgn:7002473",
        "tgn:7018450",
        "tgn:1000144",
        "tgn:7029392"
    ],
    "tgn:id":7002475,
    "tgn:name":"Galata",
    "tgn:placetype":[
        "aat:300000745"
    ]
},
  "bbox": [],
  "geometry": {"coordinates":[28.95,41.0167],"type":"Point"}
}