<<<<<<< HEAD
{
  "id": 7022901,
  "type": "Feature",
  "properties": {
    "tgn:hierarchy":[
        "tgn:7022901",
        "tgn:1000001",
        "tgn:7012149",
        "tgn:7029392"
    ],
    "tgn:id":7022901,
    "tgn:name":"Round Top Brook",
    "tgn:placetype":[
        "aat:300008699"
    ]
},
  "bbox": [],
  "geometry": {"coordinates":[-71.7,42.0167],"type":"Point"}
}
=======
{"geometry":{"type":"Point","coordinates":[-71.700000,42.016700]},"type":"Feature","properties":{"hierarchy":["tgn:7022901","tgn:1000001","tgn:7012149","tgn:7029392"],"placetype":["aat:300008699"],"id":7022901,"name:xx":"Round Top Brook"}}
>>>>>>> 03f74aca74312dbeaf24d7e61306dd6a786dc3d0
