{
  "id": 2119619,
  "type": "Feature",
  "properties": {
    "tgn:hierarchy":[
        "tgn:2119619",
        "tgn:1000001",
        "tgn:7012149",
        "tgn:2002277",
        "tgn:7013961",
        "tgn:7029392"
    ],
    "tgn:id":2119619,
    "tgn:name":"Point Pleasant",
    "tgn:placetype":[
        "aat:300008347"
    ]
},
  "bbox": [],
  "geometry": {"coordinates":[-82.1333,38.8333],"type":"Point"}
}