{
  "id": 2534987,
  "type": "Feature",
  "properties": {
    "tgn:hierarchy":[
        "tgn:2534987",
        "tgn:7023902",
        "tgn:1000001",
        "tgn:7012149",
        "tgn:7007249",
        "tgn:7029392"
    ],
    "tgn:id":2534987,
    "tgn:name":"Naluea Stream",
    "tgn:placetype":[
        "aat:300008699"
    ]
},
  "bbox": [],
  "geometry": {"coordinates":[-155.6333,20.1167],"type":"Point"}
}