<<<<<<< HEAD
{
  "id": 7485561,
  "type": "Feature",
  "properties": {
    "tgn:hierarchy":[
        "tgn:7485561",
        "tgn:1000004",
        "tgn:7467799",
        "tgn:1000141",
        "tgn:7029392"
    ],
    "tgn:id":7485561,
    "tgn:name":"Diyi Maiyucuo Ciao",
    "tgn:placetype":[
        "aat:300007836"
    ]
},
  "bbox": [],
  "geometry": {"coordinates":[120.4,24.019722],"type":"Point"}
}
=======
{"geometry":{"type":"Point","coordinates":[120.400000,24.019722]},"type":"Feature","properties":{"hierarchy":["tgn:7485561","tgn:1000004","tgn:7467799","tgn:1000141","tgn:7029392"],"placetype":["aat:300007836"],"id":7485561,"name:xx":"Diyi Maiyucuo Ciao"}}
>>>>>>> 03f74aca74312dbeaf24d7e61306dd6a786dc3d0
