{
  "id": 2269428,
  "type": "Feature",
  "properties": {
    "tgn:hierarchy":[
        "tgn:2269428",
        "tgn:7006450",
        "tgn:1000001",
        "tgn:7012149",
        "tgn:2124005",
        "tgn:7029392"
    ],
    "tgn:id":2269428,
    "tgn:name":"Crow Nest Rock",
    "tgn:placetype":[
        "aat:300008798"
    ]
},
  "bbox": [],
  "geometry": {"coordinates":[-146.0667,68.0833],"type":"Point"}
}