{
  "id": 2219469,
  "type": "Feature",
  "properties": {
    "tgn:hierarchy":[
        "tgn:2219469",
        "tgn:1000001",
        "tgn:7012149",
        "tgn:2001274",
        "tgn:7007524",
        "tgn:7029392"
    ],
    "tgn:id":2219469,
    "tgn:name":"Cannon, Mount",
    "tgn:placetype":[
        "aat:300008798"
    ]
},
  "bbox": [],
  "geometry": {"coordinates":[-113.7667,48.6833],"type":"Point"}
}