{
  "id": 2532532,
  "type": "Feature",
  "properties": {
    "tgn:hierarchy":[
        "tgn:2532532",
        "tgn:1000001",
        "tgn:7012149",
        "tgn:2000492",
        "tgn:7007250",
        "tgn:7029392"
    ],
    "tgn:id":2532532,
    "tgn:name":"Murphy Creek",
    "tgn:placetype":[
        "aat:300008706"
    ]
},
  "bbox": [],
  "geometry": {"coordinates":[-111.15,43.5333],"type":"Point"}
}