{
  "id": 2682974,
  "type": "Feature",
  "properties": {
    "tgn:hierarchy":[
        "tgn:2682974",
        "tgn:1000001",
        "tgn:7012149",
        "tgn:1002553",
        "tgn:7007920",
        "tgn:7029392"
    ],
    "tgn:id":2682974,
    "tgn:name":"Spade Creek",
    "tgn:placetype":[
        "aat:300008706"
    ]
},
  "bbox": [],
  "geometry": {"coordinates":[-121.1667,47.5333],"type":"Point"}
}