{
  "id": 2000518,
  "type": "Feature",
  "properties": {
    "tgn:hierarchy":[
        "tgn:2000518",
        "tgn:1000001",
        "tgn:7012149",
        "tgn:7007251",
        "tgn:7029392"
    ],
    "tgn:id":2000518,
    "tgn:name":"McDonough",
    "tgn:placetype":[
        "aat:300387145",
        "aat:300000771"
    ]
},
  "bbox": [],
  "geometry": {"coordinates":[-90.6667,40.4667],"type":"Point"}
}