{
  "id": 1013167,
  "type": "Feature",
  "properties": {
    "tgn:hierarchy":[
        "tgn:1013167",
        "tgn:7005694",
        "tgn:7005685",
        "tgn:1000001",
        "tgn:7029392"
    ],
    "tgn:id":1013167,
    "tgn:name":"Forestburg",
    "tgn:placetype":[
        "aat:300008347"
    ]
},
  "bbox": [],
  "geometry": {"coordinates":[-112.0167,52.5833],"type":"Point"}
}