<<<<<<< HEAD
{
  "id": 2330766,
  "type": "Feature",
  "properties": {
    "tgn:hierarchy":[
        "tgn:2330766",
        "tgn:1000001",
        "tgn:2001581",
        "tgn:7012149",
        "tgn:7007705",
        "tgn:7029392"
    ],
    "tgn:id":2330766,
    "tgn:name":"Flat Lake",
    "tgn:placetype":[
        "aat:300008680"
    ]
},
  "bbox": [],
  "geometry": {"coordinates":[-100.3,47.9833],"type":"Point"}
}
=======
{"geometry":{"type":"Point","coordinates":[-100.300000,47.983300]},"type":"Feature","properties":{"hierarchy":["tgn:2330766","tgn:1000001","tgn:2001581","tgn:7012149","tgn:7007705","tgn:7029392"],"placetype":["aat:300008680"],"id":2330766,"name:xx":"Flat Lake"}}
>>>>>>> 03f74aca74312dbeaf24d7e61306dd6a786dc3d0
