{
  "id": 2560976,
  "type": "Feature",
  "properties": {
    "tgn:hierarchy":[
        "tgn:2560976",
        "tgn:1000001",
        "tgn:1002218",
        "tgn:7012149",
        "tgn:7007157",
        "tgn:7029392"
    ],
    "tgn:id":2560976,
    "tgn:name":"Oroleve",
    "tgn:placetype":[
        "aat:300008347"
    ]
},
  "bbox": [],
  "geometry": {"coordinates":[-121.1667,39.5167],"type":"Point"}
}