{
  "id": 7497931,
  "type": "Feature",
  "properties": {
    "tgn:hierarchy":[
        "tgn:7497931",
        "tgn:7001004",
        "tgn:1000004",
        "tgn:1000141",
        "tgn:7029392"
    ],
    "tgn:id":7497931,
    "tgn:name":"Shuixiao Ciao",
    "tgn:placetype":[
        "aat:300007836"
    ]
},
  "bbox": [],
  "geometry": {"coordinates":[120.396309,22.7455],"type":"Point"}
}