{
  "id": 7420673,
  "type": "Feature",
  "properties": {
    "tgn:hierarchy":[
        "tgn:7420673",
        "tgn:7005579",
        "tgn:1000001",
        "tgn:7005560",
        "tgn:7029392"
    ],
    "tgn:id":7420673,
    "tgn:name":"El Varal",
    "tgn:placetype":[
        "aat:300008347"
    ]
},
  "bbox": [],
  "geometry": {"coordinates":[-102.375,21.833333],"type":"Point"}
}