{
  "id": 7590728,
  "type": "Feature",
  "properties": {
    "tgn:hierarchy":[
        "tgn:7590728",
        "tgn:1000004",
        "tgn:7000198",
        "tgn:7000799",
        "tgn:7029392"
    ],
    "tgn:id":7590728,
    "tgn:name:en":"Nala",
    "tgn:placetype":[
        "aat:300008347"
    ]
},
  "bbox": [],
  "geometry": {"coordinates":[73.816983,34.398199],"type":"Point"}
}