{
  "id": 7463047,
  "type": "Feature",
  "properties": {
    "tgn:hierarchy":[
        "tgn:7463047",
        "tgn:7002444",
        "tgn:1000003",
        "tgn:7008082",
        "tgn:7008591",
        "tgn:7029392"
    ],
    "tgn:id":7463047,
    "tgn:name:en":"Kinlochteacuis",
    "tgn:placetype":[
        "aat:300008347"
    ]
},
  "bbox": [],
  "geometry": {"coordinates":[-5.833333,56.616667],"type":"Point"}
}