{
  "id": 2422354,
  "type": "Feature",
  "properties": {
    "tgn:hierarchy":[
        "tgn:2422354",
        "tgn:1000001",
        "tgn:7012149",
        "tgn:2000420",
        "tgn:7007248",
        "tgn:7029392"
    ],
    "tgn:id":2422354,
    "tgn:name":"Jimmy Greene Lake",
    "tgn:placetype":[
        "aat:300006191"
    ]
},
  "bbox": [],
  "geometry": {"coordinates":[-84.1167,32.0833],"type":"Point"}
}