{
  "id": 2685230,
  "type": "Feature",
  "properties": {
    "tgn:hierarchy":[
        "tgn:2685230",
        "tgn:1000001",
        "tgn:7012149",
        "tgn:1002687",
        "tgn:7007523",
        "tgn:7029392"
    ],
    "tgn:id":2685230,
    "tgn:name":"Sportsman Lake",
    "tgn:placetype":[
        "aat:300008680"
    ]
},
  "bbox": [],
  "geometry": {"coordinates":[-91.5667,39.0333],"type":"Point"}
}