{
  "id": 2373018,
  "type": "Feature",
  "properties": {
    "tgn:hierarchy":[
        "tgn:2373018",
        "tgn:1000001",
        "tgn:7012149",
        "tgn:1002682",
        "tgn:7007710",
        "tgn:7029392"
    ],
    "tgn:id":2373018,
    "tgn:name":"Hallowood Lake",
    "tgn:placetype":[
        "aat:300006191"
    ]
},
  "bbox": [],
  "geometry": {"coordinates":[-75.1833,41.0833],"type":"Point"}
}