{
  "id": 7314785,
  "type": "Feature",
  "properties": {
    "tgn:hierarchy":[
        "tgn:7314785",
        "tgn:1001708",
        "tgn:1000049",
        "tgn:1000002",
        "tgn:7029392"
    ],
    "tgn:id":7314785,
    "tgn:name":"Las Trancas, Loma",
    "tgn:placetype":[
        "aat:300387002"
    ]
},
  "bbox": [],
  "geometry": {"coordinates":[-71.016667,-33.85],"type":"Point"}
}