{
  "id": 1135284,
  "type": "Feature",
  "properties": {
    "tgn:hierarchy":[
        "tgn:1135284",
        "tgn:7003138",
        "tgn:1000003",
        "tgn:7003080",
        "tgn:1000080",
        "tgn:7029392"
    ],
    "tgn:id":1135284,
    "tgn:name":"Magliana, Fosso",
    "tgn:placetype":[
        "aat:300008703",
        "aat:300008699"
    ]
},
  "bbox": [],
  "geometry": {"coordinates":[12.416667,41.816667],"type":"Point"}
}