{
  "id": 2605547,
  "type": "Feature",
  "properties": {
    "tgn:hierarchy":[
        "tgn:2605547",
        "tgn:1000001",
        "tgn:7012149",
        "tgn:2001233",
        "tgn:7007523",
        "tgn:7029392"
    ],
    "tgn:id":2605547,
    "tgn:name":"Railroad Cave",
    "tgn:placetype":[
        "aat:300008746"
    ]
},
  "bbox": [],
  "geometry": {"coordinates":[-92.2333,37.85],"type":"Point"}
}