{
  "id": 2085903,
  "type": "Feature",
  "properties": {
    "tgn:hierarchy":[
        "tgn:2085903",
        "tgn:1000001",
        "tgn:1002330",
        "tgn:7012149",
        "tgn:7007710",
        "tgn:7029392"
    ],
    "tgn:id":2085903,
    "tgn:name":"Aldan",
    "tgn:placetype":[
        "aat:300008347"
    ]
},
  "bbox": [],
  "geometry": {"coordinates":[-75.2833,39.9167],"type":"Point"}
}