{
  "id": 2489897,
  "type": "Feature",
  "properties": {
    "tgn:hierarchy":[
        "tgn:2489897",
        "tgn:1000001",
        "tgn:7012149",
        "tgn:2000182",
        "tgn:7007157",
        "tgn:7029392"
    ],
    "tgn:id":2489897,
    "tgn:name":"Malva Drain",
    "tgn:placetype":[
        "aat:300006075"
    ]
},
  "bbox": [],
  "geometry": {"coordinates":[-115.4167,33.05],"type":"Point"}
}