{
  "id": 2560843,
  "type": "Feature",
  "properties": {
    "tgn:hierarchy":[
        "tgn:2560843",
        "tgn:1000001",
        "tgn:7012149",
        "tgn:7007157",
        "tgn:1002956",
        "tgn:7029392"
    ],
    "tgn:id":2560843,
    "tgn:name":"Orlem",
    "tgn:placetype":[
        "aat:300008347"
    ]
},
  "bbox": [],
  "geometry": {"coordinates":[-119.0333,36.1833],"type":"Point"}
}