<<<<<<< HEAD
{
  "id": 2152258,
  "type": "Feature",
  "properties": {
    "tgn:hierarchy":[
        "tgn:2152258",
        "tgn:1000001",
        "tgn:2000924",
        "tgn:7012149",
        "tgn:7007515",
        "tgn:7029392"
    ],
    "tgn:id":2152258,
    "tgn:name":"Bay Cove Ledge",
    "tgn:placetype":[
        "aat:300132348"
    ]
},
  "bbox": [],
  "geometry": {"coordinates":[-69.3,43.9333],"type":"Point"}
}
=======
{"geometry":{"type":"Point","coordinates":[-69.300000,43.933300]},"type":"Feature","properties":{"hierarchy":["tgn:2152258","tgn:1000001","tgn:2000924","tgn:7012149","tgn:7007515","tgn:7029392"],"placetype":["aat:300132348"],"id":2152258,"name:xx":"Bay Cove Ledge"}}
>>>>>>> 03f74aca74312dbeaf24d7e61306dd6a786dc3d0
