{
  "id": 2134487,
  "type": "Feature",
  "properties": {
    "tgn:hierarchy":[
        "tgn:2134487",
        "tgn:1000001",
        "tgn:7012149",
        "tgn:2001756",
        "tgn:7007712",
        "tgn:7029392"
    ],
    "tgn:id":2134487,
    "tgn:name":"Ansel Smith Pond",
    "tgn:placetype":[
        "aat:300006191"
    ]
},
  "bbox": [],
  "geometry": {"coordinates":[-81.4667,33.8667],"type":"Point"}
}