{
  "id": 2077018,
  "type": "Feature",
  "properties": {
    "tgn:hierarchy":[
        "tgn:2077018",
        "tgn:1000001",
        "tgn:7012149",
        "tgn:2001531",
        "tgn:7007709",
        "tgn:7029392"
    ],
    "tgn:id":2077018,
    "tgn:name":"Valhalla",
    "tgn:placetype":[
        "aat:300008347",
        "aat:300387210"
    ]
},
  "bbox": [],
  "geometry": {"coordinates":[-82.25,35.2167],"type":"Point"}
}