<<<<<<< HEAD
{
  "id": 7480583,
  "type": "Feature",
  "properties": {
    "tgn:hierarchy":[
        "tgn:7480583",
        "tgn:1000004",
        "tgn:7471332",
        "tgn:1000141",
        "tgn:7029392"
    ],
    "tgn:id":7480583,
    "tgn:name":"Zhongzheng Guozhong",
    "tgn:placetype":[
        "aat:300006495"
    ]
},
  "bbox": [],
  "geometry": {"coordinates":[121.0175,24.873333],"type":"Point"}
}
=======
{"geometry":{"type":"Point","coordinates":[121.017500,24.873333]},"type":"Feature","properties":{"hierarchy":["tgn:7480583","tgn:1000004","tgn:7471332","tgn:1000141","tgn:7029392"],"placetype":["aat:300006495"],"id":7480583,"name:xx":"Zhongzheng Guozhong"}}
>>>>>>> 03f74aca74312dbeaf24d7e61306dd6a786dc3d0
