{
  "id": 7480583,
  "type": "Feature",
  "properties": {
    "tgn:hierarchy":[
        "tgn:7480583",
        "tgn:1000004",
        "tgn:7471332",
        "tgn:1000141",
        "tgn:7029392"
    ],
    "tgn:id":7480583,
    "tgn:name":"Zhongzheng Guozhong",
    "tgn:placetype":[
        "aat:300006495"
    ]
},
  "bbox": [],
  "geometry": {"coordinates":[121.0175,24.873333],"type":"Point"}
}