{
  "id": 7223649,
  "type": "Feature",
  "properties": {
    "tgn:hierarchy":[
        "tgn:7223649",
        "tgn:7002739",
        "tgn:7017076",
        "tgn:1000003",
        "tgn:1000074",
        "tgn:7029392"
    ],
    "tgn:id":7223649,
    "tgn:name":"Sarand\u00e1psikho",
    "tgn:placetype":[
        "aat:300008795"
    ]
},
  "bbox": [],
  "geometry": {"coordinates":[22.633333,37.35],"type":"Point"}
}