<<<<<<< HEAD
{
  "id": 7021787,
  "type": "Feature",
  "properties": {
    "tgn:hierarchy":[
        "tgn:7021787",
        "tgn:1000001",
        "tgn:7012149",
        "tgn:2000974",
        "tgn:7007520",
        "tgn:7029392"
    ],
    "tgn:id":7021787,
    "tgn:name":"Tippy Dam Pond",
    "tgn:placetype":[
        "aat:300006191"
    ]
},
  "bbox": [],
  "geometry": {"coordinates":[-85.9333,44.25],"type":"Point"}
}
=======
{"geometry":{"type":"Point","coordinates":[-85.933300,44.250000]},"type":"Feature","properties":{"hierarchy":["tgn:7021787","tgn:1000001","tgn:7012149","tgn:2000974","tgn:7007520","tgn:7029392"],"placetype":["aat:300006191"],"id":7021787,"name:xx":"Tippy Dam Pond"}}
>>>>>>> 03f74aca74312dbeaf24d7e61306dd6a786dc3d0
