{
  "id": 7498751,
  "type": "Feature",
  "properties": {
    "tgn:hierarchy":[
        "tgn:7498751",
        "tgn:1000004",
        "tgn:7491221",
        "tgn:1000141",
        "tgn:7029392"
    ],
    "tgn:id":7498751,
    "tgn:name":"Beinan Guozhong",
    "tgn:placetype":[
        "aat:300006495"
    ]
},
  "bbox": [],
  "geometry": {"coordinates":[121.112515,22.789786],"type":"Point"}
}