{
  "id": 1020448,
  "type": "Feature",
  "properties": {
    "tgn:hierarchy":[
        "tgn:1020448",
        "tgn:1000572",
        "tgn:1000046",
        "tgn:1000002",
        "tgn:7029392"
    ],
    "tgn:id":1020448,
    "tgn:name":"Totora",
    "tgn:placetype":[
        "aat:300008347"
    ]
},
  "bbox": [],
  "geometry": {"coordinates":[-65.1667,-17.6667],"type":"Point"}
}