{
  "id": 7489594,
  "type": "Feature",
  "properties": {
    "tgn:hierarchy":[
        "tgn:7489594",
        "tgn:7001004",
        "tgn:1000004",
        "tgn:1000141",
        "tgn:7029392"
    ],
    "tgn:id":7489594,
    "tgn:name":"Guopi",
    "tgn:placetype":[
        "aat:300008347"
    ]
},
  "bbox": [],
  "geometry": {"coordinates":[120.367911,22.588706],"type":"Point"}
}