{
  "id": 2305307,
  "type": "Feature",
  "properties": {
    "tgn:hierarchy":[
        "tgn:2305307",
        "tgn:1000001",
        "tgn:7012149",
        "tgn:7007517",
        "tgn:7029392"
    ],
    "tgn:id":2305307,
    "tgn:name":"East Branch Swift River",
    "tgn:placetype":[
        "aat:300008707"
    ]
},
  "bbox": [],
  "geometry": {"coordinates":[-72.15,42.5167],"type":"Point"}
}