<<<<<<< HEAD
{
  "id": 2332942,
  "type": "Feature",
  "properties": {
    "tgn:hierarchy":[
        "tgn:2332942",
        "tgn:1000001",
        "tgn:1002293",
        "tgn:7012149",
        "tgn:7007708",
        "tgn:7029392"
    ],
    "tgn:id":2332942,
    "tgn:name":"Flume Creek",
    "tgn:placetype":[
        "aat:300008706"
    ]
},
  "bbox": [],
  "geometry": {"coordinates":[-123.0833,46.1333],"type":"Point"}
}
=======
{"geometry":{"type":"Point","coordinates":[-123.083300,46.133300]},"type":"Feature","properties":{"hierarchy":["tgn:2332942","tgn:1000001","tgn:1002293","tgn:7012149","tgn:7007708","tgn:7029392"],"placetype":["aat:300008706"],"id":2332942,"name:xx":"Flume Creek"}}
>>>>>>> 03f74aca74312dbeaf24d7e61306dd6a786dc3d0
