{
  "id": 2191493,
  "type": "Feature",
  "properties": {
    "tgn:hierarchy":[
        "tgn:2191493",
        "tgn:1000001",
        "tgn:2002102",
        "tgn:7012149",
        "tgn:7007827",
        "tgn:7029392"
    ],
    "tgn:id":2191493,
    "tgn:name":"Bradford",
    "tgn:placetype":[
        "aat:300008347"
    ]
},
  "bbox": [],
  "geometry": {"coordinates":[-112.1333,41.6167],"type":"Point"}
}