<<<<<<< HEAD
{
  "id": 2153388,
  "type": "Feature",
  "properties": {
    "tgn:hierarchy":[
        "tgn:2153388",
        "tgn:1000001",
        "tgn:7012149",
        "tgn:2002190",
        "tgn:7007919",
        "tgn:7029392"
    ],
    "tgn:id":2153388,
    "tgn:name":"Bean Hollow",
    "tgn:placetype":[
        "aat:300008761"
    ]
},
  "bbox": [],
  "geometry": {"coordinates":[-78.7833,38.75],"type":"Point"}
}
=======
{"geometry":{"type":"Point","coordinates":[-78.783300,38.750000]},"type":"Feature","properties":{"hierarchy":["tgn:2153388","tgn:1000001","tgn:7012149","tgn:2002190","tgn:7007919","tgn:7029392"],"placetype":["aat:300008761"],"id":2153388,"name:xx":"Bean Hollow"}}
>>>>>>> 03f74aca74312dbeaf24d7e61306dd6a786dc3d0
