<<<<<<< HEAD
{
  "id": 7476595,
  "type": "Feature",
  "properties": {
    "tgn:hierarchy":[
        "tgn:7476595",
        "tgn:7487020",
        "tgn:1000004",
        "tgn:1000141",
        "tgn:7029392"
    ],
    "tgn:id":7476595,
    "tgn:name":"Sifenzi",
    "tgn:placetype":[
        "aat:300008347"
    ]
},
  "bbox": [],
  "geometry": {"coordinates":[120.78502,24.630088],"type":"Point"}
}
=======
{"geometry":{"type":"Point","coordinates":[120.785020,24.630088]},"type":"Feature","properties":{"hierarchy":["tgn:7476595","tgn:7487020","tgn:1000004","tgn:1000141","tgn:7029392"],"placetype":["aat:300008347"],"id":7476595,"name:xx":"Sifenzi"}}
>>>>>>> 03f74aca74312dbeaf24d7e61306dd6a786dc3d0
