{
  "id": 2545138,
  "type": "Feature",
  "properties": {
    "tgn:hierarchy":[
        "tgn:2545138",
        "tgn:1000001",
        "tgn:7012149",
        "tgn:7007158",
        "tgn:2000243",
        "tgn:7029392"
    ],
    "tgn:id":2545138,
    "tgn:name":"North Elk Creek",
    "tgn:placetype":[
        "aat:300008706"
    ]
},
  "bbox": [],
  "geometry": {"coordinates":[-107.65,39.8667],"type":"Point"}
}