{
  "id": 2621464,
  "type": "Feature",
  "properties": {
    "tgn:hierarchy":[
        "tgn:2621464",
        "tgn:1000001",
        "tgn:7012149",
        "tgn:1002904",
        "tgn:7007710",
        "tgn:7029392"
    ],
    "tgn:id":2621464,
    "tgn:name":"Roaring Fork",
    "tgn:placetype":[
        "aat:300008699"
    ]
},
  "bbox": [],
  "geometry": {"coordinates":[-78.75,40.2167],"type":"Point"}
}