{
  "id": 7540958,
  "type": "Feature",
  "properties": {
    "tgn:hierarchy":[
        "tgn:7540958",
        "tgn:7001242",
        "tgn:7016833",
        "tgn:7001336",
        "tgn:7029392"
    ],
    "tgn:id":7540958,
    "tgn:name:en":"Ghabghab, Gebel",
    "tgn:placetype":[
        "aat:300008795"
    ]
},
  "bbox": [],
  "geometry": {"coordinates":[34.028238,28.575846],"type":"Point"}
}