{
  "id": 2122596,
  "type": "Feature",
  "properties": {
    "tgn:hierarchy":[
        "tgn:2122596",
        "tgn:1000001",
        "tgn:7012149",
        "tgn:2002358",
        "tgn:7007922",
        "tgn:7029392"
    ],
    "tgn:id":2122596,
    "tgn:name":"Valley",
    "tgn:placetype":[
        "aat:300008347"
    ]
},
  "bbox": [],
  "geometry": {"coordinates":[-90.5333,43.6333],"type":"Point"}
}