{
  "id": 1011335,
  "type": "Feature",
  "properties": {
    "tgn:hierarchy":[
        "tgn:1011335",
        "tgn:7001242",
        "tgn:1000179",
        "tgn:7593681",
        "tgn:7029392"
    ],
    "tgn:id":1011335,
    "tgn:name":"Trois Fourches, Cap des",
    "tgn:placetype":[
        "aat:300008850"
    ]
},
  "bbox": [],
  "geometry": {"coordinates":[-2.95,35.4333],"type":"Point"}
}