{
  "id": 2128582,
  "type": "Feature",
  "properties": {
    "tgn:hierarchy":[
        "tgn:2128582",
        "tgn:1000001",
        "tgn:7012149",
        "tgn:1002928",
        "tgn:7007706",
        "tgn:7029392"
    ],
    "tgn:id":2128582,
    "tgn:name":"Alder Pond",
    "tgn:placetype":[
        "aat:300006191"
    ]
},
  "bbox": [],
  "geometry": {"coordinates":[-81.45,41.0667],"type":"Point"}
}