{
  "id": 2534615,
  "type": "Feature",
  "properties": {
    "tgn:hierarchy":[
        "tgn:2534615",
        "tgn:1000001",
        "tgn:7012149",
        "tgn:2001300",
        "tgn:7007524",
        "tgn:7029392"
    ],
    "tgn:id":2534615,
    "tgn:name":"NW SW Section 9 Mine",
    "tgn:placetype":[
        "aat:300000390"
    ]
},
  "bbox": [],
  "geometry": {"coordinates":[-113.9667,46.3667],"type":"Point"}
}