{
  "id": 2007811,
  "type": "Feature",
  "properties": {
    "tgn:hierarchy":[
        "tgn:2007811",
        "tgn:1000001",
        "tgn:7016172",
        "tgn:7012149",
        "tgn:2000165",
        "tgn:7029392"
    ],
    "tgn:id":2007811,
    "tgn:name":"Brakebill",
    "tgn:placetype":[
        "aat:300008347",
        "aat:300387210"
    ]
},
  "bbox": [],
  "geometry": {"coordinates":[-90.95,36.45],"type":"Point"}
}