{
  "id": 7461802,
  "type": "Feature",
  "properties": {
    "tgn:hierarchy":[
        "tgn:7461802",
        "tgn:7019094",
        "tgn:7002444",
        "tgn:1000003",
        "tgn:7008591",
        "tgn:7029392"
    ],
    "tgn:id":7461802,
    "tgn:name:en":"High Smerby",
    "tgn:placetype":[
        "aat:300008347"
    ]
},
  "bbox": [],
  "geometry": {"coordinates":[-5.533333,55.45],"type":"Point"}
}