{
  "id": 7269092,
  "type": "Feature",
  "properties": {
    "tgn:concordances":{
        "gn:id":"2749782"
    },
    "tgn:hierarchy":[
        "tgn:7269092",
        "tgn:1000003",
        "tgn:7003632",
        "tgn:7016845",
        "tgn:7029392"
    ],
    "tgn:id":7269092,
    "tgn:name:nl":"Noukoop",
    "tgn:placetype":[
        "aat:300008347"
    ]
},
  "bbox": [],
  "geometry": {"coordinates":[4.433333,52.033333],"type":"Point"}
}