{
  "id": 7292833,
  "type": "Feature",
  "properties": {
    "tgn:hierarchy":[
        "tgn:7292833",
        "tgn:1001623",
        "tgn:1000049",
        "tgn:1000002",
        "tgn:7029392"
    ],
    "tgn:id":7292833,
    "tgn:name":"El Morro, Islote",
    "tgn:placetype":[
        "aat:300008791"
    ]
},
  "bbox": [],
  "geometry": {"coordinates":[-73.633333,-45.133333],"type":"Point"}
}