{
  "id": 2276529,
  "type": "Feature",
  "properties": {
    "tgn:hierarchy":[
        "tgn:2276529",
        "tgn:1000001",
        "tgn:7012149",
        "tgn:2001288",
        "tgn:7007524",
        "tgn:7029392"
    ],
    "tgn:id":2276529,
    "tgn:name":"Davey Creek",
    "tgn:placetype":[
        "aat:300008706"
    ]
},
  "bbox": [],
  "geometry": {"coordinates":[-111.9667,45.2167],"type":"Point"}
}