{
  "id": 7115285,
  "type": "Feature",
  "properties": {
    "tgn:hierarchy":[
        "tgn:7115285",
        "tgn:1000003",
        "tgn:7003688",
        "tgn:7000084",
        "tgn:7029392"
    ],
    "tgn:id":7115285,
    "tgn:name":"Osterdeich",
    "tgn:placetype":[
        "aat:300008347"
    ]
},
  "bbox": [],
  "geometry": {"coordinates":[8.716667,54.383333],"type":"Point"}
}