{
  "id": 7536877,
  "type": "Feature",
  "properties": {
    "tgn:hierarchy":[
        "tgn:7536877",
        "tgn:7001242",
        "tgn:7016833",
        "tgn:1001418",
        "tgn:7029392"
    ],
    "tgn:id":7536877,
    "tgn:name:en":"\u1e28add\u016bnah, W\u0101d\u012b",
    "tgn:placetype":[
        "aat:300379998"
    ]
},
  "bbox": [],
  "geometry": {"coordinates":[26.214237,29.158677],"type":"Point"}
}