{
  "id": 7410971,
  "type": "Feature",
  "properties": {
    "tgn:hierarchy":[
        "tgn:7410971",
        "tgn:1000001",
        "tgn:7005596",
        "tgn:7005560",
        "tgn:7029392"
    ],
    "tgn:id":7410971,
    "tgn:name:es":"Boca San Jer\u00f3nimo",
    "tgn:placetype":[
        "aat:300008347"
    ]
},
  "bbox": [],
  "geometry": {"coordinates":[-91.908333,17.9125],"type":"Point"}
}