{
  "id": 2640001,
  "type": "Feature",
  "properties": {
    "tgn:hierarchy":[
        "tgn:2640001",
        "tgn:1000001",
        "tgn:1003028",
        "tgn:7012149",
        "tgn:7007159",
        "tgn:7029392"
    ],
    "tgn:id":2640001,
    "tgn:name":"Sampson Pond",
    "tgn:placetype":[
        "aat:300006191"
    ]
},
  "bbox": [],
  "geometry": {"coordinates":[-71.95,41.9667],"type":"Point"}
}