{
  "id": 7192024,
  "type": "Feature",
  "properties": {
    "tgn:hierarchy":[
        "tgn:7192024",
        "tgn:1000003",
        "tgn:7003688",
        "tgn:7000084",
        "tgn:7029392"
    ],
    "tgn:id":7192024,
    "tgn:name":"Fl\u00fche",
    "tgn:placetype":[
        "aat:300000206"
    ]
},
  "bbox": [],
  "geometry": {"coordinates":[8.916667,54.816667],"type":"Point"}
}