{
  "id": 2271321,
  "type": "Feature",
  "properties": {
    "tgn:hierarchy":[
        "tgn:2271321",
        "tgn:1000001",
        "tgn:7012149",
        "tgn:2002088",
        "tgn:7007826",
        "tgn:7029392"
    ],
    "tgn:id":2271321,
    "tgn:name":"Cully Draw",
    "tgn:placetype":[
        "aat:300008761"
    ]
},
  "bbox": [],
  "geometry": {"coordinates":[-101.1333,30.1667],"type":"Point"}
}