{
  "id": 7401977,
  "type": "Feature",
  "properties": {
    "tgn:hierarchy":[
        "tgn:7401977",
        "tgn:1000001",
        "tgn:7005599",
        "tgn:7005560",
        "tgn:7029392"
    ],
    "tgn:id":7401977,
    "tgn:name":"Paso Carretas",
    "tgn:placetype":[
        "aat:300008347"
    ]
},
  "bbox": [],
  "geometry": {"coordinates":[-96.6875,19.116667],"type":"Point"}
}