{
  "id": 7308324,
  "type": "Feature",
  "properties": {
    "tgn:hierarchy":[
        "tgn:7308324",
        "tgn:1001702",
        "tgn:1000049",
        "tgn:1000002",
        "tgn:7029392"
    ],
    "tgn:id":7308324,
    "tgn:name":"Mary, Punta",
    "tgn:placetype":[
        "aat:300386846"
    ]
},
  "bbox": [],
  "geometry": {"coordinates":[-67.033333,-55.316667],"type":"Point"}
}