{
  "id": 2565292,
  "type": "Feature",
  "properties": {
    "tgn:hierarchy":[
        "tgn:2565292",
        "tgn:1000001",
        "tgn:7012149",
        "tgn:2002084",
        "tgn:7007826",
        "tgn:7029392"
    ],
    "tgn:id":2565292,
    "tgn:name":"Paint Canyon Tank",
    "tgn:placetype":[
        "aat:300006191"
    ]
},
  "bbox": [],
  "geometry": {"coordinates":[-99.3833,33.0333],"type":"Point"}
}