{
  "id": 2295853,
  "type": "Feature",
  "properties": {
    "tgn:hierarchy":[
        "tgn:2295853",
        "tgn:1000001",
        "tgn:7012149",
        "tgn:2001029",
        "tgn:7007521",
        "tgn:7029392"
    ],
    "tgn:id":2295853,
    "tgn:name":"Drumbeater Island",
    "tgn:placetype":[
        "aat:300008791"
    ]
},
  "bbox": [],
  "geometry": {"coordinates":[-93.5833,47.1833],"type":"Point"}
}