{
  "id": 2213639,
  "type": "Feature",
  "properties": {
    "tgn:hierarchy":[
        "tgn:2213639",
        "tgn:1000001",
        "tgn:7012149",
        "tgn:2002299",
        "tgn:7013961",
        "tgn:7029392"
    ],
    "tgn:id":2213639,
    "tgn:name":"Cabwaylingo State Forest",
    "tgn:placetype":[
        "aat:300008863"
    ]
},
  "bbox": [],
  "geometry": {"coordinates":[-82.35,37.9667],"type":"Point"}
}