{
  "id": 2396311,
  "type": "Feature",
  "properties": {
    "tgn:hierarchy":[
        "tgn:2396311",
        "tgn:1000001",
        "tgn:2001946",
        "tgn:7012149",
        "tgn:7007826",
        "tgn:7029392"
    ],
    "tgn:id":2396311,
    "tgn:name":"Holmes Creek Tank",
    "tgn:placetype":[
        "aat:300006191"
    ]
},
  "bbox": [],
  "geometry": {"coordinates":[-101.1167,34.4167],"type":"Point"}
}