{
  "id": 7018608,
  "type": "Feature",
  "properties": {
    "tgn:hierarchy":[
        "tgn:7018608",
        "tgn:7018592",
        "tgn:7005559",
        "tgn:1000001",
        "tgn:7005556",
        "tgn:7029392"
    ],
    "tgn:id":7018608,
    "tgn:name":"Bath",
    "tgn:placetype":[
        "aat:300008347",
        "aat:300008375"
    ]
},
  "bbox": [],
  "geometry": {"coordinates":[-76.349,17.948],"type":"Point"}
}