{
  "id": 1065317,
  "type": "Feature",
  "properties": {
    "tgn:hierarchy":[
        "tgn:1065317",
        "tgn:1000003",
        "tgn:7017312",
        "tgn:7006663",
        "tgn:7029392"
    ],
    "tgn:id":1065317,
    "tgn:name":"Velika Gorica",
    "tgn:placetype":[
        "aat:300008347"
    ]
},
  "bbox": [],
  "geometry": {"coordinates":[16.0833,45.7333],"type":"Point"}
}