{
  "id": 2570789,
  "type": "Feature",
  "properties": {
    "tgn:hierarchy":[
        "tgn:2570789",
        "tgn:1000001",
        "tgn:7012149",
        "tgn:2000887",
        "tgn:7007256",
        "tgn:7029392"
    ],
    "tgn:id":2570789,
    "tgn:name":"Patten Slough",
    "tgn:placetype":[
        "aat:300008699"
    ]
},
  "bbox": [],
  "geometry": {"coordinates":[-91.8333,32.7333],"type":"Point"}
}