{
  "id": 7039648,
  "type": "Feature",
  "properties": {
    "tgn:hierarchy":[
        "tgn:7039648",
        "tgn:7015163",
        "tgn:1000003",
        "tgn:7003121",
        "tgn:1000080",
        "tgn:7029392"
    ],
    "tgn:id":7039648,
    "tgn:name":"Sette Ortas, Riu",
    "tgn:placetype":[
        "aat:300387032"
    ]
},
  "bbox": [],
  "geometry": {"coordinates":[8.433333,40.566667],"type":"Point"}
}