{
  "id": 1091465,
  "type": "Feature",
  "properties": {
    "tgn:hierarchy":[
        "tgn:1091465",
        "tgn:7001242",
        "tgn:1000179",
        "tgn:7593698",
        "tgn:7029392"
    ],
    "tgn:id":1091465,
    "tgn:name":"Torres de Alcala",
    "tgn:placetype":[
        "aat:300008347"
    ]
},
  "bbox": [],
  "geometry": {"coordinates":[-4.325,35.152],"type":"Point"}
}