{
  "id": 7526539,
  "type": "Feature",
  "properties": {
    "tgn:hierarchy":[
        "tgn:7526539",
        "tgn:7001242",
        "tgn:7016833",
        "tgn:7001335",
        "tgn:7029392"
    ],
    "tgn:id":7526539,
    "tgn:name":"Wakh\u0101m\u012b, W\u0101d\u012b al",
    "tgn:placetype":[
        "aat:300379998"
    ]
},
  "bbox": [],
  "geometry": {"coordinates":[33.472629,30.504194],"type":"Point"}
}