{
  "id": 7574538,
  "type": "Feature",
  "properties": {
    "tgn:hierarchy":[
        "tgn:7574538",
        "tgn:1000004",
        "tgn:1001869",
        "tgn:7000198",
        "tgn:7029392"
    ],
    "tgn:id":7574538,
    "tgn:name:en":"Kunria",
    "tgn:placetype":[
        "aat:300008347"
    ]
},
  "bbox": [],
  "geometry": {"coordinates":[69.887657,23.826347],"type":"Point"}
}