{
  "id": 1086082,
  "type": "Feature",
  "properties": {
    "tgn:hierarchy":[
        "tgn:1086082",
        "tgn:1001287",
        "tgn:7018452",
        "tgn:1000004",
        "tgn:1000144",
        "tgn:7029392"
    ],
    "tgn:id":1086082,
    "tgn:name":"Belen",
    "tgn:placetype":[
        "aat:300008347"
    ]
},
  "bbox": [],
  "geometry": {"coordinates":[36.1833,36.5333],"type":"Point"}
}