{
  "id": 2245187,
  "type": "Feature",
  "properties": {
    "tgn:hierarchy":[
        "tgn:2245187",
        "tgn:1000001",
        "tgn:7012149",
        "tgn:2002287",
        "tgn:7013961",
        "tgn:7029392"
    ],
    "tgn:id":2245187,
    "tgn:name":"Cloverlick Cave",
    "tgn:placetype":[
        "aat:300008746"
    ]
},
  "bbox": [],
  "geometry": {"coordinates":[-80.0167,38.35],"type":"Point"}
}