{
  "id": 7281807,
  "type": "Feature",
  "properties": {
    "tgn:hierarchy":[
        "tgn:7281807",
        "tgn:1001699",
        "tgn:1000049",
        "tgn:1000002",
        "tgn:7029392"
    ],
    "tgn:id":7281807,
    "tgn:name":"San Antonio, Canal",
    "tgn:placetype":[
        "aat:300387026"
    ]
},
  "bbox": [],
  "geometry": {"coordinates":[-73.251111,-41.745833],"type":"Point"}
}