{
  "id": 2639393,
  "type": "Feature",
  "properties": {
    "tgn:hierarchy":[
        "tgn:2639393",
        "tgn:1000001",
        "tgn:7012149",
        "tgn:7007158",
        "tgn:2000248",
        "tgn:7029392"
    ],
    "tgn:id":2639393,
    "tgn:name":"Saltado Creek",
    "tgn:placetype":[
        "aat:300008706"
    ]
},
  "bbox": [],
  "geometry": {"coordinates":[-108.0833,37.8833],"type":"Point"}
}