{
  "id": 2389791,
  "type": "Feature",
  "properties": {
    "tgn:hierarchy":[
        "tgn:2389791",
        "tgn:1000001",
        "tgn:7012149",
        "tgn:2001715",
        "tgn:7007708",
        "tgn:7029392"
    ],
    "tgn:id":2389791,
    "tgn:name":"High Line Ditch",
    "tgn:placetype":[
        "aat:300006075"
    ]
},
  "bbox": [],
  "geometry": {"coordinates":[-120.25,42.4167],"type":"Point"}
}