{
  "id": 1121887,
  "type": "Feature",
  "properties": {
    "tgn:hierarchy":[
        "tgn:1121887",
        "tgn:1000001",
        "tgn:7012149",
        "tgn:7007522",
        "tgn:7029392"
    ],
    "tgn:id":1121887,
    "tgn:name":"Big Black",
    "tgn:placetype":[
        "aat:300008707"
    ]
},
  "bbox": [],
  "geometry": {"coordinates":[-89.1167,33.6833],"type":"Point"}
}