{
  "id": 2490343,
  "type": "Feature",
  "properties": {
    "tgn:hierarchy":[
        "tgn:2490343",
        "tgn:1000001",
        "tgn:7012149",
        "tgn:2000969",
        "tgn:7007520",
        "tgn:7029392"
    ],
    "tgn:id":2490343,
    "tgn:name":"Manganese, Lake",
    "tgn:placetype":[
        "aat:300008680"
    ]
},
  "bbox": [],
  "geometry": {"coordinates":[-87.8667,47.45],"type":"Point"}
}