{
  "id": 2341933,
  "type": "Feature",
  "properties": {
    "tgn:hierarchy":[
        "tgn:2341933",
        "tgn:1000001",
        "tgn:7012149",
        "tgn:2001868",
        "tgn:7007825",
        "tgn:7029392"
    ],
    "tgn:id":2341933,
    "tgn:name":"Fry Cave",
    "tgn:placetype":[
        "aat:300008746"
    ]
},
  "bbox": [],
  "geometry": {"coordinates":[-83.2667,36.1833],"type":"Point"}
}