{
  "id": 7540632,
  "type": "Feature",
  "properties": {
    "tgn:hierarchy":[
        "tgn:7540632",
        "tgn:7001242",
        "tgn:7001311",
        "tgn:7016833",
        "tgn:7029392"
    ],
    "tgn:id":7540632,
    "tgn:name:en":"Qul'\u0101n, Ra's",
    "tgn:placetype":[
        "aat:300008850"
    ]
},
  "bbox": [],
  "geometry": {"coordinates":[35.369055,24.297145],"type":"Point"}
}