<<<<<<< HEAD
{
  "id": 2402298,
  "type": "Feature",
  "properties": {
    "tgn:hierarchy":[
        "tgn:2402298",
        "tgn:1000001",
        "tgn:2000272",
        "tgn:7012149",
        "tgn:7007240",
        "tgn:7029392"
    ],
    "tgn:id":2402298,
    "tgn:name":"Horton Bay",
    "tgn:placetype":[
        "aat:300008905"
    ]
},
  "bbox": [],
  "geometry": {"coordinates":[-85.9833,30.8],"type":"Point"}
}
=======
{"geometry":{"type":"Point","coordinates":[-85.983300,30.800000]},"type":"Feature","properties":{"hierarchy":["tgn:2402298","tgn:1000001","tgn:2000272","tgn:7012149","tgn:7007240","tgn:7029392"],"placetype":["aat:300008905"],"id":2402298,"name:xx":"Horton Bay"}}
>>>>>>> 03f74aca74312dbeaf24d7e61306dd6a786dc3d0
