{
  "id": 7446132,
  "type": "Feature",
  "properties": {
    "tgn:hierarchy":[
        "tgn:7446132",
        "tgn:7002445",
        "tgn:1000003",
        "tgn:7008167",
        "tgn:7008591",
        "tgn:7029392"
    ],
    "tgn:id":7446132,
    "tgn:name:en":"Sookholme",
    "tgn:placetype":[
        "aat:300008347"
    ]
},
  "bbox": [],
  "geometry": {"coordinates":[-1.183333,53.183333],"type":"Point"}
}