{
  "id": 1065501,
  "type": "Feature",
  "properties": {
    "tgn:hierarchy":[
        "tgn:1065501",
        "tgn:7016612",
        "tgn:1000004",
        "tgn:1001398",
        "tgn:7029392"
    ],
    "tgn:id":1065501,
    "tgn:name":"Qaleh-ye Saber",
    "tgn:placetype":[
        "aat:300008347"
    ]
},
  "bbox": [],
  "geometry": {"coordinates":[69.0167,34.0333],"type":"Point"}
}