{
  "id": 2468818,
  "type": "Feature",
  "properties": {
    "tgn:hierarchy":[
        "tgn:2468818",
        "tgn:1000001",
        "tgn:7012149",
        "tgn:7007825",
        "tgn:7029392"
    ],
    "tgn:id":2468818,
    "tgn:name":"Long Ridge",
    "tgn:placetype":[
        "aat:300266640"
    ]
},
  "bbox": [],
  "geometry": {"coordinates":[-85.3667,35.4833],"type":"Point"}
}