{
  "id": 7510607,
  "type": "Feature",
  "properties": {
    "tgn:hierarchy":[
        "tgn:7510607",
        "tgn:1009227",
        "tgn:1000226",
        "tgn:7016822",
        "tgn:1000006",
        "tgn:7029392"
    ],
    "tgn:id":7510607,
    "tgn:name:en":"Twins",
    "tgn:placetype":[
        "aat:300011692"
    ]
},
  "bbox": [],
  "geometry": {"coordinates":[168.266667,-46.916667],"type":"Point"}
}