<<<<<<< HEAD
{
  "id": 2158064,
  "type": "Feature",
  "properties": {
    "tgn:hierarchy":[
        "tgn:2158064",
        "tgn:1000001",
        "tgn:2000507",
        "tgn:7012149",
        "tgn:7007251",
        "tgn:7029392"
    ],
    "tgn:id":2158064,
    "tgn:name":"Beaver Pond",
    "tgn:placetype":[
        "aat:300008680"
    ]
},
  "bbox": [],
  "geometry": {"coordinates":[-88.0833,37.8667],"type":"Point"}
}
=======
{"geometry":{"type":"Point","coordinates":[-88.083300,37.866700]},"type":"Feature","properties":{"hierarchy":["tgn:2158064","tgn:1000001","tgn:2000507","tgn:7012149","tgn:7007251","tgn:7029392"],"placetype":["aat:300008680"],"id":2158064,"name:xx":"Beaver Pond"}}
>>>>>>> 03f74aca74312dbeaf24d7e61306dd6a786dc3d0
