{
  "id": 7280362,
  "type": "Feature",
  "properties": {
    "tgn:hierarchy":[
        "tgn:7280362",
        "tgn:1001702",
        "tgn:1000049",
        "tgn:1000002",
        "tgn:7029392"
    ],
    "tgn:id":7280362,
    "tgn:name":"Smyth, Seno",
    "tgn:placetype":[
        "aat:300008676"
    ]
},
  "bbox": [],
  "geometry": {"coordinates":[-72.216667,-53.816667],"type":"Point"}
}