{
  "id": 2594472,
  "type": "Feature",
  "properties": {
    "tgn:hierarchy":[
        "tgn:2594472",
        "tgn:1002808",
        "tgn:1000001",
        "tgn:7012149",
        "tgn:7007711",
        "tgn:7029392"
    ],
    "tgn:id":2594472,
    "tgn:name":"Porters Pond",
    "tgn:placetype":[
        "aat:300008680"
    ]
},
  "bbox": [],
  "geometry": {"coordinates":[-71.7167,41.7333],"type":"Point"}
}