{
  "id": 7103971,
  "type": "Feature",
  "properties": {
    "tgn:hierarchy":[
        "tgn:7103971",
        "tgn:1000003",
        "tgn:7003689",
        "tgn:7000084",
        "tgn:7029392"
    ],
    "tgn:id":7103971,
    "tgn:name":"Scheibe, Forst",
    "tgn:placetype":[
        "aat:300008863"
    ]
},
  "bbox": [],
  "geometry": {"coordinates":[11.05,50.483333],"type":"Point"}
}