{
  "id": 7371288,
  "type": "Feature",
  "properties": {
    "tgn:hierarchy":[
        "tgn:7371288",
        "tgn:1000001",
        "tgn:7005600",
        "tgn:7005560",
        "tgn:7029392"
    ],
    "tgn:id":7371288,
    "tgn:name":"Hunkanab",
    "tgn:placetype":[
        "aat:300008347"
    ]
},
  "bbox": [],
  "geometry": {"coordinates":[-89.866667,20.966667],"type":"Point"}
}