{
  "id": 7564473,
  "type": "Feature",
  "properties": {
    "tgn:hierarchy":[
        "tgn:7564473",
        "tgn:1000004",
        "tgn:7000198",
        "tgn:7016722",
        "tgn:7029392"
    ],
    "tgn:id":7564473,
    "tgn:name:en":"Barauchhi",
    "tgn:placetype":[
        "aat:300008347"
    ]
},
  "bbox": [],
  "geometry": {"coordinates":[79.914128,26.583722],"type":"Point"}
}