{
  "id": 2129268,
  "type": "Feature",
  "properties": {
    "tgn:hierarchy":[
        "tgn:2129268",
        "tgn:1000001",
        "tgn:2001268",
        "tgn:7012149",
        "tgn:7007524",
        "tgn:7029392"
    ],
    "tgn:id":2129268,
    "tgn:name":"Alice Creek",
    "tgn:placetype":[
        "aat:300008706"
    ]
},
  "bbox": [],
  "geometry": {"coordinates":[-105.15,46.2333],"type":"Point"}
}