{
  "id": 2410727,
  "type": "Feature",
  "properties": {
    "tgn:hierarchy":[
        "tgn:2410727",
        "tgn:1000001",
        "tgn:7012149",
        "tgn:1002623",
        "tgn:7007252",
        "tgn:7029392"
    ],
    "tgn:id":2410727,
    "tgn:name":"Indian Creek",
    "tgn:placetype":[
        "aat:300008706"
    ]
},
  "bbox": [],
  "geometry": {"coordinates":[-85.7333,40.1833],"type":"Point"}
}