{
  "id": 2410330,
  "type": "Feature",
  "properties": {
    "tgn:hierarchy":[
        "tgn:2410330",
        "tgn:1002538",
        "tgn:1000001",
        "tgn:7012149",
        "tgn:7007239",
        "tgn:7029392"
    ],
    "tgn:id":2410330,
    "tgn:name":"Indian Branch",
    "tgn:placetype":[
        "aat:300008699"
    ]
},
  "bbox": [],
  "geometry": {"coordinates":[-75.5167,38.95],"type":"Point"}
}