{
  "id": 7103275,
  "type": "Feature",
  "properties": {
    "tgn:hierarchy":[
        "tgn:7103275",
        "tgn:7000096",
        "tgn:1000003",
        "tgn:7000084",
        "tgn:7029392"
    ],
    "tgn:id":7103275,
    "tgn:name":"Saathain",
    "tgn:placetype":[
        "aat:300008347"
    ]
},
  "bbox": [],
  "geometry": {"coordinates":[13.466667,51.466667],"type":"Point"}
}