{
  "id": 7383032,
  "type": "Feature",
  "properties": {
    "tgn:hierarchy":[
        "tgn:7383032",
        "tgn:1000001",
        "tgn:1001960",
        "tgn:7005560",
        "tgn:7029392"
    ],
    "tgn:id":7383032,
    "tgn:name":"Or\u00e9gano",
    "tgn:placetype":[
        "aat:300008347"
    ]
},
  "bbox": [],
  "geometry": {"coordinates":[-110.75,29.25],"type":"Point"}
}