{
  "id": 7218838,
  "type": "Feature",
  "properties": {
    "tgn:hierarchy":[
        "tgn:7218838",
        "tgn:7011161",
        "tgn:7002674",
        "tgn:1000003",
        "tgn:1000074",
        "tgn:7029392"
    ],
    "tgn:id":7218838,
    "tgn:name":"Kalov\u00f3tsi Vr\u00fdsi",
    "tgn:placetype":[
        "aat:300008697"
    ]
},
  "bbox": [],
  "geometry": {"coordinates":[26.087778,38.260556],"type":"Point"}
}