{
  "id": 2023593,
  "type": "Feature",
  "properties": {
    "tgn:hierarchy":[
        "tgn:2023593",
        "tgn:1000001",
        "tgn:7012149",
        "tgn:2000342",
        "tgn:7007248",
        "tgn:7029392"
    ],
    "tgn:id":2023593,
    "tgn:name":"Meldrim",
    "tgn:placetype":[
        "aat:300008347"
    ]
},
  "bbox": [],
  "geometry": {"coordinates":[-81.3667,32.1333],"type":"Point"}
}