<<<<<<< HEAD
{
  "id": 2150372,
  "type": "Feature",
  "properties": {
    "tgn:hierarchy":[
        "tgn:2150372",
        "tgn:1000001",
        "tgn:7012149",
        "tgn:2000290",
        "tgn:7007240",
        "tgn:7029392"
    ],
    "tgn:id":2150372,
    "tgn:name":"Basin Creek",
    "tgn:placetype":[
        "aat:300008706"
    ]
},
  "bbox": [],
  "geometry": {"coordinates":[-86.3333,30.55],"type":"Point"}
}
=======
{"geometry":{"type":"Point","coordinates":[-86.333300,30.550000]},"type":"Feature","properties":{"hierarchy":["tgn:2150372","tgn:1000001","tgn:7012149","tgn:2000290","tgn:7007240","tgn:7029392"],"placetype":["aat:300008706"],"id":2150372,"name:xx":"Basin Creek"}}
>>>>>>> 03f74aca74312dbeaf24d7e61306dd6a786dc3d0
