<<<<<<< HEAD
{
  "id": 2252339,
  "type": "Feature",
  "properties": {
    "tgn:hierarchy":[
        "tgn:2252339",
        "tgn:1000001",
        "tgn:7012149",
        "tgn:7007711",
        "tgn:7029392"
    ],
    "tgn:id":2252339,
    "tgn:name":"Congdon River",
    "tgn:placetype":[
        "aat:300008707"
    ]
},
  "bbox": [],
  "geometry": {"coordinates":[-71.6167,41.5833],"type":"Point"}
}
=======
{"geometry":{"type":"Point","coordinates":[-71.616700,41.583300]},"type":"Feature","properties":{"hierarchy":["tgn:2252339","tgn:1000001","tgn:7012149","tgn:7007711","tgn:7029392"],"placetype":["aat:300008707"],"id":2252339,"name:xx":"Congdon River"}}
>>>>>>> 03f74aca74312dbeaf24d7e61306dd6a786dc3d0
