{
  "id": 7550172,
  "type": "Feature",
  "properties": {
    "tgn:hierarchy":[
        "tgn:7550172",
        "tgn:1000004",
        "tgn:7000198",
        "tgn:1001894",
        "tgn:7029392"
    ],
    "tgn:id":7550172,
    "tgn:name:en":"Bishankhera",
    "tgn:placetype":[
        "aat:300008347"
    ]
},
  "bbox": [],
  "geometry": {"coordinates":[77.574183,23.023493],"type":"Point"}
}