{
  "id": 7208675,
  "type": "Feature",
  "properties": {
    "tgn:hierarchy":[
        "tgn:7208675",
        "tgn:7000096",
        "tgn:1000003",
        "tgn:7000084",
        "tgn:7029392"
    ],
    "tgn:id":7208675,
    "tgn:name":"Beerbaumer Forst",
    "tgn:placetype":[
        "aat:300008863"
    ]
},
  "bbox": [],
  "geometry": {"coordinates":[13.783333,52.75],"type":"Point"}
}