{
  "id": 1073982,
  "type": "Feature",
  "properties": {
    "tgn:hierarchy":[
        "tgn:1073982",
        "tgn:1000004",
        "tgn:7002087",
        "tgn:1000111",
        "tgn:7029392"
    ],
    "tgn:id":1073982,
    "tgn:name":"Zhengzichang",
    "tgn:placetype":[
        "aat:300008347"
    ]
},
  "bbox": [],
  "geometry": {"coordinates":[106.6333,29.1333],"type":"Point"}
}