{
  "id": 2456158,
  "type": "Feature",
  "properties": {
    "tgn:hierarchy":[
        "tgn:2456158",
        "tgn:1000001",
        "tgn:7012149",
        "tgn:2001420",
        "tgn:7007526",
        "tgn:7029392"
    ],
    "tgn:id":2456158,
    "tgn:name":"Little Hills",
    "tgn:placetype":[
        "aat:300386831"
    ]
},
  "bbox": [],
  "geometry": {"coordinates":[-114.25,39.5667],"type":"Point"}
}