{
  "id": 7593036,
  "type": "Feature",
  "properties": {
    "tgn:hierarchy":[
        "tgn:7593036",
        "tgn:1000004",
        "tgn:7000198",
        "tgn:7000799",
        "tgn:7029392"
    ],
    "tgn:id":7593036,
    "tgn:name:en":"Titichhung",
    "tgn:placetype":[
        "aat:300008347"
    ]
},
  "bbox": [],
  "geometry": {"coordinates":[76.133333,34.523611],"type":"Point"}
}