<<<<<<< HEAD
{
  "id": 2405791,
  "type": "Feature",
  "properties": {
    "tgn:hierarchy":[
        "tgn:2405791",
        "tgn:1000001",
        "tgn:7012149",
        "tgn:2001120",
        "tgn:7007522",
        "tgn:7029392"
    ],
    "tgn:id":2405791,
    "tgn:name":"Hull Branch",
    "tgn:placetype":[
        "aat:300008699"
    ]
},
  "bbox": [],
  "geometry": {"coordinates":[-88.7,32.75],"type":"Point"}
}
=======
{"geometry":{"type":"Point","coordinates":[-88.700000,32.750000]},"type":"Feature","properties":{"hierarchy":["tgn:2405791","tgn:1000001","tgn:7012149","tgn:2001120","tgn:7007522","tgn:7029392"],"placetype":["aat:300008699"],"id":2405791,"name:xx":"Hull Branch"}}
>>>>>>> 03f74aca74312dbeaf24d7e61306dd6a786dc3d0
