{
  "id": 7149483,
  "type": "Feature",
  "properties": {
    "tgn:hierarchy":[
        "tgn:7149483",
        "tgn:7003692",
        "tgn:1000003",
        "tgn:7000084",
        "tgn:7029392"
    ],
    "tgn:id":7149483,
    "tgn:name":"Lammh\u00f6fe",
    "tgn:placetype":[
        "aat:300000206"
    ]
},
  "bbox": [],
  "geometry": {"coordinates":[8.15,48.583333],"type":"Point"}
}