{
  "id": 7398693,
  "type": "Feature",
  "properties": {
    "tgn:hierarchy":[
        "tgn:7398693",
        "tgn:1000001",
        "tgn:7005593",
        "tgn:7005560",
        "tgn:7029392"
    ],
    "tgn:id":7398693,
    "tgn:name":"San Carlos, Poza",
    "tgn:placetype":[
        "aat:300008697"
    ]
},
  "bbox": [],
  "geometry": {"coordinates":[-100.258333,20.545833],"type":"Point"}
}