{
  "id": 2316248,
  "type": "Feature",
  "properties": {
    "tgn:hierarchy":[
        "tgn:2316248",
        "tgn:1000001",
        "tgn:7012149",
        "tgn:1002401",
        "tgn:7007826",
        "tgn:7029392"
    ],
    "tgn:id":2316248,
    "tgn:name":"Elmgrove",
    "tgn:placetype":[
        "aat:300132451"
    ]
},
  "bbox": [],
  "geometry": {"coordinates":[-94.6667,29.45],"type":"Point"}
}