{
  "id": 2129676,
  "type": "Feature",
  "properties": {
    "tgn:hierarchy":[
        "tgn:2129676",
        "tgn:1000001",
        "tgn:7012149",
        "tgn:2000182",
        "tgn:7007157",
        "tgn:7029392"
    ],
    "tgn:id":2129676,
    "tgn:name":"All American Drain Thirteen",
    "tgn:placetype":[
        "aat:300006075"
    ]
},
  "bbox": [],
  "geometry": {"coordinates":[-115.6333,32.65],"type":"Point"}
}