<<<<<<< HEAD
{
  "id": 7171881,
  "type": "Feature",
  "properties": {
    "tgn:hierarchy":[
        "tgn:7171881",
        "tgn:1000003",
        "tgn:7003677",
        "tgn:7000084",
        "tgn:7029392"
    ],
    "tgn:id":7171881,
    "tgn:name":"Herrloh",
    "tgn:placetype":[
        "aat:300008795"
    ]
},
  "bbox": [],
  "geometry": {"coordinates":[8.516667,51.2],"type":"Point"}
}
=======
{"geometry":{"type":"Point","coordinates":[8.516667,51.200000]},"type":"Feature","properties":{"hierarchy":["tgn:7171881","tgn:1000003","tgn:7003677","tgn:7000084","tgn:7029392"],"placetype":["aat:300008795"],"id":7171881,"name:xx":"Herrloh"}}
>>>>>>> 03f74aca74312dbeaf24d7e61306dd6a786dc3d0
