{
  "id": 7391495,
  "type": "Feature",
  "properties": {
    "tgn:hierarchy":[
        "tgn:7391495",
        "tgn:7005581",
        "tgn:1000001",
        "tgn:7005560",
        "tgn:7029392"
    ],
    "tgn:id":7391495,
    "tgn:name":"Rancho La Salada",
    "tgn:placetype":[
        "aat:300008347"
    ]
},
  "bbox": [],
  "geometry": {"coordinates":[-108.083333,31.233333],"type":"Point"}
}