{
  "id": 7143005,
  "type": "Feature",
  "properties": {
    "tgn:hierarchy":[
        "tgn:7143005",
        "tgn:7003669",
        "tgn:1000003",
        "tgn:7000084",
        "tgn:7029392"
    ],
    "tgn:id":7143005,
    "tgn:name":"Loh Bach",
    "tgn:placetype":[
        "aat:300008699"
    ]
},
  "bbox": [],
  "geometry": {"coordinates":[11.75,47.666667],"type":"Point"}
}