{
  "id": 7453375,
  "type": "Feature",
  "properties": {
    "tgn:hierarchy":[
        "tgn:7453375",
        "tgn:7002444",
        "tgn:1000003",
        "tgn:5000460",
        "tgn:7008591",
        "tgn:7029392"
    ],
    "tgn:id":7453375,
    "tgn:name:en":"Dochart, Loch",
    "tgn:placetype":[
        "aat:300008680"
    ]
},
  "bbox": [],
  "geometry": {"coordinates":[-4.583333,56.383333],"type":"Point"}
}