{
  "id": 7328935,
  "type": "Feature",
  "properties": {
    "tgn:hierarchy":[
        "tgn:7328935",
        "tgn:7002818",
        "tgn:1001647",
        "tgn:1000003",
        "tgn:1000095",
        "tgn:7029392"
    ],
    "tgn:id":7328935,
    "tgn:name":"Redonda, Laguna",
    "tgn:placetype":[
        "aat:300008688"
    ]
},
  "bbox": [],
  "geometry": {"coordinates":[-2.316667,39.583333],"type":"Point"}
}