{
  "id": 2500733,
  "type": "Feature",
  "properties": {
    "tgn:hierarchy":[
        "tgn:2500733",
        "tgn:1000001",
        "tgn:7012149",
        "tgn:2001718",
        "tgn:7007708",
        "tgn:7029392"
    ],
    "tgn:id":2500733,
    "tgn:name":"McDowell Spring",
    "tgn:placetype":[
        "aat:300008697"
    ]
},
  "bbox": [],
  "geometry": {"coordinates":[-117.3167,44.2167],"type":"Point"}
}