{
  "id": 1044699,
  "type": "Feature",
  "properties": {
    "tgn:hierarchy":[
        "tgn:1044699",
        "tgn:1000003",
        "tgn:7003122",
        "tgn:1001753",
        "tgn:1000080",
        "tgn:7029392"
    ],
    "tgn:id":1044699,
    "tgn:name":"Francofonte",
    "tgn:placetype":[
        "aat:300008347"
    ]
},
  "bbox": [],
  "geometry": {"coordinates":[14.883333,37.233333],"type":"Point"}
}