{
  "id": 1068222,
  "type": "Feature",
  "properties": {
    "tgn:hierarchy":[
        "tgn:1068222",
        "tgn:1000004",
        "tgn:1001390",
        "tgn:1000111",
        "tgn:7029392"
    ],
    "tgn:id":1068222,
    "tgn:name":"Gaojiawopeng",
    "tgn:placetype":[
        "aat:300008347"
    ]
},
  "bbox": [],
  "geometry": {"coordinates":[122.1667,41.4667],"type":"Point"}
}