{
  "id": 2159724,
  "type": "Feature",
  "properties": {
    "tgn:hierarchy":[
        "tgn:2159724",
        "tgn:1000001",
        "tgn:7013638",
        "tgn:7012149",
        "tgn:7007568",
        "tgn:7029392"
    ],
    "tgn:id":2159724,
    "tgn:name":"Beebe Pond",
    "tgn:placetype":[
        "aat:300008680"
    ]
},
  "bbox": [],
  "geometry": {"coordinates":[-73.4167,42.3833],"type":"Point"}
}