<<<<<<< HEAD
{
  "id": 2159724,
  "type": "Feature",
  "properties": {
    "tgn:hierarchy":[
        "tgn:2159724",
        "tgn:1000001",
        "tgn:7013638",
        "tgn:7012149",
        "tgn:7007568",
        "tgn:7029392"
    ],
    "tgn:id":2159724,
    "tgn:name":"Beebe Pond",
    "tgn:placetype":[
        "aat:300008680"
    ]
},
  "bbox": [],
  "geometry": {"coordinates":[-73.4167,42.3833],"type":"Point"}
}
=======
{"geometry":{"type":"Point","coordinates":[-73.416700,42.383300]},"type":"Feature","properties":{"hierarchy":["tgn:2159724","tgn:1000001","tgn:7013638","tgn:7012149","tgn:7007568","tgn:7029392"],"placetype":["aat:300008680"],"id":2159724,"name:xx":"Beebe Pond"}}
>>>>>>> 03f74aca74312dbeaf24d7e61306dd6a786dc3d0
