{
  "id": 2770837,
  "type": "Feature",
  "properties": {
    "tgn:hierarchy":[
        "tgn:2770837",
        "tgn:1000001",
        "tgn:7012149",
        "tgn:2001698",
        "tgn:7007707",
        "tgn:7029392"
    ],
    "tgn:id":2770837,
    "tgn:name":"Wildcat Creek",
    "tgn:placetype":[
        "aat:300008706"
    ]
},
  "bbox": [],
  "geometry": {"coordinates":[-98.7667,36.5833],"type":"Point"}
}