{
  "id": 2361425,
  "type": "Feature",
  "properties": {
    "tgn:hierarchy":[
        "tgn:2361425",
        "tgn:1000001",
        "tgn:7012149",
        "tgn:7029392"
    ],
    "tgn:id":2361425,
    "tgn:name":"Gravelly Run",
    "tgn:placetype":[
        "aat:300008699"
    ]
},
  "bbox": [],
  "geometry": {"coordinates":[-75.6833,39.1667],"type":"Point"}
}