{
  "id": 7322757,
  "type": "Feature",
  "properties": {
    "tgn:hierarchy":[
        "tgn:7322757",
        "tgn:7002836",
        "tgn:7016622",
        "tgn:1000003",
        "tgn:1000095",
        "tgn:7029392"
    ],
    "tgn:id":7322757,
    "tgn:name":"Sancha, Punta",
    "tgn:placetype":[
        "aat:300386846"
    ]
},
  "bbox": [],
  "geometry": {"coordinates":[-17.716667,28.716667],"type":"Point"}
}