{
  "id": 7492204,
  "type": "Feature",
  "properties": {
    "tgn:hierarchy":[
        "tgn:7492204",
        "tgn:1000004",
        "tgn:7001002",
        "tgn:1000141",
        "tgn:7029392"
    ],
    "tgn:id":7492204,
    "tgn:name":"Shulintou",
    "tgn:placetype":[
        "aat:300008347"
    ]
},
  "bbox": [],
  "geometry": {"coordinates":[120.956111,24.823889],"type":"Point"}
}