{
  "id": 2779924,
  "type": "Feature",
  "properties": {
    "tgn:hierarchy":[
        "tgn:2779924",
        "tgn:1000001",
        "tgn:7012149",
        "tgn:2000548",
        "tgn:7007252",
        "tgn:7029392"
    ],
    "tgn:id":2779924,
    "tgn:name":"Wolfe Hill",
    "tgn:placetype":[
        "aat:300008798"
    ]
},
  "bbox": [],
  "geometry": {"coordinates":[-86.85,39.2667],"type":"Point"}
}