{
  "id": 7433618,
  "type": "Feature",
  "properties": {
    "tgn:hierarchy":[
        "tgn:7433618",
        "tgn:1000001",
        "tgn:7005597",
        "tgn:7005560",
        "tgn:7029392"
    ],
    "tgn:id":7433618,
    "tgn:name":"Vergeles",
    "tgn:placetype":[
        "aat:300008347"
    ]
},
  "bbox": [],
  "geometry": {"coordinates":[-98.883333,24.45],"type":"Point"}
}