{
  "id": 7231755,
  "type": "Feature",
  "properties": {
    "tgn:hierarchy":[
        "tgn:7231755",
        "tgn:7002750",
        "tgn:7001399",
        "tgn:1000003",
        "tgn:1000074",
        "tgn:7029392"
    ],
    "tgn:id":7231755,
    "tgn:name":"Kaliako\u00fadhas R\u00e9ma",
    "tgn:placetype":[
        "aat:300008699"
    ]
},
  "bbox": [],
  "geometry": {"coordinates":[22.933333,39.433333],"type":"Point"}
}