{
  "id": 2456160,
  "type": "Feature",
  "properties": {
    "tgn:hierarchy":[
        "tgn:2456160",
        "tgn:1000001",
        "tgn:7012149",
        "tgn:1003042",
        "tgn:7007920",
        "tgn:7029392"
    ],
    "tgn:id":2456160,
    "tgn:name":"Little Hindoo Creek",
    "tgn:placetype":[
        "aat:300008706"
    ]
},
  "bbox": [],
  "geometry": {"coordinates":[-121.2333,46.75],"type":"Point"}
}