{
  "id": 7552267,
  "type": "Feature",
  "properties": {
    "tgn:hierarchy":[
        "tgn:7552267",
        "tgn:1000004",
        "tgn:7000198",
        "tgn:7016722",
        "tgn:7029392"
    ],
    "tgn:id":7552267,
    "tgn:name:en":"Mani\u0101ri Al\u012bganj",
    "tgn:placetype":[
        "aat:300008347"
    ]
},
  "bbox": [],
  "geometry": {"coordinates":[81.87877,26.32945],"type":"Point"}
}