{
  "id": 7282079,
  "type": "Feature",
  "properties": {
    "tgn:hierarchy":[
        "tgn:7282079",
        "tgn:1001708",
        "tgn:1000049",
        "tgn:1000002",
        "tgn:7029392"
    ],
    "tgn:id":7282079,
    "tgn:name":"Salto de Agua, Estero",
    "tgn:placetype":[
        "aat:300008699"
    ]
},
  "bbox": [],
  "geometry": {"coordinates":[-70.15,-33.816667],"type":"Point"}
}