<<<<<<< HEAD
{
  "id": 7487514,
  "type": "Feature",
  "properties": {
    "tgn:hierarchy":[
        "tgn:7487514",
        "tgn:7001004",
        "tgn:1000004",
        "tgn:1000141",
        "tgn:7029392"
    ],
    "tgn:id":7487514,
    "tgn:name":"Mituo",
    "tgn:placetype":[
        "aat:300008347"
    ]
},
  "bbox": [],
  "geometry": {"coordinates":[120.2475,22.784722],"type":"Point"}
}
=======
{"geometry":{"type":"Point","coordinates":[120.247500,22.784722]},"type":"Feature","properties":{"hierarchy":["tgn:7487514","tgn:7001004","tgn:1000004","tgn:1000141","tgn:7029392"],"placetype":["aat:300008347"],"id":7487514,"name:xx":"Mituo"}}
>>>>>>> 03f74aca74312dbeaf24d7e61306dd6a786dc3d0
