{
  "id": 7487514,
  "type": "Feature",
  "properties": {
    "tgn:hierarchy":[
        "tgn:7487514",
        "tgn:7001004",
        "tgn:1000004",
        "tgn:1000141",
        "tgn:7029392"
    ],
    "tgn:id":7487514,
    "tgn:name":"Mituo",
    "tgn:placetype":[
        "aat:300008347"
    ]
},
  "bbox": [],
  "geometry": {"coordinates":[120.2475,22.784722],"type":"Point"}
}