{
  "id": 2776211,
  "type": "Feature",
  "properties": {
    "tgn:hierarchy":[
        "tgn:2776211",
        "tgn:1000001",
        "tgn:7012149",
        "tgn:7014543",
        "tgn:7007248",
        "tgn:7029392"
    ],
    "tgn:id":2776211,
    "tgn:name":"Wimberly Mill Branch",
    "tgn:placetype":[
        "aat:300008699"
    ]
},
  "bbox": [],
  "geometry": {"coordinates":[-84.7667,32.0833],"type":"Point"}
}