{
  "id": 1094307,
  "type": "Feature",
  "properties": {
    "tgn:hierarchy":[
        "tgn:1094307",
        "tgn:7001242",
        "tgn:1001056",
        "tgn:7441551",
        "tgn:7029392"
    ],
    "tgn:id":1094307,
    "tgn:name":"Kigille",
    "tgn:placetype":[
        "aat:300008347"
    ]
},
  "bbox": [],
  "geometry": {"coordinates":[34.0167,8.6667],"type":"Point"}
}