{
  "id": 7560504,
  "type": "Feature",
  "properties": {
    "tgn:hierarchy":[
        "tgn:7560504",
        "tgn:1000004",
        "tgn:7000198",
        "tgn:7016722",
        "tgn:7029392"
    ],
    "tgn:id":7560504,
    "tgn:name:en":"Al\u012bpura",
    "tgn:placetype":[
        "aat:300008347"
    ]
},
  "bbox": [],
  "geometry": {"coordinates":[79.239347,26.866994],"type":"Point"}
}