{
  "id": 2649277,
  "type": "Feature",
  "properties": {
    "tgn:hierarchy":[
        "tgn:2649277",
        "tgn:1000001",
        "tgn:7012149",
        "tgn:7007157",
        "tgn:1002863",
        "tgn:7029392"
    ],
    "tgn:id":2649277,
    "tgn:name":"Scott Rock",
    "tgn:placetype":[
        "aat:300008798"
    ]
},
  "bbox": [],
  "geometry": {"coordinates":[-121.0667,35.5667],"type":"Point"}
}