{
  "id": 1036279,
  "type": "Feature",
  "properties": {
    "tgn:hierarchy":[
        "tgn:1036279",
        "tgn:7002870",
        "tgn:1000003",
        "tgn:1000070",
        "tgn:7029392"
    ],
    "tgn:id":1036279,
    "tgn:name":"Wildenstein",
    "tgn:placetype":[
        "aat:300008347"
    ]
},
  "bbox": [],
  "geometry": {"coordinates":[6.9833,47.9667],"type":"Point"}
}