{
  "id": 7302030,
  "type": "Feature",
  "properties": {
    "tgn:hierarchy":[
        "tgn:7302030",
        "tgn:7008911",
        "tgn:1000003",
        "tgn:7002763",
        "tgn:1000095",
        "tgn:7029392"
    ],
    "tgn:id":7302030,
    "tgn:name":"Mezana",
    "tgn:placetype":[
        "aat:300008347"
    ]
},
  "bbox": [],
  "geometry": {"coordinates":[-6.733333,43.416667],"type":"Point"}
}