{
  "id": 7530678,
  "type": "Feature",
  "properties": {
    "tgn:hierarchy":[
        "tgn:7530678",
        "tgn:7001242",
        "tgn:7016833",
        "tgn:1001083",
        "tgn:7029392"
    ],
    "tgn:id":7530678,
    "tgn:name":"Ash Shirkah ash Sharq\u012byah lil Dukh\u0101n",
    "tgn:placetype":[
        "aat:300004792"
    ]
},
  "bbox": [],
  "geometry": {"coordinates":[31.18968,29.999076],"type":"Point"}
}