{
  "id": 2126241,
  "type": "Feature",
  "properties": {
    "tgn:hierarchy":[
        "tgn:2126241",
        "tgn:1000001",
        "tgn:7012149",
        "tgn:2001155",
        "tgn:7007522",
        "tgn:7029392"
    ],
    "tgn:id":2126241,
    "tgn:name":"Adkins Bottom",
    "tgn:placetype":[
        "aat:300008761"
    ]
},
  "bbox": [],
  "geometry": {"coordinates":[-88.9333,34.6833],"type":"Point"}
}