<<<<<<< HEAD
{
  "id": 7357853,
  "type": "Feature",
  "properties": {
    "tgn:hierarchy":[
        "tgn:7357853",
        "tgn:7005581",
        "tgn:1000001",
        "tgn:7005560",
        "tgn:7029392"
    ],
    "tgn:id":7357853,
    "tgn:name":"Corrillo, Puerto del",
    "tgn:placetype":[
        "aat:300259572"
    ]
},
  "bbox": [],
  "geometry": {"coordinates":[-107.65,29.766667],"type":"Point"}
}
=======
{"geometry":{"type":"Point","coordinates":[-107.650000,29.766667]},"type":"Feature","properties":{"hierarchy":["tgn:7357853","tgn:7005581","tgn:1000001","tgn:7005560","tgn:7029392"],"placetype":["aat:300259572"],"id":7357853,"name:xx":"Corrillo, Puerto del"}}
>>>>>>> 03f74aca74312dbeaf24d7e61306dd6a786dc3d0
