{
  "id": 2649877,
  "type": "Feature",
  "properties": {
    "tgn:hierarchy":[
        "tgn:2649877",
        "tgn:1000001",
        "tgn:7016172",
        "tgn:7012149",
        "tgn:7029392"
    ],
    "tgn:id":2649877,
    "tgn:name":"Scrubgrass Bayou",
    "tgn:placetype":[
        "aat:300008699"
    ]
},
  "bbox": [],
  "geometry": {"coordinates":[-91.0667,34.0167],"type":"Point"}
}