{
  "id": 7456912,
  "type": "Feature",
  "properties": {
    "tgn:hierarchy":[
        "tgn:7456912",
        "tgn:7002444",
        "tgn:1000003",
        "tgn:7029508",
        "tgn:7008591",
        "tgn:7029392"
    ],
    "tgn:id":7456912,
    "tgn:name:en":"Noup, The",
    "tgn:placetype":[
        "aat:300386846"
    ]
},
  "bbox": [],
  "geometry": {"coordinates":[-0.833333,60.85],"type":"Point"}
}