<<<<<<< HEAD
{
  "id": 7053317,
  "type": "Feature",
  "properties": {
    "tgn:hierarchy":[
        "tgn:7053317",
        "tgn:7015163",
        "tgn:1000003",
        "tgn:7003121",
        "tgn:1000080",
        "tgn:7029392"
    ],
    "tgn:id":7053317,
    "tgn:name":"Maestra Fornelli, Punta",
    "tgn:placetype":[
        "aat:300008795"
    ]
},
  "bbox": [],
  "geometry": {"coordinates":[8.231389,41.005278],"type":"Point"}
}
=======
{"geometry":{"type":"Point","coordinates":[8.231389,41.005278]},"type":"Feature","properties":{"hierarchy":["tgn:7053317","tgn:7015163","tgn:1000003","tgn:7003121","tgn:1000080","tgn:7029392"],"placetype":["aat:300008795"],"id":7053317,"name:xx":"Maestra Fornelli, Punta"}}
>>>>>>> 03f74aca74312dbeaf24d7e61306dd6a786dc3d0
