<<<<<<< HEAD
{
  "id": 7367019,
  "type": "Feature",
  "properties": {
    "tgn:hierarchy":[
        "tgn:7367019",
        "tgn:7005586",
        "tgn:1000001",
        "tgn:7005560",
        "tgn:7029392"
    ],
    "tgn:id":7367019,
    "tgn:name":"El Rodeo",
    "tgn:placetype":[
        "aat:300006191"
    ]
},
  "bbox": [],
  "geometry": {"coordinates":[-102.316667,20.8],"type":"Point"}
}
=======
{"geometry":{"type":"Point","coordinates":[-102.316667,20.800000]},"type":"Feature","properties":{"hierarchy":["tgn:7367019","tgn:7005586","tgn:1000001","tgn:7005560","tgn:7029392"],"placetype":["aat:300006191"],"id":7367019,"name:xx":"El Rodeo"}}
>>>>>>> 03f74aca74312dbeaf24d7e61306dd6a786dc3d0
