<<<<<<< HEAD
{
  "id": 7026999,
  "type": "Feature",
  "properties": {
    "tgn:hierarchy":[
        "tgn:7026999",
        "tgn:7002445",
        "tgn:1000003",
        "tgn:7008143",
        "tgn:7008591",
        "tgn:7029392"
    ],
    "tgn:id":7026999,
    "tgn:name:en":"Bacton",
    "tgn:placetype":[
        "aat:300008347",
        "aat:300008372"
    ]
},
  "bbox": [],
  "geometry": {"coordinates":[-2.916667,51.983333],"type":"Point"}
}
=======
{"geometry":{"type":"Point","coordinates":[-2.916667,51.983333]},"type":"Feature","properties":{"hierarchy":["tgn:7026999","tgn:7002445","tgn:1000003","tgn:7008143","tgn:7008591","tgn:7029392"],"placetype":["aat:300008347","aat:300008372"],"name:en":"Bacton","id":7026999}}
>>>>>>> 03f74aca74312dbeaf24d7e61306dd6a786dc3d0
