{
  "id": 7338886,
  "type": "Feature",
  "properties": {
    "tgn:hierarchy":[
        "tgn:7338886",
        "tgn:7001155",
        "tgn:1000003",
        "tgn:7002790",
        "tgn:1000095",
        "tgn:7029392"
    ],
    "tgn:id":7338886,
    "tgn:name":"Cornialto",
    "tgn:placetype":[
        "aat:300008795"
    ]
},
  "bbox": [],
  "geometry": {"coordinates":[-1.45,42.283333],"type":"Point"}
}