{
  "id": 1087964,
  "type": "Feature",
  "properties": {
    "tgn:hierarchy":[
        "tgn:1087964",
        "tgn:7001242",
        "tgn:1000149",
        "tgn:1000867",
        "tgn:7029392"
    ],
    "tgn:id":1087964,
    "tgn:name":"Quilengues",
    "tgn:placetype":[
        "aat:300008347"
    ]
},
  "bbox": [],
  "geometry": {"coordinates":[14.0667,-14.15],"type":"Point"}
}