{
  "id": 7022336,
  "type": "Feature",
  "properties": {
    "tgn:hierarchy":[
        "tgn:7022336",
        "tgn:1000001",
        "tgn:7012149",
        "tgn:7007516",
        "tgn:7029392"
    ],
    "tgn:id":7022336,
    "tgn:name":"Bar Neck",
    "tgn:placetype":[
        "aat:300387210",
        "aat:300008850"
    ]
},
  "bbox": [],
  "geometry": {"coordinates":[-76.3167,38.6833],"type":"Point"}
}