{
  "id": 2245225,
  "type": "Feature",
  "properties": {
    "tgn:hierarchy":[
        "tgn:2245225",
        "tgn:2001731",
        "tgn:1000001",
        "tgn:7012149",
        "tgn:7007712",
        "tgn:7029392"
    ],
    "tgn:id":2245225,
    "tgn:name":"Club Bridge Creek",
    "tgn:placetype":[
        "aat:300008706"
    ]
},
  "bbox": [],
  "geometry": {"coordinates":[-80.5667,32.35],"type":"Point"}
}