{
  "id": 2394455,
  "type": "Feature",
  "properties": {
    "tgn:hierarchy":[
        "tgn:2394455",
        "tgn:1000001",
        "tgn:7012149",
        "tgn:2001916",
        "tgn:7007825",
        "tgn:7029392"
    ],
    "tgn:id":2394455,
    "tgn:name":"Hoggtown Branch",
    "tgn:placetype":[
        "aat:300008699"
    ]
},
  "bbox": [],
  "geometry": {"coordinates":[-85.9333,36.3167],"type":"Point"}
}