{
  "id": 2223852,
  "type": "Feature",
  "properties": {
    "tgn:hierarchy":[
        "tgn:2223852",
        "tgn:1000001",
        "tgn:7012149",
        "tgn:2001274",
        "tgn:7007524",
        "tgn:7029392"
    ],
    "tgn:id":2223852,
    "tgn:name":"Carter, Mount",
    "tgn:placetype":[
        "aat:300008798"
    ]
},
  "bbox": [],
  "geometry": {"coordinates":[-114.0667,48.8833],"type":"Point"}
}