{
  "id": 1083707,
  "type": "Feature",
  "properties": {
    "tgn:hierarchy":[
        "tgn:1083707",
        "tgn:1000004",
        "tgn:1001490",
        "tgn:1000133",
        "tgn:7029392"
    ],
    "tgn:id":1083707,
    "tgn:name":"Pattoki",
    "tgn:placetype":[
        "aat:300008347"
    ]
},
  "bbox": [],
  "geometry": {"coordinates":[73.85,31.0167],"type":"Point"}
}