{
  "id": 1075418,
  "type": "Feature",
  "properties": {
    "tgn:hierarchy":[
        "tgn:1075418",
        "tgn:1000004",
        "tgn:7000198",
        "tgn:1001977",
        "tgn:7029392"
    ],
    "tgn:id":1075418,
    "tgn:name":"H\u0101hipur",
    "tgn:placetype":[
        "aat:300008347"
    ]
},
  "bbox": [],
  "geometry": {"coordinates":[88.1667,22.7833],"type":"Point"}
}