{
  "id": 7170681,
  "type": "Feature",
  "properties": {
    "tgn:hierarchy":[
        "tgn:7170681",
        "tgn:7003669",
        "tgn:1000003",
        "tgn:7000084",
        "tgn:7029392"
    ],
    "tgn:id":7170681,
    "tgn:name":"Hinang",
    "tgn:placetype":[
        "aat:300008347"
    ]
},
  "bbox": [],
  "geometry": {"coordinates":[10.283333,47.466667],"type":"Point"}
}