{
  "id": 2228661,
  "type": "Feature",
  "properties": {
    "tgn:hierarchy":[
        "tgn:2228661",
        "tgn:1000001",
        "tgn:7012149",
        "tgn:7007157",
        "tgn:2000189",
        "tgn:7029392"
    ],
    "tgn:id":2228661,
    "tgn:name":"Cedar Crest",
    "tgn:placetype":[
        "aat:300266640"
    ]
},
  "bbox": [],
  "geometry": {"coordinates":[-123.5833,41.7833],"type":"Point"}
}