{
  "id": 7580712,
  "type": "Feature",
  "properties": {
    "tgn:hierarchy":[
        "tgn:7580712",
        "tgn:1000004",
        "tgn:1001869",
        "tgn:7000198",
        "tgn:7029392"
    ],
    "tgn:id":7580712,
    "tgn:name:en":"Val\u0101sana",
    "tgn:placetype":[
        "aat:300008347"
    ]
},
  "bbox": [],
  "geometry": {"coordinates":[72.782965,23.828238],"type":"Point"}
}