{
  "id": 7533176,
  "type": "Feature",
  "properties": {
    "tgn:hierarchy":[
        "tgn:7533176",
        "tgn:7001242",
        "tgn:7016833",
        "tgn:1001335",
        "tgn:7029392"
    ],
    "tgn:id":7533176,
    "tgn:name:en":"Kawm Ab\u016b Rayyah",
    "tgn:placetype":[
        "aat:300008347"
    ]
},
  "bbox": [],
  "geometry": {"coordinates":[30.977687,31.23162],"type":"Point"}
}