{
  "id": 2487950,
  "type": "Feature",
  "properties": {
    "tgn:hierarchy":[
        "tgn:2487950",
        "tgn:1000001",
        "tgn:7012149",
        "tgn:2000963",
        "tgn:7007520",
        "tgn:7029392"
    ],
    "tgn:id":2487950,
    "tgn:name":"Maggie Lake",
    "tgn:placetype":[
        "aat:300008680"
    ]
},
  "bbox": [],
  "geometry": {"coordinates":[-88.8833,46.4167],"type":"Point"}
}