{
  "id": 2021420,
  "type": "Feature",
  "properties": {
    "tgn:hierarchy":[
        "tgn:2021420",
        "tgn:1000001",
        "tgn:2000263",
        "tgn:7012149",
        "tgn:7007240",
        "tgn:7029392"
    ],
    "tgn:id":2021420,
    "tgn:name":"Suwannee",
    "tgn:placetype":[
        "aat:300008347"
    ]
},
  "bbox": [],
  "geometry": {"coordinates":[-83.1333,29.3167],"type":"Point"}
}