{
  "id": 2129480,
  "type": "Feature",
  "properties": {
    "tgn:hierarchy":[
        "tgn:2129480",
        "tgn:1000001",
        "tgn:7012149",
        "tgn:2001294",
        "tgn:7007524",
        "tgn:7029392"
    ],
    "tgn:id":2129480,
    "tgn:name":"Alkali Creek",
    "tgn:placetype":[
        "aat:300008706"
    ]
},
  "bbox": [],
  "geometry": {"coordinates":[-108.35,46.7667],"type":"Point"}
}