{
  "id": 2010440,
  "type": "Feature",
  "properties": {
    "tgn:hierarchy":[
        "tgn:2010440",
        "tgn:1000001",
        "tgn:7012149",
        "tgn:7007157",
        "tgn:1002828",
        "tgn:7029392"
    ],
    "tgn:id":2010440,
    "tgn:name":"Cabazon",
    "tgn:placetype":[
        "aat:300008347"
    ]
},
  "bbox": [],
  "geometry": {"coordinates":[-116.7833,33.9167],"type":"Point"}
}