{
  "id": 2128643,
  "type": "Feature",
  "properties": {
    "tgn:hierarchy":[
        "tgn:2128643",
        "tgn:1000001",
        "tgn:7016172",
        "tgn:7012149",
        "tgn:2000136",
        "tgn:7029392"
    ],
    "tgn:id":2128643,
    "tgn:name":"Alderbrook Branch",
    "tgn:placetype":[
        "aat:300008699"
    ]
},
  "bbox": [],
  "geometry": {"coordinates":[-91.6667,35.7333],"type":"Point"}
}