{
  "id": 2778702,
  "type": "Feature",
  "properties": {
    "tgn:hierarchy":[
        "tgn:2778702",
        "tgn:7002659",
        "tgn:1000001",
        "tgn:7012149",
        "tgn:2000045",
        "tgn:7029392"
    ],
    "tgn:id":2778702,
    "tgn:name":"Wolf Branch",
    "tgn:placetype":[
        "aat:300008699"
    ]
},
  "bbox": [],
  "geometry": {"coordinates":[-87.7833,32.2167],"type":"Point"}
}