<<<<<<< HEAD
{
  "id": 7055825,
  "type": "Feature",
  "properties": {
    "tgn:hierarchy":[
        "tgn:7055825",
        "tgn:1003440",
        "tgn:1000003",
        "tgn:7003124",
        "tgn:1000080",
        "tgn:7029392"
    ],
    "tgn:id":7055825,
    "tgn:name":"Plan de Corones",
    "tgn:placetype":[
        "aat:300008795"
    ]
},
  "bbox": [],
  "geometry": {"coordinates":[11.95,46.733333],"type":"Point"}
}
=======
{"geometry":{"type":"Point","coordinates":[11.950000,46.733333]},"type":"Feature","properties":{"hierarchy":["tgn:7055825","tgn:1003440","tgn:1000003","tgn:7003124","tgn:1000080","tgn:7029392"],"placetype":["aat:300008795"],"id":7055825,"name:xx":"Plan de Corones"}}
>>>>>>> 03f74aca74312dbeaf24d7e61306dd6a786dc3d0
