{
  "id": 7132330,
  "type": "Feature",
  "properties": {
    "tgn:hierarchy":[
        "tgn:7132330",
        "tgn:1000003",
        "tgn:7003677",
        "tgn:7000084",
        "tgn:7029392"
    ],
    "tgn:id":7132330,
    "tgn:name":"Menke",
    "tgn:placetype":[
        "aat:300000206"
    ]
},
  "bbox": [],
  "geometry": {"coordinates":[7.866667,51.75],"type":"Point"}
}