{
  "id": 7297441,
  "type": "Feature",
  "properties": {
    "tgn:hierarchy":[
        "tgn:7297441",
        "tgn:7008912",
        "tgn:7030216",
        "tgn:1000003",
        "tgn:1000095",
        "tgn:7029392"
    ],
    "tgn:id":7297441,
    "tgn:name":"Tabesc\u00e1n",
    "tgn:placetype":[
        "aat:300008347"
    ]
},
  "bbox": [],
  "geometry": {"coordinates":[1.257887,42.645717],"type":"Point"}
}