{
  "id": 2473353,
  "type": "Feature",
  "properties": {
    "tgn:hierarchy":[
        "tgn:2473353",
        "tgn:1000001",
        "tgn:7012149",
        "tgn:2002382",
        "tgn:7007923",
        "tgn:7029392"
    ],
    "tgn:id":2473353,
    "tgn:name":"Lower Boulder Basin",
    "tgn:placetype":[
        "aat:300386845"
    ]
},
  "bbox": [],
  "geometry": {"coordinates":[-109.9333,43.15],"type":"Point"}
}