{
  "id": 7476794,
  "type": "Feature",
  "properties": {
    "tgn:hierarchy":[
        "tgn:7476794",
        "tgn:7001010",
        "tgn:1000004",
        "tgn:1000141",
        "tgn:7029392"
    ],
    "tgn:id":7476794,
    "tgn:name":"Wang'ai Shan",
    "tgn:placetype":[
        "aat:300008798"
    ]
},
  "bbox": [],
  "geometry": {"coordinates":[121.446577,23.939737],"type":"Point"}
}