{
  "id": 2338994,
  "type": "Feature",
  "properties": {
    "tgn:hierarchy":[
        "tgn:2338994",
        "tgn:1000001",
        "tgn:7012149",
        "tgn:2001888",
        "tgn:7007825",
        "tgn:7029392"
    ],
    "tgn:id":2338994,
    "tgn:name":"Franklin Hollow",
    "tgn:placetype":[
        "aat:300008761"
    ]
},
  "bbox": [],
  "geometry": {"coordinates":[-86.4167,35.15],"type":"Point"}
}