{
  "id": 2081698,
  "type": "Feature",
  "properties": {
    "tgn:hierarchy":[
        "tgn:2081698",
        "tgn:1000001",
        "tgn:7012149",
        "tgn:1002877",
        "tgn:7007706",
        "tgn:7029392"
    ],
    "tgn:id":2081698,
    "tgn:name":"Rubyville",
    "tgn:placetype":[
        "aat:300008347"
    ]
},
  "bbox": [],
  "geometry": {"coordinates":[-82.9167,38.8167],"type":"Point"}
}