{
  "id": 2472198,
  "type": "Feature",
  "properties": {
    "tgn:hierarchy":[
        "tgn:2472198",
        "tgn:1000001",
        "tgn:7012149",
        "tgn:7007708",
        "tgn:7029392"
    ],
    "tgn:id":2472198,
    "tgn:name":"Louie Creek",
    "tgn:placetype":[
        "aat:300008706"
    ]
},
  "bbox": [],
  "geometry": {"coordinates":[-123.7667,45.1333],"type":"Point"}
}