<<<<<<< HEAD
{
  "id": 2339066,
  "type": "Feature",
  "properties": {
    "tgn:hierarchy":[
        "tgn:2339066",
        "tgn:1000001",
        "tgn:1002724",
        "tgn:7012149",
        "tgn:7007517",
        "tgn:7029392"
    ],
    "tgn:id":2339066,
    "tgn:name":"Franklin Reservoirs",
    "tgn:placetype":[
        "aat:300006191"
    ]
},
  "bbox": [],
  "geometry": {"coordinates":[-71.3833,42.0833],"type":"Point"}
}
=======
{"geometry":{"type":"Point","coordinates":[-71.383300,42.083300]},"type":"Feature","properties":{"hierarchy":["tgn:2339066","tgn:1000001","tgn:1002724","tgn:7012149","tgn:7007517","tgn:7029392"],"placetype":["aat:300006191"],"id":2339066,"name:xx":"Franklin Reservoirs"}}
>>>>>>> 03f74aca74312dbeaf24d7e61306dd6a786dc3d0
