{
  "id": 7307070,
  "type": "Feature",
  "properties": {
    "tgn:hierarchy":[
        "tgn:7307070",
        "tgn:7002824",
        "tgn:1000003",
        "tgn:7002786",
        "tgn:1000095",
        "tgn:7029392"
    ],
    "tgn:id":7307070,
    "tgn:name":"Lobeira Chica",
    "tgn:placetype":[
        "aat:300008791"
    ]
},
  "bbox": [],
  "geometry": {"coordinates":[-9.166667,42.866667],"type":"Point"}
}