{
  "id": 7087800,
  "type": "Feature",
  "properties": {
    "tgn:hierarchy":[
        "tgn:7087800",
        "tgn:1000003",
        "tgn:7003688",
        "tgn:7000084",
        "tgn:7029392"
    ],
    "tgn:id":7087800,
    "tgn:name":"Weesbyfeld",
    "tgn:placetype":[
        "aat:300000206"
    ]
},
  "bbox": [],
  "geometry": {"coordinates":[9.133333,54.833333],"type":"Point"}
}