{
  "id": 2161256,
  "type": "Feature",
  "properties": {
    "tgn:hierarchy":[
        "tgn:2161256",
        "tgn:1000001",
        "tgn:7012149",
        "tgn:2000847",
        "tgn:7007255",
        "tgn:7029392"
    ],
    "tgn:id":2161256,
    "tgn:name":"Bell Island",
    "tgn:placetype":[
        "aat:300008791"
    ]
},
  "bbox": [],
  "geometry": {"coordinates":[-88.0833,37.7167],"type":"Point"}
}