{
  "id": 7385800,
  "type": "Feature",
  "properties": {
    "tgn:hierarchy":[
        "tgn:7385800",
        "tgn:1000001",
        "tgn:7005591",
        "tgn:7005560",
        "tgn:7029392"
    ],
    "tgn:id":7385800,
    "tgn:name:es":"Quiavicusas",
    "tgn:placetype":[
        "aat:300008347"
    ]
},
  "bbox": [],
  "geometry": {"coordinates":[-95.718611,16.877778],"type":"Point"}
}