{
  "id": 2741202,
  "type": "Feature",
  "properties": {
    "tgn:hierarchy":[
        "tgn:2741202",
        "tgn:1000001",
        "tgn:7012149",
        "tgn:2001461",
        "tgn:7007568",
        "tgn:7029392"
    ],
    "tgn:id":2741202,
    "tgn:name":"Upper Twin Brook",
    "tgn:placetype":[
        "aat:300008699"
    ]
},
  "bbox": [],
  "geometry": {"coordinates":[-73.95,44.0833],"type":"Point"}
}