{
  "id": 2096121,
  "type": "Feature",
  "properties": {
    "tgn:hierarchy":[
        "tgn:2096121",
        "tgn:2001726",
        "tgn:1000001",
        "tgn:7012149",
        "tgn:7007712",
        "tgn:7029392"
    ],
    "tgn:id":2096121,
    "tgn:name":"Langley",
    "tgn:placetype":[
        "aat:300008347"
    ]
},
  "bbox": [],
  "geometry": {"coordinates":[-81.8333,33.5167],"type":"Point"}
}