{
  "id": 2708026,
  "type": "Feature",
  "properties": {
    "tgn:hierarchy":[
        "tgn:2708026",
        "tgn:1000001",
        "tgn:7012149",
        "tgn:1002682",
        "tgn:7007710",
        "tgn:7029392"
    ],
    "tgn:id":2708026,
    "tgn:name":"Swiftwater Lake",
    "tgn:placetype":[
        "aat:300006191"
    ]
},
  "bbox": [],
  "geometry": {"coordinates":[-75.2667,41.0833],"type":"Point"}
}