{
  "id": 2159793,
  "type": "Feature",
  "properties": {
    "tgn:hierarchy":[
        "tgn:2159793",
        "tgn:7002659",
        "tgn:1000001",
        "tgn:7012149",
        "tgn:2000023",
        "tgn:7029392"
    ],
    "tgn:id":2159793,
    "tgn:name":"Beech Creek",
    "tgn:placetype":[
        "aat:300008706"
    ]
},
  "bbox": [],
  "geometry": {"coordinates":[-86.9333,32.55],"type":"Point"}
}