{
  "id": 2227413,
  "type": "Feature",
  "properties": {
    "tgn:hierarchy":[
        "tgn:2227413",
        "tgn:1000001",
        "tgn:7012149",
        "tgn:2001923",
        "tgn:7007825",
        "tgn:7029392"
    ],
    "tgn:id":2227413,
    "tgn:name":"Cave Spring",
    "tgn:placetype":[
        "aat:300008697"
    ]
},
  "bbox": [],
  "geometry": {"coordinates":[-83.9333,36.2167],"type":"Point"}
}