{
  "id": 2035258,
  "type": "Feature",
  "properties": {
    "tgn:hierarchy":[
        "tgn:2035258",
        "tgn:1000001",
        "tgn:2000568",
        "tgn:7012149",
        "tgn:7007253",
        "tgn:7029392"
    ],
    "tgn:id":2035258,
    "tgn:name":"Mineral Ridge",
    "tgn:placetype":[
        "aat:300008347"
    ]
},
  "bbox": [],
  "geometry": {"coordinates":[-93.9167,42.1833],"type":"Point"}
}