{
  "id": 7503724,
  "type": "Feature",
  "properties": {
    "tgn:hierarchy":[
        "tgn:7503724",
        "tgn:7001004",
        "tgn:1000004",
        "tgn:1000141",
        "tgn:7029392"
    ],
    "tgn:id":7503724,
    "tgn:name":"Jingyi Guoxiao",
    "tgn:placetype":[
        "aat:300006495"
    ]
},
  "bbox": [],
  "geometry": {"coordinates":[120.494722,22.955833],"type":"Point"}
}