<<<<<<< HEAD
{
  "id": 2337352,
  "type": "Feature",
  "properties": {
    "tgn:hierarchy":[
        "tgn:2337352",
        "tgn:1000001",
        "tgn:7012149",
        "tgn:2001535",
        "tgn:7007709",
        "tgn:7029392"
    ],
    "tgn:id":2337352,
    "tgn:name":"Foushee",
    "tgn:placetype":[
        "aat:300008347"
    ]
},
  "bbox": [],
  "geometry": {"coordinates":[-79.65,36.2833],"type":"Point"}
}
=======
{"geometry":{"type":"Point","coordinates":[-79.650000,36.283300]},"type":"Feature","properties":{"hierarchy":["tgn:2337352","tgn:1000001","tgn:7012149","tgn:2001535","tgn:7007709","tgn:7029392"],"placetype":["aat:300008347"],"id":2337352,"name:xx":"Foushee"}}
>>>>>>> 03f74aca74312dbeaf24d7e61306dd6a786dc3d0
