{
  "id": 2771666,
  "type": "Feature",
  "properties": {
    "tgn:hierarchy":[
        "tgn:2771666",
        "tgn:1000001",
        "tgn:7012149",
        "tgn:2001208",
        "tgn:7007523",
        "tgn:7029392"
    ],
    "tgn:id":2771666,
    "tgn:name":"Wildwood Lakes",
    "tgn:placetype":[
        "aat:300006191"
    ]
},
  "bbox": [],
  "geometry": {"coordinates":[-94.45,38.9833],"type":"Point"}
}