{
  "id": 2746162,
  "type": "Feature",
  "properties": {
    "tgn:hierarchy":[
        "tgn:2746162",
        "tgn:2001610",
        "tgn:1000001",
        "tgn:7012149",
        "tgn:7007706",
        "tgn:7029392"
    ],
    "tgn:id":2746162,
    "tgn:name":"Vore Ridge",
    "tgn:placetype":[
        "aat:300266640"
    ]
},
  "bbox": [],
  "geometry": {"coordinates":[-82.15,39.3333],"type":"Point"}
}