{
  "id": 7414768,
  "type": "Feature",
  "properties": {
    "tgn:hierarchy":[
        "tgn:7414768",
        "tgn:1000001",
        "tgn:7005591",
        "tgn:7005560",
        "tgn:7029392"
    ],
    "tgn:id":7414768,
    "tgn:name:es":"Llano Grande",
    "tgn:placetype":[
        "aat:300008347"
    ]
},
  "bbox": [],
  "geometry": {"coordinates":[-95.500833,16.456944],"type":"Point"}
}