{
  "id": 2317423,
  "type": "Feature",
  "properties": {
    "tgn:hierarchy":[
        "tgn:2317423",
        "tgn:1000001",
        "tgn:7006451",
        "tgn:7012149",
        "tgn:2000100",
        "tgn:7029392"
    ],
    "tgn:id":2317423,
    "tgn:name":"Empire Mountains",
    "tgn:placetype":[
        "aat:300008798"
    ]
},
  "bbox": [],
  "geometry": {"coordinates":[-110.6333,31.8833],"type":"Point"}
}