{
  "id": 2003939,
  "type": "Feature",
  "properties": {
    "tgn:hierarchy":[
        "tgn:2003939",
        "tgn:7002659",
        "tgn:1000001",
        "tgn:7012149",
        "tgn:2000045",
        "tgn:7029392"
    ],
    "tgn:id":2003939,
    "tgn:name":"Hugo",
    "tgn:placetype":[
        "aat:300008347",
        "aat:300387210"
    ]
},
  "bbox": [],
  "geometry": {"coordinates":[-87.6833,32.2667],"type":"Point"}
}