{
  "id": 7033434,
  "type": "Feature",
  "properties": {
    "tgn:hierarchy":[
        "tgn:7033434",
        "tgn:1003488",
        "tgn:1000003",
        "tgn:7002993",
        "tgn:1000080",
        "tgn:7029392"
    ],
    "tgn:id":7033434,
    "tgn:name":"Braidacurti",
    "tgn:placetype":[
        "aat:300008347"
    ]
},
  "bbox": [],
  "geometry": {"coordinates":[12.795556,45.882778],"type":"Point"}
}