{
  "id": 7010929,
  "type": "Feature",
  "properties": {
    "tgn:hierarchy":[
        "tgn:7010929",
        "tgn:7011163",
        "tgn:7002674",
        "tgn:1000003",
        "tgn:7002672",
        "tgn:1000074",
        "tgn:7029392"
    ],
    "tgn:id":7010929,
    "tgn:name":"Mitil\u00edni",
    "tgn:placetype":[
        "aat:300008347",
        "aat:300387220",
        "aat:300008375",
        "aat:300120599"
    ]
},
  "bbox": [],
  "geometry": {"coordinates":[26.554722,39.11],"type":"Point"}
}