{
  "id": 2383331,
  "type": "Feature",
  "properties": {
    "tgn:hierarchy":[
        "tgn:2383331",
        "tgn:1000001",
        "tgn:7012149",
        "tgn:2000494",
        "tgn:7007250",
        "tgn:7029392"
    ],
    "tgn:id":2383331,
    "tgn:name":"Heart Lake",
    "tgn:placetype":[
        "aat:300008680"
    ]
},
  "bbox": [],
  "geometry": {"coordinates":[-115.9833,45.0333],"type":"Point"}
}