{
  "id": 7577038,
  "type": "Feature",
  "properties": {
    "tgn:hierarchy":[
        "tgn:7577038",
        "tgn:1000004",
        "tgn:7000198",
        "tgn:1001895",
        "tgn:7029392"
    ],
    "tgn:id":7577038,
    "tgn:name:en":"Kh\u0101r T\u0101legaon",
    "tgn:placetype":[
        "aat:300008347"
    ]
},
  "bbox": [],
  "geometry": {"coordinates":[77.629906,20.994784],"type":"Point"}
}