{
  "id": 2268354,
  "type": "Feature",
  "properties": {
    "tgn:hierarchy":[
        "tgn:2268354",
        "tgn:1000001",
        "tgn:7012149",
        "tgn:2002353",
        "tgn:7007922",
        "tgn:7029392"
    ],
    "tgn:id":2268354,
    "tgn:name":"Crooked Rapids Creek",
    "tgn:placetype":[
        "aat:300008706"
    ]
},
  "bbox": [],
  "geometry": {"coordinates":[-91.1333,45.8333],"type":"Point"}
}