{
  "id": 2146793,
  "type": "Feature",
  "properties": {
    "tgn:hierarchy":[
        "tgn:2146793",
        "tgn:1000001",
        "tgn:7012149",
        "tgn:2000224",
        "tgn:7007158",
        "tgn:7029392"
    ],
    "tgn:id":2146793,
    "tgn:name":"Banker Mine",
    "tgn:placetype":[
        "aat:300000390"
    ]
},
  "bbox": [],
  "geometry": {"coordinates":[-106.2333,39.2333],"type":"Point"}
}