<<<<<<< HEAD
{
  "id": 2764908,
  "type": "Feature",
  "properties": {
    "tgn:hierarchy":[
        "tgn:2764908",
        "tgn:1000001",
        "tgn:2001414",
        "tgn:7012149",
        "tgn:7007526",
        "tgn:7029392"
    ],
    "tgn:id":2764908,
    "tgn:name":"Whiskey Spring",
    "tgn:placetype":[
        "aat:300008697"
    ]
},
  "bbox": [],
  "geometry": {"coordinates":[-119.1167,40.9667],"type":"Point"}
}
=======
{"geometry":{"type":"Point","coordinates":[-119.116700,40.966700]},"type":"Feature","properties":{"hierarchy":["tgn:2764908","tgn:1000001","tgn:2001414","tgn:7012149","tgn:7007526","tgn:7029392"],"placetype":["aat:300008697"],"id":2764908,"name:xx":"Whiskey Spring"}}
>>>>>>> 03f74aca74312dbeaf24d7e61306dd6a786dc3d0
