{
  "id": 7416684,
  "type": "Feature",
  "properties": {
    "tgn:hierarchy":[
        "tgn:7416684",
        "tgn:1000001",
        "tgn:7005591",
        "tgn:7005560",
        "tgn:7029392"
    ],
    "tgn:id":7416684,
    "tgn:name:es":"San Juan, Cerro",
    "tgn:placetype":[
        "aat:300008795"
    ]
},
  "bbox": [],
  "geometry": {"coordinates":[-97.493333,16.0875],"type":"Point"}
}