<<<<<<< HEAD
{
  "id": 2258704,
  "type": "Feature",
  "properties": {
    "tgn:hierarchy":[
        "tgn:2258704",
        "tgn:1000001",
        "tgn:7012149",
        "tgn:2001455",
        "tgn:7007566",
        "tgn:7029392"
    ],
    "tgn:id":2258704,
    "tgn:name":"Cottonwood Canyon",
    "tgn:placetype":[
        "aat:300008761"
    ]
},
  "bbox": [],
  "geometry": {"coordinates":[-107.6833,33.0333],"type":"Point"}
}
=======
{"geometry":{"type":"Point","coordinates":[-107.683300,33.033300]},"type":"Feature","properties":{"hierarchy":["tgn:2258704","tgn:1000001","tgn:7012149","tgn:2001455","tgn:7007566","tgn:7029392"],"placetype":["aat:300008761"],"id":2258704,"name:xx":"Cottonwood Canyon"}}
>>>>>>> 03f74aca74312dbeaf24d7e61306dd6a786dc3d0
