{
  "id": 2404922,
  "type": "Feature",
  "properties": {
    "tgn:hierarchy":[
        "tgn:2404922",
        "tgn:1000001",
        "tgn:7012149",
        "tgn:2001453",
        "tgn:7007566",
        "tgn:7029392"
    ],
    "tgn:id":2404922,
    "tgn:name":"Huddleston Tank Number 1",
    "tgn:placetype":[
        "aat:300006191"
    ]
},
  "bbox": [],
  "geometry": {"coordinates":[-105.6833,35.2833],"type":"Point"}
}