{
  "id": 1084994,
  "type": "Feature",
  "properties": {
    "tgn:hierarchy":[
        "tgn:1084994",
        "tgn:1000139",
        "tgn:7004345",
        "tgn:1000004",
        "tgn:7000261",
        "tgn:7029392"
    ],
    "tgn:id":1084994,
    "tgn:name":"Say'un",
    "tgn:placetype":[
        "aat:300008347"
    ]
},
  "bbox": [],
  "geometry": {"coordinates":[48.7833,15.9333],"type":"Point"}
}