{
  "id": 2435332,
  "type": "Feature",
  "properties": {
    "tgn:hierarchy":[
        "tgn:2435332",
        "tgn:7023902",
        "tgn:1000001",
        "tgn:7012149",
        "tgn:7007249",
        "tgn:7029392"
    ],
    "tgn:id":2435332,
    "tgn:name":"Kepuhi Point",
    "tgn:placetype":[
        "aat:300008850"
    ]
},
  "bbox": [],
  "geometry": {"coordinates":[-155.8333,20.2667],"type":"Point"}
}