{
  "id": 7536436,
  "type": "Feature",
  "properties": {
    "tgn:hierarchy":[
        "tgn:7536436",
        "tgn:7001242",
        "tgn:7016833",
        "tgn:7001312",
        "tgn:7029392"
    ],
    "tgn:id":7536436,
    "tgn:name:en":"Kafr a\u015f \u015e\u0101rim al Ba\u1e29r\u012b",
    "tgn:placetype":[
        "aat:300008347"
    ]
},
  "bbox": [],
  "geometry": {"coordinates":[31.2309,30.996474],"type":"Point"}
}