{
  "id": 7386388,
  "type": "Feature",
  "properties": {
    "tgn:hierarchy":[
        "tgn:7386388",
        "tgn:7005581",
        "tgn:1000001",
        "tgn:7005560",
        "tgn:7029392"
    ],
    "tgn:id":7386388,
    "tgn:name":"Plan de \u00c1lamos, Arroyo del",
    "tgn:placetype":[
        "aat:300008699"
    ]
},
  "bbox": [],
  "geometry": {"coordinates":[-106.85,30.15],"type":"Point"}
}