<<<<<<< HEAD
{
  "id": 2254547,
  "type": "Feature",
  "properties": {
    "tgn:hierarchy":[
        "tgn:2254547",
        "tgn:1002996",
        "tgn:1000001",
        "tgn:7012149",
        "tgn:7007711",
        "tgn:7029392"
    ],
    "tgn:id":2254547,
    "tgn:name":"Coon Hill",
    "tgn:placetype":[
        "aat:300008798"
    ]
},
  "bbox": [],
  "geometry": {"coordinates":[-71.7333,41.45],"type":"Point"}
}
=======
{"geometry":{"type":"Point","coordinates":[-71.733300,41.450000]},"type":"Feature","properties":{"hierarchy":["tgn:2254547","tgn:1002996","tgn:1000001","tgn:7012149","tgn:7007711","tgn:7029392"],"placetype":["aat:300008798"],"id":2254547,"name:xx":"Coon Hill"}}
>>>>>>> 03f74aca74312dbeaf24d7e61306dd6a786dc3d0
