{
  "id": 7591330,
  "type": "Feature",
  "properties": {
    "tgn:hierarchy":[
        "tgn:7591330",
        "tgn:1000004",
        "tgn:7000198",
        "tgn:7000799",
        "tgn:7029392"
    ],
    "tgn:id":7591330,
    "tgn:name:en":"Bhatiy\u0101ri",
    "tgn:placetype":[
        "aat:300008347"
    ]
},
  "bbox": [],
  "geometry": {"coordinates":[74.874072,32.62393],"type":"Point"}
}