{
  "id": 2031824,
  "type": "Feature",
  "properties": {
    "tgn:hierarchy":[
        "tgn:2031824",
        "tgn:1000001",
        "tgn:7012149",
        "tgn:2000559",
        "tgn:7007252",
        "tgn:7029392"
    ],
    "tgn:id":2031824,
    "tgn:name":"Fontanet",
    "tgn:placetype":[
        "aat:300008347"
    ]
},
  "bbox": [],
  "geometry": {"coordinates":[-87.2333,39.5667],"type":"Point"}
}