{
  "id": 7139701,
  "type": "Feature",
  "properties": {
    "tgn:hierarchy":[
        "tgn:7139701",
        "tgn:1000003",
        "tgn:7003676",
        "tgn:7000084",
        "tgn:7029392"
    ],
    "tgn:id":7139701,
    "tgn:name":"Langenholtensen",
    "tgn:placetype":[
        "aat:300008347"
    ]
},
  "bbox": [],
  "geometry": {"coordinates":[10.016667,51.716667],"type":"Point"}
}