{
  "id": 2654577,
  "type": "Feature",
  "properties": {
    "tgn:hierarchy":[
        "tgn:2654577",
        "tgn:7006450",
        "tgn:1000001",
        "tgn:7012149",
        "tgn:2000089",
        "tgn:7029392"
    ],
    "tgn:id":2654577,
    "tgn:name":"Shageluk",
    "tgn:placetype":[
        "aat:300008347"
    ]
},
  "bbox": [],
  "geometry": {"coordinates":[-159.55,62.6667],"type":"Point"}
}