{
  "id": 2752235,
  "type": "Feature",
  "properties": {
    "tgn:hierarchy":[
        "tgn:2752235",
        "tgn:1000001",
        "tgn:2001414",
        "tgn:7012149",
        "tgn:7007526",
        "tgn:7029392"
    ],
    "tgn:id":2752235,
    "tgn:name":"Washburn Basin",
    "tgn:placetype":[
        "aat:300386845"
    ]
},
  "bbox": [],
  "geometry": {"coordinates":[-118.0167,41.9167],"type":"Point"}
}