<<<<<<< HEAD
{
  "id": 7471025,
  "type": "Feature",
  "properties": {
    "tgn:hierarchy":[
        "tgn:7471025",
        "tgn:7469009",
        "tgn:1000004",
        "tgn:1000141",
        "tgn:7029392"
    ],
    "tgn:id":7471025,
    "tgn:name":"Jiugong Matou",
    "tgn:placetype":[
        "aat:300007928"
    ]
},
  "bbox": [],
  "geometry": {"coordinates":[118.258611,24.424722],"type":"Point"}
}
=======
{"geometry":{"type":"Point","coordinates":[118.258611,24.424722]},"type":"Feature","properties":{"hierarchy":["tgn:7471025","tgn:7469009","tgn:1000004","tgn:1000141","tgn:7029392"],"placetype":["aat:300007928"],"id":7471025,"name:xx":"Jiugong Matou"}}
>>>>>>> 03f74aca74312dbeaf24d7e61306dd6a786dc3d0
