{
  "id": 7579373,
  "type": "Feature",
  "properties": {
    "tgn:hierarchy":[
        "tgn:7579373",
        "tgn:1000004",
        "tgn:7000198",
        "tgn:7016722",
        "tgn:7029392"
    ],
    "tgn:id":7579373,
    "tgn:name:en":"Sojna",
    "tgn:placetype":[
        "aat:300008347"
    ]
},
  "bbox": [],
  "geometry": {"coordinates":[78.892943,24.54632],"type":"Point"}
}