{
  "id": 1006926,
  "type": "Feature",
  "properties": {
    "tgn:hierarchy":[
        "tgn:1006926",
        "tgn:1000004",
        "tgn:1001390",
        "tgn:1000111",
        "tgn:7029392"
    ],
    "tgn:id":1006926,
    "tgn:name":"Dawangjia Dao",
    "tgn:placetype":[
        "aat:300008791"
    ]
},
  "bbox": [],
  "geometry": {"coordinates":[123.0667,39.4333],"type":"Point"}
}