{
  "id": 7307134,
  "type": "Feature",
  "properties": {
    "tgn:hierarchy":[
        "tgn:7307134",
        "tgn:7002758",
        "tgn:7002817",
        "tgn:1000003",
        "tgn:1000095",
        "tgn:7029392"
    ],
    "tgn:id":7307134,
    "tgn:name":"Mart\u00edn, Arroyo",
    "tgn:placetype":[
        "aat:300008699"
    ]
},
  "bbox": [],
  "geometry": {"coordinates":[-4.933333,37.966667],"type":"Point"}
}