{
  "id": 2327112,
  "type": "Feature",
  "properties": {
    "tgn:hierarchy":[
        "tgn:2327112",
        "tgn:1000001",
        "tgn:7012149",
        "tgn:7020681",
        "tgn:7007256",
        "tgn:7029392"
    ],
    "tgn:id":2327112,
    "tgn:name":"First Canal",
    "tgn:placetype":[
        "aat:300006075"
    ]
},
  "bbox": [],
  "geometry": {"coordinates":[-90.3333,30.2667],"type":"Point"}
}