{
  "id": 2565614,
  "type": "Feature",
  "properties": {
    "tgn:hierarchy":[
        "tgn:2565614",
        "tgn:1000001",
        "tgn:7012149",
        "tgn:7007158",
        "tgn:7029392"
    ],
    "tgn:id":2565614,
    "tgn:name":"Paiute Peak",
    "tgn:placetype":[
        "aat:300008798"
    ]
},
  "bbox": [],
  "geometry": {"coordinates":[-105.6167,40.0833],"type":"Point"}
}