{
  "id": 7487149,
  "type": "Feature",
  "properties": {
    "tgn:hierarchy":[
        "tgn:7487149",
        "tgn:1000004",
        "tgn:7001014",
        "tgn:1000141",
        "tgn:7029392"
    ],
    "tgn:id":7487149,
    "tgn:name":"Linnei Xiang",
    "tgn:placetype":[
        "aat:300387173"
    ]
},
  "bbox": [],
  "geometry": {"coordinates":[120.624223,23.756924],"type":"Point"}
}