{
  "id": 2084321,
  "type": "Feature",
  "properties": {
    "tgn:hierarchy":[
        "tgn:2084321",
        "tgn:1000001",
        "tgn:7012149",
        "tgn:2001707",
        "tgn:7007708",
        "tgn:7029392"
    ],
    "tgn:id":2084321,
    "tgn:name":"Ajax",
    "tgn:placetype":[
        "aat:300008347",
        "aat:300387210"
    ]
},
  "bbox": [],
  "geometry": {"coordinates":[-120.4333,45.3667],"type":"Point"}
}