{
  "id": 1126883,
  "type": "Feature",
  "properties": {
    "tgn:hierarchy":[
        "tgn:1126883",
        "tgn:7001242",
        "tgn:7441551",
        "tgn:7029392"
    ],
    "tgn:id":1126883,
    "tgn:name":"Roah, River",
    "tgn:placetype":[
        "aat:300008707"
    ]
},
  "bbox": [],
  "geometry": {"coordinates":[29.396,6.088],"type":"Point"}
}