<<<<<<< HEAD
{
  "id": 7356215,
  "type": "Feature",
  "properties": {
    "tgn:hierarchy":[
        "tgn:7356215",
        "tgn:1000001",
        "tgn:7005599",
        "tgn:7005560",
        "tgn:7029392"
    ],
    "tgn:id":7356215,
    "tgn:name":"Chilapan",
    "tgn:placetype":[
        "aat:300008347"
    ]
},
  "bbox": [],
  "geometry": {"coordinates":[-97.15,19.0],"type":"Point"}
}
=======
{"geometry":{"type":"Point","coordinates":[-97.150000,19.000000]},"type":"Feature","properties":{"hierarchy":["tgn:7356215","tgn:1000001","tgn:7005599","tgn:7005560","tgn:7029392"],"placetype":["aat:300008347"],"id":7356215,"name:xx":"Chilapan"}}
>>>>>>> 03f74aca74312dbeaf24d7e61306dd6a786dc3d0
