{
  "id": 7087022,
  "type": "Feature",
  "properties": {
    "tgn:hierarchy":[
        "tgn:7087022",
        "tgn:7000096",
        "tgn:1000003",
        "tgn:7000084",
        "tgn:7029392"
    ],
    "tgn:id":7087022,
    "tgn:name":"Wein Berg",
    "tgn:placetype":[
        "aat:300008777"
    ]
},
  "bbox": [],
  "geometry": {"coordinates":[12.266667,52.566667],"type":"Point"}
}