{
  "id": 1075723,
  "type": "Feature",
  "properties": {
    "tgn:hierarchy":[
        "tgn:1075723",
        "tgn:1000004",
        "tgn:7000198",
        "tgn:7016722",
        "tgn:7029392"
    ],
    "tgn:id":1075723,
    "tgn:name:en":"Kaisarganj",
    "tgn:placetype":[
        "aat:300008347"
    ]
},
  "bbox": [],
  "geometry": {"coordinates":[81.546854,27.251006],"type":"Point"}
}