{
  "id": 2626641,
  "type": "Feature",
  "properties": {
    "tgn:hierarchy":[
        "tgn:2626641",
        "tgn:7002659",
        "tgn:1000001",
        "tgn:2000010",
        "tgn:7012149",
        "tgn:7029392"
    ],
    "tgn:id":2626641,
    "tgn:name":"Rocky Mount",
    "tgn:placetype":[
        "aat:300008347"
    ]
},
  "bbox": [],
  "geometry": {"coordinates":[-86.7167,32.9833],"type":"Point"}
}