{
  "id": 7004136,
  "type": "Feature",
  "properties": {
    "tgn:hierarchy":[
        "tgn:7004136",
        "tgn:7003248",
        "tgn:1000003",
        "tgn:7010380",
        "tgn:1000080",
        "tgn:7029392"
    ],
    "tgn:id":7004136,
    "tgn:name":"Bitetto",
    "tgn:placetype":[
        "aat:300008347",
        "aat:300008375"
    ]
},
  "bbox": [],
  "geometry": {"coordinates":[16.75,41.033333],"type":"Point"}
}