<<<<<<< HEAD
{
  "id": 2760700,
  "type": "Feature",
  "properties": {
    "tgn:hierarchy":[
        "tgn:2760700",
        "tgn:1000001",
        "tgn:7012149",
        "tgn:1002917",
        "tgn:7007706",
        "tgn:7029392"
    ],
    "tgn:id":2760700,
    "tgn:name":"West Fulton",
    "tgn:placetype":[
        "aat:300008347"
    ]
},
  "bbox": [],
  "geometry": {"coordinates":[-81.6,40.8833],"type":"Point"}
}
=======
{"geometry":{"type":"Point","coordinates":[-81.600000,40.883300]},"type":"Feature","properties":{"hierarchy":["tgn:2760700","tgn:1000001","tgn:7012149","tgn:1002917","tgn:7007706","tgn:7029392"],"placetype":["aat:300008347"],"id":2760700,"name:xx":"West Fulton"}}
>>>>>>> 03f74aca74312dbeaf24d7e61306dd6a786dc3d0
