{
  "id": 2650146,
  "type": "Feature",
  "properties": {
    "tgn:hierarchy":[
        "tgn:2650146",
        "tgn:1000001",
        "tgn:7012149",
        "tgn:1002767",
        "tgn:7007920",
        "tgn:7029392"
    ],
    "tgn:id":2650146,
    "tgn:name":"Seahaven",
    "tgn:placetype":[
        "aat:300008347",
        "aat:300167671",
        "aat:300008375"
    ]
},
  "bbox": [],
  "geometry": {"coordinates":[-123.8167,46.6833],"type":"Point"}
}