{
  "id": 2425535,
  "type": "Feature",
  "properties": {
    "tgn:hierarchy":[
        "tgn:2425535",
        "tgn:1000001",
        "tgn:2002147",
        "tgn:7012149",
        "tgn:7007919",
        "tgn:7029392"
    ],
    "tgn:id":2425535,
    "tgn:name":"Johnsons Branch",
    "tgn:placetype":[
        "aat:300008699"
    ]
},
  "bbox": [],
  "geometry": {"coordinates":[-77.8167,36.7167],"type":"Point"}
}