{
  "id": 1114913,
  "type": "Feature",
  "properties": {
    "tgn:hierarchy":[
        "tgn:1114913",
        "tgn:1000004",
        "tgn:1000135",
        "tgn:7029392"
    ],
    "tgn:id":1114913,
    "tgn:name":"Verde Island Passage",
    "tgn:placetype":[
        "aat:300387217"
    ]
},
  "bbox": [],
  "geometry": {"coordinates":[120.85,13.5667],"type":"Point"}
}