{
  "id": 7014100,
  "type": "Feature",
  "properties": {
    "tgn:hierarchy":[
        "tgn:7014100",
        "tgn:1000001",
        "tgn:7012149",
        "tgn:1003018",
        "tgn:7007919",
        "tgn:7029392"
    ],
    "tgn:id":7014100,
    "tgn:name":"Montross",
    "tgn:placetype":[
        "aat:300008347"
    ]
},
  "bbox": [],
  "geometry": {"coordinates":[-76.8167,38.0833],"type":"Point"}
}