{
  "id": 7387622,
  "type": "Feature",
  "properties": {
    "tgn:hierarchy":[
        "tgn:7387622",
        "tgn:1000001",
        "tgn:1001960",
        "tgn:7005560",
        "tgn:7029392"
    ],
    "tgn:id":7387622,
    "tgn:name":"Picacho de Tetuache",
    "tgn:placetype":[
        "aat:300008347"
    ]
},
  "bbox": [],
  "geometry": {"coordinates":[-110.333333,30.216667],"type":"Point"}
}