{
  "id": 7474423,
  "type": "Feature",
  "properties": {
    "tgn:hierarchy":[
        "tgn:7474423",
        "tgn:7001010",
        "tgn:1000004",
        "tgn:1000141",
        "tgn:7029392"
    ],
    "tgn:id":7474423,
    "tgn:name":"Tiantianguan Shan",
    "tgn:placetype":[
        "aat:300008798"
    ]
},
  "bbox": [],
  "geometry": {"coordinates":[121.698065,24.311618],"type":"Point"}
}