{
  "id": 1072608,
  "type": "Feature",
  "properties": {
    "tgn:hierarchy":[
        "tgn:1072608",
        "tgn:1000004",
        "tgn:1001390",
        "tgn:1000111",
        "tgn:7029392"
    ],
    "tgn:id":1072608,
    "tgn:name":"Wudao",
    "tgn:placetype":[
        "aat:300008347"
    ]
},
  "bbox": [],
  "geometry": {"coordinates":[121.3667,39.4167],"type":"Point"}
}