{
  "id": 2427148,
  "type": "Feature",
  "properties": {
    "tgn:hierarchy":[
        "tgn:2427148",
        "tgn:1000001",
        "tgn:7012149",
        "tgn:2000444",
        "tgn:7007248",
        "tgn:7029392"
    ],
    "tgn:id":2427148,
    "tgn:name":"Jordan",
    "tgn:placetype":[
        "aat:300008347"
    ]
},
  "bbox": [],
  "geometry": {"coordinates":[-82.6667,32.0333],"type":"Point"}
}