{
  "id": 1009243,
  "type": "Feature",
  "properties": {
    "tgn:hierarchy":[
        "tgn:1009243",
        "tgn:7015163",
        "tgn:1000003",
        "tgn:7003121",
        "tgn:1000080",
        "tgn:7029392"
    ],
    "tgn:id":1009243,
    "tgn:name":"Spargi, Isola",
    "tgn:placetype":[
        "aat:300008791"
    ]
},
  "bbox": [],
  "geometry": {"coordinates":[9.35,41.233333],"type":"Point"}
}