{
  "id": 2733032,
  "type": "Feature",
  "properties": {
    "tgn:hierarchy":[
        "tgn:2733032",
        "tgn:1000001",
        "tgn:1002267",
        "tgn:7012149",
        "tgn:7007919",
        "tgn:7029392"
    ],
    "tgn:id":2733032,
    "tgn:name":"Turkey Island",
    "tgn:placetype":[
        "aat:300008791"
    ]
},
  "bbox": [],
  "geometry": {"coordinates":[-77.25,37.35],"type":"Point"}
}