{
  "id": 7562367,
  "type": "Feature",
  "properties": {
    "tgn:hierarchy":[
        "tgn:7562367",
        "tgn:1000004",
        "tgn:7000198",
        "tgn:1001894",
        "tgn:7029392"
    ],
    "tgn:id":7562367,
    "tgn:name:en":"Jakhmoli",
    "tgn:placetype":[
        "aat:300008347"
    ]
},
  "bbox": [],
  "geometry": {"coordinates":[79.042592,26.398929],"type":"Point"}
}