{
  "id": 2488273,
  "type": "Feature",
  "properties": {
    "tgn:hierarchy":[
        "tgn:2488273",
        "tgn:1000001",
        "tgn:7012149",
        "tgn:2002115",
        "tgn:7007827",
        "tgn:7029392"
    ],
    "tgn:id":2488273,
    "tgn:name":"Magpie Hopkins Cottonwood Creek",
    "tgn:placetype":[
        "aat:300008706"
    ]
},
  "bbox": [],
  "geometry": {"coordinates":[-111.55,41.1333],"type":"Point"}
}