{
  "id": 2005310,
  "type": "Feature",
  "properties": {
    "tgn:hierarchy":[
        "tgn:2005310",
        "tgn:7002659",
        "tgn:1000001",
        "tgn:7012149",
        "tgn:2000044",
        "tgn:7029392"
    ],
    "tgn:id":2005310,
    "tgn:name":"Skinem",
    "tgn:placetype":[
        "aat:300008347",
        "aat:300387210"
    ]
},
  "bbox": [],
  "geometry": {"coordinates":[-86.5167,34.95],"type":"Point"}
}