{
  "id": 7014433,
  "type": "Feature",
  "properties": {
    "tgn:hierarchy":[
        "tgn:7014433",
        "tgn:1000004",
        "tgn:7011528",
        "tgn:7002435",
        "tgn:7029392"
    ],
    "tgn:id":7014433,
    "tgn:name":"Yakutsk",
    "tgn:placetype":[
        "aat:300387277",
        "aat:300008347",
        "aat:300387255",
        "aat:300008389",
        "aat:300387220"
    ]
},
  "bbox": [],
  "geometry": {"coordinates":[129.8333,62.1667],"type":"Point"}
}