{
  "id": 2145401,
  "type": "Feature",
  "properties": {
    "tgn:hierarchy":[
        "tgn:2145401",
        "tgn:1000001",
        "tgn:7012149",
        "tgn:7007157",
        "tgn:1002791",
        "tgn:7029392"
    ],
    "tgn:id":2145401,
    "tgn:name":"Bald Rock Mountain",
    "tgn:placetype":[
        "aat:300008798"
    ]
},
  "bbox": [],
  "geometry": {"coordinates":[-121.1333,39.0167],"type":"Point"}
}