{
  "id": 2152210,
  "type": "Feature",
  "properties": {
    "tgn:hierarchy":[
        "tgn:2152210",
        "tgn:1000001",
        "tgn:7012149",
        "tgn:2001140",
        "tgn:7007522",
        "tgn:7029392"
    ],
    "tgn:id":2152210,
    "tgn:name":"Bay Branch",
    "tgn:placetype":[
        "aat:300008699"
    ]
},
  "bbox": [],
  "geometry": {"coordinates":[-89.6333,30.5167],"type":"Point"}
}