{
  "id": 2749138,
  "type": "Feature",
  "properties": {
    "tgn:hierarchy":[
        "tgn:2749138",
        "tgn:1000001",
        "tgn:7012149",
        "tgn:1002576",
        "tgn:7007520",
        "tgn:7029392"
    ],
    "tgn:id":2749138,
    "tgn:name":"Wallace Lake",
    "tgn:placetype":[
        "aat:300008680"
    ]
},
  "bbox": [],
  "geometry": {"coordinates":[-83.35,42.9833],"type":"Point"}
}