{
  "id": 2613943,
  "type": "Feature",
  "properties": {
    "tgn:hierarchy":[
        "tgn:2613943",
        "tgn:1000001",
        "tgn:7012149",
        "tgn:1002924",
        "tgn:7007568",
        "tgn:7029392"
    ],
    "tgn:id":2613943,
    "tgn:name":"Reel Point",
    "tgn:placetype":[
        "aat:300008850"
    ]
},
  "bbox": [],
  "geometry": {"coordinates":[-72.2667,41.0667],"type":"Point"}
}