{
  "id": 7531969,
  "type": "Feature",
  "properties": {
    "tgn:hierarchy":[
        "tgn:7531969",
        "tgn:7001242",
        "tgn:7016833",
        "tgn:7001335",
        "tgn:7029392"
    ],
    "tgn:id":7531969,
    "tgn:name:en":"El-Maqbara",
    "tgn:placetype":[
        "aat:300008884"
    ]
},
  "bbox": [],
  "geometry": {"coordinates":[33.719167,31.104167],"type":"Point"}
}