{
  "id": 1015541,
  "type": "Feature",
  "properties": {
    "tgn:hierarchy":[
        "tgn:1015541",
        "tgn:7005685",
        "tgn:1000001",
        "tgn:7005804",
        "tgn:1008205",
        "tgn:7029392"
    ],
    "tgn:id":1015541,
    "tgn:name":"Outremont",
    "tgn:placetype":[
        "aat:300008347"
    ]
},
  "bbox": [],
  "geometry": {"coordinates":[-73.6167,45.5333],"type":"Point"}
}