{
  "id": 2133240,
  "type": "Feature",
  "properties": {
    "tgn:hierarchy":[
        "tgn:2133240",
        "tgn:1000001",
        "tgn:7012149",
        "tgn:2001711",
        "tgn:7007708",
        "tgn:7029392"
    ],
    "tgn:id":2133240,
    "tgn:name":"Anderson Mine",
    "tgn:placetype":[
        "aat:300000390"
    ]
},
  "bbox": [],
  "geometry": {"coordinates":[-123.1167,42.3667],"type":"Point"}
}