{
  "id": 2772767,
  "type": "Feature",
  "properties": {
    "tgn:hierarchy":[
        "tgn:2772767",
        "tgn:1000001",
        "tgn:7012149",
        "tgn:1002456",
        "tgn:7007826",
        "tgn:7029392"
    ],
    "tgn:id":2772767,
    "tgn:name":"Williams Gully",
    "tgn:placetype":[
        "aat:300008699"
    ]
},
  "bbox": [],
  "geometry": {"coordinates":[-95.1833,29.9833],"type":"Point"}
}