{
  "id": 7405842,
  "type": "Feature",
  "properties": {
    "tgn:hierarchy":[
        "tgn:7405842",
        "tgn:1000001",
        "tgn:1001906",
        "tgn:7005560",
        "tgn:7029392"
    ],
    "tgn:id":7405842,
    "tgn:name":"Los Manguitos",
    "tgn:placetype":[
        "aat:300008347"
    ]
},
  "bbox": [],
  "geometry": {"coordinates":[-104.670833,22.170833],"type":"Point"}
}