{
  "id": 7180368,
  "type": "Feature",
  "properties": {
    "tgn:hierarchy":[
        "tgn:7180368",
        "tgn:1000003",
        "tgn:7003678",
        "tgn:7000084",
        "tgn:7029392"
    ],
    "tgn:id":7180368,
    "tgn:name":"Galgen-Berg",
    "tgn:placetype":[
        "aat:300008777"
    ]
},
  "bbox": [],
  "geometry": {"coordinates":[9.133333,50.85],"type":"Point"}
}