{
  "id": 2393885,
  "type": "Feature",
  "properties": {
    "tgn:hierarchy":[
        "tgn:2393885",
        "tgn:1000001",
        "tgn:7012149",
        "tgn:2000376",
        "tgn:7007248",
        "tgn:7029392"
    ],
    "tgn:id":2393885,
    "tgn:name":"Hog Mountain",
    "tgn:placetype":[
        "aat:300008798"
    ]
},
  "bbox": [],
  "geometry": {"coordinates":[-84.1333,33.0667],"type":"Point"}
}