{
  "id": 2344197,
  "type": "Feature",
  "properties": {
    "tgn:hierarchy":[
        "tgn:2344197",
        "tgn:1000001",
        "tgn:7012149",
        "tgn:7014398",
        "tgn:7013961",
        "tgn:7029392"
    ],
    "tgn:id":2344197,
    "tgn:name":"Gammel Run",
    "tgn:placetype":[
        "aat:300008699"
    ]
},
  "bbox": [],
  "geometry": {"coordinates":[-79.3833,38.4333],"type":"Point"}
}