{
  "id": 7536950,
  "type": "Feature",
  "properties": {
    "tgn:hierarchy":[
        "tgn:7536950",
        "tgn:7001242",
        "tgn:1001075",
        "tgn:7016833",
        "tgn:7029392"
    ],
    "tgn:id":7536950,
    "tgn:name:en":"L\u0101bid, Tallat",
    "tgn:placetype":[
        "aat:300008777"
    ]
},
  "bbox": [],
  "geometry": {"coordinates":[30.503056,30.650278],"type":"Point"}
}