{
  "id": 2039733,
  "type": "Feature",
  "properties": {
    "tgn:hierarchy":[
        "tgn:2039733",
        "tgn:1000001",
        "tgn:7012149",
        "tgn:2000828",
        "tgn:7007255",
        "tgn:7029392"
    ],
    "tgn:id":2039733,
    "tgn:name":"Knob Lick",
    "tgn:placetype":[
        "aat:300008347"
    ]
},
  "bbox": [],
  "geometry": {"coordinates":[-85.6833,37.0667],"type":"Point"}
}