{
  "id": 7519628,
  "type": "Feature",
  "properties": {
    "tgn:hierarchy":[
        "tgn:7519628",
        "tgn:1009227",
        "tgn:7001866",
        "tgn:1000226",
        "tgn:1000006",
        "tgn:7029392"
    ],
    "tgn:id":7519628,
    "tgn:name:en":"Blythe River",
    "tgn:placetype":[
        "aat:300008699"
    ]
},
  "bbox": [],
  "geometry": {"coordinates":[173.266667,-42.933333],"type":"Point"}
}