{
  "id": 1114151,
  "type": "Feature",
  "properties": {
    "tgn:hierarchy":[
        "tgn:1114151",
        "tgn:1000001",
        "tgn:7012149",
        "tgn:1002715",
        "tgn:7007568",
        "tgn:7029392"
    ],
    "tgn:id":1114151,
    "tgn:name":"Hell Gate",
    "tgn:placetype":[
        "aat:300008713"
    ]
},
  "bbox": [],
  "geometry": {"coordinates":[-73.9167,40.7667],"type":"Point"}
}