{
  "id": 7386720,
  "type": "Feature",
  "properties": {
    "tgn:hierarchy":[
        "tgn:7386720",
        "tgn:1000001",
        "tgn:1001906",
        "tgn:7005560",
        "tgn:7029392"
    ],
    "tgn:id":7386720,
    "tgn:name":"Playa de Ram\u00edrez",
    "tgn:placetype":[
        "aat:300008347"
    ]
},
  "bbox": [],
  "geometry": {"coordinates":[-105.366667,21.683333],"type":"Point"}
}