{
  "id": 1014387,
  "type": "Feature",
  "properties": {
    "tgn:hierarchy":[
        "tgn:1014387",
        "tgn:7005685",
        "tgn:1000001",
        "tgn:7024197",
        "tgn:7029392"
    ],
    "tgn:id":1014387,
    "tgn:name":"Rankin Inlet",
    "tgn:placetype":[
        "aat:300008347",
        "aat:300387311",
        "aat:300008372",
        "aat:300387270"
    ]
},
  "bbox": [],
  "geometry": {"coordinates":[-92.1667,62.75],"type":"Point"}
}