{
  "id": 2667055,
  "type": "Feature",
  "properties": {
    "tgn:hierarchy":[
        "tgn:2667055",
        "tgn:1000001",
        "tgn:7012149",
        "tgn:7007157",
        "tgn:2000188",
        "tgn:7029392"
    ],
    "tgn:id":2667055,
    "tgn:name":"Ski Island",
    "tgn:placetype":[
        "aat:300008791"
    ]
},
  "bbox": [],
  "geometry": {"coordinates":[-122.25,40.75],"type":"Point"}
}