{
  "id": 7367620,
  "type": "Feature",
  "properties": {
    "tgn:hierarchy":[
        "tgn:7367620",
        "tgn:7005581",
        "tgn:1000001",
        "tgn:7005560",
        "tgn:7029392"
    ],
    "tgn:id":7367620,
    "tgn:name":"Est\u00edo, Cerro",
    "tgn:placetype":[
        "aat:300008777"
    ]
},
  "bbox": [],
  "geometry": {"coordinates":[-104.616667,27.166667],"type":"Point"}
}