{
  "id": 2570232,
  "type": "Feature",
  "properties": {
    "tgn:hierarchy":[
        "tgn:2570232",
        "tgn:1000001",
        "tgn:7012149",
        "tgn:2001300",
        "tgn:7007524",
        "tgn:7029392"
    ],
    "tgn:id":2570232,
    "tgn:name":"Pasture Draw",
    "tgn:placetype":[
        "aat:300008761"
    ]
},
  "bbox": [],
  "geometry": {"coordinates":[-113.8833,45.8833],"type":"Point"}
}