{
  "id": 2206786,
  "type": "Feature",
  "properties": {
    "tgn:hierarchy":[
        "tgn:2206786",
        "tgn:1000001",
        "tgn:2000782",
        "tgn:7012149",
        "tgn:7007255",
        "tgn:7029392"
    ],
    "tgn:id":2206786,
    "tgn:name":"Bullskin Branch",
    "tgn:placetype":[
        "aat:300008699"
    ]
},
  "bbox": [],
  "geometry": {"coordinates":[-83.6167,37.2333],"type":"Point"}
}