{
  "id": 7267571,
  "type": "Feature",
  "properties": {
    "tgn:hierarchy":[
        "tgn:7267571",
        "tgn:1000003",
        "tgn:7003632",
        "tgn:7016845",
        "tgn:7029392"
    ],
    "tgn:id":7267571,
    "tgn:name:nl":"Oosteind",
    "tgn:placetype":[
        "aat:300008347"
    ]
},
  "bbox": [],
  "geometry": {"coordinates":[4.716667,51.833333],"type":"Point"}
}