<<<<<<< HEAD
{
  "id": 7488956,
  "type": "Feature",
  "properties": {
    "tgn:hierarchy":[
        "tgn:7488956",
        "tgn:1000004",
        "tgn:7001013",
        "tgn:1000141",
        "tgn:7029392"
    ],
    "tgn:id":7488956,
    "tgn:name":"Gonghuakeng",
    "tgn:placetype":[
        "aat:300008347"
    ]
},
  "bbox": [],
  "geometry": {"coordinates":[121.35298,25.023862],"type":"Point"}
}
=======
{"geometry":{"type":"Point","coordinates":[121.352980,25.023862]},"type":"Feature","properties":{"hierarchy":["tgn:7488956","tgn:1000004","tgn:7001013","tgn:1000141","tgn:7029392"],"placetype":["aat:300008347"],"id":7488956,"name:xx":"Gonghuakeng"}}
>>>>>>> 03f74aca74312dbeaf24d7e61306dd6a786dc3d0
