{
  "id": 2622261,
  "type": "Feature",
  "properties": {
    "tgn:hierarchy":[
        "tgn:2622261",
        "tgn:1000001",
        "tgn:7012149",
        "tgn:2002191",
        "tgn:7007919",
        "tgn:7029392"
    ],
    "tgn:id":2622261,
    "tgn:name":"Robertson Branch",
    "tgn:placetype":[
        "aat:300008699"
    ]
},
  "bbox": [],
  "geometry": {"coordinates":[-81.7833,36.9167],"type":"Point"}
}