{
  "id": 7267478,
  "type": "Feature",
  "properties": {
    "tgn:concordances":{
        "gn:id":"2750192"
    },
    "tgn:hierarchy":[
        "tgn:7267478",
        "tgn:1000003",
        "tgn:7003624",
        "tgn:7016845",
        "tgn:7029392"
    ],
    "tgn:id":7267478,
    "tgn:name:nl":"Nieuwkerk",
    "tgn:placetype":[
        "aat:300008347"
    ]
},
  "bbox": [],
  "geometry": {"coordinates":[5.05,51.483333],"type":"Point"}
}