<<<<<<< HEAD
{
  "id": 7050446,
  "type": "Feature",
  "properties": {
    "tgn:hierarchy":[
        "tgn:7050446",
        "tgn:7003158",
        "tgn:1000003",
        "tgn:7003124",
        "tgn:1000080",
        "tgn:7029392"
    ],
    "tgn:id":7050446,
    "tgn:name":"Massimeno",
    "tgn:placetype":[
        "aat:300008347"
    ]
},
  "bbox": [],
  "geometry": {"coordinates":[10.766667,46.133333],"type":"Point"}
}
=======
{"geometry":{"type":"Point","coordinates":[10.766667,46.133333]},"type":"Feature","properties":{"hierarchy":["tgn:7050446","tgn:7003158","tgn:1000003","tgn:7003124","tgn:1000080","tgn:7029392"],"placetype":["aat:300008347"],"id":7050446,"name:xx":"Massimeno"}}
>>>>>>> 03f74aca74312dbeaf24d7e61306dd6a786dc3d0
