{
  "id": 2215638,
  "type": "Feature",
  "properties": {
    "tgn:hierarchy":[
        "tgn:2215638",
        "tgn:1000001",
        "tgn:7012149",
        "tgn:7007157",
        "tgn:1002863",
        "tgn:7029392"
    ],
    "tgn:id":2215638,
    "tgn:name":"Camatta Canyon",
    "tgn:placetype":[
        "aat:300008761"
    ]
},
  "bbox": [],
  "geometry": {"coordinates":[-120.2833,35.45],"type":"Point"}
}