{
  "id": 7493735,
  "type": "Feature",
  "properties": {
    "tgn:hierarchy":[
        "tgn:7493735",
        "tgn:7468018",
        "tgn:1000004",
        "tgn:1000141",
        "tgn:7029392"
    ],
    "tgn:id":7493735,
    "tgn:name":"Jiayi Nongchang",
    "tgn:placetype":[
        "aat:300000206"
    ]
},
  "bbox": [],
  "geometry": {"coordinates":[120.559424,23.249394],"type":"Point"}
}