{
  "id": 2514631,
  "type": "Feature",
  "properties": {
    "tgn:hierarchy":[
        "tgn:2514631",
        "tgn:2000105",
        "tgn:1000001",
        "tgn:7016172",
        "tgn:7012149",
        "tgn:7029392"
    ],
    "tgn:id":2514631,
    "tgn:name":"Miller Lake",
    "tgn:placetype":[
        "aat:300006191"
    ]
},
  "bbox": [],
  "geometry": {"coordinates":[-91.2833,34.2667],"type":"Point"}
}