{
  "id": 1071711,
  "type": "Feature",
  "properties": {
    "tgn:hierarchy":[
        "tgn:1071711",
        "tgn:1000004",
        "tgn:7002082",
        "tgn:1000111",
        "tgn:7029392"
    ],
    "tgn:id":1071711,
    "tgn:name":"Shimenlou",
    "tgn:placetype":[
        "aat:300008347"
    ]
},
  "bbox": [],
  "geometry": {"coordinates":[114.85,28.9667],"type":"Point"}
}