{
  "id": 7588284,
  "type": "Feature",
  "properties": {
    "tgn:hierarchy":[
        "tgn:7588284",
        "tgn:1000004",
        "tgn:1001832",
        "tgn:7000198",
        "tgn:7029392"
    ],
    "tgn:id":7588284,
    "tgn:name:en":"Tipkai",
    "tgn:placetype":[
        "aat:300008347"
    ]
},
  "bbox": [],
  "geometry": {"coordinates":[90.032529,26.289738],"type":"Point"}
}