{
  "id": 1059340,
  "type": "Feature",
  "properties": {
    "tgn:hierarchy":[
        "tgn:1059340",
        "tgn:7012076",
        "tgn:1000003",
        "tgn:7006660",
        "tgn:7029392"
    ],
    "tgn:id":1059340,
    "tgn:name":"Serebr'anka",
    "tgn:placetype":[
        "aat:300008347"
    ]
},
  "bbox": [],
  "geometry": {"coordinates":[38.1333,48.9167],"type":"Point"}
}