{
  "id": 7324038,
  "type": "Feature",
  "properties": {
    "tgn:hierarchy":[
        "tgn:7324038",
        "tgn:1001439",
        "tgn:1000003",
        "tgn:7002797",
        "tgn:1000095",
        "tgn:7029392"
    ],
    "tgn:id":7324038,
    "tgn:name":"Santa Quiteria",
    "tgn:placetype":[
        "aat:300008347"
    ]
},
  "bbox": [],
  "geometry": {"coordinates":[-1.683333,37.666667],"type":"Point"}
}