{
  "id": 7495559,
  "type": "Feature",
  "properties": {
    "tgn:hierarchy":[
        "tgn:7495559",
        "tgn:1000004",
        "tgn:7001013",
        "tgn:1000141",
        "tgn:7029392"
    ],
    "tgn:id":7495559,
    "tgn:name":"Fuxing Gong",
    "tgn:placetype":[
        "aat:300007595"
    ]
},
  "bbox": [],
  "geometry": {"coordinates":[121.310352,24.826358],"type":"Point"}
}