{
  "id": 1067230,
  "type": "Feature",
  "properties": {
    "tgn:hierarchy":[
        "tgn:1067230",
        "tgn:1000004",
        "tgn:7002080",
        "tgn:1000111",
        "tgn:7029392"
    ],
    "tgn:id":1067230,
    "tgn:name":"Chishui",
    "tgn:placetype":[
        "aat:300008347"
    ]
},
  "bbox": [],
  "geometry": {"coordinates":[105.6333,28.4833],"type":"Point"}
}