{
  "id": 2785002,
  "type": "Feature",
  "properties": {
    "tgn:hierarchy":[
        "tgn:2785002",
        "tgn:1000001",
        "tgn:7012149",
        "tgn:1002862",
        "tgn:7007920",
        "tgn:7029392"
    ],
    "tgn:id":2785002,
    "tgn:name":"Yellow Island",
    "tgn:placetype":[
        "aat:300008791"
    ]
},
  "bbox": [],
  "geometry": {"coordinates":[-123.0167,48.5833],"type":"Point"}
}