{
  "id": 2248541,
  "type": "Feature",
  "properties": {
    "tgn:hierarchy":[
        "tgn:2248541",
        "tgn:1000001",
        "tgn:7012149",
        "tgn:7016021",
        "tgn:7007568",
        "tgn:7029392"
    ],
    "tgn:id":2248541,
    "tgn:name":"Cold Spring Brook State Forest",
    "tgn:placetype":[
        "aat:300008863"
    ]
},
  "bbox": [],
  "geometry": {"coordinates":[-75.2333,44.2333],"type":"Point"}
}