{
  "id": 2265785,
  "type": "Feature",
  "properties": {
    "tgn:hierarchy":[
        "tgn:2265785",
        "tgn:7006450",
        "tgn:1000001",
        "tgn:2124053",
        "tgn:7012149",
        "tgn:7029392"
    ],
    "tgn:id":2265785,
    "tgn:name":"Crater Lake",
    "tgn:placetype":[
        "aat:300008680"
    ]
},
  "bbox": [],
  "geometry": {"coordinates":[-147.7833,62.35],"type":"Point"}
}