{
  "id": 7235931,
  "type": "Feature",
  "properties": {
    "tgn:hierarchy":[
        "tgn:7235931",
        "tgn:7002735",
        "tgn:7017076",
        "tgn:1000003",
        "tgn:1000074",
        "tgn:7029392"
    ],
    "tgn:id":7235931,
    "tgn:name":"\u00c1yios Ye\u00f3ryios",
    "tgn:placetype":[
        "aat:300008347"
    ]
},
  "bbox": [],
  "geometry": {"coordinates":[22.55,36.816667],"type":"Point"}
}