{
  "id": 7317757,
  "type": "Feature",
  "properties": {
    "tgn:hierarchy":[
        "tgn:7317757",
        "tgn:1001702",
        "tgn:1000049",
        "tgn:1000002",
        "tgn:7029392"
    ],
    "tgn:id":7317757,
    "tgn:name":"Cirujano, Seno",
    "tgn:placetype":[
        "aat:300008676"
    ]
},
  "bbox": [],
  "geometry": {"coordinates":[-75.483333,-49.133333],"type":"Point"}
}