<<<<<<< HEAD
{
  "id": 2334720,
  "type": "Feature",
  "properties": {
    "tgn:hierarchy":[
        "tgn:2334720",
        "tgn:1000001",
        "tgn:7012149",
        "tgn:1002945",
        "tgn:7007710",
        "tgn:7029392"
    ],
    "tgn:id":2334720,
    "tgn:name":"Fork Hill",
    "tgn:placetype":[
        "aat:300008798"
    ]
},
  "bbox": [],
  "geometry": {"coordinates":[-77.35,41.5667],"type":"Point"}
}
=======
{"geometry":{"type":"Point","coordinates":[-77.350000,41.566700]},"type":"Feature","properties":{"hierarchy":["tgn:2334720","tgn:1000001","tgn:7012149","tgn:1002945","tgn:7007710","tgn:7029392"],"placetype":["aat:300008798"],"id":2334720,"name:xx":"Fork Hill"}}
>>>>>>> 03f74aca74312dbeaf24d7e61306dd6a786dc3d0
