{
  "id": 1024087,
  "type": "Feature",
  "properties": {
    "tgn:hierarchy":[
        "tgn:1024087",
        "tgn:1001170",
        "tgn:7002561",
        "tgn:1000051",
        "tgn:1000002",
        "tgn:7029392"
    ],
    "tgn:id":1024087,
    "tgn:name":"Bibli\u00e1n",
    "tgn:placetype":[
        "aat:300008347"
    ]
},
  "bbox": [],
  "geometry": {"coordinates":[-78.888,-2.714],"type":"Point"}
}