{
  "id": 2572349,
  "type": "Feature",
  "properties": {
    "tgn:hierarchy":[
        "tgn:2572349",
        "tgn:1000001",
        "tgn:2002134",
        "tgn:7012149",
        "tgn:7007828",
        "tgn:7029392"
    ],
    "tgn:id":2572349,
    "tgn:name":"Peach Four Corners",
    "tgn:placetype":[
        "aat:300008347"
    ]
},
  "bbox": [],
  "geometry": {"coordinates":[-72.0833,44.05],"type":"Point"}
}