{
  "id": 7280897,
  "type": "Feature",
  "properties": {
    "tgn:hierarchy":[
        "tgn:7280897",
        "tgn:1001768",
        "tgn:1000049",
        "tgn:1000002",
        "tgn:7029392"
    ],
    "tgn:id":7280897,
    "tgn:name":"San Joaqu\u00edn, Quebrada",
    "tgn:placetype":[
        "aat:300266554",
        "aat:300008699"
    ]
},
  "bbox": [],
  "geometry": {"coordinates":[-71.133333,-32.383333],"type":"Point"}
}