{
  "id": 7399195,
  "type": "Feature",
  "properties": {
    "tgn:hierarchy":[
        "tgn:7399195",
        "tgn:1000001",
        "tgn:1001893",
        "tgn:7005560",
        "tgn:7029392"
    ],
    "tgn:id":7399195,
    "tgn:name":"Potrero Redondo",
    "tgn:placetype":[
        "aat:300008347"
    ]
},
  "bbox": [],
  "geometry": {"coordinates":[-99.817222,19.018611],"type":"Point"}
}