{
  "id": 7003295,
  "type": "Feature",
  "properties": {
    "tgn:hierarchy":[
        "tgn:7003295",
        "tgn:7003026",
        "tgn:1000003",
        "tgn:1000062",
        "tgn:7029392"
    ],
    "tgn:id":7003295,
    "tgn:name":"Enns",
    "tgn:placetype":[
        "aat:300008347",
        "aat:300387275",
        "aat:300387285"
    ]
},
  "bbox": [],
  "geometry": {"coordinates":[14.4667,48.2167],"type":"Point"}
}