{
  "id": 7277144,
  "type": "Feature",
  "properties": {
    "tgn:hierarchy":[
        "tgn:7277144",
        "tgn:1001768",
        "tgn:1000049",
        "tgn:1000002",
        "tgn:7029392"
    ],
    "tgn:id":7277144,
    "tgn:name":"Yeco",
    "tgn:placetype":[
        "aat:300008347"
    ]
},
  "bbox": [],
  "geometry": {"coordinates":[-71.633333,-33.316667],"type":"Point"}
}