{
  "id": 7328931,
  "type": "Feature",
  "properties": {
    "tgn:hierarchy":[
        "tgn:7328931",
        "tgn:7002834",
        "tgn:1000003",
        "tgn:7002786",
        "tgn:1000095",
        "tgn:7029392"
    ],
    "tgn:id":7328931,
    "tgn:name":"Redondela, R\u00edo de",
    "tgn:placetype":[
        "aat:300008699"
    ]
},
  "bbox": [],
  "geometry": {"coordinates":[-8.616667,42.283333],"type":"Point"}
}