{
  "id": 2234952,
  "type": "Feature",
  "properties": {
    "tgn:hierarchy":[
        "tgn:2234952",
        "tgn:1000001",
        "tgn:7012149",
        "tgn:1002594",
        "tgn:7007920",
        "tgn:7029392"
    ],
    "tgn:id":2234952,
    "tgn:name":"Cherry Hill",
    "tgn:placetype":[
        "aat:300008798"
    ]
},
  "bbox": [],
  "geometry": {"coordinates":[-123.25,46.5833],"type":"Point"}
}