{
  "id": 7453519,
  "type": "Feature",
  "properties": {
    "tgn:hierarchy":[
        "tgn:7453519",
        "tgn:7002445",
        "tgn:1000003",
        "tgn:7008139",
        "tgn:7008591",
        "tgn:7029392"
    ],
    "tgn:id":7453519,
    "tgn:name:en":"Christchurch Bay",
    "tgn:placetype":[
        "aat:300132316"
    ]
},
  "bbox": [],
  "geometry": {"coordinates":[-1.677727,50.718913],"type":"Point"}
}