{
  "id": 2202729,
  "type": "Feature",
  "properties": {
    "tgn:hierarchy":[
        "tgn:2202729",
        "tgn:1000001",
        "tgn:7012149",
        "tgn:2002383",
        "tgn:7007923",
        "tgn:7029392"
    ],
    "tgn:id":2202729,
    "tgn:name":"Buckboard Crossing",
    "tgn:placetype":[
        "aat:300008347"
    ]
},
  "bbox": [],
  "geometry": {"coordinates":[-109.5833,41.2333],"type":"Point"}
}