{
  "id": 2468399,
  "type": "Feature",
  "properties": {
    "tgn:hierarchy":[
        "tgn:2468399",
        "tgn:2000258",
        "tgn:1000001",
        "tgn:7012149",
        "tgn:7007240",
        "tgn:7029392"
    ],
    "tgn:id":2468399,
    "tgn:name":"Long Point",
    "tgn:placetype":[
        "aat:300008850"
    ]
},
  "bbox": [],
  "geometry": {"coordinates":[-85.75,30.2333],"type":"Point"}
}