{
  "id": 2107071,
  "type": "Feature",
  "properties": {
    "tgn:hierarchy":[
        "tgn:2107071",
        "tgn:1000001",
        "tgn:7012149",
        "tgn:1002244",
        "tgn:7007826",
        "tgn:7029392"
    ],
    "tgn:id":2107071,
    "tgn:name":"Red Hill",
    "tgn:placetype":[
        "aat:300008347",
        "aat:300387210"
    ]
},
  "bbox": [],
  "geometry": {"coordinates":[-94.3667,33.1167],"type":"Point"}
}