{
  "id": 7532898,
  "type": "Feature",
  "properties": {
    "tgn:hierarchy":[
        "tgn:7532898",
        "tgn:7001242",
        "tgn:7016833",
        "tgn:1001091",
        "tgn:7029392"
    ],
    "tgn:id":7532898,
    "tgn:name":"Shirkat ash Sharq lil Ta'm\u012bn",
    "tgn:placetype":[
        "aat:300004792"
    ]
},
  "bbox": [],
  "geometry": {"coordinates":[31.242074,30.046305],"type":"Point"}
}