{
  "id": 2281969,
  "type": "Feature",
  "properties": {
    "tgn:hierarchy":[
        "tgn:2281969",
        "tgn:1000001",
        "tgn:7012149",
        "tgn:7007923",
        "tgn:7029392"
    ],
    "tgn:id":2281969,
    "tgn:name":"Deer Gulch",
    "tgn:placetype":[
        "aat:300008761"
    ]
},
  "bbox": [],
  "geometry": {"coordinates":[-110.5667,42.45],"type":"Point"}
}