{
  "id": 7337768,
  "type": "Feature",
  "properties": {
    "tgn:hierarchy":[
        "tgn:7337768",
        "tgn:7002829",
        "tgn:1000003",
        "tgn:7002786",
        "tgn:1000095",
        "tgn:7029392"
    ],
    "tgn:id":7337768,
    "tgn:name":"Castroncelos",
    "tgn:placetype":[
        "aat:300008347"
    ]
},
  "bbox": [],
  "geometry": {"coordinates":[-7.383333,42.55],"type":"Point"}
}