{
  "id": 7420672,
  "type": "Feature",
  "properties": {
    "tgn:hierarchy":[
        "tgn:7420672",
        "tgn:7005579",
        "tgn:1000001",
        "tgn:7005560",
        "tgn:7029392"
    ],
    "tgn:id":7420672,
    "tgn:name":"San Andres",
    "tgn:placetype":[
        "aat:300008347"
    ]
},
  "bbox": [],
  "geometry": {"coordinates":[-102.375,21.866667],"type":"Point"}
}