<<<<<<< HEAD
{
  "id": 7114557,
  "type": "Feature",
  "properties": {
    "tgn:hierarchy":[
        "tgn:7114557",
        "tgn:1000003",
        "tgn:7003688",
        "tgn:7000084",
        "tgn:7029392"
    ],
    "tgn:id":7114557,
    "tgn:name":"Rixdorfer Teich",
    "tgn:placetype":[
        "aat:300008680"
    ]
},
  "bbox": [],
  "geometry": {"coordinates":[10.4,54.216667],"type":"Point"}
}
=======
{"geometry":{"type":"Point","coordinates":[10.400000,54.216667]},"type":"Feature","properties":{"hierarchy":["tgn:7114557","tgn:1000003","tgn:7003688","tgn:7000084","tgn:7029392"],"placetype":["aat:300008680"],"id":7114557,"name:xx":"Rixdorfer Teich"}}
>>>>>>> 03f74aca74312dbeaf24d7e61306dd6a786dc3d0
