{
  "id": 7348436,
  "type": "Feature",
  "properties": {
    "tgn:hierarchy":[
        "tgn:7348436",
        "tgn:7002835",
        "tgn:7001158",
        "tgn:1000003",
        "tgn:1000095",
        "tgn:7029392"
    ],
    "tgn:id":7348436,
    "tgn:name":"Agadones, R\u00edo",
    "tgn:placetype":[
        "aat:300008699"
    ]
},
  "bbox": [],
  "geometry": {"coordinates":[-6.516667,40.483333],"type":"Point"}
}