<<<<<<< HEAD
{
  "id": 2153580,
  "type": "Feature",
  "properties": {
    "tgn:hierarchy":[
        "tgn:2153580",
        "tgn:7002659",
        "tgn:1000001",
        "tgn:7012149",
        "tgn:2000029",
        "tgn:7029392"
    ],
    "tgn:id":2153580,
    "tgn:name":"Bear Branch",
    "tgn:placetype":[
        "aat:300008699"
    ]
},
  "bbox": [],
  "geometry": {"coordinates":[-88.1,34.35],"type":"Point"}
}
=======
{"geometry":{"type":"Point","coordinates":[-88.100000,34.350000]},"type":"Feature","properties":{"hierarchy":["tgn:2153580","tgn:7002659","tgn:1000001","tgn:7012149","tgn:2000029","tgn:7029392"],"placetype":["aat:300008699"],"id":2153580,"name:xx":"Bear Branch"}}
>>>>>>> 03f74aca74312dbeaf24d7e61306dd6a786dc3d0
