<<<<<<< HEAD
{
  "id": 7179621,
  "type": "Feature",
  "properties": {
    "tgn:hierarchy":[
        "tgn:7179621",
        "tgn:1000003",
        "tgn:7003682",
        "tgn:7000084",
        "tgn:7029392"
    ],
    "tgn:id":7179621,
    "tgn:name":"Hahnerhof",
    "tgn:placetype":[
        "aat:300000206"
    ]
},
  "bbox": [],
  "geometry": {"coordinates":[7.883333,49.516667],"type":"Point"}
}
=======
{"geometry":{"type":"Point","coordinates":[7.883333,49.516667]},"type":"Feature","properties":{"hierarchy":["tgn:7179621","tgn:1000003","tgn:7003682","tgn:7000084","tgn:7029392"],"placetype":["aat:300000206"],"id":7179621,"name:xx":"Hahnerhof"}}
>>>>>>> 03f74aca74312dbeaf24d7e61306dd6a786dc3d0
