{
  "id": 7463423,
  "type": "Feature",
  "properties": {
    "tgn:hierarchy":[
        "tgn:7463423",
        "tgn:7002444",
        "tgn:1000003",
        "tgn:7029508",
        "tgn:7008591",
        "tgn:7029392"
    ],
    "tgn:id":7463423,
    "tgn:name:en":"Long Guen",
    "tgn:placetype":[
        "aat:300011692"
    ]
},
  "bbox": [],
  "geometry": {"coordinates":[-0.816667,60.383333],"type":"Point"}
}