{
  "id": 2000122,
  "type": "Feature",
  "properties": {
    "tgn:hierarchy":[
        "tgn:2000122",
        "tgn:1000001",
        "tgn:7016172",
        "tgn:7012149",
        "tgn:7029392"
    ],
    "tgn:id":2000122,
    "tgn:name":"Crittenden",
    "tgn:placetype":[
        "aat:300387145",
        "aat:300000771"
    ]
},
  "bbox": [],
  "geometry": {"coordinates":[-90.2833,35.2333],"type":"Point"}
}