<<<<<<< HEAD
{
  "id": 7353484,
  "type": "Feature",
  "properties": {
    "tgn:hierarchy":[
        "tgn:7353484",
        "tgn:1000001",
        "tgn:1001960",
        "tgn:7005560",
        "tgn:7029392"
    ],
    "tgn:id":7353484,
    "tgn:name":"Bellotal, Arroyo",
    "tgn:placetype":[
        "aat:300008699"
    ]
},
  "bbox": [],
  "geometry": {"coordinates":[-110.116667,29.666667],"type":"Point"}
}
=======
{"geometry":{"type":"Point","coordinates":[-110.116667,29.666667]},"type":"Feature","properties":{"hierarchy":["tgn:7353484","tgn:1000001","tgn:1001960","tgn:7005560","tgn:7029392"],"placetype":["aat:300008699"],"id":7353484,"name:xx":"Bellotal, Arroyo"}}
>>>>>>> 03f74aca74312dbeaf24d7e61306dd6a786dc3d0
