{
  "id": 2637603,
  "type": "Feature",
  "properties": {
    "tgn:hierarchy":[
        "tgn:2637603",
        "tgn:2000090",
        "tgn:1000001",
        "tgn:7006451",
        "tgn:7012149",
        "tgn:7029392"
    ],
    "tgn:id":2637603,
    "tgn:name":"Saint Marys Lake Spring",
    "tgn:placetype":[
        "aat:300008697"
    ]
},
  "bbox": [],
  "geometry": {"coordinates":[-109.3167,33.9833],"type":"Point"}
}