{
  "id": 2156120,
  "type": "Feature",
  "properties": {
    "tgn:hierarchy":[
        "tgn:2156120",
        "tgn:1000001",
        "tgn:7016172",
        "tgn:7012149",
        "tgn:2000133",
        "tgn:7029392"
    ],
    "tgn:id":2156120,
    "tgn:name":"Beard Lake",
    "tgn:placetype":[
        "aat:300008680"
    ]
},
  "bbox": [],
  "geometry": {"coordinates":[-93.9167,33.6667],"type":"Point"}
}