<<<<<<< HEAD
{
  "id": 2156120,
  "type": "Feature",
  "properties": {
    "tgn:hierarchy":[
        "tgn:2156120",
        "tgn:1000001",
        "tgn:7016172",
        "tgn:7012149",
        "tgn:2000133",
        "tgn:7029392"
    ],
    "tgn:id":2156120,
    "tgn:name":"Beard Lake",
    "tgn:placetype":[
        "aat:300008680"
    ]
},
  "bbox": [],
  "geometry": {"coordinates":[-93.9167,33.6667],"type":"Point"}
}
=======
{"geometry":{"type":"Point","coordinates":[-93.916700,33.666700]},"type":"Feature","properties":{"hierarchy":["tgn:2156120","tgn:1000001","tgn:7016172","tgn:7012149","tgn:2000133","tgn:7029392"],"placetype":["aat:300008680"],"id":2156120,"name:xx":"Beard Lake"}}
>>>>>>> 03f74aca74312dbeaf24d7e61306dd6a786dc3d0
