{
  "id": 7158291,
  "type": "Feature",
  "properties": {
    "tgn:hierarchy":[
        "tgn:7158291",
        "tgn:7003692",
        "tgn:1000003",
        "tgn:7000084",
        "tgn:7029392"
    ],
    "tgn:id":7158291,
    "tgn:name":"H\u00f6he\u00e4cker",
    "tgn:placetype":[
        "aat:300132356"
    ]
},
  "bbox": [],
  "geometry": {"coordinates":[9.75,49.45],"type":"Point"}
}