{
  "id": 2697068,
  "type": "Feature",
  "properties": {
    "tgn:hierarchy":[
        "tgn:2697068",
        "tgn:1000001",
        "tgn:1003028",
        "tgn:7012149",
        "tgn:7007159",
        "tgn:7029392"
    ],
    "tgn:id":2697068,
    "tgn:name":"Stony Brook",
    "tgn:placetype":[
        "aat:300008699"
    ]
},
  "bbox": [],
  "geometry": {"coordinates":[-72.0167,41.7667],"type":"Point"}
}