{
  "id": 7320266,
  "type": "Feature",
  "properties": {
    "tgn:hierarchy":[
        "tgn:7320266",
        "tgn:1001699",
        "tgn:1000049",
        "tgn:1000002",
        "tgn:7029392"
    ],
    "tgn:id":7320266,
    "tgn:name":"Canutillar, Puerto el",
    "tgn:placetype":[
        "aat:300132317"
    ]
},
  "bbox": [],
  "geometry": {"coordinates":[-72.35,-41.516667],"type":"Point"}
}