{
  "id": 2189463,
  "type": "Feature",
  "properties": {
    "tgn:hierarchy":[
        "tgn:2189463",
        "tgn:1000001",
        "tgn:1002195",
        "tgn:7012149",
        "tgn:7007520",
        "tgn:7029392"
    ],
    "tgn:id":2189463,
    "tgn:name":"Bovee Lake",
    "tgn:placetype":[
        "aat:300008680"
    ]
},
  "bbox": [],
  "geometry": {"coordinates":[-84.8667,41.8167],"type":"Point"}
}