{
  "id": 2684386,
  "type": "Feature",
  "properties": {
    "tgn:hierarchy":[
        "tgn:2684386",
        "tgn:1000001",
        "tgn:1002286",
        "tgn:7012149",
        "tgn:7007710",
        "tgn:7029392"
    ],
    "tgn:id":2684386,
    "tgn:name":"Spicewood Run",
    "tgn:placetype":[
        "aat:300008699"
    ]
},
  "bbox": [],
  "geometry": {"coordinates":[-77.8833,41.3667],"type":"Point"}
}