{
  "id": 7587625,
  "type": "Feature",
  "properties": {
    "tgn:hierarchy":[
        "tgn:7587625",
        "tgn:1000004",
        "tgn:7000198",
        "tgn:7000799",
        "tgn:7029392"
    ],
    "tgn:id":7587625,
    "tgn:name:en":"Mahar\u0101jpur",
    "tgn:placetype":[
        "aat:300008347"
    ]
},
  "bbox": [],
  "geometry": {"coordinates":[74.788889,34.0625],"type":"Point"}
}