<<<<<<< HEAD
{
  "id": 2406475,
  "type": "Feature",
  "properties": {
    "tgn:hierarchy":[
        "tgn:2406475",
        "tgn:1000001",
        "tgn:1002328",
        "tgn:7012149",
        "tgn:7007568",
        "tgn:7029392"
    ],
    "tgn:id":2406475,
    "tgn:name":"Hungry Hollow",
    "tgn:placetype":[
        "aat:300008761"
    ]
},
  "bbox": [],
  "geometry": {"coordinates":[-75.3667,42.0333],"type":"Point"}
}
=======
{"geometry":{"type":"Point","coordinates":[-75.366700,42.033300]},"type":"Feature","properties":{"hierarchy":["tgn:2406475","tgn:1000001","tgn:1002328","tgn:7012149","tgn:7007568","tgn:7029392"],"placetype":["aat:300008761"],"id":2406475,"name:xx":"Hungry Hollow"}}
>>>>>>> 03f74aca74312dbeaf24d7e61306dd6a786dc3d0
