{
  "id": 7361312,
  "type": "Feature",
  "properties": {
    "tgn:hierarchy":[
        "tgn:7361312",
        "tgn:7005579",
        "tgn:1000001",
        "tgn:7005560",
        "tgn:7029392"
    ],
    "tgn:id":7361312,
    "tgn:name":"El Copudo",
    "tgn:placetype":[
        "aat:300008347"
    ]
},
  "bbox": [],
  "geometry": {"coordinates":[-97.35,25.166667],"type":"Point"}
}