{
  "id": 7571231,
  "type": "Feature",
  "properties": {
    "tgn:hierarchy":[
        "tgn:7571231",
        "tgn:1000004",
        "tgn:7000198",
        "tgn:1001895",
        "tgn:7029392"
    ],
    "tgn:id":7571231,
    "tgn:name:en":"Janj\u012bra Fort",
    "tgn:placetype":[
        "aat:300006909"
    ]
},
  "bbox": [],
  "geometry": {"coordinates":[73.083333,17.833333],"type":"Point"}
}