{
  "id": 2401275,
  "type": "Feature",
  "properties": {
    "tgn:hierarchy":[
        "tgn:2401275",
        "tgn:1000001",
        "tgn:7012149",
        "tgn:2000473",
        "tgn:7007250",
        "tgn:7029392"
    ],
    "tgn:id":2401275,
    "tgn:name":"Horsemint Spring",
    "tgn:placetype":[
        "aat:300008697"
    ]
},
  "bbox": [],
  "geometry": {"coordinates":[-111.5167,44.5167],"type":"Point"}
}