{
  "id": 2755335,
  "type": "Feature",
  "properties": {
    "tgn:hierarchy":[
        "tgn:2755335",
        "tgn:1000001",
        "tgn:7012149",
        "tgn:2001860",
        "tgn:7007825",
        "tgn:7029392"
    ],
    "tgn:id":2755335,
    "tgn:name":"Weber Branch",
    "tgn:placetype":[
        "aat:300008699"
    ]
},
  "bbox": [],
  "geometry": {"coordinates":[-89.5833,35.2333],"type":"Point"}
}