{
  "id": 1060234,
  "type": "Feature",
  "properties": {
    "tgn:hierarchy":[
        "tgn:1060234",
        "tgn:1000004",
        "tgn:7011459",
        "tgn:7014786",
        "tgn:7029392"
    ],
    "tgn:id":1060234,
    "tgn:name":"Temirtau",
    "tgn:placetype":[
        "aat:300008347"
    ]
},
  "bbox": [],
  "geometry": {"coordinates":[72.9167,50.0833],"type":"Point"}
}