{
  "id": 2780207,
  "type": "Feature",
  "properties": {
    "tgn:hierarchy":[
        "tgn:2780207",
        "tgn:1000001",
        "tgn:2000457",
        "tgn:7012149",
        "tgn:7007250",
        "tgn:7029392"
    ],
    "tgn:id":2780207,
    "tgn:name":"Wolverine Creek",
    "tgn:placetype":[
        "aat:300008706"
    ]
},
  "bbox": [],
  "geometry": {"coordinates":[-111.8667,43.2833],"type":"Point"}
}