<<<<<<< HEAD
{
  "id": 2405297,
  "type": "Feature",
  "properties": {
    "tgn:hierarchy":[
        "tgn:2405297",
        "tgn:1000001",
        "tgn:7012149",
        "tgn:1003022",
        "tgn:7007252",
        "tgn:7029392"
    ],
    "tgn:id":2405297,
    "tgn:name":"Huffman Branch",
    "tgn:placetype":[
        "aat:300008699"
    ]
},
  "bbox": [],
  "geometry": {"coordinates":[-85.5333,41.0333],"type":"Point"}
}
=======
{"geometry":{"type":"Point","coordinates":[-85.533300,41.033300]},"type":"Feature","properties":{"hierarchy":["tgn:2405297","tgn:1000001","tgn:7012149","tgn:1003022","tgn:7007252","tgn:7029392"],"placetype":["aat:300008699"],"id":2405297,"name:xx":"Huffman Branch"}}
>>>>>>> 03f74aca74312dbeaf24d7e61306dd6a786dc3d0
