{
  "id": 2171301,
  "type": "Feature",
  "properties": {
    "tgn:hierarchy":[
        "tgn:2171301",
        "tgn:1000001",
        "tgn:7012149",
        "tgn:1002517",
        "tgn:7007523",
        "tgn:7029392"
    ],
    "tgn:id":2171301,
    "tgn:name":"Big Spring Hollow",
    "tgn:placetype":[
        "aat:300008761"
    ]
},
  "bbox": [],
  "geometry": {"coordinates":[-90.4667,38.05],"type":"Point"}
}