{
  "id": 2569913,
  "type": "Feature",
  "properties": {
    "tgn:hierarchy":[
        "tgn:2569913",
        "tgn:1000001",
        "tgn:7012149",
        "tgn:2002051",
        "tgn:7007826",
        "tgn:7029392"
    ],
    "tgn:id":2569913,
    "tgn:name":"Partwood Crossing",
    "tgn:placetype":[
        "aat:300008347"
    ]
},
  "bbox": [],
  "geometry": {"coordinates":[-102.6667,35.5167],"type":"Point"}
}