{
  "id": 2310770,
  "type": "Feature",
  "properties": {
    "tgn:hierarchy":[
        "tgn:2310770",
        "tgn:1000001",
        "tgn:7012149",
        "tgn:2001310",
        "tgn:7007524",
        "tgn:7029392"
    ],
    "tgn:id":2310770,
    "tgn:name":"Eclipse Creek",
    "tgn:placetype":[
        "aat:300008706"
    ]
},
  "bbox": [],
  "geometry": {"coordinates":[-111.3833,48.8833],"type":"Point"}
}