{
  "id": 2294139,
  "type": "Feature",
  "properties": {
    "tgn:hierarchy":[
        "tgn:2294139",
        "tgn:1000001",
        "tgn:7012149",
        "tgn:2002178",
        "tgn:7007919",
        "tgn:7029392"
    ],
    "tgn:id":2294139,
    "tgn:name":"Dovel Mountain",
    "tgn:placetype":[
        "aat:300008798"
    ]
},
  "bbox": [],
  "geometry": {"coordinates":[-78.55,38.5167],"type":"Point"}
}