{
  "id": 2360570,
  "type": "Feature",
  "properties": {
    "tgn:hierarchy":[
        "tgn:2360570",
        "tgn:1000001",
        "tgn:2002151",
        "tgn:7012149",
        "tgn:7007919",
        "tgn:7029392"
    ],
    "tgn:id":2360570,
    "tgn:name":"Grassy Creek",
    "tgn:placetype":[
        "aat:300008706"
    ]
},
  "bbox": [],
  "geometry": {"coordinates":[-80.55,36.65],"type":"Point"}
}