{
  "id": 7331268,
  "type": "Feature",
  "properties": {
    "tgn:hierarchy":[
        "tgn:7331268",
        "tgn:7002824",
        "tgn:1000003",
        "tgn:7002786",
        "tgn:1000095",
        "tgn:7029392"
    ],
    "tgn:id":7331268,
    "tgn:name":"Laraje",
    "tgn:placetype":[
        "aat:300008347"
    ]
},
  "bbox": [],
  "geometry": {"coordinates":[-8.15,43.433333],"type":"Point"}
}