{
  "id": 7318493,
  "type": "Feature",
  "properties": {
    "tgn:hierarchy":[
        "tgn:7318493",
        "tgn:1001695",
        "tgn:1000049",
        "tgn:1000002",
        "tgn:7029392"
    ],
    "tgn:id":7318493,
    "tgn:name":"Charquic\u00e1n, Estero del",
    "tgn:placetype":[
        "aat:300008699"
    ]
},
  "bbox": [],
  "geometry": {"coordinates":[-70.983333,-34.516667],"type":"Point"}
}