{
  "id": 2205508,
  "type": "Feature",
  "properties": {
    "tgn:hierarchy":[
        "tgn:2205508",
        "tgn:1000001",
        "tgn:7012149",
        "tgn:2001821",
        "tgn:7007713",
        "tgn:7029392"
    ],
    "tgn:id":2205508,
    "tgn:name":"Bull Creek",
    "tgn:placetype":[
        "aat:300008706"
    ]
},
  "bbox": [],
  "geometry": {"coordinates":[-102.2167,43.8667],"type":"Point"}
}