{
  "id": 2285678,
  "type": "Feature",
  "properties": {
    "tgn:hierarchy":[
        "tgn:2285678",
        "tgn:1000001",
        "tgn:7006451",
        "tgn:7012149",
        "tgn:2000103",
        "tgn:7029392"
    ],
    "tgn:id":2285678,
    "tgn:name":"Devils Kitchen",
    "tgn:placetype":[
        "aat:300055621"
    ]
},
  "bbox": [],
  "geometry": {"coordinates":[-111.7667,34.8833],"type":"Point"}
}