{
  "id": 7362745,
  "type": "Feature",
  "properties": {
    "tgn:hierarchy":[
        "tgn:7362745",
        "tgn:1000001",
        "tgn:7005597",
        "tgn:7005560",
        "tgn:7029392"
    ],
    "tgn:id":7362745,
    "tgn:name":"Rancho El Carrizo",
    "tgn:placetype":[
        "aat:300000241"
    ]
},
  "bbox": [],
  "geometry": {"coordinates":[-98.65,24.65],"type":"Point"}
}