<<<<<<< HEAD
{
  "id": 7362745,
  "type": "Feature",
  "properties": {
    "tgn:hierarchy":[
        "tgn:7362745",
        "tgn:1000001",
        "tgn:7005597",
        "tgn:7005560",
        "tgn:7029392"
    ],
    "tgn:id":7362745,
    "tgn:name":"Rancho El Carrizo",
    "tgn:placetype":[
        "aat:300000241"
    ]
},
  "bbox": [],
  "geometry": {"coordinates":[-98.65,24.65],"type":"Point"}
}
=======
{"geometry":{"type":"Point","coordinates":[-98.650000,24.650000]},"type":"Feature","properties":{"hierarchy":["tgn:7362745","tgn:1000001","tgn:7005597","tgn:7005560","tgn:7029392"],"placetype":["aat:300000241"],"id":7362745,"name:xx":"Rancho El Carrizo"}}
>>>>>>> 03f74aca74312dbeaf24d7e61306dd6a786dc3d0
