{
  "id": 2102113,
  "type": "Feature",
  "properties": {
    "tgn:hierarchy":[
        "tgn:2102113",
        "tgn:1000001",
        "tgn:7012149",
        "tgn:2001862",
        "tgn:7007825",
        "tgn:7029392"
    ],
    "tgn:id":2102113,
    "tgn:name":"Wilder Chapel",
    "tgn:placetype":[
        "aat:300008347",
        "aat:300387210"
    ]
},
  "bbox": [],
  "geometry": {"coordinates":[-85.95,35.2833],"type":"Point"}
}