{
  "id": 7536982,
  "type": "Feature",
  "properties": {
    "tgn:hierarchy":[
        "tgn:7536982",
        "tgn:7001242",
        "tgn:7016833",
        "tgn:1001418",
        "tgn:7029392"
    ],
    "tgn:id":7536982,
    "tgn:name:en":"Kafret 'Eilet Imsh\u00e2zz",
    "tgn:placetype":[
        "aat:300008347"
    ]
},
  "bbox": [],
  "geometry": {"coordinates":[26.516667,31.466667],"type":"Point"}
}