{
  "id": 7472154,
  "type": "Feature",
  "properties": {
    "tgn:hierarchy":[
        "tgn:7472154",
        "tgn:1000004",
        "tgn:7489179",
        "tgn:1000141",
        "tgn:7029392"
    ],
    "tgn:id":7472154,
    "tgn:name":"Wuhan",
    "tgn:placetype":[
        "aat:300008347"
    ]
},
  "bbox": [],
  "geometry": {"coordinates":[121.796364,24.657264],"type":"Point"}
}