{
  "id": 7503838,
  "type": "Feature",
  "properties": {
    "tgn:hierarchy":[
        "tgn:7503838",
        "tgn:1000004",
        "tgn:7491221",
        "tgn:1000141",
        "tgn:7029392"
    ],
    "tgn:id":7503838,
    "tgn:name":"Dou Shan",
    "tgn:placetype":[
        "aat:300008798"
    ]
},
  "bbox": [],
  "geometry": {"coordinates":[120.889167,22.712778],"type":"Point"}
}