{
  "id": 7395857,
  "type": "Feature",
  "properties": {
    "tgn:hierarchy":[
        "tgn:7395857",
        "tgn:1000001",
        "tgn:7005597",
        "tgn:7005560",
        "tgn:7029392"
    ],
    "tgn:id":7395857,
    "tgn:name":"San Eugenio",
    "tgn:placetype":[
        "aat:300008347"
    ]
},
  "bbox": [],
  "geometry": {"coordinates":[-98.583333,23.266667],"type":"Point"}
}