{
  "id": 7196310,
  "type": "Feature",
  "properties": {
    "tgn:hierarchy":[
        "tgn:7196310",
        "tgn:7003692",
        "tgn:1000003",
        "tgn:7000084",
        "tgn:7029392"
    ],
    "tgn:id":7196310,
    "tgn:name":"Deutwang",
    "tgn:placetype":[
        "aat:300008347"
    ]
},
  "bbox": [],
  "geometry": {"coordinates":[9.083333,47.866667],"type":"Point"}
}