{
  "id": 7299916,
  "type": "Feature",
  "properties": {
    "tgn:hierarchy":[
        "tgn:7299916",
        "tgn:7002803",
        "tgn:1001647",
        "tgn:1000003",
        "tgn:1000095",
        "tgn:7029392"
    ],
    "tgn:id":7299916,
    "tgn:name":"Tus, R\u00edo",
    "tgn:placetype":[
        "aat:300008699"
    ]
},
  "bbox": [],
  "geometry": {"coordinates":[-2.216667,38.383333],"type":"Point"}
}