{
  "id": 2142744,
  "type": "Feature",
  "properties": {
    "tgn:hierarchy":[
        "tgn:2142744",
        "tgn:1000001",
        "tgn:7012149",
        "tgn:1003021",
        "tgn:7007252",
        "tgn:7029392"
    ],
    "tgn:id":2142744,
    "tgn:name":"Badger Grove",
    "tgn:placetype":[
        "aat:300008347"
    ]
},
  "bbox": [],
  "geometry": {"coordinates":[-86.95,40.5833],"type":"Point"}
}