{
  "id": 2652455,
  "type": "Feature",
  "properties": {
    "tgn:hierarchy":[
        "tgn:2652455",
        "tgn:1000001",
        "tgn:7012149",
        "tgn:2000835",
        "tgn:7007255",
        "tgn:7029392"
    ],
    "tgn:id":2652455,
    "tgn:name":"Seng Cove",
    "tgn:placetype":[
        "aat:300008761"
    ]
},
  "bbox": [],
  "geometry": {"coordinates":[-83.5667,37.3167],"type":"Point"}
}