{
  "id": 2274605,
  "type": "Feature",
  "properties": {
    "tgn:hierarchy":[
        "tgn:2274605",
        "tgn:7002659",
        "tgn:1000001",
        "tgn:7012149",
        "tgn:2000063",
        "tgn:7029392"
    ],
    "tgn:id":2274605,
    "tgn:name":"Dalton Mine",
    "tgn:placetype":[
        "aat:300000390"
    ]
},
  "bbox": [],
  "geometry": {"coordinates":[-87.2167,33.6667],"type":"Point"}
}