{
  "id": 1038896,
  "type": "Feature",
  "properties": {
    "tgn:hierarchy":[
        "tgn:1038896",
        "tgn:7003669",
        "tgn:1000003",
        "tgn:7000084",
        "tgn:7029392"
    ],
    "tgn:id":1038896,
    "tgn:name":"Edelshausen",
    "tgn:placetype":[
        "aat:300008347"
    ]
},
  "bbox": [],
  "geometry": {"coordinates":[11.283333,48.616667],"type":"Point"}
}