{
  "id": 2492766,
  "type": "Feature",
  "properties": {
    "tgn:hierarchy":[
        "tgn:2492766",
        "tgn:1000001",
        "tgn:7006451",
        "tgn:7012149",
        "tgn:2000097",
        "tgn:7029392"
    ],
    "tgn:id":2492766,
    "tgn:name":"Marion Spring Number One",
    "tgn:placetype":[
        "aat:300008697"
    ]
},
  "bbox": [],
  "geometry": {"coordinates":[-111.5167,33.9333],"type":"Point"}
}