{
  "id": 7336175,
  "type": "Feature",
  "properties": {
    "tgn:hierarchy":[
        "tgn:7336175",
        "tgn:7002816",
        "tgn:1001647",
        "tgn:1000003",
        "tgn:1000095",
        "tgn:7029392"
    ],
    "tgn:id":7336175,
    "tgn:name":"Gig\u00fcela, R\u00edo",
    "tgn:placetype":[
        "aat:300008699"
    ]
},
  "bbox": [],
  "geometry": {"coordinates":[-3.733333,39.133333],"type":"Point"}
}