<<<<<<< HEAD
{
  "id": 2158809,
  "type": "Feature",
  "properties": {
    "tgn:hierarchy":[
        "tgn:2158809",
        "tgn:1000001",
        "tgn:7012149",
        "tgn:2001420",
        "tgn:7007526",
        "tgn:7029392"
    ],
    "tgn:id":2158809,
    "tgn:name":"Beck Spring",
    "tgn:placetype":[
        "aat:300008697"
    ]
},
  "bbox": [],
  "geometry": {"coordinates":[-115.5833,39.6333],"type":"Point"}
}
=======
{"geometry":{"type":"Point","coordinates":[-115.583300,39.633300]},"type":"Feature","properties":{"hierarchy":["tgn:2158809","tgn:1000001","tgn:7012149","tgn:2001420","tgn:7007526","tgn:7029392"],"placetype":["aat:300008697"],"id":2158809,"name:xx":"Beck Spring"}}
>>>>>>> 03f74aca74312dbeaf24d7e61306dd6a786dc3d0
