<<<<<<< HEAD
{
  "id": 2259023,
  "type": "Feature",
  "properties": {
    "tgn:hierarchy":[
        "tgn:2259023",
        "tgn:1000001",
        "tgn:7012149",
        "tgn:1002431",
        "tgn:7007826",
        "tgn:7029392"
    ],
    "tgn:id":2259023,
    "tgn:name":"Cottonwood Creek",
    "tgn:placetype":[
        "aat:300008706"
    ]
},
  "bbox": [],
  "geometry": {"coordinates":[-98.0,29.45],"type":"Point"}
}
=======
{"geometry":{"type":"Point","coordinates":[-98.000000,29.450000]},"type":"Feature","properties":{"hierarchy":["tgn:2259023","tgn:1000001","tgn:7012149","tgn:1002431","tgn:7007826","tgn:7029392"],"placetype":["aat:300008706"],"id":2259023,"name:xx":"Cottonwood Creek"}}
>>>>>>> 03f74aca74312dbeaf24d7e61306dd6a786dc3d0
