{
  "id": 2107881,
  "type": "Feature",
  "properties": {
    "tgn:hierarchy":[
        "tgn:2107881",
        "tgn:1000001",
        "tgn:7012149",
        "tgn:2002007",
        "tgn:7007826",
        "tgn:7029392"
    ],
    "tgn:id":2107881,
    "tgn:name":"Suggs",
    "tgn:placetype":[
        "aat:300387016"
    ]
},
  "bbox": [],
  "geometry": {"coordinates":[-101.0667,31.1167],"type":"Point"}
}