{
  "id": 2164974,
  "type": "Feature",
  "properties": {
    "tgn:hierarchy":[
        "tgn:2164974",
        "tgn:7006450",
        "tgn:1000001",
        "tgn:2124053",
        "tgn:7012149",
        "tgn:7029392"
    ],
    "tgn:id":2164974,
    "tgn:name":"Beth, Lake",
    "tgn:placetype":[
        "aat:300008680"
    ]
},
  "bbox": [],
  "geometry": {"coordinates":[-149.8167,61.4167],"type":"Point"}
}