{
  "id": 7277337,
  "type": "Feature",
  "properties": {
    "tgn:hierarchy":[
        "tgn:7277337",
        "tgn:1001702",
        "tgn:1000049",
        "tgn:1000002",
        "tgn:7029392"
    ],
    "tgn:id":7277337,
    "tgn:name":"Sylvia, Punta",
    "tgn:placetype":[
        "aat:300386846"
    ]
},
  "bbox": [],
  "geometry": {"coordinates":[-68.183333,-54.908333],"type":"Point"}
}