{
  "id": 1108157,
  "type": "Feature",
  "properties": {
    "tgn:hierarchy":[
        "tgn:1108157",
        "tgn:1002169",
        "tgn:1000001",
        "tgn:7012149",
        "tgn:7007255",
        "tgn:7029392"
    ],
    "tgn:id":1108157,
    "tgn:name":"Olympus, Mount",
    "tgn:placetype":[
        "aat:300008777"
    ]
},
  "bbox": [],
  "geometry": {"coordinates":[-83.6333,38.0333],"type":"Point"}
}