{
  "id": 7473236,
  "type": "Feature",
  "properties": {
    "tgn:hierarchy":[
        "tgn:7473236",
        "tgn:1000004",
        "tgn:7001002",
        "tgn:1000141",
        "tgn:7029392"
    ],
    "tgn:id":7473236,
    "tgn:name":"Yangliao",
    "tgn:placetype":[
        "aat:300008347"
    ]
},
  "bbox": [],
  "geometry": {"coordinates":[120.923611,24.815833],"type":"Point"}
}