<<<<<<< HEAD
{
  "id": 7473236,
  "type": "Feature",
  "properties": {
    "tgn:hierarchy":[
        "tgn:7473236",
        "tgn:1000004",
        "tgn:7001002",
        "tgn:1000141",
        "tgn:7029392"
    ],
    "tgn:id":7473236,
    "tgn:name":"Yangliao",
    "tgn:placetype":[
        "aat:300008347"
    ]
},
  "bbox": [],
  "geometry": {"coordinates":[120.923611,24.815833],"type":"Point"}
}
=======
{"geometry":{"type":"Point","coordinates":[120.923611,24.815833]},"type":"Feature","properties":{"hierarchy":["tgn:7473236","tgn:1000004","tgn:7001002","tgn:1000141","tgn:7029392"],"placetype":["aat:300008347"],"id":7473236,"name:xx":"Yangliao"}}
>>>>>>> 03f74aca74312dbeaf24d7e61306dd6a786dc3d0
