{
  "id": 2333699,
  "type": "Feature",
  "properties": {
    "tgn:hierarchy":[
        "tgn:2333699",
        "tgn:1000001",
        "tgn:2000677",
        "tgn:7012149",
        "tgn:7007254",
        "tgn:7029392"
    ],
    "tgn:id":2333699,
    "tgn:name":"Foos Creek",
    "tgn:placetype":[
        "aat:300008706"
    ]
},
  "bbox": [],
  "geometry": {"coordinates":[-96.9667,37.35],"type":"Point"}
}