{
  "id": 2774068,
  "type": "Feature",
  "properties": {
    "tgn:hierarchy":[
        "tgn:2774068",
        "tgn:1000001",
        "tgn:7012149",
        "tgn:2001723",
        "tgn:7007708",
        "tgn:7029392"
    ],
    "tgn:id":2774068,
    "tgn:name":"Willow Creek",
    "tgn:placetype":[
        "aat:300008706"
    ]
},
  "bbox": [],
  "geometry": {"coordinates":[-119.9667,44.6333],"type":"Point"}
}