{
  "id": 2609258,
  "type": "Feature",
  "properties": {
    "tgn:hierarchy":[
        "tgn:2609258",
        "tgn:1000001",
        "tgn:7012149",
        "tgn:1002950",
        "tgn:7007568",
        "tgn:7029392"
    ],
    "tgn:id":2609258,
    "tgn:name":"Rawson Hollow",
    "tgn:placetype":[
        "aat:300008761"
    ]
},
  "bbox": [],
  "geometry": {"coordinates":[-76.25,42.35],"type":"Point"}
}