{
  "id": 2488373,
  "type": "Feature",
  "properties": {
    "tgn:hierarchy":[
        "tgn:2488373",
        "tgn:1000001",
        "tgn:7012149",
        "tgn:2001880",
        "tgn:7007825",
        "tgn:7029392"
    ],
    "tgn:id":2488373,
    "tgn:name":"Mahaney Cave",
    "tgn:placetype":[
        "aat:300008746"
    ]
},
  "bbox": [],
  "geometry": {"coordinates":[-85.6833,36.2833],"type":"Point"}
}