{
  "id": 7296836,
  "type": "Feature",
  "properties": {
    "tgn:hierarchy":[
        "tgn:7296836",
        "tgn:7002831",
        "tgn:1000003",
        "tgn:7002786",
        "tgn:1000095",
        "tgn:7029392"
    ],
    "tgn:id":7296836,
    "tgn:name":"Villar de Ordelles",
    "tgn:placetype":[
        "aat:300008347"
    ]
},
  "bbox": [],
  "geometry": {"coordinates":[-7.733333,42.316667],"type":"Point"}
}