{
  "id": 7403813,
  "type": "Feature",
  "properties": {
    "tgn:hierarchy":[
        "tgn:7403813",
        "tgn:7005578",
        "tgn:1000001",
        "tgn:7005560",
        "tgn:7029392"
    ],
    "tgn:id":7403813,
    "tgn:name":"La Victoria",
    "tgn:placetype":[
        "aat:300008347"
    ]
},
  "bbox": [],
  "geometry": {"coordinates":[-90.925,18.483333],"type":"Point"}
}