{
  "id": 7418549,
  "type": "Feature",
  "properties": {
    "tgn:hierarchy":[
        "tgn:7418549",
        "tgn:7005579",
        "tgn:1000001",
        "tgn:7005560",
        "tgn:7029392"
    ],
    "tgn:id":7418549,
    "tgn:name":"El Mirador, Cerro",
    "tgn:placetype":[
        "aat:300008795"
    ]
},
  "bbox": [],
  "geometry": {"coordinates":[-102.641667,22.116667],"type":"Point"}
}