{
  "id": 1030087,
  "type": "Feature",
  "properties": {
    "tgn:hierarchy":[
        "tgn:1030087",
        "tgn:7002445",
        "tgn:1000003",
        "tgn:7012077",
        "tgn:7008591",
        "tgn:7029392"
    ],
    "tgn:id":1030087,
    "tgn:name":"Moreton Hampstead",
    "tgn:placetype":[
        "aat:300008347"
    ]
},
  "bbox": [],
  "geometry": {"coordinates":[-3.75,50.65],"type":"Point"}
}