{
  "id": 7561345,
  "type": "Feature",
  "properties": {
    "tgn:hierarchy":[
        "tgn:7561345",
        "tgn:1000004",
        "tgn:7000198",
        "tgn:7016722",
        "tgn:7029392"
    ],
    "tgn:id":7561345,
    "tgn:name:en":"Mighauli",
    "tgn:placetype":[
        "aat:300008347"
    ]
},
  "bbox": [],
  "geometry": {"coordinates":[79.40573,27.154287],"type":"Point"}
}