{
  "id": 2580121,
  "type": "Feature",
  "properties": {
    "tgn:hierarchy":[
        "tgn:2580121",
        "tgn:1000001",
        "tgn:7012149",
        "tgn:2000931",
        "tgn:7007515",
        "tgn:7029392"
    ],
    "tgn:id":2580121,
    "tgn:name":"Pierce Hill",
    "tgn:placetype":[
        "aat:300008798"
    ]
},
  "bbox": [],
  "geometry": {"coordinates":[-69.2167,44.45],"type":"Point"}
}