{
  "id": 7295337,
  "type": "Feature",
  "properties": {
    "tgn:hierarchy":[
        "tgn:7295337",
        "tgn:7001165",
        "tgn:1000003",
        "tgn:7002793",
        "tgn:1000095",
        "tgn:7029392"
    ],
    "tgn:id":7295337,
    "tgn:name":"Pensamientos, Punta de los",
    "tgn:placetype":[
        "aat:300386846"
    ]
},
  "bbox": [],
  "geometry": {"coordinates":[-0.216667,39.175],"type":"Point"}
}