{
  "id": 2344956,
  "type": "Feature",
  "properties": {
    "tgn:hierarchy":[
        "tgn:2344956",
        "tgn:1002215",
        "tgn:1000001",
        "tgn:7012149",
        "tgn:7007565",
        "tgn:7029392"
    ],
    "tgn:id":2344956,
    "tgn:name":"Gardiners Landing",
    "tgn:placetype":[
        "aat:300008347"
    ]
},
  "bbox": [],
  "geometry": {"coordinates":[-74.6333,39.6167],"type":"Point"}
}