<<<<<<< HEAD
{
  "id": 2401234,
  "type": "Feature",
  "properties": {
    "tgn:hierarchy":[
        "tgn:2401234",
        "tgn:1000001",
        "tgn:7012149",
        "tgn:2001712",
        "tgn:7007708",
        "tgn:7029392"
    ],
    "tgn:id":2401234,
    "tgn:name":"Horseheaven",
    "tgn:placetype":[
        "aat:300008347"
    ]
},
  "bbox": [],
  "geometry": {"coordinates":[-120.5,44.7],"type":"Point"}
}
=======
{"geometry":{"type":"Point","coordinates":[-120.500000,44.700000]},"type":"Feature","properties":{"hierarchy":["tgn:2401234","tgn:1000001","tgn:7012149","tgn:2001712","tgn:7007708","tgn:7029392"],"placetype":["aat:300008347"],"id":2401234,"name:xx":"Horseheaven"}}
>>>>>>> 03f74aca74312dbeaf24d7e61306dd6a786dc3d0
