{
  "id": 2234711,
  "type": "Feature",
  "properties": {
    "tgn:hierarchy":[
        "tgn:2234711",
        "tgn:7002659",
        "tgn:1000001",
        "tgn:7012149",
        "tgn:2000044",
        "tgn:7029392"
    ],
    "tgn:id":2234711,
    "tgn:name":"Cherry Creek",
    "tgn:placetype":[
        "aat:300008347"
    ]
},
  "bbox": [],
  "geometry": {"coordinates":[-86.6167,34.7833],"type":"Point"}
}