<<<<<<< HEAD
{
  "id": 2766446,
  "type": "Feature",
  "properties": {
    "tgn:hierarchy":[
        "tgn:2766446",
        "tgn:1000001",
        "tgn:7012149",
        "tgn:1002632",
        "tgn:7007251",
        "tgn:7029392"
    ],
    "tgn:id":2766446,
    "tgn:name":"White Oak Branch",
    "tgn:placetype":[
        "aat:300008699"
    ]
},
  "bbox": [],
  "geometry": {"coordinates":[-88.7667,38.6833],"type":"Point"}
}
=======
{"geometry":{"type":"Point","coordinates":[-88.766700,38.683300]},"type":"Feature","properties":{"hierarchy":["tgn:2766446","tgn:1000001","tgn:7012149","tgn:1002632","tgn:7007251","tgn:7029392"],"placetype":["aat:300008699"],"id":2766446,"name:xx":"White Oak Branch"}}
>>>>>>> 03f74aca74312dbeaf24d7e61306dd6a786dc3d0
