{
  "id": 2545761,
  "type": "Feature",
  "properties": {
    "tgn:hierarchy":[
        "tgn:2545761",
        "tgn:1000001",
        "tgn:2001411",
        "tgn:7012149",
        "tgn:7007526",
        "tgn:7029392"
    ],
    "tgn:id":2545761,
    "tgn:name":"North Fork Cold Creek",
    "tgn:placetype":[
        "aat:300008706"
    ]
},
  "bbox": [],
  "geometry": {"coordinates":[-115.2833,40.7167],"type":"Point"}
}