{
  "id": 2059554,
  "type": "Feature",
  "properties": {
    "tgn:hierarchy":[
        "tgn:2059554",
        "tgn:1000001",
        "tgn:7012149",
        "tgn:1002619",
        "tgn:7007523",
        "tgn:7029392"
    ],
    "tgn:id":2059554,
    "tgn:name":"Lingo",
    "tgn:placetype":[
        "aat:300008347"
    ]
},
  "bbox": [],
  "geometry": {"coordinates":[-92.8167,39.7667],"type":"Point"}
}