{
  "id": 2314859,
  "type": "Feature",
  "properties": {
    "tgn:hierarchy":[
        "tgn:2314859",
        "tgn:1000001",
        "tgn:7012149",
        "tgn:2002371",
        "tgn:7007923",
        "tgn:7029392"
    ],
    "tgn:id":2314859,
    "tgn:name":"Elkhorn Draw",
    "tgn:placetype":[
        "aat:300008761"
    ]
},
  "bbox": [],
  "geometry": {"coordinates":[-108.9333,42.3833],"type":"Point"}
}