{
  "id": 2459906,
  "type": "Feature",
  "properties": {
    "tgn:hierarchy":[
        "tgn:2459906",
        "tgn:1000001",
        "tgn:7012149",
        "tgn:2002191",
        "tgn:7007919",
        "tgn:7029392"
    ],
    "tgn:id":2459906,
    "tgn:name":"Little Roberts Cave",
    "tgn:placetype":[
        "aat:300008746"
    ]
},
  "bbox": [],
  "geometry": {"coordinates":[-81.3833,36.7667],"type":"Point"}
}