{
  "id": 2695625,
  "type": "Feature",
  "properties": {
    "tgn:hierarchy":[
        "tgn:2695625",
        "tgn:1000001",
        "tgn:7012149",
        "tgn:2002126",
        "tgn:7007827",
        "tgn:7029392"
    ],
    "tgn:id":2695625,
    "tgn:name":"Stinking Springs",
    "tgn:placetype":[
        "aat:300008697"
    ]
},
  "bbox": [],
  "geometry": {"coordinates":[-111.0333,40.1333],"type":"Point"}
}