{
  "id": 2660955,
  "type": "Feature",
  "properties": {
    "tgn:hierarchy":[
        "tgn:2660955",
        "tgn:1000001",
        "tgn:7012149",
        "tgn:2001303",
        "tgn:7007524",
        "tgn:7029392"
    ],
    "tgn:id":2660955,
    "tgn:name":"Short Creek",
    "tgn:placetype":[
        "aat:300008706"
    ]
},
  "bbox": [],
  "geometry": {"coordinates":[-106.6833,46.3333],"type":"Point"}
}