{
  "id": 2096784,
  "type": "Feature",
  "properties": {
    "tgn:hierarchy":[
        "tgn:2096784",
        "tgn:1000001",
        "tgn:2001742",
        "tgn:7012149",
        "tgn:7007712",
        "tgn:7029392"
    ],
    "tgn:id":2096784,
    "tgn:name":"Summerville",
    "tgn:placetype":[
        "aat:300008347"
    ]
},
  "bbox": [],
  "geometry": {"coordinates":[-80.1667,33.0167],"type":"Point"}
}