{
  "id": 7475388,
  "type": "Feature",
  "properties": {
    "tgn:hierarchy":[
        "tgn:7475388",
        "tgn:1000004",
        "tgn:7490934",
        "tgn:1000141",
        "tgn:7029392"
    ],
    "tgn:id":7475388,
    "tgn:name":"Wenhua Li",
    "tgn:placetype":[
        "aat:300387200"
    ]
},
  "bbox": [],
  "geometry": {"coordinates":[120.193889,23.215],"type":"Point"}
}