<<<<<<< HEAD
{
  "id": 7475388,
  "type": "Feature",
  "properties": {
    "tgn:hierarchy":[
        "tgn:7475388",
        "tgn:1000004",
        "tgn:7490934",
        "tgn:1000141",
        "tgn:7029392"
    ],
    "tgn:id":7475388,
    "tgn:name":"Wenhua Li",
    "tgn:placetype":[
        "aat:300387200"
    ]
},
  "bbox": [],
  "geometry": {"coordinates":[120.193889,23.215],"type":"Point"}
}
=======
{"geometry":{"type":"Point","coordinates":[120.193889,23.215000]},"type":"Feature","properties":{"hierarchy":["tgn:7475388","tgn:1000004","tgn:7490934","tgn:1000141","tgn:7029392"],"placetype":["aat:300387200"],"id":7475388,"name:xx":"Wenhua Li"}}
>>>>>>> 03f74aca74312dbeaf24d7e61306dd6a786dc3d0
