{
  "id": 7311435,
  "type": "Feature",
  "properties": {
    "tgn:hierarchy":[
        "tgn:7311435",
        "tgn:1001699",
        "tgn:1000049",
        "tgn:1000002",
        "tgn:7029392"
    ],
    "tgn:id":7311435,
    "tgn:name":"Los Corrales, Laguna",
    "tgn:placetype":[
        "aat:300008680"
    ]
},
  "bbox": [],
  "geometry": {"coordinates":[-72.05,-40.366667],"type":"Point"}
}