{
  "id": 2725693,
  "type": "Feature",
  "properties": {
    "tgn:hierarchy":[
        "tgn:2725693",
        "tgn:1000001",
        "tgn:7012149",
        "tgn:1002676",
        "tgn:7007240",
        "tgn:7029392"
    ],
    "tgn:id":2725693,
    "tgn:name":"Torch Key Mangroves",
    "tgn:placetype":[
        "aat:300008791"
    ]
},
  "bbox": [],
  "geometry": {"coordinates":[-81.45,24.7167],"type":"Point"}
}