{
  "id": 7070296,
  "type": "Feature",
  "properties": {
    "tgn:hierarchy":[
        "tgn:7070296",
        "tgn:7003669",
        "tgn:1000003",
        "tgn:7000084",
        "tgn:7029392"
    ],
    "tgn:id":7070296,
    "tgn:name":"Steinbachgehau",
    "tgn:placetype":[
        "aat:300008863"
    ]
},
  "bbox": [],
  "geometry": {"coordinates":[10.283333,48.266667],"type":"Point"}
}