{
  "id": 2289529,
  "type": "Feature",
  "properties": {
    "tgn:hierarchy":[
        "tgn:2289529",
        "tgn:1000001",
        "tgn:7012149",
        "tgn:2001067",
        "tgn:7007521",
        "tgn:7029392"
    ],
    "tgn:id":2289529,
    "tgn:name":"Dixon Creek",
    "tgn:placetype":[
        "aat:300008706"
    ]
},
  "bbox": [],
  "geometry": {"coordinates":[-92.6333,48.2833],"type":"Point"}
}