{
  "id": 7158976,
  "type": "Feature",
  "properties": {
    "tgn:hierarchy":[
        "tgn:7158976",
        "tgn:7003669",
        "tgn:1000003",
        "tgn:7000084",
        "tgn:7029392"
    ],
    "tgn:id":7158976,
    "tgn:name":"Hofstetten",
    "tgn:placetype":[
        "aat:300008347"
    ]
},
  "bbox": [],
  "geometry": {"coordinates":[10.966667,48.016667],"type":"Point"}
}