{
  "id": 7034477,
  "type": "Feature",
  "properties": {
    "tgn:hierarchy":[
        "tgn:7034477",
        "tgn:1003488",
        "tgn:1000003",
        "tgn:7002993",
        "tgn:1000080",
        "tgn:7029392"
    ],
    "tgn:id":7034477,
    "tgn:name":"Giais, Forcella di",
    "tgn:placetype":[
        "aat:300259572"
    ]
},
  "bbox": [],
  "geometry": {"coordinates":[12.564722,46.125278],"type":"Point"}
}