{
  "id": 7443934,
  "type": "Feature",
  "properties": {
    "tgn:hierarchy":[
        "tgn:7443934",
        "tgn:7002444",
        "tgn:1000003",
        "tgn:7008082",
        "tgn:7008591",
        "tgn:7029392"
    ],
    "tgn:id":7443934,
    "tgn:name:en":"Upper Diabaig",
    "tgn:placetype":[
        "aat:300008347"
    ]
},
  "bbox": [],
  "geometry": {"coordinates":[-5.65,57.566667],"type":"Point"}
}