{
  "id": 2598073,
  "type": "Feature",
  "properties": {
    "tgn:hierarchy":[
        "tgn:2598073",
        "tgn:1000001",
        "tgn:7012149",
        "tgn:2001897",
        "tgn:7007825",
        "tgn:7029392"
    ],
    "tgn:id":2598073,
    "tgn:name":"Presley Hill",
    "tgn:placetype":[
        "aat:300008798"
    ]
},
  "bbox": [],
  "geometry": {"coordinates":[-84.7833,35.55],"type":"Point"}
}