{
  "id": 2616044,
  "type": "Feature",
  "properties": {
    "tgn:hierarchy":[
        "tgn:2616044",
        "tgn:1000001",
        "tgn:7016172",
        "tgn:7012149",
        "tgn:7029392"
    ],
    "tgn:id":2616044,
    "tgn:name":"Rhinehart Branch",
    "tgn:placetype":[
        "aat:300008699"
    ]
},
  "bbox": [],
  "geometry": {"coordinates":[-92.7333,34.35],"type":"Point"}
}