{
  "id": 1088698,
  "type": "Feature",
  "properties": {
    "tgn:hierarchy":[
        "tgn:1088698",
        "tgn:7001242",
        "tgn:1001023",
        "tgn:1000158",
        "tgn:7029392"
    ],
    "tgn:id":1088698,
    "tgn:name":"Mokou",
    "tgn:placetype":[
        "aat:300008347"
    ]
},
  "bbox": [],
  "geometry": {"coordinates":[15.2167,-4.2167],"type":"Point"}
}