{
  "id": 2667983,
  "type": "Feature",
  "properties": {
    "tgn:hierarchy":[
        "tgn:2667983",
        "tgn:1000001",
        "tgn:7012149",
        "tgn:7007158",
        "tgn:2000246",
        "tgn:7029392"
    ],
    "tgn:id":2667983,
    "tgn:name":"Sky City Mine",
    "tgn:placetype":[
        "aat:300000390"
    ]
},
  "bbox": [],
  "geometry": {"coordinates":[-106.6667,37.9167],"type":"Point"}
}