{
  "id": 7491176,
  "type": "Feature",
  "properties": {
    "tgn:hierarchy":[
        "tgn:7491176",
        "tgn:1000004",
        "tgn:7492971",
        "tgn:1000141",
        "tgn:7029392"
    ],
    "tgn:id":7491176,
    "tgn:name":"Sankuaicuo",
    "tgn:placetype":[
        "aat:300008347"
    ]
},
  "bbox": [],
  "geometry": {"coordinates":[120.481944,22.751111],"type":"Point"}
}