{
  "id": 2564218,
  "type": "Feature",
  "properties": {
    "tgn:hierarchy":[
        "tgn:2564218",
        "tgn:1002648",
        "tgn:1000001",
        "tgn:7019158",
        "tgn:7012149",
        "tgn:7007249",
        "tgn:7029392"
    ],
    "tgn:id":2564218,
    "tgn:name":"Paako",
    "tgn:placetype":[
        "aat:300008850"
    ]
},
  "bbox": [],
  "geometry": {"coordinates":[-156.4333,20.6167],"type":"Point"}
}