{
  "id": 2139358,
  "type": "Feature",
  "properties": {
    "tgn:hierarchy":[
        "tgn:2139358",
        "tgn:1000001",
        "tgn:2001432",
        "tgn:7012149",
        "tgn:7007566",
        "tgn:7029392"
    ],
    "tgn:id":2139358,
    "tgn:name":"Aspen Hill",
    "tgn:placetype":[
        "aat:300008798"
    ]
},
  "bbox": [],
  "geometry": {"coordinates":[-105.1333,36.2833],"type":"Point"}
}