{
  "id": 2151348,
  "type": "Feature",
  "properties": {
    "tgn:hierarchy":[
        "tgn:2151348",
        "tgn:7002659",
        "tgn:1000001",
        "tgn:7012149",
        "tgn:2000029",
        "tgn:7029392"
    ],
    "tgn:id":2151348,
    "tgn:name":"Bates Lake",
    "tgn:placetype":[
        "aat:300006191"
    ]
},
  "bbox": [],
  "geometry": {"coordinates":[-88.1333,34.4167],"type":"Point"}
}