{
  "id": 2223710,
  "type": "Feature",
  "properties": {
    "tgn:hierarchy":[
        "tgn:2223710",
        "tgn:7002659",
        "tgn:1000001",
        "tgn:2000013",
        "tgn:7012149",
        "tgn:7029392"
    ],
    "tgn:id":2223710,
    "tgn:name":"Carter Lake",
    "tgn:placetype":[
        "aat:300006191"
    ]
},
  "bbox": [],
  "geometry": {"coordinates":[-85.6833,33.2333],"type":"Point"}
}