{
  "id": 2288051,
  "type": "Feature",
  "properties": {
    "tgn:hierarchy":[
        "tgn:2288051",
        "tgn:1000001",
        "tgn:7012149",
        "tgn:2000227",
        "tgn:7007158",
        "tgn:7029392"
    ],
    "tgn:id":2288051,
    "tgn:name":"Dinner Branch",
    "tgn:placetype":[
        "aat:300008699"
    ]
},
  "bbox": [],
  "geometry": {"coordinates":[-103.3333,37.4333],"type":"Point"}
}