{
  "id": 7562577,
  "type": "Feature",
  "properties": {
    "tgn:hierarchy":[
        "tgn:7562577",
        "tgn:1000004",
        "tgn:7000198",
        "tgn:7016722",
        "tgn:7029392"
    ],
    "tgn:id":7562577,
    "tgn:name:en":"Chhabile Purwa",
    "tgn:placetype":[
        "aat:300008347"
    ]
},
  "bbox": [],
  "geometry": {"coordinates":[79.7795,27.1314],"type":"Point"}
}