{
  "id": 2673707,
  "type": "Feature",
  "properties": {
    "tgn:hierarchy":[
        "tgn:2673707",
        "tgn:1000001",
        "tgn:7012149",
        "tgn:2002374",
        "tgn:7007923",
        "tgn:7029392"
    ],
    "tgn:id":2673707,
    "tgn:name":"Snow Cave Ridge",
    "tgn:placetype":[
        "aat:300266640"
    ]
},
  "bbox": [],
  "geometry": {"coordinates":[-106.95,43.8667],"type":"Point"}
}