{
  "id": 2340590,
  "type": "Feature",
  "properties": {
    "tgn:hierarchy":[
        "tgn:2340590",
        "tgn:1000001",
        "tgn:7012149",
        "tgn:1002758",
        "tgn:7007568",
        "tgn:7029392"
    ],
    "tgn:id":2340590,
    "tgn:name":"Frenchman Island",
    "tgn:placetype":[
        "aat:300008791"
    ]
},
  "bbox": [],
  "geometry": {"coordinates":[-76.05,43.2167],"type":"Point"}
}