{
  "id": 7206662,
  "type": "Feature",
  "properties": {
    "tgn:hierarchy":[
        "tgn:7206662",
        "tgn:7003669",
        "tgn:1000003",
        "tgn:7000084",
        "tgn:7029392"
    ],
    "tgn:id":7206662,
    "tgn:name":"Burghagel",
    "tgn:placetype":[
        "aat:300008347"
    ]
},
  "bbox": [],
  "geometry": {"coordinates":[10.333333,48.633333],"type":"Point"}
}