{
  "id": 7340346,
  "type": "Feature",
  "properties": {
    "tgn:hierarchy":[
        "tgn:7340346",
        "tgn:7001155",
        "tgn:1000003",
        "tgn:7002790",
        "tgn:1000095",
        "tgn:7029392"
    ],
    "tgn:id":7340346,
    "tgn:name":"Eguiarreta",
    "tgn:placetype":[
        "aat:300008347"
    ]
},
  "bbox": [],
  "geometry": {"coordinates":[-1.85,42.933333],"type":"Point"}
}