{
  "id": 2644136,
  "type": "Feature",
  "properties": {
    "tgn:hierarchy":[
        "tgn:2644136",
        "tgn:1000001",
        "tgn:7012149",
        "tgn:2002094",
        "tgn:7007826",
        "tgn:7029392"
    ],
    "tgn:id":2644136,
    "tgn:name":"Santa Rosa Lake",
    "tgn:placetype":[
        "aat:300008680"
    ]
},
  "bbox": [],
  "geometry": {"coordinates":[-97.7167,26.3333],"type":"Point"}
}