<<<<<<< HEAD
{
  "id": 2402004,
  "type": "Feature",
  "properties": {
    "tgn:hierarchy":[
        "tgn:2402004",
        "tgn:1000001",
        "tgn:7012149",
        "tgn:1003003",
        "tgn:7007251",
        "tgn:7029392"
    ],
    "tgn:id":2402004,
    "tgn:name":"Horseshoe Pond",
    "tgn:placetype":[
        "aat:300008680"
    ]
},
  "bbox": [],
  "geometry": {"coordinates":[-88.2,38.3333],"type":"Point"}
}
=======
{"geometry":{"type":"Point","coordinates":[-88.200000,38.333300]},"type":"Feature","properties":{"hierarchy":["tgn:2402004","tgn:1000001","tgn:7012149","tgn:1003003","tgn:7007251","tgn:7029392"],"placetype":["aat:300008680"],"id":2402004,"name:xx":"Horseshoe Pond"}}
>>>>>>> 03f74aca74312dbeaf24d7e61306dd6a786dc3d0
