{
  "id": 2529133,
  "type": "Feature",
  "properties": {
    "tgn:hierarchy":[
        "tgn:2529133",
        "tgn:1000001",
        "tgn:2000264",
        "tgn:7012149",
        "tgn:7007240",
        "tgn:7029392"
    ],
    "tgn:id":2529133,
    "tgn:name":"Mud Flats Creek",
    "tgn:placetype":[
        "aat:300008706"
    ]
},
  "bbox": [],
  "geometry": {"coordinates":[-81.4833,30.3667],"type":"Point"}
}