<<<<<<< HEAD
{
  "id": 2405468,
  "type": "Feature",
  "properties": {
    "tgn:hierarchy":[
        "tgn:2405468",
        "tgn:1000001",
        "tgn:7012149",
        "tgn:2001543",
        "tgn:7007709",
        "tgn:7029392"
    ],
    "tgn:id":2405468,
    "tgn:name":"Hughes Branch",
    "tgn:placetype":[
        "aat:300008699"
    ]
},
  "bbox": [],
  "geometry": {"coordinates":[-83.4333,35.4],"type":"Point"}
}
=======
{"geometry":{"type":"Point","coordinates":[-83.433300,35.400000]},"type":"Feature","properties":{"hierarchy":["tgn:2405468","tgn:1000001","tgn:7012149","tgn:2001543","tgn:7007709","tgn:7029392"],"placetype":["aat:300008699"],"id":2405468,"name:xx":"Hughes Branch"}}
>>>>>>> 03f74aca74312dbeaf24d7e61306dd6a786dc3d0
