{
  "id": 2166083,
  "type": "Feature",
  "properties": {
    "tgn:hierarchy":[
        "tgn:2166083",
        "tgn:7006450",
        "tgn:1000001",
        "tgn:7019698",
        "tgn:7012149",
        "tgn:7029392"
    ],
    "tgn:id":2166083,
    "tgn:name":"Big Bay",
    "tgn:placetype":[
        "aat:300132316"
    ]
},
  "bbox": [],
  "geometry": {"coordinates":[-150.85,60.15],"type":"Point"}
}