{
  "id": 7510363,
  "type": "Feature",
  "properties": {
    "tgn:hierarchy":[
        "tgn:7510363",
        "tgn:7000508",
        "tgn:1008380",
        "tgn:1000226",
        "tgn:1000006",
        "tgn:7029392"
    ],
    "tgn:id":7510363,
    "tgn:name:en":"Te Hono Point",
    "tgn:placetype":[
        "aat:300386846"
    ]
},
  "bbox": [],
  "geometry": {"coordinates":[174.65,-37.033333],"type":"Point"}
}