{
  "id": 7538089,
  "type": "Feature",
  "properties": {
    "tgn:hierarchy":[
        "tgn:7538089",
        "tgn:7001242",
        "tgn:7016833",
        "tgn:1001123",
        "tgn:7029392"
    ],
    "tgn:id":7538089,
    "tgn:name":"R\u00e2s el-Riqqa, Gez\u00eeret",
    "tgn:placetype":[
        "aat:300008791"
    ]
},
  "bbox": [],
  "geometry": {"coordinates":[32.123056,31.086389],"type":"Point"}
}