{
  "id": 1003468,
  "type": "Feature",
  "properties": {
    "tgn:hierarchy":[
        "tgn:1003468",
        "tgn:1000003",
        "tgn:7010380",
        "tgn:1000080",
        "tgn:7029392"
    ],
    "tgn:id":1003468,
    "tgn:name":"Lecce",
    "tgn:placetype":[
        "aat:300387145",
        "aat:300000774"
    ]
},
  "bbox": [],
  "geometry": {"coordinates":[18.166667,40.216667],"type":"Point"}
}