{
  "id": 2452358,
  "type": "Feature",
  "properties": {
    "tgn:hierarchy":[
        "tgn:2452358",
        "tgn:1000001",
        "tgn:7012149",
        "tgn:2000480",
        "tgn:7007250",
        "tgn:7029392"
    ],
    "tgn:id":2452358,
    "tgn:name":"Little Boulder Creek",
    "tgn:placetype":[
        "aat:300008706"
    ]
},
  "bbox": [],
  "geometry": {"coordinates":[-116.3833,46.7667],"type":"Point"}
}