{
  "id": 2039619,
  "type": "Feature",
  "properties": {
    "tgn:hierarchy":[
        "tgn:2039619",
        "tgn:1000001",
        "tgn:7012149",
        "tgn:1002880",
        "tgn:7007255",
        "tgn:7029392"
    ],
    "tgn:id":2039619,
    "tgn:name":"Josephine",
    "tgn:placetype":[
        "aat:300008347",
        "aat:300387210"
    ]
},
  "bbox": [],
  "geometry": {"coordinates":[-84.65,38.3833],"type":"Point"}
}