{
  "id": 1023001,
  "type": "Feature",
  "properties": {
    "tgn:hierarchy":[
        "tgn:1023001",
        "tgn:7006064",
        "tgn:1000047",
        "tgn:7002455",
        "tgn:1000002",
        "tgn:7029392"
    ],
    "tgn:id":1023001,
    "tgn:name":"Santana do Cariri",
    "tgn:placetype":[
        "aat:300008347"
    ]
},
  "bbox": [],
  "geometry": {"coordinates":[-39.75,-7.2333],"type":"Point"}
}