{
  "id": 2368178,
  "type": "Feature",
  "properties": {
    "tgn:hierarchy":[
        "tgn:2368178",
        "tgn:1000001",
        "tgn:2001704",
        "tgn:7012149",
        "tgn:7007708",
        "tgn:7029392"
    ],
    "tgn:id":2368178,
    "tgn:name":"Guano Rock",
    "tgn:placetype":[
        "aat:300008791"
    ]
},
  "bbox": [],
  "geometry": {"coordinates":[-124.2833,42.0333],"type":"Point"}
}