{
  "id": 7430497,
  "type": "Feature",
  "properties": {
    "tgn:hierarchy":[
        "tgn:7430497",
        "tgn:1001853",
        "tgn:1000001",
        "tgn:7005560",
        "tgn:7029392"
    ],
    "tgn:id":7430497,
    "tgn:name":"Mota de Corona",
    "tgn:placetype":[
        "aat:300008347"
    ]
},
  "bbox": [],
  "geometry": {"coordinates":[-101.183333,27.416667],"type":"Point"}
}