{
  "id": 7574714,
  "type": "Feature",
  "properties": {
    "tgn:hierarchy":[
        "tgn:7574714",
        "tgn:1000004",
        "tgn:1001869",
        "tgn:7000198",
        "tgn:7029392"
    ],
    "tgn:id":7574714,
    "tgn:name:en":"Kur\u0101l",
    "tgn:placetype":[
        "aat:300008347"
    ]
},
  "bbox": [],
  "geometry": {"coordinates":[72.916667,22.15],"type":"Point"}
}