{
  "id": 1130648,
  "type": "Feature",
  "properties": {
    "tgn:hierarchy":[
        "tgn:1130648",
        "tgn:1000002",
        "tgn:7029392"
    ],
    "tgn:id":1130648,
    "tgn:name":"Tarra",
    "tgn:placetype":[
        "aat:300008707"
    ]
},
  "bbox": [],
  "geometry": {"coordinates":[-72.1167,9.05],"type":"Point"}
}