{
  "id": 2557128,
  "type": "Feature",
  "properties": {
    "tgn:hierarchy":[
        "tgn:2557128",
        "tgn:1000001",
        "tgn:2001429",
        "tgn:7012149",
        "tgn:7007566",
        "tgn:7029392"
    ],
    "tgn:id":2557128,
    "tgn:name":"Old Highway Tank",
    "tgn:placetype":[
        "aat:300006191"
    ]
},
  "bbox": [],
  "geometry": {"coordinates":[-108.9333,33.5333],"type":"Point"}
}