{
  "id": 2077789,
  "type": "Feature",
  "properties": {
    "tgn:hierarchy":[
        "tgn:2077789",
        "tgn:1000001",
        "tgn:2001571",
        "tgn:7012149",
        "tgn:7007705",
        "tgn:7029392"
    ],
    "tgn:id":2077789,
    "tgn:name":"Linton",
    "tgn:placetype":[
        "aat:300008347"
    ]
},
  "bbox": [],
  "geometry": {"coordinates":[-100.2167,46.2667],"type":"Point"}
}