<<<<<<< HEAD
{
  "id": 2257409,
  "type": "Feature",
  "properties": {
    "tgn:hierarchy":[
        "tgn:2257409",
        "tgn:1000001",
        "tgn:7012149",
        "tgn:2000790",
        "tgn:7007255",
        "tgn:7029392"
    ],
    "tgn:id":2257409,
    "tgn:name":"Cornwall Pond",
    "tgn:placetype":[
        "aat:300008680"
    ]
},
  "bbox": [],
  "geometry": {"coordinates":[-89.0667,36.6],"type":"Point"}
}
=======
{"geometry":{"type":"Point","coordinates":[-89.066700,36.600000]},"type":"Feature","properties":{"hierarchy":["tgn:2257409","tgn:1000001","tgn:7012149","tgn:2000790","tgn:7007255","tgn:7029392"],"placetype":["aat:300008680"],"id":2257409,"name:xx":"Cornwall Pond"}}
>>>>>>> 03f74aca74312dbeaf24d7e61306dd6a786dc3d0
