{
  "id": 2515001,
  "type": "Feature",
  "properties": {
    "tgn:hierarchy":[
        "tgn:2515001",
        "tgn:1000001",
        "tgn:7012149",
        "tgn:2000384",
        "tgn:7007248",
        "tgn:7029392"
    ],
    "tgn:id":2515001,
    "tgn:name":"Miller Top",
    "tgn:placetype":[
        "aat:300008798"
    ]
},
  "bbox": [],
  "geometry": {"coordinates":[-83.9167,34.6833],"type":"Point"}
}