{
  "id": 2380746,
  "type": "Feature",
  "properties": {
    "tgn:hierarchy":[
        "tgn:2380746",
        "tgn:7002659",
        "tgn:1000001",
        "tgn:2000016",
        "tgn:7012149",
        "tgn:7029392"
    ],
    "tgn:id":2380746,
    "tgn:name":"Haw Pond",
    "tgn:placetype":[
        "aat:300008680"
    ]
},
  "bbox": [],
  "geometry": {"coordinates":[-87.5833,34.7333],"type":"Point"}
}