<<<<<<< HEAD
{
  "id": 2400200,
  "type": "Feature",
  "properties": {
    "tgn:hierarchy":[
        "tgn:2400200",
        "tgn:1000001",
        "tgn:7012149",
        "tgn:2002056",
        "tgn:7007826",
        "tgn:7029392"
    ],
    "tgn:id":2400200,
    "tgn:name":"Horse Creek",
    "tgn:placetype":[
        "aat:300008706"
    ]
},
  "bbox": [],
  "geometry": {"coordinates":[-101.9833,35.3333],"type":"Point"}
}
=======
{"geometry":{"type":"Point","coordinates":[-101.983300,35.333300]},"type":"Feature","properties":{"hierarchy":["tgn:2400200","tgn:1000001","tgn:7012149","tgn:2002056","tgn:7007826","tgn:7029392"],"placetype":["aat:300008706"],"id":2400200,"name:xx":"Horse Creek"}}
>>>>>>> 03f74aca74312dbeaf24d7e61306dd6a786dc3d0
