{
  "id": 1081875,
  "type": "Feature",
  "properties": {
    "tgn:hierarchy":[
        "tgn:1081875",
        "tgn:1002057",
        "tgn:1000004",
        "tgn:1000121",
        "tgn:7029392"
    ],
    "tgn:id":1081875,
    "tgn:name":"As-Sal\u1e6d",
    "tgn:placetype":[
        "aat:300008347",
        "aat:300387220",
        "aat:300008375"
    ]
},
  "bbox": [],
  "geometry": {"coordinates":[35.7167,32.0333],"type":"Point"}
}