{
  "id": 7015616,
  "type": "Feature",
  "properties": {
    "tgn:hierarchy":[
        "tgn:7015616",
        "tgn:1000001",
        "tgn:7012149",
        "tgn:7018871",
        "tgn:7007920",
        "tgn:7029392"
    ],
    "tgn:id":7015616,
    "tgn:name":"Richmond Beach",
    "tgn:placetype":[
        "aat:300008347"
    ]
},
  "bbox": [],
  "geometry": {"coordinates":[-122.3833,47.7667],"type":"Point"}
}