{
  "id": 1074671,
  "type": "Feature",
  "properties": {
    "tgn:hierarchy":[
        "tgn:1074671",
        "tgn:1000004",
        "tgn:7000198",
        "tgn:7016788",
        "tgn:7029392"
    ],
    "tgn:id":1074671,
    "tgn:name":"Bari Sadri",
    "tgn:placetype":[
        "aat:300008347"
    ]
},
  "bbox": [],
  "geometry": {"coordinates":[74.75,24.3667],"type":"Point"}
}