{
  "id": 1077068,
  "type": "Feature",
  "properties": {
    "tgn:hierarchy":[
        "tgn:1077068",
        "tgn:1000004",
        "tgn:1001842",
        "tgn:7000198",
        "tgn:7029392"
    ],
    "tgn:id":1077068,
    "tgn:name:en":"Sagauli",
    "tgn:placetype":[
        "aat:300008347"
    ]
},
  "bbox": [],
  "geometry": {"coordinates":[84.741974,26.771366],"type":"Point"}
}