{
  "id": 2702974,
  "type": "Feature",
  "properties": {
    "tgn:hierarchy":[
        "tgn:2702974",
        "tgn:1000001",
        "tgn:7012149",
        "tgn:1002839",
        "tgn:7007826",
        "tgn:7029392"
    ],
    "tgn:id":2702974,
    "tgn:name":"Sulphur Springs Branch",
    "tgn:placetype":[
        "aat:300008699"
    ]
},
  "bbox": [],
  "geometry": {"coordinates":[-94.7667,31.9167],"type":"Point"}
}