{
  "id": 2020432,
  "type": "Feature",
  "properties": {
    "tgn:hierarchy":[
        "tgn:2020432",
        "tgn:1000001",
        "tgn:7012149",
        "tgn:1002929",
        "tgn:7007240",
        "tgn:7029392"
    ],
    "tgn:id":2020432,
    "tgn:name":"Moreland Park",
    "tgn:placetype":[
        "aat:300008347"
    ]
},
  "bbox": [],
  "geometry": {"coordinates":[-82.0333,28.8833],"type":"Point"}
}