{
  "id": 7548358,
  "type": "Feature",
  "properties": {
    "tgn:hierarchy":[
        "tgn:7548358",
        "tgn:1000004",
        "tgn:7000198",
        "tgn:1001977",
        "tgn:7029392"
    ],
    "tgn:id":7548358,
    "tgn:name:en":"Brind\u0101banpur",
    "tgn:placetype":[
        "aat:300008347"
    ]
},
  "bbox": [],
  "geometry": {"coordinates":[87.27878,23.310182],"type":"Point"}
}