{
  "id": 2347673,
  "type": "Feature",
  "properties": {
    "tgn:hierarchy":[
        "tgn:2347673",
        "tgn:1000001",
        "tgn:7012149",
        "tgn:2002265",
        "tgn:7013961",
        "tgn:7029392"
    ],
    "tgn:id":2347673,
    "tgn:name":"Georges Peak",
    "tgn:placetype":[
        "aat:300008798"
    ]
},
  "bbox": [],
  "geometry": {"coordinates":[-78.45,39.35],"type":"Point"}
}