{
  "id": 7556994,
  "type": "Feature",
  "properties": {
    "tgn:hierarchy":[
        "tgn:7556994",
        "tgn:1000004",
        "tgn:1001869",
        "tgn:7000198",
        "tgn:7029392"
    ],
    "tgn:id":7556994,
    "tgn:name:en":"Sajiavadar",
    "tgn:placetype":[
        "aat:300007783"
    ]
},
  "bbox": [],
  "geometry": {"coordinates":[71.166667,21.483333],"type":"Point"}
}