{
  "id": 1133047,
  "type": "Feature",
  "properties": {
    "tgn:hierarchy":[
        "tgn:1133047",
        "tgn:7005685",
        "tgn:1000001",
        "tgn:7013154",
        "tgn:7029392"
    ],
    "tgn:id":1133047,
    "tgn:name":"Dingman Creek",
    "tgn:placetype":[
        "aat:300008706"
    ]
},
  "bbox": [],
  "geometry": {"coordinates":[-81.4167,42.9167],"type":"Point"}
}