{
  "id": 2781270,
  "type": "Feature",
  "properties": {
    "tgn:hierarchy":[
        "tgn:2781270",
        "tgn:7002659",
        "tgn:1000001",
        "tgn:7012149",
        "tgn:2000038",
        "tgn:7029392"
    ],
    "tgn:id":2781270,
    "tgn:name":"Woodland",
    "tgn:placetype":[
        "aat:300008347"
    ]
},
  "bbox": [],
  "geometry": {"coordinates":[-87.8167,34.75],"type":"Point"}
}