<<<<<<< HEAD
{
  "id": 2259861,
  "type": "Feature",
  "properties": {
    "tgn:hierarchy":[
        "tgn:2259861",
        "tgn:1000001",
        "tgn:7012149",
        "tgn:2001307",
        "tgn:7007524",
        "tgn:7029392"
    ],
    "tgn:id":2259861,
    "tgn:name":"Coulee Creek",
    "tgn:placetype":[
        "aat:300008706"
    ]
},
  "bbox": [],
  "geometry": {"coordinates":[-109.4167,45.7167],"type":"Point"}
}
=======
{"geometry":{"type":"Point","coordinates":[-109.416700,45.716700]},"type":"Feature","properties":{"hierarchy":["tgn:2259861","tgn:1000001","tgn:7012149","tgn:2001307","tgn:7007524","tgn:7029392"],"placetype":["aat:300008706"],"id":2259861,"name:xx":"Coulee Creek"}}
>>>>>>> 03f74aca74312dbeaf24d7e61306dd6a786dc3d0
