{
  "id": 7577061,
  "type": "Feature",
  "properties": {
    "tgn:hierarchy":[
        "tgn:7577061",
        "tgn:1000004",
        "tgn:7000198",
        "tgn:1001882",
        "tgn:7029392"
    ],
    "tgn:id":7577061,
    "tgn:name:en":"Krishnar\u0101janagara",
    "tgn:placetype":[
        "aat:300007783"
    ]
},
  "bbox": [],
  "geometry": {"coordinates":[76.416667,12.433333],"type":"Point"}
}