{
  "id": 2691504,
  "type": "Feature",
  "properties": {
    "tgn:hierarchy":[
        "tgn:2691504",
        "tgn:1000001",
        "tgn:7012149",
        "tgn:7013867",
        "tgn:7007710",
        "tgn:7029392"
    ],
    "tgn:id":2691504,
    "tgn:name":"Star Rock",
    "tgn:placetype":[
        "aat:300008347"
    ]
},
  "bbox": [],
  "geometry": {"coordinates":[-76.45,39.9333],"type":"Point"}
}