{
  "id": 2125452,
  "type": "Feature",
  "properties": {
    "tgn:hierarchy":[
        "tgn:2125452",
        "tgn:1000001",
        "tgn:1002934",
        "tgn:7012149",
        "tgn:7007565",
        "tgn:7029392"
    ],
    "tgn:id":2125452,
    "tgn:name":"Acquackanonk, Lake",
    "tgn:placetype":[
        "aat:300008680"
    ]
},
  "bbox": [],
  "geometry": {"coordinates":[-74.5667,41.05],"type":"Point"}
}