{
  "id": 7112251,
  "type": "Feature",
  "properties": {
    "tgn:hierarchy":[
        "tgn:7112251",
        "tgn:7003669",
        "tgn:1000003",
        "tgn:7000084",
        "tgn:7029392"
    ],
    "tgn:id":7112251,
    "tgn:name":"Rohrbach",
    "tgn:placetype":[
        "aat:300008347"
    ]
},
  "bbox": [],
  "geometry": {"coordinates":[11.566667,48.616667],"type":"Point"}
}