<<<<<<< HEAD
{
  "id": 7379979,
  "type": "Feature",
  "properties": {
    "tgn:hierarchy":[
        "tgn:7379979",
        "tgn:7005581",
        "tgn:1000001",
        "tgn:7005560",
        "tgn:7029392"
    ],
    "tgn:id":7379979,
    "tgn:name":"Maset El Ojo",
    "tgn:placetype":[
        "aat:300000241"
    ]
},
  "bbox": [],
  "geometry": {"coordinates":[-107.666667,29.366667],"type":"Point"}
}
=======
{"geometry":{"type":"Point","coordinates":[-107.666667,29.366667]},"type":"Feature","properties":{"hierarchy":["tgn:7379979","tgn:7005581","tgn:1000001","tgn:7005560","tgn:7029392"],"placetype":["aat:300000241"],"id":7379979,"name:xx":"Maset El Ojo"}}
>>>>>>> 03f74aca74312dbeaf24d7e61306dd6a786dc3d0
