{
  "id": 7063539,
  "type": "Feature",
  "properties": {
    "tgn:hierarchy":[
        "tgn:7063539",
        "tgn:7003669",
        "tgn:1000003",
        "tgn:7000084",
        "tgn:7029392"
    ],
    "tgn:id":7063539,
    "tgn:name":"Attenmoos",
    "tgn:placetype":[
        "aat:300000206"
    ]
},
  "bbox": [],
  "geometry": {"coordinates":[12.55,47.966667],"type":"Point"}
}