{
  "id": 7343390,
  "type": "Feature",
  "properties": {
    "tgn:hierarchy":[
        "tgn:7343390",
        "tgn:7002759",
        "tgn:7008909",
        "tgn:1000003",
        "tgn:1000095",
        "tgn:7029392"
    ],
    "tgn:id":7343390,
    "tgn:name":"Cajigosa",
    "tgn:placetype":[
        "aat:300008347"
    ]
},
  "bbox": [],
  "geometry": {"coordinates":[0.153019,42.453854],"type":"Point"}
}