{
  "id": 2656185,
  "type": "Feature",
  "properties": {
    "tgn:hierarchy":[
        "tgn:2656185",
        "tgn:1000001",
        "tgn:7012149",
        "tgn:2002286",
        "tgn:7013961",
        "tgn:7029392"
    ],
    "tgn:id":2656185,
    "tgn:name":"Shawnee Run",
    "tgn:placetype":[
        "aat:300008699"
    ]
},
  "bbox": [],
  "geometry": {"coordinates":[-81.05,39.3833],"type":"Point"}
}