{
  "id": 7381891,
  "type": "Feature",
  "properties": {
    "tgn:hierarchy":[
        "tgn:7381891",
        "tgn:1000001",
        "tgn:1001906",
        "tgn:7005560",
        "tgn:7029392"
    ],
    "tgn:id":7381891,
    "tgn:name":"Los Bancos",
    "tgn:placetype":[
        "aat:300008699"
    ]
},
  "bbox": [],
  "geometry": {"coordinates":[-104.433333,21.733333],"type":"Point"}
}