{
  "id": 2747025,
  "type": "Feature",
  "properties": {
    "tgn:hierarchy":[
        "tgn:2747025",
        "tgn:1000001",
        "tgn:7012149",
        "tgn:2002381",
        "tgn:7007923",
        "tgn:7029392"
    ],
    "tgn:id":2747025,
    "tgn:name":"Wagner Reservoir",
    "tgn:placetype":[
        "aat:300006191"
    ]
},
  "bbox": [],
  "geometry": {"coordinates":[-107.2833,44.9167],"type":"Point"}
}