{
  "id": 2013309,
  "type": "Feature",
  "properties": {
    "tgn:hierarchy":[
        "tgn:2013309",
        "tgn:1000001",
        "tgn:7012149",
        "tgn:1002545",
        "tgn:7007157",
        "tgn:7029392"
    ],
    "tgn:id":2013309,
    "tgn:name":"Pentland",
    "tgn:placetype":[
        "aat:300387016"
    ]
},
  "bbox": [],
  "geometry": {"coordinates":[-119.35,34.9833],"type":"Point"}
}