{
  "id": 7281925,
  "type": "Feature",
  "properties": {
    "tgn:hierarchy":[
        "tgn:7281925",
        "tgn:1001702",
        "tgn:1000049",
        "tgn:1000002",
        "tgn:7029392"
    ],
    "tgn:id":7281925,
    "tgn:name":"Schweers, Islote",
    "tgn:placetype":[
        "aat:300008791"
    ]
},
  "bbox": [],
  "geometry": {"coordinates":[-75.066667,-49.916667],"type":"Point"}
}