{
  "id": 2125639,
  "type": "Feature",
  "properties": {
    "tgn:hierarchy":[
        "tgn:2125639",
        "tgn:1000001",
        "tgn:2002255",
        "tgn:7012149",
        "tgn:7013961",
        "tgn:7029392"
    ],
    "tgn:id":2125639,
    "tgn:name":"Adams",
    "tgn:placetype":[
        "aat:300008347"
    ]
},
  "bbox": [],
  "geometry": {"coordinates":[-81.85,38.1667],"type":"Point"}
}