{
  "id": 7430195,
  "type": "Feature",
  "properties": {
    "tgn:hierarchy":[
        "tgn:7430195",
        "tgn:1000001",
        "tgn:7005595",
        "tgn:7005560",
        "tgn:7029392"
    ],
    "tgn:id":7430195,
    "tgn:name":"El Barril",
    "tgn:placetype":[
        "aat:300008347"
    ]
},
  "bbox": [],
  "geometry": {"coordinates":[-107.533333,25.433333],"type":"Point"}
}