{
  "id": 2329034,
  "type": "Feature",
  "properties": {
    "tgn:hierarchy":[
        "tgn:2329034",
        "tgn:1000001",
        "tgn:7012149",
        "tgn:1002392",
        "tgn:7007157",
        "tgn:7029392"
    ],
    "tgn:id":2329034,
    "tgn:name":"Fiske, Mount",
    "tgn:placetype":[
        "aat:300008798"
    ]
},
  "bbox": [],
  "geometry": {"coordinates":[-118.6667,37.1333],"type":"Point"}
}