{
  "id": 2227337,
  "type": "Feature",
  "properties": {
    "tgn:hierarchy":[
        "tgn:2227337",
        "tgn:1000001",
        "tgn:7012149",
        "tgn:7007255",
        "tgn:7029392"
    ],
    "tgn:id":2227337,
    "tgn:name":"Cave Run Lake",
    "tgn:placetype":[
        "aat:300006191"
    ]
},
  "bbox": [],
  "geometry": {"coordinates":[-83.5333,38.1167],"type":"Point"}
}