{
  "id": 7460862,
  "type": "Feature",
  "properties": {
    "tgn:hierarchy":[
        "tgn:7460862",
        "tgn:7002445",
        "tgn:7018922",
        "tgn:7011781",
        "tgn:1000003",
        "tgn:7008136",
        "tgn:7008591",
        "tgn:7029392"
    ],
    "tgn:id":7460862,
    "tgn:name:en":"Holloway Road Station",
    "tgn:placetype":[
        "aat:300007783"
    ]
},
  "bbox": [],
  "geometry": {"coordinates":[-0.116667,51.55],"type":"Point"}
}