{
  "id": 2680847,
  "type": "Feature",
  "properties": {
    "tgn:hierarchy":[
        "tgn:2680847",
        "tgn:7006450",
        "tgn:1000001",
        "tgn:2124053",
        "tgn:7012149",
        "tgn:7029392"
    ],
    "tgn:id":2680847,
    "tgn:name":"South Lake",
    "tgn:placetype":[
        "aat:300008680"
    ]
},
  "bbox": [],
  "geometry": {"coordinates":[-147.3333,61.9833],"type":"Point"}
}