{
  "id": 7400406,
  "type": "Feature",
  "properties": {
    "tgn:hierarchy":[
        "tgn:7400406",
        "tgn:1000001",
        "tgn:7005599",
        "tgn:7005560",
        "tgn:7029392"
    ],
    "tgn:id":7400406,
    "tgn:name":"Amajahua",
    "tgn:placetype":[
        "aat:300008347"
    ]
},
  "bbox": [],
  "geometry": {"coordinates":[-97.383333,21.541667],"type":"Point"}
}