{
  "id": 2457606,
  "type": "Feature",
  "properties": {
    "tgn:hierarchy":[
        "tgn:2457606",
        "tgn:1000001",
        "tgn:2000591",
        "tgn:7012149",
        "tgn:7007253",
        "tgn:7029392"
    ],
    "tgn:id":2457606,
    "tgn:name":"Little Maquoketa River",
    "tgn:placetype":[
        "aat:300008707"
    ]
},
  "bbox": [],
  "geometry": {"coordinates":[-90.9833,42.4833],"type":"Point"}
}