<<<<<<< HEAD
{
  "id": 7027342,
  "type": "Feature",
  "properties": {
    "tgn:hierarchy":[
        "tgn:7027342",
        "tgn:7002445",
        "tgn:1000003",
        "tgn:7008153",
        "tgn:7008591",
        "tgn:7029392"
    ],
    "tgn:id":7027342,
    "tgn:name:en":"Brenzett",
    "tgn:placetype":[
        "aat:300008347",
        "aat:300008372"
    ]
},
  "bbox": [],
  "geometry": {"coordinates":[0.85,51.0],"type":"Point"}
}
=======
{"geometry":{"type":"Point","coordinates":[0.850000,51.000000]},"type":"Feature","properties":{"hierarchy":["tgn:7027342","tgn:7002445","tgn:1000003","tgn:7008153","tgn:7008591","tgn:7029392"],"placetype":["aat:300008347","aat:300008372"],"name:en":"Brenzett","id":7027342}}
>>>>>>> 03f74aca74312dbeaf24d7e61306dd6a786dc3d0
