{
  "id": 2772001,
  "type": "Feature",
  "properties": {
    "tgn:hierarchy":[
        "tgn:2772001",
        "tgn:1000001",
        "tgn:7012149",
        "tgn:7022542",
        "tgn:7007825",
        "tgn:7029392"
    ],
    "tgn:id":2772001,
    "tgn:name":"Wilkins Spring Branch",
    "tgn:placetype":[
        "aat:300008699"
    ]
},
  "bbox": [],
  "geometry": {"coordinates":[-84.5333,35.4333],"type":"Point"}
}