{
  "id": 2323683,
  "type": "Feature",
  "properties": {
    "tgn:hierarchy":[
        "tgn:2323683",
        "tgn:1000001",
        "tgn:7012149",
        "tgn:7007157",
        "tgn:1002869",
        "tgn:7029392"
    ],
    "tgn:id":2323683,
    "tgn:name":"Fat Buck Ridge",
    "tgn:placetype":[
        "aat:300266640"
    ]
},
  "bbox": [],
  "geometry": {"coordinates":[-122.0833,37.1833],"type":"Point"}
}