{
  "id": 7500865,
  "type": "Feature",
  "properties": {
    "tgn:hierarchy":[
        "tgn:7500865",
        "tgn:7001004",
        "tgn:1000004",
        "tgn:1000141",
        "tgn:7029392"
    ],
    "tgn:id":7500865,
    "tgn:name":"Xinzhuang",
    "tgn:placetype":[
        "aat:300008347"
    ]
},
  "bbox": [],
  "geometry": {"coordinates":[120.300556,22.813056],"type":"Point"}
}