<<<<<<< HEAD
{
  "id": 7488025,
  "type": "Feature",
  "properties": {
    "tgn:hierarchy":[
        "tgn:7488025",
        "tgn:1000004",
        "tgn:7001002",
        "tgn:1000141",
        "tgn:7029392"
    ],
    "tgn:id":7488025,
    "tgn:name":"Xiuqi Qiao",
    "tgn:placetype":[
        "aat:300007836"
    ]
},
  "bbox": [],
  "geometry": {"coordinates":[120.922778,24.783333],"type":"Point"}
}
=======
{"geometry":{"type":"Point","coordinates":[120.922778,24.783333]},"type":"Feature","properties":{"hierarchy":["tgn:7488025","tgn:1000004","tgn:7001002","tgn:1000141","tgn:7029392"],"placetype":["aat:300007836"],"id":7488025,"name:xx":"Xiuqi Qiao"}}
>>>>>>> 03f74aca74312dbeaf24d7e61306dd6a786dc3d0
