{
  "id": 2004648,
  "type": "Feature",
  "properties": {
    "tgn:hierarchy":[
        "tgn:2004648",
        "tgn:7002659",
        "tgn:1000001",
        "tgn:2000016",
        "tgn:7012149",
        "tgn:7029392"
    ],
    "tgn:id":2004648,
    "tgn:name":"Mynot",
    "tgn:placetype":[
        "aat:300008347",
        "aat:300387210"
    ]
},
  "bbox": [],
  "geometry": {"coordinates":[-88.05,34.6333],"type":"Point"}
}