{
  "id": 7526077,
  "type": "Feature",
  "properties": {
    "tgn:hierarchy":[
        "tgn:7526077",
        "tgn:7001242",
        "tgn:7016833",
        "tgn:1001091",
        "tgn:7029392"
    ],
    "tgn:id":7526077,
    "tgn:name":"Dilt\u0101 Mi\u015fr lil Ath\u0101th",
    "tgn:placetype":[
        "aat:300004792"
    ]
},
  "bbox": [],
  "geometry": {"coordinates":[31.317924,30.048018],"type":"Point"}
}