{
  "id": 2475563,
  "type": "Feature",
  "properties": {
    "tgn:hierarchy":[
        "tgn:2475563",
        "tgn:1000001",
        "tgn:7012149",
        "tgn:1002545",
        "tgn:7007157",
        "tgn:7029392"
    ],
    "tgn:id":2475563,
    "tgn:name":"Lucky Box Mine",
    "tgn:placetype":[
        "aat:300000390"
    ]
},
  "bbox": [],
  "geometry": {"coordinates":[-118.25,35.5833],"type":"Point"}
}