{
  "id": 2503185,
  "type": "Feature",
  "properties": {
    "tgn:hierarchy":[
        "tgn:2503185",
        "tgn:1000001",
        "tgn:7012149",
        "tgn:1002920",
        "tgn:7007568",
        "tgn:7029392"
    ],
    "tgn:id":2503185,
    "tgn:name":"McNutt Run",
    "tgn:placetype":[
        "aat:300008699"
    ]
},
  "bbox": [],
  "geometry": {"coordinates":[-77.1333,42.2667],"type":"Point"}
}