{
  "id": 7417859,
  "type": "Feature",
  "properties": {
    "tgn:hierarchy":[
        "tgn:7417859",
        "tgn:7005584",
        "tgn:1000001",
        "tgn:7005560",
        "tgn:7029392"
    ],
    "tgn:id":7417859,
    "tgn:name":"El Aguaje",
    "tgn:placetype":[
        "aat:300008347"
    ]
},
  "bbox": [],
  "geometry": {"coordinates":[-100.544444,20.4325],"type":"Point"}
}