{
  "id": 7308049,
  "type": "Feature",
  "properties": {
    "tgn:hierarchy":[
        "tgn:7308049",
        "tgn:1001699",
        "tgn:1000049",
        "tgn:1000002",
        "tgn:7029392"
    ],
    "tgn:id":7308049,
    "tgn:name":"Melinca, Bah\u00eda",
    "tgn:placetype":[
        "aat:300132316"
    ]
},
  "bbox": [],
  "geometry": {"coordinates":[-73.707222,-43.891944],"type":"Point"}
}