{
  "id": 2218383,
  "type": "Feature",
  "properties": {
    "tgn:hierarchy":[
        "tgn:2218383",
        "tgn:1000001",
        "tgn:7012149",
        "tgn:2001548",
        "tgn:7007709",
        "tgn:7029392"
    ],
    "tgn:id":2218383,
    "tgn:name":"Candero",
    "tgn:placetype":[
        "aat:300008347"
    ]
},
  "bbox": [],
  "geometry": {"coordinates":[-78.7333,35.8667],"type":"Point"}
}