{
  "id": 7549323,
  "type": "Feature",
  "properties": {
    "tgn:hierarchy":[
        "tgn:7549323",
        "tgn:1000004",
        "tgn:7000198",
        "tgn:7016788",
        "tgn:7029392"
    ],
    "tgn:id":7549323,
    "tgn:name:en":"Ch\u0101d\u0101har",
    "tgn:placetype":[
        "aat:300008347"
    ]
},
  "bbox": [],
  "geometry": {"coordinates":[70.911152,25.607309],"type":"Point"}
}