{
  "id": 2285489,
  "type": "Feature",
  "properties": {
    "tgn:hierarchy":[
        "tgn:2285489",
        "tgn:1000001",
        "tgn:7012149",
        "tgn:2001537",
        "tgn:7007709",
        "tgn:7029392"
    ],
    "tgn:id":2285489,
    "tgn:name":"Devils Fork",
    "tgn:placetype":[
        "aat:300008699"
    ]
},
  "bbox": [],
  "geometry": {"coordinates":[-81.7833,35.5667],"type":"Point"}
}