{
  "id": 7548320,
  "type": "Feature",
  "properties": {
    "tgn:hierarchy":[
        "tgn:7548320",
        "tgn:1000004",
        "tgn:7000198",
        "tgn:1001895",
        "tgn:7029392"
    ],
    "tgn:id":7548320,
    "tgn:name:en":"Chikli",
    "tgn:placetype":[
        "aat:300008347"
    ]
},
  "bbox": [],
  "geometry": {"coordinates":[78.25,19.516667],"type":"Point"}
}