<<<<<<< HEAD
{
  "id": 7374381,
  "type": "Feature",
  "properties": {
    "tgn:hierarchy":[
        "tgn:7374381",
        "tgn:1000001",
        "tgn:7005596",
        "tgn:7005560",
        "tgn:7029392"
    ],
    "tgn:id":7374381,
    "tgn:name":"La Constancia",
    "tgn:placetype":[
        "aat:300008347"
    ]
},
  "bbox": [],
  "geometry": {"coordinates":[-92.816667,18.433333],"type":"Point"}
}
=======
{"geometry":{"type":"Point","coordinates":[-92.816667,18.433333]},"type":"Feature","properties":{"hierarchy":["tgn:7374381","tgn:1000001","tgn:7005596","tgn:7005560","tgn:7029392"],"placetype":["aat:300008347"],"id":7374381,"name:xx":"La Constancia"}}
>>>>>>> 03f74aca74312dbeaf24d7e61306dd6a786dc3d0
