{
  "id": 2389084,
  "type": "Feature",
  "properties": {
    "tgn:hierarchy":[
        "tgn:2389084",
        "tgn:1000001",
        "tgn:2001429",
        "tgn:7012149",
        "tgn:7007566",
        "tgn:7029392"
    ],
    "tgn:id":2389084,
    "tgn:name":"Hidden Tank",
    "tgn:placetype":[
        "aat:300006191"
    ]
},
  "bbox": [],
  "geometry": {"coordinates":[-107.9167,34.1333],"type":"Point"}
}