<<<<<<< HEAD
{
  "id": 7369210,
  "type": "Feature",
  "properties": {
    "tgn:hierarchy":[
        "tgn:7369210",
        "tgn:1001835",
        "tgn:1000001",
        "tgn:7005560",
        "tgn:7029392"
    ],
    "tgn:id":7369210,
    "tgn:name":"Guadalupe, Cerro",
    "tgn:placetype":[
        "aat:300008795"
    ]
},
  "bbox": [],
  "geometry": {"coordinates":[-113.716667,29.133333],"type":"Point"}
}
=======
{"geometry":{"type":"Point","coordinates":[-113.716667,29.133333]},"type":"Feature","properties":{"hierarchy":["tgn:7369210","tgn:1001835","tgn:1000001","tgn:7005560","tgn:7029392"],"placetype":["aat:300008795"],"id":7369210,"name:xx":"Guadalupe, Cerro"}}
>>>>>>> 03f74aca74312dbeaf24d7e61306dd6a786dc3d0
