{
  "id": 7462600,
  "type": "Feature",
  "properties": {
    "tgn:hierarchy":[
        "tgn:7462600",
        "tgn:7002444",
        "tgn:7008074",
        "tgn:1000003",
        "tgn:7008591",
        "tgn:7029392"
    ],
    "tgn:id":7462600,
    "tgn:name:en":"Kirkconnell Burn",
    "tgn:placetype":[
        "aat:300008699"
    ]
},
  "bbox": [],
  "geometry": {"coordinates":[-3.916667,55.233333],"type":"Point"}
}