{
  "id": 1004134,
  "type": "Feature",
  "properties": {
    "tgn:hierarchy":[
        "tgn:1004134",
        "tgn:7001242",
        "tgn:7017576",
        "tgn:1000193",
        "tgn:7029392"
    ],
    "tgn:id":1004134,
    "tgn:name":"Booysens",
    "tgn:placetype":[
        "aat:300007748"
    ]
},
  "bbox": [],
  "geometry": {"coordinates":[28.0167,-26.2333],"type":"Point"}
}