{
  "id": 7508199,
  "type": "Feature",
  "properties": {
    "tgn:hierarchy":[
        "tgn:7508199",
        "tgn:1008380",
        "tgn:7520093",
        "tgn:1000226",
        "tgn:1000006",
        "tgn:7029392"
    ],
    "tgn:id":7508199,
    "tgn:name:en":"Papanui Stream",
    "tgn:placetype":[
        "aat:300008699"
    ]
},
  "bbox": [],
  "geometry": {"coordinates":[175.55,-39.666667],"type":"Point"}
}