{
  "id": 2753112,
  "type": "Feature",
  "properties": {
    "tgn:hierarchy":[
        "tgn:2753112",
        "tgn:1000001",
        "tgn:7012149",
        "tgn:1002984",
        "tgn:7007523",
        "tgn:7029392"
    ],
    "tgn:id":2753112,
    "tgn:name":"Water Run",
    "tgn:placetype":[
        "aat:300008699"
    ]
},
  "bbox": [],
  "geometry": {"coordinates":[-91.15,38.6667],"type":"Point"}
}