{
  "id": 1071583,
  "type": "Feature",
  "properties": {
    "tgn:hierarchy":[
        "tgn:1071583",
        "tgn:1000004",
        "tgn:7002086",
        "tgn:1000111",
        "tgn:7029392"
    ],
    "tgn:id":1071583,
    "tgn:name":"Shenchi",
    "tgn:placetype":[
        "aat:300008347"
    ]
},
  "bbox": [],
  "geometry": {"coordinates":[112.1667,39.0833],"type":"Point"}
}