{
  "id": 2672272,
  "type": "Feature",
  "properties": {
    "tgn:hierarchy":[
        "tgn:2672272",
        "tgn:1000001",
        "tgn:1002217",
        "tgn:7012149",
        "tgn:7007710",
        "tgn:7029392"
    ],
    "tgn:id":2672272,
    "tgn:name":"Smithville",
    "tgn:placetype":[
        "aat:300008347"
    ]
},
  "bbox": [],
  "geometry": {"coordinates":[-79.9167,40.9667],"type":"Point"}
}