{
  "id": 7301079,
  "type": "Feature",
  "properties": {
    "tgn:hierarchy":[
        "tgn:7301079",
        "tgn:7010420",
        "tgn:1000003",
        "tgn:7002795",
        "tgn:1000095",
        "tgn:7029392"
    ],
    "tgn:id":7301079,
    "tgn:name":"Montejo de la Sierra",
    "tgn:placetype":[
        "aat:300008347"
    ]
},
  "bbox": [],
  "geometry": {"coordinates":[-3.533333,41.066667],"type":"Point"}
}