{
  "id": 2680090,
  "type": "Feature",
  "properties": {
    "tgn:hierarchy":[
        "tgn:2680090",
        "tgn:7013349",
        "tgn:1000001",
        "tgn:7012149",
        "tgn:7007708",
        "tgn:7029392"
    ],
    "tgn:id":2680090,
    "tgn:name":"South Fork Spring Creek",
    "tgn:placetype":[
        "aat:300008706"
    ]
},
  "bbox": [],
  "geometry": {"coordinates":[-117.2333,44.95],"type":"Point"}
}