{
  "id": 2265221,
  "type": "Feature",
  "properties": {
    "tgn:hierarchy":[
        "tgn:2265221",
        "tgn:1000001",
        "tgn:7012149",
        "tgn:1003039",
        "tgn:7007706",
        "tgn:7029392"
    ],
    "tgn:id":2265221,
    "tgn:name":"Cranberry Run",
    "tgn:placetype":[
        "aat:300008699"
    ]
},
  "bbox": [],
  "geometry": {"coordinates":[-83.15,40.8167],"type":"Point"}
}