{
  "id": 1038596,
  "type": "Feature",
  "properties": {
    "tgn:hierarchy":[
        "tgn:1038596",
        "tgn:1000003",
        "tgn:7003677",
        "tgn:7000084",
        "tgn:7029392"
    ],
    "tgn:id":1038596,
    "tgn:name":"Borchen",
    "tgn:placetype":[
        "aat:300008347"
    ]
},
  "bbox": [],
  "geometry": {"coordinates":[8.7333,51.65],"type":"Point"}
}