{
  "id": 2274073,
  "type": "Feature",
  "properties": {
    "tgn:hierarchy":[
        "tgn:2274073",
        "tgn:1000001",
        "tgn:7012149",
        "tgn:1002658",
        "tgn:7007706",
        "tgn:7029392"
    ],
    "tgn:id":2274073,
    "tgn:name":"Dahlinghaus Ditch",
    "tgn:placetype":[
        "aat:300006075"
    ]
},
  "bbox": [],
  "geometry": {"coordinates":[-84.5667,40.45],"type":"Point"}
}