{
  "id": 7312858,
  "type": "Feature",
  "properties": {
    "tgn:hierarchy":[
        "tgn:7312858",
        "tgn:1001708",
        "tgn:1000049",
        "tgn:1000002",
        "tgn:7029392"
    ],
    "tgn:id":7312858,
    "tgn:name":"La Palma",
    "tgn:placetype":[
        "aat:300008347"
    ]
},
  "bbox": [],
  "geometry": {"coordinates":[-70.95,-33.333333],"type":"Point"}
}