<<<<<<< HEAD
{
  "id": 2761619,
  "type": "Feature",
  "properties": {
    "tgn:hierarchy":[
        "tgn:2761619",
        "tgn:1000001",
        "tgn:2001429",
        "tgn:7012149",
        "tgn:7007566",
        "tgn:7029392"
    ],
    "tgn:id":2761619,
    "tgn:name":"West Pie Town Tank",
    "tgn:placetype":[
        "aat:300006191"
    ]
},
  "bbox": [],
  "geometry": {"coordinates":[-108.0667,34.2833],"type":"Point"}
}
=======
{"geometry":{"type":"Point","coordinates":[-108.066700,34.283300]},"type":"Feature","properties":{"hierarchy":["tgn:2761619","tgn:1000001","tgn:2001429","tgn:7012149","tgn:7007566","tgn:7029392"],"placetype":["aat:300006191"],"id":2761619,"name:xx":"West Pie Town Tank"}}
>>>>>>> 03f74aca74312dbeaf24d7e61306dd6a786dc3d0
