{
  "id": 7225798,
  "type": "Feature",
  "properties": {
    "tgn:hierarchy":[
        "tgn:7225798",
        "tgn:7002735",
        "tgn:7017076",
        "tgn:1000003",
        "tgn:1000074",
        "tgn:7029392"
    ],
    "tgn:id":7225798,
    "tgn:name":"Psil\u00f3 Kotr\u00f3ni",
    "tgn:placetype":[
        "aat:300008795"
    ]
},
  "bbox": [],
  "geometry": {"coordinates":[22.85,36.966667],"type":"Point"}
}