{
  "id": 7418787,
  "type": "Feature",
  "properties": {
    "tgn:hierarchy":[
        "tgn:7418787",
        "tgn:7005579",
        "tgn:1000001",
        "tgn:7005560",
        "tgn:7029392"
    ],
    "tgn:id":7418787,
    "tgn:name":"Los Hornos, Arroyo",
    "tgn:placetype":[
        "aat:300266554",
        "aat:300008699"
    ]
},
  "bbox": [],
  "geometry": {"coordinates":[-102.216667,22.233333],"type":"Point"}
}