{
  "id": 2419011,
  "type": "Feature",
  "properties": {
    "tgn:hierarchy":[
        "tgn:2419011",
        "tgn:1000001",
        "tgn:7012149",
        "tgn:7013961",
        "tgn:7029392"
    ],
    "tgn:id":2419011,
    "tgn:name":"James Ridge",
    "tgn:placetype":[
        "aat:300266640"
    ]
},
  "bbox": [],
  "geometry": {"coordinates":[-80.9167,37.4667],"type":"Point"}
}