{
  "id": 7478669,
  "type": "Feature",
  "properties": {
    "tgn:hierarchy":[
        "tgn:7478669",
        "tgn:1000004",
        "tgn:7489179",
        "tgn:1000141",
        "tgn:7029392"
    ],
    "tgn:id":7478669,
    "tgn:name":"Yuying Guoxiao",
    "tgn:placetype":[
        "aat:300006495"
    ]
},
  "bbox": [],
  "geometry": {"coordinates":[121.833,24.639298],"type":"Point"}
}