{
  "id": 2777666,
  "type": "Feature",
  "properties": {
    "tgn:hierarchy":[
        "tgn:2777666",
        "tgn:1000001",
        "tgn:7016172",
        "tgn:2000121",
        "tgn:7012149",
        "tgn:7029392"
    ],
    "tgn:id":2777666,
    "tgn:name":"Winset Mountain",
    "tgn:placetype":[
        "aat:300008798"
    ]
},
  "bbox": [],
  "geometry": {"coordinates":[-94.2833,35.55],"type":"Point"}
}