{
  "id": 2555705,
  "type": "Feature",
  "properties": {
    "tgn:hierarchy":[
        "tgn:2555705",
        "tgn:1000001",
        "tgn:7012149",
        "tgn:2000476",
        "tgn:7007250",
        "tgn:7029392"
    ],
    "tgn:id":2555705,
    "tgn:name":"Ogre, The",
    "tgn:placetype":[
        "aat:300008798"
    ]
},
  "bbox": [],
  "geometry": {"coordinates":[-116.5167,45.3167],"type":"Point"}
}