{
  "id": 2374198,
  "type": "Feature",
  "properties": {
    "tgn:hierarchy":[
        "tgn:2374198",
        "tgn:1000001",
        "tgn:7012149",
        "tgn:2000927",
        "tgn:7007515",
        "tgn:7029392"
    ],
    "tgn:id":2374198,
    "tgn:name":"Hammond Pond",
    "tgn:placetype":[
        "aat:300008680"
    ]
},
  "bbox": [],
  "geometry": {"coordinates":[-68.9167,44.75],"type":"Point"}
}