{
  "id": 7422661,
  "type": "Feature",
  "properties": {
    "tgn:hierarchy":[
        "tgn:7422661",
        "tgn:1000001",
        "tgn:1001960",
        "tgn:7005560",
        "tgn:7029392"
    ],
    "tgn:id":7422661,
    "tgn:name":"R\u00edo Yaqui, Boca del",
    "tgn:placetype":[
        "aat:300387057"
    ]
},
  "bbox": [],
  "geometry": {"coordinates":[-110.666667,27.616667],"type":"Point"}
}