<<<<<<< HEAD
{
  "id": 7353302,
  "type": "Feature",
  "properties": {
    "tgn:hierarchy":[
        "tgn:7353302",
        "tgn:1000001",
        "tgn:7005599",
        "tgn:7005560",
        "tgn:7029392"
    ],
    "tgn:id":7353302,
    "tgn:name":"Ayahuil, Cerro",
    "tgn:placetype":[
        "aat:300008777"
    ]
},
  "bbox": [],
  "geometry": {"coordinates":[-97.783333,21.45],"type":"Point"}
}
=======
{"geometry":{"type":"Point","coordinates":[-97.783333,21.450000]},"type":"Feature","properties":{"hierarchy":["tgn:7353302","tgn:1000001","tgn:7005599","tgn:7005560","tgn:7029392"],"placetype":["aat:300008777"],"id":7353302,"name:xx":"Ayahuil, Cerro"}}
>>>>>>> 03f74aca74312dbeaf24d7e61306dd6a786dc3d0
