{
  "id": 2220071,
  "type": "Feature",
  "properties": {
    "tgn:hierarchy":[
        "tgn:2220071",
        "tgn:1000001",
        "tgn:2001411",
        "tgn:7012149",
        "tgn:7007526",
        "tgn:7029392"
    ],
    "tgn:id":2220071,
    "tgn:name":"Canyon Creek Pockets",
    "tgn:placetype":[
        "aat:300386845"
    ]
},
  "bbox": [],
  "geometry": {"coordinates":[-115.1667,41.8667],"type":"Point"}
}