{
  "id": 2182555,
  "type": "Feature",
  "properties": {
    "tgn:hierarchy":[
        "tgn:2182555",
        "tgn:1000001",
        "tgn:7012149",
        "tgn:2001451",
        "tgn:7007566",
        "tgn:7029392"
    ],
    "tgn:id":2182555,
    "tgn:name":"Blue Sky",
    "tgn:placetype":[
        "aat:300000390"
    ]
},
  "bbox": [],
  "geometry": {"coordinates":[-106.8333,35.5167],"type":"Point"}
}