{
  "id": 1092210,
  "type": "Feature",
  "properties": {
    "tgn:hierarchy":[
        "tgn:1092210",
        "tgn:7001242",
        "tgn:1001889",
        "tgn:1000182",
        "tgn:7029392"
    ],
    "tgn:id":1092210,
    "tgn:name":"Ojota",
    "tgn:placetype":[
        "aat:300008347"
    ]
},
  "bbox": [],
  "geometry": {"coordinates":[0.5333,6.5833],"type":"Point"}
}