{
  "id": 7021466,
  "type": "Feature",
  "properties": {
    "tgn:hierarchy":[
        "tgn:7021466",
        "tgn:1000001",
        "tgn:7012149",
        "tgn:2002299",
        "tgn:7013961",
        "tgn:7029392"
    ],
    "tgn:id":7021466,
    "tgn:name":"Spruce Fork",
    "tgn:placetype":[
        "aat:300008699"
    ]
},
  "bbox": [],
  "geometry": {"coordinates":[-82.35,37.9333],"type":"Point"}
}