{
  "id": 2021123,
  "type": "Feature",
  "properties": {
    "tgn:hierarchy":[
        "tgn:2021123",
        "tgn:1000001",
        "tgn:2000266",
        "tgn:7012149",
        "tgn:7007240",
        "tgn:7029392"
    ],
    "tgn:id":2021123,
    "tgn:name":"Saint Johns Park",
    "tgn:placetype":[
        "aat:300008347",
        "aat:300387210"
    ]
},
  "bbox": [],
  "geometry": {"coordinates":[-81.4167,29.4167],"type":"Point"}
}