{
  "id": 7122720,
  "type": "Feature",
  "properties": {
    "tgn:hierarchy":[
        "tgn:7122720",
        "tgn:1000003",
        "tgn:7003682",
        "tgn:7000084",
        "tgn:7029392"
    ],
    "tgn:id":7122720,
    "tgn:name":"Niederneisen",
    "tgn:placetype":[
        "aat:300008347"
    ]
},
  "bbox": [],
  "geometry": {"coordinates":[8.05,50.333333],"type":"Point"}
}