{
  "id": 2161583,
  "type": "Feature",
  "properties": {
    "tgn:hierarchy":[
        "tgn:2161583",
        "tgn:1000001",
        "tgn:7012149",
        "tgn:1003041",
        "tgn:7007710",
        "tgn:7029392"
    ],
    "tgn:id":2161583,
    "tgn:name":"Bellas Brook",
    "tgn:placetype":[
        "aat:300008699"
    ]
},
  "bbox": [],
  "geometry": {"coordinates":[-76.2333,41.3833],"type":"Point"}
}