{
  "id": 2495800,
  "type": "Feature",
  "properties": {
    "tgn:hierarchy":[
        "tgn:2495800",
        "tgn:1000001",
        "tgn:7012149",
        "tgn:7007923",
        "tgn:7029392"
    ],
    "tgn:id":2495800,
    "tgn:name":"Mason Creek",
    "tgn:placetype":[
        "aat:300008706"
    ]
},
  "bbox": [],
  "geometry": {"coordinates":[-104.3167,44.1833],"type":"Point"}
}