{
  "id": 1094625,
  "type": "Feature",
  "properties": {
    "tgn:hierarchy":[
        "tgn:1094625",
        "tgn:7001242",
        "tgn:1001703",
        "tgn:1000203",
        "tgn:7029392"
    ],
    "tgn:id":1094625,
    "tgn:name":"Kibara",
    "tgn:placetype":[
        "aat:300008347"
    ]
},
  "bbox": [],
  "geometry": {"coordinates":[33.4833,-2.1333],"type":"Point"}
}