{
  "id": 7435157,
  "type": "Feature",
  "properties": {
    "tgn:hierarchy":[
        "tgn:7435157",
        "tgn:1000001",
        "tgn:7005595",
        "tgn:7005560",
        "tgn:7029392"
    ],
    "tgn:id":7435157,
    "tgn:name":"Vivajaqui",
    "tgn:placetype":[
        "aat:300008347"
    ]
},
  "bbox": [],
  "geometry": {"coordinates":[-108.683333,26.35],"type":"Point"}
}