<<<<<<< HEAD
{
  "id": 2334835,
  "type": "Feature",
  "properties": {
    "tgn:hierarchy":[
        "tgn:2334835",
        "tgn:1000001",
        "tgn:7012149",
        "tgn:1002378",
        "tgn:7007710",
        "tgn:7029392"
    ],
    "tgn:id":2334835,
    "tgn:name":"Fork Run",
    "tgn:placetype":[
        "aat:300008699"
    ]
},
  "bbox": [],
  "geometry": {"coordinates":[-79.2667,41.5667],"type":"Point"}
}
=======
{"geometry":{"type":"Point","coordinates":[-79.266700,41.566700]},"type":"Feature","properties":{"hierarchy":["tgn:2334835","tgn:1000001","tgn:7012149","tgn:1002378","tgn:7007710","tgn:7029392"],"placetype":["aat:300008699"],"id":2334835,"name:xx":"Fork Run"}}
>>>>>>> 03f74aca74312dbeaf24d7e61306dd6a786dc3d0
