{
  "id": 2518122,
  "type": "Feature",
  "properties": {
    "tgn:hierarchy":[
        "tgn:2518122",
        "tgn:1000001",
        "tgn:7012149",
        "tgn:2002002",
        "tgn:7007826",
        "tgn:7029392"
    ],
    "tgn:id":2518122,
    "tgn:name":"Mission Inlet",
    "tgn:placetype":[
        "aat:300006075"
    ]
},
  "bbox": [],
  "geometry": {"coordinates":[-98.35,26.1667],"type":"Point"}
}