{
  "id": 7227383,
  "type": "Feature",
  "properties": {
    "tgn:hierarchy":[
        "tgn:7227383",
        "tgn:7011170",
        "tgn:7002715",
        "tgn:1000003",
        "tgn:1000074",
        "tgn:7029392"
    ],
    "tgn:id":7227383,
    "tgn:name":"Mon\u00ed Ikosifoin\u00edssis",
    "tgn:placetype":[
        "aat:300000641"
    ]
},
  "bbox": [],
  "geometry": {"coordinates":[24.066667,40.966667],"type":"Point"}
}