{
  "id": 2536552,
  "type": "Feature",
  "properties": {
    "tgn:hierarchy":[
        "tgn:2536552",
        "tgn:1000001",
        "tgn:7012149",
        "tgn:2000960",
        "tgn:7007520",
        "tgn:7029392"
    ],
    "tgn:id":2536552,
    "tgn:name":"Near Island",
    "tgn:placetype":[
        "aat:300008791"
    ]
},
  "bbox": [],
  "geometry": {"coordinates":[-89.0833,46.1333],"type":"Point"}
}