<<<<<<< HEAD
{
  "id": 2250060,
  "type": "Feature",
  "properties": {
    "tgn:hierarchy":[
        "tgn:2250060",
        "tgn:1000001",
        "tgn:7012149",
        "tgn:2000183",
        "tgn:7007157",
        "tgn:7029392"
    ],
    "tgn:id":2250060,
    "tgn:name":"Collins Canal",
    "tgn:placetype":[
        "aat:300006075"
    ]
},
  "bbox": [],
  "geometry": {"coordinates":[-118.3,37.3167],"type":"Point"}
}
=======
{"geometry":{"type":"Point","coordinates":[-118.300000,37.316700]},"type":"Feature","properties":{"hierarchy":["tgn:2250060","tgn:1000001","tgn:7012149","tgn:2000183","tgn:7007157","tgn:7029392"],"placetype":["aat:300006075"],"id":2250060,"name:xx":"Collins Canal"}}
>>>>>>> 03f74aca74312dbeaf24d7e61306dd6a786dc3d0
