{
  "id": 1058746,
  "type": "Feature",
  "properties": {
    "tgn:hierarchy":[
        "tgn:1058746",
        "tgn:7006642",
        "tgn:1000003",
        "tgn:7006540",
        "tgn:7029392"
    ],
    "tgn:id":1058746,
    "tgn:name:en":"Puhja",
    "tgn:placetype":[
        "aat:300008347"
    ]
},
  "bbox": [],
  "geometry": {"coordinates":[26.305,58.341],"type":"Point"}
}