{
  "id": 2234856,
  "type": "Feature",
  "properties": {
    "tgn:hierarchy":[
        "tgn:2234856",
        "tgn:1000001",
        "tgn:7012149",
        "tgn:7007526",
        "tgn:7029392"
    ],
    "tgn:id":2234856,
    "tgn:name":"Cherry Creek Range",
    "tgn:placetype":[
        "aat:300386831"
    ]
},
  "bbox": [],
  "geometry": {"coordinates":[-114.8667,40.05],"type":"Point"}
}