{
  "id": 2071883,
  "type": "Feature",
  "properties": {
    "tgn:hierarchy":[
        "tgn:2071883",
        "tgn:1000001",
        "tgn:7012149",
        "tgn:7014287",
        "tgn:7007568",
        "tgn:7029392"
    ],
    "tgn:id":2071883,
    "tgn:name":"Remsen",
    "tgn:placetype":[
        "aat:300008347"
    ]
},
  "bbox": [],
  "geometry": {"coordinates":[-75.1833,43.3167],"type":"Point"}
}