{
  "id": 7146410,
  "type": "Feature",
  "properties": {
    "tgn:hierarchy":[
        "tgn:7146410",
        "tgn:1000003",
        "tgn:7003676",
        "tgn:7000084",
        "tgn:7029392"
    ],
    "tgn:id":7146410,
    "tgn:name":"Kohnsen",
    "tgn:placetype":[
        "aat:300008347"
    ]
},
  "bbox": [],
  "geometry": {"coordinates":[9.833333,51.833333],"type":"Point"}
}