{
  "id": 2544576,
  "type": "Feature",
  "properties": {
    "tgn:hierarchy":[
        "tgn:2544576",
        "tgn:1000001",
        "tgn:2001262",
        "tgn:7012149",
        "tgn:7007524",
        "tgn:7029392"
    ],
    "tgn:id":2544576,
    "tgn:name":"North Canal",
    "tgn:placetype":[
        "aat:300006075"
    ]
},
  "bbox": [],
  "geometry": {"coordinates":[-108.6333,48.4667],"type":"Point"}
}