{
  "id": 2675118,
  "type": "Feature",
  "properties": {
    "tgn:hierarchy":[
        "tgn:2675118",
        "tgn:2000767",
        "tgn:1000001",
        "tgn:7012149",
        "tgn:7007255",
        "tgn:7029392"
    ],
    "tgn:id":2675118,
    "tgn:name":"Sodom Creek",
    "tgn:placetype":[
        "aat:300008706"
    ]
},
  "bbox": [],
  "geometry": {"coordinates":[-89.0167,37.05],"type":"Point"}
}