{
  "id": 2321689,
  "type": "Feature",
  "properties": {
    "tgn:hierarchy":[
        "tgn:2321689",
        "tgn:1000001",
        "tgn:7012149",
        "tgn:2001455",
        "tgn:7007566",
        "tgn:7029392"
    ],
    "tgn:id":2321689,
    "tgn:name":"Fairview Mountain",
    "tgn:placetype":[
        "aat:300008798"
    ]
},
  "bbox": [],
  "geometry": {"coordinates":[-106.5167,33.45],"type":"Point"}
}