<<<<<<< HEAD
{
  "id": 7116221,
  "type": "Feature",
  "properties": {
    "tgn:hierarchy":[
        "tgn:7116221",
        "tgn:1000003",
        "tgn:7003676",
        "tgn:7000084",
        "tgn:7029392"
    ],
    "tgn:id":7116221,
    "tgn:name":"Ohlenbostel",
    "tgn:placetype":[
        "aat:300000206"
    ]
},
  "bbox": [],
  "geometry": {"coordinates":[9.666667,52.533333],"type":"Point"}
}
=======
{"geometry":{"type":"Point","coordinates":[9.666667,52.533333]},"type":"Feature","properties":{"hierarchy":["tgn:7116221","tgn:1000003","tgn:7003676","tgn:7000084","tgn:7029392"],"placetype":["aat:300000206"],"id":7116221,"name:xx":"Ohlenbostel"}}
>>>>>>> 03f74aca74312dbeaf24d7e61306dd6a786dc3d0
