{
  "id": 7459115,
  "type": "Feature",
  "properties": {
    "tgn:hierarchy":[
        "tgn:7459115",
        "tgn:7002445",
        "tgn:7019021",
        "tgn:1000003",
        "tgn:7008591",
        "tgn:7029392"
    ],
    "tgn:id":7459115,
    "tgn:name:en":"Priston",
    "tgn:placetype":[
        "aat:300008347"
    ]
},
  "bbox": [],
  "geometry": {"coordinates":[-2.439167,51.343056],"type":"Point"}
}