{
  "id": 7236894,
  "type": "Feature",
  "properties": {
    "tgn:hierarchy":[
        "tgn:7236894",
        "tgn:7002735",
        "tgn:7017076",
        "tgn:1000003",
        "tgn:1000074",
        "tgn:7029392"
    ],
    "tgn:id":7236894,
    "tgn:name":"Anemodho\u00farion",
    "tgn:placetype":[
        "aat:300008347"
    ]
},
  "bbox": [],
  "geometry": {"coordinates":[22.216667,37.366667],"type":"Point"}
}