{
  "id": 2672409,
  "type": "Feature",
  "properties": {
    "tgn:hierarchy":[
        "tgn:2672409",
        "tgn:1000001",
        "tgn:2000469",
        "tgn:7012149",
        "tgn:7007250",
        "tgn:7029392"
    ],
    "tgn:id":2672409,
    "tgn:name":"Smokey Lake",
    "tgn:placetype":[
        "aat:300008680"
    ]
},
  "bbox": [],
  "geometry": {"coordinates":[-114.7667,46.7333],"type":"Point"}
}