{
  "id": 1136121,
  "type": "Feature",
  "properties": {
    "tgn:hierarchy":[
        "tgn:1136121",
        "tgn:1000003",
        "tgn:7003237",
        "tgn:1000080",
        "tgn:7029392"
    ],
    "tgn:id":1136121,
    "tgn:name":"Villoresi, Canale",
    "tgn:placetype":[
        "aat:300006075"
    ]
},
  "bbox": [],
  "geometry": {"coordinates":[9.3167,45.55],"type":"Point"}
}