<<<<<<< HEAD
{
  "id": 2409270,
  "type": "Feature",
  "properties": {
    "tgn:hierarchy":[
        "tgn:2409270",
        "tgn:1000001",
        "tgn:2001411",
        "tgn:7012149",
        "tgn:7007526",
        "tgn:7029392"
    ],
    "tgn:id":2409270,
    "tgn:name":"Ichabod, Mount",
    "tgn:placetype":[
        "aat:300008798"
    ]
},
  "bbox": [],
  "geometry": {"coordinates":[-115.6,41.5833],"type":"Point"}
}
=======
{"geometry":{"type":"Point","coordinates":[-115.600000,41.583300]},"type":"Feature","properties":{"hierarchy":["tgn:2409270","tgn:1000001","tgn:2001411","tgn:7012149","tgn:7007526","tgn:7029392"],"placetype":["aat:300008798"],"id":2409270,"name:xx":"Ichabod, Mount"}}
>>>>>>> 03f74aca74312dbeaf24d7e61306dd6a786dc3d0
