{
  "id": 7523910,
  "type": "Feature",
  "properties": {
    "tgn:hierarchy":[
        "tgn:7523910",
        "tgn:7001242",
        "tgn:7016833",
        "tgn:1001418",
        "tgn:7029392"
    ],
    "tgn:id":7523910,
    "tgn:name:en":"B\u00eer Bilheig",
    "tgn:placetype":[
        "aat:300006207"
    ]
},
  "bbox": [],
  "geometry": {"coordinates":[27.777218,30.980427],"type":"Point"}
}