{
  "id": 1083510,
  "type": "Feature",
  "properties": {
    "tgn:hierarchy":[
        "tgn:1083510",
        "tgn:7002460",
        "tgn:1000004",
        "tgn:1000133",
        "tgn:7029392"
    ],
    "tgn:id":1083510,
    "tgn:name":"Jah\u0101ng\u012bra",
    "tgn:placetype":[
        "aat:300008347"
    ]
},
  "bbox": [],
  "geometry": {"coordinates":[72.2167,33.9667],"type":"Point"}
}