{
  "id": 2030030,
  "type": "Feature",
  "properties": {
    "tgn:hierarchy":[
        "tgn:2030030",
        "tgn:1000001",
        "tgn:1002281",
        "tgn:7012149",
        "tgn:7007251",
        "tgn:7029392"
    ],
    "tgn:id":2030030,
    "tgn:name":"Saint Rose",
    "tgn:placetype":[
        "aat:300008347"
    ]
},
  "bbox": [],
  "geometry": {"coordinates":[-89.55,38.6833],"type":"Point"}
}