{
  "id": 7584265,
  "type": "Feature",
  "properties": {
    "tgn:hierarchy":[
        "tgn:7584265",
        "tgn:1000004",
        "tgn:7000198",
        "tgn:7016883",
        "tgn:7029392"
    ],
    "tgn:id":7584265,
    "tgn:name:en":"Niz\u0101mpur",
    "tgn:placetype":[
        "aat:300008347"
    ]
},
  "bbox": [],
  "geometry": {"coordinates":[76.50424,30.21454],"type":"Point"}
}