<<<<<<< HEAD
{
  "id": 2762505,
  "type": "Feature",
  "properties": {
    "tgn:hierarchy":[
        "tgn:2762505",
        "tgn:1000001",
        "tgn:7016172",
        "tgn:7012149",
        "tgn:2000168",
        "tgn:7029392"
    ],
    "tgn:id":2762505,
    "tgn:name":"West Weaver Creek",
    "tgn:placetype":[
        "aat:300008706"
    ]
},
  "bbox": [],
  "geometry": {"coordinates":[-93.7333,34.7833],"type":"Point"}
}
=======
{"geometry":{"type":"Point","coordinates":[-93.733300,34.783300]},"type":"Feature","properties":{"hierarchy":["tgn:2762505","tgn:1000001","tgn:7016172","tgn:7012149","tgn:2000168","tgn:7029392"],"placetype":["aat:300008706"],"id":2762505,"name:xx":"West Weaver Creek"}}
>>>>>>> 03f74aca74312dbeaf24d7e61306dd6a786dc3d0
