<<<<<<< HEAD
{
  "id": 2769030,
  "type": "Feature",
  "properties": {
    "tgn:hierarchy":[
        "tgn:2769030",
        "tgn:1000001",
        "tgn:2001424",
        "tgn:7012149",
        "tgn:7007564",
        "tgn:7029392"
    ],
    "tgn:id":2769030,
    "tgn:name":"Whittemore Brook",
    "tgn:placetype":[
        "aat:300008699"
    ]
},
  "bbox": [],
  "geometry": {"coordinates":[-71.7333,43.7],"type":"Point"}
}
=======
{"geometry":{"type":"Point","coordinates":[-71.733300,43.700000]},"type":"Feature","properties":{"hierarchy":["tgn:2769030","tgn:1000001","tgn:2001424","tgn:7012149","tgn:7007564","tgn:7029392"],"placetype":["aat:300008699"],"id":2769030,"name:xx":"Whittemore Brook"}}
>>>>>>> 03f74aca74312dbeaf24d7e61306dd6a786dc3d0
