{
  "id": 2035892,
  "type": "Feature",
  "properties": {
    "tgn:hierarchy":[
        "tgn:2035892",
        "tgn:1000001",
        "tgn:7012149",
        "tgn:2000630",
        "tgn:7007253",
        "tgn:7029392"
    ],
    "tgn:id":2035892,
    "tgn:name":"West Liberty",
    "tgn:placetype":[
        "aat:300008347"
    ]
},
  "bbox": [],
  "geometry": {"coordinates":[-91.25,41.5667],"type":"Point"}
}