{
  "id": 7476915,
  "type": "Feature",
  "properties": {
    "tgn:hierarchy":[
        "tgn:7476915",
        "tgn:7488858",
        "tgn:1000004",
        "tgn:1000141",
        "tgn:7029392"
    ],
    "tgn:id":7476915,
    "tgn:name":"Tudigongkeng",
    "tgn:placetype":[
        "aat:300008699"
    ]
},
  "bbox": [],
  "geometry": {"coordinates":[120.769525,23.944672],"type":"Point"}
}