{
  "id": 2622047,
  "type": "Feature",
  "properties": {
    "tgn:hierarchy":[
        "tgn:2622047",
        "tgn:1000001",
        "tgn:7012149",
        "tgn:2000623",
        "tgn:7007253",
        "tgn:7029392"
    ],
    "tgn:id":2622047,
    "tgn:name":"Roberts Creek",
    "tgn:placetype":[
        "aat:300006191"
    ]
},
  "bbox": [],
  "geometry": {"coordinates":[-93.0333,41.4167],"type":"Point"}
}