{
  "id": 2148082,
  "type": "Feature",
  "properties": {
    "tgn:hierarchy":[
        "tgn:2148082",
        "tgn:1000001",
        "tgn:7012149",
        "tgn:7007826",
        "tgn:7029392"
    ],
    "tgn:id":2148082,
    "tgn:name":"Barker Reservoir",
    "tgn:placetype":[
        "aat:300006191"
    ]
},
  "bbox": [],
  "geometry": {"coordinates":[-95.6333,29.7667],"type":"Point"}
}