{
  "id": 7499555,
  "type": "Feature",
  "properties": {
    "tgn:hierarchy":[
        "tgn:7499555",
        "tgn:1000004",
        "tgn:1000959",
        "tgn:1000141",
        "tgn:7029392"
    ],
    "tgn:id":7499555,
    "tgn:name":"Huangxi Gongyuan",
    "tgn:placetype":[
        "aat:300008187"
    ]
},
  "bbox": [],
  "geometry": {"coordinates":[121.527898,25.114169],"type":"Point"}
}