{
  "id": 2154345,
  "type": "Feature",
  "properties": {
    "tgn:hierarchy":[
        "tgn:2154345",
        "tgn:1000001",
        "tgn:7012149",
        "tgn:2001756",
        "tgn:7007712",
        "tgn:7029392"
    ],
    "tgn:id":2154345,
    "tgn:name":"Bear Creek",
    "tgn:placetype":[
        "aat:300008706"
    ]
},
  "bbox": [],
  "geometry": {"coordinates":[-81.1833,33.8333],"type":"Point"}
}