{
  "id": 2582052,
  "type": "Feature",
  "properties": {
    "tgn:hierarchy":[
        "tgn:2582052",
        "tgn:1000001",
        "tgn:1002461",
        "tgn:7012149",
        "tgn:7007159",
        "tgn:7029392"
    ],
    "tgn:id":2582052,
    "tgn:name":"Pine Cone",
    "tgn:placetype":[
        "aat:300008798"
    ]
},
  "bbox": [],
  "geometry": {"coordinates":[-72.8667,41.9333],"type":"Point"}
}