<<<<<<< HEAD
{
  "id": 7473089,
  "type": "Feature",
  "properties": {
    "tgn:hierarchy":[
        "tgn:7473089",
        "tgn:1000004",
        "tgn:7490934",
        "tgn:1000141",
        "tgn:7029392"
    ],
    "tgn:id":7473089,
    "tgn:name":"Tiexianqiao",
    "tgn:placetype":[
        "aat:300008347"
    ]
},
  "bbox": [],
  "geometry": {"coordinates":[120.276111,23.265278],"type":"Point"}
}
=======
{"geometry":{"type":"Point","coordinates":[120.276111,23.265278]},"type":"Feature","properties":{"hierarchy":["tgn:7473089","tgn:1000004","tgn:7490934","tgn:1000141","tgn:7029392"],"placetype":["aat:300008347"],"id":7473089,"name:xx":"Tiexianqiao"}}
>>>>>>> 03f74aca74312dbeaf24d7e61306dd6a786dc3d0
