{
  "id": 7507404,
  "type": "Feature",
  "properties": {
    "tgn:hierarchy":[
        "tgn:7507404",
        "tgn:1008380",
        "tgn:7520093",
        "tgn:1000226",
        "tgn:1000006",
        "tgn:7029392"
    ],
    "tgn:id":7507404,
    "tgn:name:en":"Pukehua",
    "tgn:placetype":[
        "aat:300008795"
    ]
},
  "bbox": [],
  "geometry": {"coordinates":[175.533333,-39.783333],"type":"Point"}
}