<<<<<<< HEAD
{
  "id": 7176906,
  "type": "Feature",
  "properties": {
    "tgn:hierarchy":[
        "tgn:7176906",
        "tgn:1000003",
        "tgn:7003676",
        "tgn:7000084",
        "tgn:7029392"
    ],
    "tgn:id":7176906,
    "tgn:name":"Halle",
    "tgn:placetype":[
        "aat:300387173"
    ]
},
  "bbox": [],
  "geometry": {"coordinates":[6.916667,52.45],"type":"Point"}
}
=======
{"geometry":{"type":"Point","coordinates":[6.916667,52.450000]},"type":"Feature","properties":{"hierarchy":["tgn:7176906","tgn:1000003","tgn:7003676","tgn:7000084","tgn:7029392"],"placetype":["aat:300387173"],"id":7176906,"name:xx":"Halle"}}
>>>>>>> 03f74aca74312dbeaf24d7e61306dd6a786dc3d0
