{
  "id": 1084110,
  "type": "Feature",
  "properties": {
    "tgn:hierarchy":[
        "tgn:1084110",
        "tgn:1000004",
        "tgn:1001565",
        "tgn:1000135",
        "tgn:7029392"
    ],
    "tgn:id":1084110,
    "tgn:name":"Camiling",
    "tgn:placetype":[
        "aat:300008347"
    ]
},
  "bbox": [],
  "geometry": {"coordinates":[120.3333,15.6333],"type":"Point"}
}