{
  "id": 7177433,
  "type": "Feature",
  "properties": {
    "tgn:hierarchy":[
        "tgn:7177433",
        "tgn:7003669",
        "tgn:1000003",
        "tgn:7000084",
        "tgn:7029392"
    ],
    "tgn:id":7177433,
    "tgn:name":"Hagenau",
    "tgn:placetype":[
        "aat:300008347"
    ]
},
  "bbox": [],
  "geometry": {"coordinates":[10.316667,49.316667],"type":"Point"}
}