{
  "id": 7473589,
  "type": "Feature",
  "properties": {
    "tgn:hierarchy":[
        "tgn:7473589",
        "tgn:7001004",
        "tgn:1000004",
        "tgn:1000141",
        "tgn:7029392"
    ],
    "tgn:id":7473589,
    "tgn:name":"Dongshibu",
    "tgn:placetype":[
        "aat:300008347"
    ]
},
  "bbox": [],
  "geometry": {"coordinates":[120.472778,22.930278],"type":"Point"}
}