<<<<<<< HEAD
{
  "id": 2251032,
  "type": "Feature",
  "properties": {
    "tgn:hierarchy":[
        "tgn:2251032",
        "tgn:1000001",
        "tgn:7012149",
        "tgn:7007158",
        "tgn:2000247",
        "tgn:7029392"
    ],
    "tgn:id":2251032,
    "tgn:name":"Columbus Mine",
    "tgn:placetype":[
        "aat:300000390"
    ]
},
  "bbox": [],
  "geometry": {"coordinates":[-107.5667,37.9167],"type":"Point"}
}
=======
{"geometry":{"type":"Point","coordinates":[-107.566700,37.916700]},"type":"Feature","properties":{"hierarchy":["tgn:2251032","tgn:1000001","tgn:7012149","tgn:7007158","tgn:2000247","tgn:7029392"],"placetype":["aat:300000390"],"id":2251032,"name:xx":"Columbus Mine"}}
>>>>>>> 03f74aca74312dbeaf24d7e61306dd6a786dc3d0
