{
  "id": 2186741,
  "type": "Feature",
  "properties": {
    "tgn:hierarchy":[
        "tgn:2186741",
        "tgn:1000001",
        "tgn:7012149",
        "tgn:2001720",
        "tgn:7007708",
        "tgn:7029392"
    ],
    "tgn:id":2186741,
    "tgn:name":"Bonifer",
    "tgn:placetype":[
        "aat:300008347"
    ]
},
  "bbox": [],
  "geometry": {"coordinates":[-118.35,45.6667],"type":"Point"}
}