{
  "id": 2556032,
  "type": "Feature",
  "properties": {
    "tgn:hierarchy":[
        "tgn:2556032",
        "tgn:1000001",
        "tgn:7012149",
        "tgn:2002066",
        "tgn:7007826",
        "tgn:7029392"
    ],
    "tgn:id":2556032,
    "tgn:name":"Oil Well Lake",
    "tgn:placetype":[
        "aat:300008680"
    ]
},
  "bbox": [],
  "geometry": {"coordinates":[-93.6167,31.25],"type":"Point"}
}