{
  "id": 7335401,
  "type": "Feature",
  "properties": {
    "tgn:hierarchy":[
        "tgn:7335401",
        "tgn:7002810",
        "tgn:7001158",
        "tgn:1000003",
        "tgn:1000095",
        "tgn:7029392"
    ],
    "tgn:id":7335401,
    "tgn:name":"Fresnillo de las Due\u00f1as",
    "tgn:placetype":[
        "aat:300008347"
    ]
},
  "bbox": [],
  "geometry": {"coordinates":[-3.65,41.65],"type":"Point"}
}