{
  "id": 2411751,
  "type": "Feature",
  "properties": {
    "tgn:hierarchy":[
        "tgn:2411751",
        "tgn:1000001",
        "tgn:7012149",
        "tgn:1002897",
        "tgn:7007920",
        "tgn:7029392"
    ],
    "tgn:id":2411751,
    "tgn:name":"Indian Mary Creek",
    "tgn:placetype":[
        "aat:300008706"
    ]
},
  "bbox": [],
  "geometry": {"coordinates":[-122.0667,45.6167],"type":"Point"}
}