{
  "id": 2274319,
  "type": "Feature",
  "properties": {
    "tgn:hierarchy":[
        "tgn:2274319",
        "tgn:7019618",
        "tgn:1000001",
        "tgn:7012149",
        "tgn:7007564",
        "tgn:7029392"
    ],
    "tgn:id":2274319,
    "tgn:name":"Dakin Hill",
    "tgn:placetype":[
        "aat:300008798"
    ]
},
  "bbox": [],
  "geometry": {"coordinates":[-72.1167,43.0333],"type":"Point"}
}