{
  "id": 7078453,
  "type": "Feature",
  "properties": {
    "tgn:hierarchy":[
        "tgn:7078453",
        "tgn:7000096",
        "tgn:1000003",
        "tgn:7000084",
        "tgn:7029392"
    ],
    "tgn:id":7078453,
    "tgn:name":"Wuschewier",
    "tgn:placetype":[
        "aat:300008347"
    ]
},
  "bbox": [],
  "geometry": {"coordinates":[14.266667,52.65],"type":"Point"}
}