{
  "id": 7368984,
  "type": "Feature",
  "properties": {
    "tgn:hierarchy":[
        "tgn:7368984",
        "tgn:7005581",
        "tgn:1000001",
        "tgn:7005560",
        "tgn:7029392"
    ],
    "tgn:id":7368984,
    "tgn:name":"Horcasitas",
    "tgn:placetype":[
        "aat:300007783"
    ]
},
  "bbox": [],
  "geometry": {"coordinates":[-105.833333,28.366667],"type":"Point"}
}