{
  "id": 1023893,
  "type": "Feature",
  "properties": {
    "tgn:hierarchy":[
        "tgn:1023893",
        "tgn:1000640",
        "tgn:1000050",
        "tgn:1000002",
        "tgn:7029392"
    ],
    "tgn:id":1023893,
    "tgn:name":"Neiva",
    "tgn:placetype":[
        "aat:300387277",
        "aat:300008347",
        "aat:300008389",
        "aat:300387220"
    ]
},
  "bbox": [],
  "geometry": {"coordinates":[-75.25,2.9667],"type":"Point"}
}