{
  "id": 7156571,
  "type": "Feature",
  "properties": {
    "tgn:hierarchy":[
        "tgn:7156571",
        "tgn:7003669",
        "tgn:1000003",
        "tgn:7000084",
        "tgn:7029392"
    ],
    "tgn:id":7156571,
    "tgn:name":"Kleeberg",
    "tgn:placetype":[
        "aat:300008777"
    ]
},
  "bbox": [],
  "geometry": {"coordinates":[10.883333,48.883333],"type":"Point"}
}