{
  "id": 1077922,
  "type": "Feature",
  "properties": {
    "tgn:hierarchy":[
        "tgn:1077922",
        "tgn:1007711",
        "tgn:1009846",
        "tgn:1000004",
        "tgn:1001409",
        "tgn:1000116",
        "tgn:7029392"
    ],
    "tgn:id":1077922,
    "tgn:name":"Kudene",
    "tgn:placetype":[
        "aat:300008347"
    ]
},
  "bbox": [],
  "geometry": {"coordinates":[134.65,-6.2333],"type":"Point"}
}