{
  "id": 7495101,
  "type": "Feature",
  "properties": {
    "tgn:hierarchy":[
        "tgn:7495101",
        "tgn:1000004",
        "tgn:7001013",
        "tgn:1000141",
        "tgn:7029392"
    ],
    "tgn:id":7495101,
    "tgn:name":"Guangcheng Qiao",
    "tgn:placetype":[
        "aat:300007836"
    ]
},
  "bbox": [],
  "geometry": {"coordinates":[121.282282,24.956518],"type":"Point"}
}