{
  "id": 2295181,
  "type": "Feature",
  "properties": {
    "tgn:hierarchy":[
        "tgn:2295181",
        "tgn:1000001",
        "tgn:7012149",
        "tgn:1002430",
        "tgn:7007251",
        "tgn:7029392"
    ],
    "tgn:id":2295181,
    "tgn:name":"Dresden Island",
    "tgn:placetype":[
        "aat:300008791"
    ]
},
  "bbox": [],
  "geometry": {"coordinates":[-88.2833,41.3833],"type":"Point"}
}