<<<<<<< HEAD
{
  "id": 7020917,
  "type": "Feature",
  "properties": {
    "tgn:hierarchy":[
        "tgn:7020917",
        "tgn:1000001",
        "tgn:7012149",
        "tgn:7007250",
        "tgn:7029392"
    ],
    "tgn:id":7020917,
    "tgn:name":"Coeur d'Alene",
    "tgn:placetype":[
        "aat:300008707"
    ]
},
  "bbox": [],
  "geometry": {"coordinates":[-116.25,47.55],"type":"Point"}
}
=======
{"geometry":{"type":"Point","coordinates":[-116.250000,47.550000]},"type":"Feature","properties":{"hierarchy":["tgn:7020917","tgn:1000001","tgn:7012149","tgn:7007250","tgn:7029392"],"placetype":["aat:300008707"],"id":7020917,"name:xx":"Coeur d'Alene"}}
>>>>>>> 03f74aca74312dbeaf24d7e61306dd6a786dc3d0
