{
  "id": 2165824,
  "type": "Feature",
  "properties": {
    "tgn:hierarchy":[
        "tgn:2165824",
        "tgn:1000001",
        "tgn:1002275",
        "tgn:7012149",
        "tgn:7007920",
        "tgn:7029392"
    ],
    "tgn:id":2165824,
    "tgn:name":"Biddle Lake",
    "tgn:placetype":[
        "aat:300006191"
    ]
},
  "bbox": [],
  "geometry": {"coordinates":[-122.5333,45.5833],"type":"Point"}
}