{
  "id": 2784233,
  "type": "Feature",
  "properties": {
    "tgn:hierarchy":[
        "tgn:2784233",
        "tgn:1000001",
        "tgn:7012149",
        "tgn:7007256",
        "tgn:7029392"
    ],
    "tgn:id":2784233,
    "tgn:name":"Yankee Canal",
    "tgn:placetype":[
        "aat:300006075"
    ]
},
  "bbox": [],
  "geometry": {"coordinates":[-90.2167,29.3833],"type":"Point"}
}