{
  "id": 2361215,
  "type": "Feature",
  "properties": {
    "tgn:hierarchy":[
        "tgn:2361215",
        "tgn:1000001",
        "tgn:7012149",
        "tgn:1002788",
        "tgn:7007706",
        "tgn:7029392"
    ],
    "tgn:id":2361215,
    "tgn:name":"Gravel Hill",
    "tgn:placetype":[
        "aat:300008798"
    ]
},
  "bbox": [],
  "geometry": {"coordinates":[-82.8667,38.9667],"type":"Point"}
}