{
  "id": 7144334,
  "type": "Feature",
  "properties": {
    "tgn:hierarchy":[
        "tgn:7144334",
        "tgn:1000003",
        "tgn:7003682",
        "tgn:7000084",
        "tgn:7029392"
    ],
    "tgn:id":7144334,
    "tgn:name":"K\u00f6nigsbach an der Weinstra\u00dfe",
    "tgn:placetype":[
        "aat:300008347"
    ]
},
  "bbox": [],
  "geometry": {"coordinates":[8.158889,49.386944],"type":"Point"}
}