{
  "id": 7227870,
  "type": "Feature",
  "properties": {
    "tgn:hierarchy":[
        "tgn:7227870",
        "tgn:7002743",
        "tgn:7017076",
        "tgn:1000003",
        "tgn:1000074",
        "tgn:7029392"
    ],
    "tgn:id":7227870,
    "tgn:name":"Lissar\u00e9a",
    "tgn:placetype":[
        "aat:300008347"
    ]
},
  "bbox": [],
  "geometry": {"coordinates":[21.933333,37.65],"type":"Point"}
}