{
  "id": 2428678,
  "type": "Feature",
  "properties": {
    "tgn:hierarchy":[
        "tgn:2428678",
        "tgn:1000001",
        "tgn:7012149",
        "tgn:2002162",
        "tgn:7007919",
        "tgn:7029392"
    ],
    "tgn:id":2428678,
    "tgn:name":"Julian Knob",
    "tgn:placetype":[
        "aat:300008798"
    ]
},
  "bbox": [],
  "geometry": {"coordinates":[-80.45,37.3167],"type":"Point"}
}