{
  "id": 7026011,
  "type": "Feature",
  "properties": {
    "tgn:hierarchy":[
        "tgn:7026011",
        "tgn:7002445",
        "tgn:1000003",
        "tgn:7011961",
        "tgn:7008591",
        "tgn:7029392"
    ],
    "tgn:id":7026011,
    "tgn:name:en":"Woodsford",
    "tgn:placetype":[
        "aat:300008347",
        "aat:300008372"
    ]
},
  "bbox": [],
  "geometry": {"coordinates":[-2.333333,50.716667],"type":"Point"}
}