{
  "id": 2425946,
  "type": "Feature",
  "properties": {
    "tgn:hierarchy":[
        "tgn:2425946",
        "tgn:1000001",
        "tgn:7012149",
        "tgn:2002300",
        "tgn:7013961",
        "tgn:7029392"
    ],
    "tgn:id":2425946,
    "tgn:name":"Jonathan Knob",
    "tgn:placetype":[
        "aat:300008798"
    ]
},
  "bbox": [],
  "geometry": {"coordinates":[-80.3667,38.4833],"type":"Point"}
}