<<<<<<< HEAD
{
  "id": 7026963,
  "type": "Feature",
  "properties": {
    "tgn:hierarchy":[
        "tgn:7026963",
        "tgn:7002445",
        "tgn:1000003",
        "tgn:7011430",
        "tgn:7008591",
        "tgn:7029392"
    ],
    "tgn:id":7026963,
    "tgn:name:en":"Bonchurch",
    "tgn:placetype":[
        "aat:300008347",
        "aat:300008372"
    ]
},
  "bbox": [],
  "geometry": {"coordinates":[-1.183333,50.583333],"type":"Point"}
}
=======
{"geometry":{"type":"Point","coordinates":[-1.183333,50.583333]},"type":"Feature","properties":{"hierarchy":["tgn:7026963","tgn:7002445","tgn:1000003","tgn:7011430","tgn:7008591","tgn:7029392"],"placetype":["aat:300008347","aat:300008372"],"name:en":"Bonchurch","id":7026963}}
>>>>>>> 03f74aca74312dbeaf24d7e61306dd6a786dc3d0
