{
  "id": 7026963,
  "type": "Feature",
  "properties": {
    "tgn:hierarchy":[
        "tgn:7026963",
        "tgn:7002445",
        "tgn:1000003",
        "tgn:7011430",
        "tgn:7008591",
        "tgn:7029392"
    ],
    "tgn:id":7026963,
    "tgn:name:en":"Bonchurch",
    "tgn:placetype":[
        "aat:300008347",
        "aat:300008372"
    ]
},
  "bbox": [],
  "geometry": {"coordinates":[-1.183333,50.583333],"type":"Point"}
}