<<<<<<< HEAD
{
  "id": 2762732,
  "type": "Feature",
  "properties": {
    "tgn:hierarchy":[
        "tgn:2762732",
        "tgn:1000001",
        "tgn:7012149",
        "tgn:1002676",
        "tgn:7007240",
        "tgn:7029392"
    ],
    "tgn:id":2762732,
    "tgn:name":"Western Dry Rocks",
    "tgn:placetype":[
        "aat:300132348"
    ]
},
  "bbox": [],
  "geometry": {"coordinates":[-81.9167,24.4333],"type":"Point"}
}
=======
{"geometry":{"type":"Point","coordinates":[-81.916700,24.433300]},"type":"Feature","properties":{"hierarchy":["tgn:2762732","tgn:1000001","tgn:7012149","tgn:1002676","tgn:7007240","tgn:7029392"],"placetype":["aat:300132348"],"id":2762732,"name:xx":"Western Dry Rocks"}}
>>>>>>> 03f74aca74312dbeaf24d7e61306dd6a786dc3d0
