{
  "id": 7535825,
  "type": "Feature",
  "properties": {
    "tgn:hierarchy":[
        "tgn:7535825",
        "tgn:7001242",
        "tgn:7016833",
        "tgn:1001418",
        "tgn:7029392"
    ],
    "tgn:id":7535825,
    "tgn:name:en":"Kharsha, Qaret el",
    "tgn:placetype":[
        "aat:300008777"
    ]
},
  "bbox": [],
  "geometry": {"coordinates":[26.970045,30.78729],"type":"Point"}
}