{
  "id": 2239483,
  "type": "Feature",
  "properties": {
    "tgn:hierarchy":[
        "tgn:2239483",
        "tgn:1000001",
        "tgn:7012149",
        "tgn:1002603",
        "tgn:7007520",
        "tgn:7029392"
    ],
    "tgn:id":2239483,
    "tgn:name":"Church Lake",
    "tgn:placetype":[
        "aat:300008680"
    ]
},
  "bbox": [],
  "geometry": {"coordinates":[-83.85,42.6333],"type":"Point"}
}