{
  "id": 1075956,
  "type": "Feature",
  "properties": {
    "tgn:hierarchy":[
        "tgn:1075956",
        "tgn:1000004",
        "tgn:7000198",
        "tgn:1001894",
        "tgn:7029392"
    ],
    "tgn:id":1075956,
    "tgn:name:en":"Kukshi",
    "tgn:placetype":[
        "aat:300008347"
    ]
},
  "bbox": [],
  "geometry": {"coordinates":[74.758142,22.208009],"type":"Point"}
}