<<<<<<< HEAD
{
  "id": 7480704,
  "type": "Feature",
  "properties": {
    "tgn:hierarchy":[
        "tgn:7480704",
        "tgn:1000004",
        "tgn:7490934",
        "tgn:1000141",
        "tgn:7029392"
    ],
    "tgn:id":7480704,
    "tgn:name":"Diqihao Qiao",
    "tgn:placetype":[
        "aat:300007836"
    ]
},
  "bbox": [],
  "geometry": {"coordinates":[120.271718,23.206174],"type":"Point"}
}
=======
{"geometry":{"type":"Point","coordinates":[120.271718,23.206174]},"type":"Feature","properties":{"hierarchy":["tgn:7480704","tgn:1000004","tgn:7490934","tgn:1000141","tgn:7029392"],"placetype":["aat:300007836"],"id":7480704,"name:xx":"Diqihao Qiao"}}
>>>>>>> 03f74aca74312dbeaf24d7e61306dd6a786dc3d0
