<<<<<<< HEAD
{
  "id": 2337226,
  "type": "Feature",
  "properties": {
    "tgn:hierarchy":[
        "tgn:2337226",
        "tgn:1000001",
        "tgn:7012149",
        "tgn:7013855",
        "tgn:7007251",
        "tgn:7029392"
    ],
    "tgn:id":2337226,
    "tgn:name":"Fourth Lake",
    "tgn:placetype":[
        "aat:300008680"
    ]
},
  "bbox": [],
  "geometry": {"coordinates":[-88.0167,42.3833],"type":"Point"}
}
=======
{"geometry":{"type":"Point","coordinates":[-88.016700,42.383300]},"type":"Feature","properties":{"hierarchy":["tgn:2337226","tgn:1000001","tgn:7012149","tgn:7013855","tgn:7007251","tgn:7029392"],"placetype":["aat:300008680"],"id":2337226,"name:xx":"Fourth Lake"}}
>>>>>>> 03f74aca74312dbeaf24d7e61306dd6a786dc3d0
