{
  "id": 7184420,
  "type": "Feature",
  "properties": {
    "tgn:hierarchy":[
        "tgn:7184420",
        "tgn:7003692",
        "tgn:1000003",
        "tgn:7000084",
        "tgn:7029392"
    ],
    "tgn:id":7184420,
    "tgn:name":"Grausenlock",
    "tgn:placetype":[
        "aat:300000206"
    ]
},
  "bbox": [],
  "geometry": {"coordinates":[8.316667,48.35],"type":"Point"}
}