{
  "id": 1115761,
  "type": "Feature",
  "properties": {
    "tgn:hierarchy":[
        "tgn:1115761",
        "tgn:1001641",
        "tgn:1000003",
        "tgn:7003121",
        "tgn:1000080",
        "tgn:7029392"
    ],
    "tgn:id":1115761,
    "tgn:name":"C\u00e0gliari, Stagno di",
    "tgn:placetype":[
        "aat:300008680",
        "aat:300008679"
    ]
},
  "bbox": [],
  "geometry": {"coordinates":[9.048,39.234],"type":"Point"}
}