{
  "id": 2617713,
  "type": "Feature",
  "properties": {
    "tgn:hierarchy":[
        "tgn:2617713",
        "tgn:1000001",
        "tgn:1002260",
        "tgn:7012149",
        "tgn:7007920",
        "tgn:7029392"
    ],
    "tgn:id":2617713,
    "tgn:name":"Riddle Creek",
    "tgn:placetype":[
        "aat:300008706"
    ]
},
  "bbox": [],
  "geometry": {"coordinates":[-120.7167,48.2167],"type":"Point"}
}