<<<<<<< HEAD
{
  "id": 2333046,
  "type": "Feature",
  "properties": {
    "tgn:hierarchy":[
        "tgn:2333046",
        "tgn:1000001",
        "tgn:7012149",
        "tgn:2001708",
        "tgn:7007708",
        "tgn:7029392"
    ],
    "tgn:id":2333046,
    "tgn:name":"Fly Creek",
    "tgn:placetype":[
        "aat:300008706"
    ]
},
  "bbox": [],
  "geometry": {"coordinates":[-118.3333,44.6167],"type":"Point"}
}
=======
{"geometry":{"type":"Point","coordinates":[-118.333300,44.616700]},"type":"Feature","properties":{"hierarchy":["tgn:2333046","tgn:1000001","tgn:7012149","tgn:2001708","tgn:7007708","tgn:7029392"],"placetype":["aat:300008706"],"id":2333046,"name:xx":"Fly Creek"}}
>>>>>>> 03f74aca74312dbeaf24d7e61306dd6a786dc3d0
