{
  "id": 2307619,
  "type": "Feature",
  "properties": {
    "tgn:hierarchy":[
        "tgn:2307619",
        "tgn:1000001",
        "tgn:7012149",
        "tgn:7007524",
        "tgn:7029392"
    ],
    "tgn:id":2307619,
    "tgn:name":"East Fork Sunday Creek",
    "tgn:placetype":[
        "aat:300008706"
    ]
},
  "bbox": [],
  "geometry": {"coordinates":[-114.8333,48.5167],"type":"Point"}
}