{
  "id": 2671898,
  "type": "Feature",
  "properties": {
    "tgn:hierarchy":[
        "tgn:2671898",
        "tgn:1000001",
        "tgn:2002368",
        "tgn:7012149",
        "tgn:7007923",
        "tgn:7029392"
    ],
    "tgn:id":2671898,
    "tgn:name":"Smith Reservoir",
    "tgn:placetype":[
        "aat:300006191"
    ]
},
  "bbox": [],
  "geometry": {"coordinates":[-106.3333,41.8667],"type":"Point"}
}