{
  "id": 7285186,
  "type": "Feature",
  "properties": {
    "tgn:hierarchy":[
        "tgn:7285186",
        "tgn:7016598",
        "tgn:1000049",
        "tgn:1000002",
        "tgn:7029392"
    ],
    "tgn:id":7285186,
    "tgn:name":"Piedra, Punta",
    "tgn:placetype":[
        "aat:300386846"
    ]
},
  "bbox": [],
  "geometry": {"coordinates":[-70.55,-24.666667],"type":"Point"}
}