{
  "id": 7507200,
  "type": "Feature",
  "properties": {
    "tgn:hierarchy":[
        "tgn:7507200",
        "tgn:1008380",
        "tgn:1000226",
        "tgn:7018426",
        "tgn:1000006",
        "tgn:7029392"
    ],
    "tgn:id":7507200,
    "tgn:name:en":"Puniu River",
    "tgn:placetype":[
        "aat:300008699"
    ]
},
  "bbox": [],
  "geometry": {"coordinates":[175.216667,-38.016667],"type":"Point"}
}