{
  "id": 2324082,
  "type": "Feature",
  "properties": {
    "tgn:hierarchy":[
        "tgn:2324082",
        "tgn:1000001",
        "tgn:7012149",
        "tgn:1002800",
        "tgn:7007710",
        "tgn:7029392"
    ],
    "tgn:id":2324082,
    "tgn:name":"Fay Hollow",
    "tgn:placetype":[
        "aat:300008761"
    ]
},
  "bbox": [],
  "geometry": {"coordinates":[-77.6667,41.8833],"type":"Point"}
}