{
  "id": 7570909,
  "type": "Feature",
  "properties": {
    "tgn:hierarchy":[
        "tgn:7570909",
        "tgn:1000004",
        "tgn:7000198",
        "tgn:7031783",
        "tgn:7029392"
    ],
    "tgn:id":7570909,
    "tgn:name:en":"Hariharpur",
    "tgn:placetype":[
        "aat:300008347"
    ]
},
  "bbox": [],
  "geometry": {"coordinates":[86.917072,24.423295],"type":"Point"}
}