{
  "id": 1069206,
  "type": "Feature",
  "properties": {
    "tgn:hierarchy":[
        "tgn:1069206",
        "tgn:1000004",
        "tgn:7005232",
        "tgn:1000111",
        "tgn:7029392"
    ],
    "tgn:id":1069206,
    "tgn:name":"Jiaoling",
    "tgn:placetype":[
        "aat:300008347"
    ]
},
  "bbox": [],
  "geometry": {"coordinates":[116.1167,24.7167],"type":"Point"}
}