{
  "id": 7500451,
  "type": "Feature",
  "properties": {
    "tgn:hierarchy":[
        "tgn:7500451",
        "tgn:7001004",
        "tgn:1000004",
        "tgn:1000141",
        "tgn:7029392"
    ],
    "tgn:id":7500451,
    "tgn:name":"Qishan Qiao",
    "tgn:placetype":[
        "aat:300007836"
    ]
},
  "bbox": [],
  "geometry": {"coordinates":[120.486111,22.882222],"type":"Point"}
}