{
  "id": 7395620,
  "type": "Feature",
  "properties": {
    "tgn:hierarchy":[
        "tgn:7395620",
        "tgn:1000001",
        "tgn:7005597",
        "tgn:7005560",
        "tgn:7029392"
    ],
    "tgn:id":7395620,
    "tgn:name":"San Antonio",
    "tgn:placetype":[
        "aat:300008347"
    ]
},
  "bbox": [],
  "geometry": {"coordinates":[-99.816667,23.016667],"type":"Point"}
}