{
  "id": 7264645,
  "type": "Feature",
  "properties": {
    "tgn:hierarchy":[
        "tgn:7264645",
        "tgn:1000003",
        "tgn:7003624",
        "tgn:7016845",
        "tgn:7029392"
    ],
    "tgn:id":7264645,
    "tgn:name:nl":"Kreeke",
    "tgn:placetype":[
        "aat:300132350"
    ]
},
  "bbox": [],
  "geometry": {"coordinates":[4.25,51.483333],"type":"Point"}
}