{
  "id": 2293442,
  "type": "Feature",
  "properties": {
    "tgn:hierarchy":[
        "tgn:2293442",
        "tgn:7002659",
        "tgn:1000001",
        "tgn:7012149",
        "tgn:2000035",
        "tgn:7029392"
    ],
    "tgn:id":2293442,
    "tgn:name":"Double Natural Bridge Cave",
    "tgn:placetype":[
        "aat:300008746"
    ]
},
  "bbox": [],
  "geometry": {"coordinates":[-85.95,34.8167],"type":"Point"}
}