<<<<<<< HEAD
{
  "id": 7474814,
  "type": "Feature",
  "properties": {
    "tgn:hierarchy":[
        "tgn:7474814",
        "tgn:1000004",
        "tgn:7467799",
        "tgn:1000141",
        "tgn:7029392"
    ],
    "tgn:id":7474814,
    "tgn:name":"Xigang Qiao",
    "tgn:placetype":[
        "aat:300007836"
    ]
},
  "bbox": [],
  "geometry": {"coordinates":[120.293206,23.871289],"type":"Point"}
}
=======
{"geometry":{"type":"Point","coordinates":[120.293206,23.871289]},"type":"Feature","properties":{"hierarchy":["tgn:7474814","tgn:1000004","tgn:7467799","tgn:1000141","tgn:7029392"],"placetype":["aat:300007836"],"id":7474814,"name:xx":"Xigang Qiao"}}
>>>>>>> 03f74aca74312dbeaf24d7e61306dd6a786dc3d0
