{
  "id": 2719921,
  "type": "Feature",
  "properties": {
    "tgn:hierarchy":[
        "tgn:2719921",
        "tgn:2001467",
        "tgn:1000001",
        "tgn:7012149",
        "tgn:7007709",
        "tgn:7029392"
    ],
    "tgn:id":2719921,
    "tgn:name":"Three Top Creek",
    "tgn:placetype":[
        "aat:300008706"
    ]
},
  "bbox": [],
  "geometry": {"coordinates":[-81.5667,36.35],"type":"Point"}
}