{
  "id": 2562454,
  "type": "Feature",
  "properties": {
    "tgn:hierarchy":[
        "tgn:2562454",
        "tgn:1000001",
        "tgn:7006451",
        "tgn:2000095",
        "tgn:7012149",
        "tgn:7029392"
    ],
    "tgn:id":2562454,
    "tgn:name":"Ouail Spring",
    "tgn:placetype":[
        "aat:300008697"
    ]
},
  "bbox": [],
  "geometry": {"coordinates":[-109.2667,33.15],"type":"Point"}
}