{
  "id": 7248006,
  "type": "Feature",
  "properties": {
    "tgn:hierarchy":[
        "tgn:7248006",
        "tgn:7003457",
        "tgn:1000003",
        "tgn:1000063",
        "tgn:7018236",
        "tgn:7029392"
    ],
    "tgn:id":7248006,
    "tgn:name":"Beirendries",
    "tgn:placetype":[
        "aat:300008347"
    ]
},
  "bbox": [],
  "geometry": {"coordinates":[3.816667,51.033333],"type":"Point"}
}