{
  "id": 1012451,
  "type": "Feature",
  "properties": {
    "tgn:hierarchy":[
        "tgn:1012451",
        "tgn:7004788",
        "tgn:7593622",
        "tgn:1000001",
        "tgn:7004787",
        "tgn:7029392"
    ],
    "tgn:id":1012451,
    "tgn:name":"Sandy Point",
    "tgn:placetype":[
        "aat:300386846"
    ]
},
  "bbox": [],
  "geometry": {"coordinates":[-60.8333,11.15],"type":"Point"}
}