{
  "id": 7278464,
  "type": "Feature",
  "properties": {
    "tgn:hierarchy":[
        "tgn:7278464",
        "tgn:1001623",
        "tgn:1000049",
        "tgn:1000002",
        "tgn:7029392"
    ],
    "tgn:id":7278464,
    "tgn:name":"Contrabandistas, Portezuelo de los",
    "tgn:placetype":[
        "aat:300259572"
    ]
},
  "bbox": [],
  "geometry": {"coordinates":[-71.783333,-44.416667],"type":"Point"}
}