{
  "id": 7585906,
  "type": "Feature",
  "properties": {
    "tgn:hierarchy":[
        "tgn:7585906",
        "tgn:1000004",
        "tgn:7000198",
        "tgn:7000799",
        "tgn:7029392"
    ],
    "tgn:id":7585906,
    "tgn:name:en":"Arah\u0101ma",
    "tgn:placetype":[
        "aat:300008347"
    ]
},
  "bbox": [],
  "geometry": {"coordinates":[74.816931,34.299362],"type":"Point"}
}