{
  "id": 2062454,
  "type": "Feature",
  "properties": {
    "tgn:hierarchy":[
        "tgn:2062454",
        "tgn:2001317",
        "tgn:1000001",
        "tgn:7012149",
        "tgn:7007525",
        "tgn:7029392"
    ],
    "tgn:id":2062454,
    "tgn:name":"Oakdale",
    "tgn:placetype":[
        "aat:300008347"
    ]
},
  "bbox": [],
  "geometry": {"coordinates":[-97.9667,42.0667],"type":"Point"}
}