{
  "id": 1036620,
  "type": "Feature",
  "properties": {
    "tgn:hierarchy":[
        "tgn:1036620",
        "tgn:7000096",
        "tgn:1000003",
        "tgn:7000084",
        "tgn:7029392"
    ],
    "tgn:id":1036620,
    "tgn:name":"Drebkau",
    "tgn:placetype":[
        "aat:300008347"
    ]
},
  "bbox": [],
  "geometry": {"coordinates":[14.216667,51.65],"type":"Point"}
}