{
  "id": 7559048,
  "type": "Feature",
  "properties": {
    "tgn:hierarchy":[
        "tgn:7559048",
        "tgn:1000004",
        "tgn:7000198",
        "tgn:1001578",
        "tgn:7029392"
    ],
    "tgn:id":7559048,
    "tgn:name:en":"Rabir\u0101ip\u0101ra",
    "tgn:placetype":[
        "aat:300008347"
    ]
},
  "bbox": [],
  "geometry": {"coordinates":[92.047368,23.695925],"type":"Point"}
}