{
  "id": 2443643,
  "type": "Feature",
  "properties": {
    "tgn:hierarchy":[
        "tgn:2443643",
        "tgn:1000001",
        "tgn:7012149",
        "tgn:2000908",
        "tgn:7007256",
        "tgn:7029392"
    ],
    "tgn:id":2443643,
    "tgn:name":"La Graisse, Lake",
    "tgn:placetype":[
        "aat:300008680"
    ]
},
  "bbox": [],
  "geometry": {"coordinates":[-90.5833,29.2167],"type":"Point"}
}