{
  "id": 2139315,
  "type": "Feature",
  "properties": {
    "tgn:hierarchy":[
        "tgn:2139315",
        "tgn:1000001",
        "tgn:7012149",
        "tgn:7007158",
        "tgn:2000244",
        "tgn:7029392"
    ],
    "tgn:id":2139315,
    "tgn:name":"Aspen Creek",
    "tgn:placetype":[
        "aat:300008706"
    ]
},
  "bbox": [],
  "geometry": {"coordinates":[-106.55,37.5333],"type":"Point"}
}