{
  "id": 7570405,
  "type": "Feature",
  "properties": {
    "tgn:hierarchy":[
        "tgn:7570405",
        "tgn:1000004",
        "tgn:7000198",
        "tgn:7031786",
        "tgn:7029392"
    ],
    "tgn:id":7570405,
    "tgn:name:en":"Sainj",
    "tgn:placetype":[
        "aat:300008347"
    ]
},
  "bbox": [],
  "geometry": {"coordinates":[78.622741,29.878714],"type":"Point"}
}