<<<<<<< HEAD
{
  "id": 2257797,
  "type": "Feature",
  "properties": {
    "tgn:hierarchy":[
        "tgn:2257797",
        "tgn:1000001",
        "tgn:2001419",
        "tgn:7012149",
        "tgn:7007526",
        "tgn:7029392"
    ],
    "tgn:id":2257797,
    "tgn:name":"Corral Spring",
    "tgn:placetype":[
        "aat:300008697"
    ]
},
  "bbox": [],
  "geometry": {"coordinates":[-118.6833,40.6333],"type":"Point"}
}
=======
{"geometry":{"type":"Point","coordinates":[-118.683300,40.633300]},"type":"Feature","properties":{"hierarchy":["tgn:2257797","tgn:1000001","tgn:2001419","tgn:7012149","tgn:7007526","tgn:7029392"],"placetype":["aat:300008697"],"id":2257797,"name:xx":"Corral Spring"}}
>>>>>>> 03f74aca74312dbeaf24d7e61306dd6a786dc3d0
