{
  "id": 2257797,
  "type": "Feature",
  "properties": {
    "tgn:hierarchy":[
        "tgn:2257797",
        "tgn:1000001",
        "tgn:2001419",
        "tgn:7012149",
        "tgn:7007526",
        "tgn:7029392"
    ],
    "tgn:id":2257797,
    "tgn:name":"Corral Spring",
    "tgn:placetype":[
        "aat:300008697"
    ]
},
  "bbox": [],
  "geometry": {"coordinates":[-118.6833,40.6333],"type":"Point"}
}