{
  "id": 2519726,
  "type": "Feature",
  "properties": {
    "tgn:hierarchy":[
        "tgn:2519726",
        "tgn:7013272",
        "tgn:1000001",
        "tgn:7012149",
        "tgn:7007710",
        "tgn:7029392"
    ],
    "tgn:id":2519726,
    "tgn:name":"Mohawk Valley",
    "tgn:placetype":[
        "aat:300008761"
    ]
},
  "bbox": [],
  "geometry": {"coordinates":[-80.1833,40.3667],"type":"Point"}
}