{
  "id": 2727919,
  "type": "Feature",
  "properties": {
    "tgn:hierarchy":[
        "tgn:2727919",
        "tgn:1000001",
        "tgn:7012149",
        "tgn:2001722",
        "tgn:7007708",
        "tgn:7029392"
    ],
    "tgn:id":2727919,
    "tgn:name":"Transvaal Mines",
    "tgn:placetype":[
        "aat:300000390"
    ]
},
  "bbox": [],
  "geometry": {"coordinates":[-117.15,45.25],"type":"Point"}
}