<<<<<<< HEAD
{
  "id": 2153609,
  "type": "Feature",
  "properties": {
    "tgn:hierarchy":[
        "tgn:2153609",
        "tgn:1000001",
        "tgn:7012149",
        "tgn:1002632",
        "tgn:7007251",
        "tgn:7029392"
    ],
    "tgn:id":2153609,
    "tgn:name":"Bear Branch",
    "tgn:placetype":[
        "aat:300008699"
    ]
},
  "bbox": [],
  "geometry": {"coordinates":[-88.8,38.6167],"type":"Point"}
}
=======
{"geometry":{"type":"Point","coordinates":[-88.800000,38.616700]},"type":"Feature","properties":{"hierarchy":["tgn:2153609","tgn:1000001","tgn:7012149","tgn:1002632","tgn:7007251","tgn:7029392"],"placetype":["aat:300008699"],"id":2153609,"name:xx":"Bear Branch"}}
>>>>>>> 03f74aca74312dbeaf24d7e61306dd6a786dc3d0
