{
  "id": 7076940,
  "type": "Feature",
  "properties": {
    "tgn:hierarchy":[
        "tgn:7076940",
        "tgn:7000096",
        "tgn:1000003",
        "tgn:7000084",
        "tgn:7029392"
    ],
    "tgn:id":7076940,
    "tgn:name":"Landkreis Oberhavel",
    "tgn:placetype":[
        "aat:300387198"
    ]
},
  "bbox": [],
  "geometry": {"coordinates":[13.232778,52.951667],"type":"Point"}
}