{
  "id": 7289150,
  "type": "Feature",
  "properties": {
    "tgn:hierarchy":[
        "tgn:7289150",
        "tgn:1001695",
        "tgn:1000049",
        "tgn:1000002",
        "tgn:7029392"
    ],
    "tgn:id":7289150,
    "tgn:name":"La Goyana",
    "tgn:placetype":[
        "aat:300008795"
    ]
},
  "bbox": [],
  "geometry": {"coordinates":[-70.933333,-34.75],"type":"Point"}
}