{
  "id": 7371439,
  "type": "Feature",
  "properties": {
    "tgn:hierarchy":[
        "tgn:7371439",
        "tgn:1000001",
        "tgn:1001893",
        "tgn:7005560",
        "tgn:7029392"
    ],
    "tgn:id":7371439,
    "tgn:name":"La Culebra, Cerro",
    "tgn:placetype":[
        "aat:300008795"
    ]
},
  "bbox": [],
  "geometry": {"coordinates":[-102.75,21.716667],"type":"Point"}
}