{
  "id": 7069291,
  "type": "Feature",
  "properties": {
    "tgn:hierarchy":[
        "tgn:7069291",
        "tgn:7003669",
        "tgn:1000003",
        "tgn:7000084",
        "tgn:7029392"
    ],
    "tgn:id":7069291,
    "tgn:name":"Tiefenschlag",
    "tgn:placetype":[
        "aat:300008863"
    ]
},
  "bbox": [],
  "geometry": {"coordinates":[10.75,49.216667],"type":"Point"}
}