{
  "id": 7332128,
  "type": "Feature",
  "properties": {
    "tgn:hierarchy":[
        "tgn:7332128",
        "tgn:7002849",
        "tgn:1000003",
        "tgn:7009604",
        "tgn:1000095",
        "tgn:7029392"
    ],
    "tgn:id":7332128,
    "tgn:name":"Iturrib\u00e1lzaga",
    "tgn:placetype":[
        "aat:300008347"
    ]
},
  "bbox": [],
  "geometry": {"coordinates":[-2.826196,43.342079],"type":"Point"}
}