{
  "id": 2284403,
  "type": "Feature",
  "properties": {
    "tgn:hierarchy":[
        "tgn:2284403",
        "tgn:1000001",
        "tgn:7012149",
        "tgn:2001279",
        "tgn:7007524",
        "tgn:7029392"
    ],
    "tgn:id":2284403,
    "tgn:name":"Derby/Elienore Mine",
    "tgn:placetype":[
        "aat:300000390"
    ]
},
  "bbox": [],
  "geometry": {"coordinates":[-113.2667,46.3167],"type":"Point"}
}