{
  "id": 2719656,
  "type": "Feature",
  "properties": {
    "tgn:hierarchy":[
        "tgn:2719656",
        "tgn:1000001",
        "tgn:7012149",
        "tgn:1002904",
        "tgn:7007710",
        "tgn:7029392"
    ],
    "tgn:id":2719656,
    "tgn:name":"Three Lick Run",
    "tgn:placetype":[
        "aat:300008699"
    ]
},
  "bbox": [],
  "geometry": {"coordinates":[-78.8333,39.95],"type":"Point"}
}