{
  "id": 7004583,
  "type": "Feature",
  "properties": {
    "tgn:hierarchy":[
        "tgn:7004583",
        "tgn:7003005",
        "tgn:7003014",
        "tgn:1000003",
        "tgn:1000080",
        "tgn:7029392"
    ],
    "tgn:id":7004583,
    "tgn:name":"Vietri sul Mare",
    "tgn:placetype":[
        "aat:300008347"
    ]
},
  "bbox": [],
  "geometry": {"coordinates":[14.733333,40.666667],"type":"Point"}
}