{
  "id": 2049675,
  "type": "Feature",
  "properties": {
    "tgn:hierarchy":[
        "tgn:2049675",
        "tgn:1000001",
        "tgn:1002724",
        "tgn:7012149",
        "tgn:7007517",
        "tgn:7029392"
    ],
    "tgn:id":2049675,
    "tgn:name":"Dover",
    "tgn:placetype":[
        "aat:300008347"
    ]
},
  "bbox": [],
  "geometry": {"coordinates":[-71.2833,42.2333],"type":"Point"}
}