{
  "id": 7405412,
  "type": "Feature",
  "properties": {
    "tgn:hierarchy":[
        "tgn:7405412",
        "tgn:1000001",
        "tgn:7005592",
        "tgn:7005560",
        "tgn:7029392"
    ],
    "tgn:id":7405412,
    "tgn:name":"Tlacotepec",
    "tgn:placetype":[
        "aat:300008347"
    ]
},
  "bbox": [],
  "geometry": {"coordinates":[-98.291667,18.413889],"type":"Point"}
}