{
  "id": 7405886,
  "type": "Feature",
  "properties": {
    "tgn:hierarchy":[
        "tgn:7405886",
        "tgn:7016644",
        "tgn:1000001",
        "tgn:7005560",
        "tgn:7029392"
    ],
    "tgn:id":7405886,
    "tgn:name":"El Pochote,Cerro",
    "tgn:placetype":[
        "aat:300008795"
    ]
},
  "bbox": [],
  "geometry": {"coordinates":[-103.845833,19.295833],"type":"Point"}
}