{
  "id": 7509700,
  "type": "Feature",
  "properties": {
    "tgn:hierarchy":[
        "tgn:7509700",
        "tgn:1009227",
        "tgn:1000226",
        "tgn:7016822",
        "tgn:1000006",
        "tgn:7029392"
    ],
    "tgn:id":7509700,
    "tgn:name:en":"Sunnyside",
    "tgn:placetype":[
        "aat:300000206"
    ]
},
  "bbox": [],
  "geometry": {"coordinates":[167.616667,-45.816667],"type":"Point"}
}