{
  "id": 7580487,
  "type": "Feature",
  "properties": {
    "tgn:hierarchy":[
        "tgn:7580487",
        "tgn:1000004",
        "tgn:7000198",
        "tgn:1001882",
        "tgn:7029392"
    ],
    "tgn:id":7580487,
    "tgn:name:en":"Thogad\u016bru",
    "tgn:placetype":[
        "aat:300008347"
    ]
},
  "bbox": [],
  "geometry": {"coordinates":[76.791111,12.088889],"type":"Point"}
}