{
  "id": 7320191,
  "type": "Feature",
  "properties": {
    "tgn:hierarchy":[
        "tgn:7320191",
        "tgn:7016598",
        "tgn:1000049",
        "tgn:1000002",
        "tgn:7029392"
    ],
    "tgn:id":7320191,
    "tgn:name":"Abtao, Roca",
    "tgn:placetype":[
        "aat:300011692"
    ]
},
  "bbox": [],
  "geometry": {"coordinates":[-70.516667,-23.016667],"type":"Point"}
}