{
  "id": 2523191,
  "type": "Feature",
  "properties": {
    "tgn:hierarchy":[
        "tgn:2523191",
        "tgn:1000001",
        "tgn:7012149",
        "tgn:7029392"
    ],
    "tgn:id":2523191,
    "tgn:name":"Moores Fork",
    "tgn:placetype":[
        "aat:300008699"
    ]
},
  "bbox": [],
  "geometry": {"coordinates":[-80.75,36.5167],"type":"Point"}
}