{
  "id": 2083953,
  "type": "Feature",
  "properties": {
    "tgn:hierarchy":[
        "tgn:2083953",
        "tgn:1000001",
        "tgn:7012149",
        "tgn:2001683",
        "tgn:7007707",
        "tgn:7029392"
    ],
    "tgn:id":2083953,
    "tgn:name":"Sams Point",
    "tgn:placetype":[
        "aat:300008347"
    ]
},
  "bbox": [],
  "geometry": {"coordinates":[-95.6833,35.1833],"type":"Point"}
}