<<<<<<< HEAD
{
  "id": 2402342,
  "type": "Feature",
  "properties": {
    "tgn:hierarchy":[
        "tgn:2402342",
        "tgn:1000001",
        "tgn:7012149",
        "tgn:2001709",
        "tgn:7007708",
        "tgn:7029392"
    ],
    "tgn:id":2402342,
    "tgn:name":"Horton Creek",
    "tgn:placetype":[
        "aat:300008706"
    ]
},
  "bbox": [],
  "geometry": {"coordinates":[-118.5833,42.7833],"type":"Point"}
}
=======
{"geometry":{"type":"Point","coordinates":[-118.583300,42.783300]},"type":"Feature","properties":{"hierarchy":["tgn:2402342","tgn:1000001","tgn:7012149","tgn:2001709","tgn:7007708","tgn:7029392"],"placetype":["aat:300008706"],"id":2402342,"name:xx":"Horton Creek"}}
>>>>>>> 03f74aca74312dbeaf24d7e61306dd6a786dc3d0
