{
  "id": 2402342,
  "type": "Feature",
  "properties": {
    "tgn:hierarchy":[
        "tgn:2402342",
        "tgn:1000001",
        "tgn:7012149",
        "tgn:2001709",
        "tgn:7007708",
        "tgn:7029392"
    ],
    "tgn:id":2402342,
    "tgn:name":"Horton Creek",
    "tgn:placetype":[
        "aat:300008706"
    ]
},
  "bbox": [],
  "geometry": {"coordinates":[-118.5833,42.7833],"type":"Point"}
}