{
  "id": 7307693,
  "type": "Feature",
  "properties": {
    "tgn:hierarchy":[
        "tgn:7307693",
        "tgn:7002805",
        "tgn:7002758",
        "tgn:1000003",
        "tgn:1000095",
        "tgn:7029392"
    ],
    "tgn:id":7307693,
    "tgn:name":"Los Donatos",
    "tgn:placetype":[
        "aat:300008347"
    ]
},
  "bbox": [],
  "geometry": {"coordinates":[-2.533333,37.35],"type":"Point"}
}