{
  "id": 4009864,
  "type": "Feature",
  "properties": {
    "tgn:hierarchy":[
        "tgn:4009864",
        "tgn:7594378",
        "tgn:1000003",
        "tgn:1000069",
        "tgn:7029392"
    ],
    "tgn:id":4009864,
    "tgn:name":"Saltvik",
    "tgn:placetype":[
        "aat:300008347"
    ]
},
  "bbox": [],
  "geometry": {"coordinates":[20.0833,60.2667],"type":"Point"}
}