{
  "id": 7151725,
  "type": "Feature",
  "properties": {
    "tgn:hierarchy":[
        "tgn:7151725",
        "tgn:7003669",
        "tgn:1000003",
        "tgn:7000084",
        "tgn:7029392"
    ],
    "tgn:id":7151725,
    "tgn:name":"Jedling",
    "tgn:placetype":[
        "aat:300008347"
    ]
},
  "bbox": [],
  "geometry": {"coordinates":[11.883333,47.816667],"type":"Point"}
}