{
  "id": 2763223,
  "type": "Feature",
  "properties": {
    "tgn:hierarchy":[
        "tgn:2763223",
        "tgn:2001837",
        "tgn:1000001",
        "tgn:7012149",
        "tgn:7007825",
        "tgn:7029392"
    ],
    "tgn:id":2763223,
    "tgn:name":"Westwood Estates",
    "tgn:placetype":[
        "aat:300008347"
    ]
},
  "bbox": [],
  "geometry": {"coordinates":[-84.1333,36.1167],"type":"Point"}
}