{
  "id": 7205593,
  "type": "Feature",
  "properties": {
    "tgn:hierarchy":[
        "tgn:7205593",
        "tgn:7003692",
        "tgn:1000003",
        "tgn:7000084",
        "tgn:7029392"
    ],
    "tgn:id":7205593,
    "tgn:name":"B\u00fchl",
    "tgn:placetype":[
        "aat:300008347"
    ]
},
  "bbox": [],
  "geometry": {"coordinates":[9.933333,48.216667],"type":"Point"}
}