{
  "id": 7199621,
  "type": "Feature",
  "properties": {
    "tgn:hierarchy":[
        "tgn:7199621",
        "tgn:1000003",
        "tgn:7003688",
        "tgn:7000084",
        "tgn:7029392"
    ],
    "tgn:id":7199621,
    "tgn:name":"Dreilanden Koog",
    "tgn:placetype":[
        "aat:300006163"
    ]
},
  "bbox": [],
  "geometry": {"coordinates":[8.733333,54.316667],"type":"Point"}
}