{
  "id": 2757098,
  "type": "Feature",
  "properties": {
    "tgn:hierarchy":[
        "tgn:2757098",
        "tgn:1000001",
        "tgn:7012149",
        "tgn:1002396",
        "tgn:7007252",
        "tgn:7029392"
    ],
    "tgn:id":2757098,
    "tgn:name":"Werner Ditch",
    "tgn:placetype":[
        "aat:300006075"
    ]
},
  "bbox": [],
  "geometry": {"coordinates":[-86.25,40.9833],"type":"Point"}
}