<<<<<<< HEAD
{
  "id": 7364171,
  "type": "Feature",
  "properties": {
    "tgn:hierarchy":[
        "tgn:7364171",
        "tgn:1000001",
        "tgn:7005595",
        "tgn:7005560",
        "tgn:7029392"
    ],
    "tgn:id":7364171,
    "tgn:name":"El Guayabo",
    "tgn:placetype":[
        "aat:300008347"
    ]
},
  "bbox": [],
  "geometry": {"coordinates":[-107.4,25.0],"type":"Point"}
}
=======
{"geometry":{"type":"Point","coordinates":[-107.400000,25.000000]},"type":"Feature","properties":{"hierarchy":["tgn:7364171","tgn:1000001","tgn:7005595","tgn:7005560","tgn:7029392"],"placetype":["aat:300008347"],"id":7364171,"name:xx":"El Guayabo"}}
>>>>>>> 03f74aca74312dbeaf24d7e61306dd6a786dc3d0
