{
  "id": 2337019,
  "type": "Feature",
  "properties": {
    "tgn:hierarchy":[
        "tgn:2337019",
        "tgn:1000001",
        "tgn:7012149",
        "tgn:2000386",
        "tgn:7007248",
        "tgn:7029392"
    ],
    "tgn:id":2337019,
    "tgn:name":"Fourmile Island",
    "tgn:placetype":[
        "aat:300008791"
    ]
},
  "bbox": [],
  "geometry": {"coordinates":[-81.2833,31.5333],"type":"Point"}
}