{
  "id": 2267840,
  "type": "Feature",
  "properties": {
    "tgn:hierarchy":[
        "tgn:2267840",
        "tgn:1000001",
        "tgn:7012149",
        "tgn:7029392"
    ],
    "tgn:id":2267840,
    "tgn:name":"Crooked Branch",
    "tgn:placetype":[
        "aat:300008699"
    ]
},
  "bbox": [],
  "geometry": {"coordinates":[-90.8833,30.9833],"type":"Point"}
}