{
  "id": 7411479,
  "type": "Feature",
  "properties": {
    "tgn:hierarchy":[
        "tgn:7411479",
        "tgn:7005580",
        "tgn:1000001",
        "tgn:7005560",
        "tgn:7029392"
    ],
    "tgn:id":7411479,
    "tgn:name":"Campo Bolontina",
    "tgn:placetype":[
        "aat:300008347"
    ]
},
  "bbox": [],
  "geometry": {"coordinates":[-92.083333,17.116667],"type":"Point"}
}