{
  "id": 1122562,
  "type": "Feature",
  "properties": {
    "tgn:hierarchy":[
        "tgn:1122562",
        "tgn:7006260",
        "tgn:7002454",
        "tgn:1000047",
        "tgn:1000002",
        "tgn:7029392"
    ],
    "tgn:id":1122562,
    "tgn:name":"Casca, Rio da",
    "tgn:placetype":[
        "aat:300008707"
    ]
},
  "bbox": [],
  "geometry": {"coordinates":[-55.8667,-14.8667],"type":"Point"}
}