{
  "id": 2096170,
  "type": "Feature",
  "properties": {
    "tgn:hierarchy":[
        "tgn:2096170",
        "tgn:1000001",
        "tgn:7012149",
        "tgn:2001755",
        "tgn:7007712",
        "tgn:7029392"
    ],
    "tgn:id":2096170,
    "tgn:name":"Lucknow",
    "tgn:placetype":[
        "aat:300008347",
        "aat:300387210"
    ]
},
  "bbox": [],
  "geometry": {"coordinates":[-80.3333,34.2833],"type":"Point"}
}