{
  "id": 2176051,
  "type": "Feature",
  "properties": {
    "tgn:hierarchy":[
        "tgn:2176051",
        "tgn:1000001",
        "tgn:2001418",
        "tgn:7012149",
        "tgn:7007526",
        "tgn:7029392"
    ],
    "tgn:id":2176051,
    "tgn:name":"Black Glass Canyon",
    "tgn:placetype":[
        "aat:300008761"
    ]
},
  "bbox": [],
  "geometry": {"coordinates":[-116.4333,36.9333],"type":"Point"}
}