{
  "id": 7317882,
  "type": "Feature",
  "properties": {
    "tgn:hierarchy":[
        "tgn:7317882",
        "tgn:7016598",
        "tgn:1000049",
        "tgn:1000002",
        "tgn:7029392"
    ],
    "tgn:id":7317882,
    "tgn:name":"Corral Quemado, Quebrada de",
    "tgn:placetype":[
        "aat:300266554",
        "aat:300008699"
    ]
},
  "bbox": [],
  "geometry": {"coordinates":[-68.666667,-21.616667],"type":"Point"}
}