{
  "id": 2641452,
  "type": "Feature",
  "properties": {
    "tgn:hierarchy":[
        "tgn:2641452",
        "tgn:1000001",
        "tgn:7012149",
        "tgn:2001993",
        "tgn:7007826",
        "tgn:7029392"
    ],
    "tgn:id":2641452,
    "tgn:name":"Sand Creek",
    "tgn:placetype":[
        "aat:300008706"
    ]
},
  "bbox": [],
  "geometry": {"coordinates":[-96.6667,33.6667],"type":"Point"}
}