<<<<<<< HEAD
{
  "id": 7378405,
  "type": "Feature",
  "properties": {
    "tgn:hierarchy":[
        "tgn:7378405",
        "tgn:1001853",
        "tgn:1000001",
        "tgn:7005560",
        "tgn:7029392"
    ],
    "tgn:id":7378405,
    "tgn:name":"La Zacatoza",
    "tgn:placetype":[
        "aat:300008347"
    ]
},
  "bbox": [],
  "geometry": {"coordinates":[-100.6,27.95],"type":"Point"}
}
=======
{"geometry":{"type":"Point","coordinates":[-100.600000,27.950000]},"type":"Feature","properties":{"hierarchy":["tgn:7378405","tgn:1001853","tgn:1000001","tgn:7005560","tgn:7029392"],"placetype":["aat:300008347"],"id":7378405,"name:xx":"La Zacatoza"}}
>>>>>>> 03f74aca74312dbeaf24d7e61306dd6a786dc3d0
