{
  "id": 7466635,
  "type": "Feature",
  "properties": {
    "tgn:hierarchy":[
        "tgn:7466635",
        "tgn:7002444",
        "tgn:1000003",
        "tgn:7008082",
        "tgn:7008591",
        "tgn:7029392"
    ],
    "tgn:id":7466635,
    "tgn:name:en":"An Steidh",
    "tgn:placetype":[
        "aat:300008791"
    ]
},
  "bbox": [],
  "geometry": {"coordinates":[-6.616667,57.033333],"type":"Point"}
}