{
  "id": 2500275,
  "type": "Feature",
  "properties": {
    "tgn:hierarchy":[
        "tgn:2500275",
        "tgn:7002659",
        "tgn:1000001",
        "tgn:7012149",
        "tgn:2000051",
        "tgn:7029392"
    ],
    "tgn:id":2500275,
    "tgn:name":"McCutcheon Mountain",
    "tgn:placetype":[
        "aat:300008798"
    ]
},
  "bbox": [],
  "geometry": {"coordinates":[-86.5667,34.5333],"type":"Point"}
}