{
  "id": 2179982,
  "type": "Feature",
  "properties": {
    "tgn:hierarchy":[
        "tgn:2179982",
        "tgn:1000001",
        "tgn:7012149",
        "tgn:7029392"
    ],
    "tgn:id":2179982,
    "tgn:name":"Blind Canyon",
    "tgn:placetype":[
        "aat:300008761"
    ]
},
  "bbox": [],
  "geometry": {"coordinates":[-104.6167,36.9833],"type":"Point"}
}