{
  "id": 2641921,
  "type": "Feature",
  "properties": {
    "tgn:hierarchy":[
        "tgn:2641921",
        "tgn:1000001",
        "tgn:7012149",
        "tgn:1002214",
        "tgn:7007826",
        "tgn:7029392"
    ],
    "tgn:id":2641921,
    "tgn:name":"Sand Lake",
    "tgn:placetype":[
        "aat:300008680"
    ]
},
  "bbox": [],
  "geometry": {"coordinates":[-96.8833,30.45],"type":"Point"}
}