{
  "id": 2743404,
  "type": "Feature",
  "properties": {
    "tgn:hierarchy":[
        "tgn:2743404",
        "tgn:1000001",
        "tgn:2002106",
        "tgn:7012149",
        "tgn:7007827",
        "tgn:7029392"
    ],
    "tgn:id":2743404,
    "tgn:name":"Vantage Park",
    "tgn:placetype":[
        "aat:300008347"
    ]
},
  "bbox": [],
  "geometry": {"coordinates":[-111.95,41.0333],"type":"Point"}
}