{
  "id": 4004884,
  "type": "Feature",
  "properties": {
    "tgn:hierarchy":[
        "tgn:4004884",
        "tgn:7002445",
        "tgn:1000003",
        "tgn:7008160",
        "tgn:7008591",
        "tgn:7029392"
    ],
    "tgn:id":4004884,
    "tgn:name":"Hay Green",
    "tgn:placetype":[
        "aat:300008347"
    ]
},
  "bbox": [],
  "geometry": {"coordinates":[0.7333,52.7333],"type":"Point"}
}