{
  "id": 7224646,
  "type": "Feature",
  "properties": {
    "tgn:hierarchy":[
        "tgn:7224646",
        "tgn:7002707",
        "tgn:7002705",
        "tgn:1000003",
        "tgn:1000074",
        "tgn:7029392"
    ],
    "tgn:id":7224646,
    "tgn:name":"Amfith\u00e9a",
    "tgn:placetype":[
        "aat:300008347"
    ]
},
  "bbox": [],
  "geometry": {"coordinates":[20.871111,39.689444],"type":"Point"}
}