{
  "id": 1091580,
  "type": "Feature",
  "properties": {
    "tgn:hierarchy":[
        "tgn:1091580",
        "tgn:1000855",
        "tgn:7001242",
        "tgn:1000180",
        "tgn:7029392"
    ],
    "tgn:id":1091580,
    "tgn:name":"Massangena",
    "tgn:placetype":[
        "aat:300008347"
    ]
},
  "bbox": [],
  "geometry": {"coordinates":[33.05,-21.5167],"type":"Point"}
}