{
  "id": 2293308,
  "type": "Feature",
  "properties": {
    "tgn:hierarchy":[
        "tgn:2293308",
        "tgn:1000001",
        "tgn:7012149",
        "tgn:1002999",
        "tgn:7007526",
        "tgn:7029392"
    ],
    "tgn:id":2293308,
    "tgn:name":"Double Diamond Spring",
    "tgn:placetype":[
        "aat:300008697"
    ]
},
  "bbox": [],
  "geometry": {"coordinates":[-119.7333,39.4333],"type":"Point"}
}