{
  "id": 2540150,
  "type": "Feature",
  "properties": {
    "tgn:hierarchy":[
        "tgn:2540150",
        "tgn:1000001",
        "tgn:7012149",
        "tgn:2002120",
        "tgn:7007827",
        "tgn:7029392"
    ],
    "tgn:id":2540150,
    "tgn:name":"Newfield Reservoir",
    "tgn:placetype":[
        "aat:300006191"
    ]
},
  "bbox": [],
  "geometry": {"coordinates":[-111.5833,39.1333],"type":"Point"}
}