{
  "id": 7374320,
  "type": "Feature",
  "properties": {
    "tgn:hierarchy":[
        "tgn:7374320",
        "tgn:1000001",
        "tgn:1001960",
        "tgn:7005560",
        "tgn:7029392"
    ],
    "tgn:id":7374320,
    "tgn:name":"Rancho La Bellota",
    "tgn:placetype":[
        "aat:300000241"
    ]
},
  "bbox": [],
  "geometry": {"coordinates":[-110.816667,30.533333],"type":"Point"}
}