<<<<<<< HEAD
{
  "id": 2402907,
  "type": "Feature",
  "properties": {
    "tgn:hierarchy":[
        "tgn:2402907",
        "tgn:1000001",
        "tgn:7012149",
        "tgn:7007157",
        "tgn:1002710",
        "tgn:7029392"
    ],
    "tgn:id":2402907,
    "tgn:name":"Hotwater Mine",
    "tgn:placetype":[
        "aat:300000390"
    ]
},
  "bbox": [],
  "geometry": {"coordinates":[-120.7333,39.4333],"type":"Point"}
}
=======
{"geometry":{"type":"Point","coordinates":[-120.733300,39.433300]},"type":"Feature","properties":{"hierarchy":["tgn:2402907","tgn:1000001","tgn:7012149","tgn:7007157","tgn:1002710","tgn:7029392"],"placetype":["aat:300000390"],"id":2402907,"name:xx":"Hotwater Mine"}}
>>>>>>> 03f74aca74312dbeaf24d7e61306dd6a786dc3d0
