{
  "id": 1051008,
  "type": "Feature",
  "properties": {
    "tgn:hierarchy":[
        "tgn:1051008",
        "tgn:7002444",
        "tgn:1000003",
        "tgn:7019109",
        "tgn:7008591",
        "tgn:7029392"
    ],
    "tgn:id":1051008,
    "tgn:name:en":"Portobello",
    "tgn:placetype":[
        "aat:300008347"
    ]
},
  "bbox": [],
  "geometry": {"coordinates":[-3.116667,55.95],"type":"Point"}
}