{
  "id": 2708823,
  "type": "Feature",
  "properties": {
    "tgn:hierarchy":[
        "tgn:2708823",
        "tgn:1000001",
        "tgn:7012149",
        "tgn:2001071",
        "tgn:7007521",
        "tgn:7029392"
    ],
    "tgn:id":2708823,
    "tgn:name":"Sylvia Lake",
    "tgn:placetype":[
        "aat:300006191"
    ]
},
  "bbox": [],
  "geometry": {"coordinates":[-94.7833,45.7333],"type":"Point"}
}