{
  "id": 7133407,
  "type": "Feature",
  "properties": {
    "tgn:hierarchy":[
        "tgn:7133407",
        "tgn:1000003",
        "tgn:7003688",
        "tgn:7000084",
        "tgn:7029392"
    ],
    "tgn:id":7133407,
    "tgn:name":"M\u00fchlenau",
    "tgn:placetype":[
        "aat:300008699"
    ]
},
  "bbox": [],
  "geometry": {"coordinates":[10.516667,54.383333],"type":"Point"}
}