<<<<<<< HEAD
{
  "id": 7375361,
  "type": "Feature",
  "properties": {
    "tgn:hierarchy":[
        "tgn:7375361",
        "tgn:1001836",
        "tgn:1000001",
        "tgn:7005560",
        "tgn:7029392"
    ],
    "tgn:id":7375361,
    "tgn:name":"Leones, Cerro",
    "tgn:placetype":[
        "aat:300008795"
    ]
},
  "bbox": [],
  "geometry": {"coordinates":[-113.6,27.016667],"type":"Point"}
}
=======
{"geometry":{"type":"Point","coordinates":[-113.600000,27.016667]},"type":"Feature","properties":{"hierarchy":["tgn:7375361","tgn:1001836","tgn:1000001","tgn:7005560","tgn:7029392"],"placetype":["aat:300008795"],"id":7375361,"name:xx":"Leones, Cerro"}}
>>>>>>> 03f74aca74312dbeaf24d7e61306dd6a786dc3d0
