{
  "id": 2206334,
  "type": "Feature",
  "properties": {
    "tgn:hierarchy":[
        "tgn:2206334",
        "tgn:1000001",
        "tgn:2001417",
        "tgn:7012149",
        "tgn:7007526",
        "tgn:7029392"
    ],
    "tgn:id":2206334,
    "tgn:name":"Buller Mountain",
    "tgn:placetype":[
        "aat:300008798"
    ]
},
  "bbox": [],
  "geometry": {"coordinates":[-118.6833,38.3667],"type":"Point"}
}