{
  "id": 7378719,
  "type": "Feature",
  "properties": {
    "tgn:hierarchy":[
        "tgn:7378719",
        "tgn:7005583",
        "tgn:1000001",
        "tgn:7005560",
        "tgn:7029392"
    ],
    "tgn:id":7378719,
    "tgn:name":"Metones, Arroyo de",
    "tgn:placetype":[
        "aat:300266554",
        "aat:300008699"
    ]
},
  "bbox": [],
  "geometry": {"coordinates":[-103.216667,24.666667],"type":"Point"}
}