{
  "id": 7267712,
  "type": "Feature",
  "properties": {
    "tgn:hierarchy":[
        "tgn:7267712",
        "tgn:1000003",
        "tgn:7003632",
        "tgn:7016845",
        "tgn:7029392"
    ],
    "tgn:id":7267712,
    "tgn:name:nl":"Rietbaan",
    "tgn:placetype":[
        "aat:300266560"
    ]
},
  "bbox": [],
  "geometry": {"coordinates":[4.666667,51.833333],"type":"Point"}
}