{
  "id": 7589145,
  "type": "Feature",
  "properties": {
    "tgn:hierarchy":[
        "tgn:7589145",
        "tgn:1000004",
        "tgn:7000198",
        "tgn:7000799",
        "tgn:7029392"
    ],
    "tgn:id":7589145,
    "tgn:name:en":"Buna Gura",
    "tgn:placetype":[
        "aat:300008347"
    ]
},
  "bbox": [],
  "geometry": {"coordinates":[74.177446,33.097446],"type":"Point"}
}