{
  "id": 2182860,
  "type": "Feature",
  "properties": {
    "tgn:hierarchy":[
        "tgn:2182860",
        "tgn:1000001",
        "tgn:7012149",
        "tgn:2001438",
        "tgn:7007566",
        "tgn:7029392"
    ],
    "tgn:id":2182860,
    "tgn:name":"Blue Tank",
    "tgn:placetype":[
        "aat:300006191"
    ]
},
  "bbox": [],
  "geometry": {"coordinates":[-104.1333,35.1833],"type":"Point"}
}