{
  "id": 2564362,
  "type": "Feature",
  "properties": {
    "tgn:hierarchy":[
        "tgn:2564362",
        "tgn:1000001",
        "tgn:7012149",
        "tgn:2000411",
        "tgn:7007248",
        "tgn:7029392"
    ],
    "tgn:id":2564362,
    "tgn:name":"Pachitla",
    "tgn:placetype":[
        "aat:300008347"
    ]
},
  "bbox": [],
  "geometry": {"coordinates":[-84.6667,31.75],"type":"Point"}
}