{
  "id": 2649128,
  "type": "Feature",
  "properties": {
    "tgn:hierarchy":[
        "tgn:2649128",
        "tgn:1000001",
        "tgn:7012149",
        "tgn:2001286",
        "tgn:7007524",
        "tgn:7029392"
    ],
    "tgn:id":2649128,
    "tgn:name":"Scott Island",
    "tgn:placetype":[
        "aat:300008791"
    ]
},
  "bbox": [],
  "geometry": {"coordinates":[-115.8833,48.4667],"type":"Point"}
}