{
  "id": 2466776,
  "type": "Feature",
  "properties": {
    "tgn:hierarchy":[
        "tgn:2466776",
        "tgn:1000001",
        "tgn:7012149",
        "tgn:2002171",
        "tgn:7007919",
        "tgn:7029392"
    ],
    "tgn:id":2466776,
    "tgn:name":"Long Branch",
    "tgn:placetype":[
        "aat:300008699"
    ]
},
  "bbox": [],
  "geometry": {"coordinates":[-78.0167,36.85],"type":"Point"}
}