{
  "id": 7545461,
  "type": "Feature",
  "properties": {
    "tgn:hierarchy":[
        "tgn:7545461",
        "tgn:1000004",
        "tgn:7000198",
        "tgn:7016722",
        "tgn:7029392"
    ],
    "tgn:id":7545461,
    "tgn:name:en":"Barla",
    "tgn:placetype":[
        "aat:300008347"
    ]
},
  "bbox": [],
  "geometry": {"coordinates":[78.32313,27.910547],"type":"Point"}
}