<<<<<<< HEAD
{
  "id": 7058527,
  "type": "Feature",
  "properties": {
    "tgn:hierarchy":[
        "tgn:7058527",
        "tgn:1000003",
        "tgn:1001651",
        "tgn:7003122",
        "tgn:1000080",
        "tgn:7029392"
    ],
    "tgn:id":7058527,
    "tgn:name":"Borgo Pietro Lupo",
    "tgn:placetype":[
        "aat:300008347"
    ]
},
  "bbox": [],
  "geometry": {"coordinates":[14.616667,37.333333],"type":"Point"}
}
=======
{"geometry":{"type":"Point","coordinates":[14.616667,37.333333]},"type":"Feature","properties":{"hierarchy":["tgn:7058527","tgn:1000003","tgn:1001651","tgn:7003122","tgn:1000080","tgn:7029392"],"placetype":["aat:300008347"],"id":7058527,"name:xx":"Borgo Pietro Lupo"}}
>>>>>>> 03f74aca74312dbeaf24d7e61306dd6a786dc3d0
