{
  "id": 2504004,
  "type": "Feature",
  "properties": {
    "tgn:hierarchy":[
        "tgn:2504004",
        "tgn:1000001",
        "tgn:7012149",
        "tgn:2001288",
        "tgn:7007524",
        "tgn:7029392"
    ],
    "tgn:id":2504004,
    "tgn:name":"Meadow Fork Greenhorn Creek",
    "tgn:placetype":[
        "aat:300008706"
    ]
},
  "bbox": [],
  "geometry": {"coordinates":[-111.95,45.1667],"type":"Point"}
}