{
  "id": 7410496,
  "type": "Feature",
  "properties": {
    "tgn:hierarchy":[
        "tgn:7410496",
        "tgn:1000001",
        "tgn:7005592",
        "tgn:7005560",
        "tgn:7029392"
    ],
    "tgn:id":7410496,
    "tgn:name":"Salsipuedes",
    "tgn:placetype":[
        "aat:300008347"
    ]
},
  "bbox": [],
  "geometry": {"coordinates":[-97.425,20.215278],"type":"Point"}
}