<<<<<<< HEAD
{
  "id": 2761376,
  "type": "Feature",
  "properties": {
    "tgn:hierarchy":[
        "tgn:2761376",
        "tgn:1000001",
        "tgn:7012149",
        "tgn:7014097",
        "tgn:7007158",
        "tgn:7029392"
    ],
    "tgn:id":2761376,
    "tgn:name":"West Monument Creek",
    "tgn:placetype":[
        "aat:300008706"
    ]
},
  "bbox": [],
  "geometry": {"coordinates":[-105.0,38.9833],"type":"Point"}
}
=======
{"geometry":{"type":"Point","coordinates":[-105.000000,38.983300]},"type":"Feature","properties":{"hierarchy":["tgn:2761376","tgn:1000001","tgn:7012149","tgn:7014097","tgn:7007158","tgn:7029392"],"placetype":["aat:300008706"],"id":2761376,"name:xx":"West Monument Creek"}}
>>>>>>> 03f74aca74312dbeaf24d7e61306dd6a786dc3d0
