{
  "id": 7425958,
  "type": "Feature",
  "properties": {
    "tgn:hierarchy":[
        "tgn:7425958",
        "tgn:7005581",
        "tgn:1000001",
        "tgn:7005560",
        "tgn:7029392"
    ],
    "tgn:id":7425958,
    "tgn:name":"Pres\u00f3n del Chirulo",
    "tgn:placetype":[
        "aat:300008347"
    ]
},
  "bbox": [],
  "geometry": {"coordinates":[-104.733333,27.866667],"type":"Point"}
}