{
  "id": 2643091,
  "type": "Feature",
  "properties": {
    "tgn:hierarchy":[
        "tgn:2643091",
        "tgn:1000001",
        "tgn:2000778",
        "tgn:7012149",
        "tgn:7007255",
        "tgn:7029392"
    ],
    "tgn:id":2643091,
    "tgn:name":"Sandy Branch",
    "tgn:placetype":[
        "aat:300008699"
    ]
},
  "bbox": [],
  "geometry": {"coordinates":[-89.0667,36.8333],"type":"Point"}
}