{
  "id": 7132948,
  "type": "Feature",
  "properties": {
    "tgn:hierarchy":[
        "tgn:7132948",
        "tgn:1000003",
        "tgn:7003684",
        "tgn:7000084",
        "tgn:7029392"
    ],
    "tgn:id":7132948,
    "tgn:name":"M\u00fchlen Berg",
    "tgn:placetype":[
        "aat:300008777"
    ]
},
  "bbox": [],
  "geometry": {"coordinates":[6.75,49.183333],"type":"Point"}
}