{
  "id": 7213476,
  "type": "Feature",
  "properties": {
    "tgn:hierarchy":[
        "tgn:7213476",
        "tgn:1000003",
        "tgn:7000094",
        "tgn:7000084",
        "tgn:7029392"
    ],
    "tgn:id":7213476,
    "tgn:name":"Bobbin",
    "tgn:placetype":[
        "aat:300008347"
    ]
},
  "bbox": [],
  "geometry": {"coordinates":[12.766667,53.966667],"type":"Point"}
}