<<<<<<< HEAD
{
  "id": 7472694,
  "type": "Feature",
  "properties": {
    "tgn:hierarchy":[
        "tgn:7472694",
        "tgn:7488858",
        "tgn:1000004",
        "tgn:1000141",
        "tgn:7029392"
    ],
    "tgn:id":7472694,
    "tgn:name":"Dongchi Cun",
    "tgn:placetype":[
        "aat:300387173"
    ]
},
  "bbox": [],
  "geometry": {"coordinates":[120.946343,23.900782],"type":"Point"}
}
=======
{"geometry":{"type":"Point","coordinates":[120.946343,23.900782]},"type":"Feature","properties":{"hierarchy":["tgn:7472694","tgn:7488858","tgn:1000004","tgn:1000141","tgn:7029392"],"placetype":["aat:300387173"],"id":7472694,"name:xx":"Dongchi Cun"}}
>>>>>>> 03f74aca74312dbeaf24d7e61306dd6a786dc3d0
