{
  "id": 7518948,
  "type": "Feature",
  "properties": {
    "tgn:hierarchy":[
        "tgn:7518948",
        "tgn:1009227",
        "tgn:7001866",
        "tgn:1000226",
        "tgn:1000006",
        "tgn:7029392"
    ],
    "tgn:id":7518948,
    "tgn:name:en":"Burnt Island",
    "tgn:placetype":[
        "aat:300008791"
    ]
},
  "bbox": [],
  "geometry": {"coordinates":[172.166667,-43.85],"type":"Point"}
}