{
  "id": 1043899,
  "type": "Feature",
  "properties": {
    "tgn:hierarchy":[
        "tgn:1043899",
        "tgn:1003450",
        "tgn:7007850",
        "tgn:1000003",
        "tgn:1000080",
        "tgn:7029392"
    ],
    "tgn:id":1043899,
    "tgn:name":"Carolei",
    "tgn:placetype":[
        "aat:300008347"
    ]
},
  "bbox": [],
  "geometry": {"coordinates":[16.216667,39.25],"type":"Point"}
}