{
  "id": 7391771,
  "type": "Feature",
  "properties": {
    "tgn:hierarchy":[
        "tgn:7391771",
        "tgn:1000001",
        "tgn:1001960",
        "tgn:7005560",
        "tgn:7029392"
    ],
    "tgn:id":7391771,
    "tgn:name":"Rancho Las Mayas",
    "tgn:placetype":[
        "aat:300008347"
    ]
},
  "bbox": [],
  "geometry": {"coordinates":[-109.733333,26.933333],"type":"Point"}
}