{
  "id": 7346426,
  "type": "Feature",
  "properties": {
    "tgn:hierarchy":[
        "tgn:7346426",
        "tgn:7002759",
        "tgn:7008909",
        "tgn:1000003",
        "tgn:1000095",
        "tgn:7029392"
    ],
    "tgn:id":7346426,
    "tgn:name":"Pantano de Arguis",
    "tgn:placetype":[
        "aat:300006191"
    ]
},
  "bbox": [],
  "geometry": {"coordinates":[-0.432213,42.305398],"type":"Point"}
}