{
  "id": 1052393,
  "type": "Feature",
  "properties": {
    "tgn:hierarchy":[
        "tgn:1052393",
        "tgn:1000004",
        "tgn:1003377",
        "tgn:7018214",
        "tgn:7002435",
        "tgn:7029392"
    ],
    "tgn:id":1052393,
    "tgn:name":"Babynino",
    "tgn:placetype":[
        "aat:300008347"
    ]
},
  "bbox": [],
  "geometry": {"coordinates":[35.75,54.4167],"type":"Point"}
}