{
  "id": 7247443,
  "type": "Feature",
  "properties": {
    "tgn:hierarchy":[
        "tgn:7247443",
        "tgn:7003456",
        "tgn:1000003",
        "tgn:1000063",
        "tgn:7018236",
        "tgn:7029392"
    ],
    "tgn:id":7247443,
    "tgn:name":"De Brug",
    "tgn:placetype":[
        "aat:300008347"
    ]
},
  "bbox": [],
  "geometry": {"coordinates":[4.483333,50.983333],"type":"Point"}
}