<<<<<<< HEAD
{
  "id": 2333213,
  "type": "Feature",
  "properties": {
    "tgn:hierarchy":[
        "tgn:2333213",
        "tgn:1000001",
        "tgn:1002963",
        "tgn:7012149",
        "tgn:7007565",
        "tgn:7029392"
    ],
    "tgn:id":2333213,
    "tgn:name":"Flynns Knoll",
    "tgn:placetype":[
        "aat:300132348"
    ]
},
  "bbox": [],
  "geometry": {"coordinates":[-74.0333,40.4833],"type":"Point"}
}
=======
{"geometry":{"type":"Point","coordinates":[-74.033300,40.483300]},"type":"Feature","properties":{"hierarchy":["tgn:2333213","tgn:1000001","tgn:1002963","tgn:7012149","tgn:7007565","tgn:7029392"],"placetype":["aat:300132348"],"id":2333213,"name:xx":"Flynns Knoll"}}
>>>>>>> 03f74aca74312dbeaf24d7e61306dd6a786dc3d0
