{
  "id": 2180361,
  "type": "Feature",
  "properties": {
    "tgn:hierarchy":[
        "tgn:2180361",
        "tgn:1000001",
        "tgn:7012149",
        "tgn:1002453",
        "tgn:7007706",
        "tgn:7029392"
    ],
    "tgn:id":2180361,
    "tgn:name":"Blocktown",
    "tgn:placetype":[
        "aat:300008347"
    ]
},
  "bbox": [],
  "geometry": {"coordinates":[-83.6833,40.7333],"type":"Point"}
}