{
  "id": 7389787,
  "type": "Feature",
  "properties": {
    "tgn:hierarchy":[
        "tgn:7389787",
        "tgn:1000001",
        "tgn:7005597",
        "tgn:7005560",
        "tgn:7029392"
    ],
    "tgn:id":7389787,
    "tgn:name":"Rancho Paso de La Pita",
    "tgn:placetype":[
        "aat:300008347"
    ]
},
  "bbox": [],
  "geometry": {"coordinates":[-97.366667,25.733333],"type":"Point"}
}