{
  "id": 2367803,
  "type": "Feature",
  "properties": {
    "tgn:hierarchy":[
        "tgn:2367803",
        "tgn:1000001",
        "tgn:7012149",
        "tgn:2001512",
        "tgn:7007709",
        "tgn:7029392"
    ],
    "tgn:id":2367803,
    "tgn:name":"Grove Park",
    "tgn:placetype":[
        "aat:300008347"
    ]
},
  "bbox": [],
  "geometry": {"coordinates":[-77.55,35.25],"type":"Point"}
}