<<<<<<< HEAD
{
  "id": 7178992,
  "type": "Feature",
  "properties": {
    "tgn:hierarchy":[
        "tgn:7178992",
        "tgn:7003669",
        "tgn:1000003",
        "tgn:7000084",
        "tgn:7029392"
    ],
    "tgn:id":7178992,
    "tgn:name":"Hachau",
    "tgn:placetype":[
        "aat:300387200"
    ]
},
  "bbox": [],
  "geometry": {"coordinates":[12.7,47.8],"type":"Point"}
}
=======
{"geometry":{"type":"Point","coordinates":[12.700000,47.800000]},"type":"Feature","properties":{"hierarchy":["tgn:7178992","tgn:7003669","tgn:1000003","tgn:7000084","tgn:7029392"],"placetype":["aat:300387200"],"id":7178992,"name:xx":"Hachau"}}
>>>>>>> 03f74aca74312dbeaf24d7e61306dd6a786dc3d0
