{
  "id": 7495850,
  "type": "Feature",
  "properties": {
    "tgn:hierarchy":[
        "tgn:7495850",
        "tgn:1000004",
        "tgn:7001013",
        "tgn:1000141",
        "tgn:7029392"
    ],
    "tgn:id":7495850,
    "tgn:name":"Jieshou Guozhong",
    "tgn:placetype":[
        "aat:300006495"
    ]
},
  "bbox": [],
  "geometry": {"coordinates":[121.352613,24.81955],"type":"Point"}
}