{
  "id": 7217492,
  "type": "Feature",
  "properties": {
    "tgn:hierarchy":[
        "tgn:7217492",
        "tgn:7002690",
        "tgn:7012056",
        "tgn:1000003",
        "tgn:1000074",
        "tgn:7029392"
    ],
    "tgn:id":7217492,
    "tgn:name":"Tsalian\u00e1",
    "tgn:placetype":[
        "aat:300008347"
    ]
},
  "bbox": [],
  "geometry": {"coordinates":[23.666667,35.25],"type":"Point"}
}