{
  "id": 2353422,
  "type": "Feature",
  "properties": {
    "tgn:hierarchy":[
        "tgn:2353422",
        "tgn:1000001",
        "tgn:1002260",
        "tgn:7012149",
        "tgn:7007920",
        "tgn:7029392"
    ],
    "tgn:id":2353422,
    "tgn:name":"Gold Creek Basin",
    "tgn:placetype":[
        "aat:300386845"
    ]
},
  "bbox": [],
  "geometry": {"coordinates":[-120.75,47.4167],"type":"Point"}
}