{
  "id": 2716152,
  "type": "Feature",
  "properties": {
    "tgn:hierarchy":[
        "tgn:2716152",
        "tgn:1000001",
        "tgn:1002664",
        "tgn:7012149",
        "tgn:7007159",
        "tgn:7029392"
    ],
    "tgn:id":2716152,
    "tgn:name":"Thatchbed Island",
    "tgn:placetype":[
        "aat:300008791"
    ]
},
  "bbox": [],
  "geometry": {"coordinates":[-72.3833,41.3333],"type":"Point"}
}