{
  "id": 2577096,
  "type": "Feature",
  "properties": {
    "tgn:hierarchy":[
        "tgn:2577096",
        "tgn:1000001",
        "tgn:7012149",
        "tgn:1003038",
        "tgn:7007517",
        "tgn:7029392"
    ],
    "tgn:id":2577096,
    "tgn:name":"Peter Pond",
    "tgn:placetype":[
        "aat:300006191"
    ]
},
  "bbox": [],
  "geometry": {"coordinates":[-71.8833,42.05],"type":"Point"}
}