{
  "id": 7581162,
  "type": "Feature",
  "properties": {
    "tgn:hierarchy":[
        "tgn:7581162",
        "tgn:1000004",
        "tgn:7000198",
        "tgn:1001895",
        "tgn:7029392"
    ],
    "tgn:id":7581162,
    "tgn:name:en":"Tirthp\u016bri",
    "tgn:placetype":[
        "aat:300008347"
    ]
},
  "bbox": [],
  "geometry": {"coordinates":[75.933333,19.433333],"type":"Point"}
}