{
  "id": 7155846,
  "type": "Feature",
  "properties": {
    "tgn:hierarchy":[
        "tgn:7155846",
        "tgn:1000003",
        "tgn:7003677",
        "tgn:7000084",
        "tgn:7029392"
    ],
    "tgn:id":7155846,
    "tgn:name":"Klein Graf",
    "tgn:placetype":[
        "aat:300000206"
    ]
},
  "bbox": [],
  "geometry": {"coordinates":[6.183333,51.633333],"type":"Point"}
}