{
  "id": 1001225,
  "type": "Feature",
  "properties": {
    "tgn:hierarchy":[
        "tgn:1001225",
        "tgn:7001242",
        "tgn:7016833",
        "tgn:7029392"
    ],
    "tgn:id":1001225,
    "tgn:name":"Mu\u1e29\u0101faz\u0327at Dumy\u0101\u0163",
    "tgn:placetype":[
        "aat:300387064",
        "aat:300235093"
    ]
},
  "bbox": [],
  "geometry": {"coordinates":[31.75,31.35],"type":"Point"}
}