{
  "id": 2534424,
  "type": "Feature",
  "properties": {
    "tgn:hierarchy":[
        "tgn:2534424",
        "tgn:1000001",
        "tgn:7012149",
        "tgn:2001288",
        "tgn:7007524",
        "tgn:7029392"
    ],
    "tgn:id":2534424,
    "tgn:name":"NE SE Section 19 Mine",
    "tgn:placetype":[
        "aat:300000390"
    ]
},
  "bbox": [],
  "geometry": {"coordinates":[-112.7333,45.1333],"type":"Point"}
}