{
  "id": 2765624,
  "type": "Feature",
  "properties": {
    "tgn:hierarchy":[
        "tgn:2765624",
        "tgn:1000001",
        "tgn:7012149",
        "tgn:2001420",
        "tgn:7007526",
        "tgn:7029392"
    ],
    "tgn:id":2765624,
    "tgn:name":"White Cloud Wash",
    "tgn:placetype":[
        "aat:300008701"
    ]
},
  "bbox": [],
  "geometry": {"coordinates":[-114.2333,39.5333],"type":"Point"}
}