<<<<<<< HEAD
{
  "id": 2765624,
  "type": "Feature",
  "properties": {
    "tgn:hierarchy":[
        "tgn:2765624",
        "tgn:1000001",
        "tgn:7012149",
        "tgn:2001420",
        "tgn:7007526",
        "tgn:7029392"
    ],
    "tgn:id":2765624,
    "tgn:name":"White Cloud Wash",
    "tgn:placetype":[
        "aat:300008701"
    ]
},
  "bbox": [],
  "geometry": {"coordinates":[-114.2333,39.5333],"type":"Point"}
}
=======
{"geometry":{"type":"Point","coordinates":[-114.233300,39.533300]},"type":"Feature","properties":{"hierarchy":["tgn:2765624","tgn:1000001","tgn:7012149","tgn:2001420","tgn:7007526","tgn:7029392"],"placetype":["aat:300008701"],"id":2765624,"name:xx":"White Cloud Wash"}}
>>>>>>> 03f74aca74312dbeaf24d7e61306dd6a786dc3d0
