{
  "id": 7571896,
  "type": "Feature",
  "properties": {
    "tgn:hierarchy":[
        "tgn:7571896",
        "tgn:7016678",
        "tgn:7000204",
        "tgn:1000004",
        "tgn:1007275",
        "tgn:7000198",
        "tgn:7029392"
    ],
    "tgn:id":7571896,
    "tgn:name:en":"Henpoin",
    "tgn:placetype":[
        "aat:300008347"
    ]
},
  "bbox": [],
  "geometry": {"coordinates":[93.766667,6.866667],"type":"Point"}
}