{
  "id": 7497286,
  "type": "Feature",
  "properties": {
    "tgn:hierarchy":[
        "tgn:7497286",
        "tgn:1000004",
        "tgn:1000959",
        "tgn:1000141",
        "tgn:7029392"
    ],
    "tgn:id":7497286,
    "tgn:name":"Shenmei Qiao",
    "tgn:placetype":[
        "aat:300007836"
    ]
},
  "bbox": [],
  "geometry": {"coordinates":[121.624976,25.005517],"type":"Point"}
}