{
  "id": 7568657,
  "type": "Feature",
  "properties": {
    "tgn:hierarchy":[
        "tgn:7568657",
        "tgn:1001828",
        "tgn:1000004",
        "tgn:7000198",
        "tgn:7029392"
    ],
    "tgn:id":7568657,
    "tgn:name:en":"Ann\u0101ram",
    "tgn:placetype":[
        "aat:300008347"
    ]
},
  "bbox": [],
  "geometry": {"coordinates":[78.179722,17.022222],"type":"Point"}
}