{
  "id": 2392445,
  "type": "Feature",
  "properties": {
    "tgn:hierarchy":[
        "tgn:2392445",
        "tgn:1000001",
        "tgn:2001424",
        "tgn:7012149",
        "tgn:7007564",
        "tgn:7029392"
    ],
    "tgn:id":2392445,
    "tgn:name":"Hitchcock, Mount",
    "tgn:placetype":[
        "aat:300008798"
    ]
},
  "bbox": [],
  "geometry": {"coordinates":[-71.5333,44.0667],"type":"Point"}
}