{
  "id": 7174120,
  "type": "Feature",
  "properties": {
    "tgn:hierarchy":[
        "tgn:7174120",
        "tgn:7000096",
        "tgn:1000003",
        "tgn:7000084",
        "tgn:7029392"
    ],
    "tgn:id":7174120,
    "tgn:name":"Gro\u00dfer M\u00f6ggelin-See",
    "tgn:placetype":[
        "aat:300008680"
    ]
},
  "bbox": [],
  "geometry": {"coordinates":[13.533333,52.133333],"type":"Point"}
}