<<<<<<< HEAD
{
  "id": 2255900,
  "type": "Feature",
  "properties": {
    "tgn:hierarchy":[
        "tgn:2255900",
        "tgn:1000001",
        "tgn:7012149",
        "tgn:2002381",
        "tgn:7007923",
        "tgn:7029392"
    ],
    "tgn:id":2255900,
    "tgn:name":"Copper Creek",
    "tgn:placetype":[
        "aat:300008706"
    ]
},
  "bbox": [],
  "geometry": {"coordinates":[-107.4667,44.6833],"type":"Point"}
}
=======
{"geometry":{"type":"Point","coordinates":[-107.466700,44.683300]},"type":"Feature","properties":{"hierarchy":["tgn:2255900","tgn:1000001","tgn:7012149","tgn:2002381","tgn:7007923","tgn:7029392"],"placetype":["aat:300008706"],"id":2255900,"name:xx":"Copper Creek"}}
>>>>>>> 03f74aca74312dbeaf24d7e61306dd6a786dc3d0
