{
  "id": 1017393,
  "type": "Feature",
  "properties": {
    "tgn:hierarchy":[
        "tgn:1017393",
        "tgn:1000001",
        "tgn:1001960",
        "tgn:7005560",
        "tgn:7029392"
    ],
    "tgn:id":1017393,
    "tgn:name":"El Consuelo",
    "tgn:placetype":[
        "aat:300008347"
    ]
},
  "bbox": [],
  "geometry": {"coordinates":[-111.937778,31.074722],"type":"Point"}
}