<<<<<<< HEAD
{
  "id": 7059209,
  "type": "Feature",
  "properties": {
    "tgn:hierarchy":[
        "tgn:7059209",
        "tgn:7032875",
        "tgn:7004637",
        "tgn:1000001",
        "tgn:7029392"
    ],
    "tgn:id":7059209,
    "tgn:name":"Welches Hill",
    "tgn:placetype":[
        "aat:300008347"
    ]
},
  "bbox": [],
  "geometry": {"coordinates":[-63.016,18.233],"type":"Point"}
}
=======
{"geometry":{"type":"Point","coordinates":[-63.016000,18.233000]},"type":"Feature","properties":{"hierarchy":["tgn:7059209","tgn:7032875","tgn:7004637","tgn:1000001","tgn:7029392"],"placetype":["aat:300008347"],"id":7059209,"name:xx":"Welches Hill"}}
>>>>>>> 03f74aca74312dbeaf24d7e61306dd6a786dc3d0
