{
  "id": 7432722,
  "type": "Feature",
  "properties": {
    "tgn:hierarchy":[
        "tgn:7432722",
        "tgn:1001853",
        "tgn:1000001",
        "tgn:7005560",
        "tgn:7029392"
    ],
    "tgn:id":7432722,
    "tgn:name":"Villa De Arteaga",
    "tgn:placetype":[
        "aat:300008347"
    ]
},
  "bbox": [],
  "geometry": {"coordinates":[-100.833333,25.433333],"type":"Point"}
}