{
  "id": 1033871,
  "type": "Feature",
  "properties": {
    "tgn:hierarchy":[
        "tgn:1033871",
        "tgn:1000003",
        "tgn:7002890",
        "tgn:1000070",
        "tgn:7029392"
    ],
    "tgn:id":1033871,
    "tgn:name":"Le H\u00e9rie-la-Vi\u00e9ville",
    "tgn:placetype":[
        "aat:300008347"
    ]
},
  "bbox": [],
  "geometry": {"coordinates":[3.6333,49.8167],"type":"Point"}
}