<<<<<<< HEAD
{
  "id": 2334094,
  "type": "Feature",
  "properties": {
    "tgn:hierarchy":[
        "tgn:2334094",
        "tgn:1000001",
        "tgn:7012149",
        "tgn:7007524",
        "tgn:7029392"
    ],
    "tgn:id":2334094,
    "tgn:name":"Fords Creek",
    "tgn:placetype":[
        "aat:300008706"
    ]
},
  "bbox": [],
  "geometry": {"coordinates":[-109.1833,47.2],"type":"Point"}
}
=======
{"geometry":{"type":"Point","coordinates":[-109.183300,47.200000]},"type":"Feature","properties":{"hierarchy":["tgn:2334094","tgn:1000001","tgn:7012149","tgn:7007524","tgn:7029392"],"placetype":["aat:300008706"],"id":2334094,"name:xx":"Fords Creek"}}
>>>>>>> 03f74aca74312dbeaf24d7e61306dd6a786dc3d0
