{
  "id": 2646735,
  "type": "Feature",
  "properties": {
    "tgn:hierarchy":[
        "tgn:2646735",
        "tgn:1000001",
        "tgn:7006451",
        "tgn:2000093",
        "tgn:7012149",
        "tgn:7029392"
    ],
    "tgn:id":2646735,
    "tgn:name":"Scanlon Wash",
    "tgn:placetype":[
        "aat:300008699"
    ]
},
  "bbox": [],
  "geometry": {"coordinates":[-110.95,33.4667],"type":"Point"}
}