{
  "id": 2768663,
  "type": "Feature",
  "properties": {
    "tgn:hierarchy":[
        "tgn:2768663",
        "tgn:1000001",
        "tgn:7012149",
        "tgn:2000893",
        "tgn:7007256",
        "tgn:7029392"
    ],
    "tgn:id":2768663,
    "tgn:name":"Whitley Branch",
    "tgn:placetype":[
        "aat:300008699"
    ]
},
  "bbox": [],
  "geometry": {"coordinates":[-92.6667,31.2667],"type":"Point"}
}