{
  "id": 7457549,
  "type": "Feature",
  "properties": {
    "tgn:hierarchy":[
        "tgn:7457549",
        "tgn:7002445",
        "tgn:7008116",
        "tgn:1000003",
        "tgn:7008591",
        "tgn:7029392"
    ],
    "tgn:id":7457549,
    "tgn:name:en":"Pentire Point East",
    "tgn:placetype":[
        "aat:300386846"
    ]
},
  "bbox": [],
  "geometry": {"coordinates":[-5.133333,50.416667],"type":"Point"}
}