<<<<<<< HEAD
{
  "id": 7028037,
  "type": "Feature",
  "properties": {
    "tgn:hierarchy":[
        "tgn:7028037",
        "tgn:7002445",
        "tgn:1000003",
        "tgn:7008157",
        "tgn:7008591",
        "tgn:7029392"
    ],
    "tgn:id":7028037,
    "tgn:name":"Ranby",
    "tgn:placetype":[
        "aat:300008347",
        "aat:300008372"
    ]
},
  "bbox": [],
  "geometry": {"coordinates":[-0.1667,53.2833],"type":"Point"}
}
=======
{"geometry":{"type":"Point","coordinates":[-0.166700,53.283300]},"type":"Feature","properties":{"hierarchy":["tgn:7028037","tgn:7002445","tgn:1000003","tgn:7008157","tgn:7008591","tgn:7029392"],"placetype":["aat:300008347","aat:300008372"],"id":7028037,"name:xx":"Ranby"}}
>>>>>>> 03f74aca74312dbeaf24d7e61306dd6a786dc3d0
