<<<<<<< HEAD
{
  "id": 7027305,
  "type": "Feature",
  "properties": {
    "tgn:hierarchy":[
        "tgn:7027305",
        "tgn:7002445",
        "tgn:7011980",
        "tgn:1000003",
        "tgn:7008591",
        "tgn:7029392"
    ],
    "tgn:id":7027305,
    "tgn:name:ang":"Sibestune",
    "tgn:placetype":[
        "aat:300008347",
        "aat:300008372"
    ]
},
  "bbox": [],
  "geometry": {"coordinates":[-0.3833,52.5667],"type":"Point"}
}
=======
{"geometry":{"type":"Point","coordinates":[-0.383300,52.566700]},"type":"Feature","properties":{"hierarchy":["tgn:7027305","tgn:7002445","tgn:7011980","tgn:1000003","tgn:7008591","tgn:7029392"],"placetype":["aat:300008347","aat:300008372"],"id":7027305,"name:ang":"Sibestune"}}
>>>>>>> 03f74aca74312dbeaf24d7e61306dd6a786dc3d0
