{
  "id": 2241651,
  "type": "Feature",
  "properties": {
    "tgn:hierarchy":[
        "tgn:2241651",
        "tgn:1000001",
        "tgn:2000311",
        "tgn:7012149",
        "tgn:7007248",
        "tgn:7029392"
    ],
    "tgn:id":2241651,
    "tgn:name":"Clarks Island",
    "tgn:placetype":[
        "aat:300008791"
    ]
},
  "bbox": [],
  "geometry": {"coordinates":[-81.7167,31.0667],"type":"Point"}
}