{
  "id": 2253278,
  "type": "Feature",
  "properties": {
    "tgn:hierarchy":[
        "tgn:2253278",
        "tgn:1000001",
        "tgn:7012149",
        "tgn:2000916",
        "tgn:7007256",
        "tgn:7029392"
    ],
    "tgn:id":2253278,
    "tgn:name":"Converse",
    "tgn:placetype":[
        "aat:300008347"
    ]
},
  "bbox": [],
  "geometry": {"coordinates":[-91.35,30.8667],"type":"Point"}
}