{
  "id": 7318921,
  "type": "Feature",
  "properties": {
    "tgn:hierarchy":[
        "tgn:7318921",
        "tgn:7002464",
        "tgn:1000049",
        "tgn:1000002",
        "tgn:7029392"
    ],
    "tgn:id":7318921,
    "tgn:name":"Aroma",
    "tgn:placetype":[
        "aat:300387200"
    ]
},
  "bbox": [],
  "geometry": {"coordinates":[-69.566667,-18.216667],"type":"Point"}
}