{
  "id": 2784183,
  "type": "Feature",
  "properties": {
    "tgn:hierarchy":[
        "tgn:2784183",
        "tgn:7002659",
        "tgn:1000001",
        "tgn:7012149",
        "tgn:2000027",
        "tgn:7029392"
    ],
    "tgn:id":2784183,
    "tgn:name":"Yancy",
    "tgn:placetype":[
        "aat:300008347"
    ]
},
  "bbox": [],
  "geometry": {"coordinates":[-85.9667,34.1667],"type":"Point"}
}