{
  "id": 2218703,
  "type": "Feature",
  "properties": {
    "tgn:hierarchy":[
        "tgn:2218703",
        "tgn:1000001",
        "tgn:2001181",
        "tgn:7012149",
        "tgn:7007523",
        "tgn:7029392"
    ],
    "tgn:id":2218703,
    "tgn:name":"Cane Hollow",
    "tgn:placetype":[
        "aat:300008761"
    ]
},
  "bbox": [],
  "geometry": {"coordinates":[-91.15,37.0333],"type":"Point"}
}