<<<<<<< HEAD
{
  "id": 2338184,
  "type": "Feature",
  "properties": {
    "tgn:hierarchy":[
        "tgn:2338184",
        "tgn:1000001",
        "tgn:2000923",
        "tgn:7012149",
        "tgn:7007515",
        "tgn:7029392"
    ],
    "tgn:id":2338184,
    "tgn:name":"Fox Pond",
    "tgn:placetype":[
        "aat:300008680"
    ]
},
  "bbox": [],
  "geometry": {"coordinates":[-69.5167,44.3167],"type":"Point"}
}
=======
{"geometry":{"type":"Point","coordinates":[-69.516700,44.316700]},"type":"Feature","properties":{"hierarchy":["tgn:2338184","tgn:1000001","tgn:2000923","tgn:7012149","tgn:7007515","tgn:7029392"],"placetype":["aat:300008680"],"id":2338184,"name:xx":"Fox Pond"}}
>>>>>>> 03f74aca74312dbeaf24d7e61306dd6a786dc3d0
