{
  "id": 7284829,
  "type": "Feature",
  "properties": {
    "tgn:hierarchy":[
        "tgn:7284829",
        "tgn:1001768",
        "tgn:1000049",
        "tgn:1000002",
        "tgn:7029392"
    ],
    "tgn:id":7284829,
    "tgn:name":"Pullalli, Llanos de",
    "tgn:placetype":[
        "aat:300008805"
    ]
},
  "bbox": [],
  "geometry": {"coordinates":[-71.35,-32.416667],"type":"Point"}
}