{
  "id": 2556594,
  "type": "Feature",
  "properties": {
    "tgn:hierarchy":[
        "tgn:2556594",
        "tgn:1000001",
        "tgn:7013638",
        "tgn:7012149",
        "tgn:7007568",
        "tgn:7029392"
    ],
    "tgn:id":2556594,
    "tgn:name":"Old Broken",
    "tgn:placetype":[
        "aat:300008798"
    ]
},
  "bbox": [],
  "geometry": {"coordinates":[-73.5667,42.05],"type":"Point"}
}