<<<<<<< HEAD
{
  "id": 2406621,
  "type": "Feature",
  "properties": {
    "tgn:hierarchy":[
        "tgn:2406621",
        "tgn:1000001",
        "tgn:7012149",
        "tgn:2001887",
        "tgn:7007825",
        "tgn:7029392"
    ],
    "tgn:id":2406621,
    "tgn:name":"Hunt Branch",
    "tgn:placetype":[
        "aat:300008699"
    ]
},
  "bbox": [],
  "geometry": {"coordinates":[-87.3167,35.5167],"type":"Point"}
}
=======
{"geometry":{"type":"Point","coordinates":[-87.316700,35.516700]},"type":"Feature","properties":{"hierarchy":["tgn:2406621","tgn:1000001","tgn:7012149","tgn:2001887","tgn:7007825","tgn:7029392"],"placetype":["aat:300008699"],"id":2406621,"name:xx":"Hunt Branch"}}
>>>>>>> 03f74aca74312dbeaf24d7e61306dd6a786dc3d0
