{
  "id": 2195954,
  "type": "Feature",
  "properties": {
    "tgn:hierarchy":[
        "tgn:2195954",
        "tgn:1000001",
        "tgn:2002368",
        "tgn:7012149",
        "tgn:7007923",
        "tgn:7029392"
    ],
    "tgn:id":2195954,
    "tgn:name":"Broadway Mine",
    "tgn:placetype":[
        "aat:300000390"
    ]
},
  "bbox": [],
  "geometry": {"coordinates":[-106.7333,41.0333],"type":"Point"}
}