{
  "id": 2267123,
  "type": "Feature",
  "properties": {
    "tgn:hierarchy":[
        "tgn:2267123",
        "tgn:1000001",
        "tgn:7012149",
        "tgn:2001274",
        "tgn:7007524",
        "tgn:7029392"
    ],
    "tgn:id":2267123,
    "tgn:name":"Crevice Lake",
    "tgn:placetype":[
        "aat:300008680"
    ]
},
  "bbox": [],
  "geometry": {"coordinates":[-113.65,47.8667],"type":"Point"}
}