<<<<<<< HEAD
{
  "id": 2404497,
  "type": "Feature",
  "properties": {
    "tgn:hierarchy":[
        "tgn:2404497",
        "tgn:1000001",
        "tgn:7012149",
        "tgn:2000282",
        "tgn:7007240",
        "tgn:7029392"
    ],
    "tgn:id":2404497,
    "tgn:name":"Hubbard Pond",
    "tgn:placetype":[
        "aat:300008680"
    ]
},
  "bbox": [],
  "geometry": {"coordinates":[-81.8667,29.6333],"type":"Point"}
}
=======
{"geometry":{"type":"Point","coordinates":[-81.866700,29.633300]},"type":"Feature","properties":{"hierarchy":["tgn:2404497","tgn:1000001","tgn:7012149","tgn:2000282","tgn:7007240","tgn:7029392"],"placetype":["aat:300008680"],"id":2404497,"name:xx":"Hubbard Pond"}}
>>>>>>> 03f74aca74312dbeaf24d7e61306dd6a786dc3d0
