{
  "id": 2127676,
  "type": "Feature",
  "properties": {
    "tgn:hierarchy":[
        "tgn:2127676",
        "tgn:1000001",
        "tgn:7012149",
        "tgn:2001446",
        "tgn:7007566",
        "tgn:7029392"
    ],
    "tgn:id":2127676,
    "tgn:name":"Alamito, Ca\u00f1on",
    "tgn:placetype":[
        "aat:300008761"
    ]
},
  "bbox": [],
  "geometry": {"coordinates":[-104.4167,35.8333],"type":"Point"}
}