{
  "id": 2083336,
  "type": "Feature",
  "properties": {
    "tgn:hierarchy":[
        "tgn:2083336",
        "tgn:1000001",
        "tgn:7012149",
        "tgn:2001667",
        "tgn:7007707",
        "tgn:7029392"
    ],
    "tgn:id":2083336,
    "tgn:name":"Haworth",
    "tgn:placetype":[
        "aat:300008347"
    ]
},
  "bbox": [],
  "geometry": {"coordinates":[-94.65,33.8333],"type":"Point"}
}