{
  "id": 7014956,
  "type": "Feature",
  "properties": {
    "tgn:hierarchy":[
        "tgn:7014956",
        "tgn:7001242",
        "tgn:7001630",
        "tgn:7029392"
    ],
    "tgn:id":7014956,
    "tgn:name":"Cankuzo",
    "tgn:placetype":[
        "aat:300387064",
        "aat:300000774"
    ]
},
  "bbox": [],
  "geometry": {"coordinates":[30.5833,-3.1333],"type":"Point"}
}