{
  "id": 7432302,
  "type": "Feature",
  "properties": {
    "tgn:hierarchy":[
        "tgn:7432302",
        "tgn:7005583",
        "tgn:1000001",
        "tgn:7005560",
        "tgn:7029392"
    ],
    "tgn:id":7432302,
    "tgn:name":"El Cuitaste",
    "tgn:placetype":[
        "aat:300008347"
    ]
},
  "bbox": [],
  "geometry": {"coordinates":[-104.166667,22.85],"type":"Point"}
}