{
  "id": 7500852,
  "type": "Feature",
  "properties": {
    "tgn:hierarchy":[
        "tgn:7500852",
        "tgn:7468018",
        "tgn:1000004",
        "tgn:1000141",
        "tgn:7029392"
    ],
    "tgn:id":7500852,
    "tgn:name":"Sishiwuhao Suidao",
    "tgn:placetype":[
        "aat:300007899"
    ]
},
  "bbox": [],
  "geometry": {"coordinates":[120.7725,23.506944],"type":"Point"}
}