{
  "id": 7446113,
  "type": "Feature",
  "properties": {
    "tgn:hierarchy":[
        "tgn:7446113",
        "tgn:7002444",
        "tgn:7008074",
        "tgn:1000003",
        "tgn:7008591",
        "tgn:7029392"
    ],
    "tgn:id":7446113,
    "tgn:name:en":"Soulseat Loch",
    "tgn:placetype":[
        "aat:300008680"
    ]
},
  "bbox": [],
  "geometry": {"coordinates":[-4.966667,54.883333],"type":"Point"}
}