{
  "id": 2786565,
  "type": "Feature",
  "properties": {
    "tgn:hierarchy":[
        "tgn:2786565",
        "tgn:1000001",
        "tgn:7012149",
        "tgn:2001720",
        "tgn:7007708",
        "tgn:7029392"
    ],
    "tgn:id":2786565,
    "tgn:name":"Z Canal",
    "tgn:placetype":[
        "aat:300006075"
    ]
},
  "bbox": [],
  "geometry": {"coordinates":[-119.2667,45.8667],"type":"Point"}
}