{
  "id": 2472321,
  "type": "Feature",
  "properties": {
    "tgn:hierarchy":[
        "tgn:2472321",
        "tgn:1000001",
        "tgn:7012149",
        "tgn:1002749",
        "tgn:7007240",
        "tgn:7029392"
    ],
    "tgn:id":2472321,
    "tgn:name":"Louise, Lake",
    "tgn:placetype":[
        "aat:300008680"
    ]
},
  "bbox": [],
  "geometry": {"coordinates":[-81.5333,28.4667],"type":"Point"}
}