{
  "id": 7443277,
  "type": "Feature",
  "properties": {
    "tgn:hierarchy":[
        "tgn:7443277",
        "tgn:7002445",
        "tgn:1000003",
        "tgn:7019068",
        "tgn:7008591",
        "tgn:7029392"
    ],
    "tgn:id":7443277,
    "tgn:name:en":"Tees Mouth",
    "tgn:placetype":[
        "aat:300008699"
    ]
},
  "bbox": [],
  "geometry": {"coordinates":[-1.166667,54.65],"type":"Point"}
}