<<<<<<< HEAD
{
  "id": 2763607,
  "type": "Feature",
  "properties": {
    "tgn:hierarchy":[
        "tgn:2763607",
        "tgn:1000001",
        "tgn:7012149",
        "tgn:7016021",
        "tgn:7007568",
        "tgn:7029392"
    ],
    "tgn:id":2763607,
    "tgn:name":"Whaleback Island",
    "tgn:placetype":[
        "aat:300008791"
    ]
},
  "bbox": [],
  "geometry": {"coordinates":[-75.75,44.5],"type":"Point"}
}
=======
{"geometry":{"type":"Point","coordinates":[-75.750000,44.500000]},"type":"Feature","properties":{"hierarchy":["tgn:2763607","tgn:1000001","tgn:7012149","tgn:7016021","tgn:7007568","tgn:7029392"],"placetype":["aat:300008791"],"id":2763607,"name:xx":"Whaleback Island"}}
>>>>>>> 03f74aca74312dbeaf24d7e61306dd6a786dc3d0
