{
  "id": 7322756,
  "type": "Feature",
  "properties": {
    "tgn:hierarchy":[
        "tgn:7322756",
        "tgn:7002820",
        "tgn:7030216",
        "tgn:1000003",
        "tgn:1000095",
        "tgn:7029392"
    ],
    "tgn:id":7322756,
    "tgn:name":"Salinas, Punta",
    "tgn:placetype":[
        "aat:300386846"
    ]
},
  "bbox": [],
  "geometry": {"coordinates":[3.214526,42.061099],"type":"Point"}
}