{
  "id": 7021298,
  "type": "Feature",
  "properties": {
    "tgn:hierarchy":[
        "tgn:7021298",
        "tgn:1000001",
        "tgn:7012149",
        "tgn:7029392"
    ],
    "tgn:id":7021298,
    "tgn:name":"Table Rock Lake",
    "tgn:placetype":[
        "aat:300008680",
        "aat:300006191"
    ]
},
  "bbox": [],
  "geometry": {"coordinates":[-93.5667,36.4833],"type":"Point"}
}