<<<<<<< HEAD
{
  "id": 7021298,
  "type": "Feature",
  "properties": {
    "tgn:hierarchy":[
        "tgn:7021298",
        "tgn:1000001",
        "tgn:7012149",
        "tgn:7029392"
    ],
    "tgn:id":7021298,
    "tgn:name":"Table Rock Lake",
    "tgn:placetype":[
        "aat:300008680",
        "aat:300006191"
    ]
},
  "bbox": [],
  "geometry": {"coordinates":[-93.5667,36.4833],"type":"Point"}
}
=======
{"geometry":{"type":"Point","coordinates":[-93.566700,36.483300]},"type":"Feature","properties":{"hierarchy":["tgn:7021298","tgn:1000001","tgn:7012149","tgn:7029392"],"placetype":["aat:300008680","aat:300006191"],"id":7021298,"name:xx":"Table Rock Lake"}}
>>>>>>> 03f74aca74312dbeaf24d7e61306dd6a786dc3d0
