{
  "id": 2001807,
  "type": "Feature",
  "properties": {
    "tgn:hierarchy":[
        "tgn:2001807",
        "tgn:1000001",
        "tgn:7012149",
        "tgn:7007713",
        "tgn:7029392"
    ],
    "tgn:id":2001807,
    "tgn:name":"Jones",
    "tgn:placetype":[
        "aat:300387145",
        "aat:300000771"
    ]
},
  "bbox": [],
  "geometry": {"coordinates":[-100.6667,43.95],"type":"Point"}
}