{
  "id": 2291391,
  "type": "Feature",
  "properties": {
    "tgn:hierarchy":[
        "tgn:2291391",
        "tgn:7002659",
        "tgn:1000001",
        "tgn:2000009",
        "tgn:7012149",
        "tgn:7029392"
    ],
    "tgn:id":2291391,
    "tgn:name":"Doieg Hill",
    "tgn:placetype":[
        "aat:300008798"
    ]
},
  "bbox": [],
  "geometry": {"coordinates":[-85.4833,33.9833],"type":"Point"}
}