{
  "id": 7142700,
  "type": "Feature",
  "properties": {
    "tgn:hierarchy":[
        "tgn:7142700",
        "tgn:1000003",
        "tgn:7003688",
        "tgn:7000084",
        "tgn:7029392"
    ],
    "tgn:id":7142700,
    "tgn:name":"Ludwigsburg",
    "tgn:placetype":[
        "aat:300000206"
    ]
},
  "bbox": [],
  "geometry": {"coordinates":[9.933333,54.516667],"type":"Point"}
}