{
  "id": 7224172,
  "type": "Feature",
  "properties": {
    "tgn:hierarchy":[
        "tgn:7224172",
        "tgn:4003773",
        "tgn:7001395",
        "tgn:1000003",
        "tgn:1000074",
        "tgn:7029392"
    ],
    "tgn:id":7224172,
    "tgn:name":"N\u00f3stimon",
    "tgn:placetype":[
        "aat:300008347"
    ]
},
  "bbox": [],
  "geometry": {"coordinates":[21.733333,38.866667],"type":"Point"}
}