{
  "id": 2481485,
  "type": "Feature",
  "properties": {
    "tgn:hierarchy":[
        "tgn:2481485",
        "tgn:1000001",
        "tgn:1002714",
        "tgn:7012149",
        "tgn:7007159",
        "tgn:7029392"
    ],
    "tgn:id":2481485,
    "tgn:name":"Lamphere Hill",
    "tgn:placetype":[
        "aat:300008798"
    ]
},
  "bbox": [],
  "geometry": {"coordinates":[-72.1333,41.3167],"type":"Point"}
}