{
  "id": 1044046,
  "type": "Feature",
  "properties": {
    "tgn:hierarchy":[
        "tgn:1044046",
        "tgn:1003444",
        "tgn:1000003",
        "tgn:7003241",
        "tgn:1000080",
        "tgn:7029392"
    ],
    "tgn:id":1044046,
    "tgn:name":"Castelmauro",
    "tgn:placetype":[
        "aat:300008347"
    ]
},
  "bbox": [],
  "geometry": {"coordinates":[14.716667,41.833333],"type":"Point"}
}