{
  "id": 2003834,
  "type": "Feature",
  "properties": {
    "tgn:hierarchy":[
        "tgn:2003834",
        "tgn:7002659",
        "tgn:1000001",
        "tgn:7012149",
        "tgn:2000053",
        "tgn:7029392"
    ],
    "tgn:id":2003834,
    "tgn:name":"Hickory",
    "tgn:placetype":[
        "aat:300008347",
        "aat:300387210"
    ]
},
  "bbox": [],
  "geometry": {"coordinates":[-88.05,33.15],"type":"Point"}
}