{
  "id": 2248698,
  "type": "Feature",
  "properties": {
    "tgn:hierarchy":[
        "tgn:2248698",
        "tgn:1000001",
        "tgn:7012149",
        "tgn:2001161",
        "tgn:7007522",
        "tgn:7029392"
    ],
    "tgn:id":2248698,
    "tgn:name":"Cold Springs",
    "tgn:placetype":[
        "aat:300008347"
    ]
},
  "bbox": [],
  "geometry": {"coordinates":[-90.9833,33.4667],"type":"Point"}
}