{
  "id": 2174159,
  "type": "Feature",
  "properties": {
    "tgn:hierarchy":[
        "tgn:2174159",
        "tgn:1000001",
        "tgn:7012149",
        "tgn:2002371",
        "tgn:7007923",
        "tgn:7029392"
    ],
    "tgn:id":2174159,
    "tgn:name":"Birdseye Mountain",
    "tgn:placetype":[
        "aat:300008798"
    ]
},
  "bbox": [],
  "geometry": {"coordinates":[-108.0833,43.45],"type":"Point"}
}