{
  "id": 2618552,
  "type": "Feature",
  "properties": {
    "tgn:hierarchy":[
        "tgn:2618552",
        "tgn:1000001",
        "tgn:2002148",
        "tgn:7012149",
        "tgn:7007919",
        "tgn:7029392"
    ],
    "tgn:id":2618552,
    "tgn:name":"Right Fork Guess Fork",
    "tgn:placetype":[
        "aat:300008699"
    ]
},
  "bbox": [],
  "geometry": {"coordinates":[-81.9167,37.3833],"type":"Point"}
}