{
  "id": 7099344,
  "type": "Feature",
  "properties": {
    "tgn:hierarchy":[
        "tgn:7099344",
        "tgn:7003692",
        "tgn:1000003",
        "tgn:7000084",
        "tgn:7029392"
    ],
    "tgn:id":7099344,
    "tgn:name":"Sommerberg",
    "tgn:placetype":[
        "aat:300008347"
    ]
},
  "bbox": [],
  "geometry": {"coordinates":[9.766667,49.25],"type":"Point"}
}