{
  "id": 7099361,
  "type": "Feature",
  "properties": {
    "tgn:hierarchy":[
        "tgn:7099361",
        "tgn:1000003",
        "tgn:7003676",
        "tgn:7000084",
        "tgn:7029392"
    ],
    "tgn:id":7099361,
    "tgn:name":"Sietwende",
    "tgn:placetype":[
        "aat:300008347"
    ]
},
  "bbox": [],
  "geometry": {"coordinates":[9.316667,53.716667],"type":"Point"}
}