{
  "id": 2240476,
  "type": "Feature",
  "properties": {
    "tgn:hierarchy":[
        "tgn:2240476",
        "tgn:1000001",
        "tgn:2000922",
        "tgn:7012149",
        "tgn:7007515",
        "tgn:7029392"
    ],
    "tgn:id":2240476,
    "tgn:name":"City Point",
    "tgn:placetype":[
        "aat:300008850"
    ]
},
  "bbox": [],
  "geometry": {"coordinates":[-68.4333,44.15],"type":"Point"}
}