{
  "id": 2536919,
  "type": "Feature",
  "properties": {
    "tgn:hierarchy":[
        "tgn:2536919",
        "tgn:1000001",
        "tgn:7012149",
        "tgn:7007157",
        "tgn:1002894",
        "tgn:7029392"
    ],
    "tgn:id":2536919,
    "tgn:name":"Needle Point",
    "tgn:placetype":[
        "aat:300008798"
    ]
},
  "bbox": [],
  "geometry": {"coordinates":[-120.7833,39.6667],"type":"Point"}
}