{
  "id": 2474108,
  "type": "Feature",
  "properties": {
    "tgn:hierarchy":[
        "tgn:2474108",
        "tgn:1000001",
        "tgn:7012149",
        "tgn:7007255",
        "tgn:7029392"
    ],
    "tgn:id":2474108,
    "tgn:name":"Lower Laurel Creek",
    "tgn:placetype":[
        "aat:300008706"
    ]
},
  "bbox": [],
  "geometry": {"coordinates":[-82.8667,37.9167],"type":"Point"}
}