{
  "id": 2780567,
  "type": "Feature",
  "properties": {
    "tgn:hierarchy":[
        "tgn:2780567",
        "tgn:1000001",
        "tgn:2001266",
        "tgn:7012149",
        "tgn:7007524",
        "tgn:7029392"
    ],
    "tgn:id":2780567,
    "tgn:name":"Wood Gulch",
    "tgn:placetype":[
        "aat:300008761"
    ]
},
  "bbox": [],
  "geometry": {"coordinates":[-111.05,47.0667],"type":"Point"}
}