{
  "id": 2008728,
  "type": "Feature",
  "properties": {
    "tgn:hierarchy":[
        "tgn:2008728",
        "tgn:1000001",
        "tgn:7016172",
        "tgn:7012149",
        "tgn:2000132",
        "tgn:7029392"
    ],
    "tgn:id":2008728,
    "tgn:name":"Light",
    "tgn:placetype":[
        "aat:300008347"
    ]
},
  "bbox": [],
  "geometry": {"coordinates":[-90.7333,36.0667],"type":"Point"}
}