{
  "id": 2293597,
  "type": "Feature",
  "properties": {
    "tgn:hierarchy":[
        "tgn:2293597",
        "tgn:1000001",
        "tgn:2002367",
        "tgn:7012149",
        "tgn:7007923",
        "tgn:7029392"
    ],
    "tgn:id":2293597,
    "tgn:name":"Double Tanks Draw",
    "tgn:placetype":[
        "aat:300008761"
    ]
},
  "bbox": [],
  "geometry": {"coordinates":[-105.8667,44.0833],"type":"Point"}
}