{
  "id": 2236165,
  "type": "Feature",
  "properties": {
    "tgn:hierarchy":[
        "tgn:2236165",
        "tgn:7006450",
        "tgn:1000001",
        "tgn:7019698",
        "tgn:7012149",
        "tgn:7029392"
    ],
    "tgn:id":2236165,
    "tgn:name":"Chichantna Creek",
    "tgn:placetype":[
        "aat:300008706"
    ]
},
  "bbox": [],
  "geometry": {"coordinates":[-151.6333,61.2833],"type":"Point"}
}