<<<<<<< HEAD
{
  "id": 7020125,
  "type": "Feature",
  "properties": {
    "tgn:hierarchy":[
        "tgn:7020125",
        "tgn:1000001",
        "tgn:2001801",
        "tgn:7012149",
        "tgn:7007713",
        "tgn:7029392"
    ],
    "tgn:id":7020125,
    "tgn:name":"Deep Draw",
    "tgn:placetype":[
        "aat:300008761"
    ]
},
  "bbox": [],
  "geometry": {"coordinates":[-103.1833,45.35],"type":"Point"}
}
=======
{"geometry":{"type":"Point","coordinates":[-103.183300,45.350000]},"type":"Feature","properties":{"hierarchy":["tgn:7020125","tgn:1000001","tgn:2001801","tgn:7012149","tgn:7007713","tgn:7029392"],"placetype":["aat:300008761"],"id":7020125,"name:xx":"Deep Draw"}}
>>>>>>> 03f74aca74312dbeaf24d7e61306dd6a786dc3d0
