<<<<<<< HEAD
{
  "id": 2257936,
  "type": "Feature",
  "properties": {
    "tgn:hierarchy":[
        "tgn:2257936",
        "tgn:1000001",
        "tgn:7012149",
        "tgn:2000930",
        "tgn:7007515",
        "tgn:7029392"
    ],
    "tgn:id":2257936,
    "tgn:name":"Corson Brook",
    "tgn:placetype":[
        "aat:300008699"
    ]
},
  "bbox": [],
  "geometry": {"coordinates":[-69.7,45.0167],"type":"Point"}
}
=======
{"geometry":{"type":"Point","coordinates":[-69.700000,45.016700]},"type":"Feature","properties":{"hierarchy":["tgn:2257936","tgn:1000001","tgn:7012149","tgn:2000930","tgn:7007515","tgn:7029392"],"placetype":["aat:300008699"],"id":2257936,"name:xx":"Corson Brook"}}
>>>>>>> 03f74aca74312dbeaf24d7e61306dd6a786dc3d0
