{
  "id": 7341786,
  "type": "Feature",
  "properties": {
    "tgn:hierarchy":[
        "tgn:7341786",
        "tgn:7002813",
        "tgn:7002758",
        "tgn:1000003",
        "tgn:1000095",
        "tgn:7029392"
    ],
    "tgn:id":7341786,
    "tgn:name":"Bermeja, Punta",
    "tgn:placetype":[
        "aat:300386846"
    ]
},
  "bbox": [],
  "geometry": {"coordinates":[-6.284444,36.606944],"type":"Point"}
}