<<<<<<< HEAD
{
  "id": 7054659,
  "type": "Feature",
  "properties": {
    "tgn:hierarchy":[
        "tgn:7054659",
        "tgn:7003167",
        "tgn:1000003",
        "tgn:7009760",
        "tgn:1000080",
        "tgn:7029392"
    ],
    "tgn:id":7054659,
    "tgn:name":"Ponte Buggianese",
    "tgn:placetype":[
        "aat:300008347"
    ]
},
  "bbox": [],
  "geometry": {"coordinates":[10.75,43.833333],"type":"Point"}
}
=======
{"geometry":{"type":"Point","coordinates":[10.750000,43.833333]},"type":"Feature","properties":{"hierarchy":["tgn:7054659","tgn:7003167","tgn:1000003","tgn:7009760","tgn:1000080","tgn:7029392"],"placetype":["aat:300008347"],"id":7054659,"name:xx":"Ponte Buggianese"}}
>>>>>>> 03f74aca74312dbeaf24d7e61306dd6a786dc3d0
