<<<<<<< HEAD
{
  "id": 7379427,
  "type": "Feature",
  "properties": {
    "tgn:hierarchy":[
        "tgn:7379427",
        "tgn:1000001",
        "tgn:7005589",
        "tgn:7005560",
        "tgn:7029392"
    ],
    "tgn:id":7379427,
    "tgn:name":"Rancho Los Tecolotes",
    "tgn:placetype":[
        "aat:300000241"
    ]
},
  "bbox": [],
  "geometry": {"coordinates":[-99.863056,24.946389],"type":"Point"}
}
=======
{"geometry":{"type":"Point","coordinates":[-99.863056,24.946389]},"type":"Feature","properties":{"hierarchy":["tgn:7379427","tgn:1000001","tgn:7005589","tgn:7005560","tgn:7029392"],"placetype":["aat:300000241"],"id":7379427,"name:xx":"Rancho Los Tecolotes"}}
>>>>>>> 03f74aca74312dbeaf24d7e61306dd6a786dc3d0
