{
  "id": 1097968,
  "type": "Feature",
  "properties": {
    "tgn:hierarchy":[
        "tgn:1097968",
        "tgn:7000490",
        "tgn:1000006",
        "tgn:7001834",
        "tgn:7029392"
    ],
    "tgn:id":1097968,
    "tgn:name":"Point Samson",
    "tgn:placetype":[
        "aat:300008347"
    ]
},
  "bbox": [],
  "geometry": {"coordinates":[117.1667,-20.7667],"type":"Point"}
}