{
  "id": 1073436,
  "type": "Feature",
  "properties": {
    "tgn:hierarchy":[
        "tgn:1073436",
        "tgn:1000004",
        "tgn:7002081",
        "tgn:1000111",
        "tgn:7029392"
    ],
    "tgn:id":1073436,
    "tgn:name":"Yanweigang",
    "tgn:placetype":[
        "aat:300008347"
    ]
},
  "bbox": [],
  "geometry": {"coordinates":[119.7667,34.4667],"type":"Point"}
}