{
  "id": 2242044,
  "type": "Feature",
  "properties": {
    "tgn:hierarchy":[
        "tgn:2242044",
        "tgn:1000001",
        "tgn:1002328",
        "tgn:7012149",
        "tgn:7007568",
        "tgn:7029392"
    ],
    "tgn:id":2242044,
    "tgn:name":"Clay Hill",
    "tgn:placetype":[
        "aat:300008798"
    ]
},
  "bbox": [],
  "geometry": {"coordinates":[-74.4333,42.3167],"type":"Point"}
}