<<<<<<< HEAD
{
  "id": 2252153,
  "type": "Feature",
  "properties": {
    "tgn:hierarchy":[
        "tgn:2252153",
        "tgn:1000001",
        "tgn:7012149",
        "tgn:1002553",
        "tgn:7007920",
        "tgn:7029392"
    ],
    "tgn:id":2252153,
    "tgn:name":"Cone Mountain",
    "tgn:placetype":[
        "aat:300008798"
    ]
},
  "bbox": [],
  "geometry": {"coordinates":[-121.1333,47.45],"type":"Point"}
}
=======
{"geometry":{"type":"Point","coordinates":[-121.133300,47.450000]},"type":"Feature","properties":{"hierarchy":["tgn:2252153","tgn:1000001","tgn:7012149","tgn:1002553","tgn:7007920","tgn:7029392"],"placetype":["aat:300008798"],"id":2252153,"name:xx":"Cone Mountain"}}
>>>>>>> 03f74aca74312dbeaf24d7e61306dd6a786dc3d0
