{
  "id": 2252153,
  "type": "Feature",
  "properties": {
    "tgn:hierarchy":[
        "tgn:2252153",
        "tgn:1000001",
        "tgn:7012149",
        "tgn:1002553",
        "tgn:7007920",
        "tgn:7029392"
    ],
    "tgn:id":2252153,
    "tgn:name":"Cone Mountain",
    "tgn:placetype":[
        "aat:300008798"
    ]
},
  "bbox": [],
  "geometry": {"coordinates":[-121.1333,47.45],"type":"Point"}
}