{
  "id": 2566338,
  "type": "Feature",
  "properties": {
    "tgn:hierarchy":[
        "tgn:2566338",
        "tgn:1000001",
        "tgn:7012149",
        "tgn:2001456",
        "tgn:7007566",
        "tgn:7029392"
    ],
    "tgn:id":2566338,
    "tgn:name":"Palo Blanco Spring",
    "tgn:placetype":[
        "aat:300008697"
    ]
},
  "bbox": [],
  "geometry": {"coordinates":[-107.3167,34.3667],"type":"Point"}
}