{
  "id": 2481580,
  "type": "Feature",
  "properties": {
    "tgn:hierarchy":[
        "tgn:2481580",
        "tgn:1000001",
        "tgn:7012149",
        "tgn:2001244",
        "tgn:7007523",
        "tgn:7029392"
    ],
    "tgn:id":2481580,
    "tgn:name":"Lancaster City Lake",
    "tgn:placetype":[
        "aat:300006191"
    ]
},
  "bbox": [],
  "geometry": {"coordinates":[-92.5333,40.5167],"type":"Point"}
}