{
  "id": 2348309,
  "type": "Feature",
  "properties": {
    "tgn:hierarchy":[
        "tgn:2348309",
        "tgn:1000001",
        "tgn:7012149",
        "tgn:2001711",
        "tgn:7007708",
        "tgn:7029392"
    ],
    "tgn:id":2348309,
    "tgn:name":"Geyser Spring",
    "tgn:placetype":[
        "aat:300008697"
    ]
},
  "bbox": [],
  "geometry": {"coordinates":[-122.3167,42.7333],"type":"Point"}
}