{
  "id": 1018326,
  "type": "Feature",
  "properties": {
    "tgn:hierarchy":[
        "tgn:1018326",
        "tgn:7005583",
        "tgn:1000001",
        "tgn:7005560",
        "tgn:7029392"
    ],
    "tgn:id":1018326,
    "tgn:name":"Santiago Papasquiaro",
    "tgn:placetype":[
        "aat:300008347",
        "aat:300008389",
        "aat:300005517",
        "aat:300265612"
    ]
},
  "bbox": [],
  "geometry": {"coordinates":[-105.416667,25.05],"type":"Point"}
}