{
  "id": 1069301,
  "type": "Feature",
  "properties": {
    "tgn:hierarchy":[
        "tgn:1069301",
        "tgn:1000004",
        "tgn:7002079",
        "tgn:1000111",
        "tgn:7029392"
    ],
    "tgn:id":1069301,
    "tgn:name":"Jinggang",
    "tgn:placetype":[
        "aat:300008347"
    ]
},
  "bbox": [],
  "geometry": {"coordinates":[112.7667,28.4667],"type":"Point"}
}