{
  "id": 7472282,
  "type": "Feature",
  "properties": {
    "tgn:hierarchy":[
        "tgn:7472282",
        "tgn:1000004",
        "tgn:7491221",
        "tgn:1000141",
        "tgn:7029392"
    ],
    "tgn:id":7472282,
    "tgn:name":"Zuoguluowei",
    "tgn:placetype":[
        "aat:300008798"
    ]
},
  "bbox": [],
  "geometry": {"coordinates":[120.766667,22.45],"type":"Point"}
}