<<<<<<< HEAD
{
  "id": 7472282,
  "type": "Feature",
  "properties": {
    "tgn:hierarchy":[
        "tgn:7472282",
        "tgn:1000004",
        "tgn:7491221",
        "tgn:1000141",
        "tgn:7029392"
    ],
    "tgn:id":7472282,
    "tgn:name":"Zuoguluowei",
    "tgn:placetype":[
        "aat:300008798"
    ]
},
  "bbox": [],
  "geometry": {"coordinates":[120.766667,22.45],"type":"Point"}
}
=======
{"geometry":{"type":"Point","coordinates":[120.766667,22.450000]},"type":"Feature","properties":{"hierarchy":["tgn:7472282","tgn:1000004","tgn:7491221","tgn:1000141","tgn:7029392"],"placetype":["aat:300008798"],"id":7472282,"name:xx":"Zuoguluowei"}}
>>>>>>> 03f74aca74312dbeaf24d7e61306dd6a786dc3d0
