<<<<<<< HEAD
{
  "id": 2766900,
  "type": "Feature",
  "properties": {
    "tgn:hierarchy":[
        "tgn:2766900",
        "tgn:1000001",
        "tgn:7012149",
        "tgn:2001437",
        "tgn:7007566",
        "tgn:7029392"
    ],
    "tgn:id":2766900,
    "tgn:name":"White Pinnacle",
    "tgn:placetype":[
        "aat:300008798"
    ]
},
  "bbox": [],
  "geometry": {"coordinates":[-108.4333,33.1833],"type":"Point"}
}
=======
{"geometry":{"type":"Point","coordinates":[-108.433300,33.183300]},"type":"Feature","properties":{"hierarchy":["tgn:2766900","tgn:1000001","tgn:7012149","tgn:2001437","tgn:7007566","tgn:7029392"],"placetype":["aat:300008798"],"id":2766900,"name:xx":"White Pinnacle"}}
>>>>>>> 03f74aca74312dbeaf24d7e61306dd6a786dc3d0
