<<<<<<< HEAD
{
  "id": 2251798,
  "type": "Feature",
  "properties": {
    "tgn:hierarchy":[
        "tgn:2251798",
        "tgn:1000001",
        "tgn:7022245",
        "tgn:7012149",
        "tgn:7007526",
        "tgn:7029392"
    ],
    "tgn:id":2251798,
    "tgn:name":"Comstock Extension Mine",
    "tgn:placetype":[
        "aat:300000390"
    ]
},
  "bbox": [],
  "geometry": {"coordinates":[-119.75,39.2],"type":"Point"}
}
=======
{"geometry":{"type":"Point","coordinates":[-119.750000,39.200000]},"type":"Feature","properties":{"hierarchy":["tgn:2251798","tgn:1000001","tgn:7022245","tgn:7012149","tgn:7007526","tgn:7029392"],"placetype":["aat:300000390"],"id":2251798,"name:xx":"Comstock Extension Mine"}}
>>>>>>> 03f74aca74312dbeaf24d7e61306dd6a786dc3d0
