{
  "id": 2137264,
  "type": "Feature",
  "properties": {
    "tgn:hierarchy":[
        "tgn:2137264",
        "tgn:1000001",
        "tgn:7012149",
        "tgn:1002862",
        "tgn:7007920",
        "tgn:7029392"
    ],
    "tgn:id":2137264,
    "tgn:name":"Armitage Island",
    "tgn:placetype":[
        "aat:300008791"
    ]
},
  "bbox": [],
  "geometry": {"coordinates":[-122.7833,48.5333],"type":"Point"}
}