{
  "id": 1092943,
  "type": "Feature",
  "properties": {
    "tgn:hierarchy":[
        "tgn:1092943",
        "tgn:7001242",
        "tgn:7017582",
        "tgn:1000193",
        "tgn:7029392"
    ],
    "tgn:id":1092943,
    "tgn:name":"Calvinia",
    "tgn:placetype":[
        "aat:300008347"
    ]
},
  "bbox": [],
  "geometry": {"coordinates":[19.7833,-31.4167],"type":"Point"}
}