{
  "id": 7014693,
  "type": "Feature",
  "properties": {
    "tgn:hierarchy":[
        "tgn:7014693",
        "tgn:1000001",
        "tgn:2000924",
        "tgn:7012149",
        "tgn:1009647",
        "tgn:7007515",
        "tgn:7029392"
    ],
    "tgn:id":7014693,
    "tgn:name":"Vinalhaven",
    "tgn:placetype":[
        "aat:300008347"
    ]
},
  "bbox": [],
  "geometry": {"coordinates":[-68.8167,44.0333],"type":"Point"}
}