{
  "id": 2762377,
  "type": "Feature",
  "properties": {
    "tgn:hierarchy":[
        "tgn:2762377",
        "tgn:1000001",
        "tgn:7012149",
        "tgn:7007254",
        "tgn:7029392"
    ],
    "tgn:id":2762377,
    "tgn:name":"West Turkey Creek",
    "tgn:placetype":[
        "aat:300008706"
    ]
},
  "bbox": [],
  "geometry": {"coordinates":[-97.2333,38.5833],"type":"Point"}
}