<<<<<<< HEAD
{
  "id": 2762377,
  "type": "Feature",
  "properties": {
    "tgn:hierarchy":[
        "tgn:2762377",
        "tgn:1000001",
        "tgn:7012149",
        "tgn:7007254",
        "tgn:7029392"
    ],
    "tgn:id":2762377,
    "tgn:name":"West Turkey Creek",
    "tgn:placetype":[
        "aat:300008706"
    ]
},
  "bbox": [],
  "geometry": {"coordinates":[-97.2333,38.5833],"type":"Point"}
}
=======
{"geometry":{"type":"Point","coordinates":[-97.233300,38.583300]},"type":"Feature","properties":{"hierarchy":["tgn:2762377","tgn:1000001","tgn:7012149","tgn:7007254","tgn:7029392"],"placetype":["aat:300008706"],"id":2762377,"name:xx":"West Turkey Creek"}}
>>>>>>> 03f74aca74312dbeaf24d7e61306dd6a786dc3d0
