<<<<<<< HEAD
{
  "id": 2400033,
  "type": "Feature",
  "properties": {
    "tgn:hierarchy":[
        "tgn:2400033",
        "tgn:1000001",
        "tgn:2000198",
        "tgn:7012149",
        "tgn:7007158",
        "tgn:7029392"
    ],
    "tgn:id":2400033,
    "tgn:name":"Horse Creek",
    "tgn:placetype":[
        "aat:300008706"
    ]
},
  "bbox": [],
  "geometry": {"coordinates":[-105.55,40.2333],"type":"Point"}
}
=======
{"geometry":{"type":"Point","coordinates":[-105.550000,40.233300]},"type":"Feature","properties":{"hierarchy":["tgn:2400033","tgn:1000001","tgn:2000198","tgn:7012149","tgn:7007158","tgn:7029392"],"placetype":["aat:300008706"],"id":2400033,"name:xx":"Horse Creek"}}
>>>>>>> 03f74aca74312dbeaf24d7e61306dd6a786dc3d0
