{
  "id": 1027598,
  "type": "Feature",
  "properties": {
    "tgn:hierarchy":[
        "tgn:1027598",
        "tgn:7593919",
        "tgn:1000003",
        "tgn:1001780",
        "tgn:7029392"
    ],
    "tgn:id":1027598,
    "tgn:name":"Trhomn\u00e9",
    "tgn:placetype":[
        "aat:300008347"
    ]
},
  "bbox": [],
  "geometry": {"coordinates":[13.0833,49.95],"type":"Point"}
}