{
  "id": 1095076,
  "type": "Feature",
  "properties": {
    "tgn:hierarchy":[
        "tgn:1095076",
        "tgn:7001242",
        "tgn:1000948",
        "tgn:1000206",
        "tgn:7029392"
    ],
    "tgn:id":1095076,
    "tgn:name":"Masindi",
    "tgn:placetype":[
        "aat:300008347"
    ]
},
  "bbox": [],
  "geometry": {"coordinates":[31.75,1.6833],"type":"Point"}
}