{
  "id": 7424560,
  "type": "Feature",
  "properties": {
    "tgn:hierarchy":[
        "tgn:7424560",
        "tgn:1000001",
        "tgn:7005597",
        "tgn:7005560",
        "tgn:7029392"
    ],
    "tgn:id":7424560,
    "tgn:name":"Plan de Ayala",
    "tgn:placetype":[
        "aat:300008347"
    ]
},
  "bbox": [],
  "geometry": {"coordinates":[-99.116667,24.05],"type":"Point"}
}