{
  "id": 2500365,
  "type": "Feature",
  "properties": {
    "tgn:hierarchy":[
        "tgn:2500365",
        "tgn:1000001",
        "tgn:7016172",
        "tgn:7012149",
        "tgn:2000173",
        "tgn:7029392"
    ],
    "tgn:id":2500365,
    "tgn:name":"McDermon Hollow",
    "tgn:placetype":[
        "aat:300008761"
    ]
},
  "bbox": [],
  "geometry": {"coordinates":[-91.8833,35.8333],"type":"Point"}
}