{
  "id": 1033960,
  "type": "Feature",
  "properties": {
    "tgn:hierarchy":[
        "tgn:1033960",
        "tgn:1000003",
        "tgn:7002888",
        "tgn:1000070",
        "tgn:7029392"
    ],
    "tgn:id":1033960,
    "tgn:name":"Lemberg",
    "tgn:placetype":[
        "aat:300008347"
    ]
},
  "bbox": [],
  "geometry": {"coordinates":[7.3833,49.0167],"type":"Point"}
}