{
  "id": 7112998,
  "type": "Feature",
  "properties": {
    "tgn:hierarchy":[
        "tgn:7112998",
        "tgn:1000003",
        "tgn:7003676",
        "tgn:7000084",
        "tgn:7029392"
    ],
    "tgn:id":7112998,
    "tgn:name":"Riethe",
    "tgn:placetype":[
        "aat:300008699"
    ]
},
  "bbox": [],
  "geometry": {"coordinates":[10.383333,53.35],"type":"Point"}
}