{
  "id": 7291043,
  "type": "Feature",
  "properties": {
    "tgn:hierarchy":[
        "tgn:7291043",
        "tgn:1001695",
        "tgn:1000049",
        "tgn:1000002",
        "tgn:7029392"
    ],
    "tgn:id":7291043,
    "tgn:name":"Cueva Negra, Punta",
    "tgn:placetype":[
        "aat:300386846"
    ]
},
  "bbox": [],
  "geometry": {"coordinates":[-71.983333,-34.316667],"type":"Point"}
}