{
  "id": 2142283,
  "type": "Feature",
  "properties": {
    "tgn:hierarchy":[
        "tgn:2142283",
        "tgn:1000001",
        "tgn:7012149",
        "tgn:1002591",
        "tgn:7007255",
        "tgn:7029392"
    ],
    "tgn:id":2142283,
    "tgn:name":"Backbone Hollow",
    "tgn:placetype":[
        "aat:300008761"
    ]
},
  "bbox": [],
  "geometry": {"coordinates":[-83.2667,38.55],"type":"Point"}
}