{
  "id": 1094892,
  "type": "Feature",
  "properties": {
    "tgn:hierarchy":[
        "tgn:1094892",
        "tgn:7000580",
        "tgn:7001242",
        "tgn:7016577",
        "tgn:7029392"
    ],
    "tgn:id":1094892,
    "tgn:name":"Niamtougou",
    "tgn:placetype":[
        "aat:300008347"
    ]
},
  "bbox": [],
  "geometry": {"coordinates":[1.1333,9.8333],"type":"Point"}
}