{
  "id": 7285334,
  "type": "Feature",
  "properties": {
    "tgn:hierarchy":[
        "tgn:7285334",
        "tgn:1001705",
        "tgn:1000049",
        "tgn:1000002",
        "tgn:7029392"
    ],
    "tgn:id":7285334,
    "tgn:name":"Pocillas",
    "tgn:placetype":[
        "aat:300008347"
    ]
},
  "bbox": [],
  "geometry": {"coordinates":[-72.233333,-36.166667],"type":"Point"}
}