{
  "id": 1089747,
  "type": "Feature",
  "properties": {
    "tgn:hierarchy":[
        "tgn:1089747",
        "tgn:7001242",
        "tgn:1001537",
        "tgn:7000489",
        "tgn:7029392"
    ],
    "tgn:id":1089747,
    "tgn:name":"Bogol Manya",
    "tgn:placetype":[
        "aat:300008347"
    ]
},
  "bbox": [],
  "geometry": {"coordinates":[41.4833,4.5667],"type":"Point"}
}