{
  "id": 7592256,
  "type": "Feature",
  "properties": {
    "tgn:hierarchy":[
        "tgn:7592256",
        "tgn:1000004",
        "tgn:7000198",
        "tgn:7000799",
        "tgn:7029392"
    ],
    "tgn:id":7592256,
    "tgn:name:en":"Manthal",
    "tgn:placetype":[
        "aat:300008347"
    ]
},
  "bbox": [],
  "geometry": {"coordinates":[74.965405,32.950452],"type":"Point"}
}