{
  "id": 7340478,
  "type": "Feature",
  "properties": {
    "tgn:hierarchy":[
        "tgn:7340478",
        "tgn:7002815",
        "tgn:1000003",
        "tgn:7002793",
        "tgn:1000095",
        "tgn:7029392"
    ],
    "tgn:id":7340478,
    "tgn:name":"Cortes de Arenoso",
    "tgn:placetype":[
        "aat:300008347"
    ]
},
  "bbox": [],
  "geometry": {"coordinates":[-0.533333,40.183333],"type":"Point"}
}