<<<<<<< HEAD
{
  "id": 2404935,
  "type": "Feature",
  "properties": {
    "tgn:hierarchy":[
        "tgn:2404935",
        "tgn:7002659",
        "tgn:1000001",
        "tgn:2000019",
        "tgn:7012149",
        "tgn:7029392"
    ],
    "tgn:id":2404935,
    "tgn:name":"Hudgens Pond",
    "tgn:placetype":[
        "aat:300006191"
    ]
},
  "bbox": [],
  "geometry": {"coordinates":[-86.2667,31.2],"type":"Point"}
}
=======
{"geometry":{"type":"Point","coordinates":[-86.266700,31.200000]},"type":"Feature","properties":{"hierarchy":["tgn:2404935","tgn:7002659","tgn:1000001","tgn:2000019","tgn:7012149","tgn:7029392"],"placetype":["aat:300006191"],"id":2404935,"name:xx":"Hudgens Pond"}}
>>>>>>> 03f74aca74312dbeaf24d7e61306dd6a786dc3d0
