{
  "id": 2142843,
  "type": "Feature",
  "properties": {
    "tgn:hierarchy":[
        "tgn:2142843",
        "tgn:2001422",
        "tgn:1000001",
        "tgn:7012149",
        "tgn:7007564",
        "tgn:7029392"
    ],
    "tgn:id":2142843,
    "tgn:name":"Badger Pond",
    "tgn:placetype":[
        "aat:300008680"
    ]
},
  "bbox": [],
  "geometry": {"coordinates":[-71.4667,43.45],"type":"Point"}
}