<<<<<<< HEAD
{
  "id": 2763918,
  "type": "Feature",
  "properties": {
    "tgn:hierarchy":[
        "tgn:2763918",
        "tgn:1000001",
        "tgn:7012149",
        "tgn:2002381",
        "tgn:7007923",
        "tgn:7029392"
    ],
    "tgn:id":2763918,
    "tgn:name":"Whedon Draw",
    "tgn:placetype":[
        "aat:300008761"
    ]
},
  "bbox": [],
  "geometry": {"coordinates":[-106.3167,44.85],"type":"Point"}
}
=======
{"geometry":{"type":"Point","coordinates":[-106.316700,44.850000]},"type":"Feature","properties":{"hierarchy":["tgn:2763918","tgn:1000001","tgn:7012149","tgn:2002381","tgn:7007923","tgn:7029392"],"placetype":["aat:300008761"],"id":2763918,"name:xx":"Whedon Draw"}}
>>>>>>> 03f74aca74312dbeaf24d7e61306dd6a786dc3d0
