{
  "id": 2513354,
  "type": "Feature",
  "properties": {
    "tgn:hierarchy":[
        "tgn:2513354",
        "tgn:1000001",
        "tgn:7016172",
        "tgn:7012149",
        "tgn:2000176",
        "tgn:7029392"
    ],
    "tgn:id":2513354,
    "tgn:name":"Mill Hollow",
    "tgn:placetype":[
        "aat:300008761"
    ]
},
  "bbox": [],
  "geometry": {"coordinates":[-93.9667,36.1167],"type":"Point"}
}