{
  "id": 2167139,
  "type": "Feature",
  "properties": {
    "tgn:hierarchy":[
        "tgn:2167139",
        "tgn:1002169",
        "tgn:1000001",
        "tgn:7012149",
        "tgn:7007255",
        "tgn:7029392"
    ],
    "tgn:id":2167139,
    "tgn:name":"Big Cave Run",
    "tgn:placetype":[
        "aat:300008699"
    ]
},
  "bbox": [],
  "geometry": {"coordinates":[-83.55,38.05],"type":"Point"}
}