{
  "id": 7569417,
  "type": "Feature",
  "properties": {
    "tgn:hierarchy":[
        "tgn:7569417",
        "tgn:1000004",
        "tgn:7000198",
        "tgn:7016694",
        "tgn:7029392"
    ],
    "tgn:id":7569417,
    "tgn:name:en":"Chattam Buru",
    "tgn:placetype":[
        "aat:300008777"
    ]
},
  "bbox": [],
  "geometry": {"coordinates":[86.546107,21.983926],"type":"Point"}
}