{
  "id": 1133394,
  "type": "Feature",
  "properties": {
    "tgn:hierarchy":[
        "tgn:1133394",
        "tgn:1000001",
        "tgn:2124001",
        "tgn:7012149",
        "tgn:7007516",
        "tgn:7029392"
    ],
    "tgn:id":1133394,
    "tgn:name":"Henson Creek",
    "tgn:placetype":[
        "aat:300008706"
    ]
},
  "bbox": [],
  "geometry": {"coordinates":[-76.85,38.8167],"type":"Point"}
}