{
  "id": 7413348,
  "type": "Feature",
  "properties": {
    "tgn:hierarchy":[
        "tgn:7413348",
        "tgn:7005587",
        "tgn:1000001",
        "tgn:7005560",
        "tgn:7029392"
    ],
    "tgn:id":7413348,
    "tgn:name:es":"Xoxafi, Grutas",
    "tgn:placetype":[
        "aat:300008746"
    ]
},
  "bbox": [],
  "geometry": {"coordinates":[-99.025,20.409722],"type":"Point"}
}