{
  "id": 1024967,
  "type": "Feature",
  "properties": {
    "tgn:hierarchy":[
        "tgn:1024967",
        "tgn:1000574",
        "tgn:1000002",
        "tgn:1000058",
        "tgn:7029392"
    ],
    "tgn:id":1024967,
    "tgn:name":"Rosario",
    "tgn:placetype":[
        "aat:300008347"
    ]
},
  "bbox": [],
  "geometry": {"coordinates":[-57.4333,-34.3333],"type":"Point"}
}