{
  "id": 7372030,
  "type": "Feature",
  "properties": {
    "tgn:hierarchy":[
        "tgn:7372030",
        "tgn:1000001",
        "tgn:7005595",
        "tgn:7005560",
        "tgn:7029392"
    ],
    "tgn:id":7372030,
    "tgn:name":"La Nanche",
    "tgn:placetype":[
        "aat:300008347"
    ]
},
  "bbox": [],
  "geometry": {"coordinates":[-107.816667,25.366667],"type":"Point"}
}