{
  "id": 2050918,
  "type": "Feature",
  "properties": {
    "tgn:hierarchy":[
        "tgn:2050918",
        "tgn:1000001",
        "tgn:1002665",
        "tgn:7012149",
        "tgn:7014617",
        "tgn:7007517",
        "tgn:7029392"
    ],
    "tgn:id":2050918,
    "tgn:name":"Kendal Green",
    "tgn:placetype":[
        "aat:300000745"
    ]
},
  "bbox": [],
  "geometry": {"coordinates":[-71.2667,42.3667],"type":"Point"}
}