{
  "id": 2418010,
  "type": "Feature",
  "properties": {
    "tgn:hierarchy":[
        "tgn:2418010",
        "tgn:1000001",
        "tgn:7012149",
        "tgn:2000340",
        "tgn:7007248",
        "tgn:7029392"
    ],
    "tgn:id":2418010,
    "tgn:name":"Jackson Pond",
    "tgn:placetype":[
        "aat:300008680"
    ]
},
  "bbox": [],
  "geometry": {"coordinates":[-85.0667,31.2667],"type":"Point"}
}