{
  "id": 7056137,
  "type": "Feature",
  "properties": {
    "tgn:hierarchy":[
        "tgn:7056137",
        "tgn:7003135",
        "tgn:1000003",
        "tgn:7003080",
        "tgn:1000080",
        "tgn:7029392"
    ],
    "tgn:id":7056137,
    "tgn:name":"Lemmolle",
    "tgn:placetype":[
        "aat:300008347"
    ]
},
  "bbox": [],
  "geometry": {"coordinates":[13.866667,41.616667],"type":"Point"}
}