{
  "id": 2458154,
  "type": "Feature",
  "properties": {
    "tgn:hierarchy":[
        "tgn:2458154",
        "tgn:1000001",
        "tgn:7012149",
        "tgn:2001759",
        "tgn:7007712",
        "tgn:7029392"
    ],
    "tgn:id":2458154,
    "tgn:name":"Little Mountain",
    "tgn:placetype":[
        "aat:300008347"
    ]
},
  "bbox": [],
  "geometry": {"coordinates":[-79.85,34.7833],"type":"Point"}
}