{
  "id": 2589620,
  "type": "Feature",
  "properties": {
    "tgn:hierarchy":[
        "tgn:2589620",
        "tgn:1000001",
        "tgn:7012149",
        "tgn:7007157",
        "tgn:1002972",
        "tgn:7029392"
    ],
    "tgn:id":2589620,
    "tgn:name":"Point Mugu",
    "tgn:placetype":[
        "aat:300008850"
    ]
},
  "bbox": [],
  "geometry": {"coordinates":[-119.05,34.0833],"type":"Point"}
}