{
  "id": 2424381,
  "type": "Feature",
  "properties": {
    "tgn:hierarchy":[
        "tgn:2424381",
        "tgn:1000001",
        "tgn:7012149",
        "tgn:2000928",
        "tgn:7007515",
        "tgn:7029392"
    ],
    "tgn:id":2424381,
    "tgn:name":"Johnson Brook",
    "tgn:placetype":[
        "aat:300008699"
    ]
},
  "bbox": [],
  "geometry": {"coordinates":[-69.3833,45.3333],"type":"Point"}
}