{
  "id": 7308961,
  "type": "Feature",
  "properties": {
    "tgn:hierarchy":[
        "tgn:7308961",
        "tgn:7016598",
        "tgn:1000049",
        "tgn:1000002",
        "tgn:7029392"
    ],
    "tgn:id":7308961,
    "tgn:name":"Mac\u00f3n, Cerros de",
    "tgn:placetype":[
        "aat:300008795"
    ]
},
  "bbox": [],
  "geometry": {"coordinates":[-67.866667,-23.05],"type":"Point"}
}