{
  "id": 2005258,
  "type": "Feature",
  "properties": {
    "tgn:hierarchy":[
        "tgn:2005258",
        "tgn:7002659",
        "tgn:1000001",
        "tgn:7012149",
        "tgn:2000048",
        "tgn:7029392"
    ],
    "tgn:id":2005258,
    "tgn:name":"Semmes",
    "tgn:placetype":[
        "aat:300008347"
    ]
},
  "bbox": [],
  "geometry": {"coordinates":[-88.25,30.7667],"type":"Point"}
}