{
  "id": 7464968,
  "type": "Feature",
  "properties": {
    "tgn:hierarchy":[
        "tgn:7464968",
        "tgn:5000432",
        "tgn:7002444",
        "tgn:1000003",
        "tgn:7008591",
        "tgn:7029392"
    ],
    "tgn:id":7464968,
    "tgn:name:en":"Auchmacoy",
    "tgn:placetype":[
        "aat:300008347"
    ]
},
  "bbox": [],
  "geometry": {"coordinates":[-2.016667,57.366667],"type":"Point"}
}