<<<<<<< HEAD
{
  "id": 2252730,
  "type": "Feature",
  "properties": {
    "tgn:hierarchy":[
        "tgn:2252730",
        "tgn:1000001",
        "tgn:7012149",
        "tgn:2000973",
        "tgn:7007520",
        "tgn:7029392"
    ],
    "tgn:id":2252730,
    "tgn:name":"Conners Point",
    "tgn:placetype":[
        "aat:300008850"
    ]
},
  "bbox": [],
  "geometry": {"coordinates":[-84.35,45.9667],"type":"Point"}
}
=======
{"geometry":{"type":"Point","coordinates":[-84.350000,45.966700]},"type":"Feature","properties":{"hierarchy":["tgn:2252730","tgn:1000001","tgn:7012149","tgn:2000973","tgn:7007520","tgn:7029392"],"placetype":["aat:300008850"],"id":2252730,"name:xx":"Conners Point"}}
>>>>>>> 03f74aca74312dbeaf24d7e61306dd6a786dc3d0
