{
  "id": 2661727,
  "type": "Feature",
  "properties": {
    "tgn:hierarchy":[
        "tgn:2661727",
        "tgn:1000001",
        "tgn:7012149",
        "tgn:2001912",
        "tgn:7007825",
        "tgn:7029392"
    ],
    "tgn:id":2661727,
    "tgn:name":"Shug Mountain",
    "tgn:placetype":[
        "aat:300008798"
    ]
},
  "bbox": [],
  "geometry": {"coordinates":[-84.4333,36.4667],"type":"Point"}
}