<<<<<<< HEAD
{
  "id": 7473678,
  "type": "Feature",
  "properties": {
    "tgn:hierarchy":[
        "tgn:7473678",
        "tgn:1000004",
        "tgn:7490934",
        "tgn:1000141",
        "tgn:7029392"
    ],
    "tgn:id":7473678,
    "tgn:name":"Yingqiu",
    "tgn:placetype":[
        "aat:300387033"
    ]
},
  "bbox": [],
  "geometry": {"coordinates":[120.196944,22.949167],"type":"Point"}
}
=======
{"geometry":{"type":"Point","coordinates":[120.196944,22.949167]},"type":"Feature","properties":{"hierarchy":["tgn:7473678","tgn:1000004","tgn:7490934","tgn:1000141","tgn:7029392"],"placetype":["aat:300387033"],"id":7473678,"name:xx":"Yingqiu"}}
>>>>>>> 03f74aca74312dbeaf24d7e61306dd6a786dc3d0
