{
  "id": 1025735,
  "type": "Feature",
  "properties": {
    "tgn:hierarchy":[
        "tgn:1025735",
        "tgn:7003028",
        "tgn:1000003",
        "tgn:1000062",
        "tgn:7029392"
    ],
    "tgn:id":1025735,
    "tgn:name":"Koglhof",
    "tgn:placetype":[
        "aat:300008347"
    ]
},
  "bbox": [],
  "geometry": {"coordinates":[15.6667,47.3167],"type":"Point"}
}