{
  "id": 2312750,
  "type": "Feature",
  "properties": {
    "tgn:hierarchy":[
        "tgn:2312750",
        "tgn:1000001",
        "tgn:7012149",
        "tgn:2002075",
        "tgn:7007826",
        "tgn:7029392"
    ],
    "tgn:id":2312750,
    "tgn:name":"El Leoncito Tank",
    "tgn:placetype":[
        "aat:300006191"
    ]
},
  "bbox": [],
  "geometry": {"coordinates":[-98.7667,26.5667],"type":"Point"}
}