<<<<<<< HEAD
{
  "id": 7053854,
  "type": "Feature",
  "properties": {
    "tgn:hierarchy":[
        "tgn:7053854",
        "tgn:7009084",
        "tgn:7003001",
        "tgn:1000003",
        "tgn:1000080",
        "tgn:7029392"
    ],
    "tgn:id":7053854,
    "tgn:name":"Portella, Passo della",
    "tgn:placetype":[
        "aat:300259572"
    ]
},
  "bbox": [],
  "geometry": {"coordinates":[13.533333,42.45],"type":"Point"}
}
=======
{"geometry":{"type":"Point","coordinates":[13.533333,42.450000]},"type":"Feature","properties":{"hierarchy":["tgn:7053854","tgn:7009084","tgn:7003001","tgn:1000003","tgn:1000080","tgn:7029392"],"placetype":["aat:300259572"],"id":7053854,"name:xx":"Portella, Passo della"}}
>>>>>>> 03f74aca74312dbeaf24d7e61306dd6a786dc3d0
