{
  "id": 1066080,
  "type": "Feature",
  "properties": {
    "tgn:hierarchy":[
        "tgn:1066080",
        "tgn:7002185",
        "tgn:1000004",
        "tgn:1000108",
        "tgn:7029392"
    ],
    "tgn:id":1066080,
    "tgn:name":"Konglu",
    "tgn:placetype":[
        "aat:300008347"
    ]
},
  "bbox": [],
  "geometry": {"coordinates":[97.9833,27.2333],"type":"Point"}
}