{
  "id": 7229585,
  "type": "Feature",
  "properties": {
    "tgn:hierarchy":[
        "tgn:7229585",
        "tgn:7002748",
        "tgn:7001399",
        "tgn:1000003",
        "tgn:1000074",
        "tgn:7029392"
    ],
    "tgn:id":7229585,
    "tgn:name":"Meg\u00e1lou R\u00e9matos, Technit\u00ed Ko\u00edti",
    "tgn:placetype":[
        "aat:300008699"
    ]
},
  "bbox": [],
  "geometry": {"coordinates":[21.963889,39.487778],"type":"Point"}
}