{
  "id": 1113378,
  "type": "Feature",
  "properties": {
    "tgn:hierarchy":[
        "tgn:1113378",
        "tgn:1000004",
        "tgn:1001481",
        "tgn:1000135",
        "tgn:7029392"
    ],
    "tgn:id":1113378,
    "tgn:name":"Malanut Bay",
    "tgn:placetype":[
        "aat:300132316"
    ]
},
  "bbox": [],
  "geometry": {"coordinates":[117.9833,9.2667],"type":"Point"}
}