<<<<<<< HEAD
{
  "id": 7351261,
  "type": "Feature",
  "properties": {
    "tgn:hierarchy":[
        "tgn:7351261",
        "tgn:7005581",
        "tgn:1000001",
        "tgn:7005560",
        "tgn:7029392"
    ],
    "tgn:id":7351261,
    "tgn:name":"Rancho Cacalote Arriba",
    "tgn:placetype":[
        "aat:300000241"
    ]
},
  "bbox": [],
  "geometry": {"coordinates":[-107.016667,26.166667],"type":"Point"}
}
=======
{"geometry":{"type":"Point","coordinates":[-107.016667,26.166667]},"type":"Feature","properties":{"hierarchy":["tgn:7351261","tgn:7005581","tgn:1000001","tgn:7005560","tgn:7029392"],"placetype":["aat:300000241"],"id":7351261,"name:xx":"Rancho Cacalote Arriba"}}
>>>>>>> 03f74aca74312dbeaf24d7e61306dd6a786dc3d0
