{
  "id": 2342288,
  "type": "Feature",
  "properties": {
    "tgn:hierarchy":[
        "tgn:2342288",
        "tgn:2001732",
        "tgn:1000001",
        "tgn:7012149",
        "tgn:7007712",
        "tgn:7029392"
    ],
    "tgn:id":2342288,
    "tgn:name":"Fuller Bay",
    "tgn:placetype":[
        "aat:300008905"
    ]
},
  "bbox": [],
  "geometry": {"coordinates":[-80.1167,33.2667],"type":"Point"}
}