{
  "id": 2139191,
  "type": "Feature",
  "properties": {
    "tgn:hierarchy":[
        "tgn:2139191",
        "tgn:1000001",
        "tgn:7012149",
        "tgn:1002899",
        "tgn:7007920",
        "tgn:7029392"
    ],
    "tgn:id":2139191,
    "tgn:name":"Ashton Creek",
    "tgn:placetype":[
        "aat:300008706"
    ]
},
  "bbox": [],
  "geometry": {"coordinates":[-121.6667,48.2167],"type":"Point"}
}