{
  "id": 2289929,
  "type": "Feature",
  "properties": {
    "tgn:hierarchy":[
        "tgn:2289929",
        "tgn:1000001",
        "tgn:7012149",
        "tgn:2001930",
        "tgn:7007825",
        "tgn:7029392"
    ],
    "tgn:id":2289929,
    "tgn:name":"Doc Jones Hollow",
    "tgn:placetype":[
        "aat:300008761"
    ]
},
  "bbox": [],
  "geometry": {"coordinates":[-86.9833,35.8167],"type":"Point"}
}