{
  "id": 7277412,
  "type": "Feature",
  "properties": {
    "tgn:hierarchy":[
        "tgn:7277412",
        "tgn:1001699",
        "tgn:1000049",
        "tgn:1000002",
        "tgn:7029392"
    ],
    "tgn:id":7277412,
    "tgn:name":"Vettor Pisani, Bajo",
    "tgn:placetype":[
        "aat:300008808"
    ]
},
  "bbox": [],
  "geometry": {"coordinates":[-73.466667,-42.75],"type":"Point"}
}