{
  "id": 7501542,
  "type": "Feature",
  "properties": {
    "tgn:hierarchy":[
        "tgn:7501542",
        "tgn:1000004",
        "tgn:7471332",
        "tgn:1000141",
        "tgn:7029392"
    ],
    "tgn:id":7501542,
    "tgn:name":"Zhongxing Qiao",
    "tgn:placetype":[
        "aat:300007836"
    ]
},
  "bbox": [],
  "geometry": {"coordinates":[120.992778,24.901111],"type":"Point"}
}