{
  "id": 7531879,
  "type": "Feature",
  "properties": {
    "tgn:hierarchy":[
        "tgn:7531879",
        "tgn:7001242",
        "tgn:7016833",
        "tgn:1001110",
        "tgn:7029392"
    ],
    "tgn:id":7531879,
    "tgn:name:en":"Barshah, Jabal al",
    "tgn:placetype":[
        "aat:300008795"
    ]
},
  "bbox": [],
  "geometry": {"coordinates":[31.961777,30.20188],"type":"Point"}
}