{
  "id": 2670287,
  "type": "Feature",
  "properties": {
    "tgn:hierarchy":[
        "tgn:2670287",
        "tgn:1000001",
        "tgn:7012149",
        "tgn:2002250",
        "tgn:7007920",
        "tgn:7029392"
    ],
    "tgn:id":2670287,
    "tgn:name":"Smackout Valley",
    "tgn:placetype":[
        "aat:300008761"
    ]
},
  "bbox": [],
  "geometry": {"coordinates":[-117.5667,48.7833],"type":"Point"}
}