{
  "id": 7571445,
  "type": "Feature",
  "properties": {
    "tgn:hierarchy":[
        "tgn:7571445",
        "tgn:1000004",
        "tgn:1001869",
        "tgn:7000198",
        "tgn:7029392"
    ],
    "tgn:id":7571445,
    "tgn:name:en":"H\u0101thmati River",
    "tgn:placetype":[
        "aat:300008699"
    ]
},
  "bbox": [],
  "geometry": {"coordinates":[72.824256,23.506809],"type":"Point"}
}