{
  "id": 2476611,
  "type": "Feature",
  "properties": {
    "tgn:hierarchy":[
        "tgn:2476611",
        "tgn:1000001",
        "tgn:7012149",
        "tgn:2001858",
        "tgn:7007825",
        "tgn:7029392"
    ],
    "tgn:id":2476611,
    "tgn:name":"Luther Lake Number One",
    "tgn:placetype":[
        "aat:300006191"
    ]
},
  "bbox": [],
  "geometry": {"coordinates":[-87.3667,36.0667],"type":"Point"}
}