<<<<<<< HEAD
{
  "id": 7111449,
  "type": "Feature",
  "properties": {
    "tgn:hierarchy":[
        "tgn:7111449",
        "tgn:1000003",
        "tgn:7003676",
        "tgn:7000084",
        "tgn:7029392"
    ],
    "tgn:id":7111449,
    "tgn:name":"Ridderade",
    "tgn:placetype":[
        "aat:300008347"
    ]
},
  "bbox": [],
  "geometry": {"coordinates":[8.6,52.766667],"type":"Point"}
}
=======
{"geometry":{"type":"Point","coordinates":[8.600000,52.766667]},"type":"Feature","properties":{"hierarchy":["tgn:7111449","tgn:1000003","tgn:7003676","tgn:7000084","tgn:7029392"],"placetype":["aat:300008347"],"id":7111449,"name:xx":"Ridderade"}}
>>>>>>> 03f74aca74312dbeaf24d7e61306dd6a786dc3d0
