{
  "id": 7567547,
  "type": "Feature",
  "properties": {
    "tgn:hierarchy":[
        "tgn:7567547",
        "tgn:1000004",
        "tgn:7000198",
        "tgn:7001797",
        "tgn:7029392"
    ],
    "tgn:id":7567547,
    "tgn:name:en":"P\u0101kkipuram",
    "tgn:placetype":[
        "aat:300008347"
    ]
},
  "bbox": [],
  "geometry": {"coordinates":[80.259167,13.244167],"type":"Point"}
}