{
  "id": 2133370,
  "type": "Feature",
  "properties": {
    "tgn:hierarchy":[
        "tgn:2133370",
        "tgn:1000001",
        "tgn:7012149",
        "tgn:2001190",
        "tgn:7007523",
        "tgn:7029392"
    ],
    "tgn:id":2133370,
    "tgn:name":"Anderson Spring",
    "tgn:placetype":[
        "aat:300008697"
    ]
},
  "bbox": [],
  "geometry": {"coordinates":[-91.4167,37.85],"type":"Point"}
}