{
  "id": 7077645,
  "type": "Feature",
  "properties": {
    "tgn:hierarchy":[
        "tgn:7077645",
        "tgn:1000003",
        "tgn:7003678",
        "tgn:7000084",
        "tgn:7029392"
    ],
    "tgn:id":7077645,
    "tgn:name":"Ziegelh\u00fctte",
    "tgn:placetype":[
        "aat:300008347"
    ]
},
  "bbox": [],
  "geometry": {"coordinates":[9.883333,50.433333],"type":"Point"}
}