<<<<<<< HEAD
{
  "id": 7021297,
  "type": "Feature",
  "properties": {
    "tgn:hierarchy":[
        "tgn:7021297",
        "tgn:1000001",
        "tgn:2002102",
        "tgn:7012149",
        "tgn:7007827",
        "tgn:7029392"
    ],
    "tgn:id":7021297,
    "tgn:name":"Hogup Point",
    "tgn:placetype":[
        "aat:300266640"
    ]
},
  "bbox": [],
  "geometry": {"coordinates":[-113.0667,41.2167],"type":"Point"}
}
=======
{"geometry":{"type":"Point","coordinates":[-113.066700,41.216700]},"type":"Feature","properties":{"hierarchy":["tgn:7021297","tgn:1000001","tgn:2002102","tgn:7012149","tgn:7007827","tgn:7029392"],"placetype":["aat:300266640"],"id":7021297,"name:xx":"Hogup Point"}}
>>>>>>> 03f74aca74312dbeaf24d7e61306dd6a786dc3d0
