{
  "id": 7021297,
  "type": "Feature",
  "properties": {
    "tgn:hierarchy":[
        "tgn:7021297",
        "tgn:1000001",
        "tgn:2002102",
        "tgn:7012149",
        "tgn:7007827",
        "tgn:7029392"
    ],
    "tgn:id":7021297,
    "tgn:name":"Hogup Point",
    "tgn:placetype":[
        "aat:300266640"
    ]
},
  "bbox": [],
  "geometry": {"coordinates":[-113.0667,41.2167],"type":"Point"}
}