<<<<<<< HEAD
{
  "id": 7378377,
  "type": "Feature",
  "properties": {
    "tgn:hierarchy":[
        "tgn:7378377",
        "tgn:7005578",
        "tgn:1000001",
        "tgn:7005560",
        "tgn:7029392"
    ],
    "tgn:id":7378377,
    "tgn:name":"L\u00e1zaro C\u00e1rdenas",
    "tgn:placetype":[
        "aat:300008347"
    ]
},
  "bbox": [],
  "geometry": {"coordinates":[-90.8,17.916667],"type":"Point"}
}
=======
{"geometry":{"type":"Point","coordinates":[-90.800000,17.916667]},"type":"Feature","properties":{"hierarchy":["tgn:7378377","tgn:7005578","tgn:1000001","tgn:7005560","tgn:7029392"],"placetype":["aat:300008347"],"id":7378377,"name:xx":"L\u00e1zaro C\u00e1rdenas"}}
>>>>>>> 03f74aca74312dbeaf24d7e61306dd6a786dc3d0
