{
  "id": 7035937,
  "type": "Feature",
  "properties": {
    "tgn:hierarchy":[
        "tgn:7035937",
        "tgn:1003506",
        "tgn:1000003",
        "tgn:7002993",
        "tgn:1000080",
        "tgn:7029392"
    ],
    "tgn:id":7035937,
    "tgn:name":"Rutte",
    "tgn:placetype":[
        "aat:300008347"
    ]
},
  "bbox": [],
  "geometry": {"coordinates":[13.606111,46.494722],"type":"Point"}
}