{
  "id": 1050338,
  "type": "Feature",
  "properties": {
    "tgn:hierarchy":[
        "tgn:1050338",
        "tgn:1000003",
        "tgn:1000392",
        "tgn:1000091",
        "tgn:7029392"
    ],
    "tgn:id":1050338,
    "tgn:name":"Voine\u0219ti",
    "tgn:placetype":[
        "aat:300008347"
    ]
},
  "bbox": [],
  "geometry": {"coordinates":[27.45,47.0833],"type":"Point"}
}