{
  "id": 7510842,
  "type": "Feature",
  "properties": {
    "tgn:hierarchy":[
        "tgn:7510842",
        "tgn:1009227",
        "tgn:7001866",
        "tgn:1000226",
        "tgn:1000006",
        "tgn:7029392"
    ],
    "tgn:id":7510842,
    "tgn:name:en":"Snowdale",
    "tgn:placetype":[
        "aat:300000206"
    ]
},
  "bbox": [],
  "geometry": {"coordinates":[172.133333,-43.133333],"type":"Point"}
}