{
  "id": 7584585,
  "type": "Feature",
  "properties": {
    "tgn:hierarchy":[
        "tgn:7584585",
        "tgn:1000004",
        "tgn:7000198",
        "tgn:1001894",
        "tgn:7029392"
    ],
    "tgn:id":7584585,
    "tgn:name:en":"Karampur",
    "tgn:placetype":[
        "aat:300167671"
    ]
},
  "bbox": [],
  "geometry": {"coordinates":[78.005013,24.143847],"type":"Point"}
}