{
  "id": 1091989,
  "type": "Feature",
  "properties": {
    "tgn:hierarchy":[
        "tgn:1091989",
        "tgn:7001242",
        "tgn:1001880",
        "tgn:1000182",
        "tgn:7029392"
    ],
    "tgn:id":1091989,
    "tgn:name":"Gaya",
    "tgn:placetype":[
        "aat:300008347"
    ]
},
  "bbox": [],
  "geometry": {"coordinates":[9.0167,11.8833],"type":"Point"}
}