{
  "id": 2767834,
  "type": "Feature",
  "properties": {
    "tgn:hierarchy":[
        "tgn:2767834",
        "tgn:1000001",
        "tgn:7012149",
        "tgn:2001718",
        "tgn:7007708",
        "tgn:7029392"
    ],
    "tgn:id":2767834,
    "tgn:name":"Whitehorse Mountain",
    "tgn:placetype":[
        "aat:300008798"
    ]
},
  "bbox": [],
  "geometry": {"coordinates":[-118.0167,43.2667],"type":"Point"}
}