{
  "id": 2665049,
  "type": "Feature",
  "properties": {
    "tgn:hierarchy":[
        "tgn:2665049",
        "tgn:1000001",
        "tgn:7012149",
        "tgn:2002123",
        "tgn:7007827",
        "tgn:7029392"
    ],
    "tgn:id":2665049,
    "tgn:name":"Simpson Mountains",
    "tgn:placetype":[
        "aat:300386831"
    ]
},
  "bbox": [],
  "geometry": {"coordinates":[-112.7167,39.9667],"type":"Point"}
}