{
  "id": 1022910,
  "type": "Feature",
  "properties": {
    "tgn:hierarchy":[
        "tgn:1022910",
        "tgn:7006237",
        "tgn:1000047",
        "tgn:7002457",
        "tgn:1000002",
        "tgn:7029392"
    ],
    "tgn:id":1022910,
    "tgn:name":"S\u00e3o Tom\u00e9 das Letras",
    "tgn:placetype":[
        "aat:300008347"
    ]
},
  "bbox": [],
  "geometry": {"coordinates":[-44.9833,-21.7167],"type":"Point"}
}