{
  "id": 2059406,
  "type": "Feature",
  "properties": {
    "tgn:hierarchy":[
        "tgn:2059406",
        "tgn:1000001",
        "tgn:7012149",
        "tgn:2001210",
        "tgn:7007523",
        "tgn:7029392"
    ],
    "tgn:id":2059406,
    "tgn:name":"Knob Noster",
    "tgn:placetype":[
        "aat:300008347"
    ]
},
  "bbox": [],
  "geometry": {"coordinates":[-93.55,38.7667],"type":"Point"}
}