{
  "id": 2314709,
  "type": "Feature",
  "properties": {
    "tgn:hierarchy":[
        "tgn:2314709",
        "tgn:1000001",
        "tgn:2002370",
        "tgn:7012149",
        "tgn:7007923",
        "tgn:7029392"
    ],
    "tgn:id":2314709,
    "tgn:name":"Elk Spring",
    "tgn:placetype":[
        "aat:300008697"
    ]
},
  "bbox": [],
  "geometry": {"coordinates":[-104.05,44.2333],"type":"Point"}
}