{
  "id": 7011326,
  "type": "Feature",
  "properties": {
    "tgn:hierarchy":[
        "tgn:7011326",
        "tgn:7002445",
        "tgn:1000003",
        "tgn:7012077",
        "tgn:7008591",
        "tgn:7029392"
    ],
    "tgn:id":7011326,
    "tgn:name:en":"Devonport",
    "tgn:placetype":[
        "aat:300008347"
    ]
},
  "bbox": [],
  "geometry": {"coordinates":[-4.183333,50.366667],"type":"Point"}
}