{
  "id": 2498748,
  "type": "Feature",
  "properties": {
    "tgn:hierarchy":[
        "tgn:2498748",
        "tgn:1000001",
        "tgn:7006451",
        "tgn:7012149",
        "tgn:2000100",
        "tgn:7029392"
    ],
    "tgn:id":2498748,
    "tgn:name":"McCafferty Canyon",
    "tgn:placetype":[
        "aat:300008761"
    ]
},
  "bbox": [],
  "geometry": {"coordinates":[-111.35,31.6333],"type":"Point"}
}