{
  "id": 7092593,
  "type": "Feature",
  "properties": {
    "tgn:hierarchy":[
        "tgn:7092593",
        "tgn:1000003",
        "tgn:7003676",
        "tgn:7000084",
        "tgn:7029392"
    ],
    "tgn:id":7092593,
    "tgn:name":"Uppen",
    "tgn:placetype":[
        "aat:300008347"
    ]
},
  "bbox": [],
  "geometry": {"coordinates":[10.016667,52.15],"type":"Point"}
}