{
  "id": 2582374,
  "type": "Feature",
  "properties": {
    "tgn:hierarchy":[
        "tgn:2582374",
        "tgn:1000001",
        "tgn:2001801",
        "tgn:7012149",
        "tgn:7007713",
        "tgn:7029392"
    ],
    "tgn:id":2582374,
    "tgn:name":"Pine Draw",
    "tgn:placetype":[
        "aat:300008761"
    ]
},
  "bbox": [],
  "geometry": {"coordinates":[-103.85,45.5333],"type":"Point"}
}