{
  "id": 7551224,
  "type": "Feature",
  "properties": {
    "tgn:hierarchy":[
        "tgn:7551224",
        "tgn:1000004",
        "tgn:7000198",
        "tgn:7016694",
        "tgn:7029392"
    ],
    "tgn:id":7551224,
    "tgn:name:en":"Chelli\u0101toka",
    "tgn:placetype":[
        "aat:300008777"
    ]
},
  "bbox": [],
  "geometry": {"coordinates":[85.146056,21.735257],"type":"Point"}
}