{
  "id": 2273612,
  "type": "Feature",
  "properties": {
    "tgn:hierarchy":[
        "tgn:2273612",
        "tgn:1000001",
        "tgn:7012149",
        "tgn:2000654",
        "tgn:7007253",
        "tgn:7029392"
    ],
    "tgn:id":2273612,
    "tgn:name":"Cypsum City",
    "tgn:placetype":[
        "aat:300008347"
    ]
},
  "bbox": [],
  "geometry": {"coordinates":[-94.1167,42.4667],"type":"Point"}
}