{
  "id": 1014347,
  "type": "Feature",
  "properties": {
    "tgn:hierarchy":[
        "tgn:1014347",
        "tgn:7005685",
        "tgn:7005807",
        "tgn:1000001",
        "tgn:7005801",
        "tgn:7029392"
    ],
    "tgn:id":1014347,
    "tgn:name":"Whitbourne",
    "tgn:placetype":[
        "aat:300008347"
    ]
},
  "bbox": [],
  "geometry": {"coordinates":[-53.55,47.4333],"type":"Point"}
}