<<<<<<< HEAD
{
  "id": 2250853,
  "type": "Feature",
  "properties": {
    "tgn:hierarchy":[
        "tgn:2250853",
        "tgn:1000001",
        "tgn:2000199",
        "tgn:7012149",
        "tgn:7007158",
        "tgn:7029392"
    ],
    "tgn:id":2250853,
    "tgn:name":"Columbia Creek",
    "tgn:placetype":[
        "aat:300008706"
    ]
},
  "bbox": [],
  "geometry": {"coordinates":[-106.2667,38.9667],"type":"Point"}
}
=======
{"geometry":{"type":"Point","coordinates":[-106.266700,38.966700]},"type":"Feature","properties":{"hierarchy":["tgn:2250853","tgn:1000001","tgn:2000199","tgn:7012149","tgn:7007158","tgn:7029392"],"placetype":["aat:300008706"],"id":2250853,"name:xx":"Columbia Creek"}}
>>>>>>> 03f74aca74312dbeaf24d7e61306dd6a786dc3d0
