{
  "id": 2573554,
  "type": "Feature",
  "properties": {
    "tgn:hierarchy":[
        "tgn:2573554",
        "tgn:1000001",
        "tgn:1002664",
        "tgn:7012149",
        "tgn:7007159",
        "tgn:7029392"
    ],
    "tgn:id":2573554,
    "tgn:name":"Pecausett Pond",
    "tgn:placetype":[
        "aat:300008680"
    ]
},
  "bbox": [],
  "geometry": {"coordinates":[-72.6167,41.5667],"type":"Point"}
}