{
  "id": 2275568,
  "type": "Feature",
  "properties": {
    "tgn:hierarchy":[
        "tgn:2275568",
        "tgn:1000001",
        "tgn:7012149",
        "tgn:7029392"
    ],
    "tgn:id":2275568,
    "tgn:name":"Darby Creek",
    "tgn:placetype":[
        "aat:300008706"
    ]
},
  "bbox": [],
  "geometry": {"coordinates":[-111.15,43.6667],"type":"Point"}
}