{
  "id": 7287618,
  "type": "Feature",
  "properties": {
    "tgn:hierarchy":[
        "tgn:7287618",
        "tgn:1001708",
        "tgn:1000049",
        "tgn:1000002",
        "tgn:7029392"
    ],
    "tgn:id":7287618,
    "tgn:name":"La Dormida, Cuesta",
    "tgn:placetype":[
        "aat:300259572"
    ]
},
  "bbox": [],
  "geometry": {"coordinates":[-71.033333,-33.066667],"type":"Point"}
}