{
  "id": 7505269,
  "type": "Feature",
  "properties": {
    "tgn:hierarchy":[
        "tgn:7505269",
        "tgn:1009227",
        "tgn:1000226",
        "tgn:7016729",
        "tgn:1000006",
        "tgn:7029392"
    ],
    "tgn:id":7505269,
    "tgn:name:en":"Wooded Peak",
    "tgn:placetype":[
        "aat:300008798"
    ]
},
  "bbox": [],
  "geometry": {"coordinates":[173.35,-41.333333],"type":"Point"}
}