{
  "id": 7555547,
  "type": "Feature",
  "properties": {
    "tgn:hierarchy":[
        "tgn:7555547",
        "tgn:1000004",
        "tgn:7000198",
        "tgn:1001882",
        "tgn:7029392"
    ],
    "tgn:id":7555547,
    "tgn:name:en":"Nandigunda",
    "tgn:placetype":[
        "aat:300008347"
    ]
},
  "bbox": [],
  "geometry": {"coordinates":[77.65,13.333333],"type":"Point"}
}