{
  "id": 2257015,
  "type": "Feature",
  "properties": {
    "tgn:hierarchy":[
        "tgn:2257015",
        "tgn:1000001",
        "tgn:1002359",
        "tgn:7012149",
        "tgn:7007517",
        "tgn:7029392"
    ],
    "tgn:id":2257015,
    "tgn:name":"Corn Island",
    "tgn:placetype":[
        "aat:300008791"
    ]
},
  "bbox": [],
  "geometry": {"coordinates":[-70.75,42.65],"type":"Point"}
}