{
  "id": 7276428,
  "type": "Feature",
  "properties": {
    "tgn:hierarchy":[
        "tgn:7276428",
        "tgn:7016598",
        "tgn:1000049",
        "tgn:1000002",
        "tgn:7029392"
    ],
    "tgn:id":7276428,
    "tgn:name":"Tatio, G\u00e9iser del",
    "tgn:placetype":[
        "aat:300380167"
    ]
},
  "bbox": [],
  "geometry": {"coordinates":[-68.05,-22.366667],"type":"Point"}
}