{
  "id": 2218156,
  "type": "Feature",
  "properties": {
    "tgn:hierarchy":[
        "tgn:2218156",
        "tgn:1000001",
        "tgn:7012149",
        "tgn:7007158",
        "tgn:2000246",
        "tgn:7029392"
    ],
    "tgn:id":2218156,
    "tgn:name":"Ca\u00f1ads Ancha",
    "tgn:placetype":[
        "aat:300008699"
    ]
},
  "bbox": [],
  "geometry": {"coordinates":[-106.3833,37.8167],"type":"Point"}
}