{
  "id": 2657792,
  "type": "Feature",
  "properties": {
    "tgn:hierarchy":[
        "tgn:2657792",
        "tgn:1000001",
        "tgn:7012149",
        "tgn:2001846",
        "tgn:7007825",
        "tgn:7029392"
    ],
    "tgn:id":2657792,
    "tgn:name":"Shell Creek",
    "tgn:placetype":[
        "aat:300008706"
    ]
},
  "bbox": [],
  "geometry": {"coordinates":[-82.0167,36.1333],"type":"Point"}
}