{
  "id": 6004580,
  "type": "Feature",
  "properties": {
    "tgn:hierarchy":[
        "tgn:6004580",
        "tgn:1000001",
        "tgn:7005599",
        "tgn:7005560",
        "tgn:7029392"
    ],
    "tgn:id":6004580,
    "tgn:name":"Pavon",
    "tgn:placetype":[
        "aat:300008347",
        "aat:300000810",
        "aat:300167671",
        "aat:300016619"
    ]
},
  "bbox": [],
  "geometry": {"coordinates":[-98.178699,22.048414],"type":"Point"}
}