{
  "id": 7220419,
  "type": "Feature",
  "properties": {
    "tgn:hierarchy":[
        "tgn:7220419",
        "tgn:7011330",
        "tgn:7002674",
        "tgn:1000003",
        "tgn:1000074",
        "tgn:7029392"
    ],
    "tgn:id":7220419,
    "tgn:name":"Kam\u00e1rion",
    "tgn:placetype":[
        "aat:300008347"
    ]
},
  "bbox": [],
  "geometry": {"coordinates":[26.967222,36.734722],"type":"Point"}
}