{
  "id": 2328119,
  "type": "Feature",
  "properties": {
    "tgn:hierarchy":[
        "tgn:2328119",
        "tgn:1000001",
        "tgn:7012149",
        "tgn:2000290",
        "tgn:7007240",
        "tgn:7029392"
    ],
    "tgn:id":2328119,
    "tgn:name":"Fish Pond Branch",
    "tgn:placetype":[
        "aat:300008699"
    ]
},
  "bbox": [],
  "geometry": {"coordinates":[-86.1667,30.7333],"type":"Point"}
}