{
  "id": 7030095,
  "type": "Feature",
  "properties": {
    "tgn:hierarchy":[
        "tgn:7030095",
        "tgn:7002445",
        "tgn:1000003",
        "tgn:7008166",
        "tgn:7008591",
        "tgn:7029392"
    ],
    "tgn:id":7030095,
    "tgn:name:en":"Marton",
    "tgn:placetype":[
        "aat:300008347",
        "aat:300008372"
    ]
},
  "bbox": [],
  "geometry": {"coordinates":[-1.366667,54.066667],"type":"Point"}
}