<<<<<<< HEAD
{
  "id": 7027421,
  "type": "Feature",
  "properties": {
    "tgn:hierarchy":[
        "tgn:7027421",
        "tgn:7002807",
        "tgn:1000003",
        "tgn:7003837",
        "tgn:1000095",
        "tgn:7029392"
    ],
    "tgn:id":7027421,
    "tgn:name":"Alange",
    "tgn:placetype":[
        "aat:300008347",
        "aat:300008375"
    ]
},
  "bbox": [],
  "geometry": {"coordinates":[-6.9,38.7833],"type":"Point"}
}
=======
{"geometry":{"type":"Point","coordinates":[-6.900000,38.783300]},"type":"Feature","properties":{"hierarchy":["tgn:7027421","tgn:7002807","tgn:1000003","tgn:7003837","tgn:1000095","tgn:7029392"],"placetype":["aat:300008347","aat:300008375"],"id":7027421,"name:xx":"Alange"}}
>>>>>>> 03f74aca74312dbeaf24d7e61306dd6a786dc3d0
