{
  "id": 2683635,
  "type": "Feature",
  "properties": {
    "tgn:hierarchy":[
        "tgn:2683635",
        "tgn:7002659",
        "tgn:1000001",
        "tgn:2000020",
        "tgn:7012149",
        "tgn:7029392"
    ],
    "tgn:id":2683635,
    "tgn:name":"Spears Branch",
    "tgn:placetype":[
        "aat:300008699"
    ]
},
  "bbox": [],
  "geometry": {"coordinates":[-86.4667,31.6333],"type":"Point"}
}