{
  "id": 7314882,
  "type": "Feature",
  "properties": {
    "tgn:hierarchy":[
        "tgn:7314882",
        "tgn:1001692",
        "tgn:1000049",
        "tgn:1000002",
        "tgn:7029392"
    ],
    "tgn:id":7314882,
    "tgn:name":"Estaci\u00f3n Lolenco",
    "tgn:placetype":[
        "aat:300007783"
    ]
},
  "bbox": [],
  "geometry": {"coordinates":[-72.45,-37.866667],"type":"Point"}
}