{
  "id": 7056481,
  "type": "Feature",
  "properties": {
    "tgn:hierarchy":[
        "tgn:7056481",
        "tgn:7015163",
        "tgn:1000003",
        "tgn:7003121",
        "tgn:1000080",
        "tgn:7029392"
    ],
    "tgn:id":7056481,
    "tgn:name":"Menta, Punta sa",
    "tgn:placetype":[
        "aat:300008795"
    ]
},
  "bbox": [],
  "geometry": {"coordinates":[8.727778,40.895556],"type":"Point"}
}