{
  "id": 7518598,
  "type": "Feature",
  "properties": {
    "tgn:hierarchy":[
        "tgn:7518598",
        "tgn:1009227",
        "tgn:1000226",
        "tgn:7016822",
        "tgn:1000006",
        "tgn:7029392"
    ],
    "tgn:id":7518598,
    "tgn:name:en":"Bald Hill",
    "tgn:placetype":[
        "aat:300008795"
    ]
},
  "bbox": [],
  "geometry": {"coordinates":[168.15,-45.383333],"type":"Point"}
}