{
  "id": 2387739,
  "type": "Feature",
  "properties": {
    "tgn:hierarchy":[
        "tgn:2387739",
        "tgn:1000001",
        "tgn:7016172",
        "tgn:7012149",
        "tgn:2000179",
        "tgn:7029392"
    ],
    "tgn:id":2387739,
    "tgn:name":"Hickerson Hollow",
    "tgn:placetype":[
        "aat:300008761"
    ]
},
  "bbox": [],
  "geometry": {"coordinates":[-93.2667,35.25],"type":"Point"}
}