{
  "id": 7020006,
  "type": "Feature",
  "properties": {
    "tgn:hierarchy":[
        "tgn:7020006",
        "tgn:1000001",
        "tgn:7012149",
        "tgn:7029392"
    ],
    "tgn:id":7020006,
    "tgn:name":"Chesapeake and Ohio Canal",
    "tgn:placetype":[
        "aat:300006075",
        "aat:300386977"
    ]
},
  "bbox": [],
  "geometry": {"coordinates":[-77.85,39.5167],"type":"Point"}
}