<<<<<<< HEAD
{
  "id": 7020006,
  "type": "Feature",
  "properties": {
    "tgn:hierarchy":[
        "tgn:7020006",
        "tgn:1000001",
        "tgn:7012149",
        "tgn:7029392"
    ],
    "tgn:id":7020006,
    "tgn:name":"Chesapeake and Ohio Canal",
    "tgn:placetype":[
        "aat:300006075",
        "aat:300386977"
    ]
},
  "bbox": [],
  "geometry": {"coordinates":[-77.85,39.5167],"type":"Point"}
}
=======
{"geometry":{"type":"Point","coordinates":[-77.850000,39.516700]},"type":"Feature","properties":{"hierarchy":["tgn:7020006","tgn:1000001","tgn:7012149","tgn:7029392"],"placetype":["aat:300006075","aat:300386977"],"id":7020006,"name:xx":"Chesapeake and Ohio Canal"}}
>>>>>>> 03f74aca74312dbeaf24d7e61306dd6a786dc3d0
