{
  "id": 7218070,
  "type": "Feature",
  "properties": {
    "tgn:hierarchy":[
        "tgn:7218070",
        "tgn:7011161",
        "tgn:7002674",
        "tgn:1000003",
        "tgn:1000074",
        "tgn:7029392"
    ],
    "tgn:id":7218070,
    "tgn:name":"Trif\u00edlli, \u00c1kra",
    "tgn:placetype":[
        "aat:300008850"
    ]
},
  "bbox": [],
  "geometry": {"coordinates":[25.563889,38.531944],"type":"Point"}
}