{
  "id": 7406483,
  "type": "Feature",
  "properties": {
    "tgn:hierarchy":[
        "tgn:7406483",
        "tgn:7005578",
        "tgn:1000001",
        "tgn:7005560",
        "tgn:7029392"
    ],
    "tgn:id":7406483,
    "tgn:name":"El Infierno",
    "tgn:placetype":[
        "aat:300008347"
    ]
},
  "bbox": [],
  "geometry": {"coordinates":[-90.655556,18.191667],"type":"Point"}
}