{
  "id": 7012356,
  "type": "Feature",
  "properties": {
    "tgn:hierarchy":[
        "tgn:7012356",
        "tgn:7000096",
        "tgn:1000003",
        "tgn:7000084",
        "tgn:7029392"
    ],
    "tgn:id":7012356,
    "tgn:name":"Altenhof",
    "tgn:placetype":[
        "aat:300008347"
    ]
},
  "bbox": [],
  "geometry": {"coordinates":[13.716667,52.916667],"type":"Point"}
}