{
  "id": 7292619,
  "type": "Feature",
  "properties": {
    "tgn:hierarchy":[
        "tgn:7292619",
        "tgn:1001695",
        "tgn:1000049",
        "tgn:1000002",
        "tgn:7029392"
    ],
    "tgn:id":7292619,
    "tgn:name":"El Olivar",
    "tgn:placetype":[
        "aat:300000206"
    ]
},
  "bbox": [],
  "geometry": {"coordinates":[-70.833333,-34.233333],"type":"Point"}
}