{
  "id": 2161251,
  "type": "Feature",
  "properties": {
    "tgn:hierarchy":[
        "tgn:2161251",
        "tgn:7006450",
        "tgn:1000001",
        "tgn:7012149",
        "tgn:2000082",
        "tgn:7029392"
    ],
    "tgn:id":2161251,
    "tgn:name":"Bell Island",
    "tgn:placetype":[
        "aat:300008791"
    ]
},
  "bbox": [],
  "geometry": {"coordinates":[-131.4833,55.95],"type":"Point"}
}