{
  "id": 7494406,
  "type": "Feature",
  "properties": {
    "tgn:hierarchy":[
        "tgn:7494406",
        "tgn:7488858",
        "tgn:1000004",
        "tgn:1000141",
        "tgn:7029392"
    ],
    "tgn:id":7494406,
    "tgn:name":"Dinghu",
    "tgn:placetype":[
        "aat:300008347"
    ]
},
  "bbox": [],
  "geometry": {"coordinates":[120.654625,23.953296],"type":"Point"}
}