{
  "id": 7108988,
  "type": "Feature",
  "properties": {
    "tgn:hierarchy":[
        "tgn:7108988",
        "tgn:7003669",
        "tgn:1000003",
        "tgn:7000084",
        "tgn:7029392"
    ],
    "tgn:id":7108988,
    "tgn:name":"Ranzenthal",
    "tgn:placetype":[
        "aat:300008347"
    ]
},
  "bbox": [],
  "geometry": {"coordinates":[11.616667,49.75],"type":"Point"}
}