{
  "id": 2779926,
  "type": "Feature",
  "properties": {
    "tgn:hierarchy":[
        "tgn:2779926",
        "tgn:1000001",
        "tgn:7012149",
        "tgn:2001084",
        "tgn:7007521",
        "tgn:7029392"
    ],
    "tgn:id":2779926,
    "tgn:name":"Wolfe Lake",
    "tgn:placetype":[
        "aat:300008905"
    ]
},
  "bbox": [],
  "geometry": {"coordinates":[-94.0333,45.1333],"type":"Point"}
}