{
  "id": 7573485,
  "type": "Feature",
  "properties": {
    "tgn:hierarchy":[
        "tgn:7573485",
        "tgn:1000004",
        "tgn:7000198",
        "tgn:7016788",
        "tgn:7029392"
    ],
    "tgn:id":7573485,
    "tgn:name:en":"G\u016bnga",
    "tgn:placetype":[
        "aat:300008347"
    ]
},
  "bbox": [],
  "geometry": {"coordinates":[71.21421,26.235621],"type":"Point"}
}