{
  "id": 2445832,
  "type": "Feature",
  "properties": {
    "tgn:hierarchy":[
        "tgn:2445832",
        "tgn:1000001",
        "tgn:7012149",
        "tgn:1002661",
        "tgn:7007252",
        "tgn:7029392"
    ],
    "tgn:id":2445832,
    "tgn:name":"Lesher Ditch",
    "tgn:placetype":[
        "aat:300006075"
    ]
},
  "bbox": [],
  "geometry": {"coordinates":[-86.0333,40.65],"type":"Point"}
}