<<<<<<< HEAD
{
  "id": 7473586,
  "type": "Feature",
  "properties": {
    "tgn:hierarchy":[
        "tgn:7473586",
        "tgn:1000004",
        "tgn:7490934",
        "tgn:1000141",
        "tgn:7029392"
    ],
    "tgn:id":7473586,
    "tgn:name":"Dongshi",
    "tgn:placetype":[
        "aat:300000745"
    ]
},
  "bbox": [],
  "geometry": {"coordinates":[120.335278,22.953056],"type":"Point"}
}
=======
{"geometry":{"type":"Point","coordinates":[120.335278,22.953056]},"type":"Feature","properties":{"hierarchy":["tgn:7473586","tgn:1000004","tgn:7490934","tgn:1000141","tgn:7029392"],"placetype":["aat:300000745"],"id":7473586,"name:xx":"Dongshi"}}
>>>>>>> 03f74aca74312dbeaf24d7e61306dd6a786dc3d0
