<<<<<<< HEAD
{
  "id": 2158031,
  "type": "Feature",
  "properties": {
    "tgn:hierarchy":[
        "tgn:2158031",
        "tgn:1000001",
        "tgn:7012149",
        "tgn:2001281",
        "tgn:7007524",
        "tgn:7029392"
    ],
    "tgn:id":2158031,
    "tgn:name":"Beaver Placer Mine",
    "tgn:placetype":[
        "aat:300000390"
    ]
},
  "bbox": [],
  "geometry": {"coordinates":[-112.1833,46.1],"type":"Point"}
}
=======
{"geometry":{"type":"Point","coordinates":[-112.183300,46.100000]},"type":"Feature","properties":{"hierarchy":["tgn:2158031","tgn:1000001","tgn:7012149","tgn:2001281","tgn:7007524","tgn:7029392"],"placetype":["aat:300000390"],"id":2158031,"name:xx":"Beaver Placer Mine"}}
>>>>>>> 03f74aca74312dbeaf24d7e61306dd6a786dc3d0
