{
  "id": 7537971,
  "type": "Feature",
  "properties": {
    "tgn:hierarchy":[
        "tgn:7537971",
        "tgn:7001242",
        "tgn:7016833",
        "tgn:1001088",
        "tgn:7029392"
    ],
    "tgn:id":7537971,
    "tgn:name:en":"Nazlat 'A\u015far",
    "tgn:placetype":[
        "aat:300008347"
    ]
},
  "bbox": [],
  "geometry": {"coordinates":[30.694207,28.610964],"type":"Point"}
}