{
  "id": 7399765,
  "type": "Feature",
  "properties": {
    "tgn:hierarchy":[
        "tgn:7399765",
        "tgn:1000001",
        "tgn:7005593",
        "tgn:7005560",
        "tgn:7029392"
    ],
    "tgn:id":7399765,
    "tgn:name:es":"El Espol\u00f3n, Cerro",
    "tgn:placetype":[
        "aat:300008795"
    ]
},
  "bbox": [],
  "geometry": {"coordinates":[-99.522222,20.741667],"type":"Point"}
}