{
  "id": 7454621,
  "type": "Feature",
  "properties": {
    "tgn:hierarchy":[
        "tgn:7454621",
        "tgn:7002444",
        "tgn:1000003",
        "tgn:7008082",
        "tgn:7008591",
        "tgn:7029392"
    ],
    "tgn:id":7454621,
    "tgn:name:en":"Contin",
    "tgn:placetype":[
        "aat:300008347"
    ]
},
  "bbox": [],
  "geometry": {"coordinates":[-4.566667,57.566667],"type":"Point"}
}