<<<<<<< HEAD
{
  "id": 7351026,
  "type": "Feature",
  "properties": {
    "tgn:hierarchy":[
        "tgn:7351026",
        "tgn:1000001",
        "tgn:7005595",
        "tgn:7005560",
        "tgn:7029392"
    ],
    "tgn:id":7351026,
    "tgn:name":"Boca del Arroyo",
    "tgn:placetype":[
        "aat:300008347"
    ]
},
  "bbox": [],
  "geometry": {"coordinates":[-108.755,26.316944],"type":"Point"}
}
=======
{"geometry":{"type":"Point","coordinates":[-108.755000,26.316944]},"type":"Feature","properties":{"hierarchy":["tgn:7351026","tgn:1000001","tgn:7005595","tgn:7005560","tgn:7029392"],"placetype":["aat:300008347"],"id":7351026,"name:xx":"Boca del Arroyo"}}
>>>>>>> 03f74aca74312dbeaf24d7e61306dd6a786dc3d0
