<<<<<<< HEAD
{
  "id": 7480671,
  "type": "Feature",
  "properties": {
    "tgn:hierarchy":[
        "tgn:7480671",
        "tgn:7468018",
        "tgn:1000004",
        "tgn:1000141",
        "tgn:7029392"
    ],
    "tgn:id":7480671,
    "tgn:name":"Guangrong Guoxiao Longjiao Fenxiao",
    "tgn:placetype":[
        "aat:300006495"
    ]
},
  "bbox": [],
  "geometry": {"coordinates":[120.2269,23.3684],"type":"Point"}
}
=======
{"geometry":{"type":"Point","coordinates":[120.226900,23.368400]},"type":"Feature","properties":{"hierarchy":["tgn:7480671","tgn:7468018","tgn:1000004","tgn:1000141","tgn:7029392"],"placetype":["aat:300006495"],"id":7480671,"name:xx":"Guangrong Guoxiao Longjiao Fenxiao"}}
>>>>>>> 03f74aca74312dbeaf24d7e61306dd6a786dc3d0
