<<<<<<< HEAD
{
  "id": 7054883,
  "type": "Feature",
  "properties": {
    "tgn:hierarchy":[
        "tgn:7054883",
        "tgn:7003163",
        "tgn:1000003",
        "tgn:7009760",
        "tgn:1000080",
        "tgn:7029392"
    ],
    "tgn:id":7054883,
    "tgn:name":"Molino del Piano",
    "tgn:placetype":[
        "aat:300008347"
    ]
},
  "bbox": [],
  "geometry": {"coordinates":[11.4,43.816667],"type":"Point"}
}
=======
{"geometry":{"type":"Point","coordinates":[11.400000,43.816667]},"type":"Feature","properties":{"hierarchy":["tgn:7054883","tgn:7003163","tgn:1000003","tgn:7009760","tgn:1000080","tgn:7029392"],"placetype":["aat:300008347"],"id":7054883,"name:xx":"Molino del Piano"}}
>>>>>>> 03f74aca74312dbeaf24d7e61306dd6a786dc3d0
