{
  "id": 2200554,
  "type": "Feature",
  "properties": {
    "tgn:hierarchy":[
        "tgn:2200554",
        "tgn:1000001",
        "tgn:7012149",
        "tgn:2001437",
        "tgn:7007566",
        "tgn:7029392"
    ],
    "tgn:id":2200554,
    "tgn:name":"Brushy Mountain Tank",
    "tgn:placetype":[
        "aat:300006191"
    ]
},
  "bbox": [],
  "geometry": {"coordinates":[-108.9667,32.9833],"type":"Point"}
}