{
  "id": 2458626,
  "type": "Feature",
  "properties": {
    "tgn:hierarchy":[
        "tgn:2458626",
        "tgn:1000001",
        "tgn:2001785",
        "tgn:7012149",
        "tgn:7007713",
        "tgn:7029392"
    ],
    "tgn:id":2458626,
    "tgn:name":"Little Oak Creek",
    "tgn:placetype":[
        "aat:300008706"
    ]
},
  "bbox": [],
  "geometry": {"coordinates":[-100.8667,45.5167],"type":"Point"}
}