{
  "id": 7284325,
  "type": "Feature",
  "properties": {
    "tgn:hierarchy":[
        "tgn:7284325",
        "tgn:1001657",
        "tgn:1000049",
        "tgn:1000002",
        "tgn:7029392"
    ],
    "tgn:id":7284325,
    "tgn:name":"Quilmenco, Quebrada",
    "tgn:placetype":[
        "aat:300008699"
    ]
},
  "bbox": [],
  "geometry": {"coordinates":[-70.916667,-31.566667],"type":"Point"}
}