{
  "id": 7590989,
  "type": "Feature",
  "properties": {
    "tgn:hierarchy":[
        "tgn:7590989",
        "tgn:1000004",
        "tgn:7000198",
        "tgn:7031786",
        "tgn:7029392"
    ],
    "tgn:id":7590989,
    "tgn:name:en":"Vinh\u0101r Block Reserved Forest",
    "tgn:placetype":[
        "aat:300008863"
    ]
},
  "bbox": [],
  "geometry": {"coordinates":[77.898484,30.485118],"type":"Point"}
}