{
  "id": 7417481,
  "type": "Feature",
  "properties": {
    "tgn:hierarchy":[
        "tgn:7417481",
        "tgn:1000001",
        "tgn:7005596",
        "tgn:7005560",
        "tgn:7029392"
    ],
    "tgn:id":7417481,
    "tgn:name:es":"Chichilapa",
    "tgn:placetype":[
        "aat:300008347"
    ]
},
  "bbox": [],
  "geometry": {"coordinates":[-93.183333,18.258333],"type":"Point"}
}