<<<<<<< HEAD
{
  "id": 7470078,
  "type": "Feature",
  "properties": {
    "tgn:hierarchy":[
        "tgn:7470078",
        "tgn:1000004",
        "tgn:7001009",
        "tgn:1000141",
        "tgn:7029392"
    ],
    "tgn:id":7470078,
    "tgn:name":"Hengzhenzhuang",
    "tgn:placetype":[
        "aat:300008347"
    ]
},
  "bbox": [],
  "geometry": {"coordinates":[120.613056,24.357778],"type":"Point"}
}
=======
{"geometry":{"type":"Point","coordinates":[120.613056,24.357778]},"type":"Feature","properties":{"hierarchy":["tgn:7470078","tgn:1000004","tgn:7001009","tgn:1000141","tgn:7029392"],"placetype":["aat:300008347"],"id":7470078,"name:xx":"Hengzhenzhuang"}}
>>>>>>> 03f74aca74312dbeaf24d7e61306dd6a786dc3d0
