{
  "id": 2570945,
  "type": "Feature",
  "properties": {
    "tgn:hierarchy":[
        "tgn:2570945",
        "tgn:1000001",
        "tgn:7012149",
        "tgn:2000931",
        "tgn:7007515",
        "tgn:7029392"
    ],
    "tgn:id":2570945,
    "tgn:name":"Patterson Hill",
    "tgn:placetype":[
        "aat:300008798"
    ]
},
  "bbox": [],
  "geometry": {"coordinates":[-69.05,44.3667],"type":"Point"}
}