{
  "id": 7197109,
  "type": "Feature",
  "properties": {
    "tgn:hierarchy":[
        "tgn:7197109",
        "tgn:1000003",
        "tgn:7003678",
        "tgn:7000084",
        "tgn:7029392"
    ],
    "tgn:id":7197109,
    "tgn:name":"Am Dommel",
    "tgn:placetype":[
        "aat:300000206"
    ]
},
  "bbox": [],
  "geometry": {"coordinates":[8.683333,51.333333],"type":"Point"}
}