{
  "id": 7290331,
  "type": "Feature",
  "properties": {
    "tgn:hierarchy":[
        "tgn:7290331",
        "tgn:7016598",
        "tgn:1000049",
        "tgn:1000002",
        "tgn:7029392"
    ],
    "tgn:id":7290331,
    "tgn:name":"Domingo Ramos",
    "tgn:placetype":[
        "aat:300008697"
    ]
},
  "bbox": [],
  "geometry": {"coordinates":[-68.333333,-23.05],"type":"Point"}
}