{
  "id": 2347039,
  "type": "Feature",
  "properties": {
    "tgn:hierarchy":[
        "tgn:2347039",
        "tgn:1000001",
        "tgn:7012149",
        "tgn:2000491",
        "tgn:7007250",
        "tgn:7029392"
    ],
    "tgn:id":2347039,
    "tgn:name":"General Mine",
    "tgn:placetype":[
        "aat:300000390"
    ]
},
  "bbox": [],
  "geometry": {"coordinates":[-116.2167,47.5167],"type":"Point"}
}