{
  "id": 7132620,
  "type": "Feature",
  "properties": {
    "tgn:hierarchy":[
        "tgn:7132620",
        "tgn:1000003",
        "tgn:7003678",
        "tgn:7000084",
        "tgn:7029392"
    ],
    "tgn:id":7132620,
    "tgn:name":"Matzenh\u00f6he",
    "tgn:placetype":[
        "aat:300008777"
    ]
},
  "bbox": [],
  "geometry": {"coordinates":[8.966667,51.35],"type":"Point"}
}