{
  "id": 1037586,
  "type": "Feature",
  "properties": {
    "tgn:hierarchy":[
        "tgn:1037586",
        "tgn:1000003",
        "tgn:7000094",
        "tgn:7000084",
        "tgn:7029392"
    ],
    "tgn:id":1037586,
    "tgn:name":"Ribnitz-Damgarten",
    "tgn:placetype":[
        "aat:300008347"
    ]
},
  "bbox": [],
  "geometry": {"coordinates":[12.466667,54.25],"type":"Point"}
}