{
  "id": 7267200,
  "type": "Feature",
  "properties": {
    "tgn:hierarchy":[
        "tgn:7267200",
        "tgn:1000003",
        "tgn:7003613",
        "tgn:7016845",
        "tgn:7029392"
    ],
    "tgn:id":7267200,
    "tgn:name:nl":"Oude Zuurdijkster Uiterdijkspolder",
    "tgn:placetype":[
        "aat:300006163"
    ]
},
  "bbox": [],
  "geometry": {"coordinates":[6.35,53.333333],"type":"Point"}
}