{
  "id": 7299324,
  "type": "Feature",
  "properties": {
    "tgn:hierarchy":[
        "tgn:7299324",
        "tgn:7002829",
        "tgn:1000003",
        "tgn:7002786",
        "tgn:1000095",
        "tgn:7029392"
    ],
    "tgn:id":7299324,
    "tgn:name":"Toca",
    "tgn:placetype":[
        "aat:300008347"
    ]
},
  "bbox": [],
  "geometry": {"coordinates":[-7.266667,42.716667],"type":"Point"}
}