{
  "id": 2164558,
  "type": "Feature",
  "properties": {
    "tgn:hierarchy":[
        "tgn:2164558",
        "tgn:1000001",
        "tgn:7012149",
        "tgn:2001312",
        "tgn:7007524",
        "tgn:7029392"
    ],
    "tgn:id":2164558,
    "tgn:name":"Berry Spring",
    "tgn:placetype":[
        "aat:300008697"
    ]
},
  "bbox": [],
  "geometry": {"coordinates":[-107.2333,47.7833],"type":"Point"}
}