{
  "id": 2044550,
  "type": "Feature",
  "properties": {
    "tgn:hierarchy":[
        "tgn:2044550",
        "tgn:1000001",
        "tgn:7012149",
        "tgn:2000930",
        "tgn:7007515",
        "tgn:7029392"
    ],
    "tgn:id":2044550,
    "tgn:name":"Cambridge",
    "tgn:placetype":[
        "aat:300008347"
    ]
},
  "bbox": [],
  "geometry": {"coordinates":[-69.4667,45.0167],"type":"Point"}
}