{
  "id": 2042772,
  "type": "Feature",
  "properties": {
    "tgn:hierarchy":[
        "tgn:2042772",
        "tgn:1000001",
        "tgn:7012149",
        "tgn:2000917",
        "tgn:7007256",
        "tgn:7029392"
    ],
    "tgn:id":2042772,
    "tgn:name":"Flat Creek",
    "tgn:placetype":[
        "aat:300008347",
        "aat:300387210"
    ]
},
  "bbox": [],
  "geometry": {"coordinates":[-92.3833,31.9667],"type":"Point"}
}