{
  "id": 2526755,
  "type": "Feature",
  "properties": {
    "tgn:hierarchy":[
        "tgn:2526755",
        "tgn:1000001",
        "tgn:7012149",
        "tgn:2002182",
        "tgn:7007919",
        "tgn:7029392"
    ],
    "tgn:id":2526755,
    "tgn:name":"Mottleys Lake",
    "tgn:placetype":[
        "aat:300006191"
    ]
},
  "bbox": [],
  "geometry": {"coordinates":[-78.4667,37.3167],"type":"Point"}
}