{
  "id": 1117815,
  "type": "Feature",
  "properties": {
    "tgn:hierarchy":[
        "tgn:1117815",
        "tgn:1009227",
        "tgn:7001866",
        "tgn:1000226",
        "tgn:1000006",
        "tgn:7029392"
    ],
    "tgn:id":1117815,
    "tgn:name:en":"Pukaki, Lake",
    "tgn:placetype":[
        "aat:300008680"
    ]
},
  "bbox": [],
  "geometry": {"coordinates":[170.166667,-44.116667],"type":"Point"}
}