{
  "id": 2376528,
  "type": "Feature",
  "properties": {
    "tgn:hierarchy":[
        "tgn:2376528",
        "tgn:1000001",
        "tgn:2001261",
        "tgn:7012149",
        "tgn:7007524",
        "tgn:7029392"
    ],
    "tgn:id":2376528,
    "tgn:name":"Hardrobe Spring",
    "tgn:placetype":[
        "aat:300008697"
    ]
},
  "bbox": [],
  "geometry": {"coordinates":[-106.7833,45.4667],"type":"Point"}
}