{
  "id": 2687584,
  "type": "Feature",
  "properties": {
    "tgn:hierarchy":[
        "tgn:2687584",
        "tgn:1000001",
        "tgn:7012149",
        "tgn:2001295",
        "tgn:7007524",
        "tgn:7029392"
    ],
    "tgn:id":2687584,
    "tgn:name":"Spring Park Butte",
    "tgn:placetype":[
        "aat:300008798"
    ]
},
  "bbox": [],
  "geometry": {"coordinates":[-108.4833,47.9167],"type":"Point"}
}