<<<<<<< HEAD
{
  "id": 2155094,
  "type": "Feature",
  "properties": {
    "tgn:hierarchy":[
        "tgn:2155094",
        "tgn:1000001",
        "tgn:7012149",
        "tgn:2001032",
        "tgn:7007521",
        "tgn:7029392"
    ],
    "tgn:id":2155094,
    "tgn:name":"Bear Lake",
    "tgn:placetype":[
        "aat:300008680"
    ]
},
  "bbox": [],
  "geometry": {"coordinates":[-94.9833,45.3],"type":"Point"}
}
=======
{"geometry":{"type":"Point","coordinates":[-94.983300,45.300000]},"type":"Feature","properties":{"hierarchy":["tgn:2155094","tgn:1000001","tgn:7012149","tgn:2001032","tgn:7007521","tgn:7029392"],"placetype":["aat:300008680"],"id":2155094,"name:xx":"Bear Lake"}}
>>>>>>> 03f74aca74312dbeaf24d7e61306dd6a786dc3d0
