{
  "id": 2431427,
  "type": "Feature",
  "properties": {
    "tgn:hierarchy":[
        "tgn:2431427",
        "tgn:2000452",
        "tgn:1000001",
        "tgn:7012149",
        "tgn:7007250",
        "tgn:7029392"
    ],
    "tgn:id":2431427,
    "tgn:name":"Karnes Lateral",
    "tgn:placetype":[
        "aat:300006075"
    ]
},
  "bbox": [],
  "geometry": {"coordinates":[-116.3333,43.6333],"type":"Point"}
}