{
  "id": 7278237,
  "type": "Feature",
  "properties": {
    "tgn:hierarchy":[
        "tgn:7278237",
        "tgn:1001637",
        "tgn:1000049",
        "tgn:1000002",
        "tgn:7029392"
    ],
    "tgn:id":7278237,
    "tgn:name":"Buey, Rocas",
    "tgn:placetype":[
        "aat:300011692"
    ]
},
  "bbox": [],
  "geometry": {"coordinates":[-73.083333,-36.625],"type":"Point"}
}