{
  "id": 1080508,
  "type": "Feature",
  "properties": {
    "tgn:hierarchy":[
        "tgn:1080508",
        "tgn:1001035",
        "tgn:1000004",
        "tgn:7000903",
        "tgn:1000120",
        "tgn:7029392"
    ],
    "tgn:id":1080508,
    "tgn:name":"Kawashima",
    "tgn:placetype":[
        "aat:300008347"
    ]
},
  "bbox": [],
  "geometry": {"coordinates":[134.3167,34.0667],"type":"Point"}
}