<<<<<<< HEAD
{
  "id": 7058482,
  "type": "Feature",
  "properties": {
    "tgn:hierarchy":[
        "tgn:7058482",
        "tgn:1003489",
        "tgn:7004610",
        "tgn:1000003",
        "tgn:1000080",
        "tgn:7029392"
    ],
    "tgn:id":7058482,
    "tgn:name":"Alvo, Torrente",
    "tgn:placetype":[
        "aat:300008699"
    ]
},
  "bbox": [],
  "geometry": {"coordinates":[16.05,40.716667],"type":"Point"}
}
=======
{"geometry":{"type":"Point","coordinates":[16.050000,40.716667]},"type":"Feature","properties":{"hierarchy":["tgn:7058482","tgn:1003489","tgn:7004610","tgn:1000003","tgn:1000080","tgn:7029392"],"placetype":["aat:300008699"],"id":7058482,"name:xx":"Alvo, Torrente"}}
>>>>>>> 03f74aca74312dbeaf24d7e61306dd6a786dc3d0
