{
  "id": 1051365,
  "type": "Feature",
  "properties": {
    "tgn:hierarchy":[
        "tgn:1051365",
        "tgn:1000004",
        "tgn:1003384",
        "tgn:7014786",
        "tgn:7029392"
    ],
    "tgn:id":1051365,
    "tgn:name":"Chiili",
    "tgn:placetype":[
        "aat:300008347"
    ]
},
  "bbox": [],
  "geometry": {"coordinates":[66.6167,44.1667],"type":"Point"}
}