{
  "id": 2732617,
  "type": "Feature",
  "properties": {
    "tgn:hierarchy":[
        "tgn:2732617",
        "tgn:1000001",
        "tgn:7012149",
        "tgn:2000738",
        "tgn:7007254",
        "tgn:7029392"
    ],
    "tgn:id":2732617,
    "tgn:name":"Turkey Creek",
    "tgn:placetype":[
        "aat:300008706"
    ]
},
  "bbox": [],
  "geometry": {"coordinates":[-97.4833,39.7333],"type":"Point"}
}