{
  "id": 1059721,
  "type": "Feature",
  "properties": {
    "tgn:hierarchy":[
        "tgn:1059721",
        "tgn:1000004",
        "tgn:7012941",
        "tgn:7018214",
        "tgn:7002435",
        "tgn:7029392"
    ],
    "tgn:id":1059721,
    "tgn:name":"Staraya Toropa",
    "tgn:placetype":[
        "aat:300008347"
    ]
},
  "bbox": [],
  "geometry": {"coordinates":[31.6833,56.2833],"type":"Point"}
}