{
  "id": 2663565,
  "type": "Feature",
  "properties": {
    "tgn:hierarchy":[
        "tgn:2663565",
        "tgn:1000001",
        "tgn:1002209",
        "tgn:7012149",
        "tgn:7007252",
        "tgn:7029392"
    ],
    "tgn:id":2663565,
    "tgn:name":"Silver Hook Lake",
    "tgn:placetype":[
        "aat:300006191"
    ]
},
  "bbox": [],
  "geometry": {"coordinates":[-86.1667,39.1167],"type":"Point"}
}