{
  "id": 2507190,
  "type": "Feature",
  "properties": {
    "tgn:hierarchy":[
        "tgn:2507190",
        "tgn:1000001",
        "tgn:7012149",
        "tgn:1002547",
        "tgn:7007919",
        "tgn:7029392"
    ],
    "tgn:id":2507190,
    "tgn:name":"Metomkin Point",
    "tgn:placetype":[
        "aat:300008850"
    ]
},
  "bbox": [],
  "geometry": {"coordinates":[-77.1333,38.3667],"type":"Point"}
}