{
  "id": 7432899,
  "type": "Feature",
  "properties": {
    "tgn:hierarchy":[
        "tgn:7432899",
        "tgn:7005584",
        "tgn:1000001",
        "tgn:7005560",
        "tgn:7029392"
    ],
    "tgn:id":7432899,
    "tgn:name":"Y\u00f3stiro",
    "tgn:placetype":[
        "aat:300008347"
    ]
},
  "bbox": [],
  "geometry": {"coordinates":[-101.383333,20.566667],"type":"Point"}
}