{
  "id": 1088816,
  "type": "Feature",
  "properties": {
    "tgn:hierarchy":[
        "tgn:1088816",
        "tgn:7001242",
        "tgn:1001346",
        "tgn:1000159",
        "tgn:7029392"
    ],
    "tgn:id":1088816,
    "tgn:name":"Bibanga",
    "tgn:placetype":[
        "aat:300008347"
    ]
},
  "bbox": [],
  "geometry": {"coordinates":[23.9167,-6.2833],"type":"Point"}
}