{
  "id": 7262438,
  "type": "Feature",
  "properties": {
    "tgn:hierarchy":[
        "tgn:7262438",
        "tgn:1000003",
        "tgn:7006951",
        "tgn:7016845",
        "tgn:7029392"
    ],
    "tgn:id":7262438,
    "tgn:name:nl":"Breehorn",
    "tgn:placetype":[
        "aat:300132350"
    ]
},
  "bbox": [],
  "geometry": {"coordinates":[4.966667,52.933333],"type":"Point"}
}