{
  "id": 7472558,
  "type": "Feature",
  "properties": {
    "tgn:hierarchy":[
        "tgn:7472558",
        "tgn:1000004",
        "tgn:1000959",
        "tgn:1000141",
        "tgn:7029392"
    ],
    "tgn:id":7472558,
    "tgn:name":"Yongjian Guoxiao",
    "tgn:placetype":[
        "aat:300006495"
    ]
},
  "bbox": [],
  "geometry": {"coordinates":[121.550671,24.988582],"type":"Point"}
}