{
  "id": 7343386,
  "type": "Feature",
  "properties": {
    "tgn:hierarchy":[
        "tgn:7343386",
        "tgn:7002758",
        "tgn:7002830",
        "tgn:1000003",
        "tgn:1000095",
        "tgn:7029392"
    ],
    "tgn:id":7343386,
    "tgn:name":"Cala, Arroyo de la",
    "tgn:placetype":[
        "aat:300008699"
    ]
},
  "bbox": [],
  "geometry": {"coordinates":[-5.133333,36.416667],"type":"Point"}
}