{
  "id": 7344289,
  "type": "Feature",
  "properties": {
    "tgn:hierarchy":[
        "tgn:7344289",
        "tgn:7010420",
        "tgn:1000003",
        "tgn:7002795",
        "tgn:1000095",
        "tgn:7029392"
    ],
    "tgn:id":7344289,
    "tgn:name":"Baezuela",
    "tgn:placetype":[
        "aat:300008347"
    ]
},
  "bbox": [],
  "geometry": {"coordinates":[-3.433333,40.45],"type":"Point"}
}