{
  "id": 7514479,
  "type": "Feature",
  "properties": {
    "tgn:hierarchy":[
        "tgn:7514479",
        "tgn:1008380",
        "tgn:1000226",
        "tgn:7016827",
        "tgn:1000006",
        "tgn:7029392"
    ],
    "tgn:id":7514479,
    "tgn:name:en":"Dive, Lake",
    "tgn:placetype":[
        "aat:300008680"
    ]
},
  "bbox": [],
  "geometry": {"coordinates":[174.066667,-39.333333],"type":"Point"}
}