{
  "id": 2342478,
  "type": "Feature",
  "properties": {
    "tgn:hierarchy":[
        "tgn:2342478",
        "tgn:1000001",
        "tgn:7012149",
        "tgn:1002586",
        "tgn:7007710",
        "tgn:7029392"
    ],
    "tgn:id":2342478,
    "tgn:name":"Fullerton",
    "tgn:placetype":[
        "aat:300008347"
    ]
},
  "bbox": [],
  "geometry": {"coordinates":[-75.4667,40.6167],"type":"Point"}
}