{
  "id": 2625966,
  "type": "Feature",
  "properties": {
    "tgn:hierarchy":[
        "tgn:2625966",
        "tgn:1000001",
        "tgn:1002480",
        "tgn:7012149",
        "tgn:7007564",
        "tgn:7029392"
    ],
    "tgn:id":2625966,
    "tgn:name":"Rocky Brook",
    "tgn:placetype":[
        "aat:300008699"
    ]
},
  "bbox": [],
  "geometry": {"coordinates":[-71.75,42.7333],"type":"Point"}
}