{
  "id": 7492622,
  "type": "Feature",
  "properties": {
    "tgn:hierarchy":[
        "tgn:7492622",
        "tgn:1000004",
        "tgn:7471332",
        "tgn:1000141",
        "tgn:7029392"
    ],
    "tgn:id":7492622,
    "tgn:name":"Bilin Shan",
    "tgn:placetype":[
        "aat:300008798"
    ]
},
  "bbox": [],
  "geometry": {"coordinates":[121.081111,24.540833],"type":"Point"}
}