{
  "id": 7586313,
  "type": "Feature",
  "properties": {
    "tgn:hierarchy":[
        "tgn:7586313",
        "tgn:1000004",
        "tgn:7000198",
        "tgn:7000799",
        "tgn:7029392"
    ],
    "tgn:id":7586313,
    "tgn:name:en":"Takia Arz\u0101n S\u0101hib",
    "tgn:placetype":[
        "aat:300008347"
    ]
},
  "bbox": [],
  "geometry": {"coordinates":[74.480722,34.374647],"type":"Point"}
}