{
  "id": 7402784,
  "type": "Feature",
  "properties": {
    "tgn:hierarchy":[
        "tgn:7402784",
        "tgn:1000001",
        "tgn:1001937",
        "tgn:7005560",
        "tgn:7029392"
    ],
    "tgn:id":7402784,
    "tgn:name":"Emiliano Zapata",
    "tgn:placetype":[
        "aat:300008347"
    ]
},
  "bbox": [],
  "geometry": {"coordinates":[-87.1375,20.833333],"type":"Point"}
}