{
  "id": 7359039,
  "type": "Feature",
  "properties": {
    "tgn:hierarchy":[
        "tgn:7359039",
        "tgn:1000001",
        "tgn:7005597",
        "tgn:7005560",
        "tgn:7029392"
    ],
    "tgn:id":7359039,
    "tgn:name":"El \u00c1guila",
    "tgn:placetype":[
        "aat:300008347"
    ]
},
  "bbox": [],
  "geometry": {"coordinates":[-99.633333,27.033333],"type":"Point"}
}