{
  "id": 2356092,
  "type": "Feature",
  "properties": {
    "tgn:hierarchy":[
        "tgn:2356092",
        "tgn:1000001",
        "tgn:7012149",
        "tgn:2001545",
        "tgn:7007709",
        "tgn:7029392"
    ],
    "tgn:id":2356092,
    "tgn:name":"Goose Pond Island",
    "tgn:placetype":[
        "aat:300008791"
    ]
},
  "bbox": [],
  "geometry": {"coordinates":[-76.0167,35.9333],"type":"Point"}
}