{
  "id": 7274687,
  "type": "Feature",
  "properties": {
    "tgn:hierarchy":[
        "tgn:7274687",
        "tgn:1000003",
        "tgn:7003622",
        "tgn:7016845",
        "tgn:7029392"
    ],
    "tgn:id":7274687,
    "tgn:name:nl":"Wolfrath",
    "tgn:placetype":[
        "aat:300387502"
    ]
},
  "bbox": [],
  "geometry": {"coordinates":[5.833333,51.05],"type":"Point"}
}