{
  "id": 7331969,
  "type": "Feature",
  "properties": {
    "tgn:hierarchy":[
        "tgn:7331969",
        "tgn:7010420",
        "tgn:1000003",
        "tgn:7002795",
        "tgn:1000095",
        "tgn:7029392"
    ],
    "tgn:id":7331969,
    "tgn:name":"La Paradilla",
    "tgn:placetype":[
        "aat:300008347"
    ]
},
  "bbox": [],
  "geometry": {"coordinates":[-4.25,40.566667],"type":"Point"}
}