{
  "id": 7551409,
  "type": "Feature",
  "properties": {
    "tgn:hierarchy":[
        "tgn:7551409",
        "tgn:1000004",
        "tgn:7000198",
        "tgn:1001894",
        "tgn:7029392"
    ],
    "tgn:id":7551409,
    "tgn:name:en":"Bolegaon",
    "tgn:placetype":[
        "aat:300008347"
    ]
},
  "bbox": [],
  "geometry": {"coordinates":[80.459044,21.532628],"type":"Point"}
}