{
  "id": 2269004,
  "type": "Feature",
  "properties": {
    "tgn:hierarchy":[
        "tgn:2269004",
        "tgn:2001468",
        "tgn:1000001",
        "tgn:7012149",
        "tgn:7007709",
        "tgn:7029392"
    ],
    "tgn:id":2269004,
    "tgn:name":"Crossnore Creek",
    "tgn:placetype":[
        "aat:300008706"
    ]
},
  "bbox": [],
  "geometry": {"coordinates":[-81.9333,36.0333],"type":"Point"}
}