{
  "id": 2359967,
  "type": "Feature",
  "properties": {
    "tgn:hierarchy":[
        "tgn:2359967",
        "tgn:1000001",
        "tgn:7012149",
        "tgn:2000220",
        "tgn:7007158",
        "tgn:7029392"
    ],
    "tgn:id":2359967,
    "tgn:name":"Grass Creek",
    "tgn:placetype":[
        "aat:300008706"
    ]
},
  "bbox": [],
  "geometry": {"coordinates":[-105.95,40.5167],"type":"Point"}
}