{
  "id": 2460351,
  "type": "Feature",
  "properties": {
    "tgn:hierarchy":[
        "tgn:2460351",
        "tgn:1000001",
        "tgn:7012149",
        "tgn:7007254",
        "tgn:7029392"
    ],
    "tgn:id":2460351,
    "tgn:name":"Little Salt Creek",
    "tgn:placetype":[
        "aat:300008706"
    ]
},
  "bbox": [],
  "geometry": {"coordinates":[-96.1167,37.5833],"type":"Point"}
}