{
  "id": 7414166,
  "type": "Feature",
  "properties": {
    "tgn:hierarchy":[
        "tgn:7414166",
        "tgn:7005580",
        "tgn:1000001",
        "tgn:7005560",
        "tgn:7029392"
    ],
    "tgn:id":7414166,
    "tgn:name":"Cachimba, Cerro",
    "tgn:placetype":[
        "aat:300008795"
    ]
},
  "bbox": [],
  "geometry": {"coordinates":[-93.916667,16.641667],"type":"Point"}
}