<<<<<<< HEAD
{
  "id": 7243112,
  "type": "Feature",
  "properties": {
    "tgn:hierarchy":[
        "tgn:7243112",
        "tgn:7018239",
        "tgn:1000003",
        "tgn:1000063",
        "tgn:7018236",
        "tgn:7029392"
    ],
    "tgn:id":7243112,
    "tgn:name":"Luttelkool",
    "tgn:placetype":[
        "aat:300000206"
    ]
},
  "bbox": [],
  "geometry": {"coordinates":[4.85,50.933333],"type":"Point"}
}
=======
{"geometry":{"type":"Point","coordinates":[4.850000,50.933333]},"type":"Feature","properties":{"hierarchy":["tgn:7243112","tgn:7018239","tgn:1000003","tgn:1000063","tgn:7018236","tgn:7029392"],"placetype":["aat:300000206"],"id":7243112,"name:xx":"Luttelkool"}}
>>>>>>> 03f74aca74312dbeaf24d7e61306dd6a786dc3d0
