{
  "id": 1076284,
  "type": "Feature",
  "properties": {
    "tgn:hierarchy":[
        "tgn:1076284",
        "tgn:1000004",
        "tgn:1001832",
        "tgn:7000198",
        "tgn:7029392"
    ],
    "tgn:id":1076284,
    "tgn:name:en":"Murkong Selek",
    "tgn:placetype":[
        "aat:300008347"
    ]
},
  "bbox": [],
  "geometry": {"coordinates":[95.228,27.825],"type":"Point"}
}