{
  "id": 2762977,
  "type": "Feature",
  "properties": {
    "tgn:hierarchy":[
        "tgn:2762977",
        "tgn:1000001",
        "tgn:7012149",
        "tgn:7014021",
        "tgn:7007709",
        "tgn:7029392"
    ],
    "tgn:id":2762977,
    "tgn:name":"Westmoreland",
    "tgn:placetype":[
        "aat:300008347"
    ]
},
  "bbox": [],
  "geometry": {"coordinates":[-80.9833,35.2333],"type":"Point"}
}