<<<<<<< HEAD
{
  "id": 7024661,
  "type": "Feature",
  "properties": {
    "tgn:hierarchy":[
        "tgn:7024661",
        "tgn:1000003",
        "tgn:7003678",
        "tgn:7000084",
        "tgn:7029392"
    ],
    "tgn:id":7024661,
    "tgn:name":"Eder",
    "tgn:placetype":[
        "aat:300008707",
        "aat:300008699"
    ]
},
  "bbox": [],
  "geometry": {"coordinates":[9.2,51.533333],"type":"Point"}
}
=======
{"geometry":{"type":"Point","coordinates":[9.200000,51.533333]},"type":"Feature","properties":{"hierarchy":["tgn:7024661","tgn:1000003","tgn:7003678","tgn:7000084","tgn:7029392"],"placetype":["aat:300008707","aat:300008699"],"id":7024661,"name:xx":"Eder"}}
>>>>>>> 03f74aca74312dbeaf24d7e61306dd6a786dc3d0
