{
  "id": 7429580,
  "type": "Feature",
  "properties": {
    "tgn:hierarchy":[
        "tgn:7429580",
        "tgn:1001853",
        "tgn:1000001",
        "tgn:7005560",
        "tgn:7029392"
    ],
    "tgn:id":7429580,
    "tgn:name":"Estaci\u00f3n Claudia",
    "tgn:placetype":[
        "aat:300007783"
    ]
},
  "bbox": [],
  "geometry": {"coordinates":[-103.116667,25.333333],"type":"Point"}
}