{
  "id": 7400929,
  "type": "Feature",
  "properties": {
    "tgn:hierarchy":[
        "tgn:7400929",
        "tgn:1000001",
        "tgn:7005599",
        "tgn:7005560",
        "tgn:7029392"
    ],
    "tgn:id":7400929,
    "tgn:name":"Lomas de Las Flores",
    "tgn:placetype":[
        "aat:300008347"
    ]
},
  "bbox": [],
  "geometry": {"coordinates":[-97.047222,20.033333],"type":"Point"}
}