{
  "id": 2585889,
  "type": "Feature",
  "properties": {
    "tgn:hierarchy":[
        "tgn:2585889",
        "tgn:1000001",
        "tgn:7012149",
        "tgn:2000183",
        "tgn:7007157",
        "tgn:7029392"
    ],
    "tgn:id":2585889,
    "tgn:name":"Piper Peak",
    "tgn:placetype":[
        "aat:300008798"
    ]
},
  "bbox": [],
  "geometry": {"coordinates":[-118.3833,37.15],"type":"Point"}
}