{
  "id": 7535217,
  "type": "Feature",
  "properties": {
    "tgn:hierarchy":[
        "tgn:7535217",
        "tgn:7001242",
        "tgn:7016833",
        "tgn:1001113",
        "tgn:7029392"
    ],
    "tgn:id":7535217,
    "tgn:name":"Kafr A\u1e29mad Burh\u0101m",
    "tgn:placetype":[
        "aat:300008347"
    ]
},
  "bbox": [],
  "geometry": {"coordinates":[31.60594,30.609611],"type":"Point"}
}