{
  "id": 2240293,
  "type": "Feature",
  "properties": {
    "tgn:hierarchy":[
        "tgn:2240293",
        "tgn:2002308",
        "tgn:1000001",
        "tgn:7012149",
        "tgn:7007922",
        "tgn:7029392"
    ],
    "tgn:id":2240293,
    "tgn:name":"Cisco Lake",
    "tgn:placetype":[
        "aat:300008680"
    ]
},
  "bbox": [],
  "geometry": {"coordinates":[-91.25,46.35],"type":"Point"}
}