{
  "id": 2238986,
  "type": "Feature",
  "properties": {
    "tgn:hierarchy":[
        "tgn:2238986",
        "tgn:1000001",
        "tgn:7012149",
        "tgn:7014185",
        "tgn:7007710",
        "tgn:7029392"
    ],
    "tgn:id":2238986,
    "tgn:name":"Christopher Gist Cave",
    "tgn:placetype":[
        "aat:300008746"
    ]
},
  "bbox": [],
  "geometry": {"coordinates":[-79.9167,39.9167],"type":"Point"}
}