{
  "id": 7333368,
  "type": "Feature",
  "properties": {
    "tgn:hierarchy":[
        "tgn:7333368",
        "tgn:7002826",
        "tgn:7001158",
        "tgn:1000003",
        "tgn:1000095",
        "tgn:7029392"
    ],
    "tgn:id":7333368,
    "tgn:name":"Folloso",
    "tgn:placetype":[
        "aat:300008347"
    ]
},
  "bbox": [],
  "geometry": {"coordinates":[-6.016667,42.766667],"type":"Point"}
}