<<<<<<< HEAD
{
  "id": 7112068,
  "type": "Feature",
  "properties": {
    "tgn:hierarchy":[
        "tgn:7112068",
        "tgn:7003692",
        "tgn:1000003",
        "tgn:7000084",
        "tgn:7029392"
    ],
    "tgn:id":7112068,
    "tgn:name":"Ringsheim",
    "tgn:placetype":[
        "aat:300008347"
    ]
},
  "bbox": [],
  "geometry": {"coordinates":[7.783333,48.25],"type":"Point"}
}
=======
{"geometry":{"type":"Point","coordinates":[7.783333,48.250000]},"type":"Feature","properties":{"hierarchy":["tgn:7112068","tgn:7003692","tgn:1000003","tgn:7000084","tgn:7029392"],"placetype":["aat:300008347"],"id":7112068,"name:xx":"Ringsheim"}}
>>>>>>> 03f74aca74312dbeaf24d7e61306dd6a786dc3d0
