{
  "id": 7038512,
  "type": "Feature",
  "properties": {
    "tgn:hierarchy":[
        "tgn:7038512",
        "tgn:1001724",
        "tgn:1000003",
        "tgn:7003121",
        "tgn:1000080",
        "tgn:7029392"
    ],
    "tgn:id":7038512,
    "tgn:name":"Tino, Riu",
    "tgn:placetype":[
        "aat:300008699"
    ]
},
  "bbox": [],
  "geometry": {"coordinates":[9.133333,40.116667],"type":"Point"}
}