{
  "id": 2689238,
  "type": "Feature",
  "properties": {
    "tgn:hierarchy":[
        "tgn:2689238",
        "tgn:1000001",
        "tgn:7006451",
        "tgn:2000094",
        "tgn:7012149",
        "tgn:7029392"
    ],
    "tgn:id":2689238,
    "tgn:name":"Squaw Creek",
    "tgn:placetype":[
        "aat:300008706"
    ]
},
  "bbox": [],
  "geometry": {"coordinates":[-110.2333,33.0333],"type":"Point"}
}