<<<<<<< HEAD
{
  "id": 7352685,
  "type": "Feature",
  "properties": {
    "tgn:hierarchy":[
        "tgn:7352685",
        "tgn:7005581",
        "tgn:1000001",
        "tgn:7005560",
        "tgn:7029392"
    ],
    "tgn:id":7352685,
    "tgn:name":"Basuchito",
    "tgn:placetype":[
        "aat:300008347"
    ]
},
  "bbox": [],
  "geometry": {"coordinates":[-108.25,28.183333],"type":"Point"}
}
=======
{"geometry":{"type":"Point","coordinates":[-108.250000,28.183333]},"type":"Feature","properties":{"hierarchy":["tgn:7352685","tgn:7005581","tgn:1000001","tgn:7005560","tgn:7029392"],"placetype":["aat:300008347"],"id":7352685,"name:xx":"Basuchito"}}
>>>>>>> 03f74aca74312dbeaf24d7e61306dd6a786dc3d0
