{
  "id": 2625936,
  "type": "Feature",
  "properties": {
    "tgn:hierarchy":[
        "tgn:2625936",
        "tgn:1000001",
        "tgn:7012149",
        "tgn:2002178",
        "tgn:7007919",
        "tgn:7029392"
    ],
    "tgn:id":2625936,
    "tgn:name":"Rocky Branch",
    "tgn:placetype":[
        "aat:300008699"
    ]
},
  "bbox": [],
  "geometry": {"coordinates":[-78.3167,38.6833],"type":"Point"}
}