{
  "id": 1123908,
  "type": "Feature",
  "properties": {
    "tgn:hierarchy":[
        "tgn:1123908",
        "tgn:7006260",
        "tgn:7002454",
        "tgn:1000047",
        "tgn:1000002",
        "tgn:7029392"
    ],
    "tgn:id":1123908,
    "tgn:name":"Ferro",
    "tgn:placetype":[
        "aat:300008707"
    ]
},
  "bbox": [],
  "geometry": {"coordinates":[-54.5167,-12.45],"type":"Point"}
}