{
  "id": 1040133,
  "type": "Feature",
  "properties": {
    "tgn:hierarchy":[
        "tgn:1040133",
        "tgn:1000003",
        "tgn:7003677",
        "tgn:7000084",
        "tgn:7029392"
    ],
    "tgn:id":1040133,
    "tgn:name":"Lindlar",
    "tgn:placetype":[
        "aat:300008347"
    ]
},
  "bbox": [],
  "geometry": {"coordinates":[7.383333,51.016667],"type":"Point"}
}