{
  "id": 2447287,
  "type": "Feature",
  "properties": {
    "tgn:hierarchy":[
        "tgn:2447287",
        "tgn:1000001",
        "tgn:7012149",
        "tgn:7015778",
        "tgn:7007919",
        "tgn:7029392"
    ],
    "tgn:id":2447287,
    "tgn:name":"Lick Branch",
    "tgn:placetype":[
        "aat:300008699"
    ]
},
  "bbox": [],
  "geometry": {"coordinates":[-77.6167,38.85],"type":"Point"}
}