{
  "id": 7592517,
  "type": "Feature",
  "properties": {
    "tgn:hierarchy":[
        "tgn:7592517",
        "tgn:1000004",
        "tgn:7000198",
        "tgn:7000799",
        "tgn:7029392"
    ],
    "tgn:id":7592517,
    "tgn:name:en":"Pung\u0101l\u012bw\u0101li Rakh",
    "tgn:placetype":[
        "aat:300008863"
    ]
},
  "bbox": [],
  "geometry": {"coordinates":[74.879167,32.848611],"type":"Point"}
}