{
  "id": 2368074,
  "type": "Feature",
  "properties": {
    "tgn:hierarchy":[
        "tgn:2368074",
        "tgn:1000001",
        "tgn:7012149",
        "tgn:2000346",
        "tgn:7007248",
        "tgn:7029392"
    ],
    "tgn:id":2368074,
    "tgn:name":"Grusher Branch",
    "tgn:placetype":[
        "aat:300008699"
    ]
},
  "bbox": [],
  "geometry": {"coordinates":[-84.4333,34.9667],"type":"Point"}
}