{
  "id": 2532366,
  "type": "Feature",
  "properties": {
    "tgn:hierarchy":[
        "tgn:2532366",
        "tgn:1000001",
        "tgn:2000458",
        "tgn:7012149",
        "tgn:7007250",
        "tgn:7029392"
    ],
    "tgn:id":2532366,
    "tgn:name":"Murdock Creek",
    "tgn:placetype":[
        "aat:300008706"
    ]
},
  "bbox": [],
  "geometry": {"coordinates":[-114.3333,43.8333],"type":"Point"}
}