<<<<<<< HEAD
{
  "id": 7245901,
  "type": "Feature",
  "properties": {
    "tgn:hierarchy":[
        "tgn:7245901",
        "tgn:7003461",
        "tgn:1000003",
        "tgn:1000063",
        "tgn:7018236",
        "tgn:7029392"
    ],
    "tgn:id":7245901,
    "tgn:name":"De Reiterschans",
    "tgn:placetype":[
        "aat:300000206"
    ]
},
  "bbox": [],
  "geometry": {"coordinates":[5.066667,51.066667],"type":"Point"}
}
=======
{"geometry":{"type":"Point","coordinates":[5.066667,51.066667]},"type":"Feature","properties":{"hierarchy":["tgn:7245901","tgn:7003461","tgn:1000003","tgn:1000063","tgn:7018236","tgn:7029392"],"placetype":["aat:300000206"],"id":7245901,"name:xx":"De Reiterschans"}}
>>>>>>> 03f74aca74312dbeaf24d7e61306dd6a786dc3d0
