<<<<<<< HEAD
{
  "id": 2767552,
  "type": "Feature",
  "properties": {
    "tgn:hierarchy":[
        "tgn:2767552",
        "tgn:1000001",
        "tgn:2001416",
        "tgn:7012149",
        "tgn:7007526",
        "tgn:7029392"
    ],
    "tgn:id":2767552,
    "tgn:name":"White Wash",
    "tgn:placetype":[
        "aat:300008699"
    ]
},
  "bbox": [],
  "geometry": {"coordinates":[-114.2,37.7333],"type":"Point"}
}
=======
{"geometry":{"type":"Point","coordinates":[-114.200000,37.733300]},"type":"Feature","properties":{"hierarchy":["tgn:2767552","tgn:1000001","tgn:2001416","tgn:7012149","tgn:7007526","tgn:7029392"],"placetype":["aat:300008699"],"id":2767552,"name:xx":"White Wash"}}
>>>>>>> 03f74aca74312dbeaf24d7e61306dd6a786dc3d0
