{
  "id": 7587102,
  "type": "Feature",
  "properties": {
    "tgn:hierarchy":[
        "tgn:7587102",
        "tgn:1000004",
        "tgn:7000198",
        "tgn:7000799",
        "tgn:7029392"
    ],
    "tgn:id":7587102,
    "tgn:name:en":"H\u0101yan",
    "tgn:placetype":[
        "aat:300008347"
    ]
},
  "bbox": [],
  "geometry": {"coordinates":[74.947236,34.232751],"type":"Point"}
}