{
  "id": 2297390,
  "type": "Feature",
  "properties": {
    "tgn:hierarchy":[
        "tgn:2297390",
        "tgn:1000001",
        "tgn:7012149",
        "tgn:2000805",
        "tgn:7007255",
        "tgn:7029392"
    ],
    "tgn:id":2297390,
    "tgn:name":"Dry Fork",
    "tgn:placetype":[
        "aat:300008699"
    ]
},
  "bbox": [],
  "geometry": {"coordinates":[-82.8667,37.4333],"type":"Point"}
}