{
  "id": 7381487,
  "type": "Feature",
  "properties": {
    "tgn:hierarchy":[
        "tgn:7381487",
        "tgn:1000001",
        "tgn:7005599",
        "tgn:7005560",
        "tgn:7029392"
    ],
    "tgn:id":7381487,
    "tgn:name":"Maloapan",
    "tgn:placetype":[
        "aat:300008347"
    ]
},
  "bbox": [],
  "geometry": {"coordinates":[-97.066667,20.066667],"type":"Point"}
}