{
  "id": 7228231,
  "type": "Feature",
  "properties": {
    "tgn:hierarchy":[
        "tgn:7228231",
        "tgn:7002692",
        "tgn:7012056",
        "tgn:1000003",
        "tgn:1000074",
        "tgn:7029392"
    ],
    "tgn:id":7228231,
    "tgn:name":"Lim\u00edn Kherson\u00edsou",
    "tgn:placetype":[
        "aat:300008347"
    ]
},
  "bbox": [],
  "geometry": {"coordinates":[25.383333,35.316667],"type":"Point"}
}