<<<<<<< HEAD
{
  "id": 7020069,
  "type": "Feature",
  "properties": {
    "tgn:hierarchy":[
        "tgn:7020069",
        "tgn:1000001",
        "tgn:7012149",
        "tgn:1002505",
        "tgn:7007920",
        "tgn:7029392"
    ],
    "tgn:id":7020069,
    "tgn:name":"Orrs Pond",
    "tgn:placetype":[
        "aat:300006191"
    ]
},
  "bbox": [],
  "geometry": {"coordinates":[-122.35,47.9667],"type":"Point"}
}
=======
{"geometry":{"type":"Point","coordinates":[-122.350000,47.966700]},"type":"Feature","properties":{"hierarchy":["tgn:7020069","tgn:1000001","tgn:7012149","tgn:1002505","tgn:7007920","tgn:7029392"],"placetype":["aat:300006191"],"id":7020069,"name:xx":"Orrs Pond"}}
>>>>>>> 03f74aca74312dbeaf24d7e61306dd6a786dc3d0
