{
  "id": 7132926,
  "type": "Feature",
  "properties": {
    "tgn:hierarchy":[
        "tgn:7132926",
        "tgn:7000096",
        "tgn:1000003",
        "tgn:7000084",
        "tgn:7029392"
    ],
    "tgn:id":7132926,
    "tgn:name":"M\u00fcrow",
    "tgn:placetype":[
        "aat:300008347"
    ]
},
  "bbox": [],
  "geometry": {"coordinates":[14.033333,53.05],"type":"Point"}
}