{
  "id": 2680621,
  "type": "Feature",
  "properties": {
    "tgn:hierarchy":[
        "tgn:2680621",
        "tgn:1000001",
        "tgn:7014423",
        "tgn:7012149",
        "tgn:7007517",
        "tgn:7029392"
    ],
    "tgn:id":2680621,
    "tgn:name":"South Hanson",
    "tgn:placetype":[
        "aat:300008347"
    ]
},
  "bbox": [],
  "geometry": {"coordinates":[-70.8667,42.0333],"type":"Point"}
}