<<<<<<< HEAD
{
  "id": 7175852,
  "type": "Feature",
  "properties": {
    "tgn:hierarchy":[
        "tgn:7175852",
        "tgn:7003692",
        "tgn:1000003",
        "tgn:7000084",
        "tgn:7029392"
    ],
    "tgn:id":7175852,
    "tgn:name":"Gro\u00dfvillars",
    "tgn:placetype":[
        "aat:300008347"
    ]
},
  "bbox": [],
  "geometry": {"coordinates":[8.7725,49.046389],"type":"Point"}
}
=======
{"geometry":{"type":"Point","coordinates":[8.772500,49.046389]},"type":"Feature","properties":{"hierarchy":["tgn:7175852","tgn:7003692","tgn:1000003","tgn:7000084","tgn:7029392"],"placetype":["aat:300008347"],"id":7175852,"name:xx":"Gro\u00dfvillars"}}
>>>>>>> 03f74aca74312dbeaf24d7e61306dd6a786dc3d0
