{
  "id": 2391368,
  "type": "Feature",
  "properties": {
    "tgn:hierarchy":[
        "tgn:2391368",
        "tgn:1000001",
        "tgn:7012149",
        "tgn:1002468",
        "tgn:7007252",
        "tgn:7029392"
    ],
    "tgn:id":2391368,
    "tgn:name":"Hillcrest Brook",
    "tgn:placetype":[
        "aat:300008699"
    ]
},
  "bbox": [],
  "geometry": {"coordinates":[-85.3333,39.9333],"type":"Point"}
}