{
  "id": 7067396,
  "type": "Feature",
  "properties": {
    "tgn:hierarchy":[
        "tgn:7067396",
        "tgn:1000003",
        "tgn:7003676",
        "tgn:7000084",
        "tgn:7029392"
    ],
    "tgn:id":7067396,
    "tgn:name":"St\u00f6ckser Holz",
    "tgn:placetype":[
        "aat:300008863"
    ]
},
  "bbox": [],
  "geometry": {"coordinates":[9.383333,52.633333],"type":"Point"}
}