<<<<<<< HEAD
{
  "id": 7475649,
  "type": "Feature",
  "properties": {
    "tgn:hierarchy":[
        "tgn:7475649",
        "tgn:1000004",
        "tgn:7001014",
        "tgn:1000141",
        "tgn:7029392"
    ],
    "tgn:id":7475649,
    "tgn:name":"Nancun Qiao",
    "tgn:placetype":[
        "aat:300007836"
    ]
},
  "bbox": [],
  "geometry": {"coordinates":[120.512582,23.750681],"type":"Point"}
}
=======
{"geometry":{"type":"Point","coordinates":[120.512582,23.750681]},"type":"Feature","properties":{"hierarchy":["tgn:7475649","tgn:1000004","tgn:7001014","tgn:1000141","tgn:7029392"],"placetype":["aat:300007836"],"id":7475649,"name:xx":"Nancun Qiao"}}
>>>>>>> 03f74aca74312dbeaf24d7e61306dd6a786dc3d0
