{
  "id": 7078799,
  "type": "Feature",
  "properties": {
    "tgn:hierarchy":[
        "tgn:7078799",
        "tgn:1000003",
        "tgn:7003677",
        "tgn:7000084",
        "tgn:7029392"
    ],
    "tgn:id":7078799,
    "tgn:name":"Wissentrup",
    "tgn:placetype":[
        "aat:300008347"
    ]
},
  "bbox": [],
  "geometry": {"coordinates":[8.766667,51.983333],"type":"Point"}
}