{
  "id": 2717471,
  "type": "Feature",
  "properties": {
    "tgn:hierarchy":[
        "tgn:2717471",
        "tgn:1000001",
        "tgn:7016172",
        "tgn:7012149",
        "tgn:2000169",
        "tgn:7029392"
    ],
    "tgn:id":2717471,
    "tgn:name":"Thola",
    "tgn:placetype":[
        "aat:300008347"
    ]
},
  "bbox": [],
  "geometry": {"coordinates":[-92.4167,35.8833],"type":"Point"}
}