{
  "id": 2742330,
  "type": "Feature",
  "properties": {
    "tgn:hierarchy":[
        "tgn:2742330",
        "tgn:1000001",
        "tgn:7012149",
        "tgn:7007826",
        "tgn:7029392"
    ],
    "tgn:id":2742330,
    "tgn:name":"Valley Branch",
    "tgn:placetype":[
        "aat:300008699"
    ]
},
  "bbox": [],
  "geometry": {"coordinates":[-97.2333,32.55],"type":"Point"}
}