{
  "id": 2743943,
  "type": "Feature",
  "properties": {
    "tgn:hierarchy":[
        "tgn:2743943",
        "tgn:1000001",
        "tgn:7012149",
        "tgn:2002090",
        "tgn:7007826",
        "tgn:7029392"
    ],
    "tgn:id":2743943,
    "tgn:name":"Venancio Tank",
    "tgn:placetype":[
        "aat:300006191"
    ]
},
  "bbox": [],
  "geometry": {"coordinates":[-99.7167,27.7333],"type":"Point"}
}