{
  "id": 2364238,
  "type": "Feature",
  "properties": {
    "tgn:hierarchy":[
        "tgn:2364238",
        "tgn:1000001",
        "tgn:7012149",
        "tgn:2000216",
        "tgn:7007158",
        "tgn:7029392"
    ],
    "tgn:id":2364238,
    "tgn:name":"Green Ridge",
    "tgn:placetype":[
        "aat:300266640"
    ]
},
  "bbox": [],
  "geometry": {"coordinates":[-105.8167,40.1833],"type":"Point"}
}