{
  "id": 7005318,
  "type": "Feature",
  "properties": {
    "tgn:hierarchy":[
        "tgn:7005318",
        "tgn:1000003",
        "tgn:7003676",
        "tgn:7000084",
        "tgn:7029392"
    ],
    "tgn:id":7005318,
    "tgn:name":"Bergen-Belsen",
    "tgn:placetype":[
        "aat:300000277",
        "aat:300167671",
        "aat:300380313",
        "aat:300000833",
        "aat:300006958"
    ]
},
  "bbox": [],
  "geometry": {"coordinates":[9.9167,52.7667],"type":"Point"}
}