{
  "id": 7503251,
  "type": "Feature",
  "properties": {
    "tgn:hierarchy":[
        "tgn:7503251",
        "tgn:7487020",
        "tgn:1000004",
        "tgn:1000141",
        "tgn:7029392"
    ],
    "tgn:id":7503251,
    "tgn:name":"Qiguling",
    "tgn:placetype":[
        "aat:300008347"
    ]
},
  "bbox": [],
  "geometry": {"coordinates":[120.841491,24.332811],"type":"Point"}
}