<<<<<<< HEAD
{
  "id": 2405970,
  "type": "Feature",
  "properties": {
    "tgn:hierarchy":[
        "tgn:2405970",
        "tgn:1000001",
        "tgn:7012149",
        "tgn:2000890",
        "tgn:7007256",
        "tgn:7029392"
    ],
    "tgn:id":2405970,
    "tgn:name":"Humbles Branch",
    "tgn:placetype":[
        "aat:300008699"
    ]
},
  "bbox": [],
  "geometry": {"coordinates":[-92.2667,32.45],"type":"Point"}
}
=======
{"geometry":{"type":"Point","coordinates":[-92.266700,32.450000]},"type":"Feature","properties":{"hierarchy":["tgn:2405970","tgn:1000001","tgn:7012149","tgn:2000890","tgn:7007256","tgn:7029392"],"placetype":["aat:300008699"],"id":2405970,"name:xx":"Humbles Branch"}}
>>>>>>> 03f74aca74312dbeaf24d7e61306dd6a786dc3d0
