<<<<<<< HEAD
{
  "id": 2256136,
  "type": "Feature",
  "properties": {
    "tgn:hierarchy":[
        "tgn:2256136",
        "tgn:1000001",
        "tgn:2001417",
        "tgn:7012149",
        "tgn:7007526",
        "tgn:7029392"
    ],
    "tgn:id":2256136,
    "tgn:name":"Copper Queen Mine",
    "tgn:placetype":[
        "aat:300000390"
    ]
},
  "bbox": [],
  "geometry": {"coordinates":[-118.1,38.5667],"type":"Point"}
}
=======
{"geometry":{"type":"Point","coordinates":[-118.100000,38.566700]},"type":"Feature","properties":{"hierarchy":["tgn:2256136","tgn:1000001","tgn:2001417","tgn:7012149","tgn:7007526","tgn:7029392"],"placetype":["aat:300000390"],"id":2256136,"name:xx":"Copper Queen Mine"}}
>>>>>>> 03f74aca74312dbeaf24d7e61306dd6a786dc3d0
