{
  "id": 2496127,
  "type": "Feature",
  "properties": {
    "tgn:hierarchy":[
        "tgn:2496127",
        "tgn:1000001",
        "tgn:7016172",
        "tgn:7012149",
        "tgn:2000148",
        "tgn:7029392"
    ],
    "tgn:id":2496127,
    "tgn:name":"Massey Mountain",
    "tgn:placetype":[
        "aat:300008798"
    ]
},
  "bbox": [],
  "geometry": {"coordinates":[-93.8667,35.8833],"type":"Point"}
}