{
  "id": 7496104,
  "type": "Feature",
  "properties": {
    "tgn:hierarchy":[
        "tgn:7496104",
        "tgn:1000004",
        "tgn:1000454",
        "tgn:1000141",
        "tgn:7029392"
    ],
    "tgn:id":7496104,
    "tgn:name":"Changfeng Sancun",
    "tgn:placetype":[
        "aat:300000498"
    ]
},
  "bbox": [],
  "geometry": {"coordinates":[121.44032,24.97759],"type":"Point"}
}