{
  "id": 2226291,
  "type": "Feature",
  "properties": {
    "tgn:hierarchy":[
        "tgn:2226291",
        "tgn:1000001",
        "tgn:7012149",
        "tgn:2001758",
        "tgn:7007712",
        "tgn:7029392"
    ],
    "tgn:id":2226291,
    "tgn:name":"Catfish Landing",
    "tgn:placetype":[
        "aat:300008347"
    ]
},
  "bbox": [],
  "geometry": {"coordinates":[-79.4667,33.9667],"type":"Point"}
}