{
  "id": 7144152,
  "type": "Feature",
  "properties": {
    "tgn:hierarchy":[
        "tgn:7144152",
        "tgn:1000003",
        "tgn:7003678",
        "tgn:7000084",
        "tgn:7029392"
    ],
    "tgn:id":7144152,
    "tgn:name":"Kohlbacher Hof",
    "tgn:placetype":[
        "aat:300000206"
    ]
},
  "bbox": [],
  "geometry": {"coordinates":[8.883333,49.783333],"type":"Point"}
}