{
  "id": 2204246,
  "type": "Feature",
  "properties": {
    "tgn:hierarchy":[
        "tgn:2204246",
        "tgn:1000001",
        "tgn:7012149",
        "tgn:2002160",
        "tgn:7007919",
        "tgn:7029392"
    ],
    "tgn:id":2204246,
    "tgn:name":"Buff Creek",
    "tgn:placetype":[
        "aat:300008706"
    ]
},
  "bbox": [],
  "geometry": {"coordinates":[-79.7333,37.1667],"type":"Point"}
}