<<<<<<< HEAD
{
  "id": 2157934,
  "type": "Feature",
  "properties": {
    "tgn:hierarchy":[
        "tgn:2157934",
        "tgn:1000001",
        "tgn:7012149",
        "tgn:2001717",
        "tgn:7007708",
        "tgn:7029392"
    ],
    "tgn:id":2157934,
    "tgn:name":"Beaver Lakes",
    "tgn:placetype":[
        "aat:300008680"
    ]
},
  "bbox": [],
  "geometry": {"coordinates":[-122.15,44.45],"type":"Point"}
}
=======
{"geometry":{"type":"Point","coordinates":[-122.150000,44.450000]},"type":"Feature","properties":{"hierarchy":["tgn:2157934","tgn:1000001","tgn:7012149","tgn:2001717","tgn:7007708","tgn:7029392"],"placetype":["aat:300008680"],"id":2157934,"name:xx":"Beaver Lakes"}}
>>>>>>> 03f74aca74312dbeaf24d7e61306dd6a786dc3d0
