{
  "id": 2157934,
  "type": "Feature",
  "properties": {
    "tgn:hierarchy":[
        "tgn:2157934",
        "tgn:1000001",
        "tgn:7012149",
        "tgn:2001717",
        "tgn:7007708",
        "tgn:7029392"
    ],
    "tgn:id":2157934,
    "tgn:name":"Beaver Lakes",
    "tgn:placetype":[
        "aat:300008680"
    ]
},
  "bbox": [],
  "geometry": {"coordinates":[-122.15,44.45],"type":"Point"}
}