{
  "id": 2055766,
  "type": "Feature",
  "properties": {
    "tgn:hierarchy":[
        "tgn:2055766",
        "tgn:1000001",
        "tgn:2001009",
        "tgn:7012149",
        "tgn:7007521",
        "tgn:7029392"
    ],
    "tgn:id":2055766,
    "tgn:name":"Wilkinson",
    "tgn:placetype":[
        "aat:300008347",
        "aat:300387210"
    ]
},
  "bbox": [],
  "geometry": {"coordinates":[-94.6167,47.25],"type":"Point"}
}