{
  "id": 2639679,
  "type": "Feature",
  "properties": {
    "tgn:hierarchy":[
        "tgn:2639679",
        "tgn:1000001",
        "tgn:2001481",
        "tgn:7012149",
        "tgn:7007709",
        "tgn:7029392"
    ],
    "tgn:id":2639679,
    "tgn:name":"Sam Branch",
    "tgn:placetype":[
        "aat:300008699"
    ]
},
  "bbox": [],
  "geometry": {"coordinates":[-83.9167,35.15],"type":"Point"}
}