{
  "id": 7220950,
  "type": "Feature",
  "properties": {
    "tgn:hierarchy":[
        "tgn:7220950",
        "tgn:7011164",
        "tgn:7002674",
        "tgn:1000003",
        "tgn:1000074",
        "tgn:7029392"
    ],
    "tgn:id":7220950,
    "tgn:name":"Mon\u00ed Tim\u00edou Stavro\u00fa",
    "tgn:placetype":[
        "aat:300000641"
    ]
},
  "bbox": [],
  "geometry": {"coordinates":[26.869722,37.708056],"type":"Point"}
}