{
  "id": 7536736,
  "type": "Feature",
  "properties": {
    "tgn:hierarchy":[
        "tgn:7536736",
        "tgn:7001242",
        "tgn:1001059",
        "tgn:7016833",
        "tgn:7029392"
    ],
    "tgn:id":7536736,
    "tgn:name":"Kafr at Tur'ah al Jad\u012bd",
    "tgn:placetype":[
        "aat:300008347"
    ]
},
  "bbox": [],
  "geometry": {"coordinates":[31.63035,31.250692],"type":"Point"}
}