{
  "id": 1033673,
  "type": "Feature",
  "properties": {
    "tgn:hierarchy":[
        "tgn:1033673",
        "tgn:1000003",
        "tgn:1000070",
        "tgn:7002895",
        "tgn:7029392"
    ],
    "tgn:id":1033673,
    "tgn:name":"La Madrague",
    "tgn:placetype":[
        "aat:300008347"
    ]
},
  "bbox": [],
  "geometry": {"coordinates":[5.3667,43.2333],"type":"Point"}
}