{
  "id": 2102557,
  "type": "Feature",
  "properties": {
    "tgn:hierarchy":[
        "tgn:2102557",
        "tgn:1000001",
        "tgn:7012149",
        "tgn:1002830",
        "tgn:7007826",
        "tgn:7029392"
    ],
    "tgn:id":2102557,
    "tgn:name":"Bald Prairie",
    "tgn:placetype":[
        "aat:300008347",
        "aat:300387210"
    ]
},
  "bbox": [],
  "geometry": {"coordinates":[-96.4167,31.2167],"type":"Point"}
}