{
  "id": 7550021,
  "type": "Feature",
  "properties": {
    "tgn:hierarchy":[
        "tgn:7550021",
        "tgn:1000004",
        "tgn:7000198",
        "tgn:7001797",
        "tgn:7029392"
    ],
    "tgn:id":7550021,
    "tgn:name:en":"Binakanahalli",
    "tgn:placetype":[
        "aat:300008347"
    ]
},
  "bbox": [],
  "geometry": {"coordinates":[77.133333,11.683333],"type":"Point"}
}