{
  "id": 2657735,
  "type": "Feature",
  "properties": {
    "tgn:hierarchy":[
        "tgn:2657735",
        "tgn:1000001",
        "tgn:7012149",
        "tgn:2000544",
        "tgn:7007252",
        "tgn:7029392"
    ],
    "tgn:id":2657735,
    "tgn:name":"Shelkett Ditch",
    "tgn:placetype":[
        "aat:300006075"
    ]
},
  "bbox": [],
  "geometry": {"coordinates":[-87.05,39.3667],"type":"Point"}
}