{
  "id": 2500816,
  "type": "Feature",
  "properties": {
    "tgn:hierarchy":[
        "tgn:2500816",
        "tgn:2000856",
        "tgn:1000001",
        "tgn:7012149",
        "tgn:7007256",
        "tgn:7029392"
    ],
    "tgn:id":2500816,
    "tgn:name":"McElroy Ridge",
    "tgn:placetype":[
        "aat:300266640"
    ]
},
  "bbox": [],
  "geometry": {"coordinates":[-90.7667,30.15],"type":"Point"}
}