{
  "id": 2606831,
  "type": "Feature",
  "properties": {
    "tgn:hierarchy":[
        "tgn:2606831",
        "tgn:7002659",
        "tgn:1000001",
        "tgn:7012149",
        "tgn:2000029",
        "tgn:7029392"
    ],
    "tgn:id":2606831,
    "tgn:name":"Ramsey Mill Branch",
    "tgn:placetype":[
        "aat:300008699"
    ]
},
  "bbox": [],
  "geometry": {"coordinates":[-88.1167,34.55],"type":"Point"}
}