{
  "id": 2767649,
  "type": "Feature",
  "properties": {
    "tgn:hierarchy":[
        "tgn:2767649",
        "tgn:1000001",
        "tgn:7012149",
        "tgn:2001461",
        "tgn:7007568",
        "tgn:7029392"
    ],
    "tgn:id":2767649,
    "tgn:name":"Whiteface Bay",
    "tgn:placetype":[
        "aat:300132316"
    ]
},
  "bbox": [],
  "geometry": {"coordinates":[-73.95,44.3333],"type":"Point"}
}