<<<<<<< HEAD
{
  "id": 7021452,
  "type": "Feature",
  "properties": {
    "tgn:hierarchy":[
        "tgn:7021452",
        "tgn:1000001",
        "tgn:7012149",
        "tgn:2002298",
        "tgn:7013961",
        "tgn:7029392"
    ],
    "tgn:id":7021452,
    "tgn:name":"Little Laurel Fork",
    "tgn:placetype":[
        "aat:300008699"
    ]
},
  "bbox": [],
  "geometry": {"coordinates":[-80.1167,38.95],"type":"Point"}
}
=======
{"geometry":{"type":"Point","coordinates":[-80.116700,38.950000]},"type":"Feature","properties":{"hierarchy":["tgn:7021452","tgn:1000001","tgn:7012149","tgn:2002298","tgn:7013961","tgn:7029392"],"placetype":["aat:300008699"],"id":7021452,"name:xx":"Little Laurel Fork"}}
>>>>>>> 03f74aca74312dbeaf24d7e61306dd6a786dc3d0
