{
  "id": 2390636,
  "type": "Feature",
  "properties": {
    "tgn:hierarchy":[
        "tgn:2390636",
        "tgn:1000001",
        "tgn:7012149",
        "tgn:2000476",
        "tgn:7007250",
        "tgn:7029392"
    ],
    "tgn:id":2390636,
    "tgn:name":"Highline Lakes",
    "tgn:placetype":[
        "aat:300008680"
    ]
},
  "bbox": [],
  "geometry": {"coordinates":[-115.1167,46.0167],"type":"Point"}
}