<<<<<<< HEAD
{
  "id": 7028393,
  "type": "Feature",
  "properties": {
    "tgn:hierarchy":[
        "tgn:7028393",
        "tgn:7002445",
        "tgn:1000003",
        "tgn:7008160",
        "tgn:7008591",
        "tgn:7029392"
    ],
    "tgn:id":7028393,
    "tgn:name":"Freethorpe",
    "tgn:placetype":[
        "aat:300008347",
        "aat:300008372"
    ]
},
  "bbox": [],
  "geometry": {"coordinates":[1.55,52.583333],"type":"Point"}
}
=======
{"geometry":{"type":"Point","coordinates":[1.550000,52.583333]},"type":"Feature","properties":{"hierarchy":["tgn:7028393","tgn:7002445","tgn:1000003","tgn:7008160","tgn:7008591","tgn:7029392"],"placetype":["aat:300008347","aat:300008372"],"id":7028393,"name:xx":"Freethorpe"}}
>>>>>>> 03f74aca74312dbeaf24d7e61306dd6a786dc3d0
