{
  "id": 7581293,
  "type": "Feature",
  "properties": {
    "tgn:hierarchy":[
        "tgn:7581293",
        "tgn:1000004",
        "tgn:7000198",
        "tgn:1001894",
        "tgn:7029392"
    ],
    "tgn:id":7581293,
    "tgn:name:en":"Sikrod\u0101",
    "tgn:placetype":[
        "aat:300007783"
    ]
},
  "bbox": [],
  "geometry": {"coordinates":[77.733057,26.339861],"type":"Point"}
}