{
  "id": 2329203,
  "type": "Feature",
  "properties": {
    "tgn:hierarchy":[
        "tgn:2329203",
        "tgn:7002659",
        "tgn:1000001",
        "tgn:2000010",
        "tgn:7012149",
        "tgn:7029392"
    ],
    "tgn:id":2329203,
    "tgn:name":"Fitzpatrick Mine",
    "tgn:placetype":[
        "aat:300000390"
    ]
},
  "bbox": [],
  "geometry": {"coordinates":[-86.4833,32.8667],"type":"Point"}
}