{
  "id": 7381403,
  "type": "Feature",
  "properties": {
    "tgn:hierarchy":[
        "tgn:7381403",
        "tgn:7005581",
        "tgn:1000001",
        "tgn:7005560",
        "tgn:7029392"
    ],
    "tgn:id":7381403,
    "tgn:name":"Rancho Los Morteros",
    "tgn:placetype":[
        "aat:300000241"
    ]
},
  "bbox": [],
  "geometry": {"coordinates":[-103.95,28.733333],"type":"Point"}
}