{
  "id": 2168316,
  "type": "Feature",
  "properties": {
    "tgn:hierarchy":[
        "tgn:2168316",
        "tgn:1000001",
        "tgn:7012149",
        "tgn:2001708",
        "tgn:7007708",
        "tgn:7029392"
    ],
    "tgn:id":2168316,
    "tgn:name":"Big Glade Spring",
    "tgn:placetype":[
        "aat:300008697"
    ]
},
  "bbox": [],
  "geometry": {"coordinates":[-118.95,44.1833],"type":"Point"}
}