{
  "id": 7424329,
  "type": "Feature",
  "properties": {
    "tgn:hierarchy":[
        "tgn:7424329",
        "tgn:1000001",
        "tgn:7005597",
        "tgn:7005560",
        "tgn:7029392"
    ],
    "tgn:id":7424329,
    "tgn:name":"La Higuera",
    "tgn:placetype":[
        "aat:300008347"
    ]
},
  "bbox": [],
  "geometry": {"coordinates":[-100.05,23.333333],"type":"Point"}
}