{
  "id": 2117330,
  "type": "Feature",
  "properties": {
    "tgn:hierarchy":[
        "tgn:2117330",
        "tgn:1000001",
        "tgn:2002255",
        "tgn:7012149",
        "tgn:7013961",
        "tgn:7029392"
    ],
    "tgn:id":2117330,
    "tgn:name":"Bald Knob",
    "tgn:placetype":[
        "aat:300008347"
    ]
},
  "bbox": [],
  "geometry": {"coordinates":[-81.6333,37.8667],"type":"Point"}
}