{
  "id": 2695992,
  "type": "Feature",
  "properties": {
    "tgn:hierarchy":[
        "tgn:2695992",
        "tgn:1000001",
        "tgn:7012149",
        "tgn:2002055",
        "tgn:7007826",
        "tgn:7029392"
    ],
    "tgn:id":2695992,
    "tgn:name":"Stockton Tank",
    "tgn:placetype":[
        "aat:300006191"
    ]
},
  "bbox": [],
  "geometry": {"coordinates":[-102.6667,30.6667],"type":"Point"}
}