{
  "id": 2698785,
  "type": "Feature",
  "properties": {
    "tgn:hierarchy":[
        "tgn:2698785",
        "tgn:1000001",
        "tgn:7006451",
        "tgn:7012149",
        "tgn:7029392"
    ],
    "tgn:id":2698785,
    "tgn:name":"Strawberry Canyon",
    "tgn:placetype":[
        "aat:300008761"
    ]
},
  "bbox": [],
  "geometry": {"coordinates":[-111.45,34.4333],"type":"Point"}
}