<<<<<<< HEAD
{
  "id": 7020605,
  "type": "Feature",
  "properties": {
    "tgn:hierarchy":[
        "tgn:7020605",
        "tgn:1000001",
        "tgn:7012149",
        "tgn:2000875",
        "tgn:7007256",
        "tgn:7029392"
    ],
    "tgn:id":7020605,
    "tgn:name":"Lind Lake",
    "tgn:placetype":[
        "aat:300006191"
    ]
},
  "bbox": [],
  "geometry": {"coordinates":[-92.3333,31.5333],"type":"Point"}
}
=======
{"geometry":{"type":"Point","coordinates":[-92.333300,31.533300]},"type":"Feature","properties":{"hierarchy":["tgn:7020605","tgn:1000001","tgn:7012149","tgn:2000875","tgn:7007256","tgn:7029392"],"placetype":["aat:300006191"],"id":7020605,"name:xx":"Lind Lake"}}
>>>>>>> 03f74aca74312dbeaf24d7e61306dd6a786dc3d0
