{
  "id": 7020605,
  "type": "Feature",
  "properties": {
    "tgn:hierarchy":[
        "tgn:7020605",
        "tgn:1000001",
        "tgn:7012149",
        "tgn:2000875",
        "tgn:7007256",
        "tgn:7029392"
    ],
    "tgn:id":7020605,
    "tgn:name":"Lind Lake",
    "tgn:placetype":[
        "aat:300006191"
    ]
},
  "bbox": [],
  "geometry": {"coordinates":[-92.3333,31.5333],"type":"Point"}
}