{
  "id": 7383318,
  "type": "Feature",
  "properties": {
    "tgn:hierarchy":[
        "tgn:7383318",
        "tgn:1000001",
        "tgn:7005589",
        "tgn:7005560",
        "tgn:7029392"
    ],
    "tgn:id":7383318,
    "tgn:name":"Mulato",
    "tgn:placetype":[
        "aat:300008347"
    ]
},
  "bbox": [],
  "geometry": {"coordinates":[-99.566667,26.116667],"type":"Point"}
}