<<<<<<< HEAD
{
  "id": 7364873,
  "type": "Feature",
  "properties": {
    "tgn:hierarchy":[
        "tgn:7364873",
        "tgn:1000001",
        "tgn:7005589",
        "tgn:7005560",
        "tgn:7029392"
    ],
    "tgn:id":7364873,
    "tgn:name":"El Sauz",
    "tgn:placetype":[
        "aat:300008347"
    ]
},
  "bbox": [],
  "geometry": {"coordinates":[-99.5,26.083333],"type":"Point"}
}
=======
{"geometry":{"type":"Point","coordinates":[-99.500000,26.083333]},"type":"Feature","properties":{"hierarchy":["tgn:7364873","tgn:1000001","tgn:7005589","tgn:7005560","tgn:7029392"],"placetype":["aat:300008347"],"id":7364873,"name:xx":"El Sauz"}}
>>>>>>> 03f74aca74312dbeaf24d7e61306dd6a786dc3d0
