{
  "id": 7260841,
  "type": "Feature",
  "properties": {
    "tgn:hierarchy":[
        "tgn:7260841",
        "tgn:7003616",
        "tgn:1000003",
        "tgn:7016845",
        "tgn:7029392"
    ],
    "tgn:id":7260841,
    "tgn:name:nl":"De Mieden",
    "tgn:placetype":[
        "aat:300387200"
    ]
},
  "bbox": [],
  "geometry": {"coordinates":[6.016667,53.366667],"type":"Point"}
}