{
  "id": 7191113,
  "type": "Feature",
  "properties": {
    "tgn:hierarchy":[
        "tgn:7191113",
        "tgn:1000003",
        "tgn:7003682",
        "tgn:7000084",
        "tgn:7029392"
    ],
    "tgn:id":7191113,
    "tgn:name":"Forst-Berg",
    "tgn:placetype":[
        "aat:300008777"
    ]
},
  "bbox": [],
  "geometry": {"coordinates":[7.233333,50.383333],"type":"Point"}
}