{
  "id": 2623126,
  "type": "Feature",
  "properties": {
    "tgn:hierarchy":[
        "tgn:2623126",
        "tgn:1000001",
        "tgn:7012149",
        "tgn:2001512",
        "tgn:7007709",
        "tgn:7029392"
    ],
    "tgn:id":2623126,
    "tgn:name":"Rochelle Corners",
    "tgn:placetype":[
        "aat:300008347"
    ]
},
  "bbox": [],
  "geometry": {"coordinates":[-77.6167,35.2667],"type":"Point"}
}