{
  "id": 7441438,
  "type": "Feature",
  "properties": {
    "tgn:hierarchy":[
        "tgn:7441438",
        "tgn:7005581",
        "tgn:1000001",
        "tgn:7005560",
        "tgn:7029392"
    ],
    "tgn:id":7441438,
    "tgn:name":"San Nicol\u00e1s del Tule",
    "tgn:placetype":[
        "aat:300008347"
    ]
},
  "bbox": [],
  "geometry": {"coordinates":[-105.65,27.05],"type":"Point"}
}