{
  "id": 2050117,
  "type": "Feature",
  "properties": {
    "tgn:hierarchy":[
        "tgn:2050117",
        "tgn:1000001",
        "tgn:1002359",
        "tgn:7012149",
        "tgn:2050114",
        "tgn:7007517",
        "tgn:7029392"
    ],
    "tgn:id":2050117,
    "tgn:name":"Maple Park",
    "tgn:placetype":[
        "aat:300000745"
    ]
},
  "bbox": [],
  "geometry": {"coordinates":[-71.15,42.7667],"type":"Point"}
}