{
  "id": 2482159,
  "type": "Feature",
  "properties": {
    "tgn:hierarchy":[
        "tgn:2482159",
        "tgn:1000001",
        "tgn:7012149",
        "tgn:7007255",
        "tgn:7029392"
    ],
    "tgn:id":2482159,
    "tgn:name":"Lang Run",
    "tgn:placetype":[
        "aat:300008699"
    ]
},
  "bbox": [],
  "geometry": {"coordinates":[-85.3333,38.2667],"type":"Point"}
}