{
  "id": 2629999,
  "type": "Feature",
  "properties": {
    "tgn:hierarchy":[
        "tgn:2629999",
        "tgn:1000001",
        "tgn:7012149",
        "tgn:1002977",
        "tgn:7007240",
        "tgn:7029392"
    ],
    "tgn:id":2629999,
    "tgn:name":"Rossiter Island",
    "tgn:placetype":[
        "aat:300008791"
    ]
},
  "bbox": [],
  "geometry": {"coordinates":[-81.2833,28.85],"type":"Point"}
}