{
  "id": 2429236,
  "type": "Feature",
  "properties": {
    "tgn:hierarchy":[
        "tgn:2429236",
        "tgn:1000001",
        "tgn:2001738",
        "tgn:7012149",
        "tgn:7007712",
        "tgn:7029392"
    ],
    "tgn:id":2429236,
    "tgn:name":"Juneburn Branch",
    "tgn:placetype":[
        "aat:300008699"
    ]
},
  "bbox": [],
  "geometry": {"coordinates":[-80.1667,33.75],"type":"Point"}
}