{
  "id": 2052129,
  "type": "Feature",
  "properties": {
    "tgn:hierarchy":[
        "tgn:2052129",
        "tgn:1000001",
        "tgn:2000958",
        "tgn:7012149",
        "tgn:7007520",
        "tgn:7029392"
    ],
    "tgn:id":2052129,
    "tgn:name":"Harbor Springs",
    "tgn:placetype":[
        "aat:300008347"
    ]
},
  "bbox": [],
  "geometry": {"coordinates":[-84.9833,45.4167],"type":"Point"}
}