{
  "id": 2436858,
  "type": "Feature",
  "properties": {
    "tgn:hierarchy":[
        "tgn:2436858",
        "tgn:1000001",
        "tgn:7012149",
        "tgn:2000181",
        "tgn:7007157",
        "tgn:7029392"
    ],
    "tgn:id":2436858,
    "tgn:name":"Kiler Creek",
    "tgn:placetype":[
        "aat:300008706"
    ]
},
  "bbox": [],
  "geometry": {"coordinates":[-124.0833,40.4167],"type":"Point"}
}