{
  "id": 7490076,
  "type": "Feature",
  "properties": {
    "tgn:hierarchy":[
        "tgn:7490076",
        "tgn:1000004",
        "tgn:7471332",
        "tgn:1000141",
        "tgn:7029392"
    ],
    "tgn:id":7490076,
    "tgn:name":"Shiyigu",
    "tgn:placetype":[
        "aat:300008347"
    ]
},
  "bbox": [],
  "geometry": {"coordinates":[121.028611,24.931111],"type":"Point"}
}