<<<<<<< HEAD
{
  "id": 2332669,
  "type": "Feature",
  "properties": {
    "tgn:hierarchy":[
        "tgn:2332669",
        "tgn:7002659",
        "tgn:1000001",
        "tgn:7012149",
        "tgn:2000056",
        "tgn:7029392"
    ],
    "tgn:id":2332669,
    "tgn:name":"Flournoys",
    "tgn:placetype":[
        "aat:300008347"
    ]
},
  "bbox": [],
  "geometry": {"coordinates":[-85.0,32.3667],"type":"Point"}
}
=======
{"geometry":{"type":"Point","coordinates":[-85.000000,32.366700]},"type":"Feature","properties":{"hierarchy":["tgn:2332669","tgn:7002659","tgn:1000001","tgn:7012149","tgn:2000056","tgn:7029392"],"placetype":["aat:300008347"],"id":2332669,"name:xx":"Flournoys"}}
>>>>>>> 03f74aca74312dbeaf24d7e61306dd6a786dc3d0
