{
  "id": 2270571,
  "type": "Feature",
  "properties": {
    "tgn:hierarchy":[
        "tgn:2270571",
        "tgn:1000001",
        "tgn:2000463",
        "tgn:7012149",
        "tgn:7007250",
        "tgn:7029392"
    ],
    "tgn:id":2270571,
    "tgn:name":"Crystal Pit",
    "tgn:placetype":[
        "aat:300386845"
    ]
},
  "bbox": [],
  "geometry": {"coordinates":[-113.55,43.4333],"type":"Point"}
}