<<<<<<< HEAD
{
  "id": 2253996,
  "type": "Feature",
  "properties": {
    "tgn:hierarchy":[
        "tgn:2253996",
        "tgn:7006450",
        "tgn:1000001",
        "tgn:7012149",
        "tgn:2000088",
        "tgn:7029392"
    ],
    "tgn:id":2253996,
    "tgn:name":"Cool Lake",
    "tgn:placetype":[
        "aat:300008680"
    ]
},
  "bbox": [],
  "geometry": {"coordinates":[-134.25,56.8667],"type":"Point"}
}
=======
{"geometry":{"type":"Point","coordinates":[-134.250000,56.866700]},"type":"Feature","properties":{"hierarchy":["tgn:2253996","tgn:7006450","tgn:1000001","tgn:7012149","tgn:2000088","tgn:7029392"],"placetype":["aat:300008680"],"id":2253996,"name:xx":"Cool Lake"}}
>>>>>>> 03f74aca74312dbeaf24d7e61306dd6a786dc3d0
