{
  "id": 7133719,
  "type": "Feature",
  "properties": {
    "tgn:hierarchy":[
        "tgn:7133719",
        "tgn:7003692",
        "tgn:1000003",
        "tgn:7000084",
        "tgn:7029392"
    ],
    "tgn:id":7133719,
    "tgn:name":"Moos",
    "tgn:placetype":[
        "aat:300008347"
    ]
},
  "bbox": [],
  "geometry": {"coordinates":[9.533333,47.616667],"type":"Point"}
}