<<<<<<< HEAD
{
  "id": 7246040,
  "type": "Feature",
  "properties": {
    "tgn:hierarchy":[
        "tgn:7246040",
        "tgn:7007877",
        "tgn:1000003",
        "tgn:1000063",
        "tgn:4012014",
        "tgn:7029392"
    ],
    "tgn:id":7246040,
    "tgn:name":"Ferme Bruy\u00e8re Madame",
    "tgn:placetype":[
        "aat:300000206"
    ]
},
  "bbox": [],
  "geometry": {"coordinates":[4.416667,50.633333],"type":"Point"}
}
=======
{"geometry":{"type":"Point","coordinates":[4.416667,50.633333]},"type":"Feature","properties":{"hierarchy":["tgn:7246040","tgn:7007877","tgn:1000003","tgn:1000063","tgn:4012014","tgn:7029392"],"placetype":["aat:300000206"],"id":7246040,"name:xx":"Ferme Bruy\u00e8re Madame"}}
>>>>>>> 03f74aca74312dbeaf24d7e61306dd6a786dc3d0
