{
  "id": 2325724,
  "type": "Feature",
  "properties": {
    "tgn:hierarchy":[
        "tgn:2325724",
        "tgn:1000001",
        "tgn:7012149",
        "tgn:7029392"
    ],
    "tgn:id":2325724,
    "tgn:name":"Field Creek",
    "tgn:placetype":[
        "aat:300008706"
    ]
},
  "bbox": [],
  "geometry": {"coordinates":[-91.5167,36.45],"type":"Point"}
}