{
  "id": 2025397,
  "type": "Feature",
  "properties": {
    "tgn:hierarchy":[
        "tgn:2025397",
        "tgn:1000001",
        "tgn:7012149",
        "tgn:2000475",
        "tgn:7007250",
        "tgn:7029392"
    ],
    "tgn:id":2025397,
    "tgn:name":"Bliss",
    "tgn:placetype":[
        "aat:300008347"
    ]
},
  "bbox": [],
  "geometry": {"coordinates":[-114.9333,42.9167],"type":"Point"}
}