{
  "id": 2117974,
  "type": "Feature",
  "properties": {
    "tgn:hierarchy":[
        "tgn:2117974",
        "tgn:1000001",
        "tgn:7012149",
        "tgn:2002296",
        "tgn:7013961",
        "tgn:7029392"
    ],
    "tgn:id":2117974,
    "tgn:name":"Davis",
    "tgn:placetype":[
        "aat:300008347"
    ]
},
  "bbox": [],
  "geometry": {"coordinates":[-79.45,39.1167],"type":"Point"}
}