{
  "id": 1132365,
  "type": "Feature",
  "properties": {
    "tgn:hierarchy":[
        "tgn:1132365",
        "tgn:1000001",
        "tgn:7012149",
        "tgn:7007251",
        "tgn:7029392"
    ],
    "tgn:id":1132365,
    "tgn:name":"Beaucoup Creek",
    "tgn:placetype":[
        "aat:300008706"
    ]
},
  "bbox": [],
  "geometry": {"coordinates":[-89.2833,38.35],"type":"Point"}
}