<<<<<<< HEAD
{
  "id": 7170278,
  "type": "Feature",
  "properties": {
    "tgn:hierarchy":[
        "tgn:7170278",
        "tgn:7003692",
        "tgn:1000003",
        "tgn:7000084",
        "tgn:7029392"
    ],
    "tgn:id":7170278,
    "tgn:name":"He\u00dflachshof",
    "tgn:placetype":[
        "aat:300008347"
    ]
},
  "bbox": [],
  "geometry": {"coordinates":[9.766667,49.35],"type":"Point"}
}
=======
{"geometry":{"type":"Point","coordinates":[9.766667,49.350000]},"type":"Feature","properties":{"hierarchy":["tgn:7170278","tgn:7003692","tgn:1000003","tgn:7000084","tgn:7029392"],"placetype":["aat:300008347"],"id":7170278,"name:xx":"He\u00dflachshof"}}
>>>>>>> 03f74aca74312dbeaf24d7e61306dd6a786dc3d0
