<<<<<<< HEAD
{
  "id": 2251120,
  "type": "Feature",
  "properties": {
    "tgn:hierarchy":[
        "tgn:2251120",
        "tgn:7002659",
        "tgn:1000001",
        "tgn:2000007",
        "tgn:7012149",
        "tgn:7029392"
    ],
    "tgn:id":2251120,
    "tgn:name":"Colvins Gap",
    "tgn:placetype":[
        "aat:300008347"
    ]
},
  "bbox": [],
  "geometry": {"coordinates":[-85.8,33.9333],"type":"Point"}
}
=======
{"geometry":{"type":"Point","coordinates":[-85.800000,33.933300]},"type":"Feature","properties":{"hierarchy":["tgn:2251120","tgn:7002659","tgn:1000001","tgn:2000007","tgn:7012149","tgn:7029392"],"placetype":["aat:300008347"],"id":2251120,"name:xx":"Colvins Gap"}}
>>>>>>> 03f74aca74312dbeaf24d7e61306dd6a786dc3d0
