{
  "id": 2722267,
  "type": "Feature",
  "properties": {
    "tgn:hierarchy":[
        "tgn:2722267",
        "tgn:1000001",
        "tgn:7012149",
        "tgn:1002833",
        "tgn:7007568",
        "tgn:7029392"
    ],
    "tgn:id":2722267,
    "tgn:name":"Timp Brook, The",
    "tgn:placetype":[
        "aat:300008699"
    ]
},
  "bbox": [],
  "geometry": {"coordinates":[-73.9833,41.2667],"type":"Point"}
}