{
  "id": 7131525,
  "type": "Feature",
  "properties": {
    "tgn:hierarchy":[
        "tgn:7131525",
        "tgn:1000003",
        "tgn:7003688",
        "tgn:7000084",
        "tgn:7029392"
    ],
    "tgn:id":7131525,
    "tgn:name":"Marienstedt",
    "tgn:placetype":[
        "aat:300387200"
    ]
},
  "bbox": [],
  "geometry": {"coordinates":[10.883333,53.583333],"type":"Point"}
}