{
  "id": 2379336,
  "type": "Feature",
  "properties": {
    "tgn:hierarchy":[
        "tgn:2379336",
        "tgn:1000001",
        "tgn:7012149",
        "tgn:2002251",
        "tgn:7007920",
        "tgn:7029392"
    ],
    "tgn:id":2379336,
    "tgn:name":"Harvey",
    "tgn:placetype":[
        "aat:300008347"
    ]
},
  "bbox": [],
  "geometry": {"coordinates":[-118.4667,46.3833],"type":"Point"}
}