{
  "id": 7489335,
  "type": "Feature",
  "properties": {
    "tgn:hierarchy":[
        "tgn:7489335",
        "tgn:1000004",
        "tgn:7467799",
        "tgn:1000141",
        "tgn:7029392"
    ],
    "tgn:id":7489335,
    "tgn:name":"Sanshizhangli",
    "tgn:placetype":[
        "aat:300008347"
    ]
},
  "bbox": [],
  "geometry": {"coordinates":[120.503905,23.906055],"type":"Point"}
}