{
  "id": 2216623,
  "type": "Feature",
  "properties": {
    "tgn:hierarchy":[
        "tgn:2216623",
        "tgn:1000001",
        "tgn:7012149",
        "tgn:2001976",
        "tgn:7007826",
        "tgn:7029392"
    ],
    "tgn:id":2216623,
    "tgn:name":"Camp Creek",
    "tgn:placetype":[
        "aat:300008706"
    ]
},
  "bbox": [],
  "geometry": {"coordinates":[-100.6167,35.0333],"type":"Point"}
}