{
  "id": 7255317,
  "type": "Feature",
  "properties": {
    "tgn:hierarchy":[
        "tgn:7255317",
        "tgn:7003457",
        "tgn:1000003",
        "tgn:1000063",
        "tgn:7018236",
        "tgn:7029392"
    ],
    "tgn:id":7255317,
    "tgn:name":"Ripstraat",
    "tgn:placetype":[
        "aat:300008347"
    ]
},
  "bbox": [],
  "geometry": {"coordinates":[4.116667,51.216667],"type":"Point"}
}