{
  "id": 2268990,
  "type": "Feature",
  "properties": {
    "tgn:hierarchy":[
        "tgn:2268990",
        "tgn:1000001",
        "tgn:7012149",
        "tgn:7007922",
        "tgn:7029392"
    ],
    "tgn:id":2268990,
    "tgn:name":"Crossman Creek",
    "tgn:placetype":[
        "aat:300008706"
    ]
},
  "bbox": [],
  "geometry": {"coordinates":[-90.1833,43.7167],"type":"Point"}
}