{
  "id": 7452666,
  "type": "Feature",
  "properties": {
    "tgn:hierarchy":[
        "tgn:7452666",
        "tgn:7002445",
        "tgn:1000003",
        "tgn:7008132",
        "tgn:7008591",
        "tgn:7029392"
    ],
    "tgn:id":7452666,
    "tgn:name:en":"Elmore",
    "tgn:placetype":[
        "aat:300008347"
    ]
},
  "bbox": [],
  "geometry": {"coordinates":[-2.316667,51.833333],"type":"Point"}
}