{
  "id": 7065862,
  "type": "Feature",
  "properties": {
    "tgn:hierarchy":[
        "tgn:7065862",
        "tgn:1000003",
        "tgn:7003676",
        "tgn:7000084",
        "tgn:7029392"
    ],
    "tgn:id":7065862,
    "tgn:name":"Twiste",
    "tgn:placetype":[
        "aat:300008699"
    ]
},
  "bbox": [],
  "geometry": {"coordinates":[9.25,53.333333],"type":"Point"}
}