{
  "id": 7058190,
  "type": "Feature",
  "properties": {
    "tgn:hierarchy":[
        "tgn:7058190",
        "tgn:7003127",
        "tgn:1000003",
        "tgn:7008516",
        "tgn:1000080",
        "tgn:7029392"
    ],
    "tgn:id":7058190,
    "tgn:name":"Aposa, Valle dell'",
    "tgn:placetype":[
        "aat:300008761"
    ]
},
  "bbox": [],
  "geometry": {"coordinates":[11.35,44.483333],"type":"Point"}
}