{
  "id": 1016618,
  "type": "Feature",
  "properties": {
    "tgn:hierarchy":[
        "tgn:1016618",
        "tgn:7018312",
        "tgn:1009417",
        "tgn:1010257",
        "tgn:1000001",
        "tgn:7004545",
        "tgn:7029392"
    ],
    "tgn:id":1016618,
    "tgn:name":"Terre-de-Bas",
    "tgn:placetype":[
        "aat:300008347"
    ]
},
  "bbox": [],
  "geometry": {"coordinates":[-61.65,15.85],"type":"Point"}
}