{
  "id": 7298334,
  "type": "Feature",
  "properties": {
    "tgn:hierarchy":[
        "tgn:7298334",
        "tgn:7002844",
        "tgn:7030216",
        "tgn:1000003",
        "tgn:1000095",
        "tgn:7029392"
    ],
    "tgn:id":7298334,
    "tgn:name":"Senant",
    "tgn:placetype":[
        "aat:300008347"
    ]
},
  "bbox": [],
  "geometry": {"coordinates":[1.08808,41.470228],"type":"Point"}
}