{
  "id": 7165204,
  "type": "Feature",
  "properties": {
    "tgn:hierarchy":[
        "tgn:7165204",
        "tgn:1000003",
        "tgn:7003678",
        "tgn:7000084",
        "tgn:7029392"
    ],
    "tgn:id":7165204,
    "tgn:name":"Hundsbach",
    "tgn:placetype":[
        "aat:300008347"
    ]
},
  "bbox": [],
  "geometry": {"coordinates":[10.033333,50.616667],"type":"Point"}
}