{
  "id": 1044927,
  "type": "Feature",
  "properties": {
    "tgn:hierarchy":[
        "tgn:1044927",
        "tgn:7005765",
        "tgn:1000003",
        "tgn:7003237",
        "tgn:1000080",
        "tgn:7029392"
    ],
    "tgn:id":1044927,
    "tgn:name":"Gussago",
    "tgn:placetype":[
        "aat:300008347"
    ]
},
  "bbox": [],
  "geometry": {"coordinates":[10.15,45.583333],"type":"Point"}
}