{
  "id": 2233072,
  "type": "Feature",
  "properties": {
    "tgn:hierarchy":[
        "tgn:2233072",
        "tgn:1000001",
        "tgn:7012149",
        "tgn:7022218",
        "tgn:7007919",
        "tgn:7029392"
    ],
    "tgn:id":2233072,
    "tgn:name":"Charity Neck",
    "tgn:placetype":[
        "aat:300008850"
    ]
},
  "bbox": [],
  "geometry": {"coordinates":[-75.9833,36.6667],"type":"Point"}
}