{
  "id": 2104068,
  "type": "Feature",
  "properties": {
    "tgn:hierarchy":[
        "tgn:2104068",
        "tgn:1000001",
        "tgn:7012149",
        "tgn:2002027",
        "tgn:7007826",
        "tgn:7029392"
    ],
    "tgn:id":2104068,
    "tgn:name":"Encinal",
    "tgn:placetype":[
        "aat:300008347"
    ]
},
  "bbox": [],
  "geometry": {"coordinates":[-99.35,28.0333],"type":"Point"}
}