{
  "id": 7389205,
  "type": "Feature",
  "properties": {
    "tgn:hierarchy":[
        "tgn:7389205",
        "tgn:7005583",
        "tgn:1000001",
        "tgn:7005560",
        "tgn:7029392"
    ],
    "tgn:id":7389205,
    "tgn:name":"Saguatenipa",
    "tgn:placetype":[
        "aat:300008347"
    ]
},
  "bbox": [],
  "geometry": {"coordinates":[-106.805,24.919444],"type":"Point"}
}