<<<<<<< HEAD
{
  "id": 2332170,
  "type": "Feature",
  "properties": {
    "tgn:hierarchy":[
        "tgn:2332170",
        "tgn:1000001",
        "tgn:7012149",
        "tgn:2002112",
        "tgn:7007827",
        "tgn:7029392"
    ],
    "tgn:id":2332170,
    "tgn:name":"Flint Spring",
    "tgn:placetype":[
        "aat:300008697"
    ]
},
  "bbox": [],
  "geometry": {"coordinates":[-112.95,39.8],"type":"Point"}
}
=======
{"geometry":{"type":"Point","coordinates":[-112.950000,39.800000]},"type":"Feature","properties":{"hierarchy":["tgn:2332170","tgn:1000001","tgn:7012149","tgn:2002112","tgn:7007827","tgn:7029392"],"placetype":["aat:300008697"],"id":2332170,"name:xx":"Flint Spring"}}
>>>>>>> 03f74aca74312dbeaf24d7e61306dd6a786dc3d0
