{
  "id": 2460450,
  "type": "Feature",
  "properties": {
    "tgn:hierarchy":[
        "tgn:2460450",
        "tgn:1000001",
        "tgn:7012149",
        "tgn:2000217",
        "tgn:7007158",
        "tgn:7029392"
    ],
    "tgn:id":2460450,
    "tgn:name":"Little Sand Mountain",
    "tgn:placetype":[
        "aat:300008798"
    ]
},
  "bbox": [],
  "geometry": {"coordinates":[-107.4667,38.7333],"type":"Point"}
}