{
  "id": 2113512,
  "type": "Feature",
  "properties": {
    "tgn:hierarchy":[
        "tgn:2113512",
        "tgn:1000001",
        "tgn:7012149",
        "tgn:7014160",
        "tgn:7007919",
        "tgn:7029392"
    ],
    "tgn:id":2113512,
    "tgn:name":"Keene Mill Heights",
    "tgn:placetype":[
        "aat:300008347"
    ]
},
  "bbox": [],
  "geometry": {"coordinates":[-77.25,38.7667],"type":"Point"}
}