{
  "id": 7014924,
  "type": "Feature",
  "properties": {
    "tgn:hierarchy":[
        "tgn:7014924",
        "tgn:1000004",
        "tgn:7024037",
        "tgn:7006651",
        "tgn:7029392"
    ],
    "tgn:id":7014924,
    "tgn:name":"Yegvard",
    "tgn:name:en":"Yeghvard",
    "tgn:placetype":[
        "aat:300008347",
        "aat:300008375"
    ]
},
  "bbox": [],
  "geometry": {"coordinates":[44.4667,40.3167],"type":"Point"}
}