{
  "id": 2444047,
  "type": "Feature",
  "properties": {
    "tgn:hierarchy":[
        "tgn:2444047",
        "tgn:1000001",
        "tgn:7012149",
        "tgn:2002264",
        "tgn:7013961",
        "tgn:7029392"
    ],
    "tgn:id":2444047,
    "tgn:name":"LaFayette Bottom",
    "tgn:placetype":[
        "aat:300386845"
    ]
},
  "bbox": [],
  "geometry": {"coordinates":[-80.5667,37.9833],"type":"Point"}
}