{
  "id": 2487964,
  "type": "Feature",
  "properties": {
    "tgn:hierarchy":[
        "tgn:2487964",
        "tgn:1000001",
        "tgn:7012149",
        "tgn:2001437",
        "tgn:7007566",
        "tgn:7029392"
    ],
    "tgn:id":2487964,
    "tgn:name":"Maggie Shaft",
    "tgn:placetype":[
        "aat:300000390"
    ]
},
  "bbox": [],
  "geometry": {"coordinates":[-108.05,32.8667],"type":"Point"}
}