{
  "id": 2648119,
  "type": "Feature",
  "properties": {
    "tgn:hierarchy":[
        "tgn:2648119",
        "tgn:1000001",
        "tgn:2000935",
        "tgn:7012149",
        "tgn:7007516",
        "tgn:7029392"
    ],
    "tgn:id":2648119,
    "tgn:name":"Schoolhouse Run",
    "tgn:placetype":[
        "aat:300008699"
    ]
},
  "bbox": [],
  "geometry": {"coordinates":[-79.1167,39.6833],"type":"Point"}
}