{
  "id": 7214601,
  "type": "Feature",
  "properties": {
    "tgn:hierarchy":[
        "tgn:7214601",
        "tgn:1000003",
        "tgn:7000094",
        "tgn:7000084",
        "tgn:7029392"
    ],
    "tgn:id":7214601,
    "tgn:name":"Blieschen-Berg",
    "tgn:placetype":[
        "aat:300008777"
    ]
},
  "bbox": [],
  "geometry": {"coordinates":[11.333333,53.166667],"type":"Point"}
}