{
  "id": 2422888,
  "type": "Feature",
  "properties": {
    "tgn:hierarchy":[
        "tgn:2422888",
        "tgn:1000001",
        "tgn:7012149",
        "tgn:1002481",
        "tgn:7007520",
        "tgn:7029392"
    ],
    "tgn:id":2422888,
    "tgn:name":"Joe Drain",
    "tgn:placetype":[
        "aat:300008699"
    ]
},
  "bbox": [],
  "geometry": {"coordinates":[-84.7167,41.7833],"type":"Point"}
}