{
  "id": 7145287,
  "type": "Feature",
  "properties": {
    "tgn:hierarchy":[
        "tgn:7145287",
        "tgn:1000003",
        "tgn:7003677",
        "tgn:7000084",
        "tgn:7029392"
    ],
    "tgn:id":7145287,
    "tgn:name":"Bahnhof K\u00f6ln-Holweide",
    "tgn:placetype":[
        "aat:300007783"
    ]
},
  "bbox": [],
  "geometry": {"coordinates":[7.037222,50.975278],"type":"Point"}
}