{
  "id": 2505912,
  "type": "Feature",
  "properties": {
    "tgn:hierarchy":[
        "tgn:2505912",
        "tgn:1000001",
        "tgn:2002147",
        "tgn:7012149",
        "tgn:7007919",
        "tgn:7029392"
    ],
    "tgn:id":2505912,
    "tgn:name":"Merchant",
    "tgn:placetype":[
        "aat:300008347"
    ]
},
  "bbox": [],
  "geometry": {"coordinates":[-77.95,36.6667],"type":"Point"}
}