{
  "id": 1087557,
  "type": "Feature",
  "properties": {
    "tgn:hierarchy":[
        "tgn:1087557",
        "tgn:7001242",
        "tgn:7016752",
        "tgn:1000763",
        "tgn:7029392"
    ],
    "tgn:id":1087557,
    "tgn:name":"Sidi Bel Abb\u00e8s",
    "tgn:placetype":[
        "aat:300387277",
        "aat:300008347",
        "aat:300387225",
        "aat:300008375",
        "aat:300387285"
    ]
},
  "bbox": [],
  "geometry": {"coordinates":[-0.65,35.25],"type":"Point"}
}