{
  "id": 1071524,
  "type": "Feature",
  "properties": {
    "tgn:hierarchy":[
        "tgn:1071524",
        "tgn:7002075",
        "tgn:1000004",
        "tgn:1000111",
        "tgn:7029392"
    ],
    "tgn:id":1071524,
    "tgn:name":"Shanmenjie",
    "tgn:placetype":[
        "aat:300008347"
    ]
},
  "bbox": [],
  "geometry": {"coordinates":[118.8667,30.6667],"type":"Point"}
}