{
  "id": 2365774,
  "type": "Feature",
  "properties": {
    "tgn:hierarchy":[
        "tgn:2365774",
        "tgn:1000001",
        "tgn:7012149",
        "tgn:2002043",
        "tgn:7007826",
        "tgn:7029392"
    ],
    "tgn:id":2365774,
    "tgn:name":"Gregory, Lake",
    "tgn:placetype":[
        "aat:300006191"
    ]
},
  "bbox": [],
  "geometry": {"coordinates":[-101.1333,32.4333],"type":"Point"}
}