{
  "id": 7510889,
  "type": "Feature",
  "properties": {
    "tgn:hierarchy":[
        "tgn:7510889",
        "tgn:1009227",
        "tgn:1000226",
        "tgn:7016822",
        "tgn:1000006",
        "tgn:7029392"
    ],
    "tgn:id":7510889,
    "tgn:name:en":"Tussock Creek",
    "tgn:placetype":[
        "aat:300008347"
    ]
},
  "bbox": [],
  "geometry": {"coordinates":[168.416667,-46.25],"type":"Point"}
}