{
  "id": 2636247,
  "type": "Feature",
  "properties": {
    "tgn:hierarchy":[
        "tgn:2636247",
        "tgn:1000001",
        "tgn:2000922",
        "tgn:7012149",
        "tgn:7007515",
        "tgn:7029392"
    ],
    "tgn:id":2636247,
    "tgn:name":"Saddleback Island",
    "tgn:placetype":[
        "aat:300008791"
    ]
},
  "bbox": [],
  "geometry": {"coordinates":[-68.5667,44.1333],"type":"Point"}
}