{
  "id": 2295486,
  "type": "Feature",
  "properties": {
    "tgn:hierarchy":[
        "tgn:2295486",
        "tgn:1000001",
        "tgn:7016172",
        "tgn:2000121",
        "tgn:7012149",
        "tgn:7029392"
    ],
    "tgn:id":2295486,
    "tgn:name":"Dripping Spring",
    "tgn:placetype":[
        "aat:300008697"
    ]
},
  "bbox": [],
  "geometry": {"coordinates":[-94.3833,35.5167],"type":"Point"}
}