{
  "id": 2140749,
  "type": "Feature",
  "properties": {
    "tgn:hierarchy":[
        "tgn:2140749",
        "tgn:1000001",
        "tgn:7012149",
        "tgn:7014287",
        "tgn:7007568",
        "tgn:7029392"
    ],
    "tgn:id":2140749,
    "tgn:name":"Ava Brook",
    "tgn:placetype":[
        "aat:300008699"
    ]
},
  "bbox": [],
  "geometry": {"coordinates":[-75.4667,43.4333],"type":"Point"}
}