{
  "id": 7540297,
  "type": "Feature",
  "properties": {
    "tgn:hierarchy":[
        "tgn:7540297",
        "tgn:7001242",
        "tgn:7016833",
        "tgn:7000123",
        "tgn:7029392"
    ],
    "tgn:id":7540297,
    "tgn:name:en":"Naj' al Khu\u0163bah",
    "tgn:placetype":[
        "aat:300008347"
    ]
},
  "bbox": [],
  "geometry": {"coordinates":[32.633333,25.683333],"type":"Point"}
}