{
  "id": 2052478,
  "type": "Feature",
  "properties": {
    "tgn:hierarchy":[
        "tgn:2052478",
        "tgn:1000001",
        "tgn:7012149",
        "tgn:2000995",
        "tgn:7007520",
        "tgn:7029392"
    ],
    "tgn:id":2052478,
    "tgn:name":"Lexington Heights",
    "tgn:placetype":[
        "aat:300008347"
    ]
},
  "bbox": [],
  "geometry": {"coordinates":[-82.5167,43.2167],"type":"Point"}
}