{
  "id": 2623612,
  "type": "Feature",
  "properties": {
    "tgn:hierarchy":[
        "tgn:2623612",
        "tgn:1000001",
        "tgn:7012149",
        "tgn:2001204",
        "tgn:7007523",
        "tgn:7029392"
    ],
    "tgn:id":2623612,
    "tgn:name":"Rock Creek",
    "tgn:placetype":[
        "aat:300008706"
    ]
},
  "bbox": [],
  "geometry": {"coordinates":[-95.05,39.9667],"type":"Point"}
}