{
  "id": 7282385,
  "type": "Feature",
  "properties": {
    "tgn:hierarchy":[
        "tgn:7282385",
        "tgn:1001768",
        "tgn:1000049",
        "tgn:1000002",
        "tgn:7029392"
    ],
    "tgn:id":7282385,
    "tgn:name":"Pitipeumo, Caj\u00f3n del",
    "tgn:placetype":[
        "aat:300266554",
        "aat:300008699"
    ]
},
  "bbox": [],
  "geometry": {"coordinates":[-70.916667,-32.566667],"type":"Point"}
}