{
  "id": 7368882,
  "type": "Feature",
  "properties": {
    "tgn:hierarchy":[
        "tgn:7368882",
        "tgn:1000001",
        "tgn:7005589",
        "tgn:7005560",
        "tgn:7029392"
    ],
    "tgn:id":7368882,
    "tgn:name":"Juan L\u00f3pez",
    "tgn:placetype":[
        "aat:300008347"
    ]
},
  "bbox": [],
  "geometry": {"coordinates":[-98.766667,25.966667],"type":"Point"}
}