{
  "id": 1026551,
  "type": "Feature",
  "properties": {
    "tgn:hierarchy":[
        "tgn:1026551",
        "tgn:7003458",
        "tgn:1000003",
        "tgn:1000063",
        "tgn:7018236",
        "tgn:7029392"
    ],
    "tgn:id":1026551,
    "tgn:name":"Lauwe",
    "tgn:placetype":[
        "aat:300008347"
    ]
},
  "bbox": [],
  "geometry": {"coordinates":[3.186902,50.794789],"type":"Point"}
}