{
  "id": 7064481,
  "type": "Feature",
  "properties": {
    "tgn:hierarchy":[
        "tgn:7064481",
        "tgn:1000003",
        "tgn:7003676",
        "tgn:7000084",
        "tgn:7029392"
    ],
    "tgn:id":7064481,
    "tgn:name":"Unter-Berg",
    "tgn:placetype":[
        "aat:300008777"
    ]
},
  "bbox": [],
  "geometry": {"coordinates":[9.383333,51.933333],"type":"Point"}
}