{
  "id": 2134940,
  "type": "Feature",
  "properties": {
    "tgn:hierarchy":[
        "tgn:2134940",
        "tgn:2000090",
        "tgn:1000001",
        "tgn:7006451",
        "tgn:7012149",
        "tgn:7029392"
    ],
    "tgn:id":2134940,
    "tgn:name":"Antelope Ridge",
    "tgn:placetype":[
        "aat:300266640"
    ]
},
  "bbox": [],
  "geometry": {"coordinates":[-109.7333,36.75],"type":"Point"}
}