{
  "id": 7460053,
  "type": "Feature",
  "properties": {
    "tgn:hierarchy":[
        "tgn:7460053",
        "tgn:7002443",
        "tgn:1000003",
        "tgn:7008050",
        "tgn:7008591",
        "tgn:7029392"
    ],
    "tgn:id":7460053,
    "tgn:name:en":"Pontneddfechan",
    "tgn:placetype":[
        "aat:300008347"
    ]
},
  "bbox": [],
  "geometry": {"coordinates":[-3.596389,51.7575],"type":"Point"}
}