{
  "id": 7420823,
  "type": "Feature",
  "properties": {
    "tgn:hierarchy":[
        "tgn:7420823",
        "tgn:1001836",
        "tgn:1000001",
        "tgn:7005560",
        "tgn:7029392"
    ],
    "tgn:id":7420823,
    "tgn:name":"Las Juntas",
    "tgn:placetype":[
        "aat:300008347"
    ]
},
  "bbox": [],
  "geometry": {"coordinates":[-111.748611,25.413889],"type":"Point"}
}