{
  "id": 7535543,
  "type": "Feature",
  "properties": {
    "tgn:hierarchy":[
        "tgn:7535543",
        "tgn:7001242",
        "tgn:7016833",
        "tgn:7001312",
        "tgn:7029392"
    ],
    "tgn:id":7535543,
    "tgn:name:en":"Khalwat R\u012bshah",
    "tgn:placetype":[
        "aat:300008347"
    ]
},
  "bbox": [],
  "geometry": {"coordinates":[30.917443,30.814085],"type":"Point"}
}