{
  "id": 2015967,
  "type": "Feature",
  "properties": {
    "tgn:hierarchy":[
        "tgn:2015967",
        "tgn:1000001",
        "tgn:7012149",
        "tgn:2000219",
        "tgn:7007158",
        "tgn:7029392"
    ],
    "tgn:id":2015967,
    "tgn:name":"Mayne",
    "tgn:placetype":[
        "aat:300387016"
    ]
},
  "bbox": [],
  "geometry": {"coordinates":[-104.7167,37.55],"type":"Point"}
}