<<<<<<< HEAD
{
  "id": 7176404,
  "type": "Feature",
  "properties": {
    "tgn:hierarchy":[
        "tgn:7176404",
        "tgn:1000003",
        "tgn:7003685",
        "tgn:7000084",
        "tgn:7029392"
    ],
    "tgn:id":7176404,
    "tgn:name":"Gr\u00fcnholz",
    "tgn:placetype":[
        "aat:300000206"
    ]
},
  "bbox": [],
  "geometry": {"coordinates":[12.25,50.366667],"type":"Point"}
}
=======
{"geometry":{"type":"Point","coordinates":[12.250000,50.366667]},"type":"Feature","properties":{"hierarchy":["tgn:7176404","tgn:1000003","tgn:7003685","tgn:7000084","tgn:7029392"],"placetype":["aat:300000206"],"id":7176404,"name:xx":"Gr\u00fcnholz"}}
>>>>>>> 03f74aca74312dbeaf24d7e61306dd6a786dc3d0
