{
  "id": 2162583,
  "type": "Feature",
  "properties": {
    "tgn:hierarchy":[
        "tgn:2162583",
        "tgn:1000001",
        "tgn:7012149",
        "tgn:2002382",
        "tgn:7007923",
        "tgn:7029392"
    ],
    "tgn:id":2162583,
    "tgn:name":"Bench Corral Reservoir Number 3",
    "tgn:placetype":[
        "aat:300006191"
    ]
},
  "bbox": [],
  "geometry": {"coordinates":[-110.0167,42.5667],"type":"Point"}
}