{
  "id": 2648910,
  "type": "Feature",
  "properties": {
    "tgn:hierarchy":[
        "tgn:2648910",
        "tgn:1000001",
        "tgn:7012149",
        "tgn:2001912",
        "tgn:7007825",
        "tgn:7029392"
    ],
    "tgn:id":2648910,
    "tgn:name":"Scott Branch",
    "tgn:placetype":[
        "aat:300008699"
    ]
},
  "bbox": [],
  "geometry": {"coordinates":[-84.3333,36.55],"type":"Point"}
}