{
  "id": 7367666,
  "type": "Feature",
  "properties": {
    "tgn:hierarchy":[
        "tgn:7367666",
        "tgn:1000001",
        "tgn:7005595",
        "tgn:7005560",
        "tgn:7029392"
    ],
    "tgn:id":7367666,
    "tgn:name":"El Potrero",
    "tgn:placetype":[
        "aat:300008347"
    ]
},
  "bbox": [],
  "geometry": {"coordinates":[-105.716667,23.066667],"type":"Point"}
}