{
  "id": 2029646,
  "type": "Feature",
  "properties": {
    "tgn:hierarchy":[
        "tgn:2029646",
        "tgn:1000001",
        "tgn:7012149",
        "tgn:2000517",
        "tgn:7007251",
        "tgn:7029392"
    ],
    "tgn:id":2029646,
    "tgn:name":"Petrolia",
    "tgn:placetype":[
        "aat:300008347"
    ]
},
  "bbox": [],
  "geometry": {"coordinates":[-87.7667,38.75],"type":"Point"}
}