{
  "id": 7358015,
  "type": "Feature",
  "properties": {
    "tgn:hierarchy":[
        "tgn:7358015",
        "tgn:1001835",
        "tgn:1000001",
        "tgn:7005560",
        "tgn:7029392"
    ],
    "tgn:id":7358015,
    "tgn:name":"Costa Azul, Playa",
    "tgn:placetype":[
        "aat:300008816"
    ]
},
  "bbox": [],
  "geometry": {"coordinates":[-117.116667,32.516667],"type":"Point"}
}