{
  "id": 2479605,
  "type": "Feature",
  "properties": {
    "tgn:hierarchy":[
        "tgn:2479605",
        "tgn:1000001",
        "tgn:7012149",
        "tgn:1002416",
        "tgn:7007252",
        "tgn:7029392"
    ],
    "tgn:id":2479605,
    "tgn:name":"Lake Branch",
    "tgn:placetype":[
        "aat:300008699"
    ]
},
  "bbox": [],
  "geometry": {"coordinates":[-85.4667,40.4167],"type":"Point"}
}