{
  "id": 7307772,
  "type": "Feature",
  "properties": {
    "tgn:hierarchy":[
        "tgn:7307772",
        "tgn:7002807",
        "tgn:1000003",
        "tgn:7003837",
        "tgn:1000095",
        "tgn:7029392"
    ],
    "tgn:id":7307772,
    "tgn:name":"Mar\u00eda, Rivera de",
    "tgn:placetype":[
        "aat:300008699"
    ]
},
  "bbox": [],
  "geometry": {"coordinates":[-6.05,38.033333],"type":"Point"}
}