<<<<<<< HEAD
{
  "id": 7174346,
  "type": "Feature",
  "properties": {
    "tgn:hierarchy":[
        "tgn:7174346",
        "tgn:7003692",
        "tgn:1000003",
        "tgn:7000084",
        "tgn:7029392"
    ],
    "tgn:id":7174346,
    "tgn:name":"Gro\u00dferlach",
    "tgn:placetype":[
        "aat:300008347"
    ]
},
  "bbox": [],
  "geometry": {"coordinates":[9.516667,49.05],"type":"Point"}
}
=======
{"geometry":{"type":"Point","coordinates":[9.516667,49.050000]},"type":"Feature","properties":{"hierarchy":["tgn:7174346","tgn:7003692","tgn:1000003","tgn:7000084","tgn:7029392"],"placetype":["aat:300008347"],"id":7174346,"name:xx":"Gro\u00dferlach"}}
>>>>>>> 03f74aca74312dbeaf24d7e61306dd6a786dc3d0
