{
  "id": 2334153,
  "type": "Feature",
  "properties": {
    "tgn:hierarchy":[
        "tgn:2334153",
        "tgn:1002172",
        "tgn:1000001",
        "tgn:7012149",
        "tgn:7007710",
        "tgn:7029392"
    ],
    "tgn:id":2334153,
    "tgn:name":"Foreman",
    "tgn:placetype":[
        "aat:300008347"
    ]
},
  "bbox": [],
  "geometry": {"coordinates":[-78.3833,40.0667],"type":"Point"}
}