{
  "id": 7408943,
  "type": "Feature",
  "properties": {
    "tgn:hierarchy":[
        "tgn:7408943",
        "tgn:7005580",
        "tgn:1000001",
        "tgn:7005560",
        "tgn:7029392"
    ],
    "tgn:id":7408943,
    "tgn:name":"Justo Sierra",
    "tgn:placetype":[
        "aat:300008347"
    ]
},
  "bbox": [],
  "geometry": {"coordinates":[-92.05,16.541667],"type":"Point"}
}