{
  "id": 7380043,
  "type": "Feature",
  "properties": {
    "tgn:hierarchy":[
        "tgn:7380043",
        "tgn:1000001",
        "tgn:7005589",
        "tgn:7005560",
        "tgn:7029392"
    ],
    "tgn:id":7380043,
    "tgn:name":"Mina",
    "tgn:placetype":[
        "aat:300007783"
    ]
},
  "bbox": [],
  "geometry": {"coordinates":[-100.516667,25.983333],"type":"Point"}
}