{
  "id": 7584998,
  "type": "Feature",
  "properties": {
    "tgn:hierarchy":[
        "tgn:7584998",
        "tgn:1000004",
        "tgn:7000198",
        "tgn:1001894",
        "tgn:7029392"
    ],
    "tgn:id":7584998,
    "tgn:name:en":"Cherya",
    "tgn:placetype":[
        "aat:300008795"
    ]
},
  "bbox": [],
  "geometry": {"coordinates":[78.296675,24.980173],"type":"Point"}
}