{
  "id": 2520660,
  "type": "Feature",
  "properties": {
    "tgn:hierarchy":[
        "tgn:2520660",
        "tgn:1000001",
        "tgn:7016102",
        "tgn:7012149",
        "tgn:7007516",
        "tgn:7029392"
    ],
    "tgn:id":2520660,
    "tgn:name":"Monks Island",
    "tgn:placetype":[
        "aat:300008791"
    ]
},
  "bbox": [],
  "geometry": {"coordinates":[-76.2167,39.35],"type":"Point"}
}