{
  "id": 2497096,
  "type": "Feature",
  "properties": {
    "tgn:hierarchy":[
        "tgn:2497096",
        "tgn:1002309",
        "tgn:1000001",
        "tgn:7012149",
        "tgn:7007565",
        "tgn:7029392"
    ],
    "tgn:id":2497096,
    "tgn:name":"Maurice River",
    "tgn:placetype":[
        "aat:300008347"
    ]
},
  "bbox": [],
  "geometry": {"coordinates":[-75.0167,39.2167],"type":"Point"}
}