{
  "id": 7281612,
  "type": "Feature",
  "properties": {
    "tgn:hierarchy":[
        "tgn:7281612",
        "tgn:1001708",
        "tgn:1000049",
        "tgn:1000002",
        "tgn:7029392"
    ],
    "tgn:id":7281612,
    "tgn:name":"San Antonio de Tango",
    "tgn:placetype":[
        "aat:300000206"
    ]
},
  "bbox": [],
  "geometry": {"coordinates":[-70.716667,-33.616667],"type":"Point"}
}