{
  "id": 2624096,
  "type": "Feature",
  "properties": {
    "tgn:hierarchy":[
        "tgn:2624096",
        "tgn:1000001",
        "tgn:7012149",
        "tgn:2002293",
        "tgn:7013961",
        "tgn:7029392"
    ],
    "tgn:id":2624096,
    "tgn:name":"Rock Hollow",
    "tgn:placetype":[
        "aat:300008761"
    ]
},
  "bbox": [],
  "geometry": {"coordinates":[-81.25,38.6333],"type":"Point"}
}