{
  "id": 2101481,
  "type": "Feature",
  "properties": {
    "tgn:hierarchy":[
        "tgn:2101481",
        "tgn:1000001",
        "tgn:2001838",
        "tgn:7012149",
        "tgn:7007825",
        "tgn:7029392"
    ],
    "tgn:id":2101481,
    "tgn:name":"Shelbyville Mills",
    "tgn:placetype":[
        "aat:300008347"
    ]
},
  "bbox": [],
  "geometry": {"coordinates":[-86.4833,35.4667],"type":"Point"}
}