{
  "id": 2197312,
  "type": "Feature",
  "properties": {
    "tgn:hierarchy":[
        "tgn:2197312",
        "tgn:1000001",
        "tgn:2002149",
        "tgn:7012149",
        "tgn:7007919",
        "tgn:7029392"
    ],
    "tgn:id":2197312,
    "tgn:name":"Brown Branch",
    "tgn:placetype":[
        "aat:300008699"
    ]
},
  "bbox": [],
  "geometry": {"coordinates":[-78.3167,37.35],"type":"Point"}
}