<<<<<<< HEAD
{
  "id": 2251197,
  "type": "Feature",
  "properties": {
    "tgn:hierarchy":[
        "tgn:2251197",
        "tgn:1000001",
        "tgn:7012149",
        "tgn:2000226",
        "tgn:7007158",
        "tgn:7029392"
    ],
    "tgn:id":2251197,
    "tgn:name":"Comanche Lake",
    "tgn:placetype":[
        "aat:300008680"
    ]
},
  "bbox": [],
  "geometry": {"coordinates":[-105.6833,40.5667],"type":"Point"}
}
=======
{"geometry":{"type":"Point","coordinates":[-105.683300,40.566700]},"type":"Feature","properties":{"hierarchy":["tgn:2251197","tgn:1000001","tgn:7012149","tgn:2000226","tgn:7007158","tgn:7029392"],"placetype":["aat:300008680"],"id":2251197,"name:xx":"Comanche Lake"}}
>>>>>>> 03f74aca74312dbeaf24d7e61306dd6a786dc3d0
