{
  "id": 2776624,
  "type": "Feature",
  "properties": {
    "tgn:hierarchy":[
        "tgn:2776624",
        "tgn:1000001",
        "tgn:7012149",
        "tgn:2000811",
        "tgn:7007255",
        "tgn:7029392"
    ],
    "tgn:id":2776624,
    "tgn:name":"Winding Star Hollow",
    "tgn:placetype":[
        "aat:300008761"
    ]
},
  "bbox": [],
  "geometry": {"coordinates":[-83.3333,37.15],"type":"Point"}
}