{
  "id": 7098115,
  "type": "Feature",
  "properties": {
    "tgn:hierarchy":[
        "tgn:7098115",
        "tgn:1000003",
        "tgn:7003682",
        "tgn:7000084",
        "tgn:7029392"
    ],
    "tgn:id":7098115,
    "tgn:name":"Sponheim",
    "tgn:placetype":[
        "aat:300008347"
    ]
},
  "bbox": [],
  "geometry": {"coordinates":[7.733333,49.85],"type":"Point"}
}