{
  "id": 2604994,
  "type": "Feature",
  "properties": {
    "tgn:hierarchy":[
        "tgn:2604994",
        "tgn:1000001",
        "tgn:7012149",
        "tgn:2000209",
        "tgn:7007158",
        "tgn:7029392"
    ],
    "tgn:id":2604994,
    "tgn:name":"Racoon Knob",
    "tgn:placetype":[
        "aat:300008798"
    ]
},
  "bbox": [],
  "geometry": {"coordinates":[-104.9167,39.45],"type":"Point"}
}