{
  "id": 7409929,
  "type": "Feature",
  "properties": {
    "tgn:hierarchy":[
        "tgn:7409929",
        "tgn:1000001",
        "tgn:7005590",
        "tgn:7005560",
        "tgn:7029392"
    ],
    "tgn:id":7409929,
    "tgn:name":"La Fabrica",
    "tgn:placetype":[
        "aat:300008347"
    ]
},
  "bbox": [],
  "geometry": {"coordinates":[-102.666667,18.583333],"type":"Point"}
}