{
  "id": 1128264,
  "type": "Feature",
  "properties": {
    "tgn:hierarchy":[
        "tgn:1128264",
        "tgn:7005685",
        "tgn:1000001",
        "tgn:7005734",
        "tgn:7029392"
    ],
    "tgn:id":1128264,
    "tgn:name":"Owl",
    "tgn:placetype":[
        "aat:300008707"
    ]
},
  "bbox": [],
  "geometry": {"coordinates":[-92.75,57.8333],"type":"Point"}
}