<<<<<<< HEAD
{
  "id": 7356532,
  "type": "Feature",
  "properties": {
    "tgn:hierarchy":[
        "tgn:7356532",
        "tgn:1000001",
        "tgn:7005601",
        "tgn:7005560",
        "tgn:7029392"
    ],
    "tgn:id":7356532,
    "tgn:name":"Campana",
    "tgn:placetype":[
        "aat:300008347"
    ]
},
  "bbox": [],
  "geometry": {"coordinates":[-101.083333,24.6],"type":"Point"}
}
=======
{"geometry":{"type":"Point","coordinates":[-101.083333,24.600000]},"type":"Feature","properties":{"hierarchy":["tgn:7356532","tgn:1000001","tgn:7005601","tgn:7005560","tgn:7029392"],"placetype":["aat:300008347"],"id":7356532,"name:xx":"Campana"}}
>>>>>>> 03f74aca74312dbeaf24d7e61306dd6a786dc3d0
