{
  "id": 2176631,
  "type": "Feature",
  "properties": {
    "tgn:hierarchy":[
        "tgn:2176631",
        "tgn:1000001",
        "tgn:7012149",
        "tgn:7007157",
        "tgn:1002861",
        "tgn:7029392"
    ],
    "tgn:id":2176631,
    "tgn:name":"Black Lands",
    "tgn:placetype":[
        "aat:300008347"
    ]
},
  "bbox": [],
  "geometry": {"coordinates":[-121.2333,38.05],"type":"Point"}
}