{
  "id": 2211640,
  "type": "Feature",
  "properties": {
    "tgn:hierarchy":[
        "tgn:2211640",
        "tgn:1000001",
        "tgn:7012149",
        "tgn:2001909",
        "tgn:7007825",
        "tgn:7029392"
    ],
    "tgn:id":2211640,
    "tgn:name":"Buttermilk Shores",
    "tgn:placetype":[
        "aat:300008347"
    ]
},
  "bbox": [],
  "geometry": {"coordinates":[-84.35,35.8667],"type":"Point"}
}