{
  "id": 7054208,
  "type": "Feature",
  "properties": {
    "tgn:hierarchy":[
        "tgn:7054208",
        "tgn:7003171",
        "tgn:1000003",
        "tgn:7003125",
        "tgn:1000080",
        "tgn:7029392"
    ],
    "tgn:id":7054208,
    "tgn:name":"Porchiano",
    "tgn:placetype":[
        "aat:300008347"
    ]
},
  "bbox": [],
  "geometry": {"coordinates":[12.35,42.55],"type":"Point"}
}