{
  "id": 7140234,
  "type": "Feature",
  "properties": {
    "tgn:hierarchy":[
        "tgn:7140234",
        "tgn:1000003",
        "tgn:7003677",
        "tgn:7000084",
        "tgn:7029392"
    ],
    "tgn:id":7140234,
    "tgn:name":"Lous Berg",
    "tgn:placetype":[
        "aat:300008795"
    ]
},
  "bbox": [],
  "geometry": {"coordinates":[6.083333,50.783333],"type":"Point"}
}