{
  "id": 2177104,
  "type": "Feature",
  "properties": {
    "tgn:hierarchy":[
        "tgn:2177104",
        "tgn:1000001",
        "tgn:7012149",
        "tgn:7007157",
        "tgn:1002828",
        "tgn:7029392"
    ],
    "tgn:id":2177104,
    "tgn:name":"Black Point",
    "tgn:placetype":[
        "aat:300008850"
    ]
},
  "bbox": [],
  "geometry": {"coordinates":[-114.5167,33.75],"type":"Point"}
}