{
  "id": 7507729,
  "type": "Feature",
  "properties": {
    "tgn:hierarchy":[
        "tgn:7507729",
        "tgn:1009227",
        "tgn:1000226",
        "tgn:7018437",
        "tgn:1000006",
        "tgn:7029392"
    ],
    "tgn:id":7507729,
    "tgn:name:en":"Pleasant Valley",
    "tgn:placetype":[
        "aat:300008761"
    ]
},
  "bbox": [],
  "geometry": {"coordinates":[170.783333,-45.05],"type":"Point"}
}