{
  "id": 7386955,
  "type": "Feature",
  "properties": {
    "tgn:hierarchy":[
        "tgn:7386955",
        "tgn:1000001",
        "tgn:7005599",
        "tgn:7005560",
        "tgn:7029392"
    ],
    "tgn:id":7386955,
    "tgn:name":"Ranchoapan",
    "tgn:placetype":[
        "aat:300008347"
    ]
},
  "bbox": [],
  "geometry": {"coordinates":[-94.75,17.733333],"type":"Point"}
}