<<<<<<< HEAD
{
  "id": 2336547,
  "type": "Feature",
  "properties": {
    "tgn:hierarchy":[
        "tgn:2336547",
        "tgn:1000001",
        "tgn:7012149",
        "tgn:7007157",
        "tgn:1002894",
        "tgn:7029392"
    ],
    "tgn:id":2336547,
    "tgn:name":"Four Hills Mine",
    "tgn:placetype":[
        "aat:300000390"
    ]
},
  "bbox": [],
  "geometry": {"coordinates":[-120.7,39.6833],"type":"Point"}
}
=======
{"geometry":{"type":"Point","coordinates":[-120.700000,39.683300]},"type":"Feature","properties":{"hierarchy":["tgn:2336547","tgn:1000001","tgn:7012149","tgn:7007157","tgn:1002894","tgn:7029392"],"placetype":["aat:300000390"],"id":2336547,"name:xx":"Four Hills Mine"}}
>>>>>>> 03f74aca74312dbeaf24d7e61306dd6a786dc3d0
