{
  "id": 2097608,
  "type": "Feature",
  "properties": {
    "tgn:hierarchy":[
        "tgn:2097608",
        "tgn:1000001",
        "tgn:2001776",
        "tgn:7012149",
        "tgn:7007713",
        "tgn:7029392"
    ],
    "tgn:id":2097608,
    "tgn:name":"Verdon",
    "tgn:placetype":[
        "aat:300008347"
    ]
},
  "bbox": [],
  "geometry": {"coordinates":[-98.0833,45.2333],"type":"Point"}
}