{
  "id": 2680642,
  "type": "Feature",
  "properties": {
    "tgn:hierarchy":[
        "tgn:2680642",
        "tgn:1000001",
        "tgn:7006451",
        "tgn:2000094",
        "tgn:7012149",
        "tgn:7029392"
    ],
    "tgn:id":2680642,
    "tgn:name":"South Headquarters Tank",
    "tgn:placetype":[
        "aat:300006191"
    ]
},
  "bbox": [],
  "geometry": {"coordinates":[-110.0167,33.35],"type":"Point"}
}