{
  "id": 7222559,
  "type": "Feature",
  "properties": {
    "tgn:hierarchy":[
        "tgn:7222559",
        "tgn:7002743",
        "tgn:7017076",
        "tgn:1000003",
        "tgn:1000074",
        "tgn:7029392"
    ],
    "tgn:id":7222559,
    "tgn:name":"Sim\u00f3poulon",
    "tgn:placetype":[
        "aat:300008347"
    ]
},
  "bbox": [],
  "geometry": {"coordinates":[21.566667,37.85],"type":"Point"}
}