<<<<<<< HEAD
{
  "id": 7056659,
  "type": "Feature",
  "properties": {
    "tgn:hierarchy":[
        "tgn:7056659",
        "tgn:1000003",
        "tgn:7003122",
        "tgn:7003157",
        "tgn:1000080",
        "tgn:7029392"
    ],
    "tgn:id":7056659,
    "tgn:name":"Acque Dolci",
    "tgn:placetype":[
        "aat:300008347"
    ]
},
  "bbox": [],
  "geometry": {"coordinates":[14.583333,38.05],"type":"Point"}
}
=======
{"geometry":{"type":"Point","coordinates":[14.583333,38.050000]},"type":"Feature","properties":{"hierarchy":["tgn:7056659","tgn:1000003","tgn:7003122","tgn:7003157","tgn:1000080","tgn:7029392"],"placetype":["aat:300008347"],"id":7056659,"name:xx":"Acque Dolci"}}
>>>>>>> 03f74aca74312dbeaf24d7e61306dd6a786dc3d0
