{
  "id": 2144181,
  "type": "Feature",
  "properties": {
    "tgn:hierarchy":[
        "tgn:2144181",
        "tgn:1000001",
        "tgn:7012149",
        "tgn:2000226",
        "tgn:7007158",
        "tgn:7029392"
    ],
    "tgn:id":2144181,
    "tgn:name":"Baker Lake",
    "tgn:placetype":[
        "aat:300006191"
    ]
},
  "bbox": [],
  "geometry": {"coordinates":[-104.9667,40.5833],"type":"Point"}
}