{
  "id": 2142573,
  "type": "Feature",
  "properties": {
    "tgn:hierarchy":[
        "tgn:2142573",
        "tgn:1000001",
        "tgn:7012149",
        "tgn:1002875",
        "tgn:7007568",
        "tgn:7029392"
    ],
    "tgn:id":2142573,
    "tgn:name":"Bad Indian Swamp",
    "tgn:placetype":[
        "aat:300008905"
    ]
},
  "bbox": [],
  "geometry": {"coordinates":[-76.85,42.35],"type":"Point"}
}