{
  "id": 7445341,
  "type": "Feature",
  "properties": {
    "tgn:hierarchy":[
        "tgn:7445341",
        "tgn:7002443",
        "tgn:5000552",
        "tgn:1000003",
        "tgn:7008591",
        "tgn:7029392"
    ],
    "tgn:id":7445341,
    "tgn:name:en":"Hermon",
    "tgn:placetype":[
        "aat:300008347"
    ]
},
  "bbox": [],
  "geometry": {"coordinates":[-4.383333,51.95],"type":"Point"}
}