{
  "id": 7336999,
  "type": "Feature",
  "properties": {
    "tgn:hierarchy":[
        "tgn:7336999",
        "tgn:7002758",
        "tgn:7002821",
        "tgn:1000003",
        "tgn:1000095",
        "tgn:7029392"
    ],
    "tgn:id":7336999,
    "tgn:name":"Cuesta Vieja",
    "tgn:placetype":[
        "aat:300008347"
    ]
},
  "bbox": [],
  "geometry": {"coordinates":[-3.133333,36.816667],"type":"Point"}
}