{
  "id": 2548726,
  "type": "Feature",
  "properties": {
    "tgn:hierarchy":[
        "tgn:2548726",
        "tgn:1000001",
        "tgn:7012149",
        "tgn:2000933",
        "tgn:7007515",
        "tgn:7029392"
    ],
    "tgn:id":2548726,
    "tgn:name":"North Parsonsfield",
    "tgn:placetype":[
        "aat:300008347"
    ]
},
  "bbox": [],
  "geometry": {"coordinates":[-70.9167,43.75],"type":"Point"}
}