{
  "id": 2206037,
  "type": "Feature",
  "properties": {
    "tgn:hierarchy":[
        "tgn:2206037",
        "tgn:1000001",
        "tgn:2001411",
        "tgn:7012149",
        "tgn:7007526",
        "tgn:7029392"
    ],
    "tgn:id":2206037,
    "tgn:name":"Bull Run Mountains",
    "tgn:placetype":[
        "aat:300386831"
    ]
},
  "bbox": [],
  "geometry": {"coordinates":[-116.1333,41.8333],"type":"Point"}
}