{
  "id": 2213167,
  "type": "Feature",
  "properties": {
    "tgn:hierarchy":[
        "tgn:2213167",
        "tgn:1000001",
        "tgn:7012149",
        "tgn:1002368",
        "tgn:7007919",
        "tgn:7029392"
    ],
    "tgn:id":2213167,
    "tgn:name":"Cabin Branch",
    "tgn:placetype":[
        "aat:300008699"
    ]
},
  "bbox": [],
  "geometry": {"coordinates":[-77.95,38.75],"type":"Point"}
}