{
  "id": 1118339,
  "type": "Feature",
  "properties": {
    "tgn:hierarchy":[
        "tgn:1118339",
        "tgn:1000001",
        "tgn:7012149",
        "tgn:1002785",
        "tgn:7007920",
        "tgn:7029392"
    ],
    "tgn:id":1118339,
    "tgn:name":"Tapps, Lake",
    "tgn:placetype":[
        "aat:300008680"
    ]
},
  "bbox": [],
  "geometry": {"coordinates":[-122.1833,47.2333],"type":"Point"}
}