{
  "id": 1031355,
  "type": "Feature",
  "properties": {
    "tgn:hierarchy":[
        "tgn:1031355",
        "tgn:7594378",
        "tgn:1000003",
        "tgn:1000069",
        "tgn:7029392"
    ],
    "tgn:id":1031355,
    "tgn:name":"Kastelholm",
    "tgn:placetype":[
        "aat:300008347"
    ]
},
  "bbox": [],
  "geometry": {"coordinates":[20.0667,60.2333],"type":"Point"}
}