{
  "id": 2129324,
  "type": "Feature",
  "properties": {
    "tgn:hierarchy":[
        "tgn:2129324",
        "tgn:2000947",
        "tgn:1000001",
        "tgn:7012149",
        "tgn:7007520",
        "tgn:7029392"
    ],
    "tgn:id":2129324,
    "tgn:name":"Alice, Lake",
    "tgn:placetype":[
        "aat:300008680"
    ]
},
  "bbox": [],
  "geometry": {"coordinates":[-88.0667,46.6833],"type":"Point"}
}