{
  "id": 7077965,
  "type": "Feature",
  "properties": {
    "tgn:hierarchy":[
        "tgn:7077965",
        "tgn:1000003",
        "tgn:7003687",
        "tgn:7000084",
        "tgn:7029392"
    ],
    "tgn:id":7077965,
    "tgn:name":"W\u00fcste Mark Mainz",
    "tgn:placetype":[
        "aat:300055621"
    ]
},
  "bbox": [],
  "geometry": {"coordinates":[11.466667,52.416667],"type":"Point"}
}