{
  "id": 2656455,
  "type": "Feature",
  "properties": {
    "tgn:hierarchy":[
        "tgn:2656455",
        "tgn:1000001",
        "tgn:7012149",
        "tgn:1002999",
        "tgn:7007526",
        "tgn:7029392"
    ],
    "tgn:id":2656455,
    "tgn:name":"Sheehan Spring",
    "tgn:placetype":[
        "aat:300008697"
    ]
},
  "bbox": [],
  "geometry": {"coordinates":[-119.4333,39.65],"type":"Point"}
}