{
  "id": 7080658,
  "type": "Feature",
  "properties": {
    "tgn:hierarchy":[
        "tgn:7080658",
        "tgn:7003669",
        "tgn:1000003",
        "tgn:7000084",
        "tgn:7029392"
    ],
    "tgn:id":7080658,
    "tgn:name":"Winkl",
    "tgn:placetype":[
        "aat:300008347"
    ]
},
  "bbox": [],
  "geometry": {"coordinates":[11.783333,49.033333],"type":"Point"}
}