{
  "id": 7556904,
  "type": "Feature",
  "properties": {
    "tgn:hierarchy":[
        "tgn:7556904",
        "tgn:1000004",
        "tgn:7000198",
        "tgn:7000799",
        "tgn:7029392"
    ],
    "tgn:id":7556904,
    "tgn:name:en":"R\u0101mgarh",
    "tgn:placetype":[
        "aat:300008347"
    ]
},
  "bbox": [],
  "geometry": {"coordinates":[74.223138,33.403542],"type":"Point"}
}