{
  "id": 2340781,
  "type": "Feature",
  "properties": {
    "tgn:hierarchy":[
        "tgn:2340781",
        "tgn:1000001",
        "tgn:7012149",
        "tgn:7007157",
        "tgn:7029392"
    ],
    "tgn:id":2340781,
    "tgn:name":"Fresno Canyon",
    "tgn:placetype":[
        "aat:300008761"
    ]
},
  "bbox": [],
  "geometry": {"coordinates":[-117.6333,33.85],"type":"Point"}
}