{
  "id": 2150994,
  "type": "Feature",
  "properties": {
    "tgn:hierarchy":[
        "tgn:2150994",
        "tgn:1000001",
        "tgn:7012149",
        "tgn:2000961",
        "tgn:7007520",
        "tgn:7029392"
    ],
    "tgn:id":2150994,
    "tgn:name":"Bassett Island",
    "tgn:placetype":[
        "aat:300008791"
    ]
},
  "bbox": [],
  "geometry": {"coordinates":[-85.5667,44.8667],"type":"Point"}
}