<<<<<<< HEAD
{
  "id": 7480396,
  "type": "Feature",
  "properties": {
    "tgn:hierarchy":[
        "tgn:7480396",
        "tgn:1000004",
        "tgn:7471332",
        "tgn:1000141",
        "tgn:7029392"
    ],
    "tgn:id":7480396,
    "tgn:name":"Fengshan Si",
    "tgn:placetype":[
        "aat:300007595"
    ]
},
  "bbox": [],
  "geometry": {"coordinates":[121.013889,24.878889],"type":"Point"}
}
=======
{"geometry":{"type":"Point","coordinates":[121.013889,24.878889]},"type":"Feature","properties":{"hierarchy":["tgn:7480396","tgn:1000004","tgn:7471332","tgn:1000141","tgn:7029392"],"placetype":["aat:300007595"],"id":7480396,"name:xx":"Fengshan Si"}}
>>>>>>> 03f74aca74312dbeaf24d7e61306dd6a786dc3d0
