<<<<<<< HEAD
{
  "id": 2255882,
  "type": "Feature",
  "properties": {
    "tgn:hierarchy":[
        "tgn:2255882",
        "tgn:1000001",
        "tgn:7012149",
        "tgn:1003042",
        "tgn:7007920",
        "tgn:7029392"
    ],
    "tgn:id":2255882,
    "tgn:name":"Copper Creek",
    "tgn:placetype":[
        "aat:300008706"
    ]
},
  "bbox": [],
  "geometry": {"coordinates":[-121.2833,46.75],"type":"Point"}
}
=======
{"geometry":{"type":"Point","coordinates":[-121.283300,46.750000]},"type":"Feature","properties":{"hierarchy":["tgn:2255882","tgn:1000001","tgn:7012149","tgn:1003042","tgn:7007920","tgn:7029392"],"placetype":["aat:300008706"],"id":2255882,"name:xx":"Copper Creek"}}
>>>>>>> 03f74aca74312dbeaf24d7e61306dd6a786dc3d0
