{
  "id": 2584832,
  "type": "Feature",
  "properties": {
    "tgn:hierarchy":[
        "tgn:2584832",
        "tgn:2001468",
        "tgn:1000001",
        "tgn:7012149",
        "tgn:7007709",
        "tgn:7029392"
    ],
    "tgn:id":2584832,
    "tgn:name":"Pink Ridge",
    "tgn:placetype":[
        "aat:300266640"
    ]
},
  "bbox": [],
  "geometry": {"coordinates":[-81.9667,35.9667],"type":"Point"}
}