{
  "id": 7492591,
  "type": "Feature",
  "properties": {
    "tgn:hierarchy":[
        "tgn:7492591",
        "tgn:7001004",
        "tgn:1000004",
        "tgn:1000141",
        "tgn:7029392"
    ],
    "tgn:id":7492591,
    "tgn:name":"Shanzha",
    "tgn:placetype":[
        "aat:300008347"
    ]
},
  "bbox": [],
  "geometry": {"coordinates":[120.369356,22.563451],"type":"Point"}
}