{
  "id": 2127050,
  "type": "Feature",
  "properties": {
    "tgn:hierarchy":[
        "tgn:2127050",
        "tgn:1000001",
        "tgn:7012149",
        "tgn:7007922",
        "tgn:7029392"
    ],
    "tgn:id":2127050,
    "tgn:name":"Ahnapee River",
    "tgn:placetype":[
        "aat:300008707"
    ]
},
  "bbox": [],
  "geometry": {"coordinates":[-87.5333,44.7667],"type":"Point"}
}