<<<<<<< HEAD
{
  "id": 2409024,
  "type": "Feature",
  "properties": {
    "tgn:hierarchy":[
        "tgn:2409024",
        "tgn:1000001",
        "tgn:7012149",
        "tgn:2001304",
        "tgn:7007524",
        "tgn:7029392"
    ],
    "tgn:id":2409024,
    "tgn:name":"Ibex Creek",
    "tgn:placetype":[
        "aat:300008706"
    ]
},
  "bbox": [],
  "geometry": {"coordinates":[-115.6667,48.1833],"type":"Point"}
}
=======
{"geometry":{"type":"Point","coordinates":[-115.666700,48.183300]},"type":"Feature","properties":{"hierarchy":["tgn:2409024","tgn:1000001","tgn:7012149","tgn:2001304","tgn:7007524","tgn:7029392"],"placetype":["aat:300008706"],"id":2409024,"name:xx":"Ibex Creek"}}
>>>>>>> 03f74aca74312dbeaf24d7e61306dd6a786dc3d0
