{
  "id": 2409024,
  "type": "Feature",
  "properties": {
    "tgn:hierarchy":[
        "tgn:2409024",
        "tgn:1000001",
        "tgn:7012149",
        "tgn:2001304",
        "tgn:7007524",
        "tgn:7029392"
    ],
    "tgn:id":2409024,
    "tgn:name":"Ibex Creek",
    "tgn:placetype":[
        "aat:300008706"
    ]
},
  "bbox": [],
  "geometry": {"coordinates":[-115.6667,48.1833],"type":"Point"}
}