{
  "id": 2169459,
  "type": "Feature",
  "properties": {
    "tgn:hierarchy":[
        "tgn:2169459",
        "tgn:1000001",
        "tgn:7012149",
        "tgn:2000283",
        "tgn:7007240",
        "tgn:7029392"
    ],
    "tgn:id":2169459,
    "tgn:name":"Big Lige Branch",
    "tgn:placetype":[
        "aat:300008699"
    ]
},
  "bbox": [],
  "geometry": {"coordinates":[-81.6167,30.0833],"type":"Point"}
}