{
  "id": 2622142,
  "type": "Feature",
  "properties": {
    "tgn:hierarchy":[
        "tgn:2622142",
        "tgn:1000001",
        "tgn:7012149",
        "tgn:2001231",
        "tgn:7007523",
        "tgn:7029392"
    ],
    "tgn:id":2622142,
    "tgn:name":"Roberts Lake",
    "tgn:placetype":[
        "aat:300008680"
    ]
},
  "bbox": [],
  "geometry": {"coordinates":[-94.7833,39.35],"type":"Point"}
}