{
  "id": 2394645,
  "type": "Feature",
  "properties": {
    "tgn:hierarchy":[
        "tgn:2394645",
        "tgn:1000001",
        "tgn:7012149",
        "tgn:2000836",
        "tgn:7007255",
        "tgn:7029392"
    ],
    "tgn:id":2394645,
    "tgn:name":"Hogtrough Hollow",
    "tgn:placetype":[
        "aat:300008761"
    ]
},
  "bbox": [],
  "geometry": {"coordinates":[-83.1667,37.0667],"type":"Point"}
}