{
  "id": 7590406,
  "type": "Feature",
  "properties": {
    "tgn:hierarchy":[
        "tgn:7590406",
        "tgn:1000004",
        "tgn:7000198",
        "tgn:7000799",
        "tgn:7029392"
    ],
    "tgn:id":7590406,
    "tgn:name:en":"Darw\u0101li",
    "tgn:placetype":[
        "aat:300008347"
    ]
},
  "bbox": [],
  "geometry": {"coordinates":[74.352778,33.758333],"type":"Point"}
}