{
  "id": 2623440,
  "type": "Feature",
  "properties": {
    "tgn:hierarchy":[
        "tgn:2623440",
        "tgn:1000001",
        "tgn:7006451",
        "tgn:2000091",
        "tgn:7012149",
        "tgn:7029392"
    ],
    "tgn:id":2623440,
    "tgn:name":"Rock Creek",
    "tgn:placetype":[
        "aat:300008706"
    ]
},
  "bbox": [],
  "geometry": {"coordinates":[-109.2833,31.8833],"type":"Point"}
}