{
  "id": 1045400,
  "type": "Feature",
  "properties": {
    "tgn:hierarchy":[
        "tgn:1045400",
        "tgn:7024843",
        "tgn:1000003",
        "tgn:7008516",
        "tgn:1000080",
        "tgn:7029392"
    ],
    "tgn:id":1045400,
    "tgn:name":"Misano Adriatico",
    "tgn:placetype":[
        "aat:300008347"
    ]
},
  "bbox": [],
  "geometry": {"coordinates":[12.65,43.95],"type":"Point"}
}