{
  "id": 2019447,
  "type": "Feature",
  "properties": {
    "tgn:hierarchy":[
        "tgn:2019447",
        "tgn:2000257",
        "tgn:1000001",
        "tgn:7012149",
        "tgn:7007240",
        "tgn:7029392"
    ],
    "tgn:id":2019447,
    "tgn:name":"Glen Saint Mary",
    "tgn:placetype":[
        "aat:300008347"
    ]
},
  "bbox": [],
  "geometry": {"coordinates":[-82.15,30.2667],"type":"Point"}
}