{
  "id": 7230040,
  "type": "Feature",
  "properties": {
    "tgn:hierarchy":[
        "tgn:7230040",
        "tgn:7002680",
        "tgn:7001395",
        "tgn:1000003",
        "tgn:1000074",
        "tgn:7029392"
    ],
    "tgn:id":7230040,
    "tgn:name":"L\u00e1kka",
    "tgn:placetype":[
        "aat:300008347"
    ]
},
  "bbox": [],
  "geometry": {"coordinates":[21.983333,38.233333],"type":"Point"}
}