{
  "id": 7572373,
  "type": "Feature",
  "properties": {
    "tgn:hierarchy":[
        "tgn:7572373",
        "tgn:1000004",
        "tgn:7000198",
        "tgn:1001895",
        "tgn:7029392"
    ],
    "tgn:id":7572373,
    "tgn:name:en":"Goomree",
    "tgn:placetype":[
        "aat:300008347"
    ]
},
  "bbox": [],
  "geometry": {"coordinates":[80.266667,19.966667],"type":"Point"}
}