{
  "id": 2453108,
  "type": "Feature",
  "properties": {
    "tgn:hierarchy":[
        "tgn:2453108",
        "tgn:1000001",
        "tgn:7012149",
        "tgn:2000908",
        "tgn:7007256",
        "tgn:7029392"
    ],
    "tgn:id":2453108,
    "tgn:name":"Little Carencro Bayou",
    "tgn:placetype":[
        "aat:300008699"
    ]
},
  "bbox": [],
  "geometry": {"coordinates":[-90.9833,29.4333],"type":"Point"}
}