{
  "id": 7280658,
  "type": "Feature",
  "properties": {
    "tgn:hierarchy":[
        "tgn:7280658",
        "tgn:1001695",
        "tgn:1000049",
        "tgn:1000002",
        "tgn:7029392"
    ],
    "tgn:id":7280658,
    "tgn:name":"San Jos\u00e9 de Toro",
    "tgn:placetype":[
        "aat:300000206"
    ]
},
  "bbox": [],
  "geometry": {"coordinates":[-71.166667,-34.75],"type":"Point"}
}