{
  "id": 7030513,
  "type": "Feature",
  "properties": {
    "tgn:hierarchy":[
        "tgn:7030513",
        "tgn:7002878",
        "tgn:1000003",
        "tgn:1000070",
        "tgn:7029392"
    ],
    "tgn:id":7030513,
    "tgn:name":"Jumilhac-le-Grand",
    "tgn:placetype":[
        "aat:300008347"
    ]
},
  "bbox": [],
  "geometry": {"coordinates":[1.067,45.483],"type":"Point"}
}