{
  "id": 7307628,
  "type": "Feature",
  "properties": {
    "tgn:hierarchy":[
        "tgn:7307628",
        "tgn:7002759",
        "tgn:7002845",
        "tgn:1000003",
        "tgn:1000095",
        "tgn:7029392"
    ],
    "tgn:id":7307628,
    "tgn:name":"Luna",
    "tgn:placetype":[
        "aat:300008347"
    ]
},
  "bbox": [],
  "geometry": {"coordinates":[-0.933333,42.166667],"type":"Point"}
}