{
  "id": 7416598,
  "type": "Feature",
  "properties": {
    "tgn:hierarchy":[
        "tgn:7416598",
        "tgn:1000001",
        "tgn:7005591",
        "tgn:7005560",
        "tgn:7029392"
    ],
    "tgn:id":7416598,
    "tgn:name:es":"San Felipe Zihualtepec",
    "tgn:placetype":[
        "aat:300008347"
    ]
},
  "bbox": [],
  "geometry": {"coordinates":[-95.359722,17.488056],"type":"Point"}
}