<<<<<<< HEAD
{
  "id": 2762345,
  "type": "Feature",
  "properties": {
    "tgn:hierarchy":[
        "tgn:2762345",
        "tgn:1000001",
        "tgn:7012149",
        "tgn:2000982",
        "tgn:7007520",
        "tgn:7029392"
    ],
    "tgn:id":2762345,
    "tgn:name":"West Town Corner Lake",
    "tgn:placetype":[
        "aat:300008680"
    ]
},
  "bbox": [],
  "geometry": {"coordinates":[-84.25,45.1],"type":"Point"}
}
=======
{"geometry":{"type":"Point","coordinates":[-84.250000,45.100000]},"type":"Feature","properties":{"hierarchy":["tgn:2762345","tgn:1000001","tgn:7012149","tgn:2000982","tgn:7007520","tgn:7029392"],"placetype":["aat:300008680"],"id":2762345,"name:xx":"West Town Corner Lake"}}
>>>>>>> 03f74aca74312dbeaf24d7e61306dd6a786dc3d0
