{
  "id": 7209645,
  "type": "Feature",
  "properties": {
    "tgn:hierarchy":[
        "tgn:7209645",
        "tgn:1000003",
        "tgn:7003685",
        "tgn:7000084",
        "tgn:7029392"
    ],
    "tgn:id":7209645,
    "tgn:name":"B\u00e4renlochh\u00e4user",
    "tgn:placetype":[
        "aat:300000206"
    ]
},
  "bbox": [],
  "geometry": {"coordinates":[13.283333,50.766667],"type":"Point"}
}