{
  "id": 2346928,
  "type": "Feature",
  "properties": {
    "tgn:hierarchy":[
        "tgn:2346928",
        "tgn:1000001",
        "tgn:7012149",
        "tgn:7007157",
        "tgn:1002675",
        "tgn:7029392"
    ],
    "tgn:id":2346928,
    "tgn:name":"Gem Lake",
    "tgn:placetype":[
        "aat:300008680"
    ]
},
  "bbox": [],
  "geometry": {"coordinates":[-119.15,37.75],"type":"Point"}
}