{
  "id": 2180545,
  "type": "Feature",
  "properties": {
    "tgn:hierarchy":[
        "tgn:2180545",
        "tgn:1000001",
        "tgn:7012149",
        "tgn:2001049",
        "tgn:7007521",
        "tgn:7029392"
    ],
    "tgn:id":2180545,
    "tgn:name":"Bloody Lake",
    "tgn:placetype":[
        "aat:300008680"
    ]
},
  "bbox": [],
  "geometry": {"coordinates":[-95.6667,44.1333],"type":"Point"}
}