{
  "id": 2264403,
  "type": "Feature",
  "properties": {
    "tgn:hierarchy":[
        "tgn:2264403",
        "tgn:1000001",
        "tgn:7012149",
        "tgn:2000488",
        "tgn:7007250",
        "tgn:7029392"
    ],
    "tgn:id":2264403,
    "tgn:name":"Crab Spring",
    "tgn:placetype":[
        "aat:300008697"
    ]
},
  "bbox": [],
  "geometry": {"coordinates":[-116.2833,42.55],"type":"Point"}
}