{
  "id": 2564878,
  "type": "Feature",
  "properties": {
    "tgn:hierarchy":[
        "tgn:2564878",
        "tgn:1000001",
        "tgn:7012149",
        "tgn:2001453",
        "tgn:7007566",
        "tgn:7029392"
    ],
    "tgn:id":2564878,
    "tgn:name":"Padilla, Ca\u00f1on",
    "tgn:placetype":[
        "aat:300008761"
    ]
},
  "bbox": [],
  "geometry": {"coordinates":[-104.5833,35.4833],"type":"Point"}
}