{
  "id": 7308179,
  "type": "Feature",
  "properties": {
    "tgn:hierarchy":[
        "tgn:7308179",
        "tgn:1001692",
        "tgn:1000049",
        "tgn:1000002",
        "tgn:7029392"
    ],
    "tgn:id":7308179,
    "tgn:name":"Meco, Estero",
    "tgn:placetype":[
        "aat:300008699"
    ]
},
  "bbox": [],
  "geometry": {"coordinates":[-72.65,-38.116667],"type":"Point"}
}