{
  "id": 2288742,
  "type": "Feature",
  "properties": {
    "tgn:hierarchy":[
        "tgn:2288742",
        "tgn:1000001",
        "tgn:7012149",
        "tgn:2001227",
        "tgn:7007523",
        "tgn:7029392"
    ],
    "tgn:id":2288742,
    "tgn:name":"Ditch Number 17",
    "tgn:placetype":[
        "aat:300006075"
    ]
},
  "bbox": [],
  "geometry": {"coordinates":[-89.8667,36.1667],"type":"Point"}
}