{
  "id": 7021145,
  "type": "Feature",
  "properties": {
    "tgn:hierarchy":[
        "tgn:7021145",
        "tgn:1000001",
        "tgn:7012149",
        "tgn:7029392"
    ],
    "tgn:id":7021145,
    "tgn:name":"Saluda Mountains",
    "tgn:placetype":[
        "aat:300386831",
        "aat:300266640"
    ]
},
  "bbox": [],
  "geometry": {"coordinates":[-82.4167,35.1667],"type":"Point"}
}