<<<<<<< HEAD
{
  "id": 7021145,
  "type": "Feature",
  "properties": {
    "tgn:hierarchy":[
        "tgn:7021145",
        "tgn:1000001",
        "tgn:7012149",
        "tgn:7029392"
    ],
    "tgn:id":7021145,
    "tgn:name":"Saluda Mountains",
    "tgn:placetype":[
        "aat:300386831",
        "aat:300266640"
    ]
},
  "bbox": [],
  "geometry": {"coordinates":[-82.4167,35.1667],"type":"Point"}
}
=======
{"geometry":{"type":"Point","coordinates":[-82.416700,35.166700]},"type":"Feature","properties":{"hierarchy":["tgn:7021145","tgn:1000001","tgn:7012149","tgn:7029392"],"placetype":["aat:300386831","aat:300266640"],"id":7021145,"name:xx":"Saluda Mountains"}}
>>>>>>> 03f74aca74312dbeaf24d7e61306dd6a786dc3d0
