{
  "id": 2717023,
  "type": "Feature",
  "properties": {
    "tgn:hierarchy":[
        "tgn:2717023",
        "tgn:1000001",
        "tgn:2001429",
        "tgn:7012149",
        "tgn:7007566",
        "tgn:7029392"
    ],
    "tgn:id":2717023,
    "tgn:name":"Third Apache Canyon",
    "tgn:placetype":[
        "aat:300008761"
    ]
},
  "bbox": [],
  "geometry": {"coordinates":[-108.6333,33.85],"type":"Point"}
}