{
  "id": 2709263,
  "type": "Feature",
  "properties": {
    "tgn:hierarchy":[
        "tgn:2709263",
        "tgn:1000001",
        "tgn:2000470",
        "tgn:7012149",
        "tgn:7007250",
        "tgn:7029392"
    ],
    "tgn:id":2709263,
    "tgn:name":"Table Mountain",
    "tgn:placetype":[
        "aat:300008798"
    ]
},
  "bbox": [],
  "geometry": {"coordinates":[-113.6333,43.8167],"type":"Point"}
}