{
  "id": 7399855,
  "type": "Feature",
  "properties": {
    "tgn:hierarchy":[
        "tgn:7399855",
        "tgn:1000001",
        "tgn:7005593",
        "tgn:7005560",
        "tgn:7029392"
    ],
    "tgn:id":7399855,
    "tgn:name":"San Lorenzo, Arroyo",
    "tgn:placetype":[
        "aat:300008699"
    ]
},
  "bbox": [],
  "geometry": {"coordinates":[-99.504167,21.016667],"type":"Point"}
}