{
  "id": 7511303,
  "type": "Feature",
  "properties": {
    "tgn:hierarchy":[
        "tgn:7511303",
        "tgn:1009227",
        "tgn:1000226",
        "tgn:7018437",
        "tgn:1000006",
        "tgn:7029392"
    ],
    "tgn:id":7511303,
    "tgn:name:en":"Treble Cone",
    "tgn:placetype":[
        "aat:300008798"
    ]
},
  "bbox": [],
  "geometry": {"coordinates":[168.883333,-44.633333],"type":"Point"}
}