{
  "id": 7437773,
  "type": "Feature",
  "properties": {
    "tgn:hierarchy":[
        "tgn:7437773",
        "tgn:1000001",
        "tgn:7005592",
        "tgn:7005560",
        "tgn:7029392"
    ],
    "tgn:id":7437773,
    "tgn:name":"Tenexcalco",
    "tgn:placetype":[
        "aat:300007783"
    ]
},
  "bbox": [],
  "geometry": {"coordinates":[-98.583333,18.466667],"type":"Point"}
}