{
  "id": 1136339,
  "type": "Feature",
  "properties": {
    "tgn:hierarchy":[
        "tgn:1136339",
        "tgn:1001853",
        "tgn:1000001",
        "tgn:7005560",
        "tgn:7029392"
    ],
    "tgn:id":1136339,
    "tgn:name":"Progreso",
    "tgn:placetype":[
        "aat:300008347"
    ]
},
  "bbox": [],
  "geometry": {"coordinates":[-100.983333,27.416667],"type":"Point"}
}