{
  "id": 7367884,
  "type": "Feature",
  "properties": {
    "tgn:hierarchy":[
        "tgn:7367884",
        "tgn:1000001",
        "tgn:7005589",
        "tgn:7005560",
        "tgn:7029392"
    ],
    "tgn:id":7367884,
    "tgn:name":"Federal La Laguna de San Miguel, Parque",
    "tgn:placetype":[
        "aat:300008798"
    ]
},
  "bbox": [],
  "geometry": {"coordinates":[-100.383333,25.866667],"type":"Point"}
}