{
  "id": 7189745,
  "type": "Feature",
  "properties": {
    "tgn:hierarchy":[
        "tgn:7189745",
        "tgn:7003669",
        "tgn:1000003",
        "tgn:7000084",
        "tgn:7029392"
    ],
    "tgn:id":7189745,
    "tgn:name":"Einraffshof",
    "tgn:placetype":[
        "aat:300008347"
    ]
},
  "bbox": [],
  "geometry": {"coordinates":[9.833333,50.266667],"type":"Point"}
}