{
  "id": 7105052,
  "type": "Feature",
  "properties": {
    "tgn:hierarchy":[
        "tgn:7105052",
        "tgn:7000096",
        "tgn:1000003",
        "tgn:7000084",
        "tgn:7029392"
    ],
    "tgn:id":7105052,
    "tgn:name":"Schiffsruh",
    "tgn:placetype":[
        "aat:300000206"
    ]
},
  "bbox": [],
  "geometry": {"coordinates":[14.266667,52.216667],"type":"Point"}
}