<<<<<<< HEAD
{
  "id": 7350850,
  "type": "Feature",
  "properties": {
    "tgn:hierarchy":[
        "tgn:7350850",
        "tgn:1001853",
        "tgn:1000001",
        "tgn:7005560",
        "tgn:7029392"
    ],
    "tgn:id":7350850,
    "tgn:name":"Baj\u00e1n",
    "tgn:placetype":[
        "aat:300007783"
    ]
},
  "bbox": [],
  "geometry": {"coordinates":[-101.266667,26.533333],"type":"Point"}
}
=======
{"geometry":{"type":"Point","coordinates":[-101.266667,26.533333]},"type":"Feature","properties":{"hierarchy":["tgn:7350850","tgn:1001853","tgn:1000001","tgn:7005560","tgn:7029392"],"placetype":["aat:300007783"],"id":7350850,"name:xx":"Baj\u00e1n"}}
>>>>>>> 03f74aca74312dbeaf24d7e61306dd6a786dc3d0
