<<<<<<< HEAD
{
  "id": 2330036,
  "type": "Feature",
  "properties": {
    "tgn:hierarchy":[
        "tgn:2330036",
        "tgn:1000001",
        "tgn:7012149",
        "tgn:1003038",
        "tgn:7007517",
        "tgn:7029392"
    ],
    "tgn:id":2330036,
    "tgn:name":"Flagg Hill",
    "tgn:placetype":[
        "aat:300008798"
    ]
},
  "bbox": [],
  "geometry": {"coordinates":[-71.8667,42.4333],"type":"Point"}
}
=======
{"geometry":{"type":"Point","coordinates":[-71.866700,42.433300]},"type":"Feature","properties":{"hierarchy":["tgn:2330036","tgn:1000001","tgn:7012149","tgn:1003038","tgn:7007517","tgn:7029392"],"placetype":["aat:300008798"],"id":2330036,"name:xx":"Flagg Hill"}}
>>>>>>> 03f74aca74312dbeaf24d7e61306dd6a786dc3d0
