{
  "id": 1086862,
  "type": "Feature",
  "properties": {
    "tgn:hierarchy":[
        "tgn:1086862",
        "tgn:1001410",
        "tgn:1000004",
        "tgn:7018451",
        "tgn:1000144",
        "tgn:7029392"
    ],
    "tgn:id":1086862,
    "tgn:name":"Saruhanli",
    "tgn:placetype":[
        "aat:300008347"
    ]
},
  "bbox": [],
  "geometry": {"coordinates":[27.5667,38.7333],"type":"Point"}
}