{
  "id": 2742608,
  "type": "Feature",
  "properties": {
    "tgn:hierarchy":[
        "tgn:2742608",
        "tgn:1000001",
        "tgn:7012149",
        "tgn:2000225",
        "tgn:7007158",
        "tgn:7029392"
    ],
    "tgn:id":2742608,
    "tgn:name":"Valley View Spring",
    "tgn:placetype":[
        "aat:300008697"
    ]
},
  "bbox": [],
  "geometry": {"coordinates":[-108.15,37.35],"type":"Point"}
}