{
  "id": 2386916,
  "type": "Feature",
  "properties": {
    "tgn:hierarchy":[
        "tgn:2386916",
        "tgn:1000001",
        "tgn:7012149",
        "tgn:2002384",
        "tgn:7007923",
        "tgn:7029392"
    ],
    "tgn:id":2386916,
    "tgn:name":"Heron Pond",
    "tgn:placetype":[
        "aat:300008680"
    ]
},
  "bbox": [],
  "geometry": {"coordinates":[-110.6333,43.8833],"type":"Point"}
}