{
  "id": 2506899,
  "type": "Feature",
  "properties": {
    "tgn:hierarchy":[
        "tgn:2506899",
        "tgn:1000001",
        "tgn:7012149",
        "tgn:2002068",
        "tgn:7007826",
        "tgn:7029392"
    ],
    "tgn:id":2506899,
    "tgn:name":"Mesquite Island",
    "tgn:placetype":[
        "aat:300008791"
    ]
},
  "bbox": [],
  "geometry": {"coordinates":[-97.8833,28.0667],"type":"Point"}
}