{
  "id": 2230097,
  "type": "Feature",
  "properties": {
    "tgn:hierarchy":[
        "tgn:2230097",
        "tgn:1000001",
        "tgn:7012149",
        "tgn:2001284",
        "tgn:7007524",
        "tgn:7029392"
    ],
    "tgn:id":2230097,
    "tgn:name":"Cellar Gulch",
    "tgn:placetype":[
        "aat:300008761"
    ]
},
  "bbox": [],
  "geometry": {"coordinates":[-112.45,46.8167],"type":"Point"}
}