{
  "id": 2288987,
  "type": "Feature",
  "properties": {
    "tgn:hierarchy":[
        "tgn:2288987",
        "tgn:1000001",
        "tgn:7012149",
        "tgn:2000238",
        "tgn:7007158",
        "tgn:7029392"
    ],
    "tgn:id":2288987,
    "tgn:name":"Dittemore Gulch",
    "tgn:placetype":[
        "aat:300008761"
    ]
},
  "bbox": [],
  "geometry": {"coordinates":[-105.4167,38.95],"type":"Point"}
}