<<<<<<< HEAD
{
  "id": 2159091,
  "type": "Feature",
  "properties": {
    "tgn:hierarchy":[
        "tgn:2159091",
        "tgn:1000001",
        "tgn:7012149",
        "tgn:2000933",
        "tgn:7007515",
        "tgn:7029392"
    ],
    "tgn:id":2159091,
    "tgn:name":"Bedell Crossing",
    "tgn:placetype":[
        "aat:300008347"
    ]
},
  "bbox": [],
  "geometry": {"coordinates":[-70.6667,43.1],"type":"Point"}
}
=======
{"geometry":{"type":"Point","coordinates":[-70.666700,43.100000]},"type":"Feature","properties":{"hierarchy":["tgn:2159091","tgn:1000001","tgn:7012149","tgn:2000933","tgn:7007515","tgn:7029392"],"placetype":["aat:300008347"],"id":2159091,"name:xx":"Bedell Crossing"}}
>>>>>>> 03f74aca74312dbeaf24d7e61306dd6a786dc3d0
