{
  "id": 1075121,
  "type": "Feature",
  "properties": {
    "tgn:hierarchy":[
        "tgn:1075121",
        "tgn:1000004",
        "tgn:7000198",
        "tgn:7016722",
        "tgn:7029392"
    ],
    "tgn:id":1075121,
    "tgn:name:en":"Deoband",
    "tgn:placetype":[
        "aat:300008347"
    ]
},
  "bbox": [],
  "geometry": {"coordinates":[77.67778,29.692912],"type":"Point"}
}