{
  "id": 2234339,
  "type": "Feature",
  "properties": {
    "tgn:hierarchy":[
        "tgn:2234339",
        "tgn:1000001",
        "tgn:7012149",
        "tgn:2000902",
        "tgn:7007256",
        "tgn:7029392"
    ],
    "tgn:id":2234339,
    "tgn:name":"Chenevert, Bayou",
    "tgn:placetype":[
        "aat:300008699"
    ]
},
  "bbox": [],
  "geometry": {"coordinates":[-91.8333,30.4667],"type":"Point"}
}