{
  "id": 2536206,
  "type": "Feature",
  "properties": {
    "tgn:hierarchy":[
        "tgn:2536206",
        "tgn:1000001",
        "tgn:7012149",
        "tgn:2001449",
        "tgn:7007566",
        "tgn:7029392"
    ],
    "tgn:id":2536206,
    "tgn:name":"Navajo Canyon",
    "tgn:placetype":[
        "aat:300008761"
    ]
},
  "bbox": [],
  "geometry": {"coordinates":[-106.4833,36.4167],"type":"Point"}
}