<<<<<<< HEAD
{
  "id": 2330388,
  "type": "Feature",
  "properties": {
    "tgn:hierarchy":[
        "tgn:2330388",
        "tgn:1000001",
        "tgn:7012149",
        "tgn:2001867",
        "tgn:7007825",
        "tgn:7029392"
    ],
    "tgn:id":2330388,
    "tgn:name":"Flat Branch",
    "tgn:placetype":[
        "aat:300008347"
    ]
},
  "bbox": [],
  "geometry": {"coordinates":[-85.7,35.3],"type":"Point"}
}
=======
{"geometry":{"type":"Point","coordinates":[-85.700000,35.300000]},"type":"Feature","properties":{"hierarchy":["tgn:2330388","tgn:1000001","tgn:7012149","tgn:2001867","tgn:7007825","tgn:7029392"],"placetype":["aat:300008347"],"id":2330388,"name:xx":"Flat Branch"}}
>>>>>>> 03f74aca74312dbeaf24d7e61306dd6a786dc3d0
