{
  "id": 2070114,
  "type": "Feature",
  "properties": {
    "tgn:hierarchy":[
        "tgn:2070114",
        "tgn:1000001",
        "tgn:7012149",
        "tgn:7014612",
        "tgn:7007568",
        "tgn:7029392"
    ],
    "tgn:id":2070114,
    "tgn:name":"Lake Purdy",
    "tgn:placetype":[
        "aat:300008347"
    ]
},
  "bbox": [],
  "geometry": {"coordinates":[-73.6667,41.3167],"type":"Point"}
}