{
  "id": 2191555,
  "type": "Feature",
  "properties": {
    "tgn:hierarchy":[
        "tgn:2191555",
        "tgn:1000001",
        "tgn:7012149",
        "tgn:7007157",
        "tgn:7014516",
        "tgn:7029392"
    ],
    "tgn:id":2191555,
    "tgn:name":"Bradford Mountain",
    "tgn:placetype":[
        "aat:300008798"
    ]
},
  "bbox": [],
  "geometry": {"coordinates":[-122.9667,38.6833],"type":"Point"}
}