{
  "id": 2661719,
  "type": "Feature",
  "properties": {
    "tgn:hierarchy":[
        "tgn:2661719",
        "tgn:1000001",
        "tgn:7012149",
        "tgn:1002816",
        "tgn:7007826",
        "tgn:7029392"
    ],
    "tgn:id":2661719,
    "tgn:name":"Shuffle Creek",
    "tgn:placetype":[
        "aat:300008706"
    ]
},
  "bbox": [],
  "geometry": {"coordinates":[-95.8667,32.9167],"type":"Point"}
}