{
  "id": 2228635,
  "type": "Feature",
  "properties": {
    "tgn:hierarchy":[
        "tgn:2228635",
        "tgn:1002338",
        "tgn:1000001",
        "tgn:7012149",
        "tgn:7007516",
        "tgn:7029392"
    ],
    "tgn:id":2228635,
    "tgn:name":"Cedar Creek Marsh",
    "tgn:placetype":[
        "aat:300008905"
    ]
},
  "bbox": [],
  "geometry": {"coordinates":[-76.05,38.3167],"type":"Point"}
}