{
  "id": 4005009,
  "type": "Feature",
  "properties": {
    "tgn:hierarchy":[
        "tgn:4005009",
        "tgn:7019053",
        "tgn:7002445",
        "tgn:1000003",
        "tgn:7029505",
        "tgn:7008591",
        "tgn:7029392"
    ],
    "tgn:id":4005009,
    "tgn:name":"Hickleton",
    "tgn:placetype":[
        "aat:300008347",
        "aat:300008372"
    ]
},
  "bbox": [],
  "geometry": {"coordinates":[-1.283333,53.533333],"type":"Point"}
}