{
  "id": 2541887,
  "type": "Feature",
  "properties": {
    "tgn:hierarchy":[
        "tgn:2541887",
        "tgn:1002300",
        "tgn:1000001",
        "tgn:7012149",
        "tgn:7007564",
        "tgn:7029392"
    ],
    "tgn:id":2541887,
    "tgn:name":"Nineteen Brook",
    "tgn:placetype":[
        "aat:300008699"
    ]
},
  "bbox": [],
  "geometry": {"coordinates":[-71.1833,44.25],"type":"Point"}
}