{
  "id": 7041167,
  "type": "Feature",
  "properties": {
    "tgn:hierarchy":[
        "tgn:7041167",
        "tgn:7003006",
        "tgn:1000003",
        "tgn:7002997",
        "tgn:1000080",
        "tgn:7029392"
    ],
    "tgn:id":7041167,
    "tgn:name":"Forte San Pietro",
    "tgn:placetype":[
        "aat:300006909"
    ]
},
  "bbox": [],
  "geometry": {"coordinates":[12.316667,45.333333],"type":"Point"}
}