{
  "id": 7141808,
  "type": "Feature",
  "properties": {
    "tgn:hierarchy":[
        "tgn:7141808",
        "tgn:7000096",
        "tgn:1000003",
        "tgn:7000084",
        "tgn:7029392"
    ],
    "tgn:id":7141808,
    "tgn:name":"Louisenhof",
    "tgn:placetype":[
        "aat:300000206"
    ]
},
  "bbox": [],
  "geometry": {"coordinates":[14.333333,52.633333],"type":"Point"}
}