{
  "id": 7209348,
  "type": "Feature",
  "properties": {
    "tgn:hierarchy":[
        "tgn:7209348",
        "tgn:1000003",
        "tgn:7003678",
        "tgn:7000084",
        "tgn:7029392"
    ],
    "tgn:id":7209348,
    "tgn:name":"Bechtewald",
    "tgn:placetype":[
        "aat:300008777"
    ]
},
  "bbox": [],
  "geometry": {"coordinates":[8.266667,50.15],"type":"Point"}
}