{
  "id": 2626758,
  "type": "Feature",
  "properties": {
    "tgn:hierarchy":[
        "tgn:2626758",
        "tgn:1000001",
        "tgn:7012149",
        "tgn:7007157",
        "tgn:2000185",
        "tgn:7029392"
    ],
    "tgn:id":2626758,
    "tgn:name":"Rocky Point",
    "tgn:placetype":[
        "aat:300008798"
    ]
},
  "bbox": [],
  "geometry": {"coordinates":[-123.0833,39.4667],"type":"Point"}
}