{
  "id": 7321891,
  "type": "Feature",
  "properties": {
    "tgn:hierarchy":[
        "tgn:7321891",
        "tgn:1001702",
        "tgn:1000049",
        "tgn:1000002",
        "tgn:7029392"
    ],
    "tgn:id":7321891,
    "tgn:name":"Estancia Caleta Josefina",
    "tgn:placetype":[
        "aat:300000241"
    ]
},
  "bbox": [],
  "geometry": {"coordinates":[-69.283333,-53.383333],"type":"Point"}
}