<<<<<<< HEAD
{
  "id": 7357436,
  "type": "Feature",
  "properties": {
    "tgn:hierarchy":[
        "tgn:7357436",
        "tgn:7005581",
        "tgn:1000001",
        "tgn:7005560",
        "tgn:7029392"
    ],
    "tgn:id":7357436,
    "tgn:name":"Ejido El Rancho del Alamo",
    "tgn:placetype":[
        "aat:300008347"
    ]
},
  "bbox": [],
  "geometry": {"coordinates":[-105.833333,26.916667],"type":"Point"}
}
=======
{"geometry":{"type":"Point","coordinates":[-105.833333,26.916667]},"type":"Feature","properties":{"hierarchy":["tgn:7357436","tgn:7005581","tgn:1000001","tgn:7005560","tgn:7029392"],"placetype":["aat:300008347"],"id":7357436,"name:xx":"Ejido El Rancho del Alamo"}}
>>>>>>> 03f74aca74312dbeaf24d7e61306dd6a786dc3d0
