<<<<<<< HEAD
{
  "id": 2764823,
  "type": "Feature",
  "properties": {
    "tgn:hierarchy":[
        "tgn:2764823",
        "tgn:1000001",
        "tgn:7012149",
        "tgn:1002296",
        "tgn:7007157",
        "tgn:7029392"
    ],
    "tgn:id":2764823,
    "tgn:name":"Whiskey Hill",
    "tgn:placetype":[
        "aat:300008798"
    ]
},
  "bbox": [],
  "geometry": {"coordinates":[-122.3333,39.05],"type":"Point"}
}
=======
{"geometry":{"type":"Point","coordinates":[-122.333300,39.050000]},"type":"Feature","properties":{"hierarchy":["tgn:2764823","tgn:1000001","tgn:7012149","tgn:1002296","tgn:7007157","tgn:7029392"],"placetype":["aat:300008798"],"id":2764823,"name:xx":"Whiskey Hill"}}
>>>>>>> 03f74aca74312dbeaf24d7e61306dd6a786dc3d0
