{
  "id": 2764823,
  "type": "Feature",
  "properties": {
    "tgn:hierarchy":[
        "tgn:2764823",
        "tgn:1000001",
        "tgn:7012149",
        "tgn:1002296",
        "tgn:7007157",
        "tgn:7029392"
    ],
    "tgn:id":2764823,
    "tgn:name":"Whiskey Hill",
    "tgn:placetype":[
        "aat:300008798"
    ]
},
  "bbox": [],
  "geometry": {"coordinates":[-122.3333,39.05],"type":"Point"}
}