<<<<<<< HEAD
{
  "id": 2339283,
  "type": "Feature",
  "properties": {
    "tgn:hierarchy":[
        "tgn:2339283",
        "tgn:1000001",
        "tgn:7012149",
        "tgn:2001036",
        "tgn:7007521",
        "tgn:7029392"
    ],
    "tgn:id":2339283,
    "tgn:name":"Fraser Lake",
    "tgn:placetype":[
        "aat:300008680"
    ]
},
  "bbox": [],
  "geometry": {"coordinates":[-91.1833,48.0],"type":"Point"}
}
=======
{"geometry":{"type":"Point","coordinates":[-91.183300,48.000000]},"type":"Feature","properties":{"hierarchy":["tgn:2339283","tgn:1000001","tgn:7012149","tgn:2001036","tgn:7007521","tgn:7029392"],"placetype":["aat:300008680"],"id":2339283,"name:xx":"Fraser Lake"}}
>>>>>>> 03f74aca74312dbeaf24d7e61306dd6a786dc3d0
