{
  "id": 2655571,
  "type": "Feature",
  "properties": {
    "tgn:hierarchy":[
        "tgn:2655571",
        "tgn:1000001",
        "tgn:2000313",
        "tgn:7012149",
        "tgn:7007248",
        "tgn:7029392"
    ],
    "tgn:id":2655571,
    "tgn:name":"Sharpe Creek",
    "tgn:placetype":[
        "aat:300008706"
    ]
},
  "bbox": [],
  "geometry": {"coordinates":[-85.0833,33.6667],"type":"Point"}
}