{
  "id": 2769157,
  "type": "Feature",
  "properties": {
    "tgn:hierarchy":[
        "tgn:2769157",
        "tgn:7002659",
        "tgn:1000001",
        "tgn:7012149",
        "tgn:2000060",
        "tgn:7029392"
    ],
    "tgn:id":2769157,
    "tgn:name":"Whitwood, Lake",
    "tgn:placetype":[
        "aat:300006191"
    ]
},
  "bbox": [],
  "geometry": {"coordinates":[-86.0333,33.5167],"type":"Point"}
}