<<<<<<< HEAD
{
  "id": 7376756,
  "type": "Feature",
  "properties": {
    "tgn:hierarchy":[
        "tgn:7376756",
        "tgn:1000001",
        "tgn:7005597",
        "tgn:7005560",
        "tgn:7029392"
    ],
    "tgn:id":7376756,
    "tgn:name":"Las Aguapas",
    "tgn:placetype":[
        "aat:300008347"
    ]
},
  "bbox": [],
  "geometry": {"coordinates":[-98.85,26.1],"type":"Point"}
}
=======
{"geometry":{"type":"Point","coordinates":[-98.850000,26.100000]},"type":"Feature","properties":{"hierarchy":["tgn:7376756","tgn:1000001","tgn:7005597","tgn:7005560","tgn:7029392"],"placetype":["aat:300008347"],"id":7376756,"name:xx":"Las Aguapas"}}
>>>>>>> 03f74aca74312dbeaf24d7e61306dd6a786dc3d0
