{
  "id": 2358998,
  "type": "Feature",
  "properties": {
    "tgn:hierarchy":[
        "tgn:2358998",
        "tgn:1000001",
        "tgn:7006451",
        "tgn:7012149",
        "tgn:2000101",
        "tgn:7029392"
    ],
    "tgn:id":2358998,
    "tgn:name":"Granite Knob",
    "tgn:placetype":[
        "aat:300008798"
    ]
},
  "bbox": [],
  "geometry": {"coordinates":[-111.6333,33.0667],"type":"Point"}
}