{
  "id": 7582113,
  "type": "Feature",
  "properties": {
    "tgn:hierarchy":[
        "tgn:7582113",
        "tgn:1000004",
        "tgn:7000198",
        "tgn:1001894",
        "tgn:7029392"
    ],
    "tgn:id":7582113,
    "tgn:name:en":"Bhonra Pah\u0101r",
    "tgn:placetype":[
        "aat:300008795"
    ]
},
  "bbox": [],
  "geometry": {"coordinates":[78.914729,24.222051],"type":"Point"}
}