{
  "id": 7262042,
  "type": "Feature",
  "properties": {
    "tgn:hierarchy":[
        "tgn:7262042",
        "tgn:1000003",
        "tgn:7003627",
        "tgn:7016845",
        "tgn:7029392"
    ],
    "tgn:id":7262042,
    "tgn:name:nl":"Gelderse Vallei",
    "tgn:placetype":[
        "aat:300387346"
    ]
},
  "bbox": [],
  "geometry": {"coordinates":[5.433333,52.166667],"type":"Point"}
}