{
  "id": 2090179,
  "type": "Feature",
  "properties": {
    "tgn:hierarchy":[
        "tgn:2090179",
        "tgn:1000001",
        "tgn:1002185",
        "tgn:7012149",
        "tgn:7007710",
        "tgn:7029392"
    ],
    "tgn:id":2090179,
    "tgn:name":"Linds Crossing",
    "tgn:placetype":[
        "aat:300008347",
        "aat:300387210"
    ]
},
  "bbox": [],
  "geometry": {"coordinates":[-78.3167,40.4333],"type":"Point"}
}