{
  "id": 7169367,
  "type": "Feature",
  "properties": {
    "tgn:hierarchy":[
        "tgn:7169367",
        "tgn:1000003",
        "tgn:7000094",
        "tgn:7000084",
        "tgn:7029392"
    ],
    "tgn:id":7169367,
    "tgn:name":"Hermannshof",
    "tgn:placetype":[
        "aat:300000206"
    ]
},
  "bbox": [],
  "geometry": {"coordinates":[13.583333,53.483333],"type":"Point"}
}