{
  "id": 7317433,
  "type": "Feature",
  "properties": {
    "tgn:hierarchy":[
        "tgn:7317433",
        "tgn:1001630",
        "tgn:1000049",
        "tgn:1000002",
        "tgn:7029392"
    ],
    "tgn:id":7317433,
    "tgn:name":"Conalillo, Quebrada de",
    "tgn:placetype":[
        "aat:300266554",
        "aat:300008699"
    ]
},
  "bbox": [],
  "geometry": {"coordinates":[-70.316667,-27.133333],"type":"Point"}
}