{
  "id": 7143042,
  "type": "Feature",
  "properties": {
    "tgn:hierarchy":[
        "tgn:7143042",
        "tgn:7000096",
        "tgn:1000003",
        "tgn:7000084",
        "tgn:7029392"
    ],
    "tgn:id":7143042,
    "tgn:name":"Linden-Berg",
    "tgn:placetype":[
        "aat:300008777"
    ]
},
  "bbox": [],
  "geometry": {"coordinates":[11.783333,53.116667],"type":"Point"}
}