{
  "id": 7303003,
  "type": "Feature",
  "properties": {
    "tgn:hierarchy":[
        "tgn:7303003",
        "tgn:7002825",
        "tgn:7016622",
        "tgn:1000003",
        "tgn:1000095",
        "tgn:7029392"
    ],
    "tgn:id":7303003,
    "tgn:name":"Mujeres, Playa",
    "tgn:placetype":[
        "aat:300008816"
    ]
},
  "bbox": [],
  "geometry": {"coordinates":[-13.783333,28.833333],"type":"Point"}
}