{
  "id": 7513074,
  "type": "Feature",
  "properties": {
    "tgn:hierarchy":[
        "tgn:7513074",
        "tgn:1009227",
        "tgn:1000226",
        "tgn:7016822",
        "tgn:1000006",
        "tgn:7029392"
    ],
    "tgn:id":7513074,
    "tgn:name:en":"Halls Arm",
    "tgn:placetype":[
        "aat:300132316"
    ]
},
  "bbox": [],
  "geometry": {"coordinates":[167.116667,-45.45],"type":"Point"}
}