<<<<<<< HEAD
{
  "id": 2251133,
  "type": "Feature",
  "properties": {
    "tgn:hierarchy":[
        "tgn:2251133",
        "tgn:1000001",
        "tgn:7012149",
        "tgn:2000996",
        "tgn:7007520",
        "tgn:7029392"
    ],
    "tgn:id":2251133,
    "tgn:name":"Colwell Lake",
    "tgn:placetype":[
        "aat:300008680"
    ]
},
  "bbox": [],
  "geometry": {"coordinates":[-86.4333,46.2167],"type":"Point"}
}
=======
{"geometry":{"type":"Point","coordinates":[-86.433300,46.216700]},"type":"Feature","properties":{"hierarchy":["tgn:2251133","tgn:1000001","tgn:7012149","tgn:2000996","tgn:7007520","tgn:7029392"],"placetype":["aat:300008680"],"id":2251133,"name:xx":"Colwell Lake"}}
>>>>>>> 03f74aca74312dbeaf24d7e61306dd6a786dc3d0
