{
  "id": 2221810,
  "type": "Feature",
  "properties": {
    "tgn:hierarchy":[
        "tgn:2221810",
        "tgn:7006450",
        "tgn:1000001",
        "tgn:7012149",
        "tgn:2000086",
        "tgn:7029392"
    ],
    "tgn:id":2221810,
    "tgn:name":"Carlson Lake",
    "tgn:placetype":[
        "aat:300008680"
    ]
},
  "bbox": [],
  "geometry": {"coordinates":[-143.85,62.75],"type":"Point"}
}