{
  "id": 7389370,
  "type": "Feature",
  "properties": {
    "tgn:hierarchy":[
        "tgn:7389370",
        "tgn:1000001",
        "tgn:1001960",
        "tgn:7005560",
        "tgn:7029392"
    ],
    "tgn:id":7389370,
    "tgn:name":"Rancho El Represito",
    "tgn:placetype":[
        "aat:300008347"
    ]
},
  "bbox": [],
  "geometry": {"coordinates":[-111.15,28.933333],"type":"Point"}
}