{
  "id": 2476141,
  "type": "Feature",
  "properties": {
    "tgn:hierarchy":[
        "tgn:2476141",
        "tgn:1000001",
        "tgn:7012149",
        "tgn:2002383",
        "tgn:7007923",
        "tgn:7029392"
    ],
    "tgn:id":2476141,
    "tgn:name":"Luman Butte",
    "tgn:placetype":[
        "aat:300008798"
    ]
},
  "bbox": [],
  "geometry": {"coordinates":[-108.3667,42.0167],"type":"Point"}
}