{
  "id": 2116445,
  "type": "Feature",
  "properties": {
    "tgn:hierarchy":[
        "tgn:2116445",
        "tgn:1000001",
        "tgn:7012149",
        "tgn:1003042",
        "tgn:7007920",
        "tgn:7029392"
    ],
    "tgn:id":2116445,
    "tgn:name":"Outlook",
    "tgn:placetype":[
        "aat:300008347"
    ]
},
  "bbox": [],
  "geometry": {"coordinates":[-120.0833,46.3167],"type":"Point"}
}