{
  "id": 7059173,
  "type": "Feature",
  "properties": {
    "tgn:hierarchy":[
        "tgn:7059173",
        "tgn:1000004",
        "tgn:7001325",
        "tgn:7000299",
        "tgn:7029392"
    ],
    "tgn:id":7059173,
    "tgn:name":"Pulguk-sa",
    "tgn:placetype":[
        "aat:300007595",
        "aat:300263063"
    ]
},
  "bbox": [],
  "geometry": {"coordinates":[127.067,37.48],"type":"Point"}
}