{
  "id": 2563904,
  "type": "Feature",
  "properties": {
    "tgn:hierarchy":[
        "tgn:2563904",
        "tgn:1000001",
        "tgn:7012149",
        "tgn:2002278",
        "tgn:7013961",
        "tgn:7029392"
    ],
    "tgn:id":2563904,
    "tgn:name":"Oxley Hollow",
    "tgn:placetype":[
        "aat:300008761"
    ]
},
  "bbox": [],
  "geometry": {"coordinates":[-81.0167,37.4167],"type":"Point"}
}