{
  "id": 7348103,
  "type": "Feature",
  "properties": {
    "tgn:hierarchy":[
        "tgn:7348103",
        "tgn:7002759",
        "tgn:7002843",
        "tgn:1000003",
        "tgn:1000095",
        "tgn:7029392"
    ],
    "tgn:id":7348103,
    "tgn:name":"Alac\u00f3n",
    "tgn:placetype":[
        "aat:300008347"
    ]
},
  "bbox": [],
  "geometry": {"coordinates":[-0.683333,41.016667],"type":"Point"}
}