{
  "id": 2279643,
  "type": "Feature",
  "properties": {
    "tgn:hierarchy":[
        "tgn:2279643",
        "tgn:1000001",
        "tgn:7012149",
        "tgn:2001313",
        "tgn:7007524",
        "tgn:7029392"
    ],
    "tgn:id":2279643,
    "tgn:name":"Deadmans Basin Supply Canal",
    "tgn:placetype":[
        "aat:300006075"
    ]
},
  "bbox": [],
  "geometry": {"coordinates":[-109.5333,46.35],"type":"Point"}
}