{
  "id": 7287936,
  "type": "Feature",
  "properties": {
    "tgn:hierarchy":[
        "tgn:7287936",
        "tgn:1001623",
        "tgn:1000049",
        "tgn:1000002",
        "tgn:7029392"
    ],
    "tgn:id":7287936,
    "tgn:name":"Iglesia, Cerro",
    "tgn:placetype":[
        "aat:300008795"
    ]
},
  "bbox": [],
  "geometry": {"coordinates":[-72.283333,-45.816667],"type":"Point"}
}