{
  "id": 2691179,
  "type": "Feature",
  "properties": {
    "tgn:hierarchy":[
        "tgn:2691179",
        "tgn:1000001",
        "tgn:2002370",
        "tgn:7012149",
        "tgn:7007923",
        "tgn:7029392"
    ],
    "tgn:id":2691179,
    "tgn:name":"Stanton Draw",
    "tgn:placetype":[
        "aat:300008761"
    ]
},
  "bbox": [],
  "geometry": {"coordinates":[-104.0833,44.1833],"type":"Point"}
}