{
  "id": 7533736,
  "type": "Feature",
  "properties": {
    "tgn:hierarchy":[
        "tgn:7533736",
        "tgn:7001242",
        "tgn:1001075",
        "tgn:7016833",
        "tgn:7029392"
    ],
    "tgn:id":7533736,
    "tgn:name:en":"Jarw, Tallat al",
    "tgn:placetype":[
        "aat:300008777"
    ]
},
  "bbox": [],
  "geometry": {"coordinates":[30.213611,30.606111],"type":"Point"}
}