{
  "id": 7475107,
  "type": "Feature",
  "properties": {
    "tgn:hierarchy":[
        "tgn:7475107",
        "tgn:1000004",
        "tgn:7001014",
        "tgn:1000141",
        "tgn:7029392"
    ],
    "tgn:id":7475107,
    "tgn:name":"Dazhuang Sanhao Tifang",
    "tgn:placetype":[
        "aat:300006156"
    ]
},
  "bbox": [],
  "geometry": {"coordinates":[120.352625,23.815128],"type":"Point"}
}