{
  "id": 2453262,
  "type": "Feature",
  "properties": {
    "tgn:hierarchy":[
        "tgn:2453262",
        "tgn:1000001",
        "tgn:7012149",
        "tgn:2002362",
        "tgn:7007922",
        "tgn:7029392"
    ],
    "tgn:id":2453262,
    "tgn:name":"Little Cedar Lake",
    "tgn:placetype":[
        "aat:300008680"
    ]
},
  "bbox": [],
  "geometry": {"coordinates":[-89.0833,44.2167],"type":"Point"}
}