{
  "id": 2714382,
  "type": "Feature",
  "properties": {
    "tgn:hierarchy":[
        "tgn:2714382",
        "tgn:1000001",
        "tgn:7012149",
        "tgn:2001285",
        "tgn:7007524",
        "tgn:7029392"
    ],
    "tgn:id":2714382,
    "tgn:name":"Temple  Reservoir",
    "tgn:placetype":[
        "aat:300006191"
    ]
},
  "bbox": [],
  "geometry": {"coordinates":[-110.85,48.8167],"type":"Point"}
}