{
  "id": 7362501,
  "type": "Feature",
  "properties": {
    "tgn:hierarchy":[
        "tgn:7362501",
        "tgn:7005581",
        "tgn:1000001",
        "tgn:7005560",
        "tgn:7029392"
    ],
    "tgn:id":7362501,
    "tgn:name":"El Pastor",
    "tgn:placetype":[
        "aat:300008347"
    ]
},
  "bbox": [],
  "geometry": {"coordinates":[-105.316667,29.266667],"type":"Point"}
}