{
  "id": 2490542,
  "type": "Feature",
  "properties": {
    "tgn:hierarchy":[
        "tgn:2490542",
        "tgn:1000001",
        "tgn:1002395",
        "tgn:7012149",
        "tgn:7007251",
        "tgn:7029392"
    ],
    "tgn:id":2490542,
    "tgn:name":"Manley",
    "tgn:placetype":[
        "aat:300008347"
    ]
},
  "bbox": [],
  "geometry": {"coordinates":[-90.4167,40.5833],"type":"Point"}
}