{
  "id": 1018699,
  "type": "Feature",
  "properties": {
    "tgn:hierarchy":[
        "tgn:1018699",
        "tgn:7593113",
        "tgn:7016620",
        "tgn:7593112",
        "tgn:1000001",
        "tgn:7029392"
    ],
    "tgn:id":1018699,
    "tgn:name":"Rinc\u00f3n",
    "tgn:placetype":[
        "aat:300008347"
    ]
},
  "bbox": [],
  "geometry": {"coordinates":[-68.3333,12.2333],"type":"Point"}
}