<<<<<<< HEAD
{
  "id": 2256693,
  "type": "Feature",
  "properties": {
    "tgn:hierarchy":[
        "tgn:2256693",
        "tgn:1000001",
        "tgn:7012149",
        "tgn:2001449",
        "tgn:7007566",
        "tgn:7029392"
    ],
    "tgn:id":2256693,
    "tgn:name":"Cordovas Spring",
    "tgn:placetype":[
        "aat:300008697"
    ]
},
  "bbox": [],
  "geometry": {"coordinates":[-106.7333,36.15],"type":"Point"}
}
=======
{"geometry":{"type":"Point","coordinates":[-106.733300,36.150000]},"type":"Feature","properties":{"hierarchy":["tgn:2256693","tgn:1000001","tgn:7012149","tgn:2001449","tgn:7007566","tgn:7029392"],"placetype":["aat:300008697"],"id":2256693,"name:xx":"Cordovas Spring"}}
>>>>>>> 03f74aca74312dbeaf24d7e61306dd6a786dc3d0
