{
  "id": 2463365,
  "type": "Feature",
  "properties": {
    "tgn:hierarchy":[
        "tgn:2463365",
        "tgn:1000001",
        "tgn:7012149",
        "tgn:2001987",
        "tgn:7007826",
        "tgn:7029392"
    ],
    "tgn:id":2463365,
    "tgn:name":"Llave Tank",
    "tgn:placetype":[
        "aat:300006191"
    ]
},
  "bbox": [],
  "geometry": {"coordinates":[-99.25,28.8833],"type":"Point"}
}