{
  "id": 2325925,
  "type": "Feature",
  "properties": {
    "tgn:hierarchy":[
        "tgn:2325925",
        "tgn:1000001",
        "tgn:7012149",
        "tgn:7007520",
        "tgn:7029392"
    ],
    "tgn:id":2325925,
    "tgn:name":"Fifield Creek",
    "tgn:placetype":[
        "aat:300008706"
    ]
},
  "bbox": [],
  "geometry": {"coordinates":[-84.7667,43.1333],"type":"Point"}
}