{
  "id": 1032641,
  "type": "Feature",
  "properties": {
    "tgn:hierarchy":[
        "tgn:1032641",
        "tgn:1000003",
        "tgn:7002883",
        "tgn:1000070",
        "tgn:7029392"
    ],
    "tgn:id":1032641,
    "tgn:name":"Chauvry",
    "tgn:placetype":[
        "aat:300008347"
    ]
},
  "bbox": [],
  "geometry": {"coordinates":[2.2667,49.05],"type":"Point"}
}