{
  "id": 1028387,
  "type": "Feature",
  "properties": {
    "tgn:hierarchy":[
        "tgn:1028387",
        "tgn:7002445",
        "tgn:1000003",
        "tgn:7008154",
        "tgn:7008591",
        "tgn:7029392"
    ],
    "tgn:id":1028387,
    "tgn:name:en":"Balderstone",
    "tgn:placetype":[
        "aat:300008347"
    ]
},
  "bbox": [],
  "geometry": {"coordinates":[-2.566667,53.783333],"type":"Point"}
}