{
  "id": 7403591,
  "type": "Feature",
  "properties": {
    "tgn:hierarchy":[
        "tgn:7403591",
        "tgn:1000001",
        "tgn:1001906",
        "tgn:7005560",
        "tgn:7029392"
    ],
    "tgn:id":7403591,
    "tgn:name":"Palmilla, Arroyo",
    "tgn:placetype":[
        "aat:300008699"
    ]
},
  "bbox": [],
  "geometry": {"coordinates":[-104.441667,21.425],"type":"Point"}
}