<<<<<<< HEAD
{
  "id": 2765553,
  "type": "Feature",
  "properties": {
    "tgn:hierarchy":[
        "tgn:2765553",
        "tgn:1000001",
        "tgn:7012149",
        "tgn:2000476",
        "tgn:7007250",
        "tgn:7029392"
    ],
    "tgn:id":2765553,
    "tgn:name":"White Cap Lakes",
    "tgn:placetype":[
        "aat:300008680"
    ]
},
  "bbox": [],
  "geometry": {"coordinates":[-114.45,45.9167],"type":"Point"}
}
=======
{"geometry":{"type":"Point","coordinates":[-114.450000,45.916700]},"type":"Feature","properties":{"hierarchy":["tgn:2765553","tgn:1000001","tgn:7012149","tgn:2000476","tgn:7007250","tgn:7029392"],"placetype":["aat:300008680"],"id":2765553,"name:xx":"White Cap Lakes"}}
>>>>>>> 03f74aca74312dbeaf24d7e61306dd6a786dc3d0
