{
  "id": 7428914,
  "type": "Feature",
  "properties": {
    "tgn:hierarchy":[
        "tgn:7428914",
        "tgn:7005586",
        "tgn:1000001",
        "tgn:7005560",
        "tgn:7029392"
    ],
    "tgn:id":7428914,
    "tgn:name":"Achimeque",
    "tgn:placetype":[
        "aat:300008347"
    ]
},
  "bbox": [],
  "geometry": {"coordinates":[-103.233333,22.383333],"type":"Point"}
}