{
  "id": 2321839,
  "type": "Feature",
  "properties": {
    "tgn:hierarchy":[
        "tgn:2321839",
        "tgn:1000001",
        "tgn:1002289",
        "tgn:7012149",
        "tgn:7007240",
        "tgn:7029392"
    ],
    "tgn:id":2321839,
    "tgn:name":"Fakahatchee",
    "tgn:placetype":[
        "aat:300008347"
    ]
},
  "bbox": [],
  "geometry": {"coordinates":[-81.4833,25.8667],"type":"Point"}
}