{
  "id": 2096033,
  "type": "Feature",
  "properties": {
    "tgn:hierarchy":[
        "tgn:2096033",
        "tgn:1000001",
        "tgn:2001746",
        "tgn:7012149",
        "tgn:7007712",
        "tgn:7029392"
    ],
    "tgn:id":2096033,
    "tgn:name":"Italy",
    "tgn:placetype":[
        "aat:300008347"
    ]
},
  "bbox": [],
  "geometry": {"coordinates":[-79.5333,33.4333],"type":"Point"}
}