<<<<<<< HEAD
{
  "id": 7364990,
  "type": "Feature",
  "properties": {
    "tgn:hierarchy":[
        "tgn:7364990",
        "tgn:1000001",
        "tgn:1001906",
        "tgn:7005560",
        "tgn:7029392"
    ],
    "tgn:id":7364990,
    "tgn:name":"El Quelite",
    "tgn:placetype":[
        "aat:300387007"
    ]
},
  "bbox": [],
  "geometry": {"coordinates":[-105.166667,22.616667],"type":"Point"}
}
=======
{"geometry":{"type":"Point","coordinates":[-105.166667,22.616667]},"type":"Feature","properties":{"hierarchy":["tgn:7364990","tgn:1000001","tgn:1001906","tgn:7005560","tgn:7029392"],"placetype":["aat:300387007"],"id":7364990,"name:xx":"El Quelite"}}
>>>>>>> 03f74aca74312dbeaf24d7e61306dd6a786dc3d0
