{
  "id": 7364990,
  "type": "Feature",
  "properties": {
    "tgn:hierarchy":[
        "tgn:7364990",
        "tgn:1000001",
        "tgn:1001906",
        "tgn:7005560",
        "tgn:7029392"
    ],
    "tgn:id":7364990,
    "tgn:name":"El Quelite",
    "tgn:placetype":[
        "aat:300387007"
    ]
},
  "bbox": [],
  "geometry": {"coordinates":[-105.166667,22.616667],"type":"Point"}
}