{
  "id": 7040777,
  "type": "Feature",
  "properties": {
    "tgn:hierarchy":[
        "tgn:7040777",
        "tgn:7003170",
        "tgn:1000003",
        "tgn:7003125",
        "tgn:1000080",
        "tgn:7029392"
    ],
    "tgn:id":7040777,
    "tgn:name":"Santa Maria in Valle",
    "tgn:placetype":[
        "aat:300008347"
    ]
},
  "bbox": [],
  "geometry": {"coordinates":[12.75,42.883333],"type":"Point"}
}