{
  "id": 2729724,
  "type": "Feature",
  "properties": {
    "tgn:hierarchy":[
        "tgn:2729724",
        "tgn:1000001",
        "tgn:7012149",
        "tgn:2000476",
        "tgn:7007250",
        "tgn:7029392"
    ],
    "tgn:id":2729724,
    "tgn:name":"Trough Creek",
    "tgn:placetype":[
        "aat:300008706"
    ]
},
  "bbox": [],
  "geometry": {"coordinates":[-116.05,45.6333],"type":"Point"}
}