{
  "id": 2157888,
  "type": "Feature",
  "properties": {
    "tgn:hierarchy":[
        "tgn:2157888",
        "tgn:1000001",
        "tgn:7012149",
        "tgn:2001717",
        "tgn:7007708",
        "tgn:7029392"
    ],
    "tgn:id":2157888,
    "tgn:name":"Beaver Lake",
    "tgn:placetype":[
        "aat:300008680"
    ]
},
  "bbox": [],
  "geometry": {"coordinates":[-123.1667,44.55],"type":"Point"}
}