{
  "id": 7149898,
  "type": "Feature",
  "properties": {
    "tgn:hierarchy":[
        "tgn:7149898",
        "tgn:1000003",
        "tgn:7003677",
        "tgn:7000084",
        "tgn:7029392"
    ],
    "tgn:id":7149898,
    "tgn:name":"Krauseholz",
    "tgn:placetype":[
        "aat:300000206"
    ]
},
  "bbox": [],
  "geometry": {"coordinates":[8.466667,51.266667],"type":"Point"}
}