{
  "id": 7355876,
  "type": "Feature",
  "properties": {
    "tgn:hierarchy":[
        "tgn:7355876",
        "tgn:1000001",
        "tgn:7005599",
        "tgn:7005560",
        "tgn:7029392"
    ],
    "tgn:id":7355876,
    "tgn:name":"Chicozapote",
    "tgn:placetype":[
        "aat:300008347"
    ]
},
  "bbox": [],
  "geometry": {"coordinates":[-95.25,17.733333],"type":"Point"}
}