<<<<<<< HEAD
{
  "id": 2765732,
  "type": "Feature",
  "properties": {
    "tgn:hierarchy":[
        "tgn:2765732",
        "tgn:1000001",
        "tgn:7012149",
        "tgn:7014510",
        "tgn:7007920",
        "tgn:7029392"
    ],
    "tgn:id":2765732,
    "tgn:name":"White Creek",
    "tgn:placetype":[
        "aat:300008706"
    ]
},
  "bbox": [],
  "geometry": {"coordinates":[-121.4667,48.3833],"type":"Point"}
}
=======
{"geometry":{"type":"Point","coordinates":[-121.466700,48.383300]},"type":"Feature","properties":{"hierarchy":["tgn:2765732","tgn:1000001","tgn:7012149","tgn:7014510","tgn:7007920","tgn:7029392"],"placetype":["aat:300008706"],"id":2765732,"name:xx":"White Creek"}}
>>>>>>> 03f74aca74312dbeaf24d7e61306dd6a786dc3d0
