{
  "id": 2327117,
  "type": "Feature",
  "properties": {
    "tgn:hierarchy":[
        "tgn:2327117",
        "tgn:2000195",
        "tgn:1000001",
        "tgn:7012149",
        "tgn:7007158",
        "tgn:7029392"
    ],
    "tgn:id":2327117,
    "tgn:name":"First Canyon",
    "tgn:placetype":[
        "aat:300008761"
    ]
},
  "bbox": [],
  "geometry": {"coordinates":[-106.9167,37.15],"type":"Point"}
}