{
  "id": 2395296,
  "type": "Feature",
  "properties": {
    "tgn:hierarchy":[
        "tgn:2395296",
        "tgn:1000001",
        "tgn:1002320",
        "tgn:7012149",
        "tgn:7007252",
        "tgn:7029392"
    ],
    "tgn:id":2395296,
    "tgn:name":"Holiday Lakes",
    "tgn:placetype":[
        "aat:300008680"
    ]
},
  "bbox": [],
  "geometry": {"coordinates":[-85.1167,41.2833],"type":"Point"}
}