{
  "id": 7536062,
  "type": "Feature",
  "properties": {
    "tgn:hierarchy":[
        "tgn:7536062",
        "tgn:7001242",
        "tgn:7016833",
        "tgn:1001418",
        "tgn:7029392"
    ],
    "tgn:id":7536062,
    "tgn:name:en":"Gaw\u00e2mi, Q\u00e2ret el-",
    "tgn:placetype":[
        "aat:300008777"
    ]
},
  "bbox": [],
  "geometry": {"coordinates":[25.393038,30.882216],"type":"Point"}
}