{
  "id": 1027310,
  "type": "Feature",
  "properties": {
    "tgn:hierarchy":[
        "tgn:1027310",
        "tgn:7593922",
        "tgn:1000003",
        "tgn:1001780",
        "tgn:7029392"
    ],
    "tgn:id":1027310,
    "tgn:name":"Kunovice",
    "tgn:placetype":[
        "aat:300008347"
    ]
},
  "bbox": [],
  "geometry": {"coordinates":[17.4667,49.05],"type":"Point"}
}