{
  "id": 7458592,
  "type": "Feature",
  "properties": {
    "tgn:hierarchy":[
        "tgn:7458592",
        "tgn:7002444",
        "tgn:1000003",
        "tgn:7008094",
        "tgn:7008591",
        "tgn:7029392"
    ],
    "tgn:id":7458592,
    "tgn:name:en":"Mingulay, Sound of",
    "tgn:placetype":[
        "aat:300266558"
    ]
},
  "bbox": [],
  "geometry": {"coordinates":[-7.616667,56.833333],"type":"Point"}
}