{
  "id": 2208548,
  "type": "Feature",
  "properties": {
    "tgn:hierarchy":[
        "tgn:2208548",
        "tgn:1000001",
        "tgn:7012149",
        "tgn:7007568",
        "tgn:7029392"
    ],
    "tgn:id":2208548,
    "tgn:name":"Burning Creek",
    "tgn:placetype":[
        "aat:300008706"
    ]
},
  "bbox": [],
  "geometry": {"coordinates":[-75.1333,44.05],"type":"Point"}
}