<<<<<<< HEAD
{
  "id": 2339453,
  "type": "Feature",
  "properties": {
    "tgn:hierarchy":[
        "tgn:2339453",
        "tgn:1000001",
        "tgn:2002103",
        "tgn:7012149",
        "tgn:7007827",
        "tgn:7029392"
    ],
    "tgn:id":2339453,
    "tgn:name":"Frazier Spring",
    "tgn:placetype":[
        "aat:300008697"
    ]
},
  "bbox": [],
  "geometry": {"coordinates":[-111.45,41.5333],"type":"Point"}
}
=======
{"geometry":{"type":"Point","coordinates":[-111.450000,41.533300]},"type":"Feature","properties":{"hierarchy":["tgn:2339453","tgn:1000001","tgn:2002103","tgn:7012149","tgn:7007827","tgn:7029392"],"placetype":["aat:300008697"],"id":2339453,"name:xx":"Frazier Spring"}}
>>>>>>> 03f74aca74312dbeaf24d7e61306dd6a786dc3d0
