{
  "id": 2473620,
  "type": "Feature",
  "properties": {
    "tgn:hierarchy":[
        "tgn:2473620",
        "tgn:2002307",
        "tgn:1000001",
        "tgn:7012149",
        "tgn:7007922",
        "tgn:7029392"
    ],
    "tgn:id":2473620,
    "tgn:name":"Lower Devils Lake",
    "tgn:placetype":[
        "aat:300008680"
    ]
},
  "bbox": [],
  "geometry": {"coordinates":[-91.75,45.6167],"type":"Point"}
}