{
  "id": 7304690,
  "type": "Feature",
  "properties": {
    "tgn:hierarchy":[
        "tgn:7304690",
        "tgn:7002759",
        "tgn:7002845",
        "tgn:1000003",
        "tgn:1000095",
        "tgn:7029392"
    ],
    "tgn:id":7304690,
    "tgn:name":"Lech\u00f3n",
    "tgn:placetype":[
        "aat:300008347"
    ]
},
  "bbox": [],
  "geometry": {"coordinates":[-1.283333,41.083333],"type":"Point"}
}