{
  "id": 7427731,
  "type": "Feature",
  "properties": {
    "tgn:hierarchy":[
        "tgn:7427731",
        "tgn:7005581",
        "tgn:1000001",
        "tgn:7005560",
        "tgn:7029392"
    ],
    "tgn:id":7427731,
    "tgn:name":"La Mesa",
    "tgn:placetype":[
        "aat:300008347"
    ]
},
  "bbox": [],
  "geometry": {"coordinates":[-107.916667,28.066667],"type":"Point"}
}