{
  "id": 2614283,
  "type": "Feature",
  "properties": {
    "tgn:hierarchy":[
        "tgn:2614283",
        "tgn:1000001",
        "tgn:7012149",
        "tgn:2000417",
        "tgn:7007248",
        "tgn:7029392"
    ],
    "tgn:id":2614283,
    "tgn:name":"Regents Lake",
    "tgn:placetype":[
        "aat:300006191"
    ]
},
  "bbox": [],
  "geometry": {"coordinates":[-84.1833,33.2833],"type":"Point"}
}