<<<<<<< HEAD
{
  "id": 2331197,
  "type": "Feature",
  "properties": {
    "tgn:hierarchy":[
        "tgn:2331197",
        "tgn:7006450",
        "tgn:1000001",
        "tgn:7012149",
        "tgn:2000086",
        "tgn:7029392"
    ],
    "tgn:id":2331197,
    "tgn:name":"Flat Top Mountain",
    "tgn:placetype":[
        "aat:300008798"
    ]
},
  "bbox": [],
  "geometry": {"coordinates":[-145.7,62.9333],"type":"Point"}
}
=======
{"geometry":{"type":"Point","coordinates":[-145.700000,62.933300]},"type":"Feature","properties":{"hierarchy":["tgn:2331197","tgn:7006450","tgn:1000001","tgn:7012149","tgn:2000086","tgn:7029392"],"placetype":["aat:300008798"],"id":2331197,"name:xx":"Flat Top Mountain"}}
>>>>>>> 03f74aca74312dbeaf24d7e61306dd6a786dc3d0
