{
  "id": 7455693,
  "type": "Feature",
  "properties": {
    "tgn:hierarchy":[
        "tgn:7455693",
        "tgn:7002444",
        "tgn:1000003",
        "tgn:7008082",
        "tgn:7008591",
        "tgn:7029392"
    ],
    "tgn:id":7455693,
    "tgn:name:en":"Cuilionach, Srath",
    "tgn:placetype":[
        "aat:300008761"
    ]
},
  "bbox": [],
  "geometry": {"coordinates":[-4.666667,57.883333],"type":"Point"}
}