{
  "id": 7576330,
  "type": "Feature",
  "properties": {
    "tgn:hierarchy":[
        "tgn:7576330",
        "tgn:1000004",
        "tgn:1001871",
        "tgn:7000198",
        "tgn:7029392"
    ],
    "tgn:id":7576330,
    "tgn:name:en":"Kh\u0101ndsa",
    "tgn:placetype":[
        "aat:300008347"
    ]
},
  "bbox": [],
  "geometry": {"coordinates":[77.003374,28.434799],"type":"Point"}
}