{
  "id": 2212222,
  "type": "Feature",
  "properties": {
    "tgn:hierarchy":[
        "tgn:2212222",
        "tgn:1000001",
        "tgn:7012149",
        "tgn:2000788",
        "tgn:7007255",
        "tgn:7029392"
    ],
    "tgn:id":2212222,
    "tgn:name":"Buzzard Roost",
    "tgn:placetype":[
        "aat:300008798"
    ]
},
  "bbox": [],
  "geometry": {"coordinates":[-83.9667,37.7833],"type":"Point"}
}