{
  "id": 1027233,
  "type": "Feature",
  "properties": {
    "tgn:hierarchy":[
        "tgn:1027233",
        "tgn:7027127",
        "tgn:1000003",
        "tgn:7011765",
        "tgn:7029392"
    ],
    "tgn:id":1027233,
    "tgn:name":"Jablonica",
    "tgn:placetype":[
        "aat:300008347"
    ]
},
  "bbox": [],
  "geometry": {"coordinates":[17.4333,48.6167],"type":"Point"}
}