{
  "id": 2570089,
  "type": "Feature",
  "properties": {
    "tgn:hierarchy":[
        "tgn:2570089",
        "tgn:1000001",
        "tgn:7012149",
        "tgn:2001275",
        "tgn:7007524",
        "tgn:7029392"
    ],
    "tgn:id":2570089,
    "tgn:name":"Pass Creek Mine",
    "tgn:placetype":[
        "aat:300000390"
    ]
},
  "bbox": [],
  "geometry": {"coordinates":[-111.0167,45.95],"type":"Point"}
}