{
  "id": 2465620,
  "type": "Feature",
  "properties": {
    "tgn:hierarchy":[
        "tgn:2465620",
        "tgn:1000001",
        "tgn:7012149",
        "tgn:2001720",
        "tgn:7007708",
        "tgn:7029392"
    ],
    "tgn:id":2465620,
    "tgn:name":"Lone Pine Canyon",
    "tgn:placetype":[
        "aat:300008761"
    ]
},
  "bbox": [],
  "geometry": {"coordinates":[-119.0667,45.35],"type":"Point"}
}