{
  "id": 2600402,
  "type": "Feature",
  "properties": {
    "tgn:hierarchy":[
        "tgn:2600402",
        "tgn:1000001",
        "tgn:7012149",
        "tgn:2001449",
        "tgn:7007566",
        "tgn:7029392"
    ],
    "tgn:id":2600402,
    "tgn:name":"Puertecito Tank",
    "tgn:placetype":[
        "aat:300006191"
    ]
},
  "bbox": [],
  "geometry": {"coordinates":[-106.3333,36.3833],"type":"Point"}
}