{
  "id": 7222785,
  "type": "Feature",
  "properties": {
    "tgn:hierarchy":[
        "tgn:7222785",
        "tgn:7011161",
        "tgn:7002674",
        "tgn:1000003",
        "tgn:1000074",
        "tgn:7029392"
    ],
    "tgn:id":7222785,
    "tgn:name":"Mest\u00e1, \u00c1kra",
    "tgn:placetype":[
        "aat:300008850"
    ]
},
  "bbox": [],
  "geometry": {"coordinates":[25.865833,38.241944],"type":"Point"}
}