{
  "id": 2778567,
  "type": "Feature",
  "properties": {
    "tgn:hierarchy":[
        "tgn:2778567",
        "tgn:1000001",
        "tgn:7012149",
        "tgn:2001460",
        "tgn:7007566",
        "tgn:7029392"
    ],
    "tgn:id":2778567,
    "tgn:name":"Wittwer Lateral",
    "tgn:placetype":[
        "aat:300006075"
    ]
},
  "bbox": [],
  "geometry": {"coordinates":[-106.7167,34.7833],"type":"Point"}
}