{
  "id": 7560035,
  "type": "Feature",
  "properties": {
    "tgn:hierarchy":[
        "tgn:7560035",
        "tgn:1000004",
        "tgn:7000198",
        "tgn:7016722",
        "tgn:7029392"
    ],
    "tgn:id":7560035,
    "tgn:name:en":"Nagla Bih\u0101ri",
    "tgn:placetype":[
        "aat:300008347"
    ]
},
  "bbox": [],
  "geometry": {"coordinates":[79.014886,26.932567],"type":"Point"}
}