{
  "id": 7204545,
  "type": "Feature",
  "properties": {
    "tgn:hierarchy":[
        "tgn:7204545",
        "tgn:1000003",
        "tgn:7003682",
        "tgn:7000084",
        "tgn:7029392"
    ],
    "tgn:id":7204545,
    "tgn:name":"Brandscheid",
    "tgn:placetype":[
        "aat:300008347"
    ]
},
  "bbox": [],
  "geometry": {"coordinates":[6.316667,50.216667],"type":"Point"}
}