{
  "id": 1091858,
  "type": "Feature",
  "properties": {
    "tgn:hierarchy":[
        "tgn:1091858",
        "tgn:7001242",
        "tgn:1001912",
        "tgn:1000182",
        "tgn:7029392"
    ],
    "tgn:id":1091858,
    "tgn:name":"Alawa",
    "tgn:placetype":[
        "aat:300008347"
    ]
},
  "bbox": [],
  "geometry": {"coordinates":[6.65,10.3333],"type":"Point"}
}