{
  "id": 7524326,
  "type": "Feature",
  "properties": {
    "tgn:hierarchy":[
        "tgn:7524326",
        "tgn:7001242",
        "tgn:1001075",
        "tgn:7016833",
        "tgn:7029392"
    ],
    "tgn:id":7524326,
    "tgn:name:en":"Al Qal\u0101w\u0101t",
    "tgn:placetype":[
        "aat:300008347"
    ]
},
  "bbox": [],
  "geometry": {"coordinates":[30.634441,30.753977],"type":"Point"}
}