{
  "id": 7434998,
  "type": "Feature",
  "properties": {
    "tgn:hierarchy":[
        "tgn:7434998",
        "tgn:1000001",
        "tgn:7005594",
        "tgn:7005560",
        "tgn:7029392"
    ],
    "tgn:id":7434998,
    "tgn:name":"Vallejo",
    "tgn:placetype":[
        "aat:300008347"
    ]
},
  "bbox": [],
  "geometry": {"coordinates":[-100.55,23.116667],"type":"Point"}
}