<<<<<<< HEAD
{
  "id": 7020769,
  "type": "Feature",
  "properties": {
    "tgn:hierarchy":[
        "tgn:7020769",
        "tgn:1000001",
        "tgn:2000935",
        "tgn:7012149",
        "tgn:7007516",
        "tgn:7029392"
    ],
    "tgn:id":7020769,
    "tgn:name":"Sand Spring Run",
    "tgn:placetype":[
        "aat:300008699"
    ]
},
  "bbox": [],
  "geometry": {"coordinates":[-79.4667,39.25],"type":"Point"}
}
=======
{"geometry":{"type":"Point","coordinates":[-79.466700,39.250000]},"type":"Feature","properties":{"hierarchy":["tgn:7020769","tgn:1000001","tgn:2000935","tgn:7012149","tgn:7007516","tgn:7029392"],"placetype":["aat:300008699"],"id":7020769,"name:xx":"Sand Spring Run"}}
>>>>>>> 03f74aca74312dbeaf24d7e61306dd6a786dc3d0
