{
  "id": 2205618,
  "type": "Feature",
  "properties": {
    "tgn:hierarchy":[
        "tgn:2205618",
        "tgn:1000001",
        "tgn:7012149",
        "tgn:7007252",
        "tgn:7029392"
    ],
    "tgn:id":2205618,
    "tgn:name":"Bull Fork",
    "tgn:placetype":[
        "aat:300008699"
    ]
},
  "bbox": [],
  "geometry": {"coordinates":[-85.3333,39.4667],"type":"Point"}
}