{
  "id": 1082159,
  "type": "Feature",
  "properties": {
    "tgn:hierarchy":[
        "tgn:1082159",
        "tgn:1001301",
        "tgn:1000004",
        "tgn:1000122",
        "tgn:7029392"
    ],
    "tgn:id":1082159,
    "tgn:name":"Y\u014fnan",
    "tgn:placetype":[
        "aat:300008347"
    ]
},
  "bbox": [],
  "geometry": {"coordinates":[126.1833,37.9167],"type":"Point"}
}