{
  "id": 2634625,
  "type": "Feature",
  "properties": {
    "tgn:hierarchy":[
        "tgn:2634625",
        "tgn:1000001",
        "tgn:7012149",
        "tgn:2002122",
        "tgn:7007827",
        "tgn:7029392"
    ],
    "tgn:id":2634625,
    "tgn:name":"Ruth Lake",
    "tgn:placetype":[
        "aat:300008680"
    ]
},
  "bbox": [],
  "geometry": {"coordinates":[-110.8667,40.7167],"type":"Point"}
}