{
  "id": 2144732,
  "type": "Feature",
  "properties": {
    "tgn:hierarchy":[
        "tgn:2144732",
        "tgn:1000001",
        "tgn:7012149",
        "tgn:2000543",
        "tgn:7007252",
        "tgn:7029392"
    ],
    "tgn:id":2144732,
    "tgn:name":"Bald Hill",
    "tgn:placetype":[
        "aat:300008798"
    ]
},
  "bbox": [],
  "geometry": {"coordinates":[-87.55,38.3833],"type":"Point"}
}