{
  "id": 1121891,
  "type": "Feature",
  "properties": {
    "tgn:hierarchy":[
        "tgn:1121891",
        "tgn:1000001",
        "tgn:7012149",
        "tgn:2002336",
        "tgn:7007922",
        "tgn:7029392"
    ],
    "tgn:id":1121891,
    "tgn:name":"Big Eau Pleine",
    "tgn:placetype":[
        "aat:300008707"
    ]
},
  "bbox": [],
  "geometry": {"coordinates":[-90.2333,44.9667],"type":"Point"}
}