{
  "id": 2382714,
  "type": "Feature",
  "properties": {
    "tgn:hierarchy":[
        "tgn:2382714",
        "tgn:1000001",
        "tgn:7012149",
        "tgn:2000903",
        "tgn:7007256",
        "tgn:7029392"
    ],
    "tgn:id":2382714,
    "tgn:name":"Hazel",
    "tgn:placetype":[
        "aat:300008347"
    ]
},
  "bbox": [],
  "geometry": {"coordinates":[-91.8833,30.0833],"type":"Point"}
}