{
  "id": 7429848,
  "type": "Feature",
  "properties": {
    "tgn:hierarchy":[
        "tgn:7429848",
        "tgn:1001853",
        "tgn:1000001",
        "tgn:7005560",
        "tgn:7029392"
    ],
    "tgn:id":7429848,
    "tgn:name":"Agua de los Caballos",
    "tgn:placetype":[
        "aat:300008347"
    ]
},
  "bbox": [],
  "geometry": {"coordinates":[-101.75,26.316667],"type":"Point"}
}