<<<<<<< HEAD
{
  "id": 7352983,
  "type": "Feature",
  "properties": {
    "tgn:hierarchy":[
        "tgn:7352983",
        "tgn:7005581",
        "tgn:1000001",
        "tgn:7005560",
        "tgn:7029392"
    ],
    "tgn:id":7352983,
    "tgn:name":"Rancho Atotonilco",
    "tgn:placetype":[
        "aat:300000241"
    ]
},
  "bbox": [],
  "geometry": {"coordinates":[-106.183333,30.466667],"type":"Point"}
}
=======
{"geometry":{"type":"Point","coordinates":[-106.183333,30.466667]},"type":"Feature","properties":{"hierarchy":["tgn:7352983","tgn:7005581","tgn:1000001","tgn:7005560","tgn:7029392"],"placetype":["aat:300000241"],"id":7352983,"name:xx":"Rancho Atotonilco"}}
>>>>>>> 03f74aca74312dbeaf24d7e61306dd6a786dc3d0
