{
  "id": 7352983,
  "type": "Feature",
  "properties": {
    "tgn:hierarchy":[
        "tgn:7352983",
        "tgn:7005581",
        "tgn:1000001",
        "tgn:7005560",
        "tgn:7029392"
    ],
    "tgn:id":7352983,
    "tgn:name":"Rancho Atotonilco",
    "tgn:placetype":[
        "aat:300000241"
    ]
},
  "bbox": [],
  "geometry": {"coordinates":[-106.183333,30.466667],"type":"Point"}
}