{
  "id": 7367361,
  "type": "Feature",
  "properties": {
    "tgn:hierarchy":[
        "tgn:7367361",
        "tgn:1001853",
        "tgn:1000001",
        "tgn:7005560",
        "tgn:7029392"
    ],
    "tgn:id":7367361,
    "tgn:name":"El Tulillo",
    "tgn:placetype":[
        "aat:300008347"
    ]
},
  "bbox": [],
  "geometry": {"coordinates":[-101.45,25.633333],"type":"Point"}
}