{
  "id": 2162770,
  "type": "Feature",
  "properties": {
    "tgn:hierarchy":[
        "tgn:2162770",
        "tgn:1000001",
        "tgn:7012149",
        "tgn:2000281",
        "tgn:7007240",
        "tgn:7029392"
    ],
    "tgn:id":2162770,
    "tgn:name":"Bends Creek",
    "tgn:placetype":[
        "aat:300008706"
    ]
},
  "bbox": [],
  "geometry": {"coordinates":[-86.5167,30.8333],"type":"Point"}
}