{
  "id": 7115772,
  "type": "Feature",
  "properties": {
    "tgn:hierarchy":[
        "tgn:7115772",
        "tgn:1000003",
        "tgn:7003676",
        "tgn:7000084",
        "tgn:7029392"
    ],
    "tgn:id":7115772,
    "tgn:name":"Ohren-Berg",
    "tgn:placetype":[
        "aat:300008777"
    ]
},
  "bbox": [],
  "geometry": {"coordinates":[10.65,52.066667],"type":"Point"}
}