<<<<<<< HEAD
{
  "id": 7115772,
  "type": "Feature",
  "properties": {
    "tgn:hierarchy":[
        "tgn:7115772",
        "tgn:1000003",
        "tgn:7003676",
        "tgn:7000084",
        "tgn:7029392"
    ],
    "tgn:id":7115772,
    "tgn:name":"Ohren-Berg",
    "tgn:placetype":[
        "aat:300008777"
    ]
},
  "bbox": [],
  "geometry": {"coordinates":[10.65,52.066667],"type":"Point"}
}
=======
{"geometry":{"type":"Point","coordinates":[10.650000,52.066667]},"type":"Feature","properties":{"hierarchy":["tgn:7115772","tgn:1000003","tgn:7003676","tgn:7000084","tgn:7029392"],"placetype":["aat:300008777"],"id":7115772,"name:xx":"Ohren-Berg"}}
>>>>>>> 03f74aca74312dbeaf24d7e61306dd6a786dc3d0
