<<<<<<< HEAD
{
  "id": 7055971,
  "type": "Feature",
  "properties": {
    "tgn:hierarchy":[
        "tgn:7055971",
        "tgn:1003505",
        "tgn:1000003",
        "tgn:7002993",
        "tgn:1000080",
        "tgn:7029392"
    ],
    "tgn:id":7055971,
    "tgn:name":"Oltra, Vale",
    "tgn:placetype":[
        "aat:300008761"
    ]
},
  "bbox": [],
  "geometry": {"coordinates":[13.733333,45.6],"type":"Point"}
}
=======
{"geometry":{"type":"Point","coordinates":[13.733333,45.600000]},"type":"Feature","properties":{"hierarchy":["tgn:7055971","tgn:1003505","tgn:1000003","tgn:7002993","tgn:1000080","tgn:7029392"],"placetype":["aat:300008761"],"id":7055971,"name:xx":"Oltra, Vale"}}
>>>>>>> 03f74aca74312dbeaf24d7e61306dd6a786dc3d0
