{
  "id": 2696431,
  "type": "Feature",
  "properties": {
    "tgn:hierarchy":[
        "tgn:2696431",
        "tgn:1000001",
        "tgn:7012149",
        "tgn:2002276",
        "tgn:7013961",
        "tgn:7029392"
    ],
    "tgn:id":2696431,
    "tgn:name":"Stone Hollow",
    "tgn:placetype":[
        "aat:300008761"
    ]
},
  "bbox": [],
  "geometry": {"coordinates":[-80.6667,39.75],"type":"Point"}
}