{
  "id": 7555435,
  "type": "Feature",
  "properties": {
    "tgn:hierarchy":[
        "tgn:7555435",
        "tgn:1000004",
        "tgn:7000198",
        "tgn:7001797",
        "tgn:7029392"
    ],
    "tgn:id":7555435,
    "tgn:name:en":"Pad\u0101lam",
    "tgn:placetype":[
        "aat:300008347"
    ]
},
  "bbox": [],
  "geometry": {"coordinates":[79.95,12.583333],"type":"Point"}
}