{
  "id": 2537492,
  "type": "Feature",
  "properties": {
    "tgn:hierarchy":[
        "tgn:2537492",
        "tgn:1000001",
        "tgn:7012149",
        "tgn:1002993",
        "tgn:7007568",
        "tgn:7029392"
    ],
    "tgn:id":2537492,
    "tgn:name":"Negro Marsh",
    "tgn:placetype":[
        "aat:300008905"
    ]
},
  "bbox": [],
  "geometry": {"coordinates":[-73.3667,43.7667],"type":"Point"}
}