{
  "id": 2509427,
  "type": "Feature",
  "properties": {
    "tgn:hierarchy":[
        "tgn:2509427",
        "tgn:1000001",
        "tgn:7012149",
        "tgn:7007157",
        "tgn:2000186",
        "tgn:7029392"
    ],
    "tgn:id":2509427,
    "tgn:name":"Middle Fork Spring",
    "tgn:placetype":[
        "aat:300008697"
    ]
},
  "bbox": [],
  "geometry": {"coordinates":[-120.15,41.1833],"type":"Point"}
}