{
  "id": 7532613,
  "type": "Feature",
  "properties": {
    "tgn:hierarchy":[
        "tgn:7532613",
        "tgn:7001242",
        "tgn:7016833",
        "tgn:1001091",
        "tgn:7029392"
    ],
    "tgn:id":7532613,
    "tgn:name":"\u1e28ad\u012bqat Sittat Ukt\u016bbar",
    "tgn:placetype":[
        "aat:300008187"
    ]
},
  "bbox": [],
  "geometry": {"coordinates":[31.325589,30.108593],"type":"Point"}
}