{
  "id": 2057136,
  "type": "Feature",
  "properties": {
    "tgn:hierarchy":[
        "tgn:2057136",
        "tgn:1000001",
        "tgn:2001102",
        "tgn:7012149",
        "tgn:7007522",
        "tgn:7029392"
    ],
    "tgn:id":2057136,
    "tgn:name":"Olive Branch",
    "tgn:placetype":[
        "aat:300008347"
    ]
},
  "bbox": [],
  "geometry": {"coordinates":[-89.8167,34.95],"type":"Point"}
}