{
  "id": 7332757,
  "type": "Feature",
  "properties": {
    "tgn:hierarchy":[
        "tgn:7332757",
        "tgn:7002818",
        "tgn:1001647",
        "tgn:1000003",
        "tgn:1000095",
        "tgn:7029392"
    ],
    "tgn:id":7332757,
    "tgn:name":"La Alberca de Z\u00e1ncara",
    "tgn:placetype":[
        "aat:300008347"
    ]
},
  "bbox": [],
  "geometry": {"coordinates":[-2.483333,39.516667],"type":"Point"}
}