{
  "id": 7261397,
  "type": "Feature",
  "properties": {
    "tgn:hierarchy":[
        "tgn:7261397",
        "tgn:1000003",
        "tgn:7003626",
        "tgn:7016845",
        "tgn:7029392"
    ],
    "tgn:id":7261397,
    "tgn:name:nl":"Gammelkerbeek",
    "tgn:placetype":[
        "aat:300008699"
    ]
},
  "bbox": [],
  "geometry": {"coordinates":[6.766667,52.35],"type":"Point"}
}