{
  "id": 7392842,
  "type": "Feature",
  "properties": {
    "tgn:hierarchy":[
        "tgn:7392842",
        "tgn:7005581",
        "tgn:1000001",
        "tgn:7005560",
        "tgn:7029392"
    ],
    "tgn:id":7392842,
    "tgn:name":"Rancho San Juan",
    "tgn:placetype":[
        "aat:300000241"
    ]
},
  "bbox": [],
  "geometry": {"coordinates":[-104.666667,29.083333],"type":"Point"}
}