{
  "id": 7284809,
  "type": "Feature",
  "properties": {
    "tgn:hierarchy":[
        "tgn:7284809",
        "tgn:1001623",
        "tgn:1000049",
        "tgn:1000002",
        "tgn:7029392"
    ],
    "tgn:id":7284809,
    "tgn:name":"P\u00falpito, Morro del",
    "tgn:placetype":[
        "aat:300008795"
    ]
},
  "bbox": [],
  "geometry": {"coordinates":[-72.15,-45.016667],"type":"Point"}
}