{
  "id": 7171849,
  "type": "Feature",
  "properties": {
    "tgn:hierarchy":[
        "tgn:7171849",
        "tgn:1000003",
        "tgn:7003678",
        "tgn:7000084",
        "tgn:7029392"
    ],
    "tgn:id":7171849,
    "tgn:name":"Herrnhaag",
    "tgn:placetype":[
        "aat:300008347"
    ]
},
  "bbox": [],
  "geometry": {"coordinates":[9.083333,50.266667],"type":"Point"}
}