{
  "id": 2569456,
  "type": "Feature",
  "properties": {
    "tgn:hierarchy":[
        "tgn:2569456",
        "tgn:1000001",
        "tgn:2000108",
        "tgn:7016172",
        "tgn:7012149",
        "tgn:7029392"
    ],
    "tgn:id":2569456,
    "tgn:name":"Parn",
    "tgn:placetype":[
        "aat:300008347"
    ]
},
  "bbox": [],
  "geometry": {"coordinates":[-94.3333,36.3333],"type":"Point"}
}