{
  "id": 7483137,
  "type": "Feature",
  "properties": {
    "tgn:hierarchy":[
        "tgn:7483137",
        "tgn:1000004",
        "tgn:7001009",
        "tgn:1000141",
        "tgn:7029392"
    ],
    "tgn:id":7483137,
    "tgn:name":"Ciyi Fotang",
    "tgn:placetype":[
        "aat:300007595"
    ]
},
  "bbox": [],
  "geometry": {"coordinates":[120.625556,24.335278],"type":"Point"}
}