<<<<<<< HEAD
{
  "id": 2335254,
  "type": "Feature",
  "properties": {
    "tgn:hierarchy":[
        "tgn:2335254",
        "tgn:2001731",
        "tgn:1000001",
        "tgn:7012149",
        "tgn:7007712",
        "tgn:7029392"
    ],
    "tgn:id":2335254,
    "tgn:name":"Fort Fremont",
    "tgn:placetype":[
        "aat:300008347"
    ]
},
  "bbox": [],
  "geometry": {"coordinates":[-80.6333,32.3],"type":"Point"}
}
=======
{"geometry":{"type":"Point","coordinates":[-80.633300,32.300000]},"type":"Feature","properties":{"hierarchy":["tgn:2335254","tgn:2001731","tgn:1000001","tgn:7012149","tgn:7007712","tgn:7029392"],"placetype":["aat:300008347"],"id":2335254,"name:xx":"Fort Fremont"}}
>>>>>>> 03f74aca74312dbeaf24d7e61306dd6a786dc3d0
