{
  "id": 1084939,
  "type": "Feature",
  "properties": {
    "tgn:hierarchy":[
        "tgn:1084939",
        "tgn:1000004",
        "tgn:1000138",
        "tgn:7000381",
        "tgn:7029392"
    ],
    "tgn:id":1084939,
    "tgn:name":"Seletar",
    "tgn:placetype":[
        "aat:300008347"
    ]
},
  "bbox": [],
  "geometry": {"coordinates":[103.8667,1.4167],"type":"Point"}
}