{
  "id": 7324812,
  "type": "Feature",
  "properties": {
    "tgn:hierarchy":[
        "tgn:7324812",
        "tgn:7002760",
        "tgn:1000003",
        "tgn:1000095",
        "tgn:7029392"
    ],
    "tgn:id":7324812,
    "tgn:name":"San Miguel de Aguayo",
    "tgn:placetype":[
        "aat:300008347"
    ]
},
  "bbox": [],
  "geometry": {"coordinates":[-4.016667,43.05],"type":"Point"}
}