{
  "id": 7229807,
  "type": "Feature",
  "properties": {
    "tgn:hierarchy":[
        "tgn:7229807",
        "tgn:7011270",
        "tgn:7002674",
        "tgn:1000003",
        "tgn:1000074",
        "tgn:7029392"
    ],
    "tgn:id":7229807,
    "tgn:name":"Christian\u00e1, Nis\u00eddes",
    "tgn:placetype":[
        "aat:300008791"
    ]
},
  "bbox": [],
  "geometry": {"coordinates":[25.207656,36.230689],"type":"Point"}
}