{
  "id": 1095667,
  "type": "Feature",
  "properties": {
    "tgn:hierarchy":[
        "tgn:1095667",
        "tgn:7001242",
        "tgn:1001075",
        "tgn:7016833",
        "tgn:7029392"
    ],
    "tgn:id":1095667,
    "tgn:name":"Rash\u00eed",
    "tgn:placetype":[
        "aat:300008347"
    ]
},
  "bbox": [],
  "geometry": {"coordinates":[30.416389,31.404444],"type":"Point"}
}