{
  "id": 7001898,
  "type": "Feature",
  "properties": {
    "tgn:hierarchy":[
        "tgn:7001898",
        "tgn:1000004",
        "tgn:7002084",
        "tgn:1000111",
        "tgn:7029392"
    ],
    "tgn:id":7001898,
    "tgn:name":"Baoji",
    "tgn:placetype":[
        "aat:300008347"
    ]
},
  "bbox": [],
  "geometry": {"coordinates":[107.2667,34.3833],"type":"Point"}
}