{
  "id": 7543151,
  "type": "Feature",
  "properties": {
    "tgn:hierarchy":[
        "tgn:7543151",
        "tgn:7001242",
        "tgn:1001075",
        "tgn:7016833",
        "tgn:7029392"
    ],
    "tgn:id":7543151,
    "tgn:name:en":"Ash Shah\u012bd Mu\u1e29ammad 'Azz\u0101m",
    "tgn:placetype":[
        "aat:300008347"
    ]
},
  "bbox": [],
  "geometry": {"coordinates":[30.006899,30.705725],"type":"Point"}
}