{
  "id": 7243171,
  "type": "Feature",
  "properties": {
    "tgn:hierarchy":[
        "tgn:7243171",
        "tgn:7003465",
        "tgn:1000003",
        "tgn:1000063",
        "tgn:4012014",
        "tgn:7029392"
    ],
    "tgn:id":7243171,
    "tgn:name":"Kripsenbach Busch",
    "tgn:placetype":[
        "aat:300008863"
    ]
},
  "bbox": [],
  "geometry": {"coordinates":[5.683333,49.733333],"type":"Point"}
}