<<<<<<< HEAD
{
  "id": 7367046,
  "type": "Feature",
  "properties": {
    "tgn:hierarchy":[
        "tgn:7367046",
        "tgn:7005581",
        "tgn:1000001",
        "tgn:7005560",
        "tgn:7029392"
    ],
    "tgn:id":7367046,
    "tgn:name":"Rancho El Roble",
    "tgn:placetype":[
        "aat:300000241"
    ]
},
  "bbox": [],
  "geometry": {"coordinates":[-107.083333,28.066667],"type":"Point"}
}
=======
{"geometry":{"type":"Point","coordinates":[-107.083333,28.066667]},"type":"Feature","properties":{"hierarchy":["tgn:7367046","tgn:7005581","tgn:1000001","tgn:7005560","tgn:7029392"],"placetype":["aat:300000241"],"id":7367046,"name:xx":"Rancho El Roble"}}
>>>>>>> 03f74aca74312dbeaf24d7e61306dd6a786dc3d0
