{
  "id": 7367046,
  "type": "Feature",
  "properties": {
    "tgn:hierarchy":[
        "tgn:7367046",
        "tgn:7005581",
        "tgn:1000001",
        "tgn:7005560",
        "tgn:7029392"
    ],
    "tgn:id":7367046,
    "tgn:name":"Rancho El Roble",
    "tgn:placetype":[
        "aat:300000241"
    ]
},
  "bbox": [],
  "geometry": {"coordinates":[-107.083333,28.066667],"type":"Point"}
}