{
  "id": 7372263,
  "type": "Feature",
  "properties": {
    "tgn:hierarchy":[
        "tgn:7372263",
        "tgn:1000001",
        "tgn:1001960",
        "tgn:7005560",
        "tgn:7029392"
    ],
    "tgn:id":7372263,
    "tgn:name":"Rancho La Ca\u00f1ada Larga",
    "tgn:placetype":[
        "aat:300000241"
    ]
},
  "bbox": [],
  "geometry": {"coordinates":[-109.166667,29.066667],"type":"Point"}
}