<<<<<<< HEAD
{
  "id": 7372263,
  "type": "Feature",
  "properties": {
    "tgn:hierarchy":[
        "tgn:7372263",
        "tgn:1000001",
        "tgn:1001960",
        "tgn:7005560",
        "tgn:7029392"
    ],
    "tgn:id":7372263,
    "tgn:name":"Rancho La Ca\u00f1ada Larga",
    "tgn:placetype":[
        "aat:300000241"
    ]
},
  "bbox": [],
  "geometry": {"coordinates":[-109.166667,29.066667],"type":"Point"}
}
=======
{"geometry":{"type":"Point","coordinates":[-109.166667,29.066667]},"type":"Feature","properties":{"hierarchy":["tgn:7372263","tgn:1000001","tgn:1001960","tgn:7005560","tgn:7029392"],"placetype":["aat:300000241"],"id":7372263,"name:xx":"Rancho La Ca\u00f1ada Larga"}}
>>>>>>> 03f74aca74312dbeaf24d7e61306dd6a786dc3d0
