{
  "id": 2534747,
  "type": "Feature",
  "properties": {
    "tgn:hierarchy":[
        "tgn:2534747",
        "tgn:7006450",
        "tgn:1000001",
        "tgn:7012149",
        "tgn:2000082",
        "tgn:7029392"
    ],
    "tgn:id":2534747,
    "tgn:name":"Nadzaheer Cove",
    "tgn:placetype":[
        "aat:300132316"
    ]
},
  "bbox": [],
  "geometry": {"coordinates":[-131.4667,55.2167],"type":"Point"}
}