{
  "id": 2548853,
  "type": "Feature",
  "properties": {
    "tgn:hierarchy":[
        "tgn:2548853",
        "tgn:1000001",
        "tgn:2000925",
        "tgn:7012149",
        "tgn:7007515",
        "tgn:7029392"
    ],
    "tgn:id":2548853,
    "tgn:name":"North Point",
    "tgn:placetype":[
        "aat:300008850"
    ]
},
  "bbox": [],
  "geometry": {"coordinates":[-69.7333,43.8667],"type":"Point"}
}