{
  "id": 2593225,
  "type": "Feature",
  "properties": {
    "tgn:hierarchy":[
        "tgn:2593225",
        "tgn:7002659",
        "tgn:1000001",
        "tgn:7012149",
        "tgn:2000039",
        "tgn:7029392"
    ],
    "tgn:id":2593225,
    "tgn:name":"Poplar Spring",
    "tgn:placetype":[
        "aat:300008697"
    ]
},
  "bbox": [],
  "geometry": {"coordinates":[-87.3167,34.5833],"type":"Point"}
}