{
  "id": 7224092,
  "type": "Feature",
  "properties": {
    "tgn:hierarchy":[
        "tgn:7224092",
        "tgn:7002748",
        "tgn:7001399",
        "tgn:1000003",
        "tgn:1000074",
        "tgn:7029392"
    ],
    "tgn:id":7224092,
    "tgn:name":"P\u00edrgos",
    "tgn:placetype":[
        "aat:300008347"
    ]
},
  "bbox": [],
  "geometry": {"coordinates":[22.083333,39.366667],"type":"Point"}
}