{
  "id": 2656920,
  "type": "Feature",
  "properties": {
    "tgn:hierarchy":[
        "tgn:2656920",
        "tgn:1000001",
        "tgn:7012149",
        "tgn:2000931",
        "tgn:7007515",
        "tgn:7029392"
    ],
    "tgn:id":2656920,
    "tgn:name":"Sheep Island",
    "tgn:placetype":[
        "aat:300008791"
    ]
},
  "bbox": [],
  "geometry": {"coordinates":[-69.1667,44.3833],"type":"Point"}
}