{
  "id": 2232934,
  "type": "Feature",
  "properties": {
    "tgn:hierarchy":[
        "tgn:2232934",
        "tgn:1000001",
        "tgn:7012149",
        "tgn:2000997",
        "tgn:7007520",
        "tgn:7029392"
    ],
    "tgn:id":2232934,
    "tgn:name":"Chapple Drain",
    "tgn:placetype":[
        "aat:300006075"
    ]
},
  "bbox": [],
  "geometry": {"coordinates":[-83.4667,43.4333],"type":"Point"}
}