{
  "id": 2550095,
  "type": "Feature",
  "properties": {
    "tgn:hierarchy":[
        "tgn:2550095",
        "tgn:7030515",
        "tgn:7006450",
        "tgn:1000001",
        "tgn:7012149",
        "tgn:7029392"
    ],
    "tgn:id":2550095,
    "tgn:name":"Northeast Bight",
    "tgn:placetype":[
        "aat:300132316"
    ]
},
  "bbox": [],
  "geometry": {"coordinates":[-159.8667,9.3167],"type":"Point"}
}