{
  "id": 2374080,
  "type": "Feature",
  "properties": {
    "tgn:hierarchy":[
        "tgn:2374080",
        "tgn:1000001",
        "tgn:1002664",
        "tgn:7012149",
        "tgn:7007159",
        "tgn:7029392"
    ],
    "tgn:id":2374080,
    "tgn:name":"Hammock River",
    "tgn:placetype":[
        "aat:300008707"
    ]
},
  "bbox": [],
  "geometry": {"coordinates":[-72.4833,41.2667],"type":"Point"}
}