{
  "id": 2238394,
  "type": "Feature",
  "properties": {
    "tgn:hierarchy":[
        "tgn:2238394",
        "tgn:1000001",
        "tgn:7012149",
        "tgn:2001293",
        "tgn:7007524",
        "tgn:7029392"
    ],
    "tgn:id":2238394,
    "tgn:name":"Choke-To-Death Butte",
    "tgn:placetype":[
        "aat:300008798"
    ]
},
  "bbox": [],
  "geometry": {"coordinates":[-110.35,45.85],"type":"Point"}
}