{
  "id": 7135856,
  "type": "Feature",
  "properties": {
    "tgn:hierarchy":[
        "tgn:7135856",
        "tgn:7000096",
        "tgn:1000003",
        "tgn:7000084",
        "tgn:7029392"
    ],
    "tgn:id":7135856,
    "tgn:name":"N\u00e4chst-Neuendorf",
    "tgn:placetype":[
        "aat:300008347"
    ]
},
  "bbox": [],
  "geometry": {"coordinates":[13.416667,52.233333],"type":"Point"}
}