{
  "id": 1082456,
  "type": "Feature",
  "properties": {
    "tgn:hierarchy":[
        "tgn:1082456",
        "tgn:1000004",
        "tgn:7000852",
        "tgn:1000125",
        "tgn:7029392"
    ],
    "tgn:id":1082456,
    "tgn:name":"Ban Namnga",
    "tgn:placetype":[
        "aat:300008347"
    ]
},
  "bbox": [],
  "geometry": {"coordinates":[102.3167,20.3667],"type":"Point"}
}