{
  "id": 7270703,
  "type": "Feature",
  "properties": {
    "tgn:concordances":{
        "gn:id":"2747330"
    },
    "tgn:hierarchy":[
        "tgn:7270703",
        "tgn:7003616",
        "tgn:1000003",
        "tgn:7016845",
        "tgn:7029392"
    ],
    "tgn:id":7270703,
    "tgn:name:nl":"Sijbrandaburen",
    "tgn:placetype":[
        "aat:300008347"
    ]
},
  "bbox": [],
  "geometry": {"coordinates":[5.716667,53.066667],"type":"Point"}
}