{
  "id": 7003547,
  "type": "Feature",
  "properties": {
    "tgn:hierarchy":[
        "tgn:7003547",
        "tgn:7594005",
        "tgn:1000003",
        "tgn:1000066",
        "tgn:7029392"
    ],
    "tgn:id":7003547,
    "tgn:name":"Frederikssund",
    "tgn:placetype":[
        "aat:300008347"
    ]
},
  "bbox": [],
  "geometry": {"coordinates":[12.0833,55.85],"type":"Point"}
}