{
  "id": 1074872,
  "type": "Feature",
  "properties": {
    "tgn:hierarchy":[
        "tgn:1074872",
        "tgn:1000004",
        "tgn:7000198",
        "tgn:1001895",
        "tgn:7029392"
    ],
    "tgn:id":1074872,
    "tgn:name":"Bonsari",
    "tgn:placetype":[
        "aat:300008347"
    ]
},
  "bbox": [],
  "geometry": {"coordinates":[73.0333,19.0667],"type":"Point"}
}