<<<<<<< HEAD
{
  "id": 2259140,
  "type": "Feature",
  "properties": {
    "tgn:hierarchy":[
        "tgn:2259140",
        "tgn:1000001",
        "tgn:7012149",
        "tgn:7007158",
        "tgn:2000250",
        "tgn:7029392"
    ],
    "tgn:id":2259140,
    "tgn:name":"Cottonwood Gulch",
    "tgn:placetype":[
        "aat:300008761"
    ]
},
  "bbox": [],
  "geometry": {"coordinates":[-106.2167,39.8667],"type":"Point"}
}
=======
{"geometry":{"type":"Point","coordinates":[-106.216700,39.866700]},"type":"Feature","properties":{"hierarchy":["tgn:2259140","tgn:1000001","tgn:7012149","tgn:7007158","tgn:2000250","tgn:7029392"],"placetype":["aat:300008761"],"id":2259140,"name:xx":"Cottonwood Gulch"}}
>>>>>>> 03f74aca74312dbeaf24d7e61306dd6a786dc3d0
