{
  "id": 7404497,
  "type": "Feature",
  "properties": {
    "tgn:hierarchy":[
        "tgn:7404497",
        "tgn:7005578",
        "tgn:1000001",
        "tgn:7005560",
        "tgn:7029392"
    ],
    "tgn:id":7404497,
    "tgn:name":"San Nicol\u00e1s",
    "tgn:placetype":[
        "aat:300008347"
    ]
},
  "bbox": [],
  "geometry": {"coordinates":[-91.266667,18.933333],"type":"Point"}
}