{
  "id": 7271170,
  "type": "Feature",
  "properties": {
    "tgn:hierarchy":[
        "tgn:7271170",
        "tgn:1000003",
        "tgn:7003632",
        "tgn:7016845",
        "tgn:7029392"
    ],
    "tgn:id":7271170,
    "tgn:name:nl":"Springersdiep",
    "tgn:placetype":[
        "aat:300387026"
    ]
},
  "bbox": [],
  "geometry": {"coordinates":[3.933333,51.783333],"type":"Point"}
}