{
  "id": 7290909,
  "type": "Feature",
  "properties": {
    "tgn:hierarchy":[
        "tgn:7290909",
        "tgn:7002464",
        "tgn:1000049",
        "tgn:1000002",
        "tgn:7029392"
    ],
    "tgn:id":7290909,
    "tgn:name":"Descubridora",
    "tgn:placetype":[
        "aat:300008777"
    ]
},
  "bbox": [],
  "geometry": {"coordinates":[-70.066667,-20.233333],"type":"Point"}
}