<<<<<<< HEAD
{
  "id": 2336807,
  "type": "Feature",
  "properties": {
    "tgn:hierarchy":[
        "tgn:2336807",
        "tgn:1000001",
        "tgn:2001409",
        "tgn:7012149",
        "tgn:7007526",
        "tgn:7029392"
    ],
    "tgn:id":2336807,
    "tgn:name":"Fourmile Canyon",
    "tgn:placetype":[
        "aat:300008761"
    ]
},
  "bbox": [],
  "geometry": {"coordinates":[-118.4167,39.1167],"type":"Point"}
}
=======
{"geometry":{"type":"Point","coordinates":[-118.416700,39.116700]},"type":"Feature","properties":{"hierarchy":["tgn:2336807","tgn:1000001","tgn:2001409","tgn:7012149","tgn:7007526","tgn:7029392"],"placetype":["aat:300008761"],"id":2336807,"name:xx":"Fourmile Canyon"}}
>>>>>>> 03f74aca74312dbeaf24d7e61306dd6a786dc3d0
