{
  "id": 1127633,
  "type": "Feature",
  "properties": {
    "tgn:hierarchy":[
        "tgn:1127633",
        "tgn:7005735",
        "tgn:7005685",
        "tgn:1000001",
        "tgn:7029392"
    ],
    "tgn:id":1127633,
    "tgn:name":"Nation River",
    "tgn:placetype":[
        "aat:300008707"
    ]
},
  "bbox": [],
  "geometry": {"coordinates":[-123.5833,55.4667],"type":"Point"}
}