<<<<<<< HEAD
{
  "id": 7021214,
  "type": "Feature",
  "properties": {
    "tgn:hierarchy":[
        "tgn:7021214",
        "tgn:1000001",
        "tgn:7012149",
        "tgn:2002279",
        "tgn:7013961",
        "tgn:7029392"
    ],
    "tgn:id":7021214,
    "tgn:name":"Keller Run",
    "tgn:placetype":[
        "aat:300008699"
    ]
},
  "bbox": [],
  "geometry": {"coordinates":[-78.7167,39.4667],"type":"Point"}
}
=======
{"geometry":{"type":"Point","coordinates":[-78.716700,39.466700]},"type":"Feature","properties":{"hierarchy":["tgn:7021214","tgn:1000001","tgn:7012149","tgn:2002279","tgn:7013961","tgn:7029392"],"placetype":["aat:300008699"],"id":7021214,"name:xx":"Keller Run"}}
>>>>>>> 03f74aca74312dbeaf24d7e61306dd6a786dc3d0
