{
  "id": 1059734,
  "type": "Feature",
  "properties": {
    "tgn:hierarchy":[
        "tgn:1059734",
        "tgn:1000004",
        "tgn:7002435",
        "tgn:7011524",
        "tgn:7029392"
    ],
    "tgn:id":1059734,
    "tgn:name":"Starosheshminsk",
    "tgn:placetype":[
        "aat:300008347"
    ]
},
  "bbox": [],
  "geometry": {"coordinates":[51.25,55.3833],"type":"Point"}
}