{
  "id": 2391627,
  "type": "Feature",
  "properties": {
    "tgn:hierarchy":[
        "tgn:2391627",
        "tgn:1000001",
        "tgn:1002480",
        "tgn:7012149",
        "tgn:7007564",
        "tgn:7029392"
    ],
    "tgn:id":2391627,
    "tgn:name":"Hillsboro Center",
    "tgn:placetype":[
        "aat:300008347"
    ]
},
  "bbox": [],
  "geometry": {"coordinates":[-71.9333,43.1333],"type":"Point"}
}