{
  "id": 7313801,
  "type": "Feature",
  "properties": {
    "tgn:hierarchy":[
        "tgn:7313801",
        "tgn:1001630",
        "tgn:1000049",
        "tgn:1000002",
        "tgn:7029392"
    ],
    "tgn:id":7313801,
    "tgn:name":"Llano de Pedernales",
    "tgn:placetype":[
        "aat:300387033"
    ]
},
  "bbox": [],
  "geometry": {"coordinates":[-69.166667,-26.333333],"type":"Point"}
}