{
  "id": 2410650,
  "type": "Feature",
  "properties": {
    "tgn:hierarchy":[
        "tgn:2410650",
        "tgn:1000001",
        "tgn:7012149",
        "tgn:7007157",
        "tgn:1002957",
        "tgn:7029392"
    ],
    "tgn:id":2410650,
    "tgn:name":"Indian Creek",
    "tgn:placetype":[
        "aat:300008706"
    ]
},
  "bbox": [],
  "geometry": {"coordinates":[-120.1167,37.8333],"type":"Point"}
}