{
  "id": 2683775,
  "type": "Feature",
  "properties": {
    "tgn:hierarchy":[
        "tgn:2683775",
        "tgn:1002165",
        "tgn:1000001",
        "tgn:7012149",
        "tgn:7007517",
        "tgn:7029392"
    ],
    "tgn:id":2683775,
    "tgn:name":"Spectacle Pond",
    "tgn:placetype":[
        "aat:300008680"
    ]
},
  "bbox": [],
  "geometry": {"coordinates":[-70.5833,41.5833],"type":"Point"}
}