{
  "id": 7504093,
  "type": "Feature",
  "properties": {
    "tgn:hierarchy":[
        "tgn:7504093",
        "tgn:1009227",
        "tgn:1000226",
        "tgn:7016822",
        "tgn:1000006",
        "tgn:7029392"
    ],
    "tgn:id":7504093,
    "tgn:name:en":"Wednesday Peak",
    "tgn:placetype":[
        "aat:300008798"
    ]
},
  "bbox": [],
  "geometry": {"coordinates":[166.833333,-46.15],"type":"Point"}
}