{
  "id": 2624300,
  "type": "Feature",
  "properties": {
    "tgn:hierarchy":[
        "tgn:2624300",
        "tgn:1000001",
        "tgn:7012149",
        "tgn:2001040",
        "tgn:7007521",
        "tgn:7029392"
    ],
    "tgn:id":2624300,
    "tgn:name":"Rock Lake",
    "tgn:placetype":[
        "aat:300008680"
    ]
},
  "bbox": [],
  "geometry": {"coordinates":[-95.9333,44.2667],"type":"Point"}
}