{
  "id": 2193428,
  "type": "Feature",
  "properties": {
    "tgn:hierarchy":[
        "tgn:2193428",
        "tgn:1000001",
        "tgn:7012149",
        "tgn:2000449",
        "tgn:7007248",
        "tgn:7029392"
    ],
    "tgn:id":2193428,
    "tgn:name":"Brenham Branch",
    "tgn:placetype":[
        "aat:300008699"
    ]
},
  "bbox": [],
  "geometry": {"coordinates":[-83.2167,32.7667],"type":"Point"}
}