{
  "id": 2500042,
  "type": "Feature",
  "properties": {
    "tgn:hierarchy":[
        "tgn:2500042",
        "tgn:1000001",
        "tgn:7012149",
        "tgn:2002291",
        "tgn:7013961",
        "tgn:7029392"
    ],
    "tgn:id":2500042,
    "tgn:name":"McCray Ridge",
    "tgn:placetype":[
        "aat:300266640"
    ]
},
  "bbox": [],
  "geometry": {"coordinates":[-79.65,38.85],"type":"Point"}
}