<<<<<<< HEAD
{
  "id": 7243839,
  "type": "Feature",
  "properties": {
    "tgn:hierarchy":[
        "tgn:7243839",
        "tgn:7003466",
        "tgn:1000003",
        "tgn:1000063",
        "tgn:4012014",
        "tgn:7029392"
    ],
    "tgn:id":7243839,
    "tgn:name":"Insevaux",
    "tgn:placetype":[
        "aat:300008347"
    ]
},
  "bbox": [],
  "geometry": {"coordinates":[4.791276,50.430069],"type":"Point"}
}
=======
{"geometry":{"type":"Point","coordinates":[4.791276,50.430069]},"type":"Feature","properties":{"hierarchy":["tgn:7243839","tgn:7003466","tgn:1000003","tgn:1000063","tgn:4012014","tgn:7029392"],"placetype":["aat:300008347"],"id":7243839,"name:xx":"Insevaux"}}
>>>>>>> 03f74aca74312dbeaf24d7e61306dd6a786dc3d0
