{
  "id": 2146050,
  "type": "Feature",
  "properties": {
    "tgn:hierarchy":[
        "tgn:2146050",
        "tgn:1002366",
        "tgn:1000001",
        "tgn:7012149",
        "tgn:7007159",
        "tgn:7029392"
    ],
    "tgn:id":2146050,
    "tgn:name":"Ball Pond Brook",
    "tgn:placetype":[
        "aat:300008699"
    ]
},
  "bbox": [],
  "geometry": {"coordinates":[-73.5167,41.45],"type":"Point"}
}