{
  "id": 7375582,
  "type": "Feature",
  "properties": {
    "tgn:hierarchy":[
        "tgn:7375582",
        "tgn:7005584",
        "tgn:1000001",
        "tgn:7005560",
        "tgn:7029392"
    ],
    "tgn:id":7375582,
    "tgn:name":"La Quemada",
    "tgn:placetype":[
        "aat:300008347"
    ]
},
  "bbox": [],
  "geometry": {"coordinates":[-101.116667,21.316667],"type":"Point"}
}