{
  "id": 7276579,
  "type": "Feature",
  "properties": {
    "tgn:hierarchy":[
        "tgn:7276579",
        "tgn:1001699",
        "tgn:1000049",
        "tgn:1000002",
        "tgn:7029392"
    ],
    "tgn:id":7276579,
    "tgn:name":"Puchilco",
    "tgn:placetype":[
        "aat:300008347"
    ]
},
  "bbox": [],
  "geometry": {"coordinates":[-73.591944,-42.594167],"type":"Point"}
}