{
  "id": 2471238,
  "type": "Feature",
  "properties": {
    "tgn:hierarchy":[
        "tgn:2471238",
        "tgn:1000001",
        "tgn:2001181",
        "tgn:7012149",
        "tgn:7007523",
        "tgn:7029392"
    ],
    "tgn:id":2471238,
    "tgn:name":"Lost Hollow",
    "tgn:placetype":[
        "aat:300008761"
    ]
},
  "bbox": [],
  "geometry": {"coordinates":[-90.9167,37.0167],"type":"Point"}
}