{
  "id": 7486049,
  "type": "Feature",
  "properties": {
    "tgn:hierarchy":[
        "tgn:7486049",
        "tgn:1000004",
        "tgn:7001014",
        "tgn:1000141",
        "tgn:7029392"
    ],
    "tgn:id":7486049,
    "tgn:name":"Neihu Qiao",
    "tgn:placetype":[
        "aat:300007836"
    ]
},
  "bbox": [],
  "geometry": {"coordinates":[120.605278,23.714444],"type":"Point"}
}