{
  "id": 7469448,
  "type": "Feature",
  "properties": {
    "tgn:hierarchy":[
        "tgn:7469448",
        "tgn:1000004",
        "tgn:7471332",
        "tgn:1000141",
        "tgn:7029392"
    ],
    "tgn:id":7469448,
    "tgn:name":"Xiaomaobu",
    "tgn:placetype":[
        "aat:300008347"
    ]
},
  "bbox": [],
  "geometry": {"coordinates":[121.103889,24.838333],"type":"Point"}
}