<<<<<<< HEAD
{
  "id": 2765084,
  "type": "Feature",
  "properties": {
    "tgn:hierarchy":[
        "tgn:2765084",
        "tgn:1000001",
        "tgn:7012149",
        "tgn:2001712",
        "tgn:7007708",
        "tgn:7029392"
    ],
    "tgn:id":2765084,
    "tgn:name":"Whisky Spring",
    "tgn:placetype":[
        "aat:300008697"
    ]
},
  "bbox": [],
  "geometry": {"coordinates":[-120.8833,44.6833],"type":"Point"}
}
=======
{"geometry":{"type":"Point","coordinates":[-120.883300,44.683300]},"type":"Feature","properties":{"hierarchy":["tgn:2765084","tgn:1000001","tgn:7012149","tgn:2001712","tgn:7007708","tgn:7029392"],"placetype":["aat:300008697"],"id":2765084,"name:xx":"Whisky Spring"}}
>>>>>>> 03f74aca74312dbeaf24d7e61306dd6a786dc3d0
