{
  "id": 2192704,
  "type": "Feature",
  "properties": {
    "tgn:hierarchy":[
        "tgn:2192704",
        "tgn:1000001",
        "tgn:7012149",
        "tgn:2002264",
        "tgn:7013961",
        "tgn:7029392"
    ],
    "tgn:id":2192704,
    "tgn:name":"Brants Cave",
    "tgn:placetype":[
        "aat:300008746"
    ]
},
  "bbox": [],
  "geometry": {"coordinates":[-80.4167,37.8333],"type":"Point"}
}