{
  "id": 2327013,
  "type": "Feature",
  "properties": {
    "tgn:hierarchy":[
        "tgn:2327013",
        "tgn:1000001",
        "tgn:7012149",
        "tgn:1002924",
        "tgn:7007568",
        "tgn:7029392"
    ],
    "tgn:id":2327013,
    "tgn:name":"Fireplace Neck",
    "tgn:placetype":[
        "aat:300008850"
    ]
},
  "bbox": [],
  "geometry": {"coordinates":[-72.8833,40.75],"type":"Point"}
}