<<<<<<< HEAD
{
  "id": 7111770,
  "type": "Feature",
  "properties": {
    "tgn:hierarchy":[
        "tgn:7111770",
        "tgn:7003669",
        "tgn:1000003",
        "tgn:7000084",
        "tgn:7029392"
    ],
    "tgn:id":7111770,
    "tgn:name":"Rossfelden",
    "tgn:placetype":[
        "aat:300387200"
    ]
},
  "bbox": [],
  "geometry": {"coordinates":[13.05,48.716667],"type":"Point"}
}
=======
{"geometry":{"type":"Point","coordinates":[13.050000,48.716667]},"type":"Feature","properties":{"hierarchy":["tgn:7111770","tgn:7003669","tgn:1000003","tgn:7000084","tgn:7029392"],"placetype":["aat:300387200"],"id":7111770,"name:xx":"Rossfelden"}}
>>>>>>> 03f74aca74312dbeaf24d7e61306dd6a786dc3d0
