{
  "id": 7056376,
  "type": "Feature",
  "properties": {
    "tgn:hierarchy":[
        "tgn:7056376",
        "tgn:7005765",
        "tgn:1000003",
        "tgn:7003237",
        "tgn:1000080",
        "tgn:7029392"
    ],
    "tgn:id":7056376,
    "tgn:name":"Odolo",
    "tgn:placetype":[
        "aat:300008347"
    ]
},
  "bbox": [],
  "geometry": {"coordinates":[10.383333,45.65],"type":"Point"}
}