{
  "id": 7465016,
  "type": "Feature",
  "properties": {
    "tgn:hierarchy":[
        "tgn:7465016",
        "tgn:7002443",
        "tgn:1000003",
        "tgn:7018993",
        "tgn:7008591",
        "tgn:7029392"
    ],
    "tgn:id":7465016,
    "tgn:name:en":"Abercastle",
    "tgn:placetype":[
        "aat:300008347"
    ]
},
  "bbox": [],
  "geometry": {"coordinates":[-5.125833,51.959444],"type":"Point"}
}