{
  "id": 7385117,
  "type": "Feature",
  "properties": {
    "tgn:hierarchy":[
        "tgn:7385117",
        "tgn:7005581",
        "tgn:1000001",
        "tgn:7005560",
        "tgn:7029392"
    ],
    "tgn:id":7385117,
    "tgn:name":"Molino",
    "tgn:placetype":[
        "aat:300007783"
    ]
},
  "bbox": [],
  "geometry": {"coordinates":[-105.816667,26.916667],"type":"Point"}
}