{
  "id": 7449171,
  "type": "Feature",
  "properties": {
    "tgn:hierarchy":[
        "tgn:7449171",
        "tgn:7002445",
        "tgn:1000003",
        "tgn:7008165",
        "tgn:7008591",
        "tgn:7029392"
    ],
    "tgn:id":7449171,
    "tgn:name:en":"Seal Skears",
    "tgn:placetype":[
        "aat:300386918"
    ]
},
  "bbox": [],
  "geometry": {"coordinates":[-1.516667,55.233333],"type":"Point"}
}