{
  "id": 7238731,
  "type": "Feature",
  "properties": {
    "tgn:hierarchy":[
        "tgn:7238731",
        "tgn:7007877",
        "tgn:1000003",
        "tgn:1000063",
        "tgn:4012014",
        "tgn:7029392"
    ],
    "tgn:id":7238731,
    "tgn:name":"Ferme Gavre",
    "tgn:placetype":[
        "aat:300000206"
    ]
},
  "bbox": [],
  "geometry": {"coordinates":[3.666667,50.666667],"type":"Point"}
}