{
  "id": 2749028,
  "type": "Feature",
  "properties": {
    "tgn:hierarchy":[
        "tgn:2749028",
        "tgn:1000001",
        "tgn:2001410",
        "tgn:7012149",
        "tgn:7007526",
        "tgn:7029392"
    ],
    "tgn:id":2749028,
    "tgn:name":"Wallace Canyon",
    "tgn:placetype":[
        "aat:300008761"
    ]
},
  "bbox": [],
  "geometry": {"coordinates":[-115.6833,36.2833],"type":"Point"}
}