{
  "id": 7070309,
  "type": "Feature",
  "properties": {
    "tgn:hierarchy":[
        "tgn:7070309",
        "tgn:1000003",
        "tgn:7003678",
        "tgn:7000084",
        "tgn:7029392"
    ],
    "tgn:id":7070309,
    "tgn:name":"Steinbach am Taunus",
    "tgn:placetype":[
        "aat:300008347"
    ]
},
  "bbox": [],
  "geometry": {"coordinates":[8.566667,50.166667],"type":"Point"}
}