{
  "id": 7130834,
  "type": "Feature",
  "properties": {
    "tgn:hierarchy":[
        "tgn:7130834",
        "tgn:1000003",
        "tgn:7000094",
        "tgn:7000084",
        "tgn:7029392"
    ],
    "tgn:id":7130834,
    "tgn:name":"Markow",
    "tgn:placetype":[
        "aat:300008347"
    ]
},
  "bbox": [],
  "geometry": {"coordinates":[13.016667,53.733333],"type":"Point"}
}