{
  "id": 7305720,
  "type": "Feature",
  "properties": {
    "tgn:hierarchy":[
        "tgn:7305720",
        "tgn:1001439",
        "tgn:1000003",
        "tgn:7002797",
        "tgn:1000095",
        "tgn:7029392"
    ],
    "tgn:id":7305720,
    "tgn:name":"Mazarron, Ensenada de",
    "tgn:placetype":[
        "aat:300132316"
    ]
},
  "bbox": [],
  "geometry": {"coordinates":[-1.216667,37.55],"type":"Point"}
}