{
  "id": 7135704,
  "type": "Feature",
  "properties": {
    "tgn:hierarchy":[
        "tgn:7135704",
        "tgn:7003669",
        "tgn:1000003",
        "tgn:7000084",
        "tgn:7029392"
    ],
    "tgn:id":7135704,
    "tgn:name":"M\u00f6slberg",
    "tgn:placetype":[
        "aat:300387173"
    ]
},
  "bbox": [],
  "geometry": {"coordinates":[13.733333,48.633333],"type":"Point"}
}