{
  "id": 2075037,
  "type": "Feature",
  "properties": {
    "tgn:hierarchy":[
        "tgn:2075037",
        "tgn:1000001",
        "tgn:7012149",
        "tgn:2001493",
        "tgn:7007709",
        "tgn:7029392"
    ],
    "tgn:id":2075037,
    "tgn:name":"Hazelwood Park",
    "tgn:placetype":[
        "aat:300008347",
        "aat:300387210"
    ]
},
  "bbox": [],
  "geometry": {"coordinates":[-77.6833,35.85],"type":"Point"}
}