{
  "id": 7545745,
  "type": "Feature",
  "properties": {
    "tgn:hierarchy":[
        "tgn:7545745",
        "tgn:1000004",
        "tgn:7000198",
        "tgn:1001894",
        "tgn:7029392"
    ],
    "tgn:id":7545745,
    "tgn:name:en":"Barr\u0101 S\u0101gar",
    "tgn:placetype":[
        "aat:300008347"
    ]
},
  "bbox": [],
  "geometry": {"coordinates":[80.359586,22.711037],"type":"Point"}
}