{
  "id": 2181665,
  "type": "Feature",
  "properties": {
    "tgn:hierarchy":[
        "tgn:2181665",
        "tgn:1000001",
        "tgn:7012149",
        "tgn:2002060",
        "tgn:7007826",
        "tgn:7029392"
    ],
    "tgn:id":2181665,
    "tgn:name":"Blue Hole",
    "tgn:placetype":[
        "aat:300008680"
    ]
},
  "bbox": [],
  "geometry": {"coordinates":[-99.95,29.95],"type":"Point"}
}