{
  "id": 2183872,
  "type": "Feature",
  "properties": {
    "tgn:hierarchy":[
        "tgn:2183872",
        "tgn:1000001",
        "tgn:7012149",
        "tgn:7007568",
        "tgn:7029392"
    ],
    "tgn:id":2183872,
    "tgn:name":"Boardman Creek",
    "tgn:placetype":[
        "aat:300008706"
    ]
},
  "bbox": [],
  "geometry": {"coordinates":[-76.7833,42.55],"type":"Point"}
}