{
  "id": 2508091,
  "type": "Feature",
  "properties": {
    "tgn:hierarchy":[
        "tgn:2508091",
        "tgn:1000001",
        "tgn:7012149",
        "tgn:2000995",
        "tgn:7007520",
        "tgn:7029392"
    ],
    "tgn:id":2508091,
    "tgn:name":"Middle Branch Cass River",
    "tgn:placetype":[
        "aat:300008707"
    ]
},
  "bbox": [],
  "geometry": {"coordinates":[-82.8833,43.3667],"type":"Point"}
}