{
  "id": 7352005,
  "type": "Feature",
  "properties": {
    "tgn:hierarchy":[
        "tgn:7352005",
        "tgn:1000001",
        "tgn:7005597",
        "tgn:7005560",
        "tgn:7029392"
    ],
    "tgn:id":7352005,
    "tgn:name":"Barra el Tordo",
    "tgn:placetype":[
        "aat:300008347"
    ]
},
  "bbox": [],
  "geometry": {"coordinates":[-97.766667,23.05],"type":"Point"}
}