{
  "id": 2195590,
  "type": "Feature",
  "properties": {
    "tgn:hierarchy":[
        "tgn:2195590",
        "tgn:1000001",
        "tgn:1002714",
        "tgn:7012149",
        "tgn:7007159",
        "tgn:7029392"
    ],
    "tgn:id":2195590,
    "tgn:name":"Broad Brook",
    "tgn:placetype":[
        "aat:300008699"
    ]
},
  "bbox": [],
  "geometry": {"coordinates":[-71.9333,41.5167],"type":"Point"}
}