{
  "id": 2525230,
  "type": "Feature",
  "properties": {
    "tgn:hierarchy":[
        "tgn:2525230",
        "tgn:1000001",
        "tgn:7012149",
        "tgn:1002553",
        "tgn:7007920",
        "tgn:7029392"
    ],
    "tgn:id":2525230,
    "tgn:name":"Morrison Canyon",
    "tgn:placetype":[
        "aat:300008761"
    ]
},
  "bbox": [],
  "geometry": {"coordinates":[-120.85,47.1167],"type":"Point"}
}