{
  "id": 7401431,
  "type": "Feature",
  "properties": {
    "tgn:hierarchy":[
        "tgn:7401431",
        "tgn:1000001",
        "tgn:7005599",
        "tgn:7005560",
        "tgn:7029392"
    ],
    "tgn:id":7401431,
    "tgn:name":"La Victoria",
    "tgn:placetype":[
        "aat:300008347"
    ]
},
  "bbox": [],
  "geometry": {"coordinates":[-94.999444,17.831944],"type":"Point"}
}