{
  "id": 7460175,
  "type": "Feature",
  "properties": {
    "tgn:hierarchy":[
        "tgn:7460175",
        "tgn:7002444",
        "tgn:1000003",
        "tgn:7029508",
        "tgn:7008591",
        "tgn:7029392"
    ],
    "tgn:id":7460175,
    "tgn:name:en":"Horse, Stack of the",
    "tgn:placetype":[
        "aat:300011692"
    ]
},
  "bbox": [],
  "geometry": {"coordinates":[-1.016667,60.516667],"type":"Point"}
}