<<<<<<< HEAD
{
  "id": 2157744,
  "type": "Feature",
  "properties": {
    "tgn:hierarchy":[
        "tgn:2157744",
        "tgn:1000001",
        "tgn:7012149",
        "tgn:1002624",
        "tgn:7007568",
        "tgn:7029392"
    ],
    "tgn:id":2157744,
    "tgn:name":"Beaver Hill",
    "tgn:placetype":[
        "aat:300008798"
    ]
},
  "bbox": [],
  "geometry": {"coordinates":[-75.3,42.8],"type":"Point"}
}
=======
{"geometry":{"type":"Point","coordinates":[-75.300000,42.800000]},"type":"Feature","properties":{"hierarchy":["tgn:2157744","tgn:1000001","tgn:7012149","tgn:1002624","tgn:7007568","tgn:7029392"],"placetype":["aat:300008798"],"id":2157744,"name:xx":"Beaver Hill"}}
>>>>>>> 03f74aca74312dbeaf24d7e61306dd6a786dc3d0
