{
  "id": 7565038,
  "type": "Feature",
  "properties": {
    "tgn:hierarchy":[
        "tgn:7565038",
        "tgn:1000004",
        "tgn:7000198",
        "tgn:7016722",
        "tgn:7029392"
    ],
    "tgn:id":7565038,
    "tgn:name:en":"Kundanpura",
    "tgn:placetype":[
        "aat:300008347"
    ]
},
  "bbox": [],
  "geometry": {"coordinates":[79.303214,26.126171],"type":"Point"}
}