{
  "id": 2238880,
  "type": "Feature",
  "properties": {
    "tgn:hierarchy":[
        "tgn:2238880",
        "tgn:1000001",
        "tgn:7012149",
        "tgn:1002645",
        "tgn:7007920",
        "tgn:7029392"
    ],
    "tgn:id":2238880,
    "tgn:name":"Christine, Lake",
    "tgn:placetype":[
        "aat:300008680",
        "aat:300006191"
    ]
},
  "bbox": [],
  "geometry": {"coordinates":[-122.95,47.4667],"type":"Point"}
}