{
  "id": 2180459,
  "type": "Feature",
  "properties": {
    "tgn:hierarchy":[
        "tgn:2180459",
        "tgn:1000001",
        "tgn:7012149",
        "tgn:7029392"
    ],
    "tgn:id":2180459,
    "tgn:name":"Blood River",
    "tgn:placetype":[
        "aat:300008707"
    ]
},
  "bbox": [],
  "geometry": {"coordinates":[-88.2167,36.4333],"type":"Point"}
}