<<<<<<< HEAD
{
  "id": 7373087,
  "type": "Feature",
  "properties": {
    "tgn:hierarchy":[
        "tgn:7373087",
        "tgn:1000001",
        "tgn:7005595",
        "tgn:7005560",
        "tgn:7029392"
    ],
    "tgn:id":7373087,
    "tgn:name":"La Laja",
    "tgn:placetype":[
        "aat:300008347"
    ]
},
  "bbox": [],
  "geometry": {"coordinates":[-107.433333,25.4],"type":"Point"}
}
=======
{"geometry":{"type":"Point","coordinates":[-107.433333,25.400000]},"type":"Feature","properties":{"hierarchy":["tgn:7373087","tgn:1000001","tgn:7005595","tgn:7005560","tgn:7029392"],"placetype":["aat:300008347"],"id":7373087,"name:xx":"La Laja"}}
>>>>>>> 03f74aca74312dbeaf24d7e61306dd6a786dc3d0
