{
  "id": 1100368,
  "type": "Feature",
  "properties": {
    "tgn:hierarchy":[
        "tgn:1100368",
        "tgn:1000003",
        "tgn:7003689",
        "tgn:7000084",
        "tgn:7029392"
    ],
    "tgn:id":1100368,
    "tgn:name":"Wartburg",
    "tgn:placetype":[
        "aat:300006891"
    ]
},
  "bbox": [],
  "geometry": {"coordinates":[10.283333,50.95],"type":"Point"}
}