{
  "id": 7416872,
  "type": "Feature",
  "properties": {
    "tgn:hierarchy":[
        "tgn:7416872",
        "tgn:1000001",
        "tgn:7005591",
        "tgn:7005560",
        "tgn:7029392"
    ],
    "tgn:id":7416872,
    "tgn:name:es":"San Alejo",
    "tgn:placetype":[
        "aat:300008347"
    ]
},
  "bbox": [],
  "geometry": {"coordinates":[-96.725556,17.904444],"type":"Point"}
}