<<<<<<< HEAD
{
  "id": 7112897,
  "type": "Feature",
  "properties": {
    "tgn:hierarchy":[
        "tgn:7112897",
        "tgn:7003669",
        "tgn:1000003",
        "tgn:7000084",
        "tgn:7029392"
    ],
    "tgn:id":7112897,
    "tgn:name":"Rosenhof",
    "tgn:placetype":[
        "aat:300000206"
    ]
},
  "bbox": [],
  "geometry": {"coordinates":[12.016667,50.083333],"type":"Point"}
}
=======
{"geometry":{"type":"Point","coordinates":[12.016667,50.083333]},"type":"Feature","properties":{"hierarchy":["tgn:7112897","tgn:7003669","tgn:1000003","tgn:7000084","tgn:7029392"],"placetype":["aat:300000206"],"id":7112897,"name:xx":"Rosenhof"}}
>>>>>>> 03f74aca74312dbeaf24d7e61306dd6a786dc3d0
