{
  "id": 2437175,
  "type": "Feature",
  "properties": {
    "tgn:hierarchy":[
        "tgn:2437175",
        "tgn:1000001",
        "tgn:7012149",
        "tgn:2000905",
        "tgn:7007256",
        "tgn:7029392"
    ],
    "tgn:id":2437175,
    "tgn:name":"Kimball Branch",
    "tgn:placetype":[
        "aat:300008699"
    ]
},
  "bbox": [],
  "geometry": {"coordinates":[-89.9833,30.5333],"type":"Point"}
}