{
  "id": 7571504,
  "type": "Feature",
  "properties": {
    "tgn:hierarchy":[
        "tgn:7571504",
        "tgn:1000004",
        "tgn:1001871",
        "tgn:7000198",
        "tgn:7029392"
    ],
    "tgn:id":7571504,
    "tgn:name:en":"Jasia Railroad Station",
    "tgn:placetype":[
        "aat:300007783"
    ]
},
  "bbox": [],
  "geometry": {"coordinates":[76.654133,29.01805],"type":"Point"}
}