{
  "id": 2311046,
  "type": "Feature",
  "properties": {
    "tgn:hierarchy":[
        "tgn:2311046",
        "tgn:1000001",
        "tgn:7012149",
        "tgn:1002594",
        "tgn:7007920",
        "tgn:7029392"
    ],
    "tgn:id":2311046,
    "tgn:name":"Eden Valley",
    "tgn:placetype":[
        "aat:300008761"
    ]
},
  "bbox": [],
  "geometry": {"coordinates":[-122.6667,46.3833],"type":"Point"}
}