{
  "id": 2342966,
  "type": "Feature",
  "properties": {
    "tgn:hierarchy":[
        "tgn:2342966",
        "tgn:1000001",
        "tgn:2001413",
        "tgn:7012149",
        "tgn:7007526",
        "tgn:7029392"
    ],
    "tgn:id":2342966,
    "tgn:name":"Fuzzy Spring",
    "tgn:placetype":[
        "aat:300008697"
    ]
},
  "bbox": [],
  "geometry": {"coordinates":[-116.2667,40.6167],"type":"Point"}
}