{
  "id": 7204413,
  "type": "Feature",
  "properties": {
    "tgn:hierarchy":[
        "tgn:7204413",
        "tgn:1000003",
        "tgn:7003677",
        "tgn:7000084",
        "tgn:7029392"
    ],
    "tgn:id":7204413,
    "tgn:name":"Bruckhausen",
    "tgn:placetype":[
        "aat:300008347"
    ]
},
  "bbox": [],
  "geometry": {"coordinates":[6.333333,51.35],"type":"Point"}
}