{
  "id": 2473156,
  "type": "Feature",
  "properties": {
    "tgn:hierarchy":[
        "tgn:2473156",
        "tgn:1000001",
        "tgn:2000924",
        "tgn:7012149",
        "tgn:7007515",
        "tgn:7029392"
    ],
    "tgn:id":2473156,
    "tgn:name":"Lowell Ledge",
    "tgn:placetype":[
        "aat:300132348"
    ]
},
  "bbox": [],
  "geometry": {"coordinates":[-69.0667,44.0833],"type":"Point"}
}