{
  "id": 1123617,
  "type": "Feature",
  "properties": {
    "tgn:hierarchy":[
        "tgn:1123617",
        "tgn:7005685",
        "tgn:1000001",
        "tgn:7013154",
        "tgn:7029392"
    ],
    "tgn:id":1123617,
    "tgn:name":"East Castor",
    "tgn:placetype":[
        "aat:300008707"
    ]
},
  "bbox": [],
  "geometry": {"coordinates":[-75.2833,45.2667],"type":"Point"}
}