{
  "id": 7065950,
  "type": "Feature",
  "properties": {
    "tgn:hierarchy":[
        "tgn:7065950",
        "tgn:7003692",
        "tgn:1000003",
        "tgn:7000084",
        "tgn:7029392"
    ],
    "tgn:id":7065950,
    "tgn:name":"Turner",
    "tgn:placetype":[
        "aat:300387200"
    ]
},
  "bbox": [],
  "geometry": {"coordinates":[8.116667,47.966667],"type":"Point"}
}