{
  "id": 2362696,
  "type": "Feature",
  "properties": {
    "tgn:hierarchy":[
        "tgn:2362696",
        "tgn:1000001",
        "tgn:7012149",
        "tgn:7015817",
        "tgn:7007568",
        "tgn:7029392"
    ],
    "tgn:id":2362696,
    "tgn:name":"Great Fresh Kills",
    "tgn:placetype":[
        "aat:300008699"
    ]
},
  "bbox": [],
  "geometry": {"coordinates":[-74.1833,40.5667],"type":"Point"}
}