{
  "id": 2711115,
  "type": "Feature",
  "properties": {
    "tgn:hierarchy":[
        "tgn:2711115",
        "tgn:1000001",
        "tgn:7012149",
        "tgn:2000435",
        "tgn:7007248",
        "tgn:7029392"
    ],
    "tgn:id":2711115,
    "tgn:name":"Tanner Cove",
    "tgn:placetype":[
        "aat:300132316"
    ]
},
  "bbox": [],
  "geometry": {"coordinates":[-84.0167,34.8167],"type":"Point"}
}