{
  "id": 7118176,
  "type": "Feature",
  "properties": {
    "tgn:hierarchy":[
        "tgn:7118176",
        "tgn:1000003",
        "tgn:7003688",
        "tgn:7000084",
        "tgn:7029392"
    ],
    "tgn:id":7118176,
    "tgn:name":"Oster-Offenb\u00fclldeich",
    "tgn:placetype":[
        "aat:300387200"
    ]
},
  "bbox": [],
  "geometry": {"coordinates":[8.883333,54.383333],"type":"Point"}
}