{
  "id": 2028267,
  "type": "Feature",
  "properties": {
    "tgn:hierarchy":[
        "tgn:2028267",
        "tgn:1000001",
        "tgn:7012149",
        "tgn:2000523",
        "tgn:7007251",
        "tgn:7029392"
    ],
    "tgn:id":2028267,
    "tgn:name":"Herod",
    "tgn:placetype":[
        "aat:300008347"
    ]
},
  "bbox": [],
  "geometry": {"coordinates":[-88.4333,37.5667],"type":"Point"}
}