{
  "id": 7383081,
  "type": "Feature",
  "properties": {
    "tgn:hierarchy":[
        "tgn:7383081",
        "tgn:7005586",
        "tgn:1000001",
        "tgn:7005560",
        "tgn:7029392"
    ],
    "tgn:id":7383081,
    "tgn:name":"Panal, Cerro del",
    "tgn:placetype":[
        "aat:300008795"
    ]
},
  "bbox": [],
  "geometry": {"coordinates":[-104.866667,19.683333],"type":"Point"}
}