{
  "id": 7361674,
  "type": "Feature",
  "properties": {
    "tgn:hierarchy":[
        "tgn:7361674",
        "tgn:1000001",
        "tgn:1001906",
        "tgn:7005560",
        "tgn:7029392"
    ],
    "tgn:id":7361674,
    "tgn:name":"El Cantor",
    "tgn:placetype":[
        "aat:300008699"
    ]
},
  "bbox": [],
  "geometry": {"coordinates":[-105.016667,21.183333],"type":"Point"}
}