{
  "id": 2693414,
  "type": "Feature",
  "properties": {
    "tgn:hierarchy":[
        "tgn:2693414",
        "tgn:1000001",
        "tgn:7012149",
        "tgn:7029392"
    ],
    "tgn:id":2693414,
    "tgn:name":"Steins Creek",
    "tgn:placetype":[
        "aat:300008706"
    ]
},
  "bbox": [],
  "geometry": {"coordinates":[-108.9833,32.2333],"type":"Point"}
}