{
  "id": 7382661,
  "type": "Feature",
  "properties": {
    "tgn:hierarchy":[
        "tgn:7382661",
        "tgn:7005581",
        "tgn:1000001",
        "tgn:7005560",
        "tgn:7029392"
    ],
    "tgn:id":7382661,
    "tgn:name":"Palomas, Laguna de las",
    "tgn:placetype":[
        "aat:300008680"
    ]
},
  "bbox": [],
  "geometry": {"coordinates":[-106.15,29.233333],"type":"Point"}
}