{
  "id": 2628813,
  "type": "Feature",
  "properties": {
    "tgn:hierarchy":[
        "tgn:2628813",
        "tgn:1000001",
        "tgn:7006451",
        "tgn:7012149",
        "tgn:2000103",
        "tgn:7029392"
    ],
    "tgn:id":2628813,
    "tgn:name":"Rosalie Tank",
    "tgn:placetype":[
        "aat:300006191"
    ]
},
  "bbox": [],
  "geometry": {"coordinates":[-111.9333,34.1667],"type":"Point"}
}