{
  "id": 1094354,
  "type": "Feature",
  "properties": {
    "tgn:hierarchy":[
        "tgn:1094354",
        "tgn:7001242",
        "tgn:1001212",
        "tgn:1000201",
        "tgn:7029392"
    ],
    "tgn:id":1094354,
    "tgn:name":"Markundi",
    "tgn:placetype":[
        "aat:300008347"
    ]
},
  "bbox": [],
  "geometry": {"coordinates":[23.8167,11.55],"type":"Point"}
}