{
  "id": 7317527,
  "type": "Feature",
  "properties": {
    "tgn:hierarchy":[
        "tgn:7317527",
        "tgn:1001702",
        "tgn:1000049",
        "tgn:1000002",
        "tgn:7029392"
    ],
    "tgn:id":7317527,
    "tgn:name":"Cliff, Cerro",
    "tgn:placetype":[
        "aat:300008798"
    ]
},
  "bbox": [],
  "geometry": {"coordinates":[-68.516667,-52.333333],"type":"Point"}
}