{
  "id": 2166001,
  "type": "Feature",
  "properties": {
    "tgn:hierarchy":[
        "tgn:2166001",
        "tgn:1000001",
        "tgn:7012149",
        "tgn:2001708",
        "tgn:7007708",
        "tgn:7029392"
    ],
    "tgn:id":2166001,
    "tgn:name":"Big Baldy",
    "tgn:placetype":[
        "aat:300008798"
    ]
},
  "bbox": [],
  "geometry": {"coordinates":[-119.4667,44.15],"type":"Point"}
}