<<<<<<< HEAD
{
  "id": 2337871,
  "type": "Feature",
  "properties": {
    "tgn:hierarchy":[
        "tgn:2337871",
        "tgn:1000001",
        "tgn:7016098",
        "tgn:7012149",
        "tgn:7007516",
        "tgn:7029392"
    ],
    "tgn:id":2337871,
    "tgn:name":"Fox Harbor",
    "tgn:placetype":[
        "aat:300132316"
    ]
},
  "bbox": [],
  "geometry": {"coordinates":[-76.3833,38.1167],"type":"Point"}
}
=======
{"geometry":{"type":"Point","coordinates":[-76.383300,38.116700]},"type":"Feature","properties":{"hierarchy":["tgn:2337871","tgn:1000001","tgn:7016098","tgn:7012149","tgn:7007516","tgn:7029392"],"placetype":["aat:300132316"],"id":2337871,"name:xx":"Fox Harbor"}}
>>>>>>> 03f74aca74312dbeaf24d7e61306dd6a786dc3d0
