<<<<<<< HEAD
{
  "id": 2403978,
  "type": "Feature",
  "properties": {
    "tgn:hierarchy":[
        "tgn:2403978",
        "tgn:1000001",
        "tgn:2001702",
        "tgn:7012149",
        "tgn:7007708",
        "tgn:7029392"
    ],
    "tgn:id":2403978,
    "tgn:name":"Howell Creek",
    "tgn:placetype":[
        "aat:300008706"
    ]
},
  "bbox": [],
  "geometry": {"coordinates":[-123.9,43.5333],"type":"Point"}
}
=======
{"geometry":{"type":"Point","coordinates":[-123.900000,43.533300]},"type":"Feature","properties":{"hierarchy":["tgn:2403978","tgn:1000001","tgn:2001702","tgn:7012149","tgn:7007708","tgn:7029392"],"placetype":["aat:300008706"],"id":2403978,"name:xx":"Howell Creek"}}
>>>>>>> 03f74aca74312dbeaf24d7e61306dd6a786dc3d0
