{
  "id": 7257535,
  "type": "Feature",
  "properties": {
    "tgn:concordances":{
        "gn:id":"2758791"
    },
    "tgn:hierarchy":[
        "tgn:7257535",
        "tgn:1000003",
        "tgn:7006951",
        "tgn:7016845",
        "tgn:7029392"
    ],
    "tgn:id":7257535,
    "tgn:name:nl":"Blokdijk",
    "tgn:placetype":[
        "aat:300008347"
    ]
},
  "bbox": [],
  "geometry": {"coordinates":[5.15,52.65],"type":"Point"}
}