{
  "id": 2318226,
  "type": "Feature",
  "properties": {
    "tgn:hierarchy":[
        "tgn:2318226",
        "tgn:1000001",
        "tgn:1002260",
        "tgn:7012149",
        "tgn:7007920",
        "tgn:7029392"
    ],
    "tgn:id":2318226,
    "tgn:name":"Entiat Ditch",
    "tgn:placetype":[
        "aat:300006075"
    ]
},
  "bbox": [],
  "geometry": {"coordinates":[-120.2167,47.65],"type":"Point"}
}