<<<<<<< HEAD
{
  "id": 2765764,
  "type": "Feature",
  "properties": {
    "tgn:hierarchy":[
        "tgn:2765764",
        "tgn:1000001",
        "tgn:7012149",
        "tgn:2001449",
        "tgn:7007566",
        "tgn:7029392"
    ],
    "tgn:id":2765764,
    "tgn:name":"White Deposit",
    "tgn:placetype":[
        "aat:300000390"
    ]
},
  "bbox": [],
  "geometry": {"coordinates":[-106.3333,36.1333],"type":"Point"}
}
=======
{"geometry":{"type":"Point","coordinates":[-106.333300,36.133300]},"type":"Feature","properties":{"hierarchy":["tgn:2765764","tgn:1000001","tgn:7012149","tgn:2001449","tgn:7007566","tgn:7029392"],"placetype":["aat:300000390"],"id":2765764,"name:xx":"White Deposit"}}
>>>>>>> 03f74aca74312dbeaf24d7e61306dd6a786dc3d0
