{
  "id": 1037149,
  "type": "Feature",
  "properties": {
    "tgn:hierarchy":[
        "tgn:1037149",
        "tgn:1000003",
        "tgn:7000094",
        "tgn:7000084",
        "tgn:7029392"
    ],
    "tgn:id":1037149,
    "tgn:name":"L\u00fcdersdorf",
    "tgn:placetype":[
        "aat:300008347"
    ]
},
  "bbox": [],
  "geometry": {"coordinates":[14.066667,52.933333],"type":"Point"}
}