{
  "id": 2403499,
  "type": "Feature",
  "properties": {
    "tgn:hierarchy":[
        "tgn:2403499",
        "tgn:1000001",
        "tgn:7012149",
        "tgn:1002314",
        "tgn:7007240",
        "tgn:7029392"
    ],
    "tgn:id":2403499,
    "tgn:name":"Howard",
    "tgn:placetype":[
        "aat:300008347"
    ]
},
  "bbox": [],
  "geometry": {"coordinates":[-80.3333,25.6333],"type":"Point"}
}