{
  "id": 2135093,
  "type": "Feature",
  "properties": {
    "tgn:hierarchy":[
        "tgn:2135093",
        "tgn:1000001",
        "tgn:2002108",
        "tgn:7012149",
        "tgn:7007827",
        "tgn:7029392"
    ],
    "tgn:id":2135093,
    "tgn:name":"Antelope Valley Number Three Reservoir",
    "tgn:placetype":[
        "aat:300006191"
    ]
},
  "bbox": [],
  "geometry": {"coordinates":[-110.15,38.5167],"type":"Point"}
}