{
  "id": 7234249,
  "type": "Feature",
  "properties": {
    "tgn:hierarchy":[
        "tgn:7234249",
        "tgn:7011270",
        "tgn:7002674",
        "tgn:1000003",
        "tgn:1000074",
        "tgn:7029392"
    ],
    "tgn:id":7234249,
    "tgn:name":"Avesal\u00f3s, \u00d3rmos",
    "tgn:placetype":[
        "aat:300132316"
    ]
},
  "bbox": [],
  "geometry": {"coordinates":[24.433333,37.166667],"type":"Point"}
}