{
  "id": 2473128,
  "type": "Feature",
  "properties": {
    "tgn:hierarchy":[
        "tgn:2473128",
        "tgn:1000001",
        "tgn:7012149",
        "tgn:2001288",
        "tgn:7007524",
        "tgn:7029392"
    ],
    "tgn:id":2473128,
    "tgn:name":"Lowel Bitney Gulch",
    "tgn:placetype":[
        "aat:300008761"
    ]
},
  "bbox": [],
  "geometry": {"coordinates":[-112.1167,45.5167],"type":"Point"}
}