{
  "id": 2002077,
  "type": "Feature",
  "properties": {
    "tgn:hierarchy":[
        "tgn:2002077",
        "tgn:1000001",
        "tgn:7012149",
        "tgn:7007826",
        "tgn:7029392"
    ],
    "tgn:id":2002077,
    "tgn:name":"Sterling",
    "tgn:placetype":[
        "aat:300387145",
        "aat:300000771"
    ]
},
  "bbox": [],
  "geometry": {"coordinates":[-101.05,31.8333],"type":"Point"}
}