{
  "id": 2376177,
  "type": "Feature",
  "properties": {
    "tgn:hierarchy":[
        "tgn:2376177",
        "tgn:1000001",
        "tgn:7012149",
        "tgn:2000291",
        "tgn:7007240",
        "tgn:7029392"
    ],
    "tgn:id":2376177,
    "tgn:name":"Hard Labor Creek",
    "tgn:placetype":[
        "aat:300008706"
    ]
},
  "bbox": [],
  "geometry": {"coordinates":[-85.4667,30.6833],"type":"Point"}
}