{
  "id": 7091138,
  "type": "Feature",
  "properties": {
    "tgn:hierarchy":[
        "tgn:7091138",
        "tgn:7003692",
        "tgn:1000003",
        "tgn:7000084",
        "tgn:7029392"
    ],
    "tgn:id":7091138,
    "tgn:name":"Vogelholz",
    "tgn:placetype":[
        "aat:300008863"
    ]
},
  "bbox": [],
  "geometry": {"coordinates":[9.666667,48.116667],"type":"Point"}
}