{
  "id": 2439617,
  "type": "Feature",
  "properties": {
    "tgn:hierarchy":[
        "tgn:2439617",
        "tgn:1000001",
        "tgn:7012149",
        "tgn:2000544",
        "tgn:7007252",
        "tgn:7029392"
    ],
    "tgn:id":2439617,
    "tgn:name":"Kisling Creek",
    "tgn:placetype":[
        "aat:300008706"
    ]
},
  "bbox": [],
  "geometry": {"coordinates":[-87.1333,39.0667],"type":"Point"}
}