{
  "id": 2198857,
  "type": "Feature",
  "properties": {
    "tgn:hierarchy":[
        "tgn:2198857",
        "tgn:1000001",
        "tgn:7012149",
        "tgn:2002111",
        "tgn:7007827",
        "tgn:7029392"
    ],
    "tgn:id":2198857,
    "tgn:name":"Broze Knoll",
    "tgn:placetype":[
        "aat:300008798"
    ]
},
  "bbox": [],
  "geometry": {"coordinates":[-113.4167,38.1167],"type":"Point"}
}