{
  "id": 7386376,
  "type": "Feature",
  "properties": {
    "tgn:hierarchy":[
        "tgn:7386376",
        "tgn:7005586",
        "tgn:1000001",
        "tgn:7005560",
        "tgn:7029392"
    ],
    "tgn:id":7386376,
    "tgn:name":"Plan de Cervantes",
    "tgn:placetype":[
        "aat:300008347"
    ]
},
  "bbox": [],
  "geometry": {"coordinates":[-102.933333,19.85],"type":"Point"}
}