{
  "id": 7451008,
  "type": "Feature",
  "properties": {
    "tgn:hierarchy":[
        "tgn:7451008",
        "tgn:7002443",
        "tgn:7017242",
        "tgn:1000003",
        "tgn:7008591",
        "tgn:7029392"
    ],
    "tgn:id":7451008,
    "tgn:name:en":"Gartheli",
    "tgn:placetype":[
        "aat:300008347"
    ]
},
  "bbox": [],
  "geometry": {"coordinates":[-4.066667,52.183333],"type":"Point"}
}