{
  "id": 7561774,
  "type": "Feature",
  "properties": {
    "tgn:hierarchy":[
        "tgn:7561774",
        "tgn:1000004",
        "tgn:7000198",
        "tgn:7016722",
        "tgn:7029392"
    ],
    "tgn:id":7561774,
    "tgn:name:en":"Nagla Sev",
    "tgn:placetype":[
        "aat:300008347"
    ]
},
  "bbox": [],
  "geometry": {"coordinates":[79.327315,27.111324],"type":"Point"}
}