{
  "id": 7545468,
  "type": "Feature",
  "properties": {
    "tgn:hierarchy":[
        "tgn:7545468",
        "tgn:1000004",
        "tgn:7000198",
        "tgn:7031783",
        "tgn:7029392"
    ],
    "tgn:id":7545468,
    "tgn:name:en":"Barki Nad\u012b",
    "tgn:placetype":[
        "aat:300008699"
    ]
},
  "bbox": [],
  "geometry": {"coordinates":[85.044132,23.810611],"type":"Point"}
}