{
  "id": 7123087,
  "type": "Feature",
  "properties": {
    "tgn:hierarchy":[
        "tgn:7123087",
        "tgn:1000003",
        "tgn:7003689",
        "tgn:7000084",
        "tgn:7029392"
    ],
    "tgn:id":7123087,
    "tgn:name":"Neuenbeuthen",
    "tgn:placetype":[
        "aat:300008347"
    ]
},
  "bbox": [],
  "geometry": {"coordinates":[11.583333,50.583333],"type":"Point"}
}