{
  "id": 2566596,
  "type": "Feature",
  "properties": {
    "tgn:hierarchy":[
        "tgn:2566596",
        "tgn:1000001",
        "tgn:7012149",
        "tgn:1002758",
        "tgn:7007568",
        "tgn:7029392"
    ],
    "tgn:id":2566596,
    "tgn:name":"Pancake Shoal",
    "tgn:placetype":[
        "aat:300132348"
    ]
},
  "bbox": [],
  "geometry": {"coordinates":[-75.9833,43.2167],"type":"Point"}
}