{
  "id": 7096794,
  "type": "Feature",
  "properties": {
    "tgn:hierarchy":[
        "tgn:7096794",
        "tgn:1000003",
        "tgn:7003678",
        "tgn:7000084",
        "tgn:7029392"
    ],
    "tgn:id":7096794,
    "tgn:name":"Spechtbach",
    "tgn:placetype":[
        "aat:300008347"
    ]
},
  "bbox": [],
  "geometry": {"coordinates":[8.833333,49.566667],"type":"Point"}
}