{
  "id": 2379927,
  "type": "Feature",
  "properties": {
    "tgn:hierarchy":[
        "tgn:2379927",
        "tgn:7006450",
        "tgn:1000001",
        "tgn:7012149",
        "tgn:2124005",
        "tgn:7029392"
    ],
    "tgn:id":2379927,
    "tgn:name":"Hatbox Mesa",
    "tgn:placetype":[
        "aat:300008798"
    ]
},
  "bbox": [],
  "geometry": {"coordinates":[-152.7333,68.7167],"type":"Point"}
}