{
  "id": 7501835,
  "type": "Feature",
  "properties": {
    "tgn:hierarchy":[
        "tgn:7501835",
        "tgn:1000004",
        "tgn:7492971",
        "tgn:1000141",
        "tgn:7029392"
    ],
    "tgn:id":7501835,
    "tgn:name":"Shifen Erhao Qiao",
    "tgn:placetype":[
        "aat:300007836"
    ]
},
  "bbox": [],
  "geometry": {"coordinates":[120.827778,22.113611],"type":"Point"}
}