<<<<<<< HEAD
{
  "id": 7116160,
  "type": "Feature",
  "properties": {
    "tgn:hierarchy":[
        "tgn:7116160",
        "tgn:1000003",
        "tgn:7003676",
        "tgn:7000084",
        "tgn:7029392"
    ],
    "tgn:id":7116160,
    "tgn:name":"Ostdorf",
    "tgn:placetype":[
        "aat:300000745"
    ]
},
  "bbox": [],
  "geometry": {"coordinates":[7.0,53.683333],"type":"Point"}
}
=======
{"geometry":{"type":"Point","coordinates":[7.000000,53.683333]},"type":"Feature","properties":{"hierarchy":["tgn:7116160","tgn:1000003","tgn:7003676","tgn:7000084","tgn:7029392"],"placetype":["aat:300000745"],"id":7116160,"name:xx":"Ostdorf"}}
>>>>>>> 03f74aca74312dbeaf24d7e61306dd6a786dc3d0
