<<<<<<< HEAD
{
  "id": 2703831,
  "type": "Feature",
  "properties": {
    "tgn:hierarchy":[
        "tgn:2703831",
        "tgn:1000001",
        "tgn:7012149",
        "tgn:1002645",
        "tgn:7007920",
        "tgn:7029392"
    ],
    "tgn:id":2703831,
    "tgn:name":"Sunbeach",
    "tgn:placetype":[
        "aat:300008347"
    ]
},
  "bbox": [],
  "geometry": {"coordinates":[-122.8833,47.4167],"type":"Point"}
}
=======
{"geometry":{"type":"Point","coordinates":[-122.883300,47.416700]},"type":"Feature","properties":{"hierarchy":["tgn:2703831","tgn:1000001","tgn:7012149","tgn:1002645","tgn:7007920","tgn:7029392"],"placetype":["aat:300008347"],"id":2703831,"name:xx":"Sunbeach"}}
>>>>>>> 03f74aca74312dbeaf24d7e61306dd6a786dc3d0
