{
  "id": 2703831,
  "type": "Feature",
  "properties": {
    "tgn:hierarchy":[
        "tgn:2703831",
        "tgn:1000001",
        "tgn:7012149",
        "tgn:1002645",
        "tgn:7007920",
        "tgn:7029392"
    ],
    "tgn:id":2703831,
    "tgn:name":"Sunbeach",
    "tgn:placetype":[
        "aat:300008347"
    ]
},
  "bbox": [],
  "geometry": {"coordinates":[-122.8833,47.4167],"type":"Point"}
}