{
  "id": 2613334,
  "type": "Feature",
  "properties": {
    "tgn:hierarchy":[
        "tgn:2613334",
        "tgn:1000001",
        "tgn:7012149",
        "tgn:2002196",
        "tgn:7007919",
        "tgn:7029392"
    ],
    "tgn:id":2613334,
    "tgn:name":"Reed Creek",
    "tgn:placetype":[
        "aat:300008706"
    ]
},
  "bbox": [],
  "geometry": {"coordinates":[-81.35,36.95],"type":"Point"}
}