{
  "id": 2400143,
  "type": "Feature",
  "properties": {
    "tgn:hierarchy":[
        "tgn:2400143",
        "tgn:1000001",
        "tgn:2001634",
        "tgn:7012149",
        "tgn:7007707",
        "tgn:7029392"
    ],
    "tgn:id":2400143,
    "tgn:name":"Horse Creek",
    "tgn:placetype":[
        "aat:300008706"
    ]
},
  "bbox": [],
  "geometry": {"coordinates":[-95.5333,34.0167],"type":"Point"}
}