<<<<<<< HEAD
{
  "id": 2400143,
  "type": "Feature",
  "properties": {
    "tgn:hierarchy":[
        "tgn:2400143",
        "tgn:1000001",
        "tgn:2001634",
        "tgn:7012149",
        "tgn:7007707",
        "tgn:7029392"
    ],
    "tgn:id":2400143,
    "tgn:name":"Horse Creek",
    "tgn:placetype":[
        "aat:300008706"
    ]
},
  "bbox": [],
  "geometry": {"coordinates":[-95.5333,34.0167],"type":"Point"}
}
=======
{"geometry":{"type":"Point","coordinates":[-95.533300,34.016700]},"type":"Feature","properties":{"hierarchy":["tgn:2400143","tgn:1000001","tgn:2001634","tgn:7012149","tgn:7007707","tgn:7029392"],"placetype":["aat:300008706"],"id":2400143,"name:xx":"Horse Creek"}}
>>>>>>> 03f74aca74312dbeaf24d7e61306dd6a786dc3d0
