{
  "id": 1108443,
  "type": "Feature",
  "properties": {
    "tgn:hierarchy":[
        "tgn:1108443",
        "tgn:1000004",
        "tgn:7012215",
        "tgn:7006653",
        "tgn:7029392"
    ],
    "tgn:id":1108443,
    "tgn:name":"Krestovyy Pereval",
    "tgn:placetype":[
        "aat:300259572"
    ]
},
  "bbox": [],
  "geometry": {"coordinates":[44.5333,42.5333],"type":"Point"}
}