{
  "id": 2240797,
  "type": "Feature",
  "properties": {
    "tgn:hierarchy":[
        "tgn:2240797",
        "tgn:1000001",
        "tgn:7012149",
        "tgn:1002873",
        "tgn:7007568",
        "tgn:7029392"
    ],
    "tgn:id":2240797,
    "tgn:name":"Clapper Hollow",
    "tgn:placetype":[
        "aat:300008761"
    ]
},
  "bbox": [],
  "geometry": {"coordinates":[-74.6167,42.5333],"type":"Point"}
}