{
  "id": 7544112,
  "type": "Feature",
  "properties": {
    "tgn:hierarchy":[
        "tgn:7544112",
        "tgn:7001242",
        "tgn:7016833",
        "tgn:1001110",
        "tgn:7029392"
    ],
    "tgn:id":7544112,
    "tgn:name":"Maghrat al Ba\u1e29r\u012b, W\u0101d\u012b",
    "tgn:placetype":[
        "aat:300379998"
    ]
},
  "bbox": [],
  "geometry": {"coordinates":[32.472135,29.838668],"type":"Point"}
}