{
  "id": 7440202,
  "type": "Feature",
  "properties": {
    "tgn:hierarchy":[
        "tgn:7440202",
        "tgn:1000001",
        "tgn:7005591",
        "tgn:7005560",
        "tgn:7029392"
    ],
    "tgn:id":7440202,
    "tgn:name":"Santa Mar\u00eda Cortijos",
    "tgn:placetype":[
        "aat:300008347"
    ]
},
  "bbox": [],
  "geometry": {"coordinates":[-98.233333,16.45],"type":"Point"}
}