{
  "id": 2296829,
  "type": "Feature",
  "properties": {
    "tgn:hierarchy":[
        "tgn:2296829",
        "tgn:1000001",
        "tgn:7012149",
        "tgn:7007521",
        "tgn:7029392"
    ],
    "tgn:id":2296829,
    "tgn:name":"Dry Creek",
    "tgn:placetype":[
        "aat:300008706"
    ]
},
  "bbox": [],
  "geometry": {"coordinates":[-92.35,44.0667],"type":"Point"}
}