{
  "id": 7478916,
  "type": "Feature",
  "properties": {
    "tgn:hierarchy":[
        "tgn:7478916",
        "tgn:1000004",
        "tgn:7490934",
        "tgn:1000141",
        "tgn:7029392"
    ],
    "tgn:id":7478916,
    "tgn:name":"Shalunliao",
    "tgn:placetype":[
        "aat:300008347"
    ]
},
  "bbox": [],
  "geometry": {"coordinates":[120.11,23.147222],"type":"Point"}
}