{
  "id": 2727675,
  "type": "Feature",
  "properties": {
    "tgn:hierarchy":[
        "tgn:2727675",
        "tgn:1000001",
        "tgn:7012149",
        "tgn:7007240",
        "tgn:7029392"
    ],
    "tgn:id":2727675,
    "tgn:name":"Trail Ridge",
    "tgn:placetype":[
        "aat:300266640"
    ]
},
  "bbox": [],
  "geometry": {"coordinates":[-82.05,30.1833],"type":"Point"}
}