{
  "id": 2479966,
  "type": "Feature",
  "properties": {
    "tgn:hierarchy":[
        "tgn:2479966",
        "tgn:1000001",
        "tgn:7012149",
        "tgn:1002783",
        "tgn:7007251",
        "tgn:7029392"
    ],
    "tgn:id":2479966,
    "tgn:name":"Lake Fork Special Ditch",
    "tgn:placetype":[
        "aat:300008699"
    ]
},
  "bbox": [],
  "geometry": {"coordinates":[-88.4667,39.9667],"type":"Point"}
}