{
  "id": 1065959,
  "type": "Feature",
  "properties": {
    "tgn:hierarchy":[
        "tgn:1065959",
        "tgn:1000004",
        "tgn:7000190",
        "tgn:1000105",
        "tgn:7029392"
    ],
    "tgn:id":1065959,
    "tgn:name":"Tala",
    "tgn:placetype":[
        "aat:300008347"
    ]
},
  "bbox": [],
  "geometry": {"coordinates":[89.2667,22.7667],"type":"Point"}
}