{
  "id": 7230417,
  "type": "Feature",
  "properties": {
    "tgn:hierarchy":[
        "tgn:7230417",
        "tgn:7011330",
        "tgn:7002674",
        "tgn:1000003",
        "tgn:1000074",
        "tgn:7029392"
    ],
    "tgn:id":7230417,
    "tgn:name":"Kritin\u00eda",
    "tgn:placetype":[
        "aat:300008347"
    ]
},
  "bbox": [],
  "geometry": {"coordinates":[27.85,36.233333],"type":"Point"}
}