{
  "id": 1048560,
  "type": "Feature",
  "properties": {
    "tgn:hierarchy":[
        "tgn:1048560",
        "tgn:7003653",
        "tgn:1000003",
        "tgn:1000088",
        "tgn:7029392"
    ],
    "tgn:id":1048560,
    "tgn:name":"H\u00f8yanger",
    "tgn:placetype":[
        "aat:300008347"
    ]
},
  "bbox": [],
  "geometry": {"coordinates":[6.0833,61.2167],"type":"Point"}
}