<<<<<<< HEAD
{
  "id": 2765446,
  "type": "Feature",
  "properties": {
    "tgn:hierarchy":[
        "tgn:2765446",
        "tgn:1000001",
        "tgn:7012149",
        "tgn:1003022",
        "tgn:7007252",
        "tgn:7029392"
    ],
    "tgn:id":2765446,
    "tgn:name":"White Branch",
    "tgn:placetype":[
        "aat:300006075"
    ]
},
  "bbox": [],
  "geometry": {"coordinates":[-85.6333,41.2333],"type":"Point"}
}
=======
{"geometry":{"type":"Point","coordinates":[-85.633300,41.233300]},"type":"Feature","properties":{"hierarchy":["tgn:2765446","tgn:1000001","tgn:7012149","tgn:1003022","tgn:7007252","tgn:7029392"],"placetype":["aat:300006075"],"id":2765446,"name:xx":"White Branch"}}
>>>>>>> 03f74aca74312dbeaf24d7e61306dd6a786dc3d0
