{
  "id": 2643599,
  "type": "Feature",
  "properties": {
    "tgn:hierarchy":[
        "tgn:2643599",
        "tgn:1000001",
        "tgn:7012149",
        "tgn:2000852",
        "tgn:7007255",
        "tgn:7029392"
    ],
    "tgn:id":2643599,
    "tgn:name":"Sandy Poplar Ridge",
    "tgn:placetype":[
        "aat:300266640"
    ]
},
  "bbox": [],
  "geometry": {"coordinates":[-84.25,36.8667],"type":"Point"}
}