{
  "id": 7303598,
  "type": "Feature",
  "properties": {
    "tgn:hierarchy":[
        "tgn:7303598",
        "tgn:7002824",
        "tgn:1000003",
        "tgn:7002786",
        "tgn:1000095",
        "tgn:7029392"
    ],
    "tgn:id":7303598,
    "tgn:name":"O\u00eddos, Punta de los",
    "tgn:placetype":[
        "aat:300386846"
    ]
},
  "bbox": [],
  "geometry": {"coordinates":[-9.266667,42.883333],"type":"Point"}
}