{
  "id": 7092492,
  "type": "Feature",
  "properties": {
    "tgn:hierarchy":[
        "tgn:7092492",
        "tgn:7003669",
        "tgn:1000003",
        "tgn:7000084",
        "tgn:7029392"
    ],
    "tgn:id":7092492,
    "tgn:name":"Vorderbraunau",
    "tgn:placetype":[
        "aat:300008347"
    ]
},
  "bbox": [],
  "geometry": {"coordinates":[11.133333,47.616667],"type":"Point"}
}