{
  "id": 1018616,
  "type": "Feature",
  "properties": {
    "tgn:hierarchy":[
        "tgn:1018616",
        "tgn:1000001",
        "tgn:7005597",
        "tgn:7005560",
        "tgn:7029392"
    ],
    "tgn:id":1018616,
    "tgn:name":"Villa Mainero",
    "tgn:placetype":[
        "aat:300008347"
    ]
},
  "bbox": [],
  "geometry": {"coordinates":[-99.615278,24.560833],"type":"Point"}
}