<<<<<<< HEAD
{
  "id": 7355588,
  "type": "Feature",
  "properties": {
    "tgn:hierarchy":[
        "tgn:7355588",
        "tgn:1000001",
        "tgn:7005589",
        "tgn:7005560",
        "tgn:7029392"
    ],
    "tgn:id":7355588,
    "tgn:name":"Calandrias, Cerro de las",
    "tgn:placetype":[
        "aat:300008795"
    ]
},
  "bbox": [],
  "geometry": {"coordinates":[-100.583333,24.516667],"type":"Point"}
}
=======
{"geometry":{"type":"Point","coordinates":[-100.583333,24.516667]},"type":"Feature","properties":{"hierarchy":["tgn:7355588","tgn:1000001","tgn:7005589","tgn:7005560","tgn:7029392"],"placetype":["aat:300008795"],"id":7355588,"name:xx":"Calandrias, Cerro de las"}}
>>>>>>> 03f74aca74312dbeaf24d7e61306dd6a786dc3d0
