{
  "id": 1113424,
  "type": "Feature",
  "properties": {
    "tgn:hierarchy":[
        "tgn:1113424",
        "tgn:1000003",
        "tgn:7029392"
    ],
    "tgn:id":1113424,
    "tgn:name:de":"Mecklenburger Bucht",
    "tgn:placetype":[
        "aat:300132316"
    ]
},
  "bbox": [],
  "geometry": {"coordinates":[11.6667,54.3333],"type":"Point"}
}