{
  "id": 2192891,
  "type": "Feature",
  "properties": {
    "tgn:hierarchy":[
        "tgn:2192891",
        "tgn:1000001",
        "tgn:7016172",
        "tgn:7012149",
        "tgn:2000129",
        "tgn:7029392"
    ],
    "tgn:id":2192891,
    "tgn:name":"Bray Branch",
    "tgn:placetype":[
        "aat:300008699"
    ]
},
  "bbox": [],
  "geometry": {"coordinates":[-91.95,36.35],"type":"Point"}
}