{
  "id": 2060404,
  "type": "Feature",
  "properties": {
    "tgn:hierarchy":[
        "tgn:2060404",
        "tgn:1000001",
        "tgn:7012149",
        "tgn:1002288",
        "tgn:7007523",
        "tgn:7029392"
    ],
    "tgn:id":2060404,
    "tgn:name":"Saint Thomas",
    "tgn:placetype":[
        "aat:300008347"
    ]
},
  "bbox": [],
  "geometry": {"coordinates":[-92.2167,38.3667],"type":"Point"}
}