{
  "id": 2493739,
  "type": "Feature",
  "properties": {
    "tgn:hierarchy":[
        "tgn:2493739",
        "tgn:1000001",
        "tgn:7012149",
        "tgn:1002977",
        "tgn:7007240",
        "tgn:7029392"
    ],
    "tgn:id":2493739,
    "tgn:name":"Marsh Swamp",
    "tgn:placetype":[
        "aat:300008905"
    ]
},
  "bbox": [],
  "geometry": {"coordinates":[-81.1333,28.9333],"type":"Point"}
}