<<<<<<< HEAD
{
  "id": 2253265,
  "type": "Feature",
  "properties": {
    "tgn:hierarchy":[
        "tgn:2253265",
        "tgn:1000001",
        "tgn:7012149",
        "tgn:2000494",
        "tgn:7007250",
        "tgn:7029392"
    ],
    "tgn:id":2253265,
    "tgn:name":"Control Creek",
    "tgn:placetype":[
        "aat:300008706"
    ]
},
  "bbox": [],
  "geometry": {"coordinates":[-115.8,44.35],"type":"Point"}
}
=======
{"geometry":{"type":"Point","coordinates":[-115.800000,44.350000]},"type":"Feature","properties":{"hierarchy":["tgn:2253265","tgn:1000001","tgn:7012149","tgn:2000494","tgn:7007250","tgn:7029392"],"placetype":["aat:300008706"],"id":2253265,"name:xx":"Control Creek"}}
>>>>>>> 03f74aca74312dbeaf24d7e61306dd6a786dc3d0
