{
  "id": 1132869,
  "type": "Feature",
  "properties": {
    "tgn:hierarchy":[
        "tgn:1132869",
        "tgn:1000574",
        "tgn:1000002",
        "tgn:1000058",
        "tgn:7029392"
    ],
    "tgn:id":1132869,
    "tgn:name":"Colla, Arroyo",
    "tgn:placetype":[
        "aat:300008706"
    ]
},
  "bbox": [],
  "geometry": {"coordinates":[-57.3333,-34.3167],"type":"Point"}
}