{
  "id": 2525565,
  "type": "Feature",
  "properties": {
    "tgn:hierarchy":[
        "tgn:2525565",
        "tgn:1000001",
        "tgn:7012149",
        "tgn:2000203",
        "tgn:7007158",
        "tgn:7029392"
    ],
    "tgn:id":2525565,
    "tgn:name":"Mortimer",
    "tgn:placetype":[
        "aat:300008347"
    ]
},
  "bbox": [],
  "geometry": {"coordinates":[-105.3333,37.45],"type":"Point"}
}