{
  "id": 7261313,
  "type": "Feature",
  "properties": {
    "tgn:concordances":{
        "gn:id":"2755126"
    },
    "tgn:hierarchy":[
        "tgn:7261313",
        "tgn:1000003",
        "tgn:7003632",
        "tgn:7016845",
        "tgn:7029392"
    ],
    "tgn:id":7261313,
    "tgn:name:nl":"Groot Hitland",
    "tgn:placetype":[
        "aat:300008347"
    ]
},
  "bbox": [],
  "geometry": {"coordinates":[4.633333,51.933333],"type":"Point"}
}