{
  "id": 1136490,
  "type": "Feature",
  "properties": {
    "tgn:hierarchy":[
        "tgn:1136490",
        "tgn:7016581",
        "tgn:1000047",
        "tgn:7002455",
        "tgn:1000002",
        "tgn:7029392"
    ],
    "tgn:id":1136490,
    "tgn:name":"\u00c1gua Branca",
    "tgn:placetype":[
        "aat:300008347"
    ]
},
  "bbox": [],
  "geometry": {"coordinates":[-37.9167,-9.2833],"type":"Point"}
}