{
  "id": 2185145,
  "type": "Feature",
  "properties": {
    "tgn:hierarchy":[
        "tgn:2185145",
        "tgn:1000001",
        "tgn:7012149",
        "tgn:2002010",
        "tgn:7007826",
        "tgn:7029392"
    ],
    "tgn:id":2185145,
    "tgn:name":"Boggy Canyon",
    "tgn:placetype":[
        "aat:300008761"
    ]
},
  "bbox": [],
  "geometry": {"coordinates":[-104.3667,30.8833],"type":"Point"}
}