{
  "id": 7294014,
  "type": "Feature",
  "properties": {
    "tgn:hierarchy":[
        "tgn:7294014",
        "tgn:7002826",
        "tgn:7001158",
        "tgn:1000003",
        "tgn:1000095",
        "tgn:7029392"
    ],
    "tgn:id":7294014,
    "tgn:name":"Vidanes",
    "tgn:placetype":[
        "aat:300008347"
    ]
},
  "bbox": [],
  "geometry": {"coordinates":[-5.133333,42.766667],"type":"Point"}
}