{
  "id": 2594295,
  "type": "Feature",
  "properties": {
    "tgn:hierarchy":[
        "tgn:2594295",
        "tgn:1000001",
        "tgn:7012149",
        "tgn:2001258",
        "tgn:7007523",
        "tgn:7029392"
    ],
    "tgn:id":2594295,
    "tgn:name":"Porter Lake",
    "tgn:placetype":[
        "aat:300006191"
    ]
},
  "bbox": [],
  "geometry": {"coordinates":[-92.25,37.2167],"type":"Point"}
}