{
  "id": 2770738,
  "type": "Feature",
  "properties": {
    "tgn:hierarchy":[
        "tgn:2770738",
        "tgn:1000001",
        "tgn:7012149",
        "tgn:2002195",
        "tgn:7007919",
        "tgn:7029392"
    ],
    "tgn:id":2770738,
    "tgn:name":"Wildcat Cavern",
    "tgn:placetype":[
        "aat:300008746"
    ]
},
  "bbox": [],
  "geometry": {"coordinates":[-82.7333,36.8333],"type":"Point"}
}