{
  "id": 1021540,
  "type": "Feature",
  "properties": {
    "tgn:hierarchy":[
        "tgn:1021540",
        "tgn:1001941",
        "tgn:1000047",
        "tgn:7002458",
        "tgn:1000002",
        "tgn:7029392"
    ],
    "tgn:id":1021540,
    "tgn:name":"Guarani das Miss\u00f5es",
    "tgn:placetype":[
        "aat:300008347"
    ]
},
  "bbox": [],
  "geometry": {"coordinates":[-54.5667,-28.1333],"type":"Point"}
}