{
  "id": 2458933,
  "type": "Feature",
  "properties": {
    "tgn:hierarchy":[
        "tgn:2458933",
        "tgn:1000001",
        "tgn:7012149",
        "tgn:2001612",
        "tgn:7007706",
        "tgn:7029392"
    ],
    "tgn:id":2458933,
    "tgn:name":"Little Perigen Creek",
    "tgn:placetype":[
        "aat:300008706"
    ]
},
  "bbox": [],
  "geometry": {"coordinates":[-82.3167,38.6833],"type":"Point"}
}