{
  "id": 2315282,
  "type": "Feature",
  "properties": {
    "tgn:hierarchy":[
        "tgn:2315282",
        "tgn:1000001",
        "tgn:7012149",
        "tgn:2000206",
        "tgn:7007158",
        "tgn:7029392"
    ],
    "tgn:id":2315282,
    "tgn:name":"Ellington Reservoir",
    "tgn:placetype":[
        "aat:300006191"
    ]
},
  "bbox": [],
  "geometry": {"coordinates":[-107.75,39.0167],"type":"Point"}
}