{
  "id": 7286628,
  "type": "Feature",
  "properties": {
    "tgn:hierarchy":[
        "tgn:7286628",
        "tgn:1001702",
        "tgn:1000049",
        "tgn:1000002",
        "tgn:7029392"
    ],
    "tgn:id":7286628,
    "tgn:name":"Gu\u00eda, Islotes",
    "tgn:placetype":[
        "aat:300008791"
    ]
},
  "bbox": [],
  "geometry": {"coordinates":[-74.383333,-49.183333],"type":"Point"}
}