{
  "id": 7228285,
  "type": "Feature",
  "properties": {
    "tgn:hierarchy":[
        "tgn:7228285",
        "tgn:7011270",
        "tgn:7002674",
        "tgn:1000003",
        "tgn:1000074",
        "tgn:7029392"
    ],
    "tgn:id":7228285,
    "tgn:name":"Kolimv\u00edthra, \u00d3rmos",
    "tgn:placetype":[
        "aat:300132316"
    ]
},
  "bbox": [],
  "geometry": {"coordinates":[25.15,37.633333],"type":"Point"}
}