{
  "id": 7281891,
  "type": "Feature",
  "properties": {
    "tgn:hierarchy":[
        "tgn:7281891",
        "tgn:1001702",
        "tgn:1000049",
        "tgn:1000002",
        "tgn:7029392"
    ],
    "tgn:id":7281891,
    "tgn:name":"Stange, Fiordo",
    "tgn:placetype":[
        "aat:300008676"
    ]
},
  "bbox": [],
  "geometry": {"coordinates":[-74.75,-49.766667],"type":"Point"}
}