{
  "id": 2413300,
  "type": "Feature",
  "properties": {
    "tgn:hierarchy":[
        "tgn:2413300",
        "tgn:1000001",
        "tgn:7012149",
        "tgn:2001444",
        "tgn:7007566",
        "tgn:7029392"
    ],
    "tgn:id":2413300,
    "tgn:name":"International Tank",
    "tgn:placetype":[
        "aat:300006191"
    ]
},
  "bbox": [],
  "geometry": {"coordinates":[-108.1667,31.7833],"type":"Point"}
}