{
  "id": 2661631,
  "type": "Feature",
  "properties": {
    "tgn:hierarchy":[
        "tgn:2661631",
        "tgn:1002146",
        "tgn:1000001",
        "tgn:7012149",
        "tgn:7007157",
        "tgn:7029392"
    ],
    "tgn:id":2661631,
    "tgn:name":"Shriner Lake",
    "tgn:placetype":[
        "aat:300008680"
    ]
},
  "bbox": [],
  "geometry": {"coordinates":[-120.15,38.5333],"type":"Point"}
}