{
  "id": 7591293,
  "type": "Feature",
  "properties": {
    "tgn:hierarchy":[
        "tgn:7591293",
        "tgn:1000004",
        "tgn:7000198",
        "tgn:7000799",
        "tgn:7029392"
    ],
    "tgn:id":7591293,
    "tgn:name:en":"Manna",
    "tgn:placetype":[
        "aat:300008347"
    ]
},
  "bbox": [],
  "geometry": {"coordinates":[74.450563,32.921719],"type":"Point"}
}