{
  "id": 7285779,
  "type": "Feature",
  "properties": {
    "tgn:hierarchy":[
        "tgn:7285779",
        "tgn:7016598",
        "tgn:1000049",
        "tgn:1000002",
        "tgn:7029392"
    ],
    "tgn:id":7285779,
    "tgn:name":"Providencia, Cerro",
    "tgn:placetype":[
        "aat:300008777"
    ]
},
  "bbox": [],
  "geometry": {"coordinates":[-69.233333,-24.55],"type":"Point"}
}