<<<<<<< HEAD
{
  "id": 7021236,
  "type": "Feature",
  "properties": {
    "tgn:hierarchy":[
        "tgn:7021236",
        "tgn:7002659",
        "tgn:1000001",
        "tgn:2000019",
        "tgn:7012149",
        "tgn:7029392"
    ],
    "tgn:id":7021236,
    "tgn:name":"Gantt Millpond",
    "tgn:placetype":[
        "aat:300006191"
    ]
},
  "bbox": [],
  "geometry": {"coordinates":[-86.4167,31.4],"type":"Point"}
}
=======
{"geometry":{"type":"Point","coordinates":[-86.416700,31.400000]},"type":"Feature","properties":{"hierarchy":["tgn:7021236","tgn:7002659","tgn:1000001","tgn:2000019","tgn:7012149","tgn:7029392"],"placetype":["aat:300006191"],"id":7021236,"name:xx":"Gantt Millpond"}}
>>>>>>> 03f74aca74312dbeaf24d7e61306dd6a786dc3d0
