<<<<<<< HEAD
{
  "id": 7110202,
  "type": "Feature",
  "properties": {
    "tgn:hierarchy":[
        "tgn:7110202",
        "tgn:1000003",
        "tgn:7003677",
        "tgn:7000084",
        "tgn:7029392"
    ],
    "tgn:id":7110202,
    "tgn:name":"P\u00fcsselb\u00fcren",
    "tgn:placetype":[
        "aat:300387200"
    ]
},
  "bbox": [],
  "geometry": {"coordinates":[7.666667,52.316667],"type":"Point"}
}
=======
{"geometry":{"type":"Point","coordinates":[7.666667,52.316667]},"type":"Feature","properties":{"hierarchy":["tgn:7110202","tgn:1000003","tgn:7003677","tgn:7000084","tgn:7029392"],"placetype":["aat:300387200"],"id":7110202,"name:xx":"P\u00fcsselb\u00fcren"}}
>>>>>>> 03f74aca74312dbeaf24d7e61306dd6a786dc3d0
