{
  "id": 7297382,
  "type": "Feature",
  "properties": {
    "tgn:hierarchy":[
        "tgn:7297382",
        "tgn:7001122",
        "tgn:1000003",
        "tgn:7002765",
        "tgn:1000095",
        "tgn:7029392"
    ],
    "tgn:id":7297382,
    "tgn:name":"Tagomago, Isla de",
    "tgn:placetype":[
        "aat:300008791"
    ]
},
  "bbox": [],
  "geometry": {"coordinates":[1.65,39.033333],"type":"Point"}
}