{
  "id": 2130227,
  "type": "Feature",
  "properties": {
    "tgn:hierarchy":[
        "tgn:2130227",
        "tgn:1000001",
        "tgn:7012149",
        "tgn:2001622",
        "tgn:7007706",
        "tgn:7029392"
    ],
    "tgn:id":2130227,
    "tgn:name":"Allen Run",
    "tgn:placetype":[
        "aat:300008699"
    ]
},
  "bbox": [],
  "geometry": {"coordinates":[-81.3167,39.3667],"type":"Point"}
}