<<<<<<< HEAD
{
  "id": 2405859,
  "type": "Feature",
  "properties": {
    "tgn:hierarchy":[
        "tgn:2405859",
        "tgn:7002659",
        "tgn:1000001",
        "tgn:7012149",
        "tgn:2000066",
        "tgn:7029392"
    ],
    "tgn:id":2405859,
    "tgn:name":"Hullett Branch",
    "tgn:placetype":[
        "aat:300008699"
    ]
},
  "bbox": [],
  "geometry": {"coordinates":[-87.2667,34.1167],"type":"Point"}
}
=======
{"geometry":{"type":"Point","coordinates":[-87.266700,34.116700]},"type":"Feature","properties":{"hierarchy":["tgn:2405859","tgn:7002659","tgn:1000001","tgn:7012149","tgn:2000066","tgn:7029392"],"placetype":["aat:300008699"],"id":2405859,"name:xx":"Hullett Branch"}}
>>>>>>> 03f74aca74312dbeaf24d7e61306dd6a786dc3d0
