{
  "id": 2495479,
  "type": "Feature",
  "properties": {
    "tgn:hierarchy":[
        "tgn:2495479",
        "tgn:1000001",
        "tgn:7012149",
        "tgn:7007826",
        "tgn:7029392"
    ],
    "tgn:id":2495479,
    "tgn:name":"Marys Creek",
    "tgn:placetype":[
        "aat:300008706"
    ]
},
  "bbox": [],
  "geometry": {"coordinates":[-97.6333,32.7833],"type":"Point"}
}