{
  "id": 7193514,
  "type": "Feature",
  "properties": {
    "tgn:hierarchy":[
        "tgn:7193514",
        "tgn:1000003",
        "tgn:7003678",
        "tgn:7000084",
        "tgn:7029392"
    ],
    "tgn:id":7193514,
    "tgn:name":"Bahnhof Frankfurt-West",
    "tgn:placetype":[
        "aat:300007783"
    ]
},
  "bbox": [],
  "geometry": {"coordinates":[8.638333,50.118889],"type":"Point"}
}