{
  "id": 7428900,
  "type": "Feature",
  "properties": {
    "tgn:hierarchy":[
        "tgn:7428900",
        "tgn:7005586",
        "tgn:1000001",
        "tgn:7005560",
        "tgn:7029392"
    ],
    "tgn:id":7428900,
    "tgn:name":"Sauz de los M\u00e1rquez",
    "tgn:placetype":[
        "aat:300008347"
    ]
},
  "bbox": [],
  "geometry": {"coordinates":[-103.116667,22.116667],"type":"Point"}
}