{
  "id": 2393314,
  "type": "Feature",
  "properties": {
    "tgn:hierarchy":[
        "tgn:2393314",
        "tgn:1000001",
        "tgn:2000950",
        "tgn:7012149",
        "tgn:7007520",
        "tgn:7029392"
    ],
    "tgn:id":2393314,
    "tgn:name":"Hoffman Lake",
    "tgn:placetype":[
        "aat:300008680"
    ]
},
  "bbox": [],
  "geometry": {"coordinates":[-84.7667,45.1167],"type":"Point"}
}