{
  "id": 2693350,
  "type": "Feature",
  "properties": {
    "tgn:hierarchy":[
        "tgn:2693350",
        "tgn:1000001",
        "tgn:7012149",
        "tgn:7016056",
        "tgn:7007520",
        "tgn:7029392"
    ],
    "tgn:id":2693350,
    "tgn:name":"Stein Drain",
    "tgn:placetype":[
        "aat:300006075"
    ]
},
  "bbox": [],
  "geometry": {"coordinates":[-82.8667,43.0167],"type":"Point"}
}