{
  "id": 7351628,
  "type": "Feature",
  "properties": {
    "tgn:hierarchy":[
        "tgn:7351628",
        "tgn:7005583",
        "tgn:1000001",
        "tgn:7005560",
        "tgn:7029392"
    ],
    "tgn:id":7351628,
    "tgn:name":"Boquilla",
    "tgn:placetype":[
        "aat:300008347"
    ]
},
  "bbox": [],
  "geometry": {"coordinates":[-106.583333,25.666667],"type":"Point"}
}