{
  "id": 2058450,
  "type": "Feature",
  "properties": {
    "tgn:hierarchy":[
        "tgn:2058450",
        "tgn:1000001",
        "tgn:7012149",
        "tgn:2001227",
        "tgn:7007523",
        "tgn:7029392"
    ],
    "tgn:id":2058450,
    "tgn:name":"Cottonwood Point",
    "tgn:placetype":[
        "aat:300008347",
        "aat:300387210"
    ]
},
  "bbox": [],
  "geometry": {"coordinates":[-89.6833,36.05],"type":"Point"}
}