{
  "id": 2753834,
  "type": "Feature",
  "properties": {
    "tgn:hierarchy":[
        "tgn:2753834",
        "tgn:1000001",
        "tgn:2001577",
        "tgn:7012149",
        "tgn:7007705",
        "tgn:7029392"
    ],
    "tgn:id":2753834,
    "tgn:name":"Watrous",
    "tgn:placetype":[
        "aat:300008347"
    ]
},
  "bbox": [],
  "geometry": {"coordinates":[-102.1833,46.3167],"type":"Point"}
}