{
  "id": 2200716,
  "type": "Feature",
  "properties": {
    "tgn:hierarchy":[
        "tgn:2200716",
        "tgn:1000001",
        "tgn:7012149",
        "tgn:2001120",
        "tgn:7007522",
        "tgn:7029392"
    ],
    "tgn:id":2200716,
    "tgn:name":"Bruton Pond",
    "tgn:placetype":[
        "aat:300008680"
    ]
},
  "bbox": [],
  "geometry": {"coordinates":[-88.65,32.7167],"type":"Point"}
}