{
  "id": 7394742,
  "type": "Feature",
  "properties": {
    "tgn:hierarchy":[
        "tgn:7394742",
        "tgn:7005586",
        "tgn:1000001",
        "tgn:7005560",
        "tgn:7029392"
    ],
    "tgn:id":7394742,
    "tgn:name":"San Cayetano",
    "tgn:placetype":[
        "aat:300008347"
    ]
},
  "bbox": [],
  "geometry": {"coordinates":[-101.966667,21.066667],"type":"Point"}
}