{
  "id": 7501403,
  "type": "Feature",
  "properties": {
    "tgn:hierarchy":[
        "tgn:7501403",
        "tgn:7468018",
        "tgn:1000004",
        "tgn:1000141",
        "tgn:7029392"
    ],
    "tgn:id":7501403,
    "tgn:name":"Erwanping Zhan",
    "tgn:placetype":[
        "aat:300007783"
    ]
},
  "bbox": [],
  "geometry": {"coordinates":[120.790278,23.509722],"type":"Point"}
}