{
  "id": 7389169,
  "type": "Feature",
  "properties": {
    "tgn:hierarchy":[
        "tgn:7389169",
        "tgn:1000001",
        "tgn:7005591",
        "tgn:7005560",
        "tgn:7029392"
    ],
    "tgn:id":7389169,
    "tgn:name":"Estaci\u00f3n Pearson",
    "tgn:placetype":[
        "aat:300007783"
    ]
},
  "bbox": [],
  "geometry": {"coordinates":[-95.233333,16.266667],"type":"Point"}
}