{
  "id": 7456008,
  "type": "Feature",
  "properties": {
    "tgn:hierarchy":[
        "tgn:7456008",
        "tgn:7002445",
        "tgn:7008114",
        "tgn:1000003",
        "tgn:7008591",
        "tgn:7029392"
    ],
    "tgn:id":7456008,
    "tgn:name:en":"Clotton",
    "tgn:placetype":[
        "aat:300008347"
    ]
},
  "bbox": [],
  "geometry": {"coordinates":[-2.716667,53.166667],"type":"Point"}
}