<<<<<<< HEAD
{
  "id": 7375059,
  "type": "Feature",
  "properties": {
    "tgn:hierarchy":[
        "tgn:7375059",
        "tgn:7005586",
        "tgn:1000001",
        "tgn:7005560",
        "tgn:7029392"
    ],
    "tgn:id":7375059,
    "tgn:name":"Le de Corte",
    "tgn:placetype":[
        "aat:300008347"
    ]
},
  "bbox": [],
  "geometry": {"coordinates":[-105.016667,19.383333],"type":"Point"}
}
=======
{"geometry":{"type":"Point","coordinates":[-105.016667,19.383333]},"type":"Feature","properties":{"hierarchy":["tgn:7375059","tgn:7005586","tgn:1000001","tgn:7005560","tgn:7029392"],"placetype":["aat:300008347"],"id":7375059,"name:xx":"Le de Corte"}}
>>>>>>> 03f74aca74312dbeaf24d7e61306dd6a786dc3d0
