{
  "id": 2243762,
  "type": "Feature",
  "properties": {
    "tgn:hierarchy":[
        "tgn:2243762",
        "tgn:1000001",
        "tgn:7012149",
        "tgn:7018871",
        "tgn:7007920",
        "tgn:7029392"
    ],
    "tgn:id":2243762,
    "tgn:name":"Cleopatra Mine",
    "tgn:placetype":[
        "aat:300000390"
    ]
},
  "bbox": [],
  "geometry": {"coordinates":[-121.45,47.6333],"type":"Point"}
}