{
  "id": 2486477,
  "type": "Feature",
  "properties": {
    "tgn:hierarchy":[
        "tgn:2486477",
        "tgn:1000001",
        "tgn:7012149",
        "tgn:7029392"
    ],
    "tgn:id":2486477,
    "tgn:name":"Lebanon Brook",
    "tgn:placetype":[
        "aat:300008699"
    ]
},
  "bbox": [],
  "geometry": {"coordinates":[-72.0833,41.9833],"type":"Point"}
}