{
  "id": 7413256,
  "type": "Feature",
  "properties": {
    "tgn:hierarchy":[
        "tgn:7413256",
        "tgn:7005580",
        "tgn:1000001",
        "tgn:7005560",
        "tgn:7029392"
    ],
    "tgn:id":7413256,
    "tgn:name":"Ojo de Agua",
    "tgn:placetype":[
        "aat:300008347"
    ]
},
  "bbox": [],
  "geometry": {"coordinates":[-92.716667,16.508333],"type":"Point"}
}