{
  "id": 1082551,
  "type": "Feature",
  "properties": {
    "tgn:hierarchy":[
        "tgn:1082551",
        "tgn:7000843",
        "tgn:1000004",
        "tgn:1000125",
        "tgn:7029392"
    ],
    "tgn:id":1082551,
    "tgn:name":"Sop Hao",
    "tgn:placetype":[
        "aat:300008347"
    ]
},
  "bbox": [],
  "geometry": {"coordinates":[104.45,20.55],"type":"Point"}
}