<<<<<<< HEAD
{
  "id": 2259599,
  "type": "Feature",
  "properties": {
    "tgn:hierarchy":[
        "tgn:2259599",
        "tgn:1000001",
        "tgn:7012149",
        "tgn:2000811",
        "tgn:7007255",
        "tgn:7029392"
    ],
    "tgn:id":2259599,
    "tgn:name":"Couch Branch",
    "tgn:placetype":[
        "aat:300008699"
    ]
},
  "bbox": [],
  "geometry": {"coordinates":[-83.45,37.1667],"type":"Point"}
}
=======
{"geometry":{"type":"Point","coordinates":[-83.450000,37.166700]},"type":"Feature","properties":{"hierarchy":["tgn:2259599","tgn:1000001","tgn:7012149","tgn:2000811","tgn:7007255","tgn:7029392"],"placetype":["aat:300008699"],"id":2259599,"name:xx":"Couch Branch"}}
>>>>>>> 03f74aca74312dbeaf24d7e61306dd6a786dc3d0
