{
  "id": 1088942,
  "type": "Feature",
  "properties": {
    "tgn:hierarchy":[
        "tgn:1088942",
        "tgn:7001242",
        "tgn:7016755",
        "tgn:1000159",
        "tgn:7029392"
    ],
    "tgn:id":1088942,
    "tgn:name":"Dungu",
    "tgn:placetype":[
        "aat:300008347"
    ]
},
  "bbox": [],
  "geometry": {"coordinates":[28.5333,3.6667],"type":"Point"}
}