{
  "id": 2243931,
  "type": "Feature",
  "properties": {
    "tgn:hierarchy":[
        "tgn:2243931",
        "tgn:1000001",
        "tgn:7012149",
        "tgn:2001706",
        "tgn:7007708",
        "tgn:7029392"
    ],
    "tgn:id":2243931,
    "tgn:name":"Cleves Cove",
    "tgn:placetype":[
        "aat:300132316"
    ]
},
  "bbox": [],
  "geometry": {"coordinates":[-124.1167,43.7833],"type":"Point"}
}