{
  "id": 7449726,
  "type": "Feature",
  "properties": {
    "tgn:hierarchy":[
        "tgn:7449726",
        "tgn:7002444",
        "tgn:1000003",
        "tgn:7009907",
        "tgn:7008591",
        "tgn:7029392"
    ],
    "tgn:id":7449726,
    "tgn:name:en":"Eday Gruna",
    "tgn:placetype":[
        "aat:300387036"
    ]
},
  "bbox": [],
  "geometry": {"coordinates":[-2.733333,59.133333],"type":"Point"}
}