{
  "id": 2066684,
  "type": "Feature",
  "properties": {
    "tgn:hierarchy":[
        "tgn:2066684",
        "tgn:1000001",
        "tgn:2001428",
        "tgn:7012149",
        "tgn:7007566",
        "tgn:7029392"
    ],
    "tgn:id":2066684,
    "tgn:name":"Armijo",
    "tgn:placetype":[
        "aat:300008347"
    ]
},
  "bbox": [],
  "geometry": {"coordinates":[-106.6667,35.05],"type":"Point"}
}