{
  "id": 2569226,
  "type": "Feature",
  "properties": {
    "tgn:hierarchy":[
        "tgn:2569226",
        "tgn:2124017",
        "tgn:7006450",
        "tgn:1000001",
        "tgn:7012149",
        "tgn:7029392"
    ],
    "tgn:id":2569226,
    "tgn:name":"Parks Creek",
    "tgn:placetype":[
        "aat:300008706"
    ]
},
  "bbox": [],
  "geometry": {"coordinates":[-149.45,61.3667],"type":"Point"}
}