{
  "id": 2296887,
  "type": "Feature",
  "properties": {
    "tgn:hierarchy":[
        "tgn:2296887",
        "tgn:1000001",
        "tgn:7012149",
        "tgn:2001307",
        "tgn:7007524",
        "tgn:7029392"
    ],
    "tgn:id":2296887,
    "tgn:name":"Dry Creek",
    "tgn:placetype":[
        "aat:300008706"
    ]
},
  "bbox": [],
  "geometry": {"coordinates":[-109.2167,45.6833],"type":"Point"}
}