{
  "id": 7564242,
  "type": "Feature",
  "properties": {
    "tgn:hierarchy":[
        "tgn:7564242",
        "tgn:1000004",
        "tgn:7000198",
        "tgn:7016722",
        "tgn:7029392"
    ],
    "tgn:id":7564242,
    "tgn:name:en":"Anantpur",
    "tgn:placetype":[
        "aat:300008347"
    ]
},
  "bbox": [],
  "geometry": {"coordinates":[79.644678,26.949868],"type":"Point"}
}