<<<<<<< HEAD
{
  "id": 7373671,
  "type": "Feature",
  "properties": {
    "tgn:hierarchy":[
        "tgn:7373671",
        "tgn:7005581",
        "tgn:1000001",
        "tgn:7005560",
        "tgn:7029392"
    ],
    "tgn:id":7373671,
    "tgn:name":"La Cieneguita",
    "tgn:placetype":[
        "aat:300008347"
    ]
},
  "bbox": [],
  "geometry": {"coordinates":[-108.483333,28.9],"type":"Point"}
}
=======
{"geometry":{"type":"Point","coordinates":[-108.483333,28.900000]},"type":"Feature","properties":{"hierarchy":["tgn:7373671","tgn:7005581","tgn:1000001","tgn:7005560","tgn:7029392"],"placetype":["aat:300008347"],"id":7373671,"name:xx":"La Cieneguita"}}
>>>>>>> 03f74aca74312dbeaf24d7e61306dd6a786dc3d0
