{
  "id": 7376346,
  "type": "Feature",
  "properties": {
    "tgn:hierarchy":[
        "tgn:7376346",
        "tgn:7005585",
        "tgn:1000001",
        "tgn:7005560",
        "tgn:7029392"
    ],
    "tgn:id":7376346,
    "tgn:name":"Las Juntas de Guti\u00e9rrez",
    "tgn:placetype":[
        "aat:300008347"
    ]
},
  "bbox": [],
  "geometry": {"coordinates":[-101.766667,18.266667],"type":"Point"}
}