<<<<<<< HEAD
{
  "id": 7376346,
  "type": "Feature",
  "properties": {
    "tgn:hierarchy":[
        "tgn:7376346",
        "tgn:7005585",
        "tgn:1000001",
        "tgn:7005560",
        "tgn:7029392"
    ],
    "tgn:id":7376346,
    "tgn:name":"Las Juntas de Guti\u00e9rrez",
    "tgn:placetype":[
        "aat:300008347"
    ]
},
  "bbox": [],
  "geometry": {"coordinates":[-101.766667,18.266667],"type":"Point"}
}
=======
{"geometry":{"type":"Point","coordinates":[-101.766667,18.266667]},"type":"Feature","properties":{"hierarchy":["tgn:7376346","tgn:7005585","tgn:1000001","tgn:7005560","tgn:7029392"],"placetype":["aat:300008347"],"id":7376346,"name:xx":"Las Juntas de Guti\u00e9rrez"}}
>>>>>>> 03f74aca74312dbeaf24d7e61306dd6a786dc3d0
