{
  "id": 7581962,
  "type": "Feature",
  "properties": {
    "tgn:hierarchy":[
        "tgn:7581962",
        "tgn:1000004",
        "tgn:7000198",
        "tgn:7000799",
        "tgn:7029392"
    ],
    "tgn:id":7581962,
    "tgn:name:en":"Tr\u0101gbal Pass",
    "tgn:placetype":[
        "aat:300259572"
    ]
},
  "bbox": [],
  "geometry": {"coordinates":[74.637343,34.538562],"type":"Point"}
}