{
  "id": 2759482,
  "type": "Feature",
  "properties": {
    "tgn:hierarchy":[
        "tgn:2759482",
        "tgn:1000001",
        "tgn:7012149",
        "tgn:2001304",
        "tgn:7007524",
        "tgn:7029392"
    ],
    "tgn:id":2759482,
    "tgn:name":"West Fork Dry Creek",
    "tgn:placetype":[
        "aat:300008706"
    ]
},
  "bbox": [],
  "geometry": {"coordinates":[-115.4333,47.4667],"type":"Point"}
}