{
  "id": 1075713,
  "type": "Feature",
  "properties": {
    "tgn:hierarchy":[
        "tgn:1075713",
        "tgn:1000004",
        "tgn:7000198",
        "tgn:1001882",
        "tgn:7029392"
    ],
    "tgn:id":1075713,
    "tgn:name":"Kadur",
    "tgn:placetype":[
        "aat:300008347"
    ]
},
  "bbox": [],
  "geometry": {"coordinates":[76.013056,13.553333],"type":"Point"}
}