{
  "id": 2654969,
  "type": "Feature",
  "properties": {
    "tgn:hierarchy":[
        "tgn:2654969",
        "tgn:1000001",
        "tgn:7012149",
        "tgn:7007157",
        "tgn:1002957",
        "tgn:7029392"
    ],
    "tgn:id":2654969,
    "tgn:name":"Shamrock Lake",
    "tgn:placetype":[
        "aat:300008680"
    ]
},
  "bbox": [],
  "geometry": {"coordinates":[-119.45,38.0167],"type":"Point"}
}