{
  "id": 7414015,
  "type": "Feature",
  "properties": {
    "tgn:hierarchy":[
        "tgn:7414015",
        "tgn:1000001",
        "tgn:7005598",
        "tgn:7005560",
        "tgn:7029392"
    ],
    "tgn:id":7414015,
    "tgn:name":"Presa El Centenario",
    "tgn:placetype":[
        "aat:300006191"
    ]
},
  "bbox": [],
  "geometry": {"coordinates":[-98.25,19.534722],"type":"Point"}
}