{
  "id": 2251691,
  "type": "Feature",
  "properties": {
    "tgn:hierarchy":[
        "tgn:2251691",
        "tgn:1000001",
        "tgn:7012149",
        "tgn:2000277",
        "tgn:7007240",
        "tgn:7029392"
    ],
    "tgn:id":2251691,
    "tgn:name":"Compass Point",
    "tgn:placetype":[
        "aat:300008850"
    ]
},
  "bbox": [],
  "geometry": {"coordinates":[-82.8167,29.15],"type":"Point"}
}