<<<<<<< HEAD
{
  "id": 2251691,
  "type": "Feature",
  "properties": {
    "tgn:hierarchy":[
        "tgn:2251691",
        "tgn:1000001",
        "tgn:7012149",
        "tgn:2000277",
        "tgn:7007240",
        "tgn:7029392"
    ],
    "tgn:id":2251691,
    "tgn:name":"Compass Point",
    "tgn:placetype":[
        "aat:300008850"
    ]
},
  "bbox": [],
  "geometry": {"coordinates":[-82.8167,29.15],"type":"Point"}
}
=======
{"geometry":{"type":"Point","coordinates":[-82.816700,29.150000]},"type":"Feature","properties":{"hierarchy":["tgn:2251691","tgn:1000001","tgn:7012149","tgn:2000277","tgn:7007240","tgn:7029392"],"placetype":["aat:300008850"],"id":2251691,"name:xx":"Compass Point"}}
>>>>>>> 03f74aca74312dbeaf24d7e61306dd6a786dc3d0
