{
  "id": 7116392,
  "type": "Feature",
  "properties": {
    "tgn:hierarchy":[
        "tgn:7116392",
        "tgn:1000003",
        "tgn:7003677",
        "tgn:7000084",
        "tgn:7029392"
    ],
    "tgn:id":7116392,
    "tgn:name":"Ossenberg",
    "tgn:placetype":[
        "aat:300000206"
    ]
},
  "bbox": [],
  "geometry": {"coordinates":[7.666667,51.233333],"type":"Point"}
}