{
  "id": 7028658,
  "type": "Feature",
  "properties": {
    "tgn:hierarchy":[
        "tgn:7028658",
        "tgn:7002445",
        "tgn:1000003",
        "tgn:7008160",
        "tgn:7008591",
        "tgn:7029392"
    ],
    "tgn:id":7028658,
    "tgn:name":"Thorpe Row",
    "tgn:placetype":[
        "aat:300008347",
        "aat:300008372"
    ]
},
  "bbox": [],
  "geometry": {"coordinates":[0.915,52.634],"type":"Point"}
}