{
  "id": 7321134,
  "type": "Feature",
  "properties": {
    "tgn:hierarchy":[
        "tgn:7321134",
        "tgn:1001657",
        "tgn:1000049",
        "tgn:1000002",
        "tgn:7029392"
    ],
    "tgn:id":7321134,
    "tgn:name":"Bal\u00ed",
    "tgn:placetype":[
        "aat:300008347"
    ]
},
  "bbox": [],
  "geometry": {"coordinates":[-71.433333,-30.633333],"type":"Point"}
}