{
  "id": 7588548,
  "type": "Feature",
  "properties": {
    "tgn:hierarchy":[
        "tgn:7588548",
        "tgn:1000004",
        "tgn:7000198",
        "tgn:7000799",
        "tgn:7029392"
    ],
    "tgn:id":7588548,
    "tgn:name:en":"M\u012bragund",
    "tgn:placetype":[
        "aat:300008347"
    ]
},
  "bbox": [],
  "geometry": {"coordinates":[74.716756,34.037888],"type":"Point"}
}