{
  "id": 2501203,
  "type": "Feature",
  "properties": {
    "tgn:hierarchy":[
        "tgn:2501203",
        "tgn:1000001",
        "tgn:7012149",
        "tgn:7007157",
        "tgn:7014516",
        "tgn:7029392"
    ],
    "tgn:id":2501203,
    "tgn:name":"McGill",
    "tgn:placetype":[
        "aat:300008347"
    ]
},
  "bbox": [],
  "geometry": {"coordinates":[-122.4333,38.1833],"type":"Point"}
}