<<<<<<< HEAD
{
  "id": 7249461,
  "type": "Feature",
  "properties": {
    "tgn:hierarchy":[
        "tgn:7249461",
        "tgn:7003456",
        "tgn:1000003",
        "tgn:1000063",
        "tgn:7018236",
        "tgn:7029392"
    ],
    "tgn:id":7249461,
    "tgn:name":"Nieuwe Klets",
    "tgn:placetype":[
        "aat:300000206"
    ]
},
  "bbox": [],
  "geometry": {"coordinates":[4.633333,51.116667],"type":"Point"}
}
=======
{"geometry":{"type":"Point","coordinates":[4.633333,51.116667]},"type":"Feature","properties":{"hierarchy":["tgn:7249461","tgn:7003456","tgn:1000003","tgn:1000063","tgn:7018236","tgn:7029392"],"placetype":["aat:300000206"],"id":7249461,"name:xx":"Nieuwe Klets"}}
>>>>>>> 03f74aca74312dbeaf24d7e61306dd6a786dc3d0
