{
  "id": 2423937,
  "type": "Feature",
  "properties": {
    "tgn:hierarchy":[
        "tgn:2423937",
        "tgn:1000001",
        "tgn:2002263",
        "tgn:7012149",
        "tgn:7013961",
        "tgn:7029392"
    ],
    "tgn:id":2423937,
    "tgn:name":"Johnnycake Run",
    "tgn:placetype":[
        "aat:300008699"
    ]
},
  "bbox": [],
  "geometry": {"coordinates":[-79.2167,39.2667],"type":"Point"}
}