{
  "id": 2172643,
  "type": "Feature",
  "properties": {
    "tgn:hierarchy":[
        "tgn:2172643",
        "tgn:1002165",
        "tgn:1000001",
        "tgn:7012149",
        "tgn:7007517",
        "tgn:7029392"
    ],
    "tgn:id":2172643,
    "tgn:name":"Billingsgate Shoal",
    "tgn:placetype":[
        "aat:300132348"
    ]
},
  "bbox": [],
  "geometry": {"coordinates":[-70.1167,41.85],"type":"Point"}
}