{
  "id": 7337370,
  "type": "Feature",
  "properties": {
    "tgn:hierarchy":[
        "tgn:7337370",
        "tgn:7002759",
        "tgn:7008909",
        "tgn:1000003",
        "tgn:1000095",
        "tgn:7029392"
    ],
    "tgn:id":7337370,
    "tgn:name":"Cillas",
    "tgn:placetype":[
        "aat:300008347"
    ]
},
  "bbox": [],
  "geometry": {"coordinates":[-0.211721,42.529376],"type":"Point"}
}