{
  "id": 2556583,
  "type": "Feature",
  "properties": {
    "tgn:hierarchy":[
        "tgn:2556583",
        "tgn:1000001",
        "tgn:7006451",
        "tgn:7012149",
        "tgn:2000098",
        "tgn:7029392"
    ],
    "tgn:id":2556583,
    "tgn:name":"Old Bonnie Tunnel",
    "tgn:placetype":[
        "aat:300000390"
    ]
},
  "bbox": [],
  "geometry": {"coordinates":[-113.3167,35.8833],"type":"Point"}
}