{
  "id": 7305397,
  "type": "Feature",
  "properties": {
    "tgn:hierarchy":[
        "tgn:7305397",
        "tgn:7002758",
        "tgn:7002823",
        "tgn:1000003",
        "tgn:1000095",
        "tgn:7029392"
    ],
    "tgn:id":7305397,
    "tgn:name":"Las Cefi\u00f1as",
    "tgn:placetype":[
        "aat:300008347"
    ]
},
  "bbox": [],
  "geometry": {"coordinates":[-6.85,37.966667],"type":"Point"}
}