{
  "id": 2068399,
  "type": "Feature",
  "properties": {
    "tgn:hierarchy":[
        "tgn:2068399",
        "tgn:1000001",
        "tgn:7012149",
        "tgn:1002708",
        "tgn:7007568",
        "tgn:7029392"
    ],
    "tgn:id":2068399,
    "tgn:name":"Cedarhurst",
    "tgn:placetype":[
        "aat:300008347"
    ]
},
  "bbox": [],
  "geometry": {"coordinates":[-73.7167,40.6167],"type":"Point"}
}