{
  "id": 2199509,
  "type": "Feature",
  "properties": {
    "tgn:hierarchy":[
        "tgn:2199509",
        "tgn:1000001",
        "tgn:7012149",
        "tgn:2001500",
        "tgn:7007709",
        "tgn:7029392"
    ],
    "tgn:id":2199509,
    "tgn:name":"Brush Creek",
    "tgn:placetype":[
        "aat:300008706"
    ]
},
  "bbox": [],
  "geometry": {"coordinates":[-79.95,36.1167],"type":"Point"}
}