{
  "id": 7529327,
  "type": "Feature",
  "properties": {
    "tgn:hierarchy":[
        "tgn:7529327",
        "tgn:7001242",
        "tgn:1001059",
        "tgn:7016833",
        "tgn:7029392"
    ],
    "tgn:id":7529327,
    "tgn:name:en":"Tall, Jaz\u012brat at",
    "tgn:placetype":[
        "aat:300008791"
    ]
},
  "bbox": [],
  "geometry": {"coordinates":[31.956695,31.323922],"type":"Point"}
}