{
  "id": 7000806,
  "type": "Feature",
  "properties": {
    "tgn:hierarchy":[
        "tgn:7000806",
        "tgn:7001242",
        "tgn:7016749",
        "tgn:1000193",
        "tgn:7029392"
    ],
    "tgn:id":7000806,
    "tgn:name":"Isandhlwana",
    "tgn:placetype":[
        "aat:300000833"
    ]
},
  "bbox": [],
  "geometry": {"coordinates":[30.65,-28.35],"type":"Point"}
}