{
  "id": 7511602,
  "type": "Feature",
  "properties": {
    "tgn:hierarchy":[
        "tgn:7511602",
        "tgn:1009227",
        "tgn:7001866",
        "tgn:1000226",
        "tgn:1000006",
        "tgn:7029392"
    ],
    "tgn:id":7511602,
    "tgn:name:en":"Look-up Creek",
    "tgn:placetype":[
        "aat:300008699"
    ]
},
  "bbox": [],
  "geometry": {"coordinates":[170.933333,-43.783333],"type":"Point"}
}