{
  "id": 2734666,
  "type": "Feature",
  "properties": {
    "tgn:hierarchy":[
        "tgn:2734666",
        "tgn:7006450",
        "tgn:1000001",
        "tgn:7030517",
        "tgn:7012149",
        "tgn:7029392"
    ],
    "tgn:id":2734666,
    "tgn:name":"Tutna Lake",
    "tgn:placetype":[
        "aat:300008680"
    ]
},
  "bbox": [],
  "geometry": {"coordinates":[-155.3167,60.3333],"type":"Point"}
}