{
  "id": 2765589,
  "type": "Feature",
  "properties": {
    "tgn:hierarchy":[
        "tgn:2765589",
        "tgn:1000001",
        "tgn:7012149",
        "tgn:1002681",
        "tgn:7007568",
        "tgn:7029392"
    ],
    "tgn:id":2765589,
    "tgn:name":"White City",
    "tgn:placetype":[
        "aat:300008347"
    ]
},
  "bbox": [],
  "geometry": {"coordinates":[-77.5833,43.25],"type":"Point"}
}