<<<<<<< HEAD
{
  "id": 2765589,
  "type": "Feature",
  "properties": {
    "tgn:hierarchy":[
        "tgn:2765589",
        "tgn:1000001",
        "tgn:7012149",
        "tgn:1002681",
        "tgn:7007568",
        "tgn:7029392"
    ],
    "tgn:id":2765589,
    "tgn:name":"White City",
    "tgn:placetype":[
        "aat:300008347"
    ]
},
  "bbox": [],
  "geometry": {"coordinates":[-77.5833,43.25],"type":"Point"}
}
=======
{"geometry":{"type":"Point","coordinates":[-77.583300,43.250000]},"type":"Feature","properties":{"hierarchy":["tgn:2765589","tgn:1000001","tgn:7012149","tgn:1002681","tgn:7007568","tgn:7029392"],"placetype":["aat:300008347"],"id":2765589,"name:xx":"White City"}}
>>>>>>> 03f74aca74312dbeaf24d7e61306dd6a786dc3d0
