{
  "id": 2189474,
  "type": "Feature",
  "properties": {
    "tgn:hierarchy":[
        "tgn:2189474",
        "tgn:1000001",
        "tgn:2002102",
        "tgn:7012149",
        "tgn:7007827",
        "tgn:7029392"
    ],
    "tgn:id":2189474,
    "tgn:name":"Bovine Spring",
    "tgn:placetype":[
        "aat:300008697"
    ]
},
  "bbox": [],
  "geometry": {"coordinates":[-113.6167,41.5667],"type":"Point"}
}