{
  "id": 7592141,
  "type": "Feature",
  "properties": {
    "tgn:hierarchy":[
        "tgn:7592141",
        "tgn:1000004",
        "tgn:7000198",
        "tgn:7031786",
        "tgn:7029392"
    ],
    "tgn:id":7592141,
    "tgn:name:en":"R\u0101mgarh Rao",
    "tgn:placetype":[
        "aat:300008699"
    ]
},
  "bbox": [],
  "geometry": {"coordinates":[77.884291,30.333931],"type":"Point"}
}