{
  "id": 2665416,
  "type": "Feature",
  "properties": {
    "tgn:hierarchy":[
        "tgn:2665416",
        "tgn:1000001",
        "tgn:7012149",
        "tgn:7007712",
        "tgn:7029392"
    ],
    "tgn:id":2665416,
    "tgn:name":"Singleton Swamp",
    "tgn:placetype":[
        "aat:300008699"
    ]
},
  "bbox": [],
  "geometry": {"coordinates":[-79.7167,33.7667],"type":"Point"}
}