{
  "id": 2052120,
  "type": "Feature",
  "properties": {
    "tgn:hierarchy":[
        "tgn:2052120",
        "tgn:1000001",
        "tgn:7012149",
        "tgn:1003005",
        "tgn:7007520",
        "tgn:7029392"
    ],
    "tgn:id":2052120,
    "tgn:name":"Hamtramck",
    "tgn:placetype":[
        "aat:300008347"
    ]
},
  "bbox": [],
  "geometry": {"coordinates":[-83.0333,42.3833],"type":"Point"}
}