{
  "id": 7387894,
  "type": "Feature",
  "properties": {
    "tgn:hierarchy":[
        "tgn:7387894",
        "tgn:1000001",
        "tgn:7005595",
        "tgn:7005560",
        "tgn:7029392"
    ],
    "tgn:id":7387894,
    "tgn:name":"Potrerillo",
    "tgn:placetype":[
        "aat:300008347"
    ]
},
  "bbox": [],
  "geometry": {"coordinates":[-107.983333,25.45],"type":"Point"}
}