{
  "id": 1105068,
  "type": "Feature",
  "properties": {
    "tgn:hierarchy":[
        "tgn:1105068",
        "tgn:1000001",
        "tgn:2000921",
        "tgn:7012149",
        "tgn:7007515",
        "tgn:7029392"
    ],
    "tgn:id":1105068,
    "tgn:name":"Jackson Mountain",
    "tgn:placetype":[
        "aat:300008795"
    ]
},
  "bbox": [],
  "geometry": {"coordinates":[-70.5167,44.75],"type":"Point"}
}