{
  "id": 2327279,
  "type": "Feature",
  "properties": {
    "tgn:hierarchy":[
        "tgn:2327279",
        "tgn:1000001",
        "tgn:7012149",
        "tgn:2001284",
        "tgn:7007524",
        "tgn:7029392"
    ],
    "tgn:id":2327279,
    "tgn:name":"First Gulch",
    "tgn:placetype":[
        "aat:300008761"
    ]
},
  "bbox": [],
  "geometry": {"coordinates":[-112.4333,47.0667],"type":"Point"}
}