{
  "id": 7328766,
  "type": "Feature",
  "properties": {
    "tgn:hierarchy":[
        "tgn:7328766",
        "tgn:7002807",
        "tgn:1000003",
        "tgn:7003837",
        "tgn:1000095",
        "tgn:7029392"
    ],
    "tgn:id":7328766,
    "tgn:name":"Quejigos, Arroyo de los",
    "tgn:placetype":[
        "aat:300008699"
    ]
},
  "bbox": [],
  "geometry": {"coordinates":[-4.85,39.116667],"type":"Point"}
}