{
  "id": 7458150,
  "type": "Feature",
  "properties": {
    "tgn:hierarchy":[
        "tgn:7458150",
        "tgn:7002444",
        "tgn:1000003",
        "tgn:7008082",
        "tgn:7008591",
        "tgn:7029392"
    ],
    "tgn:id":7458150,
    "tgn:name:en":"Moniack Burn",
    "tgn:placetype":[
        "aat:300008699"
    ]
},
  "bbox": [],
  "geometry": {"coordinates":[-4.383333,57.483333],"type":"Point"}
}