{
  "id": 2704478,
  "type": "Feature",
  "properties": {
    "tgn:hierarchy":[
        "tgn:2704478",
        "tgn:1000001",
        "tgn:7012149",
        "tgn:2001277",
        "tgn:7007524",
        "tgn:7029392"
    ],
    "tgn:id":2704478,
    "tgn:name":"Sunrift Gorge",
    "tgn:placetype":[
        "aat:300008761"
    ]
},
  "bbox": [],
  "geometry": {"coordinates":[-113.5833,48.6667],"type":"Point"}
}