{
  "id": 2040208,
  "type": "Feature",
  "properties": {
    "tgn:hierarchy":[
        "tgn:2040208",
        "tgn:1000001",
        "tgn:7012149",
        "tgn:1002371",
        "tgn:7007255",
        "tgn:7029392"
    ],
    "tgn:id":2040208,
    "tgn:name":"Mattoxtown",
    "tgn:placetype":[
        "aat:300008347"
    ]
},
  "bbox": [],
  "geometry": {"coordinates":[-84.45,38.1167],"type":"Point"}
}