{
  "id": 2410333,
  "type": "Feature",
  "properties": {
    "tgn:hierarchy":[
        "tgn:2410333",
        "tgn:1000001",
        "tgn:7012149",
        "tgn:2000378",
        "tgn:7007248",
        "tgn:7029392"
    ],
    "tgn:id":2410333,
    "tgn:name":"Indian Branch",
    "tgn:placetype":[
        "aat:300008699"
    ]
},
  "bbox": [],
  "geometry": {"coordinates":[-82.6667,32.5667],"type":"Point"}
}