{
  "id": 2083451,
  "type": "Feature",
  "properties": {
    "tgn:hierarchy":[
        "tgn:2083451",
        "tgn:1000001",
        "tgn:7012149",
        "tgn:2001689",
        "tgn:7007707",
        "tgn:7029392"
    ],
    "tgn:id":2083451,
    "tgn:name":"Konawa",
    "tgn:placetype":[
        "aat:300008347"
    ]
},
  "bbox": [],
  "geometry": {"coordinates":[-96.75,34.95],"type":"Point"}
}