{
  "id": 7219653,
  "type": "Feature",
  "properties": {
    "tgn:hierarchy":[
        "tgn:7219653",
        "tgn:7011330",
        "tgn:7002674",
        "tgn:1000003",
        "tgn:1000074",
        "tgn:7029392"
    ],
    "tgn:id":7219653,
    "tgn:name":"L\u00edgkia, Vrachonis\u00edda",
    "tgn:placetype":[
        "aat:300008791"
    ]
},
  "bbox": [],
  "geometry": {"coordinates":[27.174167,36.944722],"type":"Point"}
}