{
  "id": 2275448,
  "type": "Feature",
  "properties": {
    "tgn:hierarchy":[
        "tgn:2275448",
        "tgn:1000001",
        "tgn:7012149",
        "tgn:2001516",
        "tgn:7007709",
        "tgn:7029392"
    ],
    "tgn:id":2275448,
    "tgn:name":"Dans Branch",
    "tgn:placetype":[
        "aat:300008699"
    ]
},
  "bbox": [],
  "geometry": {"coordinates":[-82.5833,35.8667],"type":"Point"}
}