{
  "id": 2110899,
  "type": "Feature",
  "properties": {
    "tgn:hierarchy":[
        "tgn:2110899",
        "tgn:1000001",
        "tgn:7012149",
        "tgn:1002336",
        "tgn:7007919",
        "tgn:7029392"
    ],
    "tgn:id":2110899,
    "tgn:name":"Butterworth",
    "tgn:placetype":[
        "aat:300008347",
        "aat:300387210"
    ]
},
  "bbox": [],
  "geometry": {"coordinates":[-77.6167,37.05],"type":"Point"}
}