{
  "id": 7279586,
  "type": "Feature",
  "properties": {
    "tgn:hierarchy":[
        "tgn:7279586",
        "tgn:1001695",
        "tgn:1000049",
        "tgn:1000002",
        "tgn:7029392"
    ],
    "tgn:id":7279586,
    "tgn:name":"Rinc\u00f3n de los Murci\u00e9lagos",
    "tgn:placetype":[
        "aat:300387200"
    ]
},
  "bbox": [],
  "geometry": {"coordinates":[-71.433333,-34.783333],"type":"Point"}
}