{
  "id": 2187592,
  "type": "Feature",
  "properties": {
    "tgn:hierarchy":[
        "tgn:2187592",
        "tgn:1000001",
        "tgn:2002318",
        "tgn:7012149",
        "tgn:7007922",
        "tgn:7029392"
    ],
    "tgn:id":2187592,
    "tgn:name":"Boot Lake",
    "tgn:placetype":[
        "aat:300008680"
    ]
},
  "bbox": [],
  "geometry": {"coordinates":[-91.6167,46.3333],"type":"Point"}
}