{
  "id": 2692943,
  "type": "Feature",
  "properties": {
    "tgn:hierarchy":[
        "tgn:2692943",
        "tgn:1000001",
        "tgn:7012149",
        "tgn:2001888",
        "tgn:7007825",
        "tgn:7029392"
    ],
    "tgn:id":2692943,
    "tgn:name":"Steelman Lake",
    "tgn:placetype":[
        "aat:300006191"
    ]
},
  "bbox": [],
  "geometry": {"coordinates":[-86.45,35.05],"type":"Point"}
}