{
  "id": 2571610,
  "type": "Feature",
  "properties": {
    "tgn:hierarchy":[
        "tgn:2571610",
        "tgn:7030515",
        "tgn:7006450",
        "tgn:1000001",
        "tgn:7012149",
        "tgn:7029392"
    ],
    "tgn:id":2571610,
    "tgn:name":"Pavlof Harbor",
    "tgn:placetype":[
        "aat:300132316"
    ]
},
  "bbox": [],
  "geometry": {"coordinates":[-162.6833,54.45],"type":"Point"}
}