<<<<<<< HEAD
{
  "id": 2334903,
  "type": "Feature",
  "properties": {
    "tgn:hierarchy":[
        "tgn:2334903",
        "tgn:1000001",
        "tgn:7012149",
        "tgn:2001884",
        "tgn:7007825",
        "tgn:7029392"
    ],
    "tgn:id":2334903,
    "tgn:name":"Forked Pond",
    "tgn:placetype":[
        "aat:300132316"
    ]
},
  "bbox": [],
  "geometry": {"coordinates":[-89.3667,36.4],"type":"Point"}
}
=======
{"geometry":{"type":"Point","coordinates":[-89.366700,36.400000]},"type":"Feature","properties":{"hierarchy":["tgn:2334903","tgn:1000001","tgn:7012149","tgn:2001884","tgn:7007825","tgn:7029392"],"placetype":["aat:300132316"],"id":2334903,"name:xx":"Forked Pond"}}
>>>>>>> 03f74aca74312dbeaf24d7e61306dd6a786dc3d0
