{
  "id": 2171834,
  "type": "Feature",
  "properties": {
    "tgn:hierarchy":[
        "tgn:2171834",
        "tgn:1000001",
        "tgn:7012149",
        "tgn:7007828",
        "tgn:7029392"
    ],
    "tgn:id":2171834,
    "tgn:name":"Big Valley Brook",
    "tgn:placetype":[
        "aat:300008699"
    ]
},
  "bbox": [],
  "geometry": {"coordinates":[-72.05,44.7167],"type":"Point"}
}