{
  "id": 7221568,
  "type": "Feature",
  "properties": {
    "tgn:hierarchy":[
        "tgn:7221568",
        "tgn:7002753",
        "tgn:7002756",
        "tgn:1000003",
        "tgn:1000074",
        "tgn:7029392"
    ],
    "tgn:id":7221568,
    "tgn:name":"Zour\u00e1fa, Vrachonis\u00edda",
    "tgn:placetype":[
        "aat:300008791"
    ]
},
  "bbox": [],
  "geometry": {"coordinates":[25.838333,40.4725],"type":"Point"}
}