<<<<<<< HEAD
{
  "id": 2402835,
  "type": "Feature",
  "properties": {
    "tgn:hierarchy":[
        "tgn:2402835",
        "tgn:7002659",
        "tgn:1000001",
        "tgn:7012149",
        "tgn:2000045",
        "tgn:7029392"
    ],
    "tgn:id":2402835,
    "tgn:name":"Hotamville",
    "tgn:placetype":[
        "aat:300008347"
    ]
},
  "bbox": [],
  "geometry": {"coordinates":[-87.9333,31.9833],"type":"Point"}
}
=======
{"geometry":{"type":"Point","coordinates":[-87.933300,31.983300]},"type":"Feature","properties":{"hierarchy":["tgn:2402835","tgn:7002659","tgn:1000001","tgn:7012149","tgn:2000045","tgn:7029392"],"placetype":["aat:300008347"],"id":2402835,"name:xx":"Hotamville"}}
>>>>>>> 03f74aca74312dbeaf24d7e61306dd6a786dc3d0
