{
  "id": 2354393,
  "type": "Feature",
  "properties": {
    "tgn:hierarchy":[
        "tgn:2354393",
        "tgn:1000001",
        "tgn:7012149",
        "tgn:1002545",
        "tgn:7007157",
        "tgn:7029392"
    ],
    "tgn:id":2354393,
    "tgn:name":"Goldpan Canyon",
    "tgn:placetype":[
        "aat:300008761"
    ]
},
  "bbox": [],
  "geometry": {"coordinates":[-118.4667,35.3333],"type":"Point"}
}