{
  "id": 7241473,
  "type": "Feature",
  "properties": {
    "tgn:hierarchy":[
        "tgn:7241473",
        "tgn:7003458",
        "tgn:1000003",
        "tgn:1000063",
        "tgn:7018236",
        "tgn:7029392"
    ],
    "tgn:id":7241473,
    "tgn:name":"Liester",
    "tgn:placetype":[
        "aat:300008347"
    ]
},
  "bbox": [],
  "geometry": {"coordinates":[3.216667,50.95],"type":"Point"}
}