{
  "id": 7558843,
  "type": "Feature",
  "properties": {
    "tgn:hierarchy":[
        "tgn:7558843",
        "tgn:1000004",
        "tgn:7000198",
        "tgn:7016788",
        "tgn:7029392"
    ],
    "tgn:id":7558843,
    "tgn:name:en":"Rerwas",
    "tgn:placetype":[
        "aat:300008347"
    ]
},
  "bbox": [],
  "geometry": {"coordinates":[74.894102,25.339134],"type":"Point"}
}