{
  "id": 2606795,
  "type": "Feature",
  "properties": {
    "tgn:hierarchy":[
        "tgn:2606795",
        "tgn:1000001",
        "tgn:2001411",
        "tgn:7012149",
        "tgn:7007526",
        "tgn:7029392"
    ],
    "tgn:id":2606795,
    "tgn:name":"Ramsey Draw",
    "tgn:placetype":[
        "aat:300008761"
    ]
},
  "bbox": [],
  "geometry": {"coordinates":[-115.95,41.9833],"type":"Point"}
}