{
  "id": 2773171,
  "type": "Feature",
  "properties": {
    "tgn:hierarchy":[
        "tgn:2773171",
        "tgn:1000001",
        "tgn:2000199",
        "tgn:7012149",
        "tgn:7007158",
        "tgn:7029392"
    ],
    "tgn:id":2773171,
    "tgn:name":"Williams-Hamm Ditch",
    "tgn:placetype":[
        "aat:300006075"
    ]
},
  "bbox": [],
  "geometry": {"coordinates":[-106.0333,38.5667],"type":"Point"}
}