{
  "id": 7059242,
  "type": "Feature",
  "properties": {
    "tgn:hierarchy":[
        "tgn:7059242",
        "tgn:1000003",
        "tgn:7003677",
        "tgn:7000084",
        "tgn:7029392"
    ],
    "tgn:id":7059242,
    "tgn:name":"Aabauerschaft",
    "tgn:placetype":[
        "aat:300387200"
    ]
},
  "bbox": [],
  "geometry": {"coordinates":[7.383333,52.083333],"type":"Point"}
}