<<<<<<< HEAD
{
  "id": 7368579,
  "type": "Feature",
  "properties": {
    "tgn:hierarchy":[
        "tgn:7368579",
        "tgn:1001853",
        "tgn:1000001",
        "tgn:7005560",
        "tgn:7029392"
    ],
    "tgn:id":7368579,
    "tgn:name":"Hidalgo",
    "tgn:placetype":[
        "aat:300008347"
    ]
},
  "bbox": [],
  "geometry": {"coordinates":[-103.283333,25.816667],"type":"Point"}
}
=======
{"geometry":{"type":"Point","coordinates":[-103.283333,25.816667]},"type":"Feature","properties":{"hierarchy":["tgn:7368579","tgn:1001853","tgn:1000001","tgn:7005560","tgn:7029392"],"placetype":["aat:300008347"],"id":7368579,"name:xx":"Hidalgo"}}
>>>>>>> 03f74aca74312dbeaf24d7e61306dd6a786dc3d0
