{
  "id": 7368579,
  "type": "Feature",
  "properties": {
    "tgn:hierarchy":[
        "tgn:7368579",
        "tgn:1001853",
        "tgn:1000001",
        "tgn:7005560",
        "tgn:7029392"
    ],
    "tgn:id":7368579,
    "tgn:name":"Hidalgo",
    "tgn:placetype":[
        "aat:300008347"
    ]
},
  "bbox": [],
  "geometry": {"coordinates":[-103.283333,25.816667],"type":"Point"}
}