{
  "id": 2703366,
  "type": "Feature",
  "properties": {
    "tgn:hierarchy":[
        "tgn:2703366",
        "tgn:1000001",
        "tgn:2000470",
        "tgn:7012149",
        "tgn:7007250",
        "tgn:7029392"
    ],
    "tgn:id":2703366,
    "tgn:name":"Summit Creek",
    "tgn:placetype":[
        "aat:300008706"
    ]
},
  "bbox": [],
  "geometry": {"coordinates":[-114.9333,44.3667],"type":"Point"}
}