{
  "id": 2629138,
  "type": "Feature",
  "properties": {
    "tgn:hierarchy":[
        "tgn:2629138",
        "tgn:1000001",
        "tgn:7012149",
        "tgn:2001509",
        "tgn:7007709",
        "tgn:7029392"
    ],
    "tgn:id":2629138,
    "tgn:name":"Rose Manor",
    "tgn:placetype":[
        "aat:300008347"
    ]
},
  "bbox": [],
  "geometry": {"coordinates":[-78.3667,35.5167],"type":"Point"}
}