{
  "id": 7204942,
  "type": "Feature",
  "properties": {
    "tgn:hierarchy":[
        "tgn:7204942",
        "tgn:1000003",
        "tgn:7003687",
        "tgn:7000084",
        "tgn:7029392"
    ],
    "tgn:id":7204942,
    "tgn:name":"B\u00fclitz",
    "tgn:placetype":[
        "aat:300008347"
    ]
},
  "bbox": [],
  "geometry": {"coordinates":[11.666667,52.65],"type":"Point"}
}