<<<<<<< HEAD
{
  "id": 2408680,
  "type": "Feature",
  "properties": {
    "tgn:hierarchy":[
        "tgn:2408680",
        "tgn:1000001",
        "tgn:7012149",
        "tgn:2000221",
        "tgn:7007158",
        "tgn:7029392"
    ],
    "tgn:id":2408680,
    "tgn:name":"Hyatt Lake",
    "tgn:placetype":[
        "aat:300006191"
    ]
},
  "bbox": [],
  "geometry": {"coordinates":[-105.15,39.8],"type":"Point"}
}
=======
{"geometry":{"type":"Point","coordinates":[-105.150000,39.800000]},"type":"Feature","properties":{"hierarchy":["tgn:2408680","tgn:1000001","tgn:7012149","tgn:2000221","tgn:7007158","tgn:7029392"],"placetype":["aat:300006191"],"id":2408680,"name:xx":"Hyatt Lake"}}
>>>>>>> 03f74aca74312dbeaf24d7e61306dd6a786dc3d0
