{
  "id": 7473769,
  "type": "Feature",
  "properties": {
    "tgn:hierarchy":[
        "tgn:7473769",
        "tgn:1000004",
        "tgn:7489179",
        "tgn:1000141",
        "tgn:7029392"
    ],
    "tgn:id":7473769,
    "tgn:name":"Kulingkeng",
    "tgn:placetype":[
        "aat:300008347"
    ]
},
  "bbox": [],
  "geometry": {"coordinates":[121.674248,24.76112],"type":"Point"}
}