{
  "id": 2479096,
  "type": "Feature",
  "properties": {
    "tgn:hierarchy":[
        "tgn:2479096",
        "tgn:1000001",
        "tgn:7012149",
        "tgn:2000226",
        "tgn:7007158",
        "tgn:7029392"
    ],
    "tgn:id":2479096,
    "tgn:name":"Lady Moon Lake",
    "tgn:placetype":[
        "aat:300008680"
    ]
},
  "bbox": [],
  "geometry": {"coordinates":[-105.5167,40.7667],"type":"Point"}
}