{
  "id": 7484533,
  "type": "Feature",
  "properties": {
    "tgn:hierarchy":[
        "tgn:7484533",
        "tgn:1000004",
        "tgn:7492971",
        "tgn:1000141",
        "tgn:7029392"
    ],
    "tgn:id":7484533,
    "tgn:name":"Wenzi Tifang",
    "tgn:placetype":[
        "aat:300006156"
    ]
},
  "bbox": [],
  "geometry": {"coordinates":[120.522778,22.4225],"type":"Point"}
}