<<<<<<< HEAD
{
  "id": 2338452,
  "type": "Feature",
  "properties": {
    "tgn:hierarchy":[
        "tgn:2338452",
        "tgn:1000001",
        "tgn:7012149",
        "tgn:2001451",
        "tgn:7007566",
        "tgn:7029392"
    ],
    "tgn:id":2338452,
    "tgn:name":"Fraction",
    "tgn:placetype":[
        "aat:300000390"
    ]
},
  "bbox": [],
  "geometry": {"coordinates":[-106.0,35.7833],"type":"Point"}
}
=======
{"geometry":{"type":"Point","coordinates":[-106.000000,35.783300]},"type":"Feature","properties":{"hierarchy":["tgn:2338452","tgn:1000001","tgn:7012149","tgn:2001451","tgn:7007566","tgn:7029392"],"placetype":["aat:300000390"],"id":2338452,"name:xx":"Fraction"}}
>>>>>>> 03f74aca74312dbeaf24d7e61306dd6a786dc3d0
