<<<<<<< HEAD
{
  "id": 7372796,
  "type": "Feature",
  "properties": {
    "tgn:hierarchy":[
        "tgn:7372796",
        "tgn:7005581",
        "tgn:1000001",
        "tgn:7005560",
        "tgn:7029392"
    ],
    "tgn:id":7372796,
    "tgn:name":"La Casita",
    "tgn:placetype":[
        "aat:300008347"
    ]
},
  "bbox": [],
  "geometry": {"coordinates":[-106.816667,28.783333],"type":"Point"}
}
=======
{"geometry":{"type":"Point","coordinates":[-106.816667,28.783333]},"type":"Feature","properties":{"hierarchy":["tgn:7372796","tgn:7005581","tgn:1000001","tgn:7005560","tgn:7029392"],"placetype":["aat:300008347"],"id":7372796,"name:xx":"La Casita"}}
>>>>>>> 03f74aca74312dbeaf24d7e61306dd6a786dc3d0
