{
  "id": 7468906,
  "type": "Feature",
  "properties": {
    "tgn:hierarchy":[
        "tgn:7468906",
        "tgn:1000004",
        "tgn:7467799",
        "tgn:1000141",
        "tgn:7029392"
    ],
    "tgn:id":7468906,
    "tgn:name":"Xinsheng Cun",
    "tgn:placetype":[
        "aat:300387173"
    ]
},
  "bbox": [],
  "geometry": {"coordinates":[120.549189,23.891191],"type":"Point"}
}