{
  "id": 2384856,
  "type": "Feature",
  "properties": {
    "tgn:hierarchy":[
        "tgn:2384856",
        "tgn:1000001",
        "tgn:7006451",
        "tgn:2000095",
        "tgn:7012149",
        "tgn:7029392"
    ],
    "tgn:id":2384856,
    "tgn:name":"Hells Hole Peak",
    "tgn:placetype":[
        "aat:300008798"
    ]
},
  "bbox": [],
  "geometry": {"coordinates":[-109.0667,32.9833],"type":"Point"}
}