{
  "id": 2478543,
  "type": "Feature",
  "properties": {
    "tgn:hierarchy":[
        "tgn:2478543",
        "tgn:1000001",
        "tgn:7012149",
        "tgn:7007157",
        "tgn:1002608",
        "tgn:7029392"
    ],
    "tgn:id":2478543,
    "tgn:name":"Maddock Canyon",
    "tgn:placetype":[
        "aat:300008761"
    ]
},
  "bbox": [],
  "geometry": {"coordinates":[-117.9333,34.15],"type":"Point"}
}