{
  "id": 2313224,
  "type": "Feature",
  "properties": {
    "tgn:hierarchy":[
        "tgn:2313224",
        "tgn:1000001",
        "tgn:7012149",
        "tgn:1002945",
        "tgn:7007710",
        "tgn:7029392"
    ],
    "tgn:id":2313224,
    "tgn:name":"Elbridge",
    "tgn:placetype":[
        "aat:300008347"
    ]
},
  "bbox": [],
  "geometry": {"coordinates":[-77.2667,41.9167],"type":"Point"}
}