<<<<<<< HEAD
{
  "id": 7052643,
  "type": "Feature",
  "properties": {
    "tgn:hierarchy":[
        "tgn:7052643",
        "tgn:7003005",
        "tgn:7003014",
        "tgn:1000003",
        "tgn:1000080",
        "tgn:7029392"
    ],
    "tgn:id":7052643,
    "tgn:name":"Peglio, Torrente",
    "tgn:placetype":[
        "aat:300008699"
    ]
},
  "bbox": [],
  "geometry": {"coordinates":[15.616667,40.3],"type":"Point"}
}
=======
{"geometry":{"type":"Point","coordinates":[15.616667,40.300000]},"type":"Feature","properties":{"hierarchy":["tgn:7052643","tgn:7003005","tgn:7003014","tgn:1000003","tgn:1000080","tgn:7029392"],"placetype":["aat:300008699"],"id":7052643,"name:xx":"Peglio, Torrente"}}
>>>>>>> 03f74aca74312dbeaf24d7e61306dd6a786dc3d0
