{
  "id": 2488482,
  "type": "Feature",
  "properties": {
    "tgn:hierarchy":[
        "tgn:2488482",
        "tgn:1000001",
        "tgn:7012149",
        "tgn:7007827",
        "tgn:7029392"
    ],
    "tgn:id":2488482,
    "tgn:name":"Mahogany Knoll",
    "tgn:placetype":[
        "aat:300008798"
    ]
},
  "bbox": [],
  "geometry": {"coordinates":[-112.8167,38.1333],"type":"Point"}
}