<<<<<<< HEAD
{
  "id": 7110115,
  "type": "Feature",
  "properties": {
    "tgn:hierarchy":[
        "tgn:7110115",
        "tgn:1000003",
        "tgn:7003676",
        "tgn:7000084",
        "tgn:7029392"
    ],
    "tgn:id":7110115,
    "tgn:name":"Ramm-Berg",
    "tgn:placetype":[
        "aat:300008777"
    ]
},
  "bbox": [],
  "geometry": {"coordinates":[8.6,53.816667],"type":"Point"}
}
=======
{"geometry":{"type":"Point","coordinates":[8.600000,53.816667]},"type":"Feature","properties":{"hierarchy":["tgn:7110115","tgn:1000003","tgn:7003676","tgn:7000084","tgn:7029392"],"placetype":["aat:300008777"],"id":7110115,"name:xx":"Ramm-Berg"}}
>>>>>>> 03f74aca74312dbeaf24d7e61306dd6a786dc3d0
