{
  "id": 7162366,
  "type": "Feature",
  "properties": {
    "tgn:hierarchy":[
        "tgn:7162366",
        "tgn:1000003",
        "tgn:7003676",
        "tgn:7000084",
        "tgn:7029392"
    ],
    "tgn:id":7162366,
    "tgn:name":"Hornum",
    "tgn:placetype":[
        "aat:300000206"
    ]
},
  "bbox": [],
  "geometry": {"coordinates":[7.816667,53.583333],"type":"Point"}
}