{
  "id": 2724211,
  "type": "Feature",
  "properties": {
    "tgn:hierarchy":[
        "tgn:2724211",
        "tgn:1000001",
        "tgn:7012149",
        "tgn:2000818",
        "tgn:7007255",
        "tgn:7029392"
    ],
    "tgn:id":2724211,
    "tgn:name":"Tom Clark Hollow",
    "tgn:placetype":[
        "aat:300008761"
    ]
},
  "bbox": [],
  "geometry": {"coordinates":[-84.45,36.9333],"type":"Point"}
}