{
  "id": 2717575,
  "type": "Feature",
  "properties": {
    "tgn:hierarchy":[
        "tgn:2717575",
        "tgn:1000001",
        "tgn:7012149",
        "tgn:2001708",
        "tgn:7007708",
        "tgn:7029392"
    ],
    "tgn:id":2717575,
    "tgn:name":"Thomas Cavender Reservoir",
    "tgn:placetype":[
        "aat:300006191"
    ]
},
  "bbox": [],
  "geometry": {"coordinates":[-119.4167,44.8167],"type":"Point"}
}