{
  "id": 2217588,
  "type": "Feature",
  "properties": {
    "tgn:hierarchy":[
        "tgn:2217588",
        "tgn:1000001",
        "tgn:7012149",
        "tgn:7015666",
        "tgn:7007825",
        "tgn:7029392"
    ],
    "tgn:id":2217588,
    "tgn:name":"Campbell Hill",
    "tgn:placetype":[
        "aat:300008798"
    ]
},
  "bbox": [],
  "geometry": {"coordinates":[-87.3167,35.8167],"type":"Point"}
}