<<<<<<< HEAD
{
  "id": 2156949,
  "type": "Feature",
  "properties": {
    "tgn:hierarchy":[
        "tgn:2156949",
        "tgn:2000090",
        "tgn:1000001",
        "tgn:7006451",
        "tgn:7012149",
        "tgn:7029392"
    ],
    "tgn:id":2156949,
    "tgn:name":"Beautiful Valley",
    "tgn:placetype":[
        "aat:300008761"
    ]
},
  "bbox": [],
  "geometry": {"coordinates":[-109.5,35.8333],"type":"Point"}
}
=======
{"geometry":{"type":"Point","coordinates":[-109.500000,35.833300]},"type":"Feature","properties":{"hierarchy":["tgn:2156949","tgn:2000090","tgn:1000001","tgn:7006451","tgn:7012149","tgn:7029392"],"placetype":["aat:300008761"],"id":2156949,"name:xx":"Beautiful Valley"}}
>>>>>>> 03f74aca74312dbeaf24d7e61306dd6a786dc3d0
