{
  "id": 7398752,
  "type": "Feature",
  "properties": {
    "tgn:hierarchy":[
        "tgn:7398752",
        "tgn:1000001",
        "tgn:1001893",
        "tgn:7005560",
        "tgn:7029392"
    ],
    "tgn:id":7398752,
    "tgn:name":"Plan de San Mart\u00edn",
    "tgn:placetype":[
        "aat:300008347"
    ]
},
  "bbox": [],
  "geometry": {"coordinates":[-99.568611,19.011111],"type":"Point"}
}