{
  "id": 2180851,
  "type": "Feature",
  "properties": {
    "tgn:hierarchy":[
        "tgn:2180851",
        "tgn:7002659",
        "tgn:1000001",
        "tgn:7012149",
        "tgn:2000037",
        "tgn:7029392"
    ],
    "tgn:id":2180851,
    "tgn:name":"Blowhorn Creek",
    "tgn:placetype":[
        "aat:300008706"
    ]
},
  "bbox": [],
  "geometry": {"coordinates":[-87.95,33.7833],"type":"Point"}
}