{
  "id": 7055725,
  "type": "Feature",
  "properties": {
    "tgn:hierarchy":[
        "tgn:7055725",
        "tgn:7002994",
        "tgn:1000003",
        "tgn:7002997",
        "tgn:1000080",
        "tgn:7029392"
    ],
    "tgn:id":7055725,
    "tgn:name":"Levada di Sotto",
    "tgn:placetype":[
        "aat:300008347"
    ]
},
  "bbox": [],
  "geometry": {"coordinates":[12.066667,45.616667],"type":"Point"}
}