{
  "id": 7191186,
  "type": "Feature",
  "properties": {
    "tgn:hierarchy":[
        "tgn:7191186",
        "tgn:1000003",
        "tgn:7003682",
        "tgn:7000084",
        "tgn:7029392"
    ],
    "tgn:id":7191186,
    "tgn:name":"Finkenkreuzer",
    "tgn:placetype":[
        "aat:300004792"
    ]
},
  "bbox": [],
  "geometry": {"coordinates":[7.483333,49.383333],"type":"Point"}
}