{
  "id": 7317841,
  "type": "Feature",
  "properties": {
    "tgn:hierarchy":[
        "tgn:7317841",
        "tgn:1001630",
        "tgn:1000049",
        "tgn:1000002",
        "tgn:7029392"
    ],
    "tgn:id":7317841,
    "tgn:name":"Cortadera, Quebrada",
    "tgn:placetype":[
        "aat:300266554",
        "aat:300008699"
    ]
},
  "bbox": [],
  "geometry": {"coordinates":[-70.183333,-27.583333],"type":"Point"}
}