{
  "id": 2459724,
  "type": "Feature",
  "properties": {
    "tgn:hierarchy":[
        "tgn:2459724",
        "tgn:1000001",
        "tgn:7012149",
        "tgn:7007157",
        "tgn:1002957",
        "tgn:7029392"
    ],
    "tgn:id":2459724,
    "tgn:name":"Little Reynolds Creek",
    "tgn:placetype":[
        "aat:300008706"
    ]
},
  "bbox": [],
  "geometry": {"coordinates":[-119.9333,38.0667],"type":"Point"}
}