{
  "id": 1091058,
  "type": "Feature",
  "properties": {
    "tgn:hierarchy":[
        "tgn:1091058",
        "tgn:7001242",
        "tgn:1001459",
        "tgn:7000726",
        "tgn:7029392"
    ],
    "tgn:id":1091058,
    "tgn:name":"Chitipa",
    "tgn:placetype":[
        "aat:300008347"
    ]
},
  "bbox": [],
  "geometry": {"coordinates":[33.3167,-9.6833],"type":"Point"}
}