{
  "id": 7426132,
  "type": "Feature",
  "properties": {
    "tgn:hierarchy":[
        "tgn:7426132",
        "tgn:1000001",
        "tgn:7005594",
        "tgn:7005560",
        "tgn:7029392"
    ],
    "tgn:id":7426132,
    "tgn:name":"Villar",
    "tgn:placetype":[
        "aat:300008347"
    ]
},
  "bbox": [],
  "geometry": {"coordinates":[-100.466667,22.55],"type":"Point"}
}