{
  "id": 7576421,
  "type": "Feature",
  "properties": {
    "tgn:hierarchy":[
        "tgn:7576421",
        "tgn:1000004",
        "tgn:7000198",
        "tgn:7031786",
        "tgn:7029392"
    ],
    "tgn:id":7576421,
    "tgn:name:en":"K\u0101ndi",
    "tgn:placetype":[
        "aat:300008347"
    ]
},
  "bbox": [],
  "geometry": {"coordinates":[78.454271,29.943968],"type":"Point"}
}