{
  "id": 7468336,
  "type": "Feature",
  "properties": {
    "tgn:hierarchy":[
        "tgn:7468336",
        "tgn:1000004",
        "tgn:7467799",
        "tgn:1000141",
        "tgn:7029392"
    ],
    "tgn:id":7468336,
    "tgn:name":"Xingang",
    "tgn:placetype":[
        "aat:300008347"
    ]
},
  "bbox": [],
  "geometry": {"coordinates":[120.489722,24.172222],"type":"Point"}
}