{
  "id": 7364198,
  "type": "Feature",
  "properties": {
    "tgn:hierarchy":[
        "tgn:7364198",
        "tgn:7016644",
        "tgn:1000001",
        "tgn:7005560",
        "tgn:7029392"
    ],
    "tgn:id":7364198,
    "tgn:name":"El Ciruelo",
    "tgn:placetype":[
        "aat:300008347"
    ]
},
  "bbox": [],
  "geometry": {"coordinates":[-104.166667,18.966667],"type":"Point"}
}