{
  "id": 2165123,
  "type": "Feature",
  "properties": {
    "tgn:hierarchy":[
        "tgn:2165123",
        "tgn:1000001",
        "tgn:1002279",
        "tgn:7012149",
        "tgn:7007706",
        "tgn:7029392"
    ],
    "tgn:id":2165123,
    "tgn:name":"Bethel Reservoir",
    "tgn:placetype":[
        "aat:300006191"
    ]
},
  "bbox": [],
  "geometry": {"coordinates":[-84.0667,38.9833],"type":"Point"}
}