{
  "id": 2726777,
  "type": "Feature",
  "properties": {
    "tgn:hierarchy":[
        "tgn:2726777",
        "tgn:1000001",
        "tgn:1002461",
        "tgn:7012149",
        "tgn:7007159",
        "tgn:7029392"
    ],
    "tgn:id":2726777,
    "tgn:name":"Town Woods Hill",
    "tgn:placetype":[
        "aat:300008798"
    ]
},
  "bbox": [],
  "geometry": {"coordinates":[-72.55,41.6833],"type":"Point"}
}