{
  "id": 7147465,
  "type": "Feature",
  "properties": {
    "tgn:hierarchy":[
        "tgn:7147465",
        "tgn:7003669",
        "tgn:1000003",
        "tgn:7000084",
        "tgn:7029392"
    ],
    "tgn:id":7147465,
    "tgn:name":"Laag",
    "tgn:placetype":[
        "aat:300008347"
    ]
},
  "bbox": [],
  "geometry": {"coordinates":[11.333333,48.583333],"type":"Point"}
}