<<<<<<< HEAD
{
  "id": 7179411,
  "type": "Feature",
  "properties": {
    "tgn:hierarchy":[
        "tgn:7179411",
        "tgn:1000003",
        "tgn:7003682",
        "tgn:7000084",
        "tgn:7029392"
    ],
    "tgn:id":7179411,
    "tgn:name":"Hahnweilerhof",
    "tgn:placetype":[
        "aat:300008347"
    ]
},
  "bbox": [],
  "geometry": {"coordinates":[7.916667,49.6],"type":"Point"}
}
=======
{"geometry":{"type":"Point","coordinates":[7.916667,49.600000]},"type":"Feature","properties":{"hierarchy":["tgn:7179411","tgn:1000003","tgn:7003682","tgn:7000084","tgn:7029392"],"placetype":["aat:300008347"],"id":7179411,"name:xx":"Hahnweilerhof"}}
>>>>>>> 03f74aca74312dbeaf24d7e61306dd6a786dc3d0
