<<<<<<< HEAD
{
  "id": 2151878,
  "type": "Feature",
  "properties": {
    "tgn:hierarchy":[
        "tgn:2151878",
        "tgn:2000090",
        "tgn:1000001",
        "tgn:7006451",
        "tgn:7012149",
        "tgn:7029392"
    ],
    "tgn:id":2151878,
    "tgn:name":"Battleship, The",
    "tgn:placetype":[
        "aat:300008798"
    ]
},
  "bbox": [],
  "geometry": {"coordinates":[-109.7667,34.85],"type":"Point"}
}
=======
{"geometry":{"type":"Point","coordinates":[-109.766700,34.850000]},"type":"Feature","properties":{"hierarchy":["tgn:2151878","tgn:2000090","tgn:1000001","tgn:7006451","tgn:7012149","tgn:7029392"],"placetype":["aat:300008798"],"id":2151878,"name:xx":"Battleship, The"}}
>>>>>>> 03f74aca74312dbeaf24d7e61306dd6a786dc3d0
