{
  "id": 7383661,
  "type": "Feature",
  "properties": {
    "tgn:hierarchy":[
        "tgn:7383661",
        "tgn:1000001",
        "tgn:7005596",
        "tgn:7005560",
        "tgn:7029392"
    ],
    "tgn:id":7383661,
    "tgn:name":"Nuevo M\u00e9xico",
    "tgn:placetype":[
        "aat:300008347"
    ]
},
  "bbox": [],
  "geometry": {"coordinates":[-91.233333,17.533333],"type":"Point"}
}