{
  "id": 7261982,
  "type": "Feature",
  "properties": {
    "tgn:concordances":{
        "gn:id":"2756949"
    },
    "tgn:hierarchy":[
        "tgn:7261982",
        "tgn:1000003",
        "tgn:7006951",
        "tgn:7016845",
        "tgn:7029392"
    ],
    "tgn:id":7261982,
    "tgn:name:nl":"De Weere",
    "tgn:placetype":[
        "aat:300008347"
    ]
},
  "bbox": [],
  "geometry": {"coordinates":[4.883333,52.766667],"type":"Point"}
}