<<<<<<< HEAD
{
  "id": 7369461,
  "type": "Feature",
  "properties": {
    "tgn:hierarchy":[
        "tgn:7369461",
        "tgn:7005580",
        "tgn:1000001",
        "tgn:7005560",
        "tgn:7029392"
    ],
    "tgn:id":7369461,
    "tgn:name":"Guadalupe Victoria",
    "tgn:placetype":[
        "aat:300008347"
    ]
},
  "bbox": [],
  "geometry": {"coordinates":[-92.4,15.15],"type":"Point"}
}
=======
{"geometry":{"type":"Point","coordinates":[-92.400000,15.150000]},"type":"Feature","properties":{"hierarchy":["tgn:7369461","tgn:7005580","tgn:1000001","tgn:7005560","tgn:7029392"],"placetype":["aat:300008347"],"id":7369461,"name:xx":"Guadalupe Victoria"}}
>>>>>>> 03f74aca74312dbeaf24d7e61306dd6a786dc3d0
