{
  "id": 2551691,
  "type": "Feature",
  "properties": {
    "tgn:hierarchy":[
        "tgn:2551691",
        "tgn:1000001",
        "tgn:7012149",
        "tgn:2001250",
        "tgn:7007523",
        "tgn:7029392"
    ],
    "tgn:id":2551691,
    "tgn:name":"Number 44 Lake",
    "tgn:placetype":[
        "aat:300006191"
    ]
},
  "bbox": [],
  "geometry": {"coordinates":[-93.0667,40.05],"type":"Point"}
}