{
  "id": 2308685,
  "type": "Feature",
  "properties": {
    "tgn:hierarchy":[
        "tgn:2308685",
        "tgn:7030516",
        "tgn:7006450",
        "tgn:1000001",
        "tgn:7012149",
        "tgn:7029392"
    ],
    "tgn:id":2308685,
    "tgn:name":"East Peak",
    "tgn:placetype":[
        "aat:300008798"
    ]
},
  "bbox": [],
  "geometry": {"coordinates":[173.25,52.9167],"type":"Point"}
}