{
  "id": 1086667,
  "type": "Feature",
  "properties": {
    "tgn:hierarchy":[
        "tgn:1086667",
        "tgn:1000004",
        "tgn:1001606",
        "tgn:7018453",
        "tgn:1000144",
        "tgn:7029392"
    ],
    "tgn:id":1086667,
    "tgn:name":"Mamure",
    "tgn:placetype":[
        "aat:300008347"
    ]
},
  "bbox": [],
  "geometry": {"coordinates":[35.2833,40.1333],"type":"Point"}
}