{
  "id": 2528972,
  "type": "Feature",
  "properties": {
    "tgn:hierarchy":[
        "tgn:2528972",
        "tgn:1000001",
        "tgn:1002317",
        "tgn:7012149",
        "tgn:7007706",
        "tgn:7029392"
    ],
    "tgn:id":2528972,
    "tgn:name":"Mud Creek",
    "tgn:placetype":[
        "aat:300008706"
    ]
},
  "bbox": [],
  "geometry": {"coordinates":[-84.6833,39.9667],"type":"Point"}
}