{
  "id": 2649068,
  "type": "Feature",
  "properties": {
    "tgn:hierarchy":[
        "tgn:2649068",
        "tgn:1000001",
        "tgn:7012149",
        "tgn:7007568",
        "tgn:7029392"
    ],
    "tgn:id":2649068,
    "tgn:name":"Scott Gulf",
    "tgn:placetype":[
        "aat:300008761"
    ]
},
  "bbox": [],
  "geometry": {"coordinates":[-76.2833,42.7333],"type":"Point"}
}