<<<<<<< HEAD
{
  "id": 7179579,
  "type": "Feature",
  "properties": {
    "tgn:hierarchy":[
        "tgn:7179579",
        "tgn:1000003",
        "tgn:7003688",
        "tgn:7000084",
        "tgn:7029392"
    ],
    "tgn:id":7179579,
    "tgn:name":"Hamburgerbaum",
    "tgn:placetype":[
        "aat:300000206"
    ]
},
  "bbox": [],
  "geometry": {"coordinates":[10.116667,54.3],"type":"Point"}
}
=======
{"geometry":{"type":"Point","coordinates":[10.116667,54.300000]},"type":"Feature","properties":{"hierarchy":["tgn:7179579","tgn:1000003","tgn:7003688","tgn:7000084","tgn:7029392"],"placetype":["aat:300000206"],"id":7179579,"name:xx":"Hamburgerbaum"}}
>>>>>>> 03f74aca74312dbeaf24d7e61306dd6a786dc3d0
