{
  "id": 7591980,
  "type": "Feature",
  "properties": {
    "tgn:hierarchy":[
        "tgn:7591980",
        "tgn:1000004",
        "tgn:7000198",
        "tgn:7000799",
        "tgn:7029392"
    ],
    "tgn:id":7591980,
    "tgn:name:en":"D\u0101bar",
    "tgn:placetype":[
        "aat:300008347"
    ]
},
  "bbox": [],
  "geometry": {"coordinates":[74.869712,32.967679],"type":"Point"}
}