{
  "id": 7314463,
  "type": "Feature",
  "properties": {
    "tgn:hierarchy":[
        "tgn:7314463",
        "tgn:1001699",
        "tgn:1000049",
        "tgn:1000002",
        "tgn:7029392"
    ],
    "tgn:id":7314463,
    "tgn:name":"Lompu\u00e9, Cerros de",
    "tgn:placetype":[
        "aat:300008795"
    ]
},
  "bbox": [],
  "geometry": {"coordinates":[-73.683333,-40.466667],"type":"Point"}
}