{
  "id": 7055804,
  "type": "Feature",
  "properties": {
    "tgn:hierarchy":[
        "tgn:7055804",
        "tgn:1003440",
        "tgn:1000003",
        "tgn:7003124",
        "tgn:1000080",
        "tgn:7029392"
    ],
    "tgn:id":7055804,
    "tgn:name":"Plima, Rio",
    "tgn:placetype":[
        "aat:300008699"
    ]
},
  "bbox": [],
  "geometry": {"coordinates":[10.833333,46.616667],"type":"Point"}
}