{
  "id": 2216498,
  "type": "Feature",
  "properties": {
    "tgn:hierarchy":[
        "tgn:2216498",
        "tgn:1000001",
        "tgn:7012149",
        "tgn:2000909",
        "tgn:7007256",
        "tgn:7029392"
    ],
    "tgn:id":2216498,
    "tgn:name":"Camp Creek",
    "tgn:placetype":[
        "aat:300008706"
    ]
},
  "bbox": [],
  "geometry": {"coordinates":[-92.5667,32.9167],"type":"Point"}
}