{
  "id": 1036028,
  "type": "Feature",
  "properties": {
    "tgn:hierarchy":[
        "tgn:1036028",
        "tgn:1000003",
        "tgn:1000070",
        "tgn:7002897",
        "tgn:7029392"
    ],
    "tgn:id":1036028,
    "tgn:name":"Vaulx-en-Velin",
    "tgn:placetype":[
        "aat:300008347"
    ]
},
  "bbox": [],
  "geometry": {"coordinates":[4.9333,45.7833],"type":"Point"}
}