{
  "id": 7469805,
  "type": "Feature",
  "properties": {
    "tgn:hierarchy":[
        "tgn:7469805",
        "tgn:7468018",
        "tgn:1000004",
        "tgn:1000141",
        "tgn:7029392"
    ],
    "tgn:id":7469805,
    "tgn:name":"Haibu",
    "tgn:placetype":[
        "aat:300008347"
    ]
},
  "bbox": [],
  "geometry": {"coordinates":[120.184976,23.4706],"type":"Point"}
}