{
  "id": 2263575,
  "type": "Feature",
  "properties": {
    "tgn:hierarchy":[
        "tgn:2263575",
        "tgn:1000001",
        "tgn:7012149",
        "tgn:7007712",
        "tgn:7029392"
    ],
    "tgn:id":2263575,
    "tgn:name":"Coxs Creek",
    "tgn:placetype":[
        "aat:300008706"
    ]
},
  "bbox": [],
  "geometry": {"coordinates":[-81.4833,34.6167],"type":"Point"}
}