{
  "id": 2054689,
  "type": "Feature",
  "properties": {
    "tgn:hierarchy":[
        "tgn:2054689",
        "tgn:1000001",
        "tgn:2001025",
        "tgn:7012149",
        "tgn:7007521",
        "tgn:7029392"
    ],
    "tgn:id":2054689,
    "tgn:name":"Hopkins",
    "tgn:placetype":[
        "aat:300008347"
    ]
},
  "bbox": [],
  "geometry": {"coordinates":[-93.45,44.9167],"type":"Point"}
}