{
  "id": 1037884,
  "type": "Feature",
  "properties": {
    "tgn:hierarchy":[
        "tgn:1037884",
        "tgn:1000003",
        "tgn:7003689",
        "tgn:7000084",
        "tgn:7029392"
    ],
    "tgn:id":1037884,
    "tgn:name":"Unterwellen",
    "tgn:placetype":[
        "aat:300008347"
    ]
},
  "bbox": [],
  "geometry": {"coordinates":[11.4333,50.65],"type":"Point"}
}