{
  "id": 7230708,
  "type": "Feature",
  "properties": {
    "tgn:hierarchy":[
        "tgn:7230708",
        "tgn:7002680",
        "tgn:7001395",
        "tgn:1000003",
        "tgn:1000074",
        "tgn:7029392"
    ],
    "tgn:id":7230708,
    "tgn:name":"Matar\u00e1nga",
    "tgn:placetype":[
        "aat:300008347"
    ]
},
  "bbox": [],
  "geometry": {"coordinates":[21.466667,38.516667],"type":"Point"}
}