{
  "id": 2026595,
  "type": "Feature",
  "properties": {
    "tgn:hierarchy":[
        "tgn:2026595",
        "tgn:1000001",
        "tgn:7012149",
        "tgn:1002531",
        "tgn:7007251",
        "tgn:7029392"
    ],
    "tgn:id":2026595,
    "tgn:name":"Big Rock",
    "tgn:placetype":[
        "aat:300008347"
    ]
},
  "bbox": [],
  "geometry": {"coordinates":[-88.5333,41.75],"type":"Point"}
}