{
  "id": 1045231,
  "type": "Feature",
  "properties": {
    "tgn:hierarchy":[
        "tgn:1045231",
        "tgn:1003506",
        "tgn:1000003",
        "tgn:7002993",
        "tgn:1000080",
        "tgn:7029392"
    ],
    "tgn:id":1045231,
    "tgn:name":"Marano Lagunare",
    "tgn:placetype":[
        "aat:300008347"
    ]
},
  "bbox": [],
  "geometry": {"coordinates":[13.169167,45.766389],"type":"Point"}
}