<<<<<<< HEAD
{
  "id": 2255501,
  "type": "Feature",
  "properties": {
    "tgn:hierarchy":[
        "tgn:2255501",
        "tgn:1000001",
        "tgn:7012149",
        "tgn:2000363",
        "tgn:7007248",
        "tgn:7029392"
    ],
    "tgn:id":2255501,
    "tgn:name":"Copeland",
    "tgn:placetype":[
        "aat:300008347"
    ]
},
  "bbox": [],
  "geometry": {"coordinates":[-84.95,32.7833],"type":"Point"}
}
=======
{"geometry":{"type":"Point","coordinates":[-84.950000,32.783300]},"type":"Feature","properties":{"hierarchy":["tgn:2255501","tgn:1000001","tgn:7012149","tgn:2000363","tgn:7007248","tgn:7029392"],"placetype":["aat:300008347"],"id":2255501,"name:xx":"Copeland"}}
>>>>>>> 03f74aca74312dbeaf24d7e61306dd6a786dc3d0
