{
  "id": 7075551,
  "type": "Feature",
  "properties": {
    "tgn:hierarchy":[
        "tgn:7075551",
        "tgn:1000003",
        "tgn:7003676",
        "tgn:7000084",
        "tgn:7029392"
    ],
    "tgn:id":7075551,
    "tgn:name":"Middeldorf",
    "tgn:placetype":[
        "aat:300008347"
    ]
},
  "bbox": [],
  "geometry": {"coordinates":[8.383333,53.083333],"type":"Point"}
}