{
  "id": 7498330,
  "type": "Feature",
  "properties": {
    "tgn:hierarchy":[
        "tgn:7498330",
        "tgn:1000004",
        "tgn:7492971",
        "tgn:1000141",
        "tgn:7029392"
    ],
    "tgn:id":7498330,
    "tgn:name":"Dingyuancun",
    "tgn:placetype":[
        "aat:300008347"
    ]
},
  "bbox": [],
  "geometry": {"coordinates":[120.533607,22.8199],"type":"Point"}
}