{
  "id": 2255384,
  "type": "Feature",
  "properties": {
    "tgn:hierarchy":[
        "tgn:2255384",
        "tgn:1000001",
        "tgn:7012149",
        "tgn:2001911",
        "tgn:7007825",
        "tgn:7029392"
    ],
    "tgn:id":2255384,
    "tgn:name":"Coops Branch",
    "tgn:placetype":[
        "aat:300008699"
    ]
},
  "bbox": [],
  "geometry": {"coordinates":[-86.3833,35.5333],"type":"Point"}
}