{
  "id": 7433118,
  "type": "Feature",
  "properties": {
    "tgn:hierarchy":[
        "tgn:7433118",
        "tgn:7005581",
        "tgn:1000001",
        "tgn:7005560",
        "tgn:7029392"
    ],
    "tgn:id":7433118,
    "tgn:name":"Yeso, Cerro del",
    "tgn:placetype":[
        "aat:300008777"
    ]
},
  "bbox": [],
  "geometry": {"coordinates":[-103.816667,27.316667],"type":"Point"}
}