{
  "id": 7425029,
  "type": "Feature",
  "properties": {
    "tgn:hierarchy":[
        "tgn:7425029",
        "tgn:1000001",
        "tgn:7005597",
        "tgn:7005560",
        "tgn:7029392"
    ],
    "tgn:id":7425029,
    "tgn:name":"Espiaderos",
    "tgn:placetype":[
        "aat:300008347"
    ]
},
  "bbox": [],
  "geometry": {"coordinates":[-98.133333,25.35],"type":"Point"}
}