{
  "id": 7468775,
  "type": "Feature",
  "properties": {
    "tgn:hierarchy":[
        "tgn:7468775",
        "tgn:1000004",
        "tgn:7001013",
        "tgn:1000141",
        "tgn:7029392"
    ],
    "tgn:id":7468775,
    "tgn:name":"Zhongzheng Li",
    "tgn:placetype":[
        "aat:300387173"
    ]
},
  "bbox": [],
  "geometry": {"coordinates":[121.29235,24.99955],"type":"Point"}
}