<<<<<<< HEAD
{
  "id": 7355275,
  "type": "Feature",
  "properties": {
    "tgn:hierarchy":[
        "tgn:7355275",
        "tgn:1000001",
        "tgn:1001960",
        "tgn:7005560",
        "tgn:7029392"
    ],
    "tgn:id":7355275,
    "tgn:name":"Cedro, Arroyo",
    "tgn:placetype":[
        "aat:300008699"
    ]
},
  "bbox": [],
  "geometry": {"coordinates":[-109.1,27.233333],"type":"Point"}
}
=======
{"geometry":{"type":"Point","coordinates":[-109.100000,27.233333]},"type":"Feature","properties":{"hierarchy":["tgn:7355275","tgn:1000001","tgn:1001960","tgn:7005560","tgn:7029392"],"placetype":["aat:300008699"],"id":7355275,"name:xx":"Cedro, Arroyo"}}
>>>>>>> 03f74aca74312dbeaf24d7e61306dd6a786dc3d0
