<<<<<<< HEAD
{
  "id": 7021391,
  "type": "Feature",
  "properties": {
    "tgn:hierarchy":[
        "tgn:7021391",
        "tgn:1000001",
        "tgn:7012149",
        "tgn:7029392"
    ],
    "tgn:id":7021391,
    "tgn:name":"Wardlow Creek",
    "tgn:placetype":[
        "aat:300008706"
    ]
},
  "bbox": [],
  "geometry": {"coordinates":[-88.4333,35.05],"type":"Point"}
}
=======
{"geometry":{"type":"Point","coordinates":[-88.433300,35.050000]},"type":"Feature","properties":{"hierarchy":["tgn:7021391","tgn:1000001","tgn:7012149","tgn:7029392"],"placetype":["aat:300008706"],"id":7021391,"name:xx":"Wardlow Creek"}}
>>>>>>> 03f74aca74312dbeaf24d7e61306dd6a786dc3d0
