{
  "id": 2570787,
  "type": "Feature",
  "properties": {
    "tgn:hierarchy":[
        "tgn:2570787",
        "tgn:1000001",
        "tgn:7012149",
        "tgn:2000927",
        "tgn:7007515",
        "tgn:7029392"
    ],
    "tgn:id":2570787,
    "tgn:name":"Patten Pond",
    "tgn:placetype":[
        "aat:300008680"
    ]
},
  "bbox": [],
  "geometry": {"coordinates":[-68.95,44.75],"type":"Point"}
}