{
  "id": 7510085,
  "type": "Feature",
  "properties": {
    "tgn:hierarchy":[
        "tgn:7510085",
        "tgn:1009227",
        "tgn:1000226",
        "tgn:1000006",
        "tgn:7016850",
        "tgn:7029392"
    ],
    "tgn:id":7510085,
    "tgn:name:en":"Stillwater Creek",
    "tgn:placetype":[
        "aat:300008699"
    ]
},
  "bbox": [],
  "geometry": {"coordinates":[171.35,-42.433333],"type":"Point"}
}