{
  "id": 1061500,
  "type": "Feature",
  "properties": {
    "tgn:hierarchy":[
        "tgn:1061500",
        "tgn:1000004",
        "tgn:1003405",
        "tgn:7018214",
        "tgn:7002435",
        "tgn:7029392"
    ],
    "tgn:id":1061500,
    "tgn:name":"Zajmo-Obryv",
    "tgn:placetype":[
        "aat:300008347"
    ]
},
  "bbox": [],
  "geometry": {"coordinates":[39.3167,47.0333],"type":"Point"}
}