{
  "id": 1113772,
  "type": "Feature",
  "properties": {
    "tgn:hierarchy":[
        "tgn:1113772",
        "tgn:7005685",
        "tgn:1000001",
        "tgn:7005801",
        "tgn:7029392"
    ],
    "tgn:id":1113772,
    "tgn:name":"Sandwich Bay",
    "tgn:placetype":[
        "aat:300132316"
    ]
},
  "bbox": [],
  "geometry": {"coordinates":[-57.25,53.5833],"type":"Point"}
}