{
  "id": 7539830,
  "type": "Feature",
  "properties": {
    "tgn:hierarchy":[
        "tgn:7539830",
        "tgn:7001242",
        "tgn:7016833",
        "tgn:1001110",
        "tgn:7029392"
    ],
    "tgn:id":7539830,
    "tgn:name:en":"Qaryat al Jan\u0101'in",
    "tgn:placetype":[
        "aat:300008347"
    ]
},
  "bbox": [],
  "geometry": {"coordinates":[32.516667,30.15],"type":"Point"}
}