{
  "id": 7524908,
  "type": "Feature",
  "properties": {
    "tgn:hierarchy":[
        "tgn:7524908",
        "tgn:7001242",
        "tgn:7016833",
        "tgn:1001418",
        "tgn:7029392"
    ],
    "tgn:id":7524908,
    "tgn:name:en":"Burt Sab\u00e2i el-Gharbi, 'Alam",
    "tgn:placetype":[
        "aat:300008777"
    ]
},
  "bbox": [],
  "geometry": {"coordinates":[28.74436,30.816505],"type":"Point"}
}