{
  "id": 7282310,
  "type": "Feature",
  "properties": {
    "tgn:hierarchy":[
        "tgn:7282310",
        "tgn:7016598",
        "tgn:1000049",
        "tgn:1000002",
        "tgn:7029392"
    ],
    "tgn:id":7282310,
    "tgn:name":"Purilactis, Aguada de",
    "tgn:placetype":[
        "aat:300008697"
    ]
},
  "bbox": [],
  "geometry": {"coordinates":[-68.416667,-22.766667],"type":"Point"}
}