{
  "id": 2239537,
  "type": "Feature",
  "properties": {
    "tgn:hierarchy":[
        "tgn:2239537",
        "tgn:1002201",
        "tgn:1000001",
        "tgn:7012149",
        "tgn:7007517",
        "tgn:7029392"
    ],
    "tgn:id":2239537,
    "tgn:name":"Church Rock",
    "tgn:placetype":[
        "aat:300011692"
    ]
},
  "bbox": [],
  "geometry": {"coordinates":[-70.8833,41.55],"type":"Point"}
}