{
  "id": 1065618,
  "type": "Feature",
  "properties": {
    "tgn:hierarchy":[
        "tgn:1065618",
        "tgn:7000189",
        "tgn:1000004",
        "tgn:1000105",
        "tgn:7029392"
    ],
    "tgn:id":1065618,
    "tgn:name":"Bh\u0101nga",
    "tgn:placetype":[
        "aat:300008347"
    ]
},
  "bbox": [],
  "geometry": {"coordinates":[89.9833,23.3667],"type":"Point"}
}