{
  "id": 2254804,
  "type": "Feature",
  "properties": {
    "tgn:hierarchy":[
        "tgn:2254804",
        "tgn:1000001",
        "tgn:2001263",
        "tgn:7012149",
        "tgn:7007524",
        "tgn:7029392"
    ],
    "tgn:id":2254804,
    "tgn:name":"Cooney Gulch",
    "tgn:placetype":[
        "aat:300008761"
    ]
},
  "bbox": [],
  "geometry": {"coordinates":[-111.55,46.7333],"type":"Point"}
}