{
  "id": 7221395,
  "type": "Feature",
  "properties": {
    "tgn:hierarchy":[
        "tgn:7221395",
        "tgn:7011163",
        "tgn:7002674",
        "tgn:1000003",
        "tgn:1000074",
        "tgn:7029392"
    ],
    "tgn:id":7221395,
    "tgn:name":"Tsoukalokh\u00f3rion",
    "tgn:placetype":[
        "aat:300008347"
    ]
},
  "bbox": [],
  "geometry": {"coordinates":[26.066667,39.266667],"type":"Point"}
}