{
  "id": 7403929,
  "type": "Feature",
  "properties": {
    "tgn:hierarchy":[
        "tgn:7403929",
        "tgn:7005585",
        "tgn:1000001",
        "tgn:7005560",
        "tgn:7029392"
    ],
    "tgn:id":7403929,
    "tgn:name":"Parque Natural Grutas de Juxtlahuaca",
    "tgn:placetype":[
        "aat:300008187"
    ]
},
  "bbox": [],
  "geometry": {"coordinates":[-99.125,17.416667],"type":"Point"}
}