{
  "id": 7413043,
  "type": "Feature",
  "properties": {
    "tgn:hierarchy":[
        "tgn:7413043",
        "tgn:7005580",
        "tgn:1000001",
        "tgn:7005560",
        "tgn:7029392"
    ],
    "tgn:id":7413043,
    "tgn:name":"Los Pozos",
    "tgn:placetype":[
        "aat:300008347"
    ]
},
  "bbox": [],
  "geometry": {"coordinates":[-92.566667,16.85],"type":"Point"}
}