{
  "id": 7154827,
  "type": "Feature",
  "properties": {
    "tgn:hierarchy":[
        "tgn:7154827",
        "tgn:1000003",
        "tgn:7003688",
        "tgn:7000084",
        "tgn:7029392"
    ],
    "tgn:id":7154827,
    "tgn:name":"Ketel",
    "tgn:placetype":[
        "aat:300000206"
    ]
},
  "bbox": [],
  "geometry": {"coordinates":[10.533333,53.816667],"type":"Point"}
}