{
  "id": 2489925,
  "type": "Feature",
  "properties": {
    "tgn:hierarchy":[
        "tgn:2489925",
        "tgn:1002366",
        "tgn:1000001",
        "tgn:7012149",
        "tgn:7007159",
        "tgn:7029392"
    ],
    "tgn:id":2489925,
    "tgn:name":"Mamanasco Lake",
    "tgn:placetype":[
        "aat:300008680"
    ]
},
  "bbox": [],
  "geometry": {"coordinates":[-73.5167,41.3167],"type":"Point"}
}