{
  "id": 7592173,
  "type": "Feature",
  "properties": {
    "tgn:hierarchy":[
        "tgn:7592173",
        "tgn:1000004",
        "tgn:7000198",
        "tgn:7000799",
        "tgn:7029392"
    ],
    "tgn:id":7592173,
    "tgn:name:en":"Khalka Mal\u0101l",
    "tgn:placetype":[
        "aat:300008347"
    ]
},
  "bbox": [],
  "geometry": {"coordinates":[74.54055,32.830959],"type":"Point"}
}