{
  "id": 7552809,
  "type": "Feature",
  "properties": {
    "tgn:hierarchy":[
        "tgn:7552809",
        "tgn:1009838",
        "tgn:7000204",
        "tgn:1000004",
        "tgn:7000198",
        "tgn:1009218",
        "tgn:7029392"
    ],
    "tgn:id":7552809,
    "tgn:name:en":"Palmer Point",
    "tgn:placetype":[
        "aat:300386846"
    ]
},
  "bbox": [],
  "geometry": {"coordinates":[92.566667,11.683333],"type":"Point"}
}