{
  "id": 2672549,
  "type": "Feature",
  "properties": {
    "tgn:hierarchy":[
        "tgn:2672549",
        "tgn:1000001",
        "tgn:7012149",
        "tgn:2002252",
        "tgn:7007920",
        "tgn:7029392"
    ],
    "tgn:id":2672549,
    "tgn:name":"Smoot Hill",
    "tgn:placetype":[
        "aat:300008798"
    ]
},
  "bbox": [],
  "geometry": {"coordinates":[-117.2333,46.8167],"type":"Point"}
}