{
  "id": 2299993,
  "type": "Feature",
  "properties": {
    "tgn:hierarchy":[
        "tgn:2299993",
        "tgn:1000001",
        "tgn:2001702",
        "tgn:7012149",
        "tgn:7007708",
        "tgn:7029392"
    ],
    "tgn:id":2299993,
    "tgn:name":"Dufort Creek",
    "tgn:placetype":[
        "aat:300008706"
    ]
},
  "bbox": [],
  "geometry": {"coordinates":[-124.3833,43.0833],"type":"Point"}
}