{
  "id": 2333570,
  "type": "Feature",
  "properties": {
    "tgn:hierarchy":[
        "tgn:2333570",
        "tgn:1000001",
        "tgn:7013686",
        "tgn:7012149",
        "tgn:7007517",
        "tgn:7029392"
    ],
    "tgn:id":2333570,
    "tgn:name":"Fomer",
    "tgn:placetype":[
        "aat:300008347"
    ]
},
  "bbox": [],
  "geometry": {"coordinates":[-72.7833,42.2333],"type":"Point"}
}