{
  "id": 7141595,
  "type": "Feature",
  "properties": {
    "tgn:hierarchy":[
        "tgn:7141595",
        "tgn:1000003",
        "tgn:7003677",
        "tgn:7000084",
        "tgn:7029392"
    ],
    "tgn:id":7141595,
    "tgn:name":"Lum-Berg",
    "tgn:placetype":[
        "aat:300008777"
    ]
},
  "bbox": [],
  "geometry": {"coordinates":[8.233333,51.233333],"type":"Point"}
}