{
  "id": 2305969,
  "type": "Feature",
  "properties": {
    "tgn:hierarchy":[
        "tgn:2305969",
        "tgn:1000001",
        "tgn:7012149",
        "tgn:2000711",
        "tgn:7007254",
        "tgn:7029392"
    ],
    "tgn:id":2305969,
    "tgn:name":"East Fairmount",
    "tgn:placetype":[
        "aat:300008347"
    ]
},
  "bbox": [],
  "geometry": {"coordinates":[-94.9167,39.1833],"type":"Point"}
}