{
  "id": 7585061,
  "type": "Feature",
  "properties": {
    "tgn:hierarchy":[
        "tgn:7585061",
        "tgn:1000004",
        "tgn:7000198",
        "tgn:7016788",
        "tgn:7029392"
    ],
    "tgn:id":7585061,
    "tgn:name:en":"P\u0101t\u016bsari",
    "tgn:placetype":[
        "aat:300008347"
    ]
},
  "bbox": [],
  "geometry": {"coordinates":[75.453291,28.050363],"type":"Point"}
}