{
  "id": 7558041,
  "type": "Feature",
  "properties": {
    "tgn:hierarchy":[
        "tgn:7558041",
        "tgn:1000004",
        "tgn:7000198",
        "tgn:1001905",
        "tgn:7029392"
    ],
    "tgn:id":7558041,
    "tgn:name:en":"Pangti",
    "tgn:placetype":[
        "aat:300008347"
    ]
},
  "bbox": [],
  "geometry": {"coordinates":[94.319418,26.26167],"type":"Point"}
}