<<<<<<< HEAD
{
  "id": 2760870,
  "type": "Feature",
  "properties": {
    "tgn:hierarchy":[
        "tgn:2760870",
        "tgn:1000001",
        "tgn:7012149",
        "tgn:1002986",
        "tgn:7007568",
        "tgn:7029392"
    ],
    "tgn:id":2760870,
    "tgn:name":"West Hill",
    "tgn:placetype":[
        "aat:300008798"
    ]
},
  "bbox": [],
  "geometry": {"coordinates":[-73.9833,43.7167],"type":"Point"}
}
=======
{"geometry":{"type":"Point","coordinates":[-73.983300,43.716700]},"type":"Feature","properties":{"hierarchy":["tgn:2760870","tgn:1000001","tgn:7012149","tgn:1002986","tgn:7007568","tgn:7029392"],"placetype":["aat:300008798"],"id":2760870,"name:xx":"West Hill"}}
>>>>>>> 03f74aca74312dbeaf24d7e61306dd6a786dc3d0
