{
  "id": 2420111,
  "type": "Feature",
  "properties": {
    "tgn:hierarchy":[
        "tgn:2420111",
        "tgn:1000001",
        "tgn:7016172",
        "tgn:7012149",
        "tgn:2000136",
        "tgn:7029392"
    ],
    "tgn:id":2420111,
    "tgn:name":"Jeff Weaver Prospect",
    "tgn:placetype":[
        "aat:300000390"
    ]
},
  "bbox": [],
  "geometry": {"coordinates":[-91.6167,35.8833],"type":"Point"}
}