{
  "id": 2381226,
  "type": "Feature",
  "properties": {
    "tgn:hierarchy":[
        "tgn:2381226",
        "tgn:1000001",
        "tgn:7012149",
        "tgn:2002170",
        "tgn:7007919",
        "tgn:7029392"
    ],
    "tgn:id":2381226,
    "tgn:name":"Hawkwood Lake",
    "tgn:placetype":[
        "aat:300006191"
    ]
},
  "bbox": [],
  "geometry": {"coordinates":[-78.1833,38.0167],"type":"Point"}
}