{
  "id": 7170244,
  "type": "Feature",
  "properties": {
    "tgn:hierarchy":[
        "tgn:7170244",
        "tgn:1000003",
        "tgn:7003676",
        "tgn:7000084",
        "tgn:7029392"
    ],
    "tgn:id":7170244,
    "tgn:name":"Hestrup",
    "tgn:placetype":[
        "aat:300008347"
    ]
},
  "bbox": [],
  "geometry": {"coordinates":[7.133333,52.383333],"type":"Point"}
}