{
  "id": 7580210,
  "type": "Feature",
  "properties": {
    "tgn:hierarchy":[
        "tgn:7580210",
        "tgn:1000004",
        "tgn:1001869",
        "tgn:7000198",
        "tgn:7029392"
    ],
    "tgn:id":7580210,
    "tgn:name:en":"Thar\u0101d",
    "tgn:placetype":[
        "aat:300008347"
    ]
},
  "bbox": [],
  "geometry": {"coordinates":[71.421271,24.035934],"type":"Point"}
}