<<<<<<< HEAD
{
  "id": 2155487,
  "type": "Feature",
  "properties": {
    "tgn:hierarchy":[
        "tgn:2155487",
        "tgn:1000001",
        "tgn:7012149",
        "tgn:2002161",
        "tgn:7007919",
        "tgn:7029392"
    ],
    "tgn:id":2155487,
    "tgn:name":"Bear Ridge",
    "tgn:placetype":[
        "aat:300266640"
    ]
},
  "bbox": [],
  "geometry": {"coordinates":[-78.3833,39.1833],"type":"Point"}
}
=======
{"geometry":{"type":"Point","coordinates":[-78.383300,39.183300]},"type":"Feature","properties":{"hierarchy":["tgn:2155487","tgn:1000001","tgn:7012149","tgn:2002161","tgn:7007919","tgn:7029392"],"placetype":["aat:300266640"],"id":2155487,"name:xx":"Bear Ridge"}}
>>>>>>> 03f74aca74312dbeaf24d7e61306dd6a786dc3d0
