{
  "id": 7132180,
  "type": "Feature",
  "properties": {
    "tgn:hierarchy":[
        "tgn:7132180",
        "tgn:7003669",
        "tgn:1000003",
        "tgn:7000084",
        "tgn:7029392"
    ],
    "tgn:id":7132180,
    "tgn:name":"Maul-Kopf",
    "tgn:placetype":[
        "aat:300008795"
    ]
},
  "bbox": [],
  "geometry": {"coordinates":[10.883333,47.633333],"type":"Point"}
}