{
  "id": 2686198,
  "type": "Feature",
  "properties": {
    "tgn:hierarchy":[
        "tgn:2686198",
        "tgn:1000001",
        "tgn:7012149",
        "tgn:7014589",
        "tgn:7007515",
        "tgn:7029392"
    ],
    "tgn:id":2686198,
    "tgn:name":"Spring Cove",
    "tgn:placetype":[
        "aat:300132316"
    ]
},
  "bbox": [],
  "geometry": {"coordinates":[-67.9167,45.2167],"type":"Point"}
}