{
  "id": 2031782,
  "type": "Feature",
  "properties": {
    "tgn:hierarchy":[
        "tgn:2031782",
        "tgn:1000001",
        "tgn:7012149",
        "tgn:2000552",
        "tgn:7007252",
        "tgn:7029392"
    ],
    "tgn:id":2031782,
    "tgn:name":"Farmersville",
    "tgn:placetype":[
        "aat:300008347",
        "aat:300387210"
    ]
},
  "bbox": [],
  "geometry": {"coordinates":[-87.8833,37.9667],"type":"Point"}
}