<<<<<<< HEAD
{
  "id": 2255255,
  "type": "Feature",
  "properties": {
    "tgn:hierarchy":[
        "tgn:2255255",
        "tgn:1000001",
        "tgn:7012149",
        "tgn:2002287",
        "tgn:7013961",
        "tgn:7029392"
    ],
    "tgn:id":2255255,
    "tgn:name":"Cooper Run",
    "tgn:placetype":[
        "aat:300008699"
    ]
},
  "bbox": [],
  "geometry": {"coordinates":[-79.7667,38.3833],"type":"Point"}
}
=======
{"geometry":{"type":"Point","coordinates":[-79.766700,38.383300]},"type":"Feature","properties":{"hierarchy":["tgn:2255255","tgn:1000001","tgn:7012149","tgn:2002287","tgn:7013961","tgn:7029392"],"placetype":["aat:300008699"],"id":2255255,"name:xx":"Cooper Run"}}
>>>>>>> 03f74aca74312dbeaf24d7e61306dd6a786dc3d0
