{
  "id": 2241637,
  "type": "Feature",
  "properties": {
    "tgn:hierarchy":[
        "tgn:2241637",
        "tgn:1000001",
        "tgn:7012149",
        "tgn:2001315",
        "tgn:7007524",
        "tgn:7029392"
    ],
    "tgn:id":2241637,
    "tgn:name":"Clarks Fork Ditch",
    "tgn:placetype":[
        "aat:300006075"
    ]
},
  "bbox": [],
  "geometry": {"coordinates":[-108.7833,45.6333],"type":"Point"}
}