{
  "id": 7495241,
  "type": "Feature",
  "properties": {
    "tgn:hierarchy":[
        "tgn:7495241",
        "tgn:7468018",
        "tgn:1000004",
        "tgn:1000141",
        "tgn:7029392"
    ],
    "tgn:id":7495241,
    "tgn:name":"Zihjhu Sih",
    "tgn:placetype":[
        "aat:300007595"
    ]
},
  "bbox": [],
  "geometry": {"coordinates":[120.513583,23.430906],"type":"Point"}
}