{
  "id": 7444675,
  "type": "Feature",
  "properties": {
    "tgn:hierarchy":[
        "tgn:7444675",
        "tgn:7002444",
        "tgn:1000003",
        "tgn:7019085",
        "tgn:7008591",
        "tgn:7029392"
    ],
    "tgn:id":7444675,
    "tgn:name:en":"Turnberry Point",
    "tgn:placetype":[
        "aat:300386846"
    ]
},
  "bbox": [],
  "geometry": {"coordinates":[-4.833333,55.316667],"type":"Point"}
}