{
  "id": 7163816,
  "type": "Feature",
  "properties": {
    "tgn:hierarchy":[
        "tgn:7163816",
        "tgn:1000003",
        "tgn:7003678",
        "tgn:7000084",
        "tgn:7029392"
    ],
    "tgn:id":7163816,
    "tgn:name":"F\u00f6rsterei Kammergrund",
    "tgn:placetype":[
        "aat:300004792"
    ]
},
  "bbox": [],
  "geometry": {"coordinates":[9.383333,51.533333],"type":"Point"}
}