{
  "id": 7258585,
  "type": "Feature",
  "properties": {
    "tgn:hierarchy":[
        "tgn:7258585",
        "tgn:1000003",
        "tgn:7003632",
        "tgn:7016845",
        "tgn:7029392"
    ],
    "tgn:id":7258585,
    "tgn:name:nl":"Benedenpolder",
    "tgn:placetype":[
        "aat:300006163"
    ]
},
  "bbox": [],
  "geometry": {"coordinates":[4.316667,51.75],"type":"Point"}
}