{
  "id": 2379046,
  "type": "Feature",
  "properties": {
    "tgn:hierarchy":[
        "tgn:2379046",
        "tgn:1000001",
        "tgn:7012149",
        "tgn:7007157",
        "tgn:1002656",
        "tgn:7029392"
    ],
    "tgn:id":2379046,
    "tgn:name":"Hartley Lateral",
    "tgn:placetype":[
        "aat:300006075"
    ]
},
  "bbox": [],
  "geometry": {"coordinates":[-120.4833,37.25],"type":"Point"}
}