{
  "id": 7143446,
  "type": "Feature",
  "properties": {
    "tgn:hierarchy":[
        "tgn:7143446",
        "tgn:7003669",
        "tgn:1000003",
        "tgn:7000084",
        "tgn:7029392"
    ],
    "tgn:id":7143446,
    "tgn:name":"Loding",
    "tgn:placetype":[
        "aat:300000206"
    ]
},
  "bbox": [],
  "geometry": {"coordinates":[12.683333,48.05],"type":"Point"}
}