{
  "id": 2066358,
  "type": "Feature",
  "properties": {
    "tgn:hierarchy":[
        "tgn:2066358",
        "tgn:1000001",
        "tgn:7014090",
        "tgn:7012149",
        "tgn:7007565",
        "tgn:7029392"
    ],
    "tgn:id":2066358,
    "tgn:name":"Union Beach",
    "tgn:placetype":[
        "aat:300008347"
    ]
},
  "bbox": [],
  "geometry": {"coordinates":[-74.1667,40.4333],"type":"Point"}
}