{
  "id": 2340530,
  "type": "Feature",
  "properties": {
    "tgn:hierarchy":[
        "tgn:2340530",
        "tgn:1000001",
        "tgn:7012149",
        "tgn:7007157",
        "tgn:1002828",
        "tgn:7029392"
    ],
    "tgn:id":2340530,
    "tgn:name":"French Valley",
    "tgn:placetype":[
        "aat:300008761"
    ]
},
  "bbox": [],
  "geometry": {"coordinates":[-117.0667,33.65],"type":"Point"}
}