{
  "id": 2425170,
  "type": "Feature",
  "properties": {
    "tgn:hierarchy":[
        "tgn:2425170",
        "tgn:1000001",
        "tgn:7006451",
        "tgn:7012149",
        "tgn:2000104",
        "tgn:7029392"
    ],
    "tgn:id":2425170,
    "tgn:name":"Johnson Lateral",
    "tgn:placetype":[
        "aat:300006075"
    ]
},
  "bbox": [],
  "geometry": {"coordinates":[-114.6833,32.5667],"type":"Point"}
}