{
  "id": 2388403,
  "type": "Feature",
  "properties": {
    "tgn:hierarchy":[
        "tgn:2388403",
        "tgn:1000001",
        "tgn:7012149",
        "tgn:2002292",
        "tgn:7013961",
        "tgn:7029392"
    ],
    "tgn:id":2388403,
    "tgn:name":"Hickory Run",
    "tgn:placetype":[
        "aat:300008699"
    ]
},
  "bbox": [],
  "geometry": {"coordinates":[-81.25,39.1667],"type":"Point"}
}