{
  "id": 7205532,
  "type": "Feature",
  "properties": {
    "tgn:hierarchy":[
        "tgn:7205532",
        "tgn:1000003",
        "tgn:7003685",
        "tgn:7000084",
        "tgn:7029392"
    ],
    "tgn:id":7205532,
    "tgn:name":"Vorwerk Burkersdorf",
    "tgn:placetype":[
        "aat:300000206"
    ]
},
  "bbox": [],
  "geometry": {"coordinates":[14.216667,51.016667],"type":"Point"}
}