{
  "id": 7028279,
  "type": "Feature",
  "properties": {
    "tgn:hierarchy":[
        "tgn:7028279",
        "tgn:7002445",
        "tgn:1000003",
        "tgn:7008160",
        "tgn:7008591",
        "tgn:7029392"
    ],
    "tgn:id":7028279,
    "tgn:name":"Belaugh",
    "tgn:placetype":[
        "aat:300008347",
        "aat:300008372"
    ]
},
  "bbox": [],
  "geometry": {"coordinates":[1.389,52.702],"type":"Point"}
}