{
  "id": 2272173,
  "type": "Feature",
  "properties": {
    "tgn:hierarchy":[
        "tgn:2272173",
        "tgn:1000001",
        "tgn:2001411",
        "tgn:7012149",
        "tgn:7007526",
        "tgn:7029392"
    ],
    "tgn:id":2272173,
    "tgn:name":"Currie Ponds",
    "tgn:placetype":[
        "aat:300006191"
    ]
},
  "bbox": [],
  "geometry": {"coordinates":[-114.75,40.2333],"type":"Point"}
}