{
  "id": 2253183,
  "type": "Feature",
  "properties": {
    "tgn:hierarchy":[
        "tgn:2253183",
        "tgn:1000001",
        "tgn:2001414",
        "tgn:7012149",
        "tgn:7007526",
        "tgn:7029392"
    ],
    "tgn:id":2253183,
    "tgn:name":"Continental Lake",
    "tgn:placetype":[
        "aat:300008680"
    ]
},
  "bbox": [],
  "geometry": {"coordinates":[-118.7167,41.8833],"type":"Point"}
}