<<<<<<< HEAD
{
  "id": 2253183,
  "type": "Feature",
  "properties": {
    "tgn:hierarchy":[
        "tgn:2253183",
        "tgn:1000001",
        "tgn:2001414",
        "tgn:7012149",
        "tgn:7007526",
        "tgn:7029392"
    ],
    "tgn:id":2253183,
    "tgn:name":"Continental Lake",
    "tgn:placetype":[
        "aat:300008680"
    ]
},
  "bbox": [],
  "geometry": {"coordinates":[-118.7167,41.8833],"type":"Point"}
}
=======
{"geometry":{"type":"Point","coordinates":[-118.716700,41.883300]},"type":"Feature","properties":{"hierarchy":["tgn:2253183","tgn:1000001","tgn:2001414","tgn:7012149","tgn:7007526","tgn:7029392"],"placetype":["aat:300008680"],"id":2253183,"name:xx":"Continental Lake"}}
>>>>>>> 03f74aca74312dbeaf24d7e61306dd6a786dc3d0
