{
  "id": 1077725,
  "type": "Feature",
  "properties": {
    "tgn:hierarchy":[
        "tgn:1077725",
        "tgn:1000004",
        "tgn:1001339",
        "tgn:1000116",
        "tgn:7029392"
    ],
    "tgn:id":1077725,
    "tgn:name":"Intu",
    "tgn:placetype":[
        "aat:300008347"
    ]
},
  "bbox": [],
  "geometry": {"coordinates":[115.35,-0.25],"type":"Point"}
}