{
  "id": 2621866,
  "type": "Feature",
  "properties": {
    "tgn:hierarchy":[
        "tgn:2621866",
        "tgn:7006450",
        "tgn:1000001",
        "tgn:7012149",
        "tgn:2000086",
        "tgn:7029392"
    ],
    "tgn:id":2621866,
    "tgn:name":"Robe River",
    "tgn:placetype":[
        "aat:300008707"
    ]
},
  "bbox": [],
  "geometry": {"coordinates":[-146.1667,61.0833],"type":"Point"}
}