{
  "id": 7263757,
  "type": "Feature",
  "properties": {
    "tgn:hierarchy":[
        "tgn:7263757",
        "tgn:1000003",
        "tgn:7003632",
        "tgn:7016845",
        "tgn:7029392"
    ],
    "tgn:id":7263757,
    "tgn:name:nl":"Julianahaven",
    "tgn:placetype":[
        "aat:300120599"
    ]
},
  "bbox": [],
  "geometry": {"coordinates":[4.633333,51.783333],"type":"Point"}
}