{
  "id": 2683856,
  "type": "Feature",
  "properties": {
    "tgn:hierarchy":[
        "tgn:2683856",
        "tgn:1000001",
        "tgn:7012149",
        "tgn:7007158",
        "tgn:2000253",
        "tgn:7029392"
    ],
    "tgn:id":2683856,
    "tgn:name":"Speer Canal",
    "tgn:placetype":[
        "aat:300006075"
    ]
},
  "bbox": [],
  "geometry": {"coordinates":[-104.7167,40.1167],"type":"Point"}
}