{
  "id": 7360989,
  "type": "Feature",
  "properties": {
    "tgn:hierarchy":[
        "tgn:7360989",
        "tgn:7005581",
        "tgn:1000001",
        "tgn:7005560",
        "tgn:7029392"
    ],
    "tgn:id":7360989,
    "tgn:name":"El Bosque",
    "tgn:placetype":[
        "aat:300008347"
    ]
},
  "bbox": [],
  "geometry": {"coordinates":[-105.666667,26.833333],"type":"Point"}
}