{
  "id": 7087210,
  "type": "Feature",
  "properties": {
    "tgn:hierarchy":[
        "tgn:7087210",
        "tgn:1000003",
        "tgn:7003677",
        "tgn:7000084",
        "tgn:7029392"
    ],
    "tgn:id":7087210,
    "tgn:name":"Waldfeucht",
    "tgn:placetype":[
        "aat:300008347"
    ]
},
  "bbox": [],
  "geometry": {"coordinates":[5.983333,51.066667],"type":"Point"}
}