{
  "id": 1081658,
  "type": "Feature",
  "properties": {
    "tgn:hierarchy":[
        "tgn:1081658",
        "tgn:1000975",
        "tgn:1000004",
        "tgn:7000901",
        "tgn:1000120",
        "tgn:7029392"
    ],
    "tgn:id":1081658,
    "tgn:name":"Ukiha",
    "tgn:placetype":[
        "aat:300008347"
    ]
},
  "bbox": [],
  "geometry": {"coordinates":[130.7833,33.3167],"type":"Point"}
}