{
  "id": 7433583,
  "type": "Feature",
  "properties": {
    "tgn:hierarchy":[
        "tgn:7433583",
        "tgn:1000001",
        "tgn:7005600",
        "tgn:7005560",
        "tgn:7029392"
    ],
    "tgn:id":7433583,
    "tgn:name":"Yaxch\u00e9",
    "tgn:placetype":[
        "aat:300008347"
    ]
},
  "bbox": [],
  "geometry": {"coordinates":[-89.75,21.05],"type":"Point"}
}