{
  "id": 2339934,
  "type": "Feature",
  "properties": {
    "tgn:hierarchy":[
        "tgn:2339934",
        "tgn:1000001",
        "tgn:2000265",
        "tgn:7012149",
        "tgn:7007240",
        "tgn:7029392"
    ],
    "tgn:id":2339934,
    "tgn:name":"Freeman Springs Branch",
    "tgn:placetype":[
        "aat:300008699"
    ]
},
  "bbox": [],
  "geometry": {"coordinates":[-87.5667,30.9167],"type":"Point"}
}