<<<<<<< HEAD
{
  "id": 2339934,
  "type": "Feature",
  "properties": {
    "tgn:hierarchy":[
        "tgn:2339934",
        "tgn:1000001",
        "tgn:2000265",
        "tgn:7012149",
        "tgn:7007240",
        "tgn:7029392"
    ],
    "tgn:id":2339934,
    "tgn:name":"Freeman Springs Branch",
    "tgn:placetype":[
        "aat:300008699"
    ]
},
  "bbox": [],
  "geometry": {"coordinates":[-87.5667,30.9167],"type":"Point"}
}
=======
{"geometry":{"type":"Point","coordinates":[-87.566700,30.916700]},"type":"Feature","properties":{"hierarchy":["tgn:2339934","tgn:1000001","tgn:2000265","tgn:7012149","tgn:7007240","tgn:7029392"],"placetype":["aat:300008699"],"id":2339934,"name:xx":"Freeman Springs Branch"}}
>>>>>>> 03f74aca74312dbeaf24d7e61306dd6a786dc3d0
