{
  "id": 7585998,
  "type": "Feature",
  "properties": {
    "tgn:hierarchy":[
        "tgn:7585998",
        "tgn:1000004",
        "tgn:7000198",
        "tgn:7000799",
        "tgn:7029392"
    ],
    "tgn:id":7585998,
    "tgn:name:en":"Brimshan Forest",
    "tgn:placetype":[
        "aat:300008863"
    ]
},
  "bbox": [],
  "geometry": {"coordinates":[74.833333,34.330556],"type":"Point"}
}