<<<<<<< HEAD
{
  "id": 2333340,
  "type": "Feature",
  "properties": {
    "tgn:hierarchy":[
        "tgn:2333340",
        "tgn:1000001",
        "tgn:7012149",
        "tgn:7015666",
        "tgn:7007825",
        "tgn:7029392"
    ],
    "tgn:id":2333340,
    "tgn:name":"Fogg Hollow",
    "tgn:placetype":[
        "aat:300008761"
    ]
},
  "bbox": [],
  "geometry": {"coordinates":[-87.3667,35.75],"type":"Point"}
}
=======
{"geometry":{"type":"Point","coordinates":[-87.366700,35.750000]},"type":"Feature","properties":{"hierarchy":["tgn:2333340","tgn:1000001","tgn:7012149","tgn:7015666","tgn:7007825","tgn:7029392"],"placetype":["aat:300008761"],"id":2333340,"name:xx":"Fogg Hollow"}}
>>>>>>> 03f74aca74312dbeaf24d7e61306dd6a786dc3d0
