{
  "id": 2373934,
  "type": "Feature",
  "properties": {
    "tgn:hierarchy":[
        "tgn:2373934",
        "tgn:1000001",
        "tgn:7012149",
        "tgn:1002619",
        "tgn:7007523",
        "tgn:7029392"
    ],
    "tgn:id":2373934,
    "tgn:name":"Hammack",
    "tgn:placetype":[
        "aat:300008347"
    ]
},
  "bbox": [],
  "geometry": {"coordinates":[-92.7167,39.7167],"type":"Point"}
}