{
  "id": 2308195,
  "type": "Feature",
  "properties": {
    "tgn:hierarchy":[
        "tgn:2308195",
        "tgn:1000001",
        "tgn:7012149",
        "tgn:7007919",
        "tgn:7029392"
    ],
    "tgn:id":2308195,
    "tgn:name":"East Knob",
    "tgn:placetype":[
        "aat:300008798"
    ]
},
  "bbox": [],
  "geometry": {"coordinates":[-80.4667,36.7167],"type":"Point"}
}