{
  "id": 1136648,
  "type": "Feature",
  "properties": {
    "tgn:hierarchy":[
        "tgn:1136648",
        "tgn:7593913",
        "tgn:1000003",
        "tgn:1001780",
        "tgn:7029392"
    ],
    "tgn:id":1136648,
    "tgn:name":"Hranice",
    "tgn:placetype":[
        "aat:300008347"
    ]
},
  "bbox": [],
  "geometry": {"coordinates":[12.1833,50.2833],"type":"Point"}
}