{
  "id": 2464128,
  "type": "Feature",
  "properties": {
    "tgn:hierarchy":[
        "tgn:2464128",
        "tgn:1000001",
        "tgn:7012149",
        "tgn:2002168",
        "tgn:7007919",
        "tgn:7029392"
    ],
    "tgn:id":2464128,
    "tgn:name":"Locust Hollow",
    "tgn:placetype":[
        "aat:300008761"
    ]
},
  "bbox": [],
  "geometry": {"coordinates":[-79.4333,38.2167],"type":"Point"}
}