{
  "id": 7399714,
  "type": "Feature",
  "properties": {
    "tgn:hierarchy":[
        "tgn:7399714",
        "tgn:1000001",
        "tgn:7005593",
        "tgn:7005560",
        "tgn:7029392"
    ],
    "tgn:id":7399714,
    "tgn:name":"Rancho Viejo",
    "tgn:placetype":[
        "aat:300008347"
    ]
},
  "bbox": [],
  "geometry": {"coordinates":[-99.905556,20.925],"type":"Point"}
}