{
  "id": 7533706,
  "type": "Feature",
  "properties": {
    "tgn:hierarchy":[
        "tgn:7533706",
        "tgn:7001242",
        "tgn:7016833",
        "tgn:7001312",
        "tgn:7029392"
    ],
    "tgn:id":7533706,
    "tgn:name:en":"Kafr Ma\u1e29allat \u1e28asan",
    "tgn:placetype":[
        "aat:300008347"
    ]
},
  "bbox": [],
  "geometry": {"coordinates":[31.166667,31.033333],"type":"Point"}
}