{
  "id": 7482236,
  "type": "Feature",
  "properties": {
    "tgn:hierarchy":[
        "tgn:7482236",
        "tgn:1000004",
        "tgn:7492971",
        "tgn:1000141",
        "tgn:7029392"
    ],
    "tgn:id":7482236,
    "tgn:name":"Majia Guomin Zhongxiaoxue",
    "tgn:placetype":[
        "aat:300006495"
    ]
},
  "bbox": [],
  "geometry": {"coordinates":[120.645437,22.705899],"type":"Point"}
}