{
  "id": 7511121,
  "type": "Feature",
  "properties": {
    "tgn:hierarchy":[
        "tgn:7511121",
        "tgn:1009227",
        "tgn:1000226",
        "tgn:7520095",
        "tgn:1000006",
        "tgn:7029392"
    ],
    "tgn:id":7511121,
    "tgn:name:en":"Slippery Creek",
    "tgn:placetype":[
        "aat:300008699"
    ]
},
  "bbox": [],
  "geometry": {"coordinates":[172.716667,-41.466667],"type":"Point"}
}