{
  "id": 2780899,
  "type": "Feature",
  "properties": {
    "tgn:hierarchy":[
        "tgn:2780899",
        "tgn:1000001",
        "tgn:7012149",
        "tgn:2001307",
        "tgn:7007524",
        "tgn:7029392"
    ],
    "tgn:id":2780899,
    "tgn:name":"Woodbine Lake",
    "tgn:placetype":[
        "aat:300008680"
    ]
},
  "bbox": [],
  "geometry": {"coordinates":[-109.8667,45.2833],"type":"Point"}
}