{
  "id": 1085414,
  "type": "Feature",
  "properties": {
    "tgn:hierarchy":[
        "tgn:1085414",
        "tgn:1000004",
        "tgn:7490934",
        "tgn:1000141",
        "tgn:7029392"
    ],
    "tgn:id":1085414,
    "tgn:name":"Yen-shui-chen",
    "tgn:placetype":[
        "aat:300008347"
    ]
},
  "bbox": [],
  "geometry": {"coordinates":[120.267222,23.32],"type":"Point"}
}