{
  "id": 2208636,
  "type": "Feature",
  "properties": {
    "tgn:hierarchy":[
        "tgn:2208636",
        "tgn:1000001",
        "tgn:7012149",
        "tgn:7007157",
        "tgn:1002869",
        "tgn:7029392"
    ],
    "tgn:id":2208636,
    "tgn:name":"Burns Creek",
    "tgn:placetype":[
        "aat:300008706"
    ]
},
  "bbox": [],
  "geometry": {"coordinates":[-121.9833,37.1333],"type":"Point"}
}