{
  "id": 7593728,
  "type": "Feature",
  "properties": {
    "tgn:hierarchy":[
        "tgn:7593728",
        "tgn:1000556",
        "tgn:7001242",
        "tgn:7024167",
        "tgn:1000208",
        "tgn:7029392"
    ],
    "tgn:id":7593728,
    "tgn:name":"Laongo Longo",
    "tgn:placetype":[
        "aat:300008347"
    ]
},
  "bbox": [],
  "geometry": {"coordinates":[-1.214,12.537],"type":"Point"}
}