{
  "id": 7314404,
  "type": "Feature",
  "properties": {
    "tgn:hierarchy":[
        "tgn:7314404",
        "tgn:1001657",
        "tgn:1000049",
        "tgn:1000002",
        "tgn:7029392"
    ],
    "tgn:id":7314404,
    "tgn:name":"Los Llanos",
    "tgn:placetype":[
        "aat:300008347"
    ]
},
  "bbox": [],
  "geometry": {"coordinates":[-70.783333,-30.966667],"type":"Point"}
}