{
  "id": 2716052,
  "type": "Feature",
  "properties": {
    "tgn:hierarchy":[
        "tgn:2716052",
        "tgn:2000090",
        "tgn:1000001",
        "tgn:7006451",
        "tgn:7012149",
        "tgn:7029392"
    ],
    "tgn:id":2716052,
    "tgn:name":"Tezinie Canyon",
    "tgn:placetype":[
        "aat:300008761"
    ]
},
  "bbox": [],
  "geometry": {"coordinates":[-109.4167,36.2833],"type":"Point"}
}