{
  "id": 2327243,
  "type": "Feature",
  "properties": {
    "tgn:hierarchy":[
        "tgn:2327243",
        "tgn:1000001",
        "tgn:7012149",
        "tgn:2000928",
        "tgn:7007515",
        "tgn:7029392"
    ],
    "tgn:id":2327243,
    "tgn:name":"First Currier Pond",
    "tgn:placetype":[
        "aat:300008680"
    ]
},
  "bbox": [],
  "geometry": {"coordinates":[-69.0833,46.4167],"type":"Point"}
}