{
  "id": 2371287,
  "type": "Feature",
  "properties": {
    "tgn:hierarchy":[
        "tgn:2371287",
        "tgn:1000001",
        "tgn:7012149",
        "tgn:2001715",
        "tgn:7007708",
        "tgn:7029392"
    ],
    "tgn:id":2371287,
    "tgn:name":"Hahilly Reservoir Number Four",
    "tgn:placetype":[
        "aat:300006191"
    ]
},
  "bbox": [],
  "geometry": {"coordinates":[-119.9167,42.05],"type":"Point"}
}