{
  "id": 2612664,
  "type": "Feature",
  "properties": {
    "tgn:hierarchy":[
        "tgn:2612664",
        "tgn:1000001",
        "tgn:7012149",
        "tgn:2000351",
        "tgn:7007248",
        "tgn:7029392"
    ],
    "tgn:id":2612664,
    "tgn:name":"Redding Lake",
    "tgn:placetype":[
        "aat:300006191"
    ]
},
  "bbox": [],
  "geometry": {"coordinates":[-84.6333,33.5667],"type":"Point"}
}