<<<<<<< HEAD
{
  "id": 7026460,
  "type": "Feature",
  "properties": {
    "tgn:hierarchy":[
        "tgn:7026460",
        "tgn:7002445",
        "tgn:1000003",
        "tgn:7008168",
        "tgn:7008591",
        "tgn:7029392"
    ],
    "tgn:id":7026460,
    "tgn:name":"Shippon",
    "tgn:placetype":[
        "aat:300008347",
        "aat:300000874"
    ]
},
  "bbox": [],
  "geometry": {"coordinates":[-1.3,51.6833],"type":"Point"}
}
=======
{"geometry":{"type":"Point","coordinates":[-1.300000,51.683300]},"type":"Feature","properties":{"hierarchy":["tgn:7026460","tgn:7002445","tgn:1000003","tgn:7008168","tgn:7008591","tgn:7029392"],"placetype":["aat:300008347","aat:300000874"],"id":7026460,"name:xx":"Shippon"}}
>>>>>>> 03f74aca74312dbeaf24d7e61306dd6a786dc3d0
