{
  "id": 7501191,
  "type": "Feature",
  "properties": {
    "tgn:hierarchy":[
        "tgn:7501191",
        "tgn:1000004",
        "tgn:7467799",
        "tgn:1000141",
        "tgn:7029392"
    ],
    "tgn:id":7501191,
    "tgn:name":"Zhenxia",
    "tgn:placetype":[
        "aat:300008347"
    ]
},
  "bbox": [],
  "geometry": {"coordinates":[120.501667,24.140278],"type":"Point"}
}