{
  "id": 7563938,
  "type": "Feature",
  "properties": {
    "tgn:hierarchy":[
        "tgn:7563938",
        "tgn:1000004",
        "tgn:7000198",
        "tgn:7016722",
        "tgn:7029392"
    ],
    "tgn:id":7563938,
    "tgn:name:en":"Malhe",
    "tgn:placetype":[
        "aat:300008347"
    ]
},
  "bbox": [],
  "geometry": {"coordinates":[79.831214,26.567461],"type":"Point"}
}