{
  "id": 1079670,
  "type": "Feature",
  "properties": {
    "tgn:hierarchy":[
        "tgn:1079670",
        "tgn:1000991",
        "tgn:1000004",
        "tgn:7000903",
        "tgn:1000120",
        "tgn:7029392"
    ],
    "tgn:id":1079670,
    "tgn:name":"\u014cgata",
    "tgn:placetype":[
        "aat:300008347"
    ]
},
  "bbox": [],
  "geometry": {"coordinates":[133.0167,33.0167],"type":"Point"}
}