{
  "id": 7533449,
  "type": "Feature",
  "properties": {
    "tgn:hierarchy":[
        "tgn:7533449",
        "tgn:7001242",
        "tgn:1001059",
        "tgn:7016833",
        "tgn:7029392"
    ],
    "tgn:id":7533449,
    "tgn:name:en":"Kafr \u1e28ajj\u0101j",
    "tgn:placetype":[
        "aat:300008347"
    ]
},
  "bbox": [],
  "geometry": {"coordinates":[31.890583,31.154484],"type":"Point"}
}