{
  "id": 7302819,
  "type": "Feature",
  "properties": {
    "tgn:hierarchy":[
        "tgn:7302819",
        "tgn:7008912",
        "tgn:7030216",
        "tgn:1000003",
        "tgn:1000095",
        "tgn:7029392"
    ],
    "tgn:id":7302819,
    "tgn:name":"Mulieres, Pico de",
    "tgn:placetype":[
        "aat:300008798"
    ]
},
  "bbox": [],
  "geometry": {"coordinates":[0.698664,42.628835],"type":"Point"}
}