{
  "id": 2535427,
  "type": "Feature",
  "properties": {
    "tgn:hierarchy":[
        "tgn:2535427",
        "tgn:1000001",
        "tgn:7012149",
        "tgn:2001446",
        "tgn:7007566",
        "tgn:7029392"
    ],
    "tgn:id":2535427,
    "tgn:name":"Naranjos",
    "tgn:placetype":[
        "aat:300008347"
    ]
},
  "bbox": [],
  "geometry": {"coordinates":[-104.9667,36.15],"type":"Point"}
}