{
  "id": 1050846,
  "type": "Feature",
  "properties": {
    "tgn:hierarchy":[
        "tgn:1050846",
        "tgn:7002444",
        "tgn:1000003",
        "tgn:7008082",
        "tgn:7008591",
        "tgn:7029392"
    ],
    "tgn:id":1050846,
    "tgn:name:en":"Laide",
    "tgn:placetype":[
        "aat:300008347"
    ]
},
  "bbox": [],
  "geometry": {"coordinates":[-5.533333,57.866667],"type":"Point"}
}