{
  "id": 7147589,
  "type": "Feature",
  "properties": {
    "tgn:hierarchy":[
        "tgn:7147589",
        "tgn:7003669",
        "tgn:1000003",
        "tgn:7000084",
        "tgn:7029392"
    ],
    "tgn:id":7147589,
    "tgn:name":"Kreuz\u00f6d",
    "tgn:placetype":[
        "aat:300000206"
    ]
},
  "bbox": [],
  "geometry": {"coordinates":[12.75,48.383333],"type":"Point"}
}