{
  "id": 2375389,
  "type": "Feature",
  "properties": {
    "tgn:hierarchy":[
        "tgn:2375389",
        "tgn:1000001",
        "tgn:7012149",
        "tgn:2001708",
        "tgn:7007708",
        "tgn:7029392"
    ],
    "tgn:id":2375389,
    "tgn:name":"Hanscombe Creek",
    "tgn:placetype":[
        "aat:300008706"
    ]
},
  "bbox": [],
  "geometry": {"coordinates":[-119.0333,44.2833],"type":"Point"}
}