{
  "id": 7084436,
  "type": "Feature",
  "properties": {
    "tgn:hierarchy":[
        "tgn:7084436",
        "tgn:7003669",
        "tgn:1000003",
        "tgn:7000084",
        "tgn:7029392"
    ],
    "tgn:id":7084436,
    "tgn:name":"Weitenh\u00fcll",
    "tgn:placetype":[
        "aat:300387200"
    ]
},
  "bbox": [],
  "geometry": {"coordinates":[12.516667,48.75],"type":"Point"}
}