{
  "id": 7204323,
  "type": "Feature",
  "properties": {
    "tgn:hierarchy":[
        "tgn:7204323",
        "tgn:7003692",
        "tgn:1000003",
        "tgn:7000084",
        "tgn:7029392"
    ],
    "tgn:id":7204323,
    "tgn:name":"Branntweinerhof",
    "tgn:placetype":[
        "aat:300000206"
    ]
},
  "bbox": [],
  "geometry": {"coordinates":[9.816667,47.883333],"type":"Point"}
}