{
  "id": 7591291,
  "type": "Feature",
  "properties": {
    "tgn:hierarchy":[
        "tgn:7591291",
        "tgn:1000004",
        "tgn:7000198",
        "tgn:7000799",
        "tgn:7029392"
    ],
    "tgn:id":7591291,
    "tgn:name:en":"Sah\u0101ra",
    "tgn:placetype":[
        "aat:300008347"
    ]
},
  "bbox": [],
  "geometry": {"coordinates":[74.491006,32.926018],"type":"Point"}
}