{
  "id": 2721541,
  "type": "Feature",
  "properties": {
    "tgn:hierarchy":[
        "tgn:2721541",
        "tgn:1000001",
        "tgn:2001838",
        "tgn:7012149",
        "tgn:7007825",
        "tgn:7029392"
    ],
    "tgn:id":2721541,
    "tgn:name":"Tillett Branch",
    "tgn:placetype":[
        "aat:300008699"
    ]
},
  "bbox": [],
  "geometry": {"coordinates":[-86.35,35.3833],"type":"Point"}
}