{
  "id": 7589698,
  "type": "Feature",
  "properties": {
    "tgn:hierarchy":[
        "tgn:7589698",
        "tgn:1000004",
        "tgn:7000198",
        "tgn:7000799",
        "tgn:7029392"
    ],
    "tgn:id":7589698,
    "tgn:name:en":"Shawa Forest",
    "tgn:placetype":[
        "aat:300008863"
    ]
},
  "bbox": [],
  "geometry": {"coordinates":[74.436111,33.127778],"type":"Point"}
}