{
  "id": 2706908,
  "type": "Feature",
  "properties": {
    "tgn:hierarchy":[
        "tgn:2706908",
        "tgn:1000001",
        "tgn:7006451",
        "tgn:2000092",
        "tgn:7012149",
        "tgn:7029392"
    ],
    "tgn:id":2706908,
    "tgn:name":"Swapp Tank",
    "tgn:placetype":[
        "aat:300006191"
    ]
},
  "bbox": [],
  "geometry": {"coordinates":[-112.55,36.7333],"type":"Point"}
}