{
  "id": 7275810,
  "type": "Feature",
  "properties": {
    "tgn:hierarchy":[
        "tgn:7275810",
        "tgn:1001692",
        "tgn:1000049",
        "tgn:1000002",
        "tgn:7029392"
    ],
    "tgn:id":7275810,
    "tgn:name":"Trabunco, Estero",
    "tgn:placetype":[
        "aat:300008699"
    ]
},
  "bbox": [],
  "geometry": {"coordinates":[-72.683333,-38.633333],"type":"Point"}
}