{
  "id": 7039725,
  "type": "Feature",
  "properties": {
    "tgn:hierarchy":[
        "tgn:7039725",
        "tgn:7003170",
        "tgn:1000003",
        "tgn:7003125",
        "tgn:1000080",
        "tgn:7029392"
    ],
    "tgn:id":7039725,
    "tgn:name":"Serra Santa, Monte",
    "tgn:placetype":[
        "aat:300008795"
    ]
},
  "bbox": [],
  "geometry": {"coordinates":[12.816667,43.233333],"type":"Point"}
}