<<<<<<< HEAD
{
  "id": 7365346,
  "type": "Feature",
  "properties": {
    "tgn:hierarchy":[
        "tgn:7365346",
        "tgn:7005581",
        "tgn:1000001",
        "tgn:7005560",
        "tgn:7029392"
    ],
    "tgn:id":7365346,
    "tgn:name":"Rancho El Socorro",
    "tgn:placetype":[
        "aat:300000241"
    ]
},
  "bbox": [],
  "geometry": {"coordinates":[-104.883333,29.916667],"type":"Point"}
}
=======
{"geometry":{"type":"Point","coordinates":[-104.883333,29.916667]},"type":"Feature","properties":{"hierarchy":["tgn:7365346","tgn:7005581","tgn:1000001","tgn:7005560","tgn:7029392"],"placetype":["aat:300000241"],"id":7365346,"name:xx":"Rancho El Socorro"}}
>>>>>>> 03f74aca74312dbeaf24d7e61306dd6a786dc3d0
