{
  "id": 7545554,
  "type": "Feature",
  "properties": {
    "tgn:hierarchy":[
        "tgn:7545554",
        "tgn:1000004",
        "tgn:7000198",
        "tgn:7031786",
        "tgn:7029392"
    ],
    "tgn:id":7545554,
    "tgn:name:en":"Bhilangn\u0101 River",
    "tgn:placetype":[
        "aat:300008699"
    ]
},
  "bbox": [],
  "geometry": {"coordinates":[78.478836,30.393742],"type":"Point"}
}