{
  "id": 2276566,
  "type": "Feature",
  "properties": {
    "tgn:hierarchy":[
        "tgn:2276566",
        "tgn:1000001",
        "tgn:1002275",
        "tgn:7012149",
        "tgn:7007920",
        "tgn:7029392"
    ],
    "tgn:id":2276566,
    "tgn:name":"David Creek",
    "tgn:placetype":[
        "aat:300008706"
    ]
},
  "bbox": [],
  "geometry": {"coordinates":[-122.3667,45.6667],"type":"Point"}
}