{
  "id": 7565381,
  "type": "Feature",
  "properties": {
    "tgn:hierarchy":[
        "tgn:7565381",
        "tgn:1000004",
        "tgn:7000198",
        "tgn:1001894",
        "tgn:7029392"
    ],
    "tgn:id":7565381,
    "tgn:name:en":"Durg\u0101nagarp\u0101ra",
    "tgn:placetype":[
        "aat:300008347"
    ]
},
  "bbox": [],
  "geometry": {"coordinates":[79.033361,24.764731],"type":"Point"}
}