{
  "id": 2639071,
  "type": "Feature",
  "properties": {
    "tgn:hierarchy":[
        "tgn:2639071",
        "tgn:1000001",
        "tgn:2000952",
        "tgn:7012149",
        "tgn:7007520",
        "tgn:7029392"
    ],
    "tgn:id":2639071,
    "tgn:name":"Salt Lake",
    "tgn:placetype":[
        "aat:300008680"
    ]
},
  "bbox": [],
  "geometry": {"coordinates":[-84.9833,46.3167],"type":"Point"}
}