{
  "id": 1024561,
  "type": "Feature",
  "properties": {
    "tgn:hierarchy":[
        "tgn:1024561",
        "tgn:1000670",
        "tgn:1000002",
        "tgn:1000056",
        "tgn:7029392"
    ],
    "tgn:id":1024561,
    "tgn:name":"Jes\u00fas Mar\u00eda",
    "tgn:placetype":[
        "aat:300008347",
        "aat:300008389",
        "aat:300000874"
    ]
},
  "bbox": [],
  "geometry": {"coordinates":[-77.05,-12.05],"type":"Point"}
}