{
  "id": 1021444,
  "type": "Feature",
  "properties": {
    "tgn:hierarchy":[
        "tgn:1021444",
        "tgn:7006064",
        "tgn:1000047",
        "tgn:7002455",
        "tgn:1000002",
        "tgn:7029392"
    ],
    "tgn:id":1021444,
    "tgn:name":"Fortaleza",
    "tgn:placetype":[
        "aat:300387277",
        "aat:300008347",
        "aat:300008389",
        "aat:300387512",
        "aat:300387221",
        "aat:300120599"
    ]
},
  "bbox": [],
  "geometry": {"coordinates":[-38.5833,-3.75],"type":"Point"}
}