{
  "id": 1015913,
  "type": "Feature",
  "properties": {
    "tgn:hierarchy":[
        "tgn:1015913",
        "tgn:7005685",
        "tgn:1000001",
        "tgn:7005805",
        "tgn:7029392"
    ],
    "tgn:id":1015913,
    "tgn:name":"Estevan",
    "tgn:placetype":[
        "aat:300008347"
    ]
},
  "bbox": [],
  "geometry": {"coordinates":[-102.9833,49.15],"type":"Point"}
}