{
  "id": 2576102,
  "type": "Feature",
  "properties": {
    "tgn:hierarchy":[
        "tgn:2576102",
        "tgn:1000001",
        "tgn:7012149",
        "tgn:7007157",
        "tgn:1002710",
        "tgn:7029392"
    ],
    "tgn:id":2576102,
    "tgn:name":"Perkins Spring",
    "tgn:placetype":[
        "aat:300008697"
    ]
},
  "bbox": [],
  "geometry": {"coordinates":[-121.05,39.0333],"type":"Point"}
}