{
  "id": 2666297,
  "type": "Feature",
  "properties": {
    "tgn:hierarchy":[
        "tgn:2666297",
        "tgn:1000001",
        "tgn:7012149",
        "tgn:2001291",
        "tgn:7007524",
        "tgn:7029392"
    ],
    "tgn:id":2666297,
    "tgn:name":"Six, Point",
    "tgn:placetype":[
        "aat:300008798"
    ]
},
  "bbox": [],
  "geometry": {"coordinates":[-113.9833,47.0333],"type":"Point"}
}