{
  "id": 2229082,
  "type": "Feature",
  "properties": {
    "tgn:hierarchy":[
        "tgn:2229082",
        "tgn:1000001",
        "tgn:7012149",
        "tgn:2001440",
        "tgn:7007566",
        "tgn:7029392"
    ],
    "tgn:id":2229082,
    "tgn:name":"Cedar Knob",
    "tgn:placetype":[
        "aat:300008798"
    ]
},
  "bbox": [],
  "geometry": {"coordinates":[-108.6667,32.1667],"type":"Point"}
}