{
  "id": 2598494,
  "type": "Feature",
  "properties": {
    "tgn:hierarchy":[
        "tgn:2598494",
        "tgn:1000001",
        "tgn:7012149",
        "tgn:2001252",
        "tgn:7007523",
        "tgn:7029392"
    ],
    "tgn:id":2598494,
    "tgn:name":"Price Hollow",
    "tgn:placetype":[
        "aat:300008761"
    ]
},
  "bbox": [],
  "geometry": {"coordinates":[-92.1667,37.4667],"type":"Point"}
}