{
  "id": 7560072,
  "type": "Feature",
  "properties": {
    "tgn:hierarchy":[
        "tgn:7560072",
        "tgn:1000004",
        "tgn:7000198",
        "tgn:7016722",
        "tgn:7029392"
    ],
    "tgn:id":7560072,
    "tgn:name:en":"Andkhera",
    "tgn:placetype":[
        "aat:300008347"
    ]
},
  "bbox": [],
  "geometry": {"coordinates":[79.745009,27.634122],"type":"Point"}
}