{
  "id": 7221684,
  "type": "Feature",
  "properties": {
    "tgn:hierarchy":[
        "tgn:7221684",
        "tgn:7011170",
        "tgn:7002715",
        "tgn:1000003",
        "tgn:1000074",
        "tgn:7029392"
    ],
    "tgn:id":7221684,
    "tgn:name":"Panay\u00eda, Nis\u00eds",
    "tgn:placetype":[
        "aat:300008791"
    ]
},
  "bbox": [],
  "geometry": {"coordinates":[24.616667,40.566667],"type":"Point"}
}