{
  "id": 2404555,
  "type": "Feature",
  "properties": {
    "tgn:hierarchy":[
        "tgn:2404555",
        "tgn:1000001",
        "tgn:2001428",
        "tgn:7012149",
        "tgn:7007566",
        "tgn:7029392"
    ],
    "tgn:id":2404555,
    "tgn:name":"Hubbell Spring",
    "tgn:placetype":[
        "aat:300008697"
    ]
},
  "bbox": [],
  "geometry": {"coordinates":[-106.5167,34.9167],"type":"Point"}
}