{
  "id": 7566958,
  "type": "Feature",
  "properties": {
    "tgn:hierarchy":[
        "tgn:7566958",
        "tgn:1000004",
        "tgn:7000198",
        "tgn:7031786",
        "tgn:7029392"
    ],
    "tgn:id":7566958,
    "tgn:name:en":"Khar\u0101su",
    "tgn:placetype":[
        "aat:300008347"
    ]
},
  "bbox": [],
  "geometry": {"coordinates":[78.559883,29.868166],"type":"Point"}
}