{
  "id": 7417959,
  "type": "Feature",
  "properties": {
    "tgn:hierarchy":[
        "tgn:7417959",
        "tgn:1000001",
        "tgn:7005591",
        "tgn:7005560",
        "tgn:7029392"
    ],
    "tgn:id":7417959,
    "tgn:name:es":"San Lorenzo Villahermosa",
    "tgn:placetype":[
        "aat:300008347"
    ]
},
  "bbox": [],
  "geometry": {"coordinates":[-98.0625,17.976944],"type":"Point"}
}