{
  "id": 1049336,
  "type": "Feature",
  "properties": {
    "tgn:hierarchy":[
        "tgn:1049336",
        "tgn:1000003",
        "tgn:7024129",
        "tgn:7006366",
        "tgn:7029392"
    ],
    "tgn:id":1049336,
    "tgn:name":"Ostrowiec",
    "tgn:placetype":[
        "aat:300008347",
        "aat:300008389",
        "aat:300387270",
        "aat:300387302"
    ]
},
  "bbox": [],
  "geometry": {"coordinates":[21.3667,50.9667],"type":"Point"}
}