{
  "id": 2498754,
  "type": "Feature",
  "properties": {
    "tgn:hierarchy":[
        "tgn:2498754",
        "tgn:1000001",
        "tgn:7012149",
        "tgn:2002383",
        "tgn:7007923",
        "tgn:7029392"
    ],
    "tgn:id":2498754,
    "tgn:name":"McCagar Draw",
    "tgn:placetype":[
        "aat:300008761"
    ]
},
  "bbox": [],
  "geometry": {"coordinates":[-107.3333,41.0167],"type":"Point"}
}