{
  "id": 1068345,
  "type": "Feature",
  "properties": {
    "tgn:hierarchy":[
        "tgn:1068345",
        "tgn:1000004",
        "tgn:7002087",
        "tgn:1000111",
        "tgn:7029392"
    ],
    "tgn:id":1068345,
    "tgn:name":"Gongzui",
    "tgn:placetype":[
        "aat:300008347"
    ]
},
  "bbox": [],
  "geometry": {"coordinates":[103.4667,29.3167],"type":"Point"}
}