{
  "id": 7206854,
  "type": "Feature",
  "properties": {
    "tgn:hierarchy":[
        "tgn:7206854",
        "tgn:1000003",
        "tgn:7003676",
        "tgn:7000084",
        "tgn:7029392"
    ],
    "tgn:id":7206854,
    "tgn:name":"Butzhausen",
    "tgn:placetype":[
        "aat:300008347"
    ]
},
  "bbox": [],
  "geometry": {"coordinates":[8.566667,53.15],"type":"Point"}
}