{
  "id": 2243672,
  "type": "Feature",
  "properties": {
    "tgn:hierarchy":[
        "tgn:2243672",
        "tgn:1000001",
        "tgn:2001426",
        "tgn:7012149",
        "tgn:7007564",
        "tgn:7029392"
    ],
    "tgn:id":2243672,
    "tgn:name":"Clements Point",
    "tgn:placetype":[
        "aat:300008850"
    ]
},
  "bbox": [],
  "geometry": {"coordinates":[-70.8333,43.1333],"type":"Point"}
}