{
  "id": 1132220,
  "type": "Feature",
  "properties": {
    "tgn:hierarchy":[
        "tgn:1132220",
        "tgn:1000001",
        "tgn:7012149",
        "tgn:1002897",
        "tgn:7007920",
        "tgn:7029392"
    ],
    "tgn:id":1132220,
    "tgn:name":"Adams Creek",
    "tgn:placetype":[
        "aat:300008706"
    ]
},
  "bbox": [],
  "geometry": {"coordinates":[-121.5167,46.2167],"type":"Point"}
}