{
  "id": 2602469,
  "type": "Feature",
  "properties": {
    "tgn:hierarchy":[
        "tgn:2602469",
        "tgn:1000001",
        "tgn:2001418",
        "tgn:7012149",
        "tgn:7007526",
        "tgn:7029392"
    ],
    "tgn:id":2602469,
    "tgn:name":"Pyramid Spring",
    "tgn:placetype":[
        "aat:300008697"
    ]
},
  "bbox": [],
  "geometry": {"coordinates":[-116.1167,37.9167],"type":"Point"}
}