{
  "id": 2374399,
  "type": "Feature",
  "properties": {
    "tgn:hierarchy":[
        "tgn:2374399",
        "tgn:1000001",
        "tgn:2000769",
        "tgn:7012149",
        "tgn:7007255",
        "tgn:7029392"
    ],
    "tgn:id":2374399,
    "tgn:name":"Hampton Ridge",
    "tgn:placetype":[
        "aat:300266640"
    ]
},
  "bbox": [],
  "geometry": {"coordinates":[-83.5667,36.8167],"type":"Point"}
}