{
  "id": 2352520,
  "type": "Feature",
  "properties": {
    "tgn:hierarchy":[
        "tgn:2352520",
        "tgn:1000001",
        "tgn:2001264",
        "tgn:7012149",
        "tgn:7007524",
        "tgn:7029392"
    ],
    "tgn:id":2352520,
    "tgn:name":"Goat Lake",
    "tgn:placetype":[
        "aat:300008680"
    ]
},
  "bbox": [],
  "geometry": {"coordinates":[-109.55,45.0167],"type":"Point"}
}