<<<<<<< HEAD
{
  "id": 2402216,
  "type": "Feature",
  "properties": {
    "tgn:hierarchy":[
        "tgn:2402216",
        "tgn:1000001",
        "tgn:7012149",
        "tgn:2000217",
        "tgn:7007158",
        "tgn:7029392"
    ],
    "tgn:id":2402216,
    "tgn:name":"Horsethief Lake",
    "tgn:placetype":[
        "aat:300008680"
    ]
},
  "bbox": [],
  "geometry": {"coordinates":[-106.65,38.8833],"type":"Point"}
}
=======
{"geometry":{"type":"Point","coordinates":[-106.650000,38.883300]},"type":"Feature","properties":{"hierarchy":["tgn:2402216","tgn:1000001","tgn:7012149","tgn:2000217","tgn:7007158","tgn:7029392"],"placetype":["aat:300008680"],"id":2402216,"name:xx":"Horsethief Lake"}}
>>>>>>> 03f74aca74312dbeaf24d7e61306dd6a786dc3d0
