{
  "id": 2212264,
  "type": "Feature",
  "properties": {
    "tgn:hierarchy":[
        "tgn:2212264",
        "tgn:1000001",
        "tgn:7012149",
        "tgn:1002484",
        "tgn:7007826",
        "tgn:7029392"
    ],
    "tgn:id":2212264,
    "tgn:name":"Buzzard Roost Hollow",
    "tgn:placetype":[
        "aat:300008761"
    ]
},
  "bbox": [],
  "geometry": {"coordinates":[-97.95,32.3167],"type":"Point"}
}