{
  "id": 7575350,
  "type": "Feature",
  "properties": {
    "tgn:hierarchy":[
        "tgn:7575350",
        "tgn:1000004",
        "tgn:7000198",
        "tgn:1001977",
        "tgn:7029392"
    ],
    "tgn:id":7575350,
    "tgn:name:en":"Ker\u0101ng",
    "tgn:placetype":[
        "aat:300008347"
    ]
},
  "bbox": [],
  "geometry": {"coordinates":[88.766857,28.029466],"type":"Point"}
}