{
  "id": 7176501,
  "type": "Feature",
  "properties": {
    "tgn:hierarchy":[
        "tgn:7176501",
        "tgn:1000003",
        "tgn:7003685",
        "tgn:7000084",
        "tgn:7029392"
    ],
    "tgn:id":7176501,
    "tgn:name":"Hahn-Berg",
    "tgn:placetype":[
        "aat:300008795"
    ]
},
  "bbox": [],
  "geometry": {"coordinates":[12.633333,50.533333],"type":"Point"}
}