<<<<<<< HEAD
{
  "id": 2259088,
  "type": "Feature",
  "properties": {
    "tgn:hierarchy":[
        "tgn:2259088",
        "tgn:1000001",
        "tgn:7012149",
        "tgn:2002371",
        "tgn:7007923",
        "tgn:7029392"
    ],
    "tgn:id":2259088,
    "tgn:name":"Cottonwood Divide",
    "tgn:placetype":[
        "aat:300266640"
    ]
},
  "bbox": [],
  "geometry": {"coordinates":[-108.5,42.6333],"type":"Point"}
}
=======
{"geometry":{"type":"Point","coordinates":[-108.500000,42.633300]},"type":"Feature","properties":{"hierarchy":["tgn:2259088","tgn:1000001","tgn:7012149","tgn:2002371","tgn:7007923","tgn:7029392"],"placetype":["aat:300266640"],"id":2259088,"name:xx":"Cottonwood Divide"}}
>>>>>>> 03f74aca74312dbeaf24d7e61306dd6a786dc3d0
