<<<<<<< HEAD
{
  "id": 7478310,
  "type": "Feature",
  "properties": {
    "tgn:hierarchy":[
        "tgn:7478310",
        "tgn:1000004",
        "tgn:7492971",
        "tgn:1000141",
        "tgn:7029392"
    ],
    "tgn:id":7478310,
    "tgn:name":"Diyi Gongmu",
    "tgn:placetype":[
        "aat:300266755"
    ]
},
  "bbox": [],
  "geometry": {"coordinates":[120.505178,22.485142],"type":"Point"}
}
=======
{"geometry":{"type":"Point","coordinates":[120.505178,22.485142]},"type":"Feature","properties":{"hierarchy":["tgn:7478310","tgn:1000004","tgn:7492971","tgn:1000141","tgn:7029392"],"placetype":["aat:300266755"],"id":7478310,"name:xx":"Diyi Gongmu"}}
>>>>>>> 03f74aca74312dbeaf24d7e61306dd6a786dc3d0
