{
  "id": 7303437,
  "type": "Feature",
  "properties": {
    "tgn:hierarchy":[
        "tgn:7303437",
        "tgn:7002806",
        "tgn:7001158",
        "tgn:1000003",
        "tgn:1000095",
        "tgn:7029392"
    ],
    "tgn:id":7303437,
    "tgn:name":"Navandrinal",
    "tgn:placetype":[
        "aat:300008347"
    ]
},
  "bbox": [],
  "geometry": {"coordinates":[-4.833333,40.466667],"type":"Point"}
}