{
  "id": 7210470,
  "type": "Feature",
  "properties": {
    "tgn:hierarchy":[
        "tgn:7210470",
        "tgn:7003669",
        "tgn:1000003",
        "tgn:7000084",
        "tgn:7029392"
    ],
    "tgn:id":7210470,
    "tgn:name":"Baumberg",
    "tgn:placetype":[
        "aat:300008347"
    ]
},
  "bbox": [],
  "geometry": {"coordinates":[11.433333,47.733333],"type":"Point"}
}