{
  "id": 7493479,
  "type": "Feature",
  "properties": {
    "tgn:hierarchy":[
        "tgn:7493479",
        "tgn:1000004",
        "tgn:7001013",
        "tgn:1000141",
        "tgn:7029392"
    ],
    "tgn:id":7493479,
    "tgn:name":"Xiehe Qiao",
    "tgn:placetype":[
        "aat:300007836"
    ]
},
  "bbox": [],
  "geometry": {"coordinates":[121.279965,24.970366],"type":"Point"}
}