{
  "id": 1077319,
  "type": "Feature",
  "properties": {
    "tgn:hierarchy":[
        "tgn:1077319",
        "tgn:1000004",
        "tgn:1001871",
        "tgn:7000198",
        "tgn:7029392"
    ],
    "tgn:id":1077319,
    "tgn:name":"Yamunanagar",
    "tgn:placetype":[
        "aat:300008347"
    ]
},
  "bbox": [],
  "geometry": {"coordinates":[77.280494,30.129128],"type":"Point"}
}