<<<<<<< HEAD
{
  "id": 2251901,
  "type": "Feature",
  "properties": {
    "tgn:hierarchy":[
        "tgn:2251901",
        "tgn:7014651",
        "tgn:1000001",
        "tgn:7012149",
        "tgn:7007516",
        "tgn:7029392"
    ],
    "tgn:id":2251901,
    "tgn:name":"Conaways",
    "tgn:placetype":[
        "aat:300008347"
    ]
},
  "bbox": [],
  "geometry": {"coordinates":[-76.6833,39.0167],"type":"Point"}
}
=======
{"geometry":{"type":"Point","coordinates":[-76.683300,39.016700]},"type":"Feature","properties":{"hierarchy":["tgn:2251901","tgn:7014651","tgn:1000001","tgn:7012149","tgn:7007516","tgn:7029392"],"placetype":["aat:300008347"],"id":2251901,"name:xx":"Conaways"}}
>>>>>>> 03f74aca74312dbeaf24d7e61306dd6a786dc3d0
