{
  "id": 7147378,
  "type": "Feature",
  "properties": {
    "tgn:hierarchy":[
        "tgn:7147378",
        "tgn:1000003",
        "tgn:7003682",
        "tgn:7000084",
        "tgn:7029392"
    ],
    "tgn:id":7147378,
    "tgn:name":"Kr\u00e4henstein",
    "tgn:placetype":[
        "aat:300266640"
    ]
},
  "bbox": [],
  "geometry": {"coordinates":[8.016667,49.516667],"type":"Point"}
}