{
  "id": 1022472,
  "type": "Feature",
  "properties": {
    "tgn:hierarchy":[
        "tgn:1022472",
        "tgn:7006246",
        "tgn:1000047",
        "tgn:7002455",
        "tgn:1000002",
        "tgn:7029392"
    ],
    "tgn:id":1022472,
    "tgn:name":"Pinheiro",
    "tgn:placetype":[
        "aat:300008347"
    ]
},
  "bbox": [],
  "geometry": {"coordinates":[-45.0833,-2.5167],"type":"Point"}
}