{
  "id": 7421584,
  "type": "Feature",
  "properties": {
    "tgn:hierarchy":[
        "tgn:7421584",
        "tgn:1000001",
        "tgn:1001960",
        "tgn:7005560",
        "tgn:7029392"
    ],
    "tgn:id":7421584,
    "tgn:name":"El Tullido, Cerro",
    "tgn:placetype":[
        "aat:300008795"
    ]
},
  "bbox": [],
  "geometry": {"coordinates":[-112.848611,31.48],"type":"Point"}
}