{
  "id": 1087102,
  "type": "Feature",
  "properties": {
    "tgn:hierarchy":[
        "tgn:1087102",
        "tgn:1000004",
        "tgn:7001056",
        "tgn:1000145",
        "tgn:7029392"
    ],
    "tgn:id":1087102,
    "tgn:name":"Dak Gle",
    "tgn:placetype":[
        "aat:300008347"
    ]
},
  "bbox": [],
  "geometry": {"coordinates":[107.7667,15.2167],"type":"Point"}
}