{
  "id": 2621055,
  "type": "Feature",
  "properties": {
    "tgn:hierarchy":[
        "tgn:2621055",
        "tgn:2000090",
        "tgn:1000001",
        "tgn:7006451",
        "tgn:7012149",
        "tgn:7029392"
    ],
    "tgn:id":2621055,
    "tgn:name":"Road Forks Tank",
    "tgn:placetype":[
        "aat:300006191"
    ]
},
  "bbox": [],
  "geometry": {"coordinates":[-109.15,33.9167],"type":"Point"}
}