{
  "id": 7586306,
  "type": "Feature",
  "properties": {
    "tgn:hierarchy":[
        "tgn:7586306",
        "tgn:1000004",
        "tgn:7000198",
        "tgn:7000799",
        "tgn:7029392"
    ],
    "tgn:id":7586306,
    "tgn:name:en":"Trimukha",
    "tgn:placetype":[
        "aat:300008347"
    ]
},
  "bbox": [],
  "geometry": {"coordinates":[74.476389,34.433333],"type":"Point"}
}