{
  "id": 1087825,
  "type": "Feature",
  "properties": {
    "tgn:hierarchy":[
        "tgn:1087825",
        "tgn:7001242",
        "tgn:1000149",
        "tgn:1000867",
        "tgn:7029392"
    ],
    "tgn:id":1087825,
    "tgn:name":"Impulo",
    "tgn:placetype":[
        "aat:300008347"
    ]
},
  "bbox": [],
  "geometry": {"coordinates":[13.65,-13.85],"type":"Point"}
}