{
  "id": 2297444,
  "type": "Feature",
  "properties": {
    "tgn:hierarchy":[
        "tgn:2297444",
        "tgn:1000001",
        "tgn:7012149",
        "tgn:1002802",
        "tgn:7007706",
        "tgn:7029392"
    ],
    "tgn:id":2297444,
    "tgn:name":"Dry Fork",
    "tgn:placetype":[
        "aat:300008699"
    ]
},
  "bbox": [],
  "geometry": {"coordinates":[-84.6333,39.8833],"type":"Point"}
}