{
  "id": 7534301,
  "type": "Feature",
  "properties": {
    "tgn:hierarchy":[
        "tgn:7534301",
        "tgn:7001242",
        "tgn:7016833",
        "tgn:1001418",
        "tgn:7029392"
    ],
    "tgn:id":7534301,
    "tgn:name:en":"Mahm\u00fbd Khalii",
    "tgn:placetype":[
        "aat:300005926"
    ]
},
  "bbox": [],
  "geometry": {"coordinates":[28.583333,28.433333],"type":"Point"}
}