<<<<<<< HEAD
{
  "id": 7375370,
  "type": "Feature",
  "properties": {
    "tgn:hierarchy":[
        "tgn:7375370",
        "tgn:7005581",
        "tgn:1000001",
        "tgn:7005560",
        "tgn:7029392"
    ],
    "tgn:id":7375370,
    "tgn:name":"Las Escobas",
    "tgn:placetype":[
        "aat:300008347"
    ]
},
  "bbox": [],
  "geometry": {"coordinates":[-104.45,26.733333],"type":"Point"}
}
=======
{"geometry":{"type":"Point","coordinates":[-104.450000,26.733333]},"type":"Feature","properties":{"hierarchy":["tgn:7375370","tgn:7005581","tgn:1000001","tgn:7005560","tgn:7029392"],"placetype":["aat:300008347"],"id":7375370,"name:xx":"Las Escobas"}}
>>>>>>> 03f74aca74312dbeaf24d7e61306dd6a786dc3d0
