{
  "id": 7373063,
  "type": "Feature",
  "properties": {
    "tgn:hierarchy":[
        "tgn:7373063",
        "tgn:1000001",
        "tgn:7005595",
        "tgn:7005560",
        "tgn:7029392"
    ],
    "tgn:id":7373063,
    "tgn:name":"Rancho La Chaparrera",
    "tgn:placetype":[
        "aat:300000241"
    ]
},
  "bbox": [],
  "geometry": {"coordinates":[-108.649722,26.311667],"type":"Point"}
}