{
  "id": 2126349,
  "type": "Feature",
  "properties": {
    "tgn:hierarchy":[
        "tgn:2126349",
        "tgn:1000001",
        "tgn:2000197",
        "tgn:7012149",
        "tgn:7007158",
        "tgn:7029392"
    ],
    "tgn:id":2126349,
    "tgn:name":"Adobe Creek Reservoir Outlet Ditch",
    "tgn:placetype":[
        "aat:300006075"
    ]
},
  "bbox": [],
  "geometry": {"coordinates":[-103.2833,38.2167],"type":"Point"}
}