{
  "id": 2659331,
  "type": "Feature",
  "properties": {
    "tgn:hierarchy":[
        "tgn:2659331",
        "tgn:1000001",
        "tgn:7012149",
        "tgn:2001447",
        "tgn:7007566",
        "tgn:7029392"
    ],
    "tgn:id":2659331,
    "tgn:name":"Shiloh Hills",
    "tgn:placetype":[
        "aat:300386831"
    ]
},
  "bbox": [],
  "geometry": {"coordinates":[-105.4167,32.1833],"type":"Point"}
}