{
  "id": 7434666,
  "type": "Feature",
  "properties": {
    "tgn:hierarchy":[
        "tgn:7434666",
        "tgn:7005580",
        "tgn:1000001",
        "tgn:7005560",
        "tgn:7029392"
    ],
    "tgn:id":7434666,
    "tgn:name":"Zona Lacandona",
    "tgn:placetype":[
        "aat:300387200"
    ]
},
  "bbox": [],
  "geometry": {"coordinates":[-91.066667,16.25],"type":"Point"}
}