<<<<<<< HEAD
{
  "id": 7482028,
  "type": "Feature",
  "properties": {
    "tgn:hierarchy":[
        "tgn:7482028",
        "tgn:1000004",
        "tgn:7492971",
        "tgn:1000141",
        "tgn:7029392"
    ],
    "tgn:id":7482028,
    "tgn:name":"Chengde",
    "tgn:placetype":[
        "aat:300008347"
    ]
},
  "bbox": [],
  "geometry": {"coordinates":[120.603268,22.610504],"type":"Point"}
}
=======
{"geometry":{"type":"Point","coordinates":[120.603268,22.610504]},"type":"Feature","properties":{"hierarchy":["tgn:7482028","tgn:1000004","tgn:7492971","tgn:1000141","tgn:7029392"],"placetype":["aat:300008347"],"id":7482028,"name:xx":"Chengde"}}
>>>>>>> 03f74aca74312dbeaf24d7e61306dd6a786dc3d0
