{
  "id": 7155144,
  "type": "Feature",
  "properties": {
    "tgn:hierarchy":[
        "tgn:7155144",
        "tgn:1000003",
        "tgn:7000094",
        "tgn:7000084",
        "tgn:7029392"
    ],
    "tgn:id":7155144,
    "tgn:name":"Kleinkl\u00fctzh\u00f6ved",
    "tgn:placetype":[
        "aat:300387499"
    ]
},
  "bbox": [],
  "geometry": {"coordinates":[11.083333,54.016667],"type":"Point"}
}