{
  "id": 1064975,
  "type": "Feature",
  "properties": {
    "tgn:hierarchy":[
        "tgn:1064975",
        "tgn:1000003",
        "tgn:7006669",
        "tgn:7029392"
    ],
    "tgn:id":1064975,
    "tgn:name":"Despotovac",
    "tgn:placetype":[
        "aat:300008347"
    ]
},
  "bbox": [],
  "geometry": {"coordinates":[21.55,44.0833],"type":"Point"}
}