{
  "id": 7071373,
  "type": "Feature",
  "properties": {
    "tgn:hierarchy":[
        "tgn:7071373",
        "tgn:1000003",
        "tgn:7003676",
        "tgn:7000084",
        "tgn:7029392"
    ],
    "tgn:id":7071373,
    "tgn:name":"St\u00fchbusch",
    "tgn:placetype":[
        "aat:300008347"
    ]
},
  "bbox": [],
  "geometry": {"coordinates":[8.916667,53.533333],"type":"Point"}
}