{
  "id": 7089099,
  "type": "Feature",
  "properties": {
    "tgn:hierarchy":[
        "tgn:7089099",
        "tgn:1000003",
        "tgn:7003676",
        "tgn:7000084",
        "tgn:7029392"
    ],
    "tgn:id":7089099,
    "tgn:name":"Weiher",
    "tgn:placetype":[
        "aat:300000206"
    ]
},
  "bbox": [],
  "geometry": {"coordinates":[9.85,52.966667],"type":"Point"}
}