{
  "id": 7436556,
  "type": "Feature",
  "properties": {
    "tgn:hierarchy":[
        "tgn:7436556",
        "tgn:7005581",
        "tgn:1000001",
        "tgn:7005560",
        "tgn:7029392"
    ],
    "tgn:id":7436556,
    "tgn:name":"Santo Domingo",
    "tgn:placetype":[
        "aat:300008347"
    ]
},
  "bbox": [],
  "geometry": {"coordinates":[-105.883333,26.883333],"type":"Point"}
}