{
  "id": 2202767,
  "type": "Feature",
  "properties": {
    "tgn:hierarchy":[
        "tgn:2202767",
        "tgn:1000001",
        "tgn:7012149",
        "tgn:1002929",
        "tgn:7007240",
        "tgn:7029392"
    ],
    "tgn:id":2202767,
    "tgn:name":"Bucker Womans Town",
    "tgn:placetype":[
        "aat:300008347",
        "aat:300167671"
    ]
},
  "bbox": [],
  "geometry": {"coordinates":[-82.1333,28.5667],"type":"Point"}
}