{
  "id": 2480358,
  "type": "Feature",
  "properties": {
    "tgn:hierarchy":[
        "tgn:2480358",
        "tgn:2001422",
        "tgn:1000001",
        "tgn:7012149",
        "tgn:7007564",
        "tgn:7029392"
    ],
    "tgn:id":2480358,
    "tgn:name":"Lake Shore Park",
    "tgn:placetype":[
        "aat:300008347"
    ]
},
  "bbox": [],
  "geometry": {"coordinates":[-71.3333,43.5667],"type":"Point"}
}