{
  "id": 2235436,
  "type": "Feature",
  "properties": {
    "tgn:hierarchy":[
        "tgn:2235436",
        "tgn:1000001",
        "tgn:7012149",
        "tgn:1002798",
        "tgn:7007252",
        "tgn:7029392"
    ],
    "tgn:id":2235436,
    "tgn:name":"Chester Branch",
    "tgn:placetype":[
        "aat:300008699"
    ]
},
  "bbox": [],
  "geometry": {"coordinates":[-87.05,41.3833],"type":"Point"}
}