{
  "id": 2591383,
  "type": "Feature",
  "properties": {
    "tgn:hierarchy":[
        "tgn:2591383",
        "tgn:1000001",
        "tgn:1002191",
        "tgn:7012149",
        "tgn:7007826",
        "tgn:7029392"
    ],
    "tgn:id":2591383,
    "tgn:name":"Polnac Lake",
    "tgn:placetype":[
        "aat:300006191"
    ]
},
  "bbox": [],
  "geometry": {"coordinates":[-97.8333,32.0833],"type":"Point"}
}