{
  "id": 1074396,
  "type": "Feature",
  "properties": {
    "tgn:hierarchy":[
        "tgn:1074396",
        "tgn:1000004",
        "tgn:7000198",
        "tgn:7016788",
        "tgn:7029392"
    ],
    "tgn:id":1074396,
    "tgn:name:en":"Alwar",
    "tgn:placetype":[
        "aat:300008347"
    ]
},
  "bbox": [],
  "geometry": {"coordinates":[76.610274,27.564416],"type":"Point"}
}