{
  "id": 2771339,
  "type": "Feature",
  "properties": {
    "tgn:hierarchy":[
        "tgn:2771339",
        "tgn:1000001",
        "tgn:7012149",
        "tgn:2000181",
        "tgn:7007157",
        "tgn:7029392"
    ],
    "tgn:id":2771339,
    "tgn:name":"Wilder Gulch",
    "tgn:placetype":[
        "aat:300008761"
    ]
},
  "bbox": [],
  "geometry": {"coordinates":[-123.5333,41.3167],"type":"Point"}
}