<<<<<<< HEAD
{
  "id": 7484475,
  "type": "Feature",
  "properties": {
    "tgn:hierarchy":[
        "tgn:7484475",
        "tgn:1000004",
        "tgn:7001009",
        "tgn:1000141",
        "tgn:7029392"
    ],
    "tgn:id":7484475,
    "tgn:name":"Houzhuang",
    "tgn:placetype":[
        "aat:300008347"
    ]
},
  "bbox": [],
  "geometry": {"coordinates":[120.6725,24.266667],"type":"Point"}
}
=======
{"geometry":{"type":"Point","coordinates":[120.672500,24.266667]},"type":"Feature","properties":{"hierarchy":["tgn:7484475","tgn:1000004","tgn:7001009","tgn:1000141","tgn:7029392"],"placetype":["aat:300008347"],"id":7484475,"name:xx":"Houzhuang"}}
>>>>>>> 03f74aca74312dbeaf24d7e61306dd6a786dc3d0
