{
  "id": 1050016,
  "type": "Feature",
  "properties": {
    "tgn:hierarchy":[
        "tgn:1050016",
        "tgn:1000003",
        "tgn:1000364",
        "tgn:1000091",
        "tgn:7029392"
    ],
    "tgn:id":1050016,
    "tgn:name":"B\u0103ile\u0219ti",
    "tgn:placetype":[
        "aat:300008347"
    ]
},
  "bbox": [],
  "geometry": {"coordinates":[23.3333,44.0167],"type":"Point"}
}