{
  "id": 7585702,
  "type": "Feature",
  "properties": {
    "tgn:hierarchy":[
        "tgn:7585702",
        "tgn:1000004",
        "tgn:7000198",
        "tgn:7000799",
        "tgn:7029392"
    ],
    "tgn:id":7585702,
    "tgn:name:en":"Nari\u0101la",
    "tgn:placetype":[
        "aat:300008347"
    ]
},
  "bbox": [],
  "geometry": {"coordinates":[74.224577,33.264883],"type":"Point"}
}