{
  "id": 7235631,
  "type": "Feature",
  "properties": {
    "tgn:hierarchy":[
        "tgn:7235631",
        "tgn:7011161",
        "tgn:7002674",
        "tgn:1000003",
        "tgn:1000074",
        "tgn:7029392"
    ],
    "tgn:id":7235631,
    "tgn:name":"\u00c1yios Ye\u00f3ryios, \u00c1kra",
    "tgn:placetype":[
        "aat:300008850"
    ]
},
  "bbox": [],
  "geometry": {"coordinates":[25.602778,38.533333],"type":"Point"}
}