{
  "id": 2382352,
  "type": "Feature",
  "properties": {
    "tgn:hierarchy":[
        "tgn:2382352",
        "tgn:1000001",
        "tgn:7012149",
        "tgn:2001239",
        "tgn:7007523",
        "tgn:7029392"
    ],
    "tgn:id":2382352,
    "tgn:name":"Hays Mine",
    "tgn:placetype":[
        "aat:300000390"
    ]
},
  "bbox": [],
  "geometry": {"coordinates":[-93.9167,38.0833],"type":"Point"}
}