<<<<<<< HEAD
{
  "id": 7026115,
  "type": "Feature",
  "properties": {
    "tgn:hierarchy":[
        "tgn:7026115",
        "tgn:7002445",
        "tgn:1000003",
        "tgn:7008131",
        "tgn:7008591",
        "tgn:7029392"
    ],
    "tgn:id":7026115,
    "tgn:name:en":"Great Canfield",
    "tgn:placetype":[
        "aat:300008347",
        "aat:300008369"
    ]
},
  "bbox": [],
  "geometry": {"coordinates":[0.316667,51.833333],"type":"Point"}
}
=======
{"geometry":{"type":"Point","coordinates":[0.316667,51.833333]},"type":"Feature","properties":{"hierarchy":["tgn:7026115","tgn:7002445","tgn:1000003","tgn:7008131","tgn:7008591","tgn:7029392"],"placetype":["aat:300008347","aat:300008369"],"name:en":"Great Canfield","id":7026115}}
>>>>>>> 03f74aca74312dbeaf24d7e61306dd6a786dc3d0
