<<<<<<< HEAD
{
  "id": 2406510,
  "type": "Feature",
  "properties": {
    "tgn:hierarchy":[
        "tgn:2406510",
        "tgn:1000001",
        "tgn:7012149",
        "tgn:2002191",
        "tgn:7007919",
        "tgn:7029392"
    ],
    "tgn:id":2406510,
    "tgn:name":"Hungry Mother Creek",
    "tgn:placetype":[
        "aat:300008706"
    ]
},
  "bbox": [],
  "geometry": {"coordinates":[-81.45,36.8833],"type":"Point"}
}
=======
{"geometry":{"type":"Point","coordinates":[-81.450000,36.883300]},"type":"Feature","properties":{"hierarchy":["tgn:2406510","tgn:1000001","tgn:7012149","tgn:2002191","tgn:7007919","tgn:7029392"],"placetype":["aat:300008706"],"id":2406510,"name:xx":"Hungry Mother Creek"}}
>>>>>>> 03f74aca74312dbeaf24d7e61306dd6a786dc3d0
