{
  "id": 2688046,
  "type": "Feature",
  "properties": {
    "tgn:hierarchy":[
        "tgn:2688046",
        "tgn:1000001",
        "tgn:7019982",
        "tgn:7012149",
        "tgn:7007517",
        "tgn:7029392"
    ],
    "tgn:id":2688046,
    "tgn:name":"Springfield Water Works Intake Reservoir",
    "tgn:placetype":[
        "aat:300006191"
    ]
},
  "bbox": [],
  "geometry": {"coordinates":[-72.85,42.1167],"type":"Point"}
}