{
  "id": 2648773,
  "type": "Feature",
  "properties": {
    "tgn:hierarchy":[
        "tgn:2648773",
        "tgn:1000001",
        "tgn:1002328",
        "tgn:7012149",
        "tgn:7007568",
        "tgn:7029392"
    ],
    "tgn:id":2648773,
    "tgn:name":"Scotch Mountain",
    "tgn:placetype":[
        "aat:300008798"
    ]
},
  "bbox": [],
  "geometry": {"coordinates":[-74.9167,42.2333],"type":"Point"}
}