{
  "id": 7228422,
  "type": "Feature",
  "properties": {
    "tgn:hierarchy":[
        "tgn:7228422",
        "tgn:7002707",
        "tgn:7002705",
        "tgn:1000003",
        "tgn:1000074",
        "tgn:7029392"
    ],
    "tgn:id":7228422,
    "tgn:name":"Kastan\u00e9a",
    "tgn:placetype":[
        "aat:300008347"
    ]
},
  "bbox": [],
  "geometry": {"coordinates":[20.840278,40.187222],"type":"Point"}
}