{
  "id": 7004723,
  "type": "Feature",
  "properties": {
    "tgn:hierarchy":[
        "tgn:7004723",
        "tgn:1000003",
        "tgn:7011731",
        "tgn:7029392"
    ],
    "tgn:id":7004723,
    "tgn:name:it":"Ticino",
    "tgn:placetype":[
        "aat:300387064",
        "aat:300000769"
    ]
},
  "bbox": [],
  "geometry": {"coordinates":[8.79,46.284],"type":"Point"}
}