{
  "id": 2304134,
  "type": "Feature",
  "properties": {
    "tgn:hierarchy":[
        "tgn:2304134",
        "tgn:1000001",
        "tgn:7012149",
        "tgn:2000405",
        "tgn:7007248",
        "tgn:7029392"
    ],
    "tgn:id":2304134,
    "tgn:name":"Eagles Landing Lake",
    "tgn:placetype":[
        "aat:300006191"
    ]
},
  "bbox": [],
  "geometry": {"coordinates":[-84.3667,33.15],"type":"Point"}
}