{
  "id": 7142738,
  "type": "Feature",
  "properties": {
    "tgn:hierarchy":[
        "tgn:7142738",
        "tgn:1000003",
        "tgn:7000094",
        "tgn:7000084",
        "tgn:7029392"
    ],
    "tgn:id":7142738,
    "tgn:name":"L\u00fcdersdorf",
    "tgn:placetype":[
        "aat:300008347"
    ]
},
  "bbox": [],
  "geometry": {"coordinates":[10.816667,53.833333],"type":"Point"}
}