<<<<<<< HEAD
{
  "id": 7377706,
  "type": "Feature",
  "properties": {
    "tgn:hierarchy":[
        "tgn:7377706",
        "tgn:7005581",
        "tgn:1000001",
        "tgn:7005560",
        "tgn:7029392"
    ],
    "tgn:id":7377706,
    "tgn:name":"La Soledad",
    "tgn:placetype":[
        "aat:300008347"
    ]
},
  "bbox": [],
  "geometry": {"coordinates":[-105.9,27.05],"type":"Point"}
}
=======
{"geometry":{"type":"Point","coordinates":[-105.900000,27.050000]},"type":"Feature","properties":{"hierarchy":["tgn:7377706","tgn:7005581","tgn:1000001","tgn:7005560","tgn:7029392"],"placetype":["aat:300008347"],"id":7377706,"name:xx":"La Soledad"}}
>>>>>>> 03f74aca74312dbeaf24d7e61306dd6a786dc3d0
