<<<<<<< HEAD
{
  "id": 2761551,
  "type": "Feature",
  "properties": {
    "tgn:hierarchy":[
        "tgn:2761551",
        "tgn:7006450",
        "tgn:1000001",
        "tgn:2124053",
        "tgn:7012149",
        "tgn:7029392"
    ],
    "tgn:id":2761551,
    "tgn:name":"West Papoose Lake",
    "tgn:placetype":[
        "aat:300008680"
    ]
},
  "bbox": [],
  "geometry": {"coordinates":[-150.0833,61.5333],"type":"Point"}
}
=======
{"geometry":{"type":"Point","coordinates":[-150.083300,61.533300]},"type":"Feature","properties":{"hierarchy":["tgn:2761551","tgn:7006450","tgn:1000001","tgn:2124053","tgn:7012149","tgn:7029392"],"placetype":["aat:300008680"],"id":2761551,"name:xx":"West Papoose Lake"}}
>>>>>>> 03f74aca74312dbeaf24d7e61306dd6a786dc3d0
