{
  "id": 7552694,
  "type": "Feature",
  "properties": {
    "tgn:hierarchy":[
        "tgn:7552694",
        "tgn:1000004",
        "tgn:7000198",
        "tgn:7016788",
        "tgn:7029392"
    ],
    "tgn:id":7552694,
    "tgn:name:en":"Mansi River",
    "tgn:placetype":[
        "aat:300008699"
    ]
},
  "bbox": [],
  "geometry": {"coordinates":[74.983483,25.822934],"type":"Point"}
}