<<<<<<< HEAD
{
  "id": 2154193,
  "type": "Feature",
  "properties": {
    "tgn:hierarchy":[
        "tgn:2154193",
        "tgn:1000001",
        "tgn:7012149",
        "tgn:2001056",
        "tgn:7007521",
        "tgn:7029392"
    ],
    "tgn:id":2154193,
    "tgn:name":"Bear Creek",
    "tgn:placetype":[
        "aat:300008706"
    ]
},
  "bbox": [],
  "geometry": {"coordinates":[-92.85,45.8667],"type":"Point"}
}
=======
{"geometry":{"type":"Point","coordinates":[-92.850000,45.866700]},"type":"Feature","properties":{"hierarchy":["tgn:2154193","tgn:1000001","tgn:7012149","tgn:2001056","tgn:7007521","tgn:7029392"],"placetype":["aat:300008706"],"id":2154193,"name:xx":"Bear Creek"}}
>>>>>>> 03f74aca74312dbeaf24d7e61306dd6a786dc3d0
