{
  "id": 2619318,
  "type": "Feature",
  "properties": {
    "tgn:hierarchy":[
        "tgn:2619318",
        "tgn:1002300",
        "tgn:1000001",
        "tgn:7012149",
        "tgn:7007564",
        "tgn:7029392"
    ],
    "tgn:id":2619318,
    "tgn:name":"Rim Junction",
    "tgn:placetype":[
        "aat:300008347"
    ]
},
  "bbox": [],
  "geometry": {"coordinates":[-71.05,44.2667],"type":"Point"}
}