<<<<<<< HEAD
{
  "id": 2408009,
  "type": "Feature",
  "properties": {
    "tgn:hierarchy":[
        "tgn:2408009",
        "tgn:1000001",
        "tgn:7012149",
        "tgn:7007919",
        "tgn:7029392"
    ],
    "tgn:id":2408009,
    "tgn:name":"Hurricane Creek",
    "tgn:placetype":[
        "aat:300008706"
    ]
},
  "bbox": [],
  "geometry": {"coordinates":[-81.5333,36.7],"type":"Point"}
}
=======
{"geometry":{"type":"Point","coordinates":[-81.533300,36.700000]},"type":"Feature","properties":{"hierarchy":["tgn:2408009","tgn:1000001","tgn:7012149","tgn:7007919","tgn:7029392"],"placetype":["aat:300008706"],"id":2408009,"name:xx":"Hurricane Creek"}}
>>>>>>> 03f74aca74312dbeaf24d7e61306dd6a786dc3d0
