{
  "id": 2372565,
  "type": "Feature",
  "properties": {
    "tgn:hierarchy":[
        "tgn:2372565",
        "tgn:1000001",
        "tgn:7012149",
        "tgn:2002373",
        "tgn:7007923",
        "tgn:7029392"
    ],
    "tgn:id":2372565,
    "tgn:name":"Hall Butte",
    "tgn:placetype":[
        "aat:300008798"
    ]
},
  "bbox": [],
  "geometry": {"coordinates":[-107.8333,43.5333],"type":"Point"}
}