{
  "id": 2133492,
  "type": "Feature",
  "properties": {
    "tgn:hierarchy":[
        "tgn:2133492",
        "tgn:1000001",
        "tgn:7012149",
        "tgn:1002877",
        "tgn:7007706",
        "tgn:7029392"
    ],
    "tgn:id":2133492,
    "tgn:name":"Andre",
    "tgn:placetype":[
        "aat:300008347"
    ]
},
  "bbox": [],
  "geometry": {"coordinates":[-82.7333,38.7333],"type":"Point"}
}