{
  "id": 2272873,
  "type": "Feature",
  "properties": {
    "tgn:hierarchy":[
        "tgn:2272873",
        "tgn:1000001",
        "tgn:7012149",
        "tgn:7014097",
        "tgn:7007158",
        "tgn:7029392"
    ],
    "tgn:id":2272873,
    "tgn:name":"Cutler Reservoir",
    "tgn:placetype":[
        "aat:300006191"
    ]
},
  "bbox": [],
  "geometry": {"coordinates":[-104.05,38.95],"type":"Point"}
}