{
  "id": 2453140,
  "type": "Feature",
  "properties": {
    "tgn:hierarchy":[
        "tgn:2453140",
        "tgn:1000001",
        "tgn:2001013",
        "tgn:7012149",
        "tgn:7007521",
        "tgn:7029392"
    ],
    "tgn:id":2453140,
    "tgn:name":"Little Carver Lake",
    "tgn:placetype":[
        "aat:300008680"
    ]
},
  "bbox": [],
  "geometry": {"coordinates":[-95.3333,47.7333],"type":"Point"}
}