{
  "id": 1034264,
  "type": "Feature",
  "properties": {
    "tgn:hierarchy":[
        "tgn:1034264",
        "tgn:1000003",
        "tgn:7002890",
        "tgn:1000070",
        "tgn:7029392"
    ],
    "tgn:id":1034264,
    "tgn:name":"Margny-l\u00e8s-Compi\u00e8gne",
    "tgn:placetype":[
        "aat:300008347"
    ]
},
  "bbox": [],
  "geometry": {"coordinates":[2.8167,49.4333],"type":"Point"}
}