{
  "id": 7340171,
  "type": "Feature",
  "properties": {
    "tgn:hierarchy":[
        "tgn:7340171",
        "tgn:7002813",
        "tgn:7002758",
        "tgn:1000003",
        "tgn:1000095",
        "tgn:7029392"
    ],
    "tgn:id":7340171,
    "tgn:name":"Culebra, Arroyo de la",
    "tgn:placetype":[
        "aat:300266554",
        "aat:300008699"
    ]
},
  "bbox": [],
  "geometry": {"coordinates":[-5.75,36.25],"type":"Point"}
}