{
  "id": 2059697,
  "type": "Feature",
  "properties": {
    "tgn:hierarchy":[
        "tgn:2059697",
        "tgn:1000001",
        "tgn:7012149",
        "tgn:2001188",
        "tgn:7007523",
        "tgn:7029392"
    ],
    "tgn:id":2059697,
    "tgn:name":"Mecca",
    "tgn:placetype":[
        "aat:300008347",
        "aat:300387210"
    ]
},
  "bbox": [],
  "geometry": {"coordinates":[-94.5167,39.4833],"type":"Point"}
}