<<<<<<< HEAD
{
  "id": 2159398,
  "type": "Feature",
  "properties": {
    "tgn:hierarchy":[
        "tgn:2159398",
        "tgn:1000001",
        "tgn:7012149",
        "tgn:7007254",
        "tgn:7029392"
    ],
    "tgn:id":2159398,
    "tgn:name":"Bee Creek",
    "tgn:placetype":[
        "aat:300008706"
    ]
},
  "bbox": [],
  "geometry": {"coordinates":[-95.9833,37.2333],"type":"Point"}
}
=======
{"geometry":{"type":"Point","coordinates":[-95.983300,37.233300]},"type":"Feature","properties":{"hierarchy":["tgn:2159398","tgn:1000001","tgn:7012149","tgn:7007254","tgn:7029392"],"placetype":["aat:300008706"],"id":2159398,"name:xx":"Bee Creek"}}
>>>>>>> 03f74aca74312dbeaf24d7e61306dd6a786dc3d0
