{
  "id": 2350303,
  "type": "Feature",
  "properties": {
    "tgn:hierarchy":[
        "tgn:2350303",
        "tgn:1000001",
        "tgn:2001474",
        "tgn:7012149",
        "tgn:7007709",
        "tgn:7029392"
    ],
    "tgn:id":2350303,
    "tgn:name":"Gingercake Creek",
    "tgn:placetype":[
        "aat:300008706"
    ]
},
  "bbox": [],
  "geometry": {"coordinates":[-81.8667,35.9167],"type":"Point"}
}