{
  "id": 2016870,
  "type": "Feature",
  "properties": {
    "tgn:hierarchy":[
        "tgn:2016870",
        "tgn:1000001",
        "tgn:1002601",
        "tgn:7012149",
        "tgn:7007159",
        "tgn:7029392"
    ],
    "tgn:id":2016870,
    "tgn:name":"Falls Village",
    "tgn:placetype":[
        "aat:300008347"
    ]
},
  "bbox": [],
  "geometry": {"coordinates":[-73.35,41.95],"type":"Point"}
}