{
  "id": 7530091,
  "type": "Feature",
  "properties": {
    "tgn:hierarchy":[
        "tgn:7530091",
        "tgn:7001242",
        "tgn:7016833",
        "tgn:1001083",
        "tgn:7029392"
    ],
    "tgn:id":7530091,
    "tgn:name":"Mut\u1e29af Ma\u1e29m\u016bd Khal\u012bl",
    "tgn:placetype":[
        "aat:300005768"
    ]
},
  "bbox": [],
  "geometry": {"coordinates":[31.223755,30.056473],"type":"Point"}
}