{
  "id": 7310962,
  "type": "Feature",
  "properties": {
    "tgn:hierarchy":[
        "tgn:7310962",
        "tgn:7002464",
        "tgn:1000049",
        "tgn:1000002",
        "tgn:7029392"
    ],
    "tgn:id":7310962,
    "tgn:name":"Meza, Cerro",
    "tgn:placetype":[
        "aat:300008795"
    ]
},
  "bbox": [],
  "geometry": {"coordinates":[-68.883333,-20.083333],"type":"Point"}
}