{
  "id": 2153584,
  "type": "Feature",
  "properties": {
    "tgn:hierarchy":[
        "tgn:2153584",
        "tgn:1000001",
        "tgn:7016172",
        "tgn:7012149",
        "tgn:2000175",
        "tgn:7029392"
    ],
    "tgn:id":2153584,
    "tgn:name":"Bear Branch",
    "tgn:placetype":[
        "aat:300008699"
    ]
},
  "bbox": [],
  "geometry": {"coordinates":[-92.3333,35.6833],"type":"Point"}
}