{
  "id": 2695968,
  "type": "Feature",
  "properties": {
    "tgn:hierarchy":[
        "tgn:2695968",
        "tgn:1000001",
        "tgn:7012149",
        "tgn:2001907",
        "tgn:7007825",
        "tgn:7029392"
    ],
    "tgn:id":2695968,
    "tgn:name":"Stockton Estates",
    "tgn:placetype":[
        "aat:300008347"
    ]
},
  "bbox": [],
  "geometry": {"coordinates":[-85.45,36.25],"type":"Point"}
}