{
  "id": 7041698,
  "type": "Feature",
  "properties": {
    "tgn:hierarchy":[
        "tgn:7041698",
        "tgn:7003006",
        "tgn:1000003",
        "tgn:7002997",
        "tgn:1000080",
        "tgn:7029392"
    ],
    "tgn:id":7041698,
    "tgn:name":"San Giorgio in Alga",
    "tgn:placetype":[
        "aat:300008791"
    ]
},
  "bbox": [],
  "geometry": {"coordinates":[12.283333,45.416667],"type":"Point"}
}