{
  "id": 2321352,
  "type": "Feature",
  "properties": {
    "tgn:hierarchy":[
        "tgn:2321352",
        "tgn:1000001",
        "tgn:7012149",
        "tgn:7014160",
        "tgn:7007919",
        "tgn:7029392"
    ],
    "tgn:id":2321352,
    "tgn:name":"Fairfax, Lake",
    "tgn:placetype":[
        "aat:300006191"
    ]
},
  "bbox": [],
  "geometry": {"coordinates":[-77.3167,38.95],"type":"Point"}
}