{
  "id": 7577241,
  "type": "Feature",
  "properties": {
    "tgn:hierarchy":[
        "tgn:7577241",
        "tgn:1000004",
        "tgn:7000198",
        "tgn:7001797",
        "tgn:7029392"
    ],
    "tgn:id":7577241,
    "tgn:name:en":"Kannamangalam",
    "tgn:placetype":[
        "aat:300007783"
    ]
},
  "bbox": [],
  "geometry": {"coordinates":[79.166667,12.75],"type":"Point"}
}