{
  "id": 2177319,
  "type": "Feature",
  "properties": {
    "tgn:hierarchy":[
        "tgn:2177319",
        "tgn:1000001",
        "tgn:7012149",
        "tgn:7014287",
        "tgn:7007568",
        "tgn:7029392"
    ],
    "tgn:id":2177319,
    "tgn:name":"Black River Canal",
    "tgn:placetype":[
        "aat:300006075"
    ]
},
  "bbox": [],
  "geometry": {"coordinates":[-75.4333,43.2333],"type":"Point"}
}