<<<<<<< HEAD
{
  "id": 7357223,
  "type": "Feature",
  "properties": {
    "tgn:hierarchy":[
        "tgn:7357223",
        "tgn:1000001",
        "tgn:1001960",
        "tgn:7005560",
        "tgn:7029392"
    ],
    "tgn:id":7357223,
    "tgn:name":"Chiripa",
    "tgn:placetype":[
        "aat:300008347"
    ]
},
  "bbox": [],
  "geometry": {"coordinates":[-111.2,30.016667],"type":"Point"}
}
=======
{"geometry":{"type":"Point","coordinates":[-111.200000,30.016667]},"type":"Feature","properties":{"hierarchy":["tgn:7357223","tgn:1000001","tgn:1001960","tgn:7005560","tgn:7029392"],"placetype":["aat:300008347"],"id":7357223,"name:xx":"Chiripa"}}
>>>>>>> 03f74aca74312dbeaf24d7e61306dd6a786dc3d0
