{
  "id": 7228742,
  "type": "Feature",
  "properties": {
    "tgn:hierarchy":[
        "tgn:7228742",
        "tgn:7002745",
        "tgn:7017076",
        "tgn:1000003",
        "tgn:1000074",
        "tgn:7029392"
    ],
    "tgn:id":7228742,
    "tgn:name":"Karvoun\u00f3nisos",
    "tgn:placetype":[
        "aat:300011692"
    ]
},
  "bbox": [],
  "geometry": {"coordinates":[22.916667,36.383333],"type":"Point"}
}