{
  "id": 2108857,
  "type": "Feature",
  "properties": {
    "tgn:hierarchy":[
        "tgn:2108857",
        "tgn:1000001",
        "tgn:7012149",
        "tgn:2002125",
        "tgn:7007827",
        "tgn:7029392"
    ],
    "tgn:id":2108857,
    "tgn:name":"Fairfield",
    "tgn:placetype":[
        "aat:300008347"
    ]
},
  "bbox": [],
  "geometry": {"coordinates":[-112.0833,40.25],"type":"Point"}
}