{
  "id": 7279107,
  "type": "Feature",
  "properties": {
    "tgn:hierarchy":[
        "tgn:7279107",
        "tgn:1001702",
        "tgn:1000049",
        "tgn:1000002",
        "tgn:7029392"
    ],
    "tgn:id":7279107,
    "tgn:name":"Rub\u00ed, Isla",
    "tgn:placetype":[
        "aat:300008791"
    ]
},
  "bbox": [],
  "geometry": {"coordinates":[-74.183333,-52.083333],"type":"Point"}
}