{
  "id": 7216623,
  "type": "Feature",
  "properties": {
    "tgn:hierarchy":[
        "tgn:7216623",
        "tgn:1000003",
        "tgn:7003677",
        "tgn:7000084",
        "tgn:7029392"
    ],
    "tgn:id":7216623,
    "tgn:name":"Abel-Bach",
    "tgn:placetype":[
        "aat:300008699"
    ]
},
  "bbox": [],
  "geometry": {"coordinates":[8.516667,51.666667],"type":"Point"}
}