{
  "id": 2003143,
  "type": "Feature",
  "properties": {
    "tgn:hierarchy":[
        "tgn:2003143",
        "tgn:7002659",
        "tgn:1000001",
        "tgn:2000012",
        "tgn:7012149",
        "tgn:7029392"
    ],
    "tgn:id":2003143,
    "tgn:name":"Coffeeville",
    "tgn:placetype":[
        "aat:300008347"
    ]
},
  "bbox": [],
  "geometry": {"coordinates":[-88.0833,31.75],"type":"Point"}
}