{
  "id": 2578425,
  "type": "Feature",
  "properties": {
    "tgn:hierarchy":[
        "tgn:2578425",
        "tgn:1000001",
        "tgn:7016172",
        "tgn:2000109",
        "tgn:7012149",
        "tgn:7029392"
    ],
    "tgn:id":2578425,
    "tgn:name":"Phelps Hollow",
    "tgn:placetype":[
        "aat:300008761"
    ]
},
  "bbox": [],
  "geometry": {"coordinates":[-93.2667,36.15],"type":"Point"}
}