{
  "id": 2543104,
  "type": "Feature",
  "properties": {
    "tgn:hierarchy":[
        "tgn:2543104",
        "tgn:1000001",
        "tgn:7012149",
        "tgn:2002114",
        "tgn:7007827",
        "tgn:7029392"
    ],
    "tgn:id":2543104,
    "tgn:name":"Noon Rock Peak",
    "tgn:placetype":[
        "aat:300008798"
    ]
},
  "bbox": [],
  "geometry": {"coordinates":[-112.1167,39.1833],"type":"Point"}
}