{
  "id": 2518646,
  "type": "Feature",
  "properties": {
    "tgn:hierarchy":[
        "tgn:2518646",
        "tgn:1000001",
        "tgn:7012149",
        "tgn:2000850",
        "tgn:7007255",
        "tgn:7029392"
    ],
    "tgn:id":2518646,
    "tgn:name":"Mitchell Knob",
    "tgn:placetype":[
        "aat:300008798"
    ]
},
  "bbox": [],
  "geometry": {"coordinates":[-84.9667,36.6667],"type":"Point"}
}