<<<<<<< HEAD
{
  "id": 2402957,
  "type": "Feature",
  "properties": {
    "tgn:hierarchy":[
        "tgn:2402957",
        "tgn:1000001",
        "tgn:2000924",
        "tgn:7012149",
        "tgn:7007515",
        "tgn:7029392"
    ],
    "tgn:id":2402957,
    "tgn:name":"Hough Ledge",
    "tgn:placetype":[
        "aat:300132348"
    ]
},
  "bbox": [],
  "geometry": {"coordinates":[-69.3667,43.8667],"type":"Point"}
}
=======
{"geometry":{"type":"Point","coordinates":[-69.366700,43.866700]},"type":"Feature","properties":{"hierarchy":["tgn:2402957","tgn:1000001","tgn:2000924","tgn:7012149","tgn:7007515","tgn:7029392"],"placetype":["aat:300132348"],"id":2402957,"name:xx":"Hough Ledge"}}
>>>>>>> 03f74aca74312dbeaf24d7e61306dd6a786dc3d0
