{
  "id": 7218434,
  "type": "Feature",
  "properties": {
    "tgn:hierarchy":[
        "tgn:7218434",
        "tgn:7002681",
        "tgn:7001395",
        "tgn:1000003",
        "tgn:1000074",
        "tgn:7029392"
    ],
    "tgn:id":7218434,
    "tgn:name":"Tourkovo\u00fania",
    "tgn:placetype":[
        "aat:300008777"
    ]
},
  "bbox": [],
  "geometry": {"coordinates":[23.75,38.033333],"type":"Point"}
}