{
  "id": 2295433,
  "type": "Feature",
  "properties": {
    "tgn:hierarchy":[
        "tgn:2295433",
        "tgn:1000001",
        "tgn:7012149",
        "tgn:7007157",
        "tgn:1002608",
        "tgn:7029392"
    ],
    "tgn:id":2295433,
    "tgn:name":"Drinkwater Reservoir",
    "tgn:placetype":[
        "aat:300006191"
    ]
},
  "bbox": [],
  "geometry": {"coordinates":[-118.5167,34.5167],"type":"Point"}
}