{
  "id": 2603024,
  "type": "Feature",
  "properties": {
    "tgn:hierarchy":[
        "tgn:2603024",
        "tgn:1000001",
        "tgn:7012149",
        "tgn:2000283",
        "tgn:7007240",
        "tgn:7029392"
    ],
    "tgn:id":2603024,
    "tgn:name":"Quarry Creek",
    "tgn:placetype":[
        "aat:300008706"
    ]
},
  "bbox": [],
  "geometry": {"coordinates":[-81.2833,29.8667],"type":"Point"}
}