{
  "id": 2748956,
  "type": "Feature",
  "properties": {
    "tgn:hierarchy":[
        "tgn:2748956",
        "tgn:1000001",
        "tgn:2001432",
        "tgn:7012149",
        "tgn:7007566",
        "tgn:7029392"
    ],
    "tgn:id":2748956,
    "tgn:name":"Wall, The",
    "tgn:placetype":[
        "aat:300266640"
    ]
},
  "bbox": [],
  "geometry": {"coordinates":[-105.15,36.9333],"type":"Point"}
}