{
  "id": 7493042,
  "type": "Feature",
  "properties": {
    "tgn:hierarchy":[
        "tgn:7493042",
        "tgn:1000004",
        "tgn:1000454",
        "tgn:1000141",
        "tgn:7029392"
    ],
    "tgn:id":7493042,
    "tgn:name":"Shen'ao Li",
    "tgn:placetype":[
        "aat:300387173"
    ]
},
  "bbox": [],
  "geometry": {"coordinates":[121.8107,25.1302],"type":"Point"}
}