<<<<<<< HEAD
{
  "id": 2332253,
  "type": "Feature",
  "properties": {
    "tgn:hierarchy":[
        "tgn:2332253",
        "tgn:1000001",
        "tgn:7012149",
        "tgn:2002123",
        "tgn:7007827",
        "tgn:7029392"
    ],
    "tgn:id":2332253,
    "tgn:name":"Floating Island",
    "tgn:placetype":[
        "aat:300008798"
    ]
},
  "bbox": [],
  "geometry": {"coordinates":[-113.6333,40.9],"type":"Point"}
}
=======
{"geometry":{"type":"Point","coordinates":[-113.633300,40.900000]},"type":"Feature","properties":{"hierarchy":["tgn:2332253","tgn:1000001","tgn:7012149","tgn:2002123","tgn:7007827","tgn:7029392"],"placetype":["aat:300008798"],"id":2332253,"name:xx":"Floating Island"}}
>>>>>>> 03f74aca74312dbeaf24d7e61306dd6a786dc3d0
