{
  "id": 1113112,
  "type": "Feature",
  "properties": {
    "tgn:hierarchy":[
        "tgn:1113112",
        "tgn:7004732",
        "tgn:1000004",
        "tgn:7004542",
        "tgn:1000111",
        "tgn:7029392"
    ],
    "tgn:id":1113112,
    "tgn:name":"Hau Hoi Wan",
    "tgn:placetype":[
        "aat:300132316"
    ]
},
  "bbox": [],
  "geometry": {"coordinates":[113.9167,22.45],"type":"Point"}
}