{
  "id": 2454560,
  "type": "Feature",
  "properties": {
    "tgn:hierarchy":[
        "tgn:2454560",
        "tgn:1000001",
        "tgn:7012149",
        "tgn:2002359",
        "tgn:7007922",
        "tgn:7029392"
    ],
    "tgn:id":2454560,
    "tgn:name":"Little Deerskin River",
    "tgn:placetype":[
        "aat:300008707"
    ]
},
  "bbox": [],
  "geometry": {"coordinates":[-89.15,45.9833],"type":"Point"}
}