{
  "id": 1017041,
  "type": "Feature",
  "properties": {
    "tgn:hierarchy":[
        "tgn:1017041",
        "tgn:1000001",
        "tgn:7005601",
        "tgn:7005560",
        "tgn:7029392"
    ],
    "tgn:id":1017041,
    "tgn:name":"Atotonilco de los Mart\u00ednez",
    "tgn:placetype":[
        "aat:300008347"
    ]
},
  "bbox": [],
  "geometry": {"coordinates":[-102.75,24.25],"type":"Point"}
}