{
  "id": 2543420,
  "type": "Feature",
  "properties": {
    "tgn:hierarchy":[
        "tgn:2543420",
        "tgn:1000001",
        "tgn:7012149",
        "tgn:2000281",
        "tgn:7007240",
        "tgn:7029392"
    ],
    "tgn:id":2543420,
    "tgn:name":"Norreigo Point",
    "tgn:placetype":[
        "aat:300008850"
    ]
},
  "bbox": [],
  "geometry": {"coordinates":[-86.4833,30.3833],"type":"Point"}
}