{
  "id": 7587013,
  "type": "Feature",
  "properties": {
    "tgn:hierarchy":[
        "tgn:7587013",
        "tgn:1000004",
        "tgn:1001832",
        "tgn:7000198",
        "tgn:7029392"
    ],
    "tgn:id":7587013,
    "tgn:name:en":"Gor\u0101m\u0101ri",
    "tgn:placetype":[
        "aat:300008347"
    ]
},
  "bbox": [],
  "geometry": {"coordinates":[92.292654,26.347409],"type":"Point"}
}