{
  "id": 2041584,
  "type": "Feature",
  "properties": {
    "tgn:hierarchy":[
        "tgn:2041584",
        "tgn:1000001",
        "tgn:7012149",
        "tgn:1002544",
        "tgn:7007255",
        "tgn:7029392"
    ],
    "tgn:id":2041584,
    "tgn:name":"Taylor Mill",
    "tgn:placetype":[
        "aat:300008347"
    ]
},
  "bbox": [],
  "geometry": {"coordinates":[-84.4833,38.9833],"type":"Point"}
}