<<<<<<< HEAD
{
  "id": 2408588,
  "type": "Feature",
  "properties": {
    "tgn:hierarchy":[
        "tgn:2408588",
        "tgn:1000001",
        "tgn:7012149",
        "tgn:2002249",
        "tgn:7007920",
        "tgn:7029392"
    ],
    "tgn:id":2408588,
    "tgn:name":"Hutton Settlement",
    "tgn:placetype":[
        "aat:300008347"
    ]
},
  "bbox": [],
  "geometry": {"coordinates":[-117.25,47.7],"type":"Point"}
}
=======
{"geometry":{"type":"Point","coordinates":[-117.250000,47.700000]},"type":"Feature","properties":{"hierarchy":["tgn:2408588","tgn:1000001","tgn:7012149","tgn:2002249","tgn:7007920","tgn:7029392"],"placetype":["aat:300008347"],"id":2408588,"name:xx":"Hutton Settlement"}}
>>>>>>> 03f74aca74312dbeaf24d7e61306dd6a786dc3d0
