{
  "id": 2395789,
  "type": "Feature",
  "properties": {
    "tgn:hierarchy":[
        "tgn:2395789",
        "tgn:1000001",
        "tgn:7012149",
        "tgn:7007826",
        "tgn:7029392"
    ],
    "tgn:id":2395789,
    "tgn:name":"Hollow Rock Branch",
    "tgn:placetype":[
        "aat:300008699"
    ]
},
  "bbox": [],
  "geometry": {"coordinates":[-94.6833,31.85],"type":"Point"}
}