{
  "id": 7349611,
  "type": "Feature",
  "properties": {
    "tgn:hierarchy":[
        "tgn:7349611",
        "tgn:1000001",
        "tgn:7005595",
        "tgn:7005560",
        "tgn:7029392"
    ],
    "tgn:id":7349611,
    "tgn:name":"Agua Nueva",
    "tgn:placetype":[
        "aat:300008347"
    ]
},
  "bbox": [],
  "geometry": {"coordinates":[-106.823611,24.090278],"type":"Point"}
}