<<<<<<< HEAD
{
  "id": 7474429,
  "type": "Feature",
  "properties": {
    "tgn:hierarchy":[
        "tgn:7474429",
        "tgn:1000004",
        "tgn:7489179",
        "tgn:1000141",
        "tgn:7029392"
    ],
    "tgn:id":7474429,
    "tgn:name":"Tiansongpi",
    "tgn:placetype":[
        "aat:300008347"
    ]
},
  "bbox": [],
  "geometry": {"coordinates":[121.623137,24.661428],"type":"Point"}
}
=======
{"geometry":{"type":"Point","coordinates":[121.623137,24.661428]},"type":"Feature","properties":{"hierarchy":["tgn:7474429","tgn:1000004","tgn:7489179","tgn:1000141","tgn:7029392"],"placetype":["aat:300008347"],"id":7474429,"name:xx":"Tiansongpi"}}
>>>>>>> 03f74aca74312dbeaf24d7e61306dd6a786dc3d0
