{
  "id": 7064080,
  "type": "Feature",
  "properties": {
    "tgn:hierarchy":[
        "tgn:7064080",
        "tgn:7000096",
        "tgn:1000003",
        "tgn:7000084",
        "tgn:7029392"
    ],
    "tgn:id":7064080,
    "tgn:name":"Annenwalde",
    "tgn:placetype":[
        "aat:300008347"
    ]
},
  "bbox": [],
  "geometry": {"coordinates":[13.383333,53.133333],"type":"Point"}
}