{
  "id": 7399390,
  "type": "Feature",
  "properties": {
    "tgn:hierarchy":[
        "tgn:7399390",
        "tgn:1000001",
        "tgn:7005593",
        "tgn:7005560",
        "tgn:7029392"
    ],
    "tgn:id":7399390,
    "tgn:name":"Estancia de Santa Luc\u00eda",
    "tgn:placetype":[
        "aat:300008347"
    ]
},
  "bbox": [],
  "geometry": {"coordinates":[-100.0625,20.258333],"type":"Point"}
}