{
  "id": 7219623,
  "type": "Feature",
  "properties": {
    "tgn:hierarchy":[
        "tgn:7219623",
        "tgn:7011330",
        "tgn:7002674",
        "tgn:1000003",
        "tgn:1000074",
        "tgn:7029392"
    ],
    "tgn:id":7219623,
    "tgn:name":"Christ\u00f3s",
    "tgn:placetype":[
        "aat:300007466"
    ]
},
  "bbox": [],
  "geometry": {"coordinates":[26.938056,36.739167],"type":"Point"}
}