<<<<<<< HEAD
{
  "id": 7368441,
  "type": "Feature",
  "properties": {
    "tgn:hierarchy":[
        "tgn:7368441",
        "tgn:1000001",
        "tgn:7005589",
        "tgn:7005560",
        "tgn:7029392"
    ],
    "tgn:id":7368441,
    "tgn:name":"Joya, Arroyo de la",
    "tgn:placetype":[
        "aat:300266554",
        "aat:300008699"
    ]
},
  "bbox": [],
  "geometry": {"coordinates":[-99.183333,25.3],"type":"Point"}
}
=======
{"geometry":{"type":"Point","coordinates":[-99.183333,25.300000]},"type":"Feature","properties":{"hierarchy":["tgn:7368441","tgn:1000001","tgn:7005589","tgn:7005560","tgn:7029392"],"placetype":["aat:300266554","aat:300008699"],"id":7368441,"name:xx":"Joya, Arroyo de la"}}
>>>>>>> 03f74aca74312dbeaf24d7e61306dd6a786dc3d0
