{
  "id": 7507593,
  "type": "Feature",
  "properties": {
    "tgn:hierarchy":[
        "tgn:7507593",
        "tgn:1009227",
        "tgn:1000226",
        "tgn:7016822",
        "tgn:1000006",
        "tgn:7029392"
    ],
    "tgn:id":7507593,
    "tgn:name:en":"Port Craig",
    "tgn:placetype":[
        "aat:300008347"
    ]
},
  "bbox": [],
  "geometry": {"coordinates":[167.35,-46.216667],"type":"Point"}
}