<<<<<<< HEAD
{
  "id": 2706466,
  "type": "Feature",
  "properties": {
    "tgn:hierarchy":[
        "tgn:2706466",
        "tgn:1000001",
        "tgn:7012149",
        "tgn:2002117",
        "tgn:7007827",
        "tgn:7029392"
    ],
    "tgn:id":2706466,
    "tgn:name":"Swan Creek Spring",
    "tgn:placetype":[
        "aat:300008697"
    ]
},
  "bbox": [],
  "geometry": {"coordinates":[-111.4167,41.9833],"type":"Point"}
}
=======
{"geometry":{"type":"Point","coordinates":[-111.416700,41.983300]},"type":"Feature","properties":{"hierarchy":["tgn:2706466","tgn:1000001","tgn:7012149","tgn:2002117","tgn:7007827","tgn:7029392"],"placetype":["aat:300008697"],"id":2706466,"name:xx":"Swan Creek Spring"}}
>>>>>>> 03f74aca74312dbeaf24d7e61306dd6a786dc3d0
