{
  "id": 2721186,
  "type": "Feature",
  "properties": {
    "tgn:hierarchy":[
        "tgn:2721186",
        "tgn:1000001",
        "tgn:7012149",
        "tgn:1002977",
        "tgn:7007240",
        "tgn:7029392"
    ],
    "tgn:id":2721186,
    "tgn:name":"Tiger Bay Island",
    "tgn:placetype":[
        "aat:300008791"
    ]
},
  "bbox": [],
  "geometry": {"coordinates":[-81.1667,29.1333],"type":"Point"}
}