{
  "id": 7083053,
  "type": "Feature",
  "properties": {
    "tgn:hierarchy":[
        "tgn:7083053",
        "tgn:1000003",
        "tgn:7000094",
        "tgn:7000084",
        "tgn:7029392"
    ],
    "tgn:id":7083053,
    "tgn:name":"F\u00f6rsterei Wendeforst",
    "tgn:placetype":[
        "aat:300004792"
    ]
},
  "bbox": [],
  "geometry": {"coordinates":[12.966667,53.916667],"type":"Point"}
}