{
  "id": 1088507,
  "type": "Feature",
  "properties": {
    "tgn:hierarchy":[
        "tgn:1088507",
        "tgn:7001242",
        "tgn:1000968",
        "tgn:1000156",
        "tgn:7029392"
    ],
    "tgn:id":1088507,
    "tgn:name":"Goubon",
    "tgn:placetype":[
        "aat:300008347"
    ]
},
  "bbox": [],
  "geometry": {"coordinates":[17.15,20.7667],"type":"Point"}
}