{
  "id": 7180101,
  "type": "Feature",
  "properties": {
    "tgn:hierarchy":[
        "tgn:7180101",
        "tgn:7003692",
        "tgn:1000003",
        "tgn:7000084",
        "tgn:7029392"
    ],
    "tgn:id":7180101,
    "tgn:name":"Gebenweiler Gehren",
    "tgn:placetype":[
        "aat:300008347"
    ]
},
  "bbox": [],
  "geometry": {"coordinates":[9.666667,48.916667],"type":"Point"}
}