{
  "id": 2436769,
  "type": "Feature",
  "properties": {
    "tgn:hierarchy":[
        "tgn:2436769",
        "tgn:7023902",
        "tgn:1000001",
        "tgn:7012149",
        "tgn:7007249",
        "tgn:7029392"
    ],
    "tgn:id":2436769,
    "tgn:name":"Kilauea Forest Reserve",
    "tgn:placetype":[
        "aat:300008863"
    ]
},
  "bbox": [],
  "geometry": {"coordinates":[-155.2667,19.4667],"type":"Point"}
}