{
  "id": 7255492,
  "type": "Feature",
  "properties": {
    "tgn:hierarchy":[
        "tgn:7255492",
        "tgn:7003456",
        "tgn:1000003",
        "tgn:1000063",
        "tgn:7018236",
        "tgn:7029392"
    ],
    "tgn:id":7255492,
    "tgn:name":"Rooienberghof",
    "tgn:placetype":[
        "aat:300000206"
    ]
},
  "bbox": [],
  "geometry": {"coordinates":[4.483333,51.083333],"type":"Point"}
}