{
  "id": 7162730,
  "type": "Feature",
  "properties": {
    "tgn:hierarchy":[
        "tgn:7162730",
        "tgn:7003669",
        "tgn:1000003",
        "tgn:7000084",
        "tgn:7029392"
    ],
    "tgn:id":7162730,
    "tgn:name":"H\u00fcllen Graben",
    "tgn:placetype":[
        "aat:300008699"
    ]
},
  "bbox": [],
  "geometry": {"coordinates":[11.233333,49.733333],"type":"Point"}
}