{
  "id": 7548978,
  "type": "Feature",
  "properties": {
    "tgn:hierarchy":[
        "tgn:7548978",
        "tgn:1000004",
        "tgn:7000198",
        "tgn:7016788",
        "tgn:7029392"
    ],
    "tgn:id":7548978,
    "tgn:name:en":"Duragpura",
    "tgn:placetype":[
        "aat:300008347"
    ]
},
  "bbox": [],
  "geometry": {"coordinates":[76.135827,24.631484],"type":"Point"}
}