{
  "id": 7494054,
  "type": "Feature",
  "properties": {
    "tgn:hierarchy":[
        "tgn:7494054",
        "tgn:1000004",
        "tgn:7491221",
        "tgn:1000141",
        "tgn:7029392"
    ],
    "tgn:id":7494054,
    "tgn:name":"Songbaikeng",
    "tgn:placetype":[
        "aat:300008347"
    ]
},
  "bbox": [],
  "geometry": {"coordinates":[121.278742,23.065301],"type":"Point"}
}