{
  "id": 2510683,
  "type": "Feature",
  "properties": {
    "tgn:hierarchy":[
        "tgn:2510683",
        "tgn:1000001",
        "tgn:1002665",
        "tgn:7012149",
        "tgn:7007517",
        "tgn:7029392"
    ],
    "tgn:id":2510683,
    "tgn:name":"Middlesex Village",
    "tgn:placetype":[
        "aat:300008347"
    ]
},
  "bbox": [],
  "geometry": {"coordinates":[-71.3333,42.6333],"type":"Point"}
}