{
  "id": 7532776,
  "type": "Feature",
  "properties": {
    "tgn:hierarchy":[
        "tgn:7532776",
        "tgn:7001242",
        "tgn:7016833",
        "tgn:7001336",
        "tgn:7029392"
    ],
    "tgn:id":7532776,
    "tgn:name":"Ruheib\u00eeya, W\u00e2di",
    "tgn:placetype":[
        "aat:300379998"
    ]
},
  "bbox": [],
  "geometry": {"coordinates":[34.608335,28.706305],"type":"Point"}
}