{
  "id": 2150197,
  "type": "Feature",
  "properties": {
    "tgn:hierarchy":[
        "tgn:2150197",
        "tgn:1000001",
        "tgn:7012149",
        "tgn:1002785",
        "tgn:7007920",
        "tgn:7029392"
    ],
    "tgn:id":2150197,
    "tgn:name":"Basalt Creek",
    "tgn:placetype":[
        "aat:300008706"
    ]
},
  "bbox": [],
  "geometry": {"coordinates":[-121.65,46.8167],"type":"Point"}
}