{
  "id": 7258562,
  "type": "Feature",
  "properties": {
    "tgn:hierarchy":[
        "tgn:7258562",
        "tgn:1000003",
        "tgn:7006951",
        "tgn:7016845",
        "tgn:7029392"
    ],
    "tgn:id":7258562,
    "tgn:name:nl":"Afgesloten IJ",
    "tgn:placetype":[
        "aat:300008678"
    ]
},
  "bbox": [],
  "geometry": {"coordinates":[4.933333,52.383333],"type":"Point"}
}