{
  "id": 2674607,
  "type": "Feature",
  "properties": {
    "tgn:hierarchy":[
        "tgn:2674607",
        "tgn:1000001",
        "tgn:7016106",
        "tgn:7012149",
        "tgn:7007516",
        "tgn:7029392"
    ],
    "tgn:id":2674607,
    "tgn:name":"Snyders Landing",
    "tgn:placetype":[
        "aat:300008347"
    ]
},
  "bbox": [],
  "geometry": {"coordinates":[-77.7667,39.45],"type":"Point"}
}