{
  "id": 2638987,
  "type": "Feature",
  "properties": {
    "tgn:hierarchy":[
        "tgn:2638987",
        "tgn:1000001",
        "tgn:7012149",
        "tgn:7007157",
        "tgn:1002566",
        "tgn:7029392"
    ],
    "tgn:id":2638987,
    "tgn:name":"Salt Flat Creek",
    "tgn:placetype":[
        "aat:300008706"
    ]
},
  "bbox": [],
  "geometry": {"coordinates":[-122.9667,39.2333],"type":"Point"}
}