{
  "id": 2686990,
  "type": "Feature",
  "properties": {
    "tgn:hierarchy":[
        "tgn:2686990",
        "tgn:1000001",
        "tgn:2001411",
        "tgn:7012149",
        "tgn:7007526",
        "tgn:7029392"
    ],
    "tgn:id":2686990,
    "tgn:name":"Spring Gulch",
    "tgn:placetype":[
        "aat:300008761"
    ]
},
  "bbox": [],
  "geometry": {"coordinates":[-114.2333,40.6167],"type":"Point"}
}