<<<<<<< HEAD
{
  "id": 2252851,
  "type": "Feature",
  "properties": {
    "tgn:hierarchy":[
        "tgn:2252851",
        "tgn:1000001",
        "tgn:1002310",
        "tgn:7012149",
        "tgn:7007710",
        "tgn:7029392"
    ],
    "tgn:id":2252851,
    "tgn:name":"Conodoguinet Cave",
    "tgn:placetype":[
        "aat:300008746"
    ]
},
  "bbox": [],
  "geometry": {"coordinates":[-77.1833,40.2167],"type":"Point"}
}
=======
{"geometry":{"type":"Point","coordinates":[-77.183300,40.216700]},"type":"Feature","properties":{"hierarchy":["tgn:2252851","tgn:1000001","tgn:1002310","tgn:7012149","tgn:7007710","tgn:7029392"],"placetype":["aat:300008746"],"id":2252851,"name:xx":"Conodoguinet Cave"}}
>>>>>>> 03f74aca74312dbeaf24d7e61306dd6a786dc3d0
