{
  "id": 2689467,
  "type": "Feature",
  "properties": {
    "tgn:hierarchy":[
        "tgn:2689467",
        "tgn:1000001",
        "tgn:7012149",
        "tgn:2002124",
        "tgn:7007827",
        "tgn:7029392"
    ],
    "tgn:id":2689467,
    "tgn:name":"Squaw Hill",
    "tgn:placetype":[
        "aat:300008798"
    ]
},
  "bbox": [],
  "geometry": {"coordinates":[-109.0667,40.55],"type":"Point"}
}