{
  "id": 2607229,
  "type": "Feature",
  "properties": {
    "tgn:hierarchy":[
        "tgn:2607229",
        "tgn:1000001",
        "tgn:7012149",
        "tgn:2000523",
        "tgn:7007251",
        "tgn:7029392"
    ],
    "tgn:id":2607229,
    "tgn:name":"Randolph Branch",
    "tgn:placetype":[
        "aat:300008699"
    ]
},
  "bbox": [],
  "geometry": {"coordinates":[-88.5333,37.45],"type":"Point"}
}