{
  "id": 2615174,
  "type": "Feature",
  "properties": {
    "tgn:hierarchy":[
        "tgn:2615174",
        "tgn:1000001",
        "tgn:7012149",
        "tgn:2000388",
        "tgn:7007248",
        "tgn:7029392"
    ],
    "tgn:id":2615174,
    "tgn:name":"Reservoir 31",
    "tgn:placetype":[
        "aat:300006191"
    ]
},
  "bbox": [],
  "geometry": {"coordinates":[-83.2667,34.0333],"type":"Point"}
}