{
  "id": 2300815,
  "type": "Feature",
  "properties": {
    "tgn:hierarchy":[
        "tgn:2300815",
        "tgn:1000001",
        "tgn:7012149",
        "tgn:1002426",
        "tgn:7007255",
        "tgn:7029392"
    ],
    "tgn:id":2300815,
    "tgn:name":"Duncan Fork",
    "tgn:placetype":[
        "aat:300008699"
    ]
},
  "bbox": [],
  "geometry": {"coordinates":[-82.9833,38.4333],"type":"Point"}
}