{
  "id": 2263176,
  "type": "Feature",
  "properties": {
    "tgn:hierarchy":[
        "tgn:2263176",
        "tgn:1000001",
        "tgn:7012149",
        "tgn:2001658",
        "tgn:7007707",
        "tgn:7029392"
    ],
    "tgn:id":2263176,
    "tgn:name":"Cowskin Creek",
    "tgn:placetype":[
        "aat:300008706"
    ]
},
  "bbox": [],
  "geometry": {"coordinates":[-97.15,36.7333],"type":"Point"}
}