<<<<<<< HEAD
{
  "id": 7246505,
  "type": "Feature",
  "properties": {
    "tgn:hierarchy":[
        "tgn:7246505",
        "tgn:7003457",
        "tgn:1000003",
        "tgn:1000063",
        "tgn:7018236",
        "tgn:7029392"
    ],
    "tgn:id":7246505,
    "tgn:name":"Bosse",
    "tgn:placetype":[
        "aat:300008347"
    ]
},
  "bbox": [],
  "geometry": {"coordinates":[3.666667,50.883333],"type":"Point"}
}
=======
{"geometry":{"type":"Point","coordinates":[3.666667,50.883333]},"type":"Feature","properties":{"hierarchy":["tgn:7246505","tgn:7003457","tgn:1000003","tgn:1000063","tgn:7018236","tgn:7029392"],"placetype":["aat:300008347"],"id":7246505,"name:xx":"Bosse"}}
>>>>>>> 03f74aca74312dbeaf24d7e61306dd6a786dc3d0
