{
  "id": 7291567,
  "type": "Feature",
  "properties": {
    "tgn:hierarchy":[
        "tgn:7291567",
        "tgn:1001695",
        "tgn:1000049",
        "tgn:1000002",
        "tgn:7029392"
    ],
    "tgn:id":7291567,
    "tgn:name":"Fray Carlos, Estero",
    "tgn:placetype":[
        "aat:300008699"
    ]
},
  "bbox": [],
  "geometry": {"coordinates":[-70.416667,-34.833333],"type":"Point"}
}