{
  "id": 2339339,
  "type": "Feature",
  "properties": {
    "tgn:hierarchy":[
        "tgn:2339339",
        "tgn:7006450",
        "tgn:1000001",
        "tgn:2124053",
        "tgn:7012149",
        "tgn:7029392"
    ],
    "tgn:id":2339339,
    "tgn:name":"Frazer Lake",
    "tgn:placetype":[
        "aat:300008680"
    ]
},
  "bbox": [],
  "geometry": {"coordinates":[-150.05,61.65],"type":"Point"}
}