{
  "id": 7041447,
  "type": "Feature",
  "properties": {
    "tgn:hierarchy":[
        "tgn:7041447",
        "tgn:7003011",
        "tgn:7003005",
        "tgn:1000003",
        "tgn:1000080",
        "tgn:7029392"
    ],
    "tgn:id":7041447,
    "tgn:name":"San Marco",
    "tgn:placetype":[
        "aat:300008347"
    ]
},
  "bbox": [],
  "geometry": {"coordinates":[14.016667,41.216667],"type":"Point"}
}