{
  "id": 7553201,
  "type": "Feature",
  "properties": {
    "tgn:hierarchy":[
        "tgn:7553201",
        "tgn:1000004",
        "tgn:7000198",
        "tgn:1001882",
        "tgn:7029392"
    ],
    "tgn:id":7553201,
    "tgn:name:en":"Mulgund",
    "tgn:placetype":[
        "aat:300008347"
    ]
},
  "bbox": [],
  "geometry": {"coordinates":[75.533333,15.25],"type":"Point"}
}