<<<<<<< HEAD
{
  "id": 7356062,
  "type": "Feature",
  "properties": {
    "tgn:hierarchy":[
        "tgn:7356062",
        "tgn:1001853",
        "tgn:1000001",
        "tgn:7005560",
        "tgn:7029392"
    ],
    "tgn:id":7356062,
    "tgn:name":"Chifl\u00f3n, Sierra del",
    "tgn:placetype":[
        "aat:300008795"
    ]
},
  "bbox": [],
  "geometry": {"coordinates":[-101.25,25.7],"type":"Point"}
}
=======
{"geometry":{"type":"Point","coordinates":[-101.250000,25.700000]},"type":"Feature","properties":{"hierarchy":["tgn:7356062","tgn:1001853","tgn:1000001","tgn:7005560","tgn:7029392"],"placetype":["aat:300008795"],"id":7356062,"name:xx":"Chifl\u00f3n, Sierra del"}}
>>>>>>> 03f74aca74312dbeaf24d7e61306dd6a786dc3d0
