{
  "id": 2091252,
  "type": "Feature",
  "properties": {
    "tgn:hierarchy":[
        "tgn:2091252",
        "tgn:1000001",
        "tgn:7012149",
        "tgn:1002659",
        "tgn:7007710",
        "tgn:7029392"
    ],
    "tgn:id":2091252,
    "tgn:name":"New Hamburg",
    "tgn:placetype":[
        "aat:300008347"
    ]
},
  "bbox": [],
  "geometry": {"coordinates":[-80.3333,41.3167],"type":"Point"}
}