<<<<<<< HEAD
{
  "id": 7059758,
  "type": "Feature",
  "properties": {
    "tgn:hierarchy":[
        "tgn:7059758",
        "tgn:1000003",
        "tgn:7003676",
        "tgn:7000084",
        "tgn:7029392"
    ],
    "tgn:id":7059758,
    "tgn:name":"Ahlde",
    "tgn:placetype":[
        "aat:300387173"
    ]
},
  "bbox": [],
  "geometry": {"coordinates":[7.3,52.35],"type":"Point"}
}
=======
{"geometry":{"type":"Point","coordinates":[7.300000,52.350000]},"type":"Feature","properties":{"hierarchy":["tgn:7059758","tgn:1000003","tgn:7003676","tgn:7000084","tgn:7029392"],"placetype":["aat:300387173"],"id":7059758,"name:xx":"Ahlde"}}
>>>>>>> 03f74aca74312dbeaf24d7e61306dd6a786dc3d0
