{
  "id": 7228306,
  "type": "Feature",
  "properties": {
    "tgn:hierarchy":[
        "tgn:7228306",
        "tgn:7002681",
        "tgn:7001395",
        "tgn:1000003",
        "tgn:1000074",
        "tgn:7029392"
    ],
    "tgn:id":7228306,
    "tgn:name":"Kalavr\u00eda, \u00c1kra",
    "tgn:placetype":[
        "aat:300008850"
    ]
},
  "bbox": [],
  "geometry": {"coordinates":[23.524453,37.523613],"type":"Point"}
}