{
  "id": 7553380,
  "type": "Feature",
  "properties": {
    "tgn:hierarchy":[
        "tgn:7553380",
        "tgn:1000004",
        "tgn:7000198",
        "tgn:1001977",
        "tgn:7029392"
    ],
    "tgn:id":7553380,
    "tgn:name:en":"Mas\u0101ldaha B\u0101z\u0101r",
    "tgn:placetype":[
        "aat:300008347"
    ]
},
  "bbox": [],
  "geometry": {"coordinates":[87.916667,25.316667],"type":"Point"}
}