{
  "id": 7057907,
  "type": "Feature",
  "properties": {
    "tgn:hierarchy":[
        "tgn:7057907",
        "tgn:7003132",
        "tgn:1000003",
        "tgn:7008516",
        "tgn:1000080",
        "tgn:7029392"
    ],
    "tgn:id":7057907,
    "tgn:name":"Brugneto",
    "tgn:placetype":[
        "aat:300008347"
    ]
},
  "bbox": [],
  "geometry": {"coordinates":[9.416667,44.666667],"type":"Point"}
}