{
  "id": 7535647,
  "type": "Feature",
  "properties": {
    "tgn:hierarchy":[
        "tgn:7535647",
        "tgn:7001242",
        "tgn:7001311",
        "tgn:7016833",
        "tgn:7029392"
    ],
    "tgn:id":7535647,
    "tgn:name:en":"Khannikat Um Lahh\u00e2m, Gebel",
    "tgn:placetype":[
        "aat:300008795"
    ]
},
  "bbox": [],
  "geometry": {"coordinates":[35.111275,24.196774],"type":"Point"}
}