{
  "id": 2100402,
  "type": "Feature",
  "properties": {
    "tgn:hierarchy":[
        "tgn:2100402",
        "tgn:1000001",
        "tgn:7012149",
        "tgn:2001926",
        "tgn:7007825",
        "tgn:7029392"
    ],
    "tgn:id":2100402,
    "tgn:name":"Mill Brook",
    "tgn:placetype":[
        "aat:300008347",
        "aat:300387210"
    ]
},
  "bbox": [],
  "geometry": {"coordinates":[-82.6167,36.25],"type":"Point"}
}