{
  "id": 7305142,
  "type": "Feature",
  "properties": {
    "tgn:hierarchy":[
        "tgn:7305142",
        "tgn:7002759",
        "tgn:7008909",
        "tgn:1000003",
        "tgn:1000095",
        "tgn:7029392"
    ],
    "tgn:id":7305142,
    "tgn:name":"Laspu\u00f1a",
    "tgn:placetype":[
        "aat:300008347"
    ]
},
  "bbox": [],
  "geometry": {"coordinates":[0.154852,42.503357],"type":"Point"}
}