{
  "id": 2080983,
  "type": "Feature",
  "properties": {
    "tgn:hierarchy":[
        "tgn:2080983",
        "tgn:2001610",
        "tgn:1000001",
        "tgn:7012149",
        "tgn:7007706",
        "tgn:7029392"
    ],
    "tgn:id":2080983,
    "tgn:name":"New England",
    "tgn:placetype":[
        "aat:300008347"
    ]
},
  "bbox": [],
  "geometry": {"coordinates":[-81.9333,39.3333],"type":"Point"}
}