{
  "id": 2446993,
  "type": "Feature",
  "properties": {
    "tgn:hierarchy":[
        "tgn:2446993",
        "tgn:7002659",
        "tgn:1000001",
        "tgn:7012149",
        "tgn:2000044",
        "tgn:7029392"
    ],
    "tgn:id":2446993,
    "tgn:name":"Liberty Hill",
    "tgn:placetype":[
        "aat:300008798"
    ]
},
  "bbox": [],
  "geometry": {"coordinates":[-86.6167,34.8333],"type":"Point"}
}