{
  "id": 2468692,
  "type": "Feature",
  "properties": {
    "tgn:hierarchy":[
        "tgn:2468692",
        "tgn:1000001",
        "tgn:2002368",
        "tgn:7012149",
        "tgn:7007923",
        "tgn:7029392"
    ],
    "tgn:id":2468692,
    "tgn:name":"Long Pond Reservoir",
    "tgn:placetype":[
        "aat:300006191"
    ]
},
  "bbox": [],
  "geometry": {"coordinates":[-107.0333,41.4333],"type":"Point"}
}