{
  "id": 7298652,
  "type": "Feature",
  "properties": {
    "tgn:hierarchy":[
        "tgn:7298652",
        "tgn:7002760",
        "tgn:1000003",
        "tgn:1000095",
        "tgn:7029392"
    ],
    "tgn:id":7298652,
    "tgn:name":"Torices",
    "tgn:placetype":[
        "aat:300008347"
    ]
},
  "bbox": [],
  "geometry": {"coordinates":[-4.55,43.133333],"type":"Point"}
}