{
  "id": 2630047,
  "type": "Feature",
  "properties": {
    "tgn:hierarchy":[
        "tgn:2630047",
        "tgn:1000001",
        "tgn:7012149",
        "tgn:2001036",
        "tgn:7007521",
        "tgn:7029392"
    ],
    "tgn:id":2630047,
    "tgn:name":"Rota Lake",
    "tgn:placetype":[
        "aat:300008680"
    ]
},
  "bbox": [],
  "geometry": {"coordinates":[-91.45,47.5333],"type":"Point"}
}