{
  "id": 1020620,
  "type": "Feature",
  "properties": {
    "tgn:hierarchy":[
        "tgn:1020620",
        "tgn:7012827",
        "tgn:7002454",
        "tgn:1000047",
        "tgn:1000002",
        "tgn:7029392"
    ],
    "tgn:id":1020620,
    "tgn:name":"Anhanguera",
    "tgn:placetype":[
        "aat:300008347"
    ]
},
  "bbox": [],
  "geometry": {"coordinates":[-48.2333,-18.3167],"type":"Point"}
}