<<<<<<< HEAD
{
  "id": 7359931,
  "type": "Feature",
  "properties": {
    "tgn:hierarchy":[
        "tgn:7359931",
        "tgn:7005581",
        "tgn:1000001",
        "tgn:7005560",
        "tgn:7029392"
    ],
    "tgn:id":7359931,
    "tgn:name":"Dos Reales, Laguna de",
    "tgn:placetype":[
        "aat:300008680"
    ]
},
  "bbox": [],
  "geometry": {"coordinates":[-108.183333,30.566667],"type":"Point"}
}
=======
{"geometry":{"type":"Point","coordinates":[-108.183333,30.566667]},"type":"Feature","properties":{"hierarchy":["tgn:7359931","tgn:7005581","tgn:1000001","tgn:7005560","tgn:7029392"],"placetype":["aat:300008680"],"id":7359931,"name:xx":"Dos Reales, Laguna de"}}
>>>>>>> 03f74aca74312dbeaf24d7e61306dd6a786dc3d0
