{
  "id": 7359931,
  "type": "Feature",
  "properties": {
    "tgn:hierarchy":[
        "tgn:7359931",
        "tgn:7005581",
        "tgn:1000001",
        "tgn:7005560",
        "tgn:7029392"
    ],
    "tgn:id":7359931,
    "tgn:name":"Dos Reales, Laguna de",
    "tgn:placetype":[
        "aat:300008680"
    ]
},
  "bbox": [],
  "geometry": {"coordinates":[-108.183333,30.566667],"type":"Point"}
}