{
  "id": 7558399,
  "type": "Feature",
  "properties": {
    "tgn:hierarchy":[
        "tgn:7558399",
        "tgn:1000004",
        "tgn:7000198",
        "tgn:7001797",
        "tgn:7029392"
    ],
    "tgn:id":7558399,
    "tgn:name:en":"R\u0101yakottai",
    "tgn:placetype":[
        "aat:300008347"
    ]
},
  "bbox": [],
  "geometry": {"coordinates":[78.05,12.516667],"type":"Point"}
}