{
  "id": 7032680,
  "type": "Feature",
  "properties": {
    "tgn:hierarchy":[
        "tgn:7032680",
        "tgn:1000146",
        "tgn:7004348",
        "tgn:1000004",
        "tgn:7000261",
        "tgn:7029392"
    ],
    "tgn:id":7032680,
    "tgn:name":"Zafar",
    "tgn:placetype":[
        "aat:300008347",
        "aat:300000810",
        "aat:300167671",
        "aat:300387218",
        "aat:300008057"
    ]
},
  "bbox": [],
  "geometry": {"coordinates":[44.403,14.211],"type":"Point"}
}