{
  "id": 7562355,
  "type": "Feature",
  "properties": {
    "tgn:hierarchy":[
        "tgn:7562355",
        "tgn:1000004",
        "tgn:7000198",
        "tgn:1001894",
        "tgn:7029392"
    ],
    "tgn:id":7562355,
    "tgn:name:en":"Purwa Du\u0101r",
    "tgn:placetype":[
        "aat:300008347"
    ]
},
  "bbox": [],
  "geometry": {"coordinates":[79.126493,26.438612],"type":"Point"}
}