{
  "id": 1096317,
  "type": "Feature",
  "properties": {
    "tgn:hierarchy":[
        "tgn:1096317",
        "tgn:7000490",
        "tgn:1000006",
        "tgn:7001828",
        "tgn:7029392"
    ],
    "tgn:id":1096317,
    "tgn:name":"Bombala",
    "tgn:placetype":[
        "aat:300008347"
    ]
},
  "bbox": [],
  "geometry": {"coordinates":[149.3833,-36.8667],"type":"Point"}
}