{
  "id": 7372725,
  "type": "Feature",
  "properties": {
    "tgn:hierarchy":[
        "tgn:7372725",
        "tgn:1000001",
        "tgn:7005589",
        "tgn:7005560",
        "tgn:7029392"
    ],
    "tgn:id":7372725,
    "tgn:name":"La Osca",
    "tgn:placetype":[
        "aat:300008347"
    ]
},
  "bbox": [],
  "geometry": {"coordinates":[-98.65,25.616667],"type":"Point"}
}