{
  "id": 2471292,
  "type": "Feature",
  "properties": {
    "tgn:hierarchy":[
        "tgn:2471292",
        "tgn:1000001",
        "tgn:7012149",
        "tgn:2001274",
        "tgn:7007524",
        "tgn:7029392"
    ],
    "tgn:id":2471292,
    "tgn:name":"Lost Johnny Creek",
    "tgn:placetype":[
        "aat:300008706"
    ]
},
  "bbox": [],
  "geometry": {"coordinates":[-114.0167,48.2333],"type":"Point"}
}