{
  "id": 7264365,
  "type": "Feature",
  "properties": {
    "tgn:hierarchy":[
        "tgn:7264365",
        "tgn:1000003",
        "tgn:7003624",
        "tgn:7016845",
        "tgn:7029392"
    ],
    "tgn:id":7264365,
    "tgn:name:nl":"Kraaienberg",
    "tgn:placetype":[
        "aat:300387200"
    ]
},
  "bbox": [],
  "geometry": {"coordinates":[5.816667,51.75],"type":"Point"}
}