{
  "id": 2650044,
  "type": "Feature",
  "properties": {
    "tgn:hierarchy":[
        "tgn:2650044",
        "tgn:1000001",
        "tgn:1002473",
        "tgn:7012149",
        "tgn:7007240",
        "tgn:7029392"
    ],
    "tgn:id":2650044,
    "tgn:name":"Sea Pond",
    "tgn:placetype":[
        "aat:300008680"
    ]
},
  "bbox": [],
  "geometry": {"coordinates":[-82.2667,28.4667],"type":"Point"}
}