{
  "id": 7331245,
  "type": "Feature",
  "properties": {
    "tgn:hierarchy":[
        "tgn:7331245",
        "tgn:7002808",
        "tgn:7030216",
        "tgn:1000003",
        "tgn:1000095",
        "tgn:7029392"
    ],
    "tgn:id":7331245,
    "tgn:name":"La R\u00e1pita",
    "tgn:placetype":[
        "aat:300008347"
    ]
},
  "bbox": [],
  "geometry": {"coordinates":[1.64743,41.309708],"type":"Point"}
}