{
  "id": 7177984,
  "type": "Feature",
  "properties": {
    "tgn:hierarchy":[
        "tgn:7177984",
        "tgn:1000003",
        "tgn:7003677",
        "tgn:7000084",
        "tgn:7029392"
    ],
    "tgn:id":7177984,
    "tgn:name":"Hangs Bach",
    "tgn:placetype":[
        "aat:300008699"
    ]
},
  "bbox": [],
  "geometry": {"coordinates":[7.383333,51.983333],"type":"Point"}
}