{
  "id": 7218852,
  "type": "Feature",
  "properties": {
    "tgn:hierarchy":[
        "tgn:7218852",
        "tgn:7011270",
        "tgn:7002674",
        "tgn:1000003",
        "tgn:1000074",
        "tgn:7029392"
    ],
    "tgn:id":7218852,
    "tgn:name":"Ven\u00e9tiko, Vrachonis\u00edda",
    "tgn:placetype":[
        "aat:300008791"
    ]
},
  "bbox": [],
  "geometry": {"coordinates":[25.486389,36.856667],"type":"Point"}
}