{
  "id": 7056536,
  "type": "Feature",
  "properties": {
    "tgn:hierarchy":[
        "tgn:7056536",
        "tgn:7003132",
        "tgn:1000003",
        "tgn:7008516",
        "tgn:1000080",
        "tgn:7029392"
    ],
    "tgn:id":7056536,
    "tgn:name":"Bicchignano",
    "tgn:placetype":[
        "aat:300008347"
    ]
},
  "bbox": [],
  "geometry": {"coordinates":[9.616667,44.883333],"type":"Point"}
}