<<<<<<< HEAD
{
  "id": 7357475,
  "type": "Feature",
  "properties": {
    "tgn:hierarchy":[
        "tgn:7357475",
        "tgn:7005581",
        "tgn:1000001",
        "tgn:7005560",
        "tgn:7029392"
    ],
    "tgn:id":7357475,
    "tgn:name":"Cuiteco, Sierra",
    "tgn:placetype":[
        "aat:300008795"
    ]
},
  "bbox": [],
  "geometry": {"coordinates":[-108.033333,27.4],"type":"Point"}
}
=======
{"geometry":{"type":"Point","coordinates":[-108.033333,27.400000]},"type":"Feature","properties":{"hierarchy":["tgn:7357475","tgn:7005581","tgn:1000001","tgn:7005560","tgn:7029392"],"placetype":["aat:300008795"],"id":7357475,"name:xx":"Cuiteco, Sierra"}}
>>>>>>> 03f74aca74312dbeaf24d7e61306dd6a786dc3d0
