{
  "id": 2622114,
  "type": "Feature",
  "properties": {
    "tgn:hierarchy":[
        "tgn:2622114",
        "tgn:1000001",
        "tgn:7012149",
        "tgn:2001927",
        "tgn:7007825",
        "tgn:7029392"
    ],
    "tgn:id":2622114,
    "tgn:name":"Roberts Hollow",
    "tgn:placetype":[
        "aat:300008761"
    ]
},
  "bbox": [],
  "geometry": {"coordinates":[-87.9167,35.3333],"type":"Point"}
}