{
  "id": 2571272,
  "type": "Feature",
  "properties": {
    "tgn:hierarchy":[
        "tgn:2571272",
        "tgn:1000001",
        "tgn:1002209",
        "tgn:7012149",
        "tgn:7007252",
        "tgn:7029392"
    ],
    "tgn:id":2571272,
    "tgn:name":"Pattys Garden Ridge",
    "tgn:placetype":[
        "aat:300266640"
    ]
},
  "bbox": [],
  "geometry": {"coordinates":[-86.3167,39.2167],"type":"Point"}
}