{
  "id": 2172416,
  "type": "Feature",
  "properties": {
    "tgn:hierarchy":[
        "tgn:2172416",
        "tgn:1000001",
        "tgn:2000868",
        "tgn:7012149",
        "tgn:7007256",
        "tgn:7029392"
    ],
    "tgn:id":2172416,
    "tgn:name":"Bill John Bayou",
    "tgn:placetype":[
        "aat:300008699"
    ]
},
  "bbox": [],
  "geometry": {"coordinates":[-91.7333,31.5167],"type":"Point"}
}