{
  "id": 7543679,
  "type": "Feature",
  "properties": {
    "tgn:hierarchy":[
        "tgn:7543679",
        "tgn:7001242",
        "tgn:7016833",
        "tgn:7001336",
        "tgn:7029392"
    ],
    "tgn:id":7543679,
    "tgn:name":"Kh\u0101dim, Raw\u1e11 al",
    "tgn:placetype":[
        "aat:300379998"
    ]
},
  "bbox": [],
  "geometry": {"coordinates":[33.860278,29.795556],"type":"Point"}
}