{
  "id": 1030423,
  "type": "Feature",
  "properties": {
    "tgn:hierarchy":[
        "tgn:1030423",
        "tgn:7002445",
        "tgn:1000003",
        "tgn:7008131",
        "tgn:7008591",
        "tgn:7029392"
    ],
    "tgn:id":1030423,
    "tgn:name:en":"Rettendon",
    "tgn:placetype":[
        "aat:300008347",
        "aat:300008372"
    ]
},
  "bbox": [],
  "geometry": {"coordinates":[0.55,51.65],"type":"Point"}
}