<<<<<<< HEAD
{
  "id": 2405996,
  "type": "Feature",
  "properties": {
    "tgn:hierarchy":[
        "tgn:2405996",
        "tgn:1000001",
        "tgn:7012149",
        "tgn:2001284",
        "tgn:7007524",
        "tgn:7029392"
    ],
    "tgn:id":2405996,
    "tgn:name":"Humboldt Mine",
    "tgn:placetype":[
        "aat:300000390"
    ]
},
  "bbox": [],
  "geometry": {"coordinates":[-112.0,46.5667],"type":"Point"}
}
=======
{"geometry":{"type":"Point","coordinates":[-112.000000,46.566700]},"type":"Feature","properties":{"hierarchy":["tgn:2405996","tgn:1000001","tgn:7012149","tgn:2001284","tgn:7007524","tgn:7029392"],"placetype":["aat:300000390"],"id":2405996,"name:xx":"Humboldt Mine"}}
>>>>>>> 03f74aca74312dbeaf24d7e61306dd6a786dc3d0
