{
  "id": 7468150,
  "type": "Feature",
  "properties": {
    "tgn:hierarchy":[
        "tgn:7468150",
        "tgn:1000004",
        "tgn:7490934",
        "tgn:1000141",
        "tgn:7029392"
    ],
    "tgn:id":7468150,
    "tgn:name":"Jiaokengzi",
    "tgn:placetype":[
        "aat:300008347"
    ]
},
  "bbox": [],
  "geometry": {"coordinates":[120.385833,22.984167],"type":"Point"}
}