{
  "id": 7404257,
  "type": "Feature",
  "properties": {
    "tgn:hierarchy":[
        "tgn:7404257",
        "tgn:7005578",
        "tgn:1000001",
        "tgn:7005560",
        "tgn:7029392"
    ],
    "tgn:id":7404257,
    "tgn:name":"Oxcabal",
    "tgn:placetype":[
        "aat:300008347"
    ]
},
  "bbox": [],
  "geometry": {"coordinates":[-90.966667,18.85],"type":"Point"}
}