<<<<<<< HEAD
{
  "id": 7371255,
  "type": "Feature",
  "properties": {
    "tgn:hierarchy":[
        "tgn:7371255",
        "tgn:1000001",
        "tgn:7005594",
        "tgn:7005560",
        "tgn:7029392"
    ],
    "tgn:id":7371255,
    "tgn:name":"Ictepec",
    "tgn:placetype":[
        "aat:300008347"
    ]
},
  "bbox": [],
  "geometry": {"coordinates":[-98.65,21.283333],"type":"Point"}
}
=======
{"geometry":{"type":"Point","coordinates":[-98.650000,21.283333]},"type":"Feature","properties":{"hierarchy":["tgn:7371255","tgn:1000001","tgn:7005594","tgn:7005560","tgn:7029392"],"placetype":["aat:300008347"],"id":7371255,"name:xx":"Ictepec"}}
>>>>>>> 03f74aca74312dbeaf24d7e61306dd6a786dc3d0
