{
  "id": 7531655,
  "type": "Feature",
  "properties": {
    "tgn:hierarchy":[
        "tgn:7531655",
        "tgn:7001242",
        "tgn:7016833",
        "tgn:1001092",
        "tgn:7029392"
    ],
    "tgn:id":7531655,
    "tgn:name":"Min\u0163aqat az Zahr\u0101'",
    "tgn:placetype":[
        "aat:300000745"
    ]
},
  "bbox": [],
  "geometry": {"coordinates":[31.272793,30.131709],"type":"Point"}
}