{
  "id": 7398826,
  "type": "Feature",
  "properties": {
    "tgn:hierarchy":[
        "tgn:7398826",
        "tgn:1000001",
        "tgn:1001893",
        "tgn:7005560",
        "tgn:7029392"
    ],
    "tgn:id":7398826,
    "tgn:name":"Cerrito del Panal",
    "tgn:placetype":[
        "aat:300008347"
    ]
},
  "bbox": [],
  "geometry": {"coordinates":[-99.613611,19.493333],"type":"Point"}
}