{
  "id": 2058119,
  "type": "Feature",
  "properties": {
    "tgn:hierarchy":[
        "tgn:2058119",
        "tgn:1000001",
        "tgn:7012149",
        "tgn:2001223",
        "tgn:7007523",
        "tgn:7029392"
    ],
    "tgn:id":2058119,
    "tgn:name":"Boulder City",
    "tgn:placetype":[
        "aat:300008347",
        "aat:300387210"
    ]
},
  "bbox": [],
  "geometry": {"coordinates":[-94.2333,36.7833],"type":"Point"}
}