{
  "id": 7290088,
  "type": "Feature",
  "properties": {
    "tgn:hierarchy":[
        "tgn:7290088",
        "tgn:1001768",
        "tgn:1000049",
        "tgn:1000002",
        "tgn:7029392"
    ],
    "tgn:id":7290088,
    "tgn:name":"El Agua Clara",
    "tgn:placetype":[
        "aat:300008688"
    ]
},
  "bbox": [],
  "geometry": {"coordinates":[-71.416667,-32.583333],"type":"Point"}
}