<<<<<<< HEAD
{
  "id": 2406498,
  "type": "Feature",
  "properties": {
    "tgn:hierarchy":[
        "tgn:2406498",
        "tgn:1000001",
        "tgn:2001014",
        "tgn:7012149",
        "tgn:7007521",
        "tgn:7029392"
    ],
    "tgn:id":2406498,
    "tgn:name":"Hungry Jack Lake",
    "tgn:placetype":[
        "aat:300008680"
    ]
},
  "bbox": [],
  "geometry": {"coordinates":[-90.4333,48.05],"type":"Point"}
}
=======
{"geometry":{"type":"Point","coordinates":[-90.433300,48.050000]},"type":"Feature","properties":{"hierarchy":["tgn:2406498","tgn:1000001","tgn:2001014","tgn:7012149","tgn:7007521","tgn:7029392"],"placetype":["aat:300008680"],"id":2406498,"name:xx":"Hungry Jack Lake"}}
>>>>>>> 03f74aca74312dbeaf24d7e61306dd6a786dc3d0
