{
  "id": 2664567,
  "type": "Feature",
  "properties": {
    "tgn:hierarchy":[
        "tgn:2664567",
        "tgn:1000001",
        "tgn:2001838",
        "tgn:7012149",
        "tgn:7007825",
        "tgn:7029392"
    ],
    "tgn:id":2664567,
    "tgn:name":"Simmons Branch",
    "tgn:placetype":[
        "aat:300008699"
    ]
},
  "bbox": [],
  "geometry": {"coordinates":[-86.5667,35.3833],"type":"Point"}
}