{
  "id": 2703731,
  "type": "Feature",
  "properties": {
    "tgn:hierarchy":[
        "tgn:2703731",
        "tgn:1000001",
        "tgn:7012149",
        "tgn:2001403",
        "tgn:7007525",
        "tgn:7029392"
    ],
    "tgn:id":2703731,
    "tgn:name":"Sumter",
    "tgn:placetype":[
        "aat:300008347"
    ]
},
  "bbox": [],
  "geometry": {"coordinates":[-98.7833,41.5833],"type":"Point"}
}