{
  "id": 1087135,
  "type": "Feature",
  "properties": {
    "tgn:hierarchy":[
        "tgn:1087135",
        "tgn:1000004",
        "tgn:7001063",
        "tgn:1000145",
        "tgn:7029392"
    ],
    "tgn:id":1087135,
    "tgn:name":"H\u00f2a Th\u1edbi",
    "tgn:placetype":[
        "aat:300008347"
    ]
},
  "bbox": [],
  "geometry": {"coordinates":[106.5833,10.7333],"type":"Point"}
}