{
  "id": 1113859,
  "type": "Feature",
  "properties": {
    "tgn:hierarchy":[
        "tgn:1113859",
        "tgn:7018484",
        "tgn:7004543",
        "tgn:1000004",
        "tgn:7004542",
        "tgn:1000111",
        "tgn:7029392"
    ],
    "tgn:id":1113859,
    "tgn:name":"Stanley Bay",
    "tgn:placetype":[
        "aat:300132316"
    ]
},
  "bbox": [],
  "geometry": {"coordinates":[114.1667,22.1667],"type":"Point"}
}