<<<<<<< HEAD
{
  "id": 7377698,
  "type": "Feature",
  "properties": {
    "tgn:hierarchy":[
        "tgn:7377698",
        "tgn:7005581",
        "tgn:1000001",
        "tgn:7005560",
        "tgn:7029392"
    ],
    "tgn:id":7377698,
    "tgn:name":"La Soledad, Arroyo",
    "tgn:placetype":[
        "aat:300008699"
    ]
},
  "bbox": [],
  "geometry": {"coordinates":[-107.25,28.4],"type":"Point"}
}
=======
{"geometry":{"type":"Point","coordinates":[-107.250000,28.400000]},"type":"Feature","properties":{"hierarchy":["tgn:7377698","tgn:7005581","tgn:1000001","tgn:7005560","tgn:7029392"],"placetype":["aat:300008699"],"id":7377698,"name:xx":"La Soledad, Arroyo"}}
>>>>>>> 03f74aca74312dbeaf24d7e61306dd6a786dc3d0
