{
  "id": 2247307,
  "type": "Feature",
  "properties": {
    "tgn:hierarchy":[
        "tgn:2247307",
        "tgn:1000001",
        "tgn:7012149",
        "tgn:2000491",
        "tgn:7007250",
        "tgn:7029392"
    ],
    "tgn:id":2247307,
    "tgn:name":"Coeur d'Alene Saint Joe Divide",
    "tgn:placetype":[
        "aat:300266640"
    ]
},
  "bbox": [],
  "geometry": {"coordinates":[-115.8333,47.4333],"type":"Point"}
}