{
  "id": 2019480,
  "type": "Feature",
  "properties": {
    "tgn:hierarchy":[
        "tgn:2019480",
        "tgn:1000001",
        "tgn:7012149",
        "tgn:1002631",
        "tgn:7007240",
        "tgn:7029392"
    ],
    "tgn:id":2019480,
    "tgn:name":"Grahamsville",
    "tgn:placetype":[
        "aat:300008347",
        "aat:300387210"
    ]
},
  "bbox": [],
  "geometry": {"coordinates":[-81.95,29.2167],"type":"Point"}
}