{
  "id": 2753535,
  "type": "Feature",
  "properties": {
    "tgn:hierarchy":[
        "tgn:2753535",
        "tgn:1000001",
        "tgn:7012149",
        "tgn:2001868",
        "tgn:7007825",
        "tgn:7029392"
    ],
    "tgn:id":2753535,
    "tgn:name":"Watermelon Island",
    "tgn:placetype":[
        "aat:300386851",
        "aat:300008791"
    ]
},
  "bbox": [],
  "geometry": {"coordinates":[-83.1667,36.3167],"type":"Point"}
}