{
  "id": 2224147,
  "type": "Feature",
  "properties": {
    "tgn:hierarchy":[
        "tgn:2224147",
        "tgn:1000001",
        "tgn:7012149",
        "tgn:1002564",
        "tgn:7007710",
        "tgn:7029392"
    ],
    "tgn:id":2224147,
    "tgn:name":"Cary Mountain",
    "tgn:placetype":[
        "aat:300008798"
    ]
},
  "bbox": [],
  "geometry": {"coordinates":[-75.5667,41.5333],"type":"Point"}
}