{
  "id": 7021762,
  "type": "Feature",
  "properties": {
    "tgn:hierarchy":[
        "tgn:7021762",
        "tgn:1000001",
        "tgn:7012149",
        "tgn:2001758",
        "tgn:7007712",
        "tgn:7029392"
    ],
    "tgn:id":7021762,
    "tgn:name":"Cane Swamp",
    "tgn:placetype":[
        "aat:300008905"
    ]
},
  "bbox": [],
  "geometry": {"coordinates":[-79.4167,33.9333],"type":"Point"}
}