{
  "id": 2425482,
  "type": "Feature",
  "properties": {
    "tgn:hierarchy":[
        "tgn:2425482",
        "tgn:1000001",
        "tgn:7012149",
        "tgn:2001758",
        "tgn:7007712",
        "tgn:7029392"
    ],
    "tgn:id":2425482,
    "tgn:name":"Johnson Swamp",
    "tgn:placetype":[
        "aat:300008905"
    ]
},
  "bbox": [],
  "geometry": {"coordinates":[-79.4833,34.15],"type":"Point"}
}