{
  "id": 2520036,
  "type": "Feature",
  "properties": {
    "tgn:hierarchy":[
        "tgn:2520036",
        "tgn:1000001",
        "tgn:7012149",
        "tgn:2000183",
        "tgn:7007157",
        "tgn:7029392"
    ],
    "tgn:id":2520036,
    "tgn:name":"Mollie Gibson Canyon",
    "tgn:placetype":[
        "aat:300008761"
    ]
},
  "bbox": [],
  "geometry": {"coordinates":[-118.1333,37.35],"type":"Point"}
}