{
  "id": 2354194,
  "type": "Feature",
  "properties": {
    "tgn:hierarchy":[
        "tgn:2354194",
        "tgn:1000001",
        "tgn:1002191",
        "tgn:7012149",
        "tgn:7007826",
        "tgn:7029392"
    ],
    "tgn:id":2354194,
    "tgn:name":"Golden Mountain",
    "tgn:placetype":[
        "aat:300008798"
    ]
},
  "bbox": [],
  "geometry": {"coordinates":[-97.6667,31.8167],"type":"Point"}
}