{
  "id": 2341377,
  "type": "Feature",
  "properties": {
    "tgn:hierarchy":[
        "tgn:2341377",
        "tgn:7002659",
        "tgn:1000001",
        "tgn:7012149",
        "tgn:2000061",
        "tgn:7029392"
    ],
    "tgn:id":2341377,
    "tgn:name":"Frog Eye",
    "tgn:placetype":[
        "aat:300008347"
    ]
},
  "bbox": [],
  "geometry": {"coordinates":[-85.5833,33.0167],"type":"Point"}
}