{
  "id": 7302480,
  "type": "Feature",
  "properties": {
    "tgn:hierarchy":[
        "tgn:7302480",
        "tgn:7002758",
        "tgn:7002821",
        "tgn:1000003",
        "tgn:1000095",
        "tgn:7029392"
    ],
    "tgn:id":7302480,
    "tgn:name":"N\u00edvar",
    "tgn:placetype":[
        "aat:300008347"
    ]
},
  "bbox": [],
  "geometry": {"coordinates":[-3.583333,37.266667],"type":"Point"}
}