{
  "id": 7534273,
  "type": "Feature",
  "properties": {
    "tgn:hierarchy":[
        "tgn:7534273",
        "tgn:7001242",
        "tgn:7016833",
        "tgn:1001113",
        "tgn:7029392"
    ],
    "tgn:id":7534273,
    "tgn:name":"\u1e28aw\u1e11 a\u0163 \u0162arfah",
    "tgn:placetype":[
        "aat:300008347"
    ]
},
  "bbox": [],
  "geometry": {"coordinates":[31.391852,30.618344],"type":"Point"}
}