{
  "id": 2119769,
  "type": "Feature",
  "properties": {
    "tgn:hierarchy":[
        "tgn:2119769",
        "tgn:1000001",
        "tgn:7012149",
        "tgn:2002266",
        "tgn:7013961",
        "tgn:7029392"
    ],
    "tgn:id":2119769,
    "tgn:name":"Rig",
    "tgn:placetype":[
        "aat:300008347"
    ]
},
  "bbox": [],
  "geometry": {"coordinates":[-79.0333,39.0333],"type":"Point"}
}