{
  "id": 2370036,
  "type": "Feature",
  "properties": {
    "tgn:hierarchy":[
        "tgn:2370036",
        "tgn:1000001",
        "tgn:7012149",
        "tgn:2000353",
        "tgn:7007248",
        "tgn:7029392"
    ],
    "tgn:id":2370036,
    "tgn:name":"Guy Branch",
    "tgn:placetype":[
        "aat:300008699"
    ]
},
  "bbox": [],
  "geometry": {"coordinates":[-82.4667,33.3167],"type":"Point"}
}