{
  "id": 2061624,
  "type": "Feature",
  "properties": {
    "tgn:hierarchy":[
        "tgn:2061624",
        "tgn:1000001",
        "tgn:7012149",
        "tgn:2001272",
        "tgn:7007524",
        "tgn:7029392"
    ],
    "tgn:id":2061624,
    "tgn:name":"Plevna",
    "tgn:placetype":[
        "aat:300008347"
    ]
},
  "bbox": [],
  "geometry": {"coordinates":[-104.5167,46.4167],"type":"Point"}
}