{
  "id": 7011891,
  "type": "Feature",
  "properties": {
    "tgn:hierarchy":[
        "tgn:7011891",
        "tgn:7002445",
        "tgn:7008103",
        "tgn:1000003",
        "tgn:7008591",
        "tgn:7029392"
    ],
    "tgn:id":7011891,
    "tgn:name":"Leighton Buzzard",
    "tgn:name:ang":"Lestone",
    "tgn:placetype":[
        "aat:300008347"
    ]
},
  "bbox": [],
  "geometry": {"coordinates":[-0.65,51.916667],"type":"Point"}
}