{
  "id": 2642797,
  "type": "Feature",
  "properties": {
    "tgn:hierarchy":[
        "tgn:2642797",
        "tgn:1000001",
        "tgn:7012149",
        "tgn:2001453",
        "tgn:7007566",
        "tgn:7029392"
    ],
    "tgn:id":2642797,
    "tgn:name":"Sandoval Canyon",
    "tgn:placetype":[
        "aat:300008761"
    ]
},
  "bbox": [],
  "geometry": {"coordinates":[-105.3667,35.7167],"type":"Point"}
}