{
  "id": 7163199,
  "type": "Feature",
  "properties": {
    "tgn:hierarchy":[
        "tgn:7163199",
        "tgn:7003669",
        "tgn:1000003",
        "tgn:7000084",
        "tgn:7029392"
    ],
    "tgn:id":7163199,
    "tgn:name":"H\u00fchnerbach",
    "tgn:placetype":[
        "aat:300008699"
    ]
},
  "bbox": [],
  "geometry": {"coordinates":[10.733333,47.983333],"type":"Point"}
}