{
  "id": 2312435,
  "type": "Feature",
  "properties": {
    "tgn:hierarchy":[
        "tgn:2312435",
        "tgn:1000001",
        "tgn:7012149",
        "tgn:2000181",
        "tgn:7007157",
        "tgn:7029392"
    ],
    "tgn:id":2312435,
    "tgn:name":"Eightmile Ridge",
    "tgn:placetype":[
        "aat:300266640"
    ]
},
  "bbox": [],
  "geometry": {"coordinates":[-123.55,40.5167],"type":"Point"}
}