{
  "id": 2613459,
  "type": "Feature",
  "properties": {
    "tgn:hierarchy":[
        "tgn:2613459",
        "tgn:1000001",
        "tgn:7012149",
        "tgn:2001516",
        "tgn:7007709",
        "tgn:7029392"
    ],
    "tgn:id":2613459,
    "tgn:name":"Reed Mountain",
    "tgn:placetype":[
        "aat:300008798"
    ]
},
  "bbox": [],
  "geometry": {"coordinates":[-82.55,35.9167],"type":"Point"}
}