{
  "id": 7306674,
  "type": "Feature",
  "properties": {
    "tgn:hierarchy":[
        "tgn:7306674",
        "tgn:7002759",
        "tgn:7002843",
        "tgn:1000003",
        "tgn:1000095",
        "tgn:7029392"
    ],
    "tgn:id":7306674,
    "tgn:name":"Mases y Tamboril",
    "tgn:placetype":[
        "aat:300008347"
    ]
},
  "bbox": [],
  "geometry": {"coordinates":[-0.666667,40.066667],"type":"Point"}
}