{
  "id": 2754719,
  "type": "Feature",
  "properties": {
    "tgn:hierarchy":[
        "tgn:2754719",
        "tgn:7006450",
        "tgn:1000001",
        "tgn:7012149",
        "tgn:2000082",
        "tgn:7029392"
    ],
    "tgn:id":2754719,
    "tgn:name":"Weasel Cove",
    "tgn:placetype":[
        "aat:300132316"
    ]
},
  "bbox": [],
  "geometry": {"coordinates":[-130.8167,55.15],"type":"Point"}
}