{
  "id": 7224455,
  "type": "Feature",
  "properties": {
    "tgn:hierarchy":[
        "tgn:7224455",
        "tgn:7002692",
        "tgn:7012056",
        "tgn:1000003",
        "tgn:1000074",
        "tgn:7029392"
    ],
    "tgn:id":7224455,
    "tgn:name":"Pin\u00e1kl, Vr\u00e1choi",
    "tgn:placetype":[
        "aat:300011692"
    ]
},
  "bbox": [],
  "geometry": {"coordinates":[26.2875,35.316111],"type":"Point"}
}