{
  "id": 2669657,
  "type": "Feature",
  "properties": {
    "tgn:hierarchy":[
        "tgn:2669657",
        "tgn:1000001",
        "tgn:7012149",
        "tgn:2001706",
        "tgn:7007708",
        "tgn:7029392"
    ],
    "tgn:id":2669657,
    "tgn:name":"Slideout Creek",
    "tgn:placetype":[
        "aat:300008706"
    ]
},
  "bbox": [],
  "geometry": {"coordinates":[-123.5667,43.7833],"type":"Point"}
}