{
  "id": 7492995,
  "type": "Feature",
  "properties": {
    "tgn:hierarchy":[
        "tgn:7492995",
        "tgn:1000004",
        "tgn:7489179",
        "tgn:1000141",
        "tgn:7029392"
    ],
    "tgn:id":7492995,
    "tgn:name":"Longtan Hu",
    "tgn:placetype":[
        "aat:300008680"
    ]
},
  "bbox": [],
  "geometry": {"coordinates":[121.740506,24.795218],"type":"Point"}
}