<<<<<<< HEAD
{
  "id": 2338173,
  "type": "Feature",
  "properties": {
    "tgn:hierarchy":[
        "tgn:2338173",
        "tgn:1000001",
        "tgn:7012149",
        "tgn:1002672",
        "tgn:7007922",
        "tgn:7029392"
    ],
    "tgn:id":2338173,
    "tgn:name":"Fox Point",
    "tgn:placetype":[
        "aat:300008850"
    ]
},
  "bbox": [],
  "geometry": {"coordinates":[-87.8667,43.1667],"type":"Point"}
}
=======
{"geometry":{"type":"Point","coordinates":[-87.866700,43.166700]},"type":"Feature","properties":{"hierarchy":["tgn:2338173","tgn:1000001","tgn:7012149","tgn:1002672","tgn:7007922","tgn:7029392"],"placetype":["aat:300008850"],"id":2338173,"name:xx":"Fox Point"}}
>>>>>>> 03f74aca74312dbeaf24d7e61306dd6a786dc3d0
