{
  "id": 2338173,
  "type": "Feature",
  "properties": {
    "tgn:hierarchy":[
        "tgn:2338173",
        "tgn:1000001",
        "tgn:7012149",
        "tgn:1002672",
        "tgn:7007922",
        "tgn:7029392"
    ],
    "tgn:id":2338173,
    "tgn:name":"Fox Point",
    "tgn:placetype":[
        "aat:300008850"
    ]
},
  "bbox": [],
  "geometry": {"coordinates":[-87.8667,43.1667],"type":"Point"}
}