{
  "id": 7495581,
  "type": "Feature",
  "properties": {
    "tgn:hierarchy":[
        "tgn:7495581",
        "tgn:7487020",
        "tgn:1000004",
        "tgn:1000141",
        "tgn:7029392"
    ],
    "tgn:id":7495581,
    "tgn:name":"Shuanglian Qiao",
    "tgn:placetype":[
        "aat:300007836"
    ]
},
  "bbox": [],
  "geometry": {"coordinates":[120.85162,24.339207],"type":"Point"}
}