{
  "id": 7320679,
  "type": "Feature",
  "properties": {
    "tgn:hierarchy":[
        "tgn:7320679",
        "tgn:7002464",
        "tgn:1000049",
        "tgn:1000002",
        "tgn:7029392"
    ],
    "tgn:id":7320679,
    "tgn:name":"Ba\u00f1os de Chismisa",
    "tgn:placetype":[
        "aat:300008347"
    ]
},
  "bbox": [],
  "geometry": {"coordinates":[-69.283333,-19.516667],"type":"Point"}
}