{
  "id": 2388344,
  "type": "Feature",
  "properties": {
    "tgn:hierarchy":[
        "tgn:2388344",
        "tgn:7002659",
        "tgn:1000001",
        "tgn:7012149",
        "tgn:2000064",
        "tgn:7029392"
    ],
    "tgn:id":2388344,
    "tgn:name":"Hickory Ridge",
    "tgn:placetype":[
        "aat:300266640"
    ]
},
  "bbox": [],
  "geometry": {"coordinates":[-87.95,31.3833],"type":"Point"}
}