{
  "id": 7185548,
  "type": "Feature",
  "properties": {
    "tgn:hierarchy":[
        "tgn:7185548",
        "tgn:1000003",
        "tgn:7000094",
        "tgn:7000084",
        "tgn:7029392"
    ],
    "tgn:id":7185548,
    "tgn:name":"Grambzow",
    "tgn:placetype":[
        "aat:300008347"
    ]
},
  "bbox": [],
  "geometry": {"coordinates":[12.566667,53.733333],"type":"Point"}
}