{
  "id": 2602459,
  "type": "Feature",
  "properties": {
    "tgn:hierarchy":[
        "tgn:2602459",
        "tgn:1000001",
        "tgn:7006451",
        "tgn:7012149",
        "tgn:2000098",
        "tgn:7029392"
    ],
    "tgn:id":2602459,
    "tgn:name":"Pyramid Rock",
    "tgn:placetype":[
        "aat:300008791"
    ]
},
  "bbox": [],
  "geometry": {"coordinates":[-113.5667,35.2167],"type":"Point"}
}