{
  "id": 2043555,
  "type": "Feature",
  "properties": {
    "tgn:hierarchy":[
        "tgn:2043555",
        "tgn:1000001",
        "tgn:2000859",
        "tgn:7012149",
        "tgn:7007256",
        "tgn:7029392"
    ],
    "tgn:id":2043555,
    "tgn:name":"Neale",
    "tgn:placetype":[
        "aat:300387016"
    ]
},
  "bbox": [],
  "geometry": {"coordinates":[-93.45,30.7667],"type":"Point"}
}