{
  "id": 2481866,
  "type": "Feature",
  "properties": {
    "tgn:hierarchy":[
        "tgn:2481866",
        "tgn:1000001",
        "tgn:7012149",
        "tgn:2000368",
        "tgn:7007248",
        "tgn:7029392"
    ],
    "tgn:id":2481866,
    "tgn:name":"Lands Crossroads",
    "tgn:placetype":[
        "aat:300008347"
    ]
},
  "bbox": [],
  "geometry": {"coordinates":[-83.3833,31.7167],"type":"Point"}
}