{
  "id": 2338120,
  "type": "Feature",
  "properties": {
    "tgn:hierarchy":[
        "tgn:2338120",
        "tgn:1000001",
        "tgn:7012149",
        "tgn:7007157",
        "tgn:2000184",
        "tgn:7029392"
    ],
    "tgn:id":2338120,
    "tgn:name":"Fox Mountain",
    "tgn:placetype":[
        "aat:300008798"
    ]
},
  "bbox": [],
  "geometry": {"coordinates":[-120.8667,40.55],"type":"Point"}
}