<<<<<<< HEAD
{
  "id": 2338120,
  "type": "Feature",
  "properties": {
    "tgn:hierarchy":[
        "tgn:2338120",
        "tgn:1000001",
        "tgn:7012149",
        "tgn:7007157",
        "tgn:2000184",
        "tgn:7029392"
    ],
    "tgn:id":2338120,
    "tgn:name":"Fox Mountain",
    "tgn:placetype":[
        "aat:300008798"
    ]
},
  "bbox": [],
  "geometry": {"coordinates":[-120.8667,40.55],"type":"Point"}
}
=======
{"geometry":{"type":"Point","coordinates":[-120.866700,40.550000]},"type":"Feature","properties":{"hierarchy":["tgn:2338120","tgn:1000001","tgn:7012149","tgn:7007157","tgn:2000184","tgn:7029392"],"placetype":["aat:300008798"],"id":2338120,"name:xx":"Fox Mountain"}}
>>>>>>> 03f74aca74312dbeaf24d7e61306dd6a786dc3d0
