{
  "id": 2311298,
  "type": "Feature",
  "properties": {
    "tgn:hierarchy":[
        "tgn:2311298",
        "tgn:1000001",
        "tgn:7012149",
        "tgn:1002694",
        "tgn:7007252",
        "tgn:7029392"
    ],
    "tgn:id":2311298,
    "tgn:name":"Edgewood, Lake",
    "tgn:placetype":[
        "aat:300006191"
    ]
},
  "bbox": [],
  "geometry": {"coordinates":[-86.4333,39.4333],"type":"Point"}
}