{
  "id": 7273904,
  "type": "Feature",
  "properties": {
    "tgn:concordances":{
        "gn:id":"2744954"
    },
    "tgn:hierarchy":[
        "tgn:7273904",
        "tgn:1000003",
        "tgn:7003624",
        "tgn:7016845",
        "tgn:7029392"
    ],
    "tgn:id":7273904,
    "tgn:name:nl":"Waterstraat",
    "tgn:placetype":[
        "aat:300008347"
    ]
},
  "bbox": [],
  "geometry": {"coordinates":[5.166667,51.466667],"type":"Point"}
}