{
  "id": 2180994,
  "type": "Feature",
  "properties": {
    "tgn:hierarchy":[
        "tgn:2180994",
        "tgn:1000001",
        "tgn:7012149",
        "tgn:2001721",
        "tgn:7007708",
        "tgn:7029392"
    ],
    "tgn:id":2180994,
    "tgn:name":"Bluch Creek",
    "tgn:placetype":[
        "aat:300008706"
    ]
},
  "bbox": [],
  "geometry": {"coordinates":[-117.6833,45.3833],"type":"Point"}
}