{
  "id": 2701277,
  "type": "Feature",
  "properties": {
    "tgn:hierarchy":[
        "tgn:2701277",
        "tgn:1000001",
        "tgn:1002340",
        "tgn:7012149",
        "tgn:7007526",
        "tgn:7029392"
    ],
    "tgn:id":2701277,
    "tgn:name":"Sugar Loaf",
    "tgn:placetype":[
        "aat:300008798"
    ]
},
  "bbox": [],
  "geometry": {"coordinates":[-119.5333,38.8333],"type":"Point"}
}