{
  "id": 7501911,
  "type": "Feature",
  "properties": {
    "tgn:hierarchy":[
        "tgn:7501911",
        "tgn:7488858",
        "tgn:1000004",
        "tgn:1000141",
        "tgn:7029392"
    ],
    "tgn:id":7501911,
    "tgn:name":"Xiazhuang",
    "tgn:placetype":[
        "aat:300008347"
    ]
},
  "bbox": [],
  "geometry": {"coordinates":[120.906836,24.056745],"type":"Point"}
}