{
  "id": 7477697,
  "type": "Feature",
  "properties": {
    "tgn:hierarchy":[
        "tgn:7477697",
        "tgn:1000004",
        "tgn:7004300",
        "tgn:1000141",
        "tgn:7029392"
    ],
    "tgn:id":7477697,
    "tgn:name":"Beiji Dian",
    "tgn:placetype":[
        "aat:300007595"
    ]
},
  "bbox": [],
  "geometry": {"coordinates":[119.678678,23.581001],"type":"Point"}
}