{
  "id": 2314326,
  "type": "Feature",
  "properties": {
    "tgn:hierarchy":[
        "tgn:2314326",
        "tgn:1000001",
        "tgn:7012149",
        "tgn:7029392"
    ],
    "tgn:id":2314326,
    "tgn:name":"Elk Fork",
    "tgn:placetype":[
        "aat:300008699"
    ]
},
  "bbox": [],
  "geometry": {"coordinates":[-87.2167,36.85],"type":"Point"}
}