{
  "id": 1069976,
  "type": "Feature",
  "properties": {
    "tgn:hierarchy":[
        "tgn:1069976",
        "tgn:1000004",
        "tgn:7002081",
        "tgn:1000111",
        "tgn:7029392"
    ],
    "tgn:id":1069976,
    "tgn:name":"Lujiadu",
    "tgn:placetype":[
        "aat:300008347"
    ]
},
  "bbox": [],
  "geometry": {"coordinates":[120.55,32.25],"type":"Point"}
}