{
  "id": 2229478,
  "type": "Feature",
  "properties": {
    "tgn:hierarchy":[
        "tgn:2229478",
        "tgn:1000001",
        "tgn:7012149",
        "tgn:2001453",
        "tgn:7007566",
        "tgn:7029392"
    ],
    "tgn:id":2229478,
    "tgn:name":"Cedar Point",
    "tgn:placetype":[
        "aat:300008850"
    ]
},
  "bbox": [],
  "geometry": {"coordinates":[-104.2333,35.4667],"type":"Point"}
}