{
  "id": 7307544,
  "type": "Feature",
  "properties": {
    "tgn:hierarchy":[
        "tgn:7307544",
        "tgn:7002758",
        "tgn:7002823",
        "tgn:1000003",
        "tgn:1000095",
        "tgn:7029392"
    ],
    "tgn:id":7307544,
    "tgn:name":"M\u00e1rmol, Cumbre del",
    "tgn:placetype":[
        "aat:300008798"
    ]
},
  "bbox": [],
  "geometry": {"coordinates":[-7.05,37.85],"type":"Point"}
}