{
  "id": 1020979,
  "type": "Feature",
  "properties": {
    "tgn:hierarchy":[
        "tgn:1020979",
        "tgn:7006247",
        "tgn:1000047",
        "tgn:7002456",
        "tgn:1000002",
        "tgn:7029392"
    ],
    "tgn:id":1020979,
    "tgn:name":"Cairari",
    "tgn:placetype":[
        "aat:300008347"
    ]
},
  "bbox": [],
  "geometry": {"coordinates":[-49.0833,-2.5167],"type":"Point"}
}