{
  "id": 7333270,
  "type": "Feature",
  "properties": {
    "tgn:hierarchy":[
        "tgn:7333270",
        "tgn:7002806",
        "tgn:7001158",
        "tgn:1000003",
        "tgn:1000095",
        "tgn:7029392"
    ],
    "tgn:id":7333270,
    "tgn:name":"Garganta de los Hornos",
    "tgn:placetype":[
        "aat:300008347"
    ]
},
  "bbox": [],
  "geometry": {"coordinates":[-5.166667,40.483333],"type":"Point"}
}