{
  "id": 7137394,
  "type": "Feature",
  "properties": {
    "tgn:hierarchy":[
        "tgn:7137394",
        "tgn:7003669",
        "tgn:1000003",
        "tgn:7000084",
        "tgn:7029392"
    ],
    "tgn:id":7137394,
    "tgn:name":"Lanzing",
    "tgn:placetype":[
        "aat:300008347"
    ]
},
  "bbox": [],
  "geometry": {"coordinates":[12.733333,48.066667],"type":"Point"}
}