{
  "id": 7471785,
  "type": "Feature",
  "properties": {
    "tgn:hierarchy":[
        "tgn:7471785",
        "tgn:1000004",
        "tgn:7001014",
        "tgn:1000141",
        "tgn:7029392"
    ],
    "tgn:id":7471785,
    "tgn:name":"Xinxucuoliao",
    "tgn:placetype":[
        "aat:300008347"
    ]
},
  "bbox": [],
  "geometry": {"coordinates":[120.242778,23.704167],"type":"Point"}
}