{
  "id": 7505786,
  "type": "Feature",
  "properties": {
    "tgn:hierarchy":[
        "tgn:7505786",
        "tgn:1009227",
        "tgn:1000226",
        "tgn:7016822",
        "tgn:1000006",
        "tgn:7029392"
    ],
    "tgn:id":7505786,
    "tgn:name:en":"Tomoporakau Creek",
    "tgn:placetype":[
        "aat:300008699"
    ]
},
  "bbox": [],
  "geometry": {"coordinates":[168.283333,-46.35],"type":"Point"}
}