{
  "id": 2239683,
  "type": "Feature",
  "properties": {
    "tgn:hierarchy":[
        "tgn:2239683",
        "tgn:1000001",
        "tgn:2000923",
        "tgn:7012149",
        "tgn:7007515",
        "tgn:7029392"
    ],
    "tgn:id":2239683,
    "tgn:name":"Chute Island",
    "tgn:placetype":[
        "aat:300008791"
    ]
},
  "bbox": [],
  "geometry": {"coordinates":[-69.8333,44.55],"type":"Point"}
}