{
  "id": 2636662,
  "type": "Feature",
  "properties": {
    "tgn:hierarchy":[
        "tgn:2636662",
        "tgn:2001726",
        "tgn:1000001",
        "tgn:7012149",
        "tgn:7007712",
        "tgn:7029392"
    ],
    "tgn:id":2636662,
    "tgn:name":"Sage Mill Branch",
    "tgn:placetype":[
        "aat:300008699"
    ]
},
  "bbox": [],
  "geometry": {"coordinates":[-81.8333,33.6333],"type":"Point"}
}