{
  "id": 7354353,
  "type": "Feature",
  "properties": {
    "tgn:hierarchy":[
        "tgn:7354353",
        "tgn:7005578",
        "tgn:1000001",
        "tgn:7005560",
        "tgn:7029392"
    ],
    "tgn:id":7354353,
    "tgn:name":"Chulbac",
    "tgn:placetype":[
        "aat:300008347"
    ]
},
  "bbox": [],
  "geometry": {"coordinates":[-90.566667,19.733333],"type":"Point"}
}