{
  "id": 7462137,
  "type": "Feature",
  "properties": {
    "tgn:hierarchy":[
        "tgn:7462137",
        "tgn:7019049",
        "tgn:7002445",
        "tgn:1000003",
        "tgn:7029505",
        "tgn:7008591",
        "tgn:7029392"
    ],
    "tgn:id":7462137,
    "tgn:name:en":"Kiveton Park",
    "tgn:placetype":[
        "aat:300008347"
    ]
},
  "bbox": [],
  "geometry": {"coordinates":[-1.25,53.333333],"type":"Point"}
}