{
  "id": 7235897,
  "type": "Feature",
  "properties": {
    "tgn:hierarchy":[
        "tgn:7235897",
        "tgn:7002721",
        "tgn:7002715",
        "tgn:1000003",
        "tgn:1000074",
        "tgn:7029392"
    ],
    "tgn:id":7235897,
    "tgn:name":"\u00c1gios Ge\u00f3rgios",
    "tgn:placetype":[
        "aat:300008347"
    ]
},
  "bbox": [],
  "geometry": {"coordinates":[21.757222,39.868056],"type":"Point"}
}