{
  "id": 7417967,
  "type": "Feature",
  "properties": {
    "tgn:hierarchy":[
        "tgn:7417967",
        "tgn:1000001",
        "tgn:7005591",
        "tgn:7005560",
        "tgn:7029392"
    ],
    "tgn:id":7417967,
    "tgn:name:es":"Guadalupe Copaltepec",
    "tgn:placetype":[
        "aat:300008347"
    ]
},
  "bbox": [],
  "geometry": {"coordinates":[-98.170278,17.865],"type":"Point"}
}