{
  "id": 7586047,
  "type": "Feature",
  "properties": {
    "tgn:hierarchy":[
        "tgn:7586047",
        "tgn:1000004",
        "tgn:7000198",
        "tgn:7000799",
        "tgn:7029392"
    ],
    "tgn:id":7586047,
    "tgn:name:en":"Gund Kohor",
    "tgn:placetype":[
        "aat:300008347"
    ]
},
  "bbox": [],
  "geometry": {"coordinates":[74.300229,34.386819],"type":"Point"}
}