{
  "id": 2385776,
  "type": "Feature",
  "properties": {
    "tgn:hierarchy":[
        "tgn:2385776",
        "tgn:7006450",
        "tgn:1000001",
        "tgn:7012149",
        "tgn:2000086",
        "tgn:7029392"
    ],
    "tgn:id":2385776,
    "tgn:name":"Heney Range",
    "tgn:placetype":[
        "aat:300266640"
    ]
},
  "bbox": [],
  "geometry": {"coordinates":[-145.75,60.4833],"type":"Point"}
}