{
  "id": 7496271,
  "type": "Feature",
  "properties": {
    "tgn:hierarchy":[
        "tgn:7496271",
        "tgn:1000004",
        "tgn:7001013",
        "tgn:1000141",
        "tgn:7029392"
    ],
    "tgn:id":7496271,
    "tgn:name":"Daqin",
    "tgn:placetype":[
        "aat:300387033"
    ]
},
  "bbox": [],
  "geometry": {"coordinates":[121.287522,24.946844],"type":"Point"}
}