{
  "id": 7061570,
  "type": "Feature",
  "properties": {
    "tgn:hierarchy":[
        "tgn:7061570",
        "tgn:7000096",
        "tgn:1000003",
        "tgn:7000084",
        "tgn:7029392"
    ],
    "tgn:id":7061570,
    "tgn:name":"Auf dem Pirower Felde",
    "tgn:placetype":[
        "aat:300000206"
    ]
},
  "bbox": [],
  "geometry": {"coordinates":[11.95,53.233333],"type":"Point"}
}