{
  "id": 7423422,
  "type": "Feature",
  "properties": {
    "tgn:hierarchy":[
        "tgn:7423422",
        "tgn:1000001",
        "tgn:1001960",
        "tgn:7005560",
        "tgn:7029392"
    ],
    "tgn:id":7423422,
    "tgn:name":"Aquiles Serd\u00e1n",
    "tgn:placetype":[
        "aat:300008347"
    ]
},
  "bbox": [],
  "geometry": {"coordinates":[-114.3175,32.337778],"type":"Point"}
}