{
  "id": 7392622,
  "type": "Feature",
  "properties": {
    "tgn:hierarchy":[
        "tgn:7392622",
        "tgn:1000001",
        "tgn:7005600",
        "tgn:7005560",
        "tgn:7029392"
    ],
    "tgn:id":7392622,
    "tgn:name":"Sacnict\u00e9",
    "tgn:placetype":[
        "aat:300008347"
    ]
},
  "bbox": [],
  "geometry": {"coordinates":[-88.983333,20.966667],"type":"Point"}
}