<<<<<<< HEAD
{
  "id": 2768908,
  "type": "Feature",
  "properties": {
    "tgn:hierarchy":[
        "tgn:2768908",
        "tgn:1000001",
        "tgn:2001338",
        "tgn:7012149",
        "tgn:7007525",
        "tgn:7029392"
    ],
    "tgn:id":2768908,
    "tgn:name":"Whitney Lake",
    "tgn:placetype":[
        "aat:300008680"
    ]
},
  "bbox": [],
  "geometry": {"coordinates":[-103.3,42.7833],"type":"Point"}
}
=======
{"geometry":{"type":"Point","coordinates":[-103.300000,42.783300]},"type":"Feature","properties":{"hierarchy":["tgn:2768908","tgn:1000001","tgn:2001338","tgn:7012149","tgn:7007525","tgn:7029392"],"placetype":["aat:300008680"],"id":2768908,"name:xx":"Whitney Lake"}}
>>>>>>> 03f74aca74312dbeaf24d7e61306dd6a786dc3d0
