{
  "id": 7255415,
  "type": "Feature",
  "properties": {
    "tgn:hierarchy":[
        "tgn:7255415",
        "tgn:7003456",
        "tgn:1000003",
        "tgn:1000063",
        "tgn:7018236",
        "tgn:7029392"
    ],
    "tgn:id":7255415,
    "tgn:name":"Rodeberg",
    "tgn:placetype":[
        "aat:300008347"
    ]
},
  "bbox": [],
  "geometry": {"coordinates":[4.95,51.016667],"type":"Point"}
}