{
  "id": 7330661,
  "type": "Feature",
  "properties": {
    "tgn:hierarchy":[
        "tgn:7330661",
        "tgn:7002758",
        "tgn:7002841",
        "tgn:1000003",
        "tgn:1000095",
        "tgn:7029392"
    ],
    "tgn:id":7330661,
    "tgn:name":"Guadairilla, Arroyo de",
    "tgn:placetype":[
        "aat:300008699"
    ]
},
  "bbox": [],
  "geometry": {"coordinates":[-5.816667,37.316667],"type":"Point"}
}