{
  "id": 2351111,
  "type": "Feature",
  "properties": {
    "tgn:hierarchy":[
        "tgn:2351111",
        "tgn:1000001",
        "tgn:7012149",
        "tgn:1003008",
        "tgn:7007710",
        "tgn:7029392"
    ],
    "tgn:id":2351111,
    "tgn:name":"Glass Pond Number Two",
    "tgn:placetype":[
        "aat:300006191"
    ]
},
  "bbox": [],
  "geometry": {"coordinates":[-75.3167,41.6167],"type":"Point"}
}