{
  "id": 7585651,
  "type": "Feature",
  "properties": {
    "tgn:hierarchy":[
        "tgn:7585651",
        "tgn:1000004",
        "tgn:7000198",
        "tgn:1001977",
        "tgn:7029392"
    ],
    "tgn:id":7585651,
    "tgn:name:en":"Ganga S\u0101gar Kh\u0101l",
    "tgn:placetype":[
        "aat:300387084"
    ]
},
  "bbox": [],
  "geometry": {"coordinates":[88.091111,21.63],"type":"Point"}
}