{
  "id": 7473312,
  "type": "Feature",
  "properties": {
    "tgn:hierarchy":[
        "tgn:7473312",
        "tgn:1000004",
        "tgn:1000454",
        "tgn:1000141",
        "tgn:7029392"
    ],
    "tgn:id":7473312,
    "tgn:name":"Zhongxingkeng",
    "tgn:placetype":[
        "aat:300008347"
    ]
},
  "bbox": [],
  "geometry": {"coordinates":[121.553719,24.93367],"type":"Point"}
}