{
  "id": 2683258,
  "type": "Feature",
  "properties": {
    "tgn:hierarchy":[
        "tgn:2683258",
        "tgn:7002659",
        "tgn:1000001",
        "tgn:7012149",
        "tgn:2000034",
        "tgn:7029392"
    ],
    "tgn:id":2683258,
    "tgn:name":"Spann Ponds",
    "tgn:placetype":[
        "aat:300006191"
    ]
},
  "bbox": [],
  "geometry": {"coordinates":[-85.4667,31.2167],"type":"Point"}
}