{
  "id": 7050978,
  "type": "Feature",
  "properties": {
    "tgn:hierarchy":[
        "tgn:7050978",
        "tgn:7003137",
        "tgn:1000003",
        "tgn:7003080",
        "tgn:1000080",
        "tgn:7029392"
    ],
    "tgn:id":7050978,
    "tgn:name":"Lalombo, Monte",
    "tgn:placetype":[
        "aat:300008795"
    ]
},
  "bbox": [],
  "geometry": {"coordinates":[13.15,42.316667],"type":"Point"}
}