<<<<<<< HEAD
{
  "id": 7351345,
  "type": "Feature",
  "properties": {
    "tgn:hierarchy":[
        "tgn:7351345",
        "tgn:1000001",
        "tgn:7005601",
        "tgn:7005560",
        "tgn:7029392"
    ],
    "tgn:id":7351345,
    "tgn:name":"Arenal, R\u00edo del",
    "tgn:placetype":[
        "aat:300008699"
    ]
},
  "bbox": [],
  "geometry": {"coordinates":[-103.1,22.916667],"type":"Point"}
}
=======
{"geometry":{"type":"Point","coordinates":[-103.100000,22.916667]},"type":"Feature","properties":{"hierarchy":["tgn:7351345","tgn:1000001","tgn:7005601","tgn:7005560","tgn:7029392"],"placetype":["aat:300008699"],"id":7351345,"name:xx":"Arenal, R\u00edo del"}}
>>>>>>> 03f74aca74312dbeaf24d7e61306dd6a786dc3d0
