{
  "id": 7247230,
  "type": "Feature",
  "properties": {
    "tgn:hierarchy":[
        "tgn:7247230",
        "tgn:7003457",
        "tgn:1000003",
        "tgn:1000063",
        "tgn:7018236",
        "tgn:7029392"
    ],
    "tgn:id":7247230,
    "tgn:name":"Driehoek",
    "tgn:placetype":[
        "aat:300008347"
    ]
},
  "bbox": [],
  "geometry": {"coordinates":[3.983333,50.883333],"type":"Point"}
}