{
  "id": 2379305,
  "type": "Feature",
  "properties": {
    "tgn:hierarchy":[
        "tgn:2379305",
        "tgn:1000001",
        "tgn:7016172",
        "tgn:7012149",
        "tgn:2000127",
        "tgn:7029392"
    ],
    "tgn:id":2379305,
    "tgn:name":"Harve Creek",
    "tgn:placetype":[
        "aat:300008706"
    ]
},
  "bbox": [],
  "geometry": {"coordinates":[-92.25,35.1167],"type":"Point"}
}