{
  "id": 7276722,
  "type": "Feature",
  "properties": {
    "tgn:hierarchy":[
        "tgn:7276722",
        "tgn:1001637",
        "tgn:1000049",
        "tgn:1000002",
        "tgn:7029392"
    ],
    "tgn:id":7276722,
    "tgn:name":"Villagr\u00e1n, Estero",
    "tgn:placetype":[
        "aat:300008699"
    ]
},
  "bbox": [],
  "geometry": {"coordinates":[-71.666667,-37.133333],"type":"Point"}
}