{
  "id": 7462916,
  "type": "Feature",
  "properties": {
    "tgn:hierarchy":[
        "tgn:7462916",
        "tgn:7002445",
        "tgn:1000003",
        "tgn:7008145",
        "tgn:7008591",
        "tgn:7029392"
    ],
    "tgn:id":7462916,
    "tgn:name:en":"Ickleford",
    "tgn:placetype":[
        "aat:300008347"
    ]
},
  "bbox": [],
  "geometry": {"coordinates":[-0.266667,51.966667],"type":"Point"}
}