{
  "id": 7401643,
  "type": "Feature",
  "properties": {
    "tgn:hierarchy":[
        "tgn:7401643",
        "tgn:1000001",
        "tgn:7005599",
        "tgn:7005560",
        "tgn:7029392"
    ],
    "tgn:id":7401643,
    "tgn:name":"Benito Ju\u00e1rez",
    "tgn:placetype":[
        "aat:300008347"
    ]
},
  "bbox": [],
  "geometry": {"coordinates":[-94.918056,18.248611],"type":"Point"}
}