{
  "id": 1070574,
  "type": "Feature",
  "properties": {
    "tgn:hierarchy":[
        "tgn:1070574",
        "tgn:1000004",
        "tgn:7005232",
        "tgn:1008286",
        "tgn:1000111",
        "tgn:7029392"
    ],
    "tgn:id":1070574,
    "tgn:name":"Nan'ao Dao",
    "tgn:placetype":[
        "aat:300008347"
    ]
},
  "bbox": [],
  "geometry": {"coordinates":[117.0333,23.45],"type":"Point"}
}