{
  "id": 7501323,
  "type": "Feature",
  "properties": {
    "tgn:hierarchy":[
        "tgn:7501323",
        "tgn:7001004",
        "tgn:1000004",
        "tgn:1000141",
        "tgn:7029392"
    ],
    "tgn:id":7501323,
    "tgn:name":"Qianfeng Guoxiao",
    "tgn:placetype":[
        "aat:300006495"
    ]
},
  "bbox": [],
  "geometry": {"coordinates":[120.282222,22.792222],"type":"Point"}
}