{
  "id": 2008869,
  "type": "Feature",
  "properties": {
    "tgn:hierarchy":[
        "tgn:2008869",
        "tgn:1000001",
        "tgn:7016172",
        "tgn:2000120",
        "tgn:7012149",
        "tgn:7029392"
    ],
    "tgn:id":2008869,
    "tgn:name":"Mangrum",
    "tgn:placetype":[
        "aat:300008347",
        "aat:300387210"
    ]
},
  "bbox": [],
  "geometry": {"coordinates":[-90.35,35.7833],"type":"Point"}
}