{
  "id": 7497484,
  "type": "Feature",
  "properties": {
    "tgn:hierarchy":[
        "tgn:7497484",
        "tgn:7001004",
        "tgn:1000004",
        "tgn:1000141",
        "tgn:7029392"
    ],
    "tgn:id":7497484,
    "tgn:name":"Zhongsheshijia",
    "tgn:placetype":[
        "aat:300000745"
    ]
},
  "bbox": [],
  "geometry": {"coordinates":[120.316775,22.601238],"type":"Point"}
}