{
  "id": 2430626,
  "type": "Feature",
  "properties": {
    "tgn:hierarchy":[
        "tgn:2430626",
        "tgn:1007657",
        "tgn:1002534",
        "tgn:1000001",
        "tgn:7012149",
        "tgn:7007249",
        "tgn:7029392"
    ],
    "tgn:id":2430626,
    "tgn:name":"Kalihiwai Reservoir",
    "tgn:placetype":[
        "aat:300006191"
    ]
},
  "bbox": [],
  "geometry": {"coordinates":[-159.4333,22.1833],"type":"Point"}
}