<<<<<<< HEAD
{
  "id": 7178133,
  "type": "Feature",
  "properties": {
    "tgn:hierarchy":[
        "tgn:7178133",
        "tgn:7003669",
        "tgn:1000003",
        "tgn:7000084",
        "tgn:7029392"
    ],
    "tgn:id":7178133,
    "tgn:name":"Gundh\u00f6ring",
    "tgn:placetype":[
        "aat:300008347"
    ]
},
  "bbox": [],
  "geometry": {"coordinates":[12.516667,48.816667],"type":"Point"}
}
=======
{"geometry":{"type":"Point","coordinates":[12.516667,48.816667]},"type":"Feature","properties":{"hierarchy":["tgn:7178133","tgn:7003669","tgn:1000003","tgn:7000084","tgn:7029392"],"placetype":["aat:300008347"],"id":7178133,"name:xx":"Gundh\u00f6ring"}}
>>>>>>> 03f74aca74312dbeaf24d7e61306dd6a786dc3d0
