{
  "id": 1127942,
  "type": "Feature",
  "properties": {
    "tgn:hierarchy":[
        "tgn:1127942",
        "tgn:7001242",
        "tgn:7029392"
    ],
    "tgn:id":1127942,
    "tgn:name":"Ntem",
    "tgn:placetype":[
        "aat:300008707"
    ]
},
  "bbox": [],
  "geometry": {"coordinates":[9.75,2.25],"type":"Point"}
}