{
  "id": 7334207,
  "type": "Feature",
  "properties": {
    "tgn:hierarchy":[
        "tgn:7334207",
        "tgn:7002805",
        "tgn:7002758",
        "tgn:1000003",
        "tgn:1000095",
        "tgn:7029392"
    ],
    "tgn:id":7334207,
    "tgn:name":"El Llano de los Olleres",
    "tgn:placetype":[
        "aat:300008347"
    ]
},
  "bbox": [],
  "geometry": {"coordinates":[-2.166667,37.416667],"type":"Point"}
}