{
  "id": 7124544,
  "type": "Feature",
  "properties": {
    "tgn:hierarchy":[
        "tgn:7124544",
        "tgn:1000003",
        "tgn:7003677",
        "tgn:7000084",
        "tgn:7029392"
    ],
    "tgn:id":7124544,
    "tgn:name":"Niederdrees",
    "tgn:placetype":[
        "aat:300008347"
    ]
},
  "bbox": [],
  "geometry": {"coordinates":[6.916667,50.65],"type":"Point"}
}