{
  "id": 7292343,
  "type": "Feature",
  "properties": {
    "tgn:hierarchy":[
        "tgn:7292343",
        "tgn:1001699",
        "tgn:1000049",
        "tgn:1000002",
        "tgn:7029392"
    ],
    "tgn:id":7292343,
    "tgn:name":"El Trap\u00e9n",
    "tgn:placetype":[
        "aat:300000206"
    ]
},
  "bbox": [],
  "geometry": {"coordinates":[-73.05,-41.416667],"type":"Point"}
}