<<<<<<< HEAD
{
  "id": 7117359,
  "type": "Feature",
  "properties": {
    "tgn:hierarchy":[
        "tgn:7117359",
        "tgn:1000003",
        "tgn:7003682",
        "tgn:7000084",
        "tgn:7029392"
    ],
    "tgn:id":7117359,
    "tgn:name":"Oppertshausen",
    "tgn:placetype":[
        "aat:300008347"
    ]
},
  "bbox": [],
  "geometry": {"coordinates":[7.466667,49.95],"type":"Point"}
}
=======
{"geometry":{"type":"Point","coordinates":[7.466667,49.950000]},"type":"Feature","properties":{"hierarchy":["tgn:7117359","tgn:1000003","tgn:7003682","tgn:7000084","tgn:7029392"],"placetype":["aat:300008347"],"id":7117359,"name:xx":"Oppertshausen"}}
>>>>>>> 03f74aca74312dbeaf24d7e61306dd6a786dc3d0
