{
  "id": 7328114,
  "type": "Feature",
  "properties": {
    "tgn:hierarchy":[
        "tgn:7328114",
        "tgn:7002824",
        "tgn:1000003",
        "tgn:7002786",
        "tgn:1000095",
        "tgn:7029392"
    ],
    "tgn:id":7328114,
    "tgn:name":"Priori\u00f1o Chico, Cabo",
    "tgn:placetype":[
        "aat:300008850"
    ]
},
  "bbox": [],
  "geometry": {"coordinates":[-8.333333,43.466667],"type":"Point"}
}