{
  "id": 7412602,
  "type": "Feature",
  "properties": {
    "tgn:hierarchy":[
        "tgn:7412602",
        "tgn:1000001",
        "tgn:7005598",
        "tgn:7005560",
        "tgn:7029392"
    ],
    "tgn:id":7412602,
    "tgn:name":"Huactzingo",
    "tgn:placetype":[
        "aat:300008347"
    ]
},
  "bbox": [],
  "geometry": {"coordinates":[-98.251389,19.231944],"type":"Point"}
}