{
  "id": 1098568,
  "type": "Feature",
  "properties": {
    "tgn:hierarchy":[
        "tgn:1098568",
        "tgn:7000490",
        "tgn:1000006",
        "tgn:7001829",
        "tgn:7029392"
    ],
    "tgn:id":1098568,
    "tgn:name":"Wonarah",
    "tgn:placetype":[
        "aat:300008347"
    ]
},
  "bbox": [],
  "geometry": {"coordinates":[136.3333,-19.8333],"type":"Point"}
}