{
  "id": 1096869,
  "type": "Feature",
  "properties": {
    "tgn:hierarchy":[
        "tgn:1096869",
        "tgn:7000490",
        "tgn:1000006",
        "tgn:7001830",
        "tgn:7029392"
    ],
    "tgn:id":1096869,
    "tgn:name":"Eton",
    "tgn:placetype":[
        "aat:300008347"
    ]
},
  "bbox": [],
  "geometry": {"coordinates":[148.9667,-21.25],"type":"Point"}
}