{
  "id": 7418112,
  "type": "Feature",
  "properties": {
    "tgn:hierarchy":[
        "tgn:7418112",
        "tgn:1001836",
        "tgn:1000001",
        "tgn:7005560",
        "tgn:7029392"
    ],
    "tgn:id":7418112,
    "tgn:name":"Muleg\u00e9, R\u00edo",
    "tgn:placetype":[
        "aat:300008699"
    ]
},
  "bbox": [],
  "geometry": {"coordinates":[-112.0625,26.8125],"type":"Point"}
}