{
  "id": 7594398,
  "type": "Feature",
  "properties": {
    "tgn:hierarchy":[
        "tgn:7594398",
        "tgn:1000004",
        "tgn:7012215",
        "tgn:7006653",
        "tgn:7029392"
    ],
    "tgn:id":7594398,
    "tgn:name":"Gelati Monastery",
    "tgn:placetype":[
        "aat:300000641"
    ]
},
  "bbox": [],
  "geometry": {"coordinates":[42.7611,42.2972],"type":"Point"}
}