{
  "id": 7436393,
  "type": "Feature",
  "properties": {
    "tgn:hierarchy":[
        "tgn:7436393",
        "tgn:7005581",
        "tgn:1000001",
        "tgn:7005560",
        "tgn:7029392"
    ],
    "tgn:id":7436393,
    "tgn:name":"Terrace\u00f1o",
    "tgn:placetype":[
        "aat:300008697"
    ]
},
  "bbox": [],
  "geometry": {"coordinates":[-108.15,30.416667],"type":"Point"}
}