{
  "id": 2659088,
  "type": "Feature",
  "properties": {
    "tgn:hierarchy":[
        "tgn:2659088",
        "tgn:1000001",
        "tgn:7012149",
        "tgn:1002441",
        "tgn:7007706",
        "tgn:7029392"
    ],
    "tgn:id":2659088,
    "tgn:name":"Sherwood Village",
    "tgn:placetype":[
        "aat:300008347"
    ]
},
  "bbox": [],
  "geometry": {"coordinates":[-84.35,39.0833],"type":"Point"}
}