{
  "id": 7372965,
  "type": "Feature",
  "properties": {
    "tgn:hierarchy":[
        "tgn:7372965",
        "tgn:1000001",
        "tgn:7005590",
        "tgn:7005560",
        "tgn:7029392"
    ],
    "tgn:id":7372965,
    "tgn:name":"La Ceibilla",
    "tgn:placetype":[
        "aat:300008347"
    ]
},
  "bbox": [],
  "geometry": {"coordinates":[-100.866667,18.566667],"type":"Point"}
}