{
  "id": 2201312,
  "type": "Feature",
  "properties": {
    "tgn:hierarchy":[
        "tgn:2201312",
        "tgn:1000001",
        "tgn:7012149",
        "tgn:2001751",
        "tgn:7007712",
        "tgn:7029392"
    ],
    "tgn:id":2201312,
    "tgn:name":"Buck Bay",
    "tgn:placetype":[
        "aat:300008905"
    ]
},
  "bbox": [],
  "geometry": {"coordinates":[-81.0333,32.3833],"type":"Point"}
}