{
  "id": 7035869,
  "type": "Feature",
  "properties": {
    "tgn:hierarchy":[
        "tgn:7035869",
        "tgn:1003506",
        "tgn:1000003",
        "tgn:7002993",
        "tgn:1000080",
        "tgn:7029392"
    ],
    "tgn:id":7035869,
    "tgn:name":"Olbe, Monte",
    "tgn:placetype":[
        "aat:300008795"
    ]
},
  "bbox": [],
  "geometry": {"coordinates":[12.740556,46.4675],"type":"Point"}
}