{
  "id": 7093826,
  "type": "Feature",
  "properties": {
    "tgn:hierarchy":[
        "tgn:7093826",
        "tgn:1000003",
        "tgn:7003678",
        "tgn:7000084",
        "tgn:7029392"
    ],
    "tgn:id":7093826,
    "tgn:name":"Seek\u00fcppel",
    "tgn:placetype":[
        "aat:300008777"
    ]
},
  "bbox": [],
  "geometry": {"coordinates":[10.033333,50.933333],"type":"Point"}
}