{
  "id": 2671455,
  "type": "Feature",
  "properties": {
    "tgn:hierarchy":[
        "tgn:2671455",
        "tgn:1000001",
        "tgn:7012149",
        "tgn:2000888",
        "tgn:7007256",
        "tgn:7029392"
    ],
    "tgn:id":2671455,
    "tgn:name":"Smith Island",
    "tgn:placetype":[
        "aat:300008791"
    ]
},
  "bbox": [],
  "geometry": {"coordinates":[-93.1667,31.8667],"type":"Point"}
}