{
  "id": 1075949,
  "type": "Feature",
  "properties": {
    "tgn:hierarchy":[
        "tgn:1075949",
        "tgn:1000004",
        "tgn:7000198",
        "tgn:1001977",
        "tgn:7029392"
    ],
    "tgn:id":1075949,
    "tgn:name":"Krishnagar",
    "tgn:placetype":[
        "aat:300008347"
    ]
},
  "bbox": [],
  "geometry": {"coordinates":[87.55,23.2167],"type":"Point"}
}