{
  "id": 2435201,
  "type": "Feature",
  "properties": {
    "tgn:hierarchy":[
        "tgn:2435201",
        "tgn:2002365",
        "tgn:1000001",
        "tgn:7012149",
        "tgn:7007923",
        "tgn:7029392"
    ],
    "tgn:id":2435201,
    "tgn:name":"Kenyon Creek",
    "tgn:placetype":[
        "aat:300008706"
    ]
},
  "bbox": [],
  "geometry": {"coordinates":[-105.4833,42.35],"type":"Point"}
}