{
  "id": 1099485,
  "type": "Feature",
  "properties": {
    "tgn:hierarchy":[
        "tgn:1099485",
        "tgn:7006160",
        "tgn:1000946",
        "tgn:1000006",
        "tgn:7029392"
    ],
    "tgn:id":1099485,
    "tgn:name":"Kandrian",
    "tgn:placetype":[
        "aat:300008347"
    ]
},
  "bbox": [],
  "geometry": {"coordinates":[149.5333,-6.2333],"type":"Point"}
}