{
  "id": 1057194,
  "type": "Feature",
  "properties": {
    "tgn:hierarchy":[
        "tgn:1057194",
        "tgn:7011438",
        "tgn:1000004",
        "tgn:7006646",
        "tgn:7029392"
    ],
    "tgn:id":1057194,
    "tgn:name":"Mukhtadir",
    "tgn:placetype":[
        "aat:300008347"
    ]
},
  "bbox": [],
  "geometry": {"coordinates":[48.7667,41.65],"type":"Point"}
}