{
  "id": 7529492,
  "type": "Feature",
  "properties": {
    "tgn:hierarchy":[
        "tgn:7529492",
        "tgn:7001242",
        "tgn:7016833",
        "tgn:1001113",
        "tgn:7029392"
    ],
    "tgn:id":7529492,
    "tgn:name:en":"Taml\u012bkh, Ba\u1e29r",
    "tgn:placetype":[
        "aat:300008680"
    ]
},
  "bbox": [],
  "geometry": {"coordinates":[32.016667,30.883333],"type":"Point"}
}