{
  "id": 2481862,
  "type": "Feature",
  "properties": {
    "tgn:hierarchy":[
        "tgn:2481862",
        "tgn:1000001",
        "tgn:7012149",
        "tgn:2000910",
        "tgn:7007256",
        "tgn:7029392"
    ],
    "tgn:id":2481862,
    "tgn:name":"Landry Canal",
    "tgn:placetype":[
        "aat:300006075"
    ]
},
  "bbox": [],
  "geometry": {"coordinates":[-92.0167,29.8333],"type":"Point"}
}