{
  "id": 2224578,
  "type": "Feature",
  "properties": {
    "tgn:hierarchy":[
        "tgn:2224578",
        "tgn:1000001",
        "tgn:7012149",
        "tgn:1002518",
        "tgn:7007568",
        "tgn:7029392"
    ],
    "tgn:id":2224578,
    "tgn:name":"Casey Creek",
    "tgn:placetype":[
        "aat:300008706"
    ]
},
  "bbox": [],
  "geometry": {"coordinates":[-75.75,44.2333],"type":"Point"}
}