{
  "id": 2771845,
  "type": "Feature",
  "properties": {
    "tgn:hierarchy":[
        "tgn:2771845",
        "tgn:1000001",
        "tgn:7016172",
        "tgn:7012149",
        "tgn:7029392"
    ],
    "tgn:id":2771845,
    "tgn:name":"Wilhite Hollow",
    "tgn:placetype":[
        "aat:300008761"
    ]
},
  "bbox": [],
  "geometry": {"coordinates":[-92.6667,34.8167],"type":"Point"}
}