{
  "id": 2500608,
  "type": "Feature",
  "properties": {
    "tgn:hierarchy":[
        "tgn:2500608",
        "tgn:1000001",
        "tgn:2002254",
        "tgn:7012149",
        "tgn:7013961",
        "tgn:7029392"
    ],
    "tgn:id":2500608,
    "tgn:name":"McDonald Spring",
    "tgn:placetype":[
        "aat:300008697"
    ]
},
  "bbox": [],
  "geometry": {"coordinates":[-78.0167,39.3667],"type":"Point"}
}