{
  "id": 7157445,
  "type": "Feature",
  "properties": {
    "tgn:hierarchy":[
        "tgn:7157445",
        "tgn:1000003",
        "tgn:7000094",
        "tgn:7000084",
        "tgn:7029392"
    ],
    "tgn:id":7157445,
    "tgn:name":"Kleiner Landgraben",
    "tgn:placetype":[
        "aat:300008699"
    ]
},
  "bbox": [],
  "geometry": {"coordinates":[13.433333,53.75],"type":"Point"}
}