{
  "id": 7357146,
  "type": "Feature",
  "properties": {
    "tgn:hierarchy":[
        "tgn:7357146",
        "tgn:7005586",
        "tgn:1000001",
        "tgn:7005560",
        "tgn:7029392"
    ],
    "tgn:id":7357146,
    "tgn:name":"Chalacatepec, Punta",
    "tgn:placetype":[
        "aat:300386846"
    ]
},
  "bbox": [],
  "geometry": {"coordinates":[-105.266667,19.683333],"type":"Point"}
}