{
  "id": 7291511,
  "type": "Feature",
  "properties": {
    "tgn:hierarchy":[
        "tgn:7291511",
        "tgn:1001708",
        "tgn:1000049",
        "tgn:1000002",
        "tgn:7029392"
    ],
    "tgn:id":7291511,
    "tgn:name":"El Llano",
    "tgn:placetype":[
        "aat:300000206"
    ]
},
  "bbox": [],
  "geometry": {"coordinates":[-70.766667,-33.516667],"type":"Point"}
}