{
  "id": 1012063,
  "type": "Feature",
  "properties": {
    "tgn:hierarchy":[
        "tgn:1012063",
        "tgn:1007413",
        "tgn:7006215",
        "tgn:1000216",
        "tgn:1000006",
        "tgn:7029392"
    ],
    "tgn:id":1012063,
    "tgn:name":"Kiukiu, Pointe",
    "tgn:placetype":[
        "aat:300386846"
    ]
},
  "bbox": [],
  "geometry": {"coordinates":[-139.15,-9.7833],"type":"Point"}
}