{
  "id": 2596627,
  "type": "Feature",
  "properties": {
    "tgn:hierarchy":[
        "tgn:2596627",
        "tgn:1000001",
        "tgn:7012149",
        "tgn:2001914",
        "tgn:7007825",
        "tgn:7029392"
    ],
    "tgn:id":2596627,
    "tgn:name":"Powdermill Creek",
    "tgn:placetype":[
        "aat:300008706"
    ]
},
  "bbox": [],
  "geometry": {"coordinates":[-83.45,35.7333],"type":"Point"}
}