{
  "id": 7297142,
  "type": "Feature",
  "properties": {
    "tgn:hierarchy":[
        "tgn:7297142",
        "tgn:7001122",
        "tgn:1000003",
        "tgn:7002765",
        "tgn:1000095",
        "tgn:7029392"
    ],
    "tgn:id":7297142,
    "tgn:name":"Tarong\u00e9, Punta",
    "tgn:placetype":[
        "aat:300386846"
    ]
},
  "bbox": [],
  "geometry": {"coordinates":[4.166667,40.033333],"type":"Point"}
}