{
  "id": 7054435,
  "type": "Feature",
  "properties": {
    "tgn:hierarchy":[
        "tgn:7054435",
        "tgn:1003429",
        "tgn:1000003",
        "tgn:7003240",
        "tgn:1000080",
        "tgn:7029392"
    ],
    "tgn:id":7054435,
    "tgn:name":"Monsano",
    "tgn:placetype":[
        "aat:300008347"
    ]
},
  "bbox": [],
  "geometry": {"coordinates":[13.25,43.55],"type":"Point"}
}