{
  "id": 2565190,
  "type": "Feature",
  "properties": {
    "tgn:hierarchy":[
        "tgn:2565190",
        "tgn:7023902",
        "tgn:1000001",
        "tgn:7012149",
        "tgn:7007249",
        "tgn:7029392"
    ],
    "tgn:id":2565190,
    "tgn:name":"Paiakuli Reservoir",
    "tgn:placetype":[
        "aat:300006191"
    ]
},
  "bbox": [],
  "geometry": {"coordinates":[-155.6333,20.0167],"type":"Point"}
}