{
  "id": 2164350,
  "type": "Feature",
  "properties": {
    "tgn:hierarchy":[
        "tgn:2164350",
        "tgn:1000001",
        "tgn:7012149",
        "tgn:7007157",
        "tgn:1002894",
        "tgn:7029392"
    ],
    "tgn:id":2164350,
    "tgn:name":"Berry Creek",
    "tgn:placetype":[
        "aat:300008706"
    ]
},
  "bbox": [],
  "geometry": {"coordinates":[-120.45,39.55],"type":"Point"}
}