{
  "id": 2321712,
  "type": "Feature",
  "properties": {
    "tgn:hierarchy":[
        "tgn:2321712",
        "tgn:7013349",
        "tgn:1000001",
        "tgn:7012149",
        "tgn:7007708",
        "tgn:7029392"
    ],
    "tgn:id":2321712,
    "tgn:name":"Fairview Point",
    "tgn:placetype":[
        "aat:300008798"
    ]
},
  "bbox": [],
  "geometry": {"coordinates":[-117.5167,45.0167],"type":"Point"}
}