{
  "id": 5003180,
  "type": "Feature",
  "properties": {
    "tgn:hierarchy":[
        "tgn:5003180",
        "tgn:7002996",
        "tgn:1000003",
        "tgn:7002997",
        "tgn:1000080",
        "tgn:7029392"
    ],
    "tgn:id":5003180,
    "tgn:name":"Santa Cristina di Quinto di Treviso",
    "tgn:placetype":[
        "aat:300008347"
    ]
},
  "bbox": [],
  "geometry": {"coordinates":[12.118,45.641],"type":"Point"}
}