{
  "id": 2298239,
  "type": "Feature",
  "properties": {
    "tgn:hierarchy":[
        "tgn:2298239",
        "tgn:1000001",
        "tgn:2000582",
        "tgn:7012149",
        "tgn:7007253",
        "tgn:7029392"
    ],
    "tgn:id":2298239,
    "tgn:name":"Dry Mill Creek",
    "tgn:placetype":[
        "aat:300008706"
    ]
},
  "bbox": [],
  "geometry": {"coordinates":[-91.2833,42.9167],"type":"Point"}
}