{
  "id": 7546272,
  "type": "Feature",
  "properties": {
    "tgn:hierarchy":[
        "tgn:7546272",
        "tgn:1000004",
        "tgn:1001832",
        "tgn:7000198",
        "tgn:7029392"
    ],
    "tgn:id":7546272,
    "tgn:name:en":"B\u0101telegaon",
    "tgn:placetype":[
        "aat:300008347"
    ]
},
  "bbox": [],
  "geometry": {"coordinates":[94.690237,27.673128],"type":"Point"}
}