{
  "id": 2246246,
  "type": "Feature",
  "properties": {
    "tgn:hierarchy":[
        "tgn:2246246",
        "tgn:1000001",
        "tgn:7012149",
        "tgn:2001442",
        "tgn:7007566",
        "tgn:7029392"
    ],
    "tgn:id":2246246,
    "tgn:name":"Coalora",
    "tgn:placetype":[
        "aat:300008347"
    ]
},
  "bbox": [],
  "geometry": {"coordinates":[-105.5833,33.5667],"type":"Point"}
}