{
  "id": 2283620,
  "type": "Feature",
  "properties": {
    "tgn:hierarchy":[
        "tgn:2283620",
        "tgn:1000001",
        "tgn:7012149",
        "tgn:7016057",
        "tgn:7007520",
        "tgn:7029392"
    ],
    "tgn:id":2283620,
    "tgn:name":"Demijohn Lake",
    "tgn:placetype":[
        "aat:300008680"
    ]
},
  "bbox": [],
  "geometry": {"coordinates":[-85.4667,41.9167],"type":"Point"}
}