{
  "id": 2012010,
  "type": "Feature",
  "properties": {
    "tgn:hierarchy":[
        "tgn:2012010",
        "tgn:1000001",
        "tgn:7012149",
        "tgn:2000181",
        "tgn:7007157",
        "tgn:7029392"
    ],
    "tgn:id":2012010,
    "tgn:name":"King Salmon",
    "tgn:placetype":[
        "aat:300008347"
    ]
},
  "bbox": [],
  "geometry": {"coordinates":[-124.2167,40.7333],"type":"Point"}
}