{
  "id": 7561703,
  "type": "Feature",
  "properties": {
    "tgn:hierarchy":[
        "tgn:7561703",
        "tgn:1000004",
        "tgn:7000198",
        "tgn:7016722",
        "tgn:7029392"
    ],
    "tgn:id":7561703,
    "tgn:name:en":"Udmai",
    "tgn:placetype":[
        "aat:300008347"
    ]
},
  "bbox": [],
  "geometry": {"coordinates":[79.17275,27.960239],"type":"Point"}
}