{
  "id": 2624673,
  "type": "Feature",
  "properties": {
    "tgn:hierarchy":[
        "tgn:2624673",
        "tgn:1000001",
        "tgn:7006451",
        "tgn:7012149",
        "tgn:2000103",
        "tgn:7029392"
    ],
    "tgn:id":2624673,
    "tgn:name":"Rock Seep",
    "tgn:placetype":[
        "aat:300008697"
    ]
},
  "bbox": [],
  "geometry": {"coordinates":[-111.9167,34.3167],"type":"Point"}
}