<<<<<<< HEAD
{
  "id": 7354234,
  "type": "Feature",
  "properties": {
    "tgn:hierarchy":[
        "tgn:7354234",
        "tgn:7005575",
        "tgn:1000001",
        "tgn:7005560",
        "tgn:7029392"
    ],
    "tgn:id":7354234,
    "tgn:name":"Casas Alem\u00e1n",
    "tgn:placetype":[
        "aat:300008347"
    ]
},
  "bbox": [],
  "geometry": {"coordinates":[-99.1,19.45],"type":"Point"}
}
=======
{"geometry":{"type":"Point","coordinates":[-99.100000,19.450000]},"type":"Feature","properties":{"hierarchy":["tgn:7354234","tgn:7005575","tgn:1000001","tgn:7005560","tgn:7029392"],"placetype":["aat:300008347"],"id":7354234,"name:xx":"Casas Alem\u00e1n"}}
>>>>>>> 03f74aca74312dbeaf24d7e61306dd6a786dc3d0
