{
  "id": 2369811,
  "type": "Feature",
  "properties": {
    "tgn:hierarchy":[
        "tgn:2369811",
        "tgn:1000001",
        "tgn:2001013",
        "tgn:7012149",
        "tgn:7007521",
        "tgn:7029392"
    ],
    "tgn:id":2369811,
    "tgn:name":"Gurneau Lake",
    "tgn:placetype":[
        "aat:300008680"
    ]
},
  "bbox": [],
  "geometry": {"coordinates":[-95.25,47.8333],"type":"Point"}
}