{
  "id": 1043836,
  "type": "Feature",
  "properties": {
    "tgn:hierarchy":[
        "tgn:1043836",
        "tgn:7003154",
        "tgn:1000003",
        "tgn:7003120",
        "tgn:1000080",
        "tgn:7029392"
    ],
    "tgn:id":1043836,
    "tgn:name":"Cantoira",
    "tgn:placetype":[
        "aat:300008347"
    ]
},
  "bbox": [],
  "geometry": {"coordinates":[7.383333,45.35],"type":"Point"}
}