{
  "id": 1049045,
  "type": "Feature",
  "properties": {
    "tgn:hierarchy":[
        "tgn:1049045",
        "tgn:1000003",
        "tgn:7024122",
        "tgn:7006366",
        "tgn:7029392"
    ],
    "tgn:id":1049045,
    "tgn:name":"Garwolin",
    "tgn:placetype":[
        "aat:300008347"
    ]
},
  "bbox": [],
  "geometry": {"coordinates":[21.6333,51.9167],"type":"Point"}
}