{
  "id": 7470643,
  "type": "Feature",
  "properties": {
    "tgn:hierarchy":[
        "tgn:7470643",
        "tgn:1000004",
        "tgn:7001014",
        "tgn:1000141",
        "tgn:7029392"
    ],
    "tgn:id":7470643,
    "tgn:name":"Xiawei",
    "tgn:placetype":[
        "aat:300008347"
    ]
},
  "bbox": [],
  "geometry": {"coordinates":[120.417679,23.621082],"type":"Point"}
}