<<<<<<< HEAD
{
  "id": 7359769,
  "type": "Feature",
  "properties": {
    "tgn:hierarchy":[
        "tgn:7359769",
        "tgn:7005580",
        "tgn:1000001",
        "tgn:7005560",
        "tgn:7029392"
    ],
    "tgn:id":7359769,
    "tgn:name":"Cuatro R\u00edos",
    "tgn:placetype":[
        "aat:300008347"
    ]
},
  "bbox": [],
  "geometry": {"coordinates":[-92.433333,14.783333],"type":"Point"}
}
=======
{"geometry":{"type":"Point","coordinates":[-92.433333,14.783333]},"type":"Feature","properties":{"hierarchy":["tgn:7359769","tgn:7005580","tgn:1000001","tgn:7005560","tgn:7029392"],"placetype":["aat:300008347"],"id":7359769,"name:xx":"Cuatro R\u00edos"}}
>>>>>>> 03f74aca74312dbeaf24d7e61306dd6a786dc3d0
