{
  "id": 7007668,
  "type": "Feature",
  "properties": {
    "tgn:hierarchy":[
        "tgn:7007668",
        "tgn:1000003",
        "tgn:7003755",
        "tgn:7011731",
        "tgn:7029392"
    ],
    "tgn:id":7007668,
    "tgn:name":"Rapperswil",
    "tgn:placetype":[
        "aat:300008347"
    ]
},
  "bbox": [],
  "geometry": {"coordinates":[8.8333,47.2333],"type":"Point"}
}