{
  "id": 7401704,
  "type": "Feature",
  "properties": {
    "tgn:hierarchy":[
        "tgn:7401704",
        "tgn:1000001",
        "tgn:7005599",
        "tgn:7005560",
        "tgn:7029392"
    ],
    "tgn:id":7401704,
    "tgn:name":"La Luz Palotal Siete",
    "tgn:placetype":[
        "aat:300008347"
    ]
},
  "bbox": [],
  "geometry": {"coordinates":[-96.961111,18.918056],"type":"Point"}
}