{
  "id": 7520884,
  "type": "Feature",
  "properties": {
    "tgn:hierarchy":[
        "tgn:7520884",
        "tgn:7001242",
        "tgn:7016833",
        "tgn:1001335",
        "tgn:7029392"
    ],
    "tgn:id":7520884,
    "tgn:name:en":"Al Kurd\u012b",
    "tgn:placetype":[
        "aat:300008347"
    ]
},
  "bbox": [],
  "geometry": {"coordinates":[30.818699,31.07702],"type":"Point"}
}