{
  "id": 2132408,
  "type": "Feature",
  "properties": {
    "tgn:hierarchy":[
        "tgn:2132408",
        "tgn:1000001",
        "tgn:7012149",
        "tgn:2002118",
        "tgn:7007827",
        "tgn:7029392"
    ],
    "tgn:id":2132408,
    "tgn:name":"Amos Addition",
    "tgn:placetype":[
        "aat:300008347"
    ]
},
  "bbox": [],
  "geometry": {"coordinates":[-111.9167,40.7833],"type":"Point"}
}