{
  "id": 2278897,
  "type": "Feature",
  "properties": {
    "tgn:hierarchy":[
        "tgn:2278897",
        "tgn:1000001",
        "tgn:7012149",
        "tgn:2001167",
        "tgn:7007522",
        "tgn:7029392"
    ],
    "tgn:id":2278897,
    "tgn:name":"Dead Man Bayou",
    "tgn:placetype":[
        "aat:300008699"
    ]
},
  "bbox": [],
  "geometry": {"coordinates":[-90.3833,32.95],"type":"Point"}
}