{
  "id": 2543865,
  "type": "Feature",
  "properties": {
    "tgn:hierarchy":[
        "tgn:2543865",
        "tgn:1000001",
        "tgn:1002270",
        "tgn:7012149",
        "tgn:7007708",
        "tgn:7029392"
    ],
    "tgn:id":2543865,
    "tgn:name":"North Boulder Creek",
    "tgn:placetype":[
        "aat:300008706"
    ]
},
  "bbox": [],
  "geometry": {"coordinates":[-121.9333,45.3833],"type":"Point"}
}