{
  "id": 2138267,
  "type": "Feature",
  "properties": {
    "tgn:hierarchy":[
        "tgn:2138267",
        "tgn:1000001",
        "tgn:7012149",
        "tgn:2001829",
        "tgn:7007713",
        "tgn:7029392"
    ],
    "tgn:id":2138267,
    "tgn:name":"Artichoke Butte",
    "tgn:placetype":[
        "aat:300008798"
    ]
},
  "bbox": [],
  "geometry": {"coordinates":[-100.35,44.85],"type":"Point"}
}