{
  "id": 2563538,
  "type": "Feature",
  "properties": {
    "tgn:hierarchy":[
        "tgn:2563538",
        "tgn:1000001",
        "tgn:1002229",
        "tgn:7012149",
        "tgn:7007710",
        "tgn:7029392"
    ],
    "tgn:id":2563538,
    "tgn:name":"Owl Run",
    "tgn:placetype":[
        "aat:300008699"
    ]
},
  "bbox": [],
  "geometry": {"coordinates":[-78.0333,41.4667],"type":"Point"}
}