{
  "id": 2254350,
  "type": "Feature",
  "properties": {
    "tgn:hierarchy":[
        "tgn:2254350",
        "tgn:1000001",
        "tgn:2000669",
        "tgn:7012149",
        "tgn:7007254",
        "tgn:7029392"
    ],
    "tgn:id":2254350,
    "tgn:name":"Coon Creek",
    "tgn:placetype":[
        "aat:300008706"
    ]
},
  "bbox": [],
  "geometry": {"coordinates":[-96.1833,37.1833],"type":"Point"}
}