<<<<<<< HEAD
{
  "id": 2254350,
  "type": "Feature",
  "properties": {
    "tgn:hierarchy":[
        "tgn:2254350",
        "tgn:1000001",
        "tgn:2000669",
        "tgn:7012149",
        "tgn:7007254",
        "tgn:7029392"
    ],
    "tgn:id":2254350,
    "tgn:name":"Coon Creek",
    "tgn:placetype":[
        "aat:300008706"
    ]
},
  "bbox": [],
  "geometry": {"coordinates":[-96.1833,37.1833],"type":"Point"}
}
=======
{"geometry":{"type":"Point","coordinates":[-96.183300,37.183300]},"type":"Feature","properties":{"hierarchy":["tgn:2254350","tgn:1000001","tgn:2000669","tgn:7012149","tgn:7007254","tgn:7029392"],"placetype":["aat:300008706"],"id":2254350,"name:xx":"Coon Creek"}}
>>>>>>> 03f74aca74312dbeaf24d7e61306dd6a786dc3d0
