{
  "id": 7009923,
  "type": "Feature",
  "properties": {
    "tgn:hierarchy":[
        "tgn:7009923",
        "tgn:7002804",
        "tgn:1000003",
        "tgn:7002793",
        "tgn:1000095",
        "tgn:7029392"
    ],
    "tgn:id":7009923,
    "tgn:name":"Nao, Cabo de la",
    "tgn:placetype":[
        "aat:300008850"
    ]
},
  "bbox": [],
  "geometry": {"coordinates":[0.233333,38.733333],"type":"Point"}
}