{
  "id": 2515314,
  "type": "Feature",
  "properties": {
    "tgn:hierarchy":[
        "tgn:2515314",
        "tgn:2001423",
        "tgn:1000001",
        "tgn:7012149",
        "tgn:7007564",
        "tgn:7029392"
    ],
    "tgn:id":2515314,
    "tgn:name":"Milliken Hill",
    "tgn:placetype":[
        "aat:300008798"
    ]
},
  "bbox": [],
  "geometry": {"coordinates":[-71.1167,43.7167],"type":"Point"}
}