<<<<<<< HEAD
{
  "id": 7178215,
  "type": "Feature",
  "properties": {
    "tgn:hierarchy":[
        "tgn:7178215",
        "tgn:1000003",
        "tgn:7003677",
        "tgn:7000084",
        "tgn:7029392"
    ],
    "tgn:id":7178215,
    "tgn:name":"Hanf-Bach",
    "tgn:placetype":[
        "aat:300008699"
    ]
},
  "bbox": [],
  "geometry": {"coordinates":[7.283333,50.766667],"type":"Point"}
}
=======
{"geometry":{"type":"Point","coordinates":[7.283333,50.766667]},"type":"Feature","properties":{"hierarchy":["tgn:7178215","tgn:1000003","tgn:7003677","tgn:7000084","tgn:7029392"],"placetype":["aat:300008699"],"id":7178215,"name:xx":"Hanf-Bach"}}
>>>>>>> 03f74aca74312dbeaf24d7e61306dd6a786dc3d0
