{
  "id": 2179189,
  "type": "Feature",
  "properties": {
    "tgn:hierarchy":[
        "tgn:2179189",
        "tgn:1000001",
        "tgn:7012149",
        "tgn:2002353",
        "tgn:7007922",
        "tgn:7029392"
    ],
    "tgn:id":2179189,
    "tgn:name":"Blaisdell Lake",
    "tgn:placetype":[
        "aat:300008680"
    ]
},
  "bbox": [],
  "geometry": {"coordinates":[-90.8833,45.9333],"type":"Point"}
}