{
  "id": 7443337,
  "type": "Feature",
  "properties": {
    "tgn:hierarchy":[
        "tgn:7443337",
        "tgn:7002445",
        "tgn:7008116",
        "tgn:1000003",
        "tgn:7008591",
        "tgn:7029392"
    ],
    "tgn:id":7443337,
    "tgn:name:en":"Scilly Rock",
    "tgn:placetype":[
        "aat:300011692"
    ]
},
  "bbox": [],
  "geometry": {"coordinates":[-6.383333,49.966667],"type":"Point"}
}