<<<<<<< HEAD
{
  "id": 7480447,
  "type": "Feature",
  "properties": {
    "tgn:hierarchy":[
        "tgn:7480447",
        "tgn:1000004",
        "tgn:7490934",
        "tgn:1000141",
        "tgn:7029392"
    ],
    "tgn:id":7480447,
    "tgn:name":"Liujia",
    "tgn:placetype":[
        "aat:300008777"
    ]
},
  "bbox": [],
  "geometry": {"coordinates":[120.367377,23.225253],"type":"Point"}
}
=======
{"geometry":{"type":"Point","coordinates":[120.367377,23.225253]},"type":"Feature","properties":{"hierarchy":["tgn:7480447","tgn:1000004","tgn:7490934","tgn:1000141","tgn:7029392"],"placetype":["aat:300008777"],"id":7480447,"name:xx":"Liujia"}}
>>>>>>> 03f74aca74312dbeaf24d7e61306dd6a786dc3d0
