{
  "id": 7565939,
  "type": "Feature",
  "properties": {
    "tgn:hierarchy":[
        "tgn:7565939",
        "tgn:1000004",
        "tgn:7000198",
        "tgn:7016722",
        "tgn:7029392"
    ],
    "tgn:id":7565939,
    "tgn:name:en":"Hasanpur",
    "tgn:placetype":[
        "aat:300008347"
    ]
},
  "bbox": [],
  "geometry": {"coordinates":[79.438166,26.407229],"type":"Point"}
}