<<<<<<< HEAD
{
  "id": 7028073,
  "type": "Feature",
  "properties": {
    "tgn:hierarchy":[
        "tgn:7028073",
        "tgn:7002445",
        "tgn:1000003",
        "tgn:7008157",
        "tgn:7008591",
        "tgn:7029392"
    ],
    "tgn:id":7028073,
    "tgn:name:en":"Scotton",
    "tgn:placetype":[
        "aat:300008347",
        "aat:300008372"
    ]
},
  "bbox": [],
  "geometry": {"coordinates":[-0.65,53.466667],"type":"Point"}
}
=======
{"geometry":{"type":"Point","coordinates":[-0.650000,53.466667]},"type":"Feature","properties":{"hierarchy":["tgn:7028073","tgn:7002445","tgn:1000003","tgn:7008157","tgn:7008591","tgn:7029392"],"placetype":["aat:300008347","aat:300008372"],"name:en":"Scotton","id":7028073}}
>>>>>>> 03f74aca74312dbeaf24d7e61306dd6a786dc3d0
