{
  "id": 1104376,
  "type": "Feature",
  "properties": {
    "tgn:hierarchy":[
        "tgn:1104376",
        "tgn:7000895",
        "tgn:1000004",
        "tgn:1001031",
        "tgn:1000120",
        "tgn:7029392"
    ],
    "tgn:id":1104376,
    "tgn:name":"Dai-mugen-yama",
    "tgn:placetype":[
        "aat:300008795"
    ]
},
  "bbox": [],
  "geometry": {"coordinates":[138.1667,35.25],"type":"Point"}
}