{
  "id": 2674237,
  "type": "Feature",
  "properties": {
    "tgn:hierarchy":[
        "tgn:2674237",
        "tgn:1000001",
        "tgn:7012149",
        "tgn:7007157",
        "tgn:2000189",
        "tgn:7029392"
    ],
    "tgn:id":2674237,
    "tgn:name":"Snowshoe Creek",
    "tgn:placetype":[
        "aat:300008706"
    ]
},
  "bbox": [],
  "geometry": {"coordinates":[-123.2333,41.65],"type":"Point"}
}