{
  "id": 2424448,
  "type": "Feature",
  "properties": {
    "tgn:hierarchy":[
        "tgn:2424448",
        "tgn:1000001",
        "tgn:7012149",
        "tgn:2002377",
        "tgn:7007923",
        "tgn:7029392"
    ],
    "tgn:id":2424448,
    "tgn:name":"Johnson Canyon",
    "tgn:placetype":[
        "aat:300008761"
    ]
},
  "bbox": [],
  "geometry": {"coordinates":[-106.8333,42.9333],"type":"Point"}
}