{
  "id": 1027564,
  "type": "Feature",
  "properties": {
    "tgn:hierarchy":[
        "tgn:1027564",
        "tgn:7593921",
        "tgn:1000003",
        "tgn:1001780",
        "tgn:7029392"
    ],
    "tgn:id":1027564,
    "tgn:name":"Sv\u011btl\u00e1 nad S\u00e1zavou",
    "tgn:placetype":[
        "aat:300008347"
    ]
},
  "bbox": [],
  "geometry": {"coordinates":[15.4167,49.6667],"type":"Point"}
}