{
  "id": 7347737,
  "type": "Feature",
  "properties": {
    "tgn:hierarchy":[
        "tgn:7347737",
        "tgn:7008912",
        "tgn:7030216",
        "tgn:1000003",
        "tgn:1000095",
        "tgn:7029392"
    ],
    "tgn:id":7347737,
    "tgn:name":"Arr\u00f3s",
    "tgn:placetype":[
        "aat:300008347"
    ]
},
  "bbox": [],
  "geometry": {"coordinates":[0.760221,42.738739],"type":"Point"}
}