{
  "id": 7519374,
  "type": "Feature",
  "properties": {
    "tgn:hierarchy":[
        "tgn:7519374",
        "tgn:1009227",
        "tgn:1000226",
        "tgn:7016729",
        "tgn:1000006",
        "tgn:7029392"
    ],
    "tgn:id":7519374,
    "tgn:name:en":"Alexander, Mount",
    "tgn:placetype":[
        "aat:300008795"
    ]
},
  "bbox": [],
  "geometry": {"coordinates":[173.616667,-41.816667],"type":"Point"}
}