{
  "id": 2785166,
  "type": "Feature",
  "properties": {
    "tgn:hierarchy":[
        "tgn:2785166",
        "tgn:7006450",
        "tgn:1000001",
        "tgn:7019674",
        "tgn:7012149",
        "tgn:7029392"
    ],
    "tgn:id":2785166,
    "tgn:name":"Yellow Pup Creek",
    "tgn:placetype":[
        "aat:300008706"
    ]
},
  "bbox": [],
  "geometry": {"coordinates":[-147.3333,64.9667],"type":"Point"}
}