{
  "id": 1076776,
  "type": "Feature",
  "properties": {
    "tgn:hierarchy":[
        "tgn:1076776",
        "tgn:1000004",
        "tgn:7000198",
        "tgn:7016722",
        "tgn:7029392"
    ],
    "tgn:id":1076776,
    "tgn:name:en":"Robertsganj",
    "tgn:placetype":[
        "aat:300008347"
    ]
},
  "bbox": [],
  "geometry": {"coordinates":[83.066316,24.688895],"type":"Point"}
}