{
  "id": 2748375,
  "type": "Feature",
  "properties": {
    "tgn:hierarchy":[
        "tgn:2748375",
        "tgn:1000001",
        "tgn:7012149",
        "tgn:2002382",
        "tgn:7007923",
        "tgn:7029392"
    ],
    "tgn:id":2748375,
    "tgn:name":"Walker Creek",
    "tgn:placetype":[
        "aat:300008706"
    ]
},
  "bbox": [],
  "geometry": {"coordinates":[-110.5333,42.6333],"type":"Point"}
}