{
  "id": 7207264,
  "type": "Feature",
  "properties": {
    "tgn:hierarchy":[
        "tgn:7207264",
        "tgn:7000096",
        "tgn:1000003",
        "tgn:7000084",
        "tgn:7029392"
    ],
    "tgn:id":7207264,
    "tgn:name":"Butterlake",
    "tgn:placetype":[
        "aat:300008347"
    ]
},
  "bbox": [],
  "geometry": {"coordinates":[12.516667,52.45],"type":"Point"}
}