{
  "id": 7218543,
  "type": "Feature",
  "properties": {
    "tgn:hierarchy":[
        "tgn:7218543",
        "tgn:7011171",
        "tgn:7001395",
        "tgn:1000003",
        "tgn:1000074",
        "tgn:7029392"
    ],
    "tgn:id":7218543,
    "tgn:name":"V\u00e1les, Orm\u00edskos",
    "tgn:placetype":[
        "aat:300185707"
    ]
},
  "bbox": [],
  "geometry": {"coordinates":[24.538056,38.782222],"type":"Point"}
}