{
  "id": 7338834,
  "type": "Feature",
  "properties": {
    "tgn:hierarchy":[
        "tgn:7338834",
        "tgn:7002818",
        "tgn:1001647",
        "tgn:1000003",
        "tgn:1000095",
        "tgn:7029392"
    ],
    "tgn:id":7338834,
    "tgn:name":"Cubillo, Arroyo del",
    "tgn:placetype":[
        "aat:300266554",
        "aat:300008699"
    ]
},
  "bbox": [],
  "geometry": {"coordinates":[-2.316667,39.883333],"type":"Point"}
}