{
  "id": 7160275,
  "type": "Feature",
  "properties": {
    "tgn:hierarchy":[
        "tgn:7160275",
        "tgn:7000096",
        "tgn:1000003",
        "tgn:7000084",
        "tgn:7029392"
    ],
    "tgn:id":7160275,
    "tgn:name":"Hohlen-Berg",
    "tgn:placetype":[
        "aat:300008777"
    ]
},
  "bbox": [],
  "geometry": {"coordinates":[12.566667,53.033333],"type":"Point"}
}