{
  "id": 7588217,
  "type": "Feature",
  "properties": {
    "tgn:hierarchy":[
        "tgn:7588217",
        "tgn:1000004",
        "tgn:7000198",
        "tgn:7000799",
        "tgn:7029392"
    ],
    "tgn:id":7588217,
    "tgn:name:en":"Nasarpur",
    "tgn:placetype":[
        "aat:300008347"
    ]
},
  "bbox": [],
  "geometry": {"coordinates":[74.539079,34.018732],"type":"Point"}
}