{
  "id": 7155356,
  "type": "Feature",
  "properties": {
    "tgn:hierarchy":[
        "tgn:7155356",
        "tgn:1000003",
        "tgn:7003677",
        "tgn:7000084",
        "tgn:7029392"
    ],
    "tgn:id":7155356,
    "tgn:name":"Klein Jerusalem",
    "tgn:placetype":[
        "aat:300008347"
    ]
},
  "bbox": [],
  "geometry": {"coordinates":[6.483333,51.25],"type":"Point"}
}