<<<<<<< HEAD
{
  "id": 2408308,
  "type": "Feature",
  "properties": {
    "tgn:hierarchy":[
        "tgn:2408308",
        "tgn:1000001",
        "tgn:7012149",
        "tgn:2001083",
        "tgn:7007521",
        "tgn:7029392"
    ],
    "tgn:id":2408308,
    "tgn:name":"Husman Ridge",
    "tgn:placetype":[
        "aat:300266640"
    ]
},
  "bbox": [],
  "geometry": {"coordinates":[-91.4667,43.95],"type":"Point"}
}
=======
{"geometry":{"type":"Point","coordinates":[-91.466700,43.950000]},"type":"Feature","properties":{"hierarchy":["tgn:2408308","tgn:1000001","tgn:7012149","tgn:2001083","tgn:7007521","tgn:7029392"],"placetype":["aat:300266640"],"id":2408308,"name:xx":"Husman Ridge"}}
>>>>>>> 03f74aca74312dbeaf24d7e61306dd6a786dc3d0
