{
  "id": 2223216,
  "type": "Feature",
  "properties": {
    "tgn:hierarchy":[
        "tgn:2223216",
        "tgn:1000001",
        "tgn:1002284",
        "tgn:7012149",
        "tgn:7007568",
        "tgn:7029392"
    ],
    "tgn:id":2223216,
    "tgn:name":"Carrow Hill",
    "tgn:placetype":[
        "aat:300008798"
    ]
},
  "bbox": [],
  "geometry": {"coordinates":[-73.65,44.4833],"type":"Point"}
}