{
  "id": 1056886,
  "type": "Feature",
  "properties": {
    "tgn:hierarchy":[
        "tgn:1056886",
        "tgn:1000004",
        "tgn:7011573",
        "tgn:7018214",
        "tgn:7002435",
        "tgn:7029392"
    ],
    "tgn:id":1056886,
    "tgn:name":"Meshcherskiy",
    "tgn:placetype":[
        "aat:300008347"
    ]
},
  "bbox": [],
  "geometry": {"coordinates":[37.4167,55.6667],"type":"Point"}
}