<<<<<<< HEAD
{
  "id": 2701299,
  "type": "Feature",
  "properties": {
    "tgn:hierarchy":[
        "tgn:2701299",
        "tgn:1000001",
        "tgn:2001260",
        "tgn:7012149",
        "tgn:7007524",
        "tgn:7029392"
    ],
    "tgn:id":2701299,
    "tgn:name":"Sugar Loaf Mine",
    "tgn:placetype":[
        "aat:300000390"
    ]
},
  "bbox": [],
  "geometry": {"coordinates":[-112.8,45.4833],"type":"Point"}
}
=======
{"geometry":{"type":"Point","coordinates":[-112.800000,45.483300]},"type":"Feature","properties":{"hierarchy":["tgn:2701299","tgn:1000001","tgn:2001260","tgn:7012149","tgn:7007524","tgn:7029392"],"placetype":["aat:300000390"],"id":2701299,"name:xx":"Sugar Loaf Mine"}}
>>>>>>> 03f74aca74312dbeaf24d7e61306dd6a786dc3d0
