{
  "id": 2727713,
  "type": "Feature",
  "properties": {
    "tgn:hierarchy":[
        "tgn:2727713",
        "tgn:1000001",
        "tgn:7012149",
        "tgn:1002999",
        "tgn:7007526",
        "tgn:7029392"
    ],
    "tgn:id":2727713,
    "tgn:name":"Trail Spring",
    "tgn:placetype":[
        "aat:300008697"
    ]
},
  "bbox": [],
  "geometry": {"coordinates":[-119.6167,40.85],"type":"Point"}
}