{
  "id": 2319480,
  "type": "Feature",
  "properties": {
    "tgn:hierarchy":[
        "tgn:2319480",
        "tgn:7006450",
        "tgn:1000001",
        "tgn:7012149",
        "tgn:2000088",
        "tgn:7029392"
    ],
    "tgn:id":2319480,
    "tgn:name":"Etolin Island",
    "tgn:placetype":[
        "aat:300008791"
    ]
},
  "bbox": [],
  "geometry": {"coordinates":[-132.4667,56.2833],"type":"Point"}
}