{
  "id": 7461693,
  "type": "Feature",
  "properties": {
    "tgn:hierarchy":[
        "tgn:7461693",
        "tgn:7002445",
        "tgn:1000003",
        "tgn:5000227",
        "tgn:7008591",
        "tgn:7029392"
    ],
    "tgn:id":7461693,
    "tgn:name:en":"Kyre Magna",
    "tgn:placetype":[
        "aat:300008347"
    ]
},
  "bbox": [],
  "geometry": {"coordinates":[-2.55,52.266667],"type":"Point"}
}