{
  "id": 7502740,
  "type": "Feature",
  "properties": {
    "tgn:hierarchy":[
        "tgn:7502740",
        "tgn:1000004",
        "tgn:7471332",
        "tgn:1000141",
        "tgn:7029392"
    ],
    "tgn:id":7502740,
    "tgn:name":"Fengxiang Erhao Qiao",
    "tgn:placetype":[
        "aat:300007836"
    ]
},
  "bbox": [],
  "geometry": {"coordinates":[121.143611,24.690278],"type":"Point"}
}