{
  "id": 7154921,
  "type": "Feature",
  "properties": {
    "tgn:hierarchy":[
        "tgn:7154921",
        "tgn:1000003",
        "tgn:7003676",
        "tgn:7000084",
        "tgn:7029392"
    ],
    "tgn:id":7154921,
    "tgn:name":"Kattenhorn",
    "tgn:placetype":[
        "aat:300008347"
    ]
},
  "bbox": [],
  "geometry": {"coordinates":[8.783333,53.25],"type":"Point"}
}