<<<<<<< HEAD
{
  "id": 7352964,
  "type": "Feature",
  "properties": {
    "tgn:hierarchy":[
        "tgn:7352964",
        "tgn:1000001",
        "tgn:1001960",
        "tgn:7005560",
        "tgn:7029392"
    ],
    "tgn:id":7352964,
    "tgn:name":"Batepito",
    "tgn:placetype":[
        "aat:300008347"
    ]
},
  "bbox": [],
  "geometry": {"coordinates":[-109.2,30.816667],"type":"Point"}
}
=======
{"geometry":{"type":"Point","coordinates":[-109.200000,30.816667]},"type":"Feature","properties":{"hierarchy":["tgn:7352964","tgn:1000001","tgn:1001960","tgn:7005560","tgn:7029392"],"placetype":["aat:300008347"],"id":7352964,"name:xx":"Batepito"}}
>>>>>>> 03f74aca74312dbeaf24d7e61306dd6a786dc3d0
