{
  "id": 7528863,
  "type": "Feature",
  "properties": {
    "tgn:hierarchy":[
        "tgn:7528863",
        "tgn:7001242",
        "tgn:7016833",
        "tgn:7001336",
        "tgn:7029392"
    ],
    "tgn:id":7528863,
    "tgn:name":"Umm Maghrib, Ra's",
    "tgn:placetype":[
        "aat:300008795"
    ]
},
  "bbox": [],
  "geometry": {"coordinates":[33.233649,29.288475],"type":"Point"}
}