{
  "id": 7080371,
  "type": "Feature",
  "properties": {
    "tgn:hierarchy":[
        "tgn:7080371",
        "tgn:7003692",
        "tgn:1000003",
        "tgn:7000084",
        "tgn:7029392"
    ],
    "tgn:id":7080371,
    "tgn:name":"Wolfbauernhof",
    "tgn:placetype":[
        "aat:300000206"
    ]
},
  "bbox": [],
  "geometry": {"coordinates":[8.283333,48.183333],"type":"Point"}
}