{
  "id": 2659859,
  "type": "Feature",
  "properties": {
    "tgn:hierarchy":[
        "tgn:2659859",
        "tgn:1000001",
        "tgn:7012149",
        "tgn:2001927",
        "tgn:7007825",
        "tgn:7029392"
    ],
    "tgn:id":2659859,
    "tgn:name":"Shipman Hollow",
    "tgn:placetype":[
        "aat:300008761"
    ]
},
  "bbox": [],
  "geometry": {"coordinates":[-87.75,35.1833],"type":"Point"}
}