{
  "id": 2293782,
  "type": "Feature",
  "properties": {
    "tgn:hierarchy":[
        "tgn:2293782",
        "tgn:1000001",
        "tgn:7012149",
        "tgn:2001512",
        "tgn:7007709",
        "tgn:7029392"
    ],
    "tgn:id":2293782,
    "tgn:name":"Doughertys Cove",
    "tgn:placetype":[
        "aat:300132316"
    ]
},
  "bbox": [],
  "geometry": {"coordinates":[-77.4333,35.3333],"type":"Point"}
}