{
  "id": 7381028,
  "type": "Feature",
  "properties": {
    "tgn:hierarchy":[
        "tgn:7381028",
        "tgn:7005586",
        "tgn:1000001",
        "tgn:7005560",
        "tgn:7029392"
    ],
    "tgn:id":7381028,
    "tgn:name":"Mahuapa",
    "tgn:placetype":[
        "aat:300008347"
    ]
},
  "bbox": [],
  "geometry": {"coordinates":[-105.316667,19.916667],"type":"Point"}
}