{
  "id": 2645323,
  "type": "Feature",
  "properties": {
    "tgn:hierarchy":[
        "tgn:2645323",
        "tgn:1000001",
        "tgn:7012149",
        "tgn:2000494",
        "tgn:7007250",
        "tgn:7029392"
    ],
    "tgn:id":2645323,
    "tgn:name":"Savage Point",
    "tgn:placetype":[
        "aat:300008798"
    ]
},
  "bbox": [],
  "geometry": {"coordinates":[-115.5667,45.0667],"type":"Point"}
}