{
  "id": 2556794,
  "type": "Feature",
  "properties": {
    "tgn:hierarchy":[
        "tgn:2556794",
        "tgn:1000001",
        "tgn:7012149",
        "tgn:2001275",
        "tgn:7007524",
        "tgn:7029392"
    ],
    "tgn:id":2556794,
    "tgn:name":"Old Cooper Reservoir",
    "tgn:placetype":[
        "aat:300006191"
    ]
},
  "bbox": [],
  "geometry": {"coordinates":[-110.85,45.55],"type":"Point"}
}