{
  "id": 2538372,
  "type": "Feature",
  "properties": {
    "tgn:hierarchy":[
        "tgn:2538372",
        "tgn:1000001",
        "tgn:7012149",
        "tgn:7007158",
        "tgn:2000242",
        "tgn:7029392"
    ],
    "tgn:id":2538372,
    "tgn:name":"Nepesta Ditch",
    "tgn:placetype":[
        "aat:300006075"
    ]
},
  "bbox": [],
  "geometry": {"coordinates":[-104.2167,38.0833],"type":"Point"}
}