{
  "id": 2050108,
  "type": "Feature",
  "properties": {
    "tgn:hierarchy":[
        "tgn:2050108",
        "tgn:1000001",
        "tgn:1002665",
        "tgn:7012149",
        "tgn:2050105",
        "tgn:7007517",
        "tgn:7029392"
    ],
    "tgn:id":2050108,
    "tgn:name":"Wyoming",
    "tgn:placetype":[
        "aat:300000745"
    ]
},
  "bbox": [],
  "geometry": {"coordinates":[-71.0667,42.45],"type":"Point"}
}