{
  "id": 2426980,
  "type": "Feature",
  "properties": {
    "tgn:hierarchy":[
        "tgn:2426980",
        "tgn:1000001",
        "tgn:7012149",
        "tgn:2001919",
        "tgn:7007825",
        "tgn:7029392"
    ],
    "tgn:id":2426980,
    "tgn:name":"Jones Spring",
    "tgn:placetype":[
        "aat:300008697"
    ]
},
  "bbox": [],
  "geometry": {"coordinates":[-86.6333,36.45],"type":"Point"}
}