{
  "id": 1046115,
  "type": "Feature",
  "properties": {
    "tgn:hierarchy":[
        "tgn:1046115",
        "tgn:7004595",
        "tgn:7003005",
        "tgn:1000003",
        "tgn:1000080",
        "tgn:7029392"
    ],
    "tgn:id":1046115,
    "tgn:name":"Pontelandolfo",
    "tgn:placetype":[
        "aat:300008347"
    ]
},
  "bbox": [],
  "geometry": {"coordinates":[14.683333,41.283333],"type":"Point"}
}