{
  "id": 2509727,
  "type": "Feature",
  "properties": {
    "tgn:hierarchy":[
        "tgn:2509727",
        "tgn:1000001",
        "tgn:2001793",
        "tgn:7012149",
        "tgn:7007713",
        "tgn:7029392"
    ],
    "tgn:id":2509727,
    "tgn:name":"Middle Kneebone Draw",
    "tgn:placetype":[
        "aat:300008701"
    ]
},
  "bbox": [],
  "geometry": {"coordinates":[-103.0333,43.2333],"type":"Point"}
}