{
  "id": 2742014,
  "type": "Feature",
  "properties": {
    "tgn:hierarchy":[
        "tgn:2742014",
        "tgn:1000001",
        "tgn:2002106",
        "tgn:7012149",
        "tgn:7007827",
        "tgn:7029392"
    ],
    "tgn:id":2742014,
    "tgn:name":"Val Verda Condominium",
    "tgn:placetype":[
        "aat:300008347"
    ]
},
  "bbox": [],
  "geometry": {"coordinates":[-111.8833,40.85],"type":"Point"}
}