{
  "id": 2393849,
  "type": "Feature",
  "properties": {
    "tgn:hierarchy":[
        "tgn:2393849",
        "tgn:1000001",
        "tgn:7012149",
        "tgn:2000232",
        "tgn:7007158",
        "tgn:7029392"
    ],
    "tgn:id":2393849,
    "tgn:name":"Hog Lake",
    "tgn:placetype":[
        "aat:300008680"
    ]
},
  "bbox": [],
  "geometry": {"coordinates":[-108.9833,40.8333],"type":"Point"}
}