{
  "id": 2153743,
  "type": "Feature",
  "properties": {
    "tgn:hierarchy":[
        "tgn:2153743",
        "tgn:1000001",
        "tgn:1002360",
        "tgn:7012149",
        "tgn:7007565",
        "tgn:7029392"
    ],
    "tgn:id":2153743,
    "tgn:name":"Bear Brook",
    "tgn:placetype":[
        "aat:300008699"
    ]
},
  "bbox": [],
  "geometry": {"coordinates":[-74.2833,40.7833],"type":"Point"}
}