<<<<<<< HEAD
{
  "id": 2153743,
  "type": "Feature",
  "properties": {
    "tgn:hierarchy":[
        "tgn:2153743",
        "tgn:1000001",
        "tgn:1002360",
        "tgn:7012149",
        "tgn:7007565",
        "tgn:7029392"
    ],
    "tgn:id":2153743,
    "tgn:name":"Bear Brook",
    "tgn:placetype":[
        "aat:300008699"
    ]
},
  "bbox": [],
  "geometry": {"coordinates":[-74.2833,40.7833],"type":"Point"}
}
=======
{"geometry":{"type":"Point","coordinates":[-74.283300,40.783300]},"type":"Feature","properties":{"hierarchy":["tgn:2153743","tgn:1000001","tgn:1002360","tgn:7012149","tgn:7007565","tgn:7029392"],"placetype":["aat:300008699"],"id":2153743,"name:xx":"Bear Brook"}}
>>>>>>> 03f74aca74312dbeaf24d7e61306dd6a786dc3d0
