{
  "id": 2498152,
  "type": "Feature",
  "properties": {
    "tgn:hierarchy":[
        "tgn:2498152",
        "tgn:1000001",
        "tgn:7012149",
        "tgn:2000371",
        "tgn:7007248",
        "tgn:7029392"
    ],
    "tgn:id":2498152,
    "tgn:name":"Maysie",
    "tgn:placetype":[
        "aat:300008347"
    ]
},
  "bbox": [],
  "geometry": {"coordinates":[-82.5333,31.85],"type":"Point"}
}