{
  "id": 2514928,
  "type": "Feature",
  "properties": {
    "tgn:hierarchy":[
        "tgn:2514928",
        "tgn:7002659",
        "tgn:1000001",
        "tgn:7012149",
        "tgn:2000051",
        "tgn:7029392"
    ],
    "tgn:id":2514928,
    "tgn:name":"Miller Spring",
    "tgn:placetype":[
        "aat:300008697"
    ]
},
  "bbox": [],
  "geometry": {"coordinates":[-86.6667,34.45],"type":"Point"}
}