{
  "id": 2438313,
  "type": "Feature",
  "properties": {
    "tgn:hierarchy":[
        "tgn:2438313",
        "tgn:1000001",
        "tgn:1002963",
        "tgn:7012149",
        "tgn:7007565",
        "tgn:7029392"
    ],
    "tgn:id":2438313,
    "tgn:name":"Kings Creek",
    "tgn:placetype":[
        "aat:300008706"
    ]
},
  "bbox": [],
  "geometry": {"coordinates":[-74.25,40.6167],"type":"Point"}
}