{
  "id": 7172317,
  "type": "Feature",
  "properties": {
    "tgn:hierarchy":[
        "tgn:7172317",
        "tgn:7003692",
        "tgn:1000003",
        "tgn:7000084",
        "tgn:7029392"
    ],
    "tgn:id":7172317,
    "tgn:name":"Herrenm\u00fchle",
    "tgn:placetype":[
        "aat:300000206"
    ]
},
  "bbox": [],
  "geometry": {"coordinates":[10.116667,48.116667],"type":"Point"}
}