<<<<<<< HEAD
{
  "id": 7172317,
  "type": "Feature",
  "properties": {
    "tgn:hierarchy":[
        "tgn:7172317",
        "tgn:7003692",
        "tgn:1000003",
        "tgn:7000084",
        "tgn:7029392"
    ],
    "tgn:id":7172317,
    "tgn:name":"Herrenm\u00fchle",
    "tgn:placetype":[
        "aat:300000206"
    ]
},
  "bbox": [],
  "geometry": {"coordinates":[10.116667,48.116667],"type":"Point"}
}
=======
{"geometry":{"type":"Point","coordinates":[10.116667,48.116667]},"type":"Feature","properties":{"hierarchy":["tgn:7172317","tgn:7003692","tgn:1000003","tgn:7000084","tgn:7029392"],"placetype":["aat:300000206"],"id":7172317,"name:xx":"Herrenm\u00fchle"}}
>>>>>>> 03f74aca74312dbeaf24d7e61306dd6a786dc3d0
