{
  "id": 2612041,
  "type": "Feature",
  "properties": {
    "tgn:hierarchy":[
        "tgn:2612041",
        "tgn:1000001",
        "tgn:7012149",
        "tgn:2000737",
        "tgn:7007254",
        "tgn:7029392"
    ],
    "tgn:id":2612041,
    "tgn:name":"Red Rock Creek",
    "tgn:placetype":[
        "aat:300008706"
    ]
},
  "bbox": [],
  "geometry": {"coordinates":[-98.1167,37.9667],"type":"Point"}
}