{
  "id": 2025948,
  "type": "Feature",
  "properties": {
    "tgn:hierarchy":[
        "tgn:2025948",
        "tgn:1000001",
        "tgn:7012149",
        "tgn:2000486",
        "tgn:7007250",
        "tgn:7029392"
    ],
    "tgn:id":2025948,
    "tgn:name":"North Lapwai",
    "tgn:placetype":[
        "aat:300387016"
    ]
},
  "bbox": [],
  "geometry": {"coordinates":[-116.8333,46.4333],"type":"Point"}
}