{
  "id": 2106532,
  "type": "Feature",
  "properties": {
    "tgn:hierarchy":[
        "tgn:2106532",
        "tgn:1000001",
        "tgn:7012149",
        "tgn:2002013",
        "tgn:7007826",
        "tgn:7029392"
    ],
    "tgn:id":2106532,
    "tgn:name":"Orange Grove",
    "tgn:placetype":[
        "aat:300008347"
    ]
},
  "bbox": [],
  "geometry": {"coordinates":[-97.9333,27.95],"type":"Point"}
}