{
  "id": 7226333,
  "type": "Feature",
  "properties": {
    "tgn:hierarchy":[
        "tgn:7226333",
        "tgn:7002735",
        "tgn:7017076",
        "tgn:1000003",
        "tgn:1000074",
        "tgn:7029392"
    ],
    "tgn:id":7226333,
    "tgn:name":"P\u00e1vlia",
    "tgn:placetype":[
        "aat:300008347"
    ]
},
  "bbox": [],
  "geometry": {"coordinates":[22.133333,37.483333],"type":"Point"}
}