{
  "id": 7402391,
  "type": "Feature",
  "properties": {
    "tgn:hierarchy":[
        "tgn:7402391",
        "tgn:1000001",
        "tgn:1001937",
        "tgn:7005560",
        "tgn:7029392"
    ],
    "tgn:id":7402391,
    "tgn:name":"Campameto Veintitres",
    "tgn:placetype":[
        "aat:300008679"
    ]
},
  "bbox": [],
  "geometry": {"coordinates":[-87.883333,18.954167],"type":"Point"}
}