{
  "id": 2150301,
  "type": "Feature",
  "properties": {
    "tgn:hierarchy":[
        "tgn:2150301",
        "tgn:7002659",
        "tgn:1000001",
        "tgn:7012149",
        "tgn:2000064",
        "tgn:7029392"
    ],
    "tgn:id":2150301,
    "tgn:name":"Bashi",
    "tgn:placetype":[
        "aat:300008347"
    ]
},
  "bbox": [],
  "geometry": {"coordinates":[-88.2333,31.65],"type":"Point"}
}