{
  "id": 2222761,
  "type": "Feature",
  "properties": {
    "tgn:hierarchy":[
        "tgn:2222761",
        "tgn:1000001",
        "tgn:7012149",
        "tgn:7007525",
        "tgn:7029392"
    ],
    "tgn:id":2222761,
    "tgn:name":"Carr Lake",
    "tgn:placetype":[
        "aat:300008680"
    ]
},
  "bbox": [],
  "geometry": {"coordinates":[-101.4167,41.9667],"type":"Point"}
}