<<<<<<< HEAD
{
  "id": 2330713,
  "type": "Feature",
  "properties": {
    "tgn:hierarchy":[
        "tgn:2330713",
        "tgn:1000001",
        "tgn:7012149",
        "tgn:2002119",
        "tgn:7007827",
        "tgn:7029392"
    ],
    "tgn:id":2330713,
    "tgn:name":"Flat Iron Mesa",
    "tgn:placetype":[
        "aat:300008798"
    ]
},
  "bbox": [],
  "geometry": {"coordinates":[-109.4667,38.3167],"type":"Point"}
}
=======
{"geometry":{"type":"Point","coordinates":[-109.466700,38.316700]},"type":"Feature","properties":{"hierarchy":["tgn:2330713","tgn:1000001","tgn:7012149","tgn:2002119","tgn:7007827","tgn:7029392"],"placetype":["aat:300008798"],"id":2330713,"name:xx":"Flat Iron Mesa"}}
>>>>>>> 03f74aca74312dbeaf24d7e61306dd6a786dc3d0
