<<<<<<< HEAD
{
  "id": 2152243,
  "type": "Feature",
  "properties": {
    "tgn:hierarchy":[
        "tgn:2152243",
        "tgn:1002933",
        "tgn:1000001",
        "tgn:7012149",
        "tgn:7007239",
        "tgn:7029392"
    ],
    "tgn:id":2152243,
    "tgn:name":"Bay City",
    "tgn:placetype":[
        "aat:300008347"
    ]
},
  "bbox": [],
  "geometry": {"coordinates":[-75.1167,38.6167],"type":"Point"}
}
=======
{"geometry":{"type":"Point","coordinates":[-75.116700,38.616700]},"type":"Feature","properties":{"hierarchy":["tgn:2152243","tgn:1002933","tgn:1000001","tgn:7012149","tgn:7007239","tgn:7029392"],"placetype":["aat:300008347"],"id":2152243,"name:xx":"Bay City"}}
>>>>>>> 03f74aca74312dbeaf24d7e61306dd6a786dc3d0
