{
  "id": 2233798,
  "type": "Feature",
  "properties": {
    "tgn:hierarchy":[
        "tgn:2233798",
        "tgn:7006450",
        "tgn:1000001",
        "tgn:7019698",
        "tgn:7012149",
        "tgn:7029392"
    ],
    "tgn:id":2233798,
    "tgn:name":"Chat Cove",
    "tgn:placetype":[
        "aat:300132316"
    ]
},
  "bbox": [],
  "geometry": {"coordinates":[-149.55,59.7167],"type":"Point"}
}