{
  "id": 7417728,
  "type": "Feature",
  "properties": {
    "tgn:hierarchy":[
        "tgn:7417728",
        "tgn:1000001",
        "tgn:7005596",
        "tgn:7005560",
        "tgn:7029392"
    ],
    "tgn:id":7417728,
    "tgn:name:es":"La Union Segunda Secci\u00f3n",
    "tgn:placetype":[
        "aat:300008347"
    ]
},
  "bbox": [],
  "geometry": {"coordinates":[-93.366667,18.429167],"type":"Point"}
}