{
  "id": 2564785,
  "type": "Feature",
  "properties": {
    "tgn:hierarchy":[
        "tgn:2564785",
        "tgn:1000001",
        "tgn:7012149",
        "tgn:2001437",
        "tgn:7007566",
        "tgn:7029392"
    ],
    "tgn:id":2564785,
    "tgn:name":"Paddy Ford Shaft",
    "tgn:placetype":[
        "aat:300000390"
    ]
},
  "bbox": [],
  "geometry": {"coordinates":[-108.35,32.55],"type":"Point"}
}