{
  "id": 2199628,
  "type": "Feature",
  "properties": {
    "tgn:hierarchy":[
        "tgn:2199628",
        "tgn:1000001",
        "tgn:7012149",
        "tgn:2001312",
        "tgn:7007524",
        "tgn:7029392"
    ],
    "tgn:id":2199628,
    "tgn:name":"Brush Fork",
    "tgn:placetype":[
        "aat:300008699"
    ]
},
  "bbox": [],
  "geometry": {"coordinates":[-106.8333,48.5333],"type":"Point"}
}