{
  "id": 2224277,
  "type": "Feature",
  "properties": {
    "tgn:hierarchy":[
        "tgn:2224277",
        "tgn:1000001",
        "tgn:7012149",
        "tgn:2001714",
        "tgn:7007708",
        "tgn:7029392"
    ],
    "tgn:id":2224277,
    "tgn:name":"Cascade Canal",
    "tgn:placetype":[
        "aat:300006075"
    ]
},
  "bbox": [],
  "geometry": {"coordinates":[-122.2333,42.4167],"type":"Point"}
}