{
  "id": 7318375,
  "type": "Feature",
  "properties": {
    "tgn:hierarchy":[
        "tgn:7318375",
        "tgn:1001692",
        "tgn:1000049",
        "tgn:1000002",
        "tgn:7029392"
    ],
    "tgn:id":7318375,
    "tgn:name":"Colo, Estero",
    "tgn:placetype":[
        "aat:300008699"
    ]
},
  "bbox": [],
  "geometry": {"coordinates":[-72.416667,-38.183333],"type":"Point"}
}