{
  "id": 2712956,
  "type": "Feature",
  "properties": {
    "tgn:hierarchy":[
        "tgn:2712956",
        "tgn:1000001",
        "tgn:7016102",
        "tgn:7012149",
        "tgn:7007516",
        "tgn:7029392"
    ],
    "tgn:id":2712956,
    "tgn:name":"Taylor Island",
    "tgn:placetype":[
        "aat:300008791"
    ]
},
  "bbox": [],
  "geometry": {"coordinates":[-76.1667,39.3833],"type":"Point"}
}