{
  "id": 2460158,
  "type": "Feature",
  "properties": {
    "tgn:hierarchy":[
        "tgn:2460158",
        "tgn:1000001",
        "tgn:7012149",
        "tgn:7007157",
        "tgn:2000188",
        "tgn:7029392"
    ],
    "tgn:id":2460158,
    "tgn:name":"Little Round Mountain",
    "tgn:placetype":[
        "aat:300008798"
    ]
},
  "bbox": [],
  "geometry": {"coordinates":[-122.9167,40.35],"type":"Point"}
}