{
  "id": 2542910,
  "type": "Feature",
  "properties": {
    "tgn:hierarchy":[
        "tgn:2542910",
        "tgn:1000001",
        "tgn:7016101",
        "tgn:7012149",
        "tgn:7007516",
        "tgn:7029392"
    ],
    "tgn:id":2542910,
    "tgn:name":"Nolands Island",
    "tgn:placetype":[
        "aat:300008791"
    ]
},
  "bbox": [],
  "geometry": {"coordinates":[-77.4833,39.25],"type":"Point"}
}