{
  "id": 7304745,
  "type": "Feature",
  "properties": {
    "tgn:hierarchy":[
        "tgn:7304745",
        "tgn:7001165",
        "tgn:1000003",
        "tgn:7002793",
        "tgn:1000095",
        "tgn:7029392"
    ],
    "tgn:id":7304745,
    "tgn:name":"La Yesa",
    "tgn:placetype":[
        "aat:300008347"
    ]
},
  "bbox": [],
  "geometry": {"coordinates":[-0.95,39.883333],"type":"Point"}
}