{
  "id": 1056197,
  "type": "Feature",
  "properties": {
    "tgn:hierarchy":[
        "tgn:1056197",
        "tgn:1000004",
        "tgn:7002435",
        "tgn:7011526",
        "tgn:7029392"
    ],
    "tgn:id":1056197,
    "tgn:name":"Kvarsa",
    "tgn:placetype":[
        "aat:300008347"
    ]
},
  "bbox": [],
  "geometry": {"coordinates":[53.95,56.9667],"type":"Point"}
}