{
  "id": 7520983,
  "type": "Feature",
  "properties": {
    "tgn:hierarchy":[
        "tgn:7520983",
        "tgn:7001242",
        "tgn:1001075",
        "tgn:7016833",
        "tgn:7029392"
    ],
    "tgn:id":7520983,
    "tgn:name:en":"Ab\u016b ar R\u012bsh",
    "tgn:placetype":[
        "aat:300007783"
    ]
},
  "bbox": [],
  "geometry": {"coordinates":[30.483333,31.033333],"type":"Point"}
}