{
  "id": 2442026,
  "type": "Feature",
  "properties": {
    "tgn:hierarchy":[
        "tgn:2442026",
        "tgn:1000001",
        "tgn:7012149",
        "tgn:2002304",
        "tgn:7013961",
        "tgn:7029392"
    ],
    "tgn:id":2442026,
    "tgn:name":"Kopperston Number Three Impoundment Number Two",
    "tgn:placetype":[
        "aat:300006191"
    ]
},
  "bbox": [],
  "geometry": {"coordinates":[-81.55,37.75],"type":"Point"}
}