{
  "id": 2624940,
  "type": "Feature",
  "properties": {
    "tgn:hierarchy":[
        "tgn:2624940",
        "tgn:1000001",
        "tgn:7012149",
        "tgn:2002044",
        "tgn:7007826",
        "tgn:7029392"
    ],
    "tgn:id":2624940,
    "tgn:name":"Rock Springs Creek",
    "tgn:placetype":[
        "aat:300008706"
    ]
},
  "bbox": [],
  "geometry": {"coordinates":[-97.5833,33.8333],"type":"Point"}
}