<<<<<<< HEAD
{
  "id": 7247103,
  "type": "Feature",
  "properties": {
    "tgn:hierarchy":[
        "tgn:7247103",
        "tgn:7003460",
        "tgn:1000003",
        "tgn:1000063",
        "tgn:4012014",
        "tgn:7029392"
    ],
    "tgn:id":7247103,
    "tgn:name":"Ch\u00e2teau de Chaityfontaine",
    "tgn:placetype":[
        "aat:300005567"
    ]
},
  "bbox": [],
  "geometry": {"coordinates":[5.75,50.55],"type":"Point"}
}
=======
{"geometry":{"type":"Point","coordinates":[5.750000,50.550000]},"type":"Feature","properties":{"hierarchy":["tgn:7247103","tgn:7003460","tgn:1000003","tgn:1000063","tgn:4012014","tgn:7029392"],"placetype":["aat:300005567"],"id":7247103,"name:xx":"Ch\u00e2teau de Chaityfontaine"}}
>>>>>>> 03f74aca74312dbeaf24d7e61306dd6a786dc3d0
