<<<<<<< HEAD
{
  "id": 7050514,
  "type": "Feature",
  "properties": {
    "tgn:hierarchy":[
        "tgn:7050514",
        "tgn:1003460",
        "tgn:1000003",
        "tgn:7009760",
        "tgn:1000080",
        "tgn:7029392"
    ],
    "tgn:id":7050514,
    "tgn:name":"Sabatina",
    "tgn:placetype":[
        "aat:300008347"
    ]
},
  "bbox": [],
  "geometry": {"coordinates":[11.3,42.8],"type":"Point"}
}
=======
{"geometry":{"type":"Point","coordinates":[11.300000,42.800000]},"type":"Feature","properties":{"hierarchy":["tgn:7050514","tgn:1003460","tgn:1000003","tgn:7009760","tgn:1000080","tgn:7029392"],"placetype":["aat:300008347"],"id":7050514,"name:xx":"Sabatina"}}
>>>>>>> 03f74aca74312dbeaf24d7e61306dd6a786dc3d0
