<<<<<<< HEAD
{
  "id": 2400084,
  "type": "Feature",
  "properties": {
    "tgn:hierarchy":[
        "tgn:2400084",
        "tgn:1000001",
        "tgn:7012149",
        "tgn:7007522",
        "tgn:7029392"
    ],
    "tgn:id":2400084,
    "tgn:name":"Horse Creek",
    "tgn:placetype":[
        "aat:300008706"
    ]
},
  "bbox": [],
  "geometry": {"coordinates":[-90.6167,31.4333],"type":"Point"}
}
=======
{"geometry":{"type":"Point","coordinates":[-90.616700,31.433300]},"type":"Feature","properties":{"hierarchy":["tgn:2400084","tgn:1000001","tgn:7012149","tgn:7007522","tgn:7029392"],"placetype":["aat:300008706"],"id":2400084,"name:xx":"Horse Creek"}}
>>>>>>> 03f74aca74312dbeaf24d7e61306dd6a786dc3d0
