{
  "id": 2400084,
  "type": "Feature",
  "properties": {
    "tgn:hierarchy":[
        "tgn:2400084",
        "tgn:1000001",
        "tgn:7012149",
        "tgn:7007522",
        "tgn:7029392"
    ],
    "tgn:id":2400084,
    "tgn:name":"Horse Creek",
    "tgn:placetype":[
        "aat:300008706"
    ]
},
  "bbox": [],
  "geometry": {"coordinates":[-90.6167,31.4333],"type":"Point"}
}