{
  "id": 7544776,
  "type": "Feature",
  "properties": {
    "tgn:hierarchy":[
        "tgn:7544776",
        "tgn:1000004",
        "tgn:1001832",
        "tgn:7000198",
        "tgn:7029392"
    ],
    "tgn:id":7544776,
    "tgn:name:en":"B\u0101raigr\u0101m",
    "tgn:placetype":[
        "aat:300007783"
    ]
},
  "bbox": [],
  "geometry": {"coordinates":[92.341553,24.683438],"type":"Point"}
}