{
  "id": 7588845,
  "type": "Feature",
  "properties": {
    "tgn:hierarchy":[
        "tgn:7588845",
        "tgn:1000004",
        "tgn:7000198",
        "tgn:7000799",
        "tgn:7029392"
    ],
    "tgn:id":7588845,
    "tgn:name:en":"Mela",
    "tgn:placetype":[
        "aat:300008347"
    ]
},
  "bbox": [],
  "geometry": {"coordinates":[74.040275,33.196005],"type":"Point"}
}