<<<<<<< HEAD
{
  "id": 2401887,
  "type": "Feature",
  "properties": {
    "tgn:hierarchy":[
        "tgn:2401887",
        "tgn:1000001",
        "tgn:7012149",
        "tgn:2002092",
        "tgn:7007826",
        "tgn:7029392"
    ],
    "tgn:id":2401887,
    "tgn:name":"Horseshoe Lake",
    "tgn:placetype":[
        "aat:300006191"
    ]
},
  "bbox": [],
  "geometry": {"coordinates":[-98.6167,33.9],"type":"Point"}
}
=======
{"geometry":{"type":"Point","coordinates":[-98.616700,33.900000]},"type":"Feature","properties":{"hierarchy":["tgn:2401887","tgn:1000001","tgn:7012149","tgn:2002092","tgn:7007826","tgn:7029392"],"placetype":["aat:300006191"],"id":2401887,"name:xx":"Horseshoe Lake"}}
>>>>>>> 03f74aca74312dbeaf24d7e61306dd6a786dc3d0
