{
  "id": 2743449,
  "type": "Feature",
  "properties": {
    "tgn:hierarchy":[
        "tgn:2743449",
        "tgn:1000001",
        "tgn:2001009",
        "tgn:7012149",
        "tgn:7007521",
        "tgn:7029392"
    ],
    "tgn:id":2743449,
    "tgn:name":"Variety Lake",
    "tgn:placetype":[
        "aat:300008680"
    ]
},
  "bbox": [],
  "geometry": {"coordinates":[-94.6167,46.8833],"type":"Point"}
}