{
  "id": 7346684,
  "type": "Feature",
  "properties": {
    "tgn:hierarchy":[
        "tgn:7346684",
        "tgn:7001165",
        "tgn:1000003",
        "tgn:7002793",
        "tgn:1000095",
        "tgn:7029392"
    ],
    "tgn:id":7346684,
    "tgn:name":"B\u00e9lgida",
    "tgn:placetype":[
        "aat:300008347"
    ]
},
  "bbox": [],
  "geometry": {"coordinates":[-0.466667,38.85],"type":"Point"}
}