{
  "id": 1009344,
  "type": "Feature",
  "properties": {
    "tgn:hierarchy":[
        "tgn:1009344",
        "tgn:7006215",
        "tgn:1000216",
        "tgn:1000006",
        "tgn:7029392"
    ],
    "tgn:id":1009344,
    "tgn:name":"Tahuata",
    "tgn:placetype":[
        "aat:300008791"
    ]
},
  "bbox": [],
  "geometry": {"coordinates":[-139.0833,-9.9667],"type":"Point"}
}