<<<<<<< HEAD
{
  "id": 7487552,
  "type": "Feature",
  "properties": {
    "tgn:hierarchy":[
        "tgn:7487552",
        "tgn:1000004",
        "tgn:1000454",
        "tgn:1000141",
        "tgn:7029392"
    ],
    "tgn:id":7487552,
    "tgn:name":"Huangxitou",
    "tgn:placetype":[
        "aat:300008347"
    ]
},
  "bbox": [],
  "geometry": {"coordinates":[121.593246,25.211971],"type":"Point"}
}
=======
{"geometry":{"type":"Point","coordinates":[121.593246,25.211971]},"type":"Feature","properties":{"hierarchy":["tgn:7487552","tgn:1000004","tgn:1000454","tgn:1000141","tgn:7029392"],"placetype":["aat:300008347"],"id":7487552,"name:xx":"Huangxitou"}}
>>>>>>> 03f74aca74312dbeaf24d7e61306dd6a786dc3d0
