{
  "id": 7487552,
  "type": "Feature",
  "properties": {
    "tgn:hierarchy":[
        "tgn:7487552",
        "tgn:1000004",
        "tgn:1000454",
        "tgn:1000141",
        "tgn:7029392"
    ],
    "tgn:id":7487552,
    "tgn:name":"Huangxitou",
    "tgn:placetype":[
        "aat:300008347"
    ]
},
  "bbox": [],
  "geometry": {"coordinates":[121.593246,25.211971],"type":"Point"}
}