{
  "id": 2321790,
  "type": "Feature",
  "properties": {
    "tgn:hierarchy":[
        "tgn:2321790",
        "tgn:1000001",
        "tgn:7012149",
        "tgn:2001275",
        "tgn:7007524",
        "tgn:7029392"
    ],
    "tgn:id":2321790,
    "tgn:name":"Fairy Creek",
    "tgn:placetype":[
        "aat:300008706"
    ]
},
  "bbox": [],
  "geometry": {"coordinates":[-110.9667,45.9167],"type":"Point"}
}