{
  "id": 2627462,
  "type": "Feature",
  "properties": {
    "tgn:hierarchy":[
        "tgn:2627462",
        "tgn:1000001",
        "tgn:7012149",
        "tgn:2000285",
        "tgn:7007240",
        "tgn:7029392"
    ],
    "tgn:id":2627462,
    "tgn:name":"Roeville",
    "tgn:placetype":[
        "aat:300008347"
    ]
},
  "bbox": [],
  "geometry": {"coordinates":[-86.9833,30.6667],"type":"Point"}
}