{
  "id": 2128212,
  "type": "Feature",
  "properties": {
    "tgn:hierarchy":[
        "tgn:2128212",
        "tgn:1000001",
        "tgn:7012149",
        "tgn:1002392",
        "tgn:7007157",
        "tgn:7029392"
    ],
    "tgn:id":2128212,
    "tgn:name":"Alcalde Hills",
    "tgn:placetype":[
        "aat:300008798"
    ]
},
  "bbox": [],
  "geometry": {"coordinates":[-120.4333,36.1667],"type":"Point"}
}