{
  "id": 7221242,
  "type": "Feature",
  "properties": {
    "tgn:hierarchy":[
        "tgn:7221242",
        "tgn:7011164",
        "tgn:7002674",
        "tgn:1000003",
        "tgn:1000074",
        "tgn:7029392"
    ],
    "tgn:id":7221242,
    "tgn:name":"Amf\u00edlysos Potam\u00f3s",
    "tgn:placetype":[
        "aat:300008699"
    ]
},
  "bbox": [],
  "geometry": {"coordinates":[26.741667,37.697778],"type":"Point"}
}