{
  "id": 1081705,
  "type": "Feature",
  "properties": {
    "tgn:hierarchy":[
        "tgn:1081705",
        "tgn:1001015",
        "tgn:7000897",
        "tgn:1000004",
        "tgn:1000120",
        "tgn:7029392"
    ],
    "tgn:id":1081705,
    "tgn:name":"Wake",
    "tgn:placetype":[
        "aat:300008347"
    ]
},
  "bbox": [],
  "geometry": {"coordinates":[134.1667,34.8333],"type":"Point"}
}