{
  "id": 2186936,
  "type": "Feature",
  "properties": {
    "tgn:hierarchy":[
        "tgn:2186936",
        "tgn:1000001",
        "tgn:7012149",
        "tgn:2000226",
        "tgn:7007158",
        "tgn:7029392"
    ],
    "tgn:id":2186936,
    "tgn:name":"Bonner Spring",
    "tgn:placetype":[
        "aat:300008697"
    ]
},
  "bbox": [],
  "geometry": {"coordinates":[-105.1833,40.75],"type":"Point"}
}