{
  "id": 7490416,
  "type": "Feature",
  "properties": {
    "tgn:hierarchy":[
        "tgn:7490416",
        "tgn:1000004",
        "tgn:7492971",
        "tgn:1000141",
        "tgn:7029392"
    ],
    "tgn:id":7490416,
    "tgn:name":"Shiniu Qiao",
    "tgn:placetype":[
        "aat:300007836"
    ]
},
  "bbox": [],
  "geometry": {"coordinates":[120.785,21.945833],"type":"Point"}
}