{
  "id": 7170905,
  "type": "Feature",
  "properties": {
    "tgn:hierarchy":[
        "tgn:7170905",
        "tgn:1000003",
        "tgn:7003676",
        "tgn:7000084",
        "tgn:7029392"
    ],
    "tgn:id":7170905,
    "tgn:name":"Himmelreich",
    "tgn:placetype":[
        "aat:300008777"
    ]
},
  "bbox": [],
  "geometry": {"coordinates":[10.633333,51.583333],"type":"Point"}
}