<<<<<<< HEAD
{
  "id": 7350120,
  "type": "Feature",
  "properties": {
    "tgn:hierarchy":[
        "tgn:7350120",
        "tgn:1001853",
        "tgn:1000001",
        "tgn:7005560",
        "tgn:7029392"
    ],
    "tgn:id":7350120,
    "tgn:name":"Adjuntas",
    "tgn:placetype":[
        "aat:300007783"
    ]
},
  "bbox": [],
  "geometry": {"coordinates":[-101.35,27.05],"type":"Point"}
}
=======
{"geometry":{"type":"Point","coordinates":[-101.350000,27.050000]},"type":"Feature","properties":{"hierarchy":["tgn:7350120","tgn:1001853","tgn:1000001","tgn:7005560","tgn:7029392"],"placetype":["aat:300007783"],"id":7350120,"name:xx":"Adjuntas"}}
>>>>>>> 03f74aca74312dbeaf24d7e61306dd6a786dc3d0
