{
  "id": 7057860,
  "type": "Feature",
  "properties": {
    "tgn:hierarchy":[
        "tgn:7057860",
        "tgn:1000003",
        "tgn:7003122",
        "tgn:1000080",
        "tgn:7029392"
    ],
    "tgn:id":7057860,
    "tgn:name":"Arenella, Punta",
    "tgn:placetype":[
        "aat:300386846"
    ]
},
  "bbox": [],
  "geometry": {"coordinates":[13.366667,38.15],"type":"Point"}
}