{
  "id": 1006654,
  "type": "Feature",
  "properties": {
    "tgn:hierarchy":[
        "tgn:1006654",
        "tgn:1000004",
        "tgn:7000198",
        "tgn:1001895",
        "tgn:1114421",
        "tgn:7029392"
    ],
    "tgn:id":1006654,
    "tgn:name:en":"Butcher Island",
    "tgn:placetype":[
        "aat:300008791"
    ]
},
  "bbox": [],
  "geometry": {"coordinates":[72.9025,18.959167],"type":"Point"}
}