{
  "id": 2481692,
  "type": "Feature",
  "properties": {
    "tgn:hierarchy":[
        "tgn:2481692",
        "tgn:1000001",
        "tgn:2001419",
        "tgn:7012149",
        "tgn:7007526",
        "tgn:7029392"
    ],
    "tgn:id":2481692,
    "tgn:name":"Lander City",
    "tgn:placetype":[
        "aat:300008347",
        "aat:300167671"
    ]
},
  "bbox": [],
  "geometry": {"coordinates":[-118.1333,40.6833],"type":"Point"}
}