{
  "id": 1076138,
  "type": "Feature",
  "properties": {
    "tgn:hierarchy":[
        "tgn:1076138",
        "tgn:1000004",
        "tgn:7000198",
        "tgn:7016788",
        "tgn:7029392"
    ],
    "tgn:id":1076138,
    "tgn:name:en":"Mahwah",
    "tgn:placetype":[
        "aat:300008347"
    ]
},
  "bbox": [],
  "geometry": {"coordinates":[76.931522,27.045937],"type":"Point"}
}