{
  "id": 7277702,
  "type": "Feature",
  "properties": {
    "tgn:hierarchy":[
        "tgn:7277702",
        "tgn:1001623",
        "tgn:1000049",
        "tgn:1000002",
        "tgn:7029392"
    ],
    "tgn:id":7277702,
    "tgn:name":"R\u00edo Cuevas",
    "tgn:placetype":[
        "aat:300008699"
    ]
},
  "bbox": [],
  "geometry": {"coordinates":[-73.258611,-43.948889],"type":"Point"}
}