{
  "id": 7217661,
  "type": "Feature",
  "properties": {
    "tgn:hierarchy":[
        "tgn:7217661",
        "tgn:7011164",
        "tgn:7002674",
        "tgn:1000003",
        "tgn:1000074",
        "tgn:7029392"
    ],
    "tgn:id":7217661,
    "tgn:name":"Psil\u00ed \u00c1mmos, \u00d3rmos",
    "tgn:placetype":[
        "aat:300185707"
    ]
},
  "bbox": [],
  "geometry": {"coordinates":[27.021944,37.703889],"type":"Point"}
}