{
  "id": 2755429,
  "type": "Feature",
  "properties": {
    "tgn:hierarchy":[
        "tgn:2755429",
        "tgn:1000001",
        "tgn:7012149",
        "tgn:2001036",
        "tgn:7007521",
        "tgn:7029392"
    ],
    "tgn:id":2755429,
    "tgn:name":"Webfoot Lake",
    "tgn:placetype":[
        "aat:300008680"
    ]
},
  "bbox": [],
  "geometry": {"coordinates":[-91.75,48.1167],"type":"Point"}
}