{
  "id": 2692730,
  "type": "Feature",
  "properties": {
    "tgn:hierarchy":[
        "tgn:2692730",
        "tgn:1000001",
        "tgn:7012149",
        "tgn:7007525",
        "tgn:7029392"
    ],
    "tgn:id":2692730,
    "tgn:name":"Steel Creek",
    "tgn:placetype":[
        "aat:300008706"
    ]
},
  "bbox": [],
  "geometry": {"coordinates":[-98.3833,42.6167],"type":"Point"}
}