{
  "id": 7094162,
  "type": "Feature",
  "properties": {
    "tgn:hierarchy":[
        "tgn:7094162",
        "tgn:7003669",
        "tgn:1000003",
        "tgn:7000084",
        "tgn:7029392"
    ],
    "tgn:id":7094162,
    "tgn:name":"Naturschutzgebiet Schwarzes Moor",
    "tgn:placetype":[
        "aat:300008178"
    ]
},
  "bbox": [],
  "geometry": {"coordinates":[10.066667,50.516667],"type":"Point"}
}