{
  "id": 2392655,
  "type": "Feature",
  "properties": {
    "tgn:hierarchy":[
        "tgn:2392655",
        "tgn:1000001",
        "tgn:7012149",
        "tgn:2002382",
        "tgn:7007923",
        "tgn:7029392"
    ],
    "tgn:id":2392655,
    "tgn:name":"Hoback Basin",
    "tgn:placetype":[
        "aat:300386845"
    ]
},
  "bbox": [],
  "geometry": {"coordinates":[-110.4167,43.2167],"type":"Point"}
}