{
  "id": 2539153,
  "type": "Feature",
  "properties": {
    "tgn:hierarchy":[
        "tgn:2539153",
        "tgn:1000001",
        "tgn:7012149",
        "tgn:2001227",
        "tgn:7007523",
        "tgn:7029392"
    ],
    "tgn:id":2539153,
    "tgn:name":"New Franklin Ditch",
    "tgn:placetype":[
        "aat:300006075"
    ]
},
  "bbox": [],
  "geometry": {"coordinates":[-89.75,36.0667],"type":"Point"}
}