{
  "id": 1042887,
  "type": "Feature",
  "properties": {
    "tgn:hierarchy":[
        "tgn:1042887",
        "tgn:7001199",
        "tgn:7003491",
        "tgn:1000003",
        "tgn:1000078",
        "tgn:7029392"
    ],
    "tgn:id":1042887,
    "tgn:name":"Kinnegad",
    "tgn:placetype":[
        "aat:300008347"
    ]
},
  "bbox": [],
  "geometry": {"coordinates":[-7.0833,53.45],"type":"Point"}
}