{
  "id": 2636447,
  "type": "Feature",
  "properties": {
    "tgn:hierarchy":[
        "tgn:2636447",
        "tgn:2001837",
        "tgn:1000001",
        "tgn:7012149",
        "tgn:7007825",
        "tgn:7029392"
    ],
    "tgn:id":2636447,
    "tgn:name":"Sagamine Mine",
    "tgn:placetype":[
        "aat:300000390"
    ]
},
  "bbox": [],
  "geometry": {"coordinates":[-84.3833,36.1333],"type":"Point"}
}