<<<<<<< HEAD
{
  "id": 2150806,
  "type": "Feature",
  "properties": {
    "tgn:hierarchy":[
        "tgn:2150806",
        "tgn:1000001",
        "tgn:7012149",
        "tgn:2000968",
        "tgn:7007520",
        "tgn:7029392"
    ],
    "tgn:id":2150806,
    "tgn:name":"Bass Lake",
    "tgn:placetype":[
        "aat:300008680"
    ]
},
  "bbox": [],
  "geometry": {"coordinates":[-85.2,44.65],"type":"Point"}
}
=======
{"geometry":{"type":"Point","coordinates":[-85.200000,44.650000]},"type":"Feature","properties":{"hierarchy":["tgn:2150806","tgn:1000001","tgn:7012149","tgn:2000968","tgn:7007520","tgn:7029392"],"placetype":["aat:300008680"],"id":2150806,"name:xx":"Bass Lake"}}
>>>>>>> 03f74aca74312dbeaf24d7e61306dd6a786dc3d0
