{
  "id": 2182679,
  "type": "Feature",
  "properties": {
    "tgn:hierarchy":[
        "tgn:2182679",
        "tgn:1000001",
        "tgn:7012149",
        "tgn:7007255",
        "tgn:7029392"
    ],
    "tgn:id":2182679,
    "tgn:name":"Blue Spring Branch",
    "tgn:placetype":[
        "aat:300008699"
    ]
},
  "bbox": [],
  "geometry": {"coordinates":[-85.3833,37.15],"type":"Point"}
}