{
  "id": 7324621,
  "type": "Feature",
  "properties": {
    "tgn:hierarchy":[
        "tgn:7324621",
        "tgn:7002826",
        "tgn:7001158",
        "tgn:1000003",
        "tgn:1000095",
        "tgn:7029392"
    ],
    "tgn:id":7324621,
    "tgn:name":"San Esteban de Villacalbiel",
    "tgn:placetype":[
        "aat:300008347"
    ]
},
  "bbox": [],
  "geometry": {"coordinates":[-5.616667,42.366667],"type":"Point"}
}