{
  "id": 2222085,
  "type": "Feature",
  "properties": {
    "tgn:hierarchy":[
        "tgn:2222085",
        "tgn:1000001",
        "tgn:7012149",
        "tgn:2000336",
        "tgn:7007248",
        "tgn:7029392"
    ],
    "tgn:id":2222085,
    "tgn:name":"Carne",
    "tgn:placetype":[
        "aat:300008347"
    ]
},
  "bbox": [],
  "geometry": {"coordinates":[-83.2667,32.3167],"type":"Point"}
}