{
  "id": 2536029,
  "type": "Feature",
  "properties": {
    "tgn:hierarchy":[
        "tgn:2536029",
        "tgn:1000001",
        "tgn:7012149",
        "tgn:7007157",
        "tgn:2000189",
        "tgn:7029392"
    ],
    "tgn:id":2536029,
    "tgn:name":"Natuket Creek",
    "tgn:placetype":[
        "aat:300008706"
    ]
},
  "bbox": [],
  "geometry": {"coordinates":[-123.5333,41.3833],"type":"Point"}
}