{
  "id": 1065510,
  "type": "Feature",
  "properties": {
    "tgn:hierarchy":[
        "tgn:1065510",
        "tgn:7016612",
        "tgn:1000004",
        "tgn:1001608",
        "tgn:7029392"
    ],
    "tgn:id":1065510,
    "tgn:name":"Rashid Qaleh",
    "tgn:placetype":[
        "aat:300008347"
    ]
},
  "bbox": [],
  "geometry": {"coordinates":[67.5167,31.5167],"type":"Point"}
}