{
  "id": 2416472,
  "type": "Feature",
  "properties": {
    "tgn:hierarchy":[
        "tgn:2416472",
        "tgn:1000001",
        "tgn:1002477",
        "tgn:7012149",
        "tgn:7007240",
        "tgn:7029392"
    ],
    "tgn:id":2416472,
    "tgn:name":"Jack Creek",
    "tgn:placetype":[
        "aat:300008706"
    ]
},
  "bbox": [],
  "geometry": {"coordinates":[-81.4167,27.3333],"type":"Point"}
}