{
  "id": 2227475,
  "type": "Feature",
  "properties": {
    "tgn:hierarchy":[
        "tgn:2227475",
        "tgn:2001170",
        "tgn:1000001",
        "tgn:7012149",
        "tgn:7007523",
        "tgn:7029392"
    ],
    "tgn:id":2227475,
    "tgn:name":"Cave Spring Hollow",
    "tgn:placetype":[
        "aat:300008761"
    ]
},
  "bbox": [],
  "geometry": {"coordinates":[-93.6333,36.7667],"type":"Point"}
}