<<<<<<< HEAD
{
  "id": 2152124,
  "type": "Feature",
  "properties": {
    "tgn:hierarchy":[
        "tgn:2152124",
        "tgn:1000001",
        "tgn:7012149",
        "tgn:2001896",
        "tgn:7007825",
        "tgn:7029392"
    ],
    "tgn:id":2152124,
    "tgn:name":"Baxter Hill",
    "tgn:placetype":[
        "aat:300008798"
    ]
},
  "bbox": [],
  "geometry": {"coordinates":[-87.2833,35.65],"type":"Point"}
}
=======
{"geometry":{"type":"Point","coordinates":[-87.283300,35.650000]},"type":"Feature","properties":{"hierarchy":["tgn:2152124","tgn:1000001","tgn:7012149","tgn:2001896","tgn:7007825","tgn:7029392"],"placetype":["aat:300008798"],"id":2152124,"name:xx":"Baxter Hill"}}
>>>>>>> 03f74aca74312dbeaf24d7e61306dd6a786dc3d0
