{
  "id": 2668743,
  "type": "Feature",
  "properties": {
    "tgn:hierarchy":[
        "tgn:2668743",
        "tgn:1002808",
        "tgn:1000001",
        "tgn:7012149",
        "tgn:7007711",
        "tgn:7029392"
    ],
    "tgn:id":2668743,
    "tgn:name":"Slatersville Reservoir Upper",
    "tgn:placetype":[
        "aat:300006191"
    ]
},
  "bbox": [],
  "geometry": {"coordinates":[-71.5833,41.9833],"type":"Point"}
}