<<<<<<< HEAD
{
  "id": 2334021,
  "type": "Feature",
  "properties": {
    "tgn:hierarchy":[
        "tgn:2334021",
        "tgn:1000001",
        "tgn:7012149",
        "tgn:1009018",
        "tgn:7007157",
        "tgn:1002867",
        "tgn:7029392"
    ],
    "tgn:id":2334021,
    "tgn:name":"Ford Point",
    "tgn:placetype":[
        "aat:300008850"
    ]
},
  "bbox": [],
  "geometry": {"coordinates":[-120.0333,33.9],"type":"Point"}
}
=======
{"geometry":{"type":"Point","coordinates":[-120.033300,33.900000]},"type":"Feature","properties":{"hierarchy":["tgn:2334021","tgn:1000001","tgn:7012149","tgn:1009018","tgn:7007157","tgn:1002867","tgn:7029392"],"placetype":["aat:300008850"],"id":2334021,"name:xx":"Ford Point"}}
>>>>>>> 03f74aca74312dbeaf24d7e61306dd6a786dc3d0
