{
  "id": 7532596,
  "type": "Feature",
  "properties": {
    "tgn:hierarchy":[
        "tgn:7532596",
        "tgn:7001242",
        "tgn:7016833",
        "tgn:1001091",
        "tgn:7029392"
    ],
    "tgn:id":7532596,
    "tgn:name":"N\u0101d\u012b ash Shams",
    "tgn:placetype":[
        "aat:300004792"
    ]
},
  "bbox": [],
  "geometry": {"coordinates":[31.345851,30.119804],"type":"Point"}
}