{
  "id": 7100714,
  "type": "Feature",
  "properties": {
    "tgn:hierarchy":[
        "tgn:7100714",
        "tgn:1000003",
        "tgn:7003688",
        "tgn:7000084",
        "tgn:7029392"
    ],
    "tgn:id":7100714,
    "tgn:name":"Sand-Berg",
    "tgn:placetype":[
        "aat:300008777"
    ]
},
  "bbox": [],
  "geometry": {"coordinates":[10.683333,53.666667],"type":"Point"}
}