<<<<<<< HEAD
{
  "id": 2259294,
  "type": "Feature",
  "properties": {
    "tgn:hierarchy":[
        "tgn:2259294",
        "tgn:7006450",
        "tgn:1000001",
        "tgn:7012149",
        "tgn:2000086",
        "tgn:7029392"
    ],
    "tgn:id":2259294,
    "tgn:name":"Cottonwood Point",
    "tgn:placetype":[
        "aat:300008850"
    ]
},
  "bbox": [],
  "geometry": {"coordinates":[-144.9167,60.2833],"type":"Point"}
}
=======
{"geometry":{"type":"Point","coordinates":[-144.916700,60.283300]},"type":"Feature","properties":{"hierarchy":["tgn:2259294","tgn:7006450","tgn:1000001","tgn:7012149","tgn:2000086","tgn:7029392"],"placetype":["aat:300008850"],"id":2259294,"name:xx":"Cottonwood Point"}}
>>>>>>> 03f74aca74312dbeaf24d7e61306dd6a786dc3d0
