{
  "id": 2773613,
  "type": "Feature",
  "properties": {
    "tgn:hierarchy":[
        "tgn:2773613",
        "tgn:1000001",
        "tgn:7012149",
        "tgn:7022201",
        "tgn:7007919",
        "tgn:7029392"
    ],
    "tgn:id":2773613,
    "tgn:name":"Willoughby Bay",
    "tgn:placetype":[
        "aat:300132316"
    ]
},
  "bbox": [],
  "geometry": {"coordinates":[-76.2833,36.95],"type":"Point"}
}