{
  "id": 4001414,
  "type": "Feature",
  "properties": {
    "tgn:hierarchy":[
        "tgn:4001414",
        "tgn:1000003",
        "tgn:7003236",
        "tgn:7003144",
        "tgn:1000080",
        "tgn:7029392"
    ],
    "tgn:id":4001414,
    "tgn:name":"Bergeggi",
    "tgn:placetype":[
        "aat:300008347"
    ]
},
  "bbox": [],
  "geometry": {"coordinates":[8.433333,44.25],"type":"Point"}
}