{
  "id": 7006414,
  "type": "Feature",
  "properties": {
    "tgn:hierarchy":[
        "tgn:7006414",
        "tgn:1001424",
        "tgn:1000001",
        "tgn:7004624",
        "tgn:7029392"
    ],
    "tgn:id":7006414,
    "tgn:name":"Cochinos, Bah\u00eda de",
    "tgn:placetype":[
        "aat:300132316"
    ]
},
  "bbox": [],
  "geometry": {"coordinates":[-81.15,22.1333],"type":"Point"}
}