{
  "id": 2693566,
  "type": "Feature",
  "properties": {
    "tgn:hierarchy":[
        "tgn:2693566",
        "tgn:7006450",
        "tgn:1000001",
        "tgn:2124053",
        "tgn:7012149",
        "tgn:7029392"
    ],
    "tgn:id":2693566,
    "tgn:name":"Stephan Lake",
    "tgn:placetype":[
        "aat:300008680"
    ]
},
  "bbox": [],
  "geometry": {"coordinates":[-149.9167,61.4833],"type":"Point"}
}