{
  "id": 2533216,
  "type": "Feature",
  "properties": {
    "tgn:hierarchy":[
        "tgn:2533216",
        "tgn:1000001",
        "tgn:7012149",
        "tgn:1002942",
        "tgn:7007920",
        "tgn:7029392"
    ],
    "tgn:id":2533216,
    "tgn:name":"Mushroom Corner",
    "tgn:placetype":[
        "aat:300008347"
    ]
},
  "bbox": [],
  "geometry": {"coordinates":[-122.75,47.0333],"type":"Point"}
}