{
  "id": 7501496,
  "type": "Feature",
  "properties": {
    "tgn:hierarchy":[
        "tgn:7501496",
        "tgn:1000004",
        "tgn:7490934",
        "tgn:1000141",
        "tgn:7029392"
    ],
    "tgn:id":7501496,
    "tgn:name":"Beihua",
    "tgn:placetype":[
        "aat:300008347"
    ]
},
  "bbox": [],
  "geometry": {"coordinates":[120.340833,22.965556],"type":"Point"}
}