{
  "id": 7425903,
  "type": "Feature",
  "properties": {
    "tgn:hierarchy":[
        "tgn:7425903",
        "tgn:1000001",
        "tgn:7005594",
        "tgn:7005560",
        "tgn:7029392"
    ],
    "tgn:id":7425903,
    "tgn:name":"El Rosal",
    "tgn:placetype":[
        "aat:300008347"
    ]
},
  "bbox": [],
  "geometry": {"coordinates":[-101.366667,22.333333],"type":"Point"}
}