{
  "id": 2249628,
  "type": "Feature",
  "properties": {
    "tgn:hierarchy":[
        "tgn:2249628",
        "tgn:1002165",
        "tgn:1000001",
        "tgn:7012149",
        "tgn:7007517",
        "tgn:7029392"
    ],
    "tgn:id":2249628,
    "tgn:name":"Coles Pond",
    "tgn:placetype":[
        "aat:300008680"
    ]
},
  "bbox": [],
  "geometry": {"coordinates":[-70.1333,41.75],"type":"Point"}
}