{
  "id": 7089053,
  "type": "Feature",
  "properties": {
    "tgn:hierarchy":[
        "tgn:7089053",
        "tgn:7003692",
        "tgn:1000003",
        "tgn:7000084",
        "tgn:7029392"
    ],
    "tgn:id":7089053,
    "tgn:name":"Wagenrain",
    "tgn:placetype":[
        "aat:300008863"
    ]
},
  "bbox": [],
  "geometry": {"coordinates":[10.166667,48.783333],"type":"Point"}
}