{
  "id": 2101038,
  "type": "Feature",
  "properties": {
    "tgn:hierarchy":[
        "tgn:2101038",
        "tgn:1000001",
        "tgn:2001838",
        "tgn:7012149",
        "tgn:7007825",
        "tgn:7029392"
    ],
    "tgn:id":2101038,
    "tgn:name":"Pleasant Grove",
    "tgn:placetype":[
        "aat:300008347",
        "aat:300387210"
    ]
},
  "bbox": [],
  "geometry": {"coordinates":[-86.5333,35.4167],"type":"Point"}
}