{
  "id": 7121024,
  "type": "Feature",
  "properties": {
    "tgn:hierarchy":[
        "tgn:7121024",
        "tgn:7003692",
        "tgn:1000003",
        "tgn:7000084",
        "tgn:7029392"
    ],
    "tgn:id":7121024,
    "tgn:name":"Baschg",
    "tgn:placetype":[
        "aat:300008795"
    ]
},
  "bbox": [],
  "geometry": {"coordinates":[8.116667,48.15],"type":"Point"}
}