{
  "id": 2434324,
  "type": "Feature",
  "properties": {
    "tgn:hierarchy":[
        "tgn:2434324",
        "tgn:1000001",
        "tgn:7012149",
        "tgn:2001511",
        "tgn:7007709",
        "tgn:7029392"
    ],
    "tgn:id":2434324,
    "tgn:name":"Kendall Acres",
    "tgn:placetype":[
        "aat:300008347"
    ]
},
  "bbox": [],
  "geometry": {"coordinates":[-79.15,35.4333],"type":"Point"}
}