{
  "id": 2238341,
  "type": "Feature",
  "properties": {
    "tgn:hierarchy":[
        "tgn:2238341",
        "tgn:7002659",
        "tgn:1000001",
        "tgn:2000012",
        "tgn:7012149",
        "tgn:7029392"
    ],
    "tgn:id":2238341,
    "tgn:name":"Choctaw Creek",
    "tgn:placetype":[
        "aat:300008706"
    ]
},
  "bbox": [],
  "geometry": {"coordinates":[-87.5667,31.6167],"type":"Point"}
}