{
  "id": 7270623,
  "type": "Feature",
  "properties": {
    "tgn:hierarchy":[
        "tgn:7270623",
        "tgn:1000003",
        "tgn:7003635",
        "tgn:7016845",
        "tgn:7029392"
    ],
    "tgn:id":7270623,
    "tgn:name:nl":"Seydlitzpolder",
    "tgn:placetype":[
        "aat:300006163"
    ]
},
  "bbox": [],
  "geometry": {"coordinates":[3.783333,51.283333],"type":"Point"}
}