{
  "id": 2447246,
  "type": "Feature",
  "properties": {
    "tgn:hierarchy":[
        "tgn:2447246",
        "tgn:1000001",
        "tgn:2001840",
        "tgn:7012149",
        "tgn:7007825",
        "tgn:7029392"
    ],
    "tgn:id":2447246,
    "tgn:name":"Lick Branch",
    "tgn:placetype":[
        "aat:300008699"
    ]
},
  "bbox": [],
  "geometry": {"coordinates":[-85.0333,35.6833],"type":"Point"}
}