{
  "id": 7498821,
  "type": "Feature",
  "properties": {
    "tgn:hierarchy":[
        "tgn:7498821",
        "tgn:1000004",
        "tgn:7001009",
        "tgn:1000141",
        "tgn:7029392"
    ],
    "tgn:id":7498821,
    "tgn:name":"Chenglong Erhao Qiao",
    "tgn:placetype":[
        "aat:300007836"
    ]
},
  "bbox": [],
  "geometry": {"coordinates":[120.856596,24.194865],"type":"Point"}
}