{
  "id": 7042995,
  "type": "Feature",
  "properties": {
    "tgn:hierarchy":[
        "tgn:7042995",
        "tgn:7003132",
        "tgn:1000003",
        "tgn:7008516",
        "tgn:1000080",
        "tgn:7029392"
    ],
    "tgn:id":7042995,
    "tgn:name":"Rezzano",
    "tgn:placetype":[
        "aat:300008347"
    ]
},
  "bbox": [],
  "geometry": {"coordinates":[9.783333,44.866667],"type":"Point"}
}