{
  "id": 2679428,
  "type": "Feature",
  "properties": {
    "tgn:hierarchy":[
        "tgn:2679428",
        "tgn:1000001",
        "tgn:7012149",
        "tgn:7007157",
        "tgn:1002857",
        "tgn:7029392"
    ],
    "tgn:id":2679428,
    "tgn:name":"South Fork Mission Creek",
    "tgn:placetype":[
        "aat:300008706"
    ]
},
  "bbox": [],
  "geometry": {"coordinates":[-116.75,34.1167],"type":"Point"}
}