{
  "id": 7319608,
  "type": "Feature",
  "properties": {
    "tgn:hierarchy":[
        "tgn:7319608",
        "tgn:1001702",
        "tgn:1000049",
        "tgn:1000002",
        "tgn:7029392"
    ],
    "tgn:id":7319608,
    "tgn:name":"Almeida, Puerto",
    "tgn:placetype":[
        "aat:300008678"
    ]
},
  "bbox": [],
  "geometry": {"coordinates":[-70.633333,-54.85],"type":"Point"}
}