{
  "id": 2131281,
  "type": "Feature",
  "properties": {
    "tgn:hierarchy":[
        "tgn:2131281",
        "tgn:1000001",
        "tgn:7012149",
        "tgn:2000488",
        "tgn:7007250",
        "tgn:7029392"
    ],
    "tgn:id":2131281,
    "tgn:name":"Alta Mine",
    "tgn:placetype":[
        "aat:300000390"
    ]
},
  "bbox": [],
  "geometry": {"coordinates":[-116.8167,43.0167],"type":"Point"}
}