{
  "id": 2476820,
  "type": "Feature",
  "properties": {
    "tgn:hierarchy":[
        "tgn:2476820",
        "tgn:1000001",
        "tgn:7012149",
        "tgn:1002659",
        "tgn:7007710",
        "tgn:7029392"
    ],
    "tgn:id":2476820,
    "tgn:name":"Lyle",
    "tgn:placetype":[
        "aat:300008347"
    ]
},
  "bbox": [],
  "geometry": {"coordinates":[-80.3333,41.1333],"type":"Point"}
}