{
  "id": 2656925,
  "type": "Feature",
  "properties": {
    "tgn:hierarchy":[
        "tgn:2656925",
        "tgn:1000001",
        "tgn:2001424",
        "tgn:7012149",
        "tgn:7007564",
        "tgn:7029392"
    ],
    "tgn:id":2656925,
    "tgn:name":"Sheep Island",
    "tgn:placetype":[
        "aat:300008791"
    ]
},
  "bbox": [],
  "geometry": {"coordinates":[-71.5333,43.75],"type":"Point"}
}