{
  "id": 7199233,
  "type": "Feature",
  "properties": {
    "tgn:hierarchy":[
        "tgn:7199233",
        "tgn:1000003",
        "tgn:7003689",
        "tgn:7000084",
        "tgn:7029392"
    ],
    "tgn:id":7199233,
    "tgn:name":"F\u00f6rsterei Eichen forst",
    "tgn:placetype":[
        "aat:300004792"
    ]
},
  "bbox": [],
  "geometry": {"coordinates":[10.916667,51.55],"type":"Point"}
}