{
  "id": 7047830,
  "type": "Feature",
  "properties": {
    "tgn:hierarchy":[
        "tgn:7047830",
        "tgn:7005126",
        "tgn:1000003",
        "tgn:7003120",
        "tgn:1000080",
        "tgn:7029392"
    ],
    "tgn:id":7047830,
    "tgn:name":"Grosse Del Rio",
    "tgn:placetype":[
        "aat:300008347"
    ]
},
  "bbox": [],
  "geometry": {"coordinates":[6.983333,44.65],"type":"Point"}
}