{
  "id": 1138354,
  "type": "Feature",
  "properties": {
    "tgn:hierarchy":[
        "tgn:1138354",
        "tgn:7012187",
        "tgn:1000003",
        "tgn:7006657",
        "tgn:7029392"
    ],
    "tgn:id":1138354,
    "tgn:name":"Savi\u010di",
    "tgn:placetype":[
        "aat:300008347",
        "aat:300008375"
    ]
},
  "bbox": [],
  "geometry": {"coordinates":[29.05,52.4167],"type":"Point"}
}