{
  "id": 7282859,
  "type": "Feature",
  "properties": {
    "tgn:hierarchy":[
        "tgn:7282859",
        "tgn:1001637",
        "tgn:1000049",
        "tgn:1000002",
        "tgn:7029392"
    ],
    "tgn:id":7282859,
    "tgn:name":"Peleco",
    "tgn:placetype":[
        "aat:300000206"
    ]
},
  "bbox": [],
  "geometry": {"coordinates":[-73.366667,-37.866667],"type":"Point"}
}