{
  "id": 2605568,
  "type": "Feature",
  "properties": {
    "tgn:hierarchy":[
        "tgn:2605568",
        "tgn:2000948",
        "tgn:1000001",
        "tgn:7012149",
        "tgn:7007520",
        "tgn:7029392"
    ],
    "tgn:id":2605568,
    "tgn:name":"Railroad Drain",
    "tgn:placetype":[
        "aat:300008699"
    ]
},
  "bbox": [],
  "geometry": {"coordinates":[-84.0667,43.75],"type":"Point"}
}