{
  "id": 1062390,
  "type": "Feature",
  "properties": {
    "tgn:hierarchy":[
        "tgn:1062390",
        "tgn:7002758",
        "tgn:1001316",
        "tgn:1000003",
        "tgn:1000095",
        "tgn:7029392"
    ],
    "tgn:id":1062390,
    "tgn:name":"Quesada",
    "tgn:placetype":[
        "aat:300008347"
    ]
},
  "bbox": [],
  "geometry": {"coordinates":[-3.066667,37.85],"type":"Point"}
}