{
  "id": 7504066,
  "type": "Feature",
  "properties": {
    "tgn:hierarchy":[
        "tgn:7504066",
        "tgn:1009227",
        "tgn:1000226",
        "tgn:7016822",
        "tgn:1000006",
        "tgn:7029392"
    ],
    "tgn:id":7504066,
    "tgn:name:en":"Welcome Point",
    "tgn:placetype":[
        "aat:300386846"
    ]
},
  "bbox": [],
  "geometry": {"coordinates":[167.816667,-45.166667],"type":"Point"}
}