{
  "id": 2446066,
  "type": "Feature",
  "properties": {
    "tgn:hierarchy":[
        "tgn:2446066",
        "tgn:1000001",
        "tgn:7012149",
        "tgn:1002567",
        "tgn:7007240",
        "tgn:7029392"
    ],
    "tgn:id":2446066,
    "tgn:name":"Leven, Loch",
    "tgn:placetype":[
        "aat:300008680"
    ]
},
  "bbox": [],
  "geometry": {"coordinates":[-81.6333,28.8167],"type":"Point"}
}