{
  "id": 7495360,
  "type": "Feature",
  "properties": {
    "tgn:hierarchy":[
        "tgn:7495360",
        "tgn:1000004",
        "tgn:1000454",
        "tgn:1000141",
        "tgn:7029392"
    ],
    "tgn:id":7495360,
    "tgn:name":"Zhongbu Xi",
    "tgn:placetype":[
        "aat:300008699"
    ]
},
  "bbox": [],
  "geometry": {"coordinates":[121.369784,24.932708],"type":"Point"}
}