<<<<<<< HEAD
{
  "id": 7245535,
  "type": "Feature",
  "properties": {
    "tgn:hierarchy":[
        "tgn:7245535",
        "tgn:7018239",
        "tgn:1000003",
        "tgn:1000063",
        "tgn:7018236",
        "tgn:7029392"
    ],
    "tgn:id":7245535,
    "tgn:name":"Amelgemhoeve",
    "tgn:placetype":[
        "aat:300000206"
    ]
},
  "bbox": [],
  "geometry": {"coordinates":[4.3,50.916667],"type":"Point"}
}
=======
{"geometry":{"type":"Point","coordinates":[4.300000,50.916667]},"type":"Feature","properties":{"hierarchy":["tgn:7245535","tgn:7018239","tgn:1000003","tgn:1000063","tgn:7018236","tgn:7029392"],"placetype":["aat:300000206"],"id":7245535,"name:xx":"Amelgemhoeve"}}
>>>>>>> 03f74aca74312dbeaf24d7e61306dd6a786dc3d0
