{
  "id": 7223223,
  "type": "Feature",
  "properties": {
    "tgn:hierarchy":[
        "tgn:7223223",
        "tgn:7011330",
        "tgn:7002674",
        "tgn:1000003",
        "tgn:1000074",
        "tgn:7029392"
    ],
    "tgn:id":7223223,
    "tgn:name":"Meneta\u00ed",
    "tgn:placetype":[
        "aat:300008347"
    ]
},
  "bbox": [],
  "geometry": {"coordinates":[27.183333,35.483333],"type":"Point"}
}