{
  "id": 1004441,
  "type": "Feature",
  "properties": {
    "tgn:hierarchy":[
        "tgn:1004441",
        "tgn:1000003",
        "tgn:7003677",
        "tgn:7000084",
        "tgn:7005080",
        "tgn:7029392"
    ],
    "tgn:id":1004441,
    "tgn:name":"Erle",
    "tgn:placetype":[
        "aat:300000745",
        "aat:300387332"
    ]
},
  "bbox": [],
  "geometry": {"coordinates":[7.083333,51.55],"type":"Point"}
}