<<<<<<< HEAD
{
  "id": 2403434,
  "type": "Feature",
  "properties": {
    "tgn:hierarchy":[
        "tgn:2403434",
        "tgn:7002659",
        "tgn:1000001",
        "tgn:7012149",
        "tgn:2000035",
        "tgn:7029392"
    ],
    "tgn:id":2403434,
    "tgn:name":"Houston Spring",
    "tgn:placetype":[
        "aat:300008697"
    ]
},
  "bbox": [],
  "geometry": {"coordinates":[-85.95,34.8],"type":"Point"}
}
=======
{"geometry":{"type":"Point","coordinates":[-85.950000,34.800000]},"type":"Feature","properties":{"hierarchy":["tgn:2403434","tgn:7002659","tgn:1000001","tgn:7012149","tgn:2000035","tgn:7029392"],"placetype":["aat:300008697"],"id":2403434,"name:xx":"Houston Spring"}}
>>>>>>> 03f74aca74312dbeaf24d7e61306dd6a786dc3d0
