{
  "id": 7183016,
  "type": "Feature",
  "properties": {
    "tgn:hierarchy":[
        "tgn:7183016",
        "tgn:1000003",
        "tgn:7003687",
        "tgn:7000084",
        "tgn:7029392"
    ],
    "tgn:id":7183016,
    "tgn:name":"Galgen-Berge",
    "tgn:placetype":[
        "aat:300008777"
    ]
},
  "bbox": [],
  "geometry": {"coordinates":[11.533333,52.566667],"type":"Point"}
}