{
  "id": 7513574,
  "type": "Feature",
  "properties": {
    "tgn:hierarchy":[
        "tgn:7513574",
        "tgn:1008380",
        "tgn:1000226",
        "tgn:7016827",
        "tgn:1000006",
        "tgn:7029392"
    ],
    "tgn:id":7513574,
    "tgn:name:en":"Geddy",
    "tgn:placetype":[
        "aat:300008777"
    ]
},
  "bbox": [],
  "geometry": {"coordinates":[174.25,-39.066667],"type":"Point"}
}