{
  "id": 2172295,
  "type": "Feature",
  "properties": {
    "tgn:hierarchy":[
        "tgn:2172295",
        "tgn:1000001",
        "tgn:2001414",
        "tgn:7012149",
        "tgn:7007526",
        "tgn:7029392"
    ],
    "tgn:id":2172295,
    "tgn:name":"Bilk Creek Mountains",
    "tgn:placetype":[
        "aat:300386831"
    ]
},
  "bbox": [],
  "geometry": {"coordinates":[-118.3167,41.6667],"type":"Point"}
}