{
  "id": 7585284,
  "type": "Feature",
  "properties": {
    "tgn:hierarchy":[
        "tgn:7585284",
        "tgn:1000004",
        "tgn:7000198",
        "tgn:7016722",
        "tgn:7029392"
    ],
    "tgn:id":7585284,
    "tgn:name:en":"Tapra Tindra",
    "tgn:placetype":[
        "aat:300008347"
    ]
},
  "bbox": [],
  "geometry": {"coordinates":[78.476275,24.998088],"type":"Point"}
}