{
  "id": 7459222,
  "type": "Feature",
  "properties": {
    "tgn:hierarchy":[
        "tgn:7459222",
        "tgn:7002444",
        "tgn:1000003",
        "tgn:7009907",
        "tgn:7008591",
        "tgn:7029392"
    ],
    "tgn:id":7459222,
    "tgn:name:en":"Newark Bay",
    "tgn:placetype":[
        "aat:300132316"
    ]
},
  "bbox": [],
  "geometry": {"coordinates":[-2.75,58.916667],"type":"Point"}
}