{
  "id": 1086474,
  "type": "Feature",
  "properties": {
    "tgn:hierarchy":[
        "tgn:1086474",
        "tgn:1001363",
        "tgn:1000004",
        "tgn:7018453",
        "tgn:1000144",
        "tgn:7029392"
    ],
    "tgn:id":1086474,
    "tgn:name":"K\u0131lbasan",
    "tgn:placetype":[
        "aat:300008347"
    ]
},
  "bbox": [],
  "geometry": {"coordinates":[33.1833,37.3333],"type":"Point"}
}