{
  "id": 7198253,
  "type": "Feature",
  "properties": {
    "tgn:hierarchy":[
        "tgn:7198253",
        "tgn:1000003",
        "tgn:7003678",
        "tgn:7000084",
        "tgn:7029392"
    ],
    "tgn:id":7198253,
    "tgn:name":"Ebertsberg",
    "tgn:placetype":[
        "aat:300008777"
    ]
},
  "bbox": [],
  "geometry": {"coordinates":[8.75,50.016667],"type":"Point"}
}