{
  "id": 7380786,
  "type": "Feature",
  "properties": {
    "tgn:hierarchy":[
        "tgn:7380786",
        "tgn:7005575",
        "tgn:1000001",
        "tgn:7005560",
        "tgn:7029392"
    ],
    "tgn:id":7380786,
    "tgn:name":"Magdalena",
    "tgn:placetype":[
        "aat:300008347"
    ]
},
  "bbox": [],
  "geometry": {"coordinates":[-99.166667,19.233333],"type":"Point"}
}