{
  "id": 7382985,
  "type": "Feature",
  "properties": {
    "tgn:hierarchy":[
        "tgn:7382985",
        "tgn:1000001",
        "tgn:7005596",
        "tgn:7005560",
        "tgn:7029392"
    ],
    "tgn:id":7382985,
    "tgn:name":"Mosquitero",
    "tgn:placetype":[
        "aat:300007783"
    ]
},
  "bbox": [],
  "geometry": {"coordinates":[-93.65,17.733333],"type":"Point"}
}