{
  "id": 7208985,
  "type": "Feature",
  "properties": {
    "tgn:hierarchy":[
        "tgn:7208985",
        "tgn:1000003",
        "tgn:7003676",
        "tgn:7000084",
        "tgn:7029392"
    ],
    "tgn:id":7208985,
    "tgn:name":"Barlage",
    "tgn:placetype":[
        "aat:300008347"
    ]
},
  "bbox": [],
  "geometry": {"coordinates":[7.95,52.75],"type":"Point"}
}