{
  "id": 2242336,
  "type": "Feature",
  "properties": {
    "tgn:hierarchy":[
        "tgn:2242336",
        "tgn:1000001",
        "tgn:7012149",
        "tgn:2001872",
        "tgn:7007825",
        "tgn:7029392"
    ],
    "tgn:id":2242336,
    "tgn:name":"Clayton Branch",
    "tgn:placetype":[
        "aat:300008699"
    ]
},
  "bbox": [],
  "geometry": {"coordinates":[-88.25,35.3833],"type":"Point"}
}