{
  "id": 1071262,
  "type": "Feature",
  "properties": {
    "tgn:hierarchy":[
        "tgn:1071262",
        "tgn:1000004",
        "tgn:7001745",
        "tgn:1000111",
        "tgn:7029392"
    ],
    "tgn:id":1071262,
    "tgn:name":"Saileati",
    "tgn:placetype":[
        "aat:300008347"
    ]
},
  "bbox": [],
  "geometry": {"coordinates":[74.75,38.95],"type":"Point"}
}