{
  "id": 7381341,
  "type": "Feature",
  "properties": {
    "tgn:hierarchy":[
        "tgn:7381341",
        "tgn:7005581",
        "tgn:1000001",
        "tgn:7005560",
        "tgn:7029392"
    ],
    "tgn:id":7381341,
    "tgn:name":"Los \u00c1lvarez",
    "tgn:placetype":[
        "aat:300008347"
    ]
},
  "bbox": [],
  "geometry": {"coordinates":[-105.216667,27.633333],"type":"Point"}
}