<<<<<<< HEAD
{
  "id": 2253240,
  "type": "Feature",
  "properties": {
    "tgn:hierarchy":[
        "tgn:2253240",
        "tgn:1000001",
        "tgn:7012149",
        "tgn:2001980",
        "tgn:7007826",
        "tgn:7029392"
    ],
    "tgn:id":2253240,
    "tgn:name":"Contrary Creek",
    "tgn:placetype":[
        "aat:300008706"
    ]
},
  "bbox": [],
  "geometry": {"coordinates":[-99.9833,30.0833],"type":"Point"}
}
=======
{"geometry":{"type":"Point","coordinates":[-99.983300,30.083300]},"type":"Feature","properties":{"hierarchy":["tgn:2253240","tgn:1000001","tgn:7012149","tgn:2001980","tgn:7007826","tgn:7029392"],"placetype":["aat:300008706"],"id":2253240,"name:xx":"Contrary Creek"}}
>>>>>>> 03f74aca74312dbeaf24d7e61306dd6a786dc3d0
