{
  "id": 2253240,
  "type": "Feature",
  "properties": {
    "tgn:hierarchy":[
        "tgn:2253240",
        "tgn:1000001",
        "tgn:7012149",
        "tgn:2001980",
        "tgn:7007826",
        "tgn:7029392"
    ],
    "tgn:id":2253240,
    "tgn:name":"Contrary Creek",
    "tgn:placetype":[
        "aat:300008706"
    ]
},
  "bbox": [],
  "geometry": {"coordinates":[-99.9833,30.0833],"type":"Point"}
}