{
  "id": 7417782,
  "type": "Feature",
  "properties": {
    "tgn:hierarchy":[
        "tgn:7417782",
        "tgn:1000001",
        "tgn:7005591",
        "tgn:7005560",
        "tgn:7029392"
    ],
    "tgn:id":7417782,
    "tgn:name:es":"L\u00e1zaro C\u00e1rdenas",
    "tgn:placetype":[
        "aat:300008347"
    ]
},
  "bbox": [],
  "geometry": {"coordinates":[-97.718611,17.855],"type":"Point"}
}