{
  "id": 7307690,
  "type": "Feature",
  "properties": {
    "tgn:hierarchy":[
        "tgn:7307690",
        "tgn:7002805",
        "tgn:7002758",
        "tgn:1000003",
        "tgn:1000095",
        "tgn:7029392"
    ],
    "tgn:id":7307690,
    "tgn:name":"Los Encalmados",
    "tgn:placetype":[
        "aat:300008347"
    ]
},
  "bbox": [],
  "geometry": {"coordinates":[-2.266667,37.033333],"type":"Point"}
}