{
  "id": 2563618,
  "type": "Feature",
  "properties": {
    "tgn:hierarchy":[
        "tgn:2563618",
        "tgn:1002300",
        "tgn:1000001",
        "tgn:7012149",
        "tgn:7007564",
        "tgn:7029392"
    ],
    "tgn:id":2563618,
    "tgn:name":"Owlshead",
    "tgn:placetype":[
        "aat:300008798"
    ]
},
  "bbox": [],
  "geometry": {"coordinates":[-71.4833,44.3333],"type":"Point"}
}