<<<<<<< HEAD
{
  "id": 7479035,
  "type": "Feature",
  "properties": {
    "tgn:hierarchy":[
        "tgn:7479035",
        "tgn:1000004",
        "tgn:7490934",
        "tgn:1000141",
        "tgn:7029392"
    ],
    "tgn:id":7479035,
    "tgn:name":"Wangzi'anjiao",
    "tgn:placetype":[
        "aat:300008347"
    ]
},
  "bbox": [],
  "geometry": {"coordinates":[120.416389,23.27],"type":"Point"}
}
=======
{"geometry":{"type":"Point","coordinates":[120.416389,23.270000]},"type":"Feature","properties":{"hierarchy":["tgn:7479035","tgn:1000004","tgn:7490934","tgn:1000141","tgn:7029392"],"placetype":["aat:300008347"],"id":7479035,"name:xx":"Wangzi'anjiao"}}
>>>>>>> 03f74aca74312dbeaf24d7e61306dd6a786dc3d0
