<<<<<<< HEAD
{
  "id": 2257115,
  "type": "Feature",
  "properties": {
    "tgn:hierarchy":[
        "tgn:2257115",
        "tgn:1000001",
        "tgn:7012149",
        "tgn:2001720",
        "tgn:7007708",
        "tgn:7029392"
    ],
    "tgn:id":2257115,
    "tgn:name":"Cornell Place",
    "tgn:placetype":[
        "aat:300008347"
    ]
},
  "bbox": [],
  "geometry": {"coordinates":[-119.2833,45.8333],"type":"Point"}
}
=======
{"geometry":{"type":"Point","coordinates":[-119.283300,45.833300]},"type":"Feature","properties":{"hierarchy":["tgn:2257115","tgn:1000001","tgn:7012149","tgn:2001720","tgn:7007708","tgn:7029392"],"placetype":["aat:300008347"],"id":2257115,"name:xx":"Cornell Place"}}
>>>>>>> 03f74aca74312dbeaf24d7e61306dd6a786dc3d0
