{
  "id": 7220073,
  "type": "Feature",
  "properties": {
    "tgn:hierarchy":[
        "tgn:7220073",
        "tgn:1042193",
        "tgn:7002705",
        "tgn:1000003",
        "tgn:1000074",
        "tgn:7029392"
    ],
    "tgn:id":7220073,
    "tgn:name":"N\u00e9os Orop\u00f3s",
    "tgn:placetype":[
        "aat:300008347"
    ]
},
  "bbox": [],
  "geometry": {"coordinates":[20.736667,39.151389],"type":"Point"}
}