{
  "id": 2125309,
  "type": "Feature",
  "properties": {
    "tgn:hierarchy":[
        "tgn:2125309",
        "tgn:1002178",
        "tgn:1000001",
        "tgn:7012149",
        "tgn:7007565",
        "tgn:7029392"
    ],
    "tgn:id":2125309,
    "tgn:name":"Ackermans Creek",
    "tgn:placetype":[
        "aat:300008706"
    ]
},
  "bbox": [],
  "geometry": {"coordinates":[-74.0833,40.8167],"type":"Point"}
}