{
  "id": 7145695,
  "type": "Feature",
  "properties": {
    "tgn:hierarchy":[
        "tgn:7145695",
        "tgn:7003669",
        "tgn:1000003",
        "tgn:7000084",
        "tgn:7029392"
    ],
    "tgn:id":7145695,
    "tgn:name":"Kollmitz",
    "tgn:placetype":[
        "aat:300000206"
    ]
},
  "bbox": [],
  "geometry": {"coordinates":[12.75,49.166667],"type":"Point"}
}