{
  "id": 7269565,
  "type": "Feature",
  "properties": {
    "tgn:hierarchy":[
        "tgn:7269565",
        "tgn:7003619",
        "tgn:1000003",
        "tgn:7016845",
        "tgn:7029392"
    ],
    "tgn:id":7269565,
    "tgn:name:nl":"Mari\u00ebndaal",
    "tgn:placetype":[
        "aat:300387502"
    ]
},
  "bbox": [],
  "geometry": {"coordinates":[5.866667,51.983333],"type":"Point"}
}