{
  "id": 7416166,
  "type": "Feature",
  "properties": {
    "tgn:hierarchy":[
        "tgn:7416166",
        "tgn:1000001",
        "tgn:7005591",
        "tgn:7005560",
        "tgn:7029392"
    ],
    "tgn:id":7416166,
    "tgn:name:es":"R\u00edo Escondido",
    "tgn:placetype":[
        "aat:300008347"
    ]
},
  "bbox": [],
  "geometry": {"coordinates":[-94.750278,17.100556],"type":"Point"}
}