{
  "id": 7139688,
  "type": "Feature",
  "properties": {
    "tgn:hierarchy":[
        "tgn:7139688",
        "tgn:7000096",
        "tgn:1000003",
        "tgn:7000084",
        "tgn:7029392"
    ],
    "tgn:id":7139688,
    "tgn:name":"Laufberge",
    "tgn:placetype":[
        "aat:300008777"
    ]
},
  "bbox": [],
  "geometry": {"coordinates":[13.966667,52.183333],"type":"Point"}
}