{
  "id": 2615560,
  "type": "Feature",
  "properties": {
    "tgn:hierarchy":[
        "tgn:2615560",
        "tgn:1002156",
        "tgn:1000001",
        "tgn:7012149",
        "tgn:7007706",
        "tgn:7029392"
    ],
    "tgn:id":2615560,
    "tgn:name":"Reuschling Pond",
    "tgn:placetype":[
        "aat:300006191"
    ]
},
  "bbox": [],
  "geometry": {"coordinates":[-80.7667,41.65],"type":"Point"}
}