{
  "id": 7192259,
  "type": "Feature",
  "properties": {
    "tgn:hierarchy":[
        "tgn:7192259",
        "tgn:1000003",
        "tgn:7003676",
        "tgn:7000084",
        "tgn:7029392"
    ],
    "tgn:id":7192259,
    "tgn:name":"Fl\u00f6rkenkamp",
    "tgn:placetype":[
        "aat:300000206"
    ]
},
  "bbox": [],
  "geometry": {"coordinates":[7.966667,53.55],"type":"Point"}
}