{
  "id": 2366117,
  "type": "Feature",
  "properties": {
    "tgn:hierarchy":[
        "tgn:2366117",
        "tgn:1000001",
        "tgn:1002480",
        "tgn:7012149",
        "tgn:7007564",
        "tgn:7029392"
    ],
    "tgn:id":2366117,
    "tgn:name":"Gridley River",
    "tgn:placetype":[
        "aat:300008707"
    ]
},
  "bbox": [],
  "geometry": {"coordinates":[-71.8833,42.7667],"type":"Point"}
}