{
  "id": 2535218,
  "type": "Feature",
  "properties": {
    "tgn:hierarchy":[
        "tgn:2535218",
        "tgn:1000001",
        "tgn:2000305",
        "tgn:7012149",
        "tgn:7007248",
        "tgn:7029392"
    ],
    "tgn:id":2535218,
    "tgn:name":"Nankin",
    "tgn:placetype":[
        "aat:300008347"
    ]
},
  "bbox": [],
  "geometry": {"coordinates":[-83.4667,30.65],"type":"Point"}
}