{
  "id": 2295056,
  "type": "Feature",
  "properties": {
    "tgn:hierarchy":[
        "tgn:2295056",
        "tgn:1000001",
        "tgn:7006451",
        "tgn:2000095",
        "tgn:7012149",
        "tgn:7029392"
    ],
    "tgn:id":2295056,
    "tgn:name":"Draw Tank",
    "tgn:placetype":[
        "aat:300006191"
    ]
},
  "bbox": [],
  "geometry": {"coordinates":[-109.1333,33.1167],"type":"Point"}
}