{
  "id": 7573051,
  "type": "Feature",
  "properties": {
    "tgn:hierarchy":[
        "tgn:7573051",
        "tgn:1000004",
        "tgn:7000198",
        "tgn:1001882",
        "tgn:7029392"
    ],
    "tgn:id":7573051,
    "tgn:name:en":"G\u016bgi",
    "tgn:placetype":[
        "aat:300008347"
    ]
},
  "bbox": [],
  "geometry": {"coordinates":[76.75,16.733333],"type":"Point"}
}