{
  "id": 7183592,
  "type": "Feature",
  "properties": {
    "tgn:hierarchy":[
        "tgn:7183592",
        "tgn:7000096",
        "tgn:1000003",
        "tgn:7000084",
        "tgn:7029392"
    ],
    "tgn:id":7183592,
    "tgn:name":"Gottsdorf",
    "tgn:placetype":[
        "aat:300008347"
    ]
},
  "bbox": [],
  "geometry": {"coordinates":[13.066667,52.133333],"type":"Point"}
}