{
  "id": 2384563,
  "type": "Feature",
  "properties": {
    "tgn:hierarchy":[
        "tgn:2384563",
        "tgn:1000001",
        "tgn:7012149",
        "tgn:7007159",
        "tgn:7029392"
    ],
    "tgn:id":2384563,
    "tgn:name":"Hell Hollow",
    "tgn:placetype":[
        "aat:300008761"
    ]
},
  "bbox": [],
  "geometry": {"coordinates":[-71.8667,41.6333],"type":"Point"}
}