{
  "id": 7064600,
  "type": "Feature",
  "properties": {
    "tgn:hierarchy":[
        "tgn:7064600",
        "tgn:1000003",
        "tgn:7003677",
        "tgn:7000084",
        "tgn:7029392"
    ],
    "tgn:id":7064600,
    "tgn:name":"Unnewisse",
    "tgn:placetype":[
        "aat:300000206"
    ]
},
  "bbox": [],
  "geometry": {"coordinates":[7.65,51.816667],"type":"Point"}
}