{
  "id": 7183383,
  "type": "Feature",
  "properties": {
    "tgn:hierarchy":[
        "tgn:7183383",
        "tgn:1000003",
        "tgn:7003687",
        "tgn:7000084",
        "tgn:7029392"
    ],
    "tgn:id":7183383,
    "tgn:name":"Bahnhof Geestgottberg",
    "tgn:placetype":[
        "aat:300007783"
    ]
},
  "bbox": [],
  "geometry": {"coordinates":[11.734444,52.956389],"type":"Point"}
}