{
  "id": 2376536,
  "type": "Feature",
  "properties": {
    "tgn:hierarchy":[
        "tgn:2376536",
        "tgn:1000001",
        "tgn:7012149",
        "tgn:1002924",
        "tgn:7007568",
        "tgn:7029392"
    ],
    "tgn:id":2376536,
    "tgn:name":"Hardscrabble",
    "tgn:placetype":[
        "aat:300008347"
    ]
},
  "bbox": [],
  "geometry": {"coordinates":[-72.2167,40.9667],"type":"Point"}
}