{
  "id": 7469301,
  "type": "Feature",
  "properties": {
    "tgn:hierarchy":[
        "tgn:7469301",
        "tgn:1000004",
        "tgn:1000454",
        "tgn:1000141",
        "tgn:7029392"
    ],
    "tgn:id":7469301,
    "tgn:name":"Zhonggang Li",
    "tgn:placetype":[
        "aat:300387173"
    ]
},
  "bbox": [],
  "geometry": {"coordinates":[121.4562,25.0453],"type":"Point"}
}