<<<<<<< HEAD
{
  "id": 7353404,
  "type": "Feature",
  "properties": {
    "tgn:hierarchy":[
        "tgn:7353404",
        "tgn:7005586",
        "tgn:1000001",
        "tgn:7005560",
        "tgn:7029392"
    ],
    "tgn:id":7353404,
    "tgn:name":"Bel\u00e9m",
    "tgn:placetype":[
        "aat:300008347"
    ]
},
  "bbox": [],
  "geometry": {"coordinates":[-102.3,21.0],"type":"Point"}
}
=======
{"geometry":{"type":"Point","coordinates":[-102.300000,21.000000]},"type":"Feature","properties":{"hierarchy":["tgn:7353404","tgn:7005586","tgn:1000001","tgn:7005560","tgn:7029392"],"placetype":["aat:300008347"],"id":7353404,"name:xx":"Bel\u00e9m"}}
>>>>>>> 03f74aca74312dbeaf24d7e61306dd6a786dc3d0
