{
  "id": 2340585,
  "type": "Feature",
  "properties": {
    "tgn:hierarchy":[
        "tgn:2340585",
        "tgn:1000001",
        "tgn:7012149",
        "tgn:2002246",
        "tgn:7007920",
        "tgn:7029392"
    ],
    "tgn:id":2340585,
    "tgn:name":"Frenchman Hills Lake",
    "tgn:placetype":[
        "aat:300008680"
    ]
},
  "bbox": [],
  "geometry": {"coordinates":[-119.5667,46.9833],"type":"Point"}
}