{
  "id": 2716879,
  "type": "Feature",
  "properties": {
    "tgn:hierarchy":[
        "tgn:2716879",
        "tgn:1000001",
        "tgn:7012149",
        "tgn:2000224",
        "tgn:7007158",
        "tgn:7029392"
    ],
    "tgn:id":2716879,
    "tgn:name":"Thespian Mine",
    "tgn:placetype":[
        "aat:300000390"
    ]
},
  "bbox": [],
  "geometry": {"coordinates":[-106.2667,39.2333],"type":"Point"}
}