{
  "id": 7514068,
  "type": "Feature",
  "properties": {
    "tgn:hierarchy":[
        "tgn:7514068",
        "tgn:1008380",
        "tgn:1000226",
        "tgn:7016827",
        "tgn:1000006",
        "tgn:7029392"
    ],
    "tgn:id":7514068,
    "tgn:name:en":"Epiha Rocks",
    "tgn:placetype":[
        "aat:300011692"
    ]
},
  "bbox": [],
  "geometry": {"coordinates":[174.616667,-38.716667],"type":"Point"}
}