{
  "id": 2162197,
  "type": "Feature",
  "properties": {
    "tgn:hierarchy":[
        "tgn:2162197",
        "tgn:1000001",
        "tgn:7012149",
        "tgn:7007826",
        "tgn:7029392"
    ],
    "tgn:id":2162197,
    "tgn:name":"Belnap Creek",
    "tgn:placetype":[
        "aat:300008706"
    ]
},
  "bbox": [],
  "geometry": {"coordinates":[-97.4167,32.1833],"type":"Point"}
}