<<<<<<< HEAD
{
  "id": 7057802,
  "type": "Feature",
  "properties": {
    "tgn:hierarchy":[
        "tgn:7057802",
        "tgn:1003432",
        "tgn:1000003",
        "tgn:7003240",
        "tgn:1000080",
        "tgn:7029392"
    ],
    "tgn:id":7057802,
    "tgn:name":"Arli",
    "tgn:placetype":[
        "aat:300008347"
    ]
},
  "bbox": [],
  "geometry": {"coordinates":[13.45,42.8],"type":"Point"}
}
=======
{"geometry":{"type":"Point","coordinates":[13.450000,42.800000]},"type":"Feature","properties":{"hierarchy":["tgn:7057802","tgn:1003432","tgn:1000003","tgn:7003240","tgn:1000080","tgn:7029392"],"placetype":["aat:300008347"],"id":7057802,"name:xx":"Arli"}}
>>>>>>> 03f74aca74312dbeaf24d7e61306dd6a786dc3d0
