{
  "id": 7230162,
  "type": "Feature",
  "properties": {
    "tgn:hierarchy":[
        "tgn:7230162",
        "tgn:7002725",
        "tgn:7002715",
        "tgn:1000003",
        "tgn:1000074",
        "tgn:7029392"
    ],
    "tgn:id":7230162,
    "tgn:name":"Khorter\u00f3n",
    "tgn:placetype":[
        "aat:300008347"
    ]
},
  "bbox": [],
  "geometry": {"coordinates":[23.366667,41.216667],"type":"Point"}
}