{
  "id": 2064084,
  "type": "Feature",
  "properties": {
    "tgn:hierarchy":[
        "tgn:2064084",
        "tgn:1000001",
        "tgn:7014090",
        "tgn:7012149",
        "tgn:7007565",
        "tgn:7029392"
    ],
    "tgn:id":2064084,
    "tgn:name":"Belford",
    "tgn:placetype":[
        "aat:300008347"
    ]
},
  "bbox": [],
  "geometry": {"coordinates":[-74.0833,40.4167],"type":"Point"}
}