{
  "id": 2667640,
  "type": "Feature",
  "properties": {
    "tgn:hierarchy":[
        "tgn:2667640",
        "tgn:1000001",
        "tgn:7012149",
        "tgn:2001912",
        "tgn:7007825",
        "tgn:7029392"
    ],
    "tgn:id":2667640,
    "tgn:name":"Skull Creek",
    "tgn:placetype":[
        "aat:300008706"
    ]
},
  "bbox": [],
  "geometry": {"coordinates":[-84.6167,36.3333],"type":"Point"}
}