{
  "id": 7198839,
  "type": "Feature",
  "properties": {
    "tgn:hierarchy":[
        "tgn:7198839",
        "tgn:7003692",
        "tgn:1000003",
        "tgn:7000084",
        "tgn:7029392"
    ],
    "tgn:id":7198839,
    "tgn:name":"Eggenrot",
    "tgn:placetype":[
        "aat:300008347"
    ]
},
  "bbox": [],
  "geometry": {"coordinates":[10.083333,48.983333],"type":"Point"}
}