{
  "id": 2770740,
  "type": "Feature",
  "properties": {
    "tgn:hierarchy":[
        "tgn:2770740",
        "tgn:1000001",
        "tgn:7012149",
        "tgn:7007524",
        "tgn:7029392"
    ],
    "tgn:id":2770740,
    "tgn:name":"Wildcat Coulee",
    "tgn:placetype":[
        "aat:300008761"
    ]
},
  "bbox": [],
  "geometry": {"coordinates":[-110.6833,47.4333],"type":"Point"}
}