{
  "id": 2481834,
  "type": "Feature",
  "properties": {
    "tgn:hierarchy":[
        "tgn:2481834",
        "tgn:1000001",
        "tgn:1002235",
        "tgn:7012149",
        "tgn:7007919",
        "tgn:7029392"
    ],
    "tgn:id":2481834,
    "tgn:name":"Landor, Lake",
    "tgn:placetype":[
        "aat:300006191"
    ]
},
  "bbox": [],
  "geometry": {"coordinates":[-77.55,38.0167],"type":"Point"}
}