{
  "id": 7283205,
  "type": "Feature",
  "properties": {
    "tgn:hierarchy":[
        "tgn:7283205",
        "tgn:1001657",
        "tgn:1000049",
        "tgn:1000002",
        "tgn:7029392"
    ],
    "tgn:id":7283205,
    "tgn:name":"Paloma, Quebrada",
    "tgn:placetype":[
        "aat:300008699"
    ]
},
  "bbox": [],
  "geometry": {"coordinates":[-70.566667,-30.683333],"type":"Point"}
}