{
  "id": 7417938,
  "type": "Feature",
  "properties": {
    "tgn:hierarchy":[
        "tgn:7417938",
        "tgn:1000001",
        "tgn:7005596",
        "tgn:7005560",
        "tgn:7029392"
    ],
    "tgn:id":7417938,
    "tgn:name:es":"Villa Hormes",
    "tgn:placetype":[
        "aat:300008347"
    ]
},
  "bbox": [],
  "geometry": {"coordinates":[-92.583333,18.575],"type":"Point"}
}