{
  "id": 2398676,
  "type": "Feature",
  "properties": {
    "tgn:hierarchy":[
        "tgn:2398676",
        "tgn:1000001",
        "tgn:7012149",
        "tgn:2000893",
        "tgn:7007256",
        "tgn:7029392"
    ],
    "tgn:id":2398676,
    "tgn:name":"Hop-O-Bee, Lake",
    "tgn:placetype":[
        "aat:300006191"
    ]
},
  "bbox": [],
  "geometry": {"coordinates":[-92.5833,30.9833],"type":"Point"}
}