{
  "id": 2078645,
  "type": "Feature",
  "properties": {
    "tgn:hierarchy":[
        "tgn:2078645",
        "tgn:1000001",
        "tgn:7012149",
        "tgn:1002596",
        "tgn:7007706",
        "tgn:7029392"
    ],
    "tgn:id":2078645,
    "tgn:name":"Buckeye Lake",
    "tgn:placetype":[
        "aat:300008347"
    ]
},
  "bbox": [],
  "geometry": {"coordinates":[-82.4667,39.9333],"type":"Point"}
}