{
  "id": 2467713,
  "type": "Feature",
  "properties": {
    "tgn:hierarchy":[
        "tgn:2467713",
        "tgn:1000001",
        "tgn:7012149",
        "tgn:1002746",
        "tgn:7007568",
        "tgn:7029392"
    ],
    "tgn:id":2467713,
    "tgn:name":"Long Island",
    "tgn:placetype":[
        "aat:300008791"
    ]
},
  "bbox": [],
  "geometry": {"coordinates":[-76.05,43.15],"type":"Point"}
}