{
  "id": 7051396,
  "type": "Feature",
  "properties": {
    "tgn:hierarchy":[
        "tgn:7051396",
        "tgn:7003131",
        "tgn:1000003",
        "tgn:7008516",
        "tgn:1000080",
        "tgn:7029392"
    ],
    "tgn:id":7051396,
    "tgn:name":"La Costa",
    "tgn:placetype":[
        "aat:300008347"
    ]
},
  "bbox": [],
  "geometry": {"coordinates":[9.65,44.45],"type":"Point"}
}