{
  "id": 2656340,
  "type": "Feature",
  "properties": {
    "tgn:hierarchy":[
        "tgn:2656340",
        "tgn:1000001",
        "tgn:7012149",
        "tgn:7029392"
    ],
    "tgn:id":2656340,
    "tgn:name":"Shearing Corral Hollow",
    "tgn:placetype":[
        "aat:300008761"
    ]
},
  "bbox": [],
  "geometry": {"coordinates":[-111.05,42.0833],"type":"Point"}
}