{
  "id": 2692315,
  "type": "Feature",
  "properties": {
    "tgn:hierarchy":[
        "tgn:2692315",
        "tgn:7002659",
        "tgn:1000001",
        "tgn:2000012",
        "tgn:7012149",
        "tgn:7029392"
    ],
    "tgn:id":2692315,
    "tgn:name":"Stave Creek",
    "tgn:placetype":[
        "aat:300008347"
    ]
},
  "bbox": [],
  "geometry": {"coordinates":[-87.9333,31.55],"type":"Point"}
}