{
  "id": 2772078,
  "type": "Feature",
  "properties": {
    "tgn:hierarchy":[
        "tgn:2772078",
        "tgn:1000001",
        "tgn:7012149",
        "tgn:2001858",
        "tgn:7007825",
        "tgn:7029392"
    ],
    "tgn:id":2772078,
    "tgn:name":"Will Hall Creek",
    "tgn:placetype":[
        "aat:300008706"
    ]
},
  "bbox": [],
  "geometry": {"coordinates":[-87.3333,36.05],"type":"Point"}
}