{
  "id": 7559837,
  "type": "Feature",
  "properties": {
    "tgn:hierarchy":[
        "tgn:7559837",
        "tgn:1000004",
        "tgn:7000198",
        "tgn:7016788",
        "tgn:7029392"
    ],
    "tgn:id":7559837,
    "tgn:name:en":"Nith\u0101rw\u0101la ki Dh\u0101ni",
    "tgn:placetype":[
        "aat:300008347"
    ]
},
  "bbox": [],
  "geometry": {"coordinates":[75.539263,26.976019],"type":"Point"}
}