{
  "id": 7239837,
  "type": "Feature",
  "properties": {
    "tgn:hierarchy":[
        "tgn:7239837",
        "tgn:7003456",
        "tgn:1000003",
        "tgn:1000063",
        "tgn:7018236",
        "tgn:7029392"
    ],
    "tgn:id":7239837,
    "tgn:name":"Hontjens",
    "tgn:placetype":[
        "aat:300008347"
    ]
},
  "bbox": [],
  "geometry": {"coordinates":[5.066667,51.366667],"type":"Point"}
}