{
  "id": 2730951,
  "type": "Feature",
  "properties": {
    "tgn:hierarchy":[
        "tgn:2730951",
        "tgn:1000001",
        "tgn:7012149",
        "tgn:2001879",
        "tgn:7007825",
        "tgn:7029392"
    ],
    "tgn:id":2730951,
    "tgn:name":"Tubbs Spring",
    "tgn:placetype":[
        "aat:300008697"
    ]
},
  "bbox": [],
  "geometry": {"coordinates":[-87.7667,36.05],"type":"Point"}
}