{
  "id": 2002842,
  "type": "Feature",
  "properties": {
    "tgn:hierarchy":[
        "tgn:2002842",
        "tgn:7002659",
        "tgn:1000001",
        "tgn:7012149",
        "tgn:2000031",
        "tgn:7029392"
    ],
    "tgn:id":2002842,
    "tgn:name":"Boligee",
    "tgn:placetype":[
        "aat:300008347"
    ]
},
  "bbox": [],
  "geometry": {"coordinates":[-88.0167,32.75],"type":"Point"}
}