{
  "id": 2748041,
  "type": "Feature",
  "properties": {
    "tgn:hierarchy":[
        "tgn:2748041",
        "tgn:1000001",
        "tgn:2000201",
        "tgn:7012149",
        "tgn:7007158",
        "tgn:7029392"
    ],
    "tgn:id":2748041,
    "tgn:name":"Waldorf Mine",
    "tgn:placetype":[
        "aat:300000390"
    ]
},
  "bbox": [],
  "geometry": {"coordinates":[-105.7667,39.6333],"type":"Point"}
}