{
  "id": 2396687,
  "type": "Feature",
  "properties": {
    "tgn:hierarchy":[
        "tgn:2396687",
        "tgn:1000001",
        "tgn:7012149",
        "tgn:7007158",
        "tgn:2000254",
        "tgn:7029392"
    ],
    "tgn:id":2396687,
    "tgn:name":"Holy Joe Creek",
    "tgn:placetype":[
        "aat:300008706"
    ]
},
  "bbox": [],
  "geometry": {"coordinates":[-102.2333,40.1167],"type":"Point"}
}