{
  "id": 7392121,
  "type": "Feature",
  "properties": {
    "tgn:hierarchy":[
        "tgn:7392121",
        "tgn:7005581",
        "tgn:1000001",
        "tgn:7005560",
        "tgn:7029392"
    ],
    "tgn:id":7392121,
    "tgn:name":"Rancho Viejo",
    "tgn:placetype":[
        "aat:300008347"
    ]
},
  "bbox": [],
  "geometry": {"coordinates":[-107.466667,27.866667],"type":"Point"}
}