{
  "id": 7019192,
  "type": "Feature",
  "properties": {
    "tgn:hierarchy":[
        "tgn:7019192",
        "tgn:1002483",
        "tgn:7017508",
        "tgn:1000001",
        "tgn:7012149",
        "tgn:7007249",
        "tgn:7029392"
    ],
    "tgn:id":7019192,
    "tgn:name":"Nihoa",
    "tgn:placetype":[
        "aat:300008791"
    ]
},
  "bbox": [],
  "geometry": {"coordinates":[-161.9167,23.05],"type":"Point"}
}