{
  "id": 1134930,
  "type": "Feature",
  "properties": {
    "tgn:hierarchy":[
        "tgn:1134930",
        "tgn:1000001",
        "tgn:7012149",
        "tgn:7007255",
        "tgn:7029392"
    ],
    "tgn:id":1134930,
    "tgn:name":"Tygarts Creek",
    "tgn:placetype":[
        "aat:300008706"
    ]
},
  "bbox": [],
  "geometry": {"coordinates":[-83.2667,38.2833],"type":"Point"}
}