{
  "id": 7488495,
  "type": "Feature",
  "properties": {
    "tgn:hierarchy":[
        "tgn:7488495",
        "tgn:1000004",
        "tgn:7491221",
        "tgn:1000141",
        "tgn:7029392"
    ],
    "tgn:id":7488495,
    "tgn:name":"Longquan Xi",
    "tgn:placetype":[
        "aat:300008699"
    ]
},
  "bbox": [],
  "geometry": {"coordinates":[121.208611,23.141667],"type":"Point"}
}