{
  "id": 2375811,
  "type": "Feature",
  "properties": {
    "tgn:hierarchy":[
        "tgn:2375811",
        "tgn:1000001",
        "tgn:7012149",
        "tgn:7007825",
        "tgn:7029392"
    ],
    "tgn:id":2375811,
    "tgn:name":"Happy Hollow",
    "tgn:placetype":[
        "aat:300008761"
    ]
},
  "bbox": [],
  "geometry": {"coordinates":[-85.8833,36.4167],"type":"Point"}
}