{
  "id": 2058003,
  "type": "Feature",
  "properties": {
    "tgn:hierarchy":[
        "tgn:2058003",
        "tgn:1000001",
        "tgn:7012149",
        "tgn:2001253",
        "tgn:7007523",
        "tgn:7029392"
    ],
    "tgn:id":2058003,
    "tgn:name":"Bellamy",
    "tgn:placetype":[
        "aat:300008347",
        "aat:300387210"
    ]
},
  "bbox": [],
  "geometry": {"coordinates":[-94.1667,37.6833],"type":"Point"}
}