{
  "id": 7241709,
  "type": "Feature",
  "properties": {
    "tgn:hierarchy":[
        "tgn:7241709",
        "tgn:7007877",
        "tgn:1000003",
        "tgn:1000063",
        "tgn:4012014",
        "tgn:7029392"
    ],
    "tgn:id":7241709,
    "tgn:name":"Leernes, Bois de",
    "tgn:placetype":[
        "aat:300008863"
    ]
},
  "bbox": [],
  "geometry": {"coordinates":[4.283333,50.383333],"type":"Point"}
}