{
  "id": 7589975,
  "type": "Feature",
  "properties": {
    "tgn:hierarchy":[
        "tgn:7589975",
        "tgn:1000004",
        "tgn:7000198",
        "tgn:7000799",
        "tgn:7029392"
    ],
    "tgn:id":7589975,
    "tgn:name:en":"Alpathar",
    "tgn:placetype":[
        "aat:300008347"
    ]
},
  "bbox": [],
  "geometry": {"coordinates":[74.325949,33.987233],"type":"Point"}
}