{
  "id": 2206089,
  "type": "Feature",
  "properties": {
    "tgn:hierarchy":[
        "tgn:2206089",
        "tgn:1000001",
        "tgn:7012149",
        "tgn:2000493",
        "tgn:7007250",
        "tgn:7029392"
    ],
    "tgn:id":2206089,
    "tgn:name":"Bull Spring",
    "tgn:placetype":[
        "aat:300008697"
    ]
},
  "bbox": [],
  "geometry": {"coordinates":[-114.4833,42.0667],"type":"Point"}
}