<<<<<<< HEAD
{
  "id": 7357214,
  "type": "Feature",
  "properties": {
    "tgn:hierarchy":[
        "tgn:7357214",
        "tgn:1000001",
        "tgn:7005591",
        "tgn:7005560",
        "tgn:7029392"
    ],
    "tgn:id":7357214,
    "tgn:name":"Chisme",
    "tgn:placetype":[
        "aat:300008347"
    ]
},
  "bbox": [],
  "geometry": {"coordinates":[-95.766667,17.25],"type":"Point"}
}
=======
{"geometry":{"type":"Point","coordinates":[-95.766667,17.250000]},"type":"Feature","properties":{"hierarchy":["tgn:7357214","tgn:1000001","tgn:7005591","tgn:7005560","tgn:7029392"],"placetype":["aat:300008347"],"id":7357214,"name:xx":"Chisme"}}
>>>>>>> 03f74aca74312dbeaf24d7e61306dd6a786dc3d0
