{
  "id": 2359874,
  "type": "Feature",
  "properties": {
    "tgn:hierarchy":[
        "tgn:2359874",
        "tgn:1000001",
        "tgn:7012149",
        "tgn:2000928",
        "tgn:7007515",
        "tgn:7029392"
    ],
    "tgn:id":2359874,
    "tgn:name":"Grapevine Ridge",
    "tgn:placetype":[
        "aat:300266640"
    ]
},
  "bbox": [],
  "geometry": {"coordinates":[-69.25,45.3167],"type":"Point"}
}