{
  "id": 2510482,
  "type": "Feature",
  "properties": {
    "tgn:hierarchy":[
        "tgn:2510482",
        "tgn:1000001",
        "tgn:7012149",
        "tgn:2000216",
        "tgn:7007158",
        "tgn:7029392"
    ],
    "tgn:id":2510482,
    "tgn:name":"Middle Supply Creek",
    "tgn:placetype":[
        "aat:300008706"
    ]
},
  "bbox": [],
  "geometry": {"coordinates":[-105.9167,40.2833],"type":"Point"}
}