{
  "id": 7211006,
  "type": "Feature",
  "properties": {
    "tgn:hierarchy":[
        "tgn:7211006",
        "tgn:1000003",
        "tgn:7003682",
        "tgn:7000084",
        "tgn:7029392"
    ],
    "tgn:id":7211006,
    "tgn:name":"Balkert",
    "tgn:placetype":[
        "aat:300000206"
    ]
},
  "bbox": [],
  "geometry": {"coordinates":[7.65,50.75],"type":"Point"}
}