{
  "id": 2745102,
  "type": "Feature",
  "properties": {
    "tgn:hierarchy":[
        "tgn:2745102",
        "tgn:1000001",
        "tgn:7012149",
        "tgn:2001217",
        "tgn:7007523",
        "tgn:7029392"
    ],
    "tgn:id":2745102,
    "tgn:name":"Village Creek",
    "tgn:placetype":[
        "aat:300008706"
    ]
},
  "bbox": [],
  "geometry": {"coordinates":[-90.2333,37.6333],"type":"Point"}
}