{
  "id": 2679802,
  "type": "Feature",
  "properties": {
    "tgn:hierarchy":[
        "tgn:2679802",
        "tgn:1000001",
        "tgn:7012149",
        "tgn:7007157",
        "tgn:1002675",
        "tgn:7029392"
    ],
    "tgn:id":2679802,
    "tgn:name":"South Fork Rock Creek",
    "tgn:placetype":[
        "aat:300008706"
    ]
},
  "bbox": [],
  "geometry": {"coordinates":[-119.3833,38.4667],"type":"Point"}
}