{
  "id": 2589679,
  "type": "Feature",
  "properties": {
    "tgn:hierarchy":[
        "tgn:2589679",
        "tgn:1000001",
        "tgn:7012149",
        "tgn:1002790",
        "tgn:7007240",
        "tgn:7029392"
    ],
    "tgn:id":2589679,
    "tgn:name":"Point Pleasant",
    "tgn:placetype":[
        "aat:300008850"
    ]
},
  "bbox": [],
  "geometry": {"coordinates":[-82.8167,27.9167],"type":"Point"}
}