{
  "id": 2728281,
  "type": "Feature",
  "properties": {
    "tgn:hierarchy":[
        "tgn:2728281",
        "tgn:1000001",
        "tgn:2002320",
        "tgn:7012149",
        "tgn:7007922",
        "tgn:7029392"
    ],
    "tgn:id":2728281,
    "tgn:name":"Travis Creek",
    "tgn:placetype":[
        "aat:300008706"
    ]
},
  "bbox": [],
  "geometry": {"coordinates":[-91.0333,44.5833],"type":"Point"}
}