{
  "id": 2580432,
  "type": "Feature",
  "properties": {
    "tgn:hierarchy":[
        "tgn:2580432",
        "tgn:1000001",
        "tgn:2000920",
        "tgn:7012149",
        "tgn:7007515",
        "tgn:7029392"
    ],
    "tgn:id":2580432,
    "tgn:name":"Pigeon Brook",
    "tgn:placetype":[
        "aat:300008699"
    ]
},
  "bbox": [],
  "geometry": {"coordinates":[-70.7167,43.8333],"type":"Point"}
}