{
  "id": 1017570,
  "type": "Feature",
  "properties": {
    "tgn:hierarchy":[
        "tgn:1017570",
        "tgn:7005580",
        "tgn:1000001",
        "tgn:7005560",
        "tgn:7029392"
    ],
    "tgn:id":1017570,
    "tgn:name":"Huehuet\u00e1n",
    "tgn:placetype":[
        "aat:300008347"
    ]
},
  "bbox": [],
  "geometry": {"coordinates":[-92.366667,15.016667],"type":"Point"}
}