{
  "id": 2769309,
  "type": "Feature",
  "properties": {
    "tgn:hierarchy":[
        "tgn:2769309",
        "tgn:1002996",
        "tgn:1000001",
        "tgn:7012149",
        "tgn:7007711",
        "tgn:7029392"
    ],
    "tgn:id":2769309,
    "tgn:name":"Wickford Cove",
    "tgn:placetype":[
        "aat:300132316"
    ]
},
  "bbox": [],
  "geometry": {"coordinates":[-71.45,41.5667],"type":"Point"}
}