<<<<<<< HEAD
{
  "id": 2769309,
  "type": "Feature",
  "properties": {
    "tgn:hierarchy":[
        "tgn:2769309",
        "tgn:1002996",
        "tgn:1000001",
        "tgn:7012149",
        "tgn:7007711",
        "tgn:7029392"
    ],
    "tgn:id":2769309,
    "tgn:name":"Wickford Cove",
    "tgn:placetype":[
        "aat:300132316"
    ]
},
  "bbox": [],
  "geometry": {"coordinates":[-71.45,41.5667],"type":"Point"}
}
=======
{"geometry":{"type":"Point","coordinates":[-71.450000,41.566700]},"type":"Feature","properties":{"hierarchy":["tgn:2769309","tgn:1002996","tgn:1000001","tgn:7012149","tgn:7007711","tgn:7029392"],"placetype":["aat:300132316"],"id":2769309,"name:xx":"Wickford Cove"}}
>>>>>>> 03f74aca74312dbeaf24d7e61306dd6a786dc3d0
