{
  "id": 1130564,
  "type": "Feature",
  "properties": {
    "tgn:hierarchy":[
        "tgn:1130564",
        "tgn:7002445",
        "tgn:1000003",
        "tgn:7012077",
        "tgn:7008591",
        "tgn:7029392"
    ],
    "tgn:id":1130564,
    "tgn:name:en":"Tamar",
    "tgn:placetype":[
        "aat:300008707",
        "aat:300008699"
    ]
},
  "bbox": [],
  "geometry": {"coordinates":[-4.216667,50.466667],"type":"Point"}
}