{
  "id": 7231469,
  "type": "Feature",
  "properties": {
    "tgn:hierarchy":[
        "tgn:7231469",
        "tgn:7002681",
        "tgn:7001395",
        "tgn:1000003",
        "tgn:1000074",
        "tgn:7029392"
    ],
    "tgn:id":7231469,
    "tgn:name":"Man\u00f3li M\u00edti, \u00c1kra",
    "tgn:placetype":[
        "aat:300008850"
    ]
},
  "bbox": [],
  "geometry": {"coordinates":[23.866667,38.383333],"type":"Point"}
}