{
  "id": 7590442,
  "type": "Feature",
  "properties": {
    "tgn:hierarchy":[
        "tgn:7590442",
        "tgn:1000004",
        "tgn:7000198",
        "tgn:7000799",
        "tgn:7029392"
    ],
    "tgn:id":7590442,
    "tgn:name:en":"Gabra Forest",
    "tgn:placetype":[
        "aat:300008863"
    ]
},
  "bbox": [],
  "geometry": {"coordinates":[73.847222,34.358333],"type":"Point"}
}