{
  "id": 2728491,
  "type": "Feature",
  "properties": {
    "tgn:hierarchy":[
        "tgn:2728491",
        "tgn:1000001",
        "tgn:2001810",
        "tgn:7012149",
        "tgn:7007713",
        "tgn:7029392"
    ],
    "tgn:id":2728491,
    "tgn:name":"Trebor Draw",
    "tgn:placetype":[
        "aat:300008761"
    ]
},
  "bbox": [],
  "geometry": {"coordinates":[-103.9167,44.15],"type":"Point"}
}