{
  "id": 7298597,
  "type": "Feature",
  "properties": {
    "tgn:hierarchy":[
        "tgn:7298597",
        "tgn:7002758",
        "tgn:7002823",
        "tgn:1000003",
        "tgn:1000095",
        "tgn:7029392"
    ],
    "tgn:id":7298597,
    "tgn:name":"Trebejil, Arroyo del",
    "tgn:placetype":[
        "aat:300008699"
    ]
},
  "bbox": [],
  "geometry": {"coordinates":[-6.566667,37.15],"type":"Point"}
}