{
  "id": 2402660,
  "type": "Feature",
  "properties": {
    "tgn:hierarchy":[
        "tgn:2402660",
        "tgn:1000001",
        "tgn:7012149",
        "tgn:2001718",
        "tgn:7007708",
        "tgn:7029392"
    ],
    "tgn:id":2402660,
    "tgn:name":"Hot Rock Reservoir",
    "tgn:placetype":[
        "aat:300006191"
    ]
},
  "bbox": [],
  "geometry": {"coordinates":[-117.05,43.4167],"type":"Point"}
}