<<<<<<< HEAD
{
  "id": 7373440,
  "type": "Feature",
  "properties": {
    "tgn:hierarchy":[
        "tgn:7373440",
        "tgn:1000001",
        "tgn:7005599",
        "tgn:7005560",
        "tgn:7029392"
    ],
    "tgn:id":7373440,
    "tgn:name":"La Aguada",
    "tgn:placetype":[
        "aat:300008347"
    ]
},
  "bbox": [],
  "geometry": {"coordinates":[-97.75,22.0],"type":"Point"}
}
=======
{"geometry":{"type":"Point","coordinates":[-97.750000,22.000000]},"type":"Feature","properties":{"hierarchy":["tgn:7373440","tgn:1000001","tgn:7005599","tgn:7005560","tgn:7029392"],"placetype":["aat:300008347"],"id":7373440,"name:xx":"La Aguada"}}
>>>>>>> 03f74aca74312dbeaf24d7e61306dd6a786dc3d0
