{
  "id": 2480481,
  "type": "Feature",
  "properties": {
    "tgn:hierarchy":[
        "tgn:2480481",
        "tgn:1000001",
        "tgn:7012149",
        "tgn:7007253",
        "tgn:7029392"
    ],
    "tgn:id":2480481,
    "tgn:name":"Lake Wahaboncey",
    "tgn:placetype":[
        "aat:300008680"
    ]
},
  "bbox": [],
  "geometry": {"coordinates":[-95.8833,40.8833],"type":"Point"}
}