{
  "id": 7000965,
  "type": "Feature",
  "properties": {
    "tgn:hierarchy":[
        "tgn:7000965",
        "tgn:7005194",
        "tgn:1000004",
        "tgn:1000142",
        "tgn:7029392"
    ],
    "tgn:id":7000965,
    "tgn:name":"Sukhothai, Changwat",
    "tgn:placetype":[
        "aat:300387145",
        "aat:300000774"
    ]
},
  "bbox": [],
  "geometry": {"coordinates":[99.6667,17.25],"type":"Point"}
}