{
  "id": 2358148,
  "type": "Feature",
  "properties": {
    "tgn:hierarchy":[
        "tgn:2358148",
        "tgn:1000001",
        "tgn:7012149",
        "tgn:1002440",
        "tgn:7007568",
        "tgn:7029392"
    ],
    "tgn:id":2358148,
    "tgn:name":"Grampus Lake Mountain",
    "tgn:placetype":[
        "aat:300008798"
    ]
},
  "bbox": [],
  "geometry": {"coordinates":[-74.4333,44.0333],"type":"Point"}
}