{
  "id": 7125816,
  "type": "Feature",
  "properties": {
    "tgn:hierarchy":[
        "tgn:7125816",
        "tgn:1000003",
        "tgn:7003682",
        "tgn:7000084",
        "tgn:7029392"
    ],
    "tgn:id":7125816,
    "tgn:name":"Niederro\u00dfbach",
    "tgn:placetype":[
        "aat:300008347"
    ]
},
  "bbox": [],
  "geometry": {"coordinates":[8.033333,50.65],"type":"Point"}
}