{
  "id": 7295998,
  "type": "Feature",
  "properties": {
    "tgn:hierarchy":[
        "tgn:7295998",
        "tgn:7002810",
        "tgn:7001158",
        "tgn:1000003",
        "tgn:1000095",
        "tgn:7029392"
    ],
    "tgn:id":7295998,
    "tgn:name":"Villamor\u00f3n",
    "tgn:placetype":[
        "aat:300008347"
    ]
},
  "bbox": [],
  "geometry": {"coordinates":[-4.016667,42.466667],"type":"Point"}
}