{
  "id": 7197353,
  "type": "Feature",
  "properties": {
    "tgn:hierarchy":[
        "tgn:7197353",
        "tgn:7000096",
        "tgn:1000003",
        "tgn:7000084",
        "tgn:7029392"
    ],
    "tgn:id":7197353,
    "tgn:name":"Dollgow",
    "tgn:placetype":[
        "aat:300008347"
    ]
},
  "bbox": [],
  "geometry": {"coordinates":[13.016667,53.083333],"type":"Point"}
}