{
  "id": 2564165,
  "type": "Feature",
  "properties": {
    "tgn:hierarchy":[
        "tgn:2564165",
        "tgn:1000001",
        "tgn:7012149",
        "tgn:2000906",
        "tgn:7007256",
        "tgn:7029392"
    ],
    "tgn:id":2564165,
    "tgn:name":"P-Kaw-Shun Creek",
    "tgn:placetype":[
        "aat:300008706"
    ]
},
  "bbox": [],
  "geometry": {"coordinates":[-90.2667,30.5333],"type":"Point"}
}