{
  "id": 7518969,
  "type": "Feature",
  "properties": {
    "tgn:hierarchy":[
        "tgn:7518969",
        "tgn:1009227",
        "tgn:7001866",
        "tgn:1000226",
        "tgn:1000006",
        "tgn:7029392"
    ],
    "tgn:id":7518969,
    "tgn:name:en":"Burn Creek",
    "tgn:placetype":[
        "aat:300008699"
    ]
},
  "bbox": [],
  "geometry": {"coordinates":[172.516667,-42.183333],"type":"Point"}
}