{
  "id": 2489755,
  "type": "Feature",
  "properties": {
    "tgn:hierarchy":[
        "tgn:2489755",
        "tgn:1000001",
        "tgn:7012149",
        "tgn:2000969",
        "tgn:7007520",
        "tgn:7029392"
    ],
    "tgn:id":2489755,
    "tgn:name":"Malone Island",
    "tgn:placetype":[
        "aat:300008791"
    ]
},
  "bbox": [],
  "geometry": {"coordinates":[-88.7833,47.9667],"type":"Point"}
}