{
  "id": 2682491,
  "type": "Feature",
  "properties": {
    "tgn:hierarchy":[
        "tgn:2682491",
        "tgn:1000001",
        "tgn:7012149",
        "tgn:2002069",
        "tgn:7007826",
        "tgn:7029392"
    ],
    "tgn:id":2682491,
    "tgn:name":"Southeast Laterals Watershed Reservoir Number 9",
    "tgn:placetype":[
        "aat:300006191"
    ]
},
  "bbox": [],
  "geometry": {"coordinates":[-98.9833,31.3667],"type":"Point"}
}