{
  "id": 2108492,
  "type": "Feature",
  "properties": {
    "tgn:hierarchy":[
        "tgn:2108492",
        "tgn:1000001",
        "tgn:7012149",
        "tgn:1002898",
        "tgn:7007826",
        "tgn:7029392"
    ],
    "tgn:id":2108492,
    "tgn:name":"Whitehouse",
    "tgn:placetype":[
        "aat:300008347"
    ]
},
  "bbox": [],
  "geometry": {"coordinates":[-95.2167,32.2167],"type":"Point"}
}