{
  "id": 2132253,
  "type": "Feature",
  "properties": {
    "tgn:hierarchy":[
        "tgn:2132253",
        "tgn:1000001",
        "tgn:7012149",
        "tgn:2002122",
        "tgn:7007827",
        "tgn:7029392"
    ],
    "tgn:id":2132253,
    "tgn:name":"Amethyst Basin",
    "tgn:placetype":[
        "aat:300386845"
    ]
},
  "bbox": [],
  "geometry": {"coordinates":[-110.7667,40.75],"type":"Point"}
}