{
  "id": 7413766,
  "type": "Feature",
  "properties": {
    "tgn:hierarchy":[
        "tgn:7413766",
        "tgn:1000001",
        "tgn:7005598",
        "tgn:7005560",
        "tgn:7029392"
    ],
    "tgn:id":7413766,
    "tgn:name":"\u00c1lvaro Obreg\u00f3n",
    "tgn:placetype":[
        "aat:300008347"
    ]
},
  "bbox": [],
  "geometry": {"coordinates":[-98.473611,19.463889],"type":"Point"}
}