<<<<<<< HEAD
{
  "id": 2405514,
  "type": "Feature",
  "properties": {
    "tgn:hierarchy":[
        "tgn:2405514",
        "tgn:1000001",
        "tgn:7012149",
        "tgn:2001716",
        "tgn:7007708",
        "tgn:7029392"
    ],
    "tgn:id":2405514,
    "tgn:name":"Hughes Creek",
    "tgn:placetype":[
        "aat:300008706"
    ]
},
  "bbox": [],
  "geometry": {"coordinates":[-122.6,44.4333],"type":"Point"}
}
=======
{"geometry":{"type":"Point","coordinates":[-122.600000,44.433300]},"type":"Feature","properties":{"hierarchy":["tgn:2405514","tgn:1000001","tgn:7012149","tgn:2001716","tgn:7007708","tgn:7029392"],"placetype":["aat:300008706"],"id":2405514,"name:xx":"Hughes Creek"}}
>>>>>>> 03f74aca74312dbeaf24d7e61306dd6a786dc3d0
