{
  "id": 1045549,
  "type": "Feature",
  "properties": {
    "tgn:hierarchy":[
        "tgn:1045549",
        "tgn:1003488",
        "tgn:1000003",
        "tgn:7002993",
        "tgn:1000080",
        "tgn:7029392"
    ],
    "tgn:id":1045549,
    "tgn:name":"Montereale Valcellina",
    "tgn:placetype":[
        "aat:300008347"
    ]
},
  "bbox": [],
  "geometry": {"coordinates":[12.659444,46.159722],"type":"Point"}
}