{
  "id": 7007004,
  "type": "Feature",
  "properties": {
    "tgn:hierarchy":[
        "tgn:7007004",
        "tgn:7003501",
        "tgn:7003478",
        "tgn:1000003",
        "tgn:1000078",
        "tgn:7029392"
    ],
    "tgn:id":7007004,
    "tgn:name":"Cootehill",
    "tgn:placetype":[
        "aat:300008347"
    ]
},
  "bbox": [],
  "geometry": {"coordinates":[-7.0833,54.0667],"type":"Point"}
}