<<<<<<< HEAD
{
  "id": 2764117,
  "type": "Feature",
  "properties": {
    "tgn:hierarchy":[
        "tgn:2764117",
        "tgn:1000001",
        "tgn:7012149",
        "tgn:2000430",
        "tgn:7007248",
        "tgn:7029392"
    ],
    "tgn:id":2764117,
    "tgn:name":"Wheeler Knob",
    "tgn:placetype":[
        "aat:300008798"
    ]
},
  "bbox": [],
  "geometry": {"coordinates":[-83.5833,34.9667],"type":"Point"}
}
=======
{"geometry":{"type":"Point","coordinates":[-83.583300,34.966700]},"type":"Feature","properties":{"hierarchy":["tgn:2764117","tgn:1000001","tgn:7012149","tgn:2000430","tgn:7007248","tgn:7029392"],"placetype":["aat:300008798"],"id":2764117,"name:xx":"Wheeler Knob"}}
>>>>>>> 03f74aca74312dbeaf24d7e61306dd6a786dc3d0
