{
  "id": 7214824,
  "type": "Feature",
  "properties": {
    "tgn:hierarchy":[
        "tgn:7214824",
        "tgn:1000003",
        "tgn:7003677",
        "tgn:7000084",
        "tgn:7029392"
    ],
    "tgn:id":7214824,
    "tgn:name":"Blemcke",
    "tgn:placetype":[
        "aat:300008347"
    ]
},
  "bbox": [],
  "geometry": {"coordinates":[7.883333,51.233333],"type":"Point"}
}