{
  "id": 2639376,
  "type": "Feature",
  "properties": {
    "tgn:hierarchy":[
        "tgn:2639376",
        "tgn:1000001",
        "tgn:7012149",
        "tgn:2000799",
        "tgn:7007255",
        "tgn:7029392"
    ],
    "tgn:id":2639376,
    "tgn:name":"Salt Well Creek",
    "tgn:placetype":[
        "aat:300008706"
    ]
},
  "bbox": [],
  "geometry": {"coordinates":[-83.85,38.1167],"type":"Point"}
}