{
  "id": 7376646,
  "type": "Feature",
  "properties": {
    "tgn:hierarchy":[
        "tgn:7376646",
        "tgn:1000001",
        "tgn:7005589",
        "tgn:7005560",
        "tgn:7029392"
    ],
    "tgn:id":7376646,
    "tgn:name":"Loma Alta",
    "tgn:placetype":[
        "aat:300008347"
    ]
},
  "bbox": [],
  "geometry": {"coordinates":[-99.574167,24.694444],"type":"Point"}
}