{
  "id": 2563564,
  "type": "Feature",
  "properties": {
    "tgn:hierarchy":[
        "tgn:2563564",
        "tgn:1000001",
        "tgn:7012149",
        "tgn:2002005",
        "tgn:7007826",
        "tgn:7029392"
    ],
    "tgn:id":2563564,
    "tgn:name":"Owl Tanks",
    "tgn:placetype":[
        "aat:300006191"
    ]
},
  "bbox": [],
  "geometry": {"coordinates":[-105.9333,31.7167],"type":"Point"}
}