{
  "id": 2363926,
  "type": "Feature",
  "properties": {
    "tgn:hierarchy":[
        "tgn:2363926",
        "tgn:1000001",
        "tgn:7006451",
        "tgn:7012149",
        "tgn:2000100",
        "tgn:7029392"
    ],
    "tgn:id":2363926,
    "tgn:name":"Green Mine",
    "tgn:placetype":[
        "aat:300000390"
    ]
},
  "bbox": [],
  "geometry": {"coordinates":[-111.85,31.9833],"type":"Point"}
}