<<<<<<< HEAD
{
  "id": 2250446,
  "type": "Feature",
  "properties": {
    "tgn:hierarchy":[
        "tgn:2250446",
        "tgn:1000001",
        "tgn:2000307",
        "tgn:7012149",
        "tgn:7007248",
        "tgn:7029392"
    ],
    "tgn:id":2250446,
    "tgn:name":"Colonial Heights",
    "tgn:placetype":[
        "aat:300008347"
    ]
},
  "bbox": [],
  "geometry": {"coordinates":[-81.7333,32.4167],"type":"Point"}
}
=======
{"geometry":{"type":"Point","coordinates":[-81.733300,32.416700]},"type":"Feature","properties":{"hierarchy":["tgn:2250446","tgn:1000001","tgn:2000307","tgn:7012149","tgn:7007248","tgn:7029392"],"placetype":["aat:300008347"],"id":2250446,"name:xx":"Colonial Heights"}}
>>>>>>> 03f74aca74312dbeaf24d7e61306dd6a786dc3d0
