{
  "id": 2250446,
  "type": "Feature",
  "properties": {
    "tgn:hierarchy":[
        "tgn:2250446",
        "tgn:1000001",
        "tgn:2000307",
        "tgn:7012149",
        "tgn:7007248",
        "tgn:7029392"
    ],
    "tgn:id":2250446,
    "tgn:name":"Colonial Heights",
    "tgn:placetype":[
        "aat:300008347"
    ]
},
  "bbox": [],
  "geometry": {"coordinates":[-81.7333,32.4167],"type":"Point"}
}