{
  "id": 2316978,
  "type": "Feature",
  "properties": {
    "tgn:hierarchy":[
        "tgn:2316978",
        "tgn:1000001",
        "tgn:7012149",
        "tgn:7016021",
        "tgn:7007568",
        "tgn:7029392"
    ],
    "tgn:id":2316978,
    "tgn:name":"Emery Island",
    "tgn:placetype":[
        "aat:300008791"
    ]
},
  "bbox": [],
  "geometry": {"coordinates":[-75.6333,44.4667],"type":"Point"}
}