{
  "id": 1118574,
  "type": "Feature",
  "properties": {
    "tgn:hierarchy":[
        "tgn:1118574",
        "tgn:7003139",
        "tgn:1000003",
        "tgn:7003080",
        "tgn:1000080",
        "tgn:7029392"
    ],
    "tgn:id":1118574,
    "tgn:name":"Vico, Lago di",
    "tgn:placetype":[
        "aat:300008680"
    ]
},
  "bbox": [],
  "geometry": {"coordinates":[12.166667,42.316667],"type":"Point"}
}