<<<<<<< HEAD
{
  "id": 7020876,
  "type": "Feature",
  "properties": {
    "tgn:hierarchy":[
        "tgn:7020876",
        "tgn:1000001",
        "tgn:2000458",
        "tgn:7012149",
        "tgn:7007250",
        "tgn:7029392"
    ],
    "tgn:id":7020876,
    "tgn:name":"Dip Vat Creek",
    "tgn:placetype":[
        "aat:300008706"
    ]
},
  "bbox": [],
  "geometry": {"coordinates":[-114.0667,43.35],"type":"Point"}
}
=======
{"geometry":{"type":"Point","coordinates":[-114.066700,43.350000]},"type":"Feature","properties":{"hierarchy":["tgn:7020876","tgn:1000001","tgn:2000458","tgn:7012149","tgn:7007250","tgn:7029392"],"placetype":["aat:300008706"],"id":7020876,"name:xx":"Dip Vat Creek"}}
>>>>>>> 03f74aca74312dbeaf24d7e61306dd6a786dc3d0
