{
  "id": 7280576,
  "type": "Feature",
  "properties": {
    "tgn:hierarchy":[
        "tgn:7280576",
        "tgn:1001702",
        "tgn:1000049",
        "tgn:1000002",
        "tgn:7029392"
    ],
    "tgn:id":7280576,
    "tgn:name":"Sin Nombre, Pen\u00ednsula",
    "tgn:placetype":[
        "aat:300008804"
    ]
},
  "bbox": [],
  "geometry": {"coordinates":[-73.416667,-51.916667],"type":"Point"}
}