{
  "id": 7012275,
  "type": "Feature",
  "properties": {
    "tgn:hierarchy":[
        "tgn:7012275",
        "tgn:1000004",
        "tgn:7029392"
    ],
    "tgn:id":7012275,
    "tgn:name":"\u00c7oruh",
    "tgn:placetype":[
        "aat:300008707"
    ]
},
  "bbox": [],
  "geometry": {"coordinates":[41.6667,41.5833],"type":"Point"}
}