{
  "id": 7433993,
  "type": "Feature",
  "properties": {
    "tgn:hierarchy":[
        "tgn:7433993",
        "tgn:1000001",
        "tgn:7005590",
        "tgn:7005560",
        "tgn:7029392"
    ],
    "tgn:id":7433993,
    "tgn:name":"Tir\u00edndaro",
    "tgn:placetype":[
        "aat:300008347"
    ]
},
  "bbox": [],
  "geometry": {"coordinates":[-101.75,19.766667],"type":"Point"}
}