{
  "id": 7514596,
  "type": "Feature",
  "properties": {
    "tgn:hierarchy":[
        "tgn:7514596",
        "tgn:1009227",
        "tgn:1000226",
        "tgn:7018437",
        "tgn:1000006",
        "tgn:7029392"
    ],
    "tgn:id":7514596,
    "tgn:name:en":"Deep Creek",
    "tgn:placetype":[
        "aat:300008699"
    ]
},
  "bbox": [],
  "geometry": {"coordinates":[170.35,-44.65],"type":"Point"}
}