{
  "id": 2162715,
  "type": "Feature",
  "properties": {
    "tgn:hierarchy":[
        "tgn:2162715",
        "tgn:7030515",
        "tgn:7006450",
        "tgn:1000001",
        "tgn:7012149",
        "tgn:7029392"
    ],
    "tgn:id":2162715,
    "tgn:name":"Bendel Island",
    "tgn:placetype":[
        "aat:300008791"
    ]
},
  "bbox": [],
  "geometry": {"coordinates":[-159.7833,1.3167],"type":"Point"}
}