<<<<<<< HEAD
{
  "id": 7173264,
  "type": "Feature",
  "properties": {
    "tgn:hierarchy":[
        "tgn:7173264",
        "tgn:1000003",
        "tgn:7003687",
        "tgn:7000084",
        "tgn:7029392"
    ],
    "tgn:id":7173264,
    "tgn:name":"Gro\u00dfer Steier-Berg",
    "tgn:placetype":[
        "aat:300008777"
    ]
},
  "bbox": [],
  "geometry": {"coordinates":[10.7,51.633333],"type":"Point"}
}
=======
{"geometry":{"type":"Point","coordinates":[10.700000,51.633333]},"type":"Feature","properties":{"hierarchy":["tgn:7173264","tgn:1000003","tgn:7003687","tgn:7000084","tgn:7029392"],"placetype":["aat:300008777"],"id":7173264,"name:xx":"Gro\u00dfer Steier-Berg"}}
>>>>>>> 03f74aca74312dbeaf24d7e61306dd6a786dc3d0
