{
  "id": 7417207,
  "type": "Feature",
  "properties": {
    "tgn:hierarchy":[
        "tgn:7417207",
        "tgn:7005584",
        "tgn:1000001",
        "tgn:7005560",
        "tgn:7029392"
    ],
    "tgn:id":7417207,
    "tgn:name":"San Jos\u00e9 de la Monta\u00f1a",
    "tgn:placetype":[
        "aat:300008347"
    ]
},
  "bbox": [],
  "geometry": {"coordinates":[-101.066389,20.603333],"type":"Point"}
}