<<<<<<< HEAD
{
  "id": 7482956,
  "type": "Feature",
  "properties": {
    "tgn:hierarchy":[
        "tgn:7482956",
        "tgn:1000004",
        "tgn:7489179",
        "tgn:1000141",
        "tgn:7029392"
    ],
    "tgn:id":7482956,
    "tgn:name":"Tiannong Miao",
    "tgn:placetype":[
        "aat:300007595"
    ]
},
  "bbox": [],
  "geometry": {"coordinates":[121.758889,24.814167],"type":"Point"}
}
=======
{"geometry":{"type":"Point","coordinates":[121.758889,24.814167]},"type":"Feature","properties":{"hierarchy":["tgn:7482956","tgn:1000004","tgn:7489179","tgn:1000141","tgn:7029392"],"placetype":["aat:300007595"],"id":7482956,"name:xx":"Tiannong Miao"}}
>>>>>>> 03f74aca74312dbeaf24d7e61306dd6a786dc3d0
