{
  "id": 2642491,
  "type": "Feature",
  "properties": {
    "tgn:hierarchy":[
        "tgn:2642491",
        "tgn:1000001",
        "tgn:7012149",
        "tgn:1002773",
        "tgn:7007240",
        "tgn:7029392"
    ],
    "tgn:id":2642491,
    "tgn:name":"Sandbar Lake",
    "tgn:placetype":[
        "aat:300008680"
    ]
},
  "bbox": [],
  "geometry": {"coordinates":[-82.15,28.3333],"type":"Point"}
}