{
  "id": 7543473,
  "type": "Feature",
  "properties": {
    "tgn:hierarchy":[
        "tgn:7543473",
        "tgn:7001242",
        "tgn:7016833",
        "tgn:1001225",
        "tgn:7029392"
    ],
    "tgn:id":7543473,
    "tgn:name:en":"Tir'at al Ba\u1e29ar\u012byah",
    "tgn:placetype":[
        "aat:300006075"
    ]
},
  "bbox": [],
  "geometry": {"coordinates":[31.692021,31.239463],"type":"Point"}
}