{
  "id": 7375109,
  "type": "Feature",
  "properties": {
    "tgn:hierarchy":[
        "tgn:7375109",
        "tgn:7005581",
        "tgn:1000001",
        "tgn:7005560",
        "tgn:7029392"
    ],
    "tgn:id":7375109,
    "tgn:name":"Rancho La Pulga",
    "tgn:placetype":[
        "aat:300000241"
    ]
},
  "bbox": [],
  "geometry": {"coordinates":[-108.066667,28.266667],"type":"Point"}
}