{
  "id": 7512006,
  "type": "Feature",
  "properties": {
    "tgn:hierarchy":[
        "tgn:7512006",
        "tgn:1008380",
        "tgn:7000507",
        "tgn:1000226",
        "tgn:1000006",
        "tgn:7029392"
    ],
    "tgn:id":7512006,
    "tgn:name:en":"Kaikanui River",
    "tgn:placetype":[
        "aat:300008699"
    ]
},
  "bbox": [],
  "geometry": {"coordinates":[174.283333,-35.533333],"type":"Point"}
}