<<<<<<< HEAD
{
  "id": 2766178,
  "type": "Feature",
  "properties": {
    "tgn:hierarchy":[
        "tgn:2766178",
        "tgn:1000001",
        "tgn:7012149",
        "tgn:1002588",
        "tgn:7007520",
        "tgn:7029392"
    ],
    "tgn:id":2766178,
    "tgn:name":"White Lake",
    "tgn:placetype":[
        "aat:300008680"
    ]
},
  "bbox": [],
  "geometry": {"coordinates":[-84.2167,42.0333],"type":"Point"}
}
=======
{"geometry":{"type":"Point","coordinates":[-84.216700,42.033300]},"type":"Feature","properties":{"hierarchy":["tgn:2766178","tgn:1000001","tgn:7012149","tgn:1002588","tgn:7007520","tgn:7029392"],"placetype":["aat:300008680"],"id":2766178,"name:xx":"White Lake"}}
>>>>>>> 03f74aca74312dbeaf24d7e61306dd6a786dc3d0
