{
  "id": 7007658,
  "type": "Feature",
  "properties": {
    "tgn:hierarchy":[
        "tgn:7007658",
        "tgn:1000003",
        "tgn:7029392"
    ],
    "tgn:id":7007658,
    "tgn:name:en":"Great Saint Bernard Pass",
    "tgn:name:fr":"Grand-Saint-Bernard, Col du",
    "tgn:name:la":"Mons Jovis",
    "tgn:placetype":[
        "aat:300259572"
    ]
},
  "bbox": [],
  "geometry": {"coordinates":[7.1667,45.8333],"type":"Point"}
}