{
  "id": 2771966,
  "type": "Feature",
  "properties": {
    "tgn:hierarchy":[
        "tgn:2771966",
        "tgn:1000001",
        "tgn:7012149",
        "tgn:7007522",
        "tgn:7029392"
    ],
    "tgn:id":2771966,
    "tgn:name":"Wilkins Creek",
    "tgn:placetype":[
        "aat:300008706"
    ]
},
  "bbox": [],
  "geometry": {"coordinates":[-89.7833,33.5833],"type":"Point"}
}