{
  "id": 2506082,
  "type": "Feature",
  "properties": {
    "tgn:hierarchy":[
        "tgn:2506082",
        "tgn:1000001",
        "tgn:7012149",
        "tgn:1003038",
        "tgn:7007517",
        "tgn:7029392"
    ],
    "tgn:id":2506082,
    "tgn:name":"Merino Village",
    "tgn:placetype":[
        "aat:300008347"
    ]
},
  "bbox": [],
  "geometry": {"coordinates":[-71.8833,42.05],"type":"Point"}
}