<<<<<<< HEAD
{
  "id": 2405786,
  "type": "Feature",
  "properties": {
    "tgn:hierarchy":[
        "tgn:2405786",
        "tgn:1000001",
        "tgn:7012149",
        "tgn:2001067",
        "tgn:7007521",
        "tgn:7029392"
    ],
    "tgn:id":2405786,
    "tgn:name":"Hull",
    "tgn:placetype":[
        "aat:300008347"
    ]
},
  "bbox": [],
  "geometry": {"coordinates":[-92.9167,47.1833],"type":"Point"}
}
=======
{"geometry":{"type":"Point","coordinates":[-92.916700,47.183300]},"type":"Feature","properties":{"hierarchy":["tgn:2405786","tgn:1000001","tgn:7012149","tgn:2001067","tgn:7007521","tgn:7029392"],"placetype":["aat:300008347"],"id":2405786,"name:xx":"Hull"}}
>>>>>>> 03f74aca74312dbeaf24d7e61306dd6a786dc3d0
