{
  "id": 2520335,
  "type": "Feature",
  "properties": {
    "tgn:hierarchy":[
        "tgn:2520335",
        "tgn:1000001",
        "tgn:1002235",
        "tgn:7012149",
        "tgn:7007919",
        "tgn:7029392"
    ],
    "tgn:id":2520335,
    "tgn:name":"Moncure Corner",
    "tgn:placetype":[
        "aat:300008347"
    ]
},
  "bbox": [],
  "geometry": {"coordinates":[-77.4667,37.95],"type":"Point"}
}