{
  "id": 1121659,
  "type": "Feature",
  "properties": {
    "tgn:hierarchy":[
        "tgn:1121659",
        "tgn:1000004",
        "tgn:7016744",
        "tgn:1000135",
        "tgn:7029392"
    ],
    "tgn:id":1121659,
    "tgn:name":"Banga",
    "tgn:placetype":[
        "aat:300008707"
    ]
},
  "bbox": [],
  "geometry": {"coordinates":[124.5667,6.7333],"type":"Point"}
}