{
  "id": 2726819,
  "type": "Feature",
  "properties": {
    "tgn:hierarchy":[
        "tgn:2726819",
        "tgn:1000001",
        "tgn:7012149",
        "tgn:2002179",
        "tgn:7007919",
        "tgn:7029392"
    ],
    "tgn:id":2726819,
    "tgn:name":"Townes Reservoir",
    "tgn:placetype":[
        "aat:300006191"
    ]
},
  "bbox": [],
  "geometry": {"coordinates":[-80.4167,36.6833],"type":"Point"}
}