<<<<<<< HEAD
{
  "id": 7059831,
  "type": "Feature",
  "properties": {
    "tgn:hierarchy":[
        "tgn:7059831",
        "tgn:7003669",
        "tgn:1000003",
        "tgn:7000084",
        "tgn:7029392"
    ],
    "tgn:id":7059831,
    "tgn:name":"Allerding",
    "tgn:placetype":[
        "aat:300008347"
    ]
},
  "bbox": [],
  "geometry": {"coordinates":[12.35,48.0],"type":"Point"}
}
=======
{"geometry":{"type":"Point","coordinates":[12.350000,48.000000]},"type":"Feature","properties":{"hierarchy":["tgn:7059831","tgn:7003669","tgn:1000003","tgn:7000084","tgn:7029392"],"placetype":["aat:300008347"],"id":7059831,"name:xx":"Allerding"}}
>>>>>>> 03f74aca74312dbeaf24d7e61306dd6a786dc3d0
