{
  "id": 2189716,
  "type": "Feature",
  "properties": {
    "tgn:hierarchy":[
        "tgn:2189716",
        "tgn:1000001",
        "tgn:7012149",
        "tgn:7007157",
        "tgn:7014004",
        "tgn:7029392"
    ],
    "tgn:id":2189716,
    "tgn:name":"Bower Cave",
    "tgn:placetype":[
        "aat:300008746"
    ]
},
  "bbox": [],
  "geometry": {"coordinates":[-120.0333,37.7333],"type":"Point"}
}