{
  "id": 7548351,
  "type": "Feature",
  "properties": {
    "tgn:hierarchy":[
        "tgn:7548351",
        "tgn:1000004",
        "tgn:1001871",
        "tgn:7000198",
        "tgn:7029392"
    ],
    "tgn:id":7548351,
    "tgn:name:en":"Bub Shahar",
    "tgn:placetype":[
        "aat:300008347"
    ]
},
  "bbox": [],
  "geometry": {"coordinates":[74.616667,29.85],"type":"Point"}
}