{
  "id": 7053699,
  "type": "Feature",
  "properties": {
    "tgn:hierarchy":[
        "tgn:7053699",
        "tgn:1000003",
        "tgn:7003152",
        "tgn:7003237",
        "tgn:1000080",
        "tgn:7029392"
    ],
    "tgn:id":7053699,
    "tgn:name":"Madesimo",
    "tgn:placetype":[
        "aat:300008347"
    ]
},
  "bbox": [],
  "geometry": {"coordinates":[9.35,46.433333],"type":"Point"}
}