{
  "id": 2660499,
  "type": "Feature",
  "properties": {
    "tgn:hierarchy":[
        "tgn:2660499",
        "tgn:1000001",
        "tgn:7012149",
        "tgn:1002897",
        "tgn:7007920",
        "tgn:7029392"
    ],
    "tgn:id":2660499,
    "tgn:name":"Shoestring Glacier",
    "tgn:placetype":[
        "aat:300008835"
    ]
},
  "bbox": [],
  "geometry": {"coordinates":[-122.1667,46.1833],"type":"Point"}
}