{
  "id": 7468647,
  "type": "Feature",
  "properties": {
    "tgn:hierarchy":[
        "tgn:7468647",
        "tgn:1000004",
        "tgn:7001013",
        "tgn:1000141",
        "tgn:7029392"
    ],
    "tgn:id":7468647,
    "tgn:name":"Xiakuihui",
    "tgn:placetype":[
        "aat:300008347"
    ]
},
  "bbox": [],
  "geometry": {"coordinates":[121.327407,24.801641],"type":"Point"}
}