{
  "id": 7025362,
  "type": "Feature",
  "properties": {
    "tgn:hierarchy":[
        "tgn:7025362",
        "tgn:7002445",
        "tgn:1000003",
        "tgn:7012077",
        "tgn:7008591",
        "tgn:7029392"
    ],
    "tgn:id":7025362,
    "tgn:name":"Aller",
    "tgn:placetype":[
        "aat:300008347"
    ]
},
  "bbox": [],
  "geometry": {"coordinates":[-3.3333,50.85],"type":"Point"}
}