<<<<<<< HEAD
{
  "id": 7025362,
  "type": "Feature",
  "properties": {
    "tgn:hierarchy":[
        "tgn:7025362",
        "tgn:7002445",
        "tgn:1000003",
        "tgn:7012077",
        "tgn:7008591",
        "tgn:7029392"
    ],
    "tgn:id":7025362,
    "tgn:name":"Aller",
    "tgn:placetype":[
        "aat:300008347"
    ]
},
  "bbox": [],
  "geometry": {"coordinates":[-3.3333,50.85],"type":"Point"}
}
=======
{"geometry":{"type":"Point","coordinates":[-3.333300,50.850000]},"type":"Feature","properties":{"hierarchy":["tgn:7025362","tgn:7002445","tgn:1000003","tgn:7012077","tgn:7008591","tgn:7029392"],"placetype":["aat:300008347"],"id":7025362,"name:xx":"Aller"}}
>>>>>>> 03f74aca74312dbeaf24d7e61306dd6a786dc3d0
