{
  "id": 1075457,
  "type": "Feature",
  "properties": {
    "tgn:hierarchy":[
        "tgn:1075457",
        "tgn:1000004",
        "tgn:1001842",
        "tgn:7000198",
        "tgn:7029392"
    ],
    "tgn:id":1075457,
    "tgn:name:en":"Harinagar",
    "tgn:placetype":[
        "aat:300007783"
    ]
},
  "bbox": [],
  "geometry": {"coordinates":[84.323358,27.155434],"type":"Point"}
}