<<<<<<< HEAD
{
  "id": 2766457,
  "type": "Feature",
  "properties": {
    "tgn:hierarchy":[
        "tgn:2766457",
        "tgn:1000001",
        "tgn:7012149",
        "tgn:2000906",
        "tgn:7007256",
        "tgn:7029392"
    ],
    "tgn:id":2766457,
    "tgn:name":"White Oak Branch",
    "tgn:placetype":[
        "aat:300008699"
    ]
},
  "bbox": [],
  "geometry": {"coordinates":[-90.3167,30.55],"type":"Point"}
}
=======
{"geometry":{"type":"Point","coordinates":[-90.316700,30.550000]},"type":"Feature","properties":{"hierarchy":["tgn:2766457","tgn:1000001","tgn:7012149","tgn:2000906","tgn:7007256","tgn:7029392"],"placetype":["aat:300008699"],"id":2766457,"name:xx":"White Oak Branch"}}
>>>>>>> 03f74aca74312dbeaf24d7e61306dd6a786dc3d0
