{
  "id": 2295146,
  "type": "Feature",
  "properties": {
    "tgn:hierarchy":[
        "tgn:2295146",
        "tgn:1000001",
        "tgn:7012149",
        "tgn:1002676",
        "tgn:7007240",
        "tgn:7029392"
    ],
    "tgn:id":2295146,
    "tgn:name":"Dredgers Key",
    "tgn:placetype":[
        "aat:300008791"
    ]
},
  "bbox": [],
  "geometry": {"coordinates":[-81.7667,24.5667],"type":"Point"}
}