{
  "id": 2328469,
  "type": "Feature",
  "properties": {
    "tgn:hierarchy":[
        "tgn:2328469",
        "tgn:1000001",
        "tgn:7012149",
        "tgn:2001761",
        "tgn:7007712",
        "tgn:7029392"
    ],
    "tgn:id":2328469,
    "tgn:name":"Fisher Knob",
    "tgn:placetype":[
        "aat:300008798"
    ]
},
  "bbox": [],
  "geometry": {"coordinates":[-82.9667,34.9667],"type":"Point"}
}