<<<<<<< HEAD
{
  "id": 7171409,
  "type": "Feature",
  "properties": {
    "tgn:hierarchy":[
        "tgn:7171409",
        "tgn:1000003",
        "tgn:7003682",
        "tgn:7000084",
        "tgn:7029392"
    ],
    "tgn:id":7171409,
    "tgn:name":"Hertha Quelle",
    "tgn:placetype":[
        "aat:300008697"
    ]
},
  "bbox": [],
  "geometry": {"coordinates":[6.533333,50.15],"type":"Point"}
}
=======
{"geometry":{"type":"Point","coordinates":[6.533333,50.150000]},"type":"Feature","properties":{"hierarchy":["tgn:7171409","tgn:1000003","tgn:7003682","tgn:7000084","tgn:7029392"],"placetype":["aat:300008697"],"id":7171409,"name:xx":"Hertha Quelle"}}
>>>>>>> 03f74aca74312dbeaf24d7e61306dd6a786dc3d0
