{
  "id": 7255771,
  "type": "Feature",
  "properties": {
    "tgn:hierarchy":[
        "tgn:7255771",
        "tgn:7003460",
        "tgn:1000003",
        "tgn:1000063",
        "tgn:4012014",
        "tgn:7029392"
    ],
    "tgn:id":7255771,
    "tgn:name":"Runschen",
    "tgn:placetype":[
        "aat:300008347"
    ]
},
  "bbox": [],
  "geometry": {"coordinates":[5.966667,50.616667],"type":"Point"}
}