{
  "id": 2488821,
  "type": "Feature",
  "properties": {
    "tgn:hierarchy":[
        "tgn:2488821",
        "tgn:1000001",
        "tgn:7012149",
        "tgn:7007157",
        "tgn:1002937",
        "tgn:7029392"
    ],
    "tgn:id":2488821,
    "tgn:name":"Main Canal",
    "tgn:placetype":[
        "aat:300006075"
    ]
},
  "bbox": [],
  "geometry": {"coordinates":[-121.5833,38.8167],"type":"Point"}
}