{
  "id": 2224411,
  "type": "Feature",
  "properties": {
    "tgn:hierarchy":[
        "tgn:2224411",
        "tgn:1000001",
        "tgn:7012149",
        "tgn:1002440",
        "tgn:7007568",
        "tgn:7029392"
    ],
    "tgn:id":2224411,
    "tgn:name":"Cascade Pond",
    "tgn:placetype":[
        "aat:300008680"
    ]
},
  "bbox": [],
  "geometry": {"coordinates":[-74.4333,43.8167],"type":"Point"}
}