{
  "id": 2491587,
  "type": "Feature",
  "properties": {
    "tgn:hierarchy":[
        "tgn:2491587",
        "tgn:2000934",
        "tgn:1000001",
        "tgn:7012149",
        "tgn:7007516",
        "tgn:7029392"
    ],
    "tgn:id":2491587,
    "tgn:name":"Maple Run",
    "tgn:placetype":[
        "aat:300008699"
    ]
},
  "bbox": [],
  "geometry": {"coordinates":[-78.5167,39.65],"type":"Point"}
}