{
  "id": 1052483,
  "type": "Feature",
  "properties": {
    "tgn:hierarchy":[
        "tgn:1052483",
        "tgn:1000004",
        "tgn:7014474",
        "tgn:7018214",
        "tgn:7002435",
        "tgn:7029392"
    ],
    "tgn:id":1052483,
    "tgn:name":"Balad'ok",
    "tgn:placetype":[
        "aat:300008347"
    ]
},
  "bbox": [],
  "geometry": {"coordinates":[133.1167,53.6833],"type":"Point"}
}