<<<<<<< HEAD
{
  "id": 2337555,
  "type": "Feature",
  "properties": {
    "tgn:hierarchy":[
        "tgn:2337555",
        "tgn:1000001",
        "tgn:7012149",
        "tgn:7013517",
        "tgn:7007248",
        "tgn:7029392"
    ],
    "tgn:id":2337555,
    "tgn:name":"Fowlstown Swamp",
    "tgn:placetype":[
        "aat:300008905"
    ]
},
  "bbox": [],
  "geometry": {"coordinates":[-84.5833,30.85],"type":"Point"}
}
=======
{"geometry":{"type":"Point","coordinates":[-84.583300,30.850000]},"type":"Feature","properties":{"hierarchy":["tgn:2337555","tgn:1000001","tgn:7012149","tgn:7013517","tgn:7007248","tgn:7029392"],"placetype":["aat:300008905"],"id":2337555,"name:xx":"Fowlstown Swamp"}}
>>>>>>> 03f74aca74312dbeaf24d7e61306dd6a786dc3d0
