{
  "id": 2502291,
  "type": "Feature",
  "properties": {
    "tgn:hierarchy":[
        "tgn:2502291",
        "tgn:1000001",
        "tgn:7012149",
        "tgn:1002636",
        "tgn:7007708",
        "tgn:7029392"
    ],
    "tgn:id":2502291,
    "tgn:name":"McKinney Creek",
    "tgn:placetype":[
        "aat:300008706"
    ]
},
  "bbox": [],
  "geometry": {"coordinates":[-122.9833,44.7833],"type":"Point"}
}