{
  "id": 2102894,
  "type": "Feature",
  "properties": {
    "tgn:hierarchy":[
        "tgn:2102894",
        "tgn:1000001",
        "tgn:7012149",
        "tgn:1002670",
        "tgn:7007826",
        "tgn:7029392"
    ],
    "tgn:id":2102894,
    "tgn:name":"Briary",
    "tgn:placetype":[
        "aat:300008347",
        "aat:300387210"
    ]
},
  "bbox": [],
  "geometry": {"coordinates":[-96.8833,31.0333],"type":"Point"}
}