<<<<<<< HEAD
{
  "id": 7488352,
  "type": "Feature",
  "properties": {
    "tgn:hierarchy":[
        "tgn:7488352",
        "tgn:1000004",
        "tgn:7004300",
        "tgn:1000141",
        "tgn:7029392"
    ],
    "tgn:id":7488352,
    "tgn:name":"Guandiye Jiao",
    "tgn:placetype":[
        "aat:300011692"
    ]
},
  "bbox": [],
  "geometry": {"coordinates":[119.583333,23.8],"type":"Point"}
}
=======
{"geometry":{"type":"Point","coordinates":[119.583333,23.800000]},"type":"Feature","properties":{"hierarchy":["tgn:7488352","tgn:1000004","tgn:7004300","tgn:1000141","tgn:7029392"],"placetype":["aat:300011692"],"id":7488352,"name:xx":"Guandiye Jiao"}}
>>>>>>> 03f74aca74312dbeaf24d7e61306dd6a786dc3d0
