{
  "id": 7222888,
  "type": "Feature",
  "properties": {
    "tgn:hierarchy":[
        "tgn:7222888",
        "tgn:7011170",
        "tgn:7002715",
        "tgn:1000003",
        "tgn:1000074",
        "tgn:7029392"
    ],
    "tgn:id":7222888,
    "tgn:name":"Sik\u00e9a",
    "tgn:placetype":[
        "aat:300008347"
    ]
},
  "bbox": [],
  "geometry": {"coordinates":[23.733333,41.083333],"type":"Point"}
}