<<<<<<< HEAD
{
  "id": 7472840,
  "type": "Feature",
  "properties": {
    "tgn:hierarchy":[
        "tgn:7472840",
        "tgn:1000004",
        "tgn:1000454",
        "tgn:1000141",
        "tgn:7029392"
    ],
    "tgn:id":7472840,
    "tgn:name":"Taibei Huayuan Gongmu",
    "tgn:placetype":[
        "aat:300266755"
    ]
},
  "bbox": [],
  "geometry": {"coordinates":[121.651255,24.941069],"type":"Point"}
}
=======
{"geometry":{"type":"Point","coordinates":[121.651255,24.941069]},"type":"Feature","properties":{"hierarchy":["tgn:7472840","tgn:1000004","tgn:1000454","tgn:1000141","tgn:7029392"],"placetype":["aat:300266755"],"id":7472840,"name:xx":"Taibei Huayuan Gongmu"}}
>>>>>>> 03f74aca74312dbeaf24d7e61306dd6a786dc3d0
