{
  "id": 2358283,
  "type": "Feature",
  "properties": {
    "tgn:hierarchy":[
        "tgn:2358283",
        "tgn:1000001",
        "tgn:7012149",
        "tgn:1002392",
        "tgn:7007157",
        "tgn:7029392"
    ],
    "tgn:id":2358283,
    "tgn:name":"Grand Dike",
    "tgn:placetype":[
        "aat:300266640"
    ]
},
  "bbox": [],
  "geometry": {"coordinates":[-118.7333,36.8333],"type":"Point"}
}