{
  "id": 7103739,
  "type": "Feature",
  "properties": {
    "tgn:hierarchy":[
        "tgn:7103739",
        "tgn:1000003",
        "tgn:7003685",
        "tgn:7000084",
        "tgn:7029392"
    ],
    "tgn:id":7103739,
    "tgn:name":"Scheide-Bach",
    "tgn:placetype":[
        "aat:300008699"
    ]
},
  "bbox": [],
  "geometry": {"coordinates":[13.316667,50.733333],"type":"Point"}
}