{
  "id": 7384866,
  "type": "Feature",
  "properties": {
    "tgn:hierarchy":[
        "tgn:7384866",
        "tgn:1000001",
        "tgn:7005599",
        "tgn:7005560",
        "tgn:7029392"
    ],
    "tgn:id":7384866,
    "tgn:name":"Palmar de Vega",
    "tgn:placetype":[
        "aat:300008347"
    ]
},
  "bbox": [],
  "geometry": {"coordinates":[-96.116667,18.416667],"type":"Point"}
}