<<<<<<< HEAD
{
  "id": 2337787,
  "type": "Feature",
  "properties": {
    "tgn:hierarchy":[
        "tgn:2337787",
        "tgn:1000001",
        "tgn:7012149",
        "tgn:7007712",
        "tgn:7029392"
    ],
    "tgn:id":2337787,
    "tgn:name":"Fox Creek",
    "tgn:placetype":[
        "aat:300008706"
    ]
},
  "bbox": [],
  "geometry": {"coordinates":[-81.95,33.5833],"type":"Point"}
}
=======
{"geometry":{"type":"Point","coordinates":[-81.950000,33.583300]},"type":"Feature","properties":{"hierarchy":["tgn:2337787","tgn:1000001","tgn:7012149","tgn:7007712","tgn:7029392"],"placetype":["aat:300008706"],"id":2337787,"name:xx":"Fox Creek"}}
>>>>>>> 03f74aca74312dbeaf24d7e61306dd6a786dc3d0
