{
  "id": 7279275,
  "type": "Feature",
  "properties": {
    "tgn:hierarchy":[
        "tgn:7279275",
        "tgn:1001630",
        "tgn:1000049",
        "tgn:1000002",
        "tgn:7029392"
    ],
    "tgn:id":7279275,
    "tgn:name":"Rodr\u00edguez, Punta",
    "tgn:placetype":[
        "aat:300386846"
    ]
},
  "bbox": [],
  "geometry": {"coordinates":[-70.666667,-26.133333],"type":"Point"}
}