{
  "id": 7474105,
  "type": "Feature",
  "properties": {
    "tgn:hierarchy":[
        "tgn:7474105",
        "tgn:1000004",
        "tgn:7001014",
        "tgn:1000141",
        "tgn:7029392"
    ],
    "tgn:id":7474105,
    "tgn:name":"Youchezi",
    "tgn:placetype":[
        "aat:300008347"
    ]
},
  "bbox": [],
  "geometry": {"coordinates":[120.523967,23.744467],"type":"Point"}
}