{
  "id": 2375734,
  "type": "Feature",
  "properties": {
    "tgn:hierarchy":[
        "tgn:2375734",
        "tgn:1000001",
        "tgn:7012149",
        "tgn:7007248",
        "tgn:7029392"
    ],
    "tgn:id":2375734,
    "tgn:name":"Happy Hollow",
    "tgn:placetype":[
        "aat:300008761"
    ]
},
  "bbox": [],
  "geometry": {"coordinates":[-85.05,33.9167],"type":"Point"}
}