{
  "id": 2218262,
  "type": "Feature",
  "properties": {
    "tgn:hierarchy":[
        "tgn:2218262",
        "tgn:1000001",
        "tgn:7012149",
        "tgn:2000910",
        "tgn:7007256",
        "tgn:7029392"
    ],
    "tgn:id":2218262,
    "tgn:name":"Canal Number Ten",
    "tgn:placetype":[
        "aat:300006075"
    ]
},
  "bbox": [],
  "geometry": {"coordinates":[-92.5833,29.9167],"type":"Point"}
}