{
  "id": 2184195,
  "type": "Feature",
  "properties": {
    "tgn:hierarchy":[
        "tgn:2184195",
        "tgn:1000001",
        "tgn:7012149",
        "tgn:2001830",
        "tgn:7007713",
        "tgn:7029392"
    ],
    "tgn:id":2184195,
    "tgn:name":"Bob Lake",
    "tgn:placetype":[
        "aat:300008680"
    ]
},
  "bbox": [],
  "geometry": {"coordinates":[-101.1333,43.0167],"type":"Point"}
}