{
  "id": 2040463,
  "type": "Feature",
  "properties": {
    "tgn:hierarchy":[
        "tgn:2040463",
        "tgn:1000001",
        "tgn:2000776",
        "tgn:7012149",
        "tgn:7007255",
        "tgn:7029392"
    ],
    "tgn:id":2040463,
    "tgn:name":"Needmore",
    "tgn:placetype":[
        "aat:300008347",
        "aat:300387210"
    ]
},
  "bbox": [],
  "geometry": {"coordinates":[-87.8333,37.2167],"type":"Point"}
}