{
  "id": 7469599,
  "type": "Feature",
  "properties": {
    "tgn:hierarchy":[
        "tgn:7469599",
        "tgn:1000004",
        "tgn:7004300",
        "tgn:1000141",
        "tgn:7029392"
    ],
    "tgn:id":7469599,
    "tgn:name":"Qingwan",
    "tgn:placetype":[
        "aat:300008347"
    ]
},
  "bbox": [],
  "geometry": {"coordinates":[119.556464,23.526616],"type":"Point"}
}