{
  "id": 1024418,
  "type": "Feature",
  "properties": {
    "tgn:hierarchy":[
        "tgn:1024418",
        "tgn:1000700",
        "tgn:1000002",
        "tgn:1000056",
        "tgn:7029392"
    ],
    "tgn:id":1024418,
    "tgn:name":"Carumas",
    "tgn:placetype":[
        "aat:300008347"
    ]
},
  "bbox": [],
  "geometry": {"coordinates":[-70.7167,-16.8167],"type":"Point"}
}