{
  "id": 2438985,
  "type": "Feature",
  "properties": {
    "tgn:hierarchy":[
        "tgn:2438985",
        "tgn:1000001",
        "tgn:2001653",
        "tgn:7012149",
        "tgn:7007707",
        "tgn:7029392"
    ],
    "tgn:id":2438985,
    "tgn:name":"Kinta Lake",
    "tgn:placetype":[
        "aat:300006191"
    ]
},
  "bbox": [],
  "geometry": {"coordinates":[-95.2167,35.1167],"type":"Point"}
}