{
  "id": 7109939,
  "type": "Feature",
  "properties": {
    "tgn:hierarchy":[
        "tgn:7109939",
        "tgn:1000003",
        "tgn:7003688",
        "tgn:7000084",
        "tgn:7029392"
    ],
    "tgn:id":7109939,
    "tgn:name":"Quaal",
    "tgn:placetype":[
        "aat:300008347"
    ]
},
  "bbox": [],
  "geometry": {"coordinates":[10.366667,53.966667],"type":"Point"}
}