{
  "id": 2005469,
  "type": "Feature",
  "properties": {
    "tgn:hierarchy":[
        "tgn:2005469",
        "tgn:7002659",
        "tgn:1000001",
        "tgn:7012149",
        "tgn:2000023",
        "tgn:7029392"
    ],
    "tgn:id":2005469,
    "tgn:name":"Tasso",
    "tgn:placetype":[
        "aat:300008347",
        "aat:300387210"
    ]
},
  "bbox": [],
  "geometry": {"coordinates":[-87.1833,32.2167],"type":"Point"}
}