{
  "id": 7324327,
  "type": "Feature",
  "properties": {
    "tgn:hierarchy":[
        "tgn:7324327",
        "tgn:7002849",
        "tgn:1000003",
        "tgn:7009604",
        "tgn:1000095",
        "tgn:7029392"
    ],
    "tgn:id":7324327,
    "tgn:name":"San Pedro de Goicour\u00eda",
    "tgn:placetype":[
        "aat:300008347"
    ]
},
  "bbox": [],
  "geometry": {"coordinates":[-3.066348,43.202073],"type":"Point"}
}