{
  "id": 7208411,
  "type": "Feature",
  "properties": {
    "tgn:hierarchy":[
        "tgn:7208411",
        "tgn:7003669",
        "tgn:1000003",
        "tgn:7000084",
        "tgn:7029392"
    ],
    "tgn:id":7208411,
    "tgn:name":"Berg am Laim",
    "tgn:placetype":[
        "aat:300000745"
    ]
},
  "bbox": [],
  "geometry": {"coordinates":[11.633333,48.133333],"type":"Point"}
}