{
  "id": 7319653,
  "type": "Feature",
  "properties": {
    "tgn:hierarchy":[
        "tgn:7319653",
        "tgn:1001630",
        "tgn:1000049",
        "tgn:1000002",
        "tgn:7029392"
    ],
    "tgn:id":7319653,
    "tgn:name":"Agua de Lazo",
    "tgn:placetype":[
        "aat:300008347"
    ]
},
  "bbox": [],
  "geometry": {"coordinates":[-70.816667,-28.116667],"type":"Point"}
}