{
  "id": 2711501,
  "type": "Feature",
  "properties": {
    "tgn:hierarchy":[
        "tgn:2711501",
        "tgn:1000001",
        "tgn:2000540",
        "tgn:7012149",
        "tgn:7007252",
        "tgn:7029392"
    ],
    "tgn:id":2711501,
    "tgn:name":"Tapawingo Lake",
    "tgn:placetype":[
        "aat:300006191"
    ]
},
  "bbox": [],
  "geometry": {"coordinates":[-87.05,39.2167],"type":"Point"}
}