<<<<<<< HEAD
{
  "id": 7362381,
  "type": "Feature",
  "properties": {
    "tgn:hierarchy":[
        "tgn:7362381",
        "tgn:1000001",
        "tgn:7005599",
        "tgn:7005560",
        "tgn:7029392"
    ],
    "tgn:id":7362381,
    "tgn:name":"El Dorado",
    "tgn:placetype":[
        "aat:300008347"
    ]
},
  "bbox": [],
  "geometry": {"coordinates":[-97.966667,20.8],"type":"Point"}
}
=======
{"geometry":{"type":"Point","coordinates":[-97.966667,20.800000]},"type":"Feature","properties":{"hierarchy":["tgn:7362381","tgn:1000001","tgn:7005599","tgn:7005560","tgn:7029392"],"placetype":["aat:300008347"],"id":7362381,"name:xx":"El Dorado"}}
>>>>>>> 03f74aca74312dbeaf24d7e61306dd6a786dc3d0
