{
  "id": 2310115,
  "type": "Feature",
  "properties": {
    "tgn:hierarchy":[
        "tgn:2310115",
        "tgn:1000001",
        "tgn:7012149",
        "tgn:2001241",
        "tgn:7007523",
        "tgn:7029392"
    ],
    "tgn:id":2310115,
    "tgn:name":"Eaton Branch",
    "tgn:placetype":[
        "aat:300008699"
    ]
},
  "bbox": [],
  "geometry": {"coordinates":[-90.5833,37.8167],"type":"Point"}
}