{
  "id": 2260414,
  "type": "Feature",
  "properties": {
    "tgn:hierarchy":[
        "tgn:2260414",
        "tgn:1000001",
        "tgn:7012149",
        "tgn:2001062",
        "tgn:7007521",
        "tgn:7029392"
    ],
    "tgn:id":2260414,
    "tgn:name":"County Ditch Number Eightyone",
    "tgn:placetype":[
        "aat:300006075"
    ]
},
  "bbox": [],
  "geometry": {"coordinates":[-95.3833,44.5167],"type":"Point"}
}