{
  "id": 7501919,
  "type": "Feature",
  "properties": {
    "tgn:hierarchy":[
        "tgn:7501919",
        "tgn:7488858",
        "tgn:1000004",
        "tgn:1000141",
        "tgn:7029392"
    ],
    "tgn:id":7501919,
    "tgn:name":"Xiehe Erhao Qiao",
    "tgn:placetype":[
        "aat:300007836"
    ]
},
  "bbox": [],
  "geometry": {"coordinates":[120.884444,24.0425],"type":"Point"}
}