{
  "id": 7333965,
  "type": "Feature",
  "properties": {
    "tgn:hierarchy":[
        "tgn:7333965",
        "tgn:7001122",
        "tgn:1000003",
        "tgn:7002765",
        "tgn:1000095",
        "tgn:7029392"
    ],
    "tgn:id":7333965,
    "tgn:name":"Enderrocat, Cabo",
    "tgn:placetype":[
        "aat:300008850"
    ]
},
  "bbox": [],
  "geometry": {"coordinates":[2.716667,39.466667],"type":"Point"}
}