{
  "id": 1115021,
  "type": "Feature",
  "properties": {
    "tgn:hierarchy":[
        "tgn:1115021",
        "tgn:1000001",
        "tgn:7005118",
        "tgn:7029392"
    ],
    "tgn:id":1115021,
    "tgn:name":"Pillsbury Sound",
    "tgn:placetype":[
        "aat:300266558"
    ]
},
  "bbox": [],
  "geometry": {"coordinates":[-64.8167,18.3333],"type":"Point"}
}