{
  "id": 7096831,
  "type": "Feature",
  "properties": {
    "tgn:hierarchy":[
        "tgn:7096831",
        "tgn:1000003",
        "tgn:7003678",
        "tgn:7000084",
        "tgn:7029392"
    ],
    "tgn:id":7096831,
    "tgn:name":"Sohl-Berg",
    "tgn:placetype":[
        "aat:300008777"
    ]
},
  "bbox": [],
  "geometry": {"coordinates":[10.15,51.183333],"type":"Point"}
}