{
  "id": 2776257,
  "type": "Feature",
  "properties": {
    "tgn:hierarchy":[
        "tgn:2776257",
        "tgn:1000001",
        "tgn:7012149",
        "tgn:2001980",
        "tgn:7007826",
        "tgn:7029392"
    ],
    "tgn:id":2776257,
    "tgn:name":"Winans Spring",
    "tgn:placetype":[
        "aat:300008697"
    ]
},
  "bbox": [],
  "geometry": {"coordinates":[-100.1333,29.7167],"type":"Point"}
}