{
  "id": 2508385,
  "type": "Feature",
  "properties": {
    "tgn:hierarchy":[
        "tgn:2508385",
        "tgn:1000001",
        "tgn:7012149",
        "tgn:7007525",
        "tgn:7029392"
    ],
    "tgn:id":2508385,
    "tgn:name":"Middle Channel Platte River",
    "tgn:placetype":[
        "aat:300008707"
    ]
},
  "bbox": [],
  "geometry": {"coordinates":[-99.0333,40.65],"type":"Point"}
}