{
  "id": 7287058,
  "type": "Feature",
  "properties": {
    "tgn:hierarchy":[
        "tgn:7287058",
        "tgn:7016598",
        "tgn:1000049",
        "tgn:1000002",
        "tgn:7029392"
    ],
    "tgn:id":7287058,
    "tgn:name":"Guallaquer, Pampa de",
    "tgn:placetype":[
        "aat:300008805"
    ]
},
  "bbox": [],
  "geometry": {"coordinates":[-67.416667,-22.916667],"type":"Point"}
}