{
  "id": 2571981,
  "type": "Feature",
  "properties": {
    "tgn:hierarchy":[
        "tgn:2571981",
        "tgn:1000001",
        "tgn:7012149",
        "tgn:7007157",
        "tgn:2000186",
        "tgn:7029392"
    ],
    "tgn:id":2571981,
    "tgn:name":"Payne Peak",
    "tgn:placetype":[
        "aat:300008798"
    ]
},
  "bbox": [],
  "geometry": {"coordinates":[-120.2667,41.5333],"type":"Point"}
}