{
  "id": 7485842,
  "type": "Feature",
  "properties": {
    "tgn:hierarchy":[
        "tgn:7485842",
        "tgn:1000004",
        "tgn:7004300",
        "tgn:1000141",
        "tgn:7029392"
    ],
    "tgn:id":7485842,
    "tgn:name":"Huayu Guoxiao",
    "tgn:placetype":[
        "aat:300006495"
    ]
},
  "bbox": [],
  "geometry": {"coordinates":[119.323056,23.400278],"type":"Point"}
}