<<<<<<< HEAD
{
  "id": 2252807,
  "type": "Feature",
  "properties": {
    "tgn:hierarchy":[
        "tgn:2252807",
        "tgn:1000001",
        "tgn:2002102",
        "tgn:7012149",
        "tgn:7007827",
        "tgn:7029392"
    ],
    "tgn:id":2252807,
    "tgn:name":"Connor Springs",
    "tgn:placetype":[
        "aat:300008697"
    ]
},
  "bbox": [],
  "geometry": {"coordinates":[-112.3333,41.6167],"type":"Point"}
}
=======
{"geometry":{"type":"Point","coordinates":[-112.333300,41.616700]},"type":"Feature","properties":{"hierarchy":["tgn:2252807","tgn:1000001","tgn:2002102","tgn:7012149","tgn:7007827","tgn:7029392"],"placetype":["aat:300008697"],"id":2252807,"name:xx":"Connor Springs"}}
>>>>>>> 03f74aca74312dbeaf24d7e61306dd6a786dc3d0
