{
  "id": 2268695,
  "type": "Feature",
  "properties": {
    "tgn:hierarchy":[
        "tgn:2268695",
        "tgn:1000001",
        "tgn:7012149",
        "tgn:2000217",
        "tgn:7007158",
        "tgn:7029392"
    ],
    "tgn:id":2268695,
    "tgn:name":"Cross Creek",
    "tgn:placetype":[
        "aat:300008706"
    ]
},
  "bbox": [],
  "geometry": {"coordinates":[-106.5667,38.7333],"type":"Point"}
}