{
  "id": 2507205,
  "type": "Feature",
  "properties": {
    "tgn:hierarchy":[
        "tgn:2507205",
        "tgn:1000001",
        "tgn:7012149",
        "tgn:2001284",
        "tgn:7007524",
        "tgn:7029392"
    ],
    "tgn:id":2507205,
    "tgn:name":"Metropolitan Bar",
    "tgn:placetype":[
        "aat:300132348"
    ]
},
  "bbox": [],
  "geometry": {"coordinates":[-111.7833,46.6667],"type":"Point"}
}