{
  "id": 2347852,
  "type": "Feature",
  "properties": {
    "tgn:hierarchy":[
        "tgn:2347852",
        "tgn:1000001",
        "tgn:2001413",
        "tgn:7012149",
        "tgn:7007526",
        "tgn:7029392"
    ],
    "tgn:id":2347852,
    "tgn:name":"Gerald",
    "tgn:placetype":[
        "aat:300008347",
        "aat:300167671"
    ]
},
  "bbox": [],
  "geometry": {"coordinates":[-116.2333,40.5833],"type":"Point"}
}