{
  "id": 7316381,
  "type": "Feature",
  "properties": {
    "tgn:hierarchy":[
        "tgn:7316381",
        "tgn:1001702",
        "tgn:1000049",
        "tgn:1000002",
        "tgn:7029392"
    ],
    "tgn:id":7316381,
    "tgn:name":"Carukinca, Punta",
    "tgn:placetype":[
        "aat:300386846"
    ]
},
  "bbox": [],
  "geometry": {"coordinates":[-70.066667,-54.066667],"type":"Point"}
}