{
  "id": 2620586,
  "type": "Feature",
  "properties": {
    "tgn:hierarchy":[
        "tgn:2620586",
        "tgn:7006450",
        "tgn:1000001",
        "tgn:2124012",
        "tgn:7012149",
        "tgn:7029392"
    ],
    "tgn:id":2620586,
    "tgn:name":"Rivermouth Point",
    "tgn:placetype":[
        "aat:300008850"
    ]
},
  "bbox": [],
  "geometry": {"coordinates":[-152.7667,58.0667],"type":"Point"}
}