{
  "id": 2369944,
  "type": "Feature",
  "properties": {
    "tgn:hierarchy":[
        "tgn:2369944",
        "tgn:1000001",
        "tgn:7012149",
        "tgn:7007524",
        "tgn:7029392"
    ],
    "tgn:id":2369944,
    "tgn:name":"Gut Gulch",
    "tgn:placetype":[
        "aat:300008761"
    ]
},
  "bbox": [],
  "geometry": {"coordinates":[-114.1833,47.3333],"type":"Point"}
}