{
  "id": 7209696,
  "type": "Feature",
  "properties": {
    "tgn:hierarchy":[
        "tgn:7209696",
        "tgn:7003669",
        "tgn:1000003",
        "tgn:7000084",
        "tgn:7029392"
    ],
    "tgn:id":7209696,
    "tgn:name":"Bermering",
    "tgn:placetype":[
        "aat:300008347"
    ]
},
  "bbox": [],
  "geometry": {"coordinates":[12.616667,48.433333],"type":"Point"}
}