<<<<<<< HEAD
{
  "id": 7176096,
  "type": "Feature",
  "properties": {
    "tgn:hierarchy":[
        "tgn:7176096",
        "tgn:1000003",
        "tgn:7003676",
        "tgn:7000084",
        "tgn:7029392"
    ],
    "tgn:id":7176096,
    "tgn:name":"Gro\u00dfer Wiesen-Berg",
    "tgn:placetype":[
        "aat:300008795"
    ]
},
  "bbox": [],
  "geometry": {"coordinates":[10.433333,51.85],"type":"Point"}
}
=======
{"geometry":{"type":"Point","coordinates":[10.433333,51.850000]},"type":"Feature","properties":{"hierarchy":["tgn:7176096","tgn:1000003","tgn:7003676","tgn:7000084","tgn:7029392"],"placetype":["aat:300008795"],"id":7176096,"name:xx":"Gro\u00dfer Wiesen-Berg"}}
>>>>>>> 03f74aca74312dbeaf24d7e61306dd6a786dc3d0
