{
  "id": 7456331,
  "type": "Feature",
  "properties": {
    "tgn:hierarchy":[
        "tgn:7456331",
        "tgn:7002445",
        "tgn:1000003",
        "tgn:7008143",
        "tgn:7008591",
        "tgn:7029392"
    ],
    "tgn:id":7456331,
    "tgn:name:en":"Downton",
    "tgn:placetype":[
        "aat:300008347"
    ]
},
  "bbox": [],
  "geometry": {"coordinates":[-2.833333,52.366667],"type":"Point"}
}