{
  "id": 7234290,
  "type": "Feature",
  "properties": {
    "tgn:hierarchy":[
        "tgn:7234290",
        "tgn:7011167",
        "tgn:7001338",
        "tgn:1000003",
        "tgn:1000074",
        "tgn:7029392"
    ],
    "tgn:id":7234290,
    "tgn:name":"Ath\u00e9ras, \u00d3rmos",
    "tgn:placetype":[
        "aat:300132316"
    ]
},
  "bbox": [],
  "geometry": {"coordinates":[20.416667,38.35],"type":"Point"}
}