{
  "id": 7303044,
  "type": "Feature",
  "properties": {
    "tgn:hierarchy":[
        "tgn:7303044",
        "tgn:7002825",
        "tgn:7016622",
        "tgn:1000003",
        "tgn:1000095",
        "tgn:7029392"
    ],
    "tgn:id":7303044,
    "tgn:name":"Muellito, Punta del",
    "tgn:placetype":[
        "aat:300386846"
    ]
},
  "bbox": [],
  "geometry": {"coordinates":[-13.866667,28.35],"type":"Point"}
}