{
  "id": 7052292,
  "type": "Feature",
  "properties": {
    "tgn:hierarchy":[
        "tgn:7052292",
        "tgn:7003132",
        "tgn:1000003",
        "tgn:7008516",
        "tgn:1000080",
        "tgn:7029392"
    ],
    "tgn:id":7052292,
    "tgn:name":"Penice, Monte",
    "tgn:placetype":[
        "aat:300008795"
    ]
},
  "bbox": [],
  "geometry": {"coordinates":[9.316667,44.783333],"type":"Point"}
}