{
  "id": 7434776,
  "type": "Feature",
  "properties": {
    "tgn:hierarchy":[
        "tgn:7434776",
        "tgn:1000001",
        "tgn:7005590",
        "tgn:7005560",
        "tgn:7029392"
    ],
    "tgn:id":7434776,
    "tgn:name":"Varal",
    "tgn:placetype":[
        "aat:300008347"
    ]
},
  "bbox": [],
  "geometry": {"coordinates":[-102.716667,19.766667],"type":"Point"}
}