{
  "id": 1072457,
  "type": "Feature",
  "properties": {
    "tgn:hierarchy":[
        "tgn:1072457",
        "tgn:1000004",
        "tgn:1000960",
        "tgn:1000111",
        "tgn:7029392"
    ],
    "tgn:id":1072457,
    "tgn:name":"Wangjiatai",
    "tgn:placetype":[
        "aat:300008347"
    ]
},
  "bbox": [],
  "geometry": {"coordinates":[117.4833,39.2833],"type":"Point"}
}