{
  "id": 4001733,
  "type": "Feature",
  "properties": {
    "tgn:hierarchy":[
        "tgn:4001733",
        "tgn:1000003",
        "tgn:7002888",
        "tgn:1000070",
        "tgn:7029392"
    ],
    "tgn:id":4001733,
    "tgn:name":"Boulange",
    "tgn:placetype":[
        "aat:300008347"
    ]
},
  "bbox": [],
  "geometry": {"coordinates":[5.95,49.3833],"type":"Point"}
}