{
  "id": 7439852,
  "type": "Feature",
  "properties": {
    "tgn:hierarchy":[
        "tgn:7439852",
        "tgn:1001835",
        "tgn:1000001",
        "tgn:7005560",
        "tgn:7029392"
    ],
    "tgn:id":7439852,
    "tgn:name":"Santa Clara, R\u00edo",
    "tgn:placetype":[
        "aat:300266554",
        "aat:300008699"
    ]
},
  "bbox": [],
  "geometry": {"coordinates":[-116.383333,31.816667],"type":"Point"}
}