<<<<<<< HEAD
{
  "id": 7352349,
  "type": "Feature",
  "properties": {
    "tgn:hierarchy":[
        "tgn:7352349",
        "tgn:1000001",
        "tgn:1001893",
        "tgn:7005560",
        "tgn:7029392"
    ],
    "tgn:id":7352349,
    "tgn:name":"Bravo del Norte, R\u00edo",
    "tgn:placetype":[
        "aat:300008699"
    ]
},
  "bbox": [],
  "geometry": {"coordinates":[-97.15,25.916667],"type":"Point"}
}
=======
{"geometry":{"type":"Point","coordinates":[-97.150000,25.916667]},"type":"Feature","properties":{"hierarchy":["tgn:7352349","tgn:1000001","tgn:1001893","tgn:7005560","tgn:7029392"],"placetype":["aat:300008699"],"id":7352349,"name:xx":"Bravo del Norte, R\u00edo"}}
>>>>>>> 03f74aca74312dbeaf24d7e61306dd6a786dc3d0
