{
  "id": 7163822,
  "type": "Feature",
  "properties": {
    "tgn:hierarchy":[
        "tgn:7163822",
        "tgn:1000003",
        "tgn:7003677",
        "tgn:7000084",
        "tgn:7029392"
    ],
    "tgn:id":7163822,
    "tgn:name":"Husam",
    "tgn:placetype":[
        "aat:300000206"
    ]
},
  "bbox": [],
  "geometry": {"coordinates":[7.683333,51.85],"type":"Point"}
}