{
  "id": 1103766,
  "type": "Feature",
  "properties": {
    "tgn:hierarchy":[
        "tgn:1103766",
        "tgn:7011627",
        "tgn:1000004",
        "tgn:7014835",
        "tgn:7029392"
    ],
    "tgn:id":1103766,
    "tgn:name":"Arnavad, Pik",
    "tgn:placetype":[
        "aat:300008795"
    ]
},
  "bbox": [],
  "geometry": {"coordinates":[71.5167,38.55],"type":"Point"}
}