{
  "id": 7175598,
  "type": "Feature",
  "properties": {
    "tgn:hierarchy":[
        "tgn:7175598",
        "tgn:1000003",
        "tgn:7000094",
        "tgn:7000084",
        "tgn:7029392"
    ],
    "tgn:id":7175598,
    "tgn:name":"Gro\u00df Wootz",
    "tgn:placetype":[
        "aat:300000745"
    ]
},
  "bbox": [],
  "geometry": {"coordinates":[11.366667,53.066667],"type":"Point"}
}