{
  "id": 7493191,
  "type": "Feature",
  "properties": {
    "tgn:hierarchy":[
        "tgn:7493191",
        "tgn:1000004",
        "tgn:1000454",
        "tgn:1000141",
        "tgn:7029392"
    ],
    "tgn:id":7493191,
    "tgn:name":"Shenkeng",
    "tgn:placetype":[
        "aat:300008347"
    ]
},
  "bbox": [],
  "geometry": {"coordinates":[121.479789,24.955008],"type":"Point"}
}