{
  "id": 7438128,
  "type": "Feature",
  "properties": {
    "tgn:hierarchy":[
        "tgn:7438128",
        "tgn:1000001",
        "tgn:7005600",
        "tgn:7005560",
        "tgn:7029392"
    ],
    "tgn:id":7438128,
    "tgn:name":"Timucuy",
    "tgn:placetype":[
        "aat:300008347"
    ]
},
  "bbox": [],
  "geometry": {"coordinates":[-89.516667,20.816667],"type":"Point"}
}