{
  "id": 2755338,
  "type": "Feature",
  "properties": {
    "tgn:hierarchy":[
        "tgn:2755338",
        "tgn:1000001",
        "tgn:7012149",
        "tgn:2000233",
        "tgn:7007158",
        "tgn:7029392"
    ],
    "tgn:id":2755338,
    "tgn:name":"Weber Canyon",
    "tgn:placetype":[
        "aat:300008761"
    ]
},
  "bbox": [],
  "geometry": {"coordinates":[-108.2833,37.2833],"type":"Point"}
}