{
  "id": 7312587,
  "type": "Feature",
  "properties": {
    "tgn:hierarchy":[
        "tgn:7312587",
        "tgn:1001623",
        "tgn:1000049",
        "tgn:1000002",
        "tgn:7029392"
    ],
    "tgn:id":7312587,
    "tgn:name":"Isla Larenas",
    "tgn:placetype":[
        "aat:300008791"
    ]
},
  "bbox": [],
  "geometry": {"coordinates":[-74.050278,-43.937222],"type":"Point"}
}