{
  "id": 1007125,
  "type": "Feature",
  "properties": {
    "tgn:hierarchy":[
        "tgn:1007125",
        "tgn:1000001",
        "tgn:7012149",
        "tgn:1002785",
        "tgn:7007920",
        "tgn:7029392"
    ],
    "tgn:id":1007125,
    "tgn:name":"Fox Island",
    "tgn:placetype":[
        "aat:300008791"
    ]
},
  "bbox": [],
  "geometry": {"coordinates":[-122.6167,47.2333],"type":"Point"}
}