<<<<<<< HEAD
{
  "id": 2250021,
  "type": "Feature",
  "properties": {
    "tgn:hierarchy":[
        "tgn:2250021",
        "tgn:1000001",
        "tgn:7012149",
        "tgn:7007248",
        "tgn:7029392"
    ],
    "tgn:id":2250021,
    "tgn:name":"Collins Branch",
    "tgn:placetype":[
        "aat:300008699"
    ]
},
  "bbox": [],
  "geometry": {"coordinates":[-83.95,31.9167],"type":"Point"}
}
=======
{"geometry":{"type":"Point","coordinates":[-83.950000,31.916700]},"type":"Feature","properties":{"hierarchy":["tgn:2250021","tgn:1000001","tgn:7012149","tgn:7007248","tgn:7029392"],"placetype":["aat:300008699"],"id":2250021,"name:xx":"Collins Branch"}}
>>>>>>> 03f74aca74312dbeaf24d7e61306dd6a786dc3d0
