{
  "id": 1117501,
  "type": "Feature",
  "properties": {
    "tgn:hierarchy":[
        "tgn:1117501",
        "tgn:7005685",
        "tgn:1000001",
        "tgn:7005805",
        "tgn:7029392"
    ],
    "tgn:id":1117501,
    "tgn:name":"Nipekamew Lake",
    "tgn:placetype":[
        "aat:300008680"
    ]
},
  "bbox": [],
  "geometry": {"coordinates":[-104.8667,54.9833],"type":"Point"}
}