{
  "id": 2218108,
  "type": "Feature",
  "properties": {
    "tgn:hierarchy":[
        "tgn:2218108",
        "tgn:1000001",
        "tgn:7012149",
        "tgn:2002249",
        "tgn:7007920",
        "tgn:7029392"
    ],
    "tgn:id":2218108,
    "tgn:name":"Canada Island",
    "tgn:placetype":[
        "aat:300008791"
    ]
},
  "bbox": [],
  "geometry": {"coordinates":[-117.4167,47.65],"type":"Point"}
}