{
  "id": 2198216,
  "type": "Feature",
  "properties": {
    "tgn:hierarchy":[
        "tgn:2198216",
        "tgn:1000001",
        "tgn:2001185",
        "tgn:7012149",
        "tgn:7007523",
        "tgn:7029392"
    ],
    "tgn:id":2198216,
    "tgn:name":"Browns Branch",
    "tgn:placetype":[
        "aat:300008699"
    ]
},
  "bbox": [],
  "geometry": {"coordinates":[-93.05,36.9167],"type":"Point"}
}