{
  "id": 2668617,
  "type": "Feature",
  "properties": {
    "tgn:hierarchy":[
        "tgn:2668617",
        "tgn:1000001",
        "tgn:7006451",
        "tgn:7012149",
        "tgn:7029392"
    ],
    "tgn:id":2668617,
    "tgn:name":"Slate Mountains",
    "tgn:placetype":[
        "aat:300386831"
    ]
},
  "bbox": [],
  "geometry": {"coordinates":[-111.8667,32.5333],"type":"Point"}
}