{
  "id": 7128425,
  "type": "Feature",
  "properties": {
    "tgn:hierarchy":[
        "tgn:7128425",
        "tgn:7003692",
        "tgn:1000003",
        "tgn:7000084",
        "tgn:7029392"
    ],
    "tgn:id":7128425,
    "tgn:name":"Obererzwieselberg",
    "tgn:placetype":[
        "aat:300008347"
    ]
},
  "bbox": [],
  "geometry": {"coordinates":[8.366667,48.433333],"type":"Point"}
}