{
  "id": 2211039,
  "type": "Feature",
  "properties": {
    "tgn:hierarchy":[
        "tgn:2211039",
        "tgn:1000001",
        "tgn:7012149",
        "tgn:1002611",
        "tgn:7007706",
        "tgn:7029392"
    ],
    "tgn:id":2211039,
    "tgn:name":"Butler Island",
    "tgn:placetype":[
        "aat:300008791"
    ]
},
  "bbox": [],
  "geometry": {"coordinates":[-83.75,41.4667],"type":"Point"}
}