{
  "id": 2720425,
  "type": "Feature",
  "properties": {
    "tgn:hierarchy":[
        "tgn:2720425",
        "tgn:1000001",
        "tgn:2000922",
        "tgn:7012149",
        "tgn:7007515",
        "tgn:7029392"
    ],
    "tgn:id":2720425,
    "tgn:name":"Thunder Hole",
    "tgn:placetype":[
        "aat:300132316"
    ]
},
  "bbox": [],
  "geometry": {"coordinates":[-68.1833,44.3167],"type":"Point"}
}