{
  "id": 2147598,
  "type": "Feature",
  "properties": {
    "tgn:hierarchy":[
        "tgn:2147598",
        "tgn:1000001",
        "tgn:2001425",
        "tgn:7012149",
        "tgn:7007564",
        "tgn:7029392"
    ],
    "tgn:id":2147598,
    "tgn:name":"Barclay Brook",
    "tgn:placetype":[
        "aat:300008699"
    ]
},
  "bbox": [],
  "geometry": {"coordinates":[-71.7833,43.2667],"type":"Point"}
}