{
  "id": 2633631,
  "type": "Feature",
  "properties": {
    "tgn:hierarchy":[
        "tgn:2633631",
        "tgn:1000001",
        "tgn:2001473",
        "tgn:7012149",
        "tgn:7007709",
        "tgn:7029392"
    ],
    "tgn:id":2633631,
    "tgn:name":"Rush Branch",
    "tgn:placetype":[
        "aat:300008699"
    ]
},
  "bbox": [],
  "geometry": {"coordinates":[-82.2833,35.5333],"type":"Point"}
}