{
  "id": 1015416,
  "type": "Feature",
  "properties": {
    "tgn:hierarchy":[
        "tgn:1015416",
        "tgn:7005685",
        "tgn:1000001",
        "tgn:7005804",
        "tgn:7029392"
    ],
    "tgn:id":1015416,
    "tgn:name":"Howick",
    "tgn:placetype":[
        "aat:300008347"
    ]
},
  "bbox": [],
  "geometry": {"coordinates":[-73.85,45.1833],"type":"Point"}
}