{
  "id": 7373066,
  "type": "Feature",
  "properties": {
    "tgn:hierarchy":[
        "tgn:7373066",
        "tgn:1000001",
        "tgn:7005589",
        "tgn:7005560",
        "tgn:7029392"
    ],
    "tgn:id":7373066,
    "tgn:name":"La Chancaca",
    "tgn:placetype":[
        "aat:300008347"
    ]
},
  "bbox": [],
  "geometry": {"coordinates":[-100.183333,27.05],"type":"Point"}
}