{
  "id": 7154979,
  "type": "Feature",
  "properties": {
    "tgn:hierarchy":[
        "tgn:7154979",
        "tgn:7000096",
        "tgn:1000003",
        "tgn:7000084",
        "tgn:7029392"
    ],
    "tgn:id":7154979,
    "tgn:name":"F\u00f6rsterei Kleine Heide",
    "tgn:placetype":[
        "aat:300004792"
    ]
},
  "bbox": [],
  "geometry": {"coordinates":[14.45,51.85],"type":"Point"}
}