{
  "id": 7551471,
  "type": "Feature",
  "properties": {
    "tgn:hierarchy":[
        "tgn:7551471",
        "tgn:1000004",
        "tgn:7000198",
        "tgn:7016694",
        "tgn:7029392"
    ],
    "tgn:id":7551471,
    "tgn:name:en":"Chh\u0101munda",
    "tgn:placetype":[
        "aat:300008347"
    ]
},
  "bbox": [],
  "geometry": {"coordinates":[84.175075,21.321556],"type":"Point"}
}