{
  "id": 7280415,
  "type": "Feature",
  "properties": {
    "tgn:hierarchy":[
        "tgn:7280415",
        "tgn:1001637",
        "tgn:1000049",
        "tgn:1000002",
        "tgn:7029392"
    ],
    "tgn:id":7280415,
    "tgn:name":"Santa Rosa, Estero",
    "tgn:placetype":[
        "aat:300008699"
    ]
},
  "bbox": [],
  "geometry": {"coordinates":[-72.316667,-36.966667],"type":"Point"}
}