{
  "id": 7409451,
  "type": "Feature",
  "properties": {
    "tgn:hierarchy":[
        "tgn:7409451",
        "tgn:1000001",
        "tgn:1001893",
        "tgn:7005560",
        "tgn:7029392"
    ],
    "tgn:id":7409451,
    "tgn:name":"San Antonio Alzate",
    "tgn:placetype":[
        "aat:300008347"
    ]
},
  "bbox": [],
  "geometry": {"coordinates":[-98.783333,19.041667],"type":"Point"}
}