<<<<<<< HEAD
{
  "id": 7480735,
  "type": "Feature",
  "properties": {
    "tgn:hierarchy":[
        "tgn:7480735",
        "tgn:1000004",
        "tgn:7490934",
        "tgn:1000141",
        "tgn:7029392"
    ],
    "tgn:id":7480735,
    "tgn:name":"Longmujing Xi",
    "tgn:placetype":[
        "aat:300008699"
    ]
},
  "bbox": [],
  "geometry": {"coordinates":[120.431632,23.1379],"type":"Point"}
}
=======
{"geometry":{"type":"Point","coordinates":[120.431632,23.137900]},"type":"Feature","properties":{"hierarchy":["tgn:7480735","tgn:1000004","tgn:7490934","tgn:1000141","tgn:7029392"],"placetype":["aat:300008699"],"id":7480735,"name:xx":"Longmujing Xi"}}
>>>>>>> 03f74aca74312dbeaf24d7e61306dd6a786dc3d0
