{
  "id": 2518542,
  "type": "Feature",
  "properties": {
    "tgn:hierarchy":[
        "tgn:2518542",
        "tgn:1000001",
        "tgn:7012149",
        "tgn:2001529",
        "tgn:7007709",
        "tgn:7029392"
    ],
    "tgn:id":2518542,
    "tgn:name":"Mitchell Creek",
    "tgn:placetype":[
        "aat:300008706"
    ]
},
  "bbox": [],
  "geometry": {"coordinates":[-78.9333,36.4333],"type":"Point"}
}