{
  "id": 7324345,
  "type": "Feature",
  "properties": {
    "tgn:hierarchy":[
        "tgn:7324345",
        "tgn:7002811",
        "tgn:1000003",
        "tgn:7003837",
        "tgn:1000095",
        "tgn:7029392"
    ],
    "tgn:id":7324345,
    "tgn:name":"San Pedro, Sierra de",
    "tgn:placetype":[
        "aat:300008795"
    ]
},
  "bbox": [],
  "geometry": {"coordinates":[-6.583333,39.333333],"type":"Point"}
}