{
  "id": 7491714,
  "type": "Feature",
  "properties": {
    "tgn:hierarchy":[
        "tgn:7491714",
        "tgn:1000004",
        "tgn:7491221",
        "tgn:1000141",
        "tgn:7029392"
    ],
    "tgn:id":7491714,
    "tgn:name":"Beishining Qiao",
    "tgn:placetype":[
        "aat:300007836"
    ]
},
  "bbox": [],
  "geometry": {"coordinates":[121.416635,23.245051],"type":"Point"}
}