{
  "id": 1115256,
  "type": "Feature",
  "properties": {
    "tgn:hierarchy":[
        "tgn:1115256",
        "tgn:7005685",
        "tgn:1000001",
        "tgn:7024197",
        "tgn:7029392"
    ],
    "tgn:id":1115256,
    "tgn:name":"Simpson Strait",
    "tgn:placetype":[
        "aat:300266559"
    ]
},
  "bbox": [],
  "geometry": {"coordinates":[-97.75,68.45],"type":"Point"}
}