{
  "id": 7589909,
  "type": "Feature",
  "properties": {
    "tgn:hierarchy":[
        "tgn:7589909",
        "tgn:1000004",
        "tgn:1001871",
        "tgn:7000198",
        "tgn:7029392"
    ],
    "tgn:id":7589909,
    "tgn:name:en":"Japti Chhapra",
    "tgn:placetype":[
        "aat:300008347"
    ]
},
  "bbox": [],
  "geometry": {"coordinates":[77.177069,29.863232],"type":"Point"}
}