{
  "id": 2564699,
  "type": "Feature",
  "properties": {
    "tgn:hierarchy":[
        "tgn:2564699",
        "tgn:1000001",
        "tgn:7012149",
        "tgn:7007157",
        "tgn:1002608",
        "tgn:7029392"
    ],
    "tgn:id":2564699,
    "tgn:name":"Pacoima Reservoir",
    "tgn:placetype":[
        "aat:300006191"
    ]
},
  "bbox": [],
  "geometry": {"coordinates":[-118.3833,34.3333],"type":"Point"}
}