{
  "id": 7213557,
  "type": "Feature",
  "properties": {
    "tgn:hierarchy":[
        "tgn:7213557",
        "tgn:7003669",
        "tgn:1000003",
        "tgn:7000084",
        "tgn:7029392"
    ],
    "tgn:id":7213557,
    "tgn:name":"Bichler an der M\u00f6rn",
    "tgn:placetype":[
        "aat:300000206"
    ]
},
  "bbox": [],
  "geometry": {"coordinates":[12.466667,48.066667],"type":"Point"}
}