{
  "id": 7537386,
  "type": "Feature",
  "properties": {
    "tgn:hierarchy":[
        "tgn:7537386",
        "tgn:7001242",
        "tgn:7016833",
        "tgn:7001335",
        "tgn:7029392"
    ],
    "tgn:id":7537386,
    "tgn:name:en":"Qusaima, Bir",
    "tgn:placetype":[
        "aat:300008697"
    ]
},
  "bbox": [],
  "geometry": {"coordinates":[34.366667,30.666667],"type":"Point"}
}