{
  "id": 7052517,
  "type": "Feature",
  "properties": {
    "tgn:hierarchy":[
        "tgn:7052517",
        "tgn:7015163",
        "tgn:1000003",
        "tgn:7003121",
        "tgn:1000080",
        "tgn:7029392"
    ],
    "tgn:id":7052517,
    "tgn:name":"Malosu, Monte",
    "tgn:placetype":[
        "aat:300008795"
    ]
},
  "bbox": [],
  "geometry": {"coordinates":[8.966667,40.566667],"type":"Point"}
}