{
  "id": 7033340,
  "type": "Feature",
  "properties": {
    "tgn:hierarchy":[
        "tgn:7033340",
        "tgn:1003440",
        "tgn:1000003",
        "tgn:7003124",
        "tgn:1000080",
        "tgn:7029392"
    ],
    "tgn:id":7033340,
    "tgn:name":"Rio, Val del",
    "tgn:placetype":[
        "aat:300008761"
    ]
},
  "bbox": [],
  "geometry": {"coordinates":[12.080278,46.943889],"type":"Point"}
}