{
  "id": 2170284,
  "type": "Feature",
  "properties": {
    "tgn:hierarchy":[
        "tgn:2170284",
        "tgn:1000001",
        "tgn:7012149",
        "tgn:7029392"
    ],
    "tgn:id":2170284,
    "tgn:name":"Big Ridge",
    "tgn:placetype":[
        "aat:300266640"
    ]
},
  "bbox": [],
  "geometry": {"coordinates":[-82.45,36.0167],"type":"Point"}
}