{
  "id": 2003216,
  "type": "Feature",
  "properties": {
    "tgn:hierarchy":[
        "tgn:2003216",
        "tgn:7002659",
        "tgn:1000001",
        "tgn:7012149",
        "tgn:2000048",
        "tgn:7029392"
    ],
    "tgn:id":2003216,
    "tgn:name":"Creola",
    "tgn:placetype":[
        "aat:300008347"
    ]
},
  "bbox": [],
  "geometry": {"coordinates":[-88.0333,30.8833],"type":"Point"}
}