{
  "id": 2586858,
  "type": "Feature",
  "properties": {
    "tgn:hierarchy":[
        "tgn:2586858",
        "tgn:1000001",
        "tgn:7012149",
        "tgn:2001533",
        "tgn:7007709",
        "tgn:7029392"
    ],
    "tgn:id":2586858,
    "tgn:name":"Plain View",
    "tgn:placetype":[
        "aat:300008347"
    ]
},
  "bbox": [],
  "geometry": {"coordinates":[-79.7167,35.1333],"type":"Point"}
}