{
  "id": 2619975,
  "type": "Feature",
  "properties": {
    "tgn:hierarchy":[
        "tgn:2619975",
        "tgn:1000001",
        "tgn:7012149",
        "tgn:1002943",
        "tgn:7007708",
        "tgn:7029392"
    ],
    "tgn:id":2619975,
    "tgn:name":"Ripple Creek",
    "tgn:placetype":[
        "aat:300008706"
    ]
},
  "bbox": [],
  "geometry": {"coordinates":[-123.5667,45.6667],"type":"Point"}
}