{
  "id": 7459977,
  "type": "Feature",
  "properties": {
    "tgn:hierarchy":[
        "tgn:7459977",
        "tgn:7002444",
        "tgn:1000003",
        "tgn:7008072",
        "tgn:7008591",
        "tgn:7029392"
    ],
    "tgn:id":7459977,
    "tgn:name:en":"Mellerstain House",
    "tgn:placetype":[
        "aat:300387502"
    ]
},
  "bbox": [],
  "geometry": {"coordinates":[-2.566667,55.633333],"type":"Point"}
}