{
  "id": 2537242,
  "type": "Feature",
  "properties": {
    "tgn:hierarchy":[
        "tgn:2537242",
        "tgn:1000001",
        "tgn:2001269",
        "tgn:7012149",
        "tgn:7007524",
        "tgn:7029392"
    ],
    "tgn:id":2537242,
    "tgn:name":"Negro Coulee",
    "tgn:placetype":[
        "aat:300008761"
    ]
},
  "bbox": [],
  "geometry": {"coordinates":[-105.6167,48.7333],"type":"Point"}
}