{
  "id": 7142794,
  "type": "Feature",
  "properties": {
    "tgn:hierarchy":[
        "tgn:7142794",
        "tgn:1000003",
        "tgn:7000094",
        "tgn:7000084",
        "tgn:7029392"
    ],
    "tgn:id":7142794,
    "tgn:name":"Loh-Berg",
    "tgn:placetype":[
        "aat:300008777"
    ]
},
  "bbox": [],
  "geometry": {"coordinates":[11.933333,53.716667],"type":"Point"}
}