{
  "id": 2505892,
  "type": "Feature",
  "properties": {
    "tgn:hierarchy":[
        "tgn:2505892",
        "tgn:1000001",
        "tgn:7012149",
        "tgn:7007157",
        "tgn:1002621",
        "tgn:7029392"
    ],
    "tgn:id":2505892,
    "tgn:name":"Mercer Mountain",
    "tgn:placetype":[
        "aat:300008798"
    ]
},
  "bbox": [],
  "geometry": {"coordinates":[-119.6667,37.1167],"type":"Point"}
}