{
  "id": 2478628,
  "type": "Feature",
  "properties": {
    "tgn:hierarchy":[
        "tgn:2478628",
        "tgn:1000001",
        "tgn:7012149",
        "tgn:2002010",
        "tgn:7007826",
        "tgn:7029392"
    ],
    "tgn:id":2478628,
    "tgn:name":"Madera Canyon",
    "tgn:placetype":[
        "aat:300008761"
    ]
},
  "bbox": [],
  "geometry": {"coordinates":[-104.1667,30.6333],"type":"Point"}
}