{
  "id": 7571072,
  "type": "Feature",
  "properties": {
    "tgn:hierarchy":[
        "tgn:7571072",
        "tgn:1000004",
        "tgn:1001832",
        "tgn:7000198",
        "tgn:7029392"
    ],
    "tgn:id":7571072,
    "tgn:name:en":"K\u0101lj\u0101ni River",
    "tgn:placetype":[
        "aat:300008699"
    ]
},
  "bbox": [],
  "geometry": {"coordinates":[89.694582,26.208866],"type":"Point"}
}