{
  "id": 1038149,
  "type": "Feature",
  "properties": {
    "tgn:hierarchy":[
        "tgn:1038149",
        "tgn:1000003",
        "tgn:7003678",
        "tgn:7000084",
        "tgn:7029392"
    ],
    "tgn:id":1038149,
    "tgn:name":"Allendorf",
    "tgn:placetype":[
        "aat:300008347"
    ]
},
  "bbox": [],
  "geometry": {"coordinates":[8.666667,51.033333],"type":"Point"}
}