<<<<<<< HEAD
{
  "id": 7368001,
  "type": "Feature",
  "properties": {
    "tgn:hierarchy":[
        "tgn:7368001",
        "tgn:1000001",
        "tgn:7005599",
        "tgn:7005560",
        "tgn:7029392"
    ],
    "tgn:id":7368001,
    "tgn:name":"Jobal",
    "tgn:placetype":[
        "aat:300008347"
    ]
},
  "bbox": [],
  "geometry": {"coordinates":[-95.816667,17.866667],"type":"Point"}
}
=======
{"geometry":{"type":"Point","coordinates":[-95.816667,17.866667]},"type":"Feature","properties":{"hierarchy":["tgn:7368001","tgn:1000001","tgn:7005599","tgn:7005560","tgn:7029392"],"placetype":["aat:300008347"],"id":7368001,"name:xx":"Jobal"}}
>>>>>>> 03f74aca74312dbeaf24d7e61306dd6a786dc3d0
