<<<<<<< HEAD
{
  "id": 2256870,
  "type": "Feature",
  "properties": {
    "tgn:hierarchy":[
        "tgn:2256870",
        "tgn:1000001",
        "tgn:7012149",
        "tgn:2001307",
        "tgn:7007524",
        "tgn:7029392"
    ],
    "tgn:id":2256870,
    "tgn:name":"Corkscrew Creek",
    "tgn:placetype":[
        "aat:300008706"
    ]
},
  "bbox": [],
  "geometry": {"coordinates":[-109.95,45.1833],"type":"Point"}
}
=======
{"geometry":{"type":"Point","coordinates":[-109.950000,45.183300]},"type":"Feature","properties":{"hierarchy":["tgn:2256870","tgn:1000001","tgn:7012149","tgn:2001307","tgn:7007524","tgn:7029392"],"placetype":["aat:300008706"],"id":2256870,"name:xx":"Corkscrew Creek"}}
>>>>>>> 03f74aca74312dbeaf24d7e61306dd6a786dc3d0
