{
  "id": 1087909,
  "type": "Feature",
  "properties": {
    "tgn:hierarchy":[
        "tgn:1087909",
        "tgn:7001242",
        "tgn:1000836",
        "tgn:1000149",
        "tgn:7029392"
    ],
    "tgn:id":1087909,
    "tgn:name":"Muculo",
    "tgn:placetype":[
        "aat:300008347"
    ]
},
  "bbox": [],
  "geometry": {"coordinates":[14.8167,-16.7833],"type":"Point"}
}