{
  "id": 2776973,
  "type": "Feature",
  "properties": {
    "tgn:hierarchy":[
        "tgn:2776973",
        "tgn:1000001",
        "tgn:7012149",
        "tgn:1002899",
        "tgn:7007920",
        "tgn:7029392"
    ],
    "tgn:id":2776973,
    "tgn:name":"Windy Creek",
    "tgn:placetype":[
        "aat:300008706"
    ]
},
  "bbox": [],
  "geometry": {"coordinates":[-121.6833,48.1333],"type":"Point"}
}