{
  "id": 7508874,
  "type": "Feature",
  "properties": {
    "tgn:hierarchy":[
        "tgn:7508874",
        "tgn:7520092",
        "tgn:1008380",
        "tgn:1000226",
        "tgn:1000006",
        "tgn:7029392"
    ],
    "tgn:id":7508874,
    "tgn:name:en":"Waiomoku River",
    "tgn:placetype":[
        "aat:300008699"
    ]
},
  "bbox": [],
  "geometry": {"coordinates":[178.216667,-38.583333],"type":"Point"}
}