<<<<<<< HEAD
{
  "id": 2156702,
  "type": "Feature",
  "properties": {
    "tgn:hierarchy":[
        "tgn:2156702",
        "tgn:1000001",
        "tgn:7012149",
        "tgn:2001879",
        "tgn:7007825",
        "tgn:7029392"
    ],
    "tgn:id":2156702,
    "tgn:name":"Beason Branch",
    "tgn:placetype":[
        "aat:300008699"
    ]
},
  "bbox": [],
  "geometry": {"coordinates":[-87.9,35.8833],"type":"Point"}
}
=======
{"geometry":{"type":"Point","coordinates":[-87.900000,35.883300]},"type":"Feature","properties":{"hierarchy":["tgn:2156702","tgn:1000001","tgn:7012149","tgn:2001879","tgn:7007825","tgn:7029392"],"placetype":["aat:300008699"],"id":2156702,"name:xx":"Beason Branch"}}
>>>>>>> 03f74aca74312dbeaf24d7e61306dd6a786dc3d0
