{
  "id": 1114231,
  "type": "Feature",
  "properties": {
    "tgn:hierarchy":[
        "tgn:1114231",
        "tgn:7018508",
        "tgn:1010363",
        "tgn:1000220",
        "tgn:1000006",
        "tgn:7029392"
    ],
    "tgn:id":1114231,
    "tgn:name":"Piaanu Pass",
    "tgn:placetype":[
        "aat:300008713"
    ]
},
  "bbox": [],
  "geometry": {"coordinates":[151.45,7.35],"type":"Point"}
}