{
  "id": 2349968,
  "type": "Feature",
  "properties": {
    "tgn:hierarchy":[
        "tgn:2349968",
        "tgn:1000001",
        "tgn:7012149",
        "tgn:2002360",
        "tgn:7007922",
        "tgn:7029392"
    ],
    "tgn:id":2349968,
    "tgn:name":"Gilmore Lake",
    "tgn:placetype":[
        "aat:300008680"
    ]
},
  "bbox": [],
  "geometry": {"coordinates":[-91.8667,46.1333],"type":"Point"}
}