{
  "id": 7411616,
  "type": "Feature",
  "properties": {
    "tgn:hierarchy":[
        "tgn:7411616",
        "tgn:7005587",
        "tgn:1000001",
        "tgn:7005560",
        "tgn:7029392"
    ],
    "tgn:id":7411616,
    "tgn:name:es":"La Aguja,Cerro",
    "tgn:placetype":[
        "aat:300008795"
    ]
},
  "bbox": [],
  "geometry": {"coordinates":[-98.590278,20.8875],"type":"Point"}
}