{
  "id": 7277584,
  "type": "Feature",
  "properties": {
    "tgn:hierarchy":[
        "tgn:7277584",
        "tgn:1001702",
        "tgn:1000049",
        "tgn:1000002",
        "tgn:7029392"
    ],
    "tgn:id":7277584,
    "tgn:name":"Windward, Bah\u00eda",
    "tgn:placetype":[
        "aat:300132316"
    ]
},
  "bbox": [],
  "geometry": {"coordinates":[-74.766667,-50.066667],"type":"Point"}
}