{
  "id": 7184884,
  "type": "Feature",
  "properties": {
    "tgn:hierarchy":[
        "tgn:7184884",
        "tgn:7000096",
        "tgn:1000003",
        "tgn:7000084",
        "tgn:7029392"
    ],
    "tgn:id":7184884,
    "tgn:name":"Grase-Teich",
    "tgn:placetype":[
        "aat:300008688"
    ]
},
  "bbox": [],
  "geometry": {"coordinates":[13.516667,51.716667],"type":"Point"}
}