{
  "id": 2523196,
  "type": "Feature",
  "properties": {
    "tgn:hierarchy":[
        "tgn:2523196",
        "tgn:1000001",
        "tgn:1002902",
        "tgn:7012149",
        "tgn:7007516",
        "tgn:7029392"
    ],
    "tgn:id":2523196,
    "tgn:name":"Moores Gut",
    "tgn:placetype":[
        "aat:300008699"
    ]
},
  "bbox": [],
  "geometry": {"coordinates":[-75.9167,38.15],"type":"Point"}
}