{
  "id": 2379767,
  "type": "Feature",
  "properties": {
    "tgn:hierarchy":[
        "tgn:2379767",
        "tgn:1000001",
        "tgn:1002359",
        "tgn:7012149",
        "tgn:7007517",
        "tgn:7029392"
    ],
    "tgn:id":2379767,
    "tgn:name":"Haste Shoal",
    "tgn:placetype":[
        "aat:300132348"
    ]
},
  "bbox": [],
  "geometry": {"coordinates":[-70.8333,42.5333],"type":"Point"}
}