<<<<<<< HEAD
{
  "id": 7375270,
  "type": "Feature",
  "properties": {
    "tgn:hierarchy":[
        "tgn:7375270",
        "tgn:7005585",
        "tgn:1000001",
        "tgn:7005560",
        "tgn:7029392"
    ],
    "tgn:id":7375270,
    "tgn:name":"Las Pozas",
    "tgn:placetype":[
        "aat:300008347"
    ]
},
  "bbox": [],
  "geometry": {"coordinates":[-101.466667,17.566667],"type":"Point"}
}
=======
{"geometry":{"type":"Point","coordinates":[-101.466667,17.566667]},"type":"Feature","properties":{"hierarchy":["tgn:7375270","tgn:7005585","tgn:1000001","tgn:7005560","tgn:7029392"],"placetype":["aat:300008347"],"id":7375270,"name:xx":"Las Pozas"}}
>>>>>>> 03f74aca74312dbeaf24d7e61306dd6a786dc3d0
