<<<<<<< HEAD
{
  "id": 2338686,
  "type": "Feature",
  "properties": {
    "tgn:hierarchy":[
        "tgn:2338686",
        "tgn:1000001",
        "tgn:7012149",
        "tgn:7007157",
        "tgn:1003050",
        "tgn:7029392"
    ],
    "tgn:id":2338686,
    "tgn:name":"Francis, Lake",
    "tgn:placetype":[
        "aat:300006191"
    ]
},
  "bbox": [],
  "geometry": {"coordinates":[-121.2,39.35],"type":"Point"}
}
=======
{"geometry":{"type":"Point","coordinates":[-121.200000,39.350000]},"type":"Feature","properties":{"hierarchy":["tgn:2338686","tgn:1000001","tgn:7012149","tgn:7007157","tgn:1003050","tgn:7029392"],"placetype":["aat:300006191"],"id":2338686,"name:xx":"Francis, Lake"}}
>>>>>>> 03f74aca74312dbeaf24d7e61306dd6a786dc3d0
