{
  "id": 2547362,
  "type": "Feature",
  "properties": {
    "tgn:hierarchy":[
        "tgn:2547362",
        "tgn:1000001",
        "tgn:7012149",
        "tgn:2001715",
        "tgn:7007708",
        "tgn:7029392"
    ],
    "tgn:id":2547362,
    "tgn:name":"North Fork Silver Creek",
    "tgn:placetype":[
        "aat:300008706"
    ]
},
  "bbox": [],
  "geometry": {"coordinates":[-121.25,42.95],"type":"Point"}
}