<<<<<<< HEAD
{
  "id": 7369823,
  "type": "Feature",
  "properties": {
    "tgn:hierarchy":[
        "tgn:7369823",
        "tgn:1000001",
        "tgn:1001960",
        "tgn:7005560",
        "tgn:7029392"
    ],
    "tgn:id":7369823,
    "tgn:name":"Garambullo",
    "tgn:placetype":[
        "aat:300167671"
    ]
},
  "bbox": [],
  "geometry": {"coordinates":[-112.4,31.15],"type":"Point"}
}
=======
{"geometry":{"type":"Point","coordinates":[-112.400000,31.150000]},"type":"Feature","properties":{"hierarchy":["tgn:7369823","tgn:1000001","tgn:1001960","tgn:7005560","tgn:7029392"],"placetype":["aat:300167671"],"id":7369823,"name:xx":"Garambullo"}}
>>>>>>> 03f74aca74312dbeaf24d7e61306dd6a786dc3d0
