{
  "id": 2765909,
  "type": "Feature",
  "properties": {
    "tgn:hierarchy":[
        "tgn:2765909",
        "tgn:1000001",
        "tgn:2001016",
        "tgn:7012149",
        "tgn:7007521",
        "tgn:7029392"
    ],
    "tgn:id":2765909,
    "tgn:name":"White Hawk",
    "tgn:placetype":[
        "aat:300008347"
    ]
},
  "bbox": [],
  "geometry": {"coordinates":[-93.8167,46.3833],"type":"Point"}
}