{
  "id": 7234435,
  "type": "Feature",
  "properties": {
    "tgn:hierarchy":[
        "tgn:7234435",
        "tgn:7002706",
        "tgn:7002705",
        "tgn:1000003",
        "tgn:1000074",
        "tgn:7029392"
    ],
    "tgn:id":7234435,
    "tgn:name":"Dafno\u00fala",
    "tgn:placetype":[
        "aat:300008347"
    ]
},
  "bbox": [],
  "geometry": {"coordinates":[21.027778,39.291944],"type":"Point"}
}