{
  "id": 7408736,
  "type": "Feature",
  "properties": {
    "tgn:hierarchy":[
        "tgn:7408736",
        "tgn:1000001",
        "tgn:1001893",
        "tgn:7005560",
        "tgn:7029392"
    ],
    "tgn:id":7408736,
    "tgn:name":"Guadalupe Relinas",
    "tgn:placetype":[
        "aat:300008347"
    ]
},
  "bbox": [],
  "geometry": {"coordinates":[-98.775,19.875],"type":"Point"}
}