{
  "id": 2662520,
  "type": "Feature",
  "properties": {
    "tgn:hierarchy":[
        "tgn:2662520",
        "tgn:1000001",
        "tgn:2001429",
        "tgn:7012149",
        "tgn:7007566",
        "tgn:7029392"
    ],
    "tgn:id":2662520,
    "tgn:name":"Sign Camp Mountain",
    "tgn:placetype":[
        "aat:300008798"
    ]
},
  "bbox": [],
  "geometry": {"coordinates":[-108.6833,33.55],"type":"Point"}
}