{
  "id": 7040376,
  "type": "Feature",
  "properties": {
    "tgn:hierarchy":[
        "tgn:7040376",
        "tgn:7003011",
        "tgn:7003005",
        "tgn:1000003",
        "tgn:1000080",
        "tgn:7029392"
    ],
    "tgn:id":7040376,
    "tgn:name":"Sant'Angelo d'Alife",
    "tgn:placetype":[
        "aat:300008347"
    ]
},
  "bbox": [],
  "geometry": {"coordinates":[14.25,41.366667],"type":"Point"}
}