{
  "id": 2430192,
  "type": "Feature",
  "properties": {
    "tgn:hierarchy":[
        "tgn:2430192",
        "tgn:1000001",
        "tgn:7012149",
        "tgn:1002520",
        "tgn:7007710",
        "tgn:7029392"
    ],
    "tgn:id":2430192,
    "tgn:name":"Kahle Run",
    "tgn:placetype":[
        "aat:300008699"
    ]
},
  "bbox": [],
  "geometry": {"coordinates":[-79.1667,41.2667],"type":"Point"}
}