{
  "id": 2191212,
  "type": "Feature",
  "properties": {
    "tgn:hierarchy":[
        "tgn:2191212",
        "tgn:1000001",
        "tgn:7012149",
        "tgn:2001975",
        "tgn:7007826",
        "tgn:7029392"
    ],
    "tgn:id":2191212,
    "tgn:name":"Boynton Reservoir",
    "tgn:placetype":[
        "aat:300006191"
    ]
},
  "bbox": [],
  "geometry": {"coordinates":[-99.7667,28.6167],"type":"Point"}
}