{
  "id": 2264119,
  "type": "Feature",
  "properties": {
    "tgn:hierarchy":[
        "tgn:2264119",
        "tgn:1000001",
        "tgn:7012149",
        "tgn:1002990",
        "tgn:7007708",
        "tgn:7029392"
    ],
    "tgn:id":2264119,
    "tgn:name":"Coyote Spring",
    "tgn:placetype":[
        "aat:300008697"
    ]
},
  "bbox": [],
  "geometry": {"coordinates":[-121.4333,45.05],"type":"Point"}
}