{
  "id": 2093489,
  "type": "Feature",
  "properties": {
    "tgn:hierarchy":[
        "tgn:2093489",
        "tgn:1000001",
        "tgn:7012149",
        "tgn:1002692",
        "tgn:7007710",
        "tgn:7029392"
    ],
    "tgn:id":2093489,
    "tgn:name":"Strawberry Ridge",
    "tgn:placetype":[
        "aat:300008347",
        "aat:300387210"
    ]
},
  "bbox": [],
  "geometry": {"coordinates":[-76.65,41.0667],"type":"Point"}
}