{
  "id": 2349583,
  "type": "Feature",
  "properties": {
    "tgn:hierarchy":[
        "tgn:2349583",
        "tgn:1000001",
        "tgn:7012149",
        "tgn:7007157",
        "tgn:1002894",
        "tgn:7029392"
    ],
    "tgn:id":2349583,
    "tgn:name":"Gillespie Dam",
    "tgn:placetype":[
        "aat:300000390"
    ]
},
  "bbox": [],
  "geometry": {"coordinates":[-120.65,39.55],"type":"Point"}
}