{
  "id": 2292364,
  "type": "Feature",
  "properties": {
    "tgn:hierarchy":[
        "tgn:2292364",
        "tgn:1000001",
        "tgn:7012149",
        "tgn:7007157",
        "tgn:1002710",
        "tgn:7029392"
    ],
    "tgn:id":2292364,
    "tgn:name":"Donner Ridge",
    "tgn:placetype":[
        "aat:300266640"
    ]
},
  "bbox": [],
  "geometry": {"coordinates":[-120.2833,39.35],"type":"Point"}
}