{
  "id": 2185762,
  "type": "Feature",
  "properties": {
    "tgn:hierarchy":[
        "tgn:2185762",
        "tgn:1000001",
        "tgn:7012149",
        "tgn:7007712",
        "tgn:7029392"
    ],
    "tgn:id":2185762,
    "tgn:name":"Bold Branch",
    "tgn:placetype":[
        "aat:300008699"
    ]
},
  "bbox": [],
  "geometry": {"coordinates":[-82.3667,34.0667],"type":"Point"}
}