<<<<<<< HEAD
{
  "id": 2250731,
  "type": "Feature",
  "properties": {
    "tgn:hierarchy":[
        "tgn:2250731",
        "tgn:1000001",
        "tgn:2000299",
        "tgn:7012149",
        "tgn:7007248",
        "tgn:7029392"
    ],
    "tgn:id":2250731,
    "tgn:name":"Colston Mountain",
    "tgn:placetype":[
        "aat:300008798"
    ]
},
  "bbox": [],
  "geometry": {"coordinates":[-84.9667,34.2667],"type":"Point"}
}
=======
{"geometry":{"type":"Point","coordinates":[-84.966700,34.266700]},"type":"Feature","properties":{"hierarchy":["tgn:2250731","tgn:1000001","tgn:2000299","tgn:7012149","tgn:7007248","tgn:7029392"],"placetype":["aat:300008798"],"id":2250731,"name:xx":"Colston Mountain"}}
>>>>>>> 03f74aca74312dbeaf24d7e61306dd6a786dc3d0
