{
  "id": 2250731,
  "type": "Feature",
  "properties": {
    "tgn:hierarchy":[
        "tgn:2250731",
        "tgn:1000001",
        "tgn:2000299",
        "tgn:7012149",
        "tgn:7007248",
        "tgn:7029392"
    ],
    "tgn:id":2250731,
    "tgn:name":"Colston Mountain",
    "tgn:placetype":[
        "aat:300008798"
    ]
},
  "bbox": [],
  "geometry": {"coordinates":[-84.9667,34.2667],"type":"Point"}
}