{
  "id": 7008356,
  "type": "Feature",
  "properties": {
    "tgn:hierarchy":[
        "tgn:7008356",
        "tgn:1000003",
        "tgn:7002881",
        "tgn:1000070",
        "tgn:7029392"
    ],
    "tgn:id":7008356,
    "tgn:name":"Besan\u00e7on",
    "tgn:placetype":[
        "aat:300387236",
        "aat:300008347",
        "aat:300000810",
        "aat:300387218",
        "aat:300387225",
        "aat:300008389",
        "aat:300264742",
        "aat:300387512",
        "aat:300387302"
    ]
},
  "bbox": [],
  "geometry": {"coordinates":[6.0333,47.2333],"type":"Point"}
}