{
  "id": 7575375,
  "type": "Feature",
  "properties": {
    "tgn:hierarchy":[
        "tgn:7575375",
        "tgn:1000004",
        "tgn:7000198",
        "tgn:7031783",
        "tgn:7029392"
    ],
    "tgn:id":7575375,
    "tgn:name:en":"Kenduy\u0101dih",
    "tgn:placetype":[
        "aat:300008347"
    ]
},
  "bbox": [],
  "geometry": {"coordinates":[86.383333,23.733333],"type":"Point"}
}