{
  "id": 2477848,
  "type": "Feature",
  "properties": {
    "tgn:hierarchy":[
        "tgn:2477848",
        "tgn:1000001",
        "tgn:7012149",
        "tgn:2002252",
        "tgn:7007920",
        "tgn:7029392"
    ],
    "tgn:id":2477848,
    "tgn:name":"MacMurry Canyon",
    "tgn:placetype":[
        "aat:300008761"
    ]
},
  "bbox": [],
  "geometry": {"coordinates":[-117.3167,46.65],"type":"Point"}
}