{
  "id": 2683860,
  "type": "Feature",
  "properties": {
    "tgn:hierarchy":[
        "tgn:2683860",
        "tgn:1000001",
        "tgn:7012149",
        "tgn:2002189",
        "tgn:7007919",
        "tgn:7029392"
    ],
    "tgn:id":2683860,
    "tgn:name":"Speers Ferry Cave",
    "tgn:placetype":[
        "aat:300008746"
    ]
},
  "bbox": [],
  "geometry": {"coordinates":[-82.7333,36.6333],"type":"Point"}
}