{
  "id": 7587538,
  "type": "Feature",
  "properties": {
    "tgn:hierarchy":[
        "tgn:7587538",
        "tgn:1000004",
        "tgn:7000198",
        "tgn:7000799",
        "tgn:7029392"
    ],
    "tgn:id":7587538,
    "tgn:name:en":"Hardo W\u0101min",
    "tgn:placetype":[
        "aat:300008347"
    ]
},
  "bbox": [],
  "geometry": {"coordinates":[74.634722,34.090278],"type":"Point"}
}