{
  "id": 2261990,
  "type": "Feature",
  "properties": {
    "tgn:hierarchy":[
        "tgn:2261990",
        "tgn:1000001",
        "tgn:7012149",
        "tgn:1002456",
        "tgn:7007826",
        "tgn:7029392"
    ],
    "tgn:id":2261990,
    "tgn:name":"Cow Bayou",
    "tgn:placetype":[
        "aat:300008699"
    ]
},
  "bbox": [],
  "geometry": {"coordinates":[-95.1167,29.5333],"type":"Point"}
}