{
  "id": 1138718,
  "type": "Feature",
  "properties": {
    "tgn:hierarchy":[
        "tgn:1138718",
        "tgn:7016612",
        "tgn:1001138",
        "tgn:1000004",
        "tgn:7029392"
    ],
    "tgn:id":1138718,
    "tgn:name":"Dowlatabad",
    "tgn:placetype":[
        "aat:300008347"
    ]
},
  "bbox": [],
  "geometry": {"coordinates":[66.8167,36.9833],"type":"Point"}
}