{
  "id": 2393941,
  "type": "Feature",
  "properties": {
    "tgn:hierarchy":[
        "tgn:2393941",
        "tgn:1000001",
        "tgn:2001840",
        "tgn:7012149",
        "tgn:7007825",
        "tgn:7029392"
    ],
    "tgn:id":2393941,
    "tgn:name":"Hog Point",
    "tgn:placetype":[
        "aat:300008850"
    ]
},
  "bbox": [],
  "geometry": {"coordinates":[-85.3167,35.4833],"type":"Point"}
}