{
  "id": 2037567,
  "type": "Feature",
  "properties": {
    "tgn:hierarchy":[
        "tgn:2037567",
        "tgn:1000001",
        "tgn:7012149",
        "tgn:2000852",
        "tgn:7007255",
        "tgn:7029392"
    ],
    "tgn:id":2037567,
    "tgn:name":"Ayers",
    "tgn:placetype":[
        "aat:300008347",
        "aat:300387210"
    ]
},
  "bbox": [],
  "geometry": {"coordinates":[-84.2167,36.6167],"type":"Point"}
}