{
  "id": 2690326,
  "type": "Feature",
  "properties": {
    "tgn:hierarchy":[
        "tgn:2690326",
        "tgn:1000001",
        "tgn:7012149",
        "tgn:2002005",
        "tgn:7007826",
        "tgn:7029392"
    ],
    "tgn:id":2690326,
    "tgn:name":"Stage Road Tank",
    "tgn:placetype":[
        "aat:300006191"
    ]
},
  "bbox": [],
  "geometry": {"coordinates":[-105.1167,31.0167],"type":"Point"}
}