{
  "id": 7279693,
  "type": "Feature",
  "properties": {
    "tgn:hierarchy":[
        "tgn:7279693",
        "tgn:1001695",
        "tgn:1000049",
        "tgn:1000002",
        "tgn:7029392"
    ],
    "tgn:id":7279693,
    "tgn:name":"R\u00e1nguil Bajo",
    "tgn:placetype":[
        "aat:300000206"
    ]
},
  "bbox": [],
  "geometry": {"coordinates":[-71.766667,-34.866667],"type":"Point"}
}