{
  "id": 7502884,
  "type": "Feature",
  "properties": {
    "tgn:hierarchy":[
        "tgn:7502884",
        "tgn:1000004",
        "tgn:7471332",
        "tgn:1000141",
        "tgn:7029392"
    ],
    "tgn:id":7502884,
    "tgn:name":"Diliu Gongmu",
    "tgn:placetype":[
        "aat:300266755"
    ]
},
  "bbox": [],
  "geometry": {"coordinates":[120.936111,24.75],"type":"Point"}
}