{
  "id": 7455226,
  "type": "Feature",
  "properties": {
    "tgn:hierarchy":[
        "tgn:7455226",
        "tgn:7002443",
        "tgn:1000003",
        "tgn:5000560",
        "tgn:7008591",
        "tgn:7029392"
    ],
    "tgn:id":7455226,
    "tgn:name:en":"Cwmcarvan",
    "tgn:placetype":[
        "aat:300008347"
    ]
},
  "bbox": [],
  "geometry": {"coordinates":[-2.75,51.766667],"type":"Point"}
}