<<<<<<< HEAD
{
  "id": 7171769,
  "type": "Feature",
  "properties": {
    "tgn:hierarchy":[
        "tgn:7171769",
        "tgn:7003669",
        "tgn:1000003",
        "tgn:7000084",
        "tgn:7029392"
    ],
    "tgn:id":7171769,
    "tgn:name":"Hirnstetten",
    "tgn:placetype":[
        "aat:300008347"
    ]
},
  "bbox": [],
  "geometry": {"coordinates":[11.283333,48.966667],"type":"Point"}
}
=======
{"geometry":{"type":"Point","coordinates":[11.283333,48.966667]},"type":"Feature","properties":{"hierarchy":["tgn:7171769","tgn:7003669","tgn:1000003","tgn:7000084","tgn:7029392"],"placetype":["aat:300008347"],"id":7171769,"name:xx":"Hirnstetten"}}
>>>>>>> 03f74aca74312dbeaf24d7e61306dd6a786dc3d0
