{
  "id": 2258559,
  "type": "Feature",
  "properties": {
    "tgn:hierarchy":[
        "tgn:2258559",
        "tgn:1000001",
        "tgn:7012149",
        "tgn:7007157",
        "tgn:1002863",
        "tgn:7029392"
    ],
    "tgn:id":2258559,
    "tgn:name":"Cottontail Creek",
    "tgn:placetype":[
        "aat:300008706"
    ]
},
  "bbox": [],
  "geometry": {"coordinates":[-120.85,35.5167],"type":"Point"}
}