{
  "id": 2215206,
  "type": "Feature",
  "properties": {
    "tgn:hierarchy":[
        "tgn:2215206",
        "tgn:1000001",
        "tgn:7012149",
        "tgn:2000927",
        "tgn:7007515",
        "tgn:7029392"
    ],
    "tgn:id":2215206,
    "tgn:name":"Call Bog",
    "tgn:placetype":[
        "aat:300008905"
    ]
},
  "bbox": [],
  "geometry": {"coordinates":[-68.8667,45.0333],"type":"Point"}
}