{
  "id": 2561555,
  "type": "Feature",
  "properties": {
    "tgn:hierarchy":[
        "tgn:2561555",
        "tgn:1000001",
        "tgn:2000202",
        "tgn:7012149",
        "tgn:7007158",
        "tgn:7029392"
    ],
    "tgn:id":2561555,
    "tgn:name":"Osier Mountain",
    "tgn:placetype":[
        "aat:300008798"
    ]
},
  "bbox": [],
  "geometry": {"coordinates":[-106.3167,37.0167],"type":"Point"}
}