<<<<<<< HEAD
{
  "id": 2406127,
  "type": "Feature",
  "properties": {
    "tgn:hierarchy":[
        "tgn:2406127",
        "tgn:1000001",
        "tgn:7006451",
        "tgn:7012149",
        "tgn:2000104",
        "tgn:7029392"
    ],
    "tgn:id":2406127,
    "tgn:name":"Hummingbird Canyon",
    "tgn:placetype":[
        "aat:300008761"
    ]
},
  "bbox": [],
  "geometry": {"coordinates":[-113.5333,32.25],"type":"Point"}
}
=======
{"geometry":{"type":"Point","coordinates":[-113.533300,32.250000]},"type":"Feature","properties":{"hierarchy":["tgn:2406127","tgn:1000001","tgn:7006451","tgn:7012149","tgn:2000104","tgn:7029392"],"placetype":["aat:300008761"],"id":2406127,"name:xx":"Hummingbird Canyon"}}
>>>>>>> 03f74aca74312dbeaf24d7e61306dd6a786dc3d0
