{
  "id": 2771609,
  "type": "Feature",
  "properties": {
    "tgn:hierarchy":[
        "tgn:2771609",
        "tgn:1000001",
        "tgn:7012149",
        "tgn:2001525",
        "tgn:7007709",
        "tgn:7029392"
    ],
    "tgn:id":2771609,
    "tgn:name":"Wildwood",
    "tgn:placetype":[
        "aat:300008347"
    ]
},
  "bbox": [],
  "geometry": {"coordinates":[-79.0833,36.0333],"type":"Point"}
}