{
  "id": 2477232,
  "type": "Feature",
  "properties": {
    "tgn:hierarchy":[
        "tgn:2477232",
        "tgn:1000001",
        "tgn:7012149",
        "tgn:2001298",
        "tgn:7007524",
        "tgn:7029392"
    ],
    "tgn:id":2477232,
    "tgn:name":"Lynn Reservoir",
    "tgn:placetype":[
        "aat:300006191"
    ]
},
  "bbox": [],
  "geometry": {"coordinates":[-113.2333,47.0833],"type":"Point"}
}