{
  "id": 7072725,
  "type": "Feature",
  "properties": {
    "tgn:hierarchy":[
        "tgn:7072725",
        "tgn:1000003",
        "tgn:7003676",
        "tgn:7000084",
        "tgn:7029392"
    ],
    "tgn:id":7072725,
    "tgn:name":"S\u00fcllhof",
    "tgn:placetype":[
        "aat:300000206"
    ]
},
  "bbox": [],
  "geometry": {"coordinates":[9.116667,52.533333],"type":"Point"}
}