{
  "id": 1045053,
  "type": "Feature",
  "properties": {
    "tgn:hierarchy":[
        "tgn:1045053",
        "tgn:7009084",
        "tgn:7004154",
        "tgn:1000003",
        "tgn:1000080",
        "tgn:7029392"
    ],
    "tgn:id":1045053,
    "tgn:name":"Lecce ne' Marsi",
    "tgn:placetype":[
        "aat:300008347"
    ]
},
  "bbox": [],
  "geometry": {"coordinates":[13.683333,41.933333],"type":"Point"}
}