{
  "id": 7267086,
  "type": "Feature",
  "properties": {
    "tgn:concordances":{
        "gn:id":"2748972"
    },
    "tgn:hierarchy":[
        "tgn:7267086",
        "tgn:1000003",
        "tgn:7003632",
        "tgn:7016845",
        "tgn:7029392"
    ],
    "tgn:id":7267086,
    "tgn:name:nl":"Oudeweg",
    "tgn:placetype":[
        "aat:300008347"
    ]
},
  "bbox": [],
  "geometry": {"coordinates":[4.733333,52.05],"type":"Point"}
}