{
  "id": 7131299,
  "type": "Feature",
  "properties": {
    "tgn:hierarchy":[
        "tgn:7131299",
        "tgn:7003669",
        "tgn:1000003",
        "tgn:7000084",
        "tgn:7029392"
    ],
    "tgn:id":7131299,
    "tgn:name":"Mark",
    "tgn:placetype":[
        "aat:300008863"
    ]
},
  "bbox": [],
  "geometry": {"coordinates":[11.95,49.716667],"type":"Point"}
}