{
  "id": 2473988,
  "type": "Feature",
  "properties": {
    "tgn:hierarchy":[
        "tgn:2473988",
        "tgn:1000001",
        "tgn:7012149",
        "tgn:1002967",
        "tgn:7007520",
        "tgn:7029392"
    ],
    "tgn:id":2473988,
    "tgn:name":"Lower Jeptha Lake Drain",
    "tgn:placetype":[
        "aat:300008699"
    ]
},
  "bbox": [],
  "geometry": {"coordinates":[-86.0167,42.3333],"type":"Point"}
}