{
  "id": 2484524,
  "type": "Feature",
  "properties": {
    "tgn:hierarchy":[
        "tgn:2484524",
        "tgn:1000001",
        "tgn:7012149",
        "tgn:7007157",
        "tgn:2000185",
        "tgn:7029392"
    ],
    "tgn:id":2484524,
    "tgn:name":"Laurel Gulch",
    "tgn:placetype":[
        "aat:300008761"
    ]
},
  "bbox": [],
  "geometry": {"coordinates":[-123.6833,39.1333],"type":"Point"}
}