{
  "id": 7301879,
  "type": "Feature",
  "properties": {
    "tgn:hierarchy":[
        "tgn:7301879",
        "tgn:7002839",
        "tgn:7001158",
        "tgn:1000003",
        "tgn:1000095",
        "tgn:7029392"
    ],
    "tgn:id":7301879,
    "tgn:name":"Miguel Bueno, Arroyo de",
    "tgn:placetype":[
        "aat:300266554",
        "aat:300008699"
    ]
},
  "bbox": [],
  "geometry": {"coordinates":[-4.05,40.966667],"type":"Point"}
}