{
  "id": 7497620,
  "type": "Feature",
  "properties": {
    "tgn:hierarchy":[
        "tgn:7497620",
        "tgn:1000004",
        "tgn:7001009",
        "tgn:1000141",
        "tgn:7029392"
    ],
    "tgn:id":7497620,
    "tgn:name":"Wenxinmei Qiao",
    "tgn:placetype":[
        "aat:300007836"
    ]
},
  "bbox": [],
  "geometry": {"coordinates":[120.6798,24.1732],"type":"Point"}
}