{
  "id": 2080897,
  "type": "Feature",
  "properties": {
    "tgn:hierarchy":[
        "tgn:2080897",
        "tgn:1000001",
        "tgn:7012149",
        "tgn:1002865",
        "tgn:7007706",
        "tgn:7029392"
    ],
    "tgn:id":2080897,
    "tgn:name":"Mount Pleasant",
    "tgn:placetype":[
        "aat:300008347"
    ]
},
  "bbox": [],
  "geometry": {"coordinates":[-82.85,41.2667],"type":"Point"}
}