{
  "id": 7522284,
  "type": "Feature",
  "properties": {
    "tgn:hierarchy":[
        "tgn:7522284",
        "tgn:7001242",
        "tgn:7016833",
        "tgn:1001418",
        "tgn:7029392"
    ],
    "tgn:id":7522284,
    "tgn:name:en":"Abu Samra Reef",
    "tgn:placetype":[
        "aat:300008808"
    ]
},
  "bbox": [],
  "geometry": {"coordinates":[28.282584,31.097042],"type":"Point"}
}