{
  "id": 1088089,
  "type": "Feature",
  "properties": {
    "tgn:hierarchy":[
        "tgn:1088089",
        "tgn:1000824",
        "tgn:7001242",
        "tgn:1000150",
        "tgn:7029392"
    ],
    "tgn:id":1088089,
    "tgn:name":"Nata",
    "tgn:placetype":[
        "aat:300008347"
    ]
},
  "bbox": [],
  "geometry": {"coordinates":[26.1667,-20.1833],"type":"Point"}
}