{
  "id": 7423179,
  "type": "Feature",
  "properties": {
    "tgn:hierarchy":[
        "tgn:7423179",
        "tgn:1000001",
        "tgn:1001960",
        "tgn:7005560",
        "tgn:7029392"
    ],
    "tgn:id":7423179,
    "tgn:name":"San Pedro",
    "tgn:placetype":[
        "aat:300008347"
    ]
},
  "bbox": [],
  "geometry": {"coordinates":[-111.283333,31.066667],"type":"Point"}
}