<<<<<<< HEAD
{
  "id": 7241200,
  "type": "Feature",
  "properties": {
    "tgn:hierarchy":[
        "tgn:7241200",
        "tgn:7003457",
        "tgn:1000003",
        "tgn:1000063",
        "tgn:7018236",
        "tgn:7029392"
    ],
    "tgn:id":7241200,
    "tgn:name":"Kwatrecht",
    "tgn:placetype":[
        "aat:300008347"
    ]
},
  "bbox": [],
  "geometry": {"coordinates":[3.837562,50.987768],"type":"Point"}
}
=======
{"geometry":{"type":"Point","coordinates":[3.837562,50.987768]},"type":"Feature","properties":{"hierarchy":["tgn:7241200","tgn:7003457","tgn:1000003","tgn:1000063","tgn:7018236","tgn:7029392"],"placetype":["aat:300008347"],"id":7241200,"name:xx":"Kwatrecht"}}
>>>>>>> 03f74aca74312dbeaf24d7e61306dd6a786dc3d0
