{
  "id": 1121482,
  "type": "Feature",
  "properties": {
    "tgn:hierarchy":[
        "tgn:1121482",
        "tgn:7006477",
        "tgn:1000002",
        "tgn:7029392"
    ],
    "tgn:id":1121482,
    "tgn:name":"Atuel, R\u00edo",
    "tgn:placetype":[
        "aat:300008707"
    ]
},
  "bbox": [],
  "geometry": {"coordinates":[-66.8333,-36.2833],"type":"Point"}
}