{
  "id": 2677956,
  "type": "Feature",
  "properties": {
    "tgn:hierarchy":[
        "tgn:2677956",
        "tgn:1000001",
        "tgn:2001418",
        "tgn:7012149",
        "tgn:7007526",
        "tgn:7029392"
    ],
    "tgn:id":2677956,
    "tgn:name":"South Fork Apache Tear Canyon",
    "tgn:placetype":[
        "aat:300008761"
    ]
},
  "bbox": [],
  "geometry": {"coordinates":[-116.3333,37.3833],"type":"Point"}
}