{
  "id": 2551070,
  "type": "Feature",
  "properties": {
    "tgn:hierarchy":[
        "tgn:2551070",
        "tgn:1000001",
        "tgn:7012149",
        "tgn:1002472",
        "tgn:7007568",
        "tgn:7029392"
    ],
    "tgn:id":2551070,
    "tgn:name":"Nowadaga Creek",
    "tgn:placetype":[
        "aat:300008706"
    ]
},
  "bbox": [],
  "geometry": {"coordinates":[-74.8833,42.9667],"type":"Point"}
}