{
  "id": 7038826,
  "type": "Feature",
  "properties": {
    "tgn:hierarchy":[
        "tgn:7038826",
        "tgn:1000003",
        "tgn:7003122",
        "tgn:1000080",
        "tgn:7029392"
    ],
    "tgn:id":7038826,
    "tgn:name":"Stagnone, Isole dello",
    "tgn:placetype":[
        "aat:300008791"
    ]
},
  "bbox": [],
  "geometry": {"coordinates":[12.45,37.866667],"type":"Point"}
}