{
  "id": 2393411,
  "type": "Feature",
  "properties": {
    "tgn:hierarchy":[
        "tgn:2393411",
        "tgn:1000001",
        "tgn:7012149",
        "tgn:2000443",
        "tgn:7007248",
        "tgn:7029392"
    ],
    "tgn:id":2393411,
    "tgn:name":"Hog Branch",
    "tgn:placetype":[
        "aat:300008699"
    ]
},
  "bbox": [],
  "geometry": {"coordinates":[-84.4667,32.0667],"type":"Point"}
}