{
  "id": 7227472,
  "type": "Feature",
  "properties": {
    "tgn:hierarchy":[
        "tgn:7227472",
        "tgn:7002751",
        "tgn:7001399",
        "tgn:1000003",
        "tgn:1000074",
        "tgn:7029392"
    ],
    "tgn:id":7227472,
    "tgn:name":"Long\u00e1ria",
    "tgn:placetype":[
        "aat:300008777"
    ]
},
  "bbox": [],
  "geometry": {"coordinates":[23.25,39.133333],"type":"Point"}
}