{
  "id": 2782872,
  "type": "Feature",
  "properties": {
    "tgn:hierarchy":[
        "tgn:2782872",
        "tgn:1000001",
        "tgn:2001840",
        "tgn:7012149",
        "tgn:7007825",
        "tgn:7029392"
    ],
    "tgn:id":2782872,
    "tgn:name":"Worthington Knob",
    "tgn:placetype":[
        "aat:300008798"
    ]
},
  "bbox": [],
  "geometry": {"coordinates":[-85.05,35.6833],"type":"Point"}
}