{
  "id": 2395637,
  "type": "Feature",
  "properties": {
    "tgn:hierarchy":[
        "tgn:2395637",
        "tgn:1000001",
        "tgn:7006451",
        "tgn:2000092",
        "tgn:7012149",
        "tgn:7029392"
    ],
    "tgn:id":2395637,
    "tgn:name":"Hollingshead Mountain",
    "tgn:placetype":[
        "aat:300008798"
    ]
},
  "bbox": [],
  "geometry": {"coordinates":[-111.4167,34.6333],"type":"Point"}
}