{
  "id": 2617635,
  "type": "Feature",
  "properties": {
    "tgn:hierarchy":[
        "tgn:2617635",
        "tgn:7002659",
        "tgn:1000001",
        "tgn:2000004",
        "tgn:7012149",
        "tgn:7029392"
    ],
    "tgn:id":2617635,
    "tgn:name":"Rickles Cave",
    "tgn:placetype":[
        "aat:300008746"
    ]
},
  "bbox": [],
  "geometry": {"coordinates":[-86.8333,33.8833],"type":"Point"}
}