{
  "id": 2265336,
  "type": "Feature",
  "properties": {
    "tgn:hierarchy":[
        "tgn:2265336",
        "tgn:1000001",
        "tgn:7012149",
        "tgn:2000488",
        "tgn:7007250",
        "tgn:7029392"
    ],
    "tgn:id":2265336,
    "tgn:name":"Crane Creek",
    "tgn:placetype":[
        "aat:300008706"
    ]
},
  "bbox": [],
  "geometry": {"coordinates":[-116.8333,43.1167],"type":"Point"}
}