{
  "id": 2222028,
  "type": "Feature",
  "properties": {
    "tgn:hierarchy":[
        "tgn:2222028",
        "tgn:1000001",
        "tgn:7012149",
        "tgn:2001284",
        "tgn:7007524",
        "tgn:7029392"
    ],
    "tgn:id":2222028,
    "tgn:name":"Carmichael Ditch",
    "tgn:placetype":[
        "aat:300006075"
    ]
},
  "bbox": [],
  "geometry": {"coordinates":[-112.3833,47.3667],"type":"Point"}
}