{
  "id": 2685572,
  "type": "Feature",
  "properties": {
    "tgn:hierarchy":[
        "tgn:2685572",
        "tgn:7014651",
        "tgn:1000001",
        "tgn:7012149",
        "tgn:7007516",
        "tgn:7029392"
    ],
    "tgn:id":2685572,
    "tgn:name":"Spriggs Pond",
    "tgn:placetype":[
        "aat:300008680"
    ]
},
  "bbox": [],
  "geometry": {"coordinates":[-76.4833,39.05],"type":"Point"}
}