{
  "id": 7416911,
  "type": "Feature",
  "properties": {
    "tgn:hierarchy":[
        "tgn:7416911",
        "tgn:1000001",
        "tgn:7005591",
        "tgn:7005560",
        "tgn:7029392"
    ],
    "tgn:id":7416911,
    "tgn:name:es":"San Bernardo",
    "tgn:placetype":[
        "aat:300008347"
    ]
},
  "bbox": [],
  "geometry": {"coordinates":[-96.434167,16.172778],"type":"Point"}
}