<<<<<<< HEAD
{
  "id": 2761493,
  "type": "Feature",
  "properties": {
    "tgn:hierarchy":[
        "tgn:2761493",
        "tgn:1000001",
        "tgn:7012149",
        "tgn:1002440",
        "tgn:7007568",
        "tgn:7029392"
    ],
    "tgn:id":2761493,
    "tgn:name":"West Notch Mountain",
    "tgn:placetype":[
        "aat:300008798"
    ]
},
  "bbox": [],
  "geometry": {"coordinates":[-74.6167,43.3333],"type":"Point"}
}
=======
{"geometry":{"type":"Point","coordinates":[-74.616700,43.333300]},"type":"Feature","properties":{"hierarchy":["tgn:2761493","tgn:1000001","tgn:7012149","tgn:1002440","tgn:7007568","tgn:7029392"],"placetype":["aat:300008798"],"id":2761493,"name:xx":"West Notch Mountain"}}
>>>>>>> 03f74aca74312dbeaf24d7e61306dd6a786dc3d0
