{
  "id": 2466585,
  "type": "Feature",
  "properties": {
    "tgn:hierarchy":[
        "tgn:2466585",
        "tgn:1000001",
        "tgn:7012149",
        "tgn:7007523",
        "tgn:7029392"
    ],
    "tgn:id":2466585,
    "tgn:name":"Long Branch",
    "tgn:placetype":[
        "aat:300008699"
    ]
},
  "bbox": [],
  "geometry": {"coordinates":[-93.8833,39.7667],"type":"Point"}
}