{
  "id": 2690114,
  "type": "Feature",
  "properties": {
    "tgn:hierarchy":[
        "tgn:2690114",
        "tgn:1000001",
        "tgn:2001474",
        "tgn:7012149",
        "tgn:7007709",
        "tgn:7029392"
    ],
    "tgn:id":2690114,
    "tgn:name":"Stacy Creek",
    "tgn:placetype":[
        "aat:300008706"
    ]
},
  "bbox": [],
  "geometry": {"coordinates":[-81.6667,35.65],"type":"Point"}
}