{
  "id": 7199285,
  "type": "Feature",
  "properties": {
    "tgn:hierarchy":[
        "tgn:7199285",
        "tgn:7003669",
        "tgn:1000003",
        "tgn:7000084",
        "tgn:7029392"
    ],
    "tgn:id":7199285,
    "tgn:name":"Egenhausen",
    "tgn:placetype":[
        "aat:300008347"
    ]
},
  "bbox": [],
  "geometry": {"coordinates":[10.466667,49.433333],"type":"Point"}
}