{
  "id": 2610612,
  "type": "Feature",
  "properties": {
    "tgn:hierarchy":[
        "tgn:2610612",
        "tgn:7006450",
        "tgn:1000001",
        "tgn:2124053",
        "tgn:7012149",
        "tgn:7029392"
    ],
    "tgn:id":2610612,
    "tgn:name":"Red Creek",
    "tgn:placetype":[
        "aat:300008706"
    ]
},
  "bbox": [],
  "geometry": {"coordinates":[-147.3667,62.2333],"type":"Point"}
}