{
  "id": 2333898,
  "type": "Feature",
  "properties": {
    "tgn:hierarchy":[
        "tgn:2333898",
        "tgn:1000001",
        "tgn:7012149",
        "tgn:1003022",
        "tgn:7007252",
        "tgn:7029392"
    ],
    "tgn:id":2333898,
    "tgn:name":"Ford Branch",
    "tgn:placetype":[
        "aat:300008699"
    ]
},
  "bbox": [],
  "geometry": {"coordinates":[-85.5833,41.1167],"type":"Point"}
}