{
  "id": 7573577,
  "type": "Feature",
  "properties": {
    "tgn:hierarchy":[
        "tgn:7573577",
        "tgn:1000004",
        "tgn:7000198",
        "tgn:1001895",
        "tgn:7029392"
    ],
    "tgn:id":7573577,
    "tgn:name:en":"Gurgaon",
    "tgn:placetype":[
        "aat:300008347"
    ]
},
  "bbox": [],
  "geometry": {"coordinates":[77.283333,19.333333],"type":"Point"}
}