{
  "id": 2761355,
  "type": "Feature",
  "properties": {
    "tgn:hierarchy":[
        "tgn:2761355",
        "tgn:1000001",
        "tgn:7012149",
        "tgn:2001718",
        "tgn:7007708",
        "tgn:7029392"
    ],
    "tgn:id":2761355,
    "tgn:name":"West Mine Reservoir",
    "tgn:placetype":[
        "aat:300006191"
    ]
},
  "bbox": [],
  "geometry": {"coordinates":[-118.05,42.0667],"type":"Point"}
}