{
  "id": 2003683,
  "type": "Feature",
  "properties": {
    "tgn:hierarchy":[
        "tgn:2003683",
        "tgn:7002659",
        "tgn:1000001",
        "tgn:7012149",
        "tgn:2000061",
        "tgn:7029392"
    ],
    "tgn:id":2003683,
    "tgn:name":"Goldville",
    "tgn:placetype":[
        "aat:300008347"
    ]
},
  "bbox": [],
  "geometry": {"coordinates":[-85.7833,33.0833],"type":"Point"}
}