{
  "id": 7575432,
  "type": "Feature",
  "properties": {
    "tgn:hierarchy":[
        "tgn:7575432",
        "tgn:1000004",
        "tgn:7000198",
        "tgn:7016722",
        "tgn:7029392"
    ],
    "tgn:id":7575432,
    "tgn:name:en":"Kol\u0101ri",
    "tgn:placetype":[
        "aat:300008347"
    ]
},
  "bbox": [],
  "geometry": {"coordinates":[77.814068,26.852908],"type":"Point"}
}