{
  "id": 1027353,
  "type": "Feature",
  "properties": {
    "tgn:hierarchy":[
        "tgn:1027353",
        "tgn:7027131",
        "tgn:1000003",
        "tgn:7011765",
        "tgn:7029392"
    ],
    "tgn:id":1027353,
    "tgn:name":"Lu\u010denec",
    "tgn:placetype":[
        "aat:300008347"
    ]
},
  "bbox": [],
  "geometry": {"coordinates":[19.6667,48.3333],"type":"Point"}
}