{
  "id": 7286055,
  "type": "Feature",
  "properties": {
    "tgn:hierarchy":[
        "tgn:7286055",
        "tgn:1001702",
        "tgn:1000049",
        "tgn:1000002",
        "tgn:7029392"
    ],
    "tgn:id":7286055,
    "tgn:name":"Estancia Kark",
    "tgn:placetype":[
        "aat:300000241"
    ]
},
  "bbox": [],
  "geometry": {"coordinates":[-72.45,-51.233333],"type":"Point"}
}