{
  "id": 2520695,
  "type": "Feature",
  "properties": {
    "tgn:hierarchy":[
        "tgn:2520695",
        "tgn:1000001",
        "tgn:7012149",
        "tgn:7029392"
    ],
    "tgn:id":2520695,
    "tgn:name":"Monocacy River",
    "tgn:placetype":[
        "aat:300008707"
    ]
},
  "bbox": [],
  "geometry": {"coordinates":[-77.2167,39.7167],"type":"Point"}
}