{
  "id": 2180872,
  "type": "Feature",
  "properties": {
    "tgn:hierarchy":[
        "tgn:2180872",
        "tgn:1000001",
        "tgn:7012149",
        "tgn:2001925",
        "tgn:7007825",
        "tgn:7029392"
    ],
    "tgn:id":2180872,
    "tgn:name":"Blowing Cave",
    "tgn:placetype":[
        "aat:300008746"
    ]
},
  "bbox": [],
  "geometry": {"coordinates":[-85.65,35.5667],"type":"Point"}
}