{
  "id": 2655187,
  "type": "Feature",
  "properties": {
    "tgn:hierarchy":[
        "tgn:2655187",
        "tgn:1000001",
        "tgn:7012149",
        "tgn:2002170",
        "tgn:7007919",
        "tgn:7029392"
    ],
    "tgn:id":2655187,
    "tgn:name":"Shannon Hills",
    "tgn:placetype":[
        "aat:300008347"
    ]
},
  "bbox": [],
  "geometry": {"coordinates":[-78.0167,37.8833],"type":"Point"}
}