{
  "id": 2264151,
  "type": "Feature",
  "properties": {
    "tgn:hierarchy":[
        "tgn:2264151",
        "tgn:1000001",
        "tgn:7012149",
        "tgn:2001277",
        "tgn:7007524",
        "tgn:7029392"
    ],
    "tgn:id":2264151,
    "tgn:name":"Coyote Springs",
    "tgn:placetype":[
        "aat:300008697"
    ]
},
  "bbox": [],
  "geometry": {"coordinates":[-112.4167,48.8167],"type":"Point"}
}