{
  "id": 1133290,
  "type": "Feature",
  "properties": {
    "tgn:hierarchy":[
        "tgn:1133290",
        "tgn:1001160",
        "tgn:7006477",
        "tgn:1000002",
        "tgn:7029392"
    ],
    "tgn:id":1133290,
    "tgn:name":"Gato, Arroyo del",
    "tgn:placetype":[
        "aat:300008706"
    ]
},
  "bbox": [],
  "geometry": {"coordinates":[-58.0167,-34.9333],"type":"Point"}
}