{
  "id": 2075781,
  "type": "Feature",
  "properties": {
    "tgn:hierarchy":[
        "tgn:2075781",
        "tgn:1000001",
        "tgn:7012149",
        "tgn:2001525",
        "tgn:7007709",
        "tgn:7029392"
    ],
    "tgn:id":2075781,
    "tgn:name":"Mountain View",
    "tgn:placetype":[
        "aat:300008347"
    ]
},
  "bbox": [],
  "geometry": {"coordinates":[-79.0667,36.0667],"type":"Point"}
}