{
  "id": 2712647,
  "type": "Feature",
  "properties": {
    "tgn:hierarchy":[
        "tgn:2712647",
        "tgn:1000001",
        "tgn:7012149",
        "tgn:2002119",
        "tgn:7007827",
        "tgn:7029392"
    ],
    "tgn:id":2712647,
    "tgn:name":"Taylor Canyon",
    "tgn:placetype":[
        "aat:300008761"
    ]
},
  "bbox": [],
  "geometry": {"coordinates":[-109.8167,38.4333],"type":"Point"}
}