{
  "id": 7550882,
  "type": "Feature",
  "properties": {
    "tgn:hierarchy":[
        "tgn:7550882",
        "tgn:1000004",
        "tgn:1001871",
        "tgn:7000198",
        "tgn:7029392"
    ],
    "tgn:id":7550882,
    "tgn:name:en":"Bithmara",
    "tgn:placetype":[
        "aat:300008347"
    ]
},
  "bbox": [],
  "geometry": {"coordinates":[75.92816,29.542253],"type":"Point"}
}