{
  "id": 7440982,
  "type": "Feature",
  "properties": {
    "tgn:hierarchy":[
        "tgn:7440982",
        "tgn:1000001",
        "tgn:7005592",
        "tgn:7005560",
        "tgn:7029392"
    ],
    "tgn:id":7440982,
    "tgn:name":"Santa Ana Coatepec",
    "tgn:placetype":[
        "aat:300008347"
    ]
},
  "bbox": [],
  "geometry": {"coordinates":[-98.416667,18.833333],"type":"Point"}
}