{
  "id": 2460627,
  "type": "Feature",
  "properties": {
    "tgn:hierarchy":[
        "tgn:2460627",
        "tgn:1000001",
        "tgn:7012149",
        "tgn:2002289",
        "tgn:7013961",
        "tgn:7029392"
    ],
    "tgn:id":2460627,
    "tgn:name":"Little Scary Creek",
    "tgn:placetype":[
        "aat:300008706"
    ]
},
  "bbox": [],
  "geometry": {"coordinates":[-81.8333,38.45],"type":"Point"}
}