{
  "id": 1029921,
  "type": "Feature",
  "properties": {
    "tgn:hierarchy":[
        "tgn:1029921",
        "tgn:7002445",
        "tgn:1000003",
        "tgn:7008153",
        "tgn:7008591",
        "tgn:7029392"
    ],
    "tgn:id":1029921,
    "tgn:name":"Luton",
    "tgn:placetype":[
        "aat:300008347"
    ]
},
  "bbox": [],
  "geometry": {"coordinates":[0.5333,51.3667],"type":"Point"}
}