{
  "id": 2190334,
  "type": "Feature",
  "properties": {
    "tgn:hierarchy":[
        "tgn:2190334",
        "tgn:1000001",
        "tgn:7012149",
        "tgn:2001453",
        "tgn:7007566",
        "tgn:7029392"
    ],
    "tgn:id":2190334,
    "tgn:name":"Box Canyon",
    "tgn:placetype":[
        "aat:300008761"
    ]
},
  "bbox": [],
  "geometry": {"coordinates":[-105.1667,35.5333],"type":"Point"}
}