{
  "id": 2720524,
  "type": "Feature",
  "properties": {
    "tgn:hierarchy":[
        "tgn:2720524",
        "tgn:1000001",
        "tgn:7012149",
        "tgn:1002999",
        "tgn:7007526",
        "tgn:7029392"
    ],
    "tgn:id":2720524,
    "tgn:name":"Thunderbolt Bay",
    "tgn:placetype":[
        "aat:300132316"
    ]
},
  "bbox": [],
  "geometry": {"coordinates":[-119.6833,40.0667],"type":"Point"}
}