<<<<<<< HEAD
{
  "id": 7022383,
  "type": "Feature",
  "properties": {
    "tgn:hierarchy":[
        "tgn:7022383",
        "tgn:1000001",
        "tgn:7012149",
        "tgn:7007825",
        "tgn:7029392"
    ],
    "tgn:id":7022383,
    "tgn:name":"Betty Hollow",
    "tgn:placetype":[
        "aat:300008761"
    ]
},
  "bbox": [],
  "geometry": {"coordinates":[-87.5833,35.95],"type":"Point"}
}
=======
{"geometry":{"type":"Point","coordinates":[-87.583300,35.950000]},"type":"Feature","properties":{"hierarchy":["tgn:7022383","tgn:1000001","tgn:7012149","tgn:7007825","tgn:7029392"],"placetype":["aat:300008761"],"id":7022383,"name:xx":"Betty Hollow"}}
>>>>>>> 03f74aca74312dbeaf24d7e61306dd6a786dc3d0
