{
  "id": 7276037,
  "type": "Feature",
  "properties": {
    "tgn:hierarchy":[
        "tgn:7276037",
        "tgn:1001702",
        "tgn:1000049",
        "tgn:1000002",
        "tgn:7029392"
    ],
    "tgn:id":7276037,
    "tgn:name":"Tito, Isla",
    "tgn:placetype":[
        "aat:300008791"
    ]
},
  "bbox": [],
  "geometry": {"coordinates":[-68.266667,-54.916667],"type":"Point"}
}