{
  "id": 2367387,
  "type": "Feature",
  "properties": {
    "tgn:hierarchy":[
        "tgn:2367387",
        "tgn:1000001",
        "tgn:7016172",
        "tgn:7012149",
        "tgn:2000143",
        "tgn:7029392"
    ],
    "tgn:id":2367387,
    "tgn:name":"Ground Lump Bar",
    "tgn:placetype":[
        "aat:300132348"
    ]
},
  "bbox": [],
  "geometry": {"coordinates":[-90.5667,34.7333],"type":"Point"}
}