<<<<<<< HEAD
{
  "id": 7117374,
  "type": "Feature",
  "properties": {
    "tgn:hierarchy":[
        "tgn:7117374",
        "tgn:7003692",
        "tgn:1000003",
        "tgn:7000084",
        "tgn:7029392"
    ],
    "tgn:id":7117374,
    "tgn:name":"Oedenbach",
    "tgn:placetype":[
        "aat:300008347"
    ]
},
  "bbox": [],
  "geometry": {"coordinates":[8.1,47.916667],"type":"Point"}
}
=======
{"geometry":{"type":"Point","coordinates":[8.100000,47.916667]},"type":"Feature","properties":{"hierarchy":["tgn:7117374","tgn:7003692","tgn:1000003","tgn:7000084","tgn:7029392"],"placetype":["aat:300008347"],"id":7117374,"name:xx":"Oedenbach"}}
>>>>>>> 03f74aca74312dbeaf24d7e61306dd6a786dc3d0
