{
  "id": 1033596,
  "type": "Feature",
  "properties": {
    "tgn:hierarchy":[
        "tgn:1033596",
        "tgn:1000003",
        "tgn:7002880",
        "tgn:1000070",
        "tgn:7029392"
    ],
    "tgn:id":1033596,
    "tgn:name":"La Besace",
    "tgn:placetype":[
        "aat:300008347"
    ]
},
  "bbox": [],
  "geometry": {"coordinates":[4.9667,49.5667],"type":"Point"}
}