{
  "id": 2015007,
  "type": "Feature",
  "properties": {
    "tgn:hierarchy":[
        "tgn:2015007",
        "tgn:1000001",
        "tgn:7012149",
        "tgn:7007157",
        "tgn:1002608",
        "tgn:7029392"
    ],
    "tgn:id":2015007,
    "tgn:name":"Windsor Hills",
    "tgn:placetype":[
        "aat:300008347"
    ]
},
  "bbox": [],
  "geometry": {"coordinates":[-118.35,33.9833],"type":"Point"}
}