{
  "id": 7580646,
  "type": "Feature",
  "properties": {
    "tgn:hierarchy":[
        "tgn:7580646",
        "tgn:1000004",
        "tgn:7000198",
        "tgn:7000799",
        "tgn:7029392"
    ],
    "tgn:id":7580646,
    "tgn:name:en":"Tiggur",
    "tgn:placetype":[
        "aat:300008347"
    ]
},
  "bbox": [],
  "geometry": {"coordinates":[77.619955,34.61863],"type":"Point"}
}