{
  "id": 2242807,
  "type": "Feature",
  "properties": {
    "tgn:hierarchy":[
        "tgn:2242807",
        "tgn:1000001",
        "tgn:7012149",
        "tgn:2002125",
        "tgn:7007827",
        "tgn:7029392"
    ],
    "tgn:id":2242807,
    "tgn:name":"Clear Creek",
    "tgn:placetype":[
        "aat:300008706"
    ]
},
  "bbox": [],
  "geometry": {"coordinates":[-111.2333,39.9167],"type":"Point"}
}