<<<<<<< HEAD
{
  "id": 7377721,
  "type": "Feature",
  "properties": {
    "tgn:hierarchy":[
        "tgn:7377721",
        "tgn:1001853",
        "tgn:1000001",
        "tgn:7005560",
        "tgn:7029392"
    ],
    "tgn:id":7377721,
    "tgn:name":"La Pita",
    "tgn:placetype":[
        "aat:300008347"
    ]
},
  "bbox": [],
  "geometry": {"coordinates":[-100.433333,28.016667],"type":"Point"}
}
=======
{"geometry":{"type":"Point","coordinates":[-100.433333,28.016667]},"type":"Feature","properties":{"hierarchy":["tgn:7377721","tgn:1001853","tgn:1000001","tgn:7005560","tgn:7029392"],"placetype":["aat:300008347"],"id":7377721,"name:xx":"La Pita"}}
>>>>>>> 03f74aca74312dbeaf24d7e61306dd6a786dc3d0
