{
  "id": 1069827,
  "type": "Feature",
  "properties": {
    "tgn:hierarchy":[
        "tgn:1069827",
        "tgn:1000004",
        "tgn:7002087",
        "tgn:1000111",
        "tgn:7029392"
    ],
    "tgn:id":1069827,
    "tgn:name":"Lijiatuo",
    "tgn:placetype":[
        "aat:300008347"
    ]
},
  "bbox": [],
  "geometry": {"coordinates":[106.55,29.4667],"type":"Point"}
}