{
  "id": 7467887,
  "type": "Feature",
  "properties": {
    "tgn:hierarchy":[
        "tgn:7467887",
        "tgn:1000004",
        "tgn:7491221",
        "tgn:1000141",
        "tgn:7029392"
    ],
    "tgn:id":7467887,
    "tgn:name":"Xiaogang Yugang",
    "tgn:placetype":[
        "aat:300008678"
    ]
},
  "bbox": [],
  "geometry": {"coordinates":[121.404209,23.158118],"type":"Point"}
}