{
  "id": 7071577,
  "type": "Feature",
  "properties": {
    "tgn:hierarchy":[
        "tgn:7071577",
        "tgn:1000003",
        "tgn:7003687",
        "tgn:7000084",
        "tgn:7029392"
    ],
    "tgn:id":7071577,
    "tgn:name":"S\u00fcppling",
    "tgn:placetype":[
        "aat:300055621"
    ]
},
  "bbox": [],
  "geometry": {"coordinates":[11.816667,52.466667],"type":"Point"}
}