{
  "id": 2644854,
  "type": "Feature",
  "properties": {
    "tgn:hierarchy":[
        "tgn:2644854",
        "tgn:1000001",
        "tgn:7012149",
        "tgn:2000435",
        "tgn:7007248",
        "tgn:7029392"
    ],
    "tgn:id":2644854,
    "tgn:name":"Sassafras Mountain",
    "tgn:placetype":[
        "aat:300008798"
    ]
},
  "bbox": [],
  "geometry": {"coordinates":[-84.0833,34.6333],"type":"Point"}
}