<<<<<<< HEAD
{
  "id": 2403257,
  "type": "Feature",
  "properties": {
    "tgn:hierarchy":[
        "tgn:2403257",
        "tgn:1000001",
        "tgn:7012149",
        "tgn:1002545",
        "tgn:7007157",
        "tgn:7029392"
    ],
    "tgn:id":2403257,
    "tgn:name":"House Spring",
    "tgn:placetype":[
        "aat:300008697"
    ]
},
  "bbox": [],
  "geometry": {"coordinates":[-118.6,35.3],"type":"Point"}
}
=======
{"geometry":{"type":"Point","coordinates":[-118.600000,35.300000]},"type":"Feature","properties":{"hierarchy":["tgn:2403257","tgn:1000001","tgn:7012149","tgn:1002545","tgn:7007157","tgn:7029392"],"placetype":["aat:300008697"],"id":2403257,"name:xx":"House Spring"}}
>>>>>>> 03f74aca74312dbeaf24d7e61306dd6a786dc3d0
