{
  "id": 7545599,
  "type": "Feature",
  "properties": {
    "tgn:hierarchy":[
        "tgn:7545599",
        "tgn:1000004",
        "tgn:7018318",
        "tgn:7000198",
        "tgn:7029392"
    ],
    "tgn:id":7545599,
    "tgn:name:en":"Ambeachi-Gavol",
    "tgn:placetype":[
        "aat:300008347"
    ]
},
  "bbox": [],
  "geometry": {"coordinates":[74.183333,15.633333],"type":"Point"}
}