{
  "id": 7566058,
  "type": "Feature",
  "properties": {
    "tgn:hierarchy":[
        "tgn:7566058",
        "tgn:1000004",
        "tgn:7000198",
        "tgn:1001894",
        "tgn:7029392"
    ],
    "tgn:id":7566058,
    "tgn:name:en":"Rampura",
    "tgn:placetype":[
        "aat:300008347"
    ]
},
  "bbox": [],
  "geometry": {"coordinates":[79.003402,24.61806],"type":"Point"}
}