{
  "id": 7306253,
  "type": "Feature",
  "properties": {
    "tgn:hierarchy":[
        "tgn:7306253",
        "tgn:7002836",
        "tgn:7016622",
        "tgn:1000003",
        "tgn:1000095",
        "tgn:7029392"
    ],
    "tgn:id":7306253,
    "tgn:name":"Malpique, Punta",
    "tgn:placetype":[
        "aat:300386846"
    ]
},
  "bbox": [],
  "geometry": {"coordinates":[-17.833333,28.45],"type":"Point"}
}