{
  "id": 2112440,
  "type": "Feature",
  "properties": {
    "tgn:hierarchy":[
        "tgn:2112440",
        "tgn:1000001",
        "tgn:7012149",
        "tgn:2002173",
        "tgn:7007919",
        "tgn:7029392"
    ],
    "tgn:id":2112440,
    "tgn:name":"Jeffress",
    "tgn:placetype":[
        "aat:300008347"
    ]
},
  "bbox": [],
  "geometry": {"coordinates":[-78.5333,36.65],"type":"Point"}
}