{
  "id": 2204237,
  "type": "Feature",
  "properties": {
    "tgn:hierarchy":[
        "tgn:2204237",
        "tgn:1000001",
        "tgn:7012149",
        "tgn:2001453",
        "tgn:7007566",
        "tgn:7029392"
    ],
    "tgn:id":2204237,
    "tgn:name":"Bueyeros Canyon",
    "tgn:placetype":[
        "aat:300008761"
    ]
},
  "bbox": [],
  "geometry": {"coordinates":[-103.9333,35.7167],"type":"Point"}
}