{
  "id": 2016314,
  "type": "Feature",
  "properties": {
    "tgn:hierarchy":[
        "tgn:2016314",
        "tgn:1000001",
        "tgn:7012149",
        "tgn:2000221",
        "tgn:7007158",
        "tgn:7029392"
    ],
    "tgn:id":2016314,
    "tgn:name":"Sky Village",
    "tgn:placetype":[
        "aat:300008347"
    ]
},
  "bbox": [],
  "geometry": {"coordinates":[-105.2333,39.55],"type":"Point"}
}