{
  "id": 2759660,
  "type": "Feature",
  "properties": {
    "tgn:hierarchy":[
        "tgn:2759660",
        "tgn:7006450",
        "tgn:1000001",
        "tgn:2124053",
        "tgn:7012149",
        "tgn:7029392"
    ],
    "tgn:id":2759660,
    "tgn:name":"West Fork Grubstake Gulch",
    "tgn:placetype":[
        "aat:300008761"
    ]
},
  "bbox": [],
  "geometry": {"coordinates":[-149.4167,61.7167],"type":"Point"}
}