<<<<<<< HEAD
{
  "id": 7115708,
  "type": "Feature",
  "properties": {
    "tgn:hierarchy":[
        "tgn:7115708",
        "tgn:1000003",
        "tgn:7003687",
        "tgn:7000084",
        "tgn:7029392"
    ],
    "tgn:id":7115708,
    "tgn:name":"Oster-Berg",
    "tgn:placetype":[
        "aat:300008777"
    ]
},
  "bbox": [],
  "geometry": {"coordinates":[11.7,51.533333],"type":"Point"}
}
=======
{"geometry":{"type":"Point","coordinates":[11.700000,51.533333]},"type":"Feature","properties":{"hierarchy":["tgn:7115708","tgn:1000003","tgn:7003687","tgn:7000084","tgn:7029392"],"placetype":["aat:300008777"],"id":7115708,"name:xx":"Oster-Berg"}}
>>>>>>> 03f74aca74312dbeaf24d7e61306dd6a786dc3d0
