<<<<<<< HEAD
{
  "id": 7364294,
  "type": "Feature",
  "properties": {
    "tgn:hierarchy":[
        "tgn:7364294",
        "tgn:1000001",
        "tgn:7005593",
        "tgn:7005560",
        "tgn:7029392"
    ],
    "tgn:id":7364294,
    "tgn:name":"El Blanco",
    "tgn:placetype":[
        "aat:300008347"
    ]
},
  "bbox": [],
  "geometry": {"coordinates":[-100.083333,20.633333],"type":"Point"}
}
=======
{"geometry":{"type":"Point","coordinates":[-100.083333,20.633333]},"type":"Feature","properties":{"hierarchy":["tgn:7364294","tgn:1000001","tgn:7005593","tgn:7005560","tgn:7029392"],"placetype":["aat:300008347"],"id":7364294,"name:xx":"El Blanco"}}
>>>>>>> 03f74aca74312dbeaf24d7e61306dd6a786dc3d0
