{
  "id": 7363921,
  "type": "Feature",
  "properties": {
    "tgn:hierarchy":[
        "tgn:7363921",
        "tgn:1001853",
        "tgn:1000001",
        "tgn:7005560",
        "tgn:7029392"
    ],
    "tgn:id":7363921,
    "tgn:name":"Rancho El Cho",
    "tgn:placetype":[
        "aat:300000241"
    ]
},
  "bbox": [],
  "geometry": {"coordinates":[-103.316667,27.183333],"type":"Point"}
}