{
  "id": 2236542,
  "type": "Feature",
  "properties": {
    "tgn:hierarchy":[
        "tgn:2236542",
        "tgn:7006450",
        "tgn:1000001",
        "tgn:7012149",
        "tgn:2000082",
        "tgn:7029392"
    ],
    "tgn:id":2236542,
    "tgn:name":"Chickwan Bight",
    "tgn:placetype":[
        "aat:300132316"
    ]
},
  "bbox": [],
  "geometry": {"coordinates":[-132.75,54.6667],"type":"Point"}
}