{
  "id": 2579265,
  "type": "Feature",
  "properties": {
    "tgn:hierarchy":[
        "tgn:2579265",
        "tgn:1000001",
        "tgn:2001009",
        "tgn:7012149",
        "tgn:7007521",
        "tgn:7029392"
    ],
    "tgn:id":2579265,
    "tgn:name":"Pick Lake",
    "tgn:placetype":[
        "aat:300008680"
    ]
},
  "bbox": [],
  "geometry": {"coordinates":[-94.3333,46.9333],"type":"Point"}
}