<<<<<<< HEAD
{
  "id": 7050336,
  "type": "Feature",
  "properties": {
    "tgn:hierarchy":[
        "tgn:7050336",
        "tgn:7003005",
        "tgn:7003014",
        "tgn:1000003",
        "tgn:1000080",
        "tgn:7029392"
    ],
    "tgn:id":7050336,
    "tgn:name":"Novi Velia",
    "tgn:placetype":[
        "aat:300008347"
    ]
},
  "bbox": [],
  "geometry": {"coordinates":[15.283333,40.233333],"type":"Point"}
}
=======
{"geometry":{"type":"Point","coordinates":[15.283333,40.233333]},"type":"Feature","properties":{"hierarchy":["tgn:7050336","tgn:7003005","tgn:7003014","tgn:1000003","tgn:1000080","tgn:7029392"],"placetype":["aat:300008347"],"id":7050336,"name:xx":"Novi Velia"}}
>>>>>>> 03f74aca74312dbeaf24d7e61306dd6a786dc3d0
