{
  "id": 2268709,
  "type": "Feature",
  "properties": {
    "tgn:hierarchy":[
        "tgn:2268709",
        "tgn:1000001",
        "tgn:7012149",
        "tgn:7007522",
        "tgn:7029392"
    ],
    "tgn:id":2268709,
    "tgn:name":"Cross Creek",
    "tgn:placetype":[
        "aat:300008706"
    ]
},
  "bbox": [],
  "geometry": {"coordinates":[-89.4333,31.3333],"type":"Point"}
}