{
  "id": 1085694,
  "type": "Feature",
  "properties": {
    "tgn:hierarchy":[
        "tgn:1085694",
        "tgn:7000923",
        "tgn:7005194",
        "tgn:1000004",
        "tgn:1000142",
        "tgn:7029392"
    ],
    "tgn:id":1085694,
    "tgn:name":"Sop Prap",
    "tgn:placetype":[
        "aat:300008347"
    ]
},
  "bbox": [],
  "geometry": {"coordinates":[99.3333,17.9167],"type":"Point"}
}