{
  "id": 2733767,
  "type": "Feature",
  "properties": {
    "tgn:hierarchy":[
        "tgn:2733767",
        "tgn:1000001",
        "tgn:7012149",
        "tgn:7007158",
        "tgn:2000248",
        "tgn:7029392"
    ],
    "tgn:id":2733767,
    "tgn:name":"Turner Creek",
    "tgn:placetype":[
        "aat:300008706"
    ]
},
  "bbox": [],
  "geometry": {"coordinates":[-108.15,37.9167],"type":"Point"}
}