{
  "id": 1054339,
  "type": "Feature",
  "properties": {
    "tgn:hierarchy":[
        "tgn:1054339",
        "tgn:1003353",
        "tgn:1000004",
        "tgn:7014786",
        "tgn:7029392"
    ],
    "tgn:id":1054339,
    "tgn:name":"Imeni \u010capajeva",
    "tgn:placetype":[
        "aat:300008347"
    ]
},
  "bbox": [],
  "geometry": {"coordinates":[76.8333,43.4667],"type":"Point"}
}