{
  "id": 2776955,
  "type": "Feature",
  "properties": {
    "tgn:hierarchy":[
        "tgn:2776955",
        "tgn:7006450",
        "tgn:1000001",
        "tgn:7030517",
        "tgn:7012149",
        "tgn:7029392"
    ],
    "tgn:id":2776955,
    "tgn:name":"Windy Creek",
    "tgn:placetype":[
        "aat:300008706"
    ]
},
  "bbox": [],
  "geometry": {"coordinates":[-155.3333,58.2333],"type":"Point"}
}