{
  "id": 2260706,
  "type": "Feature",
  "properties": {
    "tgn:hierarchy":[
        "tgn:2260706",
        "tgn:1000001",
        "tgn:7012149",
        "tgn:2001058",
        "tgn:7007521",
        "tgn:7029392"
    ],
    "tgn:id":2260706,
    "tgn:name":"County Ditch Number One Hundred Eight",
    "tgn:placetype":[
        "aat:300006075"
    ]
},
  "bbox": [],
  "geometry": {"coordinates":[-96.8333,47.7167],"type":"Point"}
}