{
  "id": 2374697,
  "type": "Feature",
  "properties": {
    "tgn:hierarchy":[
        "tgn:2374697",
        "tgn:1000001",
        "tgn:2001413",
        "tgn:7012149",
        "tgn:7007526",
        "tgn:7029392"
    ],
    "tgn:id":2374697,
    "tgn:name":"Hand-me-down Spring",
    "tgn:placetype":[
        "aat:300008697"
    ]
},
  "bbox": [],
  "geometry": {"coordinates":[-116.3833,40.2833],"type":"Point"}
}