{
  "id": 2334510,
  "type": "Feature",
  "properties": {
    "tgn:hierarchy":[
        "tgn:2334510",
        "tgn:1000001",
        "tgn:7012149",
        "tgn:2001038",
        "tgn:7007521",
        "tgn:7029392"
    ],
    "tgn:id":2334510,
    "tgn:name":"Forest Prairie Creek",
    "tgn:placetype":[
        "aat:300008706"
    ]
},
  "bbox": [],
  "geometry": {"coordinates":[-93.75,44.5333],"type":"Point"}
}