{
  "id": 7281703,
  "type": "Feature",
  "properties": {
    "tgn:hierarchy":[
        "tgn:7281703",
        "tgn:1001768",
        "tgn:1000049",
        "tgn:1000002",
        "tgn:7029392"
    ],
    "tgn:id":7281703,
    "tgn:name":"Seca, Quebrada",
    "tgn:placetype":[
        "aat:300008699"
    ]
},
  "bbox": [],
  "geometry": {"coordinates":[-71.216667,-32.45],"type":"Point"}
}