{
  "id": 7272210,
  "type": "Feature",
  "properties": {
    "tgn:concordances":{
        "gn:id":"2746597"
    },
    "tgn:hierarchy":[
        "tgn:7272210",
        "tgn:1000003",
        "tgn:7003624",
        "tgn:7016845",
        "tgn:7029392"
    ],
    "tgn:id":7272210,
    "tgn:name:nl":"Strikberg",
    "tgn:placetype":[
        "aat:300008347"
    ]
},
  "bbox": [],
  "geometry": {"coordinates":[4.783333,51.616667],"type":"Point"}
}