{
  "id": 7077021,
  "type": "Feature",
  "properties": {
    "tgn:hierarchy":[
        "tgn:7077021",
        "tgn:1000003",
        "tgn:7003684",
        "tgn:7000084",
        "tgn:7029392"
    ],
    "tgn:id":7077021,
    "tgn:name":"Bostalsee",
    "tgn:placetype":[
        "aat:300008680"
    ]
},
  "bbox": [],
  "geometry": {"coordinates":[7.066667,49.55],"type":"Point"}
}