{
  "id": 2616255,
  "type": "Feature",
  "properties": {
    "tgn:hierarchy":[
        "tgn:2616255",
        "tgn:1000001",
        "tgn:2002102",
        "tgn:7012149",
        "tgn:7007827",
        "tgn:7029392"
    ],
    "tgn:id":2616255,
    "tgn:name":"Rhyolite Butte",
    "tgn:placetype":[
        "aat:300008798"
    ]
},
  "bbox": [],
  "geometry": {"coordinates":[-114.0167,41.3167],"type":"Point"}
}