{
  "id": 2548708,
  "type": "Feature",
  "properties": {
    "tgn:hierarchy":[
        "tgn:2548708",
        "tgn:1000001",
        "tgn:7012149",
        "tgn:7007826",
        "tgn:7029392"
    ],
    "tgn:id":2548708,
    "tgn:name":"North Palo Duro Creek",
    "tgn:placetype":[
        "aat:300008706"
    ]
},
  "bbox": [],
  "geometry": {"coordinates":[-102.2833,35.2167],"type":"Point"}
}