{
  "id": 4006956,
  "type": "Feature",
  "properties": {
    "tgn:hierarchy":[
        "tgn:4006956",
        "tgn:1000003",
        "tgn:7002883",
        "tgn:1000070",
        "tgn:7029392"
    ],
    "tgn:id":4006956,
    "tgn:name":"Marne-la-Vall\u00e9e",
    "tgn:placetype":[
        "aat:300008347"
    ]
},
  "bbox": [],
  "geometry": {"coordinates":[2.65,48.8333],"type":"Point"}
}