<<<<<<< HEAD
{
  "id": 2257664,
  "type": "Feature",
  "properties": {
    "tgn:hierarchy":[
        "tgn:2257664",
        "tgn:1000001",
        "tgn:2001790",
        "tgn:7012149",
        "tgn:7007713",
        "tgn:7029392"
    ],
    "tgn:id":2257664,
    "tgn:name":"Corral Creek",
    "tgn:placetype":[
        "aat:300008706"
    ]
},
  "bbox": [],
  "geometry": {"coordinates":[-100.6667,44.95],"type":"Point"}
}
=======
{"geometry":{"type":"Point","coordinates":[-100.666700,44.950000]},"type":"Feature","properties":{"hierarchy":["tgn:2257664","tgn:1000001","tgn:2001790","tgn:7012149","tgn:7007713","tgn:7029392"],"placetype":["aat:300008706"],"id":2257664,"name:xx":"Corral Creek"}}
>>>>>>> 03f74aca74312dbeaf24d7e61306dd6a786dc3d0
