{
  "id": 2300002,
  "type": "Feature",
  "properties": {
    "tgn:hierarchy":[
        "tgn:2300002",
        "tgn:1000001",
        "tgn:7012149",
        "tgn:1002990",
        "tgn:7007708",
        "tgn:7029392"
    ],
    "tgn:id":2300002,
    "tgn:name":"Dufur Orchards Reservoir",
    "tgn:placetype":[
        "aat:300006191"
    ]
},
  "bbox": [],
  "geometry": {"coordinates":[-121.2167,45.4833],"type":"Point"}
}