<<<<<<< HEAD
{
  "id": 7485504,
  "type": "Feature",
  "properties": {
    "tgn:hierarchy":[
        "tgn:7485504",
        "tgn:7488858",
        "tgn:1000004",
        "tgn:1000141",
        "tgn:7029392"
    ],
    "tgn:id":7485504,
    "tgn:name":"Kandi",
    "tgn:placetype":[
        "aat:300008347"
    ]
},
  "bbox": [],
  "geometry": {"coordinates":[120.746389,23.738889],"type":"Point"}
}
=======
{"geometry":{"type":"Point","coordinates":[120.746389,23.738889]},"type":"Feature","properties":{"hierarchy":["tgn:7485504","tgn:7488858","tgn:1000004","tgn:1000141","tgn:7029392"],"placetype":["aat:300008347"],"id":7485504,"name:xx":"Kandi"}}
>>>>>>> 03f74aca74312dbeaf24d7e61306dd6a786dc3d0
