{
  "id": 4002654,
  "type": "Feature",
  "properties": {
    "tgn:hierarchy":[
        "tgn:4002654",
        "tgn:7002445",
        "tgn:1000003",
        "tgn:7008174",
        "tgn:7008591",
        "tgn:7029392"
    ],
    "tgn:id":4002654,
    "tgn:name:en":"Church Eaton",
    "tgn:placetype":[
        "aat:300008347"
    ]
},
  "bbox": [],
  "geometry": {"coordinates":[-2.233333,52.75],"type":"Point"}
}