{
  "id": 2161162,
  "type": "Feature",
  "properties": {
    "tgn:hierarchy":[
        "tgn:2161162",
        "tgn:1000001",
        "tgn:7012149",
        "tgn:2000206",
        "tgn:7007158",
        "tgn:7029392"
    ],
    "tgn:id":2161162,
    "tgn:name":"Bell Creek Springs",
    "tgn:placetype":[
        "aat:300008697"
    ]
},
  "bbox": [],
  "geometry": {"coordinates":[-107.55,38.7833],"type":"Point"}
}