{
  "id": 2568523,
  "type": "Feature",
  "properties": {
    "tgn:hierarchy":[
        "tgn:2568523",
        "tgn:1000001",
        "tgn:7012149",
        "tgn:2000927",
        "tgn:7007515",
        "tgn:7029392"
    ],
    "tgn:id":2568523,
    "tgn:name":"Park Pond",
    "tgn:placetype":[
        "aat:300008680"
    ]
},
  "bbox": [],
  "geometry": {"coordinates":[-68.2833,45.35],"type":"Point"}
}