{
  "id": 2235159,
  "type": "Feature",
  "properties": {
    "tgn:hierarchy":[
        "tgn:2235159",
        "tgn:1000001",
        "tgn:7006451",
        "tgn:2000093",
        "tgn:7012149",
        "tgn:7029392"
    ],
    "tgn:id":2235159,
    "tgn:name":"Cherry Spring",
    "tgn:placetype":[
        "aat:300008697"
    ]
},
  "bbox": [],
  "geometry": {"coordinates":[-110.95,33.4333],"type":"Point"}
}