{
  "id": 7120231,
  "type": "Feature",
  "properties": {
    "tgn:hierarchy":[
        "tgn:7120231",
        "tgn:1000003",
        "tgn:7003682",
        "tgn:7000084",
        "tgn:7029392"
    ],
    "tgn:id":7120231,
    "tgn:name":"Pleisweiler",
    "tgn:placetype":[
        "aat:300000745"
    ]
},
  "bbox": [],
  "geometry": {"coordinates":[8.003611,49.116111],"type":"Point"}
}