{
  "id": 1056292,
  "type": "Feature",
  "properties": {
    "tgn:hierarchy":[
        "tgn:1056292",
        "tgn:1003357",
        "tgn:1000003",
        "tgn:7006657",
        "tgn:7029392"
    ],
    "tgn:id":1056292,
    "tgn:name":"Lachva",
    "tgn:placetype":[
        "aat:300008347"
    ]
},
  "bbox": [],
  "geometry": {"coordinates":[27.0667,52.2167],"type":"Point"}
}