<<<<<<< HEAD
{
  "id": 2332516,
  "type": "Feature",
  "properties": {
    "tgn:hierarchy":[
        "tgn:2332516",
        "tgn:1000001",
        "tgn:7012149",
        "tgn:1002793",
        "tgn:7007240",
        "tgn:7029392"
    ],
    "tgn:id":2332516,
    "tgn:name":"Florence, Lake",
    "tgn:placetype":[
        "aat:300008680"
    ]
},
  "bbox": [],
  "geometry": {"coordinates":[-81.6833,28.0],"type":"Point"}
}
=======
{"geometry":{"type":"Point","coordinates":[-81.683300,28.000000]},"type":"Feature","properties":{"hierarchy":["tgn:2332516","tgn:1000001","tgn:7012149","tgn:1002793","tgn:7007240","tgn:7029392"],"placetype":["aat:300008680"],"id":2332516,"name:xx":"Florence, Lake"}}
>>>>>>> 03f74aca74312dbeaf24d7e61306dd6a786dc3d0
