{
  "id": 7361097,
  "type": "Feature",
  "properties": {
    "tgn:hierarchy":[
        "tgn:7361097",
        "tgn:1000001",
        "tgn:7005599",
        "tgn:7005560",
        "tgn:7029392"
    ],
    "tgn:id":7361097,
    "tgn:name":"El Huizotate",
    "tgn:placetype":[
        "aat:300008347"
    ]
},
  "bbox": [],
  "geometry": {"coordinates":[-97.65,20.75],"type":"Point"}
}