{
  "id": 2160275,
  "type": "Feature",
  "properties": {
    "tgn:hierarchy":[
        "tgn:2160275",
        "tgn:1000001",
        "tgn:2000863",
        "tgn:7012149",
        "tgn:7007256",
        "tgn:7029392"
    ],
    "tgn:id":2160275,
    "tgn:name":"Beef Ridge",
    "tgn:placetype":[
        "aat:300266640"
    ]
},
  "bbox": [],
  "geometry": {"coordinates":[-93.6667,30.1833],"type":"Point"}
}