<<<<<<< HEAD
{
  "id": 7027243,
  "type": "Feature",
  "properties": {
    "tgn:hierarchy":[
        "tgn:7027243",
        "tgn:7002445",
        "tgn:1000003",
        "tgn:7008145",
        "tgn:7008591",
        "tgn:7029392"
    ],
    "tgn:id":7027243,
    "tgn:name:en":"Norton",
    "tgn:placetype":[
        "aat:300008347",
        "aat:300008372"
    ]
},
  "bbox": [],
  "geometry": {"coordinates":[-0.216667,51.983333],"type":"Point"}
}
=======
{"geometry":{"type":"Point","coordinates":[-0.216667,51.983333]},"type":"Feature","properties":{"hierarchy":["tgn:7027243","tgn:7002445","tgn:1000003","tgn:7008145","tgn:7008591","tgn:7029392"],"placetype":["aat:300008347","aat:300008372"],"name:en":"Norton","id":7027243}}
>>>>>>> 03f74aca74312dbeaf24d7e61306dd6a786dc3d0
