{
  "id": 7303716,
  "type": "Feature",
  "properties": {
    "tgn:hierarchy":[
        "tgn:7303716",
        "tgn:7002825",
        "tgn:7016622",
        "tgn:1000003",
        "tgn:1000095",
        "tgn:7029392"
    ],
    "tgn:id":7303716,
    "tgn:name":"Morro del Jable",
    "tgn:placetype":[
        "aat:300008347"
    ]
},
  "bbox": [],
  "geometry": {"coordinates":[-14.333333,28.05],"type":"Point"}
}