{
  "id": 7346562,
  "type": "Feature",
  "properties": {
    "tgn:hierarchy":[
        "tgn:7346562",
        "tgn:7002844",
        "tgn:7030216",
        "tgn:1000003",
        "tgn:1000095",
        "tgn:7029392"
    ],
    "tgn:id":7346562,
    "tgn:name":"Avellanar, Barranco del",
    "tgn:placetype":[
        "aat:300266554",
        "aat:300008699"
    ]
},
  "bbox": [],
  "geometry": {"coordinates":[0.316667,40.933333],"type":"Point"}
}