{
  "id": 7573205,
  "type": "Feature",
  "properties": {
    "tgn:hierarchy":[
        "tgn:7573205",
        "tgn:1000004",
        "tgn:7000198",
        "tgn:7031786",
        "tgn:7029392"
    ],
    "tgn:id":7573205,
    "tgn:name:en":"Joshiana",
    "tgn:placetype":[
        "aat:300008347"
    ]
},
  "bbox": [],
  "geometry": {"coordinates":[78.782162,30.077595],"type":"Point"}
}