<<<<<<< HEAD
{
  "id": 2338422,
  "type": "Feature",
  "properties": {
    "tgn:hierarchy":[
        "tgn:2338422",
        "tgn:1000001",
        "tgn:1003023",
        "tgn:7012149",
        "tgn:7007516",
        "tgn:7029392"
    ],
    "tgn:id":2338422,
    "tgn:name":"Foxwood",
    "tgn:placetype":[
        "aat:300008347"
    ]
},
  "bbox": [],
  "geometry": {"coordinates":[-75.5833,38.4333],"type":"Point"}
}
=======
{"geometry":{"type":"Point","coordinates":[-75.583300,38.433300]},"type":"Feature","properties":{"hierarchy":["tgn:2338422","tgn:1000001","tgn:1003023","tgn:7012149","tgn:7007516","tgn:7029392"],"placetype":["aat:300008347"],"id":2338422,"name:xx":"Foxwood"}}
>>>>>>> 03f74aca74312dbeaf24d7e61306dd6a786dc3d0
