{
  "id": 2678454,
  "type": "Feature",
  "properties": {
    "tgn:hierarchy":[
        "tgn:2678454",
        "tgn:1000001",
        "tgn:7012149",
        "tgn:2000181",
        "tgn:7007157",
        "tgn:7029392"
    ],
    "tgn:id":2678454,
    "tgn:name":"South Fork Conley Creek",
    "tgn:placetype":[
        "aat:300008706"
    ]
},
  "bbox": [],
  "geometry": {"coordinates":[-123.5667,40.2833],"type":"Point"}
}