<<<<<<< HEAD
{
  "id": 2763623,
  "type": "Feature",
  "properties": {
    "tgn:hierarchy":[
        "tgn:2763623",
        "tgn:1002996",
        "tgn:1000001",
        "tgn:7012149",
        "tgn:7007711",
        "tgn:7029392"
    ],
    "tgn:id":2763623,
    "tgn:name":"Whaleboat Point",
    "tgn:placetype":[
        "aat:300008850"
    ]
},
  "bbox": [],
  "geometry": {"coordinates":[-71.5333,41.3833],"type":"Point"}
}
=======
{"geometry":{"type":"Point","coordinates":[-71.533300,41.383300]},"type":"Feature","properties":{"hierarchy":["tgn:2763623","tgn:1002996","tgn:1000001","tgn:7012149","tgn:7007711","tgn:7029392"],"placetype":["aat:300008850"],"id":2763623,"name:xx":"Whaleboat Point"}}
>>>>>>> 03f74aca74312dbeaf24d7e61306dd6a786dc3d0
