{
  "id": 2285291,
  "type": "Feature",
  "properties": {
    "tgn:hierarchy":[
        "tgn:2285291",
        "tgn:1000001",
        "tgn:7012149",
        "tgn:2001273",
        "tgn:7007524",
        "tgn:7029392"
    ],
    "tgn:id":2285291,
    "tgn:name":"Devils Canyon Number 1 Mine",
    "tgn:placetype":[
        "aat:300000390"
    ]
},
  "bbox": [],
  "geometry": {"coordinates":[-109.2833,47.1667],"type":"Point"}
}