{
  "id": 7566509,
  "type": "Feature",
  "properties": {
    "tgn:hierarchy":[
        "tgn:7566509",
        "tgn:1000004",
        "tgn:7000198",
        "tgn:1001894",
        "tgn:7029392"
    ],
    "tgn:id":7566509,
    "tgn:name:en":"Madn\u012bw\u0101r",
    "tgn:placetype":[
        "aat:300008347"
    ]
},
  "bbox": [],
  "geometry": {"coordinates":[79.217466,24.501765],"type":"Point"}
}