{
  "id": 2639093,
  "type": "Feature",
  "properties": {
    "tgn:hierarchy":[
        "tgn:2639093",
        "tgn:1000001",
        "tgn:7012149",
        "tgn:2002041",
        "tgn:7007826",
        "tgn:7029392"
    ],
    "tgn:id":2639093,
    "tgn:name":"Salt Lake",
    "tgn:placetype":[
        "aat:300008680"
    ]
},
  "bbox": [],
  "geometry": {"coordinates":[-101.9833,31.85],"type":"Point"}
}