{
  "id": 7468978,
  "type": "Feature",
  "properties": {
    "tgn:hierarchy":[
        "tgn:7468978",
        "tgn:1000004",
        "tgn:1000454",
        "tgn:1000141",
        "tgn:7029392"
    ],
    "tgn:id":7468978,
    "tgn:name":"Kanding Li",
    "tgn:placetype":[
        "aat:300387173"
    ]
},
  "bbox": [],
  "geometry": {"coordinates":[121.4317,25.1984],"type":"Point"}
}