{
  "id": 7403600,
  "type": "Feature",
  "properties": {
    "tgn:hierarchy":[
        "tgn:7403600",
        "tgn:1000001",
        "tgn:1001906",
        "tgn:7005560",
        "tgn:7029392"
    ],
    "tgn:id":7403600,
    "tgn:name":"Acatit\u00e1n",
    "tgn:placetype":[
        "aat:300008347"
    ]
},
  "bbox": [],
  "geometry": {"coordinates":[-104.641667,21.308333],"type":"Point"}
}