<<<<<<< HEAD
{
  "id": 2338149,
  "type": "Feature",
  "properties": {
    "tgn:hierarchy":[
        "tgn:2338149",
        "tgn:1000001",
        "tgn:2000458",
        "tgn:7012149",
        "tgn:7007250",
        "tgn:7029392"
    ],
    "tgn:id":2338149,
    "tgn:name":"Fox Peak",
    "tgn:placetype":[
        "aat:300008798"
    ]
},
  "bbox": [],
  "geometry": {"coordinates":[-114.5,43.7167],"type":"Point"}
}
=======
{"geometry":{"type":"Point","coordinates":[-114.500000,43.716700]},"type":"Feature","properties":{"hierarchy":["tgn:2338149","tgn:1000001","tgn:2000458","tgn:7012149","tgn:7007250","tgn:7029392"],"placetype":["aat:300008798"],"id":2338149,"name:xx":"Fox Peak"}}
>>>>>>> 03f74aca74312dbeaf24d7e61306dd6a786dc3d0
