{
  "id": 2592987,
  "type": "Feature",
  "properties": {
    "tgn:hierarchy":[
        "tgn:2592987",
        "tgn:1000001",
        "tgn:7012149",
        "tgn:2001544",
        "tgn:7007709",
        "tgn:7029392"
    ],
    "tgn:id":2592987,
    "tgn:name":"Poplar Creek",
    "tgn:placetype":[
        "aat:300008706"
    ]
},
  "bbox": [],
  "geometry": {"coordinates":[-82.7667,35.3833],"type":"Point"}
}