{
  "id": 7462592,
  "type": "Feature",
  "properties": {
    "tgn:hierarchy":[
        "tgn:7462592",
        "tgn:7002444",
        "tgn:7008074",
        "tgn:1000003",
        "tgn:7008591",
        "tgn:7029392"
    ],
    "tgn:id":7462592,
    "tgn:name:en":"Kirkgunzeon Lane",
    "tgn:placetype":[
        "aat:300008699"
    ]
},
  "bbox": [],
  "geometry": {"coordinates":[-3.833333,54.916667],"type":"Point"}
}