{
  "id": 2615958,
  "type": "Feature",
  "properties": {
    "tgn:hierarchy":[
        "tgn:2615958",
        "tgn:1000001",
        "tgn:7012149",
        "tgn:1002697",
        "tgn:7007706",
        "tgn:7029392"
    ],
    "tgn:id":2615958,
    "tgn:name":"Reynolds Run",
    "tgn:placetype":[
        "aat:300008699"
    ]
},
  "bbox": [],
  "geometry": {"coordinates":[-82.7167,40.3667],"type":"Point"}
}