<<<<<<< HEAD
{
  "id": 7368843,
  "type": "Feature",
  "properties": {
    "tgn:hierarchy":[
        "tgn:7368843",
        "tgn:1000001",
        "tgn:1001960",
        "tgn:7005560",
        "tgn:7029392"
    ],
    "tgn:id":7368843,
    "tgn:name":"Hilitaco",
    "tgn:placetype":[
        "aat:300008347"
    ]
},
  "bbox": [],
  "geometry": {"coordinates":[-110.566667,27.9],"type":"Point"}
}
=======
{"geometry":{"type":"Point","coordinates":[-110.566667,27.900000]},"type":"Feature","properties":{"hierarchy":["tgn:7368843","tgn:1000001","tgn:1001960","tgn:7005560","tgn:7029392"],"placetype":["aat:300008347"],"id":7368843,"name:xx":"Hilitaco"}}
>>>>>>> 03f74aca74312dbeaf24d7e61306dd6a786dc3d0
