{
  "id": 7589508,
  "type": "Feature",
  "properties": {
    "tgn:hierarchy":[
        "tgn:7589508",
        "tgn:1000004",
        "tgn:7000198",
        "tgn:7000799",
        "tgn:7029392"
    ],
    "tgn:id":7589508,
    "tgn:name:en":"Kandholi",
    "tgn:placetype":[
        "aat:300008347"
    ]
},
  "bbox": [],
  "geometry": {"coordinates":[74.916541,32.798108],"type":"Point"}
}