{
  "id": 7562801,
  "type": "Feature",
  "properties": {
    "tgn:hierarchy":[
        "tgn:7562801",
        "tgn:1000004",
        "tgn:7000198",
        "tgn:7016722",
        "tgn:7029392"
    ],
    "tgn:id":7562801,
    "tgn:name:en":"Kandholi",
    "tgn:placetype":[
        "aat:300008347"
    ]
},
  "bbox": [],
  "geometry": {"coordinates":[79.206764,26.438281],"type":"Point"}
}