{
  "id": 7265040,
  "type": "Feature",
  "properties": {
    "tgn:hierarchy":[
        "tgn:7265040",
        "tgn:1000003",
        "tgn:7003613",
        "tgn:7016845",
        "tgn:7029392"
    ],
    "tgn:id":7265040,
    "tgn:name:nl":"Loosterveen",
    "tgn:placetype":[
        "aat:300387200"
    ]
},
  "bbox": [],
  "geometry": {"coordinates":[7.166667,53.066667],"type":"Point"}
}