{
  "id": 2587223,
  "type": "Feature",
  "properties": {
    "tgn:hierarchy":[
        "tgn:2587223",
        "tgn:1000001",
        "tgn:7006451",
        "tgn:2000092",
        "tgn:7012149",
        "tgn:7029392"
    ],
    "tgn:id":2587223,
    "tgn:name":"Platten Tank",
    "tgn:placetype":[
        "aat:300006191"
    ]
},
  "bbox": [],
  "geometry": {"coordinates":[-111.9667,35.55],"type":"Point"}
}