<<<<<<< HEAD
{
  "id": 2154928,
  "type": "Feature",
  "properties": {
    "tgn:hierarchy":[
        "tgn:2154928",
        "tgn:1000001",
        "tgn:7012149",
        "tgn:2001711",
        "tgn:7007708",
        "tgn:7029392"
    ],
    "tgn:id":2154928,
    "tgn:name":"Bear Hunt Gulch",
    "tgn:placetype":[
        "aat:300008761"
    ]
},
  "bbox": [],
  "geometry": {"coordinates":[-122.9333,42.1333],"type":"Point"}
}
=======
{"geometry":{"type":"Point","coordinates":[-122.933300,42.133300]},"type":"Feature","properties":{"hierarchy":["tgn:2154928","tgn:1000001","tgn:7012149","tgn:2001711","tgn:7007708","tgn:7029392"],"placetype":["aat:300008761"],"id":2154928,"name:xx":"Bear Hunt Gulch"}}
>>>>>>> 03f74aca74312dbeaf24d7e61306dd6a786dc3d0
