{
  "id": 2263749,
  "type": "Feature",
  "properties": {
    "tgn:hierarchy":[
        "tgn:2263749",
        "tgn:7006450",
        "tgn:1000001",
        "tgn:7012149",
        "tgn:2000079",
        "tgn:7029392"
    ],
    "tgn:id":2263749,
    "tgn:name":"Coyote Creek",
    "tgn:placetype":[
        "aat:300008706"
    ]
},
  "bbox": [],
  "geometry": {"coordinates":[-166.2667,65.1833],"type":"Point"}
}