{
  "id": 7349972,
  "type": "Feature",
  "properties": {
    "tgn:hierarchy":[
        "tgn:7349972",
        "tgn:1000001",
        "tgn:7005592",
        "tgn:7005560",
        "tgn:7029392"
    ],
    "tgn:id":7349972,
    "tgn:name":"Acuaca, R\u00edo",
    "tgn:placetype":[
        "aat:300008699"
    ]
},
  "bbox": [],
  "geometry": {"coordinates":[-97.566667,19.766667],"type":"Point"}
}