{
  "id": 2283150,
  "type": "Feature",
  "properties": {
    "tgn:hierarchy":[
        "tgn:2283150",
        "tgn:1000001",
        "tgn:2001411",
        "tgn:7012149",
        "tgn:7007526",
        "tgn:7029392"
    ],
    "tgn:id":2283150,
    "tgn:name":"Delano Peak",
    "tgn:placetype":[
        "aat:300008798"
    ]
},
  "bbox": [],
  "geometry": {"coordinates":[-114.25,41.6167],"type":"Point"}
}