<<<<<<< HEAD
{
  "id": 7482163,
  "type": "Feature",
  "properties": {
    "tgn:hierarchy":[
        "tgn:7482163",
        "tgn:1000004",
        "tgn:7490934",
        "tgn:1000141",
        "tgn:7029392"
    ],
    "tgn:id":7482163,
    "tgn:name":"Lingzhao Gong",
    "tgn:placetype":[
        "aat:300007595"
    ]
},
  "bbox": [],
  "geometry": {"coordinates":[120.311058,23.10148],"type":"Point"}
}
=======
{"geometry":{"type":"Point","coordinates":[120.311058,23.101480]},"type":"Feature","properties":{"hierarchy":["tgn:7482163","tgn:1000004","tgn:7490934","tgn:1000141","tgn:7029392"],"placetype":["aat:300007595"],"id":7482163,"name:xx":"Lingzhao Gong"}}
>>>>>>> 03f74aca74312dbeaf24d7e61306dd6a786dc3d0
