<<<<<<< HEAD
{
  "id": 2704717,
  "type": "Feature",
  "properties": {
    "tgn:hierarchy":[
        "tgn:2704717",
        "tgn:1000001",
        "tgn:7012149",
        "tgn:2001931",
        "tgn:7007825",
        "tgn:7029392"
    ],
    "tgn:id":2704717,
    "tgn:name":"Sunset Creek",
    "tgn:placetype":[
        "aat:300008706"
    ]
},
  "bbox": [],
  "geometry": {"coordinates":[-86.1667,36.0],"type":"Point"}
}
=======
{"geometry":{"type":"Point","coordinates":[-86.166700,36.000000]},"type":"Feature","properties":{"hierarchy":["tgn:2704717","tgn:1000001","tgn:7012149","tgn:2001931","tgn:7007825","tgn:7029392"],"placetype":["aat:300008706"],"id":2704717,"name:xx":"Sunset Creek"}}
>>>>>>> 03f74aca74312dbeaf24d7e61306dd6a786dc3d0
