{
  "id": 7092958,
  "type": "Feature",
  "properties": {
    "tgn:hierarchy":[
        "tgn:7092958",
        "tgn:1000003",
        "tgn:7003682",
        "tgn:7000084",
        "tgn:7029392"
    ],
    "tgn:id":7092958,
    "tgn:name":"Schweis Berg",
    "tgn:placetype":[
        "aat:300008777"
    ]
},
  "bbox": [],
  "geometry": {"coordinates":[7.316667,49.566667],"type":"Point"}
}