{
  "id": 2304658,
  "type": "Feature",
  "properties": {
    "tgn:hierarchy":[
        "tgn:2304658",
        "tgn:1000001",
        "tgn:7012149",
        "tgn:7007158",
        "tgn:2000246",
        "tgn:7029392"
    ],
    "tgn:id":2304658,
    "tgn:name":"East Beaver Creek",
    "tgn:placetype":[
        "aat:300008706"
    ]
},
  "bbox": [],
  "geometry": {"coordinates":[-106.85,38.2667],"type":"Point"}
}