{
  "id": 2596399,
  "type": "Feature",
  "properties": {
    "tgn:hierarchy":[
        "tgn:2596399",
        "tgn:1000001",
        "tgn:7012149",
        "tgn:1002944",
        "tgn:7007568",
        "tgn:7029392"
    ],
    "tgn:id":2596399,
    "tgn:name":"Poverty Knob",
    "tgn:placetype":[
        "aat:300008798"
    ]
},
  "bbox": [],
  "geometry": {"coordinates":[-76.3833,42.0833],"type":"Point"}
}