{
  "id": 7472240,
  "type": "Feature",
  "properties": {
    "tgn:hierarchy":[
        "tgn:7472240",
        "tgn:7001010",
        "tgn:1000004",
        "tgn:1000141",
        "tgn:7029392"
    ],
    "tgn:id":7472240,
    "tgn:name":"Caogu'an Shan",
    "tgn:placetype":[
        "aat:300008798"
    ]
},
  "bbox": [],
  "geometry": {"coordinates":[121.303891,23.489089],"type":"Point"}
}