<<<<<<< HEAD
{
  "id": 7472240,
  "type": "Feature",
  "properties": {
    "tgn:hierarchy":[
        "tgn:7472240",
        "tgn:7001010",
        "tgn:1000004",
        "tgn:1000141",
        "tgn:7029392"
    ],
    "tgn:id":7472240,
    "tgn:name":"Caogu'an Shan",
    "tgn:placetype":[
        "aat:300008798"
    ]
},
  "bbox": [],
  "geometry": {"coordinates":[121.303891,23.489089],"type":"Point"}
}
=======
{"geometry":{"type":"Point","coordinates":[121.303891,23.489089]},"type":"Feature","properties":{"hierarchy":["tgn:7472240","tgn:7001010","tgn:1000004","tgn:1000141","tgn:7029392"],"placetype":["aat:300008798"],"id":7472240,"name:xx":"Caogu'an Shan"}}
>>>>>>> 03f74aca74312dbeaf24d7e61306dd6a786dc3d0
