<<<<<<< HEAD
{
  "id": 2769891,
  "type": "Feature",
  "properties": {
    "tgn:hierarchy":[
        "tgn:2769891",
        "tgn:1000001",
        "tgn:7012149",
        "tgn:2002252",
        "tgn:7007920",
        "tgn:7029392"
    ],
    "tgn:id":2769891,
    "tgn:name":"Wilbur Creek",
    "tgn:placetype":[
        "aat:300008706"
    ]
},
  "bbox": [],
  "geometry": {"coordinates":[-117.2,46.6667],"type":"Point"}
}
=======
{"geometry":{"type":"Point","coordinates":[-117.200000,46.666700]},"type":"Feature","properties":{"hierarchy":["tgn:2769891","tgn:1000001","tgn:7012149","tgn:2002252","tgn:7007920","tgn:7029392"],"placetype":["aat:300008706"],"id":2769891,"name:xx":"Wilbur Creek"}}
>>>>>>> 03f74aca74312dbeaf24d7e61306dd6a786dc3d0
