{
  "id": 7244366,
  "type": "Feature",
  "properties": {
    "tgn:hierarchy":[
        "tgn:7244366",
        "tgn:7003457",
        "tgn:1000003",
        "tgn:1000063",
        "tgn:7018236",
        "tgn:7029392"
    ],
    "tgn:id":7244366,
    "tgn:name":"Kerksken",
    "tgn:placetype":[
        "aat:300008347"
    ]
},
  "bbox": [],
  "geometry": {"coordinates":[3.994783,50.890682],"type":"Point"}
}