<<<<<<< HEAD
{
  "id": 2409977,
  "type": "Feature",
  "properties": {
    "tgn:hierarchy":[
        "tgn:2409977",
        "tgn:2002101",
        "tgn:1000001",
        "tgn:7012149",
        "tgn:7007827",
        "tgn:7029392"
    ],
    "tgn:id":2409977,
    "tgn:name":"Imperial Mine",
    "tgn:placetype":[
        "aat:300000390"
    ]
},
  "bbox": [],
  "geometry": {"coordinates":[-113.2833,38.45],"type":"Point"}
}
=======
{"geometry":{"type":"Point","coordinates":[-113.283300,38.450000]},"type":"Feature","properties":{"hierarchy":["tgn:2409977","tgn:2002101","tgn:1000001","tgn:7012149","tgn:7007827","tgn:7029392"],"placetype":["aat:300000390"],"id":2409977,"name:xx":"Imperial Mine"}}
>>>>>>> 03f74aca74312dbeaf24d7e61306dd6a786dc3d0
