{
  "id": 2481057,
  "type": "Feature",
  "properties": {
    "tgn:hierarchy":[
        "tgn:2481057",
        "tgn:1000001",
        "tgn:7012149",
        "tgn:1002634",
        "tgn:7007523",
        "tgn:7029392"
    ],
    "tgn:id":2481057,
    "tgn:name":"Lamb",
    "tgn:placetype":[
        "aat:300008347"
    ]
},
  "bbox": [],
  "geometry": {"coordinates":[-91.3833,39.7333],"type":"Point"}
}