{
  "id": 7157148,
  "type": "Feature",
  "properties": {
    "tgn:hierarchy":[
        "tgn:7157148",
        "tgn:7003669",
        "tgn:1000003",
        "tgn:7000084",
        "tgn:7029392"
    ],
    "tgn:id":7157148,
    "tgn:name":"Kehlbachs-Berg",
    "tgn:placetype":[
        "aat:300008777"
    ]
},
  "bbox": [],
  "geometry": {"coordinates":[11.316667,50.433333],"type":"Point"}
}