{
  "id": 7165069,
  "type": "Feature",
  "properties": {
    "tgn:hierarchy":[
        "tgn:7165069",
        "tgn:7003692",
        "tgn:1000003",
        "tgn:7000084",
        "tgn:7029392"
    ],
    "tgn:id":7165069,
    "tgn:name":"Hooskirch",
    "tgn:placetype":[
        "aat:300008347"
    ]
},
  "bbox": [],
  "geometry": {"coordinates":[9.45,47.95],"type":"Point"}
}