<<<<<<< HEAD
{
  "id": 7487623,
  "type": "Feature",
  "properties": {
    "tgn:hierarchy":[
        "tgn:7487623",
        "tgn:7488858",
        "tgn:1000004",
        "tgn:1000141",
        "tgn:7029392"
    ],
    "tgn:id":7487623,
    "tgn:name":"Keketaxi",
    "tgn:placetype":[
        "aat:300008347"
    ]
},
  "bbox": [],
  "geometry": {"coordinates":[121.081389,23.801667],"type":"Point"}
}
=======
{"geometry":{"type":"Point","coordinates":[121.081389,23.801667]},"type":"Feature","properties":{"hierarchy":["tgn:7487623","tgn:7488858","tgn:1000004","tgn:1000141","tgn:7029392"],"placetype":["aat:300008347"],"id":7487623,"name:xx":"Keketaxi"}}
>>>>>>> 03f74aca74312dbeaf24d7e61306dd6a786dc3d0
