{
  "id": 7487623,
  "type": "Feature",
  "properties": {
    "tgn:hierarchy":[
        "tgn:7487623",
        "tgn:7488858",
        "tgn:1000004",
        "tgn:1000141",
        "tgn:7029392"
    ],
    "tgn:id":7487623,
    "tgn:name":"Keketaxi",
    "tgn:placetype":[
        "aat:300008347"
    ]
},
  "bbox": [],
  "geometry": {"coordinates":[121.081389,23.801667],"type":"Point"}
}