<<<<<<< HEAD
{
  "id": 7356477,
  "type": "Feature",
  "properties": {
    "tgn:hierarchy":[
        "tgn:7356477",
        "tgn:7005580",
        "tgn:1000001",
        "tgn:7005560",
        "tgn:7029392"
    ],
    "tgn:id":7356477,
    "tgn:name":"Chimborazo, Cerro",
    "tgn:placetype":[
        "aat:300008795"
    ]
},
  "bbox": [],
  "geometry": {"coordinates":[-92.216667,15.133333],"type":"Point"}
}
=======
{"geometry":{"type":"Point","coordinates":[-92.216667,15.133333]},"type":"Feature","properties":{"hierarchy":["tgn:7356477","tgn:7005580","tgn:1000001","tgn:7005560","tgn:7029392"],"placetype":["aat:300008795"],"id":7356477,"name:xx":"Chimborazo, Cerro"}}
>>>>>>> 03f74aca74312dbeaf24d7e61306dd6a786dc3d0
