{
  "id": 2566023,
  "type": "Feature",
  "properties": {
    "tgn:hierarchy":[
        "tgn:2566023",
        "tgn:1000001",
        "tgn:7012149",
        "tgn:2000977",
        "tgn:7007520",
        "tgn:7029392"
    ],
    "tgn:id":2566023,
    "tgn:name":"Palmer Creek",
    "tgn:placetype":[
        "aat:300008706"
    ]
},
  "bbox": [],
  "geometry": {"coordinates":[-85.4667,43.7667],"type":"Point"}
}