{
  "id": 1068852,
  "type": "Feature",
  "properties": {
    "tgn:hierarchy":[
        "tgn:1068852",
        "tgn:1000004",
        "tgn:7016672",
        "tgn:1000111",
        "tgn:7029392"
    ],
    "tgn:id":1068852,
    "tgn:name":"Huaibin",
    "tgn:placetype":[
        "aat:300008347"
    ]
},
  "bbox": [],
  "geometry": {"coordinates":[115.45,32.4667],"type":"Point"}
}