{
  "id": 7523276,
  "type": "Feature",
  "properties": {
    "tgn:hierarchy":[
        "tgn:7523276",
        "tgn:7001242",
        "tgn:7001311",
        "tgn:7016833",
        "tgn:7029392"
    ],
    "tgn:id":7523276,
    "tgn:name:en":"Durunk\u0101t, W\u0101d\u012b",
    "tgn:placetype":[
        "aat:300379998"
    ]
},
  "bbox": [],
  "geometry": {"coordinates":[34.709582,24.497602],"type":"Point"}
}