{
  "id": 2507850,
  "type": "Feature",
  "properties": {
    "tgn:hierarchy":[
        "tgn:2507850",
        "tgn:1000001",
        "tgn:7012149",
        "tgn:2000961",
        "tgn:7007520",
        "tgn:7029392"
    ],
    "tgn:id":2507850,
    "tgn:name":"Mickey Lake",
    "tgn:placetype":[
        "aat:300008680"
    ]
},
  "bbox": [],
  "geometry": {"coordinates":[-85.75,44.7167],"type":"Point"}
}