<<<<<<< HEAD
{
  "id": 7374911,
  "type": "Feature",
  "properties": {
    "tgn:hierarchy":[
        "tgn:7374911",
        "tgn:1000001",
        "tgn:7005595",
        "tgn:7005560",
        "tgn:7029392"
    ],
    "tgn:id":7374911,
    "tgn:name":"La Haciendita",
    "tgn:placetype":[
        "aat:300008347"
    ]
},
  "bbox": [],
  "geometry": {"coordinates":[-107.8,25.75],"type":"Point"}
}
=======
{"geometry":{"type":"Point","coordinates":[-107.800000,25.750000]},"type":"Feature","properties":{"hierarchy":["tgn:7374911","tgn:1000001","tgn:7005595","tgn:7005560","tgn:7029392"],"placetype":["aat:300008347"],"id":7374911,"name:xx":"La Haciendita"}}
>>>>>>> 03f74aca74312dbeaf24d7e61306dd6a786dc3d0
