{
  "id": 7399540,
  "type": "Feature",
  "properties": {
    "tgn:hierarchy":[
        "tgn:7399540",
        "tgn:1000001",
        "tgn:7005599",
        "tgn:7005560",
        "tgn:7029392"
    ],
    "tgn:id":7399540,
    "tgn:name":"La Esperanza",
    "tgn:placetype":[
        "aat:300008347"
    ]
},
  "bbox": [],
  "geometry": {"coordinates":[-95.516667,17.872222],"type":"Point"}
}