{
  "id": 1061682,
  "type": "Feature",
  "properties": {
    "tgn:hierarchy":[
        "tgn:1061682",
        "tgn:1000004",
        "tgn:7011600",
        "tgn:7018214",
        "tgn:7002435",
        "tgn:7029392"
    ],
    "tgn:id":1061682,
    "tgn:name":"Zyryanovskiy",
    "tgn:placetype":[
        "aat:300008347"
    ]
},
  "bbox": [],
  "geometry": {"coordinates":[61.6333,57.8333],"type":"Point"}
}