{
  "id": 7160393,
  "type": "Feature",
  "properties": {
    "tgn:hierarchy":[
        "tgn:7160393",
        "tgn:7003669",
        "tgn:1000003",
        "tgn:7000084",
        "tgn:7029392"
    ],
    "tgn:id":7160393,
    "tgn:name":"H\u00f6fats",
    "tgn:placetype":[
        "aat:300008795"
    ]
},
  "bbox": [],
  "geometry": {"coordinates":[10.35,47.366667],"type":"Point"}
}