<<<<<<< HEAD
{
  "id": 7179995,
  "type": "Feature",
  "properties": {
    "tgn:hierarchy":[
        "tgn:7179995",
        "tgn:7003669",
        "tgn:1000003",
        "tgn:7000084",
        "tgn:7029392"
    ],
    "tgn:id":7179995,
    "tgn:name":"Fuchsm\u00fchle",
    "tgn:placetype":[
        "aat:300008347"
    ]
},
  "bbox": [],
  "geometry": {"coordinates":[10.166667,49.383333],"type":"Point"}
}
=======
{"geometry":{"type":"Point","coordinates":[10.166667,49.383333]},"type":"Feature","properties":{"hierarchy":["tgn:7179995","tgn:7003669","tgn:1000003","tgn:7000084","tgn:7029392"],"placetype":["aat:300008347"],"id":7179995,"name:xx":"Fuchsm\u00fchle"}}
>>>>>>> 03f74aca74312dbeaf24d7e61306dd6a786dc3d0
