<<<<<<< HEAD
{
  "id": 7020944,
  "type": "Feature",
  "properties": {
    "tgn:hierarchy":[
        "tgn:7020944",
        "tgn:1000001",
        "tgn:7012149",
        "tgn:2000476",
        "tgn:7007250",
        "tgn:7029392"
    ],
    "tgn:id":7020944,
    "tgn:name":"Packers Creek",
    "tgn:placetype":[
        "aat:300008706"
    ]
},
  "bbox": [],
  "geometry": {"coordinates":[-116.4,45.9667],"type":"Point"}
}
=======
{"geometry":{"type":"Point","coordinates":[-116.400000,45.966700]},"type":"Feature","properties":{"hierarchy":["tgn:7020944","tgn:1000001","tgn:7012149","tgn:2000476","tgn:7007250","tgn:7029392"],"placetype":["aat:300008706"],"id":7020944,"name:xx":"Packers Creek"}}
>>>>>>> 03f74aca74312dbeaf24d7e61306dd6a786dc3d0
