<<<<<<< HEAD
{
  "id": 7481081,
  "type": "Feature",
  "properties": {
    "tgn:hierarchy":[
        "tgn:7481081",
        "tgn:7468018",
        "tgn:1000004",
        "tgn:1000141",
        "tgn:7029392"
    ],
    "tgn:id":7481081,
    "tgn:name":"Dongshi Nanqiao",
    "tgn:placetype":[
        "aat:300007836"
    ]
},
  "bbox": [],
  "geometry": {"coordinates":[120.1689,23.443576],"type":"Point"}
}
=======
{"geometry":{"type":"Point","coordinates":[120.168900,23.443576]},"type":"Feature","properties":{"hierarchy":["tgn:7481081","tgn:7468018","tgn:1000004","tgn:1000141","tgn:7029392"],"placetype":["aat:300007836"],"id":7481081,"name:xx":"Dongshi Nanqiao"}}
>>>>>>> 03f74aca74312dbeaf24d7e61306dd6a786dc3d0
