<<<<<<< HEAD
{
  "id": 7176093,
  "type": "Feature",
  "properties": {
    "tgn:hierarchy":[
        "tgn:7176093",
        "tgn:7003692",
        "tgn:1000003",
        "tgn:7000084",
        "tgn:7029392"
    ],
    "tgn:id":7176093,
    "tgn:name":"Gro\u00dfer Wimbach",
    "tgn:placetype":[
        "aat:300008699"
    ]
},
  "bbox": [],
  "geometry": {"coordinates":[9.85,48.933333],"type":"Point"}
}
=======
{"geometry":{"type":"Point","coordinates":[9.850000,48.933333]},"type":"Feature","properties":{"hierarchy":["tgn:7176093","tgn:7003692","tgn:1000003","tgn:7000084","tgn:7029392"],"placetype":["aat:300008699"],"id":7176093,"name:xx":"Gro\u00dfer Wimbach"}}
>>>>>>> 03f74aca74312dbeaf24d7e61306dd6a786dc3d0
