{
  "id": 7519678,
  "type": "Feature",
  "properties": {
    "tgn:hierarchy":[
        "tgn:7519678",
        "tgn:1009227",
        "tgn:7001866",
        "tgn:1000226",
        "tgn:1000006",
        "tgn:7029392"
    ],
    "tgn:id":7519678,
    "tgn:name:en":"Blind Stream",
    "tgn:placetype":[
        "aat:300008699"
    ]
},
  "bbox": [],
  "geometry": {"coordinates":[172.966667,-42.633333],"type":"Point"}
}