{
  "id": 7313066,
  "type": "Feature",
  "properties": {
    "tgn:hierarchy":[
        "tgn:7313066",
        "tgn:1001657",
        "tgn:1000049",
        "tgn:1000002",
        "tgn:7029392"
    ],
    "tgn:id":7313066,
    "tgn:name":"Los Choros, Quebrada",
    "tgn:placetype":[
        "aat:300008699"
    ]
},
  "bbox": [],
  "geometry": {"coordinates":[-71.066667,-29.35],"type":"Point"}
}