{
  "id": 2251854,
  "type": "Feature",
  "properties": {
    "tgn:hierarchy":[
        "tgn:2251854",
        "tgn:1000001",
        "tgn:7019982",
        "tgn:7012149",
        "tgn:7007517",
        "tgn:7029392"
    ],
    "tgn:id":2251854,
    "tgn:name":"Conant Brook Reservoir",
    "tgn:placetype":[
        "aat:300006191"
    ]
},
  "bbox": [],
  "geometry": {"coordinates":[-72.2833,42.0667],"type":"Point"}
}