<<<<<<< HEAD
{
  "id": 2251854,
  "type": "Feature",
  "properties": {
    "tgn:hierarchy":[
        "tgn:2251854",
        "tgn:1000001",
        "tgn:7019982",
        "tgn:7012149",
        "tgn:7007517",
        "tgn:7029392"
    ],
    "tgn:id":2251854,
    "tgn:name":"Conant Brook Reservoir",
    "tgn:placetype":[
        "aat:300006191"
    ]
},
  "bbox": [],
  "geometry": {"coordinates":[-72.2833,42.0667],"type":"Point"}
}
=======
{"geometry":{"type":"Point","coordinates":[-72.283300,42.066700]},"type":"Feature","properties":{"hierarchy":["tgn:2251854","tgn:1000001","tgn:7019982","tgn:7012149","tgn:7007517","tgn:7029392"],"placetype":["aat:300006191"],"id":2251854,"name:xx":"Conant Brook Reservoir"}}
>>>>>>> 03f74aca74312dbeaf24d7e61306dd6a786dc3d0
