{
  "id": 2028955,
  "type": "Feature",
  "properties": {
    "tgn:hierarchy":[
        "tgn:2028955",
        "tgn:1000001",
        "tgn:7012149",
        "tgn:2000521",
        "tgn:7007251",
        "tgn:7029392"
    ],
    "tgn:id":2028955,
    "tgn:name":"Mapleton",
    "tgn:placetype":[
        "aat:300008347"
    ]
},
  "bbox": [],
  "geometry": {"coordinates":[-89.7167,40.55],"type":"Point"}
}