{
  "id": 7402008,
  "type": "Feature",
  "properties": {
    "tgn:hierarchy":[
        "tgn:7402008",
        "tgn:1000001",
        "tgn:7005600",
        "tgn:7005560",
        "tgn:7029392"
    ],
    "tgn:id":7402008,
    "tgn:name":"San Mateo",
    "tgn:placetype":[
        "aat:300008347"
    ]
},
  "bbox": [],
  "geometry": {"coordinates":[-89.141667,19.866667],"type":"Point"}
}