{
  "id": 1129095,
  "type": "Feature",
  "properties": {
    "tgn:hierarchy":[
        "tgn:1129095",
        "tgn:7002443",
        "tgn:7017242",
        "tgn:1000003",
        "tgn:7008591",
        "tgn:7029392"
    ],
    "tgn:id":1129095,
    "tgn:name:en":"Rheidol",
    "tgn:placetype":[
        "aat:300008707",
        "aat:300008699"
    ]
},
  "bbox": [],
  "geometry": {"coordinates":[-4.083333,52.416667],"type":"Point"}
}