{
  "id": 2277612,
  "type": "Feature",
  "properties": {
    "tgn:hierarchy":[
        "tgn:2277612",
        "tgn:1000001",
        "tgn:2002370",
        "tgn:7012149",
        "tgn:7007923",
        "tgn:7029392"
    ],
    "tgn:id":2277612,
    "tgn:name":"Davis Spring",
    "tgn:placetype":[
        "aat:300008697"
    ]
},
  "bbox": [],
  "geometry": {"coordinates":[-104.4167,44.4833],"type":"Point"}
}