<<<<<<< HEAD
{
  "id": 2339820,
  "type": "Feature",
  "properties": {
    "tgn:hierarchy":[
        "tgn:2339820",
        "tgn:1000001",
        "tgn:7012149",
        "tgn:1002545",
        "tgn:7007157",
        "tgn:7029392"
    ],
    "tgn:id":2339820,
    "tgn:name":"Freeman Creek",
    "tgn:placetype":[
        "aat:300008706"
    ]
},
  "bbox": [],
  "geometry": {"coordinates":[-118.6167,35.6167],"type":"Point"}
}
=======
{"geometry":{"type":"Point","coordinates":[-118.616700,35.616700]},"type":"Feature","properties":{"hierarchy":["tgn:2339820","tgn:1000001","tgn:7012149","tgn:1002545","tgn:7007157","tgn:7029392"],"placetype":["aat:300008706"],"id":2339820,"name:xx":"Freeman Creek"}}
>>>>>>> 03f74aca74312dbeaf24d7e61306dd6a786dc3d0
