{
  "id": 2148015,
  "type": "Feature",
  "properties": {
    "tgn:hierarchy":[
        "tgn:2148015",
        "tgn:1000001",
        "tgn:7012149",
        "tgn:7007523",
        "tgn:7029392"
    ],
    "tgn:id":2148015,
    "tgn:name":"Barker Creek",
    "tgn:placetype":[
        "aat:300008706"
    ]
},
  "bbox": [],
  "geometry": {"coordinates":[-93.4667,38.5167],"type":"Point"}
}