<<<<<<< HEAD
{
  "id": 2259816,
  "type": "Feature",
  "properties": {
    "tgn:hierarchy":[
        "tgn:2259816",
        "tgn:1000001",
        "tgn:1002286",
        "tgn:7012149",
        "tgn:7007710",
        "tgn:7029392"
    ],
    "tgn:id":2259816,
    "tgn:name":"Cougar Run",
    "tgn:placetype":[
        "aat:300008699"
    ]
},
  "bbox": [],
  "geometry": {"coordinates":[-77.6167,41.4167],"type":"Point"}
}
=======
{"geometry":{"type":"Point","coordinates":[-77.616700,41.416700]},"type":"Feature","properties":{"hierarchy":["tgn:2259816","tgn:1000001","tgn:1002286","tgn:7012149","tgn:7007710","tgn:7029392"],"placetype":["aat:300008699"],"id":2259816,"name:xx":"Cougar Run"}}
>>>>>>> 03f74aca74312dbeaf24d7e61306dd6a786dc3d0
