{
  "id": 7023999,
  "type": "Feature",
  "properties": {
    "tgn:hierarchy":[
        "tgn:7023999",
        "tgn:1000001",
        "tgn:7012149",
        "tgn:7007157",
        "tgn:1002857",
        "tgn:2010925",
        "tgn:7029392"
    ],
    "tgn:id":7023999,
    "tgn:name":"Cucamonga",
    "tgn:placetype":[
        "aat:300000745"
    ]
},
  "bbox": [],
  "geometry": {"coordinates":[-117.6167,34.1333],"type":"Point"}
}