<<<<<<< HEAD
{
  "id": 7023999,
  "type": "Feature",
  "properties": {
    "tgn:hierarchy":[
        "tgn:7023999",
        "tgn:1000001",
        "tgn:7012149",
        "tgn:7007157",
        "tgn:1002857",
        "tgn:2010925",
        "tgn:7029392"
    ],
    "tgn:id":7023999,
    "tgn:name":"Cucamonga",
    "tgn:placetype":[
        "aat:300000745"
    ]
},
  "bbox": [],
  "geometry": {"coordinates":[-117.6167,34.1333],"type":"Point"}
}
=======
{"geometry":{"type":"Point","coordinates":[-117.616700,34.133300]},"type":"Feature","properties":{"hierarchy":["tgn:7023999","tgn:1000001","tgn:7012149","tgn:7007157","tgn:1002857","tgn:2010925","tgn:7029392"],"placetype":["aat:300000745"],"id":7023999,"name:xx":"Cucamonga"}}
>>>>>>> 03f74aca74312dbeaf24d7e61306dd6a786dc3d0
