{
  "id": 2510790,
  "type": "Feature",
  "properties": {
    "tgn:hierarchy":[
        "tgn:2510790",
        "tgn:1000001",
        "tgn:7012149",
        "tgn:2001717",
        "tgn:7007708",
        "tgn:7029392"
    ],
    "tgn:id":2510790,
    "tgn:name":"Midget Lake",
    "tgn:placetype":[
        "aat:300008680"
    ]
},
  "bbox": [],
  "geometry": {"coordinates":[-121.8333,44.5667],"type":"Point"}
}