{
  "id": 7164946,
  "type": "Feature",
  "properties": {
    "tgn:hierarchy":[
        "tgn:7164946",
        "tgn:1000003",
        "tgn:7003676",
        "tgn:7000084",
        "tgn:7029392"
    ],
    "tgn:id":7164946,
    "tgn:name":"Ildehausen",
    "tgn:placetype":[
        "aat:300008347"
    ]
},
  "bbox": [],
  "geometry": {"coordinates":[10.133333,51.85],"type":"Point"}
}