{
  "id": 2152964,
  "type": "Feature",
  "properties": {
    "tgn:hierarchy":[
        "tgn:2152964",
        "tgn:1000001",
        "tgn:2001483",
        "tgn:7012149",
        "tgn:7007709",
        "tgn:7029392"
    ],
    "tgn:id":2152964,
    "tgn:name":"Beach Mountain",
    "tgn:placetype":[
        "aat:300008798"
    ]
},
  "bbox": [],
  "geometry": {"coordinates":[-83.8833,35.0167],"type":"Point"}
}