{
  "id": 7137933,
  "type": "Feature",
  "properties": {
    "tgn:hierarchy":[
        "tgn:7137933",
        "tgn:1000003",
        "tgn:7000094",
        "tgn:7000084",
        "tgn:7029392"
    ],
    "tgn:id":7137933,
    "tgn:name":"Liebhof",
    "tgn:placetype":[
        "aat:300000206"
    ]
},
  "bbox": [],
  "geometry": {"coordinates":[12.266667,53.333333],"type":"Point"}
}