{
  "id": 7507650,
  "type": "Feature",
  "properties": {
    "tgn:hierarchy":[
        "tgn:7507650",
        "tgn:1008380",
        "tgn:7520093",
        "tgn:1000226",
        "tgn:1000006",
        "tgn:7029392"
    ],
    "tgn:id":7507650,
    "tgn:name:en":"Pongaroa River",
    "tgn:placetype":[
        "aat:300008699"
    ]
},
  "bbox": [],
  "geometry": {"coordinates":[176.233333,-40.583333],"type":"Point"}
}