{
  "id": 7462809,
  "type": "Feature",
  "properties": {
    "tgn:hierarchy":[
        "tgn:7462809",
        "tgn:7002444",
        "tgn:1000003",
        "tgn:7009907",
        "tgn:7008591",
        "tgn:7029392"
    ],
    "tgn:id":7462809,
    "tgn:name:en":"Ling Holm",
    "tgn:placetype":[
        "aat:300008791"
    ]
},
  "bbox": [],
  "geometry": {"coordinates":[-2.866667,59.066667],"type":"Point"}
}