{
  "id": 2001947,
  "type": "Feature",
  "properties": {
    "tgn:hierarchy":[
        "tgn:2001947",
        "tgn:1000001",
        "tgn:7012149",
        "tgn:7007826",
        "tgn:7029392"
    ],
    "tgn:id":2001947,
    "tgn:name":"Brooks",
    "tgn:placetype":[
        "aat:300387145",
        "aat:300000771"
    ]
},
  "bbox": [],
  "geometry": {"coordinates":[-98.2333,27.0333],"type":"Point"}
}