{
  "id": 7032306,
  "type": "Feature",
  "properties": {
    "tgn:hierarchy":[
        "tgn:7032306",
        "tgn:7001680",
        "tgn:7001242",
        "tgn:1000184",
        "tgn:7029392"
    ],
    "tgn:id":7032306,
    "tgn:name:fr":"Boeuf, Nez de",
    "tgn:placetype":[
        "aat:300008798"
    ]
},
  "bbox": [],
  "geometry": {"coordinates":[55.6166,-21.1833],"type":"Point"}
}