{
  "id": 7585518,
  "type": "Feature",
  "properties": {
    "tgn:hierarchy":[
        "tgn:7585518",
        "tgn:1000004",
        "tgn:7000198",
        "tgn:7000799",
        "tgn:7029392"
    ],
    "tgn:id":7585518,
    "tgn:name:en":"Banjni",
    "tgn:placetype":[
        "aat:300008347"
    ]
},
  "bbox": [],
  "geometry": {"coordinates":[74.047222,33.265278],"type":"Point"}
}