{
  "id": 2617241,
  "type": "Feature",
  "properties": {
    "tgn:hierarchy":[
        "tgn:2617241",
        "tgn:1000001",
        "tgn:7012149",
        "tgn:2001211",
        "tgn:7007523",
        "tgn:7029392"
    ],
    "tgn:id":2617241,
    "tgn:name":"Richey Hollow",
    "tgn:placetype":[
        "aat:300008761"
    ]
},
  "bbox": [],
  "geometry": {"coordinates":[-92.7667,37.8167],"type":"Point"}
}