{
  "id": 7504794,
  "type": "Feature",
  "properties": {
    "tgn:hierarchy":[
        "tgn:7504794",
        "tgn:7000508",
        "tgn:1008380",
        "tgn:1000226",
        "tgn:1000006",
        "tgn:7029392"
    ],
    "tgn:id":7504794,
    "tgn:name:en":"Piripiri Point",
    "tgn:placetype":[
        "aat:300386846"
    ]
},
  "bbox": [],
  "geometry": {"coordinates":[174.749722,-36.667222],"type":"Point"}
}