{
  "id": 7296698,
  "type": "Feature",
  "properties": {
    "tgn:hierarchy":[
        "tgn:7296698",
        "tgn:7002813",
        "tgn:7002758",
        "tgn:1000003",
        "tgn:1000095",
        "tgn:7029392"
    ],
    "tgn:id":7296698,
    "tgn:name":"Huete, Punta",
    "tgn:placetype":[
        "aat:300386846"
    ]
},
  "bbox": [],
  "geometry": {"coordinates":[-6.293056,36.613611],"type":"Point"}
}