{
  "id": 2246821,
  "type": "Feature",
  "properties": {
    "tgn:hierarchy":[
        "tgn:2246821",
        "tgn:1000001",
        "tgn:7012149",
        "tgn:7007157",
        "tgn:7029392"
    ],
    "tgn:id":2246821,
    "tgn:name":"Coches, Ca\u00f1ada De Los",
    "tgn:placetype":[
        "aat:300008761"
    ]
},
  "bbox": [],
  "geometry": {"coordinates":[-120.25,34.9667],"type":"Point"}
}