{
  "id": 2582205,
  "type": "Feature",
  "properties": {
    "tgn:hierarchy":[
        "tgn:2582205",
        "tgn:1000001",
        "tgn:7012149",
        "tgn:7007566",
        "tgn:7029392"
    ],
    "tgn:id":2582205,
    "tgn:name":"Pine Creek",
    "tgn:placetype":[
        "aat:300008706"
    ]
},
  "bbox": [],
  "geometry": {"coordinates":[-108.7167,33.2333],"type":"Point"}
}