{
  "id": 2727409,
  "type": "Feature",
  "properties": {
    "tgn:hierarchy":[
        "tgn:2727409",
        "tgn:1000001",
        "tgn:7012149",
        "tgn:2001719",
        "tgn:7007708",
        "tgn:7029392"
    ],
    "tgn:id":2727409,
    "tgn:name":"Trail Canyon",
    "tgn:placetype":[
        "aat:300008761"
    ]
},
  "bbox": [],
  "geometry": {"coordinates":[-119.2833,45.25],"type":"Point"}
}