{
  "id": 7284841,
  "type": "Feature",
  "properties": {
    "tgn:hierarchy":[
        "tgn:7284841",
        "tgn:1001699",
        "tgn:1000049",
        "tgn:1000002",
        "tgn:7029392"
    ],
    "tgn:id":7284841,
    "tgn:name":"Pulga, Punta",
    "tgn:placetype":[
        "aat:300386846"
    ]
},
  "bbox": [],
  "geometry": {"coordinates":[-74.0425,-42.086667],"type":"Point"}
}