{
  "id": 2493484,
  "type": "Feature",
  "properties": {
    "tgn:hierarchy":[
        "tgn:2493484",
        "tgn:1000001",
        "tgn:2000924",
        "tgn:7012149",
        "tgn:7007515",
        "tgn:7029392"
    ],
    "tgn:id":2493484,
    "tgn:name":"Marsh Cove",
    "tgn:placetype":[
        "aat:300132316"
    ]
},
  "bbox": [],
  "geometry": {"coordinates":[-68.65,44.0667],"type":"Point"}
}