{
  "id": 2423027,
  "type": "Feature",
  "properties": {
    "tgn:hierarchy":[
        "tgn:2423027",
        "tgn:1000001",
        "tgn:7012149",
        "tgn:2000410",
        "tgn:7007248",
        "tgn:7029392"
    ],
    "tgn:id":2423027,
    "tgn:name":"Joe Mountain",
    "tgn:placetype":[
        "aat:300008798"
    ]
},
  "bbox": [],
  "geometry": {"coordinates":[-83.4833,34.7667],"type":"Point"}
}