<<<<<<< HEAD
{
  "id": 2259000,
  "type": "Feature",
  "properties": {
    "tgn:hierarchy":[
        "tgn:2259000",
        "tgn:1000001",
        "tgn:7012149",
        "tgn:1002533",
        "tgn:7007826",
        "tgn:7029392"
    ],
    "tgn:id":2259000,
    "tgn:name":"Cottonwood Creek",
    "tgn:placetype":[
        "aat:300008706"
    ]
},
  "bbox": [],
  "geometry": {"coordinates":[-97.75,28.7333],"type":"Point"}
}
=======
{"geometry":{"type":"Point","coordinates":[-97.750000,28.733300]},"type":"Feature","properties":{"hierarchy":["tgn:2259000","tgn:1000001","tgn:7012149","tgn:1002533","tgn:7007826","tgn:7029392"],"placetype":["aat:300008706"],"id":2259000,"name:xx":"Cottonwood Creek"}}
>>>>>>> 03f74aca74312dbeaf24d7e61306dd6a786dc3d0
