<<<<<<< HEAD
{
  "id": 2159665,
  "type": "Feature",
  "properties": {
    "tgn:hierarchy":[
        "tgn:2159665",
        "tgn:1000001",
        "tgn:7012149",
        "tgn:2001903",
        "tgn:7007825",
        "tgn:7029392"
    ],
    "tgn:id":2159665,
    "tgn:name":"Bee Tree Ridge",
    "tgn:placetype":[
        "aat:300266640"
    ]
},
  "bbox": [],
  "geometry": {"coordinates":[-85.2333,36.2833],"type":"Point"}
}
=======
{"geometry":{"type":"Point","coordinates":[-85.233300,36.283300]},"type":"Feature","properties":{"hierarchy":["tgn:2159665","tgn:1000001","tgn:7012149","tgn:2001903","tgn:7007825","tgn:7029392"],"placetype":["aat:300266640"],"id":2159665,"name:xx":"Bee Tree Ridge"}}
>>>>>>> 03f74aca74312dbeaf24d7e61306dd6a786dc3d0
