{
  "id": 7419670,
  "type": "Feature",
  "properties": {
    "tgn:hierarchy":[
        "tgn:7419670",
        "tgn:1001836",
        "tgn:1000001",
        "tgn:7005560",
        "tgn:7029392"
    ],
    "tgn:id":7419670,
    "tgn:name":"La Laguna, Sierra",
    "tgn:placetype":[
        "aat:300008795"
    ]
},
  "bbox": [],
  "geometry": {"coordinates":[-109.968611,23.593611],"type":"Point"}
}