{
  "id": 2202792,
  "type": "Feature",
  "properties": {
    "tgn:hierarchy":[
        "tgn:2202792",
        "tgn:1000001",
        "tgn:2002318",
        "tgn:7012149",
        "tgn:7007922",
        "tgn:7029392"
    ],
    "tgn:id":2202792,
    "tgn:name":"Buckety Creek",
    "tgn:placetype":[
        "aat:300008706"
    ]
},
  "bbox": [],
  "geometry": {"coordinates":[-91.8833,46.35],"type":"Point"}
}