{
  "id": 7307154,
  "type": "Feature",
  "properties": {
    "tgn:hierarchy":[
        "tgn:7307154",
        "tgn:1001439",
        "tgn:1000003",
        "tgn:7002797",
        "tgn:1000095",
        "tgn:7029392"
    ],
    "tgn:id":7307154,
    "tgn:name":"Madro\u00f1o, Sierra del",
    "tgn:placetype":[
        "aat:300266640"
    ]
},
  "bbox": [],
  "geometry": {"coordinates":[-1.75,37.883333],"type":"Point"}
}