{
  "id": 2323421,
  "type": "Feature",
  "properties": {
    "tgn:hierarchy":[
        "tgn:2323421",
        "tgn:1000001",
        "tgn:7012149",
        "tgn:2002182",
        "tgn:7007919",
        "tgn:7029392"
    ],
    "tgn:id":2323421,
    "tgn:name":"Farmville Lake",
    "tgn:placetype":[
        "aat:300006191"
    ]
},
  "bbox": [],
  "geometry": {"coordinates":[-78.4167,37.2333],"type":"Point"}
}