{
  "id": 7487948,
  "type": "Feature",
  "properties": {
    "tgn:hierarchy":[
        "tgn:7487948",
        "tgn:7487020",
        "tgn:1000004",
        "tgn:1000141",
        "tgn:7029392"
    ],
    "tgn:id":7487948,
    "tgn:name":"Danan He",
    "tgn:placetype":[
        "aat:300008699"
    ]
},
  "bbox": [],
  "geometry": {"coordinates":[120.965851,24.540396],"type":"Point"}
}