<<<<<<< HEAD
{
  "id": 7487948,
  "type": "Feature",
  "properties": {
    "tgn:hierarchy":[
        "tgn:7487948",
        "tgn:7487020",
        "tgn:1000004",
        "tgn:1000141",
        "tgn:7029392"
    ],
    "tgn:id":7487948,
    "tgn:name":"Danan He",
    "tgn:placetype":[
        "aat:300008699"
    ]
},
  "bbox": [],
  "geometry": {"coordinates":[120.965851,24.540396],"type":"Point"}
}
=======
{"geometry":{"type":"Point","coordinates":[120.965851,24.540396]},"type":"Feature","properties":{"hierarchy":["tgn:7487948","tgn:7487020","tgn:1000004","tgn:1000141","tgn:7029392"],"placetype":["aat:300008699"],"id":7487948,"name:xx":"Danan He"}}
>>>>>>> 03f74aca74312dbeaf24d7e61306dd6a786dc3d0
