{
  "id": 1066319,
  "type": "Feature",
  "properties": {
    "tgn:hierarchy":[
        "tgn:1066319",
        "tgn:1000004",
        "tgn:1002109",
        "tgn:1000108",
        "tgn:7029392"
    ],
    "tgn:id":1066319,
    "tgn:name":"Tigyaing",
    "tgn:placetype":[
        "aat:300008347"
    ]
},
  "bbox": [],
  "geometry": {"coordinates":[96.15,23.8167],"type":"Point"}
}