{
  "id": 2549342,
  "type": "Feature",
  "properties": {
    "tgn:hierarchy":[
        "tgn:2549342",
        "tgn:7002659",
        "tgn:1000001",
        "tgn:7012149",
        "tgn:2000035",
        "tgn:7029392"
    ],
    "tgn:id":2549342,
    "tgn:name":"North Sauty Creek Bar",
    "tgn:placetype":[
        "aat:300132348"
    ]
},
  "bbox": [],
  "geometry": {"coordinates":[-86.0833,34.55],"type":"Point"}
}