{
  "id": 2438743,
  "type": "Feature",
  "properties": {
    "tgn:hierarchy":[
        "tgn:2438743",
        "tgn:1000001",
        "tgn:1002213",
        "tgn:7012149",
        "tgn:7007710",
        "tgn:7029392"
    ],
    "tgn:id":2438743,
    "tgn:name":"Kinkora Bar",
    "tgn:placetype":[
        "aat:300132348"
    ]
},
  "bbox": [],
  "geometry": {"coordinates":[-74.7833,40.1167],"type":"Point"}
}