{
  "id": 2310173,
  "type": "Feature",
  "properties": {
    "tgn:hierarchy":[
        "tgn:2310173",
        "tgn:1000001",
        "tgn:7012149",
        "tgn:7014589",
        "tgn:7007515",
        "tgn:7029392"
    ],
    "tgn:id":2310173,
    "tgn:name":"Eaton Point",
    "tgn:placetype":[
        "aat:300008850"
    ]
},
  "bbox": [],
  "geometry": {"coordinates":[-67.35,45.0667],"type":"Point"}
}