{
  "id": 2055785,
  "type": "Feature",
  "properties": {
    "tgn:hierarchy":[
        "tgn:2055785",
        "tgn:1000001",
        "tgn:2001012",
        "tgn:7012149",
        "tgn:7007521",
        "tgn:7029392"
    ],
    "tgn:id":2055785,
    "tgn:name":"Winnipeg Junction",
    "tgn:placetype":[
        "aat:300008347"
    ]
},
  "bbox": [],
  "geometry": {"coordinates":[-96.2333,46.8833],"type":"Point"}
}