{
  "id": 2752795,
  "type": "Feature",
  "properties": {
    "tgn:hierarchy":[
        "tgn:2752795",
        "tgn:1000001",
        "tgn:1002267",
        "tgn:7012149",
        "tgn:7007919",
        "tgn:7029392"
    ],
    "tgn:id":2752795,
    "tgn:name":"Watch Run",
    "tgn:placetype":[
        "aat:300008699"
    ]
},
  "bbox": [],
  "geometry": {"coordinates":[-77.4833,37.4167],"type":"Point"}
}