{
  "id": 7509263,
  "type": "Feature",
  "properties": {
    "tgn:hierarchy":[
        "tgn:7509263",
        "tgn:1008380",
        "tgn:1000226",
        "tgn:7000512",
        "tgn:1000006",
        "tgn:7029392"
    ],
    "tgn:id":7509263,
    "tgn:name:en":"Tiffin",
    "tgn:placetype":[
        "aat:300008777"
    ]
},
  "bbox": [],
  "geometry": {"coordinates":[175.583333,-41.066667],"type":"Point"}
}