{
  "id": 2710811,
  "type": "Feature",
  "properties": {
    "tgn:hierarchy":[
        "tgn:2710811",
        "tgn:7030515",
        "tgn:7006450",
        "tgn:1000001",
        "tgn:7012149",
        "tgn:7029392"
    ],
    "tgn:id":2710811,
    "tgn:name":"Tangik Island",
    "tgn:placetype":[
        "aat:300008791"
    ]
},
  "bbox": [],
  "geometry": {"coordinates":[-165.4833,54.1333],"type":"Point"}
}