{
  "id": 2776925,
  "type": "Feature",
  "properties": {
    "tgn:hierarchy":[
        "tgn:2776925",
        "tgn:1000001",
        "tgn:7006451",
        "tgn:2000094",
        "tgn:7012149",
        "tgn:7029392"
    ],
    "tgn:id":2776925,
    "tgn:name":"Windy Bob Tank",
    "tgn:placetype":[
        "aat:300006191"
    ]
},
  "bbox": [],
  "geometry": {"coordinates":[-109.55,33.4167],"type":"Point"}
}