{
  "id": 2464734,
  "type": "Feature",
  "properties": {
    "tgn:hierarchy":[
        "tgn:2464734",
        "tgn:7002659",
        "tgn:1000001",
        "tgn:7012149",
        "tgn:7029392"
    ],
    "tgn:id":2464734,
    "tgn:name":"Logan Creek",
    "tgn:placetype":[
        "aat:300008706"
    ]
},
  "bbox": [],
  "geometry": {"coordinates":[-87.85,33.2833],"type":"Point"}
}