<<<<<<< HEAD
{
  "id": 7377431,
  "type": "Feature",
  "properties": {
    "tgn:hierarchy":[
        "tgn:7377431",
        "tgn:1000001",
        "tgn:1001960",
        "tgn:7005560",
        "tgn:7029392"
    ],
    "tgn:id":7377431,
    "tgn:name":"Rancho Las Norias",
    "tgn:placetype":[
        "aat:300000241"
    ]
},
  "bbox": [],
  "geometry": {"coordinates":[-110.316667,29.966667],"type":"Point"}
}
=======
{"geometry":{"type":"Point","coordinates":[-110.316667,29.966667]},"type":"Feature","properties":{"hierarchy":["tgn:7377431","tgn:1000001","tgn:1001960","tgn:7005560","tgn:7029392"],"placetype":["aat:300000241"],"id":7377431,"name:xx":"Rancho Las Norias"}}
>>>>>>> 03f74aca74312dbeaf24d7e61306dd6a786dc3d0
