<<<<<<< HEAD
{
  "id": 7353238,
  "type": "Feature",
  "properties": {
    "tgn:hierarchy":[
        "tgn:7353238",
        "tgn:7005581",
        "tgn:1000001",
        "tgn:7005560",
        "tgn:7029392"
    ],
    "tgn:id":7353238,
    "tgn:name":"Anc\u00f3n de Carros",
    "tgn:placetype":[
        "aat:300008347"
    ]
},
  "bbox": [],
  "geometry": {"coordinates":[-105.233333,27.983333],"type":"Point"}
}
=======
{"geometry":{"type":"Point","coordinates":[-105.233333,27.983333]},"type":"Feature","properties":{"hierarchy":["tgn:7353238","tgn:7005581","tgn:1000001","tgn:7005560","tgn:7029392"],"placetype":["aat:300008347"],"id":7353238,"name:xx":"Anc\u00f3n de Carros"}}
>>>>>>> 03f74aca74312dbeaf24d7e61306dd6a786dc3d0
