{
  "id": 2324963,
  "type": "Feature",
  "properties": {
    "tgn:hierarchy":[
        "tgn:2324963",
        "tgn:1000001",
        "tgn:7006451",
        "tgn:7012149",
        "tgn:2000103",
        "tgn:7029392"
    ],
    "tgn:id":2324963,
    "tgn:name":"Ferguson Ridge",
    "tgn:placetype":[
        "aat:300266640"
    ]
},
  "bbox": [],
  "geometry": {"coordinates":[-113.0333,34.9167],"type":"Point"}
}