{
  "id": 2310160,
  "type": "Feature",
  "properties": {
    "tgn:hierarchy":[
        "tgn:2310160",
        "tgn:2000945",
        "tgn:1000001",
        "tgn:7012149",
        "tgn:7007520",
        "tgn:7029392"
    ],
    "tgn:id":2310160,
    "tgn:name":"Eaton Lake",
    "tgn:placetype":[
        "aat:300008680"
    ]
},
  "bbox": [],
  "geometry": {"coordinates":[-85.2667,45.15],"type":"Point"}
}