{
  "id": 7564576,
  "type": "Feature",
  "properties": {
    "tgn:hierarchy":[
        "tgn:7564576",
        "tgn:1000004",
        "tgn:7000198",
        "tgn:7016722",
        "tgn:7029392"
    ],
    "tgn:id":7564576,
    "tgn:name:en":"Purwa Mirhai",
    "tgn:placetype":[
        "aat:300008347"
    ]
},
  "bbox": [],
  "geometry": {"coordinates":[79.680911,26.940131],"type":"Point"}
}