{
  "id": 2521513,
  "type": "Feature",
  "properties": {
    "tgn:hierarchy":[
        "tgn:2521513",
        "tgn:7002659",
        "tgn:1000001",
        "tgn:7012149",
        "tgn:2000062",
        "tgn:7029392"
    ],
    "tgn:id":2521513,
    "tgn:name":"Monticello Estates",
    "tgn:placetype":[
        "aat:300008347"
    ]
},
  "bbox": [],
  "geometry": {"coordinates":[-87.4667,33.1167],"type":"Point"}
}