{
  "id": 2270004,
  "type": "Feature",
  "properties": {
    "tgn:hierarchy":[
        "tgn:2270004",
        "tgn:1000001",
        "tgn:7012149",
        "tgn:2002304",
        "tgn:7013961",
        "tgn:7029392"
    ],
    "tgn:id":2270004,
    "tgn:name":"Crumpler Impoundment Number Two",
    "tgn:placetype":[
        "aat:300006191"
    ]
},
  "bbox": [],
  "geometry": {"coordinates":[-81.3333,37.4333],"type":"Point"}
}