{
  "id": 2037736,
  "type": "Feature",
  "properties": {
    "tgn:hierarchy":[
        "tgn:2037736",
        "tgn:1000001",
        "tgn:7012149",
        "tgn:2000801",
        "tgn:7007255",
        "tgn:7029392"
    ],
    "tgn:id":2037736,
    "tgn:name":"Beulah",
    "tgn:placetype":[
        "aat:300008347"
    ]
},
  "bbox": [],
  "geometry": {"coordinates":[-87.6833,37.2667],"type":"Point"}
}