{
  "id": 7227262,
  "type": "Feature",
  "properties": {
    "tgn:hierarchy":[
        "tgn:7227262",
        "tgn:7002690",
        "tgn:7012056",
        "tgn:1000003",
        "tgn:1000074",
        "tgn:7029392"
    ],
    "tgn:id":7227262,
    "tgn:name":"Skhist\u00f3, Nis\u00eds",
    "tgn:placetype":[
        "aat:300008791"
    ]
},
  "bbox": [],
  "geometry": {"coordinates":[23.666667,35.216667],"type":"Point"}
}