{
  "id": 2476084,
  "type": "Feature",
  "properties": {
    "tgn:hierarchy":[
        "tgn:2476084",
        "tgn:1000001",
        "tgn:7012149",
        "tgn:2002287",
        "tgn:7013961",
        "tgn:7029392"
    ],
    "tgn:id":2476084,
    "tgn:name":"Lukins Run",
    "tgn:placetype":[
        "aat:300008699"
    ]
},
  "bbox": [],
  "geometry": {"coordinates":[-79.6833,38.65],"type":"Point"}
}