<<<<<<< HEAD
{
  "id": 2159515,
  "type": "Feature",
  "properties": {
    "tgn:hierarchy":[
        "tgn:2159515",
        "tgn:1000001",
        "tgn:7012149",
        "tgn:2001153",
        "tgn:7007522",
        "tgn:7029392"
    ],
    "tgn:id":2159515,
    "tgn:name":"Bee Lake",
    "tgn:placetype":[
        "aat:300008680"
    ]
},
  "bbox": [],
  "geometry": {"coordinates":[-90.25,33.8],"type":"Point"}
}
=======
{"geometry":{"type":"Point","coordinates":[-90.250000,33.800000]},"type":"Feature","properties":{"hierarchy":["tgn:2159515","tgn:1000001","tgn:7012149","tgn:2001153","tgn:7007522","tgn:7029392"],"placetype":["aat:300008680"],"id":2159515,"name:xx":"Bee Lake"}}
>>>>>>> 03f74aca74312dbeaf24d7e61306dd6a786dc3d0
