{
  "id": 7022766,
  "type": "Feature",
  "properties": {
    "tgn:hierarchy":[
        "tgn:7022766",
        "tgn:1000001",
        "tgn:2001418",
        "tgn:7012149",
        "tgn:7007526",
        "tgn:7029392"
    ],
    "tgn:id":7022766,
    "tgn:name":"Woodchopper Spring",
    "tgn:placetype":[
        "aat:300008697"
    ]
},
  "bbox": [],
  "geometry": {"coordinates":[-116.9667,38.1667],"type":"Point"}
}