{
  "id": 7576182,
  "type": "Feature",
  "properties": {
    "tgn:hierarchy":[
        "tgn:7576182",
        "tgn:1000004",
        "tgn:7000198",
        "tgn:7016788",
        "tgn:7029392"
    ],
    "tgn:id":7576182,
    "tgn:name:en":"L\u0101m\u0101kho",
    "tgn:placetype":[
        "aat:300008347"
    ]
},
  "bbox": [],
  "geometry": {"coordinates":[75.475553,25.052587],"type":"Point"}
}