{
  "id": 2182599,
  "type": "Feature",
  "properties": {
    "tgn:hierarchy":[
        "tgn:2182599",
        "tgn:1000001",
        "tgn:2000314",
        "tgn:7012149",
        "tgn:7007248",
        "tgn:7029392"
    ],
    "tgn:id":2182599,
    "tgn:name":"Blue Spring",
    "tgn:placetype":[
        "aat:300008697"
    ]
},
  "bbox": [],
  "geometry": {"coordinates":[-85.2167,34.8667],"type":"Point"}
}