{
  "id": 1118909,
  "type": "Feature",
  "properties": {
    "tgn:hierarchy":[
        "tgn:1118909",
        "tgn:1000004",
        "tgn:7001745",
        "tgn:1000111",
        "tgn:7029392"
    ],
    "tgn:id":1118909,
    "tgn:name":"Ayagekumuhu",
    "tgn:placetype":[
        "aat:300266556"
    ]
},
  "bbox": [],
  "geometry": {"coordinates":[89.25,37.55],"type":"Point"}
}