{
  "id": 7299781,
  "type": "Feature",
  "properties": {
    "tgn:hierarchy":[
        "tgn:7299781",
        "tgn:7002836",
        "tgn:7016622",
        "tgn:1000003",
        "tgn:1000095",
        "tgn:7029392"
    ],
    "tgn:id":7299781,
    "tgn:name":"Tigaday",
    "tgn:placetype":[
        "aat:300008347"
    ]
},
  "bbox": [],
  "geometry": {"coordinates":[-18.016667,27.75],"type":"Point"}
}