<<<<<<< HEAD
{
  "id": 2762675,
  "type": "Feature",
  "properties": {
    "tgn:hierarchy":[
        "tgn:2762675",
        "tgn:1000001",
        "tgn:7012149",
        "tgn:1002883",
        "tgn:7007706",
        "tgn:7029392"
    ],
    "tgn:id":2762675,
    "tgn:name":"Westerhouse Ditch",
    "tgn:placetype":[
        "aat:300006075"
    ]
},
  "bbox": [],
  "geometry": {"coordinates":[-83.0,41.1667],"type":"Point"}
}
=======
{"geometry":{"type":"Point","coordinates":[-83.000000,41.166700]},"type":"Feature","properties":{"hierarchy":["tgn:2762675","tgn:1000001","tgn:7012149","tgn:1002883","tgn:7007706","tgn:7029392"],"placetype":["aat:300006075"],"id":2762675,"name:xx":"Westerhouse Ditch"}}
>>>>>>> 03f74aca74312dbeaf24d7e61306dd6a786dc3d0
