{
  "id": 7527209,
  "type": "Feature",
  "properties": {
    "tgn:hierarchy":[
        "tgn:7527209",
        "tgn:7001242",
        "tgn:1001059",
        "tgn:7016833",
        "tgn:7029392"
    ],
    "tgn:id":7527209,
    "tgn:name:en":"\u1e6cunn\u00e2mil",
    "tgn:placetype":[
        "aat:300008347"
    ]
},
  "bbox": [],
  "geometry": {"coordinates":[31.261829,30.836952],"type":"Point"}
}