{
  "id": 7102329,
  "type": "Feature",
  "properties": {
    "tgn:hierarchy":[
        "tgn:7102329",
        "tgn:7003692",
        "tgn:1000003",
        "tgn:7000084",
        "tgn:7029392"
    ],
    "tgn:id":7102329,
    "tgn:name":"Sailerle",
    "tgn:placetype":[
        "aat:300000206"
    ]
},
  "bbox": [],
  "geometry": {"coordinates":[9.966667,47.95],"type":"Point"}
}