<<<<<<< HEAD
{
  "id": 2255282,
  "type": "Feature",
  "properties": {
    "tgn:hierarchy":[
        "tgn:2255282",
        "tgn:1000001",
        "tgn:2001430",
        "tgn:7012149",
        "tgn:7007566",
        "tgn:7029392"
    ],
    "tgn:id":2255282,
    "tgn:name":"Cooper Tank",
    "tgn:placetype":[
        "aat:300006191"
    ]
},
  "bbox": [],
  "geometry": {"coordinates":[-103.9333,33.6],"type":"Point"}
}
=======
{"geometry":{"type":"Point","coordinates":[-103.933300,33.600000]},"type":"Feature","properties":{"hierarchy":["tgn:2255282","tgn:1000001","tgn:2001430","tgn:7012149","tgn:7007566","tgn:7029392"],"placetype":["aat:300006191"],"id":2255282,"name:xx":"Cooper Tank"}}
>>>>>>> 03f74aca74312dbeaf24d7e61306dd6a786dc3d0
