{
  "id": 2628460,
  "type": "Feature",
  "properties": {
    "tgn:hierarchy":[
        "tgn:2628460",
        "tgn:1000001",
        "tgn:7012149",
        "tgn:2001239",
        "tgn:7007523",
        "tgn:7029392"
    ],
    "tgn:id":2628460,
    "tgn:name":"Rookins",
    "tgn:placetype":[
        "aat:300008347"
    ]
},
  "bbox": [],
  "geometry": {"coordinates":[-93.75,37.8333],"type":"Point"}
}