{
  "id": 7210092,
  "type": "Feature",
  "properties": {
    "tgn:hierarchy":[
        "tgn:7210092",
        "tgn:1000003",
        "tgn:7003676",
        "tgn:7000084",
        "tgn:7029392"
    ],
    "tgn:id":7210092,
    "tgn:name":"Barbrunnen",
    "tgn:placetype":[
        "aat:300008697"
    ]
},
  "bbox": [],
  "geometry": {"coordinates":[9.433333,51.933333],"type":"Point"}
}