<<<<<<< HEAD
{
  "id": 7357289,
  "type": "Feature",
  "properties": {
    "tgn:hierarchy":[
        "tgn:7357289",
        "tgn:7005581",
        "tgn:1000001",
        "tgn:7005560",
        "tgn:7029392"
    ],
    "tgn:id":7357289,
    "tgn:name":"Corral de Duarte",
    "tgn:placetype":[
        "aat:300008347"
    ]
},
  "bbox": [],
  "geometry": {"coordinates":[-106.083333,26.833333],"type":"Point"}
}
=======
{"geometry":{"type":"Point","coordinates":[-106.083333,26.833333]},"type":"Feature","properties":{"hierarchy":["tgn:7357289","tgn:7005581","tgn:1000001","tgn:7005560","tgn:7029392"],"placetype":["aat:300008347"],"id":7357289,"name:xx":"Corral de Duarte"}}
>>>>>>> 03f74aca74312dbeaf24d7e61306dd6a786dc3d0
