{
  "id": 2139390,
  "type": "Feature",
  "properties": {
    "tgn:hierarchy":[
        "tgn:2139390",
        "tgn:1000001",
        "tgn:7012149",
        "tgn:2001451",
        "tgn:7007566",
        "tgn:7029392"
    ],
    "tgn:id":2139390,
    "tgn:name":"Aspen Peak",
    "tgn:placetype":[
        "aat:300008798"
    ]
},
  "bbox": [],
  "geometry": {"coordinates":[-106.4833,35.75],"type":"Point"}
}