{
  "id": 1116366,
  "type": "Feature",
  "properties": {
    "tgn:hierarchy":[
        "tgn:1116366",
        "tgn:7005685",
        "tgn:7005807",
        "tgn:1000001",
        "tgn:7005801",
        "tgn:7029392"
    ],
    "tgn:id":1116366,
    "tgn:name":"Gander Lake",
    "tgn:placetype":[
        "aat:300008680"
    ]
},
  "bbox": [],
  "geometry": {"coordinates":[-54.75,48.95],"type":"Point"}
}