{
  "id": 2433529,
  "type": "Feature",
  "properties": {
    "tgn:hierarchy":[
        "tgn:2433529",
        "tgn:1000001",
        "tgn:2001101",
        "tgn:7012149",
        "tgn:7007522",
        "tgn:7029392"
    ],
    "tgn:id":2433529,
    "tgn:name":"Kelly",
    "tgn:placetype":[
        "aat:300008347"
    ]
},
  "bbox": [],
  "geometry": {"coordinates":[-89.4333,31.5833],"type":"Point"}
}