{
  "id": 7390228,
  "type": "Feature",
  "properties": {
    "tgn:hierarchy":[
        "tgn:7390228",
        "tgn:7005581",
        "tgn:1000001",
        "tgn:7005560",
        "tgn:7029392"
    ],
    "tgn:id":7390228,
    "tgn:name":"Ranchos, Llanos de los",
    "tgn:placetype":[
        "aat:300008805"
    ]
},
  "bbox": [],
  "geometry": {"coordinates":[-104.383333,28.533333],"type":"Point"}
}