{
  "id": 7474870,
  "type": "Feature",
  "properties": {
    "tgn:hierarchy":[
        "tgn:7474870",
        "tgn:7487020",
        "tgn:1000004",
        "tgn:1000141",
        "tgn:7029392"
    ],
    "tgn:id":7474870,
    "tgn:name":"Toufen",
    "tgn:placetype":[
        "aat:300008347"
    ]
},
  "bbox": [],
  "geometry": {"coordinates":[120.909423,24.687533],"type":"Point"}
}