{
  "id": 7477760,
  "type": "Feature",
  "properties": {
    "tgn:hierarchy":[
        "tgn:7477760",
        "tgn:1000004",
        "tgn:7001013",
        "tgn:1000141",
        "tgn:7029392"
    ],
    "tgn:id":7477760,
    "tgn:name":"Lunping",
    "tgn:placetype":[
        "aat:300387033"
    ]
},
  "bbox": [],
  "geometry": {"coordinates":[121.160383,25.024866],"type":"Point"}
}