{
  "id": 2156532,
  "type": "Feature",
  "properties": {
    "tgn:hierarchy":[
        "tgn:2156532",
        "tgn:1000001",
        "tgn:7012149",
        "tgn:7007157",
        "tgn:1002863",
        "tgn:7029392"
    ],
    "tgn:id":2156532,
    "tgn:name":"Beartrap Spring",
    "tgn:placetype":[
        "aat:300008697"
    ]
},
  "bbox": [],
  "geometry": {"coordinates":[-120.1667,35.3167],"type":"Point"}
}