{
  "id": 7580485,
  "type": "Feature",
  "properties": {
    "tgn:hierarchy":[
        "tgn:7580485",
        "tgn:1000004",
        "tgn:7000198",
        "tgn:7000799",
        "tgn:7029392"
    ],
    "tgn:id":7580485,
    "tgn:name:en":"Thoise",
    "tgn:placetype":[
        "aat:300008347"
    ]
},
  "bbox": [],
  "geometry": {"coordinates":[77.361221,34.65679],"type":"Point"}
}