{
  "id": 2609297,
  "type": "Feature",
  "properties": {
    "tgn:hierarchy":[
        "tgn:2609297",
        "tgn:1000001",
        "tgn:2001838",
        "tgn:7012149",
        "tgn:7007825",
        "tgn:7029392"
    ],
    "tgn:id":2609297,
    "tgn:name":"Ray Branch",
    "tgn:placetype":[
        "aat:300008699"
    ]
},
  "bbox": [],
  "geometry": {"coordinates":[-86.3667,35.3667],"type":"Point"}
}