{
  "id": 2420508,
  "type": "Feature",
  "properties": {
    "tgn:hierarchy":[
        "tgn:2420508",
        "tgn:1000001",
        "tgn:7012149",
        "tgn:2001918",
        "tgn:7007825",
        "tgn:7029392"
    ],
    "tgn:id":2420508,
    "tgn:name":"Jenkins Hollow",
    "tgn:placetype":[
        "aat:300008761"
    ]
},
  "bbox": [],
  "geometry": {"coordinates":[-82.1833,36.4333],"type":"Point"}
}