{
  "id": 2618346,
  "type": "Feature",
  "properties": {
    "tgn:hierarchy":[
        "tgn:2618346",
        "tgn:1000001",
        "tgn:1002286",
        "tgn:7012149",
        "tgn:7007710",
        "tgn:7029392"
    ],
    "tgn:id":2618346,
    "tgn:name":"Right Branch Lieb Run",
    "tgn:placetype":[
        "aat:300008699"
    ]
},
  "bbox": [],
  "geometry": {"coordinates":[-77.7833,41.45],"type":"Point"}
}