{
  "id": 7389882,
  "type": "Feature",
  "properties": {
    "tgn:hierarchy":[
        "tgn:7389882",
        "tgn:7005581",
        "tgn:1000001",
        "tgn:7005560",
        "tgn:7029392"
    ],
    "tgn:id":7389882,
    "tgn:name":"Rancho Polanco",
    "tgn:placetype":[
        "aat:300008347"
    ]
},
  "bbox": [],
  "geometry": {"coordinates":[-105.483333,26.716667],"type":"Point"}
}