{
  "id": 7219098,
  "type": "Feature",
  "properties": {
    "tgn:hierarchy":[
        "tgn:7219098",
        "tgn:7011161",
        "tgn:7002674",
        "tgn:1000003",
        "tgn:1000074",
        "tgn:7029392"
    ],
    "tgn:id":7219098,
    "tgn:name":"To\u00farkou, Agk\u00e1li",
    "tgn:placetype":[
        "aat:300132317"
    ]
},
  "bbox": [],
  "geometry": {"coordinates":[26.228333,38.510278],"type":"Point"}
}