{
  "id": 7349123,
  "type": "Feature",
  "properties": {
    "tgn:hierarchy":[
        "tgn:7349123",
        "tgn:1000001",
        "tgn:7005594",
        "tgn:7005560",
        "tgn:7029392"
    ],
    "tgn:id":7349123,
    "tgn:name":"Alegre",
    "tgn:placetype":[
        "aat:300008347"
    ]
},
  "bbox": [],
  "geometry": {"coordinates":[-100.85,23.283333],"type":"Point"}
}