{
  "id": 2703016,
  "type": "Feature",
  "properties": {
    "tgn:hierarchy":[
        "tgn:2703016",
        "tgn:1000001",
        "tgn:7012149",
        "tgn:2000180",
        "tgn:7007157",
        "tgn:7029392"
    ],
    "tgn:id":2703016,
    "tgn:name":"Sultan Creek",
    "tgn:placetype":[
        "aat:300008706"
    ]
},
  "bbox": [],
  "geometry": {"coordinates":[-124.0667,41.85],"type":"Point"}
}