{
  "id": 2109751,
  "type": "Feature",
  "properties": {
    "tgn:hierarchy":[
        "tgn:2109751",
        "tgn:1000001",
        "tgn:2002133",
        "tgn:7012149",
        "tgn:7007828",
        "tgn:7029392"
    ],
    "tgn:id":2109751,
    "tgn:name":"Lake Elmore",
    "tgn:placetype":[
        "aat:300008347"
    ]
},
  "bbox": [],
  "geometry": {"coordinates":[-72.5167,44.5333],"type":"Point"}
}