{
  "id": 1138695,
  "type": "Feature",
  "properties": {
    "tgn:hierarchy":[
        "tgn:1138695",
        "tgn:1000004",
        "tgn:7011585",
        "tgn:7018214",
        "tgn:7002435",
        "tgn:7029392"
    ],
    "tgn:id":1138695,
    "tgn:name":"Zubovo",
    "tgn:placetype":[
        "aat:300008347"
    ]
},
  "bbox": [],
  "geometry": {"coordinates":[44.15,56.8667],"type":"Point"}
}