{
  "id": 2182717,
  "type": "Feature",
  "properties": {
    "tgn:hierarchy":[
        "tgn:2182717",
        "tgn:1000001",
        "tgn:7012149",
        "tgn:7022246",
        "tgn:7007825",
        "tgn:7029392"
    ],
    "tgn:id":2182717,
    "tgn:name":"Blue Spring Creek",
    "tgn:placetype":[
        "aat:300008706"
    ]
},
  "bbox": [],
  "geometry": {"coordinates":[-85.6667,35.9667],"type":"Point"}
}