{
  "id": 2737292,
  "type": "Feature",
  "properties": {
    "tgn:hierarchy":[
        "tgn:2737292",
        "tgn:1000001",
        "tgn:1002712",
        "tgn:7012149",
        "tgn:7007159",
        "tgn:7029392"
    ],
    "tgn:id":2737292,
    "tgn:name":"Twomile Brook",
    "tgn:placetype":[
        "aat:300008699"
    ]
},
  "bbox": [],
  "geometry": {"coordinates":[-73.0333,41.3333],"type":"Point"}
}