{
  "id": 7233351,
  "type": "Feature",
  "properties": {
    "tgn:hierarchy":[
        "tgn:7233351",
        "tgn:7002681",
        "tgn:7001395",
        "tgn:1000003",
        "tgn:1000074",
        "tgn:7029392"
    ],
    "tgn:id":7233351,
    "tgn:name":"Dok\u00f3s, N\u00edsos",
    "tgn:placetype":[
        "aat:300008791"
    ]
},
  "bbox": [],
  "geometry": {"coordinates":[23.316667,37.333333],"type":"Point"}
}