{
  "id": 2470885,
  "type": "Feature",
  "properties": {
    "tgn:hierarchy":[
        "tgn:2470885",
        "tgn:1000001",
        "tgn:7012149",
        "tgn:7007157",
        "tgn:1002957",
        "tgn:7029392"
    ],
    "tgn:id":2470885,
    "tgn:name":"Lost Creek",
    "tgn:placetype":[
        "aat:300008706"
    ]
},
  "bbox": [],
  "geometry": {"coordinates":[-119.9667,38.05],"type":"Point"}
}