{
  "id": 2094246,
  "type": "Feature",
  "properties": {
    "tgn:hierarchy":[
        "tgn:2094246",
        "tgn:1000001",
        "tgn:7012149",
        "tgn:1002352",
        "tgn:7007710",
        "tgn:7029392"
    ],
    "tgn:id":2094246,
    "tgn:name":"Weedville",
    "tgn:placetype":[
        "aat:300008347"
    ]
},
  "bbox": [],
  "geometry": {"coordinates":[-78.4833,41.2667],"type":"Point"}
}