{
  "id": 2553804,
  "type": "Feature",
  "properties": {
    "tgn:hierarchy":[
        "tgn:2553804",
        "tgn:1000001",
        "tgn:7012149",
        "tgn:2001886",
        "tgn:7007825",
        "tgn:7029392"
    ],
    "tgn:id":2553804,
    "tgn:name":"Oak Hill",
    "tgn:placetype":[
        "aat:300008798"
    ]
},
  "bbox": [],
  "geometry": {"coordinates":[-87.2167,35.25],"type":"Point"}
}