{
  "id": 7469317,
  "type": "Feature",
  "properties": {
    "tgn:hierarchy":[
        "tgn:7469317",
        "tgn:7001004",
        "tgn:1000004",
        "tgn:1000141",
        "tgn:7029392"
    ],
    "tgn:id":7469317,
    "tgn:name":"Shijia",
    "tgn:placetype":[
        "aat:300000745"
    ]
},
  "bbox": [],
  "geometry": {"coordinates":[120.311727,22.605798],"type":"Point"}
}