{
  "id": 1022562,
  "type": "Feature",
  "properties": {
    "tgn:hierarchy":[
        "tgn:1022562",
        "tgn:1001945",
        "tgn:1000047",
        "tgn:7002457",
        "tgn:1000002",
        "tgn:7029392"
    ],
    "tgn:id":1022562,
    "tgn:name":"Porto Ferreira",
    "tgn:placetype":[
        "aat:300008347"
    ]
},
  "bbox": [],
  "geometry": {"coordinates":[-47.4667,-21.85],"type":"Point"}
}