{
  "id": 7292034,
  "type": "Feature",
  "properties": {
    "tgn:hierarchy":[
        "tgn:7292034",
        "tgn:1001702",
        "tgn:1000049",
        "tgn:1000002",
        "tgn:7029392"
    ],
    "tgn:id":7292034,
    "tgn:name":"Fletcher, Cabo",
    "tgn:placetype":[
        "aat:300008850"
    ]
},
  "bbox": [],
  "geometry": {"coordinates":[-71.283333,-54.65],"type":"Point"}
}