{
  "id": 7308048,
  "type": "Feature",
  "properties": {
    "tgn:hierarchy":[
        "tgn:7308048",
        "tgn:1001699",
        "tgn:1000049",
        "tgn:1000002",
        "tgn:7029392"
    ],
    "tgn:id":7308048,
    "tgn:name":"Melinka, Puerto",
    "tgn:placetype":[
        "aat:300008678"
    ]
},
  "bbox": [],
  "geometry": {"coordinates":[-73.752222,-43.8975],"type":"Point"}
}