{
  "id": 1137358,
  "type": "Feature",
  "properties": {
    "tgn:hierarchy":[
        "tgn:1137358",
        "tgn:1000004",
        "tgn:7011573",
        "tgn:7018214",
        "tgn:7002435",
        "tgn:7029392"
    ],
    "tgn:id":1137358,
    "tgn:name":"Davydkovo",
    "tgn:placetype":[
        "aat:300008347"
    ]
},
  "bbox": [],
  "geometry": {"coordinates":[36.8167,56.2833],"type":"Point"}
}