{
  "id": 1029886,
  "type": "Feature",
  "properties": {
    "tgn:hierarchy":[
        "tgn:1029886",
        "tgn:7002445",
        "tgn:1000003",
        "tgn:7008157",
        "tgn:7008591",
        "tgn:7029392"
    ],
    "tgn:id":1029886,
    "tgn:name:en":"Long Sutton",
    "tgn:placetype":[
        "aat:300008347",
        "aat:300008375"
    ]
},
  "bbox": [],
  "geometry": {"coordinates":[0.133333,52.783333],"type":"Point"}
}