{
  "id": 2500725,
  "type": "Feature",
  "properties": {
    "tgn:hierarchy":[
        "tgn:2500725",
        "tgn:1000001",
        "tgn:7012149",
        "tgn:2002063",
        "tgn:7007826",
        "tgn:7029392"
    ],
    "tgn:id":2500725,
    "tgn:name":"McDowell Point",
    "tgn:placetype":[
        "aat:300008850"
    ]
},
  "bbox": [],
  "geometry": {"coordinates":[-96.7833,28.35],"type":"Point"}
}