{
  "id": 2458564,
  "type": "Feature",
  "properties": {
    "tgn:hierarchy":[
        "tgn:2458564",
        "tgn:1000001",
        "tgn:7012149",
        "tgn:7007157",
        "tgn:2000185",
        "tgn:7029392"
    ],
    "tgn:id":2458564,
    "tgn:name":"Little North Fork Gualala River",
    "tgn:placetype":[
        "aat:300008707"
    ]
},
  "bbox": [],
  "geometry": {"coordinates":[-123.55,38.8167],"type":"Point"}
}