{
  "id": 2720500,
  "type": "Feature",
  "properties": {
    "tgn:hierarchy":[
        "tgn:2720500",
        "tgn:1000001",
        "tgn:7012149",
        "tgn:2001458",
        "tgn:7007566",
        "tgn:7029392"
    ],
    "tgn:id":2720500,
    "tgn:name":"Thunderbird",
    "tgn:placetype":[
        "aat:300008347"
    ]
},
  "bbox": [],
  "geometry": {"coordinates":[-106.3833,34.5667],"type":"Point"}
}