{
  "id": 1065645,
  "type": "Feature",
  "properties": {
    "tgn:hierarchy":[
        "tgn:1065645",
        "tgn:7000189",
        "tgn:1000004",
        "tgn:1000105",
        "tgn:7029392"
    ],
    "tgn:id":1065645,
    "tgn:name":"Chandra Dighalia",
    "tgn:placetype":[
        "aat:300008347"
    ]
},
  "bbox": [],
  "geometry": {"coordinates":[89.7667,23.0667],"type":"Point"}
}