{
  "id": 2293578,
  "type": "Feature",
  "properties": {
    "tgn:hierarchy":[
        "tgn:2293578",
        "tgn:1000001",
        "tgn:7012149",
        "tgn:2002021",
        "tgn:7007826",
        "tgn:7029392"
    ],
    "tgn:id":2293578,
    "tgn:name":"Double Tank",
    "tgn:placetype":[
        "aat:300006191"
    ]
},
  "bbox": [],
  "geometry": {"coordinates":[-100.4833,29.1833],"type":"Point"}
}