{
  "id": 2621072,
  "type": "Feature",
  "properties": {
    "tgn:hierarchy":[
        "tgn:2621072",
        "tgn:1000001",
        "tgn:2002368",
        "tgn:7012149",
        "tgn:7007923",
        "tgn:7029392"
    ],
    "tgn:id":2621072,
    "tgn:name":"Road Gulch",
    "tgn:placetype":[
        "aat:300008761"
    ]
},
  "bbox": [],
  "geometry": {"coordinates":[-107.1833,41.0167],"type":"Point"}
}