{
  "id": 7231960,
  "type": "Feature",
  "properties": {
    "tgn:hierarchy":[
        "tgn:7231960",
        "tgn:7002707",
        "tgn:7002705",
        "tgn:1000003",
        "tgn:1000074",
        "tgn:7029392"
    ],
    "tgn:id":7231960,
    "tgn:name":"Koumari\u00e1",
    "tgn:placetype":[
        "aat:300008347"
    ]
},
  "bbox": [],
  "geometry": {"coordinates":[20.681667,39.545],"type":"Point"}
}