{
  "id": 2200572,
  "type": "Feature",
  "properties": {
    "tgn:hierarchy":[
        "tgn:2200572",
        "tgn:1000001",
        "tgn:2000273",
        "tgn:7012149",
        "tgn:7007240",
        "tgn:7029392"
    ],
    "tgn:id":2200572,
    "tgn:name":"Brushy Pond",
    "tgn:placetype":[
        "aat:300008680"
    ]
},
  "bbox": [],
  "geometry": {"coordinates":[-85.05,30.6833],"type":"Point"}
}