{
  "id": 2161606,
  "type": "Feature",
  "properties": {
    "tgn:hierarchy":[
        "tgn:2161606",
        "tgn:1000001",
        "tgn:7012149",
        "tgn:2001918",
        "tgn:7007825",
        "tgn:7029392"
    ],
    "tgn:id":2161606,
    "tgn:name":"Belle Brook Estates",
    "tgn:placetype":[
        "aat:300008347"
    ]
},
  "bbox": [],
  "geometry": {"coordinates":[-82.1833,36.55],"type":"Point"}
}