{
  "id": 7193329,
  "type": "Feature",
  "properties": {
    "tgn:hierarchy":[
        "tgn:7193329",
        "tgn:1000003",
        "tgn:7000094",
        "tgn:7000084",
        "tgn:7029392"
    ],
    "tgn:id":7193329,
    "tgn:name":"F\u00f6rsterei Flattenwerder",
    "tgn:placetype":[
        "aat:300004792"
    ]
},
  "bbox": [],
  "geometry": {"coordinates":[14.35,53.433333],"type":"Point"}
}