{
  "id": 1013301,
  "type": "Feature",
  "properties": {
    "tgn:hierarchy":[
        "tgn:1013301",
        "tgn:7005694",
        "tgn:7005685",
        "tgn:1000001",
        "tgn:7029392"
    ],
    "tgn:id":1013301,
    "tgn:name":"Smoky Lake",
    "tgn:placetype":[
        "aat:300008347"
    ]
},
  "bbox": [],
  "geometry": {"coordinates":[-112.4333,54.1333],"type":"Point"}
}