{
  "id": 2394137,
  "type": "Feature",
  "properties": {
    "tgn:hierarchy":[
        "tgn:2394137",
        "tgn:1000001",
        "tgn:7012149",
        "tgn:2001850",
        "tgn:7007825",
        "tgn:7029392"
    ],
    "tgn:id":2394137,
    "tgn:name":"Hogan Hollow",
    "tgn:placetype":[
        "aat:300008761"
    ]
},
  "bbox": [],
  "geometry": {"coordinates":[-85.3167,36.55],"type":"Point"}
}