{
  "id": 2179940,
  "type": "Feature",
  "properties": {
    "tgn:hierarchy":[
        "tgn:2179940",
        "tgn:7006450",
        "tgn:1000001",
        "tgn:7012149",
        "tgn:2000086",
        "tgn:7029392"
    ],
    "tgn:id":2179940,
    "tgn:name":"Bligh Reef",
    "tgn:placetype":[
        "aat:300132348"
    ]
},
  "bbox": [],
  "geometry": {"coordinates":[-146.8667,60.8333],"type":"Point"}
}