{
  "id": 7276157,
  "type": "Feature",
  "properties": {
    "tgn:hierarchy":[
        "tgn:7276157",
        "tgn:1001657",
        "tgn:1000049",
        "tgn:1000002",
        "tgn:7029392"
    ],
    "tgn:id":7276157,
    "tgn:name":"Toro, Cerro del",
    "tgn:placetype":[
        "aat:300008795"
    ]
},
  "bbox": [],
  "geometry": {"coordinates":[-71.141389,-30.251944],"type":"Point"}
}