{
  "id": 7285875,
  "type": "Feature",
  "properties": {
    "tgn:hierarchy":[
        "tgn:7285875",
        "tgn:1001657",
        "tgn:1000049",
        "tgn:1000002",
        "tgn:7029392"
    ],
    "tgn:id":7285875,
    "tgn:name":"Pichasca, Cerro de la",
    "tgn:placetype":[
        "aat:300008795"
    ]
},
  "bbox": [],
  "geometry": {"coordinates":[-70.833333,-30.316667],"type":"Point"}
}