{
  "id": 7326538,
  "type": "Feature",
  "properties": {
    "tgn:hierarchy":[
        "tgn:7326538",
        "tgn:7002826",
        "tgn:7001158",
        "tgn:1000003",
        "tgn:1000095",
        "tgn:7029392"
    ],
    "tgn:id":7326538,
    "tgn:name":"Peranzanes",
    "tgn:placetype":[
        "aat:300008347"
    ]
},
  "bbox": [],
  "geometry": {"coordinates":[-6.633333,42.883333],"type":"Point"}
}