<<<<<<< HEAD
{
  "id": 2768558,
  "type": "Feature",
  "properties": {
    "tgn:hierarchy":[
        "tgn:2768558",
        "tgn:1000001",
        "tgn:7012149",
        "tgn:1002603",
        "tgn:7007520",
        "tgn:7029392"
    ],
    "tgn:id":2768558,
    "tgn:name":"Whitewood Lakes",
    "tgn:placetype":[
        "aat:300008680"
    ]
},
  "bbox": [],
  "geometry": {"coordinates":[-83.8667,42.4333],"type":"Point"}
}
=======
{"geometry":{"type":"Point","coordinates":[-83.866700,42.433300]},"type":"Feature","properties":{"hierarchy":["tgn:2768558","tgn:1000001","tgn:7012149","tgn:1002603","tgn:7007520","tgn:7029392"],"placetype":["aat:300008680"],"id":2768558,"name:xx":"Whitewood Lakes"}}
>>>>>>> 03f74aca74312dbeaf24d7e61306dd6a786dc3d0
