<<<<<<< HEAD
{
  "id": 7356555,
  "type": "Feature",
  "properties": {
    "tgn:hierarchy":[
        "tgn:7356555",
        "tgn:1000001",
        "tgn:7005595",
        "tgn:7005560",
        "tgn:7029392"
    ],
    "tgn:id":7356555,
    "tgn:name":"Camotete",
    "tgn:placetype":[
        "aat:300008347"
    ]
},
  "bbox": [],
  "geometry": {"coordinates":[-107.55,25.3],"type":"Point"}
}
=======
{"geometry":{"type":"Point","coordinates":[-107.550000,25.300000]},"type":"Feature","properties":{"hierarchy":["tgn:7356555","tgn:1000001","tgn:7005595","tgn:7005560","tgn:7029392"],"placetype":["aat:300008347"],"id":7356555,"name:xx":"Camotete"}}
>>>>>>> 03f74aca74312dbeaf24d7e61306dd6a786dc3d0
