{
  "id": 2154531,
  "type": "Feature",
  "properties": {
    "tgn:hierarchy":[
        "tgn:2154531",
        "tgn:1000001",
        "tgn:2001411",
        "tgn:7012149",
        "tgn:7007526",
        "tgn:7029392"
    ],
    "tgn:id":2154531,
    "tgn:name":"Bear Creek Summit",
    "tgn:placetype":[
        "aat:300008798"
    ]
},
  "bbox": [],
  "geometry": {"coordinates":[-115.4667,41.8167],"type":"Point"}
}