{
  "id": 1019267,
  "type": "Feature",
  "properties": {
    "tgn:hierarchy":[
        "tgn:1019267",
        "tgn:1001160",
        "tgn:7006477",
        "tgn:1000002",
        "tgn:7029392"
    ],
    "tgn:id":1019267,
    "tgn:name":"Carhu\u00e9",
    "tgn:placetype":[
        "aat:300008347"
    ]
},
  "bbox": [],
  "geometry": {"coordinates":[-62.75,-37.1667],"type":"Point"}
}