<<<<<<< HEAD
{
  "id": 7478324,
  "type": "Feature",
  "properties": {
    "tgn:hierarchy":[
        "tgn:7478324",
        "tgn:1000004",
        "tgn:7471332",
        "tgn:1000141",
        "tgn:7029392"
    ],
    "tgn:id":7478324,
    "tgn:name":"Bafenliao",
    "tgn:placetype":[
        "aat:300008777"
    ]
},
  "bbox": [],
  "geometry": {"coordinates":[120.999,24.718964],"type":"Point"}
}
=======
{"geometry":{"type":"Point","coordinates":[120.999000,24.718964]},"type":"Feature","properties":{"hierarchy":["tgn:7478324","tgn:1000004","tgn:7471332","tgn:1000141","tgn:7029392"],"placetype":["aat:300008777"],"id":7478324,"name:xx":"Bafenliao"}}
>>>>>>> 03f74aca74312dbeaf24d7e61306dd6a786dc3d0
