{
  "id": 2357596,
  "type": "Feature",
  "properties": {
    "tgn:hierarchy":[
        "tgn:2357596",
        "tgn:1000001",
        "tgn:7012149",
        "tgn:2001911",
        "tgn:7007825",
        "tgn:7029392"
    ],
    "tgn:id":2357596,
    "tgn:name":"Gowen Knob",
    "tgn:placetype":[
        "aat:300008798"
    ]
},
  "bbox": [],
  "geometry": {"coordinates":[-86.2333,35.75],"type":"Point"}
}