{
  "id": 7502584,
  "type": "Feature",
  "properties": {
    "tgn:hierarchy":[
        "tgn:7502584",
        "tgn:7488858",
        "tgn:1000004",
        "tgn:1000141",
        "tgn:7029392"
    ],
    "tgn:id":7502584,
    "tgn:name":"Shili Xi",
    "tgn:placetype":[
        "aat:300008699"
    ]
},
  "bbox": [],
  "geometry": {"coordinates":[121.125833,23.945278],"type":"Point"}
}