{
  "id": 2134505,
  "type": "Feature",
  "properties": {
    "tgn:hierarchy":[
        "tgn:2134505",
        "tgn:1000001",
        "tgn:2001945",
        "tgn:7012149",
        "tgn:7007826",
        "tgn:7029392"
    ],
    "tgn:id":2134505,
    "tgn:name":"Ansley Place",
    "tgn:placetype":[
        "aat:300008347"
    ]
},
  "bbox": [],
  "geometry": {"coordinates":[-103.1333,30.2333],"type":"Point"}
}