{
  "id": 2295014,
  "type": "Feature",
  "properties": {
    "tgn:hierarchy":[
        "tgn:2295014",
        "tgn:1000001",
        "tgn:7012149",
        "tgn:2002118",
        "tgn:7007827",
        "tgn:7029392"
    ],
    "tgn:id":2295014,
    "tgn:name":"Draper Irrigation Company Ditch",
    "tgn:placetype":[
        "aat:300006075"
    ]
},
  "bbox": [],
  "geometry": {"coordinates":[-111.8167,40.5333],"type":"Point"}
}