{
  "id": 7450992,
  "type": "Feature",
  "properties": {
    "tgn:hierarchy":[
        "tgn:7450992",
        "tgn:7002448",
        "tgn:7019216",
        "tgn:1000003",
        "tgn:7008591",
        "tgn:7029392"
    ],
    "tgn:id":7450992,
    "tgn:name:en":"Garvagh",
    "tgn:placetype":[
        "aat:300008347"
    ]
},
  "bbox": [],
  "geometry": {"coordinates":[-6.666667,54.983333],"type":"Point"}
}