<<<<<<< HEAD
{
  "id": 2251299,
  "type": "Feature",
  "properties": {
    "tgn:hierarchy":[
        "tgn:2251299",
        "tgn:1000001",
        "tgn:7012149",
        "tgn:2002169",
        "tgn:7007919",
        "tgn:7029392"
    ],
    "tgn:id":2251299,
    "tgn:name":"Combs Cave Number 1",
    "tgn:placetype":[
        "aat:300008746"
    ]
},
  "bbox": [],
  "geometry": {"coordinates":[-83.1,36.6167],"type":"Point"}
}
=======
{"geometry":{"type":"Point","coordinates":[-83.100000,36.616700]},"type":"Feature","properties":{"hierarchy":["tgn:2251299","tgn:1000001","tgn:7012149","tgn:2002169","tgn:7007919","tgn:7029392"],"placetype":["aat:300008746"],"id":2251299,"name:xx":"Combs Cave Number 1"}}
>>>>>>> 03f74aca74312dbeaf24d7e61306dd6a786dc3d0
