{
  "id": 2592139,
  "type": "Feature",
  "properties": {
    "tgn:hierarchy":[
        "tgn:2592139",
        "tgn:1000001",
        "tgn:2001812",
        "tgn:7012149",
        "tgn:7007713",
        "tgn:7029392"
    ],
    "tgn:id":2592139,
    "tgn:name":"Pontoon Creek",
    "tgn:placetype":[
        "aat:300008706"
    ]
},
  "bbox": [],
  "geometry": {"coordinates":[-99.3833,43.8833],"type":"Point"}
}