{
  "id": 2214579,
  "type": "Feature",
  "properties": {
    "tgn:hierarchy":[
        "tgn:2214579",
        "tgn:1000001",
        "tgn:7012149",
        "tgn:1002921",
        "tgn:7007526",
        "tgn:7029392"
    ],
    "tgn:id":2214579,
    "tgn:name":"Caldwell Ravine",
    "tgn:placetype":[
        "aat:300008761"
    ]
},
  "bbox": [],
  "geometry": {"coordinates":[-119.6667,39.3833],"type":"Point"}
}