{
  "id": 2414077,
  "type": "Feature",
  "properties": {
    "tgn:hierarchy":[
        "tgn:2414077",
        "tgn:1000001",
        "tgn:7012149",
        "tgn:2001708",
        "tgn:7007708",
        "tgn:7029392"
    ],
    "tgn:id":2414077,
    "tgn:name":"Iron King Mine",
    "tgn:placetype":[
        "aat:300000390"
    ]
},
  "bbox": [],
  "geometry": {"coordinates":[-118.9167,44.35],"type":"Point"}
}