{
  "id": 2769415,
  "type": "Feature",
  "properties": {
    "tgn:hierarchy":[
        "tgn:2769415",
        "tgn:2002142",
        "tgn:1000001",
        "tgn:7012149",
        "tgn:7007919",
        "tgn:7029392"
    ],
    "tgn:id":2769415,
    "tgn:name":"Wida",
    "tgn:placetype":[
        "aat:300008347"
    ]
},
  "bbox": [],
  "geometry": {"coordinates":[-79.0833,38.0167],"type":"Point"}
}