{
  "id": 2554837,
  "type": "Feature",
  "properties": {
    "tgn:hierarchy":[
        "tgn:2554837",
        "tgn:1000001",
        "tgn:7012149",
        "tgn:7007157",
        "tgn:1002857",
        "tgn:7029392"
    ],
    "tgn:id":2554837,
    "tgn:name":"Oasis of Mara",
    "tgn:placetype":[
        "aat:300008697"
    ]
},
  "bbox": [],
  "geometry": {"coordinates":[-116.0333,35.1167],"type":"Point"}
}