{
  "id": 7290987,
  "type": "Feature",
  "properties": {
    "tgn:hierarchy":[
        "tgn:7290987",
        "tgn:1001768",
        "tgn:1000049",
        "tgn:1000002",
        "tgn:7029392"
    ],
    "tgn:id":7290987,
    "tgn:name":"Curaumilla",
    "tgn:placetype":[
        "aat:300000206"
    ]
},
  "bbox": [],
  "geometry": {"coordinates":[-71.716667,-33.116667],"type":"Point"}
}