{
  "id": 2427938,
  "type": "Feature",
  "properties": {
    "tgn:hierarchy":[
        "tgn:2427938",
        "tgn:1000001",
        "tgn:7012149",
        "tgn:2002122",
        "tgn:7007827",
        "tgn:7029392"
    ],
    "tgn:id":2427938,
    "tgn:name":"Joyce Lake",
    "tgn:placetype":[
        "aat:300008680"
    ]
},
  "bbox": [],
  "geometry": {"coordinates":[-111.0167,40.8667],"type":"Point"}
}