<<<<<<< HEAD
{
  "id": 2401733,
  "type": "Feature",
  "properties": {
    "tgn:hierarchy":[
        "tgn:2401733",
        "tgn:1000001",
        "tgn:2000949",
        "tgn:7012149",
        "tgn:7007520",
        "tgn:7029392"
    ],
    "tgn:id":2401733,
    "tgn:name":"Horseshoe Lake",
    "tgn:placetype":[
        "aat:300008680"
    ]
},
  "bbox": [],
  "geometry": {"coordinates":[-85.8667,44.7667],"type":"Point"}
}
=======
{"geometry":{"type":"Point","coordinates":[-85.866700,44.766700]},"type":"Feature","properties":{"hierarchy":["tgn:2401733","tgn:1000001","tgn:2000949","tgn:7012149","tgn:7007520","tgn:7029392"],"placetype":["aat:300008680"],"id":2401733,"name:xx":"Horseshoe Lake"}}
>>>>>>> 03f74aca74312dbeaf24d7e61306dd6a786dc3d0
