{
  "id": 7563283,
  "type": "Feature",
  "properties": {
    "tgn:hierarchy":[
        "tgn:7563283",
        "tgn:1000004",
        "tgn:7000198",
        "tgn:7016722",
        "tgn:7029392"
    ],
    "tgn:id":7563283,
    "tgn:name:en":"Dary\u0101pur Chandai",
    "tgn:placetype":[
        "aat:300008347"
    ]
},
  "bbox": [],
  "geometry": {"coordinates":[79.9411,27.0646],"type":"Point"}
}