{
  "id": 2323020,
  "type": "Feature",
  "properties": {
    "tgn:hierarchy":[
        "tgn:2323020",
        "tgn:1000001",
        "tgn:7012149",
        "tgn:7007157",
        "tgn:1002859",
        "tgn:7029392"
    ],
    "tgn:id":2323020,
    "tgn:name":"Farallones, Gulf of the",
    "tgn:placetype":[
        "aat:300132316"
    ]
},
  "bbox": [],
  "geometry": {"coordinates":[-122.75,37.75],"type":"Point"}
}