{
  "id": 2045961,
  "type": "Feature",
  "properties": {
    "tgn:hierarchy":[
        "tgn:2045961",
        "tgn:1000001",
        "tgn:7016102",
        "tgn:7012149",
        "tgn:7007516",
        "tgn:7029392"
    ],
    "tgn:id":2045961,
    "tgn:name":"Aldino",
    "tgn:placetype":[
        "aat:300008347"
    ]
},
  "bbox": [],
  "geometry": {"coordinates":[-76.1833,39.55],"type":"Point"}
}