<<<<<<< HEAD
{
  "id": 2407290,
  "type": "Feature",
  "properties": {
    "tgn:hierarchy":[
        "tgn:2407290",
        "tgn:1002366",
        "tgn:1000001",
        "tgn:7012149",
        "tgn:7007159",
        "tgn:7029392"
    ],
    "tgn:id":2407290,
    "tgn:name":"Hunting Ridge",
    "tgn:placetype":[
        "aat:300008347"
    ]
},
  "bbox": [],
  "geometry": {"coordinates":[-73.5667,41.1333],"type":"Point"}
}
=======
{"geometry":{"type":"Point","coordinates":[-73.566700,41.133300]},"type":"Feature","properties":{"hierarchy":["tgn:2407290","tgn:1002366","tgn:1000001","tgn:7012149","tgn:7007159","tgn:7029392"],"placetype":["aat:300008347"],"id":2407290,"name:xx":"Hunting Ridge"}}
>>>>>>> 03f74aca74312dbeaf24d7e61306dd6a786dc3d0
