{
  "id": 2410166,
  "type": "Feature",
  "properties": {
    "tgn:hierarchy":[
        "tgn:2410166",
        "tgn:2002365",
        "tgn:1000001",
        "tgn:7012149",
        "tgn:7007923",
        "tgn:7029392"
    ],
    "tgn:id":2410166,
    "tgn:name":"Independence Mine",
    "tgn:placetype":[
        "aat:300000390"
    ]
},
  "bbox": [],
  "geometry": {"coordinates":[-106.1833,41.2667],"type":"Point"}
}