{
  "id": 2422959,
  "type": "Feature",
  "properties": {
    "tgn:hierarchy":[
        "tgn:2422959",
        "tgn:1000001",
        "tgn:7012149",
        "tgn:2001709",
        "tgn:7007708",
        "tgn:7029392"
    ],
    "tgn:id":2422959,
    "tgn:name":"Joe Huff Spring",
    "tgn:placetype":[
        "aat:300008697"
    ]
},
  "bbox": [],
  "geometry": {"coordinates":[-118.6833,42.5167],"type":"Point"}
}