{
  "id": 2350626,
  "type": "Feature",
  "properties": {
    "tgn:hierarchy":[
        "tgn:2350626",
        "tgn:2000999",
        "tgn:1000001",
        "tgn:7012149",
        "tgn:7007521",
        "tgn:7029392"
    ],
    "tgn:id":2350626,
    "tgn:name":"Glacier Lake",
    "tgn:placetype":[
        "aat:300008680"
    ]
},
  "bbox": [],
  "geometry": {"coordinates":[-93.2167,46.7833],"type":"Point"}
}