{
  "id": 2666948,
  "type": "Feature",
  "properties": {
    "tgn:hierarchy":[
        "tgn:2666948",
        "tgn:1000001",
        "tgn:7012149",
        "tgn:2000234",
        "tgn:7007158",
        "tgn:7029392"
    ],
    "tgn:id":2666948,
    "tgn:name":"Skein Mesa",
    "tgn:placetype":[
        "aat:300008798"
    ]
},
  "bbox": [],
  "geometry": {"coordinates":[-108.8667,38.25],"type":"Point"}
}