{
  "id": 7396001,
  "type": "Feature",
  "properties": {
    "tgn:hierarchy":[
        "tgn:7396001",
        "tgn:1000001",
        "tgn:7005597",
        "tgn:7005560",
        "tgn:7029392"
    ],
    "tgn:id":7396001,
    "tgn:name":"San Felipe",
    "tgn:placetype":[
        "aat:300266554",
        "aat:300008699"
    ]
},
  "bbox": [],
  "geometry": {"coordinates":[-99.233333,23.766667],"type":"Point"}
}