{
  "id": 2706294,
  "type": "Feature",
  "properties": {
    "tgn:hierarchy":[
        "tgn:2706294",
        "tgn:1000001",
        "tgn:7012149",
        "tgn:2001068",
        "tgn:7007521",
        "tgn:7029392"
    ],
    "tgn:id":2706294,
    "tgn:name":"Swamp Lake",
    "tgn:placetype":[
        "aat:300008680"
    ]
},
  "bbox": [],
  "geometry": {"coordinates":[-93.5333,44.6667],"type":"Point"}
}