{
  "id": 2688500,
  "type": "Feature",
  "properties": {
    "tgn:hierarchy":[
        "tgn:2688500",
        "tgn:1000001",
        "tgn:7012149",
        "tgn:7007158",
        "tgn:2000244",
        "tgn:7029392"
    ],
    "tgn:id":2688500,
    "tgn:name":"Spruce Lawn Ditch",
    "tgn:placetype":[
        "aat:300006075"
    ]
},
  "bbox": [],
  "geometry": {"coordinates":[-106.0667,37.4833],"type":"Point"}
}