{
  "id": 7457058,
  "type": "Feature",
  "properties": {
    "tgn:hierarchy":[
        "tgn:7457058",
        "tgn:5000432",
        "tgn:7002444",
        "tgn:1000003",
        "tgn:7008591",
        "tgn:7029392"
    ],
    "tgn:id":7457058,
    "tgn:name:en":"Marnoch",
    "tgn:placetype":[
        "aat:300008347"
    ]
},
  "bbox": [],
  "geometry": {"coordinates":[-2.666667,57.533333],"type":"Point"}
}