{
  "id": 2225646,
  "type": "Feature",
  "properties": {
    "tgn:hierarchy":[
        "tgn:2225646",
        "tgn:1000001",
        "tgn:7012149",
        "tgn:2001715",
        "tgn:7007708",
        "tgn:7029392"
    ],
    "tgn:id":2225646,
    "tgn:name":"Cat Butte",
    "tgn:placetype":[
        "aat:300008798"
    ]
},
  "bbox": [],
  "geometry": {"coordinates":[-119.6333,42.3167],"type":"Point"}
}