{
  "id": 2533290,
  "type": "Feature",
  "properties": {
    "tgn:hierarchy":[
        "tgn:2533290",
        "tgn:1000001",
        "tgn:7012149",
        "tgn:1003002",
        "tgn:7007922",
        "tgn:7029392"
    ],
    "tgn:id":2533290,
    "tgn:name":"Muskego Canal",
    "tgn:placetype":[
        "aat:300006075"
    ]
},
  "bbox": [],
  "geometry": {"coordinates":[-88.1333,42.8333],"type":"Point"}
}