<<<<<<< HEAD
{
  "id": 2765110,
  "type": "Feature",
  "properties": {
    "tgn:hierarchy":[
        "tgn:2765110",
        "tgn:1000001",
        "tgn:7012149",
        "tgn:2001770",
        "tgn:7007712",
        "tgn:7029392"
    ],
    "tgn:id":2765110,
    "tgn:name":"Whispering Hills",
    "tgn:placetype":[
        "aat:300008347"
    ]
},
  "bbox": [],
  "geometry": {"coordinates":[-81.05,34.9],"type":"Point"}
}
=======
{"geometry":{"type":"Point","coordinates":[-81.050000,34.900000]},"type":"Feature","properties":{"hierarchy":["tgn:2765110","tgn:1000001","tgn:7012149","tgn:2001770","tgn:7007712","tgn:7029392"],"placetype":["aat:300008347"],"id":2765110,"name:xx":"Whispering Hills"}}
>>>>>>> 03f74aca74312dbeaf24d7e61306dd6a786dc3d0
