{
  "id": 7429640,
  "type": "Feature",
  "properties": {
    "tgn:hierarchy":[
        "tgn:7429640",
        "tgn:7005583",
        "tgn:1000001",
        "tgn:7005560",
        "tgn:7029392"
    ],
    "tgn:id":7429640,
    "tgn:name":"Los Altares",
    "tgn:placetype":[
        "aat:300008347"
    ]
},
  "bbox": [],
  "geometry": {"coordinates":[-104.75,24.15],"type":"Point"}
}