{
  "id": 7363721,
  "type": "Feature",
  "properties": {
    "tgn:hierarchy":[
        "tgn:7363721",
        "tgn:7005580",
        "tgn:1000001",
        "tgn:7005560",
        "tgn:7029392"
    ],
    "tgn:id":7363721,
    "tgn:name":"El Gavil\u00e1n",
    "tgn:placetype":[
        "aat:300008347"
    ]
},
  "bbox": [],
  "geometry": {"coordinates":[-93.45,16.833333],"type":"Point"}
}