{
  "id": 2257676,
  "type": "Feature",
  "properties": {
    "tgn:hierarchy":[
        "tgn:2257676",
        "tgn:1000001",
        "tgn:7012149",
        "tgn:1002553",
        "tgn:7007920",
        "tgn:7029392"
    ],
    "tgn:id":2257676,
    "tgn:name":"Corral Creek",
    "tgn:placetype":[
        "aat:300008706"
    ]
},
  "bbox": [],
  "geometry": {"coordinates":[-121.05,47.3167],"type":"Point"}
}