<<<<<<< HEAD
{
  "id": 2257676,
  "type": "Feature",
  "properties": {
    "tgn:hierarchy":[
        "tgn:2257676",
        "tgn:1000001",
        "tgn:7012149",
        "tgn:1002553",
        "tgn:7007920",
        "tgn:7029392"
    ],
    "tgn:id":2257676,
    "tgn:name":"Corral Creek",
    "tgn:placetype":[
        "aat:300008706"
    ]
},
  "bbox": [],
  "geometry": {"coordinates":[-121.05,47.3167],"type":"Point"}
}
=======
{"geometry":{"type":"Point","coordinates":[-121.050000,47.316700]},"type":"Feature","properties":{"hierarchy":["tgn:2257676","tgn:1000001","tgn:7012149","tgn:1002553","tgn:7007920","tgn:7029392"],"placetype":["aat:300008706"],"id":2257676,"name:xx":"Corral Creek"}}
>>>>>>> 03f74aca74312dbeaf24d7e61306dd6a786dc3d0
