{
  "id": 7438299,
  "type": "Feature",
  "properties": {
    "tgn:hierarchy":[
        "tgn:7438299",
        "tgn:7005583",
        "tgn:1000001",
        "tgn:7005560",
        "tgn:7029392"
    ],
    "tgn:id":7438299,
    "tgn:name":"Sauz",
    "tgn:placetype":[
        "aat:300008347"
    ]
},
  "bbox": [],
  "geometry": {"coordinates":[-105.933333,25.533333],"type":"Point"}
}