{
  "id": 1038529,
  "type": "Feature",
  "properties": {
    "tgn:hierarchy":[
        "tgn:1038529",
        "tgn:7003692",
        "tgn:1000003",
        "tgn:7000084",
        "tgn:7029392"
    ],
    "tgn:id":1038529,
    "tgn:name":"Binau",
    "tgn:placetype":[
        "aat:300008347"
    ]
},
  "bbox": [],
  "geometry": {"coordinates":[9.058056,49.368333],"type":"Point"}
}