{
  "id": 2495731,
  "type": "Feature",
  "properties": {
    "tgn:hierarchy":[
        "tgn:2495731",
        "tgn:1000001",
        "tgn:7012149",
        "tgn:2001888",
        "tgn:7007825",
        "tgn:7029392"
    ],
    "tgn:id":2495731,
    "tgn:name":"Mason Branch",
    "tgn:placetype":[
        "aat:300008699"
    ]
},
  "bbox": [],
  "geometry": {"coordinates":[-86.5333,35.0333],"type":"Point"}
}