{
  "id": 2581096,
  "type": "Feature",
  "properties": {
    "tgn:hierarchy":[
        "tgn:2581096",
        "tgn:1000001",
        "tgn:7012149",
        "tgn:2001240",
        "tgn:7007523",
        "tgn:7029392"
    ],
    "tgn:id":2581096,
    "tgn:name":"Pikes Peak",
    "tgn:placetype":[
        "aat:300008798"
    ]
},
  "bbox": [],
  "geometry": {"coordinates":[-90.2333,37.9833],"type":"Point"}
}