{
  "id": 1034277,
  "type": "Feature",
  "properties": {
    "tgn:hierarchy":[
        "tgn:1034277",
        "tgn:1000003",
        "tgn:7001097",
        "tgn:1000070",
        "tgn:7029392"
    ],
    "tgn:id":1034277,
    "tgn:name":"Marly",
    "tgn:placetype":[
        "aat:300008347"
    ]
},
  "bbox": [],
  "geometry": {"coordinates":[3.55,50.35],"type":"Point"}
}