{
  "id": 2733439,
  "type": "Feature",
  "properties": {
    "tgn:hierarchy":[
        "tgn:2733439",
        "tgn:1000001",
        "tgn:7012149",
        "tgn:2002069",
        "tgn:7007826",
        "tgn:7029392"
    ],
    "tgn:id":2733439,
    "tgn:name":"Turkey Valley",
    "tgn:placetype":[
        "aat:300386845"
    ]
},
  "bbox": [],
  "geometry": {"coordinates":[-98.5167,31.1667],"type":"Point"}
}