<<<<<<< HEAD
{
  "id": 2763393,
  "type": "Feature",
  "properties": {
    "tgn:hierarchy":[
        "tgn:2763393",
        "tgn:1000001",
        "tgn:1002724",
        "tgn:7012149",
        "tgn:7007517",
        "tgn:7029392"
    ],
    "tgn:id":2763393,
    "tgn:name":"Wetherells Pond",
    "tgn:placetype":[
        "aat:300008680"
    ]
},
  "bbox": [],
  "geometry": {"coordinates":[-71.3333,42.0],"type":"Point"}
}
=======
{"geometry":{"type":"Point","coordinates":[-71.333300,42.000000]},"type":"Feature","properties":{"hierarchy":["tgn:2763393","tgn:1000001","tgn:1002724","tgn:7012149","tgn:7007517","tgn:7029392"],"placetype":["aat:300008680"],"id":2763393,"name:xx":"Wetherells Pond"}}
>>>>>>> 03f74aca74312dbeaf24d7e61306dd6a786dc3d0
