{
  "id": 2646972,
  "type": "Feature",
  "properties": {
    "tgn:hierarchy":[
        "tgn:2646972",
        "tgn:1000001",
        "tgn:1002260",
        "tgn:7012149",
        "tgn:7007920",
        "tgn:7029392"
    ],
    "tgn:id":2646972,
    "tgn:name":"Schaefer Lake",
    "tgn:placetype":[
        "aat:300008680"
    ]
},
  "bbox": [],
  "geometry": {"coordinates":[-120.8333,47.95],"type":"Point"}
}