<<<<<<< HEAD
{
  "id": 2330242,
  "type": "Feature",
  "properties": {
    "tgn:hierarchy":[
        "tgn:2330242",
        "tgn:1000001",
        "tgn:2001429",
        "tgn:7012149",
        "tgn:7007566",
        "tgn:7029392"
    ],
    "tgn:id":2330242,
    "tgn:name":"Flanigan Cienega",
    "tgn:placetype":[
        "aat:300008905"
    ]
},
  "bbox": [],
  "geometry": {"coordinates":[-109.0167,33.8833],"type":"Point"}
}
=======
{"geometry":{"type":"Point","coordinates":[-109.016700,33.883300]},"type":"Feature","properties":{"hierarchy":["tgn:2330242","tgn:1000001","tgn:2001429","tgn:7012149","tgn:7007566","tgn:7029392"],"placetype":["aat:300008905"],"id":2330242,"name:xx":"Flanigan Cienega"}}
>>>>>>> 03f74aca74312dbeaf24d7e61306dd6a786dc3d0
