{
  "id": 7093914,
  "type": "Feature",
  "properties": {
    "tgn:hierarchy":[
        "tgn:7093914",
        "tgn:7003669",
        "tgn:1000003",
        "tgn:7000084",
        "tgn:7029392"
    ],
    "tgn:id":7093914,
    "tgn:name":"Schwarzwald",
    "tgn:placetype":[
        "aat:300008863"
    ]
},
  "bbox": [],
  "geometry": {"coordinates":[11.383333,49.716667],"type":"Point"}
}