{
  "id": 2436836,
  "type": "Feature",
  "properties": {
    "tgn:hierarchy":[
        "tgn:2436836",
        "tgn:1000001",
        "tgn:7012149",
        "tgn:7013941",
        "tgn:7007568",
        "tgn:7029392"
    ],
    "tgn:id":2436836,
    "tgn:name":"Kildare",
    "tgn:placetype":[
        "aat:300008347"
    ]
},
  "bbox": [],
  "geometry": {"coordinates":[-74.5167,44.3167],"type":"Point"}
}