{
  "id": 7223899,
  "type": "Feature",
  "properties": {
    "tgn:hierarchy":[
        "tgn:7223899",
        "tgn:7002715",
        "tgn:7002731",
        "tgn:1000003",
        "tgn:1000074",
        "tgn:7029392"
    ],
    "tgn:id":7223899,
    "tgn:name":"Thessalon\u00edkis, K\u00f3lpos",
    "tgn:placetype":[
        "aat:300132316"
    ]
},
  "bbox": [],
  "geometry": {"coordinates":[22.800235,40.516827],"type":"Point"}
}