{
  "id": 2288508,
  "type": "Feature",
  "properties": {
    "tgn:hierarchy":[
        "tgn:2288508",
        "tgn:7006450",
        "tgn:1000001",
        "tgn:7012149",
        "tgn:2000086",
        "tgn:7029392"
    ],
    "tgn:id":2288508,
    "tgn:name":"Disk Island",
    "tgn:placetype":[
        "aat:300008791"
    ]
},
  "bbox": [],
  "geometry": {"coordinates":[-147.65,60.4833],"type":"Point"}
}