{
  "id": 7523033,
  "type": "Feature",
  "properties": {
    "tgn:hierarchy":[
        "tgn:7523033",
        "tgn:7001242",
        "tgn:7001311",
        "tgn:7016833",
        "tgn:7029392"
    ],
    "tgn:id":7523033,
    "tgn:name:en":"Dirrah, Ra's",
    "tgn:placetype":[
        "aat:300386846"
    ]
},
  "bbox": [],
  "geometry": {"coordinates":[34.986001,24.894798],"type":"Point"}
}