<<<<<<< HEAD
{
  "id": 2401199,
  "type": "Feature",
  "properties": {
    "tgn:hierarchy":[
        "tgn:2401199",
        "tgn:1000001",
        "tgn:7012149",
        "tgn:2000982",
        "tgn:7007520",
        "tgn:7029392"
    ],
    "tgn:id":2401199,
    "tgn:name":"Horsehead Lake",
    "tgn:placetype":[
        "aat:300008680"
    ]
},
  "bbox": [],
  "geometry": {"coordinates":[-84.2,45.1833],"type":"Point"}
}
=======
{"geometry":{"type":"Point","coordinates":[-84.200000,45.183300]},"type":"Feature","properties":{"hierarchy":["tgn:2401199","tgn:1000001","tgn:7012149","tgn:2000982","tgn:7007520","tgn:7029392"],"placetype":["aat:300008680"],"id":2401199,"name:xx":"Horsehead Lake"}}
>>>>>>> 03f74aca74312dbeaf24d7e61306dd6a786dc3d0
