{
  "id": 1066591,
  "type": "Feature",
  "properties": {
    "tgn:hierarchy":[
        "tgn:1066591",
        "tgn:1000004",
        "tgn:7001838",
        "tgn:1000111",
        "tgn:7029392"
    ],
    "tgn:id":1066591,
    "tgn:name":"Asar",
    "tgn:placetype":[
        "aat:300008347"
    ]
},
  "bbox": [],
  "geometry": {"coordinates":[117.6333,47.9333],"type":"Point"}
}