{
  "id": 2421154,
  "type": "Feature",
  "properties": {
    "tgn:hierarchy":[
        "tgn:2421154",
        "tgn:1000001",
        "tgn:7012149",
        "tgn:2002387",
        "tgn:7007923",
        "tgn:7029392"
    ],
    "tgn:id":2421154,
    "tgn:name":"Jerome",
    "tgn:placetype":[
        "aat:300008347"
    ]
},
  "bbox": [],
  "geometry": {"coordinates":[-104.5167,44.0333],"type":"Point"}
}