{
  "id": 2060142,
  "type": "Feature",
  "properties": {
    "tgn:hierarchy":[
        "tgn:2060142",
        "tgn:1000001",
        "tgn:2001173",
        "tgn:7012149",
        "tgn:7007523",
        "tgn:7029392"
    ],
    "tgn:id":2060142,
    "tgn:name":"Poplar",
    "tgn:placetype":[
        "aat:300008347",
        "aat:300167671",
        "aat:300387210"
    ]
},
  "bbox": [],
  "geometry": {"coordinates":[-93.3333,38.3167],"type":"Point"}
}