{
  "id": 7096274,
  "type": "Feature",
  "properties": {
    "tgn:hierarchy":[
        "tgn:7096274",
        "tgn:1000003",
        "tgn:7003684",
        "tgn:7000084",
        "tgn:7029392"
    ],
    "tgn:id":7096274,
    "tgn:name":"Schreck",
    "tgn:placetype":[
        "aat:300008777"
    ]
},
  "bbox": [],
  "geometry": {"coordinates":[6.95,49.583333],"type":"Point"}
}