{
  "id": 7306894,
  "type": "Feature",
  "properties": {
    "tgn:hierarchy":[
        "tgn:7306894",
        "tgn:7002844",
        "tgn:7030216",
        "tgn:1000003",
        "tgn:1000095",
        "tgn:7029392"
    ],
    "tgn:id":7306894,
    "tgn:name":"Masarbon\u00e9s",
    "tgn:placetype":[
        "aat:300008347"
    ]
},
  "bbox": [],
  "geometry": {"coordinates":[1.438472,41.260208],"type":"Point"}
}