{
  "id": 7302156,
  "type": "Feature",
  "properties": {
    "tgn:hierarchy":[
        "tgn:7302156",
        "tgn:7002759",
        "tgn:7008909",
        "tgn:1000003",
        "tgn:1000095",
        "tgn:7029392"
    ],
    "tgn:id":7302156,
    "tgn:name":"Pao, Col de",
    "tgn:placetype":[
        "aat:300259572"
    ]
},
  "bbox": [],
  "geometry": {"coordinates":[-0.665939,42.874505],"type":"Point"}
}