{
  "id": 2283091,
  "type": "Feature",
  "properties": {
    "tgn:hierarchy":[
        "tgn:2283091",
        "tgn:1000001",
        "tgn:7012149",
        "tgn:2000363",
        "tgn:7007248",
        "tgn:7029392"
    ],
    "tgn:id":2283091,
    "tgn:name":"Deland, Lake",
    "tgn:placetype":[
        "aat:300006191"
    ]
},
  "bbox": [],
  "geometry": {"coordinates":[-84.8167,32.8333],"type":"Point"}
}