{
  "id": 7317855,
  "type": "Feature",
  "properties": {
    "tgn:hierarchy":[
        "tgn:7317855",
        "tgn:7016598",
        "tgn:1000049",
        "tgn:1000002",
        "tgn:7029392"
    ],
    "tgn:id":7317855,
    "tgn:name":"Cortadera, Aguada de la",
    "tgn:placetype":[
        "aat:300008697"
    ]
},
  "bbox": [],
  "geometry": {"coordinates":[-70.45,-25.45],"type":"Point"}
}