{
  "id": 2299050,
  "type": "Feature",
  "properties": {
    "tgn:hierarchy":[
        "tgn:2299050",
        "tgn:1000001",
        "tgn:7012149",
        "tgn:2000928",
        "tgn:7007515",
        "tgn:7029392"
    ],
    "tgn:id":2299050,
    "tgn:name":"Duck Cove",
    "tgn:placetype":[
        "aat:300132316"
    ]
},
  "bbox": [],
  "geometry": {"coordinates":[-69.35,45.3667],"type":"Point"}
}