{
  "id": 7460988,
  "type": "Feature",
  "properties": {
    "tgn:hierarchy":[
        "tgn:7460988",
        "tgn:7002445",
        "tgn:1000003",
        "tgn:7008117",
        "tgn:7008591",
        "tgn:7029392"
    ],
    "tgn:id":7460988,
    "tgn:name:en":"Langwathby",
    "tgn:placetype":[
        "aat:300008347"
    ]
},
  "bbox": [],
  "geometry": {"coordinates":[-2.666667,54.683333],"type":"Point"}
}