{
  "id": 1133488,
  "type": "Feature",
  "properties": {
    "tgn:hierarchy":[
        "tgn:1133488",
        "tgn:1000001",
        "tgn:7012149",
        "tgn:1002988",
        "tgn:7007710",
        "tgn:7029392"
    ],
    "tgn:id":1133488,
    "tgn:name":"Jacks Run",
    "tgn:placetype":[
        "aat:300008706"
    ]
},
  "bbox": [],
  "geometry": {"coordinates":[-79.2833,41.6833],"type":"Point"}
}