{
  "id": 2754459,
  "type": "Feature",
  "properties": {
    "tgn:hierarchy":[
        "tgn:2754459",
        "tgn:1000001",
        "tgn:2000311",
        "tgn:7012149",
        "tgn:7007248",
        "tgn:7029392"
    ],
    "tgn:id":2754459,
    "tgn:name":"Waverly Swamp",
    "tgn:placetype":[
        "aat:300008905"
    ]
},
  "bbox": [],
  "geometry": {"coordinates":[-81.75,31.0833],"type":"Point"}
}