{
  "id": 7012002,
  "type": "Feature",
  "properties": {
    "tgn:hierarchy":[
        "tgn:7012002",
        "tgn:1000003",
        "tgn:7006660",
        "tgn:7029392"
    ],
    "tgn:id":7012002,
    "tgn:name":"\u010cernigov",
    "tgn:placetype":[
        "aat:300387064",
        "aat:300235107"
    ]
},
  "bbox": [],
  "geometry": {"coordinates":[32.75,52.2167],"type":"Point"}
}