<<<<<<< HEAD
{
  "id": 2335664,
  "type": "Feature",
  "properties": {
    "tgn:hierarchy":[
        "tgn:2335664",
        "tgn:1000001",
        "tgn:2001415",
        "tgn:7012149",
        "tgn:7007526",
        "tgn:7029392"
    ],
    "tgn:id":2335664,
    "tgn:name":"Fortuna Mine",
    "tgn:placetype":[
        "aat:300000390"
    ]
},
  "bbox": [],
  "geometry": {"coordinates":[-117.0667,39.4833],"type":"Point"}
}
=======
{"geometry":{"type":"Point","coordinates":[-117.066700,39.483300]},"type":"Feature","properties":{"hierarchy":["tgn:2335664","tgn:1000001","tgn:2001415","tgn:7012149","tgn:7007526","tgn:7029392"],"placetype":["aat:300000390"],"id":2335664,"name:xx":"Fortuna Mine"}}
>>>>>>> 03f74aca74312dbeaf24d7e61306dd6a786dc3d0
