{
  "id": 2543498,
  "type": "Feature",
  "properties": {
    "tgn:hierarchy":[
        "tgn:2543498",
        "tgn:1000001",
        "tgn:7012149",
        "tgn:2000329",
        "tgn:7007248",
        "tgn:7029392"
    ],
    "tgn:id":2543498,
    "tgn:name":"Norris Lake",
    "tgn:placetype":[
        "aat:300006191"
    ]
},
  "bbox": [],
  "geometry": {"coordinates":[-84.7167,33.4333],"type":"Point"}
}