{
  "id": 7344431,
  "type": "Feature",
  "properties": {
    "tgn:hierarchy":[
        "tgn:7344431",
        "tgn:7002822",
        "tgn:1001647",
        "tgn:1000003",
        "tgn:1000095",
        "tgn:7029392"
    ],
    "tgn:id":7344431,
    "tgn:name":"Arandilla, R\u00edo",
    "tgn:placetype":[
        "aat:300008699"
    ]
},
  "bbox": [],
  "geometry": {"coordinates":[-2.133333,40.816667],"type":"Point"}
}