{
  "id": 7412670,
  "type": "Feature",
  "properties": {
    "tgn:hierarchy":[
        "tgn:7412670",
        "tgn:7005587",
        "tgn:1000001",
        "tgn:7005560",
        "tgn:7029392"
    ],
    "tgn:id":7412670,
    "tgn:name:es":"Iturbe",
    "tgn:placetype":[
        "aat:300008347"
    ]
},
  "bbox": [],
  "geometry": {"coordinates":[-99.320833,20.075],"type":"Point"}
}