<<<<<<< HEAD
{
  "id": 7175640,
  "type": "Feature",
  "properties": {
    "tgn:hierarchy":[
        "tgn:7175640",
        "tgn:1000003",
        "tgn:7003676",
        "tgn:7000084",
        "tgn:7029392"
    ],
    "tgn:id":7175640,
    "tgn:name":"Gro\u00dfe S\u00f6se",
    "tgn:placetype":[
        "aat:300008699"
    ]
},
  "bbox": [],
  "geometry": {"coordinates":[10.4,51.766667],"type":"Point"}
}
=======
{"geometry":{"type":"Point","coordinates":[10.400000,51.766667]},"type":"Feature","properties":{"hierarchy":["tgn:7175640","tgn:1000003","tgn:7003676","tgn:7000084","tgn:7029392"],"placetype":["aat:300008699"],"id":7175640,"name:xx":"Gro\u00dfe S\u00f6se"}}
>>>>>>> 03f74aca74312dbeaf24d7e61306dd6a786dc3d0
