{
  "id": 2474089,
  "type": "Feature",
  "properties": {
    "tgn:hierarchy":[
        "tgn:2474089",
        "tgn:1000001",
        "tgn:2001416",
        "tgn:7012149",
        "tgn:7007526",
        "tgn:7029392"
    ],
    "tgn:id":2474089,
    "tgn:name":"Lower Lake Spring",
    "tgn:placetype":[
        "aat:300008697"
    ]
},
  "bbox": [],
  "geometry": {"coordinates":[-115.1333,37.1833],"type":"Point"}
}