{
  "id": 2755508,
  "type": "Feature",
  "properties": {
    "tgn:hierarchy":[
        "tgn:2755508",
        "tgn:1000001",
        "tgn:7012149",
        "tgn:2001887",
        "tgn:7007825",
        "tgn:7029392"
    ],
    "tgn:id":2755508,
    "tgn:name":"Webster Hollow",
    "tgn:placetype":[
        "aat:300008761"
    ]
},
  "bbox": [],
  "geometry": {"coordinates":[-87.35,35.55],"type":"Point"}
}