{
  "id": 7511140,
  "type": "Feature",
  "properties": {
    "tgn:hierarchy":[
        "tgn:7511140",
        "tgn:1009227",
        "tgn:1000226",
        "tgn:7016822",
        "tgn:1000006",
        "tgn:7029392"
    ],
    "tgn:id":7511140,
    "tgn:name:en":"Skirmish Bay",
    "tgn:placetype":[
        "aat:300132316"
    ]
},
  "bbox": [],
  "geometry": {"coordinates":[-176.266667,-43.733333],"type":"Point"}
}