{
  "id": 2771524,
  "type": "Feature",
  "properties": {
    "tgn:hierarchy":[
        "tgn:2771524",
        "tgn:1000001",
        "tgn:7012149",
        "tgn:2001714",
        "tgn:7007708",
        "tgn:7029392"
    ],
    "tgn:id":2771524,
    "tgn:name":"Wildhorse Spring",
    "tgn:placetype":[
        "aat:300008697"
    ]
},
  "bbox": [],
  "geometry": {"coordinates":[-121.3833,42.3333],"type":"Point"}
}