{
  "id": 2598167,
  "type": "Feature",
  "properties": {
    "tgn:hierarchy":[
        "tgn:2598167",
        "tgn:1000001",
        "tgn:7012149",
        "tgn:1002617",
        "tgn:7007520",
        "tgn:7029392"
    ],
    "tgn:id":2598167,
    "tgn:name":"Preston Corners",
    "tgn:placetype":[
        "aat:300008347"
    ]
},
  "bbox": [],
  "geometry": {"coordinates":[-82.9833,42.6833],"type":"Point"}
}