{
  "id": 2282456,
  "type": "Feature",
  "properties": {
    "tgn:hierarchy":[
        "tgn:2282456",
        "tgn:1000001",
        "tgn:7012149",
        "tgn:2000226",
        "tgn:7007158",
        "tgn:7029392"
    ],
    "tgn:id":2282456,
    "tgn:name":"Deer Ridge",
    "tgn:placetype":[
        "aat:300266640"
    ]
},
  "bbox": [],
  "geometry": {"coordinates":[-105.55,40.3667],"type":"Point"}
}