{
  "id": 7416027,
  "type": "Feature",
  "properties": {
    "tgn:hierarchy":[
        "tgn:7416027",
        "tgn:7005584",
        "tgn:1000001",
        "tgn:7005560",
        "tgn:7029392"
    ],
    "tgn:id":7416027,
    "tgn:name":"El Capul\u00edn",
    "tgn:placetype":[
        "aat:300008347"
    ]
},
  "bbox": [],
  "geometry": {"coordinates":[-101.300556,20.883889],"type":"Point"}
}