{
  "id": 7591667,
  "type": "Feature",
  "properties": {
    "tgn:hierarchy":[
        "tgn:7591667",
        "tgn:1000004",
        "tgn:7000198",
        "tgn:7000799",
        "tgn:7029392"
    ],
    "tgn:id":7591667,
    "tgn:name:en":"Karl\u016bn",
    "tgn:placetype":[
        "aat:300008347"
    ]
},
  "bbox": [],
  "geometry": {"coordinates":[74.729045,32.748332],"type":"Point"}
}