{
  "id": 2754991,
  "type": "Feature",
  "properties": {
    "tgn:hierarchy":[
        "tgn:2754991",
        "tgn:1000001",
        "tgn:7012149",
        "tgn:2001923",
        "tgn:7007825",
        "tgn:7029392"
    ],
    "tgn:id":2754991,
    "tgn:name":"Weaver Ridge",
    "tgn:placetype":[
        "aat:300266640"
    ]
},
  "bbox": [],
  "geometry": {"coordinates":[-83.7667,36.3833],"type":"Point"}
}