{
  "id": 7321393,
  "type": "Feature",
  "properties": {
    "tgn:hierarchy":[
        "tgn:7321393",
        "tgn:1001702",
        "tgn:1000049",
        "tgn:1000002",
        "tgn:7029392"
    ],
    "tgn:id":7321393,
    "tgn:name":"Backout, Fiordo",
    "tgn:placetype":[
        "aat:300008676"
    ]
},
  "bbox": [],
  "geometry": {"coordinates":[-74.533333,-49.65],"type":"Point"}
}