{
  "id": 7303245,
  "type": "Feature",
  "properties": {
    "tgn:hierarchy":[
        "tgn:7303245",
        "tgn:7002759",
        "tgn:7002845",
        "tgn:1000003",
        "tgn:1000095",
        "tgn:7029392"
    ],
    "tgn:id":7303245,
    "tgn:name":"Mozota",
    "tgn:placetype":[
        "aat:300008347"
    ]
},
  "bbox": [],
  "geometry": {"coordinates":[-1.066667,41.483333],"type":"Point"}
}