{
  "id": 2239937,
  "type": "Feature",
  "properties": {
    "tgn:hierarchy":[
        "tgn:2239937",
        "tgn:1000001",
        "tgn:7012149",
        "tgn:1002837",
        "tgn:7007255",
        "tgn:7029392"
    ],
    "tgn:id":2239937,
    "tgn:name":"Cincinnati Hollow",
    "tgn:placetype":[
        "aat:300008761"
    ]
},
  "bbox": [],
  "geometry": {"coordinates":[-83.4833,38.1667],"type":"Point"}
}