{
  "id": 7504857,
  "type": "Feature",
  "properties": {
    "tgn:hierarchy":[
        "tgn:7504857",
        "tgn:1009227",
        "tgn:7001866",
        "tgn:1000226",
        "tgn:1000006",
        "tgn:7029392"
    ],
    "tgn:id":7504857,
    "tgn:name:en":"West Patch",
    "tgn:placetype":[
        "aat:300387036"
    ]
},
  "bbox": [],
  "geometry": {"coordinates":[172.802778,-43.615278],"type":"Point"}
}