{
  "id": 7503022,
  "type": "Feature",
  "properties": {
    "tgn:hierarchy":[
        "tgn:7503022",
        "tgn:1000004",
        "tgn:7004300",
        "tgn:1000141",
        "tgn:7029392"
    ],
    "tgn:id":7503022,
    "tgn:name":"Maoweitian",
    "tgn:placetype":[
        "aat:300008347"
    ]
},
  "bbox": [],
  "geometry": {"coordinates":[119.6175,23.248056],"type":"Point"}
}