<<<<<<< HEAD
{
  "id": 7476123,
  "type": "Feature",
  "properties": {
    "tgn:hierarchy":[
        "tgn:7476123",
        "tgn:7488858",
        "tgn:1000004",
        "tgn:1000141",
        "tgn:7029392"
    ],
    "tgn:id":7476123,
    "tgn:name":"Xinsheng Qiao",
    "tgn:placetype":[
        "aat:300007836"
    ]
},
  "bbox": [],
  "geometry": {"coordinates":[120.958484,23.954145],"type":"Point"}
}
=======
{"geometry":{"type":"Point","coordinates":[120.958484,23.954145]},"type":"Feature","properties":{"hierarchy":["tgn:7476123","tgn:7488858","tgn:1000004","tgn:1000141","tgn:7029392"],"placetype":["aat:300007836"],"id":7476123,"name:xx":"Xinsheng Qiao"}}
>>>>>>> 03f74aca74312dbeaf24d7e61306dd6a786dc3d0
