{
  "id": 2607508,
  "type": "Feature",
  "properties": {
    "tgn:hierarchy":[
        "tgn:2607508",
        "tgn:1000001",
        "tgn:7012149",
        "tgn:7007157",
        "tgn:1002828",
        "tgn:7029392"
    ],
    "tgn:id":2607508,
    "tgn:name":"Rannells Drain",
    "tgn:placetype":[
        "aat:300006075"
    ]
},
  "bbox": [],
  "geometry": {"coordinates":[-114.6833,33.5667],"type":"Point"}
}