{
  "id": 2058000,
  "type": "Feature",
  "properties": {
    "tgn:hierarchy":[
        "tgn:2058000",
        "tgn:1000001",
        "tgn:7012149",
        "tgn:2001228",
        "tgn:7007523",
        "tgn:7029392"
    ],
    "tgn:id":2058000,
    "tgn:name":"Belgique",
    "tgn:placetype":[
        "aat:300008347",
        "aat:300387210"
    ]
},
  "bbox": [],
  "geometry": {"coordinates":[-89.7667,37.8333],"type":"Point"}
}