{
  "id": 2441153,
  "type": "Feature",
  "properties": {
    "tgn:hierarchy":[
        "tgn:2441153",
        "tgn:1000001",
        "tgn:7012149",
        "tgn:1002623",
        "tgn:7007252",
        "tgn:7029392"
    ],
    "tgn:id":2441153,
    "tgn:name":"Knopp Run",
    "tgn:placetype":[
        "aat:300008699"
    ]
},
  "bbox": [],
  "geometry": {"coordinates":[-85.7167,40.15],"type":"Point"}
}