<<<<<<< HEAD
{
  "id": 2252578,
  "type": "Feature",
  "properties": {
    "tgn:hierarchy":[
        "tgn:2252578",
        "tgn:1000001",
        "tgn:7012149",
        "tgn:2001286",
        "tgn:7007524",
        "tgn:7029392"
    ],
    "tgn:id":2252578,
    "tgn:name":"Conn Mountain",
    "tgn:placetype":[
        "aat:300008798"
    ]
},
  "bbox": [],
  "geometry": {"coordinates":[-115.8,48.6333],"type":"Point"}
}
=======
{"geometry":{"type":"Point","coordinates":[-115.800000,48.633300]},"type":"Feature","properties":{"hierarchy":["tgn:2252578","tgn:1000001","tgn:7012149","tgn:2001286","tgn:7007524","tgn:7029392"],"placetype":["aat:300008798"],"id":2252578,"name:xx":"Conn Mountain"}}
>>>>>>> 03f74aca74312dbeaf24d7e61306dd6a786dc3d0
