{
  "id": 1041720,
  "type": "Feature",
  "properties": {
    "tgn:hierarchy":[
        "tgn:1041720",
        "tgn:7003669",
        "tgn:1000003",
        "tgn:7000084",
        "tgn:7029392"
    ],
    "tgn:id":1041720,
    "tgn:name":"Weismain",
    "tgn:placetype":[
        "aat:300008347"
    ]
},
  "bbox": [],
  "geometry": {"coordinates":[11.233333,50.083333],"type":"Point"}
}