{
  "id": 7443811,
  "type": "Feature",
  "properties": {
    "tgn:hierarchy":[
        "tgn:7443811",
        "tgn:7002443",
        "tgn:1000003",
        "tgn:7018966",
        "tgn:7008591",
        "tgn:7029392"
    ],
    "tgn:id":7443811,
    "tgn:name:en":"Ystradowen",
    "tgn:placetype":[
        "aat:300008347"
    ]
},
  "bbox": [],
  "geometry": {"coordinates":[-3.421944,51.490556],"type":"Point"}
}