{
  "id": 7474485,
  "type": "Feature",
  "properties": {
    "tgn:hierarchy":[
        "tgn:7474485",
        "tgn:1000004",
        "tgn:7004300",
        "tgn:1000141",
        "tgn:7029392"
    ],
    "tgn:id":7474485,
    "tgn:name":"Wang'an",
    "tgn:placetype":[
        "aat:300008347"
    ]
},
  "bbox": [],
  "geometry": {"coordinates":[119.499167,23.3575],"type":"Point"}
}