{
  "id": 1095845,
  "type": "Feature",
  "properties": {
    "tgn:hierarchy":[
        "tgn:1095845",
        "tgn:7001242",
        "tgn:7024150",
        "tgn:1000604",
        "tgn:1000208",
        "tgn:7029392"
    ],
    "tgn:id":1095845,
    "tgn:name":"Ouargaye",
    "tgn:placetype":[
        "aat:300008347"
    ]
},
  "bbox": [],
  "geometry": {"coordinates":[0.0667,11.65],"type":"Point"}
}