{
  "id": 2083012,
  "type": "Feature",
  "properties": {
    "tgn:hierarchy":[
        "tgn:2083012",
        "tgn:2001623",
        "tgn:1000001",
        "tgn:7012149",
        "tgn:7007707",
        "tgn:7029392"
    ],
    "tgn:id":2083012,
    "tgn:name":"Christie",
    "tgn:placetype":[
        "aat:300008347",
        "aat:300387210"
    ]
},
  "bbox": [],
  "geometry": {"coordinates":[-94.6833,35.95],"type":"Point"}
}