{
  "id": 2633790,
  "type": "Feature",
  "properties": {
    "tgn:hierarchy":[
        "tgn:2633790",
        "tgn:1000001",
        "tgn:7012149",
        "tgn:1002517",
        "tgn:7007523",
        "tgn:7029392"
    ],
    "tgn:id":2633790,
    "tgn:name":"Rush Island",
    "tgn:placetype":[
        "aat:300008791"
    ]
},
  "bbox": [],
  "geometry": {"coordinates":[-90.2667,38.1333],"type":"Point"}
}