{
  "id": 1027476,
  "type": "Feature",
  "properties": {
    "tgn:hierarchy":[
        "tgn:1027476",
        "tgn:7593921",
        "tgn:1000003",
        "tgn:1001780",
        "tgn:7029392"
    ],
    "tgn:id":1027476,
    "tgn:name":"Poln\u00e1",
    "tgn:placetype":[
        "aat:300008347"
    ]
},
  "bbox": [],
  "geometry": {"coordinates":[15.7167,49.4833],"type":"Point"}
}