{
  "id": 7428178,
  "type": "Feature",
  "properties": {
    "tgn:hierarchy":[
        "tgn:7428178",
        "tgn:7005581",
        "tgn:1000001",
        "tgn:7005560",
        "tgn:7029392"
    ],
    "tgn:id":7428178,
    "tgn:name":"La Boquilla del Caro",
    "tgn:placetype":[
        "aat:300008347"
    ]
},
  "bbox": [],
  "geometry": {"coordinates":[-105.233333,26.55],"type":"Point"}
}