{
  "id": 2534092,
  "type": "Feature",
  "properties": {
    "tgn:hierarchy":[
        "tgn:2534092",
        "tgn:1000001",
        "tgn:7012149",
        "tgn:2000471",
        "tgn:7007250",
        "tgn:7029392"
    ],
    "tgn:id":2534092,
    "tgn:name":"Myrtle Creek",
    "tgn:placetype":[
        "aat:300008706"
    ]
},
  "bbox": [],
  "geometry": {"coordinates":[-115.4333,43.4667],"type":"Point"}
}