{
  "id": 2347750,
  "type": "Feature",
  "properties": {
    "tgn:hierarchy":[
        "tgn:2347750",
        "tgn:1000001",
        "tgn:7016172",
        "tgn:7012149",
        "tgn:2000164",
        "tgn:7029392"
    ],
    "tgn:id":2347750,
    "tgn:name":"Georgetown Lake",
    "tgn:placetype":[
        "aat:300008680"
    ]
},
  "bbox": [],
  "geometry": {"coordinates":[-92.1167,34.6167],"type":"Point"}
}