{
  "id": 2192966,
  "type": "Feature",
  "properties": {
    "tgn:hierarchy":[
        "tgn:2192966",
        "tgn:1000001",
        "tgn:7012149",
        "tgn:7013941",
        "tgn:7007568",
        "tgn:7029392"
    ],
    "tgn:id":2192966,
    "tgn:name":"Brayton Hollow",
    "tgn:placetype":[
        "aat:300008761"
    ]
},
  "bbox": [],
  "geometry": {"coordinates":[-74.1167,44.9333],"type":"Point"}
}