{
  "id": 7502720,
  "type": "Feature",
  "properties": {
    "tgn:hierarchy":[
        "tgn:7502720",
        "tgn:7487020",
        "tgn:1000004",
        "tgn:1000141",
        "tgn:7029392"
    ],
    "tgn:id":7502720,
    "tgn:name":"Fuxing Qiao",
    "tgn:placetype":[
        "aat:300007836"
    ]
},
  "bbox": [],
  "geometry": {"coordinates":[121.04,24.600833],"type":"Point"}
}