<<<<<<< HEAD
{
  "id": 2406672,
  "type": "Feature",
  "properties": {
    "tgn:hierarchy":[
        "tgn:2406672",
        "tgn:1000001",
        "tgn:7012149",
        "tgn:2000475",
        "tgn:7007250",
        "tgn:7029392"
    ],
    "tgn:id":2406672,
    "tgn:name":"Hunt Ditch",
    "tgn:placetype":[
        "aat:300006075"
    ]
},
  "bbox": [],
  "geometry": {"coordinates":[-114.9,42.7667],"type":"Point"}
}
=======
{"geometry":{"type":"Point","coordinates":[-114.900000,42.766700]},"type":"Feature","properties":{"hierarchy":["tgn:2406672","tgn:1000001","tgn:7012149","tgn:2000475","tgn:7007250","tgn:7029392"],"placetype":["aat:300006075"],"id":2406672,"name:xx":"Hunt Ditch"}}
>>>>>>> 03f74aca74312dbeaf24d7e61306dd6a786dc3d0
