{
  "id": 7390411,
  "type": "Feature",
  "properties": {
    "tgn:hierarchy":[
        "tgn:7390411",
        "tgn:7005581",
        "tgn:1000001",
        "tgn:7005560",
        "tgn:7029392"
    ],
    "tgn:id":7390411,
    "tgn:name":"Ejido La Cienegu",
    "tgn:placetype":[
        "aat:300008347"
    ]
},
  "bbox": [],
  "geometry": {"coordinates":[-105.983333,27.766667],"type":"Point"}
}