{
  "id": 7421383,
  "type": "Feature",
  "properties": {
    "tgn:hierarchy":[
        "tgn:7421383",
        "tgn:7005584",
        "tgn:1000001",
        "tgn:7005560",
        "tgn:7029392"
    ],
    "tgn:id":7421383,
    "tgn:name":"San Jos\u00e9 de Llanos",
    "tgn:placetype":[
        "aat:300008347"
    ]
},
  "bbox": [],
  "geometry": {"coordinates":[-101.508333,21.373056],"type":"Point"}
}