{
  "id": 2691727,
  "type": "Feature",
  "properties": {
    "tgn:hierarchy":[
        "tgn:2691727",
        "tgn:1000001",
        "tgn:7012149",
        "tgn:2001873",
        "tgn:7007825",
        "tgn:7029392"
    ],
    "tgn:id":2691727,
    "tgn:name":"Starnes",
    "tgn:placetype":[
        "aat:300008347"
    ]
},
  "bbox": [],
  "geometry": {"coordinates":[-82.8167,36.55],"type":"Point"}
}