{
  "id": 1129453,
  "type": "Feature",
  "properties": {
    "tgn:hierarchy":[
        "tgn:1129453",
        "tgn:1000001",
        "tgn:7012149",
        "tgn:7007520",
        "tgn:7029392"
    ],
    "tgn:id":1129453,
    "tgn:name":"Saline",
    "tgn:placetype":[
        "aat:300008707"
    ]
},
  "bbox": [],
  "geometry": {"coordinates":[-83.9333,42.15],"type":"Point"}
}