{
  "id": 7245564,
  "type": "Feature",
  "properties": {
    "tgn:hierarchy":[
        "tgn:7245564",
        "tgn:7003465",
        "tgn:1000003",
        "tgn:1000063",
        "tgn:4012014",
        "tgn:7029392"
    ],
    "tgn:id":7245564,
    "tgn:name":"Beaubru, Bois",
    "tgn:placetype":[
        "aat:300008863"
    ]
},
  "bbox": [],
  "geometry": {"coordinates":[5.083333,49.766667],"type":"Point"}
}