{
  "id": 2682906,
  "type": "Feature",
  "properties": {
    "tgn:hierarchy":[
        "tgn:2682906",
        "tgn:1000001",
        "tgn:7012149",
        "tgn:2000831",
        "tgn:7007255",
        "tgn:7029392"
    ],
    "tgn:id":2682906,
    "tgn:name":"Sow Hollow",
    "tgn:placetype":[
        "aat:300008761"
    ]
},
  "bbox": [],
  "geometry": {"coordinates":[-83.1667,37.8333],"type":"Point"}
}