{
  "id": 2261173,
  "type": "Feature",
  "properties": {
    "tgn:hierarchy":[
        "tgn:2261173",
        "tgn:1000001",
        "tgn:7012149",
        "tgn:2001082",
        "tgn:7007521",
        "tgn:7029392"
    ],
    "tgn:id":2261173,
    "tgn:name":"County Ditch Number Twentythree",
    "tgn:placetype":[
        "aat:300006075"
    ]
},
  "bbox": [],
  "geometry": {"coordinates":[-96.55,46.3833],"type":"Point"}
}