{
  "id": 2254535,
  "type": "Feature",
  "properties": {
    "tgn:hierarchy":[
        "tgn:2254535",
        "tgn:1000001",
        "tgn:7012149",
        "tgn:1002756",
        "tgn:7007240",
        "tgn:7029392"
    ],
    "tgn:id":2254535,
    "tgn:name":"Coon Hammock",
    "tgn:placetype":[
        "aat:300008791"
    ]
},
  "bbox": [],
  "geometry": {"coordinates":[-81.2667,28.0167],"type":"Point"}
}