{
  "id": 2367928,
  "type": "Feature",
  "properties": {
    "tgn:hierarchy":[
        "tgn:2367928",
        "tgn:1000001",
        "tgn:7006451",
        "tgn:7012149",
        "tgn:7029392"
    ],
    "tgn:id":2367928,
    "tgn:name":"Growler Valley",
    "tgn:placetype":[
        "aat:300008761"
    ]
},
  "bbox": [],
  "geometry": {"coordinates":[-113.0167,32.15],"type":"Point"}
}