<<<<<<< HEAD
{
  "id": 2405404,
  "type": "Feature",
  "properties": {
    "tgn:hierarchy":[
        "tgn:2405404",
        "tgn:7019618",
        "tgn:1000001",
        "tgn:7012149",
        "tgn:7007564",
        "tgn:7029392"
    ],
    "tgn:id":2405404,
    "tgn:name":"Huggins, Mount",
    "tgn:placetype":[
        "aat:300008798"
    ]
},
  "bbox": [],
  "geometry": {"coordinates":[-72.2333,42.9],"type":"Point"}
}
=======
{"geometry":{"type":"Point","coordinates":[-72.233300,42.900000]},"type":"Feature","properties":{"hierarchy":["tgn:2405404","tgn:7019618","tgn:1000001","tgn:7012149","tgn:7007564","tgn:7029392"],"placetype":["aat:300008798"],"id":2405404,"name:xx":"Huggins, Mount"}}
>>>>>>> 03f74aca74312dbeaf24d7e61306dd6a786dc3d0
