{
  "id": 7283041,
  "type": "Feature",
  "properties": {
    "tgn:hierarchy":[
        "tgn:7283041",
        "tgn:1001699",
        "tgn:1000049",
        "tgn:1000002",
        "tgn:7029392"
    ],
    "tgn:id":7283041,
    "tgn:name":"Patos, R\u00edo de los",
    "tgn:placetype":[
        "aat:300008699"
    ]
},
  "bbox": [],
  "geometry": {"coordinates":[-72.466667,-41.25],"type":"Point"}
}