<<<<<<< HEAD
{
  "id": 7051315,
  "type": "Feature",
  "properties": {
    "tgn:hierarchy":[
        "tgn:7051315",
        "tgn:1000003",
        "tgn:7003122",
        "tgn:1000080",
        "tgn:7029392"
    ],
    "tgn:id":7051315,
    "tgn:name":"Ancoraggi di Marina Lunga",
    "tgn:placetype":[
        "aat:300386968"
    ]
},
  "bbox": [],
  "geometry": {"coordinates":[14.966667,38.466667],"type":"Point"}
}
=======
{"geometry":{"type":"Point","coordinates":[14.966667,38.466667]},"type":"Feature","properties":{"hierarchy":["tgn:7051315","tgn:1000003","tgn:7003122","tgn:1000080","tgn:7029392"],"placetype":["aat:300386968"],"id":7051315,"name:xx":"Ancoraggi di Marina Lunga"}}
>>>>>>> 03f74aca74312dbeaf24d7e61306dd6a786dc3d0
