{
  "id": 7112231,
  "type": "Feature",
  "properties": {
    "tgn:hierarchy":[
        "tgn:7112231",
        "tgn:7003669",
        "tgn:1000003",
        "tgn:7000084",
        "tgn:7029392"
    ],
    "tgn:id":7112231,
    "tgn:name":"Rossbach",
    "tgn:placetype":[
        "aat:300387200"
    ]
},
  "bbox": [],
  "geometry": {"coordinates":[12.95,48.583333],"type":"Point"}
}