{
  "id": 2722162,
  "type": "Feature",
  "properties": {
    "tgn:hierarchy":[
        "tgn:2722162",
        "tgn:2000454",
        "tgn:1000001",
        "tgn:7012149",
        "tgn:7007250",
        "tgn:7029392"
    ],
    "tgn:id":2722162,
    "tgn:name":"Time Spring",
    "tgn:placetype":[
        "aat:300008697"
    ]
},
  "bbox": [],
  "geometry": {"coordinates":[-111.9167,42.4667],"type":"Point"}
}