{
  "id": 2374572,
  "type": "Feature",
  "properties": {
    "tgn:hierarchy":[
        "tgn:2374572",
        "tgn:1000001",
        "tgn:7012149",
        "tgn:2000878",
        "tgn:7007256",
        "tgn:7029392"
    ],
    "tgn:id":2374572,
    "tgn:name":"Hancock Creek",
    "tgn:placetype":[
        "aat:300008706"
    ]
},
  "bbox": [],
  "geometry": {"coordinates":[-92.55,32.3167],"type":"Point"}
}