{
  "id": 1002327,
  "type": "Feature",
  "properties": {
    "tgn:hierarchy":[
        "tgn:1002327",
        "tgn:1000001",
        "tgn:7012149",
        "tgn:7007252",
        "tgn:7029392"
    ],
    "tgn:id":1002327,
    "tgn:name":"Delaware",
    "tgn:placetype":[
        "aat:300387145",
        "aat:300000771"
    ]
},
  "bbox": [],
  "geometry": {"coordinates":[-85.3833,40.1833],"type":"Point"}
}