{
  "id": 2607440,
  "type": "Feature",
  "properties": {
    "tgn:hierarchy":[
        "tgn:2607440",
        "tgn:1000001",
        "tgn:7012149",
        "tgn:2001394",
        "tgn:7007525",
        "tgn:7029392"
    ],
    "tgn:id":2607440,
    "tgn:name":"Rangler Canal",
    "tgn:placetype":[
        "aat:300006075"
    ]
},
  "bbox": [],
  "geometry": {"coordinates":[-103.4333,41.7667],"type":"Point"}
}