{
  "id": 7425396,
  "type": "Feature",
  "properties": {
    "tgn:hierarchy":[
        "tgn:7425396",
        "tgn:1000001",
        "tgn:7005601",
        "tgn:7005560",
        "tgn:7029392"
    ],
    "tgn:id":7425396,
    "tgn:name":"San Fernando",
    "tgn:placetype":[
        "aat:300008347"
    ]
},
  "bbox": [],
  "geometry": {"coordinates":[-102.766667,24.283333],"type":"Point"}
}