{
  "id": 2720731,
  "type": "Feature",
  "properties": {
    "tgn:hierarchy":[
        "tgn:2720731",
        "tgn:1000001",
        "tgn:7012149",
        "tgn:2002372",
        "tgn:7007923",
        "tgn:7029392"
    ],
    "tgn:id":2720731,
    "tgn:name":"Tibbets Drain",
    "tgn:placetype":[
        "aat:300006075"
    ]
},
  "bbox": [],
  "geometry": {"coordinates":[-104.2667,42.0167],"type":"Point"}
}