{
  "id": 2487512,
  "type": "Feature",
  "properties": {
    "tgn:hierarchy":[
        "tgn:2487512",
        "tgn:1000001",
        "tgn:7012149",
        "tgn:2002120",
        "tgn:7007827",
        "tgn:7029392"
    ],
    "tgn:id":2487512,
    "tgn:name":"Left Fork Cottonwood Canyon",
    "tgn:placetype":[
        "aat:300008761"
    ]
},
  "bbox": [],
  "geometry": {"coordinates":[-111.3167,39.6833],"type":"Point"}
}