{
  "id": 7591621,
  "type": "Feature",
  "properties": {
    "tgn:hierarchy":[
        "tgn:7591621",
        "tgn:1000004",
        "tgn:7000198",
        "tgn:7000799",
        "tgn:7029392"
    ],
    "tgn:id":7591621,
    "tgn:name:en":"Krishannagar",
    "tgn:placetype":[
        "aat:300008347"
    ]
},
  "bbox": [],
  "geometry": {"coordinates":[74.816667,32.641667],"type":"Point"}
}