{
  "id": 2615471,
  "type": "Feature",
  "properties": {
    "tgn:hierarchy":[
        "tgn:2615471",
        "tgn:1000001",
        "tgn:2001435",
        "tgn:7012149",
        "tgn:7007566",
        "tgn:7029392"
    ],
    "tgn:id":2615471,
    "tgn:name":"Restoration Tank",
    "tgn:placetype":[
        "aat:300006191"
    ]
},
  "bbox": [],
  "geometry": {"coordinates":[-106.7167,32.6667],"type":"Point"}
}