{
  "id": 7519553,
  "type": "Feature",
  "properties": {
    "tgn:hierarchy":[
        "tgn:7519553",
        "tgn:1008380",
        "tgn:1000226",
        "tgn:7016827",
        "tgn:1000006",
        "tgn:7029392"
    ],
    "tgn:id":7519553,
    "tgn:name:en":"Ahititi",
    "tgn:placetype":[
        "aat:300008777"
    ]
},
  "bbox": [],
  "geometry": {"coordinates":[174.616667,-38.85],"type":"Point"}
}