<<<<<<< HEAD
{
  "id": 7377346,
  "type": "Feature",
  "properties": {
    "tgn:hierarchy":[
        "tgn:7377346",
        "tgn:1000001",
        "tgn:7005590",
        "tgn:7005560",
        "tgn:7029392"
    ],
    "tgn:id":7377346,
    "tgn:name":"Las Avila",
    "tgn:placetype":[
        "aat:300000241"
    ]
},
  "bbox": [],
  "geometry": {"coordinates":[-102.616667,20.083333],"type":"Point"}
}
=======
{"geometry":{"type":"Point","coordinates":[-102.616667,20.083333]},"type":"Feature","properties":{"hierarchy":["tgn:7377346","tgn:1000001","tgn:7005590","tgn:7005560","tgn:7029392"],"placetype":["aat:300000241"],"id":7377346,"name:xx":"Las Avila"}}
>>>>>>> 03f74aca74312dbeaf24d7e61306dd6a786dc3d0
