{
  "id": 2330555,
  "type": "Feature",
  "properties": {
    "tgn:hierarchy":[
        "tgn:2330555",
        "tgn:1000001",
        "tgn:7012149",
        "tgn:2001299",
        "tgn:7007524",
        "tgn:7029392"
    ],
    "tgn:id":2330555,
    "tgn:name":"Flat Creek",
    "tgn:placetype":[
        "aat:300008706"
    ]
},
  "bbox": [],
  "geometry": {"coordinates":[-105.1667,46.55],"type":"Point"}
}