{
  "id": 2126289,
  "type": "Feature",
  "properties": {
    "tgn:hierarchy":[
        "tgn:2126289",
        "tgn:1000001",
        "tgn:7016172",
        "tgn:7012149",
        "tgn:2000136",
        "tgn:7029392"
    ],
    "tgn:id":2126289,
    "tgn:name":"Adler Mine",
    "tgn:placetype":[
        "aat:300000390"
    ]
},
  "bbox": [],
  "geometry": {"coordinates":[-91.6333,35.85],"type":"Point"}
}