<<<<<<< HEAD
{
  "id": 7475473,
  "type": "Feature",
  "properties": {
    "tgn:hierarchy":[
        "tgn:7475473",
        "tgn:1000004",
        "tgn:7001014",
        "tgn:1000141",
        "tgn:7029392"
    ],
    "tgn:id":7475473,
    "tgn:name":"Jiuxionglin",
    "tgn:placetype":[
        "aat:300387033"
    ]
},
  "bbox": [],
  "geometry": {"coordinates":[120.5803,23.7581],"type":"Point"}
}
=======
{"geometry":{"type":"Point","coordinates":[120.580300,23.758100]},"type":"Feature","properties":{"hierarchy":["tgn:7475473","tgn:1000004","tgn:7001014","tgn:1000141","tgn:7029392"],"placetype":["aat:300387033"],"id":7475473,"name:xx":"Jiuxionglin"}}
>>>>>>> 03f74aca74312dbeaf24d7e61306dd6a786dc3d0
