{
  "id": 7475473,
  "type": "Feature",
  "properties": {
    "tgn:hierarchy":[
        "tgn:7475473",
        "tgn:1000004",
        "tgn:7001014",
        "tgn:1000141",
        "tgn:7029392"
    ],
    "tgn:id":7475473,
    "tgn:name":"Jiuxionglin",
    "tgn:placetype":[
        "aat:300387033"
    ]
},
  "bbox": [],
  "geometry": {"coordinates":[120.5803,23.7581],"type":"Point"}
}