{
  "id": 2191629,
  "type": "Feature",
  "properties": {
    "tgn:hierarchy":[
        "tgn:2191629",
        "tgn:1000001",
        "tgn:7012149",
        "tgn:2000926",
        "tgn:7007515",
        "tgn:7029392"
    ],
    "tgn:id":2191629,
    "tgn:name":"Bradley Brook",
    "tgn:placetype":[
        "aat:300008699"
    ]
},
  "bbox": [],
  "geometry": {"coordinates":[-70.95,44.2167],"type":"Point"}
}