{
  "id": 7434222,
  "type": "Feature",
  "properties": {
    "tgn:hierarchy":[
        "tgn:7434222",
        "tgn:1001835",
        "tgn:1000001",
        "tgn:7005560",
        "tgn:7029392"
    ],
    "tgn:id":7434222,
    "tgn:name":"Islas Agrarias Grupo A",
    "tgn:placetype":[
        "aat:300008347"
    ]
},
  "bbox": [],
  "geometry": {"coordinates":[-115.3325,32.607778],"type":"Point"}
}