{
  "id": 2579560,
  "type": "Feature",
  "properties": {
    "tgn:hierarchy":[
        "tgn:2579560",
        "tgn:1000001",
        "tgn:7012149",
        "tgn:2002061",
        "tgn:7007826",
        "tgn:7029392"
    ],
    "tgn:id":2579560,
    "tgn:name":"Pickett Creek",
    "tgn:placetype":[
        "aat:300008706"
    ]
},
  "bbox": [],
  "geometry": {"coordinates":[-95.0667,33.55],"type":"Point"}
}