{
  "id": 2496217,
  "type": "Feature",
  "properties": {
    "tgn:hierarchy":[
        "tgn:2496217",
        "tgn:1000001",
        "tgn:7012149",
        "tgn:7007157",
        "tgn:2000191",
        "tgn:7029392"
    ],
    "tgn:id":2496217,
    "tgn:name":"Masterson Meadow Lake",
    "tgn:placetype":[
        "aat:300008680"
    ]
},
  "bbox": [],
  "geometry": {"coordinates":[-122.6667,41.2667],"type":"Point"}
}