{
  "id": 2456268,
  "type": "Feature",
  "properties": {
    "tgn:hierarchy":[
        "tgn:2456268",
        "tgn:1000001",
        "tgn:7012149",
        "tgn:2001764",
        "tgn:7007712",
        "tgn:7029392"
    ],
    "tgn:id":2456268,
    "tgn:name":"Little Horse Branch",
    "tgn:placetype":[
        "aat:300008699"
    ]
},
  "bbox": [],
  "geometry": {"coordinates":[-81.0333,34.15],"type":"Point"}
}