{
  "id": 7501941,
  "type": "Feature",
  "properties": {
    "tgn:hierarchy":[
        "tgn:7501941",
        "tgn:7001004",
        "tgn:1000004",
        "tgn:1000141",
        "tgn:7029392"
    ],
    "tgn:id":7501941,
    "tgn:name":"Wenxian Qiao",
    "tgn:placetype":[
        "aat:300007836"
    ]
},
  "bbox": [],
  "geometry": {"coordinates":[120.3775,22.864444],"type":"Point"}
}