{
  "id": 2184956,
  "type": "Feature",
  "properties": {
    "tgn:hierarchy":[
        "tgn:2184956",
        "tgn:7002659",
        "tgn:1000001",
        "tgn:7012149",
        "tgn:2000023",
        "tgn:7029392"
    ],
    "tgn:id":2184956,
    "tgn:name":"Bogg Branch",
    "tgn:placetype":[
        "aat:300008699"
    ]
},
  "bbox": [],
  "geometry": {"coordinates":[-87.0167,32.5667],"type":"Point"}
}