{
  "id": 7538103,
  "type": "Feature",
  "properties": {
    "tgn:hierarchy":[
        "tgn:7538103",
        "tgn:7001242",
        "tgn:7016833",
        "tgn:1001080",
        "tgn:7029392"
    ],
    "tgn:id":7538103,
    "tgn:name":"Shih\u0101b\u012b, Jabal ash",
    "tgn:placetype":[
        "aat:300008777"
    ]
},
  "bbox": [],
  "geometry": {"coordinates":[32.226565,30.306381],"type":"Point"}
}