{
  "id": 7113864,
  "type": "Feature",
  "properties": {
    "tgn:hierarchy":[
        "tgn:7113864",
        "tgn:1000003",
        "tgn:7003676",
        "tgn:7000084",
        "tgn:7029392"
    ],
    "tgn:id":7113864,
    "tgn:name":"Roddens",
    "tgn:placetype":[
        "aat:300000206"
    ]
},
  "bbox": [],
  "geometry": {"coordinates":[8.266667,53.55],"type":"Point"}
}