{
  "id": 7524317,
  "type": "Feature",
  "properties": {
    "tgn:hierarchy":[
        "tgn:7524317",
        "tgn:7001242",
        "tgn:7016833",
        "tgn:1001087",
        "tgn:7029392"
    ],
    "tgn:id":7524317,
    "tgn:name":"Al Qan\u0101\u0163ir\u012bn",
    "tgn:placetype":[
        "aat:300008347"
    ]
},
  "bbox": [],
  "geometry": {"coordinates":[31.038917,30.322397],"type":"Point"}
}