{
  "id": 7294192,
  "type": "Feature",
  "properties": {
    "tgn:hierarchy":[
        "tgn:7294192",
        "tgn:7002842",
        "tgn:7001158",
        "tgn:1000003",
        "tgn:1000095",
        "tgn:7029392"
    ],
    "tgn:id":7294192,
    "tgn:name":"Velilla de Medinaceli",
    "tgn:placetype":[
        "aat:300008347"
    ]
},
  "bbox": [],
  "geometry": {"coordinates":[-2.333333,41.166667],"type":"Point"}
}