{
  "id": 1074058,
  "type": "Feature",
  "properties": {
    "tgn:hierarchy":[
        "tgn:1074058",
        "tgn:1000004",
        "tgn:7018053",
        "tgn:1000111",
        "tgn:7029392"
    ],
    "tgn:id":1074058,
    "tgn:name":"Zhongning",
    "tgn:placetype":[
        "aat:300008347"
    ]
},
  "bbox": [],
  "geometry": {"coordinates":[105.6667,37.4333],"type":"Point"}
}