{
  "id": 2411001,
  "type": "Feature",
  "properties": {
    "tgn:hierarchy":[
        "tgn:2411001",
        "tgn:1000001",
        "tgn:7012149",
        "tgn:1002703",
        "tgn:7007826",
        "tgn:7029392"
    ],
    "tgn:id":2411001,
    "tgn:name":"Indian Creek",
    "tgn:placetype":[
        "aat:300008706"
    ]
},
  "bbox": [],
  "geometry": {"coordinates":[-94.5167,31.8333],"type":"Point"}
}