{
  "id": 2057588,
  "type": "Feature",
  "properties": {
    "tgn:hierarchy":[
        "tgn:2057588",
        "tgn:1000001",
        "tgn:7012149",
        "tgn:2001153",
        "tgn:7007522",
        "tgn:7029392"
    ],
    "tgn:id":2057588,
    "tgn:name":"Tandy",
    "tgn:placetype":[
        "aat:300008347",
        "aat:300387210"
    ]
},
  "bbox": [],
  "geometry": {"coordinates":[-90.15,33.95],"type":"Point"}
}