{
  "id": 7456234,
  "type": "Feature",
  "properties": {
    "tgn:hierarchy":[
        "tgn:7456234",
        "tgn:1003572",
        "tgn:7002445",
        "tgn:1000003",
        "tgn:7026570",
        "tgn:7008591",
        "tgn:7029392"
    ],
    "tgn:id":7456234,
    "tgn:name:en":"Clifton Junction Station",
    "tgn:placetype":[
        "aat:300007783"
    ]
},
  "bbox": [],
  "geometry": {"coordinates":[-2.316667,53.533333],"type":"Point"}
}