<<<<<<< HEAD
{
  "id": 2401696,
  "type": "Feature",
  "properties": {
    "tgn:hierarchy":[
        "tgn:2401696",
        "tgn:1000001",
        "tgn:2000603",
        "tgn:7012149",
        "tgn:7007253",
        "tgn:7029392"
    ],
    "tgn:id":2401696,
    "tgn:name":"Horseshoe Lake",
    "tgn:placetype":[
        "aat:300008680"
    ]
},
  "bbox": [],
  "geometry": {"coordinates":[-96.05,41.6167],"type":"Point"}
}
=======
{"geometry":{"type":"Point","coordinates":[-96.050000,41.616700]},"type":"Feature","properties":{"hierarchy":["tgn:2401696","tgn:1000001","tgn:2000603","tgn:7012149","tgn:7007253","tgn:7029392"],"placetype":["aat:300008680"],"id":2401696,"name:xx":"Horseshoe Lake"}}
>>>>>>> 03f74aca74312dbeaf24d7e61306dd6a786dc3d0
