{
  "id": 7374004,
  "type": "Feature",
  "properties": {
    "tgn:hierarchy":[
        "tgn:7374004",
        "tgn:1000001",
        "tgn:7005589",
        "tgn:7005560",
        "tgn:7029392"
    ],
    "tgn:id":7374004,
    "tgn:name":"Laguna",
    "tgn:placetype":[
        "aat:300008347"
    ]
},
  "bbox": [],
  "geometry": {"coordinates":[-100.983333,26.216667],"type":"Point"}
}