{
  "id": 7438416,
  "type": "Feature",
  "properties": {
    "tgn:hierarchy":[
        "tgn:7438416",
        "tgn:1000001",
        "tgn:7005592",
        "tgn:7005560",
        "tgn:7029392"
    ],
    "tgn:id":7438416,
    "tgn:name":"Temascal",
    "tgn:placetype":[
        "aat:300008347"
    ]
},
  "bbox": [],
  "geometry": {"coordinates":[-97.983333,20.333333],"type":"Point"}
}