{
  "id": 2431164,
  "type": "Feature",
  "properties": {
    "tgn:hierarchy":[
        "tgn:2431164",
        "tgn:1000001",
        "tgn:1002308",
        "tgn:7012149",
        "tgn:7007710",
        "tgn:7029392"
    ],
    "tgn:id":2431164,
    "tgn:name":"Kantz Corners",
    "tgn:placetype":[
        "aat:300008347"
    ]
},
  "bbox": [],
  "geometry": {"coordinates":[-80.05,41.5167],"type":"Point"}
}