{
  "id": 7429379,
  "type": "Feature",
  "properties": {
    "tgn:hierarchy":[
        "tgn:7429379",
        "tgn:1001853",
        "tgn:1000001",
        "tgn:7005560",
        "tgn:7029392"
    ],
    "tgn:id":7429379,
    "tgn:name":"Valle Hermanos",
    "tgn:placetype":[
        "aat:300008347"
    ]
},
  "bbox": [],
  "geometry": {"coordinates":[-102.216667,25.216667],"type":"Point"}
}