{
  "id": 7520502,
  "type": "Feature",
  "properties": {
    "tgn:hierarchy":[
        "tgn:7520502",
        "tgn:7001242",
        "tgn:7016833",
        "tgn:1001418",
        "tgn:7029392"
    ],
    "tgn:id":7520502,
    "tgn:name:en":"Ma\u1e29a\u0163\u0163at al Jar\u0101wilah",
    "tgn:placetype":[
        "aat:300007783"
    ]
},
  "bbox": [],
  "geometry": {"coordinates":[27.394562,31.239501],"type":"Point"}
}