{
  "id": 1118904,
  "type": "Feature",
  "properties": {
    "tgn:hierarchy":[
        "tgn:1118904",
        "tgn:1000004",
        "tgn:7014786",
        "tgn:7029392"
    ],
    "tgn:id":1118904,
    "tgn:name":"Alakol, Ozero",
    "tgn:placetype":[
        "aat:300266556"
    ]
},
  "bbox": [],
  "geometry": {"coordinates":[81.75,46.1667],"type":"Point"}
}