{
  "id": 2022230,
  "type": "Feature",
  "properties": {
    "tgn:hierarchy":[
        "tgn:2022230",
        "tgn:1000001",
        "tgn:2000314",
        "tgn:7012149",
        "tgn:7007248",
        "tgn:7029392"
    ],
    "tgn:id":2022230,
    "tgn:name":"Boyd Highlands",
    "tgn:placetype":[
        "aat:300008347"
    ]
},
  "bbox": [],
  "geometry": {"coordinates":[-85.1667,34.9667],"type":"Point"}
}