{
  "id": 2349769,
  "type": "Feature",
  "properties": {
    "tgn:hierarchy":[
        "tgn:2349769",
        "tgn:1000001",
        "tgn:7012149",
        "tgn:1002993",
        "tgn:7007568",
        "tgn:7029392"
    ],
    "tgn:id":2349769,
    "tgn:name":"Gillis Brook",
    "tgn:placetype":[
        "aat:300008699"
    ]
},
  "bbox": [],
  "geometry": {"coordinates":[-73.45,43.25],"type":"Point"}
}