{
  "id": 7345285,
  "type": "Feature",
  "properties": {
    "tgn:hierarchy":[
        "tgn:7345285",
        "tgn:7002813",
        "tgn:7002758",
        "tgn:1000003",
        "tgn:1000095",
        "tgn:7029392"
    ],
    "tgn:id":7345285,
    "tgn:name":"Algar, Mesa del",
    "tgn:placetype":[
        "aat:300008777"
    ]
},
  "bbox": [],
  "geometry": {"coordinates":[-5.916667,36.35],"type":"Point"}
}