{
  "id": 2165734,
  "type": "Feature",
  "properties": {
    "tgn:hierarchy":[
        "tgn:2165734",
        "tgn:2002308",
        "tgn:1000001",
        "tgn:7012149",
        "tgn:7007922",
        "tgn:7029392"
    ],
    "tgn:id":2165734,
    "tgn:name":"Bibon Lake",
    "tgn:placetype":[
        "aat:300008680"
    ]
},
  "bbox": [],
  "geometry": {"coordinates":[-91.3833,46.7833],"type":"Point"}
}