<<<<<<< HEAD
{
  "id": 7353581,
  "type": "Feature",
  "properties": {
    "tgn:hierarchy":[
        "tgn:7353581",
        "tgn:1000001",
        "tgn:7005590",
        "tgn:7005560",
        "tgn:7029392"
    ],
    "tgn:id":7353581,
    "tgn:name":"Azajo",
    "tgn:placetype":[
        "aat:300008347"
    ]
},
  "bbox": [],
  "geometry": {"coordinates":[-101.683333,19.7],"type":"Point"}
}
=======
{"geometry":{"type":"Point","coordinates":[-101.683333,19.700000]},"type":"Feature","properties":{"hierarchy":["tgn:7353581","tgn:1000001","tgn:7005590","tgn:7005560","tgn:7029392"],"placetype":["aat:300008347"],"id":7353581,"name:xx":"Azajo"}}
>>>>>>> 03f74aca74312dbeaf24d7e61306dd6a786dc3d0
