{
  "id": 2102070,
  "type": "Feature",
  "properties": {
    "tgn:hierarchy":[
        "tgn:2102070",
        "tgn:1000001",
        "tgn:7012149",
        "tgn:2001918",
        "tgn:7007825",
        "tgn:7029392"
    ],
    "tgn:id":2102070,
    "tgn:name":"West View Park",
    "tgn:placetype":[
        "aat:300008347"
    ]
},
  "bbox": [],
  "geometry": {"coordinates":[-82.5667,36.55],"type":"Point"}
}