{
  "id": 7526589,
  "type": "Feature",
  "properties": {
    "tgn:hierarchy":[
        "tgn:7526589",
        "tgn:7001242",
        "tgn:7016833",
        "tgn:1001091",
        "tgn:7029392"
    ],
    "tgn:id":7526589,
    "tgn:name":"Al Hay'ah al '\u0100mmah lil Taw\u1e29\u012bd al Qiy\u0101s\u012b",
    "tgn:placetype":[
        "aat:300004792"
    ]
},
  "bbox": [],
  "geometry": {"coordinates":[31.300183,30.109972],"type":"Point"}
}