{
  "id": 7443126,
  "type": "Feature",
  "properties": {
    "tgn:hierarchy":[
        "tgn:7443126",
        "tgn:7002445",
        "tgn:7008116",
        "tgn:1000003",
        "tgn:7008591",
        "tgn:7029392"
    ],
    "tgn:id":7443126,
    "tgn:name:en":"White Island",
    "tgn:placetype":[
        "aat:300008791"
    ]
},
  "bbox": [],
  "geometry": {"coordinates":[-6.291084,49.977721],"type":"Point"}
}