{
  "id": 2636768,
  "type": "Feature",
  "properties": {
    "tgn:hierarchy":[
        "tgn:2636768",
        "tgn:1000001",
        "tgn:7012149",
        "tgn:2002377",
        "tgn:7007923",
        "tgn:7029392"
    ],
    "tgn:id":2636768,
    "tgn:name":"Sagehen Hill",
    "tgn:placetype":[
        "aat:300008798"
    ]
},
  "bbox": [],
  "geometry": {"coordinates":[-107.15,42.7167],"type":"Point"}
}