<<<<<<< HEAD
{
  "id": 7026075,
  "type": "Feature",
  "properties": {
    "tgn:hierarchy":[
        "tgn:7026075",
        "tgn:7019073",
        "tgn:7002445",
        "tgn:7012026",
        "tgn:1000003",
        "tgn:7012033",
        "tgn:7008591",
        "tgn:7029392"
    ],
    "tgn:id":7026075,
    "tgn:name:en":"Elswick",
    "tgn:placetype":[
        "aat:300000745"
    ]
},
  "bbox": [],
  "geometry": {"coordinates":[-1.65,54.966667],"type":"Point"}
}
=======
{"geometry":{"type":"Point","coordinates":[-1.650000,54.966667]},"type":"Feature","properties":{"hierarchy":["tgn:7026075","tgn:7019073","tgn:7002445","tgn:7012026","tgn:1000003","tgn:7012033","tgn:7008591","tgn:7029392"],"placetype":["aat:300000745"],"name:en":"Elswick","id":7026075}}
>>>>>>> 03f74aca74312dbeaf24d7e61306dd6a786dc3d0
