{
  "id": 7320495,
  "type": "Feature",
  "properties": {
    "tgn:hierarchy":[
        "tgn:7320495",
        "tgn:7016598",
        "tgn:1000049",
        "tgn:1000002",
        "tgn:7029392"
    ],
    "tgn:id":7320495,
    "tgn:name":"Cangrejos, Pen\u00ednsula",
    "tgn:placetype":[
        "aat:300008804"
    ]
},
  "bbox": [],
  "geometry": {"coordinates":[-70.55,-24.366667],"type":"Point"}
}