{
  "id": 7399095,
  "type": "Feature",
  "properties": {
    "tgn:hierarchy":[
        "tgn:7399095",
        "tgn:1000001",
        "tgn:1001893",
        "tgn:7005560",
        "tgn:7029392"
    ],
    "tgn:id":7399095,
    "tgn:name":"Mayorazgo de Le\u00f3n",
    "tgn:placetype":[
        "aat:300008347"
    ]
},
  "bbox": [],
  "geometry": {"coordinates":[-99.758611,19.456667],"type":"Point"}
}