<<<<<<< HEAD
{
  "id": 7119013,
  "type": "Feature",
  "properties": {
    "tgn:hierarchy":[
        "tgn:7119013",
        "tgn:1000003",
        "tgn:7003688",
        "tgn:7000084",
        "tgn:7029392"
    ],
    "tgn:id":7119013,
    "tgn:name":"Prinzen-Insel",
    "tgn:placetype":[
        "aat:300008791"
    ]
},
  "bbox": [],
  "geometry": {"coordinates":[10.416667,54.15],"type":"Point"}
}
=======
{"geometry":{"type":"Point","coordinates":[10.416667,54.150000]},"type":"Feature","properties":{"hierarchy":["tgn:7119013","tgn:1000003","tgn:7003688","tgn:7000084","tgn:7029392"],"placetype":["aat:300008791"],"id":7119013,"name:xx":"Prinzen-Insel"}}
>>>>>>> 03f74aca74312dbeaf24d7e61306dd6a786dc3d0
