{
  "id": 7517924,
  "type": "Feature",
  "properties": {
    "tgn:hierarchy":[
        "tgn:7517924",
        "tgn:1009227",
        "tgn:1000226",
        "tgn:1000006",
        "tgn:7016850",
        "tgn:7029392"
    ],
    "tgn:id":7517924,
    "tgn:name:en":"Mawheraiti River",
    "tgn:placetype":[
        "aat:300008699"
    ]
},
  "bbox": [],
  "geometry": {"coordinates":[171.666667,-42.283333],"type":"Point"}
}