{
  "id": 2691498,
  "type": "Feature",
  "properties": {
    "tgn:hierarchy":[
        "tgn:2691498",
        "tgn:1000001",
        "tgn:7012149",
        "tgn:2000488",
        "tgn:7007250",
        "tgn:7029392"
    ],
    "tgn:id":2691498,
    "tgn:name":"Star Ranch Table",
    "tgn:placetype":[
        "aat:300008798"
    ]
},
  "bbox": [],
  "geometry": {"coordinates":[-116.7333,42.45],"type":"Point"}
}