{
  "id": 7314981,
  "type": "Feature",
  "properties": {
    "tgn:hierarchy":[
        "tgn:7314981",
        "tgn:1001702",
        "tgn:1000049",
        "tgn:1000002",
        "tgn:7029392"
    ],
    "tgn:id":7314981,
    "tgn:name":"Lewis, Bah\u00eda",
    "tgn:placetype":[
        "aat:300132316"
    ]
},
  "bbox": [],
  "geometry": {"coordinates":[-73.333333,-53.233333],"type":"Point"}
}