{
  "id": 7493550,
  "type": "Feature",
  "properties": {
    "tgn:hierarchy":[
        "tgn:7493550",
        "tgn:1000004",
        "tgn:7001013",
        "tgn:1000141",
        "tgn:7029392"
    ],
    "tgn:id":7493550,
    "tgn:name":"Xiacuo",
    "tgn:placetype":[
        "aat:300008347"
    ]
},
  "bbox": [],
  "geometry": {"coordinates":[121.285102,24.877137],"type":"Point"}
}