{
  "id": 2082930,
  "type": "Feature",
  "properties": {
    "tgn:hierarchy":[
        "tgn:2082930",
        "tgn:1000001",
        "tgn:7012149",
        "tgn:2001697",
        "tgn:7007707",
        "tgn:7029392"
    ],
    "tgn:id":2082930,
    "tgn:name":"Burns Flat",
    "tgn:placetype":[
        "aat:300008347"
    ]
},
  "bbox": [],
  "geometry": {"coordinates":[-99.1667,35.3333],"type":"Point"}
}