<<<<<<< HEAD
{
  "id": 2768075,
  "type": "Feature",
  "properties": {
    "tgn:hierarchy":[
        "tgn:2768075",
        "tgn:1000001",
        "tgn:7012149",
        "tgn:2002191",
        "tgn:7007919",
        "tgn:7029392"
    ],
    "tgn:id":2768075,
    "tgn:name":"Whiterock Mountain",
    "tgn:placetype":[
        "aat:300008798"
    ]
},
  "bbox": [],
  "geometry": {"coordinates":[-81.7667,36.9333],"type":"Point"}
}
=======
{"geometry":{"type":"Point","coordinates":[-81.766700,36.933300]},"type":"Feature","properties":{"hierarchy":["tgn:2768075","tgn:1000001","tgn:7012149","tgn:2002191","tgn:7007919","tgn:7029392"],"placetype":["aat:300008798"],"id":2768075,"name:xx":"Whiterock Mountain"}}
>>>>>>> 03f74aca74312dbeaf24d7e61306dd6a786dc3d0
