{
  "id": 2449554,
  "type": "Feature",
  "properties": {
    "tgn:hierarchy":[
        "tgn:2449554",
        "tgn:1000001",
        "tgn:7012149",
        "tgn:2001711",
        "tgn:7007708",
        "tgn:7029392"
    ],
    "tgn:id":2449554,
    "tgn:name":"Lincoln Creek",
    "tgn:placetype":[
        "aat:300008706"
    ]
},
  "bbox": [],
  "geometry": {"coordinates":[-122.4167,42.0667],"type":"Point"}
}