{
  "id": 2420321,
  "type": "Feature",
  "properties": {
    "tgn:hierarchy":[
        "tgn:2420321",
        "tgn:1000001",
        "tgn:2000467",
        "tgn:7012149",
        "tgn:7007250",
        "tgn:7029392"
    ],
    "tgn:id":2420321,
    "tgn:name":"Jeffs Spring",
    "tgn:placetype":[
        "aat:300008697"
    ]
},
  "bbox": [],
  "geometry": {"coordinates":[-114.2167,42.3333],"type":"Point"}
}