{
  "id": 2291634,
  "type": "Feature",
  "properties": {
    "tgn:hierarchy":[
        "tgn:2291634",
        "tgn:7002659",
        "tgn:1000001",
        "tgn:7012149",
        "tgn:2000031",
        "tgn:7029392"
    ],
    "tgn:id":2291634,
    "tgn:name":"Dollarhide Camp Lake",
    "tgn:placetype":[
        "aat:300006191"
    ]
},
  "bbox": [],
  "geometry": {"coordinates":[-87.85,32.7333],"type":"Point"}
}