{
  "id": 2109577,
  "type": "Feature",
  "properties": {
    "tgn:hierarchy":[
        "tgn:2109577",
        "tgn:1000001",
        "tgn:2002134",
        "tgn:7012149",
        "tgn:7007828",
        "tgn:7029392"
    ],
    "tgn:id":2109577,
    "tgn:name":"East Brookfield",
    "tgn:placetype":[
        "aat:300008347"
    ]
},
  "bbox": [],
  "geometry": {"coordinates":[-72.5667,44.0167],"type":"Point"}
}