{
  "id": 2330494,
  "type": "Feature",
  "properties": {
    "tgn:hierarchy":[
        "tgn:2330494",
        "tgn:1000001",
        "tgn:7012149",
        "tgn:2000445",
        "tgn:7007248",
        "tgn:7029392"
    ],
    "tgn:id":2330494,
    "tgn:name":"Flat Creek",
    "tgn:placetype":[
        "aat:300008706"
    ]
},
  "bbox": [],
  "geometry": {"coordinates":[-83.6667,34.5833],"type":"Point"}
}