{
  "id": 2374733,
  "type": "Feature",
  "properties": {
    "tgn:hierarchy":[
        "tgn:2374733",
        "tgn:1000001",
        "tgn:7016172",
        "tgn:7012149",
        "tgn:2000126",
        "tgn:7029392"
    ],
    "tgn:id":2374733,
    "tgn:name":"Handly Creek",
    "tgn:placetype":[
        "aat:300008706"
    ]
},
  "bbox": [],
  "geometry": {"coordinates":[-91.8167,33.7667],"type":"Point"}
}