{
  "id": 2417845,
  "type": "Feature",
  "properties": {
    "tgn:hierarchy":[
        "tgn:2417845",
        "tgn:1000001",
        "tgn:7012149",
        "tgn:2002196",
        "tgn:7007919",
        "tgn:7029392"
    ],
    "tgn:id":2417845,
    "tgn:name":"Jackson Hollow",
    "tgn:placetype":[
        "aat:300008761"
    ]
},
  "bbox": [],
  "geometry": {"coordinates":[-81.1333,36.7833],"type":"Point"}
}