{
  "id": 2783026,
  "type": "Feature",
  "properties": {
    "tgn:hierarchy":[
        "tgn:2783026",
        "tgn:1000001",
        "tgn:7012149",
        "tgn:2000363",
        "tgn:7007248",
        "tgn:7029392"
    ],
    "tgn:id":2783026,
    "tgn:name":"Wren Lake",
    "tgn:placetype":[
        "aat:300006191"
    ]
},
  "bbox": [],
  "geometry": {"coordinates":[-84.8167,32.8333],"type":"Point"}
}