{
  "id": 7071325,
  "type": "Feature",
  "properties": {
    "tgn:hierarchy":[
        "tgn:7071325",
        "tgn:7003669",
        "tgn:1000003",
        "tgn:7000084",
        "tgn:7029392"
    ],
    "tgn:id":7071325,
    "tgn:name":"S\u00fcsswies",
    "tgn:placetype":[
        "aat:300387200"
    ]
},
  "bbox": [],
  "geometry": {"coordinates":[12.433333,48.733333],"type":"Point"}
}