{
  "id": 2539346,
  "type": "Feature",
  "properties": {
    "tgn:hierarchy":[
        "tgn:2539346",
        "tgn:1000001",
        "tgn:7012149",
        "tgn:2001718",
        "tgn:7007708",
        "tgn:7029392"
    ],
    "tgn:id":2539346,
    "tgn:name":"New Juniper Spring",
    "tgn:placetype":[
        "aat:300008697"
    ]
},
  "bbox": [],
  "geometry": {"coordinates":[-117.9333,43.9333],"type":"Point"}
}