{
  "id": 2517689,
  "type": "Feature",
  "properties": {
    "tgn:hierarchy":[
        "tgn:2517689",
        "tgn:1000001",
        "tgn:7012149",
        "tgn:1002545",
        "tgn:7007157",
        "tgn:7029392"
    ],
    "tgn:id":2517689,
    "tgn:name":"Mirasol Ditch",
    "tgn:placetype":[
        "aat:300006075"
    ]
},
  "bbox": [],
  "geometry": {"coordinates":[-119.4667,35.3667],"type":"Point"}
}