{
  "id": 7507198,
  "type": "Feature",
  "properties": {
    "tgn:hierarchy":[
        "tgn:7507198",
        "tgn:1008380",
        "tgn:1000226",
        "tgn:7016827",
        "tgn:1000006",
        "tgn:7029392"
    ],
    "tgn:id":7507198,
    "tgn:name:en":"Puniwhakau",
    "tgn:placetype":[
        "aat:300008795"
    ]
},
  "bbox": [],
  "geometry": {"coordinates":[174.65,-39.316667],"type":"Point"}
}