{
  "id": 2282922,
  "type": "Feature",
  "properties": {
    "tgn:hierarchy":[
        "tgn:2282922",
        "tgn:1000001",
        "tgn:7012149",
        "tgn:7007251",
        "tgn:7029392"
    ],
    "tgn:id":2282922,
    "tgn:name":"Degognia Creek",
    "tgn:placetype":[
        "aat:300008706"
    ]
},
  "bbox": [],
  "geometry": {"coordinates":[-89.65,37.85],"type":"Point"}
}