<<<<<<< HEAD
{
  "id": 2251425,
  "type": "Feature",
  "properties": {
    "tgn:hierarchy":[
        "tgn:2251425",
        "tgn:1000001",
        "tgn:1002261",
        "tgn:7012149",
        "tgn:7007568",
        "tgn:7029392"
    ],
    "tgn:id":2251425,
    "tgn:name":"Comfort Hill",
    "tgn:placetype":[
        "aat:300008798"
    ]
},
  "bbox": [],
  "geometry": {"coordinates":[-76.7833,42.0167],"type":"Point"}
}
=======
{"geometry":{"type":"Point","coordinates":[-76.783300,42.016700]},"type":"Feature","properties":{"hierarchy":["tgn:2251425","tgn:1000001","tgn:1002261","tgn:7012149","tgn:7007568","tgn:7029392"],"placetype":["aat:300008798"],"id":2251425,"name:xx":"Comfort Hill"}}
>>>>>>> 03f74aca74312dbeaf24d7e61306dd6a786dc3d0
