{
  "id": 2568654,
  "type": "Feature",
  "properties": {
    "tgn:hierarchy":[
        "tgn:2568654",
        "tgn:1000001",
        "tgn:7012149",
        "tgn:2000930",
        "tgn:7007515",
        "tgn:7029392"
    ],
    "tgn:id":2568654,
    "tgn:name":"Parker Bog Ponds",
    "tgn:placetype":[
        "aat:300008680"
    ]
},
  "bbox": [],
  "geometry": {"coordinates":[-70.2167,45.35],"type":"Point"}
}