{
  "id": 7333090,
  "type": "Feature",
  "properties": {
    "tgn:hierarchy":[
        "tgn:7333090",
        "tgn:7002836",
        "tgn:7016622",
        "tgn:1000003",
        "tgn:1000095",
        "tgn:7029392"
    ],
    "tgn:id":7333090,
    "tgn:name":"La Matanza de Acentejo",
    "tgn:placetype":[
        "aat:300008347"
    ]
},
  "bbox": [],
  "geometry": {"coordinates":[-16.45,28.433333],"type":"Point"}
}