<<<<<<< HEAD
{
  "id": 7352239,
  "type": "Feature",
  "properties": {
    "tgn:hierarchy":[
        "tgn:7352239",
        "tgn:1000001",
        "tgn:1001906",
        "tgn:7005560",
        "tgn:7029392"
    ],
    "tgn:id":7352239,
    "tgn:name":"Altavista",
    "tgn:placetype":[
        "aat:300008347"
    ]
},
  "bbox": [],
  "geometry": {"coordinates":[-105.15,21.083333],"type":"Point"}
}
=======
{"geometry":{"type":"Point","coordinates":[-105.150000,21.083333]},"type":"Feature","properties":{"hierarchy":["tgn:7352239","tgn:1000001","tgn:1001906","tgn:7005560","tgn:7029392"],"placetype":["aat:300008347"],"id":7352239,"name:xx":"Altavista"}}
>>>>>>> 03f74aca74312dbeaf24d7e61306dd6a786dc3d0
