{
  "id": 7537216,
  "type": "Feature",
  "properties": {
    "tgn:hierarchy":[
        "tgn:7537216",
        "tgn:7001242",
        "tgn:7016833",
        "tgn:1001418",
        "tgn:7029392"
    ],
    "tgn:id":7537216,
    "tgn:name:en":"Misharrik, Diyur el",
    "tgn:placetype":[
        "aat:300386860"
    ]
},
  "bbox": [],
  "geometry": {"coordinates":[27.459664,30.373886],"type":"Point"}
}