{
  "id": 7591906,
  "type": "Feature",
  "properties": {
    "tgn:hierarchy":[
        "tgn:7591906",
        "tgn:1000004",
        "tgn:7000198",
        "tgn:7000799",
        "tgn:7029392"
    ],
    "tgn:id":7591906,
    "tgn:name:en":"Tar\u0101li",
    "tgn:placetype":[
        "aat:300008347"
    ]
},
  "bbox": [],
  "geometry": {"coordinates":[74.221973,33.170194],"type":"Point"}
}