{
  "id": 2391162,
  "type": "Feature",
  "properties": {
    "tgn:hierarchy":[
        "tgn:2391162",
        "tgn:7002659",
        "tgn:1000001",
        "tgn:2000011",
        "tgn:7012149",
        "tgn:7029392"
    ],
    "tgn:id":2391162,
    "tgn:name":"Hill Mountain",
    "tgn:placetype":[
        "aat:300008798"
    ]
},
  "bbox": [],
  "geometry": {"coordinates":[-88.2667,32.0333],"type":"Point"}
}