{
  "id": 2370306,
  "type": "Feature",
  "properties": {
    "tgn:hierarchy":[
        "tgn:2370306",
        "tgn:1000001",
        "tgn:2001418",
        "tgn:7012149",
        "tgn:7007526",
        "tgn:7029392"
    ],
    "tgn:id":2370306,
    "tgn:name":"Gypsy Queen Mine",
    "tgn:placetype":[
        "aat:300000390"
    ]
},
  "bbox": [],
  "geometry": {"coordinates":[-117.2167,38.0667],"type":"Point"}
}