{
  "id": 7034093,
  "type": "Feature",
  "properties": {
    "tgn:hierarchy":[
        "tgn:7034093",
        "tgn:1003468",
        "tgn:1000003",
        "tgn:7010380",
        "tgn:1000080",
        "tgn:7029392"
    ],
    "tgn:id":7034093,
    "tgn:name":"Villa Marini",
    "tgn:placetype":[
        "aat:300005433"
    ]
},
  "bbox": [],
  "geometry": {"coordinates":[18.046111,40.417222],"type":"Point"}
}