{
  "id": 2594754,
  "type": "Feature",
  "properties": {
    "tgn:hierarchy":[
        "tgn:2594754",
        "tgn:1000001",
        "tgn:7012149",
        "tgn:2000401",
        "tgn:7007248",
        "tgn:7029392"
    ],
    "tgn:id":2594754,
    "tgn:name":"Possum Creek",
    "tgn:placetype":[
        "aat:300008706"
    ]
},
  "bbox": [],
  "geometry": {"coordinates":[-84.7667,33.9167],"type":"Point"}
}