<<<<<<< HEAD
{
  "id": 7249278,
  "type": "Feature",
  "properties": {
    "tgn:hierarchy":[
        "tgn:7249278",
        "tgn:7007877",
        "tgn:1000003",
        "tgn:1000063",
        "tgn:4012014",
        "tgn:7029392"
    ],
    "tgn:id":7249278,
    "tgn:name":"Moniat, Bois du",
    "tgn:placetype":[
        "aat:300008863"
    ]
},
  "bbox": [],
  "geometry": {"coordinates":[4.566667,50.45],"type":"Point"}
}
=======
{"geometry":{"type":"Point","coordinates":[4.566667,50.450000]},"type":"Feature","properties":{"hierarchy":["tgn:7249278","tgn:7007877","tgn:1000003","tgn:1000063","tgn:4012014","tgn:7029392"],"placetype":["aat:300008863"],"id":7249278,"name:xx":"Moniat, Bois du"}}
>>>>>>> 03f74aca74312dbeaf24d7e61306dd6a786dc3d0
