{
  "id": 7350967,
  "type": "Feature",
  "properties": {
    "tgn:hierarchy":[
        "tgn:7350967",
        "tgn:1000001",
        "tgn:1001960",
        "tgn:7005560",
        "tgn:7029392"
    ],
    "tgn:id":7350967,
    "tgn:name":"Baj\u00edo",
    "tgn:placetype":[
        "aat:300008347"
    ]
},
  "bbox": [],
  "geometry": {"coordinates":[-109.55,28.483333],"type":"Point"}
}