{
  "id": 7556797,
  "type": "Feature",
  "properties": {
    "tgn:hierarchy":[
        "tgn:7556797",
        "tgn:1000004",
        "tgn:7000198",
        "tgn:7016788",
        "tgn:7029392"
    ],
    "tgn:id":7556797,
    "tgn:name:en":"Sai River",
    "tgn:placetype":[
        "aat:300008699"
    ]
},
  "bbox": [],
  "geometry": {"coordinates":[73.015274,24.241558],"type":"Point"}
}