{
  "id": 7304769,
  "type": "Feature",
  "properties": {
    "tgn:hierarchy":[
        "tgn:7304769",
        "tgn:7008911",
        "tgn:1000003",
        "tgn:7002763",
        "tgn:1000095",
        "tgn:7029392"
    ],
    "tgn:id":7304769,
    "tgn:name":"La Villa",
    "tgn:placetype":[
        "aat:300008347"
    ]
},
  "bbox": [],
  "geometry": {"coordinates":[-5.966667,43.166667],"type":"Point"}
}