{
  "id": 2539001,
  "type": "Feature",
  "properties": {
    "tgn:hierarchy":[
        "tgn:2539001",
        "tgn:1000001",
        "tgn:7012149",
        "tgn:2002154",
        "tgn:7007919",
        "tgn:7029392"
    ],
    "tgn:id":2539001,
    "tgn:name":"New Castle Murder Hole",
    "tgn:placetype":[
        "aat:300008746"
    ]
},
  "bbox": [],
  "geometry": {"coordinates":[-80.1333,37.4667],"type":"Point"}
}