{
  "id": 7280743,
  "type": "Feature",
  "properties": {
    "tgn:hierarchy":[
        "tgn:7280743",
        "tgn:1001768",
        "tgn:1000049",
        "tgn:1000002",
        "tgn:7029392"
    ],
    "tgn:id":7280743,
    "tgn:name":"Talca, Punta",
    "tgn:placetype":[
        "aat:300386846"
    ]
},
  "bbox": [],
  "geometry": {"coordinates":[-71.702778,-33.418333],"type":"Point"}
}