{
  "id": 7032548,
  "type": "Feature",
  "properties": {
    "tgn:hierarchy":[
        "tgn:7032548",
        "tgn:7003712",
        "tgn:7003670",
        "tgn:1000003",
        "tgn:7000084",
        "tgn:7029392"
    ],
    "tgn:id":7032548,
    "tgn:name":"Treptow-K\u00f6penick",
    "tgn:placetype":[
        "aat:300387145",
        "aat:300387333"
    ]
},
  "bbox": [],
  "geometry": {"coordinates":[13.583333,52.45],"type":"Point"}
}