{
  "id": 2176584,
  "type": "Feature",
  "properties": {
    "tgn:hierarchy":[
        "tgn:2176584",
        "tgn:1000001",
        "tgn:7012149",
        "tgn:1002214",
        "tgn:7007826",
        "tgn:7029392"
    ],
    "tgn:id":2176584,
    "tgn:name":"Black Lake",
    "tgn:placetype":[
        "aat:300008680"
    ]
},
  "bbox": [],
  "geometry": {"coordinates":[-96.55,30.5833],"type":"Point"}
}