{
  "id": 2022986,
  "type": "Feature",
  "properties": {
    "tgn:hierarchy":[
        "tgn:2022986",
        "tgn:1000001",
        "tgn:7012149",
        "tgn:2000421",
        "tgn:7007248",
        "tgn:7029392"
    ],
    "tgn:id":2022986,
    "tgn:name":"Geneva",
    "tgn:placetype":[
        "aat:300008347"
    ]
},
  "bbox": [],
  "geometry": {"coordinates":[-84.55,32.5667],"type":"Point"}
}