{
  "id": 2008942,
  "type": "Feature",
  "properties": {
    "tgn:hierarchy":[
        "tgn:2008942",
        "tgn:1000001",
        "tgn:7016172",
        "tgn:2000115",
        "tgn:7012149",
        "tgn:7029392"
    ],
    "tgn:id":2008942,
    "tgn:name":"Moark",
    "tgn:placetype":[
        "aat:300008347"
    ]
},
  "bbox": [],
  "geometry": {"coordinates":[-90.5167,36.4833],"type":"Point"}
}