{
  "id": 2078325,
  "type": "Feature",
  "properties": {
    "tgn:hierarchy":[
        "tgn:2078325",
        "tgn:1002175",
        "tgn:1000001",
        "tgn:7012149",
        "tgn:7007706",
        "tgn:7029392"
    ],
    "tgn:id":2078325,
    "tgn:name":"Badgertown",
    "tgn:placetype":[
        "aat:300008347",
        "aat:300387210"
    ]
},
  "bbox": [],
  "geometry": {"coordinates":[-81.0667,40.0167],"type":"Point"}
}