{
  "id": 2372854,
  "type": "Feature",
  "properties": {
    "tgn:hierarchy":[
        "tgn:2372854",
        "tgn:1000001",
        "tgn:7006451",
        "tgn:7012149",
        "tgn:2000100",
        "tgn:7029392"
    ],
    "tgn:id":2372854,
    "tgn:name":"Hall Tank",
    "tgn:placetype":[
        "aat:300006191"
    ]
},
  "bbox": [],
  "geometry": {"coordinates":[-111.2833,31.95],"type":"Point"}
}