{
  "id": 7210828,
  "type": "Feature",
  "properties": {
    "tgn:hierarchy":[
        "tgn:7210828",
        "tgn:7003669",
        "tgn:1000003",
        "tgn:7000084",
        "tgn:7029392"
    ],
    "tgn:id":7210828,
    "tgn:name":"Berghof",
    "tgn:placetype":[
        "aat:300000206"
    ]
},
  "bbox": [],
  "geometry": {"coordinates":[12.133333,49.183333],"type":"Point"}
}