{
  "id": 2783748,
  "type": "Feature",
  "properties": {
    "tgn:hierarchy":[
        "tgn:2783748",
        "tgn:1000001",
        "tgn:7012149",
        "tgn:2000909",
        "tgn:7007256",
        "tgn:7029392"
    ],
    "tgn:id":2783748,
    "tgn:name":"Wynn Branch",
    "tgn:placetype":[
        "aat:300008699"
    ]
},
  "bbox": [],
  "geometry": {"coordinates":[-92.5833,32.7833],"type":"Point"}
}