{
  "id": 2232461,
  "type": "Feature",
  "properties": {
    "tgn:hierarchy":[
        "tgn:2232461",
        "tgn:1000001",
        "tgn:7012149",
        "tgn:2001067",
        "tgn:7007521",
        "tgn:7029392"
    ],
    "tgn:id":2232461,
    "tgn:name":"Chant Lake",
    "tgn:placetype":[
        "aat:300008680"
    ]
},
  "bbox": [],
  "geometry": {"coordinates":[-91.9667,47.95],"type":"Point"}
}