{
  "id": 7526691,
  "type": "Feature",
  "properties": {
    "tgn:hierarchy":[
        "tgn:7526691",
        "tgn:7001242",
        "tgn:7016833",
        "tgn:1001418",
        "tgn:7029392"
    ],
    "tgn:id":7526691,
    "tgn:name:en":"Sidi Mohammed el Sogh\u00eeyer",
    "tgn:placetype":[
        "aat:300007558"
    ]
},
  "bbox": [],
  "geometry": {"coordinates":[26.334456,30.867672],"type":"Point"}
}