{
  "id": 2723680,
  "type": "Feature",
  "properties": {
    "tgn:hierarchy":[
        "tgn:2723680",
        "tgn:1000001",
        "tgn:7012149",
        "tgn:7019676",
        "tgn:7007566",
        "tgn:7029392"
    ],
    "tgn:id":2723680,
    "tgn:name":"Todilto Park",
    "tgn:placetype":[
        "aat:300055621"
    ]
},
  "bbox": [],
  "geometry": {"coordinates":[-108.95,33.95],"type":"Point"}
}