{
  "id": 2480204,
  "type": "Feature",
  "properties": {
    "tgn:hierarchy":[
        "tgn:2480204",
        "tgn:1000001",
        "tgn:2000199",
        "tgn:7012149",
        "tgn:7007158",
        "tgn:7029392"
    ],
    "tgn:id":2480204,
    "tgn:name":"Lake O'Haver",
    "tgn:placetype":[
        "aat:300006191"
    ]
},
  "bbox": [],
  "geometry": {"coordinates":[-106.1333,38.4167],"type":"Point"}
}