{
  "id": 7288383,
  "type": "Feature",
  "properties": {
    "tgn:hierarchy":[
        "tgn:7288383",
        "tgn:1001623",
        "tgn:1000049",
        "tgn:1000002",
        "tgn:7029392"
    ],
    "tgn:id":7288383,
    "tgn:name":"Jasmund, Punta",
    "tgn:placetype":[
        "aat:300386846"
    ]
},
  "bbox": [],
  "geometry": {"coordinates":[-75.016667,-48.466667],"type":"Point"}
}