{
  "id": 2314929,
  "type": "Feature",
  "properties": {
    "tgn:hierarchy":[
        "tgn:2314929",
        "tgn:1000001",
        "tgn:7012149",
        "tgn:7007157",
        "tgn:1002901",
        "tgn:7029392"
    ],
    "tgn:id":2314929,
    "tgn:name":"Elkhorn Slough",
    "tgn:placetype":[
        "aat:300008699"
    ]
},
  "bbox": [],
  "geometry": {"coordinates":[-121.6167,38.2833],"type":"Point"}
}