{
  "id": 2745880,
  "type": "Feature",
  "properties": {
    "tgn:hierarchy":[
        "tgn:2745880",
        "tgn:1000001",
        "tgn:7012149",
        "tgn:7007566",
        "tgn:7029392"
    ],
    "tgn:id":2745880,
    "tgn:name":"Vivian, Ca\u00f1ada",
    "tgn:placetype":[
        "aat:300008699"
    ]
},
  "bbox": [],
  "geometry": {"coordinates":[-107.4667,33.4833],"type":"Point"}
}