<<<<<<< HEAD
{
  "id": 7470863,
  "type": "Feature",
  "properties": {
    "tgn:hierarchy":[
        "tgn:7470863",
        "tgn:1000004",
        "tgn:7490934",
        "tgn:1000141",
        "tgn:7029392"
    ],
    "tgn:id":7470863,
    "tgn:name":"Qiuzhuyuan",
    "tgn:placetype":[
        "aat:300008347"
    ]
},
  "bbox": [],
  "geometry": {"coordinates":[120.166667,23.183333],"type":"Point"}
}
=======
{"geometry":{"type":"Point","coordinates":[120.166667,23.183333]},"type":"Feature","properties":{"hierarchy":["tgn:7470863","tgn:1000004","tgn:7490934","tgn:1000141","tgn:7029392"],"placetype":["aat:300008347"],"id":7470863,"name:xx":"Qiuzhuyuan"}}
>>>>>>> 03f74aca74312dbeaf24d7e61306dd6a786dc3d0
