{
  "id": 2545679,
  "type": "Feature",
  "properties": {
    "tgn:hierarchy":[
        "tgn:2545679",
        "tgn:1000001",
        "tgn:7012149",
        "tgn:2002069",
        "tgn:7007826",
        "tgn:7029392"
    ],
    "tgn:id":2545679,
    "tgn:name":"North Fork Cherokee Creek",
    "tgn:placetype":[
        "aat:300008706"
    ]
},
  "bbox": [],
  "geometry": {"coordinates":[-98.8667,30.9833],"type":"Point"}
}