{
  "id": 2724883,
  "type": "Feature",
  "properties": {
    "tgn:hierarchy":[
        "tgn:2724883",
        "tgn:2001726",
        "tgn:1000001",
        "tgn:7012149",
        "tgn:7007712",
        "tgn:7029392"
    ],
    "tgn:id":2724883,
    "tgn:name":"Toms Branch",
    "tgn:placetype":[
        "aat:300008699"
    ]
},
  "bbox": [],
  "geometry": {"coordinates":[-81.4667,33.7333],"type":"Point"}
}