{
  "id": 2001113,
  "type": "Feature",
  "properties": {
    "tgn:hierarchy":[
        "tgn:2001113",
        "tgn:1000001",
        "tgn:7012149",
        "tgn:7007522",
        "tgn:7029392"
    ],
    "tgn:id":2001113,
    "tgn:name":"Issaquena",
    "tgn:placetype":[
        "aat:300387145",
        "aat:300000771"
    ]
},
  "bbox": [],
  "geometry": {"coordinates":[-90.9667,32.8333],"type":"Point"}
}