{
  "id": 2191930,
  "type": "Feature",
  "properties": {
    "tgn:hierarchy":[
        "tgn:2191930",
        "tgn:7006450",
        "tgn:1000001",
        "tgn:7012149",
        "tgn:2124002",
        "tgn:7029392"
    ],
    "tgn:id":2191930,
    "tgn:name":"Brady Island",
    "tgn:placetype":[
        "aat:300008791"
    ]
},
  "bbox": [],
  "geometry": {"coordinates":[-135.55,57.1833],"type":"Point"}
}