{
  "id": 7179246,
  "type": "Feature",
  "properties": {
    "tgn:hierarchy":[
        "tgn:7179246",
        "tgn:7003669",
        "tgn:1000003",
        "tgn:7000084",
        "tgn:7029392"
    ],
    "tgn:id":7179246,
    "tgn:name":"Haberleuthen",
    "tgn:placetype":[
        "aat:300000206"
    ]
},
  "bbox": [],
  "geometry": {"coordinates":[13.016667,48.966667],"type":"Point"}
}