{
  "id": 2384165,
  "type": "Feature",
  "properties": {
    "tgn:hierarchy":[
        "tgn:2384165",
        "tgn:7006450",
        "tgn:1000001",
        "tgn:7019674",
        "tgn:7012149",
        "tgn:7029392"
    ],
    "tgn:id":2384165,
    "tgn:name":"Heim Creek",
    "tgn:placetype":[
        "aat:300008706"
    ]
},
  "bbox": [],
  "geometry": {"coordinates":[-147.0833,65.0833],"type":"Point"}
}