{
  "id": 1077153,
  "type": "Feature",
  "properties": {
    "tgn:hierarchy":[
        "tgn:1077153",
        "tgn:1000004",
        "tgn:7000198",
        "tgn:1001895",
        "tgn:7029392"
    ],
    "tgn:id":1077153,
    "tgn:name:en":"Th\u0101kurv\u0101di",
    "tgn:placetype":[
        "aat:300008347"
    ]
},
  "bbox": [],
  "geometry": {"coordinates":[73.366667,18.816667],"type":"Point"}
}