{
  "id": 2542472,
  "type": "Feature",
  "properties": {
    "tgn:hierarchy":[
        "tgn:2542472",
        "tgn:1000001",
        "tgn:7012149",
        "tgn:2000987",
        "tgn:7007520",
        "tgn:7029392"
    ],
    "tgn:id":2542472,
    "tgn:name":"No Sho Mo, Lake",
    "tgn:placetype":[
        "aat:300008680"
    ]
},
  "bbox": [],
  "geometry": {"coordinates":[-85.5167,43.8833],"type":"Point"}
}