{
  "id": 2518545,
  "type": "Feature",
  "properties": {
    "tgn:hierarchy":[
        "tgn:2518545",
        "tgn:1000001",
        "tgn:7012149",
        "tgn:2001710",
        "tgn:7007708",
        "tgn:7029392"
    ],
    "tgn:id":2518545,
    "tgn:name":"Mitchell Creek",
    "tgn:placetype":[
        "aat:300008706"
    ]
},
  "bbox": [],
  "geometry": {"coordinates":[-121.6667,45.3333],"type":"Point"}
}