{
  "id": 7011900,
  "type": "Feature",
  "properties": {
    "tgn:hierarchy":[
        "tgn:7011900",
        "tgn:7002445",
        "tgn:7008104",
        "tgn:1000003",
        "tgn:7008591",
        "tgn:7029392"
    ],
    "tgn:id":7011900,
    "tgn:name:ang":"Wicumbe",
    "tgn:placetype":[
        "aat:300008347",
        "aat:300387308",
        "aat:300008375",
        "aat:300387302"
    ]
},
  "bbox": [],
  "geometry": {"coordinates":[-0.766667,51.633333],"type":"Point"}
}