{
  "id": 7034803,
  "type": "Feature",
  "properties": {
    "tgn:hierarchy":[
        "tgn:7034803",
        "tgn:7015163",
        "tgn:1000003",
        "tgn:7003121",
        "tgn:1000080",
        "tgn:7029392"
    ],
    "tgn:id":7034803,
    "tgn:name":"Frigiano, Secca di",
    "tgn:placetype":[
        "aat:300387036"
    ]
},
  "bbox": [],
  "geometry": {"coordinates":[8.693333,40.925],"type":"Point"}
}