{
  "id": 2386867,
  "type": "Feature",
  "properties": {
    "tgn:hierarchy":[
        "tgn:2386867",
        "tgn:1000001",
        "tgn:7012149",
        "tgn:2000491",
        "tgn:7007250",
        "tgn:7029392"
    ],
    "tgn:id":2386867,
    "tgn:name":"Hero Lake",
    "tgn:placetype":[
        "aat:300008680"
    ]
},
  "bbox": [],
  "geometry": {"coordinates":[-115.5833,46.9667],"type":"Point"}
}