{
  "id": 2185368,
  "type": "Feature",
  "properties": {
    "tgn:hierarchy":[
        "tgn:2185368",
        "tgn:1000001",
        "tgn:7012149",
        "tgn:2000520",
        "tgn:7007251",
        "tgn:7029392"
    ],
    "tgn:id":2185368,
    "tgn:name":"Bogus Chute",
    "tgn:placetype":[
        "aat:300008699"
    ]
},
  "bbox": [],
  "geometry": {"coordinates":[-91.0833,41.2667],"type":"Point"}
}