<<<<<<< HEAD
{
  "id": 7372862,
  "type": "Feature",
  "properties": {
    "tgn:hierarchy":[
        "tgn:7372862",
        "tgn:7005587",
        "tgn:1000001",
        "tgn:7005560",
        "tgn:7029392"
    ],
    "tgn:id":7372862,
    "tgn:name":"La Florida",
    "tgn:placetype":[
        "aat:300008347"
    ]
},
  "bbox": [],
  "geometry": {"coordinates":[-98.366667,20.3],"type":"Point"}
}
=======
{"geometry":{"type":"Point","coordinates":[-98.366667,20.300000]},"type":"Feature","properties":{"hierarchy":["tgn:7372862","tgn:7005587","tgn:1000001","tgn:7005560","tgn:7029392"],"placetype":["aat:300008347"],"id":7372862,"name:xx":"La Florida"}}
>>>>>>> 03f74aca74312dbeaf24d7e61306dd6a786dc3d0
