{
  "id": 7578003,
  "type": "Feature",
  "properties": {
    "tgn:hierarchy":[
        "tgn:7578003",
        "tgn:1000004",
        "tgn:7000198",
        "tgn:7016722",
        "tgn:7029392"
    ],
    "tgn:id":7578003,
    "tgn:name:en":"Khundaur",
    "tgn:placetype":[
        "aat:300008347"
    ]
},
  "bbox": [],
  "geometry": {"coordinates":[82.023379,26.035382],"type":"Point"}
}