{
  "id": 7248704,
  "type": "Feature",
  "properties": {
    "tgn:hierarchy":[
        "tgn:7248704",
        "tgn:7003458",
        "tgn:1000003",
        "tgn:1000063",
        "tgn:7018236",
        "tgn:7029392"
    ],
    "tgn:id":7248704,
    "tgn:name":"Boekhout",
    "tgn:placetype":[
        "aat:300008347"
    ]
},
  "bbox": [],
  "geometry": {"coordinates":[3.253249,51.043575],"type":"Point"}
}