{
  "id": 7274291,
  "type": "Feature",
  "properties": {
    "tgn:hierarchy":[
        "tgn:7274291",
        "tgn:7003614",
        "tgn:1000003",
        "tgn:7016845",
        "tgn:7029392"
    ],
    "tgn:id":7274291,
    "tgn:name:nl":"Zuides",
    "tgn:placetype":[
        "aat:300387200"
    ]
},
  "bbox": [],
  "geometry": {"coordinates":[6.733333,53.05],"type":"Point"}
}