{
  "id": 2505403,
  "type": "Feature",
  "properties": {
    "tgn:hierarchy":[
        "tgn:2505403",
        "tgn:1000001",
        "tgn:7012149",
        "tgn:2002099",
        "tgn:7007826",
        "tgn:7029392"
    ],
    "tgn:id":2505403,
    "tgn:name":"Melones, Arroyo",
    "tgn:placetype":[
        "aat:300008761"
    ]
},
  "bbox": [],
  "geometry": {"coordinates":[-99.1667,26.7667],"type":"Point"}
}