{
  "id": 7501731,
  "type": "Feature",
  "properties": {
    "tgn:hierarchy":[
        "tgn:7501731",
        "tgn:1000004",
        "tgn:7001009",
        "tgn:1000141",
        "tgn:7029392"
    ],
    "tgn:id":7501731,
    "tgn:name":"Houdongkeng",
    "tgn:placetype":[
        "aat:300008347"
    ]
},
  "bbox": [],
  "geometry": {"coordinates":[120.848078,24.066542],"type":"Point"}
}