<<<<<<< HEAD
{
  "id": 2252316,
  "type": "Feature",
  "properties": {
    "tgn:hierarchy":[
        "tgn:2252316",
        "tgn:1000001",
        "tgn:7012149",
        "tgn:2000471",
        "tgn:7007250",
        "tgn:7029392"
    ],
    "tgn:id":2252316,
    "tgn:name":"Confusion Lake",
    "tgn:placetype":[
        "aat:300008680"
    ]
},
  "bbox": [],
  "geometry": {"coordinates":[-115.05,43.9333],"type":"Point"}
}
=======
{"geometry":{"type":"Point","coordinates":[-115.050000,43.933300]},"type":"Feature","properties":{"hierarchy":["tgn:2252316","tgn:1000001","tgn:7012149","tgn:2000471","tgn:7007250","tgn:7029392"],"placetype":["aat:300008680"],"id":2252316,"name:xx":"Confusion Lake"}}
>>>>>>> 03f74aca74312dbeaf24d7e61306dd6a786dc3d0
