{
  "id": 2103474,
  "type": "Feature",
  "properties": {
    "tgn:hierarchy":[
        "tgn:2103474",
        "tgn:1000001",
        "tgn:7012149",
        "tgn:1002303",
        "tgn:7007826",
        "tgn:7029392"
    ],
    "tgn:id":2103474,
    "tgn:name":"Coryell",
    "tgn:placetype":[
        "aat:300008347"
    ]
},
  "bbox": [],
  "geometry": {"coordinates":[-97.6167,31.5333],"type":"Point"}
}