{
  "id": 2459865,
  "type": "Feature",
  "properties": {
    "tgn:hierarchy":[
        "tgn:2459865",
        "tgn:1000001",
        "tgn:7012149",
        "tgn:7014589",
        "tgn:7007515",
        "tgn:7029392"
    ],
    "tgn:id":2459865,
    "tgn:name":"Little River Lake",
    "tgn:placetype":[
        "aat:300008680"
    ]
},
  "bbox": [],
  "geometry": {"coordinates":[-67.8167,45.15],"type":"Point"}
}