{
  "id": 2737744,
  "type": "Feature",
  "properties": {
    "tgn:hierarchy":[
        "tgn:2737744",
        "tgn:7006450",
        "tgn:1000001",
        "tgn:2124053",
        "tgn:7012149",
        "tgn:7029392"
    ],
    "tgn:id":2737744,
    "tgn:name":"Tyone River",
    "tgn:placetype":[
        "aat:300008707"
    ]
},
  "bbox": [],
  "geometry": {"coordinates":[-146.7667,62.5167],"type":"Point"}
}