{
  "id": 2578980,
  "type": "Feature",
  "properties": {
    "tgn:hierarchy":[
        "tgn:2578980",
        "tgn:1000001",
        "tgn:2000922",
        "tgn:7012149",
        "tgn:7007515",
        "tgn:7029392"
    ],
    "tgn:id":2578980,
    "tgn:name":"Phinney Point",
    "tgn:placetype":[
        "aat:300008850"
    ]
},
  "bbox": [],
  "geometry": {"coordinates":[-68.3833,44.1667],"type":"Point"}
}