{
  "id": 1020677,
  "type": "Feature",
  "properties": {
    "tgn:hierarchy":[
        "tgn:1020677",
        "tgn:7006246",
        "tgn:1000047",
        "tgn:7002455",
        "tgn:1000002",
        "tgn:7029392"
    ],
    "tgn:id":1020677,
    "tgn:name":"Arari",
    "tgn:placetype":[
        "aat:300008347"
    ]
},
  "bbox": [],
  "geometry": {"coordinates":[-44.7333,-3.4667],"type":"Point"}
}