{
  "id": 2571410,
  "type": "Feature",
  "properties": {
    "tgn:hierarchy":[
        "tgn:2571410",
        "tgn:1000001",
        "tgn:7012149",
        "tgn:2001899",
        "tgn:7007825",
        "tgn:7029392"
    ],
    "tgn:id":2571410,
    "tgn:name":"Paula Heights",
    "tgn:placetype":[
        "aat:300008347"
    ]
},
  "bbox": [],
  "geometry": {"coordinates":[-87.2333,36.5167],"type":"Point"}
}