{
  "id": 7156050,
  "type": "Feature",
  "properties": {
    "tgn:hierarchy":[
        "tgn:7156050",
        "tgn:7003669",
        "tgn:1000003",
        "tgn:7000084",
        "tgn:7029392"
    ],
    "tgn:id":7156050,
    "tgn:name":"Kleingesee",
    "tgn:placetype":[
        "aat:300008347"
    ]
},
  "bbox": [],
  "geometry": {"coordinates":[11.35,49.733333],"type":"Point"}
}