{
  "id": 7028377,
  "type": "Feature",
  "properties": {
    "tgn:hierarchy":[
        "tgn:7028377",
        "tgn:7002445",
        "tgn:1000003",
        "tgn:7008160",
        "tgn:7008591",
        "tgn:7029392"
    ],
    "tgn:id":7028377,
    "tgn:name":"Erpingham",
    "tgn:placetype":[
        "aat:300008347",
        "aat:300008372"
    ]
},
  "bbox": [],
  "geometry": {"coordinates":[1.25,52.833333],"type":"Point"}
}