{
  "id": 2009388,
  "type": "Feature",
  "properties": {
    "tgn:hierarchy":[
        "tgn:2009388",
        "tgn:2000107",
        "tgn:1000001",
        "tgn:7016172",
        "tgn:7012149",
        "tgn:7029392"
    ],
    "tgn:id":2009388,
    "tgn:name":"Rodney",
    "tgn:placetype":[
        "aat:300008347",
        "aat:300387210"
    ]
},
  "bbox": [],
  "geometry": {"coordinates":[-92.15,36.2333],"type":"Point"}
}