{
  "id": 7451252,
  "type": "Feature",
  "properties": {
    "tgn:hierarchy":[
        "tgn:7451252",
        "tgn:7019140",
        "tgn:7002444",
        "tgn:1000003",
        "tgn:7008591",
        "tgn:7029392"
    ],
    "tgn:id":7451252,
    "tgn:name:en":"Gannachy",
    "tgn:placetype":[
        "aat:300008347"
    ]
},
  "bbox": [],
  "geometry": {"coordinates":[-2.65,56.816667],"type":"Point"}
}