{
  "id": 2404938,
  "type": "Feature",
  "properties": {
    "tgn:hierarchy":[
        "tgn:2404938",
        "tgn:7002659",
        "tgn:1000001",
        "tgn:7012149",
        "tgn:7021514",
        "tgn:7029392"
    ],
    "tgn:id":2404938,
    "tgn:name":"Hudgins Spring Cave",
    "tgn:placetype":[
        "aat:300008746"
    ]
},
  "bbox": [],
  "geometry": {"coordinates":[-85.6833,34.45],"type":"Point"}
}