{
  "id": 1113653,
  "type": "Feature",
  "properties": {
    "tgn:hierarchy":[
        "tgn:1113653",
        "tgn:7000665",
        "tgn:1000223",
        "tgn:1000006",
        "tgn:7029392"
    ],
    "tgn:id":1113653,
    "tgn:name":"Prony, Baie du",
    "tgn:placetype":[
        "aat:300132316"
    ]
},
  "bbox": [],
  "geometry": {"coordinates":[166.8667,-22.3667],"type":"Point"}
}