{
  "id": 2394393,
  "type": "Feature",
  "properties": {
    "tgn:hierarchy":[
        "tgn:2394393",
        "tgn:1000001",
        "tgn:7012149",
        "tgn:2001724",
        "tgn:7007710",
        "tgn:7029392"
    ],
    "tgn:id":2394393,
    "tgn:name":"Hoge Run",
    "tgn:placetype":[
        "aat:300008699"
    ]
},
  "bbox": [],
  "geometry": {"coordinates":[-80.3333,39.8667],"type":"Point"}
}