{
  "id": 7063013,
  "type": "Feature",
  "properties": {
    "tgn:hierarchy":[
        "tgn:7063013",
        "tgn:1000003",
        "tgn:7003677",
        "tgn:7000084",
        "tgn:7029392"
    ],
    "tgn:id":7063013,
    "tgn:name":"Ambrock",
    "tgn:placetype":[
        "aat:300008347"
    ]
},
  "bbox": [],
  "geometry": {"coordinates":[7.516667,51.316667],"type":"Point"}
}