{
  "id": 7585810,
  "type": "Feature",
  "properties": {
    "tgn:hierarchy":[
        "tgn:7585810",
        "tgn:1000004",
        "tgn:7000198",
        "tgn:7000799",
        "tgn:7029392"
    ],
    "tgn:id":7585810,
    "tgn:name:en":"Kakua",
    "tgn:placetype":[
        "aat:300387200"
    ]
},
  "bbox": [],
  "geometry": {"coordinates":[74.05,34.272222],"type":"Point"}
}