{
  "id": 7110437,
  "type": "Feature",
  "properties": {
    "tgn:hierarchy":[
        "tgn:7110437",
        "tgn:7003669",
        "tgn:1000003",
        "tgn:7000084",
        "tgn:7029392"
    ],
    "tgn:id":7110437,
    "tgn:name":"Punding",
    "tgn:placetype":[
        "aat:300008347"
    ]
},
  "bbox": [],
  "geometry": {"coordinates":[11.55,47.85],"type":"Point"}
}