{
  "id": 2072115,
  "type": "Feature",
  "properties": {
    "tgn:hierarchy":[
        "tgn:2072115",
        "tgn:1000001",
        "tgn:7012149",
        "tgn:1002472",
        "tgn:7007568",
        "tgn:7029392"
    ],
    "tgn:id":2072115,
    "tgn:name":"Salisbury",
    "tgn:placetype":[
        "aat:300008347"
    ]
},
  "bbox": [],
  "geometry": {"coordinates":[-74.8167,43.1333],"type":"Point"}
}