{
  "id": 2105742,
  "type": "Feature",
  "properties": {
    "tgn:hierarchy":[
        "tgn:2105742",
        "tgn:1000001",
        "tgn:7012149",
        "tgn:1002703",
        "tgn:7007826",
        "tgn:7029392"
    ],
    "tgn:id":2105742,
    "tgn:name":"Looneyville",
    "tgn:placetype":[
        "aat:300008347",
        "aat:300387210"
    ]
},
  "bbox": [],
  "geometry": {"coordinates":[-94.8333,31.75],"type":"Point"}
}