{
  "id": 2293947,
  "type": "Feature",
  "properties": {
    "tgn:hierarchy":[
        "tgn:2293947",
        "tgn:1000001",
        "tgn:2002202",
        "tgn:7012149",
        "tgn:7007919",
        "tgn:7029392"
    ],
    "tgn:id":2293947,
    "tgn:name":"Douglas Landing",
    "tgn:placetype":[
        "aat:300008347"
    ]
},
  "bbox": [],
  "geometry": {"coordinates":[-76.3667,36.6333],"type":"Point"}
}