{
  "id": 7584728,
  "type": "Feature",
  "properties": {
    "tgn:hierarchy":[
        "tgn:7584728",
        "tgn:1000004",
        "tgn:7000198",
        "tgn:1001998",
        "tgn:7029392"
    ],
    "tgn:id":7584728,
    "tgn:name:en":"Zem\u0101bawk",
    "tgn:placetype":[
        "aat:300008347"
    ]
},
  "bbox": [],
  "geometry": {"coordinates":[92.745235,23.739156],"type":"Point"}
}