{
  "id": 7432112,
  "type": "Feature",
  "properties": {
    "tgn:hierarchy":[
        "tgn:7432112",
        "tgn:1001835",
        "tgn:1000001",
        "tgn:7005560",
        "tgn:7029392"
    ],
    "tgn:id":7432112,
    "tgn:name":"La Mezcalosa, Mesa",
    "tgn:placetype":[
        "aat:300008811"
    ]
},
  "bbox": [],
  "geometry": {"coordinates":[-113.75,28.466667],"type":"Point"}
}