{
  "id": 2002954,
  "type": "Feature",
  "properties": {
    "tgn:hierarchy":[
        "tgn:2002954",
        "tgn:7002659",
        "tgn:1000001",
        "tgn:7012149",
        "tgn:2000036",
        "tgn:7029392"
    ],
    "tgn:id":2002954,
    "tgn:name":"Cahaba Heights",
    "tgn:placetype":[
        "aat:300008347"
    ]
},
  "bbox": [],
  "geometry": {"coordinates":[-86.7167,33.45],"type":"Point"}
}