{
  "id": 2343022,
  "type": "Feature",
  "properties": {
    "tgn:hierarchy":[
        "tgn:2343022",
        "tgn:1000001",
        "tgn:7012149",
        "tgn:2000996",
        "tgn:7007520",
        "tgn:7029392"
    ],
    "tgn:id":2343022,
    "tgn:name":"G Pool",
    "tgn:placetype":[
        "aat:300006191"
    ]
},
  "bbox": [],
  "geometry": {"coordinates":[-85.9833,46.2667],"type":"Point"}
}