{
  "id": 2372340,
  "type": "Feature",
  "properties": {
    "tgn:hierarchy":[
        "tgn:2372340",
        "tgn:1000001",
        "tgn:7012149",
        "tgn:7007157",
        "tgn:2000185",
        "tgn:7029392"
    ],
    "tgn:id":2372340,
    "tgn:name":"Halfway House Gulch",
    "tgn:placetype":[
        "aat:300008761"
    ]
},
  "bbox": [],
  "geometry": {"coordinates":[-123.4833,39.2167],"type":"Point"}
}