{
  "id": 1049348,
  "type": "Feature",
  "properties": {
    "tgn:hierarchy":[
        "tgn:1049348",
        "tgn:7024116",
        "tgn:1000003",
        "tgn:7006366",
        "tgn:7029392"
    ],
    "tgn:id":1049348,
    "tgn:name":"Pako\u015b\u00f3",
    "tgn:placetype":[
        "aat:300008347"
    ]
},
  "bbox": [],
  "geometry": {"coordinates":[18.0167,52.8167],"type":"Point"}
}