{
  "id": 1084369,
  "type": "Feature",
  "properties": {
    "tgn:hierarchy":[
        "tgn:1084369",
        "tgn:1001065",
        "tgn:1000004",
        "tgn:1000135",
        "tgn:7029392"
    ],
    "tgn:id":1084369,
    "tgn:name":"Loreto",
    "tgn:placetype":[
        "aat:300008347"
    ]
},
  "bbox": [],
  "geometry": {"coordinates":[125.6167,10.35],"type":"Point"}
}