{
  "id": 7494953,
  "type": "Feature",
  "properties": {
    "tgn:hierarchy":[
        "tgn:7494953",
        "tgn:7001010",
        "tgn:1000004",
        "tgn:1000141",
        "tgn:7029392"
    ],
    "tgn:id":7494953,
    "tgn:name":"Malalan Xi",
    "tgn:placetype":[
        "aat:300008699"
    ]
},
  "bbox": [],
  "geometry": {"coordinates":[121.505158,23.511623],"type":"Point"}
}