{
  "id": 2221999,
  "type": "Feature",
  "properties": {
    "tgn:hierarchy":[
        "tgn:2221999",
        "tgn:2001002",
        "tgn:1000001",
        "tgn:7012149",
        "tgn:7007521",
        "tgn:7029392"
    ],
    "tgn:id":2221999,
    "tgn:name":"Carmen Borgerding Wildlife Management Area",
    "tgn:placetype":[
        "aat:300008178"
    ]
},
  "bbox": [],
  "geometry": {"coordinates":[-94.6167,47.7167],"type":"Point"}
}