{
  "id": 7119039,
  "type": "Feature",
  "properties": {
    "tgn:hierarchy":[
        "tgn:7119039",
        "tgn:1000003",
        "tgn:7003688",
        "tgn:7000084",
        "tgn:7029392"
    ],
    "tgn:id":7119039,
    "tgn:name":"Pokier",
    "tgn:placetype":[
        "aat:300000206"
    ]
},
  "bbox": [],
  "geometry": {"coordinates":[9.666667,54.616667],"type":"Point"}
}