<<<<<<< HEAD
{
  "id": 2761773,
  "type": "Feature",
  "properties": {
    "tgn:hierarchy":[
        "tgn:2761773",
        "tgn:1000001",
        "tgn:7012149",
        "tgn:2001980",
        "tgn:7007826",
        "tgn:7029392"
    ],
    "tgn:id":2761773,
    "tgn:name":"West Prong Contrary Creek",
    "tgn:placetype":[
        "aat:300008706"
    ]
},
  "bbox": [],
  "geometry": {"coordinates":[-100.0,30.15],"type":"Point"}
}
=======
{"geometry":{"type":"Point","coordinates":[-100.000000,30.150000]},"type":"Feature","properties":{"hierarchy":["tgn:2761773","tgn:1000001","tgn:7012149","tgn:2001980","tgn:7007826","tgn:7029392"],"placetype":["aat:300008706"],"id":2761773,"name:xx":"West Prong Contrary Creek"}}
>>>>>>> 03f74aca74312dbeaf24d7e61306dd6a786dc3d0
