<<<<<<< HEAD
{
  "id": 2766878,
  "type": "Feature",
  "properties": {
    "tgn:hierarchy":[
        "tgn:2766878",
        "tgn:1000001",
        "tgn:7012149",
        "tgn:2002162",
        "tgn:7007919",
        "tgn:7029392"
    ],
    "tgn:id":2766878,
    "tgn:name":"White Pine Lodge",
    "tgn:placetype":[
        "aat:300008347"
    ]
},
  "bbox": [],
  "geometry": {"coordinates":[-80.55,37.3833],"type":"Point"}
}
=======
{"geometry":{"type":"Point","coordinates":[-80.550000,37.383300]},"type":"Feature","properties":{"hierarchy":["tgn:2766878","tgn:1000001","tgn:7012149","tgn:2002162","tgn:7007919","tgn:7029392"],"placetype":["aat:300008347"],"id":2766878,"name:xx":"White Pine Lodge"}}
>>>>>>> 03f74aca74312dbeaf24d7e61306dd6a786dc3d0
