{
  "id": 2149589,
  "type": "Feature",
  "properties": {
    "tgn:hierarchy":[
        "tgn:2149589",
        "tgn:1000001",
        "tgn:7012149",
        "tgn:2001292",
        "tgn:7007524",
        "tgn:7029392"
    ],
    "tgn:id":2149589,
    "tgn:name":"Barrigan Coulee",
    "tgn:placetype":[
        "aat:300008761"
    ]
},
  "bbox": [],
  "geometry": {"coordinates":[-108.4667,46.3833],"type":"Point"}
}