<<<<<<< HEAD
{
  "id": 7119954,
  "type": "Feature",
  "properties": {
    "tgn:hierarchy":[
        "tgn:7119954",
        "tgn:1000003",
        "tgn:7003688",
        "tgn:7000084",
        "tgn:7029392"
    ],
    "tgn:id":7119954,
    "tgn:name":"Prehnsfelde",
    "tgn:placetype":[
        "aat:300008347"
    ]
},
  "bbox": [],
  "geometry": {"coordinates":[9.9,54.1],"type":"Point"}
}
=======
{"geometry":{"type":"Point","coordinates":[9.900000,54.100000]},"type":"Feature","properties":{"hierarchy":["tgn:7119954","tgn:1000003","tgn:7003688","tgn:7000084","tgn:7029392"],"placetype":["aat:300008347"],"id":7119954,"name:xx":"Prehnsfelde"}}
>>>>>>> 03f74aca74312dbeaf24d7e61306dd6a786dc3d0
