{
  "id": 7434204,
  "type": "Feature",
  "properties": {
    "tgn:hierarchy":[
        "tgn:7434204",
        "tgn:1001835",
        "tgn:1000001",
        "tgn:7005560",
        "tgn:7029392"
    ],
    "tgn:id":7434204,
    "tgn:name":"Puente Trevi\u00f1o",
    "tgn:placetype":[
        "aat:300008347"
    ]
},
  "bbox": [],
  "geometry": {"coordinates":[-114.982778,32.593889],"type":"Point"}
}