{
  "id": 7317069,
  "type": "Feature",
  "properties": {
    "tgn:hierarchy":[
        "tgn:7317069",
        "tgn:1001692",
        "tgn:1000049",
        "tgn:1000002",
        "tgn:7029392"
    ],
    "tgn:id":7317069,
    "tgn:name":"Coicoimall\u00edn, Estero",
    "tgn:placetype":[
        "aat:300008699"
    ]
},
  "bbox": [],
  "geometry": {"coordinates":[-72.916667,-37.766667],"type":"Point"}
}