{
  "id": 2685538,
  "type": "Feature",
  "properties": {
    "tgn:hierarchy":[
        "tgn:2685538",
        "tgn:1000001",
        "tgn:2002321",
        "tgn:7012149",
        "tgn:7007922",
        "tgn:7029392"
    ],
    "tgn:id":2685538,
    "tgn:name":"Spread Eagle Outlet",
    "tgn:placetype":[
        "aat:300008699"
    ]
},
  "bbox": [],
  "geometry": {"coordinates":[-88.1167,45.8833],"type":"Point"}
}