{
  "id": 1033502,
  "type": "Feature",
  "properties": {
    "tgn:hierarchy":[
        "tgn:1033502",
        "tgn:1000003",
        "tgn:7002883",
        "tgn:1000070",
        "tgn:7029392"
    ],
    "tgn:id":1033502,
    "tgn:name":"Jagny-sous-Bois",
    "tgn:placetype":[
        "aat:300008347"
    ]
},
  "bbox": [],
  "geometry": {"coordinates":[2.45,49.0833],"type":"Point"}
}