{
  "id": 2628389,
  "type": "Feature",
  "properties": {
    "tgn:hierarchy":[
        "tgn:2628389",
        "tgn:1000001",
        "tgn:7012149",
        "tgn:2002119",
        "tgn:7007827",
        "tgn:7029392"
    ],
    "tgn:id":2628389,
    "tgn:name":"Rone Bailey Mesa",
    "tgn:placetype":[
        "aat:300008798"
    ]
},
  "bbox": [],
  "geometry": {"coordinates":[-109.45,38.15],"type":"Point"}
}