{
  "id": 2500863,
  "type": "Feature",
  "properties": {
    "tgn:hierarchy":[
        "tgn:2500863",
        "tgn:1000001",
        "tgn:7012149",
        "tgn:7016021",
        "tgn:7007568",
        "tgn:7029392"
    ],
    "tgn:id":2500863,
    "tgn:name":"McEwens Corner",
    "tgn:placetype":[
        "aat:300008347"
    ]
},
  "bbox": [],
  "geometry": {"coordinates":[-74.6833,44.75],"type":"Point"}
}