{
  "id": 7476161,
  "type": "Feature",
  "properties": {
    "tgn:hierarchy":[
        "tgn:7476161",
        "tgn:7487020",
        "tgn:1000004",
        "tgn:1000141",
        "tgn:7029392"
    ],
    "tgn:id":7476161,
    "tgn:name":"Zhonggang Xikou",
    "tgn:placetype":[
        "aat:300387057"
    ]
},
  "bbox": [],
  "geometry": {"coordinates":[120.8248,24.6725],"type":"Point"}
}