{
  "id": 7451911,
  "type": "Feature",
  "properties": {
    "tgn:hierarchy":[
        "tgn:7451911",
        "tgn:7002445",
        "tgn:1000003",
        "tgn:7012031",
        "tgn:7008591",
        "tgn:7029392"
    ],
    "tgn:id":7451911,
    "tgn:name:en":"Great Billing",
    "tgn:placetype":[
        "aat:300008347"
    ]
},
  "bbox": [],
  "geometry": {"coordinates":[-0.816667,52.25],"type":"Point"}
}