{
  "id": 1050058,
  "type": "Feature",
  "properties": {
    "tgn:hierarchy":[
        "tgn:1050058",
        "tgn:1000003",
        "tgn:7002700",
        "tgn:1000091",
        "tgn:7029392"
    ],
    "tgn:id":1050058,
    "tgn:name":"C\u00eempulung Moldovenesc",
    "tgn:placetype":[
        "aat:300008347"
    ]
},
  "bbox": [],
  "geometry": {"coordinates":[25.5667,47.5333],"type":"Point"}
}