{
  "id": 2787275,
  "type": "Feature",
  "properties": {
    "tgn:hierarchy":[
        "tgn:2787275",
        "tgn:1000001",
        "tgn:7012149",
        "tgn:1002590",
        "tgn:7007826",
        "tgn:7029392"
    ],
    "tgn:id":2787275,
    "tgn:name":"Zuesco Creek",
    "tgn:placetype":[
        "aat:300008706"
    ]
},
  "bbox": [],
  "geometry": {"coordinates":[-95.8167,31.5167],"type":"Point"}
}