{
  "id": 2027171,
  "type": "Feature",
  "properties": {
    "tgn:hierarchy":[
        "tgn:2027171",
        "tgn:1000001",
        "tgn:7019013",
        "tgn:7012149",
        "tgn:7007251",
        "tgn:7029392"
    ],
    "tgn:id":2027171,
    "tgn:name":"Churchville",
    "tgn:placetype":[
        "aat:300008347"
    ]
},
  "bbox": [],
  "geometry": {"coordinates":[-87.95,41.9333],"type":"Point"}
}