<<<<<<< HEAD
{
  "id": 7170453,
  "type": "Feature",
  "properties": {
    "tgn:hierarchy":[
        "tgn:7170453",
        "tgn:1000003",
        "tgn:7003678",
        "tgn:7000084",
        "tgn:7029392"
    ],
    "tgn:id":7170453,
    "tgn:name":"Hessisch-Lichtenau, Forst",
    "tgn:placetype":[
        "aat:300008863"
    ]
},
  "bbox": [],
  "geometry": {"coordinates":[9.7,51.2],"type":"Point"}
}
=======
{"geometry":{"type":"Point","coordinates":[9.700000,51.200000]},"type":"Feature","properties":{"hierarchy":["tgn:7170453","tgn:1000003","tgn:7003678","tgn:7000084","tgn:7029392"],"placetype":["aat:300008863"],"id":7170453,"name:xx":"Hessisch-Lichtenau, Forst"}}
>>>>>>> 03f74aca74312dbeaf24d7e61306dd6a786dc3d0
