<<<<<<< HEAD
{
  "id": 7353540,
  "type": "Feature",
  "properties": {
    "tgn:hierarchy":[
        "tgn:7353540",
        "tgn:7005580",
        "tgn:1000001",
        "tgn:7005560",
        "tgn:7029392"
    ],
    "tgn:id":7353540,
    "tgn:name":"Angel D\u00edaz",
    "tgn:placetype":[
        "aat:300008347"
    ]
},
  "bbox": [],
  "geometry": {"coordinates":[-92.4,15.55],"type":"Point"}
}
=======
{"geometry":{"type":"Point","coordinates":[-92.400000,15.550000]},"type":"Feature","properties":{"hierarchy":["tgn:7353540","tgn:7005580","tgn:1000001","tgn:7005560","tgn:7029392"],"placetype":["aat:300008347"],"id":7353540,"name:xx":"Angel D\u00edaz"}}
>>>>>>> 03f74aca74312dbeaf24d7e61306dd6a786dc3d0
