<<<<<<< HEAD
{
  "id": 7473386,
  "type": "Feature",
  "properties": {
    "tgn:hierarchy":[
        "tgn:7473386",
        "tgn:7001004",
        "tgn:1000004",
        "tgn:1000141",
        "tgn:7029392"
    ],
    "tgn:id":7473386,
    "tgn:name":"Tianzibu",
    "tgn:placetype":[
        "aat:300008347"
    ]
},
  "bbox": [],
  "geometry": {"coordinates":[120.408889,22.819167],"type":"Point"}
}
=======
{"geometry":{"type":"Point","coordinates":[120.408889,22.819167]},"type":"Feature","properties":{"hierarchy":["tgn:7473386","tgn:7001004","tgn:1000004","tgn:1000141","tgn:7029392"],"placetype":["aat:300008347"],"id":7473386,"name:xx":"Tianzibu"}}
>>>>>>> 03f74aca74312dbeaf24d7e61306dd6a786dc3d0
