{
  "id": 2499035,
  "type": "Feature",
  "properties": {
    "tgn:hierarchy":[
        "tgn:2499035",
        "tgn:1000001",
        "tgn:1002410",
        "tgn:7012149",
        "tgn:7007565",
        "tgn:7029392"
    ],
    "tgn:id":2499035,
    "tgn:name":"McCarthys Lakes",
    "tgn:placetype":[
        "aat:300006191"
    ]
},
  "bbox": [],
  "geometry": {"coordinates":[-74.9167,39.5667],"type":"Point"}
}