{
  "id": 2341225,
  "type": "Feature",
  "properties": {
    "tgn:hierarchy":[
        "tgn:2341225",
        "tgn:1000001",
        "tgn:2001429",
        "tgn:7012149",
        "tgn:7007566",
        "tgn:7029392"
    ],
    "tgn:id":2341225,
    "tgn:name":"Frisco Spring",
    "tgn:placetype":[
        "aat:300008697"
    ]
},
  "bbox": [],
  "geometry": {"coordinates":[-108.7833,33.6333],"type":"Point"}
}