{
  "id": 2323566,
  "type": "Feature",
  "properties": {
    "tgn:hierarchy":[
        "tgn:2323566",
        "tgn:1000001",
        "tgn:7012149",
        "tgn:2002121",
        "tgn:7007827",
        "tgn:7029392"
    ],
    "tgn:id":2323566,
    "tgn:name":"Farrell Pond",
    "tgn:placetype":[
        "aat:300008680"
    ]
},
  "bbox": [],
  "geometry": {"coordinates":[-111.45,38.5333],"type":"Point"}
}