{
  "id": 2190808,
  "type": "Feature",
  "properties": {
    "tgn:hierarchy":[
        "tgn:2190808",
        "tgn:1002140",
        "tgn:1000001",
        "tgn:7012149",
        "tgn:7007520",
        "tgn:7029392"
    ],
    "tgn:id":2190808,
    "tgn:name":"Boyd",
    "tgn:placetype":[
        "aat:300008347"
    ]
},
  "bbox": [],
  "geometry": {"coordinates":[-86.0833,42.7167],"type":"Point"}
}