{
  "id": 7098951,
  "type": "Feature",
  "properties": {
    "tgn:hierarchy":[
        "tgn:7098951",
        "tgn:7003669",
        "tgn:1000003",
        "tgn:7000084",
        "tgn:7029392"
    ],
    "tgn:id":7098951,
    "tgn:name":"Sigl",
    "tgn:placetype":[
        "aat:300008347"
    ]
},
  "bbox": [],
  "geometry": {"coordinates":[11.75,49.616667],"type":"Point"}
}