<<<<<<< HEAD
{
  "id": 2401439,
  "type": "Feature",
  "properties": {
    "tgn:hierarchy":[
        "tgn:2401439",
        "tgn:1000001",
        "tgn:7012149",
        "tgn:7007157",
        "tgn:1002858",
        "tgn:7029392"
    ],
    "tgn:id":2401439,
    "tgn:name":"Horseshoe Bend",
    "tgn:placetype":[
        "aat:300266640"
    ]
},
  "bbox": [],
  "geometry": {"coordinates":[-116.9667,32.6667],"type":"Point"}
}
=======
{"geometry":{"type":"Point","coordinates":[-116.966700,32.666700]},"type":"Feature","properties":{"hierarchy":["tgn:2401439","tgn:1000001","tgn:7012149","tgn:7007157","tgn:1002858","tgn:7029392"],"placetype":["aat:300266640"],"id":2401439,"name:xx":"Horseshoe Bend"}}
>>>>>>> 03f74aca74312dbeaf24d7e61306dd6a786dc3d0
