<<<<<<< HEAD
{
  "id": 2258984,
  "type": "Feature",
  "properties": {
    "tgn:hierarchy":[
        "tgn:2258984",
        "tgn:1000001",
        "tgn:1002168",
        "tgn:7012149",
        "tgn:7007826",
        "tgn:7029392"
    ],
    "tgn:id":2258984,
    "tgn:name":"Cottonwood Creek",
    "tgn:placetype":[
        "aat:300008706"
    ]
},
  "bbox": [],
  "geometry": {"coordinates":[-97.5167,30.1333],"type":"Point"}
}
=======
{"geometry":{"type":"Point","coordinates":[-97.516700,30.133300]},"type":"Feature","properties":{"hierarchy":["tgn:2258984","tgn:1000001","tgn:1002168","tgn:7012149","tgn:7007826","tgn:7029392"],"placetype":["aat:300008706"],"id":2258984,"name:xx":"Cottonwood Creek"}}
>>>>>>> 03f74aca74312dbeaf24d7e61306dd6a786dc3d0
