{
  "id": 7032703,
  "type": "Feature",
  "properties": {
    "tgn:hierarchy":[
        "tgn:7032703",
        "tgn:7005744",
        "tgn:1000003",
        "tgn:7594219",
        "tgn:7005729",
        "tgn:7029392"
    ],
    "tgn:id":7032703,
    "tgn:name":"\u0126al Saflieni",
    "tgn:placetype":[
        "aat:300387331"
    ]
},
  "bbox": [],
  "geometry": {"coordinates":[14.508,35.869],"type":"Point"}
}