{
  "id": 2700746,
  "type": "Feature",
  "properties": {
    "tgn:hierarchy":[
        "tgn:2700746",
        "tgn:1000001",
        "tgn:7006451",
        "tgn:2000092",
        "tgn:7012149",
        "tgn:7029392"
    ],
    "tgn:id":2700746,
    "tgn:name":"Sues Tank",
    "tgn:placetype":[
        "aat:300006191"
    ]
},
  "bbox": [],
  "geometry": {"coordinates":[-111.5167,34.7333],"type":"Point"}
}