{
  "id": 2268953,
  "type": "Feature",
  "properties": {
    "tgn:hierarchy":[
        "tgn:2268953",
        "tgn:1000001",
        "tgn:7012149",
        "tgn:2000473",
        "tgn:7007250",
        "tgn:7029392"
    ],
    "tgn:id":2268953,
    "tgn:name":"Crosscut Canal",
    "tgn:placetype":[
        "aat:300006075"
    ]
},
  "bbox": [],
  "geometry": {"coordinates":[-111.5833,43.9833],"type":"Point"}
}