{
  "id": 7186339,
  "type": "Feature",
  "properties": {
    "tgn:hierarchy":[
        "tgn:7186339",
        "tgn:7003669",
        "tgn:1000003",
        "tgn:7000084",
        "tgn:7029392"
    ],
    "tgn:id":7186339,
    "tgn:name":"Glasendicken Berg",
    "tgn:placetype":[
        "aat:300008777"
    ]
},
  "bbox": [],
  "geometry": {"coordinates":[11.416667,50.433333],"type":"Point"}
}