<<<<<<< HEAD
{
  "id": 2258945,
  "type": "Feature",
  "properties": {
    "tgn:hierarchy":[
        "tgn:2258945",
        "tgn:1000001",
        "tgn:2001649",
        "tgn:7012149",
        "tgn:7007707",
        "tgn:7029392"
    ],
    "tgn:id":2258945,
    "tgn:name":"Cottonwood Creek",
    "tgn:placetype":[
        "aat:300008706"
    ]
},
  "bbox": [],
  "geometry": {"coordinates":[-97.6833,36.8667],"type":"Point"}
}
=======
{"geometry":{"type":"Point","coordinates":[-97.683300,36.866700]},"type":"Feature","properties":{"hierarchy":["tgn:2258945","tgn:1000001","tgn:2001649","tgn:7012149","tgn:7007707","tgn:7029392"],"placetype":["aat:300008706"],"id":2258945,"name:xx":"Cottonwood Creek"}}
>>>>>>> 03f74aca74312dbeaf24d7e61306dd6a786dc3d0
