{
  "id": 7276319,
  "type": "Feature",
  "properties": {
    "tgn:hierarchy":[
        "tgn:7276319",
        "tgn:1001695",
        "tgn:1000049",
        "tgn:1000002",
        "tgn:7029392"
    ],
    "tgn:id":7276319,
    "tgn:name":"Topocalma, Caleta",
    "tgn:placetype":[
        "aat:300132317"
    ]
},
  "bbox": [],
  "geometry": {"coordinates":[-71.983333,-34.116667],"type":"Point"}
}