{
  "id": 2053290,
  "type": "Feature",
  "properties": {
    "tgn:hierarchy":[
        "tgn:2053290",
        "tgn:1000001",
        "tgn:7012149",
        "tgn:2000996",
        "tgn:7007520",
        "tgn:7029392"
    ],
    "tgn:id":2053290,
    "tgn:name":"Seney",
    "tgn:placetype":[
        "aat:300008347"
    ]
},
  "bbox": [],
  "geometry": {"coordinates":[-85.9333,46.3333],"type":"Point"}
}