{
  "id": 2470531,
  "type": "Feature",
  "properties": {
    "tgn:hierarchy":[
        "tgn:2470531",
        "tgn:1000001",
        "tgn:7012149",
        "tgn:7007157",
        "tgn:7014516",
        "tgn:7029392"
    ],
    "tgn:id":2470531,
    "tgn:name":"Los Guilicos Warm Springs",
    "tgn:placetype":[
        "aat:300008697"
    ]
},
  "bbox": [],
  "geometry": {"coordinates":[-122.55,38.3833],"type":"Point"}
}