<<<<<<< HEAD
{
  "id": 7488941,
  "type": "Feature",
  "properties": {
    "tgn:hierarchy":[
        "tgn:7488941",
        "tgn:1000004",
        "tgn:7004300",
        "tgn:1000141",
        "tgn:7029392"
    ],
    "tgn:id":7488941,
    "tgn:name":"Longtou Jiao",
    "tgn:placetype":[
        "aat:300008791"
    ]
},
  "bbox": [],
  "geometry": {"coordinates":[119.618001,23.673861],"type":"Point"}
}
=======
{"geometry":{"type":"Point","coordinates":[119.618001,23.673861]},"type":"Feature","properties":{"hierarchy":["tgn:7488941","tgn:1000004","tgn:7004300","tgn:1000141","tgn:7029392"],"placetype":["aat:300008791"],"id":7488941,"name:xx":"Longtou Jiao"}}
>>>>>>> 03f74aca74312dbeaf24d7e61306dd6a786dc3d0
