{
  "id": 1033750,
  "type": "Feature",
  "properties": {
    "tgn:hierarchy":[
        "tgn:1033750",
        "tgn:1000003",
        "tgn:7002890",
        "tgn:1000070",
        "tgn:7029392"
    ],
    "tgn:id":1033750,
    "tgn:name":"Lagny-le-Sec",
    "tgn:placetype":[
        "aat:300008347"
    ]
},
  "bbox": [],
  "geometry": {"coordinates":[2.75,49.0833],"type":"Point"}
}