{
  "id": 2001491,
  "type": "Feature",
  "properties": {
    "tgn:hierarchy":[
        "tgn:2001491",
        "tgn:1000001",
        "tgn:7012149",
        "tgn:7007709",
        "tgn:7029392"
    ],
    "tgn:id":2001491,
    "tgn:name":"Duplin",
    "tgn:placetype":[
        "aat:300387145",
        "aat:300000771"
    ]
},
  "bbox": [],
  "geometry": {"coordinates":[-77.95,34.95],"type":"Point"}
}