{
  "id": 2697866,
  "type": "Feature",
  "properties": {
    "tgn:hierarchy":[
        "tgn:2697866",
        "tgn:1000001",
        "tgn:7012149",
        "tgn:7007157",
        "tgn:7014005",
        "tgn:7029392"
    ],
    "tgn:id":2697866,
    "tgn:name":"Stormy Stack",
    "tgn:placetype":[
        "aat:300008791"
    ]
},
  "bbox": [],
  "geometry": {"coordinates":[-122.7833,37.9333],"type":"Point"}
}