{
  "id": 7317304,
  "type": "Feature",
  "properties": {
    "tgn:hierarchy":[
        "tgn:7317304",
        "tgn:1001637",
        "tgn:1000049",
        "tgn:1000002",
        "tgn:7029392"
    ],
    "tgn:id":7317304,
    "tgn:name":"Cochinos, Punta",
    "tgn:placetype":[
        "aat:300386846"
    ]
},
  "bbox": [],
  "geometry": {"coordinates":[-73.533333,-37.083333],"type":"Point"}
}