{
  "id": 7402233,
  "type": "Feature",
  "properties": {
    "tgn:hierarchy":[
        "tgn:7402233",
        "tgn:1000001",
        "tgn:7005599",
        "tgn:7005560",
        "tgn:7029392"
    ],
    "tgn:id":7402233,
    "tgn:name":"La Mancha, Lago",
    "tgn:placetype":[
        "aat:300008680"
    ]
},
  "bbox": [],
  "geometry": {"coordinates":[-96.391667,19.583333],"type":"Point"}
}