{
  "id": 2263462,
  "type": "Feature",
  "properties": {
    "tgn:hierarchy":[
        "tgn:2263462",
        "tgn:1000001",
        "tgn:7013942",
        "tgn:7012149",
        "tgn:7007517",
        "tgn:7029392"
    ],
    "tgn:id":2263462,
    "tgn:name":"Cox Pond",
    "tgn:placetype":[
        "aat:300006191"
    ]
},
  "bbox": [],
  "geometry": {"coordinates":[-72.8667,42.5667],"type":"Point"}
}