{
  "id": 2487054,
  "type": "Feature",
  "properties": {
    "tgn:hierarchy":[
        "tgn:2487054",
        "tgn:1000001",
        "tgn:7006451",
        "tgn:2000092",
        "tgn:7012149",
        "tgn:7029392"
    ],
    "tgn:id":2487054,
    "tgn:name":"Lee Spring",
    "tgn:placetype":[
        "aat:300008697"
    ]
},
  "bbox": [],
  "geometry": {"coordinates":[-111.55,34.8333],"type":"Point"}
}