{
  "id": 2255029,
  "type": "Feature",
  "properties": {
    "tgn:hierarchy":[
        "tgn:2255029",
        "tgn:1000001",
        "tgn:7012149",
        "tgn:2000841",
        "tgn:7007255",
        "tgn:7029392"
    ],
    "tgn:id":2255029,
    "tgn:name":"Cooper Creek",
    "tgn:placetype":[
        "aat:300008706"
    ]
},
  "bbox": [],
  "geometry": {"coordinates":[-85.0167,37.0667],"type":"Point"}
}