{
  "id": 1056379,
  "type": "Feature",
  "properties": {
    "tgn:hierarchy":[
        "tgn:1056379",
        "tgn:1000004",
        "tgn:6003034",
        "tgn:7018214",
        "tgn:7002435",
        "tgn:7029392"
    ],
    "tgn:id":1056379,
    "tgn:name":"Leninsk-Kuznetskiy",
    "tgn:placetype":[
        "aat:300008347",
        "aat:300387308",
        "aat:300387305",
        "aat:300008375"
    ]
},
  "bbox": [],
  "geometry": {"coordinates":[86.2167,54.7333],"type":"Point"}
}