{
  "id": 2101867,
  "type": "Feature",
  "properties": {
    "tgn:hierarchy":[
        "tgn:2101867",
        "tgn:1000001",
        "tgn:7012149",
        "tgn:2001925",
        "tgn:7007825",
        "tgn:7029392"
    ],
    "tgn:id":2101867,
    "tgn:name":"Trousdale",
    "tgn:placetype":[
        "aat:300008347",
        "aat:300387210"
    ]
},
  "bbox": [],
  "geometry": {"coordinates":[-85.9333,35.6667],"type":"Point"}
}