<<<<<<< HEAD
{
  "id": 7478481,
  "type": "Feature",
  "properties": {
    "tgn:hierarchy":[
        "tgn:7478481",
        "tgn:1000004",
        "tgn:7489179",
        "tgn:1000141",
        "tgn:7029392"
    ],
    "tgn:id":7478481,
    "tgn:name":"Gongzheng Guoxiao",
    "tgn:placetype":[
        "aat:300006495"
    ]
},
  "bbox": [],
  "geometry": {"coordinates":[121.7663,24.6786],"type":"Point"}
}
=======
{"geometry":{"type":"Point","coordinates":[121.766300,24.678600]},"type":"Feature","properties":{"hierarchy":["tgn:7478481","tgn:1000004","tgn:7489179","tgn:1000141","tgn:7029392"],"placetype":["aat:300006495"],"id":7478481,"name:xx":"Gongzheng Guoxiao"}}
>>>>>>> 03f74aca74312dbeaf24d7e61306dd6a786dc3d0
