{
  "id": 2419166,
  "type": "Feature",
  "properties": {
    "tgn:hierarchy":[
        "tgn:2419166",
        "tgn:1000001",
        "tgn:7012149",
        "tgn:7007157",
        "tgn:2000187",
        "tgn:7029392"
    ],
    "tgn:id":2419166,
    "tgn:name":"Jamison Mine",
    "tgn:placetype":[
        "aat:300000390"
    ]
},
  "bbox": [],
  "geometry": {"coordinates":[-120.6833,39.7333],"type":"Point"}
}