{
  "id": 7476493,
  "type": "Feature",
  "properties": {
    "tgn:hierarchy":[
        "tgn:7476493",
        "tgn:1000004",
        "tgn:7489179",
        "tgn:1000141",
        "tgn:7029392"
    ],
    "tgn:id":7476493,
    "tgn:name":"Meihua Hu",
    "tgn:placetype":[
        "aat:300008680"
    ]
},
  "bbox": [],
  "geometry": {"coordinates":[121.733146,24.643058],"type":"Point"}
}