{
  "id": 2124981,
  "type": "Feature",
  "properties": {
    "tgn:hierarchy":[
        "tgn:2124981",
        "tgn:1000001",
        "tgn:7006451",
        "tgn:7012149",
        "tgn:2000100",
        "tgn:7029392"
    ],
    "tgn:id":2124981,
    "tgn:name":"Abra Plain, La",
    "tgn:placetype":[
        "aat:300008805"
    ]
},
  "bbox": [],
  "geometry": {"coordinates":[-112.9333,31.95],"type":"Point"}
}