{
  "id": 7293645,
  "type": "Feature",
  "properties": {
    "tgn:hierarchy":[
        "tgn:7293645",
        "tgn:7002842",
        "tgn:7001158",
        "tgn:1000003",
        "tgn:1000095",
        "tgn:7029392"
    ],
    "tgn:id":7293645,
    "tgn:name":"Villaciervos",
    "tgn:placetype":[
        "aat:300008347"
    ]
},
  "bbox": [],
  "geometry": {"coordinates":[-2.633333,41.766667],"type":"Point"}
}