{
  "id": 7397843,
  "type": "Feature",
  "properties": {
    "tgn:hierarchy":[
        "tgn:7397843",
        "tgn:1000001",
        "tgn:7005588",
        "tgn:7005560",
        "tgn:7029392"
    ],
    "tgn:id":7397843,
    "tgn:name":"Raices, Volc\u00e1n",
    "tgn:placetype":[
        "aat:300132325"
    ]
},
  "bbox": [],
  "geometry": {"coordinates":[-99.2575,19.103333],"type":"Point"}
}