{
  "id": 2278835,
  "type": "Feature",
  "properties": {
    "tgn:hierarchy":[
        "tgn:2278835",
        "tgn:1000001",
        "tgn:7012149",
        "tgn:2002382",
        "tgn:7007923",
        "tgn:7029392"
    ],
    "tgn:id":2278835,
    "tgn:name":"Dead Indian Dome",
    "tgn:placetype":[
        "aat:300008798"
    ]
},
  "bbox": [],
  "geometry": {"coordinates":[-110.25,42.6667],"type":"Point"}
}