{
  "id": 2383512,
  "type": "Feature",
  "properties": {
    "tgn:hierarchy":[
        "tgn:2383512",
        "tgn:1000001",
        "tgn:7012149",
        "tgn:2000348",
        "tgn:7007248",
        "tgn:7029392"
    ],
    "tgn:id":2383512,
    "tgn:name":"Heath Mountain",
    "tgn:placetype":[
        "aat:300008798"
    ]
},
  "bbox": [],
  "geometry": {"coordinates":[-85.3833,34.25],"type":"Point"}
}