{
  "id": 7119226,
  "type": "Feature",
  "properties": {
    "tgn:hierarchy":[
        "tgn:7119226",
        "tgn:7000096",
        "tgn:1000003",
        "tgn:7000084",
        "tgn:7029392"
    ],
    "tgn:id":7119226,
    "tgn:name":"Priester-Berge",
    "tgn:placetype":[
        "aat:300008777"
    ]
},
  "bbox": [],
  "geometry": {"coordinates":[13.533333,52.933333],"type":"Point"}
}