{
  "id": 2212335,
  "type": "Feature",
  "properties": {
    "tgn:hierarchy":[
        "tgn:2212335",
        "tgn:1000001",
        "tgn:7012149",
        "tgn:2000181",
        "tgn:7007157",
        "tgn:7029392"
    ],
    "tgn:id":2212335,
    "tgn:name":"Buzzards Peak",
    "tgn:placetype":[
        "aat:300008798"
    ]
},
  "bbox": [],
  "geometry": {"coordinates":[-124.2167,40.5167],"type":"Point"}
}