{
  "id": 2350138,
  "type": "Feature",
  "properties": {
    "tgn:hierarchy":[
        "tgn:2350138",
        "tgn:1000001",
        "tgn:7012149",
        "tgn:2001718",
        "tgn:7007708",
        "tgn:7029392"
    ],
    "tgn:id":2350138,
    "tgn:name":"Gin Basin",
    "tgn:placetype":[
        "aat:300386845"
    ]
},
  "bbox": [],
  "geometry": {"coordinates":[-117.35,43.2667],"type":"Point"}
}