{
  "id": 7207601,
  "type": "Feature",
  "properties": {
    "tgn:hierarchy":[
        "tgn:7207601",
        "tgn:1000003",
        "tgn:7003689",
        "tgn:7000084",
        "tgn:7029392"
    ],
    "tgn:id":7207601,
    "tgn:name":"Buchfart, Forst",
    "tgn:placetype":[
        "aat:300008863"
    ]
},
  "bbox": [],
  "geometry": {"coordinates":[11.25,50.916667],"type":"Point"}
}