{
  "id": 2109127,
  "type": "Feature",
  "properties": {
    "tgn:hierarchy":[
        "tgn:2109127",
        "tgn:1000001",
        "tgn:7012149",
        "tgn:2002120",
        "tgn:7007827",
        "tgn:7029392"
    ],
    "tgn:id":2109127,
    "tgn:name":"Oak Creek",
    "tgn:placetype":[
        "aat:300008347",
        "aat:300387210"
    ]
},
  "bbox": [],
  "geometry": {"coordinates":[-111.4333,39.6667],"type":"Point"}
}