{
  "id": 7529936,
  "type": "Feature",
  "properties": {
    "tgn:hierarchy":[
        "tgn:7529936",
        "tgn:7001242",
        "tgn:7016833",
        "tgn:7001335",
        "tgn:7029392"
    ],
    "tgn:id":7529936,
    "tgn:name:en":"Ab\u016b Juway', W\u0101d\u012b",
    "tgn:placetype":[
        "aat:300379998"
    ]
},
  "bbox": [],
  "geometry": {"coordinates":[34.664167,30.026389],"type":"Point"}
}