{
  "id": 4007307,
  "type": "Feature",
  "properties": {
    "tgn:hierarchy":[
        "tgn:4007307",
        "tgn:7003008",
        "tgn:1000003",
        "tgn:7002997",
        "tgn:1000080",
        "tgn:7029392"
    ],
    "tgn:id":4007307,
    "tgn:name":"Molina",
    "tgn:placetype":[
        "aat:300008347"
    ]
},
  "bbox": [],
  "geometry": {"coordinates":[11.466667,45.666667],"type":"Point"}
}