{
  "id": 7588296,
  "type": "Feature",
  "properties": {
    "tgn:hierarchy":[
        "tgn:7588296",
        "tgn:1000004",
        "tgn:7000198",
        "tgn:7016883",
        "tgn:7029392"
    ],
    "tgn:id":7588296,
    "tgn:name:en":"Naranjanpur Fattuwal",
    "tgn:placetype":[
        "aat:300008347"
    ]
},
  "bbox": [],
  "geometry": {"coordinates":[75.207612,31.545547],"type":"Point"}
}