{
  "id": 2152539,
  "type": "Feature",
  "properties": {
    "tgn:hierarchy":[
        "tgn:2152539",
        "tgn:7030516",
        "tgn:7006450",
        "tgn:1000001",
        "tgn:7012149",
        "tgn:7029392"
    ],
    "tgn:id":2152539,
    "tgn:name":"Bay of Islands",
    "tgn:placetype":[
        "aat:300386853"
    ]
},
  "bbox": [],
  "geometry": {"coordinates":[-176.8333,51.8167],"type":"Point"}
}