{
  "id": 2076423,
  "type": "Feature",
  "properties": {
    "tgn:hierarchy":[
        "tgn:2076423",
        "tgn:1000001",
        "tgn:7012149",
        "tgn:2001553",
        "tgn:7007709",
        "tgn:7029392"
    ],
    "tgn:id":2076423,
    "tgn:name":"Ronda",
    "tgn:placetype":[
        "aat:300008347"
    ]
},
  "bbox": [],
  "geometry": {"coordinates":[-80.9333,36.2167],"type":"Point"}
}