{
  "id": 1133118,
  "type": "Feature",
  "properties": {
    "tgn:hierarchy":[
        "tgn:1133118",
        "tgn:1000001",
        "tgn:7012149",
        "tgn:7007523",
        "tgn:7029392"
    ],
    "tgn:id":1133118,
    "tgn:name":"East Yellow Creek",
    "tgn:placetype":[
        "aat:300008706"
    ]
},
  "bbox": [],
  "geometry": {"coordinates":[-92.9333,40.2333],"type":"Point"}
}