{
  "id": 2585064,
  "type": "Feature",
  "properties": {
    "tgn:hierarchy":[
        "tgn:2585064",
        "tgn:1000001",
        "tgn:7012149",
        "tgn:2000476",
        "tgn:7007250",
        "tgn:7029392"
    ],
    "tgn:id":2585064,
    "tgn:name":"Pinnacle Ridge",
    "tgn:placetype":[
        "aat:300266640"
    ]
},
  "bbox": [],
  "geometry": {"coordinates":[-116.1333,45.7667],"type":"Point"}
}