{
  "id": 2694968,
  "type": "Feature",
  "properties": {
    "tgn:hierarchy":[
        "tgn:2694968",
        "tgn:1000001",
        "tgn:7012149",
        "tgn:2002088",
        "tgn:7007826",
        "tgn:7029392"
    ],
    "tgn:id":2694968,
    "tgn:name":"Still Canyon",
    "tgn:placetype":[
        "aat:300008761"
    ]
},
  "bbox": [],
  "geometry": {"coordinates":[-101.4167,29.9333],"type":"Point"}
}