{
  "id": 1031579,
  "type": "Feature",
  "properties": {
    "tgn:hierarchy":[
        "tgn:1031579",
        "tgn:1001385",
        "tgn:1000003",
        "tgn:1000069",
        "tgn:7029392"
    ],
    "tgn:id":1031579,
    "tgn:name":"Tervola",
    "tgn:placetype":[
        "aat:300008347"
    ]
},
  "bbox": [],
  "geometry": {"coordinates":[24.8333,66.0833],"type":"Point"}
}