{
  "id": 1088935,
  "type": "Feature",
  "properties": {
    "tgn:hierarchy":[
        "tgn:1088935",
        "tgn:7001242",
        "tgn:7016755",
        "tgn:1000159",
        "tgn:7029392"
    ],
    "tgn:id":1088935,
    "tgn:name":"Dongobe",
    "tgn:placetype":[
        "aat:300008347"
    ]
},
  "bbox": [],
  "geometry": {"coordinates":[23.2167,4.5833],"type":"Point"}
}