{
  "id": 2060613,
  "type": "Feature",
  "properties": {
    "tgn:hierarchy":[
        "tgn:2060613",
        "tgn:1000001",
        "tgn:2001182",
        "tgn:7012149",
        "tgn:7007523",
        "tgn:7029392"
    ],
    "tgn:id":2060613,
    "tgn:name":"Strasburg",
    "tgn:placetype":[
        "aat:300008347"
    ]
},
  "bbox": [],
  "geometry": {"coordinates":[-94.15,38.75],"type":"Point"}
}