{
  "id": 7454675,
  "type": "Feature",
  "properties": {
    "tgn:hierarchy":[
        "tgn:7454675",
        "tgn:7002444",
        "tgn:1000003",
        "tgn:7009907",
        "tgn:7008591",
        "tgn:7029392"
    ],
    "tgn:id":7454675,
    "tgn:name:en":"Chapel Taing",
    "tgn:placetype":[
        "aat:300008808"
    ]
},
  "bbox": [],
  "geometry": {"coordinates":[-2.816667,58.933333],"type":"Point"}
}