{
  "id": 7584045,
  "type": "Feature",
  "properties": {
    "tgn:hierarchy":[
        "tgn:7584045",
        "tgn:1000004",
        "tgn:7000198",
        "tgn:1001894",
        "tgn:7029392"
    ],
    "tgn:id":7584045,
    "tgn:name:en":"L\u0101khron",
    "tgn:placetype":[
        "aat:300008347"
    ]
},
  "bbox": [],
  "geometry": {"coordinates":[78.783713,25.072026],"type":"Point"}
}