<<<<<<< HEAD
{
  "id": 7056106,
  "type": "Feature",
  "properties": {
    "tgn:hierarchy":[
        "tgn:7056106",
        "tgn:7003139",
        "tgn:1000003",
        "tgn:7003080",
        "tgn:1000080",
        "tgn:7029392"
    ],
    "tgn:id":7056106,
    "tgn:name":"Leona, Fosso",
    "tgn:placetype":[
        "aat:300008699"
    ]
},
  "bbox": [],
  "geometry": {"coordinates":[11.783333,42.283333],"type":"Point"}
}
=======
{"geometry":{"type":"Point","coordinates":[11.783333,42.283333]},"type":"Feature","properties":{"hierarchy":["tgn:7056106","tgn:7003139","tgn:1000003","tgn:7003080","tgn:1000080","tgn:7029392"],"placetype":["aat:300008699"],"id":7056106,"name:xx":"Leona, Fosso"}}
>>>>>>> 03f74aca74312dbeaf24d7e61306dd6a786dc3d0
