{
  "id": 7034774,
  "type": "Feature",
  "properties": {
    "tgn:hierarchy":[
        "tgn:7034774",
        "tgn:1000003",
        "tgn:7003142",
        "tgn:7003236",
        "tgn:1000080",
        "tgn:7029392"
    ],
    "tgn:id":7034774,
    "tgn:name":"Nostra Signora di Montallegro",
    "tgn:placetype":[
        "aat:300007466"
    ]
},
  "bbox": [],
  "geometry": {"coordinates":[9.256667,44.368333],"type":"Point"}
}