<<<<<<< HEAD
{
  "id": 2409136,
  "type": "Feature",
  "properties": {
    "tgn:hierarchy":[
        "tgn:2409136",
        "tgn:1000001",
        "tgn:7012149",
        "tgn:7020792",
        "tgn:7007524",
        "tgn:7029392"
    ],
    "tgn:id":2409136,
    "tgn:name":"Ice House Gulch",
    "tgn:placetype":[
        "aat:300008761"
    ]
},
  "bbox": [],
  "geometry": {"coordinates":[-113.0333,46.1],"type":"Point"}
}
=======
{"geometry":{"type":"Point","coordinates":[-113.033300,46.100000]},"type":"Feature","properties":{"hierarchy":["tgn:2409136","tgn:1000001","tgn:7012149","tgn:7020792","tgn:7007524","tgn:7029392"],"placetype":["aat:300008761"],"id":2409136,"name:xx":"Ice House Gulch"}}
>>>>>>> 03f74aca74312dbeaf24d7e61306dd6a786dc3d0
