{
  "id": 7039045,
  "type": "Feature",
  "properties": {
    "tgn:hierarchy":[
        "tgn:7039045",
        "tgn:1001730",
        "tgn:1000003",
        "tgn:7003121",
        "tgn:1000080",
        "tgn:7029392"
    ],
    "tgn:id":7039045,
    "tgn:name":"Soddi",
    "tgn:placetype":[
        "aat:300008347"
    ]
},
  "bbox": [],
  "geometry": {"coordinates":[8.866667,40.116667],"type":"Point"}
}