<<<<<<< HEAD
{
  "id": 7486254,
  "type": "Feature",
  "properties": {
    "tgn:hierarchy":[
        "tgn:7486254",
        "tgn:1000004",
        "tgn:7491221",
        "tgn:1000141",
        "tgn:7029392"
    ],
    "tgn:id":7486254,
    "tgn:name":"Hongtou",
    "tgn:placetype":[
        "aat:300008347"
    ]
},
  "bbox": [],
  "geometry": {"coordinates":[121.554444,22.025556],"type":"Point"}
}
=======
{"geometry":{"type":"Point","coordinates":[121.554444,22.025556]},"type":"Feature","properties":{"hierarchy":["tgn:7486254","tgn:1000004","tgn:7491221","tgn:1000141","tgn:7029392"],"placetype":["aat:300008347"],"id":7486254,"name:xx":"Hongtou"}}
>>>>>>> 03f74aca74312dbeaf24d7e61306dd6a786dc3d0
