{
  "id": 2348691,
  "type": "Feature",
  "properties": {
    "tgn:hierarchy":[
        "tgn:2348691",
        "tgn:1000001",
        "tgn:7016172",
        "tgn:7012149",
        "tgn:7029392"
    ],
    "tgn:id":2348691,
    "tgn:name":"Gibson Creek",
    "tgn:placetype":[
        "aat:300008706"
    ]
},
  "bbox": [],
  "geometry": {"coordinates":[-93.8167,33.7667],"type":"Point"}
}