{
  "id": 2200121,
  "type": "Feature",
  "properties": {
    "tgn:hierarchy":[
        "tgn:2200121",
        "tgn:1000001",
        "tgn:7012149",
        "tgn:2001202",
        "tgn:7007523",
        "tgn:7029392"
    ],
    "tgn:id":2200121,
    "tgn:name":"Brushy Creek",
    "tgn:placetype":[
        "aat:300008706"
    ]
},
  "bbox": [],
  "geometry": {"coordinates":[-94.0333,38.5167],"type":"Point"}
}