{
  "id": 2079121,
  "type": "Feature",
  "properties": {
    "tgn:hierarchy":[
        "tgn:2079121",
        "tgn:1000001",
        "tgn:7012149",
        "tgn:1002955",
        "tgn:7007706",
        "tgn:7029392"
    ],
    "tgn:id":2079121,
    "tgn:name":"Cortland",
    "tgn:placetype":[
        "aat:300008347"
    ]
},
  "bbox": [],
  "geometry": {"coordinates":[-80.7167,41.3167],"type":"Point"}
}