{
  "id": 2781913,
  "type": "Feature",
  "properties": {
    "tgn:hierarchy":[
        "tgn:2781913",
        "tgn:7002659",
        "tgn:1000001",
        "tgn:7012149",
        "tgn:2000061",
        "tgn:7029392"
    ],
    "tgn:id":2781913,
    "tgn:name":"Woods Island",
    "tgn:placetype":[
        "aat:300008791"
    ]
},
  "bbox": [],
  "geometry": {"coordinates":[-85.8833,32.8167],"type":"Point"}
}