{
  "id": 2487989,
  "type": "Feature",
  "properties": {
    "tgn:hierarchy":[
        "tgn:2487989",
        "tgn:1000001",
        "tgn:1002369",
        "tgn:7012149",
        "tgn:7007251",
        "tgn:7029392"
    ],
    "tgn:id":2487989,
    "tgn:name":"Maggot Creek",
    "tgn:placetype":[
        "aat:300008706"
    ]
},
  "bbox": [],
  "geometry": {"coordinates":[-89.1333,38.7667],"type":"Point"}
}