{
  "id": 7397979,
  "type": "Feature",
  "properties": {
    "tgn:hierarchy":[
        "tgn:7397979",
        "tgn:1000001",
        "tgn:1001960",
        "tgn:7005560",
        "tgn:7029392"
    ],
    "tgn:id":7397979,
    "tgn:name":"La Pera",
    "tgn:placetype":[
        "aat:300266554",
        "aat:300008699"
    ]
},
  "bbox": [],
  "geometry": {"coordinates":[-111.441389,30.901389],"type":"Point"}
}