{
  "id": 1042743,
  "type": "Feature",
  "properties": {
    "tgn:hierarchy":[
        "tgn:1042743",
        "tgn:7003497",
        "tgn:7001201",
        "tgn:1000003",
        "tgn:1000078",
        "tgn:7029392"
    ],
    "tgn:id":1042743,
    "tgn:name":"Crookstown",
    "tgn:placetype":[
        "aat:300008347"
    ]
},
  "bbox": [],
  "geometry": {"coordinates":[-8.8333,51.8333],"type":"Point"}
}