{
  "id": 2646274,
  "type": "Feature",
  "properties": {
    "tgn:hierarchy":[
        "tgn:2646274",
        "tgn:1000001",
        "tgn:7012149",
        "tgn:1002645",
        "tgn:7007920",
        "tgn:7029392"
    ],
    "tgn:id":2646274,
    "tgn:name":"Sawtooth Ridge",
    "tgn:placetype":[
        "aat:300266640"
    ]
},
  "bbox": [],
  "geometry": {"coordinates":[-123.3167,47.55],"type":"Point"}
}