<<<<<<< HEAD
{
  "id": 2337861,
  "type": "Feature",
  "properties": {
    "tgn:hierarchy":[
        "tgn:2337861",
        "tgn:1000001",
        "tgn:2001260",
        "tgn:7012149",
        "tgn:7007524",
        "tgn:7029392"
    ],
    "tgn:id":2337861,
    "tgn:name":"Fox Gulch",
    "tgn:placetype":[
        "aat:300008761"
    ]
},
  "bbox": [],
  "geometry": {"coordinates":[-113.3667,45.45],"type":"Point"}
}
=======
{"geometry":{"type":"Point","coordinates":[-113.366700,45.450000]},"type":"Feature","properties":{"hierarchy":["tgn:2337861","tgn:1000001","tgn:2001260","tgn:7012149","tgn:7007524","tgn:7029392"],"placetype":["aat:300008761"],"id":2337861,"name:xx":"Fox Gulch"}}
>>>>>>> 03f74aca74312dbeaf24d7e61306dd6a786dc3d0
