<<<<<<< HEAD
{
  "id": 7027975,
  "type": "Feature",
  "properties": {
    "tgn:hierarchy":[
        "tgn:7027975",
        "tgn:7002445",
        "tgn:1000003",
        "tgn:7008157",
        "tgn:7008591",
        "tgn:7029392"
    ],
    "tgn:id":7027975,
    "tgn:name:en":"Long Bennington",
    "tgn:placetype":[
        "aat:300008347",
        "aat:300008372"
    ]
},
  "bbox": [],
  "geometry": {"coordinates":[-0.75,52.966667],"type":"Point"}
}
=======
{"geometry":{"type":"Point","coordinates":[-0.750000,52.966667]},"type":"Feature","properties":{"hierarchy":["tgn:7027975","tgn:7002445","tgn:1000003","tgn:7008157","tgn:7008591","tgn:7029392"],"placetype":["aat:300008347","aat:300008372"],"name:en":"Long Bennington","id":7027975}}
>>>>>>> 03f74aca74312dbeaf24d7e61306dd6a786dc3d0
