{
  "id": 7297269,
  "type": "Feature",
  "properties": {
    "tgn:hierarchy":[
        "tgn:7297269",
        "tgn:7002829",
        "tgn:1000003",
        "tgn:7002786",
        "tgn:1000095",
        "tgn:7029392"
    ],
    "tgn:id":7297269,
    "tgn:name":"T\u00e1moga, R\u00edo",
    "tgn:placetype":[
        "aat:300008699"
    ]
},
  "bbox": [],
  "geometry": {"coordinates":[-7.583333,43.166667],"type":"Point"}
}