<<<<<<< HEAD
{
  "id": 2258222,
  "type": "Feature",
  "properties": {
    "tgn:hierarchy":[
        "tgn:2258222",
        "tgn:1000001",
        "tgn:7006451",
        "tgn:7012149",
        "tgn:2000098",
        "tgn:7029392"
    ],
    "tgn:id":2258222,
    "tgn:name":"Coters Tank",
    "tgn:placetype":[
        "aat:300006191"
    ]
},
  "bbox": [],
  "geometry": {"coordinates":[-113.3833,34.8667],"type":"Point"}
}
=======
{"geometry":{"type":"Point","coordinates":[-113.383300,34.866700]},"type":"Feature","properties":{"hierarchy":["tgn:2258222","tgn:1000001","tgn:7006451","tgn:7012149","tgn:2000098","tgn:7029392"],"placetype":["aat:300006191"],"id":2258222,"name:xx":"Coters Tank"}}
>>>>>>> 03f74aca74312dbeaf24d7e61306dd6a786dc3d0
