{
  "id": 7504574,
  "type": "Feature",
  "properties": {
    "tgn:hierarchy":[
        "tgn:7504574",
        "tgn:1008380",
        "tgn:7000507",
        "tgn:1000226",
        "tgn:1000006",
        "tgn:7029392"
    ],
    "tgn:id":7504574,
    "tgn:name:en":"Munro Bay",
    "tgn:placetype":[
        "aat:300132316"
    ]
},
  "bbox": [],
  "geometry": {"coordinates":[174.486944,-35.788056],"type":"Point"}
}