{
  "id": 2085468,
  "type": "Feature",
  "properties": {
    "tgn:hierarchy":[
        "tgn:2085468",
        "tgn:1000001",
        "tgn:1002270",
        "tgn:7012149",
        "tgn:7007708",
        "tgn:7029392"
    ],
    "tgn:id":2085468,
    "tgn:name":"Rural Dell",
    "tgn:placetype":[
        "aat:300008347",
        "aat:300387210"
    ]
},
  "bbox": [],
  "geometry": {"coordinates":[-122.65,45.1333],"type":"Point"}
}