<<<<<<< HEAD
{
  "id": 7371442,
  "type": "Feature",
  "properties": {
    "tgn:hierarchy":[
        "tgn:7371442",
        "tgn:1000001",
        "tgn:1001906",
        "tgn:7005560",
        "tgn:7029392"
    ],
    "tgn:id":7371442,
    "tgn:name":"La Culebra",
    "tgn:placetype":[
        "aat:300008347"
    ]
},
  "bbox": [],
  "geometry": {"coordinates":[-105.3,21.7],"type":"Point"}
}
=======
{"geometry":{"type":"Point","coordinates":[-105.300000,21.700000]},"type":"Feature","properties":{"hierarchy":["tgn:7371442","tgn:1000001","tgn:1001906","tgn:7005560","tgn:7029392"],"placetype":["aat:300008347"],"id":7371442,"name:xx":"La Culebra"}}
>>>>>>> 03f74aca74312dbeaf24d7e61306dd6a786dc3d0
