{
  "id": 2781372,
  "type": "Feature",
  "properties": {
    "tgn:hierarchy":[
        "tgn:2781372",
        "tgn:1000001",
        "tgn:7012149",
        "tgn:1002691",
        "tgn:7007826",
        "tgn:7029392"
    ],
    "tgn:id":2781372,
    "tgn:name":"Woodland Lake",
    "tgn:placetype":[
        "aat:300008680"
    ]
},
  "bbox": [],
  "geometry": {"coordinates":[-95.7833,30.1833],"type":"Point"}
}