{
  "id": 7568919,
  "type": "Feature",
  "properties": {
    "tgn:hierarchy":[
        "tgn:7568919",
        "tgn:1001828",
        "tgn:1000004",
        "tgn:7000198",
        "tgn:7029392"
    ],
    "tgn:id":7568919,
    "tgn:name:en":"Mansanpalli",
    "tgn:placetype":[
        "aat:300008347"
    ]
},
  "bbox": [],
  "geometry": {"coordinates":[78.391667,17.139167],"type":"Point"}
}