<<<<<<< HEAD
{
  "id": 2406700,
  "type": "Feature",
  "properties": {
    "tgn:hierarchy":[
        "tgn:2406700",
        "tgn:1002136",
        "tgn:1000001",
        "tgn:7012149",
        "tgn:7007706",
        "tgn:7029392"
    ],
    "tgn:id":2406700,
    "tgn:name":"Hunt Hollow",
    "tgn:placetype":[
        "aat:300008761"
    ]
},
  "bbox": [],
  "geometry": {"coordinates":[-83.3333,38.8167],"type":"Point"}
}
=======
{"geometry":{"type":"Point","coordinates":[-83.333300,38.816700]},"type":"Feature","properties":{"hierarchy":["tgn:2406700","tgn:1002136","tgn:1000001","tgn:7012149","tgn:7007706","tgn:7029392"],"placetype":["aat:300008761"],"id":2406700,"name:xx":"Hunt Hollow"}}
>>>>>>> 03f74aca74312dbeaf24d7e61306dd6a786dc3d0
