{
  "id": 7374354,
  "type": "Feature",
  "properties": {
    "tgn:hierarchy":[
        "tgn:7374354",
        "tgn:1000001",
        "tgn:1001960",
        "tgn:7005560",
        "tgn:7029392"
    ],
    "tgn:id":7374354,
    "tgn:name":"Laguna Prieta, Cerro",
    "tgn:placetype":[
        "aat:300008777"
    ]
},
  "bbox": [],
  "geometry": {"coordinates":[-114.566667,32.283333],"type":"Point"}
}