<<<<<<< HEAD
{
  "id": 7177809,
  "type": "Feature",
  "properties": {
    "tgn:hierarchy":[
        "tgn:7177809",
        "tgn:7003669",
        "tgn:1000003",
        "tgn:7000084",
        "tgn:7029392"
    ],
    "tgn:id":7177809,
    "tgn:name":"Hainzenberg",
    "tgn:placetype":[
        "aat:300008777"
    ]
},
  "bbox": [],
  "geometry": {"coordinates":[11.816667,49.333333],"type":"Point"}
}
=======
{"geometry":{"type":"Point","coordinates":[11.816667,49.333333]},"type":"Feature","properties":{"hierarchy":["tgn:7177809","tgn:7003669","tgn:1000003","tgn:7000084","tgn:7029392"],"placetype":["aat:300008777"],"id":7177809,"name:xx":"Hainzenberg"}}
>>>>>>> 03f74aca74312dbeaf24d7e61306dd6a786dc3d0
