{
  "id": 7570513,
  "type": "Feature",
  "properties": {
    "tgn:hierarchy":[
        "tgn:7570513",
        "tgn:1001828",
        "tgn:1000004",
        "tgn:7000198",
        "tgn:7029392"
    ],
    "tgn:id":7570513,
    "tgn:name:en":"Dakuntapalli",
    "tgn:placetype":[
        "aat:300008347"
    ]
},
  "bbox": [],
  "geometry": {"coordinates":[78.945,17.7975],"type":"Point"}
}