{
  "id": 2216627,
  "type": "Feature",
  "properties": {
    "tgn:hierarchy":[
        "tgn:2216627",
        "tgn:1000001",
        "tgn:7012149",
        "tgn:7007827",
        "tgn:7029392"
    ],
    "tgn:id":2216627,
    "tgn:name":"Camp Creek",
    "tgn:placetype":[
        "aat:300008706"
    ]
},
  "bbox": [],
  "geometry": {"coordinates":[-113.1333,37.4833],"type":"Point"}
}