{
  "id": 7161911,
  "type": "Feature",
  "properties": {
    "tgn:hierarchy":[
        "tgn:7161911",
        "tgn:7000096",
        "tgn:1000003",
        "tgn:7000084",
        "tgn:7029392"
    ],
    "tgn:id":7161911,
    "tgn:name":"Horst",
    "tgn:placetype":[
        "aat:300008347"
    ]
},
  "bbox": [],
  "geometry": {"coordinates":[12.05,53.15],"type":"Point"}
}