{
  "id": 2630996,
  "type": "Feature",
  "properties": {
    "tgn:hierarchy":[
        "tgn:2630996",
        "tgn:1000001",
        "tgn:7012149",
        "tgn:1003038",
        "tgn:7007517",
        "tgn:7029392"
    ],
    "tgn:id":2630996,
    "tgn:name":"Round Meadow Brook",
    "tgn:placetype":[
        "aat:300008699"
    ]
},
  "bbox": [],
  "geometry": {"coordinates":[-71.5333,42.0667],"type":"Point"}
}