{
  "id": 7024080,
  "type": "Feature",
  "properties": {
    "tgn:hierarchy":[
        "tgn:7024080",
        "tgn:7002870",
        "tgn:1000003",
        "tgn:1000070",
        "tgn:7029392"
    ],
    "tgn:id":7024080,
    "tgn:name":"Achenheim",
    "tgn:placetype":[
        "aat:300008347",
        "aat:300008375"
    ]
},
  "bbox": [],
  "geometry": {"coordinates":[7.6333,48.5833],"type":"Point"}
}