{
  "id": 7556725,
  "type": "Feature",
  "properties": {
    "tgn:hierarchy":[
        "tgn:7556725",
        "tgn:1000004",
        "tgn:7000198",
        "tgn:7016722",
        "tgn:7029392"
    ],
    "tgn:id":7556725,
    "tgn:name:en":"Saheri",
    "tgn:placetype":[
        "aat:300008347"
    ]
},
  "bbox": [],
  "geometry": {"coordinates":[83.447658,25.56478],"type":"Point"}
}