{
  "id": 2703939,
  "type": "Feature",
  "properties": {
    "tgn:hierarchy":[
        "tgn:2703939",
        "tgn:1000001",
        "tgn:2001587",
        "tgn:7012149",
        "tgn:7007705",
        "tgn:7029392"
    ],
    "tgn:id":2703939,
    "tgn:name":"Sunday Island",
    "tgn:placetype":[
        "aat:300008791"
    ]
},
  "bbox": [],
  "geometry": {"coordinates":[-102.5833,47.7833],"type":"Point"}
}