{
  "id": 2468891,
  "type": "Feature",
  "properties": {
    "tgn:hierarchy":[
        "tgn:2468891",
        "tgn:1000001",
        "tgn:7012149",
        "tgn:7007706",
        "tgn:7029392"
    ],
    "tgn:id":2468891,
    "tgn:name":"Long Run",
    "tgn:placetype":[
        "aat:300008699"
    ]
},
  "bbox": [],
  "geometry": {"coordinates":[-82.3333,39.2167],"type":"Point"}
}