{
  "id": 2579039,
  "type": "Feature",
  "properties": {
    "tgn:hierarchy":[
        "tgn:2579039",
        "tgn:1000001",
        "tgn:7012149",
        "tgn:2000494",
        "tgn:7007250",
        "tgn:7029392"
    ],
    "tgn:id":2579039,
    "tgn:name":"Phoebe Creek",
    "tgn:placetype":[
        "aat:300008706"
    ]
},
  "bbox": [],
  "geometry": {"coordinates":[-115.65,44.9333],"type":"Point"}
}