{
  "id": 2743619,
  "type": "Feature",
  "properties": {
    "tgn:hierarchy":[
        "tgn:2743619",
        "tgn:1000001",
        "tgn:7012149",
        "tgn:2002164",
        "tgn:7007919",
        "tgn:7029392"
    ],
    "tgn:id":2743619,
    "tgn:name":"Vaughn Branch",
    "tgn:placetype":[
        "aat:300008699"
    ]
},
  "bbox": [],
  "geometry": {"coordinates":[-81.2167,36.7333],"type":"Point"}
}