{
  "id": 2547346,
  "type": "Feature",
  "properties": {
    "tgn:hierarchy":[
        "tgn:2547346",
        "tgn:2124017",
        "tgn:7006450",
        "tgn:1000001",
        "tgn:7012149",
        "tgn:7029392"
    ],
    "tgn:id":2547346,
    "tgn:name":"North Fork Ship Creek",
    "tgn:placetype":[
        "aat:300008706"
    ]
},
  "bbox": [],
  "geometry": {"coordinates":[-149.6667,61.25],"type":"Point"}
}