{
  "id": 2059587,
  "type": "Feature",
  "properties": {
    "tgn:hierarchy":[
        "tgn:2059587",
        "tgn:1000001",
        "tgn:7012149",
        "tgn:1002598",
        "tgn:7007523",
        "tgn:7029392"
    ],
    "tgn:id":2059587,
    "tgn:name":"Louisville",
    "tgn:placetype":[
        "aat:300008347",
        "aat:300387210"
    ]
},
  "bbox": [],
  "geometry": {"coordinates":[-91.1667,39.1833],"type":"Point"}
}