<<<<<<< HEAD
{
  "id": 2152395,
  "type": "Feature",
  "properties": {
    "tgn:hierarchy":[
        "tgn:2152395",
        "tgn:1000001",
        "tgn:7012149",
        "tgn:7007256",
        "tgn:7029392"
    ],
    "tgn:id":2152395,
    "tgn:name":"Bay Natchez",
    "tgn:placetype":[
        "aat:300132316"
    ]
},
  "bbox": [],
  "geometry": {"coordinates":[-91.2167,30.0],"type":"Point"}
}
=======
{"geometry":{"type":"Point","coordinates":[-91.216700,30.000000]},"type":"Feature","properties":{"hierarchy":["tgn:2152395","tgn:1000001","tgn:7012149","tgn:7007256","tgn:7029392"],"placetype":["aat:300132316"],"id":2152395,"name:xx":"Bay Natchez"}}
>>>>>>> 03f74aca74312dbeaf24d7e61306dd6a786dc3d0
