{
  "id": 2690773,
  "type": "Feature",
  "properties": {
    "tgn:hierarchy":[
        "tgn:2690773",
        "tgn:1000001",
        "tgn:7012149",
        "tgn:7007713",
        "tgn:7029392"
    ],
    "tgn:id":2690773,
    "tgn:name":"Standfast Creek",
    "tgn:placetype":[
        "aat:300008706"
    ]
},
  "bbox": [],
  "geometry": {"coordinates":[-97.2167,45.7333],"type":"Point"}
}