{
  "id": 1100675,
  "type": "Feature",
  "properties": {
    "tgn:hierarchy":[
        "tgn:1100675",
        "tgn:7001242",
        "tgn:7016749",
        "tgn:1000193",
        "tgn:7029392"
    ],
    "tgn:id":1100675,
    "tgn:name":"Umgungundhlovu",
    "tgn:placetype":[
        "aat:300000833"
    ]
},
  "bbox": [],
  "geometry": {"coordinates":[31.4667,-28.45],"type":"Point"}
}