{
  "id": 7335852,
  "type": "Feature",
  "properties": {
    "tgn:hierarchy":[
        "tgn:7335852",
        "tgn:7002835",
        "tgn:7001158",
        "tgn:1000003",
        "tgn:1000095",
        "tgn:7029392"
    ],
    "tgn:id":7335852,
    "tgn:name":"Francos",
    "tgn:placetype":[
        "aat:300008347"
    ]
},
  "bbox": [],
  "geometry": {"coordinates":[-5.483333,40.916667],"type":"Point"}
}