{
  "id": 2355093,
  "type": "Feature",
  "properties": {
    "tgn:hierarchy":[
        "tgn:2355093",
        "tgn:1002176",
        "tgn:1000001",
        "tgn:7012149",
        "tgn:7007828",
        "tgn:7029392"
    ],
    "tgn:id":2355093,
    "tgn:name":"Goodrich Brook",
    "tgn:placetype":[
        "aat:300008699"
    ]
},
  "bbox": [],
  "geometry": {"coordinates":[-73.0333,42.75],"type":"Point"}
}