<<<<<<< HEAD
{
  "id": 2336426,
  "type": "Feature",
  "properties": {
    "tgn:hierarchy":[
        "tgn:2336426",
        "tgn:1002215",
        "tgn:1000001",
        "tgn:7012149",
        "tgn:7007565",
        "tgn:7029392"
    ],
    "tgn:id":2336426,
    "tgn:name":"Fountain Woods",
    "tgn:placetype":[
        "aat:300132451"
    ]
},
  "bbox": [],
  "geometry": {"coordinates":[-74.8333,40.05],"type":"Point"}
}
=======
{"geometry":{"type":"Point","coordinates":[-74.833300,40.050000]},"type":"Feature","properties":{"hierarchy":["tgn:2336426","tgn:1002215","tgn:1000001","tgn:7012149","tgn:7007565","tgn:7029392"],"placetype":["aat:300132451"],"id":2336426,"name:xx":"Fountain Woods"}}
>>>>>>> 03f74aca74312dbeaf24d7e61306dd6a786dc3d0
