{
  "id": 2258295,
  "type": "Feature",
  "properties": {
    "tgn:hierarchy":[
        "tgn:2258295",
        "tgn:7002659",
        "tgn:1000001",
        "tgn:2000014",
        "tgn:7012149",
        "tgn:7029392"
    ],
    "tgn:id":2258295,
    "tgn:name":"Cottaquilla Mountain",
    "tgn:placetype":[
        "aat:300008798"
    ]
},
  "bbox": [],
  "geometry": {"coordinates":[-85.6833,33.7667],"type":"Point"}
}