{
  "id": 1074108,
  "type": "Feature",
  "properties": {
    "tgn:hierarchy":[
        "tgn:1074108",
        "tgn:1000004",
        "tgn:7002081",
        "tgn:1000111",
        "tgn:7029392"
    ],
    "tgn:id":1074108,
    "tgn:name":"Zhouzhuang",
    "tgn:placetype":[
        "aat:300008347"
    ]
},
  "bbox": [],
  "geometry": {"coordinates":[120.8333,31.1167],"type":"Point"}
}