{
  "id": 2587000,
  "type": "Feature",
  "properties": {
    "tgn:hierarchy":[
        "tgn:2587000",
        "tgn:7013388",
        "tgn:1000001",
        "tgn:7012149",
        "tgn:7007517",
        "tgn:7029392"
    ],
    "tgn:id":2587000,
    "tgn:name":"Plantain Pond",
    "tgn:placetype":[
        "aat:300006191"
    ]
},
  "bbox": [],
  "geometry": {"coordinates":[-73.4333,42.0667],"type":"Point"}
}