{
  "id": 2605566,
  "type": "Feature",
  "properties": {
    "tgn:hierarchy":[
        "tgn:2605566",
        "tgn:1000001",
        "tgn:7012149",
        "tgn:7007157",
        "tgn:1002956",
        "tgn:7029392"
    ],
    "tgn:id":2605566,
    "tgn:name":"Railroad Ditch",
    "tgn:placetype":[
        "aat:300006075"
    ]
},
  "bbox": [],
  "geometry": {"coordinates":[-119.35,36.1833],"type":"Point"}
}