{
  "id": 7515017,
  "type": "Feature",
  "properties": {
    "tgn:hierarchy":[
        "tgn:7515017",
        "tgn:1009227",
        "tgn:1000226",
        "tgn:7018437",
        "tgn:1000006",
        "tgn:7029392"
    ],
    "tgn:id":7515017,
    "tgn:name:en":"Carl Creek",
    "tgn:placetype":[
        "aat:300008699"
    ]
},
  "bbox": [],
  "geometry": {"coordinates":[168.666667,-44.083333],"type":"Point"}
}