{
  "id": 2125786,
  "type": "Feature",
  "properties": {
    "tgn:hierarchy":[
        "tgn:2125786",
        "tgn:1000001",
        "tgn:7012149",
        "tgn:2001854",
        "tgn:7007825",
        "tgn:7029392"
    ],
    "tgn:id":2125786,
    "tgn:name":"Adams Creek Lake",
    "tgn:placetype":[
        "aat:300006191"
    ]
},
  "bbox": [],
  "geometry": {"coordinates":[-85.0167,36.0833],"type":"Point"}
}