<<<<<<< HEAD
{
  "id": 7363687,
  "type": "Feature",
  "properties": {
    "tgn:hierarchy":[
        "tgn:7363687",
        "tgn:7005581",
        "tgn:1000001",
        "tgn:7005560",
        "tgn:7029392"
    ],
    "tgn:id":7363687,
    "tgn:name":"El Aturdido",
    "tgn:placetype":[
        "aat:300008347"
    ]
},
  "bbox": [],
  "geometry": {"coordinates":[-105.266667,28.033333],"type":"Point"}
}
=======
{"geometry":{"type":"Point","coordinates":[-105.266667,28.033333]},"type":"Feature","properties":{"hierarchy":["tgn:7363687","tgn:7005581","tgn:1000001","tgn:7005560","tgn:7029392"],"placetype":["aat:300008347"],"id":7363687,"name:xx":"El Aturdido"}}
>>>>>>> 03f74aca74312dbeaf24d7e61306dd6a786dc3d0
