<<<<<<< HEAD
{
  "id": 2401346,
  "type": "Feature",
  "properties": {
    "tgn:hierarchy":[
        "tgn:2401346",
        "tgn:1000001",
        "tgn:7012149",
        "tgn:2001750",
        "tgn:7007712",
        "tgn:7029392"
    ],
    "tgn:id":2401346,
    "tgn:name":"Horsepen Creek",
    "tgn:placetype":[
        "aat:300008706"
    ]
},
  "bbox": [],
  "geometry": {"coordinates":[-78.9167,33.9],"type":"Point"}
}
=======
{"geometry":{"type":"Point","coordinates":[-78.916700,33.900000]},"type":"Feature","properties":{"hierarchy":["tgn:2401346","tgn:1000001","tgn:7012149","tgn:2001750","tgn:7007712","tgn:7029392"],"placetype":["aat:300008706"],"id":2401346,"name:xx":"Horsepen Creek"}}
>>>>>>> 03f74aca74312dbeaf24d7e61306dd6a786dc3d0
