<<<<<<< HEAD
{
  "id": 2250605,
  "type": "Feature",
  "properties": {
    "tgn:hierarchy":[
        "tgn:2250605",
        "tgn:1000001",
        "tgn:2001260",
        "tgn:7012149",
        "tgn:7007524",
        "tgn:7029392"
    ],
    "tgn:id":2250605,
    "tgn:name":"Colorado Creek",
    "tgn:placetype":[
        "aat:300008706"
    ]
},
  "bbox": [],
  "geometry": {"coordinates":[-113.15,44.8667],"type":"Point"}
}
=======
{"geometry":{"type":"Point","coordinates":[-113.150000,44.866700]},"type":"Feature","properties":{"hierarchy":["tgn:2250605","tgn:1000001","tgn:2001260","tgn:7012149","tgn:7007524","tgn:7029392"],"placetype":["aat:300008706"],"id":2250605,"name:xx":"Colorado Creek"}}
>>>>>>> 03f74aca74312dbeaf24d7e61306dd6a786dc3d0
