<<<<<<< HEAD
{
  "id": 7484110,
  "type": "Feature",
  "properties": {
    "tgn:hierarchy":[
        "tgn:7484110",
        "tgn:1000004",
        "tgn:7492971",
        "tgn:1000141",
        "tgn:7029392"
    ],
    "tgn:id":7484110,
    "tgn:name":"Jiuluokayoukayou Shan",
    "tgn:placetype":[
        "aat:300008798"
    ]
},
  "bbox": [],
  "geometry": {"coordinates":[120.6525,22.471111],"type":"Point"}
}
=======
{"geometry":{"type":"Point","coordinates":[120.652500,22.471111]},"type":"Feature","properties":{"hierarchy":["tgn:7484110","tgn:1000004","tgn:7492971","tgn:1000141","tgn:7029392"],"placetype":["aat:300008798"],"id":7484110,"name:xx":"Jiuluokayoukayou Shan"}}
>>>>>>> 03f74aca74312dbeaf24d7e61306dd6a786dc3d0
