{
  "id": 2360819,
  "type": "Feature",
  "properties": {
    "tgn:hierarchy":[
        "tgn:2360819",
        "tgn:1000001",
        "tgn:1002276",
        "tgn:7012149",
        "tgn:7007708",
        "tgn:7029392"
    ],
    "tgn:id":2360819,
    "tgn:name":"Grassy Lake",
    "tgn:placetype":[
        "aat:300008680"
    ]
},
  "bbox": [],
  "geometry": {"coordinates":[-123.85,45.8167],"type":"Point"}
}