{
  "id": 2287143,
  "type": "Feature",
  "properties": {
    "tgn:hierarchy":[
        "tgn:2287143",
        "tgn:1000001",
        "tgn:7012149",
        "tgn:7014612",
        "tgn:7007568",
        "tgn:7029392"
    ],
    "tgn:id":2287143,
    "tgn:name":"Dickey Brook",
    "tgn:placetype":[
        "aat:300008699"
    ]
},
  "bbox": [],
  "geometry": {"coordinates":[-73.8833,41.2833],"type":"Point"}
}