{
  "id": 2284011,
  "type": "Feature",
  "properties": {
    "tgn:hierarchy":[
        "tgn:2284011",
        "tgn:1000001",
        "tgn:7012149",
        "tgn:2001454",
        "tgn:7007566",
        "tgn:7029392"
    ],
    "tgn:id":2284011,
    "tgn:name":"Dennison Place",
    "tgn:placetype":[
        "aat:300008347"
    ]
},
  "bbox": [],
  "geometry": {"coordinates":[-106.0333,35.25],"type":"Point"}
}