{
  "id": 2071272,
  "type": "Feature",
  "properties": {
    "tgn:hierarchy":[
        "tgn:2071272",
        "tgn:1000001",
        "tgn:7012149",
        "tgn:1002624",
        "tgn:7007568",
        "tgn:7029392"
    ],
    "tgn:id":2071272,
    "tgn:name":"North Chittenango",
    "tgn:placetype":[
        "aat:300008347"
    ]
},
  "bbox": [],
  "geometry": {"coordinates":[-75.8667,43.0667],"type":"Point"}
}