{
  "id": 7018677,
  "type": "Feature",
  "properties": {
    "tgn:hierarchy":[
        "tgn:7018677",
        "tgn:1000003",
        "tgn:7011666",
        "tgn:7006660",
        "tgn:7029392"
    ],
    "tgn:id":7018677,
    "tgn:name":"Lutsenki",
    "tgn:placetype":[
        "aat:300008347"
    ]
},
  "bbox": [],
  "geometry": {"coordinates":[33.0667,50.45],"type":"Point"}
}