{
  "id": 7333309,
  "type": "Feature",
  "properties": {
    "tgn:hierarchy":[
        "tgn:7333309",
        "tgn:7002758",
        "tgn:7002823",
        "tgn:1000003",
        "tgn:1000095",
        "tgn:7029392"
    ],
    "tgn:id":7333309,
    "tgn:name":"Fuente del Oro",
    "tgn:placetype":[
        "aat:300008347"
    ]
},
  "bbox": [],
  "geometry": {"coordinates":[-6.733333,37.866667],"type":"Point"}
}