{
  "id": 2609658,
  "type": "Feature",
  "properties": {
    "tgn:hierarchy":[
        "tgn:2609658",
        "tgn:1000001",
        "tgn:7012149",
        "tgn:7007158",
        "tgn:2000243",
        "tgn:7029392"
    ],
    "tgn:id":2609658,
    "tgn:name":"Razorback Ridge",
    "tgn:placetype":[
        "aat:300266640"
    ]
},
  "bbox": [],
  "geometry": {"coordinates":[-108.6167,39.7167],"type":"Point"}
}