{
  "id": 2002992,
  "type": "Feature",
  "properties": {
    "tgn:hierarchy":[
        "tgn:2002992",
        "tgn:7002659",
        "tgn:1000001",
        "tgn:7012149",
        "tgn:2000041",
        "tgn:7029392"
    ],
    "tgn:id":2002992,
    "tgn:name":"Cartwright",
    "tgn:placetype":[
        "aat:300008347"
    ]
},
  "bbox": [],
  "geometry": {"coordinates":[-87.05,34.8667],"type":"Point"}
}