{
  "id": 2221718,
  "type": "Feature",
  "properties": {
    "tgn:hierarchy":[
        "tgn:2221718",
        "tgn:1000001",
        "tgn:7012149",
        "tgn:2002300",
        "tgn:7013961",
        "tgn:7029392"
    ],
    "tgn:id":2221718,
    "tgn:name":"Carlo Run",
    "tgn:placetype":[
        "aat:300008699"
    ]
},
  "bbox": [],
  "geometry": {"coordinates":[-80.3333,38.5833],"type":"Point"}
}