{
  "id": 2236942,
  "type": "Feature",
  "properties": {
    "tgn:hierarchy":[
        "tgn:2236942",
        "tgn:7006450",
        "tgn:1000001",
        "tgn:2124077",
        "tgn:7012149",
        "tgn:7029392"
    ],
    "tgn:id":2236942,
    "tgn:name":"Chilkat Inlet",
    "tgn:placetype":[
        "aat:300132316"
    ]
},
  "bbox": [],
  "geometry": {"coordinates":[-135.4167,59.15],"type":"Point"}
}