{
  "id": 7078655,
  "type": "Feature",
  "properties": {
    "tgn:hierarchy":[
        "tgn:7078655",
        "tgn:1000003",
        "tgn:7003678",
        "tgn:7000084",
        "tgn:7029392"
    ],
    "tgn:id":7078655,
    "tgn:name":"W\u00fcrze-Berg",
    "tgn:placetype":[
        "aat:300008777"
    ]
},
  "bbox": [],
  "geometry": {"coordinates":[8.75,50.966667],"type":"Point"}
}