{
  "id": 2685122,
  "type": "Feature",
  "properties": {
    "tgn:hierarchy":[
        "tgn:2685122",
        "tgn:7006450",
        "tgn:1000001",
        "tgn:7019698",
        "tgn:7012149",
        "tgn:7029392"
    ],
    "tgn:id":2685122,
    "tgn:name":"Spoon Glacier",
    "tgn:placetype":[
        "aat:300008835"
    ]
},
  "bbox": [],
  "geometry": {"coordinates":[-149.25,60.0167],"type":"Point"}
}