{
  "id": 1111194,
  "type": "Feature",
  "properties": {
    "tgn:hierarchy":[
        "tgn:1111194",
        "tgn:1000004",
        "tgn:1000137",
        "tgn:7029392"
    ],
    "tgn:id":1111194,
    "tgn:name":"Jizl, W\u0101d\u012b al-",
    "tgn:placetype":[
        "aat:300387091"
    ]
},
  "bbox": [],
  "geometry": {"coordinates":[38.3667,25.6167],"type":"Point"}
}