{
  "id": 2770871,
  "type": "Feature",
  "properties": {
    "tgn:hierarchy":[
        "tgn:2770871",
        "tgn:1000001",
        "tgn:7012149",
        "tgn:2001958",
        "tgn:7007826",
        "tgn:7029392"
    ],
    "tgn:id":2770871,
    "tgn:name":"Wildcat Creek",
    "tgn:placetype":[
        "aat:300008706"
    ]
},
  "bbox": [],
  "geometry": {"coordinates":[-100.5833,31.7833],"type":"Point"}
}