{
  "id": 2219019,
  "type": "Feature",
  "properties": {
    "tgn:hierarchy":[
        "tgn:2219019",
        "tgn:1000001",
        "tgn:7016172",
        "tgn:7012149",
        "tgn:2000157",
        "tgn:7029392"
    ],
    "tgn:id":2219019,
    "tgn:name":"Caney Creek",
    "tgn:placetype":[
        "aat:300008761"
    ]
},
  "bbox": [],
  "geometry": {"coordinates":[-92.7167,34.9167],"type":"Point"}
}