{
  "id": 7174373,
  "type": "Feature",
  "properties": {
    "tgn:hierarchy":[
        "tgn:7174373",
        "tgn:1000003",
        "tgn:7003678",
        "tgn:7000084",
        "tgn:7029392"
    ],
    "tgn:id":7174373,
    "tgn:name":"Gro\u00dfer Kors-Kopf",
    "tgn:placetype":[
        "aat:300008777"
    ]
},
  "bbox": [],
  "geometry": {"coordinates":[8.766667,51.183333],"type":"Point"}
}