{
  "id": 7505784,
  "type": "Feature",
  "properties": {
    "tgn:hierarchy":[
        "tgn:7505784",
        "tgn:1009227",
        "tgn:1000226",
        "tgn:1000006",
        "tgn:7016850",
        "tgn:7029392"
    ],
    "tgn:id":7505784,
    "tgn:name:en":"Toms Creek",
    "tgn:placetype":[
        "aat:300008699"
    ]
},
  "bbox": [],
  "geometry": {"coordinates":[170.55,-43.166667],"type":"Point"}
}