{
  "id": 2302746,
  "type": "Feature",
  "properties": {
    "tgn:hierarchy":[
        "tgn:2302746",
        "tgn:1000001",
        "tgn:2001100",
        "tgn:7012149",
        "tgn:7007522",
        "tgn:7029392"
    ],
    "tgn:id":2302746,
    "tgn:name":"Dye Branch",
    "tgn:placetype":[
        "aat:300008699"
    ]
},
  "bbox": [],
  "geometry": {"coordinates":[-90.3833,31.7167],"type":"Point"}
}