{
  "id": 7374014,
  "type": "Feature",
  "properties": {
    "tgn:hierarchy":[
        "tgn:7374014",
        "tgn:7005583",
        "tgn:1000001",
        "tgn:7005560",
        "tgn:7029392"
    ],
    "tgn:id":7374014,
    "tgn:name":"Rancho La Guitarrita",
    "tgn:placetype":[
        "aat:300000241"
    ]
},
  "bbox": [],
  "geometry": {"coordinates":[-105.630278,24.119167],"type":"Point"}
}