<<<<<<< HEAD
{
  "id": 7374014,
  "type": "Feature",
  "properties": {
    "tgn:hierarchy":[
        "tgn:7374014",
        "tgn:7005583",
        "tgn:1000001",
        "tgn:7005560",
        "tgn:7029392"
    ],
    "tgn:id":7374014,
    "tgn:name":"Rancho La Guitarrita",
    "tgn:placetype":[
        "aat:300000241"
    ]
},
  "bbox": [],
  "geometry": {"coordinates":[-105.630278,24.119167],"type":"Point"}
}
=======
{"geometry":{"type":"Point","coordinates":[-105.630278,24.119167]},"type":"Feature","properties":{"hierarchy":["tgn:7374014","tgn:7005583","tgn:1000001","tgn:7005560","tgn:7029392"],"placetype":["aat:300000241"],"id":7374014,"name:xx":"Rancho La Guitarrita"}}
>>>>>>> 03f74aca74312dbeaf24d7e61306dd6a786dc3d0
