{
  "id": 2632241,
  "type": "Feature",
  "properties": {
    "tgn:hierarchy":[
        "tgn:2632241",
        "tgn:1000001",
        "tgn:1002316",
        "tgn:7012149",
        "tgn:7007922",
        "tgn:7029392"
    ],
    "tgn:id":2632241,
    "tgn:name":"Roxbury Creek",
    "tgn:placetype":[
        "aat:300008706"
    ]
},
  "bbox": [],
  "geometry": {"coordinates":[-89.6167,43.2333],"type":"Point"}
}