{
  "id": 1030246,
  "type": "Feature",
  "properties": {
    "tgn:hierarchy":[
        "tgn:1030246",
        "tgn:7002445",
        "tgn:1000003",
        "tgn:7011961",
        "tgn:7008591",
        "tgn:7029392"
    ],
    "tgn:id":1030246,
    "tgn:name:ang":"Osmentone",
    "tgn:placetype":[
        "aat:300008347",
        "aat:300008372"
    ]
},
  "bbox": [],
  "geometry": {"coordinates":[-2.366667,50.633333],"type":"Point"}
}