{
  "id": 2336533,
  "type": "Feature",
  "properties": {
    "tgn:hierarchy":[
        "tgn:2336533",
        "tgn:1000001",
        "tgn:7012149",
        "tgn:2001117",
        "tgn:7007522",
        "tgn:7029392"
    ],
    "tgn:id":2336533,
    "tgn:name":"Four Forks",
    "tgn:placetype":[
        "aat:300008347"
    ]
},
  "bbox": [],
  "geometry": {"coordinates":[-91.1167,31.6167],"type":"Point"}
}