{
  "id": 7167623,
  "type": "Feature",
  "properties": {
    "tgn:hierarchy":[
        "tgn:7167623",
        "tgn:1000003",
        "tgn:7000094",
        "tgn:7000084",
        "tgn:7029392"
    ],
    "tgn:id":7167623,
    "tgn:name":"Haubach",
    "tgn:placetype":[
        "aat:300008699"
    ]
},
  "bbox": [],
  "geometry": {"coordinates":[12.333333,54.233333],"type":"Point"}
}