{
  "id": 7146752,
  "type": "Feature",
  "properties": {
    "tgn:hierarchy":[
        "tgn:7146752",
        "tgn:1000003",
        "tgn:7003676",
        "tgn:7000084",
        "tgn:7029392"
    ],
    "tgn:id":7146752,
    "tgn:name":"Klein Remels",
    "tgn:placetype":[
        "aat:300387200"
    ]
},
  "bbox": [],
  "geometry": {"coordinates":[7.733333,53.283333],"type":"Point"}
}