{
  "id": 2310053,
  "type": "Feature",
  "properties": {
    "tgn:hierarchy":[
        "tgn:2310053",
        "tgn:1000001",
        "tgn:7016172",
        "tgn:7012149",
        "tgn:2000136",
        "tgn:7029392"
    ],
    "tgn:id":2310053,
    "tgn:name":"Eastwood Addition",
    "tgn:placetype":[
        "aat:300008347"
    ]
},
  "bbox": [],
  "geometry": {"coordinates":[-91.6167,35.75],"type":"Point"}
}