{
  "id": 7474126,
  "type": "Feature",
  "properties": {
    "tgn:hierarchy":[
        "tgn:7474126",
        "tgn:7001010",
        "tgn:1000004",
        "tgn:1000141",
        "tgn:7029392"
    ],
    "tgn:id":7474126,
    "tgn:name":"Yuanwan Shan",
    "tgn:placetype":[
        "aat:300008798"
    ]
},
  "bbox": [],
  "geometry": {"coordinates":[121.345154,23.324443],"type":"Point"}
}