{
  "id": 7414686,
  "type": "Feature",
  "properties": {
    "tgn:hierarchy":[
        "tgn:7414686",
        "tgn:7005584",
        "tgn:1000001",
        "tgn:7005560",
        "tgn:7029392"
    ],
    "tgn:id":7414686,
    "tgn:name":"Estancia P\u00e9njamo",
    "tgn:placetype":[
        "aat:300008347"
    ]
},
  "bbox": [],
  "geometry": {"coordinates":[-101.693056,20.393611],"type":"Point"}
}