{
  "id": 2205060,
  "type": "Feature",
  "properties": {
    "tgn:hierarchy":[
        "tgn:2205060",
        "tgn:1000001",
        "tgn:7012149",
        "tgn:2001300",
        "tgn:7007524",
        "tgn:7029392"
    ],
    "tgn:id":2205060,
    "tgn:name":"Bugle Creek",
    "tgn:placetype":[
        "aat:300008706"
    ]
},
  "bbox": [],
  "geometry": {"coordinates":[-113.7667,45.8333],"type":"Point"}
}