{
  "id": 2094201,
  "type": "Feature",
  "properties": {
    "tgn:hierarchy":[
        "tgn:2094201",
        "tgn:1000001",
        "tgn:7012149",
        "tgn:1002995",
        "tgn:7007710",
        "tgn:7029392"
    ],
    "tgn:id":2094201,
    "tgn:name":"Washington Mall",
    "tgn:placetype":[
        "aat:300247594"
    ]
},
  "bbox": [],
  "geometry": {"coordinates":[-80.2333,40.1833],"type":"Point"}
}