{
  "id": 7140715,
  "type": "Feature",
  "properties": {
    "tgn:hierarchy":[
        "tgn:7140715",
        "tgn:1000003",
        "tgn:7000094",
        "tgn:7000084",
        "tgn:7029392"
    ],
    "tgn:id":7140715,
    "tgn:name":"Losentitz",
    "tgn:placetype":[
        "aat:300008347"
    ]
},
  "bbox": [],
  "geometry": {"coordinates":[13.333333,54.25],"type":"Point"}
}