{
  "id": 7257904,
  "type": "Feature",
  "properties": {
    "tgn:hierarchy":[
        "tgn:7257904",
        "tgn:1000003",
        "tgn:7006951",
        "tgn:7016845",
        "tgn:7029392"
    ],
    "tgn:id":7257904,
    "tgn:name:nl":"Bantam",
    "tgn:placetype":[
        "aat:300387502"
    ]
},
  "bbox": [],
  "geometry": {"coordinates":[5.133333,52.266667],"type":"Point"}
}