{
  "id": 7232067,
  "type": "Feature",
  "properties": {
    "tgn:hierarchy":[
        "tgn:7232067",
        "tgn:7002690",
        "tgn:7012056",
        "tgn:1000003",
        "tgn:1000074",
        "tgn:7029392"
    ],
    "tgn:id":7232067,
    "tgn:name":"Kef\u00e1lou R\u00e9ma",
    "tgn:placetype":[
        "aat:300008699"
    ]
},
  "bbox": [],
  "geometry": {"coordinates":[24.45,35.366667],"type":"Point"}
}