{
  "id": 2467643,
  "type": "Feature",
  "properties": {
    "tgn:hierarchy":[
        "tgn:2467643",
        "tgn:2001467",
        "tgn:1000001",
        "tgn:7012149",
        "tgn:7007709",
        "tgn:7029392"
    ],
    "tgn:id":2467643,
    "tgn:name":"Long Hope Mountain",
    "tgn:placetype":[
        "aat:300008798"
    ]
},
  "bbox": [],
  "geometry": {"coordinates":[-81.65,36.35],"type":"Point"}
}