{
  "id": 7475035,
  "type": "Feature",
  "properties": {
    "tgn:hierarchy":[
        "tgn:7475035",
        "tgn:7487020",
        "tgn:1000004",
        "tgn:1000141",
        "tgn:7029392"
    ],
    "tgn:id":7475035,
    "tgn:name":"Yutengping",
    "tgn:placetype":[
        "aat:300008347"
    ]
},
  "bbox": [],
  "geometry": {"coordinates":[120.783768,24.358874],"type":"Point"}
}