{
  "id": 7557802,
  "type": "Feature",
  "properties": {
    "tgn:hierarchy":[
        "tgn:7557802",
        "tgn:7001819",
        "tgn:1000004",
        "tgn:7000198",
        "tgn:7029392"
    ],
    "tgn:id":7557802,
    "tgn:name:en":"Poshing La",
    "tgn:placetype":[
        "aat:300259572"
    ]
},
  "bbox": [],
  "geometry": {"coordinates":[92.366667,27.533333],"type":"Point"}
}