{
  "id": 2733451,
  "type": "Feature",
  "properties": {
    "tgn:hierarchy":[
        "tgn:2733451",
        "tgn:1000001",
        "tgn:7012149",
        "tgn:7007919",
        "tgn:7029392"
    ],
    "tgn:id":2733451,
    "tgn:name":"Turkeycock Mountain",
    "tgn:placetype":[
        "aat:300008798"
    ]
},
  "bbox": [],
  "geometry": {"coordinates":[-79.6833,36.8167],"type":"Point"}
}