{
  "id": 7193538,
  "type": "Feature",
  "properties": {
    "tgn:hierarchy":[
        "tgn:7193538",
        "tgn:7003669",
        "tgn:1000003",
        "tgn:7000084",
        "tgn:7029392"
    ],
    "tgn:id":7193538,
    "tgn:name":"Frankfurt",
    "tgn:placetype":[
        "aat:300008347"
    ]
},
  "bbox": [],
  "geometry": {"coordinates":[10.533333,49.683333],"type":"Point"}
}