{
  "id": 7102007,
  "type": "Feature",
  "properties": {
    "tgn:hierarchy":[
        "tgn:7102007",
        "tgn:1000003",
        "tgn:7003689",
        "tgn:7000084",
        "tgn:7029392"
    ],
    "tgn:id":7102007,
    "tgn:name":"Oberf\u00f6rsterei Rothenburg",
    "tgn:placetype":[
        "aat:300004792"
    ]
},
  "bbox": [],
  "geometry": {"coordinates":[11.05,51.416667],"type":"Point"}
}