{
  "id": 7258700,
  "type": "Feature",
  "properties": {
    "tgn:hierarchy":[
        "tgn:7258700",
        "tgn:7003616",
        "tgn:1000003",
        "tgn:7016845",
        "tgn:7029392"
    ],
    "tgn:id":7258700,
    "tgn:name:nl":"Alpherveld",
    "tgn:placetype":[
        "aat:300387200"
    ]
},
  "bbox": [],
  "geometry": {"coordinates":[6.116667,53.05],"type":"Point"}
}