{
  "id": 7394861,
  "type": "Feature",
  "properties": {
    "tgn:hierarchy":[
        "tgn:7394861",
        "tgn:1000001",
        "tgn:7005594",
        "tgn:7005560",
        "tgn:7029392"
    ],
    "tgn:id":7394861,
    "tgn:name":"San Jos\u00e9 de Ipoa",
    "tgn:placetype":[
        "aat:300008347"
    ]
},
  "bbox": [],
  "geometry": {"coordinates":[-100.65,23.466667],"type":"Point"}
}