{
  "id": 1072949,
  "type": "Feature",
  "properties": {
    "tgn:hierarchy":[
        "tgn:1072949",
        "tgn:1000004",
        "tgn:7002077",
        "tgn:1000111",
        "tgn:7029392"
    ],
    "tgn:id":1072949,
    "tgn:name":"Xicicun",
    "tgn:placetype":[
        "aat:300008347"
    ]
},
  "bbox": [],
  "geometry": {"coordinates":[116.1333,39.4833],"type":"Point"}
}