{
  "id": 2311867,
  "type": "Feature",
  "properties": {
    "tgn:hierarchy":[
        "tgn:2311867",
        "tgn:7006450",
        "tgn:2000069",
        "tgn:1000001",
        "tgn:7012149",
        "tgn:7029392"
    ],
    "tgn:id":2311867,
    "tgn:name":"Eenayarak River",
    "tgn:placetype":[
        "aat:300008707"
    ]
},
  "bbox": [],
  "geometry": {"coordinates":[-161.7833,60.4667],"type":"Point"}
}