{
  "id": 2281465,
  "type": "Feature",
  "properties": {
    "tgn:hierarchy":[
        "tgn:2281465",
        "tgn:1000001",
        "tgn:7006451",
        "tgn:7012149",
        "tgn:2000098",
        "tgn:7029392"
    ],
    "tgn:id":2281465,
    "tgn:name":"Deer Canyon",
    "tgn:placetype":[
        "aat:300008761"
    ]
},
  "bbox": [],
  "geometry": {"coordinates":[-114.1333,34.55],"type":"Point"}
}