{
  "id": 2366234,
  "type": "Feature",
  "properties": {
    "tgn:hierarchy":[
        "tgn:2366234",
        "tgn:1000001",
        "tgn:7012149",
        "tgn:2001711",
        "tgn:7007708",
        "tgn:7029392"
    ],
    "tgn:id":2366234,
    "tgn:name":"Griffin Creek",
    "tgn:placetype":[
        "aat:300008706"
    ]
},
  "bbox": [],
  "geometry": {"coordinates":[-122.8833,42.2167],"type":"Point"}
}