<<<<<<< HEAD
{
  "id": 2337238,
  "type": "Feature",
  "properties": {
    "tgn:hierarchy":[
        "tgn:2337238",
        "tgn:1000001",
        "tgn:2001013",
        "tgn:7012149",
        "tgn:7007521",
        "tgn:7029392"
    ],
    "tgn:id":2337238,
    "tgn:name":"Fourth Lake",
    "tgn:placetype":[
        "aat:300008680"
    ]
},
  "bbox": [],
  "geometry": {"coordinates":[-95.3167,47.8167],"type":"Point"}
}
=======
{"geometry":{"type":"Point","coordinates":[-95.316700,47.816700]},"type":"Feature","properties":{"hierarchy":["tgn:2337238","tgn:1000001","tgn:2001013","tgn:7012149","tgn:7007521","tgn:7029392"],"placetype":["aat:300008680"],"id":2337238,"name:xx":"Fourth Lake"}}
>>>>>>> 03f74aca74312dbeaf24d7e61306dd6a786dc3d0
