<<<<<<< HEAD
{
  "id": 2409774,
  "type": "Feature",
  "properties": {
    "tgn:hierarchy":[
        "tgn:2409774",
        "tgn:1002648",
        "tgn:1000001",
        "tgn:1007799",
        "tgn:7012149",
        "tgn:7007249",
        "tgn:7029392"
    ],
    "tgn:id":2409774,
    "tgn:name":"Iliolono",
    "tgn:placetype":[
        "aat:300008798"
    ]
},
  "bbox": [],
  "geometry": {"coordinates":[-156.95,20.7833],"type":"Point"}
}
=======
{"geometry":{"type":"Point","coordinates":[-156.950000,20.783300]},"type":"Feature","properties":{"hierarchy":["tgn:2409774","tgn:1002648","tgn:1000001","tgn:1007799","tgn:7012149","tgn:7007249","tgn:7029392"],"placetype":["aat:300008798"],"id":2409774,"name:xx":"Iliolono"}}
>>>>>>> 03f74aca74312dbeaf24d7e61306dd6a786dc3d0
