{
  "id": 2770900,
  "type": "Feature",
  "properties": {
    "tgn:hierarchy":[
        "tgn:2770900",
        "tgn:1000001",
        "tgn:7012149",
        "tgn:2000410",
        "tgn:7007248",
        "tgn:7029392"
    ],
    "tgn:id":2770900,
    "tgn:name":"Wildcat Creek Cove",
    "tgn:placetype":[
        "aat:300132316"
    ]
},
  "bbox": [],
  "geometry": {"coordinates":[-83.5667,34.8167],"type":"Point"}
}