{
  "id": 2785093,
  "type": "Feature",
  "properties": {
    "tgn:hierarchy":[
        "tgn:2785093",
        "tgn:1000001",
        "tgn:7012149",
        "tgn:2002126",
        "tgn:7007827",
        "tgn:7029392"
    ],
    "tgn:id":2785093,
    "tgn:name":"Yellow Lake",
    "tgn:placetype":[
        "aat:300008680"
    ]
},
  "bbox": [],
  "geometry": {"coordinates":[-111.0833,40.45],"type":"Point"}
}