{
  "id": 2702369,
  "type": "Feature",
  "properties": {
    "tgn:hierarchy":[
        "tgn:2702369",
        "tgn:1000001",
        "tgn:2001418",
        "tgn:7012149",
        "tgn:7007526",
        "tgn:7029392"
    ],
    "tgn:id":2702369,
    "tgn:name":"Sullivan Mine",
    "tgn:placetype":[
        "aat:300000390"
    ]
},
  "bbox": [],
  "geometry": {"coordinates":[-117.9333,38.7667],"type":"Point"}
}