{
  "id": 2555779,
  "type": "Feature",
  "properties": {
    "tgn:hierarchy":[
        "tgn:2555779",
        "tgn:1002202",
        "tgn:1000001",
        "tgn:7012149",
        "tgn:7007711",
        "tgn:7029392"
    ],
    "tgn:id":2555779,
    "tgn:name":"Ohio Ledge",
    "tgn:placetype":[
        "aat:300132348"
    ]
},
  "bbox": [],
  "geometry": {"coordinates":[-71.3167,41.6667],"type":"Point"}
}