{
  "id": 7120702,
  "type": "Feature",
  "properties": {
    "tgn:hierarchy":[
        "tgn:7120702",
        "tgn:7003669",
        "tgn:1000003",
        "tgn:7000084",
        "tgn:7029392"
    ],
    "tgn:id":7120702,
    "tgn:name":"Platte",
    "tgn:placetype":[
        "aat:300008777"
    ]
},
  "bbox": [],
  "geometry": {"coordinates":[9.616667,49.966667],"type":"Point"}
}