{
  "id": 2237821,
  "type": "Feature",
  "properties": {
    "tgn:hierarchy":[
        "tgn:2237821",
        "tgn:1000001",
        "tgn:7012149",
        "tgn:1002954",
        "tgn:7007826",
        "tgn:7029392"
    ],
    "tgn:id":2237821,
    "tgn:name":"Chinquapin Ridge",
    "tgn:placetype":[
        "aat:300266640"
    ]
},
  "bbox": [],
  "geometry": {"coordinates":[-94.8667,31.2167],"type":"Point"}
}