{
  "id": 7226477,
  "type": "Feature",
  "properties": {
    "tgn:hierarchy":[
        "tgn:7226477",
        "tgn:7002739",
        "tgn:7017076",
        "tgn:1000003",
        "tgn:1000074",
        "tgn:7029392"
    ],
    "tgn:id":7226477,
    "tgn:name":"Solom\u00f3s",
    "tgn:placetype":[
        "aat:300008347"
    ]
},
  "bbox": [],
  "geometry": {"coordinates":[22.883333,37.883333],"type":"Point"}
}