{
  "id": 2541708,
  "type": "Feature",
  "properties": {
    "tgn:hierarchy":[
        "tgn:2541708",
        "tgn:1000001",
        "tgn:7012149",
        "tgn:7007157",
        "tgn:1002956",
        "tgn:7029392"
    ],
    "tgn:id":2541708,
    "tgn:name":"Ninemile Creek",
    "tgn:placetype":[
        "aat:300008706"
    ]
},
  "bbox": [],
  "geometry": {"coordinates":[-118.2333,36.1833],"type":"Point"}
}