{
  "id": 7495256,
  "type": "Feature",
  "properties": {
    "tgn:hierarchy":[
        "tgn:7495256",
        "tgn:7468018",
        "tgn:1000004",
        "tgn:1000141",
        "tgn:7029392"
    ],
    "tgn:id":7495256,
    "tgn:name":"Shikuaicuo",
    "tgn:placetype":[
        "aat:300008347"
    ]
},
  "bbox": [],
  "geometry": {"coordinates":[120.549873,23.447282],"type":"Point"}
}