{
  "id": 2665277,
  "type": "Feature",
  "properties": {
    "tgn:hierarchy":[
        "tgn:2665277",
        "tgn:1000001",
        "tgn:7012149",
        "tgn:2000277",
        "tgn:7007240",
        "tgn:7029392"
    ],
    "tgn:id":2665277,
    "tgn:name":"Sinclair Mine",
    "tgn:placetype":[
        "aat:300000390"
    ]
},
  "bbox": [],
  "geometry": {"coordinates":[-82.5833,29.4667],"type":"Point"}
}