{
  "id": 2427449,
  "type": "Feature",
  "properties": {
    "tgn:hierarchy":[
        "tgn:2427449",
        "tgn:1000001",
        "tgn:2000950",
        "tgn:7012149",
        "tgn:7007520",
        "tgn:7029392"
    ],
    "tgn:id":2427449,
    "tgn:name":"Jordan River",
    "tgn:placetype":[
        "aat:300008707"
    ]
},
  "bbox": [],
  "geometry": {"coordinates":[-85.5167,45.6667],"type":"Point"}
}