<<<<<<< HEAD
{
  "id": 7170988,
  "type": "Feature",
  "properties": {
    "tgn:hierarchy":[
        "tgn:7170988",
        "tgn:7003669",
        "tgn:1000003",
        "tgn:7000084",
        "tgn:7029392"
    ],
    "tgn:id":7170988,
    "tgn:name":"Hengst-Wald",
    "tgn:placetype":[
        "aat:300008863"
    ]
},
  "bbox": [],
  "geometry": {"coordinates":[10.966667,47.6],"type":"Point"}
}
=======
{"geometry":{"type":"Point","coordinates":[10.966667,47.600000]},"type":"Feature","properties":{"hierarchy":["tgn:7170988","tgn:7003669","tgn:1000003","tgn:7000084","tgn:7029392"],"placetype":["aat:300008863"],"id":7170988,"name:xx":"Hengst-Wald"}}
>>>>>>> 03f74aca74312dbeaf24d7e61306dd6a786dc3d0
