{
  "id": 1106802,
  "type": "Feature",
  "properties": {
    "tgn:hierarchy":[
        "tgn:1106802",
        "tgn:1000001",
        "tgn:7005591",
        "tgn:7005560",
        "tgn:7029392"
    ],
    "tgn:id":1106802,
    "tgn:name":"Tres Picos, Cerro",
    "tgn:placetype":[
        "aat:300008795"
    ]
},
  "bbox": [],
  "geometry": {"coordinates":[-96.480556,19.558333],"type":"Point"}
}