{
  "id": 2409547,
  "type": "Feature",
  "properties": {
    "tgn:hierarchy":[
        "tgn:2409547",
        "tgn:1000001",
        "tgn:7012149",
        "tgn:2001535",
        "tgn:7007709",
        "tgn:7029392"
    ],
    "tgn:id":2409547,
    "tgn:name":"Idol Park",
    "tgn:placetype":[
        "aat:300008347"
    ]
},
  "bbox": [],
  "geometry": {"coordinates":[-79.9667,36.3667],"type":"Point"}
}