{
  "id": 2757367,
  "type": "Feature",
  "properties": {
    "tgn:hierarchy":[
        "tgn:2757367",
        "tgn:1000001",
        "tgn:7012149",
        "tgn:2001706",
        "tgn:7007708",
        "tgn:7029392"
    ],
    "tgn:id":2757367,
    "tgn:name":"West Basin",
    "tgn:placetype":[
        "aat:300008678"
    ]
},
  "bbox": [],
  "geometry": {"coordinates":[-124.1667,43.6667],"type":"Point"}
}