<<<<<<< HEAD
{
  "id": 2401836,
  "type": "Feature",
  "properties": {
    "tgn:hierarchy":[
        "tgn:2401836",
        "tgn:1000001",
        "tgn:2001650",
        "tgn:7012149",
        "tgn:7007707",
        "tgn:7029392"
    ],
    "tgn:id":2401836,
    "tgn:name":"Horseshoe Lake",
    "tgn:placetype":[
        "aat:300008680"
    ]
},
  "bbox": [],
  "geometry": {"coordinates":[-99.3833,34.9],"type":"Point"}
}
=======
{"geometry":{"type":"Point","coordinates":[-99.383300,34.900000]},"type":"Feature","properties":{"hierarchy":["tgn:2401836","tgn:1000001","tgn:2001650","tgn:7012149","tgn:7007707","tgn:7029392"],"placetype":["aat:300008680"],"id":2401836,"name:xx":"Horseshoe Lake"}}
>>>>>>> 03f74aca74312dbeaf24d7e61306dd6a786dc3d0
