{
  "id": 2555091,
  "type": "Feature",
  "properties": {
    "tgn:hierarchy":[
        "tgn:2555091",
        "tgn:1000001",
        "tgn:2001786",
        "tgn:7012149",
        "tgn:7007713",
        "tgn:7029392"
    ],
    "tgn:id":2555091,
    "tgn:name":"Occidental Lode Mine",
    "tgn:placetype":[
        "aat:300000390"
    ]
},
  "bbox": [],
  "geometry": {"coordinates":[-103.7167,43.7667],"type":"Point"}
}