{
  "id": 2390415,
  "type": "Feature",
  "properties": {
    "tgn:hierarchy":[
        "tgn:2390415",
        "tgn:1000001",
        "tgn:7012149",
        "tgn:2002303",
        "tgn:7013961",
        "tgn:7029392"
    ],
    "tgn:id":2390415,
    "tgn:name":"Highland Lake",
    "tgn:placetype":[
        "aat:300006191"
    ]
},
  "bbox": [],
  "geometry": {"coordinates":[-81.6333,39.25],"type":"Point"}
}