{
  "id": 2376300,
  "type": "Feature",
  "properties": {
    "tgn:hierarchy":[
        "tgn:2376300",
        "tgn:1000001",
        "tgn:2002244",
        "tgn:7012149",
        "tgn:7007920",
        "tgn:7029392"
    ],
    "tgn:id":2376300,
    "tgn:name":"Harder Spring",
    "tgn:placetype":[
        "aat:300008697"
    ]
},
  "bbox": [],
  "geometry": {"coordinates":[-118.4833,46.65],"type":"Point"}
}