{
  "id": 7487143,
  "type": "Feature",
  "properties": {
    "tgn:hierarchy":[
        "tgn:7487143",
        "tgn:1000004",
        "tgn:7489179",
        "tgn:1000141",
        "tgn:7029392"
    ],
    "tgn:id":7487143,
    "tgn:name":"Baishijiao",
    "tgn:placetype":[
        "aat:300008347"
    ]
},
  "bbox": [],
  "geometry": {"coordinates":[121.784722,24.839722],"type":"Point"}
}