<<<<<<< HEAD
{
  "id": 7174819,
  "type": "Feature",
  "properties": {
    "tgn:hierarchy":[
        "tgn:7174819",
        "tgn:7000096",
        "tgn:1000003",
        "tgn:7000084",
        "tgn:7029392"
    ],
    "tgn:id":7174819,
    "tgn:name":"Gro\u00dfer Grumsinsee",
    "tgn:placetype":[
        "aat:300008680"
    ]
},
  "bbox": [],
  "geometry": {"coordinates":[13.833333,53.0],"type":"Point"}
}
=======
{"geometry":{"type":"Point","coordinates":[13.833333,53.000000]},"type":"Feature","properties":{"hierarchy":["tgn:7174819","tgn:7000096","tgn:1000003","tgn:7000084","tgn:7029392"],"placetype":["aat:300008680"],"id":7174819,"name:xx":"Gro\u00dfer Grumsinsee"}}
>>>>>>> 03f74aca74312dbeaf24d7e61306dd6a786dc3d0
