<<<<<<< HEAD
{
  "id": 2763140,
  "type": "Feature",
  "properties": {
    "tgn:hierarchy":[
        "tgn:2763140",
        "tgn:2002138",
        "tgn:1000001",
        "tgn:7012149",
        "tgn:7007919",
        "tgn:7029392"
    ],
    "tgn:id":2763140,
    "tgn:name":"Westvaco Number Two Flyash Lagoon",
    "tgn:placetype":[
        "aat:300006191"
    ]
},
  "bbox": [],
  "geometry": {"coordinates":[-80.0,37.8],"type":"Point"}
}
=======
{"geometry":{"type":"Point","coordinates":[-80.000000,37.800000]},"type":"Feature","properties":{"hierarchy":["tgn:2763140","tgn:2002138","tgn:1000001","tgn:7012149","tgn:7007919","tgn:7029392"],"placetype":["aat:300006191"],"id":2763140,"name:xx":"Westvaco Number Two Flyash Lagoon"}}
>>>>>>> 03f74aca74312dbeaf24d7e61306dd6a786dc3d0
