{
  "id": 2283791,
  "type": "Feature",
  "properties": {
    "tgn:hierarchy":[
        "tgn:2283791",
        "tgn:1000001",
        "tgn:7012149",
        "tgn:7007515",
        "tgn:7029392"
    ],
    "tgn:id":2283791,
    "tgn:name":"Denbow Heath",
    "tgn:placetype":[
        "aat:300008905"
    ]
},
  "bbox": [],
  "geometry": {"coordinates":[-68.05,44.7333],"type":"Point"}
}