{
  "id": 2042440,
  "type": "Feature",
  "properties": {
    "tgn:hierarchy":[
        "tgn:2042440",
        "tgn:1000001",
        "tgn:7020676",
        "tgn:7012149",
        "tgn:7007256",
        "tgn:7029392"
    ],
    "tgn:id":2042440,
    "tgn:name":"Cameron",
    "tgn:placetype":[
        "aat:300008347"
    ]
},
  "bbox": [],
  "geometry": {"coordinates":[-93.3167,29.7833],"type":"Point"}
}