<<<<<<< HEAD
{
  "id": 2767491,
  "type": "Feature",
  "properties": {
    "tgn:hierarchy":[
        "tgn:2767491",
        "tgn:1000001",
        "tgn:7006451",
        "tgn:7012149",
        "tgn:2000099",
        "tgn:7029392"
    ],
    "tgn:id":2767491,
    "tgn:name":"White Tank",
    "tgn:placetype":[
        "aat:300006191"
    ]
},
  "bbox": [],
  "geometry": {"coordinates":[-110.35,34.7167],"type":"Point"}
}
=======
{"geometry":{"type":"Point","coordinates":[-110.350000,34.716700]},"type":"Feature","properties":{"hierarchy":["tgn:2767491","tgn:1000001","tgn:7006451","tgn:7012149","tgn:2000099","tgn:7029392"],"placetype":["aat:300006191"],"id":2767491,"name:xx":"White Tank"}}
>>>>>>> 03f74aca74312dbeaf24d7e61306dd6a786dc3d0
