{
  "id": 1081003,
  "type": "Feature",
  "properties": {
    "tgn:hierarchy":[
        "tgn:1081003",
        "tgn:1000004",
        "tgn:1000962",
        "tgn:7000896",
        "tgn:1000120",
        "tgn:7029392"
    ],
    "tgn:id":1081003,
    "tgn:name":"Neyagawa",
    "tgn:placetype":[
        "aat:300008347",
        "aat:300008389"
    ]
},
  "bbox": [],
  "geometry": {"coordinates":[135.6333,34.75],"type":"Point"}
}