<<<<<<< HEAD
{
  "id": 2406378,
  "type": "Feature",
  "properties": {
    "tgn:hierarchy":[
        "tgn:2406378",
        "tgn:1000001",
        "tgn:7012149",
        "tgn:2001290",
        "tgn:7007524",
        "tgn:7029392"
    ],
    "tgn:id":2406378,
    "tgn:name":"Hungary Gulch",
    "tgn:placetype":[
        "aat:300008761"
    ]
},
  "bbox": [],
  "geometry": {"coordinates":[-114.9833,47.0667],"type":"Point"}
}
=======
{"geometry":{"type":"Point","coordinates":[-114.983300,47.066700]},"type":"Feature","properties":{"hierarchy":["tgn:2406378","tgn:1000001","tgn:7012149","tgn:2001290","tgn:7007524","tgn:7029392"],"placetype":["aat:300008761"],"id":2406378,"name:xx":"Hungary Gulch"}}
>>>>>>> 03f74aca74312dbeaf24d7e61306dd6a786dc3d0
