{
  "id": 7250249,
  "type": "Feature",
  "properties": {
    "tgn:hierarchy":[
        "tgn:7250249",
        "tgn:7003457",
        "tgn:1000003",
        "tgn:1000063",
        "tgn:7018236",
        "tgn:7029392"
    ],
    "tgn:id":7250249,
    "tgn:name":"Moulin, Ruisseau du",
    "tgn:placetype":[
        "aat:300008699"
    ]
},
  "bbox": [],
  "geometry": {"coordinates":[3.65,50.916667],"type":"Point"}
}