{
  "id": 2350515,
  "type": "Feature",
  "properties": {
    "tgn:hierarchy":[
        "tgn:2350515",
        "tgn:1000001",
        "tgn:7012149",
        "tgn:7007826",
        "tgn:7029392"
    ],
    "tgn:id":2350515,
    "tgn:name":"Givens Creek",
    "tgn:placetype":[
        "aat:300008706"
    ]
},
  "bbox": [],
  "geometry": {"coordinates":[-99.1667,33.05],"type":"Point"}
}