<<<<<<< HEAD
{
  "id": 7372441,
  "type": "Feature",
  "properties": {
    "tgn:hierarchy":[
        "tgn:7372441",
        "tgn:1000001",
        "tgn:7005593",
        "tgn:7005560",
        "tgn:7029392"
    ],
    "tgn:id":7372441,
    "tgn:name":"La Estacada",
    "tgn:placetype":[
        "aat:300008347"
    ]
},
  "bbox": [],
  "geometry": {"coordinates":[-100.416667,20.816667],"type":"Point"}
}
=======
{"geometry":{"type":"Point","coordinates":[-100.416667,20.816667]},"type":"Feature","properties":{"hierarchy":["tgn:7372441","tgn:1000001","tgn:7005593","tgn:7005560","tgn:7029392"],"placetype":["aat:300008347"],"id":7372441,"name:xx":"La Estacada"}}
>>>>>>> 03f74aca74312dbeaf24d7e61306dd6a786dc3d0
