{
  "id": 7104222,
  "type": "Feature",
  "properties": {
    "tgn:hierarchy":[
        "tgn:7104222",
        "tgn:1000003",
        "tgn:7003688",
        "tgn:7000084",
        "tgn:7029392"
    ],
    "tgn:id":7104222,
    "tgn:name":"Schnurrum",
    "tgn:placetype":[
        "aat:300000206"
    ]
},
  "bbox": [],
  "geometry": {"coordinates":[9.833333,54.666667],"type":"Point"}
}