{
  "id": 2752029,
  "type": "Feature",
  "properties": {
    "tgn:hierarchy":[
        "tgn:2752029",
        "tgn:1000001",
        "tgn:7012149",
        "tgn:2001288",
        "tgn:7007524",
        "tgn:7029392"
    ],
    "tgn:id":2752029,
    "tgn:name":"Warwhoop Springs",
    "tgn:placetype":[
        "aat:300008697"
    ]
},
  "bbox": [],
  "geometry": {"coordinates":[-112.1833,45.25],"type":"Point"}
}