{
  "id": 7097013,
  "type": "Feature",
  "properties": {
    "tgn:hierarchy":[
        "tgn:7097013",
        "tgn:1000003",
        "tgn:7000094",
        "tgn:7000084",
        "tgn:7029392"
    ],
    "tgn:id":7097013,
    "tgn:name":"Spantekower Forst",
    "tgn:placetype":[
        "aat:300008863"
    ]
},
  "bbox": [],
  "geometry": {"coordinates":[13.566667,53.75],"type":"Point"}
}