{
  "id": 2601839,
  "type": "Feature",
  "properties": {
    "tgn:hierarchy":[
        "tgn:2601839",
        "tgn:1002648",
        "tgn:1000001",
        "tgn:7019158",
        "tgn:7012149",
        "tgn:7007249",
        "tgn:7029392"
    ],
    "tgn:id":2601839,
    "tgn:name":"Puu Kahala",
    "tgn:placetype":[
        "aat:300008798"
    ]
},
  "bbox": [],
  "geometry": {"coordinates":[-156.3833,20.7667],"type":"Point"}
}