{
  "id": 7534707,
  "type": "Feature",
  "properties": {
    "tgn:hierarchy":[
        "tgn:7534707",
        "tgn:7001242",
        "tgn:7016833",
        "tgn:1001418",
        "tgn:7029392"
    ],
    "tgn:id":7534707,
    "tgn:name:en":"\u1e24imeim, Deir el",
    "tgn:placetype":[
        "aat:300386860"
    ]
},
  "bbox": [],
  "geometry": {"coordinates":[26.964622,30.503281],"type":"Point"}
}