{
  "id": 2785492,
  "type": "Feature",
  "properties": {
    "tgn:hierarchy":[
        "tgn:2785492",
        "tgn:1000001",
        "tgn:7012149",
        "tgn:2000886",
        "tgn:7007256",
        "tgn:7029392"
    ],
    "tgn:id":2785492,
    "tgn:name":"Yerger Lake",
    "tgn:placetype":[
        "aat:300008680"
    ]
},
  "bbox": [],
  "geometry": {"coordinates":[-91.05,32.3167],"type":"Point"}
}