{
  "id": 2421444,
  "type": "Feature",
  "properties": {
    "tgn:hierarchy":[
        "tgn:2421444",
        "tgn:1000001",
        "tgn:7012149",
        "tgn:2001492",
        "tgn:7007709",
        "tgn:7029392"
    ],
    "tgn:id":2421444,
    "tgn:name":"Jesse Cole Lake",
    "tgn:placetype":[
        "aat:300006191"
    ]
},
  "bbox": [],
  "geometry": {"coordinates":[-78.9667,36.0333],"type":"Point"}
}