{
  "id": 2180510,
  "type": "Feature",
  "properties": {
    "tgn:hierarchy":[
        "tgn:2180510",
        "tgn:1000001",
        "tgn:7012149",
        "tgn:2000903",
        "tgn:7007256",
        "tgn:7029392"
    ],
    "tgn:id":2180510,
    "tgn:name":"Bloody Bayou",
    "tgn:placetype":[
        "aat:300008699"
    ]
},
  "bbox": [],
  "geometry": {"coordinates":[-91.4833,30.1333],"type":"Point"}
}