{
  "id": 7537353,
  "type": "Feature",
  "properties": {
    "tgn:hierarchy":[
        "tgn:7537353",
        "tgn:7001242",
        "tgn:7016833",
        "tgn:1001123",
        "tgn:7029392"
    ],
    "tgn:id":7537353,
    "tgn:name":"Qu\u0163aysh, Ba\u1e29r al",
    "tgn:placetype":[
        "aat:300008713"
    ]
},
  "bbox": [],
  "geometry": {"coordinates":[32.009722,31.078611],"type":"Point"}
}