{
  "id": 2710031,
  "type": "Feature",
  "properties": {
    "tgn:hierarchy":[
        "tgn:2710031",
        "tgn:1000001",
        "tgn:2002132",
        "tgn:7012149",
        "tgn:7007828",
        "tgn:7029392"
    ],
    "tgn:id":2710031,
    "tgn:name":"Talbot Hollow",
    "tgn:placetype":[
        "aat:300008761"
    ]
},
  "bbox": [],
  "geometry": {"coordinates":[-72.8333,44.45],"type":"Point"}
}