{
  "id": 2306284,
  "type": "Feature",
  "properties": {
    "tgn:hierarchy":[
        "tgn:2306284",
        "tgn:1000001",
        "tgn:7012149",
        "tgn:2001297",
        "tgn:7007524",
        "tgn:7029392"
    ],
    "tgn:id":2306284,
    "tgn:name":"East Fork Buttes",
    "tgn:placetype":[
        "aat:300008798"
    ]
},
  "bbox": [],
  "geometry": {"coordinates":[-105.1833,45.35],"type":"Point"}
}