{
  "id": 2462232,
  "type": "Feature",
  "properties": {
    "tgn:hierarchy":[
        "tgn:2462232",
        "tgn:1000001",
        "tgn:7012149",
        "tgn:2000553",
        "tgn:7007252",
        "tgn:7029392"
    ],
    "tgn:id":2462232,
    "tgn:name":"Little Walnut Creek",
    "tgn:placetype":[
        "aat:300008706"
    ]
},
  "bbox": [],
  "geometry": {"coordinates":[-86.9833,39.7333],"type":"Point"}
}