{
  "id": 7538080,
  "type": "Feature",
  "properties": {
    "tgn:hierarchy":[
        "tgn:7538080",
        "tgn:7001242",
        "tgn:7016833",
        "tgn:1001418",
        "tgn:7029392"
    ],
    "tgn:id":7538080,
    "tgn:name:en":"Sanyet R\u00e2s el Husan",
    "tgn:placetype":[
        "aat:300006207"
    ]
},
  "bbox": [],
  "geometry": {"coordinates":[28.247262,30.923714],"type":"Point"}
}