{
  "id": 1077139,
  "type": "Feature",
  "properties": {
    "tgn:hierarchy":[
        "tgn:1077139",
        "tgn:1000004",
        "tgn:7000198",
        "tgn:7031786",
        "tgn:7029392"
    ],
    "tgn:id":1077139,
    "tgn:name:en":"Tehri",
    "tgn:placetype":[
        "aat:300008347"
    ]
},
  "bbox": [],
  "geometry": {"coordinates":[78.480299,30.390863],"type":"Point"}
}