{
  "id": 2639534,
  "type": "Feature",
  "properties": {
    "tgn:hierarchy":[
        "tgn:2639534",
        "tgn:1000001",
        "tgn:7012149",
        "tgn:2001892",
        "tgn:7007825",
        "tgn:7029392"
    ],
    "tgn:id":2639534,
    "tgn:name":"Saltpeter Cave Hollow",
    "tgn:placetype":[
        "aat:300008761"
    ]
},
  "bbox": [],
  "geometry": {"coordinates":[-86.1167,36.55],"type":"Point"}
}