<<<<<<< HEAD
{
  "id": 2762863,
  "type": "Feature",
  "properties": {
    "tgn:hierarchy":[
        "tgn:2762863",
        "tgn:1000001",
        "tgn:2000862",
        "tgn:7012149",
        "tgn:7007256",
        "tgn:7029392"
    ],
    "tgn:id":2762863,
    "tgn:name":"Westfield Point",
    "tgn:placetype":[
        "aat:300008850"
    ]
},
  "bbox": [],
  "geometry": {"coordinates":[-94.0167,32.7167],"type":"Point"}
}
=======
{"geometry":{"type":"Point","coordinates":[-94.016700,32.716700]},"type":"Feature","properties":{"hierarchy":["tgn:2762863","tgn:1000001","tgn:2000862","tgn:7012149","tgn:7007256","tgn:7029392"],"placetype":["aat:300008850"],"id":2762863,"name:xx":"Westfield Point"}}
>>>>>>> 03f74aca74312dbeaf24d7e61306dd6a786dc3d0
