{
  "id": 7020549,
  "type": "Feature",
  "properties": {
    "tgn:hierarchy":[
        "tgn:7020549",
        "tgn:1000001",
        "tgn:7012149",
        "tgn:2001284",
        "tgn:7007524",
        "tgn:7029392"
    ],
    "tgn:id":7020549,
    "tgn:name":"Monte Cristo Mine",
    "tgn:placetype":[
        "aat:300000390"
    ]
},
  "bbox": [],
  "geometry": {"coordinates":[-112.25,46.45],"type":"Point"}
}