{
  "id": 7496187,
  "type": "Feature",
  "properties": {
    "tgn:hierarchy":[
        "tgn:7496187",
        "tgn:7487020",
        "tgn:1000004",
        "tgn:1000141",
        "tgn:7029392"
    ],
    "tgn:id":7496187,
    "tgn:name":"Disanhao Suidao",
    "tgn:placetype":[
        "aat:300007899"
    ]
},
  "bbox": [],
  "geometry": {"coordinates":[120.769259,24.352185],"type":"Point"}
}