{
  "id": 2132384,
  "type": "Feature",
  "properties": {
    "tgn:hierarchy":[
        "tgn:2132384",
        "tgn:1000001",
        "tgn:7012149",
        "tgn:2001457",
        "tgn:7007566",
        "tgn:7029392"
    ],
    "tgn:id":2132384,
    "tgn:name":"Amole Canyon",
    "tgn:placetype":[
        "aat:300008761"
    ]
},
  "bbox": [],
  "geometry": {"coordinates":[-105.5667,36.1833],"type":"Point"}
}