{
  "id": 2158833,
  "type": "Feature",
  "properties": {
    "tgn:hierarchy":[
        "tgn:2158833",
        "tgn:1000001",
        "tgn:7012149",
        "tgn:1002423",
        "tgn:7007568",
        "tgn:7029392"
    ],
    "tgn:id":2158833,
    "tgn:name":"Becker Hollow",
    "tgn:placetype":[
        "aat:300008761"
    ]
},
  "bbox": [],
  "geometry": {"coordinates":[-74.2167,42.1667],"type":"Point"}
}