{
  "id": 1022810,
  "type": "Feature",
  "properties": {
    "tgn:hierarchy":[
        "tgn:1022810",
        "tgn:7006247",
        "tgn:1000047",
        "tgn:7002456",
        "tgn:1000002",
        "tgn:7029392"
    ],
    "tgn:id":1022810,
    "tgn:name":"S\u00e3o Jo\u00e3o de Pirabas",
    "tgn:placetype":[
        "aat:300008347"
    ]
},
  "bbox": [],
  "geometry": {"coordinates":[-47.1667,-0.7667],"type":"Point"}
}