<<<<<<< HEAD
{
  "id": 7114508,
  "type": "Feature",
  "properties": {
    "tgn:hierarchy":[
        "tgn:7114508",
        "tgn:1000003",
        "tgn:7003676",
        "tgn:7000084",
        "tgn:7029392"
    ],
    "tgn:id":7114508,
    "tgn:name":"Roloven",
    "tgn:placetype":[
        "aat:300008347"
    ]
},
  "bbox": [],
  "geometry": {"coordinates":[9.666667,52.3],"type":"Point"}
}
=======
{"geometry":{"type":"Point","coordinates":[9.666667,52.300000]},"type":"Feature","properties":{"hierarchy":["tgn:7114508","tgn:1000003","tgn:7003676","tgn:7000084","tgn:7029392"],"placetype":["aat:300008347"],"id":7114508,"name:xx":"Roloven"}}
>>>>>>> 03f74aca74312dbeaf24d7e61306dd6a786dc3d0
