{
  "id": 2598066,
  "type": "Feature",
  "properties": {
    "tgn:hierarchy":[
        "tgn:2598066",
        "tgn:1000001",
        "tgn:7016172",
        "tgn:7012149",
        "tgn:2000168",
        "tgn:7029392"
    ],
    "tgn:id":2598066,
    "tgn:name":"Presley Branch",
    "tgn:placetype":[
        "aat:300008699"
    ]
},
  "bbox": [],
  "geometry": {"coordinates":[-94.15,34.95],"type":"Point"}
}