{
  "id": 2323335,
  "type": "Feature",
  "properties": {
    "tgn:hierarchy":[
        "tgn:2323335",
        "tgn:1000001",
        "tgn:7012149",
        "tgn:7007158",
        "tgn:7029392"
    ],
    "tgn:id":2323335,
    "tgn:name":"Farmers Highline Ditch",
    "tgn:placetype":[
        "aat:300006075"
    ]
},
  "bbox": [],
  "geometry": {"coordinates":[-105.15,39.8333],"type":"Point"}
}