{
  "id": 2446928,
  "type": "Feature",
  "properties": {
    "tgn:hierarchy":[
        "tgn:2446928",
        "tgn:1000001",
        "tgn:2001429",
        "tgn:7012149",
        "tgn:7007566",
        "tgn:7029392"
    ],
    "tgn:id":2446928,
    "tgn:name":"Liberty Bell Number One Claim",
    "tgn:placetype":[
        "aat:300000390"
    ]
},
  "bbox": [],
  "geometry": {"coordinates":[-108.8333,33.2833],"type":"Point"}
}