{
  "id": 2298049,
  "type": "Feature",
  "properties": {
    "tgn:hierarchy":[
        "tgn:2298049",
        "tgn:1000001",
        "tgn:7012149",
        "tgn:2001312",
        "tgn:7007524",
        "tgn:7029392"
    ],
    "tgn:id":2298049,
    "tgn:name":"Dry Lake",
    "tgn:placetype":[
        "aat:300008680"
    ]
},
  "bbox": [],
  "geometry": {"coordinates":[-106.6167,48.0833],"type":"Point"}
}