<<<<<<< HEAD
{
  "id": 2765055,
  "type": "Feature",
  "properties": {
    "tgn:hierarchy":[
        "tgn:2765055",
        "tgn:1000001",
        "tgn:7012149",
        "tgn:7013855",
        "tgn:7007251",
        "tgn:7029392"
    ],
    "tgn:id":2765055,
    "tgn:name":"Whisky Point",
    "tgn:placetype":[
        "aat:300008850"
    ]
},
  "bbox": [],
  "geometry": {"coordinates":[-88.15,42.4333],"type":"Point"}
}
=======
{"geometry":{"type":"Point","coordinates":[-88.150000,42.433300]},"type":"Feature","properties":{"hierarchy":["tgn:2765055","tgn:1000001","tgn:7012149","tgn:7013855","tgn:7007251","tgn:7029392"],"placetype":["aat:300008850"],"id":2765055,"name:xx":"Whisky Point"}}
>>>>>>> 03f74aca74312dbeaf24d7e61306dd6a786dc3d0
