{
  "id": 7475011,
  "type": "Feature",
  "properties": {
    "tgn:hierarchy":[
        "tgn:7475011",
        "tgn:1000004",
        "tgn:1000454",
        "tgn:1000141",
        "tgn:7029392"
    ],
    "tgn:id":7475011,
    "tgn:name":"Zhongbajia Qiao",
    "tgn:placetype":[
        "aat:300007836"
    ]
},
  "bbox": [],
  "geometry": {"coordinates":[121.520028,25.275798],"type":"Point"}
}