<<<<<<< HEAD
{
  "id": 7475011,
  "type": "Feature",
  "properties": {
    "tgn:hierarchy":[
        "tgn:7475011",
        "tgn:1000004",
        "tgn:1000454",
        "tgn:1000141",
        "tgn:7029392"
    ],
    "tgn:id":7475011,
    "tgn:name":"Zhongbajia Qiao",
    "tgn:placetype":[
        "aat:300007836"
    ]
},
  "bbox": [],
  "geometry": {"coordinates":[121.520028,25.275798],"type":"Point"}
}
=======
{"geometry":{"type":"Point","coordinates":[121.520028,25.275798]},"type":"Feature","properties":{"hierarchy":["tgn:7475011","tgn:1000004","tgn:1000454","tgn:1000141","tgn:7029392"],"placetype":["aat:300007836"],"id":7475011,"name:xx":"Zhongbajia Qiao"}}
>>>>>>> 03f74aca74312dbeaf24d7e61306dd6a786dc3d0
