{
  "id": 7321871,
  "type": "Feature",
  "properties": {
    "tgn:hierarchy":[
        "tgn:7321871",
        "tgn:7016598",
        "tgn:1000049",
        "tgn:1000002",
        "tgn:7029392"
    ],
    "tgn:id":7321871,
    "tgn:name":"Aucla",
    "tgn:placetype":[
        "aat:300387033"
    ]
},
  "bbox": [],
  "geometry": {"coordinates":[-69.916667,-23.133333],"type":"Point"}
}