<<<<<<< HEAD
{
  "id": 7177370,
  "type": "Feature",
  "properties": {
    "tgn:hierarchy":[
        "tgn:7177370",
        "tgn:1000003",
        "tgn:7003677",
        "tgn:7000084",
        "tgn:7029392"
    ],
    "tgn:id":7177370,
    "tgn:name":"Halbig",
    "tgn:placetype":[
        "aat:300008863"
    ]
},
  "bbox": [],
  "geometry": {"coordinates":[6.583333,50.5],"type":"Point"}
}
=======
{"geometry":{"type":"Point","coordinates":[6.583333,50.500000]},"type":"Feature","properties":{"hierarchy":["tgn:7177370","tgn:1000003","tgn:7003677","tgn:7000084","tgn:7029392"],"placetype":["aat:300008863"],"id":7177370,"name:xx":"Halbig"}}
>>>>>>> 03f74aca74312dbeaf24d7e61306dd6a786dc3d0
