{
  "id": 7140588,
  "type": "Feature",
  "properties": {
    "tgn:hierarchy":[
        "tgn:7140588",
        "tgn:7003669",
        "tgn:1000003",
        "tgn:7000084",
        "tgn:7029392"
    ],
    "tgn:id":7140588,
    "tgn:name":"Mangasser",
    "tgn:placetype":[
        "aat:300000206"
    ]
},
  "bbox": [],
  "geometry": {"coordinates":[12.85,48.283333],"type":"Point"}
}