{
  "id": 7023387,
  "type": "Feature",
  "properties": {
    "tgn:hierarchy":[
        "tgn:7023387",
        "tgn:1000001",
        "tgn:7012149",
        "tgn:7029392"
    ],
    "tgn:id":7023387,
    "tgn:name":"McCallie Lake",
    "tgn:placetype":[
        "aat:300008680"
    ]
},
  "bbox": [],
  "geometry": {"coordinates":[-85.25,35.0167],"type":"Point"}
}