{
  "id": 2383883,
  "type": "Feature",
  "properties": {
    "tgn:hierarchy":[
        "tgn:2383883",
        "tgn:1000001",
        "tgn:7012149",
        "tgn:7007710",
        "tgn:7029392"
    ],
    "tgn:id":2383883,
    "tgn:name":"Hedgehog Hollow",
    "tgn:placetype":[
        "aat:300008761"
    ]
},
  "bbox": [],
  "geometry": {"coordinates":[-77.5833,41.6333],"type":"Point"}
}