<<<<<<< HEAD
{
  "id": 2336561,
  "type": "Feature",
  "properties": {
    "tgn:hierarchy":[
        "tgn:2336561",
        "tgn:1000001",
        "tgn:7012149",
        "tgn:2000975",
        "tgn:7007520",
        "tgn:7029392"
    ],
    "tgn:id":2336561,
    "tgn:name":"Four Island Lake",
    "tgn:placetype":[
        "aat:300008680"
    ]
},
  "bbox": [],
  "geometry": {"coordinates":[-88.05,46.6333],"type":"Point"}
}
=======
{"geometry":{"type":"Point","coordinates":[-88.050000,46.633300]},"type":"Feature","properties":{"hierarchy":["tgn:2336561","tgn:1000001","tgn:7012149","tgn:2000975","tgn:7007520","tgn:7029392"],"placetype":["aat:300008680"],"id":2336561,"name:xx":"Four Island Lake"}}
>>>>>>> 03f74aca74312dbeaf24d7e61306dd6a786dc3d0
