{
  "id": 2336561,
  "type": "Feature",
  "properties": {
    "tgn:hierarchy":[
        "tgn:2336561",
        "tgn:1000001",
        "tgn:7012149",
        "tgn:2000975",
        "tgn:7007520",
        "tgn:7029392"
    ],
    "tgn:id":2336561,
    "tgn:name":"Four Island Lake",
    "tgn:placetype":[
        "aat:300008680"
    ]
},
  "bbox": [],
  "geometry": {"coordinates":[-88.05,46.6333],"type":"Point"}
}