{
  "id": 7320798,
  "type": "Feature",
  "properties": {
    "tgn:hierarchy":[
        "tgn:7320798",
        "tgn:1001702",
        "tgn:1000049",
        "tgn:1000002",
        "tgn:7029392"
    ],
    "tgn:id":7320798,
    "tgn:name":"Button, Isla",
    "tgn:placetype":[
        "aat:300008791"
    ]
},
  "bbox": [],
  "geometry": {"coordinates":[-68.25,-55.016667],"type":"Point"}
}