{
  "id": 7223407,
  "type": "Feature",
  "properties": {
    "tgn:hierarchy":[
        "tgn:7223407",
        "tgn:7011270",
        "tgn:7002674",
        "tgn:1000003",
        "tgn:1000074",
        "tgn:7029392"
    ],
    "tgn:id":7223407,
    "tgn:name":"Plak\u00ed, Vrachonis\u00edda",
    "tgn:placetype":[
        "aat:300008791"
    ]
},
  "bbox": [],
  "geometry": {"coordinates":[25.622778,36.861944],"type":"Point"}
}