{
  "id": 2089732,
  "type": "Feature",
  "properties": {
    "tgn:hierarchy":[
        "tgn:2089732",
        "tgn:1000001",
        "tgn:1002266",
        "tgn:7012149",
        "tgn:7007710",
        "tgn:7029392"
    ],
    "tgn:id":2089732,
    "tgn:name":"Kenilworth",
    "tgn:placetype":[
        "aat:300008347"
    ]
},
  "bbox": [],
  "geometry": {"coordinates":[-75.6333,40.2167],"type":"Point"}
}