{
  "id": 2597598,
  "type": "Feature",
  "properties": {
    "tgn:hierarchy":[
        "tgn:2597598",
        "tgn:1000001",
        "tgn:7012149",
        "tgn:2000837",
        "tgn:7007255",
        "tgn:7029392"
    ],
    "tgn:id":2597598,
    "tgn:name":"Praise Fork",
    "tgn:placetype":[
        "aat:300008699"
    ]
},
  "bbox": [],
  "geometry": {"coordinates":[-82.3667,37.3167],"type":"Point"}
}