{
  "id": 1070172,
  "type": "Feature",
  "properties": {
    "tgn:hierarchy":[
        "tgn:1070172",
        "tgn:1000004",
        "tgn:7002077",
        "tgn:1000111",
        "tgn:7029392"
    ],
    "tgn:id":1070172,
    "tgn:name":"Lulong",
    "tgn:placetype":[
        "aat:300008347"
    ]
},
  "bbox": [],
  "geometry": {"coordinates":[118.8333,39.8667],"type":"Point"}
}