{
  "id": 2068057,
  "type": "Feature",
  "properties": {
    "tgn:hierarchy":[
        "tgn:2068057",
        "tgn:1000001",
        "tgn:7012149",
        "tgn:1002758",
        "tgn:7007568",
        "tgn:7029392"
    ],
    "tgn:id":2068057,
    "tgn:name":"Bernhards Bay",
    "tgn:placetype":[
        "aat:300008347"
    ]
},
  "bbox": [],
  "geometry": {"coordinates":[-75.9333,43.2333],"type":"Point"}
}