{
  "id": 2403274,
  "type": "Feature",
  "properties": {
    "tgn:hierarchy":[
        "tgn:2403274",
        "tgn:1000001",
        "tgn:2001430",
        "tgn:7012149",
        "tgn:7007566",
        "tgn:7029392"
    ],
    "tgn:id":2403274,
    "tgn:name":"House Tank",
    "tgn:placetype":[
        "aat:300006191"
    ]
},
  "bbox": [],
  "geometry": {"coordinates":[-104.05,33.5833],"type":"Point"}
}