{
  "id": 2681593,
  "type": "Feature",
  "properties": {
    "tgn:hierarchy":[
        "tgn:2681593",
        "tgn:2002365",
        "tgn:1000001",
        "tgn:7012149",
        "tgn:7007923",
        "tgn:7029392"
    ],
    "tgn:id":2681593,
    "tgn:name":"South Prong South Fork Little Medicine",
    "tgn:placetype":[
        "aat:300008699"
    ]
},
  "bbox": [],
  "geometry": {"coordinates":[-105.85,42.3833],"type":"Point"}
}