{
  "id": 2710472,
  "type": "Feature",
  "properties": {
    "tgn:hierarchy":[
        "tgn:2710472",
        "tgn:1000001",
        "tgn:1002284",
        "tgn:7012149",
        "tgn:7007568",
        "tgn:7029392"
    ],
    "tgn:id":2710472,
    "tgn:name":"Tamarack Hill",
    "tgn:placetype":[
        "aat:300008798"
    ]
},
  "bbox": [],
  "geometry": {"coordinates":[-73.6667,44.4833],"type":"Point"}
}