<<<<<<< HEAD
{
  "id": 7112814,
  "type": "Feature",
  "properties": {
    "tgn:hierarchy":[
        "tgn:7112814",
        "tgn:7003669",
        "tgn:1000003",
        "tgn:7000084",
        "tgn:7029392"
    ],
    "tgn:id":7112814,
    "tgn:name":"Reuth unter Neuhaus",
    "tgn:placetype":[
        "aat:300008347"
    ]
},
  "bbox": [],
  "geometry": {"coordinates":[11.133333,49.0],"type":"Point"}
}
=======
{"geometry":{"type":"Point","coordinates":[11.133333,49.000000]},"type":"Feature","properties":{"hierarchy":["tgn:7112814","tgn:7003669","tgn:1000003","tgn:7000084","tgn:7029392"],"placetype":["aat:300008347"],"id":7112814,"name:xx":"Reuth unter Neuhaus"}}
>>>>>>> 03f74aca74312dbeaf24d7e61306dd6a786dc3d0
