{
  "id": 2579106,
  "type": "Feature",
  "properties": {
    "tgn:hierarchy":[
        "tgn:2579106",
        "tgn:1000001",
        "tgn:1003028",
        "tgn:7012149",
        "tgn:7007159",
        "tgn:7029392"
    ],
    "tgn:id":2579106,
    "tgn:name":"Phoenixville Park Ponds",
    "tgn:placetype":[
        "aat:300008680"
    ]
},
  "bbox": [],
  "geometry": {"coordinates":[-72.0833,41.8833],"type":"Point"}
}