{
  "id": 7265689,
  "type": "Feature",
  "properties": {
    "tgn:hierarchy":[
        "tgn:7265689",
        "tgn:1000003",
        "tgn:7003632",
        "tgn:7016845",
        "tgn:7029392"
    ],
    "tgn:id":7265689,
    "tgn:name:nl":"Lakerveld, Polder",
    "tgn:placetype":[
        "aat:300006163"
    ]
},
  "bbox": [],
  "geometry": {"coordinates":[5.016667,51.933333],"type":"Point"}
}