<<<<<<< HEAD
{
  "id": 2766897,
  "type": "Feature",
  "properties": {
    "tgn:hierarchy":[
        "tgn:2766897",
        "tgn:1000001",
        "tgn:7012149",
        "tgn:2001720",
        "tgn:7007708",
        "tgn:7029392"
    ],
    "tgn:id":2766897,
    "tgn:name":"White Pine Trough Spring",
    "tgn:placetype":[
        "aat:300008697"
    ]
},
  "bbox": [],
  "geometry": {"coordinates":[-118.7167,45.0167],"type":"Point"}
}
=======
{"geometry":{"type":"Point","coordinates":[-118.716700,45.016700]},"type":"Feature","properties":{"hierarchy":["tgn:2766897","tgn:1000001","tgn:7012149","tgn:2001720","tgn:7007708","tgn:7029392"],"placetype":["aat:300008697"],"id":2766897,"name:xx":"White Pine Trough Spring"}}
>>>>>>> 03f74aca74312dbeaf24d7e61306dd6a786dc3d0
