{
  "id": 7484228,
  "type": "Feature",
  "properties": {
    "tgn:hierarchy":[
        "tgn:7484228",
        "tgn:7001004",
        "tgn:1000004",
        "tgn:1000141",
        "tgn:7029392"
    ],
    "tgn:id":7484228,
    "tgn:name":"Jiaxian Qiao",
    "tgn:placetype":[
        "aat:300007836"
    ]
},
  "bbox": [],
  "geometry": {"coordinates":[120.586111,23.080833],"type":"Point"}
}