<<<<<<< HEAD
{
  "id": 7484228,
  "type": "Feature",
  "properties": {
    "tgn:hierarchy":[
        "tgn:7484228",
        "tgn:7001004",
        "tgn:1000004",
        "tgn:1000141",
        "tgn:7029392"
    ],
    "tgn:id":7484228,
    "tgn:name":"Jiaxian Qiao",
    "tgn:placetype":[
        "aat:300007836"
    ]
},
  "bbox": [],
  "geometry": {"coordinates":[120.586111,23.080833],"type":"Point"}
}
=======
{"geometry":{"type":"Point","coordinates":[120.586111,23.080833]},"type":"Feature","properties":{"hierarchy":["tgn:7484228","tgn:7001004","tgn:1000004","tgn:1000141","tgn:7029392"],"placetype":["aat:300007836"],"id":7484228,"name:xx":"Jiaxian Qiao"}}
>>>>>>> 03f74aca74312dbeaf24d7e61306dd6a786dc3d0
