{
  "id": 7345569,
  "type": "Feature",
  "properties": {
    "tgn:hierarchy":[
        "tgn:7345569",
        "tgn:7001165",
        "tgn:1000003",
        "tgn:7002793",
        "tgn:1000095",
        "tgn:7029392"
    ],
    "tgn:id":7345569,
    "tgn:name":"Albuixech",
    "tgn:placetype":[
        "aat:300008347"
    ]
},
  "bbox": [],
  "geometry": {"coordinates":[-0.316667,39.55],"type":"Point"}
}