{
  "id": 7099647,
  "type": "Feature",
  "properties": {
    "tgn:hierarchy":[
        "tgn:7099647",
        "tgn:7003669",
        "tgn:1000003",
        "tgn:7000084",
        "tgn:7029392"
    ],
    "tgn:id":7099647,
    "tgn:name":"Seifriedsburg",
    "tgn:placetype":[
        "aat:300008347"
    ]
},
  "bbox": [],
  "geometry": {"coordinates":[9.75,50.066667],"type":"Point"}
}