{
  "id": 2613487,
  "type": "Feature",
  "properties": {
    "tgn:hierarchy":[
        "tgn:2613487",
        "tgn:1000001",
        "tgn:7012149",
        "tgn:2001723",
        "tgn:7007708",
        "tgn:7029392"
    ],
    "tgn:id":2613487,
    "tgn:name":"Reed Reservoir",
    "tgn:placetype":[
        "aat:300006191"
    ]
},
  "bbox": [],
  "geometry": {"coordinates":[-119.7833,44.3167],"type":"Point"}
}