{
  "id": 2030436,
  "type": "Feature",
  "properties": {
    "tgn:hierarchy":[
        "tgn:2030436",
        "tgn:1000001",
        "tgn:7012149",
        "tgn:2000521",
        "tgn:7007251",
        "tgn:7029392"
    ],
    "tgn:id":2030436,
    "tgn:name":"Trivoli",
    "tgn:placetype":[
        "aat:300008347"
    ]
},
  "bbox": [],
  "geometry": {"coordinates":[-89.8833,40.6833],"type":"Point"}
}