{
  "id": 7236759,
  "type": "Feature",
  "properties": {
    "tgn:hierarchy":[
        "tgn:7236759",
        "tgn:7002739",
        "tgn:7017076",
        "tgn:1000003",
        "tgn:1000074",
        "tgn:7029392"
    ],
    "tgn:id":7236759,
    "tgn:name":"\u00c1yios Khar\u00e1lambos",
    "tgn:placetype":[
        "aat:300008347"
    ]
},
  "bbox": [],
  "geometry": {"coordinates":[22.733333,37.35],"type":"Point"}
}