{
  "id": 7507204,
  "type": "Feature",
  "properties": {
    "tgn:hierarchy":[
        "tgn:7507204",
        "tgn:7520092",
        "tgn:1008380",
        "tgn:1000226",
        "tgn:1000006",
        "tgn:7029392"
    ],
    "tgn:id":7507204,
    "tgn:name:en":"Pungarehu",
    "tgn:placetype":[
        "aat:300008795"
    ]
},
  "bbox": [],
  "geometry": {"coordinates":[177.65,-38.216667],"type":"Point"}
}