{
  "id": 2270040,
  "type": "Feature",
  "properties": {
    "tgn:hierarchy":[
        "tgn:2270040",
        "tgn:1000001",
        "tgn:2001703",
        "tgn:7012149",
        "tgn:7007708",
        "tgn:7029392"
    ],
    "tgn:id":2270040,
    "tgn:name":"Crusher Creek",
    "tgn:placetype":[
        "aat:300008706"
    ]
},
  "bbox": [],
  "geometry": {"coordinates":[-120.3833,44.2667],"type":"Point"}
}