{
  "id": 7174285,
  "type": "Feature",
  "properties": {
    "tgn:hierarchy":[
        "tgn:7174285",
        "tgn:7003692",
        "tgn:1000003",
        "tgn:7000084",
        "tgn:7029392"
    ],
    "tgn:id":7174285,
    "tgn:name":"Gro\u00dfkuchen",
    "tgn:placetype":[
        "aat:300008347"
    ]
},
  "bbox": [],
  "geometry": {"coordinates":[10.233333,48.75],"type":"Point"}
}