{
  "id": 7004150,
  "type": "Feature",
  "properties": {
    "tgn:hierarchy":[
        "tgn:7004150",
        "tgn:1003455",
        "tgn:1000003",
        "tgn:7010380",
        "tgn:1000080",
        "tgn:7029392"
    ],
    "tgn:id":7004150,
    "tgn:name":"Lesina, Lago di",
    "tgn:placetype":[
        "aat:300008679"
    ]
},
  "bbox": [],
  "geometry": {"coordinates":[15.433333,41.883333],"type":"Point"}
}