{
  "id": 7008273,
  "type": "Feature",
  "properties": {
    "tgn:hierarchy":[
        "tgn:7008273",
        "tgn:1000003",
        "tgn:7002877",
        "tgn:1000070",
        "tgn:7029392"
    ],
    "tgn:id":7008273,
    "tgn:name":"Ch\u00e2teauroux",
    "tgn:placetype":[
        "aat:300008347",
        "aat:300387225",
        "aat:300008389",
        "aat:300387330",
        "aat:300387512",
        "aat:300387302"
    ]
},
  "bbox": [],
  "geometry": {"coordinates":[1.6833,46.8167],"type":"Point"}
}