{
  "id": 2383379,
  "type": "Feature",
  "properties": {
    "tgn:hierarchy":[
        "tgn:2383379",
        "tgn:2002365",
        "tgn:1000001",
        "tgn:7012149",
        "tgn:7007923",
        "tgn:7029392"
    ],
    "tgn:id":2383379,
    "tgn:name":"Heart Lake",
    "tgn:placetype":[
        "aat:300008680"
    ]
},
  "bbox": [],
  "geometry": {"coordinates":[-106.3167,41.3667],"type":"Point"}
}