{
  "id": 2392979,
  "type": "Feature",
  "properties": {
    "tgn:hierarchy":[
        "tgn:2392979",
        "tgn:1000001",
        "tgn:7012149",
        "tgn:2000929",
        "tgn:7007515",
        "tgn:7029392"
    ],
    "tgn:id":2392979,
    "tgn:name":"Hockomock Bay",
    "tgn:placetype":[
        "aat:300132316"
    ]
},
  "bbox": [],
  "geometry": {"coordinates":[-69.7333,43.8833],"type":"Point"}
}