{
  "id": 7412721,
  "type": "Feature",
  "properties": {
    "tgn:hierarchy":[
        "tgn:7412721",
        "tgn:7005587",
        "tgn:1000001",
        "tgn:7005560",
        "tgn:7029392"
    ],
    "tgn:id":7412721,
    "tgn:name:es":"Chalahuite",
    "tgn:placetype":[
        "aat:300008347"
    ]
},
  "bbox": [],
  "geometry": {"coordinates":[-98.940278,21.241667],"type":"Point"}
}