{
  "id": 7563530,
  "type": "Feature",
  "properties": {
    "tgn:hierarchy":[
        "tgn:7563530",
        "tgn:1000004",
        "tgn:7000198",
        "tgn:7016722",
        "tgn:7029392"
    ],
    "tgn:id":7563530,
    "tgn:name:en":"Karpah\u0101ria",
    "tgn:placetype":[
        "aat:300008347"
    ]
},
  "bbox": [],
  "geometry": {"coordinates":[79.311023,25.33646],"type":"Point"}
}