{
  "id": 7315176,
  "type": "Feature",
  "properties": {
    "tgn:hierarchy":[
        "tgn:7315176",
        "tgn:1001705",
        "tgn:1000049",
        "tgn:1000002",
        "tgn:7029392"
    ],
    "tgn:id":7315176,
    "tgn:name":"Coligual, Cerro",
    "tgn:placetype":[
        "aat:300008777"
    ]
},
  "bbox": [],
  "geometry": {"coordinates":[-70.983333,-35.516667],"type":"Point"}
}