{
  "id": 1018817,
  "type": "Feature",
  "properties": {
    "tgn:hierarchy":[
        "tgn:1018817",
        "tgn:1001593",
        "tgn:1000001",
        "tgn:7005565",
        "tgn:7029392"
    ],
    "tgn:id":1018817,
    "tgn:name":"Ca\u00f1azas",
    "tgn:placetype":[
        "aat:300008347"
    ]
},
  "bbox": [],
  "geometry": {"coordinates":[-81.1667,8.4167],"type":"Point"}
}