{
  "id": 2389505,
  "type": "Feature",
  "properties": {
    "tgn:hierarchy":[
        "tgn:2389505",
        "tgn:1000001",
        "tgn:7012149",
        "tgn:2000476",
        "tgn:7007250",
        "tgn:7029392"
    ],
    "tgn:id":2389505,
    "tgn:name":"High Breaks",
    "tgn:placetype":[
        "aat:300386831"
    ]
},
  "bbox": [],
  "geometry": {"coordinates":[-116.5167,45.8667],"type":"Point"}
}