{
  "id": 7336860,
  "type": "Feature",
  "properties": {
    "tgn:hierarchy":[
        "tgn:7336860",
        "tgn:7002844",
        "tgn:7030216",
        "tgn:1000003",
        "tgn:1000095",
        "tgn:7029392"
    ],
    "tgn:id":7336860,
    "tgn:name":"Estany Gelat, Barranco del",
    "tgn:placetype":[
        "aat:300266554",
        "aat:300008699"
    ]
},
  "bbox": [],
  "geometry": {"coordinates":[0.966667,41.016667],"type":"Point"}
}