{
  "id": 2709356,
  "type": "Feature",
  "properties": {
    "tgn:hierarchy":[
        "tgn:2709356",
        "tgn:1000001",
        "tgn:7012149",
        "tgn:1002350",
        "tgn:7007157",
        "tgn:7029392"
    ],
    "tgn:id":2709356,
    "tgn:name":"Table Rock",
    "tgn:placetype":[
        "aat:300008798"
    ]
},
  "bbox": [],
  "geometry": {"coordinates":[-120.2833,38.8333],"type":"Point"}
}