{
  "id": 1133548,
  "type": "Feature",
  "properties": {
    "tgn:hierarchy":[
        "tgn:1133548",
        "tgn:1000001",
        "tgn:1002282",
        "tgn:7012149",
        "tgn:7007252",
        "tgn:7029392"
    ],
    "tgn:id":1133548,
    "tgn:name":"Kilmore Creek",
    "tgn:placetype":[
        "aat:300008706"
    ]
},
  "bbox": [],
  "geometry": {"coordinates":[-86.2333,40.35],"type":"Point"}
}