{
  "id": 7319725,
  "type": "Feature",
  "properties": {
    "tgn:hierarchy":[
        "tgn:7319725",
        "tgn:1001695",
        "tgn:1000049",
        "tgn:1000002",
        "tgn:7029392"
    ],
    "tgn:id":7319725,
    "tgn:name":"Algorta",
    "tgn:placetype":[
        "aat:300000206"
    ]
},
  "bbox": [],
  "geometry": {"coordinates":[-71.383333,-34.183333],"type":"Point"}
}