<<<<<<< HEAD
{
  "id": 2254549,
  "type": "Feature",
  "properties": {
    "tgn:hierarchy":[
        "tgn:2254549",
        "tgn:7002659",
        "tgn:1000001",
        "tgn:7012149",
        "tgn:2000064",
        "tgn:7029392"
    ],
    "tgn:id":2254549,
    "tgn:name":"Coon Hill Ridge",
    "tgn:placetype":[
        "aat:300266640"
    ]
},
  "bbox": [],
  "geometry": {"coordinates":[-88.1,31.2333],"type":"Point"}
}
=======
{"geometry":{"type":"Point","coordinates":[-88.100000,31.233300]},"type":"Feature","properties":{"hierarchy":["tgn:2254549","tgn:7002659","tgn:1000001","tgn:7012149","tgn:2000064","tgn:7029392"],"placetype":["aat:300266640"],"id":2254549,"name:xx":"Coon Hill Ridge"}}
>>>>>>> 03f74aca74312dbeaf24d7e61306dd6a786dc3d0
