{
  "id": 7291402,
  "type": "Feature",
  "properties": {
    "tgn:hierarchy":[
        "tgn:7291402",
        "tgn:1001702",
        "tgn:1000049",
        "tgn:1000002",
        "tgn:7029392"
    ],
    "tgn:id":7291402,
    "tgn:name":"Escape, Bah\u00eda",
    "tgn:placetype":[
        "aat:300132316"
    ]
},
  "bbox": [],
  "geometry": {"coordinates":[-71.05,-54.866667],"type":"Point"}
}