<<<<<<< HEAD
{
  "id": 7174079,
  "type": "Feature",
  "properties": {
    "tgn:hierarchy":[
        "tgn:7174079",
        "tgn:7003669",
        "tgn:1000003",
        "tgn:7000084",
        "tgn:7029392"
    ],
    "tgn:id":7174079,
    "tgn:name":"Gross Lichten Berg",
    "tgn:placetype":[
        "aat:300008795"
    ]
},
  "bbox": [],
  "geometry": {"coordinates":[13.716667,48.833333],"type":"Point"}
}
=======
{"geometry":{"type":"Point","coordinates":[13.716667,48.833333]},"type":"Feature","properties":{"hierarchy":["tgn:7174079","tgn:7003669","tgn:1000003","tgn:7000084","tgn:7029392"],"placetype":["aat:300008795"],"id":7174079,"name:xx":"Gross Lichten Berg"}}
>>>>>>> 03f74aca74312dbeaf24d7e61306dd6a786dc3d0
