{
  "id": 1109824,
  "type": "Feature",
  "properties": {
    "tgn:hierarchy":[
        "tgn:1109824",
        "tgn:1000004",
        "tgn:7002077",
        "tgn:1000111",
        "tgn:7029392"
    ],
    "tgn:id":1109824,
    "tgn:name":"Xiaowutai Shan",
    "tgn:placetype":[
        "aat:300008795"
    ]
},
  "bbox": [],
  "geometry": {"coordinates":[114.9833,39.85],"type":"Point"}
}