{
  "id": 7539719,
  "type": "Feature",
  "properties": {
    "tgn:hierarchy":[
        "tgn:7539719",
        "tgn:7001242",
        "tgn:7016833",
        "tgn:1001418",
        "tgn:7029392"
    ],
    "tgn:id":7539719,
    "tgn:name:en":"Qabr Sam\u00e2l\u00fbsi",
    "tgn:placetype":[
        "aat:300005926"
    ]
},
  "bbox": [],
  "geometry": {"coordinates":[27.832215,30.953066],"type":"Point"}
}