<<<<<<< HEAD
{
  "id": 7484840,
  "type": "Feature",
  "properties": {
    "tgn:hierarchy":[
        "tgn:7484840",
        "tgn:7488858",
        "tgn:1000004",
        "tgn:1000141",
        "tgn:7029392"
    ],
    "tgn:id":7484840,
    "tgn:name":"Zhenlieba Shan",
    "tgn:placetype":[
        "aat:300008798"
    ]
},
  "bbox": [],
  "geometry": {"coordinates":[121.2025,24.1525],"type":"Point"}
}
=======
{"geometry":{"type":"Point","coordinates":[121.202500,24.152500]},"type":"Feature","properties":{"hierarchy":["tgn:7484840","tgn:7488858","tgn:1000004","tgn:1000141","tgn:7029392"],"placetype":["aat:300008798"],"id":7484840,"name:xx":"Zhenlieba Shan"}}
>>>>>>> 03f74aca74312dbeaf24d7e61306dd6a786dc3d0
