{
  "id": 7484840,
  "type": "Feature",
  "properties": {
    "tgn:hierarchy":[
        "tgn:7484840",
        "tgn:7488858",
        "tgn:1000004",
        "tgn:1000141",
        "tgn:7029392"
    ],
    "tgn:id":7484840,
    "tgn:name":"Zhenlieba Shan",
    "tgn:placetype":[
        "aat:300008798"
    ]
},
  "bbox": [],
  "geometry": {"coordinates":[121.2025,24.1525],"type":"Point"}
}