{
  "id": 2717926,
  "type": "Feature",
  "properties": {
    "tgn:hierarchy":[
        "tgn:2717926",
        "tgn:1000001",
        "tgn:7012149",
        "tgn:2001616",
        "tgn:7007706",
        "tgn:7029392"
    ],
    "tgn:id":2717926,
    "tgn:name":"Thomas Village",
    "tgn:placetype":[
        "aat:300008347"
    ]
},
  "bbox": [],
  "geometry": {"coordinates":[-82.05,39.0333],"type":"Point"}
}