{
  "id": 2583454,
  "type": "Feature",
  "properties": {
    "tgn:hierarchy":[
        "tgn:2583454",
        "tgn:1000001",
        "tgn:7006451",
        "tgn:2000092",
        "tgn:7012149",
        "tgn:7029392"
    ],
    "tgn:id":2583454,
    "tgn:name":"Pine Ridge",
    "tgn:placetype":[
        "aat:300266640"
    ]
},
  "bbox": [],
  "geometry": {"coordinates":[-112.15,35.0333],"type":"Point"}
}