{
  "id": 2389554,
  "type": "Feature",
  "properties": {
    "tgn:hierarchy":[
        "tgn:2389554",
        "tgn:1000001",
        "tgn:7012149",
        "tgn:1002553",
        "tgn:7007920",
        "tgn:7029392"
    ],
    "tgn:id":2389554,
    "tgn:name":"High Creek",
    "tgn:placetype":[
        "aat:300008706"
    ]
},
  "bbox": [],
  "geometry": {"coordinates":[-120.5167,47.2333],"type":"Point"}
}