{
  "id": 2132321,
  "type": "Feature",
  "properties": {
    "tgn:hierarchy":[
        "tgn:2132321",
        "tgn:1000001",
        "tgn:7012149",
        "tgn:7007158",
        "tgn:7029392"
    ],
    "tgn:id":2132321,
    "tgn:name":"Amity Canal",
    "tgn:placetype":[
        "aat:300006075"
    ]
},
  "bbox": [],
  "geometry": {"coordinates":[-102.3333,38.1167],"type":"Point"}
}