{
  "id": 7070891,
  "type": "Feature",
  "properties": {
    "tgn:hierarchy":[
        "tgn:7070891",
        "tgn:1000003",
        "tgn:7003676",
        "tgn:7000084",
        "tgn:7029392"
    ],
    "tgn:id":7070891,
    "tgn:name":"Stein-Berg",
    "tgn:placetype":[
        "aat:300008795"
    ]
},
  "bbox": [],
  "geometry": {"coordinates":[10.416667,51.916667],"type":"Point"}
}