<<<<<<< HEAD
{
  "id": 2768697,
  "type": "Feature",
  "properties": {
    "tgn:hierarchy":[
        "tgn:2768697",
        "tgn:1000001",
        "tgn:7012149",
        "tgn:2000980",
        "tgn:7007520",
        "tgn:7029392"
    ],
    "tgn:id":2768697,
    "tgn:name":"Whitlock Lake",
    "tgn:placetype":[
        "aat:300008680"
    ]
},
  "bbox": [],
  "geometry": {"coordinates":[-85.3167,44.35],"type":"Point"}
}
=======
{"geometry":{"type":"Point","coordinates":[-85.316700,44.350000]},"type":"Feature","properties":{"hierarchy":["tgn:2768697","tgn:1000001","tgn:7012149","tgn:2000980","tgn:7007520","tgn:7029392"],"placetype":["aat:300008680"],"id":2768697,"name:xx":"Whitlock Lake"}}
>>>>>>> 03f74aca74312dbeaf24d7e61306dd6a786dc3d0
