{
  "id": 2652901,
  "type": "Feature",
  "properties": {
    "tgn:hierarchy":[
        "tgn:2652901",
        "tgn:1000001",
        "tgn:7012149",
        "tgn:1002681",
        "tgn:7007568",
        "tgn:7029392"
    ],
    "tgn:id":2652901,
    "tgn:name":"Seth Green Island",
    "tgn:placetype":[
        "aat:300008791"
    ]
},
  "bbox": [],
  "geometry": {"coordinates":[-77.6167,43.1833],"type":"Point"}
}