{
  "id": 2040560,
  "type": "Feature",
  "properties": {
    "tgn:hierarchy":[
        "tgn:2040560",
        "tgn:1000001",
        "tgn:2000780",
        "tgn:7012149",
        "tgn:7007255",
        "tgn:7029392"
    ],
    "tgn:id":2040560,
    "tgn:name":"Oak Grove",
    "tgn:placetype":[
        "aat:300008347"
    ]
},
  "bbox": [],
  "geometry": {"coordinates":[-87.4333,36.65],"type":"Point"}
}