{
  "id": 1055935,
  "type": "Feature",
  "properties": {
    "tgn:hierarchy":[
        "tgn:1055935",
        "tgn:1000003",
        "tgn:7012067",
        "tgn:7006660",
        "tgn:7029392"
    ],
    "tgn:id":1055935,
    "tgn:name":"Kryzs'ke",
    "tgn:placetype":[
        "aat:300008347"
    ]
},
  "bbox": [],
  "geometry": {"coordinates":[39.6333,49.4667],"type":"Point"}
}