{
  "id": 2268500,
  "type": "Feature",
  "properties": {
    "tgn:hierarchy":[
        "tgn:2268500",
        "tgn:1000001",
        "tgn:7006451",
        "tgn:2000095",
        "tgn:7012149",
        "tgn:7029392"
    ],
    "tgn:id":2268500,
    "tgn:name":"Crooks Mesa",
    "tgn:placetype":[
        "aat:300008798"
    ]
},
  "bbox": [],
  "geometry": {"coordinates":[-109.25,33.5167],"type":"Point"}
}