{
  "id": 7495225,
  "type": "Feature",
  "properties": {
    "tgn:hierarchy":[
        "tgn:7495225",
        "tgn:7468018",
        "tgn:1000004",
        "tgn:1000141",
        "tgn:7029392"
    ],
    "tgn:id":7495225,
    "tgn:name":"Yaochi Gong",
    "tgn:placetype":[
        "aat:300007595"
    ]
},
  "bbox": [],
  "geometry": {"coordinates":[120.560406,23.371736],"type":"Point"}
}