{
  "id": 7090496,
  "type": "Feature",
  "properties": {
    "tgn:hierarchy":[
        "tgn:7090496",
        "tgn:7003669",
        "tgn:1000003",
        "tgn:7000084",
        "tgn:7029392"
    ],
    "tgn:id":7090496,
    "tgn:name":"Burg Veldenstein",
    "tgn:placetype":[
        "aat:300006891"
    ]
},
  "bbox": [],
  "geometry": {"coordinates":[11.55,49.633333],"type":"Point"}
}