{
  "id": 7392078,
  "type": "Feature",
  "properties": {
    "tgn:hierarchy":[
        "tgn:7392078",
        "tgn:1000001",
        "tgn:7005597",
        "tgn:7005560",
        "tgn:7029392"
    ],
    "tgn:id":7392078,
    "tgn:name":"Rosita",
    "tgn:placetype":[
        "aat:300008347"
    ]
},
  "bbox": [],
  "geometry": {"coordinates":[-99.05,23.783333],"type":"Point"}
}