{
  "id": 2556026,
  "type": "Feature",
  "properties": {
    "tgn:hierarchy":[
        "tgn:2556026",
        "tgn:1000001",
        "tgn:7012149",
        "tgn:2001683",
        "tgn:7007707",
        "tgn:7029392"
    ],
    "tgn:id":2556026,
    "tgn:name":"Oil Well Hollow",
    "tgn:placetype":[
        "aat:300008761"
    ]
},
  "bbox": [],
  "geometry": {"coordinates":[-95.6333,34.6667],"type":"Point"}
}