{
  "id": 7222270,
  "type": "Feature",
  "properties": {
    "tgn:hierarchy":[
        "tgn:7222270",
        "tgn:7002735",
        "tgn:7017076",
        "tgn:1000003",
        "tgn:1000074",
        "tgn:7029392"
    ],
    "tgn:id":7222270,
    "tgn:name":"Pori\u00e1",
    "tgn:placetype":[
        "aat:300008795"
    ]
},
  "bbox": [],
  "geometry": {"coordinates":[22.883333,37.083333],"type":"Point"}
}