{
  "id": 7260114,
  "type": "Feature",
  "properties": {
    "tgn:hierarchy":[
        "tgn:7260114",
        "tgn:7003616",
        "tgn:1000003",
        "tgn:7016845",
        "tgn:7029392"
    ],
    "tgn:id":7260114,
    "tgn:name:nl":"Deinum, Polder",
    "tgn:placetype":[
        "aat:300006163"
    ]
},
  "bbox": [],
  "geometry": {"coordinates":[5.75,53.183333],"type":"Point"}
}