{
  "id": 2425053,
  "type": "Feature",
  "properties": {
    "tgn:hierarchy":[
        "tgn:2425053",
        "tgn:1000001",
        "tgn:7012149",
        "tgn:2000441",
        "tgn:7007248",
        "tgn:7029392"
    ],
    "tgn:id":2425053,
    "tgn:name":"Johnson Lake",
    "tgn:placetype":[
        "aat:300006191"
    ]
},
  "bbox": [],
  "geometry": {"coordinates":[-82.75,32.85],"type":"Point"}
}