{
  "id": 2062515,
  "type": "Feature",
  "properties": {
    "tgn:hierarchy":[
        "tgn:2062515",
        "tgn:2001317",
        "tgn:1000001",
        "tgn:7012149",
        "tgn:7007525",
        "tgn:7029392"
    ],
    "tgn:id":2062515,
    "tgn:name":"Orchard",
    "tgn:placetype":[
        "aat:300008347"
    ]
},
  "bbox": [],
  "geometry": {"coordinates":[-98.2333,42.3333],"type":"Point"}
}