{
  "id": 2677181,
  "type": "Feature",
  "properties": {
    "tgn:hierarchy":[
        "tgn:2677181",
        "tgn:1000001",
        "tgn:7012149",
        "tgn:1002701",
        "tgn:7007706",
        "tgn:7029392"
    ],
    "tgn:id":2677181,
    "tgn:name":"South Branch Symmes Creek",
    "tgn:placetype":[
        "aat:300008706"
    ]
},
  "bbox": [],
  "geometry": {"coordinates":[-81.8833,40.0667],"type":"Point"}
}