{
  "id": 2049636,
  "type": "Feature",
  "properties": {
    "tgn:hierarchy":[
        "tgn:2049636",
        "tgn:1002201",
        "tgn:1000001",
        "tgn:7012149",
        "tgn:7007517",
        "tgn:7029392"
    ],
    "tgn:id":2049636,
    "tgn:name":"Cow Yard",
    "tgn:placetype":[
        "aat:300008347"
    ]
},
  "bbox": [],
  "geometry": {"coordinates":[-70.9667,41.5167],"type":"Point"}
}