{
  "id": 7226853,
  "type": "Feature",
  "properties": {
    "tgn:hierarchy":[
        "tgn:7226853",
        "tgn:7002741",
        "tgn:7017076",
        "tgn:1000003",
        "tgn:1000074",
        "tgn:7029392"
    ],
    "tgn:id":7226853,
    "tgn:name":"Skotin\u00ed",
    "tgn:placetype":[
        "aat:300008347"
    ]
},
  "bbox": [],
  "geometry": {"coordinates":[22.433333,37.783333],"type":"Point"}
}