{
  "id": 7166539,
  "type": "Feature",
  "properties": {
    "tgn:hierarchy":[
        "tgn:7166539",
        "tgn:1000003",
        "tgn:7000094",
        "tgn:7000084",
        "tgn:7029392"
    ],
    "tgn:id":7166539,
    "tgn:name":"Heisterbusch",
    "tgn:placetype":[
        "aat:300000206"
    ]
},
  "bbox": [],
  "geometry": {"coordinates":[10.85,53.516667],"type":"Point"}
}