{
  "id": 2145304,
  "type": "Feature",
  "properties": {
    "tgn:hierarchy":[
        "tgn:2145304",
        "tgn:1000001",
        "tgn:7012149",
        "tgn:2001288",
        "tgn:7007524",
        "tgn:7029392"
    ],
    "tgn:id":2145304,
    "tgn:name":"Bald Number 12/Wildcat Mine",
    "tgn:placetype":[
        "aat:300000390"
    ]
},
  "bbox": [],
  "geometry": {"coordinates":[-111.8833,45.4667],"type":"Point"}
}