{
  "id": 1023567,
  "type": "Feature",
  "properties": {
    "tgn:hierarchy":[
        "tgn:1023567",
        "tgn:1001708",
        "tgn:1000049",
        "tgn:1000002",
        "tgn:7029392"
    ],
    "tgn:id":1023567,
    "tgn:name":"Pe\u00f1alol\u00e9n",
    "tgn:placetype":[
        "aat:300008347"
    ]
},
  "bbox": [],
  "geometry": {"coordinates":[-70.533333,-33.483333],"type":"Point"}
}