{
  "id": 7133586,
  "type": "Feature",
  "properties": {
    "tgn:hierarchy":[
        "tgn:7133586",
        "tgn:1000003",
        "tgn:7003676",
        "tgn:7000084",
        "tgn:7029392"
    ],
    "tgn:id":7133586,
    "tgn:name":"M\u00fcnkeweg",
    "tgn:placetype":[
        "aat:300000206"
    ]
},
  "bbox": [],
  "geometry": {"coordinates":[7.433333,53.433333],"type":"Point"}
}