{
  "id": 7531808,
  "type": "Feature",
  "properties": {
    "tgn:hierarchy":[
        "tgn:7531808",
        "tgn:7001242",
        "tgn:7016833",
        "tgn:7001335",
        "tgn:7029392"
    ],
    "tgn:id":7531808,
    "tgn:name":"Al Ma\u1e29amd\u012byah",
    "tgn:placetype":[
        "aat:300008777"
    ]
},
  "bbox": [],
  "geometry": {"coordinates":[32.660126,31.04468],"type":"Point"}
}