<<<<<<< HEAD
{
  "id": 7368754,
  "type": "Feature",
  "properties": {
    "tgn:hierarchy":[
        "tgn:7368754",
        "tgn:1000001",
        "tgn:7005601",
        "tgn:7005560",
        "tgn:7029392"
    ],
    "tgn:id":7368754,
    "tgn:name":"Guadalupe",
    "tgn:placetype":[
        "aat:300008347"
    ]
},
  "bbox": [],
  "geometry": {"coordinates":[-101.916667,23.8],"type":"Point"}
}
=======
{"geometry":{"type":"Point","coordinates":[-101.916667,23.800000]},"type":"Feature","properties":{"hierarchy":["tgn:7368754","tgn:1000001","tgn:7005601","tgn:7005560","tgn:7029392"],"placetype":["aat:300008347"],"id":7368754,"name:xx":"Guadalupe"}}
>>>>>>> 03f74aca74312dbeaf24d7e61306dd6a786dc3d0
