{
  "id": 7498121,
  "type": "Feature",
  "properties": {
    "tgn:hierarchy":[
        "tgn:7498121",
        "tgn:1000004",
        "tgn:7491221",
        "tgn:1000141",
        "tgn:7029392"
    ],
    "tgn:id":7498121,
    "tgn:name":"Fude Ci",
    "tgn:placetype":[
        "aat:300007595"
    ]
},
  "bbox": [],
  "geometry": {"coordinates":[121.138607,22.919723],"type":"Point"}
}