{
  "id": 2144750,
  "type": "Feature",
  "properties": {
    "tgn:hierarchy":[
        "tgn:2144750",
        "tgn:1000001",
        "tgn:2000954",
        "tgn:7012149",
        "tgn:7007520",
        "tgn:7029392"
    ],
    "tgn:id":2144750,
    "tgn:name":"Bald Hill",
    "tgn:placetype":[
        "aat:300008798"
    ]
},
  "bbox": [],
  "geometry": {"coordinates":[-84.4833,44.7167],"type":"Point"}
}