<<<<<<< HEAD
{
  "id": 7372379,
  "type": "Feature",
  "properties": {
    "tgn:hierarchy":[
        "tgn:7372379",
        "tgn:1000001",
        "tgn:7005598",
        "tgn:7005560",
        "tgn:7029392"
    ],
    "tgn:id":7372379,
    "tgn:name":"La Candelaria",
    "tgn:placetype":[
        "aat:300008347"
    ]
},
  "bbox": [],
  "geometry": {"coordinates":[-97.9,19.45],"type":"Point"}
}
=======
{"geometry":{"type":"Point","coordinates":[-97.900000,19.450000]},"type":"Feature","properties":{"hierarchy":["tgn:7372379","tgn:1000001","tgn:7005598","tgn:7005560","tgn:7029392"],"placetype":["aat:300008347"],"id":7372379,"name:xx":"La Candelaria"}}
>>>>>>> 03f74aca74312dbeaf24d7e61306dd6a786dc3d0
