{
  "id": 2435876,
  "type": "Feature",
  "properties": {
    "tgn:hierarchy":[
        "tgn:2435876",
        "tgn:1000001",
        "tgn:7012149",
        "tgn:7007828",
        "tgn:7029392"
    ],
    "tgn:id":2435876,
    "tgn:name":"Kettle Pond",
    "tgn:placetype":[
        "aat:300008680"
    ]
},
  "bbox": [],
  "geometry": {"coordinates":[-72.3167,44.2833],"type":"Point"}
}