{
  "id": 2020221,
  "type": "Feature",
  "properties": {
    "tgn:hierarchy":[
        "tgn:2020221",
        "tgn:1000001",
        "tgn:7012149",
        "tgn:1002631",
        "tgn:7007240",
        "tgn:7029392"
    ],
    "tgn:id":2020221,
    "tgn:name":"Lowell",
    "tgn:placetype":[
        "aat:300008347"
    ]
},
  "bbox": [],
  "geometry": {"coordinates":[-82.1833,29.3167],"type":"Point"}
}