{
  "id": 7546099,
  "type": "Feature",
  "properties": {
    "tgn:hierarchy":[
        "tgn:7546099",
        "tgn:1000004",
        "tgn:7000198",
        "tgn:1001894",
        "tgn:7029392"
    ],
    "tgn:id":7546099,
    "tgn:name:en":"Baink Nad\u012b",
    "tgn:placetype":[
        "aat:300008699"
    ]
},
  "bbox": [],
  "geometry": {"coordinates":[79.464018,24.075372],"type":"Point"}
}