{
  "id": 2262147,
  "type": "Feature",
  "properties": {
    "tgn:hierarchy":[
        "tgn:2262147",
        "tgn:1000001",
        "tgn:7012149",
        "tgn:7007157",
        "tgn:7014516",
        "tgn:7029392"
    ],
    "tgn:id":2262147,
    "tgn:name":"Cow Creek",
    "tgn:placetype":[
        "aat:300008706"
    ]
},
  "bbox": [],
  "geometry": {"coordinates":[-123.1833,38.6333],"type":"Point"}
}