{
  "id": 7535560,
  "type": "Feature",
  "properties": {
    "tgn:hierarchy":[
        "tgn:7535560",
        "tgn:7001242",
        "tgn:7016833",
        "tgn:1001418",
        "tgn:7029392"
    ],
    "tgn:id":7535560,
    "tgn:name:en":"Khal\u012bl, 'Ayn",
    "tgn:placetype":[
        "aat:300008697"
    ]
},
  "bbox": [],
  "geometry": {"coordinates":[25.566667,29.183333],"type":"Point"}
}