{
  "id": 7312191,
  "type": "Feature",
  "properties": {
    "tgn:hierarchy":[
        "tgn:7312191",
        "tgn:1001768",
        "tgn:1000049",
        "tgn:1000002",
        "tgn:7029392"
    ],
    "tgn:id":7312191,
    "tgn:name":"Las Caletas",
    "tgn:placetype":[
        "aat:300387200"
    ]
},
  "bbox": [],
  "geometry": {"coordinates":[-71.316667,-32.35],"type":"Point"}
}