{
  "id": 2097606,
  "type": "Feature",
  "properties": {
    "tgn:hierarchy":[
        "tgn:2097606",
        "tgn:1000001",
        "tgn:2001815",
        "tgn:7012149",
        "tgn:7007713",
        "tgn:7029392"
    ],
    "tgn:id":2097606,
    "tgn:name":"Veblen",
    "tgn:placetype":[
        "aat:300008347"
    ]
},
  "bbox": [],
  "geometry": {"coordinates":[-97.2833,45.85],"type":"Point"}
}