{
  "id": 2101741,
  "type": "Feature",
  "properties": {
    "tgn:hierarchy":[
        "tgn:2101741",
        "tgn:1000001",
        "tgn:7012149",
        "tgn:2001887",
        "tgn:7007825",
        "tgn:7029392"
    ],
    "tgn:id":2101741,
    "tgn:name":"Sweetwater",
    "tgn:placetype":[
        "aat:300008347",
        "aat:300387210"
    ]
},
  "bbox": [],
  "geometry": {"coordinates":[-87.6167,35.4833],"type":"Point"}
}