{
  "id": 7182815,
  "type": "Feature",
  "properties": {
    "tgn:hierarchy":[
        "tgn:7182815",
        "tgn:1000003",
        "tgn:7003687",
        "tgn:7000084",
        "tgn:7029392"
    ],
    "tgn:id":7182815,
    "tgn:name":"Galgenh\u00fcgel",
    "tgn:placetype":[
        "aat:300008777"
    ]
},
  "bbox": [],
  "geometry": {"coordinates":[11.683333,51.733333],"type":"Point"}
}