{
  "id": 7574814,
  "type": "Feature",
  "properties": {
    "tgn:hierarchy":[
        "tgn:7574814",
        "tgn:1001828",
        "tgn:1000004",
        "tgn:7000198",
        "tgn:7029392"
    ],
    "tgn:id":7574814,
    "tgn:name:en":"Kaviti",
    "tgn:placetype":[
        "aat:300008347"
    ]
},
  "bbox": [],
  "geometry": {"coordinates":[84.683333,19.016667],"type":"Point"}
}