<<<<<<< HEAD
{
  "id": 2155488,
  "type": "Feature",
  "properties": {
    "tgn:hierarchy":[
        "tgn:2155488",
        "tgn:1000001",
        "tgn:7012149",
        "tgn:2002191",
        "tgn:7007919",
        "tgn:7029392"
    ],
    "tgn:id":2155488,
    "tgn:name":"Bear Ridge",
    "tgn:placetype":[
        "aat:300266640"
    ]
},
  "bbox": [],
  "geometry": {"coordinates":[-81.5,36.7167],"type":"Point"}
}
=======
{"geometry":{"type":"Point","coordinates":[-81.500000,36.716700]},"type":"Feature","properties":{"hierarchy":["tgn:2155488","tgn:1000001","tgn:7012149","tgn:2002191","tgn:7007919","tgn:7029392"],"placetype":["aat:300266640"],"id":2155488,"name:xx":"Bear Ridge"}}
>>>>>>> 03f74aca74312dbeaf24d7e61306dd6a786dc3d0
