{
  "id": 2096878,
  "type": "Feature",
  "properties": {
    "tgn:hierarchy":[
        "tgn:2096878",
        "tgn:1000001",
        "tgn:7012149",
        "tgn:2001765",
        "tgn:7007712",
        "tgn:7029392"
    ],
    "tgn:id":2096878,
    "tgn:name":"Ward",
    "tgn:placetype":[
        "aat:300008347"
    ]
},
  "bbox": [],
  "geometry": {"coordinates":[-81.7167,33.85],"type":"Point"}
}