{
  "id": 2706585,
  "type": "Feature",
  "properties": {
    "tgn:hierarchy":[
        "tgn:2706585",
        "tgn:1000001",
        "tgn:2001260",
        "tgn:7012149",
        "tgn:7007524",
        "tgn:7029392"
    ],
    "tgn:id":2706585,
    "tgn:name":"Swan Lake",
    "tgn:placetype":[
        "aat:300008680"
    ]
},
  "bbox": [],
  "geometry": {"coordinates":[-111.7167,44.6167],"type":"Point"}
}