{
  "id": 2746938,
  "type": "Feature",
  "properties": {
    "tgn:hierarchy":[
        "tgn:2746938",
        "tgn:1000001",
        "tgn:7012149",
        "tgn:2001846",
        "tgn:7007825",
        "tgn:7029392"
    ],
    "tgn:id":2746938,
    "tgn:name":"Wagner Branch",
    "tgn:placetype":[
        "aat:300008699"
    ]
},
  "bbox": [],
  "geometry": {"coordinates":[-82.05,36.25],"type":"Point"}
}