{
  "id": 7069747,
  "type": "Feature",
  "properties": {
    "tgn:hierarchy":[
        "tgn:7069747",
        "tgn:7003669",
        "tgn:1000003",
        "tgn:7000084",
        "tgn:7029392"
    ],
    "tgn:id":7069747,
    "tgn:name":"Tollbach",
    "tgn:placetype":[
        "aat:300008347"
    ]
},
  "bbox": [],
  "geometry": {"coordinates":[11.883333,48.75],"type":"Point"}
}