{
  "id": 2364945,
  "type": "Feature",
  "properties": {
    "tgn:hierarchy":[
        "tgn:2364945",
        "tgn:1000001",
        "tgn:1002209",
        "tgn:7012149",
        "tgn:7007252",
        "tgn:7029392"
    ],
    "tgn:id":2364945,
    "tgn:name":"Greenhorn Creek",
    "tgn:placetype":[
        "aat:300008706"
    ]
},
  "bbox": [],
  "geometry": {"coordinates":[-86.1833,39.15],"type":"Point"}
}