{
  "id": 7392736,
  "type": "Feature",
  "properties": {
    "tgn:hierarchy":[
        "tgn:7392736",
        "tgn:7005581",
        "tgn:1000001",
        "tgn:7005560",
        "tgn:7029392"
    ],
    "tgn:id":7392736,
    "tgn:name":"San Fernando, Cerro",
    "tgn:placetype":[
        "aat:300008795"
    ]
},
  "bbox": [],
  "geometry": {"coordinates":[-107.35,26.416667],"type":"Point"}
}