{
  "id": 2617708,
  "type": "Feature",
  "properties": {
    "tgn:hierarchy":[
        "tgn:2617708",
        "tgn:1000001",
        "tgn:7012149",
        "tgn:7029392"
    ],
    "tgn:id":2617708,
    "tgn:name":"Riddle Creek",
    "tgn:placetype":[
        "aat:300008706"
    ]
},
  "bbox": [],
  "geometry": {"coordinates":[-94.3667,35.0667],"type":"Point"}
}