{
  "id": 2613326,
  "type": "Feature",
  "properties": {
    "tgn:hierarchy":[
        "tgn:2613326",
        "tgn:1000001",
        "tgn:7012149",
        "tgn:2001861",
        "tgn:7007825",
        "tgn:7029392"
    ],
    "tgn:id":2613326,
    "tgn:name":"Reed Creek",
    "tgn:placetype":[
        "aat:300008706"
    ]
},
  "bbox": [],
  "geometry": {"coordinates":[-84.9833,36.4833],"type":"Point"}
}