{
  "id": 7475345,
  "type": "Feature",
  "properties": {
    "tgn:hierarchy":[
        "tgn:7475345",
        "tgn:7468018",
        "tgn:1000004",
        "tgn:1000141",
        "tgn:7029392"
    ],
    "tgn:id":7475345,
    "tgn:name":"Yaozizhu",
    "tgn:placetype":[
        "aat:300008347"
    ]
},
  "bbox": [],
  "geometry": {"coordinates":[120.360366,23.533637],"type":"Point"}
}