{
  "id": 2480477,
  "type": "Feature",
  "properties": {
    "tgn:hierarchy":[
        "tgn:2480477",
        "tgn:1000001",
        "tgn:7012149",
        "tgn:2002129",
        "tgn:7007827",
        "tgn:7029392"
    ],
    "tgn:id":2480477,
    "tgn:name":"Lake View Ward",
    "tgn:placetype":[
        "aat:300008347"
    ]
},
  "bbox": [],
  "geometry": {"coordinates":[-112.0167,41.1667],"type":"Point"}
}