{
  "id": 2573336,
  "type": "Feature",
  "properties": {
    "tgn:hierarchy":[
        "tgn:2573336",
        "tgn:1000001",
        "tgn:7012149",
        "tgn:1002350",
        "tgn:7007157",
        "tgn:7029392"
    ],
    "tgn:id":2573336,
    "tgn:name":"Peavine Point",
    "tgn:placetype":[
        "aat:300266640"
    ]
},
  "bbox": [],
  "geometry": {"coordinates":[-120.65,38.9333],"type":"Point"}
}