{
  "id": 2223272,
  "type": "Feature",
  "properties": {
    "tgn:hierarchy":[
        "tgn:2223272",
        "tgn:1000001",
        "tgn:7012149",
        "tgn:1002518",
        "tgn:7007568",
        "tgn:7029392"
    ],
    "tgn:id":2223272,
    "tgn:name":"Carrying Place",
    "tgn:placetype":[
        "aat:300132316"
    ]
},
  "bbox": [],
  "geometry": {"coordinates":[-76.2667,44.05],"type":"Point"}
}