{
  "id": 2386144,
  "type": "Feature",
  "properties": {
    "tgn:hierarchy":[
        "tgn:2386144",
        "tgn:1000001",
        "tgn:1002500",
        "tgn:7012149",
        "tgn:7007240",
        "tgn:7029392"
    ],
    "tgn:id":2386144,
    "tgn:name":"Henry Schacht Lake",
    "tgn:placetype":[
        "aat:300008680"
    ]
},
  "bbox": [],
  "geometry": {"coordinates":[-80.5333,27.6167],"type":"Point"}
}