{
  "id": 2267207,
  "type": "Feature",
  "properties": {
    "tgn:hierarchy":[
        "tgn:2267207",
        "tgn:1000001",
        "tgn:2001477",
        "tgn:7012149",
        "tgn:7007709",
        "tgn:7029392"
    ],
    "tgn:id":2267207,
    "tgn:name":"Cricket Island Point",
    "tgn:placetype":[
        "aat:300008850"
    ]
},
  "bbox": [],
  "geometry": {"coordinates":[-76.1833,34.95],"type":"Point"}
}