<<<<<<< HEAD
{
  "id": 2703759,
  "type": "Feature",
  "properties": {
    "tgn:hierarchy":[
        "tgn:2703759",
        "tgn:1000001",
        "tgn:7012149",
        "tgn:2002373",
        "tgn:7007923",
        "tgn:7029392"
    ],
    "tgn:id":2703759,
    "tgn:name":"Sun Ditch",
    "tgn:placetype":[
        "aat:300006075"
    ]
},
  "bbox": [],
  "geometry": {"coordinates":[-108.6667,44.0],"type":"Point"}
}
=======
{"geometry":{"type":"Point","coordinates":[-108.666700,44.000000]},"type":"Feature","properties":{"hierarchy":["tgn:2703759","tgn:1000001","tgn:7012149","tgn:2002373","tgn:7007923","tgn:7029392"],"placetype":["aat:300006075"],"id":2703759,"name:xx":"Sun Ditch"}}
>>>>>>> 03f74aca74312dbeaf24d7e61306dd6a786dc3d0
