{
  "id": 7326457,
  "type": "Feature",
  "properties": {
    "tgn:hierarchy":[
        "tgn:7326457",
        "tgn:7002758",
        "tgn:7002821",
        "tgn:1000003",
        "tgn:1000095",
        "tgn:7029392"
    ],
    "tgn:id":7326457,
    "tgn:name":"Periate, Sierra de",
    "tgn:placetype":[
        "aat:300266640"
    ]
},
  "bbox": [],
  "geometry": {"coordinates":[-2.466667,37.633333],"type":"Point"}
}