{
  "id": 2675428,
  "type": "Feature",
  "properties": {
    "tgn:hierarchy":[
        "tgn:2675428",
        "tgn:1000001",
        "tgn:7012149",
        "tgn:2000181",
        "tgn:7007157",
        "tgn:7029392"
    ],
    "tgn:id":2675428,
    "tgn:name":"Soldiers Grove",
    "tgn:placetype":[
        "aat:300132451"
    ]
},
  "bbox": [],
  "geometry": {"coordinates":[-123.6833,40.55],"type":"Point"}
}