{
  "id": 1054235,
  "type": "Feature",
  "properties": {
    "tgn:hierarchy":[
        "tgn:1054235",
        "tgn:1000004",
        "tgn:1003421",
        "tgn:7018214",
        "tgn:7002435",
        "tgn:7029392"
    ],
    "tgn:id":1054235,
    "tgn:name":"Gus'-Khrustal'nyy",
    "tgn:placetype":[
        "aat:300008347"
    ]
},
  "bbox": [],
  "geometry": {"coordinates":[40.7333,55.6333],"type":"Point"}
}