{
  "id": 2173370,
  "type": "Feature",
  "properties": {
    "tgn:hierarchy":[
        "tgn:2173370",
        "tgn:1000001",
        "tgn:7012149",
        "tgn:1002214",
        "tgn:7007826",
        "tgn:7029392"
    ],
    "tgn:id":2173370,
    "tgn:name":"Birch Creek",
    "tgn:placetype":[
        "aat:300008706"
    ]
},
  "bbox": [],
  "geometry": {"coordinates":[-96.7167,30.4167],"type":"Point"}
}