{
  "id": 2224730,
  "type": "Feature",
  "properties": {
    "tgn:hierarchy":[
        "tgn:2224730",
        "tgn:1000001",
        "tgn:7006451",
        "tgn:2000095",
        "tgn:7012149",
        "tgn:7029392"
    ],
    "tgn:id":2224730,
    "tgn:name":"Cashier Spring",
    "tgn:placetype":[
        "aat:300008697"
    ]
},
  "bbox": [],
  "geometry": {"coordinates":[-109.0667,33.55],"type":"Point"}
}