{
  "id": 7540202,
  "type": "Feature",
  "properties": {
    "tgn:hierarchy":[
        "tgn:7540202",
        "tgn:7001242",
        "tgn:7016833",
        "tgn:1001335",
        "tgn:7029392"
    ],
    "tgn:id":7540202,
    "tgn:name:en":"\u1e62andala",
    "tgn:placetype":[
        "aat:300008347"
    ]
},
  "bbox": [],
  "geometry": {"coordinates":[30.834444,31.156944],"type":"Point"}
}