{
  "id": 1051987,
  "type": "Feature",
  "properties": {
    "tgn:hierarchy":[
        "tgn:1051987",
        "tgn:1000004",
        "tgn:7011628",
        "tgn:7014835",
        "tgn:7029392"
    ],
    "tgn:id":1051987,
    "tgn:name":"Ayn\u00ed",
    "tgn:placetype":[
        "aat:300008347"
    ]
},
  "bbox": [],
  "geometry": {"coordinates":[68.5333,39.3833],"type":"Point"}
}