{
  "id": 7482906,
  "type": "Feature",
  "properties": {
    "tgn:hierarchy":[
        "tgn:7482906",
        "tgn:1000004",
        "tgn:7001014",
        "tgn:1000141",
        "tgn:7029392"
    ],
    "tgn:id":7482906,
    "tgn:name":"Zhongzhuang",
    "tgn:placetype":[
        "aat:300008347"
    ]
},
  "bbox": [],
  "geometry": {"coordinates":[120.524444,23.709444],"type":"Point"}
}