{
  "id": 2485573,
  "type": "Feature",
  "properties": {
    "tgn:hierarchy":[
        "tgn:2485573",
        "tgn:1000001",
        "tgn:7012149",
        "tgn:1002785",
        "tgn:7007920",
        "tgn:7029392"
    ],
    "tgn:id":2485573,
    "tgn:name":"Lay Inlet",
    "tgn:placetype":[
        "aat:300132316"
    ]
},
  "bbox": [],
  "geometry": {"coordinates":[-122.65,47.3333],"type":"Point"}
}