{
  "id": 7230841,
  "type": "Feature",
  "properties": {
    "tgn:hierarchy":[
        "tgn:7230841",
        "tgn:7002681",
        "tgn:7001395",
        "tgn:1000003",
        "tgn:1000074",
        "tgn:7029392"
    ],
    "tgn:id":7230841,
    "tgn:name":"Panagi\u00e1, \u00c1kra",
    "tgn:placetype":[
        "aat:300008850"
    ]
},
  "bbox": [],
  "geometry": {"coordinates":[23.304121,37.612318],"type":"Point"}
}