{
  "id": 2174550,
  "type": "Feature",
  "properties": {
    "tgn:hierarchy":[
        "tgn:2174550",
        "tgn:1000001",
        "tgn:7012149",
        "tgn:2002183",
        "tgn:7007919",
        "tgn:7029392"
    ],
    "tgn:id":2174550,
    "tgn:name":"Bishops Cave",
    "tgn:placetype":[
        "aat:300008746"
    ]
},
  "bbox": [],
  "geometry": {"coordinates":[-80.65,37.15],"type":"Point"}
}