{
  "id": 2620500,
  "type": "Feature",
  "properties": {
    "tgn:hierarchy":[
        "tgn:2620500",
        "tgn:1002933",
        "tgn:1000001",
        "tgn:7012149",
        "tgn:7007239",
        "tgn:7029392"
    ],
    "tgn:id":2620500,
    "tgn:name":"River Village",
    "tgn:placetype":[
        "aat:300008347"
    ]
},
  "bbox": [],
  "geometry": {"coordinates":[-75.1833,38.6167],"type":"Point"}
}