<<<<<<< HEAD
{
  "id": 7057142,
  "type": "Feature",
  "properties": {
    "tgn:hierarchy":[
        "tgn:7057142",
        "tgn:7003129",
        "tgn:1000003",
        "tgn:7008516",
        "tgn:1000080",
        "tgn:7029392"
    ],
    "tgn:id":7057142,
    "tgn:name":"Balze",
    "tgn:placetype":[
        "aat:300008347"
    ]
},
  "bbox": [],
  "geometry": {"coordinates":[12.083333,43.783333],"type":"Point"}
}
=======
{"geometry":{"type":"Point","coordinates":[12.083333,43.783333]},"type":"Feature","properties":{"hierarchy":["tgn:7057142","tgn:7003129","tgn:1000003","tgn:7008516","tgn:1000080","tgn:7029392"],"placetype":["aat:300008347"],"id":7057142,"name:xx":"Balze"}}
>>>>>>> 03f74aca74312dbeaf24d7e61306dd6a786dc3d0
