{
  "id": 7300575,
  "type": "Feature",
  "properties": {
    "tgn:hierarchy":[
        "tgn:7300575",
        "tgn:7002824",
        "tgn:1000003",
        "tgn:7002786",
        "tgn:1000095",
        "tgn:7029392"
    ],
    "tgn:id":7300575,
    "tgn:name":"Oroso",
    "tgn:placetype":[
        "aat:300008347"
    ]
},
  "bbox": [],
  "geometry": {"coordinates":[-8.433333,42.983333],"type":"Point"}
}