{
  "id": 7239377,
  "type": "Feature",
  "properties": {
    "tgn:hierarchy":[
        "tgn:7239377",
        "tgn:7003465",
        "tgn:1000003",
        "tgn:1000063",
        "tgn:4012014",
        "tgn:7029392"
    ],
    "tgn:id":7239377,
    "tgn:name":"Hohwattig",
    "tgn:placetype":[
        "aat:300008347"
    ]
},
  "bbox": [],
  "geometry": {"coordinates":[5.716667,49.883333],"type":"Point"}
}