{
  "id": 1096996,
  "type": "Feature",
  "properties": {
    "tgn:hierarchy":[
        "tgn:1096996",
        "tgn:7000490",
        "tgn:1000006",
        "tgn:7001831",
        "tgn:7029392"
    ],
    "tgn:id":1096996,
    "tgn:name":"Goolwa",
    "tgn:placetype":[
        "aat:300008347"
    ]
},
  "bbox": [],
  "geometry": {"coordinates":[138.75,-35.5167],"type":"Point"}
}