<<<<<<< HEAD
{
  "id": 2159728,
  "type": "Feature",
  "properties": {
    "tgn:hierarchy":[
        "tgn:2159728",
        "tgn:1002309",
        "tgn:1000001",
        "tgn:7012149",
        "tgn:7007565",
        "tgn:7029392"
    ],
    "tgn:id":2159728,
    "tgn:name":"Beebe Run",
    "tgn:placetype":[
        "aat:300008699"
    ]
},
  "bbox": [],
  "geometry": {"coordinates":[-75.2833,39.4667],"type":"Point"}
}
=======
{"geometry":{"type":"Point","coordinates":[-75.283300,39.466700]},"type":"Feature","properties":{"hierarchy":["tgn:2159728","tgn:1002309","tgn:1000001","tgn:7012149","tgn:7007565","tgn:7029392"],"placetype":["aat:300008699"],"id":2159728,"name:xx":"Beebe Run"}}
>>>>>>> 03f74aca74312dbeaf24d7e61306dd6a786dc3d0
