<<<<<<< HEAD
{
  "id": 2408289,
  "type": "Feature",
  "properties": {
    "tgn:hierarchy":[
        "tgn:2408289",
        "tgn:1000001",
        "tgn:7012149",
        "tgn:2001543",
        "tgn:7007709",
        "tgn:7029392"
    ],
    "tgn:id":2408289,
    "tgn:name":"Huskey Creek",
    "tgn:placetype":[
        "aat:300008706"
    ]
},
  "bbox": [],
  "geometry": {"coordinates":[-83.3833,35.6167],"type":"Point"}
}
=======
{"geometry":{"type":"Point","coordinates":[-83.383300,35.616700]},"type":"Feature","properties":{"hierarchy":["tgn:2408289","tgn:1000001","tgn:7012149","tgn:2001543","tgn:7007709","tgn:7029392"],"placetype":["aat:300008706"],"id":2408289,"name:xx":"Huskey Creek"}}
>>>>>>> 03f74aca74312dbeaf24d7e61306dd6a786dc3d0
