{
  "id": 1086809,
  "type": "Feature",
  "properties": {
    "tgn:hierarchy":[
        "tgn:1086809",
        "tgn:7000420",
        "tgn:7018452",
        "tgn:1000004",
        "tgn:1000144",
        "tgn:7029392"
    ],
    "tgn:id":1086809,
    "tgn:name":"Uluborlu",
    "tgn:placetype":[
        "aat:300008347"
    ]
},
  "bbox": [],
  "geometry": {"coordinates":[30.4667,38.0833],"type":"Point"}
}