{
  "id": 1138209,
  "type": "Feature",
  "properties": {
    "tgn:hierarchy":[
        "tgn:1138209",
        "tgn:1000004",
        "tgn:1003379",
        "tgn:7018214",
        "tgn:7002435",
        "tgn:7029392"
    ],
    "tgn:id":1138209,
    "tgn:name":"Peskovka",
    "tgn:placetype":[
        "aat:300008347"
    ]
},
  "bbox": [],
  "geometry": {"coordinates":[52.3333,59.05],"type":"Point"}
}