{
  "id": 2656059,
  "type": "Feature",
  "properties": {
    "tgn:hierarchy":[
        "tgn:2656059",
        "tgn:1000001",
        "tgn:7012149",
        "tgn:1003038",
        "tgn:7007517",
        "tgn:7029392"
    ],
    "tgn:id":2656059,
    "tgn:name":"Shaw Pond",
    "tgn:placetype":[
        "aat:300006191"
    ]
},
  "bbox": [],
  "geometry": {"coordinates":[-72.1833,42.25],"type":"Point"}
}