{
  "id": 2215208,
  "type": "Feature",
  "properties": {
    "tgn:hierarchy":[
        "tgn:2215208",
        "tgn:1000001",
        "tgn:2001424",
        "tgn:7012149",
        "tgn:7007564",
        "tgn:7029392"
    ],
    "tgn:id":2215208,
    "tgn:name":"Call Brook",
    "tgn:placetype":[
        "aat:300008699"
    ]
},
  "bbox": [],
  "geometry": {"coordinates":[-72.0833,43.7667],"type":"Point"}
}