{
  "id": 2389875,
  "type": "Feature",
  "properties": {
    "tgn:hierarchy":[
        "tgn:2389875",
        "tgn:1000001",
        "tgn:7012149",
        "tgn:2001437",
        "tgn:7007566",
        "tgn:7029392"
    ],
    "tgn:id":2389875,
    "tgn:name":"High Peak",
    "tgn:placetype":[
        "aat:300008798"
    ]
},
  "bbox": [],
  "geometry": {"coordinates":[-108.7333,32.85],"type":"Point"}
}