{
  "id": 2398483,
  "type": "Feature",
  "properties": {
    "tgn:hierarchy":[
        "tgn:2398483",
        "tgn:1000001",
        "tgn:7012149",
        "tgn:1002990",
        "tgn:7007708",
        "tgn:7029392"
    ],
    "tgn:id":2398483,
    "tgn:name":"Hootnanny Point",
    "tgn:placetype":[
        "aat:300008798"
    ]
},
  "bbox": [],
  "geometry": {"coordinates":[-121.3667,45.3167],"type":"Point"}
}