{
  "id": 2703942,
  "type": "Feature",
  "properties": {
    "tgn:hierarchy":[
        "tgn:2703942",
        "tgn:1000001",
        "tgn:7012149",
        "tgn:2001067",
        "tgn:7007521",
        "tgn:7029392"
    ],
    "tgn:id":2703942,
    "tgn:name":"Sunday Lake",
    "tgn:placetype":[
        "aat:300008680"
    ]
},
  "bbox": [],
  "geometry": {"coordinates":[-91.8833,48.1667],"type":"Point"}
}