<<<<<<< HEAD
{
  "id": 7020013,
  "type": "Feature",
  "properties": {
    "tgn:hierarchy":[
        "tgn:7020013",
        "tgn:1000001",
        "tgn:7012149",
        "tgn:2002383",
        "tgn:7007923",
        "tgn:7029392"
    ],
    "tgn:id":7020013,
    "tgn:name":"Red Lakes",
    "tgn:placetype":[
        "aat:300008680"
    ]
},
  "bbox": [],
  "geometry": {"coordinates":[-108.0,41.5333],"type":"Point"}
}
=======
{"geometry":{"type":"Point","coordinates":[-108.000000,41.533300]},"type":"Feature","properties":{"hierarchy":["tgn:7020013","tgn:1000001","tgn:7012149","tgn:2002383","tgn:7007923","tgn:7029392"],"placetype":["aat:300008680"],"id":7020013,"name:xx":"Red Lakes"}}
>>>>>>> 03f74aca74312dbeaf24d7e61306dd6a786dc3d0
