<<<<<<< HEAD
{
  "id": 2157590,
  "type": "Feature",
  "properties": {
    "tgn:hierarchy":[
        "tgn:2157590",
        "tgn:1002933",
        "tgn:1000001",
        "tgn:7012149",
        "tgn:7007239",
        "tgn:7029392"
    ],
    "tgn:id":2157590,
    "tgn:name":"Beaver Dam Acres",
    "tgn:placetype":[
        "aat:300008347"
    ]
},
  "bbox": [],
  "geometry": {"coordinates":[-75.2,38.6833],"type":"Point"}
}
=======
{"geometry":{"type":"Point","coordinates":[-75.200000,38.683300]},"type":"Feature","properties":{"hierarchy":["tgn:2157590","tgn:1002933","tgn:1000001","tgn:7012149","tgn:7007239","tgn:7029392"],"placetype":["aat:300008347"],"id":2157590,"name:xx":"Beaver Dam Acres"}}
>>>>>>> 03f74aca74312dbeaf24d7e61306dd6a786dc3d0
