{
  "id": 2321473,
  "type": "Feature",
  "properties": {
    "tgn:hierarchy":[
        "tgn:2321473",
        "tgn:1000001",
        "tgn:2000870",
        "tgn:7012149",
        "tgn:7007256",
        "tgn:7029392"
    ],
    "tgn:id":2321473,
    "tgn:name":"Fairmont",
    "tgn:placetype":[
        "aat:300008347"
    ]
},
  "bbox": [],
  "geometry": {"coordinates":[-91.0333,30.4333],"type":"Point"}
}