{
  "id": 7225094,
  "type": "Feature",
  "properties": {
    "tgn:hierarchy":[
        "tgn:7225094",
        "tgn:7002681",
        "tgn:7001395",
        "tgn:1000003",
        "tgn:1000074",
        "tgn:7029392"
    ],
    "tgn:id":7225094,
    "tgn:name":"R\u00e9vmata",
    "tgn:placetype":[
        "aat:300008347"
    ]
},
  "bbox": [],
  "geometry": {"coordinates":[24.833333,37.866667],"type":"Point"}
}