{
  "id": 7299424,
  "type": "Feature",
  "properties": {
    "tgn:hierarchy":[
        "tgn:7299424",
        "tgn:7002808",
        "tgn:7030216",
        "tgn:1000003",
        "tgn:1000095",
        "tgn:7029392"
    ],
    "tgn:id":7299424,
    "tgn:name":"Urbanizaci\u00f3n Feliu",
    "tgn:placetype":[
        "aat:300008347"
    ]
},
  "bbox": [],
  "geometry": {"coordinates":[1.966667,41.266667],"type":"Point"}
}