{
  "id": 2607132,
  "type": "Feature",
  "properties": {
    "tgn:hierarchy":[
        "tgn:2607132",
        "tgn:1000001",
        "tgn:7012149",
        "tgn:7029392"
    ],
    "tgn:id":2607132,
    "tgn:name":"Randall Brook",
    "tgn:placetype":[
        "aat:300008699"
    ]
},
  "bbox": [],
  "geometry": {"coordinates":[-72.7667,42.7167],"type":"Point"}
}