<<<<<<< HEAD
{
  "id": 2407582,
  "type": "Feature",
  "properties": {
    "tgn:hierarchy":[
        "tgn:2407582",
        "tgn:1000001",
        "tgn:7012149",
        "tgn:1002599",
        "tgn:7007708",
        "tgn:7029392"
    ],
    "tgn:id":2407582,
    "tgn:name":"Hurbert Creek",
    "tgn:placetype":[
        "aat:300008706"
    ]
},
  "bbox": [],
  "geometry": {"coordinates":[-124.0333,44.6333],"type":"Point"}
}
=======
{"geometry":{"type":"Point","coordinates":[-124.033300,44.633300]},"type":"Feature","properties":{"hierarchy":["tgn:2407582","tgn:1000001","tgn:7012149","tgn:1002599","tgn:7007708","tgn:7029392"],"placetype":["aat:300008706"],"id":2407582,"name:xx":"Hurbert Creek"}}
>>>>>>> 03f74aca74312dbeaf24d7e61306dd6a786dc3d0
