{
  "id": 7174354,
  "type": "Feature",
  "properties": {
    "tgn:hierarchy":[
        "tgn:7174354",
        "tgn:1000003",
        "tgn:7000094",
        "tgn:7000084",
        "tgn:7029392"
    ],
    "tgn:id":7174354,
    "tgn:name":"Gro\u00dfer Kulowsee",
    "tgn:placetype":[
        "aat:300008680"
    ]
},
  "bbox": [],
  "geometry": {"coordinates":[13.166667,53.283333],"type":"Point"}
}