{
  "id": 7564343,
  "type": "Feature",
  "properties": {
    "tgn:hierarchy":[
        "tgn:7564343",
        "tgn:1000004",
        "tgn:7000198",
        "tgn:7016788",
        "tgn:7029392"
    ],
    "tgn:id":7564343,
    "tgn:name:en":"Mal\u0101na Johri",
    "tgn:placetype":[
        "aat:300006191"
    ]
},
  "bbox": [],
  "geometry": {"coordinates":[74.329251,28.12382],"type":"Point"}
}