{
  "id": 7145718,
  "type": "Feature",
  "properties": {
    "tgn:hierarchy":[
        "tgn:7145718",
        "tgn:1000003",
        "tgn:7003688",
        "tgn:7000084",
        "tgn:7029392"
    ],
    "tgn:id":7145718,
    "tgn:name":"K\u00f6llingbek",
    "tgn:placetype":[
        "aat:300008347"
    ]
},
  "bbox": [],
  "geometry": {"coordinates":[10.183333,54.133333],"type":"Point"}
}