{
  "id": 7429293,
  "type": "Feature",
  "properties": {
    "tgn:hierarchy":[
        "tgn:7429293",
        "tgn:1000001",
        "tgn:7005595",
        "tgn:7005560",
        "tgn:7029392"
    ],
    "tgn:id":7429293,
    "tgn:name":"Jacara",
    "tgn:placetype":[
        "aat:300008347"
    ]
},
  "bbox": [],
  "geometry": {"coordinates":[-107.15,24.208333],"type":"Point"}
}