{
  "id": 2776251,
  "type": "Feature",
  "properties": {
    "tgn:hierarchy":[
        "tgn:2776251",
        "tgn:7016099",
        "tgn:1000001",
        "tgn:7012149",
        "tgn:7007516",
        "tgn:7029392"
    ],
    "tgn:id":2776251,
    "tgn:name":"Winans",
    "tgn:placetype":[
        "aat:300008347"
    ]
},
  "bbox": [],
  "geometry": {"coordinates":[-76.6833,39.2167],"type":"Point"}
}