<<<<<<< HEAD
{
  "id": 7247456,
  "type": "Feature",
  "properties": {
    "tgn:hierarchy":[
        "tgn:7247456",
        "tgn:7003457",
        "tgn:1000003",
        "tgn:1000063",
        "tgn:7018236",
        "tgn:7029392"
    ],
    "tgn:id":7247456,
    "tgn:name":"De Bijl",
    "tgn:placetype":[
        "aat:300008347"
    ]
},
  "bbox": [],
  "geometry": {"coordinates":[4.244821,51.208899],"type":"Point"}
}
=======
{"geometry":{"type":"Point","coordinates":[4.244821,51.208899]},"type":"Feature","properties":{"hierarchy":["tgn:7247456","tgn:7003457","tgn:1000003","tgn:1000063","tgn:7018236","tgn:7029392"],"placetype":["aat:300008347"],"id":7247456,"name:xx":"De Bijl"}}
>>>>>>> 03f74aca74312dbeaf24d7e61306dd6a786dc3d0
