{
  "id": 2611227,
  "type": "Feature",
  "properties": {
    "tgn:hierarchy":[
        "tgn:2611227",
        "tgn:1000001",
        "tgn:7012149",
        "tgn:2002059",
        "tgn:7007826",
        "tgn:7029392"
    ],
    "tgn:id":2611227,
    "tgn:name":"Red House Draw",
    "tgn:placetype":[
        "aat:300008761"
    ]
},
  "bbox": [],
  "geometry": {"coordinates":[-101.4667,31.35],"type":"Point"}
}