{
  "id": 2457080,
  "type": "Feature",
  "properties": {
    "tgn:hierarchy":[
        "tgn:2457080",
        "tgn:1000001",
        "tgn:1002241",
        "tgn:7012149",
        "tgn:7007251",
        "tgn:7029392"
    ],
    "tgn:id":2457080,
    "tgn:name":"Little Lake",
    "tgn:placetype":[
        "aat:300008680"
    ]
},
  "bbox": [],
  "geometry": {"coordinates":[-90.15,40.05],"type":"Point"}
}