{
  "id": 7325095,
  "type": "Feature",
  "properties": {
    "tgn:hierarchy":[
        "tgn:7325095",
        "tgn:7002758",
        "tgn:7002821",
        "tgn:1000003",
        "tgn:1000095",
        "tgn:7029392"
    ],
    "tgn:id":7325095,
    "tgn:name":"San Clemente",
    "tgn:placetype":[
        "aat:300008347"
    ]
},
  "bbox": [],
  "geometry": {"coordinates":[-2.65,37.883333],"type":"Point"}
}