{
  "id": 2703122,
  "type": "Feature",
  "properties": {
    "tgn:hierarchy":[
        "tgn:2703122",
        "tgn:1000001",
        "tgn:2001944",
        "tgn:7012149",
        "tgn:7007826",
        "tgn:7029392"
    ],
    "tgn:id":2703122,
    "tgn:name":"Summer Hill Lake",
    "tgn:placetype":[
        "aat:300008680"
    ]
},
  "bbox": [],
  "geometry": {"coordinates":[-94.0833,33.55],"type":"Point"}
}