{
  "id": 7388484,
  "type": "Feature",
  "properties": {
    "tgn:hierarchy":[
        "tgn:7388484",
        "tgn:7016644",
        "tgn:1000001",
        "tgn:7005560",
        "tgn:7029392"
    ],
    "tgn:id":7388484,
    "tgn:name":"Paso del R\u00edo",
    "tgn:placetype":[
        "aat:300008347"
    ]
},
  "bbox": [],
  "geometry": {"coordinates":[-103.933333,18.95],"type":"Point"}
}