{
  "id": 7221940,
  "type": "Feature",
  "properties": {
    "tgn:hierarchy":[
        "tgn:7221940",
        "tgn:7011161",
        "tgn:7002674",
        "tgn:1000003",
        "tgn:1000074",
        "tgn:7029392"
    ],
    "tgn:id":7221940,
    "tgn:name":"Potami\u00e1",
    "tgn:placetype":[
        "aat:300008347"
    ]
},
  "bbox": [],
  "geometry": {"coordinates":[25.9375,38.528333],"type":"Point"}
}