{
  "id": 1051968,
  "type": "Feature",
  "properties": {
    "tgn:hierarchy":[
        "tgn:1051968",
        "tgn:7011438",
        "tgn:1000004",
        "tgn:7006646",
        "tgn:7029392"
    ],
    "tgn:id":1051968,
    "tgn:name":"Agdam",
    "tgn:placetype":[
        "aat:300008347",
        "aat:300008375"
    ]
},
  "bbox": [],
  "geometry": {"coordinates":[46.9167,39.9833],"type":"Point"}
}