{
  "id": 7217752,
  "type": "Feature",
  "properties": {
    "tgn:hierarchy":[
        "tgn:7217752",
        "tgn:7002715",
        "tgn:7002731",
        "tgn:1000003",
        "tgn:1000074",
        "tgn:7029392"
    ],
    "tgn:id":7217752,
    "tgn:name":"Yeraki\u00e1",
    "tgn:placetype":[
        "aat:300008347"
    ]
},
  "bbox": [],
  "geometry": {"coordinates":[23.416667,40.583333],"type":"Point"}
}