{
  "id": 2773843,
  "type": "Feature",
  "properties": {
    "tgn:hierarchy":[
        "tgn:2773843",
        "tgn:1000001",
        "tgn:7012149",
        "tgn:1002977",
        "tgn:7007240",
        "tgn:7029392"
    ],
    "tgn:id":2773843,
    "tgn:name":"Willow Cove",
    "tgn:placetype":[
        "aat:300132316"
    ]
},
  "bbox": [],
  "geometry": {"coordinates":[-81.5333,29.2833],"type":"Point"}
}