{
  "id": 2163131,
  "type": "Feature",
  "properties": {
    "tgn:hierarchy":[
        "tgn:2163131",
        "tgn:1000001",
        "tgn:2000774",
        "tgn:7012149",
        "tgn:7007255",
        "tgn:7029392"
    ],
    "tgn:id":2163131,
    "tgn:name":"Bennett Lake",
    "tgn:placetype":[
        "aat:300006191"
    ]
},
  "bbox": [],
  "geometry": {"coordinates":[-85.8333,38.0167],"type":"Point"}
}