{
  "id": 7278984,
  "type": "Feature",
  "properties": {
    "tgn:hierarchy":[
        "tgn:7278984",
        "tgn:7002464",
        "tgn:1000049",
        "tgn:1000002",
        "tgn:7029392"
    ],
    "tgn:id":7278984,
    "tgn:name":"Sajalla, Quebrada",
    "tgn:placetype":[
        "aat:300266554",
        "aat:300008699"
    ]
},
  "bbox": [],
  "geometry": {"coordinates":[-68.833333,-19.366667],"type":"Point"}
}