{
  "id": 2770423,
  "type": "Feature",
  "properties": {
    "tgn:hierarchy":[
        "tgn:2770423",
        "tgn:1000001",
        "tgn:7012149",
        "tgn:7007158",
        "tgn:2000253",
        "tgn:7029392"
    ],
    "tgn:id":2770423,
    "tgn:name":"Wild Horse Reservoir",
    "tgn:placetype":[
        "aat:300006191"
    ]
},
  "bbox": [],
  "geometry": {"coordinates":[-104.0333,40.7167],"type":"Point"}
}