<<<<<<< HEAD
{
  "id": 7115229,
  "type": "Feature",
  "properties": {
    "tgn:hierarchy":[
        "tgn:7115229",
        "tgn:1000003",
        "tgn:7003688",
        "tgn:7000084",
        "tgn:7029392"
    ],
    "tgn:id":7115229,
    "tgn:name":"Pahlhude",
    "tgn:placetype":[
        "aat:300008347"
    ]
},
  "bbox": [],
  "geometry": {"coordinates":[9.3,54.266667],"type":"Point"}
}
=======
{"geometry":{"type":"Point","coordinates":[9.300000,54.266667]},"type":"Feature","properties":{"hierarchy":["tgn:7115229","tgn:1000003","tgn:7003688","tgn:7000084","tgn:7029392"],"placetype":["aat:300008347"],"id":7115229,"name:xx":"Pahlhude"}}
>>>>>>> 03f74aca74312dbeaf24d7e61306dd6a786dc3d0
