{
  "id": 2107948,
  "type": "Feature",
  "properties": {
    "tgn:hierarchy":[
        "tgn:2107948",
        "tgn:1000001",
        "tgn:7012149",
        "tgn:2001995",
        "tgn:7007826",
        "tgn:7029392"
    ],
    "tgn:id":2107948,
    "tgn:name":"Tampico",
    "tgn:placetype":[
        "aat:300387016"
    ]
},
  "bbox": [],
  "geometry": {"coordinates":[-100.7667,34.4667],"type":"Point"}
}