{
  "id": 2606579,
  "type": "Feature",
  "properties": {
    "tgn:hierarchy":[
        "tgn:2606579",
        "tgn:1000001",
        "tgn:7012149",
        "tgn:2002075",
        "tgn:7007826",
        "tgn:7029392"
    ],
    "tgn:id":2606579,
    "tgn:name":"Ramirez Creek",
    "tgn:placetype":[
        "aat:300008706"
    ]
},
  "bbox": [],
  "geometry": {"coordinates":[-99.0167,26.45],"type":"Point"}
}