{
  "id": 2495573,
  "type": "Feature",
  "properties": {
    "tgn:hierarchy":[
        "tgn:2495573",
        "tgn:1000001",
        "tgn:7012149",
        "tgn:7029392"
    ],
    "tgn:id":2495573,
    "tgn:name":"Masa Knob",
    "tgn:placetype":[
        "aat:300008798"
    ]
},
  "bbox": [],
  "geometry": {"coordinates":[-83.3667,35.6333],"type":"Point"}
}