<<<<<<< HEAD
{
  "id": 2150217,
  "type": "Feature",
  "properties": {
    "tgn:hierarchy":[
        "tgn:2150217",
        "tgn:7006450",
        "tgn:1000001",
        "tgn:7012149",
        "tgn:2000088",
        "tgn:7029392"
    ],
    "tgn:id":2150217,
    "tgn:name":"Basargin, Mount",
    "tgn:placetype":[
        "aat:300008798"
    ]
},
  "bbox": [],
  "geometry": {"coordinates":[-132.2167,56.7167],"type":"Point"}
}
=======
{"geometry":{"type":"Point","coordinates":[-132.216700,56.716700]},"type":"Feature","properties":{"hierarchy":["tgn:2150217","tgn:7006450","tgn:1000001","tgn:7012149","tgn:2000088","tgn:7029392"],"placetype":["aat:300008798"],"id":2150217,"name:xx":"Basargin, Mount"}}
>>>>>>> 03f74aca74312dbeaf24d7e61306dd6a786dc3d0
