<<<<<<< HEAD
{
  "id": 2408304,
  "type": "Feature",
  "properties": {
    "tgn:hierarchy":[
        "tgn:2408304",
        "tgn:1000001",
        "tgn:7012149",
        "tgn:2001851",
        "tgn:7007825",
        "tgn:7029392"
    ],
    "tgn:id":2408304,
    "tgn:name":"Huskycamp Branch",
    "tgn:placetype":[
        "aat:300008699"
    ]
},
  "bbox": [],
  "geometry": {"coordinates":[-83.15,35.8167],"type":"Point"}
}
=======
{"geometry":{"type":"Point","coordinates":[-83.150000,35.816700]},"type":"Feature","properties":{"hierarchy":["tgn:2408304","tgn:1000001","tgn:7012149","tgn:2001851","tgn:7007825","tgn:7029392"],"placetype":["aat:300008699"],"id":2408304,"name:xx":"Huskycamp Branch"}}
>>>>>>> 03f74aca74312dbeaf24d7e61306dd6a786dc3d0
