{
  "id": 2521555,
  "type": "Feature",
  "properties": {
    "tgn:hierarchy":[
        "tgn:2521555",
        "tgn:1000001",
        "tgn:7012149",
        "tgn:7019676",
        "tgn:7007566",
        "tgn:7029392"
    ],
    "tgn:id":2521555,
    "tgn:name":"Montoso, Cerro",
    "tgn:placetype":[
        "aat:300008798"
    ]
},
  "bbox": [],
  "geometry": {"coordinates":[-107.3333,35.4667],"type":"Point"}
}