{
  "id": 2002581,
  "type": "Feature",
  "properties": {
    "tgn:hierarchy":[
        "tgn:2002581",
        "tgn:7002659",
        "tgn:1000001",
        "tgn:2000016",
        "tgn:7012149",
        "tgn:7029392"
    ],
    "tgn:id":2002581,
    "tgn:name":"Barton",
    "tgn:placetype":[
        "aat:300008347"
    ]
},
  "bbox": [],
  "geometry": {"coordinates":[-87.8833,34.7333],"type":"Point"}
}