{
  "id": 7005146,
  "type": "Feature",
  "properties": {
    "tgn:hierarchy":[
        "tgn:7005146",
        "tgn:7003171",
        "tgn:1000003",
        "tgn:7003125",
        "tgn:1000080",
        "tgn:7029392"
    ],
    "tgn:id":7005146,
    "tgn:name":"Montecastrilli",
    "tgn:placetype":[
        "aat:300008347"
    ]
},
  "bbox": [],
  "geometry": {"coordinates":[12.483333,42.65],"type":"Point"}
}