{
  "id": 2014290,
  "type": "Feature",
  "properties": {
    "tgn:hierarchy":[
        "tgn:2014290",
        "tgn:1000001",
        "tgn:7012149",
        "tgn:7007157",
        "tgn:1002857",
        "tgn:7029392"
    ],
    "tgn:id":2014290,
    "tgn:name":"Sleepy Hollow",
    "tgn:placetype":[
        "aat:300008347"
    ]
},
  "bbox": [],
  "geometry": {"coordinates":[-117.7667,33.9333],"type":"Point"}
}