{
  "id": 7265064,
  "type": "Feature",
  "properties": {
    "tgn:hierarchy":[
        "tgn:7265064",
        "tgn:1000003",
        "tgn:7003624",
        "tgn:7016845",
        "tgn:7029392"
    ],
    "tgn:id":7265064,
    "tgn:name:nl":"Looikensakker",
    "tgn:placetype":[
        "aat:300387200"
    ]
},
  "bbox": [],
  "geometry": {"coordinates":[4.366667,51.533333],"type":"Point"}
}