{
  "id": 2657044,
  "type": "Feature",
  "properties": {
    "tgn:hierarchy":[
        "tgn:2657044",
        "tgn:2001423",
        "tgn:1000001",
        "tgn:7012149",
        "tgn:7007564",
        "tgn:7029392"
    ],
    "tgn:id":2657044,
    "tgn:name":"Sheep Mountain",
    "tgn:placetype":[
        "aat:300008798"
    ]
},
  "bbox": [],
  "geometry": {"coordinates":[-71.1667,43.7833],"type":"Point"}
}