{
  "id": 7472391,
  "type": "Feature",
  "properties": {
    "tgn:hierarchy":[
        "tgn:7472391",
        "tgn:7001010",
        "tgn:1000004",
        "tgn:1000141",
        "tgn:7029392"
    ],
    "tgn:id":7472391,
    "tgn:name":"Banxia",
    "tgn:placetype":[
        "aat:300008347"
    ]
},
  "bbox": [],
  "geometry": {"coordinates":[121.656898,24.177923],"type":"Point"}
}