<<<<<<< HEAD
{
  "id": 7472391,
  "type": "Feature",
  "properties": {
    "tgn:hierarchy":[
        "tgn:7472391",
        "tgn:7001010",
        "tgn:1000004",
        "tgn:1000141",
        "tgn:7029392"
    ],
    "tgn:id":7472391,
    "tgn:name":"Banxia",
    "tgn:placetype":[
        "aat:300008347"
    ]
},
  "bbox": [],
  "geometry": {"coordinates":[121.656898,24.177923],"type":"Point"}
}
=======
{"geometry":{"type":"Point","coordinates":[121.656898,24.177923]},"type":"Feature","properties":{"hierarchy":["tgn:7472391","tgn:7001010","tgn:1000004","tgn:1000141","tgn:7029392"],"placetype":["aat:300008347"],"id":7472391,"name:xx":"Banxia"}}
>>>>>>> 03f74aca74312dbeaf24d7e61306dd6a786dc3d0
