{
  "id": 7213005,
  "type": "Feature",
  "properties": {
    "tgn:hierarchy":[
        "tgn:7213005",
        "tgn:1000003",
        "tgn:7003677",
        "tgn:7000084",
        "tgn:7029392"
    ],
    "tgn:id":7213005,
    "tgn:name":"Haltepunkt Bocketal",
    "tgn:placetype":[
        "aat:300007783"
    ]
},
  "bbox": [],
  "geometry": {"coordinates":[7.733333,52.25],"type":"Point"}
}