<<<<<<< HEAD
{
  "id": 2761228,
  "type": "Feature",
  "properties": {
    "tgn:hierarchy":[
        "tgn:2761228",
        "tgn:1000001",
        "tgn:7006451",
        "tgn:7012149",
        "tgn:2000099",
        "tgn:7029392"
    ],
    "tgn:id":2761228,
    "tgn:name":"West Long Hollow Tank",
    "tgn:placetype":[
        "aat:300006191"
    ]
},
  "bbox": [],
  "geometry": {"coordinates":[-110.4333,34.4167],"type":"Point"}
}
=======
{"geometry":{"type":"Point","coordinates":[-110.433300,34.416700]},"type":"Feature","properties":{"hierarchy":["tgn:2761228","tgn:1000001","tgn:7006451","tgn:7012149","tgn:2000099","tgn:7029392"],"placetype":["aat:300006191"],"id":2761228,"name:xx":"West Long Hollow Tank"}}
>>>>>>> 03f74aca74312dbeaf24d7e61306dd6a786dc3d0
