{
  "id": 2445975,
  "type": "Feature",
  "properties": {
    "tgn:hierarchy":[
        "tgn:2445975",
        "tgn:1000001",
        "tgn:1002310",
        "tgn:7012149",
        "tgn:7007710",
        "tgn:7029392"
    ],
    "tgn:id":2445975,
    "tgn:name":"Letort Spring",
    "tgn:placetype":[
        "aat:300008697"
    ]
},
  "bbox": [],
  "geometry": {"coordinates":[-77.1833,40.1667],"type":"Point"}
}