{
  "id": 2597978,
  "type": "Feature",
  "properties": {
    "tgn:hierarchy":[
        "tgn:2597978",
        "tgn:1000001",
        "tgn:7012149",
        "tgn:2001152",
        "tgn:7007522",
        "tgn:7029392"
    ],
    "tgn:id":2597978,
    "tgn:name":"Prentiss Mound",
    "tgn:placetype":[
        "aat:300008798"
    ]
},
  "bbox": [],
  "geometry": {"coordinates":[-90.6167,33.2833],"type":"Point"}
}