{
  "id": 2117644,
  "type": "Feature",
  "properties": {
    "tgn:hierarchy":[
        "tgn:2117644",
        "tgn:1000001",
        "tgn:7012149",
        "tgn:2002288",
        "tgn:7013961",
        "tgn:7029392"
    ],
    "tgn:id":2117644,
    "tgn:name":"Caddell",
    "tgn:placetype":[
        "aat:300387016"
    ]
},
  "bbox": [],
  "geometry": {"coordinates":[-79.65,39.45],"type":"Point"}
}