{
  "id": 2086625,
  "type": "Feature",
  "properties": {
    "tgn:hierarchy":[
        "tgn:2086625",
        "tgn:1000001",
        "tgn:1002310",
        "tgn:7012149",
        "tgn:7007710",
        "tgn:7029392"
    ],
    "tgn:id":2086625,
    "tgn:name":"Brandtsville",
    "tgn:placetype":[
        "aat:300008347",
        "aat:300387210"
    ]
},
  "bbox": [],
  "geometry": {"coordinates":[-77.05,40.1333],"type":"Point"}
}