{
  "id": 2518908,
  "type": "Feature",
  "properties": {
    "tgn:hierarchy":[
        "tgn:2518908",
        "tgn:1000001",
        "tgn:7012149",
        "tgn:2001442",
        "tgn:7007566",
        "tgn:7029392"
    ],
    "tgn:id":2518908,
    "tgn:name":"Mitten Bar Spring",
    "tgn:placetype":[
        "aat:300008697"
    ]
},
  "bbox": [],
  "geometry": {"coordinates":[-105.35,33.5667],"type":"Point"}
}