<<<<<<< HEAD
{
  "id": 7357437,
  "type": "Feature",
  "properties": {
    "tgn:hierarchy":[
        "tgn:7357437",
        "tgn:7005581",
        "tgn:1000001",
        "tgn:7005560",
        "tgn:7029392"
    ],
    "tgn:id":7357437,
    "tgn:name":"Ejido El Puerto de Pintas",
    "tgn:placetype":[
        "aat:300008347"
    ]
},
  "bbox": [],
  "geometry": {"coordinates":[-105.216667,27.933333],"type":"Point"}
}
=======
{"geometry":{"type":"Point","coordinates":[-105.216667,27.933333]},"type":"Feature","properties":{"hierarchy":["tgn:7357437","tgn:7005581","tgn:1000001","tgn:7005560","tgn:7029392"],"placetype":["aat:300008347"],"id":7357437,"name:xx":"Ejido El Puerto de Pintas"}}
>>>>>>> 03f74aca74312dbeaf24d7e61306dd6a786dc3d0
