<<<<<<< HEAD
{
  "id": 7363428,
  "type": "Feature",
  "properties": {
    "tgn:hierarchy":[
        "tgn:7363428",
        "tgn:1001853",
        "tgn:1000001",
        "tgn:7005560",
        "tgn:7029392"
    ],
    "tgn:id":7363428,
    "tgn:name":"El \u00c1lamo",
    "tgn:placetype":[
        "aat:300008347"
    ]
},
  "bbox": [],
  "geometry": {"coordinates":[-101.05,28.95],"type":"Point"}
}
=======
{"geometry":{"type":"Point","coordinates":[-101.050000,28.950000]},"type":"Feature","properties":{"hierarchy":["tgn:7363428","tgn:1001853","tgn:1000001","tgn:7005560","tgn:7029392"],"placetype":["aat:300008347"],"id":7363428,"name:xx":"El \u00c1lamo"}}
>>>>>>> 03f74aca74312dbeaf24d7e61306dd6a786dc3d0
