{
  "id": 2168961,
  "type": "Feature",
  "properties": {
    "tgn:hierarchy":[
        "tgn:2168961",
        "tgn:1000001",
        "tgn:7012149",
        "tgn:2000484",
        "tgn:7007250",
        "tgn:7029392"
    ],
    "tgn:id":2168961,
    "tgn:name":"Big Island",
    "tgn:placetype":[
        "aat:300008791"
    ]
},
  "bbox": [],
  "geometry": {"coordinates":[-111.8667,43.85],"type":"Point"}
}