{
  "id": 2270558,
  "type": "Feature",
  "properties": {
    "tgn:hierarchy":[
        "tgn:2270558",
        "tgn:1000001",
        "tgn:7012149",
        "tgn:7007157",
        "tgn:1002894",
        "tgn:7029392"
    ],
    "tgn:id":2270558,
    "tgn:name":"Crystal Peak",
    "tgn:placetype":[
        "aat:300008798"
    ]
},
  "bbox": [],
  "geometry": {"coordinates":[-120.0833,39.55],"type":"Point"}
}