{
  "id": 7311736,
  "type": "Feature",
  "properties": {
    "tgn:hierarchy":[
        "tgn:7311736",
        "tgn:1001695",
        "tgn:1000049",
        "tgn:1000002",
        "tgn:7029392"
    ],
    "tgn:id":7311736,
    "tgn:name":"Las Palmas, Estero",
    "tgn:placetype":[
        "aat:300008699"
    ]
},
  "bbox": [],
  "geometry": {"coordinates":[-71.566667,-34.85],"type":"Point"}
}