{
  "id": 7354734,
  "type": "Feature",
  "properties": {
    "tgn:hierarchy":[
        "tgn:7354734",
        "tgn:7005581",
        "tgn:1000001",
        "tgn:7005560",
        "tgn:7029392"
    ],
    "tgn:id":7354734,
    "tgn:name":"Charco del Pinole",
    "tgn:placetype":[
        "aat:300008347"
    ]
},
  "bbox": [],
  "geometry": {"coordinates":[-108.633333,28.033333],"type":"Point"}
}