<<<<<<< HEAD
{
  "id": 2762669,
  "type": "Feature",
  "properties": {
    "tgn:hierarchy":[
        "tgn:2762669",
        "tgn:1000001",
        "tgn:7012149",
        "tgn:2001665",
        "tgn:7007707",
        "tgn:7029392"
    ],
    "tgn:id":2762669,
    "tgn:name":"Wester Creek",
    "tgn:placetype":[
        "aat:300008706"
    ]
},
  "bbox": [],
  "geometry": {"coordinates":[-97.15,33.7833],"type":"Point"}
}
=======
{"geometry":{"type":"Point","coordinates":[-97.150000,33.783300]},"type":"Feature","properties":{"hierarchy":["tgn:2762669","tgn:1000001","tgn:7012149","tgn:2001665","tgn:7007707","tgn:7029392"],"placetype":["aat:300008706"],"id":2762669,"name:xx":"Wester Creek"}}
>>>>>>> 03f74aca74312dbeaf24d7e61306dd6a786dc3d0
