{
  "id": 2130245,
  "type": "Feature",
  "properties": {
    "tgn:hierarchy":[
        "tgn:2130245",
        "tgn:1000001",
        "tgn:2001411",
        "tgn:7012149",
        "tgn:7007526",
        "tgn:7029392"
    ],
    "tgn:id":2130245,
    "tgn:name":"Allen Spring",
    "tgn:placetype":[
        "aat:300008697"
    ]
},
  "bbox": [],
  "geometry": {"coordinates":[-116.2833,41.5167],"type":"Point"}
}