{
  "id": 2652580,
  "type": "Feature",
  "properties": {
    "tgn:hierarchy":[
        "tgn:2652580",
        "tgn:1000001",
        "tgn:7012149",
        "tgn:2001288",
        "tgn:7007524",
        "tgn:7029392"
    ],
    "tgn:id":2652580,
    "tgn:name":"Sentinel Peak",
    "tgn:placetype":[
        "aat:300008798"
    ]
},
  "bbox": [],
  "geometry": {"coordinates":[-111.4167,44.9667],"type":"Point"}
}