{
  "id": 2497190,
  "type": "Feature",
  "properties": {
    "tgn:hierarchy":[
        "tgn:2497190",
        "tgn:1000001",
        "tgn:7006451",
        "tgn:2000095",
        "tgn:7012149",
        "tgn:7029392"
    ],
    "tgn:id":2497190,
    "tgn:name":"Maverick Hill",
    "tgn:placetype":[
        "aat:300008798"
    ]
},
  "bbox": [],
  "geometry": {"coordinates":[-109.05,33.0167],"type":"Point"}
}