{
  "id": 2697812,
  "type": "Feature",
  "properties": {
    "tgn:hierarchy":[
        "tgn:2697812",
        "tgn:1000001",
        "tgn:2001260",
        "tgn:7012149",
        "tgn:7007524",
        "tgn:7029392"
    ],
    "tgn:id":2697812,
    "tgn:name":"Storm Peak",
    "tgn:placetype":[
        "aat:300008798"
    ]
},
  "bbox": [],
  "geometry": {"coordinates":[-112.8333,45.55],"type":"Point"}
}