{
  "id": 1113548,
  "type": "Feature",
  "properties": {
    "tgn:hierarchy":[
        "tgn:1113548",
        "tgn:1000004",
        "tgn:1001388",
        "tgn:1000135",
        "tgn:7029392"
    ],
    "tgn:id":1113548,
    "tgn:name":"Ormoc Bay",
    "tgn:placetype":[
        "aat:300132316"
    ]
},
  "bbox": [],
  "geometry": {"coordinates":[124.5833,10.9667],"type":"Point"}
}