{
  "id": 2755435,
  "type": "Feature",
  "properties": {
    "tgn:hierarchy":[
        "tgn:2755435",
        "tgn:1000001",
        "tgn:7012149",
        "tgn:7007710",
        "tgn:7029392"
    ],
    "tgn:id":2755435,
    "tgn:name":"Webier Creek",
    "tgn:placetype":[
        "aat:300008706"
    ]
},
  "bbox": [],
  "geometry": {"coordinates":[-76.8333,41.75],"type":"Point"}
}