{
  "id": 2644551,
  "type": "Feature",
  "properties": {
    "tgn:hierarchy":[
        "tgn:2644551",
        "tgn:1000001",
        "tgn:7012149",
        "tgn:2002371",
        "tgn:7007923",
        "tgn:7029392"
    ],
    "tgn:id":2644551,
    "tgn:name":"Sarcophagus Butte",
    "tgn:placetype":[
        "aat:300008798"
    ]
},
  "bbox": [],
  "geometry": {"coordinates":[-107.6167,42.8167],"type":"Point"}
}