{
  "id": 7499751,
  "type": "Feature",
  "properties": {
    "tgn:hierarchy":[
        "tgn:7499751",
        "tgn:1000004",
        "tgn:7492971",
        "tgn:1000141",
        "tgn:7029392"
    ],
    "tgn:id":7499751,
    "tgn:name":"Xinxing Guoxiao",
    "tgn:placetype":[
        "aat:300006495"
    ]
},
  "bbox": [],
  "geometry": {"coordinates":[120.459119,22.57164],"type":"Point"}
}