{
  "id": 7550263,
  "type": "Feature",
  "properties": {
    "tgn:hierarchy":[
        "tgn:7550263",
        "tgn:1000004",
        "tgn:7000198",
        "tgn:1001578",
        "tgn:7029392"
    ],
    "tgn:id":7550263,
    "tgn:name:en":"Chandras\u0101dhub\u0101ri",
    "tgn:placetype":[
        "aat:300008347"
    ]
},
  "bbox": [],
  "geometry": {"coordinates":[91.51,23.807474],"type":"Point"}
}