{
  "id": 2519056,
  "type": "Feature",
  "properties": {
    "tgn:hierarchy":[
        "tgn:2519056",
        "tgn:1000001",
        "tgn:7012149",
        "tgn:1002397",
        "tgn:7007568",
        "tgn:7029392"
    ],
    "tgn:id":2519056,
    "tgn:name":"Moat Vly",
    "tgn:placetype":[
        "aat:300008905"
    ]
},
  "bbox": [],
  "geometry": {"coordinates":[-74.2833,43.1833],"type":"Point"}
}