{
  "id": 7545199,
  "type": "Feature",
  "properties": {
    "tgn:hierarchy":[
        "tgn:7545199",
        "tgn:1000004",
        "tgn:7000198",
        "tgn:1001894",
        "tgn:7029392"
    ],
    "tgn:id":7545199,
    "tgn:name:en":"Bargawa",
    "tgn:placetype":[
        "aat:300008347"
    ]
},
  "bbox": [],
  "geometry": {"coordinates":[82.456342,24.195271],"type":"Point"}
}