{
  "id": 2562919,
  "type": "Feature",
  "properties": {
    "tgn:hierarchy":[
        "tgn:2562919",
        "tgn:1000001",
        "tgn:2000469",
        "tgn:7012149",
        "tgn:7007250",
        "tgn:7029392"
    ],
    "tgn:id":2562919,
    "tgn:name":"Oviatt Creek",
    "tgn:placetype":[
        "aat:300008706"
    ]
},
  "bbox": [],
  "geometry": {"coordinates":[-116.2833,46.7833],"type":"Point"}
}