{
  "id": 2724569,
  "type": "Feature",
  "properties": {
    "tgn:hierarchy":[
        "tgn:2724569",
        "tgn:1000001",
        "tgn:7012149",
        "tgn:2001494",
        "tgn:7007709",
        "tgn:7029392"
    ],
    "tgn:id":2724569,
    "tgn:name":"Tomahawk Creek",
    "tgn:placetype":[
        "aat:300008706"
    ]
},
  "bbox": [],
  "geometry": {"coordinates":[-80.3667,36.1167],"type":"Point"}
}