{
  "id": 7336021,
  "type": "Feature",
  "properties": {
    "tgn:hierarchy":[
        "tgn:7336021",
        "tgn:7002758",
        "tgn:7002821",
        "tgn:1000003",
        "tgn:1000095",
        "tgn:7029392"
    ],
    "tgn:id":7336021,
    "tgn:name":"Gabia la Grande",
    "tgn:placetype":[
        "aat:300008347"
    ]
},
  "bbox": [],
  "geometry": {"coordinates":[-3.666667,37.133333],"type":"Point"}
}