{
  "id": 7269391,
  "type": "Feature",
  "properties": {
    "tgn:concordances":{
        "gn:id":"2748355"
    },
    "tgn:hierarchy":[
        "tgn:7269391",
        "tgn:1000003",
        "tgn:7003626",
        "tgn:7016845",
        "tgn:7029392"
    ],
    "tgn:id":7269391,
    "tgn:name:nl":"Raarhoek",
    "tgn:placetype":[
        "aat:300008347"
    ]
},
  "bbox": [],
  "geometry": {"coordinates":[6.283333,52.416667],"type":"Point"}
}