{
  "id": 2786359,
  "type": "Feature",
  "properties": {
    "tgn:hierarchy":[
        "tgn:2786359",
        "tgn:1000001",
        "tgn:2001431",
        "tgn:7012149",
        "tgn:7007566",
        "tgn:7029392"
    ],
    "tgn:id":2786359,
    "tgn:name":"Youngs Tank",
    "tgn:placetype":[
        "aat:300006191"
    ]
},
  "bbox": [],
  "geometry": {"coordinates":[-107.6833,35.3167],"type":"Point"}
}