<<<<<<< HEAD
{
  "id": 7474640,
  "type": "Feature",
  "properties": {
    "tgn:hierarchy":[
        "tgn:7474640",
        "tgn:1000004",
        "tgn:7467799",
        "tgn:1000141",
        "tgn:7029392"
    ],
    "tgn:id":7474640,
    "tgn:name":"Nantanqian",
    "tgn:placetype":[
        "aat:300008347"
    ]
},
  "bbox": [],
  "geometry": {"coordinates":[120.351115,23.834398],"type":"Point"}
}
=======
{"geometry":{"type":"Point","coordinates":[120.351115,23.834398]},"type":"Feature","properties":{"hierarchy":["tgn:7474640","tgn:1000004","tgn:7467799","tgn:1000141","tgn:7029392"],"placetype":["aat:300008347"],"id":7474640,"name:xx":"Nantanqian"}}
>>>>>>> 03f74aca74312dbeaf24d7e61306dd6a786dc3d0
