{
  "id": 2067896,
  "type": "Feature",
  "properties": {
    "tgn:hierarchy":[
        "tgn:2067896",
        "tgn:1000001",
        "tgn:1002245",
        "tgn:7012149",
        "tgn:7007568",
        "tgn:7029392"
    ],
    "tgn:id":2067896,
    "tgn:name":"Axeville",
    "tgn:placetype":[
        "aat:300008347",
        "aat:300387210"
    ]
},
  "bbox": [],
  "geometry": {"coordinates":[-78.95,42.2333],"type":"Point"}
}