{
  "id": 7346036,
  "type": "Feature",
  "properties": {
    "tgn:hierarchy":[
        "tgn:7346036",
        "tgn:1001439",
        "tgn:1000003",
        "tgn:7002797",
        "tgn:1000095",
        "tgn:7029392"
    ],
    "tgn:id":7346036,
    "tgn:name":"Barranda",
    "tgn:placetype":[
        "aat:300008347"
    ]
},
  "bbox": [],
  "geometry": {"coordinates":[-1.966667,38.05],"type":"Point"}
}