{
  "id": 2157579,
  "type": "Feature",
  "properties": {
    "tgn:hierarchy":[
        "tgn:2157579",
        "tgn:1000001",
        "tgn:1002295",
        "tgn:7012149",
        "tgn:7007706",
        "tgn:7029392"
    ],
    "tgn:id":2157579,
    "tgn:name":"Beaver Creek State Forest",
    "tgn:placetype":[
        "aat:300008863"
    ]
},
  "bbox": [],
  "geometry": {"coordinates":[-80.6667,40.7333],"type":"Point"}
}