<<<<<<< HEAD
{
  "id": 2157579,
  "type": "Feature",
  "properties": {
    "tgn:hierarchy":[
        "tgn:2157579",
        "tgn:1000001",
        "tgn:1002295",
        "tgn:7012149",
        "tgn:7007706",
        "tgn:7029392"
    ],
    "tgn:id":2157579,
    "tgn:name":"Beaver Creek State Forest",
    "tgn:placetype":[
        "aat:300008863"
    ]
},
  "bbox": [],
  "geometry": {"coordinates":[-80.6667,40.7333],"type":"Point"}
}
=======
{"geometry":{"type":"Point","coordinates":[-80.666700,40.733300]},"type":"Feature","properties":{"hierarchy":["tgn:2157579","tgn:1000001","tgn:1002295","tgn:7012149","tgn:7007706","tgn:7029392"],"placetype":["aat:300008863"],"id":2157579,"name:xx":"Beaver Creek State Forest"}}
>>>>>>> 03f74aca74312dbeaf24d7e61306dd6a786dc3d0
