{
  "id": 1049838,
  "type": "Feature",
  "properties": {
    "tgn:hierarchy":[
        "tgn:1049838",
        "tgn:1000882",
        "tgn:1000003",
        "tgn:1000090",
        "tgn:7029392"
    ],
    "tgn:id":1049838,
    "tgn:name":"Montemor",
    "tgn:placetype":[
        "aat:300008347"
    ]
},
  "bbox": [],
  "geometry": {"coordinates":[-9.201,38.82],"type":"Point"}
}