{
  "id": 1113676,
  "type": "Feature",
  "properties": {
    "tgn:hierarchy":[
        "tgn:1113676",
        "tgn:7008532",
        "tgn:7002443",
        "tgn:1000003",
        "tgn:7008591",
        "tgn:7029392"
    ],
    "tgn:id":1113676,
    "tgn:name:en":"Red Wharf Bay",
    "tgn:placetype":[
        "aat:300132316"
    ]
},
  "bbox": [],
  "geometry": {"coordinates":[-4.166667,53.333333],"type":"Point"}
}