{
  "id": 2191619,
  "type": "Feature",
  "properties": {
    "tgn:hierarchy":[
        "tgn:2191619",
        "tgn:1000001",
        "tgn:7012149",
        "tgn:2001750",
        "tgn:7007712",
        "tgn:7029392"
    ],
    "tgn:id":2191619,
    "tgn:name":"Bradley Branch",
    "tgn:placetype":[
        "aat:300008699"
    ]
},
  "bbox": [],
  "geometry": {"coordinates":[-79.15,33.7167],"type":"Point"}
}