{
  "id": 2085273,
  "type": "Feature",
  "properties": {
    "tgn:hierarchy":[
        "tgn:2085273",
        "tgn:1000001",
        "tgn:7012149",
        "tgn:2001710",
        "tgn:7007708",
        "tgn:7029392"
    ],
    "tgn:id":2085273,
    "tgn:name":"Parkdale",
    "tgn:placetype":[
        "aat:300008347"
    ]
},
  "bbox": [],
  "geometry": {"coordinates":[-121.5833,45.5167],"type":"Point"}
}