<<<<<<< HEAD
{
  "id": 7023006,
  "type": "Feature",
  "properties": {
    "tgn:hierarchy":[
        "tgn:7023006",
        "tgn:1000001",
        "tgn:7012149",
        "tgn:7029392"
    ],
    "tgn:id":7023006,
    "tgn:name":"Giesky Creek",
    "tgn:placetype":[
        "aat:300008706"
    ]
},
  "bbox": [],
  "geometry": {"coordinates":[-83.6167,34.9667],"type":"Point"}
}
=======
{"geometry":{"type":"Point","coordinates":[-83.616700,34.966700]},"type":"Feature","properties":{"hierarchy":["tgn:7023006","tgn:1000001","tgn:7012149","tgn:7029392"],"placetype":["aat:300008706"],"id":7023006,"name:xx":"Giesky Creek"}}
>>>>>>> 03f74aca74312dbeaf24d7e61306dd6a786dc3d0
