{
  "id": 2554536,
  "type": "Feature",
  "properties": {
    "tgn:hierarchy":[
        "tgn:2554536",
        "tgn:1000001",
        "tgn:7012149",
        "tgn:2002118",
        "tgn:7007827",
        "tgn:7029392"
    ],
    "tgn:id":2554536,
    "tgn:name":"Oakland Place",
    "tgn:placetype":[
        "aat:300008347"
    ]
},
  "bbox": [],
  "geometry": {"coordinates":[-111.8833,40.7167],"type":"Point"}
}