{
  "id": 7174037,
  "type": "Feature",
  "properties": {
    "tgn:hierarchy":[
        "tgn:7174037",
        "tgn:1000003",
        "tgn:7003682",
        "tgn:7000084",
        "tgn:7029392"
    ],
    "tgn:id":7174037,
    "tgn:name":"Gr\u00fcn-Berg",
    "tgn:placetype":[
        "aat:300008777"
    ]
},
  "bbox": [],
  "geometry": {"coordinates":[7.883333,49.116667],"type":"Point"}
}