<<<<<<< HEAD
{
  "id": 7174037,
  "type": "Feature",
  "properties": {
    "tgn:hierarchy":[
        "tgn:7174037",
        "tgn:1000003",
        "tgn:7003682",
        "tgn:7000084",
        "tgn:7029392"
    ],
    "tgn:id":7174037,
    "tgn:name":"Gr\u00fcn-Berg",
    "tgn:placetype":[
        "aat:300008777"
    ]
},
  "bbox": [],
  "geometry": {"coordinates":[7.883333,49.116667],"type":"Point"}
}
=======
{"geometry":{"type":"Point","coordinates":[7.883333,49.116667]},"type":"Feature","properties":{"hierarchy":["tgn:7174037","tgn:1000003","tgn:7003682","tgn:7000084","tgn:7029392"],"placetype":["aat:300008777"],"id":7174037,"name:xx":"Gr\u00fcn-Berg"}}
>>>>>>> 03f74aca74312dbeaf24d7e61306dd6a786dc3d0
