{
  "id": 7227888,
  "type": "Feature",
  "properties": {
    "tgn:hierarchy":[
        "tgn:7227888",
        "tgn:7002725",
        "tgn:7002715",
        "tgn:1000003",
        "tgn:1000074",
        "tgn:7029392"
    ],
    "tgn:id":7227888,
    "tgn:name":"Leips\u00fddrion",
    "tgn:placetype":[
        "aat:300008347"
    ]
},
  "bbox": [],
  "geometry": {"coordinates":[22.948333,40.920833],"type":"Point"}
}