{
  "id": 7229211,
  "type": "Feature",
  "properties": {
    "tgn:hierarchy":[
        "tgn:7229211",
        "tgn:7002690",
        "tgn:7012056",
        "tgn:1000003",
        "tgn:1000074",
        "tgn:7029392"
    ],
    "tgn:id":7229211,
    "tgn:name":"Galang\u00e1dhos",
    "tgn:placetype":[
        "aat:300008347"
    ]
},
  "bbox": [],
  "geometry": {"coordinates":[24.133333,35.516667],"type":"Point"}
}