<<<<<<< HEAD
{
  "id": 7170126,
  "type": "Feature",
  "properties": {
    "tgn:hierarchy":[
        "tgn:7170126",
        "tgn:1000003",
        "tgn:7000094",
        "tgn:7000084",
        "tgn:7029392"
    ],
    "tgn:id":7170126,
    "tgn:name":"Hochbassin",
    "tgn:placetype":[
        "aat:300000206"
    ]
},
  "bbox": [],
  "geometry": {"coordinates":[13.466667,54.05],"type":"Point"}
}
=======
{"geometry":{"type":"Point","coordinates":[13.466667,54.050000]},"type":"Feature","properties":{"hierarchy":["tgn:7170126","tgn:1000003","tgn:7000094","tgn:7000084","tgn:7029392"],"placetype":["aat:300000206"],"id":7170126,"name:xx":"Hochbassin"}}
>>>>>>> 03f74aca74312dbeaf24d7e61306dd6a786dc3d0
