{
  "id": 1115577,
  "type": "Feature",
  "properties": {
    "tgn:hierarchy":[
        "tgn:1115577",
        "tgn:1000001",
        "tgn:1002410",
        "tgn:7012149",
        "tgn:7007565",
        "tgn:7029392"
    ],
    "tgn:id":1115577,
    "tgn:name":"Bells Lake",
    "tgn:placetype":[
        "aat:300008680"
    ]
},
  "bbox": [],
  "geometry": {"coordinates":[-75.05,39.75],"type":"Point"}
}