{
  "id": 2598394,
  "type": "Feature",
  "properties": {
    "tgn:hierarchy":[
        "tgn:2598394",
        "tgn:1000001",
        "tgn:7016172",
        "tgn:7012149",
        "tgn:2000131",
        "tgn:7029392"
    ],
    "tgn:id":2598394,
    "tgn:name":"Price Branch",
    "tgn:placetype":[
        "aat:300008699"
    ]
},
  "bbox": [],
  "geometry": {"coordinates":[-92.2833,34.4167],"type":"Point"}
}