{
  "id": 2637365,
  "type": "Feature",
  "properties": {
    "tgn:hierarchy":[
        "tgn:2637365",
        "tgn:1000001",
        "tgn:7012149",
        "tgn:2000738",
        "tgn:7007254",
        "tgn:7029392"
    ],
    "tgn:id":2637365,
    "tgn:name":"Saint Johns Creek",
    "tgn:placetype":[
        "aat:300008706"
    ]
},
  "bbox": [],
  "geometry": {"coordinates":[-97.8833,39.7167],"type":"Point"}
}