<<<<<<< HEAD
{
  "id": 2252858,
  "type": "Feature",
  "properties": {
    "tgn:hierarchy":[
        "tgn:2252858",
        "tgn:1000001",
        "tgn:7012149",
        "tgn:2000793",
        "tgn:7007255",
        "tgn:7029392"
    ],
    "tgn:id":2252858,
    "tgn:name":"Conoloway Creek",
    "tgn:placetype":[
        "aat:300008706"
    ]
},
  "bbox": [],
  "geometry": {"coordinates":[-86.2167,37.4],"type":"Point"}
}
=======
{"geometry":{"type":"Point","coordinates":[-86.216700,37.400000]},"type":"Feature","properties":{"hierarchy":["tgn:2252858","tgn:1000001","tgn:7012149","tgn:2000793","tgn:7007255","tgn:7029392"],"placetype":["aat:300008706"],"id":2252858,"name:xx":"Conoloway Creek"}}
>>>>>>> 03f74aca74312dbeaf24d7e61306dd6a786dc3d0
