{
  "id": 2522293,
  "type": "Feature",
  "properties": {
    "tgn:hierarchy":[
        "tgn:2522293",
        "tgn:1000001",
        "tgn:7012149",
        "tgn:2002354",
        "tgn:7007922",
        "tgn:7029392"
    ],
    "tgn:id":2522293,
    "tgn:name":"Moon Lake",
    "tgn:placetype":[
        "aat:300008680"
    ]
},
  "bbox": [],
  "geometry": {"coordinates":[-88.7833,44.8667],"type":"Point"}
}