{
  "id": 7495563,
  "type": "Feature",
  "properties": {
    "tgn:hierarchy":[
        "tgn:7495563",
        "tgn:1000004",
        "tgn:7001013",
        "tgn:1000141",
        "tgn:7029392"
    ],
    "tgn:id":7495563,
    "tgn:name":"Gengsheng Qiao",
    "tgn:placetype":[
        "aat:300007836"
    ]
},
  "bbox": [],
  "geometry": {"coordinates":[121.330979,24.835129],"type":"Point"}
}