{
  "id": 7247681,
  "type": "Feature",
  "properties": {
    "tgn:hierarchy":[
        "tgn:7247681",
        "tgn:7003456",
        "tgn:1000003",
        "tgn:1000063",
        "tgn:7018236",
        "tgn:7029392"
    ],
    "tgn:id":7247681,
    "tgn:name":"Duinberg",
    "tgn:placetype":[
        "aat:300008347"
    ]
},
  "bbox": [],
  "geometry": {"coordinates":[5.066667,51.266667],"type":"Point"}
}