{
  "id": 1051557,
  "type": "Feature",
  "properties": {
    "tgn:hierarchy":[
        "tgn:1051557",
        "tgn:1000004",
        "tgn:7011498",
        "tgn:7002435",
        "tgn:7029392"
    ],
    "tgn:id":1051557,
    "tgn:name":"Sharanbashknyazevo",
    "tgn:placetype":[
        "aat:300008347"
    ]
},
  "bbox": [],
  "geometry": {"coordinates":[54.1667,54.9833],"type":"Point"}
}