{
  "id": 7557378,
  "type": "Feature",
  "properties": {
    "tgn:hierarchy":[
        "tgn:7557378",
        "tgn:7001559",
        "tgn:7549039",
        "tgn:1000004",
        "tgn:7000198",
        "tgn:1001890",
        "tgn:7029392"
    ],
    "tgn:id":7557378,
    "tgn:name:en":"Pitti Island",
    "tgn:placetype":[
        "aat:300008791"
    ]
},
  "bbox": [],
  "geometry": {"coordinates":[73.616667,10.066667],"type":"Point"}
}