{
  "id": 2001353,
  "type": "Feature",
  "properties": {
    "tgn:hierarchy":[
        "tgn:2001353",
        "tgn:1000001",
        "tgn:7012149",
        "tgn:7007525",
        "tgn:7029392"
    ],
    "tgn:id":2001353,
    "tgn:name":"Grant",
    "tgn:placetype":[
        "aat:300387145",
        "aat:300000771"
    ]
},
  "bbox": [],
  "geometry": {"coordinates":[-101.7167,42.9167],"type":"Point"}
}