{
  "id": 2378345,
  "type": "Feature",
  "properties": {
    "tgn:hierarchy":[
        "tgn:2378345",
        "tgn:7002659",
        "tgn:1000001",
        "tgn:7012149",
        "tgn:2000041",
        "tgn:7029392"
    ],
    "tgn:id":2378345,
    "tgn:name":"Harris-Sweetwater Dewatering Area",
    "tgn:placetype":[
        "aat:300008905"
    ]
},
  "bbox": [],
  "geometry": {"coordinates":[-86.9667,34.6333],"type":"Point"}
}