{
  "id": 2151800,
  "type": "Feature",
  "properties": {
    "tgn:hierarchy":[
        "tgn:2151800",
        "tgn:1000001",
        "tgn:7012149",
        "tgn:2000233",
        "tgn:7007158",
        "tgn:7029392"
    ],
    "tgn:id":2151800,
    "tgn:name":"Battle Rock",
    "tgn:placetype":[
        "aat:300008798"
    ]
},
  "bbox": [],
  "geometry": {"coordinates":[-108.8167,37.3333],"type":"Point"}
}