<<<<<<< HEAD
{
  "id": 2151800,
  "type": "Feature",
  "properties": {
    "tgn:hierarchy":[
        "tgn:2151800",
        "tgn:1000001",
        "tgn:7012149",
        "tgn:2000233",
        "tgn:7007158",
        "tgn:7029392"
    ],
    "tgn:id":2151800,
    "tgn:name":"Battle Rock",
    "tgn:placetype":[
        "aat:300008798"
    ]
},
  "bbox": [],
  "geometry": {"coordinates":[-108.8167,37.3333],"type":"Point"}
}
=======
{"geometry":{"type":"Point","coordinates":[-108.816700,37.333300]},"type":"Feature","properties":{"hierarchy":["tgn:2151800","tgn:1000001","tgn:7012149","tgn:2000233","tgn:7007158","tgn:7029392"],"placetype":["aat:300008798"],"id":2151800,"name:xx":"Battle Rock"}}
>>>>>>> 03f74aca74312dbeaf24d7e61306dd6a786dc3d0
