{
  "id": 1037092,
  "type": "Feature",
  "properties": {
    "tgn:hierarchy":[
        "tgn:1037092",
        "tgn:1000003",
        "tgn:7000094",
        "tgn:7000084",
        "tgn:7029392"
    ],
    "tgn:id":1037092,
    "tgn:name":"Klink",
    "tgn:placetype":[
        "aat:300008347"
    ]
},
  "bbox": [],
  "geometry": {"coordinates":[12.616667,53.483333],"type":"Point"}
}