{
  "id": 2743548,
  "type": "Feature",
  "properties": {
    "tgn:hierarchy":[
        "tgn:2743548",
        "tgn:1000001",
        "tgn:7012149",
        "tgn:7007157",
        "tgn:1002684",
        "tgn:7029392"
    ],
    "tgn:id":2743548,
    "tgn:name":"Vasquez Knob",
    "tgn:placetype":[
        "aat:300008798"
    ]
},
  "bbox": [],
  "geometry": {"coordinates":[-121.75,36.4667],"type":"Point"}
}