{
  "id": 7508766,
  "type": "Feature",
  "properties": {
    "tgn:hierarchy":[
        "tgn:7508766",
        "tgn:1009227",
        "tgn:1000226",
        "tgn:7018437",
        "tgn:1000006",
        "tgn:7029392"
    ],
    "tgn:id":7508766,
    "tgn:name:en":"Waipori, Lake",
    "tgn:placetype":[
        "aat:300008680"
    ]
},
  "bbox": [],
  "geometry": {"coordinates":[170.116667,-45.966667],"type":"Point"}
}