{
  "id": 2667630,
  "type": "Feature",
  "properties": {
    "tgn:hierarchy":[
        "tgn:2667630",
        "tgn:1000001",
        "tgn:2001641",
        "tgn:7012149",
        "tgn:7007707",
        "tgn:7029392"
    ],
    "tgn:id":2667630,
    "tgn:name":"Skull Creek",
    "tgn:placetype":[
        "aat:300008706"
    ]
},
  "bbox": [],
  "geometry": {"coordinates":[-96.0667,35.9167],"type":"Point"}
}