{
  "id": 2498022,
  "type": "Feature",
  "properties": {
    "tgn:hierarchy":[
        "tgn:2498022",
        "tgn:7002659",
        "tgn:1000001",
        "tgn:7012149",
        "tgn:2000047",
        "tgn:7029392"
    ],
    "tgn:id":2498022,
    "tgn:name":"Mayo Branch",
    "tgn:placetype":[
        "aat:300008699"
    ]
},
  "bbox": [],
  "geometry": {"coordinates":[-86.1333,34.25],"type":"Point"}
}