{
  "id": 7084985,
  "type": "Feature",
  "properties": {
    "tgn:hierarchy":[
        "tgn:7084985",
        "tgn:7003669",
        "tgn:1000003",
        "tgn:7000084",
        "tgn:7029392"
    ],
    "tgn:id":7084985,
    "tgn:name":"Wildberg",
    "tgn:placetype":[
        "aat:300000206"
    ]
},
  "bbox": [],
  "geometry": {"coordinates":[11.266667,50.466667],"type":"Point"}
}