{
  "id": 7076559,
  "type": "Feature",
  "properties": {
    "tgn:hierarchy":[
        "tgn:7076559",
        "tgn:1000003",
        "tgn:7003677",
        "tgn:7000084",
        "tgn:7029392"
    ],
    "tgn:id":7076559,
    "tgn:name":"Talsperre Steinbach",
    "tgn:placetype":[
        "aat:300006191"
    ]
},
  "bbox": [],
  "geometry": {"coordinates":[6.833333,50.583333],"type":"Point"}
}