{
  "id": 2202116,
  "type": "Feature",
  "properties": {
    "tgn:hierarchy":[
        "tgn:2202116",
        "tgn:1000001",
        "tgn:7012149",
        "tgn:7007157",
        "tgn:1002957",
        "tgn:7029392"
    ],
    "tgn:id":2202116,
    "tgn:name":"Buck Lake",
    "tgn:placetype":[
        "aat:300006191"
    ]
},
  "bbox": [],
  "geometry": {"coordinates":[-119.7167,38.1667],"type":"Point"}
}