{
  "id": 7091178,
  "type": "Feature",
  "properties": {
    "tgn:hierarchy":[
        "tgn:7091178",
        "tgn:1000003",
        "tgn:7000094",
        "tgn:7000084",
        "tgn:7029392"
    ],
    "tgn:id":7091178,
    "tgn:name":"Varchentin",
    "tgn:placetype":[
        "aat:300008347"
    ]
},
  "bbox": [],
  "geometry": {"coordinates":[12.85,53.583333],"type":"Point"}
}