{
  "id": 7038315,
  "type": "Feature",
  "properties": {
    "tgn:hierarchy":[
        "tgn:7038315",
        "tgn:7003137",
        "tgn:1000003",
        "tgn:7003080",
        "tgn:1000080",
        "tgn:7029392"
    ],
    "tgn:id":7038315,
    "tgn:name":"Torrecane, Monte",
    "tgn:placetype":[
        "aat:300008795"
    ]
},
  "bbox": [],
  "geometry": {"coordinates":[13.133333,42.366667],"type":"Point"}
}