{
  "id": 1074095,
  "type": "Feature",
  "properties": {
    "tgn:hierarchy":[
        "tgn:1074095",
        "tgn:1000004",
        "tgn:7002087",
        "tgn:1000111",
        "tgn:7029392"
    ],
    "tgn:id":1074095,
    "tgn:name":"Zhoupo",
    "tgn:placetype":[
        "aat:300008347"
    ]
},
  "bbox": [],
  "geometry": {"coordinates":[104.0167,29.7833],"type":"Point"}
}