{
  "id": 7007653,
  "type": "Feature",
  "properties": {
    "tgn:hierarchy":[
        "tgn:7007653",
        "tgn:7010420",
        "tgn:1000003",
        "tgn:7002795",
        "tgn:1000095",
        "tgn:7029392"
    ],
    "tgn:id":7007653,
    "tgn:name":"San Lorenzo de El Escorial",
    "tgn:placetype":[
        "aat:300387273",
        "aat:300008347",
        "aat:300005135",
        "aat:300343603",
        "aat:300008372"
    ]
},
  "bbox": [],
  "geometry": {"coordinates":[-4.116667,40.583333],"type":"Point"}
}