{
  "id": 2110844,
  "type": "Feature",
  "properties": {
    "tgn:hierarchy":[
        "tgn:2110844",
        "tgn:2002137",
        "tgn:1000001",
        "tgn:7012149",
        "tgn:7007919",
        "tgn:7029392"
    ],
    "tgn:id":2110844,
    "tgn:name":"Buckingham Circle",
    "tgn:placetype":[
        "aat:300008347"
    ]
},
  "bbox": [],
  "geometry": {"coordinates":[-78.5167,38.0167],"type":"Point"}
}