{
  "id": 7187185,
  "type": "Feature",
  "properties": {
    "tgn:hierarchy":[
        "tgn:7187185",
        "tgn:7003692",
        "tgn:1000003",
        "tgn:7000084",
        "tgn:7029392"
    ],
    "tgn:id":7187185,
    "tgn:name":"Ernst",
    "tgn:placetype":[
        "aat:300000206"
    ]
},
  "bbox": [],
  "geometry": {"coordinates":[9.75,48.916667],"type":"Point"}
}