{
  "id": 2039147,
  "type": "Feature",
  "properties": {
    "tgn:hierarchy":[
        "tgn:2039147",
        "tgn:1000001",
        "tgn:2000773",
        "tgn:7012149",
        "tgn:7007255",
        "tgn:7029392"
    ],
    "tgn:id":2039147,
    "tgn:name":"Graysville",
    "tgn:placetype":[
        "aat:300008347",
        "aat:300387210"
    ]
},
  "bbox": [],
  "geometry": {"coordinates":[-86.2833,37.7667],"type":"Point"}
}