{
  "id": 2173148,
  "type": "Feature",
  "properties": {
    "tgn:hierarchy":[
        "tgn:2173148",
        "tgn:1000001",
        "tgn:7012149",
        "tgn:2001551",
        "tgn:7007709",
        "tgn:7029392"
    ],
    "tgn:id":2173148,
    "tgn:name":"Bingham Hill",
    "tgn:placetype":[
        "aat:300008798"
    ]
},
  "bbox": [],
  "geometry": {"coordinates":[-81.7333,36.2333],"type":"Point"}
}