{
  "id": 2088426,
  "type": "Feature",
  "properties": {
    "tgn:hierarchy":[
        "tgn:2088426",
        "tgn:1000001",
        "tgn:1002272",
        "tgn:7012149",
        "tgn:7007710",
        "tgn:7029392"
    ],
    "tgn:id":2088426,
    "tgn:name":"Fern",
    "tgn:placetype":[
        "aat:300008347"
    ]
},
  "bbox": [],
  "geometry": {"coordinates":[-79.5333,41.2833],"type":"Point"}
}