<<<<<<< HEAD
{
  "id": 7119978,
  "type": "Feature",
  "properties": {
    "tgn:hierarchy":[
        "tgn:7119978",
        "tgn:7003669",
        "tgn:1000003",
        "tgn:7000084",
        "tgn:7029392"
    ],
    "tgn:id":7119978,
    "tgn:name":"Ploier",
    "tgn:placetype":[
        "aat:300000206"
    ]
},
  "bbox": [],
  "geometry": {"coordinates":[12.516667,48.216667],"type":"Point"}
}
=======
{"geometry":{"type":"Point","coordinates":[12.516667,48.216667]},"type":"Feature","properties":{"hierarchy":["tgn:7119978","tgn:7003669","tgn:1000003","tgn:7000084","tgn:7029392"],"placetype":["aat:300000206"],"id":7119978,"name:xx":"Ploier"}}
>>>>>>> 03f74aca74312dbeaf24d7e61306dd6a786dc3d0
