{
  "id": 7236196,
  "type": "Feature",
  "properties": {
    "tgn:hierarchy":[
        "tgn:7236196",
        "tgn:7002707",
        "tgn:7002705",
        "tgn:1000003",
        "tgn:1000074",
        "tgn:7029392"
    ],
    "tgn:id":7236196,
    "tgn:name":"\u00c1gios St\u00e9fanos",
    "tgn:placetype":[
        "aat:300008347"
    ]
},
  "bbox": [],
  "geometry": {"coordinates":[20.55,39.55],"type":"Point"}
}