{
  "id": 2204089,
  "type": "Feature",
  "properties": {
    "tgn:hierarchy":[
        "tgn:2204089",
        "tgn:1000001",
        "tgn:2001431",
        "tgn:7012149",
        "tgn:7007566",
        "tgn:7029392"
    ],
    "tgn:id":2204089,
    "tgn:name":"Budville",
    "tgn:placetype":[
        "aat:300008347"
    ]
},
  "bbox": [],
  "geometry": {"coordinates":[-107.5167,35.0667],"type":"Point"}
}