{
  "id": 2340159,
  "type": "Feature",
  "properties": {
    "tgn:hierarchy":[
        "tgn:2340159",
        "tgn:1000001",
        "tgn:7012149",
        "tgn:7007157",
        "tgn:7014004",
        "tgn:7029392"
    ],
    "tgn:id":2340159,
    "tgn:name":"Fremont Spring",
    "tgn:placetype":[
        "aat:300008697"
    ]
},
  "bbox": [],
  "geometry": {"coordinates":[-120.0667,37.55],"type":"Point"}
}