{
  "id": 7021796,
  "type": "Feature",
  "properties": {
    "tgn:hierarchy":[
        "tgn:7021796",
        "tgn:1000001",
        "tgn:7012149",
        "tgn:2001764",
        "tgn:7007712",
        "tgn:7029392"
    ],
    "tgn:id":7021796,
    "tgn:name":"Goodwill Lake",
    "tgn:placetype":[
        "aat:300006191"
    ]
},
  "bbox": [],
  "geometry": {"coordinates":[-80.65,33.95],"type":"Point"}
}