{
  "id": 7455597,
  "type": "Feature",
  "properties": {
    "tgn:hierarchy":[
        "tgn:7455597",
        "tgn:7002444",
        "tgn:7008074",
        "tgn:1000003",
        "tgn:7008591",
        "tgn:7029392"
    ],
    "tgn:id":7455597,
    "tgn:name:en":"Castlefairn Water",
    "tgn:placetype":[
        "aat:300008699"
    ]
},
  "bbox": [],
  "geometry": {"coordinates":[-3.916667,55.183333],"type":"Point"}
}