{
  "id": 2304497,
  "type": "Feature",
  "properties": {
    "tgn:hierarchy":[
        "tgn:2304497",
        "tgn:1000001",
        "tgn:7012149",
        "tgn:7007158",
        "tgn:2000244",
        "tgn:7029392"
    ],
    "tgn:id":2304497,
    "tgn:name":"East Alder Creek",
    "tgn:placetype":[
        "aat:300008706"
    ]
},
  "bbox": [],
  "geometry": {"coordinates":[-106.65,37.75],"type":"Point"}
}