<<<<<<< HEAD
{
  "id": 2405415,
  "type": "Feature",
  "properties": {
    "tgn:hierarchy":[
        "tgn:2405415",
        "tgn:1000001",
        "tgn:2001737",
        "tgn:7012149",
        "tgn:7007712",
        "tgn:7029392"
    ],
    "tgn:id":2405415,
    "tgn:name":"Hugh Creek",
    "tgn:placetype":[
        "aat:300008706"
    ]
},
  "bbox": [],
  "geometry": {"coordinates":[-79.8167,34.6167],"type":"Point"}
}
=======
{"geometry":{"type":"Point","coordinates":[-79.816700,34.616700]},"type":"Feature","properties":{"hierarchy":["tgn:2405415","tgn:1000001","tgn:2001737","tgn:7012149","tgn:7007712","tgn:7029392"],"placetype":["aat:300008706"],"id":2405415,"name:xx":"Hugh Creek"}}
>>>>>>> 03f74aca74312dbeaf24d7e61306dd6a786dc3d0
