{
  "id": 2433277,
  "type": "Feature",
  "properties": {
    "tgn:hierarchy":[
        "tgn:2433277",
        "tgn:1000001",
        "tgn:7012149",
        "tgn:2000477",
        "tgn:7007250",
        "tgn:7029392"
    ],
    "tgn:id":2433277,
    "tgn:name":"Kellers Island",
    "tgn:placetype":[
        "aat:300008791"
    ]
},
  "bbox": [],
  "geometry": {"coordinates":[-112.0167,43.7667],"type":"Point"}
}