{
  "id": 7125435,
  "type": "Feature",
  "properties": {
    "tgn:hierarchy":[
        "tgn:7125435",
        "tgn:1000003",
        "tgn:7003676",
        "tgn:7000084",
        "tgn:7029392"
    ],
    "tgn:id":7125435,
    "tgn:name":"Nesse",
    "tgn:placetype":[
        "aat:300008347"
    ]
},
  "bbox": [],
  "geometry": {"coordinates":[7.383333,53.65],"type":"Point"}
}