{
  "id": 7336280,
  "type": "Feature",
  "properties": {
    "tgn:hierarchy":[
        "tgn:7336280",
        "tgn:7002832",
        "tgn:7001158",
        "tgn:1000003",
        "tgn:1000095",
        "tgn:7029392"
    ],
    "tgn:id":7336280,
    "tgn:name":"Fuentes de Nava",
    "tgn:placetype":[
        "aat:300008347"
    ]
},
  "bbox": [],
  "geometry": {"coordinates":[-4.783333,42.083333],"type":"Point"}
}