{
  "id": 2748216,
  "type": "Feature",
  "properties": {
    "tgn:hierarchy":[
        "tgn:2748216",
        "tgn:1000001",
        "tgn:7012149",
        "tgn:2001931",
        "tgn:7007825",
        "tgn:7029392"
    ],
    "tgn:id":2748216,
    "tgn:name":"Walker Branch",
    "tgn:placetype":[
        "aat:300008699"
    ]
},
  "bbox": [],
  "geometry": {"coordinates":[-86.2667,36.2333],"type":"Point"}
}