{
  "id": 7537810,
  "type": "Feature",
  "properties": {
    "tgn:hierarchy":[
        "tgn:7537810",
        "tgn:7001242",
        "tgn:7016833",
        "tgn:1001418",
        "tgn:7029392"
    ],
    "tgn:id":7537810,
    "tgn:name:en":"Raml, Q\u0101rat ar",
    "tgn:placetype":[
        "aat:300008777"
    ]
},
  "bbox": [],
  "geometry": {"coordinates":[26.345421,29.041359],"type":"Point"}
}