{
  "id": 7129696,
  "type": "Feature",
  "properties": {
    "tgn:hierarchy":[
        "tgn:7129696",
        "tgn:7003669",
        "tgn:1000003",
        "tgn:7000084",
        "tgn:7029392"
    ],
    "tgn:id":7129696,
    "tgn:name":"M\u00e4rzing",
    "tgn:placetype":[
        "aat:300000206"
    ]
},
  "bbox": [],
  "geometry": {"coordinates":[13.266667,48.733333],"type":"Point"}
}