{
  "id": 2532729,
  "type": "Feature",
  "properties": {
    "tgn:hierarchy":[
        "tgn:2532729",
        "tgn:1000001",
        "tgn:7012149",
        "tgn:2000928",
        "tgn:7007515",
        "tgn:7029392"
    ],
    "tgn:id":2532729,
    "tgn:name":"Murphy Ponds",
    "tgn:placetype":[
        "aat:300008680"
    ]
},
  "bbox": [],
  "geometry": {"coordinates":[-69.1667,45.7833],"type":"Point"}
}