{
  "id": 2698391,
  "type": "Feature",
  "properties": {
    "tgn:hierarchy":[
        "tgn:2698391",
        "tgn:2002101",
        "tgn:1000001",
        "tgn:7012149",
        "tgn:7007827",
        "tgn:7029392"
    ],
    "tgn:id":2698391,
    "tgn:name":"Straight Creek",
    "tgn:placetype":[
        "aat:300008706"
    ]
},
  "bbox": [],
  "geometry": {"coordinates":[-112.4167,38.2333],"type":"Point"}
}