{
  "id": 7583651,
  "type": "Feature",
  "properties": {
    "tgn:hierarchy":[
        "tgn:7583651",
        "tgn:1000004",
        "tgn:7000198",
        "tgn:7016722",
        "tgn:7029392"
    ],
    "tgn:id":7583651,
    "tgn:name:en":"Satora",
    "tgn:placetype":[
        "aat:300008347"
    ]
},
  "bbox": [],
  "geometry": {"coordinates":[78.538313,24.53171],"type":"Point"}
}