{
  "id": 2715633,
  "type": "Feature",
  "properties": {
    "tgn:hierarchy":[
        "tgn:2715633",
        "tgn:1000001",
        "tgn:2001747",
        "tgn:7012149",
        "tgn:7007712",
        "tgn:7029392"
    ],
    "tgn:id":2715633,
    "tgn:name":"Terry Creek",
    "tgn:placetype":[
        "aat:300008706"
    ]
},
  "bbox": [],
  "geometry": {"coordinates":[-82.4667,35.1333],"type":"Point"}
}