{
  "id": 2327956,
  "type": "Feature",
  "properties": {
    "tgn:hierarchy":[
        "tgn:2327956",
        "tgn:1000001",
        "tgn:2001025",
        "tgn:7012149",
        "tgn:7007521",
        "tgn:7029392"
    ],
    "tgn:id":2327956,
    "tgn:name":"Fish Lake",
    "tgn:placetype":[
        "aat:300008680"
    ]
},
  "bbox": [],
  "geometry": {"coordinates":[-93.45,45.0833],"type":"Point"}
}