{
  "id": 2179489,
  "type": "Feature",
  "properties": {
    "tgn:hierarchy":[
        "tgn:2179489",
        "tgn:1000001",
        "tgn:1002285",
        "tgn:7012149",
        "tgn:7007706",
        "tgn:7029392"
    ],
    "tgn:id":2179489,
    "tgn:name":"Blanchester Reservoir Number Three",
    "tgn:placetype":[
        "aat:300006191"
    ]
},
  "bbox": [],
  "geometry": {"coordinates":[-83.9667,39.2833],"type":"Point"}
}