<<<<<<< HEAD
{
  "id": 2765136,
  "type": "Feature",
  "properties": {
    "tgn:hierarchy":[
        "tgn:2765136",
        "tgn:1000001",
        "tgn:7012149",
        "tgn:2001922",
        "tgn:7007825",
        "tgn:7029392"
    ],
    "tgn:id":2765136,
    "tgn:name":"Whispering Pines",
    "tgn:placetype":[
        "aat:300008347"
    ]
},
  "bbox": [],
  "geometry": {"coordinates":[-82.2833,36.2333],"type":"Point"}
}
=======
{"geometry":{"type":"Point","coordinates":[-82.283300,36.233300]},"type":"Feature","properties":{"hierarchy":["tgn:2765136","tgn:1000001","tgn:7012149","tgn:2001922","tgn:7007825","tgn:7029392"],"placetype":["aat:300008347"],"id":2765136,"name:xx":"Whispering Pines"}}
>>>>>>> 03f74aca74312dbeaf24d7e61306dd6a786dc3d0
