{
  "id": 2625610,
  "type": "Feature",
  "properties": {
    "tgn:hierarchy":[
        "tgn:2625610",
        "tgn:1000001",
        "tgn:7012149",
        "tgn:7007524",
        "tgn:7029392"
    ],
    "tgn:id":2625610,
    "tgn:name":"Rockwell, Mount",
    "tgn:placetype":[
        "aat:300008798"
    ]
},
  "bbox": [],
  "geometry": {"coordinates":[-113.45,48.4333],"type":"Point"}
}