{
  "id": 1093543,
  "type": "Feature",
  "properties": {
    "tgn:hierarchy":[
        "tgn:1093543",
        "tgn:7001242",
        "tgn:7016749",
        "tgn:1000193",
        "tgn:7029392"
    ],
    "tgn:id":1093543,
    "tgn:name":"Ramsgate",
    "tgn:placetype":[
        "aat:300008347"
    ]
},
  "bbox": [],
  "geometry": {"coordinates":[30.3333,-30.9167],"type":"Point"}
}