{
  "id": 2754718,
  "type": "Feature",
  "properties": {
    "tgn:hierarchy":[
        "tgn:2754718",
        "tgn:1000001",
        "tgn:7012149",
        "tgn:2001274",
        "tgn:7007524",
        "tgn:7029392"
    ],
    "tgn:id":2754718,
    "tgn:name":"Weasel Collar Glacier",
    "tgn:placetype":[
        "aat:300008835"
    ]
},
  "bbox": [],
  "geometry": {"coordinates":[-114.05,48.8833],"type":"Point"}
}