<<<<<<< HEAD
{
  "id": 7376823,
  "type": "Feature",
  "properties": {
    "tgn:hierarchy":[
        "tgn:7376823",
        "tgn:1000001",
        "tgn:7005599",
        "tgn:7005560",
        "tgn:7029392"
    ],
    "tgn:id":7376823,
    "tgn:name":"Las Lomas",
    "tgn:placetype":[
        "aat:300008347"
    ]
},
  "bbox": [],
  "geometry": {"coordinates":[-97.85,21.116667],"type":"Point"}
}
=======
{"geometry":{"type":"Point","coordinates":[-97.850000,21.116667]},"type":"Feature","properties":{"hierarchy":["tgn:7376823","tgn:1000001","tgn:7005599","tgn:7005560","tgn:7029392"],"placetype":["aat:300008347"],"id":7376823,"name:xx":"Las Lomas"}}
>>>>>>> 03f74aca74312dbeaf24d7e61306dd6a786dc3d0
