{
  "id": 2645024,
  "type": "Feature",
  "properties": {
    "tgn:hierarchy":[
        "tgn:2645024",
        "tgn:1000001",
        "tgn:7012149",
        "tgn:7007157",
        "tgn:1002684",
        "tgn:7029392"
    ],
    "tgn:id":2645024,
    "tgn:name":"Saucito Canyon",
    "tgn:placetype":[
        "aat:300008761"
    ]
},
  "bbox": [],
  "geometry": {"coordinates":[-121.15,36.35],"type":"Point"}
}