{
  "id": 1068809,
  "type": "Feature",
  "properties": {
    "tgn:hierarchy":[
        "tgn:1068809",
        "tgn:1000004",
        "tgn:7002081",
        "tgn:1000111",
        "tgn:7029392"
    ],
    "tgn:id":1068809,
    "tgn:name":"Houbaishu",
    "tgn:placetype":[
        "aat:300008347"
    ]
},
  "bbox": [],
  "geometry": {"coordinates":[119.1667,31.8167],"type":"Point"}
}