{
  "id": 7313501,
  "type": "Feature",
  "properties": {
    "tgn:hierarchy":[
        "tgn:7313501",
        "tgn:1001695",
        "tgn:1000049",
        "tgn:1000002",
        "tgn:7029392"
    ],
    "tgn:id":7313501,
    "tgn:name":"Los Canales El Molino, Estero",
    "tgn:placetype":[
        "aat:300008699"
    ]
},
  "bbox": [],
  "geometry": {"coordinates":[-71.133333,-34.766667],"type":"Point"}
}