<<<<<<< HEAD
{
  "id": 7369852,
  "type": "Feature",
  "properties": {
    "tgn:hierarchy":[
        "tgn:7369852",
        "tgn:1000001",
        "tgn:7005601",
        "tgn:7005560",
        "tgn:7029392"
    ],
    "tgn:id":7369852,
    "tgn:name":"Gambula",
    "tgn:placetype":[
        "aat:300008347"
    ]
},
  "bbox": [],
  "geometry": {"coordinates":[-103.55,22.75],"type":"Point"}
}
=======
{"geometry":{"type":"Point","coordinates":[-103.550000,22.750000]},"type":"Feature","properties":{"hierarchy":["tgn:7369852","tgn:1000001","tgn:7005601","tgn:7005560","tgn:7029392"],"placetype":["aat:300008347"],"id":7369852,"name:xx":"Gambula"}}
>>>>>>> 03f74aca74312dbeaf24d7e61306dd6a786dc3d0
