<<<<<<< HEAD
{
  "id": 2158435,
  "type": "Feature",
  "properties": {
    "tgn:hierarchy":[
        "tgn:2158435",
        "tgn:1000001",
        "tgn:1003037",
        "tgn:7012149",
        "tgn:7007516",
        "tgn:7029392"
    ],
    "tgn:id":2158435,
    "tgn:name":"Beaverdam Creek",
    "tgn:placetype":[
        "aat:300008706"
    ]
},
  "bbox": [],
  "geometry": {"coordinates":[-75.2333,38.2667],"type":"Point"}
}
=======
{"geometry":{"type":"Point","coordinates":[-75.233300,38.266700]},"type":"Feature","properties":{"hierarchy":["tgn:2158435","tgn:1000001","tgn:1003037","tgn:7012149","tgn:7007516","tgn:7029392"],"placetype":["aat:300008706"],"id":2158435,"name:xx":"Beaverdam Creek"}}
>>>>>>> 03f74aca74312dbeaf24d7e61306dd6a786dc3d0
