{
  "id": 7475340,
  "type": "Feature",
  "properties": {
    "tgn:hierarchy":[
        "tgn:7475340",
        "tgn:7469009",
        "tgn:1000004",
        "tgn:1000141",
        "tgn:7029392"
    ],
    "tgn:id":7475340,
    "tgn:name":"Caidian",
    "tgn:placetype":[
        "aat:300008347"
    ]
},
  "bbox": [],
  "geometry": {"coordinates":[118.42066,24.486095],"type":"Point"}
}