{
  "id": 2048946,
  "type": "Feature",
  "properties": {
    "tgn:hierarchy":[
        "tgn:2048946",
        "tgn:1000001",
        "tgn:7016104",
        "tgn:7012149",
        "tgn:7007516",
        "tgn:7029392"
    ],
    "tgn:id":2048946,
    "tgn:name":"Tilden Woods",
    "tgn:placetype":[
        "aat:300008347"
    ]
},
  "bbox": [],
  "geometry": {"coordinates":[-77.1333,39.0333],"type":"Point"}
}