{
  "id": 2332644,
  "type": "Feature",
  "properties": {
    "tgn:hierarchy":[
        "tgn:2332644",
        "tgn:1000001",
        "tgn:2001436",
        "tgn:7012149",
        "tgn:7007566",
        "tgn:7029392"
    ],
    "tgn:id":2332644,
    "tgn:name":"Flotation Plant",
    "tgn:placetype":[
        "aat:300000390"
    ]
},
  "bbox": [],
  "geometry": {"coordinates":[-104.0833,32.2833],"type":"Point"}
}