{
  "id": 2580510,
  "type": "Feature",
  "properties": {
    "tgn:hierarchy":[
        "tgn:2580510",
        "tgn:1000001",
        "tgn:7012149",
        "tgn:2002280",
        "tgn:7013961",
        "tgn:7029392"
    ],
    "tgn:id":2580510,
    "tgn:name":"Pigeon Creek",
    "tgn:placetype":[
        "aat:300008706"
    ]
},
  "bbox": [],
  "geometry": {"coordinates":[-81.9833,37.6167],"type":"Point"}
}