{
  "id": 1095903,
  "type": "Feature",
  "properties": {
    "tgn:hierarchy":[
        "tgn:1095903",
        "tgn:7001242",
        "tgn:1001461",
        "tgn:1000209",
        "tgn:7029392"
    ],
    "tgn:id":1095903,
    "tgn:name":"Chilonga",
    "tgn:placetype":[
        "aat:300008347"
    ]
},
  "bbox": [],
  "geometry": {"coordinates":[31.35,-12.0167],"type":"Point"}
}