{
  "id": 2349049,
  "type": "Feature",
  "properties": {
    "tgn:hierarchy":[
        "tgn:2349049",
        "tgn:1000001",
        "tgn:7006451",
        "tgn:7012149",
        "tgn:2000097",
        "tgn:7029392"
    ],
    "tgn:id":2349049,
    "tgn:name":"Gila Bend Canal",
    "tgn:placetype":[
        "aat:300006075"
    ]
},
  "bbox": [],
  "geometry": {"coordinates":[-112.65,33.0167],"type":"Point"}
}