<<<<<<< HEAD
{
  "id": 2152428,
  "type": "Feature",
  "properties": {
    "tgn:hierarchy":[
        "tgn:2152428",
        "tgn:1000001",
        "tgn:7012149",
        "tgn:1003048",
        "tgn:7007919",
        "tgn:7029392"
    ],
    "tgn:id":2152428,
    "tgn:name":"Bay Point",
    "tgn:placetype":[
        "aat:300008850"
    ]
},
  "bbox": [],
  "geometry": {"coordinates":[-76.3667,37.15],"type":"Point"}
}
=======
{"geometry":{"type":"Point","coordinates":[-76.366700,37.150000]},"type":"Feature","properties":{"hierarchy":["tgn:2152428","tgn:1000001","tgn:7012149","tgn:1003048","tgn:7007919","tgn:7029392"],"placetype":["aat:300008850"],"id":2152428,"name:xx":"Bay Point"}}
>>>>>>> 03f74aca74312dbeaf24d7e61306dd6a786dc3d0
