{
  "id": 2152428,
  "type": "Feature",
  "properties": {
    "tgn:hierarchy":[
        "tgn:2152428",
        "tgn:1000001",
        "tgn:7012149",
        "tgn:1003048",
        "tgn:7007919",
        "tgn:7029392"
    ],
    "tgn:id":2152428,
    "tgn:name":"Bay Point",
    "tgn:placetype":[
        "aat:300008850"
    ]
},
  "bbox": [],
  "geometry": {"coordinates":[-76.3667,37.15],"type":"Point"}
}