{
  "id": 2706376,
  "type": "Feature",
  "properties": {
    "tgn:hierarchy":[
        "tgn:2706376",
        "tgn:1000001",
        "tgn:7012149",
        "tgn:2002342",
        "tgn:7007922",
        "tgn:7029392"
    ],
    "tgn:id":2706376,
    "tgn:name":"Swamsauger Creek",
    "tgn:placetype":[
        "aat:300008706"
    ]
},
  "bbox": [],
  "geometry": {"coordinates":[-89.95,45.7667],"type":"Point"}
}