{
  "id": 2234293,
  "type": "Feature",
  "properties": {
    "tgn:hierarchy":[
        "tgn:2234293",
        "tgn:1000001",
        "tgn:7012149",
        "tgn:1002613",
        "tgn:7007710",
        "tgn:7029392"
    ],
    "tgn:id":2234293,
    "tgn:name":"Chemung",
    "tgn:placetype":[
        "aat:300008347"
    ]
},
  "bbox": [],
  "geometry": {"coordinates":[-76.8333,41.5833],"type":"Point"}
}