{
  "id": 7484660,
  "type": "Feature",
  "properties": {
    "tgn:hierarchy":[
        "tgn:7484660",
        "tgn:1000004",
        "tgn:7490934",
        "tgn:1000141",
        "tgn:7029392"
    ],
    "tgn:id":7484660,
    "tgn:name":"Houku Xi",
    "tgn:placetype":[
        "aat:300008699"
    ]
},
  "bbox": [],
  "geometry": {"coordinates":[120.549167,23.098056],"type":"Point"}
}