<<<<<<< HEAD
{
  "id": 7484660,
  "type": "Feature",
  "properties": {
    "tgn:hierarchy":[
        "tgn:7484660",
        "tgn:1000004",
        "tgn:7490934",
        "tgn:1000141",
        "tgn:7029392"
    ],
    "tgn:id":7484660,
    "tgn:name":"Houku Xi",
    "tgn:placetype":[
        "aat:300008699"
    ]
},
  "bbox": [],
  "geometry": {"coordinates":[120.549167,23.098056],"type":"Point"}
}
=======
{"geometry":{"type":"Point","coordinates":[120.549167,23.098056]},"type":"Feature","properties":{"hierarchy":["tgn:7484660","tgn:1000004","tgn:7490934","tgn:1000141","tgn:7029392"],"placetype":["aat:300008699"],"id":7484660,"name:xx":"Houku Xi"}}
>>>>>>> 03f74aca74312dbeaf24d7e61306dd6a786dc3d0
