{
  "id": 2136037,
  "type": "Feature",
  "properties": {
    "tgn:hierarchy":[
        "tgn:2136037",
        "tgn:1000001",
        "tgn:7012149",
        "tgn:2001869",
        "tgn:7007825",
        "tgn:7029392"
    ],
    "tgn:id":2136037,
    "tgn:name":"Applewood",
    "tgn:placetype":[
        "aat:300008347"
    ]
},
  "bbox": [],
  "geometry": {"coordinates":[-85.3333,35.1333],"type":"Point"}
}