{
  "id": 2622007,
  "type": "Feature",
  "properties": {
    "tgn:hierarchy":[
        "tgn:2622007",
        "tgn:2002131",
        "tgn:1000001",
        "tgn:7012149",
        "tgn:7007828",
        "tgn:7029392"
    ],
    "tgn:id":2622007,
    "tgn:name":"Roberts Brook",
    "tgn:placetype":[
        "aat:300008699"
    ]
},
  "bbox": [],
  "geometry": {"coordinates":[-71.9667,44.45],"type":"Point"}
}