{
  "id": 2439432,
  "type": "Feature",
  "properties": {
    "tgn:hierarchy":[
        "tgn:2439432",
        "tgn:1000001",
        "tgn:7012149",
        "tgn:2000227",
        "tgn:7007158",
        "tgn:7029392"
    ],
    "tgn:id":2439432,
    "tgn:name":"Kirkland Pit",
    "tgn:placetype":[
        "aat:300006191"
    ]
},
  "bbox": [],
  "geometry": {"coordinates":[-104.6333,37.4833],"type":"Point"}
}