{
  "id": 1027946,
  "type": "Feature",
  "properties": {
    "tgn:hierarchy":[
        "tgn:1027946",
        "tgn:7594008",
        "tgn:1000003",
        "tgn:1000066",
        "tgn:7029392"
    ],
    "tgn:id":1027946,
    "tgn:name":"Jyderup",
    "tgn:placetype":[
        "aat:300008347"
    ]
},
  "bbox": [],
  "geometry": {"coordinates":[11.4167,55.6667],"type":"Point"}
}