{
  "id": 2023424,
  "type": "Feature",
  "properties": {
    "tgn:hierarchy":[
        "tgn:2023424",
        "tgn:1000001",
        "tgn:7012149",
        "tgn:2000437",
        "tgn:7007248",
        "tgn:7029392"
    ],
    "tgn:id":2023424,
    "tgn:name":"Lookout Mountain",
    "tgn:placetype":[
        "aat:300008347"
    ]
},
  "bbox": [],
  "geometry": {"coordinates":[-85.35,34.9667],"type":"Point"}
}