{
  "id": 7411410,
  "type": "Feature",
  "properties": {
    "tgn:hierarchy":[
        "tgn:7411410",
        "tgn:1000001",
        "tgn:7005596",
        "tgn:7005560",
        "tgn:7029392"
    ],
    "tgn:id":7411410,
    "tgn:name:es":"Buergos",
    "tgn:placetype":[
        "aat:300008347"
    ]
},
  "bbox": [],
  "geometry": {"coordinates":[-92.641667,17.816667],"type":"Point"}
}