{
  "id": 7335751,
  "type": "Feature",
  "properties": {
    "tgn:hierarchy":[
        "tgn:7335751",
        "tgn:7002844",
        "tgn:7030216",
        "tgn:1000003",
        "tgn:1000095",
        "tgn:7029392"
    ],
    "tgn:id":7335751,
    "tgn:name":"Godall",
    "tgn:placetype":[
        "aat:300008347"
    ]
},
  "bbox": [],
  "geometry": {"coordinates":[0.466667,40.65],"type":"Point"}
}