<<<<<<< HEAD
{
  "id": 7053300,
  "type": "Feature",
  "properties": {
    "tgn:hierarchy":[
        "tgn:7053300",
        "tgn:1003429",
        "tgn:1000003",
        "tgn:7003240",
        "tgn:1000080",
        "tgn:7029392"
    ],
    "tgn:id":7053300,
    "tgn:name":"Maggio, Rio",
    "tgn:placetype":[
        "aat:300008699"
    ]
},
  "bbox": [],
  "geometry": {"coordinates":[12.983333,43.65],"type":"Point"}
}
=======
{"geometry":{"type":"Point","coordinates":[12.983333,43.650000]},"type":"Feature","properties":{"hierarchy":["tgn:7053300","tgn:1003429","tgn:1000003","tgn:7003240","tgn:1000080","tgn:7029392"],"placetype":["aat:300008699"],"id":7053300,"name:xx":"Maggio, Rio"}}
>>>>>>> 03f74aca74312dbeaf24d7e61306dd6a786dc3d0
