{
  "id": 7507561,
  "type": "Feature",
  "properties": {
    "tgn:hierarchy":[
        "tgn:7507561",
        "tgn:1009227",
        "tgn:1000226",
        "tgn:1000006",
        "tgn:7016850",
        "tgn:7029392"
    ],
    "tgn:id":7507561,
    "tgn:name:en":"Potters Creek",
    "tgn:placetype":[
        "aat:300008699"
    ]
},
  "bbox": [],
  "geometry": {"coordinates":[170.183333,-43.333333],"type":"Point"}
}