{
  "id": 7252885,
  "type": "Feature",
  "properties": {
    "tgn:hierarchy":[
        "tgn:7252885",
        "tgn:7003456",
        "tgn:1000003",
        "tgn:1000063",
        "tgn:7018236",
        "tgn:7029392"
    ],
    "tgn:id":7252885,
    "tgn:name":"Sint-Lenaarts",
    "tgn:placetype":[
        "aat:300008347"
    ]
},
  "bbox": [],
  "geometry": {"coordinates":[4.679209,51.347698],"type":"Point"}
}