{
  "id": 2381687,
  "type": "Feature",
  "properties": {
    "tgn:hierarchy":[
        "tgn:2381687",
        "tgn:1000001",
        "tgn:1003023",
        "tgn:7012149",
        "tgn:7007516",
        "tgn:7029392"
    ],
    "tgn:id":2381687,
    "tgn:name":"Hay Point Canal",
    "tgn:placetype":[
        "aat:300008699"
    ]
},
  "bbox": [],
  "geometry": {"coordinates":[-75.8167,38.35],"type":"Point"}
}