{
  "id": 7119339,
  "type": "Feature",
  "properties": {
    "tgn:hierarchy":[
        "tgn:7119339",
        "tgn:1000003",
        "tgn:7003676",
        "tgn:7000084",
        "tgn:7029392"
    ],
    "tgn:id":7119339,
    "tgn:name":"Phiesewarderbusch",
    "tgn:placetype":[
        "aat:300000206"
    ]
},
  "bbox": [],
  "geometry": {"coordinates":[8.483333,53.533333],"type":"Point"}
}