{
  "id": 1042111,
  "type": "Feature",
  "properties": {
    "tgn:hierarchy":[
        "tgn:1042111",
        "tgn:7002684",
        "tgn:7001395",
        "tgn:1000003",
        "tgn:1000074",
        "tgn:7029392"
    ],
    "tgn:id":1042111,
    "tgn:name":"Livan\u00e1tais",
    "tgn:placetype":[
        "aat:300008347"
    ]
},
  "bbox": [],
  "geometry": {"coordinates":[23.05,38.716667],"type":"Point"}
}