{
  "id": 2213529,
  "type": "Feature",
  "properties": {
    "tgn:hierarchy":[
        "tgn:2213529",
        "tgn:1000001",
        "tgn:7012149",
        "tgn:7029392"
    ],
    "tgn:id":2213529,
    "tgn:name":"Cabinet Gorge",
    "tgn:placetype":[
        "aat:300008761"
    ]
},
  "bbox": [],
  "geometry": {"coordinates":[-116.0333,48.0833],"type":"Point"}
}