{
  "id": 7404190,
  "type": "Feature",
  "properties": {
    "tgn:hierarchy":[
        "tgn:7404190",
        "tgn:7005585",
        "tgn:1000001",
        "tgn:7005560",
        "tgn:7029392"
    ],
    "tgn:id":7404190,
    "tgn:name":"El Nogal",
    "tgn:placetype":[
        "aat:300008347"
    ]
},
  "bbox": [],
  "geometry": {"coordinates":[-101.133333,17.766667],"type":"Point"}
}