{
  "id": 2714048,
  "type": "Feature",
  "properties": {
    "tgn:hierarchy":[
        "tgn:2714048",
        "tgn:1000001",
        "tgn:7012149",
        "tgn:2001279",
        "tgn:7007524",
        "tgn:7029392"
    ],
    "tgn:id":2714048,
    "tgn:name":"Tekoa Gulch",
    "tgn:placetype":[
        "aat:300008761"
    ]
},
  "bbox": [],
  "geometry": {"coordinates":[-113.7833,46.4333],"type":"Point"}
}