{
  "id": 7056182,
  "type": "Feature",
  "properties": {
    "tgn:hierarchy":[
        "tgn:7056182",
        "tgn:7003138",
        "tgn:1000003",
        "tgn:7003080",
        "tgn:1000080",
        "tgn:7029392"
    ],
    "tgn:id":7056182,
    "tgn:name":"Le Cerquete",
    "tgn:placetype":[
        "aat:300008347"
    ]
},
  "bbox": [],
  "geometry": {"coordinates":[12.266667,41.85],"type":"Point"}
}