{
  "id": 1082646,
  "type": "Feature",
  "properties": {
    "tgn:hierarchy":[
        "tgn:1082646",
        "tgn:1001317",
        "tgn:1000004",
        "tgn:1000126",
        "tgn:7029392"
    ],
    "tgn:id":1082646,
    "tgn:name":"Rishmayy\u0101",
    "tgn:placetype":[
        "aat:300008347"
    ]
},
  "bbox": [],
  "geometry": {"coordinates":[35.5833,33.7333],"type":"Point"}
}