{
  "id": 7257942,
  "type": "Feature",
  "properties": {
    "tgn:concordances":{
        "gn:id":"2758664"
    },
    "tgn:hierarchy":[
        "tgn:7257942",
        "tgn:1000003",
        "tgn:7003622",
        "tgn:7016845",
        "tgn:7029392"
    ],
    "tgn:id":7257942,
    "tgn:name:nl":"Bong",
    "tgn:placetype":[
        "aat:300008347"
    ]
},
  "bbox": [],
  "geometry": {"coordinates":[6.083333,51.333333],"type":"Point"}
}