{
  "id": 7003818,
  "type": "Feature",
  "properties": {
    "tgn:hierarchy":[
        "tgn:7003818",
        "tgn:1000003",
        "tgn:1000090",
        "tgn:7029392"
    ],
    "tgn:id":7003818,
    "tgn:name":"Bragan\u00e7a",
    "tgn:placetype":[
        "aat:300387064",
        "aat:300387081",
        "aat:300387173"
    ]
},
  "bbox": [],
  "geometry": {"coordinates":[-6.735,41.767],"type":"Point"}
}