{
  "id": 7107381,
  "type": "Feature",
  "properties": {
    "tgn:hierarchy":[
        "tgn:7107381",
        "tgn:7003669",
        "tgn:1000003",
        "tgn:7000084",
        "tgn:7029392"
    ],
    "tgn:id":7107381,
    "tgn:name":"Schein-Berg",
    "tgn:placetype":[
        "aat:300008777"
    ]
},
  "bbox": [],
  "geometry": {"coordinates":[10.066667,50.166667],"type":"Point"}
}