{
  "id": 2558722,
  "type": "Feature",
  "properties": {
    "tgn:hierarchy":[
        "tgn:2558722",
        "tgn:1000001",
        "tgn:7012149",
        "tgn:2002342",
        "tgn:7007922",
        "tgn:7029392"
    ],
    "tgn:id":2558722,
    "tgn:name":"Olmstead Island",
    "tgn:placetype":[
        "aat:300008791"
    ]
},
  "bbox": [],
  "geometry": {"coordinates":[-89.6667,45.8167],"type":"Point"}
}