{
  "id": 2077845,
  "type": "Feature",
  "properties": {
    "tgn:hierarchy":[
        "tgn:2077845",
        "tgn:1000001",
        "tgn:2001603",
        "tgn:7012149",
        "tgn:7007705",
        "tgn:7029392"
    ],
    "tgn:id":2077845,
    "tgn:name":"Millarton",
    "tgn:placetype":[
        "aat:300008347",
        "aat:300387210"
    ]
},
  "bbox": [],
  "geometry": {"coordinates":[-98.75,46.6667],"type":"Point"}
}