{
  "id": 7207543,
  "type": "Feature",
  "properties": {
    "tgn:hierarchy":[
        "tgn:7207543",
        "tgn:1000003",
        "tgn:7003682",
        "tgn:7000084",
        "tgn:7029392"
    ],
    "tgn:id":7207543,
    "tgn:name":"Burg",
    "tgn:placetype":[
        "aat:300008347"
    ]
},
  "bbox": [],
  "geometry": {"coordinates":[7.116667,50.016667],"type":"Point"}
}