{
  "id": 7278323,
  "type": "Feature",
  "properties": {
    "tgn:hierarchy":[
        "tgn:7278323",
        "tgn:7002464",
        "tgn:1000049",
        "tgn:1000002",
        "tgn:7029392"
    ],
    "tgn:id":7278323,
    "tgn:name":"V\u00edtor, Roca",
    "tgn:placetype":[
        "aat:300011692"
    ]
},
  "bbox": [],
  "geometry": {"coordinates":[-70.35,-18.633333],"type":"Point"}
}