{
  "id": 2516594,
  "type": "Feature",
  "properties": {
    "tgn:hierarchy":[
        "tgn:2516594",
        "tgn:1000001",
        "tgn:7012149",
        "tgn:2001146",
        "tgn:7007522",
        "tgn:7029392"
    ],
    "tgn:id":2516594,
    "tgn:name":"Mineral Spring",
    "tgn:placetype":[
        "aat:300008697"
    ]
},
  "bbox": [],
  "geometry": {"coordinates":[-89.7833,32.35],"type":"Point"}
}