{
  "id": 2315019,
  "type": "Feature",
  "properties": {
    "tgn:hierarchy":[
        "tgn:2315019",
        "tgn:1000001",
        "tgn:7012149",
        "tgn:2000787",
        "tgn:7007255",
        "tgn:7029392"
    ],
    "tgn:id":2315019,
    "tgn:name":"Elko",
    "tgn:placetype":[
        "aat:300008347"
    ]
},
  "bbox": [],
  "geometry": {"coordinates":[-86.1333,37.15],"type":"Point"}
}