{
  "id": 7108783,
  "type": "Feature",
  "properties": {
    "tgn:hierarchy":[
        "tgn:7108783",
        "tgn:1000003",
        "tgn:7003685",
        "tgn:7000084",
        "tgn:7029392"
    ],
    "tgn:id":7108783,
    "tgn:name":"Rabenberge",
    "tgn:placetype":[
        "aat:300008777"
    ]
},
  "bbox": [],
  "geometry": {"coordinates":[14.716667,51.416667],"type":"Point"}
}