{
  "id": 2579620,
  "type": "Feature",
  "properties": {
    "tgn:hierarchy":[
        "tgn:2579620",
        "tgn:1000001",
        "tgn:7012149",
        "tgn:2000227",
        "tgn:7007158",
        "tgn:7029392"
    ],
    "tgn:id":2579620,
    "tgn:name":"Picketwire Valley",
    "tgn:placetype":[
        "aat:300008761"
    ]
},
  "bbox": [],
  "geometry": {"coordinates":[-104.9333,37.15],"type":"Point"}
}