{
  "id": 2126358,
  "type": "Feature",
  "properties": {
    "tgn:hierarchy":[
        "tgn:2126358",
        "tgn:1000001",
        "tgn:7012149",
        "tgn:7007157",
        "tgn:1002864",
        "tgn:7029392"
    ],
    "tgn:id":2126358,
    "tgn:name":"Adobe Gulch",
    "tgn:placetype":[
        "aat:300008761"
    ]
},
  "bbox": [],
  "geometry": {"coordinates":[-122.3667,37.4833],"type":"Point"}
}