{
  "id": 2387211,
  "type": "Feature",
  "properties": {
    "tgn:hierarchy":[
        "tgn:2387211",
        "tgn:1000001",
        "tgn:7012149",
        "tgn:2000524",
        "tgn:7007251",
        "tgn:7029392"
    ],
    "tgn:id":2387211,
    "tgn:name":"Hess Bayou",
    "tgn:placetype":[
        "aat:300008699"
    ]
},
  "bbox": [],
  "geometry": {"coordinates":[-89.1333,37.1667],"type":"Point"}
}