{
  "id": 2047628,
  "type": "Feature",
  "properties": {
    "tgn:hierarchy":[
        "tgn:2047628",
        "tgn:1000001",
        "tgn:2000935",
        "tgn:7012149",
        "tgn:7007516",
        "tgn:7029392"
    ],
    "tgn:id":2047628,
    "tgn:name":"Kitzmiller",
    "tgn:placetype":[
        "aat:300008347"
    ]
},
  "bbox": [],
  "geometry": {"coordinates":[-79.1667,39.3833],"type":"Point"}
}