{
  "id": 1028592,
  "type": "Feature",
  "properties": {
    "tgn:hierarchy":[
        "tgn:1028592",
        "tgn:7002445",
        "tgn:1000003",
        "tgn:7012077",
        "tgn:7008591",
        "tgn:7029392"
    ],
    "tgn:id":1028592,
    "tgn:name:en":"Bradninch",
    "tgn:placetype":[
        "aat:300008347"
    ]
},
  "bbox": [],
  "geometry": {"coordinates":[-3.416667,50.833333],"type":"Point"}
}