{
  "id": 7590509,
  "type": "Feature",
  "properties": {
    "tgn:hierarchy":[
        "tgn:7590509",
        "tgn:1000004",
        "tgn:7000198",
        "tgn:7016722",
        "tgn:7029392"
    ],
    "tgn:id":7590509,
    "tgn:name:en":"M\u0101nakpur",
    "tgn:placetype":[
        "aat:300008347"
    ]
},
  "bbox": [],
  "geometry": {"coordinates":[77.360572,29.630983],"type":"Point"}
}