{
  "id": 7199779,
  "type": "Feature",
  "properties": {
    "tgn:hierarchy":[
        "tgn:7199779",
        "tgn:7003692",
        "tgn:1000003",
        "tgn:7000084",
        "tgn:7029392"
    ],
    "tgn:id":7199779,
    "tgn:name":"Ederstetten",
    "tgn:placetype":[
        "aat:300000206"
    ]
},
  "bbox": [],
  "geometry": {"coordinates":[8.933333,47.95],"type":"Point"}
}