{
  "id": 1017956,
  "type": "Feature",
  "properties": {
    "tgn:hierarchy":[
        "tgn:1017956",
        "tgn:7005581",
        "tgn:1000001",
        "tgn:7005560",
        "tgn:7029392"
    ],
    "tgn:id":1017956,
    "tgn:name":"Ojo de la Casa",
    "tgn:placetype":[
        "aat:300008347"
    ]
},
  "bbox": [],
  "geometry": {"coordinates":[-106.533333,31.383333],"type":"Point"}
}