{
  "id": 2597215,
  "type": "Feature",
  "properties": {
    "tgn:hierarchy":[
        "tgn:2597215",
        "tgn:1000001",
        "tgn:7020680",
        "tgn:7012149",
        "tgn:7007256",
        "tgn:7029392"
    ],
    "tgn:id":2597215,
    "tgn:name":"Prairie Bayou",
    "tgn:placetype":[
        "aat:300008699"
    ]
},
  "bbox": [],
  "geometry": {"coordinates":[-93.55,31.95],"type":"Point"}
}