{
  "id": 2712989,
  "type": "Feature",
  "properties": {
    "tgn:hierarchy":[
        "tgn:2712989",
        "tgn:1000001",
        "tgn:7012149",
        "tgn:2000420",
        "tgn:7007248",
        "tgn:7029392"
    ],
    "tgn:id":2712989,
    "tgn:name":"Taylor Lake",
    "tgn:placetype":[
        "aat:300006191"
    ]
},
  "bbox": [],
  "geometry": {"coordinates":[-84.9833,32.0667],"type":"Point"}
}