{
  "id": 2637940,
  "type": "Feature",
  "properties": {
    "tgn:hierarchy":[
        "tgn:2637940",
        "tgn:1000001",
        "tgn:7012149",
        "tgn:2002122",
        "tgn:7007827",
        "tgn:7029392"
    ],
    "tgn:id":2637940,
    "tgn:name":"Salamander Lake",
    "tgn:placetype":[
        "aat:300008680"
    ]
},
  "bbox": [],
  "geometry": {"coordinates":[-110.7667,40.7667],"type":"Point"}
}