{
  "id": 7327510,
  "type": "Feature",
  "properties": {
    "tgn:hierarchy":[
        "tgn:7327510",
        "tgn:7002759",
        "tgn:7008909",
        "tgn:1000003",
        "tgn:1000095",
        "tgn:7029392"
    ],
    "tgn:id":7327510,
    "tgn:name":"Pa\u00fales, Barranco de los",
    "tgn:placetype":[
        "aat:300266554",
        "aat:300008699"
    ]
},
  "bbox": [],
  "geometry": {"coordinates":[-0.209072,41.798943],"type":"Point"}
}