{
  "id": 2733886,
  "type": "Feature",
  "properties": {
    "tgn:hierarchy":[
        "tgn:2733886",
        "tgn:1002166",
        "tgn:1000001",
        "tgn:7012149",
        "tgn:7007520",
        "tgn:7029392"
    ],
    "tgn:id":2733886,
    "tgn:name":"Turner Lake",
    "tgn:placetype":[
        "aat:300008680"
    ]
},
  "bbox": [],
  "geometry": {"coordinates":[-85.45,42.6167],"type":"Point"}
}