{
  "id": 2700435,
  "type": "Feature",
  "properties": {
    "tgn:hierarchy":[
        "tgn:2700435",
        "tgn:7002659",
        "tgn:1000001",
        "tgn:2000011",
        "tgn:7012149",
        "tgn:7029392"
    ],
    "tgn:id":2700435,
    "tgn:name":"Sucarbowa Creek",
    "tgn:placetype":[
        "aat:300008706"
    ]
},
  "bbox": [],
  "geometry": {"coordinates":[-88.1833,32.1333],"type":"Point"}
}