{
  "id": 2208457,
  "type": "Feature",
  "properties": {
    "tgn:hierarchy":[
        "tgn:2208457",
        "tgn:7013388",
        "tgn:1000001",
        "tgn:7012149",
        "tgn:7007517",
        "tgn:7029392"
    ],
    "tgn:id":2208457,
    "tgn:name":"Burnett Pond",
    "tgn:placetype":[
        "aat:300006191"
    ]
},
  "bbox": [],
  "geometry": {"coordinates":[-73.0333,42.6167],"type":"Point"}
}