{
  "id": 1048781,
  "type": "Feature",
  "properties": {
    "tgn:hierarchy":[
        "tgn:1048781",
        "tgn:7003646",
        "tgn:1000003",
        "tgn:1000088",
        "tgn:7029392"
    ],
    "tgn:id":1048781,
    "tgn:name":"Sunde",
    "tgn:placetype":[
        "aat:300008347"
    ]
},
  "bbox": [],
  "geometry": {"coordinates":[5.7167,59.8333],"type":"Point"}
}