<<<<<<< HEAD
{
  "id": 2409857,
  "type": "Feature",
  "properties": {
    "tgn:hierarchy":[
        "tgn:2409857",
        "tgn:1000001",
        "tgn:2000593",
        "tgn:7012149",
        "tgn:7007253",
        "tgn:7029392"
    ],
    "tgn:id":2409857,
    "tgn:name":"Illyria",
    "tgn:placetype":[
        "aat:300008347"
    ]
},
  "bbox": [],
  "geometry": {"coordinates":[-91.6333,42.8833],"type":"Point"}
}
=======
{"geometry":{"type":"Point","coordinates":[-91.633300,42.883300]},"type":"Feature","properties":{"hierarchy":["tgn:2409857","tgn:1000001","tgn:2000593","tgn:7012149","tgn:7007253","tgn:7029392"],"placetype":["aat:300008347"],"id":2409857,"name:xx":"Illyria"}}
>>>>>>> 03f74aca74312dbeaf24d7e61306dd6a786dc3d0
