{
  "id": 2411814,
  "type": "Feature",
  "properties": {
    "tgn:hierarchy":[
        "tgn:2411814",
        "tgn:1000001",
        "tgn:2001948",
        "tgn:7012149",
        "tgn:7007826",
        "tgn:7029392"
    ],
    "tgn:id":2411814,
    "tgn:name":"Indian Mountain",
    "tgn:placetype":[
        "aat:300008798"
    ]
},
  "bbox": [],
  "geometry": {"coordinates":[-99.15,31.8333],"type":"Point"}
}