{
  "id": 1072509,
  "type": "Feature",
  "properties": {
    "tgn:hierarchy":[
        "tgn:1072509",
        "tgn:1000004",
        "tgn:7016672",
        "tgn:1000111",
        "tgn:7029392"
    ],
    "tgn:id":1072509,
    "tgn:name":"Wanjindian",
    "tgn:placetype":[
        "aat:300008347"
    ]
},
  "bbox": [],
  "geometry": {"coordinates":[114.6833,32.8833],"type":"Point"}
}