{
  "id": 7408334,
  "type": "Feature",
  "properties": {
    "tgn:hierarchy":[
        "tgn:7408334",
        "tgn:1000001",
        "tgn:1001893",
        "tgn:7005560",
        "tgn:7029392"
    ],
    "tgn:id":7408334,
    "tgn:name":"Trojes",
    "tgn:placetype":[
        "aat:300008347"
    ]
},
  "bbox": [],
  "geometry": {"coordinates":[-100.066667,18.708333],"type":"Point"}
}