{
  "id": 7070565,
  "type": "Feature",
  "properties": {
    "tgn:hierarchy":[
        "tgn:7070565",
        "tgn:1000003",
        "tgn:7003688",
        "tgn:7000084",
        "tgn:7029392"
    ],
    "tgn:id":7070565,
    "tgn:name":"Steinfeld",
    "tgn:placetype":[
        "aat:300008347"
    ]
},
  "bbox": [],
  "geometry": {"coordinates":[10.433333,53.833333],"type":"Point"}
}