{
  "id": 2372568,
  "type": "Feature",
  "properties": {
    "tgn:hierarchy":[
        "tgn:2372568",
        "tgn:1000001",
        "tgn:7012149",
        "tgn:7007157",
        "tgn:1002972",
        "tgn:7029392"
    ],
    "tgn:id":2372568,
    "tgn:name":"Hall Canyon",
    "tgn:placetype":[
        "aat:300008761"
    ]
},
  "bbox": [],
  "geometry": {"coordinates":[-119.2333,34.3167],"type":"Point"}
}