{
  "id": 7338634,
  "type": "Feature",
  "properties": {
    "tgn:hierarchy":[
        "tgn:7338634",
        "tgn:7002758",
        "tgn:7002823",
        "tgn:1000003",
        "tgn:1000095",
        "tgn:7029392"
    ],
    "tgn:id":7338634,
    "tgn:name":"Cubos, Barranco de los",
    "tgn:placetype":[
        "aat:300008699"
    ]
},
  "bbox": [],
  "geometry": {"coordinates":[-6.916667,37.95],"type":"Point"}
}