{
  "id": 1019039,
  "type": "Feature",
  "properties": {
    "tgn:hierarchy":[
        "tgn:1019039",
        "tgn:7017441",
        "tgn:1000001",
        "tgn:7004643",
        "tgn:7029392"
    ],
    "tgn:id":1019039,
    "tgn:name":"Tablones",
    "tgn:placetype":[
        "aat:300008347"
    ]
},
  "bbox": [],
  "geometry": {"coordinates":[-65.75,18.25],"type":"Point"}
}