{
  "id": 1057639,
  "type": "Feature",
  "properties": {
    "tgn:hierarchy":[
        "tgn:1057639",
        "tgn:1000004",
        "tgn:1003398",
        "tgn:7018214",
        "tgn:7002435",
        "tgn:7029392"
    ],
    "tgn:id":1057639,
    "tgn:name":"Novobogordskoje",
    "tgn:placetype":[
        "aat:300008347"
    ]
},
  "bbox": [],
  "geometry": {"coordinates":[53.9333,53.1833],"type":"Point"}
}