{
  "id": 2568294,
  "type": "Feature",
  "properties": {
    "tgn:hierarchy":[
        "tgn:2568294",
        "tgn:1000001",
        "tgn:2000470",
        "tgn:7012149",
        "tgn:7007250",
        "tgn:7029392"
    ],
    "tgn:id":2568294,
    "tgn:name":"Park Canyon",
    "tgn:placetype":[
        "aat:300008761"
    ]
},
  "bbox": [],
  "geometry": {"coordinates":[-114.2833,43.95],"type":"Point"}
}