{
  "id": 2732180,
  "type": "Feature",
  "properties": {
    "tgn:hierarchy":[
        "tgn:2732180",
        "tgn:1000001",
        "tgn:2001419",
        "tgn:7012149",
        "tgn:7007526",
        "tgn:7029392"
    ],
    "tgn:id":2732180,
    "tgn:name":"Tunnel Spring",
    "tgn:placetype":[
        "aat:300008697"
    ]
},
  "bbox": [],
  "geometry": {"coordinates":[-119.1333,40.2167],"type":"Point"}
}