<<<<<<< HEAD
{
  "id": 2401679,
  "type": "Feature",
  "properties": {
    "tgn:hierarchy":[
        "tgn:2401679",
        "tgn:1000001",
        "tgn:7012149",
        "tgn:2000476",
        "tgn:7007250",
        "tgn:7029392"
    ],
    "tgn:id":2401679,
    "tgn:name":"Horseshoe Lake",
    "tgn:placetype":[
        "aat:300008680"
    ]
},
  "bbox": [],
  "geometry": {"coordinates":[-115.7167,45.5167],"type":"Point"}
}
=======
{"geometry":{"type":"Point","coordinates":[-115.716700,45.516700]},"type":"Feature","properties":{"hierarchy":["tgn:2401679","tgn:1000001","tgn:7012149","tgn:2000476","tgn:7007250","tgn:7029392"],"placetype":["aat:300008680"],"id":2401679,"name:xx":"Horseshoe Lake"}}
>>>>>>> 03f74aca74312dbeaf24d7e61306dd6a786dc3d0
