{
  "id": 2558686,
  "type": "Feature",
  "properties": {
    "tgn:hierarchy":[
        "tgn:2558686",
        "tgn:1000001",
        "tgn:7012149",
        "tgn:1002599",
        "tgn:7007708",
        "tgn:7029392"
    ],
    "tgn:id":2558686,
    "tgn:name":"Ollala Lake",
    "tgn:placetype":[
        "aat:300006191"
    ]
},
  "bbox": [],
  "geometry": {"coordinates":[-123.9167,44.6667],"type":"Point"}
}