{
  "id": 7254692,
  "type": "Feature",
  "properties": {
    "tgn:hierarchy":[
        "tgn:7254692",
        "tgn:7003458",
        "tgn:1000003",
        "tgn:1000063",
        "tgn:7018236",
        "tgn:7029392"
    ],
    "tgn:id":7254692,
    "tgn:name":"Stavele",
    "tgn:placetype":[
        "aat:300008347"
    ]
},
  "bbox": [],
  "geometry": {"coordinates":[2.672415,50.940681],"type":"Point"}
}