{
  "id": 7491400,
  "type": "Feature",
  "properties": {
    "tgn:hierarchy":[
        "tgn:7491400",
        "tgn:1000004",
        "tgn:7001013",
        "tgn:1000141",
        "tgn:7029392"
    ],
    "tgn:id":7491400,
    "tgn:name":"Dagang Cun",
    "tgn:placetype":[
        "aat:300387173"
    ]
},
  "bbox": [],
  "geometry": {"coordinates":[121.3484,25.0486],"type":"Point"}
}