{
  "id": 7151476,
  "type": "Feature",
  "properties": {
    "tgn:hierarchy":[
        "tgn:7151476",
        "tgn:1000003",
        "tgn:7003676",
        "tgn:7000084",
        "tgn:7029392"
    ],
    "tgn:id":7151476,
    "tgn:name":"Jericho",
    "tgn:placetype":[
        "aat:300000206"
    ]
},
  "bbox": [],
  "geometry": {"coordinates":[8.35,53.583333],"type":"Point"}
}