{
  "id": 7275687,
  "type": "Feature",
  "properties": {
    "tgn:hierarchy":[
        "tgn:7275687",
        "tgn:1001699",
        "tgn:1000049",
        "tgn:1000002",
        "tgn:7029392"
    ],
    "tgn:id":7275687,
    "tgn:name":"Trau, Caleta",
    "tgn:placetype":[
        "aat:300132317"
    ]
},
  "bbox": [],
  "geometry": {"coordinates":[-73.816667,-43.783333],"type":"Point"}
}