{
  "id": 7094861,
  "type": "Feature",
  "properties": {
    "tgn:hierarchy":[
        "tgn:7094861",
        "tgn:7000096",
        "tgn:1000003",
        "tgn:7000084",
        "tgn:7029392"
    ],
    "tgn:id":7094861,
    "tgn:name":"Schulzenfelde",
    "tgn:placetype":[
        "aat:300000206"
    ]
},
  "bbox": [],
  "geometry": {"coordinates":[13.45,53.116667],"type":"Point"}
}