{
  "id": 2705766,
  "type": "Feature",
  "properties": {
    "tgn:hierarchy":[
        "tgn:2705766",
        "tgn:1000001",
        "tgn:7012149",
        "tgn:1002767",
        "tgn:7007920",
        "tgn:7029392"
    ],
    "tgn:id":2705766,
    "tgn:name":"Sutico",
    "tgn:placetype":[
        "aat:300008347"
    ]
},
  "bbox": [],
  "geometry": {"coordinates":[-123.5167,46.6167],"type":"Point"}
}