{
  "id": 2200413,
  "type": "Feature",
  "properties": {
    "tgn:hierarchy":[
        "tgn:2200413",
        "tgn:1000001",
        "tgn:7016172",
        "tgn:7012149",
        "tgn:2000142",
        "tgn:7029392"
    ],
    "tgn:id":2200413,
    "tgn:name":"Brushy Lake",
    "tgn:placetype":[
        "aat:300008680"
    ]
},
  "bbox": [],
  "geometry": {"coordinates":[-91.1833,35.95],"type":"Point"}
}