{
  "id": 7535607,
  "type": "Feature",
  "properties": {
    "tgn:hierarchy":[
        "tgn:7535607",
        "tgn:7001242",
        "tgn:1001075",
        "tgn:7016833",
        "tgn:7029392"
    ],
    "tgn:id":7535607,
    "tgn:name:en":"Ghi\u0163\u0101s, Bu\u1e29ayrat",
    "tgn:placetype":[
        "aat:300008680"
    ]
},
  "bbox": [],
  "geometry": {"coordinates":[30.296667,31.213056],"type":"Point"}
}