{
  "id": 2420033,
  "type": "Feature",
  "properties": {
    "tgn:hierarchy":[
        "tgn:2420033",
        "tgn:1000001",
        "tgn:2001638",
        "tgn:7012149",
        "tgn:7007707",
        "tgn:7029392"
    ],
    "tgn:id":2420033,
    "tgn:name":"Jed Johnson, Lake",
    "tgn:placetype":[
        "aat:300006191"
    ]
},
  "bbox": [],
  "geometry": {"coordinates":[-98.5833,34.7167],"type":"Point"}
}