{
  "id": 7320294,
  "type": "Feature",
  "properties": {
    "tgn:hierarchy":[
        "tgn:7320294",
        "tgn:1001623",
        "tgn:1000049",
        "tgn:1000002",
        "tgn:7029392"
    ],
    "tgn:id":7320294,
    "tgn:name":"Canquenes, Estero",
    "tgn:placetype":[
        "aat:300387026"
    ]
},
  "bbox": [],
  "geometry": {"coordinates":[-74.116667,-45.766667],"type":"Point"}
}