{
  "id": 7502706,
  "type": "Feature",
  "properties": {
    "tgn:hierarchy":[
        "tgn:7502706",
        "tgn:1000004",
        "tgn:7471332",
        "tgn:1000141",
        "tgn:7029392"
    ],
    "tgn:id":7502706,
    "tgn:name":"Tizikeng",
    "tgn:placetype":[
        "aat:300008347"
    ]
},
  "bbox": [],
  "geometry": {"coordinates":[121.018056,24.703333],"type":"Point"}
}