{
  "id": 7200602,
  "type": "Feature",
  "properties": {
    "tgn:hierarchy":[
        "tgn:7200602",
        "tgn:7003669",
        "tgn:1000003",
        "tgn:7000084",
        "tgn:7029392"
    ],
    "tgn:id":7200602,
    "tgn:name":"Eich Berg",
    "tgn:placetype":[
        "aat:300008777"
    ]
},
  "bbox": [],
  "geometry": {"coordinates":[11.483333,50.05],"type":"Point"}
}