{
  "id": 2546338,
  "type": "Feature",
  "properties": {
    "tgn:hierarchy":[
        "tgn:2546338",
        "tgn:1000001",
        "tgn:7012149",
        "tgn:7007157",
        "tgn:7014004",
        "tgn:7029392"
    ],
    "tgn:id":2546338,
    "tgn:name":"North Fork Halls Gulch",
    "tgn:placetype":[
        "aat:300008761"
    ]
},
  "bbox": [],
  "geometry": {"coordinates":[-119.9333,37.6833],"type":"Point"}
}