<<<<<<< HEAD
{
  "id": 2251069,
  "type": "Feature",
  "properties": {
    "tgn:hierarchy":[
        "tgn:2251069",
        "tgn:1000001",
        "tgn:7012149",
        "tgn:2001715",
        "tgn:7007708",
        "tgn:7029392"
    ],
    "tgn:id":2251069,
    "tgn:name":"Colvert Spring",
    "tgn:placetype":[
        "aat:300008697"
    ]
},
  "bbox": [],
  "geometry": {"coordinates":[-120.35,42.35],"type":"Point"}
}
=======
{"geometry":{"type":"Point","coordinates":[-120.350000,42.350000]},"type":"Feature","properties":{"hierarchy":["tgn:2251069","tgn:1000001","tgn:7012149","tgn:2001715","tgn:7007708","tgn:7029392"],"placetype":["aat:300008697"],"id":2251069,"name:xx":"Colvert Spring"}}
>>>>>>> 03f74aca74312dbeaf24d7e61306dd6a786dc3d0
