{
  "id": 7442905,
  "type": "Feature",
  "properties": {
    "tgn:hierarchy":[
        "tgn:7442905",
        "tgn:7002443",
        "tgn:7026278",
        "tgn:1000003",
        "tgn:7008591",
        "tgn:7029392"
    ],
    "tgn:id":7442905,
    "tgn:name:en":"Whitford",
    "tgn:placetype":[
        "aat:300008347"
    ]
},
  "bbox": [],
  "geometry": {"coordinates":[-3.283333,53.283333],"type":"Point"}
}