{
  "id": 7544858,
  "type": "Feature",
  "properties": {
    "tgn:hierarchy":[
        "tgn:7544858",
        "tgn:1000004",
        "tgn:7000198",
        "tgn:1001894",
        "tgn:7029392"
    ],
    "tgn:id":7544858,
    "tgn:name:en":"B\u0101bai",
    "tgn:placetype":[
        "aat:300008347"
    ]
},
  "bbox": [],
  "geometry": {"coordinates":[78.677674,22.831565],"type":"Point"}
}