{
  "id": 2704886,
  "type": "Feature",
  "properties": {
    "tgn:hierarchy":[
        "tgn:2704886",
        "tgn:1000001",
        "tgn:7012149",
        "tgn:7007157",
        "tgn:1002828",
        "tgn:7029392"
    ],
    "tgn:id":2704886,
    "tgn:name":"Sunset Mine",
    "tgn:placetype":[
        "aat:300000390"
    ]
},
  "bbox": [],
  "geometry": {"coordinates":[-115.6833,33.9833],"type":"Point"}
}