{
  "id": 7253869,
  "type": "Feature",
  "properties": {
    "tgn:hierarchy":[
        "tgn:7253869",
        "tgn:7018239",
        "tgn:1000003",
        "tgn:1000063",
        "tgn:7018236",
        "tgn:7029392"
    ],
    "tgn:id":7253869,
    "tgn:name":"Teralfene",
    "tgn:placetype":[
        "aat:300008347"
    ]
},
  "bbox": [],
  "geometry": {"coordinates":[4.09895,50.891949],"type":"Point"}
}