<<<<<<< HEAD
{
  "id": 2156103,
  "type": "Feature",
  "properties": {
    "tgn:hierarchy":[
        "tgn:2156103",
        "tgn:1000001",
        "tgn:7012149",
        "tgn:2000210",
        "tgn:7007158",
        "tgn:7029392"
    ],
    "tgn:id":2156103,
    "tgn:name":"Beard Creek",
    "tgn:placetype":[
        "aat:300008706"
    ]
},
  "bbox": [],
  "geometry": {"coordinates":[-106.5667,39.6833],"type":"Point"}
}
=======
{"geometry":{"type":"Point","coordinates":[-106.566700,39.683300]},"type":"Feature","properties":{"hierarchy":["tgn:2156103","tgn:1000001","tgn:7012149","tgn:2000210","tgn:7007158","tgn:7029392"],"placetype":["aat:300008706"],"id":2156103,"name:xx":"Beard Creek"}}
>>>>>>> 03f74aca74312dbeaf24d7e61306dd6a786dc3d0
