{
  "id": 2522715,
  "type": "Feature",
  "properties": {
    "tgn:hierarchy":[
        "tgn:2522715",
        "tgn:1002132",
        "tgn:1000001",
        "tgn:7012149",
        "tgn:7007919",
        "tgn:7029392"
    ],
    "tgn:id":2522715,
    "tgn:name":"Moore Branch",
    "tgn:placetype":[
        "aat:300008699"
    ]
},
  "bbox": [],
  "geometry": {"coordinates":[-75.75,37.65],"type":"Point"}
}