{
  "id": 2320149,
  "type": "Feature",
  "properties": {
    "tgn:hierarchy":[
        "tgn:2320149",
        "tgn:1000001",
        "tgn:7012149",
        "tgn:7014287",
        "tgn:7007568",
        "tgn:7029392"
    ],
    "tgn:id":2320149,
    "tgn:name":"Evans Pond",
    "tgn:placetype":[
        "aat:300006191"
    ]
},
  "bbox": [],
  "geometry": {"coordinates":[-75.1333,43.3667],"type":"Point"}
}