<<<<<<< HEAD
{
  "id": 2760622,
  "type": "Feature",
  "properties": {
    "tgn:hierarchy":[
        "tgn:2760622",
        "tgn:1000001",
        "tgn:7012149",
        "tgn:2002381",
        "tgn:7007923",
        "tgn:7029392"
    ],
    "tgn:id":2760622,
    "tgn:name":"West Fork Wildcat Creek",
    "tgn:placetype":[
        "aat:300008706"
    ]
},
  "bbox": [],
  "geometry": {"coordinates":[-106.8,44.6667],"type":"Point"}
}
=======
{"geometry":{"type":"Point","coordinates":[-106.800000,44.666700]},"type":"Feature","properties":{"hierarchy":["tgn:2760622","tgn:1000001","tgn:7012149","tgn:2002381","tgn:7007923","tgn:7029392"],"placetype":["aat:300008706"],"id":2760622,"name:xx":"West Fork Wildcat Creek"}}
>>>>>>> 03f74aca74312dbeaf24d7e61306dd6a786dc3d0
