{
  "id": 2446287,
  "type": "Feature",
  "properties": {
    "tgn:hierarchy":[
        "tgn:2446287",
        "tgn:1000001",
        "tgn:7012149",
        "tgn:7014589",
        "tgn:7007515",
        "tgn:7029392"
    ],
    "tgn:id":2446287,
    "tgn:name":"Lewis Cove",
    "tgn:placetype":[
        "aat:300132316"
    ]
},
  "bbox": [],
  "geometry": {"coordinates":[-67.0833,45.0333],"type":"Point"}
}