{
  "id": 1026410,
  "type": "Feature",
  "properties": {
    "tgn:hierarchy":[
        "tgn:1026410",
        "tgn:7003466",
        "tgn:1000003",
        "tgn:1000063",
        "tgn:4012014",
        "tgn:7029392"
    ],
    "tgn:id":1026410,
    "tgn:name":"Emptinne",
    "tgn:placetype":[
        "aat:300008347"
    ]
},
  "bbox": [],
  "geometry": {"coordinates":[5.121152,50.326021],"type":"Point"}
}