<<<<<<< HEAD
{
  "id": 2330841,
  "type": "Feature",
  "properties": {
    "tgn:hierarchy":[
        "tgn:2330841",
        "tgn:1000001",
        "tgn:7006451",
        "tgn:7012149",
        "tgn:2000098",
        "tgn:7029392"
    ],
    "tgn:id":2330841,
    "tgn:name":"Flat Pond",
    "tgn:placetype":[
        "aat:300008680"
    ]
},
  "bbox": [],
  "geometry": {"coordinates":[-113.4,36.4667],"type":"Point"}
}
=======
{"geometry":{"type":"Point","coordinates":[-113.400000,36.466700]},"type":"Feature","properties":{"hierarchy":["tgn:2330841","tgn:1000001","tgn:7006451","tgn:7012149","tgn:2000098","tgn:7029392"],"placetype":["aat:300008680"],"id":2330841,"name:xx":"Flat Pond"}}
>>>>>>> 03f74aca74312dbeaf24d7e61306dd6a786dc3d0
