{
  "id": 7576498,
  "type": "Feature",
  "properties": {
    "tgn:hierarchy":[
        "tgn:7576498",
        "tgn:1000004",
        "tgn:7000198",
        "tgn:1001895",
        "tgn:7029392"
    ],
    "tgn:id":7576498,
    "tgn:name:en":"Kh\u0101parkhera",
    "tgn:placetype":[
        "aat:300008347"
    ]
},
  "bbox": [],
  "geometry": {"coordinates":[79.444861,21.286262],"type":"Point"}
}