{
  "id": 1066175,
  "type": "Feature",
  "properties": {
    "tgn:hierarchy":[
        "tgn:1066175",
        "tgn:1000004",
        "tgn:1002093",
        "tgn:1000108",
        "tgn:7029392"
    ],
    "tgn:id":1066175,
    "tgn:name":"Mindon",
    "tgn:placetype":[
        "aat:300008347"
    ]
},
  "bbox": [],
  "geometry": {"coordinates":[94.7333,19.3333],"type":"Point"}
}