{
  "id": 7588151,
  "type": "Feature",
  "properties": {
    "tgn:hierarchy":[
        "tgn:7588151",
        "tgn:1000004",
        "tgn:7000198",
        "tgn:7000799",
        "tgn:7029392"
    ],
    "tgn:id":7588151,
    "tgn:name:en":"Wuyan",
    "tgn:placetype":[
        "aat:300008347"
    ]
},
  "bbox": [],
  "geometry": {"coordinates":[74.966287,34.025009],"type":"Point"}
}