{
  "id": 2447682,
  "type": "Feature",
  "properties": {
    "tgn:hierarchy":[
        "tgn:2447682",
        "tgn:1000001",
        "tgn:7012149",
        "tgn:2001622",
        "tgn:7007706",
        "tgn:7029392"
    ],
    "tgn:id":2447682,
    "tgn:name":"Lick Run",
    "tgn:placetype":[
        "aat:300008699"
    ]
},
  "bbox": [],
  "geometry": {"coordinates":[-81.35,39.3667],"type":"Point"}
}