{
  "id": 2423019,
  "type": "Feature",
  "properties": {
    "tgn:hierarchy":[
        "tgn:2423019",
        "tgn:1000001",
        "tgn:7012149",
        "tgn:2000231",
        "tgn:7007158",
        "tgn:7029392"
    ],
    "tgn:id":2423019,
    "tgn:name":"Joe Monn Creek",
    "tgn:placetype":[
        "aat:300008706"
    ]
},
  "bbox": [],
  "geometry": {"coordinates":[-106.7167,37.4167],"type":"Point"}
}