{
  "id": 2239828,
  "type": "Feature",
  "properties": {
    "tgn:hierarchy":[
        "tgn:2239828",
        "tgn:1000001",
        "tgn:7012149",
        "tgn:2001449",
        "tgn:7007566",
        "tgn:7029392"
    ],
    "tgn:id":2239828,
    "tgn:name":"Cienega del Oso",
    "tgn:placetype":[
        "aat:300008905"
    ]
},
  "bbox": [],
  "geometry": {"coordinates":[-106.3833,36.0167],"type":"Point"}
}