{
  "id": 7360702,
  "type": "Feature",
  "properties": {
    "tgn:hierarchy":[
        "tgn:7360702",
        "tgn:1001853",
        "tgn:1000001",
        "tgn:7005560",
        "tgn:7029392"
    ],
    "tgn:id":7360702,
    "tgn:name":"Ejido Coradonga",
    "tgn:placetype":[
        "aat:300008347"
    ]
},
  "bbox": [],
  "geometry": {"coordinates":[-103.233333,25.916667],"type":"Point"}
}