<<<<<<< HEAD
{
  "id": 7472364,
  "type": "Feature",
  "properties": {
    "tgn:hierarchy":[
        "tgn:7472364",
        "tgn:1000004",
        "tgn:7467799",
        "tgn:1000141",
        "tgn:7029392"
    ],
    "tgn:id":7472364,
    "tgn:name":"Wanxing Guozhong",
    "tgn:placetype":[
        "aat:300006495"
    ]
},
  "bbox": [],
  "geometry": {"coordinates":[120.4151,23.957233],"type":"Point"}
}
=======
{"geometry":{"type":"Point","coordinates":[120.415100,23.957233]},"type":"Feature","properties":{"hierarchy":["tgn:7472364","tgn:1000004","tgn:7467799","tgn:1000141","tgn:7029392"],"placetype":["aat:300006495"],"id":7472364,"name:xx":"Wanxing Guozhong"}}
>>>>>>> 03f74aca74312dbeaf24d7e61306dd6a786dc3d0
