{
  "id": 7472364,
  "type": "Feature",
  "properties": {
    "tgn:hierarchy":[
        "tgn:7472364",
        "tgn:1000004",
        "tgn:7467799",
        "tgn:1000141",
        "tgn:7029392"
    ],
    "tgn:id":7472364,
    "tgn:name":"Wanxing Guozhong",
    "tgn:placetype":[
        "aat:300006495"
    ]
},
  "bbox": [],
  "geometry": {"coordinates":[120.4151,23.957233],"type":"Point"}
}