<<<<<<< HEAD
{
  "id": 2404753,
  "type": "Feature",
  "properties": {
    "tgn:hierarchy":[
        "tgn:2404753",
        "tgn:1000001",
        "tgn:7012149",
        "tgn:2000818",
        "tgn:7007255",
        "tgn:7029392"
    ],
    "tgn:id":2404753,
    "tgn:name":"Huckleberry Hollow",
    "tgn:placetype":[
        "aat:300008761"
    ]
},
  "bbox": [],
  "geometry": {"coordinates":[-84.6833,36.6833],"type":"Point"}
}
=======
{"geometry":{"type":"Point","coordinates":[-84.683300,36.683300]},"type":"Feature","properties":{"hierarchy":["tgn:2404753","tgn:1000001","tgn:7012149","tgn:2000818","tgn:7007255","tgn:7029392"],"placetype":["aat:300008761"],"id":2404753,"name:xx":"Huckleberry Hollow"}}
>>>>>>> 03f74aca74312dbeaf24d7e61306dd6a786dc3d0
