{
  "id": 2404753,
  "type": "Feature",
  "properties": {
    "tgn:hierarchy":[
        "tgn:2404753",
        "tgn:1000001",
        "tgn:7012149",
        "tgn:2000818",
        "tgn:7007255",
        "tgn:7029392"
    ],
    "tgn:id":2404753,
    "tgn:name":"Huckleberry Hollow",
    "tgn:placetype":[
        "aat:300008761"
    ]
},
  "bbox": [],
  "geometry": {"coordinates":[-84.6833,36.6833],"type":"Point"}
}