{
  "id": 2148100,
  "type": "Feature",
  "properties": {
    "tgn:hierarchy":[
        "tgn:2148100",
        "tgn:1000001",
        "tgn:7012149",
        "tgn:2002069",
        "tgn:7007826",
        "tgn:7029392"
    ],
    "tgn:id":2148100,
    "tgn:name":"Barker Tank",
    "tgn:placetype":[
        "aat:300006191"
    ]
},
  "bbox": [],
  "geometry": {"coordinates":[-98.7333,31.1333],"type":"Point"}
}