{
  "id": 7505036,
  "type": "Feature",
  "properties": {
    "tgn:hierarchy":[
        "tgn:7505036",
        "tgn:7016670",
        "tgn:1008380",
        "tgn:1000226",
        "tgn:1000006",
        "tgn:7029392"
    ],
    "tgn:id":7505036,
    "tgn:name:en":"Auckland Rock",
    "tgn:placetype":[
        "aat:300011692"
    ]
},
  "bbox": [],
  "geometry": {"coordinates":[176.931944,-39.464167],"type":"Point"}
}