{
  "id": 2507474,
  "type": "Feature",
  "properties": {
    "tgn:hierarchy":[
        "tgn:2507474",
        "tgn:1000001",
        "tgn:7016172",
        "tgn:7012149",
        "tgn:7029392"
    ],
    "tgn:id":2507474,
    "tgn:name":"Meyers Creek",
    "tgn:placetype":[
        "aat:300008706"
    ]
},
  "bbox": [],
  "geometry": {"coordinates":[-93.4167,34.4833],"type":"Point"}
}