{
  "id": 7186663,
  "type": "Feature",
  "properties": {
    "tgn:hierarchy":[
        "tgn:7186663",
        "tgn:7003669",
        "tgn:1000003",
        "tgn:7000084",
        "tgn:7029392"
    ],
    "tgn:id":7186663,
    "tgn:name":"Grabenh\u00e4user",
    "tgn:placetype":[
        "aat:300000206"
    ]
},
  "bbox": [],
  "geometry": {"coordinates":[11.95,49.116667],"type":"Point"}
}