{
  "id": 2743980,
  "type": "Feature",
  "properties": {
    "tgn:hierarchy":[
        "tgn:2743980",
        "tgn:1000001",
        "tgn:7012149",
        "tgn:2001307",
        "tgn:7007524",
        "tgn:7029392"
    ],
    "tgn:id":2743980,
    "tgn:name":"Vengence, Lake",
    "tgn:placetype":[
        "aat:300008680"
    ]
},
  "bbox": [],
  "geometry": {"coordinates":[-110.0167,45.2667],"type":"Point"}
}