{
  "id": 1078234,
  "type": "Feature",
  "properties": {
    "tgn:hierarchy":[
        "tgn:1078234",
        "tgn:1000004",
        "tgn:1001323",
        "tgn:1000116",
        "tgn:7029392"
    ],
    "tgn:id":1078234,
    "tgn:name":"Ngoro",
    "tgn:placetype":[
        "aat:300008347"
    ]
},
  "bbox": [],
  "geometry": {"coordinates":[112.2667,-7.6833],"type":"Point"}
}