{
  "id": 2432592,
  "type": "Feature",
  "properties": {
    "tgn:hierarchy":[
        "tgn:2432592",
        "tgn:1000001",
        "tgn:7012149",
        "tgn:2001881",
        "tgn:7007825",
        "tgn:7029392"
    ],
    "tgn:id":2432592,
    "tgn:name":"Keel Cave",
    "tgn:placetype":[
        "aat:300008746"
    ]
},
  "bbox": [],
  "geometry": {"coordinates":[-83.5667,36.0333],"type":"Point"}
}