<<<<<<< HEAD
{
  "id": 2151538,
  "type": "Feature",
  "properties": {
    "tgn:hierarchy":[
        "tgn:2151538",
        "tgn:1000001",
        "tgn:7012149",
        "tgn:2000229",
        "tgn:7007158",
        "tgn:7029392"
    ],
    "tgn:id":2151538,
    "tgn:name":"Batten Ditch",
    "tgn:placetype":[
        "aat:300006075"
    ]
},
  "bbox": [],
  "geometry": {"coordinates":[-103.2167,40.5667],"type":"Point"}
}
=======
{"geometry":{"type":"Point","coordinates":[-103.216700,40.566700]},"type":"Feature","properties":{"hierarchy":["tgn:2151538","tgn:1000001","tgn:7012149","tgn:2000229","tgn:7007158","tgn:7029392"],"placetype":["aat:300006075"],"id":2151538,"name:xx":"Batten Ditch"}}
>>>>>>> 03f74aca74312dbeaf24d7e61306dd6a786dc3d0
