{
  "id": 2734539,
  "type": "Feature",
  "properties": {
    "tgn:hierarchy":[
        "tgn:2734539",
        "tgn:1000001",
        "tgn:7012149",
        "tgn:2001451",
        "tgn:7007566",
        "tgn:7029392"
    ],
    "tgn:id":2734539,
    "tgn:name":"Tusas Tank",
    "tgn:placetype":[
        "aat:300006191"
    ]
},
  "bbox": [],
  "geometry": {"coordinates":[-106.8167,35.8333],"type":"Point"}
}