{
  "id": 7170150,
  "type": "Feature",
  "properties": {
    "tgn:hierarchy":[
        "tgn:7170150",
        "tgn:7003669",
        "tgn:1000003",
        "tgn:7000084",
        "tgn:7029392"
    ],
    "tgn:id":7170150,
    "tgn:name":"H\u00fcbersdorf",
    "tgn:placetype":[
        "aat:300000206"
    ]
},
  "bbox": [],
  "geometry": {"coordinates":[13.316667,48.633333],"type":"Point"}
}