{
  "id": 2374053,
  "type": "Feature",
  "properties": {
    "tgn:hierarchy":[
        "tgn:2374053",
        "tgn:2000001",
        "tgn:7002659",
        "tgn:1000001",
        "tgn:7012149",
        "tgn:7029392"
    ],
    "tgn:id":2374053,
    "tgn:name":"Hammock Creek",
    "tgn:placetype":[
        "aat:300008706"
    ]
},
  "bbox": [],
  "geometry": {"coordinates":[-87.55,30.3833],"type":"Point"}
}