{
  "id": 7415747,
  "type": "Feature",
  "properties": {
    "tgn:hierarchy":[
        "tgn:7415747",
        "tgn:1000001",
        "tgn:7005591",
        "tgn:7005560",
        "tgn:7029392"
    ],
    "tgn:id":7415747,
    "tgn:name:es":"Mano del Se\u00f1or",
    "tgn:placetype":[
        "aat:300008347"
    ]
},
  "bbox": [],
  "geometry": {"coordinates":[-97.4475,16.593611],"type":"Point"}
}