{
  "id": 2514832,
  "type": "Feature",
  "properties": {
    "tgn:hierarchy":[
        "tgn:2514832",
        "tgn:1000001",
        "tgn:7013638",
        "tgn:7012149",
        "tgn:7007568",
        "tgn:7029392"
    ],
    "tgn:id":2514832,
    "tgn:name":"Miller Pond",
    "tgn:placetype":[
        "aat:300008680"
    ]
},
  "bbox": [],
  "geometry": {"coordinates":[-73.5667,42.0667],"type":"Point"}
}