{
  "id": 7118981,
  "type": "Feature",
  "properties": {
    "tgn:hierarchy":[
        "tgn:7118981",
        "tgn:1000003",
        "tgn:7003689",
        "tgn:7000084",
        "tgn:7029392"
    ],
    "tgn:id":7118981,
    "tgn:name":"Prisselberg",
    "tgn:placetype":[
        "aat:300008347"
    ]
},
  "bbox": [],
  "geometry": {"coordinates":[12.466667,50.933333],"type":"Point"}
}