{
  "id": 2531909,
  "type": "Feature",
  "properties": {
    "tgn:hierarchy":[
        "tgn:2531909",
        "tgn:1000001",
        "tgn:7012149",
        "tgn:2000837",
        "tgn:7007255",
        "tgn:7029392"
    ],
    "tgn:id":2531909,
    "tgn:name":"Mullins Branch",
    "tgn:placetype":[
        "aat:300008699"
    ]
},
  "bbox": [],
  "geometry": {"coordinates":[-82.25,37.3333],"type":"Point"}
}