{
  "id": 1106545,
  "type": "Feature",
  "properties": {
    "tgn:hierarchy":[
        "tgn:1106545",
        "tgn:1000003",
        "tgn:7003122",
        "tgn:1001762",
        "tgn:1000080",
        "tgn:7029392"
    ],
    "tgn:id":1106545,
    "tgn:name":"Sparagio, Monte",
    "tgn:placetype":[
        "aat:300008795"
    ]
},
  "bbox": [],
  "geometry": {"coordinates":[12.7833,38.0667],"type":"Point"}
}