{
  "id": 4006871,
  "type": "Feature",
  "properties": {
    "tgn:hierarchy":[
        "tgn:4006871",
        "tgn:1000001",
        "tgn:7012149",
        "tgn:2000183",
        "tgn:7007157",
        "tgn:7029392"
    ],
    "tgn:id":4006871,
    "tgn:name":"Manzanar",
    "tgn:placetype":[
        "aat:300008347"
    ]
},
  "bbox": [],
  "geometry": {"coordinates":[-118.0667,36.7333],"type":"Point"}
}