{
  "id": 7028206,
  "type": "Feature",
  "properties": {
    "tgn:hierarchy":[
        "tgn:7028206",
        "tgn:7002445",
        "tgn:1000003",
        "tgn:7019054",
        "tgn:7008591",
        "tgn:7029392"
    ],
    "tgn:id":7028206,
    "tgn:name:en":"West Halton",
    "tgn:placetype":[
        "aat:300008347",
        "aat:300008372"
    ]
},
  "bbox": [],
  "geometry": {"coordinates":[-0.633333,53.666667],"type":"Point"}
}