{
  "id": 2553612,
  "type": "Feature",
  "properties": {
    "tgn:hierarchy":[
        "tgn:2553612",
        "tgn:1000001",
        "tgn:7016172",
        "tgn:2000121",
        "tgn:7012149",
        "tgn:7029392"
    ],
    "tgn:id":2553612,
    "tgn:name":"Oak Grove",
    "tgn:placetype":[
        "aat:300008347"
    ]
},
  "bbox": [],
  "geometry": {"coordinates":[-94.2833,35.4167],"type":"Point"}
}