{
  "id": 2524749,
  "type": "Feature",
  "properties": {
    "tgn:hierarchy":[
        "tgn:2524749",
        "tgn:1000001",
        "tgn:7006451",
        "tgn:7012149",
        "tgn:2000102",
        "tgn:7029392"
    ],
    "tgn:id":2524749,
    "tgn:name":"Morning Glory Mine",
    "tgn:placetype":[
        "aat:300000390"
    ]
},
  "bbox": [],
  "geometry": {"coordinates":[-110.7167,31.4167],"type":"Point"}
}