{
  "id": 2529155,
  "type": "Feature",
  "properties": {
    "tgn:hierarchy":[
        "tgn:2529155",
        "tgn:1000001",
        "tgn:7012149",
        "tgn:2000238",
        "tgn:7007158",
        "tgn:7029392"
    ],
    "tgn:id":2529155,
    "tgn:name":"Mud Gulch",
    "tgn:placetype":[
        "aat:300008761"
    ]
},
  "bbox": [],
  "geometry": {"coordinates":[-105.7333,39.3333],"type":"Point"}
}