{
  "id": 2342510,
  "type": "Feature",
  "properties": {
    "tgn:hierarchy":[
        "tgn:2342510",
        "tgn:1000001",
        "tgn:7012149",
        "tgn:2002125",
        "tgn:7007827",
        "tgn:7029392"
    ],
    "tgn:id":2342510,
    "tgn:name":"Fullmer Hollow",
    "tgn:placetype":[
        "aat:300008761"
    ]
},
  "bbox": [],
  "geometry": {"coordinates":[-111.4167,40.2667],"type":"Point"}
}