{
  "id": 2022218,
  "type": "Feature",
  "properties": {
    "tgn:hierarchy":[
        "tgn:2022218",
        "tgn:1000001",
        "tgn:7012149",
        "tgn:2000367",
        "tgn:7007248",
        "tgn:7029392"
    ],
    "tgn:id":2022218,
    "tgn:name":"Bonaire",
    "tgn:placetype":[
        "aat:300008347"
    ]
},
  "bbox": [],
  "geometry": {"coordinates":[-83.5833,32.5333],"type":"Point"}
}