{
  "id": 7467682,
  "type": "Feature",
  "properties": {
    "tgn:hierarchy":[
        "tgn:7467682",
        "tgn:1000004",
        "tgn:7001014",
        "tgn:1000141",
        "tgn:7029392"
    ],
    "tgn:id":7467682,
    "tgn:name":"Chitouzi",
    "tgn:placetype":[
        "aat:300008347"
    ]
},
  "bbox": [],
  "geometry": {"coordinates":[120.283333,23.583333],"type":"Point"}
}