{
  "id": 2076198,
  "type": "Feature",
  "properties": {
    "tgn:hierarchy":[
        "tgn:2076198",
        "tgn:1000001",
        "tgn:7012149",
        "tgn:2001509",
        "tgn:7007709",
        "tgn:7029392"
    ],
    "tgn:id":2076198,
    "tgn:name":"Princeton",
    "tgn:placetype":[
        "aat:300008347"
    ]
},
  "bbox": [],
  "geometry": {"coordinates":[-78.15,35.45],"type":"Point"}
}