{
  "id": 7128289,
  "type": "Feature",
  "properties": {
    "tgn:hierarchy":[
        "tgn:7128289",
        "tgn:1000003",
        "tgn:7003687",
        "tgn:7000084",
        "tgn:7029392"
    ],
    "tgn:id":7128289,
    "tgn:name":"Niemberg",
    "tgn:placetype":[
        "aat:300008347"
    ]
},
  "bbox": [],
  "geometry": {"coordinates":[12.083333,51.55],"type":"Point"}
}