{
  "id": 2388666,
  "type": "Feature",
  "properties": {
    "tgn:hierarchy":[
        "tgn:2388666",
        "tgn:1000001",
        "tgn:7012149",
        "tgn:7022542",
        "tgn:7007825",
        "tgn:7029392"
    ],
    "tgn:id":2388666,
    "tgn:name":"Hicks-Brown Spring",
    "tgn:placetype":[
        "aat:300008697"
    ]
},
  "bbox": [],
  "geometry": {"coordinates":[-84.4833,35.45],"type":"Point"}
}