{
  "id": 7281426,
  "type": "Feature",
  "properties": {
    "tgn:hierarchy":[
        "tgn:7281426",
        "tgn:1001623",
        "tgn:1000049",
        "tgn:1000002",
        "tgn:7029392"
    ],
    "tgn:id":7281426,
    "tgn:name":"Sur, Morro",
    "tgn:placetype":[
        "aat:300008777"
    ]
},
  "bbox": [],
  "geometry": {"coordinates":[-75.083333,-44.916667],"type":"Point"}
}