{
  "id": 2523634,
  "type": "Feature",
  "properties": {
    "tgn:hierarchy":[
        "tgn:2523634",
        "tgn:1000001",
        "tgn:1002601",
        "tgn:7012149",
        "tgn:7007159",
        "tgn:7029392"
    ],
    "tgn:id":2523634,
    "tgn:name":"Moosehorn Brook",
    "tgn:placetype":[
        "aat:300008699"
    ]
},
  "bbox": [],
  "geometry": {"coordinates":[-73.2833,41.5833],"type":"Point"}
}