{
  "id": 2551830,
  "type": "Feature",
  "properties": {
    "tgn:hierarchy":[
        "tgn:2551830",
        "tgn:1000001",
        "tgn:7016172",
        "tgn:7012149",
        "tgn:2000160",
        "tgn:7029392"
    ],
    "tgn:id":2551830,
    "tgn:name":"Number 79, Ditch",
    "tgn:placetype":[
        "aat:300006075"
    ]
},
  "bbox": [],
  "geometry": {"coordinates":[-90.5667,35.45],"type":"Point"}
}