{
  "id": 2399869,
  "type": "Feature",
  "properties": {
    "tgn:hierarchy":[
        "tgn:2399869",
        "tgn:1000001",
        "tgn:7012149",
        "tgn:2001980",
        "tgn:7007826",
        "tgn:7029392"
    ],
    "tgn:id":2399869,
    "tgn:name":"Horse Camp Waterhole",
    "tgn:placetype":[
        "aat:300008680"
    ]
},
  "bbox": [],
  "geometry": {"coordinates":[-99.8167,30.15],"type":"Point"}
}