<<<<<<< HEAD
{
  "id": 2156127,
  "type": "Feature",
  "properties": {
    "tgn:hierarchy":[
        "tgn:2156127",
        "tgn:1000001",
        "tgn:7012149",
        "tgn:2002264",
        "tgn:7013961",
        "tgn:7029392"
    ],
    "tgn:id":2156127,
    "tgn:name":"Beard Lick Run",
    "tgn:placetype":[
        "aat:300008699"
    ]
},
  "bbox": [],
  "geometry": {"coordinates":[-80.4167,38.1],"type":"Point"}
}
=======
{"geometry":{"type":"Point","coordinates":[-80.416700,38.100000]},"type":"Feature","properties":{"hierarchy":["tgn:2156127","tgn:1000001","tgn:7012149","tgn:2002264","tgn:7013961","tgn:7029392"],"placetype":["aat:300008699"],"id":2156127,"name:xx":"Beard Lick Run"}}
>>>>>>> 03f74aca74312dbeaf24d7e61306dd6a786dc3d0
