{
  "id": 2775909,
  "type": "Feature",
  "properties": {
    "tgn:hierarchy":[
        "tgn:2775909",
        "tgn:1000001",
        "tgn:1002614",
        "tgn:7012149",
        "tgn:7007526",
        "tgn:7029392"
    ],
    "tgn:id":2775909,
    "tgn:name":"Wilson Mines",
    "tgn:placetype":[
        "aat:300000390"
    ]
},
  "bbox": [],
  "geometry": {"coordinates":[-119.1167,38.6667],"type":"Point"}
}