{
  "id": 2089699,
  "type": "Feature",
  "properties": {
    "tgn:hierarchy":[
        "tgn:2089699",
        "tgn:1002153",
        "tgn:1000001",
        "tgn:7012149",
        "tgn:7007710",
        "tgn:7029392"
    ],
    "tgn:id":2089699,
    "tgn:name":"Kaylor",
    "tgn:placetype":[
        "aat:300008347"
    ]
},
  "bbox": [],
  "geometry": {"coordinates":[-79.6667,40.9667],"type":"Point"}
}