{
  "id": 2589864,
  "type": "Feature",
  "properties": {
    "tgn:hierarchy":[
        "tgn:2589864",
        "tgn:1000001",
        "tgn:7012149",
        "tgn:7007158",
        "tgn:2000253",
        "tgn:7029392"
    ],
    "tgn:id":2589864,
    "tgn:name":"Point of Rocks",
    "tgn:placetype":[
        "aat:300008798"
    ]
},
  "bbox": [],
  "geometry": {"coordinates":[-104.35,40.4833],"type":"Point"}
}