{
  "id": 7455632,
  "type": "Feature",
  "properties": {
    "tgn:hierarchy":[
        "tgn:7455632",
        "tgn:7002445",
        "tgn:1000003",
        "tgn:7008117",
        "tgn:7008591",
        "tgn:7029392"
    ],
    "tgn:id":7455632,
    "tgn:name:en":"Duddon Bar",
    "tgn:placetype":[
        "aat:300386885"
    ]
},
  "bbox": [],
  "geometry": {"coordinates":[-3.333333,54.15],"type":"Point"}
}