{
  "id": 2384927,
  "type": "Feature",
  "properties": {
    "tgn:hierarchy":[
        "tgn:2384927",
        "tgn:1000001",
        "tgn:7012149",
        "tgn:1002891",
        "tgn:7007708",
        "tgn:7029392"
    ],
    "tgn:id":2384927,
    "tgn:name":"Helm Canyon",
    "tgn:placetype":[
        "aat:300008761"
    ]
},
  "bbox": [],
  "geometry": {"coordinates":[-120.6333,45.6667],"type":"Point"}
}