{
  "id": 7046620,
  "type": "Feature",
  "properties": {
    "tgn:hierarchy":[
        "tgn:7046620",
        "tgn:7003170",
        "tgn:1000003",
        "tgn:7003125",
        "tgn:1000080",
        "tgn:7029392"
    ],
    "tgn:id":7046620,
    "tgn:name":"Ficareto",
    "tgn:placetype":[
        "aat:300008347"
    ]
},
  "bbox": [],
  "geometry": {"coordinates":[12.483333,42.816667],"type":"Point"}
}