{
  "id": 2059115,
  "type": "Feature",
  "properties": {
    "tgn:hierarchy":[
        "tgn:2059115",
        "tgn:1000001",
        "tgn:7012149",
        "tgn:1002984",
        "tgn:7007523",
        "tgn:7029392"
    ],
    "tgn:id":2059115,
    "tgn:name":"Holstein",
    "tgn:placetype":[
        "aat:300008347"
    ]
},
  "bbox": [],
  "geometry": {"coordinates":[-91.1667,38.65],"type":"Point"}
}