{
  "id": 7562892,
  "type": "Feature",
  "properties": {
    "tgn:hierarchy":[
        "tgn:7562892",
        "tgn:1000004",
        "tgn:7000198",
        "tgn:7016722",
        "tgn:7029392"
    ],
    "tgn:id":7562892,
    "tgn:name:en":"Kalaktar Nagla",
    "tgn:placetype":[
        "aat:300008347"
    ]
},
  "bbox": [],
  "geometry": {"coordinates":[79.4366,27.860991],"type":"Point"}
}