<<<<<<< HEAD
{
  "id": 2765292,
  "type": "Feature",
  "properties": {
    "tgn:hierarchy":[
        "tgn:2765292",
        "tgn:1000001",
        "tgn:7012149",
        "tgn:2001312",
        "tgn:7007524",
        "tgn:7029392"
    ],
    "tgn:id":2765292,
    "tgn:name":"Whitbread Springs",
    "tgn:placetype":[
        "aat:300008697"
    ]
},
  "bbox": [],
  "geometry": {"coordinates":[-106.8833,48.4167],"type":"Point"}
}
=======
{"geometry":{"type":"Point","coordinates":[-106.883300,48.416700]},"type":"Feature","properties":{"hierarchy":["tgn:2765292","tgn:1000001","tgn:7012149","tgn:2001312","tgn:7007524","tgn:7029392"],"placetype":["aat:300008697"],"id":2765292,"name:xx":"Whitbread Springs"}}
>>>>>>> 03f74aca74312dbeaf24d7e61306dd6a786dc3d0
