{
  "id": 2502371,
  "type": "Feature",
  "properties": {
    "tgn:hierarchy":[
        "tgn:2502371",
        "tgn:1000001",
        "tgn:2002366",
        "tgn:7012149",
        "tgn:7007923",
        "tgn:7029392"
    ],
    "tgn:id":2502371,
    "tgn:name":"McKinnon Creek",
    "tgn:placetype":[
        "aat:300008706"
    ]
},
  "bbox": [],
  "geometry": {"coordinates":[-107.4333,44.5333],"type":"Point"}
}