{
  "id": 7393488,
  "type": "Feature",
  "properties": {
    "tgn:hierarchy":[
        "tgn:7393488",
        "tgn:7016644",
        "tgn:1000001",
        "tgn:7005560",
        "tgn:7029392"
    ],
    "tgn:id":7393488,
    "tgn:name":"San Jos\u00e9",
    "tgn:placetype":[
        "aat:300008347"
    ]
},
  "bbox": [],
  "geometry": {"coordinates":[-104.133333,19.166667],"type":"Point"}
}