{
  "id": 2712392,
  "type": "Feature",
  "properties": {
    "tgn:hierarchy":[
        "tgn:2712392",
        "tgn:7006450",
        "tgn:1000001",
        "tgn:7012149",
        "tgn:2124002",
        "tgn:7029392"
    ],
    "tgn:id":2712392,
    "tgn:name":"Tava Island",
    "tgn:placetype":[
        "aat:300008791"
    ]
},
  "bbox": [],
  "geometry": {"coordinates":[-135.4667,56.8167],"type":"Point"}
}