{
  "id": 7449052,
  "type": "Feature",
  "properties": {
    "tgn:hierarchy":[
        "tgn:7449052",
        "tgn:7002444",
        "tgn:1000003",
        "tgn:7009907",
        "tgn:7008591",
        "tgn:7029392"
    ],
    "tgn:id":7449052,
    "tgn:name:en":"Swannies Point",
    "tgn:placetype":[
        "aat:300386846"
    ]
},
  "bbox": [],
  "geometry": {"coordinates":[-2.933333,58.866667],"type":"Point"}
}