{
  "id": 7026970,
  "type": "Feature",
  "properties": {
    "tgn:hierarchy":[
        "tgn:7026970",
        "tgn:7002443",
        "tgn:1000003",
        "tgn:7008591",
        "tgn:7029392"
    ],
    "tgn:id":7026970,
    "tgn:name:en":"Conwy",
    "tgn:placetype":[
        "aat:300387064",
        "aat:300387145",
        "aat:300387071"
    ]
},
  "bbox": [],
  "geometry": {"coordinates":[-3.75,53.083333],"type":"Point"}
}