{
  "id": 7379065,
  "type": "Feature",
  "properties": {
    "tgn:hierarchy":[
        "tgn:7379065",
        "tgn:7005581",
        "tgn:1000001",
        "tgn:7005560",
        "tgn:7029392"
    ],
    "tgn:id":7379065,
    "tgn:name":"Rancho Maravillas de Armend\u00e1riz",
    "tgn:placetype":[
        "aat:300000241"
    ]
},
  "bbox": [],
  "geometry": {"coordinates":[-104.333333,27.766667],"type":"Point"}
}