{
  "id": 7304673,
  "type": "Feature",
  "properties": {
    "tgn:hierarchy":[
        "tgn:7304673",
        "tgn:7002827",
        "tgn:1000003",
        "tgn:7002789",
        "tgn:1000095",
        "tgn:7029392"
    ],
    "tgn:id":7304673,
    "tgn:name":"Ledesma, Arroyo",
    "tgn:placetype":[
        "aat:300008699"
    ]
},
  "bbox": [],
  "geometry": {"coordinates":[-2.75,42.316667],"type":"Point"}
}