{
  "id": 7132050,
  "type": "Feature",
  "properties": {
    "tgn:hierarchy":[
        "tgn:7132050",
        "tgn:7003692",
        "tgn:1000003",
        "tgn:7000084",
        "tgn:7029392"
    ],
    "tgn:id":7132050,
    "tgn:name":"Missen",
    "tgn:placetype":[
        "aat:300000206"
    ]
},
  "bbox": [],
  "geometry": {"coordinates":[9.816667,47.733333],"type":"Point"}
}