{
  "id": 2593593,
  "type": "Feature",
  "properties": {
    "tgn:hierarchy":[
        "tgn:2593593",
        "tgn:2000999",
        "tgn:1000001",
        "tgn:7012149",
        "tgn:7007521",
        "tgn:7029392"
    ],
    "tgn:id":2593593,
    "tgn:name":"Porcupine Lake",
    "tgn:placetype":[
        "aat:300008680"
    ]
},
  "bbox": [],
  "geometry": {"coordinates":[-93.3167,46.3667],"type":"Point"}
}