{
  "id": 7191915,
  "type": "Feature",
  "properties": {
    "tgn:hierarchy":[
        "tgn:7191915",
        "tgn:1000003",
        "tgn:7003685",
        "tgn:7000084",
        "tgn:7029392"
    ],
    "tgn:id":7191915,
    "tgn:name":"F\u00e4llbach",
    "tgn:placetype":[
        "aat:300008347"
    ]
},
  "bbox": [],
  "geometry": {"coordinates":[12.716667,50.483333],"type":"Point"}
}