{
  "id": 7010230,
  "type": "Feature",
  "properties": {
    "tgn:hierarchy":[
        "tgn:7010230",
        "tgn:1000004",
        "tgn:1003405",
        "tgn:7018214",
        "tgn:7002435",
        "tgn:7029392"
    ],
    "tgn:id":7010230,
    "tgn:name":"Novocherkassk",
    "tgn:placetype":[
        "aat:300008347",
        "aat:300387218",
        "aat:300008389",
        "aat:300387308",
        "aat:300387305",
        "aat:300387302"
    ]
},
  "bbox": [],
  "geometry": {"coordinates":[40.0833,47.4167],"type":"Point"}
}