{
  "id": 1129984,
  "type": "Feature",
  "properties": {
    "tgn:hierarchy":[
        "tgn:1129984",
        "tgn:1000004",
        "tgn:1001390",
        "tgn:1000111",
        "tgn:7029392"
    ],
    "tgn:id":1129984,
    "tgn:name":"Shuangtaizi",
    "tgn:placetype":[
        "aat:300008707"
    ]
},
  "bbox": [],
  "geometry": {"coordinates":[121.85,40.9833],"type":"Point"}
}