{
  "id": 7312744,
  "type": "Feature",
  "properties": {
    "tgn:hierarchy":[
        "tgn:7312744",
        "tgn:1001699",
        "tgn:1000049",
        "tgn:1000002",
        "tgn:7029392"
    ],
    "tgn:id":7312744,
    "tgn:name":"Lami, Bajos de",
    "tgn:placetype":[
        "aat:300008808"
    ]
},
  "bbox": [],
  "geometry": {"coordinates":[-73.266667,-41.833333],"type":"Point"}
}