{
  "id": 2670812,
  "type": "Feature",
  "properties": {
    "tgn:hierarchy":[
        "tgn:2670812",
        "tgn:1000001",
        "tgn:1002302",
        "tgn:7012149",
        "tgn:7007568",
        "tgn:7029392"
    ],
    "tgn:id":2670812,
    "tgn:name":"Smith Brook",
    "tgn:placetype":[
        "aat:300008699"
    ]
},
  "bbox": [],
  "geometry": {"coordinates":[-76.0167,42.5833],"type":"Point"}
}