{
  "id": 7472703,
  "type": "Feature",
  "properties": {
    "tgn:hierarchy":[
        "tgn:7472703",
        "tgn:1000004",
        "tgn:7489179",
        "tgn:1000141",
        "tgn:7029392"
    ],
    "tgn:id":7472703,
    "tgn:name":"Dong'ao Qiao",
    "tgn:placetype":[
        "aat:300007836"
    ]
},
  "bbox": [],
  "geometry": {"coordinates":[121.83476,24.521723],"type":"Point"}
}