<<<<<<< HEAD
{
  "id": 7472703,
  "type": "Feature",
  "properties": {
    "tgn:hierarchy":[
        "tgn:7472703",
        "tgn:1000004",
        "tgn:7489179",
        "tgn:1000141",
        "tgn:7029392"
    ],
    "tgn:id":7472703,
    "tgn:name":"Dong'ao Qiao",
    "tgn:placetype":[
        "aat:300007836"
    ]
},
  "bbox": [],
  "geometry": {"coordinates":[121.83476,24.521723],"type":"Point"}
}
=======
{"geometry":{"type":"Point","coordinates":[121.834760,24.521723]},"type":"Feature","properties":{"hierarchy":["tgn:7472703","tgn:1000004","tgn:7489179","tgn:1000141","tgn:7029392"],"placetype":["aat:300007836"],"id":7472703,"name:xx":"Dong'ao Qiao"}}
>>>>>>> 03f74aca74312dbeaf24d7e61306dd6a786dc3d0
