{
  "id": 7255991,
  "type": "Feature",
  "properties": {
    "tgn:hierarchy":[
        "tgn:7255991",
        "tgn:7007877",
        "tgn:1000003",
        "tgn:1000063",
        "tgn:4012014",
        "tgn:7029392"
    ],
    "tgn:id":7255991,
    "tgn:name":"Saint-Pierre",
    "tgn:placetype":[
        "aat:300008347"
    ]
},
  "bbox": [],
  "geometry": {"coordinates":[4.183333,50.316667],"type":"Point"}
}