{
  "id": 2729300,
  "type": "Feature",
  "properties": {
    "tgn:hierarchy":[
        "tgn:2729300",
        "tgn:1000001",
        "tgn:7012149",
        "tgn:1002800",
        "tgn:7007710",
        "tgn:7029392"
    ],
    "tgn:id":2729300,
    "tgn:name":"Triple Divide",
    "tgn:placetype":[
        "aat:300008798"
    ]
},
  "bbox": [],
  "geometry": {"coordinates":[-77.8333,41.8333],"type":"Point"}
}