{
  "id": 7015625,
  "type": "Feature",
  "properties": {
    "tgn:hierarchy":[
        "tgn:7015625",
        "tgn:7004595",
        "tgn:7003005",
        "tgn:1000003",
        "tgn:1000080",
        "tgn:7029392"
    ],
    "tgn:id":7015625,
    "tgn:name":"Telese",
    "tgn:placetype":[
        "aat:300008347"
    ]
},
  "bbox": [],
  "geometry": {"coordinates":[14.533333,41.216667],"type":"Point"}
}