{
  "id": 7215752,
  "type": "Feature",
  "properties": {
    "tgn:hierarchy":[
        "tgn:7215752",
        "tgn:7003692",
        "tgn:1000003",
        "tgn:7000084",
        "tgn:7029392"
    ],
    "tgn:id":7215752,
    "tgn:name":"Altmannshofen",
    "tgn:placetype":[
        "aat:300008347"
    ]
},
  "bbox": [],
  "geometry": {"coordinates":[10.05,47.883333],"type":"Point"}
}