{
  "id": 1089032,
  "type": "Feature",
  "properties": {
    "tgn:hierarchy":[
        "tgn:1089032",
        "tgn:7001242",
        "tgn:1001346",
        "tgn:1000159",
        "tgn:7029392"
    ],
    "tgn:id":1089032,
    "tgn:name":"Kabinda",
    "tgn:placetype":[
        "aat:300008347"
    ]
},
  "bbox": [],
  "geometry": {"coordinates":[24.4833,-6.1667],"type":"Point"}
}