{
  "id": 7448896,
  "type": "Feature",
  "properties": {
    "tgn:hierarchy":[
        "tgn:7448896",
        "tgn:7002445",
        "tgn:1000003",
        "tgn:7008165",
        "tgn:7008591",
        "tgn:7029392"
    ],
    "tgn:id":7448896,
    "tgn:name:en":"South Spit",
    "tgn:placetype":[
        "aat:300008808"
    ]
},
  "bbox": [],
  "geometry": {"coordinates":[-1.483333,55.133333],"type":"Point"}
}