{
  "id": 2171466,
  "type": "Feature",
  "properties": {
    "tgn:hierarchy":[
        "tgn:2171466",
        "tgn:1000001",
        "tgn:2001016",
        "tgn:7012149",
        "tgn:7007521",
        "tgn:7029392"
    ],
    "tgn:id":2171466,
    "tgn:name":"Big Stone Lake",
    "tgn:placetype":[
        "aat:300008680"
    ]
},
  "bbox": [],
  "geometry": {"coordinates":[-94.1167,46.7833],"type":"Point"}
}