<<<<<<< HEAD
{
  "id": 7361136,
  "type": "Feature",
  "properties": {
    "tgn:hierarchy":[
        "tgn:7361136",
        "tgn:1000001",
        "tgn:7005599",
        "tgn:7005560",
        "tgn:7029392"
    ],
    "tgn:id":7361136,
    "tgn:name":"El Huanal",
    "tgn:placetype":[
        "aat:300008347"
    ]
},
  "bbox": [],
  "geometry": {"coordinates":[-96.7,20.083333],"type":"Point"}
}
=======
{"geometry":{"type":"Point","coordinates":[-96.700000,20.083333]},"type":"Feature","properties":{"hierarchy":["tgn:7361136","tgn:1000001","tgn:7005599","tgn:7005560","tgn:7029392"],"placetype":["aat:300008347"],"id":7361136,"name:xx":"El Huanal"}}
>>>>>>> 03f74aca74312dbeaf24d7e61306dd6a786dc3d0
