{
  "id": 1052371,
  "type": "Feature",
  "properties": {
    "tgn:hierarchy":[
        "tgn:1052371",
        "tgn:7011438",
        "tgn:1000004",
        "tgn:7006646",
        "tgn:7029392"
    ],
    "tgn:id":1052371,
    "tgn:name":"Byandovan",
    "tgn:placetype":[
        "aat:300008347"
    ]
},
  "bbox": [],
  "geometry": {"coordinates":[49.3667,39.7667],"type":"Point"}
}