{
  "id": 2003010,
  "type": "Feature",
  "properties": {
    "tgn:hierarchy":[
        "tgn:2003010",
        "tgn:7002659",
        "tgn:1000001",
        "tgn:7012149",
        "tgn:2000041",
        "tgn:7029392"
    ],
    "tgn:id":2003010,
    "tgn:name":"Cedar Hill",
    "tgn:placetype":[
        "aat:300008347",
        "aat:300387210"
    ]
},
  "bbox": [],
  "geometry": {"coordinates":[-86.8167,34.9667],"type":"Point"}
}