{
  "id": 2735824,
  "type": "Feature",
  "properties": {
    "tgn:hierarchy":[
        "tgn:2735824",
        "tgn:7006450",
        "tgn:1000001",
        "tgn:7030517",
        "tgn:7012149",
        "tgn:7029392"
    ],
    "tgn:id":2735824,
    "tgn:name":"Twin Lakes",
    "tgn:placetype":[
        "aat:300008680"
    ]
},
  "bbox": [],
  "geometry": {"coordinates":[-153.85,60.6333],"type":"Point"}
}