{
  "id": 2259499,
  "type": "Feature",
  "properties": {
    "tgn:hierarchy":[
        "tgn:2259499",
        "tgn:1000001",
        "tgn:7006451",
        "tgn:2000093",
        "tgn:7012149",
        "tgn:7029392"
    ],
    "tgn:id":2259499,
    "tgn:name":"Cottonwood Tank",
    "tgn:placetype":[
        "aat:300006191"
    ]
},
  "bbox": [],
  "geometry": {"coordinates":[-111.2333,34.05],"type":"Point"}
}