{
  "id": 2478255,
  "type": "Feature",
  "properties": {
    "tgn:hierarchy":[
        "tgn:2478255",
        "tgn:1000001",
        "tgn:7012149",
        "tgn:2000995",
        "tgn:7007520",
        "tgn:7029392"
    ],
    "tgn:id":2478255,
    "tgn:name":"Macklem Drain",
    "tgn:placetype":[
        "aat:300006075"
    ]
},
  "bbox": [],
  "geometry": {"coordinates":[-82.8667,43.2167],"type":"Point"}
}