{
  "id": 7311795,
  "type": "Feature",
  "properties": {
    "tgn:hierarchy":[
        "tgn:7311795",
        "tgn:1001708",
        "tgn:1000049",
        "tgn:1000002",
        "tgn:7029392"
    ],
    "tgn:id":7311795,
    "tgn:name":"Las Monjas",
    "tgn:placetype":[
        "aat:300387200"
    ]
},
  "bbox": [],
  "geometry": {"coordinates":[-71.166667,-33.516667],"type":"Point"}
}