{
  "id": 2198510,
  "type": "Feature",
  "properties": {
    "tgn:hierarchy":[
        "tgn:2198510",
        "tgn:1000001",
        "tgn:7012149",
        "tgn:2001068",
        "tgn:7007521",
        "tgn:7029392"
    ],
    "tgn:id":2198510,
    "tgn:name":"Browns Lake",
    "tgn:placetype":[
        "aat:300008680"
    ]
},
  "bbox": [],
  "geometry": {"coordinates":[-93.7167,44.6333],"type":"Point"}
}