{
  "id": 2691039,
  "type": "Feature",
  "properties": {
    "tgn:hierarchy":[
        "tgn:2691039",
        "tgn:1000001",
        "tgn:7012149",
        "tgn:2000378",
        "tgn:7007248",
        "tgn:7029392"
    ],
    "tgn:id":2691039,
    "tgn:name":"Stanley Lake",
    "tgn:placetype":[
        "aat:300006191"
    ]
},
  "bbox": [],
  "geometry": {"coordinates":[-82.7833,32.65],"type":"Point"}
}