{
  "id": 7286845,
  "type": "Feature",
  "properties": {
    "tgn:hierarchy":[
        "tgn:7286845",
        "tgn:7002464",
        "tgn:1000049",
        "tgn:1000002",
        "tgn:7029392"
    ],
    "tgn:id":7286845,
    "tgn:name":"Guaneguane, Cerro",
    "tgn:placetype":[
        "aat:300008795"
    ]
},
  "bbox": [],
  "geometry": {"coordinates":[-69.283333,-18.15],"type":"Point"}
}