{
  "id": 7010100,
  "type": "Feature",
  "properties": {
    "tgn:hierarchy":[
        "tgn:7010100",
        "tgn:7002445",
        "tgn:1000003",
        "tgn:7008117",
        "tgn:7008591",
        "tgn:7029392"
    ],
    "tgn:id":7010100,
    "tgn:name:en":"Derwent",
    "tgn:placetype":[
        "aat:300008707",
        "aat:300008699"
    ]
},
  "bbox": [],
  "geometry": {"coordinates":[-0.95,53.75],"type":"Point"}
}