{
  "id": 7040676,
  "type": "Feature",
  "properties": {
    "tgn:hierarchy":[
        "tgn:7040676",
        "tgn:1003506",
        "tgn:1000003",
        "tgn:7002993",
        "tgn:1000080",
        "tgn:7029392"
    ],
    "tgn:id":7040676,
    "tgn:name":"San Quirino, Punte",
    "tgn:placetype":[
        "aat:300008795"
    ]
},
  "bbox": [],
  "geometry": {"coordinates":[13.483333,46.116667],"type":"Point"}
}