{
  "id": 2627829,
  "type": "Feature",
  "properties": {
    "tgn:hierarchy":[
        "tgn:2627829",
        "tgn:1000001",
        "tgn:7012149",
        "tgn:2001254",
        "tgn:7007523",
        "tgn:7029392"
    ],
    "tgn:id":2627829,
    "tgn:name":"Rogue Creek",
    "tgn:placetype":[
        "aat:300008706"
    ]
},
  "bbox": [],
  "geometry": {"coordinates":[-90.8833,38.05],"type":"Point"}
}