{
  "id": 2434407,
  "type": "Feature",
  "properties": {
    "tgn:hierarchy":[
        "tgn:2434407",
        "tgn:7006450",
        "tgn:1000001",
        "tgn:7012149",
        "tgn:2000082",
        "tgn:7029392"
    ],
    "tgn:id":2434407,
    "tgn:name":"Kendrick Islands",
    "tgn:placetype":[
        "aat:300386853"
    ]
},
  "bbox": [],
  "geometry": {"coordinates":[-131.9833,54.8833],"type":"Point"}
}