{
  "id": 2759586,
  "type": "Feature",
  "properties": {
    "tgn:hierarchy":[
        "tgn:2759586",
        "tgn:1000001",
        "tgn:7012149",
        "tgn:1002378",
        "tgn:7007710",
        "tgn:7029392"
    ],
    "tgn:id":2759586,
    "tgn:name":"West Fork Fork Run",
    "tgn:placetype":[
        "aat:300008699"
    ]
},
  "bbox": [],
  "geometry": {"coordinates":[-79.2833,41.5667],"type":"Point"}
}