{
  "id": 1140100,
  "type": "Feature",
  "properties": {
    "tgn:hierarchy":[
        "tgn:1140100",
        "tgn:1000004",
        "tgn:7002087",
        "tgn:1000111",
        "tgn:7029392"
    ],
    "tgn:id":1140100,
    "tgn:name":"Zhuxi",
    "tgn:placetype":[
        "aat:300008347"
    ]
},
  "bbox": [],
  "geometry": {"coordinates":[105.65,29.55],"type":"Point"}
}