<<<<<<< HEAD
{
  "id": 2259551,
  "type": "Feature",
  "properties": {
    "tgn:hierarchy":[
        "tgn:2259551",
        "tgn:1000001",
        "tgn:7012149",
        "tgn:2002113",
        "tgn:7007827",
        "tgn:7029392"
    ],
    "tgn:id":2259551,
    "tgn:name":"Cottonwood Wash",
    "tgn:placetype":[
        "aat:300008761"
    ]
},
  "bbox": [],
  "geometry": {"coordinates":[-111.3833,37.0667],"type":"Point"}
}
=======
{"geometry":{"type":"Point","coordinates":[-111.383300,37.066700]},"type":"Feature","properties":{"hierarchy":["tgn:2259551","tgn:1000001","tgn:7012149","tgn:2002113","tgn:7007827","tgn:7029392"],"placetype":["aat:300008761"],"id":2259551,"name:xx":"Cottonwood Wash"}}
>>>>>>> 03f74aca74312dbeaf24d7e61306dd6a786dc3d0
