{
  "id": 7578367,
  "type": "Feature",
  "properties": {
    "tgn:hierarchy":[
        "tgn:7578367",
        "tgn:1000004",
        "tgn:7000198",
        "tgn:1001895",
        "tgn:7029392"
    ],
    "tgn:id":7578367,
    "tgn:name:en":"Tundia Nad\u012b",
    "tgn:placetype":[
        "aat:300008699"
    ]
},
  "bbox": [],
  "geometry": {"coordinates":[79.511193,21.584515],"type":"Point"}
}