{
  "id": 7558766,
  "type": "Feature",
  "properties": {
    "tgn:hierarchy":[
        "tgn:7558766",
        "tgn:1000004",
        "tgn:7000198",
        "tgn:7016722",
        "tgn:7029392"
    ],
    "tgn:id":7558766,
    "tgn:name:en":"P\u016bth Kh\u0101s",
    "tgn:placetype":[
        "aat:300008347"
    ]
},
  "bbox": [],
  "geometry": {"coordinates":[77.584414,29.029351],"type":"Point"}
}