{
  "id": 7325188,
  "type": "Feature",
  "properties": {
    "tgn:hierarchy":[
        "tgn:7325188",
        "tgn:7002829",
        "tgn:1000003",
        "tgn:7002786",
        "tgn:1000095",
        "tgn:7029392"
    ],
    "tgn:id":7325188,
    "tgn:name":"Santa Eufemia",
    "tgn:placetype":[
        "aat:300008347"
    ]
},
  "bbox": [],
  "geometry": {"coordinates":[-7.633333,42.966667],"type":"Point"}
}