{
  "id": 2520679,
  "type": "Feature",
  "properties": {
    "tgn:hierarchy":[
        "tgn:2520679",
        "tgn:1000001",
        "tgn:7012149",
        "tgn:1002392",
        "tgn:7007157",
        "tgn:7029392"
    ],
    "tgn:id":2520679,
    "tgn:name":"Mono Divide",
    "tgn:placetype":[
        "aat:300266640"
    ]
},
  "bbox": [],
  "geometry": {"coordinates":[-118.8333,37.3667],"type":"Point"}
}