{
  "id": 2228631,
  "type": "Feature",
  "properties": {
    "tgn:hierarchy":[
        "tgn:2228631",
        "tgn:1000001",
        "tgn:2001812",
        "tgn:7012149",
        "tgn:7007713",
        "tgn:7029392"
    ],
    "tgn:id":2228631,
    "tgn:name":"Cedar Creek Island",
    "tgn:placetype":[
        "aat:300008791"
    ]
},
  "bbox": [],
  "geometry": {"coordinates":[-99.9167,44.15],"type":"Point"}
}