{
  "id": 2345449,
  "type": "Feature",
  "properties": {
    "tgn:hierarchy":[
        "tgn:2345449",
        "tgn:1000001",
        "tgn:7016172",
        "tgn:7012149",
        "tgn:2000137",
        "tgn:7029392"
    ],
    "tgn:id":2345449,
    "tgn:name":"Garner Spring",
    "tgn:placetype":[
        "aat:300008697"
    ]
},
  "bbox": [],
  "geometry": {"coordinates":[-92.1167,36.1167],"type":"Point"}
}