{
  "id": 1137875,
  "type": "Feature",
  "properties": {
    "tgn:hierarchy":[
        "tgn:1137875",
        "tgn:1000004",
        "tgn:1003418",
        "tgn:7018214",
        "tgn:7002435",
        "tgn:7029392"
    ],
    "tgn:id":1137875,
    "tgn:name":"Lunino",
    "tgn:placetype":[
        "aat:300008347"
    ]
},
  "bbox": [],
  "geometry": {"coordinates":[38.4833,54.15],"type":"Point"}
}