{
  "id": 7583605,
  "type": "Feature",
  "properties": {
    "tgn:hierarchy":[
        "tgn:7583605",
        "tgn:1000004",
        "tgn:7000198",
        "tgn:1001894",
        "tgn:7029392"
    ],
    "tgn:id":7583605,
    "tgn:name:en":"Muria ka Pah\u0101r",
    "tgn:placetype":[
        "aat:300008795"
    ]
},
  "bbox": [],
  "geometry": {"coordinates":[78.912519,25.190738],"type":"Point"}
}