{
  "id": 2361290,
  "type": "Feature",
  "properties": {
    "tgn:hierarchy":[
        "tgn:2361290",
        "tgn:1000001",
        "tgn:7012149",
        "tgn:1002682",
        "tgn:7007710",
        "tgn:7029392"
    ],
    "tgn:id":2361290,
    "tgn:name":"Gravel Place",
    "tgn:placetype":[
        "aat:300008347"
    ]
},
  "bbox": [],
  "geometry": {"coordinates":[-75.1833,41.0167],"type":"Point"}
}