{
  "id": 2341053,
  "type": "Feature",
  "properties": {
    "tgn:hierarchy":[
        "tgn:2341053",
        "tgn:1000001",
        "tgn:2000924",
        "tgn:7012149",
        "tgn:7007515",
        "tgn:7029392"
    ],
    "tgn:id":2341053,
    "tgn:name":"Friendship Harbor",
    "tgn:placetype":[
        "aat:300132316"
    ]
},
  "bbox": [],
  "geometry": {"coordinates":[-69.3333,43.9667],"type":"Point"}
}