{
  "id": 2726017,
  "type": "Feature",
  "properties": {
    "tgn:hierarchy":[
        "tgn:2726017",
        "tgn:7006450",
        "tgn:1000001",
        "tgn:7012149",
        "tgn:2000088",
        "tgn:7029392"
    ],
    "tgn:id":2726017,
    "tgn:name":"Totem Point",
    "tgn:placetype":[
        "aat:300008850"
    ]
},
  "bbox": [],
  "geometry": {"coordinates":[-133.4333,56.45],"type":"Point"}
}