<<<<<<< HEAD
{
  "id": 7358451,
  "type": "Feature",
  "properties": {
    "tgn:hierarchy":[
        "tgn:7358451",
        "tgn:7005583",
        "tgn:1000001",
        "tgn:7005560",
        "tgn:7029392"
    ],
    "tgn:id":7358451,
    "tgn:name":"Coyotes",
    "tgn:placetype":[
        "aat:300008347"
    ]
},
  "bbox": [],
  "geometry": {"coordinates":[-104.7,24.25],"type":"Point"}
}
=======
{"geometry":{"type":"Point","coordinates":[-104.700000,24.250000]},"type":"Feature","properties":{"hierarchy":["tgn:7358451","tgn:7005583","tgn:1000001","tgn:7005560","tgn:7029392"],"placetype":["aat:300008347"],"id":7358451,"name:xx":"Coyotes"}}
>>>>>>> 03f74aca74312dbeaf24d7e61306dd6a786dc3d0
