{
  "id": 2749373,
  "type": "Feature",
  "properties": {
    "tgn:hierarchy":[
        "tgn:2749373",
        "tgn:1002171",
        "tgn:1000001",
        "tgn:7012149",
        "tgn:7007710",
        "tgn:7029392"
    ],
    "tgn:id":2749373,
    "tgn:name":"Wallory Bar",
    "tgn:placetype":[
        "aat:300132348"
    ]
},
  "bbox": [],
  "geometry": {"coordinates":[-80.45,40.6167],"type":"Point"}
}