{
  "id": 7276237,
  "type": "Feature",
  "properties": {
    "tgn:hierarchy":[
        "tgn:7276237",
        "tgn:1001657",
        "tgn:1000049",
        "tgn:1000002",
        "tgn:7029392"
    ],
    "tgn:id":7276237,
    "tgn:name":"Tilito, Portezuelo",
    "tgn:placetype":[
        "aat:300259572"
    ]
},
  "bbox": [],
  "geometry": {"coordinates":[-70.15,-29.75],"type":"Point"}
}