<<<<<<< HEAD
{
  "id": 2333180,
  "type": "Feature",
  "properties": {
    "tgn:hierarchy":[
        "tgn:2333180",
        "tgn:1000001",
        "tgn:2001786",
        "tgn:7012149",
        "tgn:7007713",
        "tgn:7029392"
    ],
    "tgn:id":2333180,
    "tgn:name":"Flynn Creek",
    "tgn:placetype":[
        "aat:300008706"
    ]
},
  "bbox": [],
  "geometry": {"coordinates":[-103.55,43.6833],"type":"Point"}
}
=======
{"geometry":{"type":"Point","coordinates":[-103.550000,43.683300]},"type":"Feature","properties":{"hierarchy":["tgn:2333180","tgn:1000001","tgn:2001786","tgn:7012149","tgn:7007713","tgn:7029392"],"placetype":["aat:300008706"],"id":2333180,"name:xx":"Flynn Creek"}}
>>>>>>> 03f74aca74312dbeaf24d7e61306dd6a786dc3d0
