{
  "id": 2168870,
  "type": "Feature",
  "properties": {
    "tgn:hierarchy":[
        "tgn:2168870",
        "tgn:1000001",
        "tgn:7012149",
        "tgn:1002521",
        "tgn:7007920",
        "tgn:7029392"
    ],
    "tgn:id":2168870,
    "tgn:name":"Big Hump",
    "tgn:placetype":[
        "aat:300008798"
    ]
},
  "bbox": [],
  "geometry": {"coordinates":[-123.0833,47.6833],"type":"Point"}
}