{
  "id": 7132471,
  "type": "Feature",
  "properties": {
    "tgn:hierarchy":[
        "tgn:7132471",
        "tgn:7003669",
        "tgn:1000003",
        "tgn:7000084",
        "tgn:7029392"
    ],
    "tgn:id":7132471,
    "tgn:name":"Minderbetzigau",
    "tgn:placetype":[
        "aat:300008347"
    ]
},
  "bbox": [],
  "geometry": {"coordinates":[10.366667,47.733333],"type":"Point"}
}