{
  "id": 7536408,
  "type": "Feature",
  "properties": {
    "tgn:hierarchy":[
        "tgn:7536408",
        "tgn:7001242",
        "tgn:7016833",
        "tgn:1001418",
        "tgn:7029392"
    ],
    "tgn:id":7536408,
    "tgn:name:en":"Gill, Deir el",
    "tgn:placetype":[
        "aat:300386860"
    ]
},
  "bbox": [],
  "geometry": {"coordinates":[27.970745,30.735352],"type":"Point"}
}