{
  "id": 2501195,
  "type": "Feature",
  "properties": {
    "tgn:hierarchy":[
        "tgn:2501195",
        "tgn:7002659",
        "tgn:1000001",
        "tgn:2000013",
        "tgn:7012149",
        "tgn:7029392"
    ],
    "tgn:id":2501195,
    "tgn:name":"McGhee Mine",
    "tgn:placetype":[
        "aat:300000390"
    ]
},
  "bbox": [],
  "geometry": {"coordinates":[-86.0167,33.2167],"type":"Point"}
}