{
  "id": 2653001,
  "type": "Feature",
  "properties": {
    "tgn:hierarchy":[
        "tgn:2653001",
        "tgn:1000001",
        "tgn:7012149",
        "tgn:2002374",
        "tgn:7007923",
        "tgn:7029392"
    ],
    "tgn:id":2653001,
    "tgn:name":"Seven Brothers Lakes",
    "tgn:placetype":[
        "aat:300008680"
    ]
},
  "bbox": [],
  "geometry": {"coordinates":[-107.0667,44.3167],"type":"Point"}
}