{
  "id": 2359821,
  "type": "Feature",
  "properties": {
    "tgn:hierarchy":[
        "tgn:2359821",
        "tgn:1000001",
        "tgn:7006451",
        "tgn:7012149",
        "tgn:7029392"
    ],
    "tgn:id":2359821,
    "tgn:name":"Grapevine Draw",
    "tgn:placetype":[
        "aat:300008761"
    ]
},
  "bbox": [],
  "geometry": {"coordinates":[-110.7833,34.4667],"type":"Point"}
}