{
  "id": 2050329,
  "type": "Feature",
  "properties": {
    "tgn:hierarchy":[
        "tgn:2050329",
        "tgn:1000001",
        "tgn:7019982",
        "tgn:7012149",
        "tgn:7007517",
        "tgn:7029392"
    ],
    "tgn:id":2050329,
    "tgn:name":"North Wilbraham",
    "tgn:placetype":[
        "aat:300387016"
    ]
},
  "bbox": [],
  "geometry": {"coordinates":[-72.4167,42.15],"type":"Point"}
}