{
  "id": 2690504,
  "type": "Feature",
  "properties": {
    "tgn:hierarchy":[
        "tgn:2690504",
        "tgn:1000001",
        "tgn:2000954",
        "tgn:7012149",
        "tgn:7007520",
        "tgn:7029392"
    ],
    "tgn:id":2690504,
    "tgn:name":"Staley Lake",
    "tgn:placetype":[
        "aat:300008680"
    ]
},
  "bbox": [],
  "geometry": {"coordinates":[-84.6167,44.6333],"type":"Point"}
}