{
  "id": 7584672,
  "type": "Feature",
  "properties": {
    "tgn:hierarchy":[
        "tgn:7584672",
        "tgn:1000004",
        "tgn:7000198",
        "tgn:7016883",
        "tgn:7029392"
    ],
    "tgn:id":7584672,
    "tgn:name:en":"Ganeshpur Protected Forest",
    "tgn:placetype":[
        "aat:300008863"
    ]
},
  "bbox": [],
  "geometry": {"coordinates":[76.560575,30.113158],"type":"Point"}
}