{
  "id": 7437192,
  "type": "Feature",
  "properties": {
    "tgn:hierarchy":[
        "tgn:7437192",
        "tgn:1000001",
        "tgn:7005592",
        "tgn:7005560",
        "tgn:7029392"
    ],
    "tgn:id":7437192,
    "tgn:name":"Signoret",
    "tgn:placetype":[
        "aat:300007783"
    ]
},
  "bbox": [],
  "geometry": {"coordinates":[-98.083333,19.033333],"type":"Point"}
}