{
  "id": 2730541,
  "type": "Feature",
  "properties": {
    "tgn:hierarchy":[
        "tgn:2730541",
        "tgn:1000001",
        "tgn:7012149",
        "tgn:2002332",
        "tgn:7007922",
        "tgn:7029392"
    ],
    "tgn:id":2730541,
    "tgn:name":"Truman",
    "tgn:placetype":[
        "aat:300008347"
    ]
},
  "bbox": [],
  "geometry": {"coordinates":[-90.2167,42.7167],"type":"Point"}
}