{
  "id": 2351226,
  "type": "Feature",
  "properties": {
    "tgn:hierarchy":[
        "tgn:2351226",
        "tgn:1000001",
        "tgn:7012149",
        "tgn:1002945",
        "tgn:7007710",
        "tgn:7029392"
    ],
    "tgn:id":2351226,
    "tgn:name":"Gleason Hollow",
    "tgn:placetype":[
        "aat:300008761"
    ]
},
  "bbox": [],
  "geometry": {"coordinates":[-77.4833,41.5833],"type":"Point"}
}