<<<<<<< HEAD
{
  "id": 2158155,
  "type": "Feature",
  "properties": {
    "tgn:hierarchy":[
        "tgn:2158155",
        "tgn:1000001",
        "tgn:1002665",
        "tgn:7012149",
        "tgn:7007517",
        "tgn:7029392"
    ],
    "tgn:id":2158155,
    "tgn:name":"Beaver Pond Brook",
    "tgn:placetype":[
        "aat:300008699"
    ]
},
  "bbox": [],
  "geometry": {"coordinates":[-71.6667,42.5667],"type":"Point"}
}
=======
{"geometry":{"type":"Point","coordinates":[-71.666700,42.566700]},"type":"Feature","properties":{"hierarchy":["tgn:2158155","tgn:1000001","tgn:1002665","tgn:7012149","tgn:7007517","tgn:7029392"],"placetype":["aat:300008699"],"id":2158155,"name:xx":"Beaver Pond Brook"}}
>>>>>>> 03f74aca74312dbeaf24d7e61306dd6a786dc3d0
