<<<<<<< HEAD
{
  "id": 7375653,
  "type": "Feature",
  "properties": {
    "tgn:hierarchy":[
        "tgn:7375653",
        "tgn:1000001",
        "tgn:7005597",
        "tgn:7005560",
        "tgn:7029392"
    ],
    "tgn:id":7375653,
    "tgn:name":"Rancho Las Flores",
    "tgn:placetype":[
        "aat:300000241"
    ]
},
  "bbox": [],
  "geometry": {"coordinates":[-98.6,24.866667],"type":"Point"}
}
=======
{"geometry":{"type":"Point","coordinates":[-98.600000,24.866667]},"type":"Feature","properties":{"hierarchy":["tgn:7375653","tgn:1000001","tgn:7005597","tgn:7005560","tgn:7029392"],"placetype":["aat:300000241"],"id":7375653,"name:xx":"Rancho Las Flores"}}
>>>>>>> 03f74aca74312dbeaf24d7e61306dd6a786dc3d0
