{
  "id": 2601242,
  "type": "Feature",
  "properties": {
    "tgn:hierarchy":[
        "tgn:2601242",
        "tgn:1000001",
        "tgn:7012149",
        "tgn:2001952",
        "tgn:7007826",
        "tgn:7029392"
    ],
    "tgn:id":2601242,
    "tgn:name":"Punta de las Bahias",
    "tgn:placetype":[
        "aat:300008850"
    ]
},
  "bbox": [],
  "geometry": {"coordinates":[-97.35,26.0667],"type":"Point"}
}