<<<<<<< HEAD
{
  "id": 7023967,
  "type": "Feature",
  "properties": {
    "tgn:hierarchy":[
        "tgn:7023967",
        "tgn:1001102",
        "tgn:7018452",
        "tgn:1000004",
        "tgn:1000144",
        "tgn:7029392"
    ],
    "tgn:id":7023967,
    "tgn:name":"Aksu",
    "tgn:placetype":[
        "aat:300008347",
        "aat:300000810",
        "aat:300008375"
    ]
},
  "bbox": [],
  "geometry": {"coordinates":[30.8,36.9667],"type":"Point"}
}
=======
{"geometry":{"type":"Point","coordinates":[30.800000,36.966700]},"type":"Feature","properties":{"hierarchy":["tgn:7023967","tgn:1001102","tgn:7018452","tgn:1000004","tgn:1000144","tgn:7029392"],"placetype":["aat:300008347","aat:300000810","aat:300008375"],"id":7023967,"name:xx":"Aksu"}}
>>>>>>> 03f74aca74312dbeaf24d7e61306dd6a786dc3d0
