<<<<<<< HEAD
{
  "id": 7353192,
  "type": "Feature",
  "properties": {
    "tgn:hierarchy":[
        "tgn:7353192",
        "tgn:1000001",
        "tgn:7005595",
        "tgn:7005560",
        "tgn:7029392"
    ],
    "tgn:id":7353192,
    "tgn:name":"Buena Vista",
    "tgn:placetype":[
        "aat:300008347"
    ]
},
  "bbox": [],
  "geometry": {"coordinates":[-108.783333,26.1],"type":"Point"}
}
=======
{"geometry":{"type":"Point","coordinates":[-108.783333,26.100000]},"type":"Feature","properties":{"hierarchy":["tgn:7353192","tgn:1000001","tgn:7005595","tgn:7005560","tgn:7029392"],"placetype":["aat:300008347"],"id":7353192,"name:xx":"Buena Vista"}}
>>>>>>> 03f74aca74312dbeaf24d7e61306dd6a786dc3d0
