<<<<<<< HEAD
{
  "id": 2154782,
  "type": "Feature",
  "properties": {
    "tgn:hierarchy":[
        "tgn:2154782",
        "tgn:1000001",
        "tgn:7012149",
        "tgn:2001964",
        "tgn:7007826",
        "tgn:7029392"
    ],
    "tgn:id":2154782,
    "tgn:name":"Bear Head Creek",
    "tgn:placetype":[
        "aat:300008706"
    ]
},
  "bbox": [],
  "geometry": {"coordinates":[-97.25,33.8333],"type":"Point"}
}
=======
{"geometry":{"type":"Point","coordinates":[-97.250000,33.833300]},"type":"Feature","properties":{"hierarchy":["tgn:2154782","tgn:1000001","tgn:7012149","tgn:2001964","tgn:7007826","tgn:7029392"],"placetype":["aat:300008706"],"id":2154782,"name:xx":"Bear Head Creek"}}
>>>>>>> 03f74aca74312dbeaf24d7e61306dd6a786dc3d0
