{
  "id": 2154782,
  "type": "Feature",
  "properties": {
    "tgn:hierarchy":[
        "tgn:2154782",
        "tgn:1000001",
        "tgn:7012149",
        "tgn:2001964",
        "tgn:7007826",
        "tgn:7029392"
    ],
    "tgn:id":2154782,
    "tgn:name":"Bear Head Creek",
    "tgn:placetype":[
        "aat:300008706"
    ]
},
  "bbox": [],
  "geometry": {"coordinates":[-97.25,33.8333],"type":"Point"}
}