{
  "id": 7017240,
  "type": "Feature",
  "properties": {
    "tgn:hierarchy":[
        "tgn:7017240",
        "tgn:1000003",
        "tgn:7002881",
        "tgn:1000070",
        "tgn:7029392"
    ],
    "tgn:id":7017240,
    "tgn:name":"Luxeuil-les-Bains",
    "tgn:placetype":[
        "aat:300387273",
        "aat:300008347",
        "aat:300387330",
        "aat:300008375",
        "aat:300387294"
    ]
},
  "bbox": [],
  "geometry": {"coordinates":[6.364997,47.817099],"type":"Point"}
}