{
  "id": 7469016,
  "type": "Feature",
  "properties": {
    "tgn:hierarchy":[
        "tgn:7469016",
        "tgn:7498210",
        "tgn:1000004",
        "tgn:1000141",
        "tgn:7029392"
    ],
    "tgn:id":7469016,
    "tgn:name":"Fuzhengcun",
    "tgn:placetype":[
        "aat:300008347"
    ]
},
  "bbox": [],
  "geometry": {"coordinates":[119.983333,25.966667],"type":"Point"}
}