{
  "id": 7390496,
  "type": "Feature",
  "properties": {
    "tgn:hierarchy":[
        "tgn:7390496",
        "tgn:1001853",
        "tgn:1000001",
        "tgn:7005560",
        "tgn:7029392"
    ],
    "tgn:id":7390496,
    "tgn:name":"Rancho San Fernando",
    "tgn:placetype":[
        "aat:300008347"
    ]
},
  "bbox": [],
  "geometry": {"coordinates":[-100.866667,25.066667],"type":"Point"}
}