{
  "id": 7579227,
  "type": "Feature",
  "properties": {
    "tgn:hierarchy":[
        "tgn:7579227",
        "tgn:1000004",
        "tgn:1001869",
        "tgn:7000198",
        "tgn:7029392"
    ],
    "tgn:id":7579227,
    "tgn:name:en":"Umars\u0101di Creek",
    "tgn:placetype":[
        "aat:300387084"
    ]
},
  "bbox": [],
  "geometry": {"coordinates":[72.866667,20.533333],"type":"Point"}
}