{
  "id": 2218831,
  "type": "Feature",
  "properties": {
    "tgn:hierarchy":[
        "tgn:2218831",
        "tgn:1000001",
        "tgn:7012149",
        "tgn:7007568",
        "tgn:7029392"
    ],
    "tgn:id":2218831,
    "tgn:name":"Caneadea Creek",
    "tgn:placetype":[
        "aat:300008706"
    ]
},
  "bbox": [],
  "geometry": {"coordinates":[-78.3667,42.3333],"type":"Point"}
}