{
  "id": 2322198,
  "type": "Feature",
  "properties": {
    "tgn:hierarchy":[
        "tgn:2322198",
        "tgn:1000001",
        "tgn:1002601",
        "tgn:7012149",
        "tgn:7007159",
        "tgn:7029392"
    ],
    "tgn:id":2322198,
    "tgn:name":"Fall Mountain Lake",
    "tgn:placetype":[
        "aat:300008680"
    ]
},
  "bbox": [],
  "geometry": {"coordinates":[-72.9833,41.6333],"type":"Point"}
}