{
  "id": 7376139,
  "type": "Feature",
  "properties": {
    "tgn:hierarchy":[
        "tgn:7376139",
        "tgn:1000001",
        "tgn:7005590",
        "tgn:7005560",
        "tgn:7029392"
    ],
    "tgn:id":7376139,
    "tgn:name":"Las Zarquillas",
    "tgn:placetype":[
        "aat:300006191"
    ]
},
  "bbox": [],
  "geometry": {"coordinates":[-102.516667,20.033333],"type":"Point"}
}