{
  "id": 7354655,
  "type": "Feature",
  "properties": {
    "tgn:hierarchy":[
        "tgn:7354655",
        "tgn:7005581",
        "tgn:1000001",
        "tgn:7005560",
        "tgn:7029392"
    ],
    "tgn:id":7354655,
    "tgn:name":"Estacion Catamnas",
    "tgn:placetype":[
        "aat:300007783"
    ]
},
  "bbox": [],
  "geometry": {"coordinates":[-105.616667,26.666667],"type":"Point"}
}