{
  "id": 7068071,
  "type": "Feature",
  "properties": {
    "tgn:hierarchy":[
        "tgn:7068071",
        "tgn:7000096",
        "tgn:1000003",
        "tgn:7000084",
        "tgn:7029392"
    ],
    "tgn:id":7068071,
    "tgn:name":"Gut Triglitz",
    "tgn:placetype":[
        "aat:300000206"
    ]
},
  "bbox": [],
  "geometry": {"coordinates":[12.116667,53.216667],"type":"Point"}
}