{
  "id": 7567439,
  "type": "Feature",
  "properties": {
    "tgn:hierarchy":[
        "tgn:7567439",
        "tgn:1000004",
        "tgn:7000201",
        "tgn:7000198",
        "tgn:7029392"
    ],
    "tgn:id":7567439,
    "tgn:name:en":"Surkhpur",
    "tgn:placetype":[
        "aat:300008347"
    ]
},
  "bbox": [],
  "geometry": {"coordinates":[76.942852,28.62588],"type":"Point"}
}