{
  "id": 1052569,
  "type": "Feature",
  "properties": {
    "tgn:hierarchy":[
        "tgn:1052569",
        "tgn:1000004",
        "tgn:1003405",
        "tgn:7018214",
        "tgn:7002435",
        "tgn:7029392"
    ],
    "tgn:id":1052569,
    "tgn:name":"Bataysk",
    "tgn:placetype":[
        "aat:300008347"
    ]
},
  "bbox": [],
  "geometry": {"coordinates":[39.7667,47.15],"type":"Point"}
}