{
  "id": 7482690,
  "type": "Feature",
  "properties": {
    "tgn:hierarchy":[
        "tgn:7482690",
        "tgn:1000004",
        "tgn:7001009",
        "tgn:1000141",
        "tgn:7029392"
    ],
    "tgn:id":7482690,
    "tgn:name":"Yisheng Gong",
    "tgn:placetype":[
        "aat:300007595"
    ]
},
  "bbox": [],
  "geometry": {"coordinates":[120.568611,24.249444],"type":"Point"}
}