{
  "id": 7279637,
  "type": "Feature",
  "properties": {
    "tgn:hierarchy":[
        "tgn:7279637",
        "tgn:1001637",
        "tgn:1000049",
        "tgn:1000002",
        "tgn:7029392"
    ],
    "tgn:id":7279637,
    "tgn:name":"Renegado, Estero",
    "tgn:placetype":[
        "aat:300008699"
    ]
},
  "bbox": [],
  "geometry": {"coordinates":[-71.583333,-37.533333],"type":"Point"}
}