{
  "id": 2175246,
  "type": "Feature",
  "properties": {
    "tgn:hierarchy":[
        "tgn:2175246",
        "tgn:1000001",
        "tgn:7012149",
        "tgn:2002333",
        "tgn:7007922",
        "tgn:7029392"
    ],
    "tgn:id":2175246,
    "tgn:name":"Black Brook",
    "tgn:placetype":[
        "aat:300008699"
    ]
},
  "bbox": [],
  "geometry": {"coordinates":[-89.3167,45.2167],"type":"Point"}
}