{
  "id": 1012077,
  "type": "Feature",
  "properties": {
    "tgn:hierarchy":[
        "tgn:1012077",
        "tgn:7593113",
        "tgn:7016620",
        "tgn:7593112",
        "tgn:1000001",
        "tgn:7029392"
    ],
    "tgn:id":1012077,
    "tgn:name:nl":"Lacre Punt",
    "tgn:placetype":[
        "aat:300386846"
    ]
},
  "bbox": [],
  "geometry": {"coordinates":[-68.2333,12.0167],"type":"Point"}
}