{
  "id": 2075841,
  "type": "Feature",
  "properties": {
    "tgn:hierarchy":[
        "tgn:2075841",
        "tgn:1000001",
        "tgn:7012149",
        "tgn:2001506",
        "tgn:7007709",
        "tgn:7029392"
    ],
    "tgn:id":2075841,
    "tgn:name":"Nebraska",
    "tgn:placetype":[
        "aat:300008347"
    ]
},
  "bbox": [],
  "geometry": {"coordinates":[-76.05,35.45],"type":"Point"}
}