{
  "id": 1092014,
  "type": "Feature",
  "properties": {
    "tgn:hierarchy":[
        "tgn:1092014",
        "tgn:7001242",
        "tgn:7015049",
        "tgn:1000182",
        "tgn:7029392"
    ],
    "tgn:id":1092014,
    "tgn:name":"Ibi",
    "tgn:placetype":[
        "aat:300008347"
    ]
},
  "bbox": [],
  "geometry": {"coordinates":[9.7333,8.1833],"type":"Point"}
}