{
  "id": 2224935,
  "type": "Feature",
  "properties": {
    "tgn:hierarchy":[
        "tgn:2224935",
        "tgn:7002659",
        "tgn:1000001",
        "tgn:2000019",
        "tgn:7012149",
        "tgn:7029392"
    ],
    "tgn:id":2224935,
    "tgn:name":"Cassidy Branch",
    "tgn:placetype":[
        "aat:300008699"
    ]
},
  "bbox": [],
  "geometry": {"coordinates":[-86.2167,31.1333],"type":"Point"}
}