<<<<<<< HEAD
{
  "id": 7484804,
  "type": "Feature",
  "properties": {
    "tgn:hierarchy":[
        "tgn:7484804",
        "tgn:1000004",
        "tgn:7001009",
        "tgn:1000141",
        "tgn:7029392"
    ],
    "tgn:id":7484804,
    "tgn:name":"Qingshan Suidao",
    "tgn:placetype":[
        "aat:300007899"
    ]
},
  "bbox": [],
  "geometry": {"coordinates":[121.096667,24.241389],"type":"Point"}
}
=======
{"geometry":{"type":"Point","coordinates":[121.096667,24.241389]},"type":"Feature","properties":{"hierarchy":["tgn:7484804","tgn:1000004","tgn:7001009","tgn:1000141","tgn:7029392"],"placetype":["aat:300007899"],"id":7484804,"name:xx":"Qingshan Suidao"}}
>>>>>>> 03f74aca74312dbeaf24d7e61306dd6a786dc3d0
