{
  "id": 7013682,
  "type": "Feature",
  "properties": {
    "tgn:hierarchy":[
        "tgn:7013682",
        "tgn:1000001",
        "tgn:1002207",
        "tgn:7012149",
        "tgn:7007240",
        "tgn:7029392"
    ],
    "tgn:id":7013682,
    "tgn:name":"Hallandale",
    "tgn:placetype":[
        "aat:300008347"
    ]
},
  "bbox": [],
  "geometry": {"coordinates":[-80.1333,25.9667],"type":"Point"}
}