{
  "id": 7523682,
  "type": "Feature",
  "properties": {
    "tgn:hierarchy":[
        "tgn:7523682",
        "tgn:7001242",
        "tgn:7016833",
        "tgn:1001418",
        "tgn:7029392"
    ],
    "tgn:id":7523682,
    "tgn:name:en":"Battuma, Alam",
    "tgn:placetype":[
        "aat:300008777"
    ]
},
  "bbox": [],
  "geometry": {"coordinates":[25.217709,31.415379],"type":"Point"}
}