{
  "id": 2348158,
  "type": "Feature",
  "properties": {
    "tgn:hierarchy":[
        "tgn:2348158",
        "tgn:1000001",
        "tgn:2001577",
        "tgn:7012149",
        "tgn:7007705",
        "tgn:7029392"
    ],
    "tgn:id":2348158,
    "tgn:name":"Gert Buttes",
    "tgn:placetype":[
        "aat:300266640"
    ]
},
  "bbox": [],
  "geometry": {"coordinates":[-102.3167,46.2667],"type":"Point"}
}