<<<<<<< HEAD
{
  "id": 7028220,
  "type": "Feature",
  "properties": {
    "tgn:hierarchy":[
        "tgn:7028220",
        "tgn:7002445",
        "tgn:1000003",
        "tgn:7008157",
        "tgn:7008591",
        "tgn:7029392"
    ],
    "tgn:id":7028220,
    "tgn:name":"Wilsthorpe",
    "tgn:placetype":[
        "aat:300008347",
        "aat:300008372"
    ]
},
  "bbox": [],
  "geometry": {"coordinates":[-0.366667,52.7],"type":"Point"}
}
=======
{"geometry":{"type":"Point","coordinates":[-0.366667,52.700000]},"type":"Feature","properties":{"hierarchy":["tgn:7028220","tgn:7002445","tgn:1000003","tgn:7008157","tgn:7008591","tgn:7029392"],"placetype":["aat:300008347","aat:300008372"],"id":7028220,"name:xx":"Wilsthorpe"}}
>>>>>>> 03f74aca74312dbeaf24d7e61306dd6a786dc3d0
