{
  "id": 2254988,
  "type": "Feature",
  "properties": {
    "tgn:hierarchy":[
        "tgn:2254988",
        "tgn:1000001",
        "tgn:7012149",
        "tgn:2002124",
        "tgn:7007827",
        "tgn:7029392"
    ],
    "tgn:id":2254988,
    "tgn:name":"Cooper Canyon",
    "tgn:placetype":[
        "aat:300008761"
    ]
},
  "bbox": [],
  "geometry": {"coordinates":[-109.25,39.7167],"type":"Point"}
}