<<<<<<< HEAD
{
  "id": 2254988,
  "type": "Feature",
  "properties": {
    "tgn:hierarchy":[
        "tgn:2254988",
        "tgn:1000001",
        "tgn:7012149",
        "tgn:2002124",
        "tgn:7007827",
        "tgn:7029392"
    ],
    "tgn:id":2254988,
    "tgn:name":"Cooper Canyon",
    "tgn:placetype":[
        "aat:300008761"
    ]
},
  "bbox": [],
  "geometry": {"coordinates":[-109.25,39.7167],"type":"Point"}
}
=======
{"geometry":{"type":"Point","coordinates":[-109.250000,39.716700]},"type":"Feature","properties":{"hierarchy":["tgn:2254988","tgn:1000001","tgn:7012149","tgn:2002124","tgn:7007827","tgn:7029392"],"placetype":["aat:300008761"],"id":2254988,"name:xx":"Cooper Canyon"}}
>>>>>>> 03f74aca74312dbeaf24d7e61306dd6a786dc3d0
