{
  "id": 7180345,
  "type": "Feature",
  "properties": {
    "tgn:hierarchy":[
        "tgn:7180345",
        "tgn:1000003",
        "tgn:7003689",
        "tgn:7000084",
        "tgn:7029392"
    ],
    "tgn:id":7180345,
    "tgn:name":"Galgen-Berg",
    "tgn:placetype":[
        "aat:300008777"
    ]
},
  "bbox": [],
  "geometry": {"coordinates":[11.066667,51.166667],"type":"Point"}
}