{
  "id": 7000410,
  "type": "Feature",
  "properties": {
    "tgn:hierarchy":[
        "tgn:7000410",
        "tgn:1000004",
        "tgn:1000110",
        "tgn:7029392"
    ],
    "tgn:id":7000410,
    "tgn:name":"Central Province",
    "tgn:placetype":[
        "aat:300387064",
        "aat:300000774"
    ]
},
  "bbox": [],
  "geometry": {"coordinates":[80.75,7.3333],"type":"Point"}
}