{
  "id": 2201681,
  "type": "Feature",
  "properties": {
    "tgn:hierarchy":[
        "tgn:2201681",
        "tgn:1000001",
        "tgn:7012149",
        "tgn:2001514",
        "tgn:7007709",
        "tgn:7029392"
    ],
    "tgn:id":2201681,
    "tgn:name":"Buck Creek",
    "tgn:placetype":[
        "aat:300008706"
    ]
},
  "bbox": [],
  "geometry": {"coordinates":[-82.15,35.7667],"type":"Point"}
}