<<<<<<< HEAD
{
  "id": 7175706,
  "type": "Feature",
  "properties": {
    "tgn:hierarchy":[
        "tgn:7175706",
        "tgn:1000003",
        "tgn:7003678",
        "tgn:7000084",
        "tgn:7029392"
    ],
    "tgn:id":7175706,
    "tgn:name":"Gro\u00dfentaft",
    "tgn:placetype":[
        "aat:300008347"
    ]
},
  "bbox": [],
  "geometry": {"coordinates":[9.866667,50.733333],"type":"Point"}
}
=======
{"geometry":{"type":"Point","coordinates":[9.866667,50.733333]},"type":"Feature","properties":{"hierarchy":["tgn:7175706","tgn:1000003","tgn:7003678","tgn:7000084","tgn:7029392"],"placetype":["aat:300008347"],"id":7175706,"name:xx":"Gro\u00dfentaft"}}
>>>>>>> 03f74aca74312dbeaf24d7e61306dd6a786dc3d0
