{
  "id": 2273058,
  "type": "Feature",
  "properties": {
    "tgn:hierarchy":[
        "tgn:2273058",
        "tgn:1000001",
        "tgn:7012149",
        "tgn:7007157",
        "tgn:1002858",
        "tgn:7029392"
    ],
    "tgn:id":2273058,
    "tgn:name":"Cuyapaipe Indian Reservation",
    "tgn:placetype":[
        "aat:300008178",
        "aat:300387324"
    ]
},
  "bbox": [],
  "geometry": {"coordinates":[-116.3833,32.8333],"type":"Point"}
}