{
  "id": 2510955,
  "type": "Feature",
  "properties": {
    "tgn:hierarchy":[
        "tgn:2510955",
        "tgn:1000001",
        "tgn:2000862",
        "tgn:7012149",
        "tgn:7007256",
        "tgn:7029392"
    ],
    "tgn:id":2510955,
    "tgn:name":"Midway",
    "tgn:placetype":[
        "aat:300008347"
    ]
},
  "bbox": [],
  "geometry": {"coordinates":[-93.7667,32.4667],"type":"Point"}
}