{
  "id": 2162399,
  "type": "Feature",
  "properties": {
    "tgn:hierarchy":[
        "tgn:2162399",
        "tgn:1002224",
        "tgn:1000001",
        "tgn:7012149",
        "tgn:7007516",
        "tgn:7029392"
    ],
    "tgn:id":2162399,
    "tgn:name":"Ben Creek",
    "tgn:placetype":[
        "aat:300008706"
    ]
},
  "bbox": [],
  "geometry": {"coordinates":[-76.5667,38.4333],"type":"Point"}
}