{
  "id": 2565359,
  "type": "Feature",
  "properties": {
    "tgn:hierarchy":[
        "tgn:2565359",
        "tgn:1000001",
        "tgn:2000470",
        "tgn:7012149",
        "tgn:7007250",
        "tgn:7029392"
    ],
    "tgn:id":2565359,
    "tgn:name":"Paint Pot, The",
    "tgn:placetype":[
        "aat:300386845"
    ]
},
  "bbox": [],
  "geometry": {"coordinates":[-114.1833,44.2167],"type":"Point"}
}