{
  "id": 2342497,
  "type": "Feature",
  "properties": {
    "tgn:hierarchy":[
        "tgn:2342497",
        "tgn:1000001",
        "tgn:7012149",
        "tgn:2001112",
        "tgn:7007522",
        "tgn:7029392"
    ],
    "tgn:id":2342497,
    "tgn:name":"Fullilove Lake",
    "tgn:placetype":[
        "aat:300008680"
    ]
},
  "bbox": [],
  "geometry": {"coordinates":[-90.3833,33.1333],"type":"Point"}
}