{
  "id": 2468948,
  "type": "Feature",
  "properties": {
    "tgn:hierarchy":[
        "tgn:2468948",
        "tgn:1000001",
        "tgn:7012149",
        "tgn:2002297",
        "tgn:7013961",
        "tgn:7029392"
    ],
    "tgn:id":2468948,
    "tgn:name":"Long Run",
    "tgn:placetype":[
        "aat:300008699"
    ]
},
  "bbox": [],
  "geometry": {"coordinates":[-80.9167,39.5333],"type":"Point"}
}