<<<<<<< HEAD
{
  "id": 2332403,
  "type": "Feature",
  "properties": {
    "tgn:hierarchy":[
        "tgn:2332403",
        "tgn:1000001",
        "tgn:7012149",
        "tgn:2001455",
        "tgn:7007566",
        "tgn:7029392"
    ],
    "tgn:id":2332403,
    "tgn:name":"Flordillo Canyon",
    "tgn:placetype":[
        "aat:300008761"
    ]
},
  "bbox": [],
  "geometry": {"coordinates":[-107.2167,32.9167],"type":"Point"}
}
=======
{"geometry":{"type":"Point","coordinates":[-107.216700,32.916700]},"type":"Feature","properties":{"hierarchy":["tgn:2332403","tgn:1000001","tgn:7012149","tgn:2001455","tgn:7007566","tgn:7029392"],"placetype":["aat:300008761"],"id":2332403,"name:xx":"Flordillo Canyon"}}
>>>>>>> 03f74aca74312dbeaf24d7e61306dd6a786dc3d0
