<<<<<<< HEAD
{
  "id": 7487428,
  "type": "Feature",
  "properties": {
    "tgn:hierarchy":[
        "tgn:7487428",
        "tgn:7498210",
        "tgn:1000004",
        "tgn:1000141",
        "tgn:7029392"
    ],
    "tgn:id":7487428,
    "tgn:name":"Li Shan",
    "tgn:placetype":[
        "aat:300008777"
    ]
},
  "bbox": [],
  "geometry": {"coordinates":[119.966667,26.2],"type":"Point"}
}
=======
{"geometry":{"type":"Point","coordinates":[119.966667,26.200000]},"type":"Feature","properties":{"hierarchy":["tgn:7487428","tgn:7498210","tgn:1000004","tgn:1000141","tgn:7029392"],"placetype":["aat:300008777"],"id":7487428,"name:xx":"Li Shan"}}
>>>>>>> 03f74aca74312dbeaf24d7e61306dd6a786dc3d0
