{
  "id": 2526112,
  "type": "Feature",
  "properties": {
    "tgn:hierarchy":[
        "tgn:2526112",
        "tgn:1000001",
        "tgn:2000924",
        "tgn:7012149",
        "tgn:7007515",
        "tgn:7029392"
    ],
    "tgn:id":2526112,
    "tgn:name":"Mosquito Harbor",
    "tgn:placetype":[
        "aat:300132316"
    ]
},
  "bbox": [],
  "geometry": {"coordinates":[-69.2167,43.9333],"type":"Point"}
}