{
  "id": 7449357,
  "type": "Feature",
  "properties": {
    "tgn:hierarchy":[
        "tgn:7449357",
        "tgn:7002443",
        "tgn:1000003",
        "tgn:7019007",
        "tgn:7008591",
        "tgn:7029392"
    ],
    "tgn:id":7449357,
    "tgn:name:en":"Hanmer",
    "tgn:placetype":[
        "aat:300008347"
    ]
},
  "bbox": [],
  "geometry": {"coordinates":[-2.833333,52.95],"type":"Point"}
}