{
  "id": 1053993,
  "type": "Feature",
  "properties": {
    "tgn:hierarchy":[
        "tgn:1053993",
        "tgn:1000004",
        "tgn:1003405",
        "tgn:7018214",
        "tgn:7002435",
        "tgn:7029392"
    ],
    "tgn:id":1053993,
    "tgn:name":"Gigant",
    "tgn:placetype":[
        "aat:300008347"
    ]
},
  "bbox": [],
  "geometry": {"coordinates":[41.3333,46.5167],"type":"Point"}
}