{
  "id": 2293054,
  "type": "Feature",
  "properties": {
    "tgn:hierarchy":[
        "tgn:2293054",
        "tgn:1000001",
        "tgn:7012149",
        "tgn:1002423",
        "tgn:7007568",
        "tgn:7029392"
    ],
    "tgn:id":2293054,
    "tgn:name":"Dots Lake",
    "tgn:placetype":[
        "aat:300008680"
    ]
},
  "bbox": [],
  "geometry": {"coordinates":[-73.9333,42.3667],"type":"Point"}
}