{
  "id": 7268007,
  "type": "Feature",
  "properties": {
    "tgn:hierarchy":[
        "tgn:7268007",
        "tgn:7003614",
        "tgn:1000003",
        "tgn:7016845",
        "tgn:7029392"
    ],
    "tgn:id":7268007,
    "tgn:name:nl":"Oosterveld",
    "tgn:placetype":[
        "aat:300387200"
    ]
},
  "bbox": [],
  "geometry": {"coordinates":[6.866667,52.833333],"type":"Point"}
}