{
  "id": 7219180,
  "type": "Feature",
  "properties": {
    "tgn:hierarchy":[
        "tgn:7219180",
        "tgn:7002721",
        "tgn:7002715",
        "tgn:1000003",
        "tgn:1000074",
        "tgn:7029392"
    ],
    "tgn:id":7219180,
    "tgn:name":"Vo\u00farinos \u00d3ros",
    "tgn:placetype":[
        "aat:300008795"
    ]
},
  "bbox": [],
  "geometry": {"coordinates":[21.666667,40.183333],"type":"Point"}
}