{
  "id": 7335236,
  "type": "Feature",
  "properties": {
    "tgn:hierarchy":[
        "tgn:7335236",
        "tgn:7002829",
        "tgn:1000003",
        "tgn:7002786",
        "tgn:1000095",
        "tgn:7029392"
    ],
    "tgn:id":7335236,
    "tgn:name":"Figueiredo",
    "tgn:placetype":[
        "aat:300008347"
    ]
},
  "bbox": [],
  "geometry": {"coordinates":[-7.216667,42.416667],"type":"Point"}
}