{
  "id": 7330249,
  "type": "Feature",
  "properties": {
    "tgn:hierarchy":[
        "tgn:7330249",
        "tgn:7002822",
        "tgn:1001647",
        "tgn:1000003",
        "tgn:1000095",
        "tgn:7029392"
    ],
    "tgn:id":7330249,
    "tgn:name":"Horcajo, R\u00edo",
    "tgn:placetype":[
        "aat:300008699"
    ]
},
  "bbox": [],
  "geometry": {"coordinates":[-3.516667,41.133333],"type":"Point"}
}