{
  "id": 2136311,
  "type": "Feature",
  "properties": {
    "tgn:hierarchy":[
        "tgn:2136311",
        "tgn:1000001",
        "tgn:7012149",
        "tgn:7018871",
        "tgn:7007920",
        "tgn:7029392"
    ],
    "tgn:id":2136311,
    "tgn:name":"Arbor Lake",
    "tgn:placetype":[
        "aat:300008680"
    ]
},
  "bbox": [],
  "geometry": {"coordinates":[-122.3167,47.4833],"type":"Point"}
}