<<<<<<< HEAD
{
  "id": 2339126,
  "type": "Feature",
  "properties": {
    "tgn:hierarchy":[
        "tgn:2339126",
        "tgn:1000001",
        "tgn:7012149",
        "tgn:2001135",
        "tgn:7007522",
        "tgn:7029392"
    ],
    "tgn:id":2339126,
    "tgn:name":"Franks Branch",
    "tgn:placetype":[
        "aat:300008699"
    ]
},
  "bbox": [],
  "geometry": {"coordinates":[-89.2667,32.7667],"type":"Point"}
}
=======
{"geometry":{"type":"Point","coordinates":[-89.266700,32.766700]},"type":"Feature","properties":{"hierarchy":["tgn:2339126","tgn:1000001","tgn:7012149","tgn:2001135","tgn:7007522","tgn:7029392"],"placetype":["aat:300008699"],"id":2339126,"name:xx":"Franks Branch"}}
>>>>>>> 03f74aca74312dbeaf24d7e61306dd6a786dc3d0
