{
  "id": 2777894,
  "type": "Feature",
  "properties": {
    "tgn:hierarchy":[
        "tgn:2777894",
        "tgn:1000001",
        "tgn:7012149",
        "tgn:2002352",
        "tgn:7007922",
        "tgn:7029392"
    ],
    "tgn:id":2777894,
    "tgn:name":"Wintergreen Hollow",
    "tgn:placetype":[
        "aat:300008761"
    ]
},
  "bbox": [],
  "geometry": {"coordinates":[-89.9667,43.4667],"type":"Point"}
}