{
  "id": 7080775,
  "type": "Feature",
  "properties": {
    "tgn:hierarchy":[
        "tgn:7080775",
        "tgn:1000003",
        "tgn:7003677",
        "tgn:7000084",
        "tgn:7029392"
    ],
    "tgn:id":7080775,
    "tgn:name":"W\u00f6rfeld",
    "tgn:placetype":[
        "aat:300000206"
    ]
},
  "bbox": [],
  "geometry": {"coordinates":[8.95,51.983333],"type":"Point"}
}