{
  "id": 7578792,
  "type": "Feature",
  "properties": {
    "tgn:hierarchy":[
        "tgn:7578792",
        "tgn:1000004",
        "tgn:1001869",
        "tgn:7000198",
        "tgn:7029392"
    ],
    "tgn:id":7578792,
    "tgn:name:en":"Udhna Junction",
    "tgn:placetype":[
        "aat:300007783"
    ]
},
  "bbox": [],
  "geometry": {"coordinates":[72.85,21.166667],"type":"Point"}
}