{
  "id": 7480914,
  "type": "Feature",
  "properties": {
    "tgn:hierarchy":[
        "tgn:7480914",
        "tgn:1000004",
        "tgn:1000454",
        "tgn:1000141",
        "tgn:7029392"
    ],
    "tgn:id":7480914,
    "tgn:name":"Xingwu Shangzhuan",
    "tgn:placetype":[
        "aat:300006610"
    ]
},
  "bbox": [],
  "geometry": {"coordinates":[121.394508,25.080825],"type":"Point"}
}