{
  "id": 7076724,
  "type": "Feature",
  "properties": {
    "tgn:hierarchy":[
        "tgn:7076724",
        "tgn:1000003",
        "tgn:7003678",
        "tgn:7000084",
        "tgn:7029392"
    ],
    "tgn:id":7076724,
    "tgn:name":"R\u00f6dermark",
    "tgn:placetype":[
        "aat:300387173"
    ]
},
  "bbox": [],
  "geometry": {"coordinates":[8.795833,49.993611],"type":"Point"}
}