{
  "id": 2493345,
  "type": "Feature",
  "properties": {
    "tgn:hierarchy":[
        "tgn:2493345",
        "tgn:7006450",
        "tgn:1000001",
        "tgn:7012149",
        "tgn:2000082",
        "tgn:7029392"
    ],
    "tgn:id":2493345,
    "tgn:name":"Marr, Mount",
    "tgn:placetype":[
        "aat:300008798"
    ]
},
  "bbox": [],
  "geometry": {"coordinates":[-131.9667,55.55],"type":"Point"}
}