{
  "id": 7315071,
  "type": "Feature",
  "properties": {
    "tgn:hierarchy":[
        "tgn:7315071",
        "tgn:1001708",
        "tgn:1000049",
        "tgn:1000002",
        "tgn:7029392"
    ],
    "tgn:id":7315071,
    "tgn:name":"Los Escalones, Portillo de",
    "tgn:placetype":[
        "aat:300259572"
    ]
},
  "bbox": [],
  "geometry": {"coordinates":[-70.233333,-33.633333],"type":"Point"}
}