{
  "id": 2421530,
  "type": "Feature",
  "properties": {
    "tgn:hierarchy":[
        "tgn:2421530",
        "tgn:1000001",
        "tgn:7012149",
        "tgn:7007255",
        "tgn:7029392"
    ],
    "tgn:id":2421530,
    "tgn:name":"Jessie Run",
    "tgn:placetype":[
        "aat:300008699"
    ]
},
  "bbox": [],
  "geometry": {"coordinates":[-85.2333,37.8833],"type":"Point"}
}