{
  "id": 7567354,
  "type": "Feature",
  "properties": {
    "tgn:hierarchy":[
        "tgn:7567354",
        "tgn:1000004",
        "tgn:7000198",
        "tgn:7001797",
        "tgn:7029392"
    ],
    "tgn:id":7567354,
    "tgn:name:en":"Adanur",
    "tgn:placetype":[
        "aat:300008347"
    ]
},
  "bbox": [],
  "geometry": {"coordinates":[80.046667,12.873611],"type":"Point"}
}