{
  "id": 7363836,
  "type": "Feature",
  "properties": {
    "tgn:hierarchy":[
        "tgn:7363836",
        "tgn:1000001",
        "tgn:7005597",
        "tgn:7005560",
        "tgn:7029392"
    ],
    "tgn:id":7363836,
    "tgn:name":"El Barco",
    "tgn:placetype":[
        "aat:300008347"
    ]
},
  "bbox": [],
  "geometry": {"coordinates":[-97.95,22.583333],"type":"Point"}
}