{
  "id": 7142442,
  "type": "Feature",
  "properties": {
    "tgn:hierarchy":[
        "tgn:7142442",
        "tgn:1000003",
        "tgn:7003687",
        "tgn:7000084",
        "tgn:7029392"
    ],
    "tgn:id":7142442,
    "tgn:name":"Mahndorf",
    "tgn:placetype":[
        "aat:300008347"
    ]
},
  "bbox": [],
  "geometry": {"coordinates":[10.966667,51.883333],"type":"Point"}
}