{
  "id": 2200595,
  "type": "Feature",
  "properties": {
    "tgn:hierarchy":[
        "tgn:2200595",
        "tgn:1000001",
        "tgn:7012149",
        "tgn:2000230",
        "tgn:7007158",
        "tgn:7029392"
    ],
    "tgn:id":2200595,
    "tgn:name":"Brushy Ridge",
    "tgn:placetype":[
        "aat:300266640"
    ]
},
  "bbox": [],
  "geometry": {"coordinates":[-108.5167,38.6167],"type":"Point"}
}