{
  "id": 1136506,
  "type": "Feature",
  "properties": {
    "tgn:hierarchy":[
        "tgn:1136506",
        "tgn:1001945",
        "tgn:1000047",
        "tgn:7002457",
        "tgn:1000002",
        "tgn:7029392"
    ],
    "tgn:id":1136506,
    "tgn:name":"Borda da Mata",
    "tgn:placetype":[
        "aat:300008347"
    ]
},
  "bbox": [],
  "geometry": {"coordinates":[-47.0167,-22.6167],"type":"Point"}
}