{
  "id": 2571256,
  "type": "Feature",
  "properties": {
    "tgn:hierarchy":[
        "tgn:2571256",
        "tgn:1000001",
        "tgn:7012149",
        "tgn:2000823",
        "tgn:7007255",
        "tgn:7029392"
    ],
    "tgn:id":2571256,
    "tgn:name":"Patty Creek",
    "tgn:placetype":[
        "aat:300008706"
    ]
},
  "bbox": [],
  "geometry": {"coordinates":[-88.3667,36.75],"type":"Point"}
}