{
  "id": 2433949,
  "type": "Feature",
  "properties": {
    "tgn:hierarchy":[
        "tgn:2433949",
        "tgn:1000001",
        "tgn:7012149",
        "tgn:2002110",
        "tgn:7007827",
        "tgn:7029392"
    ],
    "tgn:id":2433949,
    "tgn:name":"Kelly Spring",
    "tgn:placetype":[
        "aat:300008697"
    ]
},
  "bbox": [],
  "geometry": {"coordinates":[-109.5167,39.35],"type":"Point"}
}