{
  "id": 2211619,
  "type": "Feature",
  "properties": {
    "tgn:hierarchy":[
        "tgn:2211619",
        "tgn:1002366",
        "tgn:1000001",
        "tgn:7012149",
        "tgn:7007159",
        "tgn:7029392"
    ],
    "tgn:id":2211619,
    "tgn:name":"Buttermilk Hollow",
    "tgn:placetype":[
        "aat:300008761"
    ]
},
  "bbox": [],
  "geometry": {"coordinates":[-73.0833,41.2833],"type":"Point"}
}