{
  "id": 7523316,
  "type": "Feature",
  "properties": {
    "tgn:hierarchy":[
        "tgn:7523316",
        "tgn:7001242",
        "tgn:7016833",
        "tgn:1001418",
        "tgn:7029392"
    ],
    "tgn:id":7523316,
    "tgn:name:en":"Asmar, 'Alam el-",
    "tgn:placetype":[
        "aat:300008777"
    ]
},
  "bbox": [],
  "geometry": {"coordinates":[25.159552,30.794458],"type":"Point"}
}