{
  "id": 7394109,
  "type": "Feature",
  "properties": {
    "tgn:hierarchy":[
        "tgn:7394109",
        "tgn:1000001",
        "tgn:1001960",
        "tgn:7005560",
        "tgn:7029392"
    ],
    "tgn:id":7394109,
    "tgn:name":"San Francisquito",
    "tgn:placetype":[
        "aat:300167671"
    ]
},
  "bbox": [],
  "geometry": {"coordinates":[-112.316667,31.583333],"type":"Point"}
}