{
  "id": 7009828,
  "type": "Feature",
  "properties": {
    "tgn:hierarchy":[
        "tgn:7009828",
        "tgn:1000003",
        "tgn:7024622",
        "tgn:1000097",
        "tgn:7029392"
    ],
    "tgn:id":7009828,
    "tgn:name":"Klippan",
    "tgn:placetype":[
        "aat:300008347"
    ]
},
  "bbox": [],
  "geometry": {"coordinates":[13.1667,56.1333],"type":"Point"}
}