{
  "id": 7369358,
  "type": "Feature",
  "properties": {
    "tgn:hierarchy":[
        "tgn:7369358",
        "tgn:1000001",
        "tgn:7005597",
        "tgn:7005560",
        "tgn:7029392"
    ],
    "tgn:id":7369358,
    "tgn:name":"Guadalupe del Yeso",
    "tgn:placetype":[
        "aat:300008347"
    ]
},
  "bbox": [],
  "geometry": {"coordinates":[-98.25,24.916667],"type":"Point"}
}