{
  "id": 7458246,
  "type": "Feature",
  "properties": {
    "tgn:hierarchy":[
        "tgn:7458246",
        "tgn:7002448",
        "tgn:7019159",
        "tgn:1000003",
        "tgn:7008591",
        "tgn:7029392"
    ],
    "tgn:id":7458246,
    "tgn:name:en":"Path Head",
    "tgn:placetype":[
        "aat:300008850"
    ]
},
  "bbox": [],
  "geometry": {"coordinates":[-5.916667,54.966667],"type":"Point"}
}