{
  "id": 7249083,
  "type": "Feature",
  "properties": {
    "tgn:hierarchy":[
        "tgn:7249083",
        "tgn:7018239",
        "tgn:1000003",
        "tgn:1000063",
        "tgn:7018236",
        "tgn:7029392"
    ],
    "tgn:id":7249083,
    "tgn:name":"Den Daal",
    "tgn:placetype":[
        "aat:300008347"
    ]
},
  "bbox": [],
  "geometry": {"coordinates":[4.159831,50.734946],"type":"Point"}
}