{
  "id": 1008271,
  "type": "Feature",
  "properties": {
    "tgn:hierarchy":[
        "tgn:1008271",
        "tgn:7024077",
        "tgn:1000003",
        "tgn:1000069",
        "tgn:7029392"
    ],
    "tgn:id":1008271,
    "tgn:name":"Nagu",
    "tgn:placetype":[
        "aat:300008791"
    ]
},
  "bbox": [],
  "geometry": {"coordinates":[21.9667,60.1667],"type":"Point"}
}