{
  "id": 7506494,
  "type": "Feature",
  "properties": {
    "tgn:hierarchy":[
        "tgn:7506494",
        "tgn:1009227",
        "tgn:1000226",
        "tgn:7018437",
        "tgn:1000006",
        "tgn:7029392"
    ],
    "tgn:id":7506494,
    "tgn:name:en":"Rosebery, Mount",
    "tgn:placetype":[
        "aat:300008795"
    ]
},
  "bbox": [],
  "geometry": {"coordinates":[169.35,-46.316667],"type":"Point"}
}