{
  "id": 1107156,
  "type": "Feature",
  "properties": {
    "tgn:hierarchy":[
        "tgn:1107156",
        "tgn:1000003",
        "tgn:7029392"
    ],
    "tgn:id":1107156,
    "tgn:name:de":"Buin, Piz",
    "tgn:placetype":[
        "aat:300008798"
    ]
},
  "bbox": [],
  "geometry": {"coordinates":[10.1167,46.8667],"type":"Point"}
}