<<<<<<< HEAD
{
  "id": 2336277,
  "type": "Feature",
  "properties": {
    "tgn:hierarchy":[
        "tgn:2336277",
        "tgn:1002148",
        "tgn:1000001",
        "tgn:7012149",
        "tgn:7007826",
        "tgn:7029392"
    ],
    "tgn:id":2336277,
    "tgn:name":"Fosterville",
    "tgn:placetype":[
        "aat:300008347"
    ]
},
  "bbox": [],
  "geometry": {"coordinates":[-95.6,32.0],"type":"Point"}
}
=======
{"geometry":{"type":"Point","coordinates":[-95.600000,32.000000]},"type":"Feature","properties":{"hierarchy":["tgn:2336277","tgn:1002148","tgn:1000001","tgn:7012149","tgn:7007826","tgn:7029392"],"placetype":["aat:300008347"],"id":2336277,"name:xx":"Fosterville"}}
>>>>>>> 03f74aca74312dbeaf24d7e61306dd6a786dc3d0
