{
  "id": 2347331,
  "type": "Feature",
  "properties": {
    "tgn:hierarchy":[
        "tgn:2347331",
        "tgn:1000001",
        "tgn:7012149",
        "tgn:7007706",
        "tgn:7029392"
    ],
    "tgn:id":2347331,
    "tgn:name":"George Creek",
    "tgn:placetype":[
        "aat:300008706"
    ]
},
  "bbox": [],
  "geometry": {"coordinates":[-82.75,39.9167],"type":"Point"}
}