{
  "id": 7321856,
  "type": "Feature",
  "properties": {
    "tgn:hierarchy":[
        "tgn:7321856",
        "tgn:1001699",
        "tgn:1000049",
        "tgn:1000002",
        "tgn:7029392"
    ],
    "tgn:id":7321856,
    "tgn:name":"Aul\u00edn, Bajo",
    "tgn:placetype":[
        "aat:300387036"
    ]
},
  "bbox": [],
  "geometry": {"coordinates":[-73.191111,-42.2425],"type":"Point"}
}