{
  "id": 2193662,
  "type": "Feature",
  "properties": {
    "tgn:hierarchy":[
        "tgn:2193662",
        "tgn:7014651",
        "tgn:1000001",
        "tgn:7012149",
        "tgn:7007516",
        "tgn:7029392"
    ],
    "tgn:id":2193662,
    "tgn:name":"Brewer Point",
    "tgn:placetype":[
        "aat:300008850"
    ]
},
  "bbox": [],
  "geometry": {"coordinates":[-76.5167,38.9167],"type":"Point"}
}