{
  "id": 7014193,
  "type": "Feature",
  "properties": {
    "tgn:hierarchy":[
        "tgn:7014193",
        "tgn:1000001",
        "tgn:7012149",
        "tgn:1002446",
        "tgn:7007251",
        "tgn:7029392"
    ],
    "tgn:id":7014193,
    "tgn:name":"Nauvoo",
    "tgn:placetype":[
        "aat:300008347"
    ]
},
  "bbox": [],
  "geometry": {"coordinates":[-91.3833,40.55],"type":"Point"}
}