{
  "id": 2440282,
  "type": "Feature",
  "properties": {
    "tgn:hierarchy":[
        "tgn:2440282",
        "tgn:1000001",
        "tgn:7012149",
        "tgn:2001036",
        "tgn:7007521",
        "tgn:7029392"
    ],
    "tgn:id":2440282,
    "tgn:name":"Klobuchar Bay",
    "tgn:placetype":[
        "aat:300132316"
    ]
},
  "bbox": [],
  "geometry": {"coordinates":[-91.7833,47.7333],"type":"Point"}
}