{
  "id": 7366743,
  "type": "Feature",
  "properties": {
    "tgn:hierarchy":[
        "tgn:7366743",
        "tgn:1000001",
        "tgn:7005599",
        "tgn:7005560",
        "tgn:7029392"
    ],
    "tgn:id":7366743,
    "tgn:name":"Espinal",
    "tgn:placetype":[
        "aat:300008347"
    ]
},
  "bbox": [],
  "geometry": {"coordinates":[-96.85,19.616667],"type":"Point"}
}