{
  "id": 7109748,
  "type": "Feature",
  "properties": {
    "tgn:hierarchy":[
        "tgn:7109748",
        "tgn:1000003",
        "tgn:7003677",
        "tgn:7000084",
        "tgn:7029392"
    ],
    "tgn:id":7109748,
    "tgn:name":"Qualburg",
    "tgn:placetype":[
        "aat:300008347"
    ]
},
  "bbox": [],
  "geometry": {"coordinates":[6.166667,51.783333],"type":"Point"}
}