{
  "id": 1011338,
  "type": "Feature",
  "properties": {
    "tgn:hierarchy":[
        "tgn:1011338",
        "tgn:7000895",
        "tgn:1000004",
        "tgn:1000974",
        "tgn:1000120",
        "tgn:7029392"
    ],
    "tgn:id":1011338,
    "tgn:name":"Tsunegami-saki",
    "tgn:placetype":[
        "aat:300008850"
    ]
},
  "bbox": [],
  "geometry": {"coordinates":[135.8167,35.6333],"type":"Point"}
}