{
  "id": 7374593,
  "type": "Feature",
  "properties": {
    "tgn:hierarchy":[
        "tgn:7374593",
        "tgn:1000001",
        "tgn:7005597",
        "tgn:7005560",
        "tgn:7029392"
    ],
    "tgn:id":7374593,
    "tgn:name":"La Bolsa",
    "tgn:placetype":[
        "aat:300008347"
    ]
},
  "bbox": [],
  "geometry": {"coordinates":[-97.866667,26.066667],"type":"Point"}
}