{
  "id": 2182678,
  "type": "Feature",
  "properties": {
    "tgn:hierarchy":[
        "tgn:2182678",
        "tgn:1000001",
        "tgn:7012149",
        "tgn:2000353",
        "tgn:7007248",
        "tgn:7029392"
    ],
    "tgn:id":2182678,
    "tgn:name":"Blue Spring Branch",
    "tgn:placetype":[
        "aat:300008699"
    ]
},
  "bbox": [],
  "geometry": {"coordinates":[-82.4833,33.25],"type":"Point"}
}