<<<<<<< HEAD
{
  "id": 7111856,
  "type": "Feature",
  "properties": {
    "tgn:hierarchy":[
        "tgn:7111856",
        "tgn:1000003",
        "tgn:7003677",
        "tgn:7000084",
        "tgn:7029392"
    ],
    "tgn:id":7111856,
    "tgn:name":"Rinne-Kopf",
    "tgn:placetype":[
        "aat:300008795"
    ]
},
  "bbox": [],
  "geometry": {"coordinates":[8.333333,51.066667],"type":"Point"}
}
=======
{"geometry":{"type":"Point","coordinates":[8.333333,51.066667]},"type":"Feature","properties":{"hierarchy":["tgn:7111856","tgn:1000003","tgn:7003677","tgn:7000084","tgn:7029392"],"placetype":["aat:300008795"],"id":7111856,"name:xx":"Rinne-Kopf"}}
>>>>>>> 03f74aca74312dbeaf24d7e61306dd6a786dc3d0
