{
  "id": 2584235,
  "type": "Feature",
  "properties": {
    "tgn:hierarchy":[
        "tgn:2584235",
        "tgn:1000001",
        "tgn:7012149",
        "tgn:2001554",
        "tgn:7007709",
        "tgn:7029392"
    ],
    "tgn:id":2584235,
    "tgn:name":"Pineview Acres",
    "tgn:placetype":[
        "aat:300008347"
    ]
},
  "bbox": [],
  "geometry": {"coordinates":[-77.95,35.7667],"type":"Point"}
}