<<<<<<< HEAD
{
  "id": 7113707,
  "type": "Feature",
  "properties": {
    "tgn:hierarchy":[
        "tgn:7113707",
        "tgn:1000003",
        "tgn:7003676",
        "tgn:7000084",
        "tgn:7029392"
    ],
    "tgn:id":7113707,
    "tgn:name":"Riehe",
    "tgn:placetype":[
        "aat:300008347"
    ]
},
  "bbox": [],
  "geometry": {"coordinates":[9.4,52.35],"type":"Point"}
}
=======
{"geometry":{"type":"Point","coordinates":[9.400000,52.350000]},"type":"Feature","properties":{"hierarchy":["tgn:7113707","tgn:1000003","tgn:7003676","tgn:7000084","tgn:7029392"],"placetype":["aat:300008347"],"id":7113707,"name:xx":"Riehe"}}
>>>>>>> 03f74aca74312dbeaf24d7e61306dd6a786dc3d0
