{
  "id": 7526809,
  "type": "Feature",
  "properties": {
    "tgn:hierarchy":[
        "tgn:7526809",
        "tgn:7001242",
        "tgn:7016833",
        "tgn:7001334",
        "tgn:7029392"
    ],
    "tgn:id":7526809,
    "tgn:name:en":"Well No. 54",
    "tgn:placetype":[
        "aat:300006207"
    ]
},
  "bbox": [],
  "geometry": {"coordinates":[30.621552,25.53704],"type":"Point"}
}