{
  "id": 7151746,
  "type": "Feature",
  "properties": {
    "tgn:hierarchy":[
        "tgn:7151746",
        "tgn:7003669",
        "tgn:1000003",
        "tgn:7000084",
        "tgn:7029392"
    ],
    "tgn:id":7151746,
    "tgn:name":"Jechling",
    "tgn:placetype":[
        "aat:300008347"
    ]
},
  "bbox": [],
  "geometry": {"coordinates":[12.883333,47.783333],"type":"Point"}
}