{
  "id": 7510693,
  "type": "Feature",
  "properties": {
    "tgn:hierarchy":[
        "tgn:7510693",
        "tgn:1009227",
        "tgn:1000226",
        "tgn:7520095",
        "tgn:1000006",
        "tgn:7029392"
    ],
    "tgn:id":7510693,
    "tgn:name:en":"Taylor Stream",
    "tgn:placetype":[
        "aat:300008699"
    ]
},
  "bbox": [],
  "geometry": {"coordinates":[172.516667,-41.35],"type":"Point"}
}