{
  "id": 7483122,
  "type": "Feature",
  "properties": {
    "tgn:hierarchy":[
        "tgn:7483122",
        "tgn:1000004",
        "tgn:7489179",
        "tgn:1000141",
        "tgn:7029392"
    ],
    "tgn:id":7483122,
    "tgn:name":"Guliao Qiao",
    "tgn:placetype":[
        "aat:300007836"
    ]
},
  "bbox": [],
  "geometry": {"coordinates":[121.885,24.929444],"type":"Point"}
}