<<<<<<< HEAD
{
  "id": 7483122,
  "type": "Feature",
  "properties": {
    "tgn:hierarchy":[
        "tgn:7483122",
        "tgn:1000004",
        "tgn:7489179",
        "tgn:1000141",
        "tgn:7029392"
    ],
    "tgn:id":7483122,
    "tgn:name":"Guliao Qiao",
    "tgn:placetype":[
        "aat:300007836"
    ]
},
  "bbox": [],
  "geometry": {"coordinates":[121.885,24.929444],"type":"Point"}
}
=======
{"geometry":{"type":"Point","coordinates":[121.885000,24.929444]},"type":"Feature","properties":{"hierarchy":["tgn:7483122","tgn:1000004","tgn:7489179","tgn:1000141","tgn:7029392"],"placetype":["aat:300007836"],"id":7483122,"name:xx":"Guliao Qiao"}}
>>>>>>> 03f74aca74312dbeaf24d7e61306dd6a786dc3d0
