{
  "id": 7460886,
  "type": "Feature",
  "properties": {
    "tgn:hierarchy":[
        "tgn:7460886",
        "tgn:7002445",
        "tgn:7019069",
        "tgn:1000003",
        "tgn:7012033",
        "tgn:7008591",
        "tgn:7029392"
    ],
    "tgn:id":7460886,
    "tgn:name:en":"Pincushion Rock",
    "tgn:placetype":[
        "aat:300011692"
    ]
},
  "bbox": [],
  "geometry": {"coordinates":[-1.341667,54.860278],"type":"Point"}
}