<<<<<<< HEAD
{
  "id": 7351615,
  "type": "Feature",
  "properties": {
    "tgn:hierarchy":[
        "tgn:7351615",
        "tgn:7005581",
        "tgn:1000001",
        "tgn:7005560",
        "tgn:7029392"
    ],
    "tgn:id":7351615,
    "tgn:name":"Boquilla, Cerro",
    "tgn:placetype":[
        "aat:300008795"
    ]
},
  "bbox": [],
  "geometry": {"coordinates":[-106.233333,28.716667],"type":"Point"}
}
=======
{"geometry":{"type":"Point","coordinates":[-106.233333,28.716667]},"type":"Feature","properties":{"hierarchy":["tgn:7351615","tgn:7005581","tgn:1000001","tgn:7005560","tgn:7029392"],"placetype":["aat:300008795"],"id":7351615,"name:xx":"Boquilla, Cerro"}}
>>>>>>> 03f74aca74312dbeaf24d7e61306dd6a786dc3d0
