<<<<<<< HEAD
{
  "id": 7119852,
  "type": "Feature",
  "properties": {
    "tgn:hierarchy":[
        "tgn:7119852",
        "tgn:7003669",
        "tgn:1000003",
        "tgn:7000084",
        "tgn:7029392"
    ],
    "tgn:id":7119852,
    "tgn:name":"Pelka",
    "tgn:placetype":[
        "aat:300008347"
    ]
},
  "bbox": [],
  "geometry": {"coordinates":[11.533333,48.4],"type":"Point"}
}
=======
{"geometry":{"type":"Point","coordinates":[11.533333,48.400000]},"type":"Feature","properties":{"hierarchy":["tgn:7119852","tgn:7003669","tgn:1000003","tgn:7000084","tgn:7029392"],"placetype":["aat:300008347"],"id":7119852,"name:xx":"Pelka"}}
>>>>>>> 03f74aca74312dbeaf24d7e61306dd6a786dc3d0
