{
  "id": 2558060,
  "type": "Feature",
  "properties": {
    "tgn:hierarchy":[
        "tgn:2558060",
        "tgn:1000001",
        "tgn:1002218",
        "tgn:7012149",
        "tgn:7007157",
        "tgn:7029392"
    ],
    "tgn:id":2558060,
    "tgn:name":"Old Utah Mine",
    "tgn:placetype":[
        "aat:300000390"
    ]
},
  "bbox": [],
  "geometry": {"coordinates":[-121.5333,39.8333],"type":"Point"}
}