{
  "id": 1064367,
  "type": "Feature",
  "properties": {
    "tgn:hierarchy":[
        "tgn:1064367",
        "tgn:7003748",
        "tgn:1000003",
        "tgn:7011731",
        "tgn:7029392"
    ],
    "tgn:id":1064367,
    "tgn:name":"Samnaun",
    "tgn:placetype":[
        "aat:300008347"
    ]
},
  "bbox": [],
  "geometry": {"coordinates":[10.3667,46.95],"type":"Point"}
}