{
  "id": 1092156,
  "type": "Feature",
  "properties": {
    "tgn:hierarchy":[
        "tgn:1092156",
        "tgn:7001242",
        "tgn:1001841",
        "tgn:1000182",
        "tgn:7029392"
    ],
    "tgn:id":1092156,
    "tgn:name":"Makurdi",
    "tgn:placetype":[
        "aat:300008347",
        "aat:300387221",
        "aat:300008375",
        "aat:300387270",
        "aat:300387285",
        "aat:300120599",
        "aat:300387286",
        "aat:300387296"
    ]
},
  "bbox": [],
  "geometry": {"coordinates":[8.5833,7.75],"type":"Point"}
}