{
  "id": 7051023,
  "type": "Feature",
  "properties": {
    "tgn:hierarchy":[
        "tgn:7051023",
        "tgn:7005852",
        "tgn:1000003",
        "tgn:7003237",
        "tgn:1000080",
        "tgn:7029392"
    ],
    "tgn:id":7051023,
    "tgn:name":"Piano Porlezza",
    "tgn:placetype":[
        "aat:300008347"
    ]
},
  "bbox": [],
  "geometry": {"coordinates":[9.166667,46.033333],"type":"Point"}
}