{
  "id": 2491711,
  "type": "Feature",
  "properties": {
    "tgn:hierarchy":[
        "tgn:2491711",
        "tgn:1000001",
        "tgn:7012149",
        "tgn:2002264",
        "tgn:7013961",
        "tgn:7029392"
    ],
    "tgn:id":2491711,
    "tgn:name":"Mapledale",
    "tgn:placetype":[
        "aat:300008347"
    ]
},
  "bbox": [],
  "geometry": {"coordinates":[-80.25,37.8333],"type":"Point"}
}