{
  "id": 7367784,
  "type": "Feature",
  "properties": {
    "tgn:hierarchy":[
        "tgn:7367784",
        "tgn:7005587",
        "tgn:1000001",
        "tgn:7005560",
        "tgn:7029392"
    ],
    "tgn:id":7367784,
    "tgn:name":"Fabrida Vieja",
    "tgn:placetype":[
        "aat:300008347"
    ]
},
  "bbox": [],
  "geometry": {"coordinates":[-98.016667,20.583333],"type":"Point"}
}