<<<<<<< HEAD
{
  "id": 7058606,
  "type": "Feature",
  "properties": {
    "tgn:hierarchy":[
        "tgn:7058606",
        "tgn:7003131",
        "tgn:1000003",
        "tgn:7008516",
        "tgn:1000080",
        "tgn:7029392"
    ],
    "tgn:id":7058606,
    "tgn:name":"Borghese",
    "tgn:placetype":[
        "aat:300008347"
    ]
},
  "bbox": [],
  "geometry": {"coordinates":[10.066667,44.933333],"type":"Point"}
}
=======
{"geometry":{"type":"Point","coordinates":[10.066667,44.933333]},"type":"Feature","properties":{"hierarchy":["tgn:7058606","tgn:7003131","tgn:1000003","tgn:7008516","tgn:1000080","tgn:7029392"],"placetype":["aat:300008347"],"id":7058606,"name:xx":"Borghese"}}
>>>>>>> 03f74aca74312dbeaf24d7e61306dd6a786dc3d0
