{
  "id": 2200270,
  "type": "Feature",
  "properties": {
    "tgn:hierarchy":[
        "tgn:2200270",
        "tgn:1000001",
        "tgn:7012149",
        "tgn:2001551",
        "tgn:7007709",
        "tgn:7029392"
    ],
    "tgn:id":2200270,
    "tgn:name":"Brushy Fork",
    "tgn:placetype":[
        "aat:300008699"
    ]
},
  "bbox": [],
  "geometry": {"coordinates":[-81.7167,36.2167],"type":"Point"}
}