{
  "id": 2315954,
  "type": "Feature",
  "properties": {
    "tgn:hierarchy":[
        "tgn:2315954",
        "tgn:1000001",
        "tgn:7012149",
        "tgn:2001683",
        "tgn:7007707",
        "tgn:7029392"
    ],
    "tgn:id":2315954,
    "tgn:name":"Elm Creek",
    "tgn:placetype":[
        "aat:300008706"
    ]
},
  "bbox": [],
  "geometry": {"coordinates":[-95.6167,34.7167],"type":"Point"}
}