{
  "id": 2135210,
  "type": "Feature",
  "properties": {
    "tgn:hierarchy":[
        "tgn:2135210",
        "tgn:1000001",
        "tgn:7012149",
        "tgn:7018871",
        "tgn:7007920",
        "tgn:7029392"
    ],
    "tgn:id":2135210,
    "tgn:name":"Anthracite Creek",
    "tgn:placetype":[
        "aat:300008706"
    ]
},
  "bbox": [],
  "geometry": {"coordinates":[-121.3167,47.6667],"type":"Point"}
}