{
  "id": 1002742,
  "type": "Feature",
  "properties": {
    "tgn:hierarchy":[
        "tgn:1002742",
        "tgn:1000001",
        "tgn:7012149",
        "tgn:7007920",
        "tgn:7029392"
    ],
    "tgn:id":1002742,
    "tgn:name":"Okanogan",
    "tgn:placetype":[
        "aat:300387145",
        "aat:300000771"
    ]
},
  "bbox": [],
  "geometry": {"coordinates":[-119.7333,48.55],"type":"Point"}
}