{
  "id": 2077075,
  "type": "Feature",
  "properties": {
    "tgn:hierarchy":[
        "tgn:2077075",
        "tgn:1000001",
        "tgn:7012149",
        "tgn:2001516",
        "tgn:7007709",
        "tgn:7029392"
    ],
    "tgn:id":2077075,
    "tgn:name":"Walnut",
    "tgn:placetype":[
        "aat:300008347"
    ]
},
  "bbox": [],
  "geometry": {"coordinates":[-82.7333,35.8333],"type":"Point"}
}