<<<<<<< HEAD
{
  "id": 2254945,
  "type": "Feature",
  "properties": {
    "tgn:hierarchy":[
        "tgn:2254945",
        "tgn:1000001",
        "tgn:7012149",
        "tgn:2001382",
        "tgn:7007525",
        "tgn:7029392"
    ],
    "tgn:id":2254945,
    "tgn:name":"Cooper Branch",
    "tgn:placetype":[
        "aat:300008699"
    ]
},
  "bbox": [],
  "geometry": {"coordinates":[-96.1833,40.1833],"type":"Point"}
}
=======
{"geometry":{"type":"Point","coordinates":[-96.183300,40.183300]},"type":"Feature","properties":{"hierarchy":["tgn:2254945","tgn:1000001","tgn:7012149","tgn:2001382","tgn:7007525","tgn:7029392"],"placetype":["aat:300008699"],"id":2254945,"name:xx":"Cooper Branch"}}
>>>>>>> 03f74aca74312dbeaf24d7e61306dd6a786dc3d0
