{
  "id": 2254945,
  "type": "Feature",
  "properties": {
    "tgn:hierarchy":[
        "tgn:2254945",
        "tgn:1000001",
        "tgn:7012149",
        "tgn:2001382",
        "tgn:7007525",
        "tgn:7029392"
    ],
    "tgn:id":2254945,
    "tgn:name":"Cooper Branch",
    "tgn:placetype":[
        "aat:300008699"
    ]
},
  "bbox": [],
  "geometry": {"coordinates":[-96.1833,40.1833],"type":"Point"}
}