{
  "id": 2550090,
  "type": "Feature",
  "properties": {
    "tgn:hierarchy":[
        "tgn:2550090",
        "tgn:1000001",
        "tgn:2000870",
        "tgn:7012149",
        "tgn:7007256",
        "tgn:7029392"
    ],
    "tgn:id":2550090,
    "tgn:name":"Northdale",
    "tgn:placetype":[
        "aat:300008347"
    ]
},
  "bbox": [],
  "geometry": {"coordinates":[-91.1667,30.45],"type":"Point"}
}