{
  "id": 2423304,
  "type": "Feature",
  "properties": {
    "tgn:hierarchy":[
        "tgn:2423304",
        "tgn:7002659",
        "tgn:1000001",
        "tgn:7012149",
        "tgn:2000060",
        "tgn:7029392"
    ],
    "tgn:id":2423304,
    "tgn:name":"Jogloma Lake",
    "tgn:placetype":[
        "aat:300006191"
    ]
},
  "bbox": [],
  "geometry": {"coordinates":[-86.05,33.3333],"type":"Point"}
}