{
  "id": 2436679,
  "type": "Feature",
  "properties": {
    "tgn:hierarchy":[
        "tgn:2436679",
        "tgn:1000001",
        "tgn:7012149",
        "tgn:2002186",
        "tgn:7007919",
        "tgn:7029392"
    ],
    "tgn:id":2436679,
    "tgn:name":"Kiger Hill",
    "tgn:placetype":[
        "aat:300008798"
    ]
},
  "bbox": [],
  "geometry": {"coordinates":[-79.5333,37.7333],"type":"Point"}
}