<<<<<<< HEAD
{
  "id": 2405866,
  "type": "Feature",
  "properties": {
    "tgn:hierarchy":[
        "tgn:2405866",
        "tgn:7014010",
        "tgn:1000001",
        "tgn:1002344",
        "tgn:7012149",
        "tgn:7007517",
        "tgn:7029392"
    ],
    "tgn:id":2405866,
    "tgn:name":"Hullman Point",
    "tgn:placetype":[
        "aat:300008850"
    ]
},
  "bbox": [],
  "geometry": {"coordinates":[-70.6167,41.45],"type":"Point"}
}
=======
{"geometry":{"type":"Point","coordinates":[-70.616700,41.450000]},"type":"Feature","properties":{"hierarchy":["tgn:2405866","tgn:7014010","tgn:1000001","tgn:1002344","tgn:7012149","tgn:7007517","tgn:7029392"],"placetype":["aat:300008850"],"id":2405866,"name:xx":"Hullman Point"}}
>>>>>>> 03f74aca74312dbeaf24d7e61306dd6a786dc3d0
