{
  "id": 1124859,
  "type": "Feature",
  "properties": {
    "tgn:hierarchy":[
        "tgn:1124859",
        "tgn:1000001",
        "tgn:7012149",
        "tgn:7007251",
        "tgn:7029392"
    ],
    "tgn:id":1124859,
    "tgn:name":"Illinois",
    "tgn:placetype":[
        "aat:300008707"
    ]
},
  "bbox": [],
  "geometry": {"coordinates":[-88.25,41.3833],"type":"Point"}
}