{
  "id": 2348407,
  "type": "Feature",
  "properties": {
    "tgn:hierarchy":[
        "tgn:2348407",
        "tgn:7002659",
        "tgn:1000001",
        "tgn:7012149",
        "tgn:2000039",
        "tgn:7029392"
    ],
    "tgn:id":2348407,
    "tgn:name":"Giant Cricket Cave",
    "tgn:placetype":[
        "aat:300008746"
    ]
},
  "bbox": [],
  "geometry": {"coordinates":[-87.3333,34.3667],"type":"Point"}
}