{
  "id": 7224798,
  "type": "Feature",
  "properties": {
    "tgn:hierarchy":[
        "tgn:7224798",
        "tgn:7002681",
        "tgn:7001395",
        "tgn:1000003",
        "tgn:1000074",
        "tgn:7029392"
    ],
    "tgn:id":7224798,
    "tgn:name":"Pig\u00e1dhia",
    "tgn:placetype":[
        "aat:300008347"
    ]
},
  "bbox": [],
  "geometry": {"coordinates":[23.383333,37.416667],"type":"Point"}
}