{
  "id": 7201358,
  "type": "Feature",
  "properties": {
    "tgn:hierarchy":[
        "tgn:7201358",
        "tgn:1000003",
        "tgn:7003677",
        "tgn:7000084",
        "tgn:7029392"
    ],
    "tgn:id":7201358,
    "tgn:name":"Bruchhausen",
    "tgn:placetype":[
        "aat:300008347"
    ]
},
  "bbox": [],
  "geometry": {"coordinates":[8.533333,51.316667],"type":"Point"}
}