{
  "id": 7230623,
  "type": "Feature",
  "properties": {
    "tgn:hierarchy":[
        "tgn:7230623",
        "tgn:7002745",
        "tgn:7017076",
        "tgn:1000003",
        "tgn:1000074",
        "tgn:7029392"
    ],
    "tgn:id":7230623,
    "tgn:name":"Kaloy\u00edrou, K\u00e1vos",
    "tgn:placetype":[
        "aat:300008850"
    ]
},
  "bbox": [],
  "geometry": {"coordinates":[22.966667,36.516667],"type":"Point"}
}