{
  "id": 7527198,
  "type": "Feature",
  "properties": {
    "tgn:hierarchy":[
        "tgn:7527198",
        "tgn:7001242",
        "tgn:7016833",
        "tgn:1001091",
        "tgn:7029392"
    ],
    "tgn:id":7527198,
    "tgn:name:en":"\u0162ur\u00e1 al \u1e28ajj\u0101rah",
    "tgn:placetype":[
        "aat:300008347"
    ]
},
  "bbox": [],
  "geometry": {"coordinates":[31.266667,29.933333],"type":"Point"}
}