{
  "id": 2326237,
  "type": "Feature",
  "properties": {
    "tgn:hierarchy":[
        "tgn:2326237",
        "tgn:1000001",
        "tgn:7012149",
        "tgn:2002114",
        "tgn:7007827",
        "tgn:7029392"
    ],
    "tgn:id":2326237,
    "tgn:name":"Fillmore Wash",
    "tgn:placetype":[
        "aat:300008761"
    ]
},
  "bbox": [],
  "geometry": {"coordinates":[-112.9833,38.95],"type":"Point"}
}