{
  "id": 7043591,
  "type": "Feature",
  "properties": {
    "tgn:hierarchy":[
        "tgn:7043591",
        "tgn:7003138",
        "tgn:1000003",
        "tgn:7003080",
        "tgn:1000080",
        "tgn:7029392"
    ],
    "tgn:id":7043591,
    "tgn:name":"Cavozza, Fosso",
    "tgn:placetype":[
        "aat:300008699"
    ]
},
  "bbox": [],
  "geometry": {"coordinates":[13.016667,41.733333],"type":"Point"}
}