{
  "id": 7336764,
  "type": "Feature",
  "properties": {
    "tgn:hierarchy":[
        "tgn:7336764",
        "tgn:7001158",
        "tgn:7002850",
        "tgn:1000003",
        "tgn:1000095",
        "tgn:7029392"
    ],
    "tgn:id":7336764,
    "tgn:name":"Fontano, R\u00edo del",
    "tgn:placetype":[
        "aat:300008699"
    ]
},
  "bbox": [],
  "geometry": {"coordinates":[-6.616667,41.933333],"type":"Point"}
}