{
  "id": 7189064,
  "type": "Feature",
  "properties": {
    "tgn:hierarchy":[
        "tgn:7189064",
        "tgn:1000003",
        "tgn:7003677",
        "tgn:7000084",
        "tgn:7029392"
    ],
    "tgn:id":7189064,
    "tgn:name":"Eisen-Berg",
    "tgn:placetype":[
        "aat:300008777"
    ]
},
  "bbox": [],
  "geometry": {"coordinates":[8.516667,51.366667],"type":"Point"}
}