{
  "id": 7117048,
  "type": "Feature",
  "properties": {
    "tgn:hierarchy":[
        "tgn:7117048",
        "tgn:7003669",
        "tgn:1000003",
        "tgn:7000084",
        "tgn:7029392"
    ],
    "tgn:id":7117048,
    "tgn:name":"Ottenberg",
    "tgn:placetype":[
        "aat:300008777"
    ]
},
  "bbox": [],
  "geometry": {"coordinates":[11.483333,49.316667],"type":"Point"}
}