{
  "id": 2597009,
  "type": "Feature",
  "properties": {
    "tgn:hierarchy":[
        "tgn:2597009",
        "tgn:1000001",
        "tgn:7006451",
        "tgn:7012149",
        "tgn:2000103",
        "tgn:7029392"
    ],
    "tgn:id":2597009,
    "tgn:name":"Powerline Tank",
    "tgn:placetype":[
        "aat:300006191"
    ]
},
  "bbox": [],
  "geometry": {"coordinates":[-112.2333,34.3167],"type":"Point"}
}