{
  "id": 1015902,
  "type": "Feature",
  "properties": {
    "tgn:hierarchy":[
        "tgn:1015902",
        "tgn:7005685",
        "tgn:1000001",
        "tgn:7005805",
        "tgn:7029392"
    ],
    "tgn:id":1015902,
    "tgn:name":"Dysart",
    "tgn:placetype":[
        "aat:300008347"
    ]
},
  "bbox": [],
  "geometry": {"coordinates":[-104.0333,50.9333],"type":"Point"}
}