{
  "id": 2204261,
  "type": "Feature",
  "properties": {
    "tgn:hierarchy":[
        "tgn:2204261",
        "tgn:1000001",
        "tgn:7012149",
        "tgn:2001715",
        "tgn:7007708",
        "tgn:7029392"
    ],
    "tgn:id":2204261,
    "tgn:name":"Buffalo",
    "tgn:placetype":[
        "aat:300008347"
    ]
},
  "bbox": [],
  "geometry": {"coordinates":[-120.3333,43.2333],"type":"Point"}
}