<<<<<<< HEAD
{
  "id": 2259975,
  "type": "Feature",
  "properties": {
    "tgn:hierarchy":[
        "tgn:2259975",
        "tgn:1000001",
        "tgn:7012149",
        "tgn:2001207",
        "tgn:7007523",
        "tgn:7029392"
    ],
    "tgn:id":2259975,
    "tgn:name":"Council Bluff Lake",
    "tgn:placetype":[
        "aat:300008680"
    ]
},
  "bbox": [],
  "geometry": {"coordinates":[-90.9,37.7167],"type":"Point"}
}
=======
{"geometry":{"type":"Point","coordinates":[-90.900000,37.716700]},"type":"Feature","properties":{"hierarchy":["tgn:2259975","tgn:1000001","tgn:7012149","tgn:2001207","tgn:7007523","tgn:7029392"],"placetype":["aat:300008680"],"id":2259975,"name:xx":"Council Bluff Lake"}}
>>>>>>> 03f74aca74312dbeaf24d7e61306dd6a786dc3d0
