{
  "id": 1033724,
  "type": "Feature",
  "properties": {
    "tgn:hierarchy":[
        "tgn:1033724",
        "tgn:1000003",
        "tgn:1000070",
        "tgn:7002897",
        "tgn:7029392"
    ],
    "tgn:id":1033724,
    "tgn:name":"Verpilli\u00e8re",
    "tgn:placetype":[
        "aat:300008347"
    ]
},
  "bbox": [],
  "geometry": {"coordinates":[5.15,45.6333],"type":"Point"}
}