{
  "id": 7065689,
  "type": "Feature",
  "properties": {
    "tgn:hierarchy":[
        "tgn:7065689",
        "tgn:7003669",
        "tgn:1000003",
        "tgn:7000084",
        "tgn:7029392"
    ],
    "tgn:id":7065689,
    "tgn:name":"Stellen Bach",
    "tgn:placetype":[
        "aat:300008699"
    ]
},
  "bbox": [],
  "geometry": {"coordinates":[10.45,47.683333],"type":"Point"}
}