{
  "id": 2211212,
  "type": "Feature",
  "properties": {
    "tgn:hierarchy":[
        "tgn:2211212",
        "tgn:1000001",
        "tgn:7006451",
        "tgn:2000093",
        "tgn:7012149",
        "tgn:7029392"
    ],
    "tgn:id":2211212,
    "tgn:name":"Butta Tank",
    "tgn:placetype":[
        "aat:300006191"
    ]
},
  "bbox": [],
  "geometry": {"coordinates":[-110.6833,33.4167],"type":"Point"}
}