{
  "id": 7470139,
  "type": "Feature",
  "properties": {
    "tgn:hierarchy":[
        "tgn:7470139",
        "tgn:1000004",
        "tgn:7004300",
        "tgn:1000141",
        "tgn:7029392"
    ],
    "tgn:id":7470139,
    "tgn:name":"Xiji Cun",
    "tgn:placetype":[
        "aat:300387173"
    ]
},
  "bbox": [],
  "geometry": {"coordinates":[119.620556,23.251111],"type":"Point"}
}