<<<<<<< HEAD
{
  "id": 2402766,
  "type": "Feature",
  "properties": {
    "tgn:hierarchy":[
        "tgn:2402766",
        "tgn:1000001",
        "tgn:7012149",
        "tgn:7007157",
        "tgn:1002675",
        "tgn:7029392"
    ],
    "tgn:id":2402766,
    "tgn:name":"Hot Springs Canyon",
    "tgn:placetype":[
        "aat:300008761"
    ]
},
  "bbox": [],
  "geometry": {"coordinates":[-119.1833,38.2],"type":"Point"}
}
=======
{"geometry":{"type":"Point","coordinates":[-119.183300,38.200000]},"type":"Feature","properties":{"hierarchy":["tgn:2402766","tgn:1000001","tgn:7012149","tgn:7007157","tgn:1002675","tgn:7029392"],"placetype":["aat:300008761"],"id":2402766,"name:xx":"Hot Springs Canyon"}}
>>>>>>> 03f74aca74312dbeaf24d7e61306dd6a786dc3d0
