{
  "id": 7549647,
  "type": "Feature",
  "properties": {
    "tgn:hierarchy":[
        "tgn:7549647",
        "tgn:1000004",
        "tgn:7000198",
        "tgn:1001894",
        "tgn:7029392"
    ],
    "tgn:id":7549647,
    "tgn:name:en":"Churelkhera",
    "tgn:placetype":[
        "aat:300008347"
    ]
},
  "bbox": [],
  "geometry": {"coordinates":[77.734316,25.730789],"type":"Point"}
}