{
  "id": 2704841,
  "type": "Feature",
  "properties": {
    "tgn:hierarchy":[
        "tgn:2704841",
        "tgn:1000001",
        "tgn:7012149",
        "tgn:2001540",
        "tgn:7007709",
        "tgn:7029392"
    ],
    "tgn:id":2704841,
    "tgn:name":"Sunset Lake",
    "tgn:placetype":[
        "aat:300006191"
    ]
},
  "bbox": [],
  "geometry": {"coordinates":[-80.4167,35.2167],"type":"Point"}
}