<<<<<<< HEAD
{
  "id": 7022230,
  "type": "Feature",
  "properties": {
    "tgn:hierarchy":[
        "tgn:7022230",
        "tgn:2001934",
        "tgn:1000001",
        "tgn:7012149",
        "tgn:7007826",
        "tgn:7029392"
    ],
    "tgn:id":7022230,
    "tgn:name":"Lakeside City",
    "tgn:placetype":[
        "aat:300008347"
    ]
},
  "bbox": [],
  "geometry": {"coordinates":[-98.5333,33.8167],"type":"Point"}
}
=======
{"geometry":{"type":"Point","coordinates":[-98.533300,33.816700]},"type":"Feature","properties":{"hierarchy":["tgn:7022230","tgn:2001934","tgn:1000001","tgn:7012149","tgn:7007826","tgn:7029392"],"placetype":["aat:300008347"],"id":7022230,"name:xx":"Lakeside City"}}
>>>>>>> 03f74aca74312dbeaf24d7e61306dd6a786dc3d0
