{
  "id": 7519387,
  "type": "Feature",
  "properties": {
    "tgn:hierarchy":[
        "tgn:7519387",
        "tgn:7000508",
        "tgn:1008380",
        "tgn:1000226",
        "tgn:1000006",
        "tgn:7029392"
    ],
    "tgn:id":7519387,
    "tgn:name:en":"Albatross Point",
    "tgn:placetype":[
        "aat:300386846"
    ]
},
  "bbox": [],
  "geometry": {"coordinates":[178.788889,-49.711389],"type":"Point"}
}