{
  "id": 2588730,
  "type": "Feature",
  "properties": {
    "tgn:hierarchy":[
        "tgn:2588730",
        "tgn:1000001",
        "tgn:2000309",
        "tgn:7012149",
        "tgn:7007248",
        "tgn:7029392"
    ],
    "tgn:id":2588730,
    "tgn:name":"Plymale Creek",
    "tgn:placetype":[
        "aat:300008706"
    ]
},
  "bbox": [],
  "geometry": {"coordinates":[-83.9167,33.2833],"type":"Point"}
}