<<<<<<< HEAD
{
  "id": 2256653,
  "type": "Feature",
  "properties": {
    "tgn:hierarchy":[
        "tgn:2256653",
        "tgn:1000001",
        "tgn:7012149",
        "tgn:1002991",
        "tgn:7007251",
        "tgn:7029392"
    ],
    "tgn:id":2256653,
    "tgn:name":"Cordes",
    "tgn:placetype":[
        "aat:300008347"
    ]
},
  "bbox": [],
  "geometry": {"coordinates":[-89.45,38.2833],"type":"Point"}
}
=======
{"geometry":{"type":"Point","coordinates":[-89.450000,38.283300]},"type":"Feature","properties":{"hierarchy":["tgn:2256653","tgn:1000001","tgn:7012149","tgn:1002991","tgn:7007251","tgn:7029392"],"placetype":["aat:300008347"],"id":2256653,"name:xx":"Cordes"}}
>>>>>>> 03f74aca74312dbeaf24d7e61306dd6a786dc3d0
