{
  "id": 2192233,
  "type": "Feature",
  "properties": {
    "tgn:hierarchy":[
        "tgn:2192233",
        "tgn:1000001",
        "tgn:7012149",
        "tgn:1002599",
        "tgn:7007708",
        "tgn:7029392"
    ],
    "tgn:id":2192233,
    "tgn:name":"Branch Creek",
    "tgn:placetype":[
        "aat:300008706"
    ]
},
  "bbox": [],
  "geometry": {"coordinates":[-123.7667,44.5167],"type":"Point"}
}