{
  "id": 2359363,
  "type": "Feature",
  "properties": {
    "tgn:hierarchy":[
        "tgn:2359363",
        "tgn:1000001",
        "tgn:7012149",
        "tgn:7007251",
        "tgn:7029392"
    ],
    "tgn:id":2359363,
    "tgn:name":"Grannys Branch",
    "tgn:placetype":[
        "aat:300008699"
    ]
},
  "bbox": [],
  "geometry": {"coordinates":[-89.2167,37.9667],"type":"Point"}
}