{
  "id": 7331938,
  "type": "Feature",
  "properties": {
    "tgn:hierarchy":[
        "tgn:7331938",
        "tgn:7002758",
        "tgn:7002817",
        "tgn:1000003",
        "tgn:1000095",
        "tgn:7029392"
    ],
    "tgn:id":7331938,
    "tgn:name":"La Paz",
    "tgn:placetype":[
        "aat:300008347"
    ]
},
  "bbox": [],
  "geometry": {"coordinates":[-4.916667,37.65],"type":"Point"}
}