{
  "id": 7467989,
  "type": "Feature",
  "properties": {
    "tgn:hierarchy":[
        "tgn:7467989",
        "tgn:1000004",
        "tgn:7004300",
        "tgn:1000141",
        "tgn:7029392"
    ],
    "tgn:id":7467989,
    "tgn:name":"Zhenhai",
    "tgn:placetype":[
        "aat:300008347"
    ]
},
  "bbox": [],
  "geometry": {"coordinates":[119.598924,23.644298],"type":"Point"}
}