{
  "id": 2474170,
  "type": "Feature",
  "properties": {
    "tgn:hierarchy":[
        "tgn:2474170",
        "tgn:1000001",
        "tgn:7012149",
        "tgn:1002645",
        "tgn:7007920",
        "tgn:7029392"
    ],
    "tgn:id":2474170,
    "tgn:name":"Lower Lynch Cove",
    "tgn:placetype":[
        "aat:300132316"
    ]
},
  "bbox": [],
  "geometry": {"coordinates":[-123.0333,47.15],"type":"Point"}
}