<<<<<<< HEAD
{
  "id": 2705336,
  "type": "Feature",
  "properties": {
    "tgn:hierarchy":[
        "tgn:2705336",
        "tgn:1000001",
        "tgn:1002198",
        "tgn:7012149",
        "tgn:7007826",
        "tgn:7029392"
    ],
    "tgn:id":2705336,
    "tgn:name":"Surfside",
    "tgn:placetype":[
        "aat:300008347"
    ]
},
  "bbox": [],
  "geometry": {"coordinates":[-95.2833,28.9333],"type":"Point"}
}
=======
{"geometry":{"type":"Point","coordinates":[-95.283300,28.933300]},"type":"Feature","properties":{"hierarchy":["tgn:2705336","tgn:1000001","tgn:1002198","tgn:7012149","tgn:7007826","tgn:7029392"],"placetype":["aat:300008347"],"id":2705336,"name:xx":"Surfside"}}
>>>>>>> 03f74aca74312dbeaf24d7e61306dd6a786dc3d0
