{
  "id": 2515650,
  "type": "Feature",
  "properties": {
    "tgn:hierarchy":[
        "tgn:2515650",
        "tgn:1000001",
        "tgn:7012149",
        "tgn:2002189",
        "tgn:7007919",
        "tgn:7029392"
    ],
    "tgn:id":2515650,
    "tgn:name":"Millstone Branch",
    "tgn:placetype":[
        "aat:300008699"
    ]
},
  "bbox": [],
  "geometry": {"coordinates":[-82.6667,36.7833],"type":"Point"}
}