{
  "id": 2471607,
  "type": "Feature",
  "properties": {
    "tgn:hierarchy":[
        "tgn:2471607",
        "tgn:1000001",
        "tgn:7012149",
        "tgn:2000181",
        "tgn:7007157",
        "tgn:7029392"
    ],
    "tgn:id":2471607,
    "tgn:name":"Lost Man Creek",
    "tgn:placetype":[
        "aat:300008706"
    ]
},
  "bbox": [],
  "geometry": {"coordinates":[-123.9833,41.2667],"type":"Point"}
}