{
  "id": 1022225,
  "type": "Feature",
  "properties": {
    "tgn:hierarchy":[
        "tgn:1022225",
        "tgn:7012827",
        "tgn:7002454",
        "tgn:1000047",
        "tgn:1000002",
        "tgn:7029392"
    ],
    "tgn:id":1022225,
    "tgn:name":"Nova Am\u00e9rica",
    "tgn:placetype":[
        "aat:300008347"
    ]
},
  "bbox": [],
  "geometry": {"coordinates":[-49.9833,-15.0167],"type":"Point"}
}