{
  "id": 7500838,
  "type": "Feature",
  "properties": {
    "tgn:hierarchy":[
        "tgn:7500838",
        "tgn:1000004",
        "tgn:7467799",
        "tgn:1000141",
        "tgn:7029392"
    ],
    "tgn:id":7500838,
    "tgn:name":"Dingnanzi",
    "tgn:placetype":[
        "aat:300008347"
    ]
},
  "bbox": [],
  "geometry": {"coordinates":[120.516951,24.096877],"type":"Point"}
}