{
  "id": 7571013,
  "type": "Feature",
  "properties": {
    "tgn:hierarchy":[
        "tgn:7571013",
        "tgn:1000004",
        "tgn:1001869",
        "tgn:7000198",
        "tgn:7029392"
    ],
    "tgn:id":7571013,
    "tgn:name:en":"Jamburi N\u0101r",
    "tgn:placetype":[
        "aat:300008699"
    ]
},
  "bbox": [],
  "geometry": {"coordinates":[70.166667,22.566667],"type":"Point"}
}