{
  "id": 2113878,
  "type": "Feature",
  "properties": {
    "tgn:hierarchy":[
        "tgn:2113878",
        "tgn:1000001",
        "tgn:7012149",
        "tgn:2002173",
        "tgn:7007919",
        "tgn:7029392"
    ],
    "tgn:id":2113878,
    "tgn:name":"Redlawn",
    "tgn:placetype":[
        "aat:300008347",
        "aat:300387210"
    ]
},
  "bbox": [],
  "geometry": {"coordinates":[-78.2333,36.6167],"type":"Point"}
}