{
  "id": 7138762,
  "type": "Feature",
  "properties": {
    "tgn:hierarchy":[
        "tgn:7138762",
        "tgn:1000003",
        "tgn:7003685",
        "tgn:7000084",
        "tgn:7029392"
    ],
    "tgn:id":7138762,
    "tgn:name":"Lauterbacher Knochen",
    "tgn:placetype":[
        "aat:300008795"
    ]
},
  "bbox": [],
  "geometry": {"coordinates":[13.166667,50.683333],"type":"Point"}
}