<<<<<<< HEAD
{
  "id": 7175858,
  "type": "Feature",
  "properties": {
    "tgn:hierarchy":[
        "tgn:7175858",
        "tgn:1000003",
        "tgn:7003688",
        "tgn:7000084",
        "tgn:7029392"
    ],
    "tgn:id":7175858,
    "tgn:name":"Gro\u00dfes Haaler Gehege",
    "tgn:placetype":[
        "aat:300008863"
    ]
},
  "bbox": [],
  "geometry": {"coordinates":[9.6,54.15],"type":"Point"}
}
=======
{"geometry":{"type":"Point","coordinates":[9.600000,54.150000]},"type":"Feature","properties":{"hierarchy":["tgn:7175858","tgn:1000003","tgn:7003688","tgn:7000084","tgn:7029392"],"placetype":["aat:300008863"],"id":7175858,"name:xx":"Gro\u00dfes Haaler Gehege"}}
>>>>>>> 03f74aca74312dbeaf24d7e61306dd6a786dc3d0
