{
  "id": 2396049,
  "type": "Feature",
  "properties": {
    "tgn:hierarchy":[
        "tgn:2396049",
        "tgn:1000001",
        "tgn:7012149",
        "tgn:2000208",
        "tgn:7007158",
        "tgn:7029392"
    ],
    "tgn:id":2396049,
    "tgn:name":"Holly Reservoir",
    "tgn:placetype":[
        "aat:300006191"
    ]
},
  "bbox": [],
  "geometry": {"coordinates":[-108.55,37.6667],"type":"Point"}
}