<<<<<<< HEAD
{
  "id": 2153923,
  "type": "Feature",
  "properties": {
    "tgn:hierarchy":[
        "tgn:2153923",
        "tgn:1000001",
        "tgn:7016172",
        "tgn:7012149",
        "tgn:2000153",
        "tgn:7029392"
    ],
    "tgn:id":2153923,
    "tgn:name":"Bear Cave Prong",
    "tgn:placetype":[
        "aat:300008699"
    ]
},
  "bbox": [],
  "geometry": {"coordinates":[-93.6167,34.7333],"type":"Point"}
}
=======
{"geometry":{"type":"Point","coordinates":[-93.616700,34.733300]},"type":"Feature","properties":{"hierarchy":["tgn:2153923","tgn:1000001","tgn:7016172","tgn:7012149","tgn:2000153","tgn:7029392"],"placetype":["aat:300008699"],"id":2153923,"name:xx":"Bear Cave Prong"}}
>>>>>>> 03f74aca74312dbeaf24d7e61306dd6a786dc3d0
