{
  "id": 7514486,
  "type": "Feature",
  "properties": {
    "tgn:hierarchy":[
        "tgn:7514486",
        "tgn:1009227",
        "tgn:1000226",
        "tgn:7016822",
        "tgn:1000006",
        "tgn:7029392"
    ],
    "tgn:id":7514486,
    "tgn:name:en":"Discovery Point",
    "tgn:placetype":[
        "aat:300386846"
    ]
},
  "bbox": [],
  "geometry": {"coordinates":[166.883333,-45.55],"type":"Point"}
}