{
  "id": 2384185,
  "type": "Feature",
  "properties": {
    "tgn:hierarchy":[
        "tgn:2384185",
        "tgn:1000001",
        "tgn:7012149",
        "tgn:2000220",
        "tgn:7007158",
        "tgn:7029392"
    ],
    "tgn:id":2384185,
    "tgn:name":"Heineman Ditch",
    "tgn:placetype":[
        "aat:300006075"
    ]
},
  "bbox": [],
  "geometry": {"coordinates":[-106.5333,40.6833],"type":"Point"}
}