{
  "id": 1033608,
  "type": "Feature",
  "properties": {
    "tgn:hierarchy":[
        "tgn:1033608",
        "tgn:1000003",
        "tgn:7002890",
        "tgn:1000070",
        "tgn:7029392"
    ],
    "tgn:id":1033608,
    "tgn:name":"Capelle-en-Thi\u00e9rache, la",
    "tgn:placetype":[
        "aat:300008347"
    ]
},
  "bbox": [],
  "geometry": {"coordinates":[3.9167,49.9833],"type":"Point"}
}