{
  "id": 7391171,
  "type": "Feature",
  "properties": {
    "tgn:hierarchy":[
        "tgn:7391171",
        "tgn:7005586",
        "tgn:1000001",
        "tgn:7005560",
        "tgn:7029392"
    ],
    "tgn:id":7391171,
    "tgn:name":"Roble, Cerro el",
    "tgn:placetype":[
        "aat:300008777"
    ]
},
  "bbox": [],
  "geometry": {"coordinates":[-104.216667,22.016667],"type":"Point"}
}