{
  "id": 7499615,
  "type": "Feature",
  "properties": {
    "tgn:hierarchy":[
        "tgn:7499615",
        "tgn:7001010",
        "tgn:1000004",
        "tgn:1000141",
        "tgn:7029392"
    ],
    "tgn:id":7499615,
    "tgn:name":"Ziqiang Yihao Suidao",
    "tgn:placetype":[
        "aat:300007899"
    ]
},
  "bbox": [],
  "geometry": {"coordinates":[121.351486,23.457206],"type":"Point"}
}