{
  "id": 2097198,
  "type": "Feature",
  "properties": {
    "tgn:hierarchy":[
        "tgn:2097198",
        "tgn:1000001",
        "tgn:2001809",
        "tgn:7012149",
        "tgn:7007713",
        "tgn:7029392"
    ],
    "tgn:id":2097198,
    "tgn:name":"Franklin",
    "tgn:placetype":[
        "aat:300008347",
        "aat:300387210"
    ]
},
  "bbox": [],
  "geometry": {"coordinates":[-97.0667,43.8833],"type":"Point"}
}