{
  "id": 1139691,
  "type": "Feature",
  "properties": {
    "tgn:hierarchy":[
        "tgn:1139691",
        "tgn:1000004",
        "tgn:7002081",
        "tgn:1000111",
        "tgn:7029392"
    ],
    "tgn:id":1139691,
    "tgn:name":"Tangtou",
    "tgn:placetype":[
        "aat:300008347"
    ]
},
  "bbox": [],
  "geometry": {"coordinates":[120.3167,31.6333],"type":"Point"}
}