{
  "id": 7299408,
  "type": "Feature",
  "properties": {
    "tgn:hierarchy":[
        "tgn:7299408",
        "tgn:7002807",
        "tgn:1000003",
        "tgn:7003837",
        "tgn:1000095",
        "tgn:7029392"
    ],
    "tgn:id":7299408,
    "tgn:name":"Valdesilos, Arroyo de",
    "tgn:placetype":[
        "aat:300266554",
        "aat:300008699"
    ]
},
  "bbox": [],
  "geometry": {"coordinates":[-6.216667,38.85],"type":"Point"}
}