{
  "id": 2610440,
  "type": "Feature",
  "properties": {
    "tgn:hierarchy":[
        "tgn:2610440",
        "tgn:1000001",
        "tgn:7012149",
        "tgn:7007566",
        "tgn:7029392"
    ],
    "tgn:id":2610440,
    "tgn:name":"Red Canyon",
    "tgn:placetype":[
        "aat:300008761"
    ]
},
  "bbox": [],
  "geometry": {"coordinates":[-106.2167,33.7667],"type":"Point"}
}