{
  "id": 2182008,
  "type": "Feature",
  "properties": {
    "tgn:hierarchy":[
        "tgn:2182008",
        "tgn:1000001",
        "tgn:7012149",
        "tgn:2001127",
        "tgn:7007522",
        "tgn:7029392"
    ],
    "tgn:id":2182008,
    "tgn:name":"Blue Lake Bayou",
    "tgn:placetype":[
        "aat:300008905"
    ]
},
  "bbox": [],
  "geometry": {"coordinates":[-90.3333,33.7667],"type":"Point"}
}