{
  "id": 2567257,
  "type": "Feature",
  "properties": {
    "tgn:hierarchy":[
        "tgn:2567257",
        "tgn:1000001",
        "tgn:7012149",
        "tgn:2001536",
        "tgn:7007709",
        "tgn:7029392"
    ],
    "tgn:id":2567257,
    "tgn:name":"Panther Point Creek",
    "tgn:placetype":[
        "aat:300008706"
    ]
},
  "bbox": [],
  "geometry": {"coordinates":[-80.3167,35.5167],"type":"Point"}
}