<<<<<<< HEAD
{
  "id": 7051690,
  "type": "Feature",
  "properties": {
    "tgn:hierarchy":[
        "tgn:7051690",
        "tgn:7024843",
        "tgn:1000003",
        "tgn:7008516",
        "tgn:1000080",
        "tgn:7029392"
    ],
    "tgn:id":7051690,
    "tgn:name":"Marecchia, Fiume",
    "tgn:placetype":[
        "aat:300008699"
    ]
},
  "bbox": [],
  "geometry": {"coordinates":[12.576667,44.076667],"type":"Point"}
}
=======
{"geometry":{"type":"Point","coordinates":[12.576667,44.076667]},"type":"Feature","properties":{"hierarchy":["tgn:7051690","tgn:7024843","tgn:1000003","tgn:7008516","tgn:1000080","tgn:7029392"],"placetype":["aat:300008699"],"id":7051690,"name:xx":"Marecchia, Fiume"}}
>>>>>>> 03f74aca74312dbeaf24d7e61306dd6a786dc3d0
