{
  "id": 2526511,
  "type": "Feature",
  "properties": {
    "tgn:hierarchy":[
        "tgn:2526511",
        "tgn:1000001",
        "tgn:2001430",
        "tgn:7012149",
        "tgn:7007566",
        "tgn:7029392"
    ],
    "tgn:id":2526511,
    "tgn:name":"Mossman",
    "tgn:placetype":[
        "aat:300008347"
    ]
},
  "bbox": [],
  "geometry": {"coordinates":[-104.35,33.05],"type":"Point"}
}