{
  "id": 7446230,
  "type": "Feature",
  "properties": {
    "tgn:hierarchy":[
        "tgn:7446230",
        "tgn:7002443",
        "tgn:7026278",
        "tgn:1000003",
        "tgn:7008591",
        "tgn:7029392"
    ],
    "tgn:id":7446230,
    "tgn:name:en":"Rhydymwyn",
    "tgn:placetype":[
        "aat:300008347"
    ]
},
  "bbox": [],
  "geometry": {"coordinates":[-3.183333,53.183333],"type":"Point"}
}