{
  "id": 7341130,
  "type": "Feature",
  "properties": {
    "tgn:hierarchy":[
        "tgn:7341130",
        "tgn:7002831",
        "tgn:1000003",
        "tgn:7002786",
        "tgn:1000095",
        "tgn:7029392"
    ],
    "tgn:id":7341130,
    "tgn:name":"Bubal, R\u00edo",
    "tgn:placetype":[
        "aat:300008699"
    ]
},
  "bbox": [],
  "geometry": {"coordinates":[-7.733333,42.45],"type":"Point"}
}