{
  "id": 1092438,
  "type": "Feature",
  "properties": {
    "tgn:hierarchy":[
        "tgn:1092438",
        "tgn:7001242",
        "tgn:1001422",
        "tgn:1000185",
        "tgn:7029392"
    ],
    "tgn:id":1092438,
    "tgn:name":"Nyamandhlovu",
    "tgn:placetype":[
        "aat:300008347"
    ]
},
  "bbox": [],
  "geometry": {"coordinates":[28.2667,-19.8333],"type":"Point"}
}