{
  "id": 7496216,
  "type": "Feature",
  "properties": {
    "tgn:hierarchy":[
        "tgn:7496216",
        "tgn:7487020",
        "tgn:1000004",
        "tgn:1000141",
        "tgn:7029392"
    ],
    "tgn:id":7496216,
    "tgn:name":"Wurongshankeng",
    "tgn:placetype":[
        "aat:300008699"
    ]
},
  "bbox": [],
  "geometry": {"coordinates":[120.865575,24.381044],"type":"Point"}
}