{
  "id": 7258895,
  "type": "Feature",
  "properties": {
    "tgn:hierarchy":[
        "tgn:7258895",
        "tgn:7003466",
        "tgn:1000003",
        "tgn:1000063",
        "tgn:4012014",
        "tgn:7029392"
    ],
    "tgn:id":7258895,
    "tgn:name":"Vir\u00e9e Sainte-Barbe, Bois de la",
    "tgn:placetype":[
        "aat:300008863"
    ]
},
  "bbox": [],
  "geometry": {"coordinates":[4.828321,50.007067],"type":"Point"}
}