{
  "id": 1138659,
  "type": "Feature",
  "properties": {
    "tgn:hierarchy":[
        "tgn:1138659",
        "tgn:1000004",
        "tgn:7011573",
        "tgn:7018214",
        "tgn:7002435",
        "tgn:7029392"
    ],
    "tgn:id":1138659,
    "tgn:name":"Zakharovo",
    "tgn:placetype":[
        "aat:300008347"
    ]
},
  "bbox": [],
  "geometry": {"coordinates":[36.7333,56.5167],"type":"Point"}
}