{
  "id": 7483269,
  "type": "Feature",
  "properties": {
    "tgn:hierarchy":[
        "tgn:7483269",
        "tgn:1000004",
        "tgn:7491221",
        "tgn:1000141",
        "tgn:7029392"
    ],
    "tgn:id":7483269,
    "tgn:name":"Meinaitian Zhushan Beifeng",
    "tgn:placetype":[
        "aat:300008798"
    ]
},
  "bbox": [],
  "geometry": {"coordinates":[120.996389,22.985556],"type":"Point"}
}