{
  "id": 7594334,
  "type": "Feature",
  "properties": {
    "tgn:hierarchy":[
        "tgn:7594334",
        "tgn:1000003",
        "tgn:7006667",
        "tgn:7029392"
    ],
    "tgn:id":7594334,
    "tgn:name":"Jegunovce",
    "tgn:placetype":[
        "aat:300387064",
        "aat:300265612"
    ]
},
  "bbox": [],
  "geometry": {"coordinates":[21.14528,42.11306],"type":"Point"}
}