{
  "id": 2614284,
  "type": "Feature",
  "properties": {
    "tgn:hierarchy":[
        "tgn:2614284",
        "tgn:1000001",
        "tgn:7012149",
        "tgn:2002298",
        "tgn:7013961",
        "tgn:7029392"
    ],
    "tgn:id":2614284,
    "tgn:name":"Reger Run",
    "tgn:placetype":[
        "aat:300008699"
    ]
},
  "bbox": [],
  "geometry": {"coordinates":[-80.25,38.7667],"type":"Point"}
}