{
  "id": 1059455,
  "type": "Feature",
  "properties": {
    "tgn:hierarchy":[
        "tgn:1059455",
        "tgn:7011651",
        "tgn:1000003",
        "tgn:7006660",
        "tgn:7029392"
    ],
    "tgn:id":1059455,
    "tgn:name":"Skadovsk",
    "tgn:placetype":[
        "aat:300008347"
    ]
},
  "bbox": [],
  "geometry": {"coordinates":[32.9333,46.1167],"type":"Point"}
}