{
  "id": 7005886,
  "type": "Feature",
  "properties": {
    "tgn:hierarchy":[
        "tgn:7005886",
        "tgn:7005328",
        "tgn:7593454",
        "tgn:1000009",
        "tgn:1000001",
        "tgn:7029392"
    ],
    "tgn:id":7005886,
    "tgn:name":"Codrington",
    "tgn:placetype":[
        "aat:300008347"
    ]
},
  "bbox": [],
  "geometry": {"coordinates":[-61.8167,17.7167],"type":"Point"}
}