{
  "id": 2671525,
  "type": "Feature",
  "properties": {
    "tgn:hierarchy":[
        "tgn:2671525",
        "tgn:1000001",
        "tgn:7012149",
        "tgn:2000347",
        "tgn:7007248",
        "tgn:7029392"
    ],
    "tgn:id":2671525,
    "tgn:name":"Smith Lake",
    "tgn:placetype":[
        "aat:300006191"
    ]
},
  "bbox": [],
  "geometry": {"coordinates":[-84.6167,33.4667],"type":"Point"}
}