{
  "id": 1125700,
  "type": "Feature",
  "properties": {
    "tgn:hierarchy":[
        "tgn:1125700",
        "tgn:7001242",
        "tgn:1000198",
        "tgn:7029392"
    ],
    "tgn:id":1125700,
    "tgn:name":"Konkiep",
    "tgn:placetype":[
        "aat:300008707"
    ]
},
  "bbox": [],
  "geometry": {"coordinates":[17.35,-28.0333],"type":"Point"}
}