{
  "id": 1007449,
  "type": "Feature",
  "properties": {
    "tgn:hierarchy":[
        "tgn:1007449",
        "tgn:1000004",
        "tgn:7492971",
        "tgn:1000141",
        "tgn:7029392"
    ],
    "tgn:id":1007449,
    "tgn:name":"Hsiao-hung-t'ou Y\u00fc",
    "tgn:placetype":[
        "aat:300008791"
    ]
},
  "bbox": [],
  "geometry": {"coordinates":[121.61,21.948889],"type":"Point"}
}