{
  "id": 2717723,
  "type": "Feature",
  "properties": {
    "tgn:hierarchy":[
        "tgn:2717723",
        "tgn:1000001",
        "tgn:7012149",
        "tgn:2002125",
        "tgn:7007827",
        "tgn:7029392"
    ],
    "tgn:id":2717723,
    "tgn:name":"Thomas Hollow",
    "tgn:placetype":[
        "aat:300008761"
    ]
},
  "bbox": [],
  "geometry": {"coordinates":[-111.6167,39.9167],"type":"Point"}
}