{
  "id": 2733228,
  "type": "Feature",
  "properties": {
    "tgn:hierarchy":[
        "tgn:2733228",
        "tgn:1000001",
        "tgn:7012149",
        "tgn:2001871",
        "tgn:7007825",
        "tgn:7029392"
    ],
    "tgn:id":2733228,
    "tgn:name":"Turkey Pond",
    "tgn:placetype":[
        "aat:300008680"
    ]
},
  "bbox": [],
  "geometry": {"coordinates":[-89.0333,35.3667],"type":"Point"}
}