{
  "id": 2582280,
  "type": "Feature",
  "properties": {
    "tgn:hierarchy":[
        "tgn:2582280",
        "tgn:1000001",
        "tgn:7012149",
        "tgn:2002188",
        "tgn:7007919",
        "tgn:7029392"
    ],
    "tgn:id":2582280,
    "tgn:name":"Pine Creek",
    "tgn:placetype":[
        "aat:300008706"
    ]
},
  "bbox": [],
  "geometry": {"coordinates":[-81.9167,37.1167],"type":"Point"}
}