{
  "id": 2144899,
  "type": "Feature",
  "properties": {
    "tgn:hierarchy":[
        "tgn:2144899",
        "tgn:1000001",
        "tgn:7012149",
        "tgn:2000846",
        "tgn:7007255",
        "tgn:7029392"
    ],
    "tgn:id":2144899,
    "tgn:name":"Bald Knob",
    "tgn:placetype":[
        "aat:300008798"
    ]
},
  "bbox": [],
  "geometry": {"coordinates":[-88.0167,36.8167],"type":"Point"}
}