{
  "id": 2092893,
  "type": "Feature",
  "properties": {
    "tgn:hierarchy":[
        "tgn:2092893",
        "tgn:1000001",
        "tgn:7012149",
        "tgn:1002586",
        "tgn:7007710",
        "tgn:7029392"
    ],
    "tgn:id":2092893,
    "tgn:name":"Seiple",
    "tgn:placetype":[
        "aat:300387016"
    ]
},
  "bbox": [],
  "geometry": {"coordinates":[-75.5167,40.6333],"type":"Point"}
}