{
  "id": 2698803,
  "type": "Feature",
  "properties": {
    "tgn:hierarchy":[
        "tgn:2698803",
        "tgn:1000001",
        "tgn:7012149",
        "tgn:7007157",
        "tgn:1002857",
        "tgn:7029392"
    ],
    "tgn:id":2698803,
    "tgn:name":"Strawberry Creek",
    "tgn:placetype":[
        "aat:300008706"
    ]
},
  "bbox": [],
  "geometry": {"coordinates":[-117.2167,34.2167],"type":"Point"}
}