{
  "id": 7203004,
  "type": "Feature",
  "properties": {
    "tgn:hierarchy":[
        "tgn:7203004",
        "tgn:1000003",
        "tgn:7003677",
        "tgn:7000084",
        "tgn:7029392"
    ],
    "tgn:id":7203004,
    "tgn:name":"Boxberg",
    "tgn:placetype":[
        "aat:300008347"
    ]
},
  "bbox": [],
  "geometry": {"coordinates":[7.633333,50.883333],"type":"Point"}
}