{
  "id": 2111543,
  "type": "Feature",
  "properties": {
    "tgn:hierarchy":[
        "tgn:2111543",
        "tgn:1000001",
        "tgn:7012149",
        "tgn:7014160",
        "tgn:7007919",
        "tgn:7029392"
    ],
    "tgn:id":2111543,
    "tgn:name":"Dunn Loring",
    "tgn:placetype":[
        "aat:300008347"
    ]
},
  "bbox": [],
  "geometry": {"coordinates":[-77.2167,38.8833],"type":"Point"}
}