{
  "id": 2451468,
  "type": "Feature",
  "properties": {
    "tgn:hierarchy":[
        "tgn:2451468",
        "tgn:1000001",
        "tgn:7016172",
        "tgn:2000120",
        "tgn:7012149",
        "tgn:7029392"
    ],
    "tgn:id":2451468,
    "tgn:name":"Little Bay Ditch",
    "tgn:placetype":[
        "aat:300006075"
    ]
},
  "bbox": [],
  "geometry": {"coordinates":[-90.5833,35.7667],"type":"Point"}
}