<<<<<<< HEAD
{
  "id": 2407229,
  "type": "Feature",
  "properties": {
    "tgn:hierarchy":[
        "tgn:2407229",
        "tgn:1000001",
        "tgn:7012149",
        "tgn:2001078",
        "tgn:7007521",
        "tgn:7029392"
    ],
    "tgn:id":2407229,
    "tgn:name":"Huntersville State Forest",
    "tgn:placetype":[
        "aat:300008863"
    ]
},
  "bbox": [],
  "geometry": {"coordinates":[-94.8333,46.7167],"type":"Point"}
}
=======
{"geometry":{"type":"Point","coordinates":[-94.833300,46.716700]},"type":"Feature","properties":{"hierarchy":["tgn:2407229","tgn:1000001","tgn:7012149","tgn:2001078","tgn:7007521","tgn:7029392"],"placetype":["aat:300008863"],"id":2407229,"name:xx":"Huntersville State Forest"}}
>>>>>>> 03f74aca74312dbeaf24d7e61306dd6a786dc3d0
