{
  "id": 7513859,
  "type": "Feature",
  "properties": {
    "tgn:hierarchy":[
        "tgn:7513859",
        "tgn:1009227",
        "tgn:1000226",
        "tgn:7016822",
        "tgn:1000006",
        "tgn:7029392"
    ],
    "tgn:id":7513859,
    "tgn:name:en":"First Cove",
    "tgn:placetype":[
        "aat:300132317"
    ]
},
  "bbox": [],
  "geometry": {"coordinates":[166.766667,-45.566667],"type":"Point"}
}