{
  "id": 2104360,
  "type": "Feature",
  "properties": {
    "tgn:hierarchy":[
        "tgn:2104360",
        "tgn:1000001",
        "tgn:7012149",
        "tgn:1002898",
        "tgn:7007826",
        "tgn:7029392"
    ],
    "tgn:id":2104360,
    "tgn:name":"Friendship",
    "tgn:placetype":[
        "aat:300008347",
        "aat:300387210"
    ]
},
  "bbox": [],
  "geometry": {"coordinates":[-95.0167,32.4833],"type":"Point"}
}