{
  "id": 7432453,
  "type": "Feature",
  "properties": {
    "tgn:hierarchy":[
        "tgn:7432453",
        "tgn:1000001",
        "tgn:7005592",
        "tgn:7005560",
        "tgn:7029392"
    ],
    "tgn:id":7432453,
    "tgn:name":"Zacaxumulco",
    "tgn:placetype":[
        "aat:300008347"
    ]
},
  "bbox": [],
  "geometry": {"coordinates":[-97.133333,19.183333],"type":"Point"}
}