{
  "id": 2528127,
  "type": "Feature",
  "properties": {
    "tgn:hierarchy":[
        "tgn:2528127",
        "tgn:1000001",
        "tgn:7012149",
        "tgn:2001544",
        "tgn:7007709",
        "tgn:7029392"
    ],
    "tgn:id":2528127,
    "tgn:name":"Mountain Tea Branch",
    "tgn:placetype":[
        "aat:300008699"
    ]
},
  "bbox": [],
  "geometry": {"coordinates":[-82.7667,35.1333],"type":"Point"}
}