{
  "id": 7073641,
  "type": "Feature",
  "properties": {
    "tgn:hierarchy":[
        "tgn:7073641",
        "tgn:1000003",
        "tgn:7003688",
        "tgn:7000084",
        "tgn:7029392"
    ],
    "tgn:id":7073641,
    "tgn:name":"S\u00fcderh\u00f6rn",
    "tgn:placetype":[
        "aat:300000206"
    ]
},
  "bbox": [],
  "geometry": {"coordinates":[8.683333,54.866667],"type":"Point"}
}