{
  "id": 2727482,
  "type": "Feature",
  "properties": {
    "tgn:hierarchy":[
        "tgn:2727482",
        "tgn:1000001",
        "tgn:2000459",
        "tgn:7012149",
        "tgn:7007250",
        "tgn:7029392"
    ],
    "tgn:id":2727482,
    "tgn:name":"Trail Creek",
    "tgn:placetype":[
        "aat:300008706"
    ]
},
  "bbox": [],
  "geometry": {"coordinates":[-115.8833,43.8667],"type":"Point"}
}