{
  "id": 7495287,
  "type": "Feature",
  "properties": {
    "tgn:hierarchy":[
        "tgn:7495287",
        "tgn:1000004",
        "tgn:7492971",
        "tgn:1000141",
        "tgn:7029392"
    ],
    "tgn:id":7495287,
    "tgn:name":"Diliu Gongmu",
    "tgn:placetype":[
        "aat:300266755"
    ]
},
  "bbox": [],
  "geometry": {"coordinates":[120.588896,22.580592],"type":"Point"}
}