<<<<<<< HEAD
{
  "id": 7024129,
  "type": "Feature",
  "properties": {
    "tgn:hierarchy":[
        "tgn:7024129",
        "tgn:1000003",
        "tgn:7006366",
        "tgn:7029392"
    ],
    "tgn:id":7024129,
    "tgn:name":"\u015awie\u031ctokrzyskie",
    "tgn:placetype":[
        "aat:300387064",
        "aat:300235112"
    ]
},
  "bbox": [],
  "geometry": {"coordinates":[20.75,50.75],"type":"Point"}
}
=======
{"geometry":{"type":"Point","coordinates":[20.750000,50.750000]},"type":"Feature","properties":{"hierarchy":["tgn:7024129","tgn:1000003","tgn:7006366","tgn:7029392"],"placetype":["aat:300387064","aat:300235112"],"id":7024129,"name:xx":"\u015awie\u031ctokrzyskie"}}
>>>>>>> 03f74aca74312dbeaf24d7e61306dd6a786dc3d0
