{
  "id": 7230575,
  "type": "Feature",
  "properties": {
    "tgn:hierarchy":[
        "tgn:7230575",
        "tgn:7002681",
        "tgn:7001395",
        "tgn:1000003",
        "tgn:1000074",
        "tgn:7029392"
    ],
    "tgn:id":7230575,
    "tgn:name":"Kam\u00e1rion",
    "tgn:placetype":[
        "aat:300008347"
    ]
},
  "bbox": [],
  "geometry": {"coordinates":[23.766667,38.466667],"type":"Point"}
}