{
  "id": 2068301,
  "type": "Feature",
  "properties": {
    "tgn:hierarchy":[
        "tgn:2068301",
        "tgn:1000001",
        "tgn:1002328",
        "tgn:7012149",
        "tgn:7007568",
        "tgn:7029392"
    ],
    "tgn:id":2068301,
    "tgn:name":"Cadosia",
    "tgn:placetype":[
        "aat:300008347"
    ]
},
  "bbox": [],
  "geometry": {"coordinates":[-75.2667,41.9667],"type":"Point"}
}