{
  "id": 7364421,
  "type": "Feature",
  "properties": {
    "tgn:hierarchy":[
        "tgn:7364421",
        "tgn:1000001",
        "tgn:7005599",
        "tgn:7005560",
        "tgn:7029392"
    ],
    "tgn:id":7364421,
    "tgn:name":"El Sauce",
    "tgn:placetype":[
        "aat:300008347"
    ]
},
  "bbox": [],
  "geometry": {"coordinates":[-97.783333,21.966667],"type":"Point"}
}