{
  "id": 2637224,
  "type": "Feature",
  "properties": {
    "tgn:hierarchy":[
        "tgn:2637224",
        "tgn:1000001",
        "tgn:1002712",
        "tgn:7012149",
        "tgn:7007159",
        "tgn:7029392"
    ],
    "tgn:id":2637224,
    "tgn:name":"Saint Helena Island",
    "tgn:placetype":[
        "aat:300008791"
    ]
},
  "bbox": [],
  "geometry": {"coordinates":[-72.7667,41.25],"type":"Point"}
}