{
  "id": 1102936,
  "type": "Feature",
  "properties": {
    "tgn:hierarchy":[
        "tgn:1102936",
        "tgn:1000003",
        "tgn:7002883",
        "tgn:1000070",
        "tgn:7008038",
        "tgn:7029392"
    ],
    "tgn:id":1102936,
    "tgn:name":"Luxembourg, Jardin du",
    "tgn:placetype":[
        "aat:300008187"
    ]
},
  "bbox": [],
  "geometry": {"coordinates":[2.3167,48.85],"type":"Point"}
}