{
  "id": 2600989,
  "type": "Feature",
  "properties": {
    "tgn:hierarchy":[
        "tgn:2600989",
        "tgn:1000001",
        "tgn:2002320",
        "tgn:7012149",
        "tgn:7007922",
        "tgn:7029392"
    ],
    "tgn:id":2600989,
    "tgn:name":"Pumpkin Valley",
    "tgn:placetype":[
        "aat:300008761"
    ]
},
  "bbox": [],
  "geometry": {"coordinates":[-91.3167,44.75],"type":"Point"}
}