{
  "id": 2109274,
  "type": "Feature",
  "properties": {
    "tgn:hierarchy":[
        "tgn:2109274",
        "tgn:1000001",
        "tgn:7012149",
        "tgn:2002122",
        "tgn:7007827",
        "tgn:7029392"
    ],
    "tgn:id":2109274,
    "tgn:name":"Snyderville",
    "tgn:placetype":[
        "aat:300008347",
        "aat:300387210"
    ]
},
  "bbox": [],
  "geometry": {"coordinates":[-111.5333,40.6833],"type":"Point"}
}