{
  "id": 2414734,
  "type": "Feature",
  "properties": {
    "tgn:hierarchy":[
        "tgn:2414734",
        "tgn:1000001",
        "tgn:7012149",
        "tgn:2002059",
        "tgn:7007826",
        "tgn:7029392"
    ],
    "tgn:id":2414734,
    "tgn:name":"Isaac Draw",
    "tgn:placetype":[
        "aat:300008761"
    ]
},
  "bbox": [],
  "geometry": {"coordinates":[-101.3667,31.1667],"type":"Point"}
}