{
  "id": 2527589,
  "type": "Feature",
  "properties": {
    "tgn:hierarchy":[
        "tgn:2527589",
        "tgn:1000001",
        "tgn:7016172",
        "tgn:7012149",
        "tgn:2000136",
        "tgn:7029392"
    ],
    "tgn:id":2527589,
    "tgn:name":"Mount Zion",
    "tgn:placetype":[
        "aat:300008347"
    ]
},
  "bbox": [],
  "geometry": {"coordinates":[-91.4167,35.7167],"type":"Point"}
}