{
  "id": 1020832,
  "type": "Feature",
  "properties": {
    "tgn:hierarchy":[
        "tgn:1020832",
        "tgn:7006252",
        "tgn:1000047",
        "tgn:7002455",
        "tgn:1000002",
        "tgn:7029392"
    ],
    "tgn:id":1020832,
    "tgn:name":"Beneditinos",
    "tgn:placetype":[
        "aat:300008347"
    ]
},
  "bbox": [],
  "geometry": {"coordinates":[-42.3667,-5.4333],"type":"Point"}
}