{
  "id": 2037288,
  "type": "Feature",
  "properties": {
    "tgn:hierarchy":[
        "tgn:2037288",
        "tgn:1000001",
        "tgn:7012149",
        "tgn:2000757",
        "tgn:7007254",
        "tgn:7029392"
    ],
    "tgn:id":2037288,
    "tgn:name":"WaKeeney",
    "tgn:placetype":[
        "aat:300008347"
    ]
},
  "bbox": [],
  "geometry": {"coordinates":[-99.8667,39.0167],"type":"Point"}
}