{
  "id": 7416481,
  "type": "Feature",
  "properties": {
    "tgn:hierarchy":[
        "tgn:7416481",
        "tgn:7005584",
        "tgn:1000001",
        "tgn:7005560",
        "tgn:7029392"
    ],
    "tgn:id":7416481,
    "tgn:name":"Calzada de la Merced",
    "tgn:placetype":[
        "aat:300008347"
    ]
},
  "bbox": [],
  "geometry": {"coordinates":[-101.859167,20.777222],"type":"Point"}
}