{
  "id": 7311564,
  "type": "Feature",
  "properties": {
    "tgn:hierarchy":[
        "tgn:7311564",
        "tgn:1001699",
        "tgn:1000049",
        "tgn:1000002",
        "tgn:7029392"
    ],
    "tgn:id":7311564,
    "tgn:name":"Leones, R\u00edo",
    "tgn:placetype":[
        "aat:300008699"
    ]
},
  "bbox": [],
  "geometry": {"coordinates":[-71.866667,-41.516667],"type":"Point"}
}