{
  "id": 7530986,
  "type": "Feature",
  "properties": {
    "tgn:hierarchy":[
        "tgn:7530986",
        "tgn:7001242",
        "tgn:7016833",
        "tgn:7001312",
        "tgn:7029392"
    ],
    "tgn:id":7530986,
    "tgn:name:en":"Mansh\u012byat al Umar\u0101'",
    "tgn:placetype":[
        "aat:300008347"
    ]
},
  "bbox": [],
  "geometry": {"coordinates":[31.170957,31.035283],"type":"Point"}
}