{
  "id": 1091899,
  "type": "Feature",
  "properties": {
    "tgn:hierarchy":[
        "tgn:1091899",
        "tgn:7001242",
        "tgn:7015576",
        "tgn:1000182",
        "tgn:7029392"
    ],
    "tgn:id":1091899,
    "tgn:name":"Benin City",
    "tgn:placetype":[
        "aat:300008347",
        "aat:300387218",
        "aat:300008389",
        "aat:300387298",
        "aat:300387221",
        "aat:300387270",
        "aat:300387302",
        "aat:300387286"
    ]
},
  "bbox": [],
  "geometry": {"coordinates":[5.6833,6.3167],"type":"Point"}
}