{
  "id": 7559814,
  "type": "Feature",
  "properties": {
    "tgn:hierarchy":[
        "tgn:7559814",
        "tgn:1000004",
        "tgn:7000198",
        "tgn:7016722",
        "tgn:7029392"
    ],
    "tgn:id":7559814,
    "tgn:name:en":"Khatria",
    "tgn:placetype":[
        "aat:300008347"
    ]
},
  "bbox": [],
  "geometry": {"coordinates":[79.622269,27.707758],"type":"Point"}
}