{
  "id": 2778295,
  "type": "Feature",
  "properties": {
    "tgn:hierarchy":[
        "tgn:2778295",
        "tgn:1000001",
        "tgn:7012149",
        "tgn:2001275",
        "tgn:7007524",
        "tgn:7029392"
    ],
    "tgn:id":2778295,
    "tgn:name":"Wisner Crossing",
    "tgn:placetype":[
        "aat:300008347"
    ]
},
  "bbox": [],
  "geometry": {"coordinates":[-111.0667,45.7667],"type":"Point"}
}