{
  "id": 2726431,
  "type": "Feature",
  "properties": {
    "tgn:hierarchy":[
        "tgn:2726431",
        "tgn:1000001",
        "tgn:7012149",
        "tgn:1002429",
        "tgn:7007826",
        "tgn:7029392"
    ],
    "tgn:id":2726431,
    "tgn:name":"Town Branch",
    "tgn:placetype":[
        "aat:300008699"
    ]
},
  "bbox": [],
  "geometry": {"coordinates":[-95.95,30.7667],"type":"Point"}
}