{
  "id": 2163389,
  "type": "Feature",
  "properties": {
    "tgn:hierarchy":[
        "tgn:2163389",
        "tgn:1000001",
        "tgn:7012149",
        "tgn:7007826",
        "tgn:7029392"
    ],
    "tgn:id":2163389,
    "tgn:name":"Bens Branch",
    "tgn:placetype":[
        "aat:300008699"
    ]
},
  "bbox": [],
  "geometry": {"coordinates":[-95.25,30.0667],"type":"Point"}
}