{
  "id": 2785676,
  "type": "Feature",
  "properties": {
    "tgn:hierarchy":[
        "tgn:2785676",
        "tgn:7002659",
        "tgn:1000001",
        "tgn:7012149",
        "tgn:2000036",
        "tgn:7029392"
    ],
    "tgn:id":2785676,
    "tgn:name":"Yolande Mine Number 2",
    "tgn:placetype":[
        "aat:300000390"
    ]
},
  "bbox": [],
  "geometry": {"coordinates":[-87.1833,33.35],"type":"Point"}
}