<<<<<<< HEAD
{
  "id": 7374355,
  "type": "Feature",
  "properties": {
    "tgn:hierarchy":[
        "tgn:7374355",
        "tgn:7005583",
        "tgn:1000001",
        "tgn:7005560",
        "tgn:7029392"
    ],
    "tgn:id":7374355,
    "tgn:name":"Laguna Prieta",
    "tgn:placetype":[
        "aat:300008347"
    ]
},
  "bbox": [],
  "geometry": {"coordinates":[-105.1,24.35],"type":"Point"}
}
=======
{"geometry":{"type":"Point","coordinates":[-105.100000,24.350000]},"type":"Feature","properties":{"hierarchy":["tgn:7374355","tgn:7005583","tgn:1000001","tgn:7005560","tgn:7029392"],"placetype":["aat:300008347"],"id":7374355,"name:xx":"Laguna Prieta"}}
>>>>>>> 03f74aca74312dbeaf24d7e61306dd6a786dc3d0
