{
  "id": 7321973,
  "type": "Feature",
  "properties": {
    "tgn:hierarchy":[
        "tgn:7321973",
        "tgn:1001692",
        "tgn:1000049",
        "tgn:1000002",
        "tgn:7029392"
    ],
    "tgn:id":7321973,
    "tgn:name":"Boyeco",
    "tgn:placetype":[
        "aat:300008347"
    ]
},
  "bbox": [],
  "geometry": {"coordinates":[-72.733333,-38.616667],"type":"Point"}
}