{
  "id": 1116599,
  "type": "Feature",
  "properties": {
    "tgn:hierarchy":[
        "tgn:1116599",
        "tgn:1000001",
        "tgn:7012149",
        "tgn:2000991",
        "tgn:7007520",
        "tgn:7029392"
    ],
    "tgn:id":1116599,
    "tgn:name":"Higgins Lake",
    "tgn:placetype":[
        "aat:300008680"
    ]
},
  "bbox": [],
  "geometry": {"coordinates":[-84.7167,44.4667],"type":"Point"}
}