{
  "id": 1108753,
  "type": "Feature",
  "properties": {
    "tgn:hierarchy":[
        "tgn:1108753",
        "tgn:1001437",
        "tgn:1000004",
        "tgn:7018455",
        "tgn:1000144",
        "tgn:7029392"
    ],
    "tgn:id":1108753,
    "tgn:name":"Bilican Daglari",
    "tgn:placetype":[
        "aat:300008795"
    ]
},
  "bbox": [],
  "geometry": {"coordinates":[42.1667,38.9667],"type":"Point"}
}