{
  "id": 7280187,
  "type": "Feature",
  "properties": {
    "tgn:hierarchy":[
        "tgn:7280187",
        "tgn:1001702",
        "tgn:1000049",
        "tgn:1000002",
        "tgn:7029392"
    ],
    "tgn:id":7280187,
    "tgn:name":"Ra\u00fal, Islote",
    "tgn:placetype":[
        "aat:300008791"
    ]
},
  "bbox": [],
  "geometry": {"coordinates":[-75.483333,-49.416667],"type":"Point"}
}