{
  "id": 7283564,
  "type": "Feature",
  "properties": {
    "tgn:hierarchy":[
        "tgn:7283564",
        "tgn:1001768",
        "tgn:1000049",
        "tgn:1000002",
        "tgn:7029392"
    ],
    "tgn:id":7283564,
    "tgn:name":"P\u00e1jaros Ni\u00f1os, Islote",
    "tgn:placetype":[
        "aat:300008791"
    ]
},
  "bbox": [],
  "geometry": {"coordinates":[-71.693056,-33.366389],"type":"Point"}
}