{
  "id": 7414179,
  "type": "Feature",
  "properties": {
    "tgn:hierarchy":[
        "tgn:7414179",
        "tgn:7005580",
        "tgn:1000001",
        "tgn:7005560",
        "tgn:7029392"
    ],
    "tgn:id":7414179,
    "tgn:name":"Las Casitas",
    "tgn:placetype":[
        "aat:300008347"
    ]
},
  "bbox": [],
  "geometry": {"coordinates":[-94.008333,16.558333],"type":"Point"}
}