{
  "id": 1119292,
  "type": "Feature",
  "properties": {
    "tgn:hierarchy":[
        "tgn:1119292",
        "tgn:1000001",
        "tgn:1002724",
        "tgn:7012149",
        "tgn:7007517",
        "tgn:7029392"
    ],
    "tgn:id":1119292,
    "tgn:name":"Morses Pond",
    "tgn:placetype":[
        "aat:300008688"
    ]
},
  "bbox": [],
  "geometry": {"coordinates":[-71.3167,42.2833],"type":"Point"}
}