{
  "id": 7044059,
  "type": "Feature",
  "properties": {
    "tgn:hierarchy":[
        "tgn:7044059",
        "tgn:7002995",
        "tgn:1000003",
        "tgn:7002997",
        "tgn:1000080",
        "tgn:7029392"
    ],
    "tgn:id":7044059,
    "tgn:name":"Capobosco",
    "tgn:placetype":[
        "aat:300008347"
    ]
},
  "bbox": [],
  "geometry": {"coordinates":[11.716667,45.016667],"type":"Point"}
}