{
  "id": 1067940,
  "type": "Feature",
  "properties": {
    "tgn:hierarchy":[
        "tgn:1067940",
        "tgn:1000004",
        "tgn:7002372",
        "tgn:1000111",
        "tgn:7029392"
    ],
    "tgn:id":1067940,
    "tgn:name":"Erdaohe",
    "tgn:placetype":[
        "aat:300008347"
    ]
},
  "bbox": [],
  "geometry": {"coordinates":[127.5833,43.6167],"type":"Point"}
}