{
  "id": 7438882,
  "type": "Feature",
  "properties": {
    "tgn:hierarchy":[
        "tgn:7438882",
        "tgn:1000001",
        "tgn:7005599",
        "tgn:7005560",
        "tgn:7029392"
    ],
    "tgn:id":7438882,
    "tgn:name":"Tecuanapa, Arroyo",
    "tgn:placetype":[
        "aat:300008699"
    ]
},
  "bbox": [],
  "geometry": {"coordinates":[-94.733333,18.433333],"type":"Point"}
}