<<<<<<< HEAD
{
  "id": 2769832,
  "type": "Feature",
  "properties": {
    "tgn:hierarchy":[
        "tgn:2769832",
        "tgn:1000001",
        "tgn:7012149",
        "tgn:2002121",
        "tgn:7007827",
        "tgn:7029392"
    ],
    "tgn:id":2769832,
    "tgn:name":"Wikieup Spring",
    "tgn:placetype":[
        "aat:300008697"
    ]
},
  "bbox": [],
  "geometry": {"coordinates":[-111.6167,38.9667],"type":"Point"}
}
=======
{"geometry":{"type":"Point","coordinates":[-111.616700,38.966700]},"type":"Feature","properties":{"hierarchy":["tgn:2769832","tgn:1000001","tgn:7012149","tgn:2002121","tgn:7007827","tgn:7029392"],"placetype":["aat:300008697"],"id":2769832,"name:xx":"Wikieup Spring"}}
>>>>>>> 03f74aca74312dbeaf24d7e61306dd6a786dc3d0
