{
  "id": 7387938,
  "type": "Feature",
  "properties": {
    "tgn:hierarchy":[
        "tgn:7387938",
        "tgn:1000001",
        "tgn:7005594",
        "tgn:7005560",
        "tgn:7029392"
    ],
    "tgn:id":7387938,
    "tgn:name":"Puerto Chanceza",
    "tgn:placetype":[
        "aat:300008347"
    ]
},
  "bbox": [],
  "geometry": {"coordinates":[-100.283333,21.683333],"type":"Point"}
}