{
  "id": 1125809,
  "type": "Feature",
  "properties": {
    "tgn:hierarchy":[
        "tgn:1125809",
        "tgn:1000004",
        "tgn:1003362",
        "tgn:7014786",
        "tgn:7029392"
    ],
    "tgn:id":1125809,
    "tgn:name":"Kuragaty",
    "tgn:placetype":[
        "aat:300008707"
    ]
},
  "bbox": [],
  "geometry": {"coordinates":[73.5833,43.9167],"type":"Point"}
}