{
  "id": 1071849,
  "type": "Feature",
  "properties": {
    "tgn:hierarchy":[
        "tgn:1071849",
        "tgn:7002075",
        "tgn:1000004",
        "tgn:1000111",
        "tgn:7029392"
    ],
    "tgn:id":1071849,
    "tgn:name":"Shuiduixia",
    "tgn:placetype":[
        "aat:300008347"
    ]
},
  "bbox": [],
  "geometry": {"coordinates":[118.8333,30.2833],"type":"Point"}
}