<<<<<<< HEAD
{
  "id": 7242859,
  "type": "Feature",
  "properties": {
    "tgn:hierarchy":[
        "tgn:7242859",
        "tgn:7003466",
        "tgn:1000003",
        "tgn:1000063",
        "tgn:4012014",
        "tgn:7029392"
    ],
    "tgn:id":7242859,
    "tgn:name":"Les Comognes",
    "tgn:placetype":[
        "aat:300008347"
    ]
},
  "bbox": [],
  "geometry": {"coordinates":[4.780813,50.469086],"type":"Point"}
}
=======
{"geometry":{"type":"Point","coordinates":[4.780813,50.469086]},"type":"Feature","properties":{"hierarchy":["tgn:7242859","tgn:7003466","tgn:1000003","tgn:1000063","tgn:4012014","tgn:7029392"],"placetype":["aat:300008347"],"id":7242859,"name:xx":"Les Comognes"}}
>>>>>>> 03f74aca74312dbeaf24d7e61306dd6a786dc3d0
