{
  "id": 2346785,
  "type": "Feature",
  "properties": {
    "tgn:hierarchy":[
        "tgn:2346785",
        "tgn:1000001",
        "tgn:2000198",
        "tgn:7012149",
        "tgn:7007158",
        "tgn:7029392"
    ],
    "tgn:id":2346785,
    "tgn:name":"Geer Canyon",
    "tgn:placetype":[
        "aat:300008761"
    ]
},
  "bbox": [],
  "geometry": {"coordinates":[-105.3333,40.15],"type":"Point"}
}