<<<<<<< HEAD
{
  "id": 2767081,
  "type": "Feature",
  "properties": {
    "tgn:hierarchy":[
        "tgn:2767081",
        "tgn:1000001",
        "tgn:2001411",
        "tgn:7012149",
        "tgn:7007526",
        "tgn:7029392"
    ],
    "tgn:id":2767081,
    "tgn:name":"White Rock",
    "tgn:placetype":[
        "aat:300008347"
    ]
},
  "bbox": [],
  "geometry": {"coordinates":[-116.1833,41.7333],"type":"Point"}
}
=======
{"geometry":{"type":"Point","coordinates":[-116.183300,41.733300]},"type":"Feature","properties":{"hierarchy":["tgn:2767081","tgn:1000001","tgn:2001411","tgn:7012149","tgn:7007526","tgn:7029392"],"placetype":["aat:300008347"],"id":2767081,"name:xx":"White Rock"}}
>>>>>>> 03f74aca74312dbeaf24d7e61306dd6a786dc3d0
