{
  "id": 2701755,
  "type": "Feature",
  "properties": {
    "tgn:hierarchy":[
        "tgn:2701755",
        "tgn:1000001",
        "tgn:7012149",
        "tgn:2000232",
        "tgn:7007158",
        "tgn:7029392"
    ],
    "tgn:id":2701755,
    "tgn:name":"Sugarloaf Basin",
    "tgn:placetype":[
        "aat:300386845"
    ]
},
  "bbox": [],
  "geometry": {"coordinates":[-107.95,40.5333],"type":"Point"}
}