{
  "id": 2639352,
  "type": "Feature",
  "properties": {
    "tgn:hierarchy":[
        "tgn:2639352",
        "tgn:1000001",
        "tgn:7012149",
        "tgn:7007827",
        "tgn:7029392"
    ],
    "tgn:id":2639352,
    "tgn:name":"Salt Wash",
    "tgn:placetype":[
        "aat:300008761"
    ]
},
  "bbox": [],
  "geometry": {"coordinates":[-111.0833,38.4667],"type":"Point"}
}