{
  "id": 2615857,
  "type": "Feature",
  "properties": {
    "tgn:hierarchy":[
        "tgn:2615857",
        "tgn:1000001",
        "tgn:2002152",
        "tgn:7012149",
        "tgn:7007919",
        "tgn:7029392"
    ],
    "tgn:id":2615857,
    "tgn:name":"Reynolds Creek",
    "tgn:placetype":[
        "aat:300008706"
    ]
},
  "bbox": [],
  "geometry": {"coordinates":[-78.55,36.8667],"type":"Point"}
}