<<<<<<< HEAD
{
  "id": 2152127,
  "type": "Feature",
  "properties": {
    "tgn:hierarchy":[
        "tgn:2152127",
        "tgn:1000001",
        "tgn:1002289",
        "tgn:7012149",
        "tgn:7007240",
        "tgn:7029392"
    ],
    "tgn:id":2152127,
    "tgn:name":"Baxter Island",
    "tgn:placetype":[
        "aat:300008905"
    ]
},
  "bbox": [],
  "geometry": {"coordinates":[-81.1833,26.15],"type":"Point"}
}
=======
{"geometry":{"type":"Point","coordinates":[-81.183300,26.150000]},"type":"Feature","properties":{"hierarchy":["tgn:2152127","tgn:1000001","tgn:1002289","tgn:7012149","tgn:7007240","tgn:7029392"],"placetype":["aat:300008905"],"id":2152127,"name:xx":"Baxter Island"}}
>>>>>>> 03f74aca74312dbeaf24d7e61306dd6a786dc3d0
