{
  "id": 2738285,
  "type": "Feature",
  "properties": {
    "tgn:hierarchy":[
        "tgn:2738285",
        "tgn:7013349",
        "tgn:1000001",
        "tgn:7012149",
        "tgn:7007708",
        "tgn:7029392"
    ],
    "tgn:id":2738285,
    "tgn:name":"Umpqua Gulch",
    "tgn:placetype":[
        "aat:300008761"
    ]
},
  "bbox": [],
  "geometry": {"coordinates":[-118.25,44.8167],"type":"Point"}
}