{
  "id": 7412999,
  "type": "Feature",
  "properties": {
    "tgn:hierarchy":[
        "tgn:7412999",
        "tgn:1000001",
        "tgn:7005596",
        "tgn:7005560",
        "tgn:7029392"
    ],
    "tgn:id":7412999,
    "tgn:name:es":"San Isidro, R\u00edo",
    "tgn:placetype":[
        "aat:300008699"
    ]
},
  "bbox": [],
  "geometry": {"coordinates":[-91.225,17.508333],"type":"Point"}
}