<<<<<<< HEAD
{
  "id": 2254404,
  "type": "Feature",
  "properties": {
    "tgn:hierarchy":[
        "tgn:2254404",
        "tgn:1000001",
        "tgn:7012149",
        "tgn:7007525",
        "tgn:7029392"
    ],
    "tgn:id":2254404,
    "tgn:name":"Coon Creek",
    "tgn:placetype":[
        "aat:300008706"
    ]
},
  "bbox": [],
  "geometry": {"coordinates":[-99.4833,42.8833],"type":"Point"}
}
=======
{"geometry":{"type":"Point","coordinates":[-99.483300,42.883300]},"type":"Feature","properties":{"hierarchy":["tgn:2254404","tgn:1000001","tgn:7012149","tgn:7007525","tgn:7029392"],"placetype":["aat:300008706"],"id":2254404,"name:xx":"Coon Creek"}}
>>>>>>> 03f74aca74312dbeaf24d7e61306dd6a786dc3d0
