{
  "id": 2449830,
  "type": "Feature",
  "properties": {
    "tgn:hierarchy":[
        "tgn:2449830",
        "tgn:1000001",
        "tgn:7012149",
        "tgn:1002579",
        "tgn:7007252",
        "tgn:7029392"
    ],
    "tgn:id":2449830,
    "tgn:name":"Linden Hollow",
    "tgn:placetype":[
        "aat:300008761"
    ]
},
  "bbox": [],
  "geometry": {"coordinates":[-86.6167,38.9667],"type":"Point"}
}