{
  "id": 7187909,
  "type": "Feature",
  "properties": {
    "tgn:hierarchy":[
        "tgn:7187909",
        "tgn:1000003",
        "tgn:7003676",
        "tgn:7000084",
        "tgn:7029392"
    ],
    "tgn:id":7187909,
    "tgn:name":"Endschlag-Bach",
    "tgn:placetype":[
        "aat:300008699"
    ]
},
  "bbox": [],
  "geometry": {"coordinates":[9.683333,51.316667],"type":"Point"}
}