{
  "id": 2104049,
  "type": "Feature",
  "properties": {
    "tgn:hierarchy":[
        "tgn:2104049",
        "tgn:1000001",
        "tgn:7012149",
        "tgn:2002075",
        "tgn:7007826",
        "tgn:7029392"
    ],
    "tgn:id":2104049,
    "tgn:name":"El Sauz",
    "tgn:placetype":[
        "aat:300008347"
    ]
},
  "bbox": [],
  "geometry": {"coordinates":[-98.8667,26.5667],"type":"Point"}
}