{
  "id": 1071266,
  "type": "Feature",
  "properties": {
    "tgn:hierarchy":[
        "tgn:1071266",
        "tgn:1000004",
        "tgn:7001319",
        "tgn:1000111",
        "tgn:7029392"
    ],
    "tgn:id":1071266,
    "tgn:name":"Sajia",
    "tgn:placetype":[
        "aat:300008347"
    ]
},
  "bbox": [],
  "geometry": {"coordinates":[88.0833,28.9167],"type":"Point"}
}