{
  "id": 2570698,
  "type": "Feature",
  "properties": {
    "tgn:hierarchy":[
        "tgn:2570698",
        "tgn:1000001",
        "tgn:7012149",
        "tgn:2000905",
        "tgn:7007256",
        "tgn:7029392"
    ],
    "tgn:id":2570698,
    "tgn:name":"Pats Hammock",
    "tgn:placetype":[
        "aat:300008791"
    ]
},
  "bbox": [],
  "geometry": {"coordinates":[-89.7833,30.4833],"type":"Point"}
}