{
  "id": 1065726,
  "type": "Feature",
  "properties": {
    "tgn:hierarchy":[
        "tgn:1065726",
        "tgn:7000189",
        "tgn:1000004",
        "tgn:1000105",
        "tgn:7029392"
    ],
    "tgn:id":1065726,
    "tgn:name":"Husainpur",
    "tgn:placetype":[
        "aat:300008347"
    ]
},
  "bbox": [],
  "geometry": {"coordinates":[90.6667,24.4167],"type":"Point"}
}