{
  "id": 2325961,
  "type": "Feature",
  "properties": {
    "tgn:hierarchy":[
        "tgn:2325961",
        "tgn:1000001",
        "tgn:7012149",
        "tgn:2000836",
        "tgn:7007255",
        "tgn:7029392"
    ],
    "tgn:id":2325961,
    "tgn:name":"Fifteenmile Creek",
    "tgn:placetype":[
        "aat:300008706"
    ]
},
  "bbox": [],
  "geometry": {"coordinates":[-83.2333,37.3333],"type":"Point"}
}