<<<<<<< HEAD
{
  "id": 7475390,
  "type": "Feature",
  "properties": {
    "tgn:hierarchy":[
        "tgn:7475390",
        "tgn:7001004",
        "tgn:1000004",
        "tgn:1000141",
        "tgn:7029392"
    ],
    "tgn:id":7475390,
    "tgn:name":"Weizinei",
    "tgn:placetype":[
        "aat:300008347"
    ]
},
  "bbox": [],
  "geometry": {"coordinates":[120.204167,22.909167],"type":"Point"}
}
=======
{"geometry":{"type":"Point","coordinates":[120.204167,22.909167]},"type":"Feature","properties":{"hierarchy":["tgn:7475390","tgn:7001004","tgn:1000004","tgn:1000141","tgn:7029392"],"placetype":["aat:300008347"],"id":7475390,"name:xx":"Weizinei"}}
>>>>>>> 03f74aca74312dbeaf24d7e61306dd6a786dc3d0
