{
  "id": 2639680,
  "type": "Feature",
  "properties": {
    "tgn:hierarchy":[
        "tgn:2639680",
        "tgn:1000001",
        "tgn:7012149",
        "tgn:2001504",
        "tgn:7007709",
        "tgn:7029392"
    ],
    "tgn:id":2639680,
    "tgn:name":"Sam Branch",
    "tgn:placetype":[
        "aat:300008699"
    ]
},
  "bbox": [],
  "geometry": {"coordinates":[-82.6333,35.3333],"type":"Point"}
}