{
  "id": 2035681,
  "type": "Feature",
  "properties": {
    "tgn:hierarchy":[
        "tgn:2035681",
        "tgn:1000001",
        "tgn:7012149",
        "tgn:2000608",
        "tgn:7007253",
        "tgn:7029392"
    ],
    "tgn:id":2035681,
    "tgn:name":"South Amana",
    "tgn:placetype":[
        "aat:300008347"
    ]
},
  "bbox": [],
  "geometry": {"coordinates":[-91.9667,41.7667],"type":"Point"}
}