{
  "id": 2370548,
  "type": "Feature",
  "properties": {
    "tgn:hierarchy":[
        "tgn:2370548",
        "tgn:1000001",
        "tgn:7006451",
        "tgn:7012149",
        "tgn:2000103",
        "tgn:7029392"
    ],
    "tgn:id":2370548,
    "tgn:name":"Hackberry Basin",
    "tgn:placetype":[
        "aat:300386845"
    ]
},
  "bbox": [],
  "geometry": {"coordinates":[-111.6667,34.4333],"type":"Point"}
}