{
  "id": 2348887,
  "type": "Feature",
  "properties": {
    "tgn:hierarchy":[
        "tgn:2348887",
        "tgn:1000001",
        "tgn:7012149",
        "tgn:2002169",
        "tgn:7007919",
        "tgn:7029392"
    ],
    "tgn:id":2348887,
    "tgn:name":"Gibson-Frazier Cave",
    "tgn:placetype":[
        "aat:300008746"
    ]
},
  "bbox": [],
  "geometry": {"coordinates":[-83.2333,36.6333],"type":"Point"}
}