{
  "id": 2648473,
  "type": "Feature",
  "properties": {
    "tgn:hierarchy":[
        "tgn:2648473",
        "tgn:1000001",
        "tgn:7012149",
        "tgn:2001461",
        "tgn:7007568",
        "tgn:7029392"
    ],
    "tgn:id":2648473,
    "tgn:name":"Schuyler Reef",
    "tgn:placetype":[
        "aat:300132348"
    ]
},
  "bbox": [],
  "geometry": {"coordinates":[-73.35,44.4833],"type":"Point"}
}