{
  "id": 7191959,
  "type": "Feature",
  "properties": {
    "tgn:hierarchy":[
        "tgn:7191959",
        "tgn:7000096",
        "tgn:1000003",
        "tgn:7000084",
        "tgn:7029392"
    ],
    "tgn:id":7191959,
    "tgn:name":"Freienwalder Stadtforst",
    "tgn:placetype":[
        "aat:300008863"
    ]
},
  "bbox": [],
  "geometry": {"coordinates":[14.033333,52.766667],"type":"Point"}
}