<<<<<<< HEAD
{
  "id": 2257206,
  "type": "Feature",
  "properties": {
    "tgn:hierarchy":[
        "tgn:2257206",
        "tgn:1000001",
        "tgn:2002107",
        "tgn:7012149",
        "tgn:7007827",
        "tgn:7029392"
    ],
    "tgn:id":2257206,
    "tgn:name":"Corner Spring",
    "tgn:placetype":[
        "aat:300008697"
    ]
},
  "bbox": [],
  "geometry": {"coordinates":[-110.5333,40.5],"type":"Point"}
}
=======
{"geometry":{"type":"Point","coordinates":[-110.533300,40.500000]},"type":"Feature","properties":{"hierarchy":["tgn:2257206","tgn:1000001","tgn:2002107","tgn:7012149","tgn:7007827","tgn:7029392"],"placetype":["aat:300008697"],"id":2257206,"name:xx":"Corner Spring"}}
>>>>>>> 03f74aca74312dbeaf24d7e61306dd6a786dc3d0
