{
  "id": 2482069,
  "type": "Feature",
  "properties": {
    "tgn:hierarchy":[
        "tgn:2482069",
        "tgn:1000001",
        "tgn:7012149",
        "tgn:7007709",
        "tgn:7029392"
    ],
    "tgn:id":2482069,
    "tgn:name":"Lanes Creek",
    "tgn:placetype":[
        "aat:300008706"
    ]
},
  "bbox": [],
  "geometry": {"coordinates":[-80.5167,34.8667],"type":"Point"}
}