<<<<<<< HEAD
{
  "id": 2760197,
  "type": "Feature",
  "properties": {
    "tgn:hierarchy":[
        "tgn:2760197",
        "tgn:1000001",
        "tgn:7012149",
        "tgn:2001709",
        "tgn:7007708",
        "tgn:7029392"
    ],
    "tgn:id":2760197,
    "tgn:name":"West Fork Rattlesnake Creek",
    "tgn:placetype":[
        "aat:300008706"
    ]
},
  "bbox": [],
  "geometry": {"coordinates":[-118.7833,43.7333],"type":"Point"}
}
=======
{"geometry":{"type":"Point","coordinates":[-118.783300,43.733300]},"type":"Feature","properties":{"hierarchy":["tgn:2760197","tgn:1000001","tgn:7012149","tgn:2001709","tgn:7007708","tgn:7029392"],"placetype":["aat:300008706"],"id":2760197,"name:xx":"West Fork Rattlesnake Creek"}}
>>>>>>> 03f74aca74312dbeaf24d7e61306dd6a786dc3d0
