{
  "id": 2306798,
  "type": "Feature",
  "properties": {
    "tgn:hierarchy":[
        "tgn:2306798",
        "tgn:1000001",
        "tgn:7012149",
        "tgn:2002364",
        "tgn:7007922",
        "tgn:7029392"
    ],
    "tgn:id":2306798,
    "tgn:name":"East Fork Hemlock Creek",
    "tgn:placetype":[
        "aat:300008706"
    ]
},
  "bbox": [],
  "geometry": {"coordinates":[-89.9333,44.55],"type":"Point"}
}