{
  "id": 2627448,
  "type": "Feature",
  "properties": {
    "tgn:hierarchy":[
        "tgn:2627448",
        "tgn:1002140",
        "tgn:1000001",
        "tgn:7012149",
        "tgn:7007520",
        "tgn:7029392"
    ],
    "tgn:id":2627448,
    "tgn:name":"Roelofs Gully",
    "tgn:placetype":[
        "aat:300008761"
    ]
},
  "bbox": [],
  "geometry": {"coordinates":[-86.0667,42.6667],"type":"Point"}
}