<<<<<<< HEAD
{
  "id": 7371494,
  "type": "Feature",
  "properties": {
    "tgn:hierarchy":[
        "tgn:7371494",
        "tgn:7005581",
        "tgn:1000001",
        "tgn:7005560",
        "tgn:7029392"
    ],
    "tgn:id":7371494,
    "tgn:name":"Hacienda Las Pampas",
    "tgn:placetype":[
        "aat:300008347"
    ]
},
  "bbox": [],
  "geometry": {"coordinates":[-104.7,27.483333],"type":"Point"}
}
=======
{"geometry":{"type":"Point","coordinates":[-104.700000,27.483333]},"type":"Feature","properties":{"hierarchy":["tgn:7371494","tgn:7005581","tgn:1000001","tgn:7005560","tgn:7029392"],"placetype":["aat:300008347"],"id":7371494,"name:xx":"Hacienda Las Pampas"}}
>>>>>>> 03f74aca74312dbeaf24d7e61306dd6a786dc3d0
