{
  "id": 2514668,
  "type": "Feature",
  "properties": {
    "tgn:hierarchy":[
        "tgn:2514668",
        "tgn:1000001",
        "tgn:2001008",
        "tgn:7012149",
        "tgn:7007521",
        "tgn:7029392"
    ],
    "tgn:id":2514668,
    "tgn:name":"Miller Lake",
    "tgn:placetype":[
        "aat:300008680"
    ]
},
  "bbox": [],
  "geometry": {"coordinates":[-93.7333,44.7833],"type":"Point"}
}