{
  "id": 2719223,
  "type": "Feature",
  "properties": {
    "tgn:hierarchy":[
        "tgn:2719223",
        "tgn:1000001",
        "tgn:7012149",
        "tgn:1003038",
        "tgn:7007517",
        "tgn:7029392"
    ],
    "tgn:id":2719223,
    "tgn:name":"Thousand Acre Swamp",
    "tgn:placetype":[
        "aat:300008905"
    ]
},
  "bbox": [],
  "geometry": {"coordinates":[-72.15,42.5833],"type":"Point"}
}