<<<<<<< HEAD
{
  "id": 7020163,
  "type": "Feature",
  "properties": {
    "tgn:hierarchy":[
        "tgn:7020163",
        "tgn:1000001",
        "tgn:2000769",
        "tgn:7012149",
        "tgn:7007255",
        "tgn:7029392"
    ],
    "tgn:id":7020163,
    "tgn:name":"Old House Branch",
    "tgn:placetype":[
        "aat:300008699"
    ]
},
  "bbox": [],
  "geometry": {"coordinates":[-83.55,36.8833],"type":"Point"}
}
=======
{"geometry":{"type":"Point","coordinates":[-83.550000,36.883300]},"type":"Feature","properties":{"hierarchy":["tgn:7020163","tgn:1000001","tgn:2000769","tgn:7012149","tgn:7007255","tgn:7029392"],"placetype":["aat:300008699"],"id":7020163,"name:xx":"Old House Branch"}}
>>>>>>> 03f74aca74312dbeaf24d7e61306dd6a786dc3d0
