{
  "id": 2100405,
  "type": "Feature",
  "properties": {
    "tgn:hierarchy":[
        "tgn:2100405",
        "tgn:1000001",
        "tgn:7012149",
        "tgn:7015666",
        "tgn:7007825",
        "tgn:7029392"
    ],
    "tgn:id":2100405,
    "tgn:name":"Mill Creek",
    "tgn:placetype":[
        "aat:300008347",
        "aat:300387210"
    ]
},
  "bbox": [],
  "geometry": {"coordinates":[-87.3667,35.8833],"type":"Point"}
}