{
  "id": 7586002,
  "type": "Feature",
  "properties": {
    "tgn:hierarchy":[
        "tgn:7586002",
        "tgn:1000004",
        "tgn:7000198",
        "tgn:7000799",
        "tgn:7029392"
    ],
    "tgn:id":7586002,
    "tgn:name:en":"Ben\u0101w\u0101s",
    "tgn:placetype":[
        "aat:300008347"
    ]
},
  "bbox": [],
  "geometry": {"coordinates":[74.800685,34.323263],"type":"Point"}
}