{
  "id": 2586844,
  "type": "Feature",
  "properties": {
    "tgn:hierarchy":[
        "tgn:2586844",
        "tgn:1000001",
        "tgn:7012149",
        "tgn:2001448",
        "tgn:7007566",
        "tgn:7029392"
    ],
    "tgn:id":2586844,
    "tgn:name":"Plain",
    "tgn:placetype":[
        "aat:300008347"
    ]
},
  "bbox": [],
  "geometry": {"coordinates":[-103.5333,34.8333],"type":"Point"}
}