{
  "id": 2235964,
  "type": "Feature",
  "properties": {
    "tgn:hierarchy":[
        "tgn:2235964",
        "tgn:1000001",
        "tgn:7006451",
        "tgn:2000092",
        "tgn:7012149",
        "tgn:7029392"
    ],
    "tgn:id":2235964,
    "tgn:name":"Chevelon Ridge",
    "tgn:placetype":[
        "aat:300266640"
    ]
},
  "bbox": [],
  "geometry": {"coordinates":[-110.8833,34.3833],"type":"Point"}
}