{
  "id": 7385503,
  "type": "Feature",
  "properties": {
    "tgn:hierarchy":[
        "tgn:7385503",
        "tgn:1000001",
        "tgn:7005599",
        "tgn:7005560",
        "tgn:7029392"
    ],
    "tgn:id":7385503,
    "tgn:name":"Monte Real",
    "tgn:placetype":[
        "aat:300008347"
    ]
},
  "bbox": [],
  "geometry": {"coordinates":[-96.916667,19.733333],"type":"Point"}
}