{
  "id": 7429292,
  "type": "Feature",
  "properties": {
    "tgn:hierarchy":[
        "tgn:7429292",
        "tgn:1000001",
        "tgn:7005595",
        "tgn:7005560",
        "tgn:7029392"
    ],
    "tgn:id":7429292,
    "tgn:name":"Presa Bebelama",
    "tgn:placetype":[
        "aat:300006191"
    ]
},
  "bbox": [],
  "geometry": {"coordinates":[-107.066667,24.216667],"type":"Point"}
}