{
  "id": 2517901,
  "type": "Feature",
  "properties": {
    "tgn:hierarchy":[
        "tgn:2517901",
        "tgn:1000001",
        "tgn:1002724",
        "tgn:7012149",
        "tgn:7007517",
        "tgn:7029392"
    ],
    "tgn:id":2517901,
    "tgn:name":"Miscoe Brook",
    "tgn:placetype":[
        "aat:300008699"
    ]
},
  "bbox": [],
  "geometry": {"coordinates":[-71.4333,42.0167],"type":"Point"}
}