{
  "id": 7301111,
  "type": "Feature",
  "properties": {
    "tgn:hierarchy":[
        "tgn:7301111",
        "tgn:7002760",
        "tgn:1000003",
        "tgn:1000095",
        "tgn:7029392"
    ],
    "tgn:id":7301111,
    "tgn:name":"Montecillo",
    "tgn:placetype":[
        "aat:300008347"
    ]
},
  "bbox": [],
  "geometry": {"coordinates":[-3.966667,42.766667],"type":"Point"}
}