{
  "id": 2028743,
  "type": "Feature",
  "properties": {
    "tgn:hierarchy":[
        "tgn:2028743",
        "tgn:1000001",
        "tgn:7012149",
        "tgn:2000532",
        "tgn:7007251",
        "tgn:7029392"
    ],
    "tgn:id":2028743,
    "tgn:name":"Lena",
    "tgn:placetype":[
        "aat:300008347"
    ]
},
  "bbox": [],
  "geometry": {"coordinates":[-89.8167,42.3667],"type":"Point"}
}