<<<<<<< HEAD
{
  "id": 2761152,
  "type": "Feature",
  "properties": {
    "tgn:hierarchy":[
        "tgn:2761152",
        "tgn:1000001",
        "tgn:7012149",
        "tgn:1002723",
        "tgn:7007252",
        "tgn:7029392"
    ],
    "tgn:id":2761152,
    "tgn:name":"West Lakes",
    "tgn:placetype":[
        "aat:300008680"
    ]
},
  "bbox": [],
  "geometry": {"coordinates":[-85.4,41.4833],"type":"Point"}
}
=======
{"geometry":{"type":"Point","coordinates":[-85.400000,41.483300]},"type":"Feature","properties":{"hierarchy":["tgn:2761152","tgn:1000001","tgn:7012149","tgn:1002723","tgn:7007252","tgn:7029392"],"placetype":["aat:300008680"],"id":2761152,"name:xx":"West Lakes"}}
>>>>>>> 03f74aca74312dbeaf24d7e61306dd6a786dc3d0
