{
  "id": 2291834,
  "type": "Feature",
  "properties": {
    "tgn:hierarchy":[
        "tgn:2291834",
        "tgn:1000001",
        "tgn:7012149",
        "tgn:7029392"
    ],
    "tgn:id":2291834,
    "tgn:name":"Dome Hill",
    "tgn:placetype":[
        "aat:300008798"
    ]
},
  "bbox": [],
  "geometry": {"coordinates":[-119.0833,38.35],"type":"Point"}
}