{
  "id": 7094553,
  "type": "Feature",
  "properties": {
    "tgn:hierarchy":[
        "tgn:7094553",
        "tgn:7000096",
        "tgn:1000003",
        "tgn:7000084",
        "tgn:7029392"
    ],
    "tgn:id":7094553,
    "tgn:name":"See-Berge",
    "tgn:placetype":[
        "aat:300008777"
    ]
},
  "bbox": [],
  "geometry": {"coordinates":[12.85,52.55],"type":"Point"}
}