{
  "id": 7289029,
  "type": "Feature",
  "properties": {
    "tgn:hierarchy":[
        "tgn:7289029",
        "tgn:1001699",
        "tgn:1000049",
        "tgn:1000002",
        "tgn:7029392"
    ],
    "tgn:id":7289029,
    "tgn:name":"La Barra, Bajo",
    "tgn:placetype":[
        "aat:300008808"
    ]
},
  "bbox": [],
  "geometry": {"coordinates":[-73.35,-42.55],"type":"Point"}
}