<<<<<<< HEAD
{
  "id": 2156742,
  "type": "Feature",
  "properties": {
    "tgn:hierarchy":[
        "tgn:2156742",
        "tgn:1000001",
        "tgn:7012149",
        "tgn:2000234",
        "tgn:7007158",
        "tgn:7029392"
    ],
    "tgn:id":2156742,
    "tgn:name":"Beaton Creek",
    "tgn:placetype":[
        "aat:300008706"
    ]
},
  "bbox": [],
  "geometry": {"coordinates":[-107.6333,38.3667],"type":"Point"}
}
=======
{"geometry":{"type":"Point","coordinates":[-107.633300,38.366700]},"type":"Feature","properties":{"hierarchy":["tgn:2156742","tgn:1000001","tgn:7012149","tgn:2000234","tgn:7007158","tgn:7029392"],"placetype":["aat:300008706"],"id":2156742,"name:xx":"Beaton Creek"}}
>>>>>>> 03f74aca74312dbeaf24d7e61306dd6a786dc3d0
