<<<<<<< HEAD
{
  "id": 7485041,
  "type": "Feature",
  "properties": {
    "tgn:hierarchy":[
        "tgn:7485041",
        "tgn:7468018",
        "tgn:1000004",
        "tgn:1000141",
        "tgn:7029392"
    ],
    "tgn:id":7485041,
    "tgn:name":"Abaquan Shan",
    "tgn:placetype":[
        "aat:300008798"
    ]
},
  "bbox": [],
  "geometry": {"coordinates":[120.596667,23.544444],"type":"Point"}
}
=======
{"geometry":{"type":"Point","coordinates":[120.596667,23.544444]},"type":"Feature","properties":{"hierarchy":["tgn:7485041","tgn:7468018","tgn:1000004","tgn:1000141","tgn:7029392"],"placetype":["aat:300008798"],"id":7485041,"name:xx":"Abaquan Shan"}}
>>>>>>> 03f74aca74312dbeaf24d7e61306dd6a786dc3d0
