{
  "id": 7347279,
  "type": "Feature",
  "properties": {
    "tgn:hierarchy":[
        "tgn:7347279",
        "tgn:7007088",
        "tgn:1000003",
        "tgn:7009604",
        "tgn:1000095",
        "tgn:7029392"
    ],
    "tgn:id":7347279,
    "tgn:name":"Art\u00f3ma\u00f1a",
    "tgn:placetype":[
        "aat:300008347"
    ]
},
  "bbox": [],
  "geometry": {"coordinates":[-2.981951,42.983545],"type":"Point"}
}