{
  "id": 2502685,
  "type": "Feature",
  "properties": {
    "tgn:hierarchy":[
        "tgn:2502685",
        "tgn:1000001",
        "tgn:7012149",
        "tgn:2002359",
        "tgn:7007922",
        "tgn:7029392"
    ],
    "tgn:id":2502685,
    "tgn:name":"McLeod Lake",
    "tgn:placetype":[
        "aat:300008680"
    ]
},
  "bbox": [],
  "geometry": {"coordinates":[-89.35,45.9833],"type":"Point"}
}