{
  "id": 1119216,
  "type": "Feature",
  "properties": {
    "tgn:hierarchy":[
        "tgn:1119216",
        "tgn:1000001",
        "tgn:7012149",
        "tgn:7007517",
        "tgn:7029392"
    ],
    "tgn:id":1119216,
    "tgn:name":"Ames Long Pond",
    "tgn:placetype":[
        "aat:300008688"
    ]
},
  "bbox": [],
  "geometry": {"coordinates":[-71.1167,42.0833],"type":"Point"}
}