{
  "id": 7058827,
  "type": "Feature",
  "properties": {
    "tgn:hierarchy":[
        "tgn:7058827",
        "tgn:7007850",
        "tgn:1003491",
        "tgn:1000003",
        "tgn:1000080",
        "tgn:7029392"
    ],
    "tgn:id":7058827,
    "tgn:name":"Allaro, Fiumara",
    "tgn:placetype":[
        "aat:300008699"
    ]
},
  "bbox": [],
  "geometry": {"coordinates":[16.466667,38.35],"type":"Point"}
}