{
  "id": 7544800,
  "type": "Feature",
  "properties": {
    "tgn:hierarchy":[
        "tgn:7544800",
        "tgn:7016678",
        "tgn:7000204",
        "tgn:1000004",
        "tgn:7000198",
        "tgn:7029392"
    ],
    "tgn:id":7544800,
    "tgn:name:en":"Albany, Cape",
    "tgn:placetype":[
        "aat:300008850"
    ]
},
  "bbox": [],
  "geometry": {"coordinates":[93.45,7.883333],"type":"Point"}
}