{
  "id": 2573230,
  "type": "Feature",
  "properties": {
    "tgn:hierarchy":[
        "tgn:2573230",
        "tgn:7014010",
        "tgn:1000001",
        "tgn:1002344",
        "tgn:7012149",
        "tgn:7007517",
        "tgn:7029392"
    ],
    "tgn:id":2573230,
    "tgn:name":"Peases Point",
    "tgn:placetype":[
        "aat:300008850"
    ]
},
  "bbox": [],
  "geometry": {"coordinates":[-70.75,41.3333],"type":"Point"}
}