{
  "id": 2341313,
  "type": "Feature",
  "properties": {
    "tgn:hierarchy":[
        "tgn:2341313",
        "tgn:1000001",
        "tgn:7012149",
        "tgn:2000476",
        "tgn:7007250",
        "tgn:7029392"
    ],
    "tgn:id":2341313,
    "tgn:name":"Fro Creek",
    "tgn:placetype":[
        "aat:300008706"
    ]
},
  "bbox": [],
  "geometry": {"coordinates":[-115.2167,46.45],"type":"Point"}
}