{
  "id": 7493532,
  "type": "Feature",
  "properties": {
    "tgn:hierarchy":[
        "tgn:7493532",
        "tgn:1000004",
        "tgn:7492971",
        "tgn:1000141",
        "tgn:7029392"
    ],
    "tgn:id":7493532,
    "tgn:name":"Nanlu Qiao",
    "tgn:placetype":[
        "aat:300007836"
    ]
},
  "bbox": [],
  "geometry": {"coordinates":[120.606039,22.80892],"type":"Point"}
}