{
  "id": 7173292,
  "type": "Feature",
  "properties": {
    "tgn:hierarchy":[
        "tgn:7173292",
        "tgn:7000096",
        "tgn:1000003",
        "tgn:7000084",
        "tgn:7029392"
    ],
    "tgn:id":7173292,
    "tgn:name":"Gro\u00dfderschau",
    "tgn:placetype":[
        "aat:300008347"
    ]
},
  "bbox": [],
  "geometry": {"coordinates":[12.35,52.783333],"type":"Point"}
}