<<<<<<< HEAD
{
  "id": 2258538,
  "type": "Feature",
  "properties": {
    "tgn:hierarchy":[
        "tgn:2258538",
        "tgn:1000001",
        "tgn:7012149",
        "tgn:2000818",
        "tgn:7007255",
        "tgn:7029392"
    ],
    "tgn:id":2258538,
    "tgn:name":"Cottonpatch Branch",
    "tgn:placetype":[
        "aat:300008699"
    ]
},
  "bbox": [],
  "geometry": {"coordinates":[-84.5667,36.6],"type":"Point"}
}
=======
{"geometry":{"type":"Point","coordinates":[-84.566700,36.600000]},"type":"Feature","properties":{"hierarchy":["tgn:2258538","tgn:1000001","tgn:7012149","tgn:2000818","tgn:7007255","tgn:7029392"],"placetype":["aat:300008699"],"id":2258538,"name:xx":"Cottonpatch Branch"}}
>>>>>>> 03f74aca74312dbeaf24d7e61306dd6a786dc3d0
