{
  "id": 7152154,
  "type": "Feature",
  "properties": {
    "tgn:hierarchy":[
        "tgn:7152154",
        "tgn:1000003",
        "tgn:7003677",
        "tgn:7000084",
        "tgn:7029392"
    ],
    "tgn:id":7152154,
    "tgn:name":"K\u00e4fringhausen",
    "tgn:placetype":[
        "aat:300008347"
    ]
},
  "bbox": [],
  "geometry": {"coordinates":[7.216667,51.083333],"type":"Point"}
}