{
  "id": 7061553,
  "type": "Feature",
  "properties": {
    "tgn:hierarchy":[
        "tgn:7061553",
        "tgn:1000003",
        "tgn:7003677",
        "tgn:7000084",
        "tgn:7029392"
    ],
    "tgn:id":7061553,
    "tgn:name":"Auf dem Schnee",
    "tgn:placetype":[
        "aat:300008347"
    ]
},
  "bbox": [],
  "geometry": {"coordinates":[7.416667,51.433333],"type":"Point"}
}