{
  "id": 7324135,
  "type": "Feature",
  "properties": {
    "tgn:hierarchy":[
        "tgn:7324135",
        "tgn:7001122",
        "tgn:1000003",
        "tgn:7002765",
        "tgn:1000095",
        "tgn:7029392"
    ],
    "tgn:id":7324135,
    "tgn:name":"San Jos\u00e9",
    "tgn:placetype":[
        "aat:300008347"
    ]
},
  "bbox": [],
  "geometry": {"coordinates":[1.283333,38.916667],"type":"Point"}
}