{
  "id": 7263079,
  "type": "Feature",
  "properties": {
    "tgn:hierarchy":[
        "tgn:7263079",
        "tgn:7003619",
        "tgn:1000003",
        "tgn:7016845",
        "tgn:7029392"
    ],
    "tgn:id":7263079,
    "tgn:name:nl":"De Bruuk",
    "tgn:placetype":[
        "aat:300008178"
    ]
},
  "bbox": [],
  "geometry": {"coordinates":[5.966667,51.766667],"type":"Point"}
}