{
  "id": 2572020,
  "type": "Feature",
  "properties": {
    "tgn:hierarchy":[
        "tgn:2572020",
        "tgn:7002659",
        "tgn:1000001",
        "tgn:7012149",
        "tgn:2000063",
        "tgn:7029392"
    ],
    "tgn:id":2572020,
    "tgn:name":"Paynes Creek",
    "tgn:placetype":[
        "aat:300008706"
    ]
},
  "bbox": [],
  "geometry": {"coordinates":[-87.1833,33.6667],"type":"Point"}
}