{
  "id": 1006826,
  "type": "Feature",
  "properties": {
    "tgn:hierarchy":[
        "tgn:1006826",
        "tgn:1002366",
        "tgn:1000001",
        "tgn:7012149",
        "tgn:1010185",
        "tgn:7007159",
        "tgn:7029392"
    ],
    "tgn:id":1006826,
    "tgn:name":"Cockenoe Island",
    "tgn:placetype":[
        "aat:300008791"
    ]
},
  "bbox": [],
  "geometry": {"coordinates":[-73.35,41.0833],"type":"Point"}
}