{
  "id": 2660001,
  "type": "Feature",
  "properties": {
    "tgn:hierarchy":[
        "tgn:2660001",
        "tgn:1000001",
        "tgn:1002257",
        "tgn:7012149",
        "tgn:7007919",
        "tgn:7029392"
    ],
    "tgn:id":2660001,
    "tgn:name":"Shirley",
    "tgn:placetype":[
        "aat:300008347"
    ]
},
  "bbox": [],
  "geometry": {"coordinates":[-77.25,37.3333],"type":"Point"}
}