{
  "id": 7450971,
  "type": "Feature",
  "properties": {
    "tgn:hierarchy":[
        "tgn:7450971",
        "tgn:7002444",
        "tgn:1000003",
        "tgn:7008094",
        "tgn:7008591",
        "tgn:7029392"
    ],
    "tgn:id":7450971,
    "tgn:name:en":"Gress Lodge",
    "tgn:placetype":[
        "aat:300004792"
    ]
},
  "bbox": [],
  "geometry": {"coordinates":[-6.266667,58.283333],"type":"Point"}
}