{
  "id": 7066840,
  "type": "Feature",
  "properties": {
    "tgn:hierarchy":[
        "tgn:7066840",
        "tgn:7003669",
        "tgn:1000003",
        "tgn:7000084",
        "tgn:7029392"
    ],
    "tgn:id":7066840,
    "tgn:name":"Stinkerbrunn",
    "tgn:placetype":[
        "aat:300008697"
    ]
},
  "bbox": [],
  "geometry": {"coordinates":[11.916667,48.95],"type":"Point"}
}