{
  "id": 2463121,
  "type": "Feature",
  "properties": {
    "tgn:hierarchy":[
        "tgn:2463121",
        "tgn:1000001",
        "tgn:7012149",
        "tgn:7007158",
        "tgn:2000242",
        "tgn:7029392"
    ],
    "tgn:id":2463121,
    "tgn:name":"Livesey Gulch",
    "tgn:placetype":[
        "aat:300008761"
    ]
},
  "bbox": [],
  "geometry": {"coordinates":[-105.0167,38.15],"type":"Point"}
}