{
  "id": 2434095,
  "type": "Feature",
  "properties": {
    "tgn:hierarchy":[
        "tgn:2434095",
        "tgn:1000001",
        "tgn:7012149",
        "tgn:2000226",
        "tgn:7007158",
        "tgn:7029392"
    ],
    "tgn:id":2434095,
    "tgn:name":"Kelsey Lake",
    "tgn:placetype":[
        "aat:300006191"
    ]
},
  "bbox": [],
  "geometry": {"coordinates":[-105.4833,40.9833],"type":"Point"}
}