{
  "id": 1014613,
  "type": "Feature",
  "properties": {
    "tgn:hierarchy":[
        "tgn:1014613",
        "tgn:7005685",
        "tgn:1000001",
        "tgn:7013154",
        "tgn:7029392"
    ],
    "tgn:id":1014613,
    "tgn:name":"Bridgenorth",
    "tgn:placetype":[
        "aat:300008347"
    ]
},
  "bbox": [],
  "geometry": {"coordinates":[-78.3833,44.3833],"type":"Point"}
}