{
  "id": 2469400,
  "type": "Feature",
  "properties": {
    "tgn:hierarchy":[
        "tgn:2469400",
        "tgn:1002238",
        "tgn:1000001",
        "tgn:7012149",
        "tgn:7007516",
        "tgn:7029392"
    ],
    "tgn:id":2469400,
    "tgn:name":"Longwell Run",
    "tgn:placetype":[
        "aat:300008699"
    ]
},
  "bbox": [],
  "geometry": {"coordinates":[-76.9833,39.5667],"type":"Point"}
}