{
  "id": 2786460,
  "type": "Feature",
  "properties": {
    "tgn:hierarchy":[
        "tgn:2786460",
        "tgn:1000001",
        "tgn:7006451",
        "tgn:7012149",
        "tgn:2000098",
        "tgn:7029392"
    ],
    "tgn:id":2786460,
    "tgn:name":"Yucca Ford Automotive Proving Grounds",
    "tgn:placetype":[
        "aat:300055621"
    ]
},
  "bbox": [],
  "geometry": {"coordinates":[-114.1167,34.8667],"type":"Point"}
}