{
  "id": 2756120,
  "type": "Feature",
  "properties": {
    "tgn:hierarchy":[
        "tgn:2756120",
        "tgn:7002659",
        "tgn:1000001",
        "tgn:2000009",
        "tgn:7012149",
        "tgn:7029392"
    ],
    "tgn:id":2756120,
    "tgn:name":"Weisner, Lake",
    "tgn:placetype":[
        "aat:300006191"
    ]
},
  "bbox": [],
  "geometry": {"coordinates":[-85.6667,34.0667],"type":"Point"}
}