{
  "id": 7201232,
  "type": "Feature",
  "properties": {
    "tgn:hierarchy":[
        "tgn:7201232",
        "tgn:1000003",
        "tgn:7003677",
        "tgn:7000084",
        "tgn:7029392"
    ],
    "tgn:id":7201232,
    "tgn:name":"Brandige Kopp",
    "tgn:placetype":[
        "aat:300008777"
    ]
},
  "bbox": [],
  "geometry": {"coordinates":[7.916667,51.25],"type":"Point"}
}