{
  "id": 7316085,
  "type": "Feature",
  "properties": {
    "tgn:hierarchy":[
        "tgn:7316085",
        "tgn:1001692",
        "tgn:1000049",
        "tgn:1000002",
        "tgn:7029392"
    ],
    "tgn:id":7316085,
    "tgn:name":"Casas de Guallal\u00ed",
    "tgn:placetype":[
        "aat:300008347"
    ]
},
  "bbox": [],
  "geometry": {"coordinates":[-71.316667,-38.05],"type":"Point"}
}