{
  "id": 2238475,
  "type": "Feature",
  "properties": {
    "tgn:hierarchy":[
        "tgn:2238475",
        "tgn:7006450",
        "tgn:1000001",
        "tgn:7012149",
        "tgn:2000086",
        "tgn:7029392"
    ],
    "tgn:id":2238475,
    "tgn:name":"Chokosna River",
    "tgn:placetype":[
        "aat:300008707"
    ]
},
  "bbox": [],
  "geometry": {"coordinates":[-143.4833,61.5333],"type":"Point"}
}