{
  "id": 1079165,
  "type": "Feature",
  "properties": {
    "tgn:hierarchy":[
        "tgn:1079165",
        "tgn:1000004",
        "tgn:7029810",
        "tgn:7000231",
        "tgn:7029392"
    ],
    "tgn:id":1079165,
    "tgn:name":"Kord K\u016by",
    "tgn:placetype":[
        "aat:300008347"
    ]
},
  "bbox": [],
  "geometry": {"coordinates":[54.1167,36.7833],"type":"Point"}
}