{
  "id": 7086749,
  "type": "Feature",
  "properties": {
    "tgn:hierarchy":[
        "tgn:7086749",
        "tgn:1000003",
        "tgn:7003685",
        "tgn:7000084",
        "tgn:7029392"
    ],
    "tgn:id":7086749,
    "tgn:name":"Waldhof",
    "tgn:placetype":[
        "aat:300008347"
    ]
},
  "bbox": [],
  "geometry": {"coordinates":[14.05,51.366667],"type":"Point"}
}