{
  "id": 2611642,
  "type": "Feature",
  "properties": {
    "tgn:hierarchy":[
        "tgn:2611642",
        "tgn:1000001",
        "tgn:7012149",
        "tgn:2002384",
        "tgn:7007923",
        "tgn:7029392"
    ],
    "tgn:id":2611642,
    "tgn:name":"Red Mountain",
    "tgn:placetype":[
        "aat:300008798"
    ]
},
  "bbox": [],
  "geometry": {"coordinates":[-110.8667,43.9667],"type":"Point"}
}