{
  "id": 2591752,
  "type": "Feature",
  "properties": {
    "tgn:hierarchy":[
        "tgn:2591752",
        "tgn:1000001",
        "tgn:7012149",
        "tgn:2001226",
        "tgn:7007523",
        "tgn:7029392"
    ],
    "tgn:id":2591752,
    "tgn:name":"Pond Fork",
    "tgn:placetype":[
        "aat:300008699"
    ]
},
  "bbox": [],
  "geometry": {"coordinates":[-92.75,36.7333],"type":"Point"}
}