{
  "id": 7018568,
  "type": "Feature",
  "properties": {
    "tgn:hierarchy":[
        "tgn:7018568",
        "tgn:7005558",
        "tgn:1000001",
        "tgn:7005556",
        "tgn:7029392"
    ],
    "tgn:id":7018568,
    "tgn:name":"Saint Ann",
    "tgn:placetype":[
        "aat:300387064",
        "aat:300387092"
    ]
},
  "bbox": [],
  "geometry": {"coordinates":[-77.266,18.35],"type":"Point"}
}