<<<<<<< HEAD
{
  "id": 2159825,
  "type": "Feature",
  "properties": {
    "tgn:hierarchy":[
        "tgn:2159825",
        "tgn:1000001",
        "tgn:2001260",
        "tgn:7012149",
        "tgn:7007524",
        "tgn:7029392"
    ],
    "tgn:id":2159825,
    "tgn:name":"Beech Creek",
    "tgn:placetype":[
        "aat:300008706"
    ]
},
  "bbox": [],
  "geometry": {"coordinates":[-112.5,44.9333],"type":"Point"}
}
=======
{"geometry":{"type":"Point","coordinates":[-112.500000,44.933300]},"type":"Feature","properties":{"hierarchy":["tgn:2159825","tgn:1000001","tgn:2001260","tgn:7012149","tgn:7007524","tgn:7029392"],"placetype":["aat:300008706"],"id":2159825,"name:xx":"Beech Creek"}}
>>>>>>> 03f74aca74312dbeaf24d7e61306dd6a786dc3d0
