{
  "id": 2609020,
  "type": "Feature",
  "properties": {
    "tgn:hierarchy":[
        "tgn:2609020",
        "tgn:1000001",
        "tgn:7012149",
        "tgn:2001029",
        "tgn:7007521",
        "tgn:7029392"
    ],
    "tgn:id":2609020,
    "tgn:name":"Raven Lake",
    "tgn:placetype":[
        "aat:300008680"
    ]
},
  "bbox": [],
  "geometry": {"coordinates":[-94.3167,47.4667],"type":"Point"}
}