{
  "id": 2649461,
  "type": "Feature",
  "properties": {
    "tgn:hierarchy":[
        "tgn:2649461",
        "tgn:1000001",
        "tgn:1003037",
        "tgn:7012149",
        "tgn:7007516",
        "tgn:7029392"
    ],
    "tgn:id":2649461,
    "tgn:name":"Scotts Point",
    "tgn:placetype":[
        "aat:300008850"
    ]
},
  "bbox": [],
  "geometry": {"coordinates":[-75.2167,38.0833],"type":"Point"}
}