<<<<<<< HEAD
{
  "id": 2336714,
  "type": "Feature",
  "properties": {
    "tgn:hierarchy":[
        "tgn:2336714",
        "tgn:1000001",
        "tgn:7012149",
        "tgn:2001711",
        "tgn:7007708",
        "tgn:7029392"
    ],
    "tgn:id":2336714,
    "tgn:name":"Fourbit Ford",
    "tgn:placetype":[
        "aat:300008347"
    ]
},
  "bbox": [],
  "geometry": {"coordinates":[-122.4,42.5],"type":"Point"}
}
=======
{"geometry":{"type":"Point","coordinates":[-122.400000,42.500000]},"type":"Feature","properties":{"hierarchy":["tgn:2336714","tgn:1000001","tgn:7012149","tgn:2001711","tgn:7007708","tgn:7029392"],"placetype":["aat:300008347"],"id":2336714,"name:xx":"Fourbit Ford"}}
>>>>>>> 03f74aca74312dbeaf24d7e61306dd6a786dc3d0
