{
  "id": 2133379,
  "type": "Feature",
  "properties": {
    "tgn:hierarchy":[
        "tgn:2133379",
        "tgn:1000001",
        "tgn:7012149",
        "tgn:7007825",
        "tgn:7029392"
    ],
    "tgn:id":2133379,
    "tgn:name":"Anderson Spring Branch",
    "tgn:placetype":[
        "aat:300008699"
    ]
},
  "bbox": [],
  "geometry": {"coordinates":[-84.9667,35.3167],"type":"Point"}
}