{
  "id": 2502349,
  "type": "Feature",
  "properties": {
    "tgn:hierarchy":[
        "tgn:2502349",
        "tgn:1000001",
        "tgn:7012149",
        "tgn:2001873",
        "tgn:7007825",
        "tgn:7029392"
    ],
    "tgn:id":2502349,
    "tgn:name":"McKinneys Islands",
    "tgn:placetype":[
        "aat:300386853"
    ]
},
  "bbox": [],
  "geometry": {"coordinates":[-82.9667,36.3667],"type":"Point"}
}