{
  "id": 2544808,
  "type": "Feature",
  "properties": {
    "tgn:hierarchy":[
        "tgn:2544808",
        "tgn:1000001",
        "tgn:7012149",
        "tgn:2000230",
        "tgn:7007158",
        "tgn:7029392"
    ],
    "tgn:id":2544808,
    "tgn:name":"North Cottonwood Canyon",
    "tgn:placetype":[
        "aat:300008761"
    ]
},
  "bbox": [],
  "geometry": {"coordinates":[-109.0167,38.5667],"type":"Point"}
}