<<<<<<< HEAD
{
  "id": 2705507,
  "type": "Feature",
  "properties": {
    "tgn:hierarchy":[
        "tgn:2705507",
        "tgn:7019618",
        "tgn:1000001",
        "tgn:7012149",
        "tgn:7007564",
        "tgn:7029392"
    ],
    "tgn:id":2705507,
    "tgn:name":"Surry Mountain",
    "tgn:placetype":[
        "aat:300008798"
    ]
},
  "bbox": [],
  "geometry": {"coordinates":[-72.3,43.0333],"type":"Point"}
}
=======
{"geometry":{"type":"Point","coordinates":[-72.300000,43.033300]},"type":"Feature","properties":{"hierarchy":["tgn:2705507","tgn:7019618","tgn:1000001","tgn:7012149","tgn:7007564","tgn:7029392"],"placetype":["aat:300008798"],"id":2705507,"name:xx":"Surry Mountain"}}
>>>>>>> 03f74aca74312dbeaf24d7e61306dd6a786dc3d0
