{
  "id": 7427689,
  "type": "Feature",
  "properties": {
    "tgn:hierarchy":[
        "tgn:7427689",
        "tgn:1000001",
        "tgn:7005594",
        "tgn:7005560",
        "tgn:7029392"
    ],
    "tgn:id":7427689,
    "tgn:name":"El Cercado",
    "tgn:placetype":[
        "aat:300008347"
    ]
},
  "bbox": [],
  "geometry": {"coordinates":[-101.933333,23.383333],"type":"Point"}
}