{
  "id": 2304911,
  "type": "Feature",
  "properties": {
    "tgn:hierarchy":[
        "tgn:2304911",
        "tgn:1000001",
        "tgn:7012149",
        "tgn:7007522",
        "tgn:7029392"
    ],
    "tgn:id":2304911,
    "tgn:name":"East Branch Deer Creek",
    "tgn:placetype":[
        "aat:300008706"
    ]
},
  "bbox": [],
  "geometry": {"coordinates":[-91.0333,33.5833],"type":"Point"}
}