{
  "id": 2143433,
  "type": "Feature",
  "properties": {
    "tgn:hierarchy":[
        "tgn:2143433",
        "tgn:2002308",
        "tgn:1000001",
        "tgn:7012149",
        "tgn:7007922",
        "tgn:7029392"
    ],
    "tgn:id":2143433,
    "tgn:name":"Bailey Lake",
    "tgn:placetype":[
        "aat:300008680"
    ]
},
  "bbox": [],
  "geometry": {"coordinates":[-91.3333,46.6167],"type":"Point"}
}