{
  "id": 7556742,
  "type": "Feature",
  "properties": {
    "tgn:hierarchy":[
        "tgn:7556742",
        "tgn:1000004",
        "tgn:7000198",
        "tgn:1001894",
        "tgn:7029392"
    ],
    "tgn:id":7556742,
    "tgn:name:en":"Rambhapur",
    "tgn:placetype":[
        "aat:300008347"
    ]
},
  "bbox": [],
  "geometry": {"coordinates":[74.490524,22.914955],"type":"Point"}
}