{
  "id": 7008791,
  "type": "Feature",
  "properties": {
    "tgn:hierarchy":[
        "tgn:7008791",
        "tgn:1000003",
        "tgn:1000070",
        "tgn:7002895",
        "tgn:7029392"
    ],
    "tgn:id":7008791,
    "tgn:name":"Fr\u00e9jus",
    "tgn:placetype":[
        "aat:300008347",
        "aat:300000810",
        "aat:300387275",
        "aat:300008375",
        "aat:300387302",
        "aat:300387291"
    ]
},
  "bbox": [],
  "geometry": {"coordinates":[6.7333,43.4333],"type":"Point"}
}