{
  "id": 7543724,
  "type": "Feature",
  "properties": {
    "tgn:hierarchy":[
        "tgn:7543724",
        "tgn:7001242",
        "tgn:7016833",
        "tgn:1001079",
        "tgn:7029392"
    ],
    "tgn:id":7543724,
    "tgn:name:en":"Az\u0327 Z\u0327\u0101fir",
    "tgn:placetype":[
        "aat:300008347"
    ]
},
  "bbox": [],
  "geometry": {"coordinates":[29.893604,30.906458],"type":"Point"}
}