{
  "id": 7320644,
  "type": "Feature",
  "properties": {
    "tgn:hierarchy":[
        "tgn:7320644",
        "tgn:1001768",
        "tgn:1000049",
        "tgn:1000002",
        "tgn:7029392"
    ],
    "tgn:id":7320644,
    "tgn:name":"Blanco, Morro",
    "tgn:placetype":[
        "aat:300008777"
    ]
},
  "bbox": [],
  "geometry": {"coordinates":[-71.333333,-32.683333],"type":"Point"}
}