{
  "id": 2198909,
  "type": "Feature",
  "properties": {
    "tgn:hierarchy":[
        "tgn:2198909",
        "tgn:1000001",
        "tgn:7012149",
        "tgn:2000787",
        "tgn:7007255",
        "tgn:7029392"
    ],
    "tgn:id":2198909,
    "tgn:name":"Bruce Hollow",
    "tgn:placetype":[
        "aat:300008761"
    ]
},
  "bbox": [],
  "geometry": {"coordinates":[-86.0833,37.1667],"type":"Point"}
}