{
  "id": 2054004,
  "type": "Feature",
  "properties": {
    "tgn:hierarchy":[
        "tgn:2054004",
        "tgn:1000001",
        "tgn:2001023",
        "tgn:7012149",
        "tgn:7007521",
        "tgn:7029392"
    ],
    "tgn:id":2054004,
    "tgn:name":"Bombay",
    "tgn:placetype":[
        "aat:300008347",
        "aat:300387210"
    ]
},
  "bbox": [],
  "geometry": {"coordinates":[-92.8833,44.2833],"type":"Point"}
}