{
  "id": 7577576,
  "type": "Feature",
  "properties": {
    "tgn:hierarchy":[
        "tgn:7577576",
        "tgn:1000004",
        "tgn:7000198",
        "tgn:1001905",
        "tgn:7029392"
    ],
    "tgn:id":7577576,
    "tgn:name:en":"L\u014dngsa",
    "tgn:placetype":[
        "aat:300008347"
    ]
},
  "bbox": [],
  "geometry": {"coordinates":[94.549938,26.220892],"type":"Point"}
}