{
  "id": 7417084,
  "type": "Feature",
  "properties": {
    "tgn:hierarchy":[
        "tgn:7417084",
        "tgn:1000001",
        "tgn:7005591",
        "tgn:7005560",
        "tgn:7029392"
    ],
    "tgn:id":7417084,
    "tgn:name:es":"El Cedral",
    "tgn:placetype":[
        "aat:300008347"
    ]
},
  "bbox": [],
  "geometry": {"coordinates":[-96.069444,18.021111],"type":"Point"}
}