{
  "id": 2493058,
  "type": "Feature",
  "properties": {
    "tgn:hierarchy":[
        "tgn:2493058",
        "tgn:1000001",
        "tgn:1002310",
        "tgn:7012149",
        "tgn:7007710",
        "tgn:7029392"
    ],
    "tgn:id":2493058,
    "tgn:name":"Marl Cave",
    "tgn:placetype":[
        "aat:300008746"
    ]
},
  "bbox": [],
  "geometry": {"coordinates":[-77.1333,40.2333],"type":"Point"}
}