{
  "id": 7267527,
  "type": "Feature",
  "properties": {
    "tgn:concordances":{
        "gn:id":"2748187"
    },
    "tgn:hierarchy":[
        "tgn:7267527",
        "tgn:1000003",
        "tgn:7003626",
        "tgn:7016845",
        "tgn:7029392"
    ],
    "tgn:id":7267527,
    "tgn:name:nl":"Rheezerveen",
    "tgn:placetype":[
        "aat:300008347"
    ]
},
  "bbox": [],
  "geometry": {"coordinates":[6.533333,52.566667],"type":"Point"}
}