{
  "id": 2425183,
  "type": "Feature",
  "properties": {
    "tgn:hierarchy":[
        "tgn:2425183",
        "tgn:1000001",
        "tgn:7012149",
        "tgn:2001714",
        "tgn:7007708",
        "tgn:7029392"
    ],
    "tgn:id":2425183,
    "tgn:name":"Johnson Meadow",
    "tgn:placetype":[
        "aat:300008905"
    ]
},
  "bbox": [],
  "geometry": {"coordinates":[-121.5833,43.25],"type":"Point"}
}