{
  "id": 2256754,
  "type": "Feature",
  "properties": {
    "tgn:hierarchy":[
        "tgn:2256754",
        "tgn:1000001",
        "tgn:7012149",
        "tgn:2001451",
        "tgn:7007566",
        "tgn:7029392"
    ],
    "tgn:id":2256754,
    "tgn:name":"Corena Lode",
    "tgn:placetype":[
        "aat:300000390"
    ]
},
  "bbox": [],
  "geometry": {"coordinates":[-106.4667,35.7333],"type":"Point"}
}