<<<<<<< HEAD
{
  "id": 2256754,
  "type": "Feature",
  "properties": {
    "tgn:hierarchy":[
        "tgn:2256754",
        "tgn:1000001",
        "tgn:7012149",
        "tgn:2001451",
        "tgn:7007566",
        "tgn:7029392"
    ],
    "tgn:id":2256754,
    "tgn:name":"Corena Lode",
    "tgn:placetype":[
        "aat:300000390"
    ]
},
  "bbox": [],
  "geometry": {"coordinates":[-106.4667,35.7333],"type":"Point"}
}
=======
{"geometry":{"type":"Point","coordinates":[-106.466700,35.733300]},"type":"Feature","properties":{"hierarchy":["tgn:2256754","tgn:1000001","tgn:7012149","tgn:2001451","tgn:7007566","tgn:7029392"],"placetype":["aat:300000390"],"id":2256754,"name:xx":"Corena Lode"}}
>>>>>>> 03f74aca74312dbeaf24d7e61306dd6a786dc3d0
