{
  "id": 7296997,
  "type": "Feature",
  "properties": {
    "tgn:hierarchy":[
        "tgn:7296997",
        "tgn:7002759",
        "tgn:7002845",
        "tgn:1000003",
        "tgn:1000095",
        "tgn:7029392"
    ],
    "tgn:id":7296997,
    "tgn:name":"Torralba de Ribota",
    "tgn:placetype":[
        "aat:300008347"
    ]
},
  "bbox": [],
  "geometry": {"coordinates":[-1.683333,41.416667],"type":"Point"}
}