{
  "id": 7053681,
  "type": "Feature",
  "properties": {
    "tgn:hierarchy":[
        "tgn:7053681",
        "tgn:7003154",
        "tgn:1000003",
        "tgn:7003120",
        "tgn:1000080",
        "tgn:7029392"
    ],
    "tgn:id":7053681,
    "tgn:name":"Madonna della Losa",
    "tgn:placetype":[
        "aat:300008347"
    ]
},
  "bbox": [],
  "geometry": {"coordinates":[7.033333,45.116667],"type":"Point"}
}