<<<<<<< HEAD
{
  "id": 7022357,
  "type": "Feature",
  "properties": {
    "tgn:hierarchy":[
        "tgn:7022357",
        "tgn:1000001",
        "tgn:7012149",
        "tgn:7029392"
    ],
    "tgn:id":7022357,
    "tgn:name":"Beaver Dam Mountains",
    "tgn:placetype":[
        "aat:300386831"
    ]
},
  "bbox": [],
  "geometry": {"coordinates":[-113.8167,36.95],"type":"Point"}
}
=======
{"geometry":{"type":"Point","coordinates":[-113.816700,36.950000]},"type":"Feature","properties":{"hierarchy":["tgn:7022357","tgn:1000001","tgn:7012149","tgn:7029392"],"placetype":["aat:300386831"],"id":7022357,"name:xx":"Beaver Dam Mountains"}}
>>>>>>> 03f74aca74312dbeaf24d7e61306dd6a786dc3d0
