{
  "id": 7354929,
  "type": "Feature",
  "properties": {
    "tgn:hierarchy":[
        "tgn:7354929",
        "tgn:1000001",
        "tgn:7005590",
        "tgn:7005560",
        "tgn:7029392"
    ],
    "tgn:id":7354929,
    "tgn:name":"Cayacal, Isla",
    "tgn:placetype":[
        "aat:300008791"
    ]
},
  "bbox": [],
  "geometry": {"coordinates":[-102.183333,17.966667],"type":"Point"}
}