{
  "id": 1045466,
  "type": "Feature",
  "properties": {
    "tgn:hierarchy":[
        "tgn:1045466",
        "tgn:7003167",
        "tgn:1000003",
        "tgn:7009760",
        "tgn:1000080",
        "tgn:7029392"
    ],
    "tgn:id":1045466,
    "tgn:name":"Montale",
    "tgn:placetype":[
        "aat:300008347"
    ]
},
  "bbox": [],
  "geometry": {"coordinates":[11.016667,43.933333],"type":"Point"}
}