{
  "id": 7577534,
  "type": "Feature",
  "properties": {
    "tgn:hierarchy":[
        "tgn:7577534",
        "tgn:1000004",
        "tgn:7000198",
        "tgn:7016788",
        "tgn:7029392"
    ],
    "tgn:id":7577534,
    "tgn:name:en":"Kudsu",
    "tgn:placetype":[
        "aat:300008347"
    ]
},
  "bbox": [],
  "geometry": {"coordinates":[73.345504,27.550586],"type":"Point"}
}