{
  "id": 2268299,
  "type": "Feature",
  "properties": {
    "tgn:hierarchy":[
        "tgn:2268299",
        "tgn:2001002",
        "tgn:1000001",
        "tgn:7012149",
        "tgn:7007521",
        "tgn:7029392"
    ],
    "tgn:id":2268299,
    "tgn:name":"Crooked Lake",
    "tgn:placetype":[
        "aat:300008680"
    ]
},
  "bbox": [],
  "geometry": {"coordinates":[-95.1667,47.8333],"type":"Point"}
}