{
  "id": 7340269,
  "type": "Feature",
  "properties": {
    "tgn:hierarchy":[
        "tgn:7340269",
        "tgn:7002831",
        "tgn:1000003",
        "tgn:7002786",
        "tgn:1000095",
        "tgn:7029392"
    ],
    "tgn:id":7340269,
    "tgn:name":"Collas, Arroyo de",
    "tgn:placetype":[
        "aat:300008699"
    ]
},
  "bbox": [],
  "geometry": {"coordinates":[-7.433333,42.033333],"type":"Point"}
}