{
  "id": 2522564,
  "type": "Feature",
  "properties": {
    "tgn:hierarchy":[
        "tgn:2522564",
        "tgn:1000001",
        "tgn:7006451",
        "tgn:7012149",
        "tgn:2000098",
        "tgn:7029392"
    ],
    "tgn:id":2522564,
    "tgn:name":"Moonshine Ridge",
    "tgn:placetype":[
        "aat:300266640"
    ]
},
  "bbox": [],
  "geometry": {"coordinates":[-112.8333,36.7833],"type":"Point"}
}