{
  "id": 2561318,
  "type": "Feature",
  "properties": {
    "tgn:hierarchy":[
        "tgn:2561318",
        "tgn:2000195",
        "tgn:1000001",
        "tgn:7012149",
        "tgn:7007158",
        "tgn:7029392"
    ],
    "tgn:id":2561318,
    "tgn:name":"Osborn Reservoir Number 2",
    "tgn:placetype":[
        "aat:300006191"
    ]
},
  "bbox": [],
  "geometry": {"coordinates":[-107.1833,37.2833],"type":"Point"}
}