{
  "id": 2180309,
  "type": "Feature",
  "properties": {
    "tgn:hierarchy":[
        "tgn:2180309",
        "tgn:1000001",
        "tgn:7012149",
        "tgn:2001488",
        "tgn:7007709",
        "tgn:7029392"
    ],
    "tgn:id":2180309,
    "tgn:name":"Blockade Shoal",
    "tgn:placetype":[
        "aat:300132348"
    ]
},
  "bbox": [],
  "geometry": {"coordinates":[-75.7167,35.9167],"type":"Point"}
}