{
  "id": 2568777,
  "type": "Feature",
  "properties": {
    "tgn:hierarchy":[
        "tgn:2568777",
        "tgn:1000001",
        "tgn:7012149",
        "tgn:2001713",
        "tgn:7007708",
        "tgn:7029392"
    ],
    "tgn:id":2568777,
    "tgn:name":"Parker Creek",
    "tgn:placetype":[
        "aat:300008706"
    ]
},
  "bbox": [],
  "geometry": {"coordinates":[-123.7333,42.1167],"type":"Point"}
}