{
  "id": 7255488,
  "type": "Feature",
  "properties": {
    "tgn:hierarchy":[
        "tgn:7255488",
        "tgn:7003457",
        "tgn:1000003",
        "tgn:1000063",
        "tgn:7018236",
        "tgn:7029392"
    ],
    "tgn:id":7255488,
    "tgn:name":"Rooigem",
    "tgn:placetype":[
        "aat:300008347"
    ]
},
  "bbox": [],
  "geometry": {"coordinates":[3.668227,50.839127],"type":"Point"}
}