{
  "id": 2357751,
  "type": "Feature",
  "properties": {
    "tgn:hierarchy":[
        "tgn:2357751",
        "tgn:1000001",
        "tgn:1002260",
        "tgn:7012149",
        "tgn:7007920",
        "tgn:7029392"
    ],
    "tgn:id":2357751,
    "tgn:name":"Grace, Lake",
    "tgn:placetype":[
        "aat:300008680"
    ]
},
  "bbox": [],
  "geometry": {"coordinates":[-120.9333,47.6833],"type":"Point"}
}