{
  "id": 7383014,
  "type": "Feature",
  "properties": {
    "tgn:hierarchy":[
        "tgn:7383014",
        "tgn:1001853",
        "tgn:1000001",
        "tgn:7005560",
        "tgn:7029392"
    ],
    "tgn:id":7383014,
    "tgn:name":"Organo, Ca\u00f1\u00f3n del",
    "tgn:placetype":[
        "aat:300008763"
    ]
},
  "bbox": [],
  "geometry": {"coordinates":[-101.466667,25.183333],"type":"Point"}
}