{
  "id": 7558062,
  "type": "Feature",
  "properties": {
    "tgn:hierarchy":[
        "tgn:7558062",
        "tgn:7001819",
        "tgn:1000004",
        "tgn:7000198",
        "tgn:7029392"
    ],
    "tgn:id":7558062,
    "tgn:name:en":"Puchep",
    "tgn:placetype":[
        "aat:300008347"
    ]
},
  "bbox": [],
  "geometry": {"coordinates":[95.847075,27.227087],"type":"Point"}
}