{
  "id": 7529813,
  "type": "Feature",
  "properties": {
    "tgn:hierarchy":[
        "tgn:7529813",
        "tgn:7001242",
        "tgn:7016833",
        "tgn:1001091",
        "tgn:7029392"
    ],
    "tgn:id":7529813,
    "tgn:name":"Q\u0101hirah, Bank al",
    "tgn:placetype":[
        "aat:300386970"
    ]
},
  "bbox": [],
  "geometry": {"coordinates":[31.227159,30.007162],"type":"Point"}
}