{
  "id": 7335860,
  "type": "Feature",
  "properties": {
    "tgn:hierarchy":[
        "tgn:7335860",
        "tgn:7002836",
        "tgn:7016622",
        "tgn:1000003",
        "tgn:1000095",
        "tgn:7029392"
    ],
    "tgn:id":7335860,
    "tgn:name":"Franceses, Lomo de",
    "tgn:placetype":[
        "aat:300266640"
    ]
},
  "bbox": [],
  "geometry": {"coordinates":[-17.85,28.783333],"type":"Point"}
}