<<<<<<< HEAD
{
  "id": 7475367,
  "type": "Feature",
  "properties": {
    "tgn:hierarchy":[
        "tgn:7475367",
        "tgn:1000004",
        "tgn:7467799",
        "tgn:1000141",
        "tgn:7029392"
    ],
    "tgn:id":7475367,
    "tgn:name":"Fenglun Guoxiao",
    "tgn:placetype":[
        "aat:300006495"
    ]
},
  "bbox": [],
  "geometry": {"coordinates":[120.460511,23.917341],"type":"Point"}
}
=======
{"geometry":{"type":"Point","coordinates":[120.460511,23.917341]},"type":"Feature","properties":{"hierarchy":["tgn:7475367","tgn:1000004","tgn:7467799","tgn:1000141","tgn:7029392"],"placetype":["aat:300006495"],"id":7475367,"name:xx":"Fenglun Guoxiao"}}
>>>>>>> 03f74aca74312dbeaf24d7e61306dd6a786dc3d0
