{
  "id": 1002602,
  "type": "Feature",
  "properties": {
    "tgn:hierarchy":[
        "tgn:1002602",
        "tgn:1000001",
        "tgn:7012149",
        "tgn:7007251",
        "tgn:7029392"
    ],
    "tgn:id":1002602,
    "tgn:name":"Livingston",
    "tgn:placetype":[
        "aat:300387145",
        "aat:300000771"
    ]
},
  "bbox": [],
  "geometry": {"coordinates":[-88.5167,40.8667],"type":"Point"}
}