<<<<<<< HEAD
{
  "id": 7360004,
  "type": "Feature",
  "properties": {
    "tgn:hierarchy":[
        "tgn:7360004",
        "tgn:1000001",
        "tgn:7005591",
        "tgn:7005560",
        "tgn:7029392"
    ],
    "tgn:id":7360004,
    "tgn:name":"Ciruelos",
    "tgn:placetype":[
        "aat:300008347"
    ]
},
  "bbox": [],
  "geometry": {"coordinates":[-96.4,15.716667],"type":"Point"}
}
=======
{"geometry":{"type":"Point","coordinates":[-96.400000,15.716667]},"type":"Feature","properties":{"hierarchy":["tgn:7360004","tgn:1000001","tgn:7005591","tgn:7005560","tgn:7029392"],"placetype":["aat:300008347"],"id":7360004,"name:xx":"Ciruelos"}}
>>>>>>> 03f74aca74312dbeaf24d7e61306dd6a786dc3d0
