{
  "id": 2201571,
  "type": "Feature",
  "properties": {
    "tgn:hierarchy":[
        "tgn:2201571",
        "tgn:2000296",
        "tgn:1000001",
        "tgn:7012149",
        "tgn:7007248",
        "tgn:7029392"
    ],
    "tgn:id":2201571,
    "tgn:name":"Buck Creek",
    "tgn:placetype":[
        "aat:300008706"
    ]
},
  "bbox": [],
  "geometry": {"coordinates":[-83.1667,33.0833],"type":"Point"}
}