<<<<<<< HEAD
{
  "id": 2400096,
  "type": "Feature",
  "properties": {
    "tgn:hierarchy":[
        "tgn:2400096",
        "tgn:1000001",
        "tgn:7012149",
        "tgn:2001308",
        "tgn:7007524",
        "tgn:7029392"
    ],
    "tgn:id":2400096,
    "tgn:name":"Horse Creek",
    "tgn:placetype":[
        "aat:300008706"
    ]
},
  "bbox": [],
  "geometry": {"coordinates":[-110.0833,45.5333],"type":"Point"}
}
=======
{"geometry":{"type":"Point","coordinates":[-110.083300,45.533300]},"type":"Feature","properties":{"hierarchy":["tgn:2400096","tgn:1000001","tgn:7012149","tgn:2001308","tgn:7007524","tgn:7029392"],"placetype":["aat:300008706"],"id":2400096,"name:xx":"Horse Creek"}}
>>>>>>> 03f74aca74312dbeaf24d7e61306dd6a786dc3d0
