{
  "id": 7489562,
  "type": "Feature",
  "properties": {
    "tgn:hierarchy":[
        "tgn:7489562",
        "tgn:1000004",
        "tgn:7001009",
        "tgn:1000141",
        "tgn:7029392"
    ],
    "tgn:id":7489562,
    "tgn:name":"Wuzhuwei",
    "tgn:placetype":[
        "aat:300000745"
    ]
},
  "bbox": [],
  "geometry": {"coordinates":[120.6933,24.120009],"type":"Point"}
}