{
  "id": 7567488,
  "type": "Feature",
  "properties": {
    "tgn:hierarchy":[
        "tgn:7567488",
        "tgn:1000004",
        "tgn:7000198",
        "tgn:7031786",
        "tgn:7029392"
    ],
    "tgn:id":7567488,
    "tgn:name:en":"Bh\u0101nkot Reserved Forest",
    "tgn:placetype":[
        "aat:300008865"
    ]
},
  "bbox": [],
  "geometry": {"coordinates":[78.640833,29.82],"type":"Point"}
}