{
  "id": 7272588,
  "type": "Feature",
  "properties": {
    "tgn:hierarchy":[
        "tgn:7272588",
        "tgn:1000003",
        "tgn:7003613",
        "tgn:7016845",
        "tgn:7029392"
    ],
    "tgn:id":7272588,
    "tgn:name:nl":"Vogelpark",
    "tgn:placetype":[
        "aat:300008187"
    ]
},
  "bbox": [],
  "geometry": {"coordinates":[6.55,53.35],"type":"Point"}
}