<<<<<<< HEAD
{
  "id": 2402856,
  "type": "Feature",
  "properties": {
    "tgn:hierarchy":[
        "tgn:2402856",
        "tgn:7006450",
        "tgn:1000001",
        "tgn:7012149",
        "tgn:2000079",
        "tgn:7029392"
    ],
    "tgn:id":2402856,
    "tgn:name":"Hotel Gulch",
    "tgn:placetype":[
        "aat:300008761"
    ]
},
  "bbox": [],
  "geometry": {"coordinates":[-165.3167,64.55],"type":"Point"}
}
=======
{"geometry":{"type":"Point","coordinates":[-165.316700,64.550000]},"type":"Feature","properties":{"hierarchy":["tgn:2402856","tgn:7006450","tgn:1000001","tgn:7012149","tgn:2000079","tgn:7029392"],"placetype":["aat:300008761"],"id":2402856,"name:xx":"Hotel Gulch"}}
>>>>>>> 03f74aca74312dbeaf24d7e61306dd6a786dc3d0
