{
  "id": 7568081,
  "type": "Feature",
  "properties": {
    "tgn:hierarchy":[
        "tgn:7568081",
        "tgn:1000004",
        "tgn:1001869",
        "tgn:7000198",
        "tgn:7029392"
    ],
    "tgn:id":7568081,
    "tgn:name:en":"Deg\u0101m",
    "tgn:placetype":[
        "aat:300008347"
    ]
},
  "bbox": [],
  "geometry": {"coordinates":[69.595833,21.698889],"type":"Point"}
}