<<<<<<< HEAD
{
  "id": 2408315,
  "type": "Feature",
  "properties": {
    "tgn:hierarchy":[
        "tgn:2408315",
        "tgn:1000001",
        "tgn:7012149",
        "tgn:7007709",
        "tgn:7029392"
    ],
    "tgn:id":2408315,
    "tgn:name":"Husons Ridge",
    "tgn:placetype":[
        "aat:300266640"
    ]
},
  "bbox": [],
  "geometry": {"coordinates":[-81.4833,36.2333],"type":"Point"}
}
=======
{"geometry":{"type":"Point","coordinates":[-81.483300,36.233300]},"type":"Feature","properties":{"hierarchy":["tgn:2408315","tgn:1000001","tgn:7012149","tgn:7007709","tgn:7029392"],"placetype":["aat:300266640"],"id":2408315,"name:xx":"Husons Ridge"}}
>>>>>>> 03f74aca74312dbeaf24d7e61306dd6a786dc3d0
