{
  "id": 2740401,
  "type": "Feature",
  "properties": {
    "tgn:hierarchy":[
        "tgn:2740401",
        "tgn:1000001",
        "tgn:2001416",
        "tgn:7012149",
        "tgn:7007526",
        "tgn:7029392"
    ],
    "tgn:id":2740401,
    "tgn:name":"Upper McCutcheon Spring",
    "tgn:placetype":[
        "aat:300008697"
    ]
},
  "bbox": [],
  "geometry": {"coordinates":[-115.6667,37.9667],"type":"Point"}
}