{
  "id": 2164620,
  "type": "Feature",
  "properties": {
    "tgn:hierarchy":[
        "tgn:2164620",
        "tgn:1000001",
        "tgn:7012149",
        "tgn:2000617",
        "tgn:7007253",
        "tgn:7029392"
    ],
    "tgn:id":2164620,
    "tgn:name":"Berrys Run",
    "tgn:placetype":[
        "aat:300008699"
    ]
},
  "bbox": [],
  "geometry": {"coordinates":[-91.5833,42.1167],"type":"Point"}
}