{
  "id": 2696058,
  "type": "Feature",
  "properties": {
    "tgn:hierarchy":[
        "tgn:2696058",
        "tgn:1000001",
        "tgn:7012149",
        "tgn:7007157",
        "tgn:1002857",
        "tgn:7029392"
    ],
    "tgn:id":2696058,
    "tgn:name":"Stoddard Valley",
    "tgn:placetype":[
        "aat:300008761"
    ]
},
  "bbox": [],
  "geometry": {"coordinates":[-117.0833,34.6833],"type":"Point"}
}