{
  "id": 2323202,
  "type": "Feature",
  "properties": {
    "tgn:hierarchy":[
        "tgn:2323202",
        "tgn:1000001",
        "tgn:7012149",
        "tgn:2000928",
        "tgn:7007515",
        "tgn:7029392"
    ],
    "tgn:id":2323202,
    "tgn:name":"Farm Quarry Number One",
    "tgn:placetype":[
        "aat:300000390"
    ]
},
  "bbox": [],
  "geometry": {"coordinates":[-69.4667,45.2667],"type":"Point"}
}