{
  "id": 2320220,
  "type": "Feature",
  "properties": {
    "tgn:hierarchy":[
        "tgn:2320220",
        "tgn:1000001",
        "tgn:7012149",
        "tgn:2001029",
        "tgn:7007521",
        "tgn:7029392"
    ],
    "tgn:id":2320220,
    "tgn:name":"Eve Lake",
    "tgn:placetype":[
        "aat:300008680"
    ]
},
  "bbox": [],
  "geometry": {"coordinates":[-93.3167,47.7333],"type":"Point"}
}