<<<<<<< HEAD
{
  "id": 7111712,
  "type": "Feature",
  "properties": {
    "tgn:hierarchy":[
        "tgn:7111712",
        "tgn:1000003",
        "tgn:7003678",
        "tgn:7000084",
        "tgn:7029392"
    ],
    "tgn:id":7111712,
    "tgn:name":"Richerode",
    "tgn:placetype":[
        "aat:300000206"
    ]
},
  "bbox": [],
  "geometry": {"coordinates":[9.116667,50.983333],"type":"Point"}
}
=======
{"geometry":{"type":"Point","coordinates":[9.116667,50.983333]},"type":"Feature","properties":{"hierarchy":["tgn:7111712","tgn:1000003","tgn:7003678","tgn:7000084","tgn:7029392"],"placetype":["aat:300000206"],"id":7111712,"name:xx":"Richerode"}}
>>>>>>> 03f74aca74312dbeaf24d7e61306dd6a786dc3d0
