{
  "id": 2664612,
  "type": "Feature",
  "properties": {
    "tgn:hierarchy":[
        "tgn:2664612",
        "tgn:1000001",
        "tgn:7012149",
        "tgn:2000888",
        "tgn:7007256",
        "tgn:7029392"
    ],
    "tgn:id":2664612,
    "tgn:name":"Simmons Creek",
    "tgn:placetype":[
        "aat:300008706"
    ]
},
  "bbox": [],
  "geometry": {"coordinates":[-93.2167,31.45],"type":"Point"}
}