{
  "id": 2570316,
  "type": "Feature",
  "properties": {
    "tgn:hierarchy":[
        "tgn:2570316",
        "tgn:1000001",
        "tgn:7012149",
        "tgn:1003031",
        "tgn:7007826",
        "tgn:7029392"
    ],
    "tgn:id":2570316,
    "tgn:name":"Pat Dick Hill",
    "tgn:placetype":[
        "aat:300008798"
    ]
},
  "bbox": [],
  "geometry": {"coordinates":[-97.55,33.15],"type":"Point"}
}