{
  "id": 7294783,
  "type": "Feature",
  "properties": {
    "tgn:hierarchy":[
        "tgn:7294783",
        "tgn:7002758",
        "tgn:7002841",
        "tgn:1000003",
        "tgn:1000095",
        "tgn:7029392"
    ],
    "tgn:id":7294783,
    "tgn:name":"Vallehondo, Arroyo de",
    "tgn:placetype":[
        "aat:300008699"
    ]
},
  "bbox": [],
  "geometry": {"coordinates":[-5.533333,37.833333],"type":"Point"}
}