{
  "id": 7423899,
  "type": "Feature",
  "properties": {
    "tgn:hierarchy":[
        "tgn:7423899",
        "tgn:1000001",
        "tgn:7005601",
        "tgn:7005560",
        "tgn:7029392"
    ],
    "tgn:id":7423899,
    "tgn:name":"La Ballena",
    "tgn:placetype":[
        "aat:300008347"
    ]
},
  "bbox": [],
  "geometry": {"coordinates":[-101.716667,22.458333],"type":"Point"}
}