{
  "id": 7289026,
  "type": "Feature",
  "properties": {
    "tgn:hierarchy":[
        "tgn:7289026",
        "tgn:1001768",
        "tgn:1000049",
        "tgn:1000002",
        "tgn:7029392"
    ],
    "tgn:id":7289026,
    "tgn:name":"La Bella Vista",
    "tgn:placetype":[
        "aat:300000206"
    ]
},
  "bbox": [],
  "geometry": {"coordinates":[-71.183333,-32.766667],"type":"Point"}
}