{
  "id": 7280077,
  "type": "Feature",
  "properties": {
    "tgn:hierarchy":[
        "tgn:7280077",
        "tgn:1001623",
        "tgn:1000049",
        "tgn:1000002",
        "tgn:7029392"
    ],
    "tgn:id":7280077,
    "tgn:name":"Reyes, Grupo",
    "tgn:placetype":[
        "aat:300008791"
    ]
},
  "bbox": [],
  "geometry": {"coordinates":[-74.666667,-47.516667],"type":"Point"}
}