{
  "id": 2464888,
  "type": "Feature",
  "properties": {
    "tgn:hierarchy":[
        "tgn:2464888",
        "tgn:1000001",
        "tgn:2002367",
        "tgn:7012149",
        "tgn:7007923",
        "tgn:7029392"
    ],
    "tgn:id":2464888,
    "tgn:name":"Logan, Mount",
    "tgn:placetype":[
        "aat:300008798"
    ]
},
  "bbox": [],
  "geometry": {"coordinates":[-105.35,43.9333],"type":"Point"}
}