{
  "id": 7563234,
  "type": "Feature",
  "properties": {
    "tgn:hierarchy":[
        "tgn:7563234",
        "tgn:1000004",
        "tgn:7000198",
        "tgn:7016722",
        "tgn:7029392"
    ],
    "tgn:id":7563234,
    "tgn:name:en":"Lauh\u0101garh",
    "tgn:placetype":[
        "aat:300008347"
    ]
},
  "bbox": [],
  "geometry": {"coordinates":[79.415838,25.396783],"type":"Point"}
}