{
  "id": 7014155,
  "type": "Feature",
  "properties": {
    "tgn:hierarchy":[
        "tgn:7014155",
        "tgn:1000001",
        "tgn:7014352",
        "tgn:7012149",
        "tgn:7007564",
        "tgn:7029392"
    ],
    "tgn:id":7014155,
    "tgn:name":"Exeter",
    "tgn:placetype":[
        "aat:300008347"
    ]
},
  "bbox": [],
  "geometry": {"coordinates":[-70.9333,42.9667],"type":"Point"}
}