<<<<<<< HEAD
{
  "id": 2702310,
  "type": "Feature",
  "properties": {
    "tgn:hierarchy":[
        "tgn:2702310",
        "tgn:1000001",
        "tgn:7012149",
        "tgn:7007524",
        "tgn:7029392"
    ],
    "tgn:id":2702310,
    "tgn:name":"Sullivan Gulch",
    "tgn:placetype":[
        "aat:300008761"
    ]
},
  "bbox": [],
  "geometry": {"coordinates":[-114.4667,47.75],"type":"Point"}
}
=======
{"geometry":{"type":"Point","coordinates":[-114.466700,47.750000]},"type":"Feature","properties":{"hierarchy":["tgn:2702310","tgn:1000001","tgn:7012149","tgn:7007524","tgn:7029392"],"placetype":["aat:300008761"],"id":2702310,"name:xx":"Sullivan Gulch"}}
>>>>>>> 03f74aca74312dbeaf24d7e61306dd6a786dc3d0
