{
  "id": 7525773,
  "type": "Feature",
  "properties": {
    "tgn:hierarchy":[
        "tgn:7525773",
        "tgn:7001242",
        "tgn:7016833",
        "tgn:1001225",
        "tgn:7029392"
    ],
    "tgn:id":7525773,
    "tgn:name:en":"Darf\u00eel, Nuqret el-",
    "tgn:placetype":[
        "aat:300132316"
    ]
},
  "bbox": [],
  "geometry": {"coordinates":[31.880833,31.493611],"type":"Point"}
}