{
  "id": 2338076,
  "type": "Feature",
  "properties": {
    "tgn:hierarchy":[
        "tgn:2338076",
        "tgn:2001558",
        "tgn:1000001",
        "tgn:7012149",
        "tgn:7007705",
        "tgn:7029392"
    ],
    "tgn:id":2338076,
    "tgn:name":"Fox Lake",
    "tgn:placetype":[
        "aat:300008680"
    ]
},
  "bbox": [],
  "geometry": {"coordinates":[-98.3333,46.95],"type":"Point"}
}