{
  "id": 2585737,
  "type": "Feature",
  "properties": {
    "tgn:hierarchy":[
        "tgn:2585737",
        "tgn:1000001",
        "tgn:7012149",
        "tgn:1002591",
        "tgn:7007255",
        "tgn:7029392"
    ],
    "tgn:id":2585737,
    "tgn:name":"Pipe Lick",
    "tgn:placetype":[
        "aat:300008699"
    ]
},
  "bbox": [],
  "geometry": {"coordinates":[-83.2833,38.5167],"type":"Point"}
}