{
  "id": 2162602,
  "type": "Feature",
  "properties": {
    "tgn:hierarchy":[
        "tgn:2162602",
        "tgn:1000001",
        "tgn:7012149",
        "tgn:2000490",
        "tgn:7007250",
        "tgn:7029392"
    ],
    "tgn:id":2162602,
    "tgn:name":"Bench Ditch",
    "tgn:placetype":[
        "aat:300006075"
    ]
},
  "bbox": [],
  "geometry": {"coordinates":[-112.8167,42.5667],"type":"Point"}
}