{
  "id": 7583378,
  "type": "Feature",
  "properties": {
    "tgn:hierarchy":[
        "tgn:7583378",
        "tgn:1000004",
        "tgn:7000198",
        "tgn:7016883",
        "tgn:7029392"
    ],
    "tgn:id":7583378,
    "tgn:name:en":"Las\u0101ra Pol\u0101b\u0101s",
    "tgn:placetype":[
        "aat:300008347"
    ]
},
  "bbox": [],
  "geometry": {"coordinates":[76.009906,30.630227],"type":"Point"}
}