{
  "id": 7485614,
  "type": "Feature",
  "properties": {
    "tgn:hierarchy":[
        "tgn:7485614",
        "tgn:1000004",
        "tgn:7490934",
        "tgn:1000141",
        "tgn:7029392"
    ],
    "tgn:id":7485614,
    "tgn:name":"Zhongyi Guoxiao",
    "tgn:placetype":[
        "aat:300006495"
    ]
},
  "bbox": [],
  "geometry": {"coordinates":[120.203056,22.990556],"type":"Point"}
}