<<<<<<< HEAD
{
  "id": 7485614,
  "type": "Feature",
  "properties": {
    "tgn:hierarchy":[
        "tgn:7485614",
        "tgn:1000004",
        "tgn:7490934",
        "tgn:1000141",
        "tgn:7029392"
    ],
    "tgn:id":7485614,
    "tgn:name":"Zhongyi Guoxiao",
    "tgn:placetype":[
        "aat:300006495"
    ]
},
  "bbox": [],
  "geometry": {"coordinates":[120.203056,22.990556],"type":"Point"}
}
=======
{"geometry":{"type":"Point","coordinates":[120.203056,22.990556]},"type":"Feature","properties":{"hierarchy":["tgn:7485614","tgn:1000004","tgn:7490934","tgn:1000141","tgn:7029392"],"placetype":["aat:300006495"],"id":7485614,"name:xx":"Zhongyi Guoxiao"}}
>>>>>>> 03f74aca74312dbeaf24d7e61306dd6a786dc3d0
