{
  "id": 1093863,
  "type": "Feature",
  "properties": {
    "tgn:hierarchy":[
        "tgn:1093863",
        "tgn:7001242",
        "tgn:7017583",
        "tgn:1000193",
        "tgn:7029392"
    ],
    "tgn:id":1093863,
    "tgn:name":"Seymour",
    "tgn:placetype":[
        "aat:300008347"
    ]
},
  "bbox": [],
  "geometry": {"coordinates":[26.7667,-32.55],"type":"Point"}
}