{
  "id": 2465642,
  "type": "Feature",
  "properties": {
    "tgn:hierarchy":[
        "tgn:2465642",
        "tgn:1000001",
        "tgn:7012149",
        "tgn:7007708",
        "tgn:7029392"
    ],
    "tgn:id":2465642,
    "tgn:name":"Lone Pine Creek",
    "tgn:placetype":[
        "aat:300008706"
    ]
},
  "bbox": [],
  "geometry": {"coordinates":[-121.05,44.4333],"type":"Point"}
}