{
  "id": 7505628,
  "type": "Feature",
  "properties": {
    "tgn:hierarchy":[
        "tgn:7505628",
        "tgn:1008380",
        "tgn:7520093",
        "tgn:1000226",
        "tgn:1000006",
        "tgn:7029392"
    ],
    "tgn:id":7505628,
    "tgn:name:en":"Whangairehe Stream",
    "tgn:placetype":[
        "aat:300008699"
    ]
},
  "bbox": [],
  "geometry": {"coordinates":[175.283333,-39.183333],"type":"Point"}
}