{
  "id": 7394765,
  "type": "Feature",
  "properties": {
    "tgn:hierarchy":[
        "tgn:7394765",
        "tgn:1001835",
        "tgn:1000001",
        "tgn:7005560",
        "tgn:7029392"
    ],
    "tgn:id":7394765,
    "tgn:name":"San Jos\u00e9 de Castillo",
    "tgn:placetype":[
        "aat:300008347"
    ]
},
  "bbox": [],
  "geometry": {"coordinates":[-115.75,31.016667],"type":"Point"}
}