{
  "id": 7236985,
  "type": "Feature",
  "properties": {
    "tgn:hierarchy":[
        "tgn:7236985",
        "tgn:7002745",
        "tgn:7017076",
        "tgn:1000003",
        "tgn:1000074",
        "tgn:7029392"
    ],
    "tgn:id":7236985,
    "tgn:name":"Elaf\u00f3nisos",
    "tgn:placetype":[
        "aat:300008347"
    ]
},
  "bbox": [],
  "geometry": {"coordinates":[22.983333,36.516667],"type":"Point"}
}