{
  "id": 7307590,
  "type": "Feature",
  "properties": {
    "tgn:hierarchy":[
        "tgn:7307590",
        "tgn:7008911",
        "tgn:1000003",
        "tgn:7002763",
        "tgn:1000095",
        "tgn:7029392"
    ],
    "tgn:id":7307590,
    "tgn:name":"Marianes",
    "tgn:placetype":[
        "aat:300008347"
    ]
},
  "bbox": [],
  "geometry": {"coordinates":[-5.516667,43.55],"type":"Point"}
}