{
  "id": 2039099,
  "type": "Feature",
  "properties": {
    "tgn:hierarchy":[
        "tgn:2039099",
        "tgn:1000001",
        "tgn:7012149",
        "tgn:2000842",
        "tgn:7007255",
        "tgn:7029392"
    ],
    "tgn:id":2039099,
    "tgn:name":"Gold City",
    "tgn:placetype":[
        "aat:300008347",
        "aat:300387210"
    ]
},
  "bbox": [],
  "geometry": {"coordinates":[-86.4333,36.75],"type":"Point"}
}