{
  "id": 7590874,
  "type": "Feature",
  "properties": {
    "tgn:hierarchy":[
        "tgn:7590874",
        "tgn:1000004",
        "tgn:7000198",
        "tgn:7000799",
        "tgn:7029392"
    ],
    "tgn:id":7590874,
    "tgn:name:en":"Mohandaor",
    "tgn:placetype":[
        "aat:300008347"
    ]
},
  "bbox": [],
  "geometry": {"coordinates":[74.366667,33.988889],"type":"Point"}
}