{
  "id": 2272112,
  "type": "Feature",
  "properties": {
    "tgn:hierarchy":[
        "tgn:2272112",
        "tgn:1000001",
        "tgn:7012149",
        "tgn:2002126",
        "tgn:7007827",
        "tgn:7029392"
    ],
    "tgn:id":2272112,
    "tgn:name":"Currant Creek Reservoir",
    "tgn:placetype":[
        "aat:300006191"
    ]
},
  "bbox": [],
  "geometry": {"coordinates":[-111.05,40.3333],"type":"Point"}
}