{
  "id": 2016258,
  "type": "Feature",
  "properties": {
    "tgn:hierarchy":[
        "tgn:2016258",
        "tgn:1000001",
        "tgn:2000202",
        "tgn:7012149",
        "tgn:7007158",
        "tgn:7029392"
    ],
    "tgn:id":2016258,
    "tgn:name":"San Antonio",
    "tgn:placetype":[
        "aat:300008347"
    ]
},
  "bbox": [],
  "geometry": {"coordinates":[-106.0167,37.0167],"type":"Point"}
}