{
  "id": 2513024,
  "type": "Feature",
  "properties": {
    "tgn:hierarchy":[
        "tgn:2513024",
        "tgn:1000001",
        "tgn:7012149",
        "tgn:2002175",
        "tgn:7007919",
        "tgn:7029392"
    ],
    "tgn:id":2513024,
    "tgn:name":"Mill Creek",
    "tgn:placetype":[
        "aat:300008706"
    ]
},
  "bbox": [],
  "geometry": {"coordinates":[-79.15,37.8167],"type":"Point"}
}