{
  "id": 1066706,
  "type": "Feature",
  "properties": {
    "tgn:hierarchy":[
        "tgn:1066706",
        "tgn:1000004",
        "tgn:7001796",
        "tgn:1000111",
        "tgn:7029392"
    ],
    "tgn:id":1066706,
    "tgn:name":"Baiyundu",
    "tgn:placetype":[
        "aat:300008347"
    ]
},
  "bbox": [],
  "geometry": {"coordinates":[118.7833,26.1667],"type":"Point"}
}