{
  "id": 7430806,
  "type": "Feature",
  "properties": {
    "tgn:hierarchy":[
        "tgn:7430806",
        "tgn:7005581",
        "tgn:1000001",
        "tgn:7005560",
        "tgn:7029392"
    ],
    "tgn:id":7430806,
    "tgn:name":"Campo 77",
    "tgn:placetype":[
        "aat:300008347"
    ]
},
  "bbox": [],
  "geometry": {"coordinates":[-106.633333,29.133333],"type":"Point"}
}