{
  "id": 7326997,
  "type": "Feature",
  "properties": {
    "tgn:hierarchy":[
        "tgn:7326997",
        "tgn:7002810",
        "tgn:7001158",
        "tgn:1000003",
        "tgn:1000095",
        "tgn:7029392"
    ],
    "tgn:id":7326997,
    "tgn:name":"Pedrosa de Duero",
    "tgn:placetype":[
        "aat:300008347"
    ]
},
  "bbox": [],
  "geometry": {"coordinates":[-3.983333,41.716667],"type":"Point"}
}