{
  "id": 2684921,
  "type": "Feature",
  "properties": {
    "tgn:hierarchy":[
        "tgn:2684921",
        "tgn:1000001",
        "tgn:7012149",
        "tgn:2000238",
        "tgn:7007158",
        "tgn:7029392"
    ],
    "tgn:id":2684921,
    "tgn:name":"Split Rock",
    "tgn:placetype":[
        "aat:300008798"
    ]
},
  "bbox": [],
  "geometry": {"coordinates":[-105.5167,39.4333],"type":"Point"}
}