<<<<<<< HEAD
{
  "id": 7360094,
  "type": "Feature",
  "properties": {
    "tgn:hierarchy":[
        "tgn:7360094",
        "tgn:7005581",
        "tgn:1000001",
        "tgn:7005560",
        "tgn:7029392"
    ],
    "tgn:id":7360094,
    "tgn:name":"Duraznito",
    "tgn:placetype":[
        "aat:300008347"
    ]
},
  "bbox": [],
  "geometry": {"coordinates":[-108.383333,27.4],"type":"Point"}
}
=======
{"geometry":{"type":"Point","coordinates":[-108.383333,27.400000]},"type":"Feature","properties":{"hierarchy":["tgn:7360094","tgn:7005581","tgn:1000001","tgn:7005560","tgn:7029392"],"placetype":["aat:300008347"],"id":7360094,"name:xx":"Duraznito"}}
>>>>>>> 03f74aca74312dbeaf24d7e61306dd6a786dc3d0
