{
  "id": 7406859,
  "type": "Feature",
  "properties": {
    "tgn:hierarchy":[
        "tgn:7406859",
        "tgn:7005585",
        "tgn:1000001",
        "tgn:7005560",
        "tgn:7029392"
    ],
    "tgn:id":7406859,
    "tgn:name":"Los Valles",
    "tgn:placetype":[
        "aat:300008347"
    ]
},
  "bbox": [],
  "geometry": {"coordinates":[-100.358333,17.283333],"type":"Point"}
}