{
  "id": 7261761,
  "type": "Feature",
  "properties": {
    "tgn:hierarchy":[
        "tgn:7261761",
        "tgn:1000003",
        "tgn:7003627",
        "tgn:7016845",
        "tgn:7029392"
    ],
    "tgn:id":7261761,
    "tgn:name:nl":"Haanwijk, Polder",
    "tgn:placetype":[
        "aat:300006163"
    ]
},
  "bbox": [],
  "geometry": {"coordinates":[4.933333,52.083333],"type":"Point"}
}