<<<<<<< HEAD
{
  "id": 2158436,
  "type": "Feature",
  "properties": {
    "tgn:hierarchy":[
        "tgn:2158436",
        "tgn:1000001",
        "tgn:1003023",
        "tgn:7012149",
        "tgn:7007516",
        "tgn:7029392"
    ],
    "tgn:id":2158436,
    "tgn:name":"Beaverdam Creek",
    "tgn:placetype":[
        "aat:300008706"
    ]
},
  "bbox": [],
  "geometry": {"coordinates":[-75.4333,38.3167],"type":"Point"}
}
=======
{"geometry":{"type":"Point","coordinates":[-75.433300,38.316700]},"type":"Feature","properties":{"hierarchy":["tgn:2158436","tgn:1000001","tgn:1003023","tgn:7012149","tgn:7007516","tgn:7029392"],"placetype":["aat:300008706"],"id":2158436,"name:xx":"Beaverdam Creek"}}
>>>>>>> 03f74aca74312dbeaf24d7e61306dd6a786dc3d0
