<<<<<<< HEAD
{
  "id": 2158169,
  "type": "Feature",
  "properties": {
    "tgn:hierarchy":[
        "tgn:2158169",
        "tgn:1000001",
        "tgn:7012149",
        "tgn:2000517",
        "tgn:7007251",
        "tgn:7029392"
    ],
    "tgn:id":2158169,
    "tgn:name":"Beaver Pond Ditch",
    "tgn:placetype":[
        "aat:300006075"
    ]
},
  "bbox": [],
  "geometry": {"coordinates":[-87.6,38.7],"type":"Point"}
}
=======
{"geometry":{"type":"Point","coordinates":[-87.600000,38.700000]},"type":"Feature","properties":{"hierarchy":["tgn:2158169","tgn:1000001","tgn:7012149","tgn:2000517","tgn:7007251","tgn:7029392"],"placetype":["aat:300006075"],"id":2158169,"name:xx":"Beaver Pond Ditch"}}
>>>>>>> 03f74aca74312dbeaf24d7e61306dd6a786dc3d0
