{
  "id": 2023549,
  "type": "Feature",
  "properties": {
    "tgn:hierarchy":[
        "tgn:2023549",
        "tgn:1000001",
        "tgn:2000313",
        "tgn:7012149",
        "tgn:7007248",
        "tgn:7029392"
    ],
    "tgn:id":2023549,
    "tgn:name":"Mandeville",
    "tgn:placetype":[
        "aat:300387016"
    ]
},
  "bbox": [],
  "geometry": {"coordinates":[-85.1333,33.65],"type":"Point"}
}