{
  "id": 2423666,
  "type": "Feature",
  "properties": {
    "tgn:hierarchy":[
        "tgn:2423666",
        "tgn:1000001",
        "tgn:2000272",
        "tgn:7012149",
        "tgn:7007240",
        "tgn:7029392"
    ],
    "tgn:id":2423666,
    "tgn:name":"John Pond",
    "tgn:placetype":[
        "aat:300008680"
    ]
},
  "bbox": [],
  "geometry": {"coordinates":[-85.95,30.7167],"type":"Point"}
}