{
  "id": 1098612,
  "type": "Feature",
  "properties": {
    "tgn:hierarchy":[
        "tgn:1098612",
        "tgn:7000490",
        "tgn:1000006",
        "tgn:7001830",
        "tgn:7029392"
    ],
    "tgn:id":1098612,
    "tgn:name":"Wynnum",
    "tgn:placetype":[
        "aat:300008347"
    ]
},
  "bbox": [],
  "geometry": {"coordinates":[153.1333,-27.4833],"type":"Point"}
}