{
  "id": 2143884,
  "type": "Feature",
  "properties": {
    "tgn:hierarchy":[
        "tgn:2143884",
        "tgn:2000105",
        "tgn:1000001",
        "tgn:7016172",
        "tgn:7012149",
        "tgn:7029392"
    ],
    "tgn:id":2143884,
    "tgn:name":"Baker Brothers Reservoir",
    "tgn:placetype":[
        "aat:300006191"
    ]
},
  "bbox": [],
  "geometry": {"coordinates":[-91.4667,34.5167],"type":"Point"}
}