{
  "id": 1083333,
  "type": "Feature",
  "properties": {
    "tgn:hierarchy":[
        "tgn:1083333",
        "tgn:7000360",
        "tgn:1000004",
        "tgn:1000133",
        "tgn:7029392"
    ],
    "tgn:id":1083333,
    "tgn:name":"Ahmad W\u0101l",
    "tgn:placetype":[
        "aat:300008347"
    ]
},
  "bbox": [],
  "geometry": {"coordinates":[65.9333,29.4167],"type":"Point"}
}