{
  "id": 2640772,
  "type": "Feature",
  "properties": {
    "tgn:hierarchy":[
        "tgn:2640772",
        "tgn:1000001",
        "tgn:7012149",
        "tgn:2000286",
        "tgn:7007240",
        "tgn:7029392"
    ],
    "tgn:id":2640772,
    "tgn:name":"San Pedro Poturiba",
    "tgn:placetype":[
        "aat:300008347",
        "aat:300167671"
    ]
},
  "bbox": [],
  "geometry": {"coordinates":[-83.0833,30.1333],"type":"Point"}
}