<<<<<<< HEAD
{
  "id": 2153118,
  "type": "Feature",
  "properties": {
    "tgn:hierarchy":[
        "tgn:2153118",
        "tgn:7002659",
        "tgn:1000001",
        "tgn:7012149",
        "tgn:2000026",
        "tgn:7029392"
    ],
    "tgn:id":2153118,
    "tgn:name":"Beader Branch",
    "tgn:placetype":[
        "aat:300008699"
    ]
},
  "bbox": [],
  "geometry": {"coordinates":[-86.7667,31.0833],"type":"Point"}
}
=======
{"geometry":{"type":"Point","coordinates":[-86.766700,31.083300]},"type":"Feature","properties":{"hierarchy":["tgn:2153118","tgn:7002659","tgn:1000001","tgn:7012149","tgn:2000026","tgn:7029392"],"placetype":["aat:300008699"],"id":2153118,"name:xx":"Beader Branch"}}
>>>>>>> 03f74aca74312dbeaf24d7e61306dd6a786dc3d0
