{
  "id": 7277694,
  "type": "Feature",
  "properties": {
    "tgn:hierarchy":[
        "tgn:7277694",
        "tgn:1001699",
        "tgn:1000049",
        "tgn:1000002",
        "tgn:7029392"
    ],
    "tgn:id":7277694,
    "tgn:name":"Morro Yal\u00ed",
    "tgn:placetype":[
        "aat:300008795"
    ]
},
  "bbox": [],
  "geometry": {"coordinates":[-73.030278,-43.510833],"type":"Point"}
}