{
  "id": 1013995,
  "type": "Feature",
  "properties": {
    "tgn:hierarchy":[
        "tgn:1013995",
        "tgn:7005685",
        "tgn:1000001",
        "tgn:7005734",
        "tgn:7029392"
    ],
    "tgn:id":1013995,
    "tgn:name":"Rossburn",
    "tgn:placetype":[
        "aat:300008347"
    ]
},
  "bbox": [],
  "geometry": {"coordinates":[-100.8333,50.6667],"type":"Point"}
}