{
  "id": 2446819,
  "type": "Feature",
  "properties": {
    "tgn:hierarchy":[
        "tgn:2446819",
        "tgn:1000001",
        "tgn:7016172",
        "tgn:2000116",
        "tgn:7012149",
        "tgn:7029392"
    ],
    "tgn:id":2446819,
    "tgn:name":"Libby",
    "tgn:placetype":[
        "aat:300008347"
    ]
},
  "bbox": [],
  "geometry": {"coordinates":[-91.95,35.45],"type":"Point"}
}