{
  "id": 2478601,
  "type": "Feature",
  "properties": {
    "tgn:hierarchy":[
        "tgn:2478601",
        "tgn:1000001",
        "tgn:7012149",
        "tgn:7013941",
        "tgn:7007568",
        "tgn:7029392"
    ],
    "tgn:id":2478601,
    "tgn:name":"Madeleine, Lake",
    "tgn:placetype":[
        "aat:300008680"
    ]
},
  "bbox": [],
  "geometry": {"coordinates":[-74.45,44.1167],"type":"Point"}
}