{
  "id": 2398596,
  "type": "Feature",
  "properties": {
    "tgn:hierarchy":[
        "tgn:2398596",
        "tgn:1000001",
        "tgn:7012149",
        "tgn:7007157",
        "tgn:1002608",
        "tgn:7029392"
    ],
    "tgn:id":2398596,
    "tgn:name":"Hoover Reservoir",
    "tgn:placetype":[
        "aat:300006191"
    ]
},
  "bbox": [],
  "geometry": {"coordinates":[-118.0333,33.9833],"type":"Point"}
}