{
  "id": 2323613,
  "type": "Feature",
  "properties": {
    "tgn:hierarchy":[
        "tgn:2323613",
        "tgn:1000001",
        "tgn:7012149",
        "tgn:1002457",
        "tgn:7007252",
        "tgn:7029392"
    ],
    "tgn:id":2323613,
    "tgn:name":"Farris Lake",
    "tgn:placetype":[
        "aat:300008680"
    ]
},
  "bbox": [],
  "geometry": {"coordinates":[-85.9667,38.1167],"type":"Point"}
}