{
  "id": 2587210,
  "type": "Feature",
  "properties": {
    "tgn:hierarchy":[
        "tgn:2587210",
        "tgn:1000001",
        "tgn:2001175",
        "tgn:7012149",
        "tgn:7007523",
        "tgn:7029392"
    ],
    "tgn:id":2587210,
    "tgn:name":"Platte River",
    "tgn:placetype":[
        "aat:300008347"
    ]
},
  "bbox": [],
  "geometry": {"coordinates":[-94.6833,39.55],"type":"Point"}
}