<<<<<<< HEAD
{
  "id": 2704599,
  "type": "Feature",
  "properties": {
    "tgn:hierarchy":[
        "tgn:2704599",
        "tgn:1000001",
        "tgn:7012149",
        "tgn:1002742",
        "tgn:7007920",
        "tgn:7029392"
    ],
    "tgn:id":2704599,
    "tgn:name":"Sunrise Peak",
    "tgn:placetype":[
        "aat:300008798"
    ]
},
  "bbox": [],
  "geometry": {"coordinates":[-120.3667,48.7167],"type":"Point"}
}
=======
{"geometry":{"type":"Point","coordinates":[-120.366700,48.716700]},"type":"Feature","properties":{"hierarchy":["tgn:2704599","tgn:1000001","tgn:7012149","tgn:1002742","tgn:7007920","tgn:7029392"],"placetype":["aat:300008798"],"id":2704599,"name:xx":"Sunrise Peak"}}
>>>>>>> 03f74aca74312dbeaf24d7e61306dd6a786dc3d0
