{
  "id": 2704599,
  "type": "Feature",
  "properties": {
    "tgn:hierarchy":[
        "tgn:2704599",
        "tgn:1000001",
        "tgn:7012149",
        "tgn:1002742",
        "tgn:7007920",
        "tgn:7029392"
    ],
    "tgn:id":2704599,
    "tgn:name":"Sunrise Peak",
    "tgn:placetype":[
        "aat:300008798"
    ]
},
  "bbox": [],
  "geometry": {"coordinates":[-120.3667,48.7167],"type":"Point"}
}