{
  "id": 2278314,
  "type": "Feature",
  "properties": {
    "tgn:hierarchy":[
        "tgn:2278314",
        "tgn:1000001",
        "tgn:7012149",
        "tgn:2002090",
        "tgn:7007826",
        "tgn:7029392"
    ],
    "tgn:id":2278314,
    "tgn:name":"De Spain Tank",
    "tgn:placetype":[
        "aat:300006191"
    ]
},
  "bbox": [],
  "geometry": {"coordinates":[-98.95,27.6333],"type":"Point"}
}