{
  "id": 2704560,
  "type": "Feature",
  "properties": {
    "tgn:hierarchy":[
        "tgn:2704560",
        "tgn:1000001",
        "tgn:7012149",
        "tgn:1002789",
        "tgn:7007710",
        "tgn:7029392"
    ],
    "tgn:id":2704560,
    "tgn:name":"Sunrise Lake",
    "tgn:placetype":[
        "aat:300006191"
    ]
},
  "bbox": [],
  "geometry": {"coordinates":[-74.95,41.3167],"type":"Point"}
}