{
  "id": 7080785,
  "type": "Feature",
  "properties": {
    "tgn:hierarchy":[
        "tgn:7080785",
        "tgn:1000003",
        "tgn:7000094",
        "tgn:7000084",
        "tgn:7029392"
    ],
    "tgn:id":7080785,
    "tgn:name":"Wohrenstorf",
    "tgn:placetype":[
        "aat:300008347"
    ]
},
  "bbox": [],
  "geometry": {"coordinates":[12.45,54.016667],"type":"Point"}
}