{
  "id": 2368962,
  "type": "Feature",
  "properties": {
    "tgn:hierarchy":[
        "tgn:2368962",
        "tgn:1000001",
        "tgn:7012149",
        "tgn:2000442",
        "tgn:7007248",
        "tgn:7029392"
    ],
    "tgn:id":2368962,
    "tgn:name":"Gum Branch",
    "tgn:placetype":[
        "aat:300008699"
    ]
},
  "bbox": [],
  "geometry": {"coordinates":[-81.7833,31.45],"type":"Point"}
}