{
  "id": 2709931,
  "type": "Feature",
  "properties": {
    "tgn:hierarchy":[
        "tgn:2709931",
        "tgn:1000001",
        "tgn:7012149",
        "tgn:2002290",
        "tgn:7013961",
        "tgn:7029392"
    ],
    "tgn:id":2709931,
    "tgn:name":"Take-In Creek",
    "tgn:placetype":[
        "aat:300008706"
    ]
},
  "bbox": [],
  "geometry": {"coordinates":[-81.15,37.6667],"type":"Point"}
}