<<<<<<< HEAD
{
  "id": 2332482,
  "type": "Feature",
  "properties": {
    "tgn:hierarchy":[
        "tgn:2332482",
        "tgn:7002659",
        "tgn:1000001",
        "tgn:2000016",
        "tgn:7012149",
        "tgn:7029392"
    ],
    "tgn:id":2332482,
    "tgn:name":"Florence Mill Hollow",
    "tgn:placetype":[
        "aat:300008761"
    ]
},
  "bbox": [],
  "geometry": {"coordinates":[-88.0,34.8],"type":"Point"}
}
=======
{"geometry":{"type":"Point","coordinates":[-88.000000,34.800000]},"type":"Feature","properties":{"hierarchy":["tgn:2332482","tgn:7002659","tgn:1000001","tgn:2000016","tgn:7012149","tgn:7029392"],"placetype":["aat:300008761"],"id":2332482,"name:xx":"Florence Mill Hollow"}}
>>>>>>> 03f74aca74312dbeaf24d7e61306dd6a786dc3d0
