{
  "id": 7380748,
  "type": "Feature",
  "properties": {
    "tgn:hierarchy":[
        "tgn:7380748",
        "tgn:1001836",
        "tgn:1000001",
        "tgn:7005560",
        "tgn:7029392"
    ],
    "tgn:id":7380748,
    "tgn:name":"Los Achemes",
    "tgn:placetype":[
        "aat:300008347"
    ]
},
  "bbox": [],
  "geometry": {"coordinates":[-111.216667,24.966667],"type":"Point"}
}