<<<<<<< HEAD
{
  "id": 2402763,
  "type": "Feature",
  "properties": {
    "tgn:hierarchy":[
        "tgn:2402763",
        "tgn:1000001",
        "tgn:7012149",
        "tgn:7007157",
        "tgn:1002972",
        "tgn:7029392"
    ],
    "tgn:id":2402763,
    "tgn:name":"Hot Springs Canyon",
    "tgn:placetype":[
        "aat:300008761"
    ]
},
  "bbox": [],
  "geometry": {"coordinates":[-119.0167,34.6167],"type":"Point"}
}
=======
{"geometry":{"type":"Point","coordinates":[-119.016700,34.616700]},"type":"Feature","properties":{"hierarchy":["tgn:2402763","tgn:1000001","tgn:7012149","tgn:7007157","tgn:1002972","tgn:7029392"],"placetype":["aat:300008761"],"id":2402763,"name:xx":"Hot Springs Canyon"}}
>>>>>>> 03f74aca74312dbeaf24d7e61306dd6a786dc3d0
