{
  "id": 2402763,
  "type": "Feature",
  "properties": {
    "tgn:hierarchy":[
        "tgn:2402763",
        "tgn:1000001",
        "tgn:7012149",
        "tgn:7007157",
        "tgn:1002972",
        "tgn:7029392"
    ],
    "tgn:id":2402763,
    "tgn:name":"Hot Springs Canyon",
    "tgn:placetype":[
        "aat:300008761"
    ]
},
  "bbox": [],
  "geometry": {"coordinates":[-119.0167,34.6167],"type":"Point"}
}