{
  "id": 7579975,
  "type": "Feature",
  "properties": {
    "tgn:hierarchy":[
        "tgn:7579975",
        "tgn:1000004",
        "tgn:1001832",
        "tgn:7000198",
        "tgn:7029392"
    ],
    "tgn:id":7579975,
    "tgn:name:en":"Teok",
    "tgn:placetype":[
        "aat:300008347"
    ]
},
  "bbox": [],
  "geometry": {"coordinates":[94.416507,26.831975],"type":"Point"}
}