{
  "id": 7570083,
  "type": "Feature",
  "properties": {
    "tgn:hierarchy":[
        "tgn:7570083",
        "tgn:1000004",
        "tgn:7000198",
        "tgn:7016788",
        "tgn:7029392"
    ],
    "tgn:id":7570083,
    "tgn:name:en":"H\u0101roti",
    "tgn:placetype":[
        "aat:300008347"
    ]
},
  "bbox": [],
  "geometry": {"coordinates":[75.728796,25.929658],"type":"Point"}
}