{
  "id": 7524576,
  "type": "Feature",
  "properties": {
    "tgn:hierarchy":[
        "tgn:7524576",
        "tgn:7001242",
        "tgn:1001059",
        "tgn:7016833",
        "tgn:7029392"
    ],
    "tgn:id":7524576,
    "tgn:name:en":"Awl\u0101d \u1e28am\u0101m",
    "tgn:placetype":[
        "aat:300008347"
    ]
},
  "bbox": [],
  "geometry": {"coordinates":[31.770778,31.377323],"type":"Point"}
}