{
  "id": 7571696,
  "type": "Feature",
  "properties": {
    "tgn:hierarchy":[
        "tgn:7571696",
        "tgn:1000004",
        "tgn:7000198",
        "tgn:7016722",
        "tgn:7029392"
    ],
    "tgn:id":7571696,
    "tgn:name:en":"Jasr\u0101na",
    "tgn:placetype":[
        "aat:300008347"
    ]
},
  "bbox": [],
  "geometry": {"coordinates":[78.652562,27.235658],"type":"Point"}
}