<<<<<<< HEAD
{
  "id": 2335045,
  "type": "Feature",
  "properties": {
    "tgn:hierarchy":[
        "tgn:2335045",
        "tgn:1000001",
        "tgn:7016098",
        "tgn:7012149",
        "tgn:7007516",
        "tgn:7029392"
    ],
    "tgn:id":2335045,
    "tgn:name":"Forrest Landing Cove",
    "tgn:placetype":[
        "aat:300132316"
    ]
},
  "bbox": [],
  "geometry": {"coordinates":[-76.5167,38.35],"type":"Point"}
}
=======
{"geometry":{"type":"Point","coordinates":[-76.516700,38.350000]},"type":"Feature","properties":{"hierarchy":["tgn:2335045","tgn:1000001","tgn:7016098","tgn:7012149","tgn:7007516","tgn:7029392"],"placetype":["aat:300132316"],"id":2335045,"name:xx":"Forrest Landing Cove"}}
>>>>>>> 03f74aca74312dbeaf24d7e61306dd6a786dc3d0
