{
  "id": 2335045,
  "type": "Feature",
  "properties": {
    "tgn:hierarchy":[
        "tgn:2335045",
        "tgn:1000001",
        "tgn:7016098",
        "tgn:7012149",
        "tgn:7007516",
        "tgn:7029392"
    ],
    "tgn:id":2335045,
    "tgn:name":"Forrest Landing Cove",
    "tgn:placetype":[
        "aat:300132316"
    ]
},
  "bbox": [],
  "geometry": {"coordinates":[-76.5167,38.35],"type":"Point"}
}