{
  "id": 2649588,
  "type": "Feature",
  "properties": {
    "tgn:hierarchy":[
        "tgn:2649588",
        "tgn:2001731",
        "tgn:1000001",
        "tgn:7012149",
        "tgn:7007712",
        "tgn:7029392"
    ],
    "tgn:id":2649588,
    "tgn:name":"Scout Island",
    "tgn:placetype":[
        "aat:300008791"
    ]
},
  "bbox": [],
  "geometry": {"coordinates":[-80.6833,32.35],"type":"Point"}
}