{
  "id": 2055372,
  "type": "Feature",
  "properties": {
    "tgn:hierarchy":[
        "tgn:2055372",
        "tgn:1000001",
        "tgn:7012149",
        "tgn:2001043",
        "tgn:7007521",
        "tgn:7029392"
    ],
    "tgn:id":2055372,
    "tgn:name":"Rosewood",
    "tgn:placetype":[
        "aat:300008347"
    ]
},
  "bbox": [],
  "geometry": {"coordinates":[-96.2833,48.1833],"type":"Point"}
}