{
  "id": 2402634,
  "type": "Feature",
  "properties": {
    "tgn:hierarchy":[
        "tgn:2402634",
        "tgn:1000001",
        "tgn:2001418",
        "tgn:7012149",
        "tgn:7007526",
        "tgn:7029392"
    ],
    "tgn:id":2402634,
    "tgn:name":"Hot Creek North Summit",
    "tgn:placetype":[
        "aat:300008798"
    ]
},
  "bbox": [],
  "geometry": {"coordinates":[-116.2833,38.6167],"type":"Point"}
}