{
  "id": 2458095,
  "type": "Feature",
  "properties": {
    "tgn:hierarchy":[
        "tgn:2458095",
        "tgn:7006450",
        "tgn:1000001",
        "tgn:7030547",
        "tgn:7012149",
        "tgn:7029392"
    ],
    "tgn:id":2458095,
    "tgn:name":"Little Mountain",
    "tgn:placetype":[
        "aat:300008798"
    ]
},
  "bbox": [],
  "geometry": {"coordinates":[-152.2167,62.8833],"type":"Point"}
}