{
  "id": 2447628,
  "type": "Feature",
  "properties": {
    "tgn:hierarchy":[
        "tgn:2447628",
        "tgn:1000001",
        "tgn:7012149",
        "tgn:7007523",
        "tgn:7029392"
    ],
    "tgn:id":2447628,
    "tgn:name":"Lick Log Creek",
    "tgn:placetype":[
        "aat:300008706"
    ]
},
  "bbox": [],
  "geometry": {"coordinates":[-90.2167,37.1167],"type":"Point"}
}