{
  "id": 7142470,
  "type": "Feature",
  "properties": {
    "tgn:hierarchy":[
        "tgn:7142470",
        "tgn:7003669",
        "tgn:1000003",
        "tgn:7000084",
        "tgn:7029392"
    ],
    "tgn:id":7142470,
    "tgn:name":"Ludwigsreut",
    "tgn:placetype":[
        "aat:300387200"
    ]
},
  "bbox": [],
  "geometry": {"coordinates":[13.766667,48.816667],"type":"Point"}
}