<<<<<<< HEAD
{
  "id": 7480104,
  "type": "Feature",
  "properties": {
    "tgn:hierarchy":[
        "tgn:7480104",
        "tgn:7001004",
        "tgn:1000004",
        "tgn:1000141",
        "tgn:7029392"
    ],
    "tgn:id":7480104,
    "tgn:name":"Qiedong Qiao",
    "tgn:placetype":[
        "aat:300007836"
    ]
},
  "bbox": [],
  "geometry": {"coordinates":[120.469219,23.003812],"type":"Point"}
}
=======
{"geometry":{"type":"Point","coordinates":[120.469219,23.003812]},"type":"Feature","properties":{"hierarchy":["tgn:7480104","tgn:7001004","tgn:1000004","tgn:1000141","tgn:7029392"],"placetype":["aat:300007836"],"id":7480104,"name:xx":"Qiedong Qiao"}}
>>>>>>> 03f74aca74312dbeaf24d7e61306dd6a786dc3d0
