{
  "id": 1004545,
  "type": "Feature",
  "properties": {
    "tgn:hierarchy":[
        "tgn:1004545",
        "tgn:1000003",
        "tgn:7003677",
        "tgn:7000084",
        "tgn:7004443",
        "tgn:7029392"
    ],
    "tgn:id":1004545,
    "tgn:name":"Golzheim",
    "tgn:placetype":[
        "aat:300000745",
        "aat:300387332"
    ]
},
  "bbox": [],
  "geometry": {"coordinates":[6.766667,51.25],"type":"Point"}
}