{
  "id": 7443476,
  "type": "Feature",
  "properties": {
    "tgn:hierarchy":[
        "tgn:7443476",
        "tgn:7002444",
        "tgn:1000003",
        "tgn:7029508",
        "tgn:7008591",
        "tgn:7029392"
    ],
    "tgn:id":7443476,
    "tgn:name:en":"Usta Ness",
    "tgn:placetype":[
        "aat:300386846"
    ]
},
  "bbox": [],
  "geometry": {"coordinates":[-1.316667,60.166667],"type":"Point"}
}