{
  "id": 2411744,
  "type": "Feature",
  "properties": {
    "tgn:hierarchy":[
        "tgn:2411744",
        "tgn:2000934",
        "tgn:1000001",
        "tgn:7012149",
        "tgn:7007516",
        "tgn:7029392"
    ],
    "tgn:id":2411744,
    "tgn:name":"Indian Lick",
    "tgn:placetype":[
        "aat:300008699"
    ]
},
  "bbox": [],
  "geometry": {"coordinates":[-78.5333,39.6333],"type":"Point"}
}