{
  "id": 7090631,
  "type": "Feature",
  "properties": {
    "tgn:hierarchy":[
        "tgn:7090631",
        "tgn:1000003",
        "tgn:7003677",
        "tgn:7000084",
        "tgn:7029392"
    ],
    "tgn:id":7090631,
    "tgn:name":"Vo\u00df-Berg",
    "tgn:placetype":[
        "aat:300008777"
    ]
},
  "bbox": [],
  "geometry": {"coordinates":[8.45,51.383333],"type":"Point"}
}