<<<<<<< HEAD
{
  "id": 2707356,
  "type": "Feature",
  "properties": {
    "tgn:hierarchy":[
        "tgn:2707356",
        "tgn:1000001",
        "tgn:7012149",
        "tgn:1002244",
        "tgn:7007826",
        "tgn:7029392"
    ],
    "tgn:id":2707356,
    "tgn:name":"Sweet Creek",
    "tgn:placetype":[
        "aat:300008706"
    ]
},
  "bbox": [],
  "geometry": {"coordinates":[-94.5833,33.1667],"type":"Point"}
}
=======
{"geometry":{"type":"Point","coordinates":[-94.583300,33.166700]},"type":"Feature","properties":{"hierarchy":["tgn:2707356","tgn:1000001","tgn:7012149","tgn:1002244","tgn:7007826","tgn:7029392"],"placetype":["aat:300008706"],"id":2707356,"name:xx":"Sweet Creek"}}
>>>>>>> 03f74aca74312dbeaf24d7e61306dd6a786dc3d0
