{
  "id": 2606294,
  "type": "Feature",
  "properties": {
    "tgn:hierarchy":[
        "tgn:2606294",
        "tgn:1000001",
        "tgn:7012149",
        "tgn:2000346",
        "tgn:7007248",
        "tgn:7029392"
    ],
    "tgn:id":2606294,
    "tgn:name":"Rall Mountain",
    "tgn:placetype":[
        "aat:300008798"
    ]
},
  "bbox": [],
  "geometry": {"coordinates":[-84.2167,34.7167],"type":"Point"}
}