<<<<<<< HEAD
{
  "id": 2250672,
  "type": "Feature",
  "properties": {
    "tgn:hierarchy":[
        "tgn:2250672",
        "tgn:1000001",
        "tgn:2001428",
        "tgn:7012149",
        "tgn:7007566",
        "tgn:7029392"
    ],
    "tgn:id":2250672,
    "tgn:name":"Colorado, Cerro",
    "tgn:placetype":[
        "aat:300008798"
    ]
},
  "bbox": [],
  "geometry": {"coordinates":[-106.9,35.0167],"type":"Point"}
}
=======
{"geometry":{"type":"Point","coordinates":[-106.900000,35.016700]},"type":"Feature","properties":{"hierarchy":["tgn:2250672","tgn:1000001","tgn:2001428","tgn:7012149","tgn:7007566","tgn:7029392"],"placetype":["aat:300008798"],"id":2250672,"name:xx":"Colorado, Cerro"}}
>>>>>>> 03f74aca74312dbeaf24d7e61306dd6a786dc3d0
