{
  "id": 2684274,
  "type": "Feature",
  "properties": {
    "tgn:hierarchy":[
        "tgn:2684274",
        "tgn:1000001",
        "tgn:7012149",
        "tgn:7007157",
        "tgn:1002956",
        "tgn:7029392"
    ],
    "tgn:id":2684274,
    "tgn:name":"Sphinx Crest",
    "tgn:placetype":[
        "aat:300266640"
    ]
},
  "bbox": [],
  "geometry": {"coordinates":[-118.5333,36.7167],"type":"Point"}
}