{
  "id": 2447569,
  "type": "Feature",
  "properties": {
    "tgn:hierarchy":[
        "tgn:2447569",
        "tgn:7002659",
        "tgn:1000001",
        "tgn:7012149",
        "tgn:2000035",
        "tgn:7029392"
    ],
    "tgn:id":2447569,
    "tgn:name":"Lick Fork Cave",
    "tgn:placetype":[
        "aat:300008746"
    ]
},
  "bbox": [],
  "geometry": {"coordinates":[-86.2833,34.9167],"type":"Point"}
}