{
  "id": 7552980,
  "type": "Feature",
  "properties": {
    "tgn:hierarchy":[
        "tgn:7552980",
        "tgn:1000004",
        "tgn:7000198",
        "tgn:1001977",
        "tgn:7029392"
    ],
    "tgn:id":7552980,
    "tgn:name:en":"Mar\u0101gh\u0101t Tea Garden",
    "tgn:placetype":[
        "aat:300387502"
    ]
},
  "bbox": [],
  "geometry": {"coordinates":[89.05,26.783333],"type":"Point"}
}