{
  "id": 1104371,
  "type": "Feature",
  "properties": {
    "tgn:hierarchy":[
        "tgn:1104371",
        "tgn:1000004",
        "tgn:1001290",
        "tgn:1000111",
        "tgn:7029392"
    ],
    "tgn:id":1104371,
    "tgn:name":"Daheiding Shan",
    "tgn:placetype":[
        "aat:300008795"
    ]
},
  "bbox": [],
  "geometry": {"coordinates":[129.1667,47.9667],"type":"Point"}
}