{
  "id": 1077421,
  "type": "Feature",
  "properties": {
    "tgn:hierarchy":[
        "tgn:1077421",
        "tgn:1006410",
        "tgn:1009869",
        "tgn:1000004",
        "tgn:1001548",
        "tgn:1000116",
        "tgn:7029392"
    ],
    "tgn:id":1077421,
    "tgn:name":"Banggai",
    "tgn:placetype":[
        "aat:300008347"
    ]
},
  "bbox": [],
  "geometry": {"coordinates":[123.55,-1.5667],"type":"Point"}
}