{
  "id": 2157804,
  "type": "Feature",
  "properties": {
    "tgn:hierarchy":[
        "tgn:2157804",
        "tgn:1000001",
        "tgn:7016172",
        "tgn:7012149",
        "tgn:7029392"
    ],
    "tgn:id":2157804,
    "tgn:name":"Beaver Lake",
    "tgn:placetype":[
        "aat:300006191"
    ]
},
  "bbox": [],
  "geometry": {"coordinates":[-93.8333,36.4167],"type":"Point"}
}