<<<<<<< HEAD
{
  "id": 2157804,
  "type": "Feature",
  "properties": {
    "tgn:hierarchy":[
        "tgn:2157804",
        "tgn:1000001",
        "tgn:7016172",
        "tgn:7012149",
        "tgn:7029392"
    ],
    "tgn:id":2157804,
    "tgn:name":"Beaver Lake",
    "tgn:placetype":[
        "aat:300006191"
    ]
},
  "bbox": [],
  "geometry": {"coordinates":[-93.8333,36.4167],"type":"Point"}
}
=======
{"geometry":{"type":"Point","coordinates":[-93.833300,36.416700]},"type":"Feature","properties":{"hierarchy":["tgn:2157804","tgn:1000001","tgn:7016172","tgn:7012149","tgn:7029392"],"placetype":["aat:300006191"],"id":2157804,"name:xx":"Beaver Lake"}}
>>>>>>> 03f74aca74312dbeaf24d7e61306dd6a786dc3d0
