{
  "id": 7318776,
  "type": "Feature",
  "properties": {
    "tgn:hierarchy":[
        "tgn:7318776",
        "tgn:1001630",
        "tgn:1000049",
        "tgn:1000002",
        "tgn:7029392"
    ],
    "tgn:id":7318776,
    "tgn:name":"Bonete, Cerro",
    "tgn:placetype":[
        "aat:300008795"
    ]
},
  "bbox": [],
  "geometry": {"coordinates":[-70.366667,-27.716667],"type":"Point"}
}