{
  "id": 2623956,
  "type": "Feature",
  "properties": {
    "tgn:hierarchy":[
        "tgn:2623956",
        "tgn:1000001",
        "tgn:7012149",
        "tgn:2000359",
        "tgn:7007248",
        "tgn:7029392"
    ],
    "tgn:id":2623956,
    "tgn:name":"Rock Ford Branch",
    "tgn:placetype":[
        "aat:300008699"
    ]
},
  "bbox": [],
  "geometry": {"coordinates":[-83.4333,34.6333],"type":"Point"}
}