{
  "id": 1053613,
  "type": "Feature",
  "properties": {
    "tgn:hierarchy":[
        "tgn:1053613",
        "tgn:1000004",
        "tgn:7012255",
        "tgn:7006661",
        "tgn:7029392"
    ],
    "tgn:id":1053613,
    "tgn:name":"Dimitrovskoye",
    "tgn:placetype":[
        "aat:300008347"
    ]
},
  "bbox": [],
  "geometry": {"coordinates":[69.05,40.2667],"type":"Point"}
}