{
  "id": 7443403,
  "type": "Feature",
  "properties": {
    "tgn:hierarchy":[
        "tgn:7443403",
        "tgn:7002445",
        "tgn:1000003",
        "tgn:7008132",
        "tgn:7008591",
        "tgn:7029392"
    ],
    "tgn:id":7443403,
    "tgn:name:en":"Whelford",
    "tgn:placetype":[
        "aat:300008347"
    ]
},
  "bbox": [],
  "geometry": {"coordinates":[-1.75,51.683333],"type":"Point"}
}