{
  "id": 7335374,
  "type": "Feature",
  "properties": {
    "tgn:hierarchy":[
        "tgn:7335374",
        "tgn:7002811",
        "tgn:1000003",
        "tgn:7003837",
        "tgn:1000095",
        "tgn:7029392"
    ],
    "tgn:id":7335374,
    "tgn:name":"Fresnos, Arroyo de los",
    "tgn:placetype":[
        "aat:300266554",
        "aat:300008699"
    ]
},
  "bbox": [],
  "geometry": {"coordinates":[-6.05,39.733333],"type":"Point"}
}