{
  "id": 2085515,
  "type": "Feature",
  "properties": {
    "tgn:hierarchy":[
        "tgn:2085515",
        "tgn:1000001",
        "tgn:7012149",
        "tgn:1002636",
        "tgn:7007708",
        "tgn:7029392"
    ],
    "tgn:id":2085515,
    "tgn:name":"Shaw",
    "tgn:placetype":[
        "aat:300008347"
    ]
},
  "bbox": [],
  "geometry": {"coordinates":[-122.8667,44.8667],"type":"Point"}
}