{
  "id": 7316026,
  "type": "Feature",
  "properties": {
    "tgn:hierarchy":[
        "tgn:7316026",
        "tgn:1001699",
        "tgn:1000049",
        "tgn:1000002",
        "tgn:7029392"
    ],
    "tgn:id":7316026,
    "tgn:name":"Caunao",
    "tgn:placetype":[
        "aat:300008347"
    ]
},
  "bbox": [],
  "geometry": {"coordinates":[-72.233333,-40.133333],"type":"Point"}
}