{
  "id": 7541557,
  "type": "Feature",
  "properties": {
    "tgn:hierarchy":[
        "tgn:7541557",
        "tgn:7001242",
        "tgn:7016833",
        "tgn:7000123",
        "tgn:7029392"
    ],
    "tgn:id":7541557,
    "tgn:name:en":"Naj' Kawm Maj\u0101n\u012bn",
    "tgn:placetype":[
        "aat:300008347"
    ]
},
  "bbox": [],
  "geometry": {"coordinates":[32.062312,26.135116],"type":"Point"}
}