{
  "id": 2746963,
  "type": "Feature",
  "properties": {
    "tgn:hierarchy":[
        "tgn:2746963",
        "tgn:1000001",
        "tgn:2001944",
        "tgn:7012149",
        "tgn:7007826",
        "tgn:7029392"
    ],
    "tgn:id":2746963,
    "tgn:name":"Wagner Creek",
    "tgn:placetype":[
        "aat:300008706"
    ]
},
  "bbox": [],
  "geometry": {"coordinates":[-94.15,33.4667],"type":"Point"}
}