{
  "id": 2141175,
  "type": "Feature",
  "properties": {
    "tgn:hierarchy":[
        "tgn:2141175",
        "tgn:1000001",
        "tgn:7012149",
        "tgn:2001712",
        "tgn:7007708",
        "tgn:7029392"
    ],
    "tgn:id":2141175,
    "tgn:name":"Axehandle Spring",
    "tgn:placetype":[
        "aat:300008697"
    ]
},
  "bbox": [],
  "geometry": {"coordinates":[-120.65,44.7333],"type":"Point"}
}