{
  "id": 7413024,
  "type": "Feature",
  "properties": {
    "tgn:hierarchy":[
        "tgn:7413024",
        "tgn:7005580",
        "tgn:1000001",
        "tgn:7005560",
        "tgn:7029392"
    ],
    "tgn:id":7413024,
    "tgn:name":"Toshib, R\u00edo",
    "tgn:placetype":[
        "aat:300008699"
    ]
},
  "bbox": [],
  "geometry": {"coordinates":[-92.433333,16.916667],"type":"Point"}
}