{
  "id": 7319407,
  "type": "Feature",
  "properties": {
    "tgn:hierarchy":[
        "tgn:7319407",
        "tgn:7002464",
        "tgn:1000049",
        "tgn:1000002",
        "tgn:7029392"
    ],
    "tgn:id":7319407,
    "tgn:name":"Amaculla, Cerro",
    "tgn:placetype":[
        "aat:300008795"
    ]
},
  "bbox": [],
  "geometry": {"coordinates":[-68.866667,-21.016667],"type":"Point"}
}