{
  "id": 7278648,
  "type": "Feature",
  "properties": {
    "tgn:hierarchy":[
        "tgn:7278648",
        "tgn:1001699",
        "tgn:1000049",
        "tgn:1000002",
        "tgn:7029392"
    ],
    "tgn:id":7278648,
    "tgn:name":"Falsa, Isla",
    "tgn:placetype":[
        "aat:300008791"
    ]
},
  "bbox": [],
  "geometry": {"coordinates":[-73.736111,-43.883889],"type":"Point"}
}