{
  "id": 7557811,
  "type": "Feature",
  "properties": {
    "tgn:hierarchy":[
        "tgn:7557811",
        "tgn:1000004",
        "tgn:7000198",
        "tgn:1001894",
        "tgn:7029392"
    ],
    "tgn:id":7557811,
    "tgn:name:en":"Porsa",
    "tgn:placetype":[
        "aat:300008347"
    ]
},
  "bbox": [],
  "geometry": {"coordinates":[78.370846,26.673243],"type":"Point"}
}