{
  "id": 7420038,
  "type": "Feature",
  "properties": {
    "tgn:hierarchy":[
        "tgn:7420038",
        "tgn:7005584",
        "tgn:1000001",
        "tgn:7005560",
        "tgn:7029392"
    ],
    "tgn:id":7420038,
    "tgn:name":"El Tequesquite",
    "tgn:placetype":[
        "aat:300008347"
    ]
},
  "bbox": [],
  "geometry": {"coordinates":[-100.130556,21.578333],"type":"Point"}
}