{
  "id": 1022785,
  "type": "Feature",
  "properties": {
    "tgn:hierarchy":[
        "tgn:1022785",
        "tgn:7006246",
        "tgn:1000047",
        "tgn:7002455",
        "tgn:1000002",
        "tgn:7029392"
    ],
    "tgn:id":1022785,
    "tgn:name":"S\u00e3o Francisco do Maranh\u00e3o",
    "tgn:placetype":[
        "aat:300008347"
    ]
},
  "bbox": [],
  "geometry": {"coordinates":[-42.9167,-6.25],"type":"Point"}
}