{
  "id": 7504001,
  "type": "Feature",
  "properties": {
    "tgn:hierarchy":[
        "tgn:7504001",
        "tgn:1009227",
        "tgn:1000226",
        "tgn:7016822",
        "tgn:1000006",
        "tgn:7029392"
    ],
    "tgn:id":7504001,
    "tgn:name:en":"Western Harbour",
    "tgn:placetype":[
        "aat:300132316"
    ]
},
  "bbox": [],
  "geometry": {"coordinates":[165.916667,-50.833333],"type":"Point"}
}