{
  "id": 7019279,
  "type": "Feature",
  "properties": {
    "tgn:hierarchy":[
        "tgn:7019279",
        "tgn:1000001",
        "tgn:2001430",
        "tgn:7012149",
        "tgn:7007566",
        "tgn:7029392"
    ],
    "tgn:id":7019279,
    "tgn:name":"Teel Canyon",
    "tgn:placetype":[
        "aat:300008761"
    ]
},
  "bbox": [],
  "geometry": {"coordinates":[-105.25,33.0333],"type":"Point"}
}