{
  "id": 2360481,
  "type": "Feature",
  "properties": {
    "tgn:hierarchy":[
        "tgn:2360481",
        "tgn:1000001",
        "tgn:2001583",
        "tgn:7012149",
        "tgn:7007705",
        "tgn:7029392"
    ],
    "tgn:id":2360481,
    "tgn:name":"Grassy Butte",
    "tgn:placetype":[
        "aat:300008798"
    ]
},
  "bbox": [],
  "geometry": {"coordinates":[-103.2333,47.3833],"type":"Point"}
}