{
  "id": 7486072,
  "type": "Feature",
  "properties": {
    "tgn:hierarchy":[
        "tgn:7486072",
        "tgn:1000004",
        "tgn:7001013",
        "tgn:1000141",
        "tgn:7029392"
    ],
    "tgn:id":7486072,
    "tgn:name":"Lala Xi",
    "tgn:placetype":[
        "aat:300008699"
    ]
},
  "bbox": [],
  "geometry": {"coordinates":[121.383333,24.696944],"type":"Point"}
}