{
  "id": 2758642,
  "type": "Feature",
  "properties": {
    "tgn:hierarchy":[
        "tgn:2758642",
        "tgn:1000001",
        "tgn:2001094",
        "tgn:7012149",
        "tgn:7007522",
        "tgn:7029392"
    ],
    "tgn:id":2758642,
    "tgn:name":"West Creek",
    "tgn:placetype":[
        "aat:300008706"
    ]
},
  "bbox": [],
  "geometry": {"coordinates":[-89.05,34.0167],"type":"Point"}
}