{
  "id": 7200320,
  "type": "Feature",
  "properties": {
    "tgn:hierarchy":[
        "tgn:7200320",
        "tgn:1000003",
        "tgn:7003688",
        "tgn:7000084",
        "tgn:7029392"
    ],
    "tgn:id":7200320,
    "tgn:name":"Drandersumkoog",
    "tgn:placetype":[
        "aat:300006163"
    ]
},
  "bbox": [],
  "geometry": {"coordinates":[9.05,54.383333],"type":"Point"}
}