<<<<<<< HEAD
{
  "id": 2764509,
  "type": "Feature",
  "properties": {
    "tgn:hierarchy":[
        "tgn:2764509",
        "tgn:1000001",
        "tgn:7012149",
        "tgn:2001488",
        "tgn:7007709",
        "tgn:7029392"
    ],
    "tgn:id":2764509,
    "tgn:name":"Whipping Creek Lake",
    "tgn:placetype":[
        "aat:300008680"
    ]
},
  "bbox": [],
  "geometry": {"coordinates":[-75.9667,35.6833],"type":"Point"}
}
=======
{"geometry":{"type":"Point","coordinates":[-75.966700,35.683300]},"type":"Feature","properties":{"hierarchy":["tgn:2764509","tgn:1000001","tgn:7012149","tgn:2001488","tgn:7007709","tgn:7029392"],"placetype":["aat:300008680"],"id":2764509,"name:xx":"Whipping Creek Lake"}}
>>>>>>> 03f74aca74312dbeaf24d7e61306dd6a786dc3d0
