{
  "id": 2764509,
  "type": "Feature",
  "properties": {
    "tgn:hierarchy":[
        "tgn:2764509",
        "tgn:1000001",
        "tgn:7012149",
        "tgn:2001488",
        "tgn:7007709",
        "tgn:7029392"
    ],
    "tgn:id":2764509,
    "tgn:name":"Whipping Creek Lake",
    "tgn:placetype":[
        "aat:300008680"
    ]
},
  "bbox": [],
  "geometry": {"coordinates":[-75.9667,35.6833],"type":"Point"}
}