{
  "id": 2344268,
  "type": "Feature",
  "properties": {
    "tgn:hierarchy":[
        "tgn:2344268",
        "tgn:1000001",
        "tgn:7012149",
        "tgn:2002114",
        "tgn:7007827",
        "tgn:7029392"
    ],
    "tgn:id":2344268,
    "tgn:name":"Gandy",
    "tgn:placetype":[
        "aat:300008347"
    ]
},
  "bbox": [],
  "geometry": {"coordinates":[-113.9667,39.45],"type":"Point"}
}