<<<<<<< HEAD
{
  "id": 2705877,
  "type": "Feature",
  "properties": {
    "tgn:hierarchy":[
        "tgn:2705877",
        "tgn:1000001",
        "tgn:7012149",
        "tgn:2001207",
        "tgn:7007523",
        "tgn:7029392"
    ],
    "tgn:id":2705877,
    "tgn:name":"Sutton Hollow",
    "tgn:placetype":[
        "aat:300008761"
    ]
},
  "bbox": [],
  "geometry": {"coordinates":[-90.7,37.3333],"type":"Point"}
}
=======
{"geometry":{"type":"Point","coordinates":[-90.700000,37.333300]},"type":"Feature","properties":{"hierarchy":["tgn:2705877","tgn:1000001","tgn:7012149","tgn:2001207","tgn:7007523","tgn:7029392"],"placetype":["aat:300008761"],"id":2705877,"name:xx":"Sutton Hollow"}}
>>>>>>> 03f74aca74312dbeaf24d7e61306dd6a786dc3d0
