{
  "id": 2282806,
  "type": "Feature",
  "properties": {
    "tgn:hierarchy":[
        "tgn:2282806",
        "tgn:1000001",
        "tgn:7012149",
        "tgn:2002327",
        "tgn:7007922",
        "tgn:7029392"
    ],
    "tgn:id":2282806,
    "tgn:name":"Deertail Lake",
    "tgn:placetype":[
        "aat:300008680"
    ]
},
  "bbox": [],
  "geometry": {"coordinates":[-90.0167,46.2333],"type":"Point"}
}