{
  "id": 7421160,
  "type": "Feature",
  "properties": {
    "tgn:hierarchy":[
        "tgn:7421160",
        "tgn:7005584",
        "tgn:1000001",
        "tgn:7005560",
        "tgn:7029392"
    ],
    "tgn:id":7421160,
    "tgn:name":"El Pirul",
    "tgn:placetype":[
        "aat:300008347"
    ]
},
  "bbox": [],
  "geometry": {"coordinates":[-101.251944,21.464722],"type":"Point"}
}