{
  "id": 2423693,
  "type": "Feature",
  "properties": {
    "tgn:hierarchy":[
        "tgn:2423693",
        "tgn:7006450",
        "tgn:1000001",
        "tgn:7012149",
        "tgn:2124002",
        "tgn:7029392"
    ],
    "tgn:id":2423693,
    "tgn:name":"John Rock",
    "tgn:placetype":[
        "aat:300008791"
    ]
},
  "bbox": [],
  "geometry": {"coordinates":[-135.45,56.7667],"type":"Point"}
}