<<<<<<< HEAD
{
  "id": 2157455,
  "type": "Feature",
  "properties": {
    "tgn:hierarchy":[
        "tgn:2157455",
        "tgn:2001728",
        "tgn:1000001",
        "tgn:7012149",
        "tgn:7007712",
        "tgn:7029392"
    ],
    "tgn:id":2157455,
    "tgn:name":"Beaver Creek",
    "tgn:placetype":[
        "aat:300008347"
    ]
},
  "bbox": [],
  "geometry": {"coordinates":[-82.6167,34.5833],"type":"Point"}
}
=======
{"geometry":{"type":"Point","coordinates":[-82.616700,34.583300]},"type":"Feature","properties":{"hierarchy":["tgn:2157455","tgn:2001728","tgn:1000001","tgn:7012149","tgn:7007712","tgn:7029392"],"placetype":["aat:300008347"],"id":2157455,"name:xx":"Beaver Creek"}}
>>>>>>> 03f74aca74312dbeaf24d7e61306dd6a786dc3d0
