{
  "id": 2552011,
  "type": "Feature",
  "properties": {
    "tgn:hierarchy":[
        "tgn:2552011",
        "tgn:1000001",
        "tgn:7012149",
        "tgn:2002347",
        "tgn:7007922",
        "tgn:7029392"
    ],
    "tgn:id":2552011,
    "tgn:name":"Number Four, Ditch",
    "tgn:placetype":[
        "aat:300006075"
    ]
},
  "bbox": [],
  "geometry": {"coordinates":[-89.5833,44.3333],"type":"Point"}
}