<<<<<<< HEAD
{
  "id": 2332033,
  "type": "Feature",
  "properties": {
    "tgn:hierarchy":[
        "tgn:2332033",
        "tgn:1000001",
        "tgn:2002109",
        "tgn:7012149",
        "tgn:7007827",
        "tgn:7029392"
    ],
    "tgn:id":2332033,
    "tgn:name":"Flint Cove",
    "tgn:placetype":[
        "aat:300008761"
    ]
},
  "bbox": [],
  "geometry": {"coordinates":[-110.1,38.1],"type":"Point"}
}
=======
{"geometry":{"type":"Point","coordinates":[-110.100000,38.100000]},"type":"Feature","properties":{"hierarchy":["tgn:2332033","tgn:1000001","tgn:2002109","tgn:7012149","tgn:7007827","tgn:7029392"],"placetype":["aat:300008761"],"id":2332033,"name:xx":"Flint Cove"}}
>>>>>>> 03f74aca74312dbeaf24d7e61306dd6a786dc3d0
