{
  "id": 2557264,
  "type": "Feature",
  "properties": {
    "tgn:hierarchy":[
        "tgn:2557264",
        "tgn:1000001",
        "tgn:2001350",
        "tgn:7012149",
        "tgn:7007525",
        "tgn:7029392"
    ],
    "tgn:id":2557264,
    "tgn:name":"Old Lady Beam Hill",
    "tgn:placetype":[
        "aat:300008798"
    ]
},
  "bbox": [],
  "geometry": {"coordinates":[-102.3667,41.7333],"type":"Point"}
}