{
  "id": 6004995,
  "type": "Feature",
  "properties": {
    "tgn:hierarchy":[
        "tgn:6004995",
        "tgn:7003139",
        "tgn:1000003",
        "tgn:7003080",
        "tgn:1000080",
        "tgn:7029392"
    ],
    "tgn:id":6004995,
    "tgn:name":"Rinaldone",
    "tgn:placetype":[
        "aat:300019276",
        "aat:300008347",
        "aat:300000810",
        "aat:300167671",
        "aat:300391489"
    ]
},
  "bbox": [],
  "geometry": {"coordinates":[12.085304,42.45918],"type":"Point"}
}