{
  "id": 7339403,
  "type": "Feature",
  "properties": {
    "tgn:hierarchy":[
        "tgn:7339403",
        "tgn:7002847",
        "tgn:1001647",
        "tgn:1000003",
        "tgn:1000095",
        "tgn:7029392"
    ],
    "tgn:id":7339403,
    "tgn:name":"Congosto, Boca del",
    "tgn:placetype":[
        "aat:300259572"
    ]
},
  "bbox": [],
  "geometry": {"coordinates":[-3.833333,39.466667],"type":"Point"}
}