{
  "id": 2457267,
  "type": "Feature",
  "properties": {
    "tgn:hierarchy":[
        "tgn:2457267",
        "tgn:1000001",
        "tgn:7012149",
        "tgn:2001516",
        "tgn:7007709",
        "tgn:7029392"
    ],
    "tgn:id":2457267,
    "tgn:name":"Little Laurel Creek",
    "tgn:placetype":[
        "aat:300008706"
    ]
},
  "bbox": [],
  "geometry": {"coordinates":[-82.7167,36.0167],"type":"Point"}
}