{
  "id": 7049842,
  "type": "Feature",
  "properties": {
    "tgn:hierarchy":[
        "tgn:7049842",
        "tgn:7009084",
        "tgn:7004154",
        "tgn:1000003",
        "tgn:1000080",
        "tgn:7029392"
    ],
    "tgn:id":7049842,
    "tgn:name":"Cardito, Monte",
    "tgn:placetype":[
        "aat:300008795"
    ]
},
  "bbox": [],
  "geometry": {"coordinates":[13.35,42.566667],"type":"Point"}
}