{
  "id": 2132650,
  "type": "Feature",
  "properties": {
    "tgn:hierarchy":[
        "tgn:2132650",
        "tgn:1000001",
        "tgn:7012149",
        "tgn:7007157",
        "tgn:1002608",
        "tgn:7029392"
    ],
    "tgn:id":2132650,
    "tgn:name":"Anaverde Creek",
    "tgn:placetype":[
        "aat:300008706"
    ]
},
  "bbox": [],
  "geometry": {"coordinates":[-118.2333,34.5333],"type":"Point"}
}