{
  "id": 2202003,
  "type": "Feature",
  "properties": {
    "tgn:hierarchy":[
        "tgn:2202003",
        "tgn:1000001",
        "tgn:7012149",
        "tgn:7007157",
        "tgn:7029392"
    ],
    "tgn:id":2202003,
    "tgn:name":"Buck Island",
    "tgn:placetype":[
        "aat:300008791"
    ]
},
  "bbox": [],
  "geometry": {"coordinates":[-122.3667,38.9167],"type":"Point"}
}