{
  "id": 7589705,
  "type": "Feature",
  "properties": {
    "tgn:hierarchy":[
        "tgn:7589705",
        "tgn:1000004",
        "tgn:7000198",
        "tgn:7000799",
        "tgn:7029392"
    ],
    "tgn:id":7589705,
    "tgn:name:en":"Potha Gala",
    "tgn:placetype":[
        "aat:300008347"
    ]
},
  "bbox": [],
  "geometry": {"coordinates":[74.475,33.147222],"type":"Point"}
}