{
  "id": 7288937,
  "type": "Feature",
  "properties": {
    "tgn:hierarchy":[
        "tgn:7288937",
        "tgn:1001695",
        "tgn:1000049",
        "tgn:1000002",
        "tgn:7029392"
    ],
    "tgn:id":7288937,
    "tgn:name":"La Guarena, Quebrada",
    "tgn:placetype":[
        "aat:300008699"
    ]
},
  "bbox": [],
  "geometry": {"coordinates":[-71.516667,-34.75],"type":"Point"}
}