{
  "id": 7349672,
  "type": "Feature",
  "properties": {
    "tgn:hierarchy":[
        "tgn:7349672",
        "tgn:7005584",
        "tgn:1000001",
        "tgn:7005560",
        "tgn:7029392"
    ],
    "tgn:id":7349672,
    "tgn:name":"Ac\u00e1mbaro",
    "tgn:placetype":[
        "aat:300007783"
    ]
},
  "bbox": [],
  "geometry": {"coordinates":[-100.716667,20.033333],"type":"Point"}
}