<<<<<<< HEAD
{
  "id": 7029893,
  "type": "Feature",
  "properties": {
    "tgn:hierarchy":[
        "tgn:7029893",
        "tgn:7002445",
        "tgn:1000003",
        "tgn:7008166",
        "tgn:7008591",
        "tgn:7029392"
    ],
    "tgn:id":7029893,
    "tgn:name":"Brearton",
    "tgn:placetype":[
        "aat:300008347",
        "aat:300008372"
    ]
},
  "bbox": [],
  "geometry": {"coordinates":[-1.508,54.034],"type":"Point"}
}
=======
{"geometry":{"type":"Point","coordinates":[-1.508000,54.034000]},"type":"Feature","properties":{"hierarchy":["tgn:7029893","tgn:7002445","tgn:1000003","tgn:7008166","tgn:7008591","tgn:7029392"],"placetype":["aat:300008347","aat:300008372"],"id":7029893,"name:xx":"Brearton"}}
>>>>>>> 03f74aca74312dbeaf24d7e61306dd6a786dc3d0
