{
  "id": 7464617,
  "type": "Feature",
  "properties": {
    "tgn:hierarchy":[
        "tgn:7464617",
        "tgn:7002444",
        "tgn:1000003",
        "tgn:7008082",
        "tgn:7008591",
        "tgn:7029392"
    ],
    "tgn:id":7464617,
    "tgn:name:en":"Braeriach",
    "tgn:placetype":[
        "aat:300008795"
    ]
},
  "bbox": [],
  "geometry": {"coordinates":[-3.716667,57.066667],"type":"Point"}
}