{
  "id": 2577264,
  "type": "Feature",
  "properties": {
    "tgn:hierarchy":[
        "tgn:2577264",
        "tgn:7006450",
        "tgn:1000001",
        "tgn:7012149",
        "tgn:2124005",
        "tgn:7029392"
    ],
    "tgn:id":2577264,
    "tgn:name":"Peters Glacier",
    "tgn:placetype":[
        "aat:300008835"
    ]
},
  "bbox": [],
  "geometry": {"coordinates":[-144.95,69.2667],"type":"Point"}
}