{
  "id": 2433536,
  "type": "Feature",
  "properties": {
    "tgn:hierarchy":[
        "tgn:2433536",
        "tgn:1000001",
        "tgn:7012149",
        "tgn:7007157",
        "tgn:7029392"
    ],
    "tgn:id":2433536,
    "tgn:name":"Kelly Bar",
    "tgn:placetype":[
        "aat:300132348"
    ]
},
  "bbox": [],
  "geometry": {"coordinates":[-121.05,39.5167],"type":"Point"}
}