{
  "id": 2735693,
  "type": "Feature",
  "properties": {
    "tgn:hierarchy":[
        "tgn:2735693",
        "tgn:1000001",
        "tgn:1002347",
        "tgn:7012149",
        "tgn:7007568",
        "tgn:7029392"
    ],
    "tgn:id":2735693,
    "tgn:name":"Twin Island Lake",
    "tgn:placetype":[
        "aat:300008680"
    ]
},
  "bbox": [],
  "geometry": {"coordinates":[-73.6667,41.9667],"type":"Point"}
}