{
  "id": 2682111,
  "type": "Feature",
  "properties": {
    "tgn:hierarchy":[
        "tgn:2682111",
        "tgn:1000001",
        "tgn:7012149",
        "tgn:2002100",
        "tgn:7007826",
        "tgn:7029392"
    ],
    "tgn:id":2682111,
    "tgn:name":"South Tank",
    "tgn:placetype":[
        "aat:300006191"
    ]
},
  "bbox": [],
  "geometry": {"coordinates":[-99.5667,28.75],"type":"Point"}
}