{
  "id": 2416036,
  "type": "Feature",
  "properties": {
    "tgn:hierarchy":[
        "tgn:2416036",
        "tgn:1000001",
        "tgn:2001411",
        "tgn:7012149",
        "tgn:7007526",
        "tgn:7029392"
    ],
    "tgn:id":2416036,
    "tgn:name":"Ivy Wilson Mine",
    "tgn:placetype":[
        "aat:300000390"
    ]
},
  "bbox": [],
  "geometry": {"coordinates":[-114.8333,41.7333],"type":"Point"}
}