{
  "id": 1006339,
  "type": "Feature",
  "properties": {
    "tgn:hierarchy":[
        "tgn:1006339",
        "tgn:1000001",
        "tgn:7012149",
        "tgn:1002251",
        "tgn:7007826",
        "tgn:7029392"
    ],
    "tgn:id":1006339,
    "tgn:name":"Atkinson Island",
    "tgn:placetype":[
        "aat:300008791"
    ]
},
  "bbox": [],
  "geometry": {"coordinates":[-94.9667,29.65],"type":"Point"}
}