{
  "id": 2618146,
  "type": "Feature",
  "properties": {
    "tgn:hierarchy":[
        "tgn:2618146",
        "tgn:1000001",
        "tgn:7012149",
        "tgn:2002060",
        "tgn:7007826",
        "tgn:7029392"
    ],
    "tgn:id":2618146,
    "tgn:name":"Riemer Creek",
    "tgn:placetype":[
        "aat:300008706"
    ]
},
  "bbox": [],
  "geometry": {"coordinates":[-99.7333,29.85],"type":"Point"}
}