{
  "id": 2687036,
  "type": "Feature",
  "properties": {
    "tgn:hierarchy":[
        "tgn:2687036",
        "tgn:1000001",
        "tgn:7012149",
        "tgn:2002248",
        "tgn:7007920",
        "tgn:7029392"
    ],
    "tgn:id":2687036,
    "tgn:name":"Spring Heel Creek",
    "tgn:placetype":[
        "aat:300008706"
    ]
},
  "bbox": [],
  "geometry": {"coordinates":[-117.3667,48.1333],"type":"Point"}
}