{
  "id": 7591809,
  "type": "Feature",
  "properties": {
    "tgn:hierarchy":[
        "tgn:7591809",
        "tgn:1000004",
        "tgn:7000198",
        "tgn:7000799",
        "tgn:7029392"
    ],
    "tgn:id":7591809,
    "tgn:name:en":"Gura",
    "tgn:placetype":[
        "aat:300008347"
    ]
},
  "bbox": [],
  "geometry": {"coordinates":[74.770323,32.925957],"type":"Point"}
}