<<<<<<< HEAD
{
  "id": 7378758,
  "type": "Feature",
  "properties": {
    "tgn:hierarchy":[
        "tgn:7378758",
        "tgn:7005581",
        "tgn:1000001",
        "tgn:7005560",
        "tgn:7029392"
    ],
    "tgn:id":7378758,
    "tgn:name":"Rancho Los Pozos",
    "tgn:placetype":[
        "aat:300000241"
    ]
},
  "bbox": [],
  "geometry": {"coordinates":[-104.716667,27.583333],"type":"Point"}
}
=======
{"geometry":{"type":"Point","coordinates":[-104.716667,27.583333]},"type":"Feature","properties":{"hierarchy":["tgn:7378758","tgn:7005581","tgn:1000001","tgn:7005560","tgn:7029392"],"placetype":["aat:300000241"],"id":7378758,"name:xx":"Rancho Los Pozos"}}
>>>>>>> 03f74aca74312dbeaf24d7e61306dd6a786dc3d0
