{
  "id": 7413177,
  "type": "Feature",
  "properties": {
    "tgn:hierarchy":[
        "tgn:7413177",
        "tgn:1000001",
        "tgn:7005596",
        "tgn:7005560",
        "tgn:7029392"
    ],
    "tgn:id":7413177,
    "tgn:name:es":"Santa Elena, Isla",
    "tgn:placetype":[
        "aat:300008791"
    ]
},
  "bbox": [],
  "geometry": {"coordinates":[-91.441667,17.55],"type":"Point"}
}