{
  "id": 2380353,
  "type": "Feature",
  "properties": {
    "tgn:hierarchy":[
        "tgn:2380353",
        "tgn:1000001",
        "tgn:2000770",
        "tgn:7012149",
        "tgn:7007255",
        "tgn:7029392"
    ],
    "tgn:id":2380353,
    "tgn:name":"Hatton Branch",
    "tgn:placetype":[
        "aat:300008699"
    ]
},
  "bbox": [],
  "geometry": {"coordinates":[-82.6333,38.2667],"type":"Point"}
}