{
  "id": 7489383,
  "type": "Feature",
  "properties": {
    "tgn:hierarchy":[
        "tgn:7489383",
        "tgn:1000004",
        "tgn:7471332",
        "tgn:1000141",
        "tgn:7029392"
    ],
    "tgn:id":7489383,
    "tgn:name":"Neidaping",
    "tgn:placetype":[
        "aat:300008347"
    ]
},
  "bbox": [],
  "geometry": {"coordinates":[121.07,24.651389],"type":"Point"}
}