<<<<<<< HEAD
{
  "id": 7489383,
  "type": "Feature",
  "properties": {
    "tgn:hierarchy":[
        "tgn:7489383",
        "tgn:1000004",
        "tgn:7471332",
        "tgn:1000141",
        "tgn:7029392"
    ],
    "tgn:id":7489383,
    "tgn:name":"Neidaping",
    "tgn:placetype":[
        "aat:300008347"
    ]
},
  "bbox": [],
  "geometry": {"coordinates":[121.07,24.651389],"type":"Point"}
}
=======
{"geometry":{"type":"Point","coordinates":[121.070000,24.651389]},"type":"Feature","properties":{"hierarchy":["tgn:7489383","tgn:1000004","tgn:7471332","tgn:1000141","tgn:7029392"],"placetype":["aat:300008347"],"id":7489383,"name:xx":"Neidaping"}}
>>>>>>> 03f74aca74312dbeaf24d7e61306dd6a786dc3d0
