{
  "id": 7458553,
  "type": "Feature",
  "properties": {
    "tgn:hierarchy":[
        "tgn:7458553",
        "tgn:7002443",
        "tgn:1000003",
        "tgn:7018993",
        "tgn:7008591",
        "tgn:7029392"
    ],
    "tgn:id":7458553,
    "tgn:name:en":"Newport Bay",
    "tgn:placetype":[
        "aat:300132316"
    ]
},
  "bbox": [],
  "geometry": {"coordinates":[-4.866667,52.033333],"type":"Point"}
}