{
  "id": 7384368,
  "type": "Feature",
  "properties": {
    "tgn:hierarchy":[
        "tgn:7384368",
        "tgn:7016644",
        "tgn:1000001",
        "tgn:7005560",
        "tgn:7029392"
    ],
    "tgn:id":7384368,
    "tgn:name":"Ocotillo",
    "tgn:placetype":[
        "aat:300008347"
    ]
},
  "bbox": [],
  "geometry": {"coordinates":[-103.65,19.333333],"type":"Point"}
}