{
  "id": 2381555,
  "type": "Feature",
  "properties": {
    "tgn:hierarchy":[
        "tgn:2381555",
        "tgn:1000001",
        "tgn:2001786",
        "tgn:7012149",
        "tgn:7007713",
        "tgn:7029392"
    ],
    "tgn:id":2381555,
    "tgn:name":"Hay Draw",
    "tgn:placetype":[
        "aat:300008761"
    ]
},
  "bbox": [],
  "geometry": {"coordinates":[-103.8833,43.75],"type":"Point"}
}