{
  "id": 2682147,
  "type": "Feature",
  "properties": {
    "tgn:hierarchy":[
        "tgn:2682147",
        "tgn:1000001",
        "tgn:7012149",
        "tgn:2002351",
        "tgn:7007922",
        "tgn:7029392"
    ],
    "tgn:id":2682147,
    "tgn:name":"South Tiffany Creek",
    "tgn:placetype":[
        "aat:300008706"
    ]
},
  "bbox": [],
  "geometry": {"coordinates":[-92.2333,45.0167],"type":"Point"}
}