{
  "id": 1106785,
  "type": "Feature",
  "properties": {
    "tgn:hierarchy":[
        "tgn:1106785",
        "tgn:7002759",
        "tgn:1000003",
        "tgn:1000095",
        "tgn:7029392"
    ],
    "tgn:id":1106785,
    "tgn:name":"Pelada, Sierra",
    "tgn:placetype":[
        "aat:300008795"
    ]
},
  "bbox": [],
  "geometry": {"coordinates":[0.189187,42.713409],"type":"Point"}
}