{
  "id": 1054631,
  "type": "Feature",
  "properties": {
    "tgn:hierarchy":[
        "tgn:1054631",
        "tgn:1000004",
        "tgn:4008031",
        "tgn:7018214",
        "tgn:7002435",
        "tgn:7029392"
    ],
    "tgn:id":1054631,
    "tgn:name":"Yedrovo",
    "tgn:placetype":[
        "aat:300008347"
    ]
},
  "bbox": [],
  "geometry": {"coordinates":[33.6333,57.9167],"type":"Point"}
}