{
  "id": 2766762,
  "type": "Feature",
  "properties": {
    "tgn:hierarchy":[
        "tgn:2766762",
        "tgn:1000001",
        "tgn:7016172",
        "tgn:7012149",
        "tgn:2000129",
        "tgn:7029392"
    ],
    "tgn:id":2766762,
    "tgn:name":"White Oak Spring",
    "tgn:placetype":[
        "aat:300008697"
    ]
},
  "bbox": [],
  "geometry": {"coordinates":[-91.4667,36.4333],"type":"Point"}
}