{
  "id": 1021286,
  "type": "Feature",
  "properties": {
    "tgn:hierarchy":[
        "tgn:1021286",
        "tgn:7006257",
        "tgn:1000047",
        "tgn:7002455",
        "tgn:1000002",
        "tgn:7029392"
    ],
    "tgn:id":1021286,
    "tgn:name":"Cruzeta",
    "tgn:placetype":[
        "aat:300008347"
    ]
},
  "bbox": [],
  "geometry": {"coordinates":[-36.7833,-6.4167],"type":"Point"}
}