{
  "id": 7382869,
  "type": "Feature",
  "properties": {
    "tgn:hierarchy":[
        "tgn:7382869",
        "tgn:7005581",
        "tgn:1000001",
        "tgn:7005560",
        "tgn:7029392"
    ],
    "tgn:id":7382869,
    "tgn:name":"Mosco, Arroyo del",
    "tgn:placetype":[
        "aat:300008699"
    ]
},
  "bbox": [],
  "geometry": {"coordinates":[-107.216667,29.916667],"type":"Point"}
}