<<<<<<< HEAD
{
  "id": 7378431,
  "type": "Feature",
  "properties": {
    "tgn:hierarchy":[
        "tgn:7378431",
        "tgn:1000001",
        "tgn:7005597",
        "tgn:7005560",
        "tgn:7029392"
    ],
    "tgn:id":7378431,
    "tgn:name":"La Providencia",
    "tgn:placetype":[
        "aat:300008347"
    ]
},
  "bbox": [],
  "geometry": {"coordinates":[-97.433333,25.6],"type":"Point"}
}
=======
{"geometry":{"type":"Point","coordinates":[-97.433333,25.600000]},"type":"Feature","properties":{"hierarchy":["tgn:7378431","tgn:1000001","tgn:7005597","tgn:7005560","tgn:7029392"],"placetype":["aat:300008347"],"id":7378431,"name:xx":"La Providencia"}}
>>>>>>> 03f74aca74312dbeaf24d7e61306dd6a786dc3d0
