{
  "id": 2621121,
  "type": "Feature",
  "properties": {
    "tgn:hierarchy":[
        "tgn:2621121",
        "tgn:1000001",
        "tgn:7012149",
        "tgn:2002125",
        "tgn:7007827",
        "tgn:7029392"
    ],
    "tgn:id":2621121,
    "tgn:name":"Road Ridge",
    "tgn:placetype":[
        "aat:300266640"
    ]
},
  "bbox": [],
  "geometry": {"coordinates":[-111.0667,39.8667],"type":"Point"}
}