{
  "id": 7412517,
  "type": "Feature",
  "properties": {
    "tgn:hierarchy":[
        "tgn:7412517",
        "tgn:7005587",
        "tgn:1000001",
        "tgn:7005560",
        "tgn:7029392"
    ],
    "tgn:id":7412517,
    "tgn:name:es":"Coyutla",
    "tgn:placetype":[
        "aat:300008347"
    ]
},
  "bbox": [],
  "geometry": {"coordinates":[-98.845833,21.058333],"type":"Point"}
}