{
  "id": 7243709,
  "type": "Feature",
  "properties": {
    "tgn:hierarchy":[
        "tgn:7243709",
        "tgn:7003466",
        "tgn:1000003",
        "tgn:1000063",
        "tgn:4012014",
        "tgn:7029392"
    ],
    "tgn:id":7243709,
    "tgn:name":"Houx",
    "tgn:placetype":[
        "aat:300008347"
    ]
},
  "bbox": [],
  "geometry": {"coordinates":[4.89882,50.302795],"type":"Point"}
}