{
  "id": 1057330,
  "type": "Feature",
  "properties": {
    "tgn:hierarchy":[
        "tgn:1057330",
        "tgn:1000004",
        "tgn:7011590",
        "tgn:7018214",
        "tgn:7002435",
        "tgn:7029392"
    ],
    "tgn:id":1057330,
    "tgn:name":"Naumovshchina",
    "tgn:placetype":[
        "aat:300008347"
    ]
},
  "bbox": [],
  "geometry": {"coordinates":[28.3333,58.3833],"type":"Point"}
}