{
  "id": 7291732,
  "type": "Feature",
  "properties": {
    "tgn:hierarchy":[
        "tgn:7291732",
        "tgn:1001695",
        "tgn:1000049",
        "tgn:1000002",
        "tgn:7029392"
    ],
    "tgn:id":7291732,
    "tgn:name":"El Planch\u00f3n",
    "tgn:placetype":[
        "aat:300008777"
    ]
},
  "bbox": [],
  "geometry": {"coordinates":[-71.966667,-34.366667],"type":"Point"}
}