{
  "id": 2165262,
  "type": "Feature",
  "properties": {
    "tgn:hierarchy":[
        "tgn:2165262",
        "tgn:1000001",
        "tgn:7012149",
        "tgn:7007251",
        "tgn:7029392"
    ],
    "tgn:id":2165262,
    "tgn:name":"Bettell Creek",
    "tgn:placetype":[
        "aat:300008706"
    ]
},
  "bbox": [],
  "geometry": {"coordinates":[-90.6667,39.4667],"type":"Point"}
}