{
  "id": 2395807,
  "type": "Feature",
  "properties": {
    "tgn:hierarchy":[
        "tgn:2395807",
        "tgn:7002659",
        "tgn:1000001",
        "tgn:7012149",
        "tgn:2000038",
        "tgn:7029392"
    ],
    "tgn:id":2395807,
    "tgn:name":"Holloway",
    "tgn:placetype":[
        "aat:300008347"
    ]
},
  "bbox": [],
  "geometry": {"coordinates":[-87.5333,34.8833],"type":"Point"}
}