<<<<<<< HEAD
{
  "id": 2403664,
  "type": "Feature",
  "properties": {
    "tgn:hierarchy":[
        "tgn:2403664",
        "tgn:1000001",
        "tgn:7014423",
        "tgn:7012149",
        "tgn:7007517",
        "tgn:7029392"
    ],
    "tgn:id":2403664,
    "tgn:name":"Howard Island",
    "tgn:placetype":[
        "aat:300008791"
    ]
},
  "bbox": [],
  "geometry": {"coordinates":[-70.85,42.0],"type":"Point"}
}
=======
{"geometry":{"type":"Point","coordinates":[-70.850000,42.000000]},"type":"Feature","properties":{"hierarchy":["tgn:2403664","tgn:1000001","tgn:7014423","tgn:7012149","tgn:7007517","tgn:7029392"],"placetype":["aat:300008791"],"id":2403664,"name:xx":"Howard Island"}}
>>>>>>> 03f74aca74312dbeaf24d7e61306dd6a786dc3d0
