<<<<<<< HEAD
{
  "id": 7489281,
  "type": "Feature",
  "properties": {
    "tgn:hierarchy":[
        "tgn:7489281",
        "tgn:7001004",
        "tgn:1000004",
        "tgn:1000141",
        "tgn:7029392"
    ],
    "tgn:id":7489281,
    "tgn:name":"Neinan Cun",
    "tgn:placetype":[
        "aat:300387173"
    ]
},
  "bbox": [],
  "geometry": {"coordinates":[120.454444,22.906389],"type":"Point"}
}
=======
{"geometry":{"type":"Point","coordinates":[120.454444,22.906389]},"type":"Feature","properties":{"hierarchy":["tgn:7489281","tgn:7001004","tgn:1000004","tgn:1000141","tgn:7029392"],"placetype":["aat:300387173"],"id":7489281,"name:xx":"Neinan Cun"}}
>>>>>>> 03f74aca74312dbeaf24d7e61306dd6a786dc3d0
