<<<<<<< HEAD
{
  "id": 2254396,
  "type": "Feature",
  "properties": {
    "tgn:hierarchy":[
        "tgn:2254396",
        "tgn:1000001",
        "tgn:7012149",
        "tgn:2001214",
        "tgn:7007523",
        "tgn:7029392"
    ],
    "tgn:id":2254396,
    "tgn:name":"Coon Creek",
    "tgn:placetype":[
        "aat:300008706"
    ]
},
  "bbox": [],
  "geometry": {"coordinates":[-93.3167,39.95],"type":"Point"}
}
=======
{"geometry":{"type":"Point","coordinates":[-93.316700,39.950000]},"type":"Feature","properties":{"hierarchy":["tgn:2254396","tgn:1000001","tgn:7012149","tgn:2001214","tgn:7007523","tgn:7029392"],"placetype":["aat:300008706"],"id":2254396,"name:xx":"Coon Creek"}}
>>>>>>> 03f74aca74312dbeaf24d7e61306dd6a786dc3d0
