{
  "id": 7481690,
  "type": "Feature",
  "properties": {
    "tgn:hierarchy":[
        "tgn:7481690",
        "tgn:1000004",
        "tgn:7471332",
        "tgn:1000141",
        "tgn:7029392"
    ],
    "tgn:id":7481690,
    "tgn:name":"Tunyeshengtai Shan",
    "tgn:placetype":[
        "aat:300387002"
    ]
},
  "bbox": [],
  "geometry": {"coordinates":[121.271944,24.6225],"type":"Point"}
}