{
  "id": 7551325,
  "type": "Feature",
  "properties": {
    "tgn:hierarchy":[
        "tgn:7551325",
        "tgn:1000004",
        "tgn:7000198",
        "tgn:1001882",
        "tgn:7029392"
    ],
    "tgn:id":7551325,
    "tgn:name:en":"Dodda Magge",
    "tgn:placetype":[
        "aat:300008347"
    ]
},
  "bbox": [],
  "geometry": {"coordinates":[76.084167,12.690833],"type":"Point"}
}