{
  "id": 2388645,
  "type": "Feature",
  "properties": {
    "tgn:hierarchy":[
        "tgn:2388645",
        "tgn:1000001",
        "tgn:1002219",
        "tgn:7012149",
        "tgn:7007157",
        "tgn:7029392"
    ],
    "tgn:id":2388645,
    "tgn:name":"Hicks Spring",
    "tgn:placetype":[
        "aat:300008697"
    ]
},
  "bbox": [],
  "geometry": {"coordinates":[-120.65,37.9833],"type":"Point"}
}