{
  "id": 7547711,
  "type": "Feature",
  "properties": {
    "tgn:hierarchy":[
        "tgn:7547711",
        "tgn:1000004",
        "tgn:7000198",
        "tgn:7031783",
        "tgn:7029392"
    ],
    "tgn:id":7547711,
    "tgn:name:en":"Aiyar",
    "tgn:placetype":[
        "aat:300008347"
    ]
},
  "bbox": [],
  "geometry": {"coordinates":[85.754899,23.707543],"type":"Point"}
}