{
  "id": 2249591,
  "type": "Feature",
  "properties": {
    "tgn:hierarchy":[
        "tgn:2249591",
        "tgn:1000001",
        "tgn:7012149",
        "tgn:7007712",
        "tgn:7029392"
    ],
    "tgn:id":2249591,
    "tgn:name":"Coles Creek",
    "tgn:placetype":[
        "aat:300008706"
    ]
},
  "bbox": [],
  "geometry": {"coordinates":[-80.8667,32.4667],"type":"Point"}
}