{
  "id": 2555356,
  "type": "Feature",
  "properties": {
    "tgn:hierarchy":[
        "tgn:2555356",
        "tgn:1000001",
        "tgn:2001260",
        "tgn:7012149",
        "tgn:7007524",
        "tgn:7029392"
    ],
    "tgn:id":2555356,
    "tgn:name":"Odell Lake",
    "tgn:placetype":[
        "aat:300008680"
    ]
},
  "bbox": [],
  "geometry": {"coordinates":[-113.2167,45.5667],"type":"Point"}
}