{
  "id": 2431653,
  "type": "Feature",
  "properties": {
    "tgn:hierarchy":[
        "tgn:2431653",
        "tgn:1000001",
        "tgn:7012149",
        "tgn:1002983",
        "tgn:7007252",
        "tgn:7029392"
    ],
    "tgn:id":2431653,
    "tgn:name":"Kates Lake",
    "tgn:placetype":[
        "aat:300008680"
    ]
},
  "bbox": [],
  "geometry": {"coordinates":[-87.1833,40.3333],"type":"Point"}
}