{
  "id": 7566426,
  "type": "Feature",
  "properties": {
    "tgn:hierarchy":[
        "tgn:7566426",
        "tgn:1000004",
        "tgn:7000198",
        "tgn:7016722",
        "tgn:7029392"
    ],
    "tgn:id":7566426,
    "tgn:name:en":"Naw\u0101da Kachhw\u0101in",
    "tgn:placetype":[
        "aat:300008347"
    ]
},
  "bbox": [],
  "geometry": {"coordinates":[79.793784,26.715479],"type":"Point"}
}