{
  "id": 2633688,
  "type": "Feature",
  "properties": {
    "tgn:hierarchy":[
        "tgn:2633688",
        "tgn:1000001",
        "tgn:7012149",
        "tgn:7019014",
        "tgn:7007251",
        "tgn:7029392"
    ],
    "tgn:id":2633688,
    "tgn:name":"Rush Creek",
    "tgn:placetype":[
        "aat:300008706"
    ]
},
  "bbox": [],
  "geometry": {"coordinates":[-88.5667,42.3833],"type":"Point"}
}