{
  "id": 2364998,
  "type": "Feature",
  "properties": {
    "tgn:hierarchy":[
        "tgn:2364998",
        "tgn:1000001",
        "tgn:7012149",
        "tgn:7014589",
        "tgn:7007515",
        "tgn:7029392"
    ],
    "tgn:id":2364998,
    "tgn:name":"Greenland Cove",
    "tgn:placetype":[
        "aat:300132316"
    ]
},
  "bbox": [],
  "geometry": {"coordinates":[-67.95,45.0167],"type":"Point"}
}