{
  "id": 2136157,
  "type": "Feature",
  "properties": {
    "tgn:hierarchy":[
        "tgn:2136157",
        "tgn:1000001",
        "tgn:2001331",
        "tgn:7012149",
        "tgn:7007525",
        "tgn:7029392"
    ],
    "tgn:id":2136157,
    "tgn:name":"Arabia",
    "tgn:placetype":[
        "aat:300008347"
    ]
},
  "bbox": [],
  "geometry": {"coordinates":[-100.3667,42.7167],"type":"Point"}
}