{
  "id": 2720829,
  "type": "Feature",
  "properties": {
    "tgn:hierarchy":[
        "tgn:2720829",
        "tgn:1000001",
        "tgn:7012149",
        "tgn:7007522",
        "tgn:7029392"
    ],
    "tgn:id":2720829,
    "tgn:name":"Tick Creek",
    "tgn:placetype":[
        "aat:300008706"
    ]
},
  "bbox": [],
  "geometry": {"coordinates":[-89.5333,31.3833],"type":"Point"}
}