{
  "id": 2678917,
  "type": "Feature",
  "properties": {
    "tgn:hierarchy":[
        "tgn:2678917",
        "tgn:1000001",
        "tgn:7012149",
        "tgn:7007157",
        "tgn:1002957",
        "tgn:7029392"
    ],
    "tgn:id":2678917,
    "tgn:name":"South Fork Griswold Creek",
    "tgn:placetype":[
        "aat:300008706"
    ]
},
  "bbox": [],
  "geometry": {"coordinates":[-120.0833,38.2833],"type":"Point"}
}