{
  "id": 7275227,
  "type": "Feature",
  "properties": {
    "tgn:hierarchy":[
        "tgn:7275227",
        "tgn:7002464",
        "tgn:1000049",
        "tgn:1000002",
        "tgn:7029392"
    ],
    "tgn:id":7275227,
    "tgn:name":"Uni\u00f3n, Rocas",
    "tgn:placetype":[
        "aat:300011692"
    ]
},
  "bbox": [],
  "geometry": {"coordinates":[-70.15,-19.95],"type":"Point"}
}