{
  "id": 7333630,
  "type": "Feature",
  "properties": {
    "tgn:hierarchy":[
        "tgn:7333630",
        "tgn:7002815",
        "tgn:1000003",
        "tgn:7002793",
        "tgn:1000095",
        "tgn:7029392"
    ],
    "tgn:id":7333630,
    "tgn:name":"Espad\u00e1n, Sierra de",
    "tgn:placetype":[
        "aat:300008795"
    ]
},
  "bbox": [],
  "geometry": {"coordinates":[-0.416667,39.95],"type":"Point"}
}