{
  "id": 2277816,
  "type": "Feature",
  "properties": {
    "tgn:hierarchy":[
        "tgn:2277816",
        "tgn:1000001",
        "tgn:1002337",
        "tgn:7012149",
        "tgn:7007922",
        "tgn:7029392"
    ],
    "tgn:id":2277816,
    "tgn:name":"Dawson Creek",
    "tgn:placetype":[
        "aat:300008706"
    ]
},
  "bbox": [],
  "geometry": {"coordinates":[-88.4833,43.2167],"type":"Point"}
}