{
  "id": 2001976,
  "type": "Feature",
  "properties": {
    "tgn:hierarchy":[
        "tgn:2001976",
        "tgn:1000001",
        "tgn:7012149",
        "tgn:7007826",
        "tgn:7029392"
    ],
    "tgn:id":2001976,
    "tgn:name":"Donley",
    "tgn:placetype":[
        "aat:300387145",
        "aat:300000771"
    ]
},
  "bbox": [],
  "geometry": {"coordinates":[-100.8167,34.9667],"type":"Point"}
}