{
  "id": 2369435,
  "type": "Feature",
  "properties": {
    "tgn:hierarchy":[
        "tgn:2369435",
        "tgn:2001423",
        "tgn:1000001",
        "tgn:7012149",
        "tgn:7007564",
        "tgn:7029392"
    ],
    "tgn:id":2369435,
    "tgn:name":"Gun Island",
    "tgn:placetype":[
        "aat:300008791"
    ]
},
  "bbox": [],
  "geometry": {"coordinates":[-71.3167,43.6833],"type":"Point"}
}