{
  "id": 2289207,
  "type": "Feature",
  "properties": {
    "tgn:hierarchy":[
        "tgn:2289207",
        "tgn:1000001",
        "tgn:7012149",
        "tgn:2000828",
        "tgn:7007255",
        "tgn:7029392"
    ],
    "tgn:id":2289207,
    "tgn:name":"Dividing Ridge",
    "tgn:placetype":[
        "aat:300266640"
    ]
},
  "bbox": [],
  "geometry": {"coordinates":[-83.1667,37.85],"type":"Point"}
}