{
  "id": 7316948,
  "type": "Feature",
  "properties": {
    "tgn:hierarchy":[
        "tgn:7316948",
        "tgn:1001657",
        "tgn:1000049",
        "tgn:1000002",
        "tgn:7029392"
    ],
    "tgn:id":7316948,
    "tgn:name":"Cruz Grande, Caleta",
    "tgn:placetype":[
        "aat:300132317"
    ]
},
  "bbox": [],
  "geometry": {"coordinates":[-71.316667,-29.433333],"type":"Point"}
}