{
  "id": 2459752,
  "type": "Feature",
  "properties": {
    "tgn:hierarchy":[
        "tgn:2459752",
        "tgn:1000001",
        "tgn:7012149",
        "tgn:7007252",
        "tgn:7029392"
    ],
    "tgn:id":2459752,
    "tgn:name":"Little Richland Creek",
    "tgn:placetype":[
        "aat:300008706"
    ]
},
  "bbox": [],
  "geometry": {"coordinates":[-86.6333,39.15],"type":"Point"}
}