{
  "id": 2482493,
  "type": "Feature",
  "properties": {
    "tgn:hierarchy":[
        "tgn:2482493",
        "tgn:1000001",
        "tgn:7012149",
        "tgn:2001283",
        "tgn:7007524",
        "tgn:7029392"
    ],
    "tgn:id":2482493,
    "tgn:name":"Lansing Point",
    "tgn:placetype":[
        "aat:300008850"
    ]
},
  "bbox": [],
  "geometry": {"coordinates":[-114.1167,47.7667],"type":"Point"}
}