{
  "id": 7427713,
  "type": "Feature",
  "properties": {
    "tgn:hierarchy":[
        "tgn:7427713",
        "tgn:1000001",
        "tgn:7005594",
        "tgn:7005560",
        "tgn:7029392"
    ],
    "tgn:id":7427713,
    "tgn:name":"La Cruz",
    "tgn:placetype":[
        "aat:300008347"
    ]
},
  "bbox": [],
  "geometry": {"coordinates":[-102.133333,23.133333],"type":"Point"}
}