<<<<<<< HEAD
{
  "id": 2403233,
  "type": "Feature",
  "properties": {
    "tgn:hierarchy":[
        "tgn:2403233",
        "tgn:7006450",
        "tgn:1000001",
        "tgn:7012149",
        "tgn:2000082",
        "tgn:7029392"
    ],
    "tgn:id":2403233,
    "tgn:name":"House Rock",
    "tgn:placetype":[
        "aat:300008791"
    ]
},
  "bbox": [],
  "geometry": {"coordinates":[-131.0,55.0],"type":"Point"}
}
=======
{"geometry":{"type":"Point","coordinates":[-131.000000,55.000000]},"type":"Feature","properties":{"hierarchy":["tgn:2403233","tgn:7006450","tgn:1000001","tgn:7012149","tgn:2000082","tgn:7029392"],"placetype":["aat:300008791"],"id":2403233,"name:xx":"House Rock"}}
>>>>>>> 03f74aca74312dbeaf24d7e61306dd6a786dc3d0
