<<<<<<< HEAD
{
  "id": 2768647,
  "type": "Feature",
  "properties": {
    "tgn:hierarchy":[
        "tgn:2768647",
        "tgn:1000001",
        "tgn:1002461",
        "tgn:7012149",
        "tgn:7007159",
        "tgn:7029392"
    ],
    "tgn:id":2768647,
    "tgn:name":"Whitings Corner",
    "tgn:placetype":[
        "aat:300008347"
    ]
},
  "bbox": [],
  "geometry": {"coordinates":[-72.7667,41.7833],"type":"Point"}
}
=======
{"geometry":{"type":"Point","coordinates":[-72.766700,41.783300]},"type":"Feature","properties":{"hierarchy":["tgn:2768647","tgn:1000001","tgn:1002461","tgn:7012149","tgn:7007159","tgn:7029392"],"placetype":["aat:300008347"],"id":2768647,"name:xx":"Whitings Corner"}}
>>>>>>> 03f74aca74312dbeaf24d7e61306dd6a786dc3d0
