{
  "id": 2247377,
  "type": "Feature",
  "properties": {
    "tgn:hierarchy":[
        "tgn:2247377",
        "tgn:1000001",
        "tgn:2000469",
        "tgn:7012149",
        "tgn:7007250",
        "tgn:7029392"
    ],
    "tgn:id":2247377,
    "tgn:name":"Coffee Creek",
    "tgn:placetype":[
        "aat:300008706"
    ]
},
  "bbox": [],
  "geometry": {"coordinates":[-115.2667,46.6667],"type":"Point"}
}