{
  "id": 2366335,
  "type": "Feature",
  "properties": {
    "tgn:hierarchy":[
        "tgn:2366335",
        "tgn:1000001",
        "tgn:7012149",
        "tgn:1002746",
        "tgn:7007568",
        "tgn:7029392"
    ],
    "tgn:id":2366335,
    "tgn:name":"Griffins Corners",
    "tgn:placetype":[
        "aat:300008347"
    ]
},
  "bbox": [],
  "geometry": {"coordinates":[-76.1833,42.9333],"type":"Point"}
}