{
  "id": 2453275,
  "type": "Feature",
  "properties": {
    "tgn:hierarchy":[
        "tgn:2453275",
        "tgn:1000001",
        "tgn:7012149",
        "tgn:2002386",
        "tgn:7007923",
        "tgn:7029392"
    ],
    "tgn:id":2453275,
    "tgn:name":"Little Cedar Ridge",
    "tgn:placetype":[
        "aat:300266640"
    ]
},
  "bbox": [],
  "geometry": {"coordinates":[-107.4833,43.8667],"type":"Point"}
}