{
  "id": 2709941,
  "type": "Feature",
  "properties": {
    "tgn:hierarchy":[
        "tgn:2709941",
        "tgn:1000001",
        "tgn:7016172",
        "tgn:7012149",
        "tgn:2000146",
        "tgn:7029392"
    ],
    "tgn:id":2709941,
    "tgn:name":"Takima, Lake",
    "tgn:placetype":[
        "aat:300008680"
    ]
},
  "bbox": [],
  "geometry": {"coordinates":[-94.0667,35.0333],"type":"Point"}
}