{
  "id": 2691562,
  "type": "Feature",
  "properties": {
    "tgn:hierarchy":[
        "tgn:2691562",
        "tgn:1000001",
        "tgn:2001418",
        "tgn:7012149",
        "tgn:7007526",
        "tgn:7029392"
    ],
    "tgn:id":2691562,
    "tgn:name":"Stargo",
    "tgn:placetype":[
        "aat:300008347",
        "aat:300167671",
        "aat:300387243",
        "aat:300387305"
    ]
},
  "bbox": [],
  "geometry": {"coordinates":[-116.4833,38.9333],"type":"Point"}
}