<<<<<<< HEAD
{
  "id": 2253279,
  "type": "Feature",
  "properties": {
    "tgn:hierarchy":[
        "tgn:2253279",
        "tgn:1000001",
        "tgn:7012149",
        "tgn:7016021",
        "tgn:7007568",
        "tgn:7029392"
    ],
    "tgn:id":2253279,
    "tgn:name":"Converse",
    "tgn:placetype":[
        "aat:300008347"
    ]
},
  "bbox": [],
  "geometry": {"coordinates":[-74.8167,44.6667],"type":"Point"}
}
=======
{"geometry":{"type":"Point","coordinates":[-74.816700,44.666700]},"type":"Feature","properties":{"hierarchy":["tgn:2253279","tgn:1000001","tgn:7012149","tgn:7016021","tgn:7007568","tgn:7029392"],"placetype":["aat:300008347"],"id":2253279,"name:xx":"Converse"}}
>>>>>>> 03f74aca74312dbeaf24d7e61306dd6a786dc3d0
