{
  "id": 2171183,
  "type": "Feature",
  "properties": {
    "tgn:hierarchy":[
        "tgn:2171183",
        "tgn:1000001",
        "tgn:7012149",
        "tgn:2002195",
        "tgn:7007919",
        "tgn:7029392"
    ],
    "tgn:id":2171183,
    "tgn:name":"Big Spring",
    "tgn:placetype":[
        "aat:300008697"
    ]
},
  "bbox": [],
  "geometry": {"coordinates":[-82.7167,36.85],"type":"Point"}
}