{
  "id": 2580048,
  "type": "Feature",
  "properties": {
    "tgn:hierarchy":[
        "tgn:2580048",
        "tgn:7016099",
        "tgn:1000001",
        "tgn:7012149",
        "tgn:7007516",
        "tgn:7029392"
    ],
    "tgn:id":2580048,
    "tgn:name":"Pierce Branch",
    "tgn:placetype":[
        "aat:300008699"
    ]
},
  "bbox": [],
  "geometry": {"coordinates":[-76.5167,39.45],"type":"Point"}
}