{
  "id": 7545228,
  "type": "Feature",
  "properties": {
    "tgn:hierarchy":[
        "tgn:7545228",
        "tgn:1000004",
        "tgn:1001871",
        "tgn:7000198",
        "tgn:7029392"
    ],
    "tgn:id":7545228,
    "tgn:name:en":"B\u0101dli",
    "tgn:placetype":[
        "aat:300008347"
    ]
},
  "bbox": [],
  "geometry": {"coordinates":[76.809755,28.573717],"type":"Point"}
}