{
  "id": 2476362,
  "type": "Feature",
  "properties": {
    "tgn:hierarchy":[
        "tgn:2476362",
        "tgn:1000001",
        "tgn:7012149",
        "tgn:1002862",
        "tgn:7007920",
        "tgn:7029392"
    ],
    "tgn:id":2476362,
    "tgn:name":"Lundberg Mountain",
    "tgn:placetype":[
        "aat:300008798"
    ]
},
  "bbox": [],
  "geometry": {"coordinates":[-123.2167,48.6833],"type":"Point"}
}