{
  "id": 2739174,
  "type": "Feature",
  "properties": {
    "tgn:hierarchy":[
        "tgn:2739174",
        "tgn:1000001",
        "tgn:7012149",
        "tgn:2000410",
        "tgn:7007248",
        "tgn:7029392"
    ],
    "tgn:id":2739174,
    "tgn:name":"Unknown",
    "tgn:placetype":[
        "aat:300006191"
    ]
},
  "bbox": [],
  "geometry": {"coordinates":[-83.3833,34.95],"type":"Point"}
}