{
  "id": 2314093,
  "type": "Feature",
  "properties": {
    "tgn:hierarchy":[
        "tgn:2314093",
        "tgn:1000001",
        "tgn:7012149",
        "tgn:2002379",
        "tgn:7007923",
        "tgn:7029392"
    ],
    "tgn:id":2314093,
    "tgn:name":"Elk Basin",
    "tgn:placetype":[
        "aat:300386845"
    ]
},
  "bbox": [],
  "geometry": {"coordinates":[-108.8667,44.9833],"type":"Point"}
}