{
  "id": 2260660,
  "type": "Feature",
  "properties": {
    "tgn:hierarchy":[
        "tgn:2260660",
        "tgn:1000001",
        "tgn:7012149",
        "tgn:2001040",
        "tgn:7007521",
        "tgn:7029392"
    ],
    "tgn:id":2260660,
    "tgn:name":"County Ditch Number Ninteen",
    "tgn:placetype":[
        "aat:300006075"
    ]
},
  "bbox": [],
  "geometry": {"coordinates":[-95.75,44.5167],"type":"Point"}
}