{
  "id": 7581384,
  "type": "Feature",
  "properties": {
    "tgn:hierarchy":[
        "tgn:7581384",
        "tgn:1000004",
        "tgn:7018318",
        "tgn:7000198",
        "tgn:7029392"
    ],
    "tgn:id":7581384,
    "tgn:name:en":"Surla",
    "tgn:placetype":[
        "aat:300008347"
    ]
},
  "bbox": [],
  "geometry": {"coordinates":[74.033333,15.483333],"type":"Point"}
}