{
  "id": 7371421,
  "type": "Feature",
  "properties": {
    "tgn:hierarchy":[
        "tgn:7371421",
        "tgn:1001835",
        "tgn:1000001",
        "tgn:7005560",
        "tgn:7029392"
    ],
    "tgn:id":7371421,
    "tgn:name":"Grande, Arroyo",
    "tgn:placetype":[
        "aat:300266554",
        "aat:300008699"
    ]
},
  "bbox": [],
  "geometry": {"coordinates":[-115.266667,31.783333],"type":"Point"}
}