{
  "id": 1128878,
  "type": "Feature",
  "properties": {
    "tgn:hierarchy":[
        "tgn:1128878",
        "tgn:7005586",
        "tgn:1000001",
        "tgn:7005560",
        "tgn:7029392"
    ],
    "tgn:id":1128878,
    "tgn:name":"Purificaci\u00f3n",
    "tgn:placetype":[
        "aat:300008707",
        "aat:300008699"
    ]
},
  "bbox": [],
  "geometry": {"coordinates":[-104.983333,19.35],"type":"Point"}
}