{
  "id": 7358321,
  "type": "Feature",
  "properties": {
    "tgn:hierarchy":[
        "tgn:7358321",
        "tgn:1001853",
        "tgn:1000001",
        "tgn:7005560",
        "tgn:7029392"
    ],
    "tgn:id":7358321,
    "tgn:name":"Ejido San Miguel",
    "tgn:placetype":[
        "aat:300008347"
    ]
},
  "bbox": [],
  "geometry": {"coordinates":[-102.933333,28.633333],"type":"Point"}
}