{
  "id": 7271422,
  "type": "Feature",
  "properties": {
    "tgn:hierarchy":[
        "tgn:7271422",
        "tgn:1000003",
        "tgn:7003624",
        "tgn:7016845",
        "tgn:7029392"
    ],
    "tgn:id":7271422,
    "tgn:name:nl":"Schooteind",
    "tgn:placetype":[
        "aat:300000745"
    ]
},
  "bbox": [],
  "geometry": {"coordinates":[5.75,51.45],"type":"Point"}
}