{
  "id": 7035355,
  "type": "Feature",
  "properties": {
    "tgn:hierarchy":[
        "tgn:7035355",
        "tgn:1003488",
        "tgn:1000003",
        "tgn:7002993",
        "tgn:1000080",
        "tgn:7029392"
    ],
    "tgn:id":7035355,
    "tgn:name":"Bier",
    "tgn:placetype":[
        "aat:300008347"
    ]
},
  "bbox": [],
  "geometry": {"coordinates":[12.772778,46.2025],"type":"Point"}
}