{
  "id": 7232314,
  "type": "Feature",
  "properties": {
    "tgn:hierarchy":[
        "tgn:7232314",
        "tgn:7002741",
        "tgn:7017076",
        "tgn:1000003",
        "tgn:1000074",
        "tgn:7029392"
    ],
    "tgn:id":7232314,
    "tgn:name":"Koufosp\u00edthari",
    "tgn:placetype":[
        "aat:300008777"
    ]
},
  "bbox": [],
  "geometry": {"coordinates":[23.033333,38.366667],"type":"Point"}
}