{
  "id": 2096319,
  "type": "Feature",
  "properties": {
    "tgn:hierarchy":[
        "tgn:2096319",
        "tgn:1000001",
        "tgn:7012149",
        "tgn:2001763",
        "tgn:7007712",
        "tgn:7029392"
    ],
    "tgn:id":2096319,
    "tgn:name":"Norris",
    "tgn:placetype":[
        "aat:300008347"
    ]
},
  "bbox": [],
  "geometry": {"coordinates":[-82.75,34.75],"type":"Point"}
}