{
  "id": 7540399,
  "type": "Feature",
  "properties": {
    "tgn:hierarchy":[
        "tgn:7540399",
        "tgn:7001242",
        "tgn:7016833",
        "tgn:7001312",
        "tgn:7029392"
    ],
    "tgn:id":7540399,
    "tgn:name:en":"Minsh\u0101t a\u015f \u015eabb\u0101\u1e29\u012b",
    "tgn:placetype":[
        "aat:300008347"
    ]
},
  "bbox": [],
  "geometry": {"coordinates":[31.218859,30.651635],"type":"Point"}
}