{
  "id": 2286824,
  "type": "Feature",
  "properties": {
    "tgn:hierarchy":[
        "tgn:2286824",
        "tgn:1000001",
        "tgn:7012149",
        "tgn:2001864",
        "tgn:7007825",
        "tgn:7029392"
    ],
    "tgn:id":2286824,
    "tgn:name":"Diana Ridge",
    "tgn:placetype":[
        "aat:300266640"
    ]
},
  "bbox": [],
  "geometry": {"coordinates":[-86.8667,35.2667],"type":"Point"}
}