{
  "id": 7391435,
  "type": "Feature",
  "properties": {
    "tgn:hierarchy":[
        "tgn:7391435",
        "tgn:7005583",
        "tgn:1000001",
        "tgn:7005560",
        "tgn:7029392"
    ],
    "tgn:id":7391435,
    "tgn:name":"Rodr\u00edguez Pueblo",
    "tgn:placetype":[
        "aat:300008347"
    ]
},
  "bbox": [],
  "geometry": {"coordinates":[-105.068056,24.320556],"type":"Point"}
}