{
  "id": 2299614,
  "type": "Feature",
  "properties": {
    "tgn:hierarchy":[
        "tgn:2299614",
        "tgn:1000001",
        "tgn:7012149",
        "tgn:1002794",
        "tgn:7007708",
        "tgn:7029392"
    ],
    "tgn:id":2299614,
    "tgn:name":"Duck Slough",
    "tgn:placetype":[
        "aat:300008699"
    ]
},
  "bbox": [],
  "geometry": {"coordinates":[-123.15,44.7833],"type":"Point"}
}