{
  "id": 2269309,
  "type": "Feature",
  "properties": {
    "tgn:hierarchy":[
        "tgn:2269309",
        "tgn:1000001",
        "tgn:7012149",
        "tgn:1002990",
        "tgn:7007708",
        "tgn:7029392"
    ],
    "tgn:id":2269309,
    "tgn:name":"Crow Creek Reservoir",
    "tgn:placetype":[
        "aat:300006191"
    ]
},
  "bbox": [],
  "geometry": {"coordinates":[-121.45,45.4667],"type":"Point"}
}