{
  "id": 1116402,
  "type": "Feature",
  "properties": {
    "tgn:hierarchy":[
        "tgn:1116402",
        "tgn:1000001",
        "tgn:7012149",
        "tgn:1002737",
        "tgn:7007520",
        "tgn:7029392"
    ],
    "tgn:id":1116402,
    "tgn:name":"Gilbert Lake",
    "tgn:placetype":[
        "aat:300008680"
    ]
},
  "bbox": [],
  "geometry": {"coordinates":[-83.2667,42.55],"type":"Point"}
}