{
  "id": 2445377,
  "type": "Feature",
  "properties": {
    "tgn:hierarchy":[
        "tgn:2445377",
        "tgn:1000001",
        "tgn:7012149",
        "tgn:1002742",
        "tgn:7007920",
        "tgn:7029392"
    ],
    "tgn:id":2445377,
    "tgn:name":"Lenner Spring",
    "tgn:placetype":[
        "aat:300008697"
    ]
},
  "bbox": [],
  "geometry": {"coordinates":[-119.4167,48.0667],"type":"Point"}
}