{
  "id": 2745503,
  "type": "Feature",
  "properties": {
    "tgn:hierarchy":[
        "tgn:2745503",
        "tgn:1000001",
        "tgn:1002665",
        "tgn:7012149",
        "tgn:7007517",
        "tgn:7029392"
    ],
    "tgn:id":2745503,
    "tgn:name":"Vinton Pond",
    "tgn:placetype":[
        "aat:300008680"
    ]
},
  "bbox": [],
  "geometry": {"coordinates":[-71.7667,42.65],"type":"Point"}
}