{
  "id": 2197966,
  "type": "Feature",
  "properties": {
    "tgn:hierarchy":[
        "tgn:2197966",
        "tgn:1000001",
        "tgn:7012149",
        "tgn:2001750",
        "tgn:7007712",
        "tgn:7029392"
    ],
    "tgn:id":2197966,
    "tgn:name":"Brown Swamp",
    "tgn:placetype":[
        "aat:300008699"
    ]
},
  "bbox": [],
  "geometry": {"coordinates":[-79.1167,33.9167],"type":"Point"}
}