{
  "id": 7345579,
  "type": "Feature",
  "properties": {
    "tgn:hierarchy":[
        "tgn:7345579",
        "tgn:7002758",
        "tgn:1001316",
        "tgn:1000003",
        "tgn:1000095",
        "tgn:7029392"
    ],
    "tgn:id":7345579,
    "tgn:name":"Aljibillo",
    "tgn:placetype":[
        "aat:300008777"
    ]
},
  "bbox": [],
  "geometry": {"coordinates":[-4.15,38.266667],"type":"Point"}
}