{
  "id": 7516663,
  "type": "Feature",
  "properties": {
    "tgn:hierarchy":[
        "tgn:7516663",
        "tgn:7016670",
        "tgn:1008380",
        "tgn:1000226",
        "tgn:1000006",
        "tgn:7029392"
    ],
    "tgn:id":7516663,
    "tgn:name:en":"Manga o Nuku Stream",
    "tgn:placetype":[
        "aat:300008699"
    ]
},
  "bbox": [],
  "geometry": {"coordinates":[176.533333,-39.916667],"type":"Point"}
}