{
  "id": 7568689,
  "type": "Feature",
  "properties": {
    "tgn:hierarchy":[
        "tgn:7568689",
        "tgn:1000004",
        "tgn:7000198",
        "tgn:7016722",
        "tgn:7029392"
    ],
    "tgn:id":7568689,
    "tgn:name:en":"Dabheri",
    "tgn:placetype":[
        "aat:300008347"
    ]
},
  "bbox": [],
  "geometry": {"coordinates":[77.441037,29.640562],"type":"Point"}
}