{
  "id": 2385912,
  "type": "Feature",
  "properties": {
    "tgn:hierarchy":[
        "tgn:2385912",
        "tgn:1000001",
        "tgn:7012149",
        "tgn:2000276",
        "tgn:7007240",
        "tgn:7029392"
    ],
    "tgn:id":2385912,
    "tgn:name":"Henrietta",
    "tgn:placetype":[
        "aat:300008347"
    ]
},
  "bbox": [],
  "geometry": {"coordinates":[-84.2833,30.3833],"type":"Point"}
}