{
  "id": 7166421,
  "type": "Feature",
  "properties": {
    "tgn:hierarchy":[
        "tgn:7166421",
        "tgn:7003669",
        "tgn:1000003",
        "tgn:7000084",
        "tgn:7029392"
    ],
    "tgn:id":7166421,
    "tgn:name":"Hauserbach",
    "tgn:placetype":[
        "aat:300008699"
    ]
},
  "bbox": [],
  "geometry": {"coordinates":[12.383333,49.183333],"type":"Point"}
}