{
  "id": 7031969,
  "type": "Feature",
  "properties": {
    "tgn:hierarchy":[
        "tgn:7031969",
        "tgn:1001623",
        "tgn:1000049",
        "tgn:1000002",
        "tgn:7029392"
    ],
    "tgn:id":7031969,
    "tgn:name:en":"San Rafael, Laguna",
    "tgn:placetype":[
        "aat:300008680"
    ]
},
  "bbox": [],
  "geometry": {"coordinates":[-73.966667,-46.666667],"type":"Point"}
}