{
  "id": 7104284,
  "type": "Feature",
  "properties": {
    "tgn:hierarchy":[
        "tgn:7104284",
        "tgn:7003669",
        "tgn:1000003",
        "tgn:7000084",
        "tgn:7029392"
    ],
    "tgn:id":7104284,
    "tgn:name":"Schluifelder Wald",
    "tgn:placetype":[
        "aat:300008863"
    ]
},
  "bbox": [],
  "geometry": {"coordinates":[11.25,48.083333],"type":"Point"}
}