{
  "id": 1116754,
  "type": "Feature",
  "properties": {
    "tgn:hierarchy":[
        "tgn:1116754",
        "tgn:7000096",
        "tgn:1000003",
        "tgn:7000084",
        "tgn:7029392"
    ],
    "tgn:id":1116754,
    "tgn:name":"Jungfern-See",
    "tgn:placetype":[
        "aat:300008680"
    ]
},
  "bbox": [],
  "geometry": {"coordinates":[13.083333,52.416667],"type":"Point"}
}