{
  "id": 2346012,
  "type": "Feature",
  "properties": {
    "tgn:hierarchy":[
        "tgn:2346012",
        "tgn:1000001",
        "tgn:7016102",
        "tgn:7012149",
        "tgn:7007516",
        "tgn:7029392"
    ],
    "tgn:id":2346012,
    "tgn:name":"Gasheys Creek",
    "tgn:placetype":[
        "aat:300008706"
    ]
},
  "bbox": [],
  "geometry": {"coordinates":[-76.15,39.5667],"type":"Point"}
}