{
  "id": 2582266,
  "type": "Feature",
  "properties": {
    "tgn:hierarchy":[
        "tgn:2582266",
        "tgn:1000001",
        "tgn:2002109",
        "tgn:7012149",
        "tgn:7007827",
        "tgn:7029392"
    ],
    "tgn:id":2582266,
    "tgn:name":"Pine Creek",
    "tgn:placetype":[
        "aat:300008706"
    ]
},
  "bbox": [],
  "geometry": {"coordinates":[-111.5833,38.05],"type":"Point"}
}