<<<<<<< HEAD
{
  "id": 7054747,
  "type": "Feature",
  "properties": {
    "tgn:hierarchy":[
        "tgn:7054747",
        "tgn:7003248",
        "tgn:1000003",
        "tgn:7010380",
        "tgn:1000080",
        "tgn:7029392"
    ],
    "tgn:id":7054747,
    "tgn:name":"Padresergio",
    "tgn:placetype":[
        "aat:300008347"
    ]
},
  "bbox": [],
  "geometry": {"coordinates":[17.2,40.916667],"type":"Point"}
}
=======
{"geometry":{"type":"Point","coordinates":[17.200000,40.916667]},"type":"Feature","properties":{"hierarchy":["tgn:7054747","tgn:7003248","tgn:1000003","tgn:7010380","tgn:1000080","tgn:7029392"],"placetype":["aat:300008347"],"id":7054747,"name:xx":"Padresergio"}}
>>>>>>> 03f74aca74312dbeaf24d7e61306dd6a786dc3d0
