{
  "id": 1098911,
  "type": "Feature",
  "properties": {
    "tgn:hierarchy":[
        "tgn:1098911",
        "tgn:1009227",
        "tgn:7001866",
        "tgn:1000226",
        "tgn:1000006",
        "tgn:7029392"
    ],
    "tgn:id":1098911,
    "tgn:name:en":"Dunsandel",
    "tgn:placetype":[
        "aat:300008347"
    ]
},
  "bbox": [],
  "geometry": {"coordinates":[172.183333,-43.666667],"type":"Point"}
}