{
  "id": 2004286,
  "type": "Feature",
  "properties": {
    "tgn:hierarchy":[
        "tgn:2004286",
        "tgn:7002659",
        "tgn:1000001",
        "tgn:7012149",
        "tgn:7021514",
        "tgn:7029392"
    ],
    "tgn:id":2004286,
    "tgn:name":"Loveless",
    "tgn:placetype":[
        "aat:300008347",
        "aat:300387210"
    ]
},
  "bbox": [],
  "geometry": {"coordinates":[-85.75,34.3167],"type":"Point"}
}