{
  "id": 2100381,
  "type": "Feature",
  "properties": {
    "tgn:hierarchy":[
        "tgn:2100381",
        "tgn:1000001",
        "tgn:7012149",
        "tgn:2001909",
        "tgn:7007825",
        "tgn:7029392"
    ],
    "tgn:id":2100381,
    "tgn:name":"Midtown",
    "tgn:placetype":[
        "aat:300008347"
    ]
},
  "bbox": [],
  "geometry": {"coordinates":[-84.55,35.8667],"type":"Point"}
}