{
  "id": 7315588,
  "type": "Feature",
  "properties": {
    "tgn:hierarchy":[
        "tgn:7315588",
        "tgn:7016598",
        "tgn:1000049",
        "tgn:1000002",
        "tgn:7029392"
    ],
    "tgn:id":7315588,
    "tgn:name":"Chaco, Quebrada del",
    "tgn:placetype":[
        "aat:300266554",
        "aat:300008699"
    ]
},
  "bbox": [],
  "geometry": {"coordinates":[-69.666667,-25.366667],"type":"Point"}
}