{
  "id": 2660168,
  "type": "Feature",
  "properties": {
    "tgn:hierarchy":[
        "tgn:2660168",
        "tgn:7030515",
        "tgn:7006450",
        "tgn:1000001",
        "tgn:7012149",
        "tgn:7029392"
    ],
    "tgn:id":2660168,
    "tgn:name":"Shoal Bay",
    "tgn:placetype":[
        "aat:300132316"
    ]
},
  "bbox": [],
  "geometry": {"coordinates":[-159.4333,55.05],"type":"Point"}
}