{
  "id": 7017198,
  "type": "Feature",
  "properties": {
    "tgn:hierarchy":[
        "tgn:7017198",
        "tgn:7032026",
        "tgn:1000001",
        "tgn:7029392"
    ],
    "tgn:id":7017198,
    "tgn:name":"Paget",
    "tgn:placetype":[
        "aat:300387064",
        "aat:300387092"
    ]
},
  "bbox": [],
  "geometry": {"coordinates":[-64.765,32.278],"type":"Point"}
}