{
  "id": 7574674,
  "type": "Feature",
  "properties": {
    "tgn:hierarchy":[
        "tgn:7574674",
        "tgn:1000004",
        "tgn:7000198",
        "tgn:1001894",
        "tgn:7029392"
    ],
    "tgn:id":7574674,
    "tgn:name:en":"Katra",
    "tgn:placetype":[
        "aat:300008347"
    ]
},
  "bbox": [],
  "geometry": {"coordinates":[81.626558,24.990371],"type":"Point"}
}