{
  "id": 2528009,
  "type": "Feature",
  "properties": {
    "tgn:hierarchy":[
        "tgn:2528009",
        "tgn:1000001",
        "tgn:2001432",
        "tgn:7012149",
        "tgn:7007566",
        "tgn:7029392"
    ],
    "tgn:id":2528009,
    "tgn:name":"Mountain Queen Number 1",
    "tgn:placetype":[
        "aat:300000390"
    ]
},
  "bbox": [],
  "geometry": {"coordinates":[-105.2333,36.6167],"type":"Point"}
}