{
  "id": 2679971,
  "type": "Feature",
  "properties": {
    "tgn:hierarchy":[
        "tgn:2679971",
        "tgn:1000001",
        "tgn:7012149",
        "tgn:2002379",
        "tgn:7007923",
        "tgn:7029392"
    ],
    "tgn:id":2679971,
    "tgn:name":"South Fork Shoshone River",
    "tgn:placetype":[
        "aat:300008707"
    ]
},
  "bbox": [],
  "geometry": {"coordinates":[-109.8167,43.8167],"type":"Point"}
}