{
  "id": 7587432,
  "type": "Feature",
  "properties": {
    "tgn:hierarchy":[
        "tgn:7587432",
        "tgn:1000004",
        "tgn:7000198",
        "tgn:7000799",
        "tgn:7029392"
    ],
    "tgn:id":7587432,
    "tgn:name:en":"Bar \u016adar",
    "tgn:placetype":[
        "aat:300008347"
    ]
},
  "bbox": [],
  "geometry": {"coordinates":[74.747222,34.1375],"type":"Point"}
}