{
  "id": 7041891,
  "type": "Feature",
  "properties": {
    "tgn:hierarchy":[
        "tgn:7041891",
        "tgn:1001641",
        "tgn:1000003",
        "tgn:7003121",
        "tgn:1000080",
        "tgn:7029392"
    ],
    "tgn:id":7041891,
    "tgn:name":"Sa Illetta",
    "tgn:placetype":[
        "aat:300008791"
    ]
},
  "bbox": [],
  "geometry": {"coordinates":[9.085278,39.218056],"type":"Point"}
}