{
  "id": 2225060,
  "type": "Feature",
  "properties": {
    "tgn:hierarchy":[
        "tgn:2225060",
        "tgn:1000001",
        "tgn:2000870",
        "tgn:7012149",
        "tgn:7007256",
        "tgn:7029392"
    ],
    "tgn:id":2225060,
    "tgn:name":"Castille",
    "tgn:placetype":[
        "aat:300008347"
    ]
},
  "bbox": [],
  "geometry": {"coordinates":[-91.0167,30.3667],"type":"Point"}
}