{
  "id": 2004692,
  "type": "Feature",
  "properties": {
    "tgn:hierarchy":[
        "tgn:2004692",
        "tgn:7002659",
        "tgn:1000001",
        "tgn:7012149",
        "tgn:2000057",
        "tgn:7029392"
    ],
    "tgn:id":2004692,
    "tgn:name":"New London",
    "tgn:placetype":[
        "aat:300008347"
    ]
},
  "bbox": [],
  "geometry": {"coordinates":[-86.35,33.4667],"type":"Point"}
}