{
  "id": 2127703,
  "type": "Feature",
  "properties": {
    "tgn:hierarchy":[
        "tgn:2127703",
        "tgn:1000001",
        "tgn:7012149",
        "tgn:2000219",
        "tgn:7007158",
        "tgn:7029392"
    ],
    "tgn:id":2127703,
    "tgn:name":"Alamo",
    "tgn:placetype":[
        "aat:300008347"
    ]
},
  "bbox": [],
  "geometry": {"coordinates":[-104.95,37.65],"type":"Point"}
}