{
  "id": 2573971,
  "type": "Feature",
  "properties": {
    "tgn:hierarchy":[
        "tgn:2573971",
        "tgn:1000001",
        "tgn:7012149",
        "tgn:1002992",
        "tgn:7007252",
        "tgn:7029392"
    ],
    "tgn:id":2573971,
    "tgn:name":"Peek-A-Boo Lake",
    "tgn:placetype":[
        "aat:300006191"
    ]
},
  "bbox": [],
  "geometry": {"coordinates":[-85.9833,38.5167],"type":"Point"}
}