{
  "id": 2646463,
  "type": "Feature",
  "properties": {
    "tgn:hierarchy":[
        "tgn:2646463",
        "tgn:2000001",
        "tgn:7002659",
        "tgn:1000001",
        "tgn:7012149",
        "tgn:7029392"
    ],
    "tgn:id":2646463,
    "tgn:name":"Saxon Bay",
    "tgn:placetype":[
        "aat:300132316"
    ]
},
  "bbox": [],
  "geometry": {"coordinates":[-87.95,30.25],"type":"Point"}
}