{
  "id": 2481677,
  "type": "Feature",
  "properties": {
    "tgn:hierarchy":[
        "tgn:2481677",
        "tgn:1000001",
        "tgn:7012149",
        "tgn:2001756",
        "tgn:7007712",
        "tgn:7029392"
    ],
    "tgn:id":2481677,
    "tgn:name":"Land of the Lakes",
    "tgn:placetype":[
        "aat:300008347"
    ]
},
  "bbox": [],
  "geometry": {"coordinates":[-81.2167,33.9333],"type":"Point"}
}