{
  "id": 2228993,
  "type": "Feature",
  "properties": {
    "tgn:hierarchy":[
        "tgn:2228993",
        "tgn:1000001",
        "tgn:2000467",
        "tgn:7012149",
        "tgn:7007250",
        "tgn:7029392"
    ],
    "tgn:id":2228993,
    "tgn:name":"Cedar Hollow Spring",
    "tgn:placetype":[
        "aat:300008697"
    ]
},
  "bbox": [],
  "geometry": {"coordinates":[-113.7333,42.2833],"type":"Point"}
}