{
  "id": 2516047,
  "type": "Feature",
  "properties": {
    "tgn:hierarchy":[
        "tgn:2516047",
        "tgn:1000001",
        "tgn:7012149",
        "tgn:7016167",
        "tgn:7007523",
        "tgn:7029392"
    ],
    "tgn:id":2516047,
    "tgn:name":"Mincke Hollow",
    "tgn:placetype":[
        "aat:300008761"
    ]
},
  "bbox": [],
  "geometry": {"coordinates":[-90.5667,38.5167],"type":"Point"}
}