<<<<<<< HEAD
{
  "id": 7179114,
  "type": "Feature",
  "properties": {
    "tgn:hierarchy":[
        "tgn:7179114",
        "tgn:1000003",
        "tgn:7003678",
        "tgn:7000084",
        "tgn:7029392"
    ],
    "tgn:id":7179114,
    "tgn:name":"Hammeraue",
    "tgn:placetype":[
        "aat:300055621"
    ]
},
  "bbox": [],
  "geometry": {"coordinates":[8.45,49.716667],"type":"Point"}
}
=======
{"geometry":{"type":"Point","coordinates":[8.450000,49.716667]},"type":"Feature","properties":{"hierarchy":["tgn:7179114","tgn:1000003","tgn:7003678","tgn:7000084","tgn:7029392"],"placetype":["aat:300055621"],"id":7179114,"name:xx":"Hammeraue"}}
>>>>>>> 03f74aca74312dbeaf24d7e61306dd6a786dc3d0
