{
  "id": 1009256,
  "type": "Feature",
  "properties": {
    "tgn:hierarchy":[
        "tgn:1009256",
        "tgn:7005735",
        "tgn:7005685",
        "tgn:1000001",
        "tgn:7029392"
    ],
    "tgn:id":1009256,
    "tgn:name":"Stephens Island",
    "tgn:placetype":[
        "aat:300008791"
    ]
},
  "bbox": [],
  "geometry": {"coordinates":[-130.75,54.1667],"type":"Point"}
}