{
  "id": 2297578,
  "type": "Feature",
  "properties": {
    "tgn:hierarchy":[
        "tgn:2297578",
        "tgn:1000001",
        "tgn:2000466",
        "tgn:7012149",
        "tgn:7007250",
        "tgn:7029392"
    ],
    "tgn:id":2297578,
    "tgn:name":"Dry Fork Draney Creek",
    "tgn:placetype":[
        "aat:300008706"
    ]
},
  "bbox": [],
  "geometry": {"coordinates":[-111.1333,42.7333],"type":"Point"}
}