{
  "id": 2621390,
  "type": "Feature",
  "properties": {
    "tgn:hierarchy":[
        "tgn:2621390",
        "tgn:1000001",
        "tgn:7012149",
        "tgn:7007159",
        "tgn:7029392"
    ],
    "tgn:id":2621390,
    "tgn:name":"Roaring Brook Number 2",
    "tgn:placetype":[
        "aat:300008699"
    ]
},
  "bbox": [],
  "geometry": {"coordinates":[-72.3667,41.4667],"type":"Point"}
}