{
  "id": 1067136,
  "type": "Feature",
  "properties": {
    "tgn:hierarchy":[
        "tgn:1067136",
        "tgn:1000004",
        "tgn:7001838",
        "tgn:1000111",
        "tgn:7029392"
    ],
    "tgn:id":1067136,
    "tgn:name":"Chaoyangcun",
    "tgn:placetype":[
        "aat:300008347"
    ]
},
  "bbox": [],
  "geometry": {"coordinates":[124.3333,50.0333],"type":"Point"}
}