{
  "id": 2319527,
  "type": "Feature",
  "properties": {
    "tgn:hierarchy":[
        "tgn:2319527",
        "tgn:1000001",
        "tgn:7012149",
        "tgn:2000362",
        "tgn:7007248",
        "tgn:7029392"
    ],
    "tgn:id":2319527,
    "tgn:name":"Eubank Lake",
    "tgn:placetype":[
        "aat:300006191"
    ]
},
  "bbox": [],
  "geometry": {"coordinates":[-85.0833,33.8833],"type":"Point"}
}