{
  "id": 2747066,
  "type": "Feature",
  "properties": {
    "tgn:hierarchy":[
        "tgn:2747066",
        "tgn:1000001",
        "tgn:7012149",
        "tgn:2002019",
        "tgn:7007826",
        "tgn:7029392"
    ],
    "tgn:id":2747066,
    "tgn:name":"Wagon Bed Draw",
    "tgn:placetype":[
        "aat:300008761"
    ]
},
  "bbox": [],
  "geometry": {"coordinates":[-99.9167,30.4333],"type":"Point"}
}