<<<<<<< HEAD
{
  "id": 7023171,
  "type": "Feature",
  "properties": {
    "tgn:hierarchy":[
        "tgn:7023171",
        "tgn:1000001",
        "tgn:2000925",
        "tgn:7012149",
        "tgn:7007515",
        "tgn:7029392"
    ],
    "tgn:id":7023171,
    "tgn:name":"Jones Corner",
    "tgn:placetype":[
        "aat:300008347",
        "aat:300387210"
    ]
},
  "bbox": [],
  "geometry": {"coordinates":[-69.45,44.25],"type":"Point"}
}
=======
{"geometry":{"type":"Point","coordinates":[-69.450000,44.250000]},"type":"Feature","properties":{"hierarchy":["tgn:7023171","tgn:1000001","tgn:2000925","tgn:7012149","tgn:7007515","tgn:7029392"],"placetype":["aat:300008347","aat:300387210"],"id":7023171,"name:xx":"Jones Corner"}}
>>>>>>> 03f74aca74312dbeaf24d7e61306dd6a786dc3d0
