<<<<<<< HEAD
{
  "id": 2339346,
  "type": "Feature",
  "properties": {
    "tgn:hierarchy":[
        "tgn:2339346",
        "tgn:1000001",
        "tgn:7012149",
        "tgn:2001381",
        "tgn:7007525",
        "tgn:7029392"
    ],
    "tgn:id":2339346,
    "tgn:name":"Frazers Island",
    "tgn:placetype":[
        "aat:300008791"
    ]
},
  "bbox": [],
  "geometry": {"coordinates":[-95.7833,40.65],"type":"Point"}
}
=======
{"geometry":{"type":"Point","coordinates":[-95.783300,40.650000]},"type":"Feature","properties":{"hierarchy":["tgn:2339346","tgn:1000001","tgn:7012149","tgn:2001381","tgn:7007525","tgn:7029392"],"placetype":["aat:300008791"],"id":2339346,"name:xx":"Frazers Island"}}
>>>>>>> 03f74aca74312dbeaf24d7e61306dd6a786dc3d0
