{
  "id": 2270828,
  "type": "Feature",
  "properties": {
    "tgn:hierarchy":[
        "tgn:2270828",
        "tgn:1000001",
        "tgn:7012149",
        "tgn:7007825",
        "tgn:7029392"
    ],
    "tgn:id":2270828,
    "tgn:name":"Cub Creek",
    "tgn:placetype":[
        "aat:300008706"
    ]
},
  "bbox": [],
  "geometry": {"coordinates":[-88.2667,35.7667],"type":"Point"}
}