{
  "id": 7105018,
  "type": "Feature",
  "properties": {
    "tgn:hierarchy":[
        "tgn:7105018",
        "tgn:7003669",
        "tgn:1000003",
        "tgn:7000084",
        "tgn:7029392"
    ],
    "tgn:id":7105018,
    "tgn:name":"Schildertschlag",
    "tgn:placetype":[
        "aat:300008347"
    ]
},
  "bbox": [],
  "geometry": {"coordinates":[13.383333,48.883333],"type":"Point"}
}