{
  "id": 1127235,
  "type": "Feature",
  "properties": {
    "tgn:hierarchy":[
        "tgn:1127235",
        "tgn:7593878",
        "tgn:1000003",
        "tgn:7006413",
        "tgn:7029392"
    ],
    "tgn:id":1127235,
    "tgn:name":"Mochuritsa",
    "tgn:placetype":[
        "aat:300008707"
    ]
},
  "bbox": [],
  "geometry": {"coordinates":[26.5333,42.5167],"type":"Point"}
}