{
  "id": 7032903,
  "type": "Feature",
  "properties": {
    "tgn:hierarchy":[
        "tgn:7032903",
        "tgn:7002692",
        "tgn:7012056",
        "tgn:1000003",
        "tgn:1000074",
        "tgn:7029392"
    ],
    "tgn:id":7032903,
    "tgn:name":"Mochlos Island",
    "tgn:placetype":[
        "aat:300020226",
        "aat:300000810",
        "aat:300019275",
        "aat:300008791",
        "aat:300387004",
        "aat:300008804"
    ]
},
  "bbox": [],
  "geometry": {"coordinates":[25.811111,35.125833],"type":"Point"}
}