{
  "id": 7251184,
  "type": "Feature",
  "properties": {
    "tgn:hierarchy":[
        "tgn:7251184",
        "tgn:7003460",
        "tgn:1000003",
        "tgn:1000063",
        "tgn:4012014",
        "tgn:7029392"
    ],
    "tgn:id":7251184,
    "tgn:name":"Neckel",
    "tgn:placetype":[
        "aat:300008347"
    ]
},
  "bbox": [],
  "geometry": {"coordinates":[6.15,50.55],"type":"Point"}
}