<<<<<<< HEAD
{
  "id": 2766270,
  "type": "Feature",
  "properties": {
    "tgn:hierarchy":[
        "tgn:2766270",
        "tgn:1000001",
        "tgn:7012149",
        "tgn:7013941",
        "tgn:7007568",
        "tgn:7029392"
    ],
    "tgn:id":2766270,
    "tgn:name":"White Lily Pond",
    "tgn:placetype":[
        "aat:300008680"
    ]
},
  "bbox": [],
  "geometry": {"coordinates":[-74.2,44.2],"type":"Point"}
}
=======
{"geometry":{"type":"Point","coordinates":[-74.200000,44.200000]},"type":"Feature","properties":{"hierarchy":["tgn:2766270","tgn:1000001","tgn:7012149","tgn:7013941","tgn:7007568","tgn:7029392"],"placetype":["aat:300008680"],"id":2766270,"name:xx":"White Lily Pond"}}
>>>>>>> 03f74aca74312dbeaf24d7e61306dd6a786dc3d0
