{
  "id": 2742706,
  "type": "Feature",
  "properties": {
    "tgn:hierarchy":[
        "tgn:2742706",
        "tgn:1000001",
        "tgn:7012149",
        "tgn:2000221",
        "tgn:7007158",
        "tgn:7029392"
    ],
    "tgn:id":2742706,
    "tgn:name":"Van Bibber Creek",
    "tgn:placetype":[
        "aat:300008706"
    ]
},
  "bbox": [],
  "geometry": {"coordinates":[-105.3333,39.8167],"type":"Point"}
}