{
  "id": 2173120,
  "type": "Feature",
  "properties": {
    "tgn:hierarchy":[
        "tgn:2173120",
        "tgn:1000001",
        "tgn:7012149",
        "tgn:2001927",
        "tgn:7007825",
        "tgn:7029392"
    ],
    "tgn:id":2173120,
    "tgn:name":"Bingham Branch",
    "tgn:placetype":[
        "aat:300008699"
    ]
},
  "bbox": [],
  "geometry": {"coordinates":[-87.95,35.35],"type":"Point"}
}