<<<<<<< HEAD
{
  "id": 2403870,
  "type": "Feature",
  "properties": {
    "tgn:hierarchy":[
        "tgn:2403870",
        "tgn:2000919",
        "tgn:1000001",
        "tgn:7012149",
        "tgn:7007515",
        "tgn:7029392"
    ],
    "tgn:id":2403870,
    "tgn:name":"Howe Brook Mountain",
    "tgn:placetype":[
        "aat:300008798"
    ]
},
  "bbox": [],
  "geometry": {"coordinates":[-68.15,46.2833],"type":"Point"}
}
=======
{"geometry":{"type":"Point","coordinates":[-68.150000,46.283300]},"type":"Feature","properties":{"hierarchy":["tgn:2403870","tgn:2000919","tgn:1000001","tgn:7012149","tgn:7007515","tgn:7029392"],"placetype":["aat:300008798"],"id":2403870,"name:xx":"Howe Brook Mountain"}}
>>>>>>> 03f74aca74312dbeaf24d7e61306dd6a786dc3d0
