<<<<<<< HEAD
{
  "id": 2150545,
  "type": "Feature",
  "properties": {
    "tgn:hierarchy":[
        "tgn:2150545",
        "tgn:1000001",
        "tgn:2000271",
        "tgn:7012149",
        "tgn:7007240",
        "tgn:7029392"
    ],
    "tgn:id":2150545,
    "tgn:name":"Basin Swamp",
    "tgn:placetype":[
        "aat:300008905"
    ]
},
  "bbox": [],
  "geometry": {"coordinates":[-82.9667,30.4833],"type":"Point"}
}
=======
{"geometry":{"type":"Point","coordinates":[-82.966700,30.483300]},"type":"Feature","properties":{"hierarchy":["tgn:2150545","tgn:1000001","tgn:2000271","tgn:7012149","tgn:7007240","tgn:7029392"],"placetype":["aat:300008905"],"id":2150545,"name:xx":"Basin Swamp"}}
>>>>>>> 03f74aca74312dbeaf24d7e61306dd6a786dc3d0
