{
  "id": 2150545,
  "type": "Feature",
  "properties": {
    "tgn:hierarchy":[
        "tgn:2150545",
        "tgn:1000001",
        "tgn:2000271",
        "tgn:7012149",
        "tgn:7007240",
        "tgn:7029392"
    ],
    "tgn:id":2150545,
    "tgn:name":"Basin Swamp",
    "tgn:placetype":[
        "aat:300008905"
    ]
},
  "bbox": [],
  "geometry": {"coordinates":[-82.9667,30.4833],"type":"Point"}
}