{
  "id": 2650000,
  "type": "Feature",
  "properties": {
    "tgn:hierarchy":[
        "tgn:2650000",
        "tgn:7006450",
        "tgn:1000001",
        "tgn:7012149",
        "tgn:2000087",
        "tgn:7029392"
    ],
    "tgn:id":2650000,
    "tgn:name":"Sea Gull Point",
    "tgn:placetype":[
        "aat:300008850"
    ]
},
  "bbox": [],
  "geometry": {"coordinates":[-164.35,63.0167],"type":"Point"}
}