{
  "id": 2783272,
  "type": "Feature",
  "properties": {
    "tgn:hierarchy":[
        "tgn:2783272",
        "tgn:7006450",
        "tgn:1000001",
        "tgn:7012149",
        "tgn:7019760",
        "tgn:7029392"
    ],
    "tgn:id":2783272,
    "tgn:name":"Wright, Mount",
    "tgn:placetype":[
        "aat:300008798"
    ]
},
  "bbox": [],
  "geometry": {"coordinates":[-136.0167,58.7833],"type":"Point"}
}