{
  "id": 7324457,
  "type": "Feature",
  "properties": {
    "tgn:hierarchy":[
        "tgn:7324457",
        "tgn:7002813",
        "tgn:7002758",
        "tgn:1000003",
        "tgn:1000095",
        "tgn:7029392"
    ],
    "tgn:id":7324457,
    "tgn:name":"Saucedilla, Arroyo de",
    "tgn:placetype":[
        "aat:300008699"
    ]
},
  "bbox": [],
  "geometry": {"coordinates":[-5.816667,36.833333],"type":"Point"}
}