<<<<<<< HEAD
{
  "id": 7023649,
  "type": "Feature",
  "properties": {
    "tgn:hierarchy":[
        "tgn:7023649",
        "tgn:1000001",
        "tgn:7012149",
        "tgn:7007826",
        "tgn:7029392"
    ],
    "tgn:id":7023649,
    "tgn:name":"Pecan Spring Creek",
    "tgn:placetype":[
        "aat:300008706"
    ]
},
  "bbox": [],
  "geometry": {"coordinates":[-99.0,30.4667],"type":"Point"}
}
=======
{"geometry":{"type":"Point","coordinates":[-99.000000,30.466700]},"type":"Feature","properties":{"hierarchy":["tgn:7023649","tgn:1000001","tgn:7012149","tgn:7007826","tgn:7029392"],"placetype":["aat:300008706"],"id":7023649,"name:xx":"Pecan Spring Creek"}}
>>>>>>> 03f74aca74312dbeaf24d7e61306dd6a786dc3d0
