{
  "id": 7433276,
  "type": "Feature",
  "properties": {
    "tgn:hierarchy":[
        "tgn:7433276",
        "tgn:1000001",
        "tgn:7005589",
        "tgn:7005560",
        "tgn:7029392"
    ],
    "tgn:id":7433276,
    "tgn:name":"Tlahualillo, Arroyo",
    "tgn:placetype":[
        "aat:300266554",
        "aat:300008699"
    ]
},
  "bbox": [],
  "geometry": {"coordinates":[-99.533333,25.466667],"type":"Point"}
}