<<<<<<< HEAD
{
  "id": 7179835,
  "type": "Feature",
  "properties": {
    "tgn:hierarchy":[
        "tgn:7179835",
        "tgn:1000003",
        "tgn:7003676",
        "tgn:7000084",
        "tgn:7029392"
    ],
    "tgn:id":7179835,
    "tgn:name":"Hahnenhorstmoor",
    "tgn:placetype":[
        "aat:300008903"
    ]
},
  "bbox": [],
  "geometry": {"coordinates":[9.483333,53.15],"type":"Point"}
}
=======
{"geometry":{"type":"Point","coordinates":[9.483333,53.150000]},"type":"Feature","properties":{"hierarchy":["tgn:7179835","tgn:1000003","tgn:7003676","tgn:7000084","tgn:7029392"],"placetype":["aat:300008903"],"id":7179835,"name:xx":"Hahnenhorstmoor"}}
>>>>>>> 03f74aca74312dbeaf24d7e61306dd6a786dc3d0
