{
  "id": 7099025,
  "type": "Feature",
  "properties": {
    "tgn:hierarchy":[
        "tgn:7099025",
        "tgn:7003669",
        "tgn:1000003",
        "tgn:7000084",
        "tgn:7029392"
    ],
    "tgn:id":7099025,
    "tgn:name":"Spital Holz",
    "tgn:placetype":[
        "aat:300008863"
    ]
},
  "bbox": [],
  "geometry": {"coordinates":[10.15,49.45],"type":"Point"}
}