{
  "id": 2156167,
  "type": "Feature",
  "properties": {
    "tgn:hierarchy":[
        "tgn:2156167",
        "tgn:1000001",
        "tgn:7012149",
        "tgn:7007564",
        "tgn:7029392"
    ],
    "tgn:id":2156167,
    "tgn:name":"Beards Brook",
    "tgn:placetype":[
        "aat:300008699"
    ]
},
  "bbox": [],
  "geometry": {"coordinates":[-72.05,43.1667],"type":"Point"}
}