{
  "id": 7164755,
  "type": "Feature",
  "properties": {
    "tgn:hierarchy":[
        "tgn:7164755",
        "tgn:1000003",
        "tgn:7003676",
        "tgn:7000084",
        "tgn:7029392"
    ],
    "tgn:id":7164755,
    "tgn:name":"H\u00fcnenburg",
    "tgn:placetype":[
        "aat:300008777"
    ]
},
  "bbox": [],
  "geometry": {"coordinates":[9.166667,52.166667],"type":"Point"}
}