<<<<<<< HEAD
{
  "id": 7054526,
  "type": "Feature",
  "properties": {
    "tgn:hierarchy":[
        "tgn:7054526",
        "tgn:1003506",
        "tgn:1000003",
        "tgn:7002993",
        "tgn:1000080",
        "tgn:7029392"
    ],
    "tgn:id":7054526,
    "tgn:name":"Canale Lovato",
    "tgn:placetype":[
        "aat:300006075"
    ]
},
  "bbox": [],
  "geometry": {"coordinates":[13.1,45.683333],"type":"Point"}
}
=======
{"geometry":{"type":"Point","coordinates":[13.100000,45.683333]},"type":"Feature","properties":{"hierarchy":["tgn:7054526","tgn:1003506","tgn:1000003","tgn:7002993","tgn:1000080","tgn:7029392"],"placetype":["aat:300006075"],"id":7054526,"name:xx":"Canale Lovato"}}
>>>>>>> 03f74aca74312dbeaf24d7e61306dd6a786dc3d0
