{
  "id": 2750503,
  "type": "Feature",
  "properties": {
    "tgn:hierarchy":[
        "tgn:2750503",
        "tgn:1000001",
        "tgn:7012149",
        "tgn:2001657",
        "tgn:7007707",
        "tgn:7029392"
    ],
    "tgn:id":2750503,
    "tgn:name":"Wapanucka Lake",
    "tgn:placetype":[
        "aat:300006191"
    ]
},
  "bbox": [],
  "geometry": {"coordinates":[-96.45,34.3667],"type":"Point"}
}