{
  "id": 7063647,
  "type": "Feature",
  "properties": {
    "tgn:hierarchy":[
        "tgn:7063647",
        "tgn:7003692",
        "tgn:1000003",
        "tgn:7000084",
        "tgn:7029392"
    ],
    "tgn:id":7063647,
    "tgn:name":"Anwanden",
    "tgn:placetype":[
        "aat:300000206"
    ]
},
  "bbox": [],
  "geometry": {"coordinates":[10.066667,47.683333],"type":"Point"}
}