{
  "id": 1073309,
  "type": "Feature",
  "properties": {
    "tgn:hierarchy":[
        "tgn:1073309",
        "tgn:1000004",
        "tgn:7016672",
        "tgn:1000111",
        "tgn:7029392"
    ],
    "tgn:id":1073309,
    "tgn:name":"Yangce",
    "tgn:placetype":[
        "aat:300008347"
    ]
},
  "bbox": [],
  "geometry": {"coordinates":[113.25,32.9833],"type":"Point"}
}