{
  "id": 2316713,
  "type": "Feature",
  "properties": {
    "tgn:hierarchy":[
        "tgn:2316713",
        "tgn:1000001",
        "tgn:7012149",
        "tgn:2001142",
        "tgn:7007522",
        "tgn:7029392"
    ],
    "tgn:id":2316713,
    "tgn:name":"Emerald",
    "tgn:placetype":[
        "aat:300008347"
    ]
},
  "bbox": [],
  "geometry": {"coordinates":[-90.35,31.0667],"type":"Point"}
}