{
  "id": 2459939,
  "type": "Feature",
  "properties": {
    "tgn:hierarchy":[
        "tgn:2459939",
        "tgn:1000001",
        "tgn:7012149",
        "tgn:7007157",
        "tgn:2000185",
        "tgn:7029392"
    ],
    "tgn:id":2459939,
    "tgn:name":"Little Rock Creek",
    "tgn:placetype":[
        "aat:300008706"
    ]
},
  "bbox": [],
  "geometry": {"coordinates":[-123.55,39.6333],"type":"Point"}
}