{
  "id": 4008953,
  "type": "Feature",
  "properties": {
    "tgn:hierarchy":[
        "tgn:4008953",
        "tgn:1000003",
        "tgn:7024122",
        "tgn:7006366",
        "tgn:7029392"
    ],
    "tgn:id":4008953,
    "tgn:name":"Pruszyn",
    "tgn:placetype":[
        "aat:300008347"
    ]
},
  "bbox": [],
  "geometry": {"coordinates":[22.4167,52.1833],"type":"Point"}
}