{
  "id": 2212139,
  "type": "Feature",
  "properties": {
    "tgn:hierarchy":[
        "tgn:2212139",
        "tgn:1000001",
        "tgn:7012149",
        "tgn:2001130",
        "tgn:7007522",
        "tgn:7029392"
    ],
    "tgn:id":2212139,
    "tgn:name":"Buzzard Lake",
    "tgn:placetype":[
        "aat:300008680"
    ]
},
  "bbox": [],
  "geometry": {"coordinates":[-90.4333,32.5667],"type":"Point"}
}