{
  "id": 2620110,
  "type": "Feature",
  "properties": {
    "tgn:hierarchy":[
        "tgn:2620110",
        "tgn:1000001",
        "tgn:7012149",
        "tgn:7029392"
    ],
    "tgn:id":2620110,
    "tgn:name":"Risue Canyon",
    "tgn:placetype":[
        "aat:300008761"
    ]
},
  "bbox": [],
  "geometry": {"coordinates":[-119.3833,38.5667],"type":"Point"}
}