{
  "id": 7318158,
  "type": "Feature",
  "properties": {
    "tgn:hierarchy":[
        "tgn:7318158",
        "tgn:1001702",
        "tgn:1000049",
        "tgn:1000002",
        "tgn:7029392"
    ],
    "tgn:id":7318158,
    "tgn:name":"Colorada, Roca",
    "tgn:placetype":[
        "aat:300011692"
    ]
},
  "bbox": [],
  "geometry": {"coordinates":[-75.233333,-51.433333],"type":"Point"}
}