{
  "id": 2438964,
  "type": "Feature",
  "properties": {
    "tgn:hierarchy":[
        "tgn:2438964",
        "tgn:7006450",
        "tgn:1000001",
        "tgn:7012149",
        "tgn:2000085",
        "tgn:7029392"
    ],
    "tgn:id":2438964,
    "tgn:name":"Kinshuda Hill",
    "tgn:placetype":[
        "aat:300008798"
    ]
},
  "bbox": [],
  "geometry": {"coordinates":[-142.4667,62.8833],"type":"Point"}
}