{
  "id": 7413446,
  "type": "Feature",
  "properties": {
    "tgn:hierarchy":[
        "tgn:7413446",
        "tgn:1000001",
        "tgn:7005596",
        "tgn:7005560",
        "tgn:7029392"
    ],
    "tgn:id":7413446,
    "tgn:name:es":"Buenavista",
    "tgn:placetype":[
        "aat:300008347"
    ]
},
  "bbox": [],
  "geometry": {"coordinates":[-92.708333,17.6625],"type":"Point"}
}