{
  "id": 2359435,
  "type": "Feature",
  "properties": {
    "tgn:hierarchy":[
        "tgn:2359435",
        "tgn:1000001",
        "tgn:7012149",
        "tgn:7007157",
        "tgn:2000189",
        "tgn:7029392"
    ],
    "tgn:id":2359435,
    "tgn:name":"Grant Creek",
    "tgn:placetype":[
        "aat:300008706"
    ]
},
  "bbox": [],
  "geometry": {"coordinates":[-123.3833,41.3167],"type":"Point"}
}