{
  "id": 7313334,
  "type": "Feature",
  "properties": {
    "tgn:hierarchy":[
        "tgn:7313334",
        "tgn:1001699",
        "tgn:1000049",
        "tgn:1000002",
        "tgn:7029392"
    ],
    "tgn:id":7313334,
    "tgn:name":"Llonqu\u00e9n, Cerro",
    "tgn:placetype":[
        "aat:300008795"
    ]
},
  "bbox": [],
  "geometry": {"coordinates":[-71.883333,-39.633333],"type":"Point"}
}