{
  "id": 1037313,
  "type": "Feature",
  "properties": {
    "tgn:hierarchy":[
        "tgn:1037313",
        "tgn:1000003",
        "tgn:7000094",
        "tgn:7000084",
        "tgn:7029392"
    ],
    "tgn:id":1037313,
    "tgn:name":"Mirow",
    "tgn:placetype":[
        "aat:300008347"
    ]
},
  "bbox": [],
  "geometry": {"coordinates":[12.816667,53.266667],"type":"Point"}
}