{
  "id": 2412061,
  "type": "Feature",
  "properties": {
    "tgn:hierarchy":[
        "tgn:2412061",
        "tgn:1000001",
        "tgn:7013649",
        "tgn:7012149",
        "tgn:7007251",
        "tgn:7029392"
    ],
    "tgn:id":2412061,
    "tgn:name":"Indian Road Woods",
    "tgn:placetype":[
        "aat:300132451"
    ]
},
  "bbox": [],
  "geometry": {"coordinates":[-87.75,41.9833],"type":"Point"}
}