{
  "id": 7592264,
  "type": "Feature",
  "properties": {
    "tgn:hierarchy":[
        "tgn:7592264",
        "tgn:1000004",
        "tgn:7000198",
        "tgn:7000799",
        "tgn:7029392"
    ],
    "tgn:id":7592264,
    "tgn:name:en":"Chak Bh\u0101gat",
    "tgn:placetype":[
        "aat:300008347"
    ]
},
  "bbox": [],
  "geometry": {"coordinates":[74.953492,32.962631],"type":"Point"}
}