{
  "id": 7148974,
  "type": "Feature",
  "properties": {
    "tgn:hierarchy":[
        "tgn:7148974",
        "tgn:1000003",
        "tgn:7003677",
        "tgn:7000084",
        "tgn:7029392"
    ],
    "tgn:id":7148974,
    "tgn:name":"Krekel",
    "tgn:placetype":[
        "aat:300008347"
    ]
},
  "bbox": [],
  "geometry": {"coordinates":[6.533333,50.466667],"type":"Point"}
}