{
  "id": 7313086,
  "type": "Feature",
  "properties": {
    "tgn:hierarchy":[
        "tgn:7313086",
        "tgn:1001630",
        "tgn:1000049",
        "tgn:1000002",
        "tgn:7029392"
    ],
    "tgn:id":7313086,
    "tgn:name":"Los Chacayes",
    "tgn:placetype":[
        "aat:300008347"
    ]
},
  "bbox": [],
  "geometry": {"coordinates":[-69.911944,-28.876667],"type":"Point"}
}