<<<<<<< HEAD
{
  "id": 2409117,
  "type": "Feature",
  "properties": {
    "tgn:hierarchy":[
        "tgn:2409117",
        "tgn:1000001",
        "tgn:7012149",
        "tgn:2001708",
        "tgn:7007708",
        "tgn:7029392"
    ],
    "tgn:id":2409117,
    "tgn:name":"Ice Creek",
    "tgn:placetype":[
        "aat:300008706"
    ]
},
  "bbox": [],
  "geometry": {"coordinates":[-119.0667,43.8167],"type":"Point"}
}
=======
{"geometry":{"type":"Point","coordinates":[-119.066700,43.816700]},"type":"Feature","properties":{"hierarchy":["tgn:2409117","tgn:1000001","tgn:7012149","tgn:2001708","tgn:7007708","tgn:7029392"],"placetype":["aat:300008706"],"id":2409117,"name:xx":"Ice Creek"}}
>>>>>>> 03f74aca74312dbeaf24d7e61306dd6a786dc3d0
