{
  "id": 2409117,
  "type": "Feature",
  "properties": {
    "tgn:hierarchy":[
        "tgn:2409117",
        "tgn:1000001",
        "tgn:7012149",
        "tgn:2001708",
        "tgn:7007708",
        "tgn:7029392"
    ],
    "tgn:id":2409117,
    "tgn:name":"Ice Creek",
    "tgn:placetype":[
        "aat:300008706"
    ]
},
  "bbox": [],
  "geometry": {"coordinates":[-119.0667,43.8167],"type":"Point"}
}