{
  "id": 2031601,
  "type": "Feature",
  "properties": {
    "tgn:hierarchy":[
        "tgn:2031601",
        "tgn:1000001",
        "tgn:1002327",
        "tgn:7012149",
        "tgn:7007252",
        "tgn:7029392"
    ],
    "tgn:id":2031601,
    "tgn:name":"Desoto",
    "tgn:placetype":[
        "aat:300008347"
    ]
},
  "bbox": [],
  "geometry": {"coordinates":[-85.2833,40.2333],"type":"Point"}
}