{
  "id": 7486798,
  "type": "Feature",
  "properties": {
    "tgn:hierarchy":[
        "tgn:7486798",
        "tgn:7001010",
        "tgn:1000004",
        "tgn:1000141",
        "tgn:7029392"
    ],
    "tgn:id":7486798,
    "tgn:name":"Shibi Shan",
    "tgn:placetype":[
        "aat:300008798"
    ]
},
  "bbox": [],
  "geometry": {"coordinates":[121.226667,23.198056],"type":"Point"}
}