{
  "id": 2452254,
  "type": "Feature",
  "properties": {
    "tgn:hierarchy":[
        "tgn:2452254",
        "tgn:7002659",
        "tgn:1000001",
        "tgn:7012149",
        "tgn:2000028",
        "tgn:7029392"
    ],
    "tgn:id":2452254,
    "tgn:name":"Little Blue Water Creek",
    "tgn:placetype":[
        "aat:300008706"
    ]
},
  "bbox": [],
  "geometry": {"coordinates":[-87.4667,33.6333],"type":"Point"}
}