{
  "id": 2629293,
  "type": "Feature",
  "properties": {
    "tgn:hierarchy":[
        "tgn:2629293",
        "tgn:1000001",
        "tgn:7012149",
        "tgn:2001709",
        "tgn:7007708",
        "tgn:7029392"
    ],
    "tgn:id":2629293,
    "tgn:name":"Rosebriar Creek",
    "tgn:placetype":[
        "aat:300008706"
    ]
},
  "bbox": [],
  "geometry": {"coordinates":[-118.35,42.15],"type":"Point"}
}