{
  "id": 2612167,
  "type": "Feature",
  "properties": {
    "tgn:hierarchy":[
        "tgn:2612167",
        "tgn:1000001",
        "tgn:7012149",
        "tgn:7007157",
        "tgn:1002858",
        "tgn:7029392"
    ],
    "tgn:id":2612167,
    "tgn:name":"Red Rose Quarry",
    "tgn:placetype":[
        "aat:300000390"
    ]
},
  "bbox": [],
  "geometry": {"coordinates":[-116.85,32.8167],"type":"Point"}
}