{
  "id": 1135877,
  "type": "Feature",
  "properties": {
    "tgn:hierarchy":[
        "tgn:1135877",
        "tgn:1000004",
        "tgn:7002081",
        "tgn:1000111",
        "tgn:7029392"
    ],
    "tgn:id":1135877,
    "tgn:name":"Chuanchang",
    "tgn:placetype":[
        "aat:300006075"
    ]
},
  "bbox": [],
  "geometry": {"coordinates":[119.85,33.7667],"type":"Point"}
}