<<<<<<< HEAD
{
  "id": 7487303,
  "type": "Feature",
  "properties": {
    "tgn:hierarchy":[
        "tgn:7487303",
        "tgn:1000004",
        "tgn:7001009",
        "tgn:1000141",
        "tgn:7029392"
    ],
    "tgn:id":7487303,
    "tgn:name":"Mindeqiao",
    "tgn:placetype":[
        "aat:300008347"
    ]
},
  "bbox": [],
  "geometry": {"coordinates":[120.766667,24.2],"type":"Point"}
}
=======
{"geometry":{"type":"Point","coordinates":[120.766667,24.200000]},"type":"Feature","properties":{"hierarchy":["tgn:7487303","tgn:1000004","tgn:7001009","tgn:1000141","tgn:7029392"],"placetype":["aat:300008347"],"id":7487303,"name:xx":"Mindeqiao"}}
>>>>>>> 03f74aca74312dbeaf24d7e61306dd6a786dc3d0
