{
  "id": 2648765,
  "type": "Feature",
  "properties": {
    "tgn:hierarchy":[
        "tgn:2648765",
        "tgn:1000001",
        "tgn:7012149",
        "tgn:7015666",
        "tgn:7007825",
        "tgn:7029392"
    ],
    "tgn:id":2648765,
    "tgn:name":"Scotch Hollow",
    "tgn:placetype":[
        "aat:300008761"
    ]
},
  "bbox": [],
  "geometry": {"coordinates":[-87.45,35.65],"type":"Point"}
}