{
  "id": 2467181,
  "type": "Feature",
  "properties": {
    "tgn:hierarchy":[
        "tgn:2467181",
        "tgn:1000001",
        "tgn:7012149",
        "tgn:2000290",
        "tgn:7007240",
        "tgn:7029392"
    ],
    "tgn:id":2467181,
    "tgn:name":"Long Creek Bay",
    "tgn:placetype":[
        "aat:300008905"
    ]
},
  "bbox": [],
  "geometry": {"coordinates":[-86.3833,30.8167],"type":"Point"}
}