{
  "id": 7026995,
  "type": "Feature",
  "properties": {
    "tgn:hierarchy":[
        "tgn:7026995",
        "tgn:7002445",
        "tgn:1000003",
        "tgn:7008143",
        "tgn:7008591",
        "tgn:7029392"
    ],
    "tgn:id":7026995,
    "tgn:name:en":"Ashperton",
    "tgn:placetype":[
        "aat:300008347",
        "aat:300008372"
    ]
},
  "bbox": [],
  "geometry": {"coordinates":[-2.516667,52.066667],"type":"Point"}
}