{
  "id": 1030835,
  "type": "Feature",
  "properties": {
    "tgn:hierarchy":[
        "tgn:1030835",
        "tgn:7002445",
        "tgn:1000003",
        "tgn:7008154",
        "tgn:7008591",
        "tgn:7029392"
    ],
    "tgn:id":1030835,
    "tgn:name:en":"Tarleton",
    "tgn:placetype":[
        "aat:300008347"
    ]
},
  "bbox": [],
  "geometry": {"coordinates":[-2.833333,53.666667],"type":"Point"}
}