{
  "id": 2289858,
  "type": "Feature",
  "properties": {
    "tgn:hierarchy":[
        "tgn:2289858",
        "tgn:1000001",
        "tgn:7012149",
        "tgn:2001769",
        "tgn:7007712",
        "tgn:7029392"
    ],
    "tgn:id":2289858,
    "tgn:name":"Dobson Bay",
    "tgn:placetype":[
        "aat:300386845"
    ]
},
  "bbox": [],
  "geometry": {"coordinates":[-79.5833,33.5833],"type":"Point"}
}