{
  "id": 2602764,
  "type": "Feature",
  "properties": {
    "tgn:hierarchy":[
        "tgn:2602764",
        "tgn:7006450",
        "tgn:1000001",
        "tgn:7019698",
        "tgn:7012149",
        "tgn:7029392"
    ],
    "tgn:id":2602764,
    "tgn:name":"Quake Lake",
    "tgn:placetype":[
        "aat:300008680"
    ]
},
  "bbox": [],
  "geometry": {"coordinates":[-150.8667,60.6167],"type":"Point"}
}