{
  "id": 7225570,
  "type": "Feature",
  "properties": {
    "tgn:hierarchy":[
        "tgn:7225570",
        "tgn:7002750",
        "tgn:7001399",
        "tgn:1000003",
        "tgn:1000074",
        "tgn:7029392"
    ],
    "tgn:id":7225570,
    "tgn:name":"Per\u00edvlepton",
    "tgn:placetype":[
        "aat:300008347"
    ]
},
  "bbox": [],
  "geometry": {"coordinates":[22.683333,39.316667],"type":"Point"}
}