<<<<<<< HEAD
{
  "id": 7365727,
  "type": "Feature",
  "properties": {
    "tgn:hierarchy":[
        "tgn:7365727",
        "tgn:1001853",
        "tgn:1000001",
        "tgn:7005560",
        "tgn:7029392"
    ],
    "tgn:id":7365727,
    "tgn:name":"Gabino V\u00e1zquez",
    "tgn:placetype":[
        "aat:300008347"
    ]
},
  "bbox": [],
  "geometry": {"coordinates":[-103.05,25.466667],"type":"Point"}
}
=======
{"geometry":{"type":"Point","coordinates":[-103.050000,25.466667]},"type":"Feature","properties":{"hierarchy":["tgn:7365727","tgn:1001853","tgn:1000001","tgn:7005560","tgn:7029392"],"placetype":["aat:300008347"],"id":7365727,"name:xx":"Gabino V\u00e1zquez"}}
>>>>>>> 03f74aca74312dbeaf24d7e61306dd6a786dc3d0
