{
  "id": 2146634,
  "type": "Feature",
  "properties": {
    "tgn:hierarchy":[
        "tgn:2146634",
        "tgn:1000001",
        "tgn:7016172",
        "tgn:7012149",
        "tgn:2000137",
        "tgn:7029392"
    ],
    "tgn:id":2146634,
    "tgn:name":"Band Mill Creek",
    "tgn:placetype":[
        "aat:300008706"
    ]
},
  "bbox": [],
  "geometry": {"coordinates":[-91.9833,36.1333],"type":"Point"}
}