{
  "id": 1130442,
  "type": "Feature",
  "properties": {
    "tgn:hierarchy":[
        "tgn:1130442",
        "tgn:7001242",
        "tgn:1000149",
        "tgn:1000888",
        "tgn:7029392"
    ],
    "tgn:id":1130442,
    "tgn:name":"Sussa",
    "tgn:placetype":[
        "aat:300008707"
    ]
},
  "bbox": [],
  "geometry": {"coordinates":[17.0833,-7.3667],"type":"Point"}
}