{
  "id": 7237864,
  "type": "Feature",
  "properties": {
    "tgn:hierarchy":[
        "tgn:7237864",
        "tgn:7003466",
        "tgn:1000003",
        "tgn:1000063",
        "tgn:4012014",
        "tgn:7029392"
    ],
    "tgn:id":7237864,
    "tgn:name":"Herock",
    "tgn:placetype":[
        "aat:300008347"
    ]
},
  "bbox": [],
  "geometry": {"coordinates":[5.05,50.183333],"type":"Point"}
}