{
  "id": 1107314,
  "type": "Feature",
  "properties": {
    "tgn:hierarchy":[
        "tgn:1107314",
        "tgn:7005735",
        "tgn:7005685",
        "tgn:1000001",
        "tgn:7029392"
    ],
    "tgn:id":1107314,
    "tgn:name":"Howson Peak",
    "tgn:placetype":[
        "aat:300008798"
    ]
},
  "bbox": [],
  "geometry": {"coordinates":[-127.7333,54.4167],"type":"Point"}
}