<<<<<<< HEAD
{
  "id": 2400463,
  "type": "Feature",
  "properties": {
    "tgn:hierarchy":[
        "tgn:2400463",
        "tgn:1000001",
        "tgn:7012149",
        "tgn:2001137",
        "tgn:7007522",
        "tgn:7029392"
    ],
    "tgn:id":2400463,
    "tgn:name":"Horse Hunters Creek",
    "tgn:placetype":[
        "aat:300008706"
    ]
},
  "bbox": [],
  "geometry": {"coordinates":[-88.55,33.25],"type":"Point"}
}
=======
{"geometry":{"type":"Point","coordinates":[-88.550000,33.250000]},"type":"Feature","properties":{"hierarchy":["tgn:2400463","tgn:1000001","tgn:7012149","tgn:2001137","tgn:7007522","tgn:7029392"],"placetype":["aat:300008706"],"id":2400463,"name:xx":"Horse Hunters Creek"}}
>>>>>>> 03f74aca74312dbeaf24d7e61306dd6a786dc3d0
