{
  "id": 1061565,
  "type": "Feature",
  "properties": {
    "tgn:hierarchy":[
        "tgn:1061565",
        "tgn:1000004",
        "tgn:7014474",
        "tgn:7018214",
        "tgn:7002435",
        "tgn:7029392"
    ],
    "tgn:id":1061565,
    "tgn:name":"Zavety Ilicha",
    "tgn:placetype":[
        "aat:300008347"
    ]
},
  "bbox": [],
  "geometry": {"coordinates":[140.3333,49.0333],"type":"Point"}
}