{
  "id": 7511923,
  "type": "Feature",
  "properties": {
    "tgn:hierarchy":[
        "tgn:7511923",
        "tgn:1008380",
        "tgn:1000226",
        "tgn:7016827",
        "tgn:1000006",
        "tgn:7029392"
    ],
    "tgn:id":7511923,
    "tgn:name:en":"Kaitane",
    "tgn:placetype":[
        "aat:300008699"
    ]
},
  "bbox": [],
  "geometry": {"coordinates":[174.983333,-39.416667],"type":"Point"}
}