{
  "id": 1117793,
  "type": "Feature",
  "properties": {
    "tgn:hierarchy":[
        "tgn:1117793",
        "tgn:1000001",
        "tgn:7013649",
        "tgn:7012149",
        "tgn:7007251",
        "tgn:7029392"
    ],
    "tgn:id":1117793,
    "tgn:name":"Powder Horn Lake",
    "tgn:placetype":[
        "aat:300008680"
    ]
},
  "bbox": [],
  "geometry": {"coordinates":[-87.5167,41.6333],"type":"Point"}
}