{
  "id": 2133973,
  "type": "Feature",
  "properties": {
    "tgn:hierarchy":[
        "tgn:2133973",
        "tgn:1000001",
        "tgn:7016172",
        "tgn:2000120",
        "tgn:7012149",
        "tgn:7029392"
    ],
    "tgn:id":2133973,
    "tgn:name":"Angle Ditch Lateral Number 4",
    "tgn:placetype":[
        "aat:300006075"
    ]
},
  "bbox": [],
  "geometry": {"coordinates":[-90.9333,35.7333],"type":"Point"}
}