{
  "id": 7428047,
  "type": "Feature",
  "properties": {
    "tgn:hierarchy":[
        "tgn:7428047",
        "tgn:1000001",
        "tgn:7005601",
        "tgn:7005560",
        "tgn:7029392"
    ],
    "tgn:id":7428047,
    "tgn:name":"San Rafael",
    "tgn:placetype":[
        "aat:300008347"
    ]
},
  "bbox": [],
  "geometry": {"coordinates":[-103.783333,23.583333],"type":"Point"}
}