{
  "id": 7585270,
  "type": "Feature",
  "properties": {
    "tgn:hierarchy":[
        "tgn:7585270",
        "tgn:1000004",
        "tgn:7000198",
        "tgn:1001894",
        "tgn:7029392"
    ],
    "tgn:id":7585270,
    "tgn:name:en":"Khiri\u0101gh\u0101t",
    "tgn:placetype":[
        "aat:300008347"
    ]
},
  "bbox": [],
  "geometry": {"coordinates":[78.787932,24.60461],"type":"Point"}
}