<<<<<<< HEAD
{
  "id": 7361401,
  "type": "Feature",
  "properties": {
    "tgn:hierarchy":[
        "tgn:7361401",
        "tgn:1001835",
        "tgn:1000001",
        "tgn:7005560",
        "tgn:7029392"
    ],
    "tgn:id":7361401,
    "tgn:name":"El Islote",
    "tgn:placetype":[
        "aat:300011692"
    ]
},
  "bbox": [],
  "geometry": {"coordinates":[-116.7,31.55],"type":"Point"}
}
=======
{"geometry":{"type":"Point","coordinates":[-116.700000,31.550000]},"type":"Feature","properties":{"hierarchy":["tgn:7361401","tgn:1001835","tgn:1000001","tgn:7005560","tgn:7029392"],"placetype":["aat:300011692"],"id":7361401,"name:xx":"El Islote"}}
>>>>>>> 03f74aca74312dbeaf24d7e61306dd6a786dc3d0
