{
  "id": 2393267,
  "type": "Feature",
  "properties": {
    "tgn:hierarchy":[
        "tgn:2393267",
        "tgn:1000001",
        "tgn:7012149",
        "tgn:7007157",
        "tgn:1002656",
        "tgn:7029392"
    ],
    "tgn:id":2393267,
    "tgn:name":"Hoffman Canyon",
    "tgn:placetype":[
        "aat:300008761"
    ]
},
  "bbox": [],
  "geometry": {"coordinates":[-121.0333,36.8667],"type":"Point"}
}