{
  "id": 7285441,
  "type": "Feature",
  "properties": {
    "tgn:hierarchy":[
        "tgn:7285441",
        "tgn:1001637",
        "tgn:1000049",
        "tgn:1000002",
        "tgn:7029392"
    ],
    "tgn:id":7285441,
    "tgn:name":"Pichipolcura, Cordillera",
    "tgn:placetype":[
        "aat:300008795"
    ]
},
  "bbox": [],
  "geometry": {"coordinates":[-71.533333,-37.266667],"type":"Point"}
}