{
  "id": 2729870,
  "type": "Feature",
  "properties": {
    "tgn:hierarchy":[
        "tgn:2729870",
        "tgn:1000001",
        "tgn:7012149",
        "tgn:1002758",
        "tgn:7007568",
        "tgn:7029392"
    ],
    "tgn:id":2729870,
    "tgn:name":"Trout Brook",
    "tgn:placetype":[
        "aat:300008699"
    ]
},
  "bbox": [],
  "geometry": {"coordinates":[-75.9167,43.65],"type":"Point"}
}