{
  "id": 1058797,
  "type": "Feature",
  "properties": {
    "tgn:hierarchy":[
        "tgn:1058797",
        "tgn:7012152",
        "tgn:1000003",
        "tgn:7006541",
        "tgn:7029392"
    ],
    "tgn:id":1058797,
    "tgn:name":"R\u016bjiena",
    "tgn:placetype":[
        "aat:300008347"
    ]
},
  "bbox": [],
  "geometry": {"coordinates":[25.3167,57.85],"type":"Point"}
}