{
  "id": 2714029,
  "type": "Feature",
  "properties": {
    "tgn:hierarchy":[
        "tgn:2714029",
        "tgn:1000001",
        "tgn:7012149",
        "tgn:2002090",
        "tgn:7007826",
        "tgn:7029392"
    ],
    "tgn:id":2714029,
    "tgn:name":"Tejones Creek",
    "tgn:placetype":[
        "aat:300008706"
    ]
},
  "bbox": [],
  "geometry": {"coordinates":[-99.4667,27.8667],"type":"Point"}
}