{
  "id": 2439567,
  "type": "Feature",
  "properties": {
    "tgn:hierarchy":[
        "tgn:2439567",
        "tgn:1000001",
        "tgn:7012149",
        "tgn:1002786",
        "tgn:7007251",
        "tgn:7029392"
    ],
    "tgn:id":2439567,
    "tgn:name":"Kiser Creek Diversion Ditch",
    "tgn:placetype":[
        "aat:300006075"
    ]
},
  "bbox": [],
  "geometry": {"coordinates":[-91.0833,39.5833],"type":"Point"}
}