<<<<<<< HEAD
{
  "id": 7054052,
  "type": "Feature",
  "properties": {
    "tgn:hierarchy":[
        "tgn:7054052",
        "tgn:1003432",
        "tgn:1000003",
        "tgn:7003240",
        "tgn:1000080",
        "tgn:7029392"
    ],
    "tgn:id":7054052,
    "tgn:name":"Montappone",
    "tgn:placetype":[
        "aat:300008347"
    ]
},
  "bbox": [],
  "geometry": {"coordinates":[13.466667,43.133333],"type":"Point"}
}
=======
{"geometry":{"type":"Point","coordinates":[13.466667,43.133333]},"type":"Feature","properties":{"hierarchy":["tgn:7054052","tgn:1003432","tgn:1000003","tgn:7003240","tgn:1000080","tgn:7029392"],"placetype":["aat:300008347"],"id":7054052,"name:xx":"Montappone"}}
>>>>>>> 03f74aca74312dbeaf24d7e61306dd6a786dc3d0
