<<<<<<< HEAD
{
  "id": 2408766,
  "type": "Feature",
  "properties": {
    "tgn:hierarchy":[
        "tgn:2408766",
        "tgn:1000001",
        "tgn:1002840",
        "tgn:7012149",
        "tgn:7007828",
        "tgn:7029392"
    ],
    "tgn:id":2408766,
    "tgn:name":"Hyde Manor",
    "tgn:placetype":[
        "aat:300008347"
    ]
},
  "bbox": [],
  "geometry": {"coordinates":[-73.2,43.7833],"type":"Point"}
}
=======
{"geometry":{"type":"Point","coordinates":[-73.200000,43.783300]},"type":"Feature","properties":{"hierarchy":["tgn:2408766","tgn:1000001","tgn:1002840","tgn:7012149","tgn:7007828","tgn:7029392"],"placetype":["aat:300008347"],"id":2408766,"name:xx":"Hyde Manor"}}
>>>>>>> 03f74aca74312dbeaf24d7e61306dd6a786dc3d0
