{
  "id": 2770411,
  "type": "Feature",
  "properties": {
    "tgn:hierarchy":[
        "tgn:2770411",
        "tgn:1000001",
        "tgn:2002368",
        "tgn:7012149",
        "tgn:7007923",
        "tgn:7029392"
    ],
    "tgn:id":2770411,
    "tgn:name":"Wild Horse Mountain",
    "tgn:placetype":[
        "aat:300008798"
    ]
},
  "bbox": [],
  "geometry": {"coordinates":[-107.0833,42.0167],"type":"Point"}
}