{
  "id": 2599971,
  "type": "Feature",
  "properties": {
    "tgn:hierarchy":[
        "tgn:2599971",
        "tgn:1000001",
        "tgn:7012149",
        "tgn:7029392"
    ],
    "tgn:id":2599971,
    "tgn:name":"Pruett Mountain",
    "tgn:placetype":[
        "aat:300008798"
    ]
},
  "bbox": [],
  "geometry": {"coordinates":[-82.4333,35.1667],"type":"Point"}
}