{
  "id": 2674797,
  "type": "Feature",
  "properties": {
    "tgn:hierarchy":[
        "tgn:2674797",
        "tgn:1000001",
        "tgn:7012149",
        "tgn:7007157",
        "tgn:1002828",
        "tgn:7029392"
    ],
    "tgn:id":2674797,
    "tgn:name":"Soboba Indian Reservation",
    "tgn:placetype":[
        "aat:300008178",
        "aat:300387324"
    ]
},
  "bbox": [],
  "geometry": {"coordinates":[-116.8833,33.7667],"type":"Point"}
}