{
  "id": 2360865,
  "type": "Feature",
  "properties": {
    "tgn:hierarchy":[
        "tgn:2360865",
        "tgn:1000001",
        "tgn:7006451",
        "tgn:7012149",
        "tgn:2000098",
        "tgn:7029392"
    ],
    "tgn:id":2360865,
    "tgn:name":"Grassy Mountain",
    "tgn:placetype":[
        "aat:300008798"
    ]
},
  "bbox": [],
  "geometry": {"coordinates":[-113.4667,36.2667],"type":"Point"}
}