{
  "id": 7319398,
  "type": "Feature",
  "properties": {
    "tgn:hierarchy":[
        "tgn:7319398",
        "tgn:1001630",
        "tgn:1000049",
        "tgn:1000002",
        "tgn:7029392"
    ],
    "tgn:id":7319398,
    "tgn:name":"Amarga, Agua",
    "tgn:placetype":[
        "aat:300008697"
    ]
},
  "bbox": [],
  "geometry": {"coordinates":[-69.55,-26.833333],"type":"Point"}
}