{
  "id": 7551435,
  "type": "Feature",
  "properties": {
    "tgn:hierarchy":[
        "tgn:7551435",
        "tgn:7001819",
        "tgn:1000004",
        "tgn:7000198",
        "tgn:7029392"
    ],
    "tgn:id":7551435,
    "tgn:name:en":"Bogu",
    "tgn:placetype":[
        "aat:300008347"
    ]
},
  "bbox": [],
  "geometry": {"coordinates":[94.664344,28.533549],"type":"Point"}
}