{
  "id": 2427227,
  "type": "Feature",
  "properties": {
    "tgn:hierarchy":[
        "tgn:2427227",
        "tgn:1000001",
        "tgn:2001702",
        "tgn:7012149",
        "tgn:7007708",
        "tgn:7029392"
    ],
    "tgn:id":2427227,
    "tgn:name":"Jordan Cove",
    "tgn:placetype":[
        "aat:300132316"
    ]
},
  "bbox": [],
  "geometry": {"coordinates":[-124.2333,43.4167],"type":"Point"}
}