{
  "id": 2059408,
  "type": "Feature",
  "properties": {
    "tgn:hierarchy":[
        "tgn:2059408",
        "tgn:1000001",
        "tgn:7012149",
        "tgn:2001235",
        "tgn:7007523",
        "tgn:7029392"
    ],
    "tgn:id":2059408,
    "tgn:name":"Knoxville",
    "tgn:placetype":[
        "aat:300008347"
    ]
},
  "bbox": [],
  "geometry": {"coordinates":[-94.0167,39.4333],"type":"Point"}
}