{
  "id": 1088249,
  "type": "Feature",
  "properties": {
    "tgn:hierarchy":[
        "tgn:1088249",
        "tgn:1001394",
        "tgn:7001242",
        "tgn:1000153",
        "tgn:7029392"
    ],
    "tgn:id":1088249,
    "tgn:name":"Mouanko",
    "tgn:placetype":[
        "aat:300008347"
    ]
},
  "bbox": [],
  "geometry": {"coordinates":[9.8167,3.65],"type":"Point"}
}