{
  "id": 2585473,
  "type": "Feature",
  "properties": {
    "tgn:hierarchy":[
        "tgn:2585473",
        "tgn:2000934",
        "tgn:1000001",
        "tgn:7012149",
        "tgn:7007516",
        "tgn:7029392"
    ],
    "tgn:id":2585473,
    "tgn:name":"Pinto Utilities Reservoir",
    "tgn:placetype":[
        "aat:300006191"
    ]
},
  "bbox": [],
  "geometry": {"coordinates":[-78.85,39.5833],"type":"Point"}
}