{
  "id": 1044260,
  "type": "Feature",
  "properties": {
    "tgn:hierarchy":[
        "tgn:1044260",
        "tgn:7003007",
        "tgn:1000003",
        "tgn:7002997",
        "tgn:1000080",
        "tgn:7029392"
    ],
    "tgn:id":1044260,
    "tgn:name":"Cisano",
    "tgn:placetype":[
        "aat:300008347"
    ]
},
  "bbox": [],
  "geometry": {"coordinates":[10.7167,45.5333],"type":"Point"}
}