{
  "id": 2607362,
  "type": "Feature",
  "properties": {
    "tgn:hierarchy":[
        "tgn:2607362",
        "tgn:1000001",
        "tgn:7012149",
        "tgn:2000550",
        "tgn:7007252",
        "tgn:7029392"
    ],
    "tgn:id":2607362,
    "tgn:name":"Ranger",
    "tgn:placetype":[
        "aat:300008347"
    ]
},
  "bbox": [],
  "geometry": {"coordinates":[-86.6833,38.0833],"type":"Point"}
}