{
  "id": 7012174,
  "type": "Feature",
  "properties": {
    "tgn:hierarchy":[
        "tgn:7012174",
        "tgn:7011626",
        "tgn:1000004",
        "tgn:7014835",
        "tgn:7029392"
    ],
    "tgn:id":7012174,
    "tgn:name":"Zaresskoje, Ozero",
    "tgn:placetype":[
        "aat:300008680"
    ]
},
  "bbox": [],
  "geometry": {"coordinates":[72.75,38.2167],"type":"Point"}
}