{
  "id": 7069578,
  "type": "Feature",
  "properties": {
    "tgn:hierarchy":[
        "tgn:7069578",
        "tgn:1000003",
        "tgn:7003677",
        "tgn:7000084",
        "tgn:7029392"
    ],
    "tgn:id":7069578,
    "tgn:name":"Thom\u00e4",
    "tgn:placetype":[
        "aat:300387200"
    ]
},
  "bbox": [],
  "geometry": {"coordinates":[8.133333,51.566667],"type":"Point"}
}