{
  "id": 2152185,
  "type": "Feature",
  "properties": {
    "tgn:hierarchy":[
        "tgn:2152185",
        "tgn:1000001",
        "tgn:7012149",
        "tgn:2000908",
        "tgn:7007256",
        "tgn:7029392"
    ],
    "tgn:id":2152185,
    "tgn:name":"Bay Blanc",
    "tgn:placetype":[
        "aat:300132316"
    ]
},
  "bbox": [],
  "geometry": {"coordinates":[-90.7167,29.1167],"type":"Point"}
}