<<<<<<< HEAD
{
  "id": 2760646,
  "type": "Feature",
  "properties": {
    "tgn:hierarchy":[
        "tgn:2760646",
        "tgn:1000001",
        "tgn:7012149",
        "tgn:2001440",
        "tgn:7007566",
        "tgn:7029392"
    ],
    "tgn:id":2760646,
    "tgn:name":"West Fork Windham Canyon",
    "tgn:placetype":[
        "aat:300008761"
    ]
},
  "bbox": [],
  "geometry": {"coordinates":[-108.95,32.7667],"type":"Point"}
}
=======
{"geometry":{"type":"Point","coordinates":[-108.950000,32.766700]},"type":"Feature","properties":{"hierarchy":["tgn:2760646","tgn:1000001","tgn:7012149","tgn:2001440","tgn:7007566","tgn:7029392"],"placetype":["aat:300008761"],"id":2760646,"name:xx":"West Fork Windham Canyon"}}
>>>>>>> 03f74aca74312dbeaf24d7e61306dd6a786dc3d0
