<<<<<<< HEAD
{
  "id": 7055859,
  "type": "Feature",
  "properties": {
    "tgn:hierarchy":[
        "tgn:7055859",
        "tgn:1003464",
        "tgn:1000003",
        "tgn:7003241",
        "tgn:1000080",
        "tgn:7029392"
    ],
    "tgn:id":7055859,
    "tgn:name":"Pizzi, Monte",
    "tgn:placetype":[
        "aat:300008795"
    ]
},
  "bbox": [],
  "geometry": {"coordinates":[14.266667,41.75],"type":"Point"}
}
=======
{"geometry":{"type":"Point","coordinates":[14.266667,41.750000]},"type":"Feature","properties":{"hierarchy":["tgn:7055859","tgn:1003464","tgn:1000003","tgn:7003241","tgn:1000080","tgn:7029392"],"placetype":["aat:300008795"],"id":7055859,"name:xx":"Pizzi, Monte"}}
>>>>>>> 03f74aca74312dbeaf24d7e61306dd6a786dc3d0
