{
  "id": 2740075,
  "type": "Feature",
  "properties": {
    "tgn:hierarchy":[
        "tgn:2740075",
        "tgn:1000001",
        "tgn:7012149",
        "tgn:1002999",
        "tgn:7007526",
        "tgn:7029392"
    ],
    "tgn:id":2740075,
    "tgn:name":"Upper High Rock Canyon",
    "tgn:placetype":[
        "aat:300008761"
    ]
},
  "bbox": [],
  "geometry": {"coordinates":[-119.5333,41.5167],"type":"Point"}
}