{
  "id": 2102163,
  "type": "Feature",
  "properties": {
    "tgn:hierarchy":[
        "tgn:2102163",
        "tgn:1000001",
        "tgn:7012149",
        "tgn:2001919",
        "tgn:7007825",
        "tgn:7029392"
    ],
    "tgn:id":2102163,
    "tgn:name":"Wolf Hill",
    "tgn:placetype":[
        "aat:300387210",
        "aat:300008798"
    ]
},
  "bbox": [],
  "geometry": {"coordinates":[-86.2333,36.45],"type":"Point"}
}