{
  "id": 2582991,
  "type": "Feature",
  "properties": {
    "tgn:hierarchy":[
        "tgn:2582991",
        "tgn:1000001",
        "tgn:7012149",
        "tgn:2000183",
        "tgn:7007157",
        "tgn:7029392"
    ],
    "tgn:id":2582991,
    "tgn:name":"Pine Lake",
    "tgn:placetype":[
        "aat:300008680"
    ]
},
  "bbox": [],
  "geometry": {"coordinates":[-118.7167,37.35],"type":"Point"}
}