<<<<<<< HEAD
{
  "id": 2333941,
  "type": "Feature",
  "properties": {
    "tgn:hierarchy":[
        "tgn:2333941",
        "tgn:1000001",
        "tgn:7012149",
        "tgn:2001926",
        "tgn:7007825",
        "tgn:7029392"
    ],
    "tgn:id":2333941,
    "tgn:name":"Ford Creek",
    "tgn:placetype":[
        "aat:300008706"
    ]
},
  "bbox": [],
  "geometry": {"coordinates":[-82.4833,36.3667],"type":"Point"}
}
=======
{"geometry":{"type":"Point","coordinates":[-82.483300,36.366700]},"type":"Feature","properties":{"hierarchy":["tgn:2333941","tgn:1000001","tgn:7012149","tgn:2001926","tgn:7007825","tgn:7029392"],"placetype":["aat:300008706"],"id":2333941,"name:xx":"Ford Creek"}}
>>>>>>> 03f74aca74312dbeaf24d7e61306dd6a786dc3d0
