{
  "id": 2184991,
  "type": "Feature",
  "properties": {
    "tgn:hierarchy":[
        "tgn:2184991",
        "tgn:1000001",
        "tgn:7012149",
        "tgn:2000546",
        "tgn:7007252",
        "tgn:7029392"
    ],
    "tgn:id":2184991,
    "tgn:name":"Boggs Creek",
    "tgn:placetype":[
        "aat:300008706"
    ]
},
  "bbox": [],
  "geometry": {"coordinates":[-86.8333,38.8667],"type":"Point"}
}