<<<<<<< HEAD
{
  "id": 2152088,
  "type": "Feature",
  "properties": {
    "tgn:hierarchy":[
        "tgn:2152088",
        "tgn:1000001",
        "tgn:2000871",
        "tgn:7012149",
        "tgn:7007256",
        "tgn:7029392"
    ],
    "tgn:id":2152088,
    "tgn:name":"Baxter Bayou",
    "tgn:placetype":[
        "aat:300008699"
    ]
},
  "bbox": [],
  "geometry": {"coordinates":[-91.2167,32.8333],"type":"Point"}
}
=======
{"geometry":{"type":"Point","coordinates":[-91.216700,32.833300]},"type":"Feature","properties":{"hierarchy":["tgn:2152088","tgn:1000001","tgn:2000871","tgn:7012149","tgn:7007256","tgn:7029392"],"placetype":["aat:300008699"],"id":2152088,"name:xx":"Baxter Bayou"}}
>>>>>>> 03f74aca74312dbeaf24d7e61306dd6a786dc3d0
