{
  "id": 2587659,
  "type": "Feature",
  "properties": {
    "tgn:hierarchy":[
        "tgn:2587659",
        "tgn:1000001",
        "tgn:7012149",
        "tgn:2000926",
        "tgn:7007515",
        "tgn:7029392"
    ],
    "tgn:id":2587659,
    "tgn:name":"Pleasant River",
    "tgn:placetype":[
        "aat:300008707"
    ]
},
  "bbox": [],
  "geometry": {"coordinates":[-70.8167,44.35],"type":"Point"}
}