{
  "id": 2376429,
  "type": "Feature",
  "properties": {
    "tgn:hierarchy":[
        "tgn:2376429",
        "tgn:1000001",
        "tgn:7012149",
        "tgn:7007713",
        "tgn:7029392"
    ],
    "tgn:id":2376429,
    "tgn:name":"Harding Creek",
    "tgn:placetype":[
        "aat:300008706"
    ]
},
  "bbox": [],
  "geometry": {"coordinates":[-101.6833,44.4167],"type":"Point"}
}