{
  "id": 2688630,
  "type": "Feature",
  "properties": {
    "tgn:hierarchy":[
        "tgn:2688630",
        "tgn:1000001",
        "tgn:7012149",
        "tgn:1002904",
        "tgn:7007710",
        "tgn:7029392"
    ],
    "tgn:id":2688630,
    "tgn:name":"Spruce Run",
    "tgn:placetype":[
        "aat:300008699"
    ]
},
  "bbox": [],
  "geometry": {"coordinates":[-78.8333,40.2167],"type":"Point"}
}