{
  "id": 2710866,
  "type": "Feature",
  "properties": {
    "tgn:hierarchy":[
        "tgn:2710866",
        "tgn:1000001",
        "tgn:1002328",
        "tgn:7012149",
        "tgn:7007568",
        "tgn:7029392"
    ],
    "tgn:id":2710866,
    "tgn:name":"Tanglewood Lake",
    "tgn:placetype":[
        "aat:300006191"
    ]
},
  "bbox": [],
  "geometry": {"coordinates":[-74.8667,42.2167],"type":"Point"}
}