{
  "id": 2706693,
  "type": "Feature",
  "properties": {
    "tgn:hierarchy":[
        "tgn:2706693",
        "tgn:1000001",
        "tgn:7012149",
        "tgn:2000545",
        "tgn:7007252",
        "tgn:7029392"
    ],
    "tgn:id":2706693,
    "tgn:name":"Swan Pond",
    "tgn:placetype":[
        "aat:300008680"
    ]
},
  "bbox": [],
  "geometry": {"coordinates":[-87.6333,38.5333],"type":"Point"}
}