{
  "id": 7442933,
  "type": "Feature",
  "properties": {
    "tgn:hierarchy":[
        "tgn:7442933",
        "tgn:7002445",
        "tgn:1000003",
        "tgn:7008166",
        "tgn:7008591",
        "tgn:7029392"
    ],
    "tgn:id":7442933,
    "tgn:name:en":"White Nab",
    "tgn:placetype":[
        "aat:300386846"
    ]
},
  "bbox": [],
  "geometry": {"coordinates":[-0.376667,54.261667],"type":"Point"}
}