{
  "id": 2533032,
  "type": "Feature",
  "properties": {
    "tgn:hierarchy":[
        "tgn:2533032",
        "tgn:1000001",
        "tgn:2001479",
        "tgn:7012149",
        "tgn:7007709",
        "tgn:7029392"
    ],
    "tgn:id":2533032,
    "tgn:name":"Murrays Hill",
    "tgn:placetype":[
        "aat:300008347"
    ]
},
  "bbox": [],
  "geometry": {"coordinates":[-81.0833,35.6667],"type":"Point"}
}