{
  "id": 7160100,
  "type": "Feature",
  "properties": {
    "tgn:hierarchy":[
        "tgn:7160100",
        "tgn:1000003",
        "tgn:7003688",
        "tgn:7000084",
        "tgn:7029392"
    ],
    "tgn:id":7160100,
    "tgn:name":"Hohenfichte",
    "tgn:placetype":[
        "aat:300000206"
    ]
},
  "bbox": [],
  "geometry": {"coordinates":[10.566667,54.016667],"type":"Point"}
}