{
  "id": 2197523,
  "type": "Feature",
  "properties": {
    "tgn:hierarchy":[
        "tgn:2197523",
        "tgn:1000001",
        "tgn:2002107",
        "tgn:7012149",
        "tgn:7007827",
        "tgn:7029392"
    ],
    "tgn:id":2197523,
    "tgn:name":"Brown Duck Mountain",
    "tgn:placetype":[
        "aat:300008798"
    ]
},
  "bbox": [],
  "geometry": {"coordinates":[-110.6167,40.6333],"type":"Point"}
}