<<<<<<< HEAD
{
  "id": 7058136,
  "type": "Feature",
  "properties": {
    "tgn:hierarchy":[
        "tgn:7058136",
        "tgn:1003459",
        "tgn:1000003",
        "tgn:7002993",
        "tgn:1000080",
        "tgn:7029392"
    ],
    "tgn:id":7058136,
    "tgn:name":"Canale Brancolo",
    "tgn:placetype":[
        "aat:300006075"
    ]
},
  "bbox": [],
  "geometry": {"coordinates":[13.533333,45.783333],"type":"Point"}
}
=======
{"geometry":{"type":"Point","coordinates":[13.533333,45.783333]},"type":"Feature","properties":{"hierarchy":["tgn:7058136","tgn:1003459","tgn:1000003","tgn:7002993","tgn:1000080","tgn:7029392"],"placetype":["aat:300006075"],"id":7058136,"name:xx":"Canale Brancolo"}}
>>>>>>> 03f74aca74312dbeaf24d7e61306dd6a786dc3d0
