<<<<<<< HEAD
{
  "id": 2338903,
  "type": "Feature",
  "properties": {
    "tgn:hierarchy":[
        "tgn:2338903",
        "tgn:1000001",
        "tgn:7012149",
        "tgn:2000911",
        "tgn:7007256",
        "tgn:7029392"
    ],
    "tgn:id":2338903,
    "tgn:name":"Franklin Branch",
    "tgn:placetype":[
        "aat:300008699"
    ]
},
  "bbox": [],
  "geometry": {"coordinates":[-93.35,31.2667],"type":"Point"}
}
=======
{"geometry":{"type":"Point","coordinates":[-93.350000,31.266700]},"type":"Feature","properties":{"hierarchy":["tgn:2338903","tgn:1000001","tgn:7012149","tgn:2000911","tgn:7007256","tgn:7029392"],"placetype":["aat:300008699"],"id":2338903,"name:xx":"Franklin Branch"}}
>>>>>>> 03f74aca74312dbeaf24d7e61306dd6a786dc3d0
