{
  "id": 2632552,
  "type": "Feature",
  "properties": {
    "tgn:hierarchy":[
        "tgn:2632552",
        "tgn:1000001",
        "tgn:2000323",
        "tgn:7012149",
        "tgn:7007248",
        "tgn:7029392"
    ],
    "tgn:id":2632552,
    "tgn:name":"Rozier Island",
    "tgn:placetype":[
        "aat:300008791"
    ]
},
  "bbox": [],
  "geometry": {"coordinates":[-82.55,30.7333],"type":"Point"}
}