{
  "id": 7412262,
  "type": "Feature",
  "properties": {
    "tgn:hierarchy":[
        "tgn:7412262",
        "tgn:7005587",
        "tgn:1000001",
        "tgn:7005560",
        "tgn:7029392"
    ],
    "tgn:id":7412262,
    "tgn:name:es":"Tepexititla",
    "tgn:placetype":[
        "aat:300008347"
    ]
},
  "bbox": [],
  "geometry": {"coordinates":[-98.45,21.130556],"type":"Point"}
}