{
  "id": 7309766,
  "type": "Feature",
  "properties": {
    "tgn:hierarchy":[
        "tgn:7309766",
        "tgn:1001699",
        "tgn:1000049",
        "tgn:1000002",
        "tgn:7029392"
    ],
    "tgn:id":7309766,
    "tgn:name":"Nalalguaca, Estero",
    "tgn:placetype":[
        "aat:300008699"
    ]
},
  "bbox": [],
  "geometry": {"coordinates":[-72.533333,-39.616667],"type":"Point"}
}