{
  "id": 2618659,
  "type": "Feature",
  "properties": {
    "tgn:hierarchy":[
        "tgn:2618659",
        "tgn:1000001",
        "tgn:2002257",
        "tgn:7012149",
        "tgn:7013961",
        "tgn:7029392"
    ],
    "tgn:id":2618659,
    "tgn:name":"Right Fork Mill Creek",
    "tgn:placetype":[
        "aat:300008706"
    ]
},
  "bbox": [],
  "geometry": {"coordinates":[-82.0833,38.4833],"type":"Point"}
}