{
  "id": 2599338,
  "type": "Feature",
  "properties": {
    "tgn:hierarchy":[
        "tgn:2599338",
        "tgn:7030516",
        "tgn:7006450",
        "tgn:1000001",
        "tgn:7012149",
        "tgn:7029392"
    ],
    "tgn:id":2599338,
    "tgn:name":"Profile Point",
    "tgn:placetype":[
        "aat:300008850"
    ]
},
  "bbox": [],
  "geometry": {"coordinates":[-174.1333,52.1667],"type":"Point"}
}