{
  "id": 2423089,
  "type": "Feature",
  "properties": {
    "tgn:hierarchy":[
        "tgn:2423089",
        "tgn:1000001",
        "tgn:7012149",
        "tgn:2002035",
        "tgn:7007826",
        "tgn:7029392"
    ],
    "tgn:id":2423089,
    "tgn:name":"Joe Tank",
    "tgn:placetype":[
        "aat:300006191"
    ]
},
  "bbox": [],
  "geometry": {"coordinates":[-98.6333,28.2167],"type":"Point"}
}