{
  "id": 2276658,
  "type": "Feature",
  "properties": {
    "tgn:hierarchy":[
        "tgn:2276658",
        "tgn:1000001",
        "tgn:7012149",
        "tgn:2001503",
        "tgn:7007709",
        "tgn:7029392"
    ],
    "tgn:id":2276658,
    "tgn:name":"Davidson Branch",
    "tgn:placetype":[
        "aat:300008699"
    ]
},
  "bbox": [],
  "geometry": {"coordinates":[-83.1167,35.65],"type":"Point"}
}