{
  "id": 2073018,
  "type": "Feature",
  "properties": {
    "tgn:hierarchy":[
        "tgn:2073018",
        "tgn:1000001",
        "tgn:7012149",
        "tgn:7014318",
        "tgn:7007568",
        "tgn:7029392"
    ],
    "tgn:id":2073018,
    "tgn:name":"Welcome",
    "tgn:placetype":[
        "aat:300008347",
        "aat:300387210"
    ]
},
  "bbox": [],
  "geometry": {"coordinates":[-75.1333,42.6167],"type":"Point"}
}