{
  "id": 1139985,
  "type": "Feature",
  "properties": {
    "tgn:hierarchy":[
        "tgn:1139985",
        "tgn:1000004",
        "tgn:1001390",
        "tgn:1000111",
        "tgn:7029392"
    ],
    "tgn:id":1139985,
    "tgn:name":"Yingchengzi",
    "tgn:placetype":[
        "aat:300008347"
    ]
},
  "bbox": [],
  "geometry": {"coordinates":[124.0667,41.8333],"type":"Point"}
}