{
  "id": 2272507,
  "type": "Feature",
  "properties": {
    "tgn:hierarchy":[
        "tgn:2272507",
        "tgn:1000001",
        "tgn:1002262",
        "tgn:7012149",
        "tgn:7007568",
        "tgn:7029392"
    ],
    "tgn:id":2272507,
    "tgn:name":"Curtis Swamp",
    "tgn:placetype":[
        "aat:300008905"
    ]
},
  "bbox": [],
  "geometry": {"coordinates":[-75.75,42.3167],"type":"Point"}
}