{
  "id": 7440286,
  "type": "Feature",
  "properties": {
    "tgn:hierarchy":[
        "tgn:7440286",
        "tgn:7005575",
        "tgn:1000001",
        "tgn:7005560",
        "tgn:7029392"
    ],
    "tgn:id":7440286,
    "tgn:name":"Santa Catarina, Sierra de",
    "tgn:placetype":[
        "aat:300008795"
    ]
},
  "bbox": [],
  "geometry": {"coordinates":[-99.033333,19.316667],"type":"Point"}
}