{
  "id": 2595395,
  "type": "Feature",
  "properties": {
    "tgn:hierarchy":[
        "tgn:2595395",
        "tgn:1000001",
        "tgn:1002260",
        "tgn:7012149",
        "tgn:7007920",
        "tgn:7029392"
    ],
    "tgn:id":2595395,
    "tgn:name":"Potato Creek",
    "tgn:placetype":[
        "aat:300008706"
    ]
},
  "bbox": [],
  "geometry": {"coordinates":[-120.3167,47.85],"type":"Point"}
}