{
  "id": 7471523,
  "type": "Feature",
  "properties": {
    "tgn:hierarchy":[
        "tgn:7471523",
        "tgn:1000004",
        "tgn:7489179",
        "tgn:1000141",
        "tgn:7029392"
    ],
    "tgn:id":7471523,
    "tgn:name":"Xingjian Cun",
    "tgn:placetype":[
        "aat:300387173"
    ]
},
  "bbox": [],
  "geometry": {"coordinates":[121.699407,24.672344],"type":"Point"}
}