{
  "id": 2199995,
  "type": "Feature",
  "properties": {
    "tgn:hierarchy":[
        "tgn:2199995",
        "tgn:1000001",
        "tgn:7006451",
        "tgn:7012149",
        "tgn:2000103",
        "tgn:7029392"
    ],
    "tgn:id":2199995,
    "tgn:name":"Brushy Canyon",
    "tgn:placetype":[
        "aat:300008761"
    ]
},
  "bbox": [],
  "geometry": {"coordinates":[-111.9833,34.0833],"type":"Point"}
}