{
  "id": 2363548,
  "type": "Feature",
  "properties": {
    "tgn:hierarchy":[
        "tgn:2363548",
        "tgn:1000001",
        "tgn:7014423",
        "tgn:7012149",
        "tgn:7007517",
        "tgn:7029392"
    ],
    "tgn:id":2363548,
    "tgn:name":"Green Harbor Marsh",
    "tgn:placetype":[
        "aat:300008905"
    ]
},
  "bbox": [],
  "geometry": {"coordinates":[-70.6667,42.0833],"type":"Point"}
}