{
  "id": 2636636,
  "type": "Feature",
  "properties": {
    "tgn:hierarchy":[
        "tgn:2636636",
        "tgn:1000001",
        "tgn:7012149",
        "tgn:7007157",
        "tgn:1002867",
        "tgn:7029392"
    ],
    "tgn:id":2636636,
    "tgn:name":"Sage Hill",
    "tgn:placetype":[
        "aat:300008798"
    ]
},
  "bbox": [],
  "geometry": {"coordinates":[-119.7833,34.55],"type":"Point"}
}