{
  "id": 2551404,
  "type": "Feature",
  "properties": {
    "tgn:hierarchy":[
        "tgn:2551404",
        "tgn:1000001",
        "tgn:7012149",
        "tgn:2000851",
        "tgn:7007255",
        "tgn:7029392"
    ],
    "tgn:id":2551404,
    "tgn:name":"Number 10, Mine",
    "tgn:placetype":[
        "aat:300000390"
    ]
},
  "bbox": [],
  "geometry": {"coordinates":[-87.85,37.4667],"type":"Point"}
}