{
  "id": 2634686,
  "type": "Feature",
  "properties": {
    "tgn:hierarchy":[
        "tgn:2634686",
        "tgn:1000001",
        "tgn:7012149",
        "tgn:7007825",
        "tgn:7029392"
    ],
    "tgn:id":2634686,
    "tgn:name":"Rutherford Creek",
    "tgn:placetype":[
        "aat:300008706"
    ]
},
  "bbox": [],
  "geometry": {"coordinates":[-86.7333,35.75],"type":"Point"}
}