{
  "id": 1028828,
  "type": "Feature",
  "properties": {
    "tgn:hierarchy":[
        "tgn:1028828",
        "tgn:7002445",
        "tgn:1000003",
        "tgn:7008131",
        "tgn:7008591",
        "tgn:7029392"
    ],
    "tgn:id":1028828,
    "tgn:name:ang":"Cingehala",
    "tgn:placetype":[
        "aat:300008347",
        "aat:300008372"
    ]
},
  "bbox": [],
  "geometry": {"coordinates":[0.4167,51.7667],"type":"Point"}
}