{
  "id": 7211533,
  "type": "Feature",
  "properties": {
    "tgn:hierarchy":[
        "tgn:7211533",
        "tgn:1000003",
        "tgn:7003676",
        "tgn:7000084",
        "tgn:7029392"
    ],
    "tgn:id":7211533,
    "tgn:name":"Behrensloh",
    "tgn:placetype":[
        "aat:300008863"
    ]
},
  "bbox": [],
  "geometry": {"coordinates":[10.166667,53.05],"type":"Point"}
}