{
  "id": 7382289,
  "type": "Feature",
  "properties": {
    "tgn:hierarchy":[
        "tgn:7382289",
        "tgn:1000001",
        "tgn:7005589",
        "tgn:7005560",
        "tgn:7029392"
    ],
    "tgn:id":7382289,
    "tgn:name":"Ojos de Agua",
    "tgn:placetype":[
        "aat:300008347"
    ]
},
  "bbox": [],
  "geometry": {"coordinates":[-100.083333,25.466667],"type":"Point"}
}