{
  "id": 7440758,
  "type": "Feature",
  "properties": {
    "tgn:hierarchy":[
        "tgn:7440758",
        "tgn:1000001",
        "tgn:7005594",
        "tgn:7005560",
        "tgn:7029392"
    ],
    "tgn:id":7440758,
    "tgn:name":"Rancho Santa Anita",
    "tgn:placetype":[
        "aat:300000241"
    ]
},
  "bbox": [],
  "geometry": {"coordinates":[-100.75,24.116667],"type":"Point"}
}