{
  "id": 1037630,
  "type": "Feature",
  "properties": {
    "tgn:hierarchy":[
        "tgn:1037630",
        "tgn:7000096",
        "tgn:1000003",
        "tgn:7000084",
        "tgn:7029392"
    ],
    "tgn:id":1037630,
    "tgn:name":"Sachsenhausen",
    "tgn:placetype":[
        "aat:300008347",
        "aat:300387268"
    ]
},
  "bbox": [],
  "geometry": {"coordinates":[13.233333,52.783333],"type":"Point"}
}