{
  "id": 2249981,
  "type": "Feature",
  "properties": {
    "tgn:hierarchy":[
        "tgn:2249981",
        "tgn:1000001",
        "tgn:7012149",
        "tgn:2002169",
        "tgn:7007919",
        "tgn:7029392"
    ],
    "tgn:id":2249981,
    "tgn:name":"Colliers Cove",
    "tgn:placetype":[
        "aat:300008761"
    ]
},
  "bbox": [],
  "geometry": {"coordinates":[-82.9167,36.8667],"type":"Point"}
}