<<<<<<< HEAD
{
  "id": 2334926,
  "type": "Feature",
  "properties": {
    "tgn:hierarchy":[
        "tgn:2334926",
        "tgn:1000001",
        "tgn:7012149",
        "tgn:1002439",
        "tgn:7007252",
        "tgn:7029392"
    ],
    "tgn:id":2334926,
    "tgn:name":"Forkner Ditch",
    "tgn:placetype":[
        "aat:300006075"
    ]
},
  "bbox": [],
  "geometry": {"coordinates":[-85.9833,40.2],"type":"Point"}
}
=======
{"geometry":{"type":"Point","coordinates":[-85.983300,40.200000]},"type":"Feature","properties":{"hierarchy":["tgn:2334926","tgn:1000001","tgn:7012149","tgn:1002439","tgn:7007252","tgn:7029392"],"placetype":["aat:300006075"],"id":2334926,"name:xx":"Forkner Ditch"}}
>>>>>>> 03f74aca74312dbeaf24d7e61306dd6a786dc3d0
