{
  "id": 7150349,
  "type": "Feature",
  "properties": {
    "tgn:hierarchy":[
        "tgn:7150349",
        "tgn:1000003",
        "tgn:7003687",
        "tgn:7000084",
        "tgn:7029392"
    ],
    "tgn:id":7150349,
    "tgn:name":"Kranichpfuhl",
    "tgn:placetype":[
        "aat:300008692"
    ]
},
  "bbox": [],
  "geometry": {"coordinates":[12.133333,52.283333],"type":"Point"}
}