{
  "id": 2121208,
  "type": "Feature",
  "properties": {
    "tgn:hierarchy":[
        "tgn:2121208",
        "tgn:1000001",
        "tgn:2002321",
        "tgn:7012149",
        "tgn:7007922",
        "tgn:7029392"
    ],
    "tgn:id":2121208,
    "tgn:name":"Florence",
    "tgn:placetype":[
        "aat:300008347"
    ]
},
  "bbox": [],
  "geometry": {"coordinates":[-88.25,45.9167],"type":"Point"}
}