{
  "id": 2519074,
  "type": "Feature",
  "properties": {
    "tgn:hierarchy":[
        "tgn:2519074",
        "tgn:1000001",
        "tgn:2002144",
        "tgn:7012149",
        "tgn:7007919",
        "tgn:7029392"
    ],
    "tgn:id":2519074,
    "tgn:name":"Mob Creek",
    "tgn:placetype":[
        "aat:300008706"
    ]
},
  "bbox": [],
  "geometry": {"coordinates":[-79.55,37.25],"type":"Point"}
}