{
  "id": 7515417,
  "type": "Feature",
  "properties": {
    "tgn:hierarchy":[
        "tgn:7515417",
        "tgn:1009227",
        "tgn:7001866",
        "tgn:1000226",
        "tgn:1000006",
        "tgn:7029392"
    ],
    "tgn:id":7515417,
    "tgn:name:en":"Castle Hill",
    "tgn:placetype":[
        "aat:300008347"
    ]
},
  "bbox": [],
  "geometry": {"coordinates":[171.716667,-43.233333],"type":"Point"}
}