{
  "id": 7342292,
  "type": "Feature",
  "properties": {
    "tgn:hierarchy":[
        "tgn:7342292",
        "tgn:7002808",
        "tgn:7030216",
        "tgn:1000003",
        "tgn:1000095",
        "tgn:7029392"
    ],
    "tgn:id":7342292,
    "tgn:name":"Castell del Areny",
    "tgn:placetype":[
        "aat:300008347"
    ]
},
  "bbox": [],
  "geometry": {"coordinates":[1.945527,42.173079],"type":"Point"}
}