{
  "id": 7415360,
  "type": "Feature",
  "properties": {
    "tgn:hierarchy":[
        "tgn:7415360",
        "tgn:7005584",
        "tgn:1000001",
        "tgn:7005560",
        "tgn:7029392"
    ],
    "tgn:id":7415360,
    "tgn:name":"La Chamacuera, R\u00edo",
    "tgn:placetype":[
        "aat:300008699"
    ]
},
  "bbox": [],
  "geometry": {"coordinates":[-100.070278,21.031111],"type":"Point"}
}