{
  "id": 2728477,
  "type": "Feature",
  "properties": {
    "tgn:hierarchy":[
        "tgn:2728477",
        "tgn:1000001",
        "tgn:7012149",
        "tgn:2000931",
        "tgn:7007515",
        "tgn:7029392"
    ],
    "tgn:id":2728477,
    "tgn:name":"Treat Point",
    "tgn:placetype":[
        "aat:300008850"
    ]
},
  "bbox": [],
  "geometry": {"coordinates":[-68.85,44.5833],"type":"Point"}
}