{
  "id": 2526588,
  "type": "Feature",
  "properties": {
    "tgn:hierarchy":[
        "tgn:2526588",
        "tgn:1000001",
        "tgn:7012149",
        "tgn:2000888",
        "tgn:7007256",
        "tgn:7029392"
    ],
    "tgn:id":2526588,
    "tgn:name":"Mossy Point",
    "tgn:placetype":[
        "aat:300008850"
    ]
},
  "bbox": [],
  "geometry": {"coordinates":[-92.8667,31.4667],"type":"Point"}
}