{
  "id": 7095542,
  "type": "Feature",
  "properties": {
    "tgn:hierarchy":[
        "tgn:7095542",
        "tgn:7000096",
        "tgn:1000003",
        "tgn:7000084",
        "tgn:7029392"
    ],
    "tgn:id":7095542,
    "tgn:name":"Schwarz Berg",
    "tgn:placetype":[
        "aat:300008777"
    ]
},
  "bbox": [],
  "geometry": {"coordinates":[14.15,52.233333],"type":"Point"}
}