<<<<<<< HEAD
{
  "id": 2154182,
  "type": "Feature",
  "properties": {
    "tgn:hierarchy":[
        "tgn:2154182",
        "tgn:1000001",
        "tgn:2000956",
        "tgn:7012149",
        "tgn:7007520",
        "tgn:7029392"
    ],
    "tgn:id":2154182,
    "tgn:name":"Bear Creek",
    "tgn:placetype":[
        "aat:300008706"
    ]
},
  "bbox": [],
  "geometry": {"coordinates":[-87.6667,46.1],"type":"Point"}
}
=======
{"geometry":{"type":"Point","coordinates":[-87.666700,46.100000]},"type":"Feature","properties":{"hierarchy":["tgn:2154182","tgn:1000001","tgn:2000956","tgn:7012149","tgn:7007520","tgn:7029392"],"placetype":["aat:300008706"],"id":2154182,"name:xx":"Bear Creek"}}
>>>>>>> 03f74aca74312dbeaf24d7e61306dd6a786dc3d0
