{
  "id": 2314666,
  "type": "Feature",
  "properties": {
    "tgn:hierarchy":[
        "tgn:2314666",
        "tgn:1000001",
        "tgn:7012149",
        "tgn:1002368",
        "tgn:7007919",
        "tgn:7029392"
    ],
    "tgn:id":2314666,
    "tgn:name":"Elk Run",
    "tgn:placetype":[
        "aat:300008347"
    ]
},
  "bbox": [],
  "geometry": {"coordinates":[-77.6667,38.55],"type":"Point"}
}