{
  "id": 7581062,
  "type": "Feature",
  "properties": {
    "tgn:hierarchy":[
        "tgn:7581062",
        "tgn:1000004",
        "tgn:1001832",
        "tgn:7000198",
        "tgn:7029392"
    ],
    "tgn:id":7581062,
    "tgn:name:en":"Si\u0101juli",
    "tgn:placetype":[
        "aat:300008347"
    ]
},
  "bbox": [],
  "geometry": {"coordinates":[94.095404,27.375647],"type":"Point"}
}