{
  "id": 1066505,
  "type": "Feature",
  "properties": {
    "tgn:hierarchy":[
        "tgn:1066505",
        "tgn:1000004",
        "tgn:7001745",
        "tgn:1000111",
        "tgn:7029392"
    ],
    "tgn:id":1066505,
    "tgn:name":"Alasitan",
    "tgn:placetype":[
        "aat:300008347"
    ]
},
  "bbox": [],
  "geometry": {"coordinates":[76.9833,37.0167],"type":"Point"}
}