{
  "id": 2013001,
  "type": "Feature",
  "properties": {
    "tgn:hierarchy":[
        "tgn:2013001",
        "tgn:1000001",
        "tgn:7012149",
        "tgn:7007157",
        "tgn:7014005",
        "tgn:7029392"
    ],
    "tgn:id":2013001,
    "tgn:name":"Novato",
    "tgn:placetype":[
        "aat:300008347"
    ]
},
  "bbox": [],
  "geometry": {"coordinates":[-122.5667,38.1167],"type":"Point"}
}