{
  "id": 7184122,
  "type": "Feature",
  "properties": {
    "tgn:hierarchy":[
        "tgn:7184122",
        "tgn:1000003",
        "tgn:7003678",
        "tgn:7000084",
        "tgn:7029392"
    ],
    "tgn:id":7184122,
    "tgn:name":"Giesh\u00fcbel",
    "tgn:placetype":[
        "aat:300000206"
    ]
},
  "bbox": [],
  "geometry": {"coordinates":[8.05,50.166667],"type":"Point"}
}