{
  "id": 2473502,
  "type": "Feature",
  "properties": {
    "tgn:hierarchy":[
        "tgn:2473502",
        "tgn:1000001",
        "tgn:2002311",
        "tgn:7012149",
        "tgn:7007922",
        "tgn:7029392"
    ],
    "tgn:id":2473502,
    "tgn:name":"Lower Clam Lake",
    "tgn:placetype":[
        "aat:300008680"
    ]
},
  "bbox": [],
  "geometry": {"coordinates":[-92.3167,45.8167],"type":"Point"}
}