<<<<<<< HEAD
{
  "id": 2250880,
  "type": "Feature",
  "properties": {
    "tgn:hierarchy":[
        "tgn:2250880",
        "tgn:1000001",
        "tgn:2000108",
        "tgn:7016172",
        "tgn:7012149",
        "tgn:7029392"
    ],
    "tgn:id":2250880,
    "tgn:name":"Columbia Hollow",
    "tgn:placetype":[
        "aat:300008761"
    ]
},
  "bbox": [],
  "geometry": {"coordinates":[-94.45,36.3333],"type":"Point"}
}
=======
{"geometry":{"type":"Point","coordinates":[-94.450000,36.333300]},"type":"Feature","properties":{"hierarchy":["tgn:2250880","tgn:1000001","tgn:2000108","tgn:7016172","tgn:7012149","tgn:7029392"],"placetype":["aat:300008761"],"id":2250880,"name:xx":"Columbia Hollow"}}
>>>>>>> 03f74aca74312dbeaf24d7e61306dd6a786dc3d0
