{
  "id": 2202171,
  "type": "Feature",
  "properties": {
    "tgn:hierarchy":[
        "tgn:2202171",
        "tgn:1000001",
        "tgn:7012149",
        "tgn:2001907",
        "tgn:7007825",
        "tgn:7029392"
    ],
    "tgn:id":2202171,
    "tgn:name":"Buck Lake",
    "tgn:placetype":[
        "aat:300008680"
    ]
},
  "bbox": [],
  "geometry": {"coordinates":[-85.4333,36.15],"type":"Point"}
}