{
  "id": 7182049,
  "type": "Feature",
  "properties": {
    "tgn:hierarchy":[
        "tgn:7182049",
        "tgn:7003669",
        "tgn:1000003",
        "tgn:7000084",
        "tgn:7029392"
    ],
    "tgn:id":7182049,
    "tgn:name":"Geis-Berg",
    "tgn:placetype":[
        "aat:300008777"
    ]
},
  "bbox": [],
  "geometry": {"coordinates":[10.066667,49.85],"type":"Point"}
}