{
  "id": 1016680,
  "type": "Feature",
  "properties": {
    "tgn:hierarchy":[
        "tgn:1016680",
        "tgn:7005494",
        "tgn:1000001",
        "tgn:7005493",
        "tgn:7029392"
    ],
    "tgn:id":1016680,
    "tgn:name":"Nueva Venecia",
    "tgn:placetype":[
        "aat:300008347"
    ]
},
  "bbox": [],
  "geometry": {"coordinates":[-91.55,14.05],"type":"Point"}
}