{
  "id": 7228508,
  "type": "Feature",
  "properties": {
    "tgn:hierarchy":[
        "tgn:7228508",
        "tgn:7002750",
        "tgn:7001399",
        "tgn:1000003",
        "tgn:1000074",
        "tgn:7029392"
    ],
    "tgn:id":7228508,
    "tgn:name":"Gl\u00e1vki",
    "tgn:placetype":[
        "aat:300008347"
    ]
},
  "bbox": [],
  "geometry": {"coordinates":[22.566667,39.616667],"type":"Point"}
}