{
  "id": 2583604,
  "type": "Feature",
  "properties": {
    "tgn:hierarchy":[
        "tgn:2583604",
        "tgn:1000001",
        "tgn:7012149",
        "tgn:2000975",
        "tgn:7007520",
        "tgn:7029392"
    ],
    "tgn:id":2583604,
    "tgn:name":"Pine River Point",
    "tgn:placetype":[
        "aat:300008850"
    ]
},
  "bbox": [],
  "geometry": {"coordinates":[-87.8167,46.8833],"type":"Point"}
}