{
  "id": 2377856,
  "type": "Feature",
  "properties": {
    "tgn:hierarchy":[
        "tgn:2377856",
        "tgn:1000001",
        "tgn:2000199",
        "tgn:7012149",
        "tgn:7007158",
        "tgn:7029392"
    ],
    "tgn:id":2377856,
    "tgn:name":"Harrington Gulch",
    "tgn:placetype":[
        "aat:300008761"
    ]
},
  "bbox": [],
  "geometry": {"coordinates":[-106.0667,38.5333],"type":"Point"}
}