{
  "id": 2106244,
  "type": "Feature",
  "properties": {
    "tgn:hierarchy":[
        "tgn:2106244",
        "tgn:1000001",
        "tgn:7012149",
        "tgn:2002015",
        "tgn:7007826",
        "tgn:7029392"
    ],
    "tgn:id":2106244,
    "tgn:name":"Nelson City",
    "tgn:placetype":[
        "aat:300008347",
        "aat:300387210"
    ]
},
  "bbox": [],
  "geometry": {"coordinates":[-98.7833,29.8667],"type":"Point"}
}