<<<<<<< HEAD
{
  "id": 2259075,
  "type": "Feature",
  "properties": {
    "tgn:hierarchy":[
        "tgn:2259075",
        "tgn:1000001",
        "tgn:2001411",
        "tgn:7012149",
        "tgn:7007526",
        "tgn:7029392"
    ],
    "tgn:id":2259075,
    "tgn:name":"Cottonwood Creek Canyon",
    "tgn:placetype":[
        "aat:300008761"
    ]
},
  "bbox": [],
  "geometry": {"coordinates":[-116.25,41.3667],"type":"Point"}
}
=======
{"geometry":{"type":"Point","coordinates":[-116.250000,41.366700]},"type":"Feature","properties":{"hierarchy":["tgn:2259075","tgn:1000001","tgn:2001411","tgn:7012149","tgn:7007526","tgn:7029392"],"placetype":["aat:300008761"],"id":2259075,"name:xx":"Cottonwood Creek Canyon"}}
>>>>>>> 03f74aca74312dbeaf24d7e61306dd6a786dc3d0
