{
  "id": 2541072,
  "type": "Feature",
  "properties": {
    "tgn:hierarchy":[
        "tgn:2541072",
        "tgn:1002153",
        "tgn:1000001",
        "tgn:7012149",
        "tgn:7007710",
        "tgn:7029392"
    ],
    "tgn:id":2541072,
    "tgn:name":"Nicholson Island",
    "tgn:placetype":[
        "aat:300008791"
    ]
},
  "bbox": [],
  "geometry": {"coordinates":[-79.5667,40.7167],"type":"Point"}
}