{
  "id": 2436187,
  "type": "Feature",
  "properties": {
    "tgn:hierarchy":[
        "tgn:2436187",
        "tgn:1000001",
        "tgn:7012149",
        "tgn:1003017",
        "tgn:7007710",
        "tgn:7029392"
    ],
    "tgn:id":2436187,
    "tgn:name":"Keystone Lake",
    "tgn:placetype":[
        "aat:300006191"
    ]
},
  "bbox": [],
  "geometry": {"coordinates":[-79.3833,40.3667],"type":"Point"}
}