{
  "id": 2115625,
  "type": "Feature",
  "properties": {
    "tgn:hierarchy":[
        "tgn:2115625",
        "tgn:1000001",
        "tgn:7012149",
        "tgn:2002248",
        "tgn:7007920",
        "tgn:7029392"
    ],
    "tgn:id":2115625,
    "tgn:name":"Diamond Lake",
    "tgn:placetype":[
        "aat:300008347"
    ]
},
  "bbox": [],
  "geometry": {"coordinates":[-117.1833,48.1167],"type":"Point"}
}