{
  "id": 2572135,
  "type": "Feature",
  "properties": {
    "tgn:hierarchy":[
        "tgn:2572135",
        "tgn:7002659",
        "tgn:1000001",
        "tgn:7012149",
        "tgn:2000021",
        "tgn:7029392"
    ],
    "tgn:id":2572135,
    "tgn:name":"Pea Ridge",
    "tgn:placetype":[
        "aat:300266640"
    ]
},
  "bbox": [],
  "geometry": {"coordinates":[-87.05,34.05],"type":"Point"}
}