{
  "id": 2067367,
  "type": "Feature",
  "properties": {
    "tgn:hierarchy":[
        "tgn:2067367",
        "tgn:1000001",
        "tgn:2001436",
        "tgn:7012149",
        "tgn:7007566",
        "tgn:7029392"
    ],
    "tgn:id":2067367,
    "tgn:name":"Queen",
    "tgn:placetype":[
        "aat:300008347",
        "aat:300387210"
    ]
},
  "bbox": [],
  "geometry": {"coordinates":[-104.7333,32.1833],"type":"Point"}
}