{
  "id": 7288600,
  "type": "Feature",
  "properties": {
    "tgn:hierarchy":[
        "tgn:7288600",
        "tgn:1001702",
        "tgn:1000049",
        "tgn:1000002",
        "tgn:7029392"
    ],
    "tgn:id":7288600,
    "tgn:name":"Jane, Isla",
    "tgn:placetype":[
        "aat:300008791"
    ]
},
  "bbox": [],
  "geometry": {"coordinates":[-75.361667,-50.018889],"type":"Point"}
}