<<<<<<< HEAD
{
  "id": 7248871,
  "type": "Feature",
  "properties": {
    "tgn:hierarchy":[
        "tgn:7248871",
        "tgn:7003466",
        "tgn:1000003",
        "tgn:1000063",
        "tgn:4012014",
        "tgn:7029392"
    ],
    "tgn:id":7248871,
    "tgn:name":"Bois-de-Villers",
    "tgn:placetype":[
        "aat:300008347"
    ]
},
  "bbox": [],
  "geometry": {"coordinates":[4.823129,50.389333],"type":"Point"}
}
=======
{"geometry":{"type":"Point","coordinates":[4.823129,50.389333]},"type":"Feature","properties":{"hierarchy":["tgn:7248871","tgn:7003466","tgn:1000003","tgn:1000063","tgn:4012014","tgn:7029392"],"placetype":["aat:300008347"],"id":7248871,"name:xx":"Bois-de-Villers"}}
>>>>>>> 03f74aca74312dbeaf24d7e61306dd6a786dc3d0
