{
  "id": 7022720,
  "type": "Feature",
  "properties": {
    "tgn:hierarchy":[
        "tgn:7022720",
        "tgn:1000001",
        "tgn:7012149",
        "tgn:7007239",
        "tgn:7029392"
    ],
    "tgn:id":7022720,
    "tgn:name":"White Marsh Branch",
    "tgn:placetype":[
        "aat:300008699"
    ]
},
  "bbox": [],
  "geometry": {"coordinates":[-75.5667,38.85],"type":"Point"}
}