<<<<<<< HEAD
{
  "id": 7022720,
  "type": "Feature",
  "properties": {
    "tgn:hierarchy":[
        "tgn:7022720",
        "tgn:1000001",
        "tgn:7012149",
        "tgn:7007239",
        "tgn:7029392"
    ],
    "tgn:id":7022720,
    "tgn:name":"White Marsh Branch",
    "tgn:placetype":[
        "aat:300008699"
    ]
},
  "bbox": [],
  "geometry": {"coordinates":[-75.5667,38.85],"type":"Point"}
}
=======
{"geometry":{"type":"Point","coordinates":[-75.566700,38.850000]},"type":"Feature","properties":{"hierarchy":["tgn:7022720","tgn:1000001","tgn:7012149","tgn:7007239","tgn:7029392"],"placetype":["aat:300008699"],"id":7022720,"name:xx":"White Marsh Branch"}}
>>>>>>> 03f74aca74312dbeaf24d7e61306dd6a786dc3d0
