{
  "id": 7566837,
  "type": "Feature",
  "properties": {
    "tgn:hierarchy":[
        "tgn:7566837",
        "tgn:1000004",
        "tgn:7000198",
        "tgn:7001797",
        "tgn:7029392"
    ],
    "tgn:id":7566837,
    "tgn:name:en":"College Bridge",
    "tgn:placetype":[
        "aat:300007836"
    ]
},
  "bbox": [],
  "geometry": {"coordinates":[80.255833,13.065278],"type":"Point"}
}