{
  "id": 2170624,
  "type": "Feature",
  "properties": {
    "tgn:hierarchy":[
        "tgn:2170624",
        "tgn:1000001",
        "tgn:7012149",
        "tgn:2001295",
        "tgn:7007524",
        "tgn:7029392"
    ],
    "tgn:id":2170624,
    "tgn:name":"Big Sag, The",
    "tgn:placetype":[
        "aat:300386845"
    ]
},
  "bbox": [],
  "geometry": {"coordinates":[-107.7667,47.9333],"type":"Point"}
}