{
  "id": 2654788,
  "type": "Feature",
  "properties": {
    "tgn:hierarchy":[
        "tgn:2654788",
        "tgn:1000001",
        "tgn:7012149",
        "tgn:2000236",
        "tgn:7007158",
        "tgn:7029392"
    ],
    "tgn:id":2654788,
    "tgn:name":"Shale Hills",
    "tgn:placetype":[
        "aat:300386831"
    ]
},
  "bbox": [],
  "geometry": {"coordinates":[-103.6333,37.7333],"type":"Point"}
}