{
  "id": 2638699,
  "type": "Feature",
  "properties": {
    "tgn:hierarchy":[
        "tgn:2638699",
        "tgn:1000001",
        "tgn:7006451",
        "tgn:2000094",
        "tgn:7012149",
        "tgn:7029392"
    ],
    "tgn:id":2638699,
    "tgn:name":"Salt Box Spring",
    "tgn:placetype":[
        "aat:300008697"
    ]
},
  "bbox": [],
  "geometry": {"coordinates":[-110.1833,33.3333],"type":"Point"}
}