{
  "id": 7015722,
  "type": "Feature",
  "properties": {
    "tgn:hierarchy":[
        "tgn:7015722",
        "tgn:7013962",
        "tgn:1000001",
        "tgn:7012149",
        "tgn:7015717",
        "tgn:7029392"
    ],
    "tgn:id":7015722,
    "tgn:name":"Brightwood",
    "tgn:placetype":[
        "aat:300000745"
    ]
},
  "bbox": [],
  "geometry": {"coordinates":[-77.0167,38.95],"type":"Point"}
}