{
  "id": 7523459,
  "type": "Feature",
  "properties": {
    "tgn:hierarchy":[
        "tgn:7523459",
        "tgn:7001242",
        "tgn:7016833",
        "tgn:7029392"
    ],
    "tgn:id":7523459,
    "tgn:name:en":"East Table",
    "tgn:placetype":[
        "aat:300008777"
    ]
},
  "bbox": [],
  "geometry": {"coordinates":[29.097625,28.667133],"type":"Point"}
}