<<<<<<< HEAD
{
  "id": 7473512,
  "type": "Feature",
  "properties": {
    "tgn:hierarchy":[
        "tgn:7473512",
        "tgn:1000004",
        "tgn:7491221",
        "tgn:1000141",
        "tgn:7029392"
    ],
    "tgn:id":7473512,
    "tgn:name":"Fengtian",
    "tgn:placetype":[
        "aat:300008347"
    ]
},
  "bbox": [],
  "geometry": {"coordinates":[121.061389,22.719444],"type":"Point"}
}
=======
{"geometry":{"type":"Point","coordinates":[121.061389,22.719444]},"type":"Feature","properties":{"hierarchy":["tgn:7473512","tgn:1000004","tgn:7491221","tgn:1000141","tgn:7029392"],"placetype":["aat:300008347"],"id":7473512,"name:xx":"Fengtian"}}
>>>>>>> 03f74aca74312dbeaf24d7e61306dd6a786dc3d0
