{
  "id": 2267317,
  "type": "Feature",
  "properties": {
    "tgn:hierarchy":[
        "tgn:2267317",
        "tgn:1000001",
        "tgn:7012149",
        "tgn:2001722",
        "tgn:7007708",
        "tgn:7029392"
    ],
    "tgn:id":2267317,
    "tgn:name":"Cripple Creek",
    "tgn:placetype":[
        "aat:300008706"
    ]
},
  "bbox": [],
  "geometry": {"coordinates":[-116.8333,45.3833],"type":"Point"}
}