{
  "id": 1123721,
  "type": "Feature",
  "properties": {
    "tgn:hierarchy":[
        "tgn:1123721",
        "tgn:1003510",
        "tgn:1000003",
        "tgn:7003120",
        "tgn:1000080",
        "tgn:7029392"
    ],
    "tgn:id":1123721,
    "tgn:name":"Elvo",
    "tgn:placetype":[
        "aat:300008707",
        "aat:300008699"
    ]
},
  "bbox": [],
  "geometry": {"coordinates":[8.35,45.383333],"type":"Point"}
}