{
  "id": 7317934,
  "type": "Feature",
  "properties": {
    "tgn:hierarchy":[
        "tgn:7317934",
        "tgn:1001637",
        "tgn:1000049",
        "tgn:1000002",
        "tgn:7029392"
    ],
    "tgn:id":7317934,
    "tgn:name":"Colorado, Cerro",
    "tgn:placetype":[
        "aat:300008795"
    ]
},
  "bbox": [],
  "geometry": {"coordinates":[-71.233333,-36.666667],"type":"Point"}
}