{
  "id": 7214776,
  "type": "Feature",
  "properties": {
    "tgn:hierarchy":[
        "tgn:7214776",
        "tgn:7003669",
        "tgn:1000003",
        "tgn:7000084",
        "tgn:7029392"
    ],
    "tgn:id":7214776,
    "tgn:name":"Bohnberg",
    "tgn:placetype":[
        "aat:300000206"
    ]
},
  "bbox": [],
  "geometry": {"coordinates":[11.166667,50.116667],"type":"Point"}
}