{
  "id": 1097780,
  "type": "Feature",
  "properties": {
    "tgn:hierarchy":[
        "tgn:1097780",
        "tgn:7000490",
        "tgn:1000006",
        "tgn:7001830",
        "tgn:7029392"
    ],
    "tgn:id":1097780,
    "tgn:name":"Nindigully",
    "tgn:placetype":[
        "aat:300008347"
    ]
},
  "bbox": [],
  "geometry": {"coordinates":[148.7833,-28.3333],"type":"Point"}
}