{
  "id": 7400317,
  "type": "Feature",
  "properties": {
    "tgn:hierarchy":[
        "tgn:7400317",
        "tgn:1000001",
        "tgn:7005599",
        "tgn:7005560",
        "tgn:7029392"
    ],
    "tgn:id":7400317,
    "tgn:name":"La Cebadilla",
    "tgn:placetype":[
        "aat:300008347"
    ]
},
  "bbox": [],
  "geometry": {"coordinates":[-97.591667,21.15],"type":"Point"}
}