{
  "id": 2771478,
  "type": "Feature",
  "properties": {
    "tgn:hierarchy":[
        "tgn:2771478",
        "tgn:1000001",
        "tgn:2001350",
        "tgn:7012149",
        "tgn:7007525",
        "tgn:7029392"
    ],
    "tgn:id":2771478,
    "tgn:name":"Wildhorse Hill",
    "tgn:placetype":[
        "aat:300008798"
    ]
},
  "bbox": [],
  "geometry": {"coordinates":[-102.2333,41.5833],"type":"Point"}
}