<<<<<<< HEAD
{
  "id": 7489280,
  "type": "Feature",
  "properties": {
    "tgn:hierarchy":[
        "tgn:7489280",
        "tgn:1000004",
        "tgn:1000454",
        "tgn:1000141",
        "tgn:7029392"
    ],
    "tgn:id":7489280,
    "tgn:name":"Neibafen",
    "tgn:placetype":[
        "aat:300008347"
    ]
},
  "bbox": [],
  "geometry": {"coordinates":[121.45,25.15],"type":"Point"}
}
=======
{"geometry":{"type":"Point","coordinates":[121.450000,25.150000]},"type":"Feature","properties":{"hierarchy":["tgn:7489280","tgn:1000004","tgn:1000454","tgn:1000141","tgn:7029392"],"placetype":["aat:300008347"],"id":7489280,"name:xx":"Neibafen"}}
>>>>>>> 03f74aca74312dbeaf24d7e61306dd6a786dc3d0
