{
  "id": 7453680,
  "type": "Feature",
  "properties": {
    "tgn:hierarchy":[
        "tgn:7453680",
        "tgn:7002443",
        "tgn:7026970",
        "tgn:1000003",
        "tgn:7008591",
        "tgn:7029392"
    ],
    "tgn:id":7453680,
    "tgn:name:en":"Llyn Cowlyd",
    "tgn:placetype":[
        "aat:300006191"
    ]
},
  "bbox": [],
  "geometry": {"coordinates":[-3.916667,53.133333],"type":"Point"}
}