{
  "id": 7423477,
  "type": "Feature",
  "properties": {
    "tgn:hierarchy":[
        "tgn:7423477",
        "tgn:1000001",
        "tgn:7005601",
        "tgn:7005560",
        "tgn:7029392"
    ],
    "tgn:id":7423477,
    "tgn:name":"Las Pollas",
    "tgn:placetype":[
        "aat:300008347"
    ]
},
  "bbox": [],
  "geometry": {"coordinates":[-101.55,22.15],"type":"Point"}
}