{
  "id": 2284793,
  "type": "Feature",
  "properties": {
    "tgn:hierarchy":[
        "tgn:2284793",
        "tgn:7002659",
        "tgn:1000001",
        "tgn:7012149",
        "tgn:2000059",
        "tgn:7029392"
    ],
    "tgn:id":2284793,
    "tgn:name":"Detain Branch",
    "tgn:placetype":[
        "aat:300008699"
    ]
},
  "bbox": [],
  "geometry": {"coordinates":[-88.35,32.3833],"type":"Point"}
}