{
  "id": 2603953,
  "type": "Feature",
  "properties": {
    "tgn:hierarchy":[
        "tgn:2603953",
        "tgn:1000001",
        "tgn:7012149",
        "tgn:1002977",
        "tgn:7007240",
        "tgn:7029392"
    ],
    "tgn:id":2603953,
    "tgn:name":"Quincy Lake",
    "tgn:placetype":[
        "aat:300008905"
    ]
},
  "bbox": [],
  "geometry": {"coordinates":[-81.2167,28.8833],"type":"Point"}
}