{
  "id": 2461497,
  "type": "Feature",
  "properties": {
    "tgn:hierarchy":[
        "tgn:2461497",
        "tgn:1000001",
        "tgn:1002281",
        "tgn:7012149",
        "tgn:7007251",
        "tgn:7029392"
    ],
    "tgn:id":2461497,
    "tgn:name":"Little Swan Lake",
    "tgn:placetype":[
        "aat:300008680"
    ]
},
  "bbox": [],
  "geometry": {"coordinates":[-89.3833,38.5167],"type":"Point"}
}