{
  "id": 2013129,
  "type": "Feature",
  "properties": {
    "tgn:hierarchy":[
        "tgn:2013129",
        "tgn:1000001",
        "tgn:1002218",
        "tgn:7012149",
        "tgn:7007157",
        "tgn:7029392"
    ],
    "tgn:id":2013129,
    "tgn:name":"Oregon City",
    "tgn:placetype":[
        "aat:300008347",
        "aat:300387210"
    ]
},
  "bbox": [],
  "geometry": {"coordinates":[-121.5167,39.5833],"type":"Point"}
}