{
  "id": 7025263,
  "type": "Feature",
  "properties": {
    "tgn:hierarchy":[
        "tgn:7025263",
        "tgn:7002445",
        "tgn:1000003",
        "tgn:7008118",
        "tgn:7008591",
        "tgn:7029392"
    ],
    "tgn:id":7025263,
    "tgn:name:ang":"Offretune",
    "tgn:placetype":[
        "aat:300386886"
    ]
},
  "bbox": [],
  "geometry": {"coordinates":[-1.6833,53.3167],"type":"Point"}
}