{
  "id": 7575788,
  "type": "Feature",
  "properties": {
    "tgn:hierarchy":[
        "tgn:7575788",
        "tgn:1000004",
        "tgn:7000198",
        "tgn:7016722",
        "tgn:7029392"
    ],
    "tgn:id":7575788,
    "tgn:name:en":"Khajr\u0101ha Buzurg",
    "tgn:placetype":[
        "aat:300008347"
    ]
},
  "bbox": [],
  "geometry": {"coordinates":[78.471836,25.313561],"type":"Point"}
}