{
  "id": 7019878,
  "type": "Feature",
  "properties": {
    "tgn:hierarchy":[
        "tgn:7019878",
        "tgn:1000001",
        "tgn:7013942",
        "tgn:7012149",
        "tgn:7007517",
        "tgn:7029392"
    ],
    "tgn:id":7019878,
    "tgn:name":"Sawyer Ponds",
    "tgn:placetype":[
        "aat:300006191"
    ]
},
  "bbox": [],
  "geometry": {"coordinates":[-72.4833,42.6833],"type":"Point"}
}