{
  "id": 2648500,
  "type": "Feature",
  "properties": {
    "tgn:hierarchy":[
        "tgn:2648500",
        "tgn:1000001",
        "tgn:2001025",
        "tgn:7012149",
        "tgn:7007521",
        "tgn:7029392"
    ],
    "tgn:id":2648500,
    "tgn:name":"Schwappauff Lake",
    "tgn:placetype":[
        "aat:300008680"
    ]
},
  "bbox": [],
  "geometry": {"coordinates":[-93.6667,45.1167],"type":"Point"}
}