{
  "id": 2334360,
  "type": "Feature",
  "properties": {
    "tgn:hierarchy":[
        "tgn:2334360",
        "tgn:1000001",
        "tgn:7012149",
        "tgn:2001494",
        "tgn:7007709",
        "tgn:7029392"
    ],
    "tgn:id":2334360,
    "tgn:name":"Forest Hills Estates",
    "tgn:placetype":[
        "aat:300008347"
    ]
},
  "bbox": [],
  "geometry": {"coordinates":[-80.4167,36.0167],"type":"Point"}
}