{
  "id": 7509608,
  "type": "Feature",
  "properties": {
    "tgn:hierarchy":[
        "tgn:7509608",
        "tgn:1008380",
        "tgn:1000226",
        "tgn:7016827",
        "tgn:1000006",
        "tgn:7029392"
    ],
    "tgn:id":7509608,
    "tgn:name:en":"Te Wera",
    "tgn:placetype":[
        "aat:300008347"
    ]
},
  "bbox": [],
  "geometry": {"coordinates":[174.583333,-39.233333],"type":"Point"}
}