{
  "id": 7503789,
  "type": "Feature",
  "properties": {
    "tgn:hierarchy":[
        "tgn:7503789",
        "tgn:1000004",
        "tgn:7491221",
        "tgn:1000141",
        "tgn:7029392"
    ],
    "tgn:id":7503789,
    "tgn:name":"Beijiaomo'er",
    "tgn:placetype":[
        "aat:300008795"
    ]
},
  "bbox": [],
  "geometry": {"coordinates":[120.860833,22.551111],"type":"Point"}
}