{
  "id": 7164055,
  "type": "Feature",
  "properties": {
    "tgn:hierarchy":[
        "tgn:7164055",
        "tgn:7003669",
        "tgn:1000003",
        "tgn:7000084",
        "tgn:7029392"
    ],
    "tgn:id":7164055,
    "tgn:name":"Huppenberg",
    "tgn:placetype":[
        "aat:300008347"
    ]
},
  "bbox": [],
  "geometry": {"coordinates":[11.533333,47.816667],"type":"Point"}
}