<<<<<<< HEAD
{
  "id": 2338029,
  "type": "Feature",
  "properties": {
    "tgn:hierarchy":[
        "tgn:2338029",
        "tgn:1000001",
        "tgn:7012149",
        "tgn:2001543",
        "tgn:7007709",
        "tgn:7029392"
    ],
    "tgn:id":2338029,
    "tgn:name":"Fox Knob",
    "tgn:placetype":[
        "aat:300008798"
    ]
},
  "bbox": [],
  "geometry": {"coordinates":[-83.3167,35.5],"type":"Point"}
}
=======
{"geometry":{"type":"Point","coordinates":[-83.316700,35.500000]},"type":"Feature","properties":{"hierarchy":["tgn:2338029","tgn:1000001","tgn:7012149","tgn:2001543","tgn:7007709","tgn:7029392"],"placetype":["aat:300008798"],"id":2338029,"name:xx":"Fox Knob"}}
>>>>>>> 03f74aca74312dbeaf24d7e61306dd6a786dc3d0
