{
  "id": 7026645,
  "type": "Feature",
  "properties": {
    "tgn:hierarchy":[
        "tgn:7026645",
        "tgn:7002445",
        "tgn:1000003",
        "tgn:7008132",
        "tgn:7008591",
        "tgn:7029392"
    ],
    "tgn:id":7026645,
    "tgn:name":"Hardwicke",
    "tgn:placetype":[
        "aat:300008347"
    ]
},
  "bbox": [],
  "geometry": {"coordinates":[-2.1333,51.95],"type":"Point"}
}