{
  "id": 7217746,
  "type": "Feature",
  "properties": {
    "tgn:hierarchy":[
        "tgn:7217746",
        "tgn:7002692",
        "tgn:7012056",
        "tgn:1000003",
        "tgn:1000074",
        "tgn:7029392"
    ],
    "tgn:id":7217746,
    "tgn:name":"Yer\u00e1kion",
    "tgn:placetype":[
        "aat:300008347"
    ]
},
  "bbox": [],
  "geometry": {"coordinates":[25.35,35.15],"type":"Point"}
}