<<<<<<< HEAD
{
  "id": 7481043,
  "type": "Feature",
  "properties": {
    "tgn:hierarchy":[
        "tgn:7481043",
        "tgn:1000004",
        "tgn:7471332",
        "tgn:1000141",
        "tgn:7029392"
    ],
    "tgn:id":7481043,
    "tgn:name":"Dongxing Qiao",
    "tgn:placetype":[
        "aat:300007836"
    ]
},
  "bbox": [],
  "geometry": {"coordinates":[121.05,24.813611],"type":"Point"}
}
=======
{"geometry":{"type":"Point","coordinates":[121.050000,24.813611]},"type":"Feature","properties":{"hierarchy":["tgn:7481043","tgn:1000004","tgn:7471332","tgn:1000141","tgn:7029392"],"placetype":["aat:300007836"],"id":7481043,"name:xx":"Dongxing Qiao"}}
>>>>>>> 03f74aca74312dbeaf24d7e61306dd6a786dc3d0
