{
  "id": 2432407,
  "type": "Feature",
  "properties": {
    "tgn:hierarchy":[
        "tgn:2432407",
        "tgn:1000001",
        "tgn:2001473",
        "tgn:7012149",
        "tgn:7007709",
        "tgn:7029392"
    ],
    "tgn:id":2432407,
    "tgn:name":"Keasler Branch",
    "tgn:placetype":[
        "aat:300008699"
    ]
},
  "bbox": [],
  "geometry": {"coordinates":[-82.4833,35.6333],"type":"Point"}
}