{
  "id": 2460525,
  "type": "Feature",
  "properties": {
    "tgn:hierarchy":[
        "tgn:2460525",
        "tgn:1000001",
        "tgn:7012149",
        "tgn:2002009",
        "tgn:7007826",
        "tgn:7029392"
    ],
    "tgn:id":2460525,
    "tgn:name":"Little Sandy Creek",
    "tgn:placetype":[
        "aat:300008706"
    ]
},
  "bbox": [],
  "geometry": {"coordinates":[-93.9333,30.95],"type":"Point"}
}