{
  "id": 2299855,
  "type": "Feature",
  "properties": {
    "tgn:hierarchy":[
        "tgn:2299855",
        "tgn:1000001",
        "tgn:7012149",
        "tgn:1002769",
        "tgn:7007826",
        "tgn:7029392"
    ],
    "tgn:id":2299855,
    "tgn:name":"Dudley Williams Point",
    "tgn:placetype":[
        "aat:300008850"
    ]
},
  "bbox": [],
  "geometry": {"coordinates":[-94.4167,32.0167],"type":"Point"}
}