<<<<<<< HEAD
{
  "id": 7023014,
  "type": "Feature",
  "properties": {
    "tgn:hierarchy":[
        "tgn:7023014",
        "tgn:1000001",
        "tgn:7012149",
        "tgn:7007920",
        "tgn:7029392"
    ],
    "tgn:id":7023014,
    "tgn:name":"Sagebrush Ridge",
    "tgn:placetype":[
        "aat:300266640"
    ]
},
  "bbox": [],
  "geometry": {"coordinates":[-119.7833,46.3167],"type":"Point"}
}
=======
{"geometry":{"type":"Point","coordinates":[-119.783300,46.316700]},"type":"Feature","properties":{"hierarchy":["tgn:7023014","tgn:1000001","tgn:7012149","tgn:7007920","tgn:7029392"],"placetype":["aat:300266640"],"id":7023014,"name:xx":"Sagebrush Ridge"}}
>>>>>>> 03f74aca74312dbeaf24d7e61306dd6a786dc3d0
