{
  "id": 2744648,
  "type": "Feature",
  "properties": {
    "tgn:hierarchy":[
        "tgn:2744648",
        "tgn:1000001",
        "tgn:7012149",
        "tgn:2001451",
        "tgn:7007566",
        "tgn:7029392"
    ],
    "tgn:id":2744648,
    "tgn:name":"Victo-Rovo-Novo-Group",
    "tgn:placetype":[
        "aat:300000390"
    ]
},
  "bbox": [],
  "geometry": {"coordinates":[-106.4333,35.2833],"type":"Point"}
}