{
  "id": 2615368,
  "type": "Feature",
  "properties": {
    "tgn:hierarchy":[
        "tgn:2615368",
        "tgn:1000001",
        "tgn:7012149",
        "tgn:7007252",
        "tgn:7029392"
    ],
    "tgn:id":2615368,
    "tgn:name":"Reservoir Number Twenty-six",
    "tgn:placetype":[
        "aat:300006191"
    ]
},
  "bbox": [],
  "geometry": {"coordinates":[-87.2333,39.0167],"type":"Point"}
}