{
  "id": 7039047,
  "type": "Feature",
  "properties": {
    "tgn:hierarchy":[
        "tgn:7039047",
        "tgn:7003168",
        "tgn:1000003",
        "tgn:7009760",
        "tgn:1000080",
        "tgn:7029392"
    ],
    "tgn:id":7039047,
    "tgn:name":"Socenna, Torrente la",
    "tgn:placetype":[
        "aat:300008699"
    ]
},
  "bbox": [],
  "geometry": {"coordinates":[11.783333,42.95],"type":"Point"}
}