{
  "id": 2165754,
  "type": "Feature",
  "properties": {
    "tgn:hierarchy":[
        "tgn:2165754",
        "tgn:1000001",
        "tgn:7012149",
        "tgn:1002918",
        "tgn:7007252",
        "tgn:7029392"
    ],
    "tgn:id":2165754,
    "tgn:name":"Bickel Ditch",
    "tgn:placetype":[
        "aat:300006075"
    ]
},
  "bbox": [],
  "geometry": {"coordinates":[-86.55,41.2667],"type":"Point"}
}