<<<<<<< HEAD
{
  "id": 7174691,
  "type": "Feature",
  "properties": {
    "tgn:hierarchy":[
        "tgn:7174691",
        "tgn:7003669",
        "tgn:1000003",
        "tgn:7000084",
        "tgn:7029392"
    ],
    "tgn:id":7174691,
    "tgn:name":"Gruber Stein",
    "tgn:placetype":[
        "aat:300008777"
    ]
},
  "bbox": [],
  "geometry": {"coordinates":[11.0,50.233333],"type":"Point"}
}
=======
{"geometry":{"type":"Point","coordinates":[11.000000,50.233333]},"type":"Feature","properties":{"hierarchy":["tgn:7174691","tgn:7003669","tgn:1000003","tgn:7000084","tgn:7029392"],"placetype":["aat:300008777"],"id":7174691,"name:xx":"Gruber Stein"}}
>>>>>>> 03f74aca74312dbeaf24d7e61306dd6a786dc3d0
