<<<<<<< HEAD
{
  "id": 7362856,
  "type": "Feature",
  "properties": {
    "tgn:hierarchy":[
        "tgn:7362856",
        "tgn:7005581",
        "tgn:1000001",
        "tgn:7005560",
        "tgn:7029392"
    ],
    "tgn:id":7362856,
    "tgn:name":"El Carrizoso",
    "tgn:placetype":[
        "aat:300008697"
    ]
},
  "bbox": [],
  "geometry": {"coordinates":[-105.583333,30.8],"type":"Point"}
}
=======
{"geometry":{"type":"Point","coordinates":[-105.583333,30.800000]},"type":"Feature","properties":{"hierarchy":["tgn:7362856","tgn:7005581","tgn:1000001","tgn:7005560","tgn:7029392"],"placetype":["aat:300008697"],"id":7362856,"name:xx":"El Carrizoso"}}
>>>>>>> 03f74aca74312dbeaf24d7e61306dd6a786dc3d0
