<<<<<<< HEAD
{
  "id": 7059577,
  "type": "Feature",
  "properties": {
    "tgn:hierarchy":[
        "tgn:7059577",
        "tgn:1000003",
        "tgn:7003676",
        "tgn:7000084",
        "tgn:7029392"
    ],
    "tgn:id":7059577,
    "tgn:name":"Ahlum",
    "tgn:placetype":[
        "aat:300008347"
    ]
},
  "bbox": [],
  "geometry": {"coordinates":[10.6,52.166667],"type":"Point"}
}
=======
{"geometry":{"type":"Point","coordinates":[10.600000,52.166667]},"type":"Feature","properties":{"hierarchy":["tgn:7059577","tgn:1000003","tgn:7003676","tgn:7000084","tgn:7029392"],"placetype":["aat:300008347"],"id":7059577,"name:xx":"Ahlum"}}
>>>>>>> 03f74aca74312dbeaf24d7e61306dd6a786dc3d0
