{
  "id": 2126353,
  "type": "Feature",
  "properties": {
    "tgn:hierarchy":[
        "tgn:2126353",
        "tgn:1000001",
        "tgn:7012149",
        "tgn:2002062",
        "tgn:7007826",
        "tgn:7029392"
    ],
    "tgn:id":2126353,
    "tgn:name":"Adobe Draw",
    "tgn:placetype":[
        "aat:300008761"
    ]
},
  "bbox": [],
  "geometry": {"coordinates":[-103.85,30.9833],"type":"Point"}
}