{
  "id": 7547320,
  "type": "Feature",
  "properties": {
    "tgn:hierarchy":[
        "tgn:7547320",
        "tgn:1000004",
        "tgn:7031781",
        "tgn:7000198",
        "tgn:7029392"
    ],
    "tgn:id":7547320,
    "tgn:name:en":"B\u0101nbarad",
    "tgn:placetype":[
        "aat:300008347"
    ]
},
  "bbox": [],
  "geometry": {"coordinates":[81.383333,21.35],"type":"Point"}
}