{
  "id": 7180218,
  "type": "Feature",
  "properties": {
    "tgn:hierarchy":[
        "tgn:7180218",
        "tgn:7003669",
        "tgn:1000003",
        "tgn:7000084",
        "tgn:7029392"
    ],
    "tgn:id":7180218,
    "tgn:name":"F\u00fcchsel Holz",
    "tgn:placetype":[
        "aat:300008863"
    ]
},
  "bbox": [],
  "geometry": {"coordinates":[12.583333,49.366667],"type":"Point"}
}