{
  "id": 2716177,
  "type": "Feature",
  "properties": {
    "tgn:hierarchy":[
        "tgn:2716177",
        "tgn:1000001",
        "tgn:7013649",
        "tgn:7012149",
        "tgn:7007251",
        "tgn:7029392"
    ],
    "tgn:id":2716177,
    "tgn:name":"Thatcher Woods",
    "tgn:placetype":[
        "aat:300132451"
    ]
},
  "bbox": [],
  "geometry": {"coordinates":[-87.8167,41.8833],"type":"Point"}
}