{
  "id": 2540814,
  "type": "Feature",
  "properties": {
    "tgn:hierarchy":[
        "tgn:2540814",
        "tgn:1000001",
        "tgn:7012149",
        "tgn:2002034",
        "tgn:7007826",
        "tgn:7029392"
    ],
    "tgn:id":2540814,
    "tgn:name":"Niblock",
    "tgn:placetype":[
        "aat:300008347"
    ]
},
  "bbox": [],
  "geometry": {"coordinates":[-99.3833,31.1333],"type":"Point"}
}