{
  "id": 2274853,
  "type": "Feature",
  "properties": {
    "tgn:hierarchy":[
        "tgn:2274853",
        "tgn:1000001",
        "tgn:7012149",
        "tgn:2001862",
        "tgn:7007825",
        "tgn:7029392"
    ],
    "tgn:id":2274853,
    "tgn:name":"Damron Hollow",
    "tgn:placetype":[
        "aat:300008761"
    ]
},
  "bbox": [],
  "geometry": {"coordinates":[-86.2833,35.2167],"type":"Point"}
}