{
  "id": 2425166,
  "type": "Feature",
  "properties": {
    "tgn:hierarchy":[
        "tgn:2425166",
        "tgn:1000001",
        "tgn:7012149",
        "tgn:2000978",
        "tgn:7007520",
        "tgn:7029392"
    ],
    "tgn:id":2425166,
    "tgn:name":"Johnson Landing",
    "tgn:placetype":[
        "aat:300008347"
    ]
},
  "bbox": [],
  "geometry": {"coordinates":[-87.45,45.2667],"type":"Point"}
}