<<<<<<< HEAD
{
  "id": 2335195,
  "type": "Feature",
  "properties": {
    "tgn:hierarchy":[
        "tgn:2335195",
        "tgn:1000001",
        "tgn:7012149",
        "tgn:2001488",
        "tgn:7007709",
        "tgn:7029392"
    ],
    "tgn:id":2335195,
    "tgn:name":"Fort Clark",
    "tgn:placetype":[
        "aat:300008347"
    ]
},
  "bbox": [],
  "geometry": {"coordinates":[-75.7167,35.1833],"type":"Point"}
}
=======
{"geometry":{"type":"Point","coordinates":[-75.716700,35.183300]},"type":"Feature","properties":{"hierarchy":["tgn:2335195","tgn:1000001","tgn:7012149","tgn:2001488","tgn:7007709","tgn:7029392"],"placetype":["aat:300008347"],"id":2335195,"name:xx":"Fort Clark"}}
>>>>>>> 03f74aca74312dbeaf24d7e61306dd6a786dc3d0
