{
  "id": 1132581,
  "type": "Feature",
  "properties": {
    "tgn:hierarchy":[
        "tgn:1132581",
        "tgn:1000001",
        "tgn:1002902",
        "tgn:7012149",
        "tgn:7007516",
        "tgn:7029392"
    ],
    "tgn:id":1132581,
    "tgn:name":"Broad Creek",
    "tgn:placetype":[
        "aat:300008706"
    ]
},
  "bbox": [],
  "geometry": {"coordinates":[-75.85,37.9333],"type":"Point"}
}