{
  "id": 2685059,
  "type": "Feature",
  "properties": {
    "tgn:hierarchy":[
        "tgn:2685059",
        "tgn:1000001",
        "tgn:7012149",
        "tgn:1002968",
        "tgn:7007706",
        "tgn:7029392"
    ],
    "tgn:id":2685059,
    "tgn:name":"Sponseller Ditch",
    "tgn:placetype":[
        "aat:300006075"
    ]
},
  "bbox": [],
  "geometry": {"coordinates":[-84.7667,40.9333],"type":"Point"}
}