{
  "id": 7027900,
  "type": "Feature",
  "properties": {
    "tgn:hierarchy":[
        "tgn:7027900",
        "tgn:7002445",
        "tgn:1000003",
        "tgn:7008157",
        "tgn:7008591",
        "tgn:7029392"
    ],
    "tgn:id":7027900,
    "tgn:name:en":"Hackthorn",
    "tgn:placetype":[
        "aat:300008347",
        "aat:300008372"
    ]
},
  "bbox": [],
  "geometry": {"coordinates":[-0.516667,53.316667],"type":"Point"}
}