{
  "id": 1010173,
  "type": "Feature",
  "properties": {
    "tgn:hierarchy":[
        "tgn:1010173",
        "tgn:7005668",
        "tgn:1010206",
        "tgn:1000006",
        "tgn:7029392"
    ],
    "tgn:id":1010173,
    "tgn:name":"Ngemelis Islands",
    "tgn:placetype":[
        "aat:300386853"
    ]
},
  "bbox": [],
  "geometry": {"coordinates":[134.25,7.1167],"type":"Point"}
}