{
  "id": 2656499,
  "type": "Feature",
  "properties": {
    "tgn:hierarchy":[
        "tgn:2656499",
        "tgn:1000001",
        "tgn:2001583",
        "tgn:7012149",
        "tgn:7007705",
        "tgn:7029392"
    ],
    "tgn:id":2656499,
    "tgn:name":"Sheep Butte",
    "tgn:placetype":[
        "aat:300008798"
    ]
},
  "bbox": [],
  "geometry": {"coordinates":[-103.7833,47.6167],"type":"Point"}
}