{
  "id": 7096484,
  "type": "Feature",
  "properties": {
    "tgn:hierarchy":[
        "tgn:7096484",
        "tgn:1000003",
        "tgn:7000094",
        "tgn:7000084",
        "tgn:7029392"
    ],
    "tgn:id":7096484,
    "tgn:name":"Sehlen",
    "tgn:placetype":[
        "aat:300008347"
    ]
},
  "bbox": [],
  "geometry": {"coordinates":[13.383333,54.383333],"type":"Point"}
}