{
  "id": 2482818,
  "type": "Feature",
  "properties": {
    "tgn:hierarchy":[
        "tgn:2482818",
        "tgn:1000001",
        "tgn:7012149",
        "tgn:2002127",
        "tgn:7007827",
        "tgn:7029392"
    ],
    "tgn:id":2482818,
    "tgn:name":"Lark Canyon",
    "tgn:placetype":[
        "aat:300008761"
    ]
},
  "bbox": [],
  "geometry": {"coordinates":[-113.55,37.3667],"type":"Point"}
}