{
  "id": 2349790,
  "type": "Feature",
  "properties": {
    "tgn:hierarchy":[
        "tgn:2349790",
        "tgn:1000001",
        "tgn:7012149",
        "tgn:1002418",
        "tgn:7007920",
        "tgn:7029392"
    ],
    "tgn:id":2349790,
    "tgn:name":"Gillis Slough",
    "tgn:placetype":[
        "aat:300008699"
    ]
},
  "bbox": [],
  "geometry": {"coordinates":[-124.0333,47.0333],"type":"Point"}
}