{
  "id": 2441124,
  "type": "Feature",
  "properties": {
    "tgn:hierarchy":[
        "tgn:2441124",
        "tgn:1000001",
        "tgn:2001479",
        "tgn:7012149",
        "tgn:7007709",
        "tgn:7029392"
    ],
    "tgn:id":2441124,
    "tgn:name":"Knolls Association Lake",
    "tgn:placetype":[
        "aat:300006191"
    ]
},
  "bbox": [],
  "geometry": {"coordinates":[-81.2167,35.6167],"type":"Point"}
}