{
  "id": 2423762,
  "type": "Feature",
  "properties": {
    "tgn:hierarchy":[
        "tgn:2423762",
        "tgn:1000001",
        "tgn:7012149",
        "tgn:2002375",
        "tgn:7007923",
        "tgn:7029392"
    ],
    "tgn:id":2423762,
    "tgn:name":"John W Griffen Reservoir",
    "tgn:placetype":[
        "aat:300006191"
    ]
},
  "bbox": [],
  "geometry": {"coordinates":[-104.9333,41.1667],"type":"Point"}
}