{
  "id": 7240718,
  "type": "Feature",
  "properties": {
    "tgn:hierarchy":[
        "tgn:7240718",
        "tgn:7003466",
        "tgn:1000003",
        "tgn:1000063",
        "tgn:4012014",
        "tgn:7029392"
    ],
    "tgn:id":7240718,
    "tgn:name":"Fioche, Bois de",
    "tgn:placetype":[
        "aat:300008863"
    ]
},
  "bbox": [],
  "geometry": {"coordinates":[4.769346,50.146577],"type":"Point"}
}