{
  "id": 2310750,
  "type": "Feature",
  "properties": {
    "tgn:hierarchy":[
        "tgn:2310750",
        "tgn:1000001",
        "tgn:2001704",
        "tgn:7012149",
        "tgn:7007708",
        "tgn:7029392"
    ],
    "tgn:id":2310750,
    "tgn:name":"Eckley",
    "tgn:placetype":[
        "aat:300008347"
    ]
},
  "bbox": [],
  "geometry": {"coordinates":[-124.1833,42.8333],"type":"Point"}
}