{
  "id": 7520439,
  "type": "Feature",
  "properties": {
    "tgn:hierarchy":[
        "tgn:7520439",
        "tgn:7001242",
        "tgn:7016833",
        "tgn:1001418",
        "tgn:7029392"
    ],
    "tgn:id":7520439,
    "tgn:name:en":"Qabr Abu Tashd\u00eeda",
    "tgn:placetype":[
        "aat:300005926"
    ]
},
  "bbox": [],
  "geometry": {"coordinates":[25.855927,30.895536],"type":"Point"}
}