{
  "id": 2437043,
  "type": "Feature",
  "properties": {
    "tgn:hierarchy":[
        "tgn:2437043",
        "tgn:7006450",
        "tgn:2000069",
        "tgn:1000001",
        "tgn:7012149",
        "tgn:7029392"
    ],
    "tgn:id":2437043,
    "tgn:name":"Killinupak Mountain",
    "tgn:placetype":[
        "aat:300008798"
    ]
},
  "bbox": [],
  "geometry": {"coordinates":[-165.1333,60.6333],"type":"Point"}
}