{
  "id": 7378201,
  "type": "Feature",
  "properties": {
    "tgn:hierarchy":[
        "tgn:7378201",
        "tgn:1000001",
        "tgn:7005593",
        "tgn:7005560",
        "tgn:7029392"
    ],
    "tgn:id":7378201,
    "tgn:name":"La Yesca",
    "tgn:placetype":[
        "aat:300008347"
    ]
},
  "bbox": [],
  "geometry": {"coordinates":[-99.116667,21.216667],"type":"Point"}
}