{
  "id": 2651544,
  "type": "Feature",
  "properties": {
    "tgn:hierarchy":[
        "tgn:2651544",
        "tgn:1000001",
        "tgn:7012149",
        "tgn:2001286",
        "tgn:7007524",
        "tgn:7029392"
    ],
    "tgn:id":2651544,
    "tgn:name":"Sedlak Creek",
    "tgn:placetype":[
        "aat:300008706"
    ]
},
  "bbox": [],
  "geometry": {"coordinates":[-115.3333,48.05],"type":"Point"}
}