{
  "id": 2488509,
  "type": "Feature",
  "properties": {
    "tgn:hierarchy":[
        "tgn:2488509",
        "tgn:1000001",
        "tgn:7012149",
        "tgn:7007157",
        "tgn:7029392"
    ],
    "tgn:id":2488509,
    "tgn:name":"Mahogany Ridge",
    "tgn:placetype":[
        "aat:300266640"
    ]
},
  "bbox": [],
  "geometry": {"coordinates":[-120.25,41.1833],"type":"Point"}
}