{
  "id": 2631536,
  "type": "Feature",
  "properties": {
    "tgn:hierarchy":[
        "tgn:2631536",
        "tgn:1000001",
        "tgn:7012149",
        "tgn:1003047",
        "tgn:7007710",
        "tgn:7029392"
    ],
    "tgn:id":2631536,
    "tgn:name":"Round Top",
    "tgn:placetype":[
        "aat:300008798"
    ]
},
  "bbox": [],
  "geometry": {"coordinates":[-76.55,40.0333],"type":"Point"}
}