{
  "id": 7391590,
  "type": "Feature",
  "properties": {
    "tgn:hierarchy":[
        "tgn:7391590",
        "tgn:1001853",
        "tgn:1000001",
        "tgn:7005560",
        "tgn:7029392"
    ],
    "tgn:id":7391590,
    "tgn:name":"Rancho Las Encinillas",
    "tgn:placetype":[
        "aat:300008347"
    ]
},
  "bbox": [],
  "geometry": {"coordinates":[-102.016667,25.433333],"type":"Point"}
}