{
  "id": 2033806,
  "type": "Feature",
  "properties": {
    "tgn:hierarchy":[
        "tgn:2033806",
        "tgn:1000001",
        "tgn:7012149",
        "tgn:1002439",
        "tgn:7007252",
        "tgn:7029392"
    ],
    "tgn:id":2033806,
    "tgn:name":"Strawtown",
    "tgn:placetype":[
        "aat:300008347"
    ]
},
  "bbox": [],
  "geometry": {"coordinates":[-85.9333,40.1167],"type":"Point"}
}