{
  "id": 2146218,
  "type": "Feature",
  "properties": {
    "tgn:hierarchy":[
        "tgn:2146218",
        "tgn:1000001",
        "tgn:7012149",
        "tgn:2001217",
        "tgn:7007523",
        "tgn:7029392"
    ],
    "tgn:id":2146218,
    "tgn:name":"Ballew Hollow",
    "tgn:placetype":[
        "aat:300008761"
    ]
},
  "bbox": [],
  "geometry": {"coordinates":[-90.35,37.3833],"type":"Point"}
}