{
  "id": 2605160,
  "type": "Feature",
  "properties": {
    "tgn:hierarchy":[
        "tgn:2605160",
        "tgn:1000001",
        "tgn:7012149",
        "tgn:2001066",
        "tgn:7007521",
        "tgn:7029392"
    ],
    "tgn:id":2605160,
    "tgn:name":"Rafferty Creek",
    "tgn:placetype":[
        "aat:300008706"
    ]
},
  "bbox": [],
  "geometry": {"coordinates":[-95.5833,48.65],"type":"Point"}
}