{
  "id": 2069121,
  "type": "Feature",
  "properties": {
    "tgn:hierarchy":[
        "tgn:2069121",
        "tgn:1000001",
        "tgn:7012149",
        "tgn:1002950",
        "tgn:7007568",
        "tgn:7029392"
    ],
    "tgn:id":2069121,
    "tgn:name":"Etna",
    "tgn:placetype":[
        "aat:300008347"
    ]
},
  "bbox": [],
  "geometry": {"coordinates":[-76.3833,42.4833],"type":"Point"}
}