{
  "id": 2326141,
  "type": "Feature",
  "properties": {
    "tgn:hierarchy":[
        "tgn:2326141",
        "tgn:1000001",
        "tgn:7006451",
        "tgn:7012149",
        "tgn:2000098",
        "tgn:7029392"
    ],
    "tgn:id":2326141,
    "tgn:name":"Figure Four Canyon",
    "tgn:placetype":[
        "aat:300008761"
    ]
},
  "bbox": [],
  "geometry": {"coordinates":[-113.8167,36.8667],"type":"Point"}
}