{
  "id": 7346284,
  "type": "Feature",
  "properties": {
    "tgn:hierarchy":[
        "tgn:7346284",
        "tgn:7002824",
        "tgn:1000003",
        "tgn:7002786",
        "tgn:1000095",
        "tgn:7029392"
    ],
    "tgn:id":7346284,
    "tgn:name":"Barizo, Puerto de",
    "tgn:placetype":[
        "aat:300132317"
    ]
},
  "bbox": [],
  "geometry": {"coordinates":[-8.866667,43.316667],"type":"Point"}
}