{
  "id": 7428080,
  "type": "Feature",
  "properties": {
    "tgn:hierarchy":[
        "tgn:7428080",
        "tgn:1000001",
        "tgn:7005594",
        "tgn:7005560",
        "tgn:7029392"
    ],
    "tgn:id":7428080,
    "tgn:name":"Tancha",
    "tgn:placetype":[
        "aat:300008347"
    ]
},
  "bbox": [],
  "geometry": {"coordinates":[-99.166667,22.216667],"type":"Point"}
}