{
  "id": 7129518,
  "type": "Feature",
  "properties": {
    "tgn:hierarchy":[
        "tgn:7129518",
        "tgn:7000096",
        "tgn:1000003",
        "tgn:7000084",
        "tgn:7029392"
    ],
    "tgn:id":7129518,
    "tgn:name":"Manker",
    "tgn:placetype":[
        "aat:300008347"
    ]
},
  "bbox": [],
  "geometry": {"coordinates":[12.666667,52.85],"type":"Point"}
}