{
  "id": 2548908,
  "type": "Feature",
  "properties": {
    "tgn:hierarchy":[
        "tgn:2548908",
        "tgn:1000001",
        "tgn:7012149",
        "tgn:7007708",
        "tgn:7029392"
    ],
    "tgn:id":2548908,
    "tgn:name":"North Pole Ridge",
    "tgn:placetype":[
        "aat:300266640"
    ]
},
  "bbox": [],
  "geometry": {"coordinates":[-120.5167,45.1167],"type":"Point"}
}