{
  "id": 2284471,
  "type": "Feature",
  "properties": {
    "tgn:hierarchy":[
        "tgn:2284471",
        "tgn:7002659",
        "tgn:1000001",
        "tgn:7012149",
        "tgn:2000051",
        "tgn:7029392"
    ],
    "tgn:id":2284471,
    "tgn:name":"Derrick Hollow",
    "tgn:placetype":[
        "aat:300008761"
    ]
},
  "bbox": [],
  "geometry": {"coordinates":[-86.75,34.3333],"type":"Point"}
}