{
  "id": 2110970,
  "type": "Feature",
  "properties": {
    "tgn:hierarchy":[
        "tgn:2110970",
        "tgn:2002137",
        "tgn:1000001",
        "tgn:7012149",
        "tgn:7007919",
        "tgn:7029392"
    ],
    "tgn:id":2110970,
    "tgn:name":"Cash Corner",
    "tgn:placetype":[
        "aat:300008347",
        "aat:300387210"
    ]
},
  "bbox": [],
  "geometry": {"coordinates":[-78.2667,38.0833],"type":"Point"}
}