{
  "id": 2694479,
  "type": "Feature",
  "properties": {
    "tgn:hierarchy":[
        "tgn:2694479",
        "tgn:1000001",
        "tgn:7012149",
        "tgn:2000435",
        "tgn:7007248",
        "tgn:7029392"
    ],
    "tgn:id":2694479,
    "tgn:name":"Stewart Cove",
    "tgn:placetype":[
        "aat:300008761"
    ]
},
  "bbox": [],
  "geometry": {"coordinates":[-84.0167,34.8167],"type":"Point"}
}