<<<<<<< HEAD
{
  "id": 7029983,
  "type": "Feature",
  "properties": {
    "tgn:hierarchy":[
        "tgn:7029983",
        "tgn:1003611",
        "tgn:7002445",
        "tgn:1000003",
        "tgn:7029507",
        "tgn:7008591",
        "tgn:7029392"
    ],
    "tgn:id":7029983,
    "tgn:name":"Flockton",
    "tgn:placetype":[
        "aat:300008347",
        "aat:300008372"
    ]
},
  "bbox": [],
  "geometry": {"coordinates":[-1.65,53.616667],"type":"Point"}
}
=======
{"geometry":{"type":"Point","coordinates":[-1.650000,53.616667]},"type":"Feature","properties":{"hierarchy":["tgn:7029983","tgn:1003611","tgn:7002445","tgn:1000003","tgn:7029507","tgn:7008591","tgn:7029392"],"placetype":["aat:300008347","aat:300008372"],"id":7029983,"name:xx":"Flockton"}}
>>>>>>> 03f74aca74312dbeaf24d7e61306dd6a786dc3d0
