{
  "id": 7540026,
  "type": "Feature",
  "properties": {
    "tgn:hierarchy":[
        "tgn:7540026",
        "tgn:7001242",
        "tgn:7016833",
        "tgn:7000124",
        "tgn:7029392"
    ],
    "tgn:id":7540026,
    "tgn:name:en":"Nag' Nikheidar",
    "tgn:placetype":[
        "aat:300008347"
    ]
},
  "bbox": [],
  "geometry": {"coordinates":[31.566667,26.683333],"type":"Point"}
}