{
  "id": 7107567,
  "type": "Feature",
  "properties": {
    "tgn:hierarchy":[
        "tgn:7107567",
        "tgn:7000096",
        "tgn:1000003",
        "tgn:7000084",
        "tgn:7029392"
    ],
    "tgn:id":7107567,
    "tgn:name":"Rauhe Berg",
    "tgn:placetype":[
        "aat:300008777"
    ]
},
  "bbox": [],
  "geometry": {"coordinates":[12.783333,52.283333],"type":"Point"}
}