{
  "id": 7120498,
  "type": "Feature",
  "properties": {
    "tgn:hierarchy":[
        "tgn:7120498",
        "tgn:7003669",
        "tgn:1000003",
        "tgn:7000084",
        "tgn:7029392"
    ],
    "tgn:id":7120498,
    "tgn:name":"Pfarrerbrunn",
    "tgn:placetype":[
        "aat:300008697"
    ]
},
  "bbox": [],
  "geometry": {"coordinates":[10.183333,49.816667],"type":"Point"}
}