{
  "id": 1140575,
  "type": "Feature",
  "properties": {
    "tgn:hierarchy":[
        "tgn:1140575",
        "tgn:7016675",
        "tgn:1000004",
        "tgn:7000896",
        "tgn:1000120",
        "tgn:7029392"
    ],
    "tgn:id":1140575,
    "tgn:name":"Shima",
    "tgn:placetype":[
        "aat:300008347"
    ]
},
  "bbox": [],
  "geometry": {"coordinates":[135.3333,34.9833],"type":"Point"}
}