{
  "id": 2388007,
  "type": "Feature",
  "properties": {
    "tgn:hierarchy":[
        "tgn:2388007",
        "tgn:1000001",
        "tgn:7012149",
        "tgn:2001114",
        "tgn:7007522",
        "tgn:7029392"
    ],
    "tgn:id":2388007,
    "tgn:name":"Hickory Creek",
    "tgn:placetype":[
        "aat:300008706"
    ]
},
  "bbox": [],
  "geometry": {"coordinates":[-88.2667,34.2333],"type":"Point"}
}