{
  "id": 7142232,
  "type": "Feature",
  "properties": {
    "tgn:hierarchy":[
        "tgn:7142232",
        "tgn:7000096",
        "tgn:1000003",
        "tgn:7000084",
        "tgn:7029392"
    ],
    "tgn:id":7142232,
    "tgn:name":"Maiblumengehege",
    "tgn:placetype":[
        "aat:300008347"
    ]
},
  "bbox": [],
  "geometry": {"coordinates":[13.416667,51.45],"type":"Point"}
}