<<<<<<< HEAD
{
  "id": 7118583,
  "type": "Feature",
  "properties": {
    "tgn:hierarchy":[
        "tgn:7118583",
        "tgn:1000003",
        "tgn:7003676",
        "tgn:7000084",
        "tgn:7029392"
    ],
    "tgn:id":7118583,
    "tgn:name":"Polstertaler Teich",
    "tgn:placetype":[
        "aat:300008688"
    ]
},
  "bbox": [],
  "geometry": {"coordinates":[10.416667,51.8],"type":"Point"}
}
=======
{"geometry":{"type":"Point","coordinates":[10.416667,51.800000]},"type":"Feature","properties":{"hierarchy":["tgn:7118583","tgn:1000003","tgn:7003676","tgn:7000084","tgn:7029392"],"placetype":["aat:300008688"],"id":7118583,"name:xx":"Polstertaler Teich"}}
>>>>>>> 03f74aca74312dbeaf24d7e61306dd6a786dc3d0
