{
  "id": 2186515,
  "type": "Feature",
  "properties": {
    "tgn:hierarchy":[
        "tgn:2186515",
        "tgn:1000001",
        "tgn:7012149",
        "tgn:2000824",
        "tgn:7007255",
        "tgn:7029392"
    ],
    "tgn:id":2186515,
    "tgn:name":"Bone Hollow",
    "tgn:placetype":[
        "aat:300008761"
    ]
},
  "bbox": [],
  "geometry": {"coordinates":[-82.45,37.8333],"type":"Point"}
}