{
  "id": 2323018,
  "type": "Feature",
  "properties": {
    "tgn:hierarchy":[
        "tgn:2323018",
        "tgn:1000001",
        "tgn:1002270",
        "tgn:7012149",
        "tgn:7007708",
        "tgn:7029392"
    ],
    "tgn:id":2323018,
    "tgn:name":"Faraday Lake",
    "tgn:placetype":[
        "aat:300006191"
    ]
},
  "bbox": [],
  "geometry": {"coordinates":[-122.3167,45.2667],"type":"Point"}
}