{
  "id": 2476125,
  "type": "Feature",
  "properties": {
    "tgn:hierarchy":[
        "tgn:2476125",
        "tgn:7002659",
        "tgn:1000001",
        "tgn:7012149",
        "tgn:2000062",
        "tgn:7029392"
    ],
    "tgn:id":2476125,
    "tgn:name":"Lulu, Lake",
    "tgn:placetype":[
        "aat:300006191"
    ]
},
  "bbox": [],
  "geometry": {"coordinates":[-87.3167,33.1167],"type":"Point"}
}