{
  "id": 2120140,
  "type": "Feature",
  "properties": {
    "tgn:hierarchy":[
        "tgn:2120140",
        "tgn:1000001",
        "tgn:7012149",
        "tgn:2002299",
        "tgn:7013961",
        "tgn:7029392"
    ],
    "tgn:id":2120140,
    "tgn:name":"Sweet Run",
    "tgn:placetype":[
        "aat:300008347"
    ]
},
  "bbox": [],
  "geometry": {"coordinates":[-82.5667,38.3667],"type":"Point"}
}