{
  "id": 2230035,
  "type": "Feature",
  "properties": {
    "tgn:hierarchy":[
        "tgn:2230035",
        "tgn:1000001",
        "tgn:7012149",
        "tgn:2001449",
        "tgn:7007566",
        "tgn:7029392"
    ],
    "tgn:id":2230035,
    "tgn:name":"Cedros, Ca\u00f1ada los",
    "tgn:placetype":[
        "aat:300008699"
    ]
},
  "bbox": [],
  "geometry": {"coordinates":[-105.8667,36.0333],"type":"Point"}
}