{
  "id": 2510306,
  "type": "Feature",
  "properties": {
    "tgn:hierarchy":[
        "tgn:2510306",
        "tgn:1000001",
        "tgn:7012149",
        "tgn:1002945",
        "tgn:7007710",
        "tgn:7029392"
    ],
    "tgn:id":2510306,
    "tgn:name":"Middle Ridge Swamp",
    "tgn:placetype":[
        "aat:300008905"
    ]
},
  "bbox": [],
  "geometry": {"coordinates":[-77.4167,41.6833],"type":"Point"}
}