<<<<<<< HEAD
{
  "id": 7021638,
  "type": "Feature",
  "properties": {
    "tgn:hierarchy":[
        "tgn:7021638",
        "tgn:1000001",
        "tgn:7012149",
        "tgn:1002761",
        "tgn:7007706",
        "tgn:7029392"
    ],
    "tgn:id":7021638,
    "tgn:name":"Mineyahta on-the-Bay",
    "tgn:placetype":[
        "aat:300008347"
    ]
},
  "bbox": [],
  "geometry": {"coordinates":[-82.6333,41.4833],"type":"Point"}
}
=======
{"geometry":{"type":"Point","coordinates":[-82.633300,41.483300]},"type":"Feature","properties":{"hierarchy":["tgn:7021638","tgn:1000001","tgn:7012149","tgn:1002761","tgn:7007706","tgn:7029392"],"placetype":["aat:300008347"],"id":7021638,"name:xx":"Mineyahta on-the-Bay"}}
>>>>>>> 03f74aca74312dbeaf24d7e61306dd6a786dc3d0
