{
  "id": 2416993,
  "type": "Feature",
  "properties": {
    "tgn:hierarchy":[
        "tgn:2416993",
        "tgn:1000001",
        "tgn:7012149",
        "tgn:2000481",
        "tgn:7007250",
        "tgn:7029392"
    ],
    "tgn:id":2416993,
    "tgn:name":"Jackass Ridge",
    "tgn:placetype":[
        "aat:300266640"
    ]
},
  "bbox": [],
  "geometry": {"coordinates":[-114.0167,45.2833],"type":"Point"}
}