{
  "id": 7480200,
  "type": "Feature",
  "properties": {
    "tgn:hierarchy":[
        "tgn:7480200",
        "tgn:1000004",
        "tgn:1000454",
        "tgn:1000141",
        "tgn:7029392"
    ],
    "tgn:id":7480200,
    "tgn:name":"Hongshijiao",
    "tgn:placetype":[
        "aat:300008347"
    ]
},
  "bbox": [],
  "geometry": {"coordinates":[121.472979,25.185349],"type":"Point"}
}