{
  "id": 2245930,
  "type": "Feature",
  "properties": {
    "tgn:hierarchy":[
        "tgn:2245930",
        "tgn:1000001",
        "tgn:7012149",
        "tgn:2001075",
        "tgn:7007521",
        "tgn:7029392"
    ],
    "tgn:id":2245930,
    "tgn:name":"Coal Lake",
    "tgn:placetype":[
        "aat:300008680"
    ]
},
  "bbox": [],
  "geometry": {"coordinates":[-94.75,46.0667],"type":"Point"}
}