{
  "id": 2741016,
  "type": "Feature",
  "properties": {
    "tgn:hierarchy":[
        "tgn:2741016",
        "tgn:1000001",
        "tgn:7012149",
        "tgn:1002522",
        "tgn:7007922",
        "tgn:7029392"
    ],
    "tgn:id":2741016,
    "tgn:name":"Upper Spring Lake",
    "tgn:placetype":[
        "aat:300006191"
    ]
},
  "bbox": [],
  "geometry": {"coordinates":[-88.55,42.8833],"type":"Point"}
}