{
  "id": 7273814,
  "type": "Feature",
  "properties": {
    "tgn:concordances":{
        "gn:id":"2744992"
    },
    "tgn:hierarchy":[
        "tgn:7273814",
        "tgn:1000003",
        "tgn:7003624",
        "tgn:7016845",
        "tgn:7029392"
    ],
    "tgn:id":7273814,
    "tgn:name:nl":"Waspik Boven",
    "tgn:placetype":[
        "aat:300008347"
    ]
},
  "bbox": [],
  "geometry": {"coordinates":[4.966667,51.683333],"type":"Point"}
}