{
  "id": 2424492,
  "type": "Feature",
  "properties": {
    "tgn:hierarchy":[
        "tgn:2424492",
        "tgn:2001423",
        "tgn:1000001",
        "tgn:7012149",
        "tgn:7007564",
        "tgn:7029392"
    ],
    "tgn:id":2424492,
    "tgn:name":"Johnson Cove",
    "tgn:placetype":[
        "aat:300132316"
    ]
},
  "bbox": [],
  "geometry": {"coordinates":[-71.25,43.5833],"type":"Point"}
}