{
  "id": 2405323,
  "type": "Feature",
  "properties": {
    "tgn:hierarchy":[
        "tgn:2405323",
        "tgn:1000001",
        "tgn:7012149",
        "tgn:2001718",
        "tgn:7007708",
        "tgn:7029392"
    ],
    "tgn:id":2405323,
    "tgn:name":"Huffman Island",
    "tgn:placetype":[
        "aat:300008791"
    ]
},
  "bbox": [],
  "geometry": {"coordinates":[-117.1667,44.25],"type":"Point"}
}