<<<<<<< HEAD
{
  "id": 2405323,
  "type": "Feature",
  "properties": {
    "tgn:hierarchy":[
        "tgn:2405323",
        "tgn:1000001",
        "tgn:7012149",
        "tgn:2001718",
        "tgn:7007708",
        "tgn:7029392"
    ],
    "tgn:id":2405323,
    "tgn:name":"Huffman Island",
    "tgn:placetype":[
        "aat:300008791"
    ]
},
  "bbox": [],
  "geometry": {"coordinates":[-117.1667,44.25],"type":"Point"}
}
=======
{"geometry":{"type":"Point","coordinates":[-117.166700,44.250000]},"type":"Feature","properties":{"hierarchy":["tgn:2405323","tgn:1000001","tgn:7012149","tgn:2001718","tgn:7007708","tgn:7029392"],"placetype":["aat:300008791"],"id":2405323,"name:xx":"Huffman Island"}}
>>>>>>> 03f74aca74312dbeaf24d7e61306dd6a786dc3d0
