{
  "id": 2640491,
  "type": "Feature",
  "properties": {
    "tgn:hierarchy":[
        "tgn:2640491",
        "tgn:1000001",
        "tgn:7012149",
        "tgn:2002075",
        "tgn:7007826",
        "tgn:7029392"
    ],
    "tgn:id":2640491,
    "tgn:name":"San Jose Tank",
    "tgn:placetype":[
        "aat:300006191"
    ]
},
  "bbox": [],
  "geometry": {"coordinates":[-98.7333,26.75],"type":"Point"}
}