{
  "id": 2477908,
  "type": "Feature",
  "properties": {
    "tgn:hierarchy":[
        "tgn:2477908",
        "tgn:1000001",
        "tgn:7012149",
        "tgn:7007157",
        "tgn:1002791",
        "tgn:7029392"
    ],
    "tgn:id":2477908,
    "tgn:name":"Macedon Tunnel",
    "tgn:placetype":[
        "aat:300000390"
    ]
},
  "bbox": [],
  "geometry": {"coordinates":[-120.5833,39.1667],"type":"Point"}
}