{
  "id": 2668516,
  "type": "Feature",
  "properties": {
    "tgn:hierarchy":[
        "tgn:2668516",
        "tgn:1000001",
        "tgn:7012149",
        "tgn:2001662",
        "tgn:7007707",
        "tgn:7029392"
    ],
    "tgn:id":2668516,
    "tgn:name":"Slate Creek",
    "tgn:placetype":[
        "aat:300008706"
    ]
},
  "bbox": [],
  "geometry": {"coordinates":[-94.4667,34.55],"type":"Point"}
}