{
  "id": 2649496,
  "type": "Feature",
  "properties": {
    "tgn:hierarchy":[
        "tgn:2649496",
        "tgn:1000001",
        "tgn:7012149",
        "tgn:2001394",
        "tgn:7007525",
        "tgn:7029392"
    ],
    "tgn:id":2649496,
    "tgn:name":"Scottsbluff Drain",
    "tgn:placetype":[
        "aat:300006075"
    ]
},
  "bbox": [],
  "geometry": {"coordinates":[-103.6833,41.8833],"type":"Point"}
}