{
  "id": 2754634,
  "type": "Feature",
  "properties": {
    "tgn:hierarchy":[
        "tgn:2754634",
        "tgn:1000001",
        "tgn:1002266",
        "tgn:7012149",
        "tgn:7007710",
        "tgn:7029392"
    ],
    "tgn:id":2754634,
    "tgn:name":"Ways Run",
    "tgn:placetype":[
        "aat:300008699"
    ]
},
  "bbox": [],
  "geometry": {"coordinates":[-75.8667,39.7667],"type":"Point"}
}