{
  "id": 1134669,
  "type": "Feature",
  "properties": {
    "tgn:hierarchy":[
        "tgn:1134669",
        "tgn:1000001",
        "tgn:7012149",
        "tgn:1002356",
        "tgn:7007568",
        "tgn:7029392"
    ],
    "tgn:id":1134669,
    "tgn:name":"Spicer Creek",
    "tgn:placetype":[
        "aat:300008706"
    ]
},
  "bbox": [],
  "geometry": {"coordinates":[-78.95,42.9833],"type":"Point"}
}