{
  "id": 2182531,
  "type": "Feature",
  "properties": {
    "tgn:hierarchy":[
        "tgn:2182531",
        "tgn:1000001",
        "tgn:7012149",
        "tgn:1002877",
        "tgn:7007706",
        "tgn:7029392"
    ],
    "tgn:id":2182531,
    "tgn:name":"Blue Run",
    "tgn:placetype":[
        "aat:300008699"
    ]
},
  "bbox": [],
  "geometry": {"coordinates":[-82.95,38.8833],"type":"Point"}
}