{
  "id": 2002393,
  "type": "Feature",
  "properties": {
    "tgn:hierarchy":[
        "tgn:2002393",
        "tgn:7002659",
        "tgn:1000001",
        "tgn:2000003",
        "tgn:7012149",
        "tgn:7029392"
    ],
    "tgn:id":2002393,
    "tgn:name":"Abercrombie",
    "tgn:placetype":[
        "aat:300008347",
        "aat:300387210"
    ]
},
  "bbox": [],
  "geometry": {"coordinates":[-87.15,32.8333],"type":"Point"}
}