{
  "id": 7378740,
  "type": "Feature",
  "properties": {
    "tgn:hierarchy":[
        "tgn:7378740",
        "tgn:1000001",
        "tgn:7005599",
        "tgn:7005560",
        "tgn:7029392"
    ],
    "tgn:id":7378740,
    "tgn:name":"Los Puestos",
    "tgn:placetype":[
        "aat:300008347"
    ]
},
  "bbox": [],
  "geometry": {"coordinates":[-97.783333,21.833333],"type":"Point"}
}