{
  "id": 1009054,
  "type": "Feature",
  "properties": {
    "tgn:hierarchy":[
        "tgn:1009054",
        "tgn:7005685",
        "tgn:1000001",
        "tgn:7005802",
        "tgn:7029392"
    ],
    "tgn:id":1009054,
    "tgn:name":"Scatarie Island",
    "tgn:placetype":[
        "aat:300008791"
    ]
},
  "bbox": [],
  "geometry": {"coordinates":[-59.7167,46.0333],"type":"Point"}
}