<<<<<<< HEAD
{
  "id": 2402386,
  "type": "Feature",
  "properties": {
    "tgn:hierarchy":[
        "tgn:2402386",
        "tgn:1000001",
        "tgn:7012149",
        "tgn:2001454",
        "tgn:7007566",
        "tgn:7029392"
    ],
    "tgn:id":2402386,
    "tgn:name":"Horton Place",
    "tgn:placetype":[
        "aat:300008347"
    ]
},
  "bbox": [],
  "geometry": {"coordinates":[-106.2,35.1333],"type":"Point"}
}
=======
{"geometry":{"type":"Point","coordinates":[-106.200000,35.133300]},"type":"Feature","properties":{"hierarchy":["tgn:2402386","tgn:1000001","tgn:7012149","tgn:2001454","tgn:7007566","tgn:7029392"],"placetype":["aat:300008347"],"id":2402386,"name:xx":"Horton Place"}}
>>>>>>> 03f74aca74312dbeaf24d7e61306dd6a786dc3d0
