{
  "id": 7088900,
  "type": "Feature",
  "properties": {
    "tgn:hierarchy":[
        "tgn:7088900",
        "tgn:7003692",
        "tgn:1000003",
        "tgn:7000084",
        "tgn:7029392"
    ],
    "tgn:id":7088900,
    "tgn:name":"Weiherbach",
    "tgn:placetype":[
        "aat:300008699"
    ]
},
  "bbox": [],
  "geometry": {"coordinates":[9.116667,47.933333],"type":"Point"}
}