<<<<<<< HEAD
{
  "id": 2257304,
  "type": "Feature",
  "properties": {
    "tgn:hierarchy":[
        "tgn:2257304",
        "tgn:1000001",
        "tgn:1002210",
        "tgn:7012149",
        "tgn:7007706",
        "tgn:7029392"
    ],
    "tgn:id":2257304,
    "tgn:name":"Cornick Run",
    "tgn:placetype":[
        "aat:300008699"
    ]
},
  "bbox": [],
  "geometry": {"coordinates":[-83.85,38.7833],"type":"Point"}
}
=======
{"geometry":{"type":"Point","coordinates":[-83.850000,38.783300]},"type":"Feature","properties":{"hierarchy":["tgn:2257304","tgn:1000001","tgn:1002210","tgn:7012149","tgn:7007706","tgn:7029392"],"placetype":["aat:300008699"],"id":2257304,"name:xx":"Cornick Run"}}
>>>>>>> 03f74aca74312dbeaf24d7e61306dd6a786dc3d0
