{
  "id": 2257304,
  "type": "Feature",
  "properties": {
    "tgn:hierarchy":[
        "tgn:2257304",
        "tgn:1000001",
        "tgn:1002210",
        "tgn:7012149",
        "tgn:7007706",
        "tgn:7029392"
    ],
    "tgn:id":2257304,
    "tgn:name":"Cornick Run",
    "tgn:placetype":[
        "aat:300008699"
    ]
},
  "bbox": [],
  "geometry": {"coordinates":[-83.85,38.7833],"type":"Point"}
}