{
  "id": 2480383,
  "type": "Feature",
  "properties": {
    "tgn:hierarchy":[
        "tgn:2480383",
        "tgn:1000001",
        "tgn:2000327",
        "tgn:7012149",
        "tgn:7007248",
        "tgn:7029392"
    ],
    "tgn:id":2480383,
    "tgn:name":"Lake Spring Creek",
    "tgn:placetype":[
        "aat:300008706"
    ]
},
  "bbox": [],
  "geometry": {"coordinates":[-82.2333,33.65],"type":"Point"}
}