{
  "id": 2760732,
  "type": "Feature",
  "properties": {
    "tgn:hierarchy":[
        "tgn:2760732",
        "tgn:1000001",
        "tgn:7012149",
        "tgn:2002069",
        "tgn:7007826",
        "tgn:7029392"
    ],
    "tgn:id":2760732,
    "tgn:name":"West Goens Creek",
    "tgn:placetype":[
        "aat:300008706"
    ]
},
  "bbox": [],
  "geometry": {"coordinates":[-99.0667,31.2167],"type":"Point"}
}