<<<<<<< HEAD
{
  "id": 2760732,
  "type": "Feature",
  "properties": {
    "tgn:hierarchy":[
        "tgn:2760732",
        "tgn:1000001",
        "tgn:7012149",
        "tgn:2002069",
        "tgn:7007826",
        "tgn:7029392"
    ],
    "tgn:id":2760732,
    "tgn:name":"West Goens Creek",
    "tgn:placetype":[
        "aat:300008706"
    ]
},
  "bbox": [],
  "geometry": {"coordinates":[-99.0667,31.2167],"type":"Point"}
}
=======
{"geometry":{"type":"Point","coordinates":[-99.066700,31.216700]},"type":"Feature","properties":{"hierarchy":["tgn:2760732","tgn:1000001","tgn:7012149","tgn:2002069","tgn:7007826","tgn:7029392"],"placetype":["aat:300008706"],"id":2760732,"name:xx":"West Goens Creek"}}
>>>>>>> 03f74aca74312dbeaf24d7e61306dd6a786dc3d0
