{
  "id": 2164649,
  "type": "Feature",
  "properties": {
    "tgn:hierarchy":[
        "tgn:2164649",
        "tgn:1000001",
        "tgn:7006451",
        "tgn:2000092",
        "tgn:7012149",
        "tgn:7029392"
    ],
    "tgn:id":2164649,
    "tgn:name":"Bert Lee Tank",
    "tgn:placetype":[
        "aat:300006191"
    ]
},
  "bbox": [],
  "geometry": {"coordinates":[-111.55,34.9167],"type":"Point"}
}