{
  "id": 7314987,
  "type": "Feature",
  "properties": {
    "tgn:hierarchy":[
        "tgn:7314987",
        "tgn:1001702",
        "tgn:1000049",
        "tgn:1000002",
        "tgn:7029392"
    ],
    "tgn:id":7314987,
    "tgn:name":"Level, Bah\u00eda",
    "tgn:placetype":[
        "aat:300132317"
    ]
},
  "bbox": [],
  "geometry": {"coordinates":[-74.383333,-49.133333],"type":"Point"}
}