{
  "id": 2179209,
  "type": "Feature",
  "properties": {
    "tgn:hierarchy":[
        "tgn:2179209",
        "tgn:1000001",
        "tgn:1002284",
        "tgn:7012149",
        "tgn:7007568",
        "tgn:7029392"
    ],
    "tgn:id":2179209,
    "tgn:name":"Blake Brook",
    "tgn:placetype":[
        "aat:300008699"
    ]
},
  "bbox": [],
  "geometry": {"coordinates":[-73.8167,44.5167],"type":"Point"}
}