<<<<<<< HEAD
{
  "id": 7244580,
  "type": "Feature",
  "properties": {
    "tgn:hierarchy":[
        "tgn:7244580",
        "tgn:7003466",
        "tgn:1000003",
        "tgn:1000063",
        "tgn:4012014",
        "tgn:7029392"
    ],
    "tgn:id":7244580,
    "tgn:name":"La Verte Place",
    "tgn:placetype":[
        "aat:300008347"
    ]
},
  "bbox": [],
  "geometry": {"coordinates":[4.483333,49.95],"type":"Point"}
}
=======
{"geometry":{"type":"Point","coordinates":[4.483333,49.950000]},"type":"Feature","properties":{"hierarchy":["tgn:7244580","tgn:7003466","tgn:1000003","tgn:1000063","tgn:4012014","tgn:7029392"],"placetype":["aat:300008347"],"id":7244580,"name:xx":"La Verte Place"}}
>>>>>>> 03f74aca74312dbeaf24d7e61306dd6a786dc3d0
