<<<<<<< HEAD
{
  "id": 7375684,
  "type": "Feature",
  "properties": {
    "tgn:hierarchy":[
        "tgn:7375684",
        "tgn:7005583",
        "tgn:1000001",
        "tgn:7005560",
        "tgn:7029392"
    ],
    "tgn:id":7375684,
    "tgn:name":"Linares del R\u00edo",
    "tgn:placetype":[
        "aat:300008347"
    ]
},
  "bbox": [],
  "geometry": {"coordinates":[-104.5,25.083333],"type":"Point"}
}
=======
{"geometry":{"type":"Point","coordinates":[-104.500000,25.083333]},"type":"Feature","properties":{"hierarchy":["tgn:7375684","tgn:7005583","tgn:1000001","tgn:7005560","tgn:7029392"],"placetype":["aat:300008347"],"id":7375684,"name:xx":"Linares del R\u00edo"}}
>>>>>>> 03f74aca74312dbeaf24d7e61306dd6a786dc3d0
