{
  "id": 7560914,
  "type": "Feature",
  "properties": {
    "tgn:hierarchy":[
        "tgn:7560914",
        "tgn:1000004",
        "tgn:7000198",
        "tgn:7016722",
        "tgn:7029392"
    ],
    "tgn:id":7560914,
    "tgn:name:en":"Nagla Banj\u0101ran",
    "tgn:placetype":[
        "aat:300008347"
    ]
},
  "bbox": [],
  "geometry": {"coordinates":[79.448836,27.186119],"type":"Point"}
}