{
  "id": 7451502,
  "type": "Feature",
  "properties": {
    "tgn:hierarchy":[
        "tgn:7451502",
        "tgn:7002445",
        "tgn:1000003",
        "tgn:7008166",
        "tgn:7008591",
        "tgn:7029392"
    ],
    "tgn:id":7451502,
    "tgn:name:en":"Fylingdales",
    "tgn:placetype":[
        "aat:300008347"
    ]
},
  "bbox": [],
  "geometry": {"coordinates":[-0.533333,54.416667],"type":"Point"}
}