{
  "id": 2530785,
  "type": "Feature",
  "properties": {
    "tgn:hierarchy":[
        "tgn:2530785",
        "tgn:1000001",
        "tgn:7012149",
        "tgn:7007919",
        "tgn:7029392"
    ],
    "tgn:id":2530785,
    "tgn:name":"Muddy Run",
    "tgn:placetype":[
        "aat:300008699"
    ]
},
  "bbox": [],
  "geometry": {"coordinates":[-76.75,38.0167],"type":"Point"}
}