{
  "id": 2284152,
  "type": "Feature",
  "properties": {
    "tgn:hierarchy":[
        "tgn:2284152",
        "tgn:1000001",
        "tgn:7006451",
        "tgn:2000092",
        "tgn:7012149",
        "tgn:7029392"
    ],
    "tgn:id":2284152,
    "tgn:name":"Dent Tank",
    "tgn:placetype":[
        "aat:300006191"
    ]
},
  "bbox": [],
  "geometry": {"coordinates":[-111.85,35.3667],"type":"Point"}
}