{
  "id": 7176137,
  "type": "Feature",
  "properties": {
    "tgn:hierarchy":[
        "tgn:7176137",
        "tgn:1000003",
        "tgn:7003677",
        "tgn:7000084",
        "tgn:7029392"
    ],
    "tgn:id":7176137,
    "tgn:name":"Gro\u00dfenbach",
    "tgn:placetype":[
        "aat:300387200"
    ]
},
  "bbox": [],
  "geometry": {"coordinates":[8.25,50.916667],"type":"Point"}
}