{
  "id": 1010813,
  "type": "Feature",
  "properties": {
    "tgn:hierarchy":[
        "tgn:1010813",
        "tgn:7002681",
        "tgn:7001395",
        "tgn:1000003",
        "tgn:1000074",
        "tgn:7011052",
        "tgn:7029392"
    ],
    "tgn:id":1010813,
    "tgn:name":"K\u00f3khi, \u00c1kra",
    "tgn:placetype":[
        "aat:300008850"
    ]
},
  "bbox": [],
  "geometry": {"coordinates":[23.448779,37.875066],"type":"Point"}
}