{
  "id": 2304423,
  "type": "Feature",
  "properties": {
    "tgn:hierarchy":[
        "tgn:2304423",
        "tgn:1000001",
        "tgn:7012149",
        "tgn:2001456",
        "tgn:7007566",
        "tgn:7029392"
    ],
    "tgn:id":2304423,
    "tgn:name":"Earth Tank Number One",
    "tgn:placetype":[
        "aat:300006191"
    ]
},
  "bbox": [],
  "geometry": {"coordinates":[-107.25,34.05],"type":"Point"}
}