{
  "id": 2062526,
  "type": "Feature",
  "properties": {
    "tgn:hierarchy":[
        "tgn:2062526",
        "tgn:1000001",
        "tgn:2001368",
        "tgn:7012149",
        "tgn:7007525",
        "tgn:7029392"
    ],
    "tgn:id":2062526,
    "tgn:name":"Owasco",
    "tgn:placetype":[
        "aat:300387016"
    ]
},
  "bbox": [],
  "geometry": {"coordinates":[-103.5667,41.2333],"type":"Point"}
}