{
  "id": 2754735,
  "type": "Feature",
  "properties": {
    "tgn:hierarchy":[
        "tgn:2754735",
        "tgn:1000001",
        "tgn:7012149",
        "tgn:2001711",
        "tgn:7007708",
        "tgn:7029392"
    ],
    "tgn:id":2754735,
    "tgn:name":"Weasel Creek",
    "tgn:placetype":[
        "aat:300008706"
    ]
},
  "bbox": [],
  "geometry": {"coordinates":[-122.7667,42.1167],"type":"Point"}
}