{
  "id": 2099790,
  "type": "Feature",
  "properties": {
    "tgn:hierarchy":[
        "tgn:2099790",
        "tgn:1000001",
        "tgn:7012149",
        "tgn:2001853",
        "tgn:7007825",
        "tgn:7029392"
    ],
    "tgn:id":2099790,
    "tgn:name":"Johnsons Grove",
    "tgn:placetype":[
        "aat:300008347"
    ]
},
  "bbox": [],
  "geometry": {"coordinates":[-89.1833,35.7667],"type":"Point"}
}