{
  "id": 7587394,
  "type": "Feature",
  "properties": {
    "tgn:hierarchy":[
        "tgn:7587394",
        "tgn:1000004",
        "tgn:7000198",
        "tgn:1001977",
        "tgn:7029392"
    ],
    "tgn:id":7587394,
    "tgn:name:en":"Natshal",
    "tgn:placetype":[
        "aat:300008347"
    ]
},
  "bbox": [],
  "geometry": {"coordinates":[88.036848,22.201554],"type":"Point"}
}