{
  "id": 7397844,
  "type": "Feature",
  "properties": {
    "tgn:hierarchy":[
        "tgn:7397844",
        "tgn:1000001",
        "tgn:7005588",
        "tgn:7005560",
        "tgn:7029392"
    ],
    "tgn:id":7397844,
    "tgn:name":"Los Cardos, Volc\u00e1n",
    "tgn:placetype":[
        "aat:300132325"
    ]
},
  "bbox": [],
  "geometry": {"coordinates":[-99.261667,19.094167],"type":"Point"}
}