{
  "id": 7099051,
  "type": "Feature",
  "properties": {
    "tgn:hierarchy":[
        "tgn:7099051",
        "tgn:1000003",
        "tgn:7003688",
        "tgn:7000084",
        "tgn:7029392"
    ],
    "tgn:id":7099051,
    "tgn:name":"Spinkwang",
    "tgn:placetype":[
        "aat:300000206"
    ]
},
  "bbox": [],
  "geometry": {"coordinates":[9.116667,54.483333],"type":"Point"}
}