{
  "id": 7590060,
  "type": "Feature",
  "properties": {
    "tgn:hierarchy":[
        "tgn:7590060",
        "tgn:1000004",
        "tgn:7000198",
        "tgn:7016722",
        "tgn:7029392"
    ],
    "tgn:id":7590060,
    "tgn:name:en":"Pan\u0101hpur",
    "tgn:placetype":[
        "aat:300008347"
    ]
},
  "bbox": [],
  "geometry": {"coordinates":[77.203026,29.776666],"type":"Point"}
}