{
  "id": 2336247,
  "type": "Feature",
  "properties": {
    "tgn:hierarchy":[
        "tgn:2336247",
        "tgn:1000001",
        "tgn:7012149",
        "tgn:2001447",
        "tgn:7007566",
        "tgn:7029392"
    ],
    "tgn:id":2336247,
    "tgn:name":"Foster Water Storage Tank",
    "tgn:placetype":[
        "aat:300006191"
    ]
},
  "bbox": [],
  "geometry": {"coordinates":[-105.0333,32.5167],"type":"Point"}
}