<<<<<<< HEAD
{
  "id": 2336247,
  "type": "Feature",
  "properties": {
    "tgn:hierarchy":[
        "tgn:2336247",
        "tgn:1000001",
        "tgn:7012149",
        "tgn:2001447",
        "tgn:7007566",
        "tgn:7029392"
    ],
    "tgn:id":2336247,
    "tgn:name":"Foster Water Storage Tank",
    "tgn:placetype":[
        "aat:300006191"
    ]
},
  "bbox": [],
  "geometry": {"coordinates":[-105.0333,32.5167],"type":"Point"}
}
=======
{"geometry":{"type":"Point","coordinates":[-105.033300,32.516700]},"type":"Feature","properties":{"hierarchy":["tgn:2336247","tgn:1000001","tgn:7012149","tgn:2001447","tgn:7007566","tgn:7029392"],"placetype":["aat:300006191"],"id":2336247,"name:xx":"Foster Water Storage Tank"}}
>>>>>>> 03f74aca74312dbeaf24d7e61306dd6a786dc3d0
