{
  "id": 7418050,
  "type": "Feature",
  "properties": {
    "tgn:hierarchy":[
        "tgn:7418050",
        "tgn:1000001",
        "tgn:7005591",
        "tgn:7005560",
        "tgn:7029392"
    ],
    "tgn:id":7418050,
    "tgn:name:es":"Las Palmas",
    "tgn:placetype":[
        "aat:300008347"
    ]
},
  "bbox": [],
  "geometry": {"coordinates":[-94.570278,16.444444],"type":"Point"}
}