{
  "id": 7388225,
  "type": "Feature",
  "properties": {
    "tgn:hierarchy":[
        "tgn:7388225",
        "tgn:1000001",
        "tgn:7005597",
        "tgn:7005560",
        "tgn:7029392"
    ],
    "tgn:id":7388225,
    "tgn:name":"Puerto \u00c9bano",
    "tgn:placetype":[
        "aat:300008347"
    ]
},
  "bbox": [],
  "geometry": {"coordinates":[-98.05,24.666667],"type":"Point"}
}