{
  "id": 2706545,
  "type": "Feature",
  "properties": {
    "tgn:hierarchy":[
        "tgn:2706545",
        "tgn:1000001",
        "tgn:7012149",
        "tgn:2000636",
        "tgn:7007253",
        "tgn:7029392"
    ],
    "tgn:id":2706545,
    "tgn:name":"Swan Lake",
    "tgn:placetype":[
        "aat:300008680"
    ]
},
  "bbox": [],
  "geometry": {"coordinates":[-94.85,42.8667],"type":"Point"}
}