{
  "id": 2398306,
  "type": "Feature",
  "properties": {
    "tgn:hierarchy":[
        "tgn:2398306",
        "tgn:1000001",
        "tgn:7012149",
        "tgn:7007157",
        "tgn:1002956",
        "tgn:7029392"
    ],
    "tgn:id":2398306,
    "tgn:name":"Hooper Ditch",
    "tgn:placetype":[
        "aat:300006075"
    ]
},
  "bbox": [],
  "geometry": {"coordinates":[-119.3833,36.1833],"type":"Point"}
}