<<<<<<< HEAD
{
  "id": 7370615,
  "type": "Feature",
  "properties": {
    "tgn:hierarchy":[
        "tgn:7370615",
        "tgn:1000001",
        "tgn:7005597",
        "tgn:7005560",
        "tgn:7029392"
    ],
    "tgn:id":7370615,
    "tgn:name":"Jerez, Cerro el",
    "tgn:placetype":[
        "aat:300008795"
    ]
},
  "bbox": [],
  "geometry": {"coordinates":[-98.066667,23.216667],"type":"Point"}
}
=======
{"geometry":{"type":"Point","coordinates":[-98.066667,23.216667]},"type":"Feature","properties":{"hierarchy":["tgn:7370615","tgn:1000001","tgn:7005597","tgn:7005560","tgn:7029392"],"placetype":["aat:300008795"],"id":7370615,"name:xx":"Jerez, Cerro el"}}
>>>>>>> 03f74aca74312dbeaf24d7e61306dd6a786dc3d0
