{
  "id": 7572357,
  "type": "Feature",
  "properties": {
    "tgn:hierarchy":[
        "tgn:7572357",
        "tgn:1000004",
        "tgn:7000198",
        "tgn:1001977",
        "tgn:7029392"
    ],
    "tgn:id":7572357,
    "tgn:name:en":"Gop\u0101lpur",
    "tgn:placetype":[
        "aat:300008347"
    ]
},
  "bbox": [],
  "geometry": {"coordinates":[87.725499,21.84875],"type":"Point"}
}