{
  "id": 2384835,
  "type": "Feature",
  "properties": {
    "tgn:hierarchy":[
        "tgn:2384835",
        "tgn:1000001",
        "tgn:7012149",
        "tgn:7007157",
        "tgn:1002956",
        "tgn:7029392"
    ],
    "tgn:id":2384835,
    "tgn:name":"Hells Hole",
    "tgn:placetype":[
        "aat:300386845"
    ]
},
  "bbox": [],
  "geometry": {"coordinates":[-118.3667,36.2333],"type":"Point"}
}