<<<<<<< HEAD
{
  "id": 7365400,
  "type": "Feature",
  "properties": {
    "tgn:hierarchy":[
        "tgn:7365400",
        "tgn:1000001",
        "tgn:7005594",
        "tgn:7005560",
        "tgn:7029392"
    ],
    "tgn:id":7365400,
    "tgn:name":"Encarnaci\u00f3n",
    "tgn:placetype":[
        "aat:300008347"
    ]
},
  "bbox": [],
  "geometry": {"coordinates":[-100.616667,23.533333],"type":"Point"}
}
=======
{"geometry":{"type":"Point","coordinates":[-100.616667,23.533333]},"type":"Feature","properties":{"hierarchy":["tgn:7365400","tgn:1000001","tgn:7005594","tgn:7005560","tgn:7029392"],"placetype":["aat:300008347"],"id":7365400,"name:xx":"Encarnaci\u00f3n"}}
>>>>>>> 03f74aca74312dbeaf24d7e61306dd6a786dc3d0
