<<<<<<< HEAD
{
  "id": 2154469,
  "type": "Feature",
  "properties": {
    "tgn:hierarchy":[
        "tgn:2154469",
        "tgn:1000001",
        "tgn:7012149",
        "tgn:2002377",
        "tgn:7007923",
        "tgn:7029392"
    ],
    "tgn:id":2154469,
    "tgn:name":"Bear Creek",
    "tgn:placetype":[
        "aat:300008706"
    ]
},
  "bbox": [],
  "geometry": {"coordinates":[-106.5833,42.4333],"type":"Point"}
}
=======
{"geometry":{"type":"Point","coordinates":[-106.583300,42.433300]},"type":"Feature","properties":{"hierarchy":["tgn:2154469","tgn:1000001","tgn:7012149","tgn:2002377","tgn:7007923","tgn:7029392"],"placetype":["aat:300008706"],"id":2154469,"name:xx":"Bear Creek"}}
>>>>>>> 03f74aca74312dbeaf24d7e61306dd6a786dc3d0
