{
  "id": 2745647,
  "type": "Feature",
  "properties": {
    "tgn:hierarchy":[
        "tgn:2745647",
        "tgn:1000001",
        "tgn:2002108",
        "tgn:7012149",
        "tgn:7007827",
        "tgn:7029392"
    ],
    "tgn:id":2745647,
    "tgn:name":"Virgin Spring Canyon",
    "tgn:placetype":[
        "aat:300008761"
    ]
},
  "bbox": [],
  "geometry": {"coordinates":[-110.75,39.0167],"type":"Point"}
}