{
  "id": 2535987,
  "type": "Feature",
  "properties": {
    "tgn:hierarchy":[
        "tgn:2535987",
        "tgn:1000001",
        "tgn:7012149",
        "tgn:2002379",
        "tgn:7007923",
        "tgn:7029392"
    ],
    "tgn:id":2535987,
    "tgn:name":"Native Lake",
    "tgn:placetype":[
        "aat:300008680"
    ]
},
  "bbox": [],
  "geometry": {"coordinates":[-109.6167,44.9833],"type":"Point"}
}