{
  "id": 7410544,
  "type": "Feature",
  "properties": {
    "tgn:hierarchy":[
        "tgn:7410544",
        "tgn:1000001",
        "tgn:7005592",
        "tgn:7005560",
        "tgn:7029392"
    ],
    "tgn:id":7410544,
    "tgn:name":"San Rafael",
    "tgn:placetype":[
        "aat:300008347"
    ]
},
  "bbox": [],
  "geometry": {"coordinates":[-97.733333,20.573611],"type":"Point"}
}