<<<<<<< HEAD
{
  "id": 7027985,
  "type": "Feature",
  "properties": {
    "tgn:hierarchy":[
        "tgn:7027985",
        "tgn:7002445",
        "tgn:1000003",
        "tgn:7008157",
        "tgn:7008591",
        "tgn:7029392"
    ],
    "tgn:id":7027985,
    "tgn:name:en":"Mareham on the Hill",
    "tgn:placetype":[
        "aat:300008347",
        "aat:300008372"
    ]
},
  "bbox": [],
  "geometry": {"coordinates":[-0.083333,53.133333],"type":"Point"}
}
=======
{"geometry":{"type":"Point","coordinates":[-0.083333,53.133333]},"type":"Feature","properties":{"hierarchy":["tgn:7027985","tgn:7002445","tgn:1000003","tgn:7008157","tgn:7008591","tgn:7029392"],"placetype":["aat:300008347","aat:300008372"],"name:en":"Mareham on the Hill","id":7027985}}
>>>>>>> 03f74aca74312dbeaf24d7e61306dd6a786dc3d0
