{
  "id": 7537266,
  "type": "Feature",
  "properties": {
    "tgn:hierarchy":[
        "tgn:7537266",
        "tgn:7001242",
        "tgn:7016833",
        "tgn:1001335",
        "tgn:7029392"
    ],
    "tgn:id":7537266,
    "tgn:name:en":"Naq'ah, B\u0101b an",
    "tgn:placetype":[
        "aat:300266559"
    ]
},
  "bbox": [],
  "geometry": {"coordinates":[30.669722,31.403333],"type":"Point"}
}