<<<<<<< HEAD
{
  "id": 2335458,
  "type": "Feature",
  "properties": {
    "tgn:hierarchy":[
        "tgn:2335458",
        "tgn:1000001",
        "tgn:7012149",
        "tgn:2000933",
        "tgn:7007515",
        "tgn:7029392"
    ],
    "tgn:id":2335458,
    "tgn:name":"Fort Point",
    "tgn:placetype":[
        "aat:300008850"
    ]
},
  "bbox": [],
  "geometry": {"coordinates":[-70.6333,43.1167],"type":"Point"}
}
=======
{"geometry":{"type":"Point","coordinates":[-70.633300,43.116700]},"type":"Feature","properties":{"hierarchy":["tgn:2335458","tgn:1000001","tgn:7012149","tgn:2000933","tgn:7007515","tgn:7029392"],"placetype":["aat:300008850"],"id":2335458,"name:xx":"Fort Point"}}
>>>>>>> 03f74aca74312dbeaf24d7e61306dd6a786dc3d0
