{
  "id": 7313958,
  "type": "Feature",
  "properties": {
    "tgn:hierarchy":[
        "tgn:7313958",
        "tgn:1001637",
        "tgn:1000049",
        "tgn:1000002",
        "tgn:7029392"
    ],
    "tgn:id":7313958,
    "tgn:name":"Los Manzanos, Quebrada",
    "tgn:placetype":[
        "aat:300008699"
    ]
},
  "bbox": [],
  "geometry": {"coordinates":[-71.916667,-37.666667],"type":"Point"}
}