{
  "id": 1068762,
  "type": "Feature",
  "properties": {
    "tgn:hierarchy":[
        "tgn:1068762",
        "tgn:1000004",
        "tgn:7001838",
        "tgn:1000111",
        "tgn:7029392"
    ],
    "tgn:id":1068762,
    "tgn:name":"Honghuaerji",
    "tgn:placetype":[
        "aat:300008347"
    ]
},
  "bbox": [],
  "geometry": {"coordinates":[120.0167,48.25],"type":"Point"}
}