{
  "id": 2343790,
  "type": "Feature",
  "properties": {
    "tgn:hierarchy":[
        "tgn:2343790",
        "tgn:1000001",
        "tgn:7006451",
        "tgn:7012149",
        "tgn:2000097",
        "tgn:7029392"
    ],
    "tgn:id":2343790,
    "tgn:name":"Galleto Tank",
    "tgn:placetype":[
        "aat:300006191"
    ]
},
  "bbox": [],
  "geometry": {"coordinates":[-113.0667,33.2833],"type":"Point"}
}