{
  "id": 7402240,
  "type": "Feature",
  "properties": {
    "tgn:hierarchy":[
        "tgn:7402240",
        "tgn:1000001",
        "tgn:7005599",
        "tgn:7005560",
        "tgn:7029392"
    ],
    "tgn:id":7402240,
    "tgn:name":"El Copite",
    "tgn:placetype":[
        "aat:300008347"
    ]
},
  "bbox": [],
  "geometry": {"coordinates":[-96.366667,19.575],"type":"Point"}
}