{
  "id": 2772669,
  "type": "Feature",
  "properties": {
    "tgn:hierarchy":[
        "tgn:2772669",
        "tgn:1000001",
        "tgn:2001702",
        "tgn:7012149",
        "tgn:7007708",
        "tgn:7029392"
    ],
    "tgn:id":2772669,
    "tgn:name":"Williams Creek",
    "tgn:placetype":[
        "aat:300008706"
    ]
},
  "bbox": [],
  "geometry": {"coordinates":[-124.35,42.9667],"type":"Point"}
}