<<<<<<< HEAD
{
  "id": 2252112,
  "type": "Feature",
  "properties": {
    "tgn:hierarchy":[
        "tgn:2252112",
        "tgn:1000001",
        "tgn:7006451",
        "tgn:2000093",
        "tgn:7012149",
        "tgn:7029392"
    ],
    "tgn:id":2252112,
    "tgn:name":"Cone Butte Tank",
    "tgn:placetype":[
        "aat:300006191"
    ]
},
  "bbox": [],
  "geometry": {"coordinates":[-110.1833,33.7667],"type":"Point"}
}
=======
{"geometry":{"type":"Point","coordinates":[-110.183300,33.766700]},"type":"Feature","properties":{"hierarchy":["tgn:2252112","tgn:1000001","tgn:7006451","tgn:2000093","tgn:7012149","tgn:7029392"],"placetype":["aat:300006191"],"id":2252112,"name:xx":"Cone Butte Tank"}}
>>>>>>> 03f74aca74312dbeaf24d7e61306dd6a786dc3d0
