{
  "id": 2252112,
  "type": "Feature",
  "properties": {
    "tgn:hierarchy":[
        "tgn:2252112",
        "tgn:1000001",
        "tgn:7006451",
        "tgn:2000093",
        "tgn:7012149",
        "tgn:7029392"
    ],
    "tgn:id":2252112,
    "tgn:name":"Cone Butte Tank",
    "tgn:placetype":[
        "aat:300006191"
    ]
},
  "bbox": [],
  "geometry": {"coordinates":[-110.1833,33.7667],"type":"Point"}
}