{
  "id": 7303844,
  "type": "Feature",
  "properties": {
    "tgn:hierarchy":[
        "tgn:7303844",
        "tgn:7008912",
        "tgn:7030216",
        "tgn:1000003",
        "tgn:1000095",
        "tgn:7029392"
    ],
    "tgn:id":7303844,
    "tgn:name":"Obeix",
    "tgn:placetype":[
        "aat:300008347"
    ]
},
  "bbox": [],
  "geometry": {"coordinates":[0.949598,42.394315],"type":"Point"}
}