<<<<<<< HEAD
{
  "id": 2769425,
  "type": "Feature",
  "properties": {
    "tgn:hierarchy":[
        "tgn:2769425",
        "tgn:1000001",
        "tgn:7012149",
        "tgn:1002296",
        "tgn:7007157",
        "tgn:7029392"
    ],
    "tgn:id":2769425,
    "tgn:name":"Wide Awake Mine",
    "tgn:placetype":[
        "aat:300000390"
    ]
},
  "bbox": [],
  "geometry": {"coordinates":[-122.4167,39.0167],"type":"Point"}
}
=======
{"geometry":{"type":"Point","coordinates":[-122.416700,39.016700]},"type":"Feature","properties":{"hierarchy":["tgn:2769425","tgn:1000001","tgn:7012149","tgn:1002296","tgn:7007157","tgn:7029392"],"placetype":["aat:300000390"],"id":2769425,"name:xx":"Wide Awake Mine"}}
>>>>>>> 03f74aca74312dbeaf24d7e61306dd6a786dc3d0
