{
  "id": 2446036,
  "type": "Feature",
  "properties": {
    "tgn:hierarchy":[
        "tgn:2446036",
        "tgn:1000001",
        "tgn:1002210",
        "tgn:7012149",
        "tgn:7007706",
        "tgn:7029392"
    ],
    "tgn:id":2446036,
    "tgn:name":"Levanna Branch",
    "tgn:placetype":[
        "aat:300008699"
    ]
},
  "bbox": [],
  "geometry": {"coordinates":[-83.8667,38.7667],"type":"Point"}
}