{
  "id": 1104399,
  "type": "Feature",
  "properties": {
    "tgn:hierarchy":[
        "tgn:1104399",
        "tgn:1000004",
        "tgn:7011500",
        "tgn:7002435",
        "tgn:7029392"
    ],
    "tgn:id":1104399,
    "tgn:name":"Davydov, Gora",
    "tgn:placetype":[
        "aat:300008795"
    ]
},
  "bbox": [],
  "geometry": {"coordinates":[107.4167,52.55],"type":"Point"}
}