{
  "id": 2608105,
  "type": "Feature",
  "properties": {
    "tgn:hierarchy":[
        "tgn:2608105",
        "tgn:1000001",
        "tgn:2000261",
        "tgn:7012149",
        "tgn:7007240",
        "tgn:7029392"
    ],
    "tgn:id":2608105,
    "tgn:name":"Rattlesnake Bend",
    "tgn:placetype":[
        "aat:300008347"
    ]
},
  "bbox": [],
  "geometry": {"coordinates":[-81.8167,30.0833],"type":"Point"}
}