{
  "id": 2220292,
  "type": "Feature",
  "properties": {
    "tgn:hierarchy":[
        "tgn:2220292",
        "tgn:1000001",
        "tgn:7012149",
        "tgn:7007157",
        "tgn:1003046",
        "tgn:7029392"
    ],
    "tgn:id":2220292,
    "tgn:name":"Capay Hills",
    "tgn:placetype":[
        "aat:300386831"
    ]
},
  "bbox": [],
  "geometry": {"coordinates":[-122.1167,38.75],"type":"Point"}
}