{
  "id": 2411768,
  "type": "Feature",
  "properties": {
    "tgn:hierarchy":[
        "tgn:2411768",
        "tgn:1000001",
        "tgn:7012149",
        "tgn:1002540",
        "tgn:7007520",
        "tgn:7029392"
    ],
    "tgn:id":2411768,
    "tgn:name":"Indian Mill Creek",
    "tgn:placetype":[
        "aat:300008706"
    ]
},
  "bbox": [],
  "geometry": {"coordinates":[-85.75,43.0833],"type":"Point"}
}