{
  "id": 7317988,
  "type": "Feature",
  "properties": {
    "tgn:hierarchy":[
        "tgn:7317988",
        "tgn:7002464",
        "tgn:1000049",
        "tgn:1000002",
        "tgn:7029392"
    ],
    "tgn:id":7317988,
    "tgn:name":"Chusquina, Quebrada",
    "tgn:placetype":[
        "aat:300266554",
        "aat:300008699"
    ]
},
  "bbox": [],
  "geometry": {"coordinates":[-68.666667,-20.816667],"type":"Point"}
}