{
  "id": 7537433,
  "type": "Feature",
  "properties": {
    "tgn:hierarchy":[
        "tgn:7537433",
        "tgn:7001242",
        "tgn:7001311",
        "tgn:7016833",
        "tgn:7029392"
    ],
    "tgn:id":7537433,
    "tgn:name:en":"Mars\u00e1 Shaqrah",
    "tgn:placetype":[
        "aat:300386968"
    ]
},
  "bbox": [],
  "geometry": {"coordinates":[34.796082,25.244765],"type":"Point"}
}