{
  "id": 2033605,
  "type": "Feature",
  "properties": {
    "tgn:hierarchy":[
        "tgn:2033605",
        "tgn:1000001",
        "tgn:1002216",
        "tgn:7012149",
        "tgn:7007706",
        "tgn:7029392"
    ],
    "tgn:id":2033605,
    "tgn:name":"Scipio",
    "tgn:placetype":[
        "aat:300008347"
    ]
},
  "bbox": [],
  "geometry": {"coordinates":[-84.8167,39.3833],"type":"Point"}
}