{
  "id": 7132854,
  "type": "Feature",
  "properties": {
    "tgn:hierarchy":[
        "tgn:7132854",
        "tgn:7003669",
        "tgn:1000003",
        "tgn:7000084",
        "tgn:7029392"
    ],
    "tgn:id":7132854,
    "tgn:name":"M\u00f6derhof",
    "tgn:placetype":[
        "aat:300008347"
    ]
},
  "bbox": [],
  "geometry": {"coordinates":[10.583333,48.883333],"type":"Point"}
}