<<<<<<< HEAD
{
  "id": 2257361,
  "type": "Feature",
  "properties": {
    "tgn:hierarchy":[
        "tgn:2257361",
        "tgn:1000001",
        "tgn:7012149",
        "tgn:2001898",
        "tgn:7007825",
        "tgn:7029392"
    ],
    "tgn:id":2257361,
    "tgn:name":"Corntassel Branch",
    "tgn:placetype":[
        "aat:300008699"
    ]
},
  "bbox": [],
  "geometry": {"coordinates":[-84.2833,35.5167],"type":"Point"}
}
=======
{"geometry":{"type":"Point","coordinates":[-84.283300,35.516700]},"type":"Feature","properties":{"hierarchy":["tgn:2257361","tgn:1000001","tgn:7012149","tgn:2001898","tgn:7007825","tgn:7029392"],"placetype":["aat:300008699"],"id":2257361,"name:xx":"Corntassel Branch"}}
>>>>>>> 03f74aca74312dbeaf24d7e61306dd6a786dc3d0
