{
  "id": 2721809,
  "type": "Feature",
  "properties": {
    "tgn:hierarchy":[
        "tgn:2721809",
        "tgn:1000001",
        "tgn:2001939",
        "tgn:7012149",
        "tgn:7007826",
        "tgn:7029392"
    ],
    "tgn:id":2721809,
    "tgn:name":"Timber Creek",
    "tgn:placetype":[
        "aat:300008706"
    ]
},
  "bbox": [],
  "geometry": {"coordinates":[-99.0833,33.6833],"type":"Point"}
}