<<<<<<< HEAD
{
  "id": 2769285,
  "type": "Feature",
  "properties": {
    "tgn:hierarchy":[
        "tgn:2769285",
        "tgn:1000001",
        "tgn:2000199",
        "tgn:7012149",
        "tgn:7007158",
        "tgn:7029392"
    ],
    "tgn:id":2769285,
    "tgn:name":"Wicker Spring",
    "tgn:placetype":[
        "aat:300008697"
    ]
},
  "bbox": [],
  "geometry": {"coordinates":[-106.0,38.4833],"type":"Point"}
}
=======
{"geometry":{"type":"Point","coordinates":[-106.000000,38.483300]},"type":"Feature","properties":{"hierarchy":["tgn:2769285","tgn:1000001","tgn:2000199","tgn:7012149","tgn:7007158","tgn:7029392"],"placetype":["aat:300008697"],"id":2769285,"name:xx":"Wicker Spring"}}
>>>>>>> 03f74aca74312dbeaf24d7e61306dd6a786dc3d0
