{
  "id": 2284443,
  "type": "Feature",
  "properties": {
    "tgn:hierarchy":[
        "tgn:2284443",
        "tgn:1000001",
        "tgn:2000460",
        "tgn:7012149",
        "tgn:7007250",
        "tgn:7029392"
    ],
    "tgn:id":2284443,
    "tgn:name":"Derr Creek",
    "tgn:placetype":[
        "aat:300008706"
    ]
},
  "bbox": [],
  "geometry": {"coordinates":[-116.2167,48.0667],"type":"Point"}
}