{
  "id": 7416571,
  "type": "Feature",
  "properties": {
    "tgn:hierarchy":[
        "tgn:7416571",
        "tgn:1000001",
        "tgn:7005596",
        "tgn:7005560",
        "tgn:7029392"
    ],
    "tgn:id":7416571,
    "tgn:name:es":"Benito Ju\u00e1rez Primera Secci\u00f3n",
    "tgn:placetype":[
        "aat:300008347"
    ]
},
  "bbox": [],
  "geometry": {"coordinates":[-93.175,18.170833],"type":"Point"}
}