<<<<<<< HEAD
{
  "id": 7176629,
  "type": "Feature",
  "properties": {
    "tgn:hierarchy":[
        "tgn:7176629",
        "tgn:1000003",
        "tgn:7003677",
        "tgn:7000084",
        "tgn:7029392"
    ],
    "tgn:id":7176629,
    "tgn:name":"Grunewald",
    "tgn:placetype":[
        "aat:300000206"
    ]
},
  "bbox": [],
  "geometry": {"coordinates":[6.383333,51.583333],"type":"Point"}
}
=======
{"geometry":{"type":"Point","coordinates":[6.383333,51.583333]},"type":"Feature","properties":{"hierarchy":["tgn:7176629","tgn:1000003","tgn:7003677","tgn:7000084","tgn:7029392"],"placetype":["aat:300000206"],"id":7176629,"name:xx":"Grunewald"}}
>>>>>>> 03f74aca74312dbeaf24d7e61306dd6a786dc3d0
