{
  "id": 2305721,
  "type": "Feature",
  "properties": {
    "tgn:hierarchy":[
        "tgn:2305721",
        "tgn:1000001",
        "tgn:2001013",
        "tgn:7012149",
        "tgn:7007521",
        "tgn:7029392"
    ],
    "tgn:id":2305721,
    "tgn:name":"East Cranberry Lake",
    "tgn:placetype":[
        "aat:300008680"
    ]
},
  "bbox": [],
  "geometry": {"coordinates":[-95.4833,47.15],"type":"Point"}
}