{
  "id": 7562014,
  "type": "Feature",
  "properties": {
    "tgn:hierarchy":[
        "tgn:7562014",
        "tgn:1000004",
        "tgn:7000198",
        "tgn:7016722",
        "tgn:7029392"
    ],
    "tgn:id":7562014,
    "tgn:name:en":"Sun\u0101li Purwa",
    "tgn:placetype":[
        "aat:300008347"
    ]
},
  "bbox": [],
  "geometry": {"coordinates":[79.9907,27.0931],"type":"Point"}
}