{
  "id": 1073357,
  "type": "Feature",
  "properties": {
    "tgn:hierarchy":[
        "tgn:1073357",
        "tgn:1000004",
        "tgn:7002079",
        "tgn:1000111",
        "tgn:7029392"
    ],
    "tgn:id":1073357,
    "tgn:name":"Yanglousi",
    "tgn:placetype":[
        "aat:300008347"
    ]
},
  "bbox": [],
  "geometry": {"coordinates":[113.6333,29.5167],"type":"Point"}
}