{
  "id": 2582976,
  "type": "Feature",
  "properties": {
    "tgn:hierarchy":[
        "tgn:2582976",
        "tgn:1000001",
        "tgn:7012149",
        "tgn:2001686",
        "tgn:7007707",
        "tgn:7029392"
    ],
    "tgn:id":2582976,
    "tgn:name":"Pine Knot Crossing",
    "tgn:placetype":[
        "aat:300008347"
    ]
},
  "bbox": [],
  "geometry": {"coordinates":[-95.1333,34.2333],"type":"Point"}
}