{
  "id": 7335154,
  "type": "Feature",
  "properties": {
    "tgn:hierarchy":[
        "tgn:7335154",
        "tgn:7002835",
        "tgn:7001158",
        "tgn:1000003",
        "tgn:1000095",
        "tgn:7029392"
    ],
    "tgn:id":7335154,
    "tgn:name":"Froya, Rivera de",
    "tgn:placetype":[
        "aat:300008699"
    ]
},
  "bbox": [],
  "geometry": {"coordinates":[-6.85,41.033333],"type":"Point"}
}