<<<<<<< HEAD
{
  "id": 2402484,
  "type": "Feature",
  "properties": {
    "tgn:hierarchy":[
        "tgn:2402484",
        "tgn:1000001",
        "tgn:7012149",
        "tgn:2001720",
        "tgn:7007708",
        "tgn:7029392"
    ],
    "tgn:id":2402484,
    "tgn:name":"Hoskins Creek",
    "tgn:placetype":[
        "aat:300008706"
    ]
},
  "bbox": [],
  "geometry": {"coordinates":[-118.1667,45.5],"type":"Point"}
}
=======
{"geometry":{"type":"Point","coordinates":[-118.166700,45.500000]},"type":"Feature","properties":{"hierarchy":["tgn:2402484","tgn:1000001","tgn:7012149","tgn:2001720","tgn:7007708","tgn:7029392"],"placetype":["aat:300008706"],"id":2402484,"name:xx":"Hoskins Creek"}}
>>>>>>> 03f74aca74312dbeaf24d7e61306dd6a786dc3d0
