{
  "id": 2217760,
  "type": "Feature",
  "properties": {
    "tgn:hierarchy":[
        "tgn:2217760",
        "tgn:7013272",
        "tgn:1000001",
        "tgn:7012149",
        "tgn:7007710",
        "tgn:7029392"
    ],
    "tgn:id":2217760,
    "tgn:name":"Campbell Run",
    "tgn:placetype":[
        "aat:300008699"
    ]
},
  "bbox": [],
  "geometry": {"coordinates":[-79.8667,40.55],"type":"Point"}
}