<<<<<<< HEAD
{
  "id": 7484593,
  "type": "Feature",
  "properties": {
    "tgn:hierarchy":[
        "tgn:7484593",
        "tgn:1000004",
        "tgn:7001014",
        "tgn:1000141",
        "tgn:7029392"
    ],
    "tgn:id":7484593,
    "tgn:name":"Yunlin Jishu Xueyuan",
    "tgn:placetype":[
        "aat:300006610"
    ]
},
  "bbox": [],
  "geometry": {"coordinates":[120.534167,23.694722],"type":"Point"}
}
=======
{"geometry":{"type":"Point","coordinates":[120.534167,23.694722]},"type":"Feature","properties":{"hierarchy":["tgn:7484593","tgn:1000004","tgn:7001014","tgn:1000141","tgn:7029392"],"placetype":["aat:300006610"],"id":7484593,"name:xx":"Yunlin Jishu Xueyuan"}}
>>>>>>> 03f74aca74312dbeaf24d7e61306dd6a786dc3d0
