{
  "id": 2217387,
  "type": "Feature",
  "properties": {
    "tgn:hierarchy":[
        "tgn:2217387",
        "tgn:1000001",
        "tgn:1002479",
        "tgn:7012149",
        "tgn:7007240",
        "tgn:7029392"
    ],
    "tgn:id":2217387,
    "tgn:name":"Campbell Branch",
    "tgn:placetype":[
        "aat:300008699"
    ]
},
  "bbox": [],
  "geometry": {"coordinates":[-82.1833,28.05],"type":"Point"}
}