{
  "id": 2520411,
  "type": "Feature",
  "properties": {
    "tgn:hierarchy":[
        "tgn:2520411",
        "tgn:1002309",
        "tgn:1000001",
        "tgn:7012149",
        "tgn:7007565",
        "tgn:7029392"
    ],
    "tgn:id":2520411,
    "tgn:name":"Money Island",
    "tgn:placetype":[
        "aat:300008850"
    ]
},
  "bbox": [],
  "geometry": {"coordinates":[-75.2333,39.2667],"type":"Point"}
}