{
  "id": 7418610,
  "type": "Feature",
  "properties": {
    "tgn:hierarchy":[
        "tgn:7418610",
        "tgn:1001835",
        "tgn:1000001",
        "tgn:7005560",
        "tgn:7029392"
    ],
    "tgn:id":7418610,
    "tgn:name":"El Milagro",
    "tgn:placetype":[
        "aat:300008347"
    ]
},
  "bbox": [],
  "geometry": {"coordinates":[-116.542222,32.088611],"type":"Point"}
}