{
  "id": 7057016,
  "type": "Feature",
  "properties": {
    "tgn:hierarchy":[
        "tgn:7057016",
        "tgn:7002995",
        "tgn:1000003",
        "tgn:7002997",
        "tgn:1000080",
        "tgn:7029392"
    ],
    "tgn:id":7057016,
    "tgn:name":"Baruchella",
    "tgn:placetype":[
        "aat:300008347"
    ]
},
  "bbox": [],
  "geometry": {"coordinates":[11.45,45.066667],"type":"Point"}
}