{
  "id": 7225567,
  "type": "Feature",
  "properties": {
    "tgn:hierarchy":[
        "tgn:7225567",
        "tgn:7002680",
        "tgn:7001395",
        "tgn:1000003",
        "tgn:1000074",
        "tgn:7029392"
    ],
    "tgn:id":7225567,
    "tgn:name":"Periv\u00f3la",
    "tgn:placetype":[
        "aat:300008347"
    ]
},
  "bbox": [],
  "geometry": {"coordinates":[21.766667,38.216667],"type":"Point"}
}