{
  "id": 1075316,
  "type": "Feature",
  "properties": {
    "tgn:hierarchy":[
        "tgn:1075316",
        "tgn:1000004",
        "tgn:7000198",
        "tgn:7016883",
        "tgn:7029392"
    ],
    "tgn:id":1075316,
    "tgn:name:en":"Garhshankar",
    "tgn:placetype":[
        "aat:300008347"
    ]
},
  "bbox": [],
  "geometry": {"coordinates":[76.141486,31.215371],"type":"Point"}
}