{
  "id": 2506921,
  "type": "Feature",
  "properties": {
    "tgn:hierarchy":[
        "tgn:2506921",
        "tgn:1000001",
        "tgn:7006451",
        "tgn:2000091",
        "tgn:7012149",
        "tgn:7029392"
    ],
    "tgn:id":2506921,
    "tgn:name":"Mesquite Tank",
    "tgn:placetype":[
        "aat:300006191"
    ]
},
  "bbox": [],
  "geometry": {"coordinates":[-109.8167,31.6333],"type":"Point"}
}