{
  "id": 2532796,
  "type": "Feature",
  "properties": {
    "tgn:hierarchy":[
        "tgn:2532796",
        "tgn:1000001",
        "tgn:7012149",
        "tgn:2000888",
        "tgn:7007256",
        "tgn:7029392"
    ],
    "tgn:id":2532796,
    "tgn:name":"Murphys Lake",
    "tgn:placetype":[
        "aat:300008680"
    ]
},
  "bbox": [],
  "geometry": {"coordinates":[-93.05,31.7333],"type":"Point"}
}