{
  "id": 7223474,
  "type": "Feature",
  "properties": {
    "tgn:hierarchy":[
        "tgn:7223474",
        "tgn:7011167",
        "tgn:7001338",
        "tgn:1000003",
        "tgn:1000074",
        "tgn:7029392"
    ],
    "tgn:id":7223474,
    "tgn:name":"Ortholithi\u00e1s, \u00d3rmos",
    "tgn:placetype":[
        "aat:300132316"
    ]
},
  "bbox": [],
  "geometry": {"coordinates":[20.366667,38.266667],"type":"Point"}
}