{
  "id": 1010302,
  "type": "Feature",
  "properties": {
    "tgn:hierarchy":[
        "tgn:1010302",
        "tgn:1000001",
        "tgn:1002902",
        "tgn:7012149",
        "tgn:7007516",
        "tgn:7029392"
    ],
    "tgn:id":1010302,
    "tgn:name":"Smith Island",
    "tgn:placetype":[
        "aat:300008791"
    ]
},
  "bbox": [],
  "geometry": {"coordinates":[-76.0167,37.9667],"type":"Point"}
}