{
  "id": 2296248,
  "type": "Feature",
  "properties": {
    "tgn:hierarchy":[
        "tgn:2296248",
        "tgn:1000001",
        "tgn:7012149",
        "tgn:2001856",
        "tgn:7007825",
        "tgn:7029392"
    ],
    "tgn:id":2296248,
    "tgn:name":"Dry Branch",
    "tgn:placetype":[
        "aat:300008699"
    ]
},
  "bbox": [],
  "geometry": {"coordinates":[-88.2167,35.4667],"type":"Point"}
}