{
  "id": 2678677,
  "type": "Feature",
  "properties": {
    "tgn:hierarchy":[
        "tgn:2678677",
        "tgn:1000001",
        "tgn:7012149",
        "tgn:2000472",
        "tgn:7007250",
        "tgn:7029392"
    ],
    "tgn:id":2678677,
    "tgn:name":"South Fork Dry Creek",
    "tgn:placetype":[
        "aat:300008706"
    ]
},
  "bbox": [],
  "geometry": {"coordinates":[-111.6167,42.2167],"type":"Point"}
}