{
  "id": 2602598,
  "type": "Feature",
  "properties": {
    "tgn:hierarchy":[
        "tgn:2602598",
        "tgn:1000001",
        "tgn:7006451",
        "tgn:7012149",
        "tgn:2000098",
        "tgn:7029392"
    ],
    "tgn:id":2602598,
    "tgn:name":"Quail Draw Reservoir",
    "tgn:placetype":[
        "aat:300006191"
    ]
},
  "bbox": [],
  "geometry": {"coordinates":[-113.55,36.8333],"type":"Point"}
}