{
  "id": 2037743,
  "type": "Feature",
  "properties": {
    "tgn:hierarchy":[
        "tgn:2037743",
        "tgn:1000001",
        "tgn:2000773",
        "tgn:7012149",
        "tgn:7007255",
        "tgn:7029392"
    ],
    "tgn:id":2037743,
    "tgn:name":"Bewleyville",
    "tgn:placetype":[
        "aat:300008347"
    ]
},
  "bbox": [],
  "geometry": {"coordinates":[-86.2333,37.8333],"type":"Point"}
}