{
  "id": 7582660,
  "type": "Feature",
  "properties": {
    "tgn:hierarchy":[
        "tgn:7582660",
        "tgn:1000004",
        "tgn:7000198",
        "tgn:7016788",
        "tgn:7029392"
    ],
    "tgn:id":7582660,
    "tgn:name:en":"R\u0101mrakh ki Dh\u0101ni",
    "tgn:placetype":[
        "aat:300008347"
    ]
},
  "bbox": [],
  "geometry": {"coordinates":[75.698121,28.266406],"type":"Point"}
}