{
  "id": 2628554,
  "type": "Feature",
  "properties": {
    "tgn:hierarchy":[
        "tgn:2628554",
        "tgn:1000001",
        "tgn:7012149",
        "tgn:2000226",
        "tgn:7007158",
        "tgn:7029392"
    ],
    "tgn:id":2628554,
    "tgn:name":"Roosevelt National Forest",
    "tgn:placetype":[
        "aat:300008863"
    ]
},
  "bbox": [],
  "geometry": {"coordinates":[-105.55,40.6833],"type":"Point"}
}