{
  "id": 1057466,
  "type": "Feature",
  "properties": {
    "tgn:hierarchy":[
        "tgn:1057466",
        "tgn:1000004",
        "tgn:7002435",
        "tgn:7011524",
        "tgn:7029392"
    ],
    "tgn:id":1057466,
    "tgn:name":"Ni\u017eneje Ku\u010dukovo",
    "tgn:placetype":[
        "aat:300008347"
    ]
},
  "bbox": [],
  "geometry": {"coordinates":[52.95,56.2167],"type":"Point"}
}