{
  "id": 2540524,
  "type": "Feature",
  "properties": {
    "tgn:hierarchy":[
        "tgn:2540524",
        "tgn:1000001",
        "tgn:7012149",
        "tgn:1002612",
        "tgn:7007710",
        "tgn:7029392"
    ],
    "tgn:id":2540524,
    "tgn:name":"Newton",
    "tgn:placetype":[
        "aat:300008347"
    ]
},
  "bbox": [],
  "geometry": {"coordinates":[-75.8833,41.2167],"type":"Point"}
}