{
  "id": 2582772,
  "type": "Feature",
  "properties": {
    "tgn:hierarchy":[
        "tgn:2582772",
        "tgn:1000001",
        "tgn:7016172",
        "tgn:2000110",
        "tgn:7012149",
        "tgn:7029392"
    ],
    "tgn:id":2582772,
    "tgn:name":"Pine Island",
    "tgn:placetype":[
        "aat:300008791"
    ]
},
  "bbox": [],
  "geometry": {"coordinates":[-92.1833,33.2333],"type":"Point"}
}