{
  "id": 1118449,
  "type": "Feature",
  "properties": {
    "tgn:hierarchy":[
        "tgn:1118449",
        "tgn:7005685",
        "tgn:1000001",
        "tgn:7005805",
        "tgn:7029392"
    ],
    "tgn:id":1118449,
    "tgn:name":"Tramping Lake",
    "tgn:placetype":[
        "aat:300008680"
    ]
},
  "bbox": [],
  "geometry": {"coordinates":[-108.95,52.1667],"type":"Point"}
}