{
  "id": 7419238,
  "type": "Feature",
  "properties": {
    "tgn:hierarchy":[
        "tgn:7419238",
        "tgn:7005579",
        "tgn:1000001",
        "tgn:7005560",
        "tgn:7029392"
    ],
    "tgn:id":7419238,
    "tgn:name":"Pe\u00f1a Blanca, Arroyo",
    "tgn:placetype":[
        "aat:300266554",
        "aat:300008699"
    ]
},
  "bbox": [],
  "geometry": {"coordinates":[-102.625,21.945833],"type":"Point"}
}