{
  "id": 7286860,
  "type": "Feature",
  "properties": {
    "tgn:hierarchy":[
        "tgn:7286860",
        "tgn:1001657",
        "tgn:1000049",
        "tgn:1000002",
        "tgn:7029392"
    ],
    "tgn:id":7286860,
    "tgn:name":"Guanaquero, Cerro",
    "tgn:placetype":[
        "aat:300008795"
    ]
},
  "bbox": [],
  "geometry": {"coordinates":[-71.446111,-30.221389],"type":"Point"}
}