{
  "id": 7582646,
  "type": "Feature",
  "properties": {
    "tgn:hierarchy":[
        "tgn:7582646",
        "tgn:1000004",
        "tgn:7000198",
        "tgn:7016788",
        "tgn:7029392"
    ],
    "tgn:id":7582646,
    "tgn:name:en":"D\u0101lmi\u0101n Ki Dh\u0101ni",
    "tgn:placetype":[
        "aat:300008347"
    ]
},
  "bbox": [],
  "geometry": {"coordinates":[75.661819,28.243138],"type":"Point"}
}