{
  "id": 7244159,
  "type": "Feature",
  "properties": {
    "tgn:hierarchy":[
        "tgn:7244159",
        "tgn:7003457",
        "tgn:1000003",
        "tgn:1000063",
        "tgn:7018236",
        "tgn:7029392"
    ],
    "tgn:id":7244159,
    "tgn:name":"Kapel Polder",
    "tgn:placetype":[
        "aat:300006163"
    ]
},
  "bbox": [],
  "geometry": {"coordinates":[3.733333,51.25],"type":"Point"}
}