{
  "id": 2145017,
  "type": "Feature",
  "properties": {
    "tgn:hierarchy":[
        "tgn:2145017",
        "tgn:1000001",
        "tgn:2002102",
        "tgn:7012149",
        "tgn:7007827",
        "tgn:7029392"
    ],
    "tgn:id":2145017,
    "tgn:name":"Bald Knoll",
    "tgn:placetype":[
        "aat:300008798"
    ]
},
  "bbox": [],
  "geometry": {"coordinates":[-113.2667,41.85],"type":"Point"}
}