<<<<<<< HEAD
{
  "id": 2256943,
  "type": "Feature",
  "properties": {
    "tgn:hierarchy":[
        "tgn:2256943",
        "tgn:1000001",
        "tgn:7012149",
        "tgn:1002676",
        "tgn:7007240",
        "tgn:7029392"
    ],
    "tgn:id":2256943,
    "tgn:name":"Cormorant Rookeries",
    "tgn:placetype":[
        "aat:300008791"
    ]
},
  "bbox": [],
  "geometry": {"coordinates":[-80.4,25.2167],"type":"Point"}
}
=======
{"geometry":{"type":"Point","coordinates":[-80.400000,25.216700]},"type":"Feature","properties":{"hierarchy":["tgn:2256943","tgn:1000001","tgn:7012149","tgn:1002676","tgn:7007240","tgn:7029392"],"placetype":["aat:300008791"],"id":2256943,"name:xx":"Cormorant Rookeries"}}
>>>>>>> 03f74aca74312dbeaf24d7e61306dd6a786dc3d0
