{
  "id": 7493143,
  "type": "Feature",
  "properties": {
    "tgn:hierarchy":[
        "tgn:7493143",
        "tgn:1000004",
        "tgn:7491221",
        "tgn:1000141",
        "tgn:7029392"
    ],
    "tgn:id":7493143,
    "tgn:name":"Shenglin Shan",
    "tgn:placetype":[
        "aat:300008795"
    ]
},
  "bbox": [],
  "geometry": {"coordinates":[120.894167,22.430556],"type":"Point"}
}