{
  "id": 1106176,
  "type": "Feature",
  "properties": {
    "tgn:hierarchy":[
        "tgn:1106176",
        "tgn:1009227",
        "tgn:7001866",
        "tgn:1000226",
        "tgn:1000006",
        "tgn:7029392"
    ],
    "tgn:id":1106176,
    "tgn:name:en":"Red Hill",
    "tgn:placetype":[
        "aat:300008795"
    ]
},
  "bbox": [],
  "geometry": {"coordinates":[171.633333,-43.316667],"type":"Point"}
}