{
  "id": 7277692,
  "type": "Feature",
  "properties": {
    "tgn:hierarchy":[
        "tgn:7277692",
        "tgn:1001699",
        "tgn:1000049",
        "tgn:1000002",
        "tgn:7029392"
    ],
    "tgn:id":7277692,
    "tgn:name":"Paso Imeley",
    "tgn:placetype":[
        "aat:300387026"
    ]
},
  "bbox": [],
  "geometry": {"coordinates":[-73.103889,-42.51],"type":"Point"}
}