{
  "id": 7161097,
  "type": "Feature",
  "properties": {
    "tgn:hierarchy":[
        "tgn:7161097",
        "tgn:7003692",
        "tgn:1000003",
        "tgn:7000084",
        "tgn:7029392"
    ],
    "tgn:id":7161097,
    "tgn:name":"Hochstra\u00dfe",
    "tgn:placetype":[
        "aat:300000206"
    ]
},
  "bbox": [],
  "geometry": {"coordinates":[8.283333,48.15],"type":"Point"}
}