<<<<<<< HEAD
{
  "id": 2330089,
  "type": "Feature",
  "properties": {
    "tgn:hierarchy":[
        "tgn:2330089",
        "tgn:1000001",
        "tgn:1002219",
        "tgn:7012149",
        "tgn:7007157",
        "tgn:7029392"
    ],
    "tgn:id":2330089,
    "tgn:name":"Flagpole Point",
    "tgn:placetype":[
        "aat:300008798"
    ]
},
  "bbox": [],
  "geometry": {"coordinates":[-120.1,38.45],"type":"Point"}
}
=======
{"geometry":{"type":"Point","coordinates":[-120.100000,38.450000]},"type":"Feature","properties":{"hierarchy":["tgn:2330089","tgn:1000001","tgn:1002219","tgn:7012149","tgn:7007157","tgn:7029392"],"placetype":["aat:300008798"],"id":2330089,"name:xx":"Flagpole Point"}}
>>>>>>> 03f74aca74312dbeaf24d7e61306dd6a786dc3d0
