{
  "id": 2194747,
  "type": "Feature",
  "properties": {
    "tgn:hierarchy":[
        "tgn:2194747",
        "tgn:1000001",
        "tgn:7012149",
        "tgn:2002164",
        "tgn:7007919",
        "tgn:7029392"
    ],
    "tgn:id":2194747,
    "tgn:name":"Brier Ridge",
    "tgn:placetype":[
        "aat:300266640"
    ]
},
  "bbox": [],
  "geometry": {"coordinates":[-81.55,36.6167],"type":"Point"}
}