{
  "id": 7174166,
  "type": "Feature",
  "properties": {
    "tgn:hierarchy":[
        "tgn:7174166",
        "tgn:7003669",
        "tgn:1000003",
        "tgn:7000084",
        "tgn:7029392"
    ],
    "tgn:id":7174166,
    "tgn:name":"Gro\u00dfaich",
    "tgn:placetype":[
        "aat:300008347"
    ]
},
  "bbox": [],
  "geometry": {"coordinates":[12.35,48.833333],"type":"Point"}
}