{
  "id": 2422940,
  "type": "Feature",
  "properties": {
    "tgn:hierarchy":[
        "tgn:2422940",
        "tgn:1000001",
        "tgn:7012149",
        "tgn:2000214",
        "tgn:7007158",
        "tgn:7029392"
    ],
    "tgn:id":2422940,
    "tgn:name":"Joe Hill",
    "tgn:placetype":[
        "aat:300008798"
    ]
},
  "bbox": [],
  "geometry": {"coordinates":[-107.5333,39.6833],"type":"Point"}
}