{
  "id": 2056048,
  "type": "Feature",
  "properties": {
    "tgn:hierarchy":[
        "tgn:2056048",
        "tgn:1000001",
        "tgn:7012149",
        "tgn:2001110",
        "tgn:7007522",
        "tgn:7029392"
    ],
    "tgn:id":2056048,
    "tgn:name":"Brownsville",
    "tgn:placetype":[
        "aat:300008347"
    ]
},
  "bbox": [],
  "geometry": {"coordinates":[-90.4333,32.4333],"type":"Point"}
}