{
  "id": 7008121,
  "type": "Feature",
  "properties": {
    "tgn:hierarchy":[
        "tgn:7008121",
        "tgn:7002870",
        "tgn:1000003",
        "tgn:1000070",
        "tgn:7029392"
    ],
    "tgn:id":7008121,
    "tgn:name":"Guebwiller",
    "tgn:placetype":[
        "aat:300008347"
    ]
},
  "bbox": [],
  "geometry": {"coordinates":[7.2167,47.9167],"type":"Point"}
}