{
  "id": 7054896,
  "type": "Feature",
  "properties": {
    "tgn:hierarchy":[
        "tgn:7054896",
        "tgn:1003429",
        "tgn:1000003",
        "tgn:7003240",
        "tgn:1000080",
        "tgn:7029392"
    ],
    "tgn:id":7054896,
    "tgn:name":"Molino Apolloni",
    "tgn:placetype":[
        "aat:300008347"
    ]
},
  "bbox": [],
  "geometry": {"coordinates":[13.083333,43.583333],"type":"Point"}
}