{
  "id": 2310835,
  "type": "Feature",
  "properties": {
    "tgn:hierarchy":[
        "tgn:2310835",
        "tgn:1000001",
        "tgn:7012149",
        "tgn:2000220",
        "tgn:7007158",
        "tgn:7029392"
    ],
    "tgn:id":2310835,
    "tgn:name":"Ed Van Draw",
    "tgn:placetype":[
        "aat:300008761"
    ]
},
  "bbox": [],
  "geometry": {"coordinates":[-106.4667,40.4667],"type":"Point"}
}