{
  "id": 1137733,
  "type": "Feature",
  "properties": {
    "tgn:hierarchy":[
        "tgn:1137733",
        "tgn:1000004",
        "tgn:1003407",
        "tgn:7018214",
        "tgn:7002435",
        "tgn:7029392"
    ],
    "tgn:id":1137733,
    "tgn:name":"Krasnoarmejskoje",
    "tgn:placetype":[
        "aat:300008347"
    ]
},
  "bbox": [],
  "geometry": {"coordinates":[50.0333,52.7333],"type":"Point"}
}