{
  "id": 7281257,
  "type": "Feature",
  "properties": {
    "tgn:hierarchy":[
        "tgn:7281257",
        "tgn:1001702",
        "tgn:1000049",
        "tgn:1000002",
        "tgn:7029392"
    ],
    "tgn:id":7281257,
    "tgn:name":"Ser\u00f3n, Punta",
    "tgn:placetype":[
        "aat:300386846"
    ]
},
  "bbox": [],
  "geometry": {"coordinates":[-72.633333,-53.366667],"type":"Point"}
}