{
  "id": 2251350,
  "type": "Feature",
  "properties": {
    "tgn:hierarchy":[
        "tgn:2251350",
        "tgn:1000001",
        "tgn:7012149",
        "tgn:2001708",
        "tgn:7007708",
        "tgn:7029392"
    ],
    "tgn:id":2251350,
    "tgn:name":"Comer",
    "tgn:placetype":[
        "aat:300008347"
    ]
},
  "bbox": [],
  "geometry": {"coordinates":[-118.6833,44.5333],"type":"Point"}
}