{
  "id": 2618250,
  "type": "Feature",
  "properties": {
    "tgn:hierarchy":[
        "tgn:2618250",
        "tgn:1000001",
        "tgn:7012149",
        "tgn:2001312",
        "tgn:7007524",
        "tgn:7029392"
    ],
    "tgn:id":2618250,
    "tgn:name":"Riggin Coulee",
    "tgn:placetype":[
        "aat:300008761"
    ]
},
  "bbox": [],
  "geometry": {"coordinates":[-106.9833,48.7833],"type":"Point"}
}