{
  "id": 2485980,
  "type": "Feature",
  "properties": {
    "tgn:hierarchy":[
        "tgn:2485980",
        "tgn:1000001",
        "tgn:2001435",
        "tgn:7012149",
        "tgn:7007566",
        "tgn:7029392"
    ],
    "tgn:id":2485980,
    "tgn:name":"Lead Camp Spring",
    "tgn:placetype":[
        "aat:300008697"
    ]
},
  "bbox": [],
  "geometry": {"coordinates":[-106.5667,32.7167],"type":"Point"}
}