{
  "id": 2298692,
  "type": "Feature",
  "properties": {
    "tgn:hierarchy":[
        "tgn:2298692",
        "tgn:1000001",
        "tgn:7012149",
        "tgn:2002128",
        "tgn:7007827",
        "tgn:7029392"
    ],
    "tgn:id":2298692,
    "tgn:name":"Dry Valley",
    "tgn:placetype":[
        "aat:300008761"
    ]
},
  "bbox": [],
  "geometry": {"coordinates":[-111.6833,38.3833],"type":"Point"}
}