{
  "id": 7083016,
  "type": "Feature",
  "properties": {
    "tgn:hierarchy":[
        "tgn:7083016",
        "tgn:1000003",
        "tgn:7003677",
        "tgn:7000084",
        "tgn:7029392"
    ],
    "tgn:id":7083016,
    "tgn:name":"Westerhaus",
    "tgn:placetype":[
        "aat:300000206"
    ]
},
  "bbox": [],
  "geometry": {"coordinates":[7.683333,51.866667],"type":"Point"}
}