{
  "id": 2378037,
  "type": "Feature",
  "properties": {
    "tgn:hierarchy":[
        "tgn:2378037",
        "tgn:1000001",
        "tgn:7012149",
        "tgn:2000725",
        "tgn:7007254",
        "tgn:7029392"
    ],
    "tgn:id":2378037,
    "tgn:name":"Harris Creek",
    "tgn:placetype":[
        "aat:300008706"
    ]
},
  "bbox": [],
  "geometry": {"coordinates":[-96.8833,39.85],"type":"Point"}
}