{
  "id": 2291288,
  "type": "Feature",
  "properties": {
    "tgn:hierarchy":[
        "tgn:2291288",
        "tgn:1000001",
        "tgn:7012149",
        "tgn:1002549",
        "tgn:7007919",
        "tgn:7029392"
    ],
    "tgn:id":2291288,
    "tgn:name":"Dogwood Fork",
    "tgn:placetype":[
        "aat:300008699"
    ]
},
  "bbox": [],
  "geometry": {"coordinates":[-77.0167,37.7833],"type":"Point"}
}