{
  "id": 2383890,
  "type": "Feature",
  "properties": {
    "tgn:hierarchy":[
        "tgn:2383890",
        "tgn:1000001",
        "tgn:7012149",
        "tgn:2000930",
        "tgn:7007515",
        "tgn:7029392"
    ],
    "tgn:id":2383890,
    "tgn:name":"Hedgehog Mountain",
    "tgn:placetype":[
        "aat:300008798"
    ]
},
  "bbox": [],
  "geometry": {"coordinates":[-70.1167,45.25],"type":"Point"}
}