{
  "id": 7394201,
  "type": "Feature",
  "properties": {
    "tgn:hierarchy":[
        "tgn:7394201",
        "tgn:1000001",
        "tgn:7005589",
        "tgn:7005560",
        "tgn:7029392"
    ],
    "tgn:id":7394201,
    "tgn:name":"San Blas",
    "tgn:placetype":[
        "aat:300008347"
    ]
},
  "bbox": [],
  "geometry": {"coordinates":[-99.833333,26.883333],"type":"Point"}
}