{
  "id": 2425472,
  "type": "Feature",
  "properties": {
    "tgn:hierarchy":[
        "tgn:2425472",
        "tgn:1000001",
        "tgn:2002323",
        "tgn:7012149",
        "tgn:7007922",
        "tgn:7029392"
    ],
    "tgn:id":2425472,
    "tgn:name":"Johnson Springs",
    "tgn:placetype":[
        "aat:300008697"
    ]
},
  "bbox": [],
  "geometry": {"coordinates":[-88.7667,45.5833],"type":"Point"}
}