<<<<<<< HEAD
{
  "id": 2333502,
  "type": "Feature",
  "properties": {
    "tgn:hierarchy":[
        "tgn:2333502",
        "tgn:1000001",
        "tgn:1002665",
        "tgn:7012149",
        "tgn:7007517",
        "tgn:7029392"
    ],
    "tgn:id":2333502,
    "tgn:name":"Folly Pond",
    "tgn:placetype":[
        "aat:300008680"
    ]
},
  "bbox": [],
  "geometry": {"coordinates":[-71.2833,42.4333],"type":"Point"}
}
=======
{"geometry":{"type":"Point","coordinates":[-71.283300,42.433300]},"type":"Feature","properties":{"hierarchy":["tgn:2333502","tgn:1000001","tgn:1002665","tgn:7012149","tgn:7007517","tgn:7029392"],"placetype":["aat:300008680"],"id":2333502,"name:xx":"Folly Pond"}}
>>>>>>> 03f74aca74312dbeaf24d7e61306dd6a786dc3d0
