{
  "id": 2379395,
  "type": "Feature",
  "properties": {
    "tgn:hierarchy":[
        "tgn:2379395",
        "tgn:1000001",
        "tgn:7012149",
        "tgn:7007825",
        "tgn:7029392"
    ],
    "tgn:id":2379395,
    "tgn:name":"Harvey Creek",
    "tgn:placetype":[
        "aat:300008706"
    ]
},
  "bbox": [],
  "geometry": {"coordinates":[-85.2333,35.35],"type":"Point"}
}