<<<<<<< HEAD
{
  "id": 2406861,
  "type": "Feature",
  "properties": {
    "tgn:hierarchy":[
        "tgn:2406861",
        "tgn:1000001",
        "tgn:2000268",
        "tgn:7012149",
        "tgn:7007240",
        "tgn:7029392"
    ],
    "tgn:id":2406861,
    "tgn:name":"Hunter Creek",
    "tgn:placetype":[
        "aat:300008706"
    ]
},
  "bbox": [],
  "geometry": {"coordinates":[-84.45,30.4833],"type":"Point"}
}
=======
{"geometry":{"type":"Point","coordinates":[-84.450000,30.483300]},"type":"Feature","properties":{"hierarchy":["tgn:2406861","tgn:1000001","tgn:2000268","tgn:7012149","tgn:7007240","tgn:7029392"],"placetype":["aat:300008706"],"id":2406861,"name:xx":"Hunter Creek"}}
>>>>>>> 03f74aca74312dbeaf24d7e61306dd6a786dc3d0
