{
  "id": 1035711,
  "type": "Feature",
  "properties": {
    "tgn:hierarchy":[
        "tgn:1035711",
        "tgn:1000003",
        "tgn:1000070",
        "tgn:7002897",
        "tgn:7029392"
    ],
    "tgn:id":1035711,
    "tgn:name":"Servoz",
    "tgn:placetype":[
        "aat:300008347"
    ]
},
  "bbox": [],
  "geometry": {"coordinates":[6.7667,45.9167],"type":"Point"}
}