{
  "id": 2174137,
  "type": "Feature",
  "properties": {
    "tgn:hierarchy":[
        "tgn:2174137",
        "tgn:1000001",
        "tgn:7012149",
        "tgn:2002267",
        "tgn:7013961",
        "tgn:7029392"
    ],
    "tgn:id":2174137,
    "tgn:name":"Birds Run",
    "tgn:placetype":[
        "aat:300008699"
    ]
},
  "bbox": [],
  "geometry": {"coordinates":[-80.2167,39.1833],"type":"Point"}
}