{
  "id": 1069556,
  "type": "Feature",
  "properties": {
    "tgn:hierarchy":[
        "tgn:1069556",
        "tgn:1000004",
        "tgn:7001838",
        "tgn:1000111",
        "tgn:7029392"
    ],
    "tgn:id":1069556,
    "tgn:name":"Kongjiawopeng",
    "tgn:placetype":[
        "aat:300008347"
    ]
},
  "bbox": [],
  "geometry": {"coordinates":[122.6833,43.9667],"type":"Point"}
}