{
  "id": 2129713,
  "type": "Feature",
  "properties": {
    "tgn:hierarchy":[
        "tgn:2129713",
        "tgn:1000001",
        "tgn:7012149",
        "tgn:2000481",
        "tgn:7007250",
        "tgn:7029392"
    ],
    "tgn:id":2129713,
    "tgn:name":"Allan Creek",
    "tgn:placetype":[
        "aat:300008706"
    ]
},
  "bbox": [],
  "geometry": {"coordinates":[-114.0333,45.5333],"type":"Point"}
}