{
  "id": 2777572,
  "type": "Feature",
  "properties": {
    "tgn:hierarchy":[
        "tgn:2777572",
        "tgn:1000001",
        "tgn:7012149",
        "tgn:7014318",
        "tgn:7007568",
        "tgn:7029392"
    ],
    "tgn:id":2777572,
    "tgn:name":"Winnie Hill",
    "tgn:placetype":[
        "aat:300008798"
    ]
},
  "bbox": [],
  "geometry": {"coordinates":[-75.0667,42.4833],"type":"Point"}
}