{
  "id": 2043948,
  "type": "Feature",
  "properties": {
    "tgn:hierarchy":[
        "tgn:2043948",
        "tgn:1000001",
        "tgn:7012149",
        "tgn:2000891",
        "tgn:7007256",
        "tgn:7029392"
    ],
    "tgn:id":2043948,
    "tgn:name":"Scarsdale",
    "tgn:placetype":[
        "aat:300008347"
    ]
},
  "bbox": [],
  "geometry": {"coordinates":[-89.9667,29.8333],"type":"Point"}
}