{
  "id": 2027394,
  "type": "Feature",
  "properties": {
    "tgn:hierarchy":[
        "tgn:2027394",
        "tgn:1000001",
        "tgn:7012149",
        "tgn:1002974",
        "tgn:7007251",
        "tgn:7029392"
    ],
    "tgn:id":2027394,
    "tgn:name":"Danville",
    "tgn:placetype":[
        "aat:300008347"
    ]
},
  "bbox": [],
  "geometry": {"coordinates":[-87.6167,40.1167],"type":"Point"}
}