<<<<<<< HEAD
{
  "id": 2404443,
  "type": "Feature",
  "properties": {
    "tgn:hierarchy":[
        "tgn:2404443",
        "tgn:1000001",
        "tgn:2002259",
        "tgn:7012149",
        "tgn:7013961",
        "tgn:7029392"
    ],
    "tgn:id":2404443,
    "tgn:name":"Hubbard Fork",
    "tgn:placetype":[
        "aat:300008699"
    ]
},
  "bbox": [],
  "geometry": {"coordinates":[-81.2,38.3],"type":"Point"}
}
=======
{"geometry":{"type":"Point","coordinates":[-81.200000,38.300000]},"type":"Feature","properties":{"hierarchy":["tgn:2404443","tgn:1000001","tgn:2002259","tgn:7012149","tgn:7013961","tgn:7029392"],"placetype":["aat:300008699"],"id":2404443,"name:xx":"Hubbard Fork"}}
>>>>>>> 03f74aca74312dbeaf24d7e61306dd6a786dc3d0
