<<<<<<< HEAD
{
  "id": 7369126,
  "type": "Feature",
  "properties": {
    "tgn:hierarchy":[
        "tgn:7369126",
        "tgn:7016644",
        "tgn:1000001",
        "tgn:7005560",
        "tgn:7029392"
    ],
    "tgn:id":7369126,
    "tgn:name":"Juluapan",
    "tgn:placetype":[
        "aat:300008347"
    ]
},
  "bbox": [],
  "geometry": {"coordinates":[-103.833333,19.3],"type":"Point"}
}
=======
{"geometry":{"type":"Point","coordinates":[-103.833333,19.300000]},"type":"Feature","properties":{"hierarchy":["tgn:7369126","tgn:7016644","tgn:1000001","tgn:7005560","tgn:7029392"],"placetype":["aat:300008347"],"id":7369126,"name:xx":"Juluapan"}}
>>>>>>> 03f74aca74312dbeaf24d7e61306dd6a786dc3d0
