{
  "id": 2464292,
  "type": "Feature",
  "properties": {
    "tgn:hierarchy":[
        "tgn:2464292",
        "tgn:1000001",
        "tgn:7016172",
        "tgn:7012149",
        "tgn:2000162",
        "tgn:7029392"
    ],
    "tgn:id":2464292,
    "tgn:name":"Lodge Lake",
    "tgn:placetype":[
        "aat:300008680"
    ]
},
  "bbox": [],
  "geometry": {"coordinates":[-93.0833,35.1333],"type":"Point"}
}