{
  "id": 1133327,
  "type": "Feature",
  "properties": {
    "tgn:hierarchy":[
        "tgn:1133327",
        "tgn:1001942",
        "tgn:1000047",
        "tgn:7002457",
        "tgn:1000002",
        "tgn:7029392"
    ],
    "tgn:id":1133327,
    "tgn:name":"Grande, Ribeir\u00e3o",
    "tgn:placetype":[
        "aat:300008706"
    ]
},
  "bbox": [],
  "geometry": {"coordinates":[-43.3167,-22.1833],"type":"Point"}
}