{
  "id": 2730105,
  "type": "Feature",
  "properties": {
    "tgn:hierarchy":[
        "tgn:2730105",
        "tgn:1000001",
        "tgn:7012149",
        "tgn:2001153",
        "tgn:7007522",
        "tgn:7029392"
    ],
    "tgn:id":2730105,
    "tgn:name":"Trout Lake",
    "tgn:placetype":[
        "aat:300008680"
    ]
},
  "bbox": [],
  "geometry": {"coordinates":[-90.1667,33.7333],"type":"Point"}
}