{
  "id": 2415735,
  "type": "Feature",
  "properties": {
    "tgn:hierarchy":[
        "tgn:2415735",
        "tgn:7006450",
        "tgn:1000001",
        "tgn:7012149",
        "tgn:2124005",
        "tgn:7029392"
    ],
    "tgn:id":2415735,
    "tgn:name":"Itimtikrak Creek",
    "tgn:placetype":[
        "aat:300008706"
    ]
},
  "bbox": [],
  "geometry": {"coordinates":[-159.3333,68.25],"type":"Point"}
}