{
  "id": 7564147,
  "type": "Feature",
  "properties": {
    "tgn:hierarchy":[
        "tgn:7564147",
        "tgn:1000004",
        "tgn:7000198",
        "tgn:7016722",
        "tgn:7029392"
    ],
    "tgn:id":7564147,
    "tgn:name:en":"Purwa L\u0101lsah\u0101l",
    "tgn:placetype":[
        "aat:300008347"
    ]
},
  "bbox": [],
  "geometry": {"coordinates":[79.651226,26.987573],"type":"Point"}
}