<<<<<<< HEAD
{
  "id": 2257648,
  "type": "Feature",
  "properties": {
    "tgn:hierarchy":[
        "tgn:2257648",
        "tgn:1000001",
        "tgn:2001583",
        "tgn:7012149",
        "tgn:7007705",
        "tgn:7029392"
    ],
    "tgn:id":2257648,
    "tgn:name":"Corral Creek",
    "tgn:placetype":[
        "aat:300008706"
    ]
},
  "bbox": [],
  "geometry": {"coordinates":[-103.7,47.55],"type":"Point"}
}
=======
{"geometry":{"type":"Point","coordinates":[-103.700000,47.550000]},"type":"Feature","properties":{"hierarchy":["tgn:2257648","tgn:1000001","tgn:2001583","tgn:7012149","tgn:7007705","tgn:7029392"],"placetype":["aat:300008706"],"id":2257648,"name:xx":"Corral Creek"}}
>>>>>>> 03f74aca74312dbeaf24d7e61306dd6a786dc3d0
