<<<<<<< HEAD
{
  "id": 7112962,
  "type": "Feature",
  "properties": {
    "tgn:hierarchy":[
        "tgn:7112962",
        "tgn:7003669",
        "tgn:1000003",
        "tgn:7000084",
        "tgn:7029392"
    ],
    "tgn:id":7112962,
    "tgn:name":"R\u00f6dlas",
    "tgn:placetype":[
        "aat:300008347"
    ]
},
  "bbox": [],
  "geometry": {"coordinates":[11.183333,49.633333],"type":"Point"}
}
=======
{"geometry":{"type":"Point","coordinates":[11.183333,49.633333]},"type":"Feature","properties":{"hierarchy":["tgn:7112962","tgn:7003669","tgn:1000003","tgn:7000084","tgn:7029392"],"placetype":["aat:300008347"],"id":7112962,"name:xx":"R\u00f6dlas"}}
>>>>>>> 03f74aca74312dbeaf24d7e61306dd6a786dc3d0
