<<<<<<< HEAD
{
  "id": 7111804,
  "type": "Feature",
  "properties": {
    "tgn:hierarchy":[
        "tgn:7111804",
        "tgn:7003669",
        "tgn:1000003",
        "tgn:7000084",
        "tgn:7029392"
    ],
    "tgn:id":7111804,
    "tgn:name":"R\u00f6hrenhof",
    "tgn:placetype":[
        "aat:300000206"
    ]
},
  "bbox": [],
  "geometry": {"coordinates":[12.433333,49.066667],"type":"Point"}
}
=======
{"geometry":{"type":"Point","coordinates":[12.433333,49.066667]},"type":"Feature","properties":{"hierarchy":["tgn:7111804","tgn:7003669","tgn:1000003","tgn:7000084","tgn:7029392"],"placetype":["aat:300000206"],"id":7111804,"name:xx":"R\u00f6hrenhof"}}
>>>>>>> 03f74aca74312dbeaf24d7e61306dd6a786dc3d0
