{
  "id": 7149171,
  "type": "Feature",
  "properties": {
    "tgn:hierarchy":[
        "tgn:7149171",
        "tgn:1000003",
        "tgn:7003685",
        "tgn:7000084",
        "tgn:7029392"
    ],
    "tgn:id":7149171,
    "tgn:name":"Kreischerhof",
    "tgn:placetype":[
        "aat:300000206"
    ]
},
  "bbox": [],
  "geometry": {"coordinates":[14.716667,50.95],"type":"Point"}
}