{
  "id": 7496392,
  "type": "Feature",
  "properties": {
    "tgn:hierarchy":[
        "tgn:7496392",
        "tgn:1000004",
        "tgn:7001009",
        "tgn:1000141",
        "tgn:7029392"
    ],
    "tgn:id":7496392,
    "tgn:name":"Huiguang Qiao",
    "tgn:placetype":[
        "aat:300007836"
    ]
},
  "bbox": [],
  "geometry": {"coordinates":[120.764391,24.276883],"type":"Point"}
}