{
  "id": 1067298,
  "type": "Feature",
  "properties": {
    "tgn:hierarchy":[
        "tgn:1067298",
        "tgn:1000004",
        "tgn:7001319",
        "tgn:1000111",
        "tgn:7029392"
    ],
    "tgn:id":1067298,
    "tgn:name":"Gyamotang",
    "tgn:placetype":[
        "aat:300008347"
    ]
},
  "bbox": [],
  "geometry": {"coordinates":[95.4333,31.5333],"type":"Point"}
}