<<<<<<< HEAD
{
  "id": 7112226,
  "type": "Feature",
  "properties": {
    "tgn:hierarchy":[
        "tgn:7112226",
        "tgn:1000003",
        "tgn:7003689",
        "tgn:7000084",
        "tgn:7029392"
    ],
    "tgn:id":7112226,
    "tgn:name":"Ro\u00df-Bach",
    "tgn:placetype":[
        "aat:300008699"
    ]
},
  "bbox": [],
  "geometry": {"coordinates":[10.65,50.5],"type":"Point"}
}
=======
{"geometry":{"type":"Point","coordinates":[10.650000,50.500000]},"type":"Feature","properties":{"hierarchy":["tgn:7112226","tgn:1000003","tgn:7003689","tgn:7000084","tgn:7029392"],"placetype":["aat:300008699"],"id":7112226,"name:xx":"Ro\u00df-Bach"}}
>>>>>>> 03f74aca74312dbeaf24d7e61306dd6a786dc3d0
