<<<<<<< HEAD
{
  "id": 7357213,
  "type": "Feature",
  "properties": {
    "tgn:hierarchy":[
        "tgn:7357213",
        "tgn:1000001",
        "tgn:7005591",
        "tgn:7005560",
        "tgn:7029392"
    ],
    "tgn:id":7357213,
    "tgn:name":"Chisme, R\u00edo del",
    "tgn:placetype":[
        "aat:300008699"
    ]
},
  "bbox": [],
  "geometry": {"coordinates":[-95.766667,17.266667],"type":"Point"}
}
=======
{"geometry":{"type":"Point","coordinates":[-95.766667,17.266667]},"type":"Feature","properties":{"hierarchy":["tgn:7357213","tgn:1000001","tgn:7005591","tgn:7005560","tgn:7029392"],"placetype":["aat:300008699"],"id":7357213,"name:xx":"Chisme, R\u00edo del"}}
>>>>>>> 03f74aca74312dbeaf24d7e61306dd6a786dc3d0
