{
  "id": 2565569,
  "type": "Feature",
  "properties": {
    "tgn:hierarchy":[
        "tgn:2565569",
        "tgn:7013272",
        "tgn:1000001",
        "tgn:7012149",
        "tgn:7007710",
        "tgn:7029392"
    ],
    "tgn:id":2565569,
    "tgn:name":"Painters Run",
    "tgn:placetype":[
        "aat:300008699"
    ]
},
  "bbox": [],
  "geometry": {"coordinates":[-80.0333,40.35],"type":"Point"}
}