{
  "id": 2729472,
  "type": "Feature",
  "properties": {
    "tgn:hierarchy":[
        "tgn:2729472",
        "tgn:1000001",
        "tgn:2001424",
        "tgn:7012149",
        "tgn:7007564",
        "tgn:7029392"
    ],
    "tgn:id":2729472,
    "tgn:name":"Tripyramid, Mount",
    "tgn:placetype":[
        "aat:300008798"
    ]
},
  "bbox": [],
  "geometry": {"coordinates":[-71.4333,43.9667],"type":"Point"}
}