{
  "id": 7164330,
  "type": "Feature",
  "properties": {
    "tgn:hierarchy":[
        "tgn:7164330",
        "tgn:7003692",
        "tgn:1000003",
        "tgn:7000084",
        "tgn:7029392"
    ],
    "tgn:id":7164330,
    "tgn:name":"Hungersberg",
    "tgn:placetype":[
        "aat:300000206"
    ]
},
  "bbox": [],
  "geometry": {"coordinates":[9.55,47.716667],"type":"Point"}
}