{
  "id": 7276535,
  "type": "Feature",
  "properties": {
    "tgn:hierarchy":[
        "tgn:7276535",
        "tgn:7016598",
        "tgn:1000049",
        "tgn:1000002",
        "tgn:7029392"
    ],
    "tgn:id":7276535,
    "tgn:name":"Blanco, Islote",
    "tgn:placetype":[
        "aat:300011692"
    ]
},
  "bbox": [],
  "geometry": {"coordinates":[-8.847222,42.583333],"type":"Point"}
}