{
  "id": 2075287,
  "type": "Feature",
  "properties": {
    "tgn:hierarchy":[
        "tgn:2075287",
        "tgn:1000001",
        "tgn:7012149",
        "tgn:2001555",
        "tgn:7007709",
        "tgn:7029392"
    ],
    "tgn:id":2075287,
    "tgn:name":"Jonesville",
    "tgn:placetype":[
        "aat:300008347"
    ]
},
  "bbox": [],
  "geometry": {"coordinates":[-80.8333,36.2333],"type":"Point"}
}