{
  "id": 2422116,
  "type": "Feature",
  "properties": {
    "tgn:hierarchy":[
        "tgn:2422116",
        "tgn:7006450",
        "tgn:1000001",
        "tgn:2124053",
        "tgn:7012149",
        "tgn:7029392"
    ],
    "tgn:id":2422116,
    "tgn:name":"Jim Lake",
    "tgn:placetype":[
        "aat:300008680"
    ]
},
  "bbox": [],
  "geometry": {"coordinates":[-148.9167,61.55],"type":"Point"}
}