{
  "id": 2181861,
  "type": "Feature",
  "properties": {
    "tgn:hierarchy":[
        "tgn:2181861",
        "tgn:1000001",
        "tgn:7012149",
        "tgn:7007157",
        "tgn:2000184",
        "tgn:7029392"
    ],
    "tgn:id":2181861,
    "tgn:name":"Blue Lake",
    "tgn:placetype":[
        "aat:300006191"
    ]
},
  "bbox": [],
  "geometry": {"coordinates":[-120.2833,41.1333],"type":"Point"}
}