{
  "id": 2450650,
  "type": "Feature",
  "properties": {
    "tgn:hierarchy":[
        "tgn:2450650",
        "tgn:1000001",
        "tgn:1002840",
        "tgn:7012149",
        "tgn:7007828",
        "tgn:7029392"
    ],
    "tgn:id":2450650,
    "tgn:name":"Lion Hill",
    "tgn:placetype":[
        "aat:300008798"
    ]
},
  "bbox": [],
  "geometry": {"coordinates":[-73.0833,43.8333],"type":"Point"}
}