{
  "id": 7449560,
  "type": "Feature",
  "properties": {
    "tgn:hierarchy":[
        "tgn:7449560",
        "tgn:7002445",
        "tgn:1000003",
        "tgn:7012034",
        "tgn:7008591",
        "tgn:7029392"
    ],
    "tgn:id":7449560,
    "tgn:name:en":"Hampton",
    "tgn:placetype":[
        "aat:300008347"
    ]
},
  "bbox": [],
  "geometry": {"coordinates":[-2.383333,52.466667],"type":"Point"}
}