{
  "id": 7256154,
  "type": "Feature",
  "properties": {
    "tgn:hierarchy":[
        "tgn:7256154",
        "tgn:7003616",
        "tgn:1000003",
        "tgn:7016845",
        "tgn:7029392"
    ],
    "tgn:id":7256154,
    "tgn:name:nl":"Berlikumerpolder",
    "tgn:placetype":[
        "aat:300006163"
    ]
},
  "bbox": [],
  "geometry": {"coordinates":[5.65,53.233333],"type":"Point"}
}