{
  "id": 2022077,
  "type": "Feature",
  "properties": {
    "tgn:hierarchy":[
        "tgn:2022077",
        "tgn:1000001",
        "tgn:2000326",
        "tgn:7012149",
        "tgn:7007248",
        "tgn:7029392"
    ],
    "tgn:id":2022077,
    "tgn:name":"Autreyville",
    "tgn:placetype":[
        "aat:300008347"
    ]
},
  "bbox": [],
  "geometry": {"coordinates":[-83.75,31.05],"type":"Point"}
}