{
  "id": 2544277,
  "type": "Feature",
  "properties": {
    "tgn:hierarchy":[
        "tgn:2544277",
        "tgn:1000001",
        "tgn:7012149",
        "tgn:7007710",
        "tgn:7029392"
    ],
    "tgn:id":2544277,
    "tgn:name":"North Branch Plum Creek",
    "tgn:placetype":[
        "aat:300008706"
    ]
},
  "bbox": [],
  "geometry": {"coordinates":[-79.1667,40.8167],"type":"Point"}
}