<<<<<<< HEAD
{
  "id": 7369420,
  "type": "Feature",
  "properties": {
    "tgn:hierarchy":[
        "tgn:7369420",
        "tgn:1000001",
        "tgn:7005595",
        "tgn:7005560",
        "tgn:7029392"
    ],
    "tgn:id":7369420,
    "tgn:name":"Huaco",
    "tgn:placetype":[
        "aat:300008347"
    ]
},
  "bbox": [],
  "geometry": {"coordinates":[-107.516667,25.15],"type":"Point"}
}
=======
{"geometry":{"type":"Point","coordinates":[-107.516667,25.150000]},"type":"Feature","properties":{"hierarchy":["tgn:7369420","tgn:1000001","tgn:7005595","tgn:7005560","tgn:7029392"],"placetype":["aat:300008347"],"id":7369420,"name:xx":"Huaco"}}
>>>>>>> 03f74aca74312dbeaf24d7e61306dd6a786dc3d0
