<<<<<<< HEAD
{
  "id": 7351657,
  "type": "Feature",
  "properties": {
    "tgn:hierarchy":[
        "tgn:7351657",
        "tgn:7005581",
        "tgn:1000001",
        "tgn:7005560",
        "tgn:7029392"
    ],
    "tgn:id":7351657,
    "tgn:name":"Rancho Baquirichic",
    "tgn:placetype":[
        "aat:300000241"
    ]
},
  "bbox": [],
  "geometry": {"coordinates":[-108.3,27.233333],"type":"Point"}
}
=======
{"geometry":{"type":"Point","coordinates":[-108.300000,27.233333]},"type":"Feature","properties":{"hierarchy":["tgn:7351657","tgn:7005581","tgn:1000001","tgn:7005560","tgn:7029392"],"placetype":["aat:300000241"],"id":7351657,"name:xx":"Rancho Baquirichic"}}
>>>>>>> 03f74aca74312dbeaf24d7e61306dd6a786dc3d0
