{
  "id": 2136711,
  "type": "Feature",
  "properties": {
    "tgn:hierarchy":[
        "tgn:2136711",
        "tgn:1000001",
        "tgn:1002249",
        "tgn:7012149",
        "tgn:7007710",
        "tgn:7029392"
    ],
    "tgn:id":2136711,
    "tgn:name":"Ardery Hollow",
    "tgn:placetype":[
        "aat:300008761"
    ]
},
  "bbox": [],
  "geometry": {"coordinates":[-78.0333,40.8333],"type":"Point"}
}