{
  "id": 2016248,
  "type": "Feature",
  "properties": {
    "tgn:hierarchy":[
        "tgn:2016248",
        "tgn:1000001",
        "tgn:7012149",
        "tgn:7007158",
        "tgn:2000242",
        "tgn:7029392"
    ],
    "tgn:id":2016248,
    "tgn:name":"Rye",
    "tgn:placetype":[
        "aat:300008347"
    ]
},
  "bbox": [],
  "geometry": {"coordinates":[-104.9167,37.9167],"type":"Point"}
}