{
  "id": 7499047,
  "type": "Feature",
  "properties": {
    "tgn:hierarchy":[
        "tgn:7499047",
        "tgn:1000004",
        "tgn:7491221",
        "tgn:1000141",
        "tgn:7029392"
    ],
    "tgn:id":7499047,
    "tgn:name":"Jiana Cun",
    "tgn:placetype":[
        "aat:300387173"
    ]
},
  "bbox": [],
  "geometry": {"coordinates":[121.076072,22.988173],"type":"Point"}
}