{
  "id": 7395852,
  "type": "Feature",
  "properties": {
    "tgn:hierarchy":[
        "tgn:7395852",
        "tgn:1001836",
        "tgn:1000001",
        "tgn:7005560",
        "tgn:7029392"
    ],
    "tgn:id":7395852,
    "tgn:name":"San Fabi\u00e1n",
    "tgn:placetype":[
        "aat:300008347"
    ]
},
  "bbox": [],
  "geometry": {"coordinates":[-111.916667,25.966667],"type":"Point"}
}