{
  "id": 7244026,
  "type": "Feature",
  "properties": {
    "tgn:hierarchy":[
        "tgn:7244026",
        "tgn:7003457",
        "tgn:1000003",
        "tgn:1000063",
        "tgn:7018236",
        "tgn:7029392"
    ],
    "tgn:id":7244026,
    "tgn:name":"Jammelshoek",
    "tgn:placetype":[
        "aat:300008347"
    ]
},
  "bbox": [],
  "geometry": {"coordinates":[3.474617,50.855772],"type":"Point"}
}