{
  "id": 2680742,
  "type": "Feature",
  "properties": {
    "tgn:hierarchy":[
        "tgn:2680742",
        "tgn:2000090",
        "tgn:1000001",
        "tgn:7006451",
        "tgn:7012149",
        "tgn:7029392"
    ],
    "tgn:id":2680742,
    "tgn:name":"South Horse Tank",
    "tgn:placetype":[
        "aat:300006191"
    ]
},
  "bbox": [],
  "geometry": {"coordinates":[-109.3667,33.7833],"type":"Point"}
}