{
  "id": 2731493,
  "type": "Feature",
  "properties": {
    "tgn:hierarchy":[
        "tgn:2731493",
        "tgn:1000001",
        "tgn:2000264",
        "tgn:7012149",
        "tgn:7007240",
        "tgn:7029392"
    ],
    "tgn:id":2731493,
    "tgn:name":"Tulane",
    "tgn:placetype":[
        "aat:300008347"
    ]
},
  "bbox": [],
  "geometry": {"coordinates":[-81.9333,30.35],"type":"Point"}
}