{
  "id": 2581892,
  "type": "Feature",
  "properties": {
    "tgn:hierarchy":[
        "tgn:2581892",
        "tgn:7002659",
        "tgn:1000001",
        "tgn:2000011",
        "tgn:7012149",
        "tgn:7029392"
    ],
    "tgn:id":2581892,
    "tgn:name":"Pine Branch",
    "tgn:placetype":[
        "aat:300008699"
    ]
},
  "bbox": [],
  "geometry": {"coordinates":[-88.3667,31.7333],"type":"Point"}
}