{
  "id": 2311986,
  "type": "Feature",
  "properties": {
    "tgn:hierarchy":[
        "tgn:2311986",
        "tgn:1000001",
        "tgn:7012149",
        "tgn:2000984",
        "tgn:7007520",
        "tgn:7029392"
    ],
    "tgn:id":2311986,
    "tgn:name":"Egg Lake",
    "tgn:placetype":[
        "aat:300008680"
    ]
},
  "bbox": [],
  "geometry": {"coordinates":[-85.8333,43.6167],"type":"Point"}
}