{
  "id": 2415994,
  "type": "Feature",
  "properties": {
    "tgn:hierarchy":[
        "tgn:2415994",
        "tgn:1000001",
        "tgn:2000782",
        "tgn:7012149",
        "tgn:7007255",
        "tgn:7029392"
    ],
    "tgn:id":2415994,
    "tgn:name":"Ivy Hollow",
    "tgn:placetype":[
        "aat:300008761"
    ]
},
  "bbox": [],
  "geometry": {"coordinates":[-83.5667,37.0833],"type":"Point"}
}