{
  "id": 7429145,
  "type": "Feature",
  "properties": {
    "tgn:hierarchy":[
        "tgn:7429145",
        "tgn:1001853",
        "tgn:1000001",
        "tgn:7005560",
        "tgn:7029392"
    ],
    "tgn:id":7429145,
    "tgn:name":"La Campana",
    "tgn:placetype":[
        "aat:300008347"
    ]
},
  "bbox": [],
  "geometry": {"coordinates":[-100.883333,24.816667],"type":"Point"}
}