{
  "id": 2393543,
  "type": "Feature",
  "properties": {
    "tgn:hierarchy":[
        "tgn:2393543",
        "tgn:1000001",
        "tgn:2000301",
        "tgn:7012149",
        "tgn:7007248",
        "tgn:7029392"
    ],
    "tgn:id":2393543,
    "tgn:name":"Hog Creek",
    "tgn:placetype":[
        "aat:300008706"
    ]
},
  "bbox": [],
  "geometry": {"coordinates":[-83.3333,31.4333],"type":"Point"}
}