{
  "id": 2519157,
  "type": "Feature",
  "properties": {
    "tgn:hierarchy":[
        "tgn:2519157",
        "tgn:7002659",
        "tgn:1000001",
        "tgn:7012149",
        "tgn:2000054",
        "tgn:7029392"
    ],
    "tgn:id":2519157,
    "tgn:name":"Moccasin Branch",
    "tgn:placetype":[
        "aat:300008699"
    ]
},
  "bbox": [],
  "geometry": {"coordinates":[-85.9333,31.8833],"type":"Point"}
}