<<<<<<< HEAD
{
  "id": 2409780,
  "type": "Feature",
  "properties": {
    "tgn:hierarchy":[
        "tgn:2409780",
        "tgn:7030516",
        "tgn:7006450",
        "tgn:1000001",
        "tgn:7012149",
        "tgn:7029392"
    ],
    "tgn:id":2409780,
    "tgn:name":"Iliuliuk Bay",
    "tgn:placetype":[
        "aat:300132316"
    ]
},
  "bbox": [],
  "geometry": {"coordinates":[-166.5,53.8833],"type":"Point"}
}
=======
{"geometry":{"type":"Point","coordinates":[-166.500000,53.883300]},"type":"Feature","properties":{"hierarchy":["tgn:2409780","tgn:7030516","tgn:7006450","tgn:1000001","tgn:7012149","tgn:7029392"],"placetype":["aat:300132316"],"id":2409780,"name:xx":"Iliuliuk Bay"}}
>>>>>>> 03f74aca74312dbeaf24d7e61306dd6a786dc3d0
