{
  "id": 2382591,
  "type": "Feature",
  "properties": {
    "tgn:hierarchy":[
        "tgn:2382591",
        "tgn:1000001",
        "tgn:7012149",
        "tgn:2000437",
        "tgn:7007248",
        "tgn:7029392"
    ],
    "tgn:id":2382591,
    "tgn:name":"Haysville",
    "tgn:placetype":[
        "aat:300008347"
    ]
},
  "bbox": [],
  "geometry": {"coordinates":[-85.35,34.8667],"type":"Point"}
}