<<<<<<< HEAD
{
  "id": 2403084,
  "type": "Feature",
  "properties": {
    "tgn:hierarchy":[
        "tgn:2403084",
        "tgn:1000001",
        "tgn:1002601",
        "tgn:7012149",
        "tgn:7007159",
        "tgn:7029392"
    ],
    "tgn:id":2403084,
    "tgn:name":"Housatonic Valley",
    "tgn:placetype":[
        "aat:300008761"
    ]
},
  "bbox": [],
  "geometry": {"coordinates":[-73.4167,41.5667],"type":"Point"}
}
=======
{"geometry":{"type":"Point","coordinates":[-73.416700,41.566700]},"type":"Feature","properties":{"hierarchy":["tgn:2403084","tgn:1000001","tgn:1002601","tgn:7012149","tgn:7007159","tgn:7029392"],"placetype":["aat:300008761"],"id":2403084,"name:xx":"Housatonic Valley"}}
>>>>>>> 03f74aca74312dbeaf24d7e61306dd6a786dc3d0
