{
  "id": 2134328,
  "type": "Feature",
  "properties": {
    "tgn:hierarchy":[
        "tgn:2134328",
        "tgn:7002659",
        "tgn:1000001",
        "tgn:7012149",
        "tgn:2000065",
        "tgn:7029392"
    ],
    "tgn:id":2134328,
    "tgn:name":"Anne Manie",
    "tgn:placetype":[
        "aat:300008347"
    ]
},
  "bbox": [],
  "geometry": {"coordinates":[-87.5667,32.05],"type":"Point"}
}