{
  "id": 7467436,
  "type": "Feature",
  "properties": {
    "tgn:hierarchy":[
        "tgn:7467436",
        "tgn:7488858",
        "tgn:1000004",
        "tgn:1000141",
        "tgn:7029392"
    ],
    "tgn:id":7467436,
    "tgn:name":"Zhizhuang",
    "tgn:placetype":[
        "aat:300008347"
    ]
},
  "bbox": [],
  "geometry": {"coordinates":[121.15,24.033333],"type":"Point"}
}