{
  "id": 7547957,
  "type": "Feature",
  "properties": {
    "tgn:hierarchy":[
        "tgn:7547957",
        "tgn:1000004",
        "tgn:7000198",
        "tgn:1001894",
        "tgn:7029392"
    ],
    "tgn:id":7547957,
    "tgn:name:en":"Atner",
    "tgn:placetype":[
        "aat:300008347"
    ]
},
  "bbox": [],
  "geometry": {"coordinates":[77.915723,21.623133],"type":"Point"}
}