{
  "id": 7511583,
  "type": "Feature",
  "properties": {
    "tgn:hierarchy":[
        "tgn:7511583",
        "tgn:1009227",
        "tgn:1000226",
        "tgn:7520095",
        "tgn:1000006",
        "tgn:7029392"
    ],
    "tgn:id":7511583,
    "tgn:name:en":"Louis Creek",
    "tgn:placetype":[
        "aat:300008699"
    ]
},
  "bbox": [],
  "geometry": {"coordinates":[172.666667,-41.766667],"type":"Point"}
}