{
  "id": 2619228,
  "type": "Feature",
  "properties": {
    "tgn:hierarchy":[
        "tgn:2619228",
        "tgn:1000001",
        "tgn:7012149",
        "tgn:2001508",
        "tgn:7007709",
        "tgn:7029392"
    ],
    "tgn:id":2619228,
    "tgn:name":"Riley Mountain",
    "tgn:placetype":[
        "aat:300008798"
    ]
},
  "bbox": [],
  "geometry": {"coordinates":[-83.0667,35.1167],"type":"Point"}
}