<<<<<<< HEAD
{
  "id": 2158366,
  "type": "Feature",
  "properties": {
    "tgn:hierarchy":[
        "tgn:2158366",
        "tgn:1000001",
        "tgn:7012149",
        "tgn:2001522",
        "tgn:7007709",
        "tgn:7029392"
    ],
    "tgn:id":2158366,
    "tgn:name":"Beaverdam Branch",
    "tgn:placetype":[
        "aat:300008699"
    ]
},
  "bbox": [],
  "geometry": {"coordinates":[-78.1,36.0167],"type":"Point"}
}
=======
{"geometry":{"type":"Point","coordinates":[-78.100000,36.016700]},"type":"Feature","properties":{"hierarchy":["tgn:2158366","tgn:1000001","tgn:7012149","tgn:2001522","tgn:7007709","tgn:7029392"],"placetype":["aat:300008699"],"id":2158366,"name:xx":"Beaverdam Branch"}}
>>>>>>> 03f74aca74312dbeaf24d7e61306dd6a786dc3d0
