{
  "id": 7031955,
  "type": "Feature",
  "properties": {
    "tgn:hierarchy":[
        "tgn:7031955",
        "tgn:7001242",
        "tgn:7017576",
        "tgn:1000193",
        "tgn:7029392"
    ],
    "tgn:id":7031955,
    "tgn:name":"Krugersdorp Wildtuin",
    "tgn:placetype":[
        "aat:300008181"
    ]
},
  "bbox": [],
  "geometry": {"coordinates":[27.728,-26.083],"type":"Point"}
}