<<<<<<< HEAD
{
  "id": 2159644,
  "type": "Feature",
  "properties": {
    "tgn:hierarchy":[
        "tgn:2159644",
        "tgn:1000001",
        "tgn:7012149",
        "tgn:2001545",
        "tgn:7007709",
        "tgn:7029392"
    ],
    "tgn:id":2159644,
    "tgn:name":"Bee Tree Canal",
    "tgn:placetype":[
        "aat:300006075"
    ]
},
  "bbox": [],
  "geometry": {"coordinates":[-76.35,35.8167],"type":"Point"}
}
=======
{"geometry":{"type":"Point","coordinates":[-76.350000,35.816700]},"type":"Feature","properties":{"hierarchy":["tgn:2159644","tgn:1000001","tgn:7012149","tgn:2001545","tgn:7007709","tgn:7029392"],"placetype":["aat:300006075"],"id":2159644,"name:xx":"Bee Tree Canal"}}
>>>>>>> 03f74aca74312dbeaf24d7e61306dd6a786dc3d0
