{
  "id": 2601580,
  "type": "Feature",
  "properties": {
    "tgn:hierarchy":[
        "tgn:2601580",
        "tgn:1000001",
        "tgn:7016172",
        "tgn:7012149",
        "tgn:2000168",
        "tgn:7029392"
    ],
    "tgn:id":2601580,
    "tgn:name":"Puryear",
    "tgn:placetype":[
        "aat:300008347"
    ]
},
  "bbox": [],
  "geometry": {"coordinates":[-94.4167,34.7833],"type":"Point"}
}