{
  "id": 1005196,
  "type": "Feature",
  "properties": {
    "tgn:hierarchy":[
        "tgn:1005196",
        "tgn:7001242",
        "tgn:7017576",
        "tgn:1000193",
        "tgn:7029392"
    ],
    "tgn:id":1005196,
    "tgn:name":"Newlands",
    "tgn:placetype":[
        "aat:300000745"
    ]
},
  "bbox": [],
  "geometry": {"coordinates":[27.9667,-26.1667],"type":"Point"}
}