{
  "id": 7131657,
  "type": "Feature",
  "properties": {
    "tgn:hierarchy":[
        "tgn:7131657",
        "tgn:1000003",
        "tgn:7003685",
        "tgn:7000084",
        "tgn:7029392"
    ],
    "tgn:id":7131657,
    "tgn:name":"Merkwitz",
    "tgn:placetype":[
        "aat:300008347"
    ]
},
  "bbox": [],
  "geometry": {"coordinates":[13.083333,51.316667],"type":"Point"}
}