<<<<<<< HEAD
{
  "id": 7362294,
  "type": "Feature",
  "properties": {
    "tgn:hierarchy":[
        "tgn:7362294",
        "tgn:7005583",
        "tgn:1000001",
        "tgn:7005560",
        "tgn:7029392"
    ],
    "tgn:id":7362294,
    "tgn:name":"Rancho El Carmen",
    "tgn:placetype":[
        "aat:300000241"
    ]
},
  "bbox": [],
  "geometry": {"coordinates":[-104.566667,24.766667],"type":"Point"}
}
=======
{"geometry":{"type":"Point","coordinates":[-104.566667,24.766667]},"type":"Feature","properties":{"hierarchy":["tgn:7362294","tgn:7005583","tgn:1000001","tgn:7005560","tgn:7029392"],"placetype":["aat:300000241"],"id":7362294,"name:xx":"Rancho El Carmen"}}
>>>>>>> 03f74aca74312dbeaf24d7e61306dd6a786dc3d0
