{
  "id": 7362294,
  "type": "Feature",
  "properties": {
    "tgn:hierarchy":[
        "tgn:7362294",
        "tgn:7005583",
        "tgn:1000001",
        "tgn:7005560",
        "tgn:7029392"
    ],
    "tgn:id":7362294,
    "tgn:name":"Rancho El Carmen",
    "tgn:placetype":[
        "aat:300000241"
    ]
},
  "bbox": [],
  "geometry": {"coordinates":[-104.566667,24.766667],"type":"Point"}
}