{
  "id": 7316036,
  "type": "Feature",
  "properties": {
    "tgn:hierarchy":[
        "tgn:7316036",
        "tgn:1001699",
        "tgn:1000049",
        "tgn:1000002",
        "tgn:7029392"
    ],
    "tgn:id":7316036,
    "tgn:name":"Cascada, Punta",
    "tgn:placetype":[
        "aat:300386846"
    ]
},
  "bbox": [],
  "geometry": {"coordinates":[-72.4625,-42.311111],"type":"Point"}
}