{
  "id": 2010417,
  "type": "Feature",
  "properties": {
    "tgn:hierarchy":[
        "tgn:2010417",
        "tgn:1000001",
        "tgn:7012149",
        "tgn:7007157",
        "tgn:7014005",
        "tgn:7029392"
    ],
    "tgn:id":2010417,
    "tgn:name":"Burdell",
    "tgn:placetype":[
        "aat:300387016"
    ]
},
  "bbox": [],
  "geometry": {"coordinates":[-122.55,38.15],"type":"Point"}
}