<<<<<<< HEAD
{
  "id": 7364342,
  "type": "Feature",
  "properties": {
    "tgn:hierarchy":[
        "tgn:7364342",
        "tgn:1000001",
        "tgn:1001960",
        "tgn:7005560",
        "tgn:7029392"
    ],
    "tgn:id":7364342,
    "tgn:name":"Rancho El Salto",
    "tgn:placetype":[
        "aat:300000241"
    ]
},
  "bbox": [],
  "geometry": {"coordinates":[-109.666667,30.483333],"type":"Point"}
}
=======
{"geometry":{"type":"Point","coordinates":[-109.666667,30.483333]},"type":"Feature","properties":{"hierarchy":["tgn:7364342","tgn:1000001","tgn:1001960","tgn:7005560","tgn:7029392"],"placetype":["aat:300000241"],"id":7364342,"name:xx":"Rancho El Salto"}}
>>>>>>> 03f74aca74312dbeaf24d7e61306dd6a786dc3d0
