{
  "id": 2143765,
  "type": "Feature",
  "properties": {
    "tgn:hierarchy":[
        "tgn:2143765",
        "tgn:7006450",
        "tgn:1000001",
        "tgn:7030517",
        "tgn:7012149",
        "tgn:7029392"
    ],
    "tgn:id":2143765,
    "tgn:name":"Baked Mountain",
    "tgn:placetype":[
        "aat:300008798"
    ]
},
  "bbox": [],
  "geometry": {"coordinates":[-155.1833,58.2667],"type":"Point"}
}