{
  "id": 7162356,
  "type": "Feature",
  "properties": {
    "tgn:hierarchy":[
        "tgn:7162356",
        "tgn:7003669",
        "tgn:1000003",
        "tgn:7000084",
        "tgn:7029392"
    ],
    "tgn:id":7162356,
    "tgn:name":"Horn-Wald",
    "tgn:placetype":[
        "aat:300008863"
    ]
},
  "bbox": [],
  "geometry": {"coordinates":[10.683333,47.783333],"type":"Point"}
}