{
  "id": 2167841,
  "type": "Feature",
  "properties": {
    "tgn:hierarchy":[
        "tgn:2167841",
        "tgn:1000001",
        "tgn:7012149",
        "tgn:2001444",
        "tgn:7007566",
        "tgn:7029392"
    ],
    "tgn:id":2167841,
    "tgn:name":"Big Digging Mines",
    "tgn:placetype":[
        "aat:300000390"
    ]
},
  "bbox": [],
  "geometry": {"coordinates":[-107.9333,32.0333],"type":"Point"}
}