<<<<<<< HEAD
{
  "id": 7470172,
  "type": "Feature",
  "properties": {
    "tgn:hierarchy":[
        "tgn:7470172",
        "tgn:7468018",
        "tgn:1000004",
        "tgn:1000141",
        "tgn:7029392"
    ],
    "tgn:id":7470172,
    "tgn:name":"Xiayangzi",
    "tgn:placetype":[
        "aat:300008347"
    ]
},
  "bbox": [],
  "geometry": {"coordinates":[120.432221,23.525628],"type":"Point"}
}
=======
{"geometry":{"type":"Point","coordinates":[120.432221,23.525628]},"type":"Feature","properties":{"hierarchy":["tgn:7470172","tgn:7468018","tgn:1000004","tgn:1000141","tgn:7029392"],"placetype":["aat:300008347"],"id":7470172,"name:xx":"Xiayangzi"}}
>>>>>>> 03f74aca74312dbeaf24d7e61306dd6a786dc3d0
