{
  "id": 2362005,
  "type": "Feature",
  "properties": {
    "tgn:hierarchy":[
        "tgn:2362005",
        "tgn:1000001",
        "tgn:2002107",
        "tgn:7012149",
        "tgn:7007827",
        "tgn:7029392"
    ],
    "tgn:id":2362005,
    "tgn:name":"Gray Mountain Canal",
    "tgn:placetype":[
        "aat:300006075"
    ]
},
  "bbox": [],
  "geometry": {"coordinates":[-110.1833,40.1333],"type":"Point"}
}