{
  "id": 7346984,
  "type": "Feature",
  "properties": {
    "tgn:hierarchy":[
        "tgn:7346984",
        "tgn:7002818",
        "tgn:1001647",
        "tgn:1000003",
        "tgn:1000095",
        "tgn:7029392"
    ],
    "tgn:id":7346984,
    "tgn:name":"Barajas de Melo",
    "tgn:placetype":[
        "aat:300008347"
    ]
},
  "bbox": [],
  "geometry": {"coordinates":[-2.916667,40.116667],"type":"Point"}
}