{
  "id": 7317495,
  "type": "Feature",
  "properties": {
    "tgn:hierarchy":[
        "tgn:7317495",
        "tgn:1001695",
        "tgn:1000049",
        "tgn:1000002",
        "tgn:7029392"
    ],
    "tgn:id":7317495,
    "tgn:name":"Cocal\u00e1n",
    "tgn:placetype":[
        "aat:300387200"
    ]
},
  "bbox": [],
  "geometry": {"coordinates":[-71.316667,-34.216667],"type":"Point"}
}