{
  "id": 2696146,
  "type": "Feature",
  "properties": {
    "tgn:hierarchy":[
        "tgn:2696146",
        "tgn:1000001",
        "tgn:7012149",
        "tgn:7007157",
        "tgn:1002956",
        "tgn:7029392"
    ],
    "tgn:id":2696146,
    "tgn:name":"Stokes Mountain",
    "tgn:placetype":[
        "aat:300008798"
    ]
},
  "bbox": [],
  "geometry": {"coordinates":[-119.1833,36.5167],"type":"Point"}
}