{
  "id": 2620121,
  "type": "Feature",
  "properties": {
    "tgn:hierarchy":[
        "tgn:2620121",
        "tgn:1000001",
        "tgn:1002267",
        "tgn:7012149",
        "tgn:7007919",
        "tgn:7029392"
    ],
    "tgn:id":2620121,
    "tgn:name":"Rita Branch",
    "tgn:placetype":[
        "aat:300008699"
    ]
},
  "bbox": [],
  "geometry": {"coordinates":[-77.5833,37.2833],"type":"Point"}
}