{
  "id": 1038765,
  "type": "Feature",
  "properties": {
    "tgn:hierarchy":[
        "tgn:1038765",
        "tgn:1000003",
        "tgn:7003677",
        "tgn:7000084",
        "tgn:7029392"
    ],
    "tgn:id":1038765,
    "tgn:name":"Darfeld",
    "tgn:placetype":[
        "aat:300008347"
    ]
},
  "bbox": [],
  "geometry": {"coordinates":[7.266667,52.033333],"type":"Point"}
}