{
  "id": 2461844,
  "type": "Feature",
  "properties": {
    "tgn:hierarchy":[
        "tgn:2461844",
        "tgn:1000001",
        "tgn:2002256",
        "tgn:7012149",
        "tgn:7013961",
        "tgn:7029392"
    ],
    "tgn:id":2461844,
    "tgn:name":"Little Trace Run",
    "tgn:placetype":[
        "aat:300008699"
    ]
},
  "bbox": [],
  "geometry": {"coordinates":[-80.7667,38.75],"type":"Point"}
}