{
  "id": 2172610,
  "type": "Feature",
  "properties": {
    "tgn:hierarchy":[
        "tgn:2172610",
        "tgn:1000001",
        "tgn:7012149",
        "tgn:7007708",
        "tgn:7029392"
    ],
    "tgn:id":2172610,
    "tgn:name":"Billings Creek",
    "tgn:placetype":[
        "aat:300008706"
    ]
},
  "bbox": [],
  "geometry": {"coordinates":[-124.0333,42.6833],"type":"Point"}
}