{
  "id": 2724155,
  "type": "Feature",
  "properties": {
    "tgn:hierarchy":[
        "tgn:2724155",
        "tgn:1000001",
        "tgn:7012149",
        "tgn:2000476",
        "tgn:7007250",
        "tgn:7029392"
    ],
    "tgn:id":2724155,
    "tgn:name":"Tom Beal Peak",
    "tgn:placetype":[
        "aat:300008798"
    ]
},
  "bbox": [],
  "geometry": {"coordinates":[-114.7667,46.4333],"type":"Point"}
}