{
  "id": 2192545,
  "type": "Feature",
  "properties": {
    "tgn:hierarchy":[
        "tgn:2192545",
        "tgn:1000001",
        "tgn:7012149",
        "tgn:1002392",
        "tgn:7007157",
        "tgn:7029392"
    ],
    "tgn:id":2192545,
    "tgn:name":"Branford Mountain",
    "tgn:placetype":[
        "aat:300008798"
    ]
},
  "bbox": [],
  "geometry": {"coordinates":[-119.2833,36.95],"type":"Point"}
}