{
  "id": 2204921,
  "type": "Feature",
  "properties": {
    "tgn:hierarchy":[
        "tgn:2204921",
        "tgn:1000001",
        "tgn:7006451",
        "tgn:2000094",
        "tgn:7012149",
        "tgn:7029392"
    ],
    "tgn:id":2204921,
    "tgn:name":"Buford Hill",
    "tgn:placetype":[
        "aat:300008798"
    ]
},
  "bbox": [],
  "geometry": {"coordinates":[-110.2333,32.8333],"type":"Point"}
}