{
  "id": 7183104,
  "type": "Feature",
  "properties": {
    "tgn:hierarchy":[
        "tgn:7183104",
        "tgn:1000003",
        "tgn:7003687",
        "tgn:7000084",
        "tgn:7029392"
    ],
    "tgn:id":7183104,
    "tgn:name":"Friedrichrode",
    "tgn:placetype":[
        "aat:300008347"
    ]
},
  "bbox": [],
  "geometry": {"coordinates":[11.383333,51.633333],"type":"Point"}
}