<<<<<<< HEAD
{
  "id": 7114700,
  "type": "Feature",
  "properties": {
    "tgn:hierarchy":[
        "tgn:7114700",
        "tgn:1000003",
        "tgn:7003682",
        "tgn:7000084",
        "tgn:7029392"
    ],
    "tgn:id":7114700,
    "tgn:name":"Ockenfels",
    "tgn:placetype":[
        "aat:300008347"
    ]
},
  "bbox": [],
  "geometry": {"coordinates":[7.283333,50.583333],"type":"Point"}
}
=======
{"geometry":{"type":"Point","coordinates":[7.283333,50.583333]},"type":"Feature","properties":{"hierarchy":["tgn:7114700","tgn:1000003","tgn:7003682","tgn:7000084","tgn:7029392"],"placetype":["aat:300008347"],"id":7114700,"name:xx":"Ockenfels"}}
>>>>>>> 03f74aca74312dbeaf24d7e61306dd6a786dc3d0
