{
  "id": 1096602,
  "type": "Feature",
  "properties": {
    "tgn:hierarchy":[
        "tgn:1096602",
        "tgn:7000490",
        "tgn:1000006",
        "tgn:7001992",
        "tgn:7029392"
    ],
    "tgn:id":1096602,
    "tgn:name":"Conara Junction",
    "tgn:placetype":[
        "aat:300008347"
    ]
},
  "bbox": [],
  "geometry": {"coordinates":[147.4333,-41.8333],"type":"Point"}
}