{
  "id": 2218197,
  "type": "Feature",
  "properties": {
    "tgn:hierarchy":[
        "tgn:2218197",
        "tgn:1000001",
        "tgn:7012149",
        "tgn:7007157",
        "tgn:2000189",
        "tgn:7029392"
    ],
    "tgn:id":2218197,
    "tgn:name":"Canal Gulch",
    "tgn:placetype":[
        "aat:300008761"
    ]
},
  "bbox": [],
  "geometry": {"coordinates":[-122.6667,41.7667],"type":"Point"}
}