<<<<<<< HEAD
{
  "id": 2156186,
  "type": "Feature",
  "properties": {
    "tgn:hierarchy":[
        "tgn:2156186",
        "tgn:1000001",
        "tgn:7012149",
        "tgn:1002873",
        "tgn:7007568",
        "tgn:7029392"
    ],
    "tgn:id":2156186,
    "tgn:name":"Beards Hollow",
    "tgn:placetype":[
        "aat:300008347"
    ]
},
  "bbox": [],
  "geometry": {"coordinates":[-74.55,42.6],"type":"Point"}
}
=======
{"geometry":{"type":"Point","coordinates":[-74.550000,42.600000]},"type":"Feature","properties":{"hierarchy":["tgn:2156186","tgn:1000001","tgn:7012149","tgn:1002873","tgn:7007568","tgn:7029392"],"placetype":["aat:300008347"],"id":2156186,"name:xx":"Beards Hollow"}}
>>>>>>> 03f74aca74312dbeaf24d7e61306dd6a786dc3d0
