{
  "id": 1056123,
  "type": "Feature",
  "properties": {
    "tgn:hierarchy":[
        "tgn:1056123",
        "tgn:1003373",
        "tgn:1000004",
        "tgn:7018214",
        "tgn:7002435",
        "tgn:7029392"
    ],
    "tgn:id":1056123,
    "tgn:name":"Kurgatey",
    "tgn:placetype":[
        "aat:300008347"
    ]
},
  "bbox": [],
  "geometry": {"coordinates":[99.4167,54.3667],"type":"Point"}
}