{
  "id": 2603848,
  "type": "Feature",
  "properties": {
    "tgn:hierarchy":[
        "tgn:2603848",
        "tgn:7006450",
        "tgn:1000001",
        "tgn:7012149",
        "tgn:7029392"
    ],
    "tgn:id":2603848,
    "tgn:name":"Quigmy River",
    "tgn:placetype":[
        "aat:300008707"
    ]
},
  "bbox": [],
  "geometry": {"coordinates":[-160.5167,59.2833],"type":"Point"}
}