{
  "id": 2716180,
  "type": "Feature",
  "properties": {
    "tgn:hierarchy":[
        "tgn:2716180",
        "tgn:1002201",
        "tgn:1000001",
        "tgn:7012149",
        "tgn:7007517",
        "tgn:7029392"
    ],
    "tgn:id":2716180,
    "tgn:name":"Thatchers Pond",
    "tgn:placetype":[
        "aat:300008680"
    ]
},
  "bbox": [],
  "geometry": {"coordinates":[-70.9667,41.8833],"type":"Point"}
}