{
  "id": 7300872,
  "type": "Feature",
  "properties": {
    "tgn:hierarchy":[
        "tgn:7300872",
        "tgn:7002818",
        "tgn:1001647",
        "tgn:1000003",
        "tgn:1000095",
        "tgn:7029392"
    ],
    "tgn:id":7300872,
    "tgn:name":"Moraleja, Arroyo de la",
    "tgn:placetype":[
        "aat:300008699"
    ]
},
  "bbox": [],
  "geometry": {"coordinates":[-2.933333,39.883333],"type":"Point"}
}