<<<<<<< HEAD
{
  "id": 7484777,
  "type": "Feature",
  "properties": {
    "tgn:hierarchy":[
        "tgn:7484777",
        "tgn:7487020",
        "tgn:1000004",
        "tgn:1000141",
        "tgn:7029392"
    ],
    "tgn:id":7484777,
    "tgn:name":"Huweiliao",
    "tgn:placetype":[
        "aat:300008347"
    ]
},
  "bbox": [],
  "geometry": {"coordinates":[120.686389,24.351944],"type":"Point"}
}
=======
{"geometry":{"type":"Point","coordinates":[120.686389,24.351944]},"type":"Feature","properties":{"hierarchy":["tgn:7484777","tgn:7487020","tgn:1000004","tgn:1000141","tgn:7029392"],"placetype":["aat:300008347"],"id":7484777,"name:xx":"Huweiliao"}}
>>>>>>> 03f74aca74312dbeaf24d7e61306dd6a786dc3d0
