{
  "id": 7562764,
  "type": "Feature",
  "properties": {
    "tgn:hierarchy":[
        "tgn:7562764",
        "tgn:1000004",
        "tgn:7000198",
        "tgn:7016722",
        "tgn:7029392"
    ],
    "tgn:id":7562764,
    "tgn:name:en":"Kairdah",
    "tgn:placetype":[
        "aat:300008347"
    ]
},
  "bbox": [],
  "geometry": {"coordinates":[79.445787,27.07067],"type":"Point"}
}