{
  "id": 2607116,
  "type": "Feature",
  "properties": {
    "tgn:hierarchy":[
        "tgn:2607116",
        "tgn:2000919",
        "tgn:1000001",
        "tgn:7012149",
        "tgn:7007515",
        "tgn:7029392"
    ],
    "tgn:id":2607116,
    "tgn:name":"Rand Pond",
    "tgn:placetype":[
        "aat:300008680"
    ]
},
  "bbox": [],
  "geometry": {"coordinates":[-67.9167,46.65],"type":"Point"}
}