{
  "id": 2673827,
  "type": "Feature",
  "properties": {
    "tgn:hierarchy":[
        "tgn:2673827",
        "tgn:7006450",
        "tgn:1000001",
        "tgn:7012149",
        "tgn:2000089",
        "tgn:7029392"
    ],
    "tgn:id":2673827,
    "tgn:name":"Snow Gulch",
    "tgn:placetype":[
        "aat:300008761"
    ]
},
  "bbox": [],
  "geometry": {"coordinates":[-158.1167,62.0333],"type":"Point"}
}