{
  "id": 7358198,
  "type": "Feature",
  "properties": {
    "tgn:hierarchy":[
        "tgn:7358198",
        "tgn:7005584",
        "tgn:1000001",
        "tgn:7005560",
        "tgn:7029392"
    ],
    "tgn:id":7358198,
    "tgn:name":"Estaci\u00f3n Covarrubias",
    "tgn:placetype":[
        "aat:300007783"
    ]
},
  "bbox": [],
  "geometry": {"coordinates":[-101.45,20.633333],"type":"Point"}
}