{
  "id": 1071393,
  "type": "Feature",
  "properties": {
    "tgn:hierarchy":[
        "tgn:1071393",
        "tgn:1000004",
        "tgn:7002077",
        "tgn:1000111",
        "tgn:7029392"
    ],
    "tgn:id":1071393,
    "tgn:name":"Shaheyi",
    "tgn:placetype":[
        "aat:300008347"
    ]
},
  "bbox": [],
  "geometry": {"coordinates":[118.5833,39.8667],"type":"Point"}
}