{
  "id": 2274258,
  "type": "Feature",
  "properties": {
    "tgn:hierarchy":[
        "tgn:2274258",
        "tgn:7002659",
        "tgn:1000001",
        "tgn:7012149",
        "tgn:2000059",
        "tgn:7029392"
    ],
    "tgn:id":2274258,
    "tgn:name":"Daisy Falls Lake",
    "tgn:placetype":[
        "aat:300006191"
    ]
},
  "bbox": [],
  "geometry": {"coordinates":[-88.1667,32.75],"type":"Point"}
}