{
  "id": 2307060,
  "type": "Feature",
  "properties": {
    "tgn:hierarchy":[
        "tgn:2307060",
        "tgn:1000001",
        "tgn:7012149",
        "tgn:7007920",
        "tgn:7029392"
    ],
    "tgn:id":2307060,
    "tgn:name":"East Fork McAlester Creek",
    "tgn:placetype":[
        "aat:300008706"
    ]
},
  "bbox": [],
  "geometry": {"coordinates":[-120.6333,48.4667],"type":"Point"}
}