{
  "id": 2570552,
  "type": "Feature",
  "properties": {
    "tgn:hierarchy":[
        "tgn:2570552",
        "tgn:1000001",
        "tgn:7012149",
        "tgn:2001442",
        "tgn:7007566",
        "tgn:7029392"
    ],
    "tgn:id":2570552,
    "tgn:name":"Patos Mountain",
    "tgn:placetype":[
        "aat:300008798"
    ]
},
  "bbox": [],
  "geometry": {"coordinates":[-105.65,33.7333],"type":"Point"}
}