{
  "id": 7306791,
  "type": "Feature",
  "properties": {
    "tgn:hierarchy":[
        "tgn:7306791",
        "tgn:7002760",
        "tgn:1000003",
        "tgn:1000095",
        "tgn:7029392"
    ],
    "tgn:id":7306791,
    "tgn:name":"Loma Somera",
    "tgn:placetype":[
        "aat:300008347"
    ]
},
  "bbox": [],
  "geometry": {"coordinates":[-4.016667,42.866667],"type":"Point"}
}