{
  "id": 2672874,
  "type": "Feature",
  "properties": {
    "tgn:hierarchy":[
        "tgn:2672874",
        "tgn:7002659",
        "tgn:1000001",
        "tgn:7012149",
        "tgn:2000053",
        "tgn:7029392"
    ],
    "tgn:id":2672874,
    "tgn:name":"Snake Creek",
    "tgn:placetype":[
        "aat:300008706"
    ]
},
  "bbox": [],
  "geometry": {"coordinates":[-88.1667,33.2833],"type":"Point"}
}