{
  "id": 2426377,
  "type": "Feature",
  "properties": {
    "tgn:hierarchy":[
        "tgn:2426377",
        "tgn:1000001",
        "tgn:7012149",
        "tgn:1002966",
        "tgn:7007826",
        "tgn:7029392"
    ],
    "tgn:id":2426377,
    "tgn:name":"Jones Creek",
    "tgn:placetype":[
        "aat:300008706"
    ]
},
  "bbox": [],
  "geometry": {"coordinates":[-94.7833,32.85],"type":"Point"}
}