{
  "id": 2668604,
  "type": "Feature",
  "properties": {
    "tgn:hierarchy":[
        "tgn:2668604",
        "tgn:1000001",
        "tgn:7006451",
        "tgn:2000092",
        "tgn:7012149",
        "tgn:7029392"
    ],
    "tgn:id":2668604,
    "tgn:name":"Slate Mountain",
    "tgn:placetype":[
        "aat:300008798"
    ]
},
  "bbox": [],
  "geometry": {"coordinates":[-111.8333,35.4833],"type":"Point"}
}