{
  "id": 2180579,
  "type": "Feature",
  "properties": {
    "tgn:hierarchy":[
        "tgn:2180579",
        "tgn:1000001",
        "tgn:7012149",
        "tgn:7007254",
        "tgn:7029392"
    ],
    "tgn:id":2180579,
    "tgn:name":"Bloody Run",
    "tgn:placetype":[
        "aat:300008699"
    ]
},
  "bbox": [],
  "geometry": {"coordinates":[-95.6833,37.75],"type":"Point"}
}