{
  "id": 7320429,
  "type": "Feature",
  "properties": {
    "tgn:hierarchy":[
        "tgn:7320429",
        "tgn:1001702",
        "tgn:1000049",
        "tgn:1000002",
        "tgn:7029392"
    ],
    "tgn:id":7320429,
    "tgn:name":"Barrancas, Punta",
    "tgn:placetype":[
        "aat:300386846"
    ]
},
  "bbox": [],
  "geometry": {"coordinates":[-69.683333,-52.55],"type":"Point"}
}