{
  "id": 1033011,
  "type": "Feature",
  "properties": {
    "tgn:hierarchy":[
        "tgn:1033011",
        "tgn:1000003",
        "tgn:7001097",
        "tgn:1000070",
        "tgn:7029392"
    ],
    "tgn:id":1033011,
    "tgn:name":"Embry",
    "tgn:placetype":[
        "aat:300008347"
    ]
},
  "bbox": [],
  "geometry": {"coordinates":[1.9667,50.4833],"type":"Point"}
}