{
  "id": 2693163,
  "type": "Feature",
  "properties": {
    "tgn:hierarchy":[
        "tgn:2693163",
        "tgn:1000001",
        "tgn:7012149",
        "tgn:2002270",
        "tgn:7013961",
        "tgn:7029392"
    ],
    "tgn:id":2693163,
    "tgn:name":"Steepgut Hollow",
    "tgn:placetype":[
        "aat:300008761"
    ]
},
  "bbox": [],
  "geometry": {"coordinates":[-81.45,38.2667],"type":"Point"}
}