{
  "id": 7401383,
  "type": "Feature",
  "properties": {
    "tgn:hierarchy":[
        "tgn:7401383",
        "tgn:1000001",
        "tgn:7005599",
        "tgn:7005560",
        "tgn:7029392"
    ],
    "tgn:id":7401383,
    "tgn:name":"Estaci\u00f3n Agrarios",
    "tgn:placetype":[
        "aat:300007783"
    ]
},
  "bbox": [],
  "geometry": {"coordinates":[-97.983333,22.05],"type":"Point"}
}