{
  "id": 1057054,
  "type": "Feature",
  "properties": {
    "tgn:hierarchy":[
        "tgn:1057054",
        "tgn:1000004",
        "tgn:4008031",
        "tgn:7018214",
        "tgn:7002435",
        "tgn:7029392"
    ],
    "tgn:id":1057054,
    "tgn:name":"Moshenskoye",
    "tgn:placetype":[
        "aat:300008347"
    ]
},
  "bbox": [],
  "geometry": {"coordinates":[34.5833,58.5167],"type":"Point"}
}