{
  "id": 7161107,
  "type": "Feature",
  "properties": {
    "tgn:hierarchy":[
        "tgn:7161107",
        "tgn:1000003",
        "tgn:7003676",
        "tgn:7000084",
        "tgn:7029392"
    ],
    "tgn:id":7161107,
    "tgn:name":"Holte",
    "tgn:placetype":[
        "aat:300008347"
    ]
},
  "bbox": [],
  "geometry": {"coordinates":[8.216667,52.533333],"type":"Point"}
}