{
  "id": 7283332,
  "type": "Feature",
  "properties": {
    "tgn:hierarchy":[
        "tgn:7283332",
        "tgn:1001623",
        "tgn:1000049",
        "tgn:1000002",
        "tgn:7029392"
    ],
    "tgn:id":7283332,
    "tgn:name":"Pangal, Islote del",
    "tgn:placetype":[
        "aat:300008791"
    ]
},
  "bbox": [],
  "geometry": {"coordinates":[-73.833333,-45.45],"type":"Point"}
}