{
  "id": 2507856,
  "type": "Feature",
  "properties": {
    "tgn:hierarchy":[
        "tgn:2507856",
        "tgn:7002659",
        "tgn:1000001",
        "tgn:7012149",
        "tgn:2000029",
        "tgn:7029392"
    ],
    "tgn:id":2507856,
    "tgn:name":"Mickins Branch",
    "tgn:placetype":[
        "aat:300008699"
    ]
},
  "bbox": [],
  "geometry": {"coordinates":[-87.85,34.55],"type":"Point"}
}