{
  "id": 2124986,
  "type": "Feature",
  "properties": {
    "tgn:hierarchy":[
        "tgn:2124986",
        "tgn:1000001",
        "tgn:7012149",
        "tgn:2002357",
        "tgn:7007922",
        "tgn:7029392"
    ],
    "tgn:id":2124986,
    "tgn:name":"Abraham Coulee",
    "tgn:placetype":[
        "aat:300008761"
    ]
},
  "bbox": [],
  "geometry": {"coordinates":[-91.3667,44.1667],"type":"Point"}
}