{
  "id": 2069024,
  "type": "Feature",
  "properties": {
    "tgn:hierarchy":[
        "tgn:2069024",
        "tgn:1000001",
        "tgn:7012149",
        "tgn:1002961",
        "tgn:7007568",
        "tgn:7029392"
    ],
    "tgn:id":2069024,
    "tgn:name":"East Wawarsing",
    "tgn:placetype":[
        "aat:300008347",
        "aat:300387210"
    ]
},
  "bbox": [],
  "geometry": {"coordinates":[-74.3333,41.7333],"type":"Point"}
}