{
  "id": 2558765,
  "type": "Feature",
  "properties": {
    "tgn:hierarchy":[
        "tgn:2558765",
        "tgn:1000001",
        "tgn:7012149",
        "tgn:2000715",
        "tgn:7007254",
        "tgn:7029392"
    ],
    "tgn:id":2558765,
    "tgn:name":"Olpe City Lake",
    "tgn:placetype":[
        "aat:300006191"
    ]
},
  "bbox": [],
  "geometry": {"coordinates":[-96.1833,38.25],"type":"Point"}
}