{
  "id": 2152074,
  "type": "Feature",
  "properties": {
    "tgn:hierarchy":[
        "tgn:2152074",
        "tgn:1000001",
        "tgn:7012149",
        "tgn:2001752",
        "tgn:7007712",
        "tgn:7029392"
    ],
    "tgn:id":2152074,
    "tgn:name":"Baxley",
    "tgn:placetype":[
        "aat:300008347"
    ]
},
  "bbox": [],
  "geometry": {"coordinates":[-80.35,34.4167],"type":"Point"}
}