<<<<<<< HEAD
{
  "id": 2152074,
  "type": "Feature",
  "properties": {
    "tgn:hierarchy":[
        "tgn:2152074",
        "tgn:1000001",
        "tgn:7012149",
        "tgn:2001752",
        "tgn:7007712",
        "tgn:7029392"
    ],
    "tgn:id":2152074,
    "tgn:name":"Baxley",
    "tgn:placetype":[
        "aat:300008347"
    ]
},
  "bbox": [],
  "geometry": {"coordinates":[-80.35,34.4167],"type":"Point"}
}
=======
{"geometry":{"type":"Point","coordinates":[-80.350000,34.416700]},"type":"Feature","properties":{"hierarchy":["tgn:2152074","tgn:1000001","tgn:7012149","tgn:2001752","tgn:7007712","tgn:7029392"],"placetype":["aat:300008347"],"id":2152074,"name:xx":"Baxley"}}
>>>>>>> 03f74aca74312dbeaf24d7e61306dd6a786dc3d0
