{
  "id": 7477398,
  "type": "Feature",
  "properties": {
    "tgn:hierarchy":[
        "tgn:7477398",
        "tgn:1000004",
        "tgn:1000454",
        "tgn:1000141",
        "tgn:7029392"
    ],
    "tgn:id":7477398,
    "tgn:name":"Ruixiang Qiao",
    "tgn:placetype":[
        "aat:300007836"
    ]
},
  "bbox": [],
  "geometry": {"coordinates":[121.795844,25.095493],"type":"Point"}
}