{
  "id": 2728109,
  "type": "Feature",
  "properties": {
    "tgn:hierarchy":[
        "tgn:2728109",
        "tgn:1000001",
        "tgn:2001260",
        "tgn:7012149",
        "tgn:7007524",
        "tgn:7029392"
    ],
    "tgn:id":2728109,
    "tgn:name":"Trapper Lake",
    "tgn:placetype":[
        "aat:300008680"
    ]
},
  "bbox": [],
  "geometry": {"coordinates":[-112.9167,45.5833],"type":"Point"}
}