{
  "id": 7309916,
  "type": "Feature",
  "properties": {
    "tgn:hierarchy":[
        "tgn:7309916",
        "tgn:1001702",
        "tgn:1000049",
        "tgn:1000002",
        "tgn:7029392"
    ],
    "tgn:id":7309916,
    "tgn:name":"Norte, Punta",
    "tgn:placetype":[
        "aat:300386846"
    ]
},
  "bbox": [],
  "geometry": {"coordinates":[-72.783333,-53.133333],"type":"Point"}
}