{
  "id": 2652039,
  "type": "Feature",
  "properties": {
    "tgn:hierarchy":[
        "tgn:2652039",
        "tgn:7002659",
        "tgn:1000001",
        "tgn:7012149",
        "tgn:2000036",
        "tgn:7029392"
    ],
    "tgn:id":2652039,
    "tgn:name":"Self Creek",
    "tgn:placetype":[
        "aat:300008706"
    ]
},
  "bbox": [],
  "geometry": {"coordinates":[-86.6167,33.7333],"type":"Point"}
}