<<<<<<< HEAD
{
  "id": 2333723,
  "type": "Feature",
  "properties": {
    "tgn:hierarchy":[
        "tgn:2333723",
        "tgn:1000001",
        "tgn:1002271",
        "tgn:7012149",
        "tgn:7007920",
        "tgn:7029392"
    ],
    "tgn:id":2333723,
    "tgn:name":"Foot Rock",
    "tgn:placetype":[
        "aat:300008798"
    ]
},
  "bbox": [],
  "geometry": {"coordinates":[-124.7,48.0167],"type":"Point"}
}
=======
{"geometry":{"type":"Point","coordinates":[-124.700000,48.016700]},"type":"Feature","properties":{"hierarchy":["tgn:2333723","tgn:1000001","tgn:1002271","tgn:7012149","tgn:7007920","tgn:7029392"],"placetype":["aat:300008798"],"id":2333723,"name:xx":"Foot Rock"}}
>>>>>>> 03f74aca74312dbeaf24d7e61306dd6a786dc3d0
