{
  "id": 7078307,
  "type": "Feature",
  "properties": {
    "tgn:hierarchy":[
        "tgn:7078307",
        "tgn:1000003",
        "tgn:7003676",
        "tgn:7000084",
        "tgn:7029392"
    ],
    "tgn:id":7078307,
    "tgn:name":"Wittfeitzen",
    "tgn:placetype":[
        "aat:300008347"
    ]
},
  "bbox": [],
  "geometry": {"coordinates":[10.95,53.016667],"type":"Point"}
}