{
  "id": 7323553,
  "type": "Feature",
  "properties": {
    "tgn:hierarchy":[
        "tgn:7323553",
        "tgn:7002844",
        "tgn:7030216",
        "tgn:1000003",
        "tgn:1000095",
        "tgn:7029392"
    ],
    "tgn:id":7323553,
    "tgn:name":"Robell\u00f3, Sierra del",
    "tgn:placetype":[
        "aat:300266640"
    ]
},
  "bbox": [],
  "geometry": {"coordinates":[0.65,41.216667],"type":"Point"}
}