{
  "id": 2339311,
  "type": "Feature",
  "properties": {
    "tgn:hierarchy":[
        "tgn:2339311",
        "tgn:1000001",
        "tgn:7012149",
        "tgn:2002248",
        "tgn:7007920",
        "tgn:7029392"
    ],
    "tgn:id":2339311,
    "tgn:name":"Frater Lake",
    "tgn:placetype":[
        "aat:300008680"
    ]
},
  "bbox": [],
  "geometry": {"coordinates":[-117.4833,48.65],"type":"Point"}
}