<<<<<<< HEAD
{
  "id": 2339311,
  "type": "Feature",
  "properties": {
    "tgn:hierarchy":[
        "tgn:2339311",
        "tgn:1000001",
        "tgn:7012149",
        "tgn:2002248",
        "tgn:7007920",
        "tgn:7029392"
    ],
    "tgn:id":2339311,
    "tgn:name":"Frater Lake",
    "tgn:placetype":[
        "aat:300008680"
    ]
},
  "bbox": [],
  "geometry": {"coordinates":[-117.4833,48.65],"type":"Point"}
}
=======
{"geometry":{"type":"Point","coordinates":[-117.483300,48.650000]},"type":"Feature","properties":{"hierarchy":["tgn:2339311","tgn:1000001","tgn:7012149","tgn:2002248","tgn:7007920","tgn:7029392"],"placetype":["aat:300008680"],"id":2339311,"name:xx":"Frater Lake"}}
>>>>>>> 03f74aca74312dbeaf24d7e61306dd6a786dc3d0
