{
  "id": 2019444,
  "type": "Feature",
  "properties": {
    "tgn:hierarchy":[
        "tgn:2019444",
        "tgn:1000001",
        "tgn:7012149",
        "tgn:1002977",
        "tgn:7007240",
        "tgn:7029392"
    ],
    "tgn:id":2019444,
    "tgn:name":"Glencoe",
    "tgn:placetype":[
        "aat:300008347"
    ]
},
  "bbox": [],
  "geometry": {"coordinates":[-80.9667,29.0167],"type":"Point"}
}