{
  "id": 2173467,
  "type": "Feature",
  "properties": {
    "tgn:hierarchy":[
        "tgn:2173467",
        "tgn:1000001",
        "tgn:7012149",
        "tgn:2000928",
        "tgn:7007515",
        "tgn:7029392"
    ],
    "tgn:id":2173467,
    "tgn:name":"Birch Island",
    "tgn:placetype":[
        "aat:300008791"
    ]
},
  "bbox": [],
  "geometry": {"coordinates":[-69.5167,45.2833],"type":"Point"}
}