{
  "id": 1049456,
  "type": "Feature",
  "properties": {
    "tgn:hierarchy":[
        "tgn:1049456",
        "tgn:1000003",
        "tgn:7024122",
        "tgn:7006366",
        "tgn:7029392"
    ],
    "tgn:id":1049456,
    "tgn:name":"Sierpc",
    "tgn:placetype":[
        "aat:300008347"
    ]
},
  "bbox": [],
  "geometry": {"coordinates":[19.6667,52.8667],"type":"Point"}
}