<<<<<<< HEAD
{
  "id": 2156968,
  "type": "Feature",
  "properties": {
    "tgn:hierarchy":[
        "tgn:2156968",
        "tgn:1000001",
        "tgn:7012149",
        "tgn:1002350",
        "tgn:7007157",
        "tgn:7029392"
    ],
    "tgn:id":2156968,
    "tgn:name":"Beauty Lake",
    "tgn:placetype":[
        "aat:300008680"
    ]
},
  "bbox": [],
  "geometry": {"coordinates":[-120.2333,38.85],"type":"Point"}
}
=======
{"geometry":{"type":"Point","coordinates":[-120.233300,38.850000]},"type":"Feature","properties":{"hierarchy":["tgn:2156968","tgn:1000001","tgn:7012149","tgn:1002350","tgn:7007157","tgn:7029392"],"placetype":["aat:300008680"],"id":2156968,"name:xx":"Beauty Lake"}}
>>>>>>> 03f74aca74312dbeaf24d7e61306dd6a786dc3d0
