{
  "id": 2616608,
  "type": "Feature",
  "properties": {
    "tgn:hierarchy":[
        "tgn:2616608",
        "tgn:1000001",
        "tgn:7012149",
        "tgn:2002111",
        "tgn:7007827",
        "tgn:7029392"
    ],
    "tgn:id":2616608,
    "tgn:name":"Rice Mountain",
    "tgn:placetype":[
        "aat:300008798"
    ]
},
  "bbox": [],
  "geometry": {"coordinates":[-114.0167,38.0167],"type":"Point"}
}