{
  "id": 2203292,
  "type": "Feature",
  "properties": {
    "tgn:hierarchy":[
        "tgn:2203292",
        "tgn:1000001",
        "tgn:7012149",
        "tgn:1002737",
        "tgn:7007520",
        "tgn:7029392"
    ],
    "tgn:id":2203292,
    "tgn:name":"Buckhorn Lake",
    "tgn:placetype":[
        "aat:300008680"
    ]
},
  "bbox": [],
  "geometry": {"coordinates":[-83.2333,42.7667],"type":"Point"}
}