{
  "id": 2370018,
  "type": "Feature",
  "properties": {
    "tgn:hierarchy":[
        "tgn:2370018",
        "tgn:1000001",
        "tgn:7012149",
        "tgn:2001708",
        "tgn:7007708",
        "tgn:7029392"
    ],
    "tgn:id":2370018,
    "tgn:name":"Gutridge Mine",
    "tgn:placetype":[
        "aat:300000390"
    ]
},
  "bbox": [],
  "geometry": {"coordinates":[-118.55,44.8667],"type":"Point"}
}