{
  "id": 7261597,
  "type": "Feature",
  "properties": {
    "tgn:concordances":{
        "gn:id":"2755737"
    },
    "tgn:hierarchy":[
        "tgn:7261597",
        "tgn:7003619",
        "tgn:1000003",
        "tgn:7016845",
        "tgn:7029392"
    ],
    "tgn:id":7261597,
    "tgn:name:nl":"Ganzert",
    "tgn:placetype":[
        "aat:300008347"
    ]
},
  "bbox": [],
  "geometry": {"coordinates":[5.466667,51.966667],"type":"Point"}
}