{
  "id": 7240080,
  "type": "Feature",
  "properties": {
    "tgn:hierarchy":[
        "tgn:7240080",
        "tgn:7003457",
        "tgn:1000003",
        "tgn:1000063",
        "tgn:7018236",
        "tgn:7029392"
    ],
    "tgn:id":7240080,
    "tgn:name":"Ekkelberg",
    "tgn:placetype":[
        "aat:300008347"
    ]
},
  "bbox": [],
  "geometry": {"coordinates":[4.05,50.716667],"type":"Point"}
}