{
  "id": 1010411,
  "type": "Feature",
  "properties": {
    "tgn:hierarchy":[
        "tgn:1010411",
        "tgn:7018452",
        "tgn:1001051",
        "tgn:1000004",
        "tgn:1000144",
        "tgn:7029392"
    ],
    "tgn:id":1010411,
    "tgn:name":"Incekum Burnu",
    "tgn:placetype":[
        "aat:300008850"
    ]
},
  "bbox": [],
  "geometry": {"coordinates":[33.9667,36.2333],"type":"Point"}
}