<<<<<<< HEAD
{
  "id": 2769581,
  "type": "Feature",
  "properties": {
    "tgn:hierarchy":[
        "tgn:2769581",
        "tgn:1000001",
        "tgn:7012149",
        "tgn:2001709",
        "tgn:7007708",
        "tgn:7029392"
    ],
    "tgn:id":2769581,
    "tgn:name":"Widow Spring",
    "tgn:placetype":[
        "aat:300008697"
    ]
},
  "bbox": [],
  "geometry": {"coordinates":[-118.9833,43.7333],"type":"Point"}
}
=======
{"geometry":{"type":"Point","coordinates":[-118.983300,43.733300]},"type":"Feature","properties":{"hierarchy":["tgn:2769581","tgn:1000001","tgn:7012149","tgn:2001709","tgn:7007708","tgn:7029392"],"placetype":["aat:300008697"],"id":2769581,"name:xx":"Widow Spring"}}
>>>>>>> 03f74aca74312dbeaf24d7e61306dd6a786dc3d0
