{
  "id": 2712496,
  "type": "Feature",
  "properties": {
    "tgn:hierarchy":[
        "tgn:2712496",
        "tgn:1000001",
        "tgn:7012149",
        "tgn:1002785",
        "tgn:7007920",
        "tgn:7029392"
    ],
    "tgn:id":2712496,
    "tgn:name":"Taylor Bay",
    "tgn:placetype":[
        "aat:300132316"
    ]
},
  "bbox": [],
  "geometry": {"coordinates":[-122.7667,47.1833],"type":"Point"}
}