<<<<<<< HEAD
{
  "id": 2762612,
  "type": "Feature",
  "properties": {
    "tgn:hierarchy":[
        "tgn:2762612",
        "tgn:1000001",
        "tgn:2000307",
        "tgn:7012149",
        "tgn:7007248",
        "tgn:7029392"
    ],
    "tgn:id":2762612,
    "tgn:name":"Westbrooke",
    "tgn:placetype":[
        "aat:300008347"
    ]
},
  "bbox": [],
  "geometry": {"coordinates":[-81.8,32.4167],"type":"Point"}
}
=======
{"geometry":{"type":"Point","coordinates":[-81.800000,32.416700]},"type":"Feature","properties":{"hierarchy":["tgn:2762612","tgn:1000001","tgn:2000307","tgn:7012149","tgn:7007248","tgn:7029392"],"placetype":["aat:300008347"],"id":2762612,"name:xx":"Westbrooke"}}
>>>>>>> 03f74aca74312dbeaf24d7e61306dd6a786dc3d0
