{
  "id": 2411925,
  "type": "Feature",
  "properties": {
    "tgn:hierarchy":[
        "tgn:2411925",
        "tgn:1000001",
        "tgn:1002284",
        "tgn:7012149",
        "tgn:7007568",
        "tgn:7029392"
    ],
    "tgn:id":2411925,
    "tgn:name":"Indian Point",
    "tgn:placetype":[
        "aat:300008850"
    ]
},
  "bbox": [],
  "geometry": {"coordinates":[-73.9667,44.7167],"type":"Point"}
}