{
  "id": 1055189,
  "type": "Feature",
  "properties": {
    "tgn:hierarchy":[
        "tgn:1055189",
        "tgn:1000003",
        "tgn:7011665",
        "tgn:7006660",
        "tgn:7029392"
    ],
    "tgn:id":1055189,
    "tgn:name":"Kazanka",
    "tgn:placetype":[
        "aat:300008347"
    ]
},
  "bbox": [],
  "geometry": {"coordinates":[32.8167,47.8333],"type":"Point"}
}