{
  "id": 7032784,
  "type": "Feature",
  "properties": {
    "tgn:hierarchy":[
        "tgn:7032784",
        "tgn:1002076",
        "tgn:1000004",
        "tgn:1000140",
        "tgn:7029392"
    ],
    "tgn:id":7032784,
    "tgn:name":"Tell Aswad",
    "tgn:placetype":[
        "aat:300008347",
        "aat:300000810",
        "aat:300019267"
    ]
},
  "bbox": [],
  "geometry": {"coordinates":[36.966,33.683],"type":"Point"}
}