{
  "id": 2089841,
  "type": "Feature",
  "properties": {
    "tgn:hierarchy":[
        "tgn:2089841",
        "tgn:1000001",
        "tgn:7012149",
        "tgn:1002945",
        "tgn:7007710",
        "tgn:7029392"
    ],
    "tgn:id":2089841,
    "tgn:name":"Knoxville",
    "tgn:placetype":[
        "aat:300008347"
    ]
},
  "bbox": [],
  "geometry": {"coordinates":[-77.4333,41.95],"type":"Point"}
}