{
  "id": 7573162,
  "type": "Feature",
  "properties": {
    "tgn:hierarchy":[
        "tgn:7573162",
        "tgn:1000004",
        "tgn:7031781",
        "tgn:7000198",
        "tgn:7029392"
    ],
    "tgn:id":7573162,
    "tgn:name:en":"J\u016bn\u0101garh",
    "tgn:placetype":[
        "aat:300008347"
    ]
},
  "bbox": [],
  "geometry": {"coordinates":[82.933333,19.866667],"type":"Point"}
}