{
  "id": 2145386,
  "type": "Feature",
  "properties": {
    "tgn:hierarchy":[
        "tgn:2145386",
        "tgn:1000001",
        "tgn:2001747",
        "tgn:7012149",
        "tgn:7007712",
        "tgn:7029392"
    ],
    "tgn:id":2145386,
    "tgn:name":"Bald Rock",
    "tgn:placetype":[
        "aat:300008798"
    ]
},
  "bbox": [],
  "geometry": {"coordinates":[-82.6167,35.0667],"type":"Point"}
}