<<<<<<< HEAD
{
  "id": 2763083,
  "type": "Feature",
  "properties": {
    "tgn:hierarchy":[
        "tgn:2763083",
        "tgn:1000001",
        "tgn:2000327",
        "tgn:7012149",
        "tgn:7007248",
        "tgn:7029392"
    ],
    "tgn:id":2763083,
    "tgn:name":"Westport",
    "tgn:placetype":[
        "aat:300008347"
    ]
},
  "bbox": [],
  "geometry": {"coordinates":[-82.0667,33.55],"type":"Point"}
}
=======
{"geometry":{"type":"Point","coordinates":[-82.066700,33.550000]},"type":"Feature","properties":{"hierarchy":["tgn:2763083","tgn:1000001","tgn:2000327","tgn:7012149","tgn:7007248","tgn:7029392"],"placetype":["aat:300008347"],"id":2763083,"name:xx":"Westport"}}
>>>>>>> 03f74aca74312dbeaf24d7e61306dd6a786dc3d0
