{
  "id": 2500194,
  "type": "Feature",
  "properties": {
    "tgn:hierarchy":[
        "tgn:2500194",
        "tgn:1000001",
        "tgn:7012149",
        "tgn:7029392"
    ],
    "tgn:id":2500194,
    "tgn:name":"McCullough Run",
    "tgn:placetype":[
        "aat:300008699"
    ]
},
  "bbox": [],
  "geometry": {"coordinates":[-80.5667,41.2833],"type":"Point"}
}