{
  "id": 2055699,
  "type": "Feature",
  "properties": {
    "tgn:hierarchy":[
        "tgn:2055699",
        "tgn:1000001",
        "tgn:7012149",
        "tgn:2001066",
        "tgn:7007521",
        "tgn:7029392"
    ],
    "tgn:id":2055699,
    "tgn:name":"Wannaska",
    "tgn:placetype":[
        "aat:300008347"
    ]
},
  "bbox": [],
  "geometry": {"coordinates":[-95.7333,48.65],"type":"Point"}
}