{
  "id": 7511620,
  "type": "Feature",
  "properties": {
    "tgn:hierarchy":[
        "tgn:7511620",
        "tgn:1009227",
        "tgn:1000226",
        "tgn:7018437",
        "tgn:1000006",
        "tgn:7029392"
    ],
    "tgn:id":7511620,
    "tgn:name:en":"Long Spur",
    "tgn:placetype":[
        "aat:300387002"
    ]
},
  "bbox": [],
  "geometry": {"coordinates":[170.066667,-44.833333],"type":"Point"}
}