{
  "id": 2468760,
  "type": "Feature",
  "properties": {
    "tgn:hierarchy":[
        "tgn:2468760",
        "tgn:1000001",
        "tgn:7012149",
        "tgn:7007157",
        "tgn:1002869",
        "tgn:7029392"
    ],
    "tgn:id":2468760,
    "tgn:name":"Long Ridge",
    "tgn:placetype":[
        "aat:300266640"
    ]
},
  "bbox": [],
  "geometry": {"coordinates":[-121.65,36.9333],"type":"Point"}
}