<<<<<<< HEAD
{
  "id": 2331408,
  "type": "Feature",
  "properties": {
    "tgn:hierarchy":[
        "tgn:2331408",
        "tgn:1000001",
        "tgn:7012149",
        "tgn:2002098",
        "tgn:7007826",
        "tgn:7029392"
    ],
    "tgn:id":2331408,
    "tgn:name":"Flatrock Creek",
    "tgn:placetype":[
        "aat:300008706"
    ]
},
  "bbox": [],
  "geometry": {"coordinates":[-98.4833,33.0667],"type":"Point"}
}
=======
{"geometry":{"type":"Point","coordinates":[-98.483300,33.066700]},"type":"Feature","properties":{"hierarchy":["tgn:2331408","tgn:1000001","tgn:7012149","tgn:2002098","tgn:7007826","tgn:7029392"],"placetype":["aat:300008706"],"id":2331408,"name:xx":"Flatrock Creek"}}
>>>>>>> 03f74aca74312dbeaf24d7e61306dd6a786dc3d0
