{
  "id": 2678607,
  "type": "Feature",
  "properties": {
    "tgn:hierarchy":[
        "tgn:2678607",
        "tgn:1000001",
        "tgn:7012149",
        "tgn:2002247",
        "tgn:7007920",
        "tgn:7029392"
    ],
    "tgn:id":2678607,
    "tgn:name":"South Fork Deep Creek",
    "tgn:placetype":[
        "aat:300008706"
    ]
},
  "bbox": [],
  "geometry": {"coordinates":[-117.8667,47.6333],"type":"Point"}
}