<<<<<<< HEAD
{
  "id": 2158483,
  "type": "Feature",
  "properties": {
    "tgn:hierarchy":[
        "tgn:2158483",
        "tgn:1000001",
        "tgn:7012149",
        "tgn:2001709",
        "tgn:7007708",
        "tgn:7029392"
    ],
    "tgn:id":2158483,
    "tgn:name":"Beaverdam Creek",
    "tgn:placetype":[
        "aat:300008706"
    ]
},
  "bbox": [],
  "geometry": {"coordinates":[-119.2833,43.8333],"type":"Point"}
}
=======
{"geometry":{"type":"Point","coordinates":[-119.283300,43.833300]},"type":"Feature","properties":{"hierarchy":["tgn:2158483","tgn:1000001","tgn:7012149","tgn:2001709","tgn:7007708","tgn:7029392"],"placetype":["aat:300008706"],"id":2158483,"name:xx":"Beaverdam Creek"}}
>>>>>>> 03f74aca74312dbeaf24d7e61306dd6a786dc3d0
