{
  "id": 2389562,
  "type": "Feature",
  "properties": {
    "tgn:hierarchy":[
        "tgn:2389562",
        "tgn:1000001",
        "tgn:7016172",
        "tgn:7012149",
        "tgn:2000148",
        "tgn:7029392"
    ],
    "tgn:id":2389562,
    "tgn:name":"High Davey Mountain",
    "tgn:placetype":[
        "aat:300008798"
    ]
},
  "bbox": [],
  "geometry": {"coordinates":[-93.7333,35.8167],"type":"Point"}
}