{
  "id": 7494588,
  "type": "Feature",
  "properties": {
    "tgn:hierarchy":[
        "tgn:7494588",
        "tgn:7488858",
        "tgn:1000004",
        "tgn:1000141",
        "tgn:7029392"
    ],
    "tgn:id":7494588,
    "tgn:name":"Kengzinei",
    "tgn:placetype":[
        "aat:300008347"
    ]
},
  "bbox": [],
  "geometry": {"coordinates":[120.622754,23.954321],"type":"Point"}
}