{
  "id": 7265251,
  "type": "Feature",
  "properties": {
    "tgn:concordances":{
        "gn:id":"2752124"
    },
    "tgn:hierarchy":[
        "tgn:7265251",
        "tgn:1000003",
        "tgn:7003632",
        "tgn:7016845",
        "tgn:7029392"
    ],
    "tgn:id":7265251,
    "tgn:name:nl":"Laag-Blokland",
    "tgn:placetype":[
        "aat:300008347"
    ]
},
  "bbox": [],
  "geometry": {"coordinates":[4.85,51.883333],"type":"Point"}
}