{
  "id": 2565666,
  "type": "Feature",
  "properties": {
    "tgn:hierarchy":[
        "tgn:2565666",
        "tgn:1002648",
        "tgn:1000001",
        "tgn:7019158",
        "tgn:7012149",
        "tgn:7007249",
        "tgn:7029392"
    ],
    "tgn:id":2565666,
    "tgn:name":"Pakaoao",
    "tgn:placetype":[
        "aat:300008798"
    ]
},
  "bbox": [],
  "geometry": {"coordinates":[-156.25,20.7167],"type":"Point"}
}