{
  "id": 2501903,
  "type": "Feature",
  "properties": {
    "tgn:hierarchy":[
        "tgn:2501903",
        "tgn:1000001",
        "tgn:7012149",
        "tgn:1002751",
        "tgn:7007568",
        "tgn:7029392"
    ],
    "tgn:id":2501903,
    "tgn:name":"McKeags Meadow",
    "tgn:placetype":[
        "aat:300008905"
    ]
},
  "bbox": [],
  "geometry": {"coordinates":[-74.2333,41.1667],"type":"Point"}
}