<<<<<<< HEAD
{
  "id": 7485387,
  "type": "Feature",
  "properties": {
    "tgn:hierarchy":[
        "tgn:7485387",
        "tgn:1000004",
        "tgn:7467799",
        "tgn:1000141",
        "tgn:7029392"
    ],
    "tgn:id":7485387,
    "tgn:name":"Buyan Guozhong",
    "tgn:placetype":[
        "aat:300006495"
    ]
},
  "bbox": [],
  "geometry": {"coordinates":[120.466389,24.0],"type":"Point"}
}
=======
{"geometry":{"type":"Point","coordinates":[120.466389,24.000000]},"type":"Feature","properties":{"hierarchy":["tgn:7485387","tgn:1000004","tgn:7467799","tgn:1000141","tgn:7029392"],"placetype":["aat:300006495"],"id":7485387,"name:xx":"Buyan Guozhong"}}
>>>>>>> 03f74aca74312dbeaf24d7e61306dd6a786dc3d0
