{
  "id": 2734487,
  "type": "Feature",
  "properties": {
    "tgn:hierarchy":[
        "tgn:2734487",
        "tgn:1000001",
        "tgn:2002242",
        "tgn:7012149",
        "tgn:7007920",
        "tgn:7029392"
    ],
    "tgn:id":2734487,
    "tgn:name":"Turtle Rock",
    "tgn:placetype":[
        "aat:300008798"
    ]
},
  "bbox": [],
  "geometry": {"coordinates":[-120.25,47.55],"type":"Point"}
}