{
  "id": 1087620,
  "type": "Feature",
  "properties": {
    "tgn:hierarchy":[
        "tgn:1087620",
        "tgn:1000815",
        "tgn:7001242",
        "tgn:1000149",
        "tgn:7029392"
    ],
    "tgn:id":1087620,
    "tgn:name":"Andulo",
    "tgn:placetype":[
        "aat:300008347"
    ]
},
  "bbox": [],
  "geometry": {"coordinates":[16.7167,-11.4833],"type":"Point"}
}