{
  "id": 2318543,
  "type": "Feature",
  "properties": {
    "tgn:hierarchy":[
        "tgn:2318543",
        "tgn:1000001",
        "tgn:7012149",
        "tgn:2000230",
        "tgn:7007158",
        "tgn:7029392"
    ],
    "tgn:id":2318543,
    "tgn:name":"Erie Canal",
    "tgn:placetype":[
        "aat:300006075"
    ]
},
  "bbox": [],
  "geometry": {"coordinates":[-107.7667,39.2333],"type":"Point"}
}