<<<<<<< HEAD
{
  "id": 2155921,
  "type": "Feature",
  "properties": {
    "tgn:hierarchy":[
        "tgn:2155921",
        "tgn:1000001",
        "tgn:7012149",
        "tgn:7007157",
        "tgn:2000187",
        "tgn:7029392"
    ],
    "tgn:id":2155921,
    "tgn:name":"Bear Valley Creek",
    "tgn:placetype":[
        "aat:300008706"
    ]
},
  "bbox": [],
  "geometry": {"coordinates":[-120.7,40.2833],"type":"Point"}
}
=======
{"geometry":{"type":"Point","coordinates":[-120.700000,40.283300]},"type":"Feature","properties":{"hierarchy":["tgn:2155921","tgn:1000001","tgn:7012149","tgn:7007157","tgn:2000187","tgn:7029392"],"placetype":["aat:300008706"],"id":2155921,"name:xx":"Bear Valley Creek"}}
>>>>>>> 03f74aca74312dbeaf24d7e61306dd6a786dc3d0
