{
  "id": 7396368,
  "type": "Feature",
  "properties": {
    "tgn:hierarchy":[
        "tgn:7396368",
        "tgn:7005578",
        "tgn:1000001",
        "tgn:7005560",
        "tgn:7029392"
    ],
    "tgn:id":7396368,
    "tgn:name":"Santa Rita",
    "tgn:placetype":[
        "aat:300008347"
    ]
},
  "bbox": [],
  "geometry": {"coordinates":[-92.016667,18.25],"type":"Point"}
}