{
  "id": 1031914,
  "type": "Feature",
  "properties": {
    "tgn:hierarchy":[
        "tgn:1031914",
        "tgn:1000003",
        "tgn:7002888",
        "tgn:1000070",
        "tgn:7029392"
    ],
    "tgn:id":1031914,
    "tgn:name":"Aumetz",
    "tgn:placetype":[
        "aat:300008347"
    ]
},
  "bbox": [],
  "geometry": {"coordinates":[5.95,49.4167],"type":"Point"}
}