<<<<<<< HEAD
{
  "id": 2150866,
  "type": "Feature",
  "properties": {
    "tgn:hierarchy":[
        "tgn:2150866",
        "tgn:1000001",
        "tgn:7012149",
        "tgn:2002250",
        "tgn:7007920",
        "tgn:7029392"
    ],
    "tgn:id":2150866,
    "tgn:name":"Bass Lake",
    "tgn:placetype":[
        "aat:300008680"
    ]
},
  "bbox": [],
  "geometry": {"coordinates":[-117.9833,48.6167],"type":"Point"}
}
=======
{"geometry":{"type":"Point","coordinates":[-117.983300,48.616700]},"type":"Feature","properties":{"hierarchy":["tgn:2150866","tgn:1000001","tgn:7012149","tgn:2002250","tgn:7007920","tgn:7029392"],"placetype":["aat:300008680"],"id":2150866,"name:xx":"Bass Lake"}}
>>>>>>> 03f74aca74312dbeaf24d7e61306dd6a786dc3d0
