{
  "id": 2524007,
  "type": "Feature",
  "properties": {
    "tgn:hierarchy":[
        "tgn:2524007",
        "tgn:1000001",
        "tgn:7012149",
        "tgn:1002785",
        "tgn:7007920",
        "tgn:7029392"
    ],
    "tgn:id":2524007,
    "tgn:name":"Morey Creek",
    "tgn:placetype":[
        "aat:300008706"
    ]
},
  "bbox": [],
  "geometry": {"coordinates":[-122.4667,47.1167],"type":"Point"}
}