{
  "id": 2680161,
  "type": "Feature",
  "properties": {
    "tgn:hierarchy":[
        "tgn:2680161",
        "tgn:1000001",
        "tgn:7012149",
        "tgn:2002123",
        "tgn:7007827",
        "tgn:7029392"
    ],
    "tgn:id":2680161,
    "tgn:name":"South Fork Swensons Canyon",
    "tgn:placetype":[
        "aat:300008761"
    ]
},
  "bbox": [],
  "geometry": {"coordinates":[-112.1833,40.55],"type":"Point"}
}