{
  "id": 2696895,
  "type": "Feature",
  "properties": {
    "tgn:hierarchy":[
        "tgn:2696895",
        "tgn:1000001",
        "tgn:7012149",
        "tgn:2000410",
        "tgn:7007248",
        "tgn:7029392"
    ],
    "tgn:id":2696895,
    "tgn:name":"Stonewall Creek",
    "tgn:placetype":[
        "aat:300008706"
    ]
},
  "bbox": [],
  "geometry": {"coordinates":[-83.4833,34.8333],"type":"Point"}
}