<<<<<<< HEAD
{
  "id": 7171588,
  "type": "Feature",
  "properties": {
    "tgn:hierarchy":[
        "tgn:7171588",
        "tgn:1000003",
        "tgn:7003678",
        "tgn:7000084",
        "tgn:7029392"
    ],
    "tgn:id":7171588,
    "tgn:name":"Hillershausen",
    "tgn:placetype":[
        "aat:300008347"
    ]
},
  "bbox": [],
  "geometry": {"coordinates":[8.75,51.216667],"type":"Point"}
}
=======
{"geometry":{"type":"Point","coordinates":[8.750000,51.216667]},"type":"Feature","properties":{"hierarchy":["tgn:7171588","tgn:1000003","tgn:7003678","tgn:7000084","tgn:7029392"],"placetype":["aat:300008347"],"id":7171588,"name:xx":"Hillershausen"}}
>>>>>>> 03f74aca74312dbeaf24d7e61306dd6a786dc3d0
