{
  "id": 7537932,
  "type": "Feature",
  "properties": {
    "tgn:hierarchy":[
        "tgn:7537932",
        "tgn:7001242",
        "tgn:7016833",
        "tgn:1001113",
        "tgn:7029392"
    ],
    "tgn:id":7537932,
    "tgn:name:en":"M\u012bt Suhayl",
    "tgn:placetype":[
        "aat:300008347"
    ]
},
  "bbox": [],
  "geometry": {"coordinates":[31.410304,30.426289],"type":"Point"}
}