{
  "id": 2699376,
  "type": "Feature",
  "properties": {
    "tgn:hierarchy":[
        "tgn:2699376",
        "tgn:1000001",
        "tgn:1002271",
        "tgn:7012149",
        "tgn:7007920",
        "tgn:7029392"
    ],
    "tgn:id":2699376,
    "tgn:name":"Striped Peak",
    "tgn:placetype":[
        "aat:300008798"
    ]
},
  "bbox": [],
  "geometry": {"coordinates":[-123.6833,48.15],"type":"Point"}
}