<<<<<<< HEAD
{
  "id": 7484416,
  "type": "Feature",
  "properties": {
    "tgn:hierarchy":[
        "tgn:7484416",
        "tgn:7001004",
        "tgn:1000004",
        "tgn:1000141",
        "tgn:7029392"
    ],
    "tgn:id":7484416,
    "tgn:name":"Huoshaoniu Shan",
    "tgn:placetype":[
        "aat:300008798"
    ]
},
  "bbox": [],
  "geometry": {"coordinates":[120.646389,23.041111],"type":"Point"}
}
=======
{"geometry":{"type":"Point","coordinates":[120.646389,23.041111]},"type":"Feature","properties":{"hierarchy":["tgn:7484416","tgn:7001004","tgn:1000004","tgn:1000141","tgn:7029392"],"placetype":["aat:300008798"],"id":7484416,"name:xx":"Huoshaoniu Shan"}}
>>>>>>> 03f74aca74312dbeaf24d7e61306dd6a786dc3d0
