{
  "id": 7484416,
  "type": "Feature",
  "properties": {
    "tgn:hierarchy":[
        "tgn:7484416",
        "tgn:7001004",
        "tgn:1000004",
        "tgn:1000141",
        "tgn:7029392"
    ],
    "tgn:id":7484416,
    "tgn:name":"Huoshaoniu Shan",
    "tgn:placetype":[
        "aat:300008798"
    ]
},
  "bbox": [],
  "geometry": {"coordinates":[120.646389,23.041111],"type":"Point"}
}