{
  "id": 2149715,
  "type": "Feature",
  "properties": {
    "tgn:hierarchy":[
        "tgn:2149715",
        "tgn:1000001",
        "tgn:7012149",
        "tgn:7007157",
        "tgn:2000191",
        "tgn:7029392"
    ],
    "tgn:id":2149715,
    "tgn:name":"Barry Creek Mine",
    "tgn:placetype":[
        "aat:300000390"
    ]
},
  "bbox": [],
  "geometry": {"coordinates":[-123.2667,40.1833],"type":"Point"}
}