<<<<<<< HEAD
{
  "id": 2250441,
  "type": "Feature",
  "properties": {
    "tgn:hierarchy":[
        "tgn:2250441",
        "tgn:1000001",
        "tgn:7012149",
        "tgn:1002451",
        "tgn:7007919",
        "tgn:7029392"
    ],
    "tgn:id":2250441,
    "tgn:name":"Colonial Forest Lake",
    "tgn:placetype":[
        "aat:300006191"
    ]
},
  "bbox": [],
  "geometry": {"coordinates":[-77.35,37.6833],"type":"Point"}
}
=======
{"geometry":{"type":"Point","coordinates":[-77.350000,37.683300]},"type":"Feature","properties":{"hierarchy":["tgn:2250441","tgn:1000001","tgn:7012149","tgn:1002451","tgn:7007919","tgn:7029392"],"placetype":["aat:300006191"],"id":2250441,"name:xx":"Colonial Forest Lake"}}
>>>>>>> 03f74aca74312dbeaf24d7e61306dd6a786dc3d0
