{
  "id": 2250441,
  "type": "Feature",
  "properties": {
    "tgn:hierarchy":[
        "tgn:2250441",
        "tgn:1000001",
        "tgn:7012149",
        "tgn:1002451",
        "tgn:7007919",
        "tgn:7029392"
    ],
    "tgn:id":2250441,
    "tgn:name":"Colonial Forest Lake",
    "tgn:placetype":[
        "aat:300006191"
    ]
},
  "bbox": [],
  "geometry": {"coordinates":[-77.35,37.6833],"type":"Point"}
}