{
  "id": 2664644,
  "type": "Feature",
  "properties": {
    "tgn:hierarchy":[
        "tgn:2664644",
        "tgn:1000001",
        "tgn:2002367",
        "tgn:7012149",
        "tgn:7007923",
        "tgn:7029392"
    ],
    "tgn:id":2664644,
    "tgn:name":"Simmons Draw",
    "tgn:placetype":[
        "aat:300008761"
    ]
},
  "bbox": [],
  "geometry": {"coordinates":[-105.8833,43.5667],"type":"Point"}
}