{
  "id": 2465237,
  "type": "Feature",
  "properties": {
    "tgn:hierarchy":[
        "tgn:2465237",
        "tgn:1000001",
        "tgn:7012149",
        "tgn:7007157",
        "tgn:1002869",
        "tgn:7029392"
    ],
    "tgn:id":2465237,
    "tgn:name":"Lompico Creek",
    "tgn:placetype":[
        "aat:300008706"
    ]
},
  "bbox": [],
  "geometry": {"coordinates":[-122.0333,37.1333],"type":"Point"}
}