<<<<<<< HEAD
{
  "id": 2404855,
  "type": "Feature",
  "properties": {
    "tgn:hierarchy":[
        "tgn:2404855",
        "tgn:1000001",
        "tgn:7012149",
        "tgn:2002052",
        "tgn:7007826",
        "tgn:7029392"
    ],
    "tgn:id":2404855,
    "tgn:name":"Huckleberry Ridge",
    "tgn:placetype":[
        "aat:300266640"
    ]
},
  "bbox": [],
  "geometry": {"coordinates":[-94.0667,30.1667],"type":"Point"}
}
=======
{"geometry":{"type":"Point","coordinates":[-94.066700,30.166700]},"type":"Feature","properties":{"hierarchy":["tgn:2404855","tgn:1000001","tgn:7012149","tgn:2002052","tgn:7007826","tgn:7029392"],"placetype":["aat:300266640"],"id":2404855,"name:xx":"Huckleberry Ridge"}}
>>>>>>> 03f74aca74312dbeaf24d7e61306dd6a786dc3d0
