{
  "id": 2307375,
  "type": "Feature",
  "properties": {
    "tgn:hierarchy":[
        "tgn:2307375",
        "tgn:1000001",
        "tgn:7012149",
        "tgn:2002189",
        "tgn:7007919",
        "tgn:7029392"
    ],
    "tgn:id":2307375,
    "tgn:name":"East Fork Roberts Creek",
    "tgn:placetype":[
        "aat:300008706"
    ]
},
  "bbox": [],
  "geometry": {"coordinates":[-82.3833,36.6167],"type":"Point"}
}