{
  "id": 2135600,
  "type": "Feature",
  "properties": {
    "tgn:hierarchy":[
        "tgn:2135600",
        "tgn:1000001",
        "tgn:2001638",
        "tgn:7012149",
        "tgn:7007707",
        "tgn:7029392"
    ],
    "tgn:id":2135600,
    "tgn:name":"Apache Lake",
    "tgn:placetype":[
        "aat:300006191"
    ]
},
  "bbox": [],
  "geometry": {"coordinates":[-98.6667,34.7333],"type":"Point"}
}