{
  "id": 7590397,
  "type": "Feature",
  "properties": {
    "tgn:hierarchy":[
        "tgn:7590397",
        "tgn:1000004",
        "tgn:7000198",
        "tgn:7000799",
        "tgn:7029392"
    ],
    "tgn:id":7590397,
    "tgn:name:en":"Muhri",
    "tgn:placetype":[
        "aat:300008347"
    ]
},
  "bbox": [],
  "geometry": {"coordinates":[74.35,33.776389],"type":"Point"}
}