{
  "id": 2356864,
  "type": "Feature",
  "properties": {
    "tgn:hierarchy":[
        "tgn:2356864",
        "tgn:1000001",
        "tgn:7012149",
        "tgn:2001768",
        "tgn:7007712",
        "tgn:7029392"
    ],
    "tgn:id":2356864,
    "tgn:name":"Goshen Hill",
    "tgn:placetype":[
        "aat:300008347"
    ]
},
  "bbox": [],
  "geometry": {"coordinates":[-81.55,34.5167],"type":"Point"}
}