{
  "id": 2708505,
  "type": "Feature",
  "properties": {
    "tgn:hierarchy":[
        "tgn:2708505",
        "tgn:1000001",
        "tgn:7012149",
        "tgn:2001206",
        "tgn:7007523",
        "tgn:7029392"
    ],
    "tgn:id":2708505,
    "tgn:name":"Sycamore Hollow",
    "tgn:placetype":[
        "aat:300008761"
    ]
},
  "bbox": [],
  "geometry": {"coordinates":[-91.7833,36.55],"type":"Point"}
}