{
  "id": 1090854,
  "type": "Feature",
  "properties": {
    "tgn:hierarchy":[
        "tgn:1090854",
        "tgn:7001242",
        "tgn:1001405",
        "tgn:1000173",
        "tgn:7029392"
    ],
    "tgn:id":1090854,
    "tgn:name":"Bekopaka",
    "tgn:placetype":[
        "aat:300008347"
    ]
},
  "bbox": [],
  "geometry": {"coordinates":[44.7833,-19.1167],"type":"Point"}
}