{
  "id": 1051915,
  "type": "Feature",
  "properties": {
    "tgn:hierarchy":[
        "tgn:1051915",
        "tgn:1000004",
        "tgn:7011573",
        "tgn:7018214",
        "tgn:7002435",
        "tgn:7029392"
    ],
    "tgn:id":1051915,
    "tgn:name":"Abramtsevo",
    "tgn:placetype":[
        "aat:300008347"
    ]
},
  "bbox": [],
  "geometry": {"coordinates":[37.8333,55.8333],"type":"Point"}
}