{
  "id": 7268913,
  "type": "Feature",
  "properties": {
    "tgn:hierarchy":[
        "tgn:7268913",
        "tgn:1000003",
        "tgn:7003627",
        "tgn:7016845",
        "tgn:7029392"
    ],
    "tgn:id":7268913,
    "tgn:name:nl":"Oudaen",
    "tgn:placetype":[
        "aat:300387502"
    ]
},
  "bbox": [],
  "geometry": {"coordinates":[5.016667,52.166667],"type":"Point"}
}