{
  "id": 7455812,
  "type": "Feature",
  "properties": {
    "tgn:hierarchy":[
        "tgn:7455812",
        "tgn:5000432",
        "tgn:7002444",
        "tgn:1000003",
        "tgn:7008591",
        "tgn:7029392"
    ],
    "tgn:id":7455812,
    "tgn:name:en":"Carvie, Water of",
    "tgn:placetype":[
        "aat:300008699"
    ]
},
  "bbox": [],
  "geometry": {"coordinates":[-3.083333,57.166667],"type":"Point"}
}