{
  "id": 2422334,
  "type": "Feature",
  "properties": {
    "tgn:hierarchy":[
        "tgn:2422334",
        "tgn:1000001",
        "tgn:7012149",
        "tgn:2000528",
        "tgn:7007251",
        "tgn:7029392"
    ],
    "tgn:id":2422334,
    "tgn:name":"Jimmy Creek",
    "tgn:placetype":[
        "aat:300008706"
    ]
},
  "bbox": [],
  "geometry": {"coordinates":[-90.5667,41.4333],"type":"Point"}
}