{
  "id": 7406232,
  "type": "Feature",
  "properties": {
    "tgn:hierarchy":[
        "tgn:7406232",
        "tgn:7005578",
        "tgn:1000001",
        "tgn:7005560",
        "tgn:7029392"
    ],
    "tgn:id":7406232,
    "tgn:name":"Manuel Crescencio Rej\u00f3n",
    "tgn:placetype":[
        "aat:300008347"
    ]
},
  "bbox": [],
  "geometry": {"coordinates":[-89.241667,17.925],"type":"Point"}
}