{
  "id": 7003037,
  "type": "Feature",
  "properties": {
    "tgn:hierarchy":[
        "tgn:7003037",
        "tgn:7003006",
        "tgn:1000003",
        "tgn:7002997",
        "tgn:1000080",
        "tgn:7029392"
    ],
    "tgn:id":7003037,
    "tgn:name":"Chioggia",
    "tgn:placetype":[
        "aat:300008347",
        "aat:300008375",
        "aat:300120599"
    ]
},
  "bbox": [],
  "geometry": {"coordinates":[12.288889,45.225556],"type":"Point"}
}