{
  "id": 2705813,
  "type": "Feature",
  "properties": {
    "tgn:hierarchy":[
        "tgn:2705813",
        "tgn:1000001",
        "tgn:2001411",
        "tgn:7012149",
        "tgn:7007526",
        "tgn:7029392"
    ],
    "tgn:id":2705813,
    "tgn:name":"Suttle Spring",
    "tgn:placetype":[
        "aat:300008697"
    ]
},
  "bbox": [],
  "geometry": {"coordinates":[-116.1667,41.2333],"type":"Point"}
}