<<<<<<< HEAD
{
  "id": 7470990,
  "type": "Feature",
  "properties": {
    "tgn:hierarchy":[
        "tgn:7470990",
        "tgn:1000004",
        "tgn:7491221",
        "tgn:1000141",
        "tgn:7029392"
    ],
    "tgn:id":7470990,
    "tgn:name":"Jingfeng",
    "tgn:placetype":[
        "aat:300008347"
    ]
},
  "bbox": [],
  "geometry": {"coordinates":[121.140966,22.989271],"type":"Point"}
}
=======
{"geometry":{"type":"Point","coordinates":[121.140966,22.989271]},"type":"Feature","properties":{"hierarchy":["tgn:7470990","tgn:1000004","tgn:7491221","tgn:1000141","tgn:7029392"],"placetype":["aat:300008347"],"id":7470990,"name:xx":"Jingfeng"}}
>>>>>>> 03f74aca74312dbeaf24d7e61306dd6a786dc3d0
