{
  "id": 2222466,
  "type": "Feature",
  "properties": {
    "tgn:hierarchy":[
        "tgn:2222466",
        "tgn:1000001",
        "tgn:7012149",
        "tgn:1002406",
        "tgn:7007520",
        "tgn:7029392"
    ],
    "tgn:id":2222466,
    "tgn:name":"Carpenter Drain",
    "tgn:placetype":[
        "aat:300006075"
    ]
},
  "bbox": [],
  "geometry": {"coordinates":[-83.6167,43.0667],"type":"Point"}
}