{
  "id": 1021322,
  "type": "Feature",
  "properties": {
    "tgn:hierarchy":[
        "tgn:1021322",
        "tgn:7006237",
        "tgn:1000047",
        "tgn:7002457",
        "tgn:1000002",
        "tgn:7029392"
    ],
    "tgn:id":1021322,
    "tgn:name":"Descoberto",
    "tgn:placetype":[
        "aat:300008347"
    ]
},
  "bbox": [],
  "geometry": {"coordinates":[-42.9667,-21.45],"type":"Point"}
}