{
  "id": 2209724,
  "type": "Feature",
  "properties": {
    "tgn:hierarchy":[
        "tgn:2209724",
        "tgn:1000001",
        "tgn:7012149",
        "tgn:2001453",
        "tgn:7007566",
        "tgn:7029392"
    ],
    "tgn:id":2209724,
    "tgn:name":"Burro Canyon",
    "tgn:placetype":[
        "aat:300008761"
    ]
},
  "bbox": [],
  "geometry": {"coordinates":[-105.55,35.7667],"type":"Point"}
}