<<<<<<< HEAD
{
  "id": 7026658,
  "type": "Feature",
  "properties": {
    "tgn:hierarchy":[
        "tgn:7026658",
        "tgn:7002445",
        "tgn:1000003",
        "tgn:7008132",
        "tgn:7008591",
        "tgn:7029392"
    ],
    "tgn:id":7026658,
    "tgn:name":"Hilcot",
    "tgn:placetype":[
        "aat:300008347",
        "aat:300008372"
    ]
},
  "bbox": [],
  "geometry": {"coordinates":[-2.0167,51.85],"type":"Point"}
}
=======
{"geometry":{"type":"Point","coordinates":[-2.016700,51.850000]},"type":"Feature","properties":{"hierarchy":["tgn:7026658","tgn:7002445","tgn:1000003","tgn:7008132","tgn:7008591","tgn:7029392"],"placetype":["aat:300008347","aat:300008372"],"id":7026658,"name:xx":"Hilcot"}}
>>>>>>> 03f74aca74312dbeaf24d7e61306dd6a786dc3d0
