{
  "id": 2333271,
  "type": "Feature",
  "properties": {
    "tgn:hierarchy":[
        "tgn:2333271",
        "tgn:1000001",
        "tgn:2001809",
        "tgn:7012149",
        "tgn:7007713",
        "tgn:7029392"
    ],
    "tgn:id":2333271,
    "tgn:name":"Fods Slough",
    "tgn:placetype":[
        "aat:300008905"
    ]
},
  "bbox": [],
  "geometry": {"coordinates":[-97.0833,43.9167],"type":"Point"}
}