<<<<<<< HEAD
{
  "id": 2333271,
  "type": "Feature",
  "properties": {
    "tgn:hierarchy":[
        "tgn:2333271",
        "tgn:1000001",
        "tgn:2001809",
        "tgn:7012149",
        "tgn:7007713",
        "tgn:7029392"
    ],
    "tgn:id":2333271,
    "tgn:name":"Fods Slough",
    "tgn:placetype":[
        "aat:300008905"
    ]
},
  "bbox": [],
  "geometry": {"coordinates":[-97.0833,43.9167],"type":"Point"}
}
=======
{"geometry":{"type":"Point","coordinates":[-97.083300,43.916700]},"type":"Feature","properties":{"hierarchy":["tgn:2333271","tgn:1000001","tgn:2001809","tgn:7012149","tgn:7007713","tgn:7029392"],"placetype":["aat:300008905"],"id":2333271,"name:xx":"Fods Slough"}}
>>>>>>> 03f74aca74312dbeaf24d7e61306dd6a786dc3d0
