{
  "id": 7003672,
  "type": "Feature",
  "properties": {
    "tgn:hierarchy":[
        "tgn:7003672",
        "tgn:1000003",
        "tgn:7000084",
        "tgn:7029392"
    ],
    "tgn:id":7003672,
    "tgn:name:de":"Bremen",
    "tgn:placetype":[
        "aat:300387064",
        "aat:300000776"
    ]
},
  "bbox": [],
  "geometry": {"coordinates":[8.8333,53.05],"type":"Point"}
}