{
  "id": 2742803,
  "type": "Feature",
  "properties": {
    "tgn:hierarchy":[
        "tgn:2742803",
        "tgn:1000001",
        "tgn:7012149",
        "tgn:7007250",
        "tgn:7029392"
    ],
    "tgn:id":2742803,
    "tgn:name":"Van Duzer Lateral",
    "tgn:placetype":[
        "aat:300006075"
    ]
},
  "bbox": [],
  "geometry": {"coordinates":[-116.4667,43.4667],"type":"Point"}
}