{
  "id": 1014836,
  "type": "Feature",
  "properties": {
    "tgn:hierarchy":[
        "tgn:1014836",
        "tgn:7005685",
        "tgn:1000001",
        "tgn:7013154",
        "tgn:7029392"
    ],
    "tgn:id":1014836,
    "tgn:name":"Inglewood",
    "tgn:placetype":[
        "aat:300008347"
    ]
},
  "bbox": [],
  "geometry": {"coordinates":[-79.9333,43.7833],"type":"Point"}
}