{
  "id": 7226481,
  "type": "Feature",
  "properties": {
    "tgn:hierarchy":[
        "tgn:7226481",
        "tgn:7002711",
        "tgn:7001338",
        "tgn:1000003",
        "tgn:1000074",
        "tgn:7029392"
    ],
    "tgn:id":7226481,
    "tgn:name":"Sokr\u00e1kion",
    "tgn:placetype":[
        "aat:300008347"
    ]
},
  "bbox": [],
  "geometry": {"coordinates":[19.789722,39.715],"type":"Point"}
}