<<<<<<< HEAD
{
  "id": 2401562,
  "type": "Feature",
  "properties": {
    "tgn:hierarchy":[
        "tgn:2401562",
        "tgn:1000001",
        "tgn:7012149",
        "tgn:2001874",
        "tgn:7007825",
        "tgn:7029392"
    ],
    "tgn:id":2401562,
    "tgn:name":"Horseshoe Cutoff",
    "tgn:placetype":[
        "aat:300008680"
    ]
},
  "bbox": [],
  "geometry": {"coordinates":[-89.1667,35.4833],"type":"Point"}
}
=======
{"geometry":{"type":"Point","coordinates":[-89.166700,35.483300]},"type":"Feature","properties":{"hierarchy":["tgn:2401562","tgn:1000001","tgn:7012149","tgn:2001874","tgn:7007825","tgn:7029392"],"placetype":["aat:300008680"],"id":2401562,"name:xx":"Horseshoe Cutoff"}}
>>>>>>> 03f74aca74312dbeaf24d7e61306dd6a786dc3d0
