{
  "id": 2320915,
  "type": "Feature",
  "properties": {
    "tgn:hierarchy":[
        "tgn:2320915",
        "tgn:1000001",
        "tgn:7012149",
        "tgn:7007158",
        "tgn:7029392"
    ],
    "tgn:id":2320915,
    "tgn:name":"F L Lateral",
    "tgn:placetype":[
        "aat:300006075"
    ]
},
  "bbox": [],
  "geometry": {"coordinates":[-108.0667,38.6833],"type":"Point"}
}