<<<<<<< HEAD
{
  "id": 2253043,
  "type": "Feature",
  "properties": {
    "tgn:hierarchy":[
        "tgn:2253043",
        "tgn:1000001",
        "tgn:7012149",
        "tgn:1002521",
        "tgn:7007920",
        "tgn:7029392"
    ],
    "tgn:id":2253043,
    "tgn:name":"Constance Creek",
    "tgn:placetype":[
        "aat:300008706"
    ]
},
  "bbox": [],
  "geometry": {"coordinates":[-123.1333,47.7333],"type":"Point"}
}
=======
{"geometry":{"type":"Point","coordinates":[-123.133300,47.733300]},"type":"Feature","properties":{"hierarchy":["tgn:2253043","tgn:1000001","tgn:7012149","tgn:1002521","tgn:7007920","tgn:7029392"],"placetype":["aat:300008706"],"id":2253043,"name:xx":"Constance Creek"}}
>>>>>>> 03f74aca74312dbeaf24d7e61306dd6a786dc3d0
