{
  "id": 2253043,
  "type": "Feature",
  "properties": {
    "tgn:hierarchy":[
        "tgn:2253043",
        "tgn:1000001",
        "tgn:7012149",
        "tgn:1002521",
        "tgn:7007920",
        "tgn:7029392"
    ],
    "tgn:id":2253043,
    "tgn:name":"Constance Creek",
    "tgn:placetype":[
        "aat:300008706"
    ]
},
  "bbox": [],
  "geometry": {"coordinates":[-123.1333,47.7333],"type":"Point"}
}