{
  "id": 2412033,
  "type": "Feature",
  "properties": {
    "tgn:hierarchy":[
        "tgn:2412033",
        "tgn:1000001",
        "tgn:7012149",
        "tgn:7013961",
        "tgn:7029392"
    ],
    "tgn:id":2412033,
    "tgn:name":"Indian Ridge",
    "tgn:placetype":[
        "aat:300266640"
    ]
},
  "bbox": [],
  "geometry": {"coordinates":[-81.5333,37.4833],"type":"Point"}
}