{
  "id": 1120841,
  "type": "Feature",
  "properties": {
    "tgn:hierarchy":[
        "tgn:1120841",
        "tgn:1000004",
        "tgn:7002435",
        "tgn:7029392"
    ],
    "tgn:id":1120841,
    "tgn:name":"Chulym",
    "tgn:placetype":[
        "aat:300008707"
    ]
},
  "bbox": [],
  "geometry": {"coordinates":[83.85,57.75],"type":"Point"}
}