{
  "id": 2376409,
  "type": "Feature",
  "properties": {
    "tgn:hierarchy":[
        "tgn:2376409",
        "tgn:1000001",
        "tgn:1002410",
        "tgn:7012149",
        "tgn:7007565",
        "tgn:7029392"
    ],
    "tgn:id":2376409,
    "tgn:name":"Harding",
    "tgn:placetype":[
        "aat:300008347"
    ]
},
  "bbox": [],
  "geometry": {"coordinates":[-75.1167,39.6333],"type":"Point"}
}