{
  "id": 7486942,
  "type": "Feature",
  "properties": {
    "tgn:hierarchy":[
        "tgn:7486942",
        "tgn:1000004",
        "tgn:7490934",
        "tgn:1000141",
        "tgn:7029392"
    ],
    "tgn:id":7486942,
    "tgn:name":"Baishalun",
    "tgn:placetype":[
        "aat:300008347"
    ]
},
  "bbox": [],
  "geometry": {"coordinates":[120.184722,22.913333],"type":"Point"}
}