{
  "id": 7358403,
  "type": "Feature",
  "properties": {
    "tgn:hierarchy":[
        "tgn:7358403",
        "tgn:1000001",
        "tgn:1001960",
        "tgn:7005560",
        "tgn:7029392"
    ],
    "tgn:id":7358403,
    "tgn:name":"Colonia San Francisco",
    "tgn:placetype":[
        "aat:300008347"
    ]
},
  "bbox": [],
  "geometry": {"coordinates":[-110.366667,27.366667],"type":"Point"}
}