{
  "id": 7264086,
  "type": "Feature",
  "properties": {
    "tgn:hierarchy":[
        "tgn:7264086",
        "tgn:7003614",
        "tgn:1000003",
        "tgn:7016845",
        "tgn:7029392"
    ],
    "tgn:id":7264086,
    "tgn:name:nl":"Kort Bossen",
    "tgn:placetype":[
        "aat:300000745"
    ]
},
  "bbox": [],
  "geometry": {"coordinates":[6.533333,52.983333],"type":"Point"}
}