{
  "id": 2699641,
  "type": "Feature",
  "properties": {
    "tgn:hierarchy":[
        "tgn:2699641",
        "tgn:1000001",
        "tgn:7012149",
        "tgn:7007515",
        "tgn:7029392"
    ],
    "tgn:id":2699641,
    "tgn:name":"Stuart Brook",
    "tgn:placetype":[
        "aat:300008699"
    ]
},
  "bbox": [],
  "geometry": {"coordinates":[-70.4167,43.5667],"type":"Point"}
}