{
  "id": 1048515,
  "type": "Feature",
  "properties": {
    "tgn:hierarchy":[
        "tgn:1048515",
        "tgn:7003646",
        "tgn:1000003",
        "tgn:1000088",
        "tgn:7029392"
    ],
    "tgn:id":1048515,
    "tgn:name":"Eidsv\u00e5g",
    "tgn:placetype":[
        "aat:300008347"
    ]
},
  "bbox": [],
  "geometry": {"coordinates":[5.3167,60.4333],"type":"Point"}
}