<<<<<<< HEAD
{
  "id": 2338321,
  "type": "Feature",
  "properties": {
    "tgn:hierarchy":[
        "tgn:2338321",
        "tgn:1000001",
        "tgn:7012149",
        "tgn:2001293",
        "tgn:7007524",
        "tgn:7029392"
    ],
    "tgn:id":2338321,
    "tgn:name":"Fox, Mount",
    "tgn:placetype":[
        "aat:300008798"
    ]
},
  "bbox": [],
  "geometry": {"coordinates":[-109.9167,45.1167],"type":"Point"}
}
=======
{"geometry":{"type":"Point","coordinates":[-109.916700,45.116700]},"type":"Feature","properties":{"hierarchy":["tgn:2338321","tgn:1000001","tgn:7012149","tgn:2001293","tgn:7007524","tgn:7029392"],"placetype":["aat:300008798"],"id":2338321,"name:xx":"Fox, Mount"}}
>>>>>>> 03f74aca74312dbeaf24d7e61306dd6a786dc3d0
