{
  "id": 2307944,
  "type": "Feature",
  "properties": {
    "tgn:hierarchy":[
        "tgn:2307944",
        "tgn:1000001",
        "tgn:7012149",
        "tgn:1002263",
        "tgn:7007826",
        "tgn:7029392"
    ],
    "tgn:id":2307944,
    "tgn:name":"East Gum Creek",
    "tgn:placetype":[
        "aat:300008706"
    ]
},
  "bbox": [],
  "geometry": {"coordinates":[-95.2667,32.0333],"type":"Point"}
}