{
  "id": 7559747,
  "type": "Feature",
  "properties": {
    "tgn:hierarchy":[
        "tgn:7559747",
        "tgn:1000004",
        "tgn:7000198",
        "tgn:7016722",
        "tgn:7029392"
    ],
    "tgn:id":7559747,
    "tgn:name:en":"\u0100nand Nagla",
    "tgn:placetype":[
        "aat:300008347"
    ]
},
  "bbox": [],
  "geometry": {"coordinates":[79.428845,27.772292],"type":"Point"}
}