<<<<<<< HEAD
{
  "id": 2251915,
  "type": "Feature",
  "properties": {
    "tgn:hierarchy":[
        "tgn:2251915",
        "tgn:1000001",
        "tgn:7012149",
        "tgn:2000891",
        "tgn:7007256",
        "tgn:7029392"
    ],
    "tgn:id":2251915,
    "tgn:name":"Concession Canal",
    "tgn:placetype":[
        "aat:300006075"
    ]
},
  "bbox": [],
  "geometry": {"coordinates":[-90.0,29.8333],"type":"Point"}
}
=======
{"geometry":{"type":"Point","coordinates":[-90.000000,29.833300]},"type":"Feature","properties":{"hierarchy":["tgn:2251915","tgn:1000001","tgn:7012149","tgn:2000891","tgn:7007256","tgn:7029392"],"placetype":["aat:300006075"],"id":2251915,"name:xx":"Concession Canal"}}
>>>>>>> 03f74aca74312dbeaf24d7e61306dd6a786dc3d0
