{
  "id": 2502252,
  "type": "Feature",
  "properties": {
    "tgn:hierarchy":[
        "tgn:2502252",
        "tgn:1000001",
        "tgn:7012149",
        "tgn:1002793",
        "tgn:7007240",
        "tgn:7029392"
    ],
    "tgn:id":2502252,
    "tgn:name":"McKinney Branch",
    "tgn:placetype":[
        "aat:300008699"
    ]
},
  "bbox": [],
  "geometry": {"coordinates":[-81.85,27.8833],"type":"Point"}
}