{
  "id": 2241490,
  "type": "Feature",
  "properties": {
    "tgn:hierarchy":[
        "tgn:2241490",
        "tgn:1000001",
        "tgn:7012149",
        "tgn:1002392",
        "tgn:7007157",
        "tgn:7029392"
    ],
    "tgn:id":2241490,
    "tgn:name":"Clark Valley",
    "tgn:placetype":[
        "aat:300386845"
    ]
},
  "bbox": [],
  "geometry": {"coordinates":[-119.3667,36.75],"type":"Point"}
}