{
  "id": 7407349,
  "type": "Feature",
  "properties": {
    "tgn:hierarchy":[
        "tgn:7407349",
        "tgn:7005580",
        "tgn:1000001",
        "tgn:7005560",
        "tgn:7029392"
    ],
    "tgn:id":7407349,
    "tgn:name":"Los Amates, R\u00edo",
    "tgn:placetype":[
        "aat:300008699"
    ]
},
  "bbox": [],
  "geometry": {"coordinates":[-93.466667,16.108333],"type":"Point"}
}