{
  "id": 7405074,
  "type": "Feature",
  "properties": {
    "tgn:hierarchy":[
        "tgn:7405074",
        "tgn:7005585",
        "tgn:1000001",
        "tgn:7005560",
        "tgn:7029392"
    ],
    "tgn:id":7405074,
    "tgn:name":"Los Resumideros",
    "tgn:placetype":[
        "aat:300008347"
    ]
},
  "bbox": [],
  "geometry": {"coordinates":[-99.566667,17.483333],"type":"Point"}
}