{
  "id": 2299975,
  "type": "Feature",
  "properties": {
    "tgn:hierarchy":[
        "tgn:2299975",
        "tgn:1000001",
        "tgn:7012149",
        "tgn:2001300",
        "tgn:7007524",
        "tgn:7029392"
    ],
    "tgn:id":2299975,
    "tgn:name":"Duffy Lake",
    "tgn:placetype":[
        "aat:300008680"
    ]
},
  "bbox": [],
  "geometry": {"coordinates":[-114.25,46.6333],"type":"Point"}
}