{
  "id": 2300505,
  "type": "Feature",
  "properties": {
    "tgn:hierarchy":[
        "tgn:2300505",
        "tgn:1002300",
        "tgn:1000001",
        "tgn:7012149",
        "tgn:7007564",
        "tgn:7029392"
    ],
    "tgn:id":2300505,
    "tgn:name":"Dummer Ponds",
    "tgn:placetype":[
        "aat:300008680"
    ]
},
  "bbox": [],
  "geometry": {"coordinates":[-71.2833,44.6833],"type":"Point"}
}