{
  "id": 7273294,
  "type": "Feature",
  "properties": {
    "tgn:concordances":{
        "gn:id":"2744648"
    },
    "tgn:hierarchy":[
        "tgn:7273294",
        "tgn:7003616",
        "tgn:1000003",
        "tgn:7016845",
        "tgn:7029392"
    ],
    "tgn:id":7273294,
    "tgn:name:nl":"Westhem",
    "tgn:placetype":[
        "aat:300008347"
    ]
},
  "bbox": [],
  "geometry": {"coordinates":[5.55,53.016667],"type":"Point"}
}