{
  "id": 2264138,
  "type": "Feature",
  "properties": {
    "tgn:hierarchy":[
        "tgn:2264138",
        "tgn:1000001",
        "tgn:7012149",
        "tgn:2002246",
        "tgn:7007920",
        "tgn:7029392"
    ],
    "tgn:id":2264138,
    "tgn:name":"Coyote Spring",
    "tgn:placetype":[
        "aat:300008697"
    ]
},
  "bbox": [],
  "geometry": {"coordinates":[-119.2667,47.5833],"type":"Point"}
}