{
  "id": 2033700,
  "type": "Feature",
  "properties": {
    "tgn:hierarchy":[
        "tgn:2033700",
        "tgn:1000001",
        "tgn:7012149",
        "tgn:2000549",
        "tgn:7007252",
        "tgn:7029392"
    ],
    "tgn:id":2033700,
    "tgn:name":"Smockville",
    "tgn:placetype":[
        "aat:300008347",
        "aat:300387210"
    ]
},
  "bbox": [],
  "geometry": {"coordinates":[-87.1167,39.6167],"type":"Point"}
}