{
  "id": 2105307,
  "type": "Feature",
  "properties": {
    "tgn:hierarchy":[
        "tgn:2105307",
        "tgn:1000001",
        "tgn:7012149",
        "tgn:1002939",
        "tgn:7007826",
        "tgn:7029392"
    ],
    "tgn:id":2105307,
    "tgn:name":"Keller",
    "tgn:placetype":[
        "aat:300008347"
    ]
},
  "bbox": [],
  "geometry": {"coordinates":[-97.25,32.9333],"type":"Point"}
}