<<<<<<< HEAD
{
  "id": 2333454,
  "type": "Feature",
  "properties": {
    "tgn:hierarchy":[
        "tgn:2333454",
        "tgn:1000001",
        "tgn:1002665",
        "tgn:7012149",
        "tgn:7007517",
        "tgn:7029392"
    ],
    "tgn:id":2333454,
    "tgn:name":"Follen Heights",
    "tgn:placetype":[
        "aat:300008347"
    ]
},
  "bbox": [],
  "geometry": {"coordinates":[-71.2,42.4167],"type":"Point"}
}
=======
{"geometry":{"type":"Point","coordinates":[-71.200000,42.416700]},"type":"Feature","properties":{"hierarchy":["tgn:2333454","tgn:1000001","tgn:1002665","tgn:7012149","tgn:7007517","tgn:7029392"],"placetype":["aat:300008347"],"id":2333454,"name:xx":"Follen Heights"}}
>>>>>>> 03f74aca74312dbeaf24d7e61306dd6a786dc3d0
