{
  "id": 7389631,
  "type": "Feature",
  "properties": {
    "tgn:hierarchy":[
        "tgn:7389631",
        "tgn:1001853",
        "tgn:1000001",
        "tgn:7005560",
        "tgn:7029392"
    ],
    "tgn:id":7389631,
    "tgn:name":"Rancho Nuevo",
    "tgn:placetype":[
        "aat:300008347"
    ]
},
  "bbox": [],
  "geometry": {"coordinates":[-101.35,27.95],"type":"Point"}
}