{
  "id": 7294864,
  "type": "Feature",
  "properties": {
    "tgn:hierarchy":[
        "tgn:7294864",
        "tgn:1001630",
        "tgn:1000049",
        "tgn:1000002",
        "tgn:7029392"
    ],
    "tgn:id":7294864,
    "tgn:name":"Sin Nombre, Cerro",
    "tgn:placetype":[
        "aat:300008795"
    ]
},
  "bbox": [],
  "geometry": {"coordinates":[-68.45,-27.05],"type":"Point"}
}