{
  "id": 2547997,
  "type": "Feature",
  "properties": {
    "tgn:hierarchy":[
        "tgn:2547997",
        "tgn:1000001",
        "tgn:7012149",
        "tgn:2000224",
        "tgn:7007158",
        "tgn:7029392"
    ],
    "tgn:id":2547997,
    "tgn:name":"North Halfmoon Creek",
    "tgn:placetype":[
        "aat:300008706"
    ]
},
  "bbox": [],
  "geometry": {"coordinates":[-106.4833,39.1667],"type":"Point"}
}