{
  "id": 7594240,
  "type": "Feature",
  "properties": {
    "tgn:hierarchy":[
        "tgn:7594240",
        "tgn:1000003",
        "tgn:7005729",
        "tgn:7029392"
    ],
    "tgn:id":7594240,
    "tgn:name":"Valletta",
    "tgn:placetype":[
        "aat:300387064",
        "aat:300387205"
    ]
},
  "bbox": [],
  "geometry": {"coordinates":[14.5125,35.898333],"type":"Point"}
}