{
  "id": 7503699,
  "type": "Feature",
  "properties": {
    "tgn:hierarchy":[
        "tgn:7503699",
        "tgn:7487020",
        "tgn:1000004",
        "tgn:1000141",
        "tgn:7029392"
    ],
    "tgn:id":7503699,
    "tgn:name":"Hongzidoukeng",
    "tgn:placetype":[
        "aat:300008699"
    ]
},
  "bbox": [],
  "geometry": {"coordinates":[120.865931,24.313718],"type":"Point"}
}