{
  "id": 7433687,
  "type": "Feature",
  "properties": {
    "tgn:hierarchy":[
        "tgn:7433687",
        "tgn:1000001",
        "tgn:1001960",
        "tgn:7005560",
        "tgn:7029392"
    ],
    "tgn:id":7433687,
    "tgn:name":"La Tubutama",
    "tgn:placetype":[
        "aat:300008347"
    ]
},
  "bbox": [],
  "geometry": {"coordinates":[-111.465278,30.885278],"type":"Point"}
}