{
  "id": 7295559,
  "type": "Feature",
  "properties": {
    "tgn:hierarchy":[
        "tgn:7295559",
        "tgn:1001439",
        "tgn:1000003",
        "tgn:7002797",
        "tgn:1000095",
        "tgn:7029392"
    ],
    "tgn:id":7295559,
    "tgn:name":"Indio Grande",
    "tgn:placetype":[
        "aat:300386846"
    ]
},
  "bbox": [],
  "geometry": {"coordinates":[-1.016667,37.583333],"type":"Point"}
}