<<<<<<< HEAD
{
  "id": 2158402,
  "type": "Feature",
  "properties": {
    "tgn:hierarchy":[
        "tgn:2158402",
        "tgn:7002659",
        "tgn:1000001",
        "tgn:7012149",
        "tgn:2000043",
        "tgn:7029392"
    ],
    "tgn:id":2158402,
    "tgn:name":"Beaverdam Creek",
    "tgn:placetype":[
        "aat:300008706"
    ]
},
  "bbox": [],
  "geometry": {"coordinates":[-85.7833,32.3333],"type":"Point"}
}
=======
{"geometry":{"type":"Point","coordinates":[-85.783300,32.333300]},"type":"Feature","properties":{"hierarchy":["tgn:2158402","tgn:7002659","tgn:1000001","tgn:7012149","tgn:2000043","tgn:7029392"],"placetype":["aat:300008706"],"id":2158402,"name:xx":"Beaverdam Creek"}}
>>>>>>> 03f74aca74312dbeaf24d7e61306dd6a786dc3d0
