{
  "id": 2600331,
  "type": "Feature",
  "properties": {
    "tgn:hierarchy":[
        "tgn:2600331",
        "tgn:1000001",
        "tgn:7012149",
        "tgn:2001453",
        "tgn:7007566",
        "tgn:7029392"
    ],
    "tgn:id":2600331,
    "tgn:name":"Pueblo, Ca\u00f1ada del",
    "tgn:placetype":[
        "aat:300008699"
    ]
},
  "bbox": [],
  "geometry": {"coordinates":[-105.65,35.1167],"type":"Point"}
}