{
  "id": 7441190,
  "type": "Feature",
  "properties": {
    "tgn:hierarchy":[
        "tgn:7441190",
        "tgn:7005581",
        "tgn:1000001",
        "tgn:7005560",
        "tgn:7029392"
    ],
    "tgn:id":7441190,
    "tgn:name":"Santa Ana",
    "tgn:placetype":[
        "aat:300008347"
    ]
},
  "bbox": [],
  "geometry": {"coordinates":[-106.583333,27.816667],"type":"Point"}
}