{
  "id": 7554845,
  "type": "Feature",
  "properties": {
    "tgn:hierarchy":[
        "tgn:7554845",
        "tgn:1000004",
        "tgn:7031781",
        "tgn:7000198",
        "tgn:7029392"
    ],
    "tgn:id":7554845,
    "tgn:name:en":"Naila",
    "tgn:placetype":[
        "aat:300007783"
    ]
},
  "bbox": [],
  "geometry": {"coordinates":[82.566548,22.022791],"type":"Point"}
}