{
  "id": 7403036,
  "type": "Feature",
  "properties": {
    "tgn:hierarchy":[
        "tgn:7403036",
        "tgn:1000001",
        "tgn:7005600",
        "tgn:7005560",
        "tgn:7029392"
    ],
    "tgn:id":7403036,
    "tgn:name":"Xpukil, Grutas",
    "tgn:placetype":[
        "aat:300008746"
    ]
},
  "bbox": [],
  "geometry": {"coordinates":[-89.916667,20.55],"type":"Point"}
}