{
  "id": 7009668,
  "type": "Feature",
  "properties": {
    "tgn:hierarchy":[
        "tgn:7009668",
        "tgn:1000003",
        "tgn:7002875",
        "tgn:1000070",
        "tgn:7029392"
    ],
    "tgn:id":7009668,
    "tgn:name":"Saulieu",
    "tgn:placetype":[
        "aat:300008347"
    ]
},
  "bbox": [],
  "geometry": {"coordinates":[4.2333,47.2833],"type":"Point"}
}