{
  "id": 7292465,
  "type": "Feature",
  "properties": {
    "tgn:hierarchy":[
        "tgn:7292465",
        "tgn:1001708",
        "tgn:1000049",
        "tgn:1000002",
        "tgn:7029392"
    ],
    "tgn:id":7292465,
    "tgn:name":"El Durazno, Quebrada",
    "tgn:placetype":[
        "aat:300008699"
    ]
},
  "bbox": [],
  "geometry": {"coordinates":[-71.083333,-33.733333],"type":"Point"}
}