{
  "id": 7210385,
  "type": "Feature",
  "properties": {
    "tgn:hierarchy":[
        "tgn:7210385",
        "tgn:7003669",
        "tgn:1000003",
        "tgn:7000084",
        "tgn:7029392"
    ],
    "tgn:id":7210385,
    "tgn:name":"Bergmooser",
    "tgn:placetype":[
        "aat:300000206"
    ]
},
  "bbox": [],
  "geometry": {"coordinates":[10.983333,48.45],"type":"Point"}
}