{
  "id": 7532104,
  "type": "Feature",
  "properties": {
    "tgn:hierarchy":[
        "tgn:7532104",
        "tgn:7001242",
        "tgn:7016833",
        "tgn:1001091",
        "tgn:7029392"
    ],
    "tgn:id":7532104,
    "tgn:name":"Markaz Shab\u0101b as Saww\u0101\u1e29",
    "tgn:placetype":[
        "aat:300004792"
    ]
},
  "bbox": [],
  "geometry": {"coordinates":[31.284591,30.112759],"type":"Point"}
}