{
  "id": 2088907,
  "type": "Feature",
  "properties": {
    "tgn:hierarchy":[
        "tgn:2088907",
        "tgn:1000001",
        "tgn:7012149",
        "tgn:7014185",
        "tgn:7007710",
        "tgn:7029392"
    ],
    "tgn:id":2088907,
    "tgn:name":"Greater Point Marion",
    "tgn:placetype":[
        "aat:300008347"
    ]
},
  "bbox": [],
  "geometry": {"coordinates":[-79.8833,39.75],"type":"Point"}
}