{
  "id": 2192857,
  "type": "Feature",
  "properties": {
    "tgn:hierarchy":[
        "tgn:2192857",
        "tgn:1000001",
        "tgn:7012149",
        "tgn:2000227",
        "tgn:7007158",
        "tgn:7029392"
    ],
    "tgn:id":2192857,
    "tgn:name":"Bravo Canyon",
    "tgn:placetype":[
        "aat:300008761"
    ]
},
  "bbox": [],
  "geometry": {"coordinates":[-103.6667,37.55],"type":"Point"}
}