{
  "id": 2459120,
  "type": "Feature",
  "properties": {
    "tgn:hierarchy":[
        "tgn:2459120",
        "tgn:1000001",
        "tgn:7012149",
        "tgn:1002593",
        "tgn:7007568",
        "tgn:7029392"
    ],
    "tgn:id":2459120,
    "tgn:name":"Little Pine Lake",
    "tgn:placetype":[
        "aat:300008680"
    ]
},
  "bbox": [],
  "geometry": {"coordinates":[-75.1333,43.6667],"type":"Point"}
}