<<<<<<< HEAD
{
  "id": 7350458,
  "type": "Feature",
  "properties": {
    "tgn:hierarchy":[
        "tgn:7350458",
        "tgn:7005581",
        "tgn:1000001",
        "tgn:7005560",
        "tgn:7029392"
    ],
    "tgn:id":7350458,
    "tgn:name":"Apache, Ojo del",
    "tgn:placetype":[
        "aat:300008697"
    ]
},
  "bbox": [],
  "geometry": {"coordinates":[-106.9,30.566667],"type":"Point"}
}
=======
{"geometry":{"type":"Point","coordinates":[-106.900000,30.566667]},"type":"Feature","properties":{"hierarchy":["tgn:7350458","tgn:7005581","tgn:1000001","tgn:7005560","tgn:7029392"],"placetype":["aat:300008697"],"id":7350458,"name:xx":"Apache, Ojo del"}}
>>>>>>> 03f74aca74312dbeaf24d7e61306dd6a786dc3d0
