<<<<<<< HEAD
{
  "id": 2768074,
  "type": "Feature",
  "properties": {
    "tgn:hierarchy":[
        "tgn:2768074",
        "tgn:1000001",
        "tgn:7012149",
        "tgn:2001515",
        "tgn:7007709",
        "tgn:7029392"
    ],
    "tgn:id":2768074,
    "tgn:name":"Whiterock Mountain",
    "tgn:placetype":[
        "aat:300008798"
    ]
},
  "bbox": [],
  "geometry": {"coordinates":[-83.3,35.0833],"type":"Point"}
}
=======
{"geometry":{"type":"Point","coordinates":[-83.300000,35.083300]},"type":"Feature","properties":{"hierarchy":["tgn:2768074","tgn:1000001","tgn:7012149","tgn:2001515","tgn:7007709","tgn:7029392"],"placetype":["aat:300008798"],"id":2768074,"name:xx":"Whiterock Mountain"}}
>>>>>>> 03f74aca74312dbeaf24d7e61306dd6a786dc3d0
