{
  "id": 1071215,
  "type": "Feature",
  "properties": {
    "tgn:hierarchy":[
        "tgn:1071215",
        "tgn:1000004",
        "tgn:7016672",
        "tgn:1000111",
        "tgn:7029392"
    ],
    "tgn:id":1071215,
    "tgn:name":"Renheji",
    "tgn:placetype":[
        "aat:300008347"
    ]
},
  "bbox": [],
  "geometry": {"coordinates":[115.1167,31.9333],"type":"Point"}
}