{
  "id": 7289821,
  "type": "Feature",
  "properties": {
    "tgn:hierarchy":[
        "tgn:7289821",
        "tgn:1001708",
        "tgn:1000049",
        "tgn:1000002",
        "tgn:7029392"
    ],
    "tgn:id":7289821,
    "tgn:name":"El Canelo",
    "tgn:placetype":[
        "aat:300008347"
    ]
},
  "bbox": [],
  "geometry": {"coordinates":[-70.45,-33.583333],"type":"Point"}
}