{
  "id": 1130607,
  "type": "Feature",
  "properties": {
    "tgn:hierarchy":[
        "tgn:1130607",
        "tgn:1000004",
        "tgn:1009319",
        "tgn:1000141",
        "tgn:7029392"
    ],
    "tgn:id":1130607,
    "tgn:name":"Tan-shui Ho",
    "tgn:placetype":[
        "aat:300008707",
        "aat:300008699"
    ]
},
  "bbox": [],
  "geometry": {"coordinates":[121.420721,25.172517],"type":"Point"}
}