{
  "id": 2488904,
  "type": "Feature",
  "properties": {
    "tgn:hierarchy":[
        "tgn:2488904",
        "tgn:1000001",
        "tgn:7012149",
        "tgn:2001197",
        "tgn:7007523",
        "tgn:7029392"
    ],
    "tgn:id":2488904,
    "tgn:name":"Main Ditch Number 1",
    "tgn:placetype":[
        "aat:300006075"
    ]
},
  "bbox": [],
  "geometry": {"coordinates":[-89.9833,36.0333],"type":"Point"}
}