<<<<<<< HEAD
{
  "id": 7020462,
  "type": "Feature",
  "properties": {
    "tgn:hierarchy":[
        "tgn:7020462",
        "tgn:1000001",
        "tgn:7012149",
        "tgn:2001275",
        "tgn:7007524",
        "tgn:7029392"
    ],
    "tgn:id":7020462,
    "tgn:name":"Moose Jaw Creek",
    "tgn:placetype":[
        "aat:300008706"
    ]
},
  "bbox": [],
  "geometry": {"coordinates":[-111.0833,45.45],"type":"Point"}
}
=======
{"geometry":{"type":"Point","coordinates":[-111.083300,45.450000]},"type":"Feature","properties":{"hierarchy":["tgn:7020462","tgn:1000001","tgn:7012149","tgn:2001275","tgn:7007524","tgn:7029392"],"placetype":["aat:300008706"],"id":7020462,"name:xx":"Moose Jaw Creek"}}
>>>>>>> 03f74aca74312dbeaf24d7e61306dd6a786dc3d0
