{
  "id": 7408510,
  "type": "Feature",
  "properties": {
    "tgn:hierarchy":[
        "tgn:7408510",
        "tgn:1000001",
        "tgn:1001893",
        "tgn:7005560",
        "tgn:7029392"
    ],
    "tgn:id":7408510,
    "tgn:name":"Dedeni Dolores",
    "tgn:placetype":[
        "aat:300008347"
    ]
},
  "bbox": [],
  "geometry": {"coordinates":[-99.641667,20.108333],"type":"Point"}
}