{
  "id": 1073738,
  "type": "Feature",
  "properties": {
    "tgn:hierarchy":[
        "tgn:1073738",
        "tgn:1000004",
        "tgn:7002085",
        "tgn:1000111",
        "tgn:7029392"
    ],
    "tgn:id":1073738,
    "tgn:name":"Yuli",
    "tgn:placetype":[
        "aat:300008347"
    ]
},
  "bbox": [],
  "geometry": {"coordinates":[121.4167,36.9833],"type":"Point"}
}