{
  "id": 7012114,
  "type": "Feature",
  "properties": {
    "tgn:hierarchy":[
        "tgn:7012114",
        "tgn:7008695",
        "tgn:7002448",
        "tgn:1000003",
        "tgn:7008591",
        "tgn:7029392"
    ],
    "tgn:id":7012114,
    "tgn:name:en":"Crumlin",
    "tgn:placetype":[
        "aat:300008347"
    ]
},
  "bbox": [],
  "geometry": {"coordinates":[-6.233333,54.616667],"type":"Point"}
}