{
  "id": 7149104,
  "type": "Feature",
  "properties": {
    "tgn:hierarchy":[
        "tgn:7149104",
        "tgn:1000003",
        "tgn:7000094",
        "tgn:7000084",
        "tgn:7029392"
    ],
    "tgn:id":7149104,
    "tgn:name":"Krugsdorf",
    "tgn:placetype":[
        "aat:300008347"
    ]
},
  "bbox": [],
  "geometry": {"coordinates":[14.083333,53.516667],"type":"Point"}
}