{
  "id": 7412447,
  "type": "Feature",
  "properties": {
    "tgn:hierarchy":[
        "tgn:7412447",
        "tgn:7005587",
        "tgn:1000001",
        "tgn:7005560",
        "tgn:7029392"
    ],
    "tgn:id":7412447,
    "tgn:name:es":"El Campanario",
    "tgn:placetype":[
        "aat:300008347"
    ]
},
  "bbox": [],
  "geometry": {"coordinates":[-98.929167,20.093056],"type":"Point"}
}