<<<<<<< HEAD
{
  "id": 2767970,
  "type": "Feature",
  "properties": {
    "tgn:hierarchy":[
        "tgn:2767970",
        "tgn:1000001",
        "tgn:7012149",
        "tgn:7007709",
        "tgn:7029392"
    ],
    "tgn:id":2767970,
    "tgn:name":"Whiteoak Branch",
    "tgn:placetype":[
        "aat:300008699"
    ]
},
  "bbox": [],
  "geometry": {"coordinates":[-77.6833,34.9833],"type":"Point"}
}
=======
{"geometry":{"type":"Point","coordinates":[-77.683300,34.983300]},"type":"Feature","properties":{"hierarchy":["tgn:2767970","tgn:1000001","tgn:7012149","tgn:7007709","tgn:7029392"],"placetype":["aat:300008699"],"id":2767970,"name:xx":"Whiteoak Branch"}}
>>>>>>> 03f74aca74312dbeaf24d7e61306dd6a786dc3d0
