{
  "id": 2718229,
  "type": "Feature",
  "properties": {
    "tgn:hierarchy":[
        "tgn:2718229",
        "tgn:1000001",
        "tgn:7012149",
        "tgn:7007825",
        "tgn:7029392"
    ],
    "tgn:id":2718229,
    "tgn:name":"Thompson Creek",
    "tgn:placetype":[
        "aat:300008706"
    ]
},
  "bbox": [],
  "geometry": {"coordinates":[-83.6333,36.0167],"type":"Point"}
}