{
  "id": 1026206,
  "type": "Feature",
  "properties": {
    "tgn:hierarchy":[
        "tgn:1026206",
        "tgn:7003026",
        "tgn:1000003",
        "tgn:1000062",
        "tgn:7029392"
    ],
    "tgn:id":1026206,
    "tgn:name":"Waldkirchen am Wesen",
    "tgn:placetype":[
        "aat:300008347"
    ]
},
  "bbox": [],
  "geometry": {"coordinates":[13.8167,48.4333],"type":"Point"}
}