{
  "id": 7331666,
  "type": "Feature",
  "properties": {
    "tgn:hierarchy":[
        "tgn:7331666",
        "tgn:7002822",
        "tgn:1001647",
        "tgn:1000003",
        "tgn:1000095",
        "tgn:7029392"
    ],
    "tgn:id":7331666,
    "tgn:name":"Jaramillos, R\u00edo de los",
    "tgn:placetype":[
        "aat:300008699"
    ]
},
  "bbox": [],
  "geometry": {"coordinates":[-3.35,41.066667],"type":"Point"}
}