{
  "id": 7344062,
  "type": "Feature",
  "properties": {
    "tgn:hierarchy":[
        "tgn:7344062",
        "tgn:7008911",
        "tgn:1000003",
        "tgn:7002763",
        "tgn:1000095",
        "tgn:7029392"
    ],
    "tgn:id":7344062,
    "tgn:name":"Campa\u00f1a, Punta",
    "tgn:placetype":[
        "aat:300386846"
    ]
},
  "bbox": [],
  "geometry": {"coordinates":[-6.733333,43.566667],"type":"Point"}
}