{
  "id": 2027215,
  "type": "Feature",
  "properties": {
    "tgn:hierarchy":[
        "tgn:2027215",
        "tgn:1000001",
        "tgn:1002322",
        "tgn:7012149",
        "tgn:7007251",
        "tgn:7029392"
    ],
    "tgn:id":2027215,
    "tgn:name":"Clinton",
    "tgn:placetype":[
        "aat:300008347"
    ]
},
  "bbox": [],
  "geometry": {"coordinates":[-88.95,40.15],"type":"Point"}
}