<<<<<<< HEAD
{
  "id": 7240239,
  "type": "Feature",
  "properties": {
    "tgn:hierarchy":[
        "tgn:7240239",
        "tgn:7003460",
        "tgn:1000003",
        "tgn:1000063",
        "tgn:4012014",
        "tgn:7029392"
    ],
    "tgn:id":7240239,
    "tgn:name":"Eienberg",
    "tgn:placetype":[
        "aat:300008777"
    ]
},
  "bbox": [],
  "geometry": {"coordinates":[6.0625,50.2475],"type":"Point"}
}
=======
{"geometry":{"type":"Point","coordinates":[6.062500,50.247500]},"type":"Feature","properties":{"hierarchy":["tgn:7240239","tgn:7003460","tgn:1000003","tgn:1000063","tgn:4012014","tgn:7029392"],"placetype":["aat:300008777"],"id":7240239,"name:xx":"Eienberg"}}
>>>>>>> 03f74aca74312dbeaf24d7e61306dd6a786dc3d0
