{
  "id": 2187726,
  "type": "Feature",
  "properties": {
    "tgn:hierarchy":[
        "tgn:2187726",
        "tgn:1000001",
        "tgn:7012149",
        "tgn:1002567",
        "tgn:7007240",
        "tgn:7029392"
    ],
    "tgn:id":2187726,
    "tgn:name":"Booths Island",
    "tgn:placetype":[
        "aat:300008791"
    ]
},
  "bbox": [],
  "geometry": {"coordinates":[-81.7667,28.65],"type":"Point"}
}