<<<<<<< HEAD
{
  "id": 2408160,
  "type": "Feature",
  "properties": {
    "tgn:hierarchy":[
        "tgn:2408160",
        "tgn:1000001",
        "tgn:7012149",
        "tgn:2002284",
        "tgn:7013961",
        "tgn:7029392"
    ],
    "tgn:id":2408160,
    "tgn:name":"Hurricane Ridge",
    "tgn:placetype":[
        "aat:300266640"
    ]
},
  "bbox": [],
  "geometry": {"coordinates":[-80.7,38.15],"type":"Point"}
}
=======
{"geometry":{"type":"Point","coordinates":[-80.700000,38.150000]},"type":"Feature","properties":{"hierarchy":["tgn:2408160","tgn:1000001","tgn:7012149","tgn:2002284","tgn:7013961","tgn:7029392"],"placetype":["aat:300266640"],"id":2408160,"name:xx":"Hurricane Ridge"}}
>>>>>>> 03f74aca74312dbeaf24d7e61306dd6a786dc3d0
