{
  "id": 7120801,
  "type": "Feature",
  "properties": {
    "tgn:hierarchy":[
        "tgn:7120801",
        "tgn:1000003",
        "tgn:7003676",
        "tgn:7000084",
        "tgn:7029392"
    ],
    "tgn:id":7120801,
    "tgn:name":"Patersweg",
    "tgn:placetype":[
        "aat:300008347"
    ]
},
  "bbox": [],
  "geometry": {"coordinates":[7.483333,53.15],"type":"Point"}
}