{
  "id": 2732913,
  "type": "Feature",
  "properties": {
    "tgn:hierarchy":[
        "tgn:2732913",
        "tgn:1000001",
        "tgn:7016172",
        "tgn:7012149",
        "tgn:2000136",
        "tgn:7029392"
    ],
    "tgn:id":2732913,
    "tgn:name":"Turkey Hill",
    "tgn:placetype":[
        "aat:300008798"
    ]
},
  "bbox": [],
  "geometry": {"coordinates":[-91.2333,35.8667],"type":"Point"}
}