{
  "id": 7021613,
  "type": "Feature",
  "properties": {
    "tgn:hierarchy":[
        "tgn:7021613",
        "tgn:1000001",
        "tgn:7012149",
        "tgn:2001975",
        "tgn:7007826",
        "tgn:7029392"
    ],
    "tgn:id":7021613,
    "tgn:name":"Asherton",
    "tgn:placetype":[
        "aat:300008347"
    ]
},
  "bbox": [],
  "geometry": {"coordinates":[-99.75,28.4333],"type":"Point"}
}