<<<<<<< HEAD
{
  "id": 2769461,
  "type": "Feature",
  "properties": {
    "tgn:hierarchy":[
        "tgn:2769461",
        "tgn:2002143",
        "tgn:1000001",
        "tgn:7012149",
        "tgn:7007919",
        "tgn:7029392"
    ],
    "tgn:id":2769461,
    "tgn:name":"Wide Hollow",
    "tgn:placetype":[
        "aat:300008761"
    ]
},
  "bbox": [],
  "geometry": {"coordinates":[-79.6,38.1833],"type":"Point"}
}
=======
{"geometry":{"type":"Point","coordinates":[-79.600000,38.183300]},"type":"Feature","properties":{"hierarchy":["tgn:2769461","tgn:2002143","tgn:1000001","tgn:7012149","tgn:7007919","tgn:7029392"],"placetype":["aat:300008761"],"id":2769461,"name:xx":"Wide Hollow"}}
>>>>>>> 03f74aca74312dbeaf24d7e61306dd6a786dc3d0
