{
  "id": 2225114,
  "type": "Feature",
  "properties": {
    "tgn:hierarchy":[
        "tgn:2225114",
        "tgn:1000001",
        "tgn:7006451",
        "tgn:7012149",
        "tgn:2000098",
        "tgn:7029392"
    ],
    "tgn:id":2225114,
    "tgn:name":"Castle Cove",
    "tgn:placetype":[
        "aat:300132316"
    ]
},
  "bbox": [],
  "geometry": {"coordinates":[-114.7167,36.05],"type":"Point"}
}