{
  "id": 7508505,
  "type": "Feature",
  "properties": {
    "tgn:hierarchy":[
        "tgn:7508505",
        "tgn:7000509",
        "tgn:1008380",
        "tgn:1000226",
        "tgn:1000006",
        "tgn:7029392"
    ],
    "tgn:id":7508505,
    "tgn:name:en":"Owhakataro Stream",
    "tgn:placetype":[
        "aat:300008699"
    ]
},
  "bbox": [],
  "geometry": {"coordinates":[176.966667,-37.966667],"type":"Point"}
}