{
  "id": 2451050,
  "type": "Feature",
  "properties": {
    "tgn:hierarchy":[
        "tgn:2451050",
        "tgn:1000001",
        "tgn:7012149",
        "tgn:2002378",
        "tgn:7007923",
        "tgn:7029392"
    ],
    "tgn:id":2451050,
    "tgn:name":"Little Alkali Creek",
    "tgn:placetype":[
        "aat:300008706"
    ]
},
  "bbox": [],
  "geometry": {"coordinates":[-104.3667,43.4167],"type":"Point"}
}