{
  "id": 7054299,
  "type": "Feature",
  "properties": {
    "tgn:hierarchy":[
        "tgn:7054299",
        "tgn:7003134",
        "tgn:1000003",
        "tgn:7008516",
        "tgn:1000080",
        "tgn:7029392"
    ],
    "tgn:id":7054299,
    "tgn:name":"Ponte Mantovano",
    "tgn:placetype":[
        "aat:300008347"
    ]
},
  "bbox": [],
  "geometry": {"coordinates":[10.616667,44.833333],"type":"Point"}
}