{
  "id": 2340257,
  "type": "Feature",
  "properties": {
    "tgn:hierarchy":[
        "tgn:2340257",
        "tgn:1000001",
        "tgn:7012149",
        "tgn:2000538",
        "tgn:7007251",
        "tgn:7029392"
    ],
    "tgn:id":2340257,
    "tgn:name":"French Creek",
    "tgn:placetype":[
        "aat:300008706"
    ]
},
  "bbox": [],
  "geometry": {"coordinates":[-89.8667,41.8333],"type":"Point"}
}