{
  "id": 2124996,
  "type": "Feature",
  "properties": {
    "tgn:hierarchy":[
        "tgn:2124996",
        "tgn:1000001",
        "tgn:7012149",
        "tgn:7007157",
        "tgn:2000190",
        "tgn:7029392"
    ],
    "tgn:id":2124996,
    "tgn:name":"Abraham Plains",
    "tgn:placetype":[
        "aat:300008805"
    ]
},
  "bbox": [],
  "geometry": {"coordinates":[-122.05,40.1833],"type":"Point"}
}