{
  "id": 7285735,
  "type": "Feature",
  "properties": {
    "tgn:hierarchy":[
        "tgn:7285735",
        "tgn:1001702",
        "tgn:1000049",
        "tgn:1000002",
        "tgn:7029392"
    ],
    "tgn:id":7285735,
    "tgn:name":"Puchachailgua, Estero",
    "tgn:placetype":[
        "aat:300008676"
    ]
},
  "bbox": [],
  "geometry": {"coordinates":[-73.833333,-53.066667],"type":"Point"}
}