<<<<<<< HEAD
{
  "id": 2769546,
  "type": "Feature",
  "properties": {
    "tgn:hierarchy":[
        "tgn:2769546",
        "tgn:1000001",
        "tgn:7012149",
        "tgn:2001276",
        "tgn:7007524",
        "tgn:7029392"
    ],
    "tgn:id":2769546,
    "tgn:name":"Widow Coulee",
    "tgn:placetype":[
        "aat:300008761"
    ]
},
  "bbox": [],
  "geometry": {"coordinates":[-107.2167,47.6167],"type":"Point"}
}
=======
{"geometry":{"type":"Point","coordinates":[-107.216700,47.616700]},"type":"Feature","properties":{"hierarchy":["tgn:2769546","tgn:1000001","tgn:7012149","tgn:2001276","tgn:7007524","tgn:7029392"],"placetype":["aat:300008761"],"id":2769546,"name:xx":"Widow Coulee"}}
>>>>>>> 03f74aca74312dbeaf24d7e61306dd6a786dc3d0
