{
  "id": 2223848,
  "type": "Feature",
  "properties": {
    "tgn:hierarchy":[
        "tgn:2223848",
        "tgn:1000001",
        "tgn:7012149",
        "tgn:2002163",
        "tgn:7007919",
        "tgn:7029392"
    ],
    "tgn:id":2223848,
    "tgn:name":"Carter and Harrell Lake",
    "tgn:placetype":[
        "aat:300006191"
    ]
},
  "bbox": [],
  "geometry": {"coordinates":[-77.7667,37.6333],"type":"Point"}
}