{
  "id": 2498023,
  "type": "Feature",
  "properties": {
    "tgn:hierarchy":[
        "tgn:2498023",
        "tgn:1000001",
        "tgn:7012149",
        "tgn:2001125",
        "tgn:7007522",
        "tgn:7029392"
    ],
    "tgn:id":2498023,
    "tgn:name":"Mayo Branch",
    "tgn:placetype":[
        "aat:300008699"
    ]
},
  "bbox": [],
  "geometry": {"coordinates":[-89.65,32.6333],"type":"Point"}
}