{
  "id": 1105501,
  "type": "Feature",
  "properties": {
    "tgn:hierarchy":[
        "tgn:1105501",
        "tgn:1008380",
        "tgn:7520093",
        "tgn:1000226",
        "tgn:1000006",
        "tgn:7029392"
    ],
    "tgn:id":1105501,
    "tgn:name":"Makorako",
    "tgn:placetype":[
        "aat:300008795"
    ]
},
  "bbox": [],
  "geometry": {"coordinates":[176.05,-39.1333],"type":"Point"}
}