{
  "id": 7280120,
  "type": "Feature",
  "properties": {
    "tgn:hierarchy":[
        "tgn:7280120",
        "tgn:1001623",
        "tgn:1000049",
        "tgn:1000002",
        "tgn:7029392"
    ],
    "tgn:id":7280120,
    "tgn:name":"Resbole, R\u00edo",
    "tgn:placetype":[
        "aat:300008699"
    ]
},
  "bbox": [],
  "geometry": {"coordinates":[-72.916667,-48.133333],"type":"Point"}
}