{
  "id": 2377896,
  "type": "Feature",
  "properties": {
    "tgn:hierarchy":[
        "tgn:2377896",
        "tgn:1000001",
        "tgn:7016172",
        "tgn:7012149",
        "tgn:2000176",
        "tgn:7029392"
    ],
    "tgn:id":2377896,
    "tgn:name":"Harris",
    "tgn:placetype":[
        "aat:300008347"
    ]
},
  "bbox": [],
  "geometry": {"coordinates":[-94.0333,36.0167],"type":"Point"}
}