{
  "id": 2717096,
  "type": "Feature",
  "properties": {
    "tgn:hierarchy":[
        "tgn:2717096",
        "tgn:1000001",
        "tgn:7012149",
        "tgn:2002018",
        "tgn:7007826",
        "tgn:7029392"
    ],
    "tgn:id":2717096,
    "tgn:name":"Third Creek",
    "tgn:placetype":[
        "aat:300008706"
    ]
},
  "bbox": [],
  "geometry": {"coordinates":[-99.05,30.0667],"type":"Point"}
}