{
  "id": 1019599,
  "type": "Feature",
  "properties": {
    "tgn:hierarchy":[
        "tgn:1019599",
        "tgn:1001160",
        "tgn:7006477",
        "tgn:1000002",
        "tgn:7029392"
    ],
    "tgn:id":1019599,
    "tgn:name":"Jos\u00e9 Santos Ar\u00e9valo",
    "tgn:placetype":[
        "aat:300008347"
    ]
},
  "bbox": [],
  "geometry": {"coordinates":[-59.2333,-35.1667],"type":"Point"}
}