{
  "id": 2000106,
  "type": "Feature",
  "properties": {
    "tgn:hierarchy":[
        "tgn:2000106",
        "tgn:1000001",
        "tgn:7016172",
        "tgn:7012149",
        "tgn:7029392"
    ],
    "tgn:id":2000106,
    "tgn:name":"Ashley",
    "tgn:placetype":[
        "aat:300387145",
        "aat:300000771"
    ]
},
  "bbox": [],
  "geometry": {"coordinates":[-91.7833,33.1833],"type":"Point"}
}