<<<<<<< HEAD
{
  "id": 2250066,
  "type": "Feature",
  "properties": {
    "tgn:hierarchy":[
        "tgn:2250066",
        "tgn:1000001",
        "tgn:7012149",
        "tgn:7007157",
        "tgn:1002748",
        "tgn:7029392"
    ],
    "tgn:id":2250066,
    "tgn:name":"Collins Channel",
    "tgn:placetype":[
        "aat:300006075"
    ]
},
  "bbox": [],
  "geometry": {"coordinates":[-117.85,33.8],"type":"Point"}
}
=======
{"geometry":{"type":"Point","coordinates":[-117.850000,33.800000]},"type":"Feature","properties":{"hierarchy":["tgn:2250066","tgn:1000001","tgn:7012149","tgn:7007157","tgn:1002748","tgn:7029392"],"placetype":["aat:300006075"],"id":2250066,"name:xx":"Collins Channel"}}
>>>>>>> 03f74aca74312dbeaf24d7e61306dd6a786dc3d0
