<<<<<<< HEAD
{
  "id": 7470856,
  "type": "Feature",
  "properties": {
    "tgn:hierarchy":[
        "tgn:7470856",
        "tgn:1000004",
        "tgn:1000454",
        "tgn:1000141",
        "tgn:7029392"
    ],
    "tgn:id":7470856,
    "tgn:name":"Jiufenkeng",
    "tgn:placetype":[
        "aat:300008347"
    ]
},
  "bbox": [],
  "geometry": {"coordinates":[121.868498,25.039365],"type":"Point"}
}
=======
{"geometry":{"type":"Point","coordinates":[121.868498,25.039365]},"type":"Feature","properties":{"hierarchy":["tgn:7470856","tgn:1000004","tgn:1000454","tgn:1000141","tgn:7029392"],"placetype":["aat:300008347"],"id":7470856,"name:xx":"Jiufenkeng"}}
>>>>>>> 03f74aca74312dbeaf24d7e61306dd6a786dc3d0
