{
  "id": 7541416,
  "type": "Feature",
  "properties": {
    "tgn:hierarchy":[
        "tgn:7541416",
        "tgn:7001242",
        "tgn:7016833",
        "tgn:1001142",
        "tgn:7029392"
    ],
    "tgn:id":7541416,
    "tgn:name:en":"Nazlat an Na\u015f\u0101r\u00e1",
    "tgn:placetype":[
        "aat:300008347"
    ]
},
  "bbox": [],
  "geometry": {"coordinates":[30.853173,28.738369],"type":"Point"}
}