{
  "id": 2706030,
  "type": "Feature",
  "properties": {
    "tgn:hierarchy":[
        "tgn:2706030",
        "tgn:1002149",
        "tgn:1000001",
        "tgn:7012149",
        "tgn:7007826",
        "tgn:7029392"
    ],
    "tgn:id":2706030,
    "tgn:name":"Swagerty Creek",
    "tgn:placetype":[
        "aat:300008706"
    ]
},
  "bbox": [],
  "geometry": {"coordinates":[-94.5667,31.3833],"type":"Point"}
}