<<<<<<< HEAD
{
  "id": 7113829,
  "type": "Feature",
  "properties": {
    "tgn:hierarchy":[
        "tgn:7113829",
        "tgn:1000003",
        "tgn:7003688",
        "tgn:7000084",
        "tgn:7029392"
    ],
    "tgn:id":7113829,
    "tgn:name":"R\u00f6nnerholz",
    "tgn:placetype":[
        "aat:300000206"
    ]
},
  "bbox": [],
  "geometry": {"coordinates":[10.2,54.266667],"type":"Point"}
}
=======
{"geometry":{"type":"Point","coordinates":[10.200000,54.266667]},"type":"Feature","properties":{"hierarchy":["tgn:7113829","tgn:1000003","tgn:7003688","tgn:7000084","tgn:7029392"],"placetype":["aat:300000206"],"id":7113829,"name:xx":"R\u00f6nnerholz"}}
>>>>>>> 03f74aca74312dbeaf24d7e61306dd6a786dc3d0
