{
  "id": 7284258,
  "type": "Feature",
  "properties": {
    "tgn:hierarchy":[
        "tgn:7284258",
        "tgn:1001637",
        "tgn:1000049",
        "tgn:1000002",
        "tgn:7029392"
    ],
    "tgn:id":7284258,
    "tgn:name":"Pino Labrado, Cerro",
    "tgn:placetype":[
        "aat:300008795"
    ]
},
  "bbox": [],
  "geometry": {"coordinates":[-73.283333,-37.633333],"type":"Point"}
}