<<<<<<< HEAD
{
  "id": 2158888,
  "type": "Feature",
  "properties": {
    "tgn:hierarchy":[
        "tgn:2158888",
        "tgn:1000001",
        "tgn:7012149",
        "tgn:2001872",
        "tgn:7007825",
        "tgn:7029392"
    ],
    "tgn:id":2158888,
    "tgn:name":"Beckham Hollow",
    "tgn:placetype":[
        "aat:300008761"
    ]
},
  "bbox": [],
  "geometry": {"coordinates":[-88.0167,35.3],"type":"Point"}
}
=======
{"geometry":{"type":"Point","coordinates":[-88.016700,35.300000]},"type":"Feature","properties":{"hierarchy":["tgn:2158888","tgn:1000001","tgn:7012149","tgn:2001872","tgn:7007825","tgn:7029392"],"placetype":["aat:300008761"],"id":2158888,"name:xx":"Beckham Hollow"}}
>>>>>>> 03f74aca74312dbeaf24d7e61306dd6a786dc3d0
