{
  "id": 2685663,
  "type": "Feature",
  "properties": {
    "tgn:hierarchy":[
        "tgn:2685663",
        "tgn:1000001",
        "tgn:7012149",
        "tgn:7007158",
        "tgn:2000242",
        "tgn:7029392"
    ],
    "tgn:id":2685663,
    "tgn:name":"Spring Branch",
    "tgn:placetype":[
        "aat:300008699"
    ]
},
  "bbox": [],
  "geometry": {"coordinates":[-104.9833,37.9667],"type":"Point"}
}