{
  "id": 2424395,
  "type": "Feature",
  "properties": {
    "tgn:hierarchy":[
        "tgn:2424395",
        "tgn:1000001",
        "tgn:2001266",
        "tgn:7012149",
        "tgn:7007524",
        "tgn:7029392"
    ],
    "tgn:id":2424395,
    "tgn:name":"Johnson Butte",
    "tgn:placetype":[
        "aat:300008798"
    ]
},
  "bbox": [],
  "geometry": {"coordinates":[-111.8333,47.2833],"type":"Point"}
}