<<<<<<< HEAD
{
  "id": 7059319,
  "type": "Feature",
  "properties": {
    "tgn:hierarchy":[
        "tgn:7059319",
        "tgn:1000003",
        "tgn:7003678",
        "tgn:7000084",
        "tgn:7029392"
    ],
    "tgn:id":7059319,
    "tgn:name":"Alter-Berg",
    "tgn:placetype":[
        "aat:300008777"
    ]
},
  "bbox": [],
  "geometry": {"coordinates":[8.216667,50.8],"type":"Point"}
}
=======
{"geometry":{"type":"Point","coordinates":[8.216667,50.800000]},"type":"Feature","properties":{"hierarchy":["tgn:7059319","tgn:1000003","tgn:7003678","tgn:7000084","tgn:7029392"],"placetype":["aat:300008777"],"id":7059319,"name:xx":"Alter-Berg"}}
>>>>>>> 03f74aca74312dbeaf24d7e61306dd6a786dc3d0
