{
  "id": 7010236,
  "type": "Feature",
  "properties": {
    "tgn:hierarchy":[
        "tgn:7010236",
        "tgn:1000003",
        "tgn:7011665",
        "tgn:7006660",
        "tgn:7029392"
    ],
    "tgn:id":7010236,
    "tgn:name":"Olbia",
    "tgn:placetype":[
        "aat:300008347",
        "aat:300000810",
        "aat:300167671"
    ]
},
  "bbox": [],
  "geometry": {"coordinates":[31.903,46.692],"type":"Point"}
}