{
  "id": 1007265,
  "type": "Feature",
  "properties": {
    "tgn:hierarchy":[
        "tgn:1007265",
        "tgn:7019094",
        "tgn:7002444",
        "tgn:1000003",
        "tgn:7008591",
        "tgn:7029392"
    ],
    "tgn:id":1007265,
    "tgn:name:en":"Great Cumbrae Island",
    "tgn:placetype":[
        "aat:300008791"
    ]
},
  "bbox": [],
  "geometry": {"coordinates":[-4.95,55.766667],"type":"Point"}
}