{
  "id": 1120668,
  "type": "Feature",
  "properties": {
    "tgn:hierarchy":[
        "tgn:1120668",
        "tgn:1000001",
        "tgn:1002903",
        "tgn:7012149",
        "tgn:7007565",
        "tgn:7029392"
    ],
    "tgn:id":1120668,
    "tgn:name":"Washington Valley Reservoir",
    "tgn:placetype":[
        "aat:300006191"
    ]
},
  "bbox": [],
  "geometry": {"coordinates":[-74.55,40.5833],"type":"Point"}
}