{
  "id": 1056474,
  "type": "Feature",
  "properties": {
    "tgn:hierarchy":[
        "tgn:1056474",
        "tgn:1000004",
        "tgn:1003424",
        "tgn:7018214",
        "tgn:7002435",
        "tgn:7029392"
    ],
    "tgn:id":1056474,
    "tgn:name":"Liski",
    "tgn:placetype":[
        "aat:300008347"
    ]
},
  "bbox": [],
  "geometry": {"coordinates":[39.4833,50.9333],"type":"Point"}
}