{
  "id": 7501386,
  "type": "Feature",
  "properties": {
    "tgn:hierarchy":[
        "tgn:7501386",
        "tgn:7488858",
        "tgn:1000004",
        "tgn:1000141",
        "tgn:7029392"
    ],
    "tgn:id":7501386,
    "tgn:name":"Zhaoping Zhan",
    "tgn:placetype":[
        "aat:300007783"
    ]
},
  "bbox": [],
  "geometry": {"coordinates":[120.814444,23.515556],"type":"Point"}
}