{
  "id": 2730839,
  "type": "Feature",
  "properties": {
    "tgn:hierarchy":[
        "tgn:2730839",
        "tgn:1000001",
        "tgn:2001471",
        "tgn:7012149",
        "tgn:7007709",
        "tgn:7029392"
    ],
    "tgn:id":2730839,
    "tgn:name":"Tub Mill Creek",
    "tgn:placetype":[
        "aat:300008706"
    ]
},
  "bbox": [],
  "geometry": {"coordinates":[-78.5333,34.6333],"type":"Point"}
}