{
  "id": 2643607,
  "type": "Feature",
  "properties": {
    "tgn:hierarchy":[
        "tgn:2643607",
        "tgn:1000001",
        "tgn:7012149",
        "tgn:2000840",
        "tgn:7007255",
        "tgn:7029392"
    ],
    "tgn:id":2643607,
    "tgn:name":"Sandy Ridge",
    "tgn:placetype":[
        "aat:300266640"
    ]
},
  "bbox": [],
  "geometry": {"coordinates":[-84.2333,37.2667],"type":"Point"}
}