{
  "id": 1058871,
  "type": "Feature",
  "properties": {
    "tgn:hierarchy":[
        "tgn:1058871",
        "tgn:1000004",
        "tgn:7011573",
        "tgn:7018214",
        "tgn:7002435",
        "tgn:7029392"
    ],
    "tgn:id":1058871,
    "tgn:name":"Rastovtsy",
    "tgn:placetype":[
        "aat:300008347"
    ]
},
  "bbox": [],
  "geometry": {"coordinates":[37.5833,56.65],"type":"Point"}
}