{
  "id": 7474218,
  "type": "Feature",
  "properties": {
    "tgn:hierarchy":[
        "tgn:7474218",
        "tgn:1000004",
        "tgn:1000454",
        "tgn:1000141",
        "tgn:7029392"
    ],
    "tgn:id":7474218,
    "tgn:name":"Nanbangliao",
    "tgn:placetype":[
        "aat:300008347"
    ]
},
  "bbox": [],
  "geometry": {"coordinates":[121.62208,24.975739],"type":"Point"}
}