{
  "id": 2338654,
  "type": "Feature",
  "properties": {
    "tgn:hierarchy":[
        "tgn:2338654",
        "tgn:1000001",
        "tgn:7012149",
        "tgn:2000183",
        "tgn:7007157",
        "tgn:7029392"
    ],
    "tgn:id":2338654,
    "tgn:name":"Francis Lake",
    "tgn:placetype":[
        "aat:300008680"
    ]
},
  "bbox": [],
  "geometry": {"coordinates":[-118.7167,37.4333],"type":"Point"}
}