<<<<<<< HEAD
{
  "id": 2338654,
  "type": "Feature",
  "properties": {
    "tgn:hierarchy":[
        "tgn:2338654",
        "tgn:1000001",
        "tgn:7012149",
        "tgn:2000183",
        "tgn:7007157",
        "tgn:7029392"
    ],
    "tgn:id":2338654,
    "tgn:name":"Francis Lake",
    "tgn:placetype":[
        "aat:300008680"
    ]
},
  "bbox": [],
  "geometry": {"coordinates":[-118.7167,37.4333],"type":"Point"}
}
=======
{"geometry":{"type":"Point","coordinates":[-118.716700,37.433300]},"type":"Feature","properties":{"hierarchy":["tgn:2338654","tgn:1000001","tgn:7012149","tgn:2000183","tgn:7007157","tgn:7029392"],"placetype":["aat:300008680"],"id":2338654,"name:xx":"Francis Lake"}}
>>>>>>> 03f74aca74312dbeaf24d7e61306dd6a786dc3d0
