{
  "id": 1128339,
  "type": "Feature",
  "properties": {
    "tgn:hierarchy":[
        "tgn:1128339",
        "tgn:1001985",
        "tgn:1000002",
        "tgn:1000059",
        "tgn:7029392"
    ],
    "tgn:id":1128339,
    "tgn:name":"Palmar, R\u00edo",
    "tgn:placetype":[
        "aat:300008707"
    ]
},
  "bbox": [],
  "geometry": {"coordinates":[-71.8667,10.1833],"type":"Point"}
}