{
  "id": 7593646,
  "type": "Feature",
  "properties": {
    "tgn:hierarchy":[
        "tgn:7593646",
        "tgn:7005518",
        "tgn:1000001",
        "tgn:7005502",
        "tgn:7029392"
    ],
    "tgn:id":7593646,
    "tgn:name":"Ganthier",
    "tgn:placetype":[
        "aat:300008347"
    ]
},
  "bbox": [],
  "geometry": {"coordinates":[-72.065,18.53],"type":"Point"}
}