<<<<<<< HEAD
{
  "id": 7054020,
  "type": "Feature",
  "properties": {
    "tgn:hierarchy":[
        "tgn:7054020",
        "tgn:7004597",
        "tgn:1000003",
        "tgn:7008516",
        "tgn:1000080",
        "tgn:7029392"
    ],
    "tgn:id":7054020,
    "tgn:name":"Montebaranzone",
    "tgn:placetype":[
        "aat:300008347"
    ]
},
  "bbox": [],
  "geometry": {"coordinates":[10.766667,44.483333],"type":"Point"}
}
=======
{"geometry":{"type":"Point","coordinates":[10.766667,44.483333]},"type":"Feature","properties":{"hierarchy":["tgn:7054020","tgn:7004597","tgn:1000003","tgn:7008516","tgn:1000080","tgn:7029392"],"placetype":["aat:300008347"],"id":7054020,"name:xx":"Montebaranzone"}}
>>>>>>> 03f74aca74312dbeaf24d7e61306dd6a786dc3d0
