{
  "id": 7588989,
  "type": "Feature",
  "properties": {
    "tgn:hierarchy":[
        "tgn:7588989",
        "tgn:1000004",
        "tgn:7000198",
        "tgn:7000799",
        "tgn:7029392"
    ],
    "tgn:id":7588989,
    "tgn:name:en":"Amargad",
    "tgn:placetype":[
        "aat:300008347"
    ]
},
  "bbox": [],
  "geometry": {"coordinates":[74.459963,34.256738],"type":"Point"}
}