<<<<<<< HEAD
{
  "id": 2764126,
  "type": "Feature",
  "properties": {
    "tgn:hierarchy":[
        "tgn:2764126",
        "tgn:1000001",
        "tgn:7012149",
        "tgn:2000401",
        "tgn:7007248",
        "tgn:7029392"
    ],
    "tgn:id":2764126,
    "tgn:name":"Wheeler Lake",
    "tgn:placetype":[
        "aat:300006191"
    ]
},
  "bbox": [],
  "geometry": {"coordinates":[-84.8667,33.8833],"type":"Point"}
}
=======
{"geometry":{"type":"Point","coordinates":[-84.866700,33.883300]},"type":"Feature","properties":{"hierarchy":["tgn:2764126","tgn:1000001","tgn:7012149","tgn:2000401","tgn:7007248","tgn:7029392"],"placetype":["aat:300006191"],"id":2764126,"name:xx":"Wheeler Lake"}}
>>>>>>> 03f74aca74312dbeaf24d7e61306dd6a786dc3d0
