<<<<<<< HEAD
{
  "id": 2256147,
  "type": "Feature",
  "properties": {
    "tgn:hierarchy":[
        "tgn:2256147",
        "tgn:1000001",
        "tgn:7006451",
        "tgn:7012149",
        "tgn:2000103",
        "tgn:7029392"
    ],
    "tgn:id":2256147,
    "tgn:name":"Copper Ridge",
    "tgn:placetype":[
        "aat:300266640"
    ]
},
  "bbox": [],
  "geometry": {"coordinates":[-113.2667,34.55],"type":"Point"}
}
=======
{"geometry":{"type":"Point","coordinates":[-113.266700,34.550000]},"type":"Feature","properties":{"hierarchy":["tgn:2256147","tgn:1000001","tgn:7006451","tgn:7012149","tgn:2000103","tgn:7029392"],"placetype":["aat:300266640"],"id":2256147,"name:xx":"Copper Ridge"}}
>>>>>>> 03f74aca74312dbeaf24d7e61306dd6a786dc3d0
