{
  "id": 7226552,
  "type": "Feature",
  "properties": {
    "tgn:hierarchy":[
        "tgn:7226552",
        "tgn:7002748",
        "tgn:7001399",
        "tgn:1000003",
        "tgn:1000074",
        "tgn:7029392"
    ],
    "tgn:id":7226552,
    "tgn:name":"Pro\u00e9rna",
    "tgn:placetype":[
        "aat:300008347"
    ]
},
  "bbox": [],
  "geometry": {"coordinates":[22.25,39.233333],"type":"Point"}
}