<<<<<<< HEAD
{
  "id": 7051113,
  "type": "Feature",
  "properties": {
    "tgn:hierarchy":[
        "tgn:7051113",
        "tgn:1003483",
        "tgn:1000003",
        "tgn:7003240",
        "tgn:1000080",
        "tgn:7029392"
    ],
    "tgn:id":7051113,
    "tgn:name":"Nesci, Monte",
    "tgn:placetype":[
        "aat:300008795"
    ]
},
  "bbox": [],
  "geometry": {"coordinates":[12.333333,43.6],"type":"Point"}
}
=======
{"geometry":{"type":"Point","coordinates":[12.333333,43.600000]},"type":"Feature","properties":{"hierarchy":["tgn:7051113","tgn:1003483","tgn:1000003","tgn:7003240","tgn:1000080","tgn:7029392"],"placetype":["aat:300008795"],"id":7051113,"name:xx":"Nesci, Monte"}}
>>>>>>> 03f74aca74312dbeaf24d7e61306dd6a786dc3d0
