{
  "id": 7209303,
  "type": "Feature",
  "properties": {
    "tgn:hierarchy":[
        "tgn:7209303",
        "tgn:1000003",
        "tgn:7000094",
        "tgn:7000084",
        "tgn:7029392"
    ],
    "tgn:id":7209303,
    "tgn:name":"Benzer Wald",
    "tgn:placetype":[
        "aat:300008863"
    ]
},
  "bbox": [],
  "geometry": {"coordinates":[11.133333,53.25],"type":"Point"}
}