{
  "id": 2742807,
  "type": "Feature",
  "properties": {
    "tgn:hierarchy":[
        "tgn:2742807",
        "tgn:1000001",
        "tgn:2001260",
        "tgn:7012149",
        "tgn:7007524",
        "tgn:7029392"
    ],
    "tgn:id":2742807,
    "tgn:name":"Van Dyke Gulch",
    "tgn:placetype":[
        "aat:300008761"
    ]
},
  "bbox": [],
  "geometry": {"coordinates":[-112.8167,45.35],"type":"Point"}
}