{
  "id": 2621097,
  "type": "Feature",
  "properties": {
    "tgn:hierarchy":[
        "tgn:2621097",
        "tgn:1000001",
        "tgn:7012149",
        "tgn:2000912",
        "tgn:7007256",
        "tgn:7029392"
    ],
    "tgn:id":2621097,
    "tgn:name":"Road Lake",
    "tgn:placetype":[
        "aat:300008680"
    ]
},
  "bbox": [],
  "geometry": {"coordinates":[-89.7333,30.9833],"type":"Point"}
}