{
  "id": 1088273,
  "type": "Feature",
  "properties": {
    "tgn:hierarchy":[
        "tgn:1088273",
        "tgn:7001242",
        "tgn:1001455",
        "tgn:1000153",
        "tgn:7029392"
    ],
    "tgn:id":1088273,
    "tgn:name":"Pousse",
    "tgn:placetype":[
        "aat:300008347"
    ]
},
  "bbox": [],
  "geometry": {"coordinates":[15.05,10.85],"type":"Point"}
}