<<<<<<< HEAD
{
  "id": 2151394,
  "type": "Feature",
  "properties": {
    "tgn:hierarchy":[
        "tgn:2151394",
        "tgn:1000001",
        "tgn:7012149",
        "tgn:7014185",
        "tgn:7007710",
        "tgn:7029392"
    ],
    "tgn:id":2151394,
    "tgn:name":"Bates Run",
    "tgn:placetype":[
        "aat:300008699"
    ]
},
  "bbox": [],
  "geometry": {"coordinates":[-79.9667,39.95],"type":"Point"}
}
=======
{"geometry":{"type":"Point","coordinates":[-79.966700,39.950000]},"type":"Feature","properties":{"hierarchy":["tgn:2151394","tgn:1000001","tgn:7012149","tgn:7014185","tgn:7007710","tgn:7029392"],"placetype":["aat:300008699"],"id":2151394,"name:xx":"Bates Run"}}
>>>>>>> 03f74aca74312dbeaf24d7e61306dd6a786dc3d0
