{
  "id": 2151394,
  "type": "Feature",
  "properties": {
    "tgn:hierarchy":[
        "tgn:2151394",
        "tgn:1000001",
        "tgn:7012149",
        "tgn:7014185",
        "tgn:7007710",
        "tgn:7029392"
    ],
    "tgn:id":2151394,
    "tgn:name":"Bates Run",
    "tgn:placetype":[
        "aat:300008699"
    ]
},
  "bbox": [],
  "geometry": {"coordinates":[-79.9667,39.95],"type":"Point"}
}