{
  "id": 1085855,
  "type": "Feature",
  "properties": {
    "tgn:hierarchy":[
        "tgn:1085855",
        "tgn:1001438",
        "tgn:1000004",
        "tgn:7018451",
        "tgn:1000144",
        "tgn:7029392"
    ],
    "tgn:id":1085855,
    "tgn:name":"Uzumlu",
    "tgn:placetype":[
        "aat:300008347"
    ]
},
  "bbox": [],
  "geometry": {"coordinates":[29.2333,36.7333],"type":"Point"}
}