{
  "id": 7006612,
  "type": "Feature",
  "properties": {
    "tgn:hierarchy":[
        "tgn:7006612",
        "tgn:1000003",
        "tgn:7006542",
        "tgn:7029392"
    ],
    "tgn:id":7006612,
    "tgn:name":"Tel\u0161iai",
    "tgn:placetype":[
        "aat:300387064",
        "aat:300265612",
        "aat:300387081"
    ]
},
  "bbox": [],
  "geometry": {"coordinates":[22.25,56.983],"type":"Point"}
}