{
  "id": 7413008,
  "type": "Feature",
  "properties": {
    "tgn:hierarchy":[
        "tgn:7413008",
        "tgn:7005580",
        "tgn:1000001",
        "tgn:7005560",
        "tgn:7029392"
    ],
    "tgn:id":7413008,
    "tgn:name":"Pedernal",
    "tgn:placetype":[
        "aat:300008347"
    ]
},
  "bbox": [],
  "geometry": {"coordinates":[-92.458333,16.75],"type":"Point"}
}