{
  "id": 1123712,
  "type": "Feature",
  "properties": {
    "tgn:hierarchy":[
        "tgn:1123712",
        "tgn:7005685",
        "tgn:1000001",
        "tgn:7024197",
        "tgn:7029392"
    ],
    "tgn:id":1123712,
    "tgn:name":"Ellice",
    "tgn:placetype":[
        "aat:300008707"
    ]
},
  "bbox": [],
  "geometry": {"coordinates":[-103.4167,68.0333],"type":"Point"}
}