{
  "id": 2572243,
  "type": "Feature",
  "properties": {
    "tgn:hierarchy":[
        "tgn:2572243",
        "tgn:1000001",
        "tgn:2000920",
        "tgn:7012149",
        "tgn:7007515",
        "tgn:7029392"
    ],
    "tgn:id":2572243,
    "tgn:name":"Peabody Pond",
    "tgn:placetype":[
        "aat:300008680"
    ]
},
  "bbox": [],
  "geometry": {"coordinates":[-70.6833,43.9333],"type":"Point"}
}