{
  "id": 1086440,
  "type": "Feature",
  "properties": {
    "tgn:hierarchy":[
        "tgn:1086440",
        "tgn:7018461",
        "tgn:1000004",
        "tgn:7018455",
        "tgn:1000144",
        "tgn:7029392"
    ],
    "tgn:id":1086440,
    "tgn:name":"Igdir",
    "tgn:placetype":[
        "aat:300008347"
    ]
},
  "bbox": [],
  "geometry": {"coordinates":[44.0333,39.9333],"type":"Point"}
}