{
  "id": 7338549,
  "type": "Feature",
  "properties": {
    "tgn:hierarchy":[
        "tgn:7338549",
        "tgn:7008911",
        "tgn:1000003",
        "tgn:7002763",
        "tgn:1000095",
        "tgn:7029392"
    ],
    "tgn:id":7338549,
    "tgn:name":"Dou",
    "tgn:placetype":[
        "aat:300008347"
    ]
},
  "bbox": [],
  "geometry": {"coordinates":[-6.85,43.066667],"type":"Point"}
}