<<<<<<< HEAD
{
  "id": 7050548,
  "type": "Feature",
  "properties": {
    "tgn:hierarchy":[
        "tgn:7050548",
        "tgn:7003167",
        "tgn:1000003",
        "tgn:7009760",
        "tgn:1000080",
        "tgn:7029392"
    ],
    "tgn:id":7050548,
    "tgn:name":"Lappato",
    "tgn:placetype":[
        "aat:300008347"
    ]
},
  "bbox": [],
  "geometry": {"coordinates":[10.65,43.9],"type":"Point"}
}
=======
{"geometry":{"type":"Point","coordinates":[10.650000,43.900000]},"type":"Feature","properties":{"hierarchy":["tgn:7050548","tgn:7003167","tgn:1000003","tgn:7009760","tgn:1000080","tgn:7029392"],"placetype":["aat:300008347"],"id":7050548,"name:xx":"Lappato"}}
>>>>>>> 03f74aca74312dbeaf24d7e61306dd6a786dc3d0
