<<<<<<< HEAD
{
  "id": 7026382,
  "type": "Feature",
  "properties": {
    "tgn:hierarchy":[
        "tgn:7026382",
        "tgn:7002445",
        "tgn:1000003",
        "tgn:7008591",
        "tgn:7029392"
    ],
    "tgn:id":7026382,
    "tgn:name:en":"West Berkshire",
    "tgn:placetype":[
        "aat:300387064",
        "aat:300387145",
        "aat:300387071"
    ]
},
  "bbox": [],
  "geometry": {"coordinates":[-1.25,51.416667],"type":"Point"}
}
=======
{"geometry":{"type":"Point","coordinates":[-1.250000,51.416667]},"type":"Feature","properties":{"hierarchy":["tgn:7026382","tgn:7002445","tgn:1000003","tgn:7008591","tgn:7029392"],"placetype":["aat:300387064","aat:300387145","aat:300387071"],"name:en":"West Berkshire","id":7026382}}
>>>>>>> 03f74aca74312dbeaf24d7e61306dd6a786dc3d0
