{
  "id": 2751702,
  "type": "Feature",
  "properties": {
    "tgn:hierarchy":[
        "tgn:2751702",
        "tgn:1000001",
        "tgn:7012149",
        "tgn:7007523",
        "tgn:7029392"
    ],
    "tgn:id":2751702,
    "tgn:name":"Warren Branch",
    "tgn:placetype":[
        "aat:300008699"
    ]
},
  "bbox": [],
  "geometry": {"coordinates":[-91.65,38.7667],"type":"Point"}
}