{
  "id": 1072559,
  "type": "Feature",
  "properties": {
    "tgn:hierarchy":[
        "tgn:1072559",
        "tgn:1000004",
        "tgn:7001800",
        "tgn:1000111",
        "tgn:7029392"
    ],
    "tgn:id":1072559,
    "tgn:name":"Wenchang",
    "tgn:placetype":[
        "aat:300008347"
    ]
},
  "bbox": [],
  "geometry": {"coordinates":[110.7667,19.6833],"type":"Point"}
}