{
  "id": 2446889,
  "type": "Feature",
  "properties": {
    "tgn:hierarchy":[
        "tgn:2446889",
        "tgn:1000001",
        "tgn:7012149",
        "tgn:2000340",
        "tgn:7007248",
        "tgn:7029392"
    ],
    "tgn:id":2446889,
    "tgn:name":"Liberty",
    "tgn:placetype":[
        "aat:300008347"
    ]
},
  "bbox": [],
  "geometry": {"coordinates":[-85.0667,31.1667],"type":"Point"}
}