{
  "id": 1131213,
  "type": "Feature",
  "properties": {
    "tgn:hierarchy":[
        "tgn:1131213",
        "tgn:7001242",
        "tgn:1000198",
        "tgn:7029392"
    ],
    "tgn:id":1131213,
    "tgn:name":"Ugab",
    "tgn:placetype":[
        "aat:300008707"
    ]
},
  "bbox": [],
  "geometry": {"coordinates":[13.6167,-21.1833],"type":"Point"}
}