{
  "id": 2288810,
  "type": "Feature",
  "properties": {
    "tgn:hierarchy":[
        "tgn:2288810",
        "tgn:1000001",
        "tgn:7012149",
        "tgn:2001197",
        "tgn:7007523",
        "tgn:7029392"
    ],
    "tgn:id":2288810,
    "tgn:name":"Ditch Number 35",
    "tgn:placetype":[
        "aat:300006075"
    ]
},
  "bbox": [],
  "geometry": {"coordinates":[-90.1167,36.0667],"type":"Point"}
}