{
  "id": 1075300,
  "type": "Feature",
  "properties": {
    "tgn:hierarchy":[
        "tgn:1075300",
        "tgn:1000004",
        "tgn:7000198",
        "tgn:7016788",
        "tgn:7029392"
    ],
    "tgn:id":1075300,
    "tgn:name:en":"Gangdh\u0101r",
    "tgn:placetype":[
        "aat:300008347"
    ]
},
  "bbox": [],
  "geometry": {"coordinates":[75.62164,23.940719],"type":"Point"}
}