{
  "id": 7480649,
  "type": "Feature",
  "properties": {
    "tgn:hierarchy":[
        "tgn:7480649",
        "tgn:1000004",
        "tgn:7490934",
        "tgn:1000141",
        "tgn:7029392"
    ],
    "tgn:id":7480649,
    "tgn:name":"Taiwan Shengli Xinying Yiyuan Beimen Fenyuan",
    "tgn:placetype":[
        "aat:300006676"
    ]
},
  "bbox": [],
  "geometry": {"coordinates":[120.12856,23.249908],"type":"Point"}
}