<<<<<<< HEAD
{
  "id": 7480649,
  "type": "Feature",
  "properties": {
    "tgn:hierarchy":[
        "tgn:7480649",
        "tgn:1000004",
        "tgn:7490934",
        "tgn:1000141",
        "tgn:7029392"
    ],
    "tgn:id":7480649,
    "tgn:name":"Taiwan Shengli Xinying Yiyuan Beimen Fenyuan",
    "tgn:placetype":[
        "aat:300006676"
    ]
},
  "bbox": [],
  "geometry": {"coordinates":[120.12856,23.249908],"type":"Point"}
}
=======
{"geometry":{"type":"Point","coordinates":[120.128560,23.249908]},"type":"Feature","properties":{"hierarchy":["tgn:7480649","tgn:1000004","tgn:7490934","tgn:1000141","tgn:7029392"],"placetype":["aat:300006676"],"id":7480649,"name:xx":"Taiwan Shengli Xinying Yiyuan Beimen Fenyuan"}}
>>>>>>> 03f74aca74312dbeaf24d7e61306dd6a786dc3d0
