{
  "id": 7468065,
  "type": "Feature",
  "properties": {
    "tgn:hierarchy":[
        "tgn:7468065",
        "tgn:7488858",
        "tgn:1000004",
        "tgn:1000141",
        "tgn:7029392"
    ],
    "tgn:id":7468065,
    "tgn:name":"Puti Si",
    "tgn:placetype":[
        "aat:300007595"
    ]
},
  "bbox": [],
  "geometry": {"coordinates":[120.828149,24.033015],"type":"Point"}
}