{
  "id": 7418670,
  "type": "Feature",
  "properties": {
    "tgn:hierarchy":[
        "tgn:7418670",
        "tgn:7005584",
        "tgn:1000001",
        "tgn:7005560",
        "tgn:7029392"
    ],
    "tgn:id":7418670,
    "tgn:name":"San Jer\u00f3nimo",
    "tgn:placetype":[
        "aat:300008347"
    ]
},
  "bbox": [],
  "geometry": {"coordinates":[-100.658333,21.143611],"type":"Point"}
}