<<<<<<< HEAD
{
  "id": 7175106,
  "type": "Feature",
  "properties": {
    "tgn:hierarchy":[
        "tgn:7175106",
        "tgn:1000003",
        "tgn:7003677",
        "tgn:7000084",
        "tgn:7029392"
    ],
    "tgn:id":7175106,
    "tgn:name":"Grimlinghausen",
    "tgn:placetype":[
        "aat:300008347"
    ]
},
  "bbox": [],
  "geometry": {"coordinates":[8.45,51.383333],"type":"Point"}
}
=======
{"geometry":{"type":"Point","coordinates":[8.450000,51.383333]},"type":"Feature","properties":{"hierarchy":["tgn:7175106","tgn:1000003","tgn:7003677","tgn:7000084","tgn:7029392"],"placetype":["aat:300008347"],"id":7175106,"name:xx":"Grimlinghausen"}}
>>>>>>> 03f74aca74312dbeaf24d7e61306dd6a786dc3d0
