{
  "id": 7472741,
  "type": "Feature",
  "properties": {
    "tgn:hierarchy":[
        "tgn:7472741",
        "tgn:1000004",
        "tgn:7001014",
        "tgn:1000141",
        "tgn:7029392"
    ],
    "tgn:id":7472741,
    "tgn:name":"Huilai",
    "tgn:placetype":[
        "aat:300008347"
    ]
},
  "bbox": [],
  "geometry": {"coordinates":[120.395514,23.765006],"type":"Point"}
}