{
  "id": 2143003,
  "type": "Feature",
  "properties": {
    "tgn:hierarchy":[
        "tgn:2143003",
        "tgn:1000001",
        "tgn:7012149",
        "tgn:2001899",
        "tgn:7007825",
        "tgn:7029392"
    ],
    "tgn:id":2143003,
    "tgn:name":"Baggett Branch",
    "tgn:placetype":[
        "aat:300008699"
    ]
},
  "bbox": [],
  "geometry": {"coordinates":[-87.4167,36.3667],"type":"Point"}
}