{
  "id": 7375344,
  "type": "Feature",
  "properties": {
    "tgn:hierarchy":[
        "tgn:7375344",
        "tgn:1000001",
        "tgn:1001893",
        "tgn:7005560",
        "tgn:7029392"
    ],
    "tgn:id":7375344,
    "tgn:name":"Lesna, Sierra de la",
    "tgn:placetype":[
        "aat:300008795"
    ]
},
  "bbox": [],
  "geometry": {"coordinates":[-112.183333,31.666667],"type":"Point"}
}