{
  "id": 2519914,
  "type": "Feature",
  "properties": {
    "tgn:hierarchy":[
        "tgn:2519914",
        "tgn:1000001",
        "tgn:7012149",
        "tgn:7007710",
        "tgn:7029392"
    ],
    "tgn:id":2519914,
    "tgn:name":"Molasses Creek",
    "tgn:placetype":[
        "aat:300008706"
    ]
},
  "bbox": [],
  "geometry": {"coordinates":[-75.4333,40.45],"type":"Point"}
}