{
  "id": 2492327,
  "type": "Feature",
  "properties": {
    "tgn:hierarchy":[
        "tgn:2492327",
        "tgn:1000001",
        "tgn:7012149",
        "tgn:1002877",
        "tgn:7007706",
        "tgn:7029392"
    ],
    "tgn:id":2492327,
    "tgn:name":"Margaret, Lake",
    "tgn:placetype":[
        "aat:300006191"
    ]
},
  "bbox": [],
  "geometry": {"coordinates":[-82.9833,38.85],"type":"Point"}
}