<<<<<<< HEAD
{
  "id": 7487287,
  "type": "Feature",
  "properties": {
    "tgn:hierarchy":[
        "tgn:7487287",
        "tgn:7488858",
        "tgn:1000004",
        "tgn:1000141",
        "tgn:7029392"
    ],
    "tgn:id":7487287,
    "tgn:name":"Xishui",
    "tgn:placetype":[
        "aat:300008347"
    ]
},
  "bbox": [],
  "geometry": {"coordinates":[120.917161,23.923371],"type":"Point"}
}
=======
{"geometry":{"type":"Point","coordinates":[120.917161,23.923371]},"type":"Feature","properties":{"hierarchy":["tgn:7487287","tgn:7488858","tgn:1000004","tgn:1000141","tgn:7029392"],"placetype":["aat:300008347"],"id":7487287,"name:xx":"Xishui"}}
>>>>>>> 03f74aca74312dbeaf24d7e61306dd6a786dc3d0
