{
  "id": 7487287,
  "type": "Feature",
  "properties": {
    "tgn:hierarchy":[
        "tgn:7487287",
        "tgn:7488858",
        "tgn:1000004",
        "tgn:1000141",
        "tgn:7029392"
    ],
    "tgn:id":7487287,
    "tgn:name":"Xishui",
    "tgn:placetype":[
        "aat:300008347"
    ]
},
  "bbox": [],
  "geometry": {"coordinates":[120.917161,23.923371],"type":"Point"}
}