{
  "id": 2430769,
  "type": "Feature",
  "properties": {
    "tgn:hierarchy":[
        "tgn:2430769",
        "tgn:1007657",
        "tgn:1002534",
        "tgn:1000001",
        "tgn:7012149",
        "tgn:7007249",
        "tgn:7029392"
    ],
    "tgn:id":2430769,
    "tgn:name":"Kamakeanu",
    "tgn:placetype":[
        "aat:300008798"
    ]
},
  "bbox": [],
  "geometry": {"coordinates":[-159.55,22.15],"type":"Point"}
}