{
  "id": 2122226,
  "type": "Feature",
  "properties": {
    "tgn:hierarchy":[
        "tgn:2122226",
        "tgn:2002307",
        "tgn:1000001",
        "tgn:7012149",
        "tgn:7007922",
        "tgn:7029392"
    ],
    "tgn:id":2122226,
    "tgn:name":"Reeve",
    "tgn:placetype":[
        "aat:300008347"
    ]
},
  "bbox": [],
  "geometry": {"coordinates":[-92.1167,45.2333],"type":"Point"}
}