{
  "id": 7559461,
  "type": "Feature",
  "properties": {
    "tgn:hierarchy":[
        "tgn:7559461",
        "tgn:1000004",
        "tgn:1001869",
        "tgn:7000198",
        "tgn:7029392"
    ],
    "tgn:id":7559461,
    "tgn:name:en":"Raipura",
    "tgn:placetype":[
        "aat:300008347"
    ]
},
  "bbox": [],
  "geometry": {"coordinates":[73.483333,21.833333],"type":"Point"}
}