{
  "id": 7206028,
  "type": "Feature",
  "properties": {
    "tgn:hierarchy":[
        "tgn:7206028",
        "tgn:1000003",
        "tgn:7003682",
        "tgn:7000084",
        "tgn:7029392"
    ],
    "tgn:id":7206028,
    "tgn:name":"B\u00fcdesheim",
    "tgn:placetype":[
        "aat:300008347"
    ]
},
  "bbox": [],
  "geometry": {"coordinates":[6.55,50.216667],"type":"Point"}
}