{
  "id": 7574007,
  "type": "Feature",
  "properties": {
    "tgn:hierarchy":[
        "tgn:7574007",
        "tgn:1000004",
        "tgn:7000198",
        "tgn:7016722",
        "tgn:7029392"
    ],
    "tgn:id":7574007,
    "tgn:name:en":"Haidar\u0101b\u0101d",
    "tgn:placetype":[
        "aat:300008347"
    ]
},
  "bbox": [],
  "geometry": {"coordinates":[80.417656,28.04576],"type":"Point"}
}