{
  "id": 2238802,
  "type": "Feature",
  "properties": {
    "tgn:hierarchy":[
        "tgn:2238802",
        "tgn:1000001",
        "tgn:7012149",
        "tgn:2001216",
        "tgn:7007523",
        "tgn:7029392"
    ],
    "tgn:id":2238802,
    "tgn:name":"Christian Spring",
    "tgn:placetype":[
        "aat:300008697"
    ]
},
  "bbox": [],
  "geometry": {"coordinates":[-94.1167,36.7333],"type":"Point"}
}