{
  "id": 2744701,
  "type": "Feature",
  "properties": {
    "tgn:hierarchy":[
        "tgn:2744701",
        "tgn:1000001",
        "tgn:1002902",
        "tgn:7012149",
        "tgn:7007516",
        "tgn:7029392"
    ],
    "tgn:id":2744701,
    "tgn:name":"Victor Point",
    "tgn:placetype":[
        "aat:300008850"
    ]
},
  "bbox": [],
  "geometry": {"coordinates":[-75.8333,38.2333],"type":"Point"}
}