{
  "id": 1097610,
  "type": "Feature",
  "properties": {
    "tgn:hierarchy":[
        "tgn:1097610",
        "tgn:7000490",
        "tgn:1000006",
        "tgn:7001830",
        "tgn:7029392"
    ],
    "tgn:id":1097610,
    "tgn:name":"Moreton",
    "tgn:placetype":[
        "aat:300008347"
    ]
},
  "bbox": [],
  "geometry": {"coordinates":[142.6333,-12.4667],"type":"Point"}
}