{
  "id": 7057162,
  "type": "Feature",
  "properties": {
    "tgn:hierarchy":[
        "tgn:7057162",
        "tgn:7005852",
        "tgn:1000003",
        "tgn:7003237",
        "tgn:1000080",
        "tgn:7029392"
    ],
    "tgn:id":7057162,
    "tgn:name":"Balisio, Colle di",
    "tgn:placetype":[
        "aat:300259572"
    ]
},
  "bbox": [],
  "geometry": {"coordinates":[9.433333,45.916667],"type":"Point"}
}