<<<<<<< HEAD
{
  "id": 7057162,
  "type": "Feature",
  "properties": {
    "tgn:hierarchy":[
        "tgn:7057162",
        "tgn:7005852",
        "tgn:1000003",
        "tgn:7003237",
        "tgn:1000080",
        "tgn:7029392"
    ],
    "tgn:id":7057162,
    "tgn:name":"Balisio, Colle di",
    "tgn:placetype":[
        "aat:300259572"
    ]
},
  "bbox": [],
  "geometry": {"coordinates":[9.433333,45.916667],"type":"Point"}
}
=======
{"geometry":{"type":"Point","coordinates":[9.433333,45.916667]},"type":"Feature","properties":{"hierarchy":["tgn:7057162","tgn:7005852","tgn:1000003","tgn:7003237","tgn:1000080","tgn:7029392"],"placetype":["aat:300259572"],"id":7057162,"name:xx":"Balisio, Colle di"}}
>>>>>>> 03f74aca74312dbeaf24d7e61306dd6a786dc3d0
