{
  "id": 2627762,
  "type": "Feature",
  "properties": {
    "tgn:hierarchy":[
        "tgn:2627762",
        "tgn:1000001",
        "tgn:7012149",
        "tgn:2000208",
        "tgn:7007158",
        "tgn:7029392"
    ],
    "tgn:id":2627762,
    "tgn:name":"Rogers Reservoir",
    "tgn:placetype":[
        "aat:300006191"
    ]
},
  "bbox": [],
  "geometry": {"coordinates":[-108.8333,37.85],"type":"Point"}
}