{
  "id": 2416701,
  "type": "Feature",
  "properties": {
    "tgn:hierarchy":[
        "tgn:2416701",
        "tgn:1000001",
        "tgn:7012149",
        "tgn:2001927",
        "tgn:7007825",
        "tgn:7029392"
    ],
    "tgn:id":2416701,
    "tgn:name":"Jack Lot Hollow",
    "tgn:placetype":[
        "aat:300008761"
    ]
},
  "bbox": [],
  "geometry": {"coordinates":[-87.7833,35.3833],"type":"Point"}
}