{
  "id": 2718893,
  "type": "Feature",
  "properties": {
    "tgn:hierarchy":[
        "tgn:2718893",
        "tgn:2002306",
        "tgn:1000001",
        "tgn:7012149",
        "tgn:7007922",
        "tgn:7029392"
    ],
    "tgn:id":2718893,
    "tgn:name":"Thornapple Creek",
    "tgn:placetype":[
        "aat:300008706"
    ]
},
  "bbox": [],
  "geometry": {"coordinates":[-90.7333,46.4833],"type":"Point"}
}