{
  "id": 7285207,
  "type": "Feature",
  "properties": {
    "tgn:hierarchy":[
        "tgn:7285207",
        "tgn:1001699",
        "tgn:1000049",
        "tgn:1000002",
        "tgn:7029392"
    ],
    "tgn:id":7285207,
    "tgn:name":"Pido, Roca",
    "tgn:placetype":[
        "aat:300011692"
    ]
},
  "bbox": [],
  "geometry": {"coordinates":[-73.481944,-42.01],"type":"Point"}
}