{
  "id": 7594254,
  "type": "Feature",
  "properties": {
    "tgn:hierarchy":[
        "tgn:7594254",
        "tgn:7002445",
        "tgn:1000003",
        "tgn:7011961",
        "tgn:7008591",
        "tgn:7029392"
    ],
    "tgn:id":7594254,
    "tgn:name":"Wardstone",
    "tgn:placetype":[
        "aat:300391494",
        "aat:300019275",
        "aat:300387004",
        "aat:300387006"
    ]
},
  "bbox": [],
  "geometry": {"coordinates":[-2.299,50.616],"type":"Point"}
}