<<<<<<< HEAD
{
  "id": 7055206,
  "type": "Feature",
  "properties": {
    "tgn:hierarchy":[
        "tgn:7055206",
        "tgn:7003138",
        "tgn:1000003",
        "tgn:7003080",
        "tgn:1000080",
        "tgn:7029392"
    ],
    "tgn:id":7055206,
    "tgn:name":"Osa, Fosso dell'",
    "tgn:placetype":[
        "aat:300008699"
    ]
},
  "bbox": [],
  "geometry": {"coordinates":[12.65,41.916667],"type":"Point"}
}
=======
{"geometry":{"type":"Point","coordinates":[12.650000,41.916667]},"type":"Feature","properties":{"hierarchy":["tgn:7055206","tgn:7003138","tgn:1000003","tgn:7003080","tgn:1000080","tgn:7029392"],"placetype":["aat:300008699"],"id":7055206,"name:xx":"Osa, Fosso dell'"}}
>>>>>>> 03f74aca74312dbeaf24d7e61306dd6a786dc3d0
