{
  "id": 2445595,
  "type": "Feature",
  "properties": {
    "tgn:hierarchy":[
        "tgn:2445595",
        "tgn:7006450",
        "tgn:1000001",
        "tgn:7012149",
        "tgn:2124002",
        "tgn:7029392"
    ],
    "tgn:id":2445595,
    "tgn:name":"Leona Lake",
    "tgn:placetype":[
        "aat:300008680"
    ]
},
  "bbox": [],
  "geometry": {"coordinates":[-134.6833,56.2667],"type":"Point"}
}