{
  "id": 7189894,
  "type": "Feature",
  "properties": {
    "tgn:hierarchy":[
        "tgn:7189894",
        "tgn:1000003",
        "tgn:7003677",
        "tgn:7000084",
        "tgn:7029392"
    ],
    "tgn:id":7189894,
    "tgn:name":"Ennepetalsperre",
    "tgn:placetype":[
        "aat:300006191"
    ]
},
  "bbox": [],
  "geometry": {"coordinates":[7.416667,51.233333],"type":"Point"}
}