{
  "id": 7548614,
  "type": "Feature",
  "properties": {
    "tgn:hierarchy":[
        "tgn:7548614",
        "tgn:1000004",
        "tgn:7031781",
        "tgn:7000198",
        "tgn:7029392"
    ],
    "tgn:id":7548614,
    "tgn:name:en":"Bundeli",
    "tgn:placetype":[
        "aat:300008347"
    ]
},
  "bbox": [],
  "geometry": {"coordinates":[81.116667,21.566667],"type":"Point"}
}