{
  "id": 1117500,
  "type": "Feature",
  "properties": {
    "tgn:hierarchy":[
        "tgn:1117500",
        "tgn:7005685",
        "tgn:1000001",
        "tgn:7013154",
        "tgn:7029392"
    ],
    "tgn:id":1117500,
    "tgn:name":"Nine Mile Lake",
    "tgn:placetype":[
        "aat:300008680"
    ]
},
  "bbox": [],
  "geometry": {"coordinates":[-79.5667,44.95],"type":"Point"}
}