{
  "id": 2160927,
  "type": "Feature",
  "properties": {
    "tgn:hierarchy":[
        "tgn:2160927",
        "tgn:1000001",
        "tgn:7012149",
        "tgn:2001753",
        "tgn:7007712",
        "tgn:7029392"
    ],
    "tgn:id":2160927,
    "tgn:name":"Belks Pond",
    "tgn:placetype":[
        "aat:300006191"
    ]
},
  "bbox": [],
  "geometry": {"coordinates":[-80.6833,34.7833],"type":"Point"}
}