{
  "id": 2134602,
  "type": "Feature",
  "properties": {
    "tgn:hierarchy":[
        "tgn:2134602",
        "tgn:1000001",
        "tgn:7012149",
        "tgn:2001309",
        "tgn:7007524",
        "tgn:7029392"
    ],
    "tgn:id":2134602,
    "tgn:name":"Antelope Butte",
    "tgn:placetype":[
        "aat:300008798"
    ]
},
  "bbox": [],
  "geometry": {"coordinates":[-112.6333,47.9667],"type":"Point"}
}