<<<<<<< HEAD
{
  "id": 2766642,
  "type": "Feature",
  "properties": {
    "tgn:hierarchy":[
        "tgn:2766642",
        "tgn:1000001",
        "tgn:2001747",
        "tgn:7012149",
        "tgn:7007712",
        "tgn:7029392"
    ],
    "tgn:id":2766642,
    "tgn:name":"White Oak Hills",
    "tgn:placetype":[
        "aat:300008347"
    ]
},
  "bbox": [],
  "geometry": {"coordinates":[-82.4667,34.8667],"type":"Point"}
}
=======
{"geometry":{"type":"Point","coordinates":[-82.466700,34.866700]},"type":"Feature","properties":{"hierarchy":["tgn:2766642","tgn:1000001","tgn:2001747","tgn:7012149","tgn:7007712","tgn:7029392"],"placetype":["aat:300008347"],"id":2766642,"name:xx":"White Oak Hills"}}
>>>>>>> 03f74aca74312dbeaf24d7e61306dd6a786dc3d0
