{
  "id": 7008785,
  "type": "Feature",
  "properties": {
    "tgn:hierarchy":[
        "tgn:7008785",
        "tgn:7007780",
        "tgn:1000003",
        "tgn:7009604",
        "tgn:1000095",
        "tgn:7029392"
    ],
    "tgn:id":7008785,
    "tgn:name":"Vergara",
    "tgn:placetype":[
        "aat:300008347"
    ]
},
  "bbox": [],
  "geometry": {"coordinates":[-2.414003,43.116477],"type":"Point"}
}