<<<<<<< HEAD
{
  "id": 7481876,
  "type": "Feature",
  "properties": {
    "tgn:hierarchy":[
        "tgn:7481876",
        "tgn:1000004",
        "tgn:7492971",
        "tgn:1000141",
        "tgn:7029392"
    ],
    "tgn:id":7481876,
    "tgn:name":"Fengnan Qiao",
    "tgn:placetype":[
        "aat:300007836"
    ]
},
  "bbox": [],
  "geometry": {"coordinates":[120.516207,22.692874],"type":"Point"}
}
=======
{"geometry":{"type":"Point","coordinates":[120.516207,22.692874]},"type":"Feature","properties":{"hierarchy":["tgn:7481876","tgn:1000004","tgn:7492971","tgn:1000141","tgn:7029392"],"placetype":["aat:300007836"],"id":7481876,"name:xx":"Fengnan Qiao"}}
>>>>>>> 03f74aca74312dbeaf24d7e61306dd6a786dc3d0
