{
  "id": 2054791,
  "type": "Feature",
  "properties": {
    "tgn:hierarchy":[
        "tgn:2054791",
        "tgn:1000001",
        "tgn:2001012",
        "tgn:7012149",
        "tgn:7007521",
        "tgn:7029392"
    ],
    "tgn:id":2054791,
    "tgn:name":"Kragnes",
    "tgn:placetype":[
        "aat:300008347"
    ]
},
  "bbox": [],
  "geometry": {"coordinates":[-96.75,46.9833],"type":"Point"}
}