{
  "id": 2753366,
  "type": "Feature",
  "properties": {
    "tgn:hierarchy":[
        "tgn:2753366",
        "tgn:2000090",
        "tgn:1000001",
        "tgn:7006451",
        "tgn:7012149",
        "tgn:7029392"
    ],
    "tgn:id":2753366,
    "tgn:name":"Waterhaul Tank",
    "tgn:placetype":[
        "aat:300006191"
    ]
},
  "bbox": [],
  "geometry": {"coordinates":[-109.7167,34.8667],"type":"Point"}
}