{
  "id": 2120386,
  "type": "Feature",
  "properties": {
    "tgn:hierarchy":[
        "tgn:2120386",
        "tgn:1000001",
        "tgn:7012149",
        "tgn:2002300",
        "tgn:7013961",
        "tgn:7029392"
    ],
    "tgn:id":2120386,
    "tgn:name":"Weese",
    "tgn:placetype":[
        "aat:300387016"
    ]
},
  "bbox": [],
  "geometry": {"coordinates":[-80.55,38.4667],"type":"Point"}
}