{
  "id": 7555978,
  "type": "Feature",
  "properties": {
    "tgn:hierarchy":[
        "tgn:7555978",
        "tgn:1000004",
        "tgn:7031781",
        "tgn:7000198",
        "tgn:7029392"
    ],
    "tgn:id":7555978,
    "tgn:name:en":"Peta",
    "tgn:placetype":[
        "aat:300008347"
    ]
},
  "bbox": [],
  "geometry": {"coordinates":[81.466667,17.916667],"type":"Point"}
}