{
  "id": 7178594,
  "type": "Feature",
  "properties": {
    "tgn:hierarchy":[
        "tgn:7178594",
        "tgn:7003692",
        "tgn:1000003",
        "tgn:7000084",
        "tgn:7029392"
    ],
    "tgn:id":7178594,
    "tgn:name":"G\u00fcltlingen",
    "tgn:placetype":[
        "aat:300008347"
    ]
},
  "bbox": [],
  "geometry": {"coordinates":[8.766667,48.65],"type":"Point"}
}