{
  "id": 2716283,
  "type": "Feature",
  "properties": {
    "tgn:hierarchy":[
        "tgn:2716283",
        "tgn:7006450",
        "tgn:1000001",
        "tgn:7012149",
        "tgn:7019760",
        "tgn:7029392"
    ],
    "tgn:id":2716283,
    "tgn:name":"Brothers, The",
    "tgn:placetype":[
        "aat:300055621"
    ]
},
  "bbox": [],
  "geometry": {"coordinates":[-133.8167,57.2833],"type":"Point"}
}