{
  "id": 7560796,
  "type": "Feature",
  "properties": {
    "tgn:hierarchy":[
        "tgn:7560796",
        "tgn:1000004",
        "tgn:7000198",
        "tgn:7016722",
        "tgn:7029392"
    ],
    "tgn:id":7560796,
    "tgn:name:en":"Muhammadpur J\u0101g\u012br",
    "tgn:placetype":[
        "aat:300008347"
    ]
},
  "bbox": [],
  "geometry": {"coordinates":[79.483826,27.179469],"type":"Point"}
}