{
  "id": 2027956,
  "type": "Feature",
  "properties": {
    "tgn:hierarchy":[
        "tgn:2027956",
        "tgn:2000496",
        "tgn:1000001",
        "tgn:7012149",
        "tgn:7007251",
        "tgn:7029392"
    ],
    "tgn:id":2027956,
    "tgn:name":"Gale",
    "tgn:placetype":[
        "aat:300008347"
    ]
},
  "bbox": [],
  "geometry": {"coordinates":[-89.4333,37.2333],"type":"Point"}
}