{
  "id": 7586175,
  "type": "Feature",
  "properties": {
    "tgn:hierarchy":[
        "tgn:7586175",
        "tgn:1000004",
        "tgn:7000198",
        "tgn:7000799",
        "tgn:7029392"
    ],
    "tgn:id":7586175,
    "tgn:name:en":"Nar\u0101yann\u0101g",
    "tgn:placetype":[
        "aat:300008347"
    ]
},
  "bbox": [],
  "geometry": {"coordinates":[74.977778,34.35],"type":"Point"}
}