{
  "id": 2002009,
  "type": "Feature",
  "properties": {
    "tgn:hierarchy":[
        "tgn:2002009",
        "tgn:1000001",
        "tgn:7012149",
        "tgn:7007826",
        "tgn:7029392"
    ],
    "tgn:id":2002009,
    "tgn:name":"Jasper",
    "tgn:placetype":[
        "aat:300387145",
        "aat:300000771"
    ]
},
  "bbox": [],
  "geometry": {"coordinates":[-94.0167,30.7333],"type":"Point"}
}