{
  "id": 7292378,
  "type": "Feature",
  "properties": {
    "tgn:hierarchy":[
        "tgn:7292378",
        "tgn:1001708",
        "tgn:1000049",
        "tgn:1000002",
        "tgn:7029392"
    ],
    "tgn:id":7292378,
    "tgn:name":"El Parr\u00f3n",
    "tgn:placetype":[
        "aat:300387200"
    ]
},
  "bbox": [],
  "geometry": {"coordinates":[-71.066667,-33.516667],"type":"Point"}
}