{
  "id": 7416912,
  "type": "Feature",
  "properties": {
    "tgn:hierarchy":[
        "tgn:7416912",
        "tgn:1000001",
        "tgn:7005591",
        "tgn:7005560",
        "tgn:7029392"
    ],
    "tgn:id":7416912,
    "tgn:name:es":"Ejido Cieneguilla",
    "tgn:placetype":[
        "aat:300008347"
    ]
},
  "bbox": [],
  "geometry": {"coordinates":[-96.418333,16.2175],"type":"Point"}
}