{
  "id": 7409326,
  "type": "Feature",
  "properties": {
    "tgn:hierarchy":[
        "tgn:7409326",
        "tgn:1000001",
        "tgn:7005590",
        "tgn:7005560",
        "tgn:7029392"
    ],
    "tgn:id":7409326,
    "tgn:name":"San Luis",
    "tgn:placetype":[
        "aat:300008347"
    ]
},
  "bbox": [],
  "geometry": {"coordinates":[-100.281944,19.558333],"type":"Point"}
}