{
  "id": 7023054,
  "type": "Feature",
  "properties": {
    "tgn:hierarchy":[
        "tgn:7023054",
        "tgn:1000001",
        "tgn:7012149",
        "tgn:7007158",
        "tgn:7029392"
    ],
    "tgn:id":7023054,
    "tgn:name":"Sand Rock Reservoir",
    "tgn:placetype":[
        "aat:300006191"
    ]
},
  "bbox": [],
  "geometry": {"coordinates":[-108.8333,37.8667],"type":"Point"}
}