<<<<<<< HEAD
{
  "id": 7023612,
  "type": "Feature",
  "properties": {
    "tgn:hierarchy":[
        "tgn:7023612",
        "tgn:1000001",
        "tgn:7012149",
        "tgn:7007157",
        "tgn:1002858",
        "tgn:7029392"
    ],
    "tgn:id":7023612,
    "tgn:name":"Oneill, Lake",
    "tgn:placetype":[
        "aat:300006191"
    ]
},
  "bbox": [],
  "geometry": {"coordinates":[-117.3167,33.3167],"type":"Point"}
}
=======
{"geometry":{"type":"Point","coordinates":[-117.316700,33.316700]},"type":"Feature","properties":{"hierarchy":["tgn:7023612","tgn:1000001","tgn:7012149","tgn:7007157","tgn:1002858","tgn:7029392"],"placetype":["aat:300006191"],"id":7023612,"name:xx":"Oneill, Lake"}}
>>>>>>> 03f74aca74312dbeaf24d7e61306dd6a786dc3d0
