{
  "id": 2556766,
  "type": "Feature",
  "properties": {
    "tgn:hierarchy":[
        "tgn:2556766",
        "tgn:1000001",
        "tgn:7012149",
        "tgn:2001958",
        "tgn:7007826",
        "tgn:7029392"
    ],
    "tgn:id":2556766,
    "tgn:name":"Old City Lake",
    "tgn:placetype":[
        "aat:300006191"
    ]
},
  "bbox": [],
  "geometry": {"coordinates":[-100.45,31.8833],"type":"Point"}
}