{
  "id": 2506020,
  "type": "Feature",
  "properties": {
    "tgn:hierarchy":[
        "tgn:2506020",
        "tgn:1000001",
        "tgn:1002190",
        "tgn:7012149",
        "tgn:7007523",
        "tgn:7029392"
    ],
    "tgn:id":2506020,
    "tgn:name":"Merideth Branch",
    "tgn:placetype":[
        "aat:300008699"
    ]
},
  "bbox": [],
  "geometry": {"coordinates":[-92.3833,38.9333],"type":"Point"}
}