{
  "id": 2632016,
  "type": "Feature",
  "properties": {
    "tgn:hierarchy":[
        "tgn:2632016",
        "tgn:1000001",
        "tgn:7016172",
        "tgn:7012149",
        "tgn:2000168",
        "tgn:7029392"
    ],
    "tgn:id":2632016,
    "tgn:name":"Rowdy Mountain",
    "tgn:placetype":[
        "aat:300008798"
    ]
},
  "bbox": [],
  "geometry": {"coordinates":[-94.15,34.8167],"type":"Point"}
}