{
  "id": 2330350,
  "type": "Feature",
  "properties": {
    "tgn:hierarchy":[
        "tgn:2330350",
        "tgn:1000001",
        "tgn:2000328",
        "tgn:7012149",
        "tgn:7007248",
        "tgn:7029392"
    ],
    "tgn:id":2330350,
    "tgn:name":"Flat Branch",
    "tgn:placetype":[
        "aat:300008699"
    ]
},
  "bbox": [],
  "geometry": {"coordinates":[-83.4833,31.2667],"type":"Point"}
}