<<<<<<< HEAD
{
  "id": 2330350,
  "type": "Feature",
  "properties": {
    "tgn:hierarchy":[
        "tgn:2330350",
        "tgn:1000001",
        "tgn:2000328",
        "tgn:7012149",
        "tgn:7007248",
        "tgn:7029392"
    ],
    "tgn:id":2330350,
    "tgn:name":"Flat Branch",
    "tgn:placetype":[
        "aat:300008699"
    ]
},
  "bbox": [],
  "geometry": {"coordinates":[-83.4833,31.2667],"type":"Point"}
}
=======
{"geometry":{"type":"Point","coordinates":[-83.483300,31.266700]},"type":"Feature","properties":{"hierarchy":["tgn:2330350","tgn:1000001","tgn:2000328","tgn:7012149","tgn:7007248","tgn:7029392"],"placetype":["aat:300008699"],"id":2330350,"name:xx":"Flat Branch"}}
>>>>>>> 03f74aca74312dbeaf24d7e61306dd6a786dc3d0
