{
  "id": 7280092,
  "type": "Feature",
  "properties": {
    "tgn:hierarchy":[
        "tgn:7280092",
        "tgn:1001702",
        "tgn:1000049",
        "tgn:1000002",
        "tgn:7029392"
    ],
    "tgn:id":7280092,
    "tgn:name":"Revell\u00edn, Punta",
    "tgn:placetype":[
        "aat:300386846"
    ]
},
  "bbox": [],
  "geometry": {"coordinates":[-66.45,-55.183333],"type":"Point"}
}