<<<<<<< HEAD
{
  "id": 2402501,
  "type": "Feature",
  "properties": {
    "tgn:hierarchy":[
        "tgn:2402501",
        "tgn:1000001",
        "tgn:7012149",
        "tgn:7019676",
        "tgn:7007566",
        "tgn:7029392"
    ],
    "tgn:id":2402501,
    "tgn:name":"Hoskins and Robinson Pit",
    "tgn:placetype":[
        "aat:300000390"
    ]
},
  "bbox": [],
  "geometry": {"coordinates":[-107.95,35.3333],"type":"Point"}
}
=======
{"geometry":{"type":"Point","coordinates":[-107.950000,35.333300]},"type":"Feature","properties":{"hierarchy":["tgn:2402501","tgn:1000001","tgn:7012149","tgn:7019676","tgn:7007566","tgn:7029392"],"placetype":["aat:300000390"],"id":2402501,"name:xx":"Hoskins and Robinson Pit"}}
>>>>>>> 03f74aca74312dbeaf24d7e61306dd6a786dc3d0
