{
  "id": 2402501,
  "type": "Feature",
  "properties": {
    "tgn:hierarchy":[
        "tgn:2402501",
        "tgn:1000001",
        "tgn:7012149",
        "tgn:7019676",
        "tgn:7007566",
        "tgn:7029392"
    ],
    "tgn:id":2402501,
    "tgn:name":"Hoskins and Robinson Pit",
    "tgn:placetype":[
        "aat:300000390"
    ]
},
  "bbox": [],
  "geometry": {"coordinates":[-107.95,35.3333],"type":"Point"}
}