{
  "id": 1027601,
  "type": "Feature",
  "properties": {
    "tgn:hierarchy":[
        "tgn:1027601",
        "tgn:7027130",
        "tgn:1000003",
        "tgn:7011765",
        "tgn:7029392"
    ],
    "tgn:id":1027601,
    "tgn:name":"Trsten\u00e1",
    "tgn:placetype":[
        "aat:300008347"
    ]
},
  "bbox": [],
  "geometry": {"coordinates":[19.5833,49.3667],"type":"Point"}
}