{
  "id": 7377475,
  "type": "Feature",
  "properties": {
    "tgn:hierarchy":[
        "tgn:7377475",
        "tgn:1001853",
        "tgn:1000001",
        "tgn:7005560",
        "tgn:7029392"
    ],
    "tgn:id":7377475,
    "tgn:name":"La Venada",
    "tgn:placetype":[
        "aat:300008347"
    ]
},
  "bbox": [],
  "geometry": {"coordinates":[-103.316667,25.433333],"type":"Point"}
}