{
  "id": 2551481,
  "type": "Feature",
  "properties": {
    "tgn:hierarchy":[
        "tgn:2551481",
        "tgn:1000001",
        "tgn:2001177",
        "tgn:7012149",
        "tgn:7007523",
        "tgn:7029392"
    ],
    "tgn:id":2551481,
    "tgn:name":"Number 167 Reservoir",
    "tgn:placetype":[
        "aat:300006191"
    ]
},
  "bbox": [],
  "geometry": {"coordinates":[-93.8167,39.7167],"type":"Point"}
}