{
  "id": 2154677,
  "type": "Feature",
  "properties": {
    "tgn:hierarchy":[
        "tgn:2154677",
        "tgn:1000001",
        "tgn:7012149",
        "tgn:2000210",
        "tgn:7007158",
        "tgn:7029392"
    ],
    "tgn:id":2154677,
    "tgn:name":"Bear Gulch",
    "tgn:placetype":[
        "aat:300008761"
    ]
},
  "bbox": [],
  "geometry": {"coordinates":[-106.4667,39.7833],"type":"Point"}
}