<<<<<<< HEAD
{
  "id": 2154677,
  "type": "Feature",
  "properties": {
    "tgn:hierarchy":[
        "tgn:2154677",
        "tgn:1000001",
        "tgn:7012149",
        "tgn:2000210",
        "tgn:7007158",
        "tgn:7029392"
    ],
    "tgn:id":2154677,
    "tgn:name":"Bear Gulch",
    "tgn:placetype":[
        "aat:300008761"
    ]
},
  "bbox": [],
  "geometry": {"coordinates":[-106.4667,39.7833],"type":"Point"}
}
=======
{"geometry":{"type":"Point","coordinates":[-106.466700,39.783300]},"type":"Feature","properties":{"hierarchy":["tgn:2154677","tgn:1000001","tgn:7012149","tgn:2000210","tgn:7007158","tgn:7029392"],"placetype":["aat:300008761"],"id":2154677,"name:xx":"Bear Gulch"}}
>>>>>>> 03f74aca74312dbeaf24d7e61306dd6a786dc3d0
