{
  "id": 1042348,
  "type": "Feature",
  "properties": {
    "tgn:hierarchy":[
        "tgn:1042348",
        "tgn:1000385",
        "tgn:1000003",
        "tgn:7006278",
        "tgn:7029392"
    ],
    "tgn:id":1042348,
    "tgn:name":"Hajd\u00fan\u00e1n\u00e1s",
    "tgn:placetype":[
        "aat:300008347"
    ]
},
  "bbox": [],
  "geometry": {"coordinates":[21.4333,47.8333],"type":"Point"}
}