{
  "id": 2629681,
  "type": "Feature",
  "properties": {
    "tgn:hierarchy":[
        "tgn:2629681",
        "tgn:1000001",
        "tgn:7012149",
        "tgn:2001690",
        "tgn:7007707",
        "tgn:7029392"
    ],
    "tgn:id":2629681,
    "tgn:name":"Ross Branch",
    "tgn:placetype":[
        "aat:300008699"
    ]
},
  "bbox": [],
  "geometry": {"coordinates":[-94.7167,35.5167],"type":"Point"}
}