{
  "id": 2382934,
  "type": "Feature",
  "properties": {
    "tgn:hierarchy":[
        "tgn:2382934",
        "tgn:1000001",
        "tgn:7012149",
        "tgn:2001913",
        "tgn:7007825",
        "tgn:7029392"
    ],
    "tgn:id":2382934,
    "tgn:name":"He Creek",
    "tgn:placetype":[
        "aat:300008706"
    ]
},
  "bbox": [],
  "geometry": {"coordinates":[-85.5333,35.5167],"type":"Point"}
}