{
  "id": 2057203,
  "type": "Feature",
  "properties": {
    "tgn:hierarchy":[
        "tgn:2057203",
        "tgn:1000001",
        "tgn:7012149",
        "tgn:2001151",
        "tgn:7007522",
        "tgn:7029392"
    ],
    "tgn:id":2057203,
    "tgn:name":"Perkinston",
    "tgn:placetype":[
        "aat:300008347"
    ]
},
  "bbox": [],
  "geometry": {"coordinates":[-89.1333,30.7667],"type":"Point"}
}