<<<<<<< HEAD
{
  "id": 7246708,
  "type": "Feature",
  "properties": {
    "tgn:hierarchy":[
        "tgn:7246708",
        "tgn:7003457",
        "tgn:1000003",
        "tgn:1000063",
        "tgn:7018236",
        "tgn:7029392"
    ],
    "tgn:id":7246708,
    "tgn:name":"Bosstraat",
    "tgn:placetype":[
        "aat:300008347"
    ]
},
  "bbox": [],
  "geometry": {"coordinates":[3.93323,50.72642],"type":"Point"}
}
=======
{"geometry":{"type":"Point","coordinates":[3.933230,50.726420]},"type":"Feature","properties":{"hierarchy":["tgn:7246708","tgn:7003457","tgn:1000003","tgn:1000063","tgn:7018236","tgn:7029392"],"placetype":["aat:300008347"],"id":7246708,"name:xx":"Bosstraat"}}
>>>>>>> 03f74aca74312dbeaf24d7e61306dd6a786dc3d0
