{
  "id": 2584580,
  "type": "Feature",
  "properties": {
    "tgn:hierarchy":[
        "tgn:2584580",
        "tgn:1000001",
        "tgn:2000939",
        "tgn:7012149",
        "tgn:7007516",
        "tgn:7029392"
    ],
    "tgn:id":2584580,
    "tgn:name":"Piney Point",
    "tgn:placetype":[
        "aat:300008850"
    ]
},
  "bbox": [],
  "geometry": {"coordinates":[-76.25,38.7167],"type":"Point"}
}