<<<<<<< HEAD
{
  "id": 7023547,
  "type": "Feature",
  "properties": {
    "tgn:hierarchy":[
        "tgn:7023547",
        "tgn:1000001",
        "tgn:7012149",
        "tgn:7007923",
        "tgn:7029392"
    ],
    "tgn:id":7023547,
    "tgn:name":"Sweetwater Rocks",
    "tgn:placetype":[
        "aat:300008798"
    ]
},
  "bbox": [],
  "geometry": {"coordinates":[-107.2,42.5],"type":"Point"}
}
=======
{"geometry":{"type":"Point","coordinates":[-107.200000,42.500000]},"type":"Feature","properties":{"hierarchy":["tgn:7023547","tgn:1000001","tgn:7012149","tgn:7007923","tgn:7029392"],"placetype":["aat:300008798"],"id":7023547,"name:xx":"Sweetwater Rocks"}}
>>>>>>> 03f74aca74312dbeaf24d7e61306dd6a786dc3d0
