{
  "id": 7200132,
  "type": "Feature",
  "properties": {
    "tgn:hierarchy":[
        "tgn:7200132",
        "tgn:1000003",
        "tgn:7003678",
        "tgn:7000084",
        "tgn:7029392"
    ],
    "tgn:id":7200132,
    "tgn:name":"Eichelbacher Hof",
    "tgn:placetype":[
        "aat:300000206"
    ]
},
  "bbox": [],
  "geometry": {"coordinates":[8.35,50.316667],"type":"Point"}
}