{
  "id": 7518891,
  "type": "Feature",
  "properties": {
    "tgn:hierarchy":[
        "tgn:7518891",
        "tgn:1009227",
        "tgn:1000226",
        "tgn:7016822",
        "tgn:1000006",
        "tgn:7029392"
    ],
    "tgn:id":7518891,
    "tgn:name:en":"Arthur River",
    "tgn:placetype":[
        "aat:300008699"
    ]
},
  "bbox": [],
  "geometry": {"coordinates":[167.833333,-44.733333],"type":"Point"}
}