{
  "id": 7225482,
  "type": "Feature",
  "properties": {
    "tgn:hierarchy":[
        "tgn:7225482",
        "tgn:7002743",
        "tgn:7017076",
        "tgn:1000003",
        "tgn:1000074",
        "tgn:7029392"
    ],
    "tgn:id":7225482,
    "tgn:name":"Pteri\u00e1",
    "tgn:placetype":[
        "aat:300008347"
    ]
},
  "bbox": [],
  "geometry": {"coordinates":[22.016667,37.75],"type":"Point"}
}