{
  "id": 7334259,
  "type": "Feature",
  "properties": {
    "tgn:hierarchy":[
        "tgn:7334259",
        "tgn:7002803",
        "tgn:1001647",
        "tgn:1000003",
        "tgn:1000095",
        "tgn:7029392"
    ],
    "tgn:id":7334259,
    "tgn:name":"El Royo",
    "tgn:placetype":[
        "aat:300008347"
    ]
},
  "bbox": [],
  "geometry": {"coordinates":[-2.016667,38.683333],"type":"Point"}
}