{
  "id": 2666485,
  "type": "Feature",
  "properties": {
    "tgn:hierarchy":[
        "tgn:2666485",
        "tgn:1000001",
        "tgn:7016172",
        "tgn:7012149",
        "tgn:2000128",
        "tgn:7029392"
    ],
    "tgn:id":2666485,
    "tgn:name":"Sixmile Creek Site 25 Reservoir",
    "tgn:placetype":[
        "aat:300006191"
    ]
},
  "bbox": [],
  "geometry": {"coordinates":[-93.8833,35.3333],"type":"Point"}
}