{
  "id": 7238208,
  "type": "Feature",
  "properties": {
    "tgn:hierarchy":[
        "tgn:7238208",
        "tgn:7003456",
        "tgn:1000003",
        "tgn:1000063",
        "tgn:7018236",
        "tgn:7029392"
    ],
    "tgn:id":7238208,
    "tgn:name":"Het Lo",
    "tgn:placetype":[
        "aat:300008347"
    ]
},
  "bbox": [],
  "geometry": {"coordinates":[4.586759,51.185474],"type":"Point"}
}