{
  "id": 2688957,
  "type": "Feature",
  "properties": {
    "tgn:hierarchy":[
        "tgn:2688957",
        "tgn:2000919",
        "tgn:1000001",
        "tgn:7012149",
        "tgn:7007515",
        "tgn:7029392"
    ],
    "tgn:id":2688957,
    "tgn:name":"Squa Pan Inlet",
    "tgn:placetype":[
        "aat:300008699"
    ]
},
  "bbox": [],
  "geometry": {"coordinates":[-68.25,46.65],"type":"Point"}
}