{
  "id": 2731611,
  "type": "Feature",
  "properties": {
    "tgn:hierarchy":[
        "tgn:2731611",
        "tgn:1000001",
        "tgn:2001414",
        "tgn:7012149",
        "tgn:7007526",
        "tgn:7029392"
    ],
    "tgn:id":2731611,
    "tgn:name":"Tule Spring",
    "tgn:placetype":[
        "aat:300008697"
    ]
},
  "bbox": [],
  "geometry": {"coordinates":[-119.05,41.4667],"type":"Point"}
}