{
  "id": 7322457,
  "type": "Feature",
  "properties": {
    "tgn:hierarchy":[
        "tgn:7322457",
        "tgn:7002829",
        "tgn:1000003",
        "tgn:7002786",
        "tgn:1000095",
        "tgn:7029392"
    ],
    "tgn:id":7322457,
    "tgn:name":"Sante, Arroyo de",
    "tgn:placetype":[
        "aat:300008699"
    ]
},
  "bbox": [],
  "geometry": {"coordinates":[-7.566667,42.483333],"type":"Point"}
}