{
  "id": 1125868,
  "type": "Feature",
  "properties": {
    "tgn:hierarchy":[
        "tgn:1125868",
        "tgn:7001242",
        "tgn:1001728",
        "tgn:1000164",
        "tgn:7029392"
    ],
    "tgn:id":1125868,
    "tgn:name":"Leyou",
    "tgn:placetype":[
        "aat:300008707"
    ]
},
  "bbox": [],
  "geometry": {"coordinates":[13.1333,-1.1167],"type":"Point"}
}