{
  "id": 7550437,
  "type": "Feature",
  "properties": {
    "tgn:hierarchy":[
        "tgn:7550437",
        "tgn:1000004",
        "tgn:1001869",
        "tgn:7000198",
        "tgn:7029392"
    ],
    "tgn:id":7550437,
    "tgn:name:en":"Bi\u0101r Bet",
    "tgn:placetype":[
        "aat:300008791"
    ]
},
  "bbox": [],
  "geometry": {"coordinates":[69.603562,24.151834],"type":"Point"}
}