{
  "id": 7456215,
  "type": "Feature",
  "properties": {
    "tgn:hierarchy":[
        "tgn:7456215",
        "tgn:7002444",
        "tgn:1000003",
        "tgn:7029508",
        "tgn:7008591",
        "tgn:7029392"
    ],
    "tgn:id":7456215,
    "tgn:name:en":"Cloa Rock",
    "tgn:placetype":[
        "aat:300008808"
    ]
},
  "bbox": [],
  "geometry": {"coordinates":[-1.033333,60.483333],"type":"Point"}
}