{
  "id": 1017115,
  "type": "Feature",
  "properties": {
    "tgn:hierarchy":[
        "tgn:1017115",
        "tgn:7005583",
        "tgn:1000001",
        "tgn:7005560",
        "tgn:7029392"
    ],
    "tgn:id":1017115,
    "tgn:name":"Canatl\u00e1n",
    "tgn:placetype":[
        "aat:300008347",
        "aat:300008389",
        "aat:300265612"
    ]
},
  "bbox": [],
  "geometry": {"coordinates":[-104.783333,24.516667],"type":"Point"}
}