{
  "id": 7427202,
  "type": "Feature",
  "properties": {
    "tgn:hierarchy":[
        "tgn:7427202",
        "tgn:1000001",
        "tgn:7005594",
        "tgn:7005560",
        "tgn:7029392"
    ],
    "tgn:id":7427202,
    "tgn:name":"Mesa del Salto",
    "tgn:placetype":[
        "aat:300008347"
    ]
},
  "bbox": [],
  "geometry": {"coordinates":[-100.066667,21.833333],"type":"Point"}
}