{
  "id": 1130765,
  "type": "Feature",
  "properties": {
    "tgn:hierarchy":[
        "tgn:1130765",
        "tgn:1000001",
        "tgn:7029392"
    ],
    "tgn:id":1130765,
    "tgn:name":"Teribe, R\u00edo",
    "tgn:placetype":[
        "aat:300008707"
    ]
},
  "bbox": [],
  "geometry": {"coordinates":[-82.5333,9.3667],"type":"Point"}
}