{
  "id": 7349918,
  "type": "Feature",
  "properties": {
    "tgn:hierarchy":[
        "tgn:7349918",
        "tgn:7005587",
        "tgn:1000001",
        "tgn:7005560",
        "tgn:7029392"
    ],
    "tgn:id":7349918,
    "tgn:name":"Acopinalco",
    "tgn:placetype":[
        "aat:300008347"
    ]
},
  "bbox": [],
  "geometry": {"coordinates":[-98.533333,19.716667],"type":"Point"}
}