{
  "id": 7412598,
  "type": "Feature",
  "properties": {
    "tgn:hierarchy":[
        "tgn:7412598",
        "tgn:1000001",
        "tgn:7005596",
        "tgn:7005560",
        "tgn:7029392"
    ],
    "tgn:id":7412598,
    "tgn:name:es":"La Manga Segunda Secci\u00f3n",
    "tgn:placetype":[
        "aat:300008347"
    ]
},
  "bbox": [],
  "geometry": {"coordinates":[-92.870833,18.0125],"type":"Point"}
}