{
  "id": 2465382,
  "type": "Feature",
  "properties": {
    "tgn:hierarchy":[
        "tgn:2465382",
        "tgn:1000001",
        "tgn:7012149",
        "tgn:2001969",
        "tgn:7007826",
        "tgn:7029392"
    ],
    "tgn:id":2465382,
    "tgn:name":"Lone Cone",
    "tgn:placetype":[
        "aat:300008798"
    ]
},
  "bbox": [],
  "geometry": {"coordinates":[-104.8167,31.7667],"type":"Point"}
}