{
  "id": 7280999,
  "type": "Feature",
  "properties": {
    "tgn:hierarchy":[
        "tgn:7280999",
        "tgn:7016598",
        "tgn:1000049",
        "tgn:1000002",
        "tgn:7029392"
    ],
    "tgn:id":7280999,
    "tgn:name":"Sierra \u00c1spera",
    "tgn:placetype":[
        "aat:300387033"
    ]
},
  "bbox": [],
  "geometry": {"coordinates":[-69.35,-24.733333],"type":"Point"}
}