{
  "id": 7409137,
  "type": "Feature",
  "properties": {
    "tgn:hierarchy":[
        "tgn:7409137",
        "tgn:1000001",
        "tgn:7005592",
        "tgn:7005560",
        "tgn:7029392"
    ],
    "tgn:id":7409137,
    "tgn:name":"San Miguel La Ci\u00e9nega",
    "tgn:placetype":[
        "aat:300008347"
    ]
},
  "bbox": [],
  "geometry": {"coordinates":[-98.741667,18.173611],"type":"Point"}
}