{
  "id": 7487026,
  "type": "Feature",
  "properties": {
    "tgn:hierarchy":[
        "tgn:7487026",
        "tgn:7488858",
        "tgn:1000004",
        "tgn:1000141",
        "tgn:7029392"
    ],
    "tgn:id":7487026,
    "tgn:name":"Miaoqian",
    "tgn:placetype":[
        "aat:300008347"
    ]
},
  "bbox": [],
  "geometry": {"coordinates":[120.972299,23.926015],"type":"Point"}
}