{
  "id": 7268541,
  "type": "Feature",
  "properties": {
    "tgn:concordances":{
        "gn:id":"2748626"
    },
    "tgn:hierarchy":[
        "tgn:7268541",
        "tgn:1000003",
        "tgn:7003632",
        "tgn:7016845",
        "tgn:7029392"
    ],
    "tgn:id":7268541,
    "tgn:name:nl":"Peursum",
    "tgn:placetype":[
        "aat:300008347"
    ]
},
  "bbox": [],
  "geometry": {"coordinates":[4.916667,51.85],"type":"Point"}
}