<<<<<<< HEAD
{
  "id": 7058530,
  "type": "Feature",
  "properties": {
    "tgn:hierarchy":[
        "tgn:7058530",
        "tgn:1003450",
        "tgn:7007850",
        "tgn:1000003",
        "tgn:1000080",
        "tgn:7029392"
    ],
    "tgn:id":7058530,
    "tgn:name":"Borgo Partenope",
    "tgn:placetype":[
        "aat:300008347"
    ]
},
  "bbox": [],
  "geometry": {"coordinates":[16.3,39.266667],"type":"Point"}
}
=======
{"geometry":{"type":"Point","coordinates":[16.300000,39.266667]},"type":"Feature","properties":{"hierarchy":["tgn:7058530","tgn:1003450","tgn:7007850","tgn:1000003","tgn:1000080","tgn:7029392"],"placetype":["aat:300008347"],"id":7058530,"name:xx":"Borgo Partenope"}}
>>>>>>> 03f74aca74312dbeaf24d7e61306dd6a786dc3d0
