{
  "id": 7459758,
  "type": "Feature",
  "properties": {
    "tgn:hierarchy":[
        "tgn:7459758",
        "tgn:7002445",
        "tgn:1000003",
        "tgn:7012034",
        "tgn:7008591",
        "tgn:7029392"
    ],
    "tgn:id":7459758,
    "tgn:name:en":"Meole Brace",
    "tgn:placetype":[
        "aat:300008347"
    ]
},
  "bbox": [],
  "geometry": {"coordinates":[-2.766667,52.683333],"type":"Point"}
}