{
  "id": 2676276,
  "type": "Feature",
  "properties": {
    "tgn:hierarchy":[
        "tgn:2676276",
        "tgn:1000001",
        "tgn:7012149",
        "tgn:2000928",
        "tgn:7007515",
        "tgn:7029392"
    ],
    "tgn:id":2676276,
    "tgn:name":"Sourdnahunk Field Campground",
    "tgn:placetype":[
        "aat:300008798"
    ]
},
  "bbox": [],
  "geometry": {"coordinates":[-69.0833,45.9667],"type":"Point"}
}