{
  "id": 2710303,
  "type": "Feature",
  "properties": {
    "tgn:hierarchy":[
        "tgn:2710303",
        "tgn:7002659",
        "tgn:1000001",
        "tgn:7012149",
        "tgn:2000033",
        "tgn:7029392"
    ],
    "tgn:id":2710303,
    "tgn:name":"Tally Branch",
    "tgn:placetype":[
        "aat:300008699"
    ]
},
  "bbox": [],
  "geometry": {"coordinates":[-85.2833,31.35],"type":"Point"}
}