{
  "id": 2677932,
  "type": "Feature",
  "properties": {
    "tgn:hierarchy":[
        "tgn:2677932",
        "tgn:1000001",
        "tgn:7012149",
        "tgn:2000237",
        "tgn:7007158",
        "tgn:7029392"
    ],
    "tgn:id":2677932,
    "tgn:name":"South Fork Alkali Creek",
    "tgn:placetype":[
        "aat:300008706"
    ]
},
  "bbox": [],
  "geometry": {"coordinates":[-107.6667,38.1667],"type":"Point"}
}