<<<<<<< HEAD
{
  "id": 7378578,
  "type": "Feature",
  "properties": {
    "tgn:hierarchy":[
        "tgn:7378578",
        "tgn:1000001",
        "tgn:7005595",
        "tgn:7005560",
        "tgn:7029392"
    ],
    "tgn:id":7378578,
    "tgn:name":"Los Pochotes",
    "tgn:placetype":[
        "aat:300008347"
    ]
},
  "bbox": [],
  "geometry": {"coordinates":[-107.477222,24.967222],"type":"Point"}
}
=======
{"geometry":{"type":"Point","coordinates":[-107.477222,24.967222]},"type":"Feature","properties":{"hierarchy":["tgn:7378578","tgn:1000001","tgn:7005595","tgn:7005560","tgn:7029392"],"placetype":["aat:300008347"],"id":7378578,"name:xx":"Los Pochotes"}}
>>>>>>> 03f74aca74312dbeaf24d7e61306dd6a786dc3d0
