<<<<<<< HEAD
{
  "id": 7479273,
  "type": "Feature",
  "properties": {
    "tgn:hierarchy":[
        "tgn:7479273",
        "tgn:1000004",
        "tgn:7491221",
        "tgn:1000141",
        "tgn:7029392"
    ],
    "tgn:id":7479273,
    "tgn:name":"Taidongshi Disi Gongmu",
    "tgn:placetype":[
        "aat:300266755"
    ]
},
  "bbox": [],
  "geometry": {"coordinates":[121.124444,22.718889],"type":"Point"}
}
=======
{"geometry":{"type":"Point","coordinates":[121.124444,22.718889]},"type":"Feature","properties":{"hierarchy":["tgn:7479273","tgn:1000004","tgn:7491221","tgn:1000141","tgn:7029392"],"placetype":["aat:300266755"],"id":7479273,"name:xx":"Taidongshi Disi Gongmu"}}
>>>>>>> 03f74aca74312dbeaf24d7e61306dd6a786dc3d0
