{
  "id": 7479273,
  "type": "Feature",
  "properties": {
    "tgn:hierarchy":[
        "tgn:7479273",
        "tgn:1000004",
        "tgn:7491221",
        "tgn:1000141",
        "tgn:7029392"
    ],
    "tgn:id":7479273,
    "tgn:name":"Taidongshi Disi Gongmu",
    "tgn:placetype":[
        "aat:300266755"
    ]
},
  "bbox": [],
  "geometry": {"coordinates":[121.124444,22.718889],"type":"Point"}
}