{
  "id": 2635514,
  "type": "Feature",
  "properties": {
    "tgn:hierarchy":[
        "tgn:2635514",
        "tgn:1000001",
        "tgn:7012149",
        "tgn:2001288",
        "tgn:7007524",
        "tgn:7029392"
    ],
    "tgn:id":2635514,
    "tgn:name":"SW NE Section 27 Mine",
    "tgn:placetype":[
        "aat:300000390"
    ]
},
  "bbox": [],
  "geometry": {"coordinates":[-112.2167,45.5333],"type":"Point"}
}