{
  "id": 7255940,
  "type": "Feature",
  "properties": {
    "tgn:hierarchy":[
        "tgn:7255940",
        "tgn:7018239",
        "tgn:1000003",
        "tgn:1000063",
        "tgn:7018236",
        "tgn:7029392"
    ],
    "tgn:id":7255940,
    "tgn:name":"Sint-Anna Pede",
    "tgn:placetype":[
        "aat:300008347"
    ]
},
  "bbox": [],
  "geometry": {"coordinates":[4.239708,50.831182],"type":"Point"}
}