{
  "id": 7519936,
  "type": "Feature",
  "properties": {
    "tgn:hierarchy":[
        "tgn:7519936",
        "tgn:1009227",
        "tgn:1000226",
        "tgn:7016822",
        "tgn:1000006",
        "tgn:7029392"
    ],
    "tgn:id":7519936,
    "tgn:name:en":"Bell Mount",
    "tgn:placetype":[
        "aat:300008736"
    ]
},
  "bbox": [],
  "geometry": {"coordinates":[167.683333,-45.866667],"type":"Point"}
}