{
  "id": 7144115,
  "type": "Feature",
  "properties": {
    "tgn:hierarchy":[
        "tgn:7144115",
        "tgn:7003669",
        "tgn:1000003",
        "tgn:7000084",
        "tgn:7029392"
    ],
    "tgn:id":7144115,
    "tgn:name":"K\u00f6nigsberg, Stadtwald",
    "tgn:placetype":[
        "aat:300008863"
    ]
},
  "bbox": [],
  "geometry": {"coordinates":[10.616667,50.083333],"type":"Point"}
}