{
  "id": 7179954,
  "type": "Feature",
  "properties": {
    "tgn:hierarchy":[
        "tgn:7179954",
        "tgn:1000003",
        "tgn:7003676",
        "tgn:7000084",
        "tgn:7029392"
    ],
    "tgn:id":7179954,
    "tgn:name":"Fuhlenbrock",
    "tgn:placetype":[
        "aat:300000206"
    ]
},
  "bbox": [],
  "geometry": {"coordinates":[7.183333,52.366667],"type":"Point"}
}