{
  "id": 7319752,
  "type": "Feature",
  "properties": {
    "tgn:hierarchy":[
        "tgn:7319752",
        "tgn:7016598",
        "tgn:1000049",
        "tgn:1000002",
        "tgn:7029392"
    ],
    "tgn:id":7319752,
    "tgn:name":"Aislado, Cerro",
    "tgn:placetype":[
        "aat:300008777"
    ]
},
  "bbox": [],
  "geometry": {"coordinates":[-69.566667,-25.283333],"type":"Point"}
}