{
  "id": 2604808,
  "type": "Feature",
  "properties": {
    "tgn:hierarchy":[
        "tgn:2604808",
        "tgn:1000001",
        "tgn:7012149",
        "tgn:2001611",
        "tgn:7007706",
        "tgn:7029392"
    ],
    "tgn:id":2604808,
    "tgn:name":"Raccoon Run",
    "tgn:placetype":[
        "aat:300008699"
    ]
},
  "bbox": [],
  "geometry": {"coordinates":[-82.45,39.7333],"type":"Point"}
}