{
  "id": 1106619,
  "type": "Feature",
  "properties": {
    "tgn:hierarchy":[
        "tgn:1106619",
        "tgn:1000001",
        "tgn:7012149",
        "tgn:2002120",
        "tgn:7007827",
        "tgn:7029392"
    ],
    "tgn:id":1106619,
    "tgn:name":"Swedish Knoll",
    "tgn:placetype":[
        "aat:300008795"
    ]
},
  "bbox": [],
  "geometry": {"coordinates":[-111.4333,39.2667],"type":"Point"}
}