{
  "id": 7490493,
  "type": "Feature",
  "properties": {
    "tgn:hierarchy":[
        "tgn:7490493",
        "tgn:1000004",
        "tgn:7491221",
        "tgn:1000141",
        "tgn:7029392"
    ],
    "tgn:id":7490493,
    "tgn:name":"Dazhu Xi",
    "tgn:placetype":[
        "aat:300008699"
    ]
},
  "bbox": [],
  "geometry": {"coordinates":[120.946111,22.455833],"type":"Point"}
}