<<<<<<< HEAD
{
  "id": 7376326,
  "type": "Feature",
  "properties": {
    "tgn:hierarchy":[
        "tgn:7376326",
        "tgn:1000001",
        "tgn:1001960",
        "tgn:7005560",
        "tgn:7029392"
    ],
    "tgn:id":7376326,
    "tgn:name":"Rancho La Tarasca",
    "tgn:placetype":[
        "aat:300000241"
    ]
},
  "bbox": [],
  "geometry": {"coordinates":[-110.616667,29.633333],"type":"Point"}
}
=======
{"geometry":{"type":"Point","coordinates":[-110.616667,29.633333]},"type":"Feature","properties":{"hierarchy":["tgn:7376326","tgn:1000001","tgn:1001960","tgn:7005560","tgn:7029392"],"placetype":["aat:300000241"],"id":7376326,"name:xx":"Rancho La Tarasca"}}
>>>>>>> 03f74aca74312dbeaf24d7e61306dd6a786dc3d0
