{
  "id": 1102275,
  "type": "Feature",
  "properties": {
    "tgn:hierarchy":[
        "tgn:1102275",
        "tgn:1000001",
        "tgn:2001815",
        "tgn:7012149",
        "tgn:7007713",
        "tgn:7029392"
    ],
    "tgn:id":1102275,
    "tgn:name":"Fort Sisseton State Park",
    "tgn:placetype":[
        "aat:300008192"
    ]
},
  "bbox": [],
  "geometry": {"coordinates":[-97.5167,45.65],"type":"Point"}
}