{
  "id": 7238168,
  "type": "Feature",
  "properties": {
    "tgn:hierarchy":[
        "tgn:7238168",
        "tgn:7007877",
        "tgn:1000003",
        "tgn:1000063",
        "tgn:4012014",
        "tgn:7029392"
    ],
    "tgn:id":7238168,
    "tgn:name":"Grandglise",
    "tgn:placetype":[
        "aat:300008347"
    ]
},
  "bbox": [],
  "geometry": {"coordinates":[3.695756,50.505184],"type":"Point"}
}