{
  "id": 2579523,
  "type": "Feature",
  "properties": {
    "tgn:hierarchy":[
        "tgn:2579523",
        "tgn:2000452",
        "tgn:1000001",
        "tgn:7012149",
        "tgn:7007250",
        "tgn:7029392"
    ],
    "tgn:id":2579523,
    "tgn:name":"Picket Pin Creek",
    "tgn:placetype":[
        "aat:300008706"
    ]
},
  "bbox": [],
  "geometry": {"coordinates":[-116.0667,43.6167],"type":"Point"}
}