{
  "id": 7503590,
  "type": "Feature",
  "properties": {
    "tgn:hierarchy":[
        "tgn:7503590",
        "tgn:1000004",
        "tgn:7492971",
        "tgn:1000141",
        "tgn:7029392"
    ],
    "tgn:id":7503590,
    "tgn:name":"Milidu Nongchang",
    "tgn:placetype":[
        "aat:300000206"
    ]
},
  "bbox": [],
  "geometry": {"coordinates":[120.483889,22.831389],"type":"Point"}
}