{
  "id": 2382555,
  "type": "Feature",
  "properties": {
    "tgn:hierarchy":[
        "tgn:2382555",
        "tgn:1000001",
        "tgn:1003029",
        "tgn:7012149",
        "tgn:7007828",
        "tgn:7029392"
    ],
    "tgn:id":2382555,
    "tgn:name":"Haystack Pond",
    "tgn:placetype":[
        "aat:300008680"
    ]
},
  "bbox": [],
  "geometry": {"coordinates":[-72.9167,42.9167],"type":"Point"}
}