{
  "id": 7491278,
  "type": "Feature",
  "properties": {
    "tgn:hierarchy":[
        "tgn:7491278",
        "tgn:1000004",
        "tgn:7467799",
        "tgn:1000141",
        "tgn:7029392"
    ],
    "tgn:id":7491278,
    "tgn:name":"Banluxiang",
    "tgn:placetype":[
        "aat:300008347"
    ]
},
  "bbox": [],
  "geometry": {"coordinates":[120.510194,24.0455],"type":"Point"}
}