{
  "id": 2612570,
  "type": "Feature",
  "properties": {
    "tgn:hierarchy":[
        "tgn:2612570",
        "tgn:1000001",
        "tgn:7012149",
        "tgn:2001106",
        "tgn:7007522",
        "tgn:7029392"
    ],
    "tgn:id":2612570,
    "tgn:name":"Redbird Lake",
    "tgn:placetype":[
        "aat:300008680"
    ]
},
  "bbox": [],
  "geometry": {"coordinates":[-88.6667,31.0333],"type":"Point"}
}