{
  "id": 2170089,
  "type": "Feature",
  "properties": {
    "tgn:hierarchy":[
        "tgn:2170089",
        "tgn:1000001",
        "tgn:2000582",
        "tgn:7012149",
        "tgn:7007253",
        "tgn:7029392"
    ],
    "tgn:id":2170089,
    "tgn:name":"Big Pond",
    "tgn:placetype":[
        "aat:300006191"
    ]
},
  "bbox": [],
  "geometry": {"coordinates":[-91.0667,42.7667],"type":"Point"}
}