{
  "id": 2329115,
  "type": "Feature",
  "properties": {
    "tgn:hierarchy":[
        "tgn:2329115",
        "tgn:1000001",
        "tgn:7012149",
        "tgn:2000476",
        "tgn:7007250",
        "tgn:7029392"
    ],
    "tgn:id":2329115,
    "tgn:name":"Fitting Creek",
    "tgn:placetype":[
        "aat:300008706"
    ]
},
  "bbox": [],
  "geometry": {"coordinates":[-114.8667,46.25],"type":"Point"}
}