{
  "id": 1015610,
  "type": "Feature",
  "properties": {
    "tgn:hierarchy":[
        "tgn:1015610",
        "tgn:7005685",
        "tgn:1000001",
        "tgn:7005804",
        "tgn:7029392"
    ],
    "tgn:id":1015610,
    "tgn:name":"Saint-\u00c9tienne-des-Gr\u00e8s",
    "tgn:placetype":[
        "aat:300008347"
    ]
},
  "bbox": [],
  "geometry": {"coordinates":[-72.7667,46.4333],"type":"Point"}
}