{
  "id": 1020054,
  "type": "Feature",
  "properties": {
    "tgn:hierarchy":[
        "tgn:1020054",
        "tgn:1001182",
        "tgn:7006477",
        "tgn:1000002",
        "tgn:7029392"
    ],
    "tgn:id":1020054,
    "tgn:name":"Saujil",
    "tgn:placetype":[
        "aat:300008347"
    ]
},
  "bbox": [],
  "geometry": {"coordinates":[-66.2333,-28.1833],"type":"Point"}
}