{
  "id": 2353558,
  "type": "Feature",
  "properties": {
    "tgn:hierarchy":[
        "tgn:2353558",
        "tgn:1000001",
        "tgn:7012149",
        "tgn:2001708",
        "tgn:7007708",
        "tgn:7029392"
    ],
    "tgn:id":2353558,
    "tgn:name":"Gold Hill",
    "tgn:placetype":[
        "aat:300008798"
    ]
},
  "bbox": [],
  "geometry": {"coordinates":[-119.0333,43.9667],"type":"Point"}
}