{
  "id": 2696787,
  "type": "Feature",
  "properties": {
    "tgn:hierarchy":[
        "tgn:2696787",
        "tgn:1000001",
        "tgn:1002279",
        "tgn:7012149",
        "tgn:7007706",
        "tgn:7029392"
    ],
    "tgn:id":2696787,
    "tgn:name":"Stonelick Lake",
    "tgn:placetype":[
        "aat:300006191"
    ]
},
  "bbox": [],
  "geometry": {"coordinates":[-84.0833,39.2167],"type":"Point"}
}