{
  "id": 2140289,
  "type": "Feature",
  "properties": {
    "tgn:hierarchy":[
        "tgn:2140289",
        "tgn:1000001",
        "tgn:2001409",
        "tgn:7012149",
        "tgn:7007526",
        "tgn:7029392"
    ],
    "tgn:id":2140289,
    "tgn:name":"Augusta, Mount",
    "tgn:placetype":[
        "aat:300008798"
    ]
},
  "bbox": [],
  "geometry": {"coordinates":[-117.9167,39.5333],"type":"Point"}
}