{
  "id": 2672455,
  "type": "Feature",
  "properties": {
    "tgn:hierarchy":[
        "tgn:2672455",
        "tgn:1000001",
        "tgn:7012149",
        "tgn:2002281",
        "tgn:7013961",
        "tgn:7029392"
    ],
    "tgn:id":2672455,
    "tgn:name":"Smoky Drain",
    "tgn:placetype":[
        "aat:300008699"
    ]
},
  "bbox": [],
  "geometry": {"coordinates":[-80.0833,39.6833],"type":"Point"}
}