{
  "id": 2484996,
  "type": "Feature",
  "properties": {
    "tgn:hierarchy":[
        "tgn:2484996",
        "tgn:1000001",
        "tgn:7006451",
        "tgn:2000092",
        "tgn:7012149",
        "tgn:7029392"
    ],
    "tgn:id":2484996,
    "tgn:name":"Lava River Cave",
    "tgn:placetype":[
        "aat:300008746"
    ]
},
  "bbox": [],
  "geometry": {"coordinates":[-111.8333,35.3333],"type":"Point"}
}