{
  "id": 2477018,
  "type": "Feature",
  "properties": {
    "tgn:hierarchy":[
        "tgn:2477018",
        "tgn:1000001",
        "tgn:7012149",
        "tgn:2002009",
        "tgn:7007826",
        "tgn:7029392"
    ],
    "tgn:id":2477018,
    "tgn:name":"Lynch Hill",
    "tgn:placetype":[
        "aat:300008798"
    ]
},
  "bbox": [],
  "geometry": {"coordinates":[-94.1667,30.9667],"type":"Point"}
}