{
  "id": 2329520,
  "type": "Feature",
  "properties": {
    "tgn:hierarchy":[
        "tgn:2329520",
        "tgn:1000001",
        "tgn:2001411",
        "tgn:7012149",
        "tgn:7007526",
        "tgn:7029392"
    ],
    "tgn:id":2329520,
    "tgn:name":"Five Springs",
    "tgn:placetype":[
        "aat:300008697"
    ]
},
  "bbox": [],
  "geometry": {"coordinates":[-115.7333,41.2333],"type":"Point"}
}