{
  "id": 1092152,
  "type": "Feature",
  "properties": {
    "tgn:hierarchy":[
        "tgn:1092152",
        "tgn:7001242",
        "tgn:7000542",
        "tgn:1000182",
        "tgn:7029392"
    ],
    "tgn:id":1092152,
    "tgn:name":"Magumeri",
    "tgn:placetype":[
        "aat:300008347"
    ]
},
  "bbox": [],
  "geometry": {"coordinates":[12.8333,12.1667],"type":"Point"}
}