{
  "id": 7443608,
  "type": "Feature",
  "properties": {
    "tgn:hierarchy":[
        "tgn:7443608",
        "tgn:7002448",
        "tgn:1000003",
        "tgn:7019166",
        "tgn:7008591",
        "tgn:7029392"
    ],
    "tgn:id":7443608,
    "tgn:name:en":"Carnmoney Hill",
    "tgn:placetype":[
        "aat:300008777"
    ]
},
  "bbox": [],
  "geometry": {"coordinates":[-5.933333,54.679167],"type":"Point"}
}