{
  "id": 2705482,
  "type": "Feature",
  "properties": {
    "tgn:hierarchy":[
        "tgn:2705482",
        "tgn:1000001",
        "tgn:7012149",
        "tgn:2000227",
        "tgn:7007158",
        "tgn:7029392"
    ],
    "tgn:id":2705482,
    "tgn:name":"Surratt Spring",
    "tgn:placetype":[
        "aat:300008697"
    ]
},
  "bbox": [],
  "geometry": {"coordinates":[-104.0167,37.1167],"type":"Point"}
}