{
  "id": 2770299,
  "type": "Feature",
  "properties": {
    "tgn:hierarchy":[
        "tgn:2770299",
        "tgn:1000001",
        "tgn:7012149",
        "tgn:2001313",
        "tgn:7007524",
        "tgn:7029392"
    ],
    "tgn:id":2770299,
    "tgn:name":"Wild Horse Butte",
    "tgn:placetype":[
        "aat:300008798"
    ]
},
  "bbox": [],
  "geometry": {"coordinates":[-109.7333,46.3333],"type":"Point"}
}