{
  "id": 7587260,
  "type": "Feature",
  "properties": {
    "tgn:hierarchy":[
        "tgn:7587260",
        "tgn:7001819",
        "tgn:1000004",
        "tgn:7000198",
        "tgn:7029392"
    ],
    "tgn:id":7587260,
    "tgn:name:en":"Sekhe",
    "tgn:placetype":[
        "aat:300008347"
    ]
},
  "bbox": [],
  "geometry": {"coordinates":[93.735895,27.350392],"type":"Point"}
}