{
  "id": 7543441,
  "type": "Feature",
  "properties": {
    "tgn:hierarchy":[
        "tgn:7543441",
        "tgn:7001242",
        "tgn:7016833",
        "tgn:1001113",
        "tgn:7029392"
    ],
    "tgn:id":7543441,
    "tgn:name":"Kafr an Nazlah",
    "tgn:placetype":[
        "aat:300008347"
    ]
},
  "bbox": [],
  "geometry": {"coordinates":[31.655123,30.765685],"type":"Point"}
}