<<<<<<< HEAD
{
  "id": 2255778,
  "type": "Feature",
  "properties": {
    "tgn:hierarchy":[
        "tgn:2255778",
        "tgn:1000001",
        "tgn:2001417",
        "tgn:7012149",
        "tgn:7007526",
        "tgn:7029392"
    ],
    "tgn:id":2255778,
    "tgn:name":"Copper Canyon",
    "tgn:placetype":[
        "aat:300008761"
    ]
},
  "bbox": [],
  "geometry": {"coordinates":[-118.8333,38.7167],"type":"Point"}
}
=======
{"geometry":{"type":"Point","coordinates":[-118.833300,38.716700]},"type":"Feature","properties":{"hierarchy":["tgn:2255778","tgn:1000001","tgn:2001417","tgn:7012149","tgn:7007526","tgn:7029392"],"placetype":["aat:300008761"],"id":2255778,"name:xx":"Copper Canyon"}}
>>>>>>> 03f74aca74312dbeaf24d7e61306dd6a786dc3d0
