<<<<<<< HEAD
{
  "id": 7350553,
  "type": "Feature",
  "properties": {
    "tgn:hierarchy":[
        "tgn:7350553",
        "tgn:1000001",
        "tgn:7005589",
        "tgn:7005560",
        "tgn:7029392"
    ],
    "tgn:id":7350553,
    "tgn:name":"Bustamante",
    "tgn:placetype":[
        "aat:300007783"
    ]
},
  "bbox": [],
  "geometry": {"coordinates":[-100.466667,26.55],"type":"Point"}
}
=======
{"geometry":{"type":"Point","coordinates":[-100.466667,26.550000]},"type":"Feature","properties":{"hierarchy":["tgn:7350553","tgn:1000001","tgn:7005589","tgn:7005560","tgn:7029392"],"placetype":["aat:300007783"],"id":7350553,"name:xx":"Bustamante"}}
>>>>>>> 03f74aca74312dbeaf24d7e61306dd6a786dc3d0
