{
  "id": 2371386,
  "type": "Feature",
  "properties": {
    "tgn:hierarchy":[
        "tgn:2371386",
        "tgn:1000001",
        "tgn:7012149",
        "tgn:2001191",
        "tgn:7007523",
        "tgn:7029392"
    ],
    "tgn:id":2371386,
    "tgn:name":"Hailey Spring",
    "tgn:placetype":[
        "aat:300008697"
    ]
},
  "bbox": [],
  "geometry": {"coordinates":[-93.65,37.5333],"type":"Point"}
}