{
  "id": 7428626,
  "type": "Feature",
  "properties": {
    "tgn:hierarchy":[
        "tgn:7428626",
        "tgn:7005581",
        "tgn:1000001",
        "tgn:7005560",
        "tgn:7029392"
    ],
    "tgn:id":7428626,
    "tgn:name":"Estaci\u00f3n Placa KB 490",
    "tgn:placetype":[
        "aat:300007783"
    ]
},
  "bbox": [],
  "geometry": {"coordinates":[-106.95,31.333333],"type":"Point"}
}