{
  "id": 2705151,
  "type": "Feature",
  "properties": {
    "tgn:hierarchy":[
        "tgn:2705151",
        "tgn:1000001",
        "tgn:7012149",
        "tgn:1002567",
        "tgn:7007240",
        "tgn:7029392"
    ],
    "tgn:id":2705151,
    "tgn:name":"Sunshine, Lake",
    "tgn:placetype":[
        "aat:300008680"
    ]
},
  "bbox": [],
  "geometry": {"coordinates":[-81.9167,28.9167],"type":"Point"}
}