<<<<<<< HEAD
{
  "id": 2769118,
  "type": "Feature",
  "properties": {
    "tgn:hierarchy":[
        "tgn:2769118",
        "tgn:1000001",
        "tgn:7012149",
        "tgn:7029392"
    ],
    "tgn:id":2769118,
    "tgn:name":"Whittington, Lake",
    "tgn:placetype":[
        "aat:300008680"
    ]
},
  "bbox": [],
  "geometry": {"coordinates":[-91.1,33.6667],"type":"Point"}
}
=======
{"geometry":{"type":"Point","coordinates":[-91.100000,33.666700]},"type":"Feature","properties":{"hierarchy":["tgn:2769118","tgn:1000001","tgn:7012149","tgn:7029392"],"placetype":["aat:300008680"],"id":2769118,"name:xx":"Whittington, Lake"}}
>>>>>>> 03f74aca74312dbeaf24d7e61306dd6a786dc3d0
