<<<<<<< HEAD
{
  "id": 7379289,
  "type": "Feature",
  "properties": {
    "tgn:hierarchy":[
        "tgn:7379289",
        "tgn:7005583",
        "tgn:1000001",
        "tgn:7005560",
        "tgn:7029392"
    ],
    "tgn:id":7379289,
    "tgn:name":"Los Sauces",
    "tgn:placetype":[
        "aat:300008347"
    ]
},
  "bbox": [],
  "geometry": {"coordinates":[-103.133333,24.5],"type":"Point"}
}
=======
{"geometry":{"type":"Point","coordinates":[-103.133333,24.500000]},"type":"Feature","properties":{"hierarchy":["tgn:7379289","tgn:7005583","tgn:1000001","tgn:7005560","tgn:7029392"],"placetype":["aat:300008347"],"id":7379289,"name:xx":"Los Sauces"}}
>>>>>>> 03f74aca74312dbeaf24d7e61306dd6a786dc3d0
