{
  "id": 1104111,
  "type": "Feature",
  "properties": {
    "tgn:hierarchy":[
        "tgn:1104111",
        "tgn:7006450",
        "tgn:2000069",
        "tgn:1000001",
        "tgn:7012149",
        "tgn:7029392"
    ],
    "tgn:id":1104111,
    "tgn:name":"Cairn Mountain",
    "tgn:placetype":[
        "aat:300008795"
    ]
},
  "bbox": [],
  "geometry": {"coordinates":[-155.3167,61.15],"type":"Point"}
}