{
  "id": 7368805,
  "type": "Feature",
  "properties": {
    "tgn:hierarchy":[
        "tgn:7368805",
        "tgn:7005580",
        "tgn:1000001",
        "tgn:7005560",
        "tgn:7029392"
    ],
    "tgn:id":7368805,
    "tgn:name":"Islamapa",
    "tgn:placetype":[
        "aat:300007783"
    ]
},
  "bbox": [],
  "geometry": {"coordinates":[-92.416667,15.083333],"type":"Point"}
}