{
  "id": 2581471,
  "type": "Feature",
  "properties": {
    "tgn:hierarchy":[
        "tgn:2581471",
        "tgn:1000001",
        "tgn:2001810",
        "tgn:7012149",
        "tgn:7007713",
        "tgn:7029392"
    ],
    "tgn:id":2581471,
    "tgn:name":"Pilot Knob",
    "tgn:placetype":[
        "aat:300008798"
    ]
},
  "bbox": [],
  "geometry": {"coordinates":[-103.5667,44.1333],"type":"Point"}
}