{
  "id": 2634815,
  "type": "Feature",
  "properties": {
    "tgn:hierarchy":[
        "tgn:2634815",
        "tgn:7002659",
        "tgn:1000001",
        "tgn:2000020",
        "tgn:7012149",
        "tgn:7029392"
    ],
    "tgn:id":2634815,
    "tgn:name":"Ryals Mill Creek",
    "tgn:placetype":[
        "aat:300008706"
    ]
},
  "bbox": [],
  "geometry": {"coordinates":[-86.3833,31.9333],"type":"Point"}
}