{
  "id": 7591038,
  "type": "Feature",
  "properties": {
    "tgn:hierarchy":[
        "tgn:7591038",
        "tgn:1000004",
        "tgn:7000198",
        "tgn:7000799",
        "tgn:7029392"
    ],
    "tgn:id":7591038,
    "tgn:name:en":"Wadi Cho N\u0101la",
    "tgn:placetype":[
        "aat:300008699"
    ]
},
  "bbox": [],
  "geometry": {"coordinates":[74.743056,32.751389],"type":"Point"}
}