{
  "id": 1135097,
  "type": "Feature",
  "properties": {
    "tgn:hierarchy":[
        "tgn:1135097",
        "tgn:1000001",
        "tgn:7012149",
        "tgn:7007157",
        "tgn:1002608",
        "tgn:7029392"
    ],
    "tgn:id":1135097,
    "tgn:name":"Winter Creek",
    "tgn:placetype":[
        "aat:300008706"
    ]
},
  "bbox": [],
  "geometry": {"coordinates":[-118.05,34.2167],"type":"Point"}
}