{
  "id": 7529384,
  "type": "Feature",
  "properties": {
    "tgn:hierarchy":[
        "tgn:7529384",
        "tgn:7001242",
        "tgn:1001059",
        "tgn:7016833",
        "tgn:7029392"
    ],
    "tgn:id":7529384,
    "tgn:name":"Tur'at Kamm\u016bn\u012b",
    "tgn:placetype":[
        "aat:300006075"
    ]
},
  "bbox": [],
  "geometry": {"coordinates":[31.550563,30.929314],"type":"Point"}
}