{
  "id": 7540387,
  "type": "Feature",
  "properties": {
    "tgn:hierarchy":[
        "tgn:7540387",
        "tgn:7001242",
        "tgn:7016833",
        "tgn:7000124",
        "tgn:7029392"
    ],
    "tgn:id":7540387,
    "tgn:name:en":"Q\u0101w Gharb",
    "tgn:placetype":[
        "aat:300008347"
    ]
},
  "bbox": [],
  "geometry": {"coordinates":[31.466647,26.900917],"type":"Point"}
}