{
  "id": 2626502,
  "type": "Feature",
  "properties": {
    "tgn:hierarchy":[
        "tgn:2626502",
        "tgn:1000001",
        "tgn:7012149",
        "tgn:2000839",
        "tgn:7007255",
        "tgn:7029392"
    ],
    "tgn:id":2626502,
    "tgn:name":"Rocky Hollow",
    "tgn:placetype":[
        "aat:300008761"
    ]
},
  "bbox": [],
  "geometry": {"coordinates":[-84.8333,37.0667],"type":"Point"}
}