{
  "id": 2170927,
  "type": "Feature",
  "properties": {
    "tgn:hierarchy":[
        "tgn:2170927",
        "tgn:1000001",
        "tgn:2001362",
        "tgn:7012149",
        "tgn:7007525",
        "tgn:7029392"
    ],
    "tgn:id":2170927,
    "tgn:name":"Big Slough",
    "tgn:placetype":[
        "aat:300008699"
    ]
},
  "bbox": [],
  "geometry": {"coordinates":[-98.5833,41.0667],"type":"Point"}
}