{
  "id": 7558566,
  "type": "Feature",
  "properties": {
    "tgn:hierarchy":[
        "tgn:7558566",
        "tgn:1000004",
        "tgn:7000198",
        "tgn:7016788",
        "tgn:7029392"
    ],
    "tgn:id":7558566,
    "tgn:name:en":"Rendari",
    "tgn:placetype":[
        "aat:300008347"
    ]
},
  "bbox": [],
  "geometry": {"coordinates":[72.989475,25.951297],"type":"Point"}
}