<<<<<<< HEAD
{
  "id": 2155315,
  "type": "Feature",
  "properties": {
    "tgn:hierarchy":[
        "tgn:2155315",
        "tgn:1000001",
        "tgn:7012149",
        "tgn:2002377",
        "tgn:7007923",
        "tgn:7029392"
    ],
    "tgn:id":2155315,
    "tgn:name":"Bear Mountain",
    "tgn:placetype":[
        "aat:300008798"
    ]
},
  "bbox": [],
  "geometry": {"coordinates":[-106.5333,42.4333],"type":"Point"}
}
=======
{"geometry":{"type":"Point","coordinates":[-106.533300,42.433300]},"type":"Feature","properties":{"hierarchy":["tgn:2155315","tgn:1000001","tgn:7012149","tgn:2002377","tgn:7007923","tgn:7029392"],"placetype":["aat:300008798"],"id":2155315,"name:xx":"Bear Mountain"}}
>>>>>>> 03f74aca74312dbeaf24d7e61306dd6a786dc3d0
