{
  "id": 1030368,
  "type": "Feature",
  "properties": {
    "tgn:hierarchy":[
        "tgn:1030368",
        "tgn:7002445",
        "tgn:1000003",
        "tgn:7011961",
        "tgn:7008591",
        "tgn:7029392"
    ],
    "tgn:id":1030368,
    "tgn:name:en":"Preston",
    "tgn:placetype":[
        "aat:300008347"
    ]
},
  "bbox": [],
  "geometry": {"coordinates":[-2.416667,50.65],"type":"Point"}
}