{
  "id": 2454827,
  "type": "Feature",
  "properties": {
    "tgn:hierarchy":[
        "tgn:2454827",
        "tgn:1000001",
        "tgn:7012149",
        "tgn:2002373",
        "tgn:7007923",
        "tgn:7029392"
    ],
    "tgn:id":2454827,
    "tgn:name":"Little Dry Muddy Spring",
    "tgn:placetype":[
        "aat:300008697"
    ]
},
  "bbox": [],
  "geometry": {"coordinates":[-109.15,43.6333],"type":"Point"}
}