{
  "id": 7077295,
  "type": "Feature",
  "properties": {
    "tgn:hierarchy":[
        "tgn:7077295",
        "tgn:7003669",
        "tgn:1000003",
        "tgn:7000084",
        "tgn:7029392"
    ],
    "tgn:id":7077295,
    "tgn:name":"Landkreis Miesbach",
    "tgn:placetype":[
        "aat:300387198"
    ]
},
  "bbox": [],
  "geometry": {"coordinates":[11.816111,47.771667],"type":"Point"}
}