{
  "id": 7369913,
  "type": "Feature",
  "properties": {
    "tgn:hierarchy":[
        "tgn:7369913",
        "tgn:1000001",
        "tgn:1001960",
        "tgn:7005560",
        "tgn:7029392"
    ],
    "tgn:id":7369913,
    "tgn:name":"Guam\u00fachil",
    "tgn:placetype":[
        "aat:300008347"
    ]
},
  "bbox": [],
  "geometry": {"coordinates":[-108.597778,26.79],"type":"Point"}
}