{
  "id": 2687119,
  "type": "Feature",
  "properties": {
    "tgn:hierarchy":[
        "tgn:2687119",
        "tgn:1000001",
        "tgn:7012149",
        "tgn:7007157",
        "tgn:1002710",
        "tgn:7029392"
    ],
    "tgn:id":2687119,
    "tgn:name":"Spring Hill Mine",
    "tgn:placetype":[
        "aat:300000390"
    ]
},
  "bbox": [],
  "geometry": {"coordinates":[-121.0333,39.2167],"type":"Point"}
}