{
  "id": 2691934,
  "type": "Feature",
  "properties": {
    "tgn:hierarchy":[
        "tgn:2691934",
        "tgn:1000001",
        "tgn:7012149",
        "tgn:1002979",
        "tgn:7007920",
        "tgn:7029392"
    ],
    "tgn:id":2691934,
    "tgn:name":"State Camp",
    "tgn:placetype":[
        "aat:300008347"
    ]
},
  "bbox": [],
  "geometry": {"coordinates":[-123.3167,46.25],"type":"Point"}
}