<<<<<<< HEAD
{
  "id": 2404659,
  "type": "Feature",
  "properties": {
    "tgn:hierarchy":[
        "tgn:2404659",
        "tgn:1000001",
        "tgn:7012149",
        "tgn:7014589",
        "tgn:7007515",
        "tgn:7029392"
    ],
    "tgn:id":2404659,
    "tgn:name":"Huckins Ledge",
    "tgn:placetype":[
        "aat:300132348"
    ]
},
  "bbox": [],
  "geometry": {"coordinates":[-67.05,44.8833],"type":"Point"}
}
=======
{"geometry":{"type":"Point","coordinates":[-67.050000,44.883300]},"type":"Feature","properties":{"hierarchy":["tgn:2404659","tgn:1000001","tgn:7012149","tgn:7014589","tgn:7007515","tgn:7029392"],"placetype":["aat:300132348"],"id":2404659,"name:xx":"Huckins Ledge"}}
>>>>>>> 03f74aca74312dbeaf24d7e61306dd6a786dc3d0
