{
  "id": 2404659,
  "type": "Feature",
  "properties": {
    "tgn:hierarchy":[
        "tgn:2404659",
        "tgn:1000001",
        "tgn:7012149",
        "tgn:7014589",
        "tgn:7007515",
        "tgn:7029392"
    ],
    "tgn:id":2404659,
    "tgn:name":"Huckins Ledge",
    "tgn:placetype":[
        "aat:300132348"
    ]
},
  "bbox": [],
  "geometry": {"coordinates":[-67.05,44.8833],"type":"Point"}
}