<<<<<<< HEAD
{
  "id": 7240791,
  "type": "Feature",
  "properties": {
    "tgn:hierarchy":[
        "tgn:7240791",
        "tgn:7018237",
        "tgn:1000003",
        "tgn:1000063",
        "tgn:7029392"
    ],
    "tgn:id":7240791,
    "tgn:name":"Flor\u00e9al",
    "tgn:placetype":[
        "aat:300008347"
    ]
},
  "bbox": [],
  "geometry": {"coordinates":[4.416667,50.8],"type":"Point"}
}
=======
{"geometry":{"type":"Point","coordinates":[4.416667,50.800000]},"type":"Feature","properties":{"hierarchy":["tgn:7240791","tgn:7018237","tgn:1000003","tgn:1000063","tgn:7029392"],"placetype":["aat:300008347"],"id":7240791,"name:xx":"Flor\u00e9al"}}
>>>>>>> 03f74aca74312dbeaf24d7e61306dd6a786dc3d0
