{
  "id": 2632746,
  "type": "Feature",
  "properties": {
    "tgn:hierarchy":[
        "tgn:2632746",
        "tgn:1000001",
        "tgn:7012149",
        "tgn:2001273",
        "tgn:7007524",
        "tgn:7029392"
    ],
    "tgn:id":2632746,
    "tgn:name":"Ruby Gulch",
    "tgn:placetype":[
        "aat:300008761"
    ]
},
  "bbox": [],
  "geometry": {"coordinates":[-109.3167,47.1333],"type":"Point"}
}