{
  "id": 7534593,
  "type": "Feature",
  "properties": {
    "tgn:hierarchy":[
        "tgn:7534593",
        "tgn:7001242",
        "tgn:7016833",
        "tgn:7029392"
    ],
    "tgn:id":7534593,
    "tgn:name:en":"Kab\u012br, Al Ghurd al",
    "tgn:placetype":[
        "aat:300008750"
    ]
},
  "bbox": [],
  "geometry": {"coordinates":[28.014317,28.601576],"type":"Point"}
}