{
  "id": 2774096,
  "type": "Feature",
  "properties": {
    "tgn:hierarchy":[
        "tgn:2774096",
        "tgn:1000001",
        "tgn:7012149",
        "tgn:1002771",
        "tgn:7007826",
        "tgn:7029392"
    ],
    "tgn:id":2774096,
    "tgn:name":"Willow Creek",
    "tgn:placetype":[
        "aat:300008706"
    ]
},
  "bbox": [],
  "geometry": {"coordinates":[-97.8667,32.8333],"type":"Point"}
}