{
  "id": 2079300,
  "type": "Feature",
  "properties": {
    "tgn:hierarchy":[
        "tgn:2079300",
        "tgn:1000001",
        "tgn:7012149",
        "tgn:1002453",
        "tgn:7007706",
        "tgn:7029392"
    ],
    "tgn:id":2079300,
    "tgn:name":"Dola",
    "tgn:placetype":[
        "aat:300008347"
    ]
},
  "bbox": [],
  "geometry": {"coordinates":[-83.6833,40.7667],"type":"Point"}
}