{
  "id": 2087510,
  "type": "Feature",
  "properties": {
    "tgn:hierarchy":[
        "tgn:2087510",
        "tgn:1000001",
        "tgn:7012149",
        "tgn:7016020",
        "tgn:7007710",
        "tgn:7029392"
    ],
    "tgn:id":2087510,
    "tgn:name":"Corwins Corners",
    "tgn:placetype":[
        "aat:300008347",
        "aat:300387210"
    ]
},
  "bbox": [],
  "geometry": {"coordinates":[-78.5667,41.9167],"type":"Point"}
}