{
  "id": 1060562,
  "type": "Feature",
  "properties": {
    "tgn:hierarchy":[
        "tgn:1060562",
        "tgn:7011538",
        "tgn:1000004",
        "tgn:7018214",
        "tgn:7002435",
        "tgn:7029392"
    ],
    "tgn:id":1060562,
    "tgn:name":"Uchami",
    "tgn:placetype":[
        "aat:300008347"
    ]
},
  "bbox": [],
  "geometry": {"coordinates":[96.55,63.8667],"type":"Point"}
}