{
  "id": 2550023,
  "type": "Feature",
  "properties": {
    "tgn:hierarchy":[
        "tgn:2550023",
        "tgn:1000001",
        "tgn:7012149",
        "tgn:7007708",
        "tgn:7029392"
    ],
    "tgn:id":2550023,
    "tgn:name":"North Wolf Creek",
    "tgn:placetype":[
        "aat:300008706"
    ]
},
  "bbox": [],
  "geometry": {"coordinates":[-119.8667,44.3167],"type":"Point"}
}