{
  "id": 2200719,
  "type": "Feature",
  "properties": {
    "tgn:hierarchy":[
        "tgn:2200719",
        "tgn:1000001",
        "tgn:7012149",
        "tgn:2001917",
        "tgn:7007825",
        "tgn:7029392"
    ],
    "tgn:id":2200719,
    "tgn:name":"Bruton Spring Branch",
    "tgn:placetype":[
        "aat:300008699"
    ]
},
  "bbox": [],
  "geometry": {"coordinates":[-87.8667,36.5667],"type":"Point"}
}