{
  "id": 2483821,
  "type": "Feature",
  "properties": {
    "tgn:hierarchy":[
        "tgn:2483821",
        "tgn:1000001",
        "tgn:7012149",
        "tgn:2002371",
        "tgn:7007923",
        "tgn:7029392"
    ],
    "tgn:id":2483821,
    "tgn:name":"Lateral P-27.0- D",
    "tgn:placetype":[
        "aat:300006075"
    ]
},
  "bbox": [],
  "geometry": {"coordinates":[-108.3667,43.1833],"type":"Point"}
}