<<<<<<< HEAD
{
  "id": 2338969,
  "type": "Feature",
  "properties": {
    "tgn:hierarchy":[
        "tgn:2338969",
        "tgn:7002659",
        "tgn:1000001",
        "tgn:7012149",
        "tgn:7021514",
        "tgn:7029392"
    ],
    "tgn:id":2338969,
    "tgn:name":"Franklin Ford",
    "tgn:placetype":[
        "aat:300008347"
    ]
},
  "bbox": [],
  "geometry": {"coordinates":[-85.7833,34.4833],"type":"Point"}
}
=======
{"geometry":{"type":"Point","coordinates":[-85.783300,34.483300]},"type":"Feature","properties":{"hierarchy":["tgn:2338969","tgn:7002659","tgn:1000001","tgn:7012149","tgn:7021514","tgn:7029392"],"placetype":["aat:300008347"],"id":2338969,"name:xx":"Franklin Ford"}}
>>>>>>> 03f74aca74312dbeaf24d7e61306dd6a786dc3d0
