<<<<<<< HEAD
{
  "id": 2333489,
  "type": "Feature",
  "properties": {
    "tgn:hierarchy":[
        "tgn:2333489",
        "tgn:1000001",
        "tgn:2001734",
        "tgn:7012149",
        "tgn:7007712",
        "tgn:7029392"
    ],
    "tgn:id":2333489,
    "tgn:name":"Folly Island",
    "tgn:placetype":[
        "aat:300008791"
    ]
},
  "bbox": [],
  "geometry": {"coordinates":[-79.9167,32.65],"type":"Point"}
}
=======
{"geometry":{"type":"Point","coordinates":[-79.916700,32.650000]},"type":"Feature","properties":{"hierarchy":["tgn:2333489","tgn:1000001","tgn:2001734","tgn:7012149","tgn:7007712","tgn:7029392"],"placetype":["aat:300008791"],"id":2333489,"name:xx":"Folly Island"}}
>>>>>>> 03f74aca74312dbeaf24d7e61306dd6a786dc3d0
