{
  "id": 2354594,
  "type": "Feature",
  "properties": {
    "tgn:hierarchy":[
        "tgn:2354594",
        "tgn:1000001",
        "tgn:7012149",
        "tgn:7007157",
        "tgn:1002858",
        "tgn:7029392"
    ],
    "tgn:id":2354594,
    "tgn:name":"Gonzales Canyon",
    "tgn:placetype":[
        "aat:300008761"
    ]
},
  "bbox": [],
  "geometry": {"coordinates":[-117.15,32.9667],"type":"Point"}
}