{
  "id": 7220959,
  "type": "Feature",
  "properties": {
    "tgn:hierarchy":[
        "tgn:7220959",
        "tgn:7011164",
        "tgn:7002674",
        "tgn:1000003",
        "tgn:1000074",
        "tgn:7029392"
    ],
    "tgn:id":7220959,
    "tgn:name":"Skl\u00e1vou",
    "tgn:placetype":[
        "aat:300008777"
    ]
},
  "bbox": [],
  "geometry": {"coordinates":[26.856111,37.705833],"type":"Point"}
}