{
  "id": 7503092,
  "type": "Feature",
  "properties": {
    "tgn:hierarchy":[
        "tgn:7503092",
        "tgn:7001010",
        "tgn:1000004",
        "tgn:1000141",
        "tgn:7029392"
    ],
    "tgn:id":7503092,
    "tgn:name":"Tengliao",
    "tgn:placetype":[
        "aat:300008347"
    ]
},
  "bbox": [],
  "geometry": {"coordinates":[121.244444,23.1875],"type":"Point"}
}