{
  "id": 2290903,
  "type": "Feature",
  "properties": {
    "tgn:hierarchy":[
        "tgn:2290903",
        "tgn:1000001",
        "tgn:7012149",
        "tgn:7014589",
        "tgn:7007515",
        "tgn:7029392"
    ],
    "tgn:id":2290903,
    "tgn:name":"Dog Islands",
    "tgn:placetype":[
        "aat:300386853"
    ]
},
  "bbox": [],
  "geometry": {"coordinates":[-67.4167,45.3667],"type":"Point"}
}