{
  "id": 2649824,
  "type": "Feature",
  "properties": {
    "tgn:hierarchy":[
        "tgn:2649824",
        "tgn:1000001",
        "tgn:7012149",
        "tgn:2000788",
        "tgn:7007255",
        "tgn:7029392"
    ],
    "tgn:id":2649824,
    "tgn:name":"Scrivner Branch",
    "tgn:placetype":[
        "aat:300008699"
    ]
},
  "bbox": [],
  "geometry": {"coordinates":[-83.9167,37.6167],"type":"Point"}
}