{
  "id": 7097073,
  "type": "Feature",
  "properties": {
    "tgn:hierarchy":[
        "tgn:7097073",
        "tgn:1000003",
        "tgn:7003676",
        "tgn:7000084",
        "tgn:7029392"
    ],
    "tgn:id":7097073,
    "tgn:name":"Smarlingen",
    "tgn:placetype":[
        "aat:300008347"
    ]
},
  "bbox": [],
  "geometry": {"coordinates":[7.316667,53.15],"type":"Point"}
}