{
  "id": 1085058,
  "type": "Feature",
  "properties": {
    "tgn:hierarchy":[
        "tgn:1085058",
        "tgn:1002052",
        "tgn:1000004",
        "tgn:1000140",
        "tgn:7029392"
    ],
    "tgn:id":1085058,
    "tgn:name":"Al At\u0101rib",
    "tgn:placetype":[
        "aat:300008347"
    ]
},
  "bbox": [],
  "geometry": {"coordinates":[36.8167,36.1333],"type":"Point"}
}