{
  "id": 7564593,
  "type": "Feature",
  "properties": {
    "tgn:hierarchy":[
        "tgn:7564593",
        "tgn:1000004",
        "tgn:7000198",
        "tgn:7016722",
        "tgn:7029392"
    ],
    "tgn:id":7564593,
    "tgn:name:en":"Bijuw\u0101pur Reserved Forest",
    "tgn:placetype":[
        "aat:300008865"
    ]
},
  "bbox": [],
  "geometry": {"coordinates":[79.394446,26.411994],"type":"Point"}
}