{
  "id": 7545903,
  "type": "Feature",
  "properties": {
    "tgn:hierarchy":[
        "tgn:7545903",
        "tgn:1000004",
        "tgn:1001869",
        "tgn:7000198",
        "tgn:7029392"
    ],
    "tgn:id":7545903,
    "tgn:name:en":"Barw\u0101la Road",
    "tgn:placetype":[
        "aat:300007783"
    ]
},
  "bbox": [],
  "geometry": {"coordinates":[70.716667,22.883333],"type":"Point"}
}