{
  "id": 7358713,
  "type": "Feature",
  "properties": {
    "tgn:hierarchy":[
        "tgn:7358713",
        "tgn:7005581",
        "tgn:1000001",
        "tgn:7005560",
        "tgn:7029392"
    ],
    "tgn:id":7358713,
    "tgn:name":"Desahijadero",
    "tgn:placetype":[
        "aat:300008347"
    ]
},
  "bbox": [],
  "geometry": {"coordinates":[-106.966667,29.983333],"type":"Point"}
}