{
  "id": 2462550,
  "type": "Feature",
  "properties": {
    "tgn:hierarchy":[
        "tgn:2462550",
        "tgn:1000001",
        "tgn:7012149",
        "tgn:2000928",
        "tgn:7007515",
        "tgn:7029392"
    ],
    "tgn:id":2462550,
    "tgn:name":"Little Wilder Pond",
    "tgn:placetype":[
        "aat:300008680"
    ]
},
  "bbox": [],
  "geometry": {"coordinates":[-69.35,45.4333],"type":"Point"}
}