{
  "id": 1095833,
  "type": "Feature",
  "properties": {
    "tgn:hierarchy":[
        "tgn:1095833",
        "tgn:7024148",
        "tgn:7001242",
        "tgn:1000604",
        "tgn:1000208",
        "tgn:7029392"
    ],
    "tgn:id":1095833,
    "tgn:name":"Matiacoli",
    "tgn:placetype":[
        "aat:300008347"
    ]
},
  "bbox": [],
  "geometry": {"coordinates":[1.0333,12.4667],"type":"Point"}
}