{
  "id": 2348709,
  "type": "Feature",
  "properties": {
    "tgn:hierarchy":[
        "tgn:2348709",
        "tgn:1000001",
        "tgn:7012149",
        "tgn:1002883",
        "tgn:7007706",
        "tgn:7029392"
    ],
    "tgn:id":2348709,
    "tgn:name":"Gibson Creek",
    "tgn:placetype":[
        "aat:300008706"
    ]
},
  "bbox": [],
  "geometry": {"coordinates":[-83.15,41.0667],"type":"Point"}
}