{
  "id": 4011024,
  "type": "Feature",
  "properties": {
    "tgn:hierarchy":[
        "tgn:4011024",
        "tgn:7002445",
        "tgn:7008104",
        "tgn:1000003",
        "tgn:7008591",
        "tgn:7029392"
    ],
    "tgn:id":4011024,
    "tgn:name:ang":"Thapeslau",
    "tgn:placetype":[
        "aat:300008347"
    ]
},
  "bbox": [],
  "geometry": {"coordinates":[-0.683333,51.516667],"type":"Point"}
}