{
  "id": 7105048,
  "type": "Feature",
  "properties": {
    "tgn:hierarchy":[
        "tgn:7105048",
        "tgn:7000096",
        "tgn:1000003",
        "tgn:7000084",
        "tgn:7029392"
    ],
    "tgn:id":7105048,
    "tgn:name":"Schigarren-Teich",
    "tgn:placetype":[
        "aat:300008688"
    ]
},
  "bbox": [],
  "geometry": {"coordinates":[14.65,51.683333],"type":"Point"}
}