{
  "id": 7407464,
  "type": "Feature",
  "properties": {
    "tgn:hierarchy":[
        "tgn:7407464",
        "tgn:1000001",
        "tgn:1001893",
        "tgn:7005560",
        "tgn:7029392"
    ],
    "tgn:id":7407464,
    "tgn:name":"Pachuquilla",
    "tgn:placetype":[
        "aat:300008347"
    ]
},
  "bbox": [],
  "geometry": {"coordinates":[-99.608333,18.883333],"type":"Point"}
}