{
  "id": 2136099,
  "type": "Feature",
  "properties": {
    "tgn:hierarchy":[
        "tgn:2136099",
        "tgn:1000001",
        "tgn:2000540",
        "tgn:7012149",
        "tgn:7007252",
        "tgn:7029392"
    ],
    "tgn:id":2136099,
    "tgn:name":"Aqua Creek",
    "tgn:placetype":[
        "aat:300008706"
    ]
},
  "bbox": [],
  "geometry": {"coordinates":[-87.1833,39.5167],"type":"Point"}
}