{
  "id": 2520940,
  "type": "Feature",
  "properties": {
    "tgn:hierarchy":[
        "tgn:2520940",
        "tgn:1000001",
        "tgn:7012149",
        "tgn:1002451",
        "tgn:7007919",
        "tgn:7029392"
    ],
    "tgn:id":2520940,
    "tgn:name":"Mont Air Creek",
    "tgn:placetype":[
        "aat:300008706"
    ]
},
  "bbox": [],
  "geometry": {"coordinates":[-77.6333,37.8667],"type":"Point"}
}