<<<<<<< HEAD
{
  "id": 2402578,
  "type": "Feature",
  "properties": {
    "tgn:hierarchy":[
        "tgn:2402578",
        "tgn:1000001",
        "tgn:2000862",
        "tgn:7012149",
        "tgn:7007256",
        "tgn:7029392"
    ],
    "tgn:id":2402578,
    "tgn:name":"Hoss Creek",
    "tgn:placetype":[
        "aat:300008706"
    ]
},
  "bbox": [],
  "geometry": {"coordinates":[-93.9167,32.9667],"type":"Point"}
}
=======
{"geometry":{"type":"Point","coordinates":[-93.916700,32.966700]},"type":"Feature","properties":{"hierarchy":["tgn:2402578","tgn:1000001","tgn:2000862","tgn:7012149","tgn:7007256","tgn:7029392"],"placetype":["aat:300008706"],"id":2402578,"name:xx":"Hoss Creek"}}
>>>>>>> 03f74aca74312dbeaf24d7e61306dd6a786dc3d0
