{
  "id": 1002461,
  "type": "Feature",
  "properties": {
    "tgn:hierarchy":[
        "tgn:1002461",
        "tgn:1000001",
        "tgn:7012149",
        "tgn:7007159",
        "tgn:7029392"
    ],
    "tgn:id":1002461,
    "tgn:name":"Hartford",
    "tgn:placetype":[
        "aat:300387145",
        "aat:300000771"
    ]
},
  "bbox": [],
  "geometry": {"coordinates":[-72.7667,41.7667],"type":"Point"}
}