{
  "id": 2256852,
  "type": "Feature",
  "properties": {
    "tgn:hierarchy":[
        "tgn:2256852",
        "tgn:1000001",
        "tgn:7012149",
        "tgn:2000471",
        "tgn:7007250",
        "tgn:7029392"
    ],
    "tgn:id":2256852,
    "tgn:name":"Corker Springs",
    "tgn:placetype":[
        "aat:300008697"
    ]
},
  "bbox": [],
  "geometry": {"coordinates":[-115.2333,43.0833],"type":"Point"}
}