{
  "id": 2109291,
  "type": "Feature",
  "properties": {
    "tgn:hierarchy":[
        "tgn:2109291",
        "tgn:1000001",
        "tgn:2002104",
        "tgn:7012149",
        "tgn:7007827",
        "tgn:7029392"
    ],
    "tgn:id":2109291,
    "tgn:name":"Spring Glen",
    "tgn:placetype":[
        "aat:300008347"
    ]
},
  "bbox": [],
  "geometry": {"coordinates":[-110.85,39.65],"type":"Point"}
}