{
  "id": 2198180,
  "type": "Feature",
  "properties": {
    "tgn:hierarchy":[
        "tgn:2198180",
        "tgn:1000001",
        "tgn:7012149",
        "tgn:2001222",
        "tgn:7007523",
        "tgn:7029392"
    ],
    "tgn:id":2198180,
    "tgn:name":"Browns",
    "tgn:placetype":[
        "aat:300008347"
    ]
},
  "bbox": [],
  "geometry": {"coordinates":[-89.6167,36.85],"type":"Point"}
}