{
  "id": 7181060,
  "type": "Feature",
  "properties": {
    "tgn:hierarchy":[
        "tgn:7181060",
        "tgn:7003692",
        "tgn:1000003",
        "tgn:7000084",
        "tgn:7029392"
    ],
    "tgn:id":7181060,
    "tgn:name":"Gaisdorf",
    "tgn:placetype":[
        "aat:300008347"
    ]
},
  "bbox": [],
  "geometry": {"coordinates":[9.746667,49.173889],"type":"Point"}
}