{
  "id": 2200612,
  "type": "Feature",
  "properties": {
    "tgn:hierarchy":[
        "tgn:2200612",
        "tgn:1000001",
        "tgn:7012149",
        "tgn:2001867",
        "tgn:7007825",
        "tgn:7029392"
    ],
    "tgn:id":2200612,
    "tgn:name":"Brushy Ridge",
    "tgn:placetype":[
        "aat:300266640"
    ]
},
  "bbox": [],
  "geometry": {"coordinates":[-85.7167,35.2833],"type":"Point"}
}