{
  "id": 2692243,
  "type": "Feature",
  "properties": {
    "tgn:hierarchy":[
        "tgn:2692243",
        "tgn:1000001",
        "tgn:7012149",
        "tgn:2001420",
        "tgn:7007526",
        "tgn:7029392"
    ],
    "tgn:id":2692243,
    "tgn:name":"Station Spring",
    "tgn:placetype":[
        "aat:300008697"
    ]
},
  "bbox": [],
  "geometry": {"coordinates":[-115.4833,40.0333],"type":"Point"}
}