{
  "id": 2363762,
  "type": "Feature",
  "properties": {
    "tgn:hierarchy":[
        "tgn:2363762",
        "tgn:2124017",
        "tgn:7006450",
        "tgn:1000001",
        "tgn:7012149",
        "tgn:7029392"
    ],
    "tgn:id":2363762,
    "tgn:name":"Green Lake",
    "tgn:placetype":[
        "aat:300008680"
    ]
},
  "bbox": [],
  "geometry": {"coordinates":[-149.8333,61.2667],"type":"Point"}
}