{
  "id": 2377029,
  "type": "Feature",
  "properties": {
    "tgn:hierarchy":[
        "tgn:2377029",
        "tgn:1000001",
        "tgn:7012149",
        "tgn:2002088",
        "tgn:7007826",
        "tgn:7029392"
    ],
    "tgn:id":2377029,
    "tgn:name":"Harland Canyon",
    "tgn:placetype":[
        "aat:300008761"
    ]
},
  "bbox": [],
  "geometry": {"coordinates":[-101.25,29.9833],"type":"Point"}
}