{
  "id": 7046391,
  "type": "Feature",
  "properties": {
    "tgn:hierarchy":[
        "tgn:7046391",
        "tgn:7003171",
        "tgn:1000003",
        "tgn:7003125",
        "tgn:1000080",
        "tgn:7029392"
    ],
    "tgn:id":7046391,
    "tgn:name":"Collevalenza",
    "tgn:placetype":[
        "aat:300008347"
    ]
},
  "bbox": [],
  "geometry": {"coordinates":[12.483333,42.75],"type":"Point"}
}