<<<<<<< HEAD
{
  "id": 7371857,
  "type": "Feature",
  "properties": {
    "tgn:hierarchy":[
        "tgn:7371857",
        "tgn:1000001",
        "tgn:7005589",
        "tgn:7005560",
        "tgn:7029392"
    ],
    "tgn:id":7371857,
    "tgn:name":"Lampazos, Sierra de",
    "tgn:placetype":[
        "aat:300008795"
    ]
},
  "bbox": [],
  "geometry": {"coordinates":[-100.4,26.95],"type":"Point"}
}
=======
{"geometry":{"type":"Point","coordinates":[-100.400000,26.950000]},"type":"Feature","properties":{"hierarchy":["tgn:7371857","tgn:1000001","tgn:7005589","tgn:7005560","tgn:7029392"],"placetype":["aat:300008795"],"id":7371857,"name:xx":"Lampazos, Sierra de"}}
>>>>>>> 03f74aca74312dbeaf24d7e61306dd6a786dc3d0
