{
  "id": 7561284,
  "type": "Feature",
  "properties": {
    "tgn:hierarchy":[
        "tgn:7561284",
        "tgn:1000004",
        "tgn:7000198",
        "tgn:7016722",
        "tgn:7029392"
    ],
    "tgn:id":7561284,
    "tgn:name:en":"Behta Aiman",
    "tgn:placetype":[
        "aat:300008347"
    ]
},
  "bbox": [],
  "geometry": {"coordinates":[79.261988,27.959006],"type":"Point"}
}