<<<<<<< HEAD
{
  "id": 2153272,
  "type": "Feature",
  "properties": {
    "tgn:hierarchy":[
        "tgn:2153272",
        "tgn:1000001",
        "tgn:2001436",
        "tgn:7012149",
        "tgn:7007566",
        "tgn:7029392"
    ],
    "tgn:id":2153272,
    "tgn:name":"Beaman Tank",
    "tgn:placetype":[
        "aat:300006191"
    ]
},
  "bbox": [],
  "geometry": {"coordinates":[-104.1833,32.2],"type":"Point"}
}
=======
{"geometry":{"type":"Point","coordinates":[-104.183300,32.200000]},"type":"Feature","properties":{"hierarchy":["tgn:2153272","tgn:1000001","tgn:2001436","tgn:7012149","tgn:7007566","tgn:7029392"],"placetype":["aat:300006191"],"id":2153272,"name:xx":"Beaman Tank"}}
>>>>>>> 03f74aca74312dbeaf24d7e61306dd6a786dc3d0
