<<<<<<< HEAD
{
  "id": 2156327,
  "type": "Feature",
  "properties": {
    "tgn:hierarchy":[
        "tgn:2156327",
        "tgn:1000001",
        "tgn:7012149",
        "tgn:2001906",
        "tgn:7007825",
        "tgn:7029392"
    ],
    "tgn:id":2156327,
    "tgn:name":"Bearpen Hill",
    "tgn:placetype":[
        "aat:300008798"
    ]
},
  "bbox": [],
  "geometry": {"coordinates":[-84.55,35.0167],"type":"Point"}
}
=======
{"geometry":{"type":"Point","coordinates":[-84.550000,35.016700]},"type":"Feature","properties":{"hierarchy":["tgn:2156327","tgn:1000001","tgn:7012149","tgn:2001906","tgn:7007825","tgn:7029392"],"placetype":["aat:300008798"],"id":2156327,"name:xx":"Bearpen Hill"}}
>>>>>>> 03f74aca74312dbeaf24d7e61306dd6a786dc3d0
