<<<<<<< HEAD
{
  "id": 7370234,
  "type": "Feature",
  "properties": {
    "tgn:hierarchy":[
        "tgn:7370234",
        "tgn:1000001",
        "tgn:7005590",
        "tgn:7005560",
        "tgn:7029392"
    ],
    "tgn:id":7370234,
    "tgn:name":"Gu\u00e1scaro",
    "tgn:placetype":[
        "aat:300007783"
    ]
},
  "bbox": [],
  "geometry": {"coordinates":[-102.533333,19.816667],"type":"Point"}
}
=======
{"geometry":{"type":"Point","coordinates":[-102.533333,19.816667]},"type":"Feature","properties":{"hierarchy":["tgn:7370234","tgn:1000001","tgn:7005590","tgn:7005560","tgn:7029392"],"placetype":["aat:300007783"],"id":7370234,"name:xx":"Gu\u00e1scaro"}}
>>>>>>> 03f74aca74312dbeaf24d7e61306dd6a786dc3d0
