{
  "id": 7348264,
  "type": "Feature",
  "properties": {
    "tgn:hierarchy":[
        "tgn:7348264",
        "tgn:7002758",
        "tgn:1001316",
        "tgn:1000003",
        "tgn:1000095",
        "tgn:7029392"
    ],
    "tgn:id":7348264,
    "tgn:name":"\u00c1guila, Piedras del",
    "tgn:placetype":[
        "aat:300266640"
    ]
},
  "bbox": [],
  "geometry": {"coordinates":[-3.166667,38.433333],"type":"Point"}
}