{
  "id": 7574168,
  "type": "Feature",
  "properties": {
    "tgn:hierarchy":[
        "tgn:7574168",
        "tgn:1000004",
        "tgn:7000198",
        "tgn:7016722",
        "tgn:7029392"
    ],
    "tgn:id":7574168,
    "tgn:name:en":"Kakarbai",
    "tgn:placetype":[
        "aat:300008347"
    ]
},
  "bbox": [],
  "geometry": {"coordinates":[79.332086,25.695831],"type":"Point"}
}