{
  "id": 1067387,
  "type": "Feature",
  "properties": {
    "tgn:hierarchy":[
        "tgn:1067387",
        "tgn:1000956",
        "tgn:1000004",
        "tgn:1000111",
        "tgn:7029392"
    ],
    "tgn:id":1067387,
    "tgn:name":"Dahuashan",
    "tgn:placetype":[
        "aat:300008347"
    ]
},
  "bbox": [],
  "geometry": {"coordinates":[117.05,40.25],"type":"Point"}
}