{
  "id": 7566107,
  "type": "Feature",
  "properties": {
    "tgn:hierarchy":[
        "tgn:7566107",
        "tgn:1000004",
        "tgn:7000198",
        "tgn:7016722",
        "tgn:7029392"
    ],
    "tgn:id":7566107,
    "tgn:name:en":"Mall\u016bpura",
    "tgn:placetype":[
        "aat:300008347"
    ]
},
  "bbox": [],
  "geometry": {"coordinates":[79.335034,26.017982],"type":"Point"}
}