{
  "id": 2446662,
  "type": "Feature",
  "properties": {
    "tgn:hierarchy":[
        "tgn:2446662",
        "tgn:1000001",
        "tgn:7012149",
        "tgn:2001286",
        "tgn:7007524",
        "tgn:7029392"
    ],
    "tgn:id":2446662,
    "tgn:name":"Lewis, Mount",
    "tgn:placetype":[
        "aat:300008798"
    ]
},
  "bbox": [],
  "geometry": {"coordinates":[-114.7167,48.8833],"type":"Point"}
}