<<<<<<< HEAD
{
  "id": 2157778,
  "type": "Feature",
  "properties": {
    "tgn:hierarchy":[
        "tgn:2157778",
        "tgn:1000001",
        "tgn:7012149",
        "tgn:1002356",
        "tgn:7007568",
        "tgn:7029392"
    ],
    "tgn:id":2157778,
    "tgn:name":"Beaver Island",
    "tgn:placetype":[
        "aat:300008791"
    ]
},
  "bbox": [],
  "geometry": {"coordinates":[-78.95,42.95],"type":"Point"}
}
=======
{"geometry":{"type":"Point","coordinates":[-78.950000,42.950000]},"type":"Feature","properties":{"hierarchy":["tgn:2157778","tgn:1000001","tgn:7012149","tgn:1002356","tgn:7007568","tgn:7029392"],"placetype":["aat:300008791"],"id":2157778,"name:xx":"Beaver Island"}}
>>>>>>> 03f74aca74312dbeaf24d7e61306dd6a786dc3d0
