{
  "id": 7293156,
  "type": "Feature",
  "properties": {
    "tgn:hierarchy":[
        "tgn:7293156",
        "tgn:1001695",
        "tgn:1000049",
        "tgn:1000002",
        "tgn:7029392"
    ],
    "tgn:id":7293156,
    "tgn:name":"El Chingue, Puntilla",
    "tgn:placetype":[
        "aat:300008777"
    ]
},
  "bbox": [],
  "geometry": {"coordinates":[-70.833333,-34.716667],"type":"Point"}
}