{
  "id": 7319236,
  "type": "Feature",
  "properties": {
    "tgn:hierarchy":[
        "tgn:7319236",
        "tgn:1001702",
        "tgn:1000049",
        "tgn:1000002",
        "tgn:7029392"
    ],
    "tgn:id":7319236,
    "tgn:name":"Andrade Taraba, Paso",
    "tgn:placetype":[
        "aat:300387026"
    ]
},
  "bbox": [],
  "geometry": {"coordinates":[-71.733333,-54.266667],"type":"Point"}
}