{
  "id": 2217003,
  "type": "Feature",
  "properties": {
    "tgn:hierarchy":[
        "tgn:2217003",
        "tgn:1002176",
        "tgn:1000001",
        "tgn:7012149",
        "tgn:7007828",
        "tgn:7029392"
    ],
    "tgn:id":2217003,
    "tgn:name":"Camp Meadows",
    "tgn:placetype":[
        "aat:300008905"
    ]
},
  "bbox": [],
  "geometry": {"coordinates":[-73.05,42.8333],"type":"Point"}
}