{
  "id": 1057782,
  "type": "Feature",
  "properties": {
    "tgn:hierarchy":[
        "tgn:1057782",
        "tgn:1000004",
        "tgn:7011539",
        "tgn:7018214",
        "tgn:7002435",
        "tgn:7029392"
    ],
    "tgn:id":1057782,
    "tgn:name":"Novosysoyevka",
    "tgn:placetype":[
        "aat:300008347"
    ]
},
  "bbox": [],
  "geometry": {"coordinates":[133.3667,44.2333],"type":"Point"}
}