{
  "id": 7411412,
  "type": "Feature",
  "properties": {
    "tgn:hierarchy":[
        "tgn:7411412",
        "tgn:1000001",
        "tgn:7005596",
        "tgn:7005560",
        "tgn:7029392"
    ],
    "tgn:id":7411412,
    "tgn:name:es":"San Juan El Alto Segunda Secci\u00f3n",
    "tgn:placetype":[
        "aat:300008347"
    ]
},
  "bbox": [],
  "geometry": {"coordinates":[-92.716667,17.816667],"type":"Point"}
}