{
  "id": 2070581,
  "type": "Feature",
  "properties": {
    "tgn:hierarchy":[
        "tgn:2070581",
        "tgn:1000001",
        "tgn:7012149",
        "tgn:1002758",
        "tgn:7007568",
        "tgn:7029392"
    ],
    "tgn:id":2070581,
    "tgn:name":"Minetto",
    "tgn:placetype":[
        "aat:300008347"
    ]
},
  "bbox": [],
  "geometry": {"coordinates":[-76.4667,43.3833],"type":"Point"}
}