{
  "id": 2275356,
  "type": "Feature",
  "properties": {
    "tgn:hierarchy":[
        "tgn:2275356",
        "tgn:1000001",
        "tgn:7012149",
        "tgn:1002995",
        "tgn:7007710",
        "tgn:7029392"
    ],
    "tgn:id":2275356,
    "tgn:name":"Daniels Run",
    "tgn:placetype":[
        "aat:300008699"
    ]
},
  "bbox": [],
  "geometry": {"coordinates":[-80.1333,40.1167],"type":"Point"}
}