{
  "id": 1069742,
  "type": "Feature",
  "properties": {
    "tgn:hierarchy":[
        "tgn:1069742",
        "tgn:1000004",
        "tgn:7002077",
        "tgn:1000111",
        "tgn:7029392"
    ],
    "tgn:id":1069742,
    "tgn:name":"Liangdawa",
    "tgn:placetype":[
        "aat:300008347"
    ]
},
  "bbox": [],
  "geometry": {"coordinates":[117.6167,40.65],"type":"Point"}
}