{
  "id": 2692590,
  "type": "Feature",
  "properties": {
    "tgn:hierarchy":[
        "tgn:2692590",
        "tgn:1000001",
        "tgn:7012149",
        "tgn:2002126",
        "tgn:7007827",
        "tgn:7029392"
    ],
    "tgn:id":2692590,
    "tgn:name":"Steamboat Tunnel",
    "tgn:placetype":[
        "aat:300000390"
    ]
},
  "bbox": [],
  "geometry": {"coordinates":[-111.5667,40.5667],"type":"Point"}
}