{
  "id": 2653855,
  "type": "Feature",
  "properties": {
    "tgn:hierarchy":[
        "tgn:2653855",
        "tgn:1000001",
        "tgn:2000952",
        "tgn:7012149",
        "tgn:7007520",
        "tgn:7029392"
    ],
    "tgn:id":2653855,
    "tgn:name":"Seymour Bay",
    "tgn:placetype":[
        "aat:300132316"
    ]
},
  "bbox": [],
  "geometry": {"coordinates":[-83.9167,45.9667],"type":"Point"}
}