{
  "id": 7557616,
  "type": "Feature",
  "properties": {
    "tgn:hierarchy":[
        "tgn:7557616",
        "tgn:1000004",
        "tgn:1001832",
        "tgn:7000198",
        "tgn:7029392"
    ],
    "tgn:id":7557616,
    "tgn:name:en":"Rangapah\u0101r",
    "tgn:placetype":[
        "aat:300008347"
    ]
},
  "bbox": [],
  "geometry": {"coordinates":[93.705163,25.855709],"type":"Point"}
}