{
  "id": 2445476,
  "type": "Feature",
  "properties": {
    "tgn:hierarchy":[
        "tgn:2445476",
        "tgn:1000001",
        "tgn:7012149",
        "tgn:7014612",
        "tgn:7007568",
        "tgn:7029392"
    ],
    "tgn:id":2445476,
    "tgn:name":"Lents Cove",
    "tgn:placetype":[
        "aat:300132316"
    ]
},
  "bbox": [],
  "geometry": {"coordinates":[-73.9333,41.2667],"type":"Point"}
}