{
  "id": 2386060,
  "type": "Feature",
  "properties": {
    "tgn:hierarchy":[
        "tgn:2386060",
        "tgn:1000001",
        "tgn:7012149",
        "tgn:2002273",
        "tgn:7013961",
        "tgn:7029392"
    ],
    "tgn:id":2386060,
    "tgn:name":"Henry Hollow",
    "tgn:placetype":[
        "aat:300008761"
    ]
},
  "bbox": [],
  "geometry": {"coordinates":[-81.8667,37.7667],"type":"Point"}
}