{
  "id": 2231934,
  "type": "Feature",
  "properties": {
    "tgn:hierarchy":[
        "tgn:2231934",
        "tgn:1000001",
        "tgn:7012149",
        "tgn:2000426",
        "tgn:7007248",
        "tgn:7029392"
    ],
    "tgn:id":2231934,
    "tgn:name":"Chamblis Lake",
    "tgn:placetype":[
        "aat:300006191"
    ]
},
  "bbox": [],
  "geometry": {"coordinates":[-84.4167,31.7833],"type":"Point"}
}