{
  "id": 1004789,
  "type": "Feature",
  "properties": {
    "tgn:hierarchy":[
        "tgn:1004789",
        "tgn:1000004",
        "tgn:7000201",
        "tgn:7000198",
        "tgn:7029392"
    ],
    "tgn:id":1004789,
    "tgn:name:en":"K\u0101lk\u0101ji Devi",
    "tgn:placetype":[
        "aat:300008347",
        "aat:300000745"
    ]
},
  "bbox": [],
  "geometry": {"coordinates":[77.2667,28.55],"type":"Point"}
}