{
  "id": 1056352,
  "type": "Feature",
  "properties": {
    "tgn:hierarchy":[
        "tgn:1056352",
        "tgn:1000004",
        "tgn:7002435",
        "tgn:7011524",
        "tgn:7029392"
    ],
    "tgn:id":1056352,
    "tgn:name":"Lebedino",
    "tgn:placetype":[
        "aat:300008347"
    ]
},
  "bbox": [],
  "geometry": {"coordinates":[49.8333,55.2333],"type":"Point"}
}