{
  "id": 7548594,
  "type": "Feature",
  "properties": {
    "tgn:hierarchy":[
        "tgn:7548594",
        "tgn:1000004",
        "tgn:1001832",
        "tgn:7000198",
        "tgn:7029392"
    ],
    "tgn:id":7548594,
    "tgn:name:en":"Buradiya Nad\u012b",
    "tgn:placetype":[
        "aat:300008699"
    ]
},
  "bbox": [],
  "geometry": {"coordinates":[91.212166,26.409029],"type":"Point"}
}