<<<<<<< HEAD
{
  "id": 7050192,
  "type": "Feature",
  "properties": {
    "tgn:hierarchy":[
        "tgn:7050192",
        "tgn:7003168",
        "tgn:1000003",
        "tgn:7009760",
        "tgn:1000080",
        "tgn:7029392"
    ],
    "tgn:id":7050192,
    "tgn:name":"Pievina",
    "tgn:placetype":[
        "aat:300008347"
    ]
},
  "bbox": [],
  "geometry": {"coordinates":[11.516667,43.25],"type":"Point"}
}
=======
{"geometry":{"type":"Point","coordinates":[11.516667,43.250000]},"type":"Feature","properties":{"hierarchy":["tgn:7050192","tgn:7003168","tgn:1000003","tgn:7009760","tgn:1000080","tgn:7029392"],"placetype":["aat:300008347"],"id":7050192,"name:xx":"Pievina"}}
>>>>>>> 03f74aca74312dbeaf24d7e61306dd6a786dc3d0
