{
  "id": 1101413,
  "type": "Feature",
  "properties": {
    "tgn:hierarchy":[
        "tgn:1101413",
        "tgn:7001242",
        "tgn:1000149",
        "tgn:1000867",
        "tgn:7029392"
    ],
    "tgn:id":1101413,
    "tgn:name":"Bikuar, Parque Nacional do",
    "tgn:placetype":[
        "aat:300008189"
    ]
},
  "bbox": [],
  "geometry": {"coordinates":[14.8333,-15.3333],"type":"Point"}
}