{
  "id": 2778839,
  "type": "Feature",
  "properties": {
    "tgn:hierarchy":[
        "tgn:2778839",
        "tgn:2000001",
        "tgn:7002659",
        "tgn:1000001",
        "tgn:7012149",
        "tgn:7029392"
    ],
    "tgn:id":2778839,
    "tgn:name":"Wolf Creek",
    "tgn:placetype":[
        "aat:300008706"
    ]
},
  "bbox": [],
  "geometry": {"coordinates":[-87.75,31.0833],"type":"Point"}
}