{
  "id": 2138355,
  "type": "Feature",
  "properties": {
    "tgn:hierarchy":[
        "tgn:2138355",
        "tgn:7006450",
        "tgn:2000069",
        "tgn:1000001",
        "tgn:7012149",
        "tgn:7029392"
    ],
    "tgn:id":2138355,
    "tgn:name":"Arwirnuk Rock",
    "tgn:placetype":[
        "aat:300008791"
    ]
},
  "bbox": [],
  "geometry": {"coordinates":[-166.4833,60.3833],"type":"Point"}
}