{
  "id": 7399660,
  "type": "Feature",
  "properties": {
    "tgn:hierarchy":[
        "tgn:7399660",
        "tgn:1000001",
        "tgn:7005593",
        "tgn:7005560",
        "tgn:7029392"
    ],
    "tgn:id":7399660,
    "tgn:name":"Escalerillas, Arroyo",
    "tgn:placetype":[
        "aat:300008699"
    ]
},
  "bbox": [],
  "geometry": {"coordinates":[-100.216667,20.883333],"type":"Point"}
}