{
  "id": 2288552,
  "type": "Feature",
  "properties": {
    "tgn:hierarchy":[
        "tgn:2288552",
        "tgn:1000001",
        "tgn:7012149",
        "tgn:2000494",
        "tgn:7007250",
        "tgn:7029392"
    ],
    "tgn:id":2288552,
    "tgn:name":"Dismal Lake",
    "tgn:placetype":[
        "aat:300008680"
    ]
},
  "bbox": [],
  "geometry": {"coordinates":[-115.8167,44.8167],"type":"Point"}
}