{
  "id": 7066392,
  "type": "Feature",
  "properties": {
    "tgn:hierarchy":[
        "tgn:7066392",
        "tgn:7003692",
        "tgn:1000003",
        "tgn:7000084",
        "tgn:7029392"
    ],
    "tgn:id":7066392,
    "tgn:name":"Uiffingen",
    "tgn:placetype":[
        "aat:300008347"
    ]
},
  "bbox": [],
  "geometry": {"coordinates":[9.593889,49.502222],"type":"Point"}
}