{
  "id": 2130006,
  "type": "Feature",
  "properties": {
    "tgn:hierarchy":[
        "tgn:2130006",
        "tgn:1000001",
        "tgn:1002275",
        "tgn:7012149",
        "tgn:7007920",
        "tgn:7029392"
    ],
    "tgn:id":2130006,
    "tgn:name":"Allen Creek",
    "tgn:placetype":[
        "aat:300008706"
    ]
},
  "bbox": [],
  "geometry": {"coordinates":[-122.6667,45.8167],"type":"Point"}
}