{
  "id": 7451026,
  "type": "Feature",
  "properties": {
    "tgn:hierarchy":[
        "tgn:7451026",
        "tgn:7002444",
        "tgn:1000003",
        "tgn:7008082",
        "tgn:7008591",
        "tgn:7029392"
    ],
    "tgn:id":7451026,
    "tgn:name:en":"Garry, River",
    "tgn:placetype":[
        "aat:300008699"
    ]
},
  "bbox": [],
  "geometry": {"coordinates":[-4.783333,57.066667],"type":"Point"}
}