{
  "id": 7150767,
  "type": "Feature",
  "properties": {
    "tgn:hierarchy":[
        "tgn:7150767",
        "tgn:1000003",
        "tgn:7003687",
        "tgn:7000084",
        "tgn:7029392"
    ],
    "tgn:id":7150767,
    "tgn:name":"Krimpe",
    "tgn:placetype":[
        "aat:300008347"
    ]
},
  "bbox": [],
  "geometry": {"coordinates":[11.75,51.533333],"type":"Point"}
}