{
  "id": 2607476,
  "type": "Feature",
  "properties": {
    "tgn:hierarchy":[
        "tgn:2607476",
        "tgn:1000001",
        "tgn:7012149",
        "tgn:2002379",
        "tgn:7007923",
        "tgn:7029392"
    ],
    "tgn:id":2607476,
    "tgn:name":"Rankin Ditch",
    "tgn:placetype":[
        "aat:300006075"
    ]
},
  "bbox": [],
  "geometry": {"coordinates":[-108.65,44.3333],"type":"Point"}
}