{
  "id": 2652888,
  "type": "Feature",
  "properties": {
    "tgn:hierarchy":[
        "tgn:2652888",
        "tgn:1002165",
        "tgn:1000001",
        "tgn:7012149",
        "tgn:7007517",
        "tgn:7029392"
    ],
    "tgn:id":2652888,
    "tgn:name":"Sesuit Creek Marshes",
    "tgn:placetype":[
        "aat:300008905"
    ]
},
  "bbox": [],
  "geometry": {"coordinates":[-70.15,41.7333],"type":"Point"}
}