{
  "id": 2629108,
  "type": "Feature",
  "properties": {
    "tgn:hierarchy":[
        "tgn:2629108",
        "tgn:1000001",
        "tgn:7012149",
        "tgn:2001029",
        "tgn:7007521",
        "tgn:7029392"
    ],
    "tgn:id":2629108,
    "tgn:name":"Rose Lake",
    "tgn:placetype":[
        "aat:300008680"
    ]
},
  "bbox": [],
  "geometry": {"coordinates":[-93.3833,47.4333],"type":"Point"}
}