{
  "id": 4012237,
  "type": "Feature",
  "properties": {
    "tgn:hierarchy":[
        "tgn:4012237",
        "tgn:7002445",
        "tgn:7018928",
        "tgn:1000003",
        "tgn:7008136",
        "tgn:7008591",
        "tgn:7029392"
    ],
    "tgn:id":4012237,
    "tgn:name:en":"Whitton",
    "tgn:placetype":[
        "aat:300000745"
    ]
},
  "bbox": [],
  "geometry": {"coordinates":[-0.316667,51.433333],"type":"Point"}
}