{
  "id": 7469427,
  "type": "Feature",
  "properties": {
    "tgn:hierarchy":[
        "tgn:7469427",
        "tgn:7468018",
        "tgn:1000004",
        "tgn:1000141",
        "tgn:7029392"
    ],
    "tgn:id":7469427,
    "tgn:name":"Xiaoping",
    "tgn:placetype":[
        "aat:300008347"
    ]
},
  "bbox": [],
  "geometry": {"coordinates":[120.522222,23.504167],"type":"Point"}
}