{
  "id": 7588555,
  "type": "Feature",
  "properties": {
    "tgn:hierarchy":[
        "tgn:7588555",
        "tgn:1000004",
        "tgn:7000198",
        "tgn:7000799",
        "tgn:7029392"
    ],
    "tgn:id":7588555,
    "tgn:name:en":"Chandapura",
    "tgn:placetype":[
        "aat:300008347"
    ]
},
  "bbox": [],
  "geometry": {"coordinates":[74.672259,34.034124],"type":"Point"}
}