{
  "id": 7593540,
  "type": "Feature",
  "properties": {
    "tgn:hierarchy":[
        "tgn:7593540",
        "tgn:7593368",
        "tgn:1000001",
        "tgn:7005388",
        "tgn:7029392"
    ],
    "tgn:id":7593540,
    "tgn:name":"La Victoria",
    "tgn:placetype":[
        "aat:300008347"
    ]
},
  "bbox": [],
  "geometry": {"coordinates":[-69.842,18.592],"type":"Point"}
}