{
  "id": 7418721,
  "type": "Feature",
  "properties": {
    "tgn:hierarchy":[
        "tgn:7418721",
        "tgn:1000001",
        "tgn:7005589",
        "tgn:7005560",
        "tgn:7029392"
    ],
    "tgn:id":7418721,
    "tgn:name:es":"El Canelito",
    "tgn:placetype":[
        "aat:300008347"
    ]
},
  "bbox": [],
  "geometry": {"coordinates":[-100.718611,24.802778],"type":"Point"}
}