{
  "id": 1138210,
  "type": "Feature",
  "properties": {
    "tgn:hierarchy":[
        "tgn:1138210",
        "tgn:1000004",
        "tgn:7011608",
        "tgn:7018214",
        "tgn:7002435",
        "tgn:7029392"
    ],
    "tgn:id":1138210,
    "tgn:name":"Pesochnoye",
    "tgn:placetype":[
        "aat:300008347"
    ]
},
  "bbox": [],
  "geometry": {"coordinates":[39.1667,58.0167],"type":"Point"}
}