{
  "id": 7434393,
  "type": "Feature",
  "properties": {
    "tgn:hierarchy":[
        "tgn:7434393",
        "tgn:7005575",
        "tgn:1000001",
        "tgn:7005560",
        "tgn:7029392"
    ],
    "tgn:id":7434393,
    "tgn:name":"Tres Estrellas",
    "tgn:placetype":[
        "aat:300000745"
    ]
},
  "bbox": [],
  "geometry": {"coordinates":[-99.116667,19.466667],"type":"Point"}
}