{
  "id": 2256243,
  "type": "Feature",
  "properties": {
    "tgn:hierarchy":[
        "tgn:2256243",
        "tgn:1000001",
        "tgn:7012149",
        "tgn:1002898",
        "tgn:7007826",
        "tgn:7029392"
    ],
    "tgn:id":2256243,
    "tgn:name":"Copperas Creek",
    "tgn:placetype":[
        "aat:300008706"
    ]
},
  "bbox": [],
  "geometry": {"coordinates":[-95.4167,32.2167],"type":"Point"}
}