{
  "id": 7589522,
  "type": "Feature",
  "properties": {
    "tgn:hierarchy":[
        "tgn:7589522",
        "tgn:1000004",
        "tgn:7000198",
        "tgn:7000799",
        "tgn:7029392"
    ],
    "tgn:id":7589522,
    "tgn:name:en":"Dhammi",
    "tgn:placetype":[
        "aat:300008347"
    ]
},
  "bbox": [],
  "geometry": {"coordinates":[74.907678,32.825532],"type":"Point"}
}