<<<<<<< HEAD
{
  "id": 2408124,
  "type": "Feature",
  "properties": {
    "tgn:hierarchy":[
        "tgn:2408124",
        "tgn:1000001",
        "tgn:7012149",
        "tgn:2001503",
        "tgn:7007709",
        "tgn:7029392"
    ],
    "tgn:id":2408124,
    "tgn:name":"Hurricane Mountain",
    "tgn:placetype":[
        "aat:300008798"
    ]
},
  "bbox": [],
  "geometry": {"coordinates":[-82.9667,35.7],"type":"Point"}
}
=======
{"geometry":{"type":"Point","coordinates":[-82.966700,35.700000]},"type":"Feature","properties":{"hierarchy":["tgn:2408124","tgn:1000001","tgn:7012149","tgn:2001503","tgn:7007709","tgn:7029392"],"placetype":["aat:300008798"],"id":2408124,"name:xx":"Hurricane Mountain"}}
>>>>>>> 03f74aca74312dbeaf24d7e61306dd6a786dc3d0
