{
  "id": 2312755,
  "type": "Feature",
  "properties": {
    "tgn:hierarchy":[
        "tgn:2312755",
        "tgn:1000001",
        "tgn:7012149",
        "tgn:2002066",
        "tgn:7007826",
        "tgn:7029392"
    ],
    "tgn:id":2312755,
    "tgn:name":"El Lobanillo Creek",
    "tgn:placetype":[
        "aat:300008706"
    ]
},
  "bbox": [],
  "geometry": {"coordinates":[-93.9667,31.5333],"type":"Point"}
}