{
  "id": 7516003,
  "type": "Feature",
  "properties": {
    "tgn:hierarchy":[
        "tgn:7516003",
        "tgn:1008380",
        "tgn:1000226",
        "tgn:7018426",
        "tgn:1000006",
        "tgn:7029392"
    ],
    "tgn:id":7516003,
    "tgn:name:en":"Okiwiriki",
    "tgn:placetype":[
        "aat:300008795"
    ]
},
  "bbox": [],
  "geometry": {"coordinates":[175.15,-38.533333],"type":"Point"}
}