{
  "id": 7585866,
  "type": "Feature",
  "properties": {
    "tgn:hierarchy":[
        "tgn:7585866",
        "tgn:1000004",
        "tgn:7000198",
        "tgn:7000799",
        "tgn:7029392"
    ],
    "tgn:id":7585866,
    "tgn:name:en":"Yidipur",
    "tgn:placetype":[
        "aat:300008347"
    ]
},
  "bbox": [],
  "geometry": {"coordinates":[74.425288,34.36596],"type":"Point"}
}