{
  "id": 7407012,
  "type": "Feature",
  "properties": {
    "tgn:hierarchy":[
        "tgn:7407012",
        "tgn:1000001",
        "tgn:1001906",
        "tgn:7005560",
        "tgn:7029392"
    ],
    "tgn:id":7407012,
    "tgn:name":"Las Patillas",
    "tgn:placetype":[
        "aat:300008347"
    ]
},
  "bbox": [],
  "geometry": {"coordinates":[-105.116667,22.633333],"type":"Point"}
}