{
  "id": 2180575,
  "type": "Feature",
  "properties": {
    "tgn:hierarchy":[
        "tgn:2180575",
        "tgn:1000001",
        "tgn:2000591",
        "tgn:7012149",
        "tgn:7007253",
        "tgn:7029392"
    ],
    "tgn:id":2180575,
    "tgn:name":"Bloody Run",
    "tgn:placetype":[
        "aat:300008699"
    ]
},
  "bbox": [],
  "geometry": {"coordinates":[-90.75,42.6167],"type":"Point"}
}