{
  "id": 2580699,
  "type": "Feature",
  "properties": {
    "tgn:hierarchy":[
        "tgn:2580699",
        "tgn:1000001",
        "tgn:7012149",
        "tgn:2000180",
        "tgn:7007157",
        "tgn:7029392"
    ],
    "tgn:id":2580699,
    "tgn:name":"Pigeon Roost Spring",
    "tgn:placetype":[
        "aat:300008697"
    ]
},
  "bbox": [],
  "geometry": {"coordinates":[-123.9667,41.6667],"type":"Point"}
}