{
  "id": 2748327,
  "type": "Feature",
  "properties": {
    "tgn:hierarchy":[
        "tgn:2748327",
        "tgn:1000001",
        "tgn:7012149",
        "tgn:2001109",
        "tgn:7007522",
        "tgn:7029392"
    ],
    "tgn:id":2748327,
    "tgn:name":"Walker Creek",
    "tgn:placetype":[
        "aat:300008706"
    ]
},
  "bbox": [],
  "geometry": {"coordinates":[-89.0333,30.55],"type":"Point"}
}