{
  "id": 2623318,
  "type": "Feature",
  "properties": {
    "tgn:hierarchy":[
        "tgn:2623318",
        "tgn:1000001",
        "tgn:7006451",
        "tgn:2000091",
        "tgn:7012149",
        "tgn:7029392"
    ],
    "tgn:id":2623318,
    "tgn:name":"Rock Canyon",
    "tgn:placetype":[
        "aat:300008761"
    ]
},
  "bbox": [],
  "geometry": {"coordinates":[-109.2667,31.8833],"type":"Point"}
}