{
  "id": 7381402,
  "type": "Feature",
  "properties": {
    "tgn:hierarchy":[
        "tgn:7381402",
        "tgn:1000001",
        "tgn:7005589",
        "tgn:7005560",
        "tgn:7029392"
    ],
    "tgn:id":7381402,
    "tgn:name":"Los Morton",
    "tgn:placetype":[
        "aat:300008347"
    ]
},
  "bbox": [],
  "geometry": {"coordinates":[-99.816667,26.883333],"type":"Point"}
}