{
  "id": 2268819,
  "type": "Feature",
  "properties": {
    "tgn:hierarchy":[
        "tgn:2268819",
        "tgn:1000001",
        "tgn:7012149",
        "tgn:2000232",
        "tgn:7007158",
        "tgn:7029392"
    ],
    "tgn:id":2268819,
    "tgn:name":"Cross Mountain",
    "tgn:placetype":[
        "aat:300008798"
    ]
},
  "bbox": [],
  "geometry": {"coordinates":[-108.3667,40.5167],"type":"Point"}
}