<<<<<<< HEAD
{
  "id": 7355160,
  "type": "Feature",
  "properties": {
    "tgn:hierarchy":[
        "tgn:7355160",
        "tgn:1000001",
        "tgn:7005600",
        "tgn:7005560",
        "tgn:7029392"
    ],
    "tgn:id":7355160,
    "tgn:name":"Chenk\u00fa",
    "tgn:placetype":[
        "aat:300008347"
    ]
},
  "bbox": [],
  "geometry": {"coordinates":[-88.833333,21.133333],"type":"Point"}
}
=======
{"geometry":{"type":"Point","coordinates":[-88.833333,21.133333]},"type":"Feature","properties":{"hierarchy":["tgn:7355160","tgn:1000001","tgn:7005600","tgn:7005560","tgn:7029392"],"placetype":["aat:300008347"],"id":7355160,"name:xx":"Chenk\u00fa"}}
>>>>>>> 03f74aca74312dbeaf24d7e61306dd6a786dc3d0
