{
  "id": 7086727,
  "type": "Feature",
  "properties": {
    "tgn:hierarchy":[
        "tgn:7086727",
        "tgn:7003692",
        "tgn:1000003",
        "tgn:7000084",
        "tgn:7029392"
    ],
    "tgn:id":7086727,
    "tgn:name":"Warrenbergle",
    "tgn:placetype":[
        "aat:300008777"
    ]
},
  "bbox": [],
  "geometry": {"coordinates":[8.833333,48.35],"type":"Point"}
}