{
  "id": 7579834,
  "type": "Feature",
  "properties": {
    "tgn:hierarchy":[
        "tgn:7579834",
        "tgn:1000004",
        "tgn:7000198",
        "tgn:7000799",
        "tgn:7029392"
    ],
    "tgn:id":7579834,
    "tgn:name:en":"Sh\u012blung La",
    "tgn:placetype":[
        "aat:300259572"
    ]
},
  "bbox": [],
  "geometry": {"coordinates":[78.55501,33.981143],"type":"Point"}
}