{
  "id": 7331968,
  "type": "Feature",
  "properties": {
    "tgn:hierarchy":[
        "tgn:7331968",
        "tgn:7002805",
        "tgn:7002758",
        "tgn:1000003",
        "tgn:1000095",
        "tgn:7029392"
    ],
    "tgn:id":7331968,
    "tgn:name":"La Parata",
    "tgn:placetype":[
        "aat:300008347"
    ]
},
  "bbox": [],
  "geometry": {"coordinates":[-1.983333,37.416667],"type":"Point"}
}