<<<<<<< HEAD
{
  "id": 2767350,
  "type": "Feature",
  "properties": {
    "tgn:hierarchy":[
        "tgn:2767350",
        "tgn:1000001",
        "tgn:7012149",
        "tgn:2001447",
        "tgn:7007566",
        "tgn:7029392"
    ],
    "tgn:id":2767350,
    "tgn:name":"White Sands Lakes",
    "tgn:placetype":[
        "aat:300008680"
    ]
},
  "bbox": [],
  "geometry": {"coordinates":[-106.1667,33.0167],"type":"Point"}
}
=======
{"geometry":{"type":"Point","coordinates":[-106.166700,33.016700]},"type":"Feature","properties":{"hierarchy":["tgn:2767350","tgn:1000001","tgn:7012149","tgn:2001447","tgn:7007566","tgn:7029392"],"placetype":["aat:300008680"],"id":2767350,"name:xx":"White Sands Lakes"}}
>>>>>>> 03f74aca74312dbeaf24d7e61306dd6a786dc3d0
