{
  "id": 2595735,
  "type": "Feature",
  "properties": {
    "tgn:hierarchy":[
        "tgn:2595735",
        "tgn:1000001",
        "tgn:7012149",
        "tgn:1002554",
        "tgn:7007920",
        "tgn:7029392"
    ],
    "tgn:id":2595735,
    "tgn:name":"Pothole Spring",
    "tgn:placetype":[
        "aat:300008697"
    ]
},
  "bbox": [],
  "geometry": {"coordinates":[-120.0167,45.95],"type":"Point"}
}