{
  "id": 2461266,
  "type": "Feature",
  "properties": {
    "tgn:hierarchy":[
        "tgn:2461266",
        "tgn:1000001",
        "tgn:7012149",
        "tgn:2001709",
        "tgn:7007708",
        "tgn:7029392"
    ],
    "tgn:id":2461266,
    "tgn:name":"Little Steamboat Point",
    "tgn:placetype":[
        "aat:300008798"
    ]
},
  "bbox": [],
  "geometry": {"coordinates":[-119.6167,42.8333],"type":"Point"}
}