{
  "id": 2598423,
  "type": "Feature",
  "properties": {
    "tgn:hierarchy":[
        "tgn:2598423",
        "tgn:1000001",
        "tgn:7012149",
        "tgn:7007827",
        "tgn:7029392"
    ],
    "tgn:id":2598423,
    "tgn:name":"Price Canyon",
    "tgn:placetype":[
        "aat:300008761"
    ]
},
  "bbox": [],
  "geometry": {"coordinates":[-110.9333,39.8167],"type":"Point"}
}