{
  "id": 7500588,
  "type": "Feature",
  "properties": {
    "tgn:hierarchy":[
        "tgn:7500588",
        "tgn:1000004",
        "tgn:7492971",
        "tgn:1000141",
        "tgn:7029392"
    ],
    "tgn:id":7500588,
    "tgn:name":"Xinji",
    "tgn:placetype":[
        "aat:300008347"
    ]
},
  "bbox": [],
  "geometry": {"coordinates":[120.469722,22.812778],"type":"Point"}
}