{
  "id": 7197161,
  "type": "Feature",
  "properties": {
    "tgn:hierarchy":[
        "tgn:7197161",
        "tgn:7003692",
        "tgn:1000003",
        "tgn:7000084",
        "tgn:7029392"
    ],
    "tgn:id":7197161,
    "tgn:name":"Dietenberg",
    "tgn:placetype":[
        "aat:300008347"
    ]
},
  "bbox": [],
  "geometry": {"coordinates":[9.983333,47.983333],"type":"Point"}
}