{
  "id": 2347250,
  "type": "Feature",
  "properties": {
    "tgn:hierarchy":[
        "tgn:2347250",
        "tgn:7002659",
        "tgn:1000001",
        "tgn:7012149",
        "tgn:2000060",
        "tgn:7029392"
    ],
    "tgn:id":2347250,
    "tgn:name":"Gents Mountain",
    "tgn:placetype":[
        "aat:300008798"
    ]
},
  "bbox": [],
  "geometry": {"coordinates":[-86.05,33.4833],"type":"Point"}
}