{
  "id": 2477725,
  "type": "Feature",
  "properties": {
    "tgn:hierarchy":[
        "tgn:2477725",
        "tgn:1000001",
        "tgn:2001644",
        "tgn:7012149",
        "tgn:7007707",
        "tgn:7029392"
    ],
    "tgn:id":2477725,
    "tgn:name":"Mabry Lake",
    "tgn:placetype":[
        "aat:300006191"
    ]
},
  "bbox": [],
  "geometry": {"coordinates":[-99.25,35.8167],"type":"Point"}
}