{
  "id": 7490164,
  "type": "Feature",
  "properties": {
    "tgn:hierarchy":[
        "tgn:7490164",
        "tgn:1000004",
        "tgn:7490934",
        "tgn:1000141",
        "tgn:7029392"
    ],
    "tgn:id":7490164,
    "tgn:name":"Budaizuiliao",
    "tgn:placetype":[
        "aat:300008347"
    ]
},
  "bbox": [],
  "geometry": {"coordinates":[120.208056,23.065833],"type":"Point"}
}