{
  "id": 7548392,
  "type": "Feature",
  "properties": {
    "tgn:hierarchy":[
        "tgn:7548392",
        "tgn:1000004",
        "tgn:7000198",
        "tgn:1001895",
        "tgn:7029392"
    ],
    "tgn:id":7548392,
    "tgn:name:en":"Chinchp\u0101da",
    "tgn:placetype":[
        "aat:300007783"
    ]
},
  "bbox": [],
  "geometry": {"coordinates":[73.916667,21.183333],"type":"Point"}
}