{
  "id": 2298524,
  "type": "Feature",
  "properties": {
    "tgn:hierarchy":[
        "tgn:2298524",
        "tgn:1000001",
        "tgn:7012149",
        "tgn:2002264",
        "tgn:7013961",
        "tgn:7029392"
    ],
    "tgn:id":2298524,
    "tgn:name":"Dry Run",
    "tgn:placetype":[
        "aat:300008699"
    ]
},
  "bbox": [],
  "geometry": {"coordinates":[-80.2333,37.8833],"type":"Point"}
}