<<<<<<< HEAD
{
  "id": 7371418,
  "type": "Feature",
  "properties": {
    "tgn:hierarchy":[
        "tgn:7371418",
        "tgn:7005586",
        "tgn:1000001",
        "tgn:7005560",
        "tgn:7029392"
    ],
    "tgn:id":7371418,
    "tgn:name":"Bordo Grande",
    "tgn:placetype":[
        "aat:300006191"
    ]
},
  "bbox": [],
  "geometry": {"coordinates":[-102.85,20.466667],"type":"Point"}
}
=======
{"geometry":{"type":"Point","coordinates":[-102.850000,20.466667]},"type":"Feature","properties":{"hierarchy":["tgn:7371418","tgn:7005586","tgn:1000001","tgn:7005560","tgn:7029392"],"placetype":["aat:300006191"],"id":7371418,"name:xx":"Bordo Grande"}}
>>>>>>> 03f74aca74312dbeaf24d7e61306dd6a786dc3d0
