{
  "id": 2318408,
  "type": "Feature",
  "properties": {
    "tgn:hierarchy":[
        "tgn:2318408",
        "tgn:1000001",
        "tgn:7012149",
        "tgn:2000278",
        "tgn:7007240",
        "tgn:7029392"
    ],
    "tgn:id":2318408,
    "tgn:name":"Equaloxic Creek",
    "tgn:placetype":[
        "aat:300008706"
    ]
},
  "bbox": [],
  "geometry": {"coordinates":[-85.05,30.2333],"type":"Point"}
}