{
  "id": 2381761,
  "type": "Feature",
  "properties": {
    "tgn:hierarchy":[
        "tgn:2381761",
        "tgn:1000001",
        "tgn:7012149",
        "tgn:2002124",
        "tgn:7007827",
        "tgn:7029392"
    ],
    "tgn:id":2381761,
    "tgn:name":"Hayden",
    "tgn:placetype":[
        "aat:300008347"
    ]
},
  "bbox": [],
  "geometry": {"coordinates":[-109.9667,40.4167],"type":"Point"}
}