{
  "id": 2010597,
  "type": "Feature",
  "properties": {
    "tgn:hierarchy":[
        "tgn:2010597",
        "tgn:1000001",
        "tgn:7016499",
        "tgn:7012149",
        "tgn:7007157",
        "tgn:1002608",
        "tgn:7029392"
    ],
    "tgn:id":2010597,
    "tgn:name":"Dominguez",
    "tgn:placetype":[
        "aat:300000745"
    ]
},
  "bbox": [],
  "geometry": {"coordinates":[-118.2167,33.8333],"type":"Point"}
}