{
  "id": 7105699,
  "type": "Feature",
  "properties": {
    "tgn:hierarchy":[
        "tgn:7105699",
        "tgn:7003669",
        "tgn:1000003",
        "tgn:7000084",
        "tgn:7029392"
    ],
    "tgn:id":7105699,
    "tgn:name":"Schlichtenberger Forst",
    "tgn:placetype":[
        "aat:300008863"
    ]
},
  "bbox": [],
  "geometry": {"coordinates":[13.633333,48.85],"type":"Point"}
}