{
  "id": 1095956,
  "type": "Feature",
  "properties": {
    "tgn:hierarchy":[
        "tgn:1095956",
        "tgn:7001242",
        "tgn:1001544",
        "tgn:1000209",
        "tgn:7029392"
    ],
    "tgn:id":1095956,
    "tgn:name":"Livingstone",
    "tgn:placetype":[
        "aat:300008347",
        "aat:300387219",
        "aat:300387223",
        "aat:300265612",
        "aat:300008375",
        "aat:300387270",
        "aat:300387291"
    ]
},
  "bbox": [],
  "geometry": {"coordinates":[25.8833,-17.8333],"type":"Point"}
}