{
  "id": 7228404,
  "type": "Feature",
  "properties": {
    "tgn:hierarchy":[
        "tgn:7228404",
        "tgn:7011170",
        "tgn:7002715",
        "tgn:1000003",
        "tgn:1000074",
        "tgn:7029392"
    ],
    "tgn:id":7228404,
    "tgn:name":"Kastanokh\u00f3rion",
    "tgn:placetype":[
        "aat:300008347"
    ]
},
  "bbox": [],
  "geometry": {"coordinates":[23.65,40.816667],"type":"Point"}
}