{
  "id": 7224265,
  "type": "Feature",
  "properties": {
    "tgn:hierarchy":[
        "tgn:7224265",
        "tgn:7002743",
        "tgn:7017076",
        "tgn:1000003",
        "tgn:1000074",
        "tgn:7029392"
    ],
    "tgn:id":7224265,
    "tgn:name":"Teri\u00e1khi",
    "tgn:placetype":[
        "aat:300008795"
    ]
},
  "bbox": [],
  "geometry": {"coordinates":[21.883333,38.066667],"type":"Point"}
}