<<<<<<< HEAD
{
  "id": 2765033,
  "type": "Feature",
  "properties": {
    "tgn:hierarchy":[
        "tgn:2765033",
        "tgn:1000001",
        "tgn:7012149",
        "tgn:7007157",
        "tgn:1002791",
        "tgn:7029392"
    ],
    "tgn:id":2765033,
    "tgn:name":"Whisky Hill",
    "tgn:placetype":[
        "aat:300008798"
    ]
},
  "bbox": [],
  "geometry": {"coordinates":[-120.5667,39.1833],"type":"Point"}
}
=======
{"geometry":{"type":"Point","coordinates":[-120.566700,39.183300]},"type":"Feature","properties":{"hierarchy":["tgn:2765033","tgn:1000001","tgn:7012149","tgn:7007157","tgn:1002791","tgn:7029392"],"placetype":["aat:300008798"],"id":2765033,"name:xx":"Whisky Hill"}}
>>>>>>> 03f74aca74312dbeaf24d7e61306dd6a786dc3d0
