{
  "id": 2765033,
  "type": "Feature",
  "properties": {
    "tgn:hierarchy":[
        "tgn:2765033",
        "tgn:1000001",
        "tgn:7012149",
        "tgn:7007157",
        "tgn:1002791",
        "tgn:7029392"
    ],
    "tgn:id":2765033,
    "tgn:name":"Whisky Hill",
    "tgn:placetype":[
        "aat:300008798"
    ]
},
  "bbox": [],
  "geometry": {"coordinates":[-120.5667,39.1833],"type":"Point"}
}