{
  "id": 1057671,
  "type": "Feature",
  "properties": {
    "tgn:hierarchy":[
        "tgn:1057671",
        "tgn:7012076",
        "tgn:1000003",
        "tgn:7006660",
        "tgn:7029392"
    ],
    "tgn:id":1057671,
    "tgn:name":"Novoignatjevka",
    "tgn:placetype":[
        "aat:300008347"
    ]
},
  "bbox": [],
  "geometry": {"coordinates":[37.6833,47.6333],"type":"Point"}
}