{
  "id": 1017146,
  "type": "Feature",
  "properties": {
    "tgn:hierarchy":[
        "tgn:1017146",
        "tgn:1000001",
        "tgn:7005591",
        "tgn:7005560",
        "tgn:7029392"
    ],
    "tgn:id":1017146,
    "tgn:name":"Chahuites",
    "tgn:placetype":[
        "aat:300008347"
    ]
},
  "bbox": [],
  "geometry": {"coordinates":[-94.183333,16.283333],"type":"Point"}
}