{
  "id": 2087700,
  "type": "Feature",
  "properties": {
    "tgn:hierarchy":[
        "tgn:2087700",
        "tgn:1000001",
        "tgn:7013387",
        "tgn:7012149",
        "tgn:7007710",
        "tgn:7029392"
    ],
    "tgn:id":2087700,
    "tgn:name":"Dauberville",
    "tgn:placetype":[
        "aat:300008347"
    ]
},
  "bbox": [],
  "geometry": {"coordinates":[-75.9667,40.45],"type":"Point"}
}