{
  "id": 2309522,
  "type": "Feature",
  "properties": {
    "tgn:hierarchy":[
        "tgn:2309522",
        "tgn:1000001",
        "tgn:2002109",
        "tgn:7012149",
        "tgn:7007827",
        "tgn:7029392"
    ],
    "tgn:id":2309522,
    "tgn:name":"East Valley",
    "tgn:placetype":[
        "aat:300008761"
    ]
},
  "bbox": [],
  "geometry": {"coordinates":[-112.0333,37.6667],"type":"Point"}
}