{
  "id": 2079933,
  "type": "Feature",
  "properties": {
    "tgn:hierarchy":[
        "tgn:2079933",
        "tgn:1000001",
        "tgn:7012149",
        "tgn:1002784",
        "tgn:7007706",
        "tgn:7029392"
    ],
    "tgn:id":2079933,
    "tgn:name":"Hayesville",
    "tgn:placetype":[
        "aat:300387016"
    ]
},
  "bbox": [],
  "geometry": {"coordinates":[-82.9167,39.5333],"type":"Point"}
}