{
  "id": 7315199,
  "type": "Feature",
  "properties": {
    "tgn:hierarchy":[
        "tgn:7315199",
        "tgn:1001708",
        "tgn:1000049",
        "tgn:1000002",
        "tgn:7029392"
    ],
    "tgn:id":7315199,
    "tgn:name":"Colegio de Bucalemu",
    "tgn:placetype":[
        "aat:300008347"
    ]
},
  "bbox": [],
  "geometry": {"coordinates":[-71.733333,-33.833333],"type":"Point"}
}