{
  "id": 7007917,
  "type": "Feature",
  "properties": {
    "tgn:hierarchy":[
        "tgn:7007917",
        "tgn:7002810",
        "tgn:7001158",
        "tgn:1000003",
        "tgn:1000095",
        "tgn:7029392"
    ],
    "tgn:id":7007917,
    "tgn:name":"Lerma",
    "tgn:placetype":[
        "aat:300008347"
    ]
},
  "bbox": [],
  "geometry": {"coordinates":[-3.75,42.033333],"type":"Point"}
}