<<<<<<< HEAD
{
  "id": 7020021,
  "type": "Feature",
  "properties": {
    "tgn:hierarchy":[
        "tgn:7020021",
        "tgn:1000001",
        "tgn:7012149",
        "tgn:2002384",
        "tgn:7007923",
        "tgn:7029392"
    ],
    "tgn:id":7020021,
    "tgn:name":"Saint John Overlook",
    "tgn:placetype":[
        "aat:300008798"
    ]
},
  "bbox": [],
  "geometry": {"coordinates":[-110.0667,43.6],"type":"Point"}
}
=======
{"geometry":{"type":"Point","coordinates":[-110.066700,43.600000]},"type":"Feature","properties":{"hierarchy":["tgn:7020021","tgn:1000001","tgn:7012149","tgn:2002384","tgn:7007923","tgn:7029392"],"placetype":["aat:300008798"],"id":7020021,"name:xx":"Saint John Overlook"}}
>>>>>>> 03f74aca74312dbeaf24d7e61306dd6a786dc3d0
