{
  "id": 2509272,
  "type": "Feature",
  "properties": {
    "tgn:hierarchy":[
        "tgn:2509272",
        "tgn:7013349",
        "tgn:1000001",
        "tgn:7012149",
        "tgn:7007708",
        "tgn:7029392"
    ],
    "tgn:id":2509272,
    "tgn:name":"Middle Fork Pine Creek",
    "tgn:placetype":[
        "aat:300008706"
    ]
},
  "bbox": [],
  "geometry": {"coordinates":[-117.2333,45.05],"type":"Point"}
}