{
  "id": 2244990,
  "type": "Feature",
  "properties": {
    "tgn:hierarchy":[
        "tgn:2244990",
        "tgn:1000001",
        "tgn:7012149",
        "tgn:2002168",
        "tgn:7007919",
        "tgn:7029392"
    ],
    "tgn:id":2244990,
    "tgn:name":"Clover Creek Hillside Cave",
    "tgn:placetype":[
        "aat:300008746"
    ]
},
  "bbox": [],
  "geometry": {"coordinates":[-79.5167,38.25],"type":"Point"}
}