{
  "id": 7590313,
  "type": "Feature",
  "properties": {
    "tgn:hierarchy":[
        "tgn:7590313",
        "tgn:1000004",
        "tgn:7000198",
        "tgn:7000799",
        "tgn:7029392"
    ],
    "tgn:id":7590313,
    "tgn:name:en":"Lah\u012bl Bela",
    "tgn:placetype":[
        "aat:300008347"
    ]
},
  "bbox": [],
  "geometry": {"coordinates":[74.306982,33.814684],"type":"Point"}
}