{
  "id": 7571934,
  "type": "Feature",
  "properties": {
    "tgn:hierarchy":[
        "tgn:7571934",
        "tgn:1000004",
        "tgn:1001869",
        "tgn:7000198",
        "tgn:7029392"
    ],
    "tgn:id":7571934,
    "tgn:name:en":"Jes\u0101w\u0101ra",
    "tgn:placetype":[
        "aat:300008347"
    ]
},
  "bbox": [],
  "geometry": {"coordinates":[74.198057,22.741493],"type":"Point"}
}