{
  "id": 7579325,
  "type": "Feature",
  "properties": {
    "tgn:hierarchy":[
        "tgn:7579325",
        "tgn:1000004",
        "tgn:7000198",
        "tgn:1003539",
        "tgn:7029392"
    ],
    "tgn:id":7579325,
    "tgn:name:en":"Ummawblei",
    "tgn:placetype":[
        "aat:300008699"
    ]
},
  "bbox": [],
  "geometry": {"coordinates":[91.104779,25.312974],"type":"Point"}
}