<<<<<<< HEAD
{
  "id": 2152393,
  "type": "Feature",
  "properties": {
    "tgn:hierarchy":[
        "tgn:2152393",
        "tgn:1000001",
        "tgn:2002370",
        "tgn:7012149",
        "tgn:7007923",
        "tgn:7029392"
    ],
    "tgn:id":2152393,
    "tgn:name":"Bay Mountain",
    "tgn:placetype":[
        "aat:300008798"
    ]
},
  "bbox": [],
  "geometry": {"coordinates":[-104.6167,44.75],"type":"Point"}
}
=======
{"geometry":{"type":"Point","coordinates":[-104.616700,44.750000]},"type":"Feature","properties":{"hierarchy":["tgn:2152393","tgn:1000001","tgn:2002370","tgn:7012149","tgn:7007923","tgn:7029392"],"placetype":["aat:300008798"],"id":2152393,"name:xx":"Bay Mountain"}}
>>>>>>> 03f74aca74312dbeaf24d7e61306dd6a786dc3d0
