{
  "id": 2152393,
  "type": "Feature",
  "properties": {
    "tgn:hierarchy":[
        "tgn:2152393",
        "tgn:1000001",
        "tgn:2002370",
        "tgn:7012149",
        "tgn:7007923",
        "tgn:7029392"
    ],
    "tgn:id":2152393,
    "tgn:name":"Bay Mountain",
    "tgn:placetype":[
        "aat:300008798"
    ]
},
  "bbox": [],
  "geometry": {"coordinates":[-104.6167,44.75],"type":"Point"}
}