{
  "id": 2222550,
  "type": "Feature",
  "properties": {
    "tgn:hierarchy":[
        "tgn:2222550",
        "tgn:1000001",
        "tgn:7012149",
        "tgn:1003038",
        "tgn:7007517",
        "tgn:7029392"
    ],
    "tgn:id":2222550,
    "tgn:name":"Carpenter Pond",
    "tgn:placetype":[
        "aat:300008680"
    ]
},
  "bbox": [],
  "geometry": {"coordinates":[-72.0167,42.0833],"type":"Point"}
}