{
  "id": 2134777,
  "type": "Feature",
  "properties": {
    "tgn:hierarchy":[
        "tgn:2134777",
        "tgn:1000001",
        "tgn:2001411",
        "tgn:7012149",
        "tgn:7007526",
        "tgn:7029392"
    ],
    "tgn:id":2134777,
    "tgn:name":"Antelope Draw",
    "tgn:placetype":[
        "aat:300008701"
    ]
},
  "bbox": [],
  "geometry": {"coordinates":[-116.45,41.0833],"type":"Point"}
}