<<<<<<< HEAD
{
  "id": 7350710,
  "type": "Feature",
  "properties": {
    "tgn:hierarchy":[
        "tgn:7350710",
        "tgn:1000001",
        "tgn:7005597",
        "tgn:7005560",
        "tgn:7029392"
    ],
    "tgn:id":7350710,
    "tgn:name":"Aquiles Serd\u00e1n",
    "tgn:placetype":[
        "aat:300008347"
    ]
},
  "bbox": [],
  "geometry": {"coordinates":[-99.533333,23.083333],"type":"Point"}
}
=======
{"geometry":{"type":"Point","coordinates":[-99.533333,23.083333]},"type":"Feature","properties":{"hierarchy":["tgn:7350710","tgn:1000001","tgn:7005597","tgn:7005560","tgn:7029392"],"placetype":["aat:300008347"],"id":7350710,"name:xx":"Aquiles Serd\u00e1n"}}
>>>>>>> 03f74aca74312dbeaf24d7e61306dd6a786dc3d0
