{
  "id": 2680590,
  "type": "Feature",
  "properties": {
    "tgn:hierarchy":[
        "tgn:2680590",
        "tgn:1000001",
        "tgn:2002103",
        "tgn:7012149",
        "tgn:7007827",
        "tgn:7029392"
    ],
    "tgn:id":2680590,
    "tgn:name":"South Grove Spring",
    "tgn:placetype":[
        "aat:300008697"
    ]
},
  "bbox": [],
  "geometry": {"coordinates":[-111.9333,41.55],"type":"Point"}
}