{
  "id": 2713020,
  "type": "Feature",
  "properties": {
    "tgn:hierarchy":[
        "tgn:2713020",
        "tgn:1000001",
        "tgn:7012149",
        "tgn:1002607",
        "tgn:7007706",
        "tgn:7029392"
    ],
    "tgn:id":2713020,
    "tgn:name":"Taylor Lake",
    "tgn:placetype":[
        "aat:300006191"
    ]
},
  "bbox": [],
  "geometry": {"coordinates":[-82.1833,41.0667],"type":"Point"}
}