{
  "id": 7236934,
  "type": "Feature",
  "properties": {
    "tgn:hierarchy":[
        "tgn:7236934",
        "tgn:7002715",
        "tgn:7002729",
        "tgn:1000003",
        "tgn:1000074",
        "tgn:7029392"
    ],
    "tgn:id":7236934,
    "tgn:name":"Elatoch\u00f3rion",
    "tgn:placetype":[
        "aat:300008347"
    ]
},
  "bbox": [],
  "geometry": {"coordinates":[22.250556,40.307778],"type":"Point"}
}