<<<<<<< HEAD
{
  "id": 7179262,
  "type": "Feature",
  "properties": {
    "tgn:hierarchy":[
        "tgn:7179262",
        "tgn:7003669",
        "tgn:1000003",
        "tgn:7000084",
        "tgn:7029392"
    ],
    "tgn:id":7179262,
    "tgn:name":"Haberb\u00fchl",
    "tgn:placetype":[
        "aat:300008347"
    ]
},
  "bbox": [],
  "geometry": {"coordinates":[13.05,49.083333],"type":"Point"}
}
=======
{"geometry":{"type":"Point","coordinates":[13.050000,49.083333]},"type":"Feature","properties":{"hierarchy":["tgn:7179262","tgn:7003669","tgn:1000003","tgn:7000084","tgn:7029392"],"placetype":["aat:300008347"],"id":7179262,"name:xx":"Haberb\u00fchl"}}
>>>>>>> 03f74aca74312dbeaf24d7e61306dd6a786dc3d0
