{
  "id": 7344648,
  "type": "Feature",
  "properties": {
    "tgn:hierarchy":[
        "tgn:7344648",
        "tgn:7002844",
        "tgn:7030216",
        "tgn:1000003",
        "tgn:1000095",
        "tgn:7029392"
    ],
    "tgn:id":7344648,
    "tgn:name":"Anfacadas, Balsa de",
    "tgn:placetype":[
        "aat:300008679"
    ]
},
  "bbox": [],
  "geometry": {"coordinates":[0.833333,40.683333],"type":"Point"}
}