{
  "id": 7539421,
  "type": "Feature",
  "properties": {
    "tgn:hierarchy":[
        "tgn:7539421",
        "tgn:7001242",
        "tgn:7016833",
        "tgn:7001336",
        "tgn:7029392"
    ],
    "tgn:id":7539421,
    "tgn:name:en":"Qabr \u1e28am\u0101dah, Jabal",
    "tgn:placetype":[
        "aat:300008795"
    ]
},
  "bbox": [],
  "geometry": {"coordinates":[34.401976,29.473712],"type":"Point"}
}