<<<<<<< HEAD
{
  "id": 2152607,
  "type": "Feature",
  "properties": {
    "tgn:hierarchy":[
        "tgn:2152607",
        "tgn:1000001",
        "tgn:7012149",
        "tgn:2000430",
        "tgn:7007248",
        "tgn:7029392"
    ],
    "tgn:id":2152607,
    "tgn:name":"Bayless Cove",
    "tgn:placetype":[
        "aat:300132316"
    ]
},
  "bbox": [],
  "geometry": {"coordinates":[-83.7667,34.9],"type":"Point"}
}
=======
{"geometry":{"type":"Point","coordinates":[-83.766700,34.900000]},"type":"Feature","properties":{"hierarchy":["tgn:2152607","tgn:1000001","tgn:7012149","tgn:2000430","tgn:7007248","tgn:7029392"],"placetype":["aat:300132316"],"id":2152607,"name:xx":"Bayless Cove"}}
>>>>>>> 03f74aca74312dbeaf24d7e61306dd6a786dc3d0
