<<<<<<< HEAD
{
  "id": 2150017,
  "type": "Feature",
  "properties": {
    "tgn:hierarchy":[
        "tgn:2150017",
        "tgn:1000001",
        "tgn:2001340",
        "tgn:7012149",
        "tgn:7007525",
        "tgn:7029392"
    ],
    "tgn:id":2150017,
    "tgn:name":"Barton",
    "tgn:placetype":[
        "aat:300008347"
    ]
},
  "bbox": [],
  "geometry": {"coordinates":[-102.1667,41.0333],"type":"Point"}
}
=======
{"geometry":{"type":"Point","coordinates":[-102.166700,41.033300]},"type":"Feature","properties":{"hierarchy":["tgn:2150017","tgn:1000001","tgn:2001340","tgn:7012149","tgn:7007525","tgn:7029392"],"placetype":["aat:300008347"],"id":2150017,"name:xx":"Barton"}}
>>>>>>> 03f74aca74312dbeaf24d7e61306dd6a786dc3d0
