{
  "id": 7586757,
  "type": "Feature",
  "properties": {
    "tgn:hierarchy":[
        "tgn:7586757",
        "tgn:1000004",
        "tgn:7000198",
        "tgn:7000799",
        "tgn:7029392"
    ],
    "tgn:id":7586757,
    "tgn:name:en":"Demnari",
    "tgn:placetype":[
        "aat:300008795"
    ]
},
  "bbox": [],
  "geometry": {"coordinates":[74.433333,34.448611],"type":"Point"}
}