{
  "id": 2453814,
  "type": "Feature",
  "properties": {
    "tgn:hierarchy":[
        "tgn:2453814",
        "tgn:1000001",
        "tgn:7016172",
        "tgn:7012149",
        "tgn:7029392"
    ],
    "tgn:id":2453814,
    "tgn:name":"Little Cow Lake",
    "tgn:placetype":[
        "aat:300008699"
    ]
},
  "bbox": [],
  "geometry": {"coordinates":[-91.1333,35.3667],"type":"Point"}
}