{
  "id": 2338033,
  "type": "Feature",
  "properties": {
    "tgn:hierarchy":[
        "tgn:2338033",
        "tgn:1000001",
        "tgn:1002283",
        "tgn:7012149",
        "tgn:7007520",
        "tgn:7029392"
    ],
    "tgn:id":2338033,
    "tgn:name":"Fox Knoll Lake",
    "tgn:placetype":[
        "aat:300008680"
    ]
},
  "bbox": [],
  "geometry": {"coordinates":[-84.3833,42.7833],"type":"Point"}
}