{
  "id": 1097530,
  "type": "Feature",
  "properties": {
    "tgn:hierarchy":[
        "tgn:1097530",
        "tgn:7000490",
        "tgn:1000006",
        "tgn:7006238",
        "tgn:7029392"
    ],
    "tgn:id":1097530,
    "tgn:name":"Merbein",
    "tgn:placetype":[
        "aat:300008347"
    ]
},
  "bbox": [],
  "geometry": {"coordinates":[142.0833,-34.1833],"type":"Point"}
}