{
  "id": 1016560,
  "type": "Feature",
  "properties": {
    "tgn:hierarchy":[
        "tgn:1016560",
        "tgn:7005450",
        "tgn:1000001",
        "tgn:7005441",
        "tgn:7029392"
    ],
    "tgn:id":1016560,
    "tgn:name":"Suchitoto",
    "tgn:placetype":[
        "aat:300008347"
    ]
},
  "bbox": [],
  "geometry": {"coordinates":[-89.0333,13.9333],"type":"Point"}
}