<<<<<<< HEAD
{
  "id": 2151102,
  "type": "Feature",
  "properties": {
    "tgn:hierarchy":[
        "tgn:2151102",
        "tgn:1000001",
        "tgn:7006451",
        "tgn:2000095",
        "tgn:7012149",
        "tgn:7029392"
    ],
    "tgn:id":2151102,
    "tgn:name":"Bat Cave",
    "tgn:placetype":[
        "aat:300008746"
    ]
},
  "bbox": [],
  "geometry": {"coordinates":[-109.4,33.0167],"type":"Point"}
}
=======
{"geometry":{"type":"Point","coordinates":[-109.400000,33.016700]},"type":"Feature","properties":{"hierarchy":["tgn:2151102","tgn:1000001","tgn:7006451","tgn:2000095","tgn:7012149","tgn:7029392"],"placetype":["aat:300008746"],"id":2151102,"name:xx":"Bat Cave"}}
>>>>>>> 03f74aca74312dbeaf24d7e61306dd6a786dc3d0
