<<<<<<< HEAD
{
  "id": 2767809,
  "type": "Feature",
  "properties": {
    "tgn:hierarchy":[
        "tgn:2767809",
        "tgn:1000001",
        "tgn:7012149",
        "tgn:2002372",
        "tgn:7007923",
        "tgn:7029392"
    ],
    "tgn:id":2767809,
    "tgn:name":"Whitehorse Butte",
    "tgn:placetype":[
        "aat:300008798"
    ]
},
  "bbox": [],
  "geometry": {"coordinates":[-104.4167,42.0],"type":"Point"}
}
=======
{"geometry":{"type":"Point","coordinates":[-104.416700,42.000000]},"type":"Feature","properties":{"hierarchy":["tgn:2767809","tgn:1000001","tgn:7012149","tgn:2002372","tgn:7007923","tgn:7029392"],"placetype":["aat:300008798"],"id":2767809,"name:xx":"Whitehorse Butte"}}
>>>>>>> 03f74aca74312dbeaf24d7e61306dd6a786dc3d0
