{
  "id": 2611756,
  "type": "Feature",
  "properties": {
    "tgn:hierarchy":[
        "tgn:2611756",
        "tgn:1000001",
        "tgn:7012149",
        "tgn:2000354",
        "tgn:7007248",
        "tgn:7029392"
    ],
    "tgn:id":2611756,
    "tgn:name":"Red Oak Island",
    "tgn:placetype":[
        "aat:300008791"
    ]
},
  "bbox": [],
  "geometry": {"coordinates":[-81.6667,31.3833],"type":"Point"}
}