{
  "id": 7407945,
  "type": "Feature",
  "properties": {
    "tgn:hierarchy":[
        "tgn:7407945",
        "tgn:1000001",
        "tgn:7005590",
        "tgn:7005560",
        "tgn:7029392"
    ],
    "tgn:id":7407945,
    "tgn:name":"San Juan, R\u00edo",
    "tgn:placetype":[
        "aat:300008699"
    ]
},
  "bbox": [],
  "geometry": {"coordinates":[-101.491667,19.391667],"type":"Point"}
}