{
  "id": 7100298,
  "type": "Feature",
  "properties": {
    "tgn:hierarchy":[
        "tgn:7100298",
        "tgn:7003669",
        "tgn:1000003",
        "tgn:7000084",
        "tgn:7029392"
    ],
    "tgn:id":7100298,
    "tgn:name":"Saale-Quelle",
    "tgn:placetype":[
        "aat:300008697"
    ]
},
  "bbox": [],
  "geometry": {"coordinates":[11.833333,50.116667],"type":"Point"}
}