{
  "id": 7488802,
  "type": "Feature",
  "properties": {
    "tgn:hierarchy":[
        "tgn:7488802",
        "tgn:1000004",
        "tgn:7489179",
        "tgn:1000141",
        "tgn:7029392"
    ],
    "tgn:id":7488802,
    "tgn:name":"Guiwei",
    "tgn:placetype":[
        "aat:300386848"
    ]
},
  "bbox": [],
  "geometry": {"coordinates":[121.934444,24.846111],"type":"Point"}
}