<<<<<<< HEAD
{
  "id": 2337308,
  "type": "Feature",
  "properties": {
    "tgn:hierarchy":[
        "tgn:2337308",
        "tgn:1000001",
        "tgn:7012149",
        "tgn:2001315",
        "tgn:7007524",
        "tgn:7029392"
    ],
    "tgn:id":2337308,
    "tgn:name":"Fourth of July Creek",
    "tgn:placetype":[
        "aat:300008706"
    ]
},
  "bbox": [],
  "geometry": {"coordinates":[-108.6,45.5167],"type":"Point"}
}
=======
{"geometry":{"type":"Point","coordinates":[-108.600000,45.516700]},"type":"Feature","properties":{"hierarchy":["tgn:2337308","tgn:1000001","tgn:7012149","tgn:2001315","tgn:7007524","tgn:7029392"],"placetype":["aat:300008706"],"id":2337308,"name:xx":"Fourth of July Creek"}}
>>>>>>> 03f74aca74312dbeaf24d7e61306dd6a786dc3d0
