{
  "id": 2379911,
  "type": "Feature",
  "properties": {
    "tgn:hierarchy":[
        "tgn:2379911",
        "tgn:1000001",
        "tgn:2002109",
        "tgn:7012149",
        "tgn:7007827",
        "tgn:7029392"
    ],
    "tgn:id":2379911,
    "tgn:name":"Hat Shop",
    "tgn:placetype":[
        "aat:300011692"
    ]
},
  "bbox": [],
  "geometry": {"coordinates":[-112.1333,37.5833],"type":"Point"}
}