{
  "id": 2272933,
  "type": "Feature",
  "properties": {
    "tgn:hierarchy":[
        "tgn:2272933",
        "tgn:1000001",
        "tgn:7012149",
        "tgn:2001108",
        "tgn:7007522",
        "tgn:7029392"
    ],
    "tgn:id":2272933,
    "tgn:name":"Cutoff Lake",
    "tgn:placetype":[
        "aat:300008680"
    ]
},
  "bbox": [],
  "geometry": {"coordinates":[-89.3833,30.35],"type":"Point"}
}