{
  "id": 2346658,
  "type": "Feature",
  "properties": {
    "tgn:hierarchy":[
        "tgn:2346658",
        "tgn:1000001",
        "tgn:7012149",
        "tgn:2000489",
        "tgn:7007250",
        "tgn:7029392"
    ],
    "tgn:id":2346658,
    "tgn:name":"Gayway Corner",
    "tgn:placetype":[
        "aat:300008347"
    ]
},
  "bbox": [],
  "geometry": {"coordinates":[-116.9167,44.0167],"type":"Point"}
}