{
  "id": 7465327,
  "type": "Feature",
  "properties": {
    "tgn:hierarchy":[
        "tgn:7465327",
        "tgn:7002444",
        "tgn:7008074",
        "tgn:1000003",
        "tgn:7008591",
        "tgn:7029392"
    ],
    "tgn:id":7465327,
    "tgn:name:en":"Beaufort's Dyke",
    "tgn:placetype":[
        "aat:300386938"
    ]
},
  "bbox": [],
  "geometry": {"coordinates":[-5.233333,54.716667],"type":"Point"}
}