{
  "id": 7398572,
  "type": "Feature",
  "properties": {
    "tgn:hierarchy":[
        "tgn:7398572",
        "tgn:1000001",
        "tgn:7005593",
        "tgn:7005560",
        "tgn:7029392"
    ],
    "tgn:id":7398572,
    "tgn:name":"Cerro Prieto",
    "tgn:placetype":[
        "aat:300008347"
    ]
},
  "bbox": [],
  "geometry": {"coordinates":[-99.533333,20.683333],"type":"Point"}
}