{
  "id": 2607294,
  "type": "Feature",
  "properties": {
    "tgn:hierarchy":[
        "tgn:2607294",
        "tgn:1002165",
        "tgn:1000001",
        "tgn:7012149",
        "tgn:7007517",
        "tgn:7029392"
    ],
    "tgn:id":2607294,
    "tgn:name":"Rands Harbor",
    "tgn:placetype":[
        "aat:300386845"
    ]
},
  "bbox": [],
  "geometry": {"coordinates":[-70.6167,41.65],"type":"Point"}
}