<<<<<<< HEAD
{
  "id": 2701618,
  "type": "Feature",
  "properties": {
    "tgn:hierarchy":[
        "tgn:2701618",
        "tgn:1000001",
        "tgn:7012149",
        "tgn:2001616",
        "tgn:7007706",
        "tgn:7029392"
    ],
    "tgn:id":2701618,
    "tgn:name":"Sugarcamp Run",
    "tgn:placetype":[
        "aat:300008699"
    ]
},
  "bbox": [],
  "geometry": {"coordinates":[-81.7833,39.15],"type":"Point"}
}
=======
{"geometry":{"type":"Point","coordinates":[-81.783300,39.150000]},"type":"Feature","properties":{"hierarchy":["tgn:2701618","tgn:1000001","tgn:7012149","tgn:2001616","tgn:7007706","tgn:7029392"],"placetype":["aat:300008699"],"id":2701618,"name:xx":"Sugarcamp Run"}}
>>>>>>> 03f74aca74312dbeaf24d7e61306dd6a786dc3d0
