<<<<<<< HEAD
{
  "id": 2407705,
  "type": "Feature",
  "properties": {
    "tgn:hierarchy":[
        "tgn:2407705",
        "tgn:1000001",
        "tgn:7012149",
        "tgn:2000964",
        "tgn:7007520",
        "tgn:7029392"
    ],
    "tgn:id":2407705,
    "tgn:name":"Huron City",
    "tgn:placetype":[
        "aat:300008347"
    ]
},
  "bbox": [],
  "geometry": {"coordinates":[-82.8167,44.0167],"type":"Point"}
}
=======
{"geometry":{"type":"Point","coordinates":[-82.816700,44.016700]},"type":"Feature","properties":{"hierarchy":["tgn:2407705","tgn:1000001","tgn:7012149","tgn:2000964","tgn:7007520","tgn:7029392"],"placetype":["aat:300008347"],"id":2407705,"name:xx":"Huron City"}}
>>>>>>> 03f74aca74312dbeaf24d7e61306dd6a786dc3d0
