{
  "id": 2232036,
  "type": "Feature",
  "properties": {
    "tgn:hierarchy":[
        "tgn:2232036",
        "tgn:1000001",
        "tgn:7012149",
        "tgn:2000817",
        "tgn:7007255",
        "tgn:7029392"
    ],
    "tgn:id":2232036,
    "tgn:name":"Champion Creek",
    "tgn:placetype":[
        "aat:300008706"
    ]
},
  "bbox": [],
  "geometry": {"coordinates":[-88.65,36.9833],"type":"Point"}
}