{
  "id": 2455369,
  "type": "Feature",
  "properties": {
    "tgn:hierarchy":[
        "tgn:2455369",
        "tgn:1000001",
        "tgn:7012149",
        "tgn:7007255",
        "tgn:7029392"
    ],
    "tgn:id":2455369,
    "tgn:name":"Little Fork Little Sandy River",
    "tgn:placetype":[
        "aat:300008707"
    ]
},
  "bbox": [],
  "geometry": {"coordinates":[-83.0167,38.05],"type":"Point"}
}