{
  "id": 1097922,
  "type": "Feature",
  "properties": {
    "tgn:hierarchy":[
        "tgn:1097922",
        "tgn:7000490",
        "tgn:1000006",
        "tgn:7001828",
        "tgn:7029392"
    ],
    "tgn:id":1097922,
    "tgn:name":"Peakhurst",
    "tgn:placetype":[
        "aat:300008347"
    ]
},
  "bbox": [],
  "geometry": {"coordinates":[151.05,-33.9667],"type":"Point"}
}