<<<<<<< HEAD
{
  "id": 2409944,
  "type": "Feature",
  "properties": {
    "tgn:hierarchy":[
        "tgn:2409944",
        "tgn:1000001",
        "tgn:7012149",
        "tgn:2001288",
        "tgn:7007524",
        "tgn:7029392"
    ],
    "tgn:id":2409944,
    "tgn:name":"Imp Peak",
    "tgn:placetype":[
        "aat:300008798"
    ]
},
  "bbox": [],
  "geometry": {"coordinates":[-111.45,44.9833],"type":"Point"}
}
=======
{"geometry":{"type":"Point","coordinates":[-111.450000,44.983300]},"type":"Feature","properties":{"hierarchy":["tgn:2409944","tgn:1000001","tgn:7012149","tgn:2001288","tgn:7007524","tgn:7029392"],"placetype":["aat:300008798"],"id":2409944,"name:xx":"Imp Peak"}}
>>>>>>> 03f74aca74312dbeaf24d7e61306dd6a786dc3d0
