<<<<<<< HEAD
{
  "id": 7356171,
  "type": "Feature",
  "properties": {
    "tgn:hierarchy":[
        "tgn:7356171",
        "tgn:1000001",
        "tgn:7005591",
        "tgn:7005560",
        "tgn:7029392"
    ],
    "tgn:id":7356171,
    "tgn:name":"Carmen",
    "tgn:placetype":[
        "aat:300008347"
    ]
},
  "bbox": [],
  "geometry": {"coordinates":[-94.116667,16.333333],"type":"Point"}
}
=======
{"geometry":{"type":"Point","coordinates":[-94.116667,16.333333]},"type":"Feature","properties":{"hierarchy":["tgn:7356171","tgn:1000001","tgn:7005591","tgn:7005560","tgn:7029392"],"placetype":["aat:300008347"],"id":7356171,"name:xx":"Carmen"}}
>>>>>>> 03f74aca74312dbeaf24d7e61306dd6a786dc3d0
