{
  "id": 2300906,
  "type": "Feature",
  "properties": {
    "tgn:hierarchy":[
        "tgn:2300906",
        "tgn:1000001",
        "tgn:2000458",
        "tgn:7012149",
        "tgn:7007250",
        "tgn:7029392"
    ],
    "tgn:id":2300906,
    "tgn:name":"Duncan Ridge",
    "tgn:placetype":[
        "aat:300266640"
    ]
},
  "bbox": [],
  "geometry": {"coordinates":[-114.1333,43.75],"type":"Point"}
}