{
  "id": 7199019,
  "type": "Feature",
  "properties": {
    "tgn:hierarchy":[
        "tgn:7199019",
        "tgn:1000003",
        "tgn:7000094",
        "tgn:7000084",
        "tgn:7029392"
    ],
    "tgn:id":7199019,
    "tgn:name":"Eichenthal",
    "tgn:placetype":[
        "aat:300008347"
    ]
},
  "bbox": [],
  "geometry": {"coordinates":[12.733333,54.066667],"type":"Point"}
}