{
  "id": 7219619,
  "type": "Feature",
  "properties": {
    "tgn:hierarchy":[
        "tgn:7219619",
        "tgn:7011161",
        "tgn:7002674",
        "tgn:1000003",
        "tgn:1000074",
        "tgn:7029392"
    ],
    "tgn:id":7219619,
    "tgn:name":"Ch\u00edou, Lim\u00e9nas",
    "tgn:placetype":[
        "aat:300008678"
    ]
},
  "bbox": [],
  "geometry": {"coordinates":[26.140556,38.368611],"type":"Point"}
}