<<<<<<< HEAD
{
  "id": 2333789,
  "type": "Feature",
  "properties": {
    "tgn:hierarchy":[
        "tgn:2333789",
        "tgn:1000001",
        "tgn:7012149",
        "tgn:2001711",
        "tgn:7007708",
        "tgn:7029392"
    ],
    "tgn:id":2333789,
    "tgn:name":"Foots Creek",
    "tgn:placetype":[
        "aat:300008706"
    ]
},
  "bbox": [],
  "geometry": {"coordinates":[-123.1,42.35],"type":"Point"}
}
=======
{"geometry":{"type":"Point","coordinates":[-123.100000,42.350000]},"type":"Feature","properties":{"hierarchy":["tgn:2333789","tgn:1000001","tgn:7012149","tgn:2001711","tgn:7007708","tgn:7029392"],"placetype":["aat:300008706"],"id":2333789,"name:xx":"Foots Creek"}}
>>>>>>> 03f74aca74312dbeaf24d7e61306dd6a786dc3d0
