{
  "id": 2653240,
  "type": "Feature",
  "properties": {
    "tgn:hierarchy":[
        "tgn:2653240",
        "tgn:1000001",
        "tgn:2001416",
        "tgn:7012149",
        "tgn:7007526",
        "tgn:7029392"
    ],
    "tgn:id":2653240,
    "tgn:name":"Seven Troughs Wash",
    "tgn:placetype":[
        "aat:300008699"
    ]
},
  "bbox": [],
  "geometry": {"coordinates":[-114.1167,38.2667],"type":"Point"}
}