{
  "id": 1008448,
  "type": "Feature",
  "properties": {
    "tgn:hierarchy":[
        "tgn:1008448",
        "tgn:7000528",
        "tgn:7000529",
        "tgn:1000006",
        "tgn:7029392"
    ],
    "tgn:id":1008448,
    "tgn:name":"Onevai",
    "tgn:placetype":[
        "aat:300008791"
    ]
},
  "bbox": [],
  "geometry": {"coordinates":[-175.1167,-21.0833],"type":"Point"}
}