<<<<<<< HEAD
{
  "id": 7020261,
  "type": "Feature",
  "properties": {
    "tgn:hierarchy":[
        "tgn:7020261",
        "tgn:1000001",
        "tgn:7012149",
        "tgn:2001502",
        "tgn:7007709",
        "tgn:7029392"
    ],
    "tgn:id":7020261,
    "tgn:name":"Stewarts Creek",
    "tgn:placetype":[
        "aat:300008706"
    ]
},
  "bbox": [],
  "geometry": {"coordinates":[-78.8167,35.3],"type":"Point"}
}
=======
{"geometry":{"type":"Point","coordinates":[-78.816700,35.300000]},"type":"Feature","properties":{"hierarchy":["tgn:7020261","tgn:1000001","tgn:7012149","tgn:2001502","tgn:7007709","tgn:7029392"],"placetype":["aat:300008706"],"id":7020261,"name:xx":"Stewarts Creek"}}
>>>>>>> 03f74aca74312dbeaf24d7e61306dd6a786dc3d0
