{
  "id": 2087359,
  "type": "Feature",
  "properties": {
    "tgn:hierarchy":[
        "tgn:2087359",
        "tgn:1000001",
        "tgn:1002249",
        "tgn:7012149",
        "tgn:7007710",
        "tgn:7029392"
    ],
    "tgn:id":2087359,
    "tgn:name":"Coburn",
    "tgn:placetype":[
        "aat:300008347"
    ]
},
  "bbox": [],
  "geometry": {"coordinates":[-77.45,40.85],"type":"Point"}
}