{
  "id": 2651652,
  "type": "Feature",
  "properties": {
    "tgn:hierarchy":[
        "tgn:2651652",
        "tgn:1002309",
        "tgn:1000001",
        "tgn:7012149",
        "tgn:7007565",
        "tgn:7029392"
    ],
    "tgn:id":2651652,
    "tgn:name":"Seeley Pond",
    "tgn:placetype":[
        "aat:300006191"
    ]
},
  "bbox": [],
  "geometry": {"coordinates":[-75.25,39.4833],"type":"Point"}
}