{
  "id": 7581173,
  "type": "Feature",
  "properties": {
    "tgn:hierarchy":[
        "tgn:7581173",
        "tgn:7001819",
        "tgn:1000004",
        "tgn:7000198",
        "tgn:7029392"
    ],
    "tgn:id":7581173,
    "tgn:name:en":"Tirkang",
    "tgn:placetype":[
        "aat:300008347"
    ]
},
  "bbox": [],
  "geometry": {"coordinates":[95.14642,29.089576],"type":"Point"}
}