{
  "id": 1021777,
  "type": "Feature",
  "properties": {
    "tgn:hierarchy":[
        "tgn:1021777",
        "tgn:1001945",
        "tgn:1000047",
        "tgn:7002457",
        "tgn:1000002",
        "tgn:7029392"
    ],
    "tgn:id":1021777,
    "tgn:name":"Itirapina",
    "tgn:placetype":[
        "aat:300008347"
    ]
},
  "bbox": [],
  "geometry": {"coordinates":[-47.8167,-22.25],"type":"Point"}
}