<<<<<<< HEAD
{
  "id": 2708987,
  "type": "Feature",
  "properties": {
    "tgn:hierarchy":[
        "tgn:2708987",
        "tgn:7002659",
        "tgn:1000001",
        "tgn:2000010",
        "tgn:7012149",
        "tgn:7029392"
    ],
    "tgn:id":2708987,
    "tgn:name":"T J Stewart Lake",
    "tgn:placetype":[
        "aat:300006191"
    ]
},
  "bbox": [],
  "geometry": {"coordinates":[-86.5667,32.8],"type":"Point"}
}
=======
{"geometry":{"type":"Point","coordinates":[-86.566700,32.800000]},"type":"Feature","properties":{"hierarchy":["tgn:2708987","tgn:7002659","tgn:1000001","tgn:2000010","tgn:7012149","tgn:7029392"],"placetype":["aat:300006191"],"id":2708987,"name:xx":"T J Stewart Lake"}}
>>>>>>> 03f74aca74312dbeaf24d7e61306dd6a786dc3d0
