<<<<<<< HEAD
{
  "id": 7025171,
  "type": "Feature",
  "properties": {
    "tgn:hierarchy":[
        "tgn:7025171",
        "tgn:7002445",
        "tgn:1000003",
        "tgn:7008118",
        "tgn:7008591",
        "tgn:7029392"
    ],
    "tgn:id":7025171,
    "tgn:name:ang":"Collei",
    "tgn:placetype":[
        "aat:300008347"
    ]
},
  "bbox": [],
  "geometry": {"coordinates":[-1.4833,53.2833],"type":"Point"}
}
=======
{"geometry":{"type":"Point","coordinates":[-1.483300,53.283300]},"type":"Feature","properties":{"hierarchy":["tgn:7025171","tgn:7002445","tgn:1000003","tgn:7008118","tgn:7008591","tgn:7029392"],"placetype":["aat:300008347"],"id":7025171,"name:ang":"Collei"}}
>>>>>>> 03f74aca74312dbeaf24d7e61306dd6a786dc3d0
