{
  "id": 7365098,
  "type": "Feature",
  "properties": {
    "tgn:hierarchy":[
        "tgn:7365098",
        "tgn:1000001",
        "tgn:7005595",
        "tgn:7005560",
        "tgn:7029392"
    ],
    "tgn:id":7365098,
    "tgn:name":"Rancho El Queremal",
    "tgn:placetype":[
        "aat:300000241"
    ]
},
  "bbox": [],
  "geometry": {"coordinates":[-108.133333,25.033333],"type":"Point"}
}