{
  "id": 7514390,
  "type": "Feature",
  "properties": {
    "tgn:hierarchy":[
        "tgn:7514390",
        "tgn:1009227",
        "tgn:1000226",
        "tgn:1000006",
        "tgn:7016850",
        "tgn:7029392"
    ],
    "tgn:id":7514390,
    "tgn:name:en":"Douglas Glacier",
    "tgn:placetype":[
        "aat:300008835"
    ]
},
  "bbox": [],
  "geometry": {"coordinates":[169.983333,-43.683333],"type":"Point"}
}