{
  "id": 7236217,
  "type": "Feature",
  "properties": {
    "tgn:hierarchy":[
        "tgn:7236217",
        "tgn:7002751",
        "tgn:7001399",
        "tgn:1000003",
        "tgn:1000074",
        "tgn:7029392"
    ],
    "tgn:id":7236217,
    "tgn:name":"\u00c1yios S\u00f3stis, \u00c1kra",
    "tgn:placetype":[
        "aat:300008850"
    ]
},
  "bbox": [],
  "geometry": {"coordinates":[22.983333,38.95],"type":"Point"}
}