{
  "id": 5001893,
  "type": "Feature",
  "properties": {
    "tgn:hierarchy":[
        "tgn:5001893",
        "tgn:1000003",
        "tgn:7003682",
        "tgn:7000084",
        "tgn:7029392"
    ],
    "tgn:id":5001893,
    "tgn:name":"Ernst an der Mosel",
    "tgn:placetype":[
        "aat:300008347",
        "aat:300008375"
    ]
},
  "bbox": [],
  "geometry": {"coordinates":[7.233333,50.15],"type":"Point"}
}