{
  "id": 2702110,
  "type": "Feature",
  "properties": {
    "tgn:hierarchy":[
        "tgn:2702110",
        "tgn:1000001",
        "tgn:7012149",
        "tgn:2002252",
        "tgn:7007920",
        "tgn:7029392"
    ],
    "tgn:id":2702110,
    "tgn:name":"Suicide Canyon",
    "tgn:placetype":[
        "aat:300008761"
    ]
},
  "bbox": [],
  "geometry": {"coordinates":[-117.3167,46.5833],"type":"Point"}
}