<<<<<<< HEAD
{
  "id": 7058617,
  "type": "Feature",
  "properties": {
    "tgn:hierarchy":[
        "tgn:7058617",
        "tgn:7009084",
        "tgn:7003000",
        "tgn:1000003",
        "tgn:1000080",
        "tgn:7029392"
    ],
    "tgn:id":7058617,
    "tgn:name":"Altino",
    "tgn:placetype":[
        "aat:300008347"
    ]
},
  "bbox": [],
  "geometry": {"coordinates":[14.316667,42.1],"type":"Point"}
}
=======
{"geometry":{"type":"Point","coordinates":[14.316667,42.100000]},"type":"Feature","properties":{"hierarchy":["tgn:7058617","tgn:7009084","tgn:7003000","tgn:1000003","tgn:1000080","tgn:7029392"],"placetype":["aat:300008347"],"id":7058617,"name:xx":"Altino"}}
>>>>>>> 03f74aca74312dbeaf24d7e61306dd6a786dc3d0
