<<<<<<< HEAD
{
  "id": 2256875,
  "type": "Feature",
  "properties": {
    "tgn:hierarchy":[
        "tgn:2256875",
        "tgn:1000001",
        "tgn:2000470",
        "tgn:7012149",
        "tgn:7007250",
        "tgn:7029392"
    ],
    "tgn:id":2256875,
    "tgn:name":"Corkscrew Mountain",
    "tgn:placetype":[
        "aat:300008798"
    ]
},
  "bbox": [],
  "geometry": {"coordinates":[-114.3667,44.5167],"type":"Point"}
}
=======
{"geometry":{"type":"Point","coordinates":[-114.366700,44.516700]},"type":"Feature","properties":{"hierarchy":["tgn:2256875","tgn:1000001","tgn:2000470","tgn:7012149","tgn:7007250","tgn:7029392"],"placetype":["aat:300008798"],"id":2256875,"name:xx":"Corkscrew Mountain"}}
>>>>>>> 03f74aca74312dbeaf24d7e61306dd6a786dc3d0
