{
  "id": 2256875,
  "type": "Feature",
  "properties": {
    "tgn:hierarchy":[
        "tgn:2256875",
        "tgn:1000001",
        "tgn:2000470",
        "tgn:7012149",
        "tgn:7007250",
        "tgn:7029392"
    ],
    "tgn:id":2256875,
    "tgn:name":"Corkscrew Mountain",
    "tgn:placetype":[
        "aat:300008798"
    ]
},
  "bbox": [],
  "geometry": {"coordinates":[-114.3667,44.5167],"type":"Point"}
}