{
  "id": 7048440,
  "type": "Feature",
  "properties": {
    "tgn:hierarchy":[
        "tgn:7048440",
        "tgn:1003488",
        "tgn:1000003",
        "tgn:7002993",
        "tgn:1000080",
        "tgn:7029392"
    ],
    "tgn:id":7048440,
    "tgn:name":"Chions",
    "tgn:placetype":[
        "aat:300008347"
    ]
},
  "bbox": [],
  "geometry": {"coordinates":[12.711111,45.848889],"type":"Point"}
}