{
  "id": 7002169,
  "type": "Feature",
  "properties": {
    "tgn:hierarchy":[
        "tgn:7002169",
        "tgn:1000004",
        "tgn:7002171",
        "tgn:1000108",
        "tgn:7029392"
    ],
    "tgn:id":7002169,
    "tgn:name":"Mandalay",
    "tgn:placetype":[
        "aat:300008347",
        "aat:300008389",
        "aat:300387222",
        "aat:300387219",
        "aat:300387220",
        "aat:300387272",
        "aat:300387286"
    ]
},
  "bbox": [],
  "geometry": {"coordinates":[96.0667,21.95],"type":"Point"}
}