{
  "id": 7292637,
  "type": "Feature",
  "properties": {
    "tgn:hierarchy":[
        "tgn:7292637",
        "tgn:1001699",
        "tgn:1000049",
        "tgn:1000002",
        "tgn:7029392"
    ],
    "tgn:id":7292637,
    "tgn:name":"El Nav\u00edo, Roca",
    "tgn:placetype":[
        "aat:300011692"
    ]
},
  "bbox": [],
  "geometry": {"coordinates":[-73.45,-43.066667],"type":"Point"}
}