{
  "id": 2305999,
  "type": "Feature",
  "properties": {
    "tgn:hierarchy":[
        "tgn:2305999",
        "tgn:1000001",
        "tgn:7016172",
        "tgn:7012149",
        "tgn:7029392"
    ],
    "tgn:id":2305999,
    "tgn:name":"East Fleming Creek",
    "tgn:placetype":[
        "aat:300008706"
    ]
},
  "bbox": [],
  "geometry": {"coordinates":[-93.7667,35.8167],"type":"Point"}
}