<<<<<<< HEAD
{
  "id": 2252040,
  "type": "Feature",
  "properties": {
    "tgn:hierarchy":[
        "tgn:2252040",
        "tgn:7006450",
        "tgn:1000001",
        "tgn:7019698",
        "tgn:7012149",
        "tgn:7029392"
    ],
    "tgn:id":2252040,
    "tgn:name":"Concordia Glacier",
    "tgn:placetype":[
        "aat:300008835"
    ]
},
  "bbox": [],
  "geometry": {"coordinates":[-148.7167,60.6833],"type":"Point"}
}
=======
{"geometry":{"type":"Point","coordinates":[-148.716700,60.683300]},"type":"Feature","properties":{"hierarchy":["tgn:2252040","tgn:7006450","tgn:1000001","tgn:7019698","tgn:7012149","tgn:7029392"],"placetype":["aat:300008835"],"id":2252040,"name:xx":"Concordia Glacier"}}
>>>>>>> 03f74aca74312dbeaf24d7e61306dd6a786dc3d0
