{
  "id": 2774829,
  "type": "Feature",
  "properties": {
    "tgn:hierarchy":[
        "tgn:2774829",
        "tgn:1000001",
        "tgn:7012149",
        "tgn:1002990",
        "tgn:7007708",
        "tgn:7029392"
    ],
    "tgn:id":2774829,
    "tgn:name":"Willow Springs",
    "tgn:placetype":[
        "aat:300008697"
    ]
},
  "bbox": [],
  "geometry": {"coordinates":[-121.6667,45.0333],"type":"Point"}
}