<<<<<<< HEAD
{
  "id": 7174167,
  "type": "Feature",
  "properties": {
    "tgn:hierarchy":[
        "tgn:7174167",
        "tgn:1000003",
        "tgn:7003688",
        "tgn:7000084",
        "tgn:7029392"
    ],
    "tgn:id":7174167,
    "tgn:name":"Gro\u00df Ahrensh\u00f6ft",
    "tgn:placetype":[
        "aat:300008347"
    ]
},
  "bbox": [],
  "geometry": {"coordinates":[9.066667,54.566667],"type":"Point"}
}
=======
{"geometry":{"type":"Point","coordinates":[9.066667,54.566667]},"type":"Feature","properties":{"hierarchy":["tgn:7174167","tgn:1000003","tgn:7003688","tgn:7000084","tgn:7029392"],"placetype":["aat:300008347"],"id":7174167,"name:xx":"Gro\u00df Ahrensh\u00f6ft"}}
>>>>>>> 03f74aca74312dbeaf24d7e61306dd6a786dc3d0
