{
  "id": 7150886,
  "type": "Feature",
  "properties": {
    "tgn:hierarchy":[
        "tgn:7150886",
        "tgn:7000096",
        "tgn:1000003",
        "tgn:7000084",
        "tgn:7029392"
    ],
    "tgn:id":7150886,
    "tgn:name":"Laasow",
    "tgn:placetype":[
        "aat:300008347"
    ]
},
  "bbox": [],
  "geometry": {"coordinates":[14.083333,51.716667],"type":"Point"}
}