{
  "id": 1083561,
  "type": "Feature",
  "properties": {
    "tgn:hierarchy":[
        "tgn:1083561",
        "tgn:1000004",
        "tgn:1001490",
        "tgn:1000133",
        "tgn:7029392"
    ],
    "tgn:id":1083561,
    "tgn:name":"Kh\u0101ngarh",
    "tgn:placetype":[
        "aat:300008347"
    ]
},
  "bbox": [],
  "geometry": {"coordinates":[71.7167,28.3667],"type":"Point"}
}