{
  "id": 2129616,
  "type": "Feature",
  "properties": {
    "tgn:hierarchy":[
        "tgn:2129616",
        "tgn:1000001",
        "tgn:7006451",
        "tgn:7012149",
        "tgn:2000103",
        "tgn:7029392"
    ],
    "tgn:id":2129616,
    "tgn:name":"Alkali Spring",
    "tgn:placetype":[
        "aat:300008697"
    ]
},
  "bbox": [],
  "geometry": {"coordinates":[-112.3667,33.9833],"type":"Point"}
}