<<<<<<< HEAD
{
  "id": 7354439,
  "type": "Feature",
  "properties": {
    "tgn:hierarchy":[
        "tgn:7354439",
        "tgn:7005581",
        "tgn:1000001",
        "tgn:7005560",
        "tgn:7029392"
    ],
    "tgn:id":7354439,
    "tgn:name":"Charamuscas, Sierra",
    "tgn:placetype":[
        "aat:300008795"
    ]
},
  "bbox": [],
  "geometry": {"coordinates":[-107.266667,28.316667],"type":"Point"}
}
=======
{"geometry":{"type":"Point","coordinates":[-107.266667,28.316667]},"type":"Feature","properties":{"hierarchy":["tgn:7354439","tgn:7005581","tgn:1000001","tgn:7005560","tgn:7029392"],"placetype":["aat:300008795"],"id":7354439,"name:xx":"Charamuscas, Sierra"}}
>>>>>>> 03f74aca74312dbeaf24d7e61306dd6a786dc3d0
