{
  "id": 2540906,
  "type": "Feature",
  "properties": {
    "tgn:hierarchy":[
        "tgn:2540906",
        "tgn:1002169",
        "tgn:1000001",
        "tgn:7012149",
        "tgn:7007255",
        "tgn:7029392"
    ],
    "tgn:id":2540906,
    "tgn:name":"Nichols Branch",
    "tgn:placetype":[
        "aat:300008699"
    ]
},
  "bbox": [],
  "geometry": {"coordinates":[-83.6833,38.0167],"type":"Point"}
}