{
  "id": 7303741,
  "type": "Feature",
  "properties": {
    "tgn:hierarchy":[
        "tgn:7303741",
        "tgn:7002842",
        "tgn:7001158",
        "tgn:1000003",
        "tgn:1000095",
        "tgn:7029392"
    ],
    "tgn:id":7303741,
    "tgn:name":"Mor\u00f3n, R\u00edo",
    "tgn:placetype":[
        "aat:300008699"
    ]
},
  "bbox": [],
  "geometry": {"coordinates":[-2.55,41.483333],"type":"Point"}
}