{
  "id": 2319833,
  "type": "Feature",
  "properties": {
    "tgn:hierarchy":[
        "tgn:2319833",
        "tgn:1000001",
        "tgn:2002317",
        "tgn:7012149",
        "tgn:7007922",
        "tgn:7029392"
    ],
    "tgn:id":2319833,
    "tgn:name":"Europe Bay",
    "tgn:placetype":[
        "aat:300132316"
    ]
},
  "bbox": [],
  "geometry": {"coordinates":[-86.9667,45.25],"type":"Point"}
}