{
  "id": 2383069,
  "type": "Feature",
  "properties": {
    "tgn:hierarchy":[
        "tgn:2383069",
        "tgn:1000001",
        "tgn:7012149",
        "tgn:7007157",
        "tgn:1002675",
        "tgn:7029392"
    ],
    "tgn:id":2383069,
    "tgn:name":"Headley Peak",
    "tgn:placetype":[
        "aat:300008798"
    ]
},
  "bbox": [],
  "geometry": {"coordinates":[-118.2833,37.6833],"type":"Point"}
}