{
  "id": 2765036,
  "type": "Feature",
  "properties": {
    "tgn:hierarchy":[
        "tgn:2765036",
        "tgn:1000001",
        "tgn:7012149",
        "tgn:7029392"
    ],
    "tgn:id":2765036,
    "tgn:name":"Whisky Hollow",
    "tgn:placetype":[
        "aat:300008761"
    ]
},
  "bbox": [],
  "geometry": {"coordinates":[-90.55,42.5167],"type":"Point"}
}