<<<<<<< HEAD
{
  "id": 2765036,
  "type": "Feature",
  "properties": {
    "tgn:hierarchy":[
        "tgn:2765036",
        "tgn:1000001",
        "tgn:7012149",
        "tgn:7029392"
    ],
    "tgn:id":2765036,
    "tgn:name":"Whisky Hollow",
    "tgn:placetype":[
        "aat:300008761"
    ]
},
  "bbox": [],
  "geometry": {"coordinates":[-90.55,42.5167],"type":"Point"}
}
=======
{"geometry":{"type":"Point","coordinates":[-90.550000,42.516700]},"type":"Feature","properties":{"hierarchy":["tgn:2765036","tgn:1000001","tgn:7012149","tgn:7029392"],"placetype":["aat:300008761"],"id":2765036,"name:xx":"Whisky Hollow"}}
>>>>>>> 03f74aca74312dbeaf24d7e61306dd6a786dc3d0
