{
  "id": 6000390,
  "type": "Feature",
  "properties": {
    "tgn:hierarchy":[
        "tgn:6000390",
        "tgn:7001242",
        "tgn:1000176",
        "tgn:7029392"
    ],
    "tgn:id":6000390,
    "tgn:name":"Arguin, \u00cele de",
    "tgn:placetype":[
        "aat:300008791"
    ]
},
  "bbox": [],
  "geometry": {"coordinates":[-16.4667,20.4667],"type":"Point"}
}