{
  "id": 7449928,
  "type": "Feature",
  "properties": {
    "tgn:hierarchy":[
        "tgn:7449928",
        "tgn:7002444",
        "tgn:7008074",
        "tgn:1000003",
        "tgn:7008591",
        "tgn:7029392"
    ],
    "tgn:id":7449928,
    "tgn:name:en":"Fingland Lane",
    "tgn:placetype":[
        "aat:300008699"
    ]
},
  "bbox": [],
  "geometry": {"coordinates":[-4.116667,55.183333],"type":"Point"}
}