{
  "id": 7569083,
  "type": "Feature",
  "properties": {
    "tgn:hierarchy":[
        "tgn:7569083",
        "tgn:1001828",
        "tgn:1000004",
        "tgn:7000198",
        "tgn:7029392"
    ],
    "tgn:id":7569083,
    "tgn:name:en":"Far\u012bd\u0101b\u0101d",
    "tgn:placetype":[
        "aat:300008347"
    ]
},
  "bbox": [],
  "geometry": {"coordinates":[78.298333,17.359167],"type":"Point"}
}