{
  "id": 7171539,
  "type": "Feature",
  "properties": {
    "tgn:hierarchy":[
        "tgn:7171539",
        "tgn:7003669",
        "tgn:1000003",
        "tgn:7000084",
        "tgn:7029392"
    ],
    "tgn:id":7171539,
    "tgn:name":"Hirsch Berg",
    "tgn:placetype":[
        "aat:300008777"
    ]
},
  "bbox": [],
  "geometry": {"coordinates":[11.116667,49.566667],"type":"Point"}
}