<<<<<<< HEAD
{
  "id": 2763482,
  "type": "Feature",
  "properties": {
    "tgn:hierarchy":[
        "tgn:2763482",
        "tgn:1000001",
        "tgn:1002261",
        "tgn:7012149",
        "tgn:7007568",
        "tgn:7029392"
    ],
    "tgn:id":2763482,
    "tgn:name":"Weyer Pond",
    "tgn:placetype":[
        "aat:300008680"
    ]
},
  "bbox": [],
  "geometry": {"coordinates":[-76.8,42.1],"type":"Point"}
}
=======
{"geometry":{"type":"Point","coordinates":[-76.800000,42.100000]},"type":"Feature","properties":{"hierarchy":["tgn:2763482","tgn:1000001","tgn:1002261","tgn:7012149","tgn:7007568","tgn:7029392"],"placetype":["aat:300008680"],"id":2763482,"name:xx":"Weyer Pond"}}
>>>>>>> 03f74aca74312dbeaf24d7e61306dd6a786dc3d0
