{
  "id": 2175730,
  "type": "Feature",
  "properties": {
    "tgn:hierarchy":[
        "tgn:2175730",
        "tgn:1000001",
        "tgn:1002934",
        "tgn:7012149",
        "tgn:7007565",
        "tgn:7029392"
    ],
    "tgn:id":2175730,
    "tgn:name":"Black Creek",
    "tgn:placetype":[
        "aat:300008706"
    ]
},
  "bbox": [],
  "geometry": {"coordinates":[-74.5167,41.15],"type":"Point"}
}