{
  "id": 2657232,
  "type": "Feature",
  "properties": {
    "tgn:hierarchy":[
        "tgn:2657232",
        "tgn:1000001",
        "tgn:2001410",
        "tgn:7012149",
        "tgn:7007526",
        "tgn:7029392"
    ],
    "tgn:id":2657232,
    "tgn:name":"Sheep Spring",
    "tgn:placetype":[
        "aat:300008697"
    ]
},
  "bbox": [],
  "geometry": {"coordinates":[-115.5333,36.15],"type":"Point"}
}