{
  "id": 7531260,
  "type": "Feature",
  "properties": {
    "tgn:hierarchy":[
        "tgn:7531260",
        "tgn:7001242",
        "tgn:7016833",
        "tgn:7029392"
    ],
    "tgn:id":7531260,
    "tgn:name":"Sadd an Na'\u0101m, W\u0101d\u012b",
    "tgn:placetype":[
        "aat:300379998"
    ]
},
  "bbox": [],
  "geometry": {"coordinates":[31.741273,29.816707],"type":"Point"}
}