{
  "id": 2096841,
  "type": "Feature",
  "properties": {
    "tgn:hierarchy":[
        "tgn:2096841",
        "tgn:1000001",
        "tgn:7012149",
        "tgn:2001768",
        "tgn:7007712",
        "tgn:7029392"
    ],
    "tgn:id":2096841,
    "tgn:name":"Tuckertown",
    "tgn:placetype":[
        "aat:300008347",
        "aat:300387210"
    ]
},
  "bbox": [],
  "geometry": {"coordinates":[-81.4833,34.5167],"type":"Point"}
}