{
  "id": 2621906,
  "type": "Feature",
  "properties": {
    "tgn:hierarchy":[
        "tgn:2621906",
        "tgn:1000001",
        "tgn:7012149",
        "tgn:2001442",
        "tgn:7007566",
        "tgn:7029392"
    ],
    "tgn:id":2621906,
    "tgn:name":"Robert E. Lee",
    "tgn:placetype":[
        "aat:300000390"
    ]
},
  "bbox": [],
  "geometry": {"coordinates":[-105.75,33.75],"type":"Point"}
}