{
  "id": 2427916,
  "type": "Feature",
  "properties": {
    "tgn:hierarchy":[
        "tgn:2427916",
        "tgn:1000001",
        "tgn:7012149",
        "tgn:7018871",
        "tgn:7007920",
        "tgn:7029392"
    ],
    "tgn:id":2427916,
    "tgn:name":"Joy, Lake",
    "tgn:placetype":[
        "aat:300008680"
    ]
},
  "bbox": [],
  "geometry": {"coordinates":[-121.8667,47.6833],"type":"Point"}
}