{
  "id": 1030222,
  "type": "Feature",
  "properties": {
    "tgn:hierarchy":[
        "tgn:1030222",
        "tgn:7002445",
        "tgn:1000003",
        "tgn:7008153",
        "tgn:7008591",
        "tgn:7029392"
    ],
    "tgn:id":1030222,
    "tgn:name":"Oad Street",
    "tgn:placetype":[
        "aat:300008347"
    ]
},
  "bbox": [],
  "geometry": {"coordinates":[0.6833,51.3333],"type":"Point"}
}