{
  "id": 2286773,
  "type": "Feature",
  "properties": {
    "tgn:hierarchy":[
        "tgn:2286773",
        "tgn:1000001",
        "tgn:7012149",
        "tgn:2001709",
        "tgn:7007708",
        "tgn:7029392"
    ],
    "tgn:id":2286773,
    "tgn:name":"Diamond Swamp",
    "tgn:placetype":[
        "aat:300008905"
    ]
},
  "bbox": [],
  "geometry": {"coordinates":[-118.7833,43.0333],"type":"Point"}
}