{
  "id": 2668055,
  "type": "Feature",
  "properties": {
    "tgn:hierarchy":[
        "tgn:2668055",
        "tgn:1000001",
        "tgn:1002243",
        "tgn:7012149",
        "tgn:7007520",
        "tgn:7029392"
    ],
    "tgn:id":2668055,
    "tgn:name":"Skyhawk Lake",
    "tgn:placetype":[
        "aat:300008680"
    ]
},
  "bbox": [],
  "geometry": {"coordinates":[-85.8167,41.9833],"type":"Point"}
}