{
  "id": 7044443,
  "type": "Feature",
  "properties": {
    "tgn:hierarchy":[
        "tgn:7044443",
        "tgn:7003006",
        "tgn:1000003",
        "tgn:7002997",
        "tgn:1000080",
        "tgn:7029392"
    ],
    "tgn:id":7044443,
    "tgn:name":"Cantarana",
    "tgn:placetype":[
        "aat:300008347"
    ]
},
  "bbox": [],
  "geometry": {"coordinates":[12.099167,45.197222],"type":"Point"}
}