{
  "id": 7319293,
  "type": "Feature",
  "properties": {
    "tgn:hierarchy":[
        "tgn:7319293",
        "tgn:7002464",
        "tgn:1000049",
        "tgn:1000002",
        "tgn:7029392"
    ],
    "tgn:id":7319293,
    "tgn:name":"Ancha, Loma",
    "tgn:placetype":[
        "aat:300008795"
    ]
},
  "bbox": [],
  "geometry": {"coordinates":[-70.016667,-20.616667],"type":"Point"}
}