{
  "id": 7473246,
  "type": "Feature",
  "properties": {
    "tgn:hierarchy":[
        "tgn:7473246",
        "tgn:7001010",
        "tgn:1000004",
        "tgn:1000141",
        "tgn:7029392"
    ],
    "tgn:id":7473246,
    "tgn:name":"Yangqing Qiao",
    "tgn:placetype":[
        "aat:300007836"
    ]
},
  "bbox": [],
  "geometry": {"coordinates":[121.47264,23.977711],"type":"Point"}
}