<<<<<<< HEAD
{
  "id": 2258877,
  "type": "Feature",
  "properties": {
    "tgn:hierarchy":[
        "tgn:2258877",
        "tgn:1000001",
        "tgn:2001177",
        "tgn:7012149",
        "tgn:7007523",
        "tgn:7029392"
    ],
    "tgn:id":2258877,
    "tgn:name":"Cottonwood Creek",
    "tgn:placetype":[
        "aat:300008706"
    ]
},
  "bbox": [],
  "geometry": {"coordinates":[-93.9833,39.7333],"type":"Point"}
}
=======
{"geometry":{"type":"Point","coordinates":[-93.983300,39.733300]},"type":"Feature","properties":{"hierarchy":["tgn:2258877","tgn:1000001","tgn:2001177","tgn:7012149","tgn:7007523","tgn:7029392"],"placetype":["aat:300008706"],"id":2258877,"name:xx":"Cottonwood Creek"}}
>>>>>>> 03f74aca74312dbeaf24d7e61306dd6a786dc3d0
