{
  "id": 2551137,
  "type": "Feature",
  "properties": {
    "tgn:hierarchy":[
        "tgn:2551137",
        "tgn:1000001",
        "tgn:7012149",
        "tgn:1002521",
        "tgn:7007920",
        "tgn:7029392"
    ],
    "tgn:id":2551137,
    "tgn:name":"Noyes, Mount",
    "tgn:placetype":[
        "aat:300008798"
    ]
},
  "bbox": [],
  "geometry": {"coordinates":[-123.5833,47.7333],"type":"Point"}
}