{
  "id": 2781759,
  "type": "Feature",
  "properties": {
    "tgn:hierarchy":[
        "tgn:2781759",
        "tgn:1000001",
        "tgn:7012149",
        "tgn:2000227",
        "tgn:7007158",
        "tgn:7029392"
    ],
    "tgn:id":2781759,
    "tgn:name":"Woods Canyon",
    "tgn:placetype":[
        "aat:300008761"
    ]
},
  "bbox": [],
  "geometry": {"coordinates":[-107.2333,37.7667],"type":"Point"}
}