{
  "id": 7114994,
  "type": "Feature",
  "properties": {
    "tgn:hierarchy":[
        "tgn:7114994",
        "tgn:7003692",
        "tgn:1000003",
        "tgn:7000084",
        "tgn:7029392"
    ],
    "tgn:id":7114994,
    "tgn:name":"Oberrotenstein",
    "tgn:placetype":[
        "aat:300000206"
    ]
},
  "bbox": [],
  "geometry": {"coordinates":[8.583333,48.133333],"type":"Point"}
}