{
  "id": 7464130,
  "type": "Feature",
  "properties": {
    "tgn:hierarchy":[
        "tgn:7464130",
        "tgn:5000432",
        "tgn:7002444",
        "tgn:1000003",
        "tgn:7008591",
        "tgn:7029392"
    ],
    "tgn:id":7464130,
    "tgn:name:en":"Aldie",
    "tgn:placetype":[
        "aat:300008347"
    ]
},
  "bbox": [],
  "geometry": {"coordinates":[-1.883333,57.45],"type":"Point"}
}