{
  "id": 7475221,
  "type": "Feature",
  "properties": {
    "tgn:hierarchy":[
        "tgn:7475221",
        "tgn:1000004",
        "tgn:7490934",
        "tgn:1000141",
        "tgn:7029392"
    ],
    "tgn:id":7475221,
    "tgn:name":"Waqingzi",
    "tgn:placetype":[
        "aat:300008347"
    ]
},
  "bbox": [],
  "geometry": {"coordinates":[120.4175,23.343333],"type":"Point"}
}