<<<<<<< HEAD
{
  "id": 7475221,
  "type": "Feature",
  "properties": {
    "tgn:hierarchy":[
        "tgn:7475221",
        "tgn:1000004",
        "tgn:7490934",
        "tgn:1000141",
        "tgn:7029392"
    ],
    "tgn:id":7475221,
    "tgn:name":"Waqingzi",
    "tgn:placetype":[
        "aat:300008347"
    ]
},
  "bbox": [],
  "geometry": {"coordinates":[120.4175,23.343333],"type":"Point"}
}
=======
{"geometry":{"type":"Point","coordinates":[120.417500,23.343333]},"type":"Feature","properties":{"hierarchy":["tgn:7475221","tgn:1000004","tgn:7490934","tgn:1000141","tgn:7029392"],"placetype":["aat:300008347"],"id":7475221,"name:xx":"Waqingzi"}}
>>>>>>> 03f74aca74312dbeaf24d7e61306dd6a786dc3d0
