{
  "id": 7291433,
  "type": "Feature",
  "properties": {
    "tgn:hierarchy":[
        "tgn:7291433",
        "tgn:1001699",
        "tgn:1000049",
        "tgn:1000002",
        "tgn:7029392"
    ],
    "tgn:id":7291433,
    "tgn:name":"Err\u00e1zuriz, Bajo",
    "tgn:placetype":[
        "aat:300387036"
    ]
},
  "bbox": [],
  "geometry": {"coordinates":[-73.55,-43.266667],"type":"Point"}
}