{
  "id": 2185804,
  "type": "Feature",
  "properties": {
    "tgn:hierarchy":[
        "tgn:2185804",
        "tgn:1000001",
        "tgn:7016172",
        "tgn:7012149",
        "tgn:2000174",
        "tgn:7029392"
    ],
    "tgn:id":2185804,
    "tgn:name":"Bolding Lake",
    "tgn:placetype":[
        "aat:300008680"
    ]
},
  "bbox": [],
  "geometry": {"coordinates":[-92.1833,33.1167],"type":"Point"}
}