{
  "id": 2666843,
  "type": "Feature",
  "properties": {
    "tgn:hierarchy":[
        "tgn:2666843",
        "tgn:7006450",
        "tgn:1000001",
        "tgn:7012149",
        "tgn:7019760",
        "tgn:7029392"
    ],
    "tgn:id":2666843,
    "tgn:name":"Skagway River",
    "tgn:placetype":[
        "aat:300008707"
    ]
},
  "bbox": [],
  "geometry": {"coordinates":[-135.3167,59.4333],"type":"Point"}
}