{
  "id": 7268230,
  "type": "Feature",
  "properties": {
    "tgn:concordances":{
        "gn:id":"2750044"
    },
    "tgn:hierarchy":[
        "tgn:7268230",
        "tgn:1000003",
        "tgn:7003626",
        "tgn:7016845",
        "tgn:7029392"
    ],
    "tgn:id":7268230,
    "tgn:name:nl":"Nijstad",
    "tgn:placetype":[
        "aat:300008347"
    ]
},
  "bbox": [],
  "geometry": {"coordinates":[6.866667,52.35],"type":"Point"}
}