{
  "id": 1035782,
  "type": "Feature",
  "properties": {
    "tgn:hierarchy":[
        "tgn:1035782",
        "tgn:1000003",
        "tgn:7002883",
        "tgn:1000070",
        "tgn:7029392"
    ],
    "tgn:id":1035782,
    "tgn:name":"Stains",
    "tgn:placetype":[
        "aat:300008347"
    ]
},
  "bbox": [],
  "geometry": {"coordinates":[2.3667,48.95],"type":"Point"}
}