{
  "id": 2519236,
  "type": "Feature",
  "properties": {
    "tgn:hierarchy":[
        "tgn:2519236",
        "tgn:1000001",
        "tgn:2002255",
        "tgn:7012149",
        "tgn:7013961",
        "tgn:7029392"
    ],
    "tgn:id":2519236,
    "tgn:name":"Moccasin Hollow",
    "tgn:placetype":[
        "aat:300008761"
    ]
},
  "bbox": [],
  "geometry": {"coordinates":[-81.4667,38.05],"type":"Point"}
}