{
  "id": 1005466,
  "type": "Feature",
  "properties": {
    "tgn:hierarchy":[
        "tgn:1005466",
        "tgn:7001242",
        "tgn:7017576",
        "tgn:1000193",
        "tgn:7029392"
    ],
    "tgn:id":1005466,
    "tgn:name":"Rosettenville",
    "tgn:placetype":[
        "aat:300000745"
    ]
},
  "bbox": [],
  "geometry": {"coordinates":[28.05,-26.25],"type":"Point"}
}