{
  "id": 2200741,
  "type": "Feature",
  "properties": {
    "tgn:hierarchy":[
        "tgn:2200741",
        "tgn:7006450",
        "tgn:1000001",
        "tgn:7012149",
        "tgn:2000089",
        "tgn:7029392"
    ],
    "tgn:id":2200741,
    "tgn:name":"Bryan Creek",
    "tgn:placetype":[
        "aat:300008706"
    ]
},
  "bbox": [],
  "geometry": {"coordinates":[-156.8167,63.3667],"type":"Point"}
}