{
  "id": 2171463,
  "type": "Feature",
  "properties": {
    "tgn:hierarchy":[
        "tgn:2171463",
        "tgn:1000001",
        "tgn:7012149",
        "tgn:2000987",
        "tgn:7007520",
        "tgn:7029392"
    ],
    "tgn:id":2171463,
    "tgn:name":"Big Stone Creek",
    "tgn:placetype":[
        "aat:300008706"
    ]
},
  "bbox": [],
  "geometry": {"coordinates":[-85.25,43.8167],"type":"Point"}
}