{
  "id": 7059364,
  "type": "Feature",
  "properties": {
    "tgn:hierarchy":[
        "tgn:7059364",
        "tgn:1000003",
        "tgn:7003682",
        "tgn:7000084",
        "tgn:7029392"
    ],
    "tgn:id":7059364,
    "tgn:name":"Allmesch",
    "tgn:placetype":[
        "aat:300266640"
    ]
},
  "bbox": [],
  "geometry": {"coordinates":[7.283333,50.166667],"type":"Point"}
}