<<<<<<< HEAD
{
  "id": 7023976,
  "type": "Feature",
  "properties": {
    "tgn:hierarchy":[
        "tgn:7023976",
        "tgn:1000001",
        "tgn:7012149",
        "tgn:7019676",
        "tgn:7007566",
        "tgn:7029392"
    ],
    "tgn:id":7023976,
    "tgn:name":"Alejandro, Laguna de",
    "tgn:placetype":[
        "aat:300008680",
        "aat:300006191"
    ]
},
  "bbox": [],
  "geometry": {"coordinates":[-107.4333,35.4],"type":"Point"}
}
=======
{"geometry":{"type":"Point","coordinates":[-107.433300,35.400000]},"type":"Feature","properties":{"hierarchy":["tgn:7023976","tgn:1000001","tgn:7012149","tgn:7019676","tgn:7007566","tgn:7029392"],"placetype":["aat:300008680","aat:300006191"],"id":7023976,"name:xx":"Alejandro, Laguna de"}}
>>>>>>> 03f74aca74312dbeaf24d7e61306dd6a786dc3d0
