<<<<<<< HEAD
{
  "id": 7058806,
  "type": "Feature",
  "properties": {
    "tgn:hierarchy":[
        "tgn:7058806",
        "tgn:7003127",
        "tgn:7004847",
        "tgn:1000003",
        "tgn:7008516",
        "tgn:1000080",
        "tgn:7029392"
    ],
    "tgn:id":7058806,
    "tgn:name":"Stazione Bologna Ravone",
    "tgn:placetype":[
        "aat:300007783"
    ]
},
  "bbox": [],
  "geometry": {"coordinates":[11.316667,44.5],"type":"Point"}
}
=======
{"geometry":{"type":"Point","coordinates":[11.316667,44.500000]},"type":"Feature","properties":{"hierarchy":["tgn:7058806","tgn:7003127","tgn:7004847","tgn:1000003","tgn:7008516","tgn:1000080","tgn:7029392"],"placetype":["aat:300007783"],"id":7058806,"name:xx":"Stazione Bologna Ravone"}}
>>>>>>> 03f74aca74312dbeaf24d7e61306dd6a786dc3d0
