<<<<<<< HEAD
{
  "id": 2332912,
  "type": "Feature",
  "properties": {
    "tgn:hierarchy":[
        "tgn:2332912",
        "tgn:1000001",
        "tgn:2001424",
        "tgn:7012149",
        "tgn:7007564",
        "tgn:7029392"
    ],
    "tgn:id":2332912,
    "tgn:name":"Flume Brook",
    "tgn:placetype":[
        "aat:300008699"
    ]
},
  "bbox": [],
  "geometry": {"coordinates":[-71.6333,44.1],"type":"Point"}
}
=======
{"geometry":{"type":"Point","coordinates":[-71.633300,44.100000]},"type":"Feature","properties":{"hierarchy":["tgn:2332912","tgn:1000001","tgn:2001424","tgn:7012149","tgn:7007564","tgn:7029392"],"placetype":["aat:300008699"],"id":2332912,"name:xx":"Flume Brook"}}
>>>>>>> 03f74aca74312dbeaf24d7e61306dd6a786dc3d0
