{
  "id": 2531189,
  "type": "Feature",
  "properties": {
    "tgn:hierarchy":[
        "tgn:2531189",
        "tgn:1000001",
        "tgn:7012149",
        "tgn:2002037",
        "tgn:7007826",
        "tgn:7029392"
    ],
    "tgn:id":2531189,
    "tgn:name":"Mulberry Creek",
    "tgn:placetype":[
        "aat:300008706"
    ]
},
  "bbox": [],
  "geometry": {"coordinates":[-99.0667,30.7167],"type":"Point"}
}