{
  "id": 1123714,
  "type": "Feature",
  "properties": {
    "tgn:hierarchy":[
        "tgn:1123714",
        "tgn:1000001",
        "tgn:2001567",
        "tgn:7012149",
        "tgn:7007705",
        "tgn:7029392"
    ],
    "tgn:id":1123714,
    "tgn:name":"Elm",
    "tgn:placetype":[
        "aat:300008707"
    ]
},
  "bbox": [],
  "geometry": {"coordinates":[-98.8667,46.1333],"type":"Point"}
}