{
  "id": 7218307,
  "type": "Feature",
  "properties": {
    "tgn:hierarchy":[
        "tgn:7218307",
        "tgn:7002748",
        "tgn:7001399",
        "tgn:1000003",
        "tgn:1000074",
        "tgn:7029392"
    ],
    "tgn:id":7218307,
    "tgn:name":"Xinon\u00e9rion",
    "tgn:placetype":[
        "aat:300008347"
    ]
},
  "bbox": [],
  "geometry": {"coordinates":[21.859167,39.3175],"type":"Point"}
}