{
  "id": 2715334,
  "type": "Feature",
  "properties": {
    "tgn:hierarchy":[
        "tgn:2715334",
        "tgn:1000001",
        "tgn:7012149",
        "tgn:2002288",
        "tgn:7013961",
        "tgn:7029392"
    ],
    "tgn:id":2715334,
    "tgn:name":"Terra Alta Lake",
    "tgn:placetype":[
        "aat:300006191"
    ]
},
  "bbox": [],
  "geometry": {"coordinates":[-79.5167,39.45],"type":"Point"}
}