{
  "id": 7351803,
  "type": "Feature",
  "properties": {
    "tgn:hierarchy":[
        "tgn:7351803",
        "tgn:1000001",
        "tgn:7005597",
        "tgn:7005560",
        "tgn:7029392"
    ],
    "tgn:id":7351803,
    "tgn:name":"Barra",
    "tgn:placetype":[
        "aat:300008347"
    ]
},
  "bbox": [],
  "geometry": {"coordinates":[-97.783333,22.983333],"type":"Point"}
}