{
  "id": 1080181,
  "type": "Feature",
  "properties": {
    "tgn:hierarchy":[
        "tgn:1080181",
        "tgn:1000993",
        "tgn:1000004",
        "tgn:7000901",
        "tgn:1000120",
        "tgn:7029392"
    ],
    "tgn:id":1080181,
    "tgn:name":"Ibusuki",
    "tgn:placetype":[
        "aat:300008347"
    ]
},
  "bbox": [],
  "geometry": {"coordinates":[130.6667,31.25],"type":"Point"}
}