{
  "id": 2254723,
  "type": "Feature",
  "properties": {
    "tgn:hierarchy":[
        "tgn:2254723",
        "tgn:1000001",
        "tgn:7012149",
        "tgn:1002701",
        "tgn:7007706",
        "tgn:7029392"
    ],
    "tgn:id":2254723,
    "tgn:name":"Coon Ridge",
    "tgn:placetype":[
        "aat:300266640"
    ]
},
  "bbox": [],
  "geometry": {"coordinates":[-81.85,39.8667],"type":"Point"}
}