{
  "id": 1075535,
  "type": "Feature",
  "properties": {
    "tgn:hierarchy":[
        "tgn:1075535",
        "tgn:1000004",
        "tgn:1001871",
        "tgn:7000198",
        "tgn:7029392"
    ],
    "tgn:id":1075535,
    "tgn:name":"Jakhal",
    "tgn:placetype":[
        "aat:300008347"
    ]
},
  "bbox": [],
  "geometry": {"coordinates":[75.823922,29.796274],"type":"Point"}
}