<<<<<<< HEAD
{
  "id": 7057408,
  "type": "Feature",
  "properties": {
    "tgn:hierarchy":[
        "tgn:7057408",
        "tgn:7003011",
        "tgn:7003005",
        "tgn:1000003",
        "tgn:1000080",
        "tgn:7029392"
    ],
    "tgn:id":7057408,
    "tgn:name":"Ausonia",
    "tgn:placetype":[
        "aat:300008347"
    ]
},
  "bbox": [],
  "geometry": {"coordinates":[13.75,41.35],"type":"Point"}
}
=======
{"geometry":{"type":"Point","coordinates":[13.750000,41.350000]},"type":"Feature","properties":{"hierarchy":["tgn:7057408","tgn:7003011","tgn:7003005","tgn:1000003","tgn:1000080","tgn:7029392"],"placetype":["aat:300008347"],"id":7057408,"name:xx":"Ausonia"}}
>>>>>>> 03f74aca74312dbeaf24d7e61306dd6a786dc3d0
