{
  "id": 7288332,
  "type": "Feature",
  "properties": {
    "tgn:hierarchy":[
        "tgn:7288332",
        "tgn:7002464",
        "tgn:1000049",
        "tgn:1000002",
        "tgn:7029392"
    ],
    "tgn:id":7288332,
    "tgn:name":"Lacataya, Cerro",
    "tgn:placetype":[
        "aat:300008795"
    ]
},
  "bbox": [],
  "geometry": {"coordinates":[-68.416667,-19.433333],"type":"Point"}
}