{
  "id": 1104936,
  "type": "Feature",
  "properties": {
    "tgn:hierarchy":[
        "tgn:1104936",
        "tgn:7003029",
        "tgn:1000003",
        "tgn:1000062",
        "tgn:7029392"
    ],
    "tgn:id":1104936,
    "tgn:name":"Hochvoget",
    "tgn:placetype":[
        "aat:300008795"
    ]
},
  "bbox": [],
  "geometry": {"coordinates":[10.4333,47.3833],"type":"Point"}
}