{
  "id": 7381285,
  "type": "Feature",
  "properties": {
    "tgn:hierarchy":[
        "tgn:7381285",
        "tgn:7005583",
        "tgn:1000001",
        "tgn:7005560",
        "tgn:7029392"
    ],
    "tgn:id":7381285,
    "tgn:name":"Rancho de los Mendez",
    "tgn:placetype":[
        "aat:300000241"
    ]
},
  "bbox": [],
  "geometry": {"coordinates":[-105.85,26.583333],"type":"Point"}
}