{
  "id": 2258644,
  "type": "Feature",
  "properties": {
    "tgn:hierarchy":[
        "tgn:2258644",
        "tgn:1000001",
        "tgn:7012149",
        "tgn:2002026",
        "tgn:7007826",
        "tgn:7029392"
    ],
    "tgn:id":2258644,
    "tgn:name":"Cottonwood Branch",
    "tgn:placetype":[
        "aat:300008699"
    ]
},
  "bbox": [],
  "geometry": {"coordinates":[-98.45,31.25],"type":"Point"}
}