<<<<<<< HEAD
{
  "id": 2155064,
  "type": "Feature",
  "properties": {
    "tgn:hierarchy":[
        "tgn:2155064",
        "tgn:1000001",
        "tgn:2000953",
        "tgn:7012149",
        "tgn:7007520",
        "tgn:7029392"
    ],
    "tgn:id":2155064,
    "tgn:name":"Bear Lake",
    "tgn:placetype":[
        "aat:300008680"
    ]
},
  "bbox": [],
  "geometry": {"coordinates":[-84.95,43.8833],"type":"Point"}
}
=======
{"geometry":{"type":"Point","coordinates":[-84.950000,43.883300]},"type":"Feature","properties":{"hierarchy":["tgn:2155064","tgn:1000001","tgn:2000953","tgn:7012149","tgn:7007520","tgn:7029392"],"placetype":["aat:300008680"],"id":2155064,"name:xx":"Bear Lake"}}
>>>>>>> 03f74aca74312dbeaf24d7e61306dd6a786dc3d0
