{
  "id": 2433606,
  "type": "Feature",
  "properties": {
    "tgn:hierarchy":[
        "tgn:2433606",
        "tgn:1000001",
        "tgn:7012149",
        "tgn:2001716",
        "tgn:7007708",
        "tgn:7029392"
    ],
    "tgn:id":2433606,
    "tgn:name":"Kelly Butte",
    "tgn:placetype":[
        "aat:300008798"
    ]
},
  "bbox": [],
  "geometry": {"coordinates":[-123.0167,44.05],"type":"Point"}
}