{
  "id": 2430801,
  "type": "Feature",
  "properties": {
    "tgn:hierarchy":[
        "tgn:2430801",
        "tgn:1000001",
        "tgn:7006451",
        "tgn:2000091",
        "tgn:7012149",
        "tgn:7029392"
    ],
    "tgn:id":2430801,
    "tgn:name":"Kambitsch Tank",
    "tgn:placetype":[
        "aat:300006191"
    ]
},
  "bbox": [],
  "geometry": {"coordinates":[-109.1667,31.75],"type":"Point"}
}