<<<<<<< HEAD
{
  "id": 2766447,
  "type": "Feature",
  "properties": {
    "tgn:hierarchy":[
        "tgn:2766447",
        "tgn:1000001",
        "tgn:7012149",
        "tgn:1002879",
        "tgn:7007252",
        "tgn:7029392"
    ],
    "tgn:id":2766447,
    "tgn:name":"White Oak Branch",
    "tgn:placetype":[
        "aat:300008699"
    ]
},
  "bbox": [],
  "geometry": {"coordinates":[-85.7,38.7667],"type":"Point"}
}
=======
{"geometry":{"type":"Point","coordinates":[-85.700000,38.766700]},"type":"Feature","properties":{"hierarchy":["tgn:2766447","tgn:1000001","tgn:7012149","tgn:1002879","tgn:7007252","tgn:7029392"],"placetype":["aat:300008699"],"id":2766447,"name:xx":"White Oak Branch"}}
>>>>>>> 03f74aca74312dbeaf24d7e61306dd6a786dc3d0
