{
  "id": 7442604,
  "type": "Feature",
  "properties": {
    "tgn:hierarchy":[
        "tgn:7442604",
        "tgn:7002445",
        "tgn:1000003",
        "tgn:7008185",
        "tgn:7008591",
        "tgn:7029392"
    ],
    "tgn:id":7442604,
    "tgn:name:en":"Corton Road",
    "tgn:placetype":[
        "aat:300386968"
    ]
},
  "bbox": [],
  "geometry": {"coordinates":[1.766667,52.516667],"type":"Point"}
}