{
  "id": 7167954,
  "type": "Feature",
  "properties": {
    "tgn:hierarchy":[
        "tgn:7167954",
        "tgn:7003669",
        "tgn:1000003",
        "tgn:7000084",
        "tgn:7029392"
    ],
    "tgn:id":7167954,
    "tgn:name":"Heimatshausen",
    "tgn:placetype":[
        "aat:300008347"
    ]
},
  "bbox": [],
  "geometry": {"coordinates":[11.033333,48.366667],"type":"Point"}
}