{
  "id": 2117200,
  "type": "Feature",
  "properties": {
    "tgn:hierarchy":[
        "tgn:2117200",
        "tgn:1000001",
        "tgn:7012149",
        "tgn:2002291",
        "tgn:7013961",
        "tgn:7029392"
    ],
    "tgn:id":2117200,
    "tgn:name":"Aggregates",
    "tgn:placetype":[
        "aat:300008347",
        "aat:300387210"
    ]
},
  "bbox": [],
  "geometry": {"coordinates":[-79.9167,38.9333],"type":"Point"}
}