{
  "id": 7220380,
  "type": "Feature",
  "properties": {
    "tgn:hierarchy":[
        "tgn:7220380",
        "tgn:7002748",
        "tgn:7001399",
        "tgn:1000003",
        "tgn:1000074",
        "tgn:7029392"
    ],
    "tgn:id":7220380,
    "tgn:name":"Zaman\u00e1tiko",
    "tgn:placetype":[
        "aat:300008347"
    ]
},
  "bbox": [],
  "geometry": {"coordinates":[21.589444,39.346389],"type":"Point"}
}