{
  "id": 7385291,
  "type": "Feature",
  "properties": {
    "tgn:hierarchy":[
        "tgn:7385291",
        "tgn:1000001",
        "tgn:1001960",
        "tgn:7005560",
        "tgn:7029392"
    ],
    "tgn:id":7385291,
    "tgn:name":"Palmita",
    "tgn:placetype":[
        "aat:300008347"
    ]
},
  "bbox": [],
  "geometry": {"coordinates":[-110.983333,28.133333],"type":"Point"}
}