{
  "id": 2780849,
  "type": "Feature",
  "properties": {
    "tgn:hierarchy":[
        "tgn:2780849",
        "tgn:7006450",
        "tgn:1000001",
        "tgn:7019698",
        "tgn:7012149",
        "tgn:7029392"
    ],
    "tgn:id":2780849,
    "tgn:name":"Woodard Canyon",
    "tgn:placetype":[
        "aat:300008761"
    ]
},
  "bbox": [],
  "geometry": {"coordinates":[-151.5333,59.65],"type":"Point"}
}