{
  "id": 2100124,
  "type": "Feature",
  "properties": {
    "tgn:hierarchy":[
        "tgn:2100124",
        "tgn:1000001",
        "tgn:7012149",
        "tgn:2001926",
        "tgn:7007825",
        "tgn:7029392"
    ],
    "tgn:id":2100124,
    "tgn:name":"Locust Mount",
    "tgn:placetype":[
        "aat:300008347",
        "aat:300387210"
    ]
},
  "bbox": [],
  "geometry": {"coordinates":[-82.5667,36.3333],"type":"Point"}
}