{
  "id": 2426589,
  "type": "Feature",
  "properties": {
    "tgn:hierarchy":[
        "tgn:2426589",
        "tgn:2002138",
        "tgn:1000001",
        "tgn:7012149",
        "tgn:7007919",
        "tgn:7029392"
    ],
    "tgn:id":2426589,
    "tgn:name":"Jones Hollow",
    "tgn:placetype":[
        "aat:300008761"
    ]
},
  "bbox": [],
  "geometry": {"coordinates":[-80.1333,37.8833],"type":"Point"}
}