{
  "id": 2276541,
  "type": "Feature",
  "properties": {
    "tgn:hierarchy":[
        "tgn:2276541",
        "tgn:1000001",
        "tgn:7012149",
        "tgn:2001280",
        "tgn:7007524",
        "tgn:7029392"
    ],
    "tgn:id":2276541,
    "tgn:name":"Daveys Coulee",
    "tgn:placetype":[
        "aat:300008761"
    ]
},
  "bbox": [],
  "geometry": {"coordinates":[-109.4833,48.4667],"type":"Point"}
}