{
  "id": 7229874,
  "type": "Feature",
  "properties": {
    "tgn:hierarchy":[
        "tgn:7229874",
        "tgn:7002743",
        "tgn:7017076",
        "tgn:1000003",
        "tgn:1000074",
        "tgn:7029392"
    ],
    "tgn:id":7229874,
    "tgn:name":"K\u00e1peli",
    "tgn:placetype":[
        "aat:300008347"
    ]
},
  "bbox": [],
  "geometry": {"coordinates":[21.55,38.133333],"type":"Point"}
}