<<<<<<< HEAD
{
  "id": 7175681,
  "type": "Feature",
  "properties": {
    "tgn:hierarchy":[
        "tgn:7175681",
        "tgn:1000003",
        "tgn:7003685",
        "tgn:7000084",
        "tgn:7029392"
    ],
    "tgn:id":7175681,
    "tgn:name":"Gro\u00dfes Horn",
    "tgn:placetype":[
        "aat:300008777"
    ]
},
  "bbox": [],
  "geometry": {"coordinates":[13.966667,50.866667],"type":"Point"}
}
=======
{"geometry":{"type":"Point","coordinates":[13.966667,50.866667]},"type":"Feature","properties":{"hierarchy":["tgn:7175681","tgn:1000003","tgn:7003685","tgn:7000084","tgn:7029392"],"placetype":["aat:300008777"],"id":7175681,"name:xx":"Gro\u00dfes Horn"}}
>>>>>>> 03f74aca74312dbeaf24d7e61306dd6a786dc3d0
