{
  "id": 7175681,
  "type": "Feature",
  "properties": {
    "tgn:hierarchy":[
        "tgn:7175681",
        "tgn:1000003",
        "tgn:7003685",
        "tgn:7000084",
        "tgn:7029392"
    ],
    "tgn:id":7175681,
    "tgn:name":"Gro\u00dfes Horn",
    "tgn:placetype":[
        "aat:300008777"
    ]
},
  "bbox": [],
  "geometry": {"coordinates":[13.966667,50.866667],"type":"Point"}
}