{
  "id": 1110074,
  "type": "Feature",
  "properties": {
    "tgn:hierarchy":[
        "tgn:1110074",
        "tgn:1000004",
        "tgn:7000198",
        "tgn:1001895",
        "tgn:7029392"
    ],
    "tgn:id":1110074,
    "tgn:name":"Mah\u0101deo Range",
    "tgn:placetype":[
        "aat:300386831",
        "aat:300008795"
    ]
},
  "bbox": [],
  "geometry": {"coordinates":[74.25,17.833333],"type":"Point"}
}