{
  "id": 2567428,
  "type": "Feature",
  "properties": {
    "tgn:hierarchy":[
        "tgn:2567428",
        "tgn:7023902",
        "tgn:1000001",
        "tgn:7012149",
        "tgn:7007249",
        "tgn:7029392"
    ],
    "tgn:id":2567428,
    "tgn:name":"Papalekoki",
    "tgn:placetype":[
        "aat:300008798"
    ]
},
  "bbox": [],
  "geometry": {"coordinates":[-155.4833,19.8667],"type":"Point"}
}