{
  "id": 7573584,
  "type": "Feature",
  "properties": {
    "tgn:hierarchy":[
        "tgn:7573584",
        "tgn:1000004",
        "tgn:7000198",
        "tgn:1001895",
        "tgn:7029392"
    ],
    "tgn:id":7573584,
    "tgn:name:en":"Gurbhela",
    "tgn:placetype":[
        "aat:300008347"
    ]
},
  "bbox": [],
  "geometry": {"coordinates":[80.55,20.416667],"type":"Point"}
}