{
  "id": 2647893,
  "type": "Feature",
  "properties": {
    "tgn:hierarchy":[
        "tgn:2647893",
        "tgn:1002300",
        "tgn:1000001",
        "tgn:7012149",
        "tgn:7007564",
        "tgn:7029392"
    ],
    "tgn:id":2647893,
    "tgn:name":"Schoolhouse Brook",
    "tgn:placetype":[
        "aat:300008699"
    ]
},
  "bbox": [],
  "geometry": {"coordinates":[-71.5167,44.7833],"type":"Point"}
}