{
  "id": 2730250,
  "type": "Feature",
  "properties": {
    "tgn:hierarchy":[
        "tgn:2730250",
        "tgn:1000001",
        "tgn:2000467",
        "tgn:7012149",
        "tgn:7007250",
        "tgn:7029392"
    ],
    "tgn:id":2730250,
    "tgn:name":"Trout Spring",
    "tgn:placetype":[
        "aat:300008697"
    ]
},
  "bbox": [],
  "geometry": {"coordinates":[-114.1667,42.0667],"type":"Point"}
}