{
  "id": 7569917,
  "type": "Feature",
  "properties": {
    "tgn:hierarchy":[
        "tgn:7569917",
        "tgn:1000004",
        "tgn:7000198",
        "tgn:7016788",
        "tgn:7029392"
    ],
    "tgn:id":7569917,
    "tgn:name:en":"Toda ka Gothra",
    "tgn:placetype":[
        "aat:300008347"
    ]
},
  "bbox": [],
  "geometry": {"coordinates":[75.601751,25.691769],"type":"Point"}
}