{
  "id": 7228273,
  "type": "Feature",
  "properties": {
    "tgn:hierarchy":[
        "tgn:7228273",
        "tgn:7002707",
        "tgn:7002705",
        "tgn:1000003",
        "tgn:1000074",
        "tgn:7029392"
    ],
    "tgn:id":7228273,
    "tgn:name":"Lyk\u00f3rrachi",
    "tgn:placetype":[
        "aat:300008347"
    ]
},
  "bbox": [],
  "geometry": {"coordinates":[20.898611,40.264444],"type":"Point"}
}