{
  "id": 7202281,
  "type": "Feature",
  "properties": {
    "tgn:hierarchy":[
        "tgn:7202281",
        "tgn:1000003",
        "tgn:7003678",
        "tgn:7000084",
        "tgn:7029392"
    ],
    "tgn:id":7202281,
    "tgn:name":"Breitenbrunn",
    "tgn:placetype":[
        "aat:300008347"
    ]
},
  "bbox": [],
  "geometry": {"coordinates":[9.067778,49.767778],"type":"Point"}
}