{
  "id": 2564265,
  "type": "Feature",
  "properties": {
    "tgn:hierarchy":[
        "tgn:2564265",
        "tgn:1000001",
        "tgn:7006451",
        "tgn:7012149",
        "tgn:2000100",
        "tgn:7029392"
    ],
    "tgn:id":2564265,
    "tgn:name":"Pablos Charco Reservoir",
    "tgn:placetype":[
        "aat:300006191"
    ]
},
  "bbox": [],
  "geometry": {"coordinates":[-112.0667,31.8667],"type":"Point"}
}