{
  "id": 1050188,
  "type": "Feature",
  "properties": {
    "tgn:hierarchy":[
        "tgn:1050188",
        "tgn:1000344",
        "tgn:1000003",
        "tgn:1000091",
        "tgn:7029392"
    ],
    "tgn:id":1050188,
    "tgn:name":"Miersig",
    "tgn:placetype":[
        "aat:300008347"
    ]
},
  "bbox": [],
  "geometry": {"coordinates":[21.85,46.8833],"type":"Point"}
}