{
  "id": 7471449,
  "type": "Feature",
  "properties": {
    "tgn:hierarchy":[
        "tgn:7471449",
        "tgn:7488858",
        "tgn:1000004",
        "tgn:1000141",
        "tgn:7029392"
    ],
    "tgn:id":7471449,
    "tgn:name":"Houdong Shan",
    "tgn:placetype":[
        "aat:300008798"
    ]
},
  "bbox": [],
  "geometry": {"coordinates":[120.968016,24.055752],"type":"Point"}
}