{
  "id": 2492638,
  "type": "Feature",
  "properties": {
    "tgn:hierarchy":[
        "tgn:2492638",
        "tgn:1000001",
        "tgn:7012149",
        "tgn:7019676",
        "tgn:7007566",
        "tgn:7029392"
    ],
    "tgn:id":2492638,
    "tgn:name":"Marinelli Pit",
    "tgn:placetype":[
        "aat:300000390"
    ]
},
  "bbox": [],
  "geometry": {"coordinates":[-108.0333,35.4167],"type":"Point"}
}