{
  "id": 7228261,
  "type": "Feature",
  "properties": {
    "tgn:hierarchy":[
        "tgn:7228261",
        "tgn:7002735",
        "tgn:7017076",
        "tgn:1000003",
        "tgn:1000074",
        "tgn:7029392"
    ],
    "tgn:id":7228261,
    "tgn:name":"Lik\u00f3trafos",
    "tgn:placetype":[
        "aat:300008347"
    ]
},
  "bbox": [],
  "geometry": {"coordinates":[21.95,37.05],"type":"Point"}
}