{
  "id": 7140404,
  "type": "Feature",
  "properties": {
    "tgn:hierarchy":[
        "tgn:7140404",
        "tgn:1000003",
        "tgn:7003676",
        "tgn:7000084",
        "tgn:7029392"
    ],
    "tgn:id":7140404,
    "tgn:name":"Lutterhausen",
    "tgn:placetype":[
        "aat:300008347"
    ]
},
  "bbox": [],
  "geometry": {"coordinates":[9.85,51.65],"type":"Point"}
}