{
  "id": 7260051,
  "type": "Feature",
  "properties": {
    "tgn:hierarchy":[
        "tgn:7260051",
        "tgn:1000003",
        "tgn:7003626",
        "tgn:7016845",
        "tgn:7029392"
    ],
    "tgn:id":7260051,
    "tgn:name:nl":"Goor",
    "tgn:placetype":[
        "aat:300008688"
    ]
},
  "bbox": [],
  "geometry": {"coordinates":[7.016667,52.366667],"type":"Point"}
}