{
  "id": 2669470,
  "type": "Feature",
  "properties": {
    "tgn:hierarchy":[
        "tgn:2669470",
        "tgn:1000001",
        "tgn:7012149",
        "tgn:7007158",
        "tgn:2000243",
        "tgn:7029392"
    ],
    "tgn:id":2669470,
    "tgn:name":"Slide Creek",
    "tgn:placetype":[
        "aat:300008706"
    ]
},
  "bbox": [],
  "geometry": {"coordinates":[-107.3667,40.1167],"type":"Point"}
}