{
  "id": 7013812,
  "type": "Feature",
  "properties": {
    "tgn:hierarchy":[
        "tgn:7013812",
        "tgn:1000001",
        "tgn:1002219",
        "tgn:7012149",
        "tgn:7007157",
        "tgn:7029392"
    ],
    "tgn:id":7013812,
    "tgn:name":"Jenny Lind",
    "tgn:placetype":[
        "aat:300008347",
        "aat:300387210"
    ]
},
  "bbox": [],
  "geometry": {"coordinates":[-120.8667,38.0833],"type":"Point"}
}