{
  "id": 7282321,
  "type": "Feature",
  "properties": {
    "tgn:hierarchy":[
        "tgn:7282321",
        "tgn:1001702",
        "tgn:1000049",
        "tgn:1000002",
        "tgn:7029392"
    ],
    "tgn:id":7282321,
    "tgn:name":"Promontorio, Punta",
    "tgn:placetype":[
        "aat:300386846"
    ]
},
  "bbox": [],
  "geometry": {"coordinates":[-72.666667,-53.35],"type":"Point"}
}