{
  "id": 2481051,
  "type": "Feature",
  "properties": {
    "tgn:hierarchy":[
        "tgn:2481051",
        "tgn:7014201",
        "tgn:1000001",
        "tgn:7012149",
        "tgn:7007239",
        "tgn:7029392"
    ],
    "tgn:id":2481051,
    "tgn:name":"Lamatan I",
    "tgn:placetype":[
        "aat:300008347"
    ]
},
  "bbox": [],
  "geometry": {"coordinates":[-75.7333,39.75],"type":"Point"}
}