{
  "id": 7528240,
  "type": "Feature",
  "properties": {
    "tgn:hierarchy":[
        "tgn:7528240",
        "tgn:7001242",
        "tgn:7016833",
        "tgn:1001123",
        "tgn:7029392"
    ],
    "tgn:id":7528240,
    "tgn:name":"Sitt al Ban\u0101t, Ra's",
    "tgn:placetype":[
        "aat:300008850"
    ]
},
  "bbox": [],
  "geometry": {"coordinates":[32.084167,31.183333],"type":"Point"}
}