{
  "id": 2377147,
  "type": "Feature",
  "properties": {
    "tgn:hierarchy":[
        "tgn:2377147",
        "tgn:1000001",
        "tgn:7012149",
        "tgn:1002974",
        "tgn:7007251",
        "tgn:7029392"
    ],
    "tgn:id":2377147,
    "tgn:name":"Harmattan Strip Mine",
    "tgn:placetype":[
        "aat:300000390"
    ]
},
  "bbox": [],
  "geometry": {"coordinates":[-87.6833,40.1333],"type":"Point"}
}