{
  "id": 1095320,
  "type": "Feature",
  "properties": {
    "tgn:hierarchy":[
        "tgn:1095320",
        "tgn:7001242",
        "tgn:7016833",
        "tgn:1001113",
        "tgn:7029392"
    ],
    "tgn:id":1095320,
    "tgn:name":"Al-Qa\u1e6d\u1e6d\u0101w\u012byah",
    "tgn:placetype":[
        "aat:300008347"
    ]
},
  "bbox": [],
  "geometry": {"coordinates":[31.662402,30.54985],"type":"Point"}
}