{
  "id": 7197440,
  "type": "Feature",
  "properties": {
    "tgn:hierarchy":[
        "tgn:7197440",
        "tgn:1000003",
        "tgn:7000094",
        "tgn:7000084",
        "tgn:7029392"
    ],
    "tgn:id":7197440,
    "tgn:name":"Der Lindenwald",
    "tgn:placetype":[
        "aat:300008863"
    ]
},
  "bbox": [],
  "geometry": {"coordinates":[11.816667,53.516667],"type":"Point"}
}