{
  "id": 2605194,
  "type": "Feature",
  "properties": {
    "tgn:hierarchy":[
        "tgn:2605194",
        "tgn:1000001",
        "tgn:7012149",
        "tgn:2002015",
        "tgn:7007826",
        "tgn:7029392"
    ],
    "tgn:id":2605194,
    "tgn:name":"Rafter Hollow",
    "tgn:placetype":[
        "aat:300008761"
    ]
},
  "bbox": [],
  "geometry": {"coordinates":[-98.7833,30.0833],"type":"Point"}
}