{
  "id": 7332433,
  "type": "Feature",
  "properties": {
    "tgn:hierarchy":[
        "tgn:7332433",
        "tgn:7002829",
        "tgn:1000003",
        "tgn:7002786",
        "tgn:1000095",
        "tgn:7029392"
    ],
    "tgn:id":7332433,
    "tgn:name":"Lago, Playa de",
    "tgn:placetype":[
        "aat:300008816"
    ]
},
  "bbox": [],
  "geometry": {"coordinates":[-7.483333,43.716667],"type":"Point"}
}