<<<<<<< HEAD
{
  "id": 7020411,
  "type": "Feature",
  "properties": {
    "tgn:hierarchy":[
        "tgn:7020411",
        "tgn:1000001",
        "tgn:7012149",
        "tgn:7007709",
        "tgn:7029392"
    ],
    "tgn:id":7020411,
    "tgn:name":"Pinnacle Knob",
    "tgn:placetype":[
        "aat:300008798"
    ]
},
  "bbox": [],
  "geometry": {"coordinates":[-83.4833,35.3],"type":"Point"}
}
=======
{"geometry":{"type":"Point","coordinates":[-83.483300,35.300000]},"type":"Feature","properties":{"hierarchy":["tgn:7020411","tgn:1000001","tgn:7012149","tgn:7007709","tgn:7029392"],"placetype":["aat:300008798"],"id":7020411,"name:xx":"Pinnacle Knob"}}
>>>>>>> 03f74aca74312dbeaf24d7e61306dd6a786dc3d0
