{
  "id": 2536215,
  "type": "Feature",
  "properties": {
    "tgn:hierarchy":[
        "tgn:2536215",
        "tgn:1000001",
        "tgn:7012149",
        "tgn:2002113",
        "tgn:7007827",
        "tgn:7029392"
    ],
    "tgn:id":2536215,
    "tgn:name":"Navajo Creek",
    "tgn:placetype":[
        "aat:300008706"
    ]
},
  "bbox": [],
  "geometry": {"coordinates":[-110.8333,37.4667],"type":"Point"}
}