<<<<<<< HEAD
{
  "id": 2769741,
  "type": "Feature",
  "properties": {
    "tgn:hierarchy":[
        "tgn:2769741",
        "tgn:1000001",
        "tgn:7012149",
        "tgn:2000472",
        "tgn:7007250",
        "tgn:7029392"
    ],
    "tgn:id":2769741,
    "tgn:name":"Wiggler Lake",
    "tgn:placetype":[
        "aat:300008680"
    ]
},
  "bbox": [],
  "geometry": {"coordinates":[-111.5667,42.0],"type":"Point"}
}
=======
{"geometry":{"type":"Point","coordinates":[-111.566700,42.000000]},"type":"Feature","properties":{"hierarchy":["tgn:2769741","tgn:1000001","tgn:7012149","tgn:2000472","tgn:7007250","tgn:7029392"],"placetype":["aat:300008680"],"id":2769741,"name:xx":"Wiggler Lake"}}
>>>>>>> 03f74aca74312dbeaf24d7e61306dd6a786dc3d0
