{
  "id": 1069826,
  "type": "Feature",
  "properties": {
    "tgn:hierarchy":[
        "tgn:1069826",
        "tgn:1000004",
        "tgn:1001390",
        "tgn:1000111",
        "tgn:7029392"
    ],
    "tgn:id":1069826,
    "tgn:name":"Lijiatun",
    "tgn:placetype":[
        "aat:300008347"
    ]
},
  "bbox": [],
  "geometry": {"coordinates":[121.3833,41.3167],"type":"Point"}
}