<<<<<<< HEAD
{
  "id": 2151141,
  "type": "Feature",
  "properties": {
    "tgn:hierarchy":[
        "tgn:2151141",
        "tgn:1000001",
        "tgn:7012149",
        "tgn:2001504",
        "tgn:7007709",
        "tgn:7029392"
    ],
    "tgn:id":2151141,
    "tgn:name":"Bat Fork",
    "tgn:placetype":[
        "aat:300008699"
    ]
},
  "bbox": [],
  "geometry": {"coordinates":[-82.4167,35.25],"type":"Point"}
}
=======
{"geometry":{"type":"Point","coordinates":[-82.416700,35.250000]},"type":"Feature","properties":{"hierarchy":["tgn:2151141","tgn:1000001","tgn:7012149","tgn:2001504","tgn:7007709","tgn:7029392"],"placetype":["aat:300008699"],"id":2151141,"name:xx":"Bat Fork"}}
>>>>>>> 03f74aca74312dbeaf24d7e61306dd6a786dc3d0
