{
  "id": 2696586,
  "type": "Feature",
  "properties": {
    "tgn:hierarchy":[
        "tgn:2696586",
        "tgn:1000001",
        "tgn:7012149",
        "tgn:1002913",
        "tgn:7007919",
        "tgn:7029392"
    ],
    "tgn:id":2696586,
    "tgn:name":"Stone Point",
    "tgn:placetype":[
        "aat:300008850"
    ]
},
  "bbox": [],
  "geometry": {"coordinates":[-77.35,38.3333],"type":"Point"}
}