{
  "id": 7349242,
  "type": "Feature",
  "properties": {
    "tgn:hierarchy":[
        "tgn:7349242",
        "tgn:1001836",
        "tgn:1000001",
        "tgn:7005560",
        "tgn:7029392"
    ],
    "tgn:id":7349242,
    "tgn:name":"Agua del Coyote",
    "tgn:placetype":[
        "aat:300008347"
    ]
},
  "bbox": [],
  "geometry": {"coordinates":[-112.133333,25.866667],"type":"Point"}
}