{
  "id": 7217399,
  "type": "Feature",
  "properties": {
    "tgn:hierarchy":[
        "tgn:7217399",
        "tgn:7002680",
        "tgn:7001395",
        "tgn:1000003",
        "tgn:1000074",
        "tgn:7029392"
    ],
    "tgn:id":7217399,
    "tgn:name":"G\u00fdra R\u00e9ma",
    "tgn:placetype":[
        "aat:300008699"
    ]
},
  "bbox": [],
  "geometry": {"coordinates":[21.413056,39.069167],"type":"Point"}
}