{
  "id": 2334539,
  "type": "Feature",
  "properties": {
    "tgn:hierarchy":[
        "tgn:2334539",
        "tgn:1000001",
        "tgn:7006451",
        "tgn:2000092",
        "tgn:7012149",
        "tgn:7029392"
    ],
    "tgn:id":2334539,
    "tgn:name":"Forest Tank",
    "tgn:placetype":[
        "aat:300006191"
    ]
},
  "bbox": [],
  "geometry": {"coordinates":[-111.25,34.6667],"type":"Point"}
}