{
  "id": 2678524,
  "type": "Feature",
  "properties": {
    "tgn:hierarchy":[
        "tgn:2678524",
        "tgn:1000001",
        "tgn:2000935",
        "tgn:7012149",
        "tgn:7007516",
        "tgn:7029392"
    ],
    "tgn:id":2678524,
    "tgn:name":"South Fork Crabtree Creek",
    "tgn:placetype":[
        "aat:300008706"
    ]
},
  "bbox": [],
  "geometry": {"coordinates":[-79.2667,39.4167],"type":"Point"}
}