<<<<<<< HEAD
{
  "id": 7358772,
  "type": "Feature",
  "properties": {
    "tgn:hierarchy":[
        "tgn:7358772",
        "tgn:1000001",
        "tgn:1001906",
        "tgn:7005560",
        "tgn:7029392"
    ],
    "tgn:id":7358772,
    "tgn:name":"El Aguacate",
    "tgn:placetype":[
        "aat:300008347"
    ]
},
  "bbox": [],
  "geometry": {"coordinates":[-104.2,21.2625],"type":"Point"}
}
=======
{"geometry":{"type":"Point","coordinates":[-104.200000,21.262500]},"type":"Feature","properties":{"hierarchy":["tgn:7358772","tgn:1000001","tgn:1001906","tgn:7005560","tgn:7029392"],"placetype":["aat:300008347"],"id":7358772,"name:xx":"El Aguacate"}}
>>>>>>> 03f74aca74312dbeaf24d7e61306dd6a786dc3d0
