{
  "id": 7310586,
  "type": "Feature",
  "properties": {
    "tgn:hierarchy":[
        "tgn:7310586",
        "tgn:1001657",
        "tgn:1000049",
        "tgn:1000002",
        "tgn:7029392"
    ],
    "tgn:id":7310586,
    "tgn:name":"Ojotas, Estero",
    "tgn:placetype":[
        "aat:300008699"
    ]
},
  "bbox": [],
  "geometry": {"coordinates":[-70.266667,-31.983333],"type":"Point"}
}