{
  "id": 2001184,
  "type": "Feature",
  "properties": {
    "tgn:hierarchy":[
        "tgn:2001184",
        "tgn:1000001",
        "tgn:7012149",
        "tgn:7007523",
        "tgn:7029392"
    ],
    "tgn:id":2001184,
    "tgn:name":"Chariton",
    "tgn:placetype":[
        "aat:300387145",
        "aat:300000771"
    ]
},
  "bbox": [],
  "geometry": {"coordinates":[-92.95,39.5167],"type":"Point"}
}