<<<<<<< HEAD
{
  "id": 2158599,
  "type": "Feature",
  "properties": {
    "tgn:hierarchy":[
        "tgn:2158599",
        "tgn:1000001",
        "tgn:7016172",
        "tgn:7012149",
        "tgn:7029392"
    ],
    "tgn:id":2158599,
    "tgn:name":"Beaverdam Slough",
    "tgn:placetype":[
        "aat:300008699"
    ]
},
  "bbox": [],
  "geometry": {"coordinates":[-92.5833,34.1333],"type":"Point"}
}
=======
{"geometry":{"type":"Point","coordinates":[-92.583300,34.133300]},"type":"Feature","properties":{"hierarchy":["tgn:2158599","tgn:1000001","tgn:7016172","tgn:7012149","tgn:7029392"],"placetype":["aat:300008699"],"id":2158599,"name:xx":"Beaverdam Slough"}}
>>>>>>> 03f74aca74312dbeaf24d7e61306dd6a786dc3d0
