{
  "id": 7123039,
  "type": "Feature",
  "properties": {
    "tgn:hierarchy":[
        "tgn:7123039",
        "tgn:7000096",
        "tgn:1000003",
        "tgn:7000084",
        "tgn:7029392"
    ],
    "tgn:id":7123039,
    "tgn:name":"F\u00f6rsterei Neuhof",
    "tgn:placetype":[
        "aat:300004792"
    ]
},
  "bbox": [],
  "geometry": {"coordinates":[13.133333,53.133333],"type":"Point"}
}