<<<<<<< HEAD
{
  "id": 7173306,
  "type": "Feature",
  "properties": {
    "tgn:hierarchy":[
        "tgn:7173306",
        "tgn:1000003",
        "tgn:7000094",
        "tgn:7000084",
        "tgn:7029392"
    ],
    "tgn:id":7173306,
    "tgn:name":"Gro\u00df Daberkow",
    "tgn:placetype":[
        "aat:300008347"
    ]
},
  "bbox": [],
  "geometry": {"coordinates":[13.633333,53.5],"type":"Point"}
}
=======
{"geometry":{"type":"Point","coordinates":[13.633333,53.500000]},"type":"Feature","properties":{"hierarchy":["tgn:7173306","tgn:1000003","tgn:7000094","tgn:7000084","tgn:7029392"],"placetype":["aat:300008347"],"id":7173306,"name:xx":"Gro\u00df Daberkow"}}
>>>>>>> 03f74aca74312dbeaf24d7e61306dd6a786dc3d0
