{
  "id": 1109573,
  "type": "Feature",
  "properties": {
    "tgn:hierarchy":[
        "tgn:1109573",
        "tgn:7017438",
        "tgn:1000001",
        "tgn:7004643",
        "tgn:7029392"
    ],
    "tgn:id":1109573,
    "tgn:name":"San Francisco, La Cadena",
    "tgn:placetype":[
        "aat:300386831"
    ]
},
  "bbox": [],
  "geometry": {"coordinates":[-67.1667,18.3167],"type":"Point"}
}