{
  "id": 2723613,
  "type": "Feature",
  "properties": {
    "tgn:hierarchy":[
        "tgn:2723613",
        "tgn:1000001",
        "tgn:7012149",
        "tgn:2000233",
        "tgn:7007158",
        "tgn:7029392"
    ],
    "tgn:id":2723613,
    "tgn:name":"Todd Mine",
    "tgn:placetype":[
        "aat:300000390"
    ]
},
  "bbox": [],
  "geometry": {"coordinates":[-108.55,37.25],"type":"Point"}
}