{
  "id": 2373041,
  "type": "Feature",
  "properties": {
    "tgn:hierarchy":[
        "tgn:2373041",
        "tgn:1000001",
        "tgn:7012149",
        "tgn:2001880",
        "tgn:7007825",
        "tgn:7029392"
    ],
    "tgn:id":2373041,
    "tgn:name":"Halls Branch",
    "tgn:placetype":[
        "aat:300008699"
    ]
},
  "bbox": [],
  "geometry": {"coordinates":[-85.8167,36.3833],"type":"Point"}
}