{
  "id": 2753308,
  "type": "Feature",
  "properties": {
    "tgn:hierarchy":[
        "tgn:2753308",
        "tgn:1000001",
        "tgn:7012149",
        "tgn:2001924",
        "tgn:7007825",
        "tgn:7029392"
    ],
    "tgn:id":2753308,
    "tgn:name":"Waterfall Hollow",
    "tgn:placetype":[
        "aat:300008761"
    ]
},
  "bbox": [],
  "geometry": {"coordinates":[-85.3667,35.75],"type":"Point"}
}