{
  "id": 7217998,
  "type": "Feature",
  "properties": {
    "tgn:hierarchy":[
        "tgn:7217998",
        "tgn:7002690",
        "tgn:7012056",
        "tgn:1000003",
        "tgn:1000074",
        "tgn:7029392"
    ],
    "tgn:id":7217998,
    "tgn:name":"Y\u00e9nna",
    "tgn:placetype":[
        "aat:300008347"
    ]
},
  "bbox": [],
  "geometry": {"coordinates":[25.083333,35.133333],"type":"Point"}
}