{
  "id": 1016410,
  "type": "Feature",
  "properties": {
    "tgn:hierarchy":[
        "tgn:1016410",
        "tgn:1001374",
        "tgn:1000001",
        "tgn:7004624",
        "tgn:7029392"
    ],
    "tgn:id":1016410,
    "tgn:name":"Playa Baracoa",
    "tgn:placetype":[
        "aat:300008347"
    ]
},
  "bbox": [],
  "geometry": {"coordinates":[-82.5667,23.05],"type":"Point"}
}