{
  "id": 2635891,
  "type": "Feature",
  "properties": {
    "tgn:hierarchy":[
        "tgn:2635891",
        "tgn:1000001",
        "tgn:7012149",
        "tgn:2002250",
        "tgn:7007920",
        "tgn:7029392"
    ],
    "tgn:id":2635891,
    "tgn:name":"Sackit Canyon",
    "tgn:placetype":[
        "aat:300008761"
    ]
},
  "bbox": [],
  "geometry": {"coordinates":[-118.0667,48.8333],"type":"Point"}
}