<<<<<<< HEAD
{
  "id": 2155839,
  "type": "Feature",
  "properties": {
    "tgn:hierarchy":[
        "tgn:2155839",
        "tgn:1000001",
        "tgn:7012149",
        "tgn:2002127",
        "tgn:7007827",
        "tgn:7029392"
    ],
    "tgn:id":2155839,
    "tgn:name":"Bear Trap Canyon",
    "tgn:placetype":[
        "aat:300008761"
    ]
},
  "bbox": [],
  "geometry": {"coordinates":[-113.0833,37.4333],"type":"Point"}
}
=======
{"geometry":{"type":"Point","coordinates":[-113.083300,37.433300]},"type":"Feature","properties":{"hierarchy":["tgn:2155839","tgn:1000001","tgn:7012149","tgn:2002127","tgn:7007827","tgn:7029392"],"placetype":["aat:300008761"],"id":2155839,"name:xx":"Bear Trap Canyon"}}
>>>>>>> 03f74aca74312dbeaf24d7e61306dd6a786dc3d0
