{
  "id": 7496717,
  "type": "Feature",
  "properties": {
    "tgn:hierarchy":[
        "tgn:7496717",
        "tgn:1000004",
        "tgn:1000454",
        "tgn:1000141",
        "tgn:7029392"
    ],
    "tgn:id":7496717,
    "tgn:name":"Diaoqiaotou",
    "tgn:placetype":[
        "aat:300008347"
    ]
},
  "bbox": [],
  "geometry": {"coordinates":[121.357244,24.854197],"type":"Point"}
}