{
  "id": 2309335,
  "type": "Feature",
  "properties": {
    "tgn:hierarchy":[
        "tgn:2309335",
        "tgn:1000001",
        "tgn:7012149",
        "tgn:2002376",
        "tgn:7007923",
        "tgn:7029392"
    ],
    "tgn:id":2309335,
    "tgn:name":"East Table Creek",
    "tgn:placetype":[
        "aat:300008706"
    ]
},
  "bbox": [],
  "geometry": {"coordinates":[-110.8167,43.2333],"type":"Point"}
}