{
  "id": 7493314,
  "type": "Feature",
  "properties": {
    "tgn:hierarchy":[
        "tgn:7493314",
        "tgn:7487020",
        "tgn:1000004",
        "tgn:1000141",
        "tgn:7029392"
    ],
    "tgn:id":7493314,
    "tgn:name":"Duoluogu Xi",
    "tgn:placetype":[
        "aat:300008699"
    ]
},
  "bbox": [],
  "geometry": {"coordinates":[120.822348,24.351705],"type":"Point"}
}