{
  "id": 2007094,
  "type": "Feature",
  "properties": {
    "tgn:hierarchy":[
        "tgn:2007094",
        "tgn:1000001",
        "tgn:7006451",
        "tgn:7012149",
        "tgn:2000100",
        "tgn:7029392"
    ],
    "tgn:id":2007094,
    "tgn:name":"Oro Valley",
    "tgn:placetype":[
        "aat:300008347"
    ]
},
  "bbox": [],
  "geometry": {"coordinates":[-110.95,32.3833],"type":"Point"}
}