{
  "id": 7046561,
  "type": "Feature",
  "properties": {
    "tgn:hierarchy":[
        "tgn:7046561",
        "tgn:1000003",
        "tgn:7003122",
        "tgn:1000080",
        "tgn:7029392"
    ],
    "tgn:id":7046561,
    "tgn:name":"Calarossa, Punta",
    "tgn:placetype":[
        "aat:300386846"
    ]
},
  "bbox": [],
  "geometry": {"coordinates":[12.366667,37.916667],"type":"Point"}
}