{
  "id": 7205002,
  "type": "Feature",
  "properties": {
    "tgn:hierarchy":[
        "tgn:7205002",
        "tgn:1000003",
        "tgn:7003685",
        "tgn:7000084",
        "tgn:7029392"
    ],
    "tgn:id":7205002,
    "tgn:name":"Buch-Berg",
    "tgn:placetype":[
        "aat:300008777"
    ]
},
  "bbox": [],
  "geometry": {"coordinates":[14.833333,50.966667],"type":"Point"}
}