{
  "id": 1071620,
  "type": "Feature",
  "properties": {
    "tgn:hierarchy":[
        "tgn:1071620",
        "tgn:1000004",
        "tgn:7002077",
        "tgn:1000111",
        "tgn:7029392"
    ],
    "tgn:id":1071620,
    "tgn:name":"Shenxing",
    "tgn:placetype":[
        "aat:300008347"
    ]
},
  "bbox": [],
  "geometry": {"coordinates":[115.3167,39.0333],"type":"Point"}
}