{
  "id": 2285184,
  "type": "Feature",
  "properties": {
    "tgn:hierarchy":[
        "tgn:2285184",
        "tgn:1000001",
        "tgn:7012149",
        "tgn:2000930",
        "tgn:7007515",
        "tgn:7029392"
    ],
    "tgn:id":2285184,
    "tgn:name":"Devils Bog",
    "tgn:placetype":[
        "aat:300008905"
    ]
},
  "bbox": [],
  "geometry": {"coordinates":[-69.6833,44.8167],"type":"Point"}
}