{
  "id": 2144838,
  "type": "Feature",
  "properties": {
    "tgn:hierarchy":[
        "tgn:2144838",
        "tgn:1000001",
        "tgn:7012149",
        "tgn:2000493",
        "tgn:7007250",
        "tgn:7029392"
    ],
    "tgn:id":2144838,
    "tgn:name":"Bald Hill Spring Number 2",
    "tgn:placetype":[
        "aat:300008697"
    ]
},
  "bbox": [],
  "geometry": {"coordinates":[-114.3333,42.1833],"type":"Point"}
}