{
  "id": 7316978,
  "type": "Feature",
  "properties": {
    "tgn:hierarchy":[
        "tgn:7316978",
        "tgn:1001708",
        "tgn:1000049",
        "tgn:1000002",
        "tgn:7029392"
    ],
    "tgn:id":7316978,
    "tgn:name":"Condorito, Cerro",
    "tgn:placetype":[
        "aat:300008777"
    ]
},
  "bbox": [],
  "geometry": {"coordinates":[-70.783333,-33.05],"type":"Point"}
}