{
  "id": 7393546,
  "type": "Feature",
  "properties": {
    "tgn:hierarchy":[
        "tgn:7393546",
        "tgn:1001853",
        "tgn:1000001",
        "tgn:7005560",
        "tgn:7029392"
    ],
    "tgn:id":7393546,
    "tgn:name":"San Juan de Sauceda",
    "tgn:placetype":[
        "aat:300008347"
    ]
},
  "bbox": [],
  "geometry": {"coordinates":[-101.15,25.783333],"type":"Point"}
}