{
  "id": 4005457,
  "type": "Feature",
  "properties": {
    "tgn:hierarchy":[
        "tgn:4005457",
        "tgn:7593914",
        "tgn:1000003",
        "tgn:1001780",
        "tgn:7029392"
    ],
    "tgn:id":4005457,
    "tgn:name":"Josefov",
    "tgn:placetype":[
        "aat:300008347"
    ]
},
  "bbox": [],
  "geometry": {"coordinates":[15.93,50.339],"type":"Point"}
}