<<<<<<< HEAD
{
  "id": 7482358,
  "type": "Feature",
  "properties": {
    "tgn:hierarchy":[
        "tgn:7482358",
        "tgn:7468018",
        "tgn:1000004",
        "tgn:1000141",
        "tgn:7029392"
    ],
    "tgn:id":7482358,
    "tgn:name":"Xiangcun Shequ",
    "tgn:placetype":[
        "aat:300000498"
    ]
},
  "bbox": [],
  "geometry": {"coordinates":[120.438889,23.428056],"type":"Point"}
}
=======
{"geometry":{"type":"Point","coordinates":[120.438889,23.428056]},"type":"Feature","properties":{"hierarchy":["tgn:7482358","tgn:7468018","tgn:1000004","tgn:1000141","tgn:7029392"],"placetype":["aat:300000498"],"id":7482358,"name:xx":"Xiangcun Shequ"}}
>>>>>>> 03f74aca74312dbeaf24d7e61306dd6a786dc3d0
