<<<<<<< HEAD
{
  "id": 7369534,
  "type": "Feature",
  "properties": {
    "tgn:hierarchy":[
        "tgn:7369534",
        "tgn:1000001",
        "tgn:7005588",
        "tgn:7005560",
        "tgn:7029392"
    ],
    "tgn:id":7369534,
    "tgn:name":"Huajintl\u00e1n",
    "tgn:placetype":[
        "aat:300008347"
    ]
},
  "bbox": [],
  "geometry": {"coordinates":[-99.416667,18.6],"type":"Point"}
}
=======
{"geometry":{"type":"Point","coordinates":[-99.416667,18.600000]},"type":"Feature","properties":{"hierarchy":["tgn:7369534","tgn:1000001","tgn:7005588","tgn:7005560","tgn:7029392"],"placetype":["aat:300008347"],"id":7369534,"name:xx":"Huajintl\u00e1n"}}
>>>>>>> 03f74aca74312dbeaf24d7e61306dd6a786dc3d0
