{
  "id": 2774728,
  "type": "Feature",
  "properties": {
    "tgn:hierarchy":[
        "tgn:2774728",
        "tgn:1000001",
        "tgn:2002107",
        "tgn:7012149",
        "tgn:7007827",
        "tgn:7029392"
    ],
    "tgn:id":2774728,
    "tgn:name":"Willow Spring",
    "tgn:placetype":[
        "aat:300008697"
    ]
},
  "bbox": [],
  "geometry": {"coordinates":[-110.3333,40.4667],"type":"Point"}
}