{
  "id": 1019547,
  "type": "Feature",
  "properties": {
    "tgn:hierarchy":[
        "tgn:1019547",
        "tgn:7006477",
        "tgn:1001375",
        "tgn:1000002",
        "tgn:7029392"
    ],
    "tgn:id":1019547,
    "tgn:name":"Guatrach\u00e9",
    "tgn:placetype":[
        "aat:300008347"
    ]
},
  "bbox": [],
  "geometry": {"coordinates":[-63.5333,-37.6667],"type":"Point"}
}