{
  "id": 7379076,
  "type": "Feature",
  "properties": {
    "tgn:hierarchy":[
        "tgn:7379076",
        "tgn:1000001",
        "tgn:7005589",
        "tgn:7005560",
        "tgn:7029392"
    ],
    "tgn:id":7379076,
    "tgn:name":"Maravillas",
    "tgn:placetype":[
        "aat:300008347"
    ]
},
  "bbox": [],
  "geometry": {"coordinates":[-99.966667,27.566667],"type":"Point"}
}