<<<<<<< HEAD
{
  "id": 2704924,
  "type": "Feature",
  "properties": {
    "tgn:hierarchy":[
        "tgn:2704924",
        "tgn:1000001",
        "tgn:7012149",
        "tgn:2001290",
        "tgn:7007524",
        "tgn:7029392"
    ],
    "tgn:id":2704924,
    "tgn:name":"Sunset Peak",
    "tgn:placetype":[
        "aat:300008798"
    ]
},
  "bbox": [],
  "geometry": {"coordinates":[-115.2167,47.2167],"type":"Point"}
}
=======
{"geometry":{"type":"Point","coordinates":[-115.216700,47.216700]},"type":"Feature","properties":{"hierarchy":["tgn:2704924","tgn:1000001","tgn:7012149","tgn:2001290","tgn:7007524","tgn:7029392"],"placetype":["aat:300008798"],"id":2704924,"name:xx":"Sunset Peak"}}
>>>>>>> 03f74aca74312dbeaf24d7e61306dd6a786dc3d0
