{
  "id": 2512721,
  "type": "Feature",
  "properties": {
    "tgn:hierarchy":[
        "tgn:2512721",
        "tgn:1000001",
        "tgn:7012149",
        "tgn:2001116",
        "tgn:7007522",
        "tgn:7029392"
    ],
    "tgn:id":2512721,
    "tgn:name":"Mill Creek",
    "tgn:placetype":[
        "aat:300008706"
    ]
},
  "bbox": [],
  "geometry": {"coordinates":[-89.05,31.85],"type":"Point"}
}