<<<<<<< HEAD
{
  "id": 7029615,
  "type": "Feature",
  "properties": {
    "tgn:hierarchy":[
        "tgn:7029615",
        "tgn:1000004",
        "tgn:1000118",
        "tgn:1001054",
        "tgn:7029392"
    ],
    "tgn:id":7029615,
    "tgn:name":"Baiji",
    "tgn:placetype":[
        "aat:300008347",
        "aat:300000810"
    ]
},
  "bbox": [],
  "geometry": {"coordinates":[43.491,34.924],"type":"Point"}
}
=======
{"geometry":{"type":"Point","coordinates":[43.491000,34.924000]},"type":"Feature","properties":{"hierarchy":["tgn:7029615","tgn:1000004","tgn:1000118","tgn:1001054","tgn:7029392"],"placetype":["aat:300008347","aat:300000810"],"id":7029615,"name:xx":"Baiji"}}
>>>>>>> 03f74aca74312dbeaf24d7e61306dd6a786dc3d0
