{
  "id": 1069611,
  "type": "Feature",
  "properties": {
    "tgn:hierarchy":[
        "tgn:1069611",
        "tgn:1000004",
        "tgn:1001290",
        "tgn:1000111",
        "tgn:7029392"
    ],
    "tgn:id":1069611,
    "tgn:name":"Laha",
    "tgn:placetype":[
        "aat:300008347"
    ]
},
  "bbox": [],
  "geometry": {"coordinates":[124.5667,48.25],"type":"Point"}
}