{
  "id": 7458825,
  "type": "Feature",
  "properties": {
    "tgn:hierarchy":[
        "tgn:7458825",
        "tgn:7002444",
        "tgn:1000003",
        "tgn:7009907",
        "tgn:7008591",
        "tgn:7029392"
    ],
    "tgn:id":7458825,
    "tgn:name:en":"Mill Sand",
    "tgn:placetype":[
        "aat:300386970"
    ]
},
  "bbox": [],
  "geometry": {"coordinates":[-2.833333,58.95],"type":"Point"}
}