{
  "id": 2430034,
  "type": "Feature",
  "properties": {
    "tgn:hierarchy":[
        "tgn:2430034",
        "tgn:7006450",
        "tgn:1000001",
        "tgn:7012149",
        "tgn:2124005",
        "tgn:7029392"
    ],
    "tgn:id":2430034,
    "tgn:name":"Kadruakvik Creek",
    "tgn:placetype":[
        "aat:300008706"
    ]
},
  "bbox": [],
  "geometry": {"coordinates":[-154.1833,68.0333],"type":"Point"}
}