{
  "id": 7591640,
  "type": "Feature",
  "properties": {
    "tgn:hierarchy":[
        "tgn:7591640",
        "tgn:1000004",
        "tgn:7000198",
        "tgn:7000799",
        "tgn:7029392"
    ],
    "tgn:id":7591640,
    "tgn:name:en":"Maishin",
    "tgn:placetype":[
        "aat:300008347"
    ]
},
  "bbox": [],
  "geometry": {"coordinates":[74.803599,32.62162],"type":"Point"}
}