{
  "id": 7369807,
  "type": "Feature",
  "properties": {
    "tgn:hierarchy":[
        "tgn:7369807",
        "tgn:1000001",
        "tgn:7005589",
        "tgn:7005560",
        "tgn:7029392"
    ],
    "tgn:id":7369807,
    "tgn:name":"Guajuquito",
    "tgn:placetype":[
        "aat:300008347"
    ]
},
  "bbox": [],
  "geometry": {"coordinates":[-100.166667,25.45],"type":"Point"}
}