{
  "id": 7081842,
  "type": "Feature",
  "properties": {
    "tgn:hierarchy":[
        "tgn:7081842",
        "tgn:1000003",
        "tgn:7003677",
        "tgn:7000084",
        "tgn:7029392"
    ],
    "tgn:id":7081842,
    "tgn:name":"W\u00fcstenhof",
    "tgn:placetype":[
        "aat:300000206"
    ]
},
  "bbox": [],
  "geometry": {"coordinates":[7.083333,51.133333],"type":"Point"}
}