<<<<<<< HEAD
{
  "id": 7359069,
  "type": "Feature",
  "properties": {
    "tgn:hierarchy":[
        "tgn:7359069",
        "tgn:7005581",
        "tgn:1000001",
        "tgn:7005560",
        "tgn:7029392"
    ],
    "tgn:id":7359069,
    "tgn:name":"Rancho El Aguaje",
    "tgn:placetype":[
        "aat:300000241"
    ]
},
  "bbox": [],
  "geometry": {"coordinates":[-106.133333,21.1],"type":"Point"}
}
=======
{"geometry":{"type":"Point","coordinates":[-106.133333,21.100000]},"type":"Feature","properties":{"hierarchy":["tgn:7359069","tgn:7005581","tgn:1000001","tgn:7005560","tgn:7029392"],"placetype":["aat:300000241"],"id":7359069,"name:xx":"Rancho El Aguaje"}}
>>>>>>> 03f74aca74312dbeaf24d7e61306dd6a786dc3d0
