{
  "id": 7278120,
  "type": "Feature",
  "properties": {
    "tgn:hierarchy":[
        "tgn:7278120",
        "tgn:7016598",
        "tgn:1000049",
        "tgn:1000002",
        "tgn:7029392"
    ],
    "tgn:id":7278120,
    "tgn:name":"Varitas, Cerro",
    "tgn:placetype":[
        "aat:300008795"
    ]
},
  "bbox": [],
  "geometry": {"coordinates":[-69.233333,-25.133333],"type":"Point"}
}