{
  "id": 7456769,
  "type": "Feature",
  "properties": {
    "tgn:hierarchy":[
        "tgn:7456769",
        "tgn:7002444",
        "tgn:1000003",
        "tgn:7008082",
        "tgn:7008591",
        "tgn:7029392"
    ],
    "tgn:id":7456769,
    "tgn:name:en":"Muice, Gleann na",
    "tgn:placetype":[
        "aat:300008761"
    ]
},
  "bbox": [],
  "geometry": {"coordinates":[-5.283333,57.75],"type":"Point"}
}