<<<<<<< HEAD
{
  "id": 2402030,
  "type": "Feature",
  "properties": {
    "tgn:hierarchy":[
        "tgn:2402030",
        "tgn:1000001",
        "tgn:7012149",
        "tgn:1002358",
        "tgn:7007710",
        "tgn:7029392"
    ],
    "tgn:id":2402030,
    "tgn:name":"Horseshoe Pond",
    "tgn:placetype":[
        "aat:300008680"
    ]
},
  "bbox": [],
  "geometry": {"coordinates":[-80.0667,42.15],"type":"Point"}
}
=======
{"geometry":{"type":"Point","coordinates":[-80.066700,42.150000]},"type":"Feature","properties":{"hierarchy":["tgn:2402030","tgn:1000001","tgn:7012149","tgn:1002358","tgn:7007710","tgn:7029392"],"placetype":["aat:300008680"],"id":2402030,"name:xx":"Horseshoe Pond"}}
>>>>>>> 03f74aca74312dbeaf24d7e61306dd6a786dc3d0
