{
  "id": 7193051,
  "type": "Feature",
  "properties": {
    "tgn:hierarchy":[
        "tgn:7193051",
        "tgn:1000003",
        "tgn:7000094",
        "tgn:7000084",
        "tgn:7029392"
    ],
    "tgn:id":7193051,
    "tgn:name":"Frauendorfer Wald",
    "tgn:placetype":[
        "aat:300008863"
    ]
},
  "bbox": [],
  "geometry": {"coordinates":[12.683333,54.316667],"type":"Point"}
}