<<<<<<< HEAD
{
  "id": 2335096,
  "type": "Feature",
  "properties": {
    "tgn:hierarchy":[
        "tgn:2335096",
        "tgn:1000001",
        "tgn:7012149",
        "tgn:2001312",
        "tgn:7007524",
        "tgn:7029392"
    ],
    "tgn:id":2335096,
    "tgn:name":"Forsman Reservoir",
    "tgn:placetype":[
        "aat:300006191"
    ]
},
  "bbox": [],
  "geometry": {"coordinates":[-106.7,48.5833],"type":"Point"}
}
=======
{"geometry":{"type":"Point","coordinates":[-106.700000,48.583300]},"type":"Feature","properties":{"hierarchy":["tgn:2335096","tgn:1000001","tgn:7012149","tgn:2001312","tgn:7007524","tgn:7029392"],"placetype":["aat:300006191"],"id":2335096,"name:xx":"Forsman Reservoir"}}
>>>>>>> 03f74aca74312dbeaf24d7e61306dd6a786dc3d0
