{
  "id": 7150469,
  "type": "Feature",
  "properties": {
    "tgn:hierarchy":[
        "tgn:7150469",
        "tgn:1000003",
        "tgn:7003678",
        "tgn:7000084",
        "tgn:7029392"
    ],
    "tgn:id":7150469,
    "tgn:name":"Kuhbett",
    "tgn:placetype":[
        "aat:300008777"
    ]
},
  "bbox": [],
  "geometry": {"coordinates":[8.333333,53.333333],"type":"Point"}
}