{
  "id": 2635193,
  "type": "Feature",
  "properties": {
    "tgn:hierarchy":[
        "tgn:2635193",
        "tgn:1000001",
        "tgn:2001336",
        "tgn:7012149",
        "tgn:7007525",
        "tgn:7029392"
    ],
    "tgn:id":2635193,
    "tgn:name":"Ryno Table",
    "tgn:placetype":[
        "aat:300008798"
    ]
},
  "bbox": [],
  "geometry": {"coordinates":[-99.75,41.3167],"type":"Point"}
}