{
  "id": 7239671,
  "type": "Feature",
  "properties": {
    "tgn:hierarchy":[
        "tgn:7239671",
        "tgn:7003460",
        "tgn:1000003",
        "tgn:1000063",
        "tgn:4012014",
        "tgn:7029392"
    ],
    "tgn:id":7239671,
    "tgn:name":"Hollogne-sur-Geer",
    "tgn:placetype":[
        "aat:300008347"
    ]
},
  "bbox": [],
  "geometry": {"coordinates":[5.204281,50.676542],"type":"Point"}
}