{
  "id": 2130247,
  "type": "Feature",
  "properties": {
    "tgn:hierarchy":[
        "tgn:2130247",
        "tgn:1000001",
        "tgn:7012149",
        "tgn:2001447",
        "tgn:7007566",
        "tgn:7029392"
    ],
    "tgn:id":2130247,
    "tgn:name":"Allen Spring",
    "tgn:placetype":[
        "aat:300008697"
    ]
},
  "bbox": [],
  "geometry": {"coordinates":[-105.5667,32.7833],"type":"Point"}
}