{
  "id": 2294226,
  "type": "Feature",
  "properties": {
    "tgn:hierarchy":[
        "tgn:2294226",
        "tgn:1000001",
        "tgn:2001416",
        "tgn:7012149",
        "tgn:7007526",
        "tgn:7029392"
    ],
    "tgn:id":2294226,
    "tgn:name":"Dow Mountain",
    "tgn:placetype":[
        "aat:300008798"
    ]
},
  "bbox": [],
  "geometry": {"coordinates":[-114.2167,37.7333],"type":"Point"}
}