<<<<<<< HEAD
{
  "id": 2251841,
  "type": "Feature",
  "properties": {
    "tgn:hierarchy":[
        "tgn:2251841",
        "tgn:1000001",
        "tgn:7012149",
        "tgn:2001282",
        "tgn:7007524",
        "tgn:7029392"
    ],
    "tgn:id":2251841,
    "tgn:name":"Conan Coulee",
    "tgn:placetype":[
        "aat:300008761"
    ]
},
  "bbox": [],
  "geometry": {"coordinates":[-110.4,47.0333],"type":"Point"}
}
=======
{"geometry":{"type":"Point","coordinates":[-110.400000,47.033300]},"type":"Feature","properties":{"hierarchy":["tgn:2251841","tgn:1000001","tgn:7012149","tgn:2001282","tgn:7007524","tgn:7029392"],"placetype":["aat:300008761"],"id":2251841,"name:xx":"Conan Coulee"}}
>>>>>>> 03f74aca74312dbeaf24d7e61306dd6a786dc3d0
