{
  "id": 2029986,
  "type": "Feature",
  "properties": {
    "tgn:hierarchy":[
        "tgn:2029986",
        "tgn:1000001",
        "tgn:7012149",
        "tgn:1002622",
        "tgn:7007251",
        "tgn:7029392"
    ],
    "tgn:id":2029986,
    "tgn:name":"Roxana",
    "tgn:placetype":[
        "aat:300008347"
    ]
},
  "bbox": [],
  "geometry": {"coordinates":[-90.0667,38.8333],"type":"Point"}
}