{
  "id": 1021606,
  "type": "Feature",
  "properties": {
    "tgn:hierarchy":[
        "tgn:1021606",
        "tgn:7016581",
        "tgn:1000047",
        "tgn:7002455",
        "tgn:1000002",
        "tgn:7029392"
    ],
    "tgn:id":1021606,
    "tgn:name":"Igaci",
    "tgn:placetype":[
        "aat:300008347"
    ]
},
  "bbox": [],
  "geometry": {"coordinates":[-36.6333,-9.55],"type":"Point"}
}