{
  "id": 7477490,
  "type": "Feature",
  "properties": {
    "tgn:hierarchy":[
        "tgn:7477490",
        "tgn:1000004",
        "tgn:7001013",
        "tgn:1000141",
        "tgn:7029392"
    ],
    "tgn:id":7477490,
    "tgn:name":"Huandong Qiao",
    "tgn:placetype":[
        "aat:300007836"
    ]
},
  "bbox": [],
  "geometry": {"coordinates":[121.249539,25.098049],"type":"Point"}
}