{
  "id": 7054196,
  "type": "Feature",
  "properties": {
    "tgn:hierarchy":[
        "tgn:7054196",
        "tgn:7003006",
        "tgn:1000003",
        "tgn:7002997",
        "tgn:1000080",
        "tgn:7029392"
    ],
    "tgn:id":7054196,
    "tgn:name":"Canale di Pordelio",
    "tgn:placetype":[
        "aat:300006075"
    ]
},
  "bbox": [],
  "geometry": {"coordinates":[12.433333,45.466667],"type":"Point"}
}