<<<<<<< HEAD
{
  "id": 2766347,
  "type": "Feature",
  "properties": {
    "tgn:hierarchy":[
        "tgn:2766347",
        "tgn:1000001",
        "tgn:7012149",
        "tgn:7007157",
        "tgn:1002858",
        "tgn:7029392"
    ],
    "tgn:id":2766347,
    "tgn:name":"White Mountain",
    "tgn:placetype":[
        "aat:300008798"
    ]
},
  "bbox": [],
  "geometry": {"coordinates":[-116.7167,32.6333],"type":"Point"}
}
=======
{"geometry":{"type":"Point","coordinates":[-116.716700,32.633300]},"type":"Feature","properties":{"hierarchy":["tgn:2766347","tgn:1000001","tgn:7012149","tgn:7007157","tgn:1002858","tgn:7029392"],"placetype":["aat:300008798"],"id":2766347,"name:xx":"White Mountain"}}
>>>>>>> 03f74aca74312dbeaf24d7e61306dd6a786dc3d0
