{
  "id": 2105600,
  "type": "Feature",
  "properties": {
    "tgn:hierarchy":[
        "tgn:2105600",
        "tgn:1000001",
        "tgn:2001936",
        "tgn:7012149",
        "tgn:7007826",
        "tgn:7029392"
    ],
    "tgn:id":2105600,
    "tgn:name":"Leming",
    "tgn:placetype":[
        "aat:300008347"
    ]
},
  "bbox": [],
  "geometry": {"coordinates":[-98.4833,29.0667],"type":"Point"}
}