{
  "id": 7486426,
  "type": "Feature",
  "properties": {
    "tgn:hierarchy":[
        "tgn:7486426",
        "tgn:7001010",
        "tgn:1000004",
        "tgn:1000141",
        "tgn:7029392"
    ],
    "tgn:id":7486426,
    "tgn:name":"Maogongyue Shan",
    "tgn:placetype":[
        "aat:300008798"
    ]
},
  "bbox": [],
  "geometry": {"coordinates":[121.48051,23.638379],"type":"Point"}
}