{
  "id": 7500429,
  "type": "Feature",
  "properties": {
    "tgn:hierarchy":[
        "tgn:7500429",
        "tgn:7001004",
        "tgn:1000004",
        "tgn:1000141",
        "tgn:7029392"
    ],
    "tgn:id":7500429,
    "tgn:name":"Cixian Gong",
    "tgn:placetype":[
        "aat:300007595"
    ]
},
  "bbox": [],
  "geometry": {"coordinates":[120.448611,22.771667],"type":"Point"}
}