{
  "id": 7552275,
  "type": "Feature",
  "properties": {
    "tgn:hierarchy":[
        "tgn:7552275",
        "tgn:1000004",
        "tgn:7000198",
        "tgn:7031783",
        "tgn:7029392"
    ],
    "tgn:id":7552275,
    "tgn:name:en":"Manh\u0101tu",
    "tgn:placetype":[
        "aat:300008347"
    ]
},
  "bbox": [],
  "geometry": {"coordinates":[85.04048,22.841911],"type":"Point"}
}