{
  "id": 7291009,
  "type": "Feature",
  "properties": {
    "tgn:hierarchy":[
        "tgn:7291009",
        "tgn:1001637",
        "tgn:1000049",
        "tgn:1000002",
        "tgn:7029392"
    ],
    "tgn:id":7291009,
    "tgn:name":"Cule, Altos de",
    "tgn:placetype":[
        "aat:300008795"
    ]
},
  "bbox": [],
  "geometry": {"coordinates":[-71.916667,-38.016667],"type":"Point"}
}