{
  "id": 2275569,
  "type": "Feature",
  "properties": {
    "tgn:hierarchy":[
        "tgn:2275569",
        "tgn:1000001",
        "tgn:7012149",
        "tgn:1002744",
        "tgn:7007255",
        "tgn:7029392"
    ],
    "tgn:id":2275569,
    "tgn:name":"Darby Creek",
    "tgn:placetype":[
        "aat:300008706"
    ]
},
  "bbox": [],
  "geometry": {"coordinates":[-85.4333,38.3833],"type":"Point"}
}