{
  "id": 2143538,
  "type": "Feature",
  "properties": {
    "tgn:hierarchy":[
        "tgn:2143538",
        "tgn:1000001",
        "tgn:7012149",
        "tgn:2001541",
        "tgn:7007709",
        "tgn:7029392"
    ],
    "tgn:id":2143538,
    "tgn:name":"Bailey Town",
    "tgn:placetype":[
        "aat:300008347"
    ]
},
  "bbox": [],
  "geometry": {"coordinates":[-80.1333,36.3167],"type":"Point"}
}