{
  "id": 7285028,
  "type": "Feature",
  "properties": {
    "tgn:hierarchy":[
        "tgn:7285028",
        "tgn:1001699",
        "tgn:1000049",
        "tgn:1000002",
        "tgn:7029392"
    ],
    "tgn:id":7285028,
    "tgn:name":"Quicav\u00ed",
    "tgn:placetype":[
        "aat:300008347"
    ]
},
  "bbox": [],
  "geometry": {"coordinates":[-73.372778,-42.255],"type":"Point"}
}