{
  "id": 1113139,
  "type": "Feature",
  "properties": {
    "tgn:hierarchy":[
        "tgn:1113139",
        "tgn:1000004",
        "tgn:1001481",
        "tgn:1000135",
        "tgn:7029392"
    ],
    "tgn:id":1113139,
    "tgn:name":"Honda Bay",
    "tgn:placetype":[
        "aat:300132316"
    ]
},
  "bbox": [],
  "geometry": {"coordinates":[118.8167,9.8833],"type":"Point"}
}