{
  "id": 2656084,
  "type": "Feature",
  "properties": {
    "tgn:hierarchy":[
        "tgn:2656084",
        "tgn:1000001",
        "tgn:2002102",
        "tgn:7012149",
        "tgn:7007827",
        "tgn:7029392"
    ],
    "tgn:id":2656084,
    "tgn:name":"Shaw Spring",
    "tgn:placetype":[
        "aat:300008697"
    ]
},
  "bbox": [],
  "geometry": {"coordinates":[-112.4167,41.35],"type":"Point"}
}