{
  "id": 2653825,
  "type": "Feature",
  "properties": {
    "tgn:hierarchy":[
        "tgn:2653825",
        "tgn:1000001",
        "tgn:7012149",
        "tgn:2001917",
        "tgn:7007825",
        "tgn:7029392"
    ],
    "tgn:id":2653825,
    "tgn:name":"Sexton Pond",
    "tgn:placetype":[
        "aat:300008680"
    ]
},
  "bbox": [],
  "geometry": {"coordinates":[-87.8833,36.4333],"type":"Point"}
}