{
  "id": 7423565,
  "type": "Feature",
  "properties": {
    "tgn:hierarchy":[
        "tgn:7423565",
        "tgn:1000001",
        "tgn:1001960",
        "tgn:7005560",
        "tgn:7029392"
    ],
    "tgn:id":7423565,
    "tgn:name":"Escalante",
    "tgn:placetype":[
        "aat:300008347"
    ]
},
  "bbox": [],
  "geometry": {"coordinates":[-110.683333,28.583333],"type":"Point"}
}