{
  "id": 2723342,
  "type": "Feature",
  "properties": {
    "tgn:hierarchy":[
        "tgn:2723342",
        "tgn:1000001",
        "tgn:7012149",
        "tgn:2000449",
        "tgn:7007248",
        "tgn:7029392"
    ],
    "tgn:id":2723342,
    "tgn:name":"Tobe Lake",
    "tgn:placetype":[
        "aat:300008680"
    ]
},
  "bbox": [],
  "geometry": {"coordinates":[-82.95,32.7333],"type":"Point"}
}