{
  "id": 7135017,
  "type": "Feature",
  "properties": {
    "tgn:hierarchy":[
        "tgn:7135017",
        "tgn:1000003",
        "tgn:7003676",
        "tgn:7000084",
        "tgn:7029392"
    ],
    "tgn:id":7135017,
    "tgn:name":"Mudderpott",
    "tgn:placetype":[
        "aat:300000206"
    ]
},
  "bbox": [],
  "geometry": {"coordinates":[7.333333,53.45],"type":"Point"}
}