{
  "id": 7586596,
  "type": "Feature",
  "properties": {
    "tgn:hierarchy":[
        "tgn:7586596",
        "tgn:1000004",
        "tgn:7000198",
        "tgn:7000799",
        "tgn:7029392"
    ],
    "tgn:id":7586596,
    "tgn:name:en":"W\u0101tal Sar",
    "tgn:placetype":[
        "aat:300008688"
    ]
},
  "bbox": [],
  "geometry": {"coordinates":[74.986111,34.458333],"type":"Point"}
}