{
  "id": 7574537,
  "type": "Feature",
  "properties": {
    "tgn:hierarchy":[
        "tgn:7574537",
        "tgn:1000004",
        "tgn:7000198",
        "tgn:7000799",
        "tgn:7029392"
    ],
    "tgn:id":7574537,
    "tgn:name:en":"Kunsang Group",
    "tgn:placetype":[
        "aat:300008795"
    ]
},
  "bbox": [],
  "geometry": {"coordinates":[78.050732,34.485017],"type":"Point"}
}