{
  "id": 2117919,
  "type": "Feature",
  "properties": {
    "tgn:hierarchy":[
        "tgn:2117919",
        "tgn:1000001",
        "tgn:2002259",
        "tgn:7012149",
        "tgn:7013961",
        "tgn:7029392"
    ],
    "tgn:id":2117919,
    "tgn:name":"Cressmont",
    "tgn:placetype":[
        "aat:300008347",
        "aat:300387210"
    ]
},
  "bbox": [],
  "geometry": {"coordinates":[-80.9667,38.45],"type":"Point"}
}