<<<<<<< HEAD
{
  "id": 2402571,
  "type": "Feature",
  "properties": {
    "tgn:hierarchy":[
        "tgn:2402571",
        "tgn:1002215",
        "tgn:1000001",
        "tgn:7012149",
        "tgn:7007565",
        "tgn:7029392"
    ],
    "tgn:id":2402571,
    "tgn:name":"Hospitality Brook",
    "tgn:placetype":[
        "aat:300008699"
    ]
},
  "bbox": [],
  "geometry": {"coordinates":[-74.5333,39.7167],"type":"Point"}
}
=======
{"geometry":{"type":"Point","coordinates":[-74.533300,39.716700]},"type":"Feature","properties":{"hierarchy":["tgn:2402571","tgn:1002215","tgn:1000001","tgn:7012149","tgn:7007565","tgn:7029392"],"placetype":["aat:300008699"],"id":2402571,"name:xx":"Hospitality Brook"}}
>>>>>>> 03f74aca74312dbeaf24d7e61306dd6a786dc3d0
