{
  "id": 2402571,
  "type": "Feature",
  "properties": {
    "tgn:hierarchy":[
        "tgn:2402571",
        "tgn:1002215",
        "tgn:1000001",
        "tgn:7012149",
        "tgn:7007565",
        "tgn:7029392"
    ],
    "tgn:id":2402571,
    "tgn:name":"Hospitality Brook",
    "tgn:placetype":[
        "aat:300008699"
    ]
},
  "bbox": [],
  "geometry": {"coordinates":[-74.5333,39.7167],"type":"Point"}
}