<<<<<<< HEAD
{
  "id": 2155201,
  "type": "Feature",
  "properties": {
    "tgn:hierarchy":[
        "tgn:2155201",
        "tgn:1000001",
        "tgn:2001413",
        "tgn:7012149",
        "tgn:7007526",
        "tgn:7029392"
    ],
    "tgn:id":2155201,
    "tgn:name":"Bear Mine",
    "tgn:placetype":[
        "aat:300000390"
    ]
},
  "bbox": [],
  "geometry": {"coordinates":[-116.0333,40.1167],"type":"Point"}
}
=======
{"geometry":{"type":"Point","coordinates":[-116.033300,40.116700]},"type":"Feature","properties":{"hierarchy":["tgn:2155201","tgn:1000001","tgn:2001413","tgn:7012149","tgn:7007526","tgn:7029392"],"placetype":["aat:300000390"],"id":2155201,"name:xx":"Bear Mine"}}
>>>>>>> 03f74aca74312dbeaf24d7e61306dd6a786dc3d0
