{
  "id": 2155201,
  "type": "Feature",
  "properties": {
    "tgn:hierarchy":[
        "tgn:2155201",
        "tgn:1000001",
        "tgn:2001413",
        "tgn:7012149",
        "tgn:7007526",
        "tgn:7029392"
    ],
    "tgn:id":2155201,
    "tgn:name":"Bear Mine",
    "tgn:placetype":[
        "aat:300000390"
    ]
},
  "bbox": [],
  "geometry": {"coordinates":[-116.0333,40.1167],"type":"Point"}
}