{
  "id": 2688901,
  "type": "Feature",
  "properties": {
    "tgn:hierarchy":[
        "tgn:2688901",
        "tgn:2000947",
        "tgn:1000001",
        "tgn:7012149",
        "tgn:7007520",
        "tgn:7029392"
    ],
    "tgn:id":2688901,
    "tgn:name":"Spurr River",
    "tgn:placetype":[
        "aat:300008707"
    ]
},
  "bbox": [],
  "geometry": {"coordinates":[-88.1833,46.5333],"type":"Point"}
}