{
  "id": 2252688,
  "type": "Feature",
  "properties": {
    "tgn:hierarchy":[
        "tgn:2252688",
        "tgn:1000001",
        "tgn:7012149",
        "tgn:2001247",
        "tgn:7007523",
        "tgn:7029392"
    ],
    "tgn:id":2252688,
    "tgn:name":"Conner Hollow",
    "tgn:placetype":[
        "aat:300008761"
    ]
},
  "bbox": [],
  "geometry": {"coordinates":[-91.5167,37.1833],"type":"Point"}
}