{
  "id": 2468776,
  "type": "Feature",
  "properties": {
    "tgn:hierarchy":[
        "tgn:2468776",
        "tgn:1000001",
        "tgn:7012149",
        "tgn:2000850",
        "tgn:7007255",
        "tgn:7029392"
    ],
    "tgn:id":2468776,
    "tgn:name":"Long Ridge",
    "tgn:placetype":[
        "aat:300266640"
    ]
},
  "bbox": [],
  "geometry": {"coordinates":[-84.6667,36.9333],"type":"Point"}
}