{
  "id": 7146601,
  "type": "Feature",
  "properties": {
    "tgn:hierarchy":[
        "tgn:7146601",
        "tgn:7003692",
        "tgn:1000003",
        "tgn:7000084",
        "tgn:7029392"
    ],
    "tgn:id":7146601,
    "tgn:name":"Kopfhalden",
    "tgn:placetype":[
        "aat:300000206"
    ]
},
  "bbox": [],
  "geometry": {"coordinates":[9.833333,47.766667],"type":"Point"}
}