{
  "id": 7061271,
  "type": "Feature",
  "properties": {
    "tgn:hierarchy":[
        "tgn:7061271",
        "tgn:1000003",
        "tgn:7003678",
        "tgn:7000084",
        "tgn:7029392"
    ],
    "tgn:id":7061271,
    "tgn:name":"B\u00e4derskopf",
    "tgn:placetype":[
        "aat:300008777"
    ]
},
  "bbox": [],
  "geometry": {"coordinates":[9.183333,50.383333],"type":"Point"}
}