{
  "id": 7293403,
  "type": "Feature",
  "properties": {
    "tgn:hierarchy":[
        "tgn:7293403",
        "tgn:7002818",
        "tgn:1001647",
        "tgn:1000003",
        "tgn:1000095",
        "tgn:7029392"
    ],
    "tgn:id":7293403,
    "tgn:name":"Villar de Ca\u00f1as",
    "tgn:placetype":[
        "aat:300008347"
    ]
},
  "bbox": [],
  "geometry": {"coordinates":[-2.55,39.783333],"type":"Point"}
}