<<<<<<< HEAD
{
  "id": 2330147,
  "type": "Feature",
  "properties": {
    "tgn:hierarchy":[
        "tgn:2330147",
        "tgn:1000001",
        "tgn:2001269",
        "tgn:7012149",
        "tgn:7007524",
        "tgn:7029392"
    ],
    "tgn:id":2330147,
    "tgn:name":"Flaherty Coulee",
    "tgn:placetype":[
        "aat:300008761"
    ]
},
  "bbox": [],
  "geometry": {"coordinates":[-106.0167,48.9167],"type":"Point"}
}
=======
{"geometry":{"type":"Point","coordinates":[-106.016700,48.916700]},"type":"Feature","properties":{"hierarchy":["tgn:2330147","tgn:1000001","tgn:2001269","tgn:7012149","tgn:7007524","tgn:7029392"],"placetype":["aat:300008761"],"id":2330147,"name:xx":"Flaherty Coulee"}}
>>>>>>> 03f74aca74312dbeaf24d7e61306dd6a786dc3d0
