<<<<<<< HEAD
{
  "id": 2409464,
  "type": "Feature",
  "properties": {
    "tgn:hierarchy":[
        "tgn:2409464",
        "tgn:1000001",
        "tgn:1002493",
        "tgn:7012149",
        "tgn:7007565",
        "tgn:7029392"
    ],
    "tgn:id":2409464,
    "tgn:name":"Idell",
    "tgn:placetype":[
        "aat:300008347"
    ]
},
  "bbox": [],
  "geometry": {"coordinates":[-75.0167,40.45],"type":"Point"}
}
=======
{"geometry":{"type":"Point","coordinates":[-75.016700,40.450000]},"type":"Feature","properties":{"hierarchy":["tgn:2409464","tgn:1000001","tgn:1002493","tgn:7012149","tgn:7007565","tgn:7029392"],"placetype":["aat:300008347"],"id":2409464,"name:xx":"Idell"}}
>>>>>>> 03f74aca74312dbeaf24d7e61306dd6a786dc3d0
