{
  "id": 2163849,
  "type": "Feature",
  "properties": {
    "tgn:hierarchy":[
        "tgn:2163849",
        "tgn:1000001",
        "tgn:7012149",
        "tgn:1002913",
        "tgn:7007919",
        "tgn:7029392"
    ],
    "tgn:id":2163849,
    "tgn:name":"Berea",
    "tgn:placetype":[
        "aat:300008347"
    ]
},
  "bbox": [],
  "geometry": {"coordinates":[-77.5167,38.35],"type":"Point"}
}