{
  "id": 7054288,
  "type": "Feature",
  "properties": {
    "tgn:hierarchy":[
        "tgn:7054288",
        "tgn:1003429",
        "tgn:1000003",
        "tgn:7003240",
        "tgn:1000080",
        "tgn:7029392"
    ],
    "tgn:id":7054288,
    "tgn:name":"Pontenuovo, Fosso di",
    "tgn:placetype":[
        "aat:300008699"
    ]
},
  "bbox": [],
  "geometry": {"coordinates":[13.15,43.483333],"type":"Point"}
}