{
  "id": 7312612,
  "type": "Feature",
  "properties": {
    "tgn:hierarchy":[
        "tgn:7312612",
        "tgn:1001708",
        "tgn:1000049",
        "tgn:1000002",
        "tgn:7029392"
    ],
    "tgn:id":7312612,
    "tgn:name":"La Rana",
    "tgn:placetype":[
        "aat:300008347"
    ]
},
  "bbox": [],
  "geometry": {"coordinates":[-70.666667,-33.816667],"type":"Point"}
}