{
  "id": 2597205,
  "type": "Feature",
  "properties": {
    "tgn:hierarchy":[
        "tgn:2597205",
        "tgn:1000001",
        "tgn:1002213",
        "tgn:7012149",
        "tgn:7007710",
        "tgn:7029392"
    ],
    "tgn:id":2597205,
    "tgn:name":"Prahls Island",
    "tgn:placetype":[
        "aat:300008791"
    ]
},
  "bbox": [],
  "geometry": {"coordinates":[-75.0667,40.4333],"type":"Point"}
}