{
  "id": 2491328,
  "type": "Feature",
  "properties": {
    "tgn:hierarchy":[
        "tgn:2491328",
        "tgn:1000001",
        "tgn:2001702",
        "tgn:7012149",
        "tgn:7007708",
        "tgn:7029392"
    ],
    "tgn:id":2491328,
    "tgn:name":"Maple Creek",
    "tgn:placetype":[
        "aat:300008706"
    ]
},
  "bbox": [],
  "geometry": {"coordinates":[-123.8833,43.15],"type":"Point"}
}