{
  "id": 7253670,
  "type": "Feature",
  "properties": {
    "tgn:hierarchy":[
        "tgn:7253670",
        "tgn:7003458",
        "tgn:1000003",
        "tgn:1000063",
        "tgn:7018236",
        "tgn:7029392"
    ],
    "tgn:id":7253670,
    "tgn:name":"Tenheide",
    "tgn:placetype":[
        "aat:300008347"
    ]
},
  "bbox": [],
  "geometry": {"coordinates":[3.422087,50.879741],"type":"Point"}
}