{
  "id": 2350216,
  "type": "Feature",
  "properties": {
    "tgn:hierarchy":[
        "tgn:2350216",
        "tgn:1000001",
        "tgn:7012149",
        "tgn:7007923",
        "tgn:7029392"
    ],
    "tgn:id":2350216,
    "tgn:name":"Gin Creek",
    "tgn:placetype":[
        "aat:300008706"
    ]
},
  "bbox": [],
  "geometry": {"coordinates":[-106.9833,44.5333],"type":"Point"}
}