{
  "id": 7029042,
  "type": "Feature",
  "properties": {
    "tgn:hierarchy":[
        "tgn:7029042",
        "tgn:7002445",
        "tgn:1000003",
        "tgn:7019057",
        "tgn:7008591",
        "tgn:7029392"
    ],
    "tgn:id":7029042,
    "tgn:name":"Kirk Ella",
    "tgn:placetype":[
        "aat:300008347",
        "aat:300008372"
    ]
},
  "bbox": [],
  "geometry": {"coordinates":[-0.45,53.75],"type":"Point"}
}