<<<<<<< HEAD
{
  "id": 7375159,
  "type": "Feature",
  "properties": {
    "tgn:hierarchy":[
        "tgn:7375159",
        "tgn:7005581",
        "tgn:1000001",
        "tgn:7005560",
        "tgn:7029392"
    ],
    "tgn:id":7375159,
    "tgn:name":"Rancho La Providencia",
    "tgn:placetype":[
        "aat:300000241"
    ]
},
  "bbox": [],
  "geometry": {"coordinates":[-105.166667,30.266667],"type":"Point"}
}
=======
{"geometry":{"type":"Point","coordinates":[-105.166667,30.266667]},"type":"Feature","properties":{"hierarchy":["tgn:7375159","tgn:7005581","tgn:1000001","tgn:7005560","tgn:7029392"],"placetype":["aat:300000241"],"id":7375159,"name:xx":"Rancho La Providencia"}}
>>>>>>> 03f74aca74312dbeaf24d7e61306dd6a786dc3d0
