{
  "id": 2250413,
  "type": "Feature",
  "properties": {
    "tgn:hierarchy":[
        "tgn:2250413",
        "tgn:1000001",
        "tgn:2002106",
        "tgn:7012149",
        "tgn:7007827",
        "tgn:7029392"
    ],
    "tgn:id":2250413,
    "tgn:name":"Colonial",
    "tgn:placetype":[
        "aat:300008347"
    ]
},
  "bbox": [],
  "geometry": {"coordinates":[-111.8667,40.8667],"type":"Point"}
}