{
  "id": 1058501,
  "type": "Feature",
  "properties": {
    "tgn:hierarchy":[
        "tgn:1058501",
        "tgn:1000004",
        "tgn:7011457",
        "tgn:7014786",
        "tgn:7029392"
    ],
    "tgn:id":1058501,
    "tgn:name":"Podstepnoje",
    "tgn:placetype":[
        "aat:300008347"
    ]
},
  "bbox": [],
  "geometry": {"coordinates":[51.4667,51.1333],"type":"Point"}
}