{
  "id": 7242420,
  "type": "Feature",
  "properties": {
    "tgn:hierarchy":[
        "tgn:7242420",
        "tgn:7003465",
        "tgn:1000003",
        "tgn:1000063",
        "tgn:4012014",
        "tgn:7029392"
    ],
    "tgn:id":7242420,
    "tgn:name":"Lepeuque, Fange",
    "tgn:placetype":[
        "aat:300008903"
    ]
},
  "bbox": [],
  "geometry": {"coordinates":[5.783333,50.233333],"type":"Point"}
}