{
  "id": 2728214,
  "type": "Feature",
  "properties": {
    "tgn:hierarchy":[
        "tgn:2728214",
        "tgn:1000001",
        "tgn:7012149",
        "tgn:2002382",
        "tgn:7007923",
        "tgn:7029392"
    ],
    "tgn:id":2728214,
    "tgn:name":"Travelute Reservoir",
    "tgn:placetype":[
        "aat:300006191"
    ]
},
  "bbox": [],
  "geometry": {"coordinates":[-110.0667,42.8667],"type":"Point"}
}