{
  "id": 2719869,
  "type": "Feature",
  "properties": {
    "tgn:hierarchy":[
        "tgn:2719869",
        "tgn:1000001",
        "tgn:7012149",
        "tgn:1002392",
        "tgn:7007157",
        "tgn:7029392"
    ],
    "tgn:id":2719869,
    "tgn:name":"Three Springs",
    "tgn:placetype":[
        "aat:300008697"
    ]
},
  "bbox": [],
  "geometry": {"coordinates":[-118.9333,36.95],"type":"Point"}
}