<<<<<<< HEAD
{
  "id": 2158274,
  "type": "Feature",
  "properties": {
    "tgn:hierarchy":[
        "tgn:2158274",
        "tgn:1000001",
        "tgn:7016172",
        "tgn:7012149",
        "tgn:2000144",
        "tgn:7029392"
    ],
    "tgn:id":2158274,
    "tgn:name":"Beaver Slough",
    "tgn:placetype":[
        "aat:300008699"
    ]
},
  "bbox": [],
  "geometry": {"coordinates":[-91.9333,33.8],"type":"Point"}
}
=======
{"geometry":{"type":"Point","coordinates":[-91.933300,33.800000]},"type":"Feature","properties":{"hierarchy":["tgn:2158274","tgn:1000001","tgn:7016172","tgn:7012149","tgn:2000144","tgn:7029392"],"placetype":["aat:300008699"],"id":2158274,"name:xx":"Beaver Slough"}}
>>>>>>> 03f74aca74312dbeaf24d7e61306dd6a786dc3d0
