<<<<<<< HEAD
{
  "id": 7052972,
  "type": "Feature",
  "properties": {
    "tgn:hierarchy":[
        "tgn:7052972",
        "tgn:7004595",
        "tgn:7003005",
        "tgn:1000003",
        "tgn:1000080",
        "tgn:7029392"
    ],
    "tgn:id":7052972,
    "tgn:name":"Ienga di Prata, Fosso",
    "tgn:placetype":[
        "aat:300008699"
    ]
},
  "bbox": [],
  "geometry": {"coordinates":[14.666667,41.133333],"type":"Point"}
}
=======
{"geometry":{"type":"Point","coordinates":[14.666667,41.133333]},"type":"Feature","properties":{"hierarchy":["tgn:7052972","tgn:7004595","tgn:7003005","tgn:1000003","tgn:1000080","tgn:7029392"],"placetype":["aat:300008699"],"id":7052972,"name:xx":"Ienga di Prata, Fosso"}}
>>>>>>> 03f74aca74312dbeaf24d7e61306dd6a786dc3d0
