{
  "id": 7205013,
  "type": "Feature",
  "properties": {
    "tgn:hierarchy":[
        "tgn:7205013",
        "tgn:1000003",
        "tgn:7000094",
        "tgn:7000084",
        "tgn:7029392"
    ],
    "tgn:id":7205013,
    "tgn:name":"Klementelvitz",
    "tgn:placetype":[
        "aat:300008347"
    ]
},
  "bbox": [],
  "geometry": {"coordinates":[13.583333,54.516667],"type":"Point"}
}