{
  "id": 7034856,
  "type": "Feature",
  "properties": {
    "tgn:hierarchy":[
        "tgn:7034856",
        "tgn:7015163",
        "tgn:1000003",
        "tgn:7003121",
        "tgn:1000080",
        "tgn:7029392"
    ],
    "tgn:id":7034856,
    "tgn:name":"Monte Balvarigas",
    "tgn:placetype":[
        "aat:300008347"
    ]
},
  "bbox": [],
  "geometry": {"coordinates":[8.650278,40.786667],"type":"Point"}
}