{
  "id": 7508600,
  "type": "Feature",
  "properties": {
    "tgn:hierarchy":[
        "tgn:7508600",
        "tgn:1008380",
        "tgn:1000226",
        "tgn:7016827",
        "tgn:1000006",
        "tgn:7029392"
    ],
    "tgn:id":7508600,
    "tgn:name:en":"Otakeho Stream",
    "tgn:placetype":[
        "aat:300008699"
    ]
},
  "bbox": [],
  "geometry": {"coordinates":[174.05,-39.566667],"type":"Point"}
}