{
  "id": 2412253,
  "type": "Feature",
  "properties": {
    "tgn:hierarchy":[
        "tgn:2412253",
        "tgn:1000001",
        "tgn:2002102",
        "tgn:7012149",
        "tgn:7007827",
        "tgn:7029392"
    ],
    "tgn:id":2412253,
    "tgn:name":"Indian Spring",
    "tgn:placetype":[
        "aat:300008697"
    ]
},
  "bbox": [],
  "geometry": {"coordinates":[-113.9667,41.2833],"type":"Point"}
}