{
  "id": 7469350,
  "type": "Feature",
  "properties": {
    "tgn:hierarchy":[
        "tgn:7469350",
        "tgn:1000004",
        "tgn:7004300",
        "tgn:1000141",
        "tgn:7029392"
    ],
    "tgn:id":7469350,
    "tgn:name":"Xiping",
    "tgn:placetype":[
        "aat:300008347"
    ]
},
  "bbox": [],
  "geometry": {"coordinates":[119.508333,23.269722],"type":"Point"}
}