{
  "id": 2682877,
  "type": "Feature",
  "properties": {
    "tgn:hierarchy":[
        "tgn:2682877",
        "tgn:1000001",
        "tgn:7012149",
        "tgn:2000906",
        "tgn:7007256",
        "tgn:7029392"
    ],
    "tgn:id":2682877,
    "tgn:name":"Southwood Ridge",
    "tgn:placetype":[
        "aat:300008347"
    ]
},
  "bbox": [],
  "geometry": {"coordinates":[-90.4333,30.4667],"type":"Point"}
}