{
  "id": 7013179,
  "type": "Feature",
  "properties": {
    "tgn:hierarchy":[
        "tgn:7013179",
        "tgn:1000004",
        "tgn:7011523",
        "tgn:7002435",
        "tgn:7029392"
    ],
    "tgn:id":7013179,
    "tgn:name":"Dmitriyev Usad",
    "tgn:placetype":[
        "aat:300008347"
    ]
},
  "bbox": [],
  "geometry": {"coordinates":[43.2667,54.2333],"type":"Point"}
}