{
  "id": 7408136,
  "type": "Feature",
  "properties": {
    "tgn:hierarchy":[
        "tgn:7408136",
        "tgn:1000001",
        "tgn:1001893",
        "tgn:7005560",
        "tgn:7029392"
    ],
    "tgn:id":7408136,
    "tgn:name":"Rinc\u00f3n de la Cofrad\u00eda",
    "tgn:placetype":[
        "aat:300008347"
    ]
},
  "bbox": [],
  "geometry": {"coordinates":[-100.266667,18.733333],"type":"Point"}
}