{
  "id": 2441425,
  "type": "Feature",
  "properties": {
    "tgn:hierarchy":[
        "tgn:2441425",
        "tgn:1000001",
        "tgn:7012149",
        "tgn:2002326",
        "tgn:7007922",
        "tgn:7029392"
    ],
    "tgn:id":2441425,
    "tgn:name":"Knudson Branch",
    "tgn:placetype":[
        "aat:300008699"
    ]
},
  "bbox": [],
  "geometry": {"coordinates":[-89.9167,43.0667],"type":"Point"}
}