{
  "id": 2697028,
  "type": "Feature",
  "properties": {
    "tgn:hierarchy":[
        "tgn:2697028",
        "tgn:1000001",
        "tgn:7012149",
        "tgn:2001067",
        "tgn:7007521",
        "tgn:7029392"
    ],
    "tgn:id":2697028,
    "tgn:name":"Stonich Island",
    "tgn:placetype":[
        "aat:300008791"
    ]
},
  "bbox": [],
  "geometry": {"coordinates":[-92.2833,47.85],"type":"Point"}
}