{
  "id": 2765647,
  "type": "Feature",
  "properties": {
    "tgn:hierarchy":[
        "tgn:2765647",
        "tgn:7006450",
        "tgn:1000001",
        "tgn:7030547",
        "tgn:7012149",
        "tgn:7029392"
    ],
    "tgn:id":2765647,
    "tgn:name":"White Creek",
    "tgn:placetype":[
        "aat:300008706"
    ]
},
  "bbox": [],
  "geometry": {"coordinates":[-151.5333,63.0667],"type":"Point"}
}