{
  "id": 7371094,
  "type": "Feature",
  "properties": {
    "tgn:hierarchy":[
        "tgn:7371094",
        "tgn:7005581",
        "tgn:1000001",
        "tgn:7005560",
        "tgn:7029392"
    ],
    "tgn:id":7371094,
    "tgn:name":"Humarizo",
    "tgn:placetype":[
        "aat:300008347"
    ]
},
  "bbox": [],
  "geometry": {"coordinates":[-106.766667,27.25],"type":"Point"}
}