<<<<<<< HEAD
{
  "id": 7363263,
  "type": "Feature",
  "properties": {
    "tgn:hierarchy":[
        "tgn:7363263",
        "tgn:1000001",
        "tgn:1001960",
        "tgn:7005560",
        "tgn:7029392"
    ],
    "tgn:id":7363263,
    "tgn:name":"El Fraile, Cerro",
    "tgn:placetype":[
        "aat:300008795"
    ]
},
  "bbox": [],
  "geometry": {"coordinates":[-109.383333,30.1],"type":"Point"}
}
=======
{"geometry":{"type":"Point","coordinates":[-109.383333,30.100000]},"type":"Feature","properties":{"hierarchy":["tgn:7363263","tgn:1000001","tgn:1001960","tgn:7005560","tgn:7029392"],"placetype":["aat:300008795"],"id":7363263,"name:xx":"El Fraile, Cerro"}}
>>>>>>> 03f74aca74312dbeaf24d7e61306dd6a786dc3d0
