{
  "id": 7371176,
  "type": "Feature",
  "properties": {
    "tgn:hierarchy":[
        "tgn:7371176",
        "tgn:7005583",
        "tgn:1000001",
        "tgn:7005560",
        "tgn:7029392"
    ],
    "tgn:id":7371176,
    "tgn:name":"Jicorica",
    "tgn:placetype":[
        "aat:300008347"
    ]
},
  "bbox": [],
  "geometry": {"coordinates":[-104.783333,25.383333],"type":"Point"}
}