{
  "id": 7485825,
  "type": "Feature",
  "properties": {
    "tgn:hierarchy":[
        "tgn:7485825",
        "tgn:7488858",
        "tgn:1000004",
        "tgn:1000141",
        "tgn:7029392"
    ],
    "tgn:id":7485825,
    "tgn:name":"Hehuan Jianshan",
    "tgn:placetype":[
        "aat:300008798"
    ]
},
  "bbox": [],
  "geometry": {"coordinates":[121.283611,24.144722],"type":"Point"}
}