{
  "id": 7190778,
  "type": "Feature",
  "properties": {
    "tgn:hierarchy":[
        "tgn:7190778",
        "tgn:7003669",
        "tgn:1000003",
        "tgn:7000084",
        "tgn:7029392"
    ],
    "tgn:id":7190778,
    "tgn:name":"Fegershof",
    "tgn:placetype":[
        "aat:300000206"
    ]
},
  "bbox": [],
  "geometry": {"coordinates":[12.516667,49.283333],"type":"Point"}
}