{
  "id": 7032397,
  "type": "Feature",
  "properties": {
    "tgn:hierarchy":[
        "tgn:7032397",
        "tgn:7000273",
        "tgn:1000004",
        "tgn:7000893",
        "tgn:1000120",
        "tgn:7029392"
    ],
    "tgn:id":7032397,
    "tgn:name":"Sannai Maruyama",
    "tgn:placetype":[
        "aat:300008347",
        "aat:300000810",
        "aat:300167671",
        "aat:300018523"
    ]
},
  "bbox": [],
  "geometry": {"coordinates":[140.695,40.811],"type":"Point"}
}