{
  "id": 1054245,
  "type": "Feature",
  "properties": {
    "tgn:hierarchy":[
        "tgn:1054245",
        "tgn:1000004",
        "tgn:7011500",
        "tgn:7002435",
        "tgn:7029392"
    ],
    "tgn:id":1054245,
    "tgn:name":"Gusinoozersk",
    "tgn:placetype":[
        "aat:300008347"
    ]
},
  "bbox": [],
  "geometry": {"coordinates":[106.5833,51.3333],"type":"Point"}
}