{
  "id": 1135165,
  "type": "Feature",
  "properties": {
    "tgn:hierarchy":[
        "tgn:1135165",
        "tgn:1000001",
        "tgn:7012149",
        "tgn:7029392"
    ],
    "tgn:id":1135165,
    "tgn:name":"Beaver Brook",
    "tgn:placetype":[
        "aat:300008703"
    ]
},
  "bbox": [],
  "geometry": {"coordinates":[-72.1333,41.7333],"type":"Point"}
}