{
  "id": 1018372,
  "type": "Feature",
  "properties": {
    "tgn:hierarchy":[
        "tgn:1018372",
        "tgn:7005586",
        "tgn:1000001",
        "tgn:7005560",
        "tgn:7029392"
    ],
    "tgn:id":1018372,
    "tgn:name":"Talpa de Allende",
    "tgn:placetype":[
        "aat:300008347"
    ]
},
  "bbox": [],
  "geometry": {"coordinates":[-104.816667,20.383333],"type":"Point"}
}