{
  "id": 2250052,
  "type": "Feature",
  "properties": {
    "tgn:hierarchy":[
        "tgn:2250052",
        "tgn:1000001",
        "tgn:1002480",
        "tgn:7012149",
        "tgn:7007564",
        "tgn:7029392"
    ],
    "tgn:id":2250052,
    "tgn:name":"Collins Brook",
    "tgn:placetype":[
        "aat:300008699"
    ]
},
  "bbox": [],
  "geometry": {"coordinates":[-71.85,43.0333],"type":"Point"}
}