<<<<<<< HEAD
{
  "id": 2250052,
  "type": "Feature",
  "properties": {
    "tgn:hierarchy":[
        "tgn:2250052",
        "tgn:1000001",
        "tgn:1002480",
        "tgn:7012149",
        "tgn:7007564",
        "tgn:7029392"
    ],
    "tgn:id":2250052,
    "tgn:name":"Collins Brook",
    "tgn:placetype":[
        "aat:300008699"
    ]
},
  "bbox": [],
  "geometry": {"coordinates":[-71.85,43.0333],"type":"Point"}
}
=======
{"geometry":{"type":"Point","coordinates":[-71.850000,43.033300]},"type":"Feature","properties":{"hierarchy":["tgn:2250052","tgn:1000001","tgn:1002480","tgn:7012149","tgn:7007564","tgn:7029392"],"placetype":["aat:300008699"],"id":2250052,"name:xx":"Collins Brook"}}
>>>>>>> 03f74aca74312dbeaf24d7e61306dd6a786dc3d0
