{
  "id": 2565081,
  "type": "Feature",
  "properties": {
    "tgn:hierarchy":[
        "tgn:2565081",
        "tgn:1000001",
        "tgn:7012149",
        "tgn:2001855",
        "tgn:7007825",
        "tgn:7029392"
    ],
    "tgn:id":2565081,
    "tgn:name":"Pages Branch",
    "tgn:placetype":[
        "aat:300008699"
    ]
},
  "bbox": [],
  "geometry": {"coordinates":[-86.7333,36.2167],"type":"Point"}
}