{
  "id": 7233587,
  "type": "Feature",
  "properties": {
    "tgn:hierarchy":[
        "tgn:7233587",
        "tgn:7002725",
        "tgn:7002715",
        "tgn:1000003",
        "tgn:1000074",
        "tgn:7029392"
    ],
    "tgn:id":7233587,
    "tgn:name":"Dip\u00f3tamos",
    "tgn:placetype":[
        "aat:300008347"
    ]
},
  "bbox": [],
  "geometry": {"coordinates":[22.951944,41.021389],"type":"Point"}
}