{
  "id": 7417664,
  "type": "Feature",
  "properties": {
    "tgn:hierarchy":[
        "tgn:7417664",
        "tgn:7005584",
        "tgn:1000001",
        "tgn:7005560",
        "tgn:7029392"
    ],
    "tgn:id":7417664,
    "tgn:name":"El Puerto",
    "tgn:placetype":[
        "aat:300008347"
    ]
},
  "bbox": [],
  "geometry": {"coordinates":[-100.394722,20.303611],"type":"Point"}
}