{
  "id": 2340132,
  "type": "Feature",
  "properties": {
    "tgn:hierarchy":[
        "tgn:2340132",
        "tgn:1000001",
        "tgn:2001342",
        "tgn:7012149",
        "tgn:7007525",
        "tgn:7029392"
    ],
    "tgn:id":2340132,
    "tgn:name":"Fremont Cutoff Ditch",
    "tgn:placetype":[
        "aat:300006075"
    ]
},
  "bbox": [],
  "geometry": {"coordinates":[-96.6333,41.4833],"type":"Point"}
}