{
  "id": 2072021,
  "type": "Feature",
  "properties": {
    "tgn:hierarchy":[
        "tgn:2072021",
        "tgn:1000001",
        "tgn:7012149",
        "tgn:1002882",
        "tgn:7007568",
        "tgn:7029392"
    ],
    "tgn:id":2072021,
    "tgn:name":"Romulus",
    "tgn:placetype":[
        "aat:300008347"
    ]
},
  "bbox": [],
  "geometry": {"coordinates":[-76.8333,42.75],"type":"Point"}
}