{
  "id": 7412607,
  "type": "Feature",
  "properties": {
    "tgn:hierarchy":[
        "tgn:7412607",
        "tgn:1000001",
        "tgn:7005598",
        "tgn:7005560",
        "tgn:7029392"
    ],
    "tgn:id":7412607,
    "tgn:name":"Cuautla",
    "tgn:placetype":[
        "aat:300008347"
    ]
},
  "bbox": [],
  "geometry": {"coordinates":[-98.230556,19.308333],"type":"Point"}
}