{
  "id": 2644590,
  "type": "Feature",
  "properties": {
    "tgn:hierarchy":[
        "tgn:2644590",
        "tgn:1000001",
        "tgn:7012149",
        "tgn:7007157",
        "tgn:1002894",
        "tgn:7029392"
    ],
    "tgn:id":2644590,
    "tgn:name":"Sardine Peak",
    "tgn:placetype":[
        "aat:300008798"
    ]
},
  "bbox": [],
  "geometry": {"coordinates":[-120.1833,39.5333],"type":"Point"}
}