{
  "id": 2278475,
  "type": "Feature",
  "properties": {
    "tgn:hierarchy":[
        "tgn:2278475",
        "tgn:1000001",
        "tgn:7012149",
        "tgn:1002579",
        "tgn:7007252",
        "tgn:7029392"
    ],
    "tgn:id":2278475,
    "tgn:name":"DeWitt Creek",
    "tgn:placetype":[
        "aat:300008706"
    ]
},
  "bbox": [],
  "geometry": {"coordinates":[-86.3333,38.8667],"type":"Point"}
}