{
  "id": 7279287,
  "type": "Feature",
  "properties": {
    "tgn:hierarchy":[
        "tgn:7279287",
        "tgn:7016598",
        "tgn:1000049",
        "tgn:1000002",
        "tgn:7029392"
    ],
    "tgn:id":7279287,
    "tgn:name":"Rodeo, Pampa",
    "tgn:placetype":[
        "aat:300008805"
    ]
},
  "bbox": [],
  "geometry": {"coordinates":[-68.55,-21.283333],"type":"Point"}
}