{
  "id": 2520704,
  "type": "Feature",
  "properties": {
    "tgn:hierarchy":[
        "tgn:2520704",
        "tgn:1000001",
        "tgn:7012149",
        "tgn:2001161",
        "tgn:7007522",
        "tgn:7029392"
    ],
    "tgn:id":2520704,
    "tgn:name":"Monocnoc, Lake",
    "tgn:placetype":[
        "aat:300008680"
    ]
},
  "bbox": [],
  "geometry": {"coordinates":[-90.8667,33.3833],"type":"Point"}
}