<<<<<<< HEAD
{
  "id": 2766735,
  "type": "Feature",
  "properties": {
    "tgn:hierarchy":[
        "tgn:2766735",
        "tgn:1000001",
        "tgn:7012149",
        "tgn:2000905",
        "tgn:7007256",
        "tgn:7029392"
    ],
    "tgn:id":2766735,
    "tgn:name":"White Oak Ridge Lake",
    "tgn:placetype":[
        "aat:300008680"
    ]
},
  "bbox": [],
  "geometry": {"coordinates":[-89.7833,30.5333],"type":"Point"}
}
=======
{"geometry":{"type":"Point","coordinates":[-89.783300,30.533300]},"type":"Feature","properties":{"hierarchy":["tgn:2766735","tgn:1000001","tgn:7012149","tgn:2000905","tgn:7007256","tgn:7029392"],"placetype":["aat:300008680"],"id":2766735,"name:xx":"White Oak Ridge Lake"}}
>>>>>>> 03f74aca74312dbeaf24d7e61306dd6a786dc3d0
