{
  "id": 2766735,
  "type": "Feature",
  "properties": {
    "tgn:hierarchy":[
        "tgn:2766735",
        "tgn:1000001",
        "tgn:7012149",
        "tgn:2000905",
        "tgn:7007256",
        "tgn:7029392"
    ],
    "tgn:id":2766735,
    "tgn:name":"White Oak Ridge Lake",
    "tgn:placetype":[
        "aat:300008680"
    ]
},
  "bbox": [],
  "geometry": {"coordinates":[-89.7833,30.5333],"type":"Point"}
}