{
  "id": 7488157,
  "type": "Feature",
  "properties": {
    "tgn:hierarchy":[
        "tgn:7488157",
        "tgn:7001010",
        "tgn:1000004",
        "tgn:1000141",
        "tgn:7029392"
    ],
    "tgn:id":7488157,
    "tgn:name":"Luoshan",
    "tgn:placetype":[
        "aat:300008347"
    ]
},
  "bbox": [],
  "geometry": {"coordinates":[121.277996,23.201113],"type":"Point"}
}