{
  "id": 2621529,
  "type": "Feature",
  "properties": {
    "tgn:hierarchy":[
        "tgn:2621529",
        "tgn:1000001",
        "tgn:7012149",
        "tgn:1002399",
        "tgn:7007710",
        "tgn:7029392"
    ],
    "tgn:id":2621529,
    "tgn:name":"Roaring Run",
    "tgn:placetype":[
        "aat:300008699"
    ]
},
  "bbox": [],
  "geometry": {"coordinates":[-78.1667,39.9667],"type":"Point"}
}