{
  "id": 2109347,
  "type": "Feature",
  "properties": {
    "tgn:hierarchy":[
        "tgn:2109347",
        "tgn:1000001",
        "tgn:7012149",
        "tgn:2002111",
        "tgn:7007827",
        "tgn:7029392"
    ],
    "tgn:id":2109347,
    "tgn:name":"Uvada",
    "tgn:placetype":[
        "aat:300008347",
        "aat:300387210"
    ]
},
  "bbox": [],
  "geometry": {"coordinates":[-114.0333,37.7167],"type":"Point"}
}