{
  "id": 2488732,
  "type": "Feature",
  "properties": {
    "tgn:hierarchy":[
        "tgn:2488732",
        "tgn:7023902",
        "tgn:1000001",
        "tgn:7012149",
        "tgn:7007249",
        "tgn:7029392"
    ],
    "tgn:id":2488732,
    "tgn:name":"Maihi Bay",
    "tgn:placetype":[
        "aat:300132316"
    ]
},
  "bbox": [],
  "geometry": {"coordinates":[-155.95,19.5333],"type":"Point"}
}