<<<<<<< HEAD
{
  "id": 7051057,
  "type": "Feature",
  "properties": {
    "tgn:hierarchy":[
        "tgn:7051057",
        "tgn:7003139",
        "tgn:1000003",
        "tgn:7003080",
        "tgn:1000080",
        "tgn:7029392"
    ],
    "tgn:id":7051057,
    "tgn:name":"Pianiano",
    "tgn:placetype":[
        "aat:300008347"
    ]
},
  "bbox": [],
  "geometry": {"coordinates":[11.733333,42.5],"type":"Point"}
}
=======
{"geometry":{"type":"Point","coordinates":[11.733333,42.500000]},"type":"Feature","properties":{"hierarchy":["tgn:7051057","tgn:7003139","tgn:1000003","tgn:7003080","tgn:1000080","tgn:7029392"],"placetype":["aat:300008347"],"id":7051057,"name:xx":"Pianiano"}}
>>>>>>> 03f74aca74312dbeaf24d7e61306dd6a786dc3d0
