{
  "id": 2663458,
  "type": "Feature",
  "properties": {
    "tgn:hierarchy":[
        "tgn:2663458",
        "tgn:1000001",
        "tgn:2001266",
        "tgn:7012149",
        "tgn:7007524",
        "tgn:7029392"
    ],
    "tgn:id":2663458,
    "tgn:name":"Silver Dyke Adit Mine",
    "tgn:placetype":[
        "aat:300000390"
    ]
},
  "bbox": [],
  "geometry": {"coordinates":[-110.6833,46.9667],"type":"Point"}
}