{
  "id": 1008672,
  "type": "Feature",
  "properties": {
    "tgn:hierarchy":[
        "tgn:1008672",
        "tgn:7001697",
        "tgn:7001242",
        "tgn:1000190",
        "tgn:7029392"
    ],
    "tgn:id":1008672,
    "tgn:name":"Providence",
    "tgn:placetype":[
        "aat:300008791"
    ]
},
  "bbox": [],
  "geometry": {"coordinates":[51.0333,-9.2333],"type":"Point"}
}