<<<<<<< HEAD
{
  "id": 2339286,
  "type": "Feature",
  "properties": {
    "tgn:hierarchy":[
        "tgn:2339286",
        "tgn:1000001",
        "tgn:7012149",
        "tgn:2001457",
        "tgn:7007566",
        "tgn:7029392"
    ],
    "tgn:id":2339286,
    "tgn:name":"Fraser Mountain",
    "tgn:placetype":[
        "aat:300008798"
    ]
},
  "bbox": [],
  "geometry": {"coordinates":[-105.4167,36.5833],"type":"Point"}
}
=======
{"geometry":{"type":"Point","coordinates":[-105.416700,36.583300]},"type":"Feature","properties":{"hierarchy":["tgn:2339286","tgn:1000001","tgn:7012149","tgn:2001457","tgn:7007566","tgn:7029392"],"placetype":["aat:300008798"],"id":2339286,"name:xx":"Fraser Mountain"}}
>>>>>>> 03f74aca74312dbeaf24d7e61306dd6a786dc3d0
