{
  "id": 7081245,
  "type": "Feature",
  "properties": {
    "tgn:hierarchy":[
        "tgn:7081245",
        "tgn:7000096",
        "tgn:1000003",
        "tgn:7000084",
        "tgn:7029392"
    ],
    "tgn:id":7081245,
    "tgn:name":"Woddow",
    "tgn:placetype":[
        "aat:300008347"
    ]
},
  "bbox": [],
  "geometry": {"coordinates":[14.183333,53.383333],"type":"Point"}
}