{
  "id": 2441582,
  "type": "Feature",
  "properties": {
    "tgn:hierarchy":[
        "tgn:2441582",
        "tgn:1000001",
        "tgn:1002273",
        "tgn:7012149",
        "tgn:7007252",
        "tgn:7029392"
    ],
    "tgn:id":2441582,
    "tgn:name":"Koetter Hollow",
    "tgn:placetype":[
        "aat:300008761"
    ]
},
  "bbox": [],
  "geometry": {"coordinates":[-85.9333,38.4167],"type":"Point"}
}