{
  "id": 1054405,
  "type": "Feature",
  "properties": {
    "tgn:hierarchy":[
        "tgn:1054405",
        "tgn:1000004",
        "tgn:7012212",
        "tgn:7006655",
        "tgn:7029392"
    ],
    "tgn:id":1054405,
    "tgn:name":"Irkeshtam",
    "tgn:placetype":[
        "aat:300008347"
    ]
},
  "bbox": [],
  "geometry": {"coordinates":[73.9667,39.6667],"type":"Point"}
}