{
  "id": 2122206,
  "type": "Feature",
  "properties": {
    "tgn:hierarchy":[
        "tgn:2122206",
        "tgn:1000001",
        "tgn:2002311",
        "tgn:7012149",
        "tgn:7007922",
        "tgn:7029392"
    ],
    "tgn:id":2122206,
    "tgn:name":"Randall",
    "tgn:placetype":[
        "aat:300008347",
        "aat:300387210"
    ]
},
  "bbox": [],
  "geometry": {"coordinates":[-92.8333,45.6833],"type":"Point"}
}