{
  "id": 2500319,
  "type": "Feature",
  "properties": {
    "tgn:hierarchy":[
        "tgn:2500319",
        "tgn:1000001",
        "tgn:7012149",
        "tgn:2001898",
        "tgn:7007825",
        "tgn:7029392"
    ],
    "tgn:id":2500319,
    "tgn:name":"McDaniel Knob",
    "tgn:placetype":[
        "aat:300008798"
    ]
},
  "bbox": [],
  "geometry": {"coordinates":[-84.3833,35.4333],"type":"Point"}
}