{
  "id": 2589838,
  "type": "Feature",
  "properties": {
    "tgn:hierarchy":[
        "tgn:2589838",
        "tgn:1000001",
        "tgn:2001477",
        "tgn:7012149",
        "tgn:7007709",
        "tgn:7029392"
    ],
    "tgn:id":2589838,
    "tgn:name":"Point of Grass Creek",
    "tgn:placetype":[
        "aat:300132316"
    ]
},
  "bbox": [],
  "geometry": {"coordinates":[-76.2833,34.8667],"type":"Point"}
}