<<<<<<< HEAD
{
  "id": 2766671,
  "type": "Feature",
  "properties": {
    "tgn:hierarchy":[
        "tgn:2766671",
        "tgn:1000001",
        "tgn:7012149",
        "tgn:1003035",
        "tgn:7007251",
        "tgn:7029392"
    ],
    "tgn:id":2766671,
    "tgn:name":"White Oak Lake",
    "tgn:placetype":[
        "aat:300006191"
    ]
},
  "bbox": [],
  "geometry": {"coordinates":[-89.2167,40.6167],"type":"Point"}
}
=======
{"geometry":{"type":"Point","coordinates":[-89.216700,40.616700]},"type":"Feature","properties":{"hierarchy":["tgn:2766671","tgn:1000001","tgn:7012149","tgn:1003035","tgn:7007251","tgn:7029392"],"placetype":["aat:300006191"],"id":2766671,"name:xx":"White Oak Lake"}}
>>>>>>> 03f74aca74312dbeaf24d7e61306dd6a786dc3d0
