{
  "id": 7234044,
  "type": "Feature",
  "properties": {
    "tgn:hierarchy":[
        "tgn:7234044",
        "tgn:7011170",
        "tgn:7002715",
        "tgn:1000003",
        "tgn:1000074",
        "tgn:7029392"
    ],
    "tgn:id":7234044,
    "tgn:name":"Akm\u00e1r R\u00e9ma",
    "tgn:placetype":[
        "aat:300008699"
    ]
},
  "bbox": [],
  "geometry": {"coordinates":[25.366667,41.116667],"type":"Point"}
}