{
  "id": 7573391,
  "type": "Feature",
  "properties": {
    "tgn:hierarchy":[
        "tgn:7573391",
        "tgn:1000004",
        "tgn:7000198",
        "tgn:7016788",
        "tgn:7029392"
    ],
    "tgn:id":7573391,
    "tgn:name:en":"Ind\u0101war",
    "tgn:placetype":[
        "aat:300008347"
    ]
},
  "bbox": [],
  "geometry": {"coordinates":[73.92904,26.568229],"type":"Point"}
}