{
  "id": 7134196,
  "type": "Feature",
  "properties": {
    "tgn:hierarchy":[
        "tgn:7134196",
        "tgn:7000096",
        "tgn:1000003",
        "tgn:7000084",
        "tgn:7029392"
    ],
    "tgn:id":7134196,
    "tgn:name":"Moor Graben",
    "tgn:placetype":[
        "aat:300008699"
    ]
},
  "bbox": [],
  "geometry": {"coordinates":[13.183333,52.683333],"type":"Point"}
}