{
  "id": 2706964,
  "type": "Feature",
  "properties": {
    "tgn:hierarchy":[
        "tgn:2706964",
        "tgn:1000001",
        "tgn:7012149",
        "tgn:2000933",
        "tgn:7007515",
        "tgn:7029392"
    ],
    "tgn:id":2706964,
    "tgn:name":"Swasey Hill",
    "tgn:placetype":[
        "aat:300008798"
    ]
},
  "bbox": [],
  "geometry": {"coordinates":[-70.7667,43.1833],"type":"Point"}
}