{
  "id": 7306867,
  "type": "Feature",
  "properties": {
    "tgn:hierarchy":[
        "tgn:7306867",
        "tgn:7002759",
        "tgn:7002843",
        "tgn:1000003",
        "tgn:1000095",
        "tgn:7029392"
    ],
    "tgn:id":7306867,
    "tgn:name":"Mas de las Matas",
    "tgn:placetype":[
        "aat:300008347"
    ]
},
  "bbox": [],
  "geometry": {"coordinates":[-0.25,40.833333],"type":"Point"}
}