{
  "id": 2356977,
  "type": "Feature",
  "properties": {
    "tgn:hierarchy":[
        "tgn:2356977",
        "tgn:7002659",
        "tgn:1000001",
        "tgn:2000012",
        "tgn:7012149",
        "tgn:7029392"
    ],
    "tgn:id":2356977,
    "tgn:name":"Gosport Landing",
    "tgn:placetype":[
        "aat:300008347"
    ]
},
  "bbox": [],
  "geometry": {"coordinates":[-87.5667,31.5333],"type":"Point"}
}