{
  "id": 7500493,
  "type": "Feature",
  "properties": {
    "tgn:hierarchy":[
        "tgn:7500493",
        "tgn:7001010",
        "tgn:1000004",
        "tgn:1000141",
        "tgn:7029392"
    ],
    "tgn:id":7500493,
    "tgn:name":"Kexipanan Shan Xifeng",
    "tgn:placetype":[
        "aat:300008798"
    ]
},
  "bbox": [],
  "geometry": {"coordinates":[121.183611,23.468056],"type":"Point"}
}