{
  "id": 1089279,
  "type": "Feature",
  "properties": {
    "tgn:hierarchy":[
        "tgn:1089279",
        "tgn:7001242",
        "tgn:7016755",
        "tgn:1000159",
        "tgn:7029392"
    ],
    "tgn:id":1089279,
    "tgn:name":"Maboma",
    "tgn:placetype":[
        "aat:300008347"
    ]
},
  "bbox": [],
  "geometry": {"coordinates":[28.2167,2.5333],"type":"Point"}
}