{
  "id": 7586928,
  "type": "Feature",
  "properties": {
    "tgn:hierarchy":[
        "tgn:7586928",
        "tgn:1000004",
        "tgn:7000198",
        "tgn:7000799",
        "tgn:7029392"
    ],
    "tgn:id":7586928,
    "tgn:name:en":"Darb\u0101gh",
    "tgn:placetype":[
        "aat:300008347"
    ]
},
  "bbox": [],
  "geometry": {"coordinates":[74.661611,34.223506],"type":"Point"}
}