{
  "id": 2202530,
  "type": "Feature",
  "properties": {
    "tgn:hierarchy":[
        "tgn:2202530",
        "tgn:1002136",
        "tgn:1000001",
        "tgn:7012149",
        "tgn:7007706",
        "tgn:7029392"
    ],
    "tgn:id":2202530,
    "tgn:name":"Buck Run",
    "tgn:placetype":[
        "aat:300008347"
    ]
},
  "bbox": [],
  "geometry": {"coordinates":[-83.5667,38.9833],"type":"Point"}
}