{
  "id": 1140227,
  "type": "Feature",
  "properties": {
    "tgn:hierarchy":[
        "tgn:1140227",
        "tgn:1000004",
        "tgn:7000198",
        "tgn:7016722",
        "tgn:7029392"
    ],
    "tgn:id":1140227,
    "tgn:name:en":"T\u0101jpur",
    "tgn:placetype":[
        "aat:300008347"
    ]
},
  "bbox": [],
  "geometry": {"coordinates":[78.484026,29.163485],"type":"Point"}
}