<<<<<<< HEAD
{
  "id": 2761966,
  "type": "Feature",
  "properties": {
    "tgn:hierarchy":[
        "tgn:2761966",
        "tgn:1000001",
        "tgn:1002664",
        "tgn:7012149",
        "tgn:7007159",
        "tgn:7029392"
    ],
    "tgn:id":2761966,
    "tgn:name":"West Round Hill Brook",
    "tgn:placetype":[
        "aat:300008699"
    ]
},
  "bbox": [],
  "geometry": {"coordinates":[-72.65,41.5],"type":"Point"}
}
=======
{"geometry":{"type":"Point","coordinates":[-72.650000,41.500000]},"type":"Feature","properties":{"hierarchy":["tgn:2761966","tgn:1000001","tgn:1002664","tgn:7012149","tgn:7007159","tgn:7029392"],"placetype":["aat:300008699"],"id":2761966,"name:xx":"West Round Hill Brook"}}
>>>>>>> 03f74aca74312dbeaf24d7e61306dd6a786dc3d0
