{
  "id": 2230107,
  "type": "Feature",
  "properties": {
    "tgn:hierarchy":[
        "tgn:2230107",
        "tgn:1000001",
        "tgn:7012149",
        "tgn:2001442",
        "tgn:7007566",
        "tgn:7029392"
    ],
    "tgn:id":2230107,
    "tgn:name":"Cellars Canyon",
    "tgn:placetype":[
        "aat:300008761"
    ]
},
  "bbox": [],
  "geometry": {"coordinates":[-105.6833,33.3667],"type":"Point"}
}