{
  "id": 4010932,
  "type": "Feature",
  "properties": {
    "tgn:hierarchy":[
        "tgn:4010932",
        "tgn:7002445",
        "tgn:1000003",
        "tgn:7008168",
        "tgn:7008591",
        "tgn:7029392"
    ],
    "tgn:id":4010932,
    "tgn:name:en":"Swalcliffe",
    "tgn:placetype":[
        "aat:300008347"
    ]
},
  "bbox": [],
  "geometry": {"coordinates":[-1.45,52.033333],"type":"Point"}
}