<<<<<<< HEAD
{
  "id": 7481976,
  "type": "Feature",
  "properties": {
    "tgn:hierarchy":[
        "tgn:7481976",
        "tgn:1000004",
        "tgn:7490934",
        "tgn:1000141",
        "tgn:7029392"
    ],
    "tgn:id":7481976,
    "tgn:name":"Xizhuang Yihao Qiao",
    "tgn:placetype":[
        "aat:300007836"
    ]
},
  "bbox": [],
  "geometry": {"coordinates":[120.301679,23.183709],"type":"Point"}
}
=======
{"geometry":{"type":"Point","coordinates":[120.301679,23.183709]},"type":"Feature","properties":{"hierarchy":["tgn:7481976","tgn:1000004","tgn:7490934","tgn:1000141","tgn:7029392"],"placetype":["aat:300007836"],"id":7481976,"name:xx":"Xizhuang Yihao Qiao"}}
>>>>>>> 03f74aca74312dbeaf24d7e61306dd6a786dc3d0
