{
  "id": 2509480,
  "type": "Feature",
  "properties": {
    "tgn:hierarchy":[
        "tgn:2509480",
        "tgn:1000001",
        "tgn:7012149",
        "tgn:7029392"
    ],
    "tgn:id":2509480,
    "tgn:name":"Middle Fork Thompson Creek",
    "tgn:placetype":[
        "aat:300008706"
    ]
},
  "bbox": [],
  "geometry": {"coordinates":[-91.25,30.8833],"type":"Point"}
}