<<<<<<< HEAD
{
  "id": 7485079,
  "type": "Feature",
  "properties": {
    "tgn:hierarchy":[
        "tgn:7485079",
        "tgn:1000004",
        "tgn:7001014",
        "tgn:1000141",
        "tgn:7029392"
    ],
    "tgn:id":7485079,
    "tgn:name":"Neihu Qiao",
    "tgn:placetype":[
        "aat:300007836"
    ]
},
  "bbox": [],
  "geometry": {"coordinates":[120.687222,23.608056],"type":"Point"}
}
=======
{"geometry":{"type":"Point","coordinates":[120.687222,23.608056]},"type":"Feature","properties":{"hierarchy":["tgn:7485079","tgn:1000004","tgn:7001014","tgn:1000141","tgn:7029392"],"placetype":["aat:300007836"],"id":7485079,"name:xx":"Neihu Qiao"}}
>>>>>>> 03f74aca74312dbeaf24d7e61306dd6a786dc3d0
