{
  "id": 7213679,
  "type": "Feature",
  "properties": {
    "tgn:hierarchy":[
        "tgn:7213679",
        "tgn:1000003",
        "tgn:7003677",
        "tgn:7000084",
        "tgn:7029392"
    ],
    "tgn:id":7213679,
    "tgn:name":"Blumenthaler Haar",
    "tgn:placetype":[
        "aat:300008347"
    ]
},
  "bbox": [],
  "geometry": {"coordinates":[7.916667,51.533333],"type":"Point"}
}